{
  "type": "Feature",
  "properties": {
    "iso:country":"DE",
    "sg:address":"Inselkammerstr. 8",
    "sg:city":"Unterhaching",
    "sg:phone":"+49 89/6144740",
    "sg:postcode":"82008",
    "sg:province":"Bayern",
    "wof:name":"Matroc Electronic Systems Gmbh",
    "wof:placetype":"venue"
},
  "geometry": {"coordinates":[11.6087818146,48.055316925],"type":"Point"}
}