{
  "type": "Feature",
  "properties": {
    "iso:country":"DE",
    "sg:address":"B\u00fcltenstr. 22",
    "sg:city":"Wunstorf",
    "sg:phone":"+49 5031/3294",
    "sg:postcode":"31515",
    "sg:province":"Niedersachsen",
    "wof:name":"Kuckuck",
    "wof:placetype":"venue"
},
  "geometry": {"coordinates":[9.4580888748,52.3844146729],"type":"Point"}
}