{
  "type": "Feature",
  "properties": {
    "iso:country":"DE",
    "sg:address":"Burgstr. 25",
    "sg:city":"Falkenberg",
    "sg:phone":"+49 33458/30051",
    "sg:postcode":"16259",
    "sg:province":"Brandenburg",
    "wof:name":"Horst K\u00fchn",
    "wof:placetype":"venue"
},
  "geometry": {"coordinates":[13.9545221329,52.7989082336],"type":"Point"}
}