{
  "type": "Feature",
  "properties": {
    "iso:country":"DE",
    "sg:address":"Edeltraudstr. 51b",
    "sg:city":"M\u00fcnchen",
    "sg:phone":"+49 89/4308763",
    "sg:postcode":"81827",
    "sg:province":"Bayern",
    "wof:name":"Rk Kosmetik Gmbh Herstellung Und Vertrieb",
    "wof:placetype":"venue"
},
  "geometry": {"coordinates":[11.687865,48.11517],"type":"Point"}
}