{
  "type": "Feature",
  "properties": {
    "iso:country":"DE",
    "sg:address":"Kastanienallee 18",
    "sg:city":"Berlin",
    "sg:phone":"+49 30/3040253",
    "sg:postcode":"14052",
    "sg:province":"Berlin",
    "wof:name":"Alfred Jack Komponist",
    "wof:placetype":"venue"
},
  "geometry": {"coordinates":[13.2683725357,52.5108642578],"type":"Point"}
}