{
  "type": "Feature",
  "properties": {
    "iso:country":"DE",
    "sg:address":"Siegfriedstr. 32",
    "sg:city":"Heppenheim",
    "sg:phone":"+49 6252/2142",
    "sg:postcode":"64646",
    "sg:province":"Hessen",
    "wof:name":"Helmut Sch\u00e4fer",
    "wof:placetype":"venue"
},
  "geometry": {"coordinates":[8.67494,49.645809],"type":"Point"}
}