{
  "type": "Feature",
  "properties": {
    "iso:country":"DE",
    "sg:city":"Utting",
    "sg:postcode":"86919",
    "sg:province":"Bayern",
    "wof:name":"Bayerische Seglervereinigung E.v.",
    "wof:placetype":"venue"
},
  "geometry": {"coordinates":[11.084764,48.026707],"type":"Point"}
}