{
  "type": "Feature",
  "properties": {
    "iso:country":"DE",
    "sg:address":"Sommerfieldring 50",
    "sg:city":"Berlin",
    "sg:phone":"+49 30/8052872",
    "sg:postcode":"14109",
    "sg:province":"Berlin",
    "wof:name":"Armin Rohloff Architekt",
    "wof:placetype":"venue"
},
  "geometry": {"coordinates":[13.143121,52.415592],"type":"Point"}
}