{
  "type": "Feature",
  "properties": {
    "iso:country":"DE",
    "sg:address":"Bahnhofstr.",
    "sg:city":"Aurach",
    "sg:phone":"+49 9804/888",
    "sg:postcode":"91589",
    "sg:province":"Bayern",
    "wof:name":"Autobahntankstelle Frankenh\u00f6he S\u00fcd Ag",
    "wof:placetype":"venue"
},
  "geometry": {"coordinates":[10.3361415863,49.2354507446],"type":"Point"}
}