{
  "type": "Feature",
  "properties": {
    "iso:country":"DE",
    "sg:address":"S\u00fcdliche Auffahrtsallee 60",
    "sg:city":"M\u00fcnchen",
    "sg:phone":"+49 89/174395",
    "sg:postcode":"80639",
    "sg:province":"Bayern",
    "wof:name":"S. V. Schiller-wilfling",
    "wof:placetype":"venue"
},
  "geometry": {"coordinates":[11.515976,48.158356],"type":"Point"}
}