{
  "type": "Feature",
  "properties": {
    "iso:country":"DE",
    "sg:address":"Hamburger Str. 32",
    "sg:city":"Leezen",
    "sg:phone":"+49 4552/213",
    "sg:postcode":"23816",
    "sg:province":"Schleswig-Holstein",
    "wof:name":"Walter Christiansen & Co.",
    "wof:placetype":"venue"
},
  "geometry": {"coordinates":[10.251725,53.866322],"type":"Point"}
}