{
  "type": "Feature",
  "properties": {
    "iso:country":"DE",
    "sg:address":"Taunusstr. 1",
    "sg:city":"Wiesbaden",
    "sg:postcode":"65193",
    "sg:province":"Hessen",
    "wof:name":"R & V Kureck Immobilien Gmbh",
    "wof:placetype":"venue"
},
  "geometry": {"coordinates":[8.2442054749,50.0860900879],"type":"Point"}
}