{
  "type": "Feature",
  "properties": {
    "iso:country":"DE",
    "sg:address":"M\u00fchlenweg 33",
    "sg:city":"Wunstorf",
    "sg:phone":"+49 5031/3450",
    "sg:postcode":"31515",
    "sg:province":"Niedersachsen",
    "wof:name":"Angelica Hirschm\u00fcller Hebamme",
    "wof:placetype":"venue"
},
  "geometry": {"coordinates":[9.426023,52.420216],"type":"Point"}
}