{
  "type": "Feature",
  "properties": {
    "iso:country":"DE",
    "sg:address":"Mittlere Eckenbergstr. 34",
    "sg:city":"Adelsheim",
    "sg:phone":"+49 6291/1378",
    "sg:postcode":"74740",
    "sg:province":"Baden-W\u00fcrttemberg",
    "wof:name":"Klaus Kistner Architekt",
    "wof:placetype":"venue"
},
  "geometry": {"coordinates":[9.389968,49.407101],"type":"Point"}
}