{
  "type": "Feature",
  "properties": {
    "iso:country":"DE",
    "sg:address":"Klosterstr. 19",
    "sg:city":"Cottbus",
    "sg:postcode":"03046",
    "sg:province":"Brandenburg",
    "wof:name":"Stadtmission Cottbus",
    "wof:placetype":"venue"
},
  "geometry": {"coordinates":[14.3332328796,51.7615776062],"type":"Point"}
}