{
  "type": "Feature",
  "properties": {
    "iso:country":"DE",
    "sg:address":"Rotenburger Str. 3",
    "sg:city":"Fintel",
    "sg:phone":"+49 4265/8182",
    "sg:postcode":"27389",
    "sg:province":"Niedersachsen",
    "wof:name":"N. Langwost & D. Schr\u00f6der",
    "wof:placetype":"venue"
},
  "geometry": {"coordinates":[9.667085,53.17197],"type":"Point"}
}