{
  "type": "Feature",
  "properties": {
    "iso:country":"DE",
    "sg:address":"Maastrichter Str. 22",
    "sg:city":"Aachen",
    "sg:postcode":"52074",
    "sg:province":"Nordrhein-Westfalen",
    "wof:name":"Mobi Com Ac Gmbh",
    "wof:placetype":"venue"
},
  "geometry": {"coordinates":[6.0709757805,50.7755088806],"type":"Point"}
}