{
  "type": "Feature",
  "properties": {
    "iso:country":"DE",
    "sg:address":"Friedrich-Ebert-Str. 79-81",
    "sg:city":"Potsdam",
    "sg:phone":"+49 331/352314",
    "sg:postcode":"14469",
    "sg:province":"Brandenburg",
    "wof:name":"Stadtarchiv",
    "wof:placetype":"venue"
},
  "geometry": {"coordinates":[13.05786,52.405148],"type":"Point"}
}