{
  "type": "Feature",
  "properties": {
    "iso:country":"DE",
    "sg:address":"Haller Str. 20",
    "sg:city":"Michelfeld",
    "sg:phone":"+49 791/84873",
    "sg:postcode":"74545",
    "sg:province":"Baden-W\u00fcrttemberg",
    "wof:name":"V. Sommer",
    "wof:placetype":"venue"
},
  "geometry": {"coordinates":[9.6787843704,49.0968666077],"type":"Point"}
}