{
  "type": "Feature",
  "properties": {
    "iso:country":"DE",
    "sg:address":"Schleusinger Str.",
    "sg:city":"Brattendorf",
    "sg:phone":"+49 36878/60413",
    "sg:postcode":"98673",
    "sg:province":"Th\u00fcringen",
    "wof:name":"Th\u00f6rmer & Th\u00f6rmer Gbr",
    "wof:placetype":"venue"
},
  "geometry": {"coordinates":[10.846775,50.472965],"type":"Point"}
}