{
  "type": "Feature",
  "properties": {
    "iso:country":"DE",
    "sg:address":"Gneisenaustr. 97",
    "sg:city":"Berlin",
    "sg:postcode":"10961",
    "sg:province":"Berlin",
    "wof:name":"Ariana Dentallabor Gmbh",
    "wof:placetype":"venue"
},
  "geometry": {"coordinates":[13.3925628662,52.4922637939],"type":"Point"}
}