{
  "type": "Feature",
  "properties": {
    "iso:country":"DE",
    "sg:address":"Eisenacher Str. 41",
    "sg:city":"Schnellmannshausen",
    "sg:phone":"+49 36926/98324",
    "sg:postcode":"99831",
    "sg:province":"Th\u00fcringen",
    "wof:name":"Willi Schwanz",
    "wof:placetype":"venue"
},
  "geometry": {"coordinates":[10.2192087173,51.1017036438],"type":"Point"}
}