{
  "type": "Feature",
  "properties": {
    "iso:country":"DE",
    "sg:address":"Sandfuhrweg 9",
    "sg:city":"Leer",
    "sg:phone":"+49 491/66946",
    "sg:postcode":"26789",
    "sg:province":"Niedersachsen",
    "wof:name":"Immobilien Harry Hecht",
    "wof:placetype":"venue"
},
  "geometry": {"coordinates":[7.436439991,53.2615737915],"type":"Point"}
}