{
  "type": "Feature",
  "properties": {
    "iso:country":"DE",
    "sg:address":"Altenha\u00dflauer Str. 1",
    "sg:city":"Gelnhausen",
    "sg:phone":"+49 6051/2712",
    "sg:postcode":"63571",
    "sg:province":"Hessen",
    "wof:name":"Herbert Denner",
    "wof:placetype":"venue"
},
  "geometry": {"coordinates":[9.191411972,50.1977615356],"type":"Point"}
}