{
  "type": "Feature",
  "properties": {
    "iso:country":"DE",
    "sg:address":"Lerchenstr. 1",
    "sg:city":"Waiblingen",
    "sg:phone":"+49 7151/21794",
    "sg:postcode":"71334",
    "sg:province":"Baden-W\u00fcrttemberg",
    "wof:name":"Gerhard Ammann Architekt",
    "wof:placetype":"venue"
},
  "geometry": {"coordinates":[9.327537,48.834499],"type":"Point"}
}