{
  "type": "Feature",
  "properties": {
    "iso:country":"DE",
    "sg:address":"Alter Weg 12 a",
    "sg:city":"Hamburg",
    "sg:phone":"+49 40/8503212",
    "sg:postcode":"22525",
    "sg:province":"Hamburg",
    "wof:name":"Henning Wiehr",
    "wof:placetype":"venue"
},
  "geometry": {"coordinates":[9.9370279312,53.579372406],"type":"Point"}
}