{
  "type": "Feature",
  "properties": {
    "iso:country":"DE",
    "sg:address":"Wohldstr. 3",
    "sg:city":"Badbergen",
    "sg:phone":"+49 5433/1242",
    "sg:postcode":"49635",
    "sg:province":"Niedersachsen",
    "wof:name":"Abendroth Datensysteme Gmbh",
    "wof:placetype":"venue"
},
  "geometry": {"coordinates":[7.9959979057,52.6643867493],"type":"Point"}
}