{
  "type": "Feature",
  "properties": {
    "iso:country":"DE",
    "sg:address":"Am Wiesengrund 1",
    "sg:city":"Kirchberg",
    "sg:phone":"+49 37602/66462",
    "sg:postcode":"08107",
    "sg:province":"Sachsen",
    "wof:name":"Kinderheim Maxim Gorki Cunnersdorf",
    "wof:placetype":"venue"
},
  "geometry": {"coordinates":[12.5165843964,50.6465950012],"type":"Point"}
}