{
  "type": "Feature",
  "properties": {
    "iso:country":"DE",
    "sg:address":"Zum Grund 22",
    "sg:city":"Rotenburg",
    "sg:phone":"+49 6623/2885",
    "sg:postcode":"36199",
    "sg:province":"Hessen",
    "wof:name":"Ernst Brand",
    "wof:placetype":"venue"
},
  "geometry": {"coordinates":[9.682729,50.987755],"type":"Point"}
}