{
  "type": "Feature",
  "properties": {
    "iso:country":"DE",
    "sg:address":"Talstr. 1-1",
    "sg:city":"Emmendingen",
    "sg:phone":"+49 7641/8405",
    "sg:postcode":"79312",
    "sg:province":"Baden-W\u00fcrttemberg",
    "wof:name":"Christel Jockmann",
    "wof:placetype":"venue"
},
  "geometry": {"coordinates":[7.8525781631,48.1215896606],"type":"Point"}
}