{
  "type": "Feature",
  "properties": {
    "iso:country":"DE",
    "sg:address":"Eichenstr. 13",
    "sg:city":"Lengenbostel",
    "sg:phone":"+49 4282/603",
    "sg:postcode":"27419",
    "sg:province":"Niedersachsen",
    "wof:name":"Egon C\u00f6llen",
    "wof:placetype":"venue"
},
  "geometry": {"coordinates":[9.521943,53.309292],"type":"Point"}
}