{
  "type": "Feature",
  "properties": {
    "iso:country":"DE",
    "sg:address":"Laurentiusstr. 18",
    "sg:city":"Bergisch Gladbach",
    "sg:phone":"+49 2202/32157",
    "sg:postcode":"51465",
    "sg:province":"Nordrhein-Westfalen",
    "wof:name":"Bestattungshaus Josef Schmitter Gmbh",
    "wof:placetype":"venue"
},
  "geometry": {"coordinates":[7.131495,50.992603],"type":"Point"}
}