{
  "type": "Feature",
  "properties": {
    "iso:country":"DE",
    "sg:address":"Schmaukstr. 3",
    "sg:city":"Stuttgart",
    "sg:phone":"+49 711/333775",
    "sg:postcode":"70327",
    "sg:province":"Baden-W\u00fcrttemberg",
    "wof:name":"Spiropoulos Transport- Gesellschaft Mbh",
    "wof:placetype":"venue"
},
  "geometry": {"coordinates":[9.2575559616,48.7874603271],"type":"Point"}
}