{
  "type": "Feature",
  "properties": {
    "iso:country":"DE",
    "sg:address":"An der Zechenbahn 6",
    "sg:city":"Waltrop",
    "sg:phone":"+49 2309/95810",
    "sg:postcode":"45731",
    "sg:province":"Nordrhein-Westfalen",
    "wof:name":"Abakus Ges. F\u00fcr Werbemittel Und Verkaufsf\u00f6rderung Mbh",
    "wof:placetype":"venue"
},
  "geometry": {"coordinates":[7.430659771,51.6221199036],"type":"Point"}
}