{
  "type": "Feature",
  "properties": {
    "iso:country":"DE",
    "sg:address":"Hauptstr. 13",
    "sg:city":"M\u00f6rschied",
    "sg:phone":"+49 6785/819",
    "sg:postcode":"55758",
    "sg:province":"Rheinland-Pfalz",
    "wof:name":"Arno Hachenthal",
    "wof:placetype":"venue"
},
  "geometry": {"coordinates":[7.3017501831,49.7854423523],"type":"Point"}
}