{
  "type": "Feature",
  "properties": {
    "iso:country":"DE",
    "sg:address":"Gottlieb-Daimler-Str. 15",
    "sg:city":"Frechen",
    "sg:phone":"+49 2234/956760",
    "sg:postcode":"50226",
    "sg:province":"Nordrhein-Westfalen",
    "wof:name":"Ad Arztbedarf Gmbh",
    "wof:placetype":"venue"
},
  "geometry": {"coordinates":[6.819907,50.922512],"type":"Point"}
}