{
  "type": "Feature",
  "properties": {
    "iso:country":"DE",
    "sg:address":"Marktstr. 8",
    "sg:city":"Lathen",
    "sg:phone":"+49 5933/903897",
    "sg:postcode":"49762",
    "sg:province":"Niedersachsen",
    "wof:name":"Blue Shamrock Bistro",
    "wof:placetype":"venue"
},
  "geometry": {"coordinates":[7.3165140152,52.8613090515],"type":"Point"}
}