{
  "type": "Feature",
  "properties": {
    "iso:country":"DE",
    "sg:address":"Langenhorner Chaussee 157",
    "sg:city":"Hamburg",
    "sg:phone":"+49 40/5310020",
    "sg:postcode":"22415",
    "sg:province":"Hamburg",
    "wof:name":"Hotel Sch\u00fcmann Am Airport",
    "wof:placetype":"venue"
},
  "geometry": {"coordinates":[10.012301445,53.6462287903],"type":"Point"}
}