{
  "type": "Feature",
  "properties": {
    "iso:country":"DE",
    "sg:address":"Grabenstr 56",
    "sg:city":"Berlin",
    "sg:phone":"+49 30/6761059",
    "sg:postcode":"12526",
    "sg:province":"Berlin",
    "wof:name":"Netzwerk-service Michael Neubert",
    "wof:placetype":"venue"
},
  "geometry": {"coordinates":[13.579832,52.405842],"type":"Point"}
}