{
  "type": "Feature",
  "properties": {
    "iso:country":"DE",
    "sg:address":"Haingrabenstr. 25",
    "sg:city":"Maintal",
    "sg:postcode":"63477",
    "sg:province":"Hessen",
    "wof:name":"Kasani Fashion Design Gmbh",
    "wof:placetype":"venue"
},
  "geometry": {"coordinates":[8.7984237671,50.1514587402],"type":"Point"}
}