{
  "type": "Feature",
  "properties": {
    "iso:country":"DE",
    "sg:address":"Barbelsenstr. 62",
    "sg:city":"M\u00f6ssingen",
    "sg:phone":"+49 4974/737646",
    "sg:postcode":"72116",
    "sg:province":"Baden-W\u00fcrttemberg",
    "wof:name":"Paul K\u00dcbler",
    "wof:placetype":"venue"
},
  "geometry": {"coordinates":[9.0422487259,48.3948364258],"type":"Point"}
}