{
  "type": "Feature",
  "properties": {
    "iso:country":"DE",
    "sg:address":"Kurf\u00fcrstenstr. 13",
    "sg:city":"Berlin",
    "sg:phone":"+49 30/34702720",
    "sg:postcode":"10785",
    "sg:province":"Berlin",
    "wof:name":"Tenea Verlag F\u00fcr Medien",
    "wof:placetype":"venue"
},
  "geometry": {"coordinates":[13.366963,52.499287],"type":"Point"}
}