{
  "type": "Feature",
  "properties": {
    "iso:country":"DE",
    "sg:address":"Am Zwirngraben 8",
    "sg:city":"Berlin",
    "sg:phone":"+49 30/9953921",
    "sg:postcode":"10178",
    "sg:province":"Berlin",
    "wof:name":"Neue B\u00f6gen Am Hackeschen Markt Gastst\u00e4tten- Und Betriebs Gmbh",
    "wof:placetype":"venue"
},
  "geometry": {"coordinates":[13.4027681351,52.522769928],"type":"Point"}
}