{
  "type": "Feature",
  "properties": {
    "iso:country":"DE",
    "sg:address":"Rathausstr. 5",
    "sg:city":"Bad K\u00f6nigshofen",
    "sg:phone":"+49 9761/6780",
    "sg:postcode":"97631",
    "sg:province":"Bayern",
    "wof:name":"Kosmetikstudio Doris",
    "wof:placetype":"venue"
},
  "geometry": {"coordinates":[10.468149,50.298615],"type":"Point"}
}