{
  "type": "Feature",
  "properties": {
    "iso:country":"DE",
    "sg:address":"Rathausring 3",
    "sg:city":"Edemissen",
    "sg:phone":"+49 5373/7722",
    "sg:postcode":"31234",
    "sg:province":"Niedersachsen",
    "wof:name":"H. Pitt",
    "wof:placetype":"venue"
},
  "geometry": {"coordinates":[10.355361,52.386059],"type":"Point"}
}