{
  "type": "Feature",
  "properties": {
    "iso:country":"DE",
    "sg:address":"Wilhelmsh\u00f6her Allee 311",
    "sg:city":"Kassel",
    "sg:phone":"+49 561/314414",
    "sg:postcode":"34131",
    "sg:province":"Hessen",
    "wof:name":"Schlo\u00df-apotheke Stefan N\u00fcrge E. K.",
    "wof:placetype":"venue"
},
  "geometry": {"coordinates":[9.435426,51.313824],"type":"Point"}
}