{
  "type": "Feature",
  "properties": {
    "iso:country":"DE",
    "sg:address":"Clarholzer Str. 50",
    "sg:city":"Herzebrock-Clarholz",
    "sg:postcode":"33442",
    "sg:province":"Nordrhein-Westfalen",
    "wof:name":"Rs Immobilien Consuling E. Kfm.",
    "wof:placetype":"venue"
},
  "geometry": {"coordinates":[8.2360200882,51.881439209],"type":"Point"}
}