{
  "type": "Feature",
  "properties": {
    "iso:country":"DE",
    "sg:address":"Bruchbergstr. 8",
    "sg:city":"Weilm\u00fcnster",
    "sg:phone":"+49 6472/911955",
    "sg:postcode":"35789",
    "sg:province":"Hessen",
    "wof:name":"Computer, Telefone, Handy, Webdesign",
    "wof:placetype":"venue"
},
  "geometry": {"coordinates":[8.322992,50.433338],"type":"Point"}
}