{
  "type": "Feature",
  "properties": {
    "iso:country":"DE",
    "sg:address":"Jacques-Offenbach-Str. 3",
    "sg:city":"W\u00f6rth",
    "sg:phone":"+49 7271/971022",
    "sg:postcode":"76744",
    "sg:province":"Rheinland-Pfalz",
    "wof:name":"Killer Rad Gmbh",
    "wof:placetype":"venue"
},
  "geometry": {"coordinates":[8.069955,49.064083],"type":"Point"}
}