{
  "type": "Feature",
  "properties": {
    "iso:country":"DE",
    "sg:address":"Marktplatz 23",
    "sg:city":"Aalen",
    "sg:phone":"+49 7361/961260",
    "sg:postcode":"73430",
    "sg:province":"Baden-W\u00fcrttemberg",
    "wof:name":"Kaisers Tengelmann Ag",
    "wof:placetype":"venue"
},
  "geometry": {"coordinates":[10.093421,48.836567],"type":"Point"}
}