{
  "type": "Feature",
  "properties": {
    "iso:country":"DE",
    "sg:address":"Hauptstr. 11",
    "sg:city":"Wehretal",
    "sg:phone":"+49 5651/40534",
    "sg:postcode":"37287",
    "sg:province":"Hessen",
    "wof:name":"Christian Fuhrmann",
    "wof:placetype":"venue"
},
  "geometry": {"coordinates":[9.943896,51.166382],"type":"Point"}
}