{
  "type": "Feature",
  "properties": {
    "iso:country":"DE",
    "sg:address":"Gespinstmarkt 8",
    "sg:city":"Ravensburg",
    "sg:phone":"+49 751/31652",
    "sg:postcode":"88212",
    "sg:province":"Baden-W\u00fcrttemberg",
    "wof:name":"Sema",
    "wof:placetype":"venue"
},
  "geometry": {"coordinates":[9.6153249741,47.7816848755],"type":"Point"}
}