{
  "type": "Feature",
  "properties": {
    "iso:country":"DE",
    "sg:address":"Ringstr. 4",
    "sg:city":"Wiesbaden",
    "sg:phone":"+49 611/711130",
    "sg:postcode":"65205",
    "sg:province":"Hessen",
    "wof:name":"H. Auth Bau- Und Kunstschlosserei",
    "wof:placetype":"venue"
},
  "geometry": {"coordinates":[8.3026981354,50.0542564392],"type":"Point"}
}