{
  "type": "Feature",
  "properties": {
    "iso:country":"DE",
    "sg:address":"Bonner Str. 11 a",
    "sg:city":"Hennef",
    "sg:postcode":"53773",
    "sg:province":"Nordrhein-Westfalen",
    "wof:name":"Ilum Licht Gmbh",
    "wof:placetype":"venue"
},
  "geometry": {"coordinates":[7.2949748039,50.7698707581],"type":"Point"}
}