{
  "type": "Feature",
  "properties": {
    "iso:country":"DE",
    "sg:address":"Graf-Dietrich-Str. 12",
    "sg:city":"Neuerburg",
    "sg:phone":"+49 6564/2220",
    "sg:postcode":"54673",
    "sg:province":"Rheinland-Pfalz",
    "wof:name":"Eduard G\u00fcth",
    "wof:placetype":"venue"
},
  "geometry": {"coordinates":[6.294796,50.011375],"type":"Point"}
}