{
  "type": "Feature",
  "properties": {
    "iso:country":"DE",
    "sg:address":"Oberheckerweg 45",
    "sg:city":"Lahnstein",
    "sg:phone":"+49 2621/18244",
    "sg:postcode":"56112",
    "sg:province":"Rheinland-Pfalz",
    "wof:name":"Stephan Hergenhahn Bedachungs Gmbh",
    "wof:placetype":"venue"
},
  "geometry": {"coordinates":[7.6208429337,50.293800354],"type":"Point"}
}