{
  "type": "Feature",
  "properties": {
    "iso:country":"DE",
    "sg:address":"Wegelerstr. 12",
    "sg:city":"Bonn",
    "sg:phone":"+49 228/732923",
    "sg:postcode":"53115",
    "sg:province":"Nordrhein-Westfalen",
    "wof:name":"Universit\u00e4t Bonn Institut F\u00fcr Physikalische",
    "wof:placetype":"venue"
},
  "geometry": {"coordinates":[7.0883841515,50.7285766602],"type":"Point"}
}