{
  "type": "Feature",
  "properties": {
    "iso:country":"DE",
    "sg:address":"Gerhart-Hauptmann-Str. 30",
    "sg:city":"Flensburg",
    "sg:phone":"+49 461/33669",
    "sg:postcode":"24943",
    "sg:province":"Schleswig-Holstein",
    "wof:name":"H. Holm Elektroinstallation",
    "wof:placetype":"venue"
},
  "geometry": {"coordinates":[9.455546,54.797161],"type":"Point"}
}