{
  "type": "Feature",
  "properties": {
    "iso:country":"DE",
    "sg:address":"Staugraben 11",
    "sg:city":"Oldenburg",
    "sg:phone":"+49 441/22280",
    "sg:postcode":"26122",
    "sg:province":"Niedersachsen",
    "wof:name":"\u00d6ffentliche Lebensver- Sicherungsanstalt",
    "wof:placetype":"venue"
},
  "geometry": {"coordinates":[8.2158060074,53.1422576904],"type":"Point"}
}