{
  "type": "Feature",
  "properties": {
    "iso:country":"DE",
    "sg:address":"Walsroder Str. 202",
    "sg:city":"Langenhagen",
    "sg:phone":"+49 511/734692",
    "sg:postcode":"30853",
    "sg:province":"Niedersachsen",
    "wof:name":"Gebr. Haase",
    "wof:placetype":"venue"
},
  "geometry": {"coordinates":[9.744219,52.455173],"type":"Point"}
}