{
  "type": "Feature",
  "properties": {
    "iso:country":"DE",
    "sg:address":"Schietinger Str. 55/1",
    "sg:city":"Nagold",
    "sg:phone":"+49 7459/665",
    "sg:postcode":"72202",
    "sg:province":"Baden-W\u00fcrttemberg",
    "wof:name":"August Rhein Inh. Valentin Rhein",
    "wof:placetype":"venue"
},
  "geometry": {"coordinates":[8.7033967972,48.5133781433],"type":"Point"}
}