{
  "type": "Feature",
  "properties": {
    "iso:country":"DE",
    "sg:address":"Noackstr. 1d",
    "sg:city":"Planegg",
    "sg:phone":"+49 89/8598748",
    "sg:postcode":"82152",
    "sg:province":"Bayern",
    "wof:name":"Erich Und Marlene Lindst\u00e4dt Immobilienmakler",
    "wof:placetype":"venue"
},
  "geometry": {"coordinates":[11.4190282822,48.1054954529],"type":"Point"}
}