{
  "type": "Feature",
  "properties": {
    "iso:country":"DE",
    "sg:address":"Herzogenstr. 9",
    "sg:city":"Goch",
    "sg:phone":"+49 2823/6937",
    "sg:postcode":"47574",
    "sg:province":"Nordrhein-Westfalen",
    "wof:name":"Echelmeyer",
    "wof:placetype":"venue"
},
  "geometry": {"coordinates":[6.159037,51.675568],"type":"Point"}
}