{
  "type": "Feature",
  "properties": {
    "iso:country":"DE",
    "sg:address":"Marienstr. 6-8",
    "sg:city":"Herrenberg",
    "sg:phone":"+49 7032/22211",
    "sg:postcode":"71083",
    "sg:province":"Baden-W\u00fcrttemberg",
    "wof:name":"Lehmann Und Partner Architekten",
    "wof:placetype":"venue"
},
  "geometry": {"coordinates":[8.872016,48.593994],"type":"Point"}
}