{
  "type": "Feature",
  "properties": {
    "iso:country":"DE",
    "sg:address":"Gleisstr. 11",
    "sg:city":"Pl\u00fcderhausen",
    "sg:phone":"+49 7181/81530",
    "sg:postcode":"73655",
    "sg:province":"Baden-W\u00fcrttemberg",
    "wof:name":"H. Weller",
    "wof:placetype":"venue"
},
  "geometry": {"coordinates":[9.5980901718,48.7941703796],"type":"Point"}
}