{
  "type": "Feature",
  "properties": {
    "iso:country":"DE",
    "sg:address":"Bachstelzenweg 9",
    "sg:city":"Neu Wulmstorf",
    "sg:phone":"+49 40/70012007",
    "sg:postcode":"21629",
    "sg:province":"Niedersachsen",
    "wof:name":"Rolf Rethmeyer Anlageberater",
    "wof:placetype":"venue"
},
  "geometry": {"coordinates":[9.7797288895,53.4692382812],"type":"Point"}
}