{
  "type": "Feature",
  "properties": {
    "iso:country":"DE",
    "sg:address":"Schallfelder Str. 6",
    "sg:city":"Gerolzhofen",
    "sg:phone":"+49 9382/8383",
    "sg:postcode":"97447",
    "sg:province":"Bayern",
    "wof:name":"Ludwig Zehnter",
    "wof:placetype":"venue"
},
  "geometry": {"coordinates":[10.351185,49.89949],"type":"Point"}
}