{
  "type": "Feature",
  "properties": {
    "iso:country":"DE",
    "sg:address":"Jagstweg 21",
    "sg:city":"Essen",
    "sg:phone":"+49 2054/2832",
    "sg:postcode":"45219",
    "sg:province":"Nordrhein-Westfalen",
    "wof:name":"G. H\u00f6busch Wettannahme",
    "wof:placetype":"venue"
},
  "geometry": {"coordinates":[6.949134,51.375618],"type":"Point"}
}