{
  "type": "Feature",
  "properties": {
    "iso:country":"DE",
    "sg:address":"Ganzenstr. 10",
    "sg:city":"Stuttgart",
    "sg:phone":"+49 711/71863330",
    "sg:postcode":"70567",
    "sg:province":"Baden-W\u00fcrttemberg",
    "wof:name":"Rolf Lechler & Joachim Burger Archtikten",
    "wof:placetype":"venue"
},
  "geometry": {"coordinates":[9.149543,48.725605],"type":"Point"}
}