{
  "type": "Feature",
  "properties": {
    "iso:country":"DE",
    "sg:address":"Oldesloer Str. 9-13",
    "sg:city":"Bad Segeberg",
    "sg:phone":"+49 4551/2608",
    "sg:postcode":"23795",
    "sg:province":"Schleswig-Holstein",
    "wof:name":"Fritz M\u00fcller Gmbh",
    "wof:placetype":"venue"
},
  "geometry": {"coordinates":[10.310426712,53.9355888367],"type":"Point"}
}