{
  "type": "Feature",
  "properties": {
    "iso:country":"DE",
    "sg:address":"Gro\u00dfer Spiegelberg 43 I",
    "sg:city":"Neustrelitz",
    "sg:phone":"+49 3981/40030",
    "sg:postcode":"17235",
    "sg:province":"Mecklenburg-Vorpommern",
    "wof:name":"Obeta Elektro Nord Gmbh",
    "wof:placetype":"venue"
},
  "geometry": {"coordinates":[13.0611600876,53.3637809753],"type":"Point"}
}