{
  "type": "Feature",
  "properties": {
    "iso:country":"DE",
    "sg:address":"Wildberghof",
    "sg:city":"Markt Nordheim",
    "sg:phone":"+49 9842/7909",
    "sg:postcode":"91478",
    "sg:province":"Bayern",
    "wof:name":"L. Endre\u00df",
    "wof:placetype":"venue"
},
  "geometry": {"coordinates":[10.318444252,49.5505447388],"type":"Point"}
}