{
  "type": "Feature",
  "properties": {
    "iso:country":"DE",
    "sg:address":"Borsigstr. 3",
    "sg:city":"Braunschweig",
    "sg:phone":"+49 531/695488",
    "sg:postcode":"38126",
    "sg:province":"Niedersachsen",
    "wof:name":"Restaurant Panoramic",
    "wof:placetype":"venue"
},
  "geometry": {"coordinates":[10.5464963913,52.2460670471],"type":"Point"}
}