{
  "type": "Feature",
  "properties": {
    "iso:country":"DE",
    "sg:address":"Neudorfer Str. 1",
    "sg:city":"Arnstein",
    "sg:phone":"+49 9728/381",
    "sg:postcode":"97450",
    "sg:province":"Bayern",
    "wof:name":"Werner Hofmann",
    "wof:placetype":"venue"
},
  "geometry": {"coordinates":[9.971134,50.049049],"type":"Point"}
}