{
  "type": "Feature",
  "properties": {
    "iso:country":"DE",
    "sg:address":"Fliederstr. 16",
    "sg:city":"Neuendettelsau",
    "sg:phone":"+49 9874/68100",
    "sg:postcode":"91564",
    "sg:province":"Bayern",
    "wof:name":"Vieweg Gmbh",
    "wof:placetype":"venue"
},
  "geometry": {"coordinates":[10.7854738235,49.2802772522],"type":"Point"}
}