{
  "type": "Feature",
  "properties": {
    "iso:country":"DE",
    "sg:address":"Badergasse 4",
    "sg:city":"Aschaffenburg",
    "sg:phone":"+49 6021/22454",
    "sg:postcode":"63739",
    "sg:province":"Bayern",
    "wof:name":"Ludwig Jordan",
    "wof:placetype":"venue"
},
  "geometry": {"coordinates":[9.147184,49.975182],"type":"Point"}
}