{
  "type": "Feature",
  "properties": {
    "iso:country":"DE",
    "sg:address":"Lindenstr. 45-49",
    "sg:city":"Bremen",
    "sg:phone":"+49 421/669844",
    "sg:postcode":"28755",
    "sg:province":"Bremen",
    "wof:name":"Kaisers Markt",
    "wof:placetype":"venue"
},
  "geometry": {"coordinates":[8.6060447693,53.1765899658],"type":"Point"}
}