{
  "type": "Feature",
  "properties": {
    "iso:country":"DE",
    "sg:address":"Cedernstr. 1",
    "sg:city":"Erlangen",
    "sg:phone":"+49 9131/862219",
    "sg:postcode":"91054",
    "sg:province":"Bayern",
    "wof:name":"Stadtarchiv Bibliothek",
    "wof:placetype":"venue"
},
  "geometry": {"coordinates":[11.004117,49.601662],"type":"Point"}
}