{
  "type": "Feature",
  "properties": {
    "iso:country":"DE",
    "sg:address":"Merianplatz 4",
    "sg:city":"Dresden",
    "sg:phone":"+49 351/4117080",
    "sg:postcode":"01169",
    "sg:province":"Sachsen",
    "wof:name":"Apotheke Im Sachsen-forum",
    "wof:placetype":"venue"
},
  "geometry": {"coordinates":[13.668424,51.044537],"type":"Point"}
}