{
  "type": "Feature",
  "properties": {
    "iso:country":"DE",
    "sg:address":"Bleckmannshof 6a",
    "sg:city":"Dinslaken",
    "sg:phone":"+49 2064/73673",
    "sg:postcode":"46535",
    "sg:province":"Nordrhein-Westfalen",
    "wof:name":"H & F Stallmann Gmbh & Co. Kg",
    "wof:placetype":"venue"
},
  "geometry": {"coordinates":[6.706852,51.564171],"type":"Point"}
}