{
  "type": "Feature",
  "properties": {
    "iso:country":"DE",
    "sg:address":"Heiligenbergstra\u00dfe 47",
    "sg:city":"Dillingen/Saar",
    "sg:phone":"+49 6831/761167",
    "sg:postcode":"66763",
    "sg:province":"Saarland",
    "wof:name":"Ferienhaus-cd",
    "wof:placetype":"venue"
},
  "geometry": {"coordinates":[6.7270431519,49.3582687378],"type":"Point"}
}