{
  "type": "Feature",
  "properties": {
    "iso:country":"DE",
    "sg:address":"Attendorner Str. 18",
    "sg:city":"K\u00f6ln",
    "sg:phone":"+49 221/895295",
    "sg:postcode":"51109",
    "sg:province":"Nordrhein-Westfalen",
    "wof:name":"Herbert Kreutzer Bildhauer",
    "wof:placetype":"venue"
},
  "geometry": {"coordinates":[7.040525,50.939301],"type":"Point"}
}