{
  "type": "Feature",
  "properties": {
    "iso:country":"DE",
    "sg:address":"Christoph-Scheffler-Str. 15",
    "sg:city":"Mainburg",
    "sg:phone":"+49 8751/3374",
    "sg:postcode":"84048",
    "sg:province":"Bayern",
    "wof:name":"Sonja Weber",
    "wof:placetype":"venue"
},
  "geometry": {"coordinates":[11.780776,48.642006],"type":"Point"}
}