{
  "type": "Feature",
  "properties": {
    "iso:country":"DE",
    "sg:address":"M\u00fchlenweg 15",
    "sg:city":"Lenzen",
    "sg:postcode":"19309",
    "sg:province":"Brandenburg",
    "wof:name":"H. A. U. S. Innenausbau Und Sanierung Gmbh",
    "wof:placetype":"venue"
},
  "geometry": {"coordinates":[11.485648,53.097439],"type":"Point"}
}