{
  "type": "Feature",
  "properties": {
    "iso:country":"DE",
    "sg:address":"Dieselstr. 55",
    "sg:city":"N\u00fcrnberg",
    "sg:phone":"+49 911/66320",
    "sg:postcode":"90441",
    "sg:province":"Bayern",
    "wof:name":"Thyssen Krupp Materials Ag",
    "wof:placetype":"venue"
},
  "geometry": {"coordinates":[11.034781,49.428783],"type":"Point"}
}