{
  "type": "Feature",
  "properties": {
    "iso:country":"DE",
    "sg:address":"Nehberghalde 14",
    "sg:city":"Burladingen",
    "sg:phone":"+49 7475/433",
    "sg:postcode":"72393",
    "sg:province":"Baden-W\u00fcrttemberg",
    "wof:name":"Ev. Pfarramt",
    "wof:placetype":"venue"
},
  "geometry": {"coordinates":[9.1089391708,48.2947311401],"type":"Point"}
}