{
  "type": "Feature",
  "properties": {
    "iso:country":"DE",
    "sg:address":"Hafenstr. 55",
    "sg:city":"Bremerhaven",
    "sg:phone":"+49 471/43427",
    "sg:postcode":"27576",
    "sg:province":"Bremen",
    "wof:name":"Tengelmann",
    "wof:placetype":"venue"
},
  "geometry": {"coordinates":[8.5825862885,53.5540122986],"type":"Point"}
}