{
  "type": "Feature",
  "properties": {
    "iso:country":"DE",
    "sg:address":"Spiegelgasse 1",
    "sg:city":"Crimmitschau",
    "sg:phone":"+49 3762/2726",
    "sg:postcode":"08451",
    "sg:province":"Sachsen",
    "wof:name":"A. Mohr",
    "wof:placetype":"venue"
},
  "geometry": {"coordinates":[12.3901796341,50.8099403381],"type":"Point"}
}