{
  "type": "Feature",
  "properties": {
    "iso:country":"DE",
    "sg:address":"Lange Str. 49",
    "sg:city":"Lohfelden",
    "sg:phone":"+49 561/514546",
    "sg:postcode":"34253",
    "sg:province":"Hessen",
    "wof:name":"Neue Apotheke Zum Rathaus Inh. Bernd Gr\u00fcnewald",
    "wof:placetype":"venue"
},
  "geometry": {"coordinates":[9.552792,51.273262],"type":"Point"}
}