{
  "type": "Feature",
  "properties": {
    "iso:country":"DE",
    "sg:address":"Hohe Str. 7",
    "sg:city":"Ilmenau",
    "sg:phone":"+49 3677/84800",
    "sg:postcode":"98693",
    "sg:province":"Th\u00fcringen",
    "wof:name":"Idi Informationsdienst Ilmenau Gmbh",
    "wof:placetype":"venue"
},
  "geometry": {"coordinates":[10.9298620224,50.6993255615],"type":"Point"}
}