{
  "type": "Feature",
  "properties": {
    "iso:country":"DE",
    "sg:address":"Gartenstr. 41B",
    "sg:city":"Siegburg",
    "sg:phone":"+49 2241/959797",
    "sg:postcode":"53721",
    "sg:province":"Nordrhein-Westfalen",
    "wof:name":"Josef B\u00f6ckem",
    "wof:placetype":"venue"
},
  "geometry": {"coordinates":[7.198767,50.803055],"type":"Point"}
}