{
  "type": "Feature",
  "properties": {
    "iso:country":"DE",
    "sg:address":"Mottenkaul 22",
    "sg:city":"K\u00f6ln",
    "sg:phone":"+49 221/9782800",
    "sg:postcode":"50769",
    "sg:province":"Nordrhein-Westfalen",
    "wof:name":"Johannes Esser",
    "wof:placetype":"venue"
},
  "geometry": {"coordinates":[6.842368,51.042309],"type":"Point"}
}