{
  "type": "Feature",
  "properties": {
    "iso:country":"DE",
    "sg:address":"K\u00e4ppelestr 4",
    "sg:city":"Karlsruhe",
    "sg:phone":"+49 721/62630",
    "sg:postcode":"76131",
    "sg:province":"Baden-W\u00fcrttemberg",
    "wof:name":"Adolf Pfeiffer Gmbh",
    "wof:placetype":"venue"
},
  "geometry": {"coordinates":[8.440209,49.009129],"type":"Point"}
}