{
  "type": "Feature",
  "properties": {
    "iso:country":"DE",
    "sg:address":"Am Pastorsgarten 1",
    "sg:city":"Hellenthal",
    "sg:phone":"+49 2482/1595",
    "sg:postcode":"53940",
    "sg:province":"Nordrhein-Westfalen",
    "wof:name":"G\u00e4stehaus Hans Rom",
    "wof:placetype":"venue"
},
  "geometry": {"coordinates":[6.4336290359,50.4932785034],"type":"Point"}
}