{
  "type": "Feature",
  "properties": {
    "iso:country":"DE",
    "sg:address":"Rotherstr. 21",
    "sg:city":"Berlin",
    "sg:phone":"+49 30/24722211",
    "sg:postcode":"10245",
    "sg:province":"Berlin",
    "wof:name":"Ampa-baugesellschaft Mbh",
    "wof:placetype":"venue"
},
  "geometry": {"coordinates":[13.450938,52.50367],"type":"Point"}
}