{
  "type": "Feature",
  "properties": {
    "iso:country":"DE",
    "sg:address":"Erlenstegenstr. 113",
    "sg:city":"N\u00fcrnberg",
    "sg:phone":"+49 911/5988450",
    "sg:postcode":"90491",
    "sg:province":"Bayern",
    "wof:name":"Telenetwork",
    "wof:placetype":"venue"
},
  "geometry": {"coordinates":[11.1383390427,49.4727478027],"type":"Point"}
}