{
  "type": "Feature",
  "properties": {
    "iso:country":"DE",
    "sg:address":"W\u00f6lfnitzstr 2",
    "sg:city":"Dresden",
    "sg:phone":"+49 351/4952149",
    "sg:postcode":"01159",
    "sg:province":"Sachsen",
    "wof:name":"Funkelektronik Sts Dresden Gmbh",
    "wof:placetype":"venue"
},
  "geometry": {"coordinates":[13.7178268433,51.0511665344],"type":"Point"}
}