{
  "type": "Feature",
  "properties": {
    "iso:country":"DE",
    "sg:address":"Egerl\u00e4nder Str. 11",
    "sg:city":"Erding",
    "sg:phone":"+49 8122/49225",
    "sg:postcode":"85435",
    "sg:province":"Bayern",
    "wof:name":"Adelco Elektronik Gmbh",
    "wof:placetype":"venue"
},
  "geometry": {"coordinates":[11.9043207169,48.3063468933],"type":"Point"}
}