{
  "type": "Feature",
  "properties": {
    "iso:country":"DE",
    "sg:address":"Langenbergstr. 62",
    "sg:city":"Bocholt",
    "sg:phone":"+49 2871/13229",
    "sg:postcode":"46397",
    "sg:province":"Nordrhein-Westfalen",
    "wof:name":"A. U H. Driessen",
    "wof:placetype":"venue"
},
  "geometry": {"coordinates":[6.6195149422,51.8388671875],"type":"Point"}
}