{
  "type": "Feature",
  "properties": {
    "iso:country":"DE",
    "sg:address":"Loyerbergstr. 24",
    "sg:city":"Rastede",
    "sg:phone":"+49 4402/3458",
    "sg:postcode":"26180",
    "sg:province":"Niedersachsen",
    "wof:name":"Manfred Krott",
    "wof:placetype":"venue"
},
  "geometry": {"coordinates":[8.2665271759,53.2341270447],"type":"Point"}
}