{
  "type": "Feature",
  "properties": {
    "iso:country":"DE",
    "sg:address":"Esplanade 17",
    "sg:city":"Hamburg",
    "sg:phone":"+49 40/313918",
    "sg:postcode":"20354",
    "sg:province":"Hamburg",
    "wof:name":"Nevada Spiel- Und Freizeit Automatenaufstellbetriebe Gmbh",
    "wof:placetype":"venue"
},
  "geometry": {"coordinates":[9.9908094406,53.5576972961],"type":"Point"}
}