{
  "type": "Feature",
  "properties": {
    "iso:country":"DE",
    "sg:address":"Kleinengroden 1",
    "sg:city":"Wangerland",
    "sg:phone":"+49 4463/245",
    "sg:postcode":"26434",
    "sg:province":"Niedersachsen",
    "wof:name":"Johann Graalfs",
    "wof:placetype":"venue"
},
  "geometry": {"coordinates":[7.84657,53.669678],"type":"Point"}
}