{
  "type": "Feature",
  "properties": {
    "iso:country":"DE",
    "sg:address":"Holzkoppelweg 17",
    "sg:city":"Kiel",
    "sg:phone":"+49 4943/1542263",
    "sg:postcode":"24118",
    "sg:province":"Schleswig-Holstein",
    "wof:name":"Steger Jr.",
    "wof:placetype":"venue"
},
  "geometry": {"coordinates":[10.113815,54.337357],"type":"Point"}
}