{
  "type": "Feature",
  "properties": {
    "iso:country":"DE",
    "sg:address":"Marktplatz 10",
    "sg:city":"Staffelstein",
    "sg:phone":"+49 9573/5885",
    "sg:postcode":"96231",
    "sg:province":"Bayern",
    "wof:name":"M 10 Johanna Dinkel",
    "wof:placetype":"venue"
},
  "geometry": {"coordinates":[10.999175,50.102413],"type":"Point"}
}