{
  "type": "Feature",
  "properties": {
    "iso:country":"DE",
    "sg:address":"Brockenstra\u00dfe 45c",
    "sg:city":"Schierke",
    "sg:postcode":"38879",
    "sg:province":"Sachsen-Anhalt",
    "wof:name":"Brocken Immobilien",
    "wof:placetype":"venue"
},
  "geometry": {"coordinates":[10.6510353088,51.7690010071],"type":"Point"}
}