{
  "type": "Feature",
  "properties": {
    "iso:country":"DE",
    "sg:address":"Bei den H\u00f6fen 11 a",
    "sg:city":"Hamburg",
    "sg:phone":"+49 40/65493864",
    "sg:postcode":"22043",
    "sg:province":"Hamburg",
    "wof:name":"Art & Style Nigam Mansoor E.k.",
    "wof:placetype":"venue"
},
  "geometry": {"coordinates":[10.13337,53.57238],"type":"Point"}
}