{
  "type": "Feature",
  "properties": {
    "iso:country":"DE",
    "sg:address":"Lindenstr. 68",
    "sg:city":"Loxstedt",
    "sg:phone":"+49 4744/6255",
    "sg:postcode":"27612",
    "sg:province":"Niedersachsen",
    "wof:name":"Klaus Jantzen Holzhandel Gmbh",
    "wof:placetype":"venue"
},
  "geometry": {"coordinates":[8.624884,53.457806],"type":"Point"}
}