{
  "type": "Feature",
  "properties": {
    "iso:country":"DE",
    "sg:address":"Dyckburgstr. 71b",
    "sg:city":"M\u00fcnster",
    "sg:phone":"+49 251/931090",
    "sg:postcode":"48155",
    "sg:province":"Nordrhein-Westfalen",
    "wof:name":"Schoster Kg",
    "wof:placetype":"venue"
},
  "geometry": {"coordinates":[7.677464962,51.9759178162],"type":"Point"}
}