{
  "type": "Feature",
  "properties": {
    "iso:country":"DE",
    "sg:address":"Dresdener Str. 97",
    "sg:city":"Putzkau",
    "sg:phone":"+49 3594/77360",
    "sg:postcode":"01877",
    "sg:province":"Sachsen",
    "wof:name":"Gunter Israel",
    "wof:placetype":"venue"
},
  "geometry": {"coordinates":[14.192605,51.109467],"type":"Point"}
}