{
  "type": "Feature",
  "properties": {
    "iso:country":"DE",
    "sg:address":"Schlosserstr. 7",
    "sg:city":"Lahr",
    "sg:phone":"+49 7821/22038",
    "sg:postcode":"77933",
    "sg:province":"Baden-W\u00fcrttemberg",
    "wof:name":"M. Fischer",
    "wof:placetype":"venue"
},
  "geometry": {"coordinates":[7.8740110397,48.3403320312],"type":"Point"}
}