{
  "type": "Feature",
  "properties": {
    "iso:country":"DE",
    "sg:address":"35457",
    "sg:city":"Lollar",
    "sg:postcode":"35457",
    "sg:province":"Hessen",
    "wof:name":"Volksbank Lollar Eg",
    "wof:placetype":"venue"
},
  "geometry": {"coordinates":[8.68898,50.668369],"type":"Point"}
}