{
  "type": "Feature",
  "properties": {
    "iso:country":"DE",
    "sg:address":"Annenesch 14",
    "sg:city":"Wald",
    "sg:phone":"+49 7578/559",
    "sg:postcode":"88639",
    "sg:province":"Baden-W\u00fcrttemberg",
    "wof:name":"Konrad W\u00f6ttke",
    "wof:placetype":"venue"
},
  "geometry": {"coordinates":[9.168912,47.936378],"type":"Point"}
}