{
  "type": "Feature",
  "properties": {
    "iso:country":"DE",
    "sg:address":"Speyerer Str. 40",
    "sg:city":"Reilingen",
    "sg:phone":"+49 6205/94770",
    "sg:postcode":"68799",
    "sg:province":"Baden-W\u00fcrttemberg",
    "wof:name":"L\u00fctzel Bau Gmbh",
    "wof:placetype":"venue"
},
  "geometry": {"coordinates":[8.5636196136,49.2930335999],"type":"Point"}
}