{
  "type": "Feature",
  "properties": {
    "iso:country":"DE",
    "sg:address":"Leipziger Str. 29",
    "sg:city":"Mittweida",
    "sg:phone":"+49 3727/976342",
    "sg:postcode":"09648",
    "sg:province":"Sachsen",
    "wof:name":"Laservorm Gmbh",
    "wof:placetype":"venue"
},
  "geometry": {"coordinates":[12.9566307068,50.990562439],"type":"Point"}
}