{
  "type": "Feature",
  "properties": {
    "iso:country":"DE",
    "sg:address":"Pfarrer-Weingand-Str. 38",
    "sg:city":"Haag",
    "sg:phone":"+49 8167/9230",
    "sg:postcode":"85410",
    "sg:province":"Bayern",
    "wof:name":"Karl-heinz Bartels Ingenieur",
    "wof:placetype":"venue"
},
  "geometry": {"coordinates":[11.8236722946,48.4593009949],"type":"Point"}
}