{
  "type": "Feature",
  "properties": {
    "iso:country":"DE",
    "sg:address":"Fliedersteig 11-13",
    "sg:city":"R\u00fcckersdorf",
    "sg:phone":"+49 911/570197",
    "sg:postcode":"90607",
    "sg:province":"Bayern",
    "wof:name":"Dr. Steinfels Sprachreisen Gmbh",
    "wof:placetype":"venue"
},
  "geometry": {"coordinates":[11.248623848,49.4984588623],"type":"Point"}
}