{
  "type": "Feature",
  "properties": {
    "iso:country":"DE",
    "sg:address":"Breitscheider Weg 10",
    "sg:city":"Ratingen",
    "sg:phone":"+49 2102/32292",
    "sg:postcode":"40885",
    "sg:province":"Nordrhein-Westfalen",
    "wof:name":"Kurt Decker Architekt",
    "wof:placetype":"venue"
},
  "geometry": {"coordinates":[6.818927,51.34],"type":"Point"}
}