{
  "type": "Feature",
  "properties": {
    "iso:country":"DE",
    "sg:address":"Sommerdeich 14a",
    "sg:city":"Kaiser-Wilhelm-Koog",
    "sg:phone":"+49 4856/510",
    "sg:postcode":"25709",
    "sg:province":"Schleswig-Holstein",
    "wof:name":"Windenergiepark Westk\u00fcste Gmbh",
    "wof:placetype":"venue"
},
  "geometry": {"coordinates":[8.950435,53.933338],"type":"Point"}
}