{
  "type": "Feature",
  "properties": {
    "iso:country":"DE",
    "sg:address":"Kellerweg 18 a",
    "sg:city":"Bad W\u00f6rishofen",
    "sg:phone":"+49 8247/90012",
    "sg:postcode":"86825",
    "sg:province":"Bayern",
    "wof:name":"Contacta Project Engineering And",
    "wof:placetype":"venue"
},
  "geometry": {"coordinates":[10.597443,47.999332],"type":"Point"}
}