{
  "type": "Feature",
  "properties": {
    "iso:country":"DE",
    "sg:address":"H\u00e4ldeweg 50",
    "sg:city":"Oberderdingen",
    "sg:postcode":"75038",
    "sg:province":"Baden-W\u00fcrttemberg",
    "wof:name":"Gabriel Blankenhorn",
    "wof:placetype":"venue"
},
  "geometry": {"coordinates":[8.773932457,49.0901145935],"type":"Point"}
}