{
  "type": "Feature",
  "properties": {
    "iso:country":"DE",
    "sg:address":"Auf der Frankenh\u00f6he",
    "sg:city":"Aurach",
    "sg:phone":"+49 9804/888",
    "sg:postcode":"91589",
    "sg:province":"Bayern",
    "wof:name":"Autobahnrastst\u00e4tte Frankenh\u00f6he S\u00fcd",
    "wof:placetype":"venue"
},
  "geometry": {"coordinates":[10.3505144119,49.2384300232],"type":"Point"}
}