{
  "type": "Feature",
  "properties": {
    "iso:country":"DE",
    "sg:address":"Stetten",
    "sg:city":"Engen",
    "sg:phone":"+49 7733/8231",
    "sg:postcode":"78234",
    "sg:province":"Baden-W\u00fcrttemberg",
    "wof:name":"Kreuz",
    "wof:placetype":"venue"
},
  "geometry": {"coordinates":[8.7779102325,47.8574333191],"type":"Point"}
}