{
  "type": "Feature",
  "properties": {
    "iso:country":"DE",
    "sg:address":"Stiftsstr. 61",
    "sg:city":"Kerpen",
    "sg:phone":"+49 2237/52155",
    "sg:postcode":"50171",
    "sg:province":"Nordrhein-Westfalen",
    "wof:name":"H. P. Schilbach",
    "wof:placetype":"venue"
},
  "geometry": {"coordinates":[6.6905808449,50.8682479858],"type":"Point"}
}