{
  "type": "Feature",
  "properties": {
    "iso:country":"DE",
    "sg:address":"Carl-Benz-Str. 4",
    "sg:city":"Schriesheim",
    "sg:phone":"+49 6203/661422",
    "sg:postcode":"69198",
    "sg:province":"Baden-W\u00fcrttemberg",
    "wof:name":"Maria Robert Praxis F\u00fcr Ergotherapie",
    "wof:placetype":"venue"
},
  "geometry": {"coordinates":[8.663483,49.466328],"type":"Point"}
}