{
  "type": "Feature",
  "properties": {
    "iso:country":"DE",
    "sg:address":"Riemenschneiderstr. 20",
    "sg:city":"Estenfeld",
    "sg:phone":"+49 9305/212",
    "sg:postcode":"97230",
    "sg:province":"Bayern",
    "wof:name":"J. Wolz",
    "wof:placetype":"venue"
},
  "geometry": {"coordinates":[10.006234169,49.8279037476],"type":"Point"}
}