{
  "type": "Feature",
  "properties": {
    "iso:country":"DE",
    "sg:address":"Hamburger Str. 2",
    "sg:city":"Essen",
    "sg:phone":"+49 201/755171",
    "sg:postcode":"45145",
    "sg:province":"Nordrhein-Westfalen",
    "wof:name":"Pinocco Pizzeria",
    "wof:placetype":"venue"
},
  "geometry": {"coordinates":[6.9579739571,51.4478683472],"type":"Point"}
}