{
  "type": "Feature",
  "properties": {
    "iso:country":"DE",
    "sg:address":"Th\u00fcringer-Wald-Str. 6",
    "sg:city":"Steinbach",
    "sg:phone":"+49 9269/334",
    "sg:postcode":"96361",
    "sg:province":"Bayern",
    "wof:name":"H. Jungkunz",
    "wof:placetype":"venue"
},
  "geometry": {"coordinates":[11.2889280319,50.4237709045],"type":"Point"}
}