{
  "type": "Feature",
  "properties": {
    "iso:country":"DE",
    "sg:address":"Antoniusstr. 14",
    "sg:city":"Rehlingen-Siersburg",
    "sg:phone":"+49 6869/753",
    "sg:postcode":"66780",
    "sg:province":"Saarland",
    "wof:name":"Manfred Siebenborn",
    "wof:placetype":"venue"
},
  "geometry": {"coordinates":[6.5661201477,49.3972244263],"type":"Point"}
}