{
  "type": "Feature",
  "properties": {
    "iso:country":"DE",
    "sg:address":"K\u00f6nigsallee 260",
    "sg:city":"Kleve",
    "sg:phone":"+49 2821/23538",
    "sg:postcode":"47533",
    "sg:province":"Nordrhein-Westfalen",
    "wof:name":"Restaurant Zum Aussichtsturm",
    "wof:placetype":"venue"
},
  "geometry": {"coordinates":[6.1407299042,51.7855110168],"type":"Point"}
}