{
  "type": "Feature",
  "properties": {
    "iso:country":"DE",
    "sg:address":"Neuh\u00e4user Str. 32",
    "sg:city":"Neuhaus-Schierschnitz",
    "sg:phone":"+49 36764/72623",
    "sg:postcode":"96524",
    "sg:province":"Th\u00fcringen",
    "wof:name":"Restaurant Zur Alten Schule",
    "wof:placetype":"venue"
},
  "geometry": {"coordinates":[11.2378740311,50.2969398499],"type":"Point"}
}