{
  "type": "Feature",
  "properties": {
    "iso:country":"DE",
    "sg:address":"Camper Str. 8",
    "sg:city":"Berne",
    "sg:phone":"+49 4406/5283",
    "sg:postcode":"27804",
    "sg:province":"Niedersachsen",
    "wof:name":"Hans-georg Bothe Und Bernd Bothe Ohg",
    "wof:placetype":"venue"
},
  "geometry": {"coordinates":[8.4900722504,53.1767463684],"type":"Point"}
}