{
  "type": "Feature",
  "properties": {
    "iso:country":"DE",
    "sg:address":"Mittelstr. 1a",
    "sg:city":"Zschepplin",
    "sg:phone":"+49 3423/604259",
    "sg:postcode":"04838",
    "sg:province":"Sachsen",
    "wof:name":"Zed-bau Gmbh",
    "wof:placetype":"venue"
},
  "geometry": {"coordinates":[12.599068,51.505287],"type":"Point"}
}