{
  "type": "Feature",
  "properties": {
    "iso:country":"DE",
    "sg:address":"Endertstr.",
    "sg:city":"Cochem",
    "sg:phone":"+49 2671/7036",
    "sg:postcode":"56812",
    "sg:province":"Rheinland-Pfalz",
    "wof:name":"Beatrix Theisen",
    "wof:placetype":"venue"
},
  "geometry": {"coordinates":[7.1514420509,50.1521148682],"type":"Point"}
}