{
  "type": "Feature",
  "properties": {
    "iso:country":"DE",
    "sg:address":"Eisenleitenstr. 23",
    "sg:city":"Bad Berneck",
    "sg:phone":"+49 9273/57115",
    "sg:postcode":"95460",
    "sg:province":"Bayern",
    "wof:name":"Sanit\u00e4tshaus Martin Gmbh",
    "wof:placetype":"venue"
},
  "geometry": {"coordinates":[11.6728258133,50.0458335876],"type":"Point"}
}