{
  "type": "Feature",
  "properties": {
    "iso:country":"DE",
    "sg:address":"Marktstr. 14",
    "sg:city":"Algermissen",
    "sg:postcode":"31191",
    "sg:province":"Niedersachsen",
    "wof:name":"Windenergie Algermissen Gmbh",
    "wof:placetype":"venue"
},
  "geometry": {"coordinates":[9.973207,52.253448],"type":"Point"}
}