{
  "type": "Feature",
  "properties": {
    "iso:country":"DE",
    "sg:address":"Porschering 14",
    "sg:city":"Kaltenkirchen",
    "sg:phone":"+49 4973/3195380",
    "sg:postcode":"24568",
    "sg:province":"Schleswig-Holstein",
    "wof:name":"Druckerei Gerthofer Gmbh",
    "wof:placetype":"venue"
},
  "geometry": {"coordinates":[9.812253952,48.6289138794],"type":"Point"}
}