{
  "type": "Feature",
  "properties": {
    "iso:country":"DE",
    "sg:address":"Heckenrosenstr. 25",
    "sg:city":"Waiblingen",
    "sg:phone":"+49 7151/82308",
    "sg:postcode":"71336",
    "sg:province":"Baden-W\u00fcrttemberg",
    "wof:name":"Franz-anton Martin Ingenieur",
    "wof:placetype":"venue"
},
  "geometry": {"coordinates":[9.3200206757,48.8641967773],"type":"Point"}
}