{
  "type": "Feature",
  "properties": {
    "iso:country":"DE",
    "sg:address":"Lutterstr. 34",
    "sg:city":"Bielefeld",
    "sg:phone":"+49 521/150967",
    "sg:postcode":"33617",
    "sg:province":"Nordrhein-Westfalen",
    "wof:name":"Rolf Scheele Steuerberater",
    "wof:placetype":"venue"
},
  "geometry": {"coordinates":[8.5192136765,52.0134468079],"type":"Point"}
}