{
  "type": "Feature",
  "properties": {
    "iso:country":"DE",
    "sg:address":"B\u00e4ckerstr. 29",
    "sg:city":"L\u00fcbbecke",
    "sg:phone":"+49 5741/5478",
    "sg:postcode":"32312",
    "sg:province":"Nordrhein-Westfalen",
    "wof:name":"Foto-pescht Inh. J\u00fcrgen Gilbert",
    "wof:placetype":"venue"
},
  "geometry": {"coordinates":[8.6195011139,52.3043403625],"type":"Point"}
}