{
  "type": "Feature",
  "properties": {
    "iso:country":"DE",
    "sg:address":"Siegfriedstr. 18",
    "sg:city":"Worms",
    "sg:phone":"+49 6241/413838",
    "sg:postcode":"67547",
    "sg:province":"Rheinland-Pfalz",
    "wof:name":"Deicke Und Schlamp Rechtsanw\u00e4lte",
    "wof:placetype":"venue"
},
  "geometry": {"coordinates":[8.3613376617,49.6347427368],"type":"Point"}
}