{
  "type": "Feature",
  "properties": {
    "iso:country":"DE",
    "sg:address":"Breite Str. 36",
    "sg:city":"Grieben",
    "sg:phone":"+49 39362/81231",
    "sg:postcode":"39517",
    "sg:province":"Sachsen-Anhalt",
    "wof:name":"Agrargenossenschaft Eg Elbvorland",
    "wof:placetype":"venue"
},
  "geometry": {"coordinates":[11.80866,52.434437],"type":"Point"}
}