{
  "type": "Feature",
  "properties": {
    "iso:country":"DE",
    "sg:address":"Kuseler Str.",
    "sg:city":"Baumholder",
    "sg:phone":"+49 6783/5087",
    "sg:postcode":"55774",
    "sg:province":"Rheinland-Pfalz",
    "wof:name":"Norma Lebensmittel- Filialbetrieb Gmbh & Co. Kg",
    "wof:placetype":"venue"
},
  "geometry": {"coordinates":[7.3431282043,49.613910675],"type":"Point"}
}