{
  "type": "Feature",
  "properties": {
    "iso:country":"DE",
    "sg:address":"Pinneberger Chaussee 134",
    "sg:city":"Hamburg",
    "sg:phone":"+49 40/573271",
    "sg:postcode":"22523",
    "sg:province":"Hamburg",
    "wof:name":"J\u00fcrgen Dierich Masseur",
    "wof:placetype":"venue"
},
  "geometry": {"coordinates":[9.887741,53.620014],"type":"Point"}
}