{
  "type": "Feature",
  "properties": {
    "iso:country":"DE",
    "sg:address":"Schwedesstr. 26",
    "sg:city":"Kassel",
    "sg:phone":"+49 561/882690",
    "sg:postcode":"34128",
    "sg:province":"Hessen",
    "wof:name":"Barbara U. Herbert Klimke Rechtsanw\u00e4lte U. Notare",
    "wof:placetype":"venue"
},
  "geometry": {"coordinates":[9.4608850479,51.3331031799],"type":"Point"}
}