{
  "type": "Feature",
  "properties": {
    "iso:country":"DE",
    "sg:address":"Winterberg 3",
    "sg:city":"Kalletal",
    "sg:phone":"+49 5733/7600",
    "sg:postcode":"32689",
    "sg:province":"Nordrhein-Westfalen",
    "wof:name":"Peter Kerski",
    "wof:placetype":"venue"
},
  "geometry": {"coordinates":[8.9006032944,52.1550102234],"type":"Point"}
}