{
  "type": "Feature",
  "properties": {
    "iso:country":"DE",
    "sg:address":"Silberstein 96",
    "sg:city":"Geroldsgr\u00fcn",
    "sg:phone":"+49 9267/319",
    "sg:postcode":"95179",
    "sg:province":"Bayern",
    "wof:name":"Pension Eberhardt",
    "wof:placetype":"venue"
},
  "geometry": {"coordinates":[11.5639677048,50.3433876038],"type":"Point"}
}