{
  "type": "Feature",
  "properties": {
    "iso:country":"DE",
    "sg:address":"Bernauer Str. 7",
    "sg:city":"Altlandsberg",
    "sg:postcode":"15345",
    "sg:province":"Brandenburg",
    "wof:name":"Gerhard Mirisch",
    "wof:placetype":"venue"
},
  "geometry": {"coordinates":[13.727968,52.566372],"type":"Point"}
}