{
  "type": "Feature",
  "properties": {
    "iso:country":"DE",
    "sg:address":"Fulerumer Str. 6",
    "sg:city":"Essen",
    "sg:phone":"+49 201/712528",
    "sg:postcode":"45149",
    "sg:province":"Nordrhein-Westfalen",
    "wof:name":"Hans-werner Brauckmann Gmbh",
    "wof:placetype":"venue"
},
  "geometry": {"coordinates":[6.964659,51.435055],"type":"Point"}
}