{
  "type": "Feature",
  "properties": {
    "iso:country":"DE",
    "sg:address":"Max-Stromeyer-Str. 21",
    "sg:city":"Konstanz",
    "sg:phone":"+49 7531/8030",
    "sg:postcode":"78467",
    "sg:province":"Baden-W\u00fcrttemberg",
    "wof:name":"Stadtwerke Konstanz",
    "wof:placetype":"venue"
},
  "geometry": {"coordinates":[9.161154,47.675861],"type":"Point"}
}