{
  "type": "Feature",
  "properties": {
    "iso:country":"DE",
    "sg:address":"Gartenstr. 18",
    "sg:city":"Reutlingen",
    "sg:phone":"+49 7121/34910",
    "sg:postcode":"72764",
    "sg:province":"Baden-W\u00fcrttemberg",
    "wof:name":"Buch Und Bibliothek",
    "wof:placetype":"venue"
},
  "geometry": {"coordinates":[9.2124891281,48.4935569763],"type":"Point"}
}