{
  "type": "Feature",
  "properties": {
    "iso:country":"DE",
    "sg:address":"Herresbacher Str. 22",
    "sg:city":"K\u00f6nigswinter",
    "sg:phone":"+49 2244/5822",
    "sg:postcode":"53639",
    "sg:province":"Nordrhein-Westfalen",
    "wof:name":"Ludwig Otto Architekt",
    "wof:placetype":"venue"
},
  "geometry": {"coordinates":[7.28019,50.707767],"type":"Point"}
}