{
  "type": "Feature",
  "properties": {
    "iso:country":"DE",
    "sg:address":"Am Stutenanger 4",
    "sg:city":"Oberschlei\u00dfheim",
    "sg:phone":"+49 89/3151385",
    "sg:postcode":"85764",
    "sg:province":"Bayern",
    "wof:name":"Restaurant Pfefferm\u00fchle",
    "wof:placetype":"venue"
},
  "geometry": {"coordinates":[11.5525436401,48.2559089661],"type":"Point"}
}