{
  "type": "Feature",
  "properties": {
    "iso:country":"DE",
    "sg:address":"Winterberg 1",
    "sg:city":"Biederbach",
    "sg:phone":"+49 7682/1455",
    "sg:postcode":"79215",
    "sg:province":"Baden-W\u00fcrttemberg",
    "wof:name":"Georg Ringwald",
    "wof:placetype":"venue"
},
  "geometry": {"coordinates":[8.005913,48.221607],"type":"Point"}
}