{
  "type": "Feature",
  "properties": {
    "iso:country":"DE",
    "sg:address":"Seligenst\u00e4dter Str. 96",
    "sg:city":"Seligenstadt",
    "sg:phone":"+49 6182/65514",
    "sg:postcode":"63500",
    "sg:province":"Hessen",
    "wof:name":"Daum Elektro- Installationen Gmbh",
    "wof:placetype":"venue"
},
  "geometry": {"coordinates":[8.94382,50.053471],"type":"Point"}
}