{
  "type": "Feature",
  "properties": {
    "iso:country":"DE",
    "sg:address":"Max-Planck-Str. 25",
    "sg:city":"Ritterhude",
    "sg:phone":"+49 421/637364",
    "sg:postcode":"27721",
    "sg:province":"Niedersachsen",
    "wof:name":"Klaus Beil Bauschlosserei Gmbh",
    "wof:placetype":"venue"
},
  "geometry": {"coordinates":[8.700751,53.192665],"type":"Point"}
}