{
  "type": "Feature",
  "properties": {
    "iso:country":"DE",
    "sg:address":"Hauptstr. 6",
    "sg:city":"Reuth",
    "sg:phone":"+49 9682/522",
    "sg:postcode":"92717",
    "sg:province":"Bayern",
    "wof:name":"Ch. Galbakioti",
    "wof:placetype":"venue"
},
  "geometry": {"coordinates":[12.1212835312,49.8436088562],"type":"Point"}
}