{
  "type": "Feature",
  "properties": {
    "iso:country":"DE",
    "sg:address":"Leimkugelstr. 10",
    "sg:city":"Essen",
    "sg:postcode":"45141",
    "sg:province":"Nordrhein-Westfalen",
    "wof:name":"Institut F\u00fcr Umweltverfahrenstechnik",
    "wof:placetype":"venue"
},
  "geometry": {"coordinates":[7.0041399002,51.4727859497],"type":"Point"}
}