{
  "type": "Feature",
  "properties": {
    "iso:country":"DE",
    "sg:address":"Ottersberger Str. 29",
    "sg:city":"Langwedel",
    "sg:phone":"+49 4232/282",
    "sg:postcode":"27299",
    "sg:province":"Niedersachsen",
    "wof:name":"H. Oetting",
    "wof:placetype":"venue"
},
  "geometry": {"coordinates":[9.209979,53.01321],"type":"Point"}
}