{
  "type": "Feature",
  "properties": {
    "iso:country":"DE",
    "sg:address":"Alte Dorfstr. 28",
    "sg:city":"Osterode",
    "sg:postcode":"37520",
    "sg:province":"Niedersachsen",
    "wof:name":"Internationaler Freundschafts- Verein",
    "wof:placetype":"venue"
},
  "geometry": {"coordinates":[10.1667833328,51.7453842163],"type":"Point"}
}