{
  "type": "Feature",
  "properties": {
    "iso:country":"DE",
    "sg:address":"Urbanstr. 103",
    "sg:city":"Berlin",
    "sg:phone":"+49 30/6931745",
    "sg:postcode":"10967",
    "sg:province":"Berlin",
    "wof:name":"Wolfgang Sch\u00e4fer",
    "wof:placetype":"venue"
},
  "geometry": {"coordinates":[13.420999527,52.4897232056],"type":"Point"}
}