{
  "type": "Feature",
  "properties": {
    "iso:country":"DE",
    "sg:address":"Mittelstr. 10",
    "sg:city":"Radefeld",
    "sg:phone":"+49 34207/70363",
    "sg:postcode":"04509",
    "sg:province":"Sachsen",
    "wof:name":"Thomas Zander Ma\u00df Schreier Gmbh",
    "wof:placetype":"venue"
},
  "geometry": {"coordinates":[12.353229,51.511105],"type":"Point"}
}