{
  "type": "Feature",
  "properties": {
    "iso:country":"DE",
    "sg:address":"Montabaurer Str. 18",
    "sg:city":"Welschneudorf",
    "sg:phone":"+49 2608/230",
    "sg:postcode":"56412",
    "sg:province":"Rheinland-Pfalz",
    "wof:name":"Werner Billaudelle",
    "wof:placetype":"venue"
},
  "geometry": {"coordinates":[7.799653,50.37344],"type":"Point"}
}