{
  "type": "Feature",
  "properties": {
    "iso:country":"DE",
    "sg:address":"Am Bergfried 16",
    "sg:city":"Langen",
    "sg:phone":"+49 6103/52026",
    "sg:postcode":"63225",
    "sg:province":"Hessen",
    "wof:name":"Ferro Gmbh",
    "wof:placetype":"venue"
},
  "geometry": {"coordinates":[8.6888923645,49.9815177917],"type":"Point"}
}