{
  "type": "Feature",
  "properties": {
    "iso:country":"DE",
    "sg:address":"M\u00fchlenweg",
    "sg:city":"Cottbus",
    "sg:phone":"+49 355/790187",
    "sg:postcode":"03048",
    "sg:province":"Brandenburg",
    "wof:name":"Gastst\u00e4tte Zum Hundefreund",
    "wof:placetype":"venue"
},
  "geometry": {"coordinates":[14.2932901382,51.7478942871],"type":"Point"}
}