{
  "type": "Feature",
  "properties": {
    "iso:country":"DE",
    "sg:address":"Im Schuhmachergewann 11-1",
    "sg:city":"Heidelberg",
    "sg:phone":"+49 6221/828081",
    "sg:postcode":"69123",
    "sg:province":"Baden-W\u00fcrttemberg",
    "wof:name":"Kdk Kalibrierdienst Kopp Gmbh",
    "wof:placetype":"venue"
},
  "geometry": {"coordinates":[8.639431,49.424046],"type":"Point"}
}