{
  "type": "Feature",
  "properties": {
    "iso:country":"DE",
    "sg:address":"Boehringerstr. 4",
    "sg:city":"Mannheim",
    "sg:phone":"+49 621/777770",
    "sg:postcode":"68307",
    "sg:province":"Baden-W\u00fcrttemberg",
    "wof:name":"Aqua-protect Middle East Gmbh",
    "wof:placetype":"venue"
},
  "geometry": {"coordinates":[8.4796733856,49.5357666016],"type":"Point"}
}