{
  "type": "Feature",
  "properties": {
    "iso:country":"DE",
    "sg:address":"Frankenallee 275",
    "sg:city":"Frankfurt",
    "sg:phone":"+49 69/735927",
    "sg:postcode":"60326",
    "sg:province":"Hessen",
    "wof:name":"Pizzeria Piccolo-mondo",
    "wof:placetype":"venue"
},
  "geometry": {"coordinates":[8.6256446838,50.1026954651],"type":"Point"}
}