{
  "type": "Feature",
  "properties": {
    "iso:country":"DE",
    "sg:address":"Gartenfelder Str. 109",
    "sg:city":"Berlin",
    "sg:phone":"+49 30/3346483",
    "sg:postcode":"13599",
    "sg:province":"Berlin",
    "wof:name":"J. Und M. Lemke",
    "wof:placetype":"venue"
},
  "geometry": {"coordinates":[13.2395887375,52.5427055359],"type":"Point"}
}