{
  "type": "Feature",
  "properties": {
    "iso:country":"DE",
    "sg:city":"Horst",
    "sg:phone":"+49 4542/1645",
    "sg:postcode":"23883",
    "sg:province":"Schleswig-Holstein",
    "wof:name":"E. Manske",
    "wof:placetype":"venue"
},
  "geometry": {"coordinates":[10.77373,53.637615],"type":"Point"}
}