{
  "type": "Feature",
  "properties": {
    "iso:country":"DE",
    "sg:address":"Arvid-Harnack-Str. 8",
    "sg:city":"Jena",
    "sg:postcode":"07743",
    "sg:province":"Th\u00fcringen",
    "wof:name":"K\u00e4hne & Kollegen Pro- Jektentwicklung Jena Ag",
    "wof:placetype":"venue"
},
  "geometry": {"coordinates":[11.589738,50.933113],"type":"Point"}
}