{
  "type": "Feature",
  "properties": {
    "iso:country":"DE",
    "sg:address":"Espenstr. 14",
    "sg:city":"Wuppertal",
    "sg:phone":"+49 202/424475",
    "sg:postcode":"42119",
    "sg:province":"Nordrhein-Westfalen",
    "wof:name":"Max Buck Ohg",
    "wof:placetype":"venue"
},
  "geometry": {"coordinates":[7.1549839973,51.2522354126],"type":"Point"}
}