{
  "type": "Feature",
  "properties": {
    "iso:country":"DE",
    "sg:address":"Braugasse 6",
    "sg:city":"Liebstadt",
    "sg:phone":"+49 35025/50311",
    "sg:postcode":"01825",
    "sg:province":"Sachsen",
    "wof:name":"Edmund Reimann",
    "wof:placetype":"venue"
},
  "geometry": {"coordinates":[13.857459,50.863777],"type":"Point"}
}