{
  "type": "Feature",
  "properties": {
    "iso:country":"DE",
    "sg:address":"Fritz-Reuter-Allee 19",
    "sg:city":"B\u00fctzow",
    "sg:phone":"+49 38461/52060",
    "sg:postcode":"18246",
    "sg:province":"Mecklenburg-Vorpommern",
    "wof:name":"Rudolf Schr\u00f6der",
    "wof:placetype":"venue"
},
  "geometry": {"coordinates":[11.993682,53.838562],"type":"Point"}
}