{
  "type": "Feature",
  "properties": {
    "iso:country":"DE",
    "sg:address":"Mariakronstr. 12",
    "sg:city":"Stralsund",
    "sg:phone":"+49 3831/299447",
    "sg:postcode":"18437",
    "sg:province":"Mecklenburg-Vorpommern",
    "wof:name":"W. Pusch",
    "wof:placetype":"venue"
},
  "geometry": {"coordinates":[13.077745,54.313103],"type":"Point"}
}