{
  "type": "Feature",
  "properties": {
    "iso:country":"DE",
    "sg:address":"Hutschenreuther Str. 2",
    "sg:city":"Selb",
    "sg:phone":"+49 9287/4465",
    "sg:postcode":"95100",
    "sg:province":"Bayern",
    "wof:name":"R. L. Czochanski",
    "wof:placetype":"venue"
},
  "geometry": {"coordinates":[12.13728,50.177982],"type":"Point"}
}