{
  "type": "Feature",
  "properties": {
    "iso:country":"DE",
    "sg:address":"Industriegebiet Voisweg",
    "sg:city":"Ratingen",
    "sg:phone":"+49 2102/87450",
    "sg:postcode":"40878",
    "sg:province":"Nordrhein-Westfalen",
    "wof:name":"Rollon Gmbh",
    "wof:placetype":"venue"
},
  "geometry": {"coordinates":[6.848095,51.29715],"type":"Point"}
}