{
  "type": "Feature",
  "properties": {
    "iso:country":"DE",
    "sg:address":"Goethestr. 9",
    "sg:city":"Dornstetten",
    "sg:phone":"+49 7443/8837",
    "sg:postcode":"72280",
    "sg:province":"Baden-W\u00fcrttemberg",
    "wof:name":"H. Jung",
    "wof:placetype":"venue"
},
  "geometry": {"coordinates":[8.5044717789,48.4719161987],"type":"Point"}
}