{
  "type": "Feature",
  "properties": {
    "iso:country":"DE",
    "sg:address":"Wilhelmistr. 2",
    "sg:city":"Hamburg",
    "sg:phone":"+49 40/823858",
    "sg:postcode":"22605",
    "sg:province":"Hamburg",
    "wof:name":"Klaus-dieter Ehlbeck Architekt",
    "wof:placetype":"venue"
},
  "geometry": {"coordinates":[9.869531,53.558002],"type":"Point"}
}