{
  "type": "Feature",
  "properties": {
    "iso:country":"DE",
    "sg:address":"B\u00e4derstr. 1",
    "sg:city":"Lensahn",
    "sg:phone":"+49 4363/2428",
    "sg:postcode":"23738",
    "sg:province":"Schleswig-Holstein",
    "wof:name":"Manfred Madsen Rechtsanwalt Und Notar",
    "wof:placetype":"venue"
},
  "geometry": {"coordinates":[10.8870820999,54.2207298279],"type":"Point"}
}