{
  "type": "Feature",
  "properties": {
    "iso:country":"DE",
    "sg:address":"Kaiserbergstr. 21",
    "sg:city":"Schw\u00e4bisch Gm\u00fcnd",
    "sg:phone":"+49 7171/5006",
    "sg:postcode":"73529",
    "sg:province":"Baden-W\u00fcrttemberg",
    "wof:name":"Klimatec",
    "wof:placetype":"venue"
},
  "geometry": {"coordinates":[9.8051795959,48.7449493408],"type":"Point"}
}