{
  "type": "Feature",
  "properties": {
    "iso:country":"DE",
    "sg:address":"Plattenstr. 2",
    "sg:city":"Ortenberg",
    "sg:phone":"+49 6041/345",
    "sg:postcode":"63683",
    "sg:province":"Hessen",
    "wof:name":"M. Stamm",
    "wof:placetype":"venue"
},
  "geometry": {"coordinates":[9.0495471954,50.3242797852],"type":"Point"}
}