{
  "type": "Feature",
  "properties": {
    "iso:country":"DE",
    "sg:address":"Celsiusstr. 57",
    "sg:city":"Berlin",
    "sg:phone":"+49 30/71389805",
    "sg:postcode":"12207",
    "sg:province":"Berlin",
    "wof:name":"Oliver Antrick",
    "wof:placetype":"venue"
},
  "geometry": {"coordinates":[13.3127746582,52.4127235413],"type":"Point"}
}