{
  "type": "Feature",
  "properties": {
    "iso:country":"DE",
    "sg:address":"Lindenstr. 27",
    "sg:city":"Nossen",
    "sg:phone":"+49 35242/64350",
    "sg:postcode":"01683",
    "sg:province":"Sachsen",
    "wof:name":"I. Vogel",
    "wof:placetype":"venue"
},
  "geometry": {"coordinates":[13.2932910919,51.0557518005],"type":"Point"}
}