{
  "type": "Feature",
  "properties": {
    "iso:country":"DE",
    "sg:address":"M\u00fcnzstr. 23",
    "sg:city":"Berlin",
    "sg:phone":"+49 30/30872887",
    "sg:postcode":"10178",
    "sg:province":"Berlin",
    "wof:name":"Variom Biotechnology Ag",
    "wof:placetype":"venue"
},
  "geometry": {"coordinates":[13.4064588547,52.5248603821],"type":"Point"}
}