{
  "type": "Feature",
  "properties": {
    "iso:country":"DE",
    "sg:address":"Dorfstr. 79",
    "sg:city":"K\u00f6nigshain",
    "sg:postcode":"02829",
    "sg:province":"Sachsen",
    "wof:name":"Wenzels Einkaufzentrum Und Postagentur",
    "wof:placetype":"venue"
},
  "geometry": {"coordinates":[14.866538,51.180943],"type":"Point"}
}