{
  "type": "Feature",
  "properties": {
    "iso:country":"DE",
    "sg:address":"Pf\u00fchlstr. 41",
    "sg:city":"Bruchm\u00fchlbach-Miesau",
    "sg:phone":"+49 6372/4260",
    "sg:postcode":"66892",
    "sg:province":"Rheinland-Pfalz",
    "wof:name":"Schlosserei Neumann Gmbh",
    "wof:placetype":"venue"
},
  "geometry": {"coordinates":[7.46166,49.387341],"type":"Point"}
}