{
  "type": "Feature",
  "properties": {
    "iso:country":"DE",
    "sg:address":"Eichendorffstr. 11",
    "sg:city":"W\u00fcrzburg",
    "sg:postcode":"97072",
    "sg:province":"Bayern",
    "wof:name":"Thalion Graphic Solutions E.k.",
    "wof:placetype":"venue"
},
  "geometry": {"coordinates":[9.9306240082,49.7830543518],"type":"Point"}
}