{
  "type": "Feature",
  "properties": {
    "iso:country":"DE",
    "sg:address":"Schreinerstr. 14",
    "sg:city":"Reisbach",
    "sg:phone":"+49 8734/7942",
    "sg:postcode":"94419",
    "sg:province":"Bayern",
    "wof:name":"Richard Sem Bau Gmbh",
    "wof:placetype":"venue"
},
  "geometry": {"coordinates":[12.638289,48.576324],"type":"Point"}
}