{
  "type": "Feature",
  "properties": {
    "iso:country":"DE",
    "sg:address":"Bahnhofstr. 1",
    "sg:city":"Gro\u00dfbottwar",
    "sg:phone":"+49 7148/2392",
    "sg:postcode":"71723",
    "sg:province":"Baden-W\u00fcrttemberg",
    "wof:name":"Bosporus Kebap",
    "wof:placetype":"venue"
},
  "geometry": {"coordinates":[9.293176651,48.9995574951],"type":"Point"}
}