{
  "type": "Feature",
  "properties": {
    "iso:country":"DE",
    "sg:address":"Maintalstr. 40",
    "sg:city":"Wertheim",
    "sg:phone":"+49 9342/7613",
    "sg:postcode":"97877",
    "sg:province":"Baden-W\u00fcrttemberg",
    "wof:name":"K. Spielmann",
    "wof:placetype":"venue"
},
  "geometry": {"coordinates":[9.5707359314,49.7476501465],"type":"Point"}
}