{
  "type": "Feature",
  "properties": {
    "iso:country":"DE",
    "sg:address":"Am Hagen 13",
    "sg:city":"Waldeck",
    "sg:phone":"+49 5634/308",
    "sg:postcode":"34513",
    "sg:province":"Hessen",
    "wof:name":"G\u00e4stehaus K.-h. Hesselbein",
    "wof:placetype":"venue"
},
  "geometry": {"coordinates":[9.0046482086,51.2102279663],"type":"Point"}
}