{
  "type": "Feature",
  "properties": {
    "iso:country":"DE",
    "sg:address":"Flurstr. 279",
    "sg:city":"Haan",
    "sg:phone":"+49 212/934084",
    "sg:postcode":"42781",
    "sg:province":"Nordrhein-Westfalen",
    "wof:name":"Taverne Waldesruhe",
    "wof:placetype":"venue"
},
  "geometry": {"coordinates":[6.9713048935,51.1960372925],"type":"Point"}
}