{
  "type": "Feature",
  "properties": {
    "iso:country":"DE",
    "sg:address":"Wolkersdorfer Berg 17",
    "sg:city":"Schwabach",
    "sg:phone":"+49 911/6370624",
    "sg:postcode":"91126",
    "sg:province":"Bayern",
    "wof:name":"J\u00fcrgen Rahmstorf Konstruktions Gmbh",
    "wof:placetype":"venue"
},
  "geometry": {"coordinates":[11.027912,49.359016],"type":"Point"}
}