{
  "type": "Feature",
  "properties": {
    "iso:country":"DE",
    "sg:address":"Benzstr. 3",
    "sg:city":"Hemmingen",
    "sg:phone":"+49 7150/2088",
    "sg:postcode":"71282",
    "sg:province":"Baden-W\u00fcrttemberg",
    "wof:name":"Fbs Flachdachbau Gmbh",
    "wof:placetype":"venue"
},
  "geometry": {"coordinates":[9.046222,48.862473],"type":"Point"}
}