{
  "type": "Feature",
  "properties": {
    "iso:country":"DE",
    "sg:address":"Burchardtstr. 23",
    "sg:city":"Aschaffenburg",
    "sg:phone":"+49 6021/413624",
    "sg:postcode":"63741",
    "sg:province":"Bayern",
    "wof:name":"Ff-textilpflege-w\u00e4scherei",
    "wof:placetype":"venue"
},
  "geometry": {"coordinates":[9.135918,49.985104],"type":"Point"}
}