{
  "type": "Feature",
  "properties": {
    "iso:country":"DE",
    "sg:address":"Gartenstr. 83",
    "sg:city":"Fellbach",
    "sg:phone":"+49 4971/1579172",
    "sg:postcode":"70734",
    "sg:province":"Baden-W\u00fcrttemberg",
    "wof:name":"Allroundmann - Hilft !",
    "wof:placetype":"venue"
},
  "geometry": {"coordinates":[9.285216,48.803612],"type":"Point"}
}