{
  "type": "Feature",
  "properties": {
    "iso:country":"DE",
    "sg:address":"Festweg 33",
    "sg:city":"Gelsenkirchen",
    "sg:phone":"+49 209/25508",
    "sg:postcode":"45886",
    "sg:province":"Nordrhein-Westfalen",
    "wof:name":"Heinrich Nowak Steuerberater",
    "wof:placetype":"venue"
},
  "geometry": {"coordinates":[7.1272449493,51.4970626831],"type":"Point"}
}