{
  "type": "Feature",
  "properties": {
    "iso:country":"DE",
    "sg:address":"Flie\u00dfauer Weg",
    "sg:city":"Zernien",
    "sg:phone":"+49 5863/1285",
    "sg:postcode":"29499",
    "sg:province":"Niedersachsen",
    "wof:name":"Ck Computergrafik Gbr",
    "wof:placetype":"venue"
},
  "geometry": {"coordinates":[10.97043,53.057045],"type":"Point"}
}