{
  "type": "Feature",
  "properties": {
    "iso:country":"DE",
    "sg:address":"Schnepfenweg 16",
    "sg:city":"Verl",
    "sg:phone":"+49 5246/92000",
    "sg:postcode":"33415",
    "sg:province":"Nordrhein-Westfalen",
    "wof:name":"Pumpenaggregate, Notstromaggregate , Stromerzeuger",
    "wof:placetype":"venue"
},
  "geometry": {"coordinates":[8.490798,51.88541],"type":"Point"}
}