{
  "type": "Feature",
  "properties": {
    "iso:country":"DE",
    "sg:address":"Dorfstr. 58",
    "sg:city":"Welsickendorf",
    "sg:phone":"+49 33746/72457",
    "sg:postcode":"14913",
    "sg:province":"Brandenburg",
    "wof:name":"Deutsches Haus",
    "wof:placetype":"venue"
},
  "geometry": {"coordinates":[13.1406030655,51.9043388367],"type":"Point"}
}