{
  "type": "Feature",
  "properties": {
    "iso:country":"DE",
    "sg:address":"Liebigstr. 6",
    "sg:city":"Langenhagen",
    "sg:phone":"+49 511/966990",
    "sg:postcode":"30851",
    "sg:province":"Niedersachsen",
    "wof:name":"Gemeinn\u00fctzige Gesellschaft F\u00fcr Behindertenarbeit Mbh",
    "wof:placetype":"venue"
},
  "geometry": {"coordinates":[9.7251605988,52.4264183044],"type":"Point"}
}