{
  "type": "Feature",
  "properties": {
    "iso:country":"DE",
    "sg:address":"Issumer Str. 3",
    "sg:city":"Geldern",
    "sg:phone":"+49 2831/6962",
    "sg:postcode":"47608",
    "sg:province":"Nordrhein-Westfalen",
    "wof:name":"Kersten Gmbh",
    "wof:placetype":"venue"
},
  "geometry": {"coordinates":[6.32689,51.519066],"type":"Point"}
}