{
  "type": "Feature",
  "properties": {
    "iso:country":"DE",
    "sg:address":"Hanns Eisler Strasse 6",
    "sg:city":"Berlin",
    "sg:phone":"+49 30/42856530",
    "sg:postcode":"10409",
    "sg:province":"Berlin",
    "wof:name":"Id-com Internet-service",
    "wof:placetype":"venue"
},
  "geometry": {"coordinates":[13.4440526962,52.5436630249],"type":"Point"}
}