{
  "type": "Feature",
  "properties": {
    "iso:country":"DE",
    "sg:address":"St. Annenstr. 1",
    "sg:city":"Jever",
    "sg:phone":"+49 4461/2221",
    "sg:postcode":"26441",
    "sg:province":"Niedersachsen",
    "wof:name":"Heinrich Wille Elektroinstallation",
    "wof:placetype":"venue"
},
  "geometry": {"coordinates":[7.899739,53.57373],"type":"Point"}
}