{
  "type": "Feature",
  "properties": {
    "iso:country":"DE",
    "sg:address":"Franz-Ludwig-Str. 6",
    "sg:city":"Bamberg",
    "sg:phone":"+49 951/203890",
    "sg:postcode":"96047",
    "sg:province":"Bayern",
    "wof:name":"H. Fuchs",
    "wof:placetype":"venue"
},
  "geometry": {"coordinates":[10.891377,49.893265],"type":"Point"}
}