{
  "type": "Feature",
  "properties": {
    "iso:country":"DE",
    "sg:address":"Kolberger Str. 2",
    "sg:city":"Blomberg",
    "sg:phone":"+49 5235/95440",
    "sg:postcode":"32825",
    "sg:province":"Nordrhein-Westfalen",
    "wof:name":"Leibenath Hohenner Und B\u00fcker Rechtsanw\u00e4lte Und Notare",
    "wof:placetype":"venue"
},
  "geometry": {"coordinates":[9.0985851288,51.9457511902],"type":"Point"}
}