{
  "type": "Feature",
  "properties": {
    "iso:country":"DE",
    "sg:address":"Am Bachberg 15",
    "sg:city":"Gammelsdorf",
    "sg:phone":"+49 8766/9124",
    "sg:postcode":"85408",
    "sg:province":"Bayern",
    "wof:name":"M. Deptalla",
    "wof:placetype":"venue"
},
  "geometry": {"coordinates":[11.9477329254,48.5519638062],"type":"Point"}
}