{
  "type": "Feature",
  "properties": {
    "iso:country":"DE",
    "sg:address":"K\u00f6lnstr. 12",
    "sg:city":"Vettwei\u00df",
    "sg:phone":"+49 2252/6238",
    "sg:postcode":"52391",
    "sg:province":"Nordrhein-Westfalen",
    "wof:name":"Dietrich Kaan",
    "wof:placetype":"venue"
},
  "geometry": {"coordinates":[6.668557,50.741055],"type":"Point"}
}