{
  "type": "Feature",
  "properties": {
    "iso:country":"DE",
    "sg:address":"Auf der Schanz 15",
    "sg:city":"Idar-Oberstein",
    "sg:phone":"+49 6784/7267",
    "sg:postcode":"55743",
    "sg:province":"Rheinland-Pfalz",
    "wof:name":"Aeroflex-west E. K.",
    "wof:placetype":"venue"
},
  "geometry": {"coordinates":[7.3963742256,49.6977882385],"type":"Point"}
}