{
  "type": "Feature",
  "properties": {
    "iso:country":"DE",
    "sg:address":"Geb\u00e4ude M 55",
    "sg:city":"R\u00fcsselsheim",
    "sg:phone":"+49 4961/428920",
    "sg:postcode":"65428",
    "sg:province":"Hessen",
    "wof:name":"Woodbridge Foam Deutschland Gmbh",
    "wof:placetype":"venue"
},
  "geometry": {"coordinates":[8.4104852676,49.9948043823],"type":"Point"}
}