{
  "type": "Feature",
  "properties": {
    "iso:country":"DE",
    "sg:address":"Clara-Zetkin-Str. 20",
    "sg:city":"Rangsdorf",
    "sg:postcode":"15834",
    "sg:province":"Brandenburg",
    "wof:name":"Pulenz Bau- Und Bautr\u00e4ger Gmbh",
    "wof:placetype":"venue"
},
  "geometry": {"coordinates":[13.427309,52.294674],"type":"Point"}
}