{
  "type": "Feature",
  "properties": {
    "iso:country":"DE",
    "sg:address":"Junkerstra\u00dfe 1",
    "sg:city":"Puchheim",
    "sg:phone":"+49 89",
    "sg:postcode":"82178",
    "sg:province":"Bayern",
    "wof:name":"Digitale Fotografie, Internationale Foto Shootings",
    "wof:placetype":"venue"
},
  "geometry": {"coordinates":[11.342328,48.161716],"type":"Point"}
}