{
  "type": "Feature",
  "properties": {
    "iso:country":"DE",
    "sg:address":"Dorfstr. 46",
    "sg:city":"Breege",
    "sg:phone":"+49 38391/12046",
    "sg:postcode":"18556",
    "sg:province":"Mecklenburg-Vorpommern",
    "wof:name":"Ferienheim Mauell Weida",
    "wof:placetype":"venue"
},
  "geometry": {"coordinates":[13.361530304,54.6142616272],"type":"Point"}
}