{
  "type": "Feature",
  "properties": {
    "iso:country":"DE",
    "sg:address":"Kobelweg 95",
    "sg:city":"Augsburg",
    "sg:phone":"+49 821/748810",
    "sg:postcode":"86156",
    "sg:province":"Bayern",
    "wof:name":"Betapharm Arzneimittel Gmbh",
    "wof:placetype":"venue"
},
  "geometry": {"coordinates":[10.847287,48.385918],"type":"Point"}
}