{
  "type": "Feature",
  "properties": {
    "iso:country":"DE",
    "sg:address":"Schlatter Str. 12",
    "sg:city":"Bad Krozingen",
    "sg:phone":"+49 7633/948094",
    "sg:postcode":"79189",
    "sg:province":"Baden-W\u00fcrttemberg",
    "wof:name":"Immobilien Walter Metzler",
    "wof:placetype":"venue"
},
  "geometry": {"coordinates":[7.6965222359,47.9165802002],"type":"Point"}
}