{
  "type": "Feature",
  "properties": {
    "iso:country":"DE",
    "sg:address":"Fischweg 1",
    "sg:city":"Chemnitz",
    "sg:phone":"+49 371/421001",
    "sg:postcode":"09114",
    "sg:province":"Sachsen",
    "wof:name":"B & R Baustoff-handel Und Recyclingges. Chemnitz Mbh",
    "wof:placetype":"venue"
},
  "geometry": {"coordinates":[12.9141302109,50.8660049438],"type":"Point"}
}