{
  "type": "Feature",
  "properties": {
    "iso:country":"DE",
    "sg:address":"Kyselh\u00e4user Str. 8",
    "sg:city":"Sangerhausen",
    "sg:postcode":"06526",
    "sg:province":"Sachsen-Anhalt",
    "wof:name":"Kreisportbund Sangerhausen E.v.",
    "wof:placetype":"venue"
},
  "geometry": {"coordinates":[11.2908287048,51.4711685181],"type":"Point"}
}