{
  "type": "Feature",
  "properties": {
    "iso:country":"DE",
    "sg:address":"M\u00fchlenstr. 82",
    "sg:city":"Br\u00fchl",
    "sg:phone":"+49 2232/46699",
    "sg:postcode":"50321",
    "sg:province":"Nordrhein-Westfalen",
    "wof:name":"Falk Bauda",
    "wof:placetype":"venue"
},
  "geometry": {"coordinates":[6.9024162292,50.8303337097],"type":"Point"}
}