{
  "type": "Feature",
  "properties": {
    "iso:country":"DE",
    "sg:address":"B\u00e4ckerstr. 11",
    "sg:city":"Uetze",
    "sg:phone":"+49 5173/98230",
    "sg:postcode":"31311",
    "sg:province":"Niedersachsen",
    "wof:name":"Gebr. Speck Elektro-u. Sanit\u00e4rinstallation",
    "wof:placetype":"venue"
},
  "geometry": {"coordinates":[10.207031,52.464584],"type":"Point"}
}