{
  "type": "Feature",
  "properties": {
    "iso:country":"DE",
    "sg:address":"Hauptstr. 9",
    "sg:city":"Wilstedt",
    "sg:postcode":"27412",
    "sg:province":"Niedersachsen",
    "wof:name":"Hund Und Katz",
    "wof:placetype":"venue"
},
  "geometry": {"coordinates":[9.087651,53.197334],"type":"Point"}
}