{
  "type": "Feature",
  "properties": {
    "iso:country":"DE",
    "sg:address":"Bayernring 30",
    "sg:city":"Berlin",
    "sg:phone":"+49 30/7864347",
    "sg:postcode":"12101",
    "sg:province":"Berlin",
    "wof:name":"Angelika Lorenz",
    "wof:placetype":"venue"
},
  "geometry": {"coordinates":[13.378027,52.483227],"type":"Point"}
}