{
  "type": "Feature",
  "properties": {
    "iso:country":"DE",
    "sg:address":"Geschwister-Scholl-Str. 41",
    "sg:city":"Eckartsberg",
    "sg:phone":"+49 3583/704071",
    "sg:postcode":"02763",
    "sg:province":"Sachsen",
    "wof:name":"Hotel Pension Restaurant Goldene H\u00f6he",
    "wof:placetype":"venue"
},
  "geometry": {"coordinates":[14.8130493164,50.9119224548],"type":"Point"}
}