{
  "type": "Feature",
  "properties": {
    "iso:country":"DE",
    "sg:address":"Furtnerh\u00f6he 1",
    "sg:city":"Simbach",
    "sg:phone":"+49 9954/247",
    "sg:postcode":"94436",
    "sg:province":"Bayern",
    "wof:name":"Rainer Buchberger",
    "wof:placetype":"venue"
},
  "geometry": {"coordinates":[12.740542,48.567444],"type":"Point"}
}