{
  "type": "Feature",
  "properties": {
    "iso:country":"DE",
    "sg:address":"Reichartstr. 23",
    "sg:city":"Erfurt",
    "sg:phone":"+49 361/2250139",
    "sg:postcode":"99094",
    "sg:province":"Th\u00fcringen",
    "wof:name":"Siegfried Schartel Ingenieur",
    "wof:placetype":"venue"
},
  "geometry": {"coordinates":[11.0180339813,50.9662971497],"type":"Point"}
}