{
  "type": "Feature",
  "properties": {
    "iso:country":"DE",
    "sg:address":"Gr\u00fcnsink 1",
    "sg:city":"Hofstetten",
    "sg:phone":"+49 8196/376",
    "sg:postcode":"86928",
    "sg:province":"Bayern",
    "wof:name":"Heinrich Hipp",
    "wof:placetype":"venue"
},
  "geometry": {"coordinates":[10.977098,47.991463],"type":"Point"}
}