{
  "type": "Feature",
  "properties": {
    "iso:country":"DE",
    "sg:address":"H\u00f6henstr. 60",
    "sg:city":"Engelsbrand",
    "sg:phone":"+49 815",
    "sg:postcode":"75331",
    "sg:province":"Baden-W\u00fcrttemberg",
    "wof:name":"Jugendfeuerwehr Engelsbrand",
    "wof:placetype":"venue"
},
  "geometry": {"coordinates":[8.653495,48.828316],"type":"Point"}
}