{
  "type": "Feature",
  "properties": {
    "iso:country":"DE",
    "sg:address":"M\u00fchlenstr. 20",
    "sg:city":"Beelitz",
    "sg:postcode":"14547",
    "sg:province":"Brandenburg",
    "wof:name":"Klaus Wardin",
    "wof:placetype":"venue"
},
  "geometry": {"coordinates":[12.974911,52.23315],"type":"Point"}
}