{
  "type": "Feature",
  "properties": {
    "iso:country":"DE",
    "sg:address":"Luruper Ch. 125 Haus 8",
    "sg:city":"Hamburg",
    "sg:phone":"+49 89/906177",
    "sg:postcode":"22761",
    "sg:province":"Hamburg",
    "wof:name":"World Freight Gmbh",
    "wof:placetype":"venue"
},
  "geometry": {"coordinates":[11.680565834,48.1447601318],"type":"Point"}
}