{
  "type": "Feature",
  "properties": {
    "iso:country":"DE",
    "sg:address":"Vogelbacher Weg 5",
    "sg:city":"Homburg",
    "sg:phone":"+49 6841/78141",
    "sg:postcode":"66424",
    "sg:province":"Saarland",
    "wof:name":"Marie-luise Wendel",
    "wof:placetype":"venue"
},
  "geometry": {"coordinates":[7.3385391235,49.3452339172],"type":"Point"}
}