{
  "type": "Feature",
  "properties": {
    "iso:country":"DE",
    "sg:address":"Fischbecker Str 18",
    "sg:city":"Hameln",
    "sg:phone":"+49 5151/24219",
    "sg:postcode":"31785",
    "sg:province":"Niedersachsen",
    "wof:name":"Molybd\u00e4n Eberhardt Kg",
    "wof:placetype":"venue"
},
  "geometry": {"coordinates":[9.3538627625,52.1107406616],"type":"Point"}
}