{
  "type": "Feature",
  "properties": {
    "iso:country":"DE",
    "sg:address":"Strontianitstr. 8",
    "sg:city":"Drensteinfurt",
    "sg:phone":"+49 2508/1077",
    "sg:postcode":"48317",
    "sg:province":"Nordrhein-Westfalen",
    "wof:name":"Dts Drensteinfurter Transport- Und Spedition Gmbh",
    "wof:placetype":"venue"
},
  "geometry": {"coordinates":[7.73106,51.785412],"type":"Point"}
}