{
  "type": "Feature",
  "properties": {
    "iso:country":"DE",
    "sg:address":"Immecker Str. 12",
    "sg:city":"Meinerzhagen",
    "sg:phone":"+49 2354/923292",
    "sg:postcode":"58540",
    "sg:province":"Nordrhein-Westfalen",
    "wof:name":"Fastenrath Verwaltungs- Gesellschaft Mbh",
    "wof:placetype":"venue"
},
  "geometry": {"coordinates":[7.6517848969,51.1056518555],"type":"Point"}
}