{
  "type": "Feature",
  "properties": {
    "iso:country":"DE",
    "sg:address":"Marienbergstr 78",
    "sg:city":"N\u00fcrnberg",
    "sg:phone":"+49 911/952190",
    "sg:postcode":"90411",
    "sg:province":"Bayern",
    "wof:name":"Cal Consult Gmbh",
    "wof:placetype":"venue"
},
  "geometry": {"coordinates":[11.095627,49.484486],"type":"Point"}
}