{
  "type": "Feature",
  "properties": {
    "iso:country":"DE",
    "sg:address":"Wentorfer Str. 14",
    "sg:city":"Hamburg",
    "sg:phone":"+49 40/7211077",
    "sg:postcode":"21029",
    "sg:province":"Hamburg",
    "wof:name":"Plansecur Systematische Verm\u00f6gensplanung",
    "wof:placetype":"venue"
},
  "geometry": {"coordinates":[10.2178735733,53.4868850708],"type":"Point"}
}