{
  "type": "Feature",
  "properties": {
    "iso:country":"DE",
    "sg:address":"Schnaitbergstr. 1",
    "sg:city":"Essingen",
    "sg:phone":"+49 7365/96250",
    "sg:postcode":"73457",
    "sg:province":"Baden-W\u00fcrttemberg",
    "wof:name":"Spedition Palm Gmbh & Co. Kg",
    "wof:placetype":"venue"
},
  "geometry": {"coordinates":[10.0278244019,48.8229255676],"type":"Point"}
}