{
  "type": "Feature",
  "properties": {
    "iso:country":"DE",
    "sg:address":"Hasenmark 21",
    "sg:city":"Berlin",
    "sg:phone":"+49 30/3333860",
    "sg:postcode":"13585",
    "sg:province":"Berlin",
    "wof:name":"Gerhard Hildebrandt Immobilienmakler",
    "wof:placetype":"venue"
},
  "geometry": {"coordinates":[13.1985931396,52.5415687561],"type":"Point"}
}