{
  "type": "Feature",
  "properties": {
    "iso:country":"DE",
    "sg:address":"Marktstr. 3",
    "sg:city":"Homburg",
    "sg:phone":"+49 6841/93300",
    "sg:postcode":"66424",
    "sg:province":"Saarland",
    "wof:name":"Marktbrunnen",
    "wof:placetype":"venue"
},
  "geometry": {"coordinates":[7.3407139778,49.3216667175],"type":"Point"}
}