{
  "type": "Feature",
  "properties": {
    "iso:country":"DE",
    "sg:address":"Euckenstr. 2",
    "sg:city":"M\u00fcnchen",
    "sg:phone":"+49 89/743590",
    "sg:postcode":"81369",
    "sg:province":"Bayern",
    "wof:name":"Foto-brunninger Hugo A. Brunninger Gmbh & Co.",
    "wof:placetype":"venue"
},
  "geometry": {"coordinates":[11.530115,48.113373],"type":"Point"}
}