{
  "type": "Feature",
  "properties": {
    "iso:country":"DE",
    "sg:address":"Weinstr. 68",
    "sg:city":"Ranschbach",
    "sg:phone":"+49 6345/7187",
    "sg:postcode":"76829",
    "sg:province":"Rheinland-Pfalz",
    "wof:name":"Weinstube M\u00fcllers Woid\u00e4chel",
    "wof:placetype":"venue"
},
  "geometry": {"coordinates":[8.0296430588,49.1964950562],"type":"Point"}
}