{
  "type": "Feature",
  "properties": {
    "iso:country":"DE",
    "sg:address":"Neuer Winkel 13",
    "sg:city":"Wunstorf",
    "sg:phone":"+49 5033/911565",
    "sg:postcode":"31515",
    "sg:province":"Niedersachsen",
    "wof:name":"Restaurant Hafenst\u00fcbchen",
    "wof:placetype":"venue"
},
  "geometry": {"coordinates":[9.352599144,52.4553642273],"type":"Point"}
}