{
  "type": "Feature",
  "properties": {
    "iso:country":"DE",
    "sg:address":"Sigiltrastr. 4",
    "sg:city":"S\u00f6gel",
    "sg:phone":"+49 5952/3618",
    "sg:postcode":"49751",
    "sg:province":"Niedersachsen",
    "wof:name":"Cafeteria Joy",
    "wof:placetype":"venue"
},
  "geometry": {"coordinates":[7.523994,52.841061],"type":"Point"}
}