{
  "type": "Feature",
  "properties": {
    "iso:country":"DE",
    "sg:address":"Auguststr. 15",
    "sg:city":"Herne",
    "sg:phone":"+49 2323/27245",
    "sg:postcode":"44629",
    "sg:province":"Nordrhein-Westfalen",
    "wof:name":"Berta Hahne",
    "wof:placetype":"venue"
},
  "geometry": {"coordinates":[7.217479229,51.5526618958],"type":"Point"}
}