{
  "type": "Feature",
  "properties": {
    "iso:country":"DE",
    "sg:address":"Kaiser-Wilhelm-Str. 11",
    "sg:city":"Beckum",
    "sg:phone":"+49 2525/2112",
    "sg:postcode":"59269",
    "sg:province":"Nordrhein-Westfalen",
    "wof:name":"Lions-club Werse-ems Dr. Bernd Sitz",
    "wof:placetype":"venue"
},
  "geometry": {"coordinates":[8.0432224274,51.7558135986],"type":"Point"}
}