{
  "type": "Feature",
  "properties": {
    "iso:country":"DE",
    "sg:address":"Motterstr. 92",
    "sg:city":"N\u00fcrnberg",
    "sg:phone":"+49 911/6491685",
    "sg:postcode":"90451",
    "sg:province":"Bayern",
    "wof:name":"Konrad Weigl Bauunternehmung Gmbh",
    "wof:placetype":"venue"
},
  "geometry": {"coordinates":[11.044133,49.4048],"type":"Point"}
}