{
  "type": "Feature",
  "properties": {
    "iso:country":"DE",
    "sg:address":"Dorfstra\u00dfe 63",
    "sg:city":"Heide",
    "sg:phone":"+49 481/86893",
    "sg:postcode":"25746",
    "sg:province":"Schleswig-Holstein",
    "wof:name":"Bauernhof Brehmer",
    "wof:placetype":"venue"
},
  "geometry": {"coordinates":[9.1153850555,54.1858482361],"type":"Point"}
}