{
  "type": "Feature",
  "properties": {
    "iso:country":"DE",
    "sg:address":"Burgfrauenstr. 21",
    "sg:city":"Berlin",
    "sg:phone":"+49 30/4011062",
    "sg:postcode":"13465",
    "sg:province":"Berlin",
    "wof:name":"Werner Krau\u00df Ingenieur",
    "wof:placetype":"venue"
},
  "geometry": {"coordinates":[13.2937631607,52.630405426],"type":"Point"}
}