{
  "type": "Feature",
  "properties": {
    "iso:country":"DE",
    "sg:address":"Weichser Weg 5",
    "sg:city":"Regensburg",
    "sg:phone":"+49 941/47715",
    "sg:postcode":"93059",
    "sg:province":"Bayern",
    "wof:name":"Rubin Gmbh",
    "wof:placetype":"venue"
},
  "geometry": {"coordinates":[12.117789,49.026596],"type":"Point"}
}