{
  "type": "Feature",
  "properties": {
    "iso:country":"DE",
    "sg:address":"Max-Stromeyer-Str. 53a",
    "sg:city":"Konstanz",
    "sg:phone":"+49 7531/59490",
    "sg:postcode":"78467",
    "sg:province":"Baden-W\u00fcrttemberg",
    "wof:name":"Quelle",
    "wof:placetype":"venue"
},
  "geometry": {"coordinates":[9.150058,47.679405],"type":"Point"}
}