{
  "type": "Feature",
  "properties": {
    "iso:country":"DE",
    "sg:address":"Falkenhagener Str. 30",
    "sg:city":"Falkensee",
    "sg:phone":"+49 3322/201080",
    "sg:postcode":"14612",
    "sg:province":"Brandenburg",
    "wof:name":"Otto Reichelt Ag",
    "wof:placetype":"venue"
},
  "geometry": {"coordinates":[13.099562645,52.5676765442],"type":"Point"}
}