{
  "type": "Feature",
  "properties": {
    "iso:country":"DE",
    "sg:address":"Rasen 33",
    "sg:city":"Geschwenda",
    "sg:phone":"+49 36205/533",
    "sg:postcode":"98716",
    "sg:province":"Th\u00fcringen",
    "wof:name":"H. Jahn",
    "wof:placetype":"venue"
},
  "geometry": {"coordinates":[10.8275337219,50.7293319702],"type":"Point"}
}