{
  "type": "Feature",
  "properties": {
    "iso:country":"DE",
    "sg:address":"Hindenburgdamm 18a",
    "sg:city":"Berlin",
    "sg:postcode":"12203",
    "sg:province":"Berlin",
    "wof:name":"Sylvia L\u00fccke Farbdesign Gmbh",
    "wof:placetype":"venue"
},
  "geometry": {"coordinates":[13.314106,52.435814],"type":"Point"}
}