{
  "type": "Feature",
  "properties": {
    "iso:country":"DE",
    "sg:address":"Lessingstr. 3",
    "sg:city":"Ilvesheim",
    "sg:phone":"+49 621/492303",
    "sg:postcode":"68549",
    "sg:province":"Baden-W\u00fcrttemberg",
    "wof:name":"Richard Bauer Reisen Gmbh",
    "wof:placetype":"venue"
},
  "geometry": {"coordinates":[8.5569286346,49.4799537659],"type":"Point"}
}