{
  "type": "Feature",
  "properties": {
    "iso:country":"DE",
    "sg:address":"Burgwallstr. 7",
    "sg:city":"Friedberg",
    "sg:phone":"+49 821/603239",
    "sg:postcode":"86316",
    "sg:province":"Bayern",
    "wof:name":"Johann Trinkl Verwaltung Von Anlage-",
    "wof:placetype":"venue"
},
  "geometry": {"coordinates":[10.9806652069,48.3579330444],"type":"Point"}
}