{
  "type": "Feature",
  "properties": {
    "iso:country":"DE",
    "sg:address":"Zur Primshalle 2",
    "sg:city":"Schmelz",
    "sg:phone":"+49 6887/3010",
    "sg:postcode":"66839",
    "sg:province":"Saarland",
    "wof:name":"Gemeindewasserwerk Schmelz",
    "wof:placetype":"venue"
},
  "geometry": {"coordinates":[6.8414540291,49.435218811],"type":"Point"}
}