{
  "type": "Feature",
  "properties": {
    "iso:country":"DE",
    "sg:address":"Saarbr\u00fccker Str. 8 A",
    "sg:city":"Schmelz",
    "sg:phone":"+49 6887/7035",
    "sg:postcode":"66839",
    "sg:province":"Saarland",
    "wof:name":"Music Center Endres",
    "wof:placetype":"venue"
},
  "geometry": {"coordinates":[6.8549528122,49.4423866272],"type":"Point"}
}