{
  "type": "Feature",
  "properties": {
    "iso:country":"DE",
    "sg:address":"Konrad-Adenauer-Str. 13",
    "sg:city":"Dachau",
    "sg:phone":"+49 8131/72042",
    "sg:postcode":"85221",
    "sg:province":"Bayern",
    "wof:name":"Kriegel Reitsport",
    "wof:placetype":"venue"
},
  "geometry": {"coordinates":[11.436144,48.260872],"type":"Point"}
}