{
  "type": "Feature",
  "properties": {
    "iso:country":"DE",
    "sg:address":"Fangdieckstr. 79::",
    "sg:city":"Hamburg",
    "sg:phone":"+49 40/84000940",
    "sg:postcode":"22547",
    "sg:province":"Hamburg",
    "wof:name":"Filmpack Gmbh Hermann Winkel",
    "wof:placetype":"venue"
},
  "geometry": {"coordinates":[9.8981389999,53.5983695984],"type":"Point"}
}