{
  "type": "Feature",
  "properties": {
    "iso:country":"DE",
    "sg:address":"Am Kanal 17",
    "sg:city":"Bremerv\u00f6rde",
    "sg:phone":"+49 4761",
    "sg:postcode":"27432",
    "sg:province":"Niedersachsen",
    "wof:name":"Der Betten-online-shop",
    "wof:placetype":"venue"
},
  "geometry": {"coordinates":[9.1367502213,53.481300354],"type":"Point"}
}