{
  "type": "Feature",
  "properties": {
    "iso:country":"DE",
    "sg:address":"Horchheimer Str. 50",
    "sg:city":"Worms",
    "sg:phone":"+49 6241/3030",
    "sg:postcode":"67547",
    "sg:province":"Rheinland-Pfalz",
    "wof:name":"Renolit Ag",
    "wof:placetype":"venue"
},
  "geometry": {"coordinates":[8.34838,49.618446],"type":"Point"}
}