{
  "type": "Feature",
  "properties": {
    "iso:country":"DE",
    "sg:address":"R\u00fcschebrinkstr. 11",
    "sg:city":"Dortmund",
    "sg:phone":"+49 231/5600042",
    "sg:postcode":"44143",
    "sg:province":"Nordrhein-Westfalen",
    "wof:name":"Calidec Gmbh",
    "wof:placetype":"venue"
},
  "geometry": {"coordinates":[7.5207691193,51.5217628479],"type":"Point"}
}