{
  "type": "Feature",
  "properties": {
    "iso:country":"DE",
    "sg:address":"Markt 8",
    "sg:city":"Adenau",
    "sg:phone":"+49 2691/930010",
    "sg:postcode":"53518",
    "sg:province":"Rheinland-Pfalz",
    "wof:name":"Hoffmann-reisen",
    "wof:placetype":"venue"
},
  "geometry": {"coordinates":[6.9293069839,50.3826675415],"type":"Point"}
}