{
  "type": "Feature",
  "properties": {
    "iso:country":"DE",
    "sg:address":"Donaustaufer Str. 48",
    "sg:city":"Regensburg",
    "sg:phone":"+49 941/402050",
    "sg:postcode":"93059",
    "sg:province":"Bayern",
    "wof:name":"Ego K\u00e4ltetechnik Gmbh & Co. Kg",
    "wof:placetype":"venue"
},
  "geometry": {"coordinates":[12.109778,49.029713],"type":"Point"}
}