{
  "type": "Feature",
  "properties": {
    "iso:country":"DE",
    "sg:address":"Am Bondenholz 13",
    "sg:city":"Barsb\u00fcttel",
    "sg:phone":"+49 40/670550",
    "sg:postcode":"22885",
    "sg:province":"Schleswig-Holstein",
    "wof:name":"Deutsche Bauh\u00fctten Gmbh",
    "wof:placetype":"venue"
},
  "geometry": {"coordinates":[10.1803445816,53.5647392273],"type":"Point"}
}