{
  "type": "Feature",
  "properties": {
    "iso:country":"DE",
    "sg:address":"Am Stadtpark 36",
    "sg:city":"Erfurt",
    "sg:phone":"+49 361/3455835",
    "sg:postcode":"99096",
    "sg:province":"Th\u00fcringen",
    "wof:name":"Dr. Seydel & Partner - Vertriebs- & Service Gmbh",
    "wof:placetype":"venue"
},
  "geometry": {"coordinates":[11.0377,50.967827],"type":"Point"}
}