{
  "type": "Feature",
  "properties": {
    "iso:country":"DE",
    "sg:address":"Am Eichert 41",
    "sg:city":"Aue",
    "sg:phone":"+49 3771/735698",
    "sg:postcode":"08280",
    "sg:province":"Sachsen",
    "wof:name":"Lutz Junghans",
    "wof:placetype":"venue"
},
  "geometry": {"coordinates":[12.6954860687,50.5737876892],"type":"Point"}
}