{
  "type": "Feature",
  "properties": {
    "iso:country":"DE",
    "sg:address":"54538",
    "sg:city":"Kinderbeuern",
    "sg:phone":"+49 6532/4682",
    "sg:postcode":"54538",
    "sg:province":"Rheinland-Pfalz",
    "wof:name":"Katholisches Pfarramt St. Servatius",
    "wof:placetype":"venue"
},
  "geometry": {"coordinates":[7.0234208107,50.0084953308],"type":"Point"}
}