{
  "type": "Feature",
  "properties": {
    "iso:country":"DE",
    "sg:address":"Theresienstr. 7",
    "sg:city":"Hof",
    "sg:phone":"+49 9281/2472",
    "sg:postcode":"95028",
    "sg:province":"Bayern",
    "wof:name":"Stumpf Verwaltungs Gmbh",
    "wof:placetype":"venue"
},
  "geometry": {"coordinates":[11.915222168,50.3119316101],"type":"Point"}
}