{
  "type": "Feature",
  "properties": {
    "iso:country":"DE",
    "sg:address":"Zur Heide 75",
    "sg:city":"K\u00f6nigswinter",
    "sg:phone":"+49 2244/1537",
    "sg:postcode":"53639",
    "sg:province":"Nordrhein-Westfalen",
    "wof:name":"G. M\u00fcller-pianka",
    "wof:placetype":"venue"
},
  "geometry": {"coordinates":[7.2198390961,50.7227210999],"type":"Point"}
}