{
  "type": "Feature",
  "properties": {
    "iso:country":"DE",
    "sg:address":"Gesundbrunnenstr. 5",
    "sg:city":"Augsburg",
    "sg:phone":"+49 821/36171",
    "sg:postcode":"86152",
    "sg:province":"Bayern",
    "wof:name":"Gehmacher Gmbh",
    "wof:placetype":"venue"
},
  "geometry": {"coordinates":[10.8874311447,48.3720207214],"type":"Point"}
}