{
  "type": "Feature",
  "properties": {
    "iso:country":"DE",
    "sg:address":"Inrather Str. 23",
    "sg:city":"Krefeld",
    "sg:phone":"+49 2151/601321",
    "sg:postcode":"47798",
    "sg:province":"Nordrhein-Westfalen",
    "wof:name":"H. Pahlings",
    "wof:placetype":"venue"
},
  "geometry": {"coordinates":[6.557844162,51.3415298462],"type":"Point"}
}