{
  "type": "Feature",
  "properties": {
    "iso:country":"DE",
    "sg:address":"Rudolst\u00e4dter Str. 90",
    "sg:city":"Jena",
    "sg:postcode":"07745",
    "sg:province":"Th\u00fcringen",
    "wof:name":"Brummi Rent Gmbh",
    "wof:placetype":"venue"
},
  "geometry": {"coordinates":[11.5890607834,50.883190155],"type":"Point"}
}