{
  "type": "Feature",
  "properties": {
    "iso:country":"DE",
    "sg:address":"Lammertsh\u00f6rn",
    "sg:city":"Esens",
    "sg:phone":"+49 4971/2010",
    "sg:postcode":"26427",
    "sg:province":"Niedersachsen",
    "wof:name":"M\u00fcttergenesungsheim Lotte Lemke",
    "wof:placetype":"venue"
},
  "geometry": {"coordinates":[7.5789699554,53.6738052368],"type":"Point"}
}