{
  "type": "Feature",
  "properties": {
    "iso:country":"DE",
    "sg:address":"Karlsbader Str. 97-99",
    "sg:city":"Schneeberg",
    "sg:postcode":"08289",
    "sg:province":"Sachsen",
    "wof:name":"Mehlhorn Gmbh",
    "wof:placetype":"venue"
},
  "geometry": {"coordinates":[12.632065773,50.5797958374],"type":"Point"}
}