{
  "type": "Feature",
  "properties": {
    "iso:country":"DE",
    "sg:address":"Laufer Str. 1",
    "sg:city":"Ottersweier",
    "sg:phone":"+49 7223/24677",
    "sg:postcode":"77833",
    "sg:province":"Baden-W\u00fcrttemberg",
    "wof:name":"Kath. Pfarramt St. Johann",
    "wof:placetype":"venue"
},
  "geometry": {"coordinates":[8.111905098,48.6676826477],"type":"Point"}
}