{
  "type": "Feature",
  "properties": {
    "iso:country":"DE",
    "sg:address":"Breite Str. 68",
    "sg:city":"Stendal",
    "sg:phone":"+49 3931/715717",
    "sg:postcode":"39576",
    "sg:province":"Sachsen-Anhalt",
    "wof:name":"Peter Bornemann",
    "wof:placetype":"venue"
},
  "geometry": {"coordinates":[11.8611125946,52.6053924561],"type":"Point"}
}