{
  "type": "Feature",
  "properties": {
    "iso:country":"DE",
    "sg:address":"Gewerbepark Fahner H\u00f6he",
    "sg:city":"Gierst\u00e4dt",
    "sg:phone":"+49 36206/23280",
    "sg:postcode":"99100",
    "sg:province":"Th\u00fcringen",
    "wof:name":"Absatzgenossenschaft Fahner Obst Eg",
    "wof:placetype":"venue"
},
  "geometry": {"coordinates":[10.822065,51.044415],"type":"Point"}
}