{
  "type": "Feature",
  "properties": {
    "iso:country":"DE",
    "sg:address":"Br\u00fchlstr. 19",
    "sg:city":"Konstanz",
    "sg:phone":"+49 7533/97060",
    "sg:postcode":"78465",
    "sg:province":"Baden-W\u00fcrttemberg",
    "wof:name":"Rombach Und Merkt Gmbh",
    "wof:placetype":"venue"
},
  "geometry": {"coordinates":[9.113808,47.730824],"type":"Point"}
}