{
  "type": "Feature",
  "properties": {
    "iso:country":"DE",
    "sg:address":"Fridtjof-Nansen-Str. 17",
    "sg:city":"Karlsruhe",
    "sg:phone":"+49 721/472723",
    "sg:postcode":"76228",
    "sg:province":"Baden-W\u00fcrttemberg",
    "wof:name":"Gerhard Irmscher Architekt",
    "wof:placetype":"venue"
},
  "geometry": {"coordinates":[8.466908,48.972885],"type":"Point"}
}