{
  "type": "Feature",
  "properties": {
    "iso:country":"DE",
    "sg:address":"Kleine Kirchenstr. 2",
    "sg:city":"Achim",
    "sg:phone":"+49 4202/2220",
    "sg:postcode":"28832",
    "sg:province":"Niedersachsen",
    "wof:name":"Dr. Hans-dieter Meislahn Tierarzt",
    "wof:placetype":"venue"
},
  "geometry": {"coordinates":[9.0310029984,53.0120544434],"type":"Point"}
}