{
  "type": "Feature",
  "properties": {
    "iso:country":"DE",
    "sg:address":"D\u00fcbener Str. 4",
    "sg:city":"L\u00f6bnitz",
    "sg:phone":"+49 34208/72150",
    "sg:postcode":"04509",
    "sg:province":"Sachsen",
    "wof:name":"Roland Schwarz",
    "wof:placetype":"venue"
},
  "geometry": {"coordinates":[12.353229,51.511105],"type":"Point"}
}