{
  "type": "Feature",
  "properties": {
    "iso:country":"DE",
    "sg:address":"Herzogstr. 6",
    "sg:city":"Blankenburg",
    "sg:phone":"+49 3944/3175",
    "sg:postcode":"38889",
    "sg:province":"Sachsen-Anhalt",
    "wof:name":"Detlef Guhl",
    "wof:placetype":"venue"
},
  "geometry": {"coordinates":[10.9599542618,51.7917098999],"type":"Point"}
}