{
  "type": "Feature",
  "properties": {
    "iso:country":"DE",
    "sg:address":"Gr\u00fcne Str. 20",
    "sg:city":"Delmenhorst",
    "sg:phone":"+49 4221/120002",
    "sg:postcode":"27749",
    "sg:province":"Niedersachsen",
    "wof:name":"City Hifi Audio- Und Videosysteme Handels Gmbh",
    "wof:placetype":"venue"
},
  "geometry": {"coordinates":[8.639585,53.047535],"type":"Point"}
}