{
  "type": "Feature",
  "properties": {
    "iso:country":"DE",
    "sg:address":"Ulmer Str. 5",
    "sg:city":"Niederstotzingen",
    "sg:phone":"+49 7325/5328",
    "sg:postcode":"89168",
    "sg:province":"Baden-W\u00fcrttemberg",
    "wof:name":"Georg Hegele",
    "wof:placetype":"venue"
},
  "geometry": {"coordinates":[10.2365159988,48.5374832153],"type":"Point"}
}