{
  "type": "Feature",
  "properties": {
    "iso:country":"DE",
    "sg:address":"Brunnenstr. 12",
    "sg:city":"Moosbach",
    "sg:phone":"+49 9656/92010",
    "sg:postcode":"92709",
    "sg:province":"Bayern",
    "wof:name":"Moosbacher Komplett-bau Gmbh & Co. Kg",
    "wof:placetype":"venue"
},
  "geometry": {"coordinates":[12.409015,49.589035],"type":"Point"}
}