{
  "type": "Feature",
  "properties": {
    "iso:country":"DE",
    "sg:address":"Hagenstr. 35",
    "sg:city":"Nottuln",
    "sg:phone":"+49 2502/8010",
    "sg:postcode":"48301",
    "sg:province":"Nordrhein-Westfalen",
    "wof:name":"Stiftung St. Gerburgis",
    "wof:placetype":"venue"
},
  "geometry": {"coordinates":[7.3543357849,51.9334602356],"type":"Point"}
}