{
  "type": "Feature",
  "properties": {
    "iso:country":"DE",
    "sg:address":"Riethornweg 32",
    "sg:city":"Burgdorf",
    "sg:phone":"+49 5136/874892",
    "sg:postcode":"31303",
    "sg:province":"Niedersachsen",
    "wof:name":"R. Gehle Finanzberater",
    "wof:placetype":"venue"
},
  "geometry": {"coordinates":[10.0318813324,52.4595870972],"type":"Point"}
}