{
  "type": "Feature",
  "properties": {
    "iso:country":"DE",
    "sg:address":"Poststr 30",
    "sg:city":"Heidenheim",
    "sg:phone":"+49 7321/35740",
    "sg:postcode":"89522",
    "sg:province":"Baden-W\u00fcrttemberg",
    "wof:name":"Piltz Pr\u00e4zisionswerkzeuge Gmbh & Co",
    "wof:placetype":"venue"
},
  "geometry": {"coordinates":[10.1603956223,48.6526679993],"type":"Point"}
}