{
  "type": "Feature",
  "properties": {
    "iso:country":"DE",
    "sg:address":"Pliezh\u00e4user Str. 6",
    "sg:city":"Reutlingen",
    "sg:phone":"+49 7121/506833",
    "sg:postcode":"72768",
    "sg:province":"Baden-W\u00fcrttemberg",
    "wof:name":"Peter Griesche",
    "wof:placetype":"venue"
},
  "geometry": {"coordinates":[9.2053461075,48.549495697],"type":"Point"}
}