{
  "type": "Feature",
  "properties": {
    "iso:country":"DE",
    "sg:address":"Walsroder Str. 2",
    "sg:city":"Fallingbostel",
    "sg:phone":"+49 5162/900080",
    "sg:postcode":"29683",
    "sg:province":"Niedersachsen",
    "wof:name":"Steuerberatungsges. Jochim Dransfeld Und Partner",
    "wof:placetype":"venue"
},
  "geometry": {"coordinates":[9.6934528351,52.8659324646],"type":"Point"}
}