{
  "type": "Feature",
  "properties": {
    "iso:country":"DE",
    "sg:address":"August-Thienemann-Str. 1",
    "sg:city":"Pl\u00f6n",
    "sg:phone":"+49 4522/8132",
    "sg:postcode":"24306",
    "sg:province":"Schleswig-Holstein",
    "wof:name":"Touristic Garni",
    "wof:placetype":"venue"
},
  "geometry": {"coordinates":[10.4329900742,54.1599731445],"type":"Point"}
}