{
  "type": "Feature",
  "properties": {
    "iso:country":"DE",
    "sg:address":"Reichsstr. 18",
    "sg:city":"Borna",
    "sg:phone":"+49 3433/204944",
    "sg:postcode":"04552",
    "sg:province":"Sachsen",
    "wof:name":"Andreas G\u00fcnther Gmbh",
    "wof:placetype":"venue"
},
  "geometry": {"coordinates":[12.4993953705,51.1237030029],"type":"Point"}
}