{
  "type": "Feature",
  "properties": {
    "iso:country":"DE",
    "sg:address":"Deichsfeld 4-6",
    "sg:city":"Bremerhaven",
    "sg:phone":"+49 471/84739",
    "sg:postcode":"27572",
    "sg:province":"Bremen",
    "wof:name":"Gudrun Schelling Heilpraktikerin",
    "wof:placetype":"venue"
},
  "geometry": {"coordinates":[8.5921926498,53.5156288147],"type":"Point"}
}