{
  "type": "Feature",
  "properties": {
    "iso:country":"DE",
    "sg:address":"Ekhofplatz 8",
    "sg:city":"Gotha",
    "sg:phone":"+49 3621/403891",
    "sg:postcode":"99867",
    "sg:province":"Th\u00fcringen",
    "wof:name":"Michael Beine",
    "wof:placetype":"venue"
},
  "geometry": {"coordinates":[10.707961,50.948807],"type":"Point"}
}