{
  "type": "Feature",
  "properties": {
    "iso:country":"DE",
    "sg:address":"Industriezubringer 19",
    "sg:city":"Cloppenburg",
    "sg:phone":"+49 4471/947277",
    "sg:postcode":"49661",
    "sg:province":"Niedersachsen",
    "wof:name":"Alfred Fette Mineral\u00f6l-grosshandel",
    "wof:placetype":"venue"
},
  "geometry": {"coordinates":[8.0801897049,52.8473968506],"type":"Point"}
}