{
  "type": "Feature",
  "properties": {
    "iso:country":"DE",
    "sg:address":"Hauptstr. 71",
    "sg:city":"Herzogenaurach",
    "sg:phone":"+49 9132/4570",
    "sg:postcode":"91074",
    "sg:province":"Bayern",
    "wof:name":"Polster Br\u00e4u Gmbh",
    "wof:placetype":"venue"
},
  "geometry": {"coordinates":[10.878292,49.570263],"type":"Point"}
}