{
  "type": "Feature",
  "properties": {
    "iso:country":"DE",
    "sg:address":"Bodelschwinghstr. 63",
    "sg:city":"Weimar",
    "sg:phone":"+49 3643/202355",
    "sg:postcode":"99425",
    "sg:province":"Th\u00fcringen",
    "wof:name":"Constantin Und Klaus G. Beyer",
    "wof:placetype":"venue"
},
  "geometry": {"coordinates":[11.3438663483,50.9754714966],"type":"Point"}
}