{
  "type": "Feature",
  "properties": {
    "iso:country":"DE",
    "sg:address":"Ernst-Frey-Str. 5",
    "sg:city":"Karlsruhe",
    "sg:postcode":"76135",
    "sg:province":"Baden-W\u00fcrttemberg",
    "wof:name":"Hinterbliebenenf\u00fcrsorge Der Deutschen Beamtenbanken Gmbh",
    "wof:placetype":"venue"
},
  "geometry": {"coordinates":[8.3777589798,48.9981880188],"type":"Point"}
}