{
  "type": "Feature",
  "properties": {
    "iso:country":"DE",
    "sg:address":"Kaltenbergstr. 42",
    "sg:city":"Eppingen",
    "sg:phone":"+49 7262/7773",
    "sg:postcode":"75031",
    "sg:province":"Baden-W\u00fcrttemberg",
    "wof:name":"Schade Umwelthygiene Gmbh",
    "wof:placetype":"venue"
},
  "geometry": {"coordinates":[8.8957080841,49.0949287415],"type":"Point"}
}