{
  "type": "Feature",
  "properties": {
    "iso:country":"DE",
    "sg:address":"Hainstr. 29",
    "sg:city":"Biedenkopf",
    "sg:phone":"+49 6461/923766",
    "sg:postcode":"35216",
    "sg:province":"Hessen",
    "wof:name":"Lifetime Jugendcaf\u00e9",
    "wof:placetype":"venue"
},
  "geometry": {"coordinates":[8.528372,50.912148],"type":"Point"}
}