{
  "type": "Feature",
  "properties": {
    "iso:country":"DE",
    "sg:address":"Konrad-Adenauer-Str. 2-4",
    "sg:city":"Remscheid",
    "sg:phone":"+49 2191/2090",
    "sg:postcode":"42853",
    "sg:province":"Nordrhein-Westfalen",
    "wof:name":"Redaktion Szene Remscheid J. F. Ziegler",
    "wof:placetype":"venue"
},
  "geometry": {"coordinates":[7.1905031204,51.1812438965],"type":"Point"}
}