{
  "type": "Feature",
  "properties": {
    "iso:country":"DE",
    "sg:address":"Ernststr. 4",
    "sg:city":"Berlin",
    "sg:phone":"+49 30/5328380",
    "sg:postcode":"12437",
    "sg:province":"Berlin",
    "wof:name":"Klaus-dieter Appl",
    "wof:placetype":"venue"
},
  "geometry": {"coordinates":[13.48853,52.466148],"type":"Point"}
}