{
  "type": "Feature",
  "properties": {
    "iso:country":"DE",
    "sg:address":"Sellerieweg 30",
    "sg:city":"N\u00fcrnberg",
    "sg:phone":"+49 911/381954",
    "sg:postcode":"90427",
    "sg:province":"Bayern",
    "wof:name":"Georg Brunner",
    "wof:placetype":"venue"
},
  "geometry": {"coordinates":[11.0343971252,49.4874916077],"type":"Point"}
}