{
  "type": "Feature",
  "properties": {
    "iso:country":"DE",
    "sg:address":"Sch\u00fctzenstr. 82",
    "sg:city":"Emsdetten",
    "sg:phone":"+49 2572/3306",
    "sg:postcode":"48282",
    "sg:province":"Nordrhein-Westfalen",
    "wof:name":"Paul Borgmann",
    "wof:placetype":"venue"
},
  "geometry": {"coordinates":[7.546413,52.169243],"type":"Point"}
}