{
  "type": "Feature",
  "properties": {
    "iso:country":"DE",
    "sg:address":"Hermann-Geisen-Str. 29",
    "sg:city":"H\u00f6hr-Grenzhausen",
    "sg:phone":"+49 2624/2551",
    "sg:postcode":"56203",
    "sg:province":"Rheinland-Pfalz",
    "wof:name":"Alfred Sauer",
    "wof:placetype":"venue"
},
  "geometry": {"coordinates":[7.655869,50.440113],"type":"Point"}
}