{
  "type": "Feature",
  "properties": {
    "iso:country":"DE",
    "sg:address":"Rudolf-Heinrich-Str. 10",
    "sg:city":"Essen",
    "sg:phone":"+49 201/679901",
    "sg:postcode":"45355",
    "sg:province":"Nordrhein-Westfalen",
    "wof:name":"Schmidt Gmbh & Co. Kg",
    "wof:placetype":"venue"
},
  "geometry": {"coordinates":[6.9525690079,51.4739151001],"type":"Point"}
}