{
  "type": "Feature",
  "properties": {
    "iso:country":"DE",
    "sg:address":"Degenfeldstra\u00dfe 4",
    "sg:city":"Karlsruhe",
    "sg:phone":"+49 721/9668016",
    "sg:postcode":"76131",
    "sg:province":"Baden-W\u00fcrttemberg",
    "wof:name":"Schumann & Sohn Gmbh",
    "wof:placetype":"venue"
},
  "geometry": {"coordinates":[8.420817,49.007801],"type":"Point"}
}