{
  "type": "Feature",
  "properties": {
    "iso:country":"DE",
    "sg:address":"Frauenberger Weg 358",
    "sg:city":"Solnhofen",
    "sg:phone":"+49 30/5499230",
    "sg:postcode":"91807",
    "sg:province":"Bayern",
    "wof:name":"Stinnes Baumarkt",
    "wof:placetype":"venue"
},
  "geometry": {"coordinates":[10.9969043732,48.8854179382],"type":"Point"}
}