{
  "type": "Feature",
  "properties": {
    "iso:country":"DE",
    "sg:address":"Marktplatz 7",
    "sg:city":"Weikersheim",
    "sg:phone":"+49 7934/692",
    "sg:postcode":"97990",
    "sg:province":"Baden-W\u00fcrttemberg",
    "wof:name":"Stadtb\u00fccherei",
    "wof:placetype":"venue"
},
  "geometry": {"coordinates":[9.897481,49.480503],"type":"Point"}
}