{
  "type": "Feature",
  "properties": {
    "iso:country":"DE",
    "sg:address":"Gewerbepark 8",
    "sg:city":"Trollenhagen",
    "sg:phone":"+49 395/429060",
    "sg:postcode":"17039",
    "sg:province":"Mecklenburg-Vorpommern",
    "wof:name":"Tdc Thermodur Constructions Gmbh",
    "wof:placetype":"venue"
},
  "geometry": {"coordinates":[13.289123,53.596684],"type":"Point"}
}