{
  "type": "Feature",
  "properties": {
    "iso:country":"DE",
    "sg:address":"Hauptstr. 15",
    "sg:city":"K\u00fcnzelsau",
    "sg:phone":"+49 7940/2337",
    "sg:postcode":"74653",
    "sg:province":"Baden-W\u00fcrttemberg",
    "wof:name":"Ochsen",
    "wof:placetype":"venue"
},
  "geometry": {"coordinates":[9.688709259,49.2781944275],"type":"Point"}
}