{
  "type": "Feature",
  "properties": {
    "iso:country":"DE",
    "sg:address":"Bahnhofstr. 77",
    "sg:city":"Dreieich",
    "sg:phone":"+49 6074/5629",
    "sg:postcode":"63303",
    "sg:province":"Hessen",
    "wof:name":"Dreieich-offenthal Campingplatz",
    "wof:placetype":"venue"
},
  "geometry": {"coordinates":[8.757133,49.985516],"type":"Point"}
}