{
  "type": "Feature",
  "properties": {
    "iso:country":"DE",
    "sg:address":"Kurzer Weg 11",
    "sg:city":"Emlichheim",
    "sg:phone":"+49 5943/98161",
    "sg:postcode":"49824",
    "sg:province":"Niedersachsen",
    "wof:name":"G. Kuipers",
    "wof:placetype":"venue"
},
  "geometry": {"coordinates":[6.8497600555,52.6167182922],"type":"Point"}
}