{
  "type": "Feature",
  "properties": {
    "iso:country":"DE",
    "sg:address":"Im Meckelesch 1",
    "sg:city":"Bissendorf",
    "sg:phone":"+49 5402/982250",
    "sg:postcode":"49143",
    "sg:province":"Niedersachsen",
    "wof:name":"Intervac Vakuumtechnik Gmbh",
    "wof:placetype":"venue"
},
  "geometry": {"coordinates":[8.184032,52.275475],"type":"Point"}
}