{
  "type": "Feature",
  "properties": {
    "iso:country":"DE",
    "sg:address":"Hessenstr. 3",
    "sg:city":"Laufach",
    "sg:postcode":"63846",
    "sg:province":"Bayern",
    "wof:name":"Eggs Gmbh",
    "wof:placetype":"venue"
},
  "geometry": {"coordinates":[9.2648563385,50.0080604553],"type":"Point"}
}