{
  "type": "Feature",
  "properties": {
    "iso:country":"DE",
    "sg:address":"Deciusstr. 43 a",
    "sg:city":"Bielefeld",
    "sg:phone":"+49 521/85859",
    "sg:postcode":"33611",
    "sg:province":"Nordrhein-Westfalen",
    "wof:name":"Jochen Kreft",
    "wof:placetype":"venue"
},
  "geometry": {"coordinates":[8.537658,52.047096],"type":"Point"}
}