{
  "type": "Feature",
  "properties": {
    "iso:country":"DE",
    "sg:address":"Thomas-Wimmer-Ring 9",
    "sg:city":"M\u00fcnchen",
    "sg:phone":"+49 172 8984184",
    "sg:postcode":"80539",
    "sg:province":"Bayern",
    "wof:name":"Rupert Kiesl Rechtsanwalt",
    "wof:placetype":"venue"
},
  "geometry": {"coordinates":[11.5833482742,48.1359672546],"type":"Point"}
}