{
  "type": "Feature",
  "properties": {
    "iso:country":"DE",
    "sg:address":"Kurgartenstr. 21",
    "sg:city":"Bad D\u00fcrkheim",
    "sg:phone":"+49 6322/989711",
    "sg:postcode":"67098",
    "sg:province":"Rheinland-Pfalz",
    "wof:name":"Harald Pankalla Rechtsanwalt",
    "wof:placetype":"venue"
},
  "geometry": {"coordinates":[8.1702013016,49.461933136],"type":"Point"}
}