{
  "type": "Feature",
  "properties": {
    "iso:country":"DE",
    "sg:address":"Wolth\u00e4user Str. 34 a",
    "sg:city":"Winsen",
    "sg:phone":"+49 5143/5547",
    "sg:postcode":"29308",
    "sg:province":"Niedersachsen",
    "wof:name":"Grundt",
    "wof:placetype":"venue"
},
  "geometry": {"coordinates":[9.9213113785,52.682636261],"type":"Point"}
}