{
  "type": "Feature",
  "properties": {
    "iso:country":"DE",
    "sg:address":"Dorfstr. 1",
    "sg:city":"Zortschau / Delitzsch",
    "sg:postcode":"04509",
    "sg:province":"Sachsen",
    "wof:name":"Ferienh\u00e4user Und Ferienwohnungen",
    "wof:placetype":"venue"
},
  "geometry": {"coordinates":[12.205895,51.465805],"type":"Point"}
}