{
  "type": "Feature",
  "properties": {
    "iso:country":"DE",
    "sg:address":"Hoppersheider Busch 34",
    "sg:city":"Bergisch Gladbach",
    "sg:phone":"+49 2202/85885",
    "sg:postcode":"51467",
    "sg:province":"Nordrhein-Westfalen",
    "wof:name":"Nittum Tennishalle",
    "wof:placetype":"venue"
},
  "geometry": {"coordinates":[7.0707688332,51.0164604187],"type":"Point"}
}