{
  "type": "Feature",
  "properties": {
    "iso:country":"DE",
    "sg:address":"Voerder Str. 28",
    "sg:city":"Ennepetal",
    "sg:phone":"+49 2333/75771",
    "sg:postcode":"58256",
    "sg:province":"Nordrhein-Westfalen",
    "wof:name":"C. Hillen",
    "wof:placetype":"venue"
},
  "geometry": {"coordinates":[7.346814,51.300159],"type":"Point"}
}