{
  "type": "Feature",
  "properties": {
    "iso:country":"DE",
    "sg:address":"Gerderather Burgstr. 15",
    "sg:city":"Erkelenz",
    "sg:phone":"+49 2432/7068",
    "sg:postcode":"41812",
    "sg:province":"Nordrhein-Westfalen",
    "wof:name":"Reiner Erdweg Gmbh",
    "wof:placetype":"venue"
},
  "geometry": {"coordinates":[6.2209100723,51.0950584412],"type":"Point"}
}