{
  "type": "Feature",
  "properties": {
    "iso:country":"DE",
    "sg:address":"Am Wei\u00dfen Berg 7b",
    "sg:city":"Kronberg",
    "sg:phone":"+49 6173/64807",
    "sg:postcode":"61476",
    "sg:province":"Hessen",
    "wof:name":"Dr. Carlo Berg",
    "wof:placetype":"venue"
},
  "geometry": {"coordinates":[8.5197353363,50.1901664734],"type":"Point"}
}