{
  "type": "Feature",
  "properties": {
    "iso:country":"DE",
    "sg:address":"B\u00fcchel 46",
    "sg:city":"Remscheid",
    "sg:postcode":"42855",
    "sg:province":"Nordrhein-Westfalen",
    "wof:name":"W & S Herkstr\u00f6ter Transport Und Logistik Gmbh",
    "wof:placetype":"venue"
},
  "geometry": {"coordinates":[7.1751198769,51.1989555359],"type":"Point"}
}