{
  "type": "Feature",
  "properties": {
    "iso:country":"DE",
    "sg:address":"Riemekestr. 76",
    "sg:city":"Paderborn",
    "sg:phone":"+49 5251/33937",
    "sg:postcode":"33102",
    "sg:province":"Nordrhein-Westfalen",
    "wof:name":"Hans Diwo",
    "wof:placetype":"venue"
},
  "geometry": {"coordinates":[8.7367200851,51.7160339355],"type":"Point"}
}