{
  "type": "Feature",
  "properties": {
    "iso:country":"DE",
    "sg:address":"Kirchrather Str. 142",
    "sg:city":"Herzogenrath",
    "sg:phone":"+49 2406/64805",
    "sg:postcode":"52134",
    "sg:province":"Nordrhein-Westfalen",
    "wof:name":"Bistro P. Ohler",
    "wof:placetype":"venue"
},
  "geometry": {"coordinates":[6.1130127907,50.8868865967],"type":"Point"}
}