{
  "type": "Feature",
  "properties": {
    "iso:country":"DE",
    "sg:address":"Elbstr. 5",
    "sg:city":"Mei\u00dfen",
    "sg:phone":"+49 3521/454025",
    "sg:postcode":"01662",
    "sg:province":"Sachsen",
    "wof:name":"Fritz G\u00fcnther",
    "wof:placetype":"venue"
},
  "geometry": {"coordinates":[13.4716062546,51.1634864807],"type":"Point"}
}