{
  "type": "Feature",
  "properties": {
    "iso:country":"DE",
    "sg:address":"Dieselstr. 10",
    "sg:city":"Meppen",
    "sg:phone":"+49 5931/80020",
    "sg:postcode":"49716",
    "sg:province":"Niedersachsen",
    "wof:name":"Lanfer - Transporte Verwaltungsgesellschaft Mbh",
    "wof:placetype":"venue"
},
  "geometry": {"coordinates":[7.2903718948,52.6643104553],"type":"Point"}
}