{
  "type": "Feature",
  "properties": {
    "iso:country":"DE",
    "sg:address":"Wirlinger Str. 5",
    "sg:city":"Buchenberg",
    "sg:phone":"+49 8378/312",
    "sg:postcode":"87474",
    "sg:province":"Bayern",
    "wof:name":"Benedikt Frey",
    "wof:placetype":"venue"
},
  "geometry": {"coordinates":[10.24126,47.695724],"type":"Point"}
}