{
  "type": "Feature",
  "properties": {
    "iso:country":"DE",
    "sg:address":"Dammstr. 7",
    "sg:city":"Nauen",
    "sg:phone":"+49 3321/455427",
    "sg:postcode":"14641",
    "sg:province":"Brandenburg",
    "wof:name":"Stadt- Und Kreisbibliothek",
    "wof:placetype":"venue"
},
  "geometry": {"coordinates":[12.879505,52.609043],"type":"Point"}
}