{
  "type": "Feature",
  "properties": {
    "iso:country":"DE",
    "sg:address":"Hannoversche Str. 21",
    "sg:city":"Staufenberg",
    "sg:phone":"+49 5543/910394",
    "sg:postcode":"34355",
    "sg:province":"Niedersachsen",
    "wof:name":"Die Gemeindejugendpflege Staufenberg",
    "wof:placetype":"venue"
},
  "geometry": {"coordinates":[9.591752,51.353546],"type":"Point"}
}