{
  "type": "Feature",
  "properties": {
    "iso:country":"DE",
    "sg:address":"Schillerstr. 1-5",
    "sg:city":"Nehren",
    "sg:phone":"+49 7473/37840",
    "sg:postcode":"72147",
    "sg:province":"Baden-W\u00fcrttemberg",
    "wof:name":"Flammer Gmbh",
    "wof:placetype":"venue"
},
  "geometry": {"coordinates":[9.065515,48.425117],"type":"Point"}
}