{
  "type": "Feature",
  "properties": {
    "iso:country":"DE",
    "sg:address":"Motzstr 9",
    "sg:city":"Berlin",
    "sg:phone":"+49 30/2150900",
    "sg:postcode":"10777",
    "sg:province":"Berlin",
    "wof:name":"Bfub Berlin Gmbh",
    "wof:placetype":"venue"
},
  "geometry": {"coordinates":[13.351142,52.498608],"type":"Point"}
}