{
  "type": "Feature",
  "properties": {
    "iso:country":"DE",
    "sg:address":"Trierer Str. 108",
    "sg:city":"Weilerswist",
    "sg:phone":"+49 2254/6355",
    "sg:postcode":"53919",
    "sg:province":"Nordrhein-Westfalen",
    "wof:name":"Avl Anh\u00e4nger-vertrieb Gmbh",
    "wof:placetype":"venue"
},
  "geometry": {"coordinates":[6.835917,50.739536],"type":"Point"}
}