{
  "type": "Feature",
  "properties": {
    "iso:country":"DE",
    "sg:address":"Niederkalbacher Str. 63",
    "sg:city":"Neuhof",
    "sg:phone":"+49 6655/1451",
    "sg:postcode":"36119",
    "sg:province":"Hessen",
    "wof:name":"Alfred Lotz E. K.",
    "wof:placetype":"venue"
},
  "geometry": {"coordinates":[9.6283302307,50.4439888],"type":"Point"}
}