{
  "type": "Feature",
  "properties": {
    "iso:country":"DE",
    "sg:address":"Hirschgraben 68",
    "sg:city":"Hamburg",
    "sg:phone":"+49 40/2513553",
    "sg:postcode":"22089",
    "sg:province":"Hamburg",
    "wof:name":"R. Rakowski Immobilienmakler",
    "wof:placetype":"venue"
},
  "geometry": {"coordinates":[10.0424537659,53.5617218018],"type":"Point"}
}