{
  "type": "Feature",
  "properties": {
    "iso:country":"DE",
    "sg:address":"Niederkasseler Lohweg 177",
    "sg:city":"D\u00fcsseldorf",
    "sg:phone":"+49 4921/152670",
    "sg:postcode":"40547",
    "sg:province":"Nordrhein-Westfalen",
    "wof:name":"Zeon Europe Gmbh",
    "wof:placetype":"venue"
},
  "geometry": {"coordinates":[6.7365717888,51.2413673401],"type":"Point"}
}