{
  "type": "Feature",
  "properties": {
    "iso:country":"DE",
    "sg:address":"Sigismundstr. 14",
    "sg:city":"Hirschaid",
    "sg:phone":"+49 9543/3374",
    "sg:postcode":"96114",
    "sg:province":"Bayern",
    "wof:name":"Karl Sp\u00f6rlein",
    "wof:placetype":"venue"
},
  "geometry": {"coordinates":[10.9843454361,49.8210601807],"type":"Point"}
}