{
  "type": "Feature",
  "properties": {
    "iso:country":"DE",
    "sg:address":"Salinenstr. 21",
    "sg:city":"Bad D\u00fcrkheim",
    "sg:phone":"+49 6322/66810",
    "sg:postcode":"67098",
    "sg:province":"Rheinland-Pfalz",
    "wof:name":"Parkcafe Traubenkur",
    "wof:placetype":"venue"
},
  "geometry": {"coordinates":[8.176502,49.464771],"type":"Point"}
}