{
  "type": "Feature",
  "properties": {
    "iso:country":"DE",
    "sg:city":"M\u00fcnchen",
    "sg:postcode":"81377",
    "sg:province":"Bayern",
    "wof:name":"Immoexpress",
    "wof:placetype":"venue"
},
  "geometry": {"coordinates":[11.50962,48.113762],"type":"Point"}
}