{
  "type": "Feature",
  "properties": {
    "iso:country":"DE",
    "sg:address":"Lindenstr. 23",
    "sg:city":"Prettin",
    "sg:phone":"+49 35386/22450",
    "sg:postcode":"06922",
    "sg:province":"Sachsen-Anhalt",
    "wof:name":"M. Steinecke",
    "wof:placetype":"venue"
},
  "geometry": {"coordinates":[12.92591,51.662281],"type":"Point"}
}