{
  "type": "Feature",
  "properties": {
    "iso:country":"DE",
    "sg:address":"Hauptstr. 25",
    "sg:city":"Gerlingen",
    "sg:phone":"+49 4971/5622076",
    "sg:postcode":"70839",
    "sg:province":"Baden-W\u00fcrttemberg",
    "wof:name":"Deutsche Bank Ag",
    "wof:placetype":"venue"
},
  "geometry": {"coordinates":[9.06218,48.799328],"type":"Point"}
}