{
  "type": "Feature",
  "properties": {
    "iso:country":"DE",
    "sg:address":"Hopfenstr. 2e",
    "sg:city":"Kiel",
    "sg:phone":"+49 431/96747",
    "sg:postcode":"24114",
    "sg:province":"Schleswig-Holstein",
    "wof:name":"Graf Dr. Kerssenbrock Und Wolfgang Kubicki",
    "wof:placetype":"venue"
},
  "geometry": {"coordinates":[10.127705574,54.3139076233],"type":"Point"}
}