{
  "type": "Feature",
  "properties": {
    "iso:country":"DE",
    "sg:address":"Maximilianstr. 3",
    "sg:city":"Ansbach",
    "sg:phone":"+49 981/977265",
    "sg:postcode":"91522",
    "sg:province":"Bayern",
    "wof:name":"Rundum Wohnbau Immobilien Gmbh",
    "wof:placetype":"venue"
},
  "geometry": {"coordinates":[10.571918,49.300182],"type":"Point"}
}