{
  "type": "Feature",
  "properties": {
    "iso:country":"DE",
    "sg:address":"Prinzenstr. 6",
    "sg:city":"G\u00f6ttingen",
    "sg:phone":"+49 551/57856",
    "sg:postcode":"37073",
    "sg:province":"Niedersachsen",
    "wof:name":"Dagmar Gloth",
    "wof:placetype":"venue"
},
  "geometry": {"coordinates":[9.93457,51.534412],"type":"Point"}
}