{
  "type": "Feature",
  "properties": {
    "iso:country":"DE",
    "sg:address":"Backsheide 18",
    "sg:city":"Steinhagen",
    "sg:phone":"+49 5204/88313",
    "sg:postcode":"33803",
    "sg:province":"Nordrhein-Westfalen",
    "wof:name":"Putenbr\u00fcterei Brockhagen Gmbh",
    "wof:placetype":"venue"
},
  "geometry": {"coordinates":[8.3606786728,52.0034103394],"type":"Point"}
}