{
  "type": "Feature",
  "properties": {
    "iso:country":"DE",
    "sg:address":"Mainzer Str. 5",
    "sg:city":"B\u00fcttelborn",
    "sg:phone":"+49 6152/58660",
    "sg:postcode":"64572",
    "sg:province":"Hessen",
    "wof:name":"Wilma Nau",
    "wof:placetype":"venue"
},
  "geometry": {"coordinates":[8.51429,49.901993],"type":"Point"}
}