{
  "type": "Feature",
  "properties": {
    "iso:country":"DE",
    "sg:address":"Alte Landstr. 115",
    "sg:city":"Hamburg",
    "sg:phone":"+49 40/53891111",
    "sg:postcode":"22339",
    "sg:province":"Hamburg",
    "wof:name":"Transatlantic Shipping Und Trading Gmbh",
    "wof:placetype":"venue"
},
  "geometry": {"coordinates":[10.0540714264,53.6401138306],"type":"Point"}
}