{
  "type": "Feature",
  "properties": {
    "iso:country":"DE",
    "sg:address":"Ginsterweg 42",
    "sg:city":"Altenholz",
    "sg:phone":"+49 431/323837",
    "sg:postcode":"24161",
    "sg:province":"Schleswig-Holstein",
    "wof:name":"Udo Handke Rechtsanwalt",
    "wof:placetype":"venue"
},
  "geometry": {"coordinates":[10.1245508194,54.4051971436],"type":"Point"}
}