{
  "type": "Feature",
  "properties": {
    "iso:country":"DE",
    "sg:address":"Frohnh\u00e4user Str. 82",
    "sg:city":"Lampertheim",
    "sg:phone":"+49 6206/2626",
    "sg:postcode":"68623",
    "sg:province":"Hessen",
    "wof:name":"H. Veltmann Steinmetzbetrieb",
    "wof:placetype":"venue"
},
  "geometry": {"coordinates":[8.4568595886,49.6006507874],"type":"Point"}
}