{
  "type": "Feature",
  "properties": {
    "iso:country":"DE",
    "sg:address":"Richard-Wagner-Platz 5",
    "sg:city":"Berlin",
    "sg:phone":"+49 30/3426502",
    "sg:postcode":"10585",
    "sg:province":"Berlin",
    "wof:name":"Fix Sportstudios Inh. Hirsch Und Sch\u00f6ndaube",
    "wof:placetype":"venue"
},
  "geometry": {"coordinates":[13.3057355881,52.5172805786],"type":"Point"}
}