{
  "type": "Feature",
  "properties": {
    "iso:country":"DE",
    "sg:address":"Stift-Keppel-Weg 15",
    "sg:city":"Hilchenbach",
    "sg:phone":"+49 2733/3585",
    "sg:postcode":"57271",
    "sg:province":"Nordrhein-Westfalen",
    "wof:name":"Keglerklause Allenbach",
    "wof:placetype":"venue"
},
  "geometry": {"coordinates":[8.090845108,50.9778518677],"type":"Point"}
}