{
  "type": "Feature",
  "properties": {
    "iso:country":"DE",
    "sg:address":"Wolfenb\u00fctteler Str. 18",
    "sg:city":"Braunschweig",
    "sg:phone":"+49 531/7996988",
    "sg:postcode":"38102",
    "sg:province":"Niedersachsen",
    "wof:name":"Skd Systemhaus F\u00fcr Kommuni- Kation Und Datentechnik Gmbh",
    "wof:placetype":"venue"
},
  "geometry": {"coordinates":[10.5293369293,52.2520904541],"type":"Point"}
}