{
  "type": "Feature",
  "properties": {
    "iso:country":"DE",
    "sg:address":"Hauptstr. 11",
    "sg:city":"Unterschweinbach",
    "sg:phone":"+49 8145/809741",
    "sg:postcode":"82282",
    "wof:name":"Albert Faltermeier",
    "wof:placetype":"venue"
},
  "geometry": {"coordinates":[11.1816663742,48.2506370544],"type":"Point"}
}