{
  "type": "Feature",
  "properties": {
    "iso:country":"DE",
    "sg:address":"Pfarrer-Bayer-Str. 6",
    "sg:city":"Gro\u00dfheubach",
    "sg:phone":"+49 9371/7427",
    "sg:postcode":"63920",
    "sg:province":"Bayern",
    "wof:name":"E. St\u00f6\u00dfenreuther",
    "wof:placetype":"venue"
},
  "geometry": {"coordinates":[9.2227869034,49.7299880981],"type":"Point"}
}