{
  "type": "Feature",
  "properties": {
    "iso:country":"DE",
    "sg:address":"Herzogstr. 1b",
    "sg:city":"M\u00fcnchen",
    "sg:phone":"+49 89/398023",
    "sg:postcode":"80803",
    "sg:province":"Bayern",
    "wof:name":"Heinz Schnaubelt Ingenieur",
    "wof:placetype":"venue"
},
  "geometry": {"coordinates":[11.5850439072,48.1619186401],"type":"Point"}
}