{
  "type": "Feature",
  "properties": {
    "iso:country":"DE",
    "sg:address":"Graf-Vollrath-Weg 6",
    "sg:city":"Frankfurt",
    "sg:phone":"+49 69/789790",
    "sg:postcode":"60489",
    "sg:province":"Hessen",
    "wof:name":"Radio Tele Ffh Gmbh",
    "wof:placetype":"venue"
},
  "geometry": {"coordinates":[8.5950307846,50.1285896301],"type":"Point"}
}