{
  "type": "Feature",
  "properties": {
    "iso:country":"DE",
    "sg:address":"Raueneggstr. 1",
    "sg:city":"Ravensburg",
    "sg:phone":"+49 751/14091",
    "sg:postcode":"88212",
    "sg:province":"Baden-W\u00fcrttemberg",
    "wof:name":"Dieter R\u00e4dle Architekt",
    "wof:placetype":"venue"
},
  "geometry": {"coordinates":[9.618977,47.781139],"type":"Point"}
}