{
  "type": "Feature",
  "properties": {
    "iso:country":"DE",
    "sg:address":"Poststr. 1",
    "sg:city":"Lastrup",
    "sg:phone":"+49 4477/385",
    "sg:postcode":"49688",
    "sg:province":"Niedersachsen",
    "wof:name":"Hubert T\u00f6nnies",
    "wof:placetype":"venue"
},
  "geometry": {"coordinates":[7.8627901077,52.7962608337],"type":"Point"}
}