{
  "type": "Feature",
  "properties": {
    "iso:country":"DE",
    "sg:address":"Hamborner Str 51",
    "sg:city":"D\u00fcsseldorf",
    "sg:phone":"+49 211/862820",
    "sg:postcode":"40472",
    "sg:province":"Nordrhein-Westfalen",
    "wof:name":"Executrack Software Gmbh",
    "wof:placetype":"venue"
},
  "geometry": {"coordinates":[6.7898287773,51.2767219543],"type":"Point"}
}