{
  "type": "Feature",
  "properties": {
    "iso:country":"DE",
    "sg:address":"Bergstr. 9",
    "sg:city":"Kaufbeuren",
    "sg:phone":"+49 8341/41254",
    "sg:postcode":"87600",
    "sg:province":"Bayern",
    "wof:name":"Sas Sicherheits Und Alarm Service Gmbh",
    "wof:placetype":"venue"
},
  "geometry": {"coordinates":[10.6152820587,47.8831481934],"type":"Point"}
}