{
  "type": "Feature",
  "properties": {
    "iso:country":"DE",
    "sg:address":"Asternweg 22",
    "sg:city":"Stade",
    "sg:postcode":"21682",
    "sg:province":"Niedersachsen",
    "wof:name":"Info-software Ugur G\u00fcrisik",
    "wof:placetype":"venue"
},
  "geometry": {"coordinates":[9.4687643051,53.6124267578],"type":"Point"}
}