{
  "type": "Feature",
  "properties": {
    "iso:country":"DE",
    "sg:address":"Flughafen",
    "sg:city":"Hamburg",
    "sg:phone":"+49 40/590454",
    "sg:postcode":"22335",
    "sg:province":"Hamburg",
    "wof:name":"Aero Lloyd Flugreisen Gmbh & Co.",
    "wof:placetype":"venue"
},
  "geometry": {"coordinates":[10.0104694366,53.6390419006],"type":"Point"}
}