{
  "type": "Feature",
  "properties": {
    "iso:country":"DE",
    "sg:address":"Bergstr. 35",
    "sg:city":"L\u00fcchow",
    "sg:phone":"+49 5841/97590",
    "sg:postcode":"29439",
    "sg:province":"Niedersachsen",
    "wof:name":"F. Hettig Ohg",
    "wof:placetype":"venue"
},
  "geometry": {"coordinates":[11.160489,52.96751],"type":"Point"}
}