{
  "type": "Feature",
  "properties": {
    "iso:country":"DE",
    "sg:address":"Rathausplatz 7",
    "sg:city":"Hemmingen",
    "sg:phone":"+49 511/415214",
    "sg:postcode":"30966",
    "sg:province":"Niedersachsen",
    "wof:name":"Klaus Willig",
    "wof:placetype":"venue"
},
  "geometry": {"coordinates":[9.7266607285,52.3264808655],"type":"Point"}
}