{
  "type": "Feature",
  "properties": {
    "iso:country":"DE",
    "sg:address":"Bahnhofstr.",
    "sg:city":"Gimbsheim",
    "sg:phone":"+49 6249/4532",
    "sg:postcode":"67578",
    "sg:province":"Rheinland-Pfalz",
    "wof:name":"Friedrich R. Muth",
    "wof:placetype":"venue"
},
  "geometry": {"coordinates":[8.381586,49.780952],"type":"Point"}
}