{
  "type": "Feature",
  "properties": {
    "iso:country":"DE",
    "sg:address":"Ellerweg 9",
    "sg:city":"Albrechts",
    "sg:phone":"+49 3681/304234",
    "sg:postcode":"98529",
    "sg:province":"Th\u00fcringen",
    "wof:name":"Peter Koch",
    "wof:placetype":"venue"
},
  "geometry": {"coordinates":[10.6419630051,50.6207504272],"type":"Point"}
}