{
  "type": "Feature",
  "properties": {
    "iso:country":"DE",
    "sg:address":"Sittelsdorf 24",
    "sg:city":"Herrngiersdorf",
    "sg:phone":"+49 8785/96010",
    "sg:postcode":"84097",
    "sg:province":"Bayern",
    "wof:name":"Ropa Fahrzeug- Und Maschinenbau Gmbh",
    "wof:placetype":"venue"
},
  "geometry": {"coordinates":[12.066627,48.774033],"type":"Point"}
}