{
  "type": "Feature",
  "properties": {
    "iso:country":"DE",
    "sg:address":"Rosenstr. 57",
    "sg:city":"Bad Bramstedt",
    "sg:phone":"+49 4192/4717",
    "sg:postcode":"24576",
    "sg:province":"Schleswig-Holstein",
    "wof:name":"H. Gr\u00e4fe",
    "wof:placetype":"venue"
},
  "geometry": {"coordinates":[9.8843412399,53.9221458435],"type":"Point"}
}