{
  "type": "Feature",
  "properties": {
    "iso:country":"DE",
    "sg:address":"Berliner Platz 10",
    "sg:city":"Eutin",
    "sg:phone":"+49 4521/3323",
    "sg:postcode":"23701",
    "sg:province":"Schleswig-Holstein",
    "wof:name":"Restaurant Rigoletto Inh. Cyrus Yazdani",
    "wof:placetype":"venue"
},
  "geometry": {"coordinates":[10.6162853241,54.1341018677],"type":"Point"}
}