{
  "type": "Feature",
  "properties": {
    "iso:country":"DE",
    "sg:address":"Tettenbusch 8",
    "sg:city":"Pr\u00fcm",
    "sg:phone":"+49 6551/3088",
    "sg:postcode":"54595",
    "sg:province":"Rheinland-Pfalz",
    "wof:name":"Redaktion Der Privatwald Verlag Waldbauverein Pr\u00fcm",
    "wof:placetype":"venue"
},
  "geometry": {"coordinates":[6.4294281006,50.214515686],"type":"Point"}
}