{
  "type": "Feature",
  "properties": {
    "iso:country":"DE",
    "sg:address":"Ambazac Str. 4",
    "sg:city":"Eckental",
    "sg:phone":"+49 9126/261150",
    "sg:postcode":"90542",
    "sg:province":"Bayern",
    "wof:name":"E Competence Center Medien Agentur Und",
    "wof:placetype":"venue"
},
  "geometry": {"coordinates":[11.2058677673,49.5770988464],"type":"Point"}
}