{
  "type": "Feature",
  "properties": {
    "iso:country":"DE",
    "sg:address":"Wissmannstr. 22",
    "sg:city":"D\u00fcsseldorf",
    "sg:phone":"+49 211/300930",
    "sg:postcode":"40219",
    "sg:province":"Nordrhein-Westfalen",
    "wof:name":"Vdk Versicherung Der Kraftfahrt Ag",
    "wof:placetype":"venue"
},
  "geometry": {"coordinates":[6.7685241699,51.2116241455],"type":"Point"}
}