{
  "type": "Feature",
  "properties": {
    "iso:country":"DE",
    "sg:address":"Bernsdorfer Str. 146",
    "sg:city":"Chemnitz",
    "sg:phone":"+49 371/586954",
    "sg:postcode":"09126",
    "sg:province":"Sachsen",
    "wof:name":"Chemnitzer Blumenring Einzelhandels Gmbh",
    "wof:placetype":"venue"
},
  "geometry": {"coordinates":[12.94155,50.808819],"type":"Point"}
}