{
  "type": "Feature",
  "properties": {
    "iso:country":"DE",
    "sg:address":"Boysenstr. 1",
    "sg:city":"Westerland",
    "sg:postcode":"25980",
    "sg:province":"Schleswig-Holstein",
    "wof:name":"Axitel-sylt Gmbh",
    "wof:placetype":"venue"
},
  "geometry": {"coordinates":[8.3045692444,54.9075737],"type":"Point"}
}