{
  "type": "Feature",
  "properties": {
    "iso:country":"DE",
    "sg:address":"Dummersdorfer Str. 20",
    "sg:city":"L\u00fcbeck",
    "sg:phone":"+49 451/301180",
    "sg:postcode":"23569",
    "sg:province":"Schleswig-Holstein",
    "wof:name":"Siedlerst\u00fcbchen",
    "wof:placetype":"venue"
},
  "geometry": {"coordinates":[10.8111715317,53.9127922058],"type":"Point"}
}