{
  "type": "Feature",
  "properties": {
    "iso:country":"DE",
    "sg:address":"Hauptstr. 12",
    "sg:city":"Bargstall",
    "sg:phone":"+49 4335/93433",
    "sg:postcode":"24806",
    "sg:province":"Schleswig-Holstein",
    "wof:name":"Gerd Derner",
    "wof:placetype":"venue"
},
  "geometry": {"coordinates":[9.464776,54.262089],"type":"Point"}
}