{
  "type": "Feature",
  "properties": {
    "iso:country":"DE",
    "sg:address":"Birkholzer Str. 5",
    "sg:city":"Cobbel",
    "sg:phone":"+49 3935/29823",
    "sg:postcode":"39517",
    "sg:province":"Sachsen-Anhalt",
    "wof:name":"Warnke Agrar Gmbh",
    "wof:placetype":"venue"
},
  "geometry": {"coordinates":[11.85498,52.395859],"type":"Point"}
}