{
  "type": "Feature",
  "properties": {
    "iso:country":"DE",
    "sg:address":"St\u00fcrzelberger Str. 59",
    "sg:city":"Dormagen",
    "sg:postcode":"41541",
    "sg:province":"Nordrhein-Westfalen",
    "wof:name":"R + L Akustik Und Trockenbau Gmbh",
    "wof:placetype":"venue"
},
  "geometry": {"coordinates":[6.837048,51.127037],"type":"Point"}
}