{
  "type": "Feature",
  "properties": {
    "iso:country":"DE",
    "sg:address":"Goldener Steig 12",
    "sg:city":"Salzweg",
    "sg:phone":"+49 851/44786",
    "sg:postcode":"94121",
    "sg:province":"Bayern",
    "wof:name":"Hermann Schweizer Steuerberater",
    "wof:placetype":"venue"
},
  "geometry": {"coordinates":[13.4898262024,48.6175842285],"type":"Point"}
}