{
  "type": "Feature",
  "properties": {
    "iso:country":"DE",
    "sg:address":"D\u00fcrener Str. 88",
    "sg:city":"K\u00f6ln",
    "sg:phone":"+49 221/405674",
    "sg:postcode":"50931",
    "sg:province":"Nordrhein-Westfalen",
    "wof:name":"Peter Meenz",
    "wof:placetype":"venue"
},
  "geometry": {"coordinates":[6.921037,50.93219],"type":"Point"}
}