{
  "type": "Feature",
  "properties": {
    "iso:country":"DE",
    "sg:address":"Heimgartenstr. 13",
    "sg:city":"Graben",
    "sg:phone":"+49 8232/6743",
    "sg:postcode":"86836",
    "sg:province":"Bayern",
    "wof:name":"Fliesentechnik & Design Walter Uenzen",
    "wof:placetype":"venue"
},
  "geometry": {"coordinates":[10.8072843552,48.16173172],"type":"Point"}
}