{
  "type": "Feature",
  "properties": {
    "iso:country":"DE",
    "sg:address":"Im Tal 50",
    "sg:city":"Hellenthal",
    "sg:phone":"+49 2482/2184",
    "sg:postcode":"53940",
    "sg:province":"Nordrhein-Westfalen",
    "wof:name":"Murk Reisen Gmbh",
    "wof:placetype":"venue"
},
  "geometry": {"coordinates":[6.4726839066,50.4747009277],"type":"Point"}
}