{
  "type": "Feature",
  "properties": {
    "iso:country":"DE",
    "sg:address":"Neue Industriestr. 4",
    "sg:city":"Reichartshausen",
    "sg:phone":"+49 6262/92160",
    "sg:postcode":"74934",
    "sg:province":"Baden-W\u00fcrttemberg",
    "wof:name":"Hs Grundst\u00fccksgesellschaft Objekt Paunsdorf Mbh",
    "wof:placetype":"venue"
},
  "geometry": {"coordinates":[8.9501886368,49.3526573181],"type":"Point"}
}