{
  "type": "Feature",
  "properties": {
    "iso:country":"DE",
    "sg:address":"Neu Stahnsdorf 7",
    "sg:city":"Alt Stahnsdorf",
    "sg:phone":"+49 33678/62853",
    "sg:postcode":"15859",
    "sg:province":"Brandenburg",
    "wof:name":"Gudrun Janke",
    "wof:placetype":"venue"
},
  "geometry": {"coordinates":[13.8895025253,52.3054504395],"type":"Point"}
}