{
  "type": "Feature",
  "properties": {
    "iso:country":"DE",
    "sg:address":"Neustadter Hauptstr. 76",
    "sg:city":"Waiblingen",
    "sg:phone":"+49 7151/81309",
    "sg:postcode":"71336",
    "sg:province":"Baden-W\u00fcrttemberg",
    "wof:name":"Weinhandlung Schluckspecht Gmbh",
    "wof:placetype":"venue"
},
  "geometry": {"coordinates":[9.3218889236,48.8477630615],"type":"Point"}
}