{
  "type": "Feature",
  "properties": {
    "iso:country":"DE",
    "sg:address":"General von Nagel Str. 6",
    "sg:city":"Freising",
    "sg:phone":"+49 8161/48560",
    "sg:postcode":"85354",
    "sg:province":"Bayern",
    "wof:name":"Reisemarkt Gmbh",
    "wof:placetype":"venue"
},
  "geometry": {"coordinates":[11.748669,48.401741],"type":"Point"}
}