{
  "type": "Feature",
  "properties": {
    "iso:country":"DE",
    "sg:address":"Max-D\u00fcnnebier-Str. 17 b",
    "sg:city":"Neuwied",
    "sg:phone":"+49 2631/71708",
    "sg:postcode":"56567",
    "sg:province":"Rheinland-Pfalz",
    "wof:name":"Bedachungsgesch\u00e4ft Rainer Will Gmbh",
    "wof:placetype":"venue"
},
  "geometry": {"coordinates":[7.409511,50.450462],"type":"Point"}
}