{
  "type": "Feature",
  "properties": {
    "iso:country":"DE",
    "sg:address":"Pfeuferstr. 38",
    "sg:city":"M\u00fcnchen",
    "sg:phone":"+49 89/771004",
    "sg:postcode":"81373",
    "sg:province":"Bayern",
    "wof:name":"Hubert Wendler Garten- Und",
    "wof:placetype":"venue"
},
  "geometry": {"coordinates":[11.541069,48.12249],"type":"Point"}
}