{
  "type": "Feature",
  "properties": {
    "iso:country":"DE",
    "sg:address":"Mittelstr. 64",
    "sg:city":"Gevelsberg",
    "sg:phone":"+49 2332/3504",
    "sg:postcode":"58285",
    "sg:province":"Nordrhein-Westfalen",
    "wof:name":"Wolfgang Kurz",
    "wof:placetype":"venue"
},
  "geometry": {"coordinates":[7.335477829,51.3185653687],"type":"Point"}
}