{
  "type": "Feature",
  "properties": {
    "iso:country":"DE",
    "sg:address":"Kirchstr. 6",
    "sg:city":"Du\u00dflingen",
    "sg:phone":"+49 7072/5718",
    "sg:postcode":"72144",
    "sg:province":"Baden-W\u00fcrttemberg",
    "wof:name":"Konrad Vollmer",
    "wof:placetype":"venue"
},
  "geometry": {"coordinates":[9.053791,48.452808],"type":"Point"}
}