{
  "type": "Feature",
  "properties": {
    "iso:country":"DE",
    "sg:address":"Stuttgartstr. 15",
    "sg:city":"Dortmund",
    "sg:phone":"+49 231/571334",
    "sg:postcode":"44143",
    "sg:province":"Nordrhein-Westfalen",
    "wof:name":"Harry G. Wagner Inh. Herbert Seidel",
    "wof:placetype":"venue"
},
  "geometry": {"coordinates":[7.5070328712,51.5174751282],"type":"Point"}
}