{
  "type": "Feature",
  "properties": {
    "iso:country":"DE",
    "sg:address":"Scheinerstr. 5 a",
    "sg:city":"M\u00fcnchen",
    "sg:phone":"+49 89/9301033",
    "sg:postcode":"81679",
    "sg:province":"Bayern",
    "wof:name":"P-age Die Presseagentur Gmbh",
    "wof:placetype":"venue"
},
  "geometry": {"coordinates":[11.6077136993,48.146900177],"type":"Point"}
}