{
  "type": "Feature",
  "properties": {
    "iso:country":"DE",
    "sg:address":"Gleiwitzer Str. 17",
    "sg:city":"Langenhagen",
    "sg:phone":"+49 511/789530",
    "sg:postcode":"30855",
    "sg:province":"Niedersachsen",
    "wof:name":"Werner Kroschk",
    "wof:placetype":"venue"
},
  "geometry": {"coordinates":[9.684685,52.432602],"type":"Point"}
}