{
  "type": "Feature",
  "properties": {
    "iso:country":"DE",
    "sg:address":"Berliner Platz 1 B",
    "sg:city":"Braunschweig",
    "sg:phone":"+49 531/2703406",
    "sg:postcode":"38102",
    "sg:province":"Niedersachsen",
    "wof:name":"Baranowski Gmbh",
    "wof:placetype":"venue"
},
  "geometry": {"coordinates":[10.538275,52.251961],"type":"Point"}
}