{
  "type": "Feature",
  "properties": {
    "iso:country":"DE",
    "sg:address":"Helene-Roth-Str. 7",
    "sg:city":"Engen",
    "sg:phone":"+49 7733/6950",
    "sg:postcode":"78234",
    "sg:province":"Baden-W\u00fcrttemberg",
    "wof:name":"Hans-peter Heiss Steuerberater",
    "wof:placetype":"venue"
},
  "geometry": {"coordinates":[8.7864427567,47.8583602905],"type":"Point"}
}