{
  "type": "Feature",
  "properties": {
    "iso:country":"DE",
    "sg:address":"Gorch-Fock-Str. 5",
    "sg:city":"Bremerhaven",
    "sg:phone":"+49 471/56562",
    "sg:postcode":"27576",
    "sg:province":"Bremen",
    "wof:name":"H. Klopp Fischerei",
    "wof:placetype":"venue"
},
  "geometry": {"coordinates":[8.5849838257,53.5559272766],"type":"Point"}
}