{
  "type": "Feature",
  "properties": {
    "iso:country":"DE",
    "sg:address":"Westlicher Stadtgraben 46 a",
    "sg:city":"Deggendorf",
    "sg:phone":"+49 991/3830156",
    "sg:postcode":"94469",
    "sg:province":"Bayern",
    "wof:name":"Charlys Pilspub",
    "wof:placetype":"venue"
},
  "geometry": {"coordinates":[12.960975647,48.8311538696],"type":"Point"}
}