{
  "type": "Feature",
  "properties": {
    "iso:country":"DE",
    "sg:address":"Am Hackenbruch 79",
    "sg:city":"D\u00fcsseldorf",
    "sg:phone":"+49 211/214306",
    "sg:postcode":"40231",
    "sg:province":"Nordrhein-Westfalen",
    "wof:name":"Josef Schwaiger",
    "wof:placetype":"venue"
},
  "geometry": {"coordinates":[6.8379788399,51.2069015503],"type":"Point"}
}