{
  "type": "Feature",
  "properties": {
    "iso:country":"DE",
    "sg:address":"Gro\u00dfe Ulrichstr. 38",
    "sg:city":"Halle",
    "sg:postcode":"06108",
    "sg:province":"Sachsen-Anhalt",
    "wof:name":"K\u00f6ster",
    "wof:placetype":"venue"
},
  "geometry": {"coordinates":[11.9672393799,51.4866714478],"type":"Point"}
}