{
  "type": "Feature",
  "properties": {
    "iso:country":"DE",
    "sg:address":"Mittelstr. 95",
    "sg:city":"Schermbeck",
    "sg:phone":"+49 2853/4166",
    "sg:postcode":"46514",
    "sg:province":"Nordrhein-Westfalen",
    "wof:name":"Achim Becker",
    "wof:placetype":"venue"
},
  "geometry": {"coordinates":[6.8760089874,51.6949424744],"type":"Point"}
}