{
  "type": "Feature",
  "properties": {
    "iso:country":"DE",
    "sg:city":"Dresden",
    "sg:postcode":"01239",
    "sg:province":"Sachsen",
    "wof:name":"Hamann Consult",
    "wof:placetype":"venue"
},
  "geometry": {"coordinates":[13.793671,51.00172],"type":"Point"}
}