{
  "type": "Feature",
  "properties": {
    "iso:country":"DE",
    "sg:address":"Finkenweg 26",
    "sg:city":"Laichingen",
    "sg:phone":"+49 7333/96030",
    "sg:postcode":"89150",
    "sg:province":"Baden-W\u00fcrttemberg",
    "wof:name":"Stucke Gmbh",
    "wof:placetype":"venue"
},
  "geometry": {"coordinates":[9.68925,48.484211],"type":"Point"}
}