{
  "type": "Feature",
  "properties": {
    "iso:country":"DE",
    "sg:address":"Marktplatz 5",
    "sg:city":"Planegg",
    "sg:phone":"+49 89/8596612",
    "sg:postcode":"82152",
    "sg:province":"Bayern",
    "wof:name":"Gerd Teebken Architekt",
    "wof:placetype":"venue"
},
  "geometry": {"coordinates":[11.419685,48.102951],"type":"Point"}
}