{
  "type": "Feature",
  "properties": {
    "iso:country":"DE",
    "sg:address":"Bismarckstr. 11",
    "sg:city":"Braunlage",
    "sg:phone":"+49 5520/690",
    "sg:postcode":"38700",
    "sg:province":"Niedersachsen",
    "wof:name":"G\u00e4stehaus Haus Christoph",
    "wof:placetype":"venue"
},
  "geometry": {"coordinates":[10.6062793732,51.7302932739],"type":"Point"}
}