{
  "type": "Feature",
  "properties": {
    "iso:country":"DE",
    "sg:address":"Westerweide 31",
    "sg:city":"Witten",
    "sg:phone":"+49 2302/71567",
    "sg:postcode":"58456",
    "sg:province":"Nordrhein-Westfalen",
    "wof:name":"Fritz Eversberg",
    "wof:placetype":"venue"
},
  "geometry": {"coordinates":[7.267996788,51.4090003967],"type":"Point"}
}