{
  "type": "Feature",
  "properties": {
    "iso:country":"DE",
    "sg:address":"Mangoldstr. 14",
    "sg:city":"Wemding",
    "sg:phone":"+49 9092/273",
    "sg:postcode":"86650",
    "sg:province":"Bayern",
    "wof:name":"Hans-georg Seefried",
    "wof:placetype":"venue"
},
  "geometry": {"coordinates":[10.726193,48.874722],"type":"Point"}
}