{
  "type": "Feature",
  "properties": {
    "iso:country":"DE",
    "sg:address":"Bahnhofstr. 56",
    "sg:city":"Bischweier",
    "sg:phone":"+49 7222/48041",
    "sg:postcode":"76476",
    "sg:province":"Baden-W\u00fcrttemberg",
    "wof:name":"L. Seitz",
    "wof:placetype":"venue"
},
  "geometry": {"coordinates":[8.278924942,48.8342590332],"type":"Point"}
}