{
  "type": "Feature",
  "properties": {
    "iso:country":"DE",
    "sg:address":"Schlo\u00df Nymphenburg",
    "sg:city":"M\u00fcnchen",
    "sg:phone":"+49 89/12081",
    "sg:postcode":"80638",
    "sg:province":"Bayern",
    "wof:name":"Bayrische Verwaltung Der Staatlichen Schl\u00f6sser. G\u00e4rten",
    "wof:placetype":"venue"
},
  "geometry": {"coordinates":[11.504295,48.159271],"type":"Point"}
}