{
  "type": "Feature",
  "properties": {
    "iso:country":"DE",
    "sg:address":"Einhart",
    "sg:city":"Ostrach",
    "sg:phone":"+49 7585/2823",
    "sg:postcode":"88356",
    "sg:province":"Baden-W\u00fcrttemberg",
    "wof:name":"Weithartsaal",
    "wof:placetype":"venue"
},
  "geometry": {"coordinates":[9.3654336929,47.9694023132],"type":"Point"}
}