{
  "type": "Feature",
  "properties": {
    "iso:country":"DE",
    "sg:address":"Genter Str. 14",
    "sg:city":"K\u00f6ln",
    "sg:postcode":"50672",
    "sg:province":"Nordrhein-Westfalen",
    "wof:name":"C. G. H. Unternehmens- Verwaltungs Gmbh",
    "wof:placetype":"venue"
},
  "geometry": {"coordinates":[6.936416,50.939629],"type":"Point"}
}