{
  "type": "Feature",
  "properties": {
    "iso:country":"DE",
    "sg:address":"Hohenberger Str. 1",
    "sg:city":"Nagold",
    "sg:phone":"+49 7452/2720",
    "sg:postcode":"72202",
    "sg:province":"Baden-W\u00fcrttemberg",
    "wof:name":"Hallenbad Lemberg",
    "wof:placetype":"venue"
},
  "geometry": {"coordinates":[8.7167158127,48.5438728333],"type":"Point"}
}