{
  "type": "Feature",
  "properties": {
    "iso:country":"DE",
    "sg:address":"Thomas-Mann-Str. 24",
    "sg:city":"Bonn",
    "sg:phone":"+49 228/659995",
    "sg:postcode":"53111",
    "sg:province":"Nordrhein-Westfalen",
    "wof:name":"J. Junkers",
    "wof:placetype":"venue"
},
  "geometry": {"coordinates":[7.0950341225,50.7355728149],"type":"Point"}
}