{
  "type": "Feature",
  "properties": {
    "iso:country":"DE",
    "sg:address":"Lichtenbergstr. 1",
    "sg:city":"Ludwigsburg",
    "sg:phone":"+49 7141/55874",
    "sg:postcode":"71642",
    "sg:province":"Baden-W\u00fcrttemberg",
    "wof:name":"L. Hack",
    "wof:placetype":"venue"
},
  "geometry": {"coordinates":[9.2057542801,48.9103393555],"type":"Point"}
}