{
  "type": "Feature",
  "properties": {
    "iso:country":"DE",
    "sg:address":"Hauptstr. 16",
    "sg:city":"Staufen",
    "sg:phone":"+49 7633/953940",
    "sg:postcode":"79219",
    "sg:province":"Baden-W\u00fcrttemberg",
    "wof:name":"S/p/i/e Digitalfoto Gmbh",
    "wof:placetype":"venue"
},
  "geometry": {"coordinates":[9.560579,51.347057],"type":"Point"}
}