{
  "type": "Feature",
  "properties": {
    "iso:country":"DE",
    "sg:address":"Schillerstr. 2",
    "sg:city":"Maintal",
    "sg:postcode":"63477",
    "sg:province":"Hessen",
    "wof:name":"Mtv Gmbh",
    "wof:placetype":"venue"
},
  "geometry": {"coordinates":[8.810738,50.15226],"type":"Point"}
}