{
  "type": "Feature",
  "properties": {
    "iso:country":"DE",
    "sg:address":"Am Hagelschlag 10",
    "sg:city":"Lebach",
    "sg:phone":"+49 6881/3012",
    "sg:postcode":"66822",
    "sg:province":"Saarland",
    "wof:name":"Steinr\u00fccke Martens Grundbesitz Gmbh & Co. Kg",
    "wof:placetype":"venue"
},
  "geometry": {"coordinates":[6.907556057,49.4172286987],"type":"Point"}
}