{
  "type": "Feature",
  "properties": {
    "iso:country":"DE",
    "sg:address":"Fritz-Erler-Str. 8",
    "sg:city":"Bruchk\u00f6bel",
    "sg:phone":"+49 6183/900720",
    "sg:postcode":"63486",
    "sg:province":"Hessen",
    "wof:name":"Metadesign Laser- Und Computer-gmbh",
    "wof:placetype":"venue"
},
  "geometry": {"coordinates":[8.9506387711,50.1982116699],"type":"Point"}
}