{
  "type": "Feature",
  "properties": {
    "iso:country":"DE",
    "sg:address":"Bissenkamp 17",
    "sg:city":"Dortmund",
    "sg:phone":"+49 231/5865061",
    "sg:postcode":"44135",
    "sg:province":"Nordrhein-Westfalen",
    "wof:name":"K & H Klinker- Und Hochbau Gmbh",
    "wof:placetype":"venue"
},
  "geometry": {"coordinates":[7.464775,51.516582],"type":"Point"}
}