{
  "type": "Feature",
  "properties": {
    "iso:country":"DE",
    "sg:address":"Sachsenallee 8",
    "sg:city":"Kesselsdorf",
    "sg:phone":"+49 35204/6810",
    "sg:postcode":"01723",
    "sg:province":"Sachsen",
    "wof:name":"Fritz Berger Gmbh",
    "wof:placetype":"venue"
},
  "geometry": {"coordinates":[13.519213,51.029343],"type":"Point"}
}