{
  "type": "Feature",
  "properties": {
    "iso:country":"DE",
    "sg:address":"Bochumer Str. 4",
    "sg:city":"Sprockh\u00f6vel",
    "sg:phone":"+49 2324/74188",
    "sg:postcode":"45549",
    "sg:province":"Nordrhein-Westfalen",
    "wof:name":"Aral Ag",
    "wof:placetype":"venue"
},
  "geometry": {"coordinates":[7.2524619102,51.3670463562],"type":"Point"}
}