{
  "type": "Feature",
  "properties": {
    "iso:country":"DE",
    "sg:address":"Im Schalbert 11",
    "sg:city":"Heppenheim",
    "sg:phone":"+49 6252/76222",
    "sg:postcode":"64646",
    "sg:province":"Hessen",
    "wof:name":"Andreas H\u00f6ppener-fidus Architekt",
    "wof:placetype":"venue"
},
  "geometry": {"coordinates":[8.652291,49.64917],"type":"Point"}
}