{
  "type": "Feature",
  "properties": {
    "iso:country":"DE",
    "sg:address":"In der Au 2",
    "sg:city":"Niederbreitbach",
    "sg:phone":"+49 2638/5109",
    "sg:postcode":"56589",
    "sg:province":"Rheinland-Pfalz",
    "wof:name":"Scheid Travelling Inh. Rudi Und Uschi Scheid",
    "wof:placetype":"venue"
},
  "geometry": {"coordinates":[7.4173059464,50.529384613],"type":"Point"}
}