{
  "type": "Feature",
  "properties": {
    "iso:country":"DE",
    "sg:address":"Hans-Sigmund-Str. 62",
    "sg:city":"Aalen",
    "sg:phone":"+49 7366/5913",
    "sg:postcode":"73434",
    "sg:province":"Baden-W\u00fcrttemberg",
    "wof:name":"E. Kurz Masseur",
    "wof:placetype":"venue"
},
  "geometry": {"coordinates":[10.048209,48.883308],"type":"Point"}
}