{
  "type": "Feature",
  "properties": {
    "iso:country":"DE",
    "sg:address":"Goslarer Str. 26",
    "sg:city":"Vienenburg",
    "sg:postcode":"38690",
    "sg:province":"Niedersachsen",
    "wof:name":"Schn\u00e4ppchen-diele Vienenburg Gmbh",
    "wof:placetype":"venue"
},
  "geometry": {"coordinates":[10.5568161011,51.9538269043],"type":"Point"}
}