{
  "type": "Feature",
  "properties": {
    "iso:country":"DE",
    "sg:address":"Hafenstr. 197",
    "sg:city":"Bremerhaven",
    "sg:phone":"+49 471/55450",
    "sg:postcode":"27568",
    "sg:province":"Bremen",
    "wof:name":"Otto Sch\u00fclmann",
    "wof:placetype":"venue"
},
  "geometry": {"coordinates":[8.58601,53.563896],"type":"Point"}
}