{
  "type": "Feature",
  "properties": {
    "iso:country":"DE",
    "sg:address":"Dammberg 13",
    "sg:city":"Bad Salzungen",
    "sg:phone":"+49 3695/3460",
    "sg:postcode":"36433",
    "sg:province":"Th\u00fcringen",
    "wof:name":"Wilfried Schulz",
    "wof:placetype":"venue"
},
  "geometry": {"coordinates":[10.2467479706,50.7990684509],"type":"Point"}
}