{
  "type": "Feature",
  "properties": {
    "iso:country":"DE",
    "sg:address":"Burgstr. 3",
    "sg:city":"Elgersburg",
    "sg:phone":"+49 3677/78205",
    "sg:postcode":"98716",
    "sg:province":"Th\u00fcringen",
    "wof:name":"Schlo\u00df Elgersburg",
    "wof:placetype":"venue"
},
  "geometry": {"coordinates":[10.851729393,50.7041778564],"type":"Point"}
}