{
  "type": "Feature",
  "properties": {
    "iso:country":"DE",
    "sg:address":"Im Sikfeld 1",
    "sg:city":"Wolfenb\u00fcttel",
    "sg:phone":"+49 5331/5729",
    "sg:postcode":"38304",
    "sg:province":"Niedersachsen",
    "wof:name":"Wilfried Zenker",
    "wof:placetype":"venue"
},
  "geometry": {"coordinates":[10.5202608109,52.1709632874],"type":"Point"}
}