{
  "type": "Feature",
  "properties": {
    "iso:country":"DE",
    "sg:address":"Krankenhausstr. 5",
    "sg:city":"Erbendorf",
    "sg:phone":"+49 9682/9300",
    "sg:postcode":"92681",
    "sg:province":"Bayern",
    "wof:name":"Kliniken F\u00fcr Geriatrie Des Deutschen Ordens Und Des Land-",
    "wof:placetype":"venue"
},
  "geometry": {"coordinates":[12.0433635712,49.8368301392],"type":"Point"}
}