{
  "type": "Feature",
  "properties": {
    "iso:country":"DE",
    "sg:address":"Bahnhofstr. 16-18",
    "sg:city":"Buxtehude",
    "sg:postcode":"21614",
    "sg:province":"Niedersachsen",
    "wof:name":"Immobilien Development U. Be- Teiligungs Niedersachsen Gmbh",
    "wof:placetype":"venue"
},
  "geometry": {"coordinates":[9.694499,53.473843],"type":"Point"}
}