{
  "type": "Feature",
  "properties": {
    "iso:country":"DE",
    "sg:address":"Thadd\u00e4us-Hornung-Weg 13",
    "sg:city":"Dillingen",
    "sg:phone":"+49 9071/2257",
    "sg:postcode":"89407",
    "sg:province":"Bayern",
    "wof:name":"G. Wittmann",
    "wof:placetype":"venue"
},
  "geometry": {"coordinates":[10.4876890182,48.5758323669],"type":"Point"}
}