{
  "type": "Feature",
  "properties": {
    "iso:country":"DE",
    "sg:address":"Am Brink 11",
    "sg:city":"B\u00f6rger",
    "sg:phone":"+49 5953/1285",
    "sg:postcode":"26904",
    "sg:province":"Niedersachsen",
    "wof:name":"Hermann Schomakers",
    "wof:placetype":"venue"
},
  "geometry": {"coordinates":[7.542312,52.911545],"type":"Point"}
}