{
  "type": "Feature",
  "properties": {
    "iso:country":"DE",
    "sg:address":"Horst 3",
    "sg:city":"Haan",
    "sg:phone":"+49 212/9959199",
    "sg:postcode":"42781",
    "sg:province":"Nordrhein-Westfalen",
    "wof:name":"Helmut Hill",
    "wof:placetype":"venue"
},
  "geometry": {"coordinates":[7.006244,51.189659],"type":"Point"}
}