{
  "type": "Feature",
  "properties": {
    "iso:country":"DE",
    "sg:address":"Neuer Weg 15",
    "sg:city":"Willingen",
    "sg:phone":"+49 5632/6470",
    "sg:postcode":"34508",
    "sg:province":"Hessen",
    "wof:name":"Pension Kramer-m\u00fcllen",
    "wof:placetype":"venue"
},
  "geometry": {"coordinates":[8.6091156006,51.2932434082],"type":"Point"}
}