{
  "type": "Feature",
  "properties": {
    "iso:country":"DE",
    "sg:address":"Marktplatz 59",
    "sg:city":"Reisbach",
    "sg:phone":"+49 8734/223",
    "sg:postcode":"94419",
    "sg:province":"Bayern",
    "wof:name":"Alois Geier",
    "wof:placetype":"venue"
},
  "geometry": {"coordinates":[12.62896,48.570648],"type":"Point"}
}