{
  "type": "Feature",
  "properties": {
    "iso:country":"DE",
    "sg:address":"Am Fichtenhang 6",
    "sg:city":"Marsberg",
    "sg:postcode":"34431",
    "sg:province":"Nordrhein-Westfalen",
    "wof:name":"Ingenieurb\u00fcro Paak & Hanke Gmbh",
    "wof:placetype":"venue"
},
  "geometry": {"coordinates":[8.8439321518,51.4641876221],"type":"Point"}
}