{
  "type": "Feature",
  "properties": {
    "iso:country":"DE",
    "sg:address":"K\u00f6lner Str. 287",
    "sg:city":"D\u00fcsseldorf",
    "sg:phone":"+49 211/786105",
    "sg:postcode":"40227",
    "sg:province":"Nordrhein-Westfalen",
    "wof:name":"Haus Meschede",
    "wof:placetype":"venue"
},
  "geometry": {"coordinates":[6.8054847717,51.2137527466],"type":"Point"}
}