{
  "type": "Feature",
  "properties": {
    "iso:country":"DE",
    "sg:address":"Traarer Str. 380",
    "sg:city":"Krefeld",
    "sg:phone":"+49 2151/43656",
    "sg:postcode":"47829",
    "sg:province":"Nordrhein-Westfalen",
    "wof:name":"Katholisches Pfarramt St. Pius X.",
    "wof:placetype":"venue"
},
  "geometry": {"coordinates":[6.615375042,51.3631439209],"type":"Point"}
}