{
  "type": "Feature",
  "properties": {
    "iso:country":"DE",
    "sg:address":"M\u00fchlenstr. 41",
    "sg:city":"Bad Iburg",
    "sg:phone":"+49 5403/4267",
    "sg:postcode":"49186",
    "sg:province":"Niedersachsen",
    "wof:name":"Heinrich Tiesmeyer",
    "wof:placetype":"venue"
},
  "geometry": {"coordinates":[8.05227,52.150963],"type":"Point"}
}