{
  "type": "Feature",
  "properties": {
    "iso:country":"DE",
    "sg:address":"Mundolfstr. 17",
    "sg:city":"Berlin",
    "sg:phone":"+49 30/6735825",
    "sg:postcode":"12524",
    "sg:province":"Berlin",
    "wof:name":"Paul & K\u00fcter Bauelemente Gmbh",
    "wof:placetype":"venue"
},
  "geometry": {"coordinates":[13.5324659348,52.4105873108],"type":"Point"}
}