{
  "type": "Feature",
  "properties": {
    "iso:country":"DE",
    "sg:address":"Alte Pasinger Str. 120",
    "sg:city":"Gr\u00e4felfing",
    "sg:phone":"+49 89/8343889",
    "sg:postcode":"82166",
    "sg:province":"Bayern",
    "wof:name":"Ingrid Hehlinger",
    "wof:placetype":"venue"
},
  "geometry": {"coordinates":[11.449115,48.12915],"type":"Point"}
}