{
  "type": "Feature",
  "properties": {
    "iso:country":"DE",
    "sg:address":"Hauptstr. 11",
    "sg:city":"Langeoog",
    "sg:phone":"+49 4972/537",
    "sg:postcode":"26465",
    "sg:province":"Niedersachsen",
    "wof:name":"G\u00e4stehaus M. Hasch",
    "wof:placetype":"venue"
},
  "geometry": {"coordinates":[7.4837369919,53.7461624146],"type":"Point"}
}