{
  "type": "Feature",
  "properties": {
    "iso:country":"DE",
    "sg:address":"Parkstr. 9",
    "sg:city":"Pohlheim",
    "sg:phone":"+49 641/45360",
    "sg:postcode":"35415",
    "sg:province":"Hessen",
    "wof:name":"Gerhard Bechtold Steuerberater",
    "wof:placetype":"venue"
},
  "geometry": {"coordinates":[8.7404527664,50.5462760925],"type":"Point"}
}