{
  "type": "Feature",
  "properties": {
    "iso:country":"DE",
    "sg:address":"Ohrwaschelweg 25",
    "sg:city":"N\u00fcrnberg",
    "sg:phone":"+49 911/522995",
    "sg:postcode":"90411",
    "sg:province":"Bayern",
    "wof:name":"Heinz Bauer Ingenieur",
    "wof:placetype":"venue"
},
  "geometry": {"coordinates":[11.1045007706,49.5054168701],"type":"Point"}
}