{
  "type": "Feature",
  "properties": {
    "iso:country":"DE",
    "sg:address":"Katharinenstr. 50",
    "sg:city":"Freudenstadt",
    "sg:phone":"+49 7441/2450",
    "sg:postcode":"72250",
    "sg:province":"Baden-W\u00fcrttemberg",
    "wof:name":"Ulrich Grossbach",
    "wof:placetype":"venue"
},
  "geometry": {"coordinates":[8.408803,48.46513],"type":"Point"}
}