{
  "type": "Feature",
  "properties": {
    "iso:country":"DE",
    "sg:address":"Zeppelinstr. 30",
    "sg:city":"Bad Bentheim",
    "sg:postcode":"48455",
    "sg:province":"Niedersachsen",
    "wof:name":"Optimal-putz Gmbh",
    "wof:placetype":"venue"
},
  "geometry": {"coordinates":[7.1677727699,52.2932853699],"type":"Point"}
}