{
  "type": "Feature",
  "properties": {
    "iso:country":"DE",
    "sg:address":"Feldstr. 4",
    "sg:city":"Garmisch-Partenkirchen",
    "sg:phone":"+49 8821/52370",
    "sg:postcode":"82467",
    "sg:province":"Bayern",
    "wof:name":"Fremdenheim Hermann Ostler",
    "wof:placetype":"venue"
},
  "geometry": {"coordinates":[11.0795574188,47.4933738708],"type":"Point"}
}