{
  "type": "Feature",
  "properties": {
    "iso:country":"DE",
    "sg:address":"Florianstr.",
    "sg:city":"Rommerskirchen",
    "sg:phone":"+49 2183/7056",
    "sg:postcode":"41569",
    "sg:province":"Nordrhein-Westfalen",
    "wof:name":"Th. Kamp Hebamme",
    "wof:placetype":"venue"
},
  "geometry": {"coordinates":[6.711485,51.050529],"type":"Point"}
}