{
  "type": "Feature",
  "properties": {
    "iso:country":"DE",
    "sg:address":"Bahnhofstr. 48-50",
    "sg:city":"Leipzig",
    "sg:phone":"+49 341/2580503",
    "sg:postcode":"04158",
    "sg:province":"Sachsen",
    "wof:name":"Gesellschaft F\u00fcr Au\u00dfenhandelsbeziehungen",
    "wof:placetype":"venue"
},
  "geometry": {"coordinates":[12.366853714,51.3900489807],"type":"Point"}
}