{
  "type": "Feature",
  "properties": {
    "iso:country":"DE",
    "sg:address":"Papenmoorweg 17",
    "sg:city":"Schenefeld",
    "sg:phone":"+49 40/8391737",
    "sg:postcode":"22869",
    "sg:province":"Schleswig-Holstein",
    "wof:name":"Relax Gastst\u00e4tten- Und Unterhaltungsges. Mbh",
    "wof:placetype":"venue"
},
  "geometry": {"coordinates":[9.8418340683,53.6023902893],"type":"Point"}
}