{
  "type": "Feature",
  "properties": {
    "iso:country":"DE",
    "sg:address":"Apothekenstr. 10",
    "sg:city":"Duderstadt",
    "sg:phone":"+49 5527/4565",
    "sg:postcode":"37115",
    "sg:province":"Niedersachsen",
    "wof:name":"Harald Schneider",
    "wof:placetype":"venue"
},
  "geometry": {"coordinates":[10.2596788406,51.5115623474],"type":"Point"}
}