{
  "type": "Feature",
  "properties": {
    "iso:country":"DE",
    "sg:address":"Sch\u00f6nauer Str. 105",
    "sg:city":"Leipzig",
    "sg:phone":"+49 341/446160",
    "sg:postcode":"04249",
    "sg:province":"Sachsen",
    "wof:name":"M\u00fchlhofer & Pfahler Leipzig Gmbh",
    "wof:placetype":"venue"
},
  "geometry": {"coordinates":[12.3092422485,51.280456543],"type":"Point"}
}