{
  "type": "Feature",
  "properties": {
    "iso:country":"DE",
    "sg:address":"Dorfstr. 22",
    "sg:city":"Engden",
    "sg:phone":"+49 5926/290",
    "sg:postcode":"48465",
    "sg:province":"Niedersachsen",
    "wof:name":"Hotel Berns",
    "wof:placetype":"venue"
},
  "geometry": {"coordinates":[7.1742482185,52.3913383484],"type":"Point"}
}