{
  "type": "Feature",
  "properties": {
    "iso:country":"DE",
    "sg:address":"Serrahnstr.",
    "sg:city":"Hamburg",
    "sg:phone":"+49 40/7218777",
    "sg:postcode":"21029",
    "sg:province":"Hamburg",
    "wof:name":"Restaurant Die Kogge",
    "wof:placetype":"venue"
},
  "geometry": {"coordinates":[10.2080402374,53.4887237549],"type":"Point"}
}