{
  "type": "Feature",
  "properties": {
    "iso:country":"DE",
    "sg:address":"Kesselei 15",
    "sg:city":"Hildesheim",
    "sg:phone":"+49 5064/1727",
    "sg:postcode":"31141",
    "sg:province":"Niedersachsen",
    "wof:name":"Franz-josef Lenz",
    "wof:placetype":"venue"
},
  "geometry": {"coordinates":[9.994748,52.111084],"type":"Point"}
}