{
  "type": "Feature",
  "properties": {
    "iso:country":"DE",
    "sg:address":"Am Seedeich 39",
    "sg:city":"Bremerhaven",
    "sg:phone":"+49 471/9712671",
    "sg:postcode":"27574",
    "sg:province":"Bremen",
    "wof:name":"Der Dialysepatient",
    "wof:placetype":"venue"
},
  "geometry": {"coordinates":[8.6387,53.519466],"type":"Point"}
}