{
  "type": "Feature",
  "properties": {
    "iso:country":"DE",
    "sg:address":"Ringstr. 22",
    "sg:city":"Wabern",
    "sg:phone":"+49 5683/5215",
    "sg:postcode":"34590",
    "sg:province":"Hessen",
    "wof:name":"Georg Siebert",
    "wof:placetype":"venue"
},
  "geometry": {"coordinates":[9.371102,51.120186],"type":"Point"}
}