{
  "type": "Feature",
  "properties": {
    "iso:country":"DE",
    "sg:address":"Industriestr. 42",
    "sg:city":"F\u00fcrth",
    "sg:phone":"+49 911/993020",
    "sg:postcode":"90765",
    "sg:province":"Bayern",
    "wof:name":"Wach- Und Eigentumschutz- Institut Theod. Arndt",
    "wof:placetype":"venue"
},
  "geometry": {"coordinates":[11.003358,49.509945],"type":"Point"}
}