{
  "type": "Feature",
  "properties": {
    "iso:country":"DE",
    "sg:address":"Am Deutenbach 2",
    "sg:city":"Schw\u00e4bisch Gm\u00fcnd",
    "sg:phone":"+49 7171/927790",
    "sg:postcode":"73525",
    "sg:province":"Baden-W\u00fcrttemberg",
    "wof:name":"Gamundia Dentalger\u00e4te Gmbh",
    "wof:placetype":"venue"
},
  "geometry": {"coordinates":[9.7689762115,48.7866897583],"type":"Point"}
}