{
  "type": "Feature",
  "properties": {
    "iso:country":"DE",
    "sg:address":"Lichtenfelser Str. 49",
    "sg:city":"Kulmbach",
    "sg:phone":"+49 9221/74286",
    "sg:postcode":"95326",
    "sg:province":"Bayern",
    "wof:name":"A-z Entsorgungspark Gmbh",
    "wof:placetype":"venue"
},
  "geometry": {"coordinates":[11.435129,50.10453],"type":"Point"}
}