{
  "type": "Feature",
  "properties": {
    "iso:country":"DE",
    "sg:address":"Bahnstr. 84",
    "sg:city":"Mendig",
    "sg:phone":"+49 2652/51158",
    "sg:postcode":"56743",
    "sg:province":"Rheinland-Pfalz",
    "wof:name":"Tankstelle Schmickler Gmbh",
    "wof:placetype":"venue"
},
  "geometry": {"coordinates":[7.28688097,50.3692626953],"type":"Point"}
}