{
  "type": "Feature",
  "properties": {
    "iso:country":"DE",
    "sg:address":"Museumsplatz 4",
    "sg:city":"Hamburg",
    "sg:postcode":"21073",
    "sg:province":"Hamburg",
    "wof:name":"Kirchengemeinde St. Maria",
    "wof:placetype":"venue"
},
  "geometry": {"coordinates":[9.9768571854,53.4586906433],"type":"Point"}
}