{
  "type": "Feature",
  "properties": {
    "iso:country":"DE",
    "sg:address":"Berliner Str. 194",
    "sg:city":"Beelitz",
    "sg:postcode":"14547",
    "sg:province":"Brandenburg",
    "wof:name":"Asparagus-apotheke Man. Schicht-schneider E. Kfr.",
    "wof:placetype":"venue"
},
  "geometry": {"coordinates":[12.977995,52.234165],"type":"Point"}
}