{
  "type": "Feature",
  "properties": {
    "iso:country":"DE",
    "sg:address":"Rauentaler Str. 4",
    "sg:city":"Berlin",
    "sg:phone":"+49 30/4015162",
    "sg:postcode":"13465",
    "sg:province":"Berlin",
    "wof:name":"Schmidt",
    "wof:placetype":"venue"
},
  "geometry": {"coordinates":[13.301981926,52.6438560486],"type":"Point"}
}