{
  "type": "Feature",
  "properties": {
    "iso:country":"DE",
    "sg:address":"Daimlerstr. 3",
    "sg:city":"B\u00fchl",
    "sg:phone":"+49 7223/25473",
    "sg:postcode":"77815",
    "sg:province":"Baden-W\u00fcrttemberg",
    "wof:name":"Gerhard Schemel",
    "wof:placetype":"venue"
},
  "geometry": {"coordinates":[8.1145277023,48.6860389709],"type":"Point"}
}