{
  "type": "Feature",
  "properties": {
    "iso:country":"DE",
    "sg:address":"Dietersdorfer Hauptstr. 59",
    "sg:city":"Sch\u00f6nsee",
    "sg:phone":"+49 9674/336",
    "sg:postcode":"92539",
    "sg:province":"Bayern",
    "wof:name":"J. Zach",
    "wof:placetype":"venue"
},
  "geometry": {"coordinates":[12.55134,49.514259],"type":"Point"}
}