{
  "type": "Feature",
  "properties": {
    "iso:country":"DE",
    "sg:address":"Schulstr. 9",
    "sg:city":"B\u00f6r\u00dfum",
    "sg:phone":"+49 5334/97500",
    "sg:postcode":"38312",
    "sg:province":"Niedersachsen",
    "wof:name":"J\u00f6rg Mahlmann",
    "wof:placetype":"venue"
},
  "geometry": {"coordinates":[10.587156,52.070164],"type":"Point"}
}