{
  "type": "Feature",
  "properties": {
    "iso:country":"DE",
    "sg:address":"Schulstr. 42",
    "sg:city":"Seevetal",
    "sg:phone":"+49 4105/81262",
    "sg:postcode":"21220",
    "sg:province":"Niedersachsen",
    "wof:name":"Quali Tex-reinigung",
    "wof:placetype":"venue"
},
  "geometry": {"coordinates":[10.042458,53.396439],"type":"Point"}
}