{
  "type": "Feature",
  "properties": {
    "iso:country":"DE",
    "sg:address":"Lange Str. 9",
    "sg:city":"Kirchlengern",
    "sg:phone":"+49 5223/72923",
    "sg:postcode":"32278",
    "sg:province":"Nordrhein-Westfalen",
    "wof:name":"Wilhelm Kollmeier",
    "wof:placetype":"venue"
},
  "geometry": {"coordinates":[8.641396,52.199917],"type":"Point"}
}