{
  "type": "Feature",
  "properties": {
    "iso:country":"DE",
    "sg:address":"G\u00e4nsemarsch 1d",
    "sg:city":"Hemmingen",
    "sg:phone":"+49 511/421008",
    "sg:postcode":"30966",
    "sg:province":"Niedersachsen",
    "wof:name":"Projektpartner Media Consult",
    "wof:placetype":"venue"
},
  "geometry": {"coordinates":[9.7495346069,52.3199043274],"type":"Point"}
}