{
  "type": "Feature",
  "properties": {
    "iso:country":"DE",
    "sg:address":"Zeughausstr. 1",
    "sg:city":"Bad Urach",
    "sg:phone":"+49 7125/4283",
    "sg:postcode":"72574",
    "sg:province":"Baden-W\u00fcrttemberg",
    "wof:name":"Erika Mutschler",
    "wof:placetype":"venue"
},
  "geometry": {"coordinates":[9.4014387131,48.4928855896],"type":"Point"}
}