{
  "type": "Feature",
  "properties": {
    "iso:country":"DE",
    "sg:address":"Detmolder Str. 652",
    "sg:city":"Bielefeld",
    "sg:phone":"+49 5202/84267",
    "sg:postcode":"33699",
    "sg:province":"Nordrhein-Westfalen",
    "wof:name":"Thomas Kronshage",
    "wof:placetype":"venue"
},
  "geometry": {"coordinates":[8.625146,51.987602],"type":"Point"}
}