{
  "type": "Feature",
  "properties": {
    "iso:country":"DE",
    "sg:address":"Zum Sporkfeld 6",
    "sg:city":"Rietberg",
    "sg:phone":"+49 5244/1280",
    "sg:postcode":"33397",
    "sg:province":"Nordrhein-Westfalen",
    "wof:name":"Angelika St\u00fccker",
    "wof:placetype":"venue"
},
  "geometry": {"coordinates":[8.4622335434,51.8171005249],"type":"Point"}
}