{
  "type": "Feature",
  "properties": {
    "iso:country":"DE",
    "sg:address":"Schlo\u00df",
    "sg:city":"Winterburg",
    "sg:phone":"+49 6706/8650",
    "sg:postcode":"55595",
    "sg:province":"Rheinland-Pfalz",
    "wof:name":"Archiv Der Freiherren Von Dalberg",
    "wof:placetype":"venue"
},
  "geometry": {"coordinates":[7.646942,49.865204],"type":"Point"}
}