{
  "type": "Feature",
  "properties": {
    "iso:country":"DE",
    "sg:address":"J\u00e4gerstr. 90",
    "sg:city":"Oberhausen",
    "sg:phone":"+49 208/645051",
    "sg:postcode":"46149",
    "sg:province":"Nordrhein-Westfalen",
    "wof:name":"Ibp Prof. Dr. Ing. Uwe Weltin Inst F\u00fcr Bauteilpr\u00fcfung Gmbh",
    "wof:placetype":"venue"
},
  "geometry": {"coordinates":[6.838251,51.532764],"type":"Point"}
}