{
  "type": "Feature",
  "properties": {
    "iso:country":"DE",
    "sg:address":"Borsigstr. 17",
    "sg:city":"L\u00fcbbecke",
    "sg:phone":"+49 5741/8042",
    "sg:postcode":"32312",
    "sg:province":"Nordrhein-Westfalen",
    "wof:name":"F. Brandstein",
    "wof:placetype":"venue"
},
  "geometry": {"coordinates":[8.620473,52.326981],"type":"Point"}
}