{
  "type": "Feature",
  "properties": {
    "iso:country":"DE",
    "sg:address":"Otto-Hahn-Str. 33",
    "sg:city":"M\u00fchlheim",
    "sg:postcode":"63165",
    "sg:province":"Hessen",
    "wof:name":"Palmbeach Computer Gmbh",
    "wof:placetype":"venue"
},
  "geometry": {"coordinates":[8.8493537903,50.1133041382],"type":"Point"}
}