{
  "type": "Feature",
  "properties": {
    "iso:country":"DE",
    "sg:address":"Br\u00fcckenstr. 1",
    "sg:city":"Ha\u00dffurt",
    "sg:phone":"+49 9521/1465",
    "sg:postcode":"97437",
    "sg:province":"Bayern",
    "wof:name":"Zehe Herrenmoden",
    "wof:placetype":"venue"
},
  "geometry": {"coordinates":[10.5069046021,50.0312690735],"type":"Point"}
}