{
  "type": "Feature",
  "properties": {
    "iso:country":"DE",
    "sg:address":"Claudiastr. 2 B",
    "sg:city":"K\u00f6ln",
    "sg:phone":"+49 2203/911320",
    "sg:postcode":"51149",
    "sg:province":"Nordrhein-Westfalen",
    "wof:name":"Otto Luft- Und Klimatechnik Gmbh & Co. Kg",
    "wof:placetype":"venue"
},
  "geometry": {"coordinates":[7.0240411758,50.9045333862],"type":"Point"}
}