{
  "type": "Feature",
  "properties": {
    "iso:country":"DE",
    "sg:address":"Oberheiden 7",
    "sg:city":"Much",
    "sg:postcode":"53804",
    "sg:province":"Nordrhein-Westfalen",
    "wof:name":"Dietmar G. Anders",
    "wof:placetype":"venue"
},
  "geometry": {"coordinates":[7.382789135,50.9194412231],"type":"Point"}
}