{
  "type": "Feature",
  "properties": {
    "iso:country":"DE",
    "sg:address":"Im M\u00fchlengrund 23",
    "sg:city":"H\u00fcrth",
    "sg:phone":"+49 2233/933303",
    "sg:postcode":"50354",
    "sg:province":"Nordrhein-Westfalen",
    "wof:name":"Herbert Kramp Anlageberater",
    "wof:placetype":"venue"
},
  "geometry": {"coordinates":[6.8500490189,50.8799285889],"type":"Point"}
}