{
  "type": "Feature",
  "properties": {
    "iso:country":"DE",
    "sg:address":"Schlachthofstr. 14",
    "sg:city":"Bremerhaven",
    "sg:phone":"+49 471/81214",
    "sg:postcode":"27576",
    "sg:province":"Bremen",
    "wof:name":"Frischdienst Nord Handelsgesellschaft Mbh",
    "wof:placetype":"venue"
},
  "geometry": {"coordinates":[8.5948667526,53.5585594177],"type":"Point"}
}