{
  "type": "Feature",
  "properties": {
    "iso:country":"DE",
    "sg:address":"Seenheim 5",
    "sg:city":"Ergersheim",
    "sg:phone":"+49 9847/771",
    "sg:postcode":"91465",
    "sg:province":"Bayern",
    "wof:name":"Eduard Reuter",
    "wof:placetype":"venue"
},
  "geometry": {"coordinates":[10.327715,49.511276],"type":"Point"}
}