{
  "type": "Feature",
  "properties": {
    "iso:country":"DE",
    "sg:address":"Blankenhainer Str. 29",
    "sg:city":"Berlin",
    "sg:phone":"+49 30/7752248",
    "sg:postcode":"12249",
    "sg:province":"Berlin",
    "wof:name":"Werner Grabs Ingenieur",
    "wof:placetype":"venue"
},
  "geometry": {"coordinates":[13.349852562,52.4221076965],"type":"Point"}
}