{
  "type": "Feature",
  "properties": {
    "iso:country":"DE",
    "sg:address":"Pagenstecherstr. 40",
    "sg:city":"Osnabr\u00fcck",
    "sg:phone":"+49 541/691120",
    "sg:postcode":"49090",
    "sg:province":"Niedersachsen",
    "wof:name":"Brillux Gmbh & Co. Kg",
    "wof:placetype":"venue"
},
  "geometry": {"coordinates":[8.030308,52.288177],"type":"Point"}
}