{
  "type": "Feature",
  "properties": {
    "iso:country":"DE",
    "sg:address":"Werler Str. 13",
    "sg:city":"Bad Salzuflen",
    "sg:phone":"+49 5222/50006",
    "sg:postcode":"32105",
    "sg:province":"Nordrhein-Westfalen",
    "wof:name":"Wanted Bikes Gmbh",
    "wof:placetype":"venue"
},
  "geometry": {"coordinates":[8.737694,52.083965],"type":"Point"}
}