{
  "type": "Feature",
  "properties": {
    "iso:country":"DE",
    "sg:address":"R\u00f6srather Str. 653",
    "sg:city":"K\u00f6ln",
    "sg:phone":"+49 221/866343",
    "sg:postcode":"51107",
    "sg:province":"Nordrhein-Westfalen",
    "wof:name":"Aps Mode",
    "wof:placetype":"venue"
},
  "geometry": {"coordinates":[7.073,50.92461],"type":"Point"}
}