{
  "type": "Feature",
  "properties": {
    "iso:country":"DE",
    "sg:address":"Alte Bonnstr. 62",
    "sg:city":"Br\u00fchl",
    "sg:phone":"+49 2232/32239",
    "sg:postcode":"50321",
    "sg:province":"Nordrhein-Westfalen",
    "wof:name":"Ulrike Gei\u00dfler",
    "wof:placetype":"venue"
},
  "geometry": {"coordinates":[6.895802,50.813038],"type":"Point"}
}