{
  "type": "Feature",
  "properties": {
    "iso:country":"DE",
    "sg:address":"Neuburger Str. 42",
    "sg:city":"Ingolstadt",
    "sg:phone":"+49 841/81861",
    "sg:postcode":"85049",
    "sg:province":"Bayern",
    "wof:name":"Erich Spanheimer",
    "wof:placetype":"venue"
},
  "geometry": {"coordinates":[11.402867,48.768272],"type":"Point"}
}