{
  "type": "Feature",
  "properties": {
    "iso:country":"DE",
    "sg:address":"M\u00fchlental 16",
    "sg:city":"Aachen",
    "sg:phone":"+49 241/61680",
    "sg:postcode":"52066",
    "sg:province":"Nordrhein-Westfalen",
    "wof:name":"K. J. Heidelberg Ingenieur",
    "wof:placetype":"venue"
},
  "geometry": {"coordinates":[6.0896830559,50.7578392029],"type":"Point"}
}