{
  "type": "Feature",
  "properties": {
    "iso:country":"DE",
    "sg:address":"Bieberkamp 75",
    "sg:city":"Menden",
    "sg:phone":"+49 2373/80860",
    "sg:postcode":"58710",
    "sg:province":"Nordrhein-Westfalen",
    "wof:name":"Grundst\u00fccksverwaltung Krutmann Gmbh & Co. Kg",
    "wof:placetype":"venue"
},
  "geometry": {"coordinates":[7.8484501839,51.4146080017],"type":"Point"}
}