{
  "type": "Feature",
  "properties": {
    "iso:country":"DE",
    "sg:address":"Forchenweg 27",
    "sg:city":"Burladingen",
    "sg:phone":"+49 7475/1607",
    "sg:postcode":"72393",
    "sg:province":"Baden-W\u00fcrttemberg",
    "wof:name":"Bernhard Werz",
    "wof:placetype":"venue"
},
  "geometry": {"coordinates":[9.1085596085,48.2996406555],"type":"Point"}
}