{
  "type": "Feature",
  "properties": {
    "iso:country":"DE",
    "sg:address":"Schlo\u00dfstr. 89",
    "sg:city":"Eislingen",
    "sg:phone":"+49 7161/817271",
    "sg:postcode":"73054",
    "sg:province":"Baden-W\u00fcrttemberg",
    "wof:name":"Peter Mulke",
    "wof:placetype":"venue"
},
  "geometry": {"coordinates":[9.719575,48.694435],"type":"Point"}
}