{
  "type": "Feature",
  "properties": {
    "iso:country":"DE",
    "sg:address":"Kirchstr. 4",
    "sg:city":"Lindern",
    "sg:phone":"+49 5957/340",
    "sg:postcode":"49699",
    "sg:province":"Niedersachsen",
    "wof:name":"Kath. Pfarramt St. Katharina",
    "wof:placetype":"venue"
},
  "geometry": {"coordinates":[7.7813057899,52.8453330994],"type":"Point"}
}