{
  "type": "Feature",
  "properties": {
    "iso:country":"DE",
    "sg:address":"G\u00fctersloher Str. 53",
    "sg:city":"Verl",
    "sg:phone":"+49 5246/2438",
    "sg:postcode":"33415",
    "sg:province":"Nordrhein-Westfalen",
    "wof:name":"Reinhard Illies",
    "wof:placetype":"venue"
},
  "geometry": {"coordinates":[8.5006990433,51.8802337646],"type":"Point"}
}