{
  "type": "Feature",
  "properties": {
    "iso:country":"DE",
    "sg:address":"Hauptstr. 78a",
    "sg:city":"Saarbr\u00fccken",
    "sg:phone":"+49 681/891218",
    "sg:postcode":"66132",
    "sg:province":"Saarland",
    "wof:name":"Thomas Block",
    "wof:placetype":"venue"
},
  "geometry": {"coordinates":[7.0732679367,49.221321106],"type":"Point"}
}