{
  "type": "Feature",
  "properties": {
    "iso:country":"DE",
    "sg:address":"Am Br\u00f6gel 21",
    "sg:city":"Wuppertal",
    "sg:postcode":"42285",
    "sg:province":"Nordrhein-Westfalen",
    "wof:name":"Aci - Technik E. K.",
    "wof:placetype":"venue"
},
  "geometry": {"coordinates":[7.1807041168,51.266292572],"type":"Point"}
}