{
  "type": "Feature",
  "properties": {
    "iso:country":"DE",
    "sg:address":"Am Kraftwerk 13",
    "sg:city":"Wuppertal",
    "sg:postcode":"42369",
    "sg:province":"Nordrhein-Westfalen",
    "wof:name":"Hartmann Metallwaren Gmbh",
    "wof:placetype":"venue"
},
  "geometry": {"coordinates":[7.206254,51.227833],"type":"Point"}
}