{
  "type": "Feature",
  "properties": {
    "iso:country":"DE",
    "sg:address":"Neu\u00f6ttinger Str. 69",
    "sg:city":"Alt\u00f6tting",
    "sg:phone":"+49 8671/988514",
    "sg:postcode":"84503",
    "sg:province":"Bayern",
    "wof:name":"Grignion-haus Altenheim",
    "wof:placetype":"venue"
},
  "geometry": {"coordinates":[12.68434,48.233551],"type":"Point"}
}