{
  "type": "Feature",
  "properties": {
    "iso:country":"DE",
    "sg:address":"Bernabeistr. 6",
    "sg:city":"M\u00fcnchen",
    "sg:phone":"+49 89/174080",
    "sg:postcode":"80639",
    "sg:province":"Bayern",
    "wof:name":"Marwede Assekuranz Vermittlungs Gmbh",
    "wof:placetype":"venue"
},
  "geometry": {"coordinates":[11.5181779861,48.1582527161],"type":"Point"}
}