{
  "type": "Feature",
  "properties": {
    "iso:country":"DE",
    "sg:address":"Nordplatz 1 c",
    "sg:city":"Eisenach",
    "sg:phone":"+49 3691/872977",
    "sg:postcode":"99817",
    "sg:province":"Th\u00fcringen",
    "wof:name":"Hochhaus-klause",
    "wof:placetype":"venue"
},
  "geometry": {"coordinates":[10.3090791702,50.9963493347],"type":"Point"}
}