{
  "type": "Feature",
  "properties": {
    "iso:country":"DE",
    "sg:address":"Friedberger Str. 9",
    "sg:city":"Usingen",
    "sg:phone":"+49 6081/3397",
    "sg:postcode":"61250",
    "sg:province":"Hessen",
    "wof:name":"Norbert Nickolai",
    "wof:placetype":"venue"
},
  "geometry": {"coordinates":[8.573041,50.361691],"type":"Point"}
}