{
  "type": "Feature",
  "properties": {
    "iso:country":"DE",
    "sg:address":"Gommernsche Str. 35",
    "sg:city":"Dresden",
    "sg:phone":"+49 351/2818546",
    "sg:postcode":"01259",
    "sg:province":"Sachsen",
    "wof:name":"Georg Beck",
    "wof:placetype":"venue"
},
  "geometry": {"coordinates":[13.815392,50.990532],"type":"Point"}
}