{
  "type": "Feature",
  "properties": {
    "iso:country":"DE",
    "sg:address":"Bindlacher Str. 4n Einheit",
    "sg:city":"Bayreuth",
    "sg:phone":"+49 921/7982182",
    "sg:postcode":"95448",
    "sg:province":"Bayern",
    "wof:name":"Tbv Spezialtransporte Bau- Maschinenverleih Gmbh & Co. Kg",
    "wof:placetype":"venue"
},
  "geometry": {"coordinates":[11.645443,49.94289],"type":"Point"}
}