{
  "type": "Feature",
  "properties": {
    "iso:country":"DE",
    "sg:address":"Gerberstr. 23",
    "sg:city":"Drolshagen",
    "sg:phone":"+49 2761/790999",
    "sg:postcode":"57489",
    "sg:province":"Nordrhein-Westfalen",
    "wof:name":"Olympia Grill",
    "wof:placetype":"venue"
},
  "geometry": {"coordinates":[7.7749881744,51.0226135254],"type":"Point"}
}