{
  "type": "Feature",
  "properties": {
    "iso:country":"DE",
    "sg:address":"Waldstr. 56",
    "sg:city":"Hennigsdorf",
    "sg:postcode":"16761",
    "sg:province":"Brandenburg",
    "wof:name":"Ma-rog Steuerberatungsges. Mbh",
    "wof:placetype":"venue"
},
  "geometry": {"coordinates":[13.199133873,52.6471786499],"type":"Point"}
}