{
  "type": "Feature",
  "properties": {
    "iso:country":"DE",
    "sg:address":"Bahnhofstr. 18",
    "sg:city":"Dabel",
    "sg:phone":"+49 38485/20470",
    "sg:postcode":"19406",
    "sg:province":"Mecklenburg-Vorpommern",
    "wof:name":"Lbb Land- Bau- Und Brennstoffmarkt Dabel Gmbh",
    "wof:placetype":"venue"
},
  "geometry": {"coordinates":[11.8913650513,53.6709442139],"type":"Point"}
}