{
  "type": "Feature",
  "properties": {
    "iso:country":"DE",
    "sg:address":"Talstr. 27",
    "sg:city":"Wiesbaden",
    "sg:phone":"+49 611/544791",
    "sg:postcode":"65191",
    "sg:province":"Hessen",
    "wof:name":"Hannelore Eider",
    "wof:placetype":"venue"
},
  "geometry": {"coordinates":[8.265085,50.103184],"type":"Point"}
}