{
  "type": "Feature",
  "properties": {
    "iso:country":"DE",
    "sg:address":"Heidenheimer Str. 13G",
    "sg:city":"G\u00fcnzburg",
    "sg:phone":"+49 8221/32143",
    "sg:postcode":"89312",
    "sg:province":"Bayern",
    "wof:name":"Walter Hauke Gmbh",
    "wof:placetype":"venue"
},
  "geometry": {"coordinates":[10.2670125961,48.4648132324],"type":"Point"}
}