{
  "type": "Feature",
  "properties": {
    "iso:country":"DE",
    "sg:address":"Boschstr. 3a",
    "sg:city":"Speyer",
    "sg:postcode":"67346",
    "sg:province":"Rheinland-Pfalz",
    "wof:name":"Quadraform Gmbh",
    "wof:placetype":"venue"
},
  "geometry": {"coordinates":[8.4204874039,49.3428535461],"type":"Point"}
}