{
  "type": "Feature",
  "properties": {
    "iso:country":"DE",
    "sg:address":"Rentforter Str. 96",
    "sg:city":"Bottrop",
    "sg:phone":"+49 2045/84196",
    "sg:postcode":"46244",
    "sg:province":"Nordrhein-Westfalen",
    "wof:name":"Dr. Hammer Gmbh",
    "wof:placetype":"venue"
},
  "geometry": {"coordinates":[6.9326100349,51.588558197],"type":"Point"}
}