{
  "type": "Feature",
  "properties": {
    "iso:country":"DE",
    "sg:address":"Lilienstr. 12",
    "sg:city":"Frielendorf",
    "sg:phone":"+49 4956/848279",
    "sg:postcode":"34621",
    "sg:province":"Hessen",
    "wof:name":"Kabel Fuer Orchesterelektronik Inh. Martin Schulz",
    "wof:placetype":"venue"
},
  "geometry": {"coordinates":[9.32777,50.96909],"type":"Point"}
}