{
  "type": "Feature",
  "properties": {
    "iso:country":"DE",
    "sg:address":"Berliner Allee 1b",
    "sg:city":"Fehrbellin",
    "sg:phone":"+49 33932/70557",
    "sg:postcode":"16833",
    "sg:province":"Brandenburg",
    "wof:name":"G\u00fcnter Kleiner",
    "wof:placetype":"venue"
},
  "geometry": {"coordinates":[12.778115,52.808788],"type":"Point"}
}