{
  "type": "Feature",
  "properties": {
    "iso:country":"DE",
    "sg:address":"Dettinger Str 129",
    "sg:city":"Kirchheim",
    "sg:phone":"+49 7021/946950",
    "sg:postcode":"73230",
    "sg:province":"Baden-W\u00fcrttemberg",
    "wof:name":"Ortlieb Pr\u00e4zisionsspannzeuge Gmbh & Co",
    "wof:placetype":"venue"
},
  "geometry": {"coordinates":[9.45332,48.636517],"type":"Point"}
}