{
  "type": "Feature",
  "properties": {
    "iso:country":"DE",
    "sg:address":"Hammerstr. 17",
    "sg:city":"Gevelsberg",
    "sg:phone":"+49 2332/2032",
    "sg:postcode":"58285",
    "sg:province":"Nordrhein-Westfalen",
    "wof:name":"Alfred Sch\u00fcrhoff Gmbh & Co.",
    "wof:placetype":"venue"
},
  "geometry": {"coordinates":[7.3261780739,51.3185005188],"type":"Point"}
}