{
  "type": "Feature",
  "properties": {
    "iso:country":"DE",
    "sg:address":"An der Trah 18",
    "sg:city":"Leer",
    "sg:phone":"+49 491/2363",
    "sg:postcode":"26789",
    "sg:province":"Niedersachsen",
    "wof:name":"E. Kleimaker",
    "wof:placetype":"venue"
},
  "geometry": {"coordinates":[7.434909,53.262543],"type":"Point"}
}