{
  "type": "Feature",
  "properties": {
    "iso:country":"DE",
    "sg:city":"Chemnitz",
    "sg:postcode":"09113",
    "sg:province":"Sachsen",
    "wof:name":"Inside Sportsysteme Gmbh",
    "wof:placetype":"venue"
},
  "geometry": {"coordinates":[12.910406,50.845341],"type":"Point"}
}