{
  "type": "Feature",
  "properties": {
    "iso:country":"DE",
    "sg:address":"Rosenweg 4",
    "sg:city":"Saarbr\u00fccken",
    "sg:phone":"+49 6893/2913",
    "sg:postcode":"66131",
    "sg:province":"Saarland",
    "wof:name":"Elke Hoffmann Steuerberaterin",
    "wof:placetype":"venue"
},
  "geometry": {"coordinates":[7.1023812294,49.2033233643],"type":"Point"}
}