{
  "type": "Feature",
  "properties": {
    "iso:country":"DE",
    "sg:address":"Steinbeisstr.",
    "sg:city":"Ilsfeld",
    "sg:phone":"+49 7062/96992",
    "sg:postcode":"74360",
    "sg:province":"Baden-W\u00fcrttemberg",
    "wof:name":"Freibad",
    "wof:placetype":"venue"
},
  "geometry": {"coordinates":[9.2584018707,49.0560379028],"type":"Point"}
}