{
  "type": "Feature",
  "properties": {
    "iso:country":"DE",
    "sg:address":"Cleversulzbacher Str. 61",
    "sg:city":"Neuenstadt",
    "sg:phone":"+49 7139/453906",
    "sg:postcode":"74196",
    "sg:province":"Baden-W\u00fcrttemberg",
    "wof:name":"Armin Huspenina E. K.",
    "wof:placetype":"venue"
},
  "geometry": {"coordinates":[9.3357410431,49.2321281433],"type":"Point"}
}