{
  "type": "Feature",
  "properties": {
    "iso:country":"DE",
    "sg:address":"Turnierstr. 7",
    "sg:city":"Stuttgart",
    "sg:phone":"+49 711/456620",
    "sg:postcode":"70599",
    "sg:province":"Baden-W\u00fcrttemberg",
    "wof:name":"Olaf Wehrle Med. Massagepraxis",
    "wof:placetype":"venue"
},
  "geometry": {"coordinates":[9.213726,48.701385],"type":"Point"}
}