{
  "type": "Feature",
  "properties": {
    "iso:country":"DE",
    "sg:address":"Rottweiler Str. 35",
    "sg:city":"Niedereschach",
    "sg:phone":"+49 7728/92750",
    "sg:postcode":"78078",
    "sg:province":"Baden-W\u00fcrttemberg",
    "wof:name":"Romer Gmbh",
    "wof:placetype":"venue"
},
  "geometry": {"coordinates":[8.5312004089,48.1353111267],"type":"Point"}
}