{
  "type": "Feature",
  "properties": {
    "iso:country":"DE",
    "sg:address":"Neuer Weg 12",
    "sg:city":"Wohratal",
    "sg:phone":"+49 6453/7194",
    "sg:postcode":"35288",
    "sg:province":"Hessen",
    "wof:name":"Heinrich Ellerich",
    "wof:placetype":"venue"
},
  "geometry": {"coordinates":[8.928693,50.961063],"type":"Point"}
}