{
  "type": "Feature",
  "properties": {
    "iso:country":"DE",
    "sg:address":"Industriestr. 9",
    "sg:city":"Hirschaid",
    "sg:phone":"+49 9543/84230",
    "sg:postcode":"96114",
    "sg:province":"Bayern",
    "wof:name":"Vesta K\u00fcchenfachhandels Gmbh",
    "wof:placetype":"venue"
},
  "geometry": {"coordinates":[11.0008459091,49.8195228577],"type":"Point"}
}