{
  "type": "Feature",
  "properties": {
    "iso:country":"DE",
    "sg:address":"John-Sieg-Str. 22",
    "sg:city":"Berlin",
    "sg:postcode":"10365",
    "sg:province":"Berlin",
    "wof:name":"Dr. Med. Magdalena Hagen",
    "wof:placetype":"venue"
},
  "geometry": {"coordinates":[13.480452,52.510185],"type":"Point"}
}