{
  "type": "Feature",
  "properties": {
    "iso:country":"DE",
    "sg:address":"Lenbachstr. 24",
    "sg:city":"Schrobenhausen",
    "sg:phone":"+49 8252/81427",
    "sg:postcode":"86529",
    "sg:province":"Bayern",
    "wof:name":"Rita Dhanjal Modeschmuck",
    "wof:placetype":"venue"
},
  "geometry": {"coordinates":[11.264457,48.561916],"type":"Point"}
}