{
  "type": "Feature",
  "properties": {
    "iso:country":"DE",
    "sg:address":"Am Bahnhof 3a",
    "sg:city":"Kirrweiler",
    "sg:phone":"+49 6321/95860",
    "sg:postcode":"67489",
    "sg:province":"Rheinland-Pfalz",
    "wof:name":"Flaschen Wittmer Rudolf Wittmer",
    "wof:placetype":"venue"
},
  "geometry": {"coordinates":[8.147581,49.305962],"type":"Point"}
}