{
  "type": "Feature",
  "properties": {
    "iso:country":"DE",
    "sg:address":"Albert-Einstein-Str. 2",
    "sg:city":"Wiehl",
    "sg:phone":"+49 2262/76200",
    "sg:postcode":"51674",
    "sg:province":"Nordrhein-Westfalen",
    "wof:name":"Energiebau L\u00fcck Gmbh",
    "wof:placetype":"venue"
},
  "geometry": {"coordinates":[7.5451288223,50.9700088501],"type":"Point"}
}