{
  "type": "Feature",
  "properties": {
    "iso:country":"DE",
    "sg:address":"Reckholderstr. 7",
    "sg:city":"Wyhl",
    "sg:phone":"+49 7642/7430",
    "sg:postcode":"79369",
    "sg:province":"Baden-W\u00fcrttemberg",
    "wof:name":"Ernst K\u00e4\u00dfheimer",
    "wof:placetype":"venue"
},
  "geometry": {"coordinates":[7.646594,48.167606],"type":"Point"}
}