{
  "type": "Feature",
  "properties": {
    "iso:country":"DE",
    "sg:address":"Wilhelmjstr. 3",
    "sg:city":"Usingen",
    "sg:phone":"+49 6081/687440",
    "sg:postcode":"61250",
    "sg:province":"Hessen",
    "wof:name":"Blumen N. Wicht",
    "wof:placetype":"venue"
},
  "geometry": {"coordinates":[8.536571,50.334175],"type":"Point"}
}