{
  "type": "Feature",
  "properties": {
    "iso:country":"DE",
    "sg:address":"Bohlweg 2",
    "sg:city":"Emmerthal",
    "sg:phone":"+49 5157/303",
    "sg:postcode":"31860",
    "sg:province":"Niedersachsen",
    "wof:name":"Hartwig Ricke",
    "wof:placetype":"venue"
},
  "geometry": {"coordinates":[9.445305,52.017071],"type":"Point"}
}