{
  "type": "Feature",
  "properties": {
    "iso:country":"DE",
    "sg:address":"Etzelstr. 29",
    "sg:city":"Heilbronn",
    "sg:phone":"+49 7131/767172",
    "sg:postcode":"74076",
    "sg:province":"Baden-W\u00fcrttemberg",
    "wof:name":"D2-fachcenter B & B Gmbh",
    "wof:placetype":"venue"
},
  "geometry": {"coordinates":[9.2154273987,49.1523628235],"type":"Point"}
}