{
  "type": "Feature",
  "properties": {
    "iso:country":"DE",
    "sg:address":"Fliederweg 20",
    "sg:city":"Steimbke",
    "sg:phone":"+49 5026/94896",
    "sg:postcode":"31634",
    "sg:province":"Niedersachsen",
    "wof:name":"Stiebel Eltron Gmbh & Co. Kg",
    "wof:placetype":"venue"
},
  "geometry": {"coordinates":[9.4017410278,52.6564292908],"type":"Point"}
}