{
  "type": "Feature",
  "properties": {
    "iso:country":"DE",
    "sg:address":"Auf'm Rott 54",
    "sg:city":"D\u00fcsseldorf",
    "sg:postcode":"40591",
    "sg:province":"Nordrhein-Westfalen",
    "wof:name":"Dannemann Feinkost Gmbh",
    "wof:placetype":"venue"
},
  "geometry": {"coordinates":[6.8242897987,51.1921691895],"type":"Point"}
}