{
  "type": "Feature",
  "properties": {
    "iso:country":"DE",
    "sg:address":"Pagendarmweg 9",
    "sg:city":"Paderborn",
    "sg:phone":"+49 5251/26068",
    "sg:postcode":"33100",
    "sg:province":"Nordrhein-Westfalen",
    "wof:name":"Karl-heinz Aupke",
    "wof:placetype":"venue"
},
  "geometry": {"coordinates":[8.773274,51.736401],"type":"Point"}
}