{
  "type": "Feature",
  "properties": {
    "iso:country":"DE",
    "sg:address":"Grafenwald",
    "sg:city":"Hermeskeil",
    "sg:phone":"+49 6503/91520",
    "sg:postcode":"54411",
    "sg:province":"Rheinland-Pfalz",
    "wof:name":"Pax Gmbh",
    "wof:placetype":"venue"
},
  "geometry": {"coordinates":[6.969933,49.672394],"type":"Point"}
}