{
  "type": "Feature",
  "properties": {
    "iso:country":"DE",
    "sg:address":"Lerchenstr. 8",
    "sg:city":"Freiburg",
    "sg:phone":"+49 761/26167",
    "sg:postcode":"79104",
    "sg:province":"Baden-W\u00fcrttemberg",
    "wof:name":"Hans-j. Schwarzer",
    "wof:placetype":"venue"
},
  "geometry": {"coordinates":[7.859164238,48.0058097839],"type":"Point"}
}