{
  "type": "Feature",
  "properties": {
    "iso:country":"DE",
    "sg:address":"Schanzstr. 52",
    "sg:city":"Kamp-Lintfort",
    "sg:phone":"+49 2842/56487",
    "sg:postcode":"47475",
    "sg:province":"Nordrhein-Westfalen",
    "wof:name":"Uwe Treeter",
    "wof:placetype":"venue"
},
  "geometry": {"coordinates":[6.540585,51.509277],"type":"Point"}
}