{
  "type": "Feature",
  "properties": {
    "iso:country":"DE",
    "sg:address":"Schandauer Str. 43",
    "sg:city":"Dresden",
    "sg:phone":"+49 351/51459",
    "sg:postcode":"01277",
    "sg:province":"Sachsen",
    "wof:name":"Bauknecht Hausger\u00e4te Gmbh",
    "wof:placetype":"venue"
},
  "geometry": {"coordinates":[13.8002023697,51.0415916443],"type":"Point"}
}