{
  "type": "Feature",
  "properties": {
    "iso:country":"DE",
    "sg:address":"An der Kirche 7",
    "sg:city":"Neukirchen",
    "sg:phone":"+49 4365/221",
    "sg:postcode":"23779",
    "sg:province":"Schleswig-Holstein",
    "wof:name":"Hans Thiel",
    "wof:placetype":"venue"
},
  "geometry": {"coordinates":[10.553013,54.214924],"type":"Point"}
}