{
  "type": "Feature",
  "properties": {
    "iso:country":"DE",
    "sg:address":"Leipziger Str. 55",
    "sg:city":"Eilenburg",
    "sg:phone":"+49 3423/602084",
    "sg:postcode":"04838",
    "sg:province":"Sachsen",
    "wof:name":"Am Leipziger Tor",
    "wof:placetype":"venue"
},
  "geometry": {"coordinates":[12.6291761398,51.4588432312],"type":"Point"}
}