{
  "type": "Feature",
  "properties": {
    "iso:country":"DE",
    "sg:address":"Bouchestr. 12",
    "sg:city":"Berlin",
    "sg:phone":"+49 30/53311733",
    "sg:postcode":"12435",
    "sg:province":"Berlin",
    "wof:name":"Steremat Werkzeug- Und Maschinenbau Gmbh",
    "wof:placetype":"venue"
},
  "geometry": {"coordinates":[13.4513530731,52.4922065735],"type":"Point"}
}