{
  "type": "Feature",
  "properties": {
    "iso:country":"DE",
    "sg:address":"Haewererweg 14",
    "sg:city":"Berlin",
    "sg:phone":"+49 30/7427361",
    "sg:postcode":"12349",
    "sg:province":"Berlin",
    "wof:name":"Varpu Ryyn\u00e4nen-kortmann",
    "wof:placetype":"venue"
},
  "geometry": {"coordinates":[13.427158,52.418159],"type":"Point"}
}