{
  "type": "Feature",
  "properties": {
    "iso:country":"DE",
    "sg:address":"Erlenh\u00f6fe",
    "sg:city":"Dautphetal",
    "sg:phone":"+49 6466/1281",
    "sg:postcode":"35232",
    "sg:province":"Hessen",
    "wof:name":"Helmut Wege",
    "wof:placetype":"venue"
},
  "geometry": {"coordinates":[8.589733,50.870647],"type":"Point"}
}