{
  "type": "Feature",
  "properties": {
    "iso:country":"DE",
    "sg:address":"Hauptstr. 23",
    "sg:city":"Schladen",
    "sg:phone":"+49 5335/5221",
    "sg:postcode":"38315",
    "sg:province":"Niedersachsen",
    "wof:name":"Gerhard Feustel Fernsehen",
    "wof:placetype":"venue"
},
  "geometry": {"coordinates":[10.5206718445,51.9876213074],"type":"Point"}
}