{
  "type": "Feature",
  "properties": {
    "iso:country":"DE",
    "sg:address":"Am Tierpark 125",
    "sg:city":"Berlin",
    "sg:phone":"+49 30/5138141",
    "sg:postcode":"10319",
    "sg:province":"Berlin",
    "wof:name":"Schloss Friedrichsfelde",
    "wof:placetype":"venue"
},
  "geometry": {"coordinates":[13.524618,52.496422],"type":"Point"}
}