{
  "type": "Feature",
  "properties": {
    "iso:country":"DE",
    "sg:address":"Laubegaster Ufer 24",
    "sg:city":"Dresden",
    "sg:phone":"+49 351/2371938",
    "sg:postcode":"01279",
    "sg:province":"Sachsen",
    "wof:name":"Siemank",
    "wof:placetype":"venue"
},
  "geometry": {"coordinates":[13.840412,51.023739],"type":"Point"}
}