{
  "type": "Feature",
  "properties": {
    "iso:country":"DE",
    "sg:address":"Feldstetter Str. 82",
    "sg:city":"Laichingen",
    "sg:phone":"+49 7333/4716",
    "sg:postcode":"89150",
    "sg:province":"Baden-W\u00fcrttemberg",
    "wof:name":"Hans Frank",
    "wof:placetype":"venue"
},
  "geometry": {"coordinates":[9.679732,48.488365],"type":"Point"}
}