{
  "type": "Feature",
  "properties": {
    "iso:country":"DE",
    "sg:address":"Wengertsberg 26",
    "sg:city":"Eichenb\u00fchl",
    "sg:phone":"+49 9371/3309",
    "sg:postcode":"63928",
    "sg:province":"Bayern",
    "wof:name":"Henny J\u00fcngst",
    "wof:placetype":"venue"
},
  "geometry": {"coordinates":[9.3333511353,49.7031478882],"type":"Point"}
}