{
  "type": "Feature",
  "properties": {
    "iso:country":"DE",
    "sg:address":"Mescheder Str. 16",
    "sg:city":"Sundern",
    "sg:phone":"+49 2933/1237",
    "sg:postcode":"59846",
    "sg:province":"Nordrhein-Westfalen",
    "wof:name":"Rote Erde Gmbh",
    "wof:placetype":"venue"
},
  "geometry": {"coordinates":[8.006666,51.330006],"type":"Point"}
}