{
  "type": "Feature",
  "properties": {
    "iso:country":"DE",
    "sg:address":"Saselkoppel 22",
    "sg:city":"Hamburg",
    "sg:phone":"+49 40/6010854",
    "sg:postcode":"22393",
    "sg:province":"Hamburg",
    "wof:name":"Johann Carl M\u00fcller-stiftung Seniorenwohnanlage",
    "wof:placetype":"venue"
},
  "geometry": {"coordinates":[10.098483,53.646481],"type":"Point"}
}