{
  "type": "Feature",
  "properties": {
    "iso:country":"DE",
    "sg:address":"Waldstr. 8",
    "sg:city":"Schlaitz",
    "sg:postcode":"06774",
    "sg:province":"Sachsen-Anhalt",
    "wof:name":"Agrarunion Schlaitz Eg",
    "wof:placetype":"venue"
},
  "geometry": {"coordinates":[12.418361,51.655148],"type":"Point"}
}