{
  "type": "Feature",
  "properties": {
    "iso:country":"DE",
    "sg:address":"Hersfelder Str. 156",
    "sg:city":"Bebra",
    "sg:phone":"+49 6622/2065",
    "sg:postcode":"36179",
    "sg:province":"Hessen",
    "wof:name":"Walter Schuster",
    "wof:placetype":"venue"
},
  "geometry": {"coordinates":[9.79469,50.965111],"type":"Point"}
}