{
  "type": "Feature",
  "properties": {
    "iso:country":"DE",
    "sg:address":"Waldsiedlung 2",
    "sg:city":"Irschenberg",
    "sg:phone":"+49 8062/1515",
    "sg:postcode":"83737",
    "sg:province":"Bayern",
    "wof:name":"Klimke Gmbh",
    "wof:placetype":"venue"
},
  "geometry": {"coordinates":[11.917796,47.833694],"type":"Point"}
}