{
  "type": "Feature",
  "properties": {
    "iso:country":"DE",
    "sg:address":"Schmaler Weg 8",
    "sg:city":"Bad Homburg",
    "sg:phone":"+49 6172/456573",
    "sg:postcode":"61352",
    "sg:province":"Hessen",
    "wof:name":"P. Koch",
    "wof:placetype":"venue"
},
  "geometry": {"coordinates":[8.679688,50.223747],"type":"Point"}
}