{
  "type": "Feature",
  "properties": {
    "iso:country":"DE",
    "sg:address":"K\u00fcpferlingstr. 52",
    "sg:city":"Rosenheim",
    "sg:phone":"+49 8031/32354",
    "sg:postcode":"83024",
    "sg:province":"Bayern",
    "wof:name":"Ferdinand Beck",
    "wof:placetype":"venue"
},
  "geometry": {"coordinates":[12.110102,47.858418],"type":"Point"}
}