{
  "type": "Feature",
  "properties": {
    "iso:country":"DE",
    "sg:address":"Schanzstr. 21",
    "sg:city":"Edenkoben",
    "sg:phone":"+49 6323/5568",
    "sg:postcode":"67480",
    "sg:province":"Rheinland-Pfalz",
    "wof:name":"Peter Gr\u00e4ber",
    "wof:placetype":"venue"
},
  "geometry": {"coordinates":[8.1360530853,49.2804298401],"type":"Point"}
}