{
  "type": "Feature",
  "properties": {
    "iso:country":"DE",
    "sg:address":"Pochwerkm\u00fchleng\u00e4\u00dfchen 3",
    "sg:city":"Geyer",
    "sg:phone":"+49 37346/1401",
    "sg:postcode":"09468",
    "sg:province":"Sachsen",
    "wof:name":"Besta Gmbh",
    "wof:placetype":"venue"
},
  "geometry": {"coordinates":[12.9213075638,50.626537323],"type":"Point"}
}