{
  "type": "Feature",
  "properties": {
    "iso:country":"DE",
    "sg:address":"Hertzstr. 3",
    "sg:city":"Karlsdorf-Neuthard",
    "sg:phone":"+49 7251/44971",
    "sg:postcode":"76689",
    "sg:province":"Baden-W\u00fcrttemberg",
    "wof:name":"Helmut Riffel Steuerberater",
    "wof:placetype":"venue"
},
  "geometry": {"coordinates":[8.5457372665,49.1324462891],"type":"Point"}
}