{
  "type": "Feature",
  "properties": {
    "iso:country":"DE",
    "sg:address":"Reinhardtstr. 56",
    "sg:city":"Saalfeld",
    "sg:phone":"+49 3671/517020",
    "sg:postcode":"07318",
    "sg:province":"Th\u00fcringen",
    "wof:name":"Frank Hanisch",
    "wof:placetype":"venue"
},
  "geometry": {"coordinates":[11.360113,50.640667],"type":"Point"}
}