{
  "type": "Feature",
  "properties": {
    "iso:country":"DE",
    "sg:address":"Herderstr. 18",
    "sg:city":"Hockenheim",
    "sg:phone":"+49 6205/101927",
    "sg:postcode":"68766",
    "sg:province":"Baden-W\u00fcrttemberg",
    "wof:name":"T. Cholewicz",
    "wof:placetype":"venue"
},
  "geometry": {"coordinates":[8.5393218994,49.3126068115],"type":"Point"}
}