{
  "type": "Feature",
  "properties": {
    "iso:country":"DE",
    "sg:address":"Tengstr. 24",
    "sg:city":"M\u00fcnchen",
    "sg:phone":"+49 89/2719228",
    "sg:postcode":"80798",
    "sg:province":"Bayern",
    "wof:name":"Marion Kaminski Heilpraktiker",
    "wof:placetype":"venue"
},
  "geometry": {"coordinates":[11.5691366196,48.1581001282],"type":"Point"}
}