{
  "type": "Feature",
  "properties": {
    "iso:country":"DE",
    "sg:address":"Auf dem M\u00fchlberg 20",
    "sg:city":"Frankfurt",
    "sg:postcode":"60599",
    "sg:province":"Hessen",
    "wof:name":"Edv-beratung Gmbh",
    "wof:placetype":"venue"
},
  "geometry": {"coordinates":[8.6975069046,50.1017723083],"type":"Point"}
}