{
  "type": "Feature",
  "properties": {
    "iso:country":"DE",
    "sg:address":"Vaihingener Str 1",
    "sg:city":"Hartha",
    "sg:phone":"+49 34328/41195",
    "sg:postcode":"04746",
    "sg:province":"Sachsen",
    "wof:name":"Kurt Kipping Spedition Gmbh",
    "wof:placetype":"venue"
},
  "geometry": {"coordinates":[12.965999,51.095062],"type":"Point"}
}