{
  "type": "Feature",
  "properties": {
    "iso:country":"DE",
    "sg:address":"Ledererzeile 32",
    "sg:city":"Wasserburg",
    "sg:phone":"+49 8071/40143",
    "sg:postcode":"83512",
    "sg:province":"Bayern",
    "wof:name":"Spielwaren Fuchs Inh. Irene Ge\u00dfler",
    "wof:placetype":"venue"
},
  "geometry": {"coordinates":[12.2306175232,48.0620536804],"type":"Point"}
}