{
  "type": "Feature",
  "properties": {
    "iso:country":"DE",
    "sg:address":"Am B\u00fchl 25",
    "sg:city":"Runding",
    "sg:phone":"+49 9971/803533",
    "sg:postcode":"93486",
    "sg:province":"Bayern",
    "wof:name":"Gra-bet Pflasterbau Gmbh",
    "wof:placetype":"venue"
},
  "geometry": {"coordinates":[12.7462081909,49.2239227295],"type":"Point"}
}