{
  "type": "Feature",
  "properties": {
    "iso:country":"DE",
    "sg:address":"Hafenbahnstr. 6a",
    "sg:city":"Stuttgart",
    "sg:postcode":"70327",
    "sg:province":"Baden-W\u00fcrttemberg",
    "wof:name":"Helmut Haase Gmbh",
    "wof:placetype":"venue"
},
  "geometry": {"coordinates":[9.2589349747,48.7710876465],"type":"Point"}
}