{
  "type": "Feature",
  "properties": {
    "iso:country":"DE",
    "sg:address":"Altendorfer Str. 34",
    "sg:city":"Holzminden",
    "sg:phone":"+49 5531/4546",
    "sg:postcode":"37603",
    "sg:province":"Niedersachsen",
    "wof:name":"Altendorfer Hof",
    "wof:placetype":"venue"
},
  "geometry": {"coordinates":[9.4669513702,51.8246955872],"type":"Point"}
}