{
  "type": "Feature",
  "properties": {
    "iso:country":"DE",
    "sg:address":"Mozartstr. 17",
    "sg:city":"Leer",
    "sg:phone":"+49 491/73033",
    "sg:postcode":"26789",
    "sg:province":"Niedersachsen",
    "wof:name":"J. Heeren",
    "wof:placetype":"venue"
},
  "geometry": {"coordinates":[7.4824080467,53.2340011597],"type":"Point"}
}