{
  "type": "Feature",
  "properties": {
    "iso:country":"DE",
    "sg:address":"Stra\u00dfe der MTS",
    "sg:city":"Falkenhain",
    "sg:postcode":"04808",
    "sg:province":"Sachsen",
    "wof:name":"Hey-tec Regelungstechnik Gmbh",
    "wof:placetype":"venue"
},
  "geometry": {"coordinates":[12.8889331818,51.3834381104],"type":"Point"}
}