{
  "type": "Feature",
  "properties": {
    "iso:country":"DE",
    "sg:address":"Blumenstr. 32 a",
    "sg:city":"Hersbruck",
    "sg:phone":"+49 9151/2402",
    "sg:postcode":"91217",
    "sg:province":"Bayern",
    "wof:name":"Klaus Groth",
    "wof:placetype":"venue"
},
  "geometry": {"coordinates":[11.434504,49.498016],"type":"Point"}
}