{
  "type": "Feature",
  "properties": {
    "iso:country":"DE",
    "sg:address":"Olgastr 7",
    "sg:city":"T\u00fcbingen",
    "sg:phone":"+49 7071/52176",
    "sg:postcode":"72074",
    "sg:province":"Baden-W\u00fcrttemberg",
    "wof:name":"Dr. Menne",
    "wof:placetype":"venue"
},
  "geometry": {"coordinates":[9.061041832,48.5194702148],"type":"Point"}
}