{
  "type": "Feature",
  "properties": {
    "iso:country":"DE",
    "sg:address":"Max-Lang-Str. 60",
    "sg:city":"Leinfelden-Echterdingen",
    "sg:phone":"+49 711/75930",
    "sg:postcode":"70771",
    "sg:province":"Baden-W\u00fcrttemberg",
    "wof:name":"Offsetdruckerei Carl Werner Gmbh",
    "wof:placetype":"venue"
},
  "geometry": {"coordinates":[9.1428289413,48.7013053894],"type":"Point"}
}