{
  "type": "Feature",
  "properties": {
    "iso:country":"DE",
    "sg:address":"Wurzner Str. 6",
    "sg:city":"Leipzig",
    "sg:phone":"+49 341/6895673",
    "sg:postcode":"04315",
    "sg:province":"Sachsen",
    "wof:name":"Frank Rei\u00dfmann",
    "wof:placetype":"venue"
},
  "geometry": {"coordinates":[12.4074573517,51.3387718201],"type":"Point"}
}