{
  "type": "Feature",
  "properties": {
    "iso:country":"DE",
    "sg:address":"Reichenbacher Str. 14",
    "sg:city":"Warendorf",
    "sg:phone":"+49 2581/96858",
    "sg:postcode":"48231",
    "sg:province":"Nordrhein-Westfalen",
    "wof:name":"Dr. Horst Schoof Tierarzt",
    "wof:placetype":"venue"
},
  "geometry": {"coordinates":[7.9861330986,51.9427452087],"type":"Point"}
}