{
  "type": "Feature",
  "properties": {
    "iso:country":"DE",
    "sg:address":"Fliederweg 7",
    "sg:city":"Renchen",
    "sg:postcode":"77871",
    "sg:province":"Baden-W\u00fcrttemberg",
    "wof:name":"Immobilien G\u00fcnter Gmbh",
    "wof:placetype":"venue"
},
  "geometry": {"coordinates":[8.013455,48.59222],"type":"Point"}
}