{
  "type": "Feature",
  "properties": {
    "iso:country":"DE",
    "sg:address":"Schubertstr. 1",
    "sg:city":"Hohenstein-Ernstthal",
    "sg:postcode":"09337",
    "sg:province":"Sachsen",
    "wof:name":"Schweizer & Partner Steuerberater Gmbh",
    "wof:placetype":"venue"
},
  "geometry": {"coordinates":[12.709777832,50.7991943359],"type":"Point"}
}