{
  "type": "Feature",
  "properties": {
    "iso:country":"DE",
    "sg:address":"Azaleenweg 8",
    "sg:city":"Rahden",
    "sg:phone":"+49 5771/1591",
    "sg:postcode":"32369",
    "sg:province":"Nordrhein-Westfalen",
    "wof:name":"W. R\u00f6denbeck",
    "wof:placetype":"venue"
},
  "geometry": {"coordinates":[8.654759,52.452206],"type":"Point"}
}