{
  "type": "Feature",
  "properties": {
    "iso:country":"DE",
    "sg:address":"Postfach 49",
    "sg:city":"Grasberg",
    "sg:phone":"+49 10330190859815",
    "sg:postcode":"28877",
    "sg:province":"Niedersachsen",
    "wof:name":"Searchingmachine / - First German !!!",
    "wof:placetype":"venue"
},
  "geometry": {"coordinates":[8.98059,53.182621],"type":"Point"}
}