{
  "type": "Feature",
  "properties": {
    "iso:country":"DE",
    "sg:address":"Geislohe 38",
    "sg:city":"Pappenheim",
    "sg:phone":"+49 9149/94110",
    "sg:postcode":"91788",
    "sg:province":"Bayern",
    "wof:name":"F. H\u00fcttinger Gmbh & Co. Transport Kg",
    "wof:placetype":"venue"
},
  "geometry": {"coordinates":[10.9890260696,48.9654388428],"type":"Point"}
}