{
  "type": "Feature",
  "properties": {
    "iso:country":"DE",
    "sg:address":"Josef J\u00e4gerhuber Str. 11",
    "sg:city":"Starnberg",
    "sg:phone":"+49 8151",
    "sg:postcode":"82319",
    "sg:province":"Bayern",
    "wof:name":"C & I Immobilien Gmbh",
    "wof:placetype":"venue"
},
  "geometry": {"coordinates":[11.3451843262,48.0007591248],"type":"Point"}
}