{
  "type": "Feature",
  "properties": {
    "iso:country":"DE",
    "sg:address":"Gotenstr. 13",
    "sg:city":"Oberdischingen",
    "sg:phone":"+49 7305/5070",
    "sg:postcode":"89610",
    "sg:province":"Baden-W\u00fcrttemberg",
    "wof:name":"M. Franke Immobilienmakler",
    "wof:placetype":"venue"
},
  "geometry": {"coordinates":[9.8405399323,48.3045082092],"type":"Point"}
}