{
  "type": "Feature",
  "properties": {
    "iso:country":"DE",
    "sg:address":"Turnstr. 8",
    "sg:city":"Quedlinburg",
    "sg:phone":"+49 4967/13780",
    "sg:postcode":"06484",
    "sg:province":"Sachsen-Anhalt",
    "wof:name":"Kreuznacher Volksbank Eg",
    "wof:placetype":"venue"
},
  "geometry": {"coordinates":[7.860755,49.84145],"type":"Point"}
}