{
  "type": "Feature",
  "properties": {
    "iso:country":"DE",
    "sg:address":"Hauptstr. 10",
    "sg:city":"Maroldsweisach",
    "sg:phone":"+49 9535/981060",
    "sg:postcode":"96126",
    "sg:province":"Bayern",
    "wof:name":"Thomas Einwag",
    "wof:placetype":"venue"
},
  "geometry": {"coordinates":[10.6604633331,50.1951942444],"type":"Point"}
}