{
  "type": "Feature",
  "properties": {
    "iso:country":"DE",
    "sg:address":"Dorfstr. 17",
    "sg:city":"Sauldorf",
    "sg:phone":"+49 7777/357",
    "sg:postcode":"88605",
    "sg:province":"Baden-W\u00fcrttemberg",
    "wof:name":"Herbert M\u00fcller",
    "wof:placetype":"venue"
},
  "geometry": {"coordinates":[9.036217,47.969566],"type":"Point"}
}