{
  "type": "Feature",
  "properties": {
    "iso:country":"DE",
    "sg:address":"Hauptstr. 39",
    "sg:city":"Bischofsheim",
    "sg:phone":"+49 9775/274",
    "sg:postcode":"97653",
    "sg:province":"Bayern",
    "wof:name":"Gasthof Ewald",
    "wof:placetype":"venue"
},
  "geometry": {"coordinates":[10.0881528854,50.3954048157],"type":"Point"}
}