{
  "type": "Feature",
  "properties": {
    "iso:country":"DE",
    "sg:address":"Eckdrift 97",
    "sg:city":"Schwerin",
    "sg:phone":"+49 385/617180",
    "sg:postcode":"19061",
    "sg:province":"Mecklenburg-Vorpommern",
    "wof:name":"Inergetic Ag",
    "wof:placetype":"venue"
},
  "geometry": {"coordinates":[11.391538,53.594761],"type":"Point"}
}