{
  "type": "Feature",
  "properties": {
    "iso:country":"DE",
    "sg:address":"Ingenrieder Str. 2",
    "sg:city":"Schongau",
    "sg:phone":"+49 8861/23080",
    "sg:postcode":"86956",
    "sg:province":"Bayern",
    "wof:name":"Sintec Keramik Gmbh & Co.kg",
    "wof:placetype":"venue"
},
  "geometry": {"coordinates":[10.87754,47.809906],"type":"Point"}
}