{
  "type": "Feature",
  "properties": {
    "iso:country":"DE",
    "sg:address":"Draisstr 12",
    "sg:city":"Speyer",
    "sg:phone":"+49 6232/31800",
    "sg:postcode":"67346",
    "sg:province":"Rheinland-Pfalz",
    "wof:name":"Druckerei Fortmann Kg",
    "wof:placetype":"venue"
},
  "geometry": {"coordinates":[8.4265022278,49.3407096863],"type":"Point"}
}