{
  "type": "Feature",
  "properties": {
    "iso:country":"DE",
    "sg:address":"Jungviehweide 18",
    "sg:city":"M\u00f6rlenbach",
    "sg:postcode":"69509",
    "sg:province":"Hessen",
    "wof:name":"Extended Management Services Gmbh",
    "wof:placetype":"venue"
},
  "geometry": {"coordinates":[8.7400798798,49.6110153198],"type":"Point"}
}