{
  "type": "Feature",
  "properties": {
    "iso:country":"DE",
    "sg:address":"Ganterweg 69a",
    "sg:city":"Lenggries",
    "sg:phone":"+49 8042/2814",
    "sg:postcode":"83661",
    "sg:province":"Bayern",
    "wof:name":"Gerg Und Hei\u00df",
    "wof:placetype":"venue"
},
  "geometry": {"coordinates":[11.581885,47.660656],"type":"Point"}
}