{
  "type": "Feature",
  "properties": {
    "iso:country":"DE",
    "sg:address":"Am Bergpfuhl 21",
    "sg:city":"Berlin",
    "sg:phone":"+49 30/6815282",
    "sg:postcode":"12347",
    "sg:province":"Berlin",
    "wof:name":"Herbert Zenke",
    "wof:placetype":"venue"
},
  "geometry": {"coordinates":[13.421621,52.44455],"type":"Point"}
}