{
  "type": "Feature",
  "properties": {
    "iso:country":"DE",
    "sg:address":"Ernststr. 7",
    "sg:city":"Meiningen",
    "sg:postcode":"98617",
    "sg:province":"Th\u00fcringen",
    "wof:name":"Georgen-haus Sozialwerk Meiningen Betriebs Gmbh",
    "wof:placetype":"venue"
},
  "geometry": {"coordinates":[10.421335,50.581123],"type":"Point"}
}