{
  "type": "Feature",
  "properties": {
    "iso:country":"DE",
    "sg:address":"Bayernstr. 1",
    "sg:city":"Ratingen",
    "sg:phone":"+49 2102/67158",
    "sg:postcode":"40883",
    "sg:province":"Nordrhein-Westfalen",
    "wof:name":"Kleinhans Gmbh",
    "wof:placetype":"venue"
},
  "geometry": {"coordinates":[6.896378994,51.3390312195],"type":"Point"}
}