{
  "type": "Feature",
  "properties": {
    "iso:country":"DE",
    "sg:address":"Stoltenh\u00e4ger Str.",
    "sg:city":"Grimmen",
    "sg:phone":"+49 38326/6050",
    "sg:postcode":"18507",
    "sg:province":"Mecklenburg-Vorpommern",
    "wof:name":"Papenburg Baugesellschaft Mbh",
    "wof:placetype":"venue"
},
  "geometry": {"coordinates":[13.054525,54.127338],"type":"Point"}
}