{
  "type": "Feature",
  "properties": {
    "iso:country":"DE",
    "sg:address":"Bahnhofstr. 66",
    "sg:city":"Trebbin",
    "sg:phone":"+49 33731/15347",
    "sg:postcode":"14959",
    "sg:province":"Brandenburg",
    "wof:name":"Manfred Weise",
    "wof:placetype":"venue"
},
  "geometry": {"coordinates":[13.228131,52.215427],"type":"Point"}
}