{
  "type": "Feature",
  "properties": {
    "iso:country":"DE",
    "sg:address":"Zelckstr. 5",
    "sg:city":"Rostock",
    "sg:postcode":"18055",
    "sg:province":"Mecklenburg-Vorpommern",
    "wof:name":"Ev.-luth. Kirche",
    "wof:placetype":"venue"
},
  "geometry": {"coordinates":[12.1314687729,54.0833816528],"type":"Point"}
}