{
  "type": "Feature",
  "properties": {
    "iso:country":"DE",
    "sg:address":"Gartenstr. 6",
    "sg:city":"Seesen",
    "sg:phone":"+49 5381/48001",
    "sg:postcode":"38723",
    "sg:province":"Niedersachsen",
    "wof:name":"Rolf Sackmann Steuerberater",
    "wof:placetype":"venue"
},
  "geometry": {"coordinates":[10.1720781326,51.8879623413],"type":"Point"}
}