{
  "type": "Feature",
  "properties": {
    "iso:country":"DE",
    "sg:address":"Brunnenstr. 1",
    "sg:city":"Tawern",
    "sg:phone":"+49 6501/17866",
    "sg:postcode":"54456",
    "sg:province":"Rheinland-Pfalz",
    "wof:name":"Elke Heidger",
    "wof:placetype":"venue"
},
  "geometry": {"coordinates":[6.518226,49.67437],"type":"Point"}
}