{
  "type": "Feature",
  "properties": {
    "iso:country":"DE",
    "sg:address":"G\u00fcrzenichstr. 24",
    "sg:city":"K\u00f6ln",
    "sg:phone":"+49 221/2580765",
    "sg:postcode":"50667",
    "sg:province":"Nordrhein-Westfalen",
    "wof:name":"Noubar Klidjian Kameramann",
    "wof:placetype":"venue"
},
  "geometry": {"coordinates":[6.9588899612,50.9362487793],"type":"Point"}
}