{
  "type": "Feature",
  "properties": {
    "iso:country":"DE",
    "sg:address":"Schillerstr. 11",
    "sg:city":"Mainz",
    "sg:phone":"+49 6131/282290",
    "sg:postcode":"55116",
    "sg:province":"Rheinland-Pfalz",
    "wof:name":"Institut Francais Bibliothek",
    "wof:placetype":"venue"
},
  "geometry": {"coordinates":[8.2660551071,49.9990005493],"type":"Point"}
}