{
  "type": "Feature",
  "properties": {
    "iso:country":"DE",
    "sg:address":"Lauenburger Str. 5",
    "sg:city":"Schwarzenbek",
    "sg:phone":"+49 4151/3653",
    "sg:postcode":"21493",
    "sg:province":"Schleswig-Holstein",
    "wof:name":"Gerhard Von Jutrczenka",
    "wof:placetype":"venue"
},
  "geometry": {"coordinates":[10.4810571671,53.5021095276],"type":"Point"}
}