{
  "type": "Feature",
  "properties": {
    "iso:country":"DE",
    "sg:address":"Steinling 16",
    "sg:city":"Edelsfeld",
    "sg:phone":"+49 9661/4462",
    "sg:postcode":"92265",
    "sg:province":"Bayern",
    "wof:name":"Georg Winter",
    "wof:placetype":"venue"
},
  "geometry": {"coordinates":[11.709855,49.56638],"type":"Point"}
}