{
  "type": "Feature",
  "properties": {
    "iso:country":"DE",
    "sg:address":"Schulstr. 49-51",
    "sg:city":"Trierweiler",
    "sg:phone":"+49 651/82430",
    "sg:postcode":"54311",
    "sg:province":"Rheinland-Pfalz",
    "wof:name":"Seniorenresidenz Niederweiler Hof Gmbh",
    "wof:placetype":"venue"
},
  "geometry": {"coordinates":[6.555168,49.758186],"type":"Point"}
}