{
  "type": "Feature",
  "properties": {
    "iso:country":"DE",
    "sg:address":"K\u00f6nigsstr. 46",
    "sg:city":"M\u00fcnster",
    "sg:phone":"+49 251/46254",
    "sg:postcode":"48143",
    "sg:province":"Nordrhein-Westfalen",
    "wof:name":"Klaus Bleckmann",
    "wof:placetype":"venue"
},
  "geometry": {"coordinates":[7.625766,51.958778],"type":"Point"}
}