{
  "type": "Feature",
  "properties": {
    "iso:country":"DE",
    "sg:city":"Frankfurt",
    "sg:postcode":"60529",
    "sg:province":"Hessen",
    "wof:name":"Reiki-spirit",
    "wof:placetype":"venue"
},
  "geometry": {"coordinates":[8.5816,50.087315],"type":"Point"}
}