{
  "type": "Feature",
  "properties": {
    "iso:country":"DE",
    "sg:address":"Orchheimer Str. 38",
    "sg:city":"Bad M\u00fcnstereifel",
    "sg:phone":"+49 2253/8599",
    "sg:postcode":"53902",
    "sg:province":"Nordrhein-Westfalen",
    "wof:name":"Karl Meyer",
    "wof:placetype":"venue"
},
  "geometry": {"coordinates":[6.762983799,50.5524597168],"type":"Point"}
}