{
  "type": "Feature",
  "properties": {
    "iso:country":"DE",
    "sg:address":"Elbestr. 39",
    "sg:city":"Hannover",
    "sg:phone":"+49 511/752711",
    "sg:postcode":"30419",
    "sg:province":"Niedersachsen",
    "wof:name":"Schwimmbad",
    "wof:placetype":"venue"
},
  "geometry": {"coordinates":[9.6790895462,52.3999023438],"type":"Point"}
}