{
  "type": "Feature",
  "properties": {
    "iso:country":"DE",
    "sg:address":"Am Nachtigallenw\u00e4ldchen 2",
    "sg:city":"Meppen",
    "sg:phone":"+49 5931/93580",
    "sg:postcode":"49716",
    "sg:province":"Niedersachsen",
    "wof:name":"Nieders. Land-gmbh Gemeinn. Unternehmen",
    "wof:placetype":"venue"
},
  "geometry": {"coordinates":[7.2986130714,52.6898651123],"type":"Point"}
}