{
  "type": "Feature",
  "properties": {
    "iso:country":"DE",
    "sg:address":"K\u00f6nigsdorfer Weg 6",
    "sg:city":"Geretsried",
    "sg:phone":"+49 8171/92850",
    "sg:postcode":"82538",
    "sg:province":"Bayern",
    "wof:name":"Huber Gmbh",
    "wof:placetype":"venue"
},
  "geometry": {"coordinates":[11.499441,47.849422],"type":"Point"}
}