{
  "type": "Feature",
  "properties": {
    "iso:country":"DE",
    "sg:address":"Rugestr 2",
    "sg:city":"Dresden",
    "sg:phone":"+49 351/4716650",
    "sg:postcode":"01069",
    "sg:province":"Sachsen",
    "wof:name":"Zeiko Computer Gmbh",
    "wof:placetype":"venue"
},
  "geometry": {"coordinates":[13.728791,51.034557],"type":"Point"}
}