{
  "type": "Feature",
  "properties": {
    "iso:country":"DE",
    "sg:address":"Ringstr. 6",
    "sg:city":"Boizenburg",
    "sg:phone":"+49 38847/50460",
    "sg:postcode":"19258",
    "sg:province":"Mecklenburg-Vorpommern",
    "wof:name":"Grimm & Ko\u00df Gmbh",
    "wof:placetype":"venue"
},
  "geometry": {"coordinates":[10.7656288147,53.3774299622],"type":"Point"}
}