{
  "type": "Feature",
  "properties": {
    "iso:country":"DE",
    "sg:address":"Lange Str. 84",
    "sg:city":"Lage",
    "sg:phone":"+49 5232/3153",
    "sg:postcode":"32791",
    "sg:province":"Nordrhein-Westfalen",
    "wof:name":"Bittner",
    "wof:placetype":"venue"
},
  "geometry": {"coordinates":[8.7937879562,51.9900817871],"type":"Point"}
}