{
  "type": "Feature",
  "properties": {
    "iso:country":"DE",
    "sg:address":"Vorm L\u00fcer 21",
    "sg:city":"Arnsberg",
    "sg:phone":"+49 2932/54110",
    "sg:postcode":"59757",
    "sg:province":"Nordrhein-Westfalen",
    "wof:name":"Maria Th. Pratt Industriebedarf",
    "wof:placetype":"venue"
},
  "geometry": {"coordinates":[7.918456,51.420166],"type":"Point"}
}