{
  "type": "Feature",
  "properties": {
    "iso:country":"DE",
    "sg:address":"Maubacher Str. 82",
    "sg:city":"Backnang",
    "sg:phone":"+49 7191/953418",
    "sg:postcode":"71522",
    "sg:province":"Baden-W\u00fcrttemberg",
    "wof:name":"Gerberst\u00fcble",
    "wof:placetype":"venue"
},
  "geometry": {"coordinates":[9.4294252396,48.9397125244],"type":"Point"}
}