{
  "type": "Feature",
  "properties": {
    "iso:country":"DE",
    "sg:address":"Markt 26-32",
    "sg:city":"Bonn",
    "sg:phone":"+49 228/604350",
    "sg:postcode":"53111",
    "sg:province":"Nordrhein-Westfalen",
    "wof:name":"Konicek Weber Und Partner Rechtsanw\u00e4lte",
    "wof:placetype":"venue"
},
  "geometry": {"coordinates":[7.1019392014,50.7357978821],"type":"Point"}
}