{
  "type": "Feature",
  "properties": {
    "iso:country":"DE",
    "sg:address":"Hohenauerstr. 7",
    "sg:city":"M\u00fchldorf",
    "sg:phone":"+49 8631/7733",
    "sg:postcode":"84453",
    "sg:province":"Bayern",
    "wof:name":"Optik Studio",
    "wof:placetype":"venue"
},
  "geometry": {"coordinates":[12.5268917084,48.2381439209],"type":"Point"}
}