{
  "type": "Feature",
  "properties": {
    "iso:country":"DE",
    "sg:address":"D\u00f6derleinstr.10",
    "sg:city":"M\u00fcnchen",
    "sg:phone":"+49 89/789338",
    "sg:postcode":"81369",
    "sg:province":"Bayern",
    "wof:name":"Holz,-metall-kunststoffbearbeitungsmaschinen",
    "wof:placetype":"venue"
},
  "geometry": {"coordinates":[11.527931,48.105209],"type":"Point"}
}