{
  "type": "Feature",
  "properties": {
    "iso:country":"DE",
    "sg:address":"Zwickauer Str. 12",
    "sg:city":"G\u00f6\u00dfnitz",
    "sg:phone":"+49 34493/30097",
    "sg:postcode":"04639",
    "sg:province":"Th\u00fcringen",
    "wof:name":"Junghardt Und Lang",
    "wof:placetype":"venue"
},
  "geometry": {"coordinates":[12.430811882,50.8866691589],"type":"Point"}
}