{
  "type": "Feature",
  "properties": {
    "iso:country":"DE",
    "sg:address":"Osterstr. 36",
    "sg:city":"Bremen",
    "sg:phone":"+49 421/508472",
    "sg:postcode":"28199",
    "sg:province":"Bremen",
    "wof:name":"Dobe",
    "wof:placetype":"venue"
},
  "geometry": {"coordinates":[8.7999601364,53.0725708008],"type":"Point"}
}