{
  "type": "Feature",
  "properties": {
    "iso:country":"DE",
    "sg:address":"August-Madsack-Str. 11",
    "sg:city":"Hannover",
    "sg:postcode":"30559",
    "sg:province":"Niedersachsen",
    "wof:name":"Beteiligungsges. Neue Zeitung Mbh & Co. Kg",
    "wof:placetype":"venue"
},
  "geometry": {"coordinates":[9.803808,52.350388],"type":"Point"}
}