{
  "type": "Feature",
  "properties": {
    "iso:country":"DE",
    "sg:address":"Vor den Teilen 109",
    "sg:city":"Ree\u00dfum",
    "sg:phone":"+49 4264/1420",
    "sg:postcode":"27367",
    "sg:province":"Niedersachsen",
    "wof:name":"Heinrich Cordes Fritz Kaldehofe Gmbh",
    "wof:placetype":"venue"
},
  "geometry": {"coordinates":[9.2057600021,53.1351318359],"type":"Point"}
}