{
  "type": "Feature",
  "properties": {
    "iso:country":"DE",
    "sg:address":"Winkelsweg 178",
    "sg:city":"Langenfeld",
    "sg:phone":"+49 2173",
    "sg:postcode":"40764",
    "sg:province":"Nordrhein-Westfalen",
    "wof:name":"Autofit Kfz Werkstatt Autotechnik H\u00e4nke",
    "wof:placetype":"venue"
},
  "geometry": {"coordinates":[6.9677228928,51.1284751892],"type":"Point"}
}