{
  "type": "Feature",
  "properties": {
    "iso:country":"DE",
    "sg:address":"Rimbachstr.",
    "sg:city":"Falkenberg",
    "sg:phone":"+49 8727/897",
    "sg:postcode":"84326",
    "sg:province":"Bayern",
    "wof:name":"Xaver Gruber",
    "wof:placetype":"venue"
},
  "geometry": {"coordinates":[12.700483,48.480297],"type":"Point"}
}