{
  "type": "Feature",
  "properties": {
    "iso:country":"DE",
    "sg:address":"Schlo\u00dfstr. 12",
    "sg:city":"Waldheim",
    "sg:phone":"+49 34327/93188",
    "sg:postcode":"04736",
    "sg:province":"Sachsen",
    "wof:name":"Annerose K\u00f6nig",
    "wof:placetype":"venue"
},
  "geometry": {"coordinates":[13.0266304016,51.0735816956],"type":"Point"}
}