{
  "type": "Feature",
  "properties": {
    "iso:country":"DE",
    "sg:address":"Birkenweg 19",
    "sg:city":"H\u00fcnfeld",
    "sg:phone":"+49 6652/3273",
    "sg:postcode":"36088",
    "sg:province":"Hessen",
    "wof:name":"Rudolf U. Elfriede Wehner",
    "wof:placetype":"venue"
},
  "geometry": {"coordinates":[9.781592,50.659672],"type":"Point"}
}