{
  "type": "Feature",
  "properties": {
    "iso:country":"DE",
    "sg:address":"Zeppelinstr. 34",
    "sg:city":"Zwickau",
    "sg:phone":"+49 375/474406",
    "sg:postcode":"08066",
    "sg:province":"Sachsen",
    "wof:name":"Floribunda Gmbh",
    "wof:placetype":"venue"
},
  "geometry": {"coordinates":[12.519369,50.731133],"type":"Point"}
}