{
  "type": "Feature",
  "properties": {
    "iso:country":"DE",
    "sg:address":"Habermannstr 3",
    "sg:city":"N\u00fcrnberg",
    "sg:phone":"+49 911/8888068",
    "sg:postcode":"90455",
    "sg:province":"Bayern",
    "wof:name":"Gerhard Meinel",
    "wof:placetype":"venue"
},
  "geometry": {"coordinates":[11.0949687958,49.3703651428],"type":"Point"}
}