{
  "type": "Feature",
  "properties": {
    "iso:country":"DE",
    "sg:address":"Geleitsstr. 24",
    "sg:city":"Offenbach",
    "sg:phone":"+49 69/8002453",
    "sg:postcode":"63065",
    "sg:province":"Hessen",
    "wof:name":"Rene Spalek",
    "wof:placetype":"venue"
},
  "geometry": {"coordinates":[8.7623224258,50.1031417847],"type":"Point"}
}