{
  "type": "Feature",
  "properties": {
    "iso:country":"DE",
    "sg:address":"Kom\u00f6dienstr. 37",
    "sg:city":"K\u00f6ln",
    "sg:phone":"+49 221/2575724",
    "sg:postcode":"50667",
    "sg:province":"Nordrhein-Westfalen",
    "wof:name":"Euro City F. Lal",
    "wof:placetype":"venue"
},
  "geometry": {"coordinates":[6.9545478821,50.9415130615],"type":"Point"}
}