{
  "type": "Feature",
  "properties": {
    "iso:country":"DE",
    "sg:address":"Marktstr. 66",
    "sg:city":"St. Leon-Rot",
    "sg:phone":"+49 6227/59579",
    "sg:postcode":"68789",
    "sg:province":"Baden-W\u00fcrttemberg",
    "wof:name":"G\u00fcnther Brecht",
    "wof:placetype":"venue"
},
  "geometry": {"coordinates":[8.599353,49.267426],"type":"Point"}
}