{
  "type": "Feature",
  "properties": {
    "iso:country":"DE",
    "sg:address":"Halberst\u00e4dter Str. 1",
    "sg:city":"Goslar",
    "sg:phone":"+49 5321/704424",
    "sg:postcode":"38644",
    "sg:province":"Niedersachsen",
    "wof:name":"Stadtentw\u00e4sserung Goslar Gmbh",
    "wof:placetype":"venue"
},
  "geometry": {"coordinates":[10.4932804108,51.9182510376],"type":"Point"}
}