{
  "type": "Feature",
  "properties": {
    "iso:country":"DE",
    "sg:address":"Neckargartacher Str. 94",
    "sg:city":"Heilbronn",
    "sg:phone":"+49 7131/477248",
    "sg:postcode":"74080",
    "sg:province":"Baden-W\u00fcrttemberg",
    "wof:name":"Optic Actuell Ag",
    "wof:placetype":"venue"
},
  "geometry": {"coordinates":[9.1964178085,49.1477012634],"type":"Point"}
}