{
  "type": "Feature",
  "properties": {
    "iso:country":"DE",
    "sg:address":"Gablenberger Hauptstr. 64",
    "sg:city":"Stuttgart",
    "sg:phone":"+49 711/4800535",
    "sg:postcode":"70186",
    "sg:province":"Baden-W\u00fcrttemberg",
    "wof:name":"Gablenberger Reiseb\u00fcro P. A. Schur",
    "wof:placetype":"venue"
},
  "geometry": {"coordinates":[9.2062244415,48.7778053284],"type":"Point"}
}