{
  "type": "Feature",
  "properties": {
    "iso:country":"DE",
    "sg:address":"Nienburger Str. 10",
    "sg:city":"Rehden",
    "sg:phone":"+49 5446/667",
    "sg:postcode":"49453",
    "sg:province":"Niedersachsen",
    "wof:name":"Gloddeck & Gies Gardinen Gmbh",
    "wof:placetype":"venue"
},
  "geometry": {"coordinates":[8.478966713,52.6103477478],"type":"Point"}
}