{
  "type": "Feature",
  "properties": {
    "iso:country":"DE",
    "sg:address":"Spitalstr. 9",
    "sg:city":"Gerolzhofen",
    "sg:phone":"+49 9382/7149",
    "sg:postcode":"97447",
    "sg:province":"Bayern",
    "wof:name":"Zur Traube",
    "wof:placetype":"venue"
},
  "geometry": {"coordinates":[10.3506765366,49.8999824524],"type":"Point"}
}