{
  "type": "Feature",
  "properties": {
    "iso:country":"DE",
    "sg:address":"Tumblingerstr. 32",
    "sg:city":"Muenchen",
    "sg:postcode":"80337",
    "sg:province":"Bayern",
    "wof:name":"Kiwi Tours",
    "wof:placetype":"venue"
},
  "geometry": {"coordinates":[11.557028,48.125542],"type":"Point"}
}