{
  "type": "Feature",
  "properties": {
    "iso:country":"DE",
    "sg:address":"Dr.-H\u00f6rmann-Str. 21",
    "sg:city":"Augsburg",
    "sg:phone":"+49 821/83253",
    "sg:postcode":"86179",
    "sg:province":"Bayern",
    "wof:name":"Johann Keim",
    "wof:placetype":"venue"
},
  "geometry": {"coordinates":[10.8994884491,48.3112068176],"type":"Point"}
}