{
  "type": "Feature",
  "properties": {
    "iso:country":"DE",
    "sg:address":"Am Hafen 2 a",
    "sg:city":"Kappeln",
    "sg:postcode":"24376",
    "sg:province":"Schleswig-Holstein",
    "wof:name":"Funk Taxi Michl E. K.",
    "wof:placetype":"venue"
},
  "geometry": {"coordinates":[9.9346904755,54.6613845825],"type":"Point"}
}