{
  "type": "Feature",
  "properties": {
    "iso:country":"DE",
    "sg:address":"Am Jagdhaus 116 a",
    "sg:city":"Wuppertal",
    "sg:phone":"+49 202/723005",
    "sg:postcode":"42113",
    "sg:province":"Nordrhein-Westfalen",
    "wof:name":"P. B\u00f6hm Steuerberater",
    "wof:placetype":"venue"
},
  "geometry": {"coordinates":[7.1041550636,51.2787780762],"type":"Point"}
}