{
  "type": "Feature",
  "properties": {
    "iso:country":"DE",
    "sg:address":"Stolzenfelsstr. 4a",
    "sg:city":"M\u00fcnchen",
    "sg:phone":"+49 89/74141272",
    "sg:postcode":"81375",
    "sg:province":"Bayern",
    "wof:name":"Manfred Paulus Ingenieur",
    "wof:placetype":"venue"
},
  "geometry": {"coordinates":[11.5005502701,48.1155548096],"type":"Point"}
}