{
  "type": "Feature",
  "properties": {
    "iso:country":"DE",
    "sg:address":"R\u00f6merstr. 11",
    "sg:city":"Neunkirchen",
    "sg:phone":"+49 9378/603",
    "sg:postcode":"63930",
    "sg:province":"Bayern",
    "wof:name":"Albert Berberich",
    "wof:placetype":"venue"
},
  "geometry": {"coordinates":[9.4017953873,49.7047042847],"type":"Point"}
}