{
  "type": "Feature",
  "properties": {
    "iso:country":"DE",
    "sg:address":"Von-Leoprechting-Str. 2 a",
    "sg:city":"Landsberg",
    "sg:postcode":"86899",
    "sg:province":"Bayern",
    "wof:name":"Stefan Neubauer Informations- Und Kommunikations-",
    "wof:placetype":"venue"
},
  "geometry": {"coordinates":[10.8810710907,48.0114326477],"type":"Point"}
}