{
  "type": "Feature",
  "properties": {
    "iso:country":"DE",
    "sg:address":"Enhofer Str 47",
    "sg:city":"Langenenslingen",
    "sg:phone":"+49 7376/96200",
    "sg:postcode":"88515",
    "sg:province":"Baden-W\u00fcrttemberg",
    "wof:name":"Rumpel",
    "wof:placetype":"venue"
},
  "geometry": {"coordinates":[9.3591451645,48.1342887878],"type":"Point"}
}