{
  "type": "Feature",
  "properties": {
    "iso:country":"DE",
    "sg:address":"Goethestr. 15 A",
    "sg:city":"Hannover",
    "sg:phone":"+49 511/39950",
    "sg:postcode":"30169",
    "sg:province":"Niedersachsen",
    "wof:name":"Trans Tec Beteiligungs- Und Managementgesellschaft Mbh",
    "wof:placetype":"venue"
},
  "geometry": {"coordinates":[9.7281303406,52.3740615845],"type":"Point"}
}