{
  "type": "Feature",
  "properties": {
    "iso:country":"DE",
    "sg:address":"Schanzenstr. 24",
    "sg:city":"K\u00f6ln",
    "sg:phone":"+49 221/6760",
    "sg:postcode":"51063",
    "sg:province":"Nordrhein-Westfalen",
    "wof:name":"Archiv Der Felten & Guilleaume",
    "wof:placetype":"venue"
},
  "geometry": {"coordinates":[7.01121,50.967854],"type":"Point"}
}