{
  "type": "Feature",
  "properties": {
    "iso:country":"DE",
    "sg:address":"Potsdamer Str. 87",
    "sg:city":"Bielefeld",
    "sg:phone":"+49 521/331837",
    "sg:postcode":"33719",
    "sg:province":"Nordrhein-Westfalen",
    "wof:name":"Heidbreder",
    "wof:placetype":"venue"
},
  "geometry": {"coordinates":[8.598043,52.01746],"type":"Point"}
}