{
  "type": "Feature",
  "properties": {
    "iso:country":"DE",
    "sg:address":"Zur Gro\u00dfenheide 9",
    "sg:city":"Stemwede",
    "sg:phone":"+49 5745/653",
    "sg:postcode":"32351",
    "sg:province":"Nordrhein-Westfalen",
    "wof:name":"Heinz Wellmann",
    "wof:placetype":"venue"
},
  "geometry": {"coordinates":[8.47374,52.389114],"type":"Point"}
}