{
  "type": "Feature",
  "properties": {
    "iso:country":"DE",
    "sg:address":"Schwarzer Weg 10",
    "sg:city":"Minden",
    "sg:phone":"+49 571/30887",
    "sg:postcode":"32423",
    "sg:province":"Nordrhein-Westfalen",
    "wof:name":"Ios Gmbh",
    "wof:placetype":"venue"
},
  "geometry": {"coordinates":[8.9323806763,52.2863769531],"type":"Point"}
}