{
  "type": "Feature",
  "properties": {
    "iso:country":"DE",
    "sg:address":"Alleestr. 27",
    "sg:city":"Bochum",
    "sg:phone":"+49 234/684024",
    "sg:postcode":"44793",
    "sg:province":"Nordrhein-Westfalen",
    "wof:name":"Deutscher Supermarkt Handels Gmbh",
    "wof:placetype":"venue"
},
  "geometry": {"coordinates":[7.2114257812,51.48097229],"type":"Point"}
}