{
  "type": "Feature",
  "properties": {
    "iso:country":"DE",
    "sg:address":"Bahnhofstr. 13",
    "sg:city":"Rheinberg",
    "sg:phone":"+49 2843/3013",
    "sg:postcode":"47495",
    "sg:province":"Nordrhein-Westfalen",
    "wof:name":"Volks- Und Raiffeisenbank Niederr., Eg",
    "wof:placetype":"venue"
},
  "geometry": {"coordinates":[6.597157,51.543354],"type":"Point"}
}