{
  "type": "Feature",
  "properties": {
    "iso:country":"DE",
    "sg:address":"Schmiedgasse 27",
    "sg:city":"Utzstetten",
    "sg:phone":"+49 7175/8779",
    "sg:postcode":"73577",
    "sg:province":"Baden-W\u00fcrttemberg",
    "wof:name":"Wilhelm Werner",
    "wof:placetype":"venue"
},
  "geometry": {"coordinates":[9.84759,48.865421],"type":"Point"}
}