{
  "type": "Feature",
  "properties": {
    "iso:country":"DE",
    "sg:address":"Johann-Friedrich-Str. 13",
    "sg:city":"Jena",
    "sg:phone":"+49 3641/615498",
    "sg:postcode":"07745",
    "sg:province":"Th\u00fcringen",
    "wof:name":"E. M\u00fcller Und Partner",
    "wof:placetype":"venue"
},
  "geometry": {"coordinates":[11.574139595,50.9281196594],"type":"Point"}
}