{
  "type": "Feature",
  "properties": {
    "iso:country":"DE",
    "sg:address":"Bahnhofstr. 7::",
    "sg:city":"Theisbergstegen",
    "sg:phone":"+49 4963/812072",
    "sg:postcode":"66871",
    "sg:province":"Rheinland-Pfalz",
    "wof:name":"Dietmar Kreutz",
    "wof:placetype":"venue"
},
  "geometry": {"coordinates":[7.447835,49.5191],"type":"Point"}
}