{
  "type": "Feature",
  "properties": {
    "iso:country":"DE",
    "sg:address":"Lindenstr. 47",
    "sg:city":"Monheim",
    "sg:postcode":"40789",
    "sg:province":"Nordrhein-Westfalen",
    "wof:name":"F. Wiegand",
    "wof:placetype":"venue"
},
  "geometry": {"coordinates":[6.8955907822,51.0953102112],"type":"Point"}
}