{
  "type": "Feature",
  "properties": {
    "iso:country":"DE",
    "sg:address":"Obere Marktstr. 2-4",
    "sg:city":"Gro\u00df-Umstadt",
    "sg:phone":"+49 6078/3422",
    "sg:postcode":"64823",
    "sg:province":"Hessen",
    "wof:name":"Ludwig Zimmer",
    "wof:placetype":"venue"
},
  "geometry": {"coordinates":[8.9286956787,49.8682174683],"type":"Point"}
}