{
  "type": "Feature",
  "properties": {
    "iso:country":"DE",
    "sg:address":"Grenzhofer Weg 21",
    "sg:city":"Mannheim",
    "sg:phone":"+49 621/474374",
    "sg:postcode":"68229",
    "sg:province":"Baden-W\u00fcrttemberg",
    "wof:name":"L. Kilian",
    "wof:placetype":"venue"
},
  "geometry": {"coordinates":[8.579729,49.432079],"type":"Point"}
}