{
  "type": "Feature",
  "properties": {
    "iso:country":"DE",
    "sg:address":"Donauweg 15",
    "sg:city":"K\u00f6ln",
    "sg:phone":"+49 221/486344",
    "sg:postcode":"50858",
    "sg:province":"Nordrhein-Westfalen",
    "wof:name":"Dr. Kurt Justen Rechtsanwalt",
    "wof:placetype":"venue"
},
  "geometry": {"coordinates":[6.863535881,50.9290428162],"type":"Point"}
}