{
  "type": "Feature",
  "properties": {
    "iso:country":"DE",
    "sg:address":"Seifartshofstr. 1",
    "sg:city":"Coburg",
    "sg:phone":"+49 9561/94440",
    "sg:postcode":"96450",
    "sg:province":"Bayern",
    "wof:name":"Raum Und Idee Roman Kirsch Gmbh",
    "wof:placetype":"venue"
},
  "geometry": {"coordinates":[10.964724,50.263401],"type":"Point"}
}