{
  "type": "Feature",
  "properties": {
    "iso:country":"DE",
    "sg:address":"In der Schmalnau 6",
    "sg:city":"Schmallenberg",
    "sg:phone":"+49 2972",
    "sg:postcode":"57392",
    "sg:province":"Nordrhein-Westfalen",
    "wof:name":"Cafe & Art - Einer F\u00fcr Alle F\u00e4lle",
    "wof:placetype":"venue"
},
  "geometry": {"coordinates":[8.320833,51.168835],"type":"Point"}
}