{
  "type": "Feature",
  "properties": {
    "iso:country":"DE",
    "sg:address":"Helbersdorfer Str. 44",
    "sg:city":"Chemnitz",
    "sg:postcode":"09120",
    "sg:province":"Sachsen",
    "wof:name":"Gvs-holding Gmbh",
    "wof:placetype":"venue"
},
  "geometry": {"coordinates":[12.897108,50.806446],"type":"Point"}
}