{
  "type": "Feature",
  "properties": {
    "iso:country":"DE",
    "sg:address":"Feldstr. 1",
    "sg:city":"Hambergen",
    "sg:phone":"+49 4793/1676",
    "sg:postcode":"27729",
    "sg:province":"Niedersachsen",
    "wof:name":"Bernhard Meyerhoff",
    "wof:placetype":"venue"
},
  "geometry": {"coordinates":[8.829154,53.310768],"type":"Point"}
}