{
  "type": "Feature",
  "properties": {
    "iso:country":"DE",
    "sg:address":"Wilhelmstr. 32",
    "sg:city":"Klingenberg",
    "sg:phone":"+49 9372/2115",
    "sg:postcode":"63911",
    "sg:province":"Bayern",
    "wof:name":"Kurt Heider",
    "wof:placetype":"venue"
},
  "geometry": {"coordinates":[9.183255,49.779491],"type":"Point"}
}