{
  "type": "Feature",
  "properties": {
    "iso:country":"DE",
    "sg:address":"Gerolzahner Str. 5",
    "sg:city":"Walld\u00fcrn",
    "sg:phone":"+49 6282/6627",
    "sg:postcode":"74731",
    "sg:province":"Baden-W\u00fcrttemberg",
    "wof:name":"Dorfst\u00fcble",
    "wof:placetype":"venue"
},
  "geometry": {"coordinates":[9.347776413,49.6218261719],"type":"Point"}
}