{
  "type": "Feature",
  "properties": {
    "iso:country":"DE",
    "sg:address":"Gutenbergstr. 3",
    "sg:city":"Gerlingen",
    "sg:postcode":"70839",
    "sg:province":"Baden-W\u00fcrttemberg",
    "wof:name":"Zebra Fashion Gmbh",
    "wof:placetype":"venue"
},
  "geometry": {"coordinates":[9.072952,48.807732],"type":"Point"}
}