{
  "type": "Feature",
  "properties": {
    "iso:country":"DE",
    "sg:address":"Emsteker Str. 14-16",
    "sg:city":"Cloppenburg",
    "sg:phone":"+49 4471/92930",
    "sg:postcode":"49661",
    "sg:province":"Niedersachsen",
    "wof:name":"Rwh Industrie- Automatisierung Gmbh",
    "wof:placetype":"venue"
},
  "geometry": {"coordinates":[8.049508,52.844032],"type":"Point"}
}