{
  "type": "Feature",
  "properties": {
    "iso:country":"DE",
    "sg:address":"An der Wuhlheide 189",
    "sg:city":"Berlin",
    "sg:postcode":"12459",
    "sg:province":"Berlin",
    "wof:name":"Berliner Parkeisenbahn Ggmbh",
    "wof:placetype":"venue"
},
  "geometry": {"coordinates":[13.5430574417,52.4579467773],"type":"Point"}
}