{
  "type": "Feature",
  "properties": {
    "iso:country":"DE",
    "sg:address":"Sch\u00f6nebecker Str. 57",
    "sg:city":"Wuppertal",
    "sg:phone":"+49 202/89391",
    "sg:postcode":"42283",
    "sg:province":"Nordrhein-Westfalen",
    "wof:name":"Mykonos Grill",
    "wof:placetype":"venue"
},
  "geometry": {"coordinates":[7.1793341637,51.2739868164],"type":"Point"}
}