{
  "type": "Feature",
  "properties": {
    "iso:country":"DE",
    "sg:address":"Bahnhofstr. 5",
    "sg:city":"Schee\u00dfel",
    "sg:phone":"+49 4263/3451",
    "sg:postcode":"27383",
    "sg:province":"Niedersachsen",
    "wof:name":"Andrea Haller Krankengymnastin",
    "wof:placetype":"venue"
},
  "geometry": {"coordinates":[9.483058,53.16814],"type":"Point"}
}