{
  "type": "Feature",
  "properties": {
    "iso:country":"DE",
    "sg:address":"Eichenweg 25",
    "sg:city":"Emsdetten",
    "sg:phone":"+49 2572/97621",
    "sg:postcode":"48282",
    "sg:province":"Nordrhein-Westfalen",
    "wof:name":"Dieter Wortmann",
    "wof:placetype":"venue"
},
  "geometry": {"coordinates":[7.552269,52.159191],"type":"Point"}
}