{
  "type": "Feature",
  "properties": {
    "iso:country":"DE",
    "sg:address":"Wilhelm-R\u00f6pke-Str. 60c",
    "sg:city":"Marburg",
    "sg:phone":"+49 6421/284566",
    "sg:postcode":"35039",
    "sg:province":"Hessen",
    "wof:name":"Lichtbildarchiv \u00c4lterer Originalurkunden",
    "wof:placetype":"venue"
},
  "geometry": {"coordinates":[8.77776,50.814941],"type":"Point"}
}