{
  "type": "Feature",
  "properties": {
    "iso:country":"DE",
    "sg:address":"Elsa-Br\u00e4ndstr\u00f6m-Str. 17",
    "sg:city":"Freiburg",
    "sg:phone":"+49 761/43243",
    "sg:postcode":"79111",
    "sg:province":"Baden-W\u00fcrttemberg",
    "wof:name":"Walter Kettner Architekt",
    "wof:placetype":"venue"
},
  "geometry": {"coordinates":[7.812459,47.980072],"type":"Point"}
}