{
  "type": "Feature",
  "properties": {
    "iso:country":"DE",
    "sg:address":"Rektor-Block-Str. 7",
    "sg:city":"Merseburg",
    "sg:phone":"+49 3461/210275",
    "sg:postcode":"06217",
    "sg:province":"Sachsen-Anhalt",
    "wof:name":"Elektro-service Inh. Fritz Schmeisser",
    "wof:placetype":"venue"
},
  "geometry": {"coordinates":[11.984459,51.353912],"type":"Point"}
}