{
  "type": "Feature",
  "properties": {
    "iso:country":"DE",
    "sg:address":"Alfons-Hundsrucker-Str. 11",
    "sg:city":"Bad Birnbach",
    "sg:phone":"+49 8563/1314",
    "sg:postcode":"84364",
    "sg:province":"Bayern",
    "wof:name":"Arc Architekturb\u00fcro",
    "wof:placetype":"venue"
},
  "geometry": {"coordinates":[13.036472,48.453999],"type":"Point"}
}