{
  "type": "Feature",
  "properties": {
    "iso:country":"DE",
    "sg:address":"Dammheider Str. 67",
    "sg:city":"Herford",
    "sg:phone":"+49 5221/7740",
    "sg:postcode":"32052",
    "sg:province":"Nordrhein-Westfalen",
    "wof:name":"Jab Teppiche Heinz Anstoetz",
    "wof:placetype":"venue"
},
  "geometry": {"coordinates":[8.6478748322,52.0683441162],"type":"Point"}
}