{
  "type": "Feature",
  "properties": {
    "iso:country":"DE",
    "sg:address":"Hugenkotten 17",
    "sg:city":"Dinklage",
    "sg:phone":"+49 4443/4322",
    "sg:postcode":"49413",
    "sg:province":"Niedersachsen",
    "wof:name":"Willy Niemann",
    "wof:placetype":"venue"
},
  "geometry": {"coordinates":[8.1218309402,52.6669464111],"type":"Point"}
}