{
  "type": "Feature",
  "properties": {
    "iso:country":"DE",
    "sg:address":"August-L\u00e4mmle-Weg 2",
    "sg:city":"Stuttgart",
    "sg:phone":"+49 711/533691",
    "sg:postcode":"70374",
    "sg:province":"Baden-W\u00fcrttemberg",
    "wof:name":"J\u00fcrgen Burger",
    "wof:placetype":"venue"
},
  "geometry": {"coordinates":[9.231751442,48.8183174133],"type":"Point"}
}