{
  "type": "Feature",
  "properties": {
    "iso:country":"DE",
    "sg:address":"Nienburger Str. 4",
    "sg:city":"Hannover",
    "sg:phone":"+49 511/7622572",
    "sg:postcode":"30167",
    "sg:province":"Niedersachsen",
    "wof:name":"Redaktion Mitteilungen Des Franzius-inst. F. Wasserbau U.",
    "wof:placetype":"venue"
},
  "geometry": {"coordinates":[9.7117509842,52.3859596252],"type":"Point"}
}