{
  "type": "Feature",
  "properties": {
    "iso:country":"DE",
    "sg:address":"Rheinstr.",
    "sg:city":"Berlin",
    "sg:phone":"+49 30/85999477",
    "sg:postcode":"12159",
    "sg:province":"Berlin",
    "wof:name":"Dr. Heinemann Diamond Tools",
    "wof:placetype":"venue"
},
  "geometry": {"coordinates":[13.3357200623,52.4720115662],"type":"Point"}
}