{
  "type": "Feature",
  "properties": {
    "iso:country":"DE",
    "sg:address":"Forchenweg 5",
    "sg:city":"Leonberg",
    "sg:phone":"+49 7152/45570",
    "sg:postcode":"71229",
    "sg:province":"Baden-W\u00fcrttemberg",
    "wof:name":"Werner Sparn Steuerberater",
    "wof:placetype":"venue"
},
  "geometry": {"coordinates":[8.9819478989,48.7676010132],"type":"Point"}
}