{
  "type": "Feature",
  "properties": {
    "iso:country":"DE",
    "sg:address":"Sebastianstr. 137",
    "sg:city":"Bad Neuenahr-Ahrweiler",
    "sg:phone":"+49 2641/4530",
    "sg:postcode":"53474",
    "sg:province":"Rheinland-Pfalz",
    "wof:name":"Kontakt Beteiligungs- Und Verwaltungs-gmbh",
    "wof:placetype":"venue"
},
  "geometry": {"coordinates":[7.12102,50.545269],"type":"Point"}
}