{
  "type": "Feature",
  "properties": {
    "iso:country":"DE",
    "sg:address":"Stader Str. 26",
    "sg:city":"Horneburg",
    "sg:phone":"+49 4163/4840",
    "sg:postcode":"21640",
    "sg:province":"Niedersachsen",
    "wof:name":"Leichlaken-verein E. V. Karl Kleinert",
    "wof:placetype":"venue"
},
  "geometry": {"coordinates":[9.5707330704,53.5149230957],"type":"Point"}
}