{
  "type": "Feature",
  "properties": {
    "iso:country":"DE",
    "sg:address":"Florian-Seidl-Str. 1",
    "sg:city":"Regensburg",
    "sg:postcode":"93053",
    "sg:province":"Bayern",
    "wof:name":"Aldi Gmbh & Co. Kg",
    "wof:placetype":"venue"
},
  "geometry": {"coordinates":[12.1030464172,48.9835700989],"type":"Point"}
}