{
  "type": "Feature",
  "properties": {
    "iso:country":"DE",
    "sg:address":"Honschaftsstr 318",
    "sg:city":"K\u00f6ln",
    "sg:phone":"+49 221/9635530",
    "sg:postcode":"51061",
    "sg:province":"Nordrhein-Westfalen",
    "wof:name":"Frappant Gastronomie Gmbh",
    "wof:placetype":"venue"
},
  "geometry": {"coordinates":[7.031975,50.983273],"type":"Point"}
}