{
  "type": "Feature",
  "properties": {
    "iso:country":"DE",
    "sg:address":"Rheydter Str. 70",
    "sg:city":"Grevenbroich",
    "sg:phone":"+49 2182/3583",
    "sg:postcode":"41515",
    "sg:province":"Nordrhein-Westfalen",
    "wof:name":"Gira Com E. K.",
    "wof:placetype":"venue"
},
  "geometry": {"coordinates":[6.576622963,51.0914993286],"type":"Point"}
}