{
  "type": "Feature",
  "properties": {
    "iso:country":"DE",
    "sg:address":"Pestalozzistr. 20",
    "sg:city":"Neukirchen",
    "sg:phone":"+49 3762/49239",
    "sg:postcode":"08459",
    "sg:province":"Sachsen",
    "wof:name":"Gottfried Falke",
    "wof:placetype":"venue"
},
  "geometry": {"coordinates":[12.379576,50.797318],"type":"Point"}
}