{
  "type": "Feature",
  "properties": {
    "iso:country":"DE",
    "sg:address":"Dorfstr. 77",
    "sg:city":"Westerdeichstrich",
    "sg:phone":"+49 4834/2932",
    "sg:postcode":"25761",
    "sg:province":"Schleswig-Holstein",
    "wof:name":"Haus Freiberg",
    "wof:placetype":"venue"
},
  "geometry": {"coordinates":[8.8614864349,54.1615104675],"type":"Point"}
}