{
  "type": "Feature",
  "properties": {
    "iso:country":"DE",
    "sg:address":"Bortsh\u00e4user Str. 26",
    "sg:city":"Ebsdorfergrund",
    "sg:phone":"+49 6424/923950",
    "sg:postcode":"35085",
    "sg:province":"Hessen",
    "wof:name":"Karl-horst Lemmer",
    "wof:placetype":"venue"
},
  "geometry": {"coordinates":[8.8115558624,50.7342643738],"type":"Point"}
}