{
  "type": "Feature",
  "properties": {
    "iso:country":"DE",
    "sg:address":"Konrad-Adenauer-Allee 65",
    "sg:city":"Augsburg",
    "sg:phone":"+49 821/519247",
    "sg:postcode":"86150",
    "sg:province":"Bayern",
    "wof:name":"Bismarck-apotheke",
    "wof:placetype":"venue"
},
  "geometry": {"coordinates":[10.897858,48.360462],"type":"Point"}
}