{
  "type": "Feature",
  "properties": {
    "iso:country":"DE",
    "sg:address":"August-Bebel-Str. 11a",
    "sg:city":"Glauchau",
    "sg:phone":"+49 3763/40910",
    "sg:postcode":"08371",
    "sg:province":"Sachsen",
    "wof:name":"Christian Metzeroth Gmbh",
    "wof:placetype":"venue"
},
  "geometry": {"coordinates":[12.545301,50.822124],"type":"Point"}
}