{
  "type": "Feature",
  "properties": {
    "iso:country":"DE",
    "sg:address":"Osterbrooksweg 35-45",
    "sg:city":"Schenefeld",
    "sg:phone":"+49 40/83940",
    "sg:postcode":"22869",
    "sg:province":"Schleswig-Holstein",
    "wof:name":"Spar Inkassokontor Gmbh & Co. Kg",
    "wof:placetype":"venue"
},
  "geometry": {"coordinates":[9.8364362717,53.5961227417],"type":"Point"}
}