{
  "type": "Feature",
  "properties": {
    "iso:country":"DE",
    "sg:address":"Rauhh\u00f6lterberg 18",
    "sg:city":"Essen",
    "sg:phone":"+49 201/501930",
    "sg:postcode":"45276",
    "sg:province":"Nordrhein-Westfalen",
    "wof:name":"Winfried Kliemann",
    "wof:placetype":"venue"
},
  "geometry": {"coordinates":[7.086778,51.447437],"type":"Point"}
}