{
  "type": "Feature",
  "properties": {
    "iso:country":"DE",
    "sg:address":"Fontanestr. 16",
    "sg:city":"Willich",
    "sg:phone":"+49 2154/951515",
    "sg:postcode":"47877",
    "sg:province":"Nordrhein-Westfalen",
    "wof:name":"Hotel An Der Atlaszeder",
    "wof:placetype":"venue"
},
  "geometry": {"coordinates":[6.535255909,51.2449035645],"type":"Point"}
}