{
  "type": "Feature",
  "properties": {
    "iso:country":"DE",
    "sg:address":"Ahlweg 1",
    "sg:city":"Albbruck",
    "sg:phone":"+49 7753/2743",
    "sg:postcode":"79774",
    "sg:province":"Baden-W\u00fcrttemberg",
    "wof:name":"A.+ T. Amann",
    "wof:placetype":"venue"
},
  "geometry": {"coordinates":[8.1485834122,47.624458313],"type":"Point"}
}