{
  "type": "Feature",
  "properties": {
    "iso:country":"DE",
    "sg:address":"W\u00f6rthstr. 15 - 17",
    "sg:city":"K\u00f6ln",
    "sg:phone":"+49 221/77680",
    "sg:postcode":"50668",
    "sg:province":"Nordrhein-Westfalen",
    "wof:name":"Bank F\u00fcr Gemeinwirtschaft, Office Of Berlin",
    "wof:placetype":"venue"
},
  "geometry": {"coordinates":[6.967295,50.952282],"type":"Point"}
}