{
  "type": "Feature",
  "properties": {
    "iso:country":"DE",
    "sg:address":"Postfach 9:: 64847 Schaafheim:: Germany.^^Wilhelm-Leuschner Str 12-14::",
    "sg:city":"Schaafheim",
    "sg:phone":"+49 6073/74110",
    "sg:postcode":"64850",
    "sg:province":"Hessen",
    "wof:name":"Raiffeisenbank Schaafheim Eg",
    "wof:placetype":"venue"
},
  "geometry": {"coordinates":[9.007588,49.921417],"type":"Point"}
}