{
  "type": "Feature",
  "properties": {
    "iso:country":"DE",
    "sg:address":"Ring 37",
    "sg:city":"M\u00f6mbris",
    "sg:phone":"+49 6029/4764",
    "sg:postcode":"63776",
    "sg:province":"Bayern",
    "wof:name":"G. M\u00fcller Und U. Kolb Architekten",
    "wof:placetype":"venue"
},
  "geometry": {"coordinates":[9.165664,50.066204],"type":"Point"}
}