{
  "type": "Feature",
  "properties": {
    "iso:country":"DE",
    "sg:address":"Stra\u00dfe der Einheit 126a",
    "sg:city":"Uder",
    "sg:phone":"+49 36083/42207",
    "sg:postcode":"37318",
    "sg:province":"Th\u00fcringen",
    "wof:name":"B. M\u00fcller",
    "wof:placetype":"venue"
},
  "geometry": {"coordinates":[10.063075,51.365307],"type":"Point"}
}