{
  "type": "Feature",
  "properties": {
    "iso:country":"DE",
    "sg:address":"Isarstr. 36",
    "sg:city":"N\u00fcrnberg",
    "sg:phone":"+49 911/963480",
    "sg:postcode":"90451",
    "sg:province":"Bayern",
    "wof:name":"Konrad Wirner Tabakwarengro\u00dfhandel",
    "wof:placetype":"venue"
},
  "geometry": {"coordinates":[11.0558071136,49.4081840515],"type":"Point"}
}