{
  "type": "Feature",
  "properties": {
    "iso:country":"DE",
    "sg:address":"Eichenweg 17",
    "sg:city":"Eppstein",
    "sg:phone":"+49 6198/9639",
    "sg:postcode":"65817",
    "sg:province":"Hessen",
    "wof:name":"Dietrich Reinke",
    "wof:placetype":"venue"
},
  "geometry": {"coordinates":[8.3819637299,50.1489448547],"type":"Point"}
}