{
  "type": "Feature",
  "properties": {
    "iso:country":"DE",
    "sg:address":"Tellkoppenstr. 7",
    "sg:city":"Altenberg",
    "sg:phone":"+49 35052/27055",
    "sg:postcode":"01773",
    "sg:province":"Sachsen",
    "wof:name":"G\u00e4stehaus S. Krumpolt",
    "wof:placetype":"venue"
},
  "geometry": {"coordinates":[13.6774454117,50.8035697937],"type":"Point"}
}