{
  "type": "Feature",
  "properties": {
    "iso:country":"DE",
    "sg:address":"Rosenweg 10",
    "sg:city":"Emerkingen",
    "sg:phone":"+49 7393/4350",
    "sg:postcode":"89607",
    "sg:province":"Baden-W\u00fcrttemberg",
    "wof:name":"Kellner",
    "wof:placetype":"venue"
},
  "geometry": {"coordinates":[9.6538267136,48.2121810913],"type":"Point"}
}