{
  "type": "Feature",
  "properties": {
    "iso:country":"DE",
    "sg:address":"Elbseestr.",
    "sg:city":"Aitrang",
    "sg:postcode":"87648",
    "sg:province":"Bayern",
    "wof:name":"Elbsee Bootsverleih",
    "wof:placetype":"venue"
},
  "geometry": {"coordinates":[10.5373020172,47.816493988],"type":"Point"}
}