{
  "type": "Feature",
  "properties": {
    "iso:country":"DE",
    "sg:city":"S\u00fcdergellersen",
    "sg:postcode":"21394",
    "sg:province":"Niedersachsen",
    "wof:name":"Wittco - Schlepper/traktoren Zubeh\u00f6r",
    "wof:placetype":"venue"
},
  "geometry": {"coordinates":[10.297443,53.213699],"type":"Point"}
}