{
  "type": "Feature",
  "properties": {
    "iso:country":"DE",
    "sg:address":"Lorenz-Hutschenreuther-Str. 71",
    "sg:city":"Selb",
    "sg:phone":"+49 9287/2080",
    "sg:postcode":"95100",
    "sg:province":"Bayern",
    "wof:name":"Florenz Michaelis",
    "wof:placetype":"venue"
},
  "geometry": {"coordinates":[12.14252,50.168789],"type":"Point"}
}