{
  "type": "Feature",
  "properties": {
    "iso:country":"DE",
    "sg:address":"Johann-Sebastian-Bach-Str. 26",
    "sg:city":"Einhausen",
    "sg:phone":"+49 6251/51837",
    "sg:postcode":"64683",
    "sg:province":"Hessen",
    "wof:name":"Margarete Steinmetz Masseurin",
    "wof:placetype":"venue"
},
  "geometry": {"coordinates":[8.552253,49.668388],"type":"Point"}
}