{
  "type": "Feature",
  "properties": {
    "iso:country":"DE",
    "sg:address":"K\u00f6nigsberger Str. 8",
    "sg:city":"Berlin",
    "sg:phone":"+49 30/7724018",
    "sg:postcode":"12207",
    "sg:province":"Berlin",
    "wof:name":"Deutsche Shell Ag",
    "wof:placetype":"venue"
},
  "geometry": {"coordinates":[13.3217763901,52.4295921326],"type":"Point"}
}