{
  "type": "Feature",
  "properties": {
    "iso:country":"DE",
    "sg:address":"Selligstr. 22",
    "sg:city":"Schifferstadt",
    "sg:phone":"+49 6235/5895",
    "sg:postcode":"67105",
    "sg:province":"Rheinland-Pfalz",
    "wof:name":"Wilfried Schw\u00e4ger Gmbh",
    "wof:placetype":"venue"
},
  "geometry": {"coordinates":[8.3837690353,49.3826751709],"type":"Point"}
}