{
  "type": "Feature",
  "properties": {
    "iso:country":"DE",
    "sg:address":"Westerfilder Str. 62",
    "sg:city":"Dortmund",
    "sg:phone":"+49 231/357080",
    "sg:postcode":"44357",
    "sg:province":"Nordrhein-Westfalen",
    "wof:name":"Hemker",
    "wof:placetype":"venue"
},
  "geometry": {"coordinates":[7.378347,51.546566],"type":"Point"}
}