{
  "type": "Feature",
  "properties": {
    "iso:country":"DE",
    "sg:address":"Nimrodstr. 10-18",
    "sg:city":"N\u00fcrnberg",
    "sg:phone":"+49 911/41200",
    "sg:postcode":"90441",
    "sg:province":"Bayern",
    "wof:name":"Geyer Ag",
    "wof:placetype":"venue"
},
  "geometry": {"coordinates":[11.06707,49.423298],"type":"Point"}
}