{
  "type": "Feature",
  "properties": {
    "iso:country":"DE",
    "sg:address":"Alt-Haarener Str. 64",
    "sg:city":"Aachen",
    "sg:phone":"+49 241/165536",
    "sg:postcode":"52080",
    "sg:province":"Nordrhein-Westfalen",
    "wof:name":"A. Palmen",
    "wof:placetype":"venue"
},
  "geometry": {"coordinates":[6.1262979507,50.7953643799],"type":"Point"}
}