{
  "type": "Feature",
  "properties": {
    "iso:country":"DE",
    "sg:address":"Marie-Bernays-Ring 11",
    "sg:city":"M\u00f6nchengladbach",
    "sg:phone":"+49 2166/623100",
    "sg:postcode":"41199",
    "sg:province":"Nordrhein-Westfalen",
    "wof:name":"System Tec Maschinenservice Gmbh",
    "wof:placetype":"venue"
},
  "geometry": {"coordinates":[6.4365959167,51.1217575073],"type":"Point"}
}