{
  "type": "Feature",
  "properties": {
    "iso:country":"DE",
    "sg:address":"Albert-Viertel-Stra\u00dfe 10",
    "sg:city":"Burgst\u00e4dt/GIP",
    "sg:phone":"+49 3724",
    "sg:postcode":"09217",
    "sg:province":"Sachsen",
    "wof:name":"Bestsellers",
    "wof:placetype":"venue"
},
  "geometry": {"coordinates":[12.813824,50.899059],"type":"Point"}
}