{
  "type": "Feature",
  "properties": {
    "iso:country":"DE",
    "sg:address":"Johanniswall 3",
    "sg:city":"Hamburg",
    "sg:phone":"+49 40/336303",
    "sg:postcode":"20095",
    "sg:province":"Hamburg",
    "wof:name":"Antiquariat Bernhardt See- Und Luftfahrt Zeitgesch.",
    "wof:placetype":"venue"
},
  "geometry": {"coordinates":[10.005206,53.549171],"type":"Point"}
}