{
  "type": "Feature",
  "properties": {
    "iso:country":"DE",
    "sg:address":"Johann-Sebastian-Bach-Str. 51",
    "sg:city":"Bammental",
    "sg:phone":"+49 6223/40316",
    "sg:postcode":"69245",
    "sg:province":"Baden-W\u00fcrttemberg",
    "wof:name":"Volkmar B\u00fchrlein Architekt",
    "wof:placetype":"venue"
},
  "geometry": {"coordinates":[8.786607,49.353649],"type":"Point"}
}