{
  "type": "Feature",
  "properties": {
    "iso:country":"DE",
    "sg:address":"Guldenbachstr. 7",
    "sg:city":"K\u00f6ln",
    "sg:phone":"+49 221/4301053",
    "sg:postcode":"50935",
    "sg:province":"Nordrhein-Westfalen",
    "wof:name":"Joachim Bacht Steuerberater",
    "wof:placetype":"venue"
},
  "geometry": {"coordinates":[6.9078001976,50.9137916565],"type":"Point"}
}