{
  "type": "Feature",
  "properties": {
    "iso:country":"DE",
    "sg:address":"Engersche Str. 135",
    "sg:city":"Bielefeld",
    "sg:phone":"+49 521/81987",
    "sg:postcode":"33611",
    "sg:province":"Nordrhein-Westfalen",
    "wof:name":"T Und M Elektronik Verwaltungs Gmbh",
    "wof:placetype":"venue"
},
  "geometry": {"coordinates":[8.5514297485,52.0545463562],"type":"Point"}
}