{
  "type": "Feature",
  "properties": {
    "iso:country":"DE",
    "sg:address":"Reiterstr. 2",
    "sg:city":"Landau",
    "sg:phone":"+49 6341/82025",
    "sg:postcode":"76829",
    "sg:province":"Rheinland-Pfalz",
    "wof:name":"K. Wagenf\u00fchrer T. Baitinger Und",
    "wof:placetype":"venue"
},
  "geometry": {"coordinates":[8.1112575531,49.1949882507],"type":"Point"}
}