{
  "type": "Feature",
  "properties": {
    "iso:country":"DE",
    "sg:address":"Zum Hermannsberg 26",
    "sg:city":"Frankenberg",
    "sg:phone":"+49 6451/24398",
    "sg:postcode":"35066",
    "sg:province":"Hessen",
    "wof:name":"Prilink Netzwerkl\u00f6sungen E. K.",
    "wof:placetype":"venue"
},
  "geometry": {"coordinates":[8.821112,51.10601],"type":"Point"}
}