{
  "type": "Feature",
  "properties": {
    "iso:country":"DE",
    "sg:address":"Falkenberg",
    "sg:city":"Falkenberg",
    "sg:postcode":"95685",
    "sg:province":"Bayern",
    "wof:name":"Raiffeisenbank Falkenberg Eg",
    "wof:placetype":"venue"
},
  "geometry": {"coordinates":[13.2362,51.588242],"type":"Point"}
}