{
  "type": "Feature",
  "properties": {
    "iso:country":"DE",
    "sg:address":"Bahnhofstr. 9",
    "sg:city":"Paderborn",
    "sg:phone":"+49 5251/23567",
    "sg:postcode":"33102",
    "sg:province":"Nordrhein-Westfalen",
    "wof:name":"Itm Informationstechnik Moch Gmbh",
    "wof:placetype":"venue"
},
  "geometry": {"coordinates":[8.744054,51.714531],"type":"Point"}
}