{
  "type": "Feature",
  "properties": {
    "iso:country":"DE",
    "sg:address":"Hornbacher Str. 42",
    "sg:city":"Walld\u00fcrn",
    "sg:phone":"+49 6282/7424",
    "sg:postcode":"74731",
    "sg:province":"Baden-W\u00fcrttemberg",
    "wof:name":"Leis Gmbh",
    "wof:placetype":"venue"
},
  "geometry": {"coordinates":[9.34896,49.582539],"type":"Point"}
}