{
  "type": "Feature",
  "properties": {
    "iso:country":"DE",
    "sg:address":"Im Harsewinkel 24",
    "sg:city":"Dorsten",
    "sg:phone":"+49 2362/75677",
    "sg:postcode":"46284",
    "sg:province":"Nordrhein-Westfalen",
    "wof:name":"Gl\u00fcckauf-apotheke",
    "wof:placetype":"venue"
},
  "geometry": {"coordinates":[6.980806,51.668701],"type":"Point"}
}