{
  "type": "Feature",
  "properties": {
    "iso:country":"DE",
    "sg:address":"Loher Str. 52",
    "sg:city":"Hamburg",
    "sg:phone":"+49 40/6720384",
    "sg:postcode":"22149",
    "sg:province":"Hamburg",
    "wof:name":"Friedrich W\u00e4ger",
    "wof:placetype":"venue"
},
  "geometry": {"coordinates":[10.1387262344,53.5941085815],"type":"Point"}
}