{
  "type": "Feature",
  "properties": {
    "iso:country":"DE",
    "sg:address":"Dorfstr. 14",
    "sg:city":"Wetter",
    "sg:phone":"+49 6423/7529",
    "sg:postcode":"35083",
    "sg:province":"Hessen",
    "wof:name":"Heinrich Gimbel",
    "wof:placetype":"venue"
},
  "geometry": {"coordinates":[8.743697,50.889194],"type":"Point"}
}