{
  "type": "Feature",
  "properties": {
    "iso:country":"DE",
    "sg:address":"Flurstr. 2",
    "sg:city":"Ennepetal",
    "sg:postcode":"58256",
    "sg:province":"Nordrhein-Westfalen",
    "wof:name":"Ibh Beratungsdienst- Leistungs Gmbh",
    "wof:placetype":"venue"
},
  "geometry": {"coordinates":[7.3892478943,51.3058242798],"type":"Point"}
}