{
  "type": "Feature",
  "properties": {
    "iso:country":"DE",
    "sg:address":"Am Schie\u00dfstand 56",
    "sg:city":"Fredenbeck",
    "sg:phone":"+49 4149/8084",
    "sg:postcode":"21717",
    "sg:province":"Niedersachsen",
    "wof:name":"Ftg Tankschiffahrts Gmbh",
    "wof:placetype":"venue"
},
  "geometry": {"coordinates":[9.4123878479,53.4988594055],"type":"Point"}
}