{
  "type": "Feature",
  "properties": {
    "iso:country":"DE",
    "sg:address":"Teichstr. 3",
    "sg:city":"Leitzkau",
    "sg:phone":"+49 39241/385",
    "sg:postcode":"39279",
    "sg:province":"Sachsen-Anhalt",
    "wof:name":"Helmut Walther",
    "wof:placetype":"venue"
},
  "geometry": {"coordinates":[11.954961,52.055893],"type":"Point"}
}