{
  "type": "Feature",
  "properties": {
    "iso:country":"DE",
    "sg:address":"S\u00fcchtelner Str. 30",
    "sg:city":"M\u00f6nchengladbach",
    "sg:phone":"+49 2161/184848",
    "sg:postcode":"41066",
    "sg:province":"Nordrhein-Westfalen",
    "wof:name":"Teddy M\u00f6bel Sb-abholmarkt Gmbh",
    "wof:placetype":"venue"
},
  "geometry": {"coordinates":[6.459351,51.212353],"type":"Point"}
}