{
  "type": "Feature",
  "properties": {
    "iso:country":"DE",
    "sg:address":"Neuenweger Reihe 19",
    "sg:city":"Hude",
    "sg:phone":"+49 4484/704",
    "sg:postcode":"27798",
    "sg:province":"Niedersachsen",
    "wof:name":"Hans-gerd Oetken",
    "wof:placetype":"venue"
},
  "geometry": {"coordinates":[8.326438,53.121262],"type":"Point"}
}