{
  "type": "Feature",
  "properties": {
    "iso:country":"DE",
    "sg:address":"Zum Braken 46",
    "sg:city":"Lehrte",
    "sg:phone":"+49 5136/895656",
    "sg:postcode":"31275",
    "sg:province":"Niedersachsen",
    "wof:name":"Andreas Schmidt",
    "wof:placetype":"venue"
},
  "geometry": {"coordinates":[9.9961748123,52.4082107544],"type":"Point"}
}