{
  "type": "Feature",
  "properties": {
    "iso:country":"DE",
    "sg:address":"Zum Wei\u00dfen Berg 6",
    "sg:city":"Petershagen",
    "sg:phone":"+49 5768/423",
    "sg:postcode":"32469",
    "sg:province":"Nordrhein-Westfalen",
    "wof:name":"Michael Nordmeyer",
    "wof:placetype":"venue"
},
  "geometry": {"coordinates":[9.097479,52.473923],"type":"Point"}
}