{
  "type": "Feature",
  "properties": {
    "iso:country":"DE",
    "sg:address":"Am Bahnhof 3",
    "sg:city":"Th\u00fcngen",
    "sg:postcode":"97289",
    "sg:province":"Bayern",
    "wof:name":"Schmitter Group Ag",
    "wof:placetype":"venue"
},
  "geometry": {"coordinates":[9.8553638458,49.9405784607],"type":"Point"}
}