{
  "type": "Feature",
  "properties": {
    "iso:country":"DE",
    "sg:address":"Turiner Str.34 c/o Iris Domanski",
    "sg:city":"Berlin",
    "sg:phone":"+49 30",
    "sg:postcode":"13347",
    "sg:province":"Berlin",
    "wof:name":"Chance2001",
    "wof:placetype":"venue"
},
  "geometry": {"coordinates":[13.36496,52.547932],"type":"Point"}
}