{
  "type": "Feature",
  "properties": {
    "iso:country":"DE",
    "sg:address":"Hohe Str. 8",
    "sg:city":"Gerbstedt",
    "sg:phone":"+49 34783/29530",
    "sg:postcode":"06347",
    "sg:province":"Sachsen-Anhalt",
    "wof:name":"Hans-j\u00fcrgen Lummel",
    "wof:placetype":"venue"
},
  "geometry": {"coordinates":[11.6265554428,51.6325454712],"type":"Point"}
}