{
  "type": "Feature",
  "properties": {
    "iso:country":"DE",
    "sg:address":"Ebertplatz 21",
    "sg:city":"K\u00f6ln",
    "sg:phone":"+49 221/9126890",
    "sg:postcode":"50668",
    "sg:province":"Nordrhein-Westfalen",
    "wof:name":"Edv U. Medien Gesellschaft F\u00fcr Datenverarbeitung Mbh",
    "wof:placetype":"venue"
},
  "geometry": {"coordinates":[6.9583120346,50.9510993958],"type":"Point"}
}