{
  "type": "Feature",
  "properties": {
    "iso:country":"DE",
    "sg:address":"D\u00f6belner Str. 7",
    "sg:city":"Gro\u00dfweitzschen",
    "sg:postcode":"04720",
    "sg:province":"Sachsen",
    "wof:name":"Iqbal Systeme Gmbh & Co. Kg",
    "wof:placetype":"venue"
},
  "geometry": {"coordinates":[13.080812,51.162975],"type":"Point"}
}