{
  "type": "Feature",
  "properties": {
    "iso:country":"DE",
    "sg:address":"Endenicher Allee 35",
    "sg:city":"Bonn",
    "sg:phone":"+49 228/616142",
    "sg:postcode":"53121",
    "sg:province":"Nordrhein-Westfalen",
    "wof:name":"Rheinlandfrucht Rheinische Fr\u00fcchte Gmbh",
    "wof:placetype":"venue"
},
  "geometry": {"coordinates":[7.0802650452,50.7264480591],"type":"Point"}
}