{
  "type": "Feature",
  "properties": {
    "iso:country":"DE",
    "sg:address":"Viekskamp 3",
    "sg:city":"Quakenbr\u00fcck",
    "sg:phone":"+49 5431/7931",
    "sg:postcode":"49610",
    "sg:province":"Niedersachsen",
    "wof:name":"Cornelius Von Der Vlugt",
    "wof:placetype":"venue"
},
  "geometry": {"coordinates":[7.95939,52.682007],"type":"Point"}
}