{
  "type": "Feature",
  "properties": {
    "iso:country":"DE",
    "sg:address":"Wischkoppel 1",
    "sg:city":"Beringstedt",
    "sg:phone":"+49 4874/1263",
    "sg:postcode":"25575",
    "sg:province":"Schleswig-Holstein",
    "wof:name":"Werner Weigl",
    "wof:placetype":"venue"
},
  "geometry": {"coordinates":[9.5230703354,54.113658905],"type":"Point"}
}