{
  "type": "Feature",
  "properties": {
    "iso:country":"DE",
    "sg:address":"Rote Flurstr. 8",
    "sg:city":"St. Ingbert",
    "sg:phone":"+49 6894/386290",
    "sg:postcode":"66386",
    "sg:province":"Saarland",
    "wof:name":"Gerd Geyer",
    "wof:placetype":"venue"
},
  "geometry": {"coordinates":[7.115208149,49.2869262695],"type":"Point"}
}