{
  "type": "Feature",
  "properties": {
    "iso:country":"DE",
    "sg:address":"Ruedorfferstr. 2",
    "sg:city":"Rosenheim",
    "sg:phone":"+49 8031/356270",
    "sg:postcode":"83022",
    "sg:province":"Bayern",
    "wof:name":"E Und L Wohnbau Gmbh",
    "wof:placetype":"venue"
},
  "geometry": {"coordinates":[12.128164,47.857101],"type":"Point"}
}