{
  "type": "Feature",
  "properties": {
    "iso:country":"DE",
    "sg:address":"H\u00fcttenstr. 13",
    "sg:city":"Kerpen",
    "sg:phone":"+49 2273/51116",
    "sg:postcode":"50170",
    "sg:province":"Nordrhein-Westfalen",
    "wof:name":"Bernd M\u00fcller",
    "wof:placetype":"venue"
},
  "geometry": {"coordinates":[6.6757698059,50.9029350281],"type":"Point"}
}