{
  "type": "Feature",
  "properties": {
    "iso:country":"DE",
    "sg:address":"Hauptstr. 36",
    "sg:city":"Mehlmeisel",
    "sg:phone":"+49 9272/1685",
    "sg:postcode":"95694",
    "sg:province":"Bayern",
    "wof:name":"Kurt Ostermann",
    "wof:placetype":"venue"
},
  "geometry": {"coordinates":[11.8619327545,49.9760780334],"type":"Point"}
}