{
  "type": "Feature",
  "properties": {
    "iso:country":"DE",
    "sg:address":"Gutenbergstr. 100",
    "sg:city":"Siegen",
    "sg:phone":"+49 4927/1772390",
    "sg:postcode":"57078",
    "sg:province":"Nordrhein-Westfalen",
    "wof:name":"Bdg Apparatebau Becker + Gehrmann Gmbh",
    "wof:placetype":"venue"
},
  "geometry": {"coordinates":[7.986194,50.935146],"type":"Point"}
}