{
  "type": "Feature",
  "properties": {
    "iso:country":"DE",
    "sg:address":"Grebbener Str. 7",
    "sg:city":"Heinsberg",
    "sg:phone":"+49 2452/962100",
    "sg:postcode":"52525",
    "sg:province":"Nordrhein-Westfalen",
    "wof:name":"Trotec Von Der Lieck Ohg",
    "wof:placetype":"venue"
},
  "geometry": {"coordinates":[6.1384701729,51.0543823242],"type":"Point"}
}