{
  "type": "Feature",
  "properties": {
    "iso:country":"DE",
    "sg:address":"\u00d6schstr. 15",
    "sg:city":"Eislingen",
    "sg:phone":"+49 7161/89570",
    "sg:postcode":"73054",
    "sg:province":"Baden-W\u00fcrttemberg",
    "wof:name":"H. Laur",
    "wof:placetype":"venue"
},
  "geometry": {"coordinates":[9.7091960907,48.7005386353],"type":"Point"}
}