{
  "type": "Feature",
  "properties": {
    "iso:country":"DE",
    "sg:address":"Karlsberg 2",
    "sg:city":"Weinheim",
    "sg:phone":"+49 6201/986440",
    "sg:postcode":"69469",
    "sg:province":"Baden-W\u00fcrttemberg",
    "wof:name":"Viwa-limousinen- Und Chauffeur-service Gmbh",
    "wof:placetype":"venue"
},
  "geometry": {"coordinates":[8.6713371277,49.5495796204],"type":"Point"}
}