{
  "type": "Feature",
  "properties": {
    "iso:country":"DE",
    "sg:address":"Am Edelberg 24",
    "sg:city":"Enkirch",
    "sg:phone":"+49 6541/1273",
    "sg:postcode":"56850",
    "sg:province":"Rheinland-Pfalz",
    "wof:name":"Wilfried Schanz",
    "wof:placetype":"venue"
},
  "geometry": {"coordinates":[7.1200151443,49.9903259277],"type":"Point"}
}