{
  "type": "Feature",
  "properties": {
    "iso:country":"DE",
    "sg:address":"Hauptstr. 6",
    "sg:city":"Oedheim",
    "sg:phone":"+49 7136/26032",
    "sg:postcode":"74229",
    "sg:province":"Baden-W\u00fcrttemberg",
    "wof:name":"Pizzeria Eiscafe Italia",
    "wof:placetype":"venue"
},
  "geometry": {"coordinates":[9.2573680878,49.2400016785],"type":"Point"}
}