{
  "type": "Feature",
  "properties": {
    "iso:country":"DE",
    "sg:address":"Eckerkoppel 196::",
    "sg:city":"Hamburg",
    "sg:phone":"+49 40/6932003",
    "sg:postcode":"22047",
    "sg:province":"Hamburg",
    "wof:name":"Loderstedt Steuerungsanlagen Gmbh",
    "wof:placetype":"venue"
},
  "geometry": {"coordinates":[10.094938,53.59618],"type":"Point"}
}