{
  "type": "Feature",
  "properties": {
    "iso:country":"DE",
    "sg:address":"Rotterdamer Str. 32",
    "sg:city":"N\u00fcrnberg",
    "sg:phone":"+49 911/64350",
    "sg:postcode":"90451",
    "sg:province":"Bayern",
    "wof:name":"Rhenus Ag & Co. Kg",
    "wof:placetype":"venue"
},
  "geometry": {"coordinates":[11.0659599304,49.3996772766],"type":"Point"}
}