{
  "type": "Feature",
  "properties": {
    "iso:country":"DE",
    "sg:address":"B\u00e4ckerstr. 7",
    "sg:city":"Trebel",
    "sg:phone":"+49 5848/285",
    "sg:postcode":"29494",
    "sg:province":"Niedersachsen",
    "wof:name":"W. Schulze",
    "wof:placetype":"venue"
},
  "geometry": {"coordinates":[11.319426,52.997238],"type":"Point"}
}