{
  "type": "Feature",
  "properties": {
    "iso:country":"DE",
    "sg:address":"Sch\u00f6nauer Str. 172",
    "sg:city":"Leipzig",
    "sg:phone":"+49 341/4229210",
    "sg:postcode":"04207",
    "sg:province":"Sachsen",
    "wof:name":"Hans-j\u00f6rg Rozynek",
    "wof:placetype":"venue"
},
  "geometry": {"coordinates":[12.307577,51.312202],"type":"Point"}
}