{
  "type": "Feature",
  "properties": {
    "iso:country":"DE",
    "sg:address":"Schlo\u00dfgartenstr. 23",
    "sg:city":"M\u00fcllheim",
    "sg:phone":"+49 7631/3991",
    "sg:postcode":"79379",
    "sg:province":"Baden-W\u00fcrttemberg",
    "wof:name":"Willi Heid",
    "wof:placetype":"venue"
},
  "geometry": {"coordinates":[7.623465,47.826843],"type":"Point"}
}