{
  "type": "Feature",
  "properties": {
    "iso:country":"DE",
    "sg:address":"Chemnitzer Str. 56-58",
    "sg:city":"Berlin",
    "sg:phone":"+49 30/5676705",
    "sg:postcode":"12621",
    "sg:province":"Berlin",
    "wof:name":"Dachklempnerei Eichner Gmbh",
    "wof:placetype":"venue"
},
  "geometry": {"coordinates":[13.5794057846,52.5009002686],"type":"Point"}
}