{
  "type": "Feature",
  "properties": {
    "iso:country":"DE",
    "sg:address":"Kahrweg 15",
    "sg:city":"Ahlen",
    "sg:phone":"+49 2528/8258",
    "sg:postcode":"59227",
    "sg:province":"Nordrhein-Westfalen",
    "wof:name":"Hammelmann",
    "wof:placetype":"venue"
},
  "geometry": {"coordinates":[7.9447398186,51.8018112183],"type":"Point"}
}