{
  "type": "Feature",
  "properties": {
    "iso:country":"DE",
    "sg:address":"Am Dreieck 6",
    "sg:city":"Grabowh\u00f6fe",
    "sg:phone":"+49 39926/3170",
    "sg:postcode":"17194",
    "sg:province":"Mecklenburg-Vorpommern",
    "wof:name":"Mecklenburger Landtechnik Wittke E. K.",
    "wof:placetype":"venue"
},
  "geometry": {"coordinates":[12.6315,53.579021],"type":"Point"}
}