{
  "type": "Feature",
  "properties": {
    "iso:country":"DE",
    "sg:address":"Belzgasse 4",
    "sg:city":"Braunfels",
    "sg:phone":"+49 6442/4862",
    "sg:postcode":"35619",
    "sg:province":"Hessen",
    "wof:name":"Ernst Lang Architekt",
    "wof:placetype":"venue"
},
  "geometry": {"coordinates":[8.389292,50.51387],"type":"Point"}
}