{
  "type": "Feature",
  "properties": {
    "iso:country":"DE",
    "sg:address":"Zum Wagner 72",
    "sg:city":"W\u00fcrchwitz",
    "sg:phone":"+49 34426/21270",
    "sg:postcode":"06712",
    "sg:province":"Sachsen-Anhalt",
    "wof:name":"Herbert Meuschke",
    "wof:placetype":"venue"
},
  "geometry": {"coordinates":[12.226969,51.01622],"type":"Point"}
}