{
  "type": "Feature",
  "properties": {
    "iso:country":"DE",
    "sg:address":"Milchmarkt 15",
    "sg:city":"Rothenburg",
    "sg:phone":"+49 9861/8933",
    "sg:postcode":"91541",
    "sg:province":"Bayern",
    "wof:name":"Bohmann",
    "wof:placetype":"venue"
},
  "geometry": {"coordinates":[10.1806526184,49.3775634766],"type":"Point"}
}