{
  "type": "Feature",
  "properties": {
    "iso:country":"DE",
    "sg:address":"Berblingerstr. 18",
    "sg:city":"Ditzingen",
    "sg:phone":"+49 7156/7138",
    "sg:postcode":"71254",
    "sg:province":"Baden-W\u00fcrttemberg",
    "wof:name":"Otto Eberhardt",
    "wof:placetype":"venue"
},
  "geometry": {"coordinates":[9.061606,48.819008],"type":"Point"}
}