{
  "type": "Feature",
  "properties": {
    "iso:country":"DE",
    "sg:address":"Klippeneckstr. 13",
    "sg:city":"Rottweil",
    "sg:phone":"+49 741/14040",
    "sg:postcode":"78628",
    "sg:province":"Baden-W\u00fcrttemberg",
    "wof:name":"S. Und I. Haas-starke Kunstmaler",
    "wof:placetype":"venue"
},
  "geometry": {"coordinates":[8.623014,48.159264],"type":"Point"}
}