{
  "type": "Feature",
  "properties": {
    "iso:country":"DE",
    "sg:address":"Holzstr. 1",
    "sg:city":"Recklinghausen",
    "sg:phone":"+49 2361/661160",
    "sg:postcode":"45661",
    "sg:province":"Nordrhein-Westfalen",
    "wof:name":"Teamsport Gerd Philipp",
    "wof:placetype":"venue"
},
  "geometry": {"coordinates":[7.187454,51.568382],"type":"Point"}
}