{
  "type": "Feature",
  "properties": {
    "iso:country":"DE",
    "sg:address":"Oskar-Coester-Weg 10",
    "sg:city":"M\u00fcnchen",
    "sg:phone":"+49 89/7916566",
    "sg:postcode":"81479",
    "sg:province":"Bayern",
    "wof:name":"Karnin Consulting E. K.",
    "wof:placetype":"venue"
},
  "geometry": {"coordinates":[11.5256996155,48.0699424744],"type":"Point"}
}