{
  "type": "Feature",
  "properties": {
    "iso:country":"DE",
    "sg:address":"Hainebuchenweg 4",
    "sg:city":"Aerzen",
    "sg:phone":"+49 5154/4158",
    "sg:postcode":"31855",
    "sg:province":"Niedersachsen",
    "wof:name":"Udo Walther",
    "wof:placetype":"venue"
},
  "geometry": {"coordinates":[9.265659,52.04702],"type":"Point"}
}