{
  "type": "Feature",
  "properties": {
    "iso:country":"DE",
    "sg:address":"Industriestr. 4",
    "sg:city":"Gro\u00dfefehn",
    "sg:phone":"+49 4943/3760",
    "sg:postcode":"26629",
    "sg:province":"Niedersachsen",
    "wof:name":"W. U. S. Industrieservice Gmbh",
    "wof:placetype":"venue"
},
  "geometry": {"coordinates":[7.651593,53.405743],"type":"Point"}
}