{
  "type": "Feature",
  "properties": {
    "iso:country":"DE",
    "sg:address":"Hans-B\u00f6ckler-Str. 5",
    "sg:city":"Maxh\u00fctte-Haidhof",
    "sg:phone":"+49 9471/4844",
    "sg:postcode":"93142",
    "sg:province":"Bayern",
    "wof:name":"Hubert Schleinkofer",
    "wof:placetype":"venue"
},
  "geometry": {"coordinates":[12.093535,49.174438],"type":"Point"}
}