{
  "type": "Feature",
  "properties": {
    "iso:country":"DE",
    "sg:address":"Hausenring 65",
    "sg:city":"Stuttgart",
    "sg:phone":"+49 711/8873850",
    "sg:postcode":"70499",
    "sg:province":"Baden-W\u00fcrttemberg",
    "wof:name":"Lothar Elschner Glas- Und Porzellanwaren",
    "wof:placetype":"venue"
},
  "geometry": {"coordinates":[9.0826501846,48.8136901855],"type":"Point"}
}