{
  "type": "Feature",
  "properties": {
    "iso:country":"DE",
    "sg:address":"Brentanostr. 18",
    "sg:city":"Schiffweiler",
    "sg:phone":"+49 6821/6306005",
    "sg:postcode":"66578",
    "sg:province":"Saarland",
    "wof:name":"Frank Kirsch",
    "wof:placetype":"venue"
},
  "geometry": {"coordinates":[7.123973,49.378963],"type":"Point"}
}