{
  "type": "Feature",
  "properties": {
    "iso:country":"DE",
    "sg:address":"Kurt-Schumacher-Ring 38",
    "sg:city":"Egelsbach",
    "sg:phone":"+49 6103/44129",
    "sg:postcode":"63329",
    "sg:province":"Hessen",
    "wof:name":"J. Friedrichs",
    "wof:placetype":"venue"
},
  "geometry": {"coordinates":[8.67059,49.9576],"type":"Point"}
}