{
  "type": "Feature",
  "properties": {
    "iso:country":"DE",
    "sg:address":"Humboldtstr. 17",
    "sg:city":"Hildesheim",
    "sg:phone":"+49 5121/12555",
    "sg:postcode":"31134",
    "sg:province":"Niedersachsen",
    "wof:name":"Norman Tragsdorf Immobilienmakler",
    "wof:placetype":"venue"
},
  "geometry": {"coordinates":[9.9463148117,52.1452331543],"type":"Point"}
}