{
  "type": "Feature",
  "properties": {
    "iso:country":"DE",
    "sg:address":"Bonsfelder Str. 93",
    "sg:city":"Velbert",
    "sg:phone":"+49 2052/2115",
    "sg:postcode":"42555",
    "sg:province":"Nordrhein-Westfalen",
    "wof:name":"Wilhelm Weustenfeld",
    "wof:placetype":"venue"
},
  "geometry": {"coordinates":[7.137331,51.371906],"type":"Point"}
}