{
  "type": "Feature",
  "properties": {
    "iso:country":"DE",
    "sg:address":"Gro\u00dfe Brauhausstr. 15/17",
    "sg:city":"Halle",
    "sg:phone":"+49 345/20503",
    "sg:postcode":"06108",
    "sg:province":"Sachsen-Anhalt",
    "wof:name":"Readymix Beton Saale Verwaltungs-gmbh",
    "wof:placetype":"venue"
},
  "geometry": {"coordinates":[11.971963,51.47913],"type":"Point"}
}