{
  "type": "Feature",
  "properties": {
    "iso:country":"DE",
    "sg:address":"Thomas-Mann-Str. 59",
    "sg:city":"N\u00fcrnberg",
    "sg:postcode":"90471",
    "sg:province":"Bayern",
    "wof:name":"Friedrich Tauscher Steuerberater",
    "wof:placetype":"venue"
},
  "geometry": {"coordinates":[11.1359777451,49.4136734009],"type":"Point"}
}