{
  "type": "Feature",
  "properties": {
    "iso:country":"DE",
    "sg:address":"Brahmsallee 87",
    "sg:city":"Hamburg",
    "sg:phone":"+49 40/459693",
    "sg:postcode":"20144",
    "sg:province":"Hamburg",
    "wof:name":"Kemna Gmbh Dienstleistung Und Handel",
    "wof:placetype":"venue"
},
  "geometry": {"coordinates":[9.9813270569,53.5784072876],"type":"Point"}
}