{
  "type": "Feature",
  "properties": {
    "iso:country":"DE",
    "sg:address":"Gaustra\u00dfe 26",
    "sg:city":"Bobenheim-Roxheim",
    "sg:phone":"+49 6239/1686",
    "sg:postcode":"67240",
    "sg:province":"Rheinland-Pfalz",
    "wof:name":"Cubulus Gbr",
    "wof:placetype":"venue"
},
  "geometry": {"coordinates":[8.3606910706,49.5757713318],"type":"Point"}
}