{
  "type": "Feature",
  "properties": {
    "iso:country":"DE",
    "sg:address":"St.-Stephans-Platz 5",
    "sg:city":"Konstanz",
    "sg:phone":"+49 7531/27005",
    "sg:postcode":"78462",
    "sg:province":"Baden-W\u00fcrttemberg",
    "wof:name":"Syrtaki",
    "wof:placetype":"venue"
},
  "geometry": {"coordinates":[9.1735486984,47.6614723206],"type":"Point"}
}