{
  "type": "Feature",
  "properties": {
    "iso:country":"DE",
    "sg:address":"Tholeyer Str. 25",
    "sg:city":"Lebach",
    "sg:phone":"+49 6881/2671",
    "sg:postcode":"66822",
    "sg:province":"Saarland",
    "wof:name":"Paul Schober",
    "wof:placetype":"venue"
},
  "geometry": {"coordinates":[6.9129347801,49.4126243591],"type":"Point"}
}