{
  "type": "Feature",
  "properties": {
    "iso:country":"DE",
    "sg:address":"Ginsterstr. 1",
    "sg:city":"Rheinberg",
    "sg:phone":"+49 2843/3829",
    "sg:postcode":"47495",
    "sg:province":"Nordrhein-Westfalen",
    "wof:name":"Rosenthal Gmbh",
    "wof:placetype":"venue"
},
  "geometry": {"coordinates":[6.6296367645,51.5340805054],"type":"Point"}
}