{
  "type": "Feature",
  "properties": {
    "iso:country":"DE",
    "sg:address":"Distelkamp 65",
    "sg:city":"Herne",
    "sg:phone":"+49 2325/33233",
    "sg:postcode":"44651",
    "sg:province":"Nordrhein-Westfalen",
    "wof:name":"Horst Roosen",
    "wof:placetype":"venue"
},
  "geometry": {"coordinates":[7.1615037918,51.5157165527],"type":"Point"}
}