{
  "type": "Feature",
  "properties": {
    "iso:country":"DE",
    "sg:address":"Am Markt 1",
    "sg:city":"Sersheim",
    "sg:phone":"+49 7042/33933",
    "sg:postcode":"74372",
    "sg:province":"Baden-W\u00fcrttemberg",
    "wof:name":"M. Velte",
    "wof:placetype":"venue"
},
  "geometry": {"coordinates":[9.0145206451,48.9593734741],"type":"Point"}
}