{
  "type": "Feature",
  "properties": {
    "iso:country":"DE",
    "sg:address":"Siegmund-Adam-Str. 39",
    "sg:city":"Eschlkam",
    "sg:phone":"+49 9947/1334",
    "sg:postcode":"93458",
    "sg:province":"Bayern",
    "wof:name":"Pension Wolfgang Iglhaut",
    "wof:placetype":"venue"
},
  "geometry": {"coordinates":[12.9815502167,49.298828125],"type":"Point"}
}