{
  "type": "Feature",
  "properties": {
    "iso:country":"DE",
    "sg:address":"Schloss::",
    "sg:city":"Salem",
    "sg:href":"http://api.simplegeo.com/1.0/features/SG_0kkCwZZSa90YEct4P8Wsjh_47.776634_9.285990@1306268793.json",
    "sg:phone":"+49 4975/53810",
    "sg:postcode":"88682",
    "sg:province":"Baden-W\u00fcrttemberg",
    "wof:name":"Markgraeflich Badische Hauptverwaltung",
    "wof:placetype":"venue"
},
  "geometry": {"coordinates":[9.28599,47.776634],"type":"Point"}
}