{"geometry":{"type":"Point","coordinates":[9.285990,47.776634]},"type":"Feature","id":102560439,"bbox":[9.285990,47.776634,9.285990,47.776634],"properties":{"sg:province":"Baden-W\u00fcrttemberg","geom:longitude":9.285990,"wof:breaches":[],"sg:href":"http://api.simplegeo.com/1.0/features/SG_0kkCwZZSa90YEct4P8Wsjh_47.776634_9.285990@1306268793.json","sg:owner":"simplegeo","sg:postcode":"88682","geom:latitude":47.776634,"sg:classifiers":[],"sg:address":"Schloss::","sg:phone":"+49 4975/53810","wof:hierarchy":[{"locality_id":101765219,"venue_id":102560439,"country_id":85633111,"region_id":85682567,"county_id":102063209}],"geom:area":0.000000,"sg:city":"Salem","wof:lastmodified":1438093254,"iso:country":"DE","wof:geomhash":"f551c6cf67c0f5bc382f05e574837dea","wof:name":"Markgraeflich Badische Hauptverwaltung","wof:belongsto":[101765219,85633111,85682567,102063209],"src:geom":"simplegeo","wof:placetype":"venue","wof:supersedes":[],"wof:id":102560439,"wof:superseded_by":[],"wof:concordances":{"sg:id":"SG_0kkCwZZSa90YEct4P8Wsjh_47.776634_9.285990@1306268793"},"wof:parent_id":101765219}}