{
  "type": "Feature",
  "properties": {
    "iso:country":"DE",
    "sg:address":"Schlo\u00dfplatz 9",
    "sg:city":"Rheinau",
    "sg:phone":"+49 7844/7609",
    "sg:postcode":"77866",
    "sg:province":"Baden-W\u00fcrttemberg",
    "wof:name":"Peter M\u00fcller",
    "wof:placetype":"venue"
},
  "geometry": {"coordinates":[7.922638,48.653564],"type":"Point"}
}