{
  "type": "Feature",
  "properties": {
    "iso:country":"DE",
    "sg:address":"Neue Str. 11",
    "sg:city":"Schopp",
    "sg:phone":"+49 6307/7354",
    "sg:postcode":"67707",
    "sg:province":"Rheinland-Pfalz",
    "wof:name":"Dr. Med. Lothar Wildmoser",
    "wof:placetype":"venue"
},
  "geometry": {"coordinates":[7.6884279251,49.3509216309],"type":"Point"}
}