{
  "type": "Feature",
  "properties": {
    "iso:country":"DE",
    "sg:address":"Enzpark 25",
    "sg:city":"Oberriexingen",
    "sg:phone":"+49 7042/22049",
    "sg:postcode":"71739",
    "sg:province":"Baden-W\u00fcrttemberg",
    "wof:name":"Heinemann Consulting Beratungsgesellschaft F\u00fcr",
    "wof:placetype":"venue"
},
  "geometry": {"coordinates":[9.0234050751,48.924041748],"type":"Point"}
}