{
  "type": "Feature",
  "properties": {
    "iso:country":"DE",
    "sg:address":"Panoramastr. 85",
    "sg:city":"Vaihingen",
    "sg:phone":"+49 7042/25614",
    "sg:postcode":"71665",
    "sg:province":"Baden-W\u00fcrttemberg",
    "wof:name":"G. Kirst\u00e4tter Ingenieur",
    "wof:placetype":"venue"
},
  "geometry": {"coordinates":[8.94982,48.959736],"type":"Point"}
}