{
  "type": "Feature",
  "properties": {
    "iso:country":"DE",
    "sg:address":"Schmeddingstr. 8",
    "sg:city":"M\u00fcnster",
    "sg:phone":"+49 251/82524",
    "sg:postcode":"48149",
    "sg:province":"Nordrhein-Westfalen",
    "wof:name":"Nbk Keramik-beteiligungs Gmbh",
    "wof:placetype":"venue"
},
  "geometry": {"coordinates":[7.596125,51.954346],"type":"Point"}
}