{
  "type": "Feature",
  "properties": {
    "iso:country":"DE",
    "sg:address":"Boschertweg 2",
    "sg:city":"A\u00dfling",
    "sg:phone":"+49 8092/6209",
    "sg:postcode":"85617",
    "sg:province":"Bayern",
    "wof:name":"J. Adam Immobilienmakler",
    "wof:placetype":"venue"
},
  "geometry": {"coordinates":[12.0058679581,47.9932899475],"type":"Point"}
}