{
  "type": "Feature",
  "properties": {
    "iso:country":"DE",
    "sg:address":"Bergisch Born 53",
    "sg:city":"Remscheid",
    "sg:phone":"+49 2191/662040",
    "sg:postcode":"42897",
    "sg:province":"Nordrhein-Westfalen",
    "wof:name":"Harald Thienel",
    "wof:placetype":"venue"
},
  "geometry": {"coordinates":[7.2651500702,51.162940979],"type":"Point"}
}