{
  "type": "Feature",
  "properties": {
    "iso:country":"DE",
    "sg:address":"Lilienweg 7",
    "sg:city":"Spangenberg",
    "sg:phone":"+49 5663/466",
    "sg:postcode":"34286",
    "sg:province":"Hessen",
    "wof:name":"Georg Nentwig",
    "wof:placetype":"venue"
},
  "geometry": {"coordinates":[9.6552152634,51.1116600037],"type":"Point"}
}