{
  "type": "Feature",
  "properties": {
    "iso:country":"DE",
    "sg:address":"Am Wellenberge 17",
    "sg:city":"Magdeburg",
    "sg:phone":"+49 391/4046127",
    "sg:postcode":"39122",
    "sg:province":"Sachsen-Anhalt",
    "wof:name":"Kresin Und Co. Kg",
    "wof:placetype":"venue"
},
  "geometry": {"coordinates":[11.6687135696,52.0594520569],"type":"Point"}
}