{
  "type": "Feature",
  "properties": {
    "iso:country":"DE",
    "sg:address":"In der B\u00fclt 8",
    "sg:city":"Kutenholz",
    "sg:phone":"+49 4762/577",
    "sg:postcode":"27449",
    "sg:province":"Niedersachsen",
    "wof:name":"Ludwigs Immobilien Gmbh",
    "wof:placetype":"venue"
},
  "geometry": {"coordinates":[9.298049,53.498806],"type":"Point"}
}