{
  "type": "Feature",
  "properties": {
    "iso:country":"DE",
    "sg:address":"Martinistr. 61",
    "sg:city":"Bremen",
    "sg:phone":"+49 421/170201",
    "sg:postcode":"28195",
    "sg:province":"Bremen",
    "wof:name":"Restaurant Bar Mexcal",
    "wof:placetype":"venue"
},
  "geometry": {"coordinates":[8.8020648956,53.0780754089],"type":"Point"}
}