{
  "type": "Feature",
  "properties": {
    "iso:country":"DE",
    "sg:address":"Niedaltdorfer Str. 6",
    "sg:city":"Rehlingen-Siersburg",
    "sg:phone":"+49 6833/253",
    "sg:postcode":"66780",
    "sg:province":"Saarland",
    "wof:name":"Gerhard M\u00fcller Eisenwaren",
    "wof:placetype":"venue"
},
  "geometry": {"coordinates":[6.615255,49.35527],"type":"Point"}
}