{
  "type": "Feature",
  "properties": {
    "iso:country":"DE",
    "sg:address":"Oranienstr. 8",
    "sg:city":"Wiesbaden",
    "sg:phone":"+49 611/300597",
    "sg:postcode":"65185",
    "sg:province":"Hessen",
    "wof:name":"G\u00fcnther H\u00e4ckel",
    "wof:placetype":"venue"
},
  "geometry": {"coordinates":[8.2371072769,50.0768127441],"type":"Point"}
}