{
  "type": "Feature",
  "properties": {
    "iso:country":"DE",
    "sg:address":"Hauptstr. 7",
    "sg:city":"Heidenau",
    "sg:phone":"+49 3529/521811",
    "sg:postcode":"01809",
    "sg:province":"Sachsen",
    "wof:name":"Aral-tankstelle",
    "wof:placetype":"venue"
},
  "geometry": {"coordinates":[13.8632278442,50.9727592468],"type":"Point"}
}