{
  "type": "Feature",
  "properties": {
    "iso:country":"DE",
    "sg:address":"Ewige Weide 9",
    "sg:city":"Ahrensburg",
    "sg:phone":"+49 4102/220687",
    "sg:postcode":"22926",
    "sg:province":"Schleswig-Holstein",
    "wof:name":"Wilhelm Fedkenheuer Werbung Und Druck",
    "wof:placetype":"venue"
},
  "geometry": {"coordinates":[10.261164,53.689571],"type":"Point"}
}