{
  "type": "Feature",
  "properties": {
    "iso:country":"DE",
    "sg:address":"Sportlerweg 1",
    "sg:city":"Riesa",
    "sg:phone":"+49 3525/731558",
    "sg:postcode":"01587",
    "sg:province":"Sachsen",
    "wof:name":"B. Eichler & J. Sperling Gbr",
    "wof:placetype":"venue"
},
  "geometry": {"coordinates":[13.269458,51.302544],"type":"Point"}
}