{
  "type": "Feature",
  "properties": {
    "iso:country":"DE",
    "sg:address":"G\u00fcstener Str. 16",
    "sg:city":"Titz",
    "sg:phone":"+49 2463/8271",
    "sg:postcode":"52445",
    "sg:province":"Nordrhein-Westfalen",
    "wof:name":"Jan Wooning",
    "wof:placetype":"venue"
},
  "geometry": {"coordinates":[6.433296,50.981873],"type":"Point"}
}