{
  "type": "Feature",
  "properties": {
    "iso:country":"DE",
    "sg:address":"H\u00fcnefeldzeile 11-12",
    "sg:city":"Berlin",
    "sg:phone":"+49 30/3029901",
    "sg:postcode":"12247",
    "sg:province":"Berlin",
    "wof:name":"Hartmut Menzel Immobilienmakler",
    "wof:placetype":"venue"
},
  "geometry": {"coordinates":[13.3557949066,52.4460067749],"type":"Point"}
}