{
  "type": "Feature",
  "properties": {
    "iso:country":"DE",
    "sg:address":"Priehlbachtal 88",
    "sg:city":"Essen",
    "sg:phone":"+49 201/482185",
    "sg:postcode":"45257",
    "sg:province":"Nordrhein-Westfalen",
    "wof:name":"Merlin",
    "wof:placetype":"venue"
},
  "geometry": {"coordinates":[7.0995588303,51.3764762878],"type":"Point"}
}