{
  "type": "Feature",
  "properties": {
    "iso:country":"DE",
    "sg:address":"Herrenstr. 7",
    "sg:city":"Burgst\u00e4dt",
    "sg:phone":"+49 3724/14133",
    "sg:postcode":"09217",
    "sg:province":"Sachsen",
    "wof:name":"Georg N\u00fc\u00dflein",
    "wof:placetype":"venue"
},
  "geometry": {"coordinates":[12.804558754,50.9199752808],"type":"Point"}
}