{
  "type": "Feature",
  "properties": {
    "iso:country":"DE",
    "sg:address":"Eintrachtstr. 43",
    "sg:city":"Solingen",
    "sg:phone":"+49 212/548585",
    "sg:postcode":"42655",
    "sg:province":"Nordrhein-Westfalen",
    "wof:name":"Druckhaus Berger Berger & Fischer Gmbh",
    "wof:placetype":"venue"
},
  "geometry": {"coordinates":[7.073801,51.180233],"type":"Point"}
}