{
  "type": "Feature",
  "properties": {
    "iso:country":"DE",
    "sg:address":"Friedrich-Ebert-Damm 54 c",
    "sg:city":"Hamburg",
    "sg:phone":"+49 40/6937336",
    "sg:postcode":"22047",
    "sg:province":"Hamburg",
    "wof:name":"Max K. Pechstein Architekt",
    "wof:placetype":"venue"
},
  "geometry": {"coordinates":[10.081335,53.585167],"type":"Point"}
}