{
  "type": "Feature",
  "properties": {
    "iso:country":"DE",
    "sg:address":"W\u00fcrmtalstr. 95",
    "sg:city":"M\u00fcnchen",
    "sg:phone":"+49 89/74100370",
    "sg:postcode":"81375",
    "sg:province":"Bayern",
    "wof:name":"Kaisers Tengelmann Ag",
    "wof:placetype":"venue"
},
  "geometry": {"coordinates":[11.4814605713,48.1148147583],"type":"Point"}
}