{
  "type": "Feature",
  "properties": {
    "iso:country":"DE",
    "sg:address":"Im Bromberger Pfad 15",
    "sg:city":"Sachsenheim",
    "sg:phone":"+49 7147/7021",
    "sg:postcode":"74343",
    "sg:province":"Baden-W\u00fcrttemberg",
    "wof:name":"Frieder Skobowsky Ingenieur",
    "wof:placetype":"venue"
},
  "geometry": {"coordinates":[9.0167045593,49.0010147095],"type":"Point"}
}