{
  "type": "Feature",
  "properties": {
    "iso:country":"DE",
    "sg:address":"Carl-Zuckmayer-Str. 10",
    "sg:city":"Nackenheim",
    "sg:phone":"+49 6135/707956",
    "sg:postcode":"55299",
    "sg:province":"Rheinland-Pfalz",
    "wof:name":"Die 4 Friseursalon",
    "wof:placetype":"venue"
},
  "geometry": {"coordinates":[8.3434772491,49.914516449],"type":"Point"}
}