{
  "type": "Feature",
  "properties": {
    "iso:country":"DE",
    "sg:address":"Hesselteicher Str. 97",
    "sg:city":"Borgholzhausen",
    "sg:phone":"+49 5425/6370",
    "sg:postcode":"33829",
    "sg:province":"Nordrhein-Westfalen",
    "wof:name":"Curt Torweihe",
    "wof:placetype":"venue"
},
  "geometry": {"coordinates":[8.254754,52.058891],"type":"Point"}
}