{
  "type": "Feature",
  "properties": {
    "iso:country":"DE",
    "sg:address":"Allinger Str. 31",
    "sg:city":"Puchheim",
    "sg:phone":"+49 89/807076",
    "sg:postcode":"82178",
    "sg:province":"Bayern",
    "wof:name":"H. G. Und M. M. Schrepfer Steuerberater",
    "wof:placetype":"venue"
},
  "geometry": {"coordinates":[11.3464689255,48.1695747375],"type":"Point"}
}