{
  "type": "Feature",
  "properties": {
    "iso:country":"DE",
    "sg:address":"Melanchthonweg 47",
    "sg:city":"Backnang",
    "sg:phone":"+49 7191/60290",
    "sg:postcode":"71522",
    "sg:province":"Baden-W\u00fcrttemberg",
    "wof:name":"Ev. Pfarramt Ii Matth\u00e4uskirche",
    "wof:placetype":"venue"
},
  "geometry": {"coordinates":[9.4355678558,48.9526100159],"type":"Point"}
}