{
  "type": "Feature",
  "properties": {
    "iso:country":"DE",
    "sg:address":"Bismarckstr. 54",
    "sg:city":"Ludwigshafen",
    "sg:postcode":"67059",
    "sg:province":"Rheinland-Pfalz",
    "wof:name":"Vitalitas Immobilien Gmbh",
    "wof:placetype":"venue"
},
  "geometry": {"coordinates":[8.4479436874,49.4815177917],"type":"Point"}
}