{
  "type": "Feature",
  "properties": {
    "iso:country":"DE",
    "sg:address":"An der Alten Ziegelei 32",
    "sg:city":"M\u00fcnster",
    "sg:phone":"+49 251/143320",
    "sg:postcode":"48157",
    "sg:province":"Nordrhein-Westfalen",
    "wof:name":"B.p.b. Bau Gmbh",
    "wof:placetype":"venue"
},
  "geometry": {"coordinates":[7.6655611992,51.9971046448],"type":"Point"}
}