{
  "type": "Feature",
  "properties": {
    "iso:country":"DE",
    "sg:address":"Fr\u00fchlingstr. 24",
    "sg:city":"Freising",
    "sg:phone":"+49 8161/50109",
    "sg:postcode":"85354",
    "sg:province":"Bayern",
    "wof:name":"Nefzger & Maier Gmbh",
    "wof:placetype":"venue"
},
  "geometry": {"coordinates":[11.7345285416,48.3917198181],"type":"Point"}
}