{
  "type": "Feature",
  "properties": {
    "iso:country":"DE",
    "sg:address":"Pivitsheider Str. 283",
    "sg:city":"Lage",
    "sg:phone":"+49 5232/86928",
    "sg:postcode":"32791",
    "sg:province":"Nordrhein-Westfalen",
    "wof:name":"Heinz Kronshage",
    "wof:placetype":"venue"
},
  "geometry": {"coordinates":[8.802892,51.964645],"type":"Point"}
}