{
  "type": "Feature",
  "properties": {
    "iso:country":"DE",
    "sg:address":"Dreierkrugplatz 3",
    "sg:city":"Detmold",
    "sg:phone":"+49 5231/5201",
    "sg:postcode":"32760",
    "sg:province":"Nordrhein-Westfalen",
    "wof:name":"Restaurant Dreierkrug",
    "wof:placetype":"venue"
},
  "geometry": {"coordinates":[8.8993473053,51.9215164185],"type":"Point"}
}