{
  "type": "Feature",
  "properties": {
    "iso:country":"DE",
    "sg:address":"Am Brennels 4",
    "sg:city":"Lilienthal",
    "sg:phone":"+49 4298/3840",
    "sg:postcode":"28865",
    "sg:province":"Niedersachsen",
    "wof:name":"A. Br\u00fcnjes Sch\u00e4ferhundzucht",
    "wof:placetype":"venue"
},
  "geometry": {"coordinates":[8.9722900391,53.1333999634],"type":"Point"}
}