{
  "type": "Feature",
  "properties": {
    "iso:country":"DE",
    "sg:address":"Turmstr. 9",
    "sg:city":"Wittenberge",
    "sg:phone":"+49 3877/73580",
    "sg:postcode":"19322",
    "sg:province":"Brandenburg",
    "wof:name":"Griechisches Restaurant Olympia",
    "wof:placetype":"venue"
},
  "geometry": {"coordinates":[11.7515411377,52.9941368103],"type":"Point"}
}