{
  "type": "Feature",
  "properties": {
    "iso:country":"DE",
    "sg:address":"Humboldtstr. 54",
    "sg:city":"Bremen",
    "sg:phone":"+49 421/703811",
    "sg:postcode":"28203",
    "sg:province":"Bremen",
    "wof:name":"W.f. Spohler Innenarchitekt",
    "wof:placetype":"venue"
},
  "geometry": {"coordinates":[8.827119,53.075008],"type":"Point"}
}