{
  "type": "Feature",
  "properties": {
    "iso:country":"DE",
    "sg:address":"Meeraner Str. 106",
    "sg:city":"Glauchau",
    "sg:phone":"+49 3763/788805",
    "sg:postcode":"08371",
    "sg:province":"Sachsen",
    "wof:name":"G\u00fcnter T\u00fcrpe",
    "wof:placetype":"venue"
},
  "geometry": {"coordinates":[12.5176973343,50.8318138123],"type":"Point"}
}