{
  "type": "Feature",
  "properties": {
    "iso:country":"DE",
    "sg:address":"Hauptstr. 102",
    "sg:city":"Neutrebbin",
    "sg:phone":"+49 33474/242",
    "sg:postcode":"15320",
    "sg:province":"Brandenburg",
    "wof:name":"S. H\u00fcbner",
    "wof:placetype":"venue"
},
  "geometry": {"coordinates":[14.2259998322,52.6659393311],"type":"Point"}
}