{
  "type": "Feature",
  "properties": {
    "iso:country":"DE",
    "sg:address":"Haingeraidestr. 40",
    "sg:city":"Eu\u00dferthal",
    "sg:phone":"+49 6345/1386",
    "sg:postcode":"76857",
    "sg:province":"Rheinland-Pfalz",
    "wof:name":"Edith Ke\u00dfler",
    "wof:placetype":"venue"
},
  "geometry": {"coordinates":[7.971365,49.243198],"type":"Point"}
}