{
  "type": "Feature",
  "properties": {
    "iso:country":"DE",
    "sg:address":"Hansestr. 9",
    "sg:city":"Bielefeld",
    "sg:phone":"+49 4952/0522800",
    "sg:postcode":"33689",
    "sg:province":"Nordrhein-Westfalen",
    "wof:name":"Detlev G\u00d6tztour-service-lichtdesign Kg",
    "wof:placetype":"venue"
},
  "geometry": {"coordinates":[8.570835,51.948746],"type":"Point"}
}