{
  "type": "Feature",
  "properties": {
    "iso:country":"DE",
    "sg:address":"Sonnenwall 55",
    "sg:city":"Duisburg",
    "sg:phone":"+49 203/22243",
    "sg:postcode":"47051",
    "sg:province":"Nordrhein-Westfalen",
    "wof:name":"Waffen Dittmar & Brouns Gmbh",
    "wof:placetype":"venue"
},
  "geometry": {"coordinates":[6.760633,51.431667],"type":"Point"}
}