{
  "type": "Feature",
  "properties": {
    "iso:country":"DE",
    "sg:address":"Stresemannstr. 74",
    "sg:city":"Berlin",
    "sg:phone":"+49 30/2652411",
    "sg:postcode":"10963",
    "sg:province":"Berlin",
    "wof:name":"Zbigniew Wolwowicz",
    "wof:placetype":"venue"
},
  "geometry": {"coordinates":[13.3834466934,52.5038452148],"type":"Point"}
}