{
  "type": "Feature",
  "properties": {
    "iso:country":"DE",
    "sg:address":"Carl-Benz-Str. 3",
    "sg:city":"Schweinfurt",
    "sg:postcode":"97424",
    "sg:province":"Bayern",
    "wof:name":"Steger Fliesen- Und Natursteinverlegung Gmbh",
    "wof:placetype":"venue"
},
  "geometry": {"coordinates":[10.2371997833,50.0363540649],"type":"Point"}
}