{
  "type": "Feature",
  "properties": {
    "iso:country":"DE",
    "sg:address":"Jordanstr. 10",
    "sg:city":"Frankfurt",
    "sg:phone":"+49 69/776653",
    "sg:postcode":"60486",
    "sg:province":"Hessen",
    "wof:name":"M. Heeg",
    "wof:placetype":"venue"
},
  "geometry": {"coordinates":[8.648089,50.118656],"type":"Point"}
}