{
  "type": "Feature",
  "properties": {
    "iso:country":"DE",
    "sg:address":"Krokusweg 1",
    "sg:city":"Pforzheim",
    "sg:postcode":"75181",
    "sg:province":"Baden-W\u00fcrttemberg",
    "wof:name":"Fischer Haus E. V.",
    "wof:placetype":"venue"
},
  "geometry": {"coordinates":[8.7334785461,48.8559150696],"type":"Point"}
}