{
  "type": "Feature",
  "properties": {
    "iso:country":"DE",
    "sg:address":"Gutenbergstr. 25",
    "sg:city":"Bergheim",
    "sg:phone":"+49 2271/61807",
    "sg:postcode":"50126",
    "sg:province":"Nordrhein-Westfalen",
    "wof:name":"Dr. Klaus Voetz Tierarzt",
    "wof:placetype":"venue"
},
  "geometry": {"coordinates":[6.6303181648,50.9479637146],"type":"Point"}
}