{
  "type": "Feature",
  "properties": {
    "iso:country":"DE",
    "sg:address":"Mittlerer Kaulberg 20",
    "sg:city":"Bamberg",
    "sg:phone":"+49 951/56409",
    "sg:postcode":"96049",
    "sg:province":"Bayern",
    "wof:name":"Ullein",
    "wof:placetype":"venue"
},
  "geometry": {"coordinates":[10.881999,49.887524],"type":"Point"}
}