{
  "type": "Feature",
  "properties": {
    "iso:country":"DE",
    "sg:address":"Im Mesnergarten 3",
    "sg:city":"Wittnau",
    "sg:phone":"+49 761/4001670",
    "sg:postcode":"79299",
    "sg:province":"Baden-W\u00fcrttemberg",
    "wof:name":"Karsten Selz",
    "wof:placetype":"venue"
},
  "geometry": {"coordinates":[7.812568,47.945702],"type":"Point"}
}