{
  "type": "Feature",
  "properties": {
    "iso:country":"DE",
    "sg:address":"Blumenstr. 1",
    "sg:city":"Weinheim",
    "sg:phone":"+49 6201/13533",
    "sg:postcode":"69469",
    "sg:province":"Baden-W\u00fcrttemberg",
    "wof:name":"Richard Grimminger",
    "wof:placetype":"venue"
},
  "geometry": {"coordinates":[8.648614,49.54496],"type":"Point"}
}