{
  "type": "Feature",
  "properties": {
    "iso:country":"DE",
    "sg:address":"Hindenburgstr. 158",
    "sg:city":"Hamburg",
    "sg:postcode":"22297",
    "sg:province":"Hamburg",
    "wof:name":"Planmeca Gmbh",
    "wof:placetype":"venue"
},
  "geometry": {"coordinates":[10.005339,53.618061],"type":"Point"}
}