{
  "type": "Feature",
  "properties": {
    "iso:country":"DE",
    "sg:address":"Adam-Schimmer-Str. 4a",
    "sg:city":"Aub",
    "sg:phone":"+49 9335/97120",
    "sg:postcode":"97239",
    "sg:province":"Bayern",
    "wof:name":"Olaf Kreuzer Rechtsanwalt",
    "wof:placetype":"venue"
},
  "geometry": {"coordinates":[10.0698738098,49.555934906],"type":"Point"}
}