{
  "type": "Feature",
  "properties": {
    "iso:country":"DE",
    "sg:address":"Holstenstr. 14",
    "sg:city":"Kiel",
    "sg:phone":"+49 431/95207",
    "sg:postcode":"24103",
    "sg:province":"Schleswig-Holstein",
    "wof:name":"Co Op Schleswig-holstein Eg",
    "wof:placetype":"venue"
},
  "geometry": {"coordinates":[10.1384162903,54.3226776123],"type":"Point"}
}