{
  "type": "Feature",
  "properties": {
    "iso:country":"DE",
    "sg:address":"Sebachstr. 41",
    "sg:city":"Neunkirchen",
    "sg:phone":"+49 6821/33258",
    "sg:postcode":"66539",
    "sg:province":"Saarland",
    "wof:name":"Schulz",
    "wof:placetype":"venue"
},
  "geometry": {"coordinates":[7.231247,49.325462],"type":"Point"}
}