{
  "type": "Feature",
  "properties": {
    "iso:country":"DE",
    "sg:address":"Machtlfinger Str. 24",
    "sg:city":"M\u00fcnchen",
    "sg:phone":"+49 89/784491",
    "sg:postcode":"81379",
    "sg:province":"Bayern",
    "wof:name":"St\u00f6gra Antriebstechnik Gmbh",
    "wof:placetype":"venue"
},
  "geometry": {"coordinates":[11.513819,48.095055],"type":"Point"}
}