{
  "type": "Feature",
  "properties": {
    "iso:country":"DE",
    "sg:address":"Winkelgasse 7",
    "sg:city":"Aichhalden",
    "sg:phone":"+49 7422/52151",
    "sg:postcode":"78733",
    "sg:province":"Baden-W\u00fcrttemberg",
    "wof:name":"Annemarie Pfister",
    "wof:placetype":"venue"
},
  "geometry": {"coordinates":[8.3992071152,48.2671356201],"type":"Point"}
}