{
  "type": "Feature",
  "properties": {
    "iso:country":"DE",
    "sg:address":"Universit\u00e4tsstr. 13-17",
    "sg:city":"M\u00fcnster",
    "sg:phone":"+49 251/832520",
    "sg:postcode":"48143",
    "sg:province":"Nordrhein-Westfalen",
    "wof:name":"Universit\u00e4t M\u00fcnster Fachbereich 1 Ev. Theologie",
    "wof:placetype":"venue"
},
  "geometry": {"coordinates":[7.620034,51.960949],"type":"Point"}
}