{
  "type": "Feature",
  "properties": {
    "iso:country":"DE",
    "sg:address":"Spitzenweg 22",
    "sg:city":"Hanau",
    "sg:phone":"+49 6181/56893",
    "sg:postcode":"63457",
    "sg:province":"Hessen",
    "wof:name":"Inge Rupp-heyne Krankengymnastin",
    "wof:placetype":"venue"
},
  "geometry": {"coordinates":[8.95661,50.101318],"type":"Point"}
}