{
  "type": "Feature",
  "properties": {
    "iso:country":"DE",
    "sg:address":"Haus-Berge-Str. 234",
    "sg:city":"Essen",
    "sg:postcode":"45356",
    "sg:province":"Nordrhein-Westfalen",
    "wof:name":"Kath. \u00f6ffentliche Bibliothek St. Mari\u00e4 Rosenkranz",
    "wof:placetype":"venue"
},
  "geometry": {"coordinates":[6.976527,51.47937],"type":"Point"}
}