{
  "type": "Feature",
  "properties": {
    "iso:country":"DE",
    "sg:address":"Buntspechtweg 1",
    "sg:city":"Bonn",
    "sg:phone":"+49 228/962000",
    "sg:postcode":"53123",
    "sg:province":"Nordrhein-Westfalen",
    "wof:name":"E. Wiegel Parkett Und Fu\u00dfboden Gmbh",
    "wof:placetype":"venue"
},
  "geometry": {"coordinates":[7.0491127968,50.7173347473],"type":"Point"}
}