{
  "type": "Feature",
  "properties": {
    "iso:country":"DE",
    "sg:address":"Julius-Lo\u00dfmann-Str. 116",
    "sg:city":"N\u00fcrnberg",
    "sg:phone":"+49 911/485784",
    "sg:postcode":"90469",
    "sg:province":"Bayern",
    "wof:name":"Norma Lebensmittelfilial- Betrieb Gmbh & Co. Kg",
    "wof:placetype":"venue"
},
  "geometry": {"coordinates":[11.0841884613,49.4089164734],"type":"Point"}
}