{
  "type": "Feature",
  "properties": {
    "iso:country":"DE",
    "sg:address":"Schivelbeiner Str. 23",
    "sg:city":"Berlin",
    "sg:phone":"+49 30/44731886",
    "sg:postcode":"10439",
    "sg:province":"Berlin",
    "wof:name":"Gastst\u00e4tte Blaumilchkanal",
    "wof:placetype":"venue"
},
  "geometry": {"coordinates":[13.4041175842,52.5511779785],"type":"Point"}
}