{
  "type": "Feature",
  "properties": {
    "iso:country":"DE",
    "sg:address":"Kurf\u00fcrstenstr 49",
    "sg:city":"Frankfurt",
    "sg:phone":"+49 69/2477490",
    "sg:postcode":"60486",
    "sg:province":"Hessen",
    "wof:name":"Elsen & Hemer Betriebs Gmbh",
    "wof:placetype":"venue"
},
  "geometry": {"coordinates":[8.6411247253,50.1198005676],"type":"Point"}
}