{
  "type": "Feature",
  "properties": {
    "iso:country":"DE",
    "sg:address":"F\u00fcrstenwalder Poststr. 106",
    "sg:city":"Frankfurt",
    "sg:phone":"+49 335/414850",
    "sg:postcode":"15234",
    "sg:province":"Brandenburg",
    "wof:name":"Hoch- Und Tiefbau Gmbh",
    "wof:placetype":"venue"
},
  "geometry": {"coordinates":[14.479763031,52.3493270874],"type":"Point"}
}