{
  "type": "Feature",
  "properties": {
    "iso:country":"DE",
    "sg:address":"Bassumer Str. 3",
    "sg:city":"Bruchhausen-Vilsen",
    "sg:phone":"+49 4252/1454",
    "sg:postcode":"27305",
    "sg:province":"Niedersachsen",
    "wof:name":"Kath. \u00d6ffentliche Bibliothek",
    "wof:placetype":"venue"
},
  "geometry": {"coordinates":[8.983764,52.827679],"type":"Point"}
}