{
  "type": "Feature",
  "properties": {
    "iso:country":"DE",
    "sg:address":"Zobelsreuther Str. 36",
    "sg:city":"Hof",
    "sg:phone":"+49 9281/94322",
    "sg:postcode":"95032",
    "sg:province":"Bayern",
    "wof:name":"Betriebsges. Mbh",
    "wof:placetype":"venue"
},
  "geometry": {"coordinates":[11.9054689407,50.30078125],"type":"Point"}
}