{
  "type": "Feature",
  "properties": {
    "iso:country":"DE",
    "sg:address":"Eichenweg",
    "sg:city":"Spessart",
    "sg:postcode":"56746",
    "sg:province":"Rheinland-Pfalz",
    "wof:name":"Stilkerieg Gmbh",
    "wof:placetype":"venue"
},
  "geometry": {"coordinates":[7.113983,50.433231],"type":"Point"}
}