{
  "type": "Feature",
  "properties": {
    "iso:country":"DE",
    "sg:address":"Borghagener Str. 19",
    "sg:city":"Castrop-Rauxel",
    "sg:phone":"+49 2305/73801",
    "sg:postcode":"44581",
    "sg:province":"Nordrhein-Westfalen",
    "wof:name":"Gastst\u00e4tte Koch-willms",
    "wof:placetype":"venue"
},
  "geometry": {"coordinates":[7.3197078705,51.5874443054],"type":"Point"}
}