{
  "type": "Feature",
  "properties": {
    "iso:country":"DE",
    "sg:address":"Fechenheimer Weg 20",
    "sg:city":"Maintal",
    "sg:phone":"+49 6109/63114",
    "sg:postcode":"63477",
    "sg:province":"Hessen",
    "wof:name":"Hanni H\u00f6pfel",
    "wof:placetype":"venue"
},
  "geometry": {"coordinates":[8.800977,50.149471],"type":"Point"}
}