{
  "type": "Feature",
  "properties": {
    "iso:country":"DE",
    "sg:address":"Riethornweg 10",
    "sg:city":"Burgdorf",
    "sg:phone":"+49 5136/82811",
    "sg:postcode":"31303",
    "sg:province":"Niedersachsen",
    "wof:name":"Sch\u00fctzenkate",
    "wof:placetype":"venue"
},
  "geometry": {"coordinates":[10.031826973,52.4588241577],"type":"Point"}
}