{
  "type": "Feature",
  "properties": {
    "iso:country":"DE",
    "sg:address":"Georgstr. 20",
    "sg:city":"Bremerhaven",
    "sg:postcode":"27570",
    "sg:province":"Bremen",
    "wof:name":"Akuss Resamed Gmbh",
    "wof:placetype":"venue"
},
  "geometry": {"coordinates":[8.5888023376,53.5336151123],"type":"Point"}
}