{
  "type": "Feature",
  "properties": {
    "iso:country":"DE",
    "sg:address":"Elisabethenstr. 11",
    "sg:city":"Offenbach",
    "sg:postcode":"63071",
    "sg:province":"Hessen",
    "wof:name":"Seyfert Wellpappe",
    "wof:placetype":"venue"
},
  "geometry": {"coordinates":[8.7755212784,50.0968284607],"type":"Point"}
}