{
  "type": "Feature",
  "properties": {
    "iso:country":"DE",
    "sg:address":"Kaiserstr. 75",
    "sg:city":"Haan",
    "sg:phone":"+49 212/92656",
    "sg:postcode":"42781",
    "sg:province":"Nordrhein-Westfalen",
    "wof:name":"E. Und M. Laux Kunstgewerbe",
    "wof:placetype":"venue"
},
  "geometry": {"coordinates":[7.013859,51.193214],"type":"Point"}
}