{
  "type": "Feature",
  "properties": {
    "iso:country":"DE",
    "sg:address":"Gro\u00dfe Bleichen 31",
    "sg:city":"Hamburg",
    "sg:postcode":"20354",
    "sg:province":"Hamburg",
    "wof:name":"Hinno-systeme",
    "wof:placetype":"venue"
},
  "geometry": {"coordinates":[9.9882335663,53.5522956848],"type":"Point"}
}