{
  "type": "Feature",
  "properties": {
    "iso:country":"DE",
    "sg:address":"Tulpenstr. 5",
    "sg:city":"Dienheim",
    "sg:phone":"+49 6133/925151",
    "sg:postcode":"55276",
    "sg:province":"Rheinland-Pfalz",
    "wof:name":"Ecos Electronic Communication Services Gmbh",
    "wof:placetype":"venue"
},
  "geometry": {"coordinates":[8.3528938293,49.8399581909],"type":"Point"}
}