{
  "type": "Feature",
  "properties": {
    "iso:country":"DE",
    "sg:address":"Oberberghofstr. 31",
    "sg:city":"Blaustein",
    "sg:phone":"+49 7304/919140",
    "sg:postcode":"89134",
    "sg:province":"Baden-W\u00fcrttemberg",
    "wof:name":"Rolf Verheyen",
    "wof:placetype":"venue"
},
  "geometry": {"coordinates":[9.9251966476,48.417137146],"type":"Point"}
}