{
  "type": "Feature",
  "properties": {
    "iso:country":"DE",
    "sg:address":"Gro\u00dfe Forststr. 224",
    "sg:city":"Niederzier",
    "sg:phone":"+49 2428/2550",
    "sg:postcode":"52382",
    "sg:province":"Nordrhein-Westfalen",
    "wof:name":"Heinz Iven",
    "wof:placetype":"venue"
},
  "geometry": {"coordinates":[6.447194,50.898109],"type":"Point"}
}