{
  "type": "Feature",
  "properties": {
    "iso:country":"DE",
    "sg:address":"Josef-Spehl-Str. 43",
    "sg:city":"Heinsberg",
    "sg:phone":"+49 2452/64011",
    "sg:postcode":"52525",
    "sg:province":"Nordrhein-Westfalen",
    "wof:name":"Anton Hilgers Steuerberater",
    "wof:placetype":"venue"
},
  "geometry": {"coordinates":[6.1310200691,51.0486335754],"type":"Point"}
}