{
  "type": "Feature",
  "properties": {
    "iso:country":"DE",
    "sg:address":"Am Rohrteich 9",
    "sg:city":"Prenzlau",
    "sg:phone":"+49 3984/71558",
    "sg:postcode":"17291",
    "sg:province":"Brandenburg",
    "wof:name":"Friedrich Burmeister",
    "wof:placetype":"venue"
},
  "geometry": {"coordinates":[13.8443088531,53.3107032776],"type":"Point"}
}