{
  "type": "Feature",
  "properties": {
    "iso:country":"DE",
    "sg:address":"S\u00fcdgraben 22",
    "sg:city":"Dorsten",
    "sg:phone":"+49 2362/26131",
    "sg:postcode":"46282",
    "sg:province":"Nordrhein-Westfalen",
    "wof:name":"Antalya Grill",
    "wof:placetype":"venue"
},
  "geometry": {"coordinates":[6.9659590721,51.6594314575],"type":"Point"}
}