{
  "type": "Feature",
  "properties": {
    "iso:country":"DE",
    "sg:address":"Draisstr. 60",
    "sg:city":"Speyer",
    "sg:phone":"+49 4962/326900",
    "sg:postcode":"67346",
    "sg:province":"Rheinland-Pfalz",
    "wof:name":"Hans Rappold Offsetdruck Gmbh",
    "wof:placetype":"venue"
},
  "geometry": {"coordinates":[8.4193620682,49.3399620056],"type":"Point"}
}