{
  "type": "Feature",
  "properties": {
    "iso:country":"DE",
    "sg:address":"Allmendstr. 13",
    "sg:city":"Rosenfeld",
    "sg:phone":"+49 7427/7207",
    "sg:postcode":"72348",
    "sg:province":"Baden-W\u00fcrttemberg",
    "wof:name":"Vereinsgastst\u00e4tte Sportverein T\u00e4bingen",
    "wof:placetype":"venue"
},
  "geometry": {"coordinates":[8.7230319977,48.2427024841],"type":"Point"}
}