{
  "type": "Feature",
  "properties": {
    "iso:country":"DE",
    "sg:address":"Frankfurter Str. 33",
    "sg:city":"Netphen",
    "sg:phone":"+49 2737/591539",
    "sg:postcode":"57250",
    "sg:province":"Nordrhein-Westfalen",
    "wof:name":"D\u00fcrschke & Meiswinkel",
    "wof:placetype":"venue"
},
  "geometry": {"coordinates":[8.1821289062,50.8668861389],"type":"Point"}
}