{
  "type": "Feature",
  "properties": {
    "iso:country":"DE",
    "sg:address":"H\u00f6chste Str. 23",
    "sg:city":"Gelsenkirchen",
    "sg:phone":"+49 209/940750",
    "sg:postcode":"45883",
    "sg:province":"Nordrhein-Westfalen",
    "wof:name":"Hfb Handelsgesellschaft F\u00fcr B\u00fcrokommunikation Gmbh",
    "wof:placetype":"venue"
},
  "geometry": {"coordinates":[7.0613260269,51.5191345215],"type":"Point"}
}