{
  "type": "Feature",
  "properties": {
    "iso:country":"DE",
    "sg:address":"K\u00f6nig-Wilhelm-Str. 31",
    "sg:city":"Ilsfeld",
    "sg:phone":"+49 7062/6801",
    "sg:postcode":"74360",
    "sg:province":"Baden-W\u00fcrttemberg",
    "wof:name":"Hotel-gasthof Ochsen",
    "wof:placetype":"venue"
},
  "geometry": {"coordinates":[9.2475643158,49.0552749634],"type":"Point"}
}