{
  "type": "Feature",
  "properties": {
    "iso:country":"DE",
    "sg:address":"Breitensteinstr. 7",
    "sg:city":"Herrenberg",
    "sg:phone":"+49 7032/24653",
    "sg:postcode":"71083",
    "sg:province":"Baden-W\u00fcrttemberg",
    "wof:name":"Erwin Donner",
    "wof:placetype":"venue"
},
  "geometry": {"coordinates":[8.8420991898,48.5822257996],"type":"Point"}
}