{
  "type": "Feature",
  "properties": {
    "iso:country":"DE",
    "sg:address":"Mittelstr. 6",
    "sg:city":"Diesbar-Seu\u00dflitz",
    "sg:phone":"+49 35267/50331",
    "sg:postcode":"01612",
    "sg:province":"Sachsen",
    "wof:name":"G\u00f6tze Immobilienmakler",
    "wof:placetype":"venue"
},
  "geometry": {"coordinates":[13.3953895569,51.2980995178],"type":"Point"}
}