{
  "type": "Feature",
  "properties": {
    "iso:country":"DE",
    "sg:address":"Brandenburger Str. 3",
    "sg:city":"Wesseling",
    "sg:phone":"+49 2236/1448",
    "sg:postcode":"50389",
    "sg:province":"Nordrhein-Westfalen",
    "wof:name":"T\u00fcrkisch-deutscher Freundschaftsverein",
    "wof:placetype":"venue"
},
  "geometry": {"coordinates":[6.9656047821,50.8120384216],"type":"Point"}
}