{
  "type": "Feature",
  "properties": {
    "iso:country":"DE",
    "sg:address":"Postfach 3042",
    "sg:city":"Coburg",
    "sg:phone":"+49 9561/95002",
    "sg:postcode":"96419",
    "sg:province":"Bayern",
    "wof:name":"Reinigungs- Und Fuhramt",
    "wof:placetype":"venue"
},
  "geometry": {"coordinates":[10.9660301208,50.2577705383],"type":"Point"}
}