{
  "type": "Feature",
  "properties": {
    "iso:country":"DE",
    "sg:address":"Gei\u00dfmannsdorfer Str. 34",
    "sg:city":"Bischofswerda",
    "sg:phone":"+49 3594/706695",
    "sg:postcode":"01877",
    "sg:province":"Sachsen",
    "wof:name":"Gei\u00dfmannsdorfer Agrar Gmbh",
    "wof:placetype":"venue"
},
  "geometry": {"coordinates":[14.165375,51.144394],"type":"Point"}
}