{
  "type": "Feature",
  "properties": {
    "iso:country":"DE",
    "sg:address":"Delecker Weg 31",
    "sg:city":"M\u00f6hnesee",
    "sg:phone":"+49 2924/2200",
    "sg:postcode":"59519",
    "sg:province":"Nordrhein-Westfalen",
    "wof:name":"K U. K K\u00e4lte Und Klima Handels-vertriebs-gmbh",
    "wof:placetype":"venue"
},
  "geometry": {"coordinates":[8.0875768661,51.5076065063],"type":"Point"}
}