{
  "type": "Feature",
  "properties": {
    "iso:country":"DE",
    "sg:address":"Eisdorfer Str. 30",
    "sg:city":"Bennstedt",
    "sg:phone":"+49 34601/360",
    "sg:postcode":"06179",
    "sg:province":"Sachsen-Anhalt",
    "wof:name":"Sconto Sb Der M\u00f6belmarkt Gmbh & Co. Kg",
    "wof:placetype":"venue"
},
  "geometry": {"coordinates":[11.8219013214,51.4751853943],"type":"Point"}
}