{
  "type": "Feature",
  "properties": {
    "iso:country":"DE",
    "sg:city":"F\u00fcrstenau",
    "sg:postcode":"49584",
    "sg:province":"Niedersachsen",
    "wof:name":"Kontakte",
    "wof:placetype":"venue"
},
  "geometry": {"coordinates":[7.679179,52.517715],"type":"Point"}
}