{
  "type": "Feature",
  "properties": {
    "iso:country":"DE",
    "sg:address":"Gro\u00dfe Riehen 5-7",
    "sg:city":"Bremen",
    "sg:postcode":"28239",
    "sg:province":"Bremen",
    "wof:name":"Pe-ra Marketing Und Vertrieb Gmbh",
    "wof:placetype":"venue"
},
  "geometry": {"coordinates":[8.7223939896,53.1346626282],"type":"Point"}
}