{
  "type": "Feature",
  "properties": {
    "iso:country":"DE",
    "sg:address":"Zettachring 6",
    "sg:city":"Stuttgart",
    "sg:phone":"+49 711/7289011",
    "sg:postcode":"70567",
    "sg:province":"Baden-W\u00fcrttemberg",
    "wof:name":"Crouzet Gmbh",
    "wof:placetype":"venue"
},
  "geometry": {"coordinates":[9.171898,48.709862],"type":"Point"}
}