{
  "type": "Feature",
  "properties": {
    "iso:country":"DE",
    "sg:address":"Marktplatz 7",
    "sg:city":"Langenhagen",
    "sg:phone":"+49 511/775712",
    "sg:postcode":"30853",
    "sg:province":"Niedersachsen",
    "wof:name":"Inclusiv-vollreinigung",
    "wof:placetype":"venue"
},
  "geometry": {"coordinates":[9.738003,52.439648],"type":"Point"}
}