{
  "type": "Feature",
  "properties": {
    "iso:country":"DE",
    "sg:address":"Siemensstr. 1",
    "sg:city":"Goch",
    "sg:phone":"+49 2823/3182",
    "sg:postcode":"47574",
    "sg:province":"Nordrhein-Westfalen",
    "wof:name":"Heinz Kempkes",
    "wof:placetype":"venue"
},
  "geometry": {"coordinates":[6.144895,51.682346],"type":"Point"}
}