{
  "type": "Feature",
  "properties": {
    "iso:country":"DE",
    "sg:address":"M\u00fchlfelder Str. 32",
    "sg:city":"Herrsching",
    "sg:phone":"+49 8152/8632",
    "sg:postcode":"82211",
    "sg:province":"Bayern",
    "wof:name":"Warthona & Sohn",
    "wof:placetype":"venue"
},
  "geometry": {"coordinates":[11.173708,47.994713],"type":"Point"}
}