{
  "type": "Feature",
  "properties": {
    "iso:country":"DE",
    "sg:address":"Oggetal 16",
    "sg:city":"Medebach",
    "sg:phone":"+49 2982/92900",
    "sg:postcode":"59964",
    "sg:province":"Nordrhein-Westfalen",
    "wof:name":"Spedition Alfons Brass Gmbh",
    "wof:placetype":"venue"
},
  "geometry": {"coordinates":[8.721280098,51.2465286255],"type":"Point"}
}