{
  "type": "Feature",
  "properties": {
    "iso:country":"DE",
    "sg:address":"Arnold-Freund-Str. 27",
    "sg:city":"Bedburg",
    "sg:phone":"+49 2272/1334",
    "sg:postcode":"50181",
    "sg:province":"Nordrhein-Westfalen",
    "wof:name":"Semedano Medizin- Und Bauplanungs-",
    "wof:placetype":"venue"
},
  "geometry": {"coordinates":[6.5747961998,50.9969100952],"type":"Point"}
}