{
  "type": "Feature",
  "properties": {
    "iso:country":"DE",
    "sg:address":"Rubensstr. 1 a",
    "sg:city":"Rosenheim",
    "sg:phone":"+49 8031/68024",
    "sg:postcode":"83026",
    "sg:province":"Bayern",
    "wof:name":"Wpm Handelsges. Mbh",
    "wof:placetype":"venue"
},
  "geometry": {"coordinates":[12.1263122559,47.8359985352],"type":"Point"}
}