{
  "type": "Feature",
  "properties": {
    "iso:country":"DE",
    "sg:address":"Harth\u00e4user Hauptstr. 1",
    "sg:city":"Filderstadt",
    "sg:phone":"+49 7158/67576",
    "sg:postcode":"70794",
    "sg:province":"Baden-W\u00fcrttemberg",
    "wof:name":"Flying Pizza Service",
    "wof:placetype":"venue"
},
  "geometry": {"coordinates":[9.246497,48.648163],"type":"Point"}
}