{
  "type": "Feature",
  "properties": {
    "iso:country":"DE",
    "sg:address":"Meller Landstr. 68",
    "sg:city":"Osnabr\u00fcck",
    "sg:phone":"+49 541/387310",
    "sg:postcode":"49086",
    "sg:province":"Niedersachsen",
    "wof:name":"Gastst\u00e4tte B. Gr\u00fcssing",
    "wof:placetype":"venue"
},
  "geometry": {"coordinates":[8.1036939621,52.2506408691],"type":"Point"}
}