{
  "type": "Feature",
  "properties": {
    "iso:country":"DE",
    "sg:address":"F\u00fcrstenhagen 31 A",
    "sg:city":"Conow",
    "sg:phone":"+49 39831/20461",
    "sg:postcode":"17258",
    "sg:province":"Mecklenburg-Vorpommern",
    "wof:name":"Gut Conow Milchwirtschaft Verwaltungsgesellschaft Mbh",
    "wof:placetype":"venue"
},
  "geometry": {"coordinates":[13.438325,53.335232],"type":"Point"}
}