{
  "type": "Feature",
  "properties": {
    "iso:country":"DE",
    "sg:address":"Ostlandstr. 9",
    "sg:city":"Bad Salzschlirf",
    "sg:phone":"+49 6648/2176",
    "sg:postcode":"36364",
    "sg:province":"Hessen",
    "wof:name":"G\u00e4stehaus Johanna Hahn",
    "wof:placetype":"venue"
},
  "geometry": {"coordinates":[9.5108470917,50.6258964539],"type":"Point"}
}