{
  "type": "Feature",
  "properties": {
    "iso:country":"DE",
    "sg:address":"Waldschulstr. 73",
    "sg:city":"M\u00fcnchen",
    "sg:postcode":"81827",
    "sg:province":"Bayern",
    "wof:name":"Nelumbo Pharma-chemie Export E. K.",
    "wof:placetype":"venue"
},
  "geometry": {"coordinates":[11.698266983,48.1053466797],"type":"Point"}
}