{
  "type": "Feature",
  "properties": {
    "iso:country":"DE",
    "sg:address":"Rheinallee 4",
    "sg:city":"Bodenheim",
    "sg:phone":"+49 6135/4567",
    "sg:postcode":"55294",
    "sg:province":"Rheinland-Pfalz",
    "wof:name":"Penny-markt Gmbh",
    "wof:placetype":"venue"
},
  "geometry": {"coordinates":[8.3104000092,49.9307861328],"type":"Point"}
}