{
  "type": "Feature",
  "properties": {
    "iso:country":"DE",
    "sg:address":"Trosslerstr. 9",
    "sg:city":"Herzogenaurach",
    "sg:postcode":"91074",
    "sg:province":"Bayern",
    "wof:name":"Aru-parkett J\u00f6rg Scheibe E. K.",
    "wof:placetype":"venue"
},
  "geometry": {"coordinates":[10.8992204666,49.5711517334],"type":"Point"}
}