{
  "type": "Feature",
  "properties": {
    "iso:country":"DE",
    "sg:address":"Niedereschacher Str 44",
    "sg:city":"Dauchingen",
    "sg:phone":"+49 7720/65000",
    "sg:postcode":"78083",
    "sg:province":"Baden-W\u00fcrttemberg",
    "wof:name":"A. Ferentschik",
    "wof:placetype":"venue"
},
  "geometry": {"coordinates":[8.5506067276,48.0964622498],"type":"Point"}
}