{
  "type": "Feature",
  "properties": {
    "iso:country":"DE",
    "sg:address":"Allmandg\u00e4\u00dfle 13",
    "sg:city":"Sulz",
    "sg:phone":"+49 7454/2597",
    "sg:postcode":"72172",
    "sg:province":"Baden-W\u00fcrttemberg",
    "wof:name":"Herbert Stockburger",
    "wof:placetype":"venue"
},
  "geometry": {"coordinates":[8.63476,48.36161],"type":"Point"}
}