{
  "type": "Feature",
  "properties": {
    "iso:country":"DE",
    "sg:address":"Martin-Luther-Str. 6",
    "sg:city":"M\u00fcnster",
    "sg:phone":"+49 251/274009",
    "sg:postcode":"48147",
    "sg:province":"Nordrhein-Westfalen",
    "wof:name":"Thomas Fischer",
    "wof:placetype":"venue"
},
  "geometry": {"coordinates":[7.615908,51.972271],"type":"Point"}
}