{
  "type": "Feature",
  "properties": {
    "iso:country":"DE",
    "sg:address":"Oststr. 16",
    "sg:city":"Grevenbroich",
    "sg:phone":"+49 2181/73273",
    "sg:postcode":"41516",
    "sg:province":"Nordrhein-Westfalen",
    "wof:name":"E. G. Hansen Steuerberater Und",
    "wof:placetype":"venue"
},
  "geometry": {"coordinates":[6.6241202354,51.105506897],"type":"Point"}
}