{
  "type": "Feature",
  "properties": {
    "iso:country":"DE",
    "sg:address":"Bahnhofstr. 40",
    "sg:city":"Jever",
    "sg:phone":"+49 4461/72331",
    "sg:postcode":"26441",
    "sg:province":"Niedersachsen",
    "wof:name":"Versicherungsagentur",
    "wof:placetype":"venue"
},
  "geometry": {"coordinates":[7.891600132,53.5703659058],"type":"Point"}
}