{
  "type": "Feature",
  "properties": {
    "iso:country":"DE",
    "sg:address":"Helenenstr. 8",
    "sg:city":"Thalheim",
    "sg:phone":"+49 3721/30923",
    "sg:postcode":"09380",
    "sg:province":"Sachsen",
    "wof:name":"D. Saupe",
    "wof:placetype":"venue"
},
  "geometry": {"coordinates":[12.855048,50.703079],"type":"Point"}
}