{
  "type": "Feature",
  "properties": {
    "iso:country":"DE",
    "sg:address":"Defreggerweg 19",
    "sg:city":"Leipzig",
    "sg:phone":"+49 341/2521477",
    "sg:postcode":"04328",
    "sg:province":"Sachsen",
    "wof:name":"Lutz Winkler",
    "wof:placetype":"venue"
},
  "geometry": {"coordinates":[12.461412,51.34737],"type":"Point"}
}