{
  "type": "Feature",
  "properties": {
    "iso:country":"DE",
    "sg:address":"Siemensstr 14",
    "sg:city":"Hainburg",
    "sg:phone":"+49 6182/990712",
    "sg:postcode":"63512",
    "sg:province":"Hessen",
    "wof:name":"Vsm Fertigungstechnik Gmbh",
    "wof:placetype":"venue"
},
  "geometry": {"coordinates":[8.965217,50.069557],"type":"Point"}
}