{
  "type": "Feature",
  "properties": {
    "iso:country":"DE",
    "sg:address":"Freudentaler Str. 3",
    "sg:city":"B\u00f6nnigheim",
    "sg:phone":"+49 7143/21580",
    "sg:postcode":"74357",
    "sg:province":"Baden-W\u00fcrttemberg",
    "wof:name":"Josef Kurz Ingenieur",
    "wof:placetype":"venue"
},
  "geometry": {"coordinates":[9.0936250687,49.0385856628],"type":"Point"}
}