{
  "type": "Feature",
  "properties": {
    "iso:country":"DE",
    "sg:address":"Briloner Str. 2",
    "sg:city":"Meschede",
    "sg:phone":"+49 291/6726",
    "sg:postcode":"59872",
    "sg:province":"Nordrhein-Westfalen",
    "wof:name":"J. Schrage",
    "wof:placetype":"venue"
},
  "geometry": {"coordinates":[8.286565,51.345779],"type":"Point"}
}