{
  "type": "Feature",
  "properties": {
    "iso:country":"DE",
    "sg:address":"Am Weidenbach 37",
    "sg:city":"K\u00f6ln",
    "sg:phone":"+49 221/315164",
    "sg:postcode":"50676",
    "sg:province":"Nordrhein-Westfalen",
    "wof:name":"Franz M\u00fcller Metzgerei",
    "wof:placetype":"venue"
},
  "geometry": {"coordinates":[6.9458260536,50.9278068542],"type":"Point"}
}