{
  "type": "Feature",
  "properties": {
    "iso:country":"DE",
    "sg:address":"Friedrichstr. 127",
    "sg:city":"Velbert",
    "sg:phone":"+49 2051/52679",
    "sg:postcode":"42551",
    "sg:province":"Nordrhein-Westfalen",
    "wof:name":"Horst Kitz",
    "wof:placetype":"venue"
},
  "geometry": {"coordinates":[7.044391,51.340782],"type":"Point"}
}