{
  "type": "Feature",
  "properties": {
    "iso:country":"DE",
    "sg:address":"Wiesenstr. 25",
    "sg:city":"Versmold",
    "sg:phone":"+49 5423/7072",
    "sg:postcode":"33775",
    "sg:province":"Nordrhein-Westfalen",
    "wof:name":"F. Wiltmann",
    "wof:placetype":"venue"
},
  "geometry": {"coordinates":[8.157144,52.036587],"type":"Point"}
}