{
  "type": "Feature",
  "properties": {
    "iso:country":"DE",
    "sg:address":"Schwieberdinger Str. 83",
    "sg:city":"Ludwigsburg",
    "sg:phone":"+49 7141/43243",
    "sg:postcode":"71636",
    "sg:province":"Baden-W\u00fcrttemberg",
    "wof:name":"Red Neck Cycles",
    "wof:placetype":"venue"
},
  "geometry": {"coordinates":[9.1714658737,48.8901672363],"type":"Point"}
}