{
  "type": "Feature",
  "properties": {
    "iso:country":"DE",
    "sg:address":"Maria-Ward-Str. 1 a",
    "sg:city":"M\u00fcnchen",
    "sg:phone":"+49 89/177084",
    "sg:postcode":"80638",
    "sg:province":"Bayern",
    "wof:name":"Institut F\u00fcr Genetik Der Universtit\u00e4t M\u00fcnchen",
    "wof:placetype":"venue"
},
  "geometry": {"coordinates":[11.5030403137,48.1610374451],"type":"Point"}
}