{
  "type": "Feature",
  "properties": {
    "iso:country":"DE",
    "sg:address":"Rodebachstr. 73",
    "sg:city":"Zella-Mehlis",
    "sg:phone":"+49 3682/482602",
    "sg:postcode":"98544",
    "sg:province":"Th\u00fcringen",
    "wof:name":"Hans Schwesinger",
    "wof:placetype":"venue"
},
  "geometry": {"coordinates":[10.667327,50.661152],"type":"Point"}
}