{
  "type": "Feature",
  "properties": {
    "iso:country":"DE",
    "sg:address":"In der Feldmark 8",
    "sg:city":"Bad Oeynhausen",
    "sg:phone":"+49 5731/866071",
    "sg:postcode":"32545",
    "sg:province":"Nordrhein-Westfalen",
    "wof:name":"K. Gebhardt",
    "wof:placetype":"venue"
},
  "geometry": {"coordinates":[8.7928066254,52.188785553],"type":"Point"}
}