{
  "type": "Feature",
  "properties": {
    "iso:country":"DE",
    "sg:address":"Mittelstr. 24",
    "sg:city":"Neuwied",
    "sg:phone":"+49 2631/23486",
    "sg:postcode":"56564",
    "sg:province":"Rheinland-Pfalz",
    "wof:name":"Claus Spindelb\u00f6ck",
    "wof:placetype":"venue"
},
  "geometry": {"coordinates":[7.4571528435,50.4281921387],"type":"Point"}
}