{
  "type": "Feature",
  "properties": {
    "iso:country":"DE",
    "sg:address":"Blumenstr. 2",
    "sg:city":"Sonthofen",
    "sg:phone":"+49 8321/89018",
    "sg:postcode":"87527",
    "sg:province":"Bayern",
    "wof:name":"Margot Mehmel",
    "wof:placetype":"venue"
},
  "geometry": {"coordinates":[10.278646,47.514301],"type":"Point"}
}