{
  "type": "Feature",
  "properties": {
    "iso:country":"DE",
    "sg:address":"Gartenstr. 10",
    "sg:city":"Pretzsch",
    "sg:phone":"+49 34926/57348",
    "sg:postcode":"06909",
    "sg:province":"Sachsen-Anhalt",
    "wof:name":"Pension An Der Dom\u00e4ne",
    "wof:placetype":"venue"
},
  "geometry": {"coordinates":[12.7967128754,51.7155189514],"type":"Point"}
}