{
  "type": "Feature",
  "properties": {
    "iso:country":"DE",
    "sg:address":"Fibigerstr. 155",
    "sg:city":"Hamburg",
    "sg:phone":"+49 40/53779266",
    "sg:postcode":"22419",
    "sg:province":"Hamburg",
    "wof:name":"Toll Haus Immobilien Gmbh",
    "wof:placetype":"venue"
},
  "geometry": {"coordinates":[10.0152587891,53.6744232178],"type":"Point"}
}