{
  "type": "Feature",
  "properties": {
    "iso:country":"DE",
    "sg:address":"Bergstr. 3",
    "sg:city":"Schliengen",
    "sg:phone":"+49 7635/81244",
    "sg:postcode":"79418",
    "sg:province":"Baden-W\u00fcrttemberg",
    "wof:name":"Siegfried Vomstein",
    "wof:placetype":"venue"
},
  "geometry": {"coordinates":[7.592764,47.763905],"type":"Point"}
}