{
  "type": "Feature",
  "properties": {
    "iso:country":"DE",
    "sg:address":"Bornheimer Landwehr 36",
    "sg:city":"Frankfurt",
    "sg:phone":"+49 69/449848",
    "sg:postcode":"60385",
    "sg:province":"Hessen",
    "wof:name":"Taxi Line Beteiligungs-gmbh",
    "wof:placetype":"venue"
},
  "geometry": {"coordinates":[8.7076559067,50.1226387024],"type":"Point"}
}