{
  "type": "Feature",
  "properties": {
    "iso:country":"DE",
    "sg:address":"Balanstr. 286",
    "sg:city":"M\u00fcnchen",
    "sg:phone":"+49 89/681356",
    "sg:postcode":"81549",
    "sg:province":"Bayern",
    "wof:name":"Ingfried Dachs",
    "wof:placetype":"venue"
},
  "geometry": {"coordinates":[11.6079788208,48.0969581604],"type":"Point"}
}