{
  "type": "Feature",
  "properties": {
    "iso:country":"DE",
    "sg:address":"Auf der Eich",
    "sg:city":"Mayen",
    "sg:phone":"+49 2651/490177",
    "sg:postcode":"56727",
    "sg:province":"Rheinland-Pfalz",
    "wof:name":"R. Werner Rechtsanwalt",
    "wof:placetype":"venue"
},
  "geometry": {"coordinates":[7.2269258499,50.3310890198],"type":"Point"}
}