{
  "type": "Feature",
  "properties": {
    "iso:country":"DE",
    "sg:address":"Hospitalstr. 11",
    "sg:city":"Magdeburg",
    "sg:postcode":"39124",
    "sg:province":"Sachsen-Anhalt",
    "wof:name":"Bauprojekt Magdeburg Gmbh",
    "wof:placetype":"venue"
},
  "geometry": {"coordinates":[11.639186,52.154743],"type":"Point"}
}