{
  "type": "Feature",
  "properties": {
    "iso:country":"DE",
    "sg:address":"Lindenplatz 3",
    "sg:city":"G\u00e4dheim",
    "sg:postcode":"97503",
    "sg:province":"Bayern",
    "wof:name":"Mefo-sport Gmbh",
    "wof:placetype":"venue"
},
  "geometry": {"coordinates":[10.3731470108,50.0195465088],"type":"Point"}
}