{
  "type": "Feature",
  "properties": {
    "iso:country":"DE",
    "sg:address":"Hauptstr. 54 d",
    "sg:city":"Bad Feilnbach",
    "sg:postcode":"83075",
    "sg:province":"Bayern",
    "wof:name":"Georg Krapfl Gmbh",
    "wof:placetype":"venue"
},
  "geometry": {"coordinates":[11.986505,47.799263],"type":"Point"}
}