{
  "type": "Feature",
  "properties": {
    "iso:country":"DE",
    "sg:address":"Kantstr. 39",
    "sg:city":"Leipzig",
    "sg:phone":"+49 341/9910227",
    "sg:postcode":"04275",
    "sg:province":"Sachsen",
    "wof:name":"Dr. Gottfried Kruse Ingenieur",
    "wof:placetype":"venue"
},
  "geometry": {"coordinates":[12.3753871918,51.3159408569],"type":"Point"}
}