{
  "type": "Feature",
  "properties": {
    "iso:country":"DE",
    "sg:address":"Privatstr. 7",
    "sg:city":"Edenkoben",
    "sg:phone":"+49 6323/3717",
    "sg:postcode":"67480",
    "sg:province":"Rheinland-Pfalz",
    "wof:name":"Dr. Heinrich Ader",
    "wof:placetype":"venue"
},
  "geometry": {"coordinates":[8.125265,49.280823],"type":"Point"}
}