{
  "type": "Feature",
  "properties": {
    "iso:country":"DE",
    "sg:address":"Johann-Stelling-Str. 1",
    "sg:city":"Gadebusch",
    "sg:phone":"+49 3886/2447",
    "sg:postcode":"19205",
    "sg:province":"Mecklenburg-Vorpommern",
    "wof:name":"Redaktion Gadebusch-rehnaer Zeitung",
    "wof:placetype":"venue"
},
  "geometry": {"coordinates":[11.1132097244,53.7011795044],"type":"Point"}
}