{
  "type": "Feature",
  "properties": {
    "iso:country":"DE",
    "sg:address":"Wenkenstr. 49",
    "sg:city":"Bad Salzuflen",
    "sg:phone":"+49 5222/61872",
    "sg:postcode":"32105",
    "sg:province":"Nordrhein-Westfalen",
    "wof:name":"Horst Biermann",
    "wof:placetype":"venue"
},
  "geometry": {"coordinates":[8.751797,52.086552],"type":"Point"}
}