{
  "type": "Feature",
  "properties": {
    "iso:country":"DE",
    "sg:address":"Markstr. 398",
    "sg:city":"Bochum",
    "sg:phone":"+49 234/460243",
    "sg:postcode":"44795",
    "sg:province":"Nordrhein-Westfalen",
    "wof:name":"Claudia Vollrath Praxis F\u00fcr Physiotherapie",
    "wof:placetype":"venue"
},
  "geometry": {"coordinates":[7.214934,51.442043],"type":"Point"}
}