{
  "type": "Feature",
  "properties": {
    "iso:country":"DE",
    "sg:address":"Engelbertstr. 31",
    "sg:city":"Gelsenkirchen",
    "sg:phone":"+49 209/9771110",
    "sg:postcode":"45892",
    "sg:province":"Nordrhein-Westfalen",
    "wof:name":"Delta Autotechnik-handel Verwaltungs- Gmbh",
    "wof:placetype":"venue"
},
  "geometry": {"coordinates":[7.1179051399,51.5781135559],"type":"Point"}
}