{
  "type": "Feature",
  "properties": {
    "iso:country":"DE",
    "sg:address":"Spielbudenplatz 18",
    "sg:city":"Hamburg",
    "sg:phone":"+49 40/3193100",
    "sg:postcode":"20359",
    "sg:province":"Hamburg",
    "wof:name":"F. Hesse Condomerie- Happy-erotic- Bazar",
    "wof:placetype":"venue"
},
  "geometry": {"coordinates":[9.9646272659,53.5492591858],"type":"Point"}
}