{
  "type": "Feature",
  "properties": {
    "iso:country":"DE",
    "sg:address":"Bahnhofstr. 10",
    "sg:city":"M\u00f6mlingen",
    "sg:phone":"+49 6022/3529",
    "sg:postcode":"63853",
    "sg:province":"Bayern",
    "wof:name":"K.-friedrich Klotz",
    "wof:placetype":"venue"
},
  "geometry": {"coordinates":[9.085606,49.853561],"type":"Point"}
}