{
  "type": "Feature",
  "properties": {
    "iso:country":"DE",
    "sg:address":"Hauptstr. 24",
    "sg:city":"Gro\u00dfenseebach",
    "sg:phone":"+49 9135/799265",
    "sg:postcode":"91091",
    "sg:province":"Bayern",
    "wof:name":"Christian Singer",
    "wof:placetype":"venue"
},
  "geometry": {"coordinates":[10.876147,49.631824],"type":"Point"}
}