{
  "type": "Feature",
  "properties": {
    "iso:country":"DE",
    "sg:address":"Schlo\u00dfstr. 7-9",
    "sg:city":"Bergisch Gladbach",
    "sg:postcode":"51429",
    "sg:province":"Nordrhein-Westfalen",
    "wof:name":"Isb Immobilienservice Bensberg E. K.",
    "wof:placetype":"venue"
},
  "geometry": {"coordinates":[7.1571598053,50.9665145874],"type":"Point"}
}