{
  "type": "Feature",
  "properties": {
    "iso:country":"DE",
    "sg:address":"Hauptstr. 116",
    "sg:city":"Bernkastel-Kues",
    "sg:phone":"+49 6531/8574",
    "sg:postcode":"54470",
    "sg:province":"Rheinland-Pfalz",
    "wof:name":"Bernhard Wiesner",
    "wof:placetype":"venue"
},
  "geometry": {"coordinates":[7.063864,49.934441],"type":"Point"}
}