{
  "type": "Feature",
  "properties": {
    "iso:country":"DE",
    "sg:address":"Sieghartstr. 5",
    "sg:city":"Ebersberg",
    "sg:phone":"+49 8092/20867",
    "sg:postcode":"85560",
    "sg:province":"Bayern",
    "wof:name":"K. Geiger",
    "wof:placetype":"venue"
},
  "geometry": {"coordinates":[11.96895,48.079315],"type":"Point"}
}