{
  "type": "Feature",
  "properties": {
    "iso:country":"DE",
    "sg:address":"Bahnhofstr. 27",
    "sg:city":"Senftenberg",
    "sg:postcode":"01968",
    "sg:province":"Brandenburg",
    "wof:name":"Freizeitklub Intakt E. V.",
    "wof:placetype":"venue"
},
  "geometry": {"coordinates":[14.0044784546,51.5224952698],"type":"Point"}
}