{
  "type": "Feature",
  "properties": {
    "iso:country":"DE",
    "sg:address":"Wedeler Landstr 93",
    "sg:city":"Hamburg",
    "sg:phone":"+49 40/8195400",
    "sg:postcode":"22559",
    "sg:province":"Hamburg",
    "wof:name":"Databit Edv Beratungs- Und Handelgesellschaft Mbh",
    "wof:placetype":"venue"
},
  "geometry": {"coordinates":[9.7490367889,53.5842857361],"type":"Point"}
}