{
  "type": "Feature",
  "properties": {
    "iso:country":"DE",
    "sg:address":"Loikumer Rott 26",
    "sg:city":"Hamminkeln",
    "sg:phone":"+49 2852/3965",
    "sg:postcode":"46499",
    "sg:province":"Nordrhein-Westfalen",
    "wof:name":"Sprock",
    "wof:placetype":"venue"
},
  "geometry": {"coordinates":[6.5880208015,51.7430229187],"type":"Point"}
}