{
  "type": "Feature",
  "properties": {
    "iso:country":"DE",
    "sg:address":"Bergstr. 8",
    "sg:city":"L\u00fcbben",
    "sg:phone":"+49 3546/8788",
    "sg:postcode":"15907",
    "sg:province":"Brandenburg",
    "wof:name":"Erwin Bauz",
    "wof:placetype":"venue"
},
  "geometry": {"coordinates":[13.879578,51.941406],"type":"Point"}
}