{
  "type": "Feature",
  "properties": {
    "iso:country":"DE",
    "sg:address":"Balthasar-D\u00fcring-Str. 6",
    "sg:city":"K\u00f6nigsberg",
    "sg:phone":"+49 9525/1421",
    "sg:postcode":"97486",
    "sg:province":"Bayern",
    "wof:name":"E. Und W. Spath",
    "wof:placetype":"venue"
},
  "geometry": {"coordinates":[10.5674104691,50.0773086548],"type":"Point"}
}