{
  "type": "Feature",
  "properties": {
    "iso:country":"DE",
    "sg:address":"Augustastr. 78",
    "sg:city":"Aachen",
    "sg:postcode":"52070",
    "sg:province":"Nordrhein-Westfalen",
    "wof:name":"Amtsgericht",
    "wof:placetype":"venue"
},
  "geometry": {"coordinates":[6.1018419266,50.7733306885],"type":"Point"}
}