{
  "type": "Feature",
  "properties": {
    "iso:country":"DE",
    "sg:address":"Postfach 1442:: 33794 Steinhagen:: Germany.^^Am Markt 29::",
    "sg:city":"Steinhagen",
    "sg:phone":"+49 5204/1010",
    "sg:postcode":"33803",
    "sg:province":"Nordrhein-Westfalen",
    "wof:name":"Volksbank Steinhagen Eg",
    "wof:placetype":"venue"
},
  "geometry": {"coordinates":[8.414257,52.004604],"type":"Point"}
}