{
  "type": "Feature",
  "properties": {
    "iso:country":"DE",
    "sg:address":"H\u00f6henkirchener Str. 30 b",
    "sg:city":"Feldkirchen-Westerham",
    "sg:phone":"+49 8063/1723",
    "sg:postcode":"83620",
    "sg:province":"Bayern",
    "wof:name":"Gertrud Gruber Massageparixis",
    "wof:placetype":"venue"
},
  "geometry": {"coordinates":[11.82484,47.903713],"type":"Point"}
}