{
  "type": "Feature",
  "properties": {
    "iso:country":"DE",
    "sg:address":"Mainzer Landstr. 619",
    "sg:city":"Frankfurt",
    "sg:phone":"+49 69/38996680",
    "sg:postcode":"65933",
    "sg:province":"Hessen",
    "wof:name":"Off Road Center Angelika Putz E. Kfr.",
    "wof:placetype":"venue"
},
  "geometry": {"coordinates":[8.5941343307,50.0999336243],"type":"Point"}
}