{
  "type": "Feature",
  "properties": {
    "iso:country":"DE",
    "sg:address":"Vohenstrau\u00dfer Str. 8",
    "sg:city":"Pleystein",
    "sg:phone":"+49 9654/537",
    "sg:postcode":"92714",
    "sg:province":"Bayern",
    "wof:name":"W. Sax",
    "wof:placetype":"venue"
},
  "geometry": {"coordinates":[12.405076,49.644779],"type":"Point"}
}