{
  "type": "Feature",
  "properties": {
    "iso:country":"DE",
    "sg:address":"Horsthauser Str. 176",
    "sg:city":"Herne",
    "sg:phone":"+49 2323/981023",
    "sg:postcode":"44628",
    "sg:province":"Nordrhein-Westfalen",
    "wof:name":"Rudolf Hampel",
    "wof:placetype":"venue"
},
  "geometry": {"coordinates":[7.2320599556,51.5611305237],"type":"Point"}
}