{
  "type": "Feature",
  "properties": {
    "iso:country":"DE",
    "sg:address":"Dannenberger Str. 15",
    "sg:city":"Gusborn",
    "sg:phone":"+49 5865/1219",
    "sg:postcode":"29476",
    "sg:province":"Niedersachsen",
    "wof:name":"Ts Die Autovermietung",
    "wof:placetype":"venue"
},
  "geometry": {"coordinates":[11.190961,53.084709],"type":"Point"}
}