{
  "type": "Feature",
  "properties": {
    "iso:country":"DE",
    "sg:address":"Lichtenrader Damm 51-57",
    "sg:city":"Berlin",
    "sg:phone":"+49 30/75608332",
    "sg:postcode":"12305",
    "sg:province":"Berlin",
    "wof:name":"Seniorenwohnheim Kurt-m\u00fcrre-haus",
    "wof:placetype":"venue"
},
  "geometry": {"coordinates":[13.40455,52.409233],"type":"Point"}
}