{
  "type": "Feature",
  "properties": {
    "iso:country":"DE",
    "sg:address":"E-Th\u00e4lmann Str. 16",
    "sg:city":"V\u00f6lpke",
    "sg:phone":"+49 39402/316",
    "sg:postcode":"39393",
    "sg:province":"Sachsen-Anhalt",
    "wof:name":"Kreissparkasse Oschersleben (b",
    "wof:placetype":"venue"
},
  "geometry": {"coordinates":[11.097297,52.137989],"type":"Point"}
}