{
  "type": "Feature",
  "properties": {
    "iso:country":"DE",
    "sg:address":"Eisenacher Str. 26",
    "sg:city":"Bebra",
    "sg:phone":"+49 6622/2112",
    "sg:postcode":"36179",
    "sg:province":"Hessen",
    "wof:name":"Prellbock",
    "wof:placetype":"venue"
},
  "geometry": {"coordinates":[9.7973651886,50.9646453857],"type":"Point"}
}