{
  "type": "Feature",
  "properties": {
    "iso:country":"DE",
    "sg:address":"Rosa-Luxemburg-Str. 14",
    "sg:city":"Remst\u00e4dt",
    "sg:phone":"+49 3621/28076",
    "sg:postcode":"99869",
    "sg:province":"Th\u00fcringen",
    "wof:name":"U. Backhaus",
    "wof:placetype":"venue"
},
  "geometry": {"coordinates":[10.690073967,50.9787559509],"type":"Point"}
}