{
  "type": "Feature",
  "properties": {
    "iso:country":"DE",
    "sg:address":"Industriestr 10",
    "sg:city":"S\u00fcdlohn",
    "sg:phone":"+49 2862/5810",
    "sg:postcode":"46354",
    "sg:province":"Nordrhein-Westfalen",
    "wof:name":"Bewital Gmbh & Co Kg",
    "wof:placetype":"venue"
},
  "geometry": {"coordinates":[6.821918,51.935036],"type":"Point"}
}