{
  "type": "Feature",
  "properties": {
    "iso:country":"DE",
    "sg:address":"Pfarrer-Sch\u00f6ller-Ring 6",
    "sg:city":"Priesendorf",
    "sg:phone":"+49 9549/981358",
    "sg:postcode":"96170",
    "sg:province":"Bayern",
    "wof:name":"H\u00fchnerstall",
    "wof:placetype":"venue"
},
  "geometry": {"coordinates":[10.7117090225,49.9068336487],"type":"Point"}
}