{
  "type": "Feature",
  "properties": {
    "iso:country":"DE",
    "sg:address":"Birkenweg 1",
    "sg:city":"Neunburg",
    "sg:phone":"+49 9672/2896",
    "sg:postcode":"92431",
    "sg:province":"Bayern",
    "wof:name":"Irmgard Kirchberger Architektin",
    "wof:placetype":"venue"
},
  "geometry": {"coordinates":[12.395714,49.353489],"type":"Point"}
}