{
  "type": "Feature",
  "properties": {
    "iso:country":"DE",
    "sg:address":"Saseler Chaussee 249",
    "sg:city":"Hamburg",
    "sg:phone":"+49 40/6011114",
    "sg:postcode":"22393",
    "sg:province":"Hamburg",
    "wof:name":"Rolf Schmitman Rechtsanwalt",
    "wof:placetype":"venue"
},
  "geometry": {"coordinates":[10.1112041473,53.6577110291],"type":"Point"}
}