{
  "type": "Feature",
  "properties": {
    "iso:country":"DE",
    "sg:address":"Lusenweg 2",
    "sg:city":"B\u00fcchlberg",
    "sg:phone":"+49 8582/436",
    "sg:postcode":"94124",
    "sg:province":"Bayern",
    "wof:name":"Pension Johann Krenn",
    "wof:placetype":"venue"
},
  "geometry": {"coordinates":[13.5364408493,48.7074432373],"type":"Point"}
}