{
  "type": "Feature",
  "properties": {
    "iso:country":"DE",
    "sg:address":"M\u00fchlenstr. 7",
    "sg:city":"March",
    "sg:phone":"+49 7665/930200",
    "sg:postcode":"79232",
    "sg:province":"Baden-W\u00fcrttemberg",
    "wof:name":"Mfw Mechanische Fertigung Wolf",
    "wof:placetype":"venue"
},
  "geometry": {"coordinates":[7.803842,48.072708],"type":"Point"}
}