{
  "type": "Feature",
  "properties": {
    "iso:country":"DE",
    "sg:address":"Hauptstr. 5",
    "sg:city":"Mainhardt",
    "sg:phone":"+49 7903/2336",
    "sg:postcode":"74535",
    "sg:province":"Baden-W\u00fcrttemberg",
    "wof:name":"J\u00fcrgen Assenheimer",
    "wof:placetype":"venue"
},
  "geometry": {"coordinates":[9.5577306747,49.0809745789],"type":"Point"}
}