{
  "type": "Feature",
  "properties": {
    "iso:country":"DE",
    "sg:address":"Elisabethstr. 9",
    "sg:city":"Lage",
    "sg:phone":"+49 5232/95960",
    "sg:postcode":"32791",
    "sg:province":"Nordrhein-Westfalen",
    "wof:name":"Lippische Milchverwertung Eg",
    "wof:placetype":"venue"
},
  "geometry": {"coordinates":[8.8029575348,51.9919319153],"type":"Point"}
}