{
  "type": "Feature",
  "properties": {
    "iso:country":"DE",
    "sg:address":"Ludwig-M\u00e4rz-Str. 32 a",
    "sg:city":"Penzberg",
    "sg:phone":"+49 8856/2921",
    "sg:postcode":"82377",
    "sg:province":"Bayern",
    "wof:name":"Manfred Reitmeier Steuerbevollm\u00e4chtigter",
    "wof:placetype":"venue"
},
  "geometry": {"coordinates":[11.3751239777,47.7451095581],"type":"Point"}
}