{
  "type": "Feature",
  "properties": {
    "iso:country":"DE",
    "sg:address":"Am Lohpohl 53a",
    "sg:city":"Bad Oeynhausen",
    "sg:postcode":"32549",
    "sg:province":"Nordrhein-Westfalen",
    "wof:name":"Handelsagentur Becker & Jachmann Gmbh",
    "wof:placetype":"venue"
},
  "geometry": {"coordinates":[8.8122558594,52.2264022827],"type":"Point"}
}