{
  "type": "Feature",
  "properties": {
    "iso:country":"DE",
    "sg:address":"Charlottenstr. 12",
    "sg:city":"Stuttgart",
    "sg:postcode":"70182",
    "sg:province":"Baden-W\u00fcrttemberg",
    "wof:name":"Kizomba E. V.",
    "wof:placetype":"venue"
},
  "geometry": {"coordinates":[9.1848154068,48.774520874],"type":"Point"}
}