{
  "type": "Feature",
  "properties": {
    "iso:country":"DE",
    "sg:address":"Oberstr. 3",
    "sg:city":"Attendorn",
    "sg:phone":"+49 2722/7759",
    "sg:postcode":"57439",
    "sg:province":"Nordrhein-Westfalen",
    "wof:name":"Werner Hellwig",
    "wof:placetype":"venue"
},
  "geometry": {"coordinates":[7.842264,51.107258],"type":"Point"}
}