{
  "type": "Feature",
  "properties": {
    "iso:country":"DE",
    "sg:address":"Bischof-Fischer-Str. 45",
    "sg:city":"Aalen",
    "sg:phone":"+49 7361/62737",
    "sg:postcode":"73430",
    "sg:province":"Baden-W\u00fcrttemberg",
    "wof:name":"A. Und G. Schwendtke",
    "wof:placetype":"venue"
},
  "geometry": {"coordinates":[10.0884914398,48.8370056152],"type":"Point"}
}