{
  "type": "Feature",
  "properties": {
    "iso:country":"DE",
    "sg:address":"Boehringerstr 17",
    "sg:city":"Mannheim",
    "sg:phone":"+49 621/7990830",
    "sg:postcode":"68307",
    "sg:province":"Baden-W\u00fcrttemberg",
    "wof:name":"Vipco Gmbh",
    "wof:placetype":"venue"
},
  "geometry": {"coordinates":[8.478489,49.535],"type":"Point"}
}