{
  "type": "Feature",
  "properties": {
    "iso:country":"DE",
    "sg:address":"Seestr. 12",
    "sg:city":"Dresden",
    "sg:phone":"+49 351/4956502",
    "sg:postcode":"01067",
    "sg:province":"Sachsen",
    "wof:name":"E. Khaireddin Architekt",
    "wof:placetype":"venue"
},
  "geometry": {"coordinates":[13.736638,51.048126],"type":"Point"}
}