{
  "type": "Feature",
  "properties": {
    "iso:country":"DE",
    "sg:address":"Bl\u00f6kenstr. 6",
    "sg:city":"Loxstedt",
    "sg:phone":"+49 4703/920179",
    "sg:postcode":"27612",
    "sg:province":"Niedersachsen",
    "wof:name":"Va Verwaltungs- Und Anlagen Gmbh",
    "wof:placetype":"venue"
},
  "geometry": {"coordinates":[8.714931,53.491787],"type":"Point"}
}