{
  "type": "Feature",
  "properties": {
    "iso:country":"DE",
    "sg:address":"Ortsstr. 138",
    "sg:city":"Birkenau",
    "sg:phone":"+49 6201/393015",
    "sg:postcode":"69488",
    "sg:province":"Hessen",
    "wof:name":"E. Netzer",
    "wof:placetype":"venue"
},
  "geometry": {"coordinates":[8.742227,49.565006],"type":"Point"}
}