{
  "type": "Feature",
  "properties": {
    "iso:country":"DE",
    "sg:address":"Neue Sorge 16",
    "sg:city":"Altenburg",
    "sg:phone":"+49 3447/315763",
    "sg:postcode":"04600",
    "sg:province":"Th\u00fcringen",
    "wof:name":"Helmut Hoffmann",
    "wof:placetype":"venue"
},
  "geometry": {"coordinates":[12.44182,50.990211],"type":"Point"}
}