{
  "type": "Feature",
  "properties": {
    "iso:country":"DE",
    "sg:address":"Brunebecker Str. 113",
    "sg:city":"Witten",
    "sg:phone":"+49 2302/80898",
    "sg:postcode":"58454",
    "sg:province":"Nordrhein-Westfalen",
    "wof:name":"Withold Kedziora Tennislehrer",
    "wof:placetype":"venue"
},
  "geometry": {"coordinates":[7.4082870483,51.4527015686],"type":"Point"}
}