{
  "type": "Feature",
  "properties": {
    "iso:country":"DE",
    "sg:address":"Neuenst\u00e4dter Str. 9-2",
    "sg:city":"Oedheim",
    "sg:phone":"+49 7136/20304",
    "sg:postcode":"74229",
    "sg:province":"Baden-W\u00fcrttemberg",
    "wof:name":"Karl Binnig",
    "wof:placetype":"venue"
},
  "geometry": {"coordinates":[9.2586584091,49.2400894165],"type":"Point"}
}