{
  "type": "Feature",
  "properties": {
    "iso:country":"DE",
    "sg:address":"Bahnhofstr. 1",
    "sg:city":"Cham",
    "sg:phone":"+49 9971/79276",
    "sg:postcode":"93413",
    "sg:province":"Bayern",
    "wof:name":"K\u00f6nig-apotheke",
    "wof:placetype":"venue"
},
  "geometry": {"coordinates":[12.658926,49.222721],"type":"Point"}
}