{
  "type": "Feature",
  "properties": {
    "iso:country":"DE",
    "sg:address":"Sickenhausen 9",
    "sg:city":"Kranzberg",
    "sg:phone":"+49 8165/8530",
    "sg:postcode":"85402",
    "sg:province":"Bayern",
    "wof:name":"Erich Past Gmbh",
    "wof:placetype":"venue"
},
  "geometry": {"coordinates":[11.6147899628,48.4060211182],"type":"Point"}
}