{
  "type": "Feature",
  "properties": {
    "iso:country":"DE",
    "sg:address":"In der Messe 27",
    "sg:city":"Stuttgart",
    "sg:phone":"+49 711/335451",
    "sg:postcode":"70327",
    "sg:province":"Baden-W\u00fcrttemberg",
    "wof:name":"E. Nemitz",
    "wof:placetype":"venue"
},
  "geometry": {"coordinates":[9.2622261047,48.7899246216],"type":"Point"}
}