{
  "type": "Feature",
  "properties": {
    "iso:country":"DE",
    "sg:address":"Freinsheimer Str. 1",
    "sg:city":"Dackenheim",
    "sg:phone":"+49 6353/3440",
    "sg:postcode":"67273",
    "sg:province":"Rheinland-Pfalz",
    "wof:name":"Helmut B\u00e4hr Weinanbau",
    "wof:placetype":"venue"
},
  "geometry": {"coordinates":[8.1854200363,49.5212516785],"type":"Point"}
}