{
  "type": "Feature",
  "properties": {
    "iso:country":"DE",
    "sg:address":"Auf dem Tigge 25",
    "sg:city":"Beckum",
    "sg:phone":"+49 2521/16103",
    "sg:postcode":"59269",
    "sg:province":"Nordrhein-Westfalen",
    "wof:name":"G. Steuer Sen. Und Jun. Kfz-autoverwertungsuntern.",
    "wof:placetype":"venue"
},
  "geometry": {"coordinates":[8.0850496292,51.7610626221],"type":"Point"}
}