{
  "type": "Feature",
  "properties": {
    "iso:country":"DE",
    "sg:address":"Pfauengasse 5",
    "sg:city":"Ulm",
    "sg:phone":"+49 731/64672",
    "sg:postcode":"89073",
    "sg:province":"Baden-W\u00fcrttemberg",
    "wof:name":"Ulmer Lederwarenhaus Inh. W. Gerlach",
    "wof:placetype":"venue"
},
  "geometry": {"coordinates":[9.989589,48.398693],"type":"Point"}
}