{
  "type": "Feature",
  "properties": {
    "iso:country":"DE",
    "sg:address":"Untere Str. 15",
    "sg:city":"Wipperf\u00fcrth",
    "sg:phone":"+49 2267/880017",
    "sg:postcode":"51688",
    "sg:province":"Nordrhein-Westfalen",
    "wof:name":"Bonita Gef\u00fchl F\u00fcr Mode Gmbh & Co. Kg",
    "wof:placetype":"venue"
},
  "geometry": {"coordinates":[7.395784,51.117035],"type":"Point"}
}