{
  "type": "Feature",
  "properties": {
    "iso:country":"DE",
    "sg:address":"Sierichstr. 132",
    "sg:city":"Hamburg",
    "sg:phone":"+49 40/4601979",
    "sg:postcode":"22299",
    "sg:province":"Hamburg",
    "wof:name":"Prospettive Darte",
    "wof:placetype":"venue"
},
  "geometry": {"coordinates":[10.000305,53.590717],"type":"Point"}
}