{
  "type": "Feature",
  "properties": {
    "iso:country":"DE",
    "sg:address":"F\u00e4rberstr. 22",
    "sg:city":"Ortenburg",
    "sg:postcode":"94496",
    "sg:province":"Bayern",
    "wof:name":"Max World E. K.",
    "wof:placetype":"venue"
},
  "geometry": {"coordinates":[13.22931,48.537037],"type":"Point"}
}