{
  "type": "Feature",
  "properties": {
    "iso:country":"DE",
    "sg:address":"R\u00f6merstr. 1",
    "sg:city":"Neunkirchen-Seelscheid",
    "sg:phone":"+49 2247/74200",
    "sg:postcode":"53819",
    "sg:province":"Nordrhein-Westfalen",
    "wof:name":"Sportladen Heyer & Nogge Sport- Und",
    "wof:placetype":"venue"
},
  "geometry": {"coordinates":[7.3249211311,50.871257782],"type":"Point"}
}