{
  "type": "Feature",
  "properties": {
    "iso:country":"DE",
    "sg:address":"Karl-G\u00fcnther-Str. 39",
    "sg:city":"Erbendorf",
    "sg:phone":"+49 9682/92130",
    "sg:postcode":"92681",
    "sg:province":"Bayern",
    "wof:name":"Josef Wallner Raumausstattung",
    "wof:placetype":"venue"
},
  "geometry": {"coordinates":[12.053,49.835751],"type":"Point"}
}