{
  "type": "Feature",
  "properties": {
    "iso:country":"DE",
    "sg:address":"Engerser Landstr. 1",
    "sg:city":"Bendorf",
    "sg:phone":"+49 4926/2210448",
    "sg:postcode":"56170",
    "sg:province":"Rheinland-Pfalz",
    "wof:name":"W. Eugen Fischer Plastbauteile Gmbh",
    "wof:placetype":"venue"
},
  "geometry": {"coordinates":[7.5699739456,50.4362678528],"type":"Point"}
}