{
  "type": "Feature",
  "properties": {
    "iso:country":"DE",
    "sg:address":"Tetzer Weg 4",
    "sg:city":"J\u00fclich",
    "sg:phone":"+49 2461/58635",
    "sg:postcode":"52428",
    "sg:province":"Nordrhein-Westfalen",
    "wof:name":"Ma Assekuranzmakler Gmbh",
    "wof:placetype":"venue"
},
  "geometry": {"coordinates":[6.3742990494,50.9625663757],"type":"Point"}
}