{
  "type": "Feature",
  "properties": {
    "iso:country":"DE",
    "sg:address":"N\u00f6rdliche M\u00fcnchner Str. 25",
    "sg:city":"Gr\u00fcnwald",
    "sg:phone":"+49 89/6498430",
    "sg:postcode":"82031",
    "sg:province":"Bayern",
    "wof:name":"Infometrica Me\u00df- Und Informationssysteme Gmbh",
    "wof:placetype":"venue"
},
  "geometry": {"coordinates":[11.5292043686,48.0462303162],"type":"Point"}
}