{
  "type": "Feature",
  "properties": {
    "iso:country":"DE",
    "sg:address":"Eisvogelweg 13",
    "sg:city":"M\u00fcnchen",
    "sg:phone":"+49 89/4303625",
    "sg:postcode":"81827",
    "sg:province":"Bayern",
    "wof:name":"Double Twist Gmbh",
    "wof:placetype":"venue"
},
  "geometry": {"coordinates":[11.693499,48.103851],"type":"Point"}
}