{
  "type": "Feature",
  "properties": {
    "iso:country":"DE",
    "sg:address":"Mathildenstr. 3",
    "sg:city":"Borken",
    "sg:phone":"+49 2861/1234",
    "sg:postcode":"46325",
    "sg:province":"Nordrhein-Westfalen",
    "wof:name":"Alois Gerwert",
    "wof:placetype":"venue"
},
  "geometry": {"coordinates":[6.855712,51.86507],"type":"Point"}
}