{
  "type": "Feature",
  "properties": {
    "iso:country":"DE",
    "sg:address":"Harzstr. 37",
    "sg:city":"Langelsheim",
    "sg:phone":"+49 5326/3687",
    "sg:postcode":"38685",
    "sg:province":"Niedersachsen",
    "wof:name":"Pfefferm\u00fchle",
    "wof:placetype":"venue"
},
  "geometry": {"coordinates":[10.3265838623,51.9355125427],"type":"Point"}
}