{
  "type": "Feature",
  "properties": {
    "iso:country":"DE",
    "sg:address":"Zur Almeke 2",
    "sg:city":"Medebach",
    "sg:phone":"+49 5632/7597",
    "sg:postcode":"59964",
    "sg:province":"Nordrhein-Westfalen",
    "wof:name":"Grundst\u00fccksverwaltungs Gbr",
    "wof:placetype":"venue"
},
  "geometry": {"coordinates":[8.6590967178,51.2414093018],"type":"Point"}
}