{
  "type": "Feature",
  "properties": {
    "iso:country":"DE",
    "sg:address":"R\u00f6merstr. 59",
    "sg:city":"M\u00f6nchengladbach",
    "sg:phone":"+49 2166/16047",
    "sg:postcode":"41238",
    "sg:province":"Nordrhein-Westfalen",
    "wof:name":"G\u00f6ters Vits Verwaltungs Gmbh",
    "wof:placetype":"venue"
},
  "geometry": {"coordinates":[6.457252,51.16367],"type":"Point"}
}