{
  "type": "Feature",
  "properties": {
    "iso:country":"DE",
    "sg:address":"Schmale Str. 22",
    "sg:city":"Korntal-M\u00fcnchingen",
    "sg:phone":"+49 7150/959970",
    "sg:postcode":"70825",
    "sg:province":"Baden-W\u00fcrttemberg",
    "wof:name":"Artwork",
    "wof:placetype":"venue"
},
  "geometry": {"coordinates":[9.091188,48.853302],"type":"Point"}
}