{
  "type": "Feature",
  "properties": {
    "iso:country":"DE",
    "sg:address":"Carl-Benz-Weg 10",
    "sg:city":"Bargteheide",
    "sg:phone":"+49 4532/3039",
    "sg:postcode":"22941",
    "sg:province":"Schleswig-Holstein",
    "wof:name":"Andresen Gmbh",
    "wof:placetype":"venue"
},
  "geometry": {"coordinates":[10.283326149,53.7215652466],"type":"Point"}
}