{
  "type": "Feature",
  "properties": {
    "iso:country":"DE",
    "sg:address":"Beimoorweg 29a",
    "sg:city":"Ahrensburg",
    "sg:phone":"+49 4979/17657",
    "sg:postcode":"22926",
    "sg:province":"Schleswig-Holstein",
    "wof:name":"Catena Schmuckgalerie Gmbh",
    "wof:placetype":"venue"
},
  "geometry": {"coordinates":[9.73623,49.114761],"type":"Point"}
}