{
  "type": "Feature",
  "properties": {
    "iso:country":"DE",
    "sg:address":"Kiebitzstr. 60",
    "sg:city":"Leipzig",
    "sg:phone":"+49 341/2328194",
    "sg:postcode":"04349",
    "sg:province":"Sachsen",
    "wof:name":"Ralf Stottmeier",
    "wof:placetype":"venue"
},
  "geometry": {"coordinates":[12.428708,51.380634],"type":"Point"}
}