{
  "type": "Feature",
  "properties": {
    "iso:country":"DE",
    "sg:address":"G\u00fcnthersburgallee 92",
    "sg:city":"Frankfurt",
    "sg:phone":"+49 69/464502",
    "sg:postcode":"60389",
    "sg:province":"Hessen",
    "wof:name":"Ernst Seiffert Steuerberater",
    "wof:placetype":"venue"
},
  "geometry": {"coordinates":[8.7000904083,50.1281013489],"type":"Point"}
}