{
  "type": "Feature",
  "properties": {
    "iso:country":"DE",
    "sg:address":"Waldkirchener Str. 2",
    "sg:city":"Zschopau",
    "sg:phone":"+49 3725/34610",
    "sg:postcode":"09405",
    "sg:province":"Sachsen",
    "wof:name":"Szh Sanit\u00e4r Heizung Und Bau-klempner Gmbh",
    "wof:placetype":"venue"
},
  "geometry": {"coordinates":[13.0749063492,50.7476119995],"type":"Point"}
}