{
  "type": "Feature",
  "properties": {
    "iso:country":"DE",
    "sg:address":"Winsener Str. 180",
    "sg:city":"Hamburg",
    "sg:phone":"+49 40/7686196",
    "sg:postcode":"21077",
    "sg:province":"Hamburg",
    "wof:name":"Walter Von Elling",
    "wof:placetype":"venue"
},
  "geometry": {"coordinates":[9.9818115234,53.4280815125],"type":"Point"}
}