{
  "type": "Feature",
  "properties": {
    "iso:country":"DE",
    "sg:address":"Gustav-Deetjen",
    "sg:city":"Bremen",
    "sg:phone":"+49 4951/156600",
    "sg:postcode":"28215",
    "sg:province":"Bremen",
    "wof:name":"Tui Ag",
    "wof:placetype":"venue"
},
  "geometry": {"coordinates":[9.8106136322,52.3836860657],"type":"Point"}
}