{
  "type": "Feature",
  "properties": {
    "iso:country":"DE",
    "sg:address":"Heusweiler Str. 69",
    "sg:city":"Lebach",
    "sg:phone":"+49 6881/2456",
    "sg:postcode":"66822",
    "sg:province":"Saarland",
    "wof:name":"Franz Sch\u00e4fer",
    "wof:placetype":"venue"
},
  "geometry": {"coordinates":[6.926204,49.388557],"type":"Point"}
}