{
  "type": "Feature",
  "properties": {
    "iso:country":"DE",
    "sg:address":"Lindenstr. 24",
    "sg:city":"Freilassing",
    "sg:phone":"+49 8654/49300",
    "sg:postcode":"83395",
    "sg:province":"Bayern",
    "wof:name":"Anton Hogger Reiseb\u00fcro",
    "wof:placetype":"venue"
},
  "geometry": {"coordinates":[12.9798431396,47.8392066956],"type":"Point"}
}