{
  "type": "Feature",
  "properties": {
    "iso:country":"DE",
    "sg:address":"Regerstr. 17",
    "sg:city":"Berglen",
    "sg:phone":"+49 7195/71157",
    "sg:postcode":"73663",
    "sg:province":"Baden-W\u00fcrttemberg",
    "wof:name":"Manfred Moser",
    "wof:placetype":"venue"
},
  "geometry": {"coordinates":[9.4696750641,48.8644256592],"type":"Point"}
}