{
  "type": "Feature",
  "properties": {
    "iso:country":"DE",
    "sg:address":"Olper Str. 31",
    "sg:city":"Overath",
    "sg:phone":"+49 2204/71010",
    "sg:postcode":"51491",
    "sg:province":"Nordrhein-Westfalen",
    "wof:name":"Gl\u00fcckauf-apotheke",
    "wof:placetype":"venue"
},
  "geometry": {"coordinates":[7.327124,50.969658],"type":"Point"}
}