{
  "type": "Feature",
  "properties": {
    "iso:country":"DE",
    "sg:address":"Maxweiler Str. 1",
    "sg:city":"Neuburg",
    "sg:phone":"+49 8454/1234",
    "sg:postcode":"86633",
    "sg:province":"Bayern",
    "wof:name":"Karl Schl\u00e4fer",
    "wof:placetype":"venue"
},
  "geometry": {"coordinates":[11.286766,48.720245],"type":"Point"}
}