{
  "type": "Feature",
  "properties": {
    "iso:country":"DE",
    "sg:address":"Marsstr. 12",
    "sg:city":"M\u00fcnchen",
    "sg:phone":"+49 89/555505",
    "sg:postcode":"80335",
    "sg:province":"Bayern",
    "wof:name":"Brigitte Hahn",
    "wof:placetype":"venue"
},
  "geometry": {"coordinates":[11.558344841,48.1433792114],"type":"Point"}
}