{
  "type": "Feature",
  "properties": {
    "iso:country":"DE",
    "sg:address":"St.-Ottilier-Weg 21",
    "sg:city":"Helsa",
    "sg:phone":"+49 5602/80980",
    "sg:postcode":"34298",
    "sg:province":"Hessen",
    "wof:name":"Cps Kompetenzzentrum F\u00fcr Das Kfz-gewerbe Ag",
    "wof:placetype":"venue"
},
  "geometry": {"coordinates":[9.658292,51.226189],"type":"Point"}
}