{
  "type": "Feature",
  "properties": {
    "iso:country":"DE",
    "sg:address":"Frankfurter Str. 193",
    "sg:city":"Gro\u00df-Gerau",
    "sg:postcode":"64521",
    "sg:province":"Hessen",
    "wof:name":"Ivg-gastst\u00e4tten Gesellschaft In Gro\u00df-gerau Mbh",
    "wof:placetype":"venue"
},
  "geometry": {"coordinates":[8.4956483841,49.9376487732],"type":"Point"}
}