{
  "type": "Feature",
  "properties": {
    "iso:country":"DE",
    "sg:address":"Rathenaustr. 29",
    "sg:city":"Worms",
    "sg:phone":"+49 6241/53336",
    "sg:postcode":"67547",
    "sg:province":"Rheinland-Pfalz",
    "wof:name":"Aaa The Investigator",
    "wof:placetype":"venue"
},
  "geometry": {"coordinates":[8.357762,49.633331],"type":"Point"}
}