{
  "type": "Feature",
  "properties": {
    "iso:country":"DE",
    "sg:address":"Raiffeisenstr. 42",
    "sg:city":"Brackenheim",
    "sg:phone":"+49 7135/6586",
    "sg:postcode":"74336",
    "sg:province":"Baden-W\u00fcrttemberg",
    "wof:name":"A. Wolf",
    "wof:placetype":"venue"
},
  "geometry": {"coordinates":[9.100074,49.079956],"type":"Point"}
}