{
  "type": "Feature",
  "properties": {
    "iso:country":"DE",
    "sg:address":"D\u00f6britscher Str.",
    "sg:city":"Camburg",
    "sg:phone":"+49 36421/22847",
    "sg:postcode":"07774",
    "sg:province":"Th\u00fcringen",
    "wof:name":"B\u00e4der Freibad",
    "wof:placetype":"venue"
},
  "geometry": {"coordinates":[11.7011728287,51.0510749817],"type":"Point"}
}