{
  "type": "Feature",
  "properties": {
    "iso:country":"DE",
    "sg:address":"Bergstr. 15",
    "sg:city":"Rinteln",
    "sg:phone":"+49 5751/6866",
    "sg:postcode":"31737",
    "sg:province":"Niedersachsen",
    "wof:name":"B\u00f6ger Stahl- Und Systembau Gmbh",
    "wof:placetype":"venue"
},
  "geometry": {"coordinates":[9.1215877533,52.2118721008],"type":"Point"}
}