{
  "type": "Feature",
  "properties": {
    "iso:country":"DE",
    "sg:address":"Upender Str.",
    "sg:city":"S\u00fcdbrookmerland",
    "sg:phone":"+49 4942/5165",
    "sg:postcode":"26624",
    "sg:province":"Niedersachsen",
    "wof:name":"La Taverna",
    "wof:placetype":"venue"
},
  "geometry": {"coordinates":[7.3617048264,53.5050048828],"type":"Point"}
}