{
  "type": "Feature",
  "properties": {
    "iso:country":"DE",
    "sg:address":"Schwartauer Str. 50 a",
    "sg:city":"Sereetz",
    "sg:postcode":"23611",
    "sg:province":"Schleswig-Holstein",
    "wof:name":"Aldi Gmbh & Co. Kg",
    "wof:placetype":"venue"
},
  "geometry": {"coordinates":[10.7253837585,53.9227867126],"type":"Point"}
}