{
  "type": "Feature",
  "properties": {
    "iso:country":"DE",
    "sg:address":"Bahnhofstr. 14",
    "sg:city":"Quakenbr\u00fcck",
    "sg:phone":"+49 5431/2292",
    "sg:postcode":"49610",
    "sg:province":"Niedersachsen",
    "wof:name":"Karrenbrock Und Oswald Rechtsanw\u00e4lte Und Notare",
    "wof:placetype":"venue"
},
  "geometry": {"coordinates":[7.9522662163,52.6738510132],"type":"Point"}
}