{
  "type": "Feature",
  "properties": {
    "iso:country":"DE",
    "sg:address":"Dorfstr. 24",
    "sg:city":"Rackith",
    "sg:phone":"+49 34927/21608",
    "sg:postcode":"06901",
    "sg:province":"Sachsen-Anhalt",
    "wof:name":"Josef Kl\u00fcgl",
    "wof:placetype":"venue"
},
  "geometry": {"coordinates":[12.6931991577,51.803352356],"type":"Point"}
}