{
  "type": "Feature",
  "properties": {
    "iso:country":"DE",
    "sg:address":"Marienbader Weg 4",
    "sg:city":"Weil am Rhein",
    "sg:phone":"+49 7621/71207",
    "sg:postcode":"79576",
    "sg:province":"Baden-W\u00fcrttemberg",
    "wof:name":"Barbara Frank",
    "wof:placetype":"venue"
},
  "geometry": {"coordinates":[7.6244401932,47.5944137573],"type":"Point"}
}