{
  "type": "Feature",
  "properties": {
    "iso:country":"DE",
    "sg:address":"Bolzstr. 10",
    "sg:city":"Stuttgart",
    "sg:phone":"+49 711/2236310",
    "sg:postcode":"70173",
    "sg:province":"Baden-W\u00fcrttemberg",
    "wof:name":"Basile Restaurant",
    "wof:placetype":"venue"
},
  "geometry": {"coordinates":[9.1778078079,48.7801818848],"type":"Point"}
}