{
  "type": "Feature",
  "properties": {
    "iso:country":"DE",
    "sg:address":"Leipziger Str. 8",
    "sg:city":"Halle",
    "sg:phone":"+49 345/211380",
    "sg:postcode":"06108",
    "sg:province":"Sachsen-Anhalt",
    "wof:name":"Nellessen Steuerberater",
    "wof:placetype":"venue"
},
  "geometry": {"coordinates":[11.9728555679,51.4817581177],"type":"Point"}
}