{
  "type": "Feature",
  "properties": {
    "iso:country":"DE",
    "sg:address":"Martha-Brautzsch-Str. 4",
    "sg:city":"Dobersch\u00fctz",
    "sg:phone":"+49 34244/50215",
    "sg:postcode":"04838",
    "sg:province":"Sachsen",
    "wof:name":"Agrargen. Dobersch\u00dctz",
    "wof:placetype":"venue"
},
  "geometry": {"coordinates":[12.746287,51.499912],"type":"Point"}
}