{
  "type": "Feature",
  "properties": {
    "iso:country":"DE",
    "sg:address":"Friesenplatz 2",
    "sg:city":"K\u00f6ln",
    "sg:phone":"+49 221/518018",
    "sg:postcode":"50672",
    "sg:province":"Nordrhein-Westfalen",
    "wof:name":"Dm Treuhand Steuerberatungs-gmbh",
    "wof:placetype":"venue"
},
  "geometry": {"coordinates":[6.9392681122,50.9407348633],"type":"Point"}
}