{
  "type": "Feature",
  "properties": {
    "iso:country":"DE",
    "sg:address":"Heckenweg 1",
    "sg:city":"Besigheim",
    "sg:phone":"+49 7143/34934",
    "sg:postcode":"74354",
    "sg:province":"Baden-W\u00fcrttemberg",
    "wof:name":"Horst Wengerter Restaurator Dvfr",
    "wof:placetype":"venue"
},
  "geometry": {"coordinates":[9.1501274109,48.9934883118],"type":"Point"}
}