{
  "type": "Feature",
  "properties": {
    "iso:country":"DE",
    "sg:address":"Victoriaplatz 1",
    "sg:city":"D\u00fcsseldorf",
    "sg:phone":"+49 211/4774798",
    "sg:postcode":"40198",
    "sg:province":"Nordrhein-Westfalen",
    "wof:name":"Vscout Stellenportal - Infos Zu Aus- Und Weiterbildung",
    "wof:placetype":"venue"
},
  "geometry": {"coordinates":[6.7741827965,51.2365036011],"type":"Point"}
}