{
  "type": "Feature",
  "properties": {
    "iso:country":"DE",
    "sg:address":"Badberger Str. 22",
    "sg:city":"Holdorf",
    "sg:phone":"+49 5494/411",
    "sg:postcode":"49451",
    "sg:province":"Niedersachsen",
    "wof:name":"Alois Rottinghaus",
    "wof:placetype":"venue"
},
  "geometry": {"coordinates":[8.115566,52.592766],"type":"Point"}
}