{
  "type": "Feature",
  "properties": {
    "iso:country":"DE",
    "sg:address":"Talstr. 16",
    "sg:city":"Stade",
    "sg:phone":"+49 4141/66677",
    "sg:postcode":"21680",
    "sg:province":"Niedersachsen",
    "wof:name":"Waltraud Und Werner Sell",
    "wof:placetype":"venue"
},
  "geometry": {"coordinates":[9.456337,53.590988],"type":"Point"}
}