{
  "type": "Feature",
  "properties": {
    "iso:country":"DE",
    "sg:address":"Kolpingweg 3",
    "sg:city":"Erlangen",
    "sg:phone":"+49 9131/991745",
    "sg:postcode":"91056",
    "sg:province":"Bayern",
    "wof:name":"Biohof G. Und R. Mayer",
    "wof:placetype":"venue"
},
  "geometry": {"coordinates":[10.962928,49.589848],"type":"Point"}
}