{
  "type": "Feature",
  "properties": {
    "iso:country":"DE",
    "sg:address":"Angerstr. 19",
    "sg:city":"Leipzig",
    "sg:phone":"+49 341/4802336",
    "sg:postcode":"04177",
    "sg:province":"Sachsen",
    "wof:name":"Michael Gronemann Architekt",
    "wof:placetype":"venue"
},
  "geometry": {"coordinates":[12.337913,51.337959],"type":"Point"}
}