{
  "type": "Feature",
  "properties": {
    "iso:country":"DE",
    "sg:address":"Brannenburger Strasse 45",
    "sg:city":"Nu\u00dfdorf",
    "sg:phone":"+49 8034/30580",
    "sg:postcode":"83131",
    "sg:province":"Bayern",
    "wof:name":"Wolfgang Dettendorfer Gmbh",
    "wof:placetype":"venue"
},
  "geometry": {"coordinates":[12.1454696655,47.7427597046],"type":"Point"}
}