{
  "type": "Feature",
  "properties": {
    "iso:country":"DE",
    "sg:address":"Banzkower Str. 08",
    "sg:city":"Banzkow",
    "sg:phone":"+49 3861/2721",
    "sg:postcode":"19079",
    "sg:province":"Mecklenburg-Vorpommern",
    "wof:name":"Ina Rost",
    "wof:placetype":"venue"
},
  "geometry": {"coordinates":[11.514992,53.523361],"type":"Point"}
}