{
  "type": "Feature",
  "properties": {
    "iso:country":"DE",
    "sg:address":"K\u00f6nigstr. 122",
    "sg:city":"Krefeld",
    "sg:phone":"+49 2151/602575",
    "sg:postcode":"47798",
    "sg:province":"Nordrhein-Westfalen",
    "wof:name":"Lutens Und Stawowy",
    "wof:placetype":"venue"
},
  "geometry": {"coordinates":[6.5637340546,51.3326072693],"type":"Point"}
}