{
  "type": "Feature",
  "properties": {
    "iso:country":"DE",
    "sg:address":"An der B 200 Nr. 16",
    "sg:city":"Jannebyfeld",
    "sg:phone":"+49 4607/1363",
    "sg:postcode":"24992",
    "sg:province":"Schleswig-Holstein",
    "wof:name":"L\u00fcth & Partner, Projektmanagement",
    "wof:placetype":"venue"
},
  "geometry": {"coordinates":[9.2721099854,54.6429862976],"type":"Point"}
}