{
  "type": "Feature",
  "properties": {
    "iso:country":"DE",
    "sg:address":"Kohlenweg 16",
    "sg:city":"Dortmund",
    "sg:phone":"+49 231/822026",
    "sg:postcode":"44147",
    "sg:province":"Nordrhein-Westfalen",
    "wof:name":"Rheinisch Westf\u00e4lische Baustoff- Und Speditionsges.",
    "wof:placetype":"venue"
},
  "geometry": {"coordinates":[7.4325790405,51.5263214111],"type":"Point"}
}