{
  "type": "Feature",
  "properties": {
    "iso:country":"DE",
    "sg:address":"Rheinstr. 10",
    "sg:city":"Kuppenheim",
    "sg:phone":"+49 7222/42981",
    "sg:postcode":"76456",
    "sg:province":"Baden-W\u00fcrttemberg",
    "wof:name":"Albert Holfelder",
    "wof:placetype":"venue"
},
  "geometry": {"coordinates":[8.2528467178,48.8278770447],"type":"Point"}
}