{
  "type": "Feature",
  "properties": {
    "iso:country":"DE",
    "sg:address":"Fahrgasse 3-5",
    "sg:city":"Limburg",
    "sg:phone":"+49 6431/27717",
    "sg:postcode":"65549",
    "sg:province":"Hessen",
    "wof:name":"Cornisa Collection-design Vertriebs Gmbh",
    "wof:placetype":"venue"
},
  "geometry": {"coordinates":[8.0639848709,50.3894119263],"type":"Point"}
}