{
  "type": "Feature",
  "properties": {
    "iso:country":"DE",
    "sg:address":"Langestr. 8",
    "sg:city":"Norderney",
    "sg:phone":"+49 4932/92440",
    "sg:postcode":"26548",
    "sg:province":"Niedersachsen",
    "wof:name":"Hans Papenfu\u00df",
    "wof:placetype":"venue"
},
  "geometry": {"coordinates":[7.1443481445,53.7068367004],"type":"Point"}
}