{
  "type": "Feature",
  "properties": {
    "iso:country":"DE",
    "sg:address":"Branigleite 4",
    "sg:city":"R\u00f6dental",
    "sg:phone":"+49 9563/3553",
    "sg:postcode":"96472",
    "sg:province":"Bayern",
    "wof:name":"Heinz M\u00fcller Architekt",
    "wof:placetype":"venue"
},
  "geometry": {"coordinates":[11.030442,50.292603],"type":"Point"}
}