{
  "type": "Feature",
  "properties": {
    "iso:country":"DE",
    "sg:address":"Lichtentaler Str. 19",
    "sg:city":"Baden-Baden",
    "sg:phone":"+49 7221/302775",
    "sg:postcode":"76530",
    "sg:province":"Baden-W\u00fcrttemberg",
    "wof:name":"Cafe L\u00f6hr",
    "wof:placetype":"venue"
},
  "geometry": {"coordinates":[8.240787,48.759163],"type":"Point"}
}