{
  "type": "Feature",
  "properties": {
    "iso:country":"DE",
    "sg:address":"Halden\u00e4cker",
    "sg:city":"Ammerbuch",
    "sg:phone":"+49 7073/829",
    "sg:postcode":"72119",
    "sg:province":"Baden-W\u00fcrttemberg",
    "wof:name":"Helmut G\u00f6hring",
    "wof:placetype":"venue"
},
  "geometry": {"coordinates":[8.911669,48.536556],"type":"Point"}
}