{
  "type": "Feature",
  "properties": {
    "iso:country":"DE",
    "sg:address":"H\u00fcsingstr. 11",
    "sg:city":"Schwerte",
    "sg:phone":"+49 2304/16406",
    "sg:postcode":"58239",
    "sg:province":"Nordrhein-Westfalen",
    "wof:name":"Lewe Fleischwaren Gmbh",
    "wof:placetype":"venue"
},
  "geometry": {"coordinates":[7.567843914,51.4411048889],"type":"Point"}
}