{
  "type": "Feature",
  "properties": {
    "iso:country":"DE",
    "sg:address":"M\u00f6llerstr. 29",
    "sg:city":"Hagen",
    "sg:phone":"+49 2334/55898",
    "sg:postcode":"58119",
    "sg:province":"Nordrhein-Westfalen",
    "wof:name":"Elseyer-apotheke",
    "wof:placetype":"venue"
},
  "geometry": {"coordinates":[7.565782,51.360775],"type":"Point"}
}