{
  "type": "Feature",
  "properties": {
    "iso:country":"DE",
    "sg:address":"Leipziger Str. 40",
    "sg:city":"Crimmitschau",
    "sg:phone":"+49 3762/44525",
    "sg:postcode":"08451",
    "sg:province":"Sachsen",
    "wof:name":"Casa Bauprojekt Gmbh",
    "wof:placetype":"venue"
},
  "geometry": {"coordinates":[12.3864078522,50.8197746277],"type":"Point"}
}