{
  "type": "Feature",
  "properties": {
    "iso:country":"DE",
    "sg:address":"Niedieckstr. 4",
    "sg:city":"Nettetal",
    "sg:phone":"+49 2153/911541",
    "sg:postcode":"41334",
    "sg:province":"Nordrhein-Westfalen",
    "wof:name":"Heinz Fegers",
    "wof:placetype":"venue"
},
  "geometry": {"coordinates":[6.2761149406,51.3083877563],"type":"Point"}
}