{
  "type": "Feature",
  "properties": {
    "iso:country":"DE",
    "sg:address":"Schauenburgerstr 32::",
    "sg:city":"Hamburg",
    "sg:postcode":"20095",
    "sg:province":"Hamburg",
    "wof:name":"Ibero Platina Bank Ag",
    "wof:placetype":"venue"
},
  "geometry": {"coordinates":[9.994677,53.549561],"type":"Point"}
}