{
  "type": "Feature",
  "properties": {
    "iso:country":"DE",
    "sg:address":"Waldstr. 32",
    "sg:city":"Willst\u00e4tt",
    "sg:phone":"+49 7852/6319",
    "sg:postcode":"77731",
    "sg:province":"Baden-W\u00fcrttemberg",
    "wof:name":"Klause",
    "wof:placetype":"venue"
},
  "geometry": {"coordinates":[7.9332900047,48.5431098938],"type":"Point"}
}