{
  "type": "Feature",
  "properties": {
    "iso:country":"DE",
    "sg:address":"Urlaubstr 2",
    "sg:city":"W\u00fcrzburg",
    "sg:phone":"+49 931/250230",
    "sg:postcode":"97076",
    "sg:province":"Bayern",
    "wof:name":"Haas + Marx Gmbh",
    "wof:placetype":"venue"
},
  "geometry": {"coordinates":[9.9550142288,49.798992157],"type":"Point"}
}