{
  "type": "Feature",
  "properties": {
    "iso:country":"DE",
    "sg:address":"Wettiner Str.",
    "sg:city":"Beesenstedt",
    "sg:phone":"+49 34773/20377",
    "sg:postcode":"06198",
    "sg:province":"Sachsen-Anhalt",
    "wof:name":"Viehmast Beesenstedt Gmbh",
    "wof:placetype":"venue"
},
  "geometry": {"coordinates":[11.7335891724,51.5681838989],"type":"Point"}
}