{
  "type": "Feature",
  "properties": {
    "iso:country":"DE",
    "sg:address":"Kirchenstr. 2",
    "sg:city":"Itzehoe",
    "sg:phone":"+49 4821/5800",
    "sg:postcode":"25524",
    "sg:province":"Schleswig-Holstein",
    "wof:name":"Stadtmanagement Itzehoe Gmbh",
    "wof:placetype":"venue"
},
  "geometry": {"coordinates":[9.5187530518,53.9230728149],"type":"Point"}
}