{
  "type": "Feature",
  "properties": {
    "iso:country":"DE",
    "sg:address":"Neuendettelsauer Str. 32a",
    "sg:city":"Heilsbronn",
    "sg:phone":"+49 9872/5678",
    "sg:postcode":"91560",
    "sg:province":"Bayern",
    "wof:name":"Fritz Barthelmes",
    "wof:placetype":"venue"
},
  "geometry": {"coordinates":[10.7921037674,49.3337059021],"type":"Point"}
}