{
  "type": "Feature",
  "properties": {
    "iso:country":"DE",
    "sg:address":"Weidestr. 8",
    "sg:city":"Eutin",
    "sg:phone":"+49 4521/70450",
    "sg:postcode":"23701",
    "sg:province":"Schleswig-Holstein",
    "wof:name":"Ksk Ingenieure Gmbh & Co.",
    "wof:placetype":"venue"
},
  "geometry": {"coordinates":[10.6179637909,54.1326065063],"type":"Point"}
}