{
  "type": "Feature",
  "properties": {
    "iso:country":"DE",
    "sg:address":"Eichstr. 1d",
    "sg:city":"Lutherstadt Wittenberg",
    "sg:phone":"+49 3491/407108",
    "sg:postcode":"06886",
    "sg:province":"Sachsen-Anhalt",
    "wof:name":"J\u00fcrgen Berg Versicherungsmakler E. K.",
    "wof:placetype":"venue"
},
  "geometry": {"coordinates":[12.6318330765,51.8785171509],"type":"Point"}
}