{
  "type": "Feature",
  "properties": {
    "iso:country":"DE",
    "sg:address":"Im R\u00f6therfeld 23 Industriegebiet Nord",
    "sg:city":"Hadamar",
    "sg:phone":"+49 4964/332652",
    "sg:postcode":"65589",
    "sg:province":"Hessen",
    "wof:name":"Kallwies Zerspanungs Gmbh",
    "wof:placetype":"venue"
},
  "geometry": {"coordinates":[8.045177,50.449917],"type":"Point"}
}