{
  "type": "Feature",
  "properties": {
    "iso:country":"DE",
    "sg:address":"Ehrental",
    "sg:city":"Schmalkalden",
    "sg:phone":"+49 3683/402902",
    "sg:postcode":"98574",
    "sg:province":"Th\u00fcringen",
    "wof:name":"Waldhotel Ehrental",
    "wof:placetype":"venue"
},
  "geometry": {"coordinates":[10.4388437271,50.7414207458],"type":"Point"}
}