{
  "type": "Feature",
  "properties": {
    "iso:country":"DE",
    "sg:address":"Bahnhofstr. 45",
    "sg:city":"M\u00fcllrose",
    "sg:phone":"+49 33606/4326",
    "sg:postcode":"15299",
    "sg:province":"Brandenburg",
    "wof:name":"Krause & Dribbisch Gbr",
    "wof:placetype":"venue"
},
  "geometry": {"coordinates":[14.4302072525,52.2434844971],"type":"Point"}
}