{
  "type": "Feature",
  "properties": {
    "iso:country":"DE",
    "sg:address":"Schie\u00dfh\u00fcttenstr. 13",
    "sg:city":"Usingen",
    "sg:phone":"+49 6081/67845",
    "sg:postcode":"61250",
    "sg:province":"Hessen",
    "wof:name":"Palmeras Immobilien Gmbh",
    "wof:placetype":"venue"
},
  "geometry": {"coordinates":[8.4707937241,50.3203964233],"type":"Point"}
}