{
  "type": "Feature",
  "properties": {
    "iso:country":"DE",
    "sg:address":"Brautgasse 1",
    "sg:city":"Bayreuth",
    "sg:phone":"+49 921/54911",
    "sg:postcode":"95444",
    "sg:province":"Bayern",
    "wof:name":"Paperla-pub",
    "wof:placetype":"venue"
},
  "geometry": {"coordinates":[11.5750312805,49.9439201355],"type":"Point"}
}