{
  "type": "Feature",
  "properties": {
    "iso:country":"DE",
    "sg:address":"Lettengrube 1",
    "sg:city":"Bietigheim-Bissingen",
    "sg:phone":"+49 7142/940225",
    "sg:postcode":"74321",
    "sg:province":"Baden-W\u00fcrttemberg",
    "wof:name":"Biohof Bernhard Schnaufer",
    "wof:placetype":"venue"
},
  "geometry": {"coordinates":[9.123448,48.970566],"type":"Point"}
}