{
  "type": "Feature",
  "properties": {
    "iso:country":"DE",
    "sg:address":"Hauptstr. 11",
    "sg:city":"Wendelstein",
    "sg:phone":"+49 9129/6775",
    "sg:postcode":"90530",
    "sg:province":"Bayern",
    "wof:name":"A. Kather",
    "wof:placetype":"venue"
},
  "geometry": {"coordinates":[11.1427564621,49.3555221558],"type":"Point"}
}