{
  "type": "Feature",
  "properties": {
    "iso:country":"DE",
    "sg:address":"Martin-Kollar-Str. 9",
    "sg:city":"M\u00fcnchen",
    "sg:phone":"+49 89/4368913",
    "sg:postcode":"81829",
    "sg:province":"Bayern",
    "wof:name":"Movietech Ag",
    "wof:placetype":"venue"
},
  "geometry": {"coordinates":[11.6597356796,48.1355819702],"type":"Point"}
}