{
  "type": "Feature",
  "properties": {
    "iso:country":"DE",
    "sg:address":"Arnold-Zweig-Str. 12",
    "sg:city":"Berlin",
    "sg:phone":"+49 30/4722164",
    "sg:postcode":"13189",
    "sg:province":"Berlin",
    "wof:name":"J\u00fcrgen Beyer Immobilienmakler",
    "wof:placetype":"venue"
},
  "geometry": {"coordinates":[13.4247579575,52.5631599426],"type":"Point"}
}