{
  "type": "Feature",
  "properties": {
    "iso:country":"DE",
    "sg:address":"In der Klinge 5",
    "sg:city":"Gotha",
    "sg:postcode":"99867",
    "sg:province":"Th\u00fcringen",
    "wof:name":"Intrasan Gesundheitszentrum",
    "wof:placetype":"venue"
},
  "geometry": {"coordinates":[10.685097,50.952885],"type":"Point"}
}