{
  "type": "Feature",
  "properties": {
    "iso:country":"DE",
    "sg:address":"Luisenweg 97",
    "sg:city":"Hamburg",
    "sg:phone":"+49 40/212071",
    "sg:postcode":"20537",
    "sg:province":"Hamburg",
    "wof:name":"Egon Holm",
    "wof:placetype":"venue"
},
  "geometry": {"coordinates":[10.0476436615,53.5501937866],"type":"Point"}
}