{
  "type": "Feature",
  "properties": {
    "iso:country":"DE",
    "sg:address":"Kernstr. 19",
    "sg:city":"Gr\u00fcnberg",
    "sg:phone":"+49 6401/5890",
    "sg:postcode":"35305",
    "sg:province":"Hessen",
    "wof:name":"S. Erb",
    "wof:placetype":"venue"
},
  "geometry": {"coordinates":[8.9828138351,50.6112785339],"type":"Point"}
}