{
  "type": "Feature",
  "properties": {
    "iso:country":"DE",
    "sg:address":"Helbeeck 1",
    "sg:city":"Greu\u00dfen",
    "sg:phone":"+49 3636/701683",
    "sg:postcode":"99718",
    "sg:province":"Th\u00fcringen",
    "wof:name":"L & G Landmaschinen- Und Gartenbautechnik-service Gmbh",
    "wof:placetype":"venue"
},
  "geometry": {"coordinates":[10.9521360397,51.2300071716],"type":"Point"}
}