{
  "type": "Feature",
  "properties": {
    "iso:country":"DE",
    "sg:address":"Tumringer Str. 274b",
    "sg:city":"L\u00f6rrach",
    "sg:phone":"+49 7621/92730",
    "sg:postcode":"79539",
    "sg:province":"Baden-W\u00fcrttemberg",
    "wof:name":"Swiss Gourmet Wa\u00dfmer Gmbh",
    "wof:placetype":"venue"
},
  "geometry": {"coordinates":[7.6591467857,47.6207542419],"type":"Point"}
}