{
  "type": "Feature",
  "properties": {
    "iso:country":"DE",
    "sg:address":"Goslarer Str. 25",
    "sg:city":"Magdeburg",
    "sg:phone":"+49 391/7333365",
    "sg:postcode":"39118",
    "sg:province":"Sachsen-Anhalt",
    "wof:name":"Flack & Co. Consulting Gmbh",
    "wof:placetype":"venue"
},
  "geometry": {"coordinates":[11.6059141159,52.1008911133],"type":"Point"}
}