{
  "type": "Feature",
  "properties": {
    "iso:country":"DE",
    "sg:address":"Gro\u00df-Neidaer-Str. 19 A",
    "sg:city":"Hoyerswerda",
    "sg:phone":"+49 3571/411222",
    "sg:postcode":"02977",
    "sg:province":"Sachsen",
    "wof:name":"Linneweber-holzbau Gmbh",
    "wof:placetype":"venue"
},
  "geometry": {"coordinates":[14.2366132736,51.4208221436],"type":"Point"}
}