{
  "type": "Feature",
  "properties": {
    "iso:country":"DE",
    "sg:address":"Beecker Str. 288",
    "sg:city":"Duisburg",
    "sg:postcode":"47166",
    "sg:province":"Nordrhein-Westfalen",
    "wof:name":"Fuchs & Golyszny Gmbh",
    "wof:placetype":"venue"
},
  "geometry": {"coordinates":[6.7855257988,51.4881858826],"type":"Point"}
}