{
  "type": "Feature",
  "properties": {
    "iso:country":"DE",
    "sg:address":"Siemensstr. 4",
    "sg:city":"Neuenkirchen",
    "sg:phone":"+49 5195/646",
    "sg:postcode":"29643",
    "sg:province":"Niedersachsen",
    "wof:name":"Bauausstattung Gebers Gmbh",
    "wof:placetype":"venue"
},
  "geometry": {"coordinates":[9.6849927902,53.0317306519],"type":"Point"}
}