{
  "type": "Feature",
  "properties": {
    "iso:country":"DE",
    "sg:address":"Katharinenweg 8",
    "sg:city":"Backnang",
    "sg:phone":"+49 7191/950144",
    "sg:postcode":"71522",
    "sg:province":"Baden-W\u00fcrttemberg",
    "wof:name":"E. Belz",
    "wof:placetype":"venue"
},
  "geometry": {"coordinates":[9.4408531189,48.9748191833],"type":"Point"}
}