{
  "type": "Feature",
  "properties": {
    "iso:country":"DE",
    "sg:address":"Am Kellerst\u00fcck 5",
    "sg:city":"Weimar",
    "sg:phone":"+49 6426/921853",
    "sg:postcode":"35096",
    "sg:province":"Hessen",
    "wof:name":"Beate Schneider Masseurin",
    "wof:placetype":"venue"
},
  "geometry": {"coordinates":[8.700733,50.737057],"type":"Point"}
}