{
  "type": "Feature",
  "properties": {
    "iso:country":"DE",
    "sg:address":"Wandlhamerstr. 34",
    "sg:city":"Gr\u00e4felfing",
    "sg:postcode":"82166",
    "sg:province":"Bayern",
    "wof:name":"S. Ruth",
    "wof:placetype":"venue"
},
  "geometry": {"coordinates":[11.435361,48.122204],"type":"Point"}
}