{
  "type": "Feature",
  "properties": {
    "iso:country":"DE",
    "sg:address":"G\u00e4nsbrunnenweg 3",
    "sg:city":"R\u00fcmmingen",
    "sg:phone":"+49 7621/140701",
    "sg:postcode":"79595",
    "sg:province":"Baden-W\u00fcrttemberg",
    "wof:name":"C. Keck",
    "wof:placetype":"venue"
},
  "geometry": {"coordinates":[7.6447038651,47.6414375305],"type":"Point"}
}