{
  "type": "Feature",
  "properties": {
    "iso:country":"DE",
    "sg:address":"Dieselstr. 9",
    "sg:city":"Neuhofen",
    "sg:phone":"+49 6236/500235",
    "sg:postcode":"67141",
    "sg:province":"Rheinland-Pfalz",
    "wof:name":"Eatec Energie- Anlagentechnik Gmbh",
    "wof:placetype":"venue"
},
  "geometry": {"coordinates":[8.414297,49.425072],"type":"Point"}
}