{
  "type": "Feature",
  "properties": {
    "iso:country":"DE",
    "sg:address":"Adenauerstr. 10",
    "sg:city":"Neuhausen",
    "sg:phone":"+49 7158/7652",
    "sg:postcode":"73765",
    "sg:province":"Baden-W\u00fcrttemberg",
    "wof:name":"Bike World",
    "wof:placetype":"venue"
},
  "geometry": {"coordinates":[9.28129,48.679878],"type":"Point"}
}