{
  "type": "Feature",
  "properties": {
    "iso:country":"DE",
    "sg:address":"Sulzbachtalstr. 96",
    "sg:city":"Sulzbach",
    "sg:phone":"+49 6897/569270",
    "sg:postcode":"66280",
    "sg:province":"Saarland",
    "wof:name":"Gerald Back Praxis F\u00fcr Ergotherapie",
    "wof:placetype":"venue"
},
  "geometry": {"coordinates":[7.063244,49.299461],"type":"Point"}
}