{
  "type": "Feature",
  "properties": {
    "iso:country":"DE",
    "sg:address":"Eppingawehr",
    "sg:city":"Jemgum",
    "sg:phone":"+49 4958/229",
    "sg:postcode":"26844",
    "sg:province":"Niedersachsen",
    "wof:name":"G. E. Loesing",
    "wof:placetype":"venue"
},
  "geometry": {"coordinates":[7.384941,53.280762],"type":"Point"}
}