{
  "type": "Feature",
  "properties": {
    "iso:country":"DE",
    "sg:address":"Lindenhardt 61",
    "sg:city":"Creu\u00dfen",
    "sg:phone":"+49 9246/791",
    "sg:postcode":"95473",
    "sg:province":"Bayern",
    "wof:name":"Lindwurm",
    "wof:placetype":"venue"
},
  "geometry": {"coordinates":[11.5325651169,49.8323097229],"type":"Point"}
}