{
  "type": "Feature",
  "properties": {
    "iso:country":"DE",
    "sg:address":"Allee 40",
    "sg:city":"Heilbronn",
    "sg:postcode":"74072",
    "sg:province":"Baden-W\u00fcrttemberg",
    "wof:name":"Condero Ag",
    "wof:placetype":"venue"
},
  "geometry": {"coordinates":[9.2230377197,49.1434249878],"type":"Point"}
}