{
  "type": "Feature",
  "properties": {
    "iso:country":"DE",
    "sg:address":"Rombachstr. 10",
    "sg:city":"Haiger",
    "sg:phone":"+49 2773/5270",
    "sg:postcode":"35708",
    "sg:province":"Hessen",
    "wof:name":"R\u00f6dling Stahl- Und Apparatebau Gmbh",
    "wof:placetype":"venue"
},
  "geometry": {"coordinates":[8.1939992905,50.7175521851],"type":"Point"}
}