{
  "type": "Feature",
  "properties": {
    "iso:country":"DE",
    "sg:address":"Karl-Liebknecht-Str. 21",
    "sg:city":"Cottbus",
    "sg:phone":"+49 355/7840100",
    "sg:postcode":"03046",
    "sg:province":"Brandenburg",
    "wof:name":"Stankewitz Tambor Und Schmitte Rechtsanw\u00e4lte",
    "wof:placetype":"venue"
},
  "geometry": {"coordinates":[14.3261919022,51.7567596436],"type":"Point"}
}