{
  "type": "Feature",
  "properties": {
    "iso:country":"DE",
    "sg:address":"Kr\u00f6llwitzer Str. 20",
    "sg:city":"Halle",
    "sg:phone":"+49 345/5504801",
    "sg:postcode":"06120",
    "sg:province":"Sachsen-Anhalt",
    "wof:name":"U. Voigt",
    "wof:placetype":"venue"
},
  "geometry": {"coordinates":[11.8624353409,51.5045318604],"type":"Point"}
}