{
  "type": "Feature",
  "properties": {
    "iso:country":"DE",
    "sg:address":"K\u00f6nigsteinstr. 11",
    "sg:city":"M\u00fcnchen",
    "sg:phone":"+49 89/3561360",
    "sg:postcode":"80807",
    "sg:province":"Bayern",
    "wof:name":"Mfv Moderne Formulartechnik Druck- Und Verlagsges. Mbh",
    "wof:placetype":"venue"
},
  "geometry": {"coordinates":[11.5744819641,48.1858711243],"type":"Point"}
}