{
  "type": "Feature",
  "properties": {
    "iso:country":"DE",
    "sg:address":"Wupperstr. 97",
    "sg:city":"Solingen",
    "sg:phone":"+49 212/18536",
    "sg:postcode":"42651",
    "sg:province":"Nordrhein-Westfalen",
    "wof:name":"P. Amann",
    "wof:placetype":"venue"
},
  "geometry": {"coordinates":[7.095125,51.174629],"type":"Point"}
}