{
  "type": "Feature",
  "properties": {
    "iso:country":"DE",
    "sg:address":"Stubenstr. 18",
    "sg:city":"Heilbad Heiligenstadt",
    "sg:phone":"+49 3606/55150",
    "sg:postcode":"37308",
    "sg:province":"Th\u00fcringen",
    "wof:name":"Alte Apotheke",
    "wof:placetype":"venue"
},
  "geometry": {"coordinates":[10.134912,51.378647],"type":"Point"}
}