{
  "type": "Feature",
  "properties": {
    "iso:country":"DE",
    "sg:address":"Alte Poststr. 6",
    "sg:city":"Bad Laer",
    "sg:phone":"+49 5424/9191",
    "sg:postcode":"49196",
    "sg:province":"Niedersachsen",
    "wof:name":"Heinrich Beermann",
    "wof:placetype":"venue"
},
  "geometry": {"coordinates":[8.1046380997,52.0886650085],"type":"Point"}
}