{
  "type": "Feature",
  "properties": {
    "iso:country":"DE",
    "sg:address":"Kirchstr. 25",
    "sg:city":"Arnsberg",
    "sg:phone":"+49 2937/1490",
    "sg:postcode":"59823",
    "sg:province":"Nordrhein-Westfalen",
    "wof:name":"W. H\u00f6mberg",
    "wof:placetype":"venue"
},
  "geometry": {"coordinates":[8.1354131699,51.3935661316],"type":"Point"}
}