{
  "type": "Feature",
  "properties": {
    "iso:country":"DE",
    "sg:address":"Am Flur 20",
    "sg:city":"Neunkirchen",
    "sg:phone":"+49 2735/61348",
    "sg:postcode":"57290",
    "sg:province":"Nordrhein-Westfalen",
    "wof:name":"Medico-service Beyer Gmbh",
    "wof:placetype":"venue"
},
  "geometry": {"coordinates":[7.9902839661,50.7811584473],"type":"Point"}
}