{
  "type": "Feature",
  "properties": {
    "iso:country":"DE",
    "sg:address":"Hegnachh\u00f6fe 1",
    "sg:city":"Hemmingen",
    "sg:phone":"+49 7150/6117",
    "sg:postcode":"71282",
    "sg:province":"Baden-W\u00fcrttemberg",
    "wof:name":"Werner Reichert",
    "wof:placetype":"venue"
},
  "geometry": {"coordinates":[9.024144,48.860474],"type":"Point"}
}