{
  "type": "Feature",
  "properties": {
    "iso:country":"DE",
    "sg:address":"Gewerbestr. 42",
    "sg:city":"Grosselfingen",
    "sg:phone":"+49 7476/2033",
    "sg:postcode":"72415",
    "sg:province":"Baden-W\u00fcrttemberg",
    "wof:name":"Ceramo M. Sulzer E. K.",
    "wof:placetype":"venue"
},
  "geometry": {"coordinates":[8.8832120895,48.3238868713],"type":"Point"}
}