{
  "type": "Feature",
  "properties": {
    "iso:country":"DE",
    "sg:city":"Rothenfels",
    "sg:phone":"+49 9393/464",
    "sg:postcode":"97851",
    "sg:province":"Bayern",
    "wof:name":"Raiffeisenbank Lohr Am Main Eg",
    "wof:placetype":"venue"
},
  "geometry": {"coordinates":[9.590436,49.893757],"type":"Point"}
}