{
  "type": "Feature",
  "properties": {
    "iso:country":"DE",
    "sg:address":"Unter den Linden 4",
    "sg:city":"Kleinm\u00fchlingen",
    "sg:phone":"+49 39291/3043",
    "sg:postcode":"39221",
    "sg:province":"Sachsen-Anhalt",
    "wof:name":"Gerhard Sauerzweig",
    "wof:placetype":"venue"
},
  "geometry": {"coordinates":[11.74488,51.945667],"type":"Point"}
}