{
  "type": "Feature",
  "properties": {
    "iso:country":"DE",
    "sg:address":"Sehretstr. 27",
    "sg:city":"Langen",
    "sg:phone":"+49 6103/24034",
    "sg:postcode":"63225",
    "sg:province":"Hessen",
    "wof:name":"A. Wiederhold",
    "wof:placetype":"venue"
},
  "geometry": {"coordinates":[8.6734695435,49.9849510193],"type":"Point"}
}