{
  "type": "Feature",
  "properties": {
    "iso:country":"DE",
    "sg:address":"Marienstr. 3 b",
    "sg:city":"Sch\u00f6ningen",
    "sg:phone":"+49 5352/59701",
    "sg:postcode":"38364",
    "sg:province":"Niedersachsen",
    "wof:name":"China-restaurant China Garden",
    "wof:placetype":"venue"
},
  "geometry": {"coordinates":[10.9710893631,52.133605957],"type":"Point"}
}