{
  "type": "Feature",
  "properties": {
    "iso:country":"DE",
    "sg:address":"Berliner Str. 92",
    "sg:city":"Preu\u00dfisch Oldendorf",
    "sg:phone":"+49 5742/920777",
    "sg:postcode":"32361",
    "sg:province":"Nordrhein-Westfalen",
    "wof:name":"R. Fiebich",
    "wof:placetype":"venue"
},
  "geometry": {"coordinates":[8.5461158752,52.2967338562],"type":"Point"}
}