{
  "type": "Feature",
  "properties": {
    "iso:country":"DE",
    "sg:address":"Eichenstr. 12",
    "sg:city":"Neubeuern",
    "sg:phone":"+49 8035/3275",
    "sg:postcode":"83115",
    "sg:province":"Bayern",
    "wof:name":"Rolf Koller Heilpraktiker",
    "wof:placetype":"venue"
},
  "geometry": {"coordinates":[12.1360521317,47.7735595703],"type":"Point"}
}