{
  "type": "Feature",
  "properties": {
    "iso:country":"DE",
    "sg:address":"Kurf\u00fcrstenstr. 9",
    "sg:city":"Duisburg",
    "sg:phone":"+49 203/491623",
    "sg:postcode":"47179",
    "sg:province":"Nordrhein-Westfalen",
    "wof:name":"Anton Eiter",
    "wof:placetype":"venue"
},
  "geometry": {"coordinates":[6.744363,51.521576],"type":"Point"}
}