{
  "type": "Feature",
  "properties": {
    "iso:country":"DE",
    "sg:address":"W\u00fcrzburger Str. 20",
    "sg:city":"Mespelbrunn",
    "sg:phone":"+49 6092/274",
    "sg:postcode":"63875",
    "sg:province":"Bayern",
    "wof:name":"Pension Rosa B\u00fcttner",
    "wof:placetype":"venue"
},
  "geometry": {"coordinates":[9.3366546631,49.9200363159],"type":"Point"}
}