{
  "type": "Feature",
  "properties": {
    "iso:country":"DE",
    "sg:address":"Heddesdorfer Str. 34",
    "sg:city":"Neuwied",
    "sg:phone":"+49 2631/23771",
    "sg:postcode":"56564",
    "sg:province":"Rheinland-Pfalz",
    "wof:name":"Teller-service Geschirrverleih, Neuwied",
    "wof:placetype":"venue"
},
  "geometry": {"coordinates":[7.465418,50.432632],"type":"Point"}
}