{
  "type": "Feature",
  "properties": {
    "iso:country":"DE",
    "sg:address":"Friedr.-Ebert-Str. 20",
    "sg:city":"Frankfurt",
    "sg:phone":"+49 4933/5555490",
    "sg:postcode":"15234",
    "sg:province":"Brandenburg",
    "wof:name":"Multi Media Frankfurt Oder Gmbh",
    "wof:placetype":"venue"
},
  "geometry": {"coordinates":[14.475705,52.371635],"type":"Point"}
}