{
  "type": "Feature",
  "properties": {
    "iso:country":"DE",
    "sg:address":"Erfurter Str. 11",
    "sg:city":"Kassel",
    "sg:phone":"+49 561/53207",
    "sg:postcode":"34123",
    "sg:province":"Hessen",
    "wof:name":"Karl-heinz Wengefeld Kfz-verwertungsuntern.",
    "wof:placetype":"venue"
},
  "geometry": {"coordinates":[9.5287742615,51.3065834045],"type":"Point"}
}