{
  "type": "Feature",
  "properties": {
    "iso:country":"DE",
    "sg:address":"Walsroder Str 18",
    "sg:city":"Soltau",
    "sg:phone":"+49 5191/4004",
    "sg:postcode":"29614",
    "sg:province":"Niedersachsen",
    "wof:name":"Mineral\u00f6l Freytag Gmbh",
    "wof:placetype":"venue"
},
  "geometry": {"coordinates":[9.83379,52.982182],"type":"Point"}
}