{
  "type": "Feature",
  "properties": {
    "iso:country":"DE",
    "sg:address":"Elbestr. 45",
    "sg:city":"Geretsried",
    "sg:phone":"+49 8171/62970",
    "sg:postcode":"82538",
    "sg:province":"Bayern",
    "wof:name":"Lorenz Gmbh & Co. Kg",
    "wof:placetype":"venue"
},
  "geometry": {"coordinates":[11.4650173187,47.8800811768],"type":"Point"}
}