{
  "type": "Feature",
  "properties": {
    "iso:country":"DE",
    "sg:address":"Rintelner Str. 416",
    "sg:city":"Porta Westfalica",
    "sg:phone":"+49 5722/1242",
    "sg:postcode":"32457",
    "sg:province":"Nordrhein-Westfalen",
    "wof:name":"W. Berg",
    "wof:placetype":"venue"
},
  "geometry": {"coordinates":[9.040279,52.226864],"type":"Point"}
}