{
  "type": "Feature",
  "properties": {
    "iso:country":"DE",
    "sg:address":"W\u00fcrzburger Str. 87",
    "sg:city":"Lauda-K\u00f6nigshofen",
    "sg:phone":"+49 9343/1394",
    "sg:postcode":"97922",
    "sg:province":"Baden-W\u00fcrttemberg",
    "wof:name":"Anton Stolz",
    "wof:placetype":"venue"
},
  "geometry": {"coordinates":[9.7202348709,49.5796318054],"type":"Point"}
}