{
  "type": "Feature",
  "properties": {
    "iso:country":"DE",
    "sg:address":"Bahnhofstr. 21",
    "sg:city":"Balduinstein",
    "sg:phone":"+49 6432/98320",
    "sg:postcode":"65558",
    "sg:province":"Rheinland-Pfalz",
    "wof:name":"W. Thust Kg",
    "wof:placetype":"venue"
},
  "geometry": {"coordinates":[7.9679999352,50.3472518921],"type":"Point"}
}