{
  "type": "Feature",
  "properties": {
    "iso:country":"DE",
    "sg:address":"Nebelberg 15",
    "sg:city":"Langdorf",
    "sg:phone":"+49 9922/2640",
    "sg:postcode":"94264",
    "sg:province":"Bayern",
    "wof:name":"G\u00e4stehaus Haus Tannwald",
    "wof:placetype":"venue"
},
  "geometry": {"coordinates":[13.1595458984,49.0211486816],"type":"Point"}
}