{
  "type": "Feature",
  "properties": {
    "iso:country":"DE",
    "sg:address":"Damkenstr. 1",
    "sg:city":"Petershagen",
    "sg:phone":"+49 5768/633",
    "sg:postcode":"32469",
    "sg:province":"Nordrhein-Westfalen",
    "wof:name":"Heinz M\u00fcller",
    "wof:placetype":"venue"
},
  "geometry": {"coordinates":[9.053012,52.466057],"type":"Point"}
}