{
  "type": "Feature",
  "properties": {
    "iso:country":"DE",
    "sg:address":"Kotzinger Str. 2 a",
    "sg:city":"Traunstein",
    "sg:phone":"+49 861/12791",
    "sg:postcode":"83278",
    "sg:province":"Bayern",
    "wof:name":"Freitsmiedl & Partner Gdbr",
    "wof:placetype":"venue"
},
  "geometry": {"coordinates":[12.6322317123,47.8836593628],"type":"Point"}
}