{
  "type": "Feature",
  "properties": {
    "iso:country":"DE",
    "sg:address":"Weinreihe 17",
    "sg:city":"Bad Sooden-Allendorf",
    "sg:phone":"+49 5652/2176",
    "sg:postcode":"37242",
    "sg:province":"Hessen",
    "wof:name":"Karl Wachsmuth",
    "wof:placetype":"venue"
},
  "geometry": {"coordinates":[9.9630403519,51.2690734863],"type":"Point"}
}