{
  "type": "Feature",
  "properties": {
    "iso:country":"DE",
    "sg:address":"Rheinstr. 32",
    "sg:city":"Biebesheim",
    "sg:phone":"+49 6258/7103",
    "sg:postcode":"64584",
    "sg:province":"Hessen",
    "wof:name":"Heldmann",
    "wof:placetype":"venue"
},
  "geometry": {"coordinates":[8.464886,49.779484],"type":"Point"}
}