{
  "type": "Feature",
  "properties": {
    "iso:country":"DE",
    "sg:address":"Flurteil Eule 6",
    "sg:city":"Colditz",
    "sg:phone":"+49 34381/8560",
    "sg:postcode":"04680",
    "sg:province":"Sachsen",
    "wof:name":"C. - R. Schlobach Jr. Baufachhandelsgesellschaft Mbh",
    "wof:placetype":"venue"
},
  "geometry": {"coordinates":[12.791663,51.138199],"type":"Point"}
}