{
  "type": "Feature",
  "properties": {
    "iso:country":"DE",
    "sg:address":"Alm 56",
    "sg:city":"Oberkirch",
    "sg:phone":"+49 7802/2530",
    "sg:postcode":"77704",
    "sg:province":"Baden-W\u00fcrttemberg",
    "wof:name":"Franz Spinner Fensterbau Gmbh",
    "wof:placetype":"venue"
},
  "geometry": {"coordinates":[8.091385,48.51416],"type":"Point"}
}