{
  "type": "Feature",
  "properties": {
    "iso:country":"DE",
    "sg:address":"Marsweilerstr. 67",
    "sg:city":"Baindt",
    "sg:phone":"+49 7502/911250",
    "sg:postcode":"88255",
    "sg:province":"Baden-W\u00fcrttemberg",
    "wof:name":"Deutschbein Ingenieur",
    "wof:placetype":"venue"
},
  "geometry": {"coordinates":[9.6691150665,47.8483543396],"type":"Point"}
}