{
  "type": "Feature",
  "properties": {
    "iso:country":"DE",
    "sg:address":"Kirchstr. 10",
    "sg:city":"Mitwitz",
    "sg:phone":"+49 9266/557",
    "sg:postcode":"96268",
    "sg:province":"Bayern",
    "wof:name":"Siegfried D\u00f6tschel",
    "wof:placetype":"venue"
},
  "geometry": {"coordinates":[11.2109241486,50.2477340698],"type":"Point"}
}