{
  "type": "Feature",
  "properties": {
    "iso:country":"DE",
    "sg:address":"Altonaer Str. 131",
    "sg:city":"Neum\u00fcnster",
    "sg:phone":"+49 4321/84498",
    "sg:postcode":"24539",
    "sg:province":"Schleswig-Holstein",
    "wof:name":"S\u00fcdbahnhof",
    "wof:placetype":"venue"
},
  "geometry": {"coordinates":[9.9820146561,54.0597724915],"type":"Point"}
}