{
  "type": "Feature",
  "properties": {
    "iso:country":"DE",
    "sg:address":"Elfringh\u00e4user Weg 6",
    "sg:city":"Twistetal",
    "sg:phone":"+49 5631/2267",
    "sg:postcode":"34477",
    "sg:province":"Hessen",
    "wof:name":"Ludwig Dohle",
    "wof:placetype":"venue"
},
  "geometry": {"coordinates":[8.902391,51.308884],"type":"Point"}
}