{
  "type": "Feature",
  "properties": {
    "iso:country":"DE",
    "sg:address":"Rosenstr. 19",
    "sg:city":"Hardthausen",
    "sg:phone":"+49 7139/7375",
    "sg:postcode":"74239",
    "sg:province":"Baden-W\u00fcrttemberg",
    "wof:name":"H. Apfelbach",
    "wof:placetype":"venue"
},
  "geometry": {"coordinates":[9.3561725616,49.2400436401],"type":"Point"}
}