{
  "type": "Feature",
  "properties": {
    "iso:country":"DE",
    "sg:address":"Postfach 1269:: 76352 Weingarten:: Germany.^^Apothekenstr 2::",
    "sg:city":"Weingarten",
    "sg:phone":"+49 7244/7210",
    "sg:postcode":"76356",
    "sg:province":"Baden-W\u00fcrttemberg",
    "wof:name":"Volksbank Weingarten-walzbachtal Eg",
    "wof:placetype":"venue"
},
  "geometry": {"coordinates":[8.531138,49.053307],"type":"Point"}
}