{
  "type": "Feature",
  "properties": {
    "iso:country":"DE",
    "sg:address":"26",
    "sg:city":"LUDRES",
    "sg:postcode":"54710",
    "wof:name":"Jolibier",
    "wof:placetype":"venue"
},
  "geometry": {"coordinates":[6.167407,48.611526],"type":"Point"}
}