{
  "type": "Feature",
  "properties": {
    "iso:country":"DE",
    "sg:address":"Helgebornstr. 14",
    "sg:city":"Rosbach",
    "sg:phone":"+49 6007/8793",
    "sg:postcode":"61191",
    "sg:province":"Hessen",
    "wof:name":"Elesdag Elektronische Steuerungs- Und",
    "wof:placetype":"venue"
},
  "geometry": {"coordinates":[8.6901054382,50.3032836914],"type":"Point"}
}