{
  "type": "Feature",
  "properties": {
    "iso:country":"DE",
    "sg:address":"Markt 1",
    "sg:city":"Schweinfurt",
    "sg:phone":"+49 9721/16419",
    "sg:postcode":"97421",
    "sg:province":"Bayern",
    "wof:name":"Ratskeller",
    "wof:placetype":"venue"
},
  "geometry": {"coordinates":[10.2349281311,50.0447998047],"type":"Point"}
}