{
  "type": "Feature",
  "properties": {
    "iso:country":"DE",
    "sg:address":"Stra\u00dfe der Jugend 44",
    "sg:city":"Klitten",
    "sg:phone":"+49 35895/50226",
    "sg:postcode":"02906",
    "sg:province":"Sachsen",
    "wof:name":"Herbert Vater",
    "wof:placetype":"venue"
},
  "geometry": {"coordinates":[14.604195,51.348682],"type":"Point"}
}