{
  "type": "Feature",
  "properties": {
    "iso:country":"DE",
    "sg:address":"Nonnenstr. 5b",
    "sg:city":"Leipzig",
    "sg:phone":"+49 341/486360",
    "sg:postcode":"04229",
    "sg:province":"Sachsen",
    "wof:name":"Ihs Gmbh",
    "wof:placetype":"venue"
},
  "geometry": {"coordinates":[12.3465204239,51.330406189],"type":"Point"}
}