{
  "type": "Feature",
  "properties": {
    "iso:country":"DE",
    "sg:address":"Am Sportplatz 1",
    "sg:city":"Zahna",
    "sg:phone":"+49 34924/20342",
    "sg:postcode":"06895",
    "sg:province":"Sachsen-Anhalt",
    "wof:name":"Sportlerheim",
    "wof:placetype":"venue"
},
  "geometry": {"coordinates":[12.7979488373,51.9136772156],"type":"Point"}
}