{
  "type": "Feature",
  "properties": {
    "iso:country":"DE",
    "sg:address":"Industriestr. 12",
    "sg:city":"Datteln",
    "sg:postcode":"45711",
    "sg:province":"Nordrhein-Westfalen",
    "wof:name":"Fleck Gmbh",
    "wof:placetype":"venue"
},
  "geometry": {"coordinates":[7.354384,51.666862],"type":"Point"}
}