{
  "type": "Feature",
  "properties": {
    "iso:country":"DE",
    "sg:address":"Wilhelmstr. 20",
    "sg:city":"Stuttgart",
    "sg:phone":"+49 711/556999",
    "sg:postcode":"70372",
    "sg:province":"Baden-W\u00fcrttemberg",
    "wof:name":"Bauer Und Maurer Rechtsanw\u00e4lte",
    "wof:placetype":"venue"
},
  "geometry": {"coordinates":[9.2169036865,48.8057022095],"type":"Point"}
}