{
  "type": "Feature",
  "properties": {
    "iso:country":"DE",
    "sg:address":"Venloer Str. 680",
    "sg:city":"K\u00f6ln",
    "sg:phone":"+49 221/9532380",
    "sg:postcode":"50827",
    "sg:province":"Nordrhein-Westfalen",
    "wof:name":"Pension Anke",
    "wof:placetype":"venue"
},
  "geometry": {"coordinates":[6.8976569176,50.9589996338],"type":"Point"}
}