{
  "type": "Feature",
  "properties": {
    "iso:country":"DE",
    "sg:address":"waldstrasse 14",
    "sg:city":"leipzig",
    "sg:phone":"+49 174 5919910",
    "sg:postcode":"04105",
    "sg:province":"Sachsen",
    "wof:name":"Die Bildschirmjaeger - Das Portal",
    "wof:placetype":"venue"
},
  "geometry": {"coordinates":[12.3594,51.34243],"type":"Point"}
}