{
  "type": "Feature",
  "properties": {
    "iso:country":"DE",
    "sg:address":"An den Linden 6",
    "sg:city":"Elsterheide",
    "sg:phone":"+49 3571/428294",
    "sg:postcode":"02979",
    "sg:province":"Sachsen",
    "wof:name":"Marianne Wogawa",
    "wof:placetype":"venue"
},
  "geometry": {"coordinates":[14.1944599152,51.4558448792],"type":"Point"}
}