{
  "type": "Feature",
  "properties": {
    "iso:country":"DE",
    "sg:address":"Oldenburgstr. 3",
    "sg:city":"Lauta",
    "sg:phone":"+49 35722/96107",
    "sg:postcode":"02991",
    "sg:province":"Sachsen",
    "wof:name":"Birgit Patzelt",
    "wof:placetype":"venue"
},
  "geometry": {"coordinates":[14.0960731506,51.4442367554],"type":"Point"}
}