{
  "type": "Feature",
  "properties": {
    "iso:country":"DE",
    "sg:address":"Josefstr. 51",
    "sg:city":"Lingen",
    "sg:phone":"+49 591/66913",
    "sg:postcode":"49809",
    "sg:province":"Niedersachsen",
    "wof:name":"Taute",
    "wof:placetype":"venue"
},
  "geometry": {"coordinates":[7.3441290855,52.5286445618],"type":"Point"}
}