{
  "type": "Feature",
  "properties": {
    "iso:country":"DE",
    "sg:address":"Frankfurter Str 95",
    "sg:city":"Raunheim",
    "sg:phone":"+49 6142/550610",
    "sg:postcode":"65479",
    "sg:province":"Hessen",
    "wof:name":"Itw Thermal Films",
    "wof:placetype":"venue"
},
  "geometry": {"coordinates":[8.4618377686,50.0174331665],"type":"Point"}
}