{
  "type": "Feature",
  "properties": {
    "iso:country":"DE",
    "sg:address":"Bahnhofstr. 19",
    "sg:city":"Lohne",
    "sg:phone":"+49 4442/1795",
    "sg:postcode":"49393",
    "sg:province":"Niedersachsen",
    "wof:name":"Adolf Thole",
    "wof:placetype":"venue"
},
  "geometry": {"coordinates":[8.231029,52.664845],"type":"Point"}
}