{
  "type": "Feature",
  "properties": {
    "iso:country":"DE",
    "sg:address":"Schlo\u00dfborner Weg 9 a",
    "sg:city":"Glash\u00fctten",
    "sg:phone":"+49 6174/63573",
    "sg:postcode":"61479",
    "sg:province":"Hessen",
    "wof:name":"Wolfgang Schmidt Architekt",
    "wof:placetype":"venue"
},
  "geometry": {"coordinates":[8.400277,50.214516],"type":"Point"}
}