{
  "type": "Feature",
  "properties": {
    "iso:country":"DE",
    "sg:address":"Bahnhof Mirke",
    "sg:city":"Wuppertal",
    "sg:phone":"+49 202/444545",
    "sg:postcode":"42105",
    "sg:province":"Nordrhein-Westfalen",
    "wof:name":"Abraham Scheer M\u00fchle",
    "wof:placetype":"venue"
},
  "geometry": {"coordinates":[7.1394200325,51.2617416382],"type":"Point"}
}