{
  "type": "Feature",
  "properties": {
    "iso:country":"DE",
    "sg:address":"Kalker Hauptstr. 98",
    "sg:city":"K\u00f6ln",
    "sg:phone":"+49 221/8702990",
    "sg:postcode":"51103",
    "sg:province":"Nordrhein-Westfalen",
    "wof:name":"A. Esendir",
    "wof:placetype":"venue"
},
  "geometry": {"coordinates":[7.0007100105,50.9375762939],"type":"Point"}
}