{
  "type": "Feature",
  "properties": {
    "iso:country":"DE",
    "sg:address":"Zur Wolfsdelle 11",
    "sg:city":"Neustadt",
    "sg:phone":"+49 6692/4692",
    "sg:postcode":"35279",
    "sg:province":"Hessen",
    "wof:name":"G. Kurz",
    "wof:placetype":"venue"
},
  "geometry": {"coordinates":[9.1071443558,50.9025001526],"type":"Point"}
}