{
  "type": "Feature",
  "properties": {
    "iso:country":"DE",
    "sg:address":"Emmentaler Str. 103",
    "sg:city":"Berlin",
    "sg:phone":"+49 30/4957041",
    "sg:postcode":"13409",
    "sg:province":"Berlin",
    "wof:name":"Zadar Grill",
    "wof:placetype":"venue"
},
  "geometry": {"coordinates":[13.362569809,52.5712051392],"type":"Point"}
}