{
  "type": "Feature",
  "properties": {
    "iso:country":"DE",
    "sg:address":"Zum Stadtturm 6",
    "sg:city":"Velburg",
    "sg:phone":"+49 9182/380",
    "sg:postcode":"92355",
    "sg:province":"Bayern",
    "wof:name":"Oskar Reithmeier Steinmetz",
    "wof:placetype":"venue"
},
  "geometry": {"coordinates":[11.6723079681,49.231212616],"type":"Point"}
}