{
  "type": "Feature",
  "properties": {
    "iso:country":"DE",
    "sg:address":"Oberes Kelterfeld 18",
    "sg:city":"Oettingen",
    "sg:phone":"+49 9082/2975",
    "sg:postcode":"86732",
    "sg:province":"Bayern",
    "wof:name":"Delphin Kolloid Gmbh",
    "wof:placetype":"venue"
},
  "geometry": {"coordinates":[10.594222,48.959702],"type":"Point"}
}