{
  "type": "Feature",
  "properties": {
    "iso:country":"DE",
    "sg:address":"K\u00f6nigsallee 14",
    "sg:city":"Gyhum",
    "sg:phone":"+49 4286/1041",
    "sg:postcode":"27404",
    "sg:province":"Niedersachsen",
    "wof:name":"Hermann Br\u00fcning",
    "wof:placetype":"venue"
},
  "geometry": {"coordinates":[9.307459,53.222027],"type":"Point"}
}