{
  "type": "Feature",
  "properties": {
    "iso:country":"DE",
    "sg:address":"Ahrstr. 23",
    "sg:city":"D\u00fcmpelfeld",
    "sg:phone":"+49 2695/251",
    "sg:postcode":"53520",
    "sg:province":"Rheinland-Pfalz",
    "wof:name":"A. Fuhrmann",
    "wof:placetype":"venue"
},
  "geometry": {"coordinates":[6.9358778,50.4448356628],"type":"Point"}
}