{
  "type": "Feature",
  "properties": {
    "iso:country":"DE",
    "sg:address":"Greizer Str. 70",
    "sg:city":"Werdau",
    "sg:phone":"+49 4937/61490",
    "sg:postcode":"08412",
    "sg:province":"Sachsen",
    "wof:name":"K\u00d6gel Werdau Gmbh",
    "wof:placetype":"venue"
},
  "geometry": {"coordinates":[12.3686218262,50.7141723633],"type":"Point"}
}