{
  "type": "Feature",
  "properties": {
    "iso:country":"DE",
    "sg:address":"Peter-M\u00fcller-Str 11",
    "sg:city":"Langen",
    "sg:phone":"+49 6103/750760",
    "sg:postcode":"63225",
    "sg:province":"Hessen",
    "wof:name":"Roger Stornfels Werbeagentur Gmbh",
    "wof:placetype":"venue"
},
  "geometry": {"coordinates":[8.670747,49.992409],"type":"Point"}
}