{
  "type": "Feature",
  "properties": {
    "iso:country":"DE",
    "sg:address":"Hermann-L\u00f6ns-Str. 4",
    "sg:city":"Braunlage",
    "sg:phone":"+49 5583/1398",
    "sg:postcode":"38700",
    "sg:province":"Niedersachsen",
    "wof:name":"Wilhelm Pilz Gmbh",
    "wof:placetype":"venue"
},
  "geometry": {"coordinates":[10.6667947769,51.6680412292],"type":"Point"}
}