{
  "type": "Feature",
  "properties": {
    "iso:country":"DE",
    "sg:address":"Lehweg 8",
    "sg:city":"Kehl",
    "sg:phone":"+49 7852/2337",
    "sg:postcode":"77694",
    "sg:province":"Baden-W\u00fcrttemberg",
    "wof:name":"Raiffeisen Warengenossenschaft Eg",
    "wof:placetype":"venue"
},
  "geometry": {"coordinates":[7.885687,48.556694],"type":"Point"}
}