{
  "type": "Feature",
  "properties": {
    "iso:country":"DE",
    "sg:address":"Maxplatz 35",
    "sg:city":"N\u00fcrnberg",
    "sg:postcode":"90403",
    "sg:province":"Bayern",
    "wof:name":"Raum & Textor Gmbh",
    "wof:placetype":"venue"
},
  "geometry": {"coordinates":[11.0715522766,49.4545021057],"type":"Point"}
}