{
  "type": "Feature",
  "properties": {
    "iso:country":"DE",
    "sg:address":"Richard-Wagner-Str. 17",
    "sg:city":"M\u00fcnchen",
    "sg:phone":"+49 89/5204630",
    "sg:postcode":"80333",
    "sg:province":"Bayern",
    "wof:name":"Wifi-unternehmensberatung Gmbh",
    "wof:placetype":"venue"
},
  "geometry": {"coordinates":[11.5633506775,48.1479988098],"type":"Point"}
}