{
  "type": "Feature",
  "properties": {
    "iso:country":"DE",
    "sg:address":"Am Dickeler Bruch 4",
    "sg:city":"Wetschen",
    "sg:phone":"+49 5446/885",
    "sg:postcode":"49453",
    "sg:province":"Niedersachsen",
    "wof:name":"Fritz Gieseke",
    "wof:placetype":"venue"
},
  "geometry": {"coordinates":[8.451719,52.613735],"type":"Point"}
}