{
  "type": "Feature",
  "properties": {
    "iso:country":"DE",
    "sg:address":"Otto-Lilienthal-Str. 10",
    "sg:city":"Wallenhorst",
    "sg:phone":"+49 5407/59893",
    "sg:postcode":"49134",
    "sg:province":"Niedersachsen",
    "wof:name":"Bernhard M\u00f6nkediek Gmbh",
    "wof:placetype":"venue"
},
  "geometry": {"coordinates":[7.999481,52.353321],"type":"Point"}
}