{
  "type": "Feature",
  "properties": {
    "iso:country":"DE",
    "sg:address":"Paulinenallee 56",
    "sg:city":"Hamburg",
    "sg:phone":"+49 40/8508600",
    "sg:postcode":"22769",
    "sg:province":"Hamburg",
    "wof:name":"G. Rathmann",
    "wof:placetype":"venue"
},
  "geometry": {"coordinates":[9.9493846893,53.5680770874],"type":"Point"}
}