{
  "type": "Feature",
  "properties": {
    "iso:country":"DE",
    "sg:address":"Hauptstr. 18",
    "sg:city":"Freiburg",
    "sg:phone":"+49 761/36139",
    "sg:postcode":"79104",
    "sg:province":"Baden-W\u00fcrttemberg",
    "wof:name":"Ev. Pfarramt Ludwigskirche N.",
    "wof:placetype":"venue"
},
  "geometry": {"coordinates":[7.8586421013,48.0073852539],"type":"Point"}
}