{
  "type": "Feature",
  "properties": {
    "iso:country":"DE",
    "sg:address":"Bahnhofstr. 34",
    "sg:city":"B\u00fcckeburg",
    "sg:phone":"+49 5722/5004",
    "sg:postcode":"31675",
    "sg:province":"Niedersachsen",
    "wof:name":"Schraepler V. Harpe Werth U. Naue",
    "wof:placetype":"venue"
},
  "geometry": {"coordinates":[9.0461778641,52.2613487244],"type":"Point"}
}