{
  "type": "Feature",
  "properties": {
    "iso:country":"DE",
    "sg:address":"Am Felshang 1 a",
    "sg:city":"Stolberg",
    "sg:phone":"+49 2402/5356",
    "sg:postcode":"52223",
    "sg:province":"Nordrhein-Westfalen",
    "wof:name":"Detlev Maschler Rechtsanwalt",
    "wof:placetype":"venue"
},
  "geometry": {"coordinates":[6.2067828178,50.7592010498],"type":"Point"}
}