{
  "type": "Feature",
  "properties": {
    "iso:country":"DE",
    "sg:address":"Schwarzburger Str. 18",
    "sg:city":"Bad Blankenburg",
    "sg:phone":"+49 36741/2518",
    "sg:postcode":"07422",
    "sg:province":"Th\u00fcringen",
    "wof:name":"Volker T\u00f6pfer Gmbh Baumaschinenverleih",
    "wof:placetype":"venue"
},
  "geometry": {"coordinates":[11.2700014114,50.6771430969],"type":"Point"}
}