{
  "type": "Feature",
  "properties": {
    "iso:country":"DE",
    "sg:address":"Sonnenstr. 7a",
    "sg:city":"Olching",
    "sg:phone":"+49 8142/489100",
    "sg:postcode":"82140",
    "sg:province":"Bayern",
    "wof:name":"Michael N\u00e4\u00dfl Steuerberater",
    "wof:placetype":"venue"
},
  "geometry": {"coordinates":[11.3092794418,48.2032089233],"type":"Point"}
}