{
  "type": "Feature",
  "properties": {
    "iso:country":"DE",
    "sg:address":"Bahnhofstr. 10",
    "sg:city":"Apolda",
    "sg:phone":"+49 3644/563625",
    "sg:postcode":"99510",
    "sg:province":"Th\u00fcringen",
    "wof:name":"Westphal",
    "wof:placetype":"venue"
},
  "geometry": {"coordinates":[11.516596,51.024158],"type":"Point"}
}