{
  "type": "Feature",
  "properties": {
    "iso:country":"DE",
    "sg:address":"Schwyzer Str. 20 c",
    "sg:city":"Berlin",
    "sg:phone":"+49 30/4552781",
    "sg:postcode":"13349",
    "sg:province":"Berlin",
    "wof:name":"Dieter Vogt Ingenieur",
    "wof:placetype":"venue"
},
  "geometry": {"coordinates":[13.3564176559,52.5595169067],"type":"Point"}
}