{
  "type": "Feature",
  "properties": {
    "iso:country":"DE",
    "sg:address":"Achternbergstr. 10",
    "sg:city":"Gelsenkirchen",
    "sg:phone":"+49 209/913940",
    "sg:postcode":"45884",
    "sg:province":"Nordrhein-Westfalen",
    "wof:name":"Elektro Gerhardt Gmbh",
    "wof:placetype":"venue"
},
  "geometry": {"coordinates":[7.085474,51.486866],"type":"Point"}
}