{
  "type": "Feature",
  "properties": {
    "iso:country":"DE",
    "sg:address":"Bistard 49 B",
    "sg:city":"Viersen",
    "sg:phone":"+49 2162/7529",
    "sg:postcode":"41751",
    "sg:province":"Nordrhein-Westfalen",
    "wof:name":"Steinfals Gmbh",
    "wof:placetype":"venue"
},
  "geometry": {"coordinates":[6.332479,51.279881],"type":"Point"}
}