{
  "type": "Feature",
  "properties": {
    "iso:country":"DE",
    "sg:address":"Lichtentaler Str. 66",
    "sg:city":"Baden-Baden",
    "sg:phone":"+49 7221/24642",
    "sg:postcode":"76530",
    "sg:province":"Baden-W\u00fcrttemberg",
    "wof:name":"Herbert M\u00fcller",
    "wof:placetype":"venue"
},
  "geometry": {"coordinates":[8.2435073853,48.7551803589],"type":"Point"}
}