{
  "type": "Feature",
  "properties": {
    "iso:country":"DE",
    "sg:address":"Domstr. 15",
    "sg:city":"W\u00fcrzburg",
    "sg:phone":"+49 931/51483",
    "sg:postcode":"97070",
    "sg:province":"Bayern",
    "wof:name":"Kresinsky",
    "wof:placetype":"venue"
},
  "geometry": {"coordinates":[9.9300889969,49.7932891846],"type":"Point"}
}