{
  "type": "Feature",
  "properties": {
    "iso:country":"DE",
    "sg:address":"Paderborner Tor 92",
    "sg:city":"Warburg",
    "sg:phone":"+49 5641/1844",
    "sg:postcode":"34414",
    "sg:province":"Nordrhein-Westfalen",
    "wof:name":"Fatma Akkoc",
    "wof:placetype":"venue"
},
  "geometry": {"coordinates":[9.1433801651,51.489151001],"type":"Point"}
}