{
  "type": "Feature",
  "properties": {
    "iso:country":"DE",
    "sg:address":"Elfershausener Str. 4",
    "sg:city":"Hammelburg",
    "sg:phone":"+49 9732/2810",
    "sg:postcode":"97762",
    "sg:province":"Bayern",
    "wof:name":"E. Schmitt",
    "wof:placetype":"venue"
},
  "geometry": {"coordinates":[9.936141,50.122356],"type":"Point"}
}