{
  "type": "Feature",
  "properties": {
    "iso:country":"DE",
    "sg:address":"Laurentiusstr. 3",
    "sg:city":"K\u00fcnzing",
    "sg:postcode":"94550",
    "sg:province":"Bayern",
    "wof:name":"Lamisafe Gmbh",
    "wof:placetype":"venue"
},
  "geometry": {"coordinates":[13.0766057968,48.6669311523],"type":"Point"}
}