{
  "type": "Feature",
  "properties": {
    "iso:country":"DE",
    "sg:address":"Hochlerchstr. 10",
    "sg:city":"Marquartstein",
    "sg:phone":"+49 8641/598052",
    "sg:postcode":"83250",
    "sg:province":"Bayern",
    "wof:name":"Pflege-mobil Wilfried Rittaler",
    "wof:placetype":"venue"
},
  "geometry": {"coordinates":[12.464497,47.762356],"type":"Point"}
}