{
  "type": "Feature",
  "properties": {
    "iso:country":"DE",
    "sg:address":"G\u00e4rtnersiedlung 9",
    "sg:city":"B\u00fcrstadt",
    "sg:phone":"+49 6206/71457",
    "sg:postcode":"68642",
    "sg:province":"Hessen",
    "wof:name":"Peter B\u00f6ttcher",
    "wof:placetype":"venue"
},
  "geometry": {"coordinates":[8.483275,49.618488],"type":"Point"}
}