{
  "type": "Feature",
  "properties": {
    "iso:country":"DE",
    "sg:address":"Im Sulzfeld 25",
    "sg:city":"Silz",
    "sg:phone":"+49 6346/5317",
    "sg:postcode":"76857",
    "sg:province":"Rheinland-Pfalz",
    "wof:name":"Pension Werner Gerstle",
    "wof:placetype":"venue"
},
  "geometry": {"coordinates":[7.9462690353,49.1453056335],"type":"Point"}
}