{
  "type": "Feature",
  "properties": {
    "iso:country":"DE",
    "sg:address":"Pfaffensteig 19",
    "sg:city":"Bad Steben",
    "sg:phone":"+49 9288/232",
    "sg:postcode":"95138",
    "sg:province":"Bayern",
    "wof:name":"Ulrike Ernst-seiler",
    "wof:placetype":"venue"
},
  "geometry": {"coordinates":[11.645475,50.368832],"type":"Point"}
}