{
  "type": "Feature",
  "properties": {
    "iso:country":"DE",
    "sg:address":"Engelsgasse 4",
    "sg:city":"Friedberg",
    "sg:phone":"+49 6031/3521",
    "sg:postcode":"61169",
    "sg:province":"Hessen",
    "wof:name":"Altstadtsch\u00e4nke",
    "wof:placetype":"venue"
},
  "geometry": {"coordinates":[8.7552242279,50.3387527466],"type":"Point"}
}