{
  "type": "Feature",
  "properties": {
    "iso:country":"DE",
    "sg:address":"Dorstener Str. 11",
    "sg:city":"Raesfeld",
    "sg:phone":"+49 2865/6526",
    "sg:postcode":"46348",
    "sg:province":"Nordrhein-Westfalen",
    "wof:name":"H\u00f6bing Und Tunholt",
    "wof:placetype":"venue"
},
  "geometry": {"coordinates":[6.8421411514,51.7689590454],"type":"Point"}
}