{
  "type": "Feature",
  "properties": {
    "iso:country":"DE",
    "sg:address":"Altdobritz 11",
    "sg:city":"Dresden",
    "sg:phone":"+49 351/2527418",
    "sg:postcode":"01237",
    "sg:province":"Sachsen",
    "wof:name":"Drei Kronen",
    "wof:placetype":"venue"
},
  "geometry": {"coordinates":[13.810271,51.018616],"type":"Point"}
}