{
  "type": "Feature",
  "properties": {
    "iso:country":"DE",
    "sg:address":"Dexionstr. 2",
    "sg:city":"Laubach",
    "sg:phone":"+49 6405/6611",
    "sg:postcode":"35321",
    "sg:province":"Hessen",
    "wof:name":"Penny Gmbh",
    "wof:placetype":"venue"
},
  "geometry": {"coordinates":[8.9799222946,50.5444450378],"type":"Point"}
}