{
  "type": "Feature",
  "properties": {
    "iso:country":"DE",
    "sg:address":"Tannenbergplatz 7",
    "sg:city":"Espelkamp",
    "sg:phone":"+49 5772/5253",
    "sg:postcode":"32339",
    "sg:province":"Nordrhein-Westfalen",
    "wof:name":"Gustav Vordenb\u00e4umen",
    "wof:placetype":"venue"
},
  "geometry": {"coordinates":[8.6045951843,52.3812103271],"type":"Point"}
}