{
  "type": "Feature",
  "properties": {
    "iso:country":"DE",
    "sg:address":"Marktstr. 15",
    "sg:city":"Homberg",
    "sg:phone":"+49 6633/919060",
    "sg:postcode":"35315",
    "sg:province":"Hessen",
    "wof:name":"Monika Knopp",
    "wof:placetype":"venue"
},
  "geometry": {"coordinates":[8.9982042313,50.7275390625],"type":"Point"}
}