{
  "type": "Feature",
  "properties": {
    "iso:country":"DE",
    "sg:address":"Hoengener Str.",
    "sg:city":"Alsdorf",
    "sg:phone":"+49 2404/969300",
    "sg:postcode":"52477",
    "sg:province":"Nordrhein-Westfalen",
    "wof:name":"H. Kaldenbach",
    "wof:placetype":"venue"
},
  "geometry": {"coordinates":[6.1806201935,50.8750915527],"type":"Point"}
}