{
  "type": "Feature",
  "properties": {
    "iso:country":"DE",
    "sg:address":"Guts-Muths-Str. 26",
    "sg:city":"Hannover",
    "sg:postcode":"30165",
    "sg:province":"Niedersachsen",
    "wof:name":"Fliesen Lohr Gmbh",
    "wof:placetype":"venue"
},
  "geometry": {"coordinates":[9.7270679474,52.3967475891],"type":"Point"}
}