{
  "type": "Feature",
  "properties": {
    "iso:country":"DE",
    "sg:address":"Alemannstr. 21",
    "sg:city":"Hannover",
    "sg:phone":"+49 511/3522222",
    "sg:postcode":"30165",
    "sg:province":"Niedersachsen",
    "wof:name":"Nieders\u00e4chsische Papier- Rollenfabrik",
    "wof:placetype":"venue"
},
  "geometry": {"coordinates":[9.7328777313,52.3911514282],"type":"Point"}
}