{
  "type": "Feature",
  "properties": {
    "iso:country":"DE",
    "sg:address":"Mittelstr. 4",
    "sg:city":"Pouch",
    "sg:postcode":"06774",
    "sg:province":"Sachsen-Anhalt",
    "wof:name":"Evangelisches Pfarramt Pouch",
    "wof:placetype":"venue"
},
  "geometry": {"coordinates":[12.3990268707,51.6257133484],"type":"Point"}
}