{
  "type": "Feature",
  "properties": {
    "iso:country":"DE",
    "sg:address":"Hohenzollernstra\u00dfe 73a",
    "sg:city":"Karlsruhe",
    "sg:phone":"+49 721",
    "sg:postcode":"76135",
    "sg:province":"Baden-W\u00fcrttemberg",
    "wof:name":"Dipl.-ing. Rainer Und Oliver Puls Gmbh",
    "wof:placetype":"venue"
},
  "geometry": {"coordinates":[8.3845205307,48.9938659668],"type":"Point"}
}