{
  "type": "Feature",
  "properties": {
    "iso:country":"DE",
    "sg:address":"Rudolf-Diesel-Str. 8",
    "sg:city":"Schwalbach",
    "sg:postcode":"66773",
    "sg:province":"Saarland",
    "wof:name":"Gross Und Partner Rechtsanw\u00e4lte",
    "wof:placetype":"venue"
},
  "geometry": {"coordinates":[6.7944197655,49.2984886169],"type":"Point"}
}