{
  "type": "Feature",
  "properties": {
    "iso:country":"DE",
    "sg:address":"Philosophenweg 12",
    "sg:city":"Heidelberg",
    "sg:postcode":"69120",
    "sg:province":"Baden-W\u00fcrttemberg",
    "wof:name":"Physikalisches Institut",
    "wof:placetype":"venue"
},
  "geometry": {"coordinates":[8.7002000809,49.4148979187],"type":"Point"}
}