{
  "type": "Feature",
  "properties": {
    "iso:country":"DE",
    "sg:address":"Kreuzwegstr. 8",
    "sg:city":"Greu\u00dfenheim",
    "sg:phone":"+49 9369/1389",
    "sg:postcode":"97259",
    "sg:province":"Bayern",
    "wof:name":"Hartmut B\u00f6hnke",
    "wof:placetype":"venue"
},
  "geometry": {"coordinates":[9.7619991302,49.8106918335],"type":"Point"}
}