{
  "type": "Feature",
  "properties": {
    "iso:country":"DE",
    "sg:address":"Eichendorffstr. 17",
    "sg:city":"Steinheim",
    "sg:phone":"+49 5233/7304",
    "sg:postcode":"32839",
    "sg:province":"Nordrhein-Westfalen",
    "wof:name":"Maria Lange",
    "wof:placetype":"venue"
},
  "geometry": {"coordinates":[9.0813083649,51.8721199036],"type":"Point"}
}