{
  "type": "Feature",
  "properties": {
    "iso:country":"DE",
    "sg:address":"Chemnitzer Str. 3",
    "sg:city":"Augustusburg",
    "sg:phone":"+49 37291/2930",
    "sg:postcode":"09573",
    "sg:province":"Sachsen",
    "wof:name":"H\u00f6sel & Kreller Gmbh",
    "wof:placetype":"venue"
},
  "geometry": {"coordinates":[13.101388,50.815128],"type":"Point"}
}