{
  "type": "Feature",
  "properties": {
    "iso:country":"DE",
    "sg:address":"Liebermannstr.16",
    "sg:city":"Magdeburg",
    "sg:phone":"+49 391/7376241",
    "sg:postcode":"39108",
    "sg:province":"Sachsen-Anhalt",
    "wof:name":"Ingenieurb\u00fcro Thomas Seidel",
    "wof:placetype":"venue"
},
  "geometry": {"coordinates":[11.6066837311,52.1320915222],"type":"Point"}
}