{
  "type": "Feature",
  "properties": {
    "iso:country":"DE",
    "sg:address":"Auf dem Leuchtenberg 44",
    "sg:city":"Grevenbroich",
    "sg:phone":"+49 2181/80608",
    "sg:postcode":"41517",
    "sg:province":"Nordrhein-Westfalen",
    "wof:name":"Barbara-apotheke P\u00e4chterin Anette Belda E. K.",
    "wof:placetype":"venue"
},
  "geometry": {"coordinates":[6.578813,51.045361],"type":"Point"}
}