{
  "type": "Feature",
  "properties": {
    "iso:country":"DE",
    "sg:address":"Heinrich-Hertz-Str 1b",
    "sg:city":"Kleinmachnow",
    "sg:phone":"+49 33203/80470",
    "sg:postcode":"14532",
    "sg:province":"Brandenburg",
    "wof:name":"Alpha Bioverfahrenstechnik Gmbh",
    "wof:placetype":"venue"
},
  "geometry": {"coordinates":[13.1868391037,52.4044075012],"type":"Point"}
}