{
  "type": "Feature",
  "properties": {
    "iso:country":"DE",
    "sg:address":"Bertolt-Brecht-Str. 3 a",
    "sg:city":"Neustadt",
    "sg:postcode":"07806",
    "sg:province":"Th\u00fcringen",
    "wof:name":"Wegel Leuchten E. K.",
    "wof:placetype":"venue"
},
  "geometry": {"coordinates":[14.262408,51.440723],"type":"Point"}
}