{
  "type": "Feature",
  "properties": {
    "iso:country":"DE",
    "sg:address":"Im Gigis 1",
    "sg:city":"Murr",
    "sg:phone":"+49 7144/821073",
    "sg:postcode":"71711",
    "sg:province":"Baden-W\u00fcrttemberg",
    "wof:name":"Diakoniestation Bottwartal",
    "wof:placetype":"venue"
},
  "geometry": {"coordinates":[9.253177,48.960503],"type":"Point"}
}