{
  "type": "Feature",
  "properties": {
    "iso:country":"DE",
    "sg:address":"Landstrasse 67 a",
    "sg:city":"Sinzheim",
    "sg:phone":"+49 7221/803333",
    "sg:postcode":"76547",
    "sg:province":"Baden-W\u00fcrttemberg",
    "wof:name":"Hotelsite Network - Www.conference-interactive.de",
    "wof:placetype":"venue"
},
  "geometry": {"coordinates":[8.169473,48.765316],"type":"Point"}
}