{
  "type": "Feature",
  "properties": {
    "iso:country":"DE",
    "sg:address":"Bautzener Str. 64",
    "sg:city":"Wei\u00dfwasser",
    "sg:phone":"+49 3576/207323",
    "sg:postcode":"02943",
    "sg:province":"Sachsen",
    "wof:name":"R\u00fcdiger Kania",
    "wof:placetype":"venue"
},
  "geometry": {"coordinates":[14.6409759521,51.5038909912],"type":"Point"}
}