{
  "type": "Feature",
  "properties": {
    "iso:country":"DE",
    "sg:address":"Ottmaringer Str. 2",
    "sg:city":"Dietfurt",
    "sg:phone":"+49 8464/388",
    "sg:postcode":"92345",
    "sg:province":"Bayern",
    "wof:name":"Getr\u00e4nkegro\u00dfhdl. Siegfr. Meier",
    "wof:placetype":"venue"
},
  "geometry": {"coordinates":[11.563396,49.02507],"type":"Point"}
}