{
  "type": "Feature",
  "properties": {
    "iso:country":"DE",
    "sg:address":"Krampnitzer Weg 8",
    "sg:city":"Berlin",
    "sg:phone":"+49 30/3658783",
    "sg:postcode":"14089",
    "sg:province":"Berlin",
    "wof:name":"Eberhard Brennecke Architekt",
    "wof:placetype":"venue"
},
  "geometry": {"coordinates":[13.1364021301,52.4524116516],"type":"Point"}
}