{
  "type": "Feature",
  "properties": {
    "iso:country":"DE",
    "sg:address":"Kuenstr. 51",
    "sg:city":"Weingarten",
    "sg:phone":"+49 751/51810",
    "sg:postcode":"88250",
    "sg:province":"Baden-W\u00fcrttemberg",
    "wof:name":"R. Kirchner Versicherungen",
    "wof:placetype":"venue"
},
  "geometry": {"coordinates":[9.628569603,47.8034133911],"type":"Point"}
}