{
  "type": "Feature",
  "properties": {
    "iso:country":"DE",
    "sg:address":"Siegfriedstr. 44",
    "sg:city":"Worms",
    "sg:postcode":"67547",
    "sg:province":"Rheinland-Pfalz",
    "wof:name":"Inter Inkasso Ag",
    "wof:placetype":"venue"
},
  "geometry": {"coordinates":[8.3582801819,49.6347084045],"type":"Point"}
}