{
  "type": "Feature",
  "properties": {
    "iso:country":"DE",
    "sg:address":"Batenbrockstr. 39-41",
    "sg:city":"Bottrop",
    "sg:postcode":"46238",
    "sg:province":"Nordrhein-Westfalen",
    "wof:name":"Nowak Transport Gmbh",
    "wof:placetype":"venue"
},
  "geometry": {"coordinates":[6.9594221115,51.5300674438],"type":"Point"}
}