{
  "type": "Feature",
  "properties": {
    "iso:country":"DE",
    "sg:address":"Sch\u00e4ferstr. 5",
    "sg:city":"Visselh\u00f6vede",
    "sg:phone":"+49 4262/704",
    "sg:postcode":"27374",
    "sg:province":"Niedersachsen",
    "wof:name":"Volksbank Visselh\u00f6vede",
    "wof:placetype":"venue"
},
  "geometry": {"coordinates":[9.582964,52.985859],"type":"Point"}
}