{
  "type": "Feature",
  "properties": {
    "iso:country":"DE",
    "sg:address":"Oerschbachstr. 2",
    "sg:city":"D\u00fcsseldorf",
    "sg:phone":"+49 211/9995800",
    "sg:postcode":"40599",
    "sg:province":"Nordrhein-Westfalen",
    "wof:name":"Wassen Dachtechnik Gmbh",
    "wof:placetype":"venue"
},
  "geometry": {"coordinates":[6.8568840027,51.1828269958],"type":"Point"}
}