{
  "type": "Feature",
  "properties": {
    "iso:country":"DE",
    "sg:address":"Sonnenstr. 9",
    "sg:city":"Sulzbachtal",
    "sg:phone":"+49 6308/1411",
    "sg:postcode":"67734",
    "sg:province":"Rheinland-Pfalz",
    "wof:name":"Kurt M\u00fcller",
    "wof:placetype":"venue"
},
  "geometry": {"coordinates":[7.694823,49.505924],"type":"Point"}
}