{
  "type": "Feature",
  "properties": {
    "iso:country":"DE",
    "sg:address":"Neubauernweg 5",
    "sg:city":"Heidenau",
    "sg:phone":"+49 3529/519250",
    "sg:postcode":"01809",
    "sg:province":"Sachsen",
    "wof:name":"Gerhard Keyser",
    "wof:placetype":"venue"
},
  "geometry": {"coordinates":[13.88555,50.951618],"type":"Point"}
}