{
  "type": "Feature",
  "properties": {
    "iso:country":"DE",
    "sg:address":"Wellenburger Str. 31",
    "sg:city":"Augsburg",
    "sg:phone":"+49 821/414666",
    "sg:postcode":"86199",
    "sg:province":"Bayern",
    "wof:name":"Nahrungs- Genussmittel Non Food Abholm\u00e4rkte Gam Gmbh",
    "wof:placetype":"venue"
},
  "geometry": {"coordinates":[10.8613872528,48.338848114],"type":"Point"}
}