{
  "type": "Feature",
  "properties": {
    "iso:country":"DE",
    "sg:address":"Rosenstr. 14",
    "sg:city":"Gelsenkirchen",
    "sg:phone":"+49 209/394508",
    "sg:postcode":"45899",
    "sg:province":"Nordrhein-Westfalen",
    "wof:name":"Margit Buttler",
    "wof:placetype":"venue"
},
  "geometry": {"coordinates":[7.028917,51.544537],"type":"Point"}
}