{
  "type": "Feature",
  "properties": {
    "iso:country":"DE",
    "sg:address":"Dillstr. 1",
    "sg:city":"A\u00dflar",
    "sg:phone":"+49 6441/87377",
    "sg:postcode":"35614",
    "sg:province":"Hessen",
    "wof:name":"Warz Gmbh",
    "wof:placetype":"venue"
},
  "geometry": {"coordinates":[8.4610309601,50.5848999023],"type":"Point"}
}