{
  "type": "Feature",
  "properties": {
    "iso:country":"DE",
    "sg:address":"Gartenweg 2",
    "sg:city":"Neum\u00fchle",
    "sg:phone":"+49 3661/434323",
    "sg:postcode":"07980",
    "sg:province":"Th\u00fcringen",
    "wof:name":"Klaus Leiterer",
    "wof:placetype":"venue"
},
  "geometry": {"coordinates":[12.1725,50.705009],"type":"Point"}
}