{
  "type": "Feature",
  "properties": {
    "iso:country":"DE",
    "sg:address":"Am Schrickenhof 7",
    "sg:city":"J\u00fclich",
    "sg:phone":"+49 2461/7490",
    "sg:postcode":"52428",
    "sg:province":"Nordrhein-Westfalen",
    "wof:name":"Peter Freyaldenhoven",
    "wof:placetype":"venue"
},
  "geometry": {"coordinates":[6.351111,50.896103],"type":"Point"}
}