{
  "type": "Feature",
  "properties": {
    "iso:country":"DE",
    "sg:address":"K\u00f6nigshainer Str.",
    "sg:city":"Reichenbach",
    "sg:phone":"+49 35828/72622",
    "sg:postcode":"02894",
    "sg:province":"Sachsen",
    "wof:name":"Milchgut Reichenbach Gmbh",
    "wof:placetype":"venue"
},
  "geometry": {"coordinates":[14.8193902969,51.1505851746],"type":"Point"}
}