{
  "type": "Feature",
  "properties": {
    "iso:country":"DE",
    "sg:address":"Lagerstr. 18",
    "sg:city":"Rostock",
    "sg:phone":"+49 381/4934346",
    "sg:postcode":"18055",
    "sg:province":"Mecklenburg-Vorpommern",
    "wof:name":"Milinski Und Haldan Ergotherapiepraxis",
    "wof:placetype":"venue"
},
  "geometry": {"coordinates":[12.13704,54.091766],"type":"Point"}
}