{
  "type": "Feature",
  "properties": {
    "iso:country":"DE",
    "sg:address":"Achimer Str. 5",
    "sg:city":"Delmenhorst",
    "sg:phone":"+49 4221/70005",
    "sg:postcode":"27755",
    "sg:province":"Niedersachsen",
    "wof:name":"Handelshaus Legler Ohg",
    "wof:placetype":"venue"
},
  "geometry": {"coordinates":[8.6695652008,53.0371932983],"type":"Point"}
}