{
  "type": "Feature",
  "properties": {
    "iso:country":"DE",
    "sg:address":"Oberstr. 1",
    "sg:city":"Nettetal",
    "sg:phone":"+49 2153/915353",
    "sg:postcode":"41334",
    "sg:province":"Nordrhein-Westfalen",
    "wof:name":"George Lickes Steuerberater",
    "wof:placetype":"venue"
},
  "geometry": {"coordinates":[6.2813467979,51.3353424072],"type":"Point"}
}