{
  "type": "Feature",
  "properties": {
    "iso:country":"DE",
    "sg:address":"Zum Kasseteich 4",
    "sg:city":"Probsteierhagen",
    "sg:phone":"+49 4348/379",
    "sg:postcode":"24253",
    "sg:province":"Schleswig-Holstein",
    "wof:name":"J\u00f6rn G\u00f6ttsch",
    "wof:placetype":"venue"
},
  "geometry": {"coordinates":[10.2646217346,54.3489646912],"type":"Point"}
}