{
  "type": "Feature",
  "properties": {
    "iso:country":"DE",
    "sg:address":"Markfestestr. 16",
    "sg:city":"Aldenhoven",
    "sg:phone":"+49 2464/1436",
    "sg:postcode":"52457",
    "sg:province":"Nordrhein-Westfalen",
    "wof:name":"Lbv Lohnsteuerberatungs- Verein E. V.",
    "wof:placetype":"venue"
},
  "geometry": {"coordinates":[6.2890758514,50.895324707],"type":"Point"}
}