{
  "type": "Feature",
  "properties": {
    "iso:country":"DE",
    "sg:address":"Stummplatz 1",
    "sg:city":"Neunkirchen",
    "sg:phone":"+49 6821/24402",
    "sg:postcode":"66538",
    "sg:province":"Saarland",
    "wof:name":"Ernst Schmidt",
    "wof:placetype":"venue"
},
  "geometry": {"coordinates":[7.1741390228,49.3482666016],"type":"Point"}
}