{
  "type": "Feature",
  "properties": {
    "iso:country":"DE",
    "sg:address":"Landauer Str. 2",
    "sg:city":"Plattling",
    "sg:phone":"+49 9931/1801",
    "sg:postcode":"94447",
    "sg:province":"Bayern",
    "wof:name":"Eggl",
    "wof:placetype":"venue"
},
  "geometry": {"coordinates":[12.8728055954,48.7764968872],"type":"Point"}
}