{
  "type": "Feature",
  "properties": {
    "iso:country":"DE",
    "sg:address":"Nibelungenstr. 146 a",
    "sg:city":"Bensheim",
    "sg:postcode":"64625",
    "sg:province":"Hessen",
    "wof:name":"Das Digital Arts Und Service Gmbh",
    "wof:placetype":"venue"
},
  "geometry": {"coordinates":[8.637077,49.685951],"type":"Point"}
}