{
  "type": "Feature",
  "properties": {
    "iso:country":"DE",
    "sg:address":"Dorfstr. 16",
    "sg:city":"Wipfratal",
    "sg:phone":"+49 3628/48173",
    "sg:postcode":"99310",
    "sg:province":"Th\u00fcringen",
    "wof:name":"Landwirtschaftliche Erzeugerges. Mbh",
    "wof:placetype":"venue"
},
  "geometry": {"coordinates":[10.942014,50.756458],"type":"Point"}
}