{
  "type": "Feature",
  "properties": {
    "iso:country":"DE",
    "sg:address":"Am Waldecker Berg",
    "sg:city":"Korbach",
    "sg:phone":"+49 5631/3125",
    "sg:postcode":"34497",
    "sg:province":"Hessen",
    "wof:name":"Herbert Sippel-heine",
    "wof:placetype":"venue"
},
  "geometry": {"coordinates":[8.886587,51.268436],"type":"Point"}
}