{
  "type": "Feature",
  "properties": {
    "iso:country":"DE",
    "sg:address":"Maria Hell 2",
    "sg:city":"Cochem",
    "sg:phone":"+49 2671/98760",
    "sg:postcode":"56812",
    "sg:province":"Rheinland-Pfalz",
    "wof:name":"Brillen M\u00fcller Gmbh",
    "wof:placetype":"venue"
},
  "geometry": {"coordinates":[7.160175,50.143635],"type":"Point"}
}