{
  "type": "Feature",
  "properties": {
    "iso:country":"DE",
    "sg:address":"Vilstalstr. 20",
    "sg:city":"Vilseck",
    "sg:phone":"+49 9662/41110",
    "sg:postcode":"92249",
    "sg:province":"Bayern",
    "wof:name":"M\u00fchlenhof Pension Winkler",
    "wof:placetype":"venue"
},
  "geometry": {"coordinates":[11.787563324,49.6052856445],"type":"Point"}
}