{
  "type": "Feature",
  "properties": {
    "iso:country":"DE",
    "sg:address":"Honschaftsstr. 298",
    "sg:city":"K\u00f6ln",
    "sg:phone":"+49 221/638600",
    "sg:postcode":"51061",
    "sg:province":"Nordrhein-Westfalen",
    "wof:name":"Optik Geuer & Nordhaus Ohg",
    "wof:placetype":"venue"
},
  "geometry": {"coordinates":[7.0327539444,50.9810028076],"type":"Point"}
}