{
  "type": "Feature",
  "properties": {
    "iso:country":"DE",
    "sg:address":"E.-Busse-Str. 4",
    "sg:city":"Weimar",
    "sg:phone":"+49 4936/434550",
    "sg:postcode":"99427",
    "sg:province":"Th\u00fcringen",
    "wof:name":"Comfort Hotel Weimar",
    "wof:placetype":"venue"
},
  "geometry": {"coordinates":[11.341267,51.012486],"type":"Point"}
}