{
  "type": "Feature",
  "properties": {
    "iso:country":"DE",
    "sg:address":"Bahnhofstr. 10",
    "sg:city":"Wetzlar",
    "sg:phone":"+49 641/25566",
    "sg:postcode":"35582",
    "sg:province":"Hessen",
    "wof:name":"J\u00fcrgen Kleinmichel Rechtsanwalt",
    "wof:placetype":"venue"
},
  "geometry": {"coordinates":[8.5996379852,50.561000824],"type":"Point"}
}