{
  "type": "Feature",
  "properties": {
    "iso:country":"DE",
    "sg:address":"Kleiwellenfeld 35",
    "sg:city":"Ahlen",
    "sg:phone":"+49 2382/98160",
    "sg:postcode":"59229",
    "sg:province":"Nordrhein-Westfalen",
    "wof:name":"Elektro-pollmeier Gmbh",
    "wof:placetype":"venue"
},
  "geometry": {"coordinates":[7.87852,51.737453],"type":"Point"}
}