{
  "type": "Feature",
  "properties": {
    "iso:country":"DE",
    "sg:address":"Klempauer Str. 2",
    "sg:city":"Krummesse",
    "sg:phone":"+49 4508/650",
    "sg:postcode":"23628",
    "sg:province":"Schleswig-Holstein",
    "wof:name":"Otto Breitling Masseur",
    "wof:placetype":"venue"
},
  "geometry": {"coordinates":[10.642002,53.780304],"type":"Point"}
}