{
  "type": "Feature",
  "properties": {
    "iso:country":"DE",
    "sg:address":"Birkenweg 1",
    "sg:city":"Asendorf",
    "sg:phone":"+49 4253/321",
    "sg:postcode":"27330",
    "sg:province":"Niedersachsen",
    "wof:name":"J. H\u00f6per",
    "wof:placetype":"venue"
},
  "geometry": {"coordinates":[8.9891281128,52.7536773682],"type":"Point"}
}