{
  "type": "Feature",
  "properties": {
    "iso:country":"DE",
    "sg:address":"Am Sengelskamp 6",
    "sg:city":"Linnich",
    "sg:phone":"+49 2462/3261",
    "sg:postcode":"52441",
    "sg:province":"Nordrhein-Westfalen",
    "wof:name":"Bau & Hobby Baumarkt Gmbh & Co. Kg",
    "wof:placetype":"venue"
},
  "geometry": {"coordinates":[6.316278,50.965977],"type":"Point"}
}