{
  "type": "Feature",
  "properties": {
    "iso:country":"DE",
    "sg:address":"Fleetrade 65 a",
    "sg:city":"Bremen",
    "sg:phone":"+49 421/441636",
    "sg:postcode":"28207",
    "sg:province":"Bremen",
    "wof:name":"Helmut Schmidt Elektroinstallation",
    "wof:placetype":"venue"
},
  "geometry": {"coordinates":[8.864512,53.064465],"type":"Point"}
}