{
  "type": "Feature",
  "properties": {
    "iso:country":"DE",
    "sg:address":"Rennweg 27",
    "sg:city":"Erding",
    "sg:phone":"+49 8122/97970",
    "sg:postcode":"85435",
    "sg:province":"Bayern",
    "wof:name":"Rainer Holme",
    "wof:placetype":"venue"
},
  "geometry": {"coordinates":[11.8946218491,48.3118515015],"type":"Point"}
}