{
  "type": "Feature",
  "properties": {
    "iso:country":"DE",
    "sg:address":"Steuppergstr 49",
    "sg:city":"Cleebronn",
    "sg:phone":"+49 7135/960458",
    "sg:postcode":"74389",
    "sg:province":"Baden-W\u00fcrttemberg",
    "wof:name":"Flammer Gmbh",
    "wof:placetype":"venue"
},
  "geometry": {"coordinates":[9.03092,49.042393],"type":"Point"}
}