{
  "type": "Feature",
  "properties": {
    "iso:country":"DE",
    "sg:address":"Dillinger Str. 12",
    "sg:city":"Wertingen",
    "sg:phone":"+49 8272/997010",
    "sg:postcode":"86637",
    "sg:province":"Bayern",
    "wof:name":"Theo Karmann Ingenieur",
    "wof:placetype":"venue"
},
  "geometry": {"coordinates":[10.6783037186,48.5604362488],"type":"Point"}
}