{
  "type": "Feature",
  "properties": {
    "iso:country":"DE",
    "sg:address":"\u00d6lbachstr. 48-52",
    "sg:city":"Vreden",
    "sg:phone":"+49 2564/3930",
    "sg:postcode":"48691",
    "sg:province":"Nordrhein-Westfalen",
    "wof:name":"Terbrack Kunststoff Gmbh & Co. Kg",
    "wof:placetype":"venue"
},
  "geometry": {"coordinates":[6.8238039017,52.0425262451],"type":"Point"}
}