{
  "type": "Feature",
  "properties": {
    "iso:country":"DE",
    "sg:address":"Harburger Str. 13",
    "sg:city":"Schneverdingen",
    "sg:phone":"+49 5193/98090",
    "sg:postcode":"29640",
    "sg:province":"Niedersachsen",
    "wof:name":"Helmuth Meyer Immobilien Gmbh",
    "wof:placetype":"venue"
},
  "geometry": {"coordinates":[9.793615,53.120045],"type":"Point"}
}