{
  "type": "Feature",
  "properties": {
    "iso:country":"DE",
    "sg:address":"Chamer Str. 10",
    "sg:city":"Runding",
    "sg:phone":"+49 9971/7342",
    "sg:postcode":"93486",
    "sg:province":"Bayern",
    "wof:name":"A. Michl",
    "wof:placetype":"venue"
},
  "geometry": {"coordinates":[12.7135896683,49.2212791443],"type":"Point"}
}