{
  "type": "Feature",
  "properties": {
    "iso:country":"DE",
    "sg:address":"Am Park 2",
    "sg:city":"Rodersdorf",
    "sg:postcode":"38828",
    "sg:province":"Sachsen-Anhalt",
    "wof:name":"Bistro Bode Inh. Th\u00e4mlitz Und B\u00fcchner Gbr",
    "wof:placetype":"venue"
},
  "geometry": {"coordinates":[11.2177352905,51.8762702942],"type":"Point"}
}