{
  "type": "Feature",
  "properties": {
    "iso:country":"DE",
    "sg:address":"H\u00f6lzlestr. 9",
    "sg:city":"Radolfzell",
    "sg:phone":"+49 7732/972860",
    "sg:postcode":"78315",
    "sg:province":"Baden-W\u00fcrttemberg",
    "wof:name":"Bernhard Lindenthal",
    "wof:placetype":"venue"
},
  "geometry": {"coordinates":[8.9340953827,47.7554855347],"type":"Point"}
}