{
  "type": "Feature",
  "properties": {
    "iso:country":"DE",
    "sg:address":"Zinnaer Str 18",
    "sg:city":"Nuthe-Urstromtal",
    "sg:phone":"+49 33734/50216",
    "sg:postcode":"14947",
    "sg:province":"Brandenburg",
    "wof:name":"Heinz Konsolke Schalt-, Steuer- Und Regelger\u00e4te",
    "wof:placetype":"venue"
},
  "geometry": {"coordinates":[13.025555,52.089478],"type":"Point"}
}