{
  "type": "Feature",
  "properties": {
    "iso:country":"DE",
    "sg:address":"Friedrichstr. 243",
    "sg:city":"Velbert",
    "sg:phone":"+49 2051/2040",
    "sg:postcode":"42551",
    "sg:province":"Nordrhein-Westfalen",
    "wof:name":"C. Ed. Schulte Gmbh",
    "wof:placetype":"venue"
},
  "geometry": {"coordinates":[7.0516881943,51.3350334167],"type":"Point"}
}