{
  "type": "Feature",
  "properties": {
    "iso:country":"DE",
    "sg:address":"Daimlerstr. 8",
    "sg:city":"Rodgau",
    "sg:phone":"+49 6106/14940",
    "sg:postcode":"63110",
    "sg:province":"Hessen",
    "wof:name":"Edgar Lang",
    "wof:placetype":"venue"
},
  "geometry": {"coordinates":[8.892077,50.05492],"type":"Point"}
}