{
  "type": "Feature",
  "properties": {
    "iso:country":"DE",
    "sg:address":"Waldwiesenstr 8",
    "sg:city":"Kreuztal",
    "sg:phone":"+49 2732/8870",
    "sg:postcode":"57223",
    "sg:province":"Nordrhein-Westfalen",
    "wof:name":"Irle Biegetechnik Gmbh",
    "wof:placetype":"venue"
},
  "geometry": {"coordinates":[7.97832,51.001572],"type":"Point"}
}