{
  "type": "Feature",
  "properties": {
    "iso:country":"DE",
    "sg:address":"Bahnhofstr. 10",
    "sg:city":"Neustadt",
    "sg:phone":"+49 9445/7667",
    "sg:postcode":"93333",
    "sg:province":"Bayern",
    "wof:name":"Hans Pirthauer",
    "wof:placetype":"venue"
},
  "geometry": {"coordinates":[8.210683,47.911247],"type":"Point"}
}