{
  "type": "Feature",
  "properties": {
    "iso:country":"DE",
    "sg:address":"Wiesenweg 1a",
    "sg:city":"Bad W\u00f6rishofen",
    "sg:phone":"+49 8247/2107",
    "sg:postcode":"86825",
    "sg:province":"Bayern",
    "wof:name":"Aral Ag",
    "wof:placetype":"venue"
},
  "geometry": {"coordinates":[10.5860538483,47.9992599487],"type":"Point"}
}