{
  "type": "Feature",
  "properties": {
    "iso:country":"DE",
    "sg:address":"Vellbr\u00fcckstr. 19",
    "sg:city":"Frechen",
    "sg:phone":"+49 2234/54628",
    "sg:postcode":"50226",
    "sg:province":"Nordrhein-Westfalen",
    "wof:name":"Hepla Heizungsbau Gmbh",
    "wof:placetype":"venue"
},
  "geometry": {"coordinates":[6.8158760071,50.9040145874],"type":"Point"}
}