{
  "type": "Feature",
  "properties": {
    "iso:country":"DE",
    "sg:address":"Lutherstr. 14",
    "sg:city":"Steinheim",
    "sg:phone":"+49 7148/922143",
    "sg:postcode":"71711",
    "sg:province":"Baden-W\u00fcrttemberg",
    "wof:name":"Maritta Lander Steuerberater",
    "wof:placetype":"venue"
},
  "geometry": {"coordinates":[9.2590465546,48.9618682861],"type":"Point"}
}