{
  "type": "Feature",
  "properties": {
    "iso:country":"DE",
    "sg:address":"Waldeck 10",
    "sg:city":"Dinkelsb\u00fchl",
    "sg:phone":"+49 9857/501",
    "sg:postcode":"91550",
    "sg:province":"Bayern",
    "wof:name":"W. Strauss Haus B\u00f6kler",
    "wof:placetype":"venue"
},
  "geometry": {"coordinates":[10.2492437363,49.1066703796],"type":"Point"}
}