{
  "type": "Feature",
  "properties": {
    "iso:country":"DE",
    "sg:address":"Lutherstr. 47",
    "sg:city":"Jena",
    "sg:phone":"+49 3641/42820",
    "sg:postcode":"07743",
    "sg:province":"Th\u00fcringen",
    "wof:name":"J. Apel Moderne Bausysteme",
    "wof:placetype":"venue"
},
  "geometry": {"coordinates":[11.577665329,50.9277191162],"type":"Point"}
}