{
  "type": "Feature",
  "properties": {
    "iso:country":"DE",
    "sg:address":"Kr\u00e4mersdorf 8",
    "sg:city":"Hattingen",
    "sg:phone":"+49 2324/25940",
    "sg:postcode":"45525",
    "sg:province":"Nordrhein-Westfalen",
    "wof:name":"Rolf Kaesler",
    "wof:placetype":"venue"
},
  "geometry": {"coordinates":[7.182702,51.398499],"type":"Point"}
}