{
  "type": "Feature",
  "properties": {
    "iso:country":"DE",
    "sg:address":"Prager Str 200::",
    "sg:city":"Leipzig",
    "sg:phone":"+49 341/8600",
    "sg:postcode":"04103",
    "sg:province":"Sachsen",
    "wof:name":"Landeszentralbank In Den Freistaaten Sachsen Und Th\u00fcringen",
    "wof:placetype":"venue"
},
  "geometry": {"coordinates":[12.394399,51.332378],"type":"Point"}
}