{
  "type": "Feature",
  "properties": {
    "iso:country":"DE",
    "sg:address":"Beethovenstr. 77",
    "sg:city":"L\u00fcbeck",
    "sg:phone":"+49 451/4050035",
    "sg:postcode":"23556",
    "sg:province":"Schleswig-Holstein",
    "wof:name":"Karlo Taxen Gmbh",
    "wof:placetype":"venue"
},
  "geometry": {"coordinates":[10.6529951096,53.8679504395],"type":"Point"}
}