{
  "type": "Feature",
  "properties": {
    "iso:country":"DE",
    "sg:address":"Jakob-D\u00f6rr-Str. 65",
    "sg:city":"Karlsruhe",
    "sg:phone":"+49 721/561652",
    "sg:postcode":"76187",
    "sg:province":"Baden-W\u00fcrttemberg",
    "wof:name":"Norbert M. Wolf Architekt",
    "wof:placetype":"venue"
},
  "geometry": {"coordinates":[8.336767,49.04245],"type":"Point"}
}