{
  "type": "Feature",
  "properties": {
    "iso:country":"DE",
    "sg:address":"Friedrich-Ebert-Str. 84",
    "sg:city":"Velbert",
    "sg:phone":"+49 2051/254731",
    "sg:postcode":"42549",
    "sg:province":"Nordrhein-Westfalen",
    "wof:name":"Th. Vinnemeier-wehrenfennig Heilpraktikerin",
    "wof:placetype":"venue"
},
  "geometry": {"coordinates":[7.0459909439,51.3369216919],"type":"Point"}
}