{
  "type": "Feature",
  "properties": {
    "iso:country":"DE",
    "sg:address":"Gerlicherheide 20",
    "sg:city":"Dorsten",
    "sg:phone":"+49 2369/4276",
    "sg:postcode":"46286",
    "sg:province":"Nordrhein-Westfalen",
    "wof:name":"Bernhard Seeber",
    "wof:placetype":"venue"
},
  "geometry": {"coordinates":[6.997329,51.720226],"type":"Point"}
}