{
  "type": "Feature",
  "properties": {
    "iso:country":"DE",
    "sg:address":"Schubertstr. 51",
    "sg:city":"Ingelheim",
    "sg:phone":"+49 6132/87661",
    "sg:postcode":"55218",
    "sg:province":"Rheinland-Pfalz",
    "wof:name":"Wolfgang Keller Steuerberater",
    "wof:placetype":"venue"
},
  "geometry": {"coordinates":[8.0300378799,49.9926834106],"type":"Point"}
}