{
  "type": "Feature",
  "properties": {
    "iso:country":"DE",
    "sg:address":"Hinterm Backofen 4",
    "sg:city":"Bendorf",
    "sg:phone":"+49 2622/3560",
    "sg:postcode":"56170",
    "sg:province":"Rheinland-Pfalz",
    "wof:name":"Hans Klotz",
    "wof:placetype":"venue"
},
  "geometry": {"coordinates":[7.579084,50.422382],"type":"Point"}
}