{
  "type": "Feature",
  "properties": {
    "iso:country":"DE",
    "sg:address":"Dortmunder Str. 200",
    "sg:city":"Castrop-Rauxel",
    "sg:phone":"+49 2305/96770",
    "sg:postcode":"44577",
    "sg:province":"Nordrhein-Westfalen",
    "wof:name":"Wischnewski Und A\u00dfheuer Rechtsanw\u00e4lte",
    "wof:placetype":"venue"
},
  "geometry": {"coordinates":[7.3359470367,51.5401344299],"type":"Point"}
}