{
  "type": "Feature",
  "properties": {
    "iso:country":"DE",
    "sg:address":"Herderstr. 2",
    "sg:city":"Kleinblittersdorf",
    "sg:phone":"+49 6805/6010020",
    "sg:postcode":"66271",
    "sg:province":"Saarland",
    "wof:name":"1. Kimia Geb\u00e4udereinigung",
    "wof:placetype":"venue"
},
  "geometry": {"coordinates":[7.063649,49.116489],"type":"Point"}
}