{
  "type": "Feature",
  "properties": {
    "iso:country":"DE",
    "sg:address":"Marktstr. 2",
    "sg:city":"Obersulm",
    "sg:phone":"+49 7134/18325",
    "sg:postcode":"74182",
    "sg:province":"Baden-W\u00fcrttemberg",
    "wof:name":"Rolf Saam Massagepraxis",
    "wof:placetype":"venue"
},
  "geometry": {"coordinates":[9.356273,49.136501],"type":"Point"}
}