{
  "type": "Feature",
  "properties": {
    "iso:country":"DE",
    "sg:address":"Hofstr. 13",
    "sg:city":"Solingen",
    "sg:phone":"+49 212/330351",
    "sg:postcode":"42699",
    "sg:province":"Nordrhein-Westfalen",
    "wof:name":"F & M Glas Rolf R\u00fcdiger Staat Kg",
    "wof:placetype":"venue"
},
  "geometry": {"coordinates":[7.0301542282,51.1676712036],"type":"Point"}
}