{
  "type": "Feature",
  "properties": {
    "iso:country":"DE",
    "sg:address":"Mozartstr. 1",
    "sg:city":"Burbach",
    "sg:phone":"+49 2736/6310",
    "sg:postcode":"57299",
    "sg:province":"Nordrhein-Westfalen",
    "wof:name":"Berthold Ochs",
    "wof:placetype":"venue"
},
  "geometry": {"coordinates":[8.088489,50.7407],"type":"Point"}
}