{
  "type": "Feature",
  "properties": {
    "iso:country":"DE",
    "sg:address":"Friedrich-Engels-Str. 1",
    "sg:city":"Potsdam",
    "sg:phone":"+49 331/296617",
    "sg:postcode":"14473",
    "sg:province":"Brandenburg",
    "wof:name":"Robert Dortschy",
    "wof:placetype":"venue"
},
  "geometry": {"coordinates":[13.066094,52.390327],"type":"Point"}
}