{
  "type": "Feature",
  "properties": {
    "iso:country":"DE",
    "sg:address":"Bruchstr. 22",
    "sg:city":"Erwitte",
    "sg:phone":"+49 2943/7414",
    "sg:postcode":"59597",
    "sg:province":"Nordrhein-Westfalen",
    "wof:name":"I. Salinus",
    "wof:placetype":"venue"
},
  "geometry": {"coordinates":[8.366713,51.632542],"type":"Point"}
}