{
  "type": "Feature",
  "properties": {
    "iso:country":"DE",
    "sg:address":"Schweier Str. 6",
    "sg:city":"Stadland",
    "sg:phone":"+49 4732/387",
    "sg:postcode":"26935",
    "sg:province":"Niedersachsen",
    "wof:name":"Heinz-gerd Abbenseth",
    "wof:placetype":"venue"
},
  "geometry": {"coordinates":[8.445693,53.401287],"type":"Point"}
}