{
  "type": "Feature",
  "properties": {
    "iso:country":"DE",
    "sg:address":"Leinenweberstr. 10",
    "sg:city":"Freiburg",
    "sg:phone":"+49 761/1526690",
    "sg:postcode":"79108",
    "sg:province":"Baden-W\u00fcrttemberg",
    "wof:name":"Eurital - Food E. K.",
    "wof:placetype":"venue"
},
  "geometry": {"coordinates":[7.8134031296,48.0379257202],"type":"Point"}
}