{
  "type": "Feature",
  "properties": {
    "iso:country":"DE",
    "sg:address":"Tegernseer Str. 1",
    "sg:city":"Holzkirchen",
    "sg:phone":"+49 8024/489990",
    "sg:postcode":"83607",
    "sg:province":"Bayern",
    "wof:name":"Widnmann Gmbh",
    "wof:placetype":"venue"
},
  "geometry": {"coordinates":[11.7019987106,47.8766021729],"type":"Point"}
}