{
  "type": "Feature",
  "properties": {
    "iso:country":"DE",
    "sg:address":"Bahnhofstr. 2",
    "sg:city":"Bad Ems",
    "sg:phone":"+49 2603/3960",
    "sg:postcode":"56130",
    "sg:province":"Rheinland-Pfalz",
    "wof:name":"Apotheke Am Bahnhof",
    "wof:placetype":"venue"
},
  "geometry": {"coordinates":[7.728656,50.328316],"type":"Point"}
}