{
  "type": "Feature",
  "properties": {
    "iso:country":"DE",
    "sg:address":"Langstra\u00dfe 22",
    "sg:city":"Limburg",
    "sg:phone":"+49 6433/2689",
    "sg:postcode":"65554",
    "sg:province":"Hessen",
    "wof:name":"Kvn-motor Deutschland 45km/h Quad",
    "wof:placetype":"venue"
},
  "geometry": {"coordinates":[8.087968,50.43573],"type":"Point"}
}