{
  "type": "Feature",
  "properties": {
    "iso:country":"DE",
    "sg:address":"Fichtelgebirgsstr. 17",
    "sg:city":"Hanau",
    "sg:phone":"+49 6181/78483",
    "sg:postcode":"63454",
    "sg:province":"Hessen",
    "wof:name":"Esh-gmbh Licht- Und Fotopausen",
    "wof:placetype":"venue"
},
  "geometry": {"coordinates":[8.8795690536,50.1802253723],"type":"Point"}
}