{
  "type": "Feature",
  "properties": {
    "iso:country":"DE",
    "sg:address":"Im Birkenfeld 4",
    "sg:city":"Kelkheim",
    "sg:phone":"+49 6198/8018",
    "sg:postcode":"65779",
    "sg:province":"Hessen",
    "wof:name":"Hansa Trading Und Consulting Gmbh",
    "wof:placetype":"venue"
},
  "geometry": {"coordinates":[8.3945598602,50.166759491],"type":"Point"}
}