{
  "type": "Feature",
  "properties": {
    "iso:country":"DE",
    "sg:address":"Am Br\u00fcnnlein 6",
    "sg:city":"Kulmbach",
    "sg:phone":"+49 9221/4668",
    "sg:postcode":"95326",
    "sg:province":"Bayern",
    "wof:name":"Gottfried Grampp",
    "wof:placetype":"venue"
},
  "geometry": {"coordinates":[11.440495,50.122578],"type":"Point"}
}