{
  "type": "Feature",
  "properties": {
    "iso:country":"DE",
    "sg:address":"Mauerstr. 12",
    "sg:city":"Halle",
    "sg:postcode":"06110",
    "sg:province":"Sachsen-Anhalt",
    "wof:name":"Katholisches Pfarramt Propstei St. Elisabeth",
    "wof:placetype":"venue"
},
  "geometry": {"coordinates":[11.9671287537,51.4783935547],"type":"Point"}
}