{
  "type": "Feature",
  "properties": {
    "iso:country":"DE",
    "sg:address":"Gro\u00dfe Barlinge 25",
    "sg:city":"Hannover",
    "sg:phone":"+49 511/5443374",
    "sg:postcode":"30171",
    "sg:province":"Niedersachsen",
    "wof:name":"Hakon Gmbh",
    "wof:placetype":"venue"
},
  "geometry": {"coordinates":[9.752094,52.36742],"type":"Point"}
}