{
  "type": "Feature",
  "properties": {
    "iso:country":"DE",
    "sg:address":"T\u00e4leswiesenstr. 4",
    "sg:city":"Reutlingen",
    "sg:phone":"+49 4971/2191610",
    "sg:postcode":"72770",
    "sg:province":"Baden-W\u00fcrttemberg",
    "wof:name":"Renz Entsorgung Gmbh & Co Kg",
    "wof:placetype":"venue"
},
  "geometry": {"coordinates":[9.147102,48.493629],"type":"Point"}
}