{
  "type": "Feature",
  "properties": {
    "iso:country":"DE",
    "sg:address":"Rathausstr. 18",
    "sg:city":"Duisburg",
    "sg:phone":"+49 203/994130",
    "sg:postcode":"47166",
    "sg:province":"Nordrhein-Westfalen",
    "wof:name":"Gerd Meier Rechtsanwalt Und Notar",
    "wof:placetype":"venue"
},
  "geometry": {"coordinates":[6.7726249695,51.4928436279],"type":"Point"}
}