{
  "type": "Feature",
  "properties": {
    "iso:country":"DE",
    "sg:address":"Holpuster Weg 2",
    "sg:city":"L\u00fcrschau",
    "sg:phone":"+49 4621/4590",
    "sg:postcode":"24850",
    "sg:province":"Schleswig-Holstein",
    "wof:name":"Bernhard John",
    "wof:placetype":"venue"
},
  "geometry": {"coordinates":[9.4965906143,54.5380821228],"type":"Point"}
}