{
  "type": "Feature",
  "properties": {
    "iso:country":"DE",
    "sg:address":"Sch\u00e4destr 7",
    "sg:city":"Zeitz",
    "sg:phone":"+49 3441/225670",
    "sg:postcode":"06712",
    "sg:province":"Sachsen-Anhalt",
    "wof:name":"Gfm Gesellschaft F\u00fcr Mikroelektronik Mbh & Co Kg",
    "wof:placetype":"venue"
},
  "geometry": {"coordinates":[12.13011,51.057259],"type":"Point"}
}