{
  "type": "Feature",
  "properties": {
    "iso:country":"DE",
    "sg:address":"Marschnerstr 57 a",
    "sg:city":"M\u00fcnchen",
    "sg:phone":"+49 89/8202744",
    "sg:postcode":"81245",
    "sg:province":"Bayern",
    "wof:name":"Net Neue Energie-technik Gmbh",
    "wof:placetype":"venue"
},
  "geometry": {"coordinates":[11.4486322403,48.1550102234],"type":"Point"}
}