{
  "type": "Feature",
  "properties": {
    "iso:country":"DE",
    "sg:address":"Karl-Marx-Str. 55",
    "sg:city":"Wiesbaden",
    "sg:postcode":"65199",
    "sg:province":"Hessen",
    "wof:name":"Telesat Direkt",
    "wof:placetype":"venue"
},
  "geometry": {"coordinates":[8.186753273,50.0700073242],"type":"Point"}
}