{
  "type": "Feature",
  "properties": {
    "iso:country":"DE",
    "sg:address":"Heerstr. 15",
    "sg:city":"Heimsheim",
    "sg:phone":"+49 7033/33341",
    "sg:postcode":"71296",
    "sg:province":"Baden-W\u00fcrttemberg",
    "wof:name":"Reinhold R\u00fchle",
    "wof:placetype":"venue"
},
  "geometry": {"coordinates":[8.865831,48.807072],"type":"Point"}
}