{
  "type": "Feature",
  "properties": {
    "iso:country":"DE",
    "sg:address":"Klausenerstr. 10 a",
    "sg:city":"Magdeburg",
    "sg:phone":"+49 391/6231623",
    "sg:postcode":"39112",
    "sg:province":"Sachsen-Anhalt",
    "wof:name":"Norbert Krull Rechtsanwalt",
    "wof:placetype":"venue"
},
  "geometry": {"coordinates":[11.6053657532,52.1132965088],"type":"Point"}
}