{
  "type": "Feature",
  "properties": {
    "iso:country":"DE",
    "sg:address":"Karlstr. 12",
    "sg:city":"Gro\u00df-Umstadt",
    "sg:phone":"+49 6078/73989",
    "sg:postcode":"64823",
    "sg:province":"Hessen",
    "wof:name":"G. Bauer Architekt",
    "wof:placetype":"venue"
},
  "geometry": {"coordinates":[8.924144,49.866859],"type":"Point"}
}