{
  "type": "Feature",
  "properties": {
    "iso:country":"DE",
    "sg:address":"Kaiser-Wilhelm-Strasse 100",
    "sg:city":"Duisburg",
    "sg:postcode":"47166",
    "sg:province":"Nordrhein-Westfalen",
    "wof:name":"Thyssen Schienen Technik Gmbh - Alles Rund Um Die Schiene",
    "wof:placetype":"venue"
},
  "geometry": {"coordinates":[6.7420549393,51.4914703369],"type":"Point"}
}