{
  "type": "Feature",
  "properties": {
    "iso:country":"DE",
    "sg:address":"Th\u00fcler Str. 12",
    "sg:city":"Salzkotten",
    "sg:phone":"+49 5258/21792",
    "sg:postcode":"33154",
    "sg:province":"Nordrhein-Westfalen",
    "wof:name":"Saltenbrock Agrartechnik Melle Gmbh",
    "wof:placetype":"venue"
},
  "geometry": {"coordinates":[8.602385,51.684956],"type":"Point"}
}