{
  "type": "Feature",
  "properties": {
    "iso:country":"DE",
    "sg:address":"Letter Str. 37",
    "sg:city":"Coesfeld",
    "sg:phone":"+49 2541/6433",
    "sg:postcode":"48653",
    "sg:province":"Nordrhein-Westfalen",
    "wof:name":"Fit Und Fun",
    "wof:placetype":"venue"
},
  "geometry": {"coordinates":[7.167277813,51.9416542053],"type":"Point"}
}