{
  "type": "Feature",
  "properties": {
    "iso:country":"DE",
    "sg:address":"Wachtstr. 12",
    "sg:city":"Irndorf",
    "sg:phone":"+49 7466/91119",
    "sg:postcode":"78597",
    "sg:province":"Baden-W\u00fcrttemberg",
    "wof:name":"Reuchlin Geologisches B\u00fcro",
    "wof:placetype":"venue"
},
  "geometry": {"coordinates":[8.977721,48.061424],"type":"Point"}
}