{
  "type": "Feature",
  "properties": {
    "iso:country":"DE",
    "sg:address":"Rilkestr. 13",
    "sg:city":"Bobenheim-Roxheim",
    "sg:phone":"+49 6239/7135",
    "sg:postcode":"67240",
    "sg:province":"Rheinland-Pfalz",
    "wof:name":"Anton Lisec Elektroinstallation",
    "wof:placetype":"venue"
},
  "geometry": {"coordinates":[8.357441,49.571701],"type":"Point"}
}