{
  "type": "Feature",
  "properties": {
    "iso:country":"DE",
    "sg:address":"L\u00f6wenwall 6",
    "sg:city":"Braunschweig",
    "sg:phone":"+49 531/40288",
    "sg:postcode":"38100",
    "sg:province":"Niedersachsen",
    "wof:name":"W.-u. Schink Rechtsanwalt",
    "wof:placetype":"venue"
},
  "geometry": {"coordinates":[10.5291128159,52.2588920593],"type":"Point"}
}