{
  "type": "Feature",
  "properties": {
    "iso:country":"DE",
    "sg:address":"K\u00f6nigstr. 9",
    "sg:city":"Aurachtal",
    "sg:phone":"+49 9132/78260",
    "sg:postcode":"91086",
    "sg:province":"Bayern",
    "wof:name":"Kompostier Betriebs Gmbh Erlangen-h\u00f6chstadt",
    "wof:placetype":"venue"
},
  "geometry": {"coordinates":[10.824175,49.575436],"type":"Point"}
}