{
  "type": "Feature",
  "properties": {
    "iso:country":"DE",
    "sg:address":"Freisinger Str. 20",
    "sg:city":"Oberding",
    "sg:phone":"+49 8122/15746",
    "sg:postcode":"85445",
    "sg:province":"Bayern",
    "wof:name":"Alfred Krause",
    "wof:placetype":"venue"
},
  "geometry": {"coordinates":[11.8452997208,48.337097168],"type":"Point"}
}