{
  "type": "Feature",
  "properties": {
    "iso:country":"DE",
    "sg:address":"Breckerfelder Str. 200",
    "sg:city":"Ennepetal",
    "sg:phone":"+49 2333/89328",
    "sg:postcode":"58256",
    "sg:province":"Nordrhein-Westfalen",
    "wof:name":"Bauunternehmung Karl Aug. Maurer Gmbh",
    "wof:placetype":"venue"
},
  "geometry": {"coordinates":[7.428555,51.288479],"type":"Point"}
}