{
  "type": "Feature",
  "properties": {
    "iso:country":"DE",
    "sg:address":"Marktstr. 20",
    "sg:city":"Horb",
    "sg:phone":"+49 7451/2272",
    "sg:postcode":"72160",
    "sg:province":"Baden-W\u00fcrttemberg",
    "wof:name":"Thomma Metzgerei Gmbh",
    "wof:placetype":"venue"
},
  "geometry": {"coordinates":[8.6904783249,48.4450454712],"type":"Point"}
}