{
  "type": "Feature",
  "properties": {
    "iso:country":"DE",
    "sg:address":"Hauptstrasse 47",
    "sg:city":"Lindenberg",
    "sg:phone":"+49 8381/941666",
    "sg:postcode":"88161",
    "sg:province":"Bayern",
    "wof:name":"Ph Creative - 3d Grafik",
    "wof:placetype":"venue"
},
  "geometry": {"coordinates":[8.095057,49.374649],"type":"Point"}
}