{
  "type": "Feature",
  "properties": {
    "iso:country":"DE",
    "sg:address":"Koogstr. 41",
    "sg:city":"Brunsb\u00fcttel",
    "sg:phone":"+49 4852/4021",
    "sg:postcode":"25541",
    "sg:province":"Schleswig-Holstein",
    "wof:name":"H\u00f6rt-h\u00f6rt Fuhlendorf Gmbh & Co. Kg",
    "wof:placetype":"venue"
},
  "geometry": {"coordinates":[9.1363935471,53.8970870972],"type":"Point"}
}