{
  "type": "Feature",
  "properties": {
    "iso:country":"DE",
    "sg:address":"Brandst\u00fccken 20",
    "sg:city":"Hamburg",
    "sg:phone":"+49 40/807220",
    "sg:postcode":"22549",
    "sg:province":"Hamburg",
    "wof:name":"Bode Immobilien Verwaltungs- Gesellschaft Gmbh & Co. Kg",
    "wof:placetype":"venue"
},
  "geometry": {"coordinates":[9.8517417908,53.5802078247],"type":"Point"}
}