{
  "type": "Feature",
  "properties": {
    "iso:country":"DE",
    "sg:address":"Hans-B\u00f6ckler-Str. 62",
    "sg:city":"Langenfeld",
    "sg:phone":"+49 2173/904240",
    "sg:postcode":"40764",
    "sg:province":"Nordrhein-Westfalen",
    "wof:name":"Dotmark Internet Und Business Software Gmbh",
    "wof:placetype":"venue"
},
  "geometry": {"coordinates":[6.9260239601,51.1221504211],"type":"Point"}
}