{
  "type": "Feature",
  "properties": {
    "iso:country":"DE",
    "sg:address":"Jakobstr. 1",
    "sg:city":"Alsdorf",
    "sg:phone":"+49 2404/62146",
    "sg:postcode":"52477",
    "sg:province":"Nordrhein-Westfalen",
    "wof:name":"Karl Hommelsheim",
    "wof:placetype":"venue"
},
  "geometry": {"coordinates":[6.2155189514,50.8557624817],"type":"Point"}
}