{
  "type": "Feature",
  "properties": {
    "iso:country":"DE",
    "sg:address":"Buchenweg 4",
    "sg:city":"Euscheid",
    "sg:phone":"+49 6556/7442",
    "sg:postcode":"54597",
    "sg:province":"Rheinland-Pfalz",
    "wof:name":"Rainer Gompelmann",
    "wof:placetype":"venue"
},
  "geometry": {"coordinates":[6.297969,50.131172],"type":"Point"}
}