{
  "type": "Feature",
  "properties": {
    "iso:country":"DE",
    "sg:address":"Ober-Saulheimer-Str. 16",
    "sg:city":"Saulheim",
    "sg:phone":"+49 6732/3832",
    "sg:postcode":"55291",
    "sg:province":"Rheinland-Pfalz",
    "wof:name":"Werner Boller",
    "wof:placetype":"venue"
},
  "geometry": {"coordinates":[8.1499795914,49.8733444214],"type":"Point"}
}