{
  "type": "Feature",
  "properties": {
    "iso:country":"DE",
    "sg:address":"Schlo\u00dfstr. 43",
    "sg:city":"Ki\u00dflegg",
    "sg:phone":"+49 7563/8483",
    "sg:postcode":"88353",
    "sg:province":"Baden-W\u00fcrttemberg",
    "wof:name":"Restaurant Kanton",
    "wof:placetype":"venue"
},
  "geometry": {"coordinates":[9.8803606033,47.7914772034],"type":"Point"}
}