{
  "type": "Feature",
  "properties": {
    "iso:country":"DE",
    "sg:address":"Stefan-Meier-Str. 105",
    "sg:city":"Freiburg",
    "sg:phone":"+49 761/275124",
    "sg:postcode":"79104",
    "sg:province":"Baden-W\u00fcrttemberg",
    "wof:name":"Friedrich Hammann",
    "wof:placetype":"venue"
},
  "geometry": {"coordinates":[7.8484611511,48.0045585632],"type":"Point"}
}