{
  "type": "Feature",
  "properties": {
    "iso:country":"DE",
    "sg:address":"An der Unstrut 33",
    "sg:city":"Dingelst\u00e4dt",
    "sg:phone":"+49 36075/62423",
    "sg:postcode":"37351",
    "sg:province":"Th\u00fcringen",
    "wof:name":"Rolf Meinhardt",
    "wof:placetype":"venue"
},
  "geometry": {"coordinates":[10.3198986053,51.3140792847],"type":"Point"}
}