{
  "type": "Feature",
  "properties": {
    "iso:country":"DE",
    "sg:address":"Bachstr. 27 a",
    "sg:city":"Dransfeld",
    "sg:phone":"+49 5502/94200",
    "sg:postcode":"37127",
    "sg:province":"Niedersachsen",
    "wof:name":"Sira Sport- Fitness- Und Gesundheitsanlagen Gmbh",
    "wof:placetype":"venue"
},
  "geometry": {"coordinates":[9.7588968277,51.5017852783],"type":"Point"}
}