{
  "type": "Feature",
  "properties": {
    "iso:country":"DE",
    "sg:address":"Quenzweg 28",
    "sg:city":"Brandenburg",
    "sg:phone":"+49 3381/701785",
    "sg:postcode":"14772",
    "sg:province":"Brandenburg",
    "wof:name":"Ute Paaschen",
    "wof:placetype":"venue"
},
  "geometry": {"coordinates":[12.4962377548,52.4254875183],"type":"Point"}
}