{
  "type": "Feature",
  "properties": {
    "iso:country":"DE",
    "sg:address":"\u00c4rmelstr. 6",
    "sg:city":"Gerstetten",
    "sg:phone":"+49 7323/5130",
    "sg:postcode":"89547",
    "sg:province":"Baden-W\u00fcrttemberg",
    "wof:name":"Gerhard Pfefferle",
    "wof:placetype":"venue"
},
  "geometry": {"coordinates":[9.961776,48.639713],"type":"Point"}
}