{
  "type": "Feature",
  "properties": {
    "iso:country":"DE",
    "sg:address":"Limburger Str. 25",
    "sg:city":"H\u00fcnfelden",
    "sg:phone":"+49 6438/2604",
    "sg:postcode":"65597",
    "sg:province":"Hessen",
    "wof:name":"Raumausstatter M\u00fcller Ohg",
    "wof:placetype":"venue"
},
  "geometry": {"coordinates":[8.155894,50.309109],"type":"Point"}
}