{
  "type": "Feature",
  "properties": {
    "iso:country":"DE",
    "sg:address":"Hindenburgstr. 15",
    "sg:city":"H\u00f6fen",
    "sg:phone":"+49 4970/815333",
    "sg:postcode":"71364",
    "sg:province":"Baden-W\u00fcrttemberg",
    "wof:name":"Volksbank Pforzheim Eg",
    "wof:placetype":"venue"
},
  "geometry": {"coordinates":[9.395121,48.876076],"type":"Point"}
}