{
  "type": "Feature",
  "properties": {
    "iso:country":"DE",
    "sg:address":"Fersenbruch 22",
    "sg:city":"Gelsenkirchen",
    "sg:phone":"+49 209/495896",
    "sg:postcode":"45883",
    "sg:province":"Nordrhein-Westfalen",
    "wof:name":"Stadtb\u00e4ckerei Friedrich Gatenbr\u00f6cker Gmbh",
    "wof:placetype":"venue"
},
  "geometry": {"coordinates":[7.059346,51.521347],"type":"Point"}
}