{
  "type": "Feature",
  "properties": {
    "iso:country":"DE",
    "sg:address":"Max-Reger-Str. 11",
    "sg:city":"W\u00fcrzburg",
    "sg:phone":"+49 931/81524",
    "sg:postcode":"97074",
    "sg:province":"Bayern",
    "wof:name":"Ines Von Gutenberg Heilpraktikerin",
    "wof:placetype":"venue"
},
  "geometry": {"coordinates":[9.9579792023,49.7907676697],"type":"Point"}
}