{
  "type": "Feature",
  "properties": {
    "iso:country":"DE",
    "sg:address":"Berliner Str.10",
    "sg:city":"Meschede",
    "sg:phone":"+49 2903/851018",
    "sg:postcode":"59872",
    "sg:province":"Nordrhein-Westfalen",
    "wof:name":"Digacom Internet Design",
    "wof:placetype":"venue"
},
  "geometry": {"coordinates":[8.175282,51.370693],"type":"Point"}
}