{
  "type": "Feature",
  "properties": {
    "iso:country":"DE",
    "sg:address":"Forstweg 4",
    "sg:city":"Kirchseeon",
    "sg:phone":"+49 8091/3136",
    "sg:postcode":"85614",
    "sg:province":"Bayern",
    "wof:name":"Fensterzentrum Gmbh K\u00fcgel & Wenig",
    "wof:placetype":"venue"
},
  "geometry": {"coordinates":[11.865989,48.083138],"type":"Point"}
}