{
  "type": "Feature",
  "properties": {
    "iso:country":"DE",
    "sg:address":"Wagnerstr. 2",
    "sg:city":"Trossingen",
    "sg:phone":"+49 7425/8379",
    "sg:postcode":"78647",
    "sg:province":"Baden-W\u00fcrttemberg",
    "wof:name":"Gerhard Neipp",
    "wof:placetype":"venue"
},
  "geometry": {"coordinates":[8.6351299286,48.0781478882],"type":"Point"}
}