{
  "type": "Feature",
  "properties": {
    "iso:country":"DE",
    "sg:address":"Roettgener Str. 90",
    "sg:city":"Bonn",
    "sg:phone":"+49 228/299168",
    "sg:postcode":"53127",
    "sg:province":"Nordrhein-Westfalen",
    "wof:name":"Afpa - Agentur F\u00fcr Public Affairs",
    "wof:placetype":"venue"
},
  "geometry": {"coordinates":[7.079834,50.699863],"type":"Point"}
}