{
  "type": "Feature",
  "properties": {
    "iso:country":"DE",
    "sg:address":"Hammstr. 10 a",
    "sg:city":"M\u00fcnchen",
    "sg:phone":"+49 89/3146041",
    "sg:postcode":"80935",
    "sg:province":"Bayern",
    "wof:name":"Alois Inhofer",
    "wof:placetype":"venue"
},
  "geometry": {"coordinates":[11.5622825623,48.2055625916],"type":"Point"}
}