{
  "type": "Feature",
  "properties": {
    "iso:country":"DE",
    "sg:address":"Effertsufer 54",
    "sg:city":"Siegen",
    "sg:phone":"+49 271/335011",
    "sg:postcode":"57072",
    "sg:province":"Nordrhein-Westfalen",
    "wof:name":"Funk-taxi Gmbh",
    "wof:placetype":"venue"
},
  "geometry": {"coordinates":[8.0086402893,50.8704071045],"type":"Point"}
}