{
  "type": "Feature",
  "properties": {
    "iso:country":"DE",
    "sg:address":"Bertha-von-Suttner-Str. 8",
    "sg:city":"Gro\u00df-Zimmern",
    "sg:phone":"+49 6071/48693",
    "sg:postcode":"64846",
    "sg:province":"Hessen",
    "wof:name":"Winfried Czarnotta Innenarchitekt",
    "wof:placetype":"venue"
},
  "geometry": {"coordinates":[8.830239,49.875015],"type":"Point"}
}