{
  "type": "Feature",
  "properties": {
    "iso:country":"DE",
    "sg:address":"Trupbacher Str. 22",
    "sg:city":"Siegen",
    "sg:phone":"+49 271/370242",
    "sg:postcode":"57072",
    "sg:province":"Nordrhein-Westfalen",
    "wof:name":"Stephan Wied",
    "wof:placetype":"venue"
},
  "geometry": {"coordinates":[7.9839138985,50.8903503418],"type":"Point"}
}