{
  "type": "Feature",
  "properties": {
    "iso:country":"DE",
    "sg:address":"Altes Dorf 25",
    "sg:city":"Lubmin",
    "sg:phone":"+49 38354/36161",
    "sg:postcode":"17509",
    "sg:province":"Mecklenburg-Vorpommern",
    "wof:name":"Kastner Bau- Und M\u00f6beltischlerei Gbr",
    "wof:placetype":"venue"
},
  "geometry": {"coordinates":[13.6117200851,54.130115509],"type":"Point"}
}