{
  "type": "Feature",
  "properties": {
    "iso:country":"DE",
    "sg:address":"Braikestr. 11",
    "sg:city":"Unterensingen",
    "sg:phone":"+49 7022/63500",
    "sg:postcode":"72669",
    "sg:province":"Baden-W\u00fcrttemberg",
    "wof:name":"K. Walker",
    "wof:placetype":"venue"
},
  "geometry": {"coordinates":[9.3593435287,48.6591644287],"type":"Point"}
}