{
  "type": "Feature",
  "properties": {
    "iso:country":"DE",
    "sg:address":"Samsweger Str. 13d",
    "sg:city":"Wolmirstedt",
    "sg:phone":"+49 39201/29585",
    "sg:postcode":"39326",
    "sg:province":"Sachsen-Anhalt",
    "wof:name":"Erhard Schmidt",
    "wof:placetype":"venue"
},
  "geometry": {"coordinates":[11.615136,52.250835],"type":"Point"}
}