{
  "type": "Feature",
  "properties": {
    "iso:country":"DE",
    "sg:address":"Herrnstr. 53",
    "sg:city":"Offenbach",
    "sg:phone":"+49 69/272240",
    "sg:postcode":"63065",
    "sg:province":"Hessen",
    "wof:name":"Inbas Institut F\u00fcr Berufliche Bildung Arbeitsmarkt- Und",
    "wof:placetype":"venue"
},
  "geometry": {"coordinates":[8.7615756989,50.107383728],"type":"Point"}
}