{
  "type": "Feature",
  "properties": {
    "iso:country":"DE",
    "sg:address":"Laurentiusstr. 17",
    "sg:city":"Trittenheim",
    "sg:phone":"+49 6507/5972",
    "sg:postcode":"54349",
    "sg:province":"Rheinland-Pfalz",
    "wof:name":"Bernhard Eifel Bernhard Eifel",
    "wof:placetype":"venue"
},
  "geometry": {"coordinates":[6.8967270851,49.8229598999],"type":"Point"}
}