{
  "type": "Feature",
  "properties": {
    "iso:country":"DE",
    "sg:address":"Kirchweg 7 d",
    "sg:city":"Bliedersdorf",
    "sg:postcode":"21640",
    "sg:province":"Niedersachsen",
    "wof:name":"Omega Handelsgesellschaft Mbh & Co. Kg",
    "wof:placetype":"venue"
},
  "geometry": {"coordinates":[9.567376,53.481342],"type":"Point"}
}