{
  "type": "Feature",
  "properties": {
    "iso:country":"DE",
    "sg:address":"Schuter 4",
    "sg:city":"Everswinkel",
    "sg:phone":"+49 2582/1243",
    "sg:postcode":"48351",
    "sg:province":"Nordrhein-Westfalen",
    "wof:name":"Burkhard Deckenbrock",
    "wof:placetype":"venue"
},
  "geometry": {"coordinates":[7.8438467979,51.8864517212],"type":"Point"}
}