{
  "type": "Feature",
  "properties": {
    "iso:country":"DE",
    "sg:address":"Esmecke 17",
    "sg:city":"Werdohl",
    "sg:phone":"+49 4975/624564",
    "sg:postcode":"58791",
    "sg:province":"Nordrhein-Westfalen",
    "wof:name":"Kolb Gmbh",
    "wof:placetype":"venue"
},
  "geometry": {"coordinates":[10.043346405,47.6965637207],"type":"Point"}
}