{
  "type": "Feature",
  "properties": {
    "iso:country":"DE",
    "sg:address":"Amerangstr. 2",
    "sg:city":"Bad Reichenhall",
    "sg:phone":"+49 8651/78516",
    "sg:postcode":"83435",
    "sg:province":"Bayern",
    "wof:name":"Signal-versicherungen Alois Pichler",
    "wof:placetype":"venue"
},
  "geometry": {"coordinates":[12.8592329025,47.7194328308],"type":"Point"}
}