{
  "type": "Feature",
  "properties": {
    "iso:country":"DE",
    "sg:address":"Hofwiesenstr. 8",
    "sg:city":"Gummersbach",
    "sg:phone":"+49 2261/22470",
    "sg:postcode":"51645",
    "sg:province":"Nordrhein-Westfalen",
    "wof:name":"C. Wilhelm Peuster",
    "wof:placetype":"venue"
},
  "geometry": {"coordinates":[7.5737009048,51.0066795349],"type":"Point"}
}