{
  "type": "Feature",
  "properties": {
    "iso:country":"DE",
    "sg:address":"Mittenheimer Str. 62",
    "sg:city":"Oberschlei\u00dfheim",
    "sg:phone":"+49 89/3156200",
    "sg:postcode":"85764",
    "sg:province":"Bayern",
    "wof:name":"Organon Gmbh",
    "wof:placetype":"venue"
},
  "geometry": {"coordinates":[11.557431221,48.262046814],"type":"Point"}
}