{
  "type": "Feature",
  "properties": {
    "iso:country":"DE",
    "sg:address":"Innsbrucker Weg 11",
    "sg:city":"Erfurt",
    "sg:phone":"+49 361/664940",
    "sg:postcode":"99085",
    "sg:province":"Th\u00fcringen",
    "wof:name":"Krolik-tele-kommunikation",
    "wof:placetype":"venue"
},
  "geometry": {"coordinates":[11.0481729507,50.993106842],"type":"Point"}
}