{
  "type": "Feature",
  "properties": {
    "iso:country":"DE",
    "sg:address":"Auf dem N\u00f6chel 8",
    "sg:city":"Kelberg",
    "sg:phone":"+49 2692/930060",
    "sg:postcode":"53539",
    "sg:province":"Rheinland-Pfalz",
    "wof:name":"P. Stetten",
    "wof:placetype":"venue"
},
  "geometry": {"coordinates":[6.9209079742,50.2829246521],"type":"Point"}
}