{
  "type": "Feature",
  "properties": {
    "iso:country":"DE",
    "sg:address":"Innstr. 14",
    "sg:city":"Mettenheim",
    "sg:phone":"+49 8631/161568",
    "sg:postcode":"84562",
    "sg:province":"Bayern",
    "wof:name":"K. Schober Immobilienmakler",
    "wof:placetype":"venue"
},
  "geometry": {"coordinates":[12.4680614471,48.2529449463],"type":"Point"}
}