{
  "type": "Feature",
  "properties": {
    "iso:country":"DE",
    "sg:address":"Hauptstr. 63",
    "sg:city":"Schwebheim",
    "sg:phone":"+49 9723/1748",
    "sg:postcode":"97525",
    "sg:province":"Bayern",
    "wof:name":"R. Wegner",
    "wof:placetype":"venue"
},
  "geometry": {"coordinates":[10.2462921143,49.9935531616],"type":"Point"}
}