{
  "type": "Feature",
  "properties": {
    "iso:country":"DE",
    "sg:address":"Dietersdorfer Str. 16",
    "sg:city":"Se\u00dflach",
    "sg:phone":"+49 9567/294",
    "sg:postcode":"96145",
    "sg:province":"Bayern",
    "wof:name":"Walter F\u00f6rtsch",
    "wof:placetype":"venue"
},
  "geometry": {"coordinates":[10.823124,50.217831],"type":"Point"}
}