{
  "type": "Feature",
  "properties": {
    "iso:country":"DE",
    "sg:address":"Segeberger Chaussee 36",
    "sg:city":"Norderstedt",
    "sg:phone":"+49 40/5267395",
    "sg:postcode":"22850",
    "sg:province":"Schleswig-Holstein",
    "wof:name":"Computer Vertrieb Ada Gmbh",
    "wof:placetype":"venue"
},
  "geometry": {"coordinates":[10.0053253174,53.6825561523],"type":"Point"}
}