{
  "type": "Feature",
  "properties": {
    "iso:country":"DE",
    "sg:address":"Burg-Windeck-Str. 25",
    "sg:city":"Ottersweier",
    "sg:phone":"+49 7223/22979",
    "sg:postcode":"77833",
    "sg:province":"Baden-W\u00fcrttemberg",
    "wof:name":"Konrad Huck",
    "wof:placetype":"venue"
},
  "geometry": {"coordinates":[8.137838,48.667763],"type":"Point"}
}