{
  "type": "Feature",
  "properties": {
    "iso:country":"DE",
    "sg:address":"St. Pauli Fischmarkt 27",
    "sg:city":"Hamburg",
    "sg:phone":"+49 40/3195336",
    "sg:postcode":"20359",
    "sg:province":"Hamburg",
    "wof:name":"Golden Pudel Klub",
    "wof:placetype":"venue"
},
  "geometry": {"coordinates":[9.9577980042,53.5460891724],"type":"Point"}
}