{
  "type": "Feature",
  "properties": {
    "iso:country":"DE",
    "sg:address":"Hegaustr. 17",
    "sg:city":"Emmingen-Liptingen",
    "sg:phone":"+49 7465/2404",
    "sg:postcode":"78576",
    "sg:province":"Baden-W\u00fcrttemberg",
    "wof:name":"Leonhard St\u00f6rk Gmbh",
    "wof:placetype":"venue"
},
  "geometry": {"coordinates":[8.8494291306,47.9268302917],"type":"Point"}
}