{
  "type": "Feature",
  "properties": {
    "iso:country":"DE",
    "sg:address":"Kapuzinerstr. 1",
    "sg:city":"W\u00fcrzburg",
    "sg:phone":"+49 931/14736",
    "sg:postcode":"97070",
    "sg:province":"Bayern",
    "wof:name":"Dr. Med. Reiner Artner Arzt F\u00fcr Allgemeinmedizin",
    "wof:placetype":"venue"
},
  "geometry": {"coordinates":[9.9372606277,49.7941856384],"type":"Point"}
}