{
  "type": "Feature",
  "properties": {
    "iso:country":"DE",
    "sg:address":"Winterberger Str. 26",
    "sg:city":"Olsberg",
    "sg:phone":"+49 2985/97510",
    "sg:postcode":"59939",
    "sg:province":"Nordrhein-Westfalen",
    "wof:name":"Grosche Gmbh",
    "wof:placetype":"venue"
},
  "geometry": {"coordinates":[8.510602951,51.2828369141],"type":"Point"}
}