{
  "type": "Feature",
  "properties": {
    "iso:country":"DE",
    "sg:address":"Hauptstr. 37",
    "sg:city":"M\u00fcnsterhausen",
    "sg:phone":"+49 8281/3412",
    "sg:postcode":"86505",
    "sg:province":"Bayern",
    "wof:name":"K. Drexel",
    "wof:placetype":"venue"
},
  "geometry": {"coordinates":[10.4506921768,48.3141517639],"type":"Point"}
}