{
  "type": "Feature",
  "properties": {
    "iso:country":"DE",
    "sg:address":"Osterkamp 3",
    "sg:city":"Porta Westfalica",
    "sg:phone":"+49 5731/7680",
    "sg:postcode":"32457",
    "sg:province":"Nordrhein-Westfalen",
    "wof:name":"Rodenberg Fenster- Und T\u00fcren Technik Ag",
    "wof:placetype":"venue"
},
  "geometry": {"coordinates":[8.878977,52.209084],"type":"Point"}
}