{
  "type": "Feature",
  "properties": {
    "iso:country":"DE",
    "sg:address":"Bl\u00e4siberg",
    "sg:city":"Wiesensteig",
    "sg:phone":"+49 7335/5095",
    "sg:postcode":"73349",
    "sg:province":"Baden-W\u00fcrttemberg",
    "wof:name":"Christliches Jugenddorf",
    "wof:placetype":"venue"
},
  "geometry": {"coordinates":[9.6166982651,48.5736312866],"type":"Point"}
}