{
  "type": "Feature",
  "properties": {
    "iso:country":"DE",
    "sg:address":"Wittener Landstr. 34",
    "sg:city":"Herdecke",
    "sg:phone":"+49 2330/70115",
    "sg:postcode":"58313",
    "sg:province":"Nordrhein-Westfalen",
    "wof:name":"Heinz Tafel",
    "wof:placetype":"venue"
},
  "geometry": {"coordinates":[7.414475,51.426971],"type":"Point"}
}