{
  "type": "Feature",
  "properties": {
    "iso:country":"DE",
    "sg:address":"Am Hohentorshafen 7",
    "sg:city":"Bremen",
    "sg:phone":"+49 4942/1549970",
    "sg:postcode":"28197",
    "sg:province":"Bremen",
    "wof:name":"Manfred Jc Niemann Hanseatischer Metallhandel Bremen Gmbh & Co. Kg",
    "wof:placetype":"venue"
},
  "geometry": {"coordinates":[8.785201,53.078571],"type":"Point"}
}