{
  "type": "Feature",
  "properties": {
    "iso:country":"DE",
    "sg:address":"Illinger Str. 26",
    "sg:city":"Illingen",
    "sg:phone":"+49 6825/43505",
    "sg:postcode":"66557",
    "sg:province":"Saarland",
    "wof:name":"Dr. Med. Myint Win Arzt F\u00fcr Allgemeinmedizin",
    "wof:placetype":"venue"
},
  "geometry": {"coordinates":[7.0391340256,49.3959312439],"type":"Point"}
}