{
  "type": "Feature",
  "properties": {
    "iso:country":"DE",
    "sg:address":"Luisenstr. 63",
    "sg:city":"Offenbach",
    "sg:phone":"+49 69/884645",
    "sg:postcode":"63067",
    "sg:province":"Hessen",
    "wof:name":"Ristorante Dino Ohg",
    "wof:placetype":"venue"
},
  "geometry": {"coordinates":[8.7569122314,50.1038627625],"type":"Point"}
}