{
  "type": "Feature",
  "properties": {
    "iso:country":"DE",
    "sg:address":"Berliner Str. 25",
    "sg:city":"Hennigsdorf",
    "sg:postcode":"16761",
    "sg:province":"Brandenburg",
    "wof:name":"Allianz Versicherungs Ag",
    "wof:placetype":"venue"
},
  "geometry": {"coordinates":[13.2059497833,52.6423034668],"type":"Point"}
}