{
  "type": "Feature",
  "properties": {
    "iso:country":"DE",
    "sg:address":"Chausseeberg 10",
    "sg:city":"Mellenthin",
    "sg:phone":"+49 38379/20304",
    "sg:postcode":"17429",
    "sg:province":"Mecklenburg-Vorpommern",
    "wof:name":"Bioproduktion-landwirtschafts Gmbh Burgwald",
    "wof:placetype":"venue"
},
  "geometry": {"coordinates":[14.019076,53.91552],"type":"Point"}
}