{
  "type": "Feature",
  "properties": {
    "iso:country":"DE",
    "sg:address":"Hoher Wald 9",
    "sg:city":"Odenthal",
    "sg:phone":"+49 2202/7230",
    "sg:postcode":"51519",
    "sg:province":"Nordrhein-Westfalen",
    "wof:name":"Herb Quick",
    "wof:placetype":"venue"
},
  "geometry": {"coordinates":[7.1164941788,51.0162963867],"type":"Point"}
}