{
  "type": "Feature",
  "properties": {
    "iso:country":"DE",
    "sg:address":"Auf den Steinen 9",
    "sg:city":"Gernrode",
    "sg:postcode":"06507",
    "sg:province":"Sachsen-Anhalt",
    "wof:name":"Dieter Frenkel & Co. Erodier- Und Zerspannungs-",
    "wof:placetype":"venue"
},
  "geometry": {"coordinates":[11.1471481323,51.7385826111],"type":"Point"}
}