{
  "type": "Feature",
  "properties": {
    "iso:country":"DE",
    "sg:address":"Schurwaldstr. 114",
    "sg:city":"Aichwald",
    "sg:phone":"+49 711/3698580",
    "sg:postcode":"73773",
    "sg:province":"Baden-W\u00fcrttemberg",
    "wof:name":"Laurel-klammern Gmbh",
    "wof:placetype":"venue"
},
  "geometry": {"coordinates":[9.3930616379,48.7838897705],"type":"Point"}
}