{
  "type": "Feature",
  "properties": {
    "iso:country":"DE",
    "sg:address":"Bertelestr. 53",
    "sg:city":"M\u00fcnchen",
    "sg:postcode":"81479",
    "sg:province":"Bayern",
    "wof:name":"Quentus Gesellschaft F\u00fcr Forschung Zur Gesundheit",
    "wof:placetype":"venue"
},
  "geometry": {"coordinates":[11.5241565704,48.0731773376],"type":"Point"}
}