{
  "type": "Feature",
  "properties": {
    "iso:country":"DE",
    "sg:address":"Hainbuchenweg 8",
    "sg:city":"Leimen",
    "sg:phone":"+49 6224/71455",
    "sg:postcode":"69181",
    "sg:province":"Baden-W\u00fcrttemberg",
    "wof:name":"Prof. Dr. Adolf Meyer",
    "wof:placetype":"venue"
},
  "geometry": {"coordinates":[8.7254524231,49.3543930054],"type":"Point"}
}