{
  "type": "Feature",
  "properties": {
    "iso:country":"DE",
    "sg:address":"Ackerstr. 144-146",
    "sg:city":"K\u00f6ln",
    "sg:phone":"+49 221/67890",
    "sg:postcode":"51065",
    "sg:province":"Nordrhein-Westfalen",
    "wof:name":"Peter Dr\u00f6sser Stahlhandel Gmbh & Co. Kg",
    "wof:placetype":"venue"
},
  "geometry": {"coordinates":[7.0180988312,50.9624252319],"type":"Point"}
}