{
  "type": "Feature",
  "properties": {
    "iso:country":"DE",
    "sg:address":"Magdalenenstr. 37",
    "sg:city":"Bonn",
    "sg:phone":"+49 228/622727",
    "sg:postcode":"53121",
    "sg:province":"Nordrhein-Westfalen",
    "wof:name":"Balthasar K\u00f6ster",
    "wof:placetype":"venue"
},
  "geometry": {"coordinates":[7.076729,50.724937],"type":"Point"}
}