{
  "type": "Feature",
  "properties": {
    "iso:country":"DE",
    "sg:address":"Gr\u00fcner Deich 15",
    "sg:city":"Hamburg",
    "sg:phone":"+49 40/300540",
    "sg:postcode":"20097",
    "sg:province":"Hamburg",
    "wof:name":"Apollinaris & Schweppes Gmbh",
    "wof:placetype":"venue"
},
  "geometry": {"coordinates":[10.028156,53.543175],"type":"Point"}
}