{
  "type": "Feature",
  "properties": {
    "iso:country":"DE",
    "sg:address":"Postfach 3:: 89156 Dornstadt:: Germany.^^Tomerdinger Str 1::",
    "sg:city":"Dornstadt",
    "sg:phone":"+49 7348/20030",
    "sg:postcode":"89160",
    "sg:province":"Baden-W\u00fcrttemberg",
    "wof:name":"Raiffeisenbank Ulmer Alb Eg",
    "wof:placetype":"venue"
},
  "geometry": {"coordinates":[9.939491,48.464966],"type":"Point"}
}