{
  "type": "Feature",
  "properties": {
    "iso:country":"DE",
    "sg:address":"Postfach 103535",
    "sg:city":"Essen",
    "sg:postcode":"45035",
    "sg:province":"Niedersachsen",
    "wof:name":"Schwab & Pepperhoff Staatliche Lotterie-einnahme",
    "wof:placetype":"venue"
},
  "geometry": {"coordinates":[7.01475,51.458019],"type":"Point"}
}