{
  "type": "Feature",
  "properties": {
    "iso:country":"DE",
    "sg:address":"Huttentalstr. 13",
    "sg:city":"Bad Soden-Salm\u00fcnster",
    "sg:phone":"+49 6056/2193",
    "sg:postcode":"63628",
    "sg:province":"Hessen",
    "wof:name":"Hermann Krack",
    "wof:placetype":"venue"
},
  "geometry": {"coordinates":[9.373293,50.314983],"type":"Point"}
}