{
  "type": "Feature",
  "properties": {
    "iso:country":"DE",
    "sg:address":"Georg-St\u00f6ckel-Str. 7",
    "sg:city":"Weiden",
    "sg:phone":"+49 4922/0231230",
    "sg:postcode":"92637",
    "sg:province":"Bayern",
    "wof:name":"Vierling Gmbh",
    "wof:placetype":"venue"
},
  "geometry": {"coordinates":[7.128467083,50.9918251038],"type":"Point"}
}