{
  "type": "Feature",
  "properties": {
    "iso:country":"DE",
    "sg:address":"Ebertstr. 51",
    "sg:city":"Oberhausen",
    "sg:phone":"+49 208/24428",
    "sg:postcode":"46045",
    "sg:province":"Nordrhein-Westfalen",
    "wof:name":"Lindner Bauelemente",
    "wof:placetype":"venue"
},
  "geometry": {"coordinates":[6.858936,51.476006],"type":"Point"}
}