{
  "type": "Feature",
  "properties": {
    "iso:country":"DE",
    "sg:address":"Hallenbad",
    "sg:city":"Schwieberdingen",
    "sg:postcode":"71701",
    "sg:province":"Baden-W\u00fcrttemberg",
    "wof:name":"Www.schwimmen.org - Die Seite F\u00fcr Schwimmfreaks",
    "wof:placetype":"venue"
},
  "geometry": {"coordinates":[9.075078,48.876553],"type":"Point"}
}