{
  "type": "Feature",
  "properties": {
    "iso:country":"DE",
    "sg:address":"Neue Amberger Str. 49",
    "sg:city":"Grafenw\u00f6hr",
    "sg:phone":"+49 9641/2205",
    "sg:postcode":"92655",
    "sg:province":"Bayern",
    "wof:name":"W. Peter",
    "wof:placetype":"venue"
},
  "geometry": {"coordinates":[11.909046,49.718777],"type":"Point"}
}