{
  "type": "Feature",
  "properties": {
    "iso:country":"DE",
    "sg:address":"Rohrbacher Str. 98 A",
    "sg:city":"Heidelberg",
    "sg:phone":"+49 6221/374625",
    "sg:postcode":"69126",
    "sg:province":"Baden-W\u00fcrttemberg",
    "wof:name":"Schiller + Fath Gmbh",
    "wof:placetype":"venue"
},
  "geometry": {"coordinates":[8.689361,49.397297],"type":"Point"}
}