{
  "type": "Feature",
  "properties": {
    "iso:country":"DE",
    "sg:address":"G\u00fcstener Str 19",
    "sg:city":"Aschersleben",
    "sg:phone":"+49 3473/226468",
    "sg:postcode":"06449",
    "sg:province":"Sachsen-Anhalt",
    "wof:name":"Nicole Manecke",
    "wof:placetype":"venue"
},
  "geometry": {"coordinates":[11.4813919067,51.7669944763],"type":"Point"}
}