{
  "type": "Feature",
  "properties": {
    "iso:country":"DE",
    "sg:address":"Linnenkamp 4",
    "sg:city":"Hildesheim",
    "sg:phone":"+49 5121/42461",
    "sg:postcode":"31137",
    "sg:province":"Niedersachsen",
    "wof:name":"Hotel-restaurant Zum Osterberg",
    "wof:placetype":"venue"
},
  "geometry": {"coordinates":[9.9127473831,52.165058136],"type":"Point"}
}