{
  "type": "Feature",
  "properties": {
    "iso:country":"DE",
    "sg:address":"Pappelstr. 12",
    "sg:city":"Sch\u00f6nebeck",
    "sg:phone":"+49 3928/400215",
    "sg:postcode":"39218",
    "sg:province":"Sachsen-Anhalt",
    "wof:name":"Rainer Schmidt",
    "wof:placetype":"venue"
},
  "geometry": {"coordinates":[11.762172699,52.0050392151],"type":"Point"}
}