{
  "type": "Feature",
  "properties": {
    "iso:country":"DE",
    "sg:address":"Glaserm\u00fchle 4",
    "sg:city":"Bischofsgr\u00fcn",
    "sg:phone":"+49 9276/457",
    "sg:postcode":"95493",
    "sg:province":"Bayern",
    "wof:name":"Gasthaus Zum Maintal",
    "wof:placetype":"venue"
},
  "geometry": {"coordinates":[11.7773189545,50.0547714233],"type":"Point"}
}