{
  "type": "Feature",
  "properties": {
    "iso:country":"DE",
    "sg:address":"Im Breitholz 9",
    "sg:city":"Andernach",
    "sg:phone":"+49 2632/82400",
    "sg:postcode":"56626",
    "sg:province":"Rheinland-Pfalz",
    "wof:name":"B. Steffens Ingenieur",
    "wof:placetype":"venue"
},
  "geometry": {"coordinates":[7.3340611458,50.4300308228],"type":"Point"}
}