{
  "type": "Feature",
  "properties": {
    "iso:country":"DE",
    "sg:address":"Burgstr. 1",
    "sg:city":"L\u00fcchow",
    "sg:phone":"+49 5841/6672",
    "sg:postcode":"29439",
    "sg:province":"Niedersachsen",
    "wof:name":"Heide B\u00f6hmer-klepper Heilpraktikerin",
    "wof:placetype":"venue"
},
  "geometry": {"coordinates":[11.1556978226,52.9672355652],"type":"Point"}
}