{
  "type": "Feature",
  "properties": {
    "iso:country":"DE",
    "sg:address":"Bahnhofstr. 2",
    "sg:city":"Oelde",
    "sg:phone":"+49 2522/60257",
    "sg:postcode":"59302",
    "sg:province":"Nordrhein-Westfalen",
    "wof:name":"F. Brormann",
    "wof:placetype":"venue"
},
  "geometry": {"coordinates":[8.1433897018,51.8259963989],"type":"Point"}
}