{
  "type": "Feature",
  "properties": {
    "iso:country":"DE",
    "sg:address":"Strandstr. 1",
    "sg:city":"Juist",
    "sg:phone":"+49 4935/412",
    "sg:postcode":"26571",
    "sg:province":"Niedersachsen",
    "wof:name":"Erich Hahn",
    "wof:placetype":"venue"
},
  "geometry": {"coordinates":[6.9952778816,53.6777458191],"type":"Point"}
}