{
  "type": "Feature",
  "properties": {
    "iso:country":"DE",
    "sg:address":"Luitpoldstr. 32",
    "sg:city":"Rockenhausen",
    "sg:phone":"+49 6361/7240",
    "sg:postcode":"67806",
    "sg:province":"Rheinland-Pfalz",
    "wof:name":"Roland Bessei",
    "wof:placetype":"venue"
},
  "geometry": {"coordinates":[7.8222379684,49.6287918091],"type":"Point"}
}