{
  "type": "Feature",
  "properties": {
    "iso:country":"DE",
    "sg:address":"Johannesstr. 24",
    "sg:city":"Neubrandenburg",
    "sg:phone":"+49 395/4225856",
    "sg:postcode":"17034",
    "sg:province":"Mecklenburg-Vorpommern",
    "wof:name":"Neubrandenburger Stra\u00dfen- Und Tiefbau Gmbh",
    "wof:placetype":"venue"
},
  "geometry": {"coordinates":[13.2805175781,53.5606575012],"type":"Point"}
}