{
  "type": "Feature",
  "properties": {
    "iso:country":"DE",
    "sg:address":"Asamstr. 3",
    "sg:city":"Rottach-Egern",
    "sg:postcode":"83700",
    "sg:province":"Bayern",
    "wof:name":"Masters Drivingrange Gmbh & Co. Kg",
    "wof:placetype":"venue"
},
  "geometry": {"coordinates":[11.753511,47.694885],"type":"Point"}
}