{
  "type": "Feature",
  "properties": {
    "iso:country":"DE",
    "sg:address":"Marktstr. 17",
    "sg:city":"Kelbra",
    "sg:phone":"+49 34651/6461",
    "sg:postcode":"06537",
    "sg:province":"Sachsen-Anhalt",
    "wof:name":"Apel",
    "wof:placetype":"venue"
},
  "geometry": {"coordinates":[11.039713,51.437428],"type":"Point"}
}