{
  "type": "Feature",
  "properties": {
    "iso:country":"DE",
    "sg:address":"Gr\u00fcner Weg 5-9",
    "sg:city":"Berlin",
    "sg:phone":"+49 30/8059420",
    "sg:postcode":"14109",
    "sg:province":"Berlin",
    "wof:name":"Profi Bootscenter In Wannsee Gmbh",
    "wof:placetype":"venue"
},
  "geometry": {"coordinates":[13.146656,52.412743],"type":"Point"}
}