{
  "type": "Feature",
  "properties": {
    "iso:country":"DE",
    "sg:address":"Holzkamp 8",
    "sg:city":"Nortorf",
    "sg:phone":"+49 4392/2808",
    "sg:postcode":"24589",
    "sg:province":"Schleswig-Holstein",
    "wof:name":"Ambulanter Pflegedienst Woschoen & J\u00f6rs",
    "wof:placetype":"venue"
},
  "geometry": {"coordinates":[9.851208,54.168213],"type":"Point"}
}