{
  "type": "Feature",
  "properties": {
    "iso:country":"DE",
    "sg:address":"Dorfstr. 60",
    "sg:city":"Westerr\u00f6nfeld",
    "sg:postcode":"24784",
    "sg:province":"Schleswig-Holstein",
    "wof:name":"Gemeindeb\u00fccherei",
    "wof:placetype":"venue"
},
  "geometry": {"coordinates":[9.646976,54.283112],"type":"Point"}
}