{
  "type": "Feature",
  "properties": {
    "iso:country":"DE",
    "sg:address":"Horstweg 5",
    "sg:city":"Berlin",
    "sg:phone":"+49 30/32601407",
    "sg:postcode":"14059",
    "sg:province":"Berlin",
    "wof:name":"Gerold Kirchner",
    "wof:placetype":"venue"
},
  "geometry": {"coordinates":[13.2946271896,52.5119132996],"type":"Point"}
}