{
  "type": "Feature",
  "properties": {
    "iso:country":"DE",
    "sg:address":"Jersbeker Str. 13",
    "sg:city":"Bargteheide",
    "sg:phone":"+49 4532/265558",
    "sg:postcode":"22941",
    "sg:province":"Schleswig-Holstein",
    "wof:name":"Musikhaus Wilke",
    "wof:placetype":"venue"
},
  "geometry": {"coordinates":[10.2571897507,53.7287712097],"type":"Point"}
}