{
  "type": "Feature",
  "properties": {
    "iso:country":"DE",
    "sg:address":"Bahnhofstr. 15",
    "sg:city":"Seubersdorf",
    "sg:phone":"+49 9497/902121",
    "sg:postcode":"92358",
    "sg:province":"Bayern",
    "wof:name":"Matthias Lutter",
    "wof:placetype":"venue"
},
  "geometry": {"coordinates":[11.6269445419,49.1662101746],"type":"Point"}
}