{
  "type": "Feature",
  "properties": {
    "iso:country":"DE",
    "sg:address":"Monaiser Str. 13",
    "sg:city":"Trier",
    "sg:phone":"+49 651/840480",
    "sg:postcode":"54294",
    "sg:province":"Rheinland-Pfalz",
    "wof:name":"Bdl Bickel Dienstleistung Und Logistik Gmbh",
    "wof:placetype":"venue"
},
  "geometry": {"coordinates":[6.594244957,49.7209129333],"type":"Point"}
}