{
  "type": "Feature",
  "properties": {
    "iso:country":"DE",
    "sg:address":"Kreuzberger Ring 23",
    "sg:city":"Wiesbaden",
    "sg:postcode":"65205",
    "sg:province":"Hessen",
    "wof:name":"Ids Medical Technology Gmbh",
    "wof:placetype":"venue"
},
  "geometry": {"coordinates":[8.289937,50.054924],"type":"Point"}
}