{
  "type": "Feature",
  "properties": {
    "iso:country":"DE",
    "sg:address":"Friedrichstr 16",
    "sg:city":"K\u00f6then",
    "sg:phone":"+49 3496/402990",
    "sg:postcode":"06366",
    "sg:province":"Sachsen-Anhalt",
    "wof:name":"Kammer & Picht Elektro-technik-gmbh",
    "wof:placetype":"venue"
},
  "geometry": {"coordinates":[11.982587,51.75404],"type":"Point"}
}