{
  "type": "Feature",
  "properties": {
    "iso:country":"DE",
    "sg:address":"Mangoldstr. 8",
    "sg:city":"Wemding",
    "sg:phone":"+49 9092/285",
    "sg:postcode":"86650",
    "sg:province":"Bayern",
    "wof:name":"Josef Seefried",
    "wof:placetype":"venue"
},
  "geometry": {"coordinates":[10.725306,48.874626],"type":"Point"}
}