{
  "type": "Feature",
  "properties": {
    "iso:country":"DE",
    "sg:address":"Sch\u00f6ffauer Str. 13",
    "sg:city":"Kiefersfelden",
    "sg:phone":"+49 8033/8206",
    "sg:postcode":"83088",
    "sg:province":"Bayern",
    "wof:name":"Dr. Med. M. Kapff-von Bippen \u00c4rztin F\u00fcr Allgemeinmedizin",
    "wof:placetype":"venue"
},
  "geometry": {"coordinates":[12.177154541,47.6245346069],"type":"Point"}
}