{
  "type": "Feature",
  "properties": {
    "iso:country":"DE",
    "sg:address":"Heiseder Str. 1 D",
    "sg:city":"Sarstedt",
    "sg:phone":"+49 5066/65720",
    "sg:postcode":"31157",
    "sg:province":"Niedersachsen",
    "wof:name":"Alka-trading Export Gmbh",
    "wof:placetype":"venue"
},
  "geometry": {"coordinates":[9.857365,52.256519],"type":"Point"}
}