{
  "type": "Feature",
  "properties": {
    "iso:country":"DE",
    "sg:address":"Schweinfurter Str. 108",
    "sg:city":"Schwarzach",
    "sg:phone":"+49 9324/1577",
    "sg:postcode":"97359",
    "sg:province":"Bayern",
    "wof:name":"Gasthaus Raimund Pfannes",
    "wof:placetype":"venue"
},
  "geometry": {"coordinates":[10.2244291306,49.8126182556],"type":"Point"}
}