{
  "type": "Feature",
  "properties": {
    "iso:country":"DE",
    "sg:address":"Leitergasse 19",
    "sg:city":"Gondelsheim",
    "sg:phone":"+49 7252/4994",
    "sg:postcode":"75053",
    "sg:province":"Baden-W\u00fcrttemberg",
    "wof:name":"Anette Ries",
    "wof:placetype":"venue"
},
  "geometry": {"coordinates":[8.6590194702,49.0597114563],"type":"Point"}
}