{
  "type": "Feature",
  "properties": {
    "iso:country":"DE",
    "sg:address":"Dresdener Str. 9",
    "sg:city":"Waldheim",
    "sg:phone":"+49 34327/92307",
    "sg:postcode":"04736",
    "sg:province":"Sachsen",
    "wof:name":"Restaurant Zur Linde",
    "wof:placetype":"venue"
},
  "geometry": {"coordinates":[13.0302944183,51.073135376],"type":"Point"}
}