{
  "type": "Feature",
  "properties": {
    "iso:country":"DE",
    "sg:address":"Friedrich-Hegel-Str. 5",
    "sg:city":"Rathenow",
    "sg:postcode":"14712",
    "sg:province":"Brandenburg",
    "wof:name":"T. Mateke",
    "wof:placetype":"venue"
},
  "geometry": {"coordinates":[12.3393526077,52.5848808289],"type":"Point"}
}