{
  "type": "Feature",
  "properties": {
    "iso:country":"DE",
    "sg:address":"Th\u00fcngersheimer Str. 91",
    "sg:city":"Veitsh\u00f6chheim",
    "sg:phone":"+49 931/91201",
    "sg:postcode":"97209",
    "sg:province":"Bayern",
    "wof:name":"Max Weckesser Gmbh",
    "wof:placetype":"venue"
},
  "geometry": {"coordinates":[9.8718271255,49.838218689],"type":"Point"}
}