{
  "type": "Feature",
  "properties": {
    "iso:country":"DE",
    "sg:address":"Kirchweg 5",
    "sg:city":"Kassel",
    "sg:phone":"+49 561/21696",
    "sg:postcode":"34121",
    "sg:province":"Hessen",
    "wof:name":"Karl Wagner Inh. Karin Hoppe",
    "wof:placetype":"venue"
},
  "geometry": {"coordinates":[9.4675559998,51.3098106384],"type":"Point"}
}