{
  "type": "Feature",
  "properties": {
    "iso:country":"DE",
    "sg:address":"Zur Buche 1",
    "sg:city":"Heidenau",
    "sg:phone":"+49 4182/4235",
    "sg:postcode":"21258",
    "sg:province":"Niedersachsen",
    "wof:name":"Heinz Inselmann",
    "wof:placetype":"venue"
},
  "geometry": {"coordinates":[9.659342,53.315121],"type":"Point"}
}