{
  "type": "Feature",
  "properties": {
    "iso:country":"DE",
    "sg:address":"Hauptstr. 53",
    "sg:city":"Spaichingen",
    "sg:phone":"+49 7424/501261",
    "sg:postcode":"78549",
    "sg:province":"Baden-W\u00fcrttemberg",
    "wof:name":"G. B\u00fchler",
    "wof:placetype":"venue"
},
  "geometry": {"coordinates":[8.7440948486,48.0703430176],"type":"Point"}
}