{
  "type": "Feature",
  "properties": {
    "iso:country":"DE",
    "sg:address":"Mus\u00e4usring 37",
    "sg:city":"Jena",
    "sg:phone":"+49 3641/395823",
    "sg:postcode":"07747",
    "sg:province":"Th\u00fcringen",
    "wof:name":"Orthop\u00e4die & Reha Technik Gmbh",
    "wof:placetype":"venue"
},
  "geometry": {"coordinates":[11.6372690201,50.8820991516],"type":"Point"}
}