{
  "type": "Feature",
  "properties": {
    "iso:country":"DE",
    "sg:address":"Am Oberen Luisenpark 13",
    "sg:city":"Mannheim",
    "sg:phone":"+49 621/440040",
    "sg:postcode":"68165",
    "sg:province":"Baden-W\u00fcrttemberg",
    "wof:name":"H. Fleischer Gmbh",
    "wof:placetype":"venue"
},
  "geometry": {"coordinates":[8.4911546707,49.4830513],"type":"Point"}
}