{
  "type": "Feature",
  "properties": {
    "iso:country":"DE",
    "sg:address":"Schm\u00f6llnsche Vorstadt 13",
    "sg:city":"Altenburg",
    "sg:postcode":"04600",
    "sg:province":"Th\u00fcringen",
    "wof:name":"Metzen Warenhandels Gmbh",
    "wof:placetype":"venue"
},
  "geometry": {"coordinates":[12.427362,50.983402],"type":"Point"}
}