{
  "type": "Feature",
  "properties": {
    "iso:country":"DE",
    "sg:address":"Postbrookstr. 8",
    "sg:city":"Bremerhaven",
    "sg:phone":"+49 471/29210",
    "sg:postcode":"27574",
    "sg:province":"Bremen",
    "wof:name":"Lutz Rothe Bedachungen E. K.",
    "wof:placetype":"venue"
},
  "geometry": {"coordinates":[8.62463,53.531456],"type":"Point"}
}