{
  "type": "Feature",
  "properties": {
    "iso:country":"DE",
    "sg:address":"Gebsattelstr. 28",
    "sg:city":"M\u00fcnchen",
    "sg:phone":"+49 89/44218750",
    "sg:postcode":"81541",
    "sg:province":"Bayern",
    "wof:name":"Gigaperls",
    "wof:placetype":"venue"
},
  "geometry": {"coordinates":[11.589009,48.124592],"type":"Point"}
}