{
  "type": "Feature",
  "properties": {
    "iso:country":"DE",
    "sg:address":"Wilhelmstr 107",
    "sg:city":"Illingen",
    "sg:phone":"+49 7042/801060",
    "sg:postcode":"75428",
    "sg:province":"Baden-W\u00fcrttemberg",
    "wof:name":"Belzer Werbung@druck Gmbh",
    "wof:placetype":"venue"
},
  "geometry": {"coordinates":[8.935011,48.955914],"type":"Point"}
}