{
  "type": "Feature",
  "properties": {
    "iso:country":"DE",
    "sg:address":"Moskauer Str. 17",
    "sg:city":"Sch\u00f6nebeck",
    "sg:phone":"+49 3928/68287",
    "sg:postcode":"39218",
    "sg:province":"Sachsen-Anhalt",
    "wof:name":"Sanit\u00e4tshaus \u00d6sterreich",
    "wof:placetype":"venue"
},
  "geometry": {"coordinates":[11.7332763672,52.010093689],"type":"Point"}
}