{
  "type": "Feature",
  "properties": {
    "iso:country":"DE",
    "sg:address":"Landsberger Str. 90",
    "sg:city":"M\u00fcnchen",
    "sg:phone":"+49 89/6803868",
    "sg:postcode":"80339",
    "sg:province":"Bayern",
    "wof:name":"Gerhard Stadler",
    "wof:placetype":"venue"
},
  "geometry": {"coordinates":[11.5383071899,48.1399688721],"type":"Point"}
}