{
  "type": "Feature",
  "properties": {
    "iso:country":"DE",
    "sg:address":"Esselberg",
    "sg:city":"Greding",
    "sg:phone":"+49 8463/739",
    "sg:postcode":"91171",
    "sg:province":"Bayern",
    "wof:name":"Josef Mosburger",
    "wof:placetype":"venue"
},
  "geometry": {"coordinates":[11.2678403854,49.0379714966],"type":"Point"}
}