{
  "type": "Feature",
  "properties": {
    "iso:country":"DE",
    "sg:address":"Alter Banter Weg 65",
    "sg:city":"Wilhelmshaven",
    "sg:phone":"+49 4421/202560",
    "sg:postcode":"26389",
    "sg:province":"Niedersachsen",
    "wof:name":"Jade-ventilatoren U. Maschinenbau Gmbh",
    "wof:placetype":"venue"
},
  "geometry": {"coordinates":[8.085346,53.514156],"type":"Point"}
}