{
  "type": "Feature",
  "properties": {
    "iso:country":"DE",
    "sg:address":"Bergweg 5 b",
    "sg:city":"Bernkastel-Kues",
    "sg:phone":"+49 6531/6178",
    "sg:postcode":"54470",
    "sg:province":"Rheinland-Pfalz",
    "wof:name":"Hotel Haus Anja",
    "wof:placetype":"venue"
},
  "geometry": {"coordinates":[7.0645279884,49.9193916321],"type":"Point"}
}