{
  "type": "Feature",
  "properties": {
    "iso:country":"DE",
    "sg:address":"Spiegelstr. 23",
    "sg:city":"W\u00fcrzburg",
    "sg:postcode":"97070",
    "sg:province":"Bayern",
    "wof:name":"Weiss Verwaltungs-gmbh",
    "wof:placetype":"venue"
},
  "geometry": {"coordinates":[9.934746,49.794975],"type":"Point"}
}