{
  "type": "Feature",
  "properties": {
    "iso:country":"DE",
    "sg:address":"Hestermannweg 4",
    "sg:city":"Recklinghausen",
    "sg:phone":"+49 2361/61064",
    "sg:postcode":"45663",
    "sg:province":"Nordrhein-Westfalen",
    "wof:name":"Monika Erdmann",
    "wof:placetype":"venue"
},
  "geometry": {"coordinates":[7.2358608246,51.5815811157],"type":"Point"}
}