{
  "type": "Feature",
  "properties": {
    "iso:country":"DE",
    "sg:address":"Hohes Lenscheid 1",
    "sg:city":"Sundern",
    "sg:phone":"+49 2395/340",
    "sg:postcode":"59846",
    "sg:province":"Nordrhein-Westfalen",
    "wof:name":"Karlheinz Ermes",
    "wof:placetype":"venue"
},
  "geometry": {"coordinates":[7.9726471901,51.242061615],"type":"Point"}
}