{
  "type": "Feature",
  "properties": {
    "iso:country":"DE",
    "sg:address":"Dorfstr. 6",
    "sg:city":"Gro\u00dfweitzschen",
    "sg:phone":"+49 34324/21060",
    "sg:postcode":"04720",
    "sg:province":"Sachsen",
    "wof:name":"Manfred Winkler",
    "wof:placetype":"venue"
},
  "geometry": {"coordinates":[13.078591,51.163864],"type":"Point"}
}