{
  "type": "Feature",
  "properties": {
    "iso:country":"DE",
    "sg:address":"Langenberger Str. 5",
    "sg:city":"Glaubitz",
    "sg:phone":"+49 35265/54259",
    "sg:postcode":"01612",
    "sg:province":"Sachsen",
    "wof:name":"Carmen Zocher",
    "wof:placetype":"venue"
},
  "geometry": {"coordinates":[13.3734006882,51.3119277954],"type":"Point"}
}