{
  "type": "Feature",
  "properties": {
    "iso:country":"DE",
    "sg:address":"Holunderweg 3",
    "sg:city":"Auenwald",
    "sg:phone":"+49 7191/310630",
    "sg:postcode":"71549",
    "sg:province":"Baden-W\u00fcrttemberg",
    "wof:name":"E. Klink Bauunternehmung Gmbh",
    "wof:placetype":"venue"
},
  "geometry": {"coordinates":[9.5038051605,48.951335907],"type":"Point"}
}