{
  "type": "Feature",
  "properties": {
    "iso:country":"DE",
    "sg:address":"Harburger Chaussee 119",
    "sg:city":"Hamburg",
    "sg:postcode":"20539",
    "sg:province":"Hamburg",
    "wof:name":"E-ra Im- Und Export Gmbh",
    "wof:placetype":"venue"
},
  "geometry": {"coordinates":[10.0042829514,53.5203132629],"type":"Point"}
}