{
  "type": "Feature",
  "properties": {
    "iso:country":"DE",
    "sg:address":"Christian-Coenen-Str. 17",
    "sg:city":"K\u00f6ln",
    "sg:phone":"+49 221/603390",
    "sg:postcode":"51069",
    "sg:province":"Nordrhein-Westfalen",
    "wof:name":"F. Meyer Immobilienmakler",
    "wof:placetype":"venue"
},
  "geometry": {"coordinates":[7.0417561531,51.0003890991],"type":"Point"}
}