{
  "type": "Feature",
  "properties": {
    "iso:country":"DE",
    "sg:address":"Burgstr. 24",
    "sg:city":"Oberursel",
    "sg:phone":"+49 6171/54136",
    "sg:postcode":"61440",
    "sg:province":"Hessen",
    "wof:name":"B\u00e4ckerei Ruppel-m\u00fcller Gmbh",
    "wof:placetype":"venue"
},
  "geometry": {"coordinates":[8.601552,50.20002],"type":"Point"}
}