{
  "type": "Feature",
  "properties": {
    "iso:country":"DE",
    "sg:address":"Ro\u00dfmarkt 6",
    "sg:city":"Aschaffenburg",
    "sg:phone":"+49 6021/218715",
    "sg:postcode":"63739",
    "sg:province":"Bayern",
    "wof:name":"Moorea Fashion Company",
    "wof:placetype":"venue"
},
  "geometry": {"coordinates":[9.148233,49.976109],"type":"Point"}
}