{
  "type": "Feature",
  "properties": {
    "iso:country":"DE",
    "sg:address":"M\u00fchlenfeldstr.",
    "sg:city":"Wadersloh",
    "sg:phone":"+49 2523/7395",
    "sg:postcode":"59329",
    "sg:province":"Nordrhein-Westfalen",
    "wof:name":"Petras Modeladen",
    "wof:placetype":"venue"
},
  "geometry": {"coordinates":[8.239545,51.736225],"type":"Point"}
}