{
  "type": "Feature",
  "properties": {
    "iso:country":"DE",
    "sg:address":"Eisdorfer Str. 12 a",
    "sg:city":"Bennstedt",
    "sg:phone":"+49 34601/21625",
    "sg:postcode":"06179",
    "sg:province":"Sachsen-Anhalt",
    "wof:name":"Landhaus",
    "wof:placetype":"venue"
},
  "geometry": {"coordinates":[11.8206157684,51.4733200073],"type":"Point"}
}