{
  "type": "Feature",
  "properties": {
    "iso:country":"DE",
    "sg:address":"Berghamer Str. 19",
    "sg:city":"Obing",
    "sg:phone":"+49 8624/89810",
    "sg:postcode":"83119",
    "sg:province":"Bayern",
    "wof:name":"Chiemsee-sailing: Sportswear, Factory Outlets",
    "wof:placetype":"venue"
},
  "geometry": {"coordinates":[12.4140443802,47.9983100891],"type":"Point"}
}