{
  "type": "Feature",
  "properties": {
    "iso:country":"DE",
    "sg:address":"Westparkstr. 106",
    "sg:city":"Krefeld",
    "sg:phone":"+49 2151/753195",
    "sg:postcode":"47803",
    "sg:province":"Nordrhein-Westfalen",
    "wof:name":"Westparkgrill",
    "wof:placetype":"venue"
},
  "geometry": {"coordinates":[6.5419678688,51.3394927979],"type":"Point"}
}