{
  "type": "Feature",
  "properties": {
    "iso:country":"DE",
    "sg:address":"Br\u00fcckenstr. 9",
    "sg:city":"Weinstadt",
    "sg:phone":"+49 7151/600506",
    "sg:postcode":"71384",
    "sg:province":"Baden-W\u00fcrttemberg",
    "wof:name":"H\u00e4ckerm\u00fchle Fam. Leybold",
    "wof:placetype":"venue"
},
  "geometry": {"coordinates":[9.3852319717,48.8168792725],"type":"Point"}
}