{
  "type": "Feature",
  "properties": {
    "iso:country":"DE",
    "sg:address":"Hauptstr. 21",
    "sg:city":"Goldkronach",
    "sg:phone":"+49 9208/381",
    "sg:postcode":"95497",
    "sg:province":"Bayern",
    "wof:name":"Anna Raps",
    "wof:placetype":"venue"
},
  "geometry": {"coordinates":[11.6592464447,49.9938697815],"type":"Point"}
}