{
  "type": "Feature",
  "properties": {
    "iso:country":"DE",
    "sg:address":"Bauernweide 11",
    "sg:city":"Hamburg",
    "sg:phone":"+49 40/702040",
    "sg:postcode":"21149",
    "sg:province":"Hamburg",
    "wof:name":"Hotel Garni Scheideholzer Hof",
    "wof:placetype":"venue"
},
  "geometry": {"coordinates":[9.8505458832,53.4710998535],"type":"Point"}
}