{
  "type": "Feature",
  "properties": {
    "iso:country":"DE",
    "sg:address":"Br\u00fcckenstr. 4",
    "sg:city":"Chemnitz",
    "sg:phone":"+49 371/6949260",
    "sg:postcode":"09111",
    "sg:province":"Sachsen",
    "wof:name":"Multipolster Gmbh & Co. Handels Kg",
    "wof:placetype":"venue"
},
  "geometry": {"coordinates":[12.9254961014,50.8343963623],"type":"Point"}
}