{
  "type": "Feature",
  "properties": {
    "iso:country":"DE",
    "sg:address":"Borndeel 10a",
    "sg:city":"Hamburg",
    "sg:phone":"+49 40/588245",
    "sg:postcode":"22453",
    "sg:province":"Hamburg",
    "wof:name":"Klaus B\u00f6ttcher Gmbh Handelsvertretungen",
    "wof:placetype":"venue"
},
  "geometry": {"coordinates":[9.9486274719,53.6130180359],"type":"Point"}
}