{
  "type": "Feature",
  "properties": {
    "iso:country":"DE",
    "sg:address":"Mettestr. 10a",
    "sg:city":"Wernigerode",
    "sg:phone":"+49 3943/607669",
    "sg:postcode":"38855",
    "sg:province":"Sachsen-Anhalt",
    "wof:name":"J. Sch\u00fctte",
    "wof:placetype":"venue"
},
  "geometry": {"coordinates":[10.788943,51.827412],"type":"Point"}
}