{
  "type": "Feature",
  "properties": {
    "iso:country":"DE",
    "sg:address":"Husmannstr. 4",
    "sg:city":"Gladbeck",
    "sg:phone":"+49 2043/989125",
    "sg:postcode":"45966",
    "sg:province":"Nordrhein-Westfalen",
    "wof:name":"Ulf Wencker Gmbh",
    "wof:placetype":"venue"
},
  "geometry": {"coordinates":[6.962459,51.590481],"type":"Point"}
}