{
  "type": "Feature",
  "properties": {
    "iso:country":"DE",
    "sg:address":"Carl-Spitzweg-Str. 9",
    "sg:city":"Leinfelden-Echterdingen",
    "sg:phone":"+49 711/7545500",
    "sg:postcode":"70771",
    "sg:province":"Baden-W\u00fcrttemberg",
    "wof:name":"Kurt Munz Ingenieur",
    "wof:placetype":"venue"
},
  "geometry": {"coordinates":[9.1240367889,48.7026634216],"type":"Point"}
}