{
  "type": "Feature",
  "properties": {
    "iso:country":"DE",
    "sg:address":"F\u00fcrstenwalder Damm 440",
    "sg:city":"Berlin",
    "sg:phone":"+49 30/6453815",
    "sg:postcode":"12587",
    "sg:province":"Berlin",
    "wof:name":"Reinhard Adam",
    "wof:placetype":"venue"
},
  "geometry": {"coordinates":[13.63589,52.45657],"type":"Point"}
}