{
  "type": "Feature",
  "properties": {
    "iso:country":"DE",
    "sg:address":"Angerweg 1",
    "sg:city":"Olching",
    "sg:phone":"+49 8142/1040",
    "sg:postcode":"82140",
    "sg:province":"Bayern",
    "wof:name":"Efa Wohnbau Gmbh",
    "wof:placetype":"venue"
},
  "geometry": {"coordinates":[11.30671978,48.1997413635],"type":"Point"}
}