{
  "type": "Feature",
  "properties": {
    "iso:country":"DE",
    "sg:address":"Kirchstr. 1",
    "sg:city":"Altusried",
    "sg:phone":"+49 8373/363",
    "sg:postcode":"87452",
    "sg:province":"Bayern",
    "wof:name":"Plus Warenhandels Gmbh & Co. Ohg",
    "wof:placetype":"venue"
},
  "geometry": {"coordinates":[10.2142372131,47.8047142029],"type":"Point"}
}