{
  "type": "Feature",
  "properties": {
    "iso:country":"DE",
    "sg:address":"Logestr. 12",
    "sg:city":"Beverstedt",
    "sg:phone":"+49 4747/337",
    "sg:postcode":"27616",
    "sg:province":"Niedersachsen",
    "wof:name":"Ursula Bruns",
    "wof:placetype":"venue"
},
  "geometry": {"coordinates":[8.820817,53.434017],"type":"Point"}
}