{
  "type": "Feature",
  "properties": {
    "iso:country":"DE",
    "sg:address":"Werftweg 15 a",
    "sg:city":"Oldenburg",
    "sg:postcode":"26135",
    "sg:province":"Niedersachsen",
    "wof:name":"Helgis Verwaltungsges. Mbh",
    "wof:placetype":"venue"
},
  "geometry": {"coordinates":[8.249593,53.140686],"type":"Point"}
}