{
  "type": "Feature",
  "properties": {
    "iso:country":"DE",
    "sg:address":"De-Vos-Str. 27",
    "sg:city":"Itzehoe",
    "sg:phone":"+49 4948/2189610",
    "sg:postcode":"25524",
    "sg:province":"Schleswig-Holstein",
    "wof:name":"Walter Otto M\u00dcller Gmbh & Co. Kg",
    "wof:placetype":"venue"
},
  "geometry": {"coordinates":[9.4910326004,53.904624939],"type":"Point"}
}