{
  "type": "Feature",
  "properties": {
    "iso:country":"DE",
    "sg:address":"Markt 4",
    "sg:city":"Sonnefeld",
    "sg:phone":"+49 9562/6095",
    "sg:postcode":"96242",
    "sg:province":"Bayern",
    "wof:name":"Vereinigte Coburger Sparkassen",
    "wof:placetype":"venue"
},
  "geometry": {"coordinates":[11.13598,50.22298],"type":"Point"}
}