{
  "type": "Feature",
  "properties": {
    "iso:country":"DE",
    "sg:address":"Illtalstr. 15 a",
    "sg:city":"Eppelborn",
    "sg:phone":"+49 6881/6174",
    "sg:postcode":"66571",
    "sg:province":"Saarland",
    "wof:name":"Joachim Sch\u00e4fer Gmbh",
    "wof:placetype":"venue"
},
  "geometry": {"coordinates":[6.948523,49.40976],"type":"Point"}
}