{
  "type": "Feature",
  "properties": {
    "iso:country":"DE",
    "sg:address":"K\u00e4mmererstr. 46",
    "sg:city":"Worms",
    "sg:phone":"+49 6241/920650",
    "sg:postcode":"67547",
    "sg:province":"Rheinland-Pfalz",
    "wof:name":"Bhw Bausparkasse Ag",
    "wof:placetype":"venue"
},
  "geometry": {"coordinates":[8.364229,49.632908],"type":"Point"}
}