{
  "type": "Feature",
  "properties": {
    "iso:country":"DE",
    "sg:address":"Schlo\u00dfstr. 5",
    "sg:city":"Dettelbach",
    "sg:phone":"+49 9324/735",
    "sg:postcode":"97337",
    "sg:province":"Bayern",
    "wof:name":"Ev. Pfarramt Gem. Schernau",
    "wof:placetype":"venue"
},
  "geometry": {"coordinates":[10.1067228317,49.7989883423],"type":"Point"}
}