{
  "type": "Feature",
  "properties": {
    "iso:country":"DE",
    "sg:address":"Lorenzer Str. 10",
    "sg:city":"Lappersdorf",
    "sg:phone":"+49 941/85811",
    "sg:postcode":"93138",
    "sg:province":"Bayern",
    "wof:name":"St. \u00c4gidius-apotheke Inh. Georg Gr\u00fcnwald",
    "wof:placetype":"venue"
},
  "geometry": {"coordinates":[12.055418,49.07251],"type":"Point"}
}