{
  "type": "Feature",
  "properties": {
    "iso:country":"DE",
    "sg:address":"Br\u00fcningstr. 64",
    "sg:city":"Bernkastel-Kues",
    "sg:phone":"+49 6531/91088",
    "sg:postcode":"54470",
    "sg:province":"Rheinland-Pfalz",
    "wof:name":"Der Handyman",
    "wof:placetype":"venue"
},
  "geometry": {"coordinates":[7.0657868385,49.9170341492],"type":"Point"}
}