{
  "type": "Feature",
  "properties": {
    "iso:country":"DE",
    "sg:address":"Hegestieg 12",
    "sg:city":"Hamburg",
    "sg:phone":"+49 40/461046",
    "sg:postcode":"20249",
    "sg:province":"Hamburg",
    "wof:name":"Ingrid Keuneke",
    "wof:placetype":"venue"
},
  "geometry": {"coordinates":[9.9836330414,53.5848884583],"type":"Point"}
}