{
  "type": "Feature",
  "properties": {
    "iso:country":"DE",
    "sg:address":"Franziskastr. 22",
    "sg:city":"Essen",
    "sg:phone":"+49 201/782678",
    "sg:postcode":"45131",
    "sg:province":"Nordrhein-Westfalen",
    "wof:name":"Kath. Beratungsstelle F\u00fcr Werdende M\u00fctter In Not- Und",
    "wof:placetype":"venue"
},
  "geometry": {"coordinates":[7.007363,51.433632],"type":"Point"}
}