{
  "type": "Feature",
  "properties": {
    "iso:country":"DE",
    "sg:address":"Am Ringofen 4",
    "sg:city":"Wuppertal",
    "sg:phone":"+49 2058/981041",
    "sg:postcode":"42327",
    "sg:province":"Nordrhein-Westfalen",
    "wof:name":"P. R. O. Software- Consulting Gmbh",
    "wof:placetype":"venue"
},
  "geometry": {"coordinates":[7.0719618797,51.2651596069],"type":"Point"}
}