{
  "type": "Feature",
  "properties": {
    "iso:country":"DE",
    "sg:address":"Dischinger Str. 2",
    "sg:city":"Neresheim",
    "sg:phone":"+49 7326/7222",
    "sg:postcode":"73450",
    "sg:province":"Baden-W\u00fcrttemberg",
    "wof:name":"Vereinsgastst\u00e4tte Sportverein Neresheim E. V.",
    "wof:placetype":"venue"
},
  "geometry": {"coordinates":[10.3369865417,48.751739502],"type":"Point"}
}