{
  "type": "Feature",
  "properties": {
    "iso:country":"DE",
    "sg:address":"Krailing",
    "sg:city":"Prackenbach",
    "sg:phone":"+49 9942/8466",
    "sg:postcode":"94267",
    "sg:province":"Bayern",
    "wof:name":"Karl Wols",
    "wof:placetype":"venue"
},
  "geometry": {"coordinates":[12.828361,49.095844],"type":"Point"}
}