{
  "type": "Feature",
  "properties": {
    "iso:country":"DE",
    "sg:address":"Holsteiner Chaussee 402",
    "sg:city":"Hamburg",
    "sg:phone":"+49 40/5597910",
    "sg:postcode":"22457",
    "sg:province":"Hamburg",
    "wof:name":"Montgomery Inn",
    "wof:placetype":"venue"
},
  "geometry": {"coordinates":[9.9078845978,53.6474647522],"type":"Point"}
}