{
  "type": "Feature",
  "properties": {
    "iso:country":"DE",
    "sg:address":"Oberkasseler Str. 96",
    "sg:city":"D\u00fcsseldorf",
    "sg:phone":"+49 5201/666246",
    "sg:postcode":"40545",
    "sg:province":"Nordrhein-Westfalen",
    "wof:name":"Weindeele Christoph Nolte",
    "wof:placetype":"venue"
},
  "geometry": {"coordinates":[6.7561559677,51.2325057983],"type":"Point"}
}