{
  "type": "Feature",
  "properties": {
    "iso:country":"DE",
    "sg:address":"Deichstr. 12",
    "sg:city":"Sch\u00f6nebeck",
    "sg:postcode":"39218",
    "sg:province":"Sachsen-Anhalt",
    "wof:name":"Ultra M\u00f6bel Handels Gmbh",
    "wof:placetype":"venue"
},
  "geometry": {"coordinates":[11.750005722,52.0270729065],"type":"Point"}
}