{
  "type": "Feature",
  "properties": {
    "iso:country":"DE",
    "sg:address":"Rosenstr. 5",
    "sg:city":"Osterburg",
    "sg:postcode":"39606",
    "sg:province":"Sachsen-Anhalt",
    "wof:name":"Pflegeheim",
    "wof:placetype":"venue"
},
  "geometry": {"coordinates":[11.75106,52.795509],"type":"Point"}
}