{
  "type": "Feature",
  "properties": {
    "iso:country":"DE",
    "sg:address":"Badstubenweg 8",
    "sg:city":"Munderkingen",
    "sg:postcode":"89597",
    "sg:province":"Baden-W\u00fcrttemberg",
    "wof:name":"Musicline Gunkel & Gedenk Gmbh",
    "wof:placetype":"venue"
},
  "geometry": {"coordinates":[9.6429538727,48.2340965271],"type":"Point"}
}