{
  "type": "Feature",
  "properties": {
    "iso:country":"DE",
    "sg:address":"Ebertzweg 15",
    "sg:city":"Memmingen",
    "sg:phone":"+49 8331/86754",
    "sg:postcode":"87700",
    "sg:province":"Bayern",
    "wof:name":"Georg Huith",
    "wof:placetype":"venue"
},
  "geometry": {"coordinates":[10.182759285,48.0088691711],"type":"Point"}
}