{
  "type": "Feature",
  "properties": {
    "iso:country":"DE",
    "sg:address":"Waldstr. 7",
    "sg:city":"Schrobenhausen",
    "sg:phone":"+49 8252/2582",
    "sg:postcode":"86529",
    "sg:province":"Bayern",
    "wof:name":"Joh. Fr\u00f6hlich",
    "wof:placetype":"venue"
},
  "geometry": {"coordinates":[11.242678,48.567596],"type":"Point"}
}