{
  "type": "Feature",
  "properties": {
    "iso:country":"DE",
    "sg:address":"Im Oberdorf 7",
    "sg:city":"Wallerstein",
    "sg:phone":"+49 9081/7280",
    "sg:postcode":"86757",
    "sg:province":"Bayern",
    "wof:name":"Hans Hiesinger",
    "wof:placetype":"venue"
},
  "geometry": {"coordinates":[10.472688,48.876446],"type":"Point"}
}