{
  "type": "Feature",
  "properties": {
    "iso:country":"DE",
    "sg:address":"Hauptstr. 32",
    "sg:city":"Eningen",
    "sg:phone":"+49 7121/81860",
    "sg:postcode":"72800",
    "sg:province":"Baden-W\u00fcrttemberg",
    "wof:name":"Karl Mayer",
    "wof:placetype":"venue"
},
  "geometry": {"coordinates":[9.2576112747,48.4858551025],"type":"Point"}
}