{
  "type": "Feature",
  "properties": {
    "iso:country":"DE",
    "sg:address":"An der Weidenm\u00fchle 12",
    "sg:city":"Gundersheim",
    "sg:postcode":"67598",
    "sg:province":"Rheinland-Pfalz",
    "wof:name":"Neuenburger Tank- Und Rastst\u00e4tten Gmbh",
    "wof:placetype":"venue"
},
  "geometry": {"coordinates":[8.2042970657,49.6991577148],"type":"Point"}
}