{
  "type": "Feature",
  "properties": {
    "iso:country":"DE",
    "sg:address":"Wahnbachtalstr. 2 a",
    "sg:city":"Siegburg",
    "sg:phone":"+49 2241/69211",
    "sg:postcode":"53721",
    "sg:province":"Nordrhein-Westfalen",
    "wof:name":"Blitz-fritz Schneppenheim Gmbh",
    "wof:placetype":"venue"
},
  "geometry": {"coordinates":[7.2207970619,50.7876205444],"type":"Point"}
}