{
  "type": "Feature",
  "properties": {
    "iso:country":"DE",
    "sg:address":"Eberle-K\u00f6gl-Str. 19",
    "sg:city":"Marktoberdorf",
    "sg:phone":"+49 8342/2683",
    "sg:postcode":"87616",
    "sg:province":"Bayern",
    "wof:name":"L. Kessler",
    "wof:placetype":"venue"
},
  "geometry": {"coordinates":[10.6214570999,47.7781562805],"type":"Point"}
}