{
  "type": "Feature",
  "properties": {
    "iso:country":"DE",
    "sg:address":"Residenzstr. 21",
    "sg:city":"M\u00fcnchen",
    "sg:postcode":"80333",
    "sg:province":"Bayern",
    "wof:name":"Tlm Kaffee-produkte Vertriebsgesellschaft Mbh",
    "wof:placetype":"venue"
},
  "geometry": {"coordinates":[11.5772600174,48.1406517029],"type":"Point"}
}