{
  "type": "Feature",
  "properties": {
    "iso:country":"DE",
    "sg:address":"B\u00fcssemstr. 17",
    "sg:city":"Essen",
    "sg:phone":"+49 201/511745",
    "sg:postcode":"45276",
    "sg:province":"Nordrhein-Westfalen",
    "wof:name":"Frank Klauwer",
    "wof:placetype":"venue"
},
  "geometry": {"coordinates":[7.068449,51.445702],"type":"Point"}
}