{
  "type": "Feature",
  "properties": {
    "iso:country":"DE",
    "sg:address":"Holzweg 3",
    "sg:city":"Brilon",
    "sg:phone":"+49 2991/304",
    "sg:postcode":"59929",
    "sg:province":"Nordrhein-Westfalen",
    "wof:name":"Brune Maschinenbau Gmbh",
    "wof:placetype":"venue"
},
  "geometry": {"coordinates":[8.723328,51.432762],"type":"Point"}
}