{
  "type": "Feature",
  "properties": {
    "iso:country":"DE",
    "sg:address":"D\u00fcsseldorfer Str. 15",
    "sg:city":"Frankfurt",
    "sg:phone":"+49 69/233506",
    "sg:postcode":"60329",
    "sg:province":"Hessen",
    "wof:name":"A. Kostis",
    "wof:placetype":"venue"
},
  "geometry": {"coordinates":[8.661188,50.108948],"type":"Point"}
}