{
  "type": "Feature",
  "properties": {
    "iso:country":"DE",
    "sg:address":"Bustedter Str.",
    "sg:city":"B\u00fcnde",
    "sg:phone":"+49 5223/87539",
    "sg:postcode":"32257",
    "sg:province":"Nordrhein-Westfalen",
    "wof:name":"Saluec Gesellschaft F\u00fcr Umweltschutztechnik Und",
    "wof:placetype":"venue"
},
  "geometry": {"coordinates":[8.5981054306,52.1826858521],"type":"Point"}
}