{
  "type": "Feature",
  "properties": {
    "iso:country":"DE",
    "sg:address":"Schelpmilser Weg 2",
    "sg:city":"Bielefeld",
    "sg:postcode":"33609",
    "sg:province":"Nordrhein-Westfalen",
    "wof:name":"Walkenhorst Metallbau- Und Handelsges. Mbh",
    "wof:placetype":"venue"
},
  "geometry": {"coordinates":[8.602012,52.03804],"type":"Point"}
}