{
  "type": "Feature",
  "properties": {
    "iso:country":"DE",
    "sg:address":"Wedekindstr. 34",
    "sg:city":"Hannover",
    "sg:phone":"+49 511/313252",
    "sg:postcode":"30161",
    "sg:province":"Niedersachsen",
    "wof:name":"B\u00f6ker",
    "wof:placetype":"venue"
},
  "geometry": {"coordinates":[9.7475442886,52.3856430054],"type":"Point"}
}