{
  "type": "Feature",
  "properties": {
    "iso:country":"DE",
    "sg:address":"Brockhagener Str. 21",
    "sg:city":"Bielefeld",
    "sg:postcode":"33649",
    "sg:province":"Nordrhein-Westfalen",
    "wof:name":"Brinkmann Verwaltungs Gmbh",
    "wof:placetype":"venue"
},
  "geometry": {"coordinates":[8.484317,51.987469],"type":"Point"}
}