{
  "type": "Feature",
  "properties": {
    "iso:country":"DE",
    "sg:address":"M\u00fchlenstr. 8",
    "sg:city":"Lahntal",
    "sg:phone":"+49 6420/414",
    "sg:postcode":"35094",
    "sg:province":"Hessen",
    "wof:name":"Margot M\u00fcller",
    "wof:placetype":"venue"
},
  "geometry": {"coordinates":[8.6687631607,50.8476715088],"type":"Point"}
}