{
  "type": "Feature",
  "properties": {
    "iso:country":"DE",
    "sg:address":"Br\u00fcmmelkamp 19",
    "sg:city":"Winsen",
    "sg:phone":"+49 4171/71244",
    "sg:postcode":"21423",
    "sg:province":"Niedersachsen",
    "wof:name":"Ernst-august Bardowicks",
    "wof:placetype":"venue"
},
  "geometry": {"coordinates":[10.206072,53.331345],"type":"Point"}
}