{
  "type": "Feature",
  "properties": {
    "iso:country":"DE",
    "sg:address":"Petersstr. 28",
    "sg:city":"Crimmitschau",
    "sg:phone":"+49 3762/2309",
    "sg:postcode":"08451",
    "sg:province":"Sachsen",
    "wof:name":"Erich Vogel",
    "wof:placetype":"venue"
},
  "geometry": {"coordinates":[12.3876,50.824219],"type":"Point"}
}