{
  "type": "Feature",
  "properties": {
    "iso:country":"DE",
    "sg:address":"Friedrichstaler Str. 1a",
    "sg:city":"Gummersbach",
    "sg:phone":"+49 2261/76556",
    "sg:postcode":"51645",
    "sg:province":"Nordrhein-Westfalen",
    "wof:name":"B. Ley",
    "wof:placetype":"venue"
},
  "geometry": {"coordinates":[7.5682702065,51.0011177063],"type":"Point"}
}