{
  "type": "Feature",
  "properties": {
    "iso:country":"DE",
    "sg:address":"Kirchh\u00f6rder Str. 78",
    "sg:city":"Dortmund",
    "sg:phone":"+49 231/732327",
    "sg:postcode":"44229",
    "sg:province":"Nordrhein-Westfalen",
    "wof:name":"Bommert Bestattungen",
    "wof:placetype":"venue"
},
  "geometry": {"coordinates":[7.477237,51.459152],"type":"Point"}
}