{
  "type": "Feature",
  "properties": {
    "iso:country":"DE",
    "sg:address":"Am Schillbach 20",
    "sg:city":"Niefern-\u00d6schelbronn",
    "sg:phone":"+49 7233/1783",
    "sg:postcode":"75223",
    "sg:province":"Baden-W\u00fcrttemberg",
    "wof:name":"Heinz Krie\u00dfler",
    "wof:placetype":"venue"
},
  "geometry": {"coordinates":[8.780152,48.91114],"type":"Point"}
}