{
  "type": "Feature",
  "properties": {
    "iso:country":"DE",
    "sg:address":"Schwaibachtal 1",
    "sg:city":"Gengenbach",
    "sg:phone":"+49 7803/2257",
    "sg:postcode":"77723",
    "sg:province":"Baden-W\u00fcrttemberg",
    "wof:name":"Oskar Schilli",
    "wof:placetype":"venue"
},
  "geometry": {"coordinates":[8.033554,48.392235],"type":"Point"}
}