{
  "type": "Feature",
  "properties": {
    "iso:country":"DE",
    "sg:address":"Hehlertstr. 1",
    "sg:city":"Parsau",
    "sg:phone":"+49 5368/834",
    "sg:postcode":"38470",
    "sg:province":"Niedersachsen",
    "wof:name":"Ev. Pfarramt Freikirchl. Gem. Parsau",
    "wof:placetype":"venue"
},
  "geometry": {"coordinates":[10.8907594681,52.5344810486],"type":"Point"}
}