{
  "type": "Feature",
  "properties": {
    "iso:country":"DE",
    "sg:address":"Marktstr. 9",
    "sg:city":"Wiesloch",
    "sg:phone":"+49 6222/50055",
    "sg:postcode":"69168",
    "sg:province":"Baden-W\u00fcrttemberg",
    "wof:name":"Sport Hans-joachim Wagner",
    "wof:placetype":"venue"
},
  "geometry": {"coordinates":[8.699394,49.294464],"type":"Point"}
}