{
  "type": "Feature",
  "properties": {
    "iso:country":"DE",
    "sg:address":"Rainwiesen 23",
    "sg:city":"Remseck",
    "sg:phone":"+49 7146/9656",
    "sg:postcode":"71686",
    "sg:province":"Baden-W\u00fcrttemberg",
    "wof:name":"Stiller Gmbh",
    "wof:placetype":"venue"
},
  "geometry": {"coordinates":[9.2610902786,48.8929290771],"type":"Point"}
}