{
  "type": "Feature",
  "properties": {
    "iso:country":"DE",
    "sg:address":"Kirchwender Str. 14",
    "sg:city":"Hannover",
    "sg:phone":"+49 511/854998",
    "sg:postcode":"30175",
    "sg:province":"Niedersachsen",
    "wof:name":"Rex Immobilien Vertriebs Gmbh",
    "wof:placetype":"venue"
},
  "geometry": {"coordinates":[9.7529706955,52.3753318787],"type":"Point"}
}