{
  "type": "Feature",
  "properties": {
    "iso:country":"DE",
    "sg:address":"Deutz-M\u00fclheimer Str. 132",
    "sg:city":"K\u00f6ln",
    "sg:phone":"+49 221/8879020",
    "sg:postcode":"51063",
    "sg:province":"Nordrhein-Westfalen",
    "wof:name":"Sbv Schiwora Und Bachem Verwaltungs Gmbh",
    "wof:placetype":"venue"
},
  "geometry": {"coordinates":[6.9864001274,50.9483985901],"type":"Point"}
}