{
  "type": "Feature",
  "properties": {
    "iso:country":"DE",
    "sg:address":"Langgasse 14",
    "sg:city":"Gr\u00fcnstadt",
    "sg:phone":"+49 6359/6805",
    "sg:postcode":"67269",
    "sg:province":"Rheinland-Pfalz",
    "wof:name":"Historisches Gew\u00f6lbe",
    "wof:placetype":"venue"
},
  "geometry": {"coordinates":[8.1617803574,49.5781097412],"type":"Point"}
}