{
  "type": "Feature",
  "properties": {
    "iso:country":"DE",
    "sg:address":"Rochusstr. 23",
    "sg:city":"D\u00fcsseldorf",
    "sg:phone":"+49 211/4932660",
    "sg:postcode":"40479",
    "sg:province":"Nordrhein-Westfalen",
    "wof:name":"Fgh F\u00f6rderungsgesellschaft F\u00fcr Haustechnik Mbh",
    "wof:placetype":"venue"
},
  "geometry": {"coordinates":[6.7850928307,51.2345085144],"type":"Point"}
}