{
  "type": "Feature",
  "properties": {
    "iso:country":"DE",
    "sg:address":"Magdeburger Str. 21",
    "sg:city":"Pl\u00f6tzky",
    "sg:postcode":"39245",
    "sg:province":"Sachsen-Anhalt",
    "wof:name":"Evangelisches Pfarramt",
    "wof:placetype":"venue"
},
  "geometry": {"coordinates":[11.800778389,52.0525550842],"type":"Point"}
}