{
  "type": "Feature",
  "properties": {
    "iso:country":"DE",
    "sg:address":"Lucherweg 3",
    "sg:city":"Speicher",
    "sg:phone":"+49 6562/3159",
    "sg:postcode":"54662",
    "sg:province":"Rheinland-Pfalz",
    "wof:name":"W. H. Brummer Steuerberater",
    "wof:placetype":"venue"
},
  "geometry": {"coordinates":[6.6453900337,49.9328155518],"type":"Point"}
}