{
  "type": "Feature",
  "properties": {
    "iso:country":"DE",
    "sg:address":"Eibseestr. 13",
    "sg:city":"Bayreuth",
    "sg:phone":"+49 921/44586",
    "sg:postcode":"95445",
    "sg:province":"Bayern",
    "wof:name":"Dr. Walter Weinhold Tierarzt",
    "wof:placetype":"venue"
},
  "geometry": {"coordinates":[11.5433206558,49.9417724609],"type":"Point"}
}