{
  "type": "Feature",
  "properties": {
    "iso:country":"DE",
    "sg:address":"Str\u00f6her Str. 6",
    "sg:city":"Varrel",
    "sg:phone":"+49 4274/312",
    "sg:postcode":"27259",
    "sg:province":"Niedersachsen",
    "wof:name":"Fritz Nuttelmann",
    "wof:placetype":"venue"
},
  "geometry": {"coordinates":[8.72496,52.615131],"type":"Point"}
}