{
  "type": "Feature",
  "properties": {
    "iso:country":"DE",
    "sg:address":"Senefelderstr. 19/a",
    "sg:city":"Stuttgart",
    "sg:phone":"+49 711",
    "sg:postcode":"70178",
    "sg:province":"Baden-W\u00fcrttemberg",
    "wof:name":"Uwer Kommunikation",
    "wof:placetype":"venue"
},
  "geometry": {"coordinates":[9.16407,48.770802],"type":"Point"}
}