{
  "type": "Feature",
  "properties": {
    "iso:country":"DE",
    "sg:address":"Hauptstr. 31",
    "sg:city":"Viersen",
    "sg:phone":"+49 2162/17368",
    "sg:postcode":"41747",
    "sg:province":"Nordrhein-Westfalen",
    "wof:name":"M & S Mode Gmbh",
    "wof:placetype":"venue"
},
  "geometry": {"coordinates":[6.38825,51.257526],"type":"Point"}
}