{
  "type": "Feature",
  "properties": {
    "iso:country":"DE",
    "sg:address":"Jakobstr. 36",
    "sg:city":"Chemnitz",
    "sg:phone":"+49 371/444430",
    "sg:postcode":"09130",
    "sg:province":"Sachsen",
    "wof:name":"Evr Reisen Gmbh",
    "wof:placetype":"venue"
},
  "geometry": {"coordinates":[12.9380283356,50.8322868347],"type":"Point"}
}