{
  "type": "Feature",
  "properties": {
    "iso:country":"DE",
    "sg:address":"Eduard-Rhein-Str. 3",
    "sg:city":"K\u00f6nigswinter",
    "sg:phone":"+49 4922/4492390",
    "sg:postcode":"53639",
    "sg:province":"Nordrhein-Westfalen",
    "wof:name":"J K Licht Gmbh",
    "wof:placetype":"venue"
},
  "geometry": {"coordinates":[7.276031,50.696545],"type":"Point"}
}