{
  "type": "Feature",
  "properties": {
    "iso:country":"DE",
    "sg:address":"Emmerich-Josef-Str. 42",
    "sg:city":"Frankfurt",
    "sg:phone":"+49 69/312350",
    "sg:postcode":"65929",
    "sg:province":"Hessen",
    "wof:name":"Hoover Universal Jci Beteiligungs-gmbh",
    "wof:placetype":"venue"
},
  "geometry": {"coordinates":[8.545885,50.100609],"type":"Point"}
}