{
  "type": "Feature",
  "properties": {
    "iso:country":"DE",
    "sg:address":"Kampstr. 50",
    "sg:city":"Gevelsberg",
    "sg:phone":"+49 2332/3211",
    "sg:postcode":"58285",
    "sg:province":"Nordrhein-Westfalen",
    "wof:name":"Hans-werner Masuch",
    "wof:placetype":"venue"
},
  "geometry": {"coordinates":[7.331019,51.31459],"type":"Point"}
}