{
  "type": "Feature",
  "properties": {
    "iso:country":"DE",
    "sg:address":"Im Lehmp\u00fctt 11",
    "sg:city":"Goch",
    "sg:phone":"+49 2823/2493",
    "sg:postcode":"47574",
    "sg:province":"Nordrhein-Westfalen",
    "wof:name":"Sicherheit Jetzt F\u00fcr Alle M\u00f6glich",
    "wof:placetype":"venue"
},
  "geometry": {"coordinates":[6.118173,51.696457],"type":"Point"}
}