{
  "type": "Feature",
  "properties": {
    "iso:country":"DE",
    "sg:address":"D\u00fcsseldorfer Str. 10",
    "sg:city":"Meerbusch",
    "sg:phone":"+49 2132/960688",
    "sg:postcode":"40667",
    "sg:province":"Nordrhein-Westfalen",
    "wof:name":"Lee Cooper Germany Gmbh",
    "wof:placetype":"venue"
},
  "geometry": {"coordinates":[6.690315,51.250713],"type":"Point"}
}