{
  "type": "Feature",
  "properties": {
    "iso:country":"DE",
    "sg:address":"Hollstadt",
    "sg:city":"Hollstadt",
    "sg:phone":"+49 9773/786",
    "sg:postcode":"97618",
    "sg:province":"Bayern",
    "wof:name":"Volksbank Bad Neustadt Eg",
    "wof:placetype":"venue"
},
  "geometry": {"coordinates":[10.290115,50.352554],"type":"Point"}
}