{
  "type": "Feature",
  "properties": {
    "iso:country":"DE",
    "sg:address":"Bregstr. 1",
    "sg:city":"Furtwangen",
    "sg:phone":"+49 7723/630",
    "sg:postcode":"78120",
    "sg:province":"Baden-W\u00fcrttemberg",
    "wof:name":"S. Siedle & S\u00f6hne Stiftung & Co. Gmbh",
    "wof:placetype":"venue"
},
  "geometry": {"coordinates":[8.2030067444,48.0490837097],"type":"Point"}
}