{
  "type": "Feature",
  "properties": {
    "iso:country":"DE",
    "sg:address":"B\u00fcrgerstr. 75",
    "sg:city":"Berlin",
    "sg:phone":"+49 30/6251675",
    "sg:postcode":"12347",
    "sg:province":"Berlin",
    "wof:name":"Alfred Wulff",
    "wof:placetype":"venue"
},
  "geometry": {"coordinates":[13.4361181259,52.4613075256],"type":"Point"}
}