{
  "type": "Feature",
  "properties": {
    "iso:country":"DE",
    "sg:address":"Weide 16",
    "sg:city":"Bim\u00f6hlen",
    "sg:phone":"+49 4327/812",
    "sg:postcode":"24576",
    "sg:province":"Schleswig-Holstein",
    "wof:name":"Hauke Carstensen",
    "wof:placetype":"venue"
},
  "geometry": {"coordinates":[10.027815,53.939358],"type":"Point"}
}