{
  "type": "Feature",
  "properties": {
    "iso:country":"DE",
    "sg:address":"Altenstr. 5",
    "sg:city":"Annweiler",
    "sg:phone":"+49 6346/7374",
    "sg:postcode":"76855",
    "sg:province":"Rheinland-Pfalz",
    "wof:name":"E. Hertha-benn Masseurin",
    "wof:placetype":"venue"
},
  "geometry": {"coordinates":[7.961787,49.203411],"type":"Point"}
}