{
  "type": "Feature",
  "properties": {
    "iso:country":"DE",
    "sg:address":"Wilmersdorfer Str. 58",
    "sg:city":"Berlin",
    "sg:phone":"+49 30/3243661",
    "sg:postcode":"10627",
    "sg:province":"Berlin",
    "wof:name":"Wolfgang B\u00fcsch Rechtsanw\u00e4lte Und Notar",
    "wof:placetype":"venue"
},
  "geometry": {"coordinates":[13.3061676025,52.5075645447],"type":"Point"}
}