{
  "type": "Feature",
  "properties": {
    "iso:country":"DE",
    "sg:address":"Kuchelstr. 40",
    "sg:city":"Kiel",
    "sg:phone":"+49 431/721818",
    "sg:postcode":"24148",
    "sg:province":"Schleswig-Holstein",
    "wof:name":"Ellerbeker B\u00fcttgill Von 1666 E. V.",
    "wof:placetype":"venue"
},
  "geometry": {"coordinates":[10.1765804291,54.3238258362],"type":"Point"}
}