{
  "type": "Feature",
  "properties": {
    "iso:country":"DE",
    "sg:address":"August-Bebel-Str. 11",
    "sg:city":"Altenburg",
    "sg:phone":"+49 3447/311822",
    "sg:postcode":"04600",
    "sg:province":"Th\u00fcringen",
    "wof:name":"Gerhard Hendel",
    "wof:placetype":"venue"
},
  "geometry": {"coordinates":[12.43294,50.980568],"type":"Point"}
}