{
  "type": "Feature",
  "properties": {
    "iso:country":"DE",
    "sg:address":"M\u00e4rkische Str.1",
    "sg:city":"Woltersdorf",
    "sg:phone":"+49 3362/29256",
    "sg:postcode":"15569",
    "sg:province":"Brandenburg",
    "wof:name":"Homepage Des Erc-96",
    "wof:placetype":"venue"
},
  "geometry": {"coordinates":[13.739218,52.454971],"type":"Point"}
}