{
  "type": "Feature",
  "properties": {
    "iso:country":"DE",
    "sg:address":"Lindenstr. 37",
    "sg:city":"Calau",
    "sg:postcode":"03205",
    "sg:province":"Brandenburg",
    "wof:name":"Quelle-agentur Calau",
    "wof:placetype":"venue"
},
  "geometry": {"coordinates":[13.9499979019,51.7443008423],"type":"Point"}
}