{
  "type": "Feature",
  "properties": {
    "iso:country":"DE",
    "sg:address":"Cuxhavener Str. 90b",
    "sg:city":"Cuxhaven",
    "sg:phone":"+49 4721/25270",
    "sg:postcode":"27476",
    "sg:province":"Niedersachsen",
    "wof:name":"Duhner Hansagrill",
    "wof:placetype":"venue"
},
  "geometry": {"coordinates":[8.6448688507,53.8858261108],"type":"Point"}
}