{
  "type": "Feature",
  "properties": {
    "iso:country":"DE",
    "sg:address":"Industriestr. 7",
    "sg:city":"N\u00f6rten-Hardenberg",
    "sg:postcode":"37176",
    "sg:province":"Niedersachsen",
    "wof:name":"Massivbau- Bau- Und Sandstrahl Gmbh",
    "wof:placetype":"venue"
},
  "geometry": {"coordinates":[9.9375829697,51.6216773987],"type":"Point"}
}