{
  "type": "Feature",
  "properties": {
    "iso:country":"DE",
    "sg:address":"Schlo\u00dfbergstr. 5",
    "sg:city":"Anzing",
    "sg:phone":"+49 8121/3087",
    "sg:postcode":"85646",
    "sg:province":"Bayern",
    "wof:name":"Fritz Bachmayer",
    "wof:placetype":"venue"
},
  "geometry": {"coordinates":[11.843795,48.134884],"type":"Point"}
}