{
  "type": "Feature",
  "properties": {
    "iso:country":"DE",
    "sg:address":"Talbr\u00fcckenstr. 67",
    "sg:city":"Bielefeld",
    "sg:phone":"+49 521/81417",
    "sg:postcode":"33611",
    "sg:province":"Nordrhein-Westfalen",
    "wof:name":"I. Deppe",
    "wof:placetype":"venue"
},
  "geometry": {"coordinates":[8.5623521805,52.055519104],"type":"Point"}
}