{
  "type": "Feature",
  "properties": {
    "iso:country":"DE",
    "sg:address":"Am Eggenkopf 15",
    "sg:city":"Kirchhundem",
    "sg:phone":"+49 2723/72988",
    "sg:postcode":"57399",
    "sg:province":"Nordrhein-Westfalen",
    "wof:name":"Schmidtchen Immobilienmakler",
    "wof:placetype":"venue"
},
  "geometry": {"coordinates":[8.1630563736,51.0701408386],"type":"Point"}
}