{
  "type": "Feature",
  "properties": {
    "iso:country":"DE",
    "sg:address":"Hauptstr. 21",
    "sg:city":"Buch",
    "sg:phone":"+49 8709/95888",
    "sg:postcode":"84172",
    "sg:province":"Bayern",
    "wof:name":"Apotheke Am Erlbach E. K.",
    "wof:placetype":"venue"
},
  "geometry": {"coordinates":[10.17947,48.225311],"type":"Point"}
}