{
  "type": "Feature",
  "properties": {
    "iso:country":"DE",
    "sg:address":"Egerl\u00e4nder Str. 14",
    "sg:city":"Burglengenfeld",
    "sg:phone":"+49 9471/8959",
    "sg:postcode":"93133",
    "sg:province":"Bayern",
    "wof:name":"Reinhard Sertl",
    "wof:placetype":"venue"
},
  "geometry": {"coordinates":[12.036506,49.200447],"type":"Point"}
}