{
  "type": "Feature",
  "properties": {
    "iso:country":"DE",
    "sg:address":"Steinheilstr. 12",
    "sg:city":"Ingolstadt",
    "sg:phone":"+49 841/65555",
    "sg:postcode":"85053",
    "sg:province":"Bayern",
    "wof:name":"Golf Wagner Gmbh",
    "wof:placetype":"venue"
},
  "geometry": {"coordinates":[11.4696140289,48.7416687012],"type":"Point"}
}