{
  "type": "Feature",
  "properties": {
    "iso:country":"DE",
    "sg:address":"Emil-M\u00f6rsch-Weg 64",
    "sg:city":"Metzingen",
    "sg:phone":"+49 7123/42029",
    "sg:postcode":"72555",
    "sg:province":"Baden-W\u00fcrttemberg",
    "wof:name":"Johannes B. R\u00fcdrich Ingenieur",
    "wof:placetype":"venue"
},
  "geometry": {"coordinates":[9.29847,48.537865],"type":"Point"}
}