{
  "type": "Feature",
  "properties": {
    "iso:country":"DE",
    "sg:address":"Holtener Str. 88",
    "sg:city":"Oberhausen",
    "sg:phone":"+49 208/645779",
    "sg:postcode":"46145",
    "sg:province":"Nordrhein-Westfalen",
    "wof:name":"Otto Echterbruck",
    "wof:placetype":"venue"
},
  "geometry": {"coordinates":[6.8485460281,51.5210342407],"type":"Point"}
}