{
  "type": "Feature",
  "properties": {
    "iso:country":"DE",
    "sg:address":"Sebaldplatz 5",
    "sg:city":"Schw\u00e4bisch Gm\u00fcnd",
    "sg:phone":"+49 7171/61434",
    "sg:postcode":"73525",
    "sg:province":"Baden-W\u00fcrttemberg",
    "wof:name":"Hildegard Schmid Heissmangel",
    "wof:placetype":"venue"
},
  "geometry": {"coordinates":[9.8000574112,48.7964668274],"type":"Point"}
}