{
  "type": "Feature",
  "properties": {
    "iso:country":"DE",
    "sg:address":"Stra\u00dfburger Allee 18",
    "sg:city":"Erkelenz",
    "sg:phone":"+49 2431/9410",
    "sg:postcode":"41812",
    "sg:province":"Nordrhein-Westfalen",
    "wof:name":"Elitegroup Computer Systems Gmbh",
    "wof:placetype":"venue"
},
  "geometry": {"coordinates":[6.308056,51.061199],"type":"Point"}
}