{
  "type": "Feature",
  "properties": {
    "iso:country":"DE",
    "sg:address":"Dornspachstr. 37",
    "sg:city":"Zittau",
    "sg:phone":"+49 3583/703240",
    "sg:postcode":"02763",
    "sg:province":"Sachsen",
    "wof:name":"Erika Wagner",
    "wof:placetype":"venue"
},
  "geometry": {"coordinates":[14.8164978027,50.9030342102],"type":"Point"}
}