{
  "type": "Feature",
  "properties": {
    "iso:country":"DE",
    "sg:address":"Kurt-Schlosser-Str. 12",
    "sg:city":"Riesa",
    "sg:phone":"+49 3525/737959",
    "sg:postcode":"01591",
    "sg:province":"Sachsen",
    "wof:name":"L. Steinchen",
    "wof:placetype":"venue"
},
  "geometry": {"coordinates":[13.261106,51.319263],"type":"Point"}
}