{
  "type": "Feature",
  "properties": {
    "iso:country":"DE",
    "sg:address":"Neust\u00e4dter Str. 7",
    "sg:city":"Weiden",
    "sg:phone":"+49 961/32095",
    "sg:postcode":"92637",
    "sg:province":"Bayern",
    "wof:name":"W. Kusterer",
    "wof:placetype":"venue"
},
  "geometry": {"coordinates":[12.1633491516,49.6920776367],"type":"Point"}
}