{
  "type": "Feature",
  "properties": {
    "iso:country":"DE",
    "sg:address":"Frankfurter Str. 79",
    "sg:city":"Darmstadt",
    "sg:phone":"+49 6151/77000",
    "sg:postcode":"64293",
    "sg:province":"Hessen",
    "wof:name":"Rwl Langer Hotel- Restaurant Ohg",
    "wof:placetype":"venue"
},
  "geometry": {"coordinates":[8.6525087357,49.8869171143],"type":"Point"}
}