{
  "type": "Feature",
  "properties": {
    "iso:country":"DE",
    "sg:address":"Gothaer Str. 37",
    "sg:city":"M\u00fchlberg",
    "sg:phone":"+49 36256/20248",
    "sg:postcode":"99869",
    "sg:province":"Th\u00fcringen",
    "wof:name":"Agrargenossenschaft Drei Gleichen M\u00fchlberg Eg",
    "wof:placetype":"venue"
},
  "geometry": {"coordinates":[10.81748,50.869122],"type":"Point"}
}