{
  "type": "Feature",
  "properties": {
    "iso:country":"DE",
    "sg:address":"Elverdisser Str. 313",
    "sg:city":"Herford",
    "sg:phone":"+49 5221/979480",
    "sg:postcode":"32052",
    "sg:province":"Nordrhein-Westfalen",
    "wof:name":"Otto Kern Gmbh",
    "wof:placetype":"venue"
},
  "geometry": {"coordinates":[8.653019,52.082623],"type":"Point"}
}