{
  "type": "Feature",
  "properties": {
    "iso:country":"DE",
    "sg:address":"Max-Reger-Str. 6",
    "sg:city":"Dorsten",
    "sg:phone":"+49 2362/793429",
    "sg:postcode":"46282",
    "sg:province":"Nordrhein-Westfalen",
    "wof:name":"Aktien, W\u00e4hrungen, Gold, Dollar Oder Andere",
    "wof:placetype":"venue"
},
  "geometry": {"coordinates":[6.987793,51.653755],"type":"Point"}
}