{
  "type": "Feature",
  "properties": {
    "iso:country":"DE",
    "sg:address":"Berliner Chaussee 1",
    "sg:city":"Magdeburg",
    "sg:phone":"+49 391/8115637",
    "sg:postcode":"39114",
    "sg:province":"Sachsen-Anhalt",
    "wof:name":"K\u00e4seglocke Schnellbistro Inh. Torsten Klemann",
    "wof:placetype":"venue"
},
  "geometry": {"coordinates":[11.6835594177,52.1312713623],"type":"Point"}
}