{
  "type": "Feature",
  "properties": {
    "iso:country":"DE",
    "sg:address":"Sa\u00dfnitzer Str. 31",
    "sg:city":"Osnabr\u00fcck",
    "sg:phone":"+49 541/67770",
    "sg:postcode":"49090",
    "sg:province":"Niedersachsen",
    "wof:name":"Stadtbibliothek Haste",
    "wof:placetype":"venue"
},
  "geometry": {"coordinates":[8.049593,52.308754],"type":"Point"}
}