{
  "type": "Feature",
  "properties": {
    "iso:country":"DE",
    "sg:address":"Weimarer Str. 2",
    "sg:city":"C\u00f6lbe",
    "sg:phone":"+49 6421/82203",
    "sg:postcode":"35091",
    "sg:province":"Hessen",
    "wof:name":"Ev. Pfarramt Ii C\u00f6lbe",
    "wof:placetype":"venue"
},
  "geometry": {"coordinates":[8.7794981003,50.8526077271],"type":"Point"}
}