{
  "type": "Feature",
  "properties": {
    "iso:country":"DE",
    "sg:address":"H\u00f6rgensweg",
    "sg:city":"Hamburg",
    "sg:postcode":"22523",
    "sg:province":"Hamburg",
    "wof:name":"Praktiker Bau- Und Heimwerkermarkt",
    "wof:placetype":"venue"
},
  "geometry": {"coordinates":[9.9000339508,53.619846344],"type":"Point"}
}