{
  "type": "Feature",
  "properties": {
    "iso:country":"DE",
    "sg:address":"St.-Georgener-Str. 9",
    "sg:city":"Freiburg",
    "sg:phone":"+49 761/474917",
    "sg:postcode":"79111",
    "sg:province":"Baden-W\u00fcrttemberg",
    "wof:name":"Tiroler Stuben",
    "wof:placetype":"venue"
},
  "geometry": {"coordinates":[7.8005309105,47.9879264832],"type":"Point"}
}