{
  "type": "Feature",
  "properties": {
    "iso:country":"DE",
    "sg:address":"Ortsstr. 10a",
    "sg:city":"Heilingen",
    "sg:phone":"+49 36742/60144",
    "sg:postcode":"07407",
    "sg:province":"Th\u00fcringen",
    "wof:name":"H.-j. B\u00e4hring",
    "wof:placetype":"venue"
},
  "geometry": {"coordinates":[11.4607610703,50.7712211609],"type":"Point"}
}