{
  "type": "Feature",
  "properties": {
    "iso:country":"DE",
    "sg:address":"Gr\u00e4ulinger Str. 103",
    "sg:city":"D\u00fcsseldorf",
    "sg:phone":"+49 211/282051",
    "sg:postcode":"40625",
    "sg:province":"Nordrhein-Westfalen",
    "wof:name":"Rheinische Schule F\u00fcr Schwerh\u00f6rige",
    "wof:placetype":"venue"
},
  "geometry": {"coordinates":[6.8587031364,51.2429847717],"type":"Point"}
}