{
  "type": "Feature",
  "properties": {
    "iso:country":"DE",
    "sg:address":"Hauptstr. 79",
    "sg:city":"Lengenfeld unterm Stein",
    "sg:phone":"+49 36027/70337",
    "sg:postcode":"99976",
    "sg:province":"Th\u00fcringen",
    "wof:name":"Martin Hardegen",
    "wof:placetype":"venue"
},
  "geometry": {"coordinates":[10.224621,51.212887],"type":"Point"}
}