{
  "type": "Feature",
  "properties": {
    "iso:country":"DE",
    "sg:address":"Schweinauer Hauptstr. 110",
    "sg:city":"N\u00fcrnberg",
    "sg:phone":"+49 911/6200228",
    "sg:postcode":"90441",
    "sg:province":"Bayern",
    "wof:name":"Speisegastst\u00e4tte Seitzengarten",
    "wof:placetype":"venue"
},
  "geometry": {"coordinates":[11.0429906845,49.428024292],"type":"Point"}
}