{
  "type": "Feature",
  "properties": {
    "iso:country":"DE",
    "sg:address":"Steinhofweg 33 a",
    "sg:city":"Heidelberg",
    "sg:phone":"+49 6221/775005",
    "sg:postcode":"69123",
    "sg:province":"Baden-W\u00fcrttemberg",
    "wof:name":"Eurosysteam Europ\u00e4ische Gesellschaft F\u00fcr Systemische",
    "wof:placetype":"venue"
},
  "geometry": {"coordinates":[8.6511793137,49.396572113],"type":"Point"}
}