{
  "type": "Feature",
  "properties": {
    "iso:country":"DE",
    "sg:address":"Zur Osterheide 1",
    "sg:city":"Garlstorf",
    "sg:phone":"+49 4172/5564",
    "sg:postcode":"21376",
    "sg:province":"Niedersachsen",
    "wof:name":"Guderian & Schl\u00fcter",
    "wof:placetype":"venue"
},
  "geometry": {"coordinates":[10.103778,53.237411],"type":"Point"}
}