{
  "type": "Feature",
  "properties": {
    "iso:country":"DE",
    "sg:address":"Burgstr. 30",
    "sg:city":"Alpen",
    "sg:phone":"+49 2802/2277",
    "sg:postcode":"46519",
    "sg:province":"Nordrhein-Westfalen",
    "wof:name":"Annemarie Beckmann",
    "wof:placetype":"venue"
},
  "geometry": {"coordinates":[6.513502121,51.576259613],"type":"Point"}
}