{
  "type": "Feature",
  "properties": {
    "iso:country":"DE",
    "sg:address":"Postfach 1161:: Raiffeisenstr 1::",
    "sg:city":"Dersum",
    "sg:phone":"+49 4963/91160",
    "sg:postcode":"26906",
    "sg:province":"Niedersachsen",
    "wof:name":"Spar-und Darlehnskasse Eg Dersum",
    "wof:placetype":"venue"
},
  "geometry": {"coordinates":[7.27643,52.960064],"type":"Point"}
}