{
  "type": "Feature",
  "properties": {
    "iso:country":"DE",
    "sg:address":"Breite Str. 16",
    "sg:city":"Pirna",
    "sg:postcode":"01796",
    "sg:province":"Sachsen",
    "wof:name":"Q-linar Verwaltungs Gmbh",
    "wof:placetype":"venue"
},
  "geometry": {"coordinates":[13.9388017654,50.9589233398],"type":"Point"}
}