{
  "type": "Feature",
  "properties": {
    "iso:country":"DE",
    "sg:address":"W\u00f6rthstr. 34",
    "sg:city":"K\u00f6ln",
    "sg:phone":"+49 221/77650",
    "sg:postcode":"50668",
    "sg:province":"Nordrhein-Westfalen",
    "wof:name":"Interorgana Chemiehandel Gmbh & Co. Kg",
    "wof:placetype":"venue"
},
  "geometry": {"coordinates":[6.967501,50.951851],"type":"Point"}
}