{
  "type": "Feature",
  "properties": {
    "iso:country":"DE",
    "sg:address":"Lengenfelder Str. 4",
    "sg:city":"Kirchberg",
    "sg:phone":"+49 37602/66248",
    "sg:postcode":"08107",
    "sg:province":"Sachsen",
    "wof:name":"Klaus-dieter Neubert",
    "wof:placetype":"venue"
},
  "geometry": {"coordinates":[12.5252122879,50.6223335266],"type":"Point"}
}