{
  "type": "Feature",
  "properties": {
    "iso:country":"DE",
    "sg:address":"Bachgasse 15",
    "sg:city":"Wei\u00dfenburg",
    "sg:phone":"+49 9141/2407",
    "sg:postcode":"91781",
    "sg:province":"Bayern",
    "wof:name":"Andreas Schneider",
    "wof:placetype":"venue"
},
  "geometry": {"coordinates":[10.975221,49.029568],"type":"Point"}
}