{
  "type": "Feature",
  "properties": {
    "iso:country":"DE",
    "sg:address":"Franz-Bals-Str 2",
    "sg:city":"Paderborn",
    "sg:phone":"+49 5254/933587",
    "sg:postcode":"33106",
    "sg:province":"Nordrhein-Westfalen",
    "wof:name":"Valuecare Deutschland Gmbh",
    "wof:placetype":"venue"
},
  "geometry": {"coordinates":[8.677291,51.740051],"type":"Point"}
}