{
  "type": "Feature",
  "properties": {
    "iso:country":"DE",
    "sg:address":"Sch\u00fctzenweg",
    "sg:city":"Gruibingen",
    "sg:phone":"+49 7335/5153",
    "sg:postcode":"73344",
    "sg:province":"Baden-W\u00fcrttemberg",
    "wof:name":"Campingplatz Winkelbachtal",
    "wof:placetype":"venue"
},
  "geometry": {"coordinates":[9.636702,48.592087],"type":"Point"}
}