{
  "type": "Feature",
  "properties": {
    "iso:country":"DE",
    "sg:address":"Gelsenkirchener Str. 305",
    "sg:city":"Essen",
    "sg:phone":"+49 201/301309",
    "sg:postcode":"45327",
    "sg:province":"Nordrhein-Westfalen",
    "wof:name":"W. Van Veenendaal",
    "wof:placetype":"venue"
},
  "geometry": {"coordinates":[7.053261,51.493572],"type":"Point"}
}