{
  "type": "Feature",
  "properties": {
    "iso:country":"DE",
    "sg:address":"Hauptstr. 29",
    "sg:city":"Ostrach",
    "sg:phone":"+49 7585/645",
    "sg:postcode":"88356",
    "sg:province":"Baden-W\u00fcrttemberg",
    "wof:name":"Alfons Klein",
    "wof:placetype":"venue"
},
  "geometry": {"coordinates":[9.381070137,47.9514503479],"type":"Point"}
}