{
  "type": "Feature",
  "properties": {
    "iso:country":"DE",
    "sg:address":"Auf der Burg 4",
    "sg:city":"Frankenberg",
    "sg:phone":"+49 6451/8801",
    "sg:postcode":"35066",
    "sg:province":"Hessen",
    "wof:name":"Ev. Pfarramt Iii Frankenberg",
    "wof:placetype":"venue"
},
  "geometry": {"coordinates":[8.7988920212,51.0582199097],"type":"Point"}
}