{
  "type": "Feature",
  "properties": {
    "iso:country":"DE",
    "sg:address":"Schulstra\u00dfe 7",
    "sg:city":"Girod",
    "sg:postcode":"56412",
    "sg:province":"Rheinland-Pfalz",
    "wof:name":"Reifenexport Winkler",
    "wof:placetype":"venue"
},
  "geometry": {"coordinates":[7.909119,50.450226],"type":"Point"}
}