{
  "type": "Feature",
  "properties": {
    "iso:country":"DE",
    "sg:address":"Hauptstr. 23",
    "sg:city":"Pulheim",
    "sg:phone":"+49 2238/14109",
    "sg:postcode":"50259",
    "sg:province":"Nordrhein-Westfalen",
    "wof:name":"B. Klose",
    "wof:placetype":"venue"
},
  "geometry": {"coordinates":[6.7548060417,51.0167694092],"type":"Point"}
}