{
  "type": "Feature",
  "properties": {
    "iso:country":"DE",
    "sg:address":"Friedensplatz 6",
    "sg:city":"Dortmund",
    "sg:postcode":"44135",
    "sg:province":"Nordrhein-Westfalen",
    "wof:name":"Prospektiv Ges. F\u00fcr Betriebl. Zukunftsgestaltung Mbh",
    "wof:placetype":"venue"
},
  "geometry": {"coordinates":[7.46657,51.511715],"type":"Point"}
}