{
  "type": "Feature",
  "properties": {
    "iso:country":"DE",
    "sg:address":"Weberstr. 30",
    "sg:city":"Nettetal",
    "sg:phone":"+49 2153/730247",
    "sg:postcode":"41334",
    "sg:province":"Nordrhein-Westfalen",
    "wof:name":"Sms Sanit\u00e4r-montage- Systeme Gmbh",
    "wof:placetype":"venue"
},
  "geometry": {"coordinates":[6.2374181747,51.3109512329],"type":"Point"}
}