{
  "type": "Feature",
  "properties": {
    "iso:country":"DE",
    "sg:address":"Lange Str. 20",
    "sg:city":"Friesoythe",
    "sg:phone":"+49 4491/1817",
    "sg:postcode":"26169",
    "sg:province":"Niedersachsen",
    "wof:name":"You Modewaren",
    "wof:placetype":"venue"
},
  "geometry": {"coordinates":[7.853784,53.03014],"type":"Point"}
}