{
  "type": "Feature",
  "properties": {
    "iso:country":"DE",
    "sg:address":"Urbanstr. 7",
    "sg:city":"M\u00fcnster",
    "sg:phone":"+49 251/46255",
    "sg:postcode":"48143",
    "sg:province":"Nordrhein-Westfalen",
    "wof:name":"Urban-apotheke",
    "wof:placetype":"venue"
},
  "geometry": {"coordinates":[7.63436,51.958424],"type":"Point"}
}