{
  "type": "Feature",
  "properties": {
    "iso:country":"DE",
    "sg:city":"Berlin",
    "sg:postcode":"12353",
    "sg:province":"Berlin",
    "wof:name":"Treffpunkt Berlin",
    "wof:placetype":"venue"
},
  "geometry": {"coordinates":[13.45287,52.428856],"type":"Point"}
}