{
  "type": "Feature",
  "properties": {
    "iso:country":"DE",
    "sg:address":"Barf\u00fc\u00dferstr. 16",
    "sg:city":"Erfurt",
    "sg:postcode":"99084",
    "sg:province":"Th\u00fcringen",
    "wof:name":"J & M Musikland Ohg",
    "wof:placetype":"venue"
},
  "geometry": {"coordinates":[11.0306882858,50.9750862122],"type":"Point"}
}