{
  "type": "Feature",
  "properties": {
    "iso:country":"DE",
    "sg:address":"Luisenstr. 126",
    "sg:city":"D\u00fcsseldorf",
    "sg:phone":"+49 211/9940921",
    "sg:postcode":"40822",
    "sg:province":"Nordrhein-Westfalen",
    "wof:name":"Schmidt-schnell. Werbung Und Design",
    "wof:placetype":"venue"
},
  "geometry": {"coordinates":[6.789168,51.216999],"type":"Point"}
}