{
  "type": "Feature",
  "properties": {
    "iso:country":"DE",
    "sg:address":"Kaiserstr. 62",
    "sg:city":"Homburg",
    "sg:phone":"+49 6841/4001",
    "sg:postcode":"66424",
    "sg:province":"Saarland",
    "wof:name":"Peter Hoffmann Rechtsanwalt",
    "wof:placetype":"venue"
},
  "geometry": {"coordinates":[7.3333559036,49.3211212158],"type":"Point"}
}