{
  "type": "Feature",
  "properties": {
    "iso:country":"DE",
    "sg:address":"Doerriesweg 10",
    "sg:city":"Hamburg",
    "sg:postcode":"22525",
    "sg:province":"Hamburg",
    "wof:name":"Neuform Vereinigte Dt. Reformh\u00e4user E.g.",
    "wof:placetype":"venue"
},
  "geometry": {"coordinates":[9.9149341583,53.5956611633],"type":"Point"}
}