{
  "type": "Feature",
  "properties": {
    "iso:country":"DE",
    "sg:address":"J\u00fcdefelderstr. 41",
    "sg:city":"M\u00fcnster",
    "sg:phone":"+49 251/519997",
    "sg:postcode":"48143",
    "sg:province":"Nordrhein-Westfalen",
    "wof:name":"Mal\u00f6r",
    "wof:placetype":"venue"
},
  "geometry": {"coordinates":[7.6181612015,51.9661712646],"type":"Point"}
}