{
  "type": "Feature",
  "properties": {
    "iso:country":"DE",
    "sg:address":"August-Fischbach-Str. 11",
    "sg:city":"Donaueschingen",
    "sg:phone":"+49 771/14647",
    "sg:postcode":"78166",
    "sg:province":"Baden-W\u00fcrttemberg",
    "wof:name":"Vino-gastro Service Gmbh",
    "wof:placetype":"venue"
},
  "geometry": {"coordinates":[8.5093746185,47.9609146118],"type":"Point"}
}