{
  "type": "Feature",
  "properties": {
    "iso:country":"DE",
    "sg:address":"Goethestr. 12",
    "sg:city":"Schwerte",
    "sg:phone":"+49 2304/16136",
    "sg:postcode":"58239",
    "sg:province":"Nordrhein-Westfalen",
    "wof:name":"Klaus Friedrichs",
    "wof:placetype":"venue"
},
  "geometry": {"coordinates":[7.566476,51.44334],"type":"Point"}
}