{
  "type": "Feature",
  "properties": {
    "iso:country":"DE",
    "sg:address":"Max-Planck-Str. 4",
    "sg:city":"D\u00fcsseldorf",
    "sg:phone":"+49 211/6803499",
    "sg:postcode":"40237",
    "sg:province":"Nordrhein-Westfalen",
    "wof:name":"Index Immobilien",
    "wof:placetype":"venue"
},
  "geometry": {"coordinates":[6.8125038147,51.2398986816],"type":"Point"}
}