{
  "type": "Feature",
  "properties": {
    "iso:country":"DE",
    "sg:address":"Goethestra\u00dfe 15",
    "sg:city":"Kassel",
    "sg:postcode":"34119",
    "sg:province":"Hessen",
    "wof:name":"Historische Strassenbahn Kassel",
    "wof:placetype":"venue"
},
  "geometry": {"coordinates":[9.476152,51.314678],"type":"Point"}
}