{
  "type": "Feature",
  "properties": {
    "iso:country":"DE",
    "sg:address":"Wiesenh\u00fcttenweg 39",
    "sg:city":"Frankfurt",
    "sg:phone":"+49 69/230882",
    "sg:postcode":"60329",
    "sg:province":"Hessen",
    "wof:name":"Pars Travel",
    "wof:placetype":"venue"
},
  "geometry": {"coordinates":[8.6656980515,50.1057434082],"type":"Point"}
}