{
  "type": "Feature",
  "properties": {
    "iso:country":"DE",
    "sg:address":"Ismaninger Str. 45 b",
    "sg:city":"M\u00fcnchen",
    "sg:phone":"+49 89/4555590",
    "sg:postcode":"81675",
    "sg:province":"Bayern",
    "wof:name":"Ofenstein Dehning Werbeagentur Gmbh",
    "wof:placetype":"venue"
},
  "geometry": {"coordinates":[11.600230217,48.1412353516],"type":"Point"}
}