{
  "type": "Feature",
  "properties": {
    "iso:country":"DE",
    "sg:address":"Kevenh\u00fcller Str. 6",
    "sg:city":"Beilngries",
    "sg:phone":"+49 8461/7774",
    "sg:postcode":"92339",
    "sg:province":"Bayern",
    "wof:name":"Peter Wittmann",
    "wof:placetype":"venue"
},
  "geometry": {"coordinates":[11.5179624557,49.0563697815],"type":"Point"}
}