{
  "type": "Feature",
  "properties": {
    "iso:country":"DE",
    "sg:address":"Berliner Str. 21",
    "sg:city":"Waldkraiburg",
    "sg:phone":"+49 8638/83702",
    "sg:postcode":"84478",
    "sg:province":"Bayern",
    "wof:name":"Handyland & Gamesworld",
    "wof:placetype":"venue"
},
  "geometry": {"coordinates":[12.4038877487,48.206615448],"type":"Point"}
}