{
  "type": "Feature",
  "properties": {
    "iso:country":"DE",
    "sg:address":"Pasinger Heuweg 54",
    "sg:city":"M\u00fcnchen",
    "sg:phone":"+49 89/81897939",
    "sg:postcode":"80999",
    "sg:province":"Bayern",
    "wof:name":"Eventman Catering Und Veranstaltungsservice",
    "wof:placetype":"venue"
},
  "geometry": {"coordinates":[11.453571,48.178318],"type":"Point"}
}