{
  "type": "Feature",
  "properties": {
    "iso:country":"DE",
    "sg:address":"Johannisplatz 5-11",
    "sg:city":"Leipzig",
    "sg:phone":"+49 341/21420",
    "sg:postcode":"04103",
    "sg:province":"Sachsen",
    "wof:name":"Grassimuseum Museum Des Kunsthandwerks",
    "wof:placetype":"venue"
},
  "geometry": {"coordinates":[12.383047,51.337753],"type":"Point"}
}