{
  "type": "Feature",
  "properties": {
    "iso:country":"DE",
    "sg:address":"Steinstr. 6",
    "sg:city":"Westeregeln",
    "sg:phone":"+49 39268/2596",
    "sg:postcode":"39448",
    "sg:province":"Sachsen-Anhalt",
    "wof:name":"Hans-juergen Witt",
    "wof:placetype":"venue"
},
  "geometry": {"coordinates":[11.391689,51.963764],"type":"Point"}
}