{
  "type": "Feature",
  "properties": {
    "iso:country":"DE",
    "sg:address":"Obere Waldstr.",
    "sg:city":"Burtenbach",
    "sg:postcode":"89349",
    "sg:province":"Bayern",
    "wof:name":"Anton Egger",
    "wof:placetype":"venue"
},
  "geometry": {"coordinates":[10.456945,48.337109],"type":"Point"}
}