{
  "type": "Feature",
  "properties": {
    "iso:country":"DE",
    "sg:address":"K\u00f6lner Str. 381",
    "sg:city":"M\u00fclheim",
    "sg:phone":"+49 208/488643",
    "sg:postcode":"45481",
    "sg:province":"Nordrhein-Westfalen",
    "wof:name":"Juliana K\u00fchnel",
    "wof:placetype":"venue"
},
  "geometry": {"coordinates":[6.863563,51.368603],"type":"Point"}
}