{
  "type": "Feature",
  "properties": {
    "iso:country":"DE",
    "sg:address":"Gemmericher Str. 76",
    "sg:city":"Ahlen",
    "sg:phone":"+49 2382/71428",
    "sg:postcode":"59229",
    "sg:province":"Nordrhein-Westfalen",
    "wof:name":"Heinz Kott",
    "wof:placetype":"venue"
},
  "geometry": {"coordinates":[7.8871250153,51.7464065552],"type":"Point"}
}