{
  "type": "Feature",
  "properties": {
    "iso:country":"DE",
    "sg:address":"Schwetzinger Str. 77",
    "sg:city":"Heidelberg",
    "sg:phone":"+49 6221/783378",
    "sg:postcode":"69124",
    "sg:province":"Baden-W\u00fcrttemberg",
    "wof:name":"G\u00fcnther Rehm Augenoptiker",
    "wof:placetype":"venue"
},
  "geometry": {"coordinates":[8.6698627472,49.3797531128],"type":"Point"}
}