{
  "type": "Feature",
  "properties": {
    "iso:country":"DE",
    "sg:address":"Mozartstr. 3",
    "sg:city":"Frankenthal",
    "sg:phone":"+49 6233/21632",
    "sg:postcode":"67227",
    "sg:province":"Rheinland-Pfalz",
    "wof:name":"B. Biermann Heilpraktiker",
    "wof:placetype":"venue"
},
  "geometry": {"coordinates":[8.3439741135,49.539188385],"type":"Point"}
}