{
  "type": "Feature",
  "properties": {
    "iso:country":"DE",
    "sg:address":"Firnhaberstr. 12",
    "sg:city":"Nordhorn",
    "sg:phone":"+49 5921/89440",
    "sg:postcode":"48529",
    "sg:province":"Niedersachsen",
    "wof:name":"Vechte Dental Gmbh",
    "wof:placetype":"venue"
},
  "geometry": {"coordinates":[7.0720939636,52.4349594116],"type":"Point"}
}