{
  "type": "Feature",
  "properties": {
    "iso:country":"DE",
    "sg:address":"Jacobsenweg 3",
    "sg:city":"Hamburg",
    "sg:phone":"+49 40/544910",
    "sg:postcode":"22525",
    "sg:province":"Hamburg",
    "wof:name":"W + S Wartung & Service Airline Gmbh",
    "wof:placetype":"venue"
},
  "geometry": {"coordinates":[9.913454,53.5952],"type":"Point"}
}