{
  "type": "Feature",
  "properties": {
    "iso:country":"DE",
    "sg:address":"Krayer Str. 258",
    "sg:city":"Essen",
    "sg:phone":"+49 201/555330",
    "sg:postcode":"45307",
    "sg:province":"Nordrhein-Westfalen",
    "wof:name":"Hubertus-bad Fahr Kray",
    "wof:placetype":"venue"
},
  "geometry": {"coordinates":[7.081233,51.46817],"type":"Point"}
}