{
  "type": "Feature",
  "properties": {
    "iso:country":"DE",
    "sg:address":"Nr. 155",
    "sg:city":"K\u00f6nigshain",
    "sg:phone":"+49 35826/60205",
    "sg:postcode":"02829",
    "sg:province":"Sachsen",
    "wof:name":"Eberhard Melzer",
    "wof:placetype":"venue"
},
  "geometry": {"coordinates":[14.912377,51.176189],"type":"Point"}
}