{
  "type": "Feature",
  "properties": {
    "iso:country":"DE",
    "sg:address":"Trostberger Str. 5",
    "sg:city":"Alt\u00f6tting",
    "sg:phone":"+49 8671/5642",
    "sg:postcode":"84503",
    "sg:province":"Bayern",
    "wof:name":"Josef Borst",
    "wof:placetype":"venue"
},
  "geometry": {"coordinates":[12.67553,48.224564],"type":"Point"}
}