{
  "type": "Feature",
  "properties": {
    "iso:country":"DE",
    "sg:address":"Kanalstr. 33",
    "sg:city":"Solingen",
    "sg:phone":"+49 212/815871",
    "sg:postcode":"42657",
    "sg:province":"Nordrhein-Westfalen",
    "wof:name":"Pr\u00f6pper Gmbh",
    "wof:placetype":"venue"
},
  "geometry": {"coordinates":[7.0779380798,51.158454895],"type":"Point"}
}