{
  "type": "Feature",
  "properties": {
    "iso:country":"DE",
    "sg:address":"M\u00fchlweg 13",
    "sg:city":"Zeithain",
    "sg:phone":"+49 3525/76610",
    "sg:postcode":"01619",
    "sg:province":"Sachsen",
    "wof:name":"K\u00f6hler Gmbh",
    "wof:placetype":"venue"
},
  "geometry": {"coordinates":[13.3027124405,51.3223075867],"type":"Point"}
}