{
  "type": "Feature",
  "properties": {
    "iso:country":"DE",
    "sg:address":"Aschheimer Str. 28",
    "sg:city":"Unterf\u00f6hring",
    "sg:postcode":"85774",
    "sg:province":"Bayern",
    "wof:name":"Venture Personal Consult S. Kramer E. K.",
    "wof:placetype":"venue"
},
  "geometry": {"coordinates":[11.651869,48.198902],"type":"Point"}
}