{
  "type": "Feature",
  "properties": {
    "iso:country":"DE",
    "sg:address":"Lange M\u00fchren 9",
    "sg:city":"Hamburg",
    "sg:phone":"+49 40/30107",
    "sg:postcode":"20095",
    "sg:province":"Hamburg",
    "wof:name":"Walter P. Goodale",
    "wof:placetype":"venue"
},
  "geometry": {"coordinates":[10.0042877197,53.551990509],"type":"Point"}
}