{
  "type": "Feature",
  "properties": {
    "iso:country":"DE",
    "sg:address":"Sprungschanzenweg 101 a",
    "sg:city":"Berlin",
    "sg:phone":"+49 4930/8212125",
    "sg:postcode":"14169",
    "sg:province":"Berlin",
    "wof:name":"Olli\u00b4s Spielparadies",
    "wof:placetype":"venue"
},
  "geometry": {"coordinates":[13.251902,52.453472],"type":"Point"}
}