{
  "type": "Feature",
  "properties": {
    "iso:country":"DE",
    "sg:address":"Am Niederholz 38",
    "sg:city":"Leipzig",
    "sg:postcode":"04288",
    "sg:province":"Sachsen",
    "wof:name":"R. Blume",
    "wof:placetype":"venue"
},
  "geometry": {"coordinates":[12.47684,51.275391],"type":"Point"}
}