{
  "type": "Feature",
  "properties": {
    "iso:country":"DE",
    "sg:address":"Hufenkamp 1",
    "sg:city":"Kronshagen",
    "sg:phone":"+49 431/589972",
    "sg:postcode":"24119",
    "sg:province":"Schleswig-Holstein",
    "wof:name":"Otto Sommerburg",
    "wof:placetype":"venue"
},
  "geometry": {"coordinates":[10.0897102356,54.332233429],"type":"Point"}
}