{
  "type": "Feature",
  "properties": {
    "iso:country":"DE",
    "sg:address":"Besselstr. 12",
    "sg:city":"Mannheim",
    "sg:phone":"+49 621/877870",
    "sg:postcode":"68219",
    "sg:province":"Baden-W\u00fcrttemberg",
    "wof:name":"In-night Holding Gmbh",
    "wof:placetype":"venue"
},
  "geometry": {"coordinates":[8.516816,49.450157],"type":"Point"}
}