{
  "type": "Feature",
  "properties": {
    "iso:country":"DE",
    "sg:address":"Karl-Hermann-Flach-Str. 11",
    "sg:city":"Oberursel",
    "sg:phone":"+49 6171/506690",
    "sg:postcode":"61440",
    "sg:province":"Hessen",
    "wof:name":"Reifen-seher- Und Fahrzeugtechnik Gmbh",
    "wof:placetype":"venue"
},
  "geometry": {"coordinates":[8.597167,50.204086],"type":"Point"}
}