{
  "type": "Feature",
  "properties": {
    "iso:country":"DE",
    "sg:address":"Am Elzdamm 45",
    "sg:city":"Emmendingen",
    "sg:phone":"+49 7641/935851",
    "sg:postcode":"79312",
    "sg:province":"Baden-W\u00fcrttemberg",
    "wof:name":"Minimal",
    "wof:placetype":"venue"
},
  "geometry": {"coordinates":[7.8278441429,48.1263885498],"type":"Point"}
}