{
  "type": "Feature",
  "properties": {
    "iso:country":"DE",
    "sg:address":"Rockwinkeler Heerstr. 19",
    "sg:city":"Bremen",
    "sg:phone":"+49 421/259088",
    "sg:postcode":"28355",
    "sg:province":"Bremen",
    "wof:name":"Apotheke Oberneuland",
    "wof:placetype":"venue"
},
  "geometry": {"coordinates":[8.931519,53.089691],"type":"Point"}
}