{
  "type": "Feature",
  "properties": {
    "iso:country":"DE",
    "sg:address":"Friedberger Str. 39",
    "sg:city":"Augsburg",
    "sg:postcode":"86161",
    "sg:province":"Bayern",
    "wof:name":"Rco Vitalis E. K.",
    "wof:placetype":"venue"
},
  "geometry": {"coordinates":[10.9146575928,48.3562088013],"type":"Point"}
}