{
  "type": "Feature",
  "properties": {
    "iso:country":"DE",
    "sg:address":"Dorfstr. 36",
    "sg:city":"Betten",
    "sg:phone":"+49 3531/700401",
    "sg:postcode":"03238",
    "sg:province":"Brandenburg",
    "wof:name":"E. Nadebohr",
    "wof:placetype":"venue"
},
  "geometry": {"coordinates":[13.7691106796,51.6261138916],"type":"Point"}
}