{
  "type": "Feature",
  "properties": {
    "iso:country":"DE",
    "sg:address":"Friedrich-Ebert-Str. 5",
    "sg:city":"Dossenheim",
    "sg:phone":"+49 6221/861269",
    "sg:postcode":"69221",
    "sg:province":"Baden-W\u00fcrttemberg",
    "wof:name":"J. Pokrandt",
    "wof:placetype":"venue"
},
  "geometry": {"coordinates":[8.6762714386,49.4457168579],"type":"Point"}
}