{
  "type": "Feature",
  "properties": {
    "iso:country":"DE",
    "sg:address":"Schwalbenweg 61",
    "sg:city":"Kempten",
    "sg:postcode":"87439",
    "sg:province":"Bayern",
    "wof:name":"Lebenshilfe Bef\u00f6rderungs- Dienst Ggmbh",
    "wof:placetype":"venue"
},
  "geometry": {"coordinates":[10.2868890762,47.7399787903],"type":"Point"}
}