{
  "type": "Feature",
  "properties": {
    "iso:country":"DE",
    "sg:address":"Waldh\u00f6henstr. 8",
    "sg:city":"Ilsenburg",
    "sg:phone":"+49 39452/2449",
    "sg:postcode":"38871",
    "sg:province":"Sachsen-Anhalt",
    "wof:name":"Eggert",
    "wof:placetype":"venue"
},
  "geometry": {"coordinates":[10.671652,51.862522],"type":"Point"}
}