{
  "type": "Feature",
  "properties": {
    "iso:country":"DE",
    "sg:address":"Im Engler 21a",
    "sg:city":"Kriftel",
    "sg:phone":"+49 69/5602532",
    "sg:postcode":"65830",
    "sg:province":"Hessen",
    "wof:name":"K. F. Hau Steuerberater",
    "wof:placetype":"venue"
},
  "geometry": {"coordinates":[8.4700593948,50.0882720947],"type":"Point"}
}