{
  "type": "Feature",
  "properties": {
    "iso:country":"DE",
    "sg:address":"Streckewalder Str 5",
    "sg:city":"Mildenau",
    "sg:phone":"+49 3733/556293",
    "sg:postcode":"09456",
    "sg:province":"Sachsen",
    "wof:name":"Kr\u00e4uterhof Mildenau Gmbh",
    "wof:placetype":"venue"
},
  "geometry": {"coordinates":[13.0671815872,50.6076774597],"type":"Point"}
}