{
  "type": "Feature",
  "properties": {
    "iso:country":"DE",
    "sg:address":"Bullerdeich 14",
    "sg:city":"Hamburg",
    "sg:phone":"+49 40/24827953",
    "sg:postcode":"20537",
    "sg:province":"Hamburg",
    "wof:name":"Look! Calling Cards",
    "wof:placetype":"venue"
},
  "geometry": {"coordinates":[10.0362863541,53.544380188],"type":"Point"}
}