{
  "type": "Feature",
  "properties": {
    "iso:country":"DE",
    "sg:address":"Industriestr. 3",
    "sg:city":"Fuldabr\u00fcck",
    "sg:phone":"+49 561/9583600",
    "sg:postcode":"34277",
    "sg:province":"Hessen",
    "wof:name":"Ti Group Automotive Systems Fuldabr\u00fcck Gmbh",
    "wof:placetype":"venue"
},
  "geometry": {"coordinates":[9.504495,51.269447],"type":"Point"}
}