{
  "type": "Feature",
  "properties": {
    "iso:country":"DE",
    "sg:address":"Hauptstr. 28",
    "sg:city":"Mei\u00dfenheim",
    "sg:phone":"+49 7824/2409",
    "sg:postcode":"77974",
    "sg:province":"Baden-W\u00fcrttemberg",
    "wof:name":"Rolladenbau Schweinfurth Gmbh",
    "wof:placetype":"venue"
},
  "geometry": {"coordinates":[7.776391983,48.4083213806],"type":"Point"}
}