{
  "type": "Feature",
  "properties": {
    "iso:country":"DE",
    "sg:address":"Bahnhofstr. 37",
    "sg:city":"R\u00f6dermark",
    "sg:phone":"+49 6074/7434",
    "sg:postcode":"63322",
    "sg:province":"Hessen",
    "wof:name":"Rh\u00f6nsch\u00e4nke",
    "wof:placetype":"venue"
},
  "geometry": {"coordinates":[8.7974967957,49.9730033875],"type":"Point"}
}