{
  "type": "Feature",
  "properties": {
    "iso:country":"DE",
    "sg:address":"Brucknerstr. 10",
    "sg:city":"Welzheim",
    "sg:phone":"+49 7182/528",
    "sg:postcode":"73642",
    "sg:province":"Baden-W\u00fcrttemberg",
    "wof:name":"Werner H\u00f6fer Gmbh",
    "wof:placetype":"venue"
},
  "geometry": {"coordinates":[9.6273202896,48.8668785095],"type":"Point"}
}