{
  "type": "Feature",
  "properties": {
    "iso:country":"DE",
    "sg:address":"Max-Pechstein-Str. 23",
    "sg:city":"K\u00f6ln",
    "sg:phone":"+49 221/9486110",
    "sg:postcode":"50858",
    "sg:province":"Nordrhein-Westfalen",
    "wof:name":"Portfolio Concept Gmbh, Broker, Verm\u00f6gensverwaltung, Fonds",
    "wof:placetype":"venue"
},
  "geometry": {"coordinates":[6.8585510254,50.9406471252],"type":"Point"}
}