{
  "type": "Feature",
  "properties": {
    "iso:country":"DE",
    "sg:address":"Wacholderweg 9",
    "sg:city":"Neustadt",
    "sg:phone":"+49 5032/3968",
    "sg:postcode":"31535",
    "sg:province":"Niedersachsen",
    "wof:name":"Ev. Pfarramt Johannesgemeinde",
    "wof:placetype":"venue"
},
  "geometry": {"coordinates":[9.4435977936,52.5027999878],"type":"Point"}
}