{
  "type": "Feature",
  "properties": {
    "iso:country":"DE",
    "sg:address":"Westerbachstr. 17",
    "sg:city":"H\u00f6xter",
    "sg:phone":"+49 5271/7797",
    "sg:postcode":"37671",
    "sg:province":"Nordrhein-Westfalen",
    "wof:name":"Fred Mietzner",
    "wof:placetype":"venue"
},
  "geometry": {"coordinates":[9.379792,51.77417],"type":"Point"}
}