{
  "type": "Feature",
  "properties": {
    "iso:country":"DE",
    "sg:address":"Marthastr. 38",
    "sg:city":"N\u00fcrnberg",
    "sg:phone":"+49 911/543890",
    "sg:postcode":"90482",
    "sg:province":"Bayern",
    "wof:name":"H. Ringler",
    "wof:placetype":"venue"
},
  "geometry": {"coordinates":[11.1139364243,49.4534797668],"type":"Point"}
}