{
  "type": "Feature",
  "properties": {
    "iso:country":"DE",
    "sg:address":"Stra\u00dfe der DSF 14",
    "sg:city":"Zeulenroda",
    "sg:phone":"+49 36628/2602",
    "sg:postcode":"07937",
    "sg:province":"Th\u00fcringen",
    "wof:name":"R. Meinhard",
    "wof:placetype":"venue"
},
  "geometry": {"coordinates":[11.9807491302,50.6531143188],"type":"Point"}
}