{
  "type": "Feature",
  "properties": {
    "iso:country":"DE",
    "sg:address":"Sandwingert 49",
    "sg:city":"Heidelberg",
    "sg:phone":"+49 6221/834926",
    "sg:postcode":"69123",
    "sg:province":"Baden-W\u00fcrttemberg",
    "wof:name":"Martin Noll",
    "wof:placetype":"venue"
},
  "geometry": {"coordinates":[8.6433258057,49.4202804565],"type":"Point"}
}