{
  "type": "Feature",
  "properties": {
    "iso:country":"DE",
    "sg:address":"Wirtheimer Str. 5",
    "sg:city":"Biebergem\u00fcnd",
    "sg:phone":"+49 6050/97270",
    "sg:postcode":"63599",
    "sg:province":"Hessen",
    "wof:name":"G. Strauss",
    "wof:placetype":"venue"
},
  "geometry": {"coordinates":[9.2728700638,50.2133750916],"type":"Point"}
}