{
  "type": "Feature",
  "properties": {
    "iso:country":"DE",
    "sg:address":"Burgweg 1",
    "sg:city":"Katlenburg-Lindau",
    "sg:phone":"+49 5552/225",
    "sg:postcode":"37191",
    "sg:province":"Niedersachsen",
    "wof:name":"C. Metje",
    "wof:placetype":"venue"
},
  "geometry": {"coordinates":[10.0951166153,51.7079277039],"type":"Point"}
}