{
  "type": "Feature",
  "properties": {
    "iso:country":"DE",
    "sg:address":"Am Alten Friedhof 15",
    "sg:city":"Kornwestheim",
    "sg:phone":"+49 7154/29719",
    "sg:postcode":"70806",
    "sg:province":"Baden-W\u00fcrttemberg",
    "wof:name":"Dr. Gerhard Schilpp Tierarzt",
    "wof:placetype":"venue"
},
  "geometry": {"coordinates":[9.1925468445,48.8661308289],"type":"Point"}
}