{
  "type": "Feature",
  "properties": {
    "iso:country":"DE",
    "sg:address":"Keekener Str. 100",
    "sg:city":"Kleve",
    "sg:phone":"+49 2821/3501",
    "sg:postcode":"47533",
    "sg:province":"Nordrhein-Westfalen",
    "wof:name":"Nzl Niederrheinische Zuckerr\u00fcbengesellschaft Mbh",
    "wof:placetype":"venue"
},
  "geometry": {"coordinates":[6.113124,51.822384],"type":"Point"}
}