{
  "type": "Feature",
  "properties": {
    "iso:country":"DE",
    "sg:address":"Schwarzwaldstr. 30",
    "sg:city":"Frankfurt",
    "sg:phone":"+49 69/675581",
    "sg:postcode":"60528",
    "sg:province":"Hessen",
    "wof:name":"Linda Moden Mode Und Bekleidungshaus",
    "wof:placetype":"venue"
},
  "geometry": {"coordinates":[8.646519,50.086357],"type":"Point"}
}