{
  "type": "Feature",
  "properties": {
    "iso:country":"DE",
    "sg:address":"Mendelssohnstr. 10",
    "sg:city":"M\u00f6glingen",
    "sg:phone":"+49 7141/484188",
    "sg:postcode":"71696",
    "sg:province":"Baden-W\u00fcrttemberg",
    "wof:name":"Gkd Gasger\u00e4te Vertriebs- Und Service Gmbh",
    "wof:placetype":"venue"
},
  "geometry": {"coordinates":[9.1230888367,48.8851127625],"type":"Point"}
}