{
  "type": "Feature",
  "properties": {
    "iso:country":"DE",
    "sg:address":"Padling 311 - 318",
    "sg:city":"Hunding",
    "sg:phone":"+49 9904/926",
    "sg:postcode":"94551",
    "sg:province":"Bayern",
    "wof:name":"Gastst\u00e4tte Zum Ferdl",
    "wof:placetype":"venue"
},
  "geometry": {"coordinates":[13.141418457,48.8450393677],"type":"Point"}
}