{
  "type": "Feature",
  "properties": {
    "iso:country":"DE",
    "sg:address":"Postfach",
    "sg:city":"Abensberg",
    "sg:postcode":"93320",
    "sg:province":"Bayern",
    "wof:name":"Kinderheim Offenstetten",
    "wof:placetype":"venue"
},
  "geometry": {"coordinates":[11.8473939896,48.8157577515],"type":"Point"}
}