{
  "type": "Feature",
  "properties": {
    "iso:country":"DE",
    "sg:address":"Drabertstr. 8-11a",
    "sg:city":"Minden",
    "sg:phone":"+49 571/27051",
    "sg:postcode":"32425",
    "sg:province":"Nordrhein-Westfalen",
    "wof:name":"Z & K Bauglas Gmbh",
    "wof:placetype":"venue"
},
  "geometry": {"coordinates":[8.9001321793,52.2998886108],"type":"Point"}
}