{
  "type": "Feature",
  "properties": {
    "iso:country":"DE",
    "sg:address":"Pfarrsteige 35/1",
    "sg:city":"G\u00f6ppingen",
    "sg:phone":"+49 7161/811682",
    "sg:postcode":"73037",
    "sg:province":"Baden-W\u00fcrttemberg",
    "wof:name":"Siegfried Gretler Architekt",
    "wof:placetype":"venue"
},
  "geometry": {"coordinates":[9.694863,48.685635],"type":"Point"}
}