{
  "type": "Feature",
  "properties": {
    "iso:country":"DE",
    "sg:address":"Michael-Kazmierczak-Str. 19",
    "sg:city":"Leipzig",
    "sg:phone":"+49 341/9116984",
    "sg:postcode":"04157",
    "sg:province":"Sachsen",
    "wof:name":"Wolfgang Sauer",
    "wof:placetype":"venue"
},
  "geometry": {"coordinates":[12.3730802536,51.3665466309],"type":"Point"}
}