{
  "type": "Feature",
  "properties": {
    "iso:country":"DE",
    "sg:address":"Hixberger Str. 28",
    "sg:city":"Riegelsberg",
    "sg:phone":"+49 6806/3660",
    "sg:postcode":"66292",
    "sg:province":"Saarland",
    "wof:name":"Dea Tankstelle",
    "wof:placetype":"venue"
},
  "geometry": {"coordinates":[6.9349517822,49.2958679199],"type":"Point"}
}