{
  "type": "Feature",
  "properties": {
    "iso:country":"DE",
    "sg:address":"Florian-Geyer-Str. 72",
    "sg:city":"W\u00fcrzburg",
    "sg:phone":"+49 931/274266",
    "sg:postcode":"97076",
    "sg:province":"Bayern",
    "wof:name":"Willi Fausel",
    "wof:placetype":"venue"
},
  "geometry": {"coordinates":[9.9719657898,49.8056030273],"type":"Point"}
}