{
  "type": "Feature",
  "properties": {
    "iso:country":"DE",
    "sg:address":"Hauptstr. 10",
    "sg:city":"Neroth",
    "sg:phone":"+49 6591/5389",
    "sg:postcode":"54570",
    "sg:province":"Rheinland-Pfalz",
    "wof:name":"E. Schommers",
    "wof:placetype":"venue"
},
  "geometry": {"coordinates":[6.7420868874,50.1963882446],"type":"Point"}
}