{
  "type": "Feature",
  "properties": {
    "iso:country":"DE",
    "sg:address":"Siedlerweg 8",
    "sg:city":"Kaufbeuren",
    "sg:postcode":"87600",
    "sg:province":"Bayern",
    "wof:name":"Motorrad P\u00fcschel",
    "wof:placetype":"venue"
},
  "geometry": {"coordinates":[10.6405382156,47.8829879761],"type":"Point"}
}