{
  "type": "Feature",
  "properties": {
    "iso:country":"DE",
    "sg:address":"Werinherstr. 43",
    "sg:city":"M\u00fcnchen",
    "sg:phone":"+49 89/6915020",
    "sg:postcode":"81541",
    "sg:province":"Bayern",
    "wof:name":"Ina Elnain Mylife By",
    "wof:placetype":"venue"
},
  "geometry": {"coordinates":[11.590148,48.115349],"type":"Point"}
}