{
  "type": "Feature",
  "properties": {
    "iso:country":"DE",
    "sg:address":"Jersbeker Str 12",
    "sg:city":"Bargteheide",
    "sg:phone":"+49 4532/6517",
    "sg:postcode":"22941",
    "sg:province":"Schleswig-Holstein",
    "wof:name":"J.a. Reinecke & Co Gmbh",
    "wof:placetype":"venue"
},
  "geometry": {"coordinates":[10.2572164536,53.7290916443],"type":"Point"}
}