{
  "type": "Feature",
  "properties": {
    "iso:country":"DE",
    "sg:address":"Friedrichstr. 41",
    "sg:city":"Hennickendorf",
    "sg:phone":"+49 33434/46447",
    "sg:postcode":"15378",
    "sg:province":"Brandenburg",
    "wof:name":"P. Liss",
    "wof:placetype":"venue"
},
  "geometry": {"coordinates":[13.845421,52.508133],"type":"Point"}
}