{
  "type": "Feature",
  "properties": {
    "iso:country":"DE",
    "sg:address":"Stephanienstr. 54",
    "sg:city":"Baden-Baden",
    "sg:phone":"+49 7221/23450",
    "sg:postcode":"76530",
    "sg:province":"Baden-W\u00fcrttemberg",
    "wof:name":"K. Herr Werkzeuge",
    "wof:placetype":"venue"
},
  "geometry": {"coordinates":[8.242536,48.757374],"type":"Point"}
}