{
  "type": "Feature",
  "properties": {
    "iso:country":"DE",
    "sg:address":"Lerchenhainprivatweg 3a",
    "sg:city":"Magdeburg",
    "sg:phone":"+49 391",
    "sg:postcode":"39114",
    "sg:province":"Sachsen-Anhalt",
    "wof:name":"Gatti-transporte Magdeburg",
    "wof:placetype":"venue"
},
  "geometry": {"coordinates":[11.6884393692,52.1246109009],"type":"Point"}
}