{
  "type": "Feature",
  "properties": {
    "iso:country":"DE",
    "sg:address":"Seesenthom 7",
    "sg:city":"Bremen",
    "sg:phone":"+49 421/86263",
    "sg:postcode":"28201",
    "sg:province":"Bremen",
    "wof:name":"Thw Helfervereinigung Bremen- Neustadt E. V.",
    "wof:placetype":"venue"
},
  "geometry": {"coordinates":[8.8194618225,53.0563774109],"type":"Point"}
}