{
  "type": "Feature",
  "properties": {
    "iso:country":"DE",
    "sg:address":"Regensburger Str. 63 - 67",
    "sg:city":"N\u00fcrnberg",
    "sg:phone":"+49 911/469898",
    "sg:postcode":"90478",
    "sg:province":"Bayern",
    "wof:name":"Restaurant Sawadi",
    "wof:placetype":"venue"
},
  "geometry": {"coordinates":[11.099354744,49.4435157776],"type":"Point"}
}