{
  "type": "Feature",
  "properties": {
    "iso:country":"DE",
    "sg:address":"Zu den Rotten 12",
    "sg:city":"Salzgitter",
    "sg:phone":"+49 5341/27555",
    "sg:postcode":"38239",
    "sg:province":"Niedersachsen",
    "wof:name":"Johannes Andersen",
    "wof:placetype":"venue"
},
  "geometry": {"coordinates":[10.451786,52.152382],"type":"Point"}
}