{
  "type": "Feature",
  "properties": {
    "iso:country":"DE",
    "sg:address":"Kaiserstr. 86",
    "sg:city":"Offenbach",
    "sg:phone":"+49 69/8004019",
    "sg:postcode":"63065",
    "sg:province":"Hessen",
    "wof:name":"Billard Cafe",
    "wof:placetype":"venue"
},
  "geometry": {"coordinates":[8.757329,50.107803],"type":"Point"}
}