{
  "type": "Feature",
  "properties": {
    "iso:country":"DE",
    "sg:address":"Bahnhofstr 17",
    "sg:city":"Herzlake",
    "sg:phone":"+49 5962/92525",
    "sg:postcode":"49770",
    "sg:province":"Niedersachsen",
    "wof:name":"Rgm Schaufler Regalmontagen Gmbh & Co Kg",
    "wof:placetype":"venue"
},
  "geometry": {"coordinates":[7.603564,52.686619],"type":"Point"}
}