{
  "type": "Feature",
  "properties": {
    "iso:country":"DE",
    "sg:address":"Kieselstr. 38",
    "sg:city":"Saarbr\u00fccken",
    "sg:phone":"+49 6897/761189",
    "sg:postcode":"66125",
    "sg:province":"Saarland",
    "wof:name":"Horst Jost Architekt",
    "wof:placetype":"venue"
},
  "geometry": {"coordinates":[7.031195,49.285465],"type":"Point"}
}