{
  "type": "Feature",
  "properties": {
    "iso:country":"DE",
    "sg:address":"H\u00fcttenstr. 31",
    "sg:city":"D\u00fcsseldorf",
    "sg:phone":"+49 211/3807490",
    "sg:postcode":"40215",
    "sg:province":"Nordrhein-Westfalen",
    "wof:name":"Mediacom Agentur Fuer Media-beratung Gmbh",
    "wof:placetype":"venue"
},
  "geometry": {"coordinates":[6.784378,51.216091],"type":"Point"}
}