{
  "type": "Feature",
  "properties": {
    "iso:country":"DE",
    "sg:address":"Sedanstr. 63",
    "sg:city":"Hannover",
    "sg:phone":"+49 511/342134",
    "sg:postcode":"30161",
    "sg:province":"Niedersachsen",
    "wof:name":"Wolfgang Dreyer Steuerbevollm\u00e4chtigter",
    "wof:placetype":"venue"
},
  "geometry": {"coordinates":[9.7480535507,52.3802680969],"type":"Point"}
}