{
  "type": "Feature",
  "properties": {
    "iso:country":"DE",
    "sg:address":"Werner-von-Siemens-Str. 29",
    "sg:city":"Erlangen",
    "sg:phone":"+49 9131/22845",
    "sg:postcode":"91052",
    "sg:province":"Bayern",
    "wof:name":"China-restaurant Shanghai",
    "wof:placetype":"venue"
},
  "geometry": {"coordinates":[11.0154619217,49.594581604],"type":"Point"}
}