{
  "type": "Feature",
  "properties": {
    "iso:country":"DE",
    "sg:address":"Br\u00fchler Str. 42",
    "sg:city":"Wesseling",
    "sg:phone":"+49 2236/943250",
    "sg:postcode":"50389",
    "sg:province":"Nordrhein-Westfalen",
    "wof:name":"Wilhelm Henseler Inh. Hans Vossen",
    "wof:placetype":"venue"
},
  "geometry": {"coordinates":[6.968978,50.831448],"type":"Point"}
}