{
  "type": "Feature",
  "properties": {
    "iso:country":"DE",
    "sg:address":"M\u00fchlendamm 1",
    "sg:city":"Viesecke",
    "sg:phone":"+49 38796/40207",
    "sg:postcode":"19336",
    "sg:province":"Brandenburg",
    "wof:name":"Agrarproduktiv Viesecke Eg",
    "wof:placetype":"venue"
},
  "geometry": {"coordinates":[11.94465,52.95557],"type":"Point"}
}