{
  "type": "Feature",
  "properties": {
    "iso:country":"DE",
    "sg:address":"Leopoldstr. 85",
    "sg:city":"M\u00fcnchen",
    "sg:phone":"+49 89/5440950",
    "sg:postcode":"80802",
    "sg:province":"Bayern",
    "wof:name":"Leasfinanz-vermietung Von Investitionsg\u00fctern",
    "wof:placetype":"venue"
},
  "geometry": {"coordinates":[11.5861272812,48.1637763977],"type":"Point"}
}