{
  "type": "Feature",
  "properties": {
    "iso:country":"DE",
    "sg:address":"Neue Unlinger Str. 10",
    "sg:city":"Riedlingen",
    "sg:phone":"+49 7371/7269",
    "sg:postcode":"88499",
    "sg:province":"Baden-W\u00fcrttemberg",
    "wof:name":"B\u00e4ckerei Cafe Bochtler Gmbh",
    "wof:placetype":"venue"
},
  "geometry": {"coordinates":[9.485795,48.14896],"type":"Point"}
}