{
  "type": "Feature",
  "properties": {
    "iso:country":"DE",
    "sg:address":"Schwedenstr. 37",
    "sg:city":"Kronach",
    "sg:phone":"+49 9261/3628",
    "sg:postcode":"96317",
    "sg:province":"Bayern",
    "wof:name":"Filmburg",
    "wof:placetype":"venue"
},
  "geometry": {"coordinates":[11.323033,50.243828],"type":"Point"}
}