{
  "type": "Feature",
  "properties": {
    "iso:country":"DE",
    "sg:address":"K\u00e4the-Kollwitz-Str. 4",
    "sg:city":"Karlsruhe",
    "sg:postcode":"76227",
    "sg:province":"Baden-W\u00fcrttemberg",
    "wof:name":"Blumenstube",
    "wof:placetype":"venue"
},
  "geometry": {"coordinates":[8.480145,48.992718],"type":"Point"}
}