{
  "type": "Feature",
  "properties": {
    "iso:country":"DE",
    "sg:address":"Kirchstr. 2",
    "sg:city":"Altmittweida",
    "sg:phone":"+49 3727/62070",
    "sg:postcode":"09648",
    "sg:province":"Sachsen",
    "wof:name":"Autohaus Zwinzscher",
    "wof:placetype":"venue"
},
  "geometry": {"coordinates":[12.9478712082,50.96484375],"type":"Point"}
}