{
  "type": "Feature",
  "properties": {
    "iso:country":"DE",
    "sg:address":"Werkstr. 7",
    "sg:city":"B\u00f6hlen",
    "sg:postcode":"04564",
    "sg:province":"Sachsen",
    "wof:name":"Semmler Beteiligungs Gmbh",
    "wof:placetype":"venue"
},
  "geometry": {"coordinates":[12.380925,51.200737],"type":"Point"}
}