{
  "type": "Feature",
  "properties": {
    "iso:country":"DE",
    "sg:address":"Hauptstr. 42",
    "sg:city":"Meuselbach-Schwarzm\u00fchle",
    "sg:phone":"+49 36705/60224",
    "sg:postcode":"98746",
    "sg:province":"Th\u00fcringen",
    "wof:name":"A. Voigt",
    "wof:placetype":"venue"
},
  "geometry": {"coordinates":[11.096258,50.573822],"type":"Point"}
}