{
  "type": "Feature",
  "properties": {
    "iso:country":"DE",
    "sg:address":"Ammerstra\u00dfe 49",
    "sg:city":"Dortmund",
    "sg:phone":"+49 231/356191",
    "sg:postcode":"44359",
    "sg:province":"Nordrhein-Westfalen",
    "wof:name":"Dose",
    "wof:placetype":"venue"
},
  "geometry": {"coordinates":[7.382827,51.564194],"type":"Point"}
}