{
  "type": "Feature",
  "properties": {
    "iso:country":"DE",
    "sg:address":"Schwarzwaldstr. 28 A",
    "sg:city":"Oberhausen",
    "sg:phone":"+49 208/601144",
    "sg:postcode":"46119",
    "sg:province":"Nordrhein-Westfalen",
    "wof:name":"Wilfried Freund Grabdenkm\u00e4ler",
    "wof:placetype":"venue"
},
  "geometry": {"coordinates":[6.8766088486,51.5260925293],"type":"Point"}
}