{
  "type": "Feature",
  "properties": {
    "iso:country":"DE",
    "sg:address":"Am Treptower Park 36",
    "sg:city":"Berlin",
    "sg:phone":"+49 30/22506860",
    "sg:postcode":"12435",
    "sg:province":"Berlin",
    "wof:name":"Fit For Office Computer Und Cafe Gmbh",
    "wof:placetype":"venue"
},
  "geometry": {"coordinates":[13.4648447037,52.4866714478],"type":"Point"}
}