{
  "type": "Feature",
  "properties": {
    "iso:country":"DE",
    "sg:address":"Kirsch\u00e4ckerstr. 13",
    "sg:city":"Bamberg",
    "sg:phone":"+49 951/39711",
    "sg:postcode":"96052",
    "sg:province":"Bayern",
    "wof:name":"Schreinerei Benkert Gmbh",
    "wof:placetype":"venue"
},
  "geometry": {"coordinates":[10.907572,49.912327],"type":"Point"}
}