{
  "type": "Feature",
  "properties": {
    "iso:country":"DE",
    "sg:address":"Feuersteinstr. 16",
    "sg:city":"M\u00fcnchen",
    "sg:phone":"+49 89/933128",
    "sg:postcode":"81927",
    "sg:province":"Bayern",
    "wof:name":"Fritz Tippel Ingenieur",
    "wof:placetype":"venue"
},
  "geometry": {"coordinates":[11.6465816498,48.160900116],"type":"Point"}
}