{
  "type": "Feature",
  "properties": {
    "iso:country":"DE",
    "sg:address":"Klingenweg 22/2",
    "sg:city":"Eberbach",
    "sg:phone":"+49 6271/6363",
    "sg:postcode":"69412",
    "sg:province":"Baden-W\u00fcrttemberg",
    "wof:name":"Wolfgang Huber Architekt",
    "wof:placetype":"venue"
},
  "geometry": {"coordinates":[8.97743,49.45256],"type":"Point"}
}