{
  "type": "Feature",
  "properties": {
    "iso:country":"DE",
    "sg:address":"Im Baumhof 26",
    "sg:city":"Wiehl",
    "sg:phone":"+49 2262/91820",
    "sg:postcode":"51674",
    "sg:province":"Nordrhein-Westfalen",
    "wof:name":"Hannelore Becher",
    "wof:placetype":"venue"
},
  "geometry": {"coordinates":[7.5497779846,50.9506797791],"type":"Point"}
}