{
  "type": "Feature",
  "properties": {
    "iso:country":"DE",
    "sg:address":"Rainwaldstr. 3",
    "sg:city":"Oberstaufen",
    "sg:phone":"+49 8386/960242",
    "sg:postcode":"87534",
    "sg:province":"Bayern",
    "wof:name":"Restaurant Gemse",
    "wof:placetype":"venue"
},
  "geometry": {"coordinates":[10.0239257812,47.5539131165],"type":"Point"}
}