{
  "type": "Feature",
  "properties": {
    "iso:country":"DE",
    "sg:address":"Brunnengasse 27",
    "sg:city":"N\u00fcrnberg",
    "sg:phone":"+49 911/223001",
    "sg:postcode":"90402",
    "sg:province":"Bayern",
    "wof:name":"A. Nauke",
    "wof:placetype":"venue"
},
  "geometry": {"coordinates":[11.0758066177,49.4502487183],"type":"Point"}
}