{
  "type": "Feature",
  "properties": {
    "iso:country":"DE",
    "sg:address":"Marktler Str. 35",
    "sg:city":"Burghausen",
    "sg:phone":"+49 8677/3872",
    "sg:postcode":"84489",
    "sg:province":"Bayern",
    "wof:name":"Gerh. Hell",
    "wof:placetype":"venue"
},
  "geometry": {"coordinates":[12.8302688599,48.1721878052],"type":"Point"}
}