{
  "type": "Feature",
  "properties": {
    "iso:country":"DE",
    "sg:address":"Gau\u00dfstr. 2",
    "sg:city":"Herford",
    "sg:phone":"+49 5221/71212",
    "sg:postcode":"32052",
    "sg:province":"Nordrhein-Westfalen",
    "wof:name":"Georg Ottmann",
    "wof:placetype":"venue"
},
  "geometry": {"coordinates":[8.6817073822,52.1028900146],"type":"Point"}
}