{
  "type": "Feature",
  "properties": {
    "iso:country":"DE",
    "sg:address":"Antoniterstr. 47",
    "sg:city":"Alzey",
    "sg:phone":"+49 6731/1285",
    "sg:postcode":"55232",
    "sg:province":"Rheinland-Pfalz",
    "wof:name":"Rebe",
    "wof:placetype":"venue"
},
  "geometry": {"coordinates":[8.1121721268,49.7476806641],"type":"Point"}
}