{
  "type": "Feature",
  "properties": {
    "iso:country":"DE",
    "sg:address":"Esslinger Str. 24",
    "sg:city":"Stuttgart",
    "sg:phone":"+49 711/2364735",
    "sg:postcode":"70182",
    "sg:province":"Baden-W\u00fcrttemberg",
    "wof:name":"W. F. Lenz",
    "wof:placetype":"venue"
},
  "geometry": {"coordinates":[9.18242,48.77454],"type":"Point"}
}