{
  "type": "Feature",
  "properties": {
    "iso:country":"DE",
    "sg:address":"Bahnhofstr. 13",
    "sg:city":"Hambergen",
    "sg:phone":"+49 4793/444",
    "sg:postcode":"27729",
    "sg:province":"Niedersachsen",
    "wof:name":"Fritz Demand",
    "wof:placetype":"venue"
},
  "geometry": {"coordinates":[8.823195,53.308159],"type":"Point"}
}