{
  "type": "Feature",
  "properties": {
    "iso:country":"DE",
    "sg:address":"Bahnhofstr. 35",
    "sg:city":"Neum\u00fcnster",
    "sg:phone":"+49 4321/42589",
    "sg:postcode":"24534",
    "sg:province":"Schleswig-Holstein",
    "wof:name":"Kath. Pfarramt St. Vicelin",
    "wof:placetype":"venue"
},
  "geometry": {"coordinates":[9.9798727036,54.0735626221],"type":"Point"}
}