{
  "type": "Feature",
  "properties": {
    "iso:country":"DE",
    "sg:address":"Bad Sodener Str. 1",
    "sg:city":"Brachttal",
    "sg:phone":"+49 6054/5622",
    "sg:postcode":"63636",
    "sg:province":"Hessen",
    "wof:name":"H. Bergmann Landwirt. Lohnbetrieb",
    "wof:placetype":"venue"
},
  "geometry": {"coordinates":[9.33653,50.31435],"type":"Point"}
}