{
  "type": "Feature",
  "properties": {
    "iso:country":"DE",
    "sg:address":"Bonholzstr. 2-1",
    "sg:city":"Waldenbuch",
    "sg:phone":"+49 7157/72853",
    "sg:postcode":"71111",
    "sg:province":"Baden-W\u00fcrttemberg",
    "wof:name":"Rupro Gmbh",
    "wof:placetype":"venue"
},
  "geometry": {"coordinates":[9.136194,48.62933],"type":"Point"}
}