{
  "type": "Feature",
  "properties": {
    "iso:country":"DE",
    "sg:address":"Br\u00fccknerstr 4",
    "sg:city":"W\u00fcrzburg",
    "sg:phone":"+49 931/23072",
    "sg:postcode":"97070",
    "sg:province":"Bayern",
    "wof:name":"Hypo-bank Ag",
    "wof:placetype":"venue"
},
  "geometry": {"coordinates":[9.944278,49.801865],"type":"Point"}
}