{
  "type": "Feature",
  "properties": {
    "iso:country":"DE",
    "sg:address":"Postfach 25",
    "sg:city":"Treuenbrietzen",
    "sg:postcode":"14929",
    "sg:province":"Brandenburg",
    "wof:name":"Der Spd-ortsverein Treuenbrietzen Im Netz",
    "wof:placetype":"venue"
},
  "geometry": {"coordinates":[12.86752,52.095955],"type":"Point"}
}