{
  "type": "Feature",
  "properties": {
    "iso:country":"DE",
    "sg:address":"Donaustr. 2",
    "sg:city":"Niederalteich",
    "sg:phone":"+49 9901/1669",
    "sg:postcode":"94557",
    "sg:province":"Bayern",
    "wof:name":"Franz Gotzler",
    "wof:placetype":"venue"
},
  "geometry": {"coordinates":[13.0239448547,48.7658615112],"type":"Point"}
}