{
  "type": "Feature",
  "properties": {
    "iso:country":"DE",
    "sg:address":"Mulzerweg 10",
    "sg:city":"Schwandorf",
    "sg:phone":"+49 9431/42070",
    "sg:postcode":"92421",
    "sg:province":"Bayern",
    "wof:name":"Dietmar Schmid",
    "wof:placetype":"venue"
},
  "geometry": {"coordinates":[12.0938949585,49.3338241577],"type":"Point"}
}