{
  "type": "Feature",
  "properties": {
    "iso:country":"DE",
    "sg:address":"Schacht 2",
    "sg:city":"Ummendorf",
    "sg:phone":"+49 39400/2051",
    "sg:postcode":"39365",
    "sg:province":"Sachsen-Anhalt",
    "wof:name":"Agrargenossenschaft Wefensleben Eg",
    "wof:placetype":"venue"
},
  "geometry": {"coordinates":[11.181408,52.16494],"type":"Point"}
}