{
  "type": "Feature",
  "properties": {
    "iso:country":"DE",
    "sg:address":"Hellefelder Str. 64",
    "sg:city":"Arnsberg",
    "sg:phone":"+49 2931/12500",
    "sg:postcode":"59821",
    "sg:province":"Nordrhein-Westfalen",
    "wof:name":"T. Stratenschulte",
    "wof:placetype":"venue"
},
  "geometry": {"coordinates":[8.071151,51.391151],"type":"Point"}
}