{
  "type": "Feature",
  "properties": {
    "iso:country":"DE",
    "sg:address":"Luckaer Str. 36",
    "sg:city":"Windischleuba",
    "sg:postcode":"04603",
    "sg:province":"Th\u00fcringen",
    "wof:name":"C. D. S. Container- Dienstleistungs-",
    "wof:placetype":"venue"
},
  "geometry": {"coordinates":[12.468226,51.016323],"type":"Point"}
}