{
  "type": "Feature",
  "properties": {
    "iso:country":"DE",
    "sg:address":"Abt-Eckhard-Str. 6",
    "sg:city":"Ebersberg",
    "sg:phone":"+49 8092/22176",
    "sg:postcode":"85560",
    "sg:province":"Bayern",
    "wof:name":"Monika Gro\u00df",
    "wof:placetype":"venue"
},
  "geometry": {"coordinates":[11.9736223221,48.0808296204],"type":"Point"}
}