{
  "type": "Feature",
  "properties": {
    "iso:country":"DE",
    "sg:address":"Eichelgartenstr. 2",
    "sg:city":"Frankenhardt",
    "sg:postcode":"74586",
    "sg:province":"Baden-W\u00fcrttemberg",
    "wof:name":"E-daves Gmbh",
    "wof:placetype":"venue"
},
  "geometry": {"coordinates":[10.043346405,49.0659255981],"type":"Point"}
}