{
  "type": "Feature",
  "properties": {
    "iso:country":"DE",
    "sg:address":"Sendstr. 67",
    "sg:city":"Dortmund",
    "sg:phone":"+49 231/92550",
    "sg:postcode":"44309",
    "sg:province":"Nordrhein-Westfalen",
    "wof:name":"Karola-zorwald-zentrum",
    "wof:placetype":"venue"
},
  "geometry": {"coordinates":[7.529471,51.525482],"type":"Point"}
}