{
  "type": "Feature",
  "properties": {
    "iso:country":"DE",
    "sg:address":"Obertal 32",
    "sg:city":"Oberharmersbach",
    "sg:phone":"+49 7837/212",
    "sg:postcode":"77784",
    "sg:province":"Baden-W\u00fcrttemberg",
    "wof:name":"Holz-hobel-impr\u00e4gnierwerk Joachim Lehmann",
    "wof:placetype":"venue"
},
  "geometry": {"coordinates":[8.1466913223,48.3922462463],"type":"Point"}
}