{
  "type": "Feature",
  "properties": {
    "iso:country":"DE",
    "sg:address":"Birkenhain 1 a",
    "sg:city":"Bergisch Gladbach",
    "sg:phone":"+49 2202/30082",
    "sg:postcode":"51469",
    "sg:province":"Nordrhein-Westfalen",
    "wof:name":"Gerhard Ludwig",
    "wof:placetype":"venue"
},
  "geometry": {"coordinates":[7.126641,50.981567],"type":"Point"}
}