{
  "type": "Feature",
  "properties": {
    "iso:country":"DE",
    "sg:address":"Gathe 45",
    "sg:city":"Wuppertal",
    "sg:postcode":"42107",
    "sg:province":"Nordrhein-Westfalen",
    "wof:name":"Enver",
    "wof:placetype":"venue"
},
  "geometry": {"coordinates":[7.1479411125,51.2630119324],"type":"Point"}
}