{
  "type": "Feature",
  "properties": {
    "iso:country":"DE",
    "sg:address":"Moltkestr. 2",
    "sg:city":"Friedrichshafen",
    "sg:phone":"+49 7541/21360",
    "sg:postcode":"88046",
    "sg:province":"Baden-W\u00fcrttemberg",
    "wof:name":"A. Schaugg Jun.",
    "wof:placetype":"venue"
},
  "geometry": {"coordinates":[9.4838228226,47.6532974243],"type":"Point"}
}