{
  "type": "Feature",
  "properties": {
    "iso:country":"DE",
    "sg:address":"Lambertistr. 128",
    "sg:city":"Ahlen",
    "sg:phone":"+49 2382/70800",
    "sg:postcode":"59229",
    "sg:province":"Nordrhein-Westfalen",
    "wof:name":"Peter Stache Werbetechnik",
    "wof:placetype":"venue"
},
  "geometry": {"coordinates":[7.899917,51.720402],"type":"Point"}
}