{
  "type": "Feature",
  "properties": {
    "iso:country":"DE",
    "sg:address":"Klappergasse 4",
    "sg:city":"Krauchenwies",
    "sg:phone":"+49 7576/92292",
    "sg:postcode":"72505",
    "sg:province":"Baden-W\u00fcrttemberg",
    "wof:name":"Buhl",
    "wof:placetype":"venue"
},
  "geometry": {"coordinates":[9.251576,48.017868],"type":"Point"}
}