{
  "type": "Feature",
  "properties": {
    "iso:country":"DE",
    "sg:address":"Kooksweg 5",
    "sg:city":"Oberhausen",
    "sg:postcode":"46147",
    "sg:province":"Nordrhein-Westfalen",
    "wof:name":"Auto Toy Store Gmbh",
    "wof:placetype":"venue"
},
  "geometry": {"coordinates":[6.836231,51.549568],"type":"Point"}
}