{
  "type": "Feature",
  "properties": {
    "iso:country":"DE",
    "sg:address":"Liebigstr. 33",
    "sg:city":"Langen",
    "sg:phone":"+49 800 2311900",
    "sg:postcode":"63225",
    "sg:province":"Hessen",
    "wof:name":"Gerhard Wagner Gmbh",
    "wof:placetype":"venue"
},
  "geometry": {"coordinates":[8.6585140228,50.0002479553],"type":"Point"}
}