{
  "type": "Feature",
  "properties": {
    "iso:country":"DE",
    "sg:address":"Warzenried",
    "sg:city":"Eschlkam",
    "sg:phone":"+49 9947/484",
    "sg:postcode":"93458",
    "sg:province":"Bayern",
    "wof:name":"J. Eisenreich",
    "wof:placetype":"venue"
},
  "geometry": {"coordinates":[12.9450778961,49.2928581238],"type":"Point"}
}