{
  "type": "Feature",
  "properties": {
    "iso:country":"DE",
    "sg:address":"Im Lohfeld 4",
    "sg:city":"Paderborn",
    "sg:phone":"+49 5251/37316",
    "sg:postcode":"33102",
    "sg:province":"Nordrhein-Westfalen",
    "wof:name":"Christian Hage Architekt",
    "wof:placetype":"venue"
},
  "geometry": {"coordinates":[8.73029,51.719597],"type":"Point"}
}