{
  "type": "Feature",
  "properties": {
    "iso:country":"DE",
    "sg:address":"Marienberger Str. 8",
    "sg:city":"Chemnitz",
    "sg:phone":"+49 177 2411948",
    "sg:postcode":"09125",
    "sg:province":"Sachsen",
    "wof:name":"Ralf Franke Rechtsanwalt",
    "wof:placetype":"venue"
},
  "geometry": {"coordinates":[12.9260063171,50.7931213379],"type":"Point"}
}