{
  "type": "Feature",
  "properties": {
    "iso:country":"DE",
    "sg:address":"Sonnenhang 16",
    "sg:city":"Kn\u00fcllwald",
    "sg:phone":"+49 5685/596",
    "sg:postcode":"34593",
    "sg:province":"Hessen",
    "wof:name":"Birgit Geppert",
    "wof:placetype":"venue"
},
  "geometry": {"coordinates":[9.519698143,51.0378875732],"type":"Point"}
}