{
  "type": "Feature",
  "properties": {
    "iso:country":"DE",
    "sg:address":"Barmbeker Str 4a",
    "sg:city":"Hamburg",
    "sg:phone":"+49 40/854090",
    "sg:postcode":"22303",
    "sg:province":"Hamburg",
    "wof:name":"Vest-wood Deutschland Gmbh",
    "wof:placetype":"venue"
},
  "geometry": {"coordinates":[10.0196142197,53.5827674866],"type":"Point"}
}