{
  "type": "Feature",
  "properties": {
    "iso:country":"DE",
    "sg:address":"Barbarastr. 15",
    "sg:city":"Kleinostheim",
    "sg:postcode":"63801",
    "sg:province":"Bayern",
    "wof:name":"Earl Automaten Gmbh Brigitte",
    "wof:placetype":"venue"
},
  "geometry": {"coordinates":[9.0779619217,50.0044555664],"type":"Point"}
}