{
  "type": "Feature",
  "properties": {
    "iso:country":"DE",
    "sg:address":"Haseng\u00e4rtlestr. 52",
    "sg:city":"Aulendorf",
    "sg:phone":"+49 7525/2175",
    "sg:postcode":"88326",
    "sg:province":"Baden-W\u00fcrttemberg",
    "wof:name":"Burger Recycling Gmbh",
    "wof:placetype":"venue"
},
  "geometry": {"coordinates":[9.6351356506,47.9400901794],"type":"Point"}
}