{
  "type": "Feature",
  "properties": {
    "iso:country":"DE",
    "sg:address":"Hohensteiner Str. 12",
    "sg:city":"Untersiemau",
    "sg:phone":"+49 9565/2919",
    "sg:postcode":"96253",
    "sg:province":"Bayern",
    "wof:name":"Helmut H\u00f6llein",
    "wof:placetype":"venue"
},
  "geometry": {"coordinates":[10.962837,50.217953],"type":"Point"}
}