{
  "type": "Feature",
  "properties": {
    "iso:country":"DE",
    "sg:address":"Freiheitstr. 28",
    "sg:city":"Singen",
    "sg:phone":"+49 7731/65146",
    "sg:postcode":"78224",
    "sg:province":"Baden-W\u00fcrttemberg",
    "wof:name":"U. Seeberger",
    "wof:placetype":"venue"
},
  "geometry": {"coordinates":[8.8389883041,47.7629051208],"type":"Point"}
}