{
  "type": "Feature",
  "properties": {
    "iso:country":"DE",
    "sg:city":"Klingenm\u00fcnster",
    "sg:phone":"+49 4963/496475",
    "sg:postcode":"76889",
    "sg:province":"Rheinland-Pfalz",
    "wof:name":"Sparkasse S\u00fcdliche Weinstr. Landau",
    "wof:placetype":"venue"
},
  "geometry": {"coordinates":[8.019159,49.140846],"type":"Point"}
}