{
  "type": "Feature",
  "properties": {
    "iso:country":"DE",
    "sg:address":"Seidlstr. 3",
    "sg:city":"Ingolstadt",
    "sg:phone":"+49 841/81680",
    "sg:postcode":"85049",
    "sg:province":"Bayern",
    "wof:name":"Heinrich W. Schwarz",
    "wof:placetype":"venue"
},
  "geometry": {"coordinates":[11.4040727615,48.7679023743],"type":"Point"}
}