{
  "type": "Feature",
  "properties": {
    "iso:country":"DE",
    "sg:address":"Hofackerweg 1",
    "sg:city":"\u00d6hringen",
    "sg:phone":"+49 7941/36585",
    "sg:postcode":"74613",
    "sg:province":"Baden-W\u00fcrttemberg",
    "wof:name":"K. Busch",
    "wof:placetype":"venue"
},
  "geometry": {"coordinates":[9.5596542358,49.1746482849],"type":"Point"}
}