{
  "type": "Feature",
  "properties": {
    "iso:country":"DE",
    "sg:address":"J\u00e4gerstr. 2",
    "sg:city":"Thurnau",
    "sg:phone":"+49 9228/5445",
    "sg:postcode":"95349",
    "sg:province":"Bayern",
    "wof:name":"Bernd H\u00e4nseler Masseur",
    "wof:placetype":"venue"
},
  "geometry": {"coordinates":[11.395747,50.025681],"type":"Point"}
}