{
  "type": "Feature",
  "properties": {
    "iso:country":"DE",
    "sg:address":"Senefelderstr. 15",
    "sg:city":"Straubing",
    "sg:phone":"+49 9421/61011",
    "sg:postcode":"94315",
    "sg:province":"Bayern",
    "wof:name":"Bavaria Gmbh Immobilien",
    "wof:placetype":"venue"
},
  "geometry": {"coordinates":[12.6199169159,48.8881607056],"type":"Point"}
}