{
  "type": "Feature",
  "properties": {
    "iso:country":"DE",
    "sg:address":"Franz-Mang-Str. 29",
    "sg:city":"Illertissen",
    "sg:phone":"+49 7303/5270",
    "sg:postcode":"89257",
    "sg:province":"Bayern",
    "wof:name":"G. Stecker",
    "wof:placetype":"venue"
},
  "geometry": {"coordinates":[10.108226,48.216476],"type":"Point"}
}