{
  "type": "Feature",
  "properties": {
    "iso:country":"DE",
    "sg:address":"Mulitz 3",
    "sg:city":"Samtens",
    "sg:phone":"+49 38306/1243",
    "sg:postcode":"18573",
    "sg:province":"Mecklenburg-Vorpommern",
    "wof:name":"M. Walther-st\u00f6hr",
    "wof:placetype":"venue"
},
  "geometry": {"coordinates":[13.278982,54.347549],"type":"Point"}
}