{
  "type": "Feature",
  "properties": {
    "iso:country":"DE",
    "sg:address":"Kapellenstr. 8",
    "sg:city":"Aachen",
    "sg:phone":"+49 241/65480",
    "sg:postcode":"52066",
    "sg:province":"Nordrhein-Westfalen",
    "wof:name":"Cafe Esser Franz Josef Esser",
    "wof:placetype":"venue"
},
  "geometry": {"coordinates":[6.092024,50.761635],"type":"Point"}
}