{
  "type": "Feature",
  "properties": {
    "iso:country":"DE",
    "sg:address":"Aachener Str. 319",
    "sg:city":"K\u00f6ln",
    "sg:phone":"+49 221/402636",
    "sg:postcode":"50931",
    "sg:province":"Nordrhein-Westfalen",
    "wof:name":"Blumenhaus Klein Inh. Ruth Platt",
    "wof:placetype":"venue"
},
  "geometry": {"coordinates":[6.914047,50.936626],"type":"Point"}
}