{
  "type": "Feature",
  "properties": {
    "iso:country":"DE",
    "sg:address":"Wodanstr. 7",
    "sg:city":"Velbert",
    "sg:phone":"+49 2052/6463",
    "sg:postcode":"42555",
    "sg:province":"Nordrhein-Westfalen",
    "wof:name":"A. S. Stella Azzurra Velbert Giuseppe Vento",
    "wof:placetype":"venue"
},
  "geometry": {"coordinates":[7.1447401047,51.3716812134],"type":"Point"}
}