{
  "type": "Feature",
  "properties": {
    "iso:country":"DE",
    "sg:address":"Hauptstr. 18",
    "sg:city":"Hamersleben",
    "sg:phone":"+49 39401/6610",
    "sg:postcode":"39393",
    "sg:province":"Sachsen-Anhalt",
    "wof:name":"Elektro-fahrig Inh. Christian Fahrig",
    "wof:placetype":"venue"
},
  "geometry": {"coordinates":[11.08096,52.062164],"type":"Point"}
}