{
  "type": "Feature",
  "properties": {
    "iso:country":"DE",
    "sg:address":"Esusweg 9",
    "sg:city":"82008",
    "sg:postcode":"82008",
    "sg:province":"Bayern",
    "wof:name":"Dejan Jovanovic Homepage",
    "wof:placetype":"venue"
},
  "geometry": {"coordinates":[-104.813599,41.133369],"type":"Point"}
}