{
  "type": "Feature",
  "properties": {
    "iso:country":"DE",
    "sg:address":"M\u00f6wenstr. 8",
    "sg:city":"Wuppertal",
    "sg:phone":"+49 4920/2250710",
    "sg:postcode":"42281",
    "sg:province":"Nordrhein-Westfalen",
    "wof:name":"Wilhelm Sandk\u00dchler Gmbh",
    "wof:placetype":"venue"
},
  "geometry": {"coordinates":[7.197299,51.275139],"type":"Point"}
}