{
  "type": "Feature",
  "properties": {
    "iso:country":"DE",
    "sg:address":"R\u00fcdesheimer Str. 21",
    "sg:city":"Geisenheim",
    "sg:phone":"+49 6722/8383",
    "sg:postcode":"65366",
    "sg:province":"Hessen",
    "wof:name":"Gabriele Schleyer",
    "wof:placetype":"venue"
},
  "geometry": {"coordinates":[7.96495,49.982937],"type":"Point"}
}