{
  "type": "Feature",
  "properties": {
    "iso:country":"DE",
    "sg:address":"Kirchstr. 8",
    "sg:city":"Seelze",
    "sg:phone":"+49 511/406199",
    "sg:postcode":"30926",
    "sg:province":"Niedersachsen",
    "wof:name":"Wolff Und Rolf Rechtsanw\u00e4lte",
    "wof:placetype":"venue"
},
  "geometry": {"coordinates":[9.6410551071,52.3971252441],"type":"Point"}
}