{
  "type": "Feature",
  "properties": {
    "iso:country":"DE",
    "sg:address":"K\u00f6nig-Karl-Str. 83",
    "sg:city":"Stuttgart",
    "sg:phone":"+49 711/568176",
    "sg:postcode":"70372",
    "sg:province":"Baden-W\u00fcrttemberg",
    "wof:name":"Broadway Studios",
    "wof:placetype":"venue"
},
  "geometry": {"coordinates":[9.2137508392,48.8010253906],"type":"Point"}
}