{
  "type": "Feature",
  "properties": {
    "iso:country":"DE",
    "sg:address":"Beguinenstr. 20",
    "sg:city":"Wesel",
    "sg:phone":"+49 281/28377",
    "sg:postcode":"46483",
    "sg:province":"Nordrhein-Westfalen",
    "wof:name":"Manfred Kurtz",
    "wof:placetype":"venue"
},
  "geometry": {"coordinates":[6.6183447838,51.6581687927],"type":"Point"}
}