{
  "type": "Feature",
  "properties": {
    "iso:country":"DE",
    "sg:address":"Ensdorf 15",
    "sg:city":"Kraiburg",
    "sg:phone":"+49 8638/72155",
    "sg:postcode":"84559",
    "sg:province":"Bayern",
    "wof:name":"Erich Althammer",
    "wof:placetype":"venue"
},
  "geometry": {"coordinates":[12.446582,48.190151],"type":"Point"}
}