{
  "type": "Feature",
  "properties": {
    "iso:country":"DE",
    "sg:address":"Stra\u00dfe des Friedens",
    "sg:city":"Lindow",
    "sg:phone":"+49 33933/71547",
    "sg:postcode":"16835",
    "sg:province":"Brandenburg",
    "wof:name":"A. N\u00f6lte",
    "wof:placetype":"venue"
},
  "geometry": {"coordinates":[12.988016,52.971073],"type":"Point"}
}