{
  "type": "Feature",
  "properties": {
    "iso:country":"DE",
    "sg:address":"Tecklenburger Str. 15",
    "sg:city":"Lengerich",
    "sg:phone":"+49 5481/6226",
    "sg:postcode":"49525",
    "sg:province":"Nordrhein-Westfalen",
    "wof:name":"G. Schallenberg Mineral\u00f6lhandelsges. Mbh",
    "wof:placetype":"venue"
},
  "geometry": {"coordinates":[7.8457632065,52.1917228699],"type":"Point"}
}