{
  "type": "Feature",
  "properties": {
    "iso:country":"DE",
    "sg:address":"Kurallee 17",
    "sg:city":"Halle",
    "sg:phone":"+49 345/43497",
    "sg:postcode":"06114",
    "sg:province":"Sachsen-Anhalt",
    "wof:name":"Erich Gittel",
    "wof:placetype":"venue"
},
  "geometry": {"coordinates":[11.9656600952,51.5044250488],"type":"Point"}
}