{
  "type": "Feature",
  "properties": {
    "iso:country":"DE",
    "sg:address":"Akazienstr. 1",
    "sg:city":"Niederkassel",
    "sg:phone":"+49 2208/4125",
    "sg:postcode":"53859",
    "sg:province":"Nordrhein-Westfalen",
    "wof:name":"Reinhard Rochow Farben Und Tapeten",
    "wof:placetype":"venue"
},
  "geometry": {"coordinates":[7.0521240234,50.7938232422],"type":"Point"}
}