{
  "type": "Feature",
  "properties": {
    "iso:country":"DE",
    "sg:address":"Postfach 1304",
    "sg:city":"H\u00fcckelhoven",
    "sg:phone":"+49 190856280",
    "sg:postcode":"41825",
    "sg:province":"Nordrhein-Westfalen",
    "wof:name":"Erosear.ch - Jeder Eintrag Ein Erfolg -",
    "wof:placetype":"venue"
},
  "geometry": {"coordinates":[6.22367,51.052471],"type":"Point"}
}