{
  "type": "Feature",
  "properties": {
    "iso:country":"DE",
    "sg:address":"Querstr. 14",
    "sg:city":"Niederaula",
    "sg:phone":"+49 6625/5132",
    "sg:postcode":"36272",
    "sg:province":"Hessen",
    "wof:name":"Oceana",
    "wof:placetype":"venue"
},
  "geometry": {"coordinates":[9.608195,50.800144],"type":"Point"}
}