{
  "type": "Feature",
  "properties": {
    "iso:country":"DE",
    "sg:address":"Angermunder Weg 41",
    "sg:city":"Ratingen",
    "sg:phone":"+49 2102/443565",
    "sg:postcode":"40880",
    "sg:province":"Nordrhein-Westfalen",
    "wof:name":"G\u00e4stehaus Kaiser Garni",
    "wof:placetype":"venue"
},
  "geometry": {"coordinates":[6.8108038902,51.3035125732],"type":"Point"}
}