{
  "type": "Feature",
  "properties": {
    "iso:country":"DE",
    "sg:address":"Hermsdorfer Str. 26",
    "sg:city":"Berlin",
    "sg:phone":"+49 2208/910023",
    "sg:postcode":"13469",
    "sg:province":"Berlin",
    "wof:name":"Heribert Meinass Ingenieur",
    "wof:placetype":"venue"
},
  "geometry": {"coordinates":[13.3243589401,52.5998344421],"type":"Point"}
}