{
  "type": "Feature",
  "properties": {
    "iso:country":"DE",
    "sg:address":"Lindenstra\u00dfe 38",
    "sg:city":"Greiz",
    "sg:phone":"+49 3661/433871",
    "sg:postcode":"07973",
    "sg:province":"Th\u00fcringen",
    "wof:name":"Ostth\u00dcringer Zeitung Lokalredaktionen Saale-orla",
    "wof:placetype":"venue"
},
  "geometry": {"coordinates":[12.210793,50.654652],"type":"Point"}
}