{
  "type": "Feature",
  "properties": {
    "iso:country":"DE",
    "sg:address":"Silberpappelweg 25",
    "sg:city":"Stuttgart",
    "sg:postcode":"70597",
    "sg:province":"Baden-W\u00fcrttemberg",
    "wof:name":"S\u00fcd G\u00fc Gmbh",
    "wof:placetype":"venue"
},
  "geometry": {"coordinates":[9.1796264648,48.746006012],"type":"Point"}
}