{
  "type": "Feature",
  "properties": {
    "iso:country":"DE",
    "sg:address":"Bahnhofstr. 9",
    "sg:city":"M\u00f6ckern",
    "sg:phone":"+49 39221/5901",
    "sg:postcode":"39291",
    "sg:province":"Sachsen-Anhalt",
    "wof:name":"B-team Gmbh",
    "wof:placetype":"venue"
},
  "geometry": {"coordinates":[11.8493947983,52.145816803],"type":"Point"}
}