{
  "type": "Feature",
  "properties": {
    "iso:country":"DE",
    "sg:address":"Freiberger Str. 73",
    "sg:city":"Pfaffroda",
    "sg:postcode":"09526",
    "sg:province":"Sachsen",
    "wof:name":"S\u00e4ge- Und Hobelwerk",
    "wof:placetype":"venue"
},
  "geometry": {"coordinates":[13.3507614136,50.7071151733],"type":"Point"}
}