{
  "type": "Feature",
  "properties": {
    "iso:country":"DE",
    "sg:address":"Pappelall. 61",
    "sg:city":"Hamburg",
    "sg:phone":"+49 40/658020",
    "sg:postcode":"22089",
    "sg:province":"Hamburg",
    "wof:name":"Ibis - Hotel",
    "wof:placetype":"venue"
},
  "geometry": {"coordinates":[10.061162,53.568745],"type":"Point"}
}