{
  "type": "Feature",
  "properties": {
    "iso:country":"DE",
    "sg:address":"Eichenstr. 4",
    "sg:city":"Kronberg",
    "sg:phone":"+49 6173/78515",
    "sg:postcode":"61476",
    "sg:province":"Hessen",
    "wof:name":"Helmut Ebner Vorm. Ph. Antoni",
    "wof:placetype":"venue"
},
  "geometry": {"coordinates":[8.5075817108,50.1799354553],"type":"Point"}
}