{
  "type": "Feature",
  "properties": {
    "iso:country":"DE",
    "sg:address":"Obere Str. 35",
    "sg:city":"Holzminden",
    "sg:phone":"+49 5531/7429",
    "sg:postcode":"37603",
    "sg:province":"Niedersachsen",
    "wof:name":"Mothes Und Habbel",
    "wof:placetype":"venue"
},
  "geometry": {"coordinates":[9.4465351105,51.827709198],"type":"Point"}
}