{
  "type": "Feature",
  "properties": {
    "iso:country":"DE",
    "sg:address":"Bahnhofstr. 1",
    "sg:city":"Ergoldsbach",
    "sg:phone":"+49 8771/3677",
    "sg:postcode":"84061",
    "sg:province":"Bayern",
    "wof:name":"Bierfilzl",
    "wof:placetype":"venue"
},
  "geometry": {"coordinates":[12.203042984,48.6932792664],"type":"Point"}
}