{
  "type": "Feature",
  "properties": {
    "iso:country":"DE",
    "sg:address":"Rottkamp 3",
    "sg:city":"Coesfeld",
    "sg:phone":"+49 2541/7390",
    "sg:postcode":"48653",
    "sg:province":"Nordrhein-Westfalen",
    "wof:name":"Heinrich Mellmann Gmbh & Co.",
    "wof:placetype":"venue"
},
  "geometry": {"coordinates":[7.172665,51.920067],"type":"Point"}
}