{
  "type": "Feature",
  "properties": {
    "iso:country":"DE",
    "sg:address":"Gleisstr. 10",
    "sg:city":"Hockenheim",
    "sg:postcode":"68766",
    "sg:province":"Baden-W\u00fcrttemberg",
    "wof:name":"Ihr Wasch-platz K. H. Schuetterle",
    "wof:placetype":"venue"
},
  "geometry": {"coordinates":[8.5405931473,49.3272323608],"type":"Point"}
}