{
  "type": "Feature",
  "properties": {
    "iso:country":"DE",
    "sg:address":"Darmst\u00e4dter Str. 10",
    "sg:city":"Gernsheim",
    "sg:phone":"+49 6258/2008",
    "sg:postcode":"64579",
    "sg:province":"Hessen",
    "wof:name":"Kurt Worsch Heilpraktiker",
    "wof:placetype":"venue"
},
  "geometry": {"coordinates":[8.4868297577,49.7543983459],"type":"Point"}
}