{
  "type": "Feature",
  "properties": {
    "iso:country":"DE",
    "sg:address":"Blumenfeldstr. 26",
    "sg:city":"Bochum",
    "sg:phone":"+49 234/434684",
    "sg:postcode":"44795",
    "sg:province":"Nordrhein-Westfalen",
    "wof:name":"Body-gym-weitmar",
    "wof:placetype":"venue"
},
  "geometry": {"coordinates":[7.1870307922,51.4509010315],"type":"Point"}
}