{
  "type": "Feature",
  "properties": {
    "iso:country":"DE",
    "sg:address":"Karlstr. 40",
    "sg:city":"Essen",
    "sg:phone":"+49 201/342571",
    "sg:postcode":"45329",
    "sg:province":"Nordrhein-Westfalen",
    "wof:name":"Norbert Hallmann",
    "wof:placetype":"venue"
},
  "geometry": {"coordinates":[7.011207,51.501301],"type":"Point"}
}