{
  "type": "Feature",
  "properties": {
    "iso:country":"DE",
    "sg:address":"Goethestr. 11",
    "sg:city":"Gotha",
    "sg:phone":"+49 3621/707023",
    "sg:postcode":"99867",
    "sg:province":"Th\u00fcringen",
    "wof:name":"G. Kohl Immobilienmakler",
    "wof:placetype":"venue"
},
  "geometry": {"coordinates":[10.6947250366,50.9418334961],"type":"Point"}
}