{
  "type": "Feature",
  "properties": {
    "iso:country":"DE",
    "sg:address":"Lenggrieser Str. 52-54",
    "sg:city":"Bad T\u00f6lz",
    "sg:phone":"+49 8041/5081",
    "sg:postcode":"83646",
    "sg:province":"Bayern",
    "wof:name":"Moralt Holzwerkstoffe Gmbh & Co. Kg",
    "wof:placetype":"venue"
},
  "geometry": {"coordinates":[11.5627393723,47.7506866455],"type":"Point"}
}