{
  "type": "Feature",
  "properties": {
    "iso:country":"DE",
    "sg:address":"Weseler Str. 14",
    "sg:city":"Alpen",
    "sg:phone":"+49 2802/6837",
    "sg:postcode":"46519",
    "sg:province":"Nordrhein-Westfalen",
    "wof:name":"Artur Van Vorst Gmbh",
    "wof:placetype":"venue"
},
  "geometry": {"coordinates":[6.5121808052,51.5748710632],"type":"Point"}
}