{
  "type": "Feature",
  "properties": {
    "iso:country":"DE",
    "sg:address":"Schragestr. 10",
    "sg:city":"Bremen",
    "sg:phone":"+49 421/647727",
    "sg:postcode":"28239",
    "sg:province":"Bremen",
    "wof:name":"Klaus-j. Zimmermann Fleisch- Und Wurstgro\u00dfhandel",
    "wof:placetype":"venue"
},
  "geometry": {"coordinates":[8.745759964,53.1358909607],"type":"Point"}
}