{
  "type": "Feature",
  "properties": {
    "iso:country":"DE",
    "sg:address":"Gathe 84",
    "sg:city":"Wuppertal",
    "sg:phone":"+49 4920/2442179",
    "sg:postcode":"42107",
    "sg:province":"Nordrhein-Westfalen",
    "wof:name":"Flugb\u00d6rse Cs Reisen Gmbh Inh Dirk Henschel",
    "wof:placetype":"venue"
},
  "geometry": {"coordinates":[7.147514,51.26049],"type":"Point"}
}