{
  "type": "Feature",
  "properties": {
    "iso:country":"DE",
    "sg:address":"Kopernikusweg 2",
    "sg:city":"Laupheim",
    "sg:phone":"+49 7392/96460",
    "sg:postcode":"88471",
    "sg:province":"Baden-W\u00fcrttemberg",
    "wof:name":"Rudolf Me\u00dfmer Steuerberater",
    "wof:placetype":"venue"
},
  "geometry": {"coordinates":[9.8939151764,48.2361679077],"type":"Point"}
}