{
  "type": "Feature",
  "properties": {
    "iso:country":"DE",
    "sg:address":"Hauptstr. 1",
    "sg:city":"Freiburg",
    "sg:phone":"+49 4779/388",
    "sg:postcode":"21729",
    "sg:province":"Niedersachsen",
    "wof:name":"August Steffens",
    "wof:placetype":"venue"
},
  "geometry": {"coordinates":[9.288135,53.824341],"type":"Point"}
}