{
  "type": "Feature",
  "properties": {
    "iso:country":"DE",
    "sg:address":"Burgstr. 4",
    "sg:city":"Rheinfelden",
    "sg:phone":"+49 7623/50538",
    "sg:postcode":"79618",
    "sg:province":"Baden-W\u00fcrttemberg",
    "wof:name":"Rheinblick",
    "wof:placetype":"venue"
},
  "geometry": {"coordinates":[7.813038826,47.5866203308],"type":"Point"}
}