{
  "type": "Feature",
  "properties": {
    "iso:country":"DE",
    "sg:address":"Strehlhoferweg",
    "sg:city":"Volkach",
    "sg:postcode":"97332",
    "sg:province":"Bayern",
    "wof:name":"Wka Gera Gmbh & Co. Kg",
    "wof:placetype":"venue"
},
  "geometry": {"coordinates":[10.233075,49.861229],"type":"Point"}
}