{
  "type": "Feature",
  "properties": {
    "iso:country":"DE",
    "sg:address":"Hildebrandtstr. 24",
    "sg:city":"D\u00fcsseldorf",
    "sg:phone":"+49 211/9337040",
    "sg:postcode":"40215",
    "sg:province":"Nordrhein-Westfalen",
    "wof:name":"Maor Handelsgesellschaft Ohg",
    "wof:placetype":"venue"
},
  "geometry": {"coordinates":[6.784011,51.209953],"type":"Point"}
}