{
  "type": "Feature",
  "properties": {
    "iso:country":"DE",
    "sg:address":"Rennstr. 24",
    "sg:city":"Zerbst",
    "sg:phone":"+49 3923/781982",
    "sg:postcode":"39261",
    "sg:province":"Sachsen-Anhalt",
    "wof:name":"Ralf Riehl",
    "wof:placetype":"venue"
},
  "geometry": {"coordinates":[12.0900859833,51.9696884155],"type":"Point"}
}