{
  "type": "Feature",
  "properties": {
    "iso:country":"DE",
    "sg:address":"Bruchsaler Str. 17",
    "sg:city":"Weingarten",
    "sg:phone":"+49 4972/1576078",
    "sg:postcode":"76356",
    "sg:province":"Baden-W\u00fcrttemberg",
    "wof:name":"Sparkasse Karlsruhe",
    "wof:placetype":"venue"
},
  "geometry": {"coordinates":[8.381752,49.044903],"type":"Point"}
}