{
  "type": "Feature",
  "properties": {
    "iso:country":"DE",
    "sg:address":"An der Wende 14",
    "sg:city":"Gummersbach",
    "sg:phone":"+49 2261/60190",
    "sg:postcode":"51643",
    "sg:province":"Nordrhein-Westfalen",
    "wof:name":"Avb Allgemeine Verwaltungs- Und Beteiligungs-gmbh",
    "wof:placetype":"venue"
},
  "geometry": {"coordinates":[7.5380301476,51.0261688232],"type":"Point"}
}