{
  "type": "Feature",
  "properties": {
    "iso:country":"DE",
    "sg:address":"Hauptstr. 40",
    "sg:city":"Eberstadt",
    "sg:phone":"+49 7134/961040",
    "sg:postcode":"74246",
    "sg:province":"Baden-W\u00fcrttemberg",
    "wof:name":"G. Hebert",
    "wof:placetype":"venue"
},
  "geometry": {"coordinates":[9.3216543198,49.1793060303],"type":"Point"}
}