{
  "type": "Feature",
  "properties": {
    "iso:country":"DE",
    "sg:address":"Holtenauer Str. 45",
    "sg:city":"Kiel",
    "sg:phone":"+49 431/565756",
    "sg:postcode":"24105",
    "sg:province":"Schleswig-Holstein",
    "wof:name":"Tempo Schnell-reinigung Inh. Wolfgang Schoen",
    "wof:placetype":"venue"
},
  "geometry": {"coordinates":[10.131952,54.331993],"type":"Point"}
}