{
  "type": "Feature",
  "properties": {
    "iso:country":"DE",
    "sg:address":"Industriestr 6",
    "sg:city":"Haiterbach",
    "sg:phone":"+49 7469/4110",
    "sg:postcode":"72221",
    "sg:province":"Baden-W\u00fcrttemberg",
    "wof:name":"Ms Schwarzwaldm\u00f6bel M. Schuon Gmbh",
    "wof:placetype":"venue"
},
  "geometry": {"coordinates":[8.625696,48.506626],"type":"Point"}
}