{
  "type": "Feature",
  "properties": {
    "iso:country":"DE",
    "sg:address":"Berckheimstr. 1",
    "sg:city":"Dillingen",
    "sg:phone":"+49 6831/707873",
    "sg:postcode":"66763",
    "sg:province":"Saarland",
    "wof:name":"Deutsche Bahn Ag",
    "wof:placetype":"venue"
},
  "geometry": {"coordinates":[6.7247109413,49.3511199951],"type":"Point"}
}