{
  "type": "Feature",
  "properties": {
    "iso:country":"DE",
    "sg:address":"Im Floting 2",
    "sg:city":"Bad M\u00fcnstereifel",
    "sg:phone":"+49 2253/930063",
    "sg:postcode":"53902",
    "sg:province":"Nordrhein-Westfalen",
    "wof:name":"Johannes Dederichs",
    "wof:placetype":"venue"
},
  "geometry": {"coordinates":[6.7956829071,50.6002197266],"type":"Point"}
}