{
  "type": "Feature",
  "properties": {
    "iso:country":"DE",
    "sg:address":"Bernadottestr. 34",
    "sg:city":"Frankfurt",
    "sg:phone":"+49 69/573108",
    "sg:postcode":"60439",
    "sg:province":"Hessen",
    "wof:name":"W. Barthel",
    "wof:placetype":"venue"
},
  "geometry": {"coordinates":[8.629847,50.157764],"type":"Point"}
}