{
  "type": "Feature",
  "properties": {
    "iso:country":"DE",
    "sg:address":"Kirchweg 4",
    "sg:city":"Bettenfeld",
    "sg:phone":"+49 6572/572",
    "sg:postcode":"54533",
    "sg:province":"Rheinland-Pfalz",
    "wof:name":"Willi Roden",
    "wof:placetype":"venue"
},
  "geometry": {"coordinates":[6.759018898,50.0859718323],"type":"Point"}
}