{
  "type": "Feature",
  "properties": {
    "iso:country":"DE",
    "sg:address":"Harretstr 6",
    "sg:city":"Eningen",
    "sg:phone":"+49 7121/989833",
    "sg:postcode":"72800",
    "sg:province":"Baden-W\u00fcrttemberg",
    "wof:name":"Ensslin Im Arena Verlag Gmbh",
    "wof:placetype":"venue"
},
  "geometry": {"coordinates":[9.2570476532,48.4746437073],"type":"Point"}
}