{
  "type": "Feature",
  "properties": {
    "iso:country":"DE",
    "sg:address":"Grindelallee",
    "sg:city":"Hamburg",
    "sg:phone":"+49 40/41351295",
    "sg:postcode":"20146",
    "sg:province":"Hamburg",
    "wof:name":"Global Web Promotion",
    "wof:placetype":"venue"
},
  "geometry": {"coordinates":[9.9796152115,53.5690765381],"type":"Point"}
}