{
  "type": "Feature",
  "properties": {
    "iso:country":"DE",
    "sg:address":"Karlstr. 8",
    "sg:city":"Zirndorf",
    "sg:phone":"+49 911/606077",
    "sg:postcode":"90513",
    "sg:province":"Bayern",
    "wof:name":"Pickel & Macher",
    "wof:placetype":"venue"
},
  "geometry": {"coordinates":[10.960888,49.441151],"type":"Point"}
}