{
  "type": "Feature",
  "properties": {
    "iso:country":"DE",
    "sg:address":"Schweinfurter Str. 56",
    "sg:city":"Gochsheim",
    "sg:phone":"+49 9721/62167",
    "sg:postcode":"97469",
    "sg:province":"Bayern",
    "wof:name":"H. Geyer",
    "wof:placetype":"venue"
},
  "geometry": {"coordinates":[10.2789268494,50.0209465027],"type":"Point"}
}