{
  "type": "Feature",
  "properties": {
    "iso:country":"DE",
    "sg:address":"Kuhlhoffstr. 40",
    "sg:city":"Essen",
    "sg:phone":"+49 201/356109",
    "sg:postcode":"45329",
    "sg:province":"Nordrhein-Westfalen",
    "wof:name":"R. M\u00fcller Transport Gmbh",
    "wof:placetype":"venue"
},
  "geometry": {"coordinates":[7.0238308907,51.5084686279],"type":"Point"}
}