{
  "type": "Feature",
  "properties": {
    "iso:country":"DE",
    "sg:address":"Ludwigstr. 4",
    "sg:city":"Feldkirchen",
    "sg:phone":"+49 89/9034283",
    "sg:postcode":"85622",
    "sg:province":"Bayern",
    "wof:name":"J. Karbaumer",
    "wof:placetype":"venue"
},
  "geometry": {"coordinates":[11.725151062,48.1460418701],"type":"Point"}
}