{
  "type": "Feature",
  "properties": {
    "iso:country":"DE",
    "sg:address":"Max-von-Eyth-Str. 5",
    "sg:city":"Landsberg",
    "sg:phone":"+49 8191/46053",
    "sg:postcode":"86899",
    "sg:province":"Bayern",
    "wof:name":"Paul Wachter Gmbh",
    "wof:placetype":"venue"
},
  "geometry": {"coordinates":[10.858088,48.063763],"type":"Point"}
}