{
  "type": "Feature",
  "properties": {
    "iso:country":"DE",
    "sg:address":"Gottfried-B\u00f6hm-Ring 34",
    "sg:city":"M\u00fcnchen",
    "sg:phone":"+49 89/786126",
    "sg:postcode":"81369",
    "sg:province":"Bayern",
    "wof:name":"H. G. Ex Dentalvertriebs Gmbh",
    "wof:placetype":"venue"
},
  "geometry": {"coordinates":[11.527986,48.109325],"type":"Point"}
}