{
  "type": "Feature",
  "properties": {
    "iso:country":"DE",
    "sg:address":"Tannenweg 6",
    "sg:city":"Sulzbach-Rosenberg",
    "sg:phone":"+49 9661/6102",
    "sg:postcode":"92237",
    "sg:province":"Bayern",
    "wof:name":"E. Stubenvoll",
    "wof:placetype":"venue"
},
  "geometry": {"coordinates":[11.798158,49.485786],"type":"Point"}
}