{
  "type": "Feature",
  "properties": {
    "iso:country":"DE",
    "sg:address":"Neustadter Str. 9",
    "sg:city":"Coburg",
    "sg:phone":"+49 9561/86320",
    "sg:postcode":"96450",
    "sg:province":"Bayern",
    "wof:name":"Dat Pr\u00fcf- Und Sch\u00e4tzungsstelle",
    "wof:placetype":"venue"
},
  "geometry": {"coordinates":[10.970072,50.272289],"type":"Point"}
}