{
  "type": "Feature",
  "properties": {
    "iso:country":"DE",
    "sg:address":"Tulpenweg 2",
    "sg:city":"Mudersbach",
    "sg:phone":"+49 2745/930082",
    "sg:postcode":"57555",
    "sg:province":"Rheinland-Pfalz",
    "wof:name":"Ursula Hamb\u00fcrger",
    "wof:placetype":"venue"
},
  "geometry": {"coordinates":[7.944106102,50.8262672424],"type":"Point"}
}