{
  "type": "Feature",
  "properties": {
    "iso:country":"DE",
    "sg:address":"Wilhelmstr. 13",
    "sg:city":"Nienburg",
    "sg:phone":"+49 5021/97710",
    "sg:postcode":"31582",
    "sg:province":"Niedersachsen",
    "wof:name":"Schwarck Und Radtke Rechtsanw\u00e4lte",
    "wof:placetype":"venue"
},
  "geometry": {"coordinates":[9.2124557495,52.6434440613],"type":"Point"}
}