{
  "type": "Feature",
  "properties": {
    "iso:country":"DE",
    "sg:address":"Alzeyer Str. 162",
    "sg:city":"Fl\u00f6rsheim-Dalsheim",
    "sg:phone":"+49 6243/398",
    "sg:postcode":"67592",
    "sg:province":"Rheinland-Pfalz",
    "wof:name":"Gerhard Jost",
    "wof:placetype":"venue"
},
  "geometry": {"coordinates":[8.2027044296,49.6637458801],"type":"Point"}
}