{
  "type": "Feature",
  "properties": {
    "iso:country":"DE",
    "sg:address":"Wetzlarer Str. 9",
    "sg:city":"Hohenahr",
    "sg:phone":"+49 6446/921219",
    "sg:postcode":"35644",
    "sg:province":"Hessen",
    "wof:name":"Bistro U. Pizzaria Taormina",
    "wof:placetype":"venue"
},
  "geometry": {"coordinates":[8.5162744522,50.6507492065],"type":"Point"}
}