{
  "type": "Feature",
  "properties": {
    "iso:country":"DE",
    "sg:address":"Osterbrooksweg 42",
    "sg:city":"Schenefeld",
    "sg:phone":"+49 40/830330",
    "sg:postcode":"22869",
    "sg:province":"Schleswig-Holstein",
    "wof:name":"Interschalt Gmbh",
    "wof:placetype":"venue"
},
  "geometry": {"coordinates":[9.834312,53.592659],"type":"Point"}
}