{
  "type": "Feature",
  "properties": {
    "iso:country":"DE",
    "sg:address":"Setzer Weg 8",
    "sg:city":"Siegen",
    "sg:phone":"+49 271/72777",
    "sg:postcode":"57076",
    "sg:province":"Nordrhein-Westfalen",
    "wof:name":"Prof. Dr. G\u00fcnter Kretschmer",
    "wof:placetype":"venue"
},
  "geometry": {"coordinates":[8.0285234451,50.9017524719],"type":"Point"}
}