{
  "type": "Feature",
  "properties": {
    "iso:country":"DE",
    "sg:address":"Am Zehnthof 63",
    "sg:city":"Dortmund",
    "sg:phone":"+49 231/596453",
    "sg:postcode":"44141",
    "sg:province":"Nordrhein-Westfalen",
    "wof:name":"Patzer & Schlegel Inhaber Torsten Schlegel E. K.",
    "wof:placetype":"venue"
},
  "geometry": {"coordinates":[7.5087609291,51.5111656189],"type":"Point"}
}