{
  "type": "Feature",
  "properties": {
    "iso:country":"DE",
    "sg:address":"Caspar-M\u00fcller-Str. 18",
    "sg:city":"Euskirchen",
    "sg:phone":"+49 2251/6888",
    "sg:postcode":"53881",
    "sg:province":"Nordrhein-Westfalen",
    "wof:name":"Kath. Pfarramt St. Stephanus",
    "wof:placetype":"venue"
},
  "geometry": {"coordinates":[6.808827877,50.6448059082],"type":"Point"}
}