{
  "type": "Feature",
  "properties": {
    "iso:country":"DE",
    "sg:address":"Viktor-Wildsch\u00fctte-Str. 9",
    "sg:city":"Forst",
    "sg:phone":"+49 7251/86512",
    "sg:postcode":"76694",
    "sg:province":"Baden-W\u00fcrttemberg",
    "wof:name":"Mbi Manfred B\u00f6ser Industrievertrieb Gmbh",
    "wof:placetype":"venue"
},
  "geometry": {"coordinates":[8.5941543579,49.1544418335],"type":"Point"}
}