{
  "type": "Feature",
  "properties": {
    "iso:country":"DE",
    "sg:address":"Lagesche Str. 83",
    "sg:city":"Lemgo",
    "sg:postcode":"32657",
    "sg:province":"Nordrhein-Westfalen",
    "wof:name":"Eilers Gmbh & Co. Kg",
    "wof:placetype":"venue"
},
  "geometry": {"coordinates":[8.879732132,52.0215873718],"type":"Point"}
}