{
  "type": "Feature",
  "properties": {
    "iso:country":"DE",
    "sg:address":"Petzer Str. 9",
    "sg:city":"B\u00fcckeburg",
    "sg:phone":"+49 5722/1475",
    "sg:postcode":"31675",
    "sg:province":"Niedersachsen",
    "wof:name":"Grill Bei Mirko",
    "wof:placetype":"venue"
},
  "geometry": {"coordinates":[9.0294055939,52.2648620605],"type":"Point"}
}