{
  "type": "Feature",
  "properties": {
    "iso:country":"DE",
    "sg:address":"Bahnhofstr. 20",
    "sg:city":"Warstein",
    "sg:phone":"+49 2902/71797",
    "sg:postcode":"59581",
    "sg:province":"Nordrhein-Westfalen",
    "wof:name":"Brillen Rottler Ohg",
    "wof:placetype":"venue"
},
  "geometry": {"coordinates":[8.3364467621,51.4866905212],"type":"Point"}
}