{
  "type": "Feature",
  "properties": {
    "iso:country":"DE",
    "sg:address":"Am Messenbruch 19",
    "sg:city":"Bad M\u00fcnder",
    "sg:phone":"+49 5042/3457",
    "sg:postcode":"31848",
    "sg:province":"Niedersachsen",
    "wof:name":"Knief Gmbh",
    "wof:placetype":"venue"
},
  "geometry": {"coordinates":[9.4138898849,52.1980895996],"type":"Point"}
}