{
  "type": "Feature",
  "properties": {
    "iso:country":"DE",
    "sg:address":"Wittelsbachstr. 39",
    "sg:city":"D\u00fcsseldorf",
    "sg:phone":"+49 211/681707",
    "sg:postcode":"40629",
    "sg:province":"Nordrhein-Westfalen",
    "wof:name":"Resch Gmbh",
    "wof:placetype":"venue"
},
  "geometry": {"coordinates":[6.8351178169,51.2368812561],"type":"Point"}
}