{
  "type": "Feature",
  "properties": {
    "iso:country":"DE",
    "sg:address":"Am Rathaus 6",
    "sg:city":"K\u00fcps",
    "sg:phone":"+49 9264/9640",
    "sg:postcode":"96328",
    "sg:province":"Bayern",
    "wof:name":"Reiseb\u00fcro Extratours B. Grampp E. K.",
    "wof:placetype":"venue"
},
  "geometry": {"coordinates":[11.2749052048,50.1923217773],"type":"Point"}
}