{
  "type": "Feature",
  "properties": {
    "iso:country":"DE",
    "sg:address":"Kantstr. 6 c",
    "sg:city":"Heidenau",
    "sg:postcode":"01809",
    "sg:province":"Sachsen",
    "wof:name":"Dr. Med. Hans-dietrich Bauer",
    "wof:placetype":"venue"
},
  "geometry": {"coordinates":[13.867511,50.982391],"type":"Point"}
}