{
  "type": "Feature",
  "properties": {
    "iso:country":"DE",
    "sg:address":"Rechthienstr. 8",
    "sg:city":"Bad Vilbel",
    "sg:phone":"+49 6101/85280",
    "sg:postcode":"61118",
    "sg:province":"Hessen",
    "wof:name":"Maria R\u00f6ll",
    "wof:placetype":"venue"
},
  "geometry": {"coordinates":[8.7406902313,50.1773834229],"type":"Point"}
}