{
  "type": "Feature",
  "properties": {
    "iso:country":"DE",
    "sg:address":"Schlo\u00dfstr. 41",
    "sg:city":"Barby",
    "sg:phone":"+49 39298/7493",
    "sg:postcode":"39249",
    "sg:province":"Sachsen-Anhalt",
    "wof:name":"Kurt R\u00f6\u00dfner",
    "wof:placetype":"venue"
},
  "geometry": {"coordinates":[11.8343639374,51.993144989],"type":"Point"}
}