{
  "type": "Feature",
  "properties": {
    "iso:country":"DE",
    "sg:address":"Neuburger Str 3",
    "sg:city":"P\u00f6ttmes",
    "sg:phone":"+49 8253/6466",
    "sg:postcode":"86554",
    "sg:province":"Bayern",
    "wof:name":"Druckerei Schlaegel",
    "wof:placetype":"venue"
},
  "geometry": {"coordinates":[11.087467,48.585548],"type":"Point"}
}