{
  "type": "Feature",
  "properties": {
    "iso:country":"DE",
    "sg:address":"Im Dorn 9",
    "sg:city":"Neustadt",
    "sg:phone":"+49 5032/3621",
    "sg:postcode":"31535",
    "sg:province":"Niedersachsen",
    "wof:name":"Friedrich Re\u00dfmeyer",
    "wof:placetype":"venue"
},
  "geometry": {"coordinates":[9.534465,52.562756],"type":"Point"}
}