{
  "type": "Feature",
  "properties": {
    "iso:country":"DE",
    "sg:address":"Adersstr. 72",
    "sg:city":"D\u00fcsseldorf",
    "sg:phone":"+49 211/3858913",
    "sg:postcode":"40215",
    "sg:province":"Nordrhein-Westfalen",
    "wof:name":"Ralf Hillebrand",
    "wof:placetype":"venue"
},
  "geometry": {"coordinates":[6.7862682343,51.2180328369],"type":"Point"}
}