{
  "type": "Feature",
  "properties": {
    "iso:country":"DE",
    "sg:address":"Markt 34",
    "sg:city":"Waldershof",
    "sg:phone":"+49 9231/72896",
    "sg:postcode":"95679",
    "sg:province":"Bayern",
    "wof:name":"A. H\u00e4rtl",
    "wof:placetype":"venue"
},
  "geometry": {"coordinates":[12.0626192093,49.9776000977],"type":"Point"}
}