{
  "type": "Feature",
  "properties": {
    "iso:country":"DE",
    "sg:address":"Alte Bergstr. 91",
    "sg:city":"Alsbach-H\u00e4hnlein",
    "sg:phone":"+49 6257/1009",
    "sg:postcode":"64665",
    "sg:province":"Hessen",
    "wof:name":"P. Pschera",
    "wof:placetype":"venue"
},
  "geometry": {"coordinates":[8.6229228973,49.7454299927],"type":"Point"}
}