{
  "type": "Feature",
  "properties": {
    "iso:country":"DE",
    "sg:address":"Sonnenstr. 2",
    "sg:city":"Gie\u00dfen",
    "sg:phone":"+49 641/932100",
    "sg:postcode":"35390",
    "sg:province":"Hessen",
    "wof:name":"Haftpflichtverband Der Deutschen Industrie V. Ag",
    "wof:placetype":"venue"
},
  "geometry": {"coordinates":[8.6762666702,50.5864105225],"type":"Point"}
}