{
  "type": "Feature",
  "properties": {
    "iso:country":"DE",
    "sg:address":"Rostocker Str. 12",
    "sg:city":"Ratingen",
    "sg:phone":"+49 2102/474375",
    "sg:postcode":"40880",
    "sg:province":"Nordrhein-Westfalen",
    "wof:name":"Richard Schr\u00f6der Steuerberater",
    "wof:placetype":"venue"
},
  "geometry": {"coordinates":[6.8277368546,51.2901000977],"type":"Point"}
}