{
  "type": "Feature",
  "properties": {
    "iso:country":"DE",
    "sg:address":"Bahnhofstr. 73",
    "sg:city":"Gingen",
    "sg:phone":"+49 7162/41360",
    "sg:postcode":"73333",
    "sg:province":"Baden-W\u00fcrttemberg",
    "wof:name":"Kastanienhof",
    "wof:placetype":"venue"
},
  "geometry": {"coordinates":[9.7868251801,48.660736084],"type":"Point"}
}