{
  "type": "Feature",
  "properties": {
    "iso:country":"DE",
    "sg:address":"Lange Str. 29",
    "sg:city":"Dannenberg",
    "sg:phone":"+49 5861/2207",
    "sg:postcode":"29451",
    "sg:province":"Niedersachsen",
    "wof:name":"Buchdruckerei Otto Dennstedt",
    "wof:placetype":"venue"
},
  "geometry": {"coordinates":[11.090345,53.09668],"type":"Point"}
}