{
  "type": "Feature",
  "properties": {
    "iso:country":"DE",
    "sg:address":"Niggenb\u00f6lling 1",
    "sg:city":"Hagen",
    "sg:phone":"+49 2337/8321",
    "sg:postcode":"58091",
    "sg:province":"Nordrhein-Westfalen",
    "wof:name":"Walter Fischer",
    "wof:placetype":"venue"
},
  "geometry": {"coordinates":[7.564999,51.295895],"type":"Point"}
}