{
  "type": "Feature",
  "properties": {
    "iso:country":"DE",
    "sg:address":"Insel Mainau",
    "sg:city":"Konstanz",
    "sg:phone":"+49 7531/303101",
    "sg:postcode":"78465",
    "sg:province":"Baden-W\u00fcrttemberg",
    "wof:name":"Lennart-bernadotte-stiftung",
    "wof:placetype":"venue"
},
  "geometry": {"coordinates":[9.1890592575,47.7044944763],"type":"Point"}
}