{
  "type": "Feature",
  "properties": {
    "iso:country":"DE",
    "sg:address":"Schwarzerden 44",
    "sg:city":"Celle",
    "sg:phone":"+49 5141/47328",
    "sg:postcode":"29225",
    "sg:province":"Niedersachsen",
    "wof:name":"Robert M\u00fcller",
    "wof:placetype":"venue"
},
  "geometry": {"coordinates":[10.019997,52.604401],"type":"Point"}
}