{
  "type": "Feature",
  "properties": {
    "iso:country":"DE",
    "sg:address":"K\u00f6nigsbr\u00fccker Str. 67",
    "sg:city":"Dresden",
    "sg:phone":"+49 351/4715931",
    "sg:postcode":"01099",
    "sg:province":"Sachsen",
    "wof:name":"Treukontax Steuerberatungsges. Mbh",
    "wof:placetype":"venue"
},
  "geometry": {"coordinates":[13.7516994476,51.0727996826],"type":"Point"}
}