{
  "type": "Feature",
  "properties": {
    "iso:country":"DE",
    "sg:address":"Bismarckstr. 4",
    "sg:city":"Bad Harzburg",
    "sg:phone":"+49 5322/1368",
    "sg:postcode":"38667",
    "sg:province":"Niedersachsen",
    "wof:name":"K. Und W.",
    "wof:placetype":"venue"
},
  "geometry": {"coordinates":[10.5547208786,51.886756897],"type":"Point"}
}