{
  "type": "Feature",
  "properties": {
    "iso:country":"DE",
    "sg:address":"Kanadische Str. 14",
    "sg:city":"Emden",
    "sg:phone":"+49 4921/80010",
    "sg:postcode":"26723",
    "sg:province":"Niedersachsen",
    "wof:name":"L\u00f6schen & Partner",
    "wof:placetype":"venue"
},
  "geometry": {"coordinates":[7.17835,53.341995],"type":"Point"}
}