{
  "type": "Feature",
  "properties": {
    "iso:country":"DE",
    "sg:address":"Ulmer Str. 121",
    "sg:city":"Stuttgart",
    "sg:phone":"+49 711/465050",
    "sg:postcode":"70188",
    "sg:province":"Baden-W\u00fcrttemberg",
    "wof:name":"Bergmann Elektrotechnik Gmbh",
    "wof:placetype":"venue"
},
  "geometry": {"coordinates":[9.207927,48.782021],"type":"Point"}
}