{
  "type": "Feature",
  "properties": {
    "iso:country":"DE",
    "sg:address":"Hauptstr. 28",
    "sg:city":"Vorra",
    "sg:phone":"+49 9152/8567",
    "sg:postcode":"91247",
    "sg:province":"Bayern",
    "wof:name":"E. Volk Wettannahme",
    "wof:placetype":"venue"
},
  "geometry": {"coordinates":[11.492176,49.55735],"type":"Point"}
}