{
  "type": "Feature",
  "properties": {
    "iso:country":"DE",
    "sg:address":"Konrad-Adenauer-Str 4",
    "sg:city":"Neustadt",
    "sg:phone":"+49 6321/86066",
    "sg:postcode":"67433",
    "sg:province":"Rheinland-Pfalz",
    "wof:name":"Jotter & Ibelsh\u00e4user Werbeagentur Gbr",
    "wof:placetype":"venue"
},
  "geometry": {"coordinates":[8.139912,49.353344],"type":"Point"}
}