{
  "type": "Feature",
  "properties": {
    "iso:country":"DE",
    "sg:address":"Kirchenstr. 6",
    "sg:city":"Trittau",
    "sg:phone":"+49 4154/3091",
    "sg:postcode":"22946",
    "sg:province":"Schleswig-Holstein",
    "wof:name":"Paul G\u00fcnther Reiseb\u00fcro Gmbh",
    "wof:placetype":"venue"
},
  "geometry": {"coordinates":[10.4034700394,53.6123962402],"type":"Point"}
}