{
  "type": "Feature",
  "properties": {
    "iso:country":"DE",
    "sg:address":"Otto-Hahn-Str. 22",
    "sg:city":"Borken",
    "sg:postcode":"46325",
    "sg:province":"Nordrhein-Westfalen",
    "wof:name":"Best Food Fleisch- Und Gem\u00fcseprodukte Gmbh",
    "wof:placetype":"venue"
},
  "geometry": {"coordinates":[6.8722419739,51.8563041687],"type":"Point"}
}