{
  "type": "Feature",
  "properties": {
    "iso:country":"DE",
    "sg:address":"Waldemarstr. 3",
    "sg:city":"Berlin",
    "sg:phone":"+49 30/4759890",
    "sg:postcode":"13156",
    "sg:province":"Berlin",
    "wof:name":"Heiteg Gmbh",
    "wof:placetype":"venue"
},
  "geometry": {"coordinates":[13.4091396332,52.5856132507],"type":"Point"}
}