{
  "type": "Feature",
  "properties": {
    "iso:country":"DE",
    "sg:address":"Eckertshohl",
    "sg:city":"Nickenich",
    "sg:phone":"+49 2632/81594",
    "sg:postcode":"56645",
    "sg:province":"Rheinland-Pfalz",
    "wof:name":"K. Hohnsbehn",
    "wof:placetype":"venue"
},
  "geometry": {"coordinates":[7.334921,50.411755],"type":"Point"}
}