{
  "type": "Feature",
  "properties": {
    "iso:country":"DE",
    "sg:address":"Gewerbestr. 83",
    "sg:city":"Gundelfingen",
    "sg:phone":"+49 761/582525",
    "sg:postcode":"79194",
    "sg:province":"Baden-W\u00fcrttemberg",
    "wof:name":"R. Werner \u00dcberdachungsbau-technik Gmbh",
    "wof:placetype":"venue"
},
  "geometry": {"coordinates":[7.861775,48.044395],"type":"Point"}
}