{
  "type": "Feature",
  "properties": {
    "iso:country":"DE",
    "sg:address":"Schlachthofstr. 1",
    "sg:city":"Schwabach",
    "sg:postcode":"91126",
    "sg:province":"Bayern",
    "wof:name":"Wolfgang Hertrich Fleischerei- Bedarf Gro\u00df- U. Einzelh. E. K.",
    "wof:placetype":"venue"
},
  "geometry": {"coordinates":[11.04379,49.33181],"type":"Point"}
}