{
  "type": "Feature",
  "properties": {
    "iso:country":"DE",
    "sg:address":"Uhlandstrasse 13",
    "sg:city":"Adelmannsfelden",
    "sg:phone":"+49 7963/8231",
    "sg:postcode":"73486",
    "sg:province":"Baden-W\u00fcrttemberg",
    "wof:name":"Tierschutzjugend People For Animal Rights (par)",
    "wof:placetype":"venue"
},
  "geometry": {"coordinates":[10.006243,48.951534],"type":"Point"}
}