{
  "type": "Feature",
  "properties": {
    "iso:country":"DE",
    "sg:address":"Ernst-Th\u00e4lmann-Str. 7",
    "sg:city":"Wei\u00dfenberg",
    "sg:phone":"+49 35876/42810",
    "sg:postcode":"02627",
    "sg:province":"Sachsen",
    "wof:name":"Renate Staude",
    "wof:placetype":"venue"
},
  "geometry": {"coordinates":[14.66061306,51.1969032288],"type":"Point"}
}