{
  "type": "Feature",
  "properties": {
    "iso:country":"DE",
    "sg:address":"Am M\u00fchlstetter Graben 7",
    "sg:city":"Puchheim",
    "sg:phone":"+49 89/89009661",
    "sg:postcode":"82178",
    "sg:province":"Bayern",
    "wof:name":"Marlies Und Bernhard Eller",
    "wof:placetype":"venue"
},
  "geometry": {"coordinates":[11.35814,48.171928],"type":"Point"}
}