{
  "type": "Feature",
  "properties": {
    "iso:country":"DE",
    "sg:address":"Deuil-La-Barre-Str. 9",
    "sg:city":"Frankfurt",
    "sg:phone":"+49 69/5071405",
    "sg:postcode":"60437",
    "sg:province":"Hessen",
    "wof:name":"Kurt Reinsch Elektroinstallation",
    "wof:placetype":"venue"
},
  "geometry": {"coordinates":[8.667325,50.197269],"type":"Point"}
}