{
  "type": "Feature",
  "properties": {
    "iso:country":"DE",
    "sg:address":"Edigheimer Str. 100",
    "sg:city":"Ludwigshafen",
    "sg:phone":"+49 621/654604",
    "sg:postcode":"67069",
    "sg:province":"Rheinland-Pfalz",
    "wof:name":"R. Hauck",
    "wof:placetype":"venue"
},
  "geometry": {"coordinates":[8.3985729218,49.5254440308],"type":"Point"}
}