{
  "type": "Feature",
  "properties": {
    "iso:country":"DE",
    "sg:address":"Kaldenhoverbaum 2",
    "sg:city":"Essen",
    "sg:phone":"+49 201/671549",
    "sg:postcode":"45359",
    "sg:province":"Nordrhein-Westfalen",
    "wof:name":"Willi Holtwiesche",
    "wof:placetype":"venue"
},
  "geometry": {"coordinates":[6.941719,51.454628],"type":"Point"}
}