{
  "type": "Feature",
  "properties": {
    "iso:country":"DE",
    "sg:address":"Landgrafenstr. 31",
    "sg:city":"K\u00f6ln",
    "sg:phone":"+49 221/9405900",
    "sg:postcode":"50931",
    "sg:province":"Nordrhein-Westfalen",
    "wof:name":"Solidaris Treuhand Gmbh",
    "wof:placetype":"venue"
},
  "geometry": {"coordinates":[6.9109921455,50.9269790649],"type":"Point"}
}