{
  "type": "Feature",
  "properties": {
    "iso:country":"DE",
    "sg:address":"Schaafhausen 16",
    "sg:city":"Dannenberg",
    "sg:phone":"+49 5861/4249",
    "sg:postcode":"29451",
    "sg:province":"Niedersachsen",
    "wof:name":"Royalclub",
    "wof:placetype":"venue"
},
  "geometry": {"coordinates":[11.0697612762,53.0727844238],"type":"Point"}
}