{
  "type": "Feature",
  "properties": {
    "iso:country":"DE",
    "sg:address":"Sulzbachtalstr. 140",
    "sg:city":"Sulzbach",
    "sg:phone":"+49 6897/53740",
    "sg:postcode":"66280",
    "sg:province":"Saarland",
    "wof:name":"H. Kuckartz",
    "wof:placetype":"venue"
},
  "geometry": {"coordinates":[7.068556,49.302101],"type":"Point"}
}