{
  "type": "Feature",
  "properties": {
    "iso:country":"DE",
    "sg:address":"Winterleite 5",
    "sg:city":"Reichenberg",
    "sg:phone":"+49 931/60444",
    "sg:postcode":"97234",
    "sg:province":"Bayern",
    "wof:name":"A. Nagel",
    "wof:placetype":"venue"
},
  "geometry": {"coordinates":[9.9072885513,49.7327194214],"type":"Point"}
}