{
  "type": "Feature",
  "properties": {
    "iso:country":"DE",
    "sg:address":"Hauptstr. 18",
    "sg:city":"Hatzfeld",
    "sg:phone":"+49 6467/278",
    "sg:postcode":"35116",
    "sg:province":"Hessen",
    "wof:name":"Friedrich Zissel",
    "wof:placetype":"venue"
},
  "geometry": {"coordinates":[8.5813741684,50.9631767273],"type":"Point"}
}