{
  "type": "Feature",
  "properties": {
    "iso:country":"DE",
    "sg:address":"An der Talm\u00fchle 10",
    "sg:city":"K\u00f6nigstein",
    "sg:postcode":"61462",
    "sg:province":"Hessen",
    "wof:name":"Edma Services",
    "wof:placetype":"venue"
},
  "geometry": {"coordinates":[8.46029,50.177818],"type":"Point"}
}