{
  "type": "Feature",
  "properties": {
    "iso:country":"DE",
    "sg:address":"Bensberger Str 27",
    "sg:city":"Overath",
    "sg:phone":"+49 2204/75427",
    "sg:postcode":"51491",
    "sg:province":"Nordrhein-Westfalen",
    "wof:name":"Raiffeisenbank Overath-r\u00f6srath Eg",
    "wof:placetype":"venue"
},
  "geometry": {"coordinates":[7.25496,50.938583],"type":"Point"}
}