{
  "type": "Feature",
  "properties": {
    "iso:country":"DE",
    "sg:address":"L\u00fctzowstr. 11b",
    "sg:city":"Leipzig",
    "sg:phone":"+49 341/5648238",
    "sg:postcode":"04155",
    "sg:province":"Sachsen",
    "wof:name":"Frank",
    "wof:placetype":"venue"
},
  "geometry": {"coordinates":[12.371149,51.3619],"type":"Point"}
}