{
  "type": "Feature",
  "properties": {
    "iso:country":"DE",
    "sg:address":"Herrmannsgr\u00fcner Str. 10",
    "sg:city":"Greiz",
    "sg:phone":"+49 3661/41576",
    "sg:postcode":"07973",
    "sg:province":"Th\u00fcringen",
    "wof:name":"Peter G\u00f6rner",
    "wof:placetype":"venue"
},
  "geometry": {"coordinates":[12.224283,50.666626],"type":"Point"}
}