{
  "type": "Feature",
  "properties": {
    "iso:country":"DE",
    "sg:address":"Hansastr. 17",
    "sg:city":"Berlin",
    "sg:postcode":"13409",
    "sg:province":"Berlin",
    "wof:name":"Vario-konzept Gmbh",
    "wof:placetype":"venue"
},
  "geometry": {"coordinates":[13.3706531525,52.5585861206],"type":"Point"}
}