{
  "type": "Feature",
  "properties": {
    "iso:country":"DE",
    "sg:address":"Queckhain 10 c",
    "sg:city":"Leisnig",
    "sg:phone":"+49 34321/13497",
    "sg:postcode":"04703",
    "sg:province":"Sachsen",
    "wof:name":"Marianne Grellert",
    "wof:placetype":"venue"
},
  "geometry": {"coordinates":[12.957359314,51.1311531067],"type":"Point"}
}