{
  "type": "Feature",
  "properties": {
    "iso:country":"DE",
    "sg:address":"Leonberger Str. 18",
    "sg:city":"Ditzingen",
    "sg:phone":"+49 7156/951852",
    "sg:postcode":"71254",
    "sg:province":"Baden-W\u00fcrttemberg",
    "wof:name":"Alexander Dorsch",
    "wof:placetype":"venue"
},
  "geometry": {"coordinates":[9.0654,48.825451],"type":"Point"}
}