{
  "type": "Feature",
  "properties": {
    "iso:country":"DE",
    "sg:address":"Alpspitzstr. 34",
    "sg:city":"Grainau",
    "sg:phone":"+49 8821/9870",
    "sg:postcode":"82491",
    "sg:province":"Bayern",
    "wof:name":"Hotel Alpenhof",
    "wof:placetype":"venue"
},
  "geometry": {"coordinates":[11.0292787552,47.4749946594],"type":"Point"}
}