{
  "type": "Feature",
  "properties": {
    "iso:country":"DE",
    "sg:address":"Aubinger Str. 12",
    "sg:city":"M\u00fcnchen",
    "sg:phone":"+49 89/8212537",
    "sg:postcode":"81243",
    "sg:province":"Bayern",
    "wof:name":"Augustinerbr\u00e4u",
    "wof:placetype":"venue"
},
  "geometry": {"coordinates":[11.4459705353,48.1482086182],"type":"Point"}
}