{
  "type": "Feature",
  "properties": {
    "iso:country":"DE",
    "sg:address":"Neum\u00fchlener Weg 19",
    "sg:city":"Kellinghusen",
    "sg:phone":"+49 4822/1528",
    "sg:postcode":"25548",
    "sg:province":"Schleswig-Holstein",
    "wof:name":"Kurt Waldhaus",
    "wof:placetype":"venue"
},
  "geometry": {"coordinates":[9.706908,53.952816],"type":"Point"}
}