{
  "type": "Feature",
  "properties": {
    "iso:country":"DE",
    "sg:address":"Ortsstr. 31",
    "sg:city":"Lachen",
    "sg:phone":"+49 8331/49179",
    "sg:postcode":"87760",
    "sg:province":"Bayern",
    "wof:name":"Ernst Glatz",
    "wof:placetype":"venue"
},
  "geometry": {"coordinates":[10.225908,47.945915],"type":"Point"}
}