{
  "type": "Feature",
  "properties": {
    "iso:country":"DE",
    "sg:address":"Eichstr. 3",
    "sg:city":"Tauberbischofsheim",
    "sg:phone":"+49 9341/2202",
    "sg:postcode":"97941",
    "sg:province":"Baden-W\u00fcrttemberg",
    "wof:name":"Konrad",
    "wof:placetype":"venue"
},
  "geometry": {"coordinates":[9.662113,49.621819],"type":"Point"}
}