{
  "type": "Feature",
  "properties": {
    "iso:country":"DE",
    "sg:address":"Wellingsb\u00fcttler Weg 117",
    "sg:city":"Hamburg",
    "sg:phone":"+49 40/5367860",
    "sg:postcode":"22391",
    "sg:province":"Hamburg",
    "wof:name":"Gsl Gesellschaft F\u00fcr Sicherheits-leitsysteme Mbh",
    "wof:placetype":"venue"
},
  "geometry": {"coordinates":[10.080302,53.641426],"type":"Point"}
}