{
  "type": "Feature",
  "properties": {
    "iso:country":"DE",
    "sg:address":"Auf dem Dudel 58",
    "sg:city":"Duisburg",
    "sg:phone":"+49 2065/60683",
    "sg:postcode":"47228",
    "sg:province":"Nordrhein-Westfalen",
    "wof:name":"Andrea Wenczek",
    "wof:placetype":"venue"
},
  "geometry": {"coordinates":[6.6840720177,51.4131698608],"type":"Point"}
}