{
  "type": "Feature",
  "properties": {
    "iso:country":"DE",
    "sg:address":"Markt 16",
    "sg:city":"Minden",
    "sg:phone":"+49 571/85311",
    "sg:postcode":"32423",
    "sg:province":"Nordrhein-Westfalen",
    "wof:name":"Going Inh. Helga Gunkel",
    "wof:placetype":"venue"
},
  "geometry": {"coordinates":[8.9164028168,52.2878265381],"type":"Point"}
}