{
  "type": "Feature",
  "properties": {
    "iso:country":"DE",
    "sg:address":"Mosbacher Str. 21",
    "sg:city":"Mannheim",
    "sg:phone":"+49 621/712051",
    "sg:postcode":"68259",
    "sg:province":"Baden-W\u00fcrttemberg",
    "wof:name":"Rosi-ann",
    "wof:placetype":"venue"
},
  "geometry": {"coordinates":[8.549173,49.496243],"type":"Point"}
}