{
  "type": "Feature",
  "properties": {
    "iso:country":"DE",
    "sg:address":"Marktstr. 29",
    "sg:city":"Neuwied",
    "sg:phone":"+49 2631/22711",
    "sg:postcode":"56564",
    "sg:province":"Rheinland-Pfalz",
    "wof:name":"Aladins Wohnkultur Gmbh",
    "wof:placetype":"venue"
},
  "geometry": {"coordinates":[7.460373,50.428616],"type":"Point"}
}