{
  "type": "Feature",
  "properties": {
    "iso:country":"DE",
    "sg:address":"Naunhofer Str. 12",
    "sg:city":"Leipzig",
    "sg:phone":"+49 341/8782386",
    "sg:postcode":"04299",
    "sg:province":"Sachsen",
    "wof:name":"W. Richter",
    "wof:placetype":"venue"
},
  "geometry": {"coordinates":[12.40943,51.318218],"type":"Point"}
}