{
  "type": "Feature",
  "properties": {
    "iso:country":"DE",
    "sg:address":"Kl\u00f6nnestr. 89",
    "sg:city":"Dortmund",
    "sg:phone":"+49 231/5310186",
    "sg:postcode":"44143",
    "sg:province":"Nordrhein-Westfalen",
    "wof:name":"B & R Brand & Reissenweber",
    "wof:placetype":"venue"
},
  "geometry": {"coordinates":[7.488437,51.519276],"type":"Point"}
}