{
  "type": "Feature",
  "properties": {
    "iso:country":"DE",
    "sg:address":"Am Leineufer 51",
    "sg:city":"Hannover",
    "sg:phone":"+49 511/79030",
    "sg:postcode":"30419",
    "sg:province":"Niedersachsen",
    "wof:name":"Varta Autobatterie Gmbh",
    "wof:placetype":"venue"
},
  "geometry": {"coordinates":[9.633198,52.417294],"type":"Point"}
}