{
  "type": "Feature",
  "properties": {
    "iso:country":"DE",
    "sg:address":"Am Wolfshorn 35",
    "sg:city":"Kirchhundem",
    "sg:phone":"+49 2764/7970",
    "sg:postcode":"57399",
    "sg:province":"Nordrhein-Westfalen",
    "wof:name":"E. Picker Heissmangel",
    "wof:placetype":"venue"
},
  "geometry": {"coordinates":[8.0118274689,51.0464363098],"type":"Point"}
}