{
  "type": "Feature",
  "properties": {
    "iso:country":"DE",
    "sg:address":"Berghamer Str. 7",
    "sg:city":"Erding",
    "sg:postcode":"85435",
    "sg:province":"Bayern",
    "wof:name":"Aldi Gmbh & Co. Kg",
    "wof:placetype":"venue"
},
  "geometry": {"coordinates":[11.8991317749,48.276802063],"type":"Point"}
}