{
  "type": "Feature",
  "properties": {
    "iso:country":"DE",
    "sg:address":"Neunkircher Str. 23",
    "sg:city":"Rehlingen-Siersburg",
    "sg:phone":"+49 6833/783",
    "sg:postcode":"66780",
    "sg:province":"Saarland",
    "wof:name":"A. Und Karl Plegniere",
    "wof:placetype":"venue"
},
  "geometry": {"coordinates":[6.595657,49.340054],"type":"Point"}
}