{
  "type": "Feature",
  "properties": {
    "iso:country":"DE",
    "sg:address":"Wanner Str. 6",
    "sg:city":"Gelsenkirchen",
    "sg:phone":"+49 209/15140",
    "sg:postcode":"45879",
    "sg:province":"Nordrhein-Westfalen",
    "wof:name":"N & W Innenausbau Gmbh",
    "wof:placetype":"venue"
},
  "geometry": {"coordinates":[7.101325,51.513466],"type":"Point"}
}