{
  "type": "Feature",
  "properties": {
    "iso:country":"DE",
    "sg:address":"Dr.-Friedrichs-Ring 2a",
    "sg:city":"Zwickau",
    "sg:phone":"+49 375/5361261",
    "sg:postcode":"08056",
    "sg:province":"Sachsen",
    "wof:name":"Archiv Der Hochschule F\u00fcr Technik Und Wirtschaft Zwickau",
    "wof:placetype":"venue"
},
  "geometry": {"coordinates":[12.493583,50.716461],"type":"Point"}
}