{
  "type": "Feature",
  "properties": {
    "iso:country":"DE",
    "sg:address":"Kapellener Str. 11",
    "sg:city":"Duisburg",
    "sg:phone":"+49 2065/22643",
    "sg:postcode":"47239",
    "sg:province":"Nordrhein-Westfalen",
    "wof:name":"Horst Heinen",
    "wof:placetype":"venue"
},
  "geometry": {"coordinates":[6.6573548317,51.4022254944],"type":"Point"}
}