{
  "type": "Feature",
  "properties": {
    "iso:country":"DE",
    "sg:address":"H\u00fcttenwerkstr. 30",
    "sg:city":"Dillingen",
    "sg:phone":"+49 6831/71097",
    "sg:postcode":"66763",
    "sg:province":"Saarland",
    "wof:name":"Berliner Kaufhaus J. Br\u00fcck",
    "wof:placetype":"venue"
},
  "geometry": {"coordinates":[6.729926,49.354088],"type":"Point"}
}