{
  "type": "Feature",
  "properties": {
    "iso:country":"DE",
    "sg:address":"Denksteinweg 75",
    "sg:city":"Hamburg",
    "sg:phone":"+49 40/6535384",
    "sg:postcode":"22043",
    "sg:province":"Hamburg",
    "wof:name":"Malereibetrieb Otto Gerber Gmbh",
    "wof:placetype":"venue"
},
  "geometry": {"coordinates":[10.128152,53.568302],"type":"Point"}
}