{
  "type": "Feature",
  "properties": {
    "iso:country":"DE",
    "sg:address":"Salinenstr. 9",
    "sg:city":"Bad Rothenfelde",
    "sg:phone":"+49 5424/1638",
    "sg:postcode":"49214",
    "sg:province":"Niedersachsen",
    "wof:name":"Central Cafe",
    "wof:placetype":"venue"
},
  "geometry": {"coordinates":[8.162687,52.109653],"type":"Point"}
}