{
  "type": "Feature",
  "properties": {
    "iso:country":"DE",
    "sg:address":"Grosser Zimmerhof 23",
    "sg:city":"Wolfenb\u00fcttel",
    "sg:phone":"+49 5331/9293031",
    "sg:postcode":"38300",
    "sg:province":"Niedersachsen",
    "wof:name":"Fakehair",
    "wof:placetype":"venue"
},
  "geometry": {"coordinates":[10.533713,52.161701],"type":"Point"}
}