{
  "type": "Feature",
  "properties": {
    "iso:country":"DE",
    "sg:address":"Kellerberg",
    "sg:city":"Geringswalde",
    "sg:phone":"+49 37382/8774",
    "sg:postcode":"09326",
    "sg:province":"Sachsen",
    "wof:name":"Knoche & Junghans Gmbh",
    "wof:placetype":"venue"
},
  "geometry": {"coordinates":[12.9066457748,51.0788536072],"type":"Point"}
}