{
  "type": "Feature",
  "properties": {
    "iso:country":"DE",
    "sg:address":"Lindenstr. 1",
    "sg:city":"Stra\u00dfenhaus",
    "sg:phone":"+49 2634/4315",
    "sg:postcode":"56587",
    "sg:province":"Rheinland-Pfalz",
    "wof:name":"Cafe Hoffmann",
    "wof:placetype":"venue"
},
  "geometry": {"coordinates":[7.513119,50.540051],"type":"Point"}
}