{
  "type": "Feature",
  "properties": {
    "iso:country":"DE",
    "sg:address":"Clara-Zetkin-Str. 28",
    "sg:city":"Hohenm\u00f6lsen",
    "sg:phone":"+49 34441/4830",
    "sg:postcode":"06679",
    "sg:province":"Sachsen-Anhalt",
    "wof:name":"Gemeinn. Wohnungsbauges. Mbh",
    "wof:placetype":"venue"
},
  "geometry": {"coordinates":[12.097415,51.159435],"type":"Point"}
}