{
  "type": "Feature",
  "properties": {
    "iso:country":"DE",
    "sg:address":"Maschstr. 22",
    "sg:city":"Herford",
    "sg:phone":"+49 5221/98290",
    "sg:postcode":"32052",
    "sg:province":"Nordrhein-Westfalen",
    "wof:name":"Wiebrock Verwaltungs Gmbh",
    "wof:placetype":"venue"
},
  "geometry": {"coordinates":[8.6971874237,52.1009254456],"type":"Point"}
}