{
  "type": "Feature",
  "properties": {
    "iso:country":"DE",
    "sg:address":"Seelenbachweg 13",
    "sg:city":"Schw\u00e4bisch Gm\u00fcnd",
    "sg:phone":"+49 7171/61508",
    "sg:postcode":"73525",
    "sg:province":"Baden-W\u00fcrttemberg",
    "wof:name":"Werner Dlouhy",
    "wof:placetype":"venue"
},
  "geometry": {"coordinates":[9.7757854462,48.7889213562],"type":"Point"}
}