{
  "type": "Feature",
  "properties": {
    "iso:country":"DE",
    "sg:address":"Ketschengasse 52",
    "sg:city":"Coburg",
    "sg:phone":"+49 9561/90668",
    "sg:postcode":"96450",
    "sg:province":"Bayern",
    "wof:name":"Ewald Rei\u00dfenweber Kg",
    "wof:placetype":"venue"
},
  "geometry": {"coordinates":[10.964108,50.255428],"type":"Point"}
}