{
  "type": "Feature",
  "properties": {
    "iso:country":"DE",
    "sg:address":"Kanalstr. 30",
    "sg:city":"Fulda",
    "sg:phone":"+49 661/70053",
    "sg:postcode":"36037",
    "sg:province":"Hessen",
    "wof:name":"Hallimasch",
    "wof:placetype":"venue"
},
  "geometry": {"coordinates":[9.6745586395,50.5508613586],"type":"Point"}
}