{
  "type": "Feature",
  "properties": {
    "iso:country":"DE",
    "sg:address":"Kappelwindeckstr. 24",
    "sg:city":"B\u00fchl",
    "sg:phone":"+49 7223/27628",
    "sg:postcode":"77815",
    "sg:province":"Baden-W\u00fcrttemberg",
    "wof:name":"Franz Gartner",
    "wof:placetype":"venue"
},
  "geometry": {"coordinates":[8.145332,48.691574],"type":"Point"}
}