{
  "type": "Feature",
  "properties": {
    "iso:country":"DE",
    "sg:address":"Talstr. 72 a",
    "sg:city":"Neusalza-Spremberg",
    "sg:phone":"+49 35872/32040",
    "sg:postcode":"02742",
    "sg:province":"Sachsen",
    "wof:name":"M\u00fcller Bau Gmbh",
    "wof:placetype":"venue"
},
  "geometry": {"coordinates":[14.5266580582,51.0422935486],"type":"Point"}
}