{
  "type": "Feature",
  "properties": {
    "iso:country":"DE",
    "sg:address":"Neckarsteige 27",
    "sg:city":"N\u00fcrtingen",
    "sg:phone":"+49 7022/39117",
    "sg:postcode":"72622",
    "sg:province":"Baden-W\u00fcrttemberg",
    "wof:name":"Josef Heinz",
    "wof:placetype":"venue"
},
  "geometry": {"coordinates":[9.334353447,48.6276130676],"type":"Point"}
}