{
  "type": "Feature",
  "properties": {
    "iso:country":"DE",
    "sg:address":"Erlenweg 1",
    "sg:city":"Pirna",
    "sg:phone":"+49 3501/523539",
    "sg:postcode":"01796",
    "sg:province":"Sachsen",
    "wof:name":"Olga B\u00fcst",
    "wof:placetype":"venue"
},
  "geometry": {"coordinates":[13.93567276,50.984752655],"type":"Point"}
}