{
  "type": "Feature",
  "properties": {
    "iso:country":"DE",
    "sg:address":"Waldstr. 7",
    "sg:city":"Heidenrod",
    "sg:phone":"+49 6120/7207",
    "sg:postcode":"65321",
    "sg:province":"Hessen",
    "wof:name":"Trim-line Schwicker",
    "wof:placetype":"venue"
},
  "geometry": {"coordinates":[8.006264,50.188915],"type":"Point"}
}