{
  "type": "Feature",
  "properties": {
    "iso:country":"DE",
    "sg:address":"Am Rheinberg 4",
    "sg:city":"Bingen",
    "sg:postcode":"55411",
    "sg:province":"Rheinland-Pfalz",
    "wof:name":"Techno Clean Heidi Wegener Gmbh",
    "wof:placetype":"venue"
},
  "geometry": {"coordinates":[7.9166622162,49.9684333801],"type":"Point"}
}