{
  "type": "Feature",
  "properties": {
    "iso:country":"DE",
    "sg:address":"Elzstr. 5",
    "sg:city":"Schwanau",
    "sg:phone":"+49 7824/66845",
    "sg:postcode":"77963",
    "sg:province":"Baden-W\u00fcrttemberg",
    "wof:name":"Fst Franz Strobel Netzwerktechnik Gmbh",
    "wof:placetype":"venue"
},
  "geometry": {"coordinates":[7.752619,48.32856],"type":"Point"}
}