{
  "type": "Feature",
  "properties": {
    "iso:country":"DE",
    "sg:address":"Lerchenweg 23",
    "sg:city":"Barendorf",
    "sg:phone":"+49 4137/810191",
    "sg:postcode":"21397",
    "sg:province":"Niedersachsen",
    "wof:name":"Andreas Und Ute Hertel",
    "wof:placetype":"venue"
},
  "geometry": {"coordinates":[10.5407428741,53.2251434326],"type":"Point"}
}