{
  "type": "Feature",
  "properties": {
    "iso:country":"DE",
    "sg:address":"Am W\u00e4ldchen 13",
    "sg:city":"Lutzerath",
    "sg:phone":"+49 2677/553",
    "sg:postcode":"56826",
    "sg:province":"Rheinland-Pfalz",
    "wof:name":"Lothar Zirwes",
    "wof:placetype":"venue"
},
  "geometry": {"coordinates":[7.015869,50.133526],"type":"Point"}
}