{
  "type": "Feature",
  "properties": {
    "iso:country":"DE",
    "sg:address":"Friedensstr. 11",
    "sg:city":"Dielheim",
    "sg:phone":"+49 6222/75932",
    "sg:postcode":"69234",
    "sg:province":"Baden-W\u00fcrttemberg",
    "wof:name":"Alois Knopf",
    "wof:placetype":"venue"
},
  "geometry": {"coordinates":[8.7309541702,49.2841758728],"type":"Point"}
}