{
  "type": "Feature",
  "properties": {
    "iso:country":"DE",
    "sg:address":"Mindener Str. 94",
    "sg:city":"Uchte",
    "sg:phone":"+49 5763/1660",
    "sg:postcode":"31600",
    "sg:province":"Niedersachsen",
    "wof:name":"Verg\u00f6lst-partnerbetrieb Oetting & Westermann Gmbh",
    "wof:placetype":"venue"
},
  "geometry": {"coordinates":[8.8932256699,52.4912528992],"type":"Point"}
}