{
  "type": "Feature",
  "properties": {
    "iso:country":"DE",
    "sg:address":"Flughafen 76/1",
    "sg:city":"Friedrichshafen",
    "sg:phone":"+49 4975/4138890",
    "sg:postcode":"88046",
    "sg:province":"Baden-W\u00fcrttemberg",
    "wof:name":"Carbofibretec Gmbh",
    "wof:placetype":"venue"
},
  "geometry": {"coordinates":[9.506213,47.665371],"type":"Point"}
}