{
  "type": "Feature",
  "properties": {
    "iso:country":"DE",
    "sg:address":"Bergmannstr. 23",
    "sg:city":"Berlin",
    "sg:phone":"+49 30/6937881",
    "sg:postcode":"10961",
    "sg:province":"Berlin",
    "wof:name":"Kaiser-apotheke",
    "wof:placetype":"venue"
},
  "geometry": {"coordinates":[13.394029,52.488949],"type":"Point"}
}