{
  "type": "Feature",
  "properties": {
    "iso:country":"DE",
    "sg:address":"Rudolf-Diesel-Str. 16",
    "sg:city":"Wei\u00dfenfels",
    "sg:phone":"+49 3443/302212",
    "sg:postcode":"06667",
    "sg:province":"Sachsen-Anhalt",
    "wof:name":"Frank Behm E. K.",
    "wof:placetype":"venue"
},
  "geometry": {"coordinates":[11.9802494049,51.1869926453],"type":"Point"}
}