{
  "type": "Feature",
  "properties": {
    "iso:country":"DE",
    "sg:address":"Breite Str. 6",
    "sg:city":"L\u00fcbeck",
    "sg:phone":"+49 451/1351",
    "sg:postcode":"23552",
    "sg:province":"Schleswig-Holstein",
    "wof:name":"Redaktion Ostseejahrbuch Verlag Ihk",
    "wof:placetype":"venue"
},
  "geometry": {"coordinates":[10.6830062866,53.8663520813],"type":"Point"}
}