{
  "type": "Feature",
  "properties": {
    "iso:country":"DE",
    "sg:address":"Tannenstr 1",
    "sg:city":"Herrenberg",
    "sg:phone":"+49 7032/93530",
    "sg:postcode":"71083",
    "sg:province":"Baden-W\u00fcrttemberg",
    "wof:name":"Ddd Motor-bericht",
    "wof:placetype":"venue"
},
  "geometry": {"coordinates":[8.854979,48.597271],"type":"Point"}
}