{
  "type": "Feature",
  "properties": {
    "iso:country":"DE",
    "sg:address":"Ruppiner Chausse 331",
    "sg:city":"Berlin",
    "sg:phone":"+49 30/43669165",
    "sg:postcode":"13503",
    "sg:province":"Berlin",
    "wof:name":"Men At Work - Die Menstripshow !!!",
    "wof:placetype":"venue"
},
  "geometry": {"coordinates":[13.2105503082,52.6066932678],"type":"Point"}
}