{
  "type": "Feature",
  "properties": {
    "iso:country":"DE",
    "sg:address":"Johann-Sebastian-Bach-Str.",
    "sg:city":"Erfurt",
    "sg:phone":"+49 361/347683",
    "sg:postcode":"99096",
    "sg:province":"Th\u00fcringen",
    "wof:name":"Gastst\u00e4tte Schwimmhalle-s\u00fcd",
    "wof:placetype":"venue"
},
  "geometry": {"coordinates":[11.0387983322,50.9639892578],"type":"Point"}
}