{
  "type": "Feature",
  "properties": {
    "iso:country":"DE",
    "sg:address":"Kirchstr. 8",
    "sg:city":"Neustadt",
    "sg:phone":"+49 6321/7899",
    "sg:postcode":"67433",
    "sg:province":"Rheinland-Pfalz",
    "wof:name":"Reinhard Moster Architekt",
    "wof:placetype":"venue"
},
  "geometry": {"coordinates":[8.14973,49.352482],"type":"Point"}
}