{
  "type": "Feature",
  "properties": {
    "iso:country":"DE",
    "sg:address":"Stephanienstr. 25",
    "sg:city":"Baden-Baden",
    "sg:phone":"+49 7221/3017560",
    "sg:postcode":"76530",
    "sg:province":"Baden-W\u00fcrttemberg",
    "wof:name":"Presse Informations Agentur Ag",
    "wof:placetype":"venue"
},
  "geometry": {"coordinates":[8.2429151535,48.7587203979],"type":"Point"}
}