{
  "type": "Feature",
  "properties": {
    "iso:country":"DE",
    "sg:address":"Martin-Luther-Str. 2",
    "sg:city":"Goslar",
    "sg:phone":"+49 5321/7840",
    "sg:postcode":"38640",
    "sg:province":"Niedersachsen",
    "wof:name":"Haus Abendfrieden",
    "wof:placetype":"venue"
},
  "geometry": {"coordinates":[10.441051,51.910828],"type":"Point"}
}