{
  "type": "Feature",
  "properties": {
    "iso:country":"DE",
    "sg:address":"Reinhartshauser Str. 7",
    "sg:city":"Bobingen",
    "sg:phone":"+49 8234/42570",
    "sg:postcode":"86399",
    "sg:province":"Bayern",
    "wof:name":"Schlienz Gmbh Raumdesign",
    "wof:placetype":"venue"
},
  "geometry": {"coordinates":[10.7770996094,48.2700576782],"type":"Point"}
}