{
  "type": "Feature",
  "properties": {
    "iso:country":"DE",
    "sg:address":"Waldenserstr. 25",
    "sg:city":"M\u00fchlacker",
    "sg:phone":"+49 7041/812725",
    "sg:postcode":"75417",
    "sg:province":"Baden-W\u00fcrttemberg",
    "wof:name":"A & A Colonia Versicherung Hobusch & Schwerdtfeger",
    "wof:placetype":"venue"
},
  "geometry": {"coordinates":[8.8414878845,48.9423713684],"type":"Point"}
}