{
  "type": "Feature",
  "properties": {
    "iso:country":"DE",
    "sg:address":"Schubertstr. 5",
    "sg:city":"Steinau",
    "sg:phone":"+49 6663/919360",
    "sg:postcode":"36396",
    "sg:province":"Hessen",
    "wof:name":"Ilse Greulich",
    "wof:placetype":"venue"
},
  "geometry": {"coordinates":[9.4695053101,50.3200531006],"type":"Point"}
}