{
  "type": "Feature",
  "properties": {
    "iso:country":"DE",
    "sg:address":"Wolfenb\u00fctteler Str. 4",
    "sg:city":"S\u00f6hlde",
    "sg:phone":"+49 5129/7400",
    "sg:postcode":"31185",
    "sg:province":"Niedersachsen",
    "wof:name":"Carl Behrens",
    "wof:placetype":"venue"
},
  "geometry": {"coordinates":[10.233642,52.186634],"type":"Point"}
}