{
  "type": "Feature",
  "properties": {
    "iso:country":"DE",
    "sg:address":"M\u00f6nchsrother Str. 27",
    "sg:city":"Dinkelsb\u00fchl",
    "sg:phone":"+49 9851/2354",
    "sg:postcode":"91550",
    "sg:province":"Bayern",
    "wof:name":"Otto Karl & S\u00f6hne Gmbh",
    "wof:placetype":"venue"
},
  "geometry": {"coordinates":[10.3310518265,49.0599822998],"type":"Point"}
}