{
  "type": "Feature",
  "properties": {
    "iso:country":"DE",
    "sg:address":"Simeonstiftplatz",
    "sg:city":"Trier",
    "sg:phone":"+49 651/7182440",
    "sg:postcode":"54290",
    "sg:province":"Rheinland-Pfalz",
    "wof:name":"St\u00e4dt. Museum Simeonsstift",
    "wof:placetype":"venue"
},
  "geometry": {"coordinates":[6.642455,49.759861],"type":"Point"}
}