{
  "type": "Feature",
  "properties": {
    "iso:country":"DE",
    "sg:address":"Steinstr. 11",
    "sg:city":"D\u00fcsseldorf",
    "sg:phone":"+49 211/326700",
    "sg:postcode":"40212",
    "sg:province":"Nordrhein-Westfalen",
    "wof:name":"Grundst\u00fccksgesellschaft Wohnpark Jacobstr. 21-23",
    "wof:placetype":"venue"
},
  "geometry": {"coordinates":[6.7806777954,51.2228889465],"type":"Point"}
}