{
  "type": "Feature",
  "properties": {
    "iso:country":"DE",
    "sg:address":"Borsigstr. 9",
    "sg:city":"Barbing",
    "sg:phone":"+49 9401/92590",
    "sg:postcode":"93092",
    "sg:province":"Bayern",
    "wof:name":"Dinkhauser Kartonagen Vertriebs Gmbh",
    "wof:placetype":"venue"
},
  "geometry": {"coordinates":[12.238604,48.992687],"type":"Point"}
}