{
  "type": "Feature",
  "properties": {
    "iso:country":"DE",
    "sg:address":"\u00d6sterreicher Str. 6",
    "sg:city":"Goldbach",
    "sg:phone":"+49 6021/52122",
    "sg:postcode":"63773",
    "sg:province":"Bayern",
    "wof:name":"Fenster-sch\u00e4fer Gmbh",
    "wof:placetype":"venue"
},
  "geometry": {"coordinates":[9.180311,49.989719],"type":"Point"}
}