{
  "type": "Feature",
  "properties": {
    "iso:country":"DE",
    "sg:address":"Bunsenstr 30",
    "sg:city":"Darmstadt",
    "sg:phone":"+49 6151/8080",
    "sg:postcode":"64293",
    "sg:province":"Hessen",
    "wof:name":"Electronic Network Emk Elektro-mechanische Komponenten Gmbh",
    "wof:placetype":"venue"
},
  "geometry": {"coordinates":[8.623306,49.886707],"type":"Point"}
}