{
  "type": "Feature",
  "properties": {
    "iso:country":"DE",
    "sg:address":"Alsterkrugchaussee 435 A",
    "sg:city":"Hamburg",
    "sg:phone":"+49 40/2795741",
    "sg:postcode":"22335",
    "sg:province":"Hamburg",
    "wof:name":"Hilgert Print Agentur Gmbh",
    "wof:placetype":"venue"
},
  "geometry": {"coordinates":[10.01014,53.621235],"type":"Point"}
}