{
  "type": "Feature",
  "properties": {
    "iso:country":"DE",
    "sg:address":"Schmiedstr. 3",
    "sg:city":"R\u00fcdesheim am Rhein",
    "sg:phone":"+49 6726/9394",
    "sg:postcode":"65385",
    "sg:province":"Hessen",
    "wof:name":"Gebr\u00fcder Scholl Gmbh",
    "wof:placetype":"venue"
},
  "geometry": {"coordinates":[7.8930540085,50.051235199],"type":"Point"}
}