{
  "type": "Feature",
  "properties": {
    "iso:country":"DE",
    "sg:address":"Thambach 14",
    "sg:city":"Reichertsheim",
    "sg:phone":"+49 8073/1361",
    "sg:postcode":"84437",
    "sg:province":"Bayern",
    "wof:name":"Mathilde Etzelsbeck",
    "wof:placetype":"venue"
},
  "geometry": {"coordinates":[12.2621040344,48.1886253357],"type":"Point"}
}