{
  "type": "Feature",
  "properties": {
    "iso:country":"DE",
    "sg:address":"Koogstr. 64",
    "sg:city":"Friedrichskoog",
    "sg:phone":"+49 4854/90090",
    "sg:postcode":"25718",
    "sg:province":"Schleswig-Holstein",
    "wof:name":"Krabben-apotheke",
    "wof:placetype":"venue"
},
  "geometry": {"coordinates":[8.910141,54.008896],"type":"Point"}
}