{
  "type": "Feature",
  "properties": {
    "iso:country":"DE",
    "sg:address":"Steinlachstr. 3",
    "sg:city":"M\u00f6ssingen",
    "sg:phone":"+49 7473/94950",
    "sg:postcode":"72116",
    "sg:province":"Baden-W\u00fcrttemberg",
    "wof:name":"Ottmar Scherer",
    "wof:placetype":"venue"
},
  "geometry": {"coordinates":[9.1081943512,48.3807487488],"type":"Point"}
}