{
  "type": "Feature",
  "properties": {
    "iso:country":"DE",
    "sg:address":"Zeppelinstr. 58 a",
    "sg:city":"Aachen",
    "sg:phone":"+49 241/5791958",
    "sg:postcode":"52068",
    "sg:province":"Nordrhein-Westfalen",
    "wof:name":"H\u00e4mpi's Speisehaus",
    "wof:placetype":"venue"
},
  "geometry": {"coordinates":[6.1250891685,50.7702140808],"type":"Point"}
}