{
  "type": "Feature",
  "properties": {
    "iso:country":"DE",
    "sg:address":"S\u00f6gestr. 18",
    "sg:city":"Schortens",
    "sg:phone":"+49 4423/6505",
    "sg:postcode":"26419",
    "sg:province":"Niedersachsen",
    "wof:name":"Taddigs Kulturbau Gmbh",
    "wof:placetype":"venue"
},
  "geometry": {"coordinates":[7.9833488464,53.575668335],"type":"Point"}
}