{
  "type": "Feature",
  "properties": {
    "iso:country":"DE",
    "sg:address":"Piccoloministr. 314",
    "sg:city":"K\u00f6ln",
    "sg:phone":"+49 221/631396",
    "sg:postcode":"51067",
    "sg:province":"Nordrhein-Westfalen",
    "wof:name":"Piccolomini",
    "wof:placetype":"venue"
},
  "geometry": {"coordinates":[7.0390920639,50.9715461731],"type":"Point"}
}