{
  "type": "Feature",
  "properties": {
    "iso:country":"DE",
    "sg:address":"Kiebitzweg 10",
    "sg:city":"Westerland",
    "sg:phone":"+49 4651/24721",
    "sg:postcode":"25980",
    "sg:province":"Schleswig-Holstein",
    "wof:name":"I. Bauer",
    "wof:placetype":"venue"
},
  "geometry": {"coordinates":[8.3063287735,54.9001617432],"type":"Point"}
}