{
  "type": "Feature",
  "properties": {
    "iso:country":"DE",
    "sg:address":"S\u00fcdstr. 36",
    "sg:city":"Wuppertal",
    "sg:phone":"+49 202/301290",
    "sg:postcode":"42103",
    "sg:province":"Nordrhein-Westfalen",
    "wof:name":"Werners Kaminst\u00fcbchen",
    "wof:placetype":"venue"
},
  "geometry": {"coordinates":[7.1408882141,51.2519569397],"type":"Point"}
}