{
  "type": "Feature",
  "properties": {
    "iso:country":"DE",
    "sg:address":"Ahrenshooper Zeile 12",
    "sg:city":"Berlin",
    "sg:phone":"+49 30/80906276",
    "sg:postcode":"14129",
    "sg:province":"Berlin",
    "wof:name":"Udo Kr\u00fcger",
    "wof:placetype":"venue"
},
  "geometry": {"coordinates":[13.2217512131,52.4393997192],"type":"Point"}
}