{
  "type": "Feature",
  "properties": {
    "iso:country":"DE",
    "sg:address":"Haigelbergweg 1",
    "sg:city":"Cham",
    "sg:phone":"+49 9971/7101",
    "sg:postcode":"93413",
    "sg:province":"Bayern",
    "wof:name":"G. Hiebl",
    "wof:placetype":"venue"
},
  "geometry": {"coordinates":[12.7102861404,49.2391357422],"type":"Point"}
}