{
  "type": "Feature",
  "properties": {
    "iso:country":"DE",
    "sg:address":"Poststr. 14",
    "sg:city":"G\u00f6ppingen",
    "sg:phone":"+49 7161/78915",
    "sg:postcode":"73033",
    "sg:province":"Baden-W\u00fcrttemberg",
    "wof:name":"Apotheke Im Kaiserbau Ernest Techentin",
    "wof:placetype":"venue"
},
  "geometry": {"coordinates":[9.659525,48.702145],"type":"Point"}
}