{
  "type": "Feature",
  "properties": {
    "iso:country":"DE",
    "sg:address":"Kirchweg 10",
    "sg:city":"Diepholz",
    "sg:phone":"+49 5441/1433",
    "sg:postcode":"49356",
    "sg:province":"Niedersachsen",
    "wof:name":"Ev. Pfarramt Ii St. H\u00fclfe-wetschen",
    "wof:placetype":"venue"
},
  "geometry": {"coordinates":[8.3906984329,52.6231765747],"type":"Point"}
}