{
  "type": "Feature",
  "properties": {
    "iso:country":"DE",
    "sg:address":"K\u00f6lner Str. 187",
    "sg:city":"K\u00f6ln",
    "sg:phone":"+49 2203/16274",
    "sg:postcode":"51149",
    "sg:province":"Nordrhein-Westfalen",
    "wof:name":"Hans Euler Architekt",
    "wof:placetype":"venue"
},
  "geometry": {"coordinates":[7.028166,50.901016],"type":"Point"}
}