{
  "type": "Feature",
  "properties": {
    "iso:country":"DE",
    "sg:address":"Pfarrgasse 2",
    "sg:city":"Schnelldorf",
    "sg:phone":"+49 7950/673",
    "sg:postcode":"91625",
    "sg:province":"Bayern",
    "wof:name":"Ev. Luth. Pfarramt",
    "wof:placetype":"venue"
},
  "geometry": {"coordinates":[10.2059545517,49.202205658],"type":"Point"}
}