{
  "type": "Feature",
  "properties": {
    "iso:country":"DE",
    "sg:address":"Gei\u00dfertweg 17",
    "sg:city":"Mettlach",
    "sg:phone":"+49 6864/1008",
    "sg:postcode":"66693",
    "sg:province":"Saarland",
    "wof:name":"U. Ziegler Immobilienmakler",
    "wof:placetype":"venue"
},
  "geometry": {"coordinates":[6.609855175,49.495010376],"type":"Point"}
}