{
  "type": "Feature",
  "properties": {
    "iso:country":"DE",
    "sg:address":"Struhbarg 27",
    "sg:city":"Bargteheide",
    "sg:phone":"+49 4532/24095",
    "sg:postcode":"22941",
    "sg:province":"Schleswig-Holstein",
    "wof:name":"Detlef Ahlers Architekt",
    "wof:placetype":"venue"
},
  "geometry": {"coordinates":[10.275727,53.729572],"type":"Point"}
}