{
  "type": "Feature",
  "properties": {
    "iso:country":"DE",
    "sg:address":"Hauptstr. 129",
    "sg:city":"Rechtenbach",
    "sg:phone":"+49 9352/2834",
    "sg:postcode":"97848",
    "sg:province":"Bayern",
    "wof:name":"R. Matreux",
    "wof:placetype":"venue"
},
  "geometry": {"coordinates":[9.49942,49.982525],"type":"Point"}
}