{
  "type": "Feature",
  "properties": {
    "iso:country":"DE",
    "sg:address":"Eisenbahnstra\u00dfe 3",
    "sg:city":"Buggingen",
    "sg:phone":"+49 7631",
    "sg:postcode":"79426",
    "sg:province":"Baden-W\u00fcrttemberg",
    "wof:name":"Weinhof Weber",
    "wof:placetype":"venue"
},
  "geometry": {"coordinates":[7.6365461349,47.8486633301],"type":"Point"}
}