{
  "type": "Feature",
  "properties": {
    "iso:country":"DE",
    "sg:address":"Lychener Str. 16",
    "sg:city":"Templin",
    "sg:phone":"+49 3987/51662",
    "sg:postcode":"17268",
    "sg:province":"Brandenburg",
    "wof:name":"Dekra Automobil Gmbh",
    "wof:placetype":"venue"
},
  "geometry": {"coordinates":[13.4898929596,53.1285209656],"type":"Point"}
}