{
  "type": "Feature",
  "properties": {
    "iso:country":"DE",
    "sg:address":"Seltersweg 69",
    "sg:city":"Gie\u00dfen",
    "sg:phone":"+49 641/78715",
    "sg:postcode":"35390",
    "sg:province":"Hessen",
    "wof:name":"G\u00fcnther Baumgart Steuerbevollm\u00e4chtigter",
    "wof:placetype":"venue"
},
  "geometry": {"coordinates":[8.671880722,50.5829925537],"type":"Point"}
}