{
  "type": "Feature",
  "properties": {
    "iso:country":"DE",
    "sg:address":"Raiffeisenstr. 4",
    "sg:city":"Flammersfeld",
    "sg:phone":"+49 2685/1049",
    "sg:postcode":"57632",
    "sg:province":"Rheinland-Pfalz",
    "wof:name":"Brunnen-apotheke",
    "wof:placetype":"venue"
},
  "geometry": {"coordinates":[7.524723,50.646175],"type":"Point"}
}