{
  "type": "Feature",
  "properties": {
    "iso:country":"DE",
    "sg:address":"Nordwall 21",
    "sg:city":"Medebach",
    "sg:phone":"+49 2982/625",
    "sg:postcode":"59964",
    "sg:province":"Nordrhein-Westfalen",
    "wof:name":"Friedrich K\u00f6ster Schreinerei",
    "wof:placetype":"venue"
},
  "geometry": {"coordinates":[8.705365,51.199886],"type":"Point"}
}