{
  "type": "Feature",
  "properties": {
    "iso:country":"DE",
    "sg:address":"Bergerwaldstr. 41b",
    "sg:city":"M\u00fcnchen",
    "sg:phone":"+49 89/421793",
    "sg:postcode":"81825",
    "sg:province":"Bayern",
    "wof:name":"Adalbert H\u00f6rmann",
    "wof:placetype":"venue"
},
  "geometry": {"coordinates":[11.6592092514,48.1141853333],"type":"Point"}
}