{
  "type": "Feature",
  "properties": {
    "iso:country":"DE",
    "sg:address":"Lindenallee 10",
    "sg:city":"Essen",
    "sg:phone":"+49 201/224246",
    "sg:postcode":"45127",
    "sg:province":"Nordrhein-Westfalen",
    "wof:name":"Deutschlandhaus Essen Gmbh & Co.",
    "wof:placetype":"venue"
},
  "geometry": {"coordinates":[7.0102758408,51.4534721375],"type":"Point"}
}