{
  "type": "Feature",
  "properties": {
    "iso:country":"DE",
    "sg:address":"Friedrich-List-Str. 17",
    "sg:city":"Falkenberg",
    "sg:phone":"+49 35365/34743",
    "sg:postcode":"04895",
    "sg:province":"Brandenburg",
    "wof:name":"Gastst\u00e4tte Schultheiss",
    "wof:placetype":"venue"
},
  "geometry": {"coordinates":[13.240316391,51.5874404907],"type":"Point"}
}