{
  "type": "Feature",
  "properties": {
    "iso:country":"DE",
    "sg:address":"Hofstr. 7",
    "sg:city":"Weilheim",
    "sg:phone":"+49 881/40576",
    "sg:postcode":"82362",
    "sg:province":"Bayern",
    "wof:name":"Leopold Begerack Schl\u00fcsseldienst",
    "wof:placetype":"venue"
},
  "geometry": {"coordinates":[11.1428451538,47.8385543823],"type":"Point"}
}