{
  "type": "Feature",
  "properties": {
    "iso:country":"DE",
    "sg:address":"B\u00f6ttcherkamp 22",
    "sg:city":"Hamburg",
    "sg:phone":"+49 40/4226515",
    "sg:postcode":"22549",
    "sg:province":"Hamburg",
    "wof:name":"Paul Ladwig Tischlerei Inh. Olaf Ladwig",
    "wof:placetype":"venue"
},
  "geometry": {"coordinates":[9.875727,53.586517],"type":"Point"}
}