{
  "type": "Feature",
  "properties": {
    "iso:country":"DE",
    "sg:address":"Ludwig-Neu-Str. 7",
    "sg:city":"Alzenau",
    "sg:phone":"+49 6023/5049847",
    "sg:postcode":"63755",
    "sg:province":"Bayern",
    "wof:name":"Town & Country Selbstbau Lizenzgeber Gmbh",
    "wof:placetype":"venue"
},
  "geometry": {"coordinates":[9.077881,50.073643],"type":"Point"}
}