{
  "type": "Feature",
  "properties": {
    "iso:country":"DE",
    "sg:address":"Lameystr. 19",
    "sg:city":"Mannheim",
    "sg:phone":"+49 621/412151",
    "sg:postcode":"68165",
    "sg:province":"Baden-W\u00fcrttemberg",
    "wof:name":"Elefanten-apotheke",
    "wof:placetype":"venue"
},
  "geometry": {"coordinates":[8.479026,49.486881],"type":"Point"}
}