{
  "type": "Feature",
  "properties": {
    "iso:country":"DE",
    "sg:address":"Kumpfm\u00fchler Str. 61",
    "sg:city":"Regensburg",
    "sg:phone":"+49 941/999878",
    "sg:postcode":"93051",
    "sg:province":"Bayern",
    "wof:name":"Anneliese L\u00fcftl Rechtsanw\u00e4ltin",
    "wof:placetype":"venue"
},
  "geometry": {"coordinates":[12.0867128372,49.0065116882],"type":"Point"}
}