{
  "type": "Feature",
  "properties": {
    "iso:country":"DE",
    "sg:address":"Schlo\u00dfhof 3",
    "sg:city":"Nebra",
    "sg:phone":"+49 34461/22089",
    "sg:postcode":"06642",
    "sg:province":"Sachsen-Anhalt",
    "wof:name":"Umweltbildungszentrum Saale-unstrut E. V.",
    "wof:placetype":"venue"
},
  "geometry": {"coordinates":[11.5452852249,51.2680587769],"type":"Point"}
}