{
  "type": "Feature",
  "properties": {
    "iso:country":"DE",
    "sg:address":"N\u00fcssle 7",
    "sg:city":"Schwaigern",
    "sg:phone":"+49 7138/67527",
    "sg:postcode":"74193",
    "sg:province":"Baden-W\u00fcrttemberg",
    "wof:name":"G. Landauer",
    "wof:placetype":"venue"
},
  "geometry": {"coordinates":[9.011203,49.13401],"type":"Point"}
}