{
  "type": "Feature",
  "properties": {
    "iso:country":"DE",
    "sg:address":"Steinstr. 14",
    "sg:city":"Bingen",
    "sg:phone":"+49 6721/47790",
    "sg:postcode":"55411",
    "sg:province":"Rheinland-Pfalz",
    "wof:name":"Gemein Immobilienmakler",
    "wof:placetype":"venue"
},
  "geometry": {"coordinates":[7.915353775,49.9470367432],"type":"Point"}
}