{
  "type": "Feature",
  "properties": {
    "iso:country":"DE",
    "sg:address":"Tulpenweg 15 A",
    "sg:city":"Idstein",
    "sg:phone":"+49 6126/4612",
    "sg:postcode":"65510",
    "sg:province":"Hessen",
    "wof:name":"Karl Horst Reuter Architekt",
    "wof:placetype":"venue"
},
  "geometry": {"coordinates":[8.25348,50.241131],"type":"Point"}
}