{
  "type": "Feature",
  "properties": {
    "iso:country":"DE",
    "sg:address":"In der Etzmatt 6",
    "sg:city":"Heitersheim",
    "sg:phone":"+49 7633/982030",
    "sg:postcode":"79423",
    "sg:province":"Baden-W\u00fcrttemberg",
    "wof:name":"W. Sagawe",
    "wof:placetype":"venue"
},
  "geometry": {"coordinates":[7.6774477959,47.8831443787],"type":"Point"}
}