{
  "type": "Feature",
  "properties": {
    "iso:country":"DE",
    "sg:city":"Wuppertal",
    "sg:postcode":"42103",
    "sg:province":"Nordrhein-Westfalen",
    "wof:name":"Heisse Bienen - Ihr Privatclub In Wuppertal",
    "wof:placetype":"venue"
},
  "geometry": {"coordinates":[7.146295,51.2589],"type":"Point"}
}