{
  "type": "Feature",
  "properties": {
    "iso:country":"DE",
    "sg:address":"Postplatz 2",
    "sg:city":"Schwerte",
    "sg:phone":"+49 2304/16294",
    "sg:postcode":"58239",
    "sg:province":"Nordrhein-Westfalen",
    "wof:name":"Klaus Kayser Fachgesch\u00e4ft F\u00fcr Optik",
    "wof:placetype":"venue"
},
  "geometry": {"coordinates":[7.5655860901,51.4415893555],"type":"Point"}
}