{
  "type": "Feature",
  "properties": {
    "iso:country":"DE",
    "sg:address":"Am Schie\u00dfstand 3",
    "sg:city":"Sehnde",
    "sg:phone":"+49 5138/616624",
    "sg:postcode":"31319",
    "sg:province":"Niedersachsen",
    "wof:name":"Heinrich Holicki",
    "wof:placetype":"venue"
},
  "geometry": {"coordinates":[10.051375,52.309921],"type":"Point"}
}