{
  "type": "Feature",
  "properties": {
    "iso:country":"DE",
    "sg:address":"Starnberger Wiese 58",
    "sg:city":"Starnberg",
    "sg:phone":"+49 8151/21995",
    "sg:postcode":"82319",
    "sg:province":"Bayern",
    "wof:name":"Sca Holz Gmbh",
    "wof:placetype":"venue"
},
  "geometry": {"coordinates":[11.348333,48.017017],"type":"Point"}
}