{
  "type": "Feature",
  "properties": {
    "iso:country":"DE",
    "sg:address":"Omerskopfstr. 16",
    "sg:city":"Achern",
    "sg:phone":"+49 7841/24257",
    "sg:postcode":"77855",
    "sg:province":"Baden-W\u00fcrttemberg",
    "wof:name":"Siegfried Dammer",
    "wof:placetype":"venue"
},
  "geometry": {"coordinates":[8.090388298,48.6301269531],"type":"Point"}
}