{
  "type": "Feature",
  "properties": {
    "iso:country":"DE",
    "sg:address":"Reutlinger Str. 19",
    "sg:city":"Eningen",
    "sg:phone":"+49 4952/2295400",
    "sg:postcode":"72800",
    "sg:province":"Baden-W\u00fcrttemberg",
    "wof:name":"Project Kunststoff-profiltechnik Gmbh Co & Kg",
    "wof:placetype":"venue"
},
  "geometry": {"coordinates":[8.7240457535,52.089969635],"type":"Point"}
}