{
  "type": "Feature",
  "properties": {
    "iso:country":"DE",
    "sg:address":"Hauptstr. 6",
    "sg:city":"Eppingen",
    "sg:phone":"+49 7262/4442",
    "sg:postcode":"75031",
    "sg:province":"Baden-W\u00fcrttemberg",
    "wof:name":"Hermann Holz",
    "wof:placetype":"venue"
},
  "geometry": {"coordinates":[8.8995161057,49.1004371643],"type":"Point"}
}