{
  "type": "Feature",
  "properties": {
    "iso:country":"DE",
    "sg:address":"Kaiserstra\u00dfe 160-162",
    "sg:city":"Karlsruhe",
    "sg:phone":"+49 721/859008",
    "sg:postcode":"76133",
    "sg:province":"Baden-W\u00fcrttemberg",
    "wof:name":"Creativware J. Picht",
    "wof:placetype":"venue"
},
  "geometry": {"coordinates":[8.393243,49.01022],"type":"Point"}
}