{
  "type": "Feature",
  "properties": {
    "iso:country":"DE",
    "sg:address":"An der Buchenforst 2",
    "sg:city":"Ilsede",
    "sg:phone":"+49 5172/13073",
    "sg:postcode":"31241",
    "sg:province":"Niedersachsen",
    "wof:name":"E.-j. Starke Malereibetrieb Gmbh",
    "wof:placetype":"venue"
},
  "geometry": {"coordinates":[10.203661,52.282551],"type":"Point"}
}