{
  "type": "Feature",
  "properties": {
    "iso:country":"DE",
    "sg:address":"Lindenstr. 45",
    "sg:city":"Schiffweiler",
    "sg:phone":"+49 6824/4742",
    "sg:postcode":"66578",
    "sg:province":"Saarland",
    "wof:name":"Dorfbrunnen",
    "wof:placetype":"venue"
},
  "geometry": {"coordinates":[7.1130299568,49.3893356323],"type":"Point"}
}