{
  "type": "Feature",
  "properties": {
    "iso:country":"DE",
    "sg:address":"Rul\u00e4nderweg 7",
    "sg:city":"Freiberg",
    "sg:phone":"+49 7141/271834",
    "sg:postcode":"71691",
    "sg:province":"Baden-W\u00fcrttemberg",
    "wof:name":"G. Maser Steuerberater",
    "wof:placetype":"venue"
},
  "geometry": {"coordinates":[9.2066726685,48.9333000183],"type":"Point"}
}