{
  "type": "Feature",
  "properties": {
    "iso:country":"DE",
    "sg:address":"Bruno-Bergner-Str. 1",
    "sg:city":"Greiz",
    "sg:phone":"+49 3661/673185",
    "sg:postcode":"07973",
    "sg:province":"Th\u00fcringen",
    "wof:name":"Adelbert Schaarschmidt",
    "wof:placetype":"venue"
},
  "geometry": {"coordinates":[12.1978492737,50.6551437378],"type":"Point"}
}