{
  "type": "Feature",
  "properties": {
    "iso:country":"DE",
    "sg:address":"Hinterer Graben 10",
    "sg:city":"Bamberg",
    "sg:phone":"+49 951/26345",
    "sg:postcode":"96047",
    "sg:province":"Bayern",
    "wof:name":"Raumausstattung Adalbert Holl",
    "wof:placetype":"venue"
},
  "geometry": {"coordinates":[10.884221077,49.8947143555],"type":"Point"}
}