{
  "type": "Feature",
  "properties": {
    "iso:country":"DE",
    "sg:address":"M\u00fchlwiesenstr. 10",
    "sg:city":"Bietigheim-Bissingen",
    "sg:phone":"+49 7142/45673",
    "sg:postcode":"74321",
    "sg:province":"Baden-W\u00fcrttemberg",
    "wof:name":"Gastst\u00e4tte Wei\u00dfbierhaus",
    "wof:placetype":"venue"
},
  "geometry": {"coordinates":[9.1329460144,48.9605026245],"type":"Point"}
}