{
  "type": "Feature",
  "properties": {
    "iso:country":"DE",
    "sg:address":"Bruchwiesenstr. 15",
    "sg:city":"Darmstadt",
    "sg:phone":"+49 6151/963000",
    "sg:postcode":"64285",
    "sg:province":"Hessen",
    "wof:name":"Mhe Gmbh",
    "wof:placetype":"venue"
},
  "geometry": {"coordinates":[8.6562957764,49.8613243103],"type":"Point"}
}