{
  "type": "Feature",
  "properties": {
    "iso:country":"DE",
    "sg:address":"Mechtelstr. 2",
    "sg:city":"Trier",
    "sg:phone":"+49 651/64000",
    "sg:postcode":"54293",
    "sg:province":"Rheinland-Pfalz",
    "wof:name":"Klaus Pauly",
    "wof:placetype":"venue"
},
  "geometry": {"coordinates":[6.692085,49.780293],"type":"Point"}
}