{
  "type": "Feature",
  "properties": {
    "iso:country":"DE",
    "sg:address":"Bothostr. 3",
    "sg:city":"N\u00fcrnberg",
    "sg:phone":"+49 911/4466650",
    "sg:postcode":"90461",
    "sg:province":"Bayern",
    "wof:name":"Airport- Und Firmen-express G\u00fcnter Ruppert",
    "wof:placetype":"venue"
},
  "geometry": {"coordinates":[11.0924367905,49.431388855],"type":"Point"}
}