{
  "type": "Feature",
  "properties": {
    "iso:country":"DE",
    "sg:address":"Hauptstr. 57",
    "sg:city":"B\u00f6nnigheim",
    "sg:phone":"+49 7143/88780",
    "sg:postcode":"74357",
    "sg:province":"Baden-W\u00fcrttemberg",
    "wof:name":"Horst Schollenberger",
    "wof:placetype":"venue"
},
  "geometry": {"coordinates":[9.0934791565,49.0425415039],"type":"Point"}
}