{
  "type": "Feature",
  "properties": {
    "iso:country":"DE",
    "sg:address":"Brunnenstr. 43",
    "sg:city":"Horn-Bad Meinberg",
    "sg:phone":"+49 5234/9886",
    "sg:postcode":"32805",
    "sg:province":"Nordrhein-Westfalen",
    "wof:name":"Ev. Pfarramt Ev. Reform. Gemeinde Meinberg",
    "wof:placetype":"venue"
},
  "geometry": {"coordinates":[8.9781999588,51.8968391418],"type":"Point"}
}