{
  "type": "Feature",
  "properties": {
    "iso:country":"DE",
    "sg:address":"Menzelstr. 4",
    "sg:city":"Konstanz",
    "sg:phone":"+49 7531/54282",
    "sg:postcode":"78467",
    "sg:province":"Baden-W\u00fcrttemberg",
    "wof:name":"Pension B. Und Hildegard Krumm",
    "wof:placetype":"venue"
},
  "geometry": {"coordinates":[9.1770906448,47.6775093079],"type":"Point"}
}