{
  "type": "Feature",
  "properties": {
    "iso:country":"DE",
    "sg:address":"Braunschweiger Str. 67 b",
    "sg:city":"Salzgitter",
    "sg:phone":"+49 5341/34090",
    "sg:postcode":"38259",
    "sg:province":"Niedersachsen",
    "wof:name":"Garten-center Nordharz Gmbh & Co.",
    "wof:placetype":"venue"
},
  "geometry": {"coordinates":[10.36624,52.049511],"type":"Point"}
}