{
  "type": "Feature",
  "properties": {
    "iso:country":"DE",
    "sg:address":"Am Brabrinke 2-4",
    "sg:city":"Hannover",
    "sg:postcode":"30519",
    "sg:province":"Niedersachsen",
    "wof:name":"Troester Gmbh",
    "wof:placetype":"venue"
},
  "geometry": {"coordinates":[9.785012,52.323792],"type":"Point"}
}