{
  "type": "Feature",
  "properties": {
    "iso:country":"DE",
    "sg:address":"Gemeindeplatz 6",
    "sg:city":"Gro\u00dfpostwitz",
    "sg:phone":"+49 35938/51384",
    "sg:postcode":"02692",
    "sg:province":"Sachsen",
    "wof:name":"A. M\u00fcller",
    "wof:placetype":"venue"
},
  "geometry": {"coordinates":[14.41587,51.128208],"type":"Point"}
}