{
  "type": "Feature",
  "properties": {
    "iso:country":"DE",
    "sg:address":"Reuterstr. 47",
    "sg:city":"Berlin",
    "sg:phone":"+49 30/6243464",
    "sg:postcode":"12047",
    "sg:province":"Berlin",
    "wof:name":"Wellness-center Andrea Reuscher",
    "wof:placetype":"venue"
},
  "geometry": {"coordinates":[13.428895,52.490112],"type":"Point"}
}