{
  "type": "Feature",
  "properties": {
    "iso:country":"DE",
    "sg:address":"Karl-Maser-Str. 8",
    "sg:city":"Brensbach",
    "sg:phone":"+49 6161/428",
    "sg:postcode":"64395",
    "sg:province":"Hessen",
    "wof:name":"Wilh. Trinkaus",
    "wof:placetype":"venue"
},
  "geometry": {"coordinates":[8.8774318695,49.7743721008],"type":"Point"}
}