{
  "type": "Feature",
  "properties": {
    "iso:country":"DE",
    "sg:address":"Hellensteinstr. 56",
    "sg:city":"M\u00fcnchen",
    "sg:phone":"+49 89/876968",
    "sg:postcode":"81243",
    "sg:province":"Bayern",
    "wof:name":"Sophie Schierbaum",
    "wof:placetype":"venue"
},
  "geometry": {"coordinates":[11.435473,48.151649],"type":"Point"}
}