{
  "type": "Feature",
  "properties": {
    "iso:country":"DE",
    "sg:address":"Staberger Str. 35a",
    "sg:city":"L\u00fcdenscheid",
    "sg:phone":"+49 2351/860606",
    "sg:postcode":"58511",
    "sg:province":"Nordrhein-Westfalen",
    "wof:name":"Otto Schmidt",
    "wof:placetype":"venue"
},
  "geometry": {"coordinates":[7.63918,51.212688],"type":"Point"}
}