{
  "type": "Feature",
  "properties": {
    "iso:country":"DE",
    "sg:address":"Wiesenstr. 6",
    "sg:city":"Wildeck",
    "sg:postcode":"36208",
    "sg:province":"Hessen",
    "wof:name":"Schnupferclub Oal Schn\u00fc Ottwin Landefeld",
    "wof:placetype":"venue"
},
  "geometry": {"coordinates":[9.9404277802,50.9354286194],"type":"Point"}
}