{
  "type": "Feature",
  "properties": {
    "iso:country":"DE",
    "sg:address":"Klosterstr. 52",
    "sg:city":"Gronau",
    "sg:phone":"+49 2565/1596",
    "sg:postcode":"48599",
    "sg:province":"Nordrhein-Westfalen",
    "wof:name":"Erwin B\u00fccker",
    "wof:placetype":"venue"
},
  "geometry": {"coordinates":[7.024716,52.190296],"type":"Point"}
}