{
  "type": "Feature",
  "properties": {
    "iso:country":"DE",
    "sg:address":"Querstr. 3",
    "sg:city":"Ahlden",
    "sg:phone":"+49 5164/8337",
    "sg:postcode":"29693",
    "sg:province":"Niedersachsen",
    "wof:name":"Fritz K\u00fcker & Sohn",
    "wof:placetype":"venue"
},
  "geometry": {"coordinates":[9.553642,52.760174],"type":"Point"}
}