{
  "type": "Feature",
  "properties": {
    "iso:country":"DE",
    "sg:address":"Marktstr. 115",
    "sg:city":"Oberhausen",
    "sg:phone":"+49 208/21066",
    "sg:postcode":"46045",
    "sg:province":"Nordrhein-Westfalen",
    "wof:name":"Bernhard Suthoff",
    "wof:placetype":"venue"
},
  "geometry": {"coordinates":[6.857006,51.468609],"type":"Point"}
}