{
  "type": "Feature",
  "properties": {
    "iso:country":"DE",
    "sg:address":"Kantstr. 15",
    "sg:city":"Berlin",
    "sg:phone":"+49 30/3131645",
    "sg:postcode":"10623",
    "sg:province":"Berlin",
    "wof:name":"Martin Hartknoch Steuerberater",
    "wof:placetype":"venue"
},
  "geometry": {"coordinates":[13.3265447617,52.5057754517],"type":"Point"}
}