{
  "type": "Feature",
  "properties": {
    "iso:country":"DE",
    "sg:address":"Insterburger Paltz 5",
    "sg:city":"Krefeld",
    "sg:phone":"+49 2151",
    "sg:postcode":"47829",
    "sg:province":"Nordrhein-Westfalen",
    "wof:name":"Reiseb\u00fcro Bernards",
    "wof:placetype":"venue"
},
  "geometry": {"coordinates":[6.64993,51.353821],"type":"Point"}
}