{
  "type": "Feature",
  "properties": {
    "iso:country":"DE",
    "sg:address":"Klosterhof 24",
    "sg:city":"Hann. M\u00fcnden",
    "sg:phone":"+49 5544/91070",
    "sg:postcode":"34346",
    "sg:province":"Niedersachsen",
    "wof:name":"Restaurant Klosterm\u00fchle",
    "wof:placetype":"venue"
},
  "geometry": {"coordinates":[9.6233453751,51.5429992676],"type":"Point"}
}