{
  "type": "Feature",
  "properties": {
    "iso:country":"DE",
    "sg:address":"Am H\u00e4ngelbach 4",
    "sg:city":"Bendorf",
    "sg:phone":"+49 2622/90490",
    "sg:postcode":"56170",
    "sg:province":"Rheinland-Pfalz",
    "wof:name":"W. Scheidweiler Gmbh",
    "wof:placetype":"venue"
},
  "geometry": {"coordinates":[7.5616559982,50.4261627197],"type":"Point"}
}