{
  "type": "Feature",
  "properties": {
    "iso:country":"DE",
    "sg:address":"Rathausplatz 4",
    "sg:city":"Vellmar",
    "sg:phone":"+49 561/827585",
    "sg:postcode":"34246",
    "sg:province":"Hessen",
    "wof:name":"Gertrud Siekmann Kg",
    "wof:placetype":"venue"
},
  "geometry": {"coordinates":[9.468624115,51.3621292114],"type":"Point"}
}