{
  "type": "Feature",
  "properties": {
    "iso:country":"DE",
    "sg:address":"Auf dem H\u00f6verich 8",
    "sg:city":"Much",
    "sg:phone":"+49 2245/4599",
    "sg:postcode":"53804",
    "sg:province":"Nordrhein-Westfalen",
    "wof:name":"Bernd Wessel Ingenieur",
    "wof:placetype":"venue"
},
  "geometry": {"coordinates":[7.4386119843,50.8884544373],"type":"Point"}
}