{
  "type": "Feature",
  "properties": {
    "iso:country":"DE",
    "sg:address":"Joliot-Curie-Str. 6",
    "sg:city":"Wilkau-Ha\u00dflau",
    "sg:phone":"+49 375/671927",
    "sg:postcode":"08112",
    "sg:province":"Sachsen",
    "wof:name":"Bernd Schlegel",
    "wof:placetype":"venue"
},
  "geometry": {"coordinates":[12.507604599,50.6810073853],"type":"Point"}
}