{
  "type": "Feature",
  "properties": {
    "iso:country":"DE",
    "sg:address":"Altendorfer Str. 104",
    "sg:city":"Essen",
    "sg:phone":"+49 201/827400",
    "sg:postcode":"45143",
    "sg:province":"Nordrhein-Westfalen",
    "wof:name":"Kobefab Gesellschaft F\u00fcr Heim-",
    "wof:placetype":"venue"
},
  "geometry": {"coordinates":[6.9939279556,51.4603729248],"type":"Point"}
}