{
  "type": "Feature",
  "properties": {
    "iso:country":"DE",
    "sg:address":"Ortsstr. 103",
    "sg:city":"Crispendorf",
    "sg:phone":"+49 3663/428155",
    "sg:postcode":"07924",
    "sg:province":"Th\u00fcringen",
    "wof:name":"Hofmann U. Noll Ohg",
    "wof:placetype":"venue"
},
  "geometry": {"coordinates":[11.7302894592,50.5906105042],"type":"Point"}
}