{
  "type": "Feature",
  "properties": {
    "iso:country":"DE",
    "sg:address":"Weihersbergstr. 7",
    "sg:city":"Melsbach",
    "sg:phone":"+49 2634/2600",
    "sg:postcode":"56581",
    "sg:province":"Rheinland-Pfalz",
    "wof:name":"C. Schmidt",
    "wof:placetype":"venue"
},
  "geometry": {"coordinates":[7.4763288498,50.488067627],"type":"Point"}
}