{
  "type": "Feature",
  "properties": {
    "iso:country":"DE",
    "sg:address":"Grindeler Str. 13a",
    "sg:city":"Kirchen",
    "sg:phone":"+49 2741/62636",
    "sg:postcode":"57548",
    "sg:province":"Rheinland-Pfalz",
    "wof:name":"Josef Laubenthal",
    "wof:placetype":"venue"
},
  "geometry": {"coordinates":[7.8698291779,50.8119049072],"type":"Point"}
}