{
  "type": "Feature",
  "properties": {
    "iso:country":"DE",
    "sg:address":"Werler Str. 66",
    "sg:city":"Hamm",
    "sg:phone":"+49 2381/26617",
    "sg:postcode":"59065",
    "sg:province":"Nordrhein-Westfalen",
    "wof:name":"Spitzweg-apotheke",
    "wof:placetype":"venue"
},
  "geometry": {"coordinates":[7.824607,51.672913],"type":"Point"}
}