{
  "type": "Feature",
  "properties": {
    "iso:country":"DE",
    "sg:address":"Mauerstr. 2",
    "sg:city":"Altenburg",
    "sg:phone":"+49 3447/311282",
    "sg:postcode":"04600",
    "sg:province":"Th\u00fcringen",
    "wof:name":"Ralf Hendel",
    "wof:placetype":"venue"
},
  "geometry": {"coordinates":[12.438334,50.982521],"type":"Point"}
}