{
  "type": "Feature",
  "properties": {
    "iso:country":"DE",
    "sg:address":"Lengfurter Str. 24",
    "sg:city":"Kreuzwertheim",
    "sg:phone":"+49 9342/6503",
    "sg:postcode":"97892",
    "sg:province":"Bayern",
    "wof:name":"Dr. Med. Philipp Eichelbauer Arzt F\u00fcr Allgemeinmedizin",
    "wof:placetype":"venue"
},
  "geometry": {"coordinates":[9.5196361542,49.7672386169],"type":"Point"}
}