{
  "type": "Feature",
  "properties": {
    "iso:country":"DE",
    "sg:address":"Guderslebener Str. 2",
    "sg:city":"Woffleben",
    "sg:phone":"+49 36332/70465",
    "sg:postcode":"99762",
    "sg:province":"Th\u00fcringen",
    "wof:name":"Gastst\u00e4tte E. Schild",
    "wof:placetype":"venue"
},
  "geometry": {"coordinates":[-164.4948425293,65.1407165527],"type":"Point"}
}