{
  "type": "Feature",
  "properties": {
    "iso:country":"DE",
    "sg:address":"Bessemerstr 42b",
    "sg:city":"Berlin",
    "sg:phone":"+49 30/75446598",
    "sg:postcode":"12103",
    "sg:province":"Berlin",
    "wof:name":"Rkb Rohrleitungs- Und Kanalbau Gmbh",
    "wof:placetype":"venue"
},
  "geometry": {"coordinates":[13.3667001724,52.4641151428],"type":"Point"}
}