{
  "type": "Feature",
  "properties": {
    "iso:country":"DE",
    "sg:address":"Carl-Maria-von-Weber-Str. 5",
    "sg:city":"Marktoberdorf",
    "sg:phone":"+49 8342/6402",
    "sg:postcode":"87616",
    "sg:province":"Bayern",
    "wof:name":"Hieronimus Rieger Bildhauer",
    "wof:placetype":"venue"
},
  "geometry": {"coordinates":[10.618706,47.77705],"type":"Point"}
}