{
  "type": "Feature",
  "properties": {
    "iso:country":"DE",
    "sg:address":"Engelstr. 65",
    "sg:city":"Trier",
    "sg:phone":"+49 651/9911199",
    "sg:postcode":"54292",
    "sg:province":"Rheinland-Pfalz",
    "wof:name":"Neuseeland-jetzt: Ihre Neuseeland-reise Planen, Re",
    "wof:placetype":"venue"
},
  "geometry": {"coordinates":[6.64636,49.763557],"type":"Point"}
}