{
  "type": "Feature",
  "properties": {
    "iso:country":"DE",
    "sg:address":"Weinmarkt 4",
    "sg:city":"N\u00fcrnberg",
    "sg:phone":"+49 911/222004",
    "sg:postcode":"90403",
    "sg:province":"Bayern",
    "wof:name":"Nagel Flechtner Und Pernet Rechtsanw\u00e4lte",
    "wof:placetype":"venue"
},
  "geometry": {"coordinates":[11.0753679276,49.4554748535],"type":"Point"}
}