{
  "type": "Feature",
  "properties": {
    "iso:country":"DE",
    "sg:address":"Cranachweg 6",
    "sg:city":"Regensburg",
    "sg:phone":"+49 941/920760",
    "sg:postcode":"93051",
    "sg:province":"Bayern",
    "wof:name":"Ratisbona Steuerberatungs- Gesellschaft Mbh",
    "wof:placetype":"venue"
},
  "geometry": {"coordinates":[12.0652580261,49.0059280396],"type":"Point"}
}