{
  "type": "Feature",
  "properties": {
    "iso:country":"DE",
    "sg:address":"Zwischen den Wegen 20",
    "sg:city":"Kirkel",
    "sg:phone":"+49 6849/6720",
    "sg:postcode":"66459",
    "sg:province":"Saarland",
    "wof:name":"Heinz Henrichs Architekt",
    "wof:placetype":"venue"
},
  "geometry": {"coordinates":[7.227949,49.27951],"type":"Point"}
}