{
  "type": "Feature",
  "properties": {
    "iso:country":"DE",
    "sg:address":"Ehinger Str. 46",
    "sg:city":"M\u00fcnsingen",
    "sg:phone":"+49 7383/527",
    "sg:postcode":"72525",
    "sg:province":"Baden-W\u00fcrttemberg",
    "wof:name":"Hermann M\u00fcnch",
    "wof:placetype":"venue"
},
  "geometry": {"coordinates":[9.539541,48.341839],"type":"Point"}
}