{
  "type": "Feature",
  "properties": {
    "iso:country":"DE",
    "sg:address":"Forstenrieder Allee 125",
    "sg:city":"M\u00fcnchen",
    "sg:phone":"+49 89/750315",
    "sg:postcode":"81476",
    "sg:province":"Bayern",
    "wof:name":"Michael P. Adolf Rechtsanwalt",
    "wof:placetype":"venue"
},
  "geometry": {"coordinates":[11.4971866608,48.0904960632],"type":"Point"}
}