{
  "type": "Feature",
  "properties": {
    "iso:country":"DE",
    "sg:address":"Rheinauer Ring 117",
    "sg:city":"Rastatt",
    "sg:phone":"+49 7222/29383",
    "sg:postcode":"76437",
    "sg:province":"Baden-W\u00fcrttemberg",
    "wof:name":"Murgblick",
    "wof:placetype":"venue"
},
  "geometry": {"coordinates":[8.1982364655,48.8741035461],"type":"Point"}
}