{
  "type": "Feature",
  "properties": {
    "iso:country":"DE",
    "sg:address":"Schleizer Str. 83",
    "sg:city":"Hof",
    "sg:phone":"+49 9281/84496",
    "sg:postcode":"95028",
    "sg:province":"Bayern",
    "wof:name":"Max Rank Haus- Und K\u00fcchen- Ger\u00e4te, Gro\u00dfhandlung",
    "wof:placetype":"venue"
},
  "geometry": {"coordinates":[11.9120187759,50.331401825],"type":"Point"}
}