{
  "type": "Feature",
  "properties": {
    "iso:country":"DE",
    "sg:address":"Koppelweg 12",
    "sg:city":"Neu Wulmstorf",
    "sg:phone":"+49 4168/254",
    "sg:postcode":"21629",
    "sg:province":"Niedersachsen",
    "wof:name":"Heinz Ahrens",
    "wof:placetype":"venue"
},
  "geometry": {"coordinates":[9.80016,53.420712],"type":"Point"}
}