{
  "type": "Feature",
  "properties": {
    "iso:country":"DE",
    "sg:address":"Zum Wasserberg 7",
    "sg:city":"Salzkotten",
    "sg:phone":"+49 2955/76560",
    "sg:postcode":"33154",
    "sg:province":"Nordrhein-Westfalen",
    "wof:name":"Elektro Steffen Gmbh",
    "wof:placetype":"venue"
},
  "geometry": {"coordinates":[8.671587,51.639584],"type":"Point"}
}