{
  "type": "Feature",
  "properties": {
    "iso:country":"DE",
    "sg:address":"Hinter dem Hirsch 1",
    "sg:city":"Emmerich",
    "sg:phone":"+49 2822/75405",
    "sg:postcode":"46446",
    "sg:province":"Nordrhein-Westfalen",
    "wof:name":"Stadtb\u00fccherei",
    "wof:placetype":"venue"
},
  "geometry": {"coordinates":[6.238568,51.830929],"type":"Point"}
}