{
  "type": "Feature",
  "properties": {
    "iso:country":"DE",
    "sg:address":"Heinrich-B\u00fcssing-Ring 41",
    "sg:city":"Braunschweig",
    "sg:phone":"+49 531/7996744",
    "sg:postcode":"38102",
    "sg:province":"Niedersachsen",
    "wof:name":"Droste Meyer-schwickerath Und Warner",
    "wof:placetype":"venue"
},
  "geometry": {"coordinates":[10.530327,52.250885],"type":"Point"}
}