{
  "type": "Feature",
  "properties": {
    "iso:country":"DE",
    "sg:address":"Dettinger Str. 41/1",
    "sg:city":"Kirchheim",
    "sg:phone":"+49 7021/6582",
    "sg:postcode":"73230",
    "sg:province":"Baden-W\u00fcrttemberg",
    "wof:name":"Hans Feucht",
    "wof:placetype":"venue"
},
  "geometry": {"coordinates":[9.451746,48.644127],"type":"Point"}
}