{
  "type": "Feature",
  "properties": {
    "iso:country":"DE",
    "sg:address":"Berliner Str. 16",
    "sg:city":"Hemmingen",
    "sg:phone":"+49 511/41080",
    "sg:postcode":"30966",
    "sg:province":"Niedersachsen",
    "wof:name":"Senioren-residenz Am Rosen- Garten Hemmingen-westerfeld",
    "wof:placetype":"venue"
},
  "geometry": {"coordinates":[9.733074,52.324703],"type":"Point"}
}