{
  "type": "Feature",
  "properties": {
    "iso:country":"DE",
    "sg:address":"Buchenweg 2",
    "sg:city":"Drolshagen",
    "sg:phone":"+49 2763/285",
    "sg:postcode":"57489",
    "sg:province":"Nordrhein-Westfalen",
    "wof:name":"Kurt Koch",
    "wof:placetype":"venue"
},
  "geometry": {"coordinates":[7.7605419159,51.0524749756],"type":"Point"}
}