{
  "type": "Feature",
  "properties": {
    "iso:country":"DE",
    "sg:address":"Schnellerstr. 24",
    "sg:city":"Berlin",
    "sg:phone":"+49 30/6361738",
    "sg:postcode":"12439",
    "sg:province":"Berlin",
    "wof:name":"Andreas Pietzker",
    "wof:placetype":"venue"
},
  "geometry": {"coordinates":[13.512083,52.45575],"type":"Point"}
}