{
  "type": "Feature",
  "properties": {
    "iso:country":"DE",
    "sg:address":"Gro\u00dfe Str. 24",
    "sg:city":"Bad Iburg",
    "sg:phone":"+49 5403/73200",
    "sg:postcode":"49186",
    "sg:province":"Niedersachsen",
    "wof:name":"Rainer Preu\u00df Steuerberater",
    "wof:placetype":"venue"
},
  "geometry": {"coordinates":[8.0448122025,52.1560935974],"type":"Point"}
}