{
  "type": "Feature",
  "properties": {
    "iso:country":"DE",
    "sg:address":"Brannenburger Str. 36 a",
    "sg:city":"Nu\u00dfdorf",
    "sg:phone":"+49 8034/3190",
    "sg:postcode":"83131",
    "sg:province":"Bayern",
    "wof:name":"Kaspar Mayer",
    "wof:placetype":"venue"
},
  "geometry": {"coordinates":[12.147278,47.743294],"type":"Point"}
}