{
  "type": "Feature",
  "properties": {
    "iso:country":"DE",
    "sg:address":"Styrumer Str. 7",
    "sg:city":"Oberhausen",
    "sg:phone":"+49 208/203296",
    "sg:postcode":"46045",
    "sg:province":"Nordrhein-Westfalen",
    "wof:name":"Heike Malke Und Valentino De Hond",
    "wof:placetype":"venue"
},
  "geometry": {"coordinates":[6.84817,51.470428],"type":"Point"}
}