{
  "type": "Feature",
  "properties": {
    "iso:country":"DE",
    "sg:address":"Schifferstr. 2",
    "sg:city":"Weisenheim am Sand",
    "sg:phone":"+49 6353/8605",
    "sg:postcode":"67256",
    "sg:province":"Rheinland-Pfalz",
    "wof:name":"Kurt Fischer",
    "wof:placetype":"venue"
},
  "geometry": {"coordinates":[8.2498311996,49.5194320679],"type":"Point"}
}