{
  "type": "Feature",
  "properties": {
    "iso:country":"DE",
    "sg:address":"Industriestr 17",
    "sg:city":"Herne",
    "sg:phone":"+49 2323/17880",
    "sg:postcode":"44628",
    "sg:province":"Nordrhein-Westfalen",
    "wof:name":"Druckerei Frisch Gmbh & Cie Kg",
    "wof:placetype":"venue"
},
  "geometry": {"coordinates":[7.2431530952,51.549407959],"type":"Point"}
}