{
  "type": "Feature",
  "properties": {
    "iso:country":"DE",
    "sg:address":"Sandkaulstr. 15",
    "sg:city":"Aachen",
    "sg:phone":"+49 241/23975",
    "sg:postcode":"52062",
    "sg:province":"Nordrhein-Westfalen",
    "wof:name":"Galerie",
    "wof:placetype":"venue"
},
  "geometry": {"coordinates":[6.0883498192,50.7789115906],"type":"Point"}
}