{
  "type": "Feature",
  "properties": {
    "iso:country":"DE",
    "sg:address":"Bessererstr. 15",
    "sg:city":"Ulm",
    "sg:phone":"+49 731/610234",
    "sg:postcode":"89073",
    "sg:province":"Baden-W\u00fcrttemberg",
    "wof:name":"Hans-j\u00fcrgen W\u00f6lfinger Masseur",
    "wof:placetype":"venue"
},
  "geometry": {"coordinates":[9.98737,48.403019],"type":"Point"}
}