{
  "type": "Feature",
  "properties": {
    "iso:country":"DE",
    "sg:address":"Mar\u00e4zweg 9",
    "sg:city":"Kressbronn",
    "sg:postcode":"88079",
    "sg:province":"Baden-W\u00fcrttemberg",
    "wof:name":"Westpark Grundst\u00fccks- Verwaltungs Gmbh & Co.",
    "wof:placetype":"venue"
},
  "geometry": {"coordinates":[9.59785,47.60783],"type":"Point"}
}