{
  "type": "Feature",
  "properties": {
    "iso:country":"DE",
    "sg:address":"Zum Kreuzkamp 3",
    "sg:city":"Heeslingen",
    "sg:phone":"+49 4281/2249",
    "sg:postcode":"27404",
    "sg:province":"Niedersachsen",
    "wof:name":"Molkerei Heeslingen",
    "wof:placetype":"venue"
},
  "geometry": {"coordinates":[9.335623,53.317699],"type":"Point"}
}