{
  "type": "Feature",
  "properties": {
    "iso:country":"DE",
    "sg:address":"Ernst-Tellering-Str. 50",
    "sg:city":"Langenfeld",
    "sg:phone":"+49 2173/92700",
    "sg:postcode":"40764",
    "sg:province":"Nordrhein-Westfalen",
    "wof:name":"Auto-strunk Karl-heinrich Strunk Gmbh",
    "wof:placetype":"venue"
},
  "geometry": {"coordinates":[6.9668917656,51.1227874756],"type":"Point"}
}