{
  "type": "Feature",
  "properties": {
    "iso:country":"DE",
    "sg:address":"Akazienweg 5",
    "sg:city":"Saarbr\u00fccken",
    "sg:phone":"+49 681/818363",
    "sg:postcode":"66121",
    "sg:province":"Saarland",
    "wof:name":"Eckel Gmbh",
    "wof:placetype":"venue"
},
  "geometry": {"coordinates":[7.052823,49.234715],"type":"Point"}
}