{
  "type": "Feature",
  "properties": {
    "iso:country":"DE",
    "sg:address":"D\u00fcrnauer Str. 7",
    "sg:city":"Bad Saulgau",
    "sg:phone":"+49 7581/7936",
    "sg:postcode":"88348",
    "sg:province":"Baden-W\u00fcrttemberg",
    "wof:name":"Ernst Wicker",
    "wof:placetype":"venue"
},
  "geometry": {"coordinates":[9.518683,48.046738],"type":"Point"}
}