{
  "type": "Feature",
  "properties": {
    "iso:country":"DE",
    "sg:address":"Kulturstr. 37 - 39",
    "sg:city":"Duisburg",
    "sg:postcode":"47055",
    "sg:province":"Nordrhein-Westfalen",
    "wof:name":"Aldi Gmbh & Co. Kg",
    "wof:placetype":"venue"
},
  "geometry": {"coordinates":[6.7568092346,51.4068107605],"type":"Point"}
}