{
  "type": "Feature",
  "properties": {
    "iso:country":"DE",
    "sg:address":"Klosterstr. 19",
    "sg:city":"Worphausen",
    "sg:phone":"+49 4208/515",
    "sg:postcode":"28865",
    "sg:province":"Niedersachsen",
    "wof:name":"Kreissparkasse Osterholz",
    "wof:placetype":"venue"
},
  "geometry": {"coordinates":[8.907968,53.141422],"type":"Point"}
}