{
  "type": "Feature",
  "properties": {
    "iso:country":"DE",
    "sg:address":"Raiffeisenstr. 22",
    "sg:city":"Neuburg",
    "sg:phone":"+49 8431/48789",
    "sg:postcode":"86633",
    "sg:province":"Bayern",
    "wof:name":"Wilfried Und Doris Arnold Finanzberater",
    "wof:placetype":"venue"
},
  "geometry": {"coordinates":[11.2607984543,48.7160186768],"type":"Point"}
}