{
  "type": "Feature",
  "properties": {
    "iso:country":"DE",
    "sg:address":"Crailsheimstr. 12",
    "sg:city":"Traunstein",
    "sg:phone":"+49 861/60045",
    "sg:postcode":"83278",
    "sg:province":"Bayern",
    "wof:name":"Chinarestaurant Win Fat",
    "wof:placetype":"venue"
},
  "geometry": {"coordinates":[12.6397285461,47.8683166504],"type":"Point"}
}