{
  "type": "Feature",
  "properties": {
    "iso:country":"DE",
    "sg:address":"Kermeterstr. 36",
    "sg:city":"Heimbach",
    "sg:phone":"+49 2446/95550",
    "sg:postcode":"52396",
    "sg:province":"Nordrhein-Westfalen",
    "wof:name":"Hotel Cafe Ritterstuben",
    "wof:placetype":"venue"
},
  "geometry": {"coordinates":[6.5439682007,50.622089386],"type":"Point"}
}