{
  "type": "Feature",
  "properties": {
    "iso:country":"DE",
    "sg:city":"Oberstadion",
    "sg:phone":"+49 4973/57602",
    "sg:postcode":"89613",
    "sg:province":"Baden-W\u00fcrttemberg",
    "wof:name":"Sparkasse",
    "wof:placetype":"venue"
},
  "geometry": {"coordinates":[9.690745,48.185623],"type":"Point"}
}