{
  "type": "Feature",
  "properties": {
    "iso:country":"DE",
    "sg:address":"Sch\u00fctzenstr. 89",
    "sg:city":"Hamburg",
    "sg:postcode":"22761",
    "sg:province":"Hamburg",
    "wof:name":"Media Sounds",
    "wof:placetype":"venue"
},
  "geometry": {"coordinates":[9.9290800095,53.5672798157],"type":"Point"}
}