{
  "type": "Feature",
  "properties": {
    "iso:country":"DE",
    "sg:address":"Hauptstr. 19",
    "sg:city":"Ruhstorf",
    "sg:phone":"+49 8531/93140",
    "sg:postcode":"94099",
    "sg:province":"Bayern",
    "wof:name":"Hotel Math\u00e4ser",
    "wof:placetype":"venue"
},
  "geometry": {"coordinates":[13.3367681503,48.4370040894],"type":"Point"}
}