{
  "type": "Feature",
  "properties": {
    "iso:country":"DE",
    "sg:address":"Rotenh\u00e4user Weg 60",
    "sg:city":"Osterode",
    "sg:phone":"+49 5522/3578",
    "sg:postcode":"37520",
    "sg:province":"Niedersachsen",
    "wof:name":"Helmut Holzapfel Architekt",
    "wof:placetype":"venue"
},
  "geometry": {"coordinates":[10.273288,51.730339],"type":"Point"}
}