{
  "type": "Feature",
  "properties": {
    "iso:country":"DE",
    "sg:address":"Neue Str. 46",
    "sg:city":"K\u00f6nigslutter",
    "sg:phone":"+49 5353/1656",
    "sg:postcode":"38154",
    "sg:province":"Niedersachsen",
    "wof:name":"Familias Die H\u00e4usliche Krankenpflege",
    "wof:placetype":"venue"
},
  "geometry": {"coordinates":[10.818135,52.250126],"type":"Point"}
}