{
  "type": "Feature",
  "properties": {
    "iso:country":"DE",
    "sg:address":"Industriestr. 18",
    "sg:city":"Winterbach",
    "sg:postcode":"73650",
    "sg:province":"Baden-W\u00fcrttemberg",
    "wof:name":"Brosch Immobilien Gmbh",
    "wof:placetype":"venue"
},
  "geometry": {"coordinates":[9.475938797,48.8041725159],"type":"Point"}
}