{
  "type": "Feature",
  "properties": {
    "iso:country":"DE",
    "sg:address":"Dr.-Thann-Str. 1a",
    "sg:city":"Kolbermoor",
    "sg:phone":"+49 8061/30049",
    "sg:postcode":"83059",
    "sg:province":"Bayern",
    "wof:name":"Zentraleinkauf Baustoff- Handel S\u00fcd Gmbh",
    "wof:placetype":"venue"
},
  "geometry": {"coordinates":[12.041546,47.83564],"type":"Point"}
}