{
  "type": "Feature",
  "properties": {
    "iso:country":"DE",
    "sg:address":"Glemsstr. 36",
    "sg:city":"Markgr\u00f6ningen",
    "sg:phone":"+49 4971/477425",
    "sg:postcode":"71706",
    "sg:province":"Baden-W\u00fcrttemberg",
    "wof:name":"Domroes Druck Gmbh",
    "wof:placetype":"venue"
},
  "geometry": {"coordinates":[9.0542945862,48.9368019104],"type":"Point"}
}