{
  "type": "Feature",
  "properties": {
    "iso:country":"DE",
    "sg:address":"Kanalstr. 20-24",
    "sg:city":"Velten",
    "sg:phone":"+49 3304/500122",
    "sg:postcode":"16727",
    "sg:province":"Brandenburg",
    "wof:name":"Teutonia Hochbau Gmbh",
    "wof:placetype":"venue"
},
  "geometry": {"coordinates":[13.196727,52.679245],"type":"Point"}
}