{
  "type": "Feature",
  "properties": {
    "iso:country":"DE",
    "sg:address":"Grotrian-Steinweg-Stra\u00dfe 4a",
    "sg:city":"Braunschweig",
    "sg:phone":"+49 531/310120",
    "sg:postcode":"38112",
    "sg:province":"Niedersachsen",
    "wof:name":"Herbst F\u00f6rder- Und Hebetechnik Gmbh",
    "wof:placetype":"venue"
},
  "geometry": {"coordinates":[10.4954481125,52.3181762695],"type":"Point"}
}