{
  "type": "Feature",
  "properties": {
    "iso:country":"DE",
    "sg:address":"Daimlerstr. 5",
    "sg:city":"Aspach",
    "sg:phone":"+49 7191/20083",
    "sg:postcode":"71546",
    "sg:province":"Baden-W\u00fcrttemberg",
    "wof:name":"Altmann Gmbh",
    "wof:placetype":"venue"
},
  "geometry": {"coordinates":[9.387988,48.972473],"type":"Point"}
}