{
  "type": "Feature",
  "properties": {
    "iso:country":"DE",
    "sg:address":"Bahnhofstr. 25 a",
    "sg:city":"Schwalmtal",
    "sg:phone":"+49 2163/948990",
    "sg:postcode":"41366",
    "sg:province":"Nordrhein-Westfalen",
    "wof:name":"Kraftverkehr Schwalmtal Von Der Forst Gmbh & Co. Kg",
    "wof:placetype":"venue"
},
  "geometry": {"coordinates":[6.272776,51.216217],"type":"Point"}
}