{
  "type": "Feature",
  "properties": {
    "iso:country":"DE",
    "sg:address":"Blumenstr. 33",
    "sg:city":"V\u00f6lklingen",
    "sg:phone":"+49 6898/83930",
    "sg:postcode":"66333",
    "sg:province":"Saarland",
    "wof:name":"Karin Mehn-gelmedien",
    "wof:placetype":"venue"
},
  "geometry": {"coordinates":[6.85701,49.256748],"type":"Point"}
}