{
  "type": "Feature",
  "properties": {
    "iso:country":"DE",
    "sg:address":"Leipziger Str. 25a",
    "sg:city":"Zwickau",
    "sg:phone":"+49 375/23289",
    "sg:postcode":"08056",
    "sg:province":"Sachsen",
    "wof:name":"Trend Videothek Und Copy-shop",
    "wof:placetype":"venue"
},
  "geometry": {"coordinates":[12.4907503128,50.7089691162],"type":"Point"}
}