{
  "type": "Feature",
  "properties": {
    "iso:country":"DE",
    "sg:address":"Stahlstr. 45 a",
    "sg:city":"Wiefelstede",
    "sg:phone":"+49 4402/6140",
    "sg:postcode":"26215",
    "sg:province":"Niedersachsen",
    "wof:name":"Cbs Compound Building Systems Gmbh",
    "wof:placetype":"venue"
},
  "geometry": {"coordinates":[8.1199989319,53.2419776917],"type":"Point"}
}