{
  "type": "Feature",
  "properties": {
    "iso:country":"DE",
    "sg:address":"Feldstr. 25",
    "sg:city":"Danndorf",
    "sg:phone":"+49 5364/1300",
    "sg:postcode":"38461",
    "sg:province":"Niedersachsen",
    "wof:name":"Seegastst\u00e4tte Agv Vorsfelde",
    "wof:placetype":"venue"
},
  "geometry": {"coordinates":[10.9223299026,52.4232254028],"type":"Point"}
}