{
  "type": "Feature",
  "properties": {
    "iso:country":"DE",
    "sg:address":"An den K\u00e4mpen 56",
    "sg:city":"Bad Zwischenahn",
    "sg:phone":"+49 4403/6070",
    "sg:postcode":"26160",
    "sg:province":"Niedersachsen",
    "wof:name":"Erwin Janssen Beteiligungs- Und Verwaltungs Gmbh",
    "wof:placetype":"venue"
},
  "geometry": {"coordinates":[8.0011672974,53.1702919006],"type":"Point"}
}