{
  "type": "Feature",
  "properties": {
    "iso:country":"DE",
    "sg:address":"Lange Str. 59",
    "sg:city":"Springe",
    "sg:phone":"+49 5044/98127",
    "sg:postcode":"31832",
    "sg:province":"Niedersachsen",
    "wof:name":"H. Rollwage",
    "wof:placetype":"venue"
},
  "geometry": {"coordinates":[9.55567,52.207417],"type":"Point"}
}