{
  "type": "Feature",
  "properties": {
    "iso:country":"DE",
    "sg:address":"Amtshausstr. 3",
    "sg:city":"Herford",
    "sg:postcode":"32051",
    "sg:province":"Nordrhein-Westfalen",
    "wof:name":"Die Chance Ggmbh",
    "wof:placetype":"venue"
},
  "geometry": {"coordinates":[8.661101,52.115936],"type":"Point"}
}