{
  "type": "Feature",
  "properties": {
    "iso:country":"DE",
    "sg:address":"Marksburgstr. 37",
    "sg:city":"Berlin",
    "sg:phone":"+49 30/5099644",
    "sg:postcode":"10318",
    "sg:province":"Berlin",
    "wof:name":"Marksburg-apotheke Inh. Kirsten Wieker",
    "wof:placetype":"venue"
},
  "geometry": {"coordinates":[13.523974,52.487076],"type":"Point"}
}