{
  "type": "Feature",
  "properties": {
    "iso:country":"DE",
    "sg:address":"Wandsbeker Chaussee 34-36",
    "sg:city":"Hamburg",
    "sg:phone":"+49 40/2514651",
    "sg:postcode":"22089",
    "sg:province":"Hamburg",
    "wof:name":"Convent Verlag Gmbh",
    "wof:placetype":"venue"
},
  "geometry": {"coordinates":[10.0371446609,53.5652885437],"type":"Point"}
}