{
  "type": "Feature",
  "properties": {
    "iso:country":"DE",
    "sg:address":"Hohenlindener Str 12",
    "sg:city":"Feldkirchen",
    "sg:phone":"+49 89/909973",
    "sg:postcode":"85622",
    "sg:province":"Bayern",
    "wof:name":"Raiffeisenbank Feldkirchen Bei M\u00fcnc",
    "wof:placetype":"venue"
},
  "geometry": {"coordinates":[11.732509,48.147358],"type":"Point"}
}