{
  "type": "Feature",
  "properties": {
    "iso:country":"DE",
    "sg:address":"Mozartstr. 4",
    "sg:city":"Schwaikheim",
    "sg:phone":"+49 7195/969039",
    "sg:postcode":"71409",
    "sg:province":"Baden-W\u00fcrttemberg",
    "wof:name":"Werner Haag",
    "wof:placetype":"venue"
},
  "geometry": {"coordinates":[9.3571987152,48.8704681396],"type":"Point"}
}