{
  "type": "Feature",
  "properties": {
    "iso:country":"DE",
    "sg:address":"Romualdstr 82a",
    "sg:city":"Ochsenhausen",
    "sg:phone":"+49 7352/202970",
    "sg:postcode":"88416",
    "sg:province":"Baden-W\u00fcrttemberg",
    "wof:name":"Hawacast Gmbh Kunststofftechnik",
    "wof:placetype":"venue"
},
  "geometry": {"coordinates":[9.938592,48.069756],"type":"Point"}
}