{
  "type": "Feature",
  "properties": {
    "iso:country":"DE",
    "sg:address":"Grenzwaldstr. 15 a",
    "sg:city":"Nettetal",
    "sg:phone":"+49 2157/3575",
    "sg:postcode":"41334",
    "sg:province":"Nordrhein-Westfalen",
    "wof:name":"Corso-film-casino",
    "wof:placetype":"venue"
},
  "geometry": {"coordinates":[6.195452,51.31078],"type":"Point"}
}