{
  "type": "Feature",
  "properties": {
    "iso:country":"DE",
    "sg:address":"Ortsstr. 10",
    "sg:city":"Ebermannsdorf",
    "sg:phone":"+49 9438/4291",
    "sg:postcode":"92263",
    "sg:province":"Bayern",
    "wof:name":"Franz Brickl Bildhauer",
    "wof:placetype":"venue"
},
  "geometry": {"coordinates":[12.027824,49.37196],"type":"Point"}
}