{
  "type": "Feature",
  "properties": {
    "iso:country":"DE",
    "sg:address":"Sleidanusstr. 10",
    "sg:city":"Schleiden",
    "sg:phone":"+49 2445/5382",
    "sg:postcode":"53937",
    "sg:province":"Nordrhein-Westfalen",
    "wof:name":"Restaurant Schlo\u00df-sch\u00e4nke",
    "wof:placetype":"venue"
},
  "geometry": {"coordinates":[6.4751081467,50.5281715393],"type":"Point"}
}