{
  "type": "Feature",
  "properties": {
    "iso:country":"DE",
    "sg:address":"Hengtestr. 23",
    "sg:city":"Coesfeld",
    "sg:phone":"+49 2541/980990",
    "sg:postcode":"48653",
    "sg:province":"Nordrhein-Westfalen",
    "wof:name":"Karl Brockmann Architekt",
    "wof:placetype":"venue"
},
  "geometry": {"coordinates":[7.159337,51.946873],"type":"Point"}
}