{
  "type": "Feature",
  "properties": {
    "iso:country":"DE",
    "sg:address":"Goldenstedter Str. 35",
    "sg:city":"Visbek",
    "sg:phone":"+49 4445/7523",
    "sg:postcode":"49429",
    "sg:province":"Niedersachsen",
    "wof:name":"Diersen Metallbau Gmbh",
    "wof:placetype":"venue"
},
  "geometry": {"coordinates":[8.318054,52.83345],"type":"Point"}
}