{
  "type": "Feature",
  "properties": {
    "iso:country":"DE",
    "sg:address":"Industriestr. 5",
    "sg:city":"Wasbek",
    "sg:postcode":"24647",
    "sg:province":"Schleswig-Holstein",
    "wof:name":"Was Beteiligungs Gmbh",
    "wof:placetype":"venue"
},
  "geometry": {"coordinates":[9.914602,54.073788],"type":"Point"}
}