{
  "type": "Feature",
  "properties": {
    "iso:country":"DE",
    "sg:address":"Kiefernweg 15",
    "sg:city":"Eitorf",
    "sg:phone":"+49 2243/3244",
    "sg:postcode":"53783",
    "sg:province":"Nordrhein-Westfalen",
    "wof:name":"G\u00fcnter R\u00fcbcke Gmbh",
    "wof:placetype":"venue"
},
  "geometry": {"coordinates":[7.460162,50.768295],"type":"Point"}
}