{
  "type": "Feature",
  "properties": {
    "iso:country":"DE",
    "sg:address":"Berghausen 1",
    "sg:city":"Remscheid",
    "sg:phone":"+49 2191/591080",
    "sg:postcode":"42859",
    "sg:province":"Nordrhein-Westfalen",
    "wof:name":"Profi.l Gesellschaft F\u00fcr Management Und Logistikberatung Gmbh",
    "wof:placetype":"venue"
},
  "geometry": {"coordinates":[7.216195,51.167854],"type":"Point"}
}