{
  "type": "Feature",
  "properties": {
    "iso:country":"DE",
    "sg:address":"Hermannstr. 4",
    "sg:city":"Eisenach",
    "sg:phone":"+49 3691/71356",
    "sg:postcode":"99817",
    "sg:province":"Th\u00fcringen",
    "wof:name":"Horst K\u00f6hler",
    "wof:placetype":"venue"
},
  "geometry": {"coordinates":[10.33868,50.977657],"type":"Point"}
}