{
  "type": "Feature",
  "properties": {
    "iso:country":"DE",
    "sg:address":"Priesterweg 55",
    "sg:city":"Zepernick",
    "sg:phone":"+49 30/9442106",
    "sg:postcode":"16341",
    "sg:province":"Brandenburg",
    "wof:name":"Heinz Kant",
    "wof:placetype":"venue"
},
  "geometry": {"coordinates":[13.53415,52.664978],"type":"Point"}
}