{
  "type": "Feature",
  "properties": {
    "iso:country":"DE",
    "sg:address":"Wohnsdorf 10",
    "sg:city":"Hollfeld",
    "sg:phone":"+49 9274/1774",
    "sg:postcode":"96142",
    "sg:province":"Bayern",
    "wof:name":"G. Und A. Seeber",
    "wof:placetype":"venue"
},
  "geometry": {"coordinates":[11.3485679626,49.9172439575],"type":"Point"}
}