{
  "type": "Feature",
  "properties": {
    "iso:country":"DE",
    "sg:address":"Brombeerweg 43",
    "sg:city":"Hamburg",
    "sg:phone":"+49 40/590329",
    "sg:postcode":"22339",
    "sg:province":"Hamburg",
    "wof:name":"Gehlsen Holzhandel Gmbh & Co. Kg",
    "wof:placetype":"venue"
},
  "geometry": {"coordinates":[10.0296497345,53.6310081482],"type":"Point"}
}