{
  "type": "Feature",
  "properties": {
    "iso:country":"DE",
    "sg:address":"An St. Sebastian 33-35",
    "sg:city":"Nettetal",
    "sg:phone":"+49 2153/5211",
    "sg:postcode":"41334",
    "sg:province":"Nordrhein-Westfalen",
    "wof:name":"Katholisches Pfarramt St. Sebastian",
    "wof:placetype":"venue"
},
  "geometry": {"coordinates":[6.272960186,51.3083763123],"type":"Point"}
}