{
  "type": "Feature",
  "properties": {
    "iso:country":"DE",
    "sg:address":"Bochumer Str. 52",
    "sg:city":"Leipzig",
    "sg:phone":"+49 341/6019404",
    "sg:postcode":"04357",
    "sg:province":"Sachsen",
    "wof:name":"Detlef Schatte",
    "wof:placetype":"venue"
},
  "geometry": {"coordinates":[12.402799,51.3759],"type":"Point"}
}