{
  "type": "Feature",
  "properties": {
    "iso:country":"DE",
    "sg:address":"Schemmener Str. 28-30",
    "sg:city":"Gummersbach",
    "sg:phone":"+49 2261/81080",
    "sg:postcode":"51647",
    "sg:province":"Nordrhein-Westfalen",
    "wof:name":"M\u00f6ller Schaltger\u00e4te Gmbh",
    "wof:placetype":"venue"
},
  "geometry": {"coordinates":[7.5751152039,51.0509910583],"type":"Point"}
}