{
  "type": "Feature",
  "properties": {
    "iso:country":"DE",
    "sg:address":"Osianderstr. 17",
    "sg:city":"Gunzenhausen",
    "sg:phone":"+49 9831/2085",
    "sg:postcode":"91710",
    "sg:province":"Bayern",
    "wof:name":"Karl Hofer",
    "wof:placetype":"venue"
},
  "geometry": {"coordinates":[10.753304,49.117489],"type":"Point"}
}