{
  "type": "Feature",
  "properties": {
    "iso:country":"DE",
    "sg:address":"Hauptstr. 55",
    "sg:city":"Pl\u00fcderhausen",
    "sg:phone":"+49 7181/81624",
    "sg:postcode":"73655",
    "sg:province":"Baden-W\u00fcrttemberg",
    "wof:name":"Heinz Breitenb\u00fccher",
    "wof:placetype":"venue"
},
  "geometry": {"coordinates":[9.599059,48.795467],"type":"Point"}
}