{
  "type": "Feature",
  "properties": {
    "iso:country":"DE",
    "sg:address":"Dillinger Str. 4",
    "sg:city":"G\u00fcnzburg",
    "sg:phone":"+49 8221/5317",
    "sg:postcode":"89312",
    "sg:province":"Bayern",
    "wof:name":"Kaufhaus Schiele Inh. Hans Baur",
    "wof:placetype":"venue"
},
  "geometry": {"coordinates":[10.279419,48.456913],"type":"Point"}
}