{
  "type": "Feature",
  "properties": {
    "iso:country":"DE",
    "sg:address":"Rauentaler Str. 23",
    "sg:city":"Rastatt",
    "sg:postcode":"76437",
    "sg:province":"Baden-W\u00fcrttemberg",
    "wof:name":"J. E. Bauprojekt Gmbh",
    "wof:placetype":"venue"
},
  "geometry": {"coordinates":[8.2211465836,48.8608398438],"type":"Point"}
}