{
  "type": "Feature",
  "properties": {
    "iso:country":"DE",
    "sg:address":"Feuerbacher Heide 38-42",
    "sg:city":"Stuttgart",
    "sg:phone":"+49 711/227420",
    "sg:postcode":"70192",
    "sg:province":"Baden-W\u00fcrttemberg",
    "wof:name":"Fachhochschule F\u00fcr Bibliothekswesen Stuttgart",
    "wof:placetype":"venue"
},
  "geometry": {"coordinates":[9.154853,48.789921],"type":"Point"}
}