{
  "type": "Feature",
  "properties": {
    "iso:country":"DE",
    "sg:address":"Schefflenzstr. 15",
    "sg:city":"Gundelsheim",
    "sg:postcode":"74831",
    "sg:province":"Baden-W\u00fcrttemberg",
    "wof:name":"Strecker Verm\u00f6gens- Verwaltungs Gmbh & Co. Kg",
    "wof:placetype":"venue"
},
  "geometry": {"coordinates":[9.2264003754,49.2859802246],"type":"Point"}
}