{
  "type": "Feature",
  "properties": {
    "iso:country":"DE",
    "sg:address":"Edisonstr. 2",
    "sg:city":"Kempten",
    "sg:phone":"+49 831/23291",
    "sg:postcode":"87437",
    "sg:province":"Bayern",
    "wof:name":"H\u00fcbner Und Kollegen Patentanw\u00e4lte",
    "wof:placetype":"venue"
},
  "geometry": {"coordinates":[10.3239841461,47.7467918396],"type":"Point"}
}