{
  "type": "Feature",
  "properties": {
    "iso:country":"DE",
    "sg:address":"K\u00f6nigseer Str. 19",
    "sg:city":"Bad Blankenburg",
    "sg:phone":"+49 36741/2754",
    "sg:postcode":"07422",
    "sg:province":"Th\u00fcringen",
    "wof:name":"Paul Kohlbach",
    "wof:placetype":"venue"
},
  "geometry": {"coordinates":[11.242772,50.689053],"type":"Point"}
}