{
  "type": "Feature",
  "properties": {
    "iso:country":"DE",
    "sg:address":"Trotzenburg 8",
    "sg:city":"R\u00f6dinghausen",
    "sg:phone":"+49 5226/5278",
    "sg:postcode":"32289",
    "sg:province":"Nordrhein-Westfalen",
    "wof:name":"Baugesch\u00e4ft Schmidt Gmbh",
    "wof:placetype":"venue"
},
  "geometry": {"coordinates":[8.500289917,52.214931488],"type":"Point"}
}