{
  "type": "Feature",
  "properties": {
    "iso:country":"DE",
    "sg:address":"H\u00e4g 2",
    "sg:city":"H\u00e4g-Ehrsberg",
    "sg:phone":"+49 7625/609",
    "sg:postcode":"79685",
    "sg:province":"Baden-W\u00fcrttemberg",
    "wof:name":"Hermann Faller",
    "wof:placetype":"venue"
},
  "geometry": {"coordinates":[7.9226269722,47.7320404053],"type":"Point"}
}