{
  "type": "Feature",
  "properties": {
    "iso:country":"DE",
    "sg:address":"Hauptstrasse",
    "sg:city":"Dorf Tirol",
    "sg:phone":"+49 4739/23562",
    "sg:postcode":"39019",
    "wof:name":"Egger Erich Dekorative Malerei",
    "wof:placetype":"venue"
},
  "geometry": {"coordinates":[10.95928,47.090279],"type":"Point"}
}