{
  "type": "Feature",
  "properties": {
    "iso:country":"DE",
    "sg:address":"Markt 15-17",
    "sg:city":"Straelen",
    "sg:phone":"+49 2834/2040",
    "sg:postcode":"47638",
    "sg:province":"Nordrhein-Westfalen",
    "wof:name":"Otto Syben Inh. Helmut Syben",
    "wof:placetype":"venue"
},
  "geometry": {"coordinates":[6.2660970688,51.4450912476],"type":"Point"}
}