{
  "type": "Feature",
  "properties": {
    "iso:country":"DE",
    "sg:address":"Kuckucksallee 2 a",
    "sg:city":"Pinnow",
    "sg:postcode":"19065",
    "sg:province":"Mecklenburg-Vorpommern",
    "wof:name":"Lebensmittelmarkt Wandschneider Gmbh",
    "wof:placetype":"venue"
},
  "geometry": {"coordinates":[11.5564613342,53.601348877],"type":"Point"}
}