{
  "type": "Feature",
  "properties": {
    "iso:country":"DE",
    "sg:address":"Sedanstr. 1",
    "sg:city":"Lindenberg",
    "sg:phone":"+49 8381/92290",
    "sg:postcode":"88161",
    "sg:province":"Bayern",
    "wof:name":"Hermann Liebhard Steuerberater",
    "wof:placetype":"venue"
},
  "geometry": {"coordinates":[9.8865022659,47.6016082764],"type":"Point"}
}