{
  "type": "Feature",
  "properties": {
    "iso:country":"DE",
    "sg:address":"Bundesautobahntankstelle",
    "sg:city":"Weibersbrunn",
    "sg:postcode":"63879",
    "sg:province":"Bayern",
    "wof:name":"Bat Spessart-nordseite E. K.",
    "wof:placetype":"venue"
},
  "geometry": {"coordinates":[9.3629074097,49.9341125488],"type":"Point"}
}