{
  "type": "Feature",
  "properties": {
    "iso:country":"DE",
    "sg:address":"Gottschedstr. 12",
    "sg:city":"Leipzig",
    "sg:postcode":"04109",
    "sg:province":"Sachsen",
    "wof:name":"Zefa Farbbildagentur",
    "wof:placetype":"venue"
},
  "geometry": {"coordinates":[12.368262291,51.3409156799],"type":"Point"}
}