{
  "type": "Feature",
  "properties": {
    "iso:country":"DE",
    "sg:address":"Birken 1",
    "sg:city":"Lohmar",
    "sg:phone":"+49 2206/1285",
    "sg:postcode":"53797",
    "sg:province":"Nordrhein-Westfalen",
    "wof:name":"Otto Kiel Architekt",
    "wof:placetype":"venue"
},
  "geometry": {"coordinates":[7.24834,50.90163],"type":"Point"}
}