{
  "type": "Feature",
  "properties": {
    "iso:country":"DE",
    "sg:address":"K\u00f6lner Str. 53",
    "sg:city":"Gummersbach",
    "sg:postcode":"51645",
    "sg:province":"Nordrhein-Westfalen",
    "wof:name":"Schuba Automaten Ohg",
    "wof:placetype":"venue"
},
  "geometry": {"coordinates":[7.621702,51.006138],"type":"Point"}
}