{
  "type": "Feature",
  "properties": {
    "iso:country":"DE",
    "sg:address":"Carl-Zeiss-Promenade 10",
    "sg:city":"Jena",
    "sg:phone":"+49 5524/931410",
    "sg:postcode":"07745",
    "sg:province":"Th\u00fcringen",
    "wof:name":"Pr\u00e4weba Gravier- Und Hsc-technik Gmbh",
    "wof:placetype":"venue"
},
  "geometry": {"coordinates":[10.485278,51.634274],"type":"Point"}
}