{
  "type": "Feature",
  "properties": {
    "iso:country":"DE",
    "sg:address":"Bauernstr. 19",
    "sg:city":"Cremlingen",
    "sg:phone":"+49 5306/4636",
    "sg:postcode":"38162",
    "sg:province":"Niedersachsen",
    "wof:name":"Alfred Beckedorf",
    "wof:placetype":"venue"
},
  "geometry": {"coordinates":[10.624522,52.27039],"type":"Point"}
}