{
  "type": "Feature",
  "properties": {
    "iso:country":"DE",
    "sg:address":"Hohenrenner Weg 21",
    "sg:city":"Blomberg",
    "sg:postcode":"32825",
    "sg:province":"Nordrhein-Westfalen",
    "wof:name":"Aldi Gmbh & Co. Kg",
    "wof:placetype":"venue"
},
  "geometry": {"coordinates":[9.0986843109,51.9476394653],"type":"Point"}
}