{
  "type": "Feature",
  "properties": {
    "iso:country":"DE",
    "sg:address":"Friedrichstr. 40",
    "sg:city":"Wiesbaden",
    "sg:phone":"+49 611/305235",
    "sg:postcode":"65185",
    "sg:province":"Hessen",
    "wof:name":"J. G. G\u00e4rtner Inh. Petra Becker",
    "wof:placetype":"venue"
},
  "geometry": {"coordinates":[8.23827,50.080166],"type":"Point"}
}