{
  "type": "Feature",
  "properties": {
    "iso:country":"DE",
    "sg:address":"Volkartstr. 24",
    "sg:city":"M\u00fcnchen",
    "sg:phone":"+49 89/131850",
    "sg:postcode":"80634",
    "sg:province":"Bayern",
    "wof:name":"Pardi",
    "wof:placetype":"venue"
},
  "geometry": {"coordinates":[11.5346460342,48.1555900574],"type":"Point"}
}