{
  "type": "Feature",
  "properties": {
    "iso:country":"DE",
    "sg:address":"Katharinenstr. 68",
    "sg:city":"Mannheim",
    "sg:phone":"+49 621/856424",
    "sg:postcode":"68199",
    "sg:province":"Baden-W\u00fcrttemberg",
    "wof:name":"Heiner Arnold",
    "wof:placetype":"venue"
},
  "geometry": {"coordinates":[8.4873847961,49.4570083618],"type":"Point"}
}