{
  "type": "Feature",
  "properties": {
    "iso:country":"DE",
    "sg:address":"Eichendorffstr. 6",
    "sg:city":"Wolfhagen",
    "sg:phone":"+49 5692/2286",
    "sg:postcode":"34466",
    "sg:province":"Hessen",
    "wof:name":"Helmut Krueger Tischlereibedarfshdl.",
    "wof:placetype":"venue"
},
  "geometry": {"coordinates":[9.178268,51.321167],"type":"Point"}
}