{
  "type": "Feature",
  "properties": {
    "iso:country":"DE",
    "sg:address":"Twellbachtal 111",
    "sg:city":"Bielefeld",
    "sg:phone":"+49 521/101239",
    "sg:postcode":"33619",
    "sg:province":"Nordrhein-Westfalen",
    "wof:name":"Lutz Lang Verwaltungs Gmbh",
    "wof:placetype":"venue"
},
  "geometry": {"coordinates":[8.4626808167,52.0352401733],"type":"Point"}
}