{
  "type": "Feature",
  "properties": {
    "iso:country":"DE",
    "sg:address":"Am Doven 11",
    "sg:city":"Hattingen",
    "sg:phone":"+49 2324/21455",
    "sg:postcode":"45529",
    "sg:province":"Nordrhein-Westfalen",
    "wof:name":"Wilhelm Krunke Gmbh",
    "wof:placetype":"venue"
},
  "geometry": {"coordinates":[7.200014,51.357082],"type":"Point"}
}