{
  "type": "Feature",
  "properties": {
    "iso:country":"DE",
    "sg:address":"Hauptstr. 45",
    "sg:city":"Dierbach",
    "sg:phone":"+49 6340/404",
    "sg:postcode":"76889",
    "sg:province":"Rheinland-Pfalz",
    "wof:name":"Rudolf Huthmacher",
    "wof:placetype":"venue"
},
  "geometry": {"coordinates":[8.0693054199,49.0825424194],"type":"Point"}
}