{
  "type": "Feature",
  "properties": {
    "iso:country":"DE",
    "sg:address":"Oberbieberer Str. 4 b",
    "sg:city":"Neuwied",
    "sg:phone":"+49 2631/58528",
    "sg:postcode":"56567",
    "sg:province":"Rheinland-Pfalz",
    "wof:name":"Dieter K\u00f6hn Architekt Bdb",
    "wof:placetype":"venue"
},
  "geometry": {"coordinates":[7.471278,50.462364],"type":"Point"}
}