{
  "type": "Feature",
  "properties": {
    "iso:country":"DE",
    "sg:address":"Unterdorfstr. 4",
    "sg:city":"Friesenheim",
    "sg:phone":"+49 7821/61271",
    "sg:postcode":"77948",
    "sg:province":"Baden-W\u00fcrttemberg",
    "wof:name":"Franz Silberer",
    "wof:placetype":"venue"
},
  "geometry": {"coordinates":[7.849527,48.382362],"type":"Point"}
}