{
  "type": "Feature",
  "properties": {
    "iso:country":"DE",
    "sg:address":"Faulenbergstr. 1",
    "sg:city":"W\u00fcrzburg",
    "sg:phone":"+49 931/286210",
    "sg:postcode":"97076",
    "sg:province":"Bayern",
    "wof:name":"Mc Donalds Deutschland",
    "wof:placetype":"venue"
},
  "geometry": {"coordinates":[9.9871683121,49.7977714539],"type":"Point"}
}