{
  "type": "Feature",
  "properties": {
    "iso:country":"DE",
    "sg:address":"St.-Bernhard-Platz 2",
    "sg:city":"Kissing",
    "sg:phone":"+49 8233/5792",
    "sg:postcode":"86438",
    "sg:province":"Bayern",
    "wof:name":"Kath. Pfarramt St. Bernhard",
    "wof:placetype":"venue"
},
  "geometry": {"coordinates":[10.9663190842,48.3036727905],"type":"Point"}
}