{
  "type": "Feature",
  "properties": {
    "iso:country":"DE",
    "sg:address":"Sachsendorfer Wiesen 1-2",
    "sg:city":"Cottbus",
    "sg:phone":"+49 35552225463375",
    "sg:postcode":"03048",
    "sg:province":"Brandenburg",
    "wof:name":"Familienkita Cottbus",
    "wof:placetype":"venue"
},
  "geometry": {"coordinates":[14.320978,51.73666],"type":"Point"}
}