{
  "type": "Feature",
  "properties": {
    "iso:country":"DE",
    "sg:address":"Baseler Str. 35",
    "sg:city":"Frankfurt",
    "sg:phone":"+49 69/250256",
    "sg:postcode":"60329",
    "sg:province":"Hessen",
    "wof:name":"Stipo Tabak",
    "wof:placetype":"venue"
},
  "geometry": {"coordinates":[8.6647043228,50.1055641174],"type":"Point"}
}