{
  "type": "Feature",
  "properties": {
    "iso:country":"DE",
    "sg:address":"Heselst\u00fccken 3",
    "sg:city":"Hamburg",
    "sg:postcode":"22453",
    "sg:province":"Hamburg",
    "wof:name":"Paul Kaack & Co. Service Gmbh",
    "wof:placetype":"venue"
},
  "geometry": {"coordinates":[9.999406,53.615654],"type":"Point"}
}