{
  "type": "Feature",
  "properties": {
    "iso:country":"DE",
    "sg:address":"Alte Landstr. 1",
    "sg:city":"Schneverdingen",
    "sg:phone":"+49 5193/7120",
    "sg:postcode":"29640",
    "sg:province":"Niedersachsen",
    "wof:name":"E. St\u00f6lpe",
    "wof:placetype":"venue"
},
  "geometry": {"coordinates":[9.6909580231,53.1118431091],"type":"Point"}
}