{
  "type": "Feature",
  "properties": {
    "iso:country":"DE",
    "sg:address":"Ziethenstr. 15",
    "sg:city":"Dortmund",
    "sg:phone":"+49 231/436075",
    "sg:postcode":"44141",
    "sg:province":"Nordrhein-Westfalen",
    "wof:name":"Manfred Schr\u00f6der",
    "wof:placetype":"venue"
},
  "geometry": {"coordinates":[7.4839491844,51.4983482361],"type":"Point"}
}