{
  "type": "Feature",
  "properties": {
    "iso:country":"DE",
    "sg:address":"Selenter Weg 4",
    "sg:city":"Martensrade",
    "sg:postcode":"24238",
    "sg:province":"Schleswig-Holstein",
    "wof:name":"Pour Le Merite Verlag F\u00fcr Milit\u00e4rgeschichte Zw.niederl.",
    "wof:placetype":"venue"
},
  "geometry": {"coordinates":[10.3945741653,54.2797470093],"type":"Point"}
}