{
  "type": "Feature",
  "properties": {
    "iso:country":"DE",
    "sg:address":"Kufsteiner Str. 57",
    "sg:city":"Rosenheim",
    "sg:phone":"+49 8031/13256",
    "sg:postcode":"83022",
    "sg:province":"Bayern",
    "wof:name":"Aral Ag",
    "wof:placetype":"venue"
},
  "geometry": {"coordinates":[12.1276874542,47.8490943909],"type":"Point"}
}