{
  "type": "Feature",
  "properties": {
    "iso:country":"DE",
    "sg:address":"Im Langental 12",
    "sg:city":"Neunkirchen",
    "sg:phone":"+49 4968/2194060",
    "sg:postcode":"66539",
    "sg:province":"Saarland",
    "wof:name":"Tectro Kunststofftechnik Gmbh",
    "wof:placetype":"venue"
},
  "geometry": {"coordinates":[7.2395048141,49.3483657837],"type":"Point"}
}