{
  "type": "Feature",
  "properties": {
    "iso:country":"DE",
    "sg:address":"Maa\u00dfstr. 30",
    "sg:city":"Heidelberg",
    "sg:phone":"+49 6221/83220",
    "sg:postcode":"69123",
    "sg:province":"Baden-W\u00fcrttemberg",
    "wof:name":"Gfn Training Gmbh",
    "wof:placetype":"venue"
},
  "geometry": {"coordinates":[8.6397647858,49.4208564758],"type":"Point"}
}