{
  "type": "Feature",
  "properties": {
    "iso:country":"DE",
    "sg:address":"Am Markt 7",
    "sg:city":"Kremmen",
    "sg:phone":"+49 33055/7780",
    "sg:postcode":"16766",
    "sg:province":"Brandenburg",
    "wof:name":"Adler-apotheke E. K.",
    "wof:placetype":"venue"
},
  "geometry": {"coordinates":[13.024962,52.760468],"type":"Point"}
}