{
  "type": "Feature",
  "properties": {
    "iso:country":"DE",
    "sg:address":"Erlengrund 28",
    "sg:city":"Bad Doberan",
    "sg:phone":"+49 38203/63698",
    "sg:postcode":"18209",
    "sg:province":"Mecklenburg-Vorpommern",
    "wof:name":"Bauservice G\u00fcnter Kath Gmbh",
    "wof:placetype":"venue"
},
  "geometry": {"coordinates":[11.917789,54.093109],"type":"Point"}
}