{
  "type": "Feature",
  "properties": {
    "iso:country":"DE",
    "sg:address":"Im Leimenfeld 13",
    "sg:city":"Ringsheim",
    "sg:phone":"+49 7822/44197",
    "sg:postcode":"77975",
    "sg:province":"Baden-W\u00fcrttemberg",
    "wof:name":"Mbd-superbike Bikini For Naked Bikes And More",
    "wof:placetype":"venue"
},
  "geometry": {"coordinates":[7.7701158524,48.2474632263],"type":"Point"}
}