{
  "type": "Feature",
  "properties": {
    "iso:country":"DE",
    "sg:address":"Max-Planck-Str 23",
    "sg:city":"Brehna",
    "sg:phone":"+49 34954/48778",
    "sg:postcode":"06796",
    "sg:province":"Sachsen-Anhalt",
    "wof:name":"Aw Technic Gesellschaft F\u00fcr Spezialfahrzeugbau Mbh",
    "wof:placetype":"venue"
},
  "geometry": {"coordinates":[12.1946306229,51.5460014343],"type":"Point"}
}