{
  "type": "Feature",
  "properties": {
    "iso:country":"DE",
    "sg:address":"Osnabr\u00fccker Str. 2",
    "sg:city":"Barnstorf",
    "sg:phone":"+49 5442/991979",
    "sg:postcode":"49406",
    "sg:province":"Niedersachsen",
    "wof:name":"Eiscafe Franco",
    "wof:placetype":"venue"
},
  "geometry": {"coordinates":[8.503182,52.710148],"type":"Point"}
}