{
  "type": "Feature",
  "properties": {
    "iso:country":"DE",
    "sg:address":"Gutleutweg 10",
    "sg:city":"Alpirsbach",
    "sg:phone":"+49 7444/3136",
    "sg:postcode":"72275",
    "sg:province":"Baden-W\u00fcrttemberg",
    "wof:name":"E Und B Erddeponie In",
    "wof:placetype":"venue"
},
  "geometry": {"coordinates":[8.402957,48.343807],"type":"Point"}
}