{
  "type": "Feature",
  "properties": {
    "iso:country":"DE",
    "sg:address":"Flurstr. 8",
    "sg:city":"Viechtach",
    "sg:phone":"+49 9942/466",
    "sg:postcode":"94234",
    "sg:province":"Bayern",
    "wof:name":"J. Traimer & Brunhofer",
    "wof:placetype":"venue"
},
  "geometry": {"coordinates":[12.887439,49.075241],"type":"Point"}
}