{
  "type": "Feature",
  "properties": {
    "iso:country":"DE",
    "sg:address":"Schubertstr. 32",
    "sg:city":"Neu-Anspach",
    "sg:phone":"+49 6081/8830",
    "sg:postcode":"61267",
    "sg:province":"Hessen",
    "wof:name":"Apotheke Am \u00c4rztehaus Ferdinand Gabriel",
    "wof:placetype":"venue"
},
  "geometry": {"coordinates":[8.508931,50.295528],"type":"Point"}
}