{
  "type": "Feature",
  "properties": {
    "iso:country":"DE",
    "sg:address":"Johann-Zinken-Str. 1",
    "sg:city":"Seesen",
    "sg:phone":"+49 5381/70041",
    "sg:postcode":"38723",
    "sg:province":"Niedersachsen",
    "wof:name":"Ohse Design Inh. Gisela Ohse",
    "wof:placetype":"venue"
},
  "geometry": {"coordinates":[10.1570205688,51.8793563843],"type":"Point"}
}