{
  "type": "Feature",
  "properties": {
    "iso:country":"DE",
    "sg:address":"Kapellenstr. 94",
    "sg:city":"Baesweiler",
    "sg:phone":"+49 2401/1262",
    "sg:postcode":"52499",
    "sg:province":"Nordrhein-Westfalen",
    "wof:name":"L. Fesenberg",
    "wof:placetype":"venue"
},
  "geometry": {"coordinates":[6.178351,50.902515],"type":"Point"}
}