{
  "type": "Feature",
  "properties": {
    "iso:country":"DE",
    "sg:address":"Villenweg 13",
    "sg:city":"Kronshagen",
    "sg:phone":"+49 431/580707",
    "sg:postcode":"24119",
    "sg:province":"Schleswig-Holstein",
    "wof:name":"Zeutec Opto-elektronik Gmbh",
    "wof:placetype":"venue"
},
  "geometry": {"coordinates":[10.088882,54.331764],"type":"Point"}
}