{
  "type": "Feature",
  "properties": {
    "iso:country":"DE",
    "sg:address":"Freudenst\u00e4dter Str. 40",
    "sg:city":"Baiersbronn",
    "sg:phone":"+49 7442/2214",
    "sg:postcode":"72270",
    "sg:province":"Baden-W\u00fcrttemberg",
    "wof:name":"Deutsche Bahn Ag",
    "wof:placetype":"venue"
},
  "geometry": {"coordinates":[8.3723096848,48.5041542053],"type":"Point"}
}