{
  "type": "Feature",
  "properties": {
    "iso:country":"DE",
    "sg:address":"Am Brink 24a",
    "sg:city":"Grambek",
    "sg:phone":"+49 4542/843936",
    "sg:postcode":"23883",
    "sg:province":"Schleswig-Holstein",
    "wof:name":"W\u00fcrttembergische Versicherung Andreas Klippel",
    "wof:placetype":"venue"
},
  "geometry": {"coordinates":[10.6803388596,53.5702056885],"type":"Point"}
}