{
  "type": "Feature",
  "properties": {
    "iso:country":"DE",
    "sg:address":"Hauptstr. 204",
    "sg:city":"Ostrhauderfehn",
    "sg:postcode":"26842",
    "sg:province":"Niedersachsen",
    "wof:name":"Igje Ostrhauderfehn E.v. / Das Fetenteam",
    "wof:placetype":"venue"
},
  "geometry": {"coordinates":[7.6362,53.14011],"type":"Point"}
}