{
  "type": "Feature",
  "properties": {
    "iso:country":"DE",
    "sg:address":"Sch\u00e4ferstr. 5",
    "sg:city":"Peine",
    "sg:postcode":"31224",
    "sg:province":"Niedersachsen",
    "wof:name":"Henniges Beteiligungs Gmbh",
    "wof:placetype":"venue"
},
  "geometry": {"coordinates":[10.248621,52.319454],"type":"Point"}
}