{
  "type": "Feature",
  "properties": {
    "iso:country":"DE",
    "sg:address":"Gartenstr. 27",
    "sg:city":"Rudolstadt",
    "sg:phone":"+49 3672/422121",
    "sg:postcode":"07407",
    "sg:province":"Th\u00fcringen",
    "wof:name":"Th\u00fcringer Technikhandel Gmbh",
    "wof:placetype":"venue"
},
  "geometry": {"coordinates":[11.3485393524,50.7203216553],"type":"Point"}
}