{
  "type": "Feature",
  "properties": {
    "iso:country":"DE",
    "sg:address":"Salzhof 7 b",
    "sg:city":"Berlin",
    "sg:phone":"+49 30/78702864",
    "sg:postcode":"13599",
    "sg:province":"Berlin",
    "wof:name":"Has Import Und Export Gmbh",
    "wof:placetype":"venue"
},
  "geometry": {"coordinates":[13.226064682,52.552028656],"type":"Point"}
}