{
  "type": "Feature",
  "properties": {
    "iso:country":"DE",
    "sg:address":"Hirtenstaller Weg 37b",
    "sg:city":"B\u00fcsum",
    "sg:phone":"+49 4321",
    "sg:postcode":"25761",
    "sg:province":"Schleswig-Holstein",
    "wof:name":"Ferienwohnung Voigt",
    "wof:placetype":"venue"
},
  "geometry": {"coordinates":[8.8589143753,54.1413803101],"type":"Point"}
}