{
  "type": "Feature",
  "properties": {
    "iso:country":"DE",
    "sg:address":"Essinger Str. 31",
    "sg:city":"Offenbach",
    "sg:phone":"+49 6348/302",
    "sg:postcode":"76877",
    "sg:province":"Rheinland-Pfalz",
    "wof:name":"K. Flick",
    "wof:placetype":"venue"
},
  "geometry": {"coordinates":[8.189827919,49.1963424683],"type":"Point"}
}