{
  "type": "Feature",
  "properties": {
    "iso:country":"DE",
    "sg:address":"F\u00fcrstenrieder Str. 95",
    "sg:city":"M\u00fcnchen",
    "sg:phone":"+49 89/569186",
    "sg:postcode":"80686",
    "sg:province":"Bayern",
    "wof:name":"J. Und U. Kumpf",
    "wof:placetype":"venue"
},
  "geometry": {"coordinates":[11.503145,48.13203],"type":"Point"}
}