{
  "type": "Feature",
  "properties": {
    "iso:country":"DE",
    "sg:address":"Ostsiedlung 13",
    "sg:city":"Delitzsch",
    "sg:phone":"+49 34202/53676",
    "sg:postcode":"04509",
    "sg:province":"Sachsen",
    "wof:name":"Karl-heinz G\u00f6dicke",
    "wof:placetype":"venue"
},
  "geometry": {"coordinates":[12.3562583923,51.5299949646],"type":"Point"}
}