{
  "type": "Feature",
  "properties": {
    "iso:country":"DE",
    "sg:address":"Am Pfarrgarten 8",
    "sg:city":"Unterwachingen",
    "sg:phone":"+49 7393/1614",
    "sg:postcode":"89597",
    "sg:province":"Baden-W\u00fcrttemberg",
    "wof:name":"Alois A\u00dffalg",
    "wof:placetype":"venue"
},
  "geometry": {"coordinates":[9.644583,48.20121],"type":"Point"}
}