{
  "type": "Feature",
  "properties": {
    "iso:country":"DE",
    "sg:address":"Annaberger Str. 67",
    "sg:city":"Raschau",
    "sg:phone":"+49 3774/81322",
    "sg:postcode":"08352",
    "sg:province":"Sachsen",
    "wof:name":"Manfred Schubert",
    "wof:placetype":"venue"
},
  "geometry": {"coordinates":[12.831797,50.531826],"type":"Point"}
}