{
  "type": "Feature",
  "properties": {
    "iso:country":"DE",
    "sg:address":"Guntersh\u00e4userstra\u00dfe 54",
    "sg:city":"Baunatal",
    "sg:phone":"+49 561/4910956",
    "sg:postcode":"34225",
    "sg:province":"Hessen",
    "wof:name":"Deutche Charts",
    "wof:placetype":"venue"
},
  "geometry": {"coordinates":[9.453444,51.253101],"type":"Point"}
}