{
  "type": "Feature",
  "properties": {
    "iso:country":"DE",
    "sg:address":"Eisenbahnstr. 68",
    "sg:city":"Saarbr\u00fccken",
    "sg:phone":"+49 681/57877",
    "sg:postcode":"66117",
    "sg:province":"Saarland",
    "wof:name":"H. G. A. Hoffmann & Guillaume Arbeitnehmer\u00fcberlassung Gmbh",
    "wof:placetype":"venue"
},
  "geometry": {"coordinates":[6.9897451401,49.2358131409],"type":"Point"}
}