{
  "type": "Feature",
  "properties": {
    "iso:country":"DE",
    "sg:address":"M\u00fclheimer Str. 76",
    "sg:city":"Bergisch Gladbach",
    "sg:postcode":"51469",
    "sg:province":"Nordrhein-Westfalen",
    "wof:name":"Heimtex Fachmarkt Bergisch Gladbach Gmbh",
    "wof:placetype":"venue"
},
  "geometry": {"coordinates":[7.102022171,50.9838600159],"type":"Point"}
}