{
  "type": "Feature",
  "properties": {
    "iso:country":"DE",
    "sg:address":"Schwarzenberger Str. 11",
    "sg:city":"Scheinfeld",
    "sg:phone":"+49 9162/7593",
    "sg:postcode":"91443",
    "sg:province":"Bayern",
    "wof:name":"Paletti",
    "wof:placetype":"venue"
},
  "geometry": {"coordinates":[10.4659938812,49.6665496826],"type":"Point"}
}