{
  "type": "Feature",
  "properties": {
    "iso:country":"DE",
    "sg:address":"Kirchplatz 2",
    "sg:city":"A\u00dfling",
    "sg:phone":"+49 8092/32325",
    "sg:postcode":"85617",
    "sg:province":"Bayern",
    "wof:name":"Raiffeisenbank Eg",
    "wof:placetype":"venue"
},
  "geometry": {"coordinates":[12.006174,47.992867],"type":"Point"}
}