{
  "type": "Feature",
  "properties": {
    "iso:country":"DE",
    "sg:address":"Idsteiner Str. 83 - 87",
    "sg:city":"Taunusstein",
    "sg:phone":"+49 4971/7160060",
    "sg:postcode":"65232",
    "sg:province":"Hessen",
    "wof:name":"Remsdruckerei Sigg, Haertel & Co",
    "wof:placetype":"venue"
},
  "geometry": {"coordinates":[9.7978096008,48.797039032],"type":"Point"}
}