{
  "type": "Feature",
  "properties": {
    "iso:country":"DE",
    "sg:address":"Hildesheimer Str. 264",
    "sg:city":"Hannover",
    "sg:phone":"+49 511/831820",
    "sg:postcode":"30519",
    "sg:province":"Niedersachsen",
    "wof:name":"Restaurant Delphi",
    "wof:placetype":"venue"
},
  "geometry": {"coordinates":[9.7682504654,52.3381309509],"type":"Point"}
}