{
  "type": "Feature",
  "properties": {
    "iso:country":"DE",
    "sg:address":"Mittelpilghausen 30",
    "sg:city":"Solingen",
    "sg:phone":"+49 212/812143",
    "sg:postcode":"42657",
    "sg:province":"Nordrhein-Westfalen",
    "wof:name":"Gustav Krebs",
    "wof:placetype":"venue"
},
  "geometry": {"coordinates":[7.062769,51.159122],"type":"Point"}
}