{
  "type": "Feature",
  "properties": {
    "iso:country":"DE",
    "sg:address":"Ravensberger Str. 6",
    "sg:city":"Versmold",
    "sg:phone":"+49 5423/94930",
    "sg:postcode":"33775",
    "sg:province":"Nordrhein-Westfalen",
    "wof:name":"Tv Koch Siegfried Koch",
    "wof:placetype":"venue"
},
  "geometry": {"coordinates":[8.1557483673,52.0405654907],"type":"Point"}
}