{
  "type": "Feature",
  "properties": {
    "iso:country":"DE",
    "sg:address":"K\u00f6lner Str. 62",
    "sg:city":"Nettetal",
    "sg:phone":"+49 2157/6039",
    "sg:postcode":"41334",
    "sg:province":"Nordrhein-Westfalen",
    "wof:name":"August Gerhards",
    "wof:placetype":"venue"
},
  "geometry": {"coordinates":[6.2040109634,51.311958313],"type":"Point"}
}