{
  "type": "Feature",
  "properties": {
    "iso:country":"DE",
    "sg:address":"H\u00f6fenkamp 5 a",
    "sg:city":"Hamburg",
    "sg:phone":"+49 40/232668",
    "sg:postcode":"22393",
    "sg:province":"Hamburg",
    "wof:name":"Ilse Poggensee Gmbh & Co.",
    "wof:placetype":"venue"
},
  "geometry": {"coordinates":[10.1165075302,53.647102356],"type":"Point"}
}