{
  "type": "Feature",
  "properties": {
    "iso:country":"DE",
    "sg:address":"Sch\u00e4fereiweg 3",
    "sg:city":"Frohburg",
    "sg:phone":"+49 34348/54956",
    "sg:postcode":"04654",
    "sg:province":"Sachsen",
    "wof:name":"Andreas Steigert",
    "wof:placetype":"venue"
},
  "geometry": {"coordinates":[12.563374,51.051388],"type":"Point"}
}