{
  "type": "Feature",
  "properties": {
    "iso:country":"DE",
    "sg:address":"Bahnhofstr. 40",
    "sg:city":"Quickborn",
    "sg:phone":"+49 4106/67715",
    "sg:postcode":"25451",
    "sg:province":"Schleswig-Holstein",
    "wof:name":"Istanbul Kebap",
    "wof:placetype":"venue"
},
  "geometry": {"coordinates":[9.9012441635,53.7307777405],"type":"Point"}
}