{
  "type": "Feature",
  "properties": {
    "iso:country":"DE",
    "sg:address":"An der Vogelrute 32",
    "sg:city":"Euskirchen",
    "sg:phone":"+49 2251/89444",
    "sg:postcode":"53879",
    "sg:province":"Nordrhein-Westfalen",
    "wof:name":"Samland",
    "wof:placetype":"venue"
},
  "geometry": {"coordinates":[6.7971539497,50.6548728943],"type":"Point"}
}