{
  "type": "Feature",
  "properties": {
    "iso:country":"DE",
    "sg:address":"Am Karpfenpfuhl 4",
    "sg:city":"Berlin",
    "sg:phone":"+49 30/8174786",
    "sg:postcode":"14167",
    "sg:province":"Berlin",
    "wof:name":"Dr. Med. Armin Schilling",
    "wof:placetype":"venue"
},
  "geometry": {"coordinates":[13.2848997116,52.431438446],"type":"Point"}
}