{
  "type": "Feature",
  "properties": {
    "iso:country":"DE",
    "sg:address":"Albrecht-D\u00fcrer-Str. 15",
    "sg:city":"Hoyerswerda",
    "sg:postcode":"02977",
    "sg:province":"Sachsen",
    "wof:name":"Krija Allianz Hauptvertretung",
    "wof:placetype":"venue"
},
  "geometry": {"coordinates":[14.2610187531,51.4511795044],"type":"Point"}
}