{
  "type": "Feature",
  "properties": {
    "iso:country":"DE",
    "sg:address":"Herzog-Wilhelm-Str. 1",
    "sg:city":"M\u00fcnchen",
    "sg:phone":"+49 89/2355780",
    "sg:postcode":"80331",
    "sg:province":"Bayern",
    "wof:name":"Hdi Lebensversicherung Ag",
    "wof:placetype":"venue"
},
  "geometry": {"coordinates":[11.5671157837,48.1385765076],"type":"Point"}
}