{
  "type": "Feature",
  "properties": {
    "iso:country":"DE",
    "sg:address":"Dorfstr. 29",
    "sg:city":"Gro\u00df Ziescht",
    "sg:postcode":"15837",
    "sg:province":"Brandenburg",
    "wof:name":"Evangelisches Pfarramt",
    "wof:placetype":"venue"
},
  "geometry": {"coordinates":[13.5029602051,52.0450706482],"type":"Point"}
}