{
  "type": "Feature",
  "properties": {
    "iso:country":"DE",
    "sg:address":"Achauerstrasse 8",
    "sg:city":"Trossingen",
    "sg:phone":"+49 7425/9400813",
    "sg:postcode":"78647",
    "sg:province":"Baden-W\u00fcrttemberg",
    "wof:name":"Ctp-kauer Gmbh Druckformen-service",
    "wof:placetype":"venue"
},
  "geometry": {"coordinates":[8.636331,48.072441],"type":"Point"}
}