{
  "type": "Feature",
  "properties": {
    "iso:country":"DE",
    "sg:address":"Hauptstr. 118",
    "sg:city":"Flonheim",
    "sg:phone":"+49 6734/8718",
    "sg:postcode":"55237",
    "sg:province":"Rheinland-Pfalz",
    "wof:name":"Manfred Becher",
    "wof:placetype":"venue"
},
  "geometry": {"coordinates":[8.0214395523,49.7817306519],"type":"Point"}
}