{
  "type": "Feature",
  "properties": {
    "iso:country":"DE",
    "sg:address":"Landsberger Str. 20",
    "sg:city":"Buchloe",
    "sg:phone":"+49 8241/5920",
    "sg:postcode":"86807",
    "sg:province":"Bayern",
    "wof:name":"Wilfried Kremer Gmbh",
    "wof:placetype":"venue"
},
  "geometry": {"coordinates":[10.732693,48.035938],"type":"Point"}
}