{
  "type": "Feature",
  "properties": {
    "iso:country":"DE",
    "sg:address":"Schulstr. 26",
    "sg:city":"Heideland",
    "sg:postcode":"07613",
    "sg:province":"Th\u00fcringen",
    "wof:name":"Die Nudel Gmbh",
    "wof:placetype":"venue"
},
  "geometry": {"coordinates":[11.907790184,51.0022888184],"type":"Point"}
}