{
  "type": "Feature",
  "properties": {
    "iso:country":"DE",
    "sg:address":"Stahlbergstr. 45",
    "sg:city":"Mainz",
    "sg:phone":"+49 6131/52156",
    "sg:postcode":"55131",
    "sg:province":"Rheinland-Pfalz",
    "wof:name":"Heidi Und G\u00fcnter Kamp",
    "wof:placetype":"venue"
},
  "geometry": {"coordinates":[8.261058,49.99062],"type":"Point"}
}