{
  "type": "Feature",
  "properties": {
    "iso:country":"DE",
    "sg:address":"Dr.-M\u00fcller-Desterro-Str. 12a",
    "sg:city":"Windischholzhausen",
    "sg:phone":"+49 361/413712",
    "sg:postcode":"99102",
    "sg:province":"Th\u00fcringen",
    "wof:name":"Willy Pechtel",
    "wof:placetype":"venue"
},
  "geometry": {"coordinates":[11.093863,50.946289],"type":"Point"}
}