{
  "type": "Feature",
  "properties": {
    "iso:country":"DE",
    "sg:address":"Mittelstr. 29",
    "sg:city":"K\u00f6ln",
    "sg:phone":"+49 221/256402",
    "sg:postcode":"50672",
    "sg:province":"Nordrhein-Westfalen",
    "wof:name":"C. Wa\u00dfer",
    "wof:placetype":"venue"
},
  "geometry": {"coordinates":[6.94154,50.93671],"type":"Point"}
}