{
  "type": "Feature",
  "properties": {
    "iso:country":"DE",
    "sg:address":"Schmiedestr. 10",
    "sg:city":"Elze",
    "sg:phone":"+49 5068/2472",
    "sg:postcode":"31008",
    "sg:province":"Niedersachsen",
    "wof:name":"Ernst Feuerhake",
    "wof:placetype":"venue"
},
  "geometry": {"coordinates":[9.734272,52.121841],"type":"Point"}
}