{
  "type": "Feature",
  "properties": {
    "iso:country":"DE",
    "sg:address":"Am Markt 13",
    "sg:city":"Neustadt",
    "sg:postcode":"23730",
    "sg:province":"Schleswig-Holstein",
    "wof:name":"Holding Kaufhaus Martin Stolz Gmbh & Co. Kg",
    "wof:placetype":"venue"
},
  "geometry": {"coordinates":[10.885068,54.134293],"type":"Point"}
}