{
  "type": "Feature",
  "properties": {
    "iso:country":"DE",
    "sg:address":"Altonaer Str 350",
    "sg:city":"Halstenbek",
    "sg:phone":"+49 4101/38740",
    "sg:postcode":"25469",
    "sg:province":"Schleswig-Holstein",
    "wof:name":"Groth Luftfahrt- Und Systemtechnik Gmbh & Co. Kg",
    "wof:placetype":"venue"
},
  "geometry": {"coordinates":[9.87321,53.626839],"type":"Point"}
}