{
  "type": "Feature",
  "properties": {
    "iso:country":"DE",
    "sg:address":"W\u00f6hlerstr. 11",
    "sg:city":"Freiburg",
    "sg:phone":"+49 761/51420",
    "sg:postcode":"79108",
    "sg:province":"Baden-W\u00fcrttemberg",
    "wof:name":"Fraunhofer-institut F\u00fcr Werkstoffmechanik Iwm",
    "wof:placetype":"venue"
},
  "geometry": {"coordinates":[7.8519620895,48.0335731506],"type":"Point"}
}