{
  "type": "Feature",
  "properties": {
    "iso:country":"DE",
    "sg:address":"Lotharstra\u00dfe 21",
    "sg:city":"Meerbusch",
    "sg:phone":"+49 2150/6892",
    "sg:postcode":"40668",
    "sg:province":"Nordrhein-Westfalen",
    "wof:name":"Brandschutz & Sicherheitstechnik Motes",
    "wof:placetype":"venue"
},
  "geometry": {"coordinates":[6.715857,51.313255],"type":"Point"}
}