{
  "type": "Feature",
  "properties": {
    "iso:country":"DE",
    "sg:address":"Weinstr. 1",
    "sg:city":"Herxheim am Berg",
    "sg:phone":"+49 6353/989100",
    "sg:postcode":"67273",
    "sg:province":"Rheinland-Pfalz",
    "wof:name":"Winzergenossenschaft Herxheim Am Berg Eg",
    "wof:placetype":"venue"
},
  "geometry": {"coordinates":[8.1794500351,49.5083618164],"type":"Point"}
}