{
  "type": "Feature",
  "properties": {
    "iso:country":"DE",
    "sg:address":"Grazer Str. 1",
    "sg:city":"Hohenleipisch",
    "sg:phone":"+49 3533/161220",
    "sg:postcode":"04934",
    "sg:province":"Brandenburg",
    "wof:name":"Carla Throne",
    "wof:placetype":"venue"
},
  "geometry": {"coordinates":[13.5665187836,51.4985733032],"type":"Point"}
}