{
  "type": "Feature",
  "properties": {
    "iso:country":"DE",
    "sg:address":"Heidtorstr. 2",
    "sg:city":"Rehburg-Loccum",
    "sg:phone":"+49 5766/1541",
    "sg:postcode":"31547",
    "sg:province":"Niedersachsen",
    "wof:name":"Golfplatz Rehburg-loccum Verwaltungs Gmbh",
    "wof:placetype":"venue"
},
  "geometry": {"coordinates":[9.2287521362,52.4741401672],"type":"Point"}
}