{
  "type": "Feature",
  "properties": {
    "iso:country":"DE",
    "sg:address":"Am Vosh\u00f6vel 48",
    "sg:city":"Schermbeck",
    "sg:phone":"+49 2856/2373",
    "sg:postcode":"46514",
    "sg:province":"Nordrhein-Westfalen",
    "wof:name":"Josef Gernemann",
    "wof:placetype":"venue"
},
  "geometry": {"coordinates":[6.746093,51.715549],"type":"Point"}
}