{
  "type": "Feature",
  "properties": {
    "iso:country":"DE",
    "sg:address":"Speicherstr. 1",
    "sg:city":"G\u00fcstrow",
    "sg:phone":"+49 3843/682454",
    "sg:postcode":"18273",
    "sg:province":"Mecklenburg-Vorpommern",
    "wof:name":"Video Und Spielpalast Fintzen & Radtke Videopalast",
    "wof:placetype":"venue"
},
  "geometry": {"coordinates":[12.1710100174,53.7999572754],"type":"Point"}
}