{
  "type": "Feature",
  "properties": {
    "iso:country":"DE",
    "sg:address":"Konradstr. 3",
    "sg:city":"K\u00f6ln",
    "sg:phone":"+49 221/418201",
    "sg:postcode":"50937",
    "sg:province":"Nordrhein-Westfalen",
    "wof:name":"M. Bellinghausen Architekt",
    "wof:placetype":"venue"
},
  "geometry": {"coordinates":[6.931107,50.919899],"type":"Point"}
}