{
  "type": "Feature",
  "properties": {
    "iso:country":"DE",
    "sg:address":"In der Sieke 21",
    "sg:city":"Heidenau",
    "sg:phone":"+49 4182/4269",
    "sg:postcode":"21258",
    "sg:province":"Niedersachsen",
    "wof:name":"Wilhelm Br\u00f6han & Co.",
    "wof:placetype":"venue"
},
  "geometry": {"coordinates":[9.6517238617,53.3112449646],"type":"Point"}
}