{
  "type": "Feature",
  "properties": {
    "iso:country":"DE",
    "sg:address":"Winterstr. 10",
    "sg:city":"Karlsruhe",
    "sg:phone":"+49 721/31546",
    "sg:postcode":"76137",
    "sg:province":"Baden-W\u00fcrttemberg",
    "wof:name":"Fritz Dilli",
    "wof:placetype":"venue"
},
  "geometry": {"coordinates":[8.4048366547,48.9982185364],"type":"Point"}
}