{
  "type": "Feature",
  "properties": {
    "iso:country":"DE",
    "sg:address":"Gro\u00dftiefenbach 18",
    "sg:city":"Grafling",
    "sg:phone":"+49 991/284254",
    "sg:postcode":"94539",
    "sg:province":"Bayern",
    "wof:name":"Brigitte Gegenfurtner",
    "wof:placetype":"venue"
},
  "geometry": {"coordinates":[12.9567832947,48.8730354309],"type":"Point"}
}