{
  "type": "Feature",
  "properties": {
    "iso:country":"DE",
    "sg:address":"Kesselstr. 20",
    "sg:city":"Dormagen",
    "sg:phone":"+49 2182/7639",
    "sg:postcode":"41542",
    "sg:province":"Nordrhein-Westfalen",
    "wof:name":"Willi F\u00f6rster Drogerie",
    "wof:placetype":"venue"
},
  "geometry": {"coordinates":[6.720694,51.097229],"type":"Point"}
}