{
  "type": "Feature",
  "properties": {
    "iso:country":"DE",
    "sg:address":"Frauenstr. 12",
    "sg:city":"Ulm",
    "sg:phone":"+49 731/22250",
    "sg:postcode":"89073",
    "sg:province":"Baden-W\u00fcrttemberg",
    "wof:name":"Emilien M\u00f6ssner Inh. Grudrun Hoffmann",
    "wof:placetype":"venue"
},
  "geometry": {"coordinates":[9.9961299896,48.3980674744],"type":"Point"}
}