{
  "type": "Feature",
  "properties": {
    "iso:country":"DE",
    "sg:address":"Speicherstr. 9",
    "sg:city":"Riesa",
    "sg:phone":"+49 4935/2572950",
    "sg:postcode":"01587",
    "sg:province":"Sachsen",
    "wof:name":"Speicherei & Speditions Ag",
    "wof:placetype":"venue"
},
  "geometry": {"coordinates":[13.2935800552,51.3009986877],"type":"Point"}
}