{
  "type": "Feature",
  "properties": {
    "iso:country":"DE",
    "sg:address":"Orker Str. 13",
    "sg:city":"Lichtenfels",
    "sg:postcode":"35104",
    "sg:province":"Hessen",
    "wof:name":"Gemeindeb\u00fccherei Sachsenberg",
    "wof:placetype":"venue"
},
  "geometry": {"coordinates":[8.807623,51.200691],"type":"Point"}
}