{
  "type": "Feature",
  "properties": {
    "iso:country":"DE",
    "sg:address":"In der Hohl 5",
    "sg:city":"Bendorf",
    "sg:phone":"+49 2622/3315",
    "sg:postcode":"56170",
    "sg:province":"Rheinland-Pfalz",
    "wof:name":"Werner Vogt Bildhauer",
    "wof:placetype":"venue"
},
  "geometry": {"coordinates":[7.579536,50.423801],"type":"Point"}
}