{
  "type": "Feature",
  "properties": {
    "iso:country":"DE",
    "sg:address":"Im Tirol 6",
    "sg:city":"Borgentreich",
    "sg:phone":"+49 5643/8253",
    "sg:postcode":"34434",
    "sg:province":"Nordrhein-Westfalen",
    "wof:name":"G & G Naturpack Gmbh",
    "wof:placetype":"venue"
},
  "geometry": {"coordinates":[9.2779464722,51.5342407227],"type":"Point"}
}