{
  "type": "Feature",
  "properties": {
    "iso:country":"DE",
    "sg:address":"Rudolf-Breitscheid-Str. 11",
    "sg:city":"Sangerhausen",
    "sg:phone":"+49 3464/572848",
    "sg:postcode":"06526",
    "sg:province":"Sachsen-Anhalt",
    "wof:name":"Eberhard Ritter",
    "wof:placetype":"venue"
},
  "geometry": {"coordinates":[11.2979049683,51.4772529602],"type":"Point"}
}