{
  "type": "Feature",
  "properties": {
    "iso:country":"DE",
    "sg:address":"Luther Weg 39",
    "sg:city":"Wunstorf",
    "sg:phone":"+49 5031/972056",
    "sg:postcode":"31515",
    "sg:province":"Niedersachsen",
    "wof:name":"Martin M\u00fcller-steffen Rechtsanwalt",
    "wof:placetype":"venue"
},
  "geometry": {"coordinates":[9.4432411194,52.4263725281],"type":"Point"}
}