{
  "type": "Feature",
  "properties": {
    "iso:country":"DE",
    "sg:address":"Klosterstr. 34",
    "sg:city":"Worms",
    "sg:postcode":"67547",
    "sg:province":"Rheinland-Pfalz",
    "wof:name":"Atropa Handels Gmbh",
    "wof:placetype":"venue"
},
  "geometry": {"coordinates":[8.3584089279,49.6201095581],"type":"Point"}
}