{
  "type": "Feature",
  "properties": {
    "iso:country":"DE",
    "sg:address":"Gewerbegebiet Nord 9",
    "sg:city":"Mildenau",
    "sg:postcode":"09456",
    "sg:province":"Sachsen",
    "wof:name":"Secatec E. K.",
    "wof:placetype":"venue"
},
  "geometry": {"coordinates":[13.062303,50.599953],"type":"Point"}
}