{
  "type": "Feature",
  "properties": {
    "iso:country":"DE",
    "sg:address":"Mammendorfer Str. 1",
    "sg:city":"Ochtmersleben",
    "sg:phone":"+49 39206/50208",
    "sg:postcode":"39167",
    "sg:province":"Sachsen-Anhalt",
    "wof:name":"H. Schwarz",
    "wof:placetype":"venue"
},
  "geometry": {"coordinates":[11.4126548767,52.158241272],"type":"Point"}
}