{
  "type": "Feature",
  "properties": {
    "iso:country":"DE",
    "sg:address":"29614",
    "sg:city":"Soltau",
    "sg:phone":"+49 5191/3623",
    "sg:postcode":"29614",
    "sg:province":"Niedersachsen",
    "wof:name":"Bahnhofsgastst\u00e4tte",
    "wof:placetype":"venue"
},
  "geometry": {"coordinates":[9.844909668,53.0038414001],"type":"Point"}
}