{
  "type": "Feature",
  "properties": {
    "iso:country":"DE",
    "sg:address":"Scheveninger Str 12",
    "sg:city":"Bremen",
    "sg:phone":"+49 421/5798252",
    "sg:postcode":"28259",
    "sg:province":"Bremen",
    "wof:name":"Elektro-technik Elfers Gmbh & Co Kg",
    "wof:placetype":"venue"
},
  "geometry": {"coordinates":[8.721518,53.040001],"type":"Point"}
}