{
  "type": "Feature",
  "properties": {
    "iso:country":"DE",
    "sg:address":"H\u00f6rbacher Str. 6",
    "sg:city":"Althegnenberg",
    "sg:phone":"+49 8202/8345",
    "sg:postcode":"82278",
    "sg:province":"Bayern",
    "wof:name":"Ludwig Ostermeir",
    "wof:placetype":"venue"
},
  "geometry": {"coordinates":[11.0646,48.23267],"type":"Point"}
}