{
  "type": "Feature",
  "properties": {
    "iso:country":"DE",
    "sg:address":"Am Steinbruch 4",
    "sg:city":"Waldbr\u00f6l",
    "sg:phone":"+49 2291/80327",
    "sg:postcode":"51545",
    "sg:province":"Nordrhein-Westfalen",
    "wof:name":"Bewoedv - Webdesign Bernhard Wollersheim",
    "wof:placetype":"venue"
},
  "geometry": {"coordinates":[7.5728211403,50.8598175049],"type":"Point"}
}