{
  "type": "Feature",
  "properties": {
    "iso:country":"DE",
    "sg:address":"Ostdolberger Weg 28",
    "sg:city":"Ahlen",
    "sg:phone":"+49 2388/302993",
    "sg:postcode":"59229",
    "sg:province":"Nordrhein-Westfalen",
    "wof:name":"Norbert Lodenkemper",
    "wof:placetype":"venue"
},
  "geometry": {"coordinates":[7.94224,51.708309],"type":"Point"}
}