{
  "type": "Feature",
  "properties": {
    "iso:country":"DE",
    "sg:address":"Im Rank 2",
    "sg:city":"Rudersberg",
    "sg:phone":"+49 7183/1592",
    "sg:postcode":"73635",
    "sg:province":"Baden-W\u00fcrttemberg",
    "wof:name":"B. Frank",
    "wof:placetype":"venue"
},
  "geometry": {"coordinates":[9.5290403366,48.8598861694],"type":"Point"}
}