{
  "type": "Feature",
  "properties": {
    "iso:country":"DE",
    "sg:address":"Speckheim 14",
    "sg:city":"Windsbach",
    "sg:phone":"+49 9871/268",
    "sg:postcode":"91575",
    "sg:province":"Bayern",
    "wof:name":"Dieterle Gmbh",
    "wof:placetype":"venue"
},
  "geometry": {"coordinates":[10.782739,49.231079],"type":"Point"}
}