{
  "type": "Feature",
  "properties": {
    "iso:country":"DE",
    "sg:address":"Unter den Linden 21",
    "sg:city":"Berlin",
    "sg:postcode":"10117",
    "sg:province":"Berlin",
    "wof:name":"Erste Amsc Untern- Nehmensbeteiligungs Gmbh",
    "wof:placetype":"venue"
},
  "geometry": {"coordinates":[13.38983,52.516811],"type":"Point"}
}