{
  "type": "Feature",
  "properties": {
    "iso:country":"DE",
    "sg:address":"Schwebelstr. 11",
    "sg:city":"Pforzheim",
    "sg:postcode":"75172",
    "sg:province":"Baden-W\u00fcrttemberg",
    "wof:name":"Margot Korbus Amc - T\u00f6pfe",
    "wof:placetype":"venue"
},
  "geometry": {"coordinates":[8.6846504211,48.8909797668],"type":"Point"}
}