{
  "type": "Feature",
  "properties": {
    "iso:country":"DE",
    "sg:address":"Zur M\u00fchle 9",
    "sg:city":"Sonthofen",
    "sg:phone":"+49 8321/3786",
    "sg:postcode":"87527",
    "sg:province":"Bayern",
    "wof:name":"W. Hessmann",
    "wof:placetype":"venue"
},
  "geometry": {"coordinates":[10.28059,47.484089],"type":"Point"}
}