{
  "type": "Feature",
  "properties": {
    "iso:country":"DE",
    "sg:address":"Thonhausen 16",
    "sg:city":"Hemau",
    "sg:phone":"+49 9491/902063",
    "sg:postcode":"93155",
    "sg:province":"Bayern",
    "wof:name":"Baugesch\u00e4ft Eichenseher Gmbh",
    "wof:placetype":"venue"
},
  "geometry": {"coordinates":[11.842152,49.046307],"type":"Point"}
}