{
  "type": "Feature",
  "properties": {
    "iso:country":"DE",
    "sg:address":"Boldevitz",
    "sg:city":"Parchtitz",
    "sg:postcode":"18528",
    "sg:province":"Mecklenburg-Vorpommern",
    "wof:name":"Boldevitzer Bau Gmbh",
    "wof:placetype":"venue"
},
  "geometry": {"coordinates":[13.333621,54.442898],"type":"Point"}
}