{
  "type": "Feature",
  "properties": {
    "iso:country":"DE",
    "sg:address":"Kloppenheimer Str. 51",
    "sg:city":"Mannheim",
    "sg:phone":"+49 621/477151",
    "sg:postcode":"68239",
    "sg:province":"Baden-W\u00fcrttemberg",
    "wof:name":"A. Geier",
    "wof:placetype":"venue"
},
  "geometry": {"coordinates":[8.5608901978,49.4638710022],"type":"Point"}
}