{
  "type": "Feature",
  "properties": {
    "iso:country":"DE",
    "sg:address":"Wachtelstr. 25",
    "sg:city":"Zweibr\u00fccken",
    "sg:phone":"+49 6332/17239",
    "sg:postcode":"66482",
    "sg:province":"Rheinland-Pfalz",
    "wof:name":"Hans Pirrong Elektroinstallation",
    "wof:placetype":"venue"
},
  "geometry": {"coordinates":[7.365802,49.237896],"type":"Point"}
}