{
  "type": "Feature",
  "properties": {
    "iso:country":"DE",
    "sg:address":"Merziger Str. 148",
    "sg:city":"Dillingen",
    "sg:phone":"+49 6831/71494",
    "sg:postcode":"66763",
    "sg:province":"Saarland",
    "wof:name":"Esso Deutschland Gmbh",
    "wof:placetype":"venue"
},
  "geometry": {"coordinates":[6.7180571556,49.3588180542],"type":"Point"}
}