{
  "type": "Feature",
  "properties": {
    "iso:country":"DE",
    "sg:address":"Dorfstr. 5",
    "sg:city":"Schl\u00f6ben",
    "sg:phone":"+49 36428/40440",
    "sg:postcode":"07646",
    "sg:province":"Th\u00fcringen",
    "wof:name":"Edgar Schr\u00f6der",
    "wof:placetype":"venue"
},
  "geometry": {"coordinates":[11.6881923676,50.8936767578],"type":"Point"}
}