{
  "type": "Feature",
  "properties": {
    "iso:country":"DE",
    "sg:address":"S\u00fcdstr. 54",
    "sg:city":"Salz",
    "sg:postcode":"56414",
    "sg:province":"Rheinland-Pfalz",
    "wof:name":"Ferreira Valente Bau-gmbh",
    "wof:placetype":"venue"
},
  "geometry": {"coordinates":[7.965807,50.507725],"type":"Point"}
}