{
  "type": "Feature",
  "properties": {
    "iso:country":"DE",
    "sg:address":"Hofmark 1",
    "sg:city":"Schierling",
    "sg:phone":"+49 9451/93230",
    "sg:postcode":"84069",
    "sg:province":"Bayern",
    "wof:name":"Malzfabrik Albert M\u00fcller Verwaltungs Gmbh",
    "wof:placetype":"venue"
},
  "geometry": {"coordinates":[12.249142,48.838642],"type":"Point"}
}