{
  "type": "Feature",
  "properties": {
    "iso:country":"DE",
    "sg:address":"Ernststr. 19",
    "sg:city":"Hannover",
    "sg:phone":"+49 511/513068",
    "sg:postcode":"30559",
    "sg:province":"Niedersachsen",
    "wof:name":"Friedrich Palandt",
    "wof:placetype":"venue"
},
  "geometry": {"coordinates":[9.824936,52.359516],"type":"Point"}
}