{
  "type": "Feature",
  "properties": {
    "iso:country":"DE",
    "sg:address":"H\u00e4ndelstr. 5",
    "sg:city":"Kaarst",
    "sg:phone":"+49 2131/518185",
    "sg:postcode":"41564",
    "sg:province":"Nordrhein-Westfalen",
    "wof:name":"Marlies Maciejewski",
    "wof:placetype":"venue"
},
  "geometry": {"coordinates":[6.604987,51.193905],"type":"Point"}
}