{
  "type": "Feature",
  "properties": {
    "iso:country":"DE",
    "sg:address":"Erbacher Str. 6",
    "sg:city":"Wiesbaden",
    "sg:phone":"+49 611/846685",
    "sg:postcode":"65197",
    "sg:province":"Hessen",
    "wof:name":"G. Reckels Und H. Schneider Reckels",
    "wof:placetype":"venue"
},
  "geometry": {"coordinates":[8.230022,50.073952],"type":"Point"}
}