{
  "type": "Feature",
  "properties": {
    "iso:country":"DE",
    "sg:address":"Am Herrenh\u00e4user Bahnhof 26-28",
    "sg:city":"Hannover",
    "sg:phone":"+49 511/79040",
    "sg:postcode":"30419",
    "sg:province":"Niedersachsen",
    "wof:name":"Quadral Gmbh & Co Kg",
    "wof:placetype":"venue"
},
  "geometry": {"coordinates":[9.686113,52.401787],"type":"Point"}
}