{
  "type": "Feature",
  "properties": {
    "iso:country":"DE",
    "sg:address":"Haverbecker Weg 5",
    "sg:city":"Bremen",
    "sg:phone":"+49 421/462849",
    "sg:postcode":"28329",
    "sg:province":"Bremen",
    "wof:name":"Heidemarie Knaak Kg",
    "wof:placetype":"venue"
},
  "geometry": {"coordinates":[8.878576,53.072899],"type":"Point"}
}