{
  "type": "Feature",
  "properties": {
    "iso:country":"DE",
    "sg:address":"N\u00fcrnberger Str. 67",
    "sg:city":"Ansbach",
    "sg:phone":"+49 981/94195",
    "sg:postcode":"91522",
    "sg:province":"Bayern",
    "wof:name":"Lothar Gugel",
    "wof:placetype":"venue"
},
  "geometry": {"coordinates":[10.5827388763,49.3039779663],"type":"Point"}
}