{
  "type": "Feature",
  "properties": {
    "iso:country":"DE",
    "sg:address":"Mittelstenaher Str. 2",
    "sg:city":"Lamstedt",
    "sg:phone":"+49 4773/543",
    "sg:postcode":"21769",
    "sg:province":"Niedersachsen",
    "wof:name":"Hans Ney",
    "wof:placetype":"venue"
},
  "geometry": {"coordinates":[9.094512,53.636623],"type":"Point"}
}