{
  "type": "Feature",
  "properties": {
    "iso:country":"DE",
    "sg:address":"Erfurter Str. 8",
    "sg:city":"Ilmenau",
    "sg:phone":"+49 3677/64640",
    "sg:postcode":"98693",
    "sg:province":"Th\u00fcringen",
    "wof:name":"Jekat & Witting Gmbh",
    "wof:placetype":"venue"
},
  "geometry": {"coordinates":[10.91322,50.688572],"type":"Point"}
}