{
  "type": "Feature",
  "properties": {
    "iso:country":"DE",
    "sg:address":"Friedenstr. 12",
    "sg:city":"Reckendorf",
    "sg:phone":"+49 9544/6769",
    "sg:postcode":"96182",
    "sg:province":"Bayern",
    "wof:name":"Ludwig K\u00f6nig Schuhwaren",
    "wof:placetype":"venue"
},
  "geometry": {"coordinates":[10.835603714,50.0180664062],"type":"Point"}
}