{
  "type": "Feature",
  "properties": {
    "iso:country":"DE",
    "sg:address":"Bahnhofstr. 17",
    "sg:city":"Biedenkopf",
    "sg:phone":"+49 6461/8144",
    "sg:postcode":"35216",
    "sg:province":"Hessen",
    "wof:name":"E. Schwarz",
    "wof:placetype":"venue"
},
  "geometry": {"coordinates":[8.4706382751,50.9254760742],"type":"Point"}
}