{
  "type": "Feature",
  "properties": {
    "iso:country":"DE",
    "sg:address":"Leonhardstr. 22",
    "sg:city":"Rostock",
    "sg:phone":"+49 381/2007022",
    "sg:postcode":"18057",
    "sg:province":"Mecklenburg-Vorpommern",
    "wof:name":"Mecks Verlag Und Marketing Gmbh",
    "wof:placetype":"venue"
},
  "geometry": {"coordinates":[12.12059021,54.0880661011],"type":"Point"}
}