{
  "type": "Feature",
  "properties": {
    "iso:country":"DE",
    "sg:address":"Augustastr. 45",
    "sg:city":"Neuwied",
    "sg:phone":"+49 2631/24337",
    "sg:postcode":"56564",
    "sg:province":"Rheinland-Pfalz",
    "wof:name":"Bahnhofssch\u00e4nke",
    "wof:placetype":"venue"
},
  "geometry": {"coordinates":[7.4770078659,50.4306678772],"type":"Point"}
}