{
  "type": "Feature",
  "properties": {
    "iso:country":"DE",
    "sg:address":"K\u00f6penicker Allee 123-135",
    "sg:city":"Berlin",
    "sg:phone":"+49 30/5088097",
    "sg:postcode":"10318",
    "sg:province":"Berlin",
    "wof:name":"Cpic Import-export Gmbh",
    "wof:placetype":"venue"
},
  "geometry": {"coordinates":[13.539139,52.484253],"type":"Point"}
}