{
  "type": "Feature",
  "properties": {
    "iso:country":"DE",
    "sg:address":"Klosterstr. 55",
    "sg:city":"Pfullingen",
    "sg:phone":"+49 7121/72543",
    "sg:postcode":"72793",
    "sg:province":"Baden-W\u00fcrttemberg",
    "wof:name":"Kurt Walter Elektroinstallation",
    "wof:placetype":"venue"
},
  "geometry": {"coordinates":[9.22751,48.461269],"type":"Point"}
}