{
  "type": "Feature",
  "properties": {
    "iso:country":"DE",
    "sg:address":"Am Beuel 4",
    "sg:city":"Windeck",
    "sg:phone":"+49 2292/2064",
    "sg:postcode":"51570",
    "sg:province":"Nordrhein-Westfalen",
    "wof:name":"Wolfgang Adams",
    "wof:placetype":"venue"
},
  "geometry": {"coordinates":[7.5769071579,50.7960281372],"type":"Point"}
}