{
  "type": "Feature",
  "properties": {
    "iso:country":"DE",
    "sg:address":"Altenberger-Dom-Str. 124d",
    "sg:city":"Bergisch Gladbach",
    "sg:phone":"+49 2202/84172",
    "sg:postcode":"51467",
    "sg:province":"Nordrhein-Westfalen",
    "wof:name":"Hofamat Gmbh",
    "wof:placetype":"venue"
},
  "geometry": {"coordinates":[7.079919,51.014412],"type":"Point"}
}