{
  "type": "Feature",
  "properties": {
    "iso:country":"DE",
    "sg:address":"Oldenburger Str. 22",
    "sg:city":"Berlin",
    "sg:phone":"+49 30/3953037",
    "sg:postcode":"10551",
    "sg:province":"Berlin",
    "wof:name":"Beratungsstelle Des Deutschen Roten Kreuzes F\u00fcr T\u00fcrkische",
    "wof:placetype":"venue"
},
  "geometry": {"coordinates":[13.336758,52.531895],"type":"Point"}
}