{
  "type": "Feature",
  "properties": {
    "iso:country":"DE",
    "sg:address":"Betpfad 6a",
    "sg:city":"W\u00fcrzburg",
    "sg:phone":"+49 931/72024",
    "sg:postcode":"97082",
    "sg:province":"Bayern",
    "wof:name":"J\u00f6rg Braun-feldweg Architekt",
    "wof:placetype":"venue"
},
  "geometry": {"coordinates":[9.9240617752,49.7768325806],"type":"Point"}
}