{
  "type": "Feature",
  "properties": {
    "iso:country":"DE",
    "sg:address":"Hagertshausen 7",
    "sg:city":"Wolnzach",
    "sg:phone":"+49 8442/3015",
    "sg:postcode":"85283",
    "sg:province":"Bayern",
    "wof:name":"Bentronic Gesellschaft F\u00fcr Medizin-elektronik Mbh",
    "wof:placetype":"venue"
},
  "geometry": {"coordinates":[11.695395,48.597527],"type":"Point"}
}