{
  "type": "Feature",
  "properties": {
    "iso:country":"DE",
    "sg:address":"Parkstr. 96",
    "sg:city":"Bochum",
    "sg:phone":"+49 2327/85681",
    "sg:postcode":"44866",
    "sg:province":"Nordrhein-Westfalen",
    "wof:name":"M. Hardwig Ingenieur",
    "wof:placetype":"venue"
},
  "geometry": {"coordinates":[7.1393408775,51.4895515442],"type":"Point"}
}