{
  "type": "Feature",
  "properties": {
    "iso:country":"DE",
    "sg:address":"Eichenstr. 29",
    "sg:city":"Sch\u00f6neiche",
    "sg:phone":"+49 30/6498598",
    "sg:postcode":"15566",
    "sg:province":"Brandenburg",
    "wof:name":"Klaus Lubina",
    "wof:placetype":"venue"
},
  "geometry": {"coordinates":[13.691635,52.466831],"type":"Point"}
}