{
  "type": "Feature",
  "properties": {
    "iso:country":"DE",
    "sg:address":"Erholungsweg 71 c",
    "sg:city":"Berlin",
    "sg:phone":"+49 30/4348315",
    "sg:postcode":"13509",
    "sg:province":"Berlin",
    "wof:name":"Malereibetrieb Schedlinski Gmbh",
    "wof:placetype":"venue"
},
  "geometry": {"coordinates":[13.298067,52.596859],"type":"Point"}
}