{
  "type": "Feature",
  "properties": {
    "iso:country":"DE",
    "sg:address":"Am W\u00f6rtzgarten 8",
    "sg:city":"Idstein",
    "sg:phone":"+49 6126/5900",
    "sg:postcode":"65510",
    "sg:province":"Hessen",
    "wof:name":"Glyn Jones Verwaltungs Gmbh",
    "wof:placetype":"venue"
},
  "geometry": {"coordinates":[8.256035,50.206081],"type":"Point"}
}