{
  "type": "Feature",
  "properties": {
    "iso:country":"DE",
    "sg:address":"Ankergasse 35",
    "sg:city":"Klingenberg",
    "sg:phone":"+49 9372/2670",
    "sg:postcode":"63911",
    "sg:province":"Bayern",
    "wof:name":"Neis- Kunststoffbeschichtungs-",
    "wof:placetype":"venue"
},
  "geometry": {"coordinates":[9.1747627258,49.7732276917],"type":"Point"}
}