{
  "type": "Feature",
  "properties": {
    "iso:country":"DE",
    "sg:address":"Gartenstr. 25a",
    "sg:city":"Hillscheid",
    "sg:postcode":"56204",
    "sg:province":"Rheinland-Pfalz",
    "wof:name":"City",
    "wof:placetype":"venue"
},
  "geometry": {"coordinates":[7.6939811707,50.4059944153],"type":"Point"}
}