{
  "type": "Feature",
  "properties": {
    "iso:country":"DE",
    "sg:address":"Wengerberg 7",
    "sg:city":"Scheyern",
    "sg:phone":"+49 8441/84666",
    "sg:postcode":"85298",
    "sg:province":"Bayern",
    "wof:name":"Dr. H.-j. Quandt Tierarzt",
    "wof:placetype":"venue"
},
  "geometry": {"coordinates":[11.460234642,48.5005989075],"type":"Point"}
}