{
  "type": "Feature",
  "properties": {
    "iso:country":"DE",
    "sg:address":"Unterl\u00fc\u00dfer Str. 12",
    "sg:city":"Fa\u00dfberg",
    "sg:phone":"+49 5053/1345",
    "sg:postcode":"29328",
    "sg:province":"Niedersachsen",
    "wof:name":"Antiquit\u00e4tencafe",
    "wof:placetype":"venue"
},
  "geometry": {"coordinates":[10.122704,52.876484],"type":"Point"}
}