{
  "type": "Feature",
  "properties": {
    "iso:country":"DE",
    "sg:address":"Kaiserstr. 110",
    "sg:city":"Dortmund",
    "sg:phone":"+49 231/573406",
    "sg:postcode":"44135",
    "sg:province":"Nordrhein-Westfalen",
    "wof:name":"Briefmarken Furda Gmbh",
    "wof:placetype":"venue"
},
  "geometry": {"coordinates":[7.4841899872,51.5132217407],"type":"Point"}
}