{
  "type": "Feature",
  "properties": {
    "iso:country":"DE",
    "sg:address":"Speckstr. 20",
    "sg:city":"Versmold",
    "sg:phone":"+49 5423/94470",
    "sg:postcode":"33775",
    "sg:province":"Nordrhein-Westfalen",
    "wof:name":"Vassemer Gefl\u00fcgelfeinkost Gmbh",
    "wof:placetype":"venue"
},
  "geometry": {"coordinates":[8.1438150406,52.0479774475],"type":"Point"}
}