{
  "type": "Feature",
  "properties": {
    "iso:country":"DE",
    "sg:address":"Rosenweg 12",
    "sg:city":"Gardelegen",
    "sg:phone":"+49 3907/712548",
    "sg:postcode":"39638",
    "sg:province":"Sachsen-Anhalt",
    "wof:name":"Rosen-apotheke Ilona Ruchotzki",
    "wof:placetype":"venue"
},
  "geometry": {"coordinates":[11.400757,52.520912],"type":"Point"}
}