{
  "type": "Feature",
  "properties": {
    "iso:country":"DE",
    "sg:address":"Bergteilweg 4",
    "sg:city":"Igling",
    "sg:phone":"+49 8248/901049",
    "sg:postcode":"86859",
    "sg:province":"Bayern",
    "wof:name":"Karl Sauter Holz- Und Bautenschutz",
    "wof:placetype":"venue"
},
  "geometry": {"coordinates":[10.802686,48.070229],"type":"Point"}
}