{
  "type": "Feature",
  "properties": {
    "iso:country":"DE",
    "sg:address":"Viehmarktplatz 11",
    "sg:city":"Trier",
    "sg:phone":"+49 651/43113",
    "sg:postcode":"54290",
    "sg:province":"Rheinland-Pfalz",
    "wof:name":"Simplicissmus",
    "wof:placetype":"venue"
},
  "geometry": {"coordinates":[6.6373810768,49.7520866394],"type":"Point"}
}