{
  "type": "Feature",
  "properties": {
    "iso:country":"DE",
    "sg:address":"Jesuitengasse 2",
    "sg:city":"D\u00fcren",
    "sg:phone":"+49 2421/16193",
    "sg:postcode":"52349",
    "sg:province":"Nordrhein-Westfalen",
    "wof:name":"Ulrich Liebich Steuerberater",
    "wof:placetype":"venue"
},
  "geometry": {"coordinates":[6.4848761559,50.8014907837],"type":"Point"}
}