{
  "type": "Feature",
  "properties": {
    "iso:country":"DE",
    "sg:address":"Potsdamer Str. 86",
    "sg:city":"Berlin",
    "sg:postcode":"10785",
    "sg:province":"Berlin",
    "wof:name":"Vedat Savas E. K.",
    "wof:placetype":"venue"
},
  "geometry": {"coordinates":[13.36568,52.503178],"type":"Point"}
}