{
  "type": "Feature",
  "properties": {
    "iso:country":"DE",
    "sg:address":"Theresienstr. 7",
    "sg:city":"Ingolstadt",
    "sg:phone":"+49 841/934670",
    "sg:postcode":"85049",
    "sg:province":"Bayern",
    "wof:name":"Kuntz Und Schmalzl Notare",
    "wof:placetype":"venue"
},
  "geometry": {"coordinates":[11.423617363,48.7642288208],"type":"Point"}
}