{
  "type": "Feature",
  "properties": {
    "iso:country":"DE",
    "sg:address":"Stettiner Str. 13",
    "sg:city":"Altensteig",
    "sg:phone":"+49 7458/7139",
    "sg:postcode":"72213",
    "sg:province":"Baden-W\u00fcrttemberg",
    "wof:name":"F. Sch\u00f6ttle",
    "wof:placetype":"venue"
},
  "geometry": {"coordinates":[8.653844,48.579632],"type":"Point"}
}