{
  "type": "Feature",
  "properties": {
    "iso:country":"DE",
    "sg:address":"Dorfstr. 31",
    "sg:city":"Hermstedt",
    "sg:phone":"+49 3644/553831",
    "sg:postcode":"99510",
    "sg:province":"Th\u00fcringen",
    "wof:name":"W. Krause",
    "wof:placetype":"venue"
},
  "geometry": {"coordinates":[11.5336561203,50.9948120117],"type":"Point"}
}