{
  "type": "Feature",
  "properties": {
    "iso:country":"DE",
    "sg:address":"Burgstr. 82",
    "sg:city":"Solingen",
    "sg:phone":"+49 212/207213",
    "sg:postcode":"42655",
    "sg:province":"Nordrhein-Westfalen",
    "wof:name":"Waldemar Lucas Rechtsanwalt",
    "wof:placetype":"venue"
},
  "geometry": {"coordinates":[7.0771012306,51.1762924194],"type":"Point"}
}