{
  "type": "Feature",
  "properties": {
    "iso:country":"DE",
    "sg:address":"K\u00f6nigsbr\u00fccker Str. 114 A",
    "sg:city":"Dresden",
    "sg:phone":"+49 351/8805033",
    "sg:postcode":"01099",
    "sg:province":"Sachsen",
    "wof:name":"G. Und K. K\u00f6hler",
    "wof:placetype":"venue"
},
  "geometry": {"coordinates":[13.7658462524,51.0919914246],"type":"Point"}
}