{
  "type": "Feature",
  "properties": {
    "iso:country":"DE",
    "sg:address":"Laubenbergweg 4",
    "sg:city":"Schonach",
    "sg:phone":"+49 7722/6165",
    "sg:postcode":"78136",
    "sg:province":"Baden-W\u00fcrttemberg",
    "wof:name":"Oskar M\u00fcller",
    "wof:placetype":"venue"
},
  "geometry": {"coordinates":[8.240445137,48.147644043],"type":"Point"}
}