{
  "type": "Feature",
  "properties": {
    "iso:country":"DE",
    "sg:address":"Frankfurter Str. 103",
    "sg:city":"Braunheim",
    "sg:phone":"+49 6142/603360",
    "sg:postcode":"65479",
    "sg:province":"Hessen",
    "wof:name":"Speyer & Grund Gmbh",
    "wof:placetype":"venue"
},
  "geometry": {"coordinates":[-91.7025299072,37.2923583984],"type":"Point"}
}