{
  "type": "Feature",
  "properties": {
    "iso:country":"DE",
    "sg:address":"Isarstr. 5",
    "sg:city":"Langenbach",
    "sg:phone":"+49 8761/1707",
    "sg:postcode":"85416",
    "sg:province":"Bayern",
    "wof:name":"A. Neumair",
    "wof:placetype":"venue"
},
  "geometry": {"coordinates":[11.8726949692,48.4260482788],"type":"Point"}
}