{
  "type": "Feature",
  "properties": {
    "iso:country":"DE",
    "sg:address":"Rathausplatz 6",
    "sg:city":"Neuenmarkt",
    "sg:phone":"+49 9227/6629",
    "sg:postcode":"95339",
    "sg:province":"Bayern",
    "wof:name":"Kino Im Gemeindesaal Neuenmarkt",
    "wof:placetype":"venue"
},
  "geometry": {"coordinates":[11.582789,50.094116],"type":"Point"}
}