{
  "type": "Feature",
  "properties": {
    "iso:country":"DE",
    "sg:address":"Schulstr. 4",
    "sg:city":"Maisach",
    "sg:phone":"+49 8142/2230",
    "sg:postcode":"82216",
    "sg:province":"Bayern",
    "wof:name":"Peter Geyer Gmbh",
    "wof:placetype":"venue"
},
  "geometry": {"coordinates":[11.2581634521,48.217792511],"type":"Point"}
}