{
  "type": "Feature",
  "properties": {
    "iso:country":"DE",
    "sg:address":"Lessingstr. 9",
    "sg:city":"Westerstede",
    "sg:phone":"+49 4488/3685",
    "sg:postcode":"26655",
    "sg:province":"Niedersachsen",
    "wof:name":"Heidi Erhardt",
    "wof:placetype":"venue"
},
  "geometry": {"coordinates":[7.9395899773,53.2543640137],"type":"Point"}
}