{
  "type": "Feature",
  "properties": {
    "iso:country":"DE",
    "sg:address":"Zum S\u00fcdhang 12",
    "sg:city":"Saarbr\u00fccken",
    "sg:phone":"+49 6893/3848",
    "sg:postcode":"66130",
    "sg:province":"Saarland",
    "wof:name":"Hans Dieter Pulverm\u00fcller Architekt",
    "wof:placetype":"venue"
},
  "geometry": {"coordinates":[7.071791,49.202892],"type":"Point"}
}