{
  "type": "Feature",
  "properties": {
    "iso:country":"DE",
    "sg:address":"Ulrichplatz 5",
    "sg:city":"G\u00fcstrow",
    "sg:postcode":"18273",
    "sg:province":"Mecklenburg-Vorpommern",
    "wof:name":"Christa-maria J\u00e4rke Delikatessengesch\u00e4ft",
    "wof:placetype":"venue"
},
  "geometry": {"coordinates":[12.162451,53.796719],"type":"Point"}
}