{
  "type": "Feature",
  "properties": {
    "iso:country":"DE",
    "sg:address":"Kiefernstr. 12",
    "sg:city":"Eichenau",
    "sg:phone":"+49 8141/71195",
    "sg:postcode":"82223",
    "sg:province":"Bayern",
    "wof:name":"Alois Wimmer",
    "wof:placetype":"venue"
},
  "geometry": {"coordinates":[11.3254823685,48.1633453369],"type":"Point"}
}