{
  "type": "Feature",
  "properties": {
    "iso:country":"DE",
    "sg:address":"N\u00fcrnberger Str. 6",
    "sg:city":"Gunzenhausen",
    "sg:phone":"+49 9831/9960",
    "sg:postcode":"91710",
    "sg:province":"Bayern",
    "wof:name":"Brigittes Musikshop",
    "wof:placetype":"venue"
},
  "geometry": {"coordinates":[10.7554578781,49.1175689697],"type":"Point"}
}