{
  "type": "Feature",
  "properties": {
    "iso:country":"DE",
    "sg:address":"Hermann-L\u00f6ns-Weg 2",
    "sg:city":"Dillingen",
    "sg:phone":"+49 6831/702570",
    "sg:postcode":"66763",
    "sg:province":"Saarland",
    "wof:name":"I. Reiter J. Schmeyer",
    "wof:placetype":"venue"
},
  "geometry": {"coordinates":[6.7224931717,49.3589363098],"type":"Point"}
}