{
  "type": "Feature",
  "properties": {
    "iso:country":"DE",
    "sg:address":"Elbestr. 27",
    "sg:city":"M\u00fclheim",
    "sg:phone":"+49 4920/852034",
    "sg:postcode":"45478",
    "sg:province":"Nordrhein-Westfalen",
    "wof:name":"Msm Markier-sensor Systeme Gmbh",
    "wof:placetype":"venue"
},
  "geometry": {"coordinates":[6.860143,51.431667],"type":"Point"}
}