{
  "type": "Feature",
  "properties": {
    "iso:country":"DE",
    "sg:address":"Spitalstr. 10",
    "sg:city":"Zell",
    "sg:phone":"+49 7835/549636",
    "sg:postcode":"77736",
    "sg:province":"Baden-W\u00fcrttemberg",
    "wof:name":"Jappo Siegfried W\u00f6lfle",
    "wof:placetype":"venue"
},
  "geometry": {"coordinates":[8.067785,48.345795],"type":"Point"}
}