{
  "type": "Feature",
  "properties": {
    "iso:country":"DE",
    "sg:address":"Bayernstr. 51",
    "sg:city":"Rheine",
    "sg:phone":"+49 5971/791155",
    "sg:postcode":"48429",
    "sg:province":"Nordrhein-Westfalen",
    "wof:name":"Hermann Twieling Gmbh & Co. Kg",
    "wof:placetype":"venue"
},
  "geometry": {"coordinates":[7.4407849312,52.2892990112],"type":"Point"}
}