{
  "type": "Feature",
  "properties": {
    "iso:country":"DE",
    "sg:address":"Obertorstr. 91",
    "sg:city":"Bad Camberg",
    "sg:phone":"+49 6434/5555",
    "sg:postcode":"65520",
    "sg:province":"Hessen",
    "wof:name":"Leber Bau Gmbh",
    "wof:placetype":"venue"
},
  "geometry": {"coordinates":[8.27947,50.297951],"type":"Point"}
}