{
  "type": "Feature",
  "properties": {
    "iso:country":"DE",
    "sg:address":"Rurstr. 41",
    "sg:city":"D\u00fcren",
    "sg:phone":"+49 2421/43481",
    "sg:postcode":"52349",
    "sg:province":"Nordrhein-Westfalen",
    "wof:name":"Johann Turowski",
    "wof:placetype":"venue"
},
  "geometry": {"coordinates":[6.47425,50.798512],"type":"Point"}
}