{
  "type": "Feature",
  "properties": {
    "iso:country":"DE",
    "sg:address":"Seiferhof",
    "sg:city":"Vettelscho\u00df",
    "sg:postcode":"53560",
    "sg:province":"Rheinland-Pfalz",
    "wof:name":"Grewe Gmbh",
    "wof:placetype":"venue"
},
  "geometry": {"coordinates":[7.334318161,50.6257743835],"type":"Point"}
}