{
  "type": "Feature",
  "properties": {
    "iso:country":"DE",
    "sg:address":"In den Kolkwiesen 50-52",
    "sg:city":"Langenhagen",
    "sg:phone":"+49 511/731095",
    "sg:postcode":"30851",
    "sg:province":"Niedersachsen",
    "wof:name":"Gardinen Weberei Otto G\u00f6schel Gmbh",
    "wof:placetype":"venue"
},
  "geometry": {"coordinates":[9.748164,52.431526],"type":"Point"}
}