{
  "type": "Feature",
  "properties": {
    "iso:country":"DE",
    "sg:address":"Mengeder Str. 43c",
    "sg:city":"L\u00fcnen",
    "sg:phone":"+49 231/873353",
    "sg:postcode":"44536",
    "sg:province":"Nordrhein-Westfalen",
    "wof:name":"Fu\u00dfbodenbau Peter Schulz",
    "wof:placetype":"venue"
},
  "geometry": {"coordinates":[7.4333648682,51.5952186584],"type":"Point"}
}