{
  "type": "Feature",
  "properties": {
    "iso:country":"DE",
    "sg:address":"Am Brachland 10",
    "sg:city":"Essen",
    "sg:phone":"+49 201/689505",
    "sg:postcode":"45355",
    "sg:province":"Nordrhein-Westfalen",
    "wof:name":"Ivi Kielisch Gmbh",
    "wof:placetype":"venue"
},
  "geometry": {"coordinates":[6.9458880424,51.4744644165],"type":"Point"}
}