{
  "type": "Feature",
  "properties": {
    "iso:country":"DE",
    "sg:address":"Nicolaistr. 22",
    "sg:city":"Berlin",
    "sg:phone":"+49 30/896080",
    "sg:postcode":"12247",
    "sg:province":"Berlin",
    "wof:name":"Diagnostisches Zentrum Verwaltungs Gmbh & Co.",
    "wof:placetype":"venue"
},
  "geometry": {"coordinates":[13.3346099854,52.4433135986],"type":"Point"}
}