{
  "type": "Feature",
  "properties": {
    "iso:country":"DE",
    "sg:address":"Villengang 2",
    "sg:city":"Jena",
    "sg:postcode":"07745",
    "sg:province":"Th\u00fcringen",
    "wof:name":"Acta Histochemica Fischer Verlag",
    "wof:placetype":"venue"
},
  "geometry": {"coordinates":[11.5815601349,50.9239845276],"type":"Point"}
}