{
  "type": "Feature",
  "properties": {
    "iso:country":"DE",
    "sg:address":"Florastr. 23",
    "sg:city":"Willich",
    "sg:phone":"+49 2154/5902",
    "sg:postcode":"47877",
    "sg:province":"Nordrhein-Westfalen",
    "wof:name":"Hans H\u00fcsgen",
    "wof:placetype":"venue"
},
  "geometry": {"coordinates":[6.526664,51.240341],"type":"Point"}
}