{
  "type": "Feature",
  "properties": {
    "iso:country":"DE",
    "sg:address":"Apothekenstr. 3",
    "sg:city":"L\u00fcneburg",
    "sg:phone":"+49 4131/41650",
    "sg:postcode":"21335",
    "sg:province":"Niedersachsen",
    "wof:name":"Holger Findorff",
    "wof:placetype":"venue"
},
  "geometry": {"coordinates":[10.4084730148,53.2488632202],"type":"Point"}
}