{
  "type": "Feature",
  "properties": {
    "iso:country":"DE",
    "sg:address":"Marburger Str. 25",
    "sg:city":"Erndtebr\u00fcck",
    "sg:phone":"+49 2753/2085",
    "sg:postcode":"57339",
    "sg:province":"Nordrhein-Westfalen",
    "wof:name":"Aral-tankstelle Kurt Thomas",
    "wof:placetype":"venue"
},
  "geometry": {"coordinates":[8.2597637177,50.9916915894],"type":"Point"}
}