{
  "type": "Feature",
  "properties": {
    "iso:country":"DE",
    "sg:address":"Kaiserstr. 61",
    "sg:city":"Lahr",
    "sg:phone":"+49 7821/22592",
    "sg:postcode":"77933",
    "sg:province":"Baden-W\u00fcrttemberg",
    "wof:name":"Rehfu\u00df",
    "wof:placetype":"venue"
},
  "geometry": {"coordinates":[7.8690729141,48.3416595459],"type":"Point"}
}