{
  "type": "Feature",
  "properties": {
    "iso:country":"DE",
    "sg:address":"Woltorfer Str. 57/59",
    "sg:city":"Peine",
    "sg:phone":"+49 5171/77910",
    "sg:postcode":"31224",
    "sg:province":"Niedersachsen",
    "wof:name":"Berufsbildungs- Und Besch\u00e4ftigungsgesellschaft",
    "wof:placetype":"venue"
},
  "geometry": {"coordinates":[10.243103981,52.3204689026],"type":"Point"}
}