{
  "type": "Feature",
  "properties": {
    "iso:country":"DE",
    "sg:address":"August-Dehning-Weg 2",
    "sg:city":"Wietzendorf",
    "sg:phone":"+49 5196/523",
    "sg:postcode":"29649",
    "sg:province":"Niedersachsen",
    "wof:name":"Versicherungsb\u00fcro Arthur Grimm E. K.",
    "wof:placetype":"venue"
},
  "geometry": {"coordinates":[9.97377491,52.9134674072],"type":"Point"}
}