{
  "type": "Feature",
  "properties": {
    "iso:country":"DE",
    "sg:address":"Alte Str. 36",
    "sg:city":"N\u00fcrnberg",
    "sg:phone":"+49 911/642270",
    "sg:postcode":"90451",
    "sg:province":"Bayern",
    "wof:name":"Klemens Geiger Rechtsanwalt",
    "wof:placetype":"venue"
},
  "geometry": {"coordinates":[11.033867836,49.403301239],"type":"Point"}
}