{
  "type": "Feature",
  "properties": {
    "iso:country":"DE",
    "sg:address":"Nachtigallstr. 3",
    "sg:city":"D\u00fcsseldorf",
    "sg:phone":"+49 211/287698",
    "sg:postcode":"40625",
    "sg:province":"Nordrhein-Westfalen",
    "wof:name":"Bei Mama Lisi",
    "wof:placetype":"venue"
},
  "geometry": {"coordinates":[6.8640041351,51.2237663269],"type":"Point"}
}