{
  "type": "Feature",
  "properties": {
    "iso:country":"DE",
    "sg:address":"B\u00fcrgerm.-Weigand-Str. 1",
    "sg:city":"Gerolzhofen",
    "sg:phone":"+49 9382/1439",
    "sg:postcode":"97447",
    "sg:province":"Bayern",
    "wof:name":"Friedrich Kg",
    "wof:placetype":"venue"
},
  "geometry": {"coordinates":[10.3483066559,49.9007759094],"type":"Point"}
}