{
  "type": "Feature",
  "properties": {
    "iso:country":"DE",
    "sg:address":"Weyerstr. 314-316",
    "sg:city":"Solingen",
    "sg:phone":"+49 212/310126",
    "sg:postcode":"42719",
    "sg:province":"Nordrhein-Westfalen",
    "wof:name":"Kath. \u00d6ffentliche Bibliothek St. Katharina",
    "wof:placetype":"venue"
},
  "geometry": {"coordinates":[7.034672,51.179398],"type":"Point"}
}