{
  "type": "Feature",
  "properties": {
    "iso:country":"DE",
    "sg:address":"Romerstr. 17a",
    "sg:city":"Coswig",
    "sg:postcode":"01640",
    "sg:province":"Sachsen",
    "wof:name":"Deutsche Verm\u00f6gensberatung Ag",
    "wof:placetype":"venue"
},
  "geometry": {"coordinates":[13.5705728531,51.125328064],"type":"Point"}
}