{
  "type": "Feature",
  "properties": {
    "iso:country":"DE",
    "sg:address":"Br\u00fcderstr. 4",
    "sg:city":"Glauchau",
    "sg:phone":"+49 3763/2883",
    "sg:postcode":"08371",
    "sg:province":"Sachsen",
    "wof:name":"Melodie Elektronik Handels Gmbh",
    "wof:placetype":"venue"
},
  "geometry": {"coordinates":[12.5423336029,50.8185272217],"type":"Point"}
}