{
  "type": "Feature",
  "properties": {
    "iso:country":"DE",
    "sg:address":"Ackerstr 1",
    "sg:city":"Herne",
    "sg:phone":"+49 2325/41646",
    "sg:postcode":"44652",
    "sg:province":"Nordrhein-Westfalen",
    "wof:name":"Maschinen- Und Apparatebau Hans Serbent Nachfolger Gmbh",
    "wof:placetype":"venue"
},
  "geometry": {"coordinates":[7.184222,51.535332],"type":"Point"}
}