{
  "type": "Feature",
  "properties": {
    "iso:country":"DE",
    "sg:address":"Stettenstr. 27",
    "sg:city":"Augsburg",
    "sg:postcode":"86150",
    "sg:province":"Bayern",
    "wof:name":"Harman Lebensmittel Gmbh",
    "wof:placetype":"venue"
},
  "geometry": {"coordinates":[10.8909549713,48.3608131409],"type":"Point"}
}