{
  "type": "Feature",
  "properties": {
    "iso:country":"DE",
    "sg:address":"Augustinerstr. 20",
    "sg:city":"W\u00fcrzburg",
    "sg:phone":"+49 931/53470",
    "sg:postcode":"97070",
    "sg:province":"Bayern",
    "wof:name":"Richard Dantscher",
    "wof:placetype":"venue"
},
  "geometry": {"coordinates":[9.9285335541,49.791103363],"type":"Point"}
}