{
  "type": "Feature",
  "properties": {
    "iso:country":"DE",
    "sg:address":"Grenzstr. 43",
    "sg:city":"Dietzenbach",
    "sg:postcode":"63128",
    "sg:province":"Hessen",
    "wof:name":"Sathy Sai Vereinigung E. V.",
    "wof:placetype":"venue"
},
  "geometry": {"coordinates":[8.7781248093,50.0034790039],"type":"Point"}
}