{
  "type": "Feature",
  "properties": {
    "iso:country":"DE",
    "sg:address":"Zur Marienh\u00f6he 15",
    "sg:city":"Sinzing",
    "sg:phone":"+49 941/33908",
    "sg:postcode":"93161",
    "sg:province":"Bayern",
    "wof:name":"Kolpingfamilie St. Wolfgang E. V.",
    "wof:placetype":"venue"
},
  "geometry": {"coordinates":[12.0243110657,49.0124588013],"type":"Point"}
}