{
  "type": "Feature",
  "properties": {
    "iso:country":"DE",
    "sg:address":"Brandenburgische Str. 37",
    "sg:city":"Berlin",
    "sg:phone":"+49 30/8926488",
    "sg:postcode":"10707",
    "sg:province":"Berlin",
    "wof:name":"Brandenburg-apotheke",
    "wof:placetype":"venue"
},
  "geometry": {"coordinates":[13.307124,52.498447],"type":"Point"}
}