{
  "type": "Feature",
  "properties": {
    "iso:country":"DE",
    "sg:address":"Ostseeallee 43a",
    "sg:city":"K\u00fchlungsborn",
    "sg:phone":"+49 38293/13838",
    "sg:postcode":"18225",
    "sg:province":"Mecklenburg-Vorpommern",
    "wof:name":"Restaurant Strand-corso Inh. Frank K\u00fchne",
    "wof:placetype":"venue"
},
  "geometry": {"coordinates":[11.7312450409,54.1525306702],"type":"Point"}
}