{
  "type": "Feature",
  "properties": {
    "iso:country":"DE",
    "sg:address":"Turnackerstr. 23",
    "sg:city":"Filderstadt",
    "sg:phone":"+49 711/703193",
    "sg:postcode":"70794",
    "sg:province":"Baden-W\u00fcrttemberg",
    "wof:name":"Alfred St\u00e4bler",
    "wof:placetype":"venue"
},
  "geometry": {"coordinates":[9.2102689743,48.6797790527],"type":"Point"}
}