{
  "type": "Feature",
  "properties": {
    "iso:country":"DE",
    "sg:address":"Hauptstr. 6",
    "sg:city":"Wernau",
    "sg:phone":"+49 7153/38070",
    "sg:postcode":"73249",
    "sg:province":"Baden-W\u00fcrttemberg",
    "wof:name":"W. Frey",
    "wof:placetype":"venue"
},
  "geometry": {"coordinates":[9.4229898453,48.6894073486],"type":"Point"}
}