{
  "type": "Feature",
  "properties": {
    "iso:country":"DE",
    "sg:address":"Gartenstr. 32",
    "sg:city":"Sonneberg",
    "sg:phone":"+49 3675/403503",
    "sg:postcode":"96515",
    "sg:province":"Th\u00fcringen",
    "wof:name":"R. Eckart",
    "wof:placetype":"venue"
},
  "geometry": {"coordinates":[11.2021417618,50.3458099365],"type":"Point"}
}