{
  "type": "Feature",
  "properties": {
    "iso:country":"DE",
    "sg:address":"Beeckstr. 9",
    "sg:city":"Aachen",
    "sg:phone":"+49 241/407224",
    "sg:postcode":"52062",
    "sg:province":"Nordrhein-Westfalen",
    "wof:name":"A. Windm\u00fcller",
    "wof:placetype":"venue"
},
  "geometry": {"coordinates":[6.094192,50.774094],"type":"Point"}
}