{
  "type": "Feature",
  "properties": {
    "iso:country":"DE",
    "sg:address":"Wallstr. 12",
    "sg:city":"Bautzen",
    "sg:phone":"+49 3591/499060",
    "sg:postcode":"02625",
    "sg:province":"Sachsen",
    "wof:name":"S\u00e4chsische Immobilien- Und Finanzagentur",
    "wof:placetype":"venue"
},
  "geometry": {"coordinates":[14.4312200546,51.1779212952],"type":"Point"}
}