{
  "type": "Feature",
  "properties": {
    "iso:country":"DE",
    "sg:address":"Brandenburger Str. 54",
    "sg:city":"Genthin",
    "sg:phone":"+49 3933/805496",
    "sg:postcode":"39307",
    "sg:province":"Sachsen-Anhalt",
    "wof:name":"Sanit\u00e4tshaus Marlies Kamp",
    "wof:placetype":"venue"
},
  "geometry": {"coordinates":[12.158706665,52.4057998657],"type":"Point"}
}