{
  "type": "Feature",
  "properties": {
    "iso:country":"DE",
    "sg:address":"Neue Str. 5",
    "sg:city":"Kehmstedt",
    "sg:phone":"+49 36338/42061",
    "sg:postcode":"99752",
    "sg:province":"Th\u00fcringen",
    "wof:name":"S. Heise",
    "wof:placetype":"venue"
},
  "geometry": {"coordinates":[10.6133108139,51.4732894897],"type":"Point"}
}