{
  "type": "Feature",
  "properties": {
    "iso:country":"DE",
    "sg:address":"Am Mitterfeld 22",
    "sg:city":"M\u00fcnchen",
    "sg:phone":"+49 89/429180",
    "sg:postcode":"81829",
    "sg:province":"Bayern",
    "wof:name":"Ritschel Bau Gmbh",
    "wof:placetype":"venue"
},
  "geometry": {"coordinates":[11.6756391525,48.1279029846],"type":"Point"}
}