{
  "type": "Feature",
  "properties": {
    "iso:country":"DE",
    "sg:address":"Hauptstr. 1",
    "sg:city":"Vienenburg",
    "sg:phone":"+49 5324/1676",
    "sg:postcode":"38690",
    "sg:province":"Niedersachsen",
    "wof:name":"Wilhelm Heimberg",
    "wof:placetype":"venue"
},
  "geometry": {"coordinates":[10.555703,51.979557],"type":"Point"}
}