{
  "type": "Feature",
  "properties": {
    "iso:country":"DE",
    "sg:address":"Bahnhofstr. 42-44",
    "sg:city":"Winsen",
    "sg:phone":"+49 4171/61096",
    "sg:postcode":"21423",
    "sg:province":"Niedersachsen",
    "wof:name":"Dorothea Halle Gmbh",
    "wof:placetype":"venue"
},
  "geometry": {"coordinates":[10.206244,53.358334],"type":"Point"}
}