{
  "type": "Feature",
  "properties": {
    "iso:country":"DE",
    "sg:address":"Hermannstr. 17",
    "sg:city":"Schwerin",
    "sg:postcode":"19053",
    "sg:province":"Mecklenburg-Vorpommern",
    "wof:name":"Kaffe Und Konditorei Kopf Gmbh",
    "wof:placetype":"venue"
},
  "geometry": {"coordinates":[11.405815,53.621788],"type":"Point"}
}