{
  "type": "Feature",
  "properties": {
    "iso:country":"DE",
    "sg:address":"Oelsnitzer Landstr. 1a",
    "sg:city":"Plauen",
    "sg:phone":"+49 3741",
    "sg:postcode":"08527",
    "sg:province":"Sachsen",
    "wof:name":"Immobilienservice Luckner",
    "wof:placetype":"venue"
},
  "geometry": {"coordinates":[12.1447992325,50.4778022766],"type":"Point"}
}