{
  "type": "Feature",
  "properties": {
    "iso:country":"DE",
    "sg:address":"Schwanseestr. 111",
    "sg:city":"Weimar",
    "sg:postcode":"99427",
    "sg:province":"Th\u00fcringen",
    "wof:name":"Passivhaus-weimar.de Gmbh",
    "wof:placetype":"venue"
},
  "geometry": {"coordinates":[11.3040065765,50.9836997986],"type":"Point"}
}