{
  "type": "Feature",
  "properties": {
    "iso:country":"DE",
    "sg:address":"Alzenauer Str. 30b",
    "sg:city":"Rodenbach",
    "sg:phone":"+49 6184/50449",
    "sg:postcode":"63517",
    "sg:province":"Hessen",
    "wof:name":"Apotheke Am Rathaus Alexander Wick E. K.",
    "wof:placetype":"venue"
},
  "geometry": {"coordinates":[9.026628,50.141327],"type":"Point"}
}