{
  "type": "Feature",
  "properties": {
    "iso:country":"DE",
    "sg:address":"Quakernacks Hof 3",
    "sg:city":"Bielefeld",
    "sg:phone":"+49 521/402755",
    "sg:postcode":"33647",
    "sg:province":"Nordrhein-Westfalen",
    "wof:name":"C. Zobel-quakernack",
    "wof:placetype":"venue"
},
  "geometry": {"coordinates":[8.4951162338,51.9654197693],"type":"Point"}
}