{
  "type": "Feature",
  "properties": {
    "iso:country":"DE",
    "sg:address":"Friedrichstr. 6",
    "sg:city":"Denkendorf",
    "sg:phone":"+49 711/344103",
    "sg:postcode":"73770",
    "sg:province":"Baden-W\u00fcrttemberg",
    "wof:name":"Rathaus-apotheke",
    "wof:placetype":"venue"
},
  "geometry": {"coordinates":[9.316606,48.694405],"type":"Point"}
}