{
  "type": "Feature",
  "properties": {
    "iso:country":"DE",
    "sg:address":"M\u00fchlberggasse 4",
    "sg:city":"Schneeberg",
    "sg:phone":"+49 3772/28450",
    "sg:postcode":"08289",
    "sg:province":"Sachsen",
    "wof:name":"Kleingartenanlage Urschelh\u00f6he",
    "wof:placetype":"venue"
},
  "geometry": {"coordinates":[12.6364297867,50.5938606262],"type":"Point"}
}