{
  "type": "Feature",
  "properties": {
    "iso:country":"DE",
    "sg:address":"Karlstr. 165",
    "sg:city":"Karlsruhe",
    "sg:phone":"+49 721/387626",
    "sg:postcode":"76135",
    "sg:province":"Baden-W\u00fcrttemberg",
    "wof:name":"Pinguin Club",
    "wof:placetype":"venue"
},
  "geometry": {"coordinates":[8.3935270309,48.9933776855],"type":"Point"}
}