{
  "type": "Feature",
  "properties": {
    "iso:country":"DE",
    "sg:city":"K\u00f6ln",
    "sg:phone":"+49 221",
    "sg:postcode":"51061",
    "sg:province":"Nordrhein-Westfalen",
    "wof:name":"Dabbelju Music",
    "wof:placetype":"venue"
},
  "geometry": {"coordinates":[7.03177,50.983383],"type":"Point"}
}