{
  "type": "Feature",
  "properties": {
    "iso:country":"DE",
    "sg:address":"Benesisstr. 36",
    "sg:city":"K\u00f6ln",
    "sg:phone":"+49 221/2570174",
    "sg:postcode":"50672",
    "sg:province":"Nordrhein-Westfalen",
    "wof:name":"Hertha Elscheidt Gmbh & Co. Kg",
    "wof:placetype":"venue"
},
  "geometry": {"coordinates":[6.942461,50.937],"type":"Point"}
}