{
  "type": "Feature",
  "properties": {
    "iso:country":"DE",
    "sg:address":"Lange Str. 130",
    "sg:city":"Viersen",
    "sg:phone":"+49 2162/590",
    "sg:postcode":"41751",
    "sg:province":"Nordrhein-Westfalen",
    "wof:name":"Terachemie Gmbh",
    "wof:placetype":"venue"
},
  "geometry": {"coordinates":[6.332575,51.248569],"type":"Point"}
}