{
  "type": "Feature",
  "properties": {
    "iso:country":"DE",
    "sg:address":"Oberweg 1a",
    "sg:city":"Bensheim",
    "sg:phone":"+49 6251/77795",
    "sg:postcode":"64625",
    "sg:province":"Hessen",
    "wof:name":"Gem\u00dc Gebr. M\u00fcller Apparatebau Gmbh & Co. Kg",
    "wof:placetype":"venue"
},
  "geometry": {"coordinates":[8.622378,49.681973],"type":"Point"}
}