{
  "type": "Feature",
  "properties": {
    "iso:country":"DE",
    "sg:address":"S\u00fcntelring 29",
    "sg:city":"Belm",
    "sg:phone":"+49 5406/9535",
    "sg:postcode":"49191",
    "sg:province":"Niedersachsen",
    "wof:name":"E. Und W. Sommer",
    "wof:placetype":"venue"
},
  "geometry": {"coordinates":[8.155863,52.35051],"type":"Point"}
}