{
  "type": "Feature",
  "properties": {
    "iso:country":"DE",
    "sg:address":"Krumme Str. 6",
    "sg:city":"Ludwigslust",
    "sg:phone":"+49 3874/21205",
    "sg:postcode":"19288",
    "sg:province":"Mecklenburg-Vorpommern",
    "wof:name":"Arnd Schmidt Steurberater",
    "wof:placetype":"venue"
},
  "geometry": {"coordinates":[11.4951381683,53.3320884705],"type":"Point"}
}