{
  "type": "Feature",
  "properties": {
    "iso:country":"DE",
    "sg:address":"Am Bugapark 60",
    "sg:city":"Gelsenkirchen",
    "sg:phone":"+49 209/5083122",
    "sg:postcode":"45899",
    "sg:province":"Nordrhein-Westfalen",
    "wof:name":"Sparkling Kr\u00e4mer Gmbh",
    "wof:placetype":"venue"
},
  "geometry": {"coordinates":[7.028434,51.525852],"type":"Point"}
}