{
  "type": "Feature",
  "properties": {
    "iso:country":"DE",
    "sg:address":"Lichtenberger Str. 24",
    "sg:city":"Rheinau",
    "sg:phone":"+49 7844/1481",
    "sg:postcode":"77866",
    "sg:province":"Baden-W\u00fcrttemberg",
    "wof:name":"Theo Assmus",
    "wof:placetype":"venue"
},
  "geometry": {"coordinates":[7.9368247986,48.6529998779],"type":"Point"}
}