{
  "type": "Feature",
  "properties": {
    "iso:country":"DE",
    "sg:address":"Siemensstr. 21",
    "sg:city":"Bad Homburg",
    "sg:phone":"+49 6172/8050",
    "sg:postcode":"61352",
    "sg:province":"Hessen",
    "wof:name":"Ppd Management Gmbh",
    "wof:placetype":"venue"
},
  "geometry": {"coordinates":[8.615981,50.217129],"type":"Point"}
}