{
  "type": "Feature",
  "properties": {
    "iso:country":"DE",
    "sg:address":"Harksheider Weg 81",
    "sg:city":"Quickborn",
    "sg:phone":"+49 4106/82350",
    "sg:postcode":"25451",
    "sg:province":"Schleswig-Holstein",
    "wof:name":"Marion Rodde-wirbals Heilpraktikerin",
    "wof:placetype":"venue"
},
  "geometry": {"coordinates":[9.911397934,53.7281455994],"type":"Point"}
}