{
  "type": "Feature",
  "properties": {
    "iso:country":"DE",
    "sg:address":"F\u00fcrstenstr. 3",
    "sg:city":"Saarbr\u00fccken",
    "sg:phone":"+49 681/9387100",
    "sg:postcode":"66111",
    "sg:province":"Saarland",
    "wof:name":"Jan Christians Rechtsanwalt",
    "wof:placetype":"venue"
},
  "geometry": {"coordinates":[6.994931221,49.2331581116],"type":"Point"}
}