{
  "type": "Feature",
  "properties": {
    "iso:country":"DE",
    "sg:address":"Sonnenstr. 4",
    "sg:city":"Pfaffenhofen",
    "sg:phone":"+49 8441/6033",
    "sg:postcode":"85276",
    "sg:province":"Bayern",
    "wof:name":"Ludwig Hirschberger Gmbh",
    "wof:placetype":"venue"
},
  "geometry": {"coordinates":[11.5066213608,48.5292739868],"type":"Point"}
}