{
  "type": "Feature",
  "properties": {
    "iso:country":"DE",
    "sg:address":"Asmussenstr. 42",
    "sg:city":"Husum",
    "sg:phone":"+49 4841/2278",
    "sg:postcode":"25813",
    "sg:province":"Schleswig-Holstein",
    "wof:name":"Harry Kr\u00e4mer",
    "wof:placetype":"venue"
},
  "geometry": {"coordinates":[9.0538158417,54.4791374207],"type":"Point"}
}