{
  "type": "Feature",
  "properties": {
    "iso:country":"DE",
    "sg:address":"Uerdinger Str. 134-142",
    "sg:city":"Krefeld",
    "sg:phone":"+49 2151/22223",
    "sg:postcode":"47799",
    "sg:province":"Nordrhein-Westfalen",
    "wof:name":"M\u00f6belhaus Skandinavia",
    "wof:placetype":"venue"
},
  "geometry": {"coordinates":[6.580053,51.33709],"type":"Point"}
}