{
  "type": "Feature",
  "properties": {
    "iso:country":"DE",
    "sg:address":"T\u00f6lzer Str. 3",
    "sg:city":"Unterhaching",
    "sg:phone":"+49 89/61501796",
    "sg:postcode":"82008",
    "sg:province":"Bayern",
    "wof:name":"R. Schaller",
    "wof:placetype":"venue"
},
  "geometry": {"coordinates":[11.6195735931,48.0563774109],"type":"Point"}
}