{
  "type": "Feature",
  "properties": {
    "iso:country":"DE",
    "sg:address":"Otterbacher Str. 2",
    "sg:city":"Schw\u00e4bisch Hall",
    "sg:phone":"+49 7907/2568",
    "sg:postcode":"74523",
    "sg:province":"Baden-W\u00fcrttemberg",
    "wof:name":"Gerhard Rupp",
    "wof:placetype":"venue"
},
  "geometry": {"coordinates":[9.8164548874,49.1222343445],"type":"Point"}
}