{
  "type": "Feature",
  "properties": {
    "iso:country":"DE",
    "sg:address":"Rappoltweg 9",
    "sg:city":"Hamburg",
    "sg:phone":"+49 40/7383571",
    "sg:postcode":"21031",
    "sg:province":"Hamburg",
    "wof:name":"Saxonia-apotheke",
    "wof:placetype":"venue"
},
  "geometry": {"coordinates":[10.197643,53.510113],"type":"Point"}
}