{
  "type": "Feature",
  "properties": {
    "iso:country":"DE",
    "sg:address":"Siegelsdorfer Str. 44",
    "sg:city":"F\u00fcrth",
    "sg:phone":"+49 911/756020",
    "sg:postcode":"90768",
    "sg:province":"Bayern",
    "wof:name":"Evenord Bank Einkaufs- Und Verwertungsgenossenschaft Der",
    "wof:placetype":"venue"
},
  "geometry": {"coordinates":[10.919679,49.495258],"type":"Point"}
}