{
  "type": "Feature",
  "properties": {
    "iso:country":"DE",
    "sg:address":"Feldstr. 13",
    "sg:city":"Erlangen",
    "sg:phone":"+49 9131/898911",
    "sg:postcode":"91052",
    "sg:province":"Bayern",
    "wof:name":"Katrin Baumg\u00e4rtel",
    "wof:placetype":"venue"
},
  "geometry": {"coordinates":[11.017385,49.595692],"type":"Point"}
}