{
  "type": "Feature",
  "properties": {
    "iso:country":"DE",
    "sg:address":"Dorfstr. 97",
    "sg:city":"Elmstein",
    "sg:phone":"+49 6328/252",
    "sg:postcode":"67471",
    "sg:province":"Rheinland-Pfalz",
    "wof:name":"Hotel B. Und W. Steigert",
    "wof:placetype":"venue"
},
  "geometry": {"coordinates":[7.9147157669,49.3321418762],"type":"Point"}
}