{
  "type": "Feature",
  "properties": {
    "iso:country":"DE",
    "sg:address":"Am Steigfeld 3",
    "sg:city":"Hollenbach",
    "sg:phone":"+49 8257/2126",
    "sg:postcode":"86568",
    "sg:province":"Bayern",
    "wof:name":"Engelschalk",
    "wof:placetype":"venue"
},
  "geometry": {"coordinates":[11.0925264359,48.4913291931],"type":"Point"}
}