{
  "type": "Feature",
  "properties": {
    "iso:country":"DE",
    "sg:address":"Silberburgstr. 49",
    "sg:city":"Hechingen",
    "sg:phone":"+49 7471/621543",
    "sg:postcode":"72379",
    "sg:province":"Baden-W\u00fcrttemberg",
    "wof:name":"Hueftluxation",
    "wof:placetype":"venue"
},
  "geometry": {"coordinates":[8.96512,48.345894],"type":"Point"}
}