{
  "type": "Feature",
  "properties": {
    "iso:country":"DE",
    "sg:address":"Liebigstr. 92",
    "sg:city":"Hamburg",
    "sg:phone":"+49 4954/727174",
    "sg:postcode":"22113",
    "sg:province":"Schleswig-Holstein",
    "wof:name":"Heinrich Ellebrecht Transport Gmbh & Co. Kg",
    "wof:placetype":"venue"
},
  "geometry": {"coordinates":[8.4210062027,52.3141708374],"type":"Point"}
}