{
  "type": "Feature",
  "properties": {
    "iso:country":"DE",
    "sg:address":"Rosenstr. 37",
    "sg:city":"Ravensburg",
    "sg:phone":"+49 751/33848",
    "sg:postcode":"88212",
    "sg:province":"Baden-W\u00fcrttemberg",
    "wof:name":"Infracommun Bauland- Erschlie\u00dfung Gmbh",
    "wof:placetype":"venue"
},
  "geometry": {"coordinates":[9.612756,47.783871],"type":"Point"}
}