{
  "type": "Feature",
  "properties": {
    "iso:country":"DE",
    "sg:address":"Osdorfer Landstr. 307",
    "sg:city":"Hamburg",
    "sg:phone":"+49 40/872804",
    "sg:postcode":"22589",
    "sg:province":"Hamburg",
    "wof:name":"Wolfgang M\u00f6ller Gmbh",
    "wof:placetype":"venue"
},
  "geometry": {"coordinates":[9.835511,53.573963],"type":"Point"}
}