{
  "type": "Feature",
  "properties": {
    "iso:country":"DE",
    "sg:address":"Friedrich-List-Allee 16",
    "sg:city":"Wegberg",
    "sg:postcode":"41844",
    "sg:province":"Nordrhein-Westfalen",
    "wof:name":"Vdt-impex Gmbh",
    "wof:placetype":"venue"
},
  "geometry": {"coordinates":[6.217454,51.121487],"type":"Point"}
}