{
  "type": "Feature",
  "properties": {
    "iso:country":"DE",
    "sg:address":"Spreeler Weg 122",
    "sg:city":"Ennepetal",
    "sg:phone":"+49 202/611425",
    "sg:postcode":"58256",
    "sg:province":"Nordrhein-Westfalen",
    "wof:name":"W. Rogalski",
    "wof:placetype":"venue"
},
  "geometry": {"coordinates":[7.325727,51.249569],"type":"Point"}
}