{
  "type": "Feature",
  "properties": {
    "iso:country":"DE",
    "sg:address":"Im Hungerborn 13-15",
    "sg:city":"Bingen",
    "sg:phone":"+49 6721/990870",
    "sg:postcode":"55411",
    "sg:province":"Rheinland-Pfalz",
    "wof:name":"Dr. Utz Neef",
    "wof:placetype":"venue"
},
  "geometry": {"coordinates":[7.907271862,49.965057373],"type":"Point"}
}