{
  "type": "Feature",
  "properties": {
    "iso:country":"DE",
    "sg:address":"Hauptstr. 42 c",
    "sg:city":"Bielefeld",
    "sg:phone":"+49 521/411304",
    "sg:postcode":"33647",
    "sg:province":"Nordrhein-Westfalen",
    "wof:name":"Cafe Am Kirchplatz",
    "wof:placetype":"venue"
},
  "geometry": {"coordinates":[8.514383,51.98814],"type":"Point"}
}