{
  "type": "Feature",
  "properties": {
    "iso:country":"DE",
    "sg:address":"Stukenbrocker Str. 15",
    "sg:city":"Augustdorf",
    "sg:postcode":"32832",
    "sg:province":"Nordrhein-Westfalen",
    "wof:name":"Aldi Gmbh & Co. Kg",
    "wof:placetype":"venue"
},
  "geometry": {"coordinates":[8.7263536453,51.9081420898],"type":"Point"}
}