{
  "type": "Feature",
  "properties": {
    "iso:country":"DE",
    "sg:address":"K\u00e4the-Kollwitz-Str. 6",
    "sg:city":"Grimma",
    "sg:phone":"+49 3437/919701",
    "sg:postcode":"04668",
    "sg:province":"Sachsen",
    "wof:name":"Annett Voigt Praxis F\u00fcr Physiotherapie",
    "wof:placetype":"venue"
},
  "geometry": {"coordinates":[12.7221422195,51.2379493713],"type":"Point"}
}