{
  "type": "Feature",
  "properties": {
    "iso:country":"DE",
    "sg:address":"Bitburger Str. 3",
    "sg:city":"Steinborn",
    "sg:phone":"+49 6567/260",
    "sg:postcode":"54655",
    "sg:province":"Rheinland-Pfalz",
    "wof:name":"Peter Ludowicy",
    "wof:placetype":"venue"
},
  "geometry": {"coordinates":[6.630982,50.07029],"type":"Point"}
}