{
  "type": "Feature",
  "properties": {
    "iso:country":"DE",
    "sg:address":"Ostweg 37",
    "sg:city":"Oldenburg",
    "sg:phone":"+49 441/204200",
    "sg:postcode":"26135",
    "sg:province":"Niedersachsen",
    "wof:name":"Walter Barkemeyer Wettannahme",
    "wof:placetype":"venue"
},
  "geometry": {"coordinates":[8.254935,53.125477],"type":"Point"}
}