{
  "type": "Feature",
  "properties": {
    "iso:country":"DE",
    "sg:address":"Max-Schuster-Str. 1",
    "sg:city":"Dirlewang",
    "sg:phone":"+49 8267/511",
    "sg:postcode":"87742",
    "sg:province":"Bayern",
    "wof:name":"W. Kling Ingenieur Gmbh",
    "wof:placetype":"venue"
},
  "geometry": {"coordinates":[10.5067148209,48.0043869019],"type":"Point"}
}