{
  "type": "Feature",
  "properties": {
    "iso:country":"DE",
    "sg:address":"Engelsh\u00f6he 35",
    "sg:city":"Wuppertal",
    "sg:phone":"+49 202/730796",
    "sg:postcode":"42329",
    "sg:province":"Nordrhein-Westfalen",
    "wof:name":"Kleinwohnungsbau Gmbh & Co. Kg",
    "wof:placetype":"venue"
},
  "geometry": {"coordinates":[7.0614171028,51.2176437378],"type":"Point"}
}