{
  "type": "Feature",
  "properties": {
    "iso:country":"DE",
    "sg:address":"Hauptstr. 9",
    "sg:city":"Idar-Oberstein",
    "sg:phone":"+49 6781/43387",
    "sg:postcode":"55743",
    "sg:province":"Rheinland-Pfalz",
    "wof:name":"B\u00fccherei Der Evangelischen Kirchengemeinde",
    "wof:placetype":"venue"
},
  "geometry": {"coordinates":[7.297166,49.723648],"type":"Point"}
}