{
  "type": "Feature",
  "properties": {
    "iso:country":"DE",
    "sg:address":"Mittelweg 5",
    "sg:city":"Schm\u00f6len",
    "sg:postcode":"04828",
    "sg:province":"Sachsen",
    "wof:name":"Hkw Wohn- Und Gewerbebau Gmbh",
    "wof:placetype":"venue"
},
  "geometry": {"coordinates":[12.719328,51.350609],"type":"Point"}
}