{
  "type": "Feature",
  "properties": {
    "iso:country":"DE",
    "sg:address":"Hans-Bredow-Str. 19",
    "sg:city":"Bremen",
    "sg:phone":"+49 421/488251",
    "sg:postcode":"28307",
    "sg:province":"Bremen",
    "wof:name":"Kostelidis Cafe Gmbh",
    "wof:placetype":"venue"
},
  "geometry": {"coordinates":[8.960342,53.049149],"type":"Point"}
}