{
  "type": "Feature",
  "properties": {
    "iso:country":"DE",
    "sg:address":"Sachsenring 146",
    "sg:city":"Essen",
    "sg:postcode":"45279",
    "sg:province":"Nordrhein-Westfalen",
    "wof:name":"Com2 You",
    "wof:placetype":"venue"
},
  "geometry": {"coordinates":[7.1135702133,51.4472846985],"type":"Point"}
}