{
  "type": "Feature",
  "properties": {
    "iso:country":"DE",
    "sg:address":"Parkstr. 42",
    "sg:city":"Schiffweiler",
    "sg:phone":"+49 6821/67065",
    "sg:postcode":"66578",
    "sg:province":"Saarland",
    "wof:name":"Klaus Quint",
    "wof:placetype":"venue"
},
  "geometry": {"coordinates":[7.1227412224,49.3705024719],"type":"Point"}
}