{
  "type": "Feature",
  "properties": {
    "iso:country":"DE",
    "sg:address":"Gehringstr. 38",
    "sg:city":"Berlin",
    "sg:phone":"+49 30/96205060",
    "sg:postcode":"13088",
    "sg:province":"Berlin",
    "wof:name":"Bkh-keramik-handels- Agentur Gmbh",
    "wof:placetype":"venue"
},
  "geometry": {"coordinates":[13.4714107513,52.561668396],"type":"Point"}
}