{
  "type": "Feature",
  "properties": {
    "iso:country":"DE",
    "sg:address":"Richard-Strauss-Str. 16",
    "sg:city":"Berg",
    "sg:phone":"+49 751/23877",
    "sg:postcode":"88276",
    "sg:province":"Baden-W\u00fcrttemberg",
    "wof:name":"Engelbert Rundel",
    "wof:placetype":"venue"
},
  "geometry": {"coordinates":[9.6008815765,47.8100318909],"type":"Point"}
}