{
  "type": "Feature",
  "properties": {
    "iso:country":"DE",
    "sg:address":"Rolandskoppel 2",
    "sg:city":"Westerr\u00f6nfeld",
    "sg:postcode":"24784",
    "sg:province":"Schleswig-Holstein",
    "wof:name":"Aldi Gmbh & Co. Kg",
    "wof:placetype":"venue"
},
  "geometry": {"coordinates":[9.6586818695,54.2753448486],"type":"Point"}
}