{
  "type": "Feature",
  "properties": {
    "iso:country":"DE",
    "sg:address":"Kemnater Str. 2",
    "sg:city":"Kaufbeuren",
    "sg:phone":"+49 8341/2441",
    "sg:postcode":"87600",
    "sg:province":"Bayern",
    "wof:name":"Adlerkeller",
    "wof:placetype":"venue"
},
  "geometry": {"coordinates":[10.6151399612,47.8819618225],"type":"Point"}
}