{
  "type": "Feature",
  "properties": {
    "iso:country":"DE",
    "sg:address":"Am Burgberg 7",
    "sg:city":"Dassel",
    "sg:postcode":"37586",
    "sg:province":"Niedersachsen",
    "wof:name":"Trustor Automotive Holding Gmbh",
    "wof:placetype":"venue"
},
  "geometry": {"coordinates":[9.699321,51.792957],"type":"Point"}
}