{
  "type": "Feature",
  "properties": {
    "iso:country":"DE",
    "sg:address":"Breitenlohe 1",
    "sg:city":"Schwaig",
    "sg:phone":"+49 911/995800",
    "sg:postcode":"90571",
    "sg:province":"Bayern",
    "wof:name":"Arcosys Arzt-computer-service Gmbh",
    "wof:placetype":"venue"
},
  "geometry": {"coordinates":[11.196472168,49.482624054],"type":"Point"}
}