{
  "type": "Feature",
  "properties": {
    "iso:country":"DE",
    "sg:address":"M\u00fchlweg 35",
    "sg:city":"Oberpframmern",
    "sg:phone":"+49 8093/4940",
    "sg:postcode":"85667",
    "sg:province":"Bayern",
    "wof:name":"R. Huber",
    "wof:placetype":"venue"
},
  "geometry": {"coordinates":[11.815901,48.025051],"type":"Point"}
}