{
  "type": "Feature",
  "properties": {
    "iso:country":"DE",
    "sg:address":"Wiesenstr. 17",
    "sg:city":"Attendorn",
    "sg:phone":"+49 2722/5632",
    "sg:postcode":"57439",
    "sg:province":"Nordrhein-Westfalen",
    "wof:name":"I. Henneke",
    "wof:placetype":"venue"
},
  "geometry": {"coordinates":[7.9134750366,51.1436843872],"type":"Point"}
}