{
  "type": "Feature",
  "properties": {
    "iso:country":"DE",
    "sg:address":"Feldschmiede 29",
    "sg:city":"Itzehoe",
    "sg:phone":"+49 4821/63100",
    "sg:postcode":"25524",
    "sg:province":"Schleswig-Holstein",
    "wof:name":"Mobil-com-shop Itzehoe",
    "wof:placetype":"venue"
},
  "geometry": {"coordinates":[9.5168151855,53.9247436523],"type":"Point"}
}