{
  "type": "Feature",
  "properties": {
    "iso:country":"DE",
    "sg:address":"T\u00f6nisvorster Str. 12",
    "sg:city":"Grefrath",
    "sg:phone":"+49 2158/6192",
    "sg:postcode":"47929",
    "sg:province":"Nordrhein-Westfalen",
    "wof:name":"Odysseus",
    "wof:placetype":"venue"
},
  "geometry": {"coordinates":[6.3817458153,51.3262290955],"type":"Point"}
}