{
  "type": "Feature",
  "properties": {
    "iso:country":"DE",
    "sg:address":"Friedrich-Engels-Str. 20",
    "sg:city":"Schwarzenberg",
    "sg:phone":"+49 3774/23616",
    "sg:postcode":"08340",
    "sg:province":"Sachsen",
    "wof:name":"Charmant-friseur Gmbh",
    "wof:placetype":"venue"
},
  "geometry": {"coordinates":[12.7601108551,50.5541114807],"type":"Point"}
}