{
  "type": "Feature",
  "properties": {
    "iso:country":"DE",
    "sg:address":"Grandweg 9",
    "sg:city":"Soest",
    "sg:phone":"+49 2921/16380",
    "sg:postcode":"59494",
    "sg:province":"Nordrhein-Westfalen",
    "wof:name":"Pembe Keskin",
    "wof:placetype":"venue"
},
  "geometry": {"coordinates":[8.1091709137,51.5705184937],"type":"Point"}
}