{
  "type": "Feature",
  "properties": {
    "iso:country":"DE",
    "sg:address":"Am Tunnel 4",
    "sg:city":"Nachrodt-Wiblingwerde",
    "sg:phone":"+49 2352/320018",
    "sg:postcode":"58769",
    "sg:province":"Nordrhein-Westfalen",
    "wof:name":"H.-d. H\u00f6wt",
    "wof:placetype":"venue"
},
  "geometry": {"coordinates":[7.600828,51.325016],"type":"Point"}
}