{
  "type": "Feature",
  "properties": {
    "iso:country":"DE",
    "sg:address":"Sonnenstr. 18",
    "sg:city":"Hohenpei\u00dfenberg",
    "sg:phone":"+49 8805/329",
    "sg:postcode":"82383",
    "sg:province":"Bayern",
    "wof:name":"Ev. Luth. Pfarramt",
    "wof:placetype":"venue"
},
  "geometry": {"coordinates":[11.0109939575,47.7938079834],"type":"Point"}
}