{
  "type": "Feature",
  "properties": {
    "iso:country":"DE",
    "sg:address":"Friedrichstr. 62",
    "sg:city":"Sch\u00f6neck",
    "sg:phone":"+49 6187/5942",
    "sg:postcode":"61137",
    "sg:province":"Hessen",
    "wof:name":"Rainer Schiebener Architekt",
    "wof:placetype":"venue"
},
  "geometry": {"coordinates":[8.831976,50.218182],"type":"Point"}
}