{
  "type": "Feature",
  "properties": {
    "iso:country":"DE",
    "sg:address":"Braacher Str. 14",
    "sg:city":"Rotenburg",
    "sg:phone":"+49 6623/41313",
    "sg:postcode":"36199",
    "sg:province":"Hessen",
    "wof:name":"Fulmin Tankstelle",
    "wof:placetype":"venue"
},
  "geometry": {"coordinates":[9.7180166245,51.0009727478],"type":"Point"}
}