{
  "type": "Feature",
  "properties": {
    "iso:country":"DE",
    "sg:address":"Wiesenweg 1",
    "sg:city":"Klipphausen",
    "sg:phone":"+49 351/4537871",
    "sg:postcode":"01665",
    "sg:province":"Sachsen",
    "wof:name":"Manfred Maurer",
    "wof:placetype":"venue"
},
  "geometry": {"coordinates":[13.591137886,51.0878944397],"type":"Point"}
}