{
  "type": "Feature",
  "properties": {
    "iso:country":"DE",
    "sg:address":"Steinweg 39",
    "sg:city":"Eschershausen",
    "sg:phone":"+49 5534/3798",
    "sg:postcode":"37632",
    "sg:province":"Niedersachsen",
    "wof:name":"Klinke Und Kolar",
    "wof:placetype":"venue"
},
  "geometry": {"coordinates":[9.639289856,51.9269294739],"type":"Point"}
}