{
  "type": "Feature",
  "properties": {
    "iso:country":"DE",
    "sg:address":"Am Kurpark 3",
    "sg:city":"Staffelstein",
    "sg:phone":"+49 9573/5151",
    "sg:postcode":"96231",
    "sg:province":"Bayern",
    "wof:name":"Hallenbad",
    "wof:placetype":"venue"
},
  "geometry": {"coordinates":[10.9927034378,50.1084747314],"type":"Point"}
}