{
  "type": "Feature",
  "properties": {
    "iso:country":"DE",
    "sg:address":"Vogelsanger Str. 296",
    "sg:city":"K\u00f6ln",
    "sg:phone":"+49 221/3991520",
    "sg:postcode":"50825",
    "sg:province":"Nordrhein-Westfalen",
    "wof:name":"R. T\u00fccks Rechtsanwalt",
    "wof:placetype":"venue"
},
  "geometry": {"coordinates":[6.9014868736,50.9523124695],"type":"Point"}
}