{
  "type": "Feature",
  "properties": {
    "iso:country":"DE",
    "sg:address":"Wertstr. 30",
    "sg:city":"Wendlingen",
    "sg:phone":"+49 7024/983120",
    "sg:postcode":"73240",
    "sg:province":"Baden-W\u00fcrttemberg",
    "wof:name":"C. F. Scheer Gmbh & Co. Kg",
    "wof:placetype":"venue"
},
  "geometry": {"coordinates":[9.361588,48.669811],"type":"Point"}
}