{
  "type": "Feature",
  "properties": {
    "iso:country":"DE",
    "sg:address":"Berkenb\u00fcscher Str. 2",
    "sg:city":"Stemwede",
    "sg:postcode":"32351",
    "sg:province":"Nordrhein-Westfalen",
    "wof:name":"S. Vette Und E. M\u00f6ller",
    "wof:placetype":"venue"
},
  "geometry": {"coordinates":[8.4845762253,52.443939209],"type":"Point"}
}