{
  "type": "Feature",
  "properties": {
    "iso:country":"DE",
    "sg:address":"Fuldastr. 13",
    "sg:city":"Riedstadt",
    "sg:phone":"+49 6158/71274",
    "sg:postcode":"64560",
    "sg:province":"Hessen",
    "wof:name":"D. Keil",
    "wof:placetype":"venue"
},
  "geometry": {"coordinates":[8.4945230484,49.8506393433],"type":"Point"}
}