{
  "type": "Feature",
  "properties": {
    "iso:country":"DE",
    "sg:address":"Sch\u00f6nberger Str. 22",
    "sg:city":"Kiel",
    "sg:phone":"+49 431/728657",
    "sg:postcode":"24148",
    "sg:province":"Schleswig-Holstein",
    "wof:name":"Tanzlokal-restaurant Horoskop",
    "wof:placetype":"venue"
},
  "geometry": {"coordinates":[10.1847066879,54.3261604309],"type":"Point"}
}