{
  "type": "Feature",
  "properties": {
    "iso:country":"DE",
    "sg:address":"Montplanetstr. 13",
    "sg:city":"Kamp-Lintfort",
    "sg:phone":"+49 2842/10684",
    "sg:postcode":"47475",
    "sg:province":"Nordrhein-Westfalen",
    "wof:name":"Fr.-w. M\u00fcller-jahn Architekt",
    "wof:placetype":"venue"
},
  "geometry": {"coordinates":[6.551135,51.501297],"type":"Point"}
}