{
  "type": "Feature",
  "properties": {
    "iso:country":"DE",
    "sg:address":"An der Altm\u00fchl 7",
    "sg:city":"Riedenburg",
    "sg:phone":"+49 9442/1274",
    "sg:postcode":"93339",
    "sg:province":"Bayern",
    "wof:name":"Georg Roider",
    "wof:placetype":"venue"
},
  "geometry": {"coordinates":[11.684407,48.962791],"type":"Point"}
}