{
  "type": "Feature",
  "properties": {
    "iso:country":"DE",
    "sg:address":"In den Billen 23",
    "sg:city":"Elsdorf",
    "sg:phone":"+49 2274/81918",
    "sg:postcode":"50189",
    "sg:province":"Nordrhein-Westfalen",
    "wof:name":"Karin Imgrund Steuerberaterin",
    "wof:placetype":"venue"
},
  "geometry": {"coordinates":[6.55707407,50.9440231323],"type":"Point"}
}