{
  "type": "Feature",
  "properties": {
    "iso:country":"DE",
    "sg:address":"Tauberstr. 11",
    "sg:city":"Lauda-K\u00f6nigshofen",
    "sg:phone":"+49 9343/62220",
    "sg:postcode":"97922",
    "sg:province":"Baden-W\u00fcrttemberg",
    "wof:name":"Herm Mineral\u00f6lvertrieb Verwaltungs Gmbh",
    "wof:placetype":"venue"
},
  "geometry": {"coordinates":[9.7083110809,49.5681648254],"type":"Point"}
}