{
  "type": "Feature",
  "properties": {
    "iso:country":"DE",
    "sg:address":"Bornweg 88",
    "sg:city":"M\u00fchlheim",
    "sg:phone":"+49 6108/700330",
    "sg:postcode":"63165",
    "sg:province":"Hessen",
    "wof:name":"Norbert Ohlig Architekt",
    "wof:placetype":"venue"
},
  "geometry": {"coordinates":[8.862458,50.124043],"type":"Point"}
}