{
  "type": "Feature",
  "properties": {
    "iso:country":"DE",
    "sg:address":"Bahnhofstr. 2",
    "sg:city":"Heilbad Heiligenstadt",
    "sg:phone":"+49 3606/612253",
    "sg:postcode":"37308",
    "sg:province":"Th\u00fcringen",
    "wof:name":"Hotel Zur Traube",
    "wof:placetype":"venue"
},
  "geometry": {"coordinates":[10.1334295273,51.3809165955],"type":"Point"}
}