{
  "type": "Feature",
  "properties": {
    "iso:country":"DE",
    "sg:address":"Wilhelmplatz 9",
    "sg:city":"Kiel",
    "sg:postcode":"24116",
    "sg:province":"Schleswig-Holstein",
    "wof:name":"Raudy Gmbh Immobilien",
    "wof:placetype":"venue"
},
  "geometry": {"coordinates":[10.1192913055,54.3240242004],"type":"Point"}
}