{
  "type": "Feature",
  "properties": {
    "iso:country":"DE",
    "sg:address":"Hauptstr 77",
    "sg:city":"Herrstein",
    "sg:phone":"+49 6785/892",
    "sg:postcode":"55756",
    "sg:province":"Rheinland-Pfalz",
    "wof:name":"Wendel Schornsteintechnik Gmbh",
    "wof:placetype":"venue"
},
  "geometry": {"coordinates":[7.334596,49.783474],"type":"Point"}
}