{
  "type": "Feature",
  "properties": {
    "iso:country":"DE",
    "sg:address":"Schlemminer Str.",
    "sg:city":"Trinwillershagen",
    "sg:postcode":"18320",
    "sg:province":"Mecklenburg-Vorpommern",
    "wof:name":"Raiffeisen-handels- Genossenschaft Eg",
    "wof:placetype":"venue"
},
  "geometry": {"coordinates":[12.6241064072,54.2547683716],"type":"Point"}
}