{
  "type": "Feature",
  "properties": {
    "iso:country":"DE",
    "sg:address":"Johannes-Girmes-Str. 126",
    "sg:city":"Grefrath",
    "sg:phone":"+49 2158/5785",
    "sg:postcode":"47929",
    "sg:province":"Nordrhein-Westfalen",
    "wof:name":"Heinrich Heyer",
    "wof:placetype":"venue"
},
  "geometry": {"coordinates":[6.371927,51.334965],"type":"Point"}
}