{
  "type": "Feature",
  "properties": {
    "iso:country":"DE",
    "sg:address":"Bahnhofstr 10",
    "sg:city":"Bautzen",
    "sg:phone":"+49 3591/304972",
    "sg:postcode":"02625",
    "sg:province":"Sachsen",
    "wof:name":"Agentur F\u00fcr Sicherheit Und Dienstleistung Gbr",
    "wof:placetype":"venue"
},
  "geometry": {"coordinates":[14.429091,51.175301],"type":"Point"}
}