{
  "type": "Feature",
  "properties": {
    "iso:country":"DE",
    "sg:address":"Stettenklingenhof 1",
    "sg:city":"Pfaffenhofen",
    "sg:phone":"+49 7046/9880",
    "sg:postcode":"74397",
    "sg:province":"Baden-W\u00fcrttemberg",
    "wof:name":"A & S Altholzverwertung Beteiligungs- Gmbh",
    "wof:placetype":"venue"
},
  "geometry": {"coordinates":[8.964267,49.056244],"type":"Point"}
}