{
  "type": "Feature",
  "properties": {
    "iso:country":"DE",
    "sg:address":"Pingsdorfer Str. 7",
    "sg:city":"Br\u00fchl",
    "sg:phone":"+49 2232/42380",
    "sg:postcode":"50321",
    "sg:province":"Nordrhein-Westfalen",
    "wof:name":"Luise K\u00f6nig",
    "wof:placetype":"venue"
},
  "geometry": {"coordinates":[6.899806,50.824287],"type":"Point"}
}