{
  "type": "Feature",
  "properties": {
    "iso:country":"DE",
    "sg:address":"B\u00e4renweg 31",
    "sg:city":"Karlsruhe",
    "sg:phone":"+49 721/788855",
    "sg:postcode":"76149",
    "sg:province":"Baden-W\u00fcrttemberg",
    "wof:name":"Reise Studio Neureut",
    "wof:placetype":"venue"
},
  "geometry": {"coordinates":[8.3804636002,49.0458335876],"type":"Point"}
}