{
  "type": "Feature",
  "properties": {
    "iso:country":"DE",
    "sg:address":"Filder Str. 84",
    "sg:city":"Moers",
    "sg:phone":"+49 2841/26422",
    "sg:postcode":"47441",
    "sg:province":"Nordrhein-Westfalen",
    "wof:name":"M. Maywald",
    "wof:placetype":"venue"
},
  "geometry": {"coordinates":[6.625332,51.444084],"type":"Point"}
}