{
  "type": "Feature",
  "properties": {
    "iso:country":"DE",
    "sg:address":"Tulpenweg 9",
    "sg:city":"L\u00f6chgau",
    "sg:phone":"+49 7143/7327",
    "sg:postcode":"74369",
    "sg:province":"Baden-W\u00fcrttemberg",
    "wof:name":"Alfred Scheuler",
    "wof:placetype":"venue"
},
  "geometry": {"coordinates":[9.108518,48.998577],"type":"Point"}
}