{
  "type": "Feature",
  "properties": {
    "iso:country":"DE",
    "sg:address":"Kufsteiner Str. 21",
    "sg:city":"Bad Feilnbach",
    "sg:phone":"+49 8066/263",
    "sg:postcode":"83075",
    "sg:province":"Bayern",
    "wof:name":"B\u00e4ckerei Konditorei Cafe Sebastian Hirsch Gmbh",
    "wof:placetype":"venue"
},
  "geometry": {"coordinates":[12.006637,47.773952],"type":"Point"}
}