{
  "type": "Feature",
  "properties": {
    "iso:country":"DE",
    "sg:address":"Ahrstr. 5-13",
    "sg:city":"Solingen",
    "sg:phone":"+49 212/2331203",
    "sg:postcode":"42697",
    "sg:province":"Nordrhein-Westfalen",
    "wof:name":"Informa Internationale Wirt- Schaftsauskunftei Gmbh",
    "wof:placetype":"venue"
},
  "geometry": {"coordinates":[6.999963,51.157944],"type":"Point"}
}