{
  "type": "Feature",
  "properties": {
    "iso:country":"DE",
    "sg:address":"Gro\u00dfe Rittergasse 41-43",
    "sg:city":"Frankfurt",
    "sg:phone":"+49 69/614336",
    "sg:postcode":"60594",
    "sg:province":"Hessen",
    "wof:name":"Spritzenhaus Hotel-gast- St\u00e4tten-betriebs- Und",
    "wof:placetype":"venue"
},
  "geometry": {"coordinates":[8.6914520264,50.1057853699],"type":"Point"}
}