{
  "type": "Feature",
  "properties": {
    "iso:country":"DE",
    "sg:address":"Vogesenstr. 2a",
    "sg:city":"B\u00fchl",
    "sg:phone":"+49 7223/98620",
    "sg:postcode":"77815",
    "sg:province":"Baden-W\u00fcrttemberg",
    "wof:name":"Josef Zink Gmbh",
    "wof:placetype":"venue"
},
  "geometry": {"coordinates":[8.135925293,48.6953582764],"type":"Point"}
}