{
  "type": "Feature",
  "properties": {
    "iso:country":"DE",
    "sg:address":"Ostallee 35",
    "sg:city":"Trier",
    "sg:phone":"+49 651/978500",
    "sg:postcode":"54290",
    "sg:province":"Rheinland-Pfalz",
    "wof:name":"Fendel Verwaltungs-gmbh",
    "wof:placetype":"venue"
},
  "geometry": {"coordinates":[6.6470308304,49.7539710999],"type":"Point"}
}