{
  "type": "Feature",
  "properties": {
    "iso:country":"DE",
    "sg:address":"M\u00fcnchner Str. 10",
    "sg:city":"F\u00fcrstenfeldbruck",
    "sg:postcode":"82256",
    "sg:province":"Bayern",
    "wof:name":"Contrast Fashion Style Gmbh",
    "wof:placetype":"venue"
},
  "geometry": {"coordinates":[11.258682251,48.1762733459],"type":"Point"}
}