{
  "type": "Feature",
  "properties": {
    "iso:country":"DE",
    "sg:address":"R\u00f6merstr. 9",
    "sg:city":"K\u00f6ln",
    "sg:postcode":"50996",
    "sg:province":"Nordrhein-Westfalen",
    "wof:name":"Promarkta M. L. L\u00fccke Kg",
    "wof:placetype":"venue"
},
  "geometry": {"coordinates":[6.987613,50.889908],"type":"Point"}
}