{
  "type": "Feature",
  "properties": {
    "iso:country":"DE",
    "sg:address":"Eselsberg 7",
    "sg:city":"Kitzingen",
    "sg:phone":"+49 9321/6429",
    "sg:postcode":"97318",
    "sg:province":"Bayern",
    "wof:name":"Fritz Thauer Gmbh & Co. Immobilien Kg",
    "wof:placetype":"venue"
},
  "geometry": {"coordinates":[10.154773,49.741707],"type":"Point"}
}