{
  "type": "Feature",
  "properties": {
    "iso:country":"DE",
    "sg:address":"Morgensternstr. 64",
    "sg:city":"Egelsbach",
    "sg:phone":"+49 6103/45452",
    "sg:postcode":"63329",
    "sg:province":"Hessen",
    "wof:name":"Ebert Concept Gmbh",
    "wof:placetype":"venue"
},
  "geometry": {"coordinates":[8.6701135635,49.953086853],"type":"Point"}
}