{
  "type": "Feature",
  "properties": {
    "iso:country":"DE",
    "sg:address":"Wilhelmstr 62",
    "sg:city":"Wiesbaden",
    "sg:phone":"+49 611/9700990",
    "sg:postcode":"65183",
    "sg:province":"Hessen",
    "wof:name":"Nest Gmbh",
    "wof:placetype":"venue"
},
  "geometry": {"coordinates":[8.244252,50.085781],"type":"Point"}
}