{
  "type": "Feature",
  "properties": {
    "iso:country":"DE",
    "sg:address":"Marktstr. 8",
    "sg:city":"Calw",
    "sg:phone":"+49 7051/12557",
    "sg:postcode":"75365",
    "sg:province":"Baden-W\u00fcrttemberg",
    "wof:name":"M\u00f6belfabrik Wackenhut Gmbh & Co.",
    "wof:placetype":"venue"
},
  "geometry": {"coordinates":[8.739927,48.713814],"type":"Point"}
}