{
  "type": "Feature",
  "properties": {
    "iso:country":"DE",
    "sg:address":"Plantage 15",
    "sg:city":"Bremen",
    "sg:phone":"+49 421/3776790",
    "sg:postcode":"28215",
    "sg:province":"Bremen",
    "wof:name":"Erich Hennig E. K.",
    "wof:placetype":"venue"
},
  "geometry": {"coordinates":[8.8047771454,53.088886261],"type":"Point"}
}