{
  "type": "Feature",
  "properties": {
    "iso:country":"DE",
    "sg:address":"Sophienweg 3",
    "sg:city":"Meschede",
    "sg:phone":"+49 291/82409",
    "sg:postcode":"59872",
    "sg:province":"Nordrhein-Westfalen",
    "wof:name":"D. N. S. Grafik-design",
    "wof:placetype":"venue"
},
  "geometry": {"coordinates":[8.2702989578,51.3512916565],"type":"Point"}
}