{
  "type": "Feature",
  "properties": {
    "iso:country":"DE",
    "sg:address":"Holm 8",
    "sg:city":"Tarp",
    "sg:phone":"+49 4638/1459",
    "sg:postcode":"24963",
    "sg:province":"Schleswig-Holstein",
    "wof:name":"Peter Weiss",
    "wof:placetype":"venue"
},
  "geometry": {"coordinates":[9.4035701752,54.6627883911],"type":"Point"}
}