{
  "type": "Feature",
  "properties": {
    "iso:country":"DE",
    "sg:address":"Erfstr. 38",
    "sg:city":"B\u00fcrgstadt",
    "sg:phone":"+49 9371/67623",
    "sg:postcode":"63927",
    "sg:province":"Bayern",
    "wof:name":"Siegbert Gehrlich",
    "wof:placetype":"venue"
},
  "geometry": {"coordinates":[9.2802915573,49.7057762146],"type":"Point"}
}