{
  "type": "Feature",
  "properties": {
    "iso:country":"DE",
    "sg:address":"Schwarzenberger Str. 11",
    "sg:city":"Schlettau",
    "sg:phone":"+49 3733/65127",
    "sg:postcode":"09487",
    "sg:province":"Sachsen",
    "wof:name":"J\u00fcrgen Einenkel",
    "wof:placetype":"venue"
},
  "geometry": {"coordinates":[12.9507226944,50.5578422546],"type":"Point"}
}