{
  "type": "Feature",
  "properties": {
    "iso:country":"DE",
    "sg:address":"Eresburgstr. 12",
    "sg:city":"Berlin",
    "sg:phone":"+49 30/7521012",
    "sg:postcode":"12103",
    "sg:province":"Berlin",
    "wof:name":"Isomontage Gmbh",
    "wof:placetype":"venue"
},
  "geometry": {"coordinates":[13.3720798492,52.4672088623],"type":"Point"}
}