{
  "type": "Feature",
  "properties": {
    "iso:country":"DE",
    "sg:address":"Lemgoer Str. 4",
    "sg:city":"Bielefeld",
    "sg:postcode":"33604",
    "sg:province":"Nordrhein-Westfalen",
    "wof:name":"Wl-unternehmensberatung Gmbh",
    "wof:placetype":"venue"
},
  "geometry": {"coordinates":[8.5418739319,52.0124282837],"type":"Point"}
}