{
  "type": "Feature",
  "properties": {
    "iso:country":"DE",
    "sg:address":"Rengersh\u00e4user Str.",
    "sg:city":"Bad Mergentheim",
    "sg:postcode":"97980",
    "sg:province":"Baden-W\u00fcrttemberg",
    "wof:name":"Katholisches Pfarramt St. Leonhard",
    "wof:placetype":"venue"
},
  "geometry": {"coordinates":[9.7536430359,49.4482154846],"type":"Point"}
}