{
  "type": "Feature",
  "properties": {
    "iso:country":"DE",
    "sg:address":"Eichenallee 47",
    "sg:city":"G\u00fctersloh",
    "sg:phone":"+49 5241/56669",
    "sg:postcode":"33332",
    "sg:province":"Nordrhein-Westfalen",
    "wof:name":"B. Sch\u00e4fertomwasen",
    "wof:placetype":"venue"
},
  "geometry": {"coordinates":[8.378704071,51.8923835754],"type":"Point"}
}