{
  "type": "Feature",
  "properties": {
    "iso:country":"DE",
    "sg:address":"Am Ostrand 2",
    "sg:city":"Cuxhaven",
    "sg:phone":"+49 4723/3216",
    "sg:postcode":"27476",
    "sg:province":"Niedersachsen",
    "wof:name":"Ursula Lange-hafert",
    "wof:placetype":"venue"
},
  "geometry": {"coordinates":[8.588665,53.836716],"type":"Point"}
}