{
  "type": "Feature",
  "properties": {
    "iso:country":"DE",
    "sg:address":"Wetzlarer Str. 5",
    "sg:city":"Wetzlar",
    "sg:phone":"+49 6441/77219",
    "sg:postcode":"35581",
    "sg:province":"Hessen",
    "wof:name":"Roland Hofmann",
    "wof:placetype":"venue"
},
  "geometry": {"coordinates":[8.575761795,50.5489311218],"type":"Point"}
}