{
  "type": "Feature",
  "properties": {
    "iso:country":"DE",
    "sg:address":"Vahrenwalder Str. 193 a",
    "sg:city":"Hannover",
    "sg:phone":"+49 511/3503146",
    "sg:postcode":"30165",
    "sg:province":"Niedersachsen",
    "wof:name":"Gom Automobile Gmbh",
    "wof:placetype":"venue"
},
  "geometry": {"coordinates":[9.734899,52.404251],"type":"Point"}
}