{
  "type": "Feature",
  "properties": {
    "iso:country":"DE",
    "sg:address":"Seiferstetterstr. 34",
    "sg:city":"Landsberg",
    "sg:postcode":"86899",
    "sg:province":"Bayern",
    "wof:name":"Brain Trust Analysen- Planungen-konzepte E. K.",
    "wof:placetype":"venue"
},
  "geometry": {"coordinates":[10.882036,48.006611],"type":"Point"}
}