{
  "type": "Feature",
  "properties": {
    "iso:country":"DE",
    "sg:address":"Friedrich-R\u00e4tzer-Str. 15",
    "sg:city":"Schweinfurt",
    "sg:phone":"+49 9721/77190",
    "sg:postcode":"97424",
    "sg:province":"Bayern",
    "wof:name":"Winfried H\u00e4usner",
    "wof:placetype":"venue"
},
  "geometry": {"coordinates":[10.2352962494,50.031627655],"type":"Point"}
}