{
  "type": "Feature",
  "properties": {
    "iso:country":"DE",
    "sg:address":"Bahnhofstr. 23",
    "sg:city":"M\u00f6nchengladbach",
    "sg:phone":"+49 2166/41940",
    "sg:postcode":"41236",
    "sg:province":"Nordrhein-Westfalen",
    "wof:name":"Waffen Berger",
    "wof:placetype":"venue"
},
  "geometry": {"coordinates":[6.4413609505,51.1642990112],"type":"Point"}
}