{
  "type": "Feature",
  "properties": {
    "iso:country":"DE",
    "sg:address":"Albstr. 2",
    "sg:city":"M\u00f6nchsdeggingen",
    "sg:phone":"+49 9088/615",
    "sg:postcode":"86751",
    "sg:province":"Bayern",
    "wof:name":"Auto K\u00f6nig Gmbh & Co. Kg",
    "wof:placetype":"venue"
},
  "geometry": {"coordinates":[10.583187,48.77713],"type":"Point"}
}