{
  "type": "Feature",
  "properties": {
    "iso:country":"DE",
    "sg:address":"Uhlandstr. 16",
    "sg:city":"Baunatal",
    "sg:phone":"+49 561/4912281",
    "sg:postcode":"34225",
    "sg:province":"Hessen",
    "wof:name":"Gabriele Heitmann",
    "wof:placetype":"venue"
},
  "geometry": {"coordinates":[9.402173,51.25061],"type":"Point"}
}