{
  "type": "Feature",
  "properties": {
    "iso:country":"DE",
    "sg:address":"Lindenstr. 18",
    "sg:city":"Wadgassen",
    "sg:phone":"+49 6834/943633",
    "sg:postcode":"66787",
    "sg:province":"Saarland",
    "wof:name":"Kutschen Lauer",
    "wof:placetype":"venue"
},
  "geometry": {"coordinates":[6.789436,49.268105],"type":"Point"}
}