{
  "type": "Feature",
  "properties": {
    "iso:country":"DE",
    "sg:address":"Klammstra\u00dfe 21",
    "sg:city":"Bous",
    "sg:phone":"+49 6834/922445",
    "sg:postcode":"66359",
    "sg:province":"Saarland",
    "wof:name":"Clemens J\u00fcrgen Clemens Accessoires",
    "wof:placetype":"venue"
},
  "geometry": {"coordinates":[6.8021001816,49.275592804],"type":"Point"}
}