{
  "type": "Feature",
  "properties": {
    "iso:country":"DE",
    "sg:address":"Antoniusstr. 26",
    "sg:city":"Herten",
    "sg:phone":"+49 2366/36909",
    "sg:postcode":"45699",
    "sg:province":"Nordrhein-Westfalen",
    "wof:name":"Alfons P\u00f6ppinghaus",
    "wof:placetype":"venue"
},
  "geometry": {"coordinates":[7.1379380226,51.5928153992],"type":"Point"}
}