{
  "type": "Feature",
  "properties": {
    "iso:country":"DE",
    "sg:address":"Vitalisstr. 112",
    "sg:city":"K\u00f6ln",
    "sg:phone":"+49 2236/82377",
    "sg:postcode":"50827",
    "sg:province":"Nordrhein-Westfalen",
    "wof:name":"Spechtmeier Ingenieur",
    "wof:placetype":"venue"
},
  "geometry": {"coordinates":[6.8981571198,50.9535331726],"type":"Point"}
}