{
  "type": "Feature",
  "properties": {
    "iso:country":"DE",
    "sg:address":"Sickenh\u00e4user Str. 56",
    "sg:city":"Reutlingen",
    "sg:phone":"+49 7121/300712",
    "sg:postcode":"72760",
    "sg:province":"Baden-W\u00fcrttemberg",
    "wof:name":"Christa Abele",
    "wof:placetype":"venue"
},
  "geometry": {"coordinates":[9.2000312805,48.5041923523],"type":"Point"}
}