{
  "type": "Feature",
  "properties": {
    "iso:country":"DE",
    "sg:address":"Am Kirschberg 14",
    "sg:city":"Bennewitz",
    "sg:postcode":"04828",
    "sg:province":"Sachsen",
    "wof:name":"Nig Massivhaus Gmbh",
    "wof:placetype":"venue"
},
  "geometry": {"coordinates":[12.706603,51.353348],"type":"Point"}
}