{
  "type": "Feature",
  "properties": {
    "iso:country":"DE",
    "sg:address":"Sophienstr. 27",
    "sg:city":"Karlsruhe",
    "sg:phone":"+49 721/24904",
    "sg:postcode":"76133",
    "sg:province":"Baden-W\u00fcrttemberg",
    "wof:name":"Alten- Und Pflegeheim Elisabethen-haus",
    "wof:placetype":"venue"
},
  "geometry": {"coordinates":[8.392251,49.006496],"type":"Point"}
}