{
  "type": "Feature",
  "properties": {
    "iso:country":"DE",
    "sg:address":"Kr\u00e4henberg 2",
    "sg:city":"Giekau",
    "sg:phone":"+49 4385/659",
    "sg:postcode":"24321",
    "sg:province":"Schleswig-Holstein",
    "wof:name":"Sport & Freizeit Shop Jutta Sch\u00fcmann",
    "wof:placetype":"venue"
},
  "geometry": {"coordinates":[10.583598,54.288204],"type":"Point"}
}