{
  "type": "Feature",
  "properties": {
    "iso:country":"DE",
    "sg:address":"Weitesthaler Str. 19",
    "sg:city":"Sachsenbrunn",
    "sg:phone":"+49 3686/60000",
    "sg:postcode":"98678",
    "sg:province":"Th\u00fcringen",
    "wof:name":"H. Buff",
    "wof:placetype":"venue"
},
  "geometry": {"coordinates":[10.9447603226,50.4418182373],"type":"Point"}
}