{
  "type": "Feature",
  "properties": {
    "iso:country":"DE",
    "sg:address":"Neuhauser Str. 3",
    "sg:city":"W\u00fcrselen",
    "sg:phone":"+49 2405/91468",
    "sg:postcode":"52146",
    "sg:province":"Nordrhein-Westfalen",
    "wof:name":"Eiscafe Ernesto Casal",
    "wof:placetype":"venue"
},
  "geometry": {"coordinates":[6.132197,50.818138],"type":"Point"}
}