{
  "type": "Feature",
  "properties": {
    "iso:country":"DE",
    "sg:address":"Schinnaer Landstr. 26 A",
    "sg:city":"Stolzenau",
    "sg:phone":"+49 4957/6192210",
    "sg:postcode":"31592",
    "sg:province":"Niedersachsen",
    "wof:name":"Weserdruckerei Rolf Oeselmann Gmbh",
    "wof:placetype":"venue"
},
  "geometry": {"coordinates":[9.0755815506,52.5162734985],"type":"Point"}
}