{
  "type": "Feature",
  "properties": {
    "iso:country":"DE",
    "sg:address":"Fraunhoferstr. 6",
    "sg:city":"Ingolstadt",
    "sg:phone":"+49 841/69259",
    "sg:postcode":"85053",
    "sg:province":"Bayern",
    "wof:name":"W. Steinbei\u00dfer",
    "wof:placetype":"venue"
},
  "geometry": {"coordinates":[11.442465,48.74979],"type":"Point"}
}