{
  "type": "Feature",
  "properties": {
    "iso:country":"DE",
    "sg:address":"Max-Planck-Str. 20",
    "sg:city":"Benningen",
    "sg:phone":"+49 7144/4332",
    "sg:postcode":"71726",
    "sg:province":"Baden-W\u00fcrttemberg",
    "wof:name":"Inge Sch\u00f6llhorn Steuerberaterin",
    "wof:placetype":"venue"
},
  "geometry": {"coordinates":[9.2350959778,48.9421577454],"type":"Point"}
}