{
  "type": "Feature",
  "properties": {
    "iso:country":"DE",
    "sg:address":"Unter den Eichen 5 + 7",
    "sg:city":"Wiesbaden",
    "sg:phone":"+49 611/5310",
    "sg:postcode":"65195",
    "sg:province":"Hessen",
    "wof:name":"Taunus Ton Bearbeitungs-gmbh",
    "wof:placetype":"venue"
},
  "geometry": {"coordinates":[8.2185077667,50.0958747864],"type":"Point"}
}