{
  "type": "Feature",
  "properties": {
    "iso:country":"DE",
    "sg:address":"Stein 8",
    "sg:city":"Hartenstein",
    "sg:phone":"+49 37605/760",
    "sg:postcode":"08118",
    "sg:province":"Sachsen",
    "wof:name":"Hotel Schlo\u00df Wolfsbrunn Hartenstein Gmbh",
    "wof:placetype":"venue"
},
  "geometry": {"coordinates":[12.660161972,50.6497650146],"type":"Point"}
}