{
  "type": "Feature",
  "properties": {
    "iso:country":"DE",
    "sg:address":"Riesengebirgstra\u00dfe 43",
    "sg:city":"Regensburg",
    "sg:phone":"+49 941",
    "sg:postcode":"93057",
    "sg:province":"Bayern",
    "wof:name":"P&p Studios /funkwerbung & Audio-design",
    "wof:placetype":"venue"
},
  "geometry": {"coordinates":[12.107475,49.038082],"type":"Point"}
}