{
  "type": "Feature",
  "properties": {
    "iso:country":"DE",
    "sg:address":"Dresdner Str. 5",
    "sg:city":"Mei\u00dfen",
    "sg:phone":"+49 3521/734164",
    "sg:postcode":"01662",
    "sg:province":"Sachsen",
    "wof:name":"Dagmar Glawon",
    "wof:placetype":"venue"
},
  "geometry": {"coordinates":[13.481962204,51.1624641418],"type":"Point"}
}