{
  "type": "Feature",
  "properties": {
    "iso:country":"DE",
    "sg:address":"Rheinstr. 42",
    "sg:city":"Darmstadt",
    "sg:phone":"+49 6151/31035",
    "sg:postcode":"64283",
    "sg:province":"Hessen",
    "wof:name":"Deutscher Ring Lebensversicherungs Ag",
    "wof:placetype":"venue"
},
  "geometry": {"coordinates":[8.6437349319,49.8715744019],"type":"Point"}
}