{
  "type": "Feature",
  "properties": {
    "iso:country":"DE",
    "sg:address":"Hauptstr. 30",
    "sg:city":"Riedenheim",
    "sg:phone":"+49 9338/1533",
    "sg:postcode":"97283",
    "sg:province":"Bayern",
    "wof:name":"Nepomuk-stuben",
    "wof:placetype":"venue"
},
  "geometry": {"coordinates":[9.9746246338,49.5583572388],"type":"Point"}
}