{
  "type": "Feature",
  "properties": {
    "iso:country":"DE",
    "sg:address":"Waxensteinstr. 2",
    "sg:city":"Garmisch-Partenkirchen",
    "sg:phone":"+49 8821/79356",
    "sg:postcode":"82467",
    "sg:province":"Bayern",
    "wof:name":"Helmke & Jockenh\u00f6fer Hausverwaltungsges. Mbh",
    "wof:placetype":"venue"
},
  "geometry": {"coordinates":[11.083326,47.486637],"type":"Point"}
}