{
  "type": "Feature",
  "properties": {
    "iso:country":"DE",
    "sg:address":"Kastanienweg 8",
    "sg:city":"Osterspai",
    "sg:phone":"+49 2627/974034",
    "sg:postcode":"56340",
    "sg:province":"Rheinland-Pfalz",
    "wof:name":"Peter Didinger",
    "wof:placetype":"venue"
},
  "geometry": {"coordinates":[7.6166319847,50.2435035706],"type":"Point"}
}