{
  "type": "Feature",
  "properties": {
    "iso:country":"DE",
    "sg:address":"Grunewaldstr. 19",
    "sg:city":"Duisburg",
    "sg:phone":"+49 203/69175",
    "sg:postcode":"47053",
    "sg:province":"Nordrhein-Westfalen",
    "wof:name":"K. Hobohm",
    "wof:placetype":"venue"
},
  "geometry": {"coordinates":[6.7602062225,51.414276123],"type":"Point"}
}