{
  "type": "Feature",
  "properties": {
    "iso:country":"DE",
    "sg:address":"Nibelungenstr. 25",
    "sg:city":"B\u00fcrstadt",
    "sg:phone":"+49 6206/75700",
    "sg:postcode":"68642",
    "sg:province":"Hessen",
    "wof:name":"Hilger & Kern Gmbh",
    "wof:placetype":"venue"
},
  "geometry": {"coordinates":[8.452008,49.640472],"type":"Point"}
}