{
  "type": "Feature",
  "properties": {
    "iso:country":"DE",
    "sg:address":"Am Dreifaltigkeitsberg 30",
    "sg:city":"Regensburg",
    "sg:phone":"+49 941/85672",
    "sg:postcode":"93059",
    "sg:province":"Bayern",
    "wof:name":"Hermann Weis",
    "wof:placetype":"venue"
},
  "geometry": {"coordinates":[12.092261,49.032841],"type":"Point"}
}