{
  "type": "Feature",
  "properties": {
    "iso:country":"DE",
    "sg:address":"Friedrich-Dannenmann-Str. 60",
    "sg:city":"T\u00fcbingen",
    "sg:phone":"+49 7071/49255",
    "sg:postcode":"72070",
    "sg:province":"Baden-W\u00fcrttemberg",
    "wof:name":"Ev. Pfarramt Stephanuskirche",
    "wof:placetype":"venue"
},
  "geometry": {"coordinates":[9.0328950882,48.5247650146],"type":"Point"}
}