{
  "type": "Feature",
  "properties": {
    "iso:country":"DE",
    "sg:address":"Untert\u00fcrkheimer Str. 23",
    "sg:city":"Saarbr\u00fccken",
    "sg:postcode":"66117",
    "sg:province":"Saarland",
    "wof:name":"Evs Hans Erich Hautz",
    "wof:placetype":"venue"
},
  "geometry": {"coordinates":[6.9719247818,49.2125511169],"type":"Point"}
}