{
  "type": "Feature",
  "properties": {
    "iso:country":"DE",
    "sg:address":"pfalsberger 44",
    "sg:city":"Bremen",
    "sg:phone":"+49 421/66585",
    "sg:postcode":"28236",
    "sg:province":"Bremen",
    "wof:name":"Designofweb Die Internetmacher",
    "wof:placetype":"venue"
},
  "geometry": {"coordinates":[8.80466,53.075161],"type":"Point"}
}