{
  "type": "Feature",
  "properties": {
    "iso:country":"DE",
    "sg:address":"Am Pilgerweg 4",
    "sg:city":"Wildsteig",
    "sg:phone":"+49 8867/1828",
    "sg:postcode":"82409",
    "sg:province":"Bayern",
    "wof:name":"Franz Kell",
    "wof:placetype":"venue"
},
  "geometry": {"coordinates":[10.929151,47.697632],"type":"Point"}
}