{
  "type": "Feature",
  "properties": {
    "iso:country":"DE",
    "sg:address":"Im Erlenteich 62",
    "sg:city":"Pirmasens",
    "sg:phone":"+49 6331/70899",
    "sg:postcode":"66955",
    "sg:province":"Rheinland-Pfalz",
    "wof:name":"Kurt Balzer",
    "wof:placetype":"venue"
},
  "geometry": {"coordinates":[7.5854182243,49.1898803711],"type":"Point"}
}