{
  "type": "Feature",
  "properties": {
    "iso:country":"DE",
    "sg:address":"Servatiusstr. 5",
    "sg:city":"Koblenz",
    "sg:phone":"+49 261/45615",
    "sg:postcode":"56072",
    "sg:province":"Rheinland-Pfalz",
    "wof:name":"J.-g. Schmidt",
    "wof:placetype":"venue"
},
  "geometry": {"coordinates":[7.550657,50.343433],"type":"Point"}
}