{
  "type": "Feature",
  "properties": {
    "iso:country":"DE",
    "sg:address":"Im Osterholz 18",
    "sg:city":"Asperg",
    "sg:phone":"+49 7141/62975",
    "sg:postcode":"71679",
    "sg:province":"Baden-W\u00fcrttemberg",
    "wof:name":"Naturfreundehaus Klein Aspergle",
    "wof:placetype":"venue"
},
  "geometry": {"coordinates":[9.1430988312,48.9031600952],"type":"Point"}
}