{
  "type": "Feature",
  "properties": {
    "iso:country":"DE",
    "sg:address":"Neumarkt 7 b",
    "sg:city":"Menden",
    "sg:phone":"+49 2373/3080",
    "sg:postcode":"58706",
    "sg:province":"Nordrhein-Westfalen",
    "wof:name":"Gerhard Dirks",
    "wof:placetype":"venue"
},
  "geometry": {"coordinates":[7.7942490578,51.4376602173],"type":"Point"}
}