{
  "type": "Feature",
  "properties": {
    "iso:country":"DE",
    "sg:address":"Kirchenstr. 2",
    "sg:city":"F\u00fcrth",
    "sg:phone":"+49 911/7406905",
    "sg:postcode":"90762",
    "sg:province":"Bayern",
    "wof:name":"Gothaer Versicherungen D. Radtke",
    "wof:placetype":"venue"
},
  "geometry": {"coordinates":[10.9945306778,49.4715614319],"type":"Point"}
}