{
  "type": "Feature",
  "properties": {
    "iso:country":"DE",
    "sg:address":"Br\u00fchl 26",
    "sg:city":"Chemnitz",
    "sg:phone":"+49 371/461480",
    "sg:postcode":"09111",
    "sg:province":"Sachsen",
    "wof:name":"Hotel & Restaurant S\u00e4chsicher Hof Ohg",
    "wof:placetype":"venue"
},
  "geometry": {"coordinates":[12.9240322113,50.84116745],"type":"Point"}
}