{
  "type": "Feature",
  "properties": {
    "iso:country":"DE",
    "sg:address":"B\u00e4ckerstr. 104",
    "sg:city":"Goslar",
    "sg:phone":"+49 5321/34380",
    "sg:postcode":"38640",
    "sg:province":"Niedersachsen",
    "wof:name":"Neue-hottenrott-einzelhandel Gmbh",
    "wof:placetype":"venue"
},
  "geometry": {"coordinates":[10.4277496338,51.9074630737],"type":"Point"}
}