{
  "type": "Feature",
  "properties": {
    "iso:country":"DE",
    "sg:address":"Breite Str. 31",
    "sg:city":"Bad Harzburg",
    "sg:phone":"+49 5322/86493",
    "sg:postcode":"38667",
    "sg:province":"Niedersachsen",
    "wof:name":"Enderich Foto",
    "wof:placetype":"venue"
},
  "geometry": {"coordinates":[10.5371046066,51.8798294067],"type":"Point"}
}