{
  "type": "Feature",
  "properties": {
    "iso:country":"DE",
    "sg:address":"Robert-Bosch-Stra\u00dfe 9",
    "sg:city":"Mainz",
    "sg:phone":"+49 6131",
    "sg:postcode":"55129",
    "sg:province":"Rheinland-Pfalz",
    "wof:name":"Saab Zentrum Mainz - Autohaus Scholl",
    "wof:placetype":"venue"
},
  "geometry": {"coordinates":[8.2618503571,49.9591560364],"type":"Point"}
}