{
  "type": "Feature",
  "properties": {
    "iso:country":"DE",
    "sg:address":"Narzissenweg 12",
    "sg:city":"L\u00fcbeck",
    "sg:phone":"+49 451/84164",
    "sg:postcode":"23558",
    "sg:province":"Schleswig-Holstein",
    "wof:name":"Kath. Pfarramt St. Birgitta",
    "wof:placetype":"venue"
},
  "geometry": {"coordinates":[10.6581811905,53.8522033691],"type":"Point"}
}