{
  "type": "Feature",
  "properties": {
    "iso:country":"DE",
    "sg:address":"Henri-Dunant-Str. 38",
    "sg:city":"Bensheim",
    "sg:phone":"+49 6251/38803",
    "sg:postcode":"64625",
    "sg:province":"Hessen",
    "wof:name":"Steven P. & The Hound Dogs",
    "wof:placetype":"venue"
},
  "geometry": {"coordinates":[8.60115242,49.6810417175],"type":"Point"}
}