{
  "type": "Feature",
  "properties": {
    "iso:country":"DE",
    "sg:address":"Buschhausener Str. 20-30",
    "sg:city":"Oberhausen",
    "sg:phone":"+49 208/859280",
    "sg:postcode":"46049",
    "sg:province":"Nordrhein-Westfalen",
    "wof:name":"Lohmar & Meller Ohg",
    "wof:placetype":"venue"
},
  "geometry": {"coordinates":[6.8507180214,51.4778900146],"type":"Point"}
}