{
  "type": "Feature",
  "properties": {
    "iso:country":"DE",
    "sg:address":"Andreastr. 17",
    "sg:city":"Kirchheimbolanden",
    "sg:phone":"+49 6352/3640",
    "sg:postcode":"67292",
    "sg:province":"Rheinland-Pfalz",
    "wof:name":"Erika Kotysch Massagepraxis",
    "wof:placetype":"venue"
},
  "geometry": {"coordinates":[8.014762,49.663162],"type":"Point"}
}