{
  "type": "Feature",
  "properties": {
    "iso:country":"DE",
    "sg:address":"Lobker Str. 24",
    "sg:city":"Sehnde",
    "sg:phone":"+49 5138/1417",
    "sg:postcode":"31319",
    "sg:province":"Niedersachsen",
    "wof:name":"Horst-steffen Diers",
    "wof:placetype":"venue"
},
  "geometry": {"coordinates":[10.014072,52.283218],"type":"Point"}
}