{
  "type": "Feature",
  "properties": {
    "iso:country":"DE",
    "sg:address":"Berliner Weg 3",
    "sg:city":"Amelinghausen",
    "sg:phone":"+49 4132/8299",
    "sg:postcode":"21385",
    "sg:province":"Niedersachsen",
    "wof:name":"H. Dekartz-krejsta",
    "wof:placetype":"venue"
},
  "geometry": {"coordinates":[10.2081184387,53.1209716797],"type":"Point"}
}