{
  "type": "Feature",
  "properties": {
    "iso:country":"DE",
    "sg:address":"Drontheimer Str. 28",
    "sg:city":"Berlin",
    "sg:postcode":"13359",
    "sg:province":"Berlin",
    "wof:name":"Wiv Wein International Ag",
    "wof:placetype":"venue"
},
  "geometry": {"coordinates":[13.3767356873,52.5594367981],"type":"Point"}
}