{
  "type": "Feature",
  "properties": {
    "iso:country":"DE",
    "sg:address":"F\u00e4ustheck 8",
    "sg:city":"Nohfelden",
    "sg:phone":"+49 6852/81954",
    "sg:postcode":"66625",
    "sg:province":"Saarland",
    "wof:name":"Maria Ke\u00dfler-alt Heilpraktikerin",
    "wof:placetype":"venue"
},
  "geometry": {"coordinates":[7.0448951721,49.5712585449],"type":"Point"}
}