{
  "type": "Feature",
  "properties": {
    "iso:country":"DE",
    "sg:address":"Borgplatz",
    "sg:city":"L\u00fcdinghausen",
    "sg:phone":"+49 2594/3830",
    "sg:postcode":"59348",
    "sg:province":"Nordrhein-Westfalen",
    "wof:name":"M. Schur Ingenieur",
    "wof:placetype":"venue"
},
  "geometry": {"coordinates":[7.4424581528,51.7721595764],"type":"Point"}
}