{
  "type": "Feature",
  "properties": {
    "iso:country":"DE",
    "sg:address":"Hackl\u00e4nderstr. 33",
    "sg:city":"Stuttgart",
    "sg:phone":"+49 711/993420",
    "sg:postcode":"70184",
    "sg:province":"Baden-W\u00fcrttemberg",
    "wof:name":"Schlemmer Immobilien",
    "wof:placetype":"venue"
},
  "geometry": {"coordinates":[9.1970062256,48.7747688293],"type":"Point"}
}