{
  "type": "Feature",
  "properties": {
    "iso:country":"DE",
    "sg:address":"Jahnstr. 14",
    "sg:city":"Hemau",
    "sg:phone":"+49 9491/775",
    "sg:postcode":"93155",
    "sg:province":"Bayern",
    "wof:name":"Stefan Plankl",
    "wof:placetype":"venue"
},
  "geometry": {"coordinates":[11.780211,49.048538],"type":"Point"}
}