{
  "type": "Feature",
  "properties": {
    "iso:country":"DE",
    "sg:address":"Hinterhausen 16",
    "sg:city":"Odernheim",
    "sg:phone":"+49 6755/517",
    "sg:postcode":"55571",
    "sg:province":"Rheinland-Pfalz",
    "wof:name":"Josef Walheim",
    "wof:placetype":"venue"
},
  "geometry": {"coordinates":[7.706122,49.765903],"type":"Point"}
}