{
  "type": "Feature",
  "properties": {
    "iso:country":"DE",
    "sg:address":"Wallotstr. 20",
    "sg:city":"Dresden",
    "sg:phone":"+49 351/4421467",
    "sg:postcode":"01309",
    "sg:province":"Sachsen",
    "wof:name":"Egbert Steinfelder Architekt",
    "wof:placetype":"venue"
},
  "geometry": {"coordinates":[13.771014,51.044155],"type":"Point"}
}