{
  "type": "Feature",
  "properties": {
    "iso:country":"DE",
    "sg:address":"Deutschordenstr. 7",
    "sg:city":"Aalen",
    "sg:phone":"+49 4973/67316",
    "sg:postcode":"73434",
    "sg:province":"Baden-W\u00fcrttemberg",
    "wof:name":"Raiffeisenbank Waldhausen Eg",
    "wof:placetype":"venue"
},
  "geometry": {"coordinates":[10.20541,48.823586],"type":"Point"}
}