{
  "type": "Feature",
  "properties": {
    "iso:country":"DE",
    "sg:address":"Mosbacher Str. 21",
    "sg:city":"Mannheim",
    "sg:phone":"+49 621/703335",
    "sg:postcode":"68259",
    "sg:province":"Baden-W\u00fcrttemberg",
    "wof:name":"C. Packh\u00e4user",
    "wof:placetype":"venue"
},
  "geometry": {"coordinates":[8.5491733551,49.4962425232],"type":"Point"}
}