{
  "type": "Feature",
  "properties": {
    "iso:country":"DE",
    "sg:address":"Westendstr. 52",
    "sg:city":"Frankfurt",
    "sg:phone":"+49 69/727266",
    "sg:postcode":"60325",
    "sg:province":"Hessen",
    "wof:name":"J.r. K\u00fctzing",
    "wof:placetype":"venue"
},
  "geometry": {"coordinates":[8.660939,50.114548],"type":"Point"}
}