{
  "type": "Feature",
  "properties": {
    "iso:country":"DE",
    "sg:address":"An der Staufenmauer 3",
    "sg:city":"Frankfurt",
    "sg:phone":"+49 69/285008",
    "sg:postcode":"60311",
    "sg:province":"Hessen",
    "wof:name":"City-residence Gmbh",
    "wof:placetype":"venue"
},
  "geometry": {"coordinates":[8.687171936,50.1135482788],"type":"Point"}
}