{
  "type": "Feature",
  "properties": {
    "iso:country":"DE",
    "sg:address":"Simmerner Str. 15",
    "sg:city":"Boppard",
    "sg:phone":"+49 6742/2216",
    "sg:postcode":"56154",
    "sg:province":"Rheinland-Pfalz",
    "wof:name":"Sozialberatungsstelle Caritasverband",
    "wof:placetype":"venue"
},
  "geometry": {"coordinates":[7.593514,50.229324],"type":"Point"}
}