{
  "type": "Feature",
  "properties": {
    "iso:country":"DE",
    "sg:address":"Im Damm 9",
    "sg:city":"Edesheim",
    "sg:phone":"+49 6323/949090",
    "sg:postcode":"67483",
    "sg:province":"Rheinland-Pfalz",
    "wof:name":"Team Projekt Veranstaltungs- Service Eventmarketing Und",
    "wof:placetype":"venue"
},
  "geometry": {"coordinates":[8.1086988449,49.2554664612],"type":"Point"}
}