{
  "type": "Feature",
  "properties": {
    "iso:country":"DE",
    "sg:address":"Langenberger Str. 233",
    "sg:city":"Velbert",
    "sg:phone":"+49 2051/250140",
    "sg:postcode":"42551",
    "sg:province":"Nordrhein-Westfalen",
    "wof:name":"Klemens Hoeren",
    "wof:placetype":"venue"
},
  "geometry": {"coordinates":[7.068687,51.34441],"type":"Point"}
}