{
  "type": "Feature",
  "properties": {
    "iso:country":"DE",
    "sg:address":"Falltorstr. 7",
    "sg:city":"Offenbach",
    "sg:phone":"+49 69/86781033",
    "sg:postcode":"63075",
    "sg:province":"Hessen",
    "wof:name":"Elektro R\u00f6der Installations Gmbh",
    "wof:placetype":"venue"
},
  "geometry": {"coordinates":[8.78439,50.117748],"type":"Point"}
}