{
  "type": "Feature",
  "properties": {
    "iso:country":"DE",
    "sg:address":"Hauptstr. 60",
    "sg:city":"Kurort Seiffen",
    "sg:phone":"+49 37362/8261",
    "sg:postcode":"09548",
    "sg:province":"Sachsen",
    "wof:name":"Emil A. Schalling Kg",
    "wof:placetype":"venue"
},
  "geometry": {"coordinates":[13.4470815659,50.6476669312],"type":"Point"}
}