{
  "type": "Feature",
  "properties": {
    "iso:country":"DE",
    "sg:address":"Oststr. 25",
    "sg:city":"Gevelsberg",
    "sg:phone":"+49 4923/3296840",
    "sg:postcode":"58285",
    "sg:province":"Nordrhein-Westfalen",
    "wof:name":"Dieckerhoff Guss Gmbh",
    "wof:placetype":"venue"
},
  "geometry": {"coordinates":[7.357447,51.327873],"type":"Point"}
}