{
  "type": "Feature",
  "properties": {
    "iso:country":"DE",
    "sg:address":"Prager Rg. 1-15",
    "sg:city":"Aachen",
    "sg:phone":"+49 4924/1182020",
    "sg:postcode":"52070",
    "sg:province":"Nordrhein-Westfalen",
    "wof:name":"Fecken-kirfel Gmbh & Co.kg",
    "wof:placetype":"venue"
},
  "geometry": {"coordinates":[6.118264,50.791977],"type":"Point"}
}