{
  "type": "Feature",
  "properties": {
    "iso:country":"DE",
    "sg:address":"Gustav-Heinemann-Str. 59",
    "sg:city":"Bremen",
    "sg:phone":"+49 421/357197",
    "sg:postcode":"28215",
    "sg:province":"Bremen",
    "wof:name":"M. Golla Rechtsanwalt",
    "wof:placetype":"venue"
},
  "geometry": {"coordinates":[8.8185901642,53.0999336243],"type":"Point"}
}