{
  "type": "Feature",
  "properties": {
    "iso:country":"DE",
    "sg:address":"Weststr. 36",
    "sg:city":"L\u00f6hne",
    "sg:phone":"+49 5732/3242",
    "sg:postcode":"32584",
    "sg:province":"Nordrhein-Westfalen",
    "wof:name":"Linnenbr\u00fcgger Holz",
    "wof:placetype":"venue"
},
  "geometry": {"coordinates":[8.677740097,52.2057495117],"type":"Point"}
}