{
  "type": "Feature",
  "properties": {
    "iso:country":"DE",
    "sg:address":"Schulgasse 4",
    "sg:city":"Hohnstein",
    "sg:phone":"+49 35975/80994",
    "sg:postcode":"01848",
    "sg:province":"Sachsen",
    "wof:name":"Erlebnisbad",
    "wof:placetype":"venue"
},
  "geometry": {"coordinates":[14.1100215912,50.9809379578],"type":"Point"}
}