{
  "type": "Feature",
  "properties": {
    "iso:country":"DE",
    "sg:address":"Ziergartenweg 2",
    "sg:city":"Hergensweiler",
    "sg:phone":"+49 8388/248",
    "sg:postcode":"88138",
    "sg:province":"Bayern",
    "wof:name":"Werner Stuhler",
    "wof:placetype":"venue"
},
  "geometry": {"coordinates":[9.774728775,47.6110496521],"type":"Point"}
}