{
  "type": "Feature",
  "properties": {
    "iso:country":"DE",
    "sg:address":"Eberwinstr. 26",
    "sg:city":"Neckarsulm",
    "sg:phone":"+49 7132/41080",
    "sg:postcode":"74172",
    "sg:province":"Baden-W\u00fcrttemberg",
    "wof:name":"Vereinsgastst\u00e4tte Vfl Obereisesheim",
    "wof:placetype":"venue"
},
  "geometry": {"coordinates":[9.2022714615,49.2019386292],"type":"Point"}
}