{
  "type": "Feature",
  "properties": {
    "iso:country":"DE",
    "sg:address":"Hauptstr. 22",
    "sg:city":"Kitzscher",
    "sg:postcode":"04567",
    "sg:province":"Sachsen",
    "wof:name":"Andreas Glauch",
    "wof:placetype":"venue"
},
  "geometry": {"coordinates":[12.559228,51.191208],"type":"Point"}
}