{
  "type": "Feature",
  "properties": {
    "iso:country":"DE",
    "sg:address":"Eysenbachstr. 3",
    "sg:city":"Darmstadt",
    "sg:phone":"+49 6151/54594",
    "sg:postcode":"64297",
    "sg:province":"Hessen",
    "wof:name":"Erika Hartmann",
    "wof:placetype":"venue"
},
  "geometry": {"coordinates":[8.634311676,49.8165626526],"type":"Point"}
}