{
  "type": "Feature",
  "properties": {
    "iso:country":"DE",
    "sg:address":"Papenstr. 122",
    "sg:city":"Hamburg",
    "sg:phone":"+49 40/27148994",
    "sg:postcode":"22089",
    "sg:province":"Hamburg",
    "wof:name":"Bm-nettworks E. K.",
    "wof:placetype":"venue"
},
  "geometry": {"coordinates":[10.0496120453,53.56508255],"type":"Point"}
}