{
  "type": "Feature",
  "properties": {
    "iso:country":"DE",
    "sg:address":"Am Haidh\u00fcgel 13",
    "sg:city":"Kulmbach",
    "sg:phone":"+49 9221/924152",
    "sg:postcode":"95326",
    "sg:province":"Bayern",
    "wof:name":"Gisela Gall",
    "wof:placetype":"venue"
},
  "geometry": {"coordinates":[11.42433,50.130806],"type":"Point"}
}