{
  "type": "Feature",
  "properties": {
    "iso:country":"DE",
    "sg:address":"Cranachstr. 8",
    "sg:city":"Schwarzenbach a d Saale",
    "sg:phone":"+49 9284/800091",
    "sg:postcode":"95126",
    "sg:province":"Bayern",
    "wof:name":"T. Bauer",
    "wof:placetype":"venue"
},
  "geometry": {"coordinates":[11.9484939575,50.2223739624],"type":"Point"}
}