{
  "type": "Feature",
  "properties": {
    "iso:country":"DE",
    "sg:address":"Hamburger Str. 7",
    "sg:city":"L\u00fctjensee",
    "sg:phone":"+49 4154/7242",
    "sg:postcode":"22952",
    "sg:province":"Schleswig-Holstein",
    "wof:name":"Orthop\u00f6die-schuhtechnik Dieter Stehle E. K.",
    "wof:placetype":"venue"
},
  "geometry": {"coordinates":[10.3614807129,53.6461524963],"type":"Point"}
}