{
  "type": "Feature",
  "properties": {
    "iso:country":"DE",
    "sg:address":"Eichenstr. 44",
    "sg:city":"Oldenburg",
    "sg:phone":"+49 441/51991",
    "sg:postcode":"26131",
    "sg:province":"Niedersachsen",
    "wof:name":"Kurt Hoppe",
    "wof:placetype":"venue"
},
  "geometry": {"coordinates":[8.182608,53.136887],"type":"Point"}
}