{
  "type": "Feature",
  "properties": {
    "iso:country":"DE",
    "sg:address":"Hauptstr. 14",
    "sg:city":"Schl\u00fcsselfeld",
    "sg:phone":"+49 9555/585",
    "sg:postcode":"96132",
    "sg:province":"Bayern",
    "wof:name":"A. Kossmann",
    "wof:placetype":"venue"
},
  "geometry": {"coordinates":[10.562379837,49.7720451355],"type":"Point"}
}