{
  "type": "Feature",
  "properties": {
    "iso:country":"DE",
    "sg:address":"Galgenleite 12",
    "sg:city":"Schweinfurt",
    "sg:phone":"+49 9721/23477",
    "sg:postcode":"97424",
    "sg:province":"Bayern",
    "wof:name":"M\u00fcller Bestattungen",
    "wof:placetype":"venue"
},
  "geometry": {"coordinates":[10.223956,50.052418],"type":"Point"}
}