{
  "type": "Feature",
  "properties": {
    "iso:country":"DE",
    "sg:address":"Krummbogen 16",
    "sg:city":"Marburg",
    "sg:phone":"+49 6421/67200",
    "sg:postcode":"35039",
    "sg:province":"Hessen",
    "wof:name":"Dieter Stallberg",
    "wof:placetype":"venue"
},
  "geometry": {"coordinates":[8.77709198,50.8156547546],"type":"Point"}
}