{
  "type": "Feature",
  "properties": {
    "iso:country":"DE",
    "sg:address":"Hochstr. 44",
    "sg:city":"Berlin",
    "sg:phone":"+49 30/4618584",
    "sg:postcode":"12209",
    "sg:province":"Berlin",
    "wof:name":"H. Leder Und D. Rempen Rechtsanw\u00e4lte Und Notare",
    "wof:placetype":"venue"
},
  "geometry": {"coordinates":[13.3199901581,52.4188995361],"type":"Point"}
}