{
  "type": "Feature",
  "properties": {
    "iso:country":"DE",
    "sg:address":"Neuoffsteiner Str. 11",
    "sg:city":"Offstein",
    "sg:phone":"+49 6243/5218",
    "sg:postcode":"67591",
    "sg:province":"Rheinland-Pfalz",
    "wof:name":"Hartmut Ewald Obstanbau",
    "wof:placetype":"venue"
},
  "geometry": {"coordinates":[8.2373046875,49.6064376831],"type":"Point"}
}