{
  "type": "Feature",
  "properties": {
    "iso:country":"DE",
    "sg:address":"Moltkestr. 3-5",
    "sg:city":"Pinneberg",
    "sg:phone":"+49 4101/50990",
    "sg:postcode":"25421",
    "sg:province":"Schleswig-Holstein",
    "wof:name":"Mallick Und Reski Rechtsanw\u00e4lte",
    "wof:placetype":"venue"
},
  "geometry": {"coordinates":[9.7991571426,53.6583404541],"type":"Point"}
}