{
  "type": "Feature",
  "properties": {
    "iso:country":"DE",
    "sg:address":"Dieselstr. 53",
    "sg:city":"Dresden",
    "sg:phone":"+49 351/2036576",
    "sg:postcode":"01257",
    "sg:province":"Sachsen",
    "wof:name":"Ingrid Kr\u00fcger",
    "wof:placetype":"venue"
},
  "geometry": {"coordinates":[13.82912,51.010494],"type":"Point"}
}