{
  "type": "Feature",
  "properties": {
    "iso:country":"DE",
    "sg:address":"Luisenstr 90-100",
    "sg:city":"Burscheid",
    "sg:phone":"+49 2174/679800",
    "sg:postcode":"51399",
    "sg:province":"Nordrhein-Westfalen",
    "wof:name":"Ohm Werkzeuge Wolfgang Vomm",
    "wof:placetype":"venue"
},
  "geometry": {"coordinates":[7.1138467789,51.0921211243],"type":"Point"}
}