{
  "type": "Feature",
  "properties": {
    "iso:country":"DE",
    "sg:address":"Langgasse 26",
    "sg:city":"Gau-Algesheim",
    "sg:phone":"+49 6725/3768",
    "sg:postcode":"55435",
    "sg:province":"Rheinland-Pfalz",
    "wof:name":"Anneliese Chmella",
    "wof:placetype":"venue"
},
  "geometry": {"coordinates":[8.014213562,49.9591522217],"type":"Point"}
}