{
  "type": "Feature",
  "properties": {
    "iso:country":"DE",
    "sg:address":"Steinstr. 29 I",
    "sg:city":"L\u00fcnen",
    "sg:phone":"+49 2306/6059",
    "sg:postcode":"44534",
    "sg:province":"Nordrhein-Westfalen",
    "wof:name":"Dr. U. Und Dr. A. Schmidt Tier\u00e4rzte",
    "wof:placetype":"venue"
},
  "geometry": {"coordinates":[7.5190501213,51.6128501892],"type":"Point"}
}