{
  "type": "Feature",
  "properties": {
    "iso:country":"DE",
    "sg:address":"Heidelbergweg 9",
    "sg:city":"Ronneburg",
    "sg:postcode":"07580",
    "sg:province":"Th\u00fcringen",
    "wof:name":"Blr Lager- Und Handelshaus Gmbh",
    "wof:placetype":"venue"
},
  "geometry": {"coordinates":[12.1653499603,50.8661499023],"type":"Point"}
}