{
  "type": "Feature",
  "properties": {
    "iso:country":"DE",
    "sg:address":"Bahnstr. 17",
    "sg:city":"Siegen",
    "sg:phone":"+49 271/81647",
    "sg:postcode":"57078",
    "sg:province":"Nordrhein-Westfalen",
    "wof:name":"Bergmann Kg",
    "wof:placetype":"venue"
},
  "geometry": {"coordinates":[8.01354,50.9161],"type":"Point"}
}