{
  "type": "Feature",
  "properties": {
    "iso:country":"DE",
    "sg:address":"Marienbader Str. 8",
    "sg:city":"Fl\u00f6rsheim",
    "sg:phone":"+49 6145/32486",
    "sg:postcode":"65439",
    "sg:province":"Hessen",
    "wof:name":"Jarosch-druck",
    "wof:placetype":"venue"
},
  "geometry": {"coordinates":[8.430949,50.042187],"type":"Point"}
}