{
  "type": "Feature",
  "properties": {
    "iso:country":"DE",
    "sg:address":"Am Kreisforst 6",
    "sg:city":"Meppen",
    "sg:phone":"+49 5931/98970",
    "sg:postcode":"49716",
    "sg:province":"Niedersachsen",
    "wof:name":"Goertz Fleischwaren Gmbh",
    "wof:placetype":"venue"
},
  "geometry": {"coordinates":[7.2003240585,52.6674118042],"type":"Point"}
}