{
  "type": "Feature",
  "properties": {
    "iso:country":"DE",
    "sg:address":"K\u00f6rtestr. 2",
    "sg:city":"Berlin",
    "sg:phone":"+49 30/6938939",
    "sg:postcode":"10967",
    "sg:province":"Berlin",
    "wof:name":"Gastst\u00e4tte Klaus N\u00fc\u00dfler",
    "wof:placetype":"venue"
},
  "geometry": {"coordinates":[13.4119348526,52.4916267395],"type":"Point"}
}