{
  "type": "Feature",
  "properties": {
    "iso:country":"DE",
    "sg:address":"Buchenweg 4",
    "sg:city":"Mengerskirchen",
    "sg:phone":"+49 6476/911915",
    "sg:postcode":"35794",
    "sg:province":"Hessen",
    "wof:name":"Brigitte Wagner Heilpraktikerin",
    "wof:placetype":"venue"
},
  "geometry": {"coordinates":[8.1415967941,50.5400657654],"type":"Point"}
}