{
  "type": "Feature",
  "properties": {
    "iso:country":"DE",
    "sg:address":"Gereonswall 1 a",
    "sg:city":"K\u00f6ln",
    "sg:postcode":"50668",
    "sg:province":"Nordrhein-Westfalen",
    "wof:name":"G\u00f6ser Sport-wetten Gmbh",
    "wof:placetype":"venue"
},
  "geometry": {"coordinates":[6.956493,50.949146],"type":"Point"}
}