{
  "type": "Feature",
  "properties": {
    "iso:country":"DE",
    "sg:address":"Solmsstr. 22",
    "sg:city":"Berlin",
    "sg:phone":"+49 30/6949138",
    "sg:postcode":"10961",
    "sg:province":"Berlin",
    "wof:name":"Consatel Telekommunikation Sattelitenempfangs- Und",
    "wof:placetype":"venue"
},
  "geometry": {"coordinates":[13.392157,52.49073],"type":"Point"}
}