{
  "type": "Feature",
  "properties": {
    "iso:country":"DE",
    "sg:address":"Gewerbestr. 1",
    "sg:city":"Pliening",
    "sg:phone":"+49 89/603804",
    "sg:postcode":"85652",
    "sg:province":"Bayern",
    "wof:name":"Lm Liftmaterial Gmbh",
    "wof:placetype":"venue"
},
  "geometry": {"coordinates":[11.7736,48.18119],"type":"Point"}
}