{
  "type": "Feature",
  "properties": {
    "iso:country":"DE",
    "sg:address":"Am Klentsch 6",
    "sg:city":"Lichtenfels",
    "sg:phone":"+49 9571/3676",
    "sg:postcode":"96215",
    "sg:province":"Bayern",
    "wof:name":"Brigitta Knoth",
    "wof:placetype":"venue"
},
  "geometry": {"coordinates":[11.05905056,50.13463974],"type":"Point"}
}