{
  "type": "Feature",
  "properties": {
    "iso:country":"DE",
    "sg:address":"Steinweg 10 a",
    "sg:city":"Mei\u00dfner",
    "sg:phone":"+49 5657/305",
    "sg:postcode":"37290",
    "sg:province":"Hessen",
    "wof:name":"J. Lang",
    "wof:placetype":"venue"
},
  "geometry": {"coordinates":[9.932181,51.209637],"type":"Point"}
}