{
  "type": "Feature",
  "properties": {
    "iso:country":"DE",
    "sg:address":"Friedhofstr. 22",
    "sg:city":"Prenzlau",
    "sg:phone":"+49 3984/5064",
    "sg:postcode":"17291",
    "sg:province":"Brandenburg",
    "wof:name":"Lothar Mertens",
    "wof:placetype":"venue"
},
  "geometry": {"coordinates":[13.8643712997,53.3047866821],"type":"Point"}
}