{
  "type": "Feature",
  "properties": {
    "iso:country":"DE",
    "sg:address":"Forststr. 16",
    "sg:city":"Plauen",
    "sg:phone":"+49 3741/226242",
    "sg:postcode":"08523",
    "sg:province":"Sachsen",
    "wof:name":"Glanz Und Glanz Rechtsanw\u00e4lte",
    "wof:placetype":"venue"
},
  "geometry": {"coordinates":[12.1374607086,50.497428894],"type":"Point"}
}