{
  "type": "Feature",
  "properties": {
    "iso:country":"DE",
    "sg:address":"M\u00fcncheberger Weg 3",
    "sg:city":"Trebnitz",
    "sg:phone":"+49 33477/4505",
    "sg:postcode":"15320",
    "sg:province":"Brandenburg",
    "wof:name":"Tap Trebnitzer Agrar- Produktionsgesellschaft Mbh",
    "wof:placetype":"venue"
},
  "geometry": {"coordinates":[14.217069,52.529694],"type":"Point"}
}