{
  "type": "Feature",
  "properties": {
    "iso:country":"DE",
    "sg:address":"Turmstr. 19",
    "sg:city":"Bad Oeynhausen",
    "sg:phone":"+49 5731/796055",
    "sg:postcode":"32547",
    "sg:province":"Nordrhein-Westfalen",
    "wof:name":"M\u00fcller Verwaltungs Gmbh",
    "wof:placetype":"venue"
},
  "geometry": {"coordinates":[8.8067674637,52.1891555786],"type":"Point"}
}