{
  "type": "Feature",
  "properties": {
    "iso:country":"DE",
    "sg:address":"Bahnhofstr. 164 a",
    "sg:city":"Herne",
    "sg:phone":"+49 2323/52264",
    "sg:postcode":"44629",
    "sg:province":"Nordrhein-Westfalen",
    "wof:name":"Baby-markt Boekstegen Gmbh & Co. Kg",
    "wof:placetype":"venue"
},
  "geometry": {"coordinates":[7.2102198601,51.5570793152],"type":"Point"}
}