{
  "type": "Feature",
  "properties": {
    "iso:country":"DE",
    "sg:address":"Klosterweg 100",
    "sg:city":"Goch",
    "sg:postcode":"47574",
    "sg:province":"Nordrhein-Westfalen",
    "wof:name":"Maxxmo E. K.",
    "wof:placetype":"venue"
},
  "geometry": {"coordinates":[6.0889019966,51.7080078125],"type":"Point"}
}