{
  "type": "Feature",
  "properties": {
    "iso:country":"DE",
    "sg:address":"Vorderr\u00fcbach 13",
    "sg:city":"Lindlar",
    "sg:phone":"+49 2266/470304",
    "sg:postcode":"51789",
    "sg:province":"Nordrhein-Westfalen",
    "wof:name":"D. Kuckelberg Immobilienmakler",
    "wof:placetype":"venue"
},
  "geometry": {"coordinates":[7.3973097801,51.0303192139],"type":"Point"}
}