{
  "type": "Feature",
  "properties": {
    "iso:country":"DE",
    "sg:address":"An St. Johann 6",
    "sg:city":"Geilenkirchen",
    "sg:phone":"+49 2451/921619",
    "sg:postcode":"52511",
    "sg:province":"Nordrhein-Westfalen",
    "wof:name":"Ving Chun Kampfkunst E.vc.c.",
    "wof:placetype":"venue"
},
  "geometry": {"coordinates":[6.128923893,50.9628677368],"type":"Point"}
}