{
  "type": "Feature",
  "properties": {
    "iso:country":"DE",
    "sg:address":"Alleestr. 27",
    "sg:city":"Heusweiler",
    "sg:phone":"+49 6806/989254",
    "sg:postcode":"66265",
    "sg:province":"Saarland",
    "wof:name":"Lothar Kunzler",
    "wof:placetype":"venue"
},
  "geometry": {"coordinates":[6.9923968315,49.3297233582],"type":"Point"}
}