{
  "type": "Feature",
  "properties": {
    "iso:country":"DE",
    "sg:address":"Westfalenweg 210",
    "sg:city":"Wuppertal",
    "sg:phone":"+49 202/75931",
    "sg:postcode":"42111",
    "sg:province":"Nordrhein-Westfalen",
    "wof:name":"Dr. Heinrich Feuchter-stiftung",
    "wof:placetype":"venue"
},
  "geometry": {"coordinates":[7.14926,51.284336],"type":"Point"}
}