{
  "type": "Feature",
  "properties": {
    "iso:country":"DE",
    "sg:address":"Sielminger Str. 51",
    "sg:city":"Leinfelden-Echterdingen",
    "sg:phone":"+49 711/7973300",
    "sg:postcode":"70771",
    "sg:province":"Baden-W\u00fcrttemberg",
    "wof:name":"Carus-verlag Gmbh",
    "wof:placetype":"venue"
},
  "geometry": {"coordinates":[9.1812286377,48.6731033325],"type":"Point"}
}