{
  "type": "Feature",
  "properties": {
    "iso:country":"DE",
    "sg:address":"Propst-Hellmich-Promenade 43",
    "sg:city":"Bochum",
    "sg:phone":"+49 2327/322614",
    "sg:postcode":"44866",
    "sg:province":"Nordrhein-Westfalen",
    "wof:name":"Pizzeria Don Nicola",
    "wof:placetype":"venue"
},
  "geometry": {"coordinates":[7.1294698715,51.4801864624],"type":"Point"}
}