{
  "type": "Feature",
  "properties": {
    "iso:country":"DE",
    "sg:address":"Oberdorfstr. 32",
    "sg:city":"Meckenheim",
    "sg:phone":"+49 2225/7687",
    "sg:postcode":"53340",
    "sg:province":"Nordrhein-Westfalen",
    "wof:name":"Johannes Br\u00fcnagel",
    "wof:placetype":"venue"
},
  "geometry": {"coordinates":[7.0037059784,50.5937957764],"type":"Point"}
}