{
  "type": "Feature",
  "properties": {
    "iso:country":"DE",
    "sg:address":"Rudolf-Diesel-Str. 1",
    "sg:city":"Polch",
    "sg:phone":"+49 2654/94970",
    "sg:postcode":"56751",
    "sg:province":"Rheinland-Pfalz",
    "wof:name":"T & P Volumentransport Gmbh",
    "wof:placetype":"venue"
},
  "geometry": {"coordinates":[7.3163399696,50.3096313477],"type":"Point"}
}