{
  "type": "Feature",
  "properties": {
    "iso:country":"DE",
    "sg:address":"Karlsbader Str. 5",
    "sg:city":"Eibenstock",
    "sg:postcode":"08309",
    "sg:province":"Sachsen",
    "wof:name":"Baufuchs Heimwerker Und Baumarkt L\u00e4ssig & Funke",
    "wof:placetype":"venue"
},
  "geometry": {"coordinates":[12.6033906937,50.492767334],"type":"Point"}
}