{
  "type": "Feature",
  "properties": {
    "iso:country":"DE",
    "sg:address":"Bachstr. 35",
    "sg:city":"Bendorf",
    "sg:phone":"+49 2622/3915",
    "sg:postcode":"56170",
    "sg:province":"Rheinland-Pfalz",
    "wof:name":"Werner Jungen",
    "wof:placetype":"venue"
},
  "geometry": {"coordinates":[7.5761442184,50.4223518372],"type":"Point"}
}