{
  "type": "Feature",
  "properties": {
    "iso:country":"DE",
    "sg:address":"Hauptstr. 12",
    "sg:city":"Gimbsheim",
    "sg:phone":"+49 6249/5943",
    "sg:postcode":"67578",
    "sg:province":"Rheinland-Pfalz",
    "wof:name":"Jutta M\u00fchling",
    "wof:placetype":"venue"
},
  "geometry": {"coordinates":[8.3746232986,49.780418396],"type":"Point"}
}