{
  "type": "Feature",
  "properties": {
    "iso:country":"DE",
    "sg:address":"Sch\u00fctzenb\u00fchlstr. 63 a",
    "sg:city":"Stuttgart",
    "sg:phone":"+49 711/8263385",
    "sg:postcode":"70435",
    "sg:province":"Baden-W\u00fcrttemberg",
    "wof:name":"Albert Hess Inh. Alfred Lamla",
    "wof:placetype":"venue"
},
  "geometry": {"coordinates":[9.157875061,48.8341674805],"type":"Point"}
}