{
  "type": "Feature",
  "properties": {
    "iso:country":"DE",
    "sg:address":"M\u00fcnchener Str. 18",
    "sg:city":"Haar",
    "sg:phone":"+49 89/4564070",
    "sg:postcode":"85540",
    "sg:province":"Bayern",
    "wof:name":"Obi Gmbh & Co. Kg",
    "wof:placetype":"venue"
},
  "geometry": {"coordinates":[11.7213134766,48.1089782715],"type":"Point"}
}