{
  "type": "Feature",
  "properties": {
    "iso:country":"DE",
    "sg:address":"Johann-Sigismund-Str. 8",
    "sg:city":"Berlin",
    "sg:postcode":"10711",
    "sg:province":"Berlin",
    "wof:name":"Sigrid Lesser Wissenschaftl. Graphologin",
    "wof:placetype":"venue"
},
  "geometry": {"coordinates":[13.2931451797,52.495716095],"type":"Point"}
}