{
  "type": "Feature",
  "properties": {
    "iso:country":"DE",
    "sg:address":"Kastellstr. 21",
    "sg:city":"Taunusstein",
    "sg:phone":"+49 6128/71201",
    "sg:postcode":"65232",
    "sg:province":"Hessen",
    "wof:name":"Hans K\u00f6rner Gmbh",
    "wof:placetype":"venue"
},
  "geometry": {"coordinates":[8.188091,50.18335],"type":"Point"}
}