{
  "type": "Feature",
  "properties": {
    "iso:country":"DE",
    "sg:address":"Am Taubenfeld 37",
    "sg:city":"Heidelberg",
    "sg:phone":"+49 6221/839081",
    "sg:postcode":"69123",
    "sg:province":"Baden-W\u00fcrttemberg",
    "wof:name":"Hubert Haarmann Holzimport Gmbh",
    "wof:placetype":"venue"
},
  "geometry": {"coordinates":[8.637943,49.429611],"type":"Point"}
}