{
  "type": "Feature",
  "properties": {
    "iso:country":"DE",
    "sg:address":"Marktstr. 28",
    "sg:city":"Gladenbach",
    "sg:phone":"+49 6462/6593",
    "sg:postcode":"35075",
    "sg:province":"Hessen",
    "wof:name":"Pizzeria Toscana",
    "wof:placetype":"venue"
},
  "geometry": {"coordinates":[8.5830183029,50.7685546875],"type":"Point"}
}