{
  "type": "Feature",
  "properties": {
    "iso:country":"DE",
    "sg:address":"Weststr. 38",
    "sg:city":"Chemnitz",
    "sg:phone":"+49 371/304511",
    "sg:postcode":"09112",
    "sg:province":"Sachsen",
    "wof:name":"Cheob Immobilien Und Bau- Tr\u00e4gergesellschaft Mbh",
    "wof:placetype":"venue"
},
  "geometry": {"coordinates":[12.902907,50.832462],"type":"Point"}
}