{
  "type": "Feature",
  "properties": {
    "iso:country":"DE",
    "sg:address":"Dorfstr. 11",
    "sg:city":"Blankenhain",
    "sg:postcode":"99444",
    "sg:province":"Th\u00fcringen",
    "wof:name":"W. Kammer",
    "wof:placetype":"venue"
},
  "geometry": {"coordinates":[11.278222,50.843746],"type":"Point"}
}