{
  "type": "Feature",
  "properties": {
    "iso:country":"DE",
    "sg:address":"Dorfstr. 17",
    "sg:city":"Limsdorf",
    "sg:postcode":"15864",
    "sg:province":"Brandenburg",
    "wof:name":"Martina Trett",
    "wof:placetype":"venue"
},
  "geometry": {"coordinates":[14.019619,52.158813],"type":"Point"}
}