{
  "type": "Feature",
  "properties": {
    "iso:country":"DE",
    "sg:address":"Planckstr. 3",
    "sg:city":"Vaihingen",
    "sg:phone":"+49 7042/970170",
    "sg:postcode":"71665",
    "sg:province":"Baden-W\u00fcrttemberg",
    "wof:name":"Ulrich A. Berberich",
    "wof:placetype":"venue"
},
  "geometry": {"coordinates":[8.967442,48.928581],"type":"Point"}
}