{
  "type": "Feature",
  "properties": {
    "iso:country":"DE",
    "sg:address":"Nauener Chaussee 30",
    "sg:city":"Falkensee",
    "sg:phone":"+49 3322/50050",
    "sg:postcode":"14612",
    "sg:province":"Brandenburg",
    "wof:name":"Ro-ma Bau- Und Gartenh\u00f6lzer Gmbh",
    "wof:placetype":"venue"
},
  "geometry": {"coordinates":[13.081410408,52.5760345459],"type":"Point"}
}