{
  "type": "Feature",
  "properties": {
    "iso:country":"DE",
    "sg:address":"W\u00e4chtersbacher Str 59-61",
    "sg:city":"Frankfurt",
    "sg:phone":"+49 69/4200060",
    "sg:postcode":"60386",
    "sg:province":"Hessen",
    "wof:name":"Euro Planen + Service Gmbh",
    "wof:placetype":"venue"
},
  "geometry": {"coordinates":[8.753499,50.132553],"type":"Point"}
}