{
  "type": "Feature",
  "properties": {
    "iso:country":"DE",
    "sg:address":"Kirchstr. 16 C",
    "sg:city":"Obertshausen",
    "sg:phone":"+49 6104/941650",
    "sg:postcode":"63179",
    "sg:province":"Hessen",
    "wof:name":"Wolfgang Artur Nauerz Rechtsanwalt",
    "wof:placetype":"venue"
},
  "geometry": {"coordinates":[8.8506727219,50.0711975098],"type":"Point"}
}