{
  "type": "Feature",
  "properties": {
    "iso:country":"DE",
    "sg:address":"Bachernstr. 38",
    "sg:city":"Friedberg",
    "sg:postcode":"86316",
    "sg:province":"Bayern",
    "wof:name":"Rci Verlag E. K.",
    "wof:placetype":"venue"
},
  "geometry": {"coordinates":[10.9870462418,48.3497962952],"type":"Point"}
}