{
  "type": "Feature",
  "properties": {
    "iso:country":"DE",
    "sg:address":"Finkenweg 40",
    "sg:city":"Postbauer-Heng",
    "sg:phone":"+49 9188/2622",
    "sg:postcode":"92353",
    "sg:province":"Bayern",
    "wof:name":"Bernd Flormann Ingenieur",
    "wof:placetype":"venue"
},
  "geometry": {"coordinates":[11.3480396271,49.2978515625],"type":"Point"}
}