{
  "type": "Feature",
  "properties": {
    "iso:country":"DE",
    "sg:address":"Pinienhof 2",
    "sg:city":"Flensburg",
    "sg:phone":"+49 461/37191",
    "sg:postcode":"24944",
    "sg:province":"Schleswig-Holstein",
    "wof:name":"Kurt Myler Ingenieur",
    "wof:placetype":"venue"
},
  "geometry": {"coordinates":[9.4801130295,54.8092384338],"type":"Point"}
}