{
  "type": "Feature",
  "properties": {
    "iso:country":"DE",
    "sg:address":"Ringstr. 2",
    "sg:city":"Wiesbaden",
    "sg:phone":"+49 4955/24820",
    "sg:postcode":"65205",
    "sg:province":"Hessen",
    "wof:name":"Deutsche Exide Gmbh",
    "wof:placetype":"venue"
},
  "geometry": {"coordinates":[10.48765,51.642738],"type":"Point"}
}