{
  "type": "Feature",
  "properties": {
    "iso:country":"DE",
    "sg:address":"Capeller Str. 134",
    "sg:city":"Werne",
    "sg:phone":"+49 2389/1503",
    "sg:postcode":"59368",
    "sg:province":"Nordrhein-Westfalen",
    "wof:name":"B\u00fclhoff Verwaltungs Gmbh",
    "wof:placetype":"venue"
},
  "geometry": {"coordinates":[7.6228518486,51.6787414551],"type":"Point"}
}