{
  "type": "Feature",
  "properties": {
    "iso:country":"DE",
    "sg:address":"Saarlandstr. 34",
    "sg:city":"Villingen-Schwenningen",
    "sg:phone":"+49 7721/90265",
    "sg:postcode":"78050",
    "sg:province":"Baden-W\u00fcrttemberg",
    "wof:name":"Eva-maria Lang",
    "wof:placetype":"venue"
},
  "geometry": {"coordinates":[8.450764,48.055714],"type":"Point"}
}