{
  "type": "Feature",
  "properties": {
    "iso:country":"DE",
    "sg:address":"Segerothstr. 105",
    "sg:city":"Essen",
    "sg:phone":"+49 201/327376",
    "sg:postcode":"45141",
    "sg:province":"Nordrhein-Westfalen",
    "wof:name":"Unikum",
    "wof:placetype":"venue"
},
  "geometry": {"coordinates":[7.0013508797,51.4646759033],"type":"Point"}
}