{
  "type": "Feature",
  "properties": {
    "iso:country":"DE",
    "sg:address":"Waltroper Str. 24",
    "sg:city":"L\u00fcnen",
    "sg:phone":"+49 2306/873772",
    "sg:postcode":"44536",
    "sg:province":"Nordrhein-Westfalen",
    "wof:name":"W. Beuckelmann Rechtsanw\u00e4lte",
    "wof:placetype":"venue"
},
  "geometry": {"coordinates":[7.4387149811,51.5973243713],"type":"Point"}
}