{
  "type": "Feature",
  "properties": {
    "iso:country":"DE",
    "sg:address":"Eickhoffstr. 11",
    "sg:city":"G\u00fctersloh",
    "sg:phone":"+49 5241/51290",
    "sg:postcode":"33330",
    "sg:province":"Nordrhein-Westfalen",
    "wof:name":"Stadttheater-lichtpiele",
    "wof:placetype":"venue"
},
  "geometry": {"coordinates":[8.3821630478,51.9072990417],"type":"Point"}
}