{
  "type": "Feature",
  "properties": {
    "iso:country":"DE",
    "sg:address":"Schlo\u00dfstr. 44",
    "sg:city":"Berlin",
    "sg:phone":"+49 30/7919044",
    "sg:postcode":"12165",
    "sg:province":"Berlin",
    "wof:name":"Ev. Pfarramt Matth\u00e4us-gemeinde",
    "wof:placetype":"venue"
},
  "geometry": {"coordinates":[13.3192501068,52.4557914734],"type":"Point"}
}