{
  "type": "Feature",
  "properties": {
    "iso:country":"DE",
    "sg:address":"Wernstr. 10-12",
    "sg:city":"Arnstein",
    "sg:phone":"+49 9363/90600",
    "sg:postcode":"97450",
    "sg:province":"Bayern",
    "wof:name":"L\u00f6mpel-bautenschutz Gmbh & Co. Kg",
    "wof:placetype":"venue"
},
  "geometry": {"coordinates":[9.963536,49.976627],"type":"Point"}
}