{
  "type": "Feature",
  "properties": {
    "iso:country":"DE",
    "sg:address":"B\u00e4rensteiner Str. 12 a",
    "sg:city":"Annaberg-Buchholz",
    "sg:postcode":"09456",
    "sg:province":"Sachsen",
    "wof:name":"Hts Gmbh Bau Und M\u00f6beltischlerei",
    "wof:placetype":"venue"
},
  "geometry": {"coordinates":[13.0039281845,50.5701980591],"type":"Point"}
}