{
  "type": "Feature",
  "properties": {
    "iso:country":"DE",
    "sg:address":"Hauptstr. 5/1",
    "sg:city":"Gechingen",
    "sg:phone":"+49 4970/561711",
    "sg:postcode":"75391",
    "sg:province":"Baden-W\u00fcrttemberg",
    "wof:name":"Kreissparkasse Calw",
    "wof:placetype":"venue"
},
  "geometry": {"coordinates":[8.829216,48.694729],"type":"Point"}
}