{
  "type": "Feature",
  "properties": {
    "iso:country":"DE",
    "sg:address":"Dr.-Hell-Str",
    "sg:city":"Kiel",
    "sg:phone":"+49 431/3860",
    "sg:postcode":"24107",
    "sg:province":"Schleswig-Holstein",
    "wof:name":"Heidelberger Druckmaschinen Ag",
    "wof:placetype":"venue"
},
  "geometry": {"coordinates":[10.08852005,54.3495292664],"type":"Point"}
}