{
  "type": "Feature",
  "properties": {
    "iso:country":"DE",
    "sg:address":"Valpichlerstr. 99",
    "sg:city":"M\u00fcnchen",
    "sg:phone":"+49 89/5804096",
    "sg:postcode":"80686",
    "sg:province":"Bayern",
    "wof:name":"Clemens Frhr. Von Taube Rechtsanwalt",
    "wof:placetype":"venue"
},
  "geometry": {"coordinates":[11.4929199219,48.1377677917],"type":"Point"}
}