{
  "type": "Feature",
  "properties": {
    "iso:country":"DE",
    "sg:address":"Remscheider Str. 259 b",
    "sg:city":"Remscheid",
    "sg:phone":"+49 2191/927330",
    "sg:postcode":"42855",
    "sg:province":"Nordrhein-Westfalen",
    "wof:name":"H.-j. Braun",
    "wof:placetype":"venue"
},
  "geometry": {"coordinates":[7.2378430367,51.1831474304],"type":"Point"}
}