{
  "type": "Feature",
  "properties": {
    "iso:country":"DE",
    "sg:address":"An der Molkerei 28",
    "sg:city":"Bedburg-Hau",
    "sg:phone":"+49 2821/6881",
    "sg:postcode":"47551",
    "sg:province":"Nordrhein-Westfalen",
    "wof:name":"Booms-pastoors Gmbh Stahl- Und Hallenbau Gmbh",
    "wof:placetype":"venue"
},
  "geometry": {"coordinates":[6.191974,51.766651],"type":"Point"}
}