{
  "type": "Feature",
  "properties": {
    "iso:country":"DE",
    "sg:address":"Am Kirchfeld 35",
    "sg:city":"Seelze",
    "sg:postcode":"30926",
    "sg:province":"Niedersachsen",
    "wof:name":"Traffic-assekuranz Gmbh",
    "wof:placetype":"venue"
},
  "geometry": {"coordinates":[9.6508970261,52.3669128418],"type":"Point"}
}