{
  "type": "Feature",
  "properties": {
    "iso:country":"DE",
    "sg:address":"Hauptstr. 44",
    "sg:city":"Lemf\u00f6rde",
    "sg:phone":"+49 5443/2459",
    "sg:postcode":"49448",
    "sg:province":"Niedersachsen",
    "wof:name":"Ihr Platz Drogeriemarkt",
    "wof:placetype":"venue"
},
  "geometry": {"coordinates":[8.374265,52.470654],"type":"Point"}
}