{
  "type": "Feature",
  "properties": {
    "iso:country":"DE",
    "sg:address":"Danziger Str. 82",
    "sg:city":"Ostfildern",
    "sg:phone":"+49 711/3481557",
    "sg:postcode":"73760",
    "sg:province":"Baden-W\u00fcrttemberg",
    "wof:name":"Claus & Bosch",
    "wof:placetype":"venue"
},
  "geometry": {"coordinates":[9.28325,48.72522],"type":"Point"}
}