{
  "type": "Feature",
  "properties": {
    "iso:country":"DE",
    "sg:address":"Coburger Str. 68",
    "sg:city":"Lautertal",
    "sg:phone":"+49 9561/69472",
    "sg:postcode":"96486",
    "sg:province":"Bayern",
    "wof:name":"Wolfgang B\u00fcttner",
    "wof:placetype":"venue"
},
  "geometry": {"coordinates":[10.976615,50.296577],"type":"Point"}
}