{
  "type": "Feature",
  "properties": {
    "iso:country":"DE",
    "sg:address":"Nordstr. 3",
    "sg:city":"Oschatz",
    "sg:phone":"+49 3435/920516",
    "sg:postcode":"04758",
    "sg:province":"Sachsen",
    "wof:name":"Wolfgang D\u00e4beritz Ingenieur",
    "wof:placetype":"venue"
},
  "geometry": {"coordinates":[13.0990619659,51.3068618774],"type":"Point"}
}