{
  "type": "Feature",
  "properties": {
    "iso:country":"DE",
    "sg:address":"Bremmental 6",
    "sg:city":"T\u00f6nisvorst",
    "sg:phone":"+49 2151/799192",
    "sg:postcode":"47918",
    "sg:province":"Nordrhein-Westfalen",
    "wof:name":"D. Pasch Elektroinstallation",
    "wof:placetype":"venue"
},
  "geometry": {"coordinates":[6.506667,51.313919],"type":"Point"}
}