{
  "type": "Feature",
  "properties": {
    "iso:country":"DE",
    "sg:address":"Parkstr. 16",
    "sg:city":"Bad Nauheim",
    "sg:phone":"+49 6032/32439",
    "sg:postcode":"61231",
    "sg:province":"Hessen",
    "wof:name":"Beirakdar",
    "wof:placetype":"venue"
},
  "geometry": {"coordinates":[8.7376937866,50.3652992249],"type":"Point"}
}