{
  "type": "Feature",
  "properties": {
    "iso:country":"DE",
    "sg:address":"H\u00f6hestr. 5",
    "sg:city":"Burscheid",
    "sg:phone":"+49 2174/5959",
    "sg:postcode":"51399",
    "sg:province":"Nordrhein-Westfalen",
    "wof:name":"Paul Luchtenberg-stiftung",
    "wof:placetype":"venue"
},
  "geometry": {"coordinates":[7.1189761162,51.0825119019],"type":"Point"}
}