{
  "type": "Feature",
  "properties": {
    "iso:country":"DE",
    "sg:address":"Monschauer Str. 131",
    "sg:city":"D\u00fcren",
    "sg:phone":"+49 2421/64880",
    "sg:postcode":"52355",
    "sg:province":"Nordrhein-Westfalen",
    "wof:name":"Altmann",
    "wof:placetype":"venue"
},
  "geometry": {"coordinates":[6.4608149529,50.7775802612],"type":"Point"}
}