{
  "type": "Feature",
  "properties": {
    "iso:country":"DE",
    "sg:address":"Geveker Kamp 56",
    "sg:city":"Hannover",
    "sg:phone":"+49 511/407363",
    "sg:postcode":"30453",
    "sg:province":"Niedersachsen",
    "wof:name":"Helios-apotheke",
    "wof:placetype":"venue"
},
  "geometry": {"coordinates":[9.667558,52.373688],"type":"Point"}
}