{
  "type": "Feature",
  "properties": {
    "iso:country":"DE",
    "sg:address":"Lindenstr. 28",
    "sg:city":"Unterschlei\u00dfheim",
    "sg:phone":"+49 89/3104400",
    "sg:postcode":"85716",
    "sg:province":"Bayern",
    "wof:name":"Annan Orthofer-tihanyi Krankengymnastin",
    "wof:placetype":"venue"
},
  "geometry": {"coordinates":[11.582832,48.281307],"type":"Point"}
}