{
  "type": "Feature",
  "properties": {
    "iso:country":"DE",
    "sg:address":"Am Hechenberg 61",
    "sg:city":"Mainz",
    "sg:phone":"+49 6131/957830",
    "sg:postcode":"55129",
    "sg:province":"Rheinland-Pfalz",
    "wof:name":"Jochen G. Bielefeld",
    "wof:placetype":"venue"
},
  "geometry": {"coordinates":[8.2748794556,49.9709434509],"type":"Point"}
}