{
  "type": "Feature",
  "properties": {
    "iso:country":"DE",
    "sg:address":"M\u00fchlenstr. 3",
    "sg:city":"Bawinkel",
    "sg:phone":"+49 5963/1300",
    "sg:postcode":"49844",
    "sg:province":"Niedersachsen",
    "wof:name":"Dr. Dirk J\u00fcnemann Tierarzt",
    "wof:placetype":"venue"
},
  "geometry": {"coordinates":[7.4154138565,52.6028366089],"type":"Point"}
}