{
  "type": "Feature",
  "properties": {
    "iso:country":"DE",
    "sg:address":"Katherl-Berg-Str. 20",
    "sg:city":"Haselbach",
    "sg:phone":"+49 9961/8177",
    "sg:postcode":"94354",
    "sg:province":"Bayern",
    "wof:name":"Gemy Bauger\u00e4te Geith & Mlynek Gmbh",
    "wof:placetype":"venue"
},
  "geometry": {"coordinates":[12.682084,48.998375],"type":"Point"}
}