{
  "type": "Feature",
  "properties": {
    "iso:country":"DE",
    "sg:address":"Stra\u00dfe des 13. Januar 88",
    "sg:city":"V\u00f6lklingen",
    "sg:phone":"+49 6898/870326",
    "sg:postcode":"66333",
    "sg:province":"Saarland",
    "wof:name":"Lothar Maurer Steuerberater",
    "wof:placetype":"venue"
},
  "geometry": {"coordinates":[6.8688502312,49.2511711121],"type":"Point"}
}