{
  "type": "Feature",
  "properties": {
    "iso:country":"DE",
    "sg:address":"Am Altenkamp 8",
    "sg:city":"Aschendorf",
    "sg:phone":"+49 4962/1450",
    "sg:postcode":"26871",
    "sg:province":"Niedersachsen",
    "wof:name":"Wilhelm Harpel Ingenieur Und Architekt",
    "wof:placetype":"venue"
},
  "geometry": {"coordinates":[7.339349,53.051781],"type":"Point"}
}