{
  "type": "Feature",
  "properties": {
    "iso:country":"DE",
    "sg:address":"Joh-Ev-Holzer-Str 6",
    "sg:city":"S\u00f6gel",
    "sg:phone":"+49 5952/98520",
    "sg:postcode":"49751",
    "sg:province":"Niedersachsen",
    "wof:name":"Stehr",
    "wof:placetype":"venue"
},
  "geometry": {"coordinates":[7.5173020363,52.8443412781],"type":"Point"}
}