{
  "type": "Feature",
  "properties": {
    "iso:country":"DE",
    "sg:address":"Am Sportplatz 5",
    "sg:city":"Hausen",
    "sg:phone":"+49 9722/91070",
    "sg:postcode":"97262",
    "sg:province":"Bayern",
    "wof:name":"A. Schraud Gmbh",
    "wof:placetype":"venue"
},
  "geometry": {"coordinates":[10.04907,49.938091],"type":"Point"}
}