{
  "type": "Feature",
  "properties": {
    "iso:country":"DE",
    "sg:address":"Parkstr. 5",
    "sg:city":"Bad Camberg",
    "sg:phone":"+49 6434/3411",
    "sg:postcode":"65520",
    "sg:province":"Hessen",
    "wof:name":"Park-cafe",
    "wof:placetype":"venue"
},
  "geometry": {"coordinates":[8.2744932175,50.2962608337],"type":"Point"}
}