{
  "type": "Feature",
  "properties": {
    "iso:country":"DE",
    "sg:address":"Ewaldstr. 16",
    "sg:city":"Bochum",
    "sg:phone":"+49 234/332312",
    "sg:postcode":"44789",
    "sg:province":"Nordrhein-Westfalen",
    "wof:name":"Euramedia Gesellschaft F\u00fcr Medienintegration Mbh",
    "wof:placetype":"venue"
},
  "geometry": {"coordinates":[7.2194190025,51.4720802307],"type":"Point"}
}