{
  "type": "Feature",
  "properties": {
    "iso:country":"DE",
    "sg:address":"Hubertusweg 2",
    "sg:city":"Freiberg",
    "sg:phone":"+49 3731/71356",
    "sg:postcode":"09599",
    "sg:province":"Sachsen",
    "wof:name":"Pension Hubertushof",
    "wof:placetype":"venue"
},
  "geometry": {"coordinates":[13.3131465912,50.903755188],"type":"Point"}
}