{
  "type": "Feature",
  "properties": {
    "iso:country":"DE",
    "sg:address":"Engershauser Str. 12",
    "sg:city":"Preu\u00dfisch Oldendorf",
    "sg:phone":"+49 5742/2955",
    "sg:postcode":"32361",
    "sg:province":"Nordrhein-Westfalen",
    "wof:name":"Horst Redeker",
    "wof:placetype":"venue"
},
  "geometry": {"coordinates":[8.502636,52.31126],"type":"Point"}
}