{
  "type": "Feature",
  "properties": {
    "iso:country":"DE",
    "sg:address":"Staulinie 15",
    "sg:city":"Oldenburg",
    "sg:postcode":"26122",
    "sg:province":"Niedersachsen",
    "wof:name":"Windpark Wesselburenerkoog Gmbh & Co. Wehren Kg",
    "wof:placetype":"venue"
},
  "geometry": {"coordinates":[8.215908,53.14093],"type":"Point"}
}