{
  "type": "Feature",
  "properties": {
    "iso:country":"DE",
    "sg:address":"Erikastr. 27",
    "sg:city":"Osnabr\u00fcck",
    "sg:phone":"+49 541/37397",
    "sg:postcode":"49086",
    "sg:province":"Niedersachsen",
    "wof:name":"Autohaus Kleforn Verwaltungs- Und",
    "wof:placetype":"venue"
},
  "geometry": {"coordinates":[8.0965890884,52.256980896],"type":"Point"}
}