{
  "type": "Feature",
  "properties": {
    "iso:country":"DE",
    "sg:address":"Lindenstr. 11",
    "sg:city":"Diemelsee",
    "sg:phone":"+49 2993/353",
    "sg:postcode":"34519",
    "sg:province":"Hessen",
    "wof:name":"Chr. Becker",
    "wof:placetype":"venue"
},
  "geometry": {"coordinates":[8.893513,51.38409],"type":"Point"}
}