{
  "type": "Feature",
  "properties": {
    "iso:country":"DE",
    "sg:address":"Benzstr. 9",
    "sg:city":"Veitsh\u00f6chheim",
    "sg:phone":"+49 931/95367",
    "sg:postcode":"97209",
    "sg:province":"Bayern",
    "wof:name":"Norbert Wie\u00dfmann",
    "wof:placetype":"venue"
},
  "geometry": {"coordinates":[9.9000806808,49.830619812],"type":"Point"}
}