{
  "type": "Feature",
  "properties": {
    "iso:country":"DE",
    "sg:address":"Krefelder Str. 55",
    "sg:city":"M\u00f6nchengladbach",
    "sg:phone":"+49 2161/12229",
    "sg:postcode":"41063",
    "sg:province":"Nordrhein-Westfalen",
    "wof:name":"Friedrich Lerpscher",
    "wof:placetype":"venue"
},
  "geometry": {"coordinates":[6.4572329521,51.2052230835],"type":"Point"}
}