{
  "type": "Feature",
  "properties": {
    "iso:country":"DE",
    "sg:address":"Schlo\u00dfstr. 83",
    "sg:city":"Dinslaken",
    "sg:phone":"+49 2064/43380",
    "sg:postcode":"46535",
    "sg:province":"Nordrhein-Westfalen",
    "wof:name":"Novo Zeitarbeit Gmbh",
    "wof:placetype":"venue"
},
  "geometry": {"coordinates":[6.7387070656,51.55651474],"type":"Point"}
}