{
  "type": "Feature",
  "properties": {
    "iso:country":"DE",
    "sg:address":"D\u00fcsselring 54",
    "sg:city":"Mettmann",
    "sg:phone":"+49 2104/70646",
    "sg:postcode":"40822",
    "sg:province":"Nordrhein-Westfalen",
    "wof:name":"A. Heyers Elektroinstallation",
    "wof:placetype":"venue"
},
  "geometry": {"coordinates":[6.95917,51.248615],"type":"Point"}
}