{
  "type": "Feature",
  "properties": {
    "iso:country":"DE",
    "sg:address":"Eriagstr. 26",
    "sg:city":"Ingolstadt",
    "sg:postcode":"85053",
    "sg:province":"Bayern",
    "wof:name":"Smart Shopping Ohg",
    "wof:placetype":"venue"
},
  "geometry": {"coordinates":[11.474168,48.74902],"type":"Point"}
}