{
  "type": "Feature",
  "properties": {
    "iso:country":"DE",
    "sg:address":"Beurener Str. 56-1",
    "sg:city":"Heubach",
    "sg:phone":"+49 7173/4818",
    "sg:postcode":"73540",
    "sg:province":"Baden-W\u00fcrttemberg",
    "wof:name":"S. Bombera Garten- Und",
    "wof:placetype":"venue"
},
  "geometry": {"coordinates":[9.931164,48.783886],"type":"Point"}
}