{
  "type": "Feature",
  "properties": {
    "iso:country":"DE",
    "sg:address":"Bachstr. 35",
    "sg:city":"Bad F\u00fcssing",
    "sg:phone":"+49 8531/9530",
    "sg:postcode":"94072",
    "sg:province":"Bayern",
    "wof:name":"G\u00e4stehaus A. Und F. Grabner",
    "wof:placetype":"venue"
},
  "geometry": {"coordinates":[13.3054599762,48.3470687866],"type":"Point"}
}