{
  "type": "Feature",
  "properties": {
    "iso:country":"DE",
    "sg:address":"Kelzstr. 21",
    "sg:city":"Saalfeld",
    "sg:phone":"+49 3671",
    "sg:postcode":"07318",
    "sg:province":"Th\u00fcringen",
    "wof:name":"Afi Akademie F\u00fcr Informatik Gmbh",
    "wof:placetype":"venue"
},
  "geometry": {"coordinates":[11.367542,50.644054],"type":"Point"}
}