{
  "type": "Feature",
  "properties": {
    "iso:country":"DE",
    "sg:address":"In den Steinen 19",
    "sg:city":"Gro\u00dfalmerode",
    "sg:phone":"+49 5604/915057",
    "sg:postcode":"37247",
    "sg:province":"Hessen",
    "wof:name":"Rewe-markt Weldner Ohg",
    "wof:placetype":"venue"
},
  "geometry": {"coordinates":[9.7829122543,51.2557601929],"type":"Point"}
}