{
  "type": "Feature",
  "properties": {
    "iso:country":"DE",
    "sg:address":"Sieverse Str. 3",
    "sg:city":"M\u00f6rsdorf",
    "sg:phone":"+49 36428/4440",
    "sg:postcode":"07646",
    "sg:province":"Th\u00fcringen",
    "wof:name":"Ditzinger Fernmeldebauges. Mbh",
    "wof:placetype":"venue"
},
  "geometry": {"coordinates":[11.7863302231,50.8687705994],"type":"Point"}
}