{
  "type": "Feature",
  "properties": {
    "iso:country":"DE",
    "sg:address":"Mittelstr. 22a",
    "sg:city":"Bad Salzuflen",
    "sg:phone":"+49 5222/22524",
    "sg:postcode":"32108",
    "sg:province":"Nordrhein-Westfalen",
    "wof:name":"Karin Prauser Masseurin",
    "wof:placetype":"venue"
},
  "geometry": {"coordinates":[8.786096,52.065884],"type":"Point"}
}