{
  "type": "Feature",
  "properties": {
    "iso:country":"DE",
    "sg:address":"Stifterstr. 28",
    "sg:city":"Konstanz",
    "sg:phone":"+49 7531/77127",
    "sg:postcode":"78467",
    "sg:province":"Baden-W\u00fcrttemberg",
    "wof:name":"Willi Wiggenhauser",
    "wof:placetype":"venue"
},
  "geometry": {"coordinates":[9.1556301117,47.6873207092],"type":"Point"}
}