{
  "type": "Feature",
  "properties": {
    "iso:country":"DE",
    "sg:address":"Dorfstr. 3",
    "sg:city":"Todtnau-Herrenschwand",
    "sg:phone":"+49 7674",
    "sg:postcode":"79674",
    "sg:province":"Baden-W\u00fcrttemberg",
    "wof:name":"B\u00fcro F\u00fcr Bauwesen Und Immobilien",
    "wof:placetype":"venue"
},
  "geometry": {"coordinates":[7.9463448524,47.8288764954],"type":"Point"}
}