{
  "type": "Feature",
  "properties": {
    "iso:country":"DE",
    "sg:address":"Ewerhartstr 2a",
    "sg:city":"Irrel",
    "sg:phone":"+49 4965/257771",
    "sg:postcode":"54666",
    "sg:province":"Rheinland-Pfalz",
    "wof:name":"Raiffeisenbank Eg",
    "wof:placetype":"venue"
},
  "geometry": {"coordinates":[6.455209,49.844013],"type":"Point"}
}