{
  "type": "Feature",
  "properties": {
    "iso:country":"DE",
    "sg:address":"Carl-Zeiss-Str 5",
    "sg:city":"Pliezhausen",
    "sg:phone":"+49 7127/9880",
    "sg:postcode":"72124",
    "sg:province":"Baden-W\u00fcrttemberg",
    "wof:name":"Schmieder It-solutions Gmbh",
    "wof:placetype":"venue"
},
  "geometry": {"coordinates":[9.200944,48.565372],"type":"Point"}
}