{
  "type": "Feature",
  "properties": {
    "iso:country":"DE",
    "sg:address":"Obersteiner Str. 5",
    "sg:city":"Kirn",
    "sg:phone":"+49 6752/8030",
    "sg:postcode":"55606",
    "sg:province":"Rheinland-Pfalz",
    "wof:name":"Hermann Schmitt",
    "wof:placetype":"venue"
},
  "geometry": {"coordinates":[7.456065,49.781841],"type":"Point"}
}