{
  "type": "Feature",
  "properties": {
    "iso:country":"DE",
    "sg:address":"Luisenplatz",
    "sg:city":"Neuwied",
    "sg:phone":"+49 2631/23700",
    "sg:postcode":"56564",
    "sg:province":"Rheinland-Pfalz",
    "wof:name":"City-taxi Platz Ohg Taxi",
    "wof:placetype":"venue"
},
  "geometry": {"coordinates":[7.4598751068,50.4287796021],"type":"Point"}
}