{
  "type": "Feature",
  "properties": {
    "iso:country":"DE",
    "sg:address":"Paul-Ehrlich-Str. 8",
    "sg:city":"Frankfurt",
    "sg:phone":"+49 69/96360881",
    "sg:postcode":"60596",
    "sg:province":"Hessen",
    "wof:name":"R\u00f6sch & Associates Information Engineering Gmbh",
    "wof:placetype":"venue"
},
  "geometry": {"coordinates":[8.668826,50.098061],"type":"Point"}
}