{
  "type": "Feature",
  "properties": {
    "iso:country":"DE",
    "sg:address":"Bullermannshof 8",
    "sg:city":"Moers",
    "sg:phone":"+49 2841/16481",
    "sg:postcode":"47441",
    "sg:province":"Nordrhein-Westfalen",
    "wof:name":"Lennartz Leihwagen Inh. Franz Lennartz E. K.",
    "wof:placetype":"venue"
},
  "geometry": {"coordinates":[6.617005,51.459461],"type":"Point"}
}