{
  "type": "Feature",
  "properties": {
    "iso:country":"DE",
    "sg:address":"Zubermoosstr. 90",
    "sg:city":"Aichhalden",
    "sg:phone":"+49 7444/4606",
    "sg:postcode":"78733",
    "sg:province":"Baden-W\u00fcrttemberg",
    "wof:name":"P. Ziegler",
    "wof:placetype":"venue"
},
  "geometry": {"coordinates":[8.4238195419,48.2980499268],"type":"Point"}
}