{
  "type": "Feature",
  "properties": {
    "iso:country":"DE",
    "sg:address":"Schillerstr. 74",
    "sg:city":"Grevenbroich",
    "sg:phone":"+49 2181/41132",
    "sg:postcode":"41515",
    "sg:province":"Nordrhein-Westfalen",
    "wof:name":"J. Heyll Elektroinstallation",
    "wof:placetype":"venue"
},
  "geometry": {"coordinates":[6.577681,51.09687],"type":"Point"}
}