{
  "type": "Feature",
  "properties": {
    "iso:country":"DE",
    "sg:address":"Martin-Luther-Str. 1",
    "sg:city":"Leinfelden-Echterdingen",
    "sg:phone":"+49 711/792773",
    "sg:postcode":"70771",
    "sg:province":"Baden-W\u00fcrttemberg",
    "wof:name":"Restaurant Zeus",
    "wof:placetype":"venue"
},
  "geometry": {"coordinates":[9.1630544662,48.6839485168],"type":"Point"}
}