{
  "type": "Feature",
  "properties": {
    "iso:country":"DE",
    "sg:address":"Ebereschenweg 36",
    "sg:city":"Oberhausen",
    "sg:phone":"+49 208/670058",
    "sg:postcode":"46147",
    "sg:province":"Nordrhein-Westfalen",
    "wof:name":"Karl-heinz W\u00f6lfer Ingenieur",
    "wof:placetype":"venue"
},
  "geometry": {"coordinates":[6.830619812,51.5445785522],"type":"Point"}
}