{
  "type": "Feature",
  "properties": {
    "iso:country":"DE",
    "sg:address":"Wurzerstr. 16",
    "sg:city":"M\u00fcnchen",
    "sg:postcode":"80539",
    "sg:province":"Bayern",
    "wof:name":"Egp Verwaltungs-gmbh",
    "wof:placetype":"venue"
},
  "geometry": {"coordinates":[11.582621,48.139175],"type":"Point"}
}