{
  "type": "Feature",
  "properties": {
    "iso:country":"DE",
    "sg:address":"Aachener Str. 19b",
    "sg:city":"D\u00fcren",
    "sg:phone":"+49 2421/503450",
    "sg:postcode":"52349",
    "sg:province":"Nordrhein-Westfalen",
    "wof:name":"N. Merkens Rechtsanwalt",
    "wof:placetype":"venue"
},
  "geometry": {"coordinates":[6.4782390594,50.7978973389],"type":"Point"}
}