{
  "type": "Feature",
  "properties": {
    "iso:country":"DE",
    "sg:address":"Rosenweg 5",
    "sg:city":"Weiden",
    "sg:phone":"+49 961/5979",
    "sg:postcode":"92637",
    "sg:province":"Bayern",
    "wof:name":"Georg H\u00e4rtl",
    "wof:placetype":"venue"
},
  "geometry": {"coordinates":[12.1419658661,49.6468276978],"type":"Point"}
}