{
  "type": "Feature",
  "properties": {
    "iso:country":"DE",
    "sg:address":"Haslacher Feld 5",
    "sg:city":"Traunstein",
    "sg:phone":"+49 861/986430",
    "sg:postcode":"83278",
    "sg:province":"Bayern",
    "wof:name":"Real",
    "wof:placetype":"venue"
},
  "geometry": {"coordinates":[12.6283025742,47.8539581299],"type":"Point"}
}