{
  "type": "Feature",
  "properties": {
    "iso:country":"DE",
    "sg:address":"Kantstr. 13",
    "sg:city":"Lorsch",
    "sg:phone":"+49 6251/54892",
    "sg:postcode":"64653",
    "sg:province":"Hessen",
    "wof:name":"Sozialkreis Hannelore Lohrum",
    "wof:placetype":"venue"
},
  "geometry": {"coordinates":[8.5615558624,49.6454658508],"type":"Point"}
}