{
  "type": "Feature",
  "properties": {
    "iso:country":"DE",
    "sg:address":"Hauptstr. 33",
    "sg:city":"Ulrichstein",
    "sg:phone":"+49 6645/7140",
    "sg:postcode":"35327",
    "sg:province":"Hessen",
    "wof:name":"Bistro Lichtblick",
    "wof:placetype":"venue"
},
  "geometry": {"coordinates":[9.1891622543,50.5792579651],"type":"Point"}
}