{
  "type": "Feature",
  "properties": {
    "iso:country":"DE",
    "sg:address":"Sch\u00f6nfeldstr. 19",
    "sg:city":"M\u00fcnchen",
    "sg:postcode":"80539",
    "sg:province":"Bayern",
    "wof:name":"New Tom Deutschland Ag",
    "wof:placetype":"venue"
},
  "geometry": {"coordinates":[11.5834932327,48.1456375122],"type":"Point"}
}