{
  "type": "Feature",
  "properties": {
    "iso:country":"DE",
    "sg:address":"Am Hohen Ufer 1",
    "sg:city":"Schwarmstedt",
    "sg:postcode":"29690",
    "sg:province":"Niedersachsen",
    "wof:name":"Leva Quell Levitations- Und Kolloidaltechnologie Ag",
    "wof:placetype":"venue"
},
  "geometry": {"coordinates":[9.6019706726,52.6847572327],"type":"Point"}
}