{
  "type": "Feature",
  "properties": {
    "iso:country":"DE",
    "sg:address":"Sernatingenstr. 8a",
    "sg:city":"Bodman-Ludwigshafen",
    "sg:phone":"+49 7773/5308",
    "sg:postcode":"78351",
    "sg:province":"Baden-W\u00fcrttemberg",
    "wof:name":"Fritz Blender",
    "wof:placetype":"venue"
},
  "geometry": {"coordinates":[9.059161,47.818909],"type":"Point"}
}