{
  "type": "Feature",
  "properties": {
    "iso:country":"DE",
    "sg:address":"H\u00f6chsten 29",
    "sg:city":"Wuppertal",
    "sg:phone":"+49 202/445233",
    "sg:postcode":"42105",
    "sg:province":"Nordrhein-Westfalen",
    "wof:name":"Willi Stiefeling",
    "wof:placetype":"venue"
},
  "geometry": {"coordinates":[7.141407,51.262783],"type":"Point"}
}