{
  "type": "Feature",
  "properties": {
    "iso:country":"DE",
    "sg:address":"Wolfhager Str. 315",
    "sg:city":"Kassel",
    "sg:phone":"+49 561/883927",
    "sg:postcode":"34128",
    "sg:province":"Hessen",
    "wof:name":"Klaus Nasemann",
    "wof:placetype":"venue"
},
  "geometry": {"coordinates":[9.4535217285,51.3314056396],"type":"Point"}
}