{
  "type": "Feature",
  "properties": {
    "iso:country":"DE",
    "sg:address":"Karl-Schurz-Str. 62",
    "sg:city":"Karlsruhe",
    "sg:phone":"+49 721/562801",
    "sg:postcode":"76187",
    "sg:province":"Baden-W\u00fcrttemberg",
    "wof:name":"J. Helfer",
    "wof:placetype":"venue"
},
  "geometry": {"coordinates":[8.3510608673,49.0342597961],"type":"Point"}
}