{
  "type": "Feature",
  "properties": {
    "iso:country":"DE",
    "sg:address":"Mechenharder Str. 23",
    "sg:city":"Elsenfeld",
    "sg:phone":"+49 6022/9265",
    "sg:postcode":"63820",
    "sg:province":"Bayern",
    "wof:name":"Ernst Reichert",
    "wof:placetype":"venue"
},
  "geometry": {"coordinates":[9.202854,49.828018],"type":"Point"}
}