{
  "type": "Feature",
  "properties": {
    "iso:country":"DE",
    "sg:address":"Alter Markt 13",
    "sg:city":"Magdeburg",
    "sg:phone":"+49 391/5682323",
    "sg:postcode":"39104",
    "sg:province":"Sachsen-Anhalt",
    "wof:name":"Ratskeller Gastst\u00e4tte",
    "wof:placetype":"venue"
},
  "geometry": {"coordinates":[11.6383800507,52.1319694519],"type":"Point"}
}