{
  "type": "Feature",
  "properties": {
    "iso:country":"DE",
    "sg:address":"Ansbacher Str. 56",
    "sg:city":"Bechhofen",
    "sg:phone":"+49 9822/82810",
    "sg:postcode":"91572",
    "sg:province":"Bayern",
    "wof:name":"Spedition Friedrich Zwengauer",
    "wof:placetype":"venue"
},
  "geometry": {"coordinates":[10.5563154221,49.1610794067],"type":"Point"}
}