{
  "type": "Feature",
  "properties": {
    "iso:country":"DE",
    "sg:address":"Friesenheimer Str. 7b",
    "sg:city":"Mannheim",
    "sg:phone":"+49 621/32320",
    "sg:postcode":"68169",
    "sg:province":"Baden-W\u00fcrttemberg",
    "wof:name":"Silbernagel Verwaltungs Gmbh & Co. Beteiligungs- Und",
    "wof:placetype":"venue"
},
  "geometry": {"coordinates":[8.453464,49.511185],"type":"Point"}
}