{
  "type": "Feature",
  "properties": {
    "iso:country":"DE",
    "sg:address":"Eberhardstr. 2",
    "sg:city":"Giengen",
    "sg:phone":"+49 7322/22244",
    "sg:postcode":"89537",
    "sg:province":"Baden-W\u00fcrttemberg",
    "wof:name":"Gabriele Maletz Krankengymnastin",
    "wof:placetype":"venue"
},
  "geometry": {"coordinates":[10.246038,48.622898],"type":"Point"}
}