{
  "type": "Feature",
  "properties": {
    "iso:country":"DE",
    "sg:address":"Kronprinzenstr. 9",
    "sg:city":"Essen",
    "sg:phone":"+49 201/821530",
    "sg:postcode":"45128",
    "sg:province":"Nordrhein-Westfalen",
    "wof:name":"Aachener Siedlungs- Und Wohnungsgesellschaft Mbh",
    "wof:placetype":"venue"
},
  "geometry": {"coordinates":[7.0181851387,51.4458389282],"type":"Point"}
}