{
  "type": "Feature",
  "properties": {
    "iso:country":"DE",
    "sg:address":"Stader Str. 26",
    "sg:city":"Wischhafen",
    "sg:phone":"+49 4770/7102",
    "sg:postcode":"21737",
    "sg:province":"Niedersachsen",
    "wof:name":"Gastst\u00e4tte W. Kurbjuweit",
    "wof:placetype":"venue"
},
  "geometry": {"coordinates":[9.3326368332,53.746006012],"type":"Point"}
}