{
  "type": "Feature",
  "properties": {
    "iso:country":"DE",
    "sg:address":"Kiefernweg 48",
    "sg:city":"Unna",
    "sg:phone":"+49 2303/86909",
    "sg:postcode":"59423",
    "sg:province":"Nordrhein-Westfalen",
    "wof:name":"K. Witschass Ingenieur",
    "wof:placetype":"venue"
},
  "geometry": {"coordinates":[7.6770401001,51.526184082],"type":"Point"}
}