{
  "type": "Feature",
  "properties": {
    "iso:country":"DE",
    "sg:address":"Mindener Str. 6",
    "sg:city":"Berlin",
    "sg:phone":"+49 30/3442017",
    "sg:postcode":"10589",
    "sg:province":"Berlin",
    "wof:name":"Arbeiterwohlfahrt Landesverband Berlin E. V.",
    "wof:placetype":"venue"
},
  "geometry": {"coordinates":[13.300833,52.525017],"type":"Point"}
}