{
  "type": "Feature",
  "properties": {
    "iso:country":"DE",
    "sg:address":"Erbacher Str. 2",
    "sg:city":"H\u00f6chst",
    "sg:phone":"+49 6163/2264",
    "sg:postcode":"64739",
    "sg:province":"Hessen",
    "wof:name":"Probst",
    "wof:placetype":"venue"
},
  "geometry": {"coordinates":[8.97035,49.789299],"type":"Point"}
}