{
  "type": "Feature",
  "properties": {
    "iso:country":"DE",
    "sg:address":"In der R\u00f6de 32",
    "sg:city":"M\u00fchltal",
    "sg:phone":"+49 6151/14310",
    "sg:postcode":"64367",
    "sg:province":"Hessen",
    "wof:name":"Rolf Werle Architekt",
    "wof:placetype":"venue"
},
  "geometry": {"coordinates":[8.692682,49.840511],"type":"Point"}
}