{
  "type": "Feature",
  "properties": {
    "iso:country":"DE",
    "sg:address":"Villichgasse 17",
    "sg:city":"Bonn",
    "sg:phone":"+49 228/364997",
    "sg:postcode":"53177",
    "sg:province":"Nordrhein-Westfalen",
    "wof:name":"Spielkisten Automaten- Aufstellungsges. Mbh & Co. Kg",
    "wof:placetype":"venue"
},
  "geometry": {"coordinates":[7.1534309387,50.6841430664],"type":"Point"}
}