{
  "type": "Feature",
  "properties": {
    "iso:country":"DE",
    "sg:address":"Waldhofstr. 15",
    "sg:city":"Ellerbek",
    "sg:phone":"+49 4101/38180",
    "sg:postcode":"25474",
    "sg:province":"Schleswig-Holstein",
    "wof:name":"G\u00fcnter Kr\u00fcger S\u00f6hne Gmbh",
    "wof:placetype":"venue"
},
  "geometry": {"coordinates":[9.8854951859,53.6438903809],"type":"Point"}
}