{
  "type": "Feature",
  "properties": {
    "iso:country":"DE",
    "sg:address":"Thuyring 27",
    "sg:city":"Berlin",
    "sg:postcode":"12101",
    "sg:province":"Berlin",
    "wof:name":"Dr. Helga Moerickes Homepage",
    "wof:placetype":"venue"
},
  "geometry": {"coordinates":[13.382063,52.474571],"type":"Point"}
}