{
  "type": "Feature",
  "properties": {
    "iso:country":"DE",
    "sg:address":"Weinbergstr. 26",
    "sg:city":"Neckarbischofsheim",
    "sg:phone":"+49 7263/6209",
    "sg:postcode":"74924",
    "sg:province":"Baden-W\u00fcrttemberg",
    "wof:name":"Helmut Vanek",
    "wof:placetype":"venue"
},
  "geometry": {"coordinates":[8.9763832092,49.2940750122],"type":"Point"}
}