{
  "type": "Feature",
  "properties": {
    "iso:country":"DE",
    "sg:address":"Ringstr. 14",
    "sg:city":"Ramstein-Miesenbach",
    "sg:phone":"+49 6371/50691",
    "sg:postcode":"66877",
    "sg:province":"Rheinland-Pfalz",
    "wof:name":"Ev. Pfarramt Miesenbach",
    "wof:placetype":"venue"
},
  "geometry": {"coordinates":[7.553937912,49.4603919983],"type":"Point"}
}