{
  "type": "Feature",
  "properties": {
    "iso:country":"DE",
    "sg:address":"Happinger Str. 98",
    "sg:city":"Rosenheim",
    "sg:postcode":"83026",
    "sg:province":"Bayern",
    "wof:name":"Medi-develop Medizinische Und Technische Handels-gmbh",
    "wof:placetype":"venue"
},
  "geometry": {"coordinates":[12.124812,47.840038],"type":"Point"}
}