{
  "type": "Feature",
  "properties": {
    "iso:country":"DE",
    "sg:address":"Lerchenweg 5",
    "sg:city":"L\u00fcdinghausen",
    "sg:phone":"+49 2591/8318",
    "sg:postcode":"59348",
    "sg:province":"Nordrhein-Westfalen",
    "wof:name":"I. Drees Heissmangel",
    "wof:placetype":"venue"
},
  "geometry": {"coordinates":[7.3943829536,51.761051178],"type":"Point"}
}