{
  "type": "Feature",
  "properties": {
    "iso:country":"DE",
    "sg:address":"Keltenstr. 4",
    "sg:city":"Reichling",
    "sg:postcode":"86934",
    "sg:province":"Bayern",
    "wof:name":"Bk-electronics Verwaltungs Gmbh",
    "wof:placetype":"venue"
},
  "geometry": {"coordinates":[10.9266633987,47.9240989685],"type":"Point"}
}