{
  "type": "Feature",
  "properties": {
    "iso:country":"DE",
    "sg:address":"Raiffeisenweg 7",
    "sg:city":"Kirchhain - Betziesdorf",
    "sg:phone":"+49 6427/478",
    "sg:postcode":"35274",
    "sg:province":"Hessen",
    "wof:name":"Folklore - Tanz Mit Der Folkloregruppe Betziesdorf",
    "wof:placetype":"venue"
},
  "geometry": {"coordinates":[8.921126,50.821774],"type":"Point"}
}