{
  "type": "Feature",
  "properties": {
    "iso:country":"DE",
    "sg:address":"Rosenstr. 4",
    "sg:city":"Filderstadt",
    "sg:phone":"+49 711/7001450",
    "sg:postcode":"70794",
    "sg:province":"Baden-W\u00fcrttemberg",
    "wof:name":"Viw Asset Management Ges. F\u00fcr Verm\u00f6gensberatung",
    "wof:placetype":"venue"
},
  "geometry": {"coordinates":[9.2157831192,48.6784934998],"type":"Point"}
}