{
  "type": "Feature",
  "properties": {
    "iso:country":"DE",
    "sg:address":"Bottinger Str. 9",
    "sg:city":"Teningen",
    "sg:phone":"+49 7663/50022",
    "sg:postcode":"79331",
    "sg:province":"Baden-W\u00fcrttemberg",
    "wof:name":"Eloma-pac Gmbh",
    "wof:placetype":"venue"
},
  "geometry": {"coordinates":[7.7784018517,48.106086731],"type":"Point"}
}