{
  "type": "Feature",
  "properties": {
    "iso:country":"DE",
    "sg:address":"Seitenbeutel 16",
    "sg:city":"Strodehne",
    "sg:postcode":"14728",
    "sg:province":"Brandenburg",
    "wof:name":"Havell\u00e4ndische Angel- Ger\u00e4tebau Gmbh",
    "wof:placetype":"venue"
},
  "geometry": {"coordinates":[12.2250156403,52.7637748718],"type":"Point"}
}