{
  "type": "Feature",
  "properties": {
    "iso:country":"DE",
    "sg:address":"Feldstr. 53",
    "sg:city":"Delbr\u00fcck",
    "sg:phone":"+49 5294/98600",
    "sg:postcode":"33129",
    "sg:province":"Nordrhein-Westfalen",
    "wof:name":"Junior Spielplatzger\u00e4te Gmbh",
    "wof:placetype":"venue"
},
  "geometry": {"coordinates":[8.6102256775,51.8099822998],"type":"Point"}
}