{
  "type": "Feature",
  "properties": {
    "iso:country":"DE",
    "sg:address":"Schlesierplatz 11",
    "sg:city":"Brunsb\u00fcttel",
    "sg:phone":"+49 4852/4370",
    "sg:postcode":"25541",
    "sg:province":"Schleswig-Holstein",
    "wof:name":"J\u00fcrgen Franck",
    "wof:placetype":"venue"
},
  "geometry": {"coordinates":[9.1473093033,53.9049224854],"type":"Point"}
}