{
  "type": "Feature",
  "properties": {
    "iso:country":"DE",
    "sg:address":"Saarstr. 115",
    "sg:city":"Kandel",
    "sg:phone":"+49 7275/2229",
    "sg:postcode":"76870",
    "sg:province":"Rheinland-Pfalz",
    "wof:name":"Willi Jung",
    "wof:placetype":"venue"
},
  "geometry": {"coordinates":[8.1777582169,49.0765113831],"type":"Point"}
}