{
  "type": "Feature",
  "properties": {
    "iso:country":"DE",
    "sg:address":"Lindenaustr. 2",
    "sg:city":"Ohrdruf",
    "sg:phone":"+49 3624/402211",
    "sg:postcode":"99885",
    "sg:province":"Th\u00fcringen",
    "wof:name":"Ingo Schelter",
    "wof:placetype":"venue"
},
  "geometry": {"coordinates":[10.734357,50.825619],"type":"Point"}
}