{
  "type": "Feature",
  "properties": {
    "iso:country":"DE",
    "sg:address":"Landskroner Str. 112",
    "sg:city":"Bad Neuenahr-Ahrweiler",
    "sg:phone":"+49 2641/25182",
    "sg:postcode":"53474",
    "sg:province":"Rheinland-Pfalz",
    "wof:name":"Paul Sch\u00e4fer",
    "wof:placetype":"venue"
},
  "geometry": {"coordinates":[7.1636009216,50.5510520935],"type":"Point"}
}