{
  "type": "Feature",
  "properties": {
    "iso:country":"DE",
    "sg:address":"Schafshagenberg 5A",
    "sg:city":"Hamburg",
    "sg:phone":"+49 40/7600025",
    "sg:postcode":"21077",
    "sg:province":"Hamburg",
    "wof:name":"Barona Sportwerbung Gmbh",
    "wof:placetype":"venue"
},
  "geometry": {"coordinates":[9.952249527,53.4369812012],"type":"Point"}
}