{
  "type": "Feature",
  "properties": {
    "iso:country":"DE",
    "sg:address":"Egerlandstr. 8",
    "sg:city":"B\u00fcrgstadt",
    "sg:phone":"+49 9371/2972",
    "sg:postcode":"63927",
    "sg:province":"Bayern",
    "wof:name":"Heinz Ahrens",
    "wof:placetype":"venue"
},
  "geometry": {"coordinates":[9.2735013962,49.7087669373],"type":"Point"}
}