{
  "type": "Feature",
  "properties": {
    "iso:country":"DE",
    "sg:address":"Maximilianstr. 28",
    "sg:city":"Speyer",
    "sg:phone":"+49 6232/292830",
    "sg:postcode":"67346",
    "sg:province":"Rheinland-Pfalz",
    "wof:name":"Dirk Hiltner",
    "wof:placetype":"venue"
},
  "geometry": {"coordinates":[8.4359807968,49.3173866272],"type":"Point"}
}