{
  "type": "Feature",
  "properties": {
    "iso:country":"DE",
    "sg:address":"F\u00e4rbergasse 1",
    "sg:city":"Waldkirchen",
    "sg:phone":"+49 8581/2844",
    "sg:postcode":"94065",
    "sg:province":"Bayern",
    "wof:name":"Charivari",
    "wof:placetype":"venue"
},
  "geometry": {"coordinates":[13.6021757126,48.730922699],"type":"Point"}
}