{
  "type": "Feature",
  "properties": {
    "iso:country":"DE",
    "sg:address":"Nevinghoff 25::",
    "sg:city":"Muenster",
    "sg:phone":"+49 4925/1288",
    "sg:postcode":"48147",
    "sg:province":"Nordrhein-Westfalen",
    "wof:name":"Buchungszentrale Der Westfaelisch-lippischen Sparkassen, Gesellschaft Mit Beschraenkter Ha",
    "wof:placetype":"venue"
},
  "geometry": {"coordinates":[7.632849,51.985046],"type":"Point"}
}