{
  "type": "Feature",
  "properties": {
    "iso:country":"DE",
    "sg:address":"Joachimsthaler Weg 5",
    "sg:city":"St. Andreasberg",
    "sg:phone":"+49 5582/290",
    "sg:postcode":"37444",
    "sg:province":"Niedersachsen",
    "wof:name":"Haus Ursula",
    "wof:placetype":"venue"
},
  "geometry": {"coordinates":[10.5174074173,51.7179412842],"type":"Point"}
}