{
  "type": "Feature",
  "properties": {
    "iso:country":"DE",
    "sg:address":"Dieselstr. 25",
    "sg:city":"Garbsen",
    "sg:phone":"+49 5131/6689",
    "sg:postcode":"30827",
    "sg:province":"Niedersachsen",
    "wof:name":"U. Wagenknecht Gmbh",
    "wof:placetype":"venue"
},
  "geometry": {"coordinates":[9.6002969742,52.4490890503],"type":"Point"}
}