{
  "type": "Feature",
  "properties": {
    "iso:country":"DE",
    "sg:address":"Waldstra\u00dfe 11",
    "sg:city":"Rotenhain",
    "sg:phone":"+49 2661/951155",
    "sg:postcode":"56459",
    "sg:province":"Rheinland-Pfalz",
    "wof:name":"Tauch-paradise",
    "wof:placetype":"venue"
},
  "geometry": {"coordinates":[7.880102,50.59819],"type":"Point"}
}