{
  "type": "Feature",
  "properties": {
    "iso:country":"DE",
    "sg:address":"Daimlerstr. 16",
    "sg:city":"Dornhan",
    "sg:phone":"+49 7455/509",
    "sg:postcode":"72175",
    "sg:province":"Baden-W\u00fcrttemberg",
    "wof:name":"Helmut Bossert",
    "wof:placetype":"venue"
},
  "geometry": {"coordinates":[8.502649,48.350288],"type":"Point"}
}