{
  "type": "Feature",
  "properties": {
    "iso:country":"DE",
    "sg:address":"Seilergasse 1",
    "sg:city":"Fl\u00f6rsheim",
    "sg:phone":"+49 6145/6664",
    "sg:postcode":"65439",
    "sg:province":"Hessen",
    "wof:name":"K.-p. Kraus",
    "wof:placetype":"venue"
},
  "geometry": {"coordinates":[8.4255361557,50.010635376],"type":"Point"}
}