{
  "type": "Feature",
  "properties": {
    "iso:country":"DE",
    "sg:address":"Amselstr. 39",
    "sg:city":"Hemhofen",
    "sg:phone":"+49 9195/2905",
    "sg:postcode":"91334",
    "sg:province":"Bayern",
    "wof:name":"G. Und H. Motz",
    "wof:placetype":"venue"
},
  "geometry": {"coordinates":[10.9385690689,49.6890907288],"type":"Point"}
}