{
  "type": "Feature",
  "properties": {
    "iso:country":"DE",
    "sg:address":"M\u00fchlenweg 26",
    "sg:city":"Seeburg",
    "sg:phone":"+49 5528/581",
    "sg:postcode":"37136",
    "sg:province":"Niedersachsen",
    "wof:name":"Walter W\u00fcstefeld Fliesenlegerei",
    "wof:placetype":"venue"
},
  "geometry": {"coordinates":[10.1866989136,51.5655479431],"type":"Point"}
}