{
  "type": "Feature",
  "properties": {
    "iso:country":"DE",
    "sg:address":"Urnenweg 33",
    "sg:city":"Preetz",
    "sg:postcode":"24211",
    "sg:province":"Schleswig-Holstein",
    "wof:name":"B\u00e4hr Bau Gmbh",
    "wof:placetype":"venue"
},
  "geometry": {"coordinates":[10.290998,54.244591],"type":"Point"}
}