{
  "type": "Feature",
  "properties": {
    "iso:country":"DE",
    "sg:address":"Griesstetter Str. 46",
    "sg:city":"Dietfurt",
    "sg:phone":"+49 8464/1826",
    "sg:postcode":"92345",
    "sg:province":"Bayern",
    "wof:name":"Wilfried Handfest",
    "wof:placetype":"venue"
},
  "geometry": {"coordinates":[11.59634,49.02401],"type":"Point"}
}