{
  "type": "Feature",
  "properties": {
    "iso:country":"DE",
    "sg:address":"Hochweiseler Str. 36",
    "sg:city":"Butzbach",
    "sg:phone":"+49 6033/5582",
    "sg:postcode":"35510",
    "sg:province":"Hessen",
    "wof:name":"H\u00fcttl S Blumeneck",
    "wof:placetype":"venue"
},
  "geometry": {"coordinates":[8.664735,50.428982],"type":"Point"}
}