{
  "type": "Feature",
  "properties": {
    "iso:country":"DE",
    "sg:address":"Schillingsstr. 40",
    "sg:city":"D\u00fcren",
    "sg:phone":"+49 2421/63920",
    "sg:postcode":"52355",
    "sg:province":"Nordrhein-Westfalen",
    "wof:name":"Schillings-apotheke",
    "wof:placetype":"venue"
},
  "geometry": {"coordinates":[6.450158,50.797382],"type":"Point"}
}