{
  "type": "Feature",
  "properties": {
    "iso:country":"DE",
    "sg:address":"Birkhahnweg 49",
    "sg:city":"M\u00fcnchen",
    "sg:phone":"+49 89/4304278",
    "sg:postcode":"81827",
    "sg:province":"Bayern",
    "wof:name":"Karl Rauffer",
    "wof:placetype":"venue"
},
  "geometry": {"coordinates":[11.70049,48.111057],"type":"Point"}
}