{
  "type": "Feature",
  "properties": {
    "iso:country":"DE",
    "sg:address":"Von-Wemighe-Str. 20",
    "sg:city":"Sehnde",
    "sg:phone":"+49 5138/616770",
    "sg:postcode":"31319",
    "sg:province":"Niedersachsen",
    "wof:name":"Heinrich Heineke",
    "wof:placetype":"venue"
},
  "geometry": {"coordinates":[9.934374,52.299465],"type":"Point"}
}