{
  "type": "Feature",
  "properties": {
    "iso:country":"DE",
    "sg:address":"Zum Klosterstein 20",
    "sg:city":"Ludwigsau",
    "sg:phone":"+49 6670/287",
    "sg:postcode":"36251",
    "sg:province":"Hessen",
    "wof:name":"H. Rossbach & Sohn",
    "wof:placetype":"venue"
},
  "geometry": {"coordinates":[9.575742,50.965836],"type":"Point"}
}