{
  "type": "Feature",
  "properties": {
    "iso:country":"DE",
    "sg:address":"H\u00f6lderlinstr. 28",
    "sg:city":"Rudersberg",
    "sg:phone":"+49 7183",
    "sg:postcode":"73635",
    "sg:province":"Baden-W\u00fcrttemberg",
    "wof:name":"Webdesign, Pr\u00e4sentationen, Prospekte - Silke Degel",
    "wof:placetype":"venue"
},
  "geometry": {"coordinates":[9.526041,48.890106],"type":"Point"}
}