{
  "type": "Feature",
  "properties": {
    "iso:country":"DE",
    "sg:address":"Geschwister-Scholl-Str. 8",
    "sg:city":"Caputh",
    "sg:phone":"+49 33209/70232",
    "sg:postcode":"14548",
    "sg:province":"Brandenburg",
    "wof:name":"Thomas Helm",
    "wof:placetype":"venue"
},
  "geometry": {"coordinates":[12.9815206528,52.3401565552],"type":"Point"}
}