{
  "type": "Feature",
  "properties": {
    "iso:country":"DE",
    "sg:address":"Schwarzenbergstr. 34",
    "sg:city":"Hamburg",
    "sg:postcode":"21073",
    "sg:province":"Hamburg",
    "wof:name":"Avd Loft-konzeptbau Gmbh",
    "wof:placetype":"venue"
},
  "geometry": {"coordinates":[9.97592,53.461937],"type":"Point"}
}