{
  "type": "Feature",
  "properties": {
    "iso:country":"DE",
    "sg:address":"Bogenstr. 3 b",
    "sg:city":"Schwabach",
    "sg:phone":"+49 9122/5257",
    "sg:postcode":"91126",
    "sg:province":"Bayern",
    "wof:name":"Willi Schneider Industrievertretungen Gmbh",
    "wof:placetype":"venue"
},
  "geometry": {"coordinates":[11.0167427063,49.3267631531],"type":"Point"}
}