{
  "type": "Feature",
  "properties": {
    "iso:country":"DE",
    "sg:address":"Oberdorfstr. 27a",
    "sg:city":"Singen",
    "sg:phone":"+49 7731/947020",
    "sg:postcode":"78224",
    "sg:province":"Baden-W\u00fcrttemberg",
    "wof:name":"Bk-eckert Gmbh",
    "wof:placetype":"venue"
},
  "geometry": {"coordinates":[8.8291578293,47.7674102783],"type":"Point"}
}