{
  "type": "Feature",
  "properties": {
    "iso:country":"DE",
    "sg:address":"Untere Vorstadt 21",
    "sg:city":"Albstadt",
    "sg:phone":"+49 7431/2526",
    "sg:postcode":"72458",
    "sg:province":"Baden-W\u00fcrttemberg",
    "wof:name":"Froemel Und Traeger Rechtsanw\u00e4lte",
    "wof:placetype":"venue"
},
  "geometry": {"coordinates":[9.0239591599,48.2135238647],"type":"Point"}
}