{
  "type": "Feature",
  "properties": {
    "iso:country":"DE",
    "sg:address":"Goethestr. 1",
    "sg:city":"Ketsch",
    "sg:phone":"+49 6202/69900",
    "sg:postcode":"68775",
    "sg:province":"Baden-W\u00fcrttemberg",
    "wof:name":"Arno Gruler Und Franz Weis Steuerberater",
    "wof:placetype":"venue"
},
  "geometry": {"coordinates":[8.5321464539,49.3676223755],"type":"Point"}
}