{
  "type": "Feature",
  "properties": {
    "iso:country":"DE",
    "sg:address":"Ziegelstr. 12",
    "sg:city":"Aalen",
    "sg:phone":"+49 7361/93040",
    "sg:postcode":"73431",
    "sg:province":"Baden-W\u00fcrttemberg",
    "wof:name":"Landeszentralbank In Baden-w\u00fcrttemberg",
    "wof:placetype":"venue"
},
  "geometry": {"coordinates":[10.1006336212,48.8379745483],"type":"Point"}
}