{
  "type": "Feature",
  "properties": {
    "iso:country":"DE",
    "sg:address":"M\u00fchlenstra\u00dfe 15/16",
    "sg:city":"G\u00fcstrow",
    "sg:phone":"+49 3843",
    "sg:postcode":"18273",
    "sg:province":"Mecklenburg-Vorpommern",
    "wof:name":"Citypoint Gmbh",
    "wof:placetype":"venue"
},
  "geometry": {"coordinates":[12.1787443161,53.7942962646],"type":"Point"}
}