{
  "type": "Feature",
  "properties": {
    "iso:country":"DE",
    "sg:address":"Gr\u00fcnbergallee 281",
    "sg:city":"Berlin",
    "sg:phone":"+49 30/6790090",
    "sg:postcode":"12526",
    "sg:province":"Berlin",
    "wof:name":"Wilfried Sievers Garten- Und Landschaft Gmbh",
    "wof:placetype":"venue"
},
  "geometry": {"coordinates":[13.5455589294,52.3989486694],"type":"Point"}
}