{
  "type": "Feature",
  "properties": {
    "iso:country":"DE",
    "sg:address":"Rh\u00f6nstr. 7",
    "sg:city":"H\u00fcnstetten",
    "sg:phone":"+49 6438/4204",
    "sg:postcode":"65510",
    "sg:province":"Hessen",
    "wof:name":"T. G. Ritter Spezialmaschinen Gmbh",
    "wof:placetype":"venue"
},
  "geometry": {"coordinates":[8.2123231888,50.2840690613],"type":"Point"}
}