{
  "type": "Feature",
  "properties": {
    "iso:country":"DE",
    "sg:address":"Auf der Heide 3",
    "sg:city":"Norken",
    "sg:phone":"+49 2661/7735",
    "sg:postcode":"57629",
    "sg:province":"Rheinland-Pfalz",
    "wof:name":"Josef Cappi",
    "wof:placetype":"venue"
},
  "geometry": {"coordinates":[7.900312,50.67498],"type":"Point"}
}