{
  "type": "Feature",
  "properties": {
    "iso:country":"DE",
    "sg:address":"Rudolf-Diesel-Str. 3",
    "sg:city":"Loxstedt",
    "sg:phone":"+49 4947/444630",
    "sg:postcode":"27612",
    "sg:province":"Niedersachsen",
    "wof:name":"Pinland Manufaktur & Handel Gmbh",
    "wof:placetype":"venue"
},
  "geometry": {"coordinates":[8.655443,53.476044],"type":"Point"}
}