{
  "type": "Feature",
  "properties": {
    "iso:country":"DE",
    "sg:address":"Ratzeburger Allee 96",
    "sg:city":"L\u00fcbeck",
    "sg:phone":"+49 451/599406",
    "sg:postcode":"23562",
    "sg:province":"Schleswig-Holstein",
    "wof:name":"T. Schreiber",
    "wof:placetype":"venue"
},
  "geometry": {"coordinates":[10.7078771591,53.8457794189],"type":"Point"}
}