{
  "type": "Feature",
  "properties": {
    "iso:country":"DE",
    "sg:address":"Weiler Str. 14 /1",
    "sg:city":"Blaubeuren",
    "sg:phone":"+49 7344/6563",
    "sg:postcode":"89143",
    "sg:province":"Baden-W\u00fcrttemberg",
    "wof:name":"Birgit Schurr",
    "wof:placetype":"venue"
},
  "geometry": {"coordinates":[9.78381,48.410355],"type":"Point"}
}