{
  "type": "Feature",
  "properties": {
    "iso:country":"DE",
    "sg:address":"Hebborner Feld 23",
    "sg:city":"Bergisch Gladbach",
    "sg:postcode":"51467",
    "sg:province":"Nordrhein-Westfalen",
    "wof:name":"Gtb Gastro Team Bergisch Gladbach Gmbh & Co.",
    "wof:placetype":"venue"
},
  "geometry": {"coordinates":[7.1280388832,51.0023193359],"type":"Point"}
}