{
  "type": "Feature",
  "properties": {
    "iso:country":"DE",
    "sg:address":"Bochumer Str. 30",
    "sg:city":"Nordhausen",
    "sg:phone":"+49 3631/994974",
    "sg:postcode":"99734",
    "sg:province":"Th\u00fcringen",
    "wof:name":"Huk-coburg",
    "wof:placetype":"venue"
},
  "geometry": {"coordinates":[10.7816028595,51.5010147095],"type":"Point"}
}