{
  "type": "Feature",
  "properties": {
    "iso:country":"DE",
    "sg:address":"Waitzstr. 10",
    "sg:city":"Kiel",
    "sg:phone":"+49 431/566263",
    "sg:postcode":"24105",
    "sg:province":"Schleswig-Holstein",
    "wof:name":"F\u00f6hrde Club",
    "wof:placetype":"venue"
},
  "geometry": {"coordinates":[10.1414442062,54.335483551],"type":"Point"}
}