{
  "type": "Feature",
  "properties": {
    "iso:country":"DE",
    "sg:city":"Ellenz-Poltersdorf",
    "sg:phone":"+49 2673/1272",
    "sg:postcode":"56821",
    "sg:province":"Rheinland-Pfalz",
    "wof:name":"Campingplatz S\u00e4nger",
    "wof:placetype":"venue"
},
  "geometry": {"coordinates":[7.232598,50.117344],"type":"Point"}
}