{
  "type": "Feature",
  "properties": {
    "iso:country":"DE",
    "sg:address":"Diestedder Str. 3",
    "sg:city":"Wadersloh",
    "sg:postcode":"59329",
    "sg:province":"Nordrhein-Westfalen",
    "wof:name":"Gloria Werke - Feuerl\u00f6scher Und Ger\u00e4te F\u00fcr Haus Und Garten",
    "wof:placetype":"venue"
},
  "geometry": {"coordinates":[8.2424812317,51.7353019714],"type":"Point"}
}