{
  "type": "Feature",
  "properties": {
    "iso:country":"DE",
    "sg:address":"Clara-Viebig-Str. 4",
    "sg:city":"Bad Bertrich",
    "sg:phone":"+49 2674/1820",
    "sg:postcode":"56864",
    "sg:province":"Rheinland-Pfalz",
    "wof:name":"Blank-klinik Gesch\u00e4fts- F\u00fchrungs- Und Verwaltungs Gmbh",
    "wof:placetype":"venue"
},
  "geometry": {"coordinates":[7.030378,50.070278],"type":"Point"}
}