{
  "type": "Feature",
  "properties": {
    "iso:country":"DE",
    "sg:address":"Ansgarstr. 46b",
    "sg:city":"Elmshorn",
    "sg:phone":"+49 4121/462660",
    "sg:postcode":"25336",
    "sg:province":"Schleswig-Holstein",
    "wof:name":"Automatenbetriebe Zur Speeldeel",
    "wof:placetype":"venue"
},
  "geometry": {"coordinates":[9.6597089767,53.7442741394],"type":"Point"}
}