{
  "type": "Feature",
  "properties": {
    "iso:country":"DE",
    "sg:address":"Bodelschwinghstr. 4",
    "sg:city":"Aachen",
    "sg:phone":"+49 241/35522",
    "sg:postcode":"52078",
    "sg:province":"Nordrhein-Westfalen",
    "wof:name":"Planungsgruppe-ladenbau",
    "wof:placetype":"venue"
},
  "geometry": {"coordinates":[6.13962,50.761208],"type":"Point"}
}