{
  "type": "Feature",
  "properties": {
    "iso:country":"DE",
    "sg:address":"Rittergutstr. 13",
    "sg:city":"Neustadt",
    "sg:phone":"+49 9568/5718",
    "sg:postcode":"96465",
    "sg:province":"Bayern",
    "wof:name":"Gerda Roos",
    "wof:placetype":"venue"
},
  "geometry": {"coordinates":[11.1296319962,50.3452186584],"type":"Point"}
}