{
  "type": "Feature",
  "properties": {
    "iso:country":"DE",
    "sg:address":"Hannoversche Str. 8-10",
    "sg:city":"Niestetal",
    "sg:phone":"+49 561/522061",
    "sg:postcode":"34266",
    "sg:province":"Hessen",
    "wof:name":"Heinrich Degenhardt Brennstoffhandel Kg",
    "wof:placetype":"venue"
},
  "geometry": {"coordinates":[9.5402,51.314919],"type":"Point"}
}