{
  "type": "Feature",
  "properties": {
    "iso:country":"DE",
    "sg:address":"Unterer Wei\u00dfer Weg 10",
    "sg:city":"K\u00f6ln",
    "sg:phone":"+49 221/393919",
    "sg:postcode":"50999",
    "sg:province":"Nordrhein-Westfalen",
    "wof:name":"Ulrike Spie\u00df Tennisanlage",
    "wof:placetype":"venue"
},
  "geometry": {"coordinates":[7.0274891853,50.8782844543],"type":"Point"}
}