{
  "type": "Feature",
  "properties": {
    "iso:country":"DE",
    "sg:address":"Kammerratsheide 13",
    "sg:city":"Bielefeld",
    "sg:phone":"+49 521",
    "sg:postcode":"33609",
    "sg:province":"Nordrhein-Westfalen",
    "wof:name":"Reinhard Stannek Rs Gmbh",
    "wof:placetype":"venue"
},
  "geometry": {"coordinates":[8.575663,52.040531],"type":"Point"}
}