{
  "type": "Feature",
  "properties": {
    "iso:country":"DE",
    "sg:address":"Sacco-Vanzetti-Str. 35",
    "sg:city":"Birkenwerder",
    "sg:phone":"+49 3303/402439",
    "sg:postcode":"16547",
    "sg:province":"Brandenburg",
    "wof:name":"Helmut Sauer & Partner",
    "wof:placetype":"venue"
},
  "geometry": {"coordinates":[13.279599,52.694069],"type":"Point"}
}