{
  "type": "Feature",
  "properties": {
    "iso:country":"DE",
    "sg:address":"Ostendorf 21",
    "sg:city":"Steinfurt",
    "sg:phone":"+49 2552/3802",
    "sg:postcode":"48565",
    "sg:province":"Nordrhein-Westfalen",
    "wof:name":"Reinhold Kamer",
    "wof:placetype":"venue"
},
  "geometry": {"coordinates":[7.441946,52.125458],"type":"Point"}
}