{
  "type": "Feature",
  "properties": {
    "iso:country":"DE",
    "sg:address":"Bahnhofstr. 17",
    "sg:city":"Gr\u00e4felfing",
    "sg:phone":"+49 89/852518",
    "sg:postcode":"82166",
    "sg:province":"Bayern",
    "wof:name":"H.-p. Brugger",
    "wof:placetype":"venue"
},
  "geometry": {"coordinates":[11.430432,48.117859],"type":"Point"}
}