{
  "type": "Feature",
  "properties": {
    "iso:country":"DE",
    "sg:address":"Am Teich 3",
    "sg:city":"Niesky",
    "sg:phone":"+49 3588/203203",
    "sg:postcode":"02906",
    "sg:province":"Sachsen",
    "wof:name":"Max Wieczorek",
    "wof:placetype":"venue"
},
  "geometry": {"coordinates":[14.7814655304,51.2963066101],"type":"Point"}
}