{
  "type": "Feature",
  "properties": {
    "iso:country":"DE",
    "sg:address":"Franz\u00f6sische Str. 7",
    "sg:city":"Saarlouis",
    "sg:phone":"+49 6831/46215",
    "sg:postcode":"66740",
    "sg:province":"Saarland",
    "wof:name":"J. Welling",
    "wof:placetype":"venue"
},
  "geometry": {"coordinates":[6.751696,49.314957],"type":"Point"}
}