{
  "type": "Feature",
  "properties": {
    "iso:country":"DE",
    "sg:address":"Hauptstr. 45",
    "sg:city":"G\u00f6llheim",
    "sg:phone":"+49 6351/5039",
    "sg:postcode":"67307",
    "sg:province":"Rheinland-Pfalz",
    "wof:name":"Becker Kaufhaus",
    "wof:placetype":"venue"
},
  "geometry": {"coordinates":[8.051044,49.594955],"type":"Point"}
}