{
  "type": "Feature",
  "properties": {
    "iso:country":"DE",
    "sg:address":"Krummbogen 15",
    "sg:city":"Marburg",
    "sg:phone":"+49 6421/62625",
    "sg:postcode":"35039",
    "sg:province":"Hessen",
    "wof:name":"Zeikon Zeichnung Und Konstruktion Gmbh",
    "wof:placetype":"venue"
},
  "geometry": {"coordinates":[8.776916,50.815784],"type":"Point"}
}