{
  "type": "Feature",
  "properties": {
    "iso:country":"DE",
    "sg:address":"Sossenheimer Weg 5-7",
    "sg:city":"Frankfurt",
    "sg:phone":"+49 69/3140620",
    "sg:postcode":"65929",
    "sg:province":"Hessen",
    "wof:name":"Hk Computer & Systemhaus",
    "wof:placetype":"venue"
},
  "geometry": {"coordinates":[8.5381803513,50.1116790771],"type":"Point"}
}