{
  "type": "Feature",
  "properties": {
    "iso:country":"DE",
    "sg:address":"Robert-Bosch-Str. 13",
    "sg:city":"Langen",
    "sg:phone":"+49 6103/7670",
    "sg:postcode":"63225",
    "sg:province":"Hessen",
    "wof:name":"Dreieich Spiegel Langener Druck- U. Verlagsges.",
    "wof:placetype":"venue"
},
  "geometry": {"coordinates":[8.6535730362,50.0015869141],"type":"Point"}
}