{
  "type": "Feature",
  "properties": {
    "iso:country":"DE",
    "sg:address":"Kleine Johannisstr. 17",
    "sg:city":"Hamburg",
    "sg:phone":"+49 40/335988",
    "sg:postcode":"20457",
    "sg:province":"Hamburg",
    "wof:name":"City Foto Hamburg Renate Jahnke",
    "wof:placetype":"venue"
},
  "geometry": {"coordinates":[9.9940023422,53.5491065979],"type":"Point"}
}