{
  "type": "Feature",
  "properties": {
    "iso:country":"DE",
    "sg:address":"Schmiedegasse 2",
    "sg:city":"Thum-Jahnsbach",
    "sg:phone":"+49 37297/2306",
    "sg:postcode":"09419",
    "sg:province":"Sachsen",
    "wof:name":"Herbert M\u00fcnzer",
    "wof:placetype":"venue"
},
  "geometry": {"coordinates":[12.936049,50.66621],"type":"Point"}
}