{
  "type": "Feature",
  "properties": {
    "iso:country":"DE",
    "sg:address":"Neugasse 10",
    "sg:city":"Konstanz",
    "sg:phone":"+49 7531/22950",
    "sg:postcode":"78462",
    "sg:province":"Baden-W\u00fcrttemberg",
    "wof:name":"Capri-fischerstube",
    "wof:placetype":"venue"
},
  "geometry": {"coordinates":[9.173789978,47.6588973999],"type":"Point"}
}