{
  "type": "Feature",
  "properties": {
    "iso:country":"DE",
    "sg:address":"Winkelser Str. 1",
    "sg:city":"Bad Kissingen",
    "sg:postcode":"97688",
    "sg:province":"Bayern",
    "wof:name":"Ahg Autohandelsges. Gaul Mbh",
    "wof:placetype":"venue"
},
  "geometry": {"coordinates":[10.0906562805,50.2031402588],"type":"Point"}
}