{
  "type": "Feature",
  "properties": {
    "iso:country":"DE",
    "sg:address":"Niederfeld 14",
    "sg:city":"Grefrath",
    "sg:phone":"+49 2158/4284",
    "sg:postcode":"47929",
    "sg:province":"Nordrhein-Westfalen",
    "wof:name":"A. Fuhrmann",
    "wof:placetype":"venue"
},
  "geometry": {"coordinates":[6.368938,51.352547],"type":"Point"}
}