{
  "type": "Feature",
  "properties": {
    "iso:country":"DE",
    "sg:address":"Lindenstr. 34",
    "sg:city":"Frankfurt",
    "sg:phone":"+49 335/23551",
    "sg:postcode":"15230",
    "sg:province":"Brandenburg",
    "wof:name":"B. Schulz",
    "wof:placetype":"venue"
},
  "geometry": {"coordinates":[14.5530748367,52.3347549438],"type":"Point"}
}