{
  "type": "Feature",
  "properties": {
    "iso:country":"DE",
    "sg:address":"Nienwohlder Str. 2",
    "sg:city":"Bargfeld-Stegen",
    "sg:phone":"+49 4532/1838",
    "sg:postcode":"23863",
    "sg:province":"Schleswig-Holstein",
    "wof:name":"Klaus Kock",
    "wof:placetype":"venue"
},
  "geometry": {"coordinates":[10.189365387,53.7668380737],"type":"Point"}
}