{
  "type": "Feature",
  "properties": {
    "iso:country":"DE",
    "sg:address":"K\u00f6nigsbacher Str. 78",
    "sg:city":"Pfinztal",
    "sg:phone":"+49 7240/4836",
    "sg:postcode":"76327",
    "sg:province":"Baden-W\u00fcrttemberg",
    "wof:name":"Kleintierzuchtverein C 11 Berghausen",
    "wof:placetype":"venue"
},
  "geometry": {"coordinates":[8.5525789261,48.9833869934],"type":"Point"}
}