{
  "type": "Feature",
  "properties": {
    "iso:country":"DE",
    "sg:address":"Klingenhagen 22",
    "sg:city":"Sassenberg",
    "sg:phone":"+49 2583/1033",
    "sg:postcode":"48336",
    "sg:province":"Nordrhein-Westfalen",
    "wof:name":"Berhard Schr\u00e4der",
    "wof:placetype":"venue"
},
  "geometry": {"coordinates":[8.042961,51.992584],"type":"Point"}
}