{
  "type": "Feature",
  "properties": {
    "iso:country":"DE",
    "sg:address":"Hauptstr. 28",
    "sg:city":"Bad Bodenteich",
    "sg:phone":"+49 5824/633",
    "sg:postcode":"29389",
    "sg:province":"Niedersachsen",
    "wof:name":"B. Und M. L\u00fcthe",
    "wof:placetype":"venue"
},
  "geometry": {"coordinates":[10.6819095612,52.8309059143],"type":"Point"}
}