{
  "type": "Feature",
  "properties": {
    "iso:country":"DE",
    "sg:address":"Hirschgasse 1",
    "sg:city":"T\u00fcbingen",
    "sg:phone":"+49 7071/551499",
    "sg:postcode":"72070",
    "sg:province":"Baden-W\u00fcrttemberg",
    "wof:name":"Pro Optik Augenoptik Fachgesch\u00e4ft Gmbh",
    "wof:placetype":"venue"
},
  "geometry": {"coordinates":[9.054206,48.520779],"type":"Point"}
}