{
  "type": "Feature",
  "properties": {
    "iso:country":"DE",
    "sg:address":"Leeraner Str. 10",
    "sg:city":"Filsum",
    "sg:phone":"+49 4957/477",
    "sg:postcode":"26849",
    "sg:province":"Niedersachsen",
    "wof:name":"Rsd-design Gmbh Lackierung U. Beschriftung Von Fahrzeugen U.",
    "wof:placetype":"venue"
},
  "geometry": {"coordinates":[7.629281,53.238865],"type":"Point"}
}