{
  "type": "Feature",
  "properties": {
    "iso:country":"DE",
    "sg:address":"Rennstieg 24",
    "sg:city":"Bremen",
    "sg:phone":"+49 421/445383",
    "sg:postcode":"28205",
    "sg:province":"Bremen",
    "wof:name":"Otto K\u00f6ther Gmbh & Co. Kg",
    "wof:placetype":"venue"
},
  "geometry": {"coordinates":[8.848877,53.070255],"type":"Point"}
}