{
  "type": "Feature",
  "properties": {
    "iso:country":"DE",
    "sg:address":"Hiera",
    "sg:city":"Lenzkirch",
    "sg:postcode":"79853",
    "sg:province":"Baden-W\u00fcrttemberg",
    "wof:name":"Lenzkircher Maschinen- Gemeinschaften",
    "wof:placetype":"venue"
},
  "geometry": {"coordinates":[8.2029094696,47.8829879761],"type":"Point"}
}