{
  "type": "Feature",
  "properties": {
    "iso:country":"DE",
    "sg:address":"Rosenring 7",
    "sg:city":"Scharnebeck",
    "sg:phone":"+49 4136/653",
    "sg:postcode":"21379",
    "sg:province":"Niedersachsen",
    "wof:name":"Hermann Kahle",
    "wof:placetype":"venue"
},
  "geometry": {"coordinates":[10.5056114197,53.2958068848],"type":"Point"}
}