{
  "type": "Feature",
  "properties": {
    "iso:country":"DE",
    "sg:address":"An der Schonung 34",
    "sg:city":"Cuxhaven",
    "sg:postcode":"27478",
    "sg:province":"Niedersachsen",
    "wof:name":"Rehdner Ingenieur",
    "wof:placetype":"venue"
},
  "geometry": {"coordinates":[8.6602497101,53.8244781494],"type":"Point"}
}