{
  "type": "Feature",
  "properties": {
    "iso:country":"DE",
    "sg:address":"Oberzierer Str. 28",
    "sg:city":"Niederzier",
    "sg:phone":"+49 2428/3814",
    "sg:postcode":"52382",
    "sg:province":"Nordrhein-Westfalen",
    "wof:name":"Gottfried Cremanns",
    "wof:placetype":"venue"
},
  "geometry": {"coordinates":[6.459629,50.857574],"type":"Point"}
}