{
  "type": "Feature",
  "properties": {
    "iso:country":"DE",
    "sg:address":"D\u00f6bernsche Str. 29",
    "sg:city":"Torgau",
    "sg:phone":"+49 3421/706975",
    "sg:postcode":"04860",
    "sg:province":"Sachsen",
    "wof:name":"Gerhard Riedner",
    "wof:placetype":"venue"
},
  "geometry": {"coordinates":[12.9947004318,51.5715484619],"type":"Point"}
}