{
  "type": "Feature",
  "properties": {
    "iso:country":"DE",
    "sg:address":"Kaufstr. 14",
    "sg:city":"Gr\u00fcnkraut",
    "sg:phone":"+49 751/60080",
    "sg:postcode":"88287",
    "sg:province":"Baden-W\u00fcrttemberg",
    "wof:name":"Blum-novotest Gmbh",
    "wof:placetype":"venue"
},
  "geometry": {"coordinates":[9.655189,47.753933],"type":"Point"}
}