{
  "type": "Feature",
  "properties": {
    "iso:country":"DE",
    "sg:address":"S\u00e4gerb\u00e4ume 4",
    "sg:city":"Wolfsburg",
    "sg:phone":"+49 4953/6394270",
    "sg:postcode":"38448",
    "sg:province":"Niedersachsen",
    "wof:name":"Haltern & Kaufmann Landschafts, Sportplatz & Tiefbau Gmbh",
    "wof:placetype":"venue"
},
  "geometry": {"coordinates":[10.857336,52.435528],"type":"Point"}
}