{
  "type": "Feature",
  "properties": {
    "iso:country":"DE",
    "sg:address":"Gereonswall 31 a",
    "sg:city":"K\u00f6ln",
    "sg:phone":"+49 221/131940",
    "sg:postcode":"50670",
    "sg:province":"Nordrhein-Westfalen",
    "wof:name":"Adriastube",
    "wof:placetype":"venue"
},
  "geometry": {"coordinates":[6.9429459572,50.9426727295],"type":"Point"}
}