{
  "type": "Feature",
  "properties": {
    "iso:country":"DE",
    "sg:address":"Albertstr. 7",
    "sg:city":"Backnang",
    "sg:phone":"+49 7191/68540",
    "sg:postcode":"71522",
    "sg:province":"Baden-W\u00fcrttemberg",
    "wof:name":"W\u00fcrttembergische Versicherung B.-m. Clauss",
    "wof:placetype":"venue"
},
  "geometry": {"coordinates":[9.4296016693,48.9451446533],"type":"Point"}
}