{
  "type": "Feature",
  "properties": {
    "iso:country":"DE",
    "sg:address":"Am Schie\u00dfgraben 11",
    "sg:city":"Elzach",
    "sg:phone":"+49 7682/9050",
    "sg:postcode":"79215",
    "sg:province":"Baden-W\u00fcrttemberg",
    "wof:name":"St. Elisabeth",
    "wof:placetype":"venue"
},
  "geometry": {"coordinates":[8.07005,48.174061],"type":"Point"}
}