{
  "type": "Feature",
  "properties": {
    "iso:country":"DE",
    "sg:address":"Akazienstr. 25",
    "sg:city":"Mannheim",
    "sg:phone":"+49 621/743877",
    "sg:postcode":"68305",
    "sg:province":"Baden-W\u00fcrttemberg",
    "wof:name":"Coffenco International Gmbh",
    "wof:placetype":"venue"
},
  "geometry": {"coordinates":[8.4766807556,49.5155792236],"type":"Point"}
}