{
  "type": "Feature",
  "properties": {
    "iso:country":"DE",
    "sg:address":"N\u00f6tten-Br\u00fcder-Wallstr. 22",
    "sg:city":"Soest",
    "sg:phone":"+49 2921/16257",
    "sg:postcode":"59494",
    "sg:province":"Nordrhein-Westfalen",
    "wof:name":"Euro Pub N\u00f6tten",
    "wof:placetype":"venue"
},
  "geometry": {"coordinates":[8.102388382,51.5758972168],"type":"Point"}
}