{
  "type": "Feature",
  "properties": {
    "iso:country":"DE",
    "sg:address":"Hauptstr. 21",
    "sg:city":"Linsburg",
    "sg:phone":"+49 5027/304",
    "sg:postcode":"31636",
    "sg:province":"Niedersachsen",
    "wof:name":"Heinfried Tegtmeyer",
    "wof:placetype":"venue"
},
  "geometry": {"coordinates":[9.308424,52.595272],"type":"Point"}
}