{
  "type": "Feature",
  "properties": {
    "iso:country":"DE",
    "sg:address":"Scharfstr. 22",
    "sg:city":"Mainburg",
    "sg:phone":"+49 8751/1470",
    "sg:postcode":"84048",
    "sg:province":"Bayern",
    "wof:name":"Zieglerbr\u00e4u-mainburg Hermine Randeltshofer",
    "wof:placetype":"venue"
},
  "geometry": {"coordinates":[11.788852,48.641788],"type":"Point"}
}