{
  "type": "Feature",
  "properties": {
    "iso:country":"DE",
    "sg:address":"Stadtkoppel 33",
    "sg:city":"L\u00fcneburg",
    "sg:phone":"+49 4131/86310",
    "sg:postcode":"21337",
    "sg:province":"Niedersachsen",
    "wof:name":"Hans-ulrich Wilke",
    "wof:placetype":"venue"
},
  "geometry": {"coordinates":[10.4523210526,53.2441978455],"type":"Point"}
}