{
  "type": "Feature",
  "properties": {
    "iso:country":"DE",
    "sg:address":"Georgstr. 2",
    "sg:city":"Arnstorf",
    "sg:phone":"+49 8723/96020",
    "sg:postcode":"94424",
    "sg:province":"Bayern",
    "wof:name":"Efko Maschinen Und Ger\u00e4tebau Gmbh",
    "wof:placetype":"venue"
},
  "geometry": {"coordinates":[12.8080396652,48.5638542175],"type":"Point"}
}