{
  "type": "Feature",
  "properties": {
    "iso:country":"DE",
    "sg:address":"Obermarkt 14",
    "sg:city":"Murnau",
    "sg:phone":"+49 8841/5183",
    "sg:postcode":"82418",
    "sg:province":"Bayern",
    "wof:name":"Kaisers Tengelmann Ag",
    "wof:placetype":"venue"
},
  "geometry": {"coordinates":[11.2011022568,47.6788978577],"type":"Point"}
}