{
  "type": "Feature",
  "properties": {
    "iso:country":"DE",
    "sg:address":"Alemannenstr. 1",
    "sg:city":"Gemmrigheim",
    "sg:phone":"+49 7143/94368",
    "sg:postcode":"74376",
    "sg:province":"Baden-W\u00fcrttemberg",
    "wof:name":"W. Reisinger",
    "wof:placetype":"venue"
},
  "geometry": {"coordinates":[9.15496,49.029449],"type":"Point"}
}