{
  "type": "Feature",
  "properties": {
    "iso:country":"DE",
    "sg:address":"R\u00f6merstr. 86a",
    "sg:city":"Obernburg",
    "sg:phone":"+49 6022/9449",
    "sg:postcode":"63785",
    "sg:province":"Bayern",
    "wof:name":"Harald Mause Rechtsanwalt",
    "wof:placetype":"venue"
},
  "geometry": {"coordinates":[9.1504659653,49.8453826904],"type":"Point"}
}