{
  "type": "Feature",
  "properties": {
    "iso:country":"DE",
    "sg:address":"Haydnstr. 4",
    "sg:city":"Pullach",
    "sg:phone":"+49 89/7931957",
    "sg:postcode":"82049",
    "sg:province":"Bayern",
    "wof:name":"Richard Wagner Inh. Christian Wirth",
    "wof:placetype":"venue"
},
  "geometry": {"coordinates":[11.518421,48.064407],"type":"Point"}
}