{
  "type": "Feature",
  "properties": {
    "iso:country":"DE",
    "sg:address":"Friesenstr. 82",
    "sg:city":"Ihlow",
    "sg:phone":"+49 4928/1551",
    "sg:postcode":"26632",
    "sg:province":"Niedersachsen",
    "wof:name":"Birkoben Gmbh",
    "wof:placetype":"venue"
},
  "geometry": {"coordinates":[7.3446698189,53.3892097473],"type":"Point"}
}