{
  "type": "Feature",
  "properties": {
    "iso:country":"DE",
    "sg:address":"Am Forsthaus 18",
    "sg:city":"Biedenkopf",
    "sg:phone":"+49 6461/2330",
    "sg:postcode":"35216",
    "sg:province":"Hessen",
    "wof:name":"H. Acker",
    "wof:placetype":"venue"
},
  "geometry": {"coordinates":[8.5570192337,50.8758392334],"type":"Point"}
}