{
  "type": "Feature",
  "properties": {
    "iso:country":"DE",
    "sg:address":"Wienbergen 7",
    "sg:city":"Hilgermissen",
    "sg:phone":"+49 4256/613",
    "sg:postcode":"27318",
    "sg:province":"Niedersachsen",
    "wof:name":"Roman Und Susanne Podolski",
    "wof:placetype":"venue"
},
  "geometry": {"coordinates":[9.169564,52.834949],"type":"Point"}
}