{
  "type": "Feature",
  "properties": {
    "iso:country":"DE",
    "sg:address":"Kurl\u00e4nder Allee 27",
    "sg:city":"Berlin",
    "sg:phone":"+49 30/3027189",
    "sg:postcode":"14055",
    "sg:province":"Berlin",
    "wof:name":"Profunda Immobilien Gmbh",
    "wof:placetype":"venue"
},
  "geometry": {"coordinates":[13.2610311508,52.5033912659],"type":"Point"}
}