{
  "type": "Feature",
  "properties": {
    "iso:country":"DE",
    "sg:address":"Hochstr. 11",
    "sg:city":"Hamm",
    "sg:phone":"+49 2381/73085",
    "sg:postcode":"59075",
    "sg:province":"Nordrhein-Westfalen",
    "wof:name":"Dieter Langner",
    "wof:placetype":"venue"
},
  "geometry": {"coordinates":[7.744297,51.694595],"type":"Point"}
}