{
  "type": "Feature",
  "properties": {
    "iso:country":"DE",
    "sg:address":"Erfurter Str. 1",
    "sg:city":"Mittelhausen",
    "sg:phone":"+49 361/735033",
    "sg:postcode":"99195",
    "sg:province":"Th\u00fcringen",
    "wof:name":"J. Dausel",
    "wof:placetype":"venue"
},
  "geometry": {"coordinates":[11.0032262802,51.0391426086],"type":"Point"}
}