{
  "type": "Feature",
  "properties": {
    "iso:country":"DE",
    "sg:address":"Holdermannstr. 60",
    "sg:city":"Stuttgart",
    "sg:phone":"+49 711/967810",
    "sg:postcode":"70567",
    "sg:province":"Baden-W\u00fcrttemberg",
    "wof:name":"Baugenossenschaft Friedenau Der Stra\u00dfenbahner Eg",
    "wof:placetype":"venue"
},
  "geometry": {"coordinates":[9.1486558914,48.7301940918],"type":"Point"}
}