{
  "type": "Feature",
  "properties": {
    "iso:country":"DE",
    "sg:address":"Hundsfelder Str. 34",
    "sg:city":"Berlin",
    "sg:phone":"+49 30/6767226",
    "sg:postcode":"12526",
    "sg:province":"Berlin",
    "wof:name":"Wolfgang Hampel Ingenieur",
    "wof:placetype":"venue"
},
  "geometry": {"coordinates":[13.5658836365,52.3991584778],"type":"Point"}
}