{
  "type": "Feature",
  "properties": {
    "iso:country":"DE",
    "sg:address":"Kiefernweg 15",
    "sg:city":"Oerlinghausen",
    "sg:phone":"+49 5202/71229",
    "sg:postcode":"33813",
    "sg:province":"Nordrhein-Westfalen",
    "wof:name":"Wolfgang Pf\u00f6rtner",
    "wof:placetype":"venue"
},
  "geometry": {"coordinates":[8.628521,51.936428],"type":"Point"}
}