{
  "type": "Feature",
  "properties": {
    "iso:country":"DE",
    "sg:address":"Friedrich-Ebert-Str. 40",
    "sg:city":"Gotha",
    "sg:phone":"+49 3621/758846",
    "sg:postcode":"99867",
    "sg:province":"Th\u00fcringen",
    "wof:name":"Klaus Pruchnewski",
    "wof:placetype":"venue"
},
  "geometry": {"coordinates":[10.6922922134,50.932926178],"type":"Point"}
}