{
  "type": "Feature",
  "properties": {
    "iso:country":"DE",
    "sg:address":"Am Lieberg 65",
    "sg:city":"H\u00fcckelhoven",
    "sg:phone":"+49 2433/90520",
    "sg:postcode":"41836",
    "sg:province":"Nordrhein-Westfalen",
    "wof:name":"F. P. Greven Architekt",
    "wof:placetype":"venue"
},
  "geometry": {"coordinates":[6.236325,51.052517],"type":"Point"}
}