{
  "type": "Feature",
  "properties": {
    "iso:country":"DE",
    "sg:address":"Schalmenaeckerstr. 4 Geisslingen",
    "sg:city":"Klettgau",
    "sg:phone":"+49 4977/4292330",
    "sg:postcode":"79771",
    "sg:province":"Baden-W\u00fcrttemberg",
    "wof:name":"Mack Gmbh",
    "wof:placetype":"venue"
},
  "geometry": {"coordinates":[8.420114,47.661087],"type":"Point"}
}