{
  "type": "Feature",
  "properties": {
    "iso:country":"DE",
    "sg:address":"Wallburgstr. 30",
    "sg:city":"Herne",
    "sg:postcode":"44629",
    "sg:province":"Nordrhein-Westfalen",
    "wof:name":"Kollegium Zur Geisteswissen- Schaftlichen Erarbeitung Nach",
    "wof:placetype":"venue"
},
  "geometry": {"coordinates":[7.205039978,51.5499954224],"type":"Point"}
}