{
  "type": "Feature",
  "properties": {
    "iso:country":"DE",
    "sg:address":"Hauptstr. 1",
    "sg:city":"H\u00f6chenschwand",
    "sg:phone":"+49 7672/4476",
    "sg:postcode":"79862",
    "sg:province":"Baden-W\u00fcrttemberg",
    "wof:name":"Peters Bierstube",
    "wof:placetype":"venue"
},
  "geometry": {"coordinates":[8.165104866,47.7349853516],"type":"Point"}
}