{
  "type": "Feature",
  "properties": {
    "iso:country":"DE",
    "sg:address":"Fortunastr. 10",
    "sg:city":"W\u00fclfrath",
    "sg:phone":"+49 2058/79545",
    "sg:postcode":"42489",
    "sg:province":"Nordrhein-Westfalen",
    "wof:name":"T. J. Madison Modevertriebs Gmbh",
    "wof:placetype":"venue"
},
  "geometry": {"coordinates":[7.0147352219,51.2774734497],"type":"Point"}
}