{
  "type": "Feature",
  "properties": {
    "iso:country":"DE",
    "sg:address":"Immermannstr. 24",
    "sg:city":"Emsdetten",
    "sg:phone":"+49 2572/4985",
    "sg:postcode":"48282",
    "sg:province":"Nordrhein-Westfalen",
    "wof:name":"Anni Wegmann",
    "wof:placetype":"venue"
},
  "geometry": {"coordinates":[7.5238528252,52.1702651978],"type":"Point"}
}