{
  "type": "Feature",
  "properties": {
    "iso:country":"DE",
    "sg:address":"Breslauer Str. 2",
    "sg:city":"Krummh\u00f6rn",
    "sg:phone":"+49 4923/8447",
    "sg:postcode":"26736",
    "sg:province":"Niedersachsen",
    "wof:name":"G. R\u00f6mer",
    "wof:placetype":"venue"
},
  "geometry": {"coordinates":[7.0967679024,53.4318237305],"type":"Point"}
}