{
  "type": "Feature",
  "properties": {
    "iso:country":"DE",
    "sg:address":"Dr.-Aicher-Str. 3",
    "sg:city":"Landau",
    "sg:phone":"+49 9951/8122",
    "sg:postcode":"94405",
    "sg:province":"Bayern",
    "wof:name":"Max Gerhaher Ingenieur",
    "wof:placetype":"venue"
},
  "geometry": {"coordinates":[12.6983165741,48.6631278992],"type":"Point"}
}