{
  "type": "Feature",
  "properties": {
    "iso:country":"DE",
    "sg:address":"Belgradstr. 29",
    "sg:city":"M\u00fcnchen",
    "sg:phone":"+49 89/303166",
    "sg:postcode":"80796",
    "sg:province":"Bayern",
    "wof:name":"Thomam\u00fcller",
    "wof:placetype":"venue"
},
  "geometry": {"coordinates":[11.5743198395,48.1636543274],"type":"Point"}
}