{
  "type": "Feature",
  "properties": {
    "iso:country":"DE",
    "sg:address":"Geusaer Str. 1",
    "sg:city":"Merseburg",
    "sg:phone":"+49 3461/547459",
    "sg:postcode":"06217",
    "sg:province":"Sachsen-Anhalt",
    "wof:name":"Ivet Ingenieurgesellschaft F\u00fcr Verfahrensentwicklung Und",
    "wof:placetype":"venue"
},
  "geometry": {"coordinates":[11.9898195267,51.3536109924],"type":"Point"}
}