{
  "type": "Feature",
  "properties": {
    "iso:country":"DE",
    "sg:address":"Heidelberger Landstr. 37",
    "sg:city":"Darmstadt",
    "sg:phone":"+49 6151/537547",
    "sg:postcode":"64297",
    "sg:province":"Hessen",
    "wof:name":"R. Krause-pfeiffer Innenarchitekt",
    "wof:placetype":"venue"
},
  "geometry": {"coordinates":[8.645276,49.837967],"type":"Point"}
}