{
  "type": "Feature",
  "properties": {
    "iso:country":"DE",
    "sg:address":"Kaiser-Wilhelm-Str. 1-3",
    "sg:city":"Ludwigshafen",
    "sg:phone":"+49 621/59630",
    "sg:postcode":"67059",
    "sg:province":"Rheinland-Pfalz",
    "wof:name":"Landeszentralbank In Rheinland-pfalz Und Saarland",
    "wof:placetype":"venue"
},
  "geometry": {"coordinates":[8.4503469467,49.482383728],"type":"Point"}
}