{
  "type": "Feature",
  "properties": {
    "iso:country":"DE",
    "sg:address":"Viereimergasse 1",
    "sg:city":"Regensburg",
    "sg:phone":"+49 941/51776",
    "sg:postcode":"93047",
    "sg:province":"Bayern",
    "wof:name":"Gescha - Fachgesch\u00e4ft F\u00fcr W\u00e4sche Mieder Bademoden E. K.",
    "wof:placetype":"venue"
},
  "geometry": {"coordinates":[12.098034,49.017014],"type":"Point"}
}