{
  "type": "Feature",
  "properties": {
    "iso:country":"DE",
    "sg:address":"Rosenbergstr. 6",
    "sg:city":"Daun",
    "sg:postcode":"54550",
    "sg:province":"Rheinland-Pfalz",
    "wof:name":"Mbr Agrarservice Daun Gmbh",
    "wof:placetype":"venue"
},
  "geometry": {"coordinates":[6.828617,50.197132],"type":"Point"}
}