{
  "type": "Feature",
  "properties": {
    "iso:country":"DE",
    "sg:address":"Sandrocken 2a",
    "sg:city":"Garrel",
    "sg:phone":"+49 4474/277",
    "sg:postcode":"49681",
    "sg:province":"Niedersachsen",
    "wof:name":"Aumann & Co. Zimmereibetrieb Gmbh",
    "wof:placetype":"venue"
},
  "geometry": {"coordinates":[8.0038948059,52.961265564],"type":"Point"}
}