{
  "type": "Feature",
  "properties": {
    "iso:country":"DE",
    "sg:address":"Pfarrhofstr. 1",
    "sg:city":"Lohr",
    "sg:phone":"+49 9352/3527",
    "sg:postcode":"97816",
    "sg:province":"Bayern",
    "wof:name":"A. Scherg",
    "wof:placetype":"venue"
},
  "geometry": {"coordinates":[9.600815,49.962593],"type":"Point"}
}