{
  "type": "Feature",
  "properties": {
    "iso:country":"DE",
    "sg:address":"Saarstr. 98",
    "sg:city":"Trier",
    "sg:phone":"+49 651/31642",
    "sg:postcode":"54290",
    "sg:province":"Rheinland-Pfalz",
    "wof:name":"Ernst Langer",
    "wof:placetype":"venue"
},
  "geometry": {"coordinates":[6.6339378357,49.7436676025],"type":"Point"}
}