{
  "type": "Feature",
  "properties": {
    "iso:country":"DE",
    "sg:address":"Marktstr. 5",
    "sg:city":"Fulda",
    "sg:phone":"+49 661/9709190",
    "sg:postcode":"36037",
    "sg:province":"Hessen",
    "wof:name":"Bonita Gef\u00fchl F\u00fcr Mode Gmbh & Co. Kg",
    "wof:placetype":"venue"
},
  "geometry": {"coordinates":[9.676541,50.551632],"type":"Point"}
}