{
  "type": "Feature",
  "properties": {
    "iso:country":"DE",
    "sg:address":"Untere Hauptstr. 156",
    "sg:city":"Herxheim",
    "sg:phone":"+49 7276/7520",
    "sg:postcode":"76863",
    "sg:province":"Rheinland-Pfalz",
    "wof:name":"Walter Dudenh\u00f6ffer",
    "wof:placetype":"venue"
},
  "geometry": {"coordinates":[8.2166900635,49.1467399597],"type":"Point"}
}