{
  "type": "Feature",
  "properties": {
    "iso:country":"DE",
    "sg:address":"Nordring 14",
    "sg:city":"Melle",
    "sg:postcode":"49328",
    "sg:province":"Niedersachsen",
    "wof:name":"Box Design M\u00f6bel Gmbh & Co. Kg",
    "wof:placetype":"venue"
},
  "geometry": {"coordinates":[8.4061498642,52.2542152405],"type":"Point"}
}