{
  "type": "Feature",
  "properties": {
    "iso:country":"DE",
    "sg:address":"M\u00fchlfeldstr. 3",
    "sg:city":"Heiligkreuzsteinach",
    "sg:phone":"+49 6220/1844",
    "sg:postcode":"69253",
    "sg:province":"Baden-W\u00fcrttemberg",
    "wof:name":"Steinach-apotheke",
    "wof:placetype":"venue"
},
  "geometry": {"coordinates":[8.796759,49.485142],"type":"Point"}
}