{
  "type": "Feature",
  "properties": {
    "iso:country":"DE",
    "sg:address":"Kruppstr. 18-20",
    "sg:city":"Hildesheim",
    "sg:phone":"+49 5121/519833",
    "sg:postcode":"31135",
    "sg:province":"Niedersachsen",
    "wof:name":"Qualifizierung Und Arbeit Statt Sozialhilfe Quass-ggmbh",
    "wof:placetype":"venue"
},
  "geometry": {"coordinates":[9.972703,52.168068],"type":"Point"}
}