{
  "type": "Feature",
  "properties": {
    "iso:country":"DE",
    "sg:address":"Geseniusstr. 20",
    "sg:city":"Elze",
    "sg:phone":"+49 5182/6104",
    "sg:postcode":"31008",
    "sg:province":"Niedersachsen",
    "wof:name":"Alten- Und Pflegeheim Haus Sissi",
    "wof:placetype":"venue"
},
  "geometry": {"coordinates":[9.680236,52.08247],"type":"Point"}
}