{
  "type": "Feature",
  "properties": {
    "iso:country":"DE",
    "sg:address":"Flachskamp 7",
    "sg:city":"Achim",
    "sg:phone":"+49 4202/881190",
    "sg:postcode":"28832",
    "sg:province":"Niedersachsen",
    "wof:name":"Hans K\u00f6ster",
    "wof:placetype":"venue"
},
  "geometry": {"coordinates":[9.02433,53.012024],"type":"Point"}
}