{
  "type": "Feature",
  "properties": {
    "iso:country":"DE",
    "sg:address":"Oberstedter Str. 14",
    "sg:city":"Oberursel",
    "sg:phone":"+49 6171/691202",
    "sg:postcode":"61440",
    "sg:province":"Hessen",
    "wof:name":"Columbus Versicherungs- Vermittlungs- Und Service Gmbh",
    "wof:placetype":"venue"
},
  "geometry": {"coordinates":[8.574962616,50.2105674744],"type":"Point"}
}