{
  "type": "Feature",
  "properties": {
    "iso:country":"DE",
    "sg:address":"Dorfstr. 22",
    "sg:city":"Reit im Winkl",
    "sg:phone":"+49 8640/8253",
    "sg:postcode":"83242",
    "sg:province":"Bayern",
    "wof:name":"G\u00e4stehaus Manfred Gstatter",
    "wof:placetype":"venue"
},
  "geometry": {"coordinates":[12.4722299576,47.6761322021],"type":"Point"}
}