{
  "type": "Feature",
  "properties": {
    "iso:country":"DE",
    "sg:address":"Ascher Str. 63",
    "sg:city":"Maintal",
    "sg:phone":"+49 6181/491298",
    "sg:postcode":"63477",
    "sg:province":"Hessen",
    "wof:name":"Rolf Horstmann Ingenieur",
    "wof:placetype":"venue"
},
  "geometry": {"coordinates":[8.8320560455,50.136882782],"type":"Point"}
}