{
  "type": "Feature",
  "properties": {
    "iso:country":"DE",
    "sg:address":"M\u00fchle 32",
    "sg:city":"Billroda",
    "sg:phone":"+49 36377/4474",
    "sg:postcode":"06647",
    "sg:province":"Sachsen-Anhalt",
    "wof:name":"D. Becker Ingenieur",
    "wof:placetype":"venue"
},
  "geometry": {"coordinates":[11.4499931335,51.199848175],"type":"Point"}
}