{
  "type": "Feature",
  "properties": {
    "iso:country":"DE",
    "sg:address":"B\u00f6nninghauser Str. 8 a",
    "sg:city":"Geseke",
    "sg:phone":"+49 2942/1552",
    "sg:postcode":"59590",
    "sg:province":"Nordrhein-Westfalen",
    "wof:name":"Dr\u00f6ge Recycling Gmbh",
    "wof:placetype":"venue"
},
  "geometry": {"coordinates":[8.5060024261,51.6447181702],"type":"Point"}
}