{
  "type": "Feature",
  "properties": {
    "iso:country":"DE",
    "sg:address":"Pfarrwiese 14",
    "sg:city":"Wieda",
    "sg:phone":"+49 5586/8208",
    "sg:postcode":"37447",
    "sg:province":"Niedersachsen",
    "wof:name":"Restaurant Forellengrund",
    "wof:placetype":"venue"
},
  "geometry": {"coordinates":[10.5814409256,51.6177062988],"type":"Point"}
}