{
  "type": "Feature",
  "properties": {
    "iso:country":"DE",
    "sg:address":"Melissenweg 10",
    "sg:city":"Hamburg",
    "sg:phone":"+49 40/60014920",
    "sg:postcode":"22395",
    "sg:province":"Hamburg",
    "wof:name":"Ilse Rickert",
    "wof:placetype":"venue"
},
  "geometry": {"coordinates":[10.109926,53.66116],"type":"Point"}
}