{
  "type": "Feature",
  "properties": {
    "iso:country":"DE",
    "sg:address":"Oldenburger Str. 7",
    "sg:city":"Zeuthen",
    "sg:phone":"+49 33762/71198",
    "sg:postcode":"15738",
    "sg:province":"Brandenburg",
    "wof:name":"Gerhard K. Hauptmann Rechtsanwalt",
    "wof:placetype":"venue"
},
  "geometry": {"coordinates":[13.6243934631,52.3492393494],"type":"Point"}
}