{
  "type": "Feature",
  "properties": {
    "iso:country":"DE",
    "sg:address":"Erlengarten 3",
    "sg:city":"Boll",
    "sg:phone":"+49 7164/6667",
    "sg:postcode":"73087",
    "sg:province":"Baden-W\u00fcrttemberg",
    "wof:name":"Die Kommode W\u00e4sche Und Mode E. Fischer E. K.",
    "wof:placetype":"venue"
},
  "geometry": {"coordinates":[9.6130409241,48.6422271729],"type":"Point"}
}