{
  "type": "Feature",
  "properties": {
    "iso:country":"DE",
    "sg:address":"Kellerbergstr. 18",
    "sg:city":"Dinkelscherben",
    "sg:phone":"+49 8292/1529",
    "sg:postcode":"86424",
    "sg:province":"Bayern",
    "wof:name":"Josef Lichtblau",
    "wof:placetype":"venue"
},
  "geometry": {"coordinates":[10.5865125656,48.3518676758],"type":"Point"}
}