{
  "type": "Feature",
  "properties": {
    "iso:country":"DE",
    "sg:address":"Zum Emskai 1",
    "sg:city":"Emden",
    "sg:phone":"+49 4921/92180",
    "sg:postcode":"26723",
    "sg:province":"Niedersachsen",
    "wof:name":"Tramosa Fahrzeug-spezial-transporte Gmbh",
    "wof:placetype":"venue"
},
  "geometry": {"coordinates":[7.1814699173,53.3475837708],"type":"Point"}
}