{
  "type": "Feature",
  "properties": {
    "iso:country":"DE",
    "sg:address":"Am Pulverschoppen 8",
    "sg:city":"Hamm",
    "sg:phone":"+49 2381/880022",
    "sg:postcode":"59071",
    "sg:province":"Nordrhein-Westfalen",
    "wof:name":"B\u00fcrgel",
    "wof:placetype":"venue"
},
  "geometry": {"coordinates":[7.879857,51.691929],"type":"Point"}
}