{
  "type": "Feature",
  "properties": {
    "iso:country":"DE",
    "sg:address":"Poghausener Str. 22",
    "sg:city":"Uplengen",
    "sg:phone":"+49 4956/743",
    "sg:postcode":"26670",
    "sg:province":"Niedersachsen",
    "wof:name":"Wilhelm Anneessen",
    "wof:placetype":"venue"
},
  "geometry": {"coordinates":[7.78328,53.33638],"type":"Point"}
}