{
  "type": "Feature",
  "properties": {
    "iso:country":"DE",
    "sg:address":"Alte M\u00fchle 2",
    "sg:city":"Buchholz",
    "sg:phone":"+49 5071/768",
    "sg:postcode":"29690",
    "sg:province":"Niedersachsen",
    "wof:name":"Gerhard Sperber",
    "wof:placetype":"venue"
},
  "geometry": {"coordinates":[9.660756,52.663841],"type":"Point"}
}