{
  "type": "Feature",
  "properties": {
    "iso:country":"DE",
    "sg:address":"Am Ravensburger Tor 9",
    "sg:city":"Bad Waldsee",
    "sg:phone":"+49 7524/8913",
    "sg:postcode":"88339",
    "sg:province":"Baden-W\u00fcrttemberg",
    "wof:name":"Brigitte Grimm",
    "wof:placetype":"venue"
},
  "geometry": {"coordinates":[9.7554512024,47.9192733765],"type":"Point"}
}