{
  "type": "Feature",
  "properties": {
    "iso:country":"DE",
    "sg:address":"Donnersbergstr. 50",
    "sg:city":"Winnweiler",
    "sg:phone":"+49 6302/81060",
    "sg:postcode":"67722",
    "sg:province":"Rheinland-Pfalz",
    "wof:name":"Paul-gerhard Hehrlein",
    "wof:placetype":"venue"
},
  "geometry": {"coordinates":[7.8447451591,49.5669784546],"type":"Point"}
}