{
  "type": "Feature",
  "properties": {
    "iso:country":"DE",
    "sg:address":"Thomas-Mann-Str. 1",
    "sg:city":"Arnstadt",
    "sg:phone":"+49 3628/723060",
    "sg:postcode":"99310",
    "sg:province":"Th\u00fcringen",
    "wof:name":"Reiseb\u00fcro Sabelin Inh. Olaf Woitonik E. K.",
    "wof:placetype":"venue"
},
  "geometry": {"coordinates":[10.9472913742,50.8417510986],"type":"Point"}
}