{
  "type": "Feature",
  "properties": {
    "iso:country":"DE",
    "sg:address":"N\u00f6denstr. 9",
    "sg:city":"Rotenburg",
    "sg:phone":"+49 4261/67570",
    "sg:postcode":"27356",
    "sg:province":"Niedersachsen",
    "wof:name":"Hallen- Und Freibad",
    "wof:placetype":"venue"
},
  "geometry": {"coordinates":[9.4010057449,53.1135292053],"type":"Point"}
}