{
  "type": "Feature",
  "properties": {
    "iso:country":"DE",
    "sg:address":"Windthorststr. 11",
    "sg:city":"Speyer",
    "sg:phone":"+49 6232/77192",
    "sg:postcode":"67346",
    "sg:province":"Rheinland-Pfalz",
    "wof:name":"Da Roberto",
    "wof:placetype":"venue"
},
  "geometry": {"coordinates":[8.4309206009,49.3045043945],"type":"Point"}
}