{
  "type": "Feature",
  "properties": {
    "iso:country":"DE",
    "sg:address":"Laischeweg 9",
    "sg:city":"Weyhausen",
    "sg:phone":"+49 4953/6297890",
    "sg:postcode":"38554",
    "sg:province":"Niedersachsen",
    "wof:name":"Otto Wolf Gmbh, Erdbau-kieswerke-transporte-baustoffrecycling-rohrverlegung-pflasterarbeit",
    "wof:placetype":"venue"
},
  "geometry": {"coordinates":[10.72016,52.46439],"type":"Point"}
}