{
  "type": "Feature",
  "properties": {
    "iso:country":"DE",
    "sg:address":"Nienbr\u00fcgger Weg 200",
    "sg:city":"Kiel",
    "sg:postcode":"24107",
    "sg:province":"Schleswig-Holstein",
    "wof:name":"Raudy-beteiligungs- Gmbh",
    "wof:placetype":"venue"
},
  "geometry": {"coordinates":[10.07163,54.355179],"type":"Point"}
}