{
  "type": "Feature",
  "properties": {
    "iso:country":"DE",
    "sg:address":"Zaucheweg 6",
    "sg:city":"Leipzig",
    "sg:phone":"+49 341/659840",
    "sg:postcode":"04316",
    "sg:province":"Sachsen",
    "wof:name":"Busse Gmbh",
    "wof:placetype":"venue"
},
  "geometry": {"coordinates":[12.490434,51.322449],"type":"Point"}
}