{
  "type": "Feature",
  "properties": {
    "iso:country":"DE",
    "sg:address":"Ferdinand-Hiller-Weg 17",
    "sg:city":"D\u00fcsseldorf",
    "sg:phone":"+49 211/704190",
    "sg:postcode":"40593",
    "sg:province":"Nordrhein-Westfalen",
    "wof:name":"Gebr. Van Beek Gmbh Import-export",
    "wof:placetype":"venue"
},
  "geometry": {"coordinates":[6.8870959282,51.1520843506],"type":"Point"}
}