{
  "type": "Feature",
  "properties": {
    "iso:country":"DE",
    "sg:address":"Unter den Buchen",
    "sg:city":"Beckingen",
    "sg:phone":"+49 6832/91190",
    "sg:postcode":"66701",
    "sg:province":"Saarland",
    "wof:name":"Wolfgang Schmidt Gmbh",
    "wof:placetype":"venue"
},
  "geometry": {"coordinates":[6.7613110542,49.4486427307],"type":"Point"}
}