{
  "type": "Feature",
  "properties": {
    "iso:country":"DE",
    "sg:address":"Frankenstr. 13",
    "sg:city":"Stockstadt",
    "sg:phone":"+49 6027/401713",
    "sg:postcode":"63811",
    "sg:province":"Bayern",
    "wof:name":"Theobald Lang Architekt",
    "wof:placetype":"venue"
},
  "geometry": {"coordinates":[9.064273,49.973122],"type":"Point"}
}