{
  "type": "Feature",
  "properties": {
    "iso:country":"DE",
    "sg:address":"Troppauer Str.",
    "sg:city":"M\u00fcnchen",
    "sg:phone":"+49 89/3181050",
    "sg:postcode":"80937",
    "sg:province":"Bayern",
    "wof:name":"Readymix Beton S\u00fcdbayern Gmbh",
    "wof:placetype":"venue"
},
  "geometry": {"coordinates":[11.573465,48.195206],"type":"Point"}
}