{
  "type": "Feature",
  "properties": {
    "iso:country":"DE",
    "sg:address":"Hofstetter Str. 14",
    "sg:city":"Haslach",
    "sg:phone":"+49 7832/2345",
    "sg:postcode":"77716",
    "sg:province":"Baden-W\u00fcrttemberg",
    "wof:name":"Cafe-pizzeria Bei Oronzo",
    "wof:placetype":"venue"
},
  "geometry": {"coordinates":[8.1109752655,48.287071228],"type":"Point"}
}