{
  "type": "Feature",
  "properties": {
    "iso:country":"DE",
    "sg:address":"Lindenstr. 26",
    "sg:city":"Oberkirch",
    "sg:phone":"+49 7805/3584",
    "sg:postcode":"77704",
    "sg:province":"Baden-W\u00fcrttemberg",
    "wof:name":"Hirsch",
    "wof:placetype":"venue"
},
  "geometry": {"coordinates":[8.015165329,48.5461921692],"type":"Point"}
}