{
  "type": "Feature",
  "properties": {
    "iso:country":"DE",
    "sg:address":"Georgstr. 46",
    "sg:city":"Hannover",
    "sg:phone":"+49 511/326803",
    "sg:postcode":"30159",
    "sg:province":"Niedersachsen",
    "wof:name":"J\u00fcrgen Weitz Gmbh",
    "wof:placetype":"venue"
},
  "geometry": {"coordinates":[9.7403259277,52.3721427917],"type":"Point"}
}