{
  "type": "Feature",
  "properties": {
    "iso:country":"DE",
    "sg:address":"Zei\u00dfstr. 10",
    "sg:city":"Hamburg",
    "sg:phone":"+49 40/3906199",
    "sg:postcode":"22765",
    "sg:province":"Hamburg",
    "wof:name":"Malereibetrieb G. B\u00fcttner & G. Solecke",
    "wof:placetype":"venue"
},
  "geometry": {"coordinates":[9.929027,53.555275],"type":"Point"}
}