{
  "type": "Feature",
  "properties": {
    "iso:country":"DE",
    "sg:address":"Bahnhofstr. 8",
    "sg:city":"Rendsburg",
    "sg:phone":"+49 4331/5241",
    "sg:postcode":"24768",
    "sg:province":"Schleswig-Holstein",
    "wof:name":"Vach Rechtsanwalt",
    "wof:placetype":"venue"
},
  "geometry": {"coordinates":[9.6683216095,54.3027305603],"type":"Point"}
}