{
  "type": "Feature",
  "properties": {
    "iso:country":"DE",
    "sg:address":"Gutzberger Dorfstr. 2",
    "sg:city":"Stein",
    "sg:phone":"+49 9127/8434",
    "sg:postcode":"90547",
    "sg:province":"Bayern",
    "wof:name":"Walter H\u00f6fler",
    "wof:placetype":"venue"
},
  "geometry": {"coordinates":[10.9659404755,49.3898010254],"type":"Point"}
}