{
  "type": "Feature",
  "properties": {
    "iso:country":"DE",
    "sg:address":"Sch\u00fctzenwall 22-28",
    "sg:city":"Norderstedt",
    "sg:phone":"+49 40/5252084",
    "sg:postcode":"22844",
    "sg:province":"Schleswig-Holstein",
    "wof:name":"Rppc Vertrieb",
    "wof:placetype":"venue"
},
  "geometry": {"coordinates":[10.023363,53.710026],"type":"Point"}
}