{
  "type": "Feature",
  "properties": {
    "iso:country":"DE",
    "sg:address":"Bettackerstr. 19",
    "sg:city":"Freiburg",
    "sg:phone":"+49 761/43043",
    "sg:postcode":"79115",
    "sg:province":"Baden-W\u00fcrttemberg",
    "wof:name":"Cveta Savic Abschleppdienst",
    "wof:placetype":"venue"
},
  "geometry": {"coordinates":[7.8076372147,47.9862365723],"type":"Point"}
}