{
  "type": "Feature",
  "properties": {
    "iso:country":"DE",
    "sg:address":"Tannenstr. 16",
    "sg:city":"G\u00f6ppingen",
    "sg:phone":"+49 7161/83737",
    "sg:postcode":"73037",
    "sg:province":"Baden-W\u00fcrttemberg",
    "wof:name":"Billard-cafe Pegasus",
    "wof:placetype":"venue"
},
  "geometry": {"coordinates":[9.6901903152,48.6656990051],"type":"Point"}
}