{
  "type": "Feature",
  "properties": {
    "iso:country":"DE",
    "sg:address":"Grevener Str 3",
    "sg:city":"Werder",
    "sg:phone":"+49 38731/21312",
    "sg:postcode":"19386",
    "sg:province":"Mecklenburg-Vorpommern",
    "wof:name":"Gummi-schmidt Roland Schmidt",
    "wof:placetype":"venue"
},
  "geometry": {"coordinates":[12.0042171478,53.4995155334],"type":"Point"}
}