{
  "type": "Feature",
  "properties": {
    "iso:country":"DE",
    "sg:address":"Ostring 12",
    "sg:city":"Riedstadt",
    "sg:phone":"+49 6158/975310",
    "sg:postcode":"64560",
    "sg:province":"Hessen",
    "wof:name":"Imic Institut F\u00fcr Management Information Und",
    "wof:placetype":"venue"
},
  "geometry": {"coordinates":[8.4477853775,49.8567276001],"type":"Point"}
}