{
  "type": "Feature",
  "properties": {
    "iso:country":"DE",
    "sg:address":"Allmendstr. 39",
    "sg:city":"Bonndorf",
    "sg:phone":"+49 4977/031796",
    "sg:postcode":"79848",
    "sg:province":"Baden-W\u00fcrttemberg",
    "wof:name":"Guido Woll",
    "wof:placetype":"venue"
},
  "geometry": {"coordinates":[8.331584,47.809425],"type":"Point"}
}