{
  "type": "Feature",
  "properties": {
    "iso:country":"DE",
    "sg:address":"Berliner Platz 22",
    "sg:city":"N\u00fcrnberg",
    "sg:phone":"+49 911/534133",
    "sg:postcode":"90489",
    "sg:province":"Bayern",
    "wof:name":"Yvonne Rothschild",
    "wof:placetype":"venue"
},
  "geometry": {"coordinates":[11.097079,49.463444],"type":"Point"}
}