{
  "type": "Feature",
  "properties": {
    "iso:country":"DE",
    "sg:address":"Karl-Marx-Str. 6",
    "sg:city":"Reinheim",
    "sg:phone":"+49 6162/3989",
    "sg:postcode":"64354",
    "sg:province":"Hessen",
    "wof:name":"Ernst Miller Anlageberater",
    "wof:placetype":"venue"
},
  "geometry": {"coordinates":[8.8437042236,49.8230438232],"type":"Point"}
}