{
  "type": "Feature",
  "properties": {
    "iso:country":"DE",
    "sg:address":"Klaus-Conrad-Str. 1",
    "sg:city":"Hirschau",
    "sg:phone":"+49 9622/300",
    "sg:postcode":"92242",
    "sg:province":"Bayern",
    "wof:name":"Conrad Holding Gmbh",
    "wof:placetype":"venue"
},
  "geometry": {"coordinates":[11.943432,49.540047],"type":"Point"}
}