{
  "type": "Feature",
  "properties": {
    "iso:country":"DE",
    "sg:address":"Zweierweg 33",
    "sg:city":"W\u00fcrzburg",
    "sg:phone":"+49 931/883865",
    "sg:postcode":"97074",
    "sg:province":"Bayern",
    "wof:name":"Klaus Kurzmann Jun.",
    "wof:placetype":"venue"
},
  "geometry": {"coordinates":[9.963635,49.792606],"type":"Point"}
}