{
  "type": "Feature",
  "properties": {
    "iso:country":"DE",
    "sg:address":"suedring 9",
    "sg:city":"visselhoevede",
    "sg:postcode":"27374",
    "sg:province":"Niedersachsen",
    "wof:name":"Inter-nostalgia",
    "wof:placetype":"venue"
},
  "geometry": {"coordinates":[9.5734386444,52.9787254333],"type":"Point"}
}