{
  "type": "Feature",
  "properties": {
    "iso:country":"DE",
    "sg:address":"Werkstr. 13",
    "sg:city":"T\u00f6ging",
    "sg:postcode":"84513",
    "sg:province":"Bayern",
    "wof:name":"Werk 13 Ag",
    "wof:placetype":"venue"
},
  "geometry": {"coordinates":[12.5876989365,48.2522239685],"type":"Point"}
}