{
  "type": "Feature",
  "properties": {
    "iso:country":"DE",
    "sg:address":"Sontheimer Feld 1",
    "sg:city":"Talheim",
    "sg:phone":"+49 4971/3398060",
    "sg:postcode":"74388",
    "sg:province":"Baden-W\u00fcrttemberg",
    "wof:name":"Kunststoffspritzerei Str\u00dcber & Co Gmbh",
    "wof:placetype":"venue"
},
  "geometry": {"coordinates":[9.1871051788,49.1025352478],"type":"Point"}
}