{
  "type": "Feature",
  "properties": {
    "iso:country":"DE",
    "sg:address":"Freiburger Str. 12",
    "sg:city":"Mannheim",
    "sg:phone":"+49 621/4815659",
    "sg:postcode":"68239",
    "sg:province":"Baden-W\u00fcrttemberg",
    "wof:name":"Mannheimer Pflege Dienst",
    "wof:placetype":"venue"
},
  "geometry": {"coordinates":[8.56115,49.466682],"type":"Point"}
}