{
  "type": "Feature",
  "properties": {
    "iso:country":"DE",
    "sg:address":"Haschbacher Str. 24",
    "sg:city":"Rammelsbach",
    "sg:phone":"+49 6381/3376",
    "sg:postcode":"66887",
    "sg:province":"Rheinland-Pfalz",
    "wof:name":"Otto Cappel",
    "wof:placetype":"venue"
},
  "geometry": {"coordinates":[7.44481,49.541237],"type":"Point"}
}