{
  "type": "Feature",
  "properties": {
    "iso:country":"DE",
    "sg:address":"Hochstr. 3",
    "sg:city":"Kleinwallstadt",
    "sg:phone":"+49 6022/654797",
    "sg:postcode":"63839",
    "sg:province":"Bayern",
    "wof:name":"Raab Werbestudio",
    "wof:placetype":"venue"
},
  "geometry": {"coordinates":[9.1981935501,49.8605918884],"type":"Point"}
}