{
  "type": "Feature",
  "properties": {
    "iso:country":"DE",
    "sg:address":"Kandelsweg 3",
    "sg:city":"Preist",
    "sg:phone":"+49 6562/1245",
    "sg:postcode":"54664",
    "sg:province":"Rheinland-Pfalz",
    "wof:name":"B. R. Schmidt Heilpraktiker",
    "wof:placetype":"venue"
},
  "geometry": {"coordinates":[6.6289968491,49.9064865112],"type":"Point"}
}