{
  "type": "Feature",
  "properties": {
    "iso:country":"DE",
    "sg:address":"Erchenstr. 14",
    "sg:city":"Heidenheim",
    "sg:phone":"+49 7321/95980",
    "sg:postcode":"89522",
    "sg:province":"Baden-W\u00fcrttemberg",
    "wof:name":"Hotel-pension P\u00f6ltl",
    "wof:placetype":"venue"
},
  "geometry": {"coordinates":[10.1506948471,48.6731643677],"type":"Point"}
}