{
  "type": "Feature",
  "properties": {
    "iso:country":"DE",
    "sg:address":"Gleichmannstr.4",
    "sg:city":"M\u00fcnchen",
    "sg:phone":"+49 89/8345061",
    "sg:postcode":"81241",
    "sg:province":"Bayern",
    "wof:name":"Dresdner Bank",
    "wof:placetype":"venue"
},
  "geometry": {"coordinates":[11.46001,48.147083],"type":"Point"}
}