{
  "type": "Feature",
  "properties": {
    "iso:country":"DE",
    "sg:address":"Wolbecker Str. 8",
    "sg:city":"Telgte",
    "sg:phone":"+49 2504/3166",
    "sg:postcode":"48291",
    "sg:province":"Nordrhein-Westfalen",
    "wof:name":"M. Stallmeier",
    "wof:placetype":"venue"
},
  "geometry": {"coordinates":[7.7854471207,51.9801826477],"type":"Point"}
}