{
  "type": "Feature",
  "properties": {
    "iso:country":"DE",
    "sg:address":"Bergstr. 2",
    "sg:city":"Heiligenhafen",
    "sg:phone":"+49 4362/908770",
    "sg:postcode":"23774",
    "sg:province":"Schleswig-Holstein",
    "wof:name":"Sefkan Grillimbi\u00df",
    "wof:placetype":"venue"
},
  "geometry": {"coordinates":[10.9774780273,54.3724212646],"type":"Point"}
}