{
  "type": "Feature",
  "properties": {
    "iso:country":"DE",
    "sg:address":"Hafenstr. 117",
    "sg:city":"Bremerhaven",
    "sg:phone":"+49 471/26194",
    "sg:postcode":"27576",
    "sg:province":"Bremen",
    "wof:name":"Beratungsstelle Der Verbraucherzentrale",
    "wof:placetype":"venue"
},
  "geometry": {"coordinates":[8.585203,53.557915],"type":"Point"}
}