{
  "type": "Feature",
  "properties": {
    "iso:country":"DE",
    "sg:address":"Poststr. 32",
    "sg:city":"B\u00f6blingen",
    "sg:phone":"+49 7031/224577",
    "sg:postcode":"71032",
    "sg:province":"Baden-W\u00fcrttemberg",
    "wof:name":"Alt B\u00f6blingen",
    "wof:placetype":"venue"
},
  "geometry": {"coordinates":[9.012842,48.684013],"type":"Point"}
}