{
  "type": "Feature",
  "properties": {
    "iso:country":"DE",
    "sg:address":"Haarbergstr. 71",
    "sg:city":"Erfurt",
    "sg:phone":"+49 361/4426911",
    "sg:postcode":"99097",
    "sg:province":"Th\u00fcringen",
    "wof:name":"Meonic System Engineering Gmbh",
    "wof:placetype":"venue"
},
  "geometry": {"coordinates":[11.0869131088,50.947227478],"type":"Point"}
}