{
  "type": "Feature",
  "properties": {
    "iso:country":"DE",
    "sg:address":"Jesinger Hauptstr. 99",
    "sg:city":"T\u00fcbingen",
    "sg:phone":"+49 7073/6247",
    "sg:postcode":"72070",
    "sg:province":"Baden-W\u00fcrttemberg",
    "wof:name":"Orion",
    "wof:placetype":"venue"
},
  "geometry": {"coordinates":[8.9833831787,48.5255470276],"type":"Point"}
}