{
  "type": "Feature",
  "properties": {
    "iso:country":"DE",
    "sg:address":"Linzer Str. 13",
    "sg:city":"Stuttgart",
    "sg:phone":"+49 711/6979977",
    "sg:postcode":"70469",
    "sg:province":"Baden-W\u00fcrttemberg",
    "wof:name":"Gesellschaft F\u00fcr Beteiligungen Mbh",
    "wof:placetype":"venue"
},
  "geometry": {"coordinates":[9.15631,48.809811],"type":"Point"}
}