{
  "type": "Feature",
  "properties": {
    "iso:country":"DE",
    "sg:address":"Friedrich-Engels-Allee 282",
    "sg:city":"Wuppertal",
    "sg:phone":"+49 202/85055",
    "sg:postcode":"42285",
    "sg:province":"Nordrhein-Westfalen",
    "wof:name":"Praxis Dr. Med. Bruchhausen",
    "wof:placetype":"venue"
},
  "geometry": {"coordinates":[7.1810259819,51.2640342712],"type":"Point"}
}