{
  "type": "Feature",
  "properties": {
    "iso:country":"DE",
    "sg:address":"Falkenstr. 3",
    "sg:city":"Remchingen",
    "sg:phone":"+49 7232/71815",
    "sg:postcode":"75196",
    "sg:province":"Baden-W\u00fcrttemberg",
    "wof:name":"Trentini Gmbh",
    "wof:placetype":"venue"
},
  "geometry": {"coordinates":[8.577559,48.957565],"type":"Point"}
}