{
  "type": "Feature",
  "properties": {
    "iso:country":"DE",
    "sg:address":"Bahnhofstr. 17",
    "sg:city":"Oberr\u00f6blingen",
    "sg:postcode":"06528",
    "sg:province":"Sachsen-Anhalt",
    "wof:name":"Industrie-arbeitsmittel- Service Gmbh",
    "wof:placetype":"venue"
},
  "geometry": {"coordinates":[11.29484,51.422379],"type":"Point"}
}