{
  "type": "Feature",
  "properties": {
    "iso:country":"DE",
    "sg:address":"Herbolzheimer Str. 23",
    "sg:city":"Rheinhausen",
    "sg:phone":"+49 7643/6167",
    "sg:postcode":"79365",
    "sg:province":"Baden-W\u00fcrttemberg",
    "wof:name":"Hannelore Naas",
    "wof:placetype":"venue"
},
  "geometry": {"coordinates":[7.7132368088,48.2279853821],"type":"Point"}
}