{
  "type": "Feature",
  "properties": {
    "iso:country":"DE",
    "sg:address":"Werdohler Landstr. 193",
    "sg:city":"L\u00fcdenscheid",
    "sg:phone":"+49 2351/14668",
    "sg:postcode":"58513",
    "sg:province":"Nordrhein-Westfalen",
    "wof:name":"Heinz Richter",
    "wof:placetype":"venue"
},
  "geometry": {"coordinates":[7.6612272263,51.2292327881],"type":"Point"}
}