{
  "type": "Feature",
  "properties": {
    "iso:country":"DE",
    "sg:address":"Am Markt 07",
    "sg:city":"Storkow",
    "sg:phone":"+49 33678/72014",
    "sg:postcode":"15859",
    "sg:province":"Brandenburg",
    "wof:name":"Storch-apotheke H. Schr\u00f6der & H. Walmuth Ohg",
    "wof:placetype":"venue"
},
  "geometry": {"coordinates":[13.931645,52.254707],"type":"Point"}
}