{
  "type": "Feature",
  "properties": {
    "iso:country":"DE",
    "sg:address":"D\u00fcversbrucher Str. 38",
    "sg:city":"Rehden",
    "sg:phone":"+49 5446/713",
    "sg:postcode":"49453",
    "sg:province":"Niedersachsen",
    "wof:name":"Wilhelm Schmidt",
    "wof:placetype":"venue"
},
  "geometry": {"coordinates":[8.4787092209,52.6038551331],"type":"Point"}
}