{
  "type": "Feature",
  "properties": {
    "iso:country":"DE",
    "sg:address":"Gewerbestr. 7",
    "sg:city":"Waging",
    "sg:phone":"+49 8681/4173",
    "sg:postcode":"83329",
    "sg:province":"Bayern",
    "wof:name":"Sprint Gmbh",
    "wof:placetype":"venue"
},
  "geometry": {"coordinates":[12.7067956924,47.92445755],"type":"Point"}
}