{
  "type": "Feature",
  "properties": {
    "iso:country":"DE",
    "sg:address":"Am Buchenring 6",
    "sg:city":"Stromberg",
    "sg:phone":"+49 6724/93080",
    "sg:postcode":"55442",
    "sg:province":"Rheinland-Pfalz",
    "wof:name":"Park Village Golfanlagen Gmbh",
    "wof:placetype":"venue"
},
  "geometry": {"coordinates":[7.7712640762,49.933303833],"type":"Point"}
}