{
  "type": "Feature",
  "properties": {
    "iso:country":"DE",
    "sg:address":"Osserstr. 26",
    "sg:city":"M\u00fcnchen",
    "sg:phone":"+49 89/986614",
    "sg:postcode":"81679",
    "sg:province":"Bayern",
    "wof:name":"M. Himmler Immobilienmakler",
    "wof:placetype":"venue"
},
  "geometry": {"coordinates":[11.6144094467,48.1452178955],"type":"Point"}
}