{
  "type": "Feature",
  "properties": {
    "iso:country":"DE",
    "sg:address":"Ledererzeile 13",
    "sg:city":"Wasserburg",
    "sg:phone":"+49 8071/3638",
    "sg:postcode":"83512",
    "sg:province":"Bayern",
    "wof:name":"Ludwig Vital Ingenieur",
    "wof:placetype":"venue"
},
  "geometry": {"coordinates":[12.231416,48.06208],"type":"Point"}
}