{
  "type": "Feature",
  "properties": {
    "iso:country":"DE",
    "sg:address":"K\u00f6nneritzstr. 2",
    "sg:city":"Leipzig",
    "sg:postcode":"04229",
    "sg:province":"Sachsen",
    "wof:name":"D\u00fcwe Dienstleistungs Gmbh",
    "wof:placetype":"venue"
},
  "geometry": {"coordinates":[12.346163,51.328812],"type":"Point"}
}