{
  "type": "Feature",
  "properties": {
    "iso:country":"DE",
    "sg:address":"Keltenstr. 2",
    "sg:city":"Aschaffenburg",
    "sg:phone":"+49 6021/863180",
    "sg:postcode":"63741",
    "sg:province":"Bayern",
    "wof:name":"Vsl Viktoria Service Und Logistik Gmbh",
    "wof:placetype":"venue"
},
  "geometry": {"coordinates":[9.103045,49.967346],"type":"Point"}
}