{
  "type": "Feature",
  "properties": {
    "iso:country":"DE",
    "sg:address":"Im Dorfe 8",
    "sg:city":"Bad Nenndorf",
    "sg:phone":"+49 5723/2567",
    "sg:postcode":"31542",
    "sg:province":"Niedersachsen",
    "wof:name":"Otto Oltrogge",
    "wof:placetype":"venue"
},
  "geometry": {"coordinates":[9.381824,52.33712],"type":"Point"}
}