{
  "type": "Feature",
  "properties": {
    "iso:country":"DE",
    "sg:address":"Hauptstr. 31",
    "sg:city":"Reichelsheim",
    "sg:phone":"+49 6164/2118",
    "sg:postcode":"64385",
    "sg:province":"Hessen",
    "wof:name":"Landgasthaus K\u00f6nigsbrunnen",
    "wof:placetype":"venue"
},
  "geometry": {"coordinates":[8.8404016495,49.7125053406],"type":"Point"}
}