{
  "type": "Feature",
  "properties": {
    "iso:country":"DE",
    "sg:address":"Steinweg 15",
    "sg:city":"M\u00fchlhausen",
    "sg:phone":"+49 36018/74896",
    "sg:postcode":"99974",
    "sg:province":"Th\u00fcringen",
    "wof:name":"Ok Foto-labor Shop Gmbh",
    "wof:placetype":"venue"
},
  "geometry": {"coordinates":[10.464009285,51.2092132568],"type":"Point"}
}