{
  "type": "Feature",
  "properties": {
    "iso:country":"DE",
    "sg:address":"Mittlerer Weg 1",
    "sg:city":"Krumbach",
    "sg:phone":"+49 8282/2892",
    "sg:postcode":"86381",
    "sg:province":"Bayern",
    "wof:name":"Feuerwehrverein Attenhausen Konrad Rothermel",
    "wof:placetype":"venue"
},
  "geometry": {"coordinates":[10.4074983597,48.2668304443],"type":"Point"}
}