{
  "type": "Feature",
  "properties": {
    "iso:country":"DE",
    "sg:address":"Langer Grund",
    "sg:city":"Bad Pyrmont",
    "sg:phone":"+49 5281/4561",
    "sg:postcode":"31812",
    "sg:province":"Niedersachsen",
    "wof:name":"Langer Grund",
    "wof:placetype":"venue"
},
  "geometry": {"coordinates":[9.2685394287,52.0023536682],"type":"Point"}
}