{
  "type": "Feature",
  "properties": {
    "iso:country":"DE",
    "sg:address":"Werner-Seelenbinder-Stra\u00dfe 6",
    "sg:city":"Schleiz",
    "sg:phone":"+49 3663/422488",
    "sg:postcode":"07907",
    "sg:province":"Th\u00fcringen",
    "wof:name":"Homarus Meeresspezialit\u00e4ten",
    "wof:placetype":"venue"
},
  "geometry": {"coordinates":[11.8154287338,50.575088501],"type":"Point"}
}