{
  "type": "Feature",
  "properties": {
    "iso:country":"DE",
    "sg:address":"Rotenfelser Str. 14",
    "sg:city":"Bad M\u00fcnster-Ebernburg",
    "sg:postcode":"55583",
    "sg:province":"Rheinland-Pfalz",
    "wof:name":"M & B Service Team Gmbh",
    "wof:placetype":"venue"
},
  "geometry": {"coordinates":[7.84337,49.812565],"type":"Point"}
}