{
  "type": "Feature",
  "properties": {
    "iso:country":"DE",
    "sg:address":"Postplatz 7",
    "sg:city":"B\u00f6blingen",
    "sg:phone":"+49 7031/222830",
    "sg:postcode":"71032",
    "sg:province":"Baden-W\u00fcrttemberg",
    "wof:name":"Creativblume",
    "wof:placetype":"venue"
},
  "geometry": {"coordinates":[9.016444,48.685703],"type":"Point"}
}