{
  "type": "Feature",
  "properties": {
    "iso:country":"DE",
    "sg:address":"Riedweg 17",
    "sg:city":"Essingen",
    "sg:phone":"+49 7365/919332",
    "sg:postcode":"73457",
    "sg:province":"Baden-W\u00fcrttemberg",
    "wof:name":"Ute Janouschek",
    "wof:placetype":"venue"
},
  "geometry": {"coordinates":[10.023645,48.806141],"type":"Point"}
}