{
  "type": "Feature",
  "properties": {
    "iso:country":"DE",
    "sg:address":"Max-Caspar-Str. 20/1",
    "sg:city":"Weil der Stadt",
    "sg:phone":"+49 7033/9521",
    "sg:postcode":"71263",
    "sg:province":"Baden-W\u00fcrttemberg",
    "wof:name":"Gerhard Renz Architekt",
    "wof:placetype":"venue"
},
  "geometry": {"coordinates":[8.867295,48.753269],"type":"Point"}
}