{
  "type": "Feature",
  "properties": {
    "iso:country":"DE",
    "sg:address":"Seerosenweg 10",
    "sg:city":"Kirchansch\u00f6ring",
    "sg:phone":"+49 8685/321",
    "sg:postcode":"83417",
    "sg:province":"Bayern",
    "wof:name":"Franz Hell Zimmerei Gmbh",
    "wof:placetype":"venue"
},
  "geometry": {"coordinates":[12.8281908035,47.9620246887],"type":"Point"}
}