{
  "type": "Feature",
  "properties": {
    "iso:country":"DE",
    "sg:address":"Biesendorfer Str. 13",
    "sg:city":"Engen",
    "sg:phone":"+49 7733/1856",
    "sg:postcode":"78234",
    "sg:province":"Baden-W\u00fcrttemberg",
    "wof:name":"Egon Ruh",
    "wof:placetype":"venue"
},
  "geometry": {"coordinates":[8.812112,47.912327],"type":"Point"}
}