{
  "type": "Feature",
  "properties": {
    "iso:country":"DE",
    "sg:address":"Johannisstr. 28a",
    "sg:city":"Senden",
    "sg:postcode":"48308",
    "sg:province":"Nordrhein-Westfalen",
    "wof:name":"R. Knickenberg",
    "wof:placetype":"venue"
},
  "geometry": {"coordinates":[7.481853,51.915615],"type":"Point"}
}