{
  "type": "Feature",
  "properties": {
    "iso:country":"DE",
    "sg:address":"Brandvorwerkstr. 24",
    "sg:city":"Leipzig",
    "sg:phone":"+49 341/3987432",
    "sg:postcode":"04275",
    "sg:province":"Sachsen",
    "wof:name":"Reinhard Fehre",
    "wof:placetype":"venue"
},
  "geometry": {"coordinates":[12.3675117493,51.3230552673],"type":"Point"}
}