{
  "type": "Feature",
  "properties": {
    "iso:country":"DE",
    "sg:address":"Bessunger Str. 53",
    "sg:city":"Griesheim",
    "sg:phone":"+49 6155/2284",
    "sg:postcode":"64347",
    "sg:province":"Hessen",
    "wof:name":"Werner Gebauer",
    "wof:placetype":"venue"
},
  "geometry": {"coordinates":[8.5631446838,49.8589019775],"type":"Point"}
}