{
  "type": "Feature",
  "properties": {
    "iso:country":"DE",
    "sg:address":"Schulstr. 7",
    "sg:city":"Horrweiler",
    "sg:phone":"+49 6727/8374",
    "sg:postcode":"55457",
    "sg:province":"Rheinland-Pfalz",
    "wof:name":"Norbert Geyer",
    "wof:placetype":"venue"
},
  "geometry": {"coordinates":[7.967979,49.897984],"type":"Point"}
}