{
  "type": "Feature",
  "properties": {
    "iso:country":"DE",
    "sg:city":"Gau-Algesheim",
    "sg:postcode":"55435",
    "sg:province":"Rheinland-Pfalz",
    "wof:name":"Polygon Hausbau Gmbh",
    "wof:placetype":"venue"
},
  "geometry": {"coordinates":[8.013377,49.959183],"type":"Point"}
}