{
  "type": "Feature",
  "properties": {
    "iso:country":"DE",
    "sg:address":"H\u00f6fnerwinkel 11 a",
    "sg:city":"Eicklingen",
    "sg:phone":"+49 5149/92860",
    "sg:postcode":"29358",
    "sg:province":"Niedersachsen",
    "wof:name":"Concept Leben Werbe- Und Einkaufgesellschaft F\u00fcr Den",
    "wof:placetype":"venue"
},
  "geometry": {"coordinates":[10.1798992157,52.5596122742],"type":"Point"}
}