{
  "type": "Feature",
  "properties": {
    "iso:country":"DE",
    "sg:address":"Richard-Wagner-Str. 11",
    "sg:city":"Mannheim",
    "sg:phone":"+49 621/407008",
    "sg:postcode":"68165",
    "sg:province":"Baden-W\u00fcrttemberg",
    "wof:name":"Walter Bohm Und Eckhard Gei\u00df Rechtsanw\u00e4lte",
    "wof:placetype":"venue"
},
  "geometry": {"coordinates":[8.4792451859,49.4816017151],"type":"Point"}
}