{
  "type": "Feature",
  "properties": {
    "iso:country":"DE",
    "sg:address":"Radestr. 79",
    "sg:city":"Kassel",
    "sg:postcode":"34123",
    "sg:province":"Hessen",
    "wof:name":"Global Student. Services Europe",
    "wof:placetype":"venue"
},
  "geometry": {"coordinates":[9.531043,51.292027],"type":"Point"}
}