{
  "type": "Feature",
  "properties": {
    "iso:country":"DE",
    "sg:address":"Langenaubacher Str. 59",
    "sg:city":"Haiger",
    "sg:phone":"+49 2773/5356",
    "sg:postcode":"35708",
    "sg:province":"Hessen",
    "wof:name":"Horst Lommel Haushaltwaren",
    "wof:placetype":"venue"
},
  "geometry": {"coordinates":[8.1832952499,50.7156219482],"type":"Point"}
}