{
  "type": "Feature",
  "properties": {
    "iso:country":"DE",
    "sg:address":"Rosenstr. 25a",
    "sg:city":"Riemerling",
    "sg:phone":"+49 89/60013654",
    "sg:postcode":"85521",
    "sg:province":"Bayern",
    "wof:name":"Ingbert Sch\u00e4ffer Steuerberater",
    "wof:placetype":"venue"
},
  "geometry": {"coordinates":[11.6864843369,48.0620803833],"type":"Point"}
}