{
  "type": "Feature",
  "properties": {
    "iso:country":"DE",
    "sg:address":"N\u00fcrnberger Str. 44",
    "sg:city":"Hemau",
    "sg:postcode":"93155",
    "sg:province":"Bayern",
    "wof:name":"Reco-recycling-rohstoffe Eckl Beteiligungs-gmbh",
    "wof:placetype":"venue"
},
  "geometry": {"coordinates":[11.7783241272,49.0549125671],"type":"Point"}
}