{
  "type": "Feature",
  "properties": {
    "iso:country":"DE",
    "sg:address":"Brenzstr. 18",
    "sg:city":"Gundelfingen",
    "sg:phone":"+49 9073/91803",
    "sg:postcode":"89423",
    "sg:province":"Bayern",
    "wof:name":"Mf Metall- Und Fassadenbau Gmbh",
    "wof:placetype":"venue"
},
  "geometry": {"coordinates":[10.3941469193,48.5585403442],"type":"Point"}
}