{
  "type": "Feature",
  "properties": {
    "iso:country":"DE",
    "sg:address":"Von-Humboldt-Str. 6",
    "sg:city":"L\u00f6hne",
    "sg:phone":"+49 5732/3792",
    "sg:postcode":"32584",
    "sg:province":"Nordrhein-Westfalen",
    "wof:name":"Klaus Heidemann Steuerberater",
    "wof:placetype":"venue"
},
  "geometry": {"coordinates":[8.7200202942,52.1950302124],"type":"Point"}
}