{
  "type": "Feature",
  "properties": {
    "iso:country":"DE",
    "sg:address":"Wilthener Str. 11",
    "sg:city":"Bautzen",
    "sg:phone":"+49 3591/305496",
    "sg:postcode":"02625",
    "sg:province":"Sachsen",
    "wof:name":"Rene Jacob",
    "wof:placetype":"venue"
},
  "geometry": {"coordinates":[14.423652,51.170147],"type":"Point"}
}