{
  "type": "Feature",
  "properties": {
    "iso:country":"DE",
    "sg:address":"Lange Str. 31",
    "sg:city":"Liebenau",
    "sg:phone":"+49 5023/4545",
    "sg:postcode":"31618",
    "sg:province":"Niedersachsen",
    "wof:name":"Britta Faltus Und Susanne Humke",
    "wof:placetype":"venue"
},
  "geometry": {"coordinates":[9.09461,52.60434],"type":"Point"}
}