{
  "type": "Feature",
  "properties": {
    "iso:country":"DE",
    "sg:address":"Pallaswiesenstr. 210",
    "sg:city":"Darmstadt",
    "sg:phone":"+49 6151/891358",
    "sg:postcode":"64293",
    "sg:province":"Hessen",
    "wof:name":"Alfred Feix & Ahmet Sancak Top Wash Autowaschstr. Gmbh",
    "wof:placetype":"venue"
},
  "geometry": {"coordinates":[8.6294,49.884636],"type":"Point"}
}