{
  "type": "Feature",
  "properties": {
    "iso:country":"DE",
    "sg:address":"An der Ahlm\u00fchle 4",
    "sg:city":"Ilbesheim",
    "sg:phone":"+49 6341/30034",
    "sg:postcode":"76831",
    "sg:province":"Rheinland-Pfalz",
    "wof:name":"Timrott-bioprodukte Gmbh",
    "wof:placetype":"venue"
},
  "geometry": {"coordinates":[8.044801,49.173531],"type":"Point"}
}