{
  "type": "Feature",
  "properties": {
    "iso:country":"DE",
    "sg:address":"Am Bahnhof 1a",
    "sg:city":"Tostedt",
    "sg:phone":"+49 4182/7120",
    "sg:postcode":"21255",
    "sg:province":"Niedersachsen",
    "wof:name":"Gerald Fritsche",
    "wof:placetype":"venue"
},
  "geometry": {"coordinates":[9.7260370255,53.2697944641],"type":"Point"}
}