{
  "type": "Feature",
  "properties": {
    "iso:country":"DE",
    "sg:address":"Fichtestr. 128",
    "sg:city":"Brieselang",
    "sg:phone":"+49 33232/35108",
    "sg:postcode":"14656",
    "sg:province":"Brandenburg",
    "wof:name":"Hhk Havell\u00e4ndisches Hauskontor Vertriebs Kg",
    "wof:placetype":"venue"
},
  "geometry": {"coordinates":[12.988740921,52.6014633179],"type":"Point"}
}