{
  "type": "Feature",
  "properties": {
    "iso:country":"DE",
    "sg:address":"In der Tr\u00e4nk 39",
    "sg:city":"Offenbach",
    "sg:phone":"+49 69/862962",
    "sg:postcode":"63075",
    "sg:province":"Hessen",
    "wof:name":"Klaus Botta",
    "wof:placetype":"venue"
},
  "geometry": {"coordinates":[8.7949857712,50.129447937],"type":"Point"}
}