{
  "type": "Feature",
  "properties": {
    "iso:country":"DE",
    "sg:address":"Puschkinstr. 14",
    "sg:city":"Perleberg",
    "sg:phone":"+49 3876/300218",
    "sg:postcode":"19348",
    "sg:province":"Brandenburg",
    "wof:name":"Bewa Betriebsges. Wallgeb\u00e4ude Perleberg Mbh & Co.",
    "wof:placetype":"venue"
},
  "geometry": {"coordinates":[11.864265,53.076851],"type":"Point"}
}