{
  "type": "Feature",
  "properties": {
    "iso:country":"DE",
    "sg:address":"Meglingerstr 13b",
    "sg:city":"M\u00fcnchen",
    "sg:phone":"+49 89/7489080",
    "sg:postcode":"81477",
    "sg:province":"Bayern",
    "wof:name":"Marina Wassersport Gmbh",
    "wof:placetype":"venue"
},
  "geometry": {"coordinates":[11.5070772171,48.0929603577],"type":"Point"}
}