{
  "type": "Feature",
  "properties": {
    "iso:country":"DE",
    "sg:address":"Subecksweg 39",
    "sg:city":"Bad Gandersheim",
    "sg:phone":"+49 5382/98300",
    "sg:postcode":"37581",
    "sg:province":"Niedersachsen",
    "wof:name":"Henke & Partner Gmbh",
    "wof:placetype":"venue"
},
  "geometry": {"coordinates":[10.0107221603,51.875579834],"type":"Point"}
}