{
  "type": "Feature",
  "properties": {
    "iso:country":"DE",
    "sg:address":"Riedingerstr. 40",
    "sg:city":"Augsburg",
    "sg:phone":"+49 821/3244808",
    "sg:postcode":"86153",
    "sg:province":"Bayern",
    "wof:name":"Amt F\u00fcr Abfallwirtschaft Und Stadtreinigung",
    "wof:placetype":"venue"
},
  "geometry": {"coordinates":[10.8878583908,48.3850097656],"type":"Point"}
}