{
  "type": "Feature",
  "properties": {
    "iso:country":"DE",
    "sg:address":"kronskamp 90",
    "sg:city":"Wedel",
    "sg:postcode":"22880",
    "sg:province":"Schleswig-Holstein",
    "wof:name":"Svenosen",
    "wof:placetype":"venue"
},
  "geometry": {"coordinates":[9.724726,53.58157],"type":"Point"}
}