{
  "type": "Feature",
  "properties": {
    "iso:country":"DE",
    "sg:address":"Goseburgstr. 83",
    "sg:city":"L\u00fcneburg",
    "sg:phone":"+49 4131/391394",
    "sg:postcode":"21339",
    "sg:province":"Niedersachsen",
    "wof:name":"Gesellschaft F\u00fcr Lagereibetriebe Mbh",
    "wof:placetype":"venue"
},
  "geometry": {"coordinates":[10.41819,53.266541],"type":"Point"}
}