{
  "type": "Feature",
  "properties": {
    "iso:country":"DE",
    "sg:address":"Universit\u00e4tsstr. 20",
    "sg:city":"Bochum",
    "sg:phone":"+49 234/337608",
    "sg:postcode":"44789",
    "sg:province":"Nordrhein-Westfalen",
    "wof:name":"Margarete Scheibehenne-h\u00f6tten",
    "wof:placetype":"venue"
},
  "geometry": {"coordinates":[7.222762,51.477127],"type":"Point"}
}