{
  "type": "Feature",
  "properties": {
    "iso:country":"DE",
    "sg:address":"Kirchspiel 9",
    "sg:city":"Wiesbaden",
    "sg:phone":"+49 6122/3225",
    "sg:postcode":"65205",
    "sg:province":"Hessen",
    "wof:name":"Anneliese Skonieczny",
    "wof:placetype":"venue"
},
  "geometry": {"coordinates":[8.3626680374,50.0459976196],"type":"Point"}
}