{
  "type": "Feature",
  "properties": {
    "iso:country":"DE",
    "sg:address":"An der Lach 43",
    "sg:city":"N\u00f6rdlingen",
    "sg:phone":"+49 9081/86418",
    "sg:postcode":"86720",
    "sg:province":"Bayern",
    "wof:name":"H\u00f6rndlein Schilderservice Gmbh",
    "wof:placetype":"venue"
},
  "geometry": {"coordinates":[10.511717,48.844559],"type":"Point"}
}