{
  "type": "Feature",
  "properties": {
    "iso:country":"DE",
    "sg:address":"S\u00fcdring 25",
    "sg:city":"Bochum",
    "sg:phone":"+49 234/14750",
    "sg:postcode":"44787",
    "sg:province":"Nordrhein-Westfalen",
    "wof:name":"Friedrich Werdier Zweigndl. Bochum",
    "wof:placetype":"venue"
},
  "geometry": {"coordinates":[7.216714,51.478497],"type":"Point"}
}