{
  "type": "Feature",
  "properties": {
    "iso:country":"DE",
    "sg:address":"Birkenweg 2",
    "sg:city":"Berghuelen",
    "sg:phone":"+49 7344/919004",
    "sg:postcode":"89180",
    "sg:province":"Baden-W\u00fcrttemberg",
    "wof:name":"Haufler Industrievertretungen",
    "wof:placetype":"venue"
},
  "geometry": {"coordinates":[9.7633609772,48.4652633667],"type":"Point"}
}