{
  "type": "Feature",
  "properties": {
    "iso:country":"DE",
    "sg:address":"S\u00fcdbeckenstr. 30",
    "sg:city":"Karlsruhe",
    "sg:phone":"+49 721/550994",
    "sg:postcode":"76189",
    "sg:province":"Baden-W\u00fcrttemberg",
    "wof:name":"Friedrich Quarzsandwerke Kg",
    "wof:placetype":"venue"
},
  "geometry": {"coordinates":[8.3290500641,49.0141029358],"type":"Point"}
}