{
  "type": "Feature",
  "properties": {
    "iso:country":"DE",
    "sg:address":"An der G\u00fcnz 15",
    "sg:city":"Deisenhausen",
    "sg:phone":"+49 8282/4385",
    "sg:postcode":"86489",
    "sg:province":"Bayern",
    "wof:name":"Irmgard Sallinger",
    "wof:placetype":"venue"
},
  "geometry": {"coordinates":[10.320909,48.259163],"type":"Point"}
}