{
  "type": "Feature",
  "properties": {
    "iso:country":"DE",
    "sg:address":"Hauptstr. 13 a",
    "sg:city":"Ahnatal",
    "sg:phone":"+49 5609/1550",
    "sg:postcode":"34292",
    "sg:province":"Hessen",
    "wof:name":"Helfenstein Apotheke Inh. Ulrike J\u00e4hning",
    "wof:placetype":"venue"
},
  "geometry": {"coordinates":[9.426123,51.365562],"type":"Point"}
}