{
  "type": "Feature",
  "properties": {
    "iso:country":"DE",
    "sg:address":"Wei\u00dfenfelser Str. 46c",
    "sg:city":"Merseburg",
    "sg:phone":"+49 3461/205581",
    "sg:postcode":"06217",
    "sg:province":"Sachsen-Anhalt",
    "wof:name":"Mph Industrieprojekt- Management Gmbh",
    "wof:placetype":"venue"
},
  "geometry": {"coordinates":[11.9955835342,51.346244812],"type":"Point"}
}