{
  "type": "Feature",
  "properties": {
    "iso:country":"DE",
    "sg:address":"Paul-Sch\u00fcrholz-Str. 6",
    "sg:city":"Recklinghausen",
    "sg:postcode":"45657",
    "sg:province":"Nordrhein-Westfalen",
    "wof:name":"Immobiliengesellschaft Lauffer Gmbh & Co. Kg",
    "wof:placetype":"venue"
},
  "geometry": {"coordinates":[7.1852798462,51.6232795715],"type":"Point"}
}