{
  "type": "Feature",
  "properties": {
    "iso:country":"DE",
    "sg:address":"Schlo\u00dfstr. 1",
    "sg:city":"Delitzsch",
    "sg:phone":"+49 34202/59695",
    "sg:postcode":"04509",
    "sg:province":"Sachsen",
    "wof:name":"Jens Siebert",
    "wof:placetype":"venue"
},
  "geometry": {"coordinates":[12.331823349,51.5229110718],"type":"Point"}
}