{
  "type": "Feature",
  "properties": {
    "iso:country":"DE",
    "sg:address":"Siedlung am Wald",
    "sg:city":"Sellin",
    "sg:phone":"+49 38303/8484",
    "sg:postcode":"18586",
    "sg:province":"Mecklenburg-Vorpommern",
    "wof:name":"Cliff-hotel Gmbh",
    "wof:placetype":"venue"
},
  "geometry": {"coordinates":[13.7081232071,54.3656921387],"type":"Point"}
}