{
  "type": "Feature",
  "properties": {
    "iso:country":"DE",
    "sg:address":"Burgstr. 31",
    "sg:city":"Wittlich",
    "sg:phone":"+49 6571/6396",
    "sg:postcode":"54516",
    "sg:province":"Rheinland-Pfalz",
    "wof:name":"Gebr. L\u00fctticken",
    "wof:placetype":"venue"
},
  "geometry": {"coordinates":[6.888912,49.986202],"type":"Point"}
}