{
  "type": "Feature",
  "properties": {
    "iso:country":"DE",
    "sg:address":"Erlenstr. 7",
    "sg:city":"Berndorf",
    "sg:phone":"+49 6593/986915",
    "sg:postcode":"54578",
    "sg:province":"Rheinland-Pfalz",
    "wof:name":"Ingo Junk Architekt",
    "wof:placetype":"venue"
},
  "geometry": {"coordinates":[6.700644,50.307014],"type":"Point"}
}