{
  "type": "Feature",
  "properties": {
    "iso:country":"DE",
    "sg:address":"Bahnhofstr. 10",
    "sg:city":"Besigheim",
    "sg:phone":"+49 4971/433009",
    "sg:postcode":"74354",
    "sg:province":"Baden-W\u00fcrttemberg",
    "wof:name":"Walheimer Bank Eg",
    "wof:placetype":"venue"
},
  "geometry": {"coordinates":[9.138869,48.997704],"type":"Point"}
}