{
  "type": "Feature",
  "properties": {
    "iso:country":"DE",
    "sg:address":"Hornbergstr. 102",
    "sg:city":"Stuttgart",
    "sg:phone":"+49 711/461212",
    "sg:postcode":"70188",
    "sg:province":"Baden-W\u00fcrttemberg",
    "wof:name":"Rose",
    "wof:placetype":"venue"
},
  "geometry": {"coordinates":[9.2162904739,48.7823905945],"type":"Point"}
}