{
  "type": "Feature",
  "properties": {
    "iso:country":"DE",
    "sg:address":"Hauptstr. 42",
    "sg:city":"Petershagen",
    "sg:postcode":"32469",
    "sg:province":"Nordrhein-Westfalen",
    "wof:name":"Depot",
    "wof:placetype":"venue"
},
  "geometry": {"coordinates":[8.964676857,52.3773002625],"type":"Point"}
}