{
  "type": "Feature",
  "properties": {
    "iso:country":"DE",
    "sg:address":"Kaiserstr. 6",
    "sg:city":"Frankfurt",
    "sg:phone":"+49 69/2998070",
    "sg:postcode":"60311",
    "sg:province":"Hessen",
    "wof:name":"Frankfurter Verband F\u00fcr Alten- Und Behindertenhilfe E. V.",
    "wof:placetype":"venue"
},
  "geometry": {"coordinates":[8.67628,50.111607],"type":"Point"}
}