{
  "type": "Feature",
  "properties": {
    "iso:country":"DE",
    "sg:address":"R\u00fcttenscheider Str. 166",
    "sg:city":"Essen",
    "sg:phone":"+49 201/410927",
    "sg:postcode":"45131",
    "sg:province":"Nordrhein-Westfalen",
    "wof:name":"Dirck Schr\u00f6der",
    "wof:placetype":"venue"
},
  "geometry": {"coordinates":[7.003056,51.429459],"type":"Point"}
}