{
  "type": "Feature",
  "properties": {
    "iso:country":"DE",
    "sg:address":"Zweenfurther Weg 5",
    "sg:city":"Gerichshain",
    "sg:phone":"+49 34292/72152",
    "sg:postcode":"04827",
    "sg:province":"Sachsen",
    "wof:name":"Rheinzimk Gmbh",
    "wof:placetype":"venue"
},
  "geometry": {"coordinates":[12.576035,51.353577],"type":"Point"}
}