{
  "type": "Feature",
  "properties": {
    "iso:country":"DE",
    "sg:address":"M\u00fclgaustr. 356",
    "sg:city":"M\u00f6nchengladbach",
    "sg:phone":"+49 2166/187031",
    "sg:postcode":"41238",
    "sg:province":"Nordrhein-Westfalen",
    "wof:name":"Deutsche Shell Ag",
    "wof:placetype":"venue"
},
  "geometry": {"coordinates":[6.4538240433,51.1518516541],"type":"Point"}
}