{
  "type": "Feature",
  "properties": {
    "iso:country":"DE",
    "sg:address":"Im Morchhof 34",
    "sg:city":"Mannheim",
    "sg:phone":"+49 621/815910",
    "sg:postcode":"68199",
    "sg:province":"Baden-W\u00fcrttemberg",
    "wof:name":"Schmidt & Kapp Ohg",
    "wof:placetype":"venue"
},
  "geometry": {"coordinates":[8.508312,49.455189],"type":"Point"}
}