{
  "type": "Feature",
  "properties": {
    "iso:country":"DE",
    "sg:address":"Heinkelstr. 27",
    "sg:city":"Schorndorf",
    "sg:phone":"+49 7181/63642",
    "sg:postcode":"73614",
    "sg:province":"Baden-W\u00fcrttemberg",
    "wof:name":"Mykonos",
    "wof:placetype":"venue"
},
  "geometry": {"coordinates":[9.5338249207,48.8077888489],"type":"Point"}
}