{
  "type": "Feature",
  "properties": {
    "iso:country":"DE",
    "sg:address":"Tilsiter Str. 2",
    "sg:city":"Lindhorst",
    "sg:phone":"+49 5725/913803",
    "sg:postcode":"31698",
    "sg:province":"Niedersachsen",
    "wof:name":"Walter Brandenburg",
    "wof:placetype":"venue"
},
  "geometry": {"coordinates":[9.2845649719,52.3617362976],"type":"Point"}
}