{
  "type": "Feature",
  "properties": {
    "iso:country":"DE",
    "sg:address":"Oststr. 20",
    "sg:city":"Velbert",
    "sg:phone":"+49 2051/262285",
    "sg:postcode":"42551",
    "sg:province":"Nordrhein-Westfalen",
    "wof:name":"Deutsches Schlo\u00df- Und Beschl\u00e4ge Museum",
    "wof:placetype":"venue"
},
  "geometry": {"coordinates":[7.047171,51.34153],"type":"Point"}
}