{
  "type": "Feature",
  "properties": {
    "iso:country":"DE",
    "sg:address":"Goebenstr. 24",
    "sg:city":"Essen",
    "sg:phone":"+49 201/280313",
    "sg:postcode":"45139",
    "sg:province":"Nordrhein-Westfalen",
    "wof:name":"M. Hoff Garten- Und",
    "wof:placetype":"venue"
},
  "geometry": {"coordinates":[7.032744,51.453876],"type":"Point"}
}