{
  "type": "Feature",
  "properties": {
    "iso:country":"DE",
    "sg:address":"Hauptstr. 37",
    "sg:city":"Masserberg",
    "sg:phone":"+49 36870/51984",
    "sg:postcode":"98666",
    "sg:province":"Th\u00fcringen",
    "wof:name":"Masserberger Abwasserbeseitigungs Gmbh",
    "wof:placetype":"venue"
},
  "geometry": {"coordinates":[10.969393,50.520008],"type":"Point"}
}