{
  "type": "Feature",
  "properties": {
    "iso:country":"DE",
    "sg:address":"M\u00e4hnstr. 42",
    "sg:city":"Kerpen",
    "sg:phone":"+49 2273/53646",
    "sg:postcode":"50171",
    "sg:province":"Nordrhein-Westfalen",
    "wof:name":"Rapunzel Kinderhaus Service Gmbh",
    "wof:placetype":"venue"
},
  "geometry": {"coordinates":[6.6988320351,50.8699264526],"type":"Point"}
}