{
  "type": "Feature",
  "properties": {
    "iso:country":"DE",
    "sg:address":"Hauptstr. 17",
    "sg:city":"Titisee-Neustadt",
    "sg:phone":"+49 7651/932123",
    "sg:postcode":"79822",
    "sg:province":"Baden-W\u00fcrttemberg",
    "wof:name":"Peter Sigwarth Rechtsanwalt",
    "wof:placetype":"venue"
},
  "geometry": {"coordinates":[8.2120389938,47.9128494263],"type":"Point"}
}