{
  "type": "Feature",
  "properties": {
    "iso:country":"DE",
    "sg:address":"S\u00fclldorfer Brooksweg 65",
    "sg:city":"Hamburg",
    "sg:phone":"+49 40/802429",
    "sg:postcode":"22559",
    "sg:province":"Hamburg",
    "wof:name":"Gerlinde Koebel",
    "wof:placetype":"venue"
},
  "geometry": {"coordinates":[9.7549152374,53.5821266174],"type":"Point"}
}