{
  "type": "Feature",
  "properties": {
    "iso:country":"DE",
    "sg:address":"Nerotal 18",
    "sg:city":"Wiesbaden",
    "sg:phone":"+49 611/180530",
    "sg:postcode":"65193",
    "sg:province":"Hessen",
    "wof:name":"Dr. Med. Manfred Hartung",
    "wof:placetype":"venue"
},
  "geometry": {"coordinates":[8.2306728363,50.093837738],"type":"Point"}
}