{
  "type": "Feature",
  "properties": {
    "iso:country":"DE",
    "sg:address":"Kuhbacher Hauptstr. 75",
    "sg:city":"Lahr",
    "sg:phone":"+49 7821/7534",
    "sg:postcode":"77933",
    "sg:province":"Baden-W\u00fcrttemberg",
    "wof:name":"Josef Kammerer",
    "wof:placetype":"venue"
},
  "geometry": {"coordinates":[7.911265,48.337612],"type":"Point"}
}