{
  "type": "Feature",
  "properties": {
    "iso:country":"DE",
    "sg:address":"Abtsbrede 129",
    "sg:city":"Paderborn",
    "sg:phone":"+49 5251/1700",
    "sg:postcode":"33098",
    "sg:province":"Nordrhein-Westfalen",
    "wof:name":"Adam Titz Vertriebs-gmbh",
    "wof:placetype":"venue"
},
  "geometry": {"coordinates":[8.733297,51.703022],"type":"Point"}
}