{
  "type": "Feature",
  "properties": {
    "iso:country":"DE",
    "sg:address":"Judengasse 23",
    "sg:city":"Worms",
    "sg:phone":"+49 6241/6997",
    "sg:postcode":"67547",
    "sg:province":"Rheinland-Pfalz",
    "wof:name":"Hans Cziumplik Architekt",
    "wof:placetype":"venue"
},
  "geometry": {"coordinates":[8.366001,49.634296],"type":"Point"}
}