{
  "type": "Feature",
  "properties": {
    "iso:country":"DE",
    "sg:address":"Beethovenstr. 8",
    "sg:city":"Illerkirchberg",
    "sg:phone":"+49 7346/2868",
    "sg:postcode":"89171",
    "sg:province":"Baden-W\u00fcrttemberg",
    "wof:name":"Gisela Laib",
    "wof:placetype":"venue"
},
  "geometry": {"coordinates":[10.0191364288,48.3205184937],"type":"Point"}
}