{
  "type": "Feature",
  "properties": {
    "iso:country":"DE",
    "sg:address":"Bruhnstr. 22",
    "sg:city":"Ingolstadt",
    "sg:phone":"+49 841/62439",
    "sg:postcode":"85053",
    "sg:province":"Bayern",
    "wof:name":"Winkelbeiner Gmbh",
    "wof:placetype":"venue"
},
  "geometry": {"coordinates":[11.477661,48.745445],"type":"Point"}
}