{
  "type": "Feature",
  "properties": {
    "iso:country":"DE",
    "sg:address":"Pfarrstr. 2",
    "sg:city":"Dierdorf",
    "sg:phone":"+49 2689/3937",
    "sg:postcode":"56269",
    "sg:province":"Rheinland-Pfalz",
    "wof:name":"Manfred Schmidt Architekt",
    "wof:placetype":"venue"
},
  "geometry": {"coordinates":[7.657196,50.546993],"type":"Point"}
}