{
  "type": "Feature",
  "properties": {
    "iso:country":"DE",
    "sg:address":"Albertstr. 5",
    "sg:city":"Ehrenfriedersdorf",
    "sg:phone":"+49 37341/2184",
    "sg:postcode":"09427",
    "sg:province":"Sachsen",
    "wof:name":"Klaus Richter",
    "wof:placetype":"venue"
},
  "geometry": {"coordinates":[12.9708442688,50.6480407715],"type":"Point"}
}