{
  "type": "Feature",
  "properties": {
    "iso:country":"DE",
    "sg:address":"B\u00fcttelweg 1",
    "sg:city":"Elpersb\u00fcttel",
    "sg:phone":"+49 4832/8364",
    "sg:postcode":"25704",
    "sg:province":"Schleswig-Holstein",
    "wof:name":"Heinrich Thie\u00dfen",
    "wof:placetype":"venue"
},
  "geometry": {"coordinates":[9.074088,54.059311],"type":"Point"}
}