{
  "type": "Feature",
  "properties": {
    "iso:country":"DE",
    "sg:address":"Oststr. 11",
    "sg:city":"Heilbronn",
    "sg:phone":"+49 7131/628330",
    "sg:postcode":"74072",
    "sg:province":"Baden-W\u00fcrttemberg",
    "wof:name":"H. Kampka",
    "wof:placetype":"venue"
},
  "geometry": {"coordinates":[9.2286758423,49.1349372864],"type":"Point"}
}