{
  "type": "Feature",
  "properties": {
    "iso:country":"DE",
    "sg:address":"Hauptstr. 198",
    "sg:city":"Kerpen",
    "sg:phone":"+49 2273/4432",
    "sg:postcode":"50169",
    "sg:province":"Nordrhein-Westfalen",
    "wof:name":"Kath. Pfarramt Christ K\u00f6nig",
    "wof:placetype":"venue"
},
  "geometry": {"coordinates":[6.7056307793,50.924495697],"type":"Point"}
}