{
  "type": "Feature",
  "properties": {
    "iso:country":"DE",
    "sg:address":"Hauptstr. 23",
    "sg:city":"Lollschied",
    "sg:phone":"+49 6772/6875",
    "sg:postcode":"56357",
    "sg:province":"Rheinland-Pfalz",
    "wof:name":"Frank Fuhr",
    "wof:placetype":"venue"
},
  "geometry": {"coordinates":[7.8677229881,50.2554855347],"type":"Point"}
}