{
  "type": "Feature",
  "properties": {
    "iso:country":"DE",
    "sg:address":"Besebrucher Str. 26",
    "sg:city":"Bad Oeynhausen",
    "sg:phone":"+49 5734/7306",
    "sg:postcode":"32549",
    "sg:province":"Nordrhein-Westfalen",
    "wof:name":"I. Gostmann",
    "wof:placetype":"venue"
},
  "geometry": {"coordinates":[8.7420701981,52.2459907532],"type":"Point"}
}