{
  "type": "Feature",
  "properties": {
    "iso:country":"DE",
    "sg:address":"Mahndorfer Heerstr. 44",
    "sg:city":"Bremen",
    "sg:phone":"+49 421/487388",
    "sg:postcode":"28307",
    "sg:province":"Bremen",
    "wof:name":"Achimer Stadtb\u00e4ckerei",
    "wof:placetype":"venue"
},
  "geometry": {"coordinates":[8.944085,53.038094],"type":"Point"}
}