{
  "type": "Feature",
  "properties": {
    "iso:country":"DE",
    "sg:address":"Weidenbruchsweg 11",
    "sg:city":"Neustadt",
    "sg:postcode":"31535",
    "sg:province":"Niedersachsen",
    "wof:name":"Stemke & D\u00f6rbaum Gastst\u00e4tten- Und Bootssteg-",
    "wof:placetype":"venue"
},
  "geometry": {"coordinates":[9.3205280304,52.4908981323],"type":"Point"}
}