{
  "type": "Feature",
  "properties": {
    "iso:country":"DE",
    "sg:address":"Ziegendorfer Chaussee 2",
    "sg:city":"Parchim",
    "sg:phone":"+49 3871/43000",
    "sg:postcode":"19370",
    "sg:province":"Mecklenburg-Vorpommern",
    "wof:name":"Sigro Parchim Gmbh",
    "wof:placetype":"venue"
},
  "geometry": {"coordinates":[11.8362569809,53.4290275574],"type":"Point"}
}