{
  "type": "Feature",
  "properties": {
    "iso:country":"DE",
    "sg:address":"Op de Schanz 4",
    "sg:city":"Xanten",
    "sg:phone":"+49 2802/1835",
    "sg:postcode":"46509",
    "sg:province":"Nordrhein-Westfalen",
    "wof:name":"M. Laakmann Gmbh",
    "wof:placetype":"venue"
},
  "geometry": {"coordinates":[6.494918,51.621552],"type":"Point"}
}