{
  "type": "Feature",
  "properties": {
    "iso:country":"DE",
    "sg:address":"Veilchenweg 2",
    "sg:city":"Dresden",
    "sg:phone":"+49 351/2641240",
    "sg:postcode":"01326",
    "sg:province":"Sachsen",
    "wof:name":"Claus P\u00e4perer",
    "wof:placetype":"venue"
},
  "geometry": {"coordinates":[13.815661,51.053745],"type":"Point"}
}