{
  "type": "Feature",
  "properties": {
    "iso:country":"DE",
    "sg:address":"Kirchenweg 5",
    "sg:city":"Westerland",
    "sg:phone":"+49 4651/1455",
    "sg:postcode":"25980",
    "sg:province":"Schleswig-Holstein",
    "wof:name":"Falk Hartmann",
    "wof:placetype":"venue"
},
  "geometry": {"coordinates":[8.309469223,54.9081115723],"type":"Point"}
}