{
  "type": "Feature",
  "properties": {
    "iso:country":"DE",
    "sg:address":"Ludwigsweg 2",
    "sg:city":"Herbstein",
    "sg:phone":"+49 6643/7171",
    "sg:postcode":"36358",
    "sg:province":"Hessen",
    "wof:name":"Pension Ilse Leister Und Pius",
    "wof:placetype":"venue"
},
  "geometry": {"coordinates":[9.3438796997,50.5588264465],"type":"Point"}
}