{
  "type": "Feature",
  "properties": {
    "iso:country":"DE",
    "sg:address":"Obergasse 5",
    "sg:city":"Ensheim",
    "sg:phone":"+49 4967/322995",
    "sg:postcode":"55232",
    "sg:province":"Rheinland-Pfalz",
    "wof:name":"Volksbank W\u00f6rrstadt Eg",
    "wof:placetype":"venue"
},
  "geometry": {"coordinates":[8.114789,49.805897],"type":"Point"}
}