{
  "type": "Feature",
  "properties": {
    "iso:country":"DE",
    "sg:address":"Bahnhofstr. 2",
    "sg:city":"Lenting",
    "sg:phone":"+49 8456/5536",
    "sg:postcode":"85101",
    "sg:province":"Bayern",
    "wof:name":"Franz H\u00e4ndl",
    "wof:placetype":"venue"
},
  "geometry": {"coordinates":[11.461522,48.807022],"type":"Point"}
}