{
  "type": "Feature",
  "properties": {
    "iso:country":"DE",
    "sg:address":"Wiesenweg 13",
    "sg:city":"Schrobenhausen",
    "sg:phone":"+49 8252/1710",
    "sg:postcode":"86529",
    "sg:province":"Bayern",
    "wof:name":"Peter Brendt",
    "wof:placetype":"venue"
},
  "geometry": {"coordinates":[11.24769,48.568439],"type":"Point"}
}