{
  "type": "Feature",
  "properties": {
    "iso:country":"DE",
    "sg:address":"Hauptstr. 10",
    "sg:city":"Fischbach",
    "sg:postcode":"01477",
    "sg:province":"Sachsen",
    "wof:name":"Gemeindeschwesterstation",
    "wof:placetype":"venue"
},
  "geometry": {"coordinates":[14.018818,51.085133],"type":"Point"}
}