{
  "type": "Feature",
  "properties": {
    "iso:country":"DE",
    "sg:address":"Hauptstr. 8",
    "sg:city":"Merching",
    "sg:postcode":"86504",
    "sg:province":"Bayern",
    "wof:name":"Landgasthof Aumiller Beteiligungs- Gmbh",
    "wof:placetype":"venue"
},
  "geometry": {"coordinates":[10.984738,48.244812],"type":"Point"}
}