{
  "type": "Feature",
  "properties": {
    "iso:country":"DE",
    "sg:address":"Neue-Anlage-Str. 2",
    "sg:city":"Karlsruhe",
    "sg:phone":"+49 721/868992",
    "sg:postcode":"76135",
    "sg:province":"Baden-W\u00fcrttemberg",
    "wof:name":"Regina Behrendt Praxis F\u00fcr Krankengymnastik",
    "wof:placetype":"venue"
},
  "geometry": {"coordinates":[8.384387,48.990471],"type":"Point"}
}