{
  "type": "Feature",
  "properties": {
    "iso:country":"DE",
    "sg:address":"St.-Kastulus-Weg 3",
    "sg:city":"Utting",
    "sg:phone":"+49 8806/7465",
    "sg:postcode":"86919",
    "sg:province":"Bayern",
    "wof:name":"T. Und I. Huber Antiquit\u00e4ten",
    "wof:placetype":"venue"
},
  "geometry": {"coordinates":[11.085934,48.022659],"type":"Point"}
}