{
  "type": "Feature",
  "properties": {
    "iso:country":"DE",
    "sg:address":"Bollmannstr. 34",
    "sg:city":"Nienburg",
    "sg:phone":"+49 5021/66483",
    "sg:postcode":"31582",
    "sg:province":"Niedersachsen",
    "wof:name":"Hb Industriemontagen Gmbh",
    "wof:placetype":"venue"
},
  "geometry": {"coordinates":[9.2236022949,52.6606063843],"type":"Point"}
}