{
  "type": "Feature",
  "properties": {
    "iso:country":"DE",
    "sg:address":"M\u00fchlenweg 131",
    "sg:city":"Norderstedt",
    "sg:phone":"+49 40/52681530",
    "sg:postcode":"22844",
    "sg:province":"Schleswig-Holstein",
    "wof:name":"Mkm Mansfelder Kupfer U. Messing Gmbh",
    "wof:placetype":"venue"
},
  "geometry": {"coordinates":[10.017606,53.727623],"type":"Point"}
}