{
  "type": "Feature",
  "properties": {
    "iso:country":"DE",
    "sg:address":"Am Wirthemb\u00f6sch 14",
    "sg:city":"St. Wendel",
    "sg:phone":"+49 6851/6768",
    "sg:postcode":"66606",
    "sg:province":"Saarland",
    "wof:name":"R. Peter Heissmangel",
    "wof:placetype":"venue"
},
  "geometry": {"coordinates":[7.1599411964,49.4647712708],"type":"Point"}
}