{
  "type": "Feature",
  "properties": {
    "iso:country":"DE",
    "sg:address":"Distelkamp 12",
    "sg:city":"Wedemark",
    "sg:phone":"+49 5130/7012",
    "sg:postcode":"30900",
    "sg:province":"Niedersachsen",
    "wof:name":"Prof. Dr. Hartmut Jacob Und Monika Jocob-goldeck",
    "wof:placetype":"venue"
},
  "geometry": {"coordinates":[9.69718,52.52475],"type":"Point"}
}