{
  "type": "Feature",
  "properties": {
    "iso:country":"DE",
    "sg:address":"Sandstr. 10",
    "sg:city":"Rosenheim",
    "sg:phone":"+49 8031/37407",
    "sg:postcode":"83022",
    "sg:province":"Bayern",
    "wof:name":"Georg Renner",
    "wof:placetype":"venue"
},
  "geometry": {"coordinates":[12.1172981262,47.8534126282],"type":"Point"}
}