{
  "type": "Feature",
  "properties": {
    "iso:country":"DE",
    "sg:address":"D\u00f6ttscheider Weg 14",
    "sg:city":"K\u00f6nigswinter",
    "sg:phone":"+49 2223/27293",
    "sg:postcode":"53639",
    "sg:province":"Nordrhein-Westfalen",
    "wof:name":"Peter H\u00f6mmerich",
    "wof:placetype":"venue"
},
  "geometry": {"coordinates":[7.264747,50.686451],"type":"Point"}
}