{
  "type": "Feature",
  "properties": {
    "iso:country":"DE",
    "sg:address":"Freiberger Str. 13",
    "sg:city":"Frankenberg",
    "sg:phone":"+49 37206/2835",
    "sg:postcode":"09669",
    "sg:province":"Sachsen",
    "wof:name":"Wws Steuerberatungsges. Mbh",
    "wof:placetype":"venue"
},
  "geometry": {"coordinates":[13.0356550217,50.9109039307],"type":"Point"}
}