{
  "type": "Feature",
  "properties": {
    "iso:country":"DE",
    "sg:address":"Sallach 41",
    "sg:city":"Geiselh\u00f6ring",
    "sg:phone":"+49 9423/833",
    "sg:postcode":"94333",
    "sg:province":"Bayern",
    "wof:name":"Anni Gottwald",
    "wof:placetype":"venue"
},
  "geometry": {"coordinates":[12.3932800293,48.8259887695],"type":"Point"}
}