{
  "type": "Feature",
  "properties": {
    "iso:country":"DE",
    "sg:address":"Regensburger Str. 11",
    "sg:city":"Alteglofsheim",
    "sg:phone":"+49 9453/99370",
    "sg:postcode":"93087",
    "sg:province":"Bayern",
    "wof:name":"Aumer Treppenwerk Inh. Walter Aumer E. K.",
    "wof:placetype":"venue"
},
  "geometry": {"coordinates":[12.2089500427,48.922252655],"type":"Point"}
}