{
  "type": "Feature",
  "properties": {
    "iso:country":"DE",
    "sg:address":"Lange Str. 4",
    "sg:city":"Bar\u00dfel",
    "sg:phone":"+49 4499/923016",
    "sg:postcode":"26676",
    "sg:province":"Niedersachsen",
    "wof:name":"Fehn-grill",
    "wof:placetype":"venue"
},
  "geometry": {"coordinates":[7.742193222,53.1693878174],"type":"Point"}
}