{
  "type": "Feature",
  "properties": {
    "iso:country":"DE",
    "sg:address":"Normannische Str. 3",
    "sg:city":"Ronnenberg",
    "sg:phone":"+49 5109/1448",
    "sg:postcode":"30952",
    "sg:province":"Niedersachsen",
    "wof:name":"Edmund Raetsel",
    "wof:placetype":"venue"
},
  "geometry": {"coordinates":[9.649618,52.316902],"type":"Point"}
}