{
  "type": "Feature",
  "properties": {
    "iso:country":"DE",
    "sg:address":"M\u00fcnchner Str. 3",
    "sg:city":"Sch\u00e4ftlarn",
    "sg:phone":"+49 8178/97010",
    "sg:postcode":"82069",
    "sg:province":"Bayern",
    "wof:name":"Koppermann Computersysteme Gmbh",
    "wof:placetype":"venue"
},
  "geometry": {"coordinates":[11.4638357162,47.99792099],"type":"Point"}
}