{
  "type": "Feature",
  "properties": {
    "iso:country":"DE",
    "sg:address":"Wiesenstr. 19",
    "sg:city":"Helmstedt",
    "sg:phone":"+49 5351/3670",
    "sg:postcode":"38350",
    "sg:province":"Niedersachsen",
    "wof:name":"Schrader Gmbh Inh. Peter Hille",
    "wof:placetype":"venue"
},
  "geometry": {"coordinates":[10.9686994553,52.2420310974],"type":"Point"}
}