{
  "type": "Feature",
  "properties": {
    "iso:country":"DE",
    "sg:address":"Etelser Bahnhofstr. 15",
    "sg:city":"Langwedel",
    "sg:phone":"+49 4235/595",
    "sg:postcode":"27299",
    "sg:province":"Niedersachsen",
    "wof:name":"Kreissparkasse",
    "wof:placetype":"venue"
},
  "geometry": {"coordinates":[9.11766,52.996674],"type":"Point"}
}