{
  "type": "Feature",
  "properties": {
    "iso:country":"DE",
    "sg:address":"Austr. 11",
    "sg:city":"Stuttgart",
    "sg:phone":"+49 711/591869",
    "sg:postcode":"70376",
    "sg:province":"Baden-W\u00fcrttemberg",
    "wof:name":"Hermann Seif",
    "wof:placetype":"venue"
},
  "geometry": {"coordinates":[9.225810051,48.8209114075],"type":"Point"}
}