{
  "type": "Feature",
  "properties": {
    "iso:country":"DE",
    "sg:address":"Schulterblatt 17",
    "sg:city":"Hamburg",
    "sg:phone":"+49 40/4300548",
    "sg:postcode":"20357",
    "sg:province":"Hamburg",
    "wof:name":"G\u00fcr Gmbh",
    "wof:placetype":"venue"
},
  "geometry": {"coordinates":[9.96366,53.559792],"type":"Point"}
}