{
  "type": "Feature",
  "properties": {
    "iso:country":"DE",
    "sg:address":"Gartenstr. 10",
    "sg:city":"Berlin",
    "sg:phone":"+49 30/4424462",
    "sg:postcode":"13129",
    "sg:province":"Berlin",
    "wof:name":"Hobema Handels Gmbh",
    "wof:placetype":"venue"
},
  "geometry": {"coordinates":[13.454638,52.594482],"type":"Point"}
}