{
  "type": "Feature",
  "properties": {
    "iso:country":"DE",
    "sg:address":"Linsenhofstr. 16",
    "sg:city":"Gomaringen",
    "sg:phone":"+49 7072/920865",
    "sg:postcode":"72810",
    "sg:province":"Baden-W\u00fcrttemberg",
    "wof:name":"A. Von Kutzschenbach Hebamme",
    "wof:placetype":"venue"
},
  "geometry": {"coordinates":[9.098755,48.453308],"type":"Point"}
}