{
  "type": "Feature",
  "properties": {
    "iso:country":"DE",
    "sg:address":"Hildener Str. 143",
    "sg:city":"D\u00fcsseldorf",
    "sg:phone":"+49 211/7184836",
    "sg:postcode":"40597",
    "sg:province":"Nordrhein-Westfalen",
    "wof:name":"Gemeinsinn Direkt E. K.",
    "wof:placetype":"venue"
},
  "geometry": {"coordinates":[6.895276,51.161179],"type":"Point"}
}