{
  "type": "Feature",
  "properties": {
    "iso:country":"DE",
    "sg:address":"Morgenbergstr. 41",
    "sg:city":"Plauen",
    "sg:phone":"+49 3741/525674",
    "sg:postcode":"08525",
    "sg:province":"Sachsen",
    "wof:name":"Andreas Beier Und Andreas Huster Gbr",
    "wof:placetype":"venue"
},
  "geometry": {"coordinates":[12.127251,50.513557],"type":"Point"}
}