{
  "type": "Feature",
  "properties": {
    "iso:country":"DE",
    "sg:address":"Hauptstr. 47",
    "sg:city":"Wald-Michelbach",
    "sg:phone":"+49 6207/2608",
    "sg:postcode":"69483",
    "sg:province":"Hessen",
    "wof:name":"Koudele Elektro",
    "wof:placetype":"venue"
},
  "geometry": {"coordinates":[8.854838,49.597721],"type":"Point"}
}