{
  "type": "Feature",
  "properties": {
    "iso:country":"DE",
    "sg:address":"Rathausplatz 2",
    "sg:city":"Gro\u00df-Zimmern",
    "sg:phone":"+49 6071/43277",
    "sg:postcode":"64846",
    "sg:province":"Hessen",
    "wof:name":"Mehrzweckhalle",
    "wof:placetype":"venue"
},
  "geometry": {"coordinates":[8.83343,49.873405],"type":"Point"}
}