{
  "type": "Feature",
  "properties": {
    "iso:country":"DE",
    "sg:address":"Wei\u00dfenburger Str. 61",
    "sg:city":"Gunzenhausen",
    "sg:phone":"+49 9831/67200",
    "sg:postcode":"91710",
    "sg:province":"Bayern",
    "wof:name":"Ivg-immobilien Vermittlungs Gmbh",
    "wof:placetype":"venue"
},
  "geometry": {"coordinates":[10.7583036423,49.1084365845],"type":"Point"}
}