{
  "type": "Feature",
  "properties": {
    "iso:country":"DE",
    "sg:address":"Koblenzer Str. 77",
    "sg:city":"Mudersbach",
    "sg:postcode":"57555",
    "sg:province":"Rheinland-Pfalz",
    "wof:name":"Raif Pramenkovic Gmbh",
    "wof:placetype":"venue"
},
  "geometry": {"coordinates":[7.9402618408,50.8237991333],"type":"Point"}
}