{
  "type": "Feature",
  "properties": {
    "iso:country":"DE",
    "sg:address":"Bahnhofstr. 5",
    "sg:city":"Schmallenberg",
    "sg:phone":"+49 2972/5607",
    "sg:postcode":"57392",
    "sg:province":"Nordrhein-Westfalen",
    "wof:name":"Gastst\u00e4tte T. C. Foong",
    "wof:placetype":"venue"
},
  "geometry": {"coordinates":[8.2564678192,51.1359901428],"type":"Point"}
}