{
  "type": "Feature",
  "properties": {
    "iso:country":"DE",
    "sg:address":"Dorfstr. 38 b",
    "sg:city":"Oehna",
    "sg:phone":"+49 33742/60233",
    "sg:postcode":"14913",
    "sg:province":"Brandenburg",
    "wof:name":"Pension Oehnaland",
    "wof:placetype":"venue"
},
  "geometry": {"coordinates":[13.0435113907,51.929145813],"type":"Point"}
}