{
  "type": "Feature",
  "properties": {
    "iso:country":"DE",
    "sg:address":"Am Kanal 26",
    "sg:city":"Twist",
    "sg:phone":"+49 5936/505",
    "sg:postcode":"49767",
    "sg:province":"Niedersachsen",
    "wof:name":"Birkhahn-apotheke Martin Hasenbank E. K.",
    "wof:placetype":"venue"
},
  "geometry": {"coordinates":[7.098704,52.64547],"type":"Point"}
}