{
  "type": "Feature",
  "properties": {
    "iso:country":"DE",
    "sg:address":"Nr. 76",
    "sg:city":"Guderhandviertel",
    "sg:phone":"+49 4142/2426",
    "sg:postcode":"21720",
    "sg:province":"Niedersachsen",
    "wof:name":"Diedrich Borgmann",
    "wof:placetype":"venue"
},
  "geometry": {"coordinates":[9.6092042923,53.5613708496],"type":"Point"}
}