{
  "type": "Feature",
  "properties": {
    "iso:country":"DE",
    "sg:address":"Br\u00fcckenstr. 10",
    "sg:city":"Saarburg",
    "sg:phone":"+49 6581/6856",
    "sg:postcode":"54439",
    "sg:province":"Rheinland-Pfalz",
    "wof:name":"Lidl Markt",
    "wof:placetype":"venue"
},
  "geometry": {"coordinates":[6.5561327934,49.6065406799],"type":"Point"}
}