{
  "type": "Feature",
  "properties": {
    "iso:country":"DE",
    "sg:address":"Heinrich-Hertz-Str. 10",
    "sg:city":"Erkrath",
    "sg:phone":"+49 211/250040",
    "sg:postcode":"40699",
    "sg:province":"Nordrhein-Westfalen",
    "wof:name":"Romaco Gmbh",
    "wof:placetype":"venue"
},
  "geometry": {"coordinates":[6.915788,51.198296],"type":"Point"}
}