{
  "type": "Feature",
  "properties": {
    "iso:country":"DE",
    "sg:address":"Neumarkter Str. 34",
    "sg:city":"M\u00fcnchen",
    "sg:phone":"+49 89/4313048",
    "sg:postcode":"81673",
    "sg:province":"Bayern",
    "wof:name":"Coffema International Handel Gmbh",
    "wof:placetype":"venue"
},
  "geometry": {"coordinates":[11.6215906143,48.1324043274],"type":"Point"}
}