{
  "type": "Feature",
  "properties": {
    "iso:country":"DE",
    "sg:address":"Stra\u00dfe der Jugend 1",
    "sg:city":"Werdau",
    "sg:phone":"+49 3761/5230",
    "sg:postcode":"08412",
    "sg:province":"Sachsen",
    "wof:name":"Sanit\u00e4tshaus Backhaus Gmbh",
    "wof:placetype":"venue"
},
  "geometry": {"coordinates":[12.3783798218,50.728729248],"type":"Point"}
}