{
  "type": "Feature",
  "properties": {
    "iso:country":"DE",
    "sg:address":"Kronst\u00e4dter Platz 1",
    "sg:city":"Dresden",
    "sg:phone":"+49 351/2571932",
    "sg:postcode":"01279",
    "sg:province":"Sachsen",
    "wof:name":"P. Rother",
    "wof:placetype":"venue"
},
  "geometry": {"coordinates":[13.839875,51.021965],"type":"Point"}
}