{
  "type": "Feature",
  "properties": {
    "iso:country":"DE",
    "sg:address":"Am Sedanplatz 3-4",
    "sg:city":"Bremen",
    "sg:phone":"+49 421/658560",
    "sg:postcode":"28757",
    "sg:province":"Bremen",
    "wof:name":"K\u00f6rber Gmbh",
    "wof:placetype":"venue"
},
  "geometry": {"coordinates":[8.617333,53.173637],"type":"Point"}
}