{
  "type": "Feature",
  "properties": {
    "iso:country":"DE",
    "sg:address":"Oberdorfstr. 20",
    "sg:city":"Wagh\u00e4usel",
    "sg:postcode":"68753",
    "sg:province":"Baden-W\u00fcrttemberg",
    "wof:name":"Rolf Heinzmann",
    "wof:placetype":"venue"
},
  "geometry": {"coordinates":[8.5475616455,49.2410697937],"type":"Point"}
}