{
  "type": "Feature",
  "properties": {
    "iso:country":"DE",
    "sg:address":"Bieberkamp 199",
    "sg:city":"Menden",
    "sg:phone":"+49 4923/79449",
    "sg:postcode":"58708",
    "sg:province":"Nordrhein-Westfalen",
    "wof:name":"Rolf Eckert",
    "wof:placetype":"venue"
},
  "geometry": {"coordinates":[7.84526,51.43438],"type":"Point"}
}