{
  "type": "Feature",
  "properties": {
    "iso:country":"DE",
    "sg:address":"F\u00fcrst-Bismarck-Str 21",
    "sg:city":"Duisburg",
    "sg:phone":"+49 203/8000444",
    "sg:postcode":"47119",
    "sg:province":"Nordrhein-Westfalen",
    "wof:name":"Eutra Transport & Logistik Gmbh",
    "wof:placetype":"venue"
},
  "geometry": {"coordinates":[6.731098175,51.4555549622],"type":"Point"}
}