{
  "type": "Feature",
  "properties": {
    "iso:country":"DE",
    "sg:address":"Am Markt 2",
    "sg:city":"Elstra",
    "sg:phone":"+49 35793/5290",
    "sg:postcode":"01920",
    "sg:province":"Sachsen",
    "wof:name":"Schwarzes Ro\u00df",
    "wof:placetype":"venue"
},
  "geometry": {"coordinates":[14.1331882477,51.2218322754],"type":"Point"}
}