{
  "type": "Feature",
  "properties": {
    "iso:country":"DE",
    "sg:address":"Regensburger Str. 92",
    "sg:city":"Neumarkt",
    "sg:phone":"+49 9181/254801",
    "sg:postcode":"92318",
    "sg:province":"Bayern",
    "wof:name":"Oliver Und Andre Schottner Oase Engineering Gmbh",
    "wof:placetype":"venue"
},
  "geometry": {"coordinates":[11.4721708298,49.2669906616],"type":"Point"}
}