{
  "type": "Feature",
  "properties": {
    "iso:country":"DE",
    "sg:address":"Am Schwarzenberg",
    "sg:city":"Schmallenberg",
    "sg:phone":"+49 2972/2040",
    "sg:postcode":"57392",
    "sg:province":"Nordrhein-Westfalen",
    "wof:name":"Willi Starke",
    "wof:placetype":"venue"
},
  "geometry": {"coordinates":[8.2288160324,51.1272239685],"type":"Point"}
}