{
  "type": "Feature",
  "properties": {
    "iso:country":"DE",
    "sg:address":"Dufkampstr. 21",
    "sg:city":"Stadtlohn",
    "sg:phone":"+49 2563/1831",
    "sg:postcode":"48703",
    "sg:province":"Nordrhein-Westfalen",
    "wof:name":"Heinrich Nathues",
    "wof:placetype":"venue"
},
  "geometry": {"coordinates":[6.9189510345,51.9934921265],"type":"Point"}
}