{
  "type": "Feature",
  "properties": {
    "iso:country":"DE",
    "sg:address":"Spessartstr. 18",
    "sg:city":"Walluf",
    "sg:phone":"+49 6123/73123",
    "sg:postcode":"65396",
    "sg:province":"Hessen",
    "wof:name":"Die Rebl\u00e4use Karl-ernst Eschborn",
    "wof:placetype":"venue"
},
  "geometry": {"coordinates":[8.1584730148,50.0393753052],"type":"Point"}
}