{
  "type": "Feature",
  "properties": {
    "iso:country":"DE",
    "sg:address":"Haabergstr. 135",
    "sg:city":"B\u00fchlertal",
    "sg:phone":"+49 7223/72120",
    "sg:postcode":"77830",
    "sg:province":"Baden-W\u00fcrttemberg",
    "wof:name":"Erpe Bauleistungs- Gesellschaft Mbh",
    "wof:placetype":"venue"
},
  "geometry": {"coordinates":[8.1789007187,48.6812477112],"type":"Point"}
}