{
  "type": "Feature",
  "properties": {
    "iso:country":"DE",
    "sg:address":"Extumer Br\u00fcckenstr. 98",
    "sg:city":"Aurich",
    "sg:phone":"+49 4941/87645",
    "sg:postcode":"26605",
    "sg:province":"Niedersachsen",
    "wof:name":"Wolfgang Rieken",
    "wof:placetype":"venue"
},
  "geometry": {"coordinates":[7.433472,53.472057],"type":"Point"}
}