{
  "type": "Feature",
  "properties": {
    "iso:country":"DE",
    "sg:address":"H\u00fcttenweg 2",
    "sg:city":"Baruth",
    "sg:phone":"+49 33704/61644",
    "sg:postcode":"15837",
    "sg:province":"Brandenburg",
    "wof:name":"Kleintierz\u00fcchterverein D. L\u00f6ffler",
    "wof:placetype":"venue"
},
  "geometry": {"coordinates":[13.584031105,52.0265045166],"type":"Point"}
}