{
  "type": "Feature",
  "properties": {
    "iso:country":"DE",
    "sg:address":"Konrad-Adenauer-Str. 26",
    "sg:city":"Linden",
    "sg:phone":"+49 6403/64556",
    "sg:postcode":"35440",
    "sg:province":"Hessen",
    "wof:name":"Lindener Ratsstuben",
    "wof:placetype":"venue"
},
  "geometry": {"coordinates":[8.6648387909,50.5253334045],"type":"Point"}
}