{
  "type": "Feature",
  "properties": {
    "iso:country":"DE",
    "sg:address":"Kastanienstr. 15",
    "sg:city":"Schellerten",
    "sg:phone":"+49 5123/8470",
    "sg:postcode":"31174",
    "sg:province":"Niedersachsen",
    "wof:name":"Wilhelm Maasberg",
    "wof:placetype":"venue"
},
  "geometry": {"coordinates":[10.108835,52.208649],"type":"Point"}
}