{
  "type": "Feature",
  "properties": {
    "iso:country":"DE",
    "sg:address":"Albrechtstr. 51",
    "sg:city":"Berlin",
    "sg:phone":"+49 30/7517706",
    "sg:postcode":"12103",
    "sg:province":"Berlin",
    "wof:name":"Jazz F\u00fcr Alle E. V.",
    "wof:placetype":"venue"
},
  "geometry": {"coordinates":[13.3824701309,52.4612007141],"type":"Point"}
}