{
  "type": "Feature",
  "properties": {
    "iso:country":"DE",
    "sg:address":"Kampenwandstr. 17",
    "sg:city":"Poing",
    "sg:phone":"+49 8121/76447",
    "sg:postcode":"85586",
    "sg:province":"Bayern",
    "wof:name":"M. Tiefert",
    "wof:placetype":"venue"
},
  "geometry": {"coordinates":[11.822455,48.170525],"type":"Point"}
}