{
  "type": "Feature",
  "properties": {
    "iso:country":"DE",
    "sg:address":"Im Neuen Felde 61",
    "sg:city":"Uelzen",
    "sg:phone":"+49 581/2831",
    "sg:postcode":"29525",
    "sg:province":"Niedersachsen",
    "wof:name":"Hans-j\u00fcrgen Mack Fern- Und Grossk\u00fcche \u00f6ffentl.",
    "wof:placetype":"venue"
},
  "geometry": {"coordinates":[10.559472084,52.9806175232],"type":"Point"}
}