{
  "type": "Feature",
  "properties": {
    "iso:country":"DE",
    "sg:address":"Flinger Richtweg 60",
    "sg:city":"D\u00fcsseldorf",
    "sg:phone":"+49 211/230502",
    "sg:postcode":"40235",
    "sg:province":"Nordrhein-Westfalen",
    "wof:name":"Mfb Anlagenbau Gmbh",
    "wof:placetype":"venue"
},
  "geometry": {"coordinates":[6.829712,51.23201],"type":"Point"}
}