{
  "type": "Feature",
  "properties": {
    "iso:country":"DE",
    "sg:address":"K\u00f6hlstr. 13",
    "sg:city":"Quierschied",
    "sg:phone":"+49 6897/66400",
    "sg:postcode":"66287",
    "sg:province":"Saarland",
    "wof:name":"Dieters Kneipe",
    "wof:placetype":"venue"
},
  "geometry": {"coordinates":[7.0546751022,49.3294715881],"type":"Point"}
}