{
  "type": "Feature",
  "properties": {
    "iso:country":"DE",
    "sg:address":"Bismarckstr. 314",
    "sg:city":"Gelsenkirchen",
    "sg:phone":"+49 209/82897",
    "sg:postcode":"45889",
    "sg:province":"Nordrhein-Westfalen",
    "wof:name":"Bp Tankstelle",
    "wof:placetype":"venue"
},
  "geometry": {"coordinates":[7.1105089188,51.5365715027],"type":"Point"}
}