{
  "type": "Feature",
  "properties": {
    "iso:country":"DE",
    "sg:address":"Plau\u00dfiger Dorfstr. 37",
    "sg:city":"Leipzig",
    "sg:phone":"+49 34298/68324",
    "sg:postcode":"04349",
    "sg:province":"Sachsen",
    "wof:name":"Manfred Paul",
    "wof:placetype":"venue"
},
  "geometry": {"coordinates":[12.458063,51.39299],"type":"Point"}
}