{
  "type": "Feature",
  "properties": {
    "iso:country":"DE",
    "sg:address":"Kirchweg 7",
    "sg:city":"Bad Wildbad",
    "sg:phone":"+49 7055/1720",
    "sg:postcode":"75323",
    "sg:province":"Baden-W\u00fcrttemberg",
    "wof:name":"Ev. Pfarramt Aichelberg",
    "wof:placetype":"venue"
},
  "geometry": {"coordinates":[8.5226230621,48.6640014648],"type":"Point"}
}