{
  "type": "Feature",
  "properties": {
    "iso:country":"DE",
    "sg:address":"Dorfstr. 13",
    "sg:city":"Sch\u00f6nerlinde",
    "sg:phone":"+49 30/94009500",
    "sg:postcode":"16352",
    "wof:name":"Sch\u00f6nerlindener Rohrleitungsbau",
    "wof:placetype":"venue"
},
  "geometry": {"coordinates":[9.8496370316,50.2494239807],"type":"Point"}
}