{
  "type": "Feature",
  "properties": {
    "iso:country":"DE",
    "sg:address":"Bonner Rg. 49",
    "sg:city":"Erftstadt",
    "sg:phone":"+49 2235/955210",
    "sg:postcode":"50374",
    "sg:province":"Nordrhein-Westfalen",
    "wof:name":"Welter Peter Gmbh & Co Kg",
    "wof:placetype":"venue"
},
  "geometry": {"coordinates":[6.775007,50.7952],"type":"Point"}
}