{
  "type": "Feature",
  "properties": {
    "iso:country":"DE",
    "sg:address":"Goebenstr. 15",
    "sg:city":"Halle",
    "sg:phone":"+49 5201/668320",
    "sg:postcode":"33790",
    "sg:province":"Nordrhein-Westfalen",
    "wof:name":"Ergotherapiepraxis Vincke",
    "wof:placetype":"venue"
},
  "geometry": {"coordinates":[8.355942,52.05872],"type":"Point"}
}