{
  "type": "Feature",
  "properties": {
    "iso:country":"DE",
    "sg:address":"Georg-Schlosser-Str. 13",
    "sg:city":"Gie\u00dfen",
    "sg:phone":"+49 641/34591",
    "sg:postcode":"35390",
    "sg:province":"Hessen",
    "wof:name":"Hotel-pension Burkart",
    "wof:placetype":"venue"
},
  "geometry": {"coordinates":[8.6729202271,50.5876083374],"type":"Point"}
}