{
  "type": "Feature",
  "properties": {
    "iso:country":"DE",
    "sg:address":"Am Markt",
    "sg:city":"Oberwiesenthal",
    "sg:phone":"+49 37348/400",
    "sg:postcode":"09484",
    "sg:province":"Sachsen",
    "wof:name":"Kreissparkasse",
    "wof:placetype":"venue"
},
  "geometry": {"coordinates":[12.97074,50.418831],"type":"Point"}
}