{
  "type": "Feature",
  "properties": {
    "iso:country":"DE",
    "sg:address":"Rudolfswieke 192",
    "sg:city":"Moormerland",
    "sg:phone":"+49 4950/2726",
    "sg:postcode":"26802",
    "sg:province":"Niedersachsen",
    "wof:name":"Heiko Follrichs",
    "wof:placetype":"venue"
},
  "geometry": {"coordinates":[7.541277,53.302685],"type":"Point"}
}