{
  "type": "Feature",
  "properties": {
    "iso:country":"DE",
    "sg:address":"D\u00fclkener Str. 45",
    "sg:city":"Viersen",
    "sg:phone":"+49 2162/93550",
    "sg:postcode":"41747",
    "sg:province":"Nordrhein-Westfalen",
    "wof:name":"Viers Finanz Gmbh",
    "wof:placetype":"venue"
},
  "geometry": {"coordinates":[6.3818860054,51.2583618164],"type":"Point"}
}