{
  "type": "Feature",
  "properties": {
    "iso:country":"DE",
    "sg:address":"Bahnhofstr. 11",
    "sg:city":"Schee\u00dfel",
    "sg:phone":"+49 4263/3355",
    "sg:postcode":"27383",
    "sg:province":"Niedersachsen",
    "wof:name":"Eckhard Schlobohm Und Petra Hahne",
    "wof:placetype":"venue"
},
  "geometry": {"coordinates":[9.4842977524,53.1682243347],"type":"Point"}
}