{
  "type": "Feature",
  "properties": {
    "iso:country":"DE",
    "sg:address":"Kampsriede 6 A",
    "sg:city":"Hannover",
    "sg:phone":"+49 511/61711",
    "sg:postcode":"30659",
    "sg:province":"Niedersachsen",
    "wof:name":"Kliche Architekt",
    "wof:placetype":"venue"
},
  "geometry": {"coordinates":[9.823014,52.417259],"type":"Point"}
}