{
  "type": "Feature",
  "properties": {
    "iso:country":"DE",
    "sg:address":"Ernst-Bergmann-Str. 10",
    "sg:city":"Neustadt",
    "sg:phone":"+49 9568/2196",
    "sg:postcode":"96465",
    "sg:province":"Bayern",
    "wof:name":"Ulrich Bieberbach Architekt",
    "wof:placetype":"venue"
},
  "geometry": {"coordinates":[11.124176,50.319511],"type":"Point"}
}