{
  "type": "Feature",
  "properties": {
    "iso:country":"DE",
    "sg:address":"Niederbergheimer Str. 52",
    "sg:city":"Soest",
    "sg:phone":"+49 2921/73590",
    "sg:postcode":"59494",
    "sg:province":"Nordrhein-Westfalen",
    "wof:name":"Edeka-markt Buschk\u00fchle",
    "wof:placetype":"venue"
},
  "geometry": {"coordinates":[8.1209669113,51.562702179],"type":"Point"}
}