{
  "type": "Feature",
  "properties": {
    "iso:country":"DE",
    "sg:address":"Bahnhofstr. 10",
    "sg:city":"Kamen",
    "sg:phone":"+49 2307/967138",
    "sg:postcode":"59174",
    "sg:province":"Nordrhein-Westfalen",
    "wof:name":"Volksbank Kamen-werne Eg",
    "wof:placetype":"venue"
},
  "geometry": {"coordinates":[7.664124012,51.5903511047],"type":"Point"}
}