{
  "type": "Feature",
  "properties": {
    "iso:country":"DE",
    "sg:address":"Rudolf-Breitscheid-Str. 25",
    "sg:city":"Hohen Neuendorf",
    "sg:phone":"+49 3303/402346",
    "sg:postcode":"16540",
    "sg:province":"Brandenburg",
    "wof:name":"Wirtshaus An Der Niederheide Inh. Karin Benecke",
    "wof:placetype":"venue"
},
  "geometry": {"coordinates":[13.2671394348,52.6811485291],"type":"Point"}
}