{
  "type": "Feature",
  "properties": {
    "iso:country":"DE",
    "sg:address":"Seepromenade 8",
    "sg:city":"Strausberg",
    "sg:postcode":"15344",
    "sg:province":"Brandenburg",
    "wof:name":"Horst Baldasus",
    "wof:placetype":"venue"
},
  "geometry": {"coordinates":[13.884248,52.59148],"type":"Point"}
}