{
  "type": "Feature",
  "properties": {
    "iso:country":"DE",
    "sg:address":"Am Torhaus 4",
    "sg:city":"Lohr",
    "sg:phone":"+49 9352/3618",
    "sg:postcode":"97816",
    "sg:province":"Bayern",
    "wof:name":"Italia Ristorante Rexroth-st\u00fcbchen",
    "wof:placetype":"venue"
},
  "geometry": {"coordinates":[9.5689992905,49.9958953857],"type":"Point"}
}