{
  "type": "Feature",
  "properties": {
    "iso:country":"DE",
    "sg:address":"Biedermannstr. 9",
    "sg:city":"Leipzig",
    "sg:phone":"+49 341/305910",
    "sg:postcode":"04277",
    "sg:province":"Sachsen",
    "wof:name":"Dr. Martin Sch\u00f6nleber & Heinz-friedr. Sch\u00f6nleber Kg",
    "wof:placetype":"venue"
},
  "geometry": {"coordinates":[12.3751440048,51.308467865],"type":"Point"}
}