{
  "type": "Feature",
  "properties": {
    "iso:country":"DE",
    "sg:address":"Am Rathaus 2",
    "sg:city":"Minden",
    "sg:postcode":"32423",
    "sg:province":"Nordrhein-Westfalen",
    "wof:name":"A & C Verwaltungs- Und Gesch\u00e4ftsf\u00fchrungsges. Mbh",
    "wof:placetype":"venue"
},
  "geometry": {"coordinates":[8.918766,52.289761],"type":"Point"}
}