{
  "type": "Feature",
  "properties": {
    "iso:country":"DE",
    "sg:address":"Brahmsallee 50",
    "sg:city":"Hamburg",
    "sg:phone":"+49 40/442165",
    "sg:postcode":"20144",
    "sg:province":"Hamburg",
    "wof:name":"Duwe-tv Fernsehproduktion",
    "wof:placetype":"venue"
},
  "geometry": {"coordinates":[9.9821243286,53.577003479],"type":"Point"}
}