{
  "type": "Feature",
  "properties": {
    "iso:country":"DE",
    "sg:address":"An der M\u00fchle 16",
    "sg:city":"Hummeltal",
    "sg:phone":"+49 9201/79425",
    "sg:postcode":"95503",
    "sg:province":"Bayern",
    "wof:name":"Seidel-schleifservice Gmbh",
    "wof:placetype":"venue"
},
  "geometry": {"coordinates":[11.512736,49.893318],"type":"Point"}
}