{
  "type": "Feature",
  "properties": {
    "iso:country":"DE",
    "sg:address":"Kastanienallee 4",
    "sg:city":"Gotha",
    "sg:phone":"+49 3621/52313",
    "sg:postcode":"99867",
    "sg:province":"Th\u00fcringen",
    "wof:name":"Pro Aqua Ges. F\u00fcr Ausr\u00fcstungs- Ger\u00e4te Des Umweltschutzes Mbh",
    "wof:placetype":"venue"
},
  "geometry": {"coordinates":[10.710287,50.949436],"type":"Point"}
}