{
  "type": "Feature",
  "properties": {
    "iso:country":"DE",
    "sg:address":"Postfach 4172",
    "sg:city":"Bruchsal",
    "sg:postcode":"76625",
    "sg:province":"Baden-W\u00fcrttemberg",
    "wof:name":"Plag & Fehrenbach Datenerfassung",
    "wof:placetype":"venue"
},
  "geometry": {"coordinates":[8.5977,49.12579],"type":"Point"}
}