{
  "type": "Feature",
  "properties": {
    "iso:country":"DE",
    "sg:address":"Reyherstr. 6",
    "sg:city":"Gotha",
    "sg:phone":"+49 3621/401941",
    "sg:postcode":"99867",
    "sg:province":"Th\u00fcringen",
    "wof:name":"Matthias Hey",
    "wof:placetype":"venue"
},
  "geometry": {"coordinates":[10.7163963318,50.9431610107],"type":"Point"}
}