{
  "type": "Feature",
  "properties": {
    "iso:country":"DE",
    "sg:address":"Konzendorfer Str. 1",
    "sg:city":"D\u00fcren",
    "sg:phone":"+49 2421/67433",
    "sg:postcode":"52355",
    "sg:province":"Nordrhein-Westfalen",
    "wof:name":"Franz-josef Jacobs",
    "wof:placetype":"venue"
},
  "geometry": {"coordinates":[6.421153,50.810978],"type":"Point"}
}