{
  "type": "Feature",
  "properties": {
    "iso:country":"DE",
    "sg:address":"Im \u00d6hler 2",
    "sg:city":"Bestwig",
    "sg:phone":"+49 2904/6162",
    "sg:postcode":"59909",
    "sg:province":"Nordrhein-Westfalen",
    "wof:name":"Urban Schwei\u00dftechnik Gmbh",
    "wof:placetype":"venue"
},
  "geometry": {"coordinates":[8.3540029526,51.3539733887],"type":"Point"}
}