{
  "type": "Feature",
  "properties": {
    "iso:country":"DE",
    "sg:address":"J\u00fctlandring 15",
    "sg:city":"Kiel",
    "sg:phone":"+49 431/523700",
    "sg:postcode":"24109",
    "sg:province":"Schleswig-Holstein",
    "wof:name":"Adolf Hauschild",
    "wof:placetype":"venue"
},
  "geometry": {"coordinates":[10.051289,54.314407],"type":"Point"}
}