{
  "type": "Feature",
  "properties": {
    "iso:country":"DE",
    "sg:address":"Jader Str. 60",
    "sg:city":"Jade",
    "sg:phone":"+49 4454/8188",
    "sg:postcode":"26349",
    "sg:province":"Niedersachsen",
    "wof:name":"A. Kirchhoff",
    "wof:placetype":"venue"
},
  "geometry": {"coordinates":[8.2476320267,53.3481483459],"type":"Point"}
}