{
  "type": "Feature",
  "properties": {
    "iso:country":"DE",
    "sg:address":"Dessauer Allee 18",
    "sg:city":"Wolfen",
    "sg:phone":"+49 3494/368293",
    "sg:postcode":"06766",
    "sg:province":"Sachsen-Anhalt",
    "wof:name":"Tgs Computer.de",
    "wof:placetype":"venue"
},
  "geometry": {"coordinates":[12.264808,51.686035],"type":"Point"}
}