{
  "type": "Feature",
  "properties": {
    "iso:country":"DE",
    "sg:address":"Hauptstr. 9",
    "sg:city":"Handorf",
    "sg:phone":"+49 4133/7585",
    "sg:postcode":"21447",
    "sg:province":"Niedersachsen",
    "wof:name":"Antike Wandteller Margitte Marquardt",
    "wof:placetype":"venue"
},
  "geometry": {"coordinates":[10.3433408737,53.3468055725],"type":"Point"}
}