{
  "type": "Feature",
  "properties": {
    "iso:country":"DE",
    "sg:address":"Rote Erde 4",
    "sg:city":"M\u00fcnster",
    "sg:phone":"+49 251/714335",
    "sg:postcode":"48163",
    "sg:province":"Nordrhein-Westfalen",
    "wof:name":"Efh Entwicklungs- Und Konstruktionsgesellschaft F\u00fcr",
    "wof:placetype":"venue"
},
  "geometry": {"coordinates":[7.5705070496,51.9288978577],"type":"Point"}
}