{
  "type": "Feature",
  "properties": {
    "iso:country":"DE",
    "sg:address":"Mittlerer Hasenpfad 50",
    "sg:city":"Frankfurt",
    "sg:phone":"+49 69/624153",
    "sg:postcode":"60598",
    "sg:province":"Hessen",
    "wof:name":"Harald Schmidtke Architekt",
    "wof:placetype":"venue"
},
  "geometry": {"coordinates":[8.683946,50.093784],"type":"Point"}
}