{
  "type": "Feature",
  "properties": {
    "iso:country":"DE",
    "sg:address":"Grindelallee 24",
    "sg:city":"Hamburg",
    "sg:phone":"+49 40/4105593",
    "sg:postcode":"20146",
    "sg:province":"Hamburg",
    "wof:name":"Galerie Lapislazuli",
    "wof:placetype":"venue"
},
  "geometry": {"coordinates":[9.983658,53.565029],"type":"Point"}
}