{
  "type": "Feature",
  "properties": {
    "iso:country":"DE",
    "sg:address":"Biberbachstr. 9",
    "sg:city":"Augsburg",
    "sg:phone":"+49 821/41030",
    "sg:postcode":"86154",
    "sg:province":"Bayern",
    "wof:name":"Zeuna-st\u00c4rker Gmbh & Co. Kg",
    "wof:placetype":"venue"
},
  "geometry": {"coordinates":[10.877228,48.402069],"type":"Point"}
}