{
  "type": "Feature",
  "properties": {
    "iso:country":"DE",
    "sg:address":"Weinbergstr. 7",
    "sg:city":"Ockfen",
    "sg:phone":"+49 6581/3128",
    "sg:postcode":"54441",
    "sg:province":"Rheinland-Pfalz",
    "wof:name":"Martin Schuster Architekt",
    "wof:placetype":"venue"
},
  "geometry": {"coordinates":[6.5890030861,49.6230545044],"type":"Point"}
}