{
  "type": "Feature",
  "properties": {
    "iso:country":"DE",
    "sg:address":"Allee der Kosmonauten 131",
    "sg:city":"Berlin",
    "sg:phone":"+49 30/5436083",
    "sg:postcode":"12681",
    "sg:province":"Berlin",
    "wof:name":"Muskelkater",
    "wof:placetype":"venue"
},
  "geometry": {"coordinates":[13.5472803116,52.5300292969],"type":"Point"}
}