{
  "type": "Feature",
  "properties": {
    "iso:country":"DE",
    "sg:address":"R\u00f6merstr.48",
    "sg:city":"Schwabm\u00fcnchen",
    "sg:phone":"+49 8232/9594518",
    "sg:postcode":"86830",
    "sg:province":"Bayern",
    "wof:name":"B\u00f6rsensoftware ! B\u00f6rsenerfolg Live Erleben !",
    "wof:placetype":"venue"
},
  "geometry": {"coordinates":[10.755773,48.191429],"type":"Point"}
}