{
  "type": "Feature",
  "properties": {
    "iso:country":"DE",
    "sg:address":"Rugoweg 6-8",
    "sg:city":"Hasbergen",
    "sg:phone":"+49 5405/96161",
    "sg:postcode":"49205",
    "sg:province":"Niedersachsen",
    "wof:name":"Tk Pharma-trade Handelsgesellschaft Mbh",
    "wof:placetype":"venue"
},
  "geometry": {"coordinates":[7.9579701424,52.2595787048],"type":"Point"}
}