{
  "type": "Feature",
  "properties": {
    "iso:country":"DE",
    "sg:address":"Beim Br\u00fcnnele 5",
    "sg:city":"Schorndorf",
    "sg:phone":"+49 7181/22730",
    "sg:postcode":"73614",
    "sg:province":"Baden-W\u00fcrttemberg",
    "wof:name":"Maxx",
    "wof:placetype":"venue"
},
  "geometry": {"coordinates":[9.5279350281,48.8047065735],"type":"Point"}
}