{
  "type": "Feature",
  "properties": {
    "iso:country":"DE",
    "sg:address":"Stromeyerstr. 27",
    "sg:city":"Weiler-Simmerberg",
    "sg:phone":"+49 8387/466",
    "sg:postcode":"88171",
    "sg:province":"Bayern",
    "wof:name":"Weinstube Sonnenhof",
    "wof:placetype":"venue"
},
  "geometry": {"coordinates":[9.9127206802,47.5807495117],"type":"Point"}
}