{
  "type": "Feature",
  "properties": {
    "iso:country":"DE",
    "sg:address":"Zerzabelshofer Hauptstr. 52",
    "sg:city":"N\u00fcrnberg",
    "sg:phone":"+49 911/409304",
    "sg:postcode":"90480",
    "sg:province":"Bayern",
    "wof:name":"G. Liebel",
    "wof:placetype":"venue"
},
  "geometry": {"coordinates":[11.1267747879,49.4442977905],"type":"Point"}
}