{
  "type": "Feature",
  "properties": {
    "iso:country":"DE",
    "sg:address":"Schulstr. 2",
    "sg:city":"Monzelfeld",
    "sg:phone":"+49 6531/2774",
    "sg:postcode":"54472",
    "sg:province":"Rheinland-Pfalz",
    "wof:name":"Michael Und Simone Grasnick",
    "wof:placetype":"venue"
},
  "geometry": {"coordinates":[7.074474,49.889484],"type":"Point"}
}