{
  "type": "Feature",
  "properties": {
    "iso:country":"DE",
    "sg:address":"Hauptstr. 35",
    "sg:city":"Kreuzau",
    "sg:phone":"+49 2422/1315",
    "sg:postcode":"52372",
    "sg:province":"Nordrhein-Westfalen",
    "wof:name":"Atelier Vermeegen",
    "wof:placetype":"venue"
},
  "geometry": {"coordinates":[6.48823,50.747108],"type":"Point"}
}