{
  "type": "Feature",
  "properties": {
    "iso:country":"DE",
    "sg:address":"Ringstr. 76",
    "sg:city":"Alpen",
    "sg:phone":"+49 2802/2833",
    "sg:postcode":"46519",
    "sg:province":"Nordrhein-Westfalen",
    "wof:name":"Rudolf Engenhorst",
    "wof:placetype":"venue"
},
  "geometry": {"coordinates":[6.5294971466,51.6168556213],"type":"Point"}
}