{
  "type": "Feature",
  "properties": {
    "iso:country":"DE",
    "sg:address":"Neugel\u00e4ndstr.",
    "sg:city":"Saarbr\u00fccken",
    "sg:postcode":"66117",
    "sg:province":"Saarland",
    "wof:name":"Messegesellschaft Halle Mbh",
    "wof:placetype":"venue"
},
  "geometry": {"coordinates":[6.98715,49.235065],"type":"Point"}
}