{
  "type": "Feature",
  "properties": {
    "iso:country":"DE",
    "sg:address":"An der Spreeschanze 6-8",
    "sg:city":"Berlin",
    "sg:phone":"+49 30/338990",
    "sg:postcode":"13599",
    "sg:province":"Berlin",
    "wof:name":"Wall Ag",
    "wof:placetype":"venue"
},
  "geometry": {"coordinates":[13.213494,52.538029],"type":"Point"}
}