{
  "type": "Feature",
  "properties": {
    "iso:country":"DE",
    "sg:address":"Am Poggenbach 25",
    "sg:city":"Wettringen",
    "sg:phone":"+49 2557/98730",
    "sg:postcode":"48493",
    "sg:province":"Nordrhein-Westfalen",
    "wof:name":"Ultra-data Unternehmensberatungs Gmbh",
    "wof:placetype":"venue"
},
  "geometry": {"coordinates":[7.306719,52.205269],"type":"Point"}
}