{
  "type": "Feature",
  "properties": {
    "iso:country":"DE",
    "sg:address":"G\u00f6rlitzer Str. 11",
    "sg:city":"Dresden",
    "sg:phone":"+49 351/8048656",
    "sg:postcode":"01099",
    "sg:province":"Sachsen",
    "wof:name":"Ralf Lunau Rechtsanwalt",
    "wof:placetype":"venue"
},
  "geometry": {"coordinates":[13.7539825439,51.0669822693],"type":"Point"}
}