{
  "type": "Feature",
  "properties": {
    "iso:country":"DE",
    "sg:address":"Sulinger Str. 1",
    "sg:city":"Siedenburg",
    "sg:postcode":"27254",
    "sg:province":"Niedersachsen",
    "wof:name":"Baumschule Husmann E. K.",
    "wof:placetype":"venue"
},
  "geometry": {"coordinates":[8.932523,52.69479],"type":"Point"}
}