{
  "type": "Feature",
  "properties": {
    "iso:country":"DE",
    "sg:address":"Tannenweg 21",
    "sg:city":"Altenholz",
    "sg:phone":"+49 431/321124",
    "sg:postcode":"24161",
    "sg:province":"Schleswig-Holstein",
    "wof:name":"Vera Frfr. Von Hammerstein Graphologin",
    "wof:placetype":"venue"
},
  "geometry": {"coordinates":[10.1301736832,54.4087333679],"type":"Point"}
}