{
  "type": "Feature",
  "properties": {
    "iso:country":"DE",
    "sg:address":"Feldmochinger Str. 79",
    "sg:city":"M\u00fcnchen",
    "sg:phone":"+49 89/1492439",
    "sg:postcode":"80993",
    "sg:province":"Bayern",
    "wof:name":"B. K\u00fchmstedt",
    "wof:placetype":"venue"
},
  "geometry": {"coordinates":[11.5201330185,48.1891708374],"type":"Point"}
}