{
  "type": "Feature",
  "properties": {
    "iso:country":"DE",
    "sg:address":"Rellinghauser Str. 276",
    "sg:city":"Essen",
    "sg:phone":"+49 201/250084",
    "sg:postcode":"45136",
    "sg:province":"Nordrhein-Westfalen",
    "wof:name":"S\u00fcd-apotheke",
    "wof:placetype":"venue"
},
  "geometry": {"coordinates":[7.032802,51.436493],"type":"Point"}
}