{
  "type": "Feature",
  "properties": {
    "iso:country":"DE",
    "sg:address":"Ringstr. 15",
    "sg:city":"Nordheim",
    "sg:phone":"+49 7133/15072",
    "sg:postcode":"74226",
    "sg:province":"Baden-W\u00fcrttemberg",
    "wof:name":"Brako Brandschutz Und Korrosionsschutz Gmbh",
    "wof:placetype":"venue"
},
  "geometry": {"coordinates":[9.1319284439,49.1099319458],"type":"Point"}
}