{
  "type": "Feature",
  "properties": {
    "iso:country":"DE",
    "sg:address":"S\u00fcderstr. 44",
    "sg:city":"Borkum",
    "sg:phone":"+49 4922/1695",
    "sg:postcode":"26757",
    "sg:province":"Niedersachsen",
    "wof:name":"Pension Haus Weber",
    "wof:placetype":"venue"
},
  "geometry": {"coordinates":[6.6683678627,53.5832824707],"type":"Point"}
}