{
  "type": "Feature",
  "properties": {
    "iso:country":"DE",
    "sg:address":"Saumstr. 9",
    "sg:city":"M\u00f6nchengladbach",
    "sg:phone":"+49 2161/26583",
    "sg:postcode":"41063",
    "sg:province":"Nordrhein-Westfalen",
    "wof:name":"Alois Spinnler",
    "wof:placetype":"venue"
},
  "geometry": {"coordinates":[6.448889,51.213779],"type":"Point"}
}