{
  "type": "Feature",
  "properties": {
    "iso:country":"DE",
    "sg:address":"Lachgartenweg 9",
    "sg:city":"Pappenheim",
    "sg:phone":"+49 9143/501",
    "sg:postcode":"91788",
    "sg:province":"Bayern",
    "wof:name":"Heinz Steil Inh. Werner Steil",
    "wof:placetype":"venue"
},
  "geometry": {"coordinates":[10.964709,48.927525],"type":"Point"}
}