{
  "type": "Feature",
  "properties": {
    "iso:country":"DE",
    "sg:address":"L\u00fcdinghauser Str. 15",
    "sg:city":"M\u00fcnster",
    "sg:phone":"+49 251/785259",
    "sg:postcode":"48163",
    "sg:province":"Nordrhein-Westfalen",
    "wof:name":"George Zabe",
    "wof:placetype":"venue"
},
  "geometry": {"coordinates":[7.606205,51.933895],"type":"Point"}
}