{
  "type": "Feature",
  "properties": {
    "iso:country":"DE",
    "sg:address":"Westbahnhofstr. 3a",
    "sg:city":"Jena",
    "sg:phone":"+49 3641/673188",
    "sg:postcode":"07745",
    "sg:province":"Th\u00fcringen",
    "wof:name":"Gtc Tele Communikation",
    "wof:placetype":"venue"
},
  "geometry": {"coordinates":[11.5812959671,50.9253044128],"type":"Point"}
}