{
  "type": "Feature",
  "properties": {
    "iso:country":"DE",
    "sg:address":"Coesfelder Str. 36",
    "sg:city":"D\u00fclmen",
    "sg:phone":"+49 2594/948482",
    "sg:postcode":"48249",
    "sg:province":"Nordrhein-Westfalen",
    "wof:name":"Cafe Bistro Amadeus",
    "wof:placetype":"venue"
},
  "geometry": {"coordinates":[7.2765269279,51.8318977356],"type":"Point"}
}