{
  "type": "Feature",
  "properties": {
    "iso:country":"DE",
    "sg:address":"Freiligrathstr. 21",
    "sg:city":"D\u00fcsseldorf",
    "sg:phone":"+49 211/494078",
    "sg:postcode":"40479",
    "sg:province":"Nordrhein-Westfalen",
    "wof:name":"Hgh Hotel Germania Gmbh",
    "wof:placetype":"venue"
},
  "geometry": {"coordinates":[6.7774920464,51.2343215942],"type":"Point"}
}