{
  "type": "Feature",
  "properties": {
    "iso:country":"DE",
    "sg:address":"W\u00f6llsteiner Str. 8",
    "sg:city":"Gau-Bickelheim",
    "sg:phone":"+49 6701/7003",
    "sg:postcode":"55599",
    "sg:province":"Rheinland-Pfalz",
    "wof:name":"Fuhr & Lenz",
    "wof:placetype":"venue"
},
  "geometry": {"coordinates":[8.0184059143,49.8350486755],"type":"Point"}
}