{
  "type": "Feature",
  "properties": {
    "iso:country":"DE",
    "sg:address":"St.-Michael-Str. 45",
    "sg:city":"Piesport",
    "sg:phone":"+49 6507/2448",
    "sg:postcode":"54498",
    "sg:province":"Rheinland-Pfalz",
    "wof:name":"Johann Longen",
    "wof:placetype":"venue"
},
  "geometry": {"coordinates":[6.9208698273,49.8869934082],"type":"Point"}
}