{
  "type": "Feature",
  "properties": {
    "iso:country":"DE",
    "sg:address":"Jakobstr. 13",
    "sg:city":"Neunkirchen",
    "sg:phone":"+49 6821/21335",
    "sg:postcode":"66538",
    "sg:province":"Saarland",
    "wof:name":"Armin Weckmann Gmbh",
    "wof:placetype":"venue"
},
  "geometry": {"coordinates":[7.177802,49.344414],"type":"Point"}
}