{
  "type": "Feature",
  "properties": {
    "iso:country":"DE",
    "sg:address":"Chemnitzer Str. 48",
    "sg:city":"Frankenberg",
    "sg:phone":"+49 37206/2585",
    "sg:postcode":"09669",
    "sg:province":"Sachsen",
    "wof:name":"H. Klier",
    "wof:placetype":"venue"
},
  "geometry": {"coordinates":[13.0294933319,50.9093093872],"type":"Point"}
}