{
  "type": "Feature",
  "properties": {
    "iso:country":"DE",
    "sg:address":"Karlsplatz 16",
    "sg:city":"Prichsenstadt",
    "sg:phone":"+49 9383/447",
    "sg:postcode":"97357",
    "sg:province":"Bayern",
    "wof:name":"Hans Bausewein",
    "wof:placetype":"venue"
},
  "geometry": {"coordinates":[10.3537874222,49.8174552917],"type":"Point"}
}