{
  "type": "Feature",
  "properties": {
    "iso:country":"DE",
    "sg:address":"Hupfeldstr. 2",
    "sg:city":"Kassel",
    "sg:phone":"+49 561/311312",
    "sg:postcode":"34121",
    "sg:province":"Hessen",
    "wof:name":"Boonoonoos",
    "wof:placetype":"venue"
},
  "geometry": {"coordinates":[9.4607810974,51.3124885559],"type":"Point"}
}