{
  "type": "Feature",
  "properties": {
    "iso:country":"DE",
    "sg:address":"Industriestr. 4",
    "sg:city":"St Katharinen",
    "sg:phone":"+49 2645/971189",
    "sg:postcode":"53562",
    "sg:province":"Rheinland-Pfalz",
    "wof:name":"Hora Software- Gmbh",
    "wof:placetype":"venue"
},
  "geometry": {"coordinates":[7.3540620804,50.5614738464],"type":"Point"}
}