{
  "type": "Feature",
  "properties": {
    "iso:country":"DE",
    "sg:address":"Hauptstr. 18",
    "sg:city":"Hennweiler",
    "sg:phone":"+49 6752/8274",
    "sg:postcode":"55619",
    "sg:province":"Rheinland-Pfalz",
    "wof:name":"Burghard Und Freds Backstuben Gmbh",
    "wof:placetype":"venue"
},
  "geometry": {"coordinates":[7.434963,49.819023],"type":"Point"}
}