{
  "type": "Feature",
  "properties": {
    "iso:country":"DE",
    "sg:address":"Lindenthaler Str. 6",
    "sg:city":"Leipzig",
    "sg:postcode":"04155",
    "sg:province":"Sachsen",
    "wof:name":"N & Z Wohn- Und Gewerbebau Gmbh",
    "wof:placetype":"venue"
},
  "geometry": {"coordinates":[12.36568,51.359901],"type":"Point"}
}