{
  "type": "Feature",
  "properties": {
    "iso:country":"DE",
    "sg:address":"Bahnhofstr. 14 c",
    "sg:city":"Marklkofen",
    "sg:phone":"+49 8732/1263",
    "sg:postcode":"84163",
    "sg:province":"Bayern",
    "wof:name":"Franz X. Leiprecht",
    "wof:placetype":"venue"
},
  "geometry": {"coordinates":[12.555061,48.553059],"type":"Point"}
}