{
  "type": "Feature",
  "properties": {
    "iso:country":"DE",
    "sg:address":"Bettelhecker Str. 128",
    "sg:city":"Sonneberg",
    "sg:phone":"+49 3675/742843",
    "sg:postcode":"96515",
    "sg:province":"Th\u00fcringen",
    "wof:name":"Sgb Sandgewinnung Gmbh & Co. Bettelhecken Kg",
    "wof:placetype":"venue"
},
  "geometry": {"coordinates":[11.1493682861,50.3642501831],"type":"Point"}
}