{
  "type": "Feature",
  "properties": {
    "iso:country":"DE",
    "sg:address":"Kabeler Str. 25",
    "sg:city":"Hagen",
    "sg:postcode":"58099",
    "sg:province":"Nordrhein-Westfalen",
    "wof:name":"Real",
    "wof:placetype":"venue"
},
  "geometry": {"coordinates":[7.4750928879,51.4093284607],"type":"Point"}
}