{
  "type": "Feature",
  "properties": {
    "iso:country":"DE",
    "sg:address":"\u00dcbrigsh\u00e4user Str. 5",
    "sg:city":"Unterm\u00fcnkheim",
    "sg:phone":"+49 7944/2000",
    "sg:postcode":"74547",
    "sg:province":"Baden-W\u00fcrttemberg",
    "wof:name":"Rolf Bullinger",
    "wof:placetype":"venue"
},
  "geometry": {"coordinates":[9.7001075745,49.176399231],"type":"Point"}
}