{
  "type": "Feature",
  "properties": {
    "iso:country":"DE",
    "sg:address":"Fritz-Josephs-Str. 10",
    "sg:city":"Warstein",
    "sg:postcode":"59581",
    "sg:province":"Nordrhein-Westfalen",
    "wof:name":"S & B",
    "wof:placetype":"venue"
},
  "geometry": {"coordinates":[8.3539552689,51.4422988892],"type":"Point"}
}