{
  "type": "Feature",
  "properties": {
    "iso:country":"DE",
    "sg:address":"Kantstr. 162",
    "sg:city":"Berlin",
    "sg:phone":"+49 30/8816497",
    "sg:postcode":"10623",
    "sg:province":"Berlin",
    "wof:name":"Herbert Brosch Steuerberater",
    "wof:placetype":"venue"
},
  "geometry": {"coordinates":[13.3320350647,52.5050926208],"type":"Point"}
}