{
  "type": "Feature",
  "properties": {
    "iso:country":"DE",
    "sg:address":"An der Schule 1",
    "sg:city":"Radolfzell",
    "sg:phone":"+49 7732/2860",
    "sg:postcode":"78315",
    "sg:province":"Baden-W\u00fcrttemberg",
    "wof:name":"Herbert Baumann",
    "wof:placetype":"venue"
},
  "geometry": {"coordinates":[8.9388256073,47.7543029785],"type":"Point"}
}