{
  "type": "Feature",
  "properties": {
    "iso:country":"DE",
    "sg:address":"Kronenburgstr. 2-4",
    "sg:city":"Mannheim",
    "sg:phone":"+49 621/879800",
    "sg:postcode":"68219",
    "sg:province":"Baden-W\u00fcrttemberg",
    "wof:name":"Karg & Pfister",
    "wof:placetype":"venue"
},
  "geometry": {"coordinates":[8.51864,49.442383],"type":"Point"}
}