{
  "type": "Feature",
  "properties": {
    "iso:country":"DE",
    "sg:address":"Im Hangelstein 18",
    "sg:city":"Esslingen",
    "sg:phone":"+49 711/366428",
    "sg:postcode":"73730",
    "sg:province":"Baden-W\u00fcrttemberg",
    "wof:name":"Prof. Walter Wrycza Ingenieur",
    "wof:placetype":"venue"
},
  "geometry": {"coordinates":[9.3603277206,48.7272644043],"type":"Point"}
}