{
  "type": "Feature",
  "properties": {
    "iso:country":"DE",
    "sg:address":"Parchwitzer Str. 234",
    "sg:city":"Berlin",
    "sg:phone":"+49 30/67808531",
    "sg:postcode":"12526",
    "sg:province":"Berlin",
    "wof:name":"Bevd Beh\u00e4lter- Einkaufs, -vertriebs Und",
    "wof:placetype":"venue"
},
  "geometry": {"coordinates":[13.5607595444,52.3971672058],"type":"Point"}
}