{
  "type": "Feature",
  "properties": {
    "iso:country":"DE",
    "sg:address":"Uhlandstr. 98",
    "sg:city":"Berlin",
    "sg:phone":"+49 30/8329698",
    "sg:postcode":"10715",
    "sg:province":"Berlin",
    "wof:name":"Gro\u00dfraumsysteme Gmbh",
    "wof:placetype":"venue"
},
  "geometry": {"coordinates":[13.3221588135,52.4859848022],"type":"Point"}
}