{
  "type": "Feature",
  "properties": {
    "iso:country":"DE",
    "sg:address":"Kur-Mainzer-Platz 6",
    "sg:city":"R\u00fcdershausen",
    "sg:phone":"+49 5529/391",
    "sg:postcode":"37434",
    "sg:province":"Niedersachsen",
    "wof:name":"M. Ahlborn",
    "wof:placetype":"venue"
},
  "geometry": {"coordinates":[10.265658,51.581562],"type":"Point"}
}