{
  "type": "Feature",
  "properties": {
    "iso:country":"DE",
    "sg:address":"Hanauer Str. 85",
    "sg:city":"M\u00fcnchen",
    "sg:phone":"+49 89/1431340",
    "sg:postcode":"80993",
    "sg:province":"Bayern",
    "wof:name":"S. Swoboda Gmbh",
    "wof:placetype":"venue"
},
  "geometry": {"coordinates":[11.5313854218,48.1843223572],"type":"Point"}
}