{
  "type": "Feature",
  "properties": {
    "iso:country":"DE",
    "sg:address":"Birkhuhnweg 18",
    "sg:city":"Reken / Maria - Veen",
    "sg:phone":"+49 2864/882977",
    "sg:postcode":"48734",
    "sg:province":"Nordrhein-Westfalen",
    "wof:name":"J\u00fcrgen Lohm\u00fcller - Auszeichnungstechnik",
    "wof:placetype":"venue"
},
  "geometry": {"coordinates":[-83.741249,43.353901],"type":"Point"}
}