{
  "type": "Feature",
  "properties": {
    "iso:country":"DE",
    "sg:address":"Hermann-L\u00f6ns-Weg 8",
    "sg:city":"Kronberg",
    "sg:postcode":"61476",
    "sg:province":"Hessen",
    "wof:name":"Smart Haus Gmbh",
    "wof:placetype":"venue"
},
  "geometry": {"coordinates":[8.5227870941,50.1886901855],"type":"Point"}
}