{
  "type": "Feature",
  "properties": {
    "iso:country":"DE",
    "sg:address":"Neustr. 18",
    "sg:city":"Euskirchen",
    "sg:phone":"+49 2251/70070",
    "sg:postcode":"53879",
    "sg:province":"Nordrhein-Westfalen",
    "wof:name":"Top-markt Gesellschaft F\u00fcr Sb-warenh\u00e4user Mbh",
    "wof:placetype":"venue"
},
  "geometry": {"coordinates":[6.7889118195,50.6605567932],"type":"Point"}
}