{
  "type": "Feature",
  "properties": {
    "iso:country":"DE",
    "sg:address":"Schlosserstr. 14",
    "sg:city":"Frankfurt",
    "sg:phone":"+49 69/595287",
    "sg:postcode":"60322",
    "sg:province":"Hessen",
    "wof:name":"Franz Christen Architekt",
    "wof:placetype":"venue"
},
  "geometry": {"coordinates":[8.682667,50.131325],"type":"Point"}
}