{
  "type": "Feature",
  "properties": {
    "iso:country":"DE",
    "sg:address":"Drosselweg 5",
    "sg:city":"Bisingen",
    "sg:phone":"+49 7476/1318",
    "sg:postcode":"72406",
    "sg:province":"Baden-W\u00fcrttemberg",
    "wof:name":"Rainer Haag Ingenieur",
    "wof:placetype":"venue"
},
  "geometry": {"coordinates":[8.9119319916,48.3185348511],"type":"Point"}
}