{
  "type": "Feature",
  "properties": {
    "iso:country":"DE",
    "sg:address":"Spitalstr. 8",
    "sg:city":"Heidenheim",
    "sg:phone":"+49 7321/98330",
    "sg:postcode":"89518",
    "sg:province":"Baden-W\u00fcrttemberg",
    "wof:name":"Stiftung Haus Lindenhof",
    "wof:placetype":"venue"
},
  "geometry": {"coordinates":[10.13046,48.68504],"type":"Point"}
}