{
  "type": "Feature",
  "properties": {
    "iso:country":"DE",
    "sg:address":"Luisenstr 17",
    "sg:city":"Buchholz",
    "sg:phone":"+49 2683/967260",
    "sg:postcode":"53567",
    "sg:province":"Rheinland-Pfalz",
    "wof:name":"M\u00fcller K\u00e4lte- Und Klimatechnik Gmbh",
    "wof:placetype":"venue"
},
  "geometry": {"coordinates":[7.4258451462,50.6660194397],"type":"Point"}
}