{
  "type": "Feature",
  "properties": {
    "iso:country":"DE",
    "sg:address":"Steubenstr. 34",
    "sg:city":"Wiesbaden",
    "sg:phone":"+49 611/377648",
    "sg:postcode":"65189",
    "sg:province":"Hessen",
    "wof:name":"Hartmut Miegel",
    "wof:placetype":"venue"
},
  "geometry": {"coordinates":[8.2540588379,50.0821266174],"type":"Point"}
}