{
  "type": "Feature",
  "properties": {
    "iso:country":"DE",
    "sg:address":"Horrenbacher Str. 4",
    "sg:city":"B\u00fchl",
    "sg:phone":"+49 7223/8892",
    "sg:postcode":"77815",
    "sg:province":"Baden-W\u00fcrttemberg",
    "wof:name":"O. Bernhardt",
    "wof:placetype":"venue"
},
  "geometry": {"coordinates":[8.1648302078,48.7156486511],"type":"Point"}
}