{
  "type": "Feature",
  "properties": {
    "iso:country":"DE",
    "sg:address":"Neue Reihe 73",
    "sg:city":"K\u00fchlungsborn",
    "sg:postcode":"18225",
    "sg:province":"Mecklenburg-Vorpommern",
    "wof:name":"Ta Renovierungsges. Mbh",
    "wof:placetype":"venue"
},
  "geometry": {"coordinates":[11.7327,54.146576],"type":"Point"}
}