{
  "type": "Feature",
  "properties": {
    "iso:country":"DE",
    "sg:address":"Wolfenb\u00fctteler Str. 21",
    "sg:city":"Magdeburg",
    "sg:phone":"+49 391/6224256",
    "sg:postcode":"39112",
    "sg:province":"Sachsen-Anhalt",
    "wof:name":"Drogerie Gold Inh. Monika Gold",
    "wof:placetype":"venue"
},
  "geometry": {"coordinates":[11.60078,52.116596],"type":"Point"}
}