{
  "type": "Feature",
  "properties": {
    "iso:country":"DE",
    "sg:address":"Lindenstr. 69",
    "sg:city":"Annaberg-Buchholz",
    "sg:phone":"+49 3733/24140",
    "sg:postcode":"09456",
    "sg:province":"Sachsen",
    "wof:name":"Wein-bierkeller Wolpertinger",
    "wof:placetype":"venue"
},
  "geometry": {"coordinates":[13.0103998184,50.5780830383],"type":"Point"}
}