{
  "type": "Feature",
  "properties": {
    "iso:country":"DE",
    "sg:address":"Stra\u00dfe der DSF 6",
    "sg:city":"Wernshausen",
    "sg:phone":"+49 36848/20523",
    "sg:postcode":"98590",
    "sg:province":"Th\u00fcringen",
    "wof:name":"Wolfgang Fleischer",
    "wof:placetype":"venue"
},
  "geometry": {"coordinates":[10.3525238037,50.7242584229],"type":"Point"}
}