{
  "type": "Feature",
  "properties": {
    "iso:country":"DE",
    "sg:address":"\u00d6denburger Str. 66",
    "sg:city":"Darmstadt",
    "sg:phone":"+49 6151/315815",
    "sg:postcode":"64295",
    "sg:province":"Hessen",
    "wof:name":"Heinrich Und Ursula Sch\u00e4fer",
    "wof:placetype":"venue"
},
  "geometry": {"coordinates":[8.6220321655,49.84532547],"type":"Point"}
}