{
  "type": "Feature",
  "properties": {
    "iso:country":"DE",
    "sg:address":"Dingst\u00e4tte 47",
    "sg:city":"Pinneberg",
    "sg:phone":"+49 4101/22086",
    "sg:postcode":"25421",
    "sg:province":"Schleswig-Holstein",
    "wof:name":"Paul Fenske & S\u00f6hne",
    "wof:placetype":"venue"
},
  "geometry": {"coordinates":[9.7935934067,53.6616172791],"type":"Point"}
}