{
  "type": "Feature",
  "properties": {
    "iso:country":"DE",
    "sg:address":"Wiesenthalstr. 34",
    "sg:city":"Freising",
    "sg:postcode":"85356",
    "sg:province":"Bayern",
    "wof:name":"Alpha Logistics E. K.",
    "wof:placetype":"venue"
},
  "geometry": {"coordinates":[11.7601003647,48.4102554321],"type":"Point"}
}