{
  "type": "Feature",
  "properties": {
    "iso:country":"DE",
    "sg:address":"Friedensstra\u00dfe 82",
    "sg:city":"Schleife",
    "sg:phone":"+49 35773/70442",
    "sg:postcode":"02959",
    "sg:province":"Sachsen",
    "wof:name":"Ihs Schleife",
    "wof:placetype":"venue"
},
  "geometry": {"coordinates":[14.535171,51.54203],"type":"Point"}
}