{
  "type": "Feature",
  "properties": {
    "iso:country":"DE",
    "sg:address":"Horemansstr. 6",
    "sg:city":"Ismaning",
    "sg:phone":"+49 89/969253",
    "sg:postcode":"85737",
    "sg:province":"Bayern",
    "wof:name":"Werner Schardt Rechtsanwalt",
    "wof:placetype":"venue"
},
  "geometry": {"coordinates":[11.6672172546,48.2175750732],"type":"Point"}
}