{
  "type": "Feature",
  "properties": {
    "iso:country":"DE",
    "sg:address":"Kellerstr. 5",
    "sg:city":"Murnau",
    "sg:phone":"+49 8841/9411",
    "sg:postcode":"82418",
    "sg:province":"Bayern",
    "wof:name":"W. Tichelkamp",
    "wof:placetype":"venue"
},
  "geometry": {"coordinates":[11.19557,47.680531],"type":"Point"}
}