{
  "type": "Feature",
  "properties": {
    "iso:country":"DE",
    "sg:address":"M\u00fchlenreiher Weg 12",
    "sg:city":"Hemmoor",
    "sg:phone":"+49 4771/3912",
    "sg:postcode":"21745",
    "sg:province":"Niedersachsen",
    "wof:name":"Wilhelm Kahrs",
    "wof:placetype":"venue"
},
  "geometry": {"coordinates":[9.180164,53.663734],"type":"Point"}
}