{
  "type": "Feature",
  "properties": {
    "iso:country":"DE",
    "sg:address":"Dorheimer Str. 13",
    "sg:city":"Neuental",
    "sg:phone":"+49 6693/372",
    "sg:postcode":"34599",
    "sg:province":"Hessen",
    "wof:name":"Johann Kremser",
    "wof:placetype":"venue"
},
  "geometry": {"coordinates":[9.230689,50.977661],"type":"Point"}
}