{
  "type": "Feature",
  "properties": {
    "iso:country":"DE",
    "sg:address":"Ramsbacher Str. 9",
    "sg:city":"Schw\u00e4bisch Hall",
    "sg:phone":"+49 7907/1360",
    "sg:postcode":"74523",
    "sg:province":"Baden-W\u00fcrttemberg",
    "wof:name":"Dieter Vogt",
    "wof:placetype":"venue"
},
  "geometry": {"coordinates":[9.812128,49.126759],"type":"Point"}
}