{
  "type": "Feature",
  "properties": {
    "iso:country":"DE",
    "sg:address":"Bahnhofstr. 17",
    "sg:city":"Markdorf",
    "sg:phone":"+49 7544/741744",
    "sg:postcode":"88677",
    "sg:province":"Baden-W\u00fcrttemberg",
    "wof:name":"Obstgrossmarkt Markdorf Widemann & Sp\u00e4th Gmbh & Co.",
    "wof:placetype":"venue"
},
  "geometry": {"coordinates":[9.389228,47.717785],"type":"Point"}
}