{
  "type": "Feature",
  "properties": {
    "iso:country":"DE",
    "sg:address":"Bramfelder Str. 110a",
    "sg:city":"Hamburg",
    "sg:postcode":"22305",
    "sg:province":"Hamburg",
    "wof:name":"Woltmann Reisen Gmbh",
    "wof:placetype":"venue"
},
  "geometry": {"coordinates":[10.0537996292,53.5895767212],"type":"Point"}
}