{
  "type": "Feature",
  "properties": {
    "iso:country":"DE",
    "sg:address":"Wartestr. 13",
    "sg:city":"Gransee",
    "sg:phone":"+49 3306/213232",
    "sg:postcode":"16775",
    "sg:province":"Brandenburg",
    "wof:name":"U. Bauer",
    "wof:placetype":"venue"
},
  "geometry": {"coordinates":[13.1497812271,53.0048675537],"type":"Point"}
}