{
  "type": "Feature",
  "properties": {
    "iso:country":"DE",
    "sg:address":"Kendelstr. 6",
    "sg:city":"Kleve",
    "sg:phone":"+49 2821/26620",
    "sg:postcode":"47533",
    "sg:province":"Nordrhein-Westfalen",
    "wof:name":"Dr. Klaus Dirk Hasche Tierarzt",
    "wof:placetype":"venue"
},
  "geometry": {"coordinates":[6.1046791077,51.7793655396],"type":"Point"}
}