{
  "type": "Feature",
  "properties": {
    "iso:country":"DE",
    "sg:address":"Pattenhofen",
    "sg:city":"Burgthann",
    "sg:phone":"+49 9183/3393",
    "sg:postcode":"90559",
    "sg:province":"Bayern",
    "wof:name":"J. Reisl\u00f6hner Ingenieur",
    "wof:placetype":"venue"
},
  "geometry": {"coordinates":[11.3018102646,49.3589782715],"type":"Point"}
}