{
  "type": "Feature",
  "properties": {
    "iso:country":"DE",
    "sg:address":"Breyeller Str. 66a",
    "sg:city":"Nettetal",
    "sg:phone":"+49 2153/4170",
    "sg:postcode":"41334",
    "sg:province":"Nordrhein-Westfalen",
    "wof:name":"A. Beck Und S. Hillebrand",
    "wof:placetype":"venue"
},
  "geometry": {"coordinates":[6.2702817917,51.3040313721],"type":"Point"}
}