{
  "type": "Feature",
  "properties": {
    "iso:country":"DE",
    "sg:address":"Heggrabenstr. 3",
    "sg:city":"Wettenberg",
    "sg:postcode":"35435",
    "sg:province":"Hessen",
    "wof:name":"Car Fleet Service Gmbh",
    "wof:placetype":"venue"
},
  "geometry": {"coordinates":[8.6388,50.629593],"type":"Point"}
}