{
  "type": "Feature",
  "properties": {
    "iso:country":"DE",
    "sg:address":"M\u00fchlenstr. 77",
    "sg:city":"Berlin",
    "sg:phone":"+49 30/4852240",
    "sg:postcode":"13187",
    "sg:province":"Berlin",
    "wof:name":"Pieper Und Partner",
    "wof:placetype":"venue"
},
  "geometry": {"coordinates":[13.405769,52.5667],"type":"Point"}
}