{
  "type": "Feature",
  "properties": {
    "iso:country":"DE",
    "sg:address":"Auf dem Garten 33",
    "sg:city":"Karlshausen",
    "sg:phone":"+49 6564/960515",
    "sg:postcode":"54673",
    "sg:province":"Rheinland-Pfalz",
    "wof:name":"Metallbau Karlshausen Gmbh",
    "wof:placetype":"venue"
},
  "geometry": {"coordinates":[6.21812,50.017262],"type":"Point"}
}