{
  "type": "Feature",
  "properties": {
    "iso:country":"DE",
    "sg:address":"M\u00fcnchner Str. 44",
    "sg:city":"Isen",
    "sg:phone":"+49 8083/261",
    "sg:postcode":"84424",
    "sg:province":"Bayern",
    "wof:name":"Georg Schnellinger",
    "wof:placetype":"venue"
},
  "geometry": {"coordinates":[12.055336,48.209976],"type":"Point"}
}