{
  "type": "Feature",
  "properties": {
    "iso:country":"DE",
    "sg:address":"Friedrich-Wienke-Str. 12",
    "sg:city":"Lage",
    "sg:phone":"+49 5232/3256",
    "sg:postcode":"32791",
    "sg:province":"Nordrhein-Westfalen",
    "wof:name":"Gerhard Schmidt Vermietungen Und Verpachtungen E. K.",
    "wof:placetype":"venue"
},
  "geometry": {"coordinates":[8.8096017838,51.9846382141],"type":"Point"}
}