{
  "type": "Feature",
  "properties": {
    "iso:country":"DE",
    "sg:address":"An der Radrunde 151",
    "sg:city":"N\u00fcrnberg",
    "sg:phone":"+49 911/882544",
    "sg:postcode":"90455",
    "sg:province":"Bayern",
    "wof:name":"G. Gugel",
    "wof:placetype":"venue"
},
  "geometry": {"coordinates":[11.081666,49.371414],"type":"Point"}
}