{
  "type": "Feature",
  "properties": {
    "iso:country":"DE",
    "sg:address":"Angerstr. 25",
    "sg:city":"T\u00f6ttelst\u00e4dt",
    "sg:postcode":"99100",
    "sg:province":"Th\u00fcringen",
    "wof:name":"Agrar Bienstedt Gmbh",
    "wof:placetype":"venue"
},
  "geometry": {"coordinates":[10.82781,51.043186],"type":"Point"}
}