{
  "type": "Feature",
  "properties": {
    "iso:country":"DE",
    "sg:address":"Fritz-Ribot-Str. 12",
    "sg:city":"Schwabach",
    "sg:phone":"+49 9122/77025",
    "sg:postcode":"91126",
    "sg:province":"Bayern",
    "wof:name":"Wilhelm Mazuvczak",
    "wof:placetype":"venue"
},
  "geometry": {"coordinates":[11.023686409,49.3356895447],"type":"Point"}
}