{
  "type": "Feature",
  "properties": {
    "iso:country":"DE",
    "sg:address":"Feldbergstr. 15",
    "sg:city":"Grenzach-Wyhlen",
    "sg:phone":"+49 7624/4522",
    "sg:postcode":"79639",
    "sg:province":"Baden-W\u00fcrttemberg",
    "wof:name":"Emil Motsch",
    "wof:placetype":"venue"
},
  "geometry": {"coordinates":[7.705994,47.569115],"type":"Point"}
}