{
  "type": "Feature",
  "properties": {
    "iso:country":"DE",
    "sg:address":"Wackenbrucher Str. 126",
    "sg:city":"Wesel",
    "sg:phone":"+49 281/50827",
    "sg:postcode":"46485",
    "sg:province":"Nordrhein-Westfalen",
    "wof:name":"Heinrich Gilhaus",
    "wof:placetype":"venue"
},
  "geometry": {"coordinates":[6.641659,51.655941],"type":"Point"}
}