{
  "type": "Feature",
  "properties": {
    "iso:country":"DE",
    "sg:address":"August-Bebel-Str. 45",
    "sg:city":"Burg",
    "sg:phone":"+49 3921/983586",
    "sg:postcode":"39288",
    "sg:province":"Sachsen-Anhalt",
    "wof:name":"Com Data Systems Gmbh",
    "wof:placetype":"venue"
},
  "geometry": {"coordinates":[11.8334531784,52.2661323547],"type":"Point"}
}