{
  "type": "Feature",
  "properties": {
    "iso:country":"DE",
    "sg:address":"Bleichestr. 16",
    "sg:city":"Burg",
    "sg:phone":"+49 35603/620",
    "sg:postcode":"03096",
    "sg:province":"Brandenburg",
    "wof:name":"Hotel Zur Bleiche Heinrich Michael Clausing",
    "wof:placetype":"venue"
},
  "geometry": {"coordinates":[14.1262512207,51.8435592651],"type":"Point"}
}