{
  "type": "Feature",
  "properties": {
    "iso:country":"DE",
    "sg:address":"M\u00fcnzgasse 30",
    "sg:city":"Konstanz",
    "sg:phone":"+49 7531/22278",
    "sg:postcode":"78462",
    "sg:province":"Baden-W\u00fcrttemberg",
    "wof:name":"Bettenhaus Hilngrainer Gmbh",
    "wof:placetype":"venue"
},
  "geometry": {"coordinates":[9.174202919,47.6613616943],"type":"Point"}
}