{
  "type": "Feature",
  "properties": {
    "iso:country":"DE",
    "sg:address":"Plackenweg 26",
    "sg:city":"Hameln",
    "sg:phone":"+49 5151/8551",
    "sg:postcode":"31787",
    "sg:province":"Niedersachsen",
    "wof:name":"Ak Autohaus Kr\u00fcger Gmbh",
    "wof:placetype":"venue"
},
  "geometry": {"coordinates":[9.392537117,52.1557769775],"type":"Point"}
}