{
  "type": "Feature",
  "properties": {
    "iso:country":"DE",
    "sg:address":"Rudolf-Breitscheid-Str. 4",
    "sg:city":"Masserberg",
    "sg:postcode":"98666",
    "sg:province":"Th\u00fcringen",
    "wof:name":"Gie\u00df\u00fcbel",
    "wof:placetype":"venue"
},
  "geometry": {"coordinates":[10.9256954193,50.5051231384],"type":"Point"}
}