{
  "type": "Feature",
  "properties": {
    "iso:country":"DE",
    "sg:address":"Schlo\u00dfstr. 1",
    "sg:city":"Waldheim",
    "sg:phone":"+49 34327/92380",
    "sg:postcode":"04736",
    "sg:province":"Sachsen",
    "wof:name":"Christine Eckardt",
    "wof:placetype":"venue"
},
  "geometry": {"coordinates":[13.0249862671,51.0734596252],"type":"Point"}
}