{
  "type": "Feature",
  "properties": {
    "iso:country":"DE",
    "sg:address":"Eichenweg 5",
    "sg:city":"Ruppichteroth",
    "sg:phone":"+49 2295/5348",
    "sg:postcode":"53809",
    "sg:province":"Nordrhein-Westfalen",
    "wof:name":"Peter Hohn",
    "wof:placetype":"venue"
},
  "geometry": {"coordinates":[7.47109,50.84206],"type":"Point"}
}