{
  "type": "Feature",
  "properties": {
    "iso:country":"DE",
    "sg:address":"Ahornstr. 15",
    "sg:city":"Reit im Winkl",
    "sg:phone":"+49 8640/8365",
    "sg:postcode":"83242",
    "sg:province":"Bayern",
    "wof:name":"G\u00e4stehaus S. Und M. Rauch",
    "wof:placetype":"venue"
},
  "geometry": {"coordinates":[12.4618730545,47.675983429],"type":"Point"}
}