{
  "type": "Feature",
  "properties": {
    "iso:country":"DE",
    "sg:address":"Marktstr. 21",
    "sg:city":"Erfurt",
    "sg:postcode":"99084",
    "sg:province":"Th\u00fcringen",
    "wof:name":"Kinder- Und Jugendbibliothek",
    "wof:placetype":"venue"
},
  "geometry": {"coordinates":[11.025813,50.977554],"type":"Point"}
}