{
  "type": "Feature",
  "properties": {
    "iso:country":"DE",
    "sg:address":"An dem Bach 1",
    "sg:city":"Gem\u00fcnden",
    "sg:phone":"+49 6453/7567",
    "sg:postcode":"35285",
    "sg:province":"Hessen",
    "wof:name":"H. Linker",
    "wof:placetype":"venue"
},
  "geometry": {"coordinates":[8.995387,50.950802],"type":"Point"}
}