{
  "type": "Feature",
  "properties": {
    "iso:country":"DE",
    "sg:city":"m\u00fcnster",
    "sg:postcode":"48157",
    "sg:province":"Nordrhein-Westfalen",
    "wof:name":"Ruben Wojtecki",
    "wof:placetype":"venue"
},
  "geometry": {"coordinates":[7.699018,51.988331],"type":"Point"}
}