{
  "type": "Feature",
  "properties": {
    "iso:country":"DE",
    "sg:address":"Goethestr. 2a",
    "sg:city":"Gifhorn",
    "sg:phone":"+49 5371/94680",
    "sg:postcode":"38518",
    "sg:province":"Niedersachsen",
    "wof:name":"Four Seasons Mode Gmbh",
    "wof:placetype":"venue"
},
  "geometry": {"coordinates":[10.540587,52.48214],"type":"Point"}
}