{
  "type": "Feature",
  "properties": {
    "iso:country":"DE",
    "sg:address":"Osterholderstr.10",
    "sg:city":"Appen",
    "sg:phone":"+49 4101/553888",
    "sg:postcode":"25482",
    "sg:province":"Schleswig-Holstein",
    "wof:name":"Autohandel Rerinck",
    "wof:placetype":"venue"
},
  "geometry": {"coordinates":[9.7547426224,53.6600265503],"type":"Point"}
}