{
  "type": "Feature",
  "properties": {
    "iso:country":"DE",
    "sg:address":"Elisabethstr. 42",
    "sg:city":"Essen",
    "sg:phone":"+49 201/210192",
    "sg:postcode":"45139",
    "sg:province":"Nordrhein-Westfalen",
    "wof:name":"M. Gassmann",
    "wof:placetype":"venue"
},
  "geometry": {"coordinates":[7.040053,51.463078],"type":"Point"}
}