{
  "type": "Feature",
  "properties": {
    "iso:country":"DE",
    "sg:address":"Kr\u00f6b 32",
    "sg:city":"Schwangau",
    "sg:phone":"+49 8362/8253",
    "sg:postcode":"87645",
    "sg:province":"Bayern",
    "wof:name":"Maria Isele Hebamme",
    "wof:placetype":"venue"
},
  "geometry": {"coordinates":[10.73421,47.580601],"type":"Point"}
}