{
  "type": "Feature",
  "properties": {
    "iso:country":"DE",
    "sg:address":"Horster Str. 376",
    "sg:city":"Bottrop",
    "sg:phone":"+49 2041/43372",
    "sg:postcode":"46240",
    "sg:province":"Nordrhein-Westfalen",
    "wof:name":"Eiscafe Giancarlo",
    "wof:placetype":"venue"
},
  "geometry": {"coordinates":[6.98591,51.536201],"type":"Point"}
}