{
  "type": "Feature",
  "properties": {
    "iso:country":"DE",
    "sg:address":"Katteweg 23 b",
    "sg:city":"Berlin",
    "sg:phone":"+49 30/80403040",
    "sg:postcode":"14129",
    "sg:province":"Berlin",
    "wof:name":"Pr-werbung Urban Gmbh",
    "wof:placetype":"venue"
},
  "geometry": {"coordinates":[13.2013902664,52.4189147949],"type":"Point"}
}