{
  "type": "Feature",
  "properties": {
    "iso:country":"DE",
    "sg:address":"Charlottenburger Ufer 1",
    "sg:city":"Berlin",
    "sg:phone":"+49 30/3482406",
    "sg:postcode":"10587",
    "sg:province":"Berlin",
    "wof:name":"Alcatraz",
    "wof:placetype":"venue"
},
  "geometry": {"coordinates":[13.300133,52.521152],"type":"Point"}
}