{
  "type": "Feature",
  "properties": {
    "iso:country":"DE",
    "sg:address":"Stuttgarter Str. 102",
    "sg:city":"Leonberg",
    "sg:phone":"+49 7152/28287",
    "sg:postcode":"71229",
    "sg:province":"Baden-W\u00fcrttemberg",
    "wof:name":"Edmund Schmitt Wohnbau- Gmbh",
    "wof:placetype":"venue"
},
  "geometry": {"coordinates":[9.02732,48.801929],"type":"Point"}
}