{
  "type": "Feature",
  "properties": {
    "iso:country":"DE",
    "sg:address":"Max-Ernst-Str. 7",
    "sg:city":"Bonn",
    "sg:postcode":"53125",
    "sg:province":"Nordrhein-Westfalen",
    "wof:name":"Bonnova Gesellschaft F\u00fcr Immobilienentwicklung",
    "wof:placetype":"venue"
},
  "geometry": {"coordinates":[7.062534,50.688309],"type":"Point"}
}