{
  "type": "Feature",
  "properties": {
    "iso:country":"DE",
    "sg:address":"Planetenfeldstr. 100",
    "sg:city":"Dortmund",
    "sg:phone":"+49 231/610060",
    "sg:postcode":"44379",
    "sg:province":"Nordrhein-Westfalen",
    "wof:name":"Muus Gmbh",
    "wof:placetype":"venue"
},
  "geometry": {"coordinates":[7.394235,51.503754],"type":"Point"}
}