{
  "type": "Feature",
  "properties": {
    "iso:country":"DE",
    "sg:address":"Hanekamp 16",
    "sg:city":"Brakel",
    "sg:phone":"+49 5272/9923",
    "sg:postcode":"33034",
    "sg:province":"Nordrhein-Westfalen",
    "wof:name":"Engelbert Schr\u00f6der Inh. Barbara Potente E. K.",
    "wof:placetype":"venue"
},
  "geometry": {"coordinates":[9.181796,51.715935],"type":"Point"}
}