{
  "type": "Feature",
  "properties": {
    "iso:country":"DE",
    "sg:address":"Pietschstr. 417",
    "sg:city":"Wietzen",
    "sg:postcode":"31613",
    "sg:province":"Niedersachsen",
    "wof:name":"Poseidon Haustechnik Gmbh",
    "wof:placetype":"venue"
},
  "geometry": {"coordinates":[9.0814380646,52.7004051208],"type":"Point"}
}