{
  "type": "Feature",
  "properties": {
    "iso:country":"DE",
    "sg:address":"Argelanderstr. 141",
    "sg:city":"Bonn",
    "sg:phone":"+49 228/264201",
    "sg:postcode":"53115",
    "sg:province":"Nordrhein-Westfalen",
    "wof:name":"M. Dahm",
    "wof:placetype":"venue"
},
  "geometry": {"coordinates":[7.098715,50.722111],"type":"Point"}
}