{
  "type": "Feature",
  "properties": {
    "iso:country":"DE",
    "sg:address":"Johnsatz 22",
    "sg:city":"Rottenburg",
    "sg:phone":"+49 7472/5544",
    "sg:postcode":"72108",
    "sg:province":"Baden-W\u00fcrttemberg",
    "wof:name":"H. Mauch",
    "wof:placetype":"venue"
},
  "geometry": {"coordinates":[8.9254770279,48.448890686],"type":"Point"}
}