{
  "type": "Feature",
  "properties": {
    "iso:country":"DE",
    "sg:address":"Wendefeld 1",
    "sg:city":"Gransee",
    "sg:phone":"+49 3306/28631",
    "sg:postcode":"16775",
    "sg:province":"Brandenburg",
    "wof:name":"Pension Gutssch\u00e4nke",
    "wof:placetype":"venue"
},
  "geometry": {"coordinates":[13.1583948135,53.0353431702],"type":"Point"}
}