{
  "type": "Feature",
  "properties": {
    "iso:country":"DE",
    "sg:address":"Kurf\u00fcrstenstr. 14",
    "sg:city":"Berlin",
    "sg:phone":"+49 30/2628021",
    "sg:postcode":"10785",
    "sg:province":"Berlin",
    "wof:name":"Institut F\u00fcr \u00f6kologisches Recycling",
    "wof:placetype":"venue"
},
  "geometry": {"coordinates":[13.3668003082,52.4993095398],"type":"Point"}
}