{
  "type": "Feature",
  "properties": {
    "iso:country":"DE",
    "sg:address":"Beyenburger Freiheit 15",
    "sg:city":"Wuppertal",
    "sg:phone":"+49 202/612438",
    "sg:postcode":"42399",
    "sg:province":"Nordrhein-Westfalen",
    "wof:name":"I. Rondorf",
    "wof:placetype":"venue"
},
  "geometry": {"coordinates":[7.298471,51.24979],"type":"Point"}
}