{
  "type": "Feature",
  "properties": {
    "iso:country":"DE",
    "sg:address":"Johannistal 6",
    "sg:city":"Eisenach",
    "sg:phone":"+49 3691/203508",
    "sg:postcode":"99817",
    "sg:province":"Th\u00fcringen",
    "wof:name":"Dr. Fritz B\u00fchner Tierarzt",
    "wof:placetype":"venue"
},
  "geometry": {"coordinates":[10.3237485886,50.9644432068],"type":"Point"}
}