{
  "type": "Feature",
  "properties": {
    "iso:country":"DE",
    "sg:address":"Hirtenweg 73",
    "sg:city":"Erlenbach",
    "sg:phone":"+49 9372/944977",
    "sg:postcode":"63906",
    "sg:province":"Bayern",
    "wof:name":"Arndt Gartendesign",
    "wof:placetype":"venue"
},
  "geometry": {"coordinates":[9.145261,49.810677],"type":"Point"}
}