{
  "type": "Feature",
  "properties": {
    "iso:country":"DE",
    "sg:address":"Markt 6",
    "sg:city":"Sch\u00f6ningen",
    "sg:phone":"+49 5352/909231",
    "sg:postcode":"38364",
    "sg:province":"Niedersachsen",
    "wof:name":"Gastst\u00e4tte Spucknapf",
    "wof:placetype":"venue"
},
  "geometry": {"coordinates":[10.9681615829,52.1396064758],"type":"Point"}
}