{
  "type": "Feature",
  "properties": {
    "iso:country":"DE",
    "sg:address":"Auf dem Graben 2",
    "sg:city":"Recklinghausen",
    "sg:phone":"+49 2361/582880",
    "sg:postcode":"45657",
    "sg:province":"Nordrhein-Westfalen",
    "wof:name":"Bmv Bistumszeitung M\u00fcnster Verlagsges. Mbh",
    "wof:placetype":"venue"
},
  "geometry": {"coordinates":[7.1947832108,51.6120529175],"type":"Point"}
}