{
  "type": "Feature",
  "properties": {
    "iso:country":"DE",
    "sg:address":"Kiebitzweg 36",
    "sg:city":"Weyhe",
    "sg:phone":"+49 421/804049",
    "sg:postcode":"28844",
    "sg:province":"Niedersachsen",
    "wof:name":"W. Eggers",
    "wof:placetype":"venue"
},
  "geometry": {"coordinates":[8.789691,52.963734],"type":"Point"}
}