{
  "type": "Feature",
  "properties": {
    "iso:country":"DE",
    "sg:address":"Bischof-Kaller-Str. 3",
    "sg:city":"K\u00f6nigstein",
    "sg:postcode":"61462",
    "sg:province":"Hessen",
    "wof:name":"Haus Der Begegnung Betriebsges. Mbh",
    "wof:placetype":"venue"
},
  "geometry": {"coordinates":[8.473320961,50.178653717],"type":"Point"}
}