{
  "type": "Feature",
  "properties": {
    "iso:country":"DE",
    "sg:address":"Sternstr. 78",
    "sg:city":"Bonn",
    "sg:phone":"+49 228/638104",
    "sg:postcode":"53111",
    "sg:province":"Nordrhein-Westfalen",
    "wof:name":"Zum Gequetschten Gastst\u00e4tten-gmbh",
    "wof:placetype":"venue"
},
  "geometry": {"coordinates":[7.0984492302,50.7358322144],"type":"Point"}
}