{
  "type": "Feature",
  "properties": {
    "iso:country":"DE",
    "sg:address":"Austr. 7",
    "sg:city":"Redwitz",
    "sg:phone":"+49 9264/9650",
    "sg:postcode":"96257",
    "sg:province":"Bayern",
    "wof:name":"Rainer Niechziol",
    "wof:placetype":"venue"
},
  "geometry": {"coordinates":[11.2143392563,50.1959037781],"type":"Point"}
}