{
  "type": "Feature",
  "properties": {
    "iso:country":"DE",
    "sg:address":"Augsburger Str. 34",
    "sg:city":"Augsburg",
    "sg:phone":"+49 821/2290907",
    "sg:postcode":"86157",
    "sg:province":"Bayern",
    "wof:name":"D2 Shop Pfersee",
    "wof:placetype":"venue"
},
  "geometry": {"coordinates":[10.8695411682,48.3626708984],"type":"Point"}
}