{
  "type": "Feature",
  "properties": {
    "iso:country":"DE",
    "sg:address":"Am Unteranger 1",
    "sg:city":"Thierhaupten",
    "sg:phone":"+49 821/217950",
    "sg:postcode":"86672",
    "sg:province":"Bayern",
    "wof:name":"M\u00fcscha Alu-gu\u00df Gmbh & Co. Kg",
    "wof:placetype":"venue"
},
  "geometry": {"coordinates":[10.9029893875,48.5694580078],"type":"Point"}
}