{
  "type": "Feature",
  "properties": {
    "iso:country":"DE",
    "sg:address":"Markt 21",
    "sg:city":"Jena",
    "sg:phone":"+49 3641/489538",
    "sg:postcode":"07743",
    "sg:province":"Th\u00fcringen",
    "wof:name":"E-plus Shop",
    "wof:placetype":"venue"
},
  "geometry": {"coordinates":[11.5882463455,50.928440094],"type":"Point"}
}