{
  "type": "Feature",
  "properties": {
    "iso:country":"DE",
    "sg:address":"Lorcher Str. 55/2",
    "sg:city":"Schw\u00e4bisch Gm\u00fcnd",
    "sg:phone":"+49 7171/2917",
    "sg:postcode":"73525",
    "sg:province":"Baden-W\u00fcrttemberg",
    "wof:name":"Otto Kaiser",
    "wof:placetype":"venue"
},
  "geometry": {"coordinates":[9.7832813263,48.7976875305],"type":"Point"}
}