{
  "type": "Feature",
  "properties": {
    "iso:country":"DE",
    "sg:address":"Oberdie\u00dfemer Str. 16",
    "sg:city":"Krefeld",
    "sg:phone":"+49 2151/310863",
    "sg:postcode":"47805",
    "sg:province":"Nordrhein-Westfalen",
    "wof:name":"Wilhelm Beckmann Autolackiererei Gmbh",
    "wof:placetype":"venue"
},
  "geometry": {"coordinates":[6.580928,51.328568],"type":"Point"}
}