{
  "type": "Feature",
  "properties": {
    "iso:country":"DE",
    "sg:address":"Blarerplatz 2",
    "sg:city":"Esslingen",
    "sg:phone":"+49 711/357626",
    "sg:postcode":"73728",
    "sg:province":"Baden-W\u00fcrttemberg",
    "wof:name":"Cafe Am Blarer",
    "wof:placetype":"venue"
},
  "geometry": {"coordinates":[9.310057,48.740978],"type":"Point"}
}