{
  "type": "Feature",
  "properties": {
    "iso:country":"DE",
    "sg:address":"Hauptstr. 11",
    "sg:city":"Bruckberg",
    "sg:phone":"+49 8765/479",
    "sg:postcode":"84079",
    "sg:province":"Bayern",
    "wof:name":"Josef Wernthaler",
    "wof:placetype":"venue"
},
  "geometry": {"coordinates":[12.0345830917,48.5264015198],"type":"Point"}
}