{
  "type": "Feature",
  "properties": {
    "iso:country":"DE",
    "sg:address":"Schallershofer Str. 421/2",
    "sg:city":"Erlangen",
    "sg:phone":"+49 9131/41508",
    "sg:postcode":"91056",
    "sg:province":"Bayern",
    "wof:name":"Condi-markt",
    "wof:placetype":"venue"
},
  "geometry": {"coordinates":[10.9624032974,49.5892753601],"type":"Point"}
}