{
  "type": "Feature",
  "properties": {
    "iso:country":"DE",
    "sg:address":"K\u00e4strich 9",
    "sg:city":"Alzey",
    "sg:phone":"+49 6731/42902",
    "sg:postcode":"55232",
    "sg:province":"Rheinland-Pfalz",
    "wof:name":"Joachim Huber",
    "wof:placetype":"venue"
},
  "geometry": {"coordinates":[8.1157808304,49.7459640503],"type":"Point"}
}