{
  "type": "Feature",
  "properties": {
    "iso:country":"DE",
    "sg:address":"Karlsplatz 15-19",
    "sg:city":"Eisenach",
    "sg:phone":"+49 3691/624609",
    "sg:postcode":"99817",
    "sg:province":"Th\u00fcringen",
    "wof:name":"Volksbank Und Raiffeisenbank E. G.",
    "wof:placetype":"venue"
},
  "geometry": {"coordinates":[10.324977,50.976002],"type":"Point"}
}