{
  "type": "Feature",
  "properties": {
    "iso:country":"DE",
    "sg:address":"Gerbersruhstr. 31",
    "sg:city":"Wiesloch",
    "sg:phone":"+49 6222/4190",
    "sg:postcode":"69168",
    "sg:province":"Baden-W\u00fcrttemberg",
    "wof:name":"Martha Sp\u00e4th",
    "wof:placetype":"venue"
},
  "geometry": {"coordinates":[8.697470665,49.2959938049],"type":"Point"}
}