{
  "type": "Feature",
  "properties": {
    "iso:country":"DE",
    "sg:address":"Rottweiler Str. 4-1",
    "sg:city":"Villingendorf",
    "sg:phone":"+49 741/31616",
    "sg:postcode":"78667",
    "sg:province":"Baden-W\u00fcrttemberg",
    "wof:name":"Richard Engesser",
    "wof:placetype":"venue"
},
  "geometry": {"coordinates":[8.5901079178,48.2018165588],"type":"Point"}
}