{
  "type": "Feature",
  "properties": {
    "iso:country":"DE",
    "sg:address":"Babstadter Str. 23",
    "sg:city":"Bad Rappenau",
    "sg:phone":"+49 7264/2100",
    "sg:postcode":"74906",
    "sg:province":"Baden-W\u00fcrttemberg",
    "wof:name":"Hotel-restaurant Dominikaner",
    "wof:placetype":"venue"
},
  "geometry": {"coordinates":[9.0992746353,49.2397079468],"type":"Point"}
}