{
  "type": "Feature",
  "properties": {
    "iso:country":"DE",
    "sg:address":"Langelsheimer Str. 18",
    "sg:city":"Goslar",
    "sg:phone":"+49 5321/81226",
    "sg:postcode":"38644",
    "sg:province":"Niedersachsen",
    "wof:name":"Ernst-august Lindenberg",
    "wof:placetype":"venue"
},
  "geometry": {"coordinates":[10.380058,51.951046],"type":"Point"}
}