{
  "type": "Feature",
  "properties": {
    "iso:country":"DE",
    "sg:address":"Lindauer Str. 27",
    "sg:city":"Katlenburg-Lindau",
    "sg:phone":"+49 5556/357",
    "sg:postcode":"37191",
    "sg:province":"Niedersachsen",
    "wof:name":"Karl-heinz Fahlbusch",
    "wof:placetype":"venue"
},
  "geometry": {"coordinates":[10.10322,51.636948],"type":"Point"}
}