{
  "type": "Feature",
  "properties": {
    "iso:country":"DE",
    "sg:address":"Friedrichstr. 24",
    "sg:city":"Wendlingen",
    "sg:phone":"+49 7024/929600",
    "sg:postcode":"73240",
    "sg:province":"Baden-W\u00fcrttemberg",
    "wof:name":"Dietmut Ferrari \u00dcbersetzer",
    "wof:placetype":"venue"
},
  "geometry": {"coordinates":[9.384199,48.67186],"type":"Point"}
}