{
  "type": "Feature",
  "properties": {
    "iso:country":"DE",
    "sg:address":"H\u00f6nower Str. 145",
    "sg:city":"Berlin",
    "sg:postcode":"12623",
    "sg:province":"Berlin",
    "wof:name":"Emwebe Transfer Und Handels Gmbh",
    "wof:placetype":"venue"
},
  "geometry": {"coordinates":[13.6144065857,52.5172653198],"type":"Point"}
}