{
  "type": "Feature",
  "properties": {
    "iso:country":"DE",
    "sg:address":"\u00dcberkinger Str. 4",
    "sg:city":"Geislingen",
    "sg:phone":"+49 7331/65358",
    "sg:postcode":"73312",
    "sg:province":"Baden-W\u00fcrttemberg",
    "wof:name":"C. Kosmider",
    "wof:placetype":"venue"
},
  "geometry": {"coordinates":[9.826606,48.624603],"type":"Point"}
}