{
  "type": "Feature",
  "properties": {
    "iso:country":"DE",
    "sg:address":"Ziegeleiweg 3",
    "sg:city":"Gl\u00fccksburg",
    "sg:phone":"+49 4631/8690",
    "sg:postcode":"24960",
    "sg:province":"Schleswig-Holstein",
    "wof:name":"Reinhard Bartsch Heilpraktiker",
    "wof:placetype":"venue"
},
  "geometry": {"coordinates":[9.5968093872,54.8680381775],"type":"Point"}
}