{
  "type": "Feature",
  "properties": {
    "iso:country":"DE",
    "sg:address":"W\u00f6bbensredder 32",
    "sg:city":"Malente",
    "sg:phone":"+49 4523/3378",
    "sg:postcode":"23714",
    "sg:province":"Schleswig-Holstein",
    "wof:name":"Ursula Bela Hebamme",
    "wof:placetype":"venue"
},
  "geometry": {"coordinates":[10.57011,54.167259],"type":"Point"}
}