{
  "type": "Feature",
  "properties": {
    "iso:country":"DE",
    "sg:address":"Ottostr. 10",
    "sg:city":"M\u00fcnchen",
    "sg:phone":"+49 89/596872",
    "sg:postcode":"80333",
    "sg:province":"Bayern",
    "wof:name":"Kunstauktionshaus Sch\u00f6ninger & Co.",
    "wof:placetype":"venue"
},
  "geometry": {"coordinates":[11.568406105,48.1419258118],"type":"Point"}
}