{
  "type": "Feature",
  "properties": {
    "iso:country":"DE",
    "sg:address":"Burgstr. 5",
    "sg:city":"Hann. M\u00fcnden",
    "sg:phone":"+49 5541/6163",
    "sg:postcode":"34346",
    "sg:province":"Niedersachsen",
    "wof:name":"Kaminstube",
    "wof:placetype":"venue"
},
  "geometry": {"coordinates":[9.6533555984,51.4174537659],"type":"Point"}
}