{
  "type": "Feature",
  "properties": {
    "iso:country":"DE",
    "sg:address":"Peter-Jakob-Busch-Str. 13",
    "sg:city":"Kempen",
    "sg:phone":"+49 2152/20330",
    "sg:postcode":"47906",
    "sg:province":"Nordrhein-Westfalen",
    "wof:name":"Gsw Schwabe Fertigung Gmbh",
    "wof:placetype":"venue"
},
  "geometry": {"coordinates":[6.442543,51.367157],"type":"Point"}
}