{
  "type": "Feature",
  "properties": {
    "iso:country":"DE",
    "sg:address":"Hermelinstr. 36",
    "sg:city":"Aalen",
    "sg:phone":"+49 7361/45629",
    "sg:postcode":"73434",
    "sg:province":"Baden-W\u00fcrttemberg",
    "wof:name":"Gastst\u00e4tte Reinhold Kurz",
    "wof:placetype":"venue"
},
  "geometry": {"coordinates":[10.0541944504,48.8459358215],"type":"Point"}
}