{
  "type": "Feature",
  "properties": {
    "iso:country":"DE",
    "sg:address":"Wilhelm-Leuschner-Str. 1",
    "sg:city":"Worms",
    "sg:phone":"+49 6241/23706",
    "sg:postcode":"67547",
    "sg:province":"Rheinland-Pfalz",
    "wof:name":"City-optik Weber + Puder Inh. Wolfgang Schantz",
    "wof:placetype":"venue"
},
  "geometry": {"coordinates":[8.360226,49.632725],"type":"Point"}
}