{
  "type": "Feature",
  "properties": {
    "iso:country":"DE",
    "sg:address":"Hauptstr. 57",
    "sg:city":"Briedel",
    "sg:phone":"+49 6542/41184",
    "sg:postcode":"56867",
    "sg:province":"Rheinland-Pfalz",
    "wof:name":"Karl H. Steffens Weinanbau",
    "wof:placetype":"venue"
},
  "geometry": {"coordinates":[7.1500530243,50.0208702087],"type":"Point"}
}