{
  "type": "Feature",
  "properties": {
    "iso:country":"DE",
    "sg:address":"Jordanstr. 31",
    "sg:city":"D\u00fcsseldorf",
    "sg:phone":"+49 211/460505",
    "sg:postcode":"40477",
    "sg:province":"Nordrhein-Westfalen",
    "wof:name":"Hans-michael Werner Ingenieur",
    "wof:placetype":"venue"
},
  "geometry": {"coordinates":[6.7916488647,51.24168396],"type":"Point"}
}