{
  "type": "Feature",
  "properties": {
    "iso:country":"DE",
    "sg:address":"Lausitzer Str. 8",
    "sg:city":"Geretsried",
    "sg:phone":"+49 8171/34930",
    "sg:postcode":"82538",
    "sg:province":"Bayern",
    "wof:name":"Byk-gardner Gmbh",
    "wof:placetype":"venue"
},
  "geometry": {"coordinates":[11.4905529022,47.8571357727],"type":"Point"}
}