{
  "type": "Feature",
  "properties": {
    "iso:country":"DE",
    "sg:address":"Tornauer Str. 23",
    "sg:city":"Stendal",
    "sg:phone":"+49 3931/315202",
    "sg:postcode":"39576",
    "sg:province":"Sachsen-Anhalt",
    "wof:name":"K Und N Isoliertechnik Gmbh",
    "wof:placetype":"venue"
},
  "geometry": {"coordinates":[11.825089,52.590843],"type":"Point"}
}