{
  "type": "Feature",
  "properties": {
    "iso:country":"DE",
    "sg:address":"Kantgasse 26",
    "sg:city":"Alsdorf",
    "sg:phone":"+49 2404/22240",
    "sg:postcode":"52477",
    "sg:province":"Nordrhein-Westfalen",
    "wof:name":"Fleu-modellbau",
    "wof:placetype":"venue"
},
  "geometry": {"coordinates":[6.1570181847,50.8804740906],"type":"Point"}
}