{
  "type": "Feature",
  "properties": {
    "iso:country":"DE",
    "sg:address":"Kirchtalstr. 48",
    "sg:city":"Kornwestheim",
    "sg:postcode":"70806",
    "sg:province":"Baden-W\u00fcrttemberg",
    "wof:name":"W. Dr\u00e4ger Hebamme",
    "wof:placetype":"venue"
},
  "geometry": {"coordinates":[9.193046,48.867828],"type":"Point"}
}