{
  "type": "Feature",
  "properties": {
    "iso:country":"DE",
    "sg:address":"Frankfurter Str. 110",
    "sg:city":"Offenbach",
    "sg:phone":"+49 69/822010",
    "sg:postcode":"63067",
    "sg:province":"Hessen",
    "wof:name":"Stefan Demuth Architekturb\u00fcro",
    "wof:placetype":"venue"
},
  "geometry": {"coordinates":[8.751003,50.102863],"type":"Point"}
}