{
  "type": "Feature",
  "properties": {
    "iso:country":"DE",
    "sg:address":"Gr\u00fcner Grund 21",
    "sg:city":"Beelen",
    "sg:postcode":"48361",
    "sg:province":"Nordrhein-Westfalen",
    "wof:name":"Trend House",
    "wof:placetype":"venue"
},
  "geometry": {"coordinates":[8.1211252213,51.9226531982],"type":"Point"}
}