{
  "type": "Feature",
  "properties": {
    "iso:country":"DE",
    "sg:address":"Am Treppchen 2",
    "sg:city":"Steinheim",
    "sg:phone":"+49 5238/216",
    "sg:postcode":"32839",
    "sg:province":"Nordrhein-Westfalen",
    "wof:name":"E. Schmidt",
    "wof:placetype":"venue"
},
  "geometry": {"coordinates":[8.9865016937,51.8262214661],"type":"Point"}
}