{
  "type": "Feature",
  "properties": {
    "iso:country":"DE",
    "sg:address":"Kloppenburger Str. 14",
    "sg:city":"Oyten",
    "sg:phone":"+49 4207/2379",
    "sg:postcode":"28876",
    "sg:province":"Niedersachsen",
    "wof:name":"Hinrich Asendorf",
    "wof:placetype":"venue"
},
  "geometry": {"coordinates":[9.025792,53.053658],"type":"Point"}
}