{
  "type": "Feature",
  "properties": {
    "iso:country":"DE",
    "sg:address":"Richtst\u00e4ttenweg 20",
    "sg:city":"Belm",
    "sg:phone":"+49 5406/7007",
    "sg:postcode":"49191",
    "sg:province":"Niedersachsen",
    "wof:name":"Decor Metall",
    "wof:placetype":"venue"
},
  "geometry": {"coordinates":[8.115096,52.297684],"type":"Point"}
}