{
  "type": "Feature",
  "properties": {
    "iso:country":"DE",
    "sg:address":"Wengertstr. 3",
    "sg:city":"Reutlingen",
    "sg:phone":"+49 7121/493328",
    "sg:postcode":"72766",
    "sg:province":"Baden-W\u00fcrttemberg",
    "wof:name":"Kurt Rist",
    "wof:placetype":"venue"
},
  "geometry": {"coordinates":[9.2264509201,48.5403175354],"type":"Point"}
}