{
  "type": "Feature",
  "properties": {
    "iso:country":"DE",
    "sg:address":"Im Meerfeld 15",
    "sg:city":"Bad Oeynhausen",
    "sg:phone":"+49 5731/3100",
    "sg:postcode":"32547",
    "sg:province":"Nordrhein-Westfalen",
    "wof:name":"Bootcenter Krick Gmbh Handel Und Charter",
    "wof:placetype":"venue"
},
  "geometry": {"coordinates":[8.845892,52.207352],"type":"Point"}
}