{
  "type": "Feature",
  "properties": {
    "iso:country":"DE",
    "sg:address":"Auf der Halloh 1",
    "sg:city":"Stade",
    "sg:postcode":"21684",
    "sg:province":"Niedersachsen",
    "wof:name":"Hafenbetriebs- Und Beteiligungs-gmbh",
    "wof:placetype":"venue"
},
  "geometry": {"coordinates":[9.405785,53.589676],"type":"Point"}
}