{
  "type": "Feature",
  "properties": {
    "iso:country":"DE",
    "sg:address":"Schleifweg 47-53",
    "sg:city":"N\u00fcrnberg",
    "sg:phone":"+49 911/36550",
    "sg:postcode":"90409",
    "sg:province":"Bayern",
    "wof:name":"Arotel Hotelbetriebs Gmbh",
    "wof:placetype":"venue"
},
  "geometry": {"coordinates":[11.0868120193,49.4710617065],"type":"Point"}
}