{
  "type": "Feature",
  "properties": {
    "iso:country":"DE",
    "sg:address":"Brunnenstr. 26",
    "sg:city":"Bad M\u00fcnstereifel",
    "sg:phone":"+49 2253/8292",
    "sg:postcode":"53902",
    "sg:province":"Nordrhein-Westfalen",
    "wof:name":"Gastst\u00e4tte Eckard Wassong",
    "wof:placetype":"venue"
},
  "geometry": {"coordinates":[6.7219572067,50.5486488342],"type":"Point"}
}