{
  "type": "Feature",
  "properties": {
    "iso:country":"DE",
    "sg:address":"Talweg 14",
    "sg:city":"R\u00f6dinghausen",
    "sg:phone":"+49 5746/1245",
    "sg:postcode":"32289",
    "sg:province":"Nordrhein-Westfalen",
    "wof:name":"Wilh. Clamor",
    "wof:placetype":"venue"
},
  "geometry": {"coordinates":[8.508941,52.253754],"type":"Point"}
}