{
  "type": "Feature",
  "properties": {
    "iso:country":"DE",
    "sg:address":"Hackl\u00e4nderweg 29",
    "sg:city":"Berlin",
    "sg:phone":"+49 30/36809950",
    "sg:postcode":"14089",
    "sg:province":"Berlin",
    "wof:name":"Nowatek Ingenieur",
    "wof:placetype":"venue"
},
  "geometry": {"coordinates":[13.1265792847,52.450881958],"type":"Point"}
}