{
  "type": "Feature",
  "properties": {
    "iso:country":"DE",
    "sg:address":"Valencienner Str. 117",
    "sg:city":"D\u00fcren",
    "sg:phone":"+49 2421/61966",
    "sg:postcode":"52355",
    "sg:province":"Nordrhein-Westfalen",
    "wof:name":"Valentin Helmer",
    "wof:placetype":"venue"
},
  "geometry": {"coordinates":[6.4622001648,50.7968711853],"type":"Point"}
}