{
  "type": "Feature",
  "properties": {
    "iso:country":"DE",
    "sg:address":"Paulmannsh\u00f6her Stra\u00dfe 17",
    "sg:city":"L\u00fcdenscheid",
    "sg:phone":"+49 2351",
    "sg:postcode":"58515",
    "sg:province":"Nordrhein-Westfalen",
    "wof:name":"Krankenhaus F\u00fcr Sportverletzte",
    "wof:placetype":"venue"
},
  "geometry": {"coordinates":[7.657396,51.207943],"type":"Point"}
}