{
  "type": "Feature",
  "properties": {
    "iso:country":"DE",
    "sg:address":"Hinterm Eckerkamp 2",
    "sg:city":"L\u00fcder",
    "sg:phone":"+49 5824/2329",
    "sg:postcode":"29394",
    "sg:province":"Niedersachsen",
    "wof:name":"H. Chors Jun.",
    "wof:placetype":"venue"
},
  "geometry": {"coordinates":[10.6669197083,52.8048095703],"type":"Point"}
}