{
  "type": "Feature",
  "properties": {
    "iso:country":"DE",
    "sg:address":"Hackenbroicher Str. 58",
    "sg:city":"K\u00f6ln",
    "sg:phone":"+49 221/781288",
    "sg:postcode":"50769",
    "sg:province":"Nordrhein-Westfalen",
    "wof:name":"Gerd Schmitz Ingenieur",
    "wof:placetype":"venue"
},
  "geometry": {"coordinates":[6.8607549667,51.0650596619],"type":"Point"}
}