{
  "type": "Feature",
  "properties": {
    "iso:country":"DE",
    "sg:address":"Oberstadtstr. 52",
    "sg:city":"Haigerloch",
    "sg:phone":"+49 7474/6363",
    "sg:postcode":"72401",
    "sg:province":"Baden-W\u00fcrttemberg",
    "wof:name":"Obere Apotheke",
    "wof:placetype":"venue"
},
  "geometry": {"coordinates":[8.800812,48.366241],"type":"Point"}
}