{
  "type": "Feature",
  "properties": {
    "iso:country":"DE",
    "sg:address":"Freyel 16",
    "sg:city":"Breitnau",
    "sg:phone":"+49 7652/384",
    "sg:postcode":"79874",
    "sg:province":"Baden-W\u00fcrttemberg",
    "wof:name":"Dietmar Benitz",
    "wof:placetype":"venue"
},
  "geometry": {"coordinates":[8.071211,47.95245],"type":"Point"}
}