{
  "type": "Feature",
  "properties": {
    "iso:country":"DE",
    "sg:address":"Herforder Str. 25",
    "sg:city":"Vlotho",
    "sg:phone":"+49 5733/2470",
    "sg:postcode":"32602",
    "sg:province":"Nordrhein-Westfalen",
    "wof:name":"H. Westhoff",
    "wof:placetype":"venue"
},
  "geometry": {"coordinates":[8.8545875549,52.1652259827],"type":"Point"}
}