{
  "type": "Feature",
  "properties": {
    "iso:country":"DE",
    "sg:address":"Moosacher Str. 26 a",
    "sg:city":"M\u00fcnchen",
    "sg:phone":"+49 89/35651910",
    "sg:postcode":"80809",
    "sg:province":"Bayern",
    "wof:name":"Springbrunnen Textilhandel Beteiligungs Gmbh",
    "wof:placetype":"venue"
},
  "geometry": {"coordinates":[11.557938,48.186653],"type":"Point"}
}