{
  "type": "Feature",
  "properties": {
    "iso:country":"DE",
    "sg:address":"Immelmannstr. 2",
    "sg:city":"Essen",
    "sg:postcode":"45309",
    "sg:province":"Nordrhein-Westfalen",
    "wof:name":"Kath. \u00f6ffentliche Bibliothek St. Elisabeth",
    "wof:placetype":"venue"
},
  "geometry": {"coordinates":[7.062804,51.480469],"type":"Point"}
}