{
  "type": "Feature",
  "properties": {
    "iso:country":"DE",
    "sg:address":"Zanderstr. 5",
    "sg:city":"Bonn",
    "sg:phone":"+49 228/8440",
    "sg:postcode":"53177",
    "sg:province":"Nordrhein-Westfalen",
    "wof:name":"Ivg Immobilienbeteiligungs- Gesellschaft Mbh",
    "wof:placetype":"venue"
},
  "geometry": {"coordinates":[7.162492,50.678307],"type":"Point"}
}