{
  "type": "Feature",
  "properties": {
    "iso:country":"DE",
    "sg:address":"Biggen 12",
    "sg:city":"Attendorn",
    "sg:postcode":"57439",
    "sg:province":"Nordrhein-Westfalen",
    "wof:name":"H\u00fcttemann-wegner Verwaltungs-gmbh",
    "wof:placetype":"venue"
},
  "geometry": {"coordinates":[7.9237341881,51.1315193176],"type":"Point"}
}