{
  "type": "Feature",
  "properties": {
    "iso:country":"DE",
    "sg:address":"Oehleckerring 28",
    "sg:city":"Hamburg",
    "sg:phone":"+49 40/5313067",
    "sg:postcode":"22419",
    "sg:province":"Hamburg",
    "wof:name":"Klaus Poppe Steuerberater",
    "wof:placetype":"venue"
},
  "geometry": {"coordinates":[10.0065689087,53.6631126404],"type":"Point"}
}