{
  "type": "Feature",
  "properties": {
    "iso:country":"DE",
    "sg:address":"Hauptstr. 64",
    "sg:city":"Feucht",
    "sg:phone":"+49 9128/3395",
    "sg:postcode":"90537",
    "sg:province":"Bayern",
    "wof:name":"Evang. B\u00fccherei",
    "wof:placetype":"venue"
},
  "geometry": {"coordinates":[11.213741,49.374249],"type":"Point"}
}