{
  "type": "Feature",
  "properties": {
    "iso:country":"DE",
    "sg:address":"Birkenweg 5",
    "sg:city":"Nittenau",
    "sg:phone":"+49 9436/940777",
    "sg:postcode":"93149",
    "sg:province":"Bayern",
    "wof:name":"Krieger-schmidhuber Gmbh",
    "wof:placetype":"venue"
},
  "geometry": {"coordinates":[12.2734231949,49.2037086487],"type":"Point"}
}