{
  "type": "Feature",
  "properties": {
    "iso:country":"DE",
    "sg:address":"M\u00fcllerstr. 21 POSTFACH 110506",
    "sg:city":"Regensburg",
    "sg:phone":"+49 941/8305240",
    "sg:postcode":"93018",
    "sg:province":"Bayern",
    "wof:name":"Lauf-und Ausdauer-sportverlag E.k.",
    "wof:placetype":"venue"
},
  "geometry": {"coordinates":[12.0943822861,49.0229225159],"type":"Point"}
}