{
  "type": "Feature",
  "properties": {
    "iso:country":"DE",
    "sg:address":"Bannhof 17",
    "sg:city":"Geseke",
    "sg:phone":"+49 2942/574100",
    "sg:postcode":"59590",
    "sg:province":"Nordrhein-Westfalen",
    "wof:name":"Mb Modernes Bauen Gmbh",
    "wof:placetype":"venue"
},
  "geometry": {"coordinates":[8.470827,51.635521],"type":"Point"}
}