{
  "type": "Feature",
  "properties": {
    "iso:country":"DE",
    "sg:address":"Werastr. 25",
    "sg:city":"N\u00fcrtingen",
    "sg:phone":"+49 7022/32218",
    "sg:postcode":"72622",
    "sg:province":"Baden-W\u00fcrttemberg",
    "wof:name":"Ursula Jah",
    "wof:placetype":"venue"
},
  "geometry": {"coordinates":[9.3448038101,48.6231651306],"type":"Point"}
}