{
  "type": "Feature",
  "properties": {
    "iso:country":"DE",
    "sg:address":"Hauptstr. 41",
    "sg:city":"Wallerstein",
    "sg:phone":"+49 9081/7107",
    "sg:postcode":"86757",
    "sg:province":"Bayern",
    "wof:name":"Karl H\u00e4hnlein",
    "wof:placetype":"venue"
},
  "geometry": {"coordinates":[10.4715480804,48.8862113953],"type":"Point"}
}