{
  "type": "Feature",
  "properties": {
    "iso:country":"DE",
    "sg:address":"Trollblumenweg 6-1",
    "sg:city":"Isny",
    "sg:phone":"+49 7562/3733",
    "sg:postcode":"88316",
    "sg:province":"Baden-W\u00fcrttemberg",
    "wof:name":"Lang",
    "wof:placetype":"venue"
},
  "geometry": {"coordinates":[10.0368366241,47.7021636963],"type":"Point"}
}