{
  "type": "Feature",
  "properties": {
    "iso:country":"DE",
    "sg:address":"Lange Str. 101a",
    "sg:city":"Waldkirch",
    "sg:phone":"+49 7681/9346",
    "sg:postcode":"79183",
    "sg:province":"Baden-W\u00fcrttemberg",
    "wof:name":"Aral Tankstelle",
    "wof:placetype":"venue"
},
  "geometry": {"coordinates":[7.9604969025,48.0936164856],"type":"Point"}
}