{
  "type": "Feature",
  "properties": {
    "iso:country":"DE",
    "sg:address":"Pyrnaer Str. 9",
    "sg:city":"K\u00fchren-Burkartshain",
    "sg:phone":"+49 34261/261",
    "sg:postcode":"04808",
    "sg:province":"Sachsen",
    "wof:name":"M. Weyer",
    "wof:placetype":"venue"
},
  "geometry": {"coordinates":[12.791865,51.392357],"type":"Point"}
}