{
  "type": "Feature",
  "properties": {
    "iso:country":"DE",
    "sg:address":"B\u00fchlstr. 16",
    "sg:city":"Tiefenbronn",
    "sg:phone":"+49 7234/980220",
    "sg:postcode":"75233",
    "sg:province":"Baden-W\u00fcrttemberg",
    "wof:name":"Dietger Patalong Verwaltungs Gmbh",
    "wof:placetype":"venue"
},
  "geometry": {"coordinates":[8.821268,48.797329],"type":"Point"}
}