{
  "type": "Feature",
  "properties": {
    "iso:country":"DE",
    "sg:address":"Hauptstr. 23",
    "sg:city":"Hohenberg-Krusemark",
    "sg:phone":"+49 39394/81476",
    "sg:postcode":"39596",
    "sg:province":"Sachsen-Anhalt",
    "wof:name":"Hans-hermann Linke",
    "wof:placetype":"venue"
},
  "geometry": {"coordinates":[11.94746,52.723038],"type":"Point"}
}