{
  "type": "Feature",
  "properties": {
    "iso:country":"DE",
    "sg:address":"Hauptstr. 184",
    "sg:city":"Herne",
    "sg:phone":"+49 2325",
    "sg:postcode":"44652",
    "sg:province":"Nordrhein-Westfalen",
    "wof:name":"Puma Profi Shop",
    "wof:placetype":"venue"
},
  "geometry": {"coordinates":[7.162028,51.525269],"type":"Point"}
}