{
  "type": "Feature",
  "properties": {
    "iso:country":"DE",
    "sg:address":"Burgstr. 30a",
    "sg:city":"Bergisch Gladbach",
    "sg:phone":"+49 2204/62490",
    "sg:postcode":"51427",
    "sg:province":"Nordrhein-Westfalen",
    "wof:name":"Roland Sprenger",
    "wof:placetype":"venue"
},
  "geometry": {"coordinates":[7.1252598763,50.9598426819],"type":"Point"}
}