{
  "type": "Feature",
  "properties": {
    "iso:country":"DE",
    "sg:address":"Mainzer Str. 16 a",
    "sg:city":"M\u00fcnchen",
    "sg:phone":"+49 89/363132",
    "sg:postcode":"80804",
    "sg:province":"Bayern",
    "wof:name":"Hermann Aust Rechtsanwalt",
    "wof:placetype":"venue"
},
  "geometry": {"coordinates":[11.5812425613,48.1684074402],"type":"Point"}
}