{
  "type": "Feature",
  "properties": {
    "iso:country":"DE",
    "sg:address":"Beethovenstr. 2",
    "sg:city":"Schongau",
    "sg:phone":"+49 8861/7580",
    "sg:postcode":"86956",
    "sg:province":"Bayern",
    "wof:name":"Angelika Tiegs",
    "wof:placetype":"venue"
},
  "geometry": {"coordinates":[10.8840646744,47.8132743835],"type":"Point"}
}