{
  "type": "Feature",
  "properties": {
    "iso:country":"DE",
    "sg:address":"Cecilienstr. 13",
    "sg:city":"Saarbr\u00fccken",
    "sg:phone":"+49 681/36501",
    "sg:postcode":"66111",
    "sg:province":"Saarland",
    "wof:name":"Remington",
    "wof:placetype":"venue"
},
  "geometry": {"coordinates":[6.99792099,49.2363052368],"type":"Point"}
}