{
  "type": "Feature",
  "properties": {
    "iso:country":"DE",
    "sg:address":"Talstr. 18",
    "sg:city":"Wissen",
    "sg:phone":"+49 2742/4367",
    "sg:postcode":"57537",
    "sg:province":"Rheinland-Pfalz",
    "wof:name":"St. Hildegard",
    "wof:placetype":"venue"
},
  "geometry": {"coordinates":[7.73094,50.780849],"type":"Point"}
}