{
  "type": "Feature",
  "properties": {
    "iso:country":"DE",
    "sg:address":"Fabrikstr. 11",
    "sg:city":"Plauen",
    "sg:phone":"+49 3741/225276",
    "sg:postcode":"08527",
    "sg:province":"Sachsen",
    "wof:name":"Rolf Gr\u00fcnbeck",
    "wof:placetype":"venue"
},
  "geometry": {"coordinates":[12.13805,50.489803],"type":"Point"}
}