{
  "type": "Feature",
  "properties": {
    "iso:country":"DE",
    "sg:address":"Schlagenweg 2c",
    "sg:city":"G\u00f6ttingen",
    "sg:phone":"+49 551/371808",
    "sg:postcode":"37077",
    "sg:province":"Niedersachsen",
    "wof:name":"He\u00dfmann Ingenieur",
    "wof:placetype":"venue"
},
  "geometry": {"coordinates":[9.9376525879,51.5609474182],"type":"Point"}
}