{
  "type": "Feature",
  "properties": {
    "iso:country":"DE",
    "sg:address":"In der Fl\u00f6te 16",
    "sg:city":"Ahnsen",
    "sg:phone":"+49 5722/84275",
    "sg:postcode":"31708",
    "sg:province":"Niedersachsen",
    "wof:name":"G\u00f6tz Hohmann",
    "wof:placetype":"venue"
},
  "geometry": {"coordinates":[9.091558,52.259205],"type":"Point"}
}