{
  "type": "Feature",
  "properties": {
    "iso:country":"DE",
    "sg:address":"Alter Schulweg 63",
    "sg:city":"Vlotho",
    "sg:phone":"+49 5228/7166",
    "sg:postcode":"32602",
    "sg:province":"Nordrhein-Westfalen",
    "wof:name":"Erich Altemasch",
    "wof:placetype":"venue"
},
  "geometry": {"coordinates":[8.775668,52.144932],"type":"Point"}
}