{
  "type": "Feature",
  "properties": {
    "iso:country":"DE",
    "sg:address":"Oberdorf 25",
    "sg:city":"Traunreut",
    "sg:phone":"+49 8669/86360",
    "sg:postcode":"83301",
    "sg:province":"Bayern",
    "wof:name":"Konrad Anderl Gmbh",
    "wof:placetype":"venue"
},
  "geometry": {"coordinates":[12.5688199997,47.956829071],"type":"Point"}
}