{
  "type": "Feature",
  "properties": {
    "iso:country":"DE",
    "sg:address":"Winkelsgarten 40",
    "sg:city":"Paderborn",
    "sg:phone":"+49 5251/9872",
    "sg:postcode":"33106",
    "sg:province":"Nordrhein-Westfalen",
    "wof:name":"Heinz Keck",
    "wof:placetype":"venue"
},
  "geometry": {"coordinates":[8.6910791397,51.684009552],"type":"Point"}
}