{
  "type": "Feature",
  "properties": {
    "iso:country":"DE",
    "sg:address":"Fredericiastr. 5",
    "sg:city":"Berlin",
    "sg:phone":"+49 30/3023673",
    "sg:postcode":"14059",
    "sg:province":"Berlin",
    "wof:name":"Willy Hoffmann",
    "wof:placetype":"venue"
},
  "geometry": {"coordinates":[13.2827682495,52.5111923218],"type":"Point"}
}