{
  "type": "Feature",
  "properties": {
    "iso:country":"DE",
    "sg:address":"Saargem\u00fcnder Str. 125",
    "sg:city":"Saarbr\u00fccken",
    "sg:phone":"+49 681/851159",
    "sg:postcode":"66119",
    "sg:province":"Saarland",
    "wof:name":"Kramersche-apotheke Inh. Rita Kappel E. Kfr.",
    "wof:placetype":"venue"
},
  "geometry": {"coordinates":[7.013191,49.218746],"type":"Point"}
}