{
  "type": "Feature",
  "properties": {
    "iso:country":"DE",
    "sg:address":"Bahnhofstr. 12",
    "sg:city":"Tholey",
    "sg:phone":"+49 6853/2452",
    "sg:postcode":"66636",
    "sg:province":"Saarland",
    "wof:name":"Kuhn Gmbh",
    "wof:placetype":"venue"
},
  "geometry": {"coordinates":[7.0388188362,49.4860496521],"type":"Point"}
}