{
  "type": "Feature",
  "properties": {
    "iso:country":"DE",
    "sg:address":"In der Finstermail 20",
    "sg:city":"N\u00fcrnberg",
    "sg:phone":"+49 911/501060",
    "sg:postcode":"90482",
    "sg:province":"Bayern",
    "wof:name":"N\u00fcrbau Gmbh",
    "wof:placetype":"venue"
},
  "geometry": {"coordinates":[11.163705,49.462029],"type":"Point"}
}