{
  "type": "Feature",
  "properties": {
    "iso:country":"DE",
    "sg:address":"Freienhagen 13",
    "sg:city":"Melle",
    "sg:phone":"+49 5422/2643",
    "sg:postcode":"49326",
    "sg:province":"Niedersachsen",
    "wof:name":"Aug. Hasemann",
    "wof:placetype":"venue"
},
  "geometry": {"coordinates":[8.272528,52.21151],"type":"Point"}
}