{
  "type": "Feature",
  "properties": {
    "iso:country":"DE",
    "sg:address":"Erikaweg 1",
    "sg:city":"Arnsberg",
    "sg:phone":"+49 2932/24140",
    "sg:postcode":"59755",
    "sg:province":"Nordrhein-Westfalen",
    "wof:name":"Josef Plesser",
    "wof:placetype":"venue"
},
  "geometry": {"coordinates":[7.990727,51.464298],"type":"Point"}
}