{
  "type": "Feature",
  "properties": {
    "iso:country":"DE",
    "sg:address":"Nadorster Str. 50 a",
    "sg:city":"Oldenburg",
    "sg:postcode":"26123",
    "sg:province":"Niedersachsen",
    "wof:name":"Hypofinanznet Gmbh",
    "wof:placetype":"venue"
},
  "geometry": {"coordinates":[8.2169952393,53.1507606506],"type":"Point"}
}