{
  "type": "Feature",
  "properties": {
    "iso:country":"DE",
    "sg:address":"Karolinenstr. 20",
    "sg:city":"Bad Aibling",
    "sg:phone":"+49 8061/2545",
    "sg:postcode":"83043",
    "sg:province":"Bayern",
    "wof:name":"Josef Knabl",
    "wof:placetype":"venue"
},
  "geometry": {"coordinates":[12.006655,47.86338],"type":"Point"}
}