{
  "type": "Feature",
  "properties": {
    "iso:country":"DE",
    "sg:address":"Unterreute 5",
    "sg:city":"Oberreute",
    "sg:phone":"+49 8387/92000",
    "sg:postcode":"88179",
    "sg:province":"Bayern",
    "wof:name":"Privates Mayr-kursanatorium Pankraz",
    "wof:placetype":"venue"
},
  "geometry": {"coordinates":[9.93464,47.565269],"type":"Point"}
}