{
  "type": "Feature",
  "properties": {
    "iso:country":"DE",
    "sg:address":"Kleine Schmiedestr. 6",
    "sg:city":"Stade",
    "sg:phone":"+49 4141/44409",
    "sg:postcode":"21682",
    "sg:province":"Niedersachsen",
    "wof:name":"Apropos",
    "wof:placetype":"venue"
},
  "geometry": {"coordinates":[9.476849556,53.6009635925],"type":"Point"}
}