{
  "type": "Feature",
  "properties": {
    "iso:country":"DE",
    "sg:address":"Kaiserstr. 88",
    "sg:city":"Wetter",
    "sg:phone":"+49 2335/4466",
    "sg:postcode":"58300",
    "sg:province":"Nordrhein-Westfalen",
    "wof:name":"Heribert Kamm",
    "wof:placetype":"venue"
},
  "geometry": {"coordinates":[7.388531,51.385391],"type":"Point"}
}