{
  "type": "Feature",
  "properties": {
    "iso:country":"DE",
    "sg:address":"Neckarstr. 136",
    "sg:city":"Stuttgart",
    "sg:phone":"+49 711/260023",
    "sg:postcode":"70190",
    "sg:province":"Baden-W\u00fcrttemberg",
    "wof:name":"St\u00f6ckach-apotheke",
    "wof:placetype":"venue"
},
  "geometry": {"coordinates":[9.193423,48.787857],"type":"Point"}
}