{
  "type": "Feature",
  "properties": {
    "iso:country":"DE",
    "sg:address":"St.-Benedikt-Str. 6",
    "sg:city":"Tettenweis",
    "sg:phone":"+49 8534/8249",
    "sg:postcode":"94167",
    "sg:province":"Bayern",
    "wof:name":"Ingenieurb\u00fcro Bauer Gmbh",
    "wof:placetype":"venue"
},
  "geometry": {"coordinates":[13.2704582214,48.4389915466],"type":"Point"}
}