{
  "type": "Feature",
  "properties": {
    "iso:country":"DE",
    "sg:address":"Ohrdrufer Str. 63",
    "sg:city":"Geraberg",
    "sg:phone":"+49 3677/790572",
    "sg:postcode":"98716",
    "sg:province":"Th\u00fcringen",
    "wof:name":"Geratal-apotheke",
    "wof:placetype":"venue"
},
  "geometry": {"coordinates":[10.836524,50.716003],"type":"Point"}
}