{
  "type": "Feature",
  "properties": {
    "iso:country":"DE",
    "sg:address":"Rh\u00f6nstr. 3",
    "sg:city":"Hainburg",
    "sg:phone":"+49 6182/5674",
    "sg:postcode":"63512",
    "sg:province":"Hessen",
    "wof:name":"B\u00e4rbel Gottwald",
    "wof:placetype":"venue"
},
  "geometry": {"coordinates":[8.93450737,50.0808639526],"type":"Point"}
}