{
  "type": "Feature",
  "properties": {
    "iso:country":"DE",
    "sg:address":"Erbshausener Str.",
    "sg:city":"Hausen",
    "sg:postcode":"97262",
    "sg:province":"Bayern",
    "wof:name":"E. O. K. Simon Bildhauer",
    "wof:placetype":"venue"
},
  "geometry": {"coordinates":[10.019215,49.90992],"type":"Point"}
}