{
  "type": "Feature",
  "properties": {
    "iso:country":"DE",
    "sg:address":"Niederau\u00dfemer Str. 45",
    "sg:city":"Bergheim",
    "sg:phone":"+49 2271/54227",
    "sg:postcode":"50129",
    "sg:province":"Nordrhein-Westfalen",
    "wof:name":"Christa Kaiser",
    "wof:placetype":"venue"
},
  "geometry": {"coordinates":[6.6791791916,50.975643158],"type":"Point"}
}