{
  "type": "Feature",
  "properties": {
    "iso:country":"DE",
    "sg:address":"Herzmoor 12",
    "sg:city":"Hamburg",
    "sg:phone":"+49 40/5205407",
    "sg:postcode":"22417",
    "sg:province":"Hamburg",
    "wof:name":"Cns-ingenieur-b\u00fcro- Hamburg Gmbh",
    "wof:placetype":"venue"
},
  "geometry": {"coordinates":[10.0310373306,53.6619377136],"type":"Point"}
}