{
  "type": "Feature",
  "properties": {
    "iso:country":"DE",
    "sg:address":"Max-Liebermann-Str. 3",
    "sg:city":"Dresden",
    "sg:phone":"+49 351/4714399",
    "sg:postcode":"01217",
    "sg:province":"Sachsen",
    "wof:name":"B. Schaarschmidt",
    "wof:placetype":"venue"
},
  "geometry": {"coordinates":[13.7423000336,51.0293121338],"type":"Point"}
}