{
  "type": "Feature",
  "properties": {
    "iso:country":"DE",
    "sg:address":"Bayernstr. 49",
    "sg:city":"Oberhausen",
    "sg:phone":"+49 208/665429",
    "sg:postcode":"46149",
    "sg:province":"Nordrhein-Westfalen",
    "wof:name":"A. K\u00f6bnick",
    "wof:placetype":"venue"
},
  "geometry": {"coordinates":[6.8393778801,51.507648468],"type":"Point"}
}