{
  "type": "Feature",
  "properties": {
    "iso:country":"DE",
    "sg:address":"Ludwigstr. 3",
    "sg:city":"Ingolstadt",
    "sg:phone":"+49 841/42492",
    "sg:postcode":"85049",
    "sg:province":"Bayern",
    "wof:name":"Haderthauer Und Haderthauer Rechtsanw\u00e4lte",
    "wof:placetype":"venue"
},
  "geometry": {"coordinates":[11.4246311188,48.7643241882],"type":"Point"}
}