{
  "type": "Feature",
  "properties": {
    "iso:country":"DE",
    "sg:address":"Bismarckstr. 5",
    "sg:city":"Berlin",
    "sg:phone":"+49 30/3412053",
    "sg:postcode":"10625",
    "sg:province":"Berlin",
    "wof:name":"Oscar L. Sandner Rechtsanwalt",
    "wof:placetype":"venue"
},
  "geometry": {"coordinates":[13.3186912537,52.5126037598],"type":"Point"}
}