{
  "type": "Feature",
  "properties": {
    "iso:country":"DE",
    "sg:address":"Marktstr. 41",
    "sg:city":"Greven",
    "sg:phone":"+49 2571/952756",
    "sg:postcode":"48268",
    "sg:province":"Nordrhein-Westfalen",
    "wof:name":"Klaus Nikolai Rechtsanwalt",
    "wof:placetype":"venue"
},
  "geometry": {"coordinates":[7.6111950874,52.0954246521],"type":"Point"}
}