{
  "type": "Feature",
  "properties": {
    "iso:country":"DE",
    "sg:address":"Neustr. 42",
    "sg:city":"D\u00fcsseldorf",
    "sg:phone":"+49 211/8639053",
    "sg:postcode":"40213",
    "sg:province":"Nordrhein-Westfalen",
    "wof:name":"E-plus Shop",
    "wof:placetype":"venue"
},
  "geometry": {"coordinates":[6.7763280869,51.2256660461],"type":"Point"}
}