{
  "type": "Feature",
  "properties": {
    "iso:country":"DE",
    "sg:address":"Teichstr. 20",
    "sg:city":"Zeuthen",
    "sg:phone":"+49 33762/71807",
    "sg:postcode":"15738",
    "sg:province":"Brandenburg",
    "wof:name":"M. Popp",
    "wof:placetype":"venue"
},
  "geometry": {"coordinates":[13.6151027679,52.3498687744],"type":"Point"}
}