{
  "type": "Feature",
  "properties": {
    "iso:country":"DE",
    "sg:address":"Vereinsstr. 7",
    "sg:city":"Heide",
    "sg:phone":"+49 481/683083",
    "sg:postcode":"25746",
    "sg:province":"Schleswig-Holstein",
    "wof:name":"Pension Garni G\u00e4stehaus Geli",
    "wof:placetype":"venue"
},
  "geometry": {"coordinates":[9.0943098068,54.1868667603],"type":"Point"}
}