{
  "type": "Feature",
  "properties": {
    "iso:country":"DE",
    "sg:address":"Mittelstr. 15",
    "sg:city":"D\u00f6rentrup",
    "sg:phone":"+49 5265/203",
    "sg:postcode":"32694",
    "sg:province":"Nordrhein-Westfalen",
    "wof:name":"Gustav Blattgerste",
    "wof:placetype":"venue"
},
  "geometry": {"coordinates":[9.0055999756,52.0320281982],"type":"Point"}
}