{
  "type": "Feature",
  "properties": {
    "iso:country":"DE",
    "sg:address":"Lange Str. 40",
    "sg:city":"Wunstorf",
    "sg:phone":"+49 5031/916910",
    "sg:postcode":"31515",
    "sg:province":"Niedersachsen",
    "wof:name":"Fielmann Augenoptik Ag & Co.",
    "wof:placetype":"venue"
},
  "geometry": {"coordinates":[9.4252109528,52.4257888794],"type":"Point"}
}