{
  "type": "Feature",
  "properties": {
    "iso:country":"DE",
    "sg:address":"Wendemarken 3",
    "sg:city":"Kleinmachnow",
    "sg:postcode":"14532",
    "sg:province":"Brandenburg",
    "wof:name":"Johannisplatz 8 Jena Grundst\u00fccks- Gmbh & Co. Kg",
    "wof:placetype":"venue"
},
  "geometry": {"coordinates":[13.22237,52.41893],"type":"Point"}
}