{
  "type": "Feature",
  "properties": {
    "iso:country":"DE",
    "sg:address":"Appelhoff 1",
    "sg:city":"Jork",
    "sg:phone":"+49 4162/7170",
    "sg:postcode":"21635",
    "sg:province":"Niedersachsen",
    "wof:name":"Heiko Ott",
    "wof:placetype":"venue"
},
  "geometry": {"coordinates":[9.684887886,53.5400772095],"type":"Point"}
}