{
  "type": "Feature",
  "properties": {
    "iso:country":"DE",
    "sg:address":"Bahnhofstra\u00dfe 26",
    "sg:city":"Eberbach",
    "sg:phone":"+49 6271/919737",
    "sg:postcode":"69412",
    "sg:province":"Baden-W\u00fcrttemberg",
    "wof:name":"Fairness Gmbh Pflegedienst",
    "wof:placetype":"venue"
},
  "geometry": {"coordinates":[8.985928,49.463013],"type":"Point"}
}