{
  "type": "Feature",
  "properties": {
    "iso:country":"DE",
    "sg:address":"Fuhrenkamp 11 d",
    "sg:city":"Gnarrenburg",
    "sg:phone":"+49 4763",
    "sg:postcode":"27442",
    "sg:province":"Niedersachsen",
    "wof:name":"Stark Wie Eine",
    "wof:placetype":"venue"
},
  "geometry": {"coordinates":[9.009691,53.388466],"type":"Point"}
}