{
  "type": "Feature",
  "properties": {
    "iso:country":"DE",
    "sg:address":"Dorstener Str. 377 a",
    "sg:city":"Herne",
    "sg:phone":"+49 2325/71598",
    "sg:postcode":"44653",
    "sg:province":"Nordrhein-Westfalen",
    "wof:name":"Sassenhof",
    "wof:placetype":"venue"
},
  "geometry": {"coordinates":[7.1736769676,51.5402832031],"type":"Point"}
}