{
  "type": "Feature",
  "properties": {
    "iso:country":"DE",
    "sg:address":"Vogelsbergstr. 19",
    "sg:city":"Altenstadt",
    "sg:phone":"+49 6047/4431",
    "sg:postcode":"63674",
    "sg:province":"Hessen",
    "wof:name":"Stefanie Renner Wollst\u00fcbchen",
    "wof:placetype":"venue"
},
  "geometry": {"coordinates":[8.943518,50.285313],"type":"Point"}
}