{
  "type": "Feature",
  "properties": {
    "iso:country":"DE",
    "sg:address":"Josef-Schregel-Str. 70",
    "sg:city":"D\u00fcren",
    "sg:phone":"+49 2421/44853",
    "sg:postcode":"52349",
    "sg:province":"Nordrhein-Westfalen",
    "wof:name":"Mehmed Yardimc",
    "wof:placetype":"venue"
},
  "geometry": {"coordinates":[6.4801177979,50.8089294434],"type":"Point"}
}