{
  "type": "Feature",
  "properties": {
    "iso:country":"DE",
    "sg:address":"Heckelstr. 14",
    "sg:city":"Allersberg",
    "sg:phone":"+49 9176/5212",
    "sg:postcode":"90584",
    "sg:province":"Bayern",
    "wof:name":"Delta Warenhandels Gmbh",
    "wof:placetype":"venue"
},
  "geometry": {"coordinates":[11.2379693985,49.2516822815],"type":"Point"}
}