{
  "type": "Feature",
  "properties": {
    "iso:country":"DE",
    "sg:address":"Merseburger Landstr. 12 a",
    "sg:city":"Leipzig",
    "sg:phone":"+49 341/4419237",
    "sg:postcode":"04178",
    "sg:province":"Sachsen",
    "wof:name":"Wagner Gmbh",
    "wof:placetype":"venue"
},
  "geometry": {"coordinates":[12.28734,51.343739],"type":"Point"}
}