{
  "type": "Feature",
  "properties": {
    "iso:country":"DE",
    "sg:address":"Drosselweg 6",
    "sg:city":"Aschheim",
    "sg:phone":"+49 89/94500455",
    "sg:postcode":"85609",
    "sg:province":"Bayern",
    "wof:name":"Microcare Systemhaus Gmbh",
    "wof:placetype":"venue"
},
  "geometry": {"coordinates":[11.695393,48.151314],"type":"Point"}
}