{
  "type": "Feature",
  "properties": {
    "iso:country":"DE",
    "sg:address":"Onkel-Tom-Str. 15",
    "sg:city":"Berlin",
    "sg:phone":"+49 30",
    "sg:postcode":"14169",
    "sg:province":"Berlin",
    "wof:name":"Pin Berlin, Garten- Und Landschaftsarchitekt Manuel Christel",
    "wof:placetype":"venue"
},
  "geometry": {"coordinates":[13.2576589584,52.4371566772],"type":"Point"}
}