{
  "type": "Feature",
  "properties": {
    "iso:country":"DE",
    "sg:address":"Schwiesower Str.",
    "sg:city":"L\u00fcssow",
    "sg:postcode":"18276",
    "sg:province":"Mecklenburg-Vorpommern",
    "wof:name":"Agrofarm Eg",
    "wof:placetype":"venue"
},
  "geometry": {"coordinates":[12.142937,53.838615],"type":"Point"}
}