{
  "type": "Feature",
  "properties": {
    "iso:country":"DE",
    "sg:address":"Po\u00dfmoorweg 21",
    "sg:city":"Hamburg",
    "sg:phone":"+49 40/27806280",
    "sg:postcode":"22301",
    "sg:province":"Hamburg",
    "wof:name":"A&sd Acoustic & Sound Design Vertriebs- Und Einrichtungs Gmbh",
    "wof:placetype":"venue"
},
  "geometry": {"coordinates":[10.009424,53.586117],"type":"Point"}
}