{
  "type": "Feature",
  "properties": {
    "iso:country":"DE",
    "sg:address":"Holstenwall 10",
    "sg:city":"Hamburg",
    "sg:postcode":"20355",
    "sg:province":"Hamburg",
    "wof:name":"M & M Aerospace Hardware Gmbh",
    "wof:placetype":"venue"
},
  "geometry": {"coordinates":[9.9771642685,53.5535087585],"type":"Point"}
}