{
  "type": "Feature",
  "properties": {
    "iso:country":"DE",
    "sg:address":"Am Industriehafen 5",
    "sg:city":"Flensburg",
    "sg:phone":"+49 461/17691",
    "sg:postcode":"24937",
    "sg:province":"Schleswig-Holstein",
    "wof:name":"Stenhoj Maschinenfabrik Gmbh",
    "wof:placetype":"venue"
},
  "geometry": {"coordinates":[9.4384441376,54.8007049561],"type":"Point"}
}