{
  "type": "Feature",
  "properties": {
    "iso:country":"DE",
    "sg:address":"Blockmacherring",
    "sg:city":"Rostock",
    "sg:postcode":"18109",
    "sg:province":"Mecklenburg-Vorpommern",
    "wof:name":"Eurospar",
    "wof:placetype":"venue"
},
  "geometry": {"coordinates":[12.0767011642,54.1467285156],"type":"Point"}
}