{
  "type": "Feature",
  "properties": {
    "iso:country":"DE",
    "sg:address":"Niekoppel 1",
    "sg:city":"Goltoft",
    "sg:phone":"+49 4622/180030",
    "sg:postcode":"24864",
    "sg:province":"Schleswig-Holstein",
    "wof:name":"Bjerno Consulting Gmbh",
    "wof:placetype":"venue"
},
  "geometry": {"coordinates":[9.7212314606,54.5497894287],"type":"Point"}
}