{
  "type": "Feature",
  "properties": {
    "iso:country":"DE",
    "sg:address":"M\u00fchlweg 1",
    "sg:city":"Scheibenhardt",
    "sg:phone":"+49 7277/343",
    "sg:postcode":"76779",
    "sg:province":"Rheinland-Pfalz",
    "wof:name":"L. Und A. Saum",
    "wof:placetype":"venue"
},
  "geometry": {"coordinates":[8.140357,48.981033],"type":"Point"}
}