{
  "type": "Feature",
  "properties": {
    "iso:country":"DE",
    "sg:address":"Am Kr\u00f6kentor 3",
    "sg:city":"Magdeburg",
    "sg:phone":"+49 391/532150",
    "sg:postcode":"39104",
    "sg:province":"Sachsen-Anhalt",
    "wof:name":"Berufsbildende Schulen Iii Der Kreisfreien Stadt Magdeburg",
    "wof:placetype":"venue"
},
  "geometry": {"coordinates":[11.6363658905,52.1386680603],"type":"Point"}
}