{
  "type": "Feature",
  "properties": {
    "iso:country":"DE",
    "sg:address":"Wiesenstr. 1",
    "sg:city":"Riedlingen",
    "sg:phone":"+49 7373/668",
    "sg:postcode":"88499",
    "sg:province":"Baden-W\u00fcrttemberg",
    "wof:name":"X. Schien",
    "wof:placetype":"venue"
},
  "geometry": {"coordinates":[9.516014,48.217922],"type":"Point"}
}