{
  "type": "Feature",
  "properties": {
    "iso:country":"DE",
    "sg:address":"Ahornstr. 19",
    "sg:city":"M\u00fchldorf",
    "sg:phone":"+49 8631/12391",
    "sg:postcode":"84453",
    "sg:province":"Bayern",
    "wof:name":"Herbert Mall Architekt",
    "wof:placetype":"venue"
},
  "geometry": {"coordinates":[12.550778,48.232063],"type":"Point"}
}