{
  "type": "Feature",
  "properties": {
    "iso:country":"DE",
    "sg:address":"Im Rad 18",
    "sg:city":"Wiesbaden",
    "sg:phone":"+49 611/9812656",
    "sg:postcode":"65197",
    "sg:province":"Hessen",
    "wof:name":"Gustav Wilhelm Verwaltungs-gmbh",
    "wof:placetype":"venue"
},
  "geometry": {"coordinates":[8.212776,50.074986],"type":"Point"}
}