{
  "type": "Feature",
  "properties": {
    "iso:country":"DE",
    "sg:address":"St. Margaretha Weg 11",
    "sg:city":"Raisting",
    "sg:postcode":"82399",
    "sg:province":"Bayern",
    "wof:name":"Moore & Company",
    "wof:placetype":"venue"
},
  "geometry": {"coordinates":[11.1186256409,47.913433075],"type":"Point"}
}