{
  "type": "Feature",
  "properties": {
    "iso:country":"DE",
    "sg:address":"Schulstr. 18",
    "sg:city":"Burgwedel",
    "sg:phone":"+49 5139/8390",
    "sg:postcode":"30938",
    "sg:province":"Niedersachsen",
    "wof:name":"Herbert Hofer",
    "wof:placetype":"venue"
},
  "geometry": {"coordinates":[9.882074,52.507755],"type":"Point"}
}