{
  "type": "Feature",
  "properties": {
    "iso:country":"DE",
    "sg:address":"Sonnenlandstr. 27",
    "sg:city":"Potsdam",
    "sg:phone":"+49 331/964703",
    "sg:postcode":"14471",
    "sg:province":"Brandenburg",
    "wof:name":"Nichelmann",
    "wof:placetype":"venue"
},
  "geometry": {"coordinates":[13.017342,52.384312],"type":"Point"}
}