{
  "type": "Feature",
  "properties": {
    "iso:country":"DE",
    "sg:address":"Neue Str. 6",
    "sg:city":"Teltow",
    "sg:postcode":"14513",
    "sg:province":"Brandenburg",
    "wof:name":"Staatliche Allgemeinbibliothek",
    "wof:placetype":"venue"
},
  "geometry": {"coordinates":[13.262008,52.402508],"type":"Point"}
}