{
  "type": "Feature",
  "properties": {
    "iso:country":"DE",
    "sg:address":"Stadtplatz 1",
    "sg:city":"Geisenfeld",
    "sg:phone":"+49 8452/72700",
    "sg:postcode":"85290",
    "sg:province":"Bayern",
    "wof:name":"Bayerische Hypo- Und Vereinsbank Ag",
    "wof:placetype":"venue"
},
  "geometry": {"coordinates":[11.6117963791,48.6839485168],"type":"Point"}
}