{
  "type": "Feature",
  "properties": {
    "iso:country":"DE",
    "sg:address":"Ritterstr. 6",
    "sg:city":"Leer",
    "sg:phone":"+49 491/9791960",
    "sg:postcode":"26789",
    "sg:province":"Niedersachsen",
    "wof:name":"Egon Wessels",
    "wof:placetype":"venue"
},
  "geometry": {"coordinates":[7.496423,53.235111],"type":"Point"}
}