{
  "type": "Feature",
  "properties": {
    "iso:country":"DE",
    "sg:address":"Porgesrg. 42",
    "sg:city":"Hamburg",
    "sg:phone":"+49 40/7313380",
    "sg:postcode":"22113",
    "sg:province":"Schleswig-Holstein",
    "wof:name":"Patiga Kg",
    "wof:placetype":"venue"
},
  "geometry": {"coordinates":[10.1010837555,53.5213432312],"type":"Point"}
}