{
  "type": "Feature",
  "properties": {
    "iso:country":"DE",
    "sg:address":"Weinstr. 64",
    "sg:city":"Rhodt",
    "sg:postcode":"76835",
    "sg:province":"Rheinland-Pfalz",
    "wof:name":"Netzwerk Unternehmens- Beratung Gmbh",
    "wof:placetype":"venue"
},
  "geometry": {"coordinates":[-81.12242126460001,38.9796791077],"type":"Point"}
}