{
  "type": "Feature",
  "properties": {
    "iso:country":"DE",
    "sg:address":"Carl-Schurz-Str. 2",
    "sg:city":"Bremen",
    "sg:phone":"+49 421/3430900",
    "sg:postcode":"28209",
    "sg:province":"Bremen",
    "wof:name":"Alten- Und Pflegeheim Haus Sorgenfrei",
    "wof:placetype":"venue"
},
  "geometry": {"coordinates":[8.8416,53.083492],"type":"Point"}
}