{
  "type": "Feature",
  "properties": {
    "iso:country":"DE",
    "sg:address":"Cleeberger Str. 21",
    "sg:city":"Waldsolms",
    "sg:phone":"+49 6085/3033",
    "sg:postcode":"35647",
    "sg:province":"Hessen",
    "wof:name":"L\u00f6wen-apotheke Inh. Rolf Achim Lettermann",
    "wof:placetype":"venue"
},
  "geometry": {"coordinates":[8.499864,50.433178],"type":"Point"}
}