{
  "type": "Feature",
  "properties": {
    "iso:country":"DE",
    "sg:address":"Postfach 26",
    "sg:city":"Walkenried",
    "sg:phone":"+49 5525/805",
    "sg:postcode":"37445",
    "sg:province":"Niedersachsen",
    "wof:name":"Fritz Und Thomas Husung",
    "wof:placetype":"venue"
},
  "geometry": {"coordinates":[10.617395401,51.5853462219],"type":"Point"}
}