{
  "type": "Feature",
  "properties": {
    "iso:country":"DE",
    "sg:address":"Am Elsaw\u00e4ldchen 8",
    "sg:city":"Ennigerloh",
    "sg:phone":"+49 2525/4952",
    "sg:postcode":"59320",
    "sg:province":"Nordrhein-Westfalen",
    "wof:name":"Deutscher Bund F\u00fcr Vogelschutz Kreisverband Warendorf E. V.",
    "wof:placetype":"venue"
},
  "geometry": {"coordinates":[8.0207986832,51.8146324158],"type":"Point"}
}