{
  "type": "Feature",
  "properties": {
    "iso:country":"DE",
    "sg:address":"M\u00fcnchnerstr.",
    "sg:city":"Weilersheim",
    "sg:phone":"+49 89/2513852",
    "sg:postcode":"89235",
    "wof:name":"Wellness-hotel, Wellness-hotel, Judo, Judo",
    "wof:placetype":"venue"
},
  "geometry": {"coordinates":[-97.842628479,22.2432308197],"type":"Point"}
}