{
  "type": "Feature",
  "properties": {
    "iso:country":"DE",
    "sg:address":"Gewerbegebiet West 7",
    "sg:city":"Brumby",
    "sg:phone":"+49 39291/5160",
    "sg:postcode":"39240",
    "sg:province":"Sachsen-Anhalt",
    "wof:name":"Babock Hydroform Gmbh",
    "wof:placetype":"venue"
},
  "geometry": {"coordinates":[11.708375,51.895855],"type":"Point"}
}