{
  "type": "Feature",
  "properties": {
    "iso:country":"DE",
    "sg:address":"Hauptstr. 21",
    "sg:city":"Maisach",
    "sg:postcode":"82216",
    "sg:province":"Bayern",
    "wof:name":"Bmc Messsysteme Gmbh - Innovative Messtechnik",
    "wof:placetype":"venue"
},
  "geometry": {"coordinates":[11.262652,48.21735],"type":"Point"}
}