{
  "type": "Feature",
  "properties": {
    "iso:country":"DE",
    "sg:address":"Pfarrgasse 8",
    "sg:city":"Ingolstadt",
    "sg:phone":"+49 841/910874",
    "sg:postcode":"85049",
    "sg:province":"Bayern",
    "wof:name":"American Store Pedersen Gmbh",
    "wof:placetype":"venue"
},
  "geometry": {"coordinates":[11.4259796143,48.7638511658],"type":"Point"}
}