{
  "type": "Feature",
  "properties": {
    "iso:country":"DE",
    "sg:address":"Im Eschle 18",
    "sg:city":"Stockach",
    "sg:phone":"+49 7771/62162",
    "sg:postcode":"78333",
    "sg:province":"Baden-W\u00fcrttemberg",
    "wof:name":"Maurer Wohnbau",
    "wof:placetype":"venue"
},
  "geometry": {"coordinates":[9.00302,47.863098],"type":"Point"}
}