{
  "type": "Feature",
  "properties": {
    "iso:country":"DE",
    "sg:address":"Teichgraben 1",
    "sg:city":"Jena",
    "sg:postcode":"07743",
    "sg:province":"Th\u00fcringen",
    "wof:name":"Zimmermann Hotelmanagement Gmbh",
    "wof:placetype":"venue"
},
  "geometry": {"coordinates":[11.5849103928,50.9271469116],"type":"Point"}
}