{
  "type": "Feature",
  "properties": {
    "iso:country":"DE",
    "sg:address":"Macherstr. 18",
    "sg:city":"Kamenz",
    "sg:phone":"+49 35783/8430",
    "sg:postcode":"01917",
    "sg:province":"Sachsen",
    "wof:name":"Renner",
    "wof:placetype":"venue"
},
  "geometry": {"coordinates":[14.1031951904,51.2788543701],"type":"Point"}
}