{
  "type": "Feature",
  "properties": {
    "iso:country":"DE",
    "sg:address":"Allee 1",
    "sg:city":"T\u00f6nning",
    "sg:phone":"+49 4861/5134",
    "sg:postcode":"25832",
    "sg:province":"Schleswig-Holstein",
    "wof:name":"Gasthaus H. Und L. Petersen",
    "wof:placetype":"venue"
},
  "geometry": {"coordinates":[8.9413671494,54.3143806458],"type":"Point"}
}