{
  "type": "Feature",
  "properties": {
    "iso:country":"DE",
    "sg:address":"Wilhelminenkoog",
    "sg:city":"Tating",
    "sg:phone":"+49 4862/266",
    "sg:postcode":"25881",
    "sg:province":"Schleswig-Holstein",
    "wof:name":"H. Reichl",
    "wof:placetype":"venue"
},
  "geometry": {"coordinates":[8.717306,54.296406],"type":"Point"}
}