{
  "type": "Feature",
  "properties": {
    "iso:country":"DE",
    "sg:address":"Sch\u00fcttenhengst 1A",
    "sg:city":"Urbach",
    "sg:phone":"+49 7181/998780",
    "sg:postcode":"73660",
    "sg:province":"Baden-W\u00fcrttemberg",
    "wof:name":"J. Kurz",
    "wof:placetype":"venue"
},
  "geometry": {"coordinates":[9.5662193298,48.8176460266],"type":"Point"}
}