{
  "type": "Feature",
  "properties": {
    "iso:country":"DE",
    "sg:address":"Prinzregentenstr. 66",
    "sg:city":"M\u00fcnchen",
    "sg:phone":"+49 89/479353",
    "sg:postcode":"81675",
    "sg:province":"Bayern",
    "wof:name":"Norbert Ulbrich Heilpraktiker",
    "wof:placetype":"venue"
},
  "geometry": {"coordinates":[11.6007204056,48.1404457092],"type":"Point"}
}