{
  "type": "Feature",
  "properties": {
    "iso:country":"DE",
    "sg:address":"Schlo\u00dfstr. 14a",
    "sg:city":"Gr\u00fcnwald",
    "sg:phone":"+49 89/6412726",
    "sg:postcode":"82031",
    "sg:province":"Bayern",
    "wof:name":"Photo Karl Kitt Gmbh",
    "wof:placetype":"venue"
},
  "geometry": {"coordinates":[11.5238380432,48.0413665771],"type":"Point"}
}