{
  "type": "Feature",
  "properties": {
    "iso:country":"DE",
    "sg:address":"Neumarkt 24",
    "sg:city":"Leipzig",
    "sg:phone":"+49 341/141880",
    "sg:postcode":"04109",
    "sg:province":"Sachsen",
    "wof:name":"W\u00dcba W\u00fcrttembergische Und Badische Versicherungs- Ag",
    "wof:placetype":"venue"
},
  "geometry": {"coordinates":[12.3760957718,51.3385391235],"type":"Point"}
}