{
  "type": "Feature",
  "properties": {
    "iso:country":"DE",
    "sg:address":"F\u00fchrtbruchstr. 19",
    "sg:city":"Kraichtal",
    "sg:phone":"+49 7250/8553",
    "sg:postcode":"76703",
    "sg:province":"Baden-W\u00fcrttemberg",
    "wof:name":"R. Augustin",
    "wof:placetype":"venue"
},
  "geometry": {"coordinates":[8.7099590302,49.1245155334],"type":"Point"}
}