{
  "type": "Feature",
  "properties": {
    "iso:country":"DE",
    "sg:address":"Am Inselweg 31",
    "sg:city":"Elchingen",
    "sg:phone":"+49 731/264390",
    "sg:postcode":"89275",
    "sg:province":"Bayern",
    "wof:name":"Sportgastst\u00e4tte Thalfingen",
    "wof:placetype":"venue"
},
  "geometry": {"coordinates":[10.0525083542,48.4339447021],"type":"Point"}
}