{
  "type": "Feature",
  "properties": {
    "iso:country":"DE",
    "sg:address":"Lilienthalstr. 3",
    "sg:city":"Neustadt",
    "sg:phone":"+49 6327/625",
    "sg:postcode":"67435",
    "sg:province":"Rheinland-Pfalz",
    "wof:name":"Heinz Derwand",
    "wof:placetype":"venue"
},
  "geometry": {"coordinates":[8.199709,49.3377],"type":"Point"}
}