{
  "type": "Feature",
  "properties": {
    "iso:country":"DE",
    "sg:address":"Stavenhagener Str. 29",
    "sg:city":"Demmin",
    "sg:phone":"+49 3998/223123",
    "sg:postcode":"17109",
    "sg:province":"Mecklenburg-Vorpommern",
    "wof:name":"Petra Baustoffhandel Gmbh",
    "wof:placetype":"venue"
},
  "geometry": {"coordinates":[13.0408382416,53.9060287476],"type":"Point"}
}