{
  "type": "Feature",
  "properties": {
    "iso:country":"DE",
    "sg:address":"Altmannsgr\u00fcner Str. 1",
    "sg:city":"Treuen",
    "sg:postcode":"08233",
    "sg:province":"Sachsen",
    "wof:name":"Trebatal",
    "wof:placetype":"venue"
},
  "geometry": {"coordinates":[12.3091363907,50.5370903015],"type":"Point"}
}