{
  "type": "Feature",
  "properties": {
    "iso:country":"DE",
    "sg:address":"Wollinstr. 25",
    "sg:city":"B\u00fcdelsdorf",
    "sg:phone":"+49 4331/3580",
    "sg:postcode":"24782",
    "sg:province":"Schleswig-Holstein",
    "wof:name":"Vereinigte Asphalt Mischwerke Gmbh & Co. Kg",
    "wof:placetype":"venue"
},
  "geometry": {"coordinates":[9.701874733,54.3147659302],"type":"Point"}
}