{
  "type": "Feature",
  "properties": {
    "iso:country":"DE",
    "sg:address":"Am Seigen 2",
    "sg:city":"Roding",
    "sg:phone":"+49 9461/1764",
    "sg:postcode":"93426",
    "sg:province":"Bayern",
    "wof:name":"Willibald Wiesmeier",
    "wof:placetype":"venue"
},
  "geometry": {"coordinates":[12.5211248398,49.1969490051],"type":"Point"}
}