{
  "type": "Feature",
  "properties": {
    "iso:country":"DE",
    "sg:address":"Herdentorsteinweg",
    "sg:city":"Bremen",
    "sg:postcode":"28195",
    "sg:province":"Bremen",
    "wof:name":"Vectura Inceptum E. K.",
    "wof:placetype":"venue"
},
  "geometry": {"coordinates":[8.810975,53.080231],"type":"Point"}
}