{
  "type": "Feature",
  "properties": {
    "iso:country":"DE",
    "sg:address":"Schuegrafstr. 9",
    "sg:city":"M\u00fcnchen",
    "sg:phone":"+49 89/8960540",
    "sg:postcode":"81245",
    "sg:province":"Bayern",
    "wof:name":"Transcharter Gmbh",
    "wof:placetype":"venue"
},
  "geometry": {"coordinates":[11.4761981964,48.1518363953],"type":"Point"}
}