{
  "type": "Feature",
  "properties": {
    "iso:country":"DE",
    "sg:address":"Talstr. 16",
    "sg:city":"Stolpen",
    "sg:phone":"+49 35973/26604",
    "sg:postcode":"01833",
    "sg:province":"Sachsen",
    "wof:name":"Peter Willkommen",
    "wof:placetype":"venue"
},
  "geometry": {"coordinates":[14.066681,51.042141],"type":"Point"}
}