{
  "type": "Feature",
  "properties": {
    "iso:country":"DE",
    "sg:address":"Talstr. 50",
    "sg:city":"Kreischa",
    "sg:phone":"+49 35206/21478",
    "sg:postcode":"01731",
    "sg:province":"Sachsen",
    "wof:name":"Albert Krohn",
    "wof:placetype":"venue"
},
  "geometry": {"coordinates":[13.716638,50.948231],"type":"Point"}
}