{
  "type": "Feature",
  "properties": {
    "iso:country":"DE",
    "sg:address":"Elsener Str. 26",
    "sg:city":"Paderborn",
    "sg:phone":"+49 5251/133333",
    "sg:postcode":"33102",
    "sg:province":"Nordrhein-Westfalen",
    "wof:name":"Gerhard Peitz",
    "wof:placetype":"venue"
},
  "geometry": {"coordinates":[8.7328195572,51.7257385254],"type":"Point"}
}