{
  "type": "Feature",
  "properties": {
    "iso:country":"DE",
    "sg:address":"An der Bober 1",
    "sg:city":"Hohenweiden",
    "sg:phone":"+49 3461/77150",
    "sg:postcode":"06179",
    "sg:province":"Sachsen-Anhalt",
    "wof:name":"Ilbau Gmbh",
    "wof:placetype":"venue"
},
  "geometry": {"coordinates":[11.8105401993,51.460899353],"type":"Point"}
}