{
  "type": "Feature",
  "properties": {
    "iso:country":"DE",
    "sg:address":"Hunoldstr. 5 b",
    "sg:city":"K\u00f6ln",
    "sg:phone":"+49 2203/99970",
    "sg:postcode":"51147",
    "sg:province":"Nordrhein-Westfalen",
    "wof:name":"Repro-rozsa",
    "wof:placetype":"venue"
},
  "geometry": {"coordinates":[7.099362,50.856232],"type":"Point"}
}