{
  "type": "Feature",
  "properties": {
    "iso:country":"DE",
    "sg:city":"Overath",
    "sg:postcode":"51491",
    "sg:province":"Nordrhein-Westfalen",
    "wof:name":"Irish Wolfhounds Von Den Erzminen\u00b4",
    "wof:placetype":"venue"
},
  "geometry": {"coordinates":[7.2882,50.93338],"type":"Point"}
}