{
  "type": "Feature",
  "properties": {
    "iso:country":"DE",
    "sg:address":"Uepser Str. 33",
    "sg:city":"Asendorf",
    "sg:phone":"+49 4253/1489",
    "sg:postcode":"27330",
    "sg:province":"Niedersachsen",
    "wof:name":"Heinz Tecklenburg",
    "wof:placetype":"venue"
},
  "geometry": {"coordinates":[8.972797,52.736816],"type":"Point"}
}