{
  "type": "Feature",
  "properties": {
    "iso:country":"DE",
    "sg:address":"Westendstr. 13",
    "sg:city":"Dresden",
    "sg:phone":"+49 351/2815277",
    "sg:postcode":"01187",
    "sg:province":"Sachsen",
    "wof:name":"Ingenieurb\u00fcro Dr. Riechert",
    "wof:placetype":"venue"
},
  "geometry": {"coordinates":[13.7141389847,51.0253143311],"type":"Point"}
}