{
  "type": "Feature",
  "properties": {
    "iso:country":"DE",
    "sg:address":"Carl-Benz-Str. 26",
    "sg:city":"Burbach",
    "sg:phone":"+49 2736/5911",
    "sg:postcode":"57299",
    "sg:province":"Nordrhein-Westfalen",
    "wof:name":"Burbacher Objekteinrichtungen Gmbh & Co. Kg",
    "wof:placetype":"venue"
},
  "geometry": {"coordinates":[8.107837677,50.7526893616],"type":"Point"}
}