{
  "type": "Feature",
  "properties": {
    "iso:country":"DE",
    "sg:address":"Schelde-Lahn-Str. 24",
    "sg:city":"Dautphetal",
    "sg:phone":"+49 6468/352",
    "sg:postcode":"35232",
    "sg:province":"Hessen",
    "wof:name":"H. Leinweber",
    "wof:placetype":"venue"
},
  "geometry": {"coordinates":[8.509299,50.846272],"type":"Point"}
}