{
  "type": "Feature",
  "properties": {
    "iso:country":"DE",
    "sg:address":"Untere Hauptstr. 15-19a",
    "sg:city":"Hockenheim",
    "sg:phone":"+49 6205/4090",
    "sg:postcode":"68766",
    "sg:province":"Baden-W\u00fcrttemberg",
    "wof:name":"Deniz Reise- Und Dolmetscherb\u00fcro",
    "wof:placetype":"venue"
},
  "geometry": {"coordinates":[8.5460805893,49.3198852539],"type":"Point"}
}