{
  "type": "Feature",
  "properties": {
    "iso:country":"DE",
    "sg:address":"Kaiserring 10a",
    "sg:city":"Wesel",
    "sg:phone":"+49 281/27224",
    "sg:postcode":"46483",
    "sg:province":"Nordrhein-Westfalen",
    "wof:name":"Heide Kleindiek",
    "wof:placetype":"venue"
},
  "geometry": {"coordinates":[6.6257,51.657787],"type":"Point"}
}