{
  "type": "Feature",
  "properties": {
    "iso:country":"DE",
    "sg:address":"Lohm\u00fcllerstr. 2",
    "sg:city":"K\u00f6ln",
    "sg:phone":"+49 221/5991391",
    "sg:postcode":"50737",
    "sg:province":"Nordrhein-Westfalen",
    "wof:name":"Dr. Med. Rudolf Lukosch",
    "wof:placetype":"venue"
},
  "geometry": {"coordinates":[6.9195299149,50.9914093018],"type":"Point"}
}