{
  "type": "Feature",
  "properties": {
    "iso:country":"DE",
    "sg:address":"96138",
    "sg:city":"Burgebrach",
    "sg:phone":"+49 9546/6511",
    "sg:postcode":"96138",
    "sg:province":"Bayern",
    "wof:name":"Discothek Way Up",
    "wof:placetype":"venue"
},
  "geometry": {"coordinates":[10.72298,49.822281],"type":"Point"}
}