{
  "type": "Feature",
  "properties": {
    "iso:country":"DE",
    "sg:address":"Bahnhofstr. 2",
    "sg:city":"Zschortau",
    "sg:phone":"+49 34202/91373",
    "sg:postcode":"04509",
    "sg:province":"Sachsen",
    "wof:name":"Konrad Nowak",
    "wof:placetype":"venue"
},
  "geometry": {"coordinates":[12.360937,51.482849],"type":"Point"}
}