{
  "type": "Feature",
  "properties": {
    "iso:country":"DE",
    "sg:address":"Geitlingstr 101",
    "sg:city":"M\u00fclheim",
    "sg:phone":"+49 208/993290",
    "sg:postcode":"45472",
    "sg:province":"Nordrhein-Westfalen",
    "wof:name":"Harmuth Entsorgung Gmbh",
    "wof:placetype":"venue"
},
  "geometry": {"coordinates":[6.92318,51.440411],"type":"Point"}
}