{
  "type": "Feature",
  "properties": {
    "iso:country":"DE",
    "sg:address":"Holstenhagen 3",
    "sg:city":"Trent",
    "sg:phone":"+49 38309/1427",
    "sg:postcode":"18569",
    "sg:province":"Mecklenburg-Vorpommern",
    "wof:name":"Rigo Ohlrich",
    "wof:placetype":"venue"
},
  "geometry": {"coordinates":[13.2493085861,54.5330352783],"type":"Point"}
}