{
  "type": "Feature",
  "properties": {
    "iso:country":"DE",
    "sg:address":"S\u00fcnneby 14",
    "sg:city":"Wanderup",
    "sg:postcode":"24997",
    "sg:province":"Schleswig-Holstein",
    "wof:name":"Rogge Hallen Gmbh",
    "wof:placetype":"venue"
},
  "geometry": {"coordinates":[9.3308439255,54.6860237122],"type":"Point"}
}