{
  "type": "Feature",
  "properties": {
    "iso:country":"DE",
    "sg:address":"Zum Neuhof 4",
    "sg:city":"Bad Kreuznach",
    "sg:phone":"+49 671/30079",
    "sg:postcode":"55545",
    "sg:province":"Rheinland-Pfalz",
    "wof:name":"A. Kopp",
    "wof:placetype":"venue"
},
  "geometry": {"coordinates":[7.8643860817,49.8684425354],"type":"Point"}
}