{
  "type": "Feature",
  "properties": {
    "iso:country":"DE",
    "sg:address":"Kelterstr. 46/1",
    "sg:city":"Esslingen",
    "sg:phone":"+49 711/371900",
    "sg:postcode":"73733",
    "sg:province":"Baden-W\u00fcrttemberg",
    "wof:name":"Gerhard Sohn",
    "wof:placetype":"venue"
},
  "geometry": {"coordinates":[9.294371,48.755657],"type":"Point"}
}