{
  "type": "Feature",
  "properties": {
    "iso:country":"DE",
    "sg:address":"Schulstr. 7",
    "sg:city":"Gersheim",
    "sg:phone":"+49 6843/91360",
    "sg:postcode":"66453",
    "sg:province":"Saarland",
    "wof:name":"Harig & Jochum Versicherungs- Makler Homburg Gmbh",
    "wof:placetype":"venue"
},
  "geometry": {"coordinates":[7.2104687691,49.1465988159],"type":"Point"}
}