{
  "type": "Feature",
  "properties": {
    "iso:country":"DE",
    "sg:address":"Breslauer Str. 7",
    "sg:city":"Hannover",
    "sg:phone":"+49 511/867573",
    "sg:postcode":"30519",
    "sg:province":"Niedersachsen",
    "wof:name":"Artur Gr\u00fcnberg",
    "wof:placetype":"venue"
},
  "geometry": {"coordinates":[9.791274,52.332737],"type":"Point"}
}