{
  "type": "Feature",
  "properties": {
    "iso:country":"DE",
    "sg:address":"Holl\u00e4ndische Str. 205a",
    "sg:city":"Kassel",
    "sg:phone":"+49 561/83618",
    "sg:postcode":"34127",
    "sg:province":"Hessen",
    "wof:name":"Holzhandel Knobloch Gmbh & Co. Handels- Und Verwaltungs- Kg",
    "wof:placetype":"venue"
},
  "geometry": {"coordinates":[9.4782419205,51.3425674438],"type":"Point"}
}