{
  "type": "Feature",
  "properties": {
    "iso:country":"DE",
    "sg:address":"St.-Barbara-Weg 16",
    "sg:city":"D\u00fclmen",
    "sg:phone":"+49 2594/7229",
    "sg:postcode":"48249",
    "sg:province":"Nordrhein-Westfalen",
    "wof:name":"J\u00fcrgen Fromme",
    "wof:placetype":"venue"
},
  "geometry": {"coordinates":[7.2568697929,51.8086395264],"type":"Point"}
}