{
  "type": "Feature",
  "properties": {
    "iso:country":"DE",
    "sg:address":"Hauptstr. 68",
    "sg:city":"Wallhausen",
    "sg:phone":"+49 6706/1854",
    "sg:postcode":"55595",
    "sg:province":"Rheinland-Pfalz",
    "wof:name":"Paul-dieter Eckes",
    "wof:placetype":"venue"
},
  "geometry": {"coordinates":[7.76731,49.889488],"type":"Point"}
}