{
  "type": "Feature",
  "properties": {
    "iso:country":"DE",
    "sg:address":"Hinterm Bahnhof 58",
    "sg:city":"Neuenrade",
    "sg:phone":"+49 2392/62259",
    "sg:postcode":"58809",
    "sg:province":"Nordrhein-Westfalen",
    "wof:name":"Hubert Hesse",
    "wof:placetype":"venue"
},
  "geometry": {"coordinates":[7.795555,51.286263],"type":"Point"}
}