{
  "type": "Feature",
  "properties": {
    "iso:country":"DE",
    "sg:address":"R\u00fcssen 55",
    "sg:city":"Twistringen",
    "sg:phone":"+49 4246/625",
    "sg:postcode":"27239",
    "sg:province":"Niedersachsen",
    "wof:name":"N. Karl",
    "wof:placetype":"venue"
},
  "geometry": {"coordinates":[8.484824,52.768505],"type":"Point"}
}