{
  "type": "Feature",
  "properties": {
    "iso:country":"DE",
    "sg:address":"Frohmestr. 108",
    "sg:city":"Hamburg",
    "sg:phone":"+49 40/5503355",
    "sg:postcode":"22459",
    "sg:province":"Hamburg",
    "wof:name":"J\u00fcrgen Schneemann E. K.",
    "wof:placetype":"venue"
},
  "geometry": {"coordinates":[9.9308872223,53.6289176941],"type":"Point"}
}