{
  "type": "Feature",
  "properties": {
    "iso:country":"DE",
    "sg:address":"Gartenstr. 107",
    "sg:city":"Ravensburg",
    "sg:phone":"+49 751/810",
    "sg:postcode":"88212",
    "sg:province":"Baden-W\u00fcrttemberg",
    "wof:name":"Deutsche Telekom T-punkt",
    "wof:placetype":"venue"
},
  "geometry": {"coordinates":[9.6238460541,47.7935028076],"type":"Point"}
}