{
  "type": "Feature",
  "properties": {
    "iso:country":"DE",
    "sg:address":"N\u00fctzenberger Str. 283",
    "sg:city":"Wuppertal",
    "sg:phone":"+49 202/719550",
    "sg:postcode":"42115",
    "sg:province":"Nordrhein-Westfalen",
    "wof:name":"Heinrich Petry Verwaltungs Gmbh",
    "wof:placetype":"venue"
},
  "geometry": {"coordinates":[7.1143460274,51.2508354187],"type":"Point"}
}