{
  "type": "Feature",
  "properties": {
    "iso:country":"DE",
    "sg:address":"Hauptstr 164",
    "sg:city":"Meuselbach-Schwarzm\u00fchle",
    "sg:phone":"+49 3644/652541",
    "sg:postcode":"98746",
    "sg:province":"Th\u00fcringen",
    "wof:name":"Zm Vakuum Gmbh",
    "wof:placetype":"venue"
},
  "geometry": {"coordinates":[11.087458,50.571217],"type":"Point"}
}