{
  "type": "Feature",
  "properties": {
    "iso:country":"DE",
    "sg:address":"Lange Reihe 12",
    "sg:city":"Burgwedel",
    "sg:phone":"+49 5139/8114",
    "sg:postcode":"30938",
    "sg:province":"Niedersachsen",
    "wof:name":"Thomas R. Walter",
    "wof:placetype":"venue"
},
  "geometry": {"coordinates":[9.9019966125,52.4933700562],"type":"Point"}
}