{
  "type": "Feature",
  "properties": {
    "iso:country":"DE",
    "sg:address":"Hochdahler Str. 126",
    "sg:city":"Haan",
    "sg:postcode":"42781",
    "sg:province":"Nordrhein-Westfalen",
    "wof:name":"Ibc Mobiltechnik",
    "wof:placetype":"venue"
},
  "geometry": {"coordinates":[6.9881649017,51.1931266785],"type":"Point"}
}