{
  "type": "Feature",
  "properties": {
    "iso:country":"DE",
    "sg:address":"Mainstr. 25-29",
    "sg:city":"Neuss",
    "sg:phone":"+49 2137/3787",
    "sg:postcode":"41469",
    "sg:province":"Nordrhein-Westfalen",
    "wof:name":"Gelria Food Group Gmbh",
    "wof:placetype":"venue"
},
  "geometry": {"coordinates":[6.7448840141,51.1513938904],"type":"Point"}
}