{
  "type": "Feature",
  "properties": {
    "iso:country":"DE",
    "sg:address":"Maxim-Gorki-Str. 12",
    "sg:city":"Halle",
    "sg:phone":"+49 345/5279100",
    "sg:postcode":"06114",
    "sg:province":"Sachsen-Anhalt",
    "wof:name":"Bildungswerk Des Lsb Sachsen-anhalt",
    "wof:placetype":"venue"
},
  "geometry": {"coordinates":[11.9716682434,51.4965705872],"type":"Point"}
}