{
  "type": "Feature",
  "properties": {
    "iso:country":"DE",
    "sg:address":"Sudberger Str. 51b",
    "sg:city":"Wuppertal",
    "sg:phone":"+49 202/470793",
    "sg:postcode":"42349",
    "sg:province":"Nordrhein-Westfalen",
    "wof:name":"Wolfgang Und Andrea M\u00f6ller Graphiker-designer",
    "wof:placetype":"venue"
},
  "geometry": {"coordinates":[7.13487,51.175613],"type":"Point"}
}