{
  "type": "Feature",
  "properties": {
    "iso:country":"DE",
    "sg:address":"Eichenrieder Str. 5",
    "sg:city":"Kalbach",
    "sg:phone":"+49 9742/365",
    "sg:postcode":"36148",
    "sg:province":"Hessen",
    "wof:name":"Helmut M\u00fcller",
    "wof:placetype":"venue"
},
  "geometry": {"coordinates":[9.670989,50.403255],"type":"Point"}
}