{
  "type": "Feature",
  "properties": {
    "iso:country":"DE",
    "sg:address":"M\u00fcnchhof 4",
    "sg:city":"Dannstadt-Schauernheim",
    "sg:phone":"+49 4962/3191433",
    "sg:postcode":"67125",
    "sg:province":"Rheinland-Pfalz",
    "wof:name":"Bernhard Hery",
    "wof:placetype":"venue"
},
  "geometry": {"coordinates":[8.318915,49.414055],"type":"Point"}
}