{
  "type": "Feature",
  "properties": {
    "iso:country":"DE",
    "sg:address":"Untere Zahlbacher Str. 68",
    "sg:city":"Mainz",
    "sg:phone":"+49 6131/934660",
    "sg:postcode":"55131",
    "sg:province":"Rheinland-Pfalz",
    "wof:name":"Stiftung Mainzer Blindenwerk",
    "wof:placetype":"venue"
},
  "geometry": {"coordinates":[8.2534503937,49.9958343506],"type":"Point"}
}