{
  "type": "Feature",
  "properties": {
    "iso:country":"DE",
    "sg:address":"Triebstr. 14",
    "sg:city":"M\u00fcnchen",
    "sg:phone":"+49 89/14987690",
    "sg:postcode":"80993",
    "sg:province":"Bayern",
    "wof:name":"Kaut-bullinger & Co.",
    "wof:placetype":"venue"
},
  "geometry": {"coordinates":[11.529147,48.187119],"type":"Point"}
}