{
  "type": "Feature",
  "properties": {
    "iso:country":"DE",
    "sg:address":"Gografenweg 8",
    "sg:city":"Borken",
    "sg:phone":"+49 2861/604196",
    "sg:postcode":"46325",
    "sg:province":"Nordrhein-Westfalen",
    "wof:name":"R. Bruland",
    "wof:placetype":"venue"
},
  "geometry": {"coordinates":[6.8465518951,51.844707489],"type":"Point"}
}