{
  "type": "Feature",
  "properties": {
    "iso:country":"DE",
    "sg:address":"Westerwaldstr 29",
    "sg:city":"Burbach",
    "sg:phone":"+49 2661/7044",
    "sg:postcode":"57299",
    "sg:province":"Nordrhein-Westfalen",
    "wof:name":"Wemano-polsterm\u00f6belfabrik Kurt Kr\u00fcger Gmbh",
    "wof:placetype":"venue"
},
  "geometry": {"coordinates":[8.1393003464,50.7280540466],"type":"Point"}
}