{
  "type": "Feature",
  "properties": {
    "iso:country":"DE",
    "sg:address":"Sonnenstr. 16",
    "sg:city":"Brand",
    "sg:phone":"+49 9236/1733",
    "sg:postcode":"95682",
    "sg:province":"Bayern",
    "wof:name":"Probau Bautr\u00e4ger Gmbh",
    "wof:placetype":"venue"
},
  "geometry": {"coordinates":[11.907264,49.969379],"type":"Point"}
}