{
  "type": "Feature",
  "properties": {
    "iso:country":"DE",
    "sg:address":"Max-Planck-Str 1",
    "sg:city":"Espelkamp",
    "sg:phone":"+49 5772/4797300",
    "sg:postcode":"32339",
    "sg:province":"Nordrhein-Westfalen",
    "wof:name":"Harting Vending Gmbh & Co.kg Elektronische Shop- Und Service-systeme",
    "wof:placetype":"venue"
},
  "geometry": {"coordinates":[8.615289,52.33886],"type":"Point"}
}