{
  "type": "Feature",
  "properties": {
    "iso:country":"DE",
    "sg:address":"Schlo\u00dfbergstr. 5",
    "sg:city":"Neuenburg",
    "sg:phone":"+49 7634/4914",
    "sg:postcode":"79395",
    "sg:province":"Baden-W\u00fcrttemberg",
    "wof:name":"Martin K\u00fcbler",
    "wof:placetype":"venue"
},
  "geometry": {"coordinates":[7.592491,47.877392],"type":"Point"}
}