{
  "type": "Feature",
  "properties": {
    "iso:country":"DE",
    "sg:address":"Siemensstr. 9",
    "sg:city":"Wolfhagen",
    "sg:phone":"+49 4956/9298830",
    "sg:postcode":"34466",
    "sg:province":"Hessen",
    "wof:name":"Gartencenter Bachmann Gmbh",
    "wof:placetype":"venue"
},
  "geometry": {"coordinates":[9.168898,51.33046],"type":"Point"}
}