{
  "type": "Feature",
  "properties": {
    "iso:country":"DE",
    "sg:address":"Postfach 1527",
    "sg:city":"Rehau",
    "sg:phone":"+49 9283/1269",
    "sg:postcode":"95105",
    "sg:province":"Bayern",
    "wof:name":"Freibad",
    "wof:placetype":"venue"
},
  "geometry": {"coordinates":[12.0322599411,50.2473716736],"type":"Point"}
}