{
  "type": "Feature",
  "properties": {
    "iso:country":"DE",
    "sg:address":"Gminderstr. 6",
    "sg:city":"Reutlingen",
    "sg:phone":"+49 7121/339882",
    "sg:postcode":"72762",
    "sg:province":"Baden-W\u00fcrttemberg",
    "wof:name":"Bernd Wurster",
    "wof:placetype":"venue"
},
  "geometry": {"coordinates":[9.2053022385,48.4953308105],"type":"Point"}
}