{
  "type": "Feature",
  "properties": {
    "iso:country":"DE",
    "sg:address":"Gro\u00df Sonnendeich 68",
    "sg:city":"Seester",
    "sg:phone":"+49 4125/592",
    "sg:postcode":"25370",
    "sg:province":"Schleswig-Holstein",
    "wof:name":"Hartmut Poll",
    "wof:placetype":"venue"
},
  "geometry": {"coordinates":[9.584809,53.701851],"type":"Point"}
}