{
  "type": "Feature",
  "properties": {
    "iso:country":"DE",
    "sg:address":"Burger Str. 18",
    "sg:city":"St. Michaelisdonn",
    "sg:phone":"+49 4853/880826",
    "sg:postcode":"25693",
    "sg:province":"Schleswig-Holstein",
    "wof:name":"Imbiss",
    "wof:placetype":"venue"
},
  "geometry": {"coordinates":[9.1169967651,53.993309021],"type":"Point"}
}