{
  "type": "Feature",
  "properties": {
    "iso:country":"DE",
    "sg:address":"Horather Str. 169",
    "sg:city":"Wuppertal",
    "sg:phone":"+49 202/703155",
    "sg:postcode":"42111",
    "sg:province":"Nordrhein-Westfalen",
    "wof:name":"J\u00f6rg K\u00f6pper",
    "wof:placetype":"venue"
},
  "geometry": {"coordinates":[7.161238,51.300758],"type":"Point"}
}