{
  "type": "Feature",
  "properties": {
    "iso:country":"DE",
    "sg:address":"Ernst-Bergeest-Weg 59",
    "sg:city":"Hamburg",
    "sg:phone":"+49 40/7602786",
    "sg:postcode":"21077",
    "sg:province":"Hamburg",
    "wof:name":"Peter Becker",
    "wof:placetype":"venue"
},
  "geometry": {"coordinates":[9.960005,53.44054],"type":"Point"}
}