{
  "type": "Feature",
  "properties": {
    "iso:country":"DE",
    "sg:address":"Enggasse 9",
    "sg:city":"Nieder-Olm",
    "sg:phone":"+49 6136/7001",
    "sg:postcode":"55268",
    "sg:province":"Rheinland-Pfalz",
    "wof:name":"Johann Staffa Masseur",
    "wof:placetype":"venue"
},
  "geometry": {"coordinates":[8.201149,49.909325],"type":"Point"}
}