{
  "type": "Feature",
  "properties": {
    "iso:country":"DE",
    "sg:address":"Buchwaldstr. 17",
    "sg:city":"Eisenh\u00fcttenstadt",
    "sg:phone":"+49 3364/411578",
    "sg:postcode":"15890",
    "sg:province":"Brandenburg",
    "wof:name":"Igp Ingenieurgesellschaft G\u00e4bges & Partner Mbh",
    "wof:placetype":"venue"
},
  "geometry": {"coordinates":[14.6886377335,52.1569747925],"type":"Point"}
}