{
  "type": "Feature",
  "properties": {
    "iso:country":"DE",
    "sg:address":"Gew\u00e4hrhau",
    "sg:city":"J\u00fclich",
    "sg:phone":"+49 2461/2724",
    "sg:postcode":"52428",
    "sg:province":"Nordrhein-Westfalen",
    "wof:name":"H. P. Wachten",
    "wof:placetype":"venue"
},
  "geometry": {"coordinates":[6.378742,50.931454],"type":"Point"}
}