{
  "type": "Feature",
  "properties": {
    "iso:country":"DE",
    "sg:address":"S\u00fcltstr. 30",
    "sg:city":"Berlin",
    "sg:phone":"+49 30/4247025",
    "sg:postcode":"10409",
    "sg:province":"Berlin",
    "wof:name":"Dr. Med. J\u00fcrg. Wendler",
    "wof:placetype":"venue"
},
  "geometry": {"coordinates":[13.431593,52.547043],"type":"Point"}
}