{
  "type": "Feature",
  "properties": {
    "iso:country":"DE",
    "sg:address":"Leipziger Str. 19",
    "sg:city":"Berlin",
    "sg:phone":"+49 30/2012054",
    "sg:postcode":"10117",
    "sg:province":"Berlin",
    "wof:name":"Kubrat",
    "wof:placetype":"venue"
},
  "geometry": {"coordinates":[13.3773078918,52.5100708008],"type":"Point"}
}