{
  "type": "Feature",
  "properties": {
    "iso:country":"DE",
    "sg:address":"Goethestr. 63",
    "sg:city":"Rathenow",
    "sg:phone":"+49 3385/510909",
    "sg:postcode":"14712",
    "sg:province":"Brandenburg",
    "wof:name":"Restaurant Weinkeller",
    "wof:placetype":"venue"
},
  "geometry": {"coordinates":[12.3459568024,52.6102371216],"type":"Point"}
}