{
  "type": "Feature",
  "properties": {
    "iso:country":"DE",
    "sg:address":"Kasseler Str. 2",
    "sg:city":"Wolfhagen",
    "sg:phone":"+49 5692/2043",
    "sg:postcode":"34466",
    "sg:province":"Hessen",
    "wof:name":"Manfred Alheidt",
    "wof:placetype":"venue"
},
  "geometry": {"coordinates":[9.240999,51.302696],"type":"Point"}
}