{
  "type": "Feature",
  "properties": {
    "iso:country":"DE",
    "sg:address":"Landwehr 34",
    "sg:city":"Ganderkesee",
    "sg:phone":"+49 4222/2254",
    "sg:postcode":"27777",
    "sg:province":"Niedersachsen",
    "wof:name":"Johann Schmidt",
    "wof:placetype":"venue"
},
  "geometry": {"coordinates":[8.558214,53.005512],"type":"Point"}
}