{
  "type": "Feature",
  "properties": {
    "iso:country":"DE",
    "sg:address":"Nymphenburger Str. 162",
    "sg:city":"M\u00fcnchen",
    "sg:phone":"+49 89/1689241",
    "sg:postcode":"80634",
    "sg:province":"Bayern",
    "wof:name":"Jagdschl\u00f6ssl",
    "wof:placetype":"venue"
},
  "geometry": {"coordinates":[11.5334968567,48.1532897949],"type":"Point"}
}