{
  "type": "Feature",
  "properties": {
    "iso:country":"DE",
    "sg:address":"Schlesische Str. 2",
    "sg:city":"Berlin",
    "sg:phone":"+49 30/6126962",
    "sg:postcode":"10997",
    "sg:province":"Berlin",
    "wof:name":"Bagdad",
    "wof:placetype":"venue"
},
  "geometry": {"coordinates":[13.4424705505,52.500629425],"type":"Point"}
}