{
  "type": "Feature",
  "properties": {
    "iso:country":"DE",
    "sg:address":"Sterzenbach 55",
    "sg:city":"Hohenfels",
    "sg:phone":"+49 9472/377",
    "sg:postcode":"92366",
    "sg:province":"Bayern",
    "wof:name":"F. Lassleben Elektroinstallation",
    "wof:placetype":"venue"
},
  "geometry": {"coordinates":[11.853054,49.203346],"type":"Point"}
}