{
  "type": "Feature",
  "properties": {
    "iso:country":"DE",
    "sg:address":"Heilig-Grab-Gasse 4",
    "sg:city":"Augsburg",
    "sg:postcode":"86150",
    "sg:province":"Bayern",
    "wof:name":"Ics Mode Gmbh & Co. Kg",
    "wof:placetype":"venue"
},
  "geometry": {"coordinates":[10.9003782272,48.3647346497],"type":"Point"}
}