{
  "type": "Feature",
  "properties": {
    "iso:country":"DE",
    "sg:address":"Dammelhof",
    "sg:city":"Gersfeld",
    "sg:phone":"+49 6656/307",
    "sg:postcode":"36129",
    "sg:province":"Hessen",
    "wof:name":"Ev. Pfarramt Dalherda",
    "wof:placetype":"venue"
},
  "geometry": {"coordinates":[9.9408664703,50.4351577759],"type":"Point"}
}