{
  "type": "Feature",
  "properties": {
    "iso:country":"DE",
    "sg:address":"Hackhausen 16",
    "sg:city":"J\u00fcchen",
    "sg:phone":"+49 2165/911050",
    "sg:postcode":"41363",
    "sg:province":"Nordrhein-Westfalen",
    "wof:name":"Yamaha-zweirad",
    "wof:placetype":"venue"
},
  "geometry": {"coordinates":[6.473657,51.105057],"type":"Point"}
}