{
  "type": "Feature",
  "properties": {
    "iso:country":"DE",
    "sg:address":"Herrenm\u00fchle 1",
    "sg:city":"Adelberg",
    "sg:phone":"+49 7166/1329",
    "sg:postcode":"73099",
    "sg:province":"Baden-W\u00fcrttemberg",
    "wof:name":"Gastst\u00e4tte K.-e. Frasch",
    "wof:placetype":"venue"
},
  "geometry": {"coordinates":[9.5984830856,48.7539825439],"type":"Point"}
}