{
  "type": "Feature",
  "properties": {
    "iso:country":"DE",
    "sg:address":"Mindener Str. 79",
    "sg:city":"Herford",
    "sg:phone":"+49 5221/21919",
    "sg:postcode":"32049",
    "sg:province":"Nordrhein-Westfalen",
    "wof:name":"R. G. Kloss",
    "wof:placetype":"venue"
},
  "geometry": {"coordinates":[8.684056282,52.1257781982],"type":"Point"}
}