{
  "type": "Feature",
  "properties": {
    "iso:country":"DE",
    "sg:address":"Frans-Hals-Weg 30",
    "sg:city":"Magdeburg",
    "sg:phone":"+49 391/7220662",
    "sg:postcode":"39128",
    "sg:province":"Sachsen-Anhalt",
    "wof:name":"Knot Tief- Und Industriebau Magdeburg Gmbh",
    "wof:placetype":"venue"
},
  "geometry": {"coordinates":[11.595687,52.148479],"type":"Point"}
}