{
  "type": "Feature",
  "properties": {
    "iso:country":"DE",
    "sg:address":"Steilshooper Allee 53",
    "sg:city":"Hamburg",
    "sg:phone":"+49 40/6320070",
    "sg:postcode":"22309",
    "sg:province":"Hamburg",
    "wof:name":"Ingenieurgruppe Hsp",
    "wof:placetype":"venue"
},
  "geometry": {"coordinates":[10.0519323349,53.6086997986],"type":"Point"}
}