{
  "type": "Feature",
  "properties": {
    "iso:country":"DE",
    "sg:address":"Blumenstr. 34",
    "sg:city":"Nordhalben",
    "sg:phone":"+49 9267/1614",
    "sg:postcode":"96365",
    "sg:province":"Bayern",
    "wof:name":"M. Und I. Mohler",
    "wof:placetype":"venue"
},
  "geometry": {"coordinates":[11.509004,50.369034],"type":"Point"}
}