{
  "type": "Feature",
  "properties": {
    "iso:country":"DE",
    "sg:address":"M\u00fchlstra\u00dfe 4",
    "sg:city":"Reinheim",
    "sg:phone":"+49 6162",
    "sg:postcode":"64354",
    "sg:province":"Hessen",
    "wof:name":"Werbeagentur Diva - Darmstadt/hessen",
    "wof:placetype":"venue"
},
  "geometry": {"coordinates":[8.826669,49.84129],"type":"Point"}
}