{
  "type": "Feature",
  "properties": {
    "iso:country":"DE",
    "sg:address":"Boschstr. 19",
    "sg:city":"Berglen",
    "sg:phone":"+49 7195/7826",
    "sg:postcode":"73663",
    "sg:province":"Baden-W\u00fcrttemberg",
    "wof:name":"Bewa Rohrhalterungen Gmbh",
    "wof:placetype":"venue"
},
  "geometry": {"coordinates":[9.44859,48.847179],"type":"Point"}
}