{
  "type": "Feature",
  "properties": {
    "iso:country":"DE",
    "sg:address":"Hermann-L\u00f6ns-Str. 82",
    "sg:city":"Zirndorf",
    "sg:phone":"+49 911/606494",
    "sg:postcode":"90513",
    "sg:province":"Bayern",
    "wof:name":"Fotodesign Eberhardt",
    "wof:placetype":"venue"
},
  "geometry": {"coordinates":[10.9674968719,49.4486160278],"type":"Point"}
}