{
  "type": "Feature",
  "properties": {
    "iso:country":"DE",
    "sg:address":"Bregstr. 6",
    "sg:city":"Furtwangen",
    "sg:phone":"+49 7723/2937",
    "sg:postcode":"78120",
    "sg:province":"Baden-W\u00fcrttemberg",
    "wof:name":"J. Popp",
    "wof:placetype":"venue"
},
  "geometry": {"coordinates":[8.202544,48.04916],"type":"Point"}
}