{
  "type": "Feature",
  "properties": {
    "iso:country":"DE",
    "sg:address":"Goethestr. 9",
    "sg:city":"Hankensb\u00fcttel",
    "sg:phone":"+49 5832/1751",
    "sg:postcode":"29386",
    "sg:province":"Niedersachsen",
    "wof:name":"Hans-henning Rehwinkel Rechtsanwalt Und Notar",
    "wof:placetype":"venue"
},
  "geometry": {"coordinates":[10.6109647751,52.7276649475],"type":"Point"}
}