{
  "type": "Feature",
  "properties": {
    "iso:country":"DE",
    "sg:address":"Im Forst 10",
    "sg:city":"K\u00f6ln",
    "sg:phone":"+49 221/983770",
    "sg:postcode":"51105",
    "sg:province":"Nordrhein-Westfalen",
    "wof:name":"Barbara E. Sch\u00e4fer Immobilienmaklerin",
    "wof:placetype":"venue"
},
  "geometry": {"coordinates":[6.9989881516,50.914730072],"type":"Point"}
}