{
  "type": "Feature",
  "properties": {
    "iso:country":"DE",
    "sg:address":"Arnsdorfer Str. 3",
    "sg:city":"Guteborn",
    "sg:phone":"+49 35752/5124",
    "sg:postcode":"01945",
    "sg:province":"Brandenburg",
    "wof:name":"At Landmaschinen Handels Gmbh",
    "wof:placetype":"venue"
},
  "geometry": {"coordinates":[13.914502,51.426971],"type":"Point"}
}