{
  "type": "Feature",
  "properties": {
    "iso:country":"DE",
    "sg:address":"Fischbachstr. 119",
    "sg:city":"Stolberg",
    "sg:phone":"+49 2402/71661",
    "sg:postcode":"52224",
    "sg:province":"Nordrhein-Westfalen",
    "wof:name":"Robert Fleischmann Architekt",
    "wof:placetype":"venue"
},
  "geometry": {"coordinates":[6.27626,50.738651],"type":"Point"}
}