{
  "type": "Feature",
  "properties": {
    "iso:country":"DE",
    "sg:address":"Hauptstr. 65",
    "sg:city":"Schwelm",
    "sg:phone":"+49 2336/3510",
    "sg:postcode":"58332",
    "sg:province":"Nordrhein-Westfalen",
    "wof:name":"Blumen-basar Overkott Gmbh",
    "wof:placetype":"venue"
},
  "geometry": {"coordinates":[7.29523,51.284832],"type":"Point"}
}