{
  "type": "Feature",
  "properties": {
    "iso:country":"DE",
    "sg:address":"Gro\u00dfe Hohl 4",
    "sg:city":"Obrigheim",
    "sg:phone":"+49 6359/8980",
    "sg:postcode":"67283",
    "sg:province":"Rheinland-Pfalz",
    "wof:name":"Pro Seniore Residenz Rosengarten",
    "wof:placetype":"venue"
},
  "geometry": {"coordinates":[8.201901,49.590828],"type":"Point"}
}