{
  "type": "Feature",
  "properties": {
    "iso:country":"DE",
    "sg:address":"Crawinkler Str. 8",
    "sg:city":"Oberhof",
    "sg:phone":"+49 36842/22456",
    "sg:postcode":"98559",
    "sg:province":"Th\u00fcringen",
    "wof:name":"Hartmut Werner",
    "wof:placetype":"venue"
},
  "geometry": {"coordinates":[10.724964,50.707741],"type":"Point"}
}