{
  "type": "Feature",
  "properties": {
    "iso:country":"DE",
    "sg:address":"Birgen 3",
    "sg:city":"Schwalmtal",
    "sg:postcode":"41366",
    "sg:province":"Nordrhein-Westfalen",
    "wof:name":"Las Vegas Spiel- Und Unterhaltungs Gmbh",
    "wof:placetype":"venue"
},
  "geometry": {"coordinates":[6.289248,51.22501],"type":"Point"}
}