{
  "type": "Feature",
  "properties": {
    "iso:country":"DE",
    "sg:address":"Leipziger Str. 50",
    "sg:city":"Markranst\u00e4dt",
    "sg:phone":"+49 34205/65920",
    "sg:postcode":"04420",
    "sg:province":"Sachsen",
    "wof:name":"Thomas Hauck Dekorationsmalerei Gmbh",
    "wof:placetype":"venue"
},
  "geometry": {"coordinates":[12.225755,51.305908],"type":"Point"}
}