{
  "type": "Feature",
  "properties": {
    "iso:country":"DE",
    "sg:address":"Naumburger Str. 29",
    "sg:city":"Klosterh\u00e4seler",
    "sg:postcode":"06647",
    "sg:province":"Sachsen-Anhalt",
    "wof:name":"Schlo\u00dfgut Kloster- H\u00e4seler Agrar Eg",
    "wof:placetype":"venue"
},
  "geometry": {"coordinates":[11.606695,51.161777],"type":"Point"}
}