{
  "type": "Feature",
  "properties": {
    "iso:country":"DE",
    "sg:address":"Promenadenstr. 6-12",
    "sg:city":"Bensheim",
    "sg:phone":"+49 6251/581956",
    "sg:postcode":"64625",
    "sg:province":"Hessen",
    "wof:name":"Mobil Star Bensheim Gmbh",
    "wof:placetype":"venue"
},
  "geometry": {"coordinates":[8.6198797226,49.6803817749],"type":"Point"}
}