{
  "type": "Feature",
  "properties": {
    "iso:country":"DE",
    "sg:address":"R\u00f6dder 32",
    "sg:city":"D\u00fclmen",
    "sg:phone":"+49 2594/99689",
    "sg:postcode":"48249",
    "sg:province":"Nordrhein-Westfalen",
    "wof:name":"Anton Reher Steuerberater",
    "wof:placetype":"venue"
},
  "geometry": {"coordinates":[7.3213768005,51.8336181641],"type":"Point"}
}