{
  "type": "Feature",
  "properties": {
    "iso:country":"DE",
    "sg:address":"Bernhard-Vo\u00df-Str. 25-27",
    "sg:city":"Radebeul",
    "sg:phone":"+49 351/8302915",
    "sg:postcode":"01445",
    "sg:province":"Sachsen",
    "wof:name":"Medizin- Und Labortechnik Engineering Gmbh",
    "wof:placetype":"venue"
},
  "geometry": {"coordinates":[13.643456459,51.1051521301],"type":"Point"}
}