{
  "type": "Feature",
  "properties": {
    "iso:country":"DE",
    "sg:address":"Philadelphiastr. 147",
    "sg:city":"Krefeld",
    "sg:phone":"+49 2151/606874",
    "sg:postcode":"47799",
    "sg:province":"Nordrhein-Westfalen",
    "wof:name":"Planteam Haus- Und Wohnungsbauges. Mbh",
    "wof:placetype":"venue"
},
  "geometry": {"coordinates":[6.571841,51.334175],"type":"Point"}
}