{
  "type": "Feature",
  "properties": {
    "iso:country":"DE",
    "sg:address":"Mittelweg 8",
    "sg:city":"Witzenhausen",
    "sg:phone":"+49 5545/1538",
    "sg:postcode":"37217",
    "sg:province":"Hessen",
    "wof:name":"Hermann B\u00f6decker",
    "wof:placetype":"venue"
},
  "geometry": {"coordinates":[9.7520914078,51.3638000488],"type":"Point"}
}