{
  "type": "Feature",
  "properties": {
    "iso:country":"DE",
    "sg:address":"Rote Str. 15 a",
    "sg:city":"Flensburg",
    "sg:phone":"+49 461/24132",
    "sg:postcode":"24937",
    "sg:province":"Schleswig-Holstein",
    "wof:name":"Karl-heinz Buse",
    "wof:placetype":"venue"
},
  "geometry": {"coordinates":[9.4360609055,54.7816123962],"type":"Point"}
}