{
  "type": "Feature",
  "properties": {
    "iso:country":"DE",
    "sg:address":"Am Riesenstein 16",
    "sg:city":"Dahlenburg",
    "sg:phone":"+49 5851/1485",
    "sg:postcode":"21368",
    "sg:province":"Niedersachsen",
    "wof:name":"G\u00e4stehaus M\u00fcller",
    "wof:placetype":"venue"
},
  "geometry": {"coordinates":[10.7552986145,53.1855239868],"type":"Point"}
}