{
  "type": "Feature",
  "properties": {
    "iso:country":"DE",
    "sg:address":"Halligweg 8",
    "sg:city":"Husum",
    "sg:phone":"+49 4841/9567",
    "sg:postcode":"25813",
    "sg:province":"Schleswig-Holstein",
    "wof:name":"Windenergie Consulting Gmbh",
    "wof:placetype":"venue"
},
  "geometry": {"coordinates":[9.07575,54.480343],"type":"Point"}
}