{
  "type": "Feature",
  "properties": {
    "iso:country":"DE",
    "sg:address":"Nonnenplan 2",
    "sg:city":"Jena",
    "sg:postcode":"07743",
    "sg:province":"Th\u00fcringen",
    "wof:name":"Depuy-biotech Jena Gmbh",
    "wof:placetype":"venue"
},
  "geometry": {"coordinates":[11.5853948593,50.9271850586],"type":"Point"}
}