{
  "type": "Feature",
  "properties": {
    "iso:country":"DE",
    "sg:address":"Hauptstr. 11",
    "sg:city":"Neunburg",
    "sg:phone":"+49 9672/1302",
    "sg:postcode":"92431",
    "sg:province":"Bayern",
    "wof:name":"Otto Baumg\u00e4rtner Haus- Und K\u00fcchenger\u00e4te",
    "wof:placetype":"venue"
},
  "geometry": {"coordinates":[12.3839235306,49.349407196],"type":"Point"}
}