{
  "type": "Feature",
  "properties": {
    "iso:country":"DE",
    "sg:address":"Mozartweg 18",
    "sg:city":"Bad Sch\u00f6nborn",
    "sg:phone":"+49 7253/31520",
    "sg:postcode":"76669",
    "sg:province":"Baden-W\u00fcrttemberg",
    "wof:name":"Franz Scherer",
    "wof:placetype":"venue"
},
  "geometry": {"coordinates":[8.6480312347,49.1984481812],"type":"Point"}
}