{
  "type": "Feature",
  "properties": {
    "iso:country":"DE",
    "sg:address":"Hohenhorster Chaussee 13",
    "sg:city":"Haselau",
    "sg:phone":"+49 4129/259",
    "sg:postcode":"25489",
    "sg:province":"Schleswig-Holstein",
    "wof:name":"H. Brauer",
    "wof:placetype":"venue"
},
  "geometry": {"coordinates":[9.5654096603,53.6495742798],"type":"Point"}
}