{
  "type": "Feature",
  "properties": {
    "iso:country":"DE",
    "sg:address":"Saalburgstr. 155",
    "sg:city":"Bad Homburg",
    "sg:phone":"+49 6172/964300",
    "sg:postcode":"61350",
    "sg:province":"Hessen",
    "wof:name":"Mc Market Research Gmbh",
    "wof:placetype":"venue"
},
  "geometry": {"coordinates":[8.5632095337,50.2504310608],"type":"Point"}
}