{
  "type": "Feature",
  "properties": {
    "iso:country":"DE",
    "sg:address":"Brunnenstr. 6",
    "sg:city":"Mintraching",
    "sg:phone":"+49 9406/2933",
    "sg:postcode":"93098",
    "sg:province":"Bayern",
    "wof:name":"Gasthaus Goldener Krug",
    "wof:placetype":"venue"
},
  "geometry": {"coordinates":[12.2874679565,48.9243812561],"type":"Point"}
}