{
  "type": "Feature",
  "properties": {
    "iso:country":"DE",
    "sg:address":"Wiescheider Str. 14",
    "sg:city":"Neunkirchen-Seelscheid",
    "sg:phone":"+49 2247/912920",
    "sg:postcode":"53819",
    "sg:province":"Nordrhein-Westfalen",
    "wof:name":"Rkn Bautenschutz Gmbh",
    "wof:placetype":"venue"
},
  "geometry": {"coordinates":[7.3366370201,50.8434753418],"type":"Point"}
}