{
  "type": "Feature",
  "properties": {
    "iso:country":"DE",
    "sg:address":"Hauptstra\u00dfe 22",
    "sg:city":"Neukirch",
    "sg:postcode":"01904",
    "sg:province":"Sachsen",
    "wof:name":"Ralph Schaeffer, Neukirch(lausitz)",
    "wof:placetype":"venue"
},
  "geometry": {"coordinates":[14.316327,51.093853],"type":"Point"}
}