{
  "type": "Feature",
  "properties": {
    "iso:country":"DE",
    "sg:address":"Chiemseestr. 10",
    "sg:city":"Traunstein",
    "sg:postcode":"83278",
    "sg:province":"Bayern",
    "wof:name":"Aktiv-markt",
    "wof:placetype":"venue"
},
  "geometry": {"coordinates":[12.6301050186,47.8672790527],"type":"Point"}
}