{
  "type": "Feature",
  "properties": {
    "iso:country":"DE",
    "sg:address":"Eldering 57",
    "sg:city":"Steinkirchen",
    "sg:phone":"+49 8084/1273",
    "sg:postcode":"84439",
    "sg:province":"Bayern",
    "wof:name":"Johann Angermeier",
    "wof:placetype":"venue"
},
  "geometry": {"coordinates":[12.1052799225,48.3544998169],"type":"Point"}
}