{
  "type": "Feature",
  "properties": {
    "iso:country":"DE",
    "sg:address":"Carumer Dorfstr. 12a",
    "sg:city":"Bakum",
    "sg:postcode":"49456",
    "sg:province":"Niedersachsen",
    "wof:name":"L. Vossmann",
    "wof:placetype":"venue"
},
  "geometry": {"coordinates":[8.113098,52.70686],"type":"Point"}
}