{
  "type": "Feature",
  "properties": {
    "iso:country":"DE",
    "sg:address":"Im Hammereisen 12 Nuetterden",
    "sg:city":"Kranenburg",
    "sg:phone":"+49 4928/261079",
    "sg:postcode":"47559",
    "sg:province":"Nordrhein-Westfalen",
    "wof:name":"Herbert Janhsen Gmbh",
    "wof:placetype":"venue"
},
  "geometry": {"coordinates":[6.01382,51.787479],"type":"Point"}
}