{
  "type": "Feature",
  "properties": {
    "iso:country":"DE",
    "sg:address":"Heinrich-Mann-Str. 19a",
    "sg:city":"Bad Liebenstein",
    "sg:phone":"+49 36961/31669",
    "sg:postcode":"36448",
    "sg:province":"Th\u00fcringen",
    "wof:name":"Frank Eberlein",
    "wof:placetype":"venue"
},
  "geometry": {"coordinates":[10.3517599106,50.8131752014],"type":"Point"}
}