{
  "type": "Feature",
  "properties": {
    "iso:country":"DE",
    "sg:address":"M\u00f6rfelder Landstr. 112",
    "sg:city":"Frankfurt",
    "sg:phone":"+49 69/613625",
    "sg:postcode":"60598",
    "sg:province":"Hessen",
    "wof:name":"Horst Ziegenfusz",
    "wof:placetype":"venue"
},
  "geometry": {"coordinates":[8.6822977066,50.0957298279],"type":"Point"}
}