{
  "type": "Feature",
  "properties": {
    "iso:country":"DE",
    "sg:address":"Markt 19",
    "sg:city":"Dornburg",
    "sg:phone":"+49 36427/22529",
    "sg:postcode":"07778",
    "sg:province":"Th\u00fcringen",
    "wof:name":"Lebensmittelgesch\u00e4ft Weischner",
    "wof:placetype":"venue"
},
  "geometry": {"coordinates":[11.665389061,51.006729126],"type":"Point"}
}