{
  "type": "Feature",
  "properties": {
    "iso:country":"DE",
    "sg:address":"Neckarstr. 20",
    "sg:city":"Obrigheim",
    "sg:phone":"+49 4962/616380",
    "sg:postcode":"74847",
    "sg:province":"Baden-W\u00fcrttemberg",
    "wof:name":"Mb Quart Gmbh",
    "wof:placetype":"venue"
},
  "geometry": {"coordinates":[9.09902,49.34988],"type":"Point"}
}