{
  "type": "Feature",
  "properties": {
    "iso:country":"DE",
    "sg:address":"Stendaler Str. 34",
    "sg:city":"Osterburg",
    "sg:postcode":"39606",
    "sg:province":"Sachsen-Anhalt",
    "wof:name":"Ivv Immobilien- Und Verm\u00f6gensverwaltungsges. Mbh",
    "wof:placetype":"venue"
},
  "geometry": {"coordinates":[11.7551527023,52.7850189209],"type":"Point"}
}