{
  "type": "Feature",
  "properties": {
    "iso:country":"DE",
    "sg:address":"Schafhof 18",
    "sg:city":"Hallstadt",
    "sg:phone":"+49 951/73635",
    "sg:postcode":"96103",
    "sg:province":"Bayern",
    "wof:name":"Kaspar Feulner",
    "wof:placetype":"venue"
},
  "geometry": {"coordinates":[10.886487,49.928314],"type":"Point"}
}