{
  "type": "Feature",
  "properties": {
    "iso:country":"DE",
    "sg:address":"Syker Str. 110",
    "sg:city":"Delmenhorst",
    "sg:postcode":"27751",
    "sg:province":"Niedersachsen",
    "wof:name":"E & E Logistik-agrar-handel- Dienstleistungs Gmbh",
    "wof:placetype":"venue"
},
  "geometry": {"coordinates":[8.6572389603,53.0493774414],"type":"Point"}
}