{
  "type": "Feature",
  "properties": {
    "iso:country":"DE",
    "sg:address":"Habichtsberger Str. 22",
    "sg:city":"Kalletal",
    "sg:phone":"+49 5264/8922",
    "sg:postcode":"32689",
    "sg:province":"Nordrhein-Westfalen",
    "wof:name":"Laue",
    "wof:placetype":"venue"
},
  "geometry": {"coordinates":[8.964091,52.140163],"type":"Point"}
}