{
  "type": "Feature",
  "properties": {
    "iso:country":"DE",
    "sg:address":"Erlerring 6",
    "sg:city":"Hamburg",
    "sg:phone":"+49 40/75061224",
    "sg:postcode":"21109",
    "sg:province":"Hamburg",
    "wof:name":"G\u00fcnaytekin Bau Gmbh",
    "wof:placetype":"venue"
},
  "geometry": {"coordinates":[10.0200185776,53.485244751],"type":"Point"}
}