{
  "type": "Feature",
  "properties": {
    "iso:country":"DE",
    "sg:address":"Linder Weg 91a",
    "sg:city":"K\u00f6ln",
    "sg:phone":"+49 2203/962240",
    "sg:postcode":"51147",
    "sg:province":"Nordrhein-Westfalen",
    "wof:name":"Labodent Zahntechnik Gmbh",
    "wof:placetype":"venue"
},
  "geometry": {"coordinates":[7.103974,50.852375],"type":"Point"}
}