{
  "type": "Feature",
  "properties": {
    "iso:country":"DE",
    "sg:address":"Dahlienweg 25",
    "sg:city":"Schenefeld",
    "sg:phone":"+49 40/8300463",
    "sg:postcode":"22869",
    "sg:province":"Schleswig-Holstein",
    "wof:name":"Sames Sanit\u00e4rtechnik Gmbh",
    "wof:placetype":"venue"
},
  "geometry": {"coordinates":[9.8496294022,53.604057312],"type":"Point"}
}