{
  "type": "Feature",
  "properties": {
    "iso:country":"DE",
    "sg:address":"Talweg 14",
    "sg:city":"Wittlich",
    "sg:phone":"+49 6571/8849",
    "sg:postcode":"54516",
    "sg:province":"Rheinland-Pfalz",
    "wof:name":"U. Hess",
    "wof:placetype":"venue"
},
  "geometry": {"coordinates":[6.8966631889,49.985660553],"type":"Point"}
}