{
  "type": "Feature",
  "properties": {
    "iso:country":"DE",
    "sg:address":"Fraunhoferstr. 18",
    "sg:city":"Straubing",
    "sg:phone":"+49 9421/2401",
    "sg:postcode":"94315",
    "sg:province":"Bayern",
    "wof:name":"H\u00f6rger\u00e4te Seifert Gmbh",
    "wof:placetype":"venue"
},
  "geometry": {"coordinates":[12.571097374,48.8829536438],"type":"Point"}
}