{
  "type": "Feature",
  "properties": {
    "iso:country":"DE",
    "sg:address":"Kreuzackerstr. 5",
    "sg:city":"Hebertshausen",
    "sg:phone":"+49 8139/6507",
    "sg:postcode":"85241",
    "sg:province":"Bayern",
    "wof:name":"Eduard Bachinger Rechtsanwalt",
    "wof:placetype":"venue"
},
  "geometry": {"coordinates":[11.4849090576,48.3035049438],"type":"Point"}
}