{
  "type": "Feature",
  "properties": {
    "iso:country":"DE",
    "sg:address":"Untergasse 33",
    "sg:city":"Villmar",
    "sg:phone":"+49 6483/7836",
    "sg:postcode":"65606",
    "sg:province":"Hessen",
    "wof:name":"Manfred H\u00f6pp",
    "wof:placetype":"venue"
},
  "geometry": {"coordinates":[8.227594,50.36475],"type":"Point"}
}