{
  "type": "Feature",
  "properties": {
    "iso:country":"DE",
    "sg:address":"Hauptstr. 55",
    "sg:city":"Oberlahr",
    "sg:phone":"+49 2685/95190",
    "sg:postcode":"57641",
    "sg:province":"Rheinland-Pfalz",
    "wof:name":"Hirsch Ohg",
    "wof:placetype":"venue"
},
  "geometry": {"coordinates":[7.509763,50.624214],"type":"Point"}
}