{
  "type": "Feature",
  "properties": {
    "iso:country":"DE",
    "sg:address":"Am Tiergarten 52",
    "sg:city":"Hannover",
    "sg:postcode":"30559",
    "sg:province":"Niedersachsen",
    "wof:name":"E. Luth. Altenwerk St. Martin Anderten E. V.",
    "wof:placetype":"venue"
},
  "geometry": {"coordinates":[9.8469133377,52.3615608215],"type":"Point"}
}