{
  "type": "Feature",
  "properties": {
    "iso:country":"DE",
    "sg:address":"Raiffeisenstr. 5",
    "sg:city":"Laufen",
    "sg:phone":"+49 8682/89850",
    "sg:postcode":"83410",
    "sg:province":"Bayern",
    "wof:name":"Franz Josef Bauer Gmbh",
    "wof:placetype":"venue"
},
  "geometry": {"coordinates":[12.921516,47.936619],"type":"Point"}
}