{
  "type": "Feature",
  "properties": {
    "iso:country":"DE",
    "sg:address":"Sternkamp 32",
    "sg:city":"M\u00fcnster",
    "sg:postcode":"48165",
    "sg:province":"Nordrhein-Westfalen",
    "wof:name":"Alt-katholische Kirchen- Gemeinde St. Johannes",
    "wof:placetype":"venue"
},
  "geometry": {"coordinates":[7.6204681396,51.8961181641],"type":"Point"}
}