{
  "type": "Feature",
  "properties": {
    "iso:country":"DE",
    "sg:address":"Schwabstr. 19",
    "sg:city":"Steinheim",
    "sg:phone":"+49 7329/6041",
    "sg:postcode":"89555",
    "sg:province":"Baden-W\u00fcrttemberg",
    "wof:name":"M\u00f6belhof Ostalb Heinz Krause Gmbh",
    "wof:placetype":"venue"
},
  "geometry": {"coordinates":[10.0742492676,48.6892967224],"type":"Point"}
}