{
  "type": "Feature",
  "properties": {
    "iso:country":"DE",
    "sg:address":"Kilianst\u00e4dter Str. 8",
    "sg:city":"Sch\u00f6neck",
    "sg:phone":"+49 6187/6848",
    "sg:postcode":"61137",
    "sg:province":"Hessen",
    "wof:name":"L. Neumann Masseur",
    "wof:placetype":"venue"
},
  "geometry": {"coordinates":[8.841197,50.214581],"type":"Point"}
}