{
  "type": "Feature",
  "properties": {
    "iso:country":"DE",
    "sg:address":"Heinrich-Heine-Str. 43a",
    "sg:city":"Zeulenroda",
    "sg:phone":"+49 36628/82706",
    "sg:postcode":"07937",
    "sg:province":"Th\u00fcringen",
    "wof:name":"Zeulenrodaer M\u00f6bel Gmbh",
    "wof:placetype":"venue"
},
  "geometry": {"coordinates":[11.99414,50.652996],"type":"Point"}
}