{
  "type": "Feature",
  "properties": {
    "iso:country":"DE",
    "sg:address":"Adolf-Kolping-Str. 1",
    "sg:city":"Donzdorf",
    "sg:phone":"+49 7162/910220",
    "sg:postcode":"73072",
    "sg:province":"Baden-W\u00fcrttemberg",
    "wof:name":"Sotec Gmbh",
    "wof:placetype":"venue"
},
  "geometry": {"coordinates":[9.7950639725,48.6848526001],"type":"Point"}
}