{
  "type": "Feature",
  "properties": {
    "iso:country":"DE",
    "sg:address":"Schulstr. 28",
    "sg:city":"Heeslingen",
    "sg:postcode":"27404",
    "sg:province":"Niedersachsen",
    "wof:name":"Viebrock Daten Service Gmbh",
    "wof:placetype":"venue"
},
  "geometry": {"coordinates":[9.3003110886,53.3480300903],"type":"Point"}
}