{
  "type": "Feature",
  "properties": {
    "iso:country":"DE",
    "sg:address":"Steinbacher Str. 33",
    "sg:city":"Dresden",
    "sg:phone":"+49 351/4212836",
    "sg:postcode":"01157",
    "sg:province":"Sachsen",
    "wof:name":"F. Ke\u00dfler",
    "wof:placetype":"venue"
},
  "geometry": {"coordinates":[13.680855,51.052441],"type":"Point"}
}