{
  "type": "Feature",
  "properties": {
    "iso:country":"DE",
    "sg:address":"Waldstr. 12",
    "sg:city":"Bad Mergentheim",
    "sg:phone":"+49 7931/6050",
    "sg:postcode":"97980",
    "sg:province":"Baden-W\u00fcrttemberg",
    "wof:name":"Dr. Walter Cantner Rechtsanwalt",
    "wof:placetype":"venue"
},
  "geometry": {"coordinates":[9.7844772339,49.5029754639],"type":"Point"}
}