{
  "type": "Feature",
  "properties": {
    "iso:country":"DE",
    "sg:address":"Lautenfelsenstr. 23",
    "sg:city":"Gernsbach",
    "sg:phone":"+49 7224/2602",
    "sg:postcode":"76593",
    "sg:province":"Baden-W\u00fcrttemberg",
    "wof:name":"Pension Sonne",
    "wof:placetype":"venue"
},
  "geometry": {"coordinates":[8.3734426498,48.7545661926],"type":"Point"}
}