{
  "type": "Feature",
  "properties": {
    "iso:country":"DE",
    "sg:address":"Raiffeisenstr. 15",
    "sg:city":"Konz",
    "sg:phone":"+49 6501/3595",
    "sg:postcode":"54329",
    "sg:province":"Rheinland-Pfalz",
    "wof:name":"Prof. Dr. E. Neurath Ingenieur",
    "wof:placetype":"venue"
},
  "geometry": {"coordinates":[6.5918488503,49.7028656006],"type":"Point"}
}