{
  "type": "Feature",
  "properties": {
    "iso:country":"DE",
    "sg:address":"Landwehrstr. 17",
    "sg:city":"Darmstadt",
    "sg:phone":"+49 6151/20160",
    "sg:postcode":"64293",
    "sg:province":"Hessen",
    "wof:name":"Avos",
    "wof:placetype":"venue"
},
  "geometry": {"coordinates":[8.647488,49.877525],"type":"Point"}
}