{
  "type": "Feature",
  "properties": {
    "iso:country":"DE",
    "sg:address":"Lerchenbergstr. 20",
    "sg:city":"Weissach",
    "sg:phone":"+49 7044/32415",
    "sg:postcode":"71287",
    "sg:province":"Baden-W\u00fcrttemberg",
    "wof:name":"H. Saile",
    "wof:placetype":"venue"
},
  "geometry": {"coordinates":[8.9097299576,48.8330116272],"type":"Point"}
}