{
  "type": "Feature",
  "properties": {
    "iso:country":"DE",
    "sg:address":"J\u00e4gerstr. 2",
    "sg:city":"Dortmund",
    "sg:phone":"+49 231/835354",
    "sg:postcode":"44145",
    "sg:province":"Nordrhein-Westfalen",
    "wof:name":"Merhaba",
    "wof:placetype":"venue"
},
  "geometry": {"coordinates":[7.4708957672,51.5211524963],"type":"Point"}
}