{
  "type": "Feature",
  "properties": {
    "iso:country":"DE",
    "sg:address":"Nordh\u00e4user Str. 25",
    "sg:city":"Berga",
    "sg:phone":"+49 34651/32121",
    "sg:postcode":"06536",
    "sg:province":"Sachsen-Anhalt",
    "wof:name":"W. Beischall Steuerberater",
    "wof:placetype":"venue"
},
  "geometry": {"coordinates":[11.0044994354,51.4556999207],"type":"Point"}
}