{
  "type": "Feature",
  "properties": {
    "iso:country":"DE",
    "sg:address":"Bonl\u00e4nder Hauptstr. 62",
    "sg:city":"Filderstadt",
    "sg:phone":"+49 711/7787137",
    "sg:postcode":"70794",
    "sg:province":"Baden-W\u00fcrttemberg",
    "wof:name":"Pizzeria Il Capriccio Inh. Antonio Di Tommaso",
    "wof:placetype":"venue"
},
  "geometry": {"coordinates":[9.2170763016,48.6553840637],"type":"Point"}
}