{
  "type": "Feature",
  "properties": {
    "iso:country":"DE",
    "sg:address":"Etapartstr 1",
    "sg:city":"Tr\u00f6bitz",
    "sg:phone":"+49 35326/9830",
    "sg:postcode":"03253",
    "sg:province":"Brandenburg",
    "wof:name":"Etapart Gmbh",
    "wof:placetype":"venue"
},
  "geometry": {"coordinates":[13.4340209961,51.5968971252],"type":"Point"}
}