{
  "type": "Feature",
  "properties": {
    "iso:country":"DE",
    "sg:address":"Kneippstr. 7",
    "sg:city":"Speyer",
    "sg:phone":"+49 6232/35718",
    "sg:postcode":"67346",
    "sg:province":"Rheinland-Pfalz",
    "wof:name":"Artur Deibert Druckereibedarf",
    "wof:placetype":"venue"
},
  "geometry": {"coordinates":[8.421862,49.330547],"type":"Point"}
}