{
  "type": "Feature",
  "properties": {
    "iso:country":"DE",
    "sg:address":"Biesenstr. 73",
    "sg:city":"Hilden",
    "sg:phone":"+49 2103/40211",
    "sg:postcode":"40724",
    "sg:province":"Nordrhein-Westfalen",
    "wof:name":"Werner Schwarz Rechtsanwalt",
    "wof:placetype":"venue"
},
  "geometry": {"coordinates":[6.9433660507,51.1785545349],"type":"Point"}
}