{
  "type": "Feature",
  "properties": {
    "iso:country":"DE",
    "sg:address":"Hessenstr. 121",
    "sg:city":"W\u00fcrzburg",
    "sg:phone":"+49 931/2877577",
    "sg:postcode":"97078",
    "sg:province":"Bayern",
    "wof:name":"S. Sahyoun",
    "wof:placetype":"venue"
},
  "geometry": {"coordinates":[9.9746255875,49.8129844666],"type":"Point"}
}