{
  "type": "Feature",
  "properties": {
    "iso:country":"DE",
    "sg:address":"Langgasse 37",
    "sg:city":"Albig",
    "sg:phone":"+49 6731/7141",
    "sg:postcode":"55234",
    "sg:province":"Rheinland-Pfalz",
    "wof:name":"O. Jakobs",
    "wof:placetype":"venue"
},
  "geometry": {"coordinates":[8.119369,49.772758],"type":"Point"}
}