{
  "type": "Feature",
  "properties": {
    "iso:country":"DE",
    "sg:address":"Gutenbergstr. 4",
    "sg:city":"Tuttlingen",
    "sg:phone":"+49 7462/2853",
    "sg:postcode":"78532",
    "sg:province":"Baden-W\u00fcrttemberg",
    "wof:name":"Kath. Pfarrb\u00fccherei Leiter Josef Kremer",
    "wof:placetype":"venue"
},
  "geometry": {"coordinates":[8.822175,47.985722],"type":"Point"}
}