{
  "type": "Feature",
  "properties": {
    "iso:country":"DE",
    "sg:address":"Forstweg 19",
    "sg:city":"Oberhaching",
    "sg:phone":"+49 89/6133589",
    "sg:postcode":"82041",
    "sg:province":"Bayern",
    "wof:name":"Alex Kefis",
    "wof:placetype":"venue"
},
  "geometry": {"coordinates":[11.5726356506,48.0289077759],"type":"Point"}
}