{
  "type": "Feature",
  "properties": {
    "iso:country":"DE",
    "sg:address":"Pfarrer-Rudolf-Str. 32",
    "sg:city":"Gau-Algesheim",
    "sg:phone":"+49 6725/2409",
    "sg:postcode":"55435",
    "sg:province":"Rheinland-Pfalz",
    "wof:name":"Klesy & Partners Marketingagentur Gmbh",
    "wof:placetype":"venue"
},
  "geometry": {"coordinates":[8.0148468018,49.9512138367],"type":"Point"}
}