{
  "type": "Feature",
  "properties": {
    "iso:country":"DE",
    "sg:address":"Fuldaer Str. 30",
    "sg:city":"Schl\u00fcchtern",
    "sg:phone":"+49 6661/3284",
    "sg:postcode":"36381",
    "sg:province":"Hessen",
    "wof:name":"Hans-j\u00fcrgen Katzer",
    "wof:placetype":"venue"
},
  "geometry": {"coordinates":[9.524661,50.354996],"type":"Point"}
}