{
  "type": "Feature",
  "properties": {
    "iso:country":"DE",
    "sg:address":"Maybachufer 14-15",
    "sg:city":"Berlin",
    "sg:phone":"+49 30/61286997",
    "sg:postcode":"12047",
    "sg:province":"Berlin",
    "wof:name":"Tic-service",
    "wof:placetype":"venue"
},
  "geometry": {"coordinates":[13.425574,52.494152],"type":"Point"}
}