{
  "type": "Feature",
  "properties": {
    "iso:country":"DE",
    "sg:address":"Otterzhofen 24",
    "sg:city":"Riedenburg",
    "sg:phone":"+49 9442/829",
    "sg:postcode":"93339",
    "sg:province":"Bayern",
    "wof:name":"Ludwig Pollinger",
    "wof:placetype":"venue"
},
  "geometry": {"coordinates":[11.689977,49.006397],"type":"Point"}
}