{
  "type": "Feature",
  "properties": {
    "iso:country":"DE",
    "sg:address":"Hohnhorstweg 24",
    "sg:city":"Lehrte",
    "sg:phone":"+49 5132/4475",
    "sg:postcode":"31275",
    "sg:province":"Niedersachsen",
    "wof:name":"Hallenbad Lehrte",
    "wof:placetype":"venue"
},
  "geometry": {"coordinates":[9.9931602478,52.3806495667],"type":"Point"}
}