{
  "type": "Feature",
  "properties": {
    "iso:country":"DE",
    "sg:address":"Weidenweg 51",
    "sg:city":"berlin",
    "sg:phone":"+49 30/42780530",
    "sg:postcode":"10249",
    "sg:province":"Berlin",
    "wof:name":"Dr. Alfons Sommer",
    "wof:placetype":"venue"
},
  "geometry": {"coordinates":[13.452195,52.51852],"type":"Point"}
}