{
  "type": "Feature",
  "properties": {
    "iso:country":"DE",
    "sg:address":"Paulusstr. 2",
    "sg:city":"Bielefeld",
    "sg:phone":"+49 521/66462",
    "sg:postcode":"33602",
    "sg:province":"Nordrhein-Westfalen",
    "wof:name":"Wilfried Meise",
    "wof:placetype":"venue"
},
  "geometry": {"coordinates":[8.53579,52.026718],"type":"Point"}
}