{
  "type": "Feature",
  "properties": {
    "iso:country":"DE",
    "sg:address":"Am Dorfkrug 5",
    "sg:city":"Todesfelde",
    "sg:phone":"+49 4558/362",
    "sg:postcode":"23826",
    "sg:province":"Schleswig-Holstein",
    "wof:name":"Holger B\u00f6hm",
    "wof:placetype":"venue"
},
  "geometry": {"coordinates":[10.1750125885,53.8913612366],"type":"Point"}
}