{
  "type": "Feature",
  "properties": {
    "iso:country":"DE",
    "sg:address":"Alemannenstr. 28",
    "sg:city":"Niedereschach",
    "sg:phone":"+49 7728/7503",
    "sg:postcode":"78078",
    "sg:province":"Baden-W\u00fcrttemberg",
    "wof:name":"F. Hauser & V. G\u00f6tz Gbr",
    "wof:placetype":"venue"
},
  "geometry": {"coordinates":[8.5185108185,48.1327476501],"type":"Point"}
}