{
  "type": "Feature",
  "properties": {
    "iso:country":"DE",
    "sg:address":"Am Weiherplatz",
    "sg:city":"Linkenbach",
    "sg:phone":"+49 2684/4137",
    "sg:postcode":"56317",
    "sg:province":"Rheinland-Pfalz",
    "wof:name":"Helmut Blum",
    "wof:placetype":"venue"
},
  "geometry": {"coordinates":[7.553363,50.569958],"type":"Point"}
}