{
  "type": "Feature",
  "properties": {
    "iso:country":"DE",
    "sg:address":"Rellinger Str. 64a",
    "sg:city":"Hamburg",
    "sg:postcode":"20257",
    "sg:province":"Hamburg",
    "wof:name":"Crp Konzertagentur Gmbh",
    "wof:placetype":"venue"
},
  "geometry": {"coordinates":[9.9389410019,53.5781288147],"type":"Point"}
}