{
  "type": "Feature",
  "properties": {
    "iso:country":"DE",
    "sg:address":"Denksteinweg 73",
    "sg:city":"Hamburg",
    "sg:phone":"+49 40/6530322",
    "sg:postcode":"22043",
    "sg:province":"Hamburg",
    "wof:name":"Bernhard Siggel",
    "wof:placetype":"venue"
},
  "geometry": {"coordinates":[10.1284284592,53.5685958862],"type":"Point"}
}