{
  "type": "Feature",
  "properties": {
    "iso:country":"DE",
    "sg:address":"51789",
    "sg:city":"Lindlar",
    "sg:postcode":"51789",
    "sg:province":"Nordrhein-Westfalen",
    "wof:name":"Raiffeisenbank Lindlar Eg",
    "wof:placetype":"venue"
},
  "geometry": {"coordinates":[7.35703,51.025669],"type":"Point"}
}