{
  "type": "Feature",
  "properties": {
    "iso:country":"DE",
    "sg:address":"Eisenstr. 41",
    "sg:city":"Bielefeld",
    "sg:phone":"+49 521/45860",
    "sg:postcode":"33649",
    "sg:province":"Nordrhein-Westfalen",
    "wof:name":"Hans Clausen",
    "wof:placetype":"venue"
},
  "geometry": {"coordinates":[8.453209,51.98904],"type":"Point"}
}