{
  "type": "Feature",
  "properties": {
    "iso:country":"DE",
    "sg:address":"Batzdamm 4",
    "sg:city":"Heide",
    "sg:phone":"+49 481/3688",
    "sg:postcode":"25746",
    "sg:province":"Schleswig-Holstein",
    "wof:name":"Vpv Versicherungen R\u00fcdiger Scholtz",
    "wof:placetype":"venue"
},
  "geometry": {"coordinates":[9.1215648651,54.2011833191],"type":"Point"}
}