{
  "type": "Feature",
  "properties": {
    "iso:country":"DE",
    "sg:address":"Staum\u00fchler Str. 180",
    "sg:city":"H\u00f6velhof",
    "sg:postcode":"33161",
    "sg:province":"Nordrhein-Westfalen",
    "wof:name":"Bbr Baurec Baustoff Recycling",
    "wof:placetype":"venue"
},
  "geometry": {"coordinates":[8.700314,51.818195],"type":"Point"}
}