{
  "type": "Feature",
  "properties": {
    "iso:country":"DE",
    "sg:address":"Mozartstr. 7a",
    "sg:city":"Bad Salzungen",
    "sg:phone":"+49 3695/872370",
    "sg:postcode":"36433",
    "sg:province":"Th\u00fcringen",
    "wof:name":"Ralph Freitag",
    "wof:placetype":"venue"
},
  "geometry": {"coordinates":[10.2426052094,50.8124465942],"type":"Point"}
}