{
  "type": "Feature",
  "properties": {
    "iso:country":"DE",
    "sg:address":"Eisenacher Str. 9",
    "sg:city":"Kaltennordheim",
    "sg:phone":"+49 36966/7730",
    "sg:postcode":"36452",
    "sg:province":"Th\u00fcringen",
    "wof:name":"Gk Wolf Beratungsges. Mbh",
    "wof:placetype":"venue"
},
  "geometry": {"coordinates":[10.1553726196,50.6293792725],"type":"Point"}
}