{
  "type": "Feature",
  "properties": {
    "iso:country":"DE",
    "sg:address":"Nr. 34",
    "sg:city":"Boritz",
    "sg:postcode":"01594",
    "sg:province":"Sachsen",
    "wof:name":"Evangelisches Pfarramt Boritz",
    "wof:placetype":"venue"
},
  "geometry": {"coordinates":[13.2890195847,51.2541313171],"type":"Point"}
}