{
  "type": "Feature",
  "properties": {
    "iso:country":"DE",
    "sg:address":"Ringstrasse 2",
    "sg:city":"Hoehenkirchen",
    "sg:phone":"+49 8102/74380",
    "sg:postcode":"85635",
    "sg:province":"Bayern",
    "wof:name":"Meso Products Unternehmensberatung",
    "wof:placetype":"venue"
},
  "geometry": {"coordinates":[-110.17189,31.586281],"type":"Point"}
}