{
  "type": "Feature",
  "properties": {
    "iso:country":"DE",
    "sg:address":"Woppenrieth 7",
    "sg:city":"T\u00e4nnesberg",
    "sg:phone":"+49 9659/483",
    "sg:postcode":"92723",
    "sg:province":"Bayern",
    "wof:name":"Pension H. Bauer",
    "wof:placetype":"venue"
},
  "geometry": {"coordinates":[12.2954330444,49.5652351379],"type":"Point"}
}