{
  "type": "Feature",
  "properties": {
    "iso:country":"DE",
    "sg:address":"Karl-Heine-Str. 39",
    "sg:city":"Leipzig",
    "sg:phone":"+49 341/4011363",
    "sg:postcode":"04229",
    "sg:province":"Sachsen",
    "wof:name":"Cornelia Frisch",
    "wof:placetype":"venue"
},
  "geometry": {"coordinates":[12.3379449844,51.3322792053],"type":"Point"}
}