{
  "type": "Feature",
  "properties": {
    "iso:country":"DE",
    "sg:address":"Kurtalstr. 2",
    "sg:city":"Bad Bergzabern",
    "sg:phone":"+49 4963/437020",
    "sg:postcode":"76887",
    "sg:province":"Rheinland-Pfalz",
    "wof:name":"Volksbank Eg",
    "wof:placetype":"venue"
},
  "geometry": {"coordinates":[7.9906,49.099579],"type":"Point"}
}