{
  "type": "Feature",
  "properties": {
    "iso:country":"DE",
    "sg:address":"Rennstr. 9",
    "sg:city":"Dessau",
    "sg:phone":"+49 340/215490",
    "sg:postcode":"06842",
    "sg:province":"Sachsen-Anhalt",
    "wof:name":"City-service-center Heike Czuja",
    "wof:placetype":"venue"
},
  "geometry": {"coordinates":[12.2434282303,51.8298149109],"type":"Point"}
}