{
  "type": "Feature",
  "properties": {
    "iso:country":"DE",
    "sg:address":"Berliner Platz 24-28",
    "sg:city":"M\u00fcnster",
    "sg:phone":"+49 251/58662",
    "sg:postcode":"48143",
    "sg:province":"Nordrhein-Westfalen",
    "wof:name":"Wolfgang Koch Heilpraktiker",
    "wof:placetype":"venue"
},
  "geometry": {"coordinates":[7.6337127686,51.9560508728],"type":"Point"}
}