{
  "type": "Feature",
  "properties": {
    "iso:country":"DE",
    "sg:address":"Schillerstr. 19-27",
    "sg:city":"Zweibr\u00fccken",
    "sg:phone":"+49 6332/92180",
    "sg:postcode":"66482",
    "sg:province":"Rheinland-Pfalz",
    "wof:name":"Ksd Kransysteme Gmbh",
    "wof:placetype":"venue"
},
  "geometry": {"coordinates":[7.3560218811,49.2498245239],"type":"Point"}
}