{
  "type": "Feature",
  "properties": {
    "iso:country":"DE",
    "sg:address":"Nr. 14",
    "sg:city":"Lagendorf",
    "sg:phone":"+49 39039/305",
    "sg:postcode":"29413",
    "sg:province":"Sachsen-Anhalt",
    "wof:name":"Dietrich Booss",
    "wof:placetype":"venue"
},
  "geometry": {"coordinates":[10.881906,52.752426],"type":"Point"}
}