{
  "type": "Feature",
  "properties": {
    "iso:country":"DE",
    "sg:address":"Karkpad 6",
    "sg:city":"Upgant-Schott",
    "sg:phone":"+49 4934/1392",
    "sg:postcode":"26529",
    "sg:province":"Niedersachsen",
    "wof:name":"Gesa Jordan",
    "wof:placetype":"venue"
},
  "geometry": {"coordinates":[7.2854881287,53.4984436035],"type":"Point"}
}