{
  "type": "Feature",
  "properties": {
    "iso:country":"DE",
    "sg:address":"Otto-Spielmann-Str 5",
    "sg:city":"Halberstadt",
    "sg:phone":"+49 3941/68360",
    "sg:postcode":"38820",
    "sg:province":"Sachsen-Anhalt",
    "wof:name":"Hmw M\u00f6bel Gmbh",
    "wof:placetype":"venue"
},
  "geometry": {"coordinates":[11.060949,51.886681],"type":"Point"}
}