{
  "type": "Feature",
  "properties": {
    "iso:country":"DE",
    "sg:address":"Philipp-Reis-Str. 13",
    "sg:city":"Henstedt-Ulzburg",
    "sg:phone":"+49 4193/892583",
    "sg:postcode":"24558",
    "sg:province":"Schleswig-Holstein",
    "wof:name":"Patriarchi-elektro - Elektroinstallationen",
    "wof:placetype":"venue"
},
  "geometry": {"coordinates":[9.980273,53.765327],"type":"Point"}
}