{
  "type": "Feature",
  "properties": {
    "iso:country":"DE",
    "sg:address":"Thedestra\u00dfe 13-15",
    "sg:city":"Hamburg",
    "sg:phone":"+49 40/311453",
    "sg:postcode":"22767",
    "sg:province":"Hamburg",
    "wof:name":"Die Berater F\u00fcr Marketing & Finanzwesen",
    "wof:placetype":"venue"
},
  "geometry": {"coordinates":[9.948884,53.552292],"type":"Point"}
}