{
  "type": "Feature",
  "properties": {
    "iso:country":"DE",
    "sg:address":"Probststr. 18",
    "sg:city":"Friedberg",
    "sg:phone":"+49 821/601063",
    "sg:postcode":"86316",
    "sg:province":"Bayern",
    "wof:name":"Gerhard Waha Gmbh",
    "wof:placetype":"venue"
},
  "geometry": {"coordinates":[10.994889,48.348866],"type":"Point"}
}