{
  "type": "Feature",
  "properties": {
    "iso:country":"DE",
    "sg:address":"Nelkenstr. 5",
    "sg:city":"Saarbr\u00fccken",
    "sg:phone":"+49 681/583856",
    "sg:postcode":"66128",
    "sg:province":"Saarland",
    "wof:name":"G. Germann",
    "wof:placetype":"venue"
},
  "geometry": {"coordinates":[6.9077401161,49.2285194397],"type":"Point"}
}