{
  "type": "Feature",
  "properties": {
    "iso:country":"DE",
    "sg:address":"Rotdornallee 42",
    "sg:city":"Remscheid",
    "sg:phone":"+49 2191/61876",
    "sg:postcode":"42897",
    "sg:province":"Nordrhein-Westfalen",
    "wof:name":"Heinrich Lewandowski Inh. Rolf Schumacher",
    "wof:placetype":"venue"
},
  "geometry": {"coordinates":[7.261801,51.187374],"type":"Point"}
}