{
  "type": "Feature",
  "properties": {
    "iso:country":"DE",
    "sg:address":"Florastr. 39 a",
    "sg:city":"M\u00fcnchen",
    "sg:phone":"+49 89/4396468",
    "sg:postcode":"81827",
    "sg:province":"Bayern",
    "wof:name":"J. Voelzke",
    "wof:placetype":"venue"
},
  "geometry": {"coordinates":[11.687749,48.114292],"type":"Point"}
}