{
  "type": "Feature",
  "properties": {
    "iso:country":"DE",
    "sg:address":"Jansenstr. 22 A",
    "sg:city":"Berlin",
    "sg:phone":"+49 30/4118189",
    "sg:postcode":"13437",
    "sg:province":"Berlin",
    "wof:name":"Cornelia Riemer",
    "wof:placetype":"venue"
},
  "geometry": {"coordinates":[13.3338279724,52.5846366882],"type":"Point"}
}