{
  "type": "Feature",
  "properties": {
    "iso:country":"DE",
    "sg:address":"Zwingenberger Str. 37",
    "sg:city":"M\u00fcnchen",
    "sg:phone":"+49 89/8632300",
    "sg:postcode":"81245",
    "sg:province":"Bayern",
    "wof:name":"Eb Heizungs- Und W\u00e4rmetechnik Gmbh & Co. Kg",
    "wof:placetype":"venue"
},
  "geometry": {"coordinates":[11.4302120209,48.1548156738],"type":"Point"}
}