{
  "type": "Feature",
  "properties": {
    "iso:country":"DE",
    "sg:address":"Alter Schulweg",
    "sg:city":"Ahrensb\u00f6k",
    "sg:phone":"+49 4525/3434",
    "sg:postcode":"23623",
    "sg:province":"Schleswig-Holstein",
    "wof:name":"G\u00fcnter Jankowsky Architekt",
    "wof:placetype":"venue"
},
  "geometry": {"coordinates":[10.559456,53.977154],"type":"Point"}
}