{
  "type": "Feature",
  "properties": {
    "iso:country":"DE",
    "sg:address":"An der Hasenbahn 3",
    "sg:city":"Celle",
    "sg:phone":"+49 5141/45373",
    "sg:postcode":"29225",
    "sg:province":"Niedersachsen",
    "wof:name":"I. Zeising",
    "wof:placetype":"venue"
},
  "geometry": {"coordinates":[10.057682,52.608345],"type":"Point"}
}