{
  "type": "Feature",
  "properties": {
    "iso:country":"DE",
    "sg:address":"Natruper Str. 209",
    "sg:city":"Osnabr\u00fcck",
    "sg:phone":"+49 541/33060",
    "sg:postcode":"49090",
    "sg:province":"Niedersachsen",
    "wof:name":"Konkret Planen & Bauen Gmbh",
    "wof:placetype":"venue"
},
  "geometry": {"coordinates":[8.015725,52.292889],"type":"Point"}
}