{
  "type": "Feature",
  "properties": {
    "iso:country":"DE",
    "sg:address":"M\u00fcllenborner Str. 125",
    "sg:city":"Gerolstein",
    "sg:phone":"+49 6591/4608",
    "sg:postcode":"54568",
    "sg:province":"Rheinland-Pfalz",
    "wof:name":"M. Knobloch",
    "wof:placetype":"venue"
},
  "geometry": {"coordinates":[6.6019148827,50.2414283752],"type":"Point"}
}