{
  "type": "Feature",
  "properties": {
    "iso:country":"DE",
    "sg:address":"Paschacker 52",
    "sg:city":"Duisburg",
    "sg:phone":"+49 2065/77610",
    "sg:postcode":"47228",
    "sg:province":"Nordrhein-Westfalen",
    "wof:name":"R\u00fcdiger Kaleschke Architekt",
    "wof:placetype":"venue"
},
  "geometry": {"coordinates":[6.687285,51.4156],"type":"Point"}
}