{
  "type": "Feature",
  "properties": {
    "iso:country":"DE",
    "sg:address":"Homburger Landstr. 268",
    "sg:city":"Frankfurt",
    "sg:postcode":"60433",
    "sg:province":"Hessen",
    "wof:name":"Aldi Gmbh & Co. Kg",
    "wof:placetype":"venue"
},
  "geometry": {"coordinates":[8.6873188019,50.1601104736],"type":"Point"}
}