{
  "type": "Feature",
  "properties": {
    "iso:country":"DE",
    "sg:address":"Ernst-Zindel-Str. 4",
    "sg:city":"Dessau",
    "sg:phone":"+49 340/512105",
    "sg:postcode":"06847",
    "sg:province":"Sachsen-Anhalt",
    "wof:name":"Parf\u00fcmerie Le Coeur",
    "wof:placetype":"venue"
},
  "geometry": {"coordinates":[12.178966,51.818188],"type":"Point"}
}