{
  "type": "Feature",
  "properties": {
    "iso:country":"DE",
    "sg:address":"Sudammsbreite 36",
    "sg:city":"Wolfsburg",
    "sg:postcode":"38448",
    "sg:province":"Niedersachsen",
    "wof:name":"G & G Bau Gmbh",
    "wof:placetype":"venue"
},
  "geometry": {"coordinates":[10.860608,52.436367],"type":"Point"}
}