{
  "type": "Feature",
  "properties": {
    "iso:country":"DE",
    "sg:address":"Unterer Dorfweg 1",
    "sg:city":"Neunburg",
    "sg:phone":"+49 9672/703",
    "sg:postcode":"92431",
    "sg:province":"Bayern",
    "wof:name":"J. Schmid",
    "wof:placetype":"venue"
},
  "geometry": {"coordinates":[12.455601,49.330654],"type":"Point"}
}