{
  "type": "Feature",
  "properties": {
    "iso:country":"DE",
    "sg:address":"Am L\u00fcnedeich 151 A",
    "sg:city":"Bremerhaven",
    "sg:phone":"+49 4947/1308120",
    "sg:postcode":"27572",
    "sg:province":"Bremen",
    "wof:name":"Abc Industriebedarf Walter Zettler Gmbh",
    "wof:placetype":"venue"
},
  "geometry": {"coordinates":[8.5912437439,53.5012550354],"type":"Point"}
}