{
  "type": "Feature",
  "properties": {
    "iso:country":"DE",
    "sg:address":"Chamonixstr. 2",
    "sg:city":"Garmisch-Partenkirchen",
    "sg:phone":"+49 8821/2883",
    "sg:postcode":"82467",
    "sg:province":"Bayern",
    "wof:name":"Kr\u00e4h Immobilien Gmbh",
    "wof:placetype":"venue"
},
  "geometry": {"coordinates":[11.09244,47.494511],"type":"Point"}
}