{
  "type": "Feature",
  "properties": {
    "iso:country":"DE",
    "sg:address":"Westerstr. 14",
    "sg:city":"Wolfsburg",
    "sg:phone":"+49 5362/3212",
    "sg:postcode":"38442",
    "sg:province":"Niedersachsen",
    "wof:name":"Plinkenburg",
    "wof:placetype":"venue"
},
  "geometry": {"coordinates":[10.71285,52.417767],"type":"Point"}
}