{
  "type": "Feature",
  "properties": {
    "iso:country":"DE",
    "sg:address":"Christophstr. 24",
    "sg:city":"Essen",
    "sg:phone":"+49 201/776906",
    "sg:postcode":"45130",
    "sg:province":"Nordrhein-Westfalen",
    "wof:name":"Foto B. K\u00fcpper",
    "wof:placetype":"venue"
},
  "geometry": {"coordinates":[7.0031762123,51.4367332458],"type":"Point"}
}