{
  "type": "Feature",
  "properties": {
    "iso:country":"DE",
    "sg:address":"Lange Geismarstr. 19",
    "sg:city":"G\u00f6ttingen",
    "sg:phone":"+49 551/43297",
    "sg:postcode":"37073",
    "sg:province":"Niedersachsen",
    "wof:name":"Funkes Reisewelt Gmbh",
    "wof:placetype":"venue"
},
  "geometry": {"coordinates":[9.9378042221,51.5312767029],"type":"Point"}
}