{
  "type": "Feature",
  "properties": {
    "iso:country":"DE",
    "sg:address":"Berkenstr. 11",
    "sg:city":"Iserlohn",
    "sg:phone":"+49 2371/40957",
    "sg:postcode":"58640",
    "sg:province":"Nordrhein-Westfalen",
    "wof:name":"Roman Gloger Stahl- Und Schneidwaren",
    "wof:placetype":"venue"
},
  "geometry": {"coordinates":[7.7071919441,51.4263916016],"type":"Point"}
}