{
  "type": "Feature",
  "properties": {
    "iso:country":"DE",
    "sg:address":"Walther-Rathenau-Str. 22",
    "sg:city":"Radegast",
    "sg:phone":"+49 34978/22880",
    "sg:postcode":"06369",
    "sg:province":"Sachsen-Anhalt",
    "wof:name":"Elektro-ratey",
    "wof:placetype":"venue"
},
  "geometry": {"coordinates":[12.093252,51.656361],"type":"Point"}
}