{
  "type": "Feature",
  "properties": {
    "iso:country":"DE",
    "sg:address":"Kapellenweg 2b",
    "sg:city":"Bolsterlang",
    "sg:phone":"+49 8326/8218",
    "sg:postcode":"87538",
    "sg:province":"Bayern",
    "wof:name":"Dr. T. Budny",
    "wof:placetype":"venue"
},
  "geometry": {"coordinates":[10.2342329025,47.4610443115],"type":"Point"}
}