{
  "type": "Feature",
  "properties": {
    "iso:country":"DE",
    "sg:address":"Werner-Habig-Str. 1",
    "sg:city":"Oelde",
    "sg:phone":"+49 2522/770",
    "sg:postcode":"59302",
    "sg:province":"Nordrhein-Westfalen",
    "wof:name":"Westfalia Separator Engineering Gmbh",
    "wof:placetype":"venue"
},
  "geometry": {"coordinates":[8.137424,51.828949],"type":"Point"}
}