{
  "type": "Feature",
  "properties": {
    "iso:country":"DE",
    "sg:address":"D\u00fcrkheimer Hof",
    "sg:city":"St Johann",
    "sg:phone":"+49 6701/1207",
    "sg:postcode":"55578",
    "sg:province":"Rheinland-Pfalz",
    "wof:name":"Richard Goll",
    "wof:placetype":"venue"
},
  "geometry": {"coordinates":[8.026035,49.871868],"type":"Point"}
}