{
  "type": "Feature",
  "properties": {
    "iso:country":"DE",
    "sg:address":"Kurze Str. 2",
    "sg:city":"Chemnitz",
    "sg:phone":"+49 371/850815",
    "sg:postcode":"09117",
    "sg:province":"Sachsen",
    "wof:name":"Schmidt Gmbh",
    "wof:placetype":"venue"
},
  "geometry": {"coordinates":[12.819236,50.827847],"type":"Point"}
}