{
  "type": "Feature",
  "properties": {
    "iso:country":"DE",
    "sg:address":"Bahnhofstr. 2",
    "sg:city":"Neunkirchen",
    "sg:phone":"+49 9134/5915",
    "sg:postcode":"91077",
    "sg:province":"Bayern",
    "wof:name":"Bischof Schottdorf",
    "wof:placetype":"venue"
},
  "geometry": {"coordinates":[11.1286373138,49.61095047],"type":"Point"}
}