{
  "type": "Feature",
  "properties": {
    "iso:country":"DE",
    "sg:address":"M\u00fchlweg 11",
    "sg:city":"Heidelberg",
    "sg:phone":"+49 6221/801445",
    "sg:postcode":"69118",
    "sg:province":"Baden-W\u00fcrttemberg",
    "wof:name":"Katholisches Pfarramt St. Laurentius",
    "wof:placetype":"venue"
},
  "geometry": {"coordinates":[8.7523336411,49.4231681824],"type":"Point"}
}