{
  "type": "Feature",
  "properties": {
    "iso:country":"DE",
    "sg:address":"Im Kornfeld 13",
    "sg:city":"M\u00f6glingen",
    "sg:phone":"+49 7141/482041",
    "sg:postcode":"71696",
    "sg:province":"Baden-W\u00fcrttemberg",
    "wof:name":"Albert Pflugfelder",
    "wof:placetype":"venue"
},
  "geometry": {"coordinates":[9.127227,48.867153],"type":"Point"}
}