{
  "type": "Feature",
  "properties": {
    "iso:country":"DE",
    "sg:address":"Schwalbengraben 1",
    "sg:city":"Wetzlar",
    "sg:phone":"+49 6441/87515",
    "sg:postcode":"35576",
    "sg:province":"Hessen",
    "wof:name":"Eximas Maschinen Export-import Gmbh",
    "wof:placetype":"venue"
},
  "geometry": {"coordinates":[8.480084,50.564156],"type":"Point"}
}