{
  "type": "Feature",
  "properties": {
    "iso:country":"DE",
    "sg:address":"Nebendahlstr 8-10",
    "sg:city":"Hamburg",
    "sg:phone":"+49 40/681054",
    "sg:postcode":"22041",
    "sg:province":"Hamburg",
    "wof:name":"Buchdruckerei Franz Mentzel Gmbh",
    "wof:placetype":"venue"
},
  "geometry": {"coordinates":[10.0660896301,53.5775680542],"type":"Point"}
}