{
  "type": "Feature",
  "properties": {
    "iso:country":"DE",
    "sg:address":"Buchendorfer Str. 27",
    "sg:city":"M\u00fcnchen",
    "sg:phone":"+49 89/7558307",
    "sg:postcode":"81475",
    "sg:province":"Bayern",
    "wof:name":"Rr Wohn- Und Gewerbebau Gmbh",
    "wof:placetype":"venue"
},
  "geometry": {"coordinates":[11.472834,48.085484],"type":"Point"}
}