{
  "type": "Feature",
  "properties": {
    "iso:country":"DE",
    "sg:address":"Wildeshauser Str. 59",
    "sg:city":"Harpstedt",
    "sg:phone":"+49 4244/332",
    "sg:postcode":"27243",
    "sg:province":"Niedersachsen",
    "wof:name":"Hermann Mahlstedt",
    "wof:placetype":"venue"
},
  "geometry": {"coordinates":[8.552995,52.897987],"type":"Point"}
}