{
  "type": "Feature",
  "properties": {
    "iso:country":"DE",
    "sg:address":"Schlo\u00dfplatz 4",
    "sg:city":"Waldheim",
    "sg:phone":"+49 34327/54234",
    "sg:postcode":"04736",
    "sg:province":"Sachsen",
    "wof:name":"Esw Elektroservice Waldheim Gmbh",
    "wof:placetype":"venue"
},
  "geometry": {"coordinates":[13.026875,51.074287],"type":"Point"}
}