{
  "type": "Feature",
  "properties": {
    "iso:country":"DE",
    "sg:address":"Bahnhofstr. 45",
    "sg:city":"Schkeuditz",
    "sg:phone":"+49 34204/60074",
    "sg:postcode":"04435",
    "sg:province":"Sachsen",
    "wof:name":"Barth",
    "wof:placetype":"venue"
},
  "geometry": {"coordinates":[12.220951,51.400932],"type":"Point"}
}