{
  "type": "Feature",
  "properties": {
    "iso:country":"DE",
    "sg:address":"Warnowallee 23/24",
    "sg:city":"Rostock",
    "sg:postcode":"18107",
    "sg:province":"Mecklenburg-Vorpommern",
    "wof:name":"Ident-haus Bautr\u00e4gerges. Mbh",
    "wof:placetype":"venue"
},
  "geometry": {"coordinates":[12.04712677,54.1383743286],"type":"Point"}
}