{
  "type": "Feature",
  "properties": {
    "iso:country":"DE",
    "sg:address":"Rh\u00f6nstr. 82",
    "sg:city":"Wildflecken",
    "sg:phone":"+49 9749/237",
    "sg:postcode":"97772",
    "sg:province":"Bayern",
    "wof:name":"J. Ziegler",
    "wof:placetype":"venue"
},
  "geometry": {"coordinates":[9.882222,50.347408],"type":"Point"}
}