{
  "type": "Feature",
  "properties": {
    "iso:country":"DE",
    "sg:address":"Weingartener Str. 99",
    "sg:city":"Bruchsal",
    "sg:phone":"+49 7257/91140",
    "sg:postcode":"76646",
    "sg:province":"Baden-W\u00fcrttemberg",
    "wof:name":"Lauber Kg",
    "wof:placetype":"venue"
},
  "geometry": {"coordinates":[8.5492191315,49.0802116394],"type":"Point"}
}