{
  "type": "Feature",
  "properties": {
    "iso:country":"DE",
    "sg:address":"Georg-L\u00f6wel-Str. 4",
    "sg:city":"Worms",
    "sg:phone":"+49 6241/975358",
    "sg:postcode":"67549",
    "sg:province":"Rheinland-Pfalz",
    "wof:name":"Zvg Zeitungsvertriebsgesell. F\u00fcr Worms-nord Mbh",
    "wof:placetype":"venue"
},
  "geometry": {"coordinates":[8.3214111328,49.6334762573],"type":"Point"}
}