{
  "type": "Feature",
  "properties": {
    "iso:country":"DE",
    "sg:address":"Gro\u00dfe Allee 61",
    "sg:city":"Bad Arolsen",
    "sg:phone":"+49 5691/895860",
    "sg:postcode":"34454",
    "sg:province":"Hessen",
    "wof:name":"Wohnungsbaugenossenschaft Arolsen Eg",
    "wof:placetype":"venue"
},
  "geometry": {"coordinates":[9.0067749023,51.3782730103],"type":"Point"}
}