{
  "type": "Feature",
  "properties": {
    "iso:country":"DE",
    "sg:address":"Hammermeisterstr. 4",
    "sg:city":"Amberg",
    "sg:phone":"+49 9621/61334",
    "sg:postcode":"92224",
    "sg:province":"Bayern",
    "wof:name":"Elfriede G\u00d6tz",
    "wof:placetype":"venue"
},
  "geometry": {"coordinates":[11.855085,49.462643],"type":"Point"}
}