{
  "type": "Feature",
  "properties": {
    "iso:country":"DE",
    "sg:address":"Schopenhauerstr. 24",
    "sg:city":"N\u00fcrnberg",
    "sg:phone":"+49 911/361136",
    "sg:postcode":"90409",
    "sg:province":"Bayern",
    "wof:name":"Peter Reinhold",
    "wof:placetype":"venue"
},
  "geometry": {"coordinates":[11.0888910294,49.4696731567],"type":"Point"}
}