{
  "type": "Feature",
  "properties": {
    "iso:country":"DE",
    "sg:city":"Herzogenaurach",
    "sg:phone":"+49 9132/63985",
    "sg:postcode":"91074",
    "sg:province":"Bayern",
    "wof:name":"Manuela Funke Hardwarehandel",
    "wof:placetype":"venue"
},
  "geometry": {"coordinates":[10.880872,49.569061],"type":"Point"}
}