{
  "type": "Feature",
  "properties": {
    "iso:country":"DE",
    "sg:address":"Am Brink 19",
    "sg:city":"Twistringen",
    "sg:phone":"+49 4243/5107752",
    "sg:postcode":"27239",
    "sg:province":"Niedersachsen",
    "wof:name":"Heinrich Bellersen",
    "wof:placetype":"venue"
},
  "geometry": {"coordinates":[8.627259,52.79007],"type":"Point"}
}