{
  "type": "Feature",
  "properties": {
    "iso:country":"DE",
    "sg:address":"Luitpoldstr. 63",
    "sg:city":"Neuburg",
    "sg:phone":"+49 8431/2789",
    "sg:postcode":"86633",
    "sg:province":"Bayern",
    "wof:name":"Hofgarten-theater Gr. Haus",
    "wof:placetype":"venue"
},
  "geometry": {"coordinates":[11.182195,48.737015],"type":"Point"}
}