{
  "type": "Feature",
  "properties": {
    "iso:country":"DE",
    "sg:address":"Luxemburger Str. 142",
    "sg:city":"Trier",
    "sg:phone":"+49 651/821232",
    "sg:postcode":"54294",
    "sg:province":"Rheinland-Pfalz",
    "wof:name":"Bistro Bertard",
    "wof:placetype":"venue"
},
  "geometry": {"coordinates":[6.6164340973,49.7395935059],"type":"Point"}
}