{
  "type": "Feature",
  "properties": {
    "iso:country":"DE",
    "sg:address":"Gartenstr. 18",
    "sg:city":"Altdorf",
    "sg:phone":"+49 7031/601178",
    "sg:postcode":"71155",
    "sg:province":"Baden-W\u00fcrttemberg",
    "wof:name":"Johannes Berner",
    "wof:placetype":"venue"
},
  "geometry": {"coordinates":[8.993457,48.628349],"type":"Point"}
}