{
  "type": "Feature",
  "properties": {
    "iso:country":"DE",
    "sg:address":"Th\u00fcringer Stra\u00dfe 4",
    "sg:city":"Diepholz",
    "sg:phone":"+49 5441",
    "sg:postcode":"49356",
    "sg:province":"Niedersachsen",
    "wof:name":"P S Polyurethan-elastomere",
    "wof:placetype":"venue"
},
  "geometry": {"coordinates":[8.3634796143,52.6146278381],"type":"Point"}
}