{
  "type": "Feature",
  "properties": {
    "iso:country":"DE",
    "sg:address":"Friedrich-Naumann-Str. 43",
    "sg:city":"Reutlingen",
    "sg:phone":"+49 7121/26730",
    "sg:postcode":"72762",
    "sg:province":"Baden-W\u00fcrttemberg",
    "wof:name":"Harry Schulze",
    "wof:placetype":"venue"
},
  "geometry": {"coordinates":[9.192415,48.486706],"type":"Point"}
}