{
  "type": "Feature",
  "properties": {
    "iso:country":"DE",
    "sg:address":"Marktstr. 20",
    "sg:city":"Wassertr\u00fcdingen",
    "sg:phone":"+49 9832/313",
    "sg:postcode":"91717",
    "sg:province":"Bayern",
    "wof:name":"Sch\u00f6nherr",
    "wof:placetype":"venue"
},
  "geometry": {"coordinates":[10.5974149704,49.0395736694],"type":"Point"}
}