{
  "type": "Feature",
  "properties": {
    "iso:country":"DE",
    "sg:address":"Sch\u00f6nriedlstr.",
    "sg:city":"Peiting",
    "sg:phone":"+49 8861/4071",
    "sg:postcode":"86971",
    "sg:province":"Bayern",
    "wof:name":"Aldund Design Gmbh",
    "wof:placetype":"venue"
},
  "geometry": {"coordinates":[10.943014,47.787041],"type":"Point"}
}