{
  "type": "Feature",
  "properties": {
    "iso:country":"DE",
    "sg:address":"Am Steinberg 4",
    "sg:city":"Lohmar",
    "sg:phone":"+49 2246/4873",
    "sg:postcode":"53797",
    "sg:province":"Nordrhein-Westfalen",
    "wof:name":"Paul Herchenbach",
    "wof:placetype":"venue"
},
  "geometry": {"coordinates":[7.26289,50.847115],"type":"Point"}
}