{
  "type": "Feature",
  "properties": {
    "iso:country":"DE",
    "sg:address":"S\u00fcdhang 21",
    "sg:city":"Gro\u00dfenhain",
    "sg:phone":"+49 3522/509249",
    "sg:postcode":"01558",
    "sg:province":"Sachsen",
    "wof:name":"Christa Arndt",
    "wof:placetype":"venue"
},
  "geometry": {"coordinates":[13.510423,51.293949],"type":"Point"}
}