{
  "type": "Feature",
  "properties": {
    "iso:country":"DE",
    "sg:address":"Grabenweg 7",
    "sg:city":"Adelberg",
    "sg:phone":"+49 7166/845",
    "sg:postcode":"73099",
    "sg:province":"Baden-W\u00fcrttemberg",
    "wof:name":"D. Und A. St\u00e4hle",
    "wof:placetype":"venue"
},
  "geometry": {"coordinates":[9.6029949188,48.7610015869],"type":"Point"}
}