{
  "type": "Feature",
  "properties": {
    "iso:country":"DE",
    "sg:address":"M\u00fcnchener Str. 41",
    "sg:city":"Freilassing",
    "sg:phone":"+49 8654/2866",
    "sg:postcode":"83395",
    "sg:province":"Bayern",
    "wof:name":"C. Widauer",
    "wof:placetype":"venue"
},
  "geometry": {"coordinates":[12.973955,47.84251],"type":"Point"}
}