{
  "type": "Feature",
  "properties": {
    "iso:country":"DE",
    "sg:address":"Hospitalstr. 10",
    "sg:city":"K\u00f6lleda",
    "sg:phone":"+49 3635/482244",
    "sg:postcode":"99625",
    "sg:province":"Th\u00fcringen",
    "wof:name":"Benedikt Schuster",
    "wof:placetype":"venue"
},
  "geometry": {"coordinates":[11.2415885925,51.1890983582],"type":"Point"}
}