{
  "type": "Feature",
  "properties": {
    "iso:country":"DE",
    "sg:address":"Birkenweg 8",
    "sg:city":"Cottbus",
    "sg:phone":"+49 355/524790",
    "sg:postcode":"03050",
    "sg:province":"Brandenburg",
    "wof:name":"Dr. Med. Rudolf Hagen",
    "wof:placetype":"venue"
},
  "geometry": {"coordinates":[14.345142,51.730274],"type":"Point"}
}