{
  "type": "Feature",
  "properties": {
    "iso:country":"DE",
    "sg:address":"Am Zwinger 4",
    "sg:city":"Gilching",
    "sg:phone":"+49 8105/23626",
    "sg:postcode":"82205",
    "sg:province":"Bayern",
    "wof:name":"H. Herwehg Licht- Und Fotopausen",
    "wof:placetype":"venue"
},
  "geometry": {"coordinates":[11.3032712936,48.1082229614],"type":"Point"}
}