{
  "type": "Feature",
  "properties": {
    "iso:country":"DE",
    "sg:address":"Lindenweg 1",
    "sg:city":"Telgte",
    "sg:phone":"+49 2504/2473",
    "sg:postcode":"48291",
    "sg:province":"Nordrhein-Westfalen",
    "wof:name":"W. Glahn Ingenieur",
    "wof:placetype":"venue"
},
  "geometry": {"coordinates":[7.8089809418,51.9842720032],"type":"Point"}
}