{
  "type": "Feature",
  "properties": {
    "iso:country":"DE",
    "sg:address":"Carl-Benz-Str 11",
    "sg:city":"Sinsheim",
    "sg:phone":"+49 7261/92830",
    "sg:postcode":"74889",
    "sg:province":"Baden-W\u00fcrttemberg",
    "wof:name":"Junker Filter Gmbh",
    "wof:placetype":"venue"
},
  "geometry": {"coordinates":[8.86236763,49.2527999878],"type":"Point"}
}