{
  "type": "Feature",
  "properties": {
    "iso:country":"DE",
    "sg:address":"Gro\u00df-Hasenbach-Str. 38",
    "sg:city":"Offenbach",
    "sg:phone":"+49 69/885989",
    "sg:postcode":"63065",
    "sg:province":"Hessen",
    "wof:name":"Robert Baar",
    "wof:placetype":"venue"
},
  "geometry": {"coordinates":[8.76283,50.102047],"type":"Point"}
}