{
  "type": "Feature",
  "properties": {
    "iso:country":"DE",
    "sg:address":"Liebigstr. 1",
    "sg:city":"Aurich",
    "sg:phone":"+49 4941/97950",
    "sg:postcode":"26607",
    "sg:province":"Niedersachsen",
    "wof:name":"Kerker Tiefbau Gmbh",
    "wof:placetype":"venue"
},
  "geometry": {"coordinates":[7.4850001335,53.5052528381],"type":"Point"}
}