{
  "type": "Feature",
  "properties": {
    "iso:country":"DE",
    "sg:address":"Sonnenstr. 9 a",
    "sg:city":"R\u00f6thlein",
    "sg:postcode":"97520",
    "sg:province":"Bayern",
    "wof:name":"Saalmann Gmbh",
    "wof:placetype":"venue"
},
  "geometry": {"coordinates":[10.1891145706,49.9465026855],"type":"Point"}
}