{
  "type": "Feature",
  "properties": {
    "iso:country":"DE",
    "sg:address":"Am Michelsgrund 6",
    "sg:city":"Weinheim",
    "sg:phone":"+49 6201/62069",
    "sg:postcode":"69469",
    "sg:province":"Baden-W\u00fcrttemberg",
    "wof:name":"Albert Bechtold",
    "wof:placetype":"venue"
},
  "geometry": {"coordinates":[8.6719923019,49.5359954834],"type":"Point"}
}