{
  "type": "Feature",
  "properties": {
    "iso:country":"DE",
    "sg:address":"Hauptstr. 25",
    "sg:city":"Syrau",
    "sg:phone":"+49 37431/3281",
    "sg:postcode":"08548",
    "sg:province":"Sachsen",
    "wof:name":"Klaus Eisenschmidt",
    "wof:placetype":"venue"
},
  "geometry": {"coordinates":[12.0771799088,50.5426063538],"type":"Point"}
}