{
  "type": "Feature",
  "properties": {
    "iso:country":"DE",
    "sg:address":"Rudolf-Breitscheid-Str. 11",
    "sg:city":"Wernshausen",
    "sg:phone":"+49 36848/2930",
    "sg:postcode":"98590",
    "sg:province":"Th\u00fcringen",
    "wof:name":"Apotheke Am Sternplatz Inh. Manuela K\u00f6nig",
    "wof:placetype":"venue"
},
  "geometry": {"coordinates":[10.350977,50.724792],"type":"Point"}
}