{
  "type": "Feature",
  "properties": {
    "iso:country":"DE",
    "sg:address":"Heinrichstr. 11",
    "sg:city":"Plauen",
    "sg:phone":"+49 3741/222727",
    "sg:postcode":"08523",
    "sg:province":"Sachsen",
    "wof:name":"W. Schulz Parkettverlegebetrieb",
    "wof:placetype":"venue"
},
  "geometry": {"coordinates":[12.1410770416,50.4979705811],"type":"Point"}
}