{
  "type": "Feature",
  "properties": {
    "iso:country":"DE",
    "sg:address":"Gro\u00dfe Venedig 31",
    "sg:city":"Hildesheim",
    "sg:phone":"+49 5121/130651",
    "sg:postcode":"31134",
    "sg:province":"Niedersachsen",
    "wof:name":"Jung Gesellschaft F\u00fcr Bauen Und Wohnen Mbh",
    "wof:placetype":"venue"
},
  "geometry": {"coordinates":[9.947261,52.141987],"type":"Point"}
}