{
  "type": "Feature",
  "properties": {
    "iso:country":"DE",
    "sg:address":"Dieselstr 6",
    "sg:city":"Schlierbach",
    "sg:phone":"+49 7021/72760",
    "sg:postcode":"73278",
    "sg:province":"Baden-W\u00fcrttemberg",
    "wof:name":"Dima Freizeitm\u00f6bel Gmbh",
    "wof:placetype":"venue"
},
  "geometry": {"coordinates":[9.533437,48.677979],"type":"Point"}
}