{
  "type": "Feature",
  "properties": {
    "iso:country":"DE",
    "sg:address":"Kornstr. 5",
    "sg:city":"Bautzen",
    "sg:phone":"+49 3591/47446",
    "sg:postcode":"02625",
    "sg:province":"Sachsen",
    "wof:name":"Deutschmann",
    "wof:placetype":"venue"
},
  "geometry": {"coordinates":[14.4248924255,51.1819496155],"type":"Point"}
}