{
  "type": "Feature",
  "properties": {
    "iso:country":"DE",
    "sg:address":"K\u00e4the-Niederkirchner-Str. 27",
    "sg:city":"Hoyerswerda",
    "sg:phone":"+49 3571/972085",
    "sg:postcode":"02977",
    "sg:province":"Sachsen",
    "wof:name":"Sch\u00f6nheitsstudio",
    "wof:placetype":"venue"
},
  "geometry": {"coordinates":[14.2651,51.442089],"type":"Point"}
}