{
  "type": "Feature",
  "properties": {
    "iso:country":"DE",
    "sg:address":"Neherstr. 8",
    "sg:city":"Biberach",
    "sg:postcode":"88400",
    "sg:province":"Baden-W\u00fcrttemberg",
    "wof:name":"Erd- Und Ingenieurbau Biberach Gmbh",
    "wof:placetype":"venue"
},
  "geometry": {"coordinates":[9.793418,48.099277],"type":"Point"}
}