{
  "type": "Feature",
  "properties": {
    "iso:country":"DE",
    "sg:address":"H\u00fcninger Str. 9",
    "sg:city":"Berlin",
    "sg:phone":"+49 30/8324419",
    "sg:postcode":"14195",
    "sg:province":"Berlin",
    "wof:name":"Wolfgang Wossilus Steuerberater",
    "wof:placetype":"venue"
},
  "geometry": {"coordinates":[13.2780332565,52.4430122375],"type":"Point"}
}