{
  "type": "Feature",
  "properties": {
    "iso:country":"DE",
    "sg:address":"Reuterweg 68-70",
    "sg:city":"Frankfurt",
    "sg:phone":"+49 69/727417",
    "sg:postcode":"60323",
    "sg:province":"Hessen",
    "wof:name":"Apotheke Am Reuterweg Inh. Dr. Livia Gati",
    "wof:placetype":"venue"
},
  "geometry": {"coordinates":[8.670709,50.121212],"type":"Point"}
}