{
  "type": "Feature",
  "properties": {
    "iso:country":"DE",
    "sg:address":"Kleistr. 17",
    "sg:city":"Unna",
    "sg:phone":"+49 2303/951200",
    "sg:postcode":"59427",
    "sg:province":"Nordrhein-Westfalen",
    "wof:name":"Wolf Verwaltungs Gmbh",
    "wof:placetype":"venue"
},
  "geometry": {"coordinates":[7.648199,51.536339],"type":"Point"}
}