{
  "type": "Feature",
  "properties": {
    "iso:country":"DE",
    "sg:address":"Dr.-Wilhelm-K\u00fclz-Str. 15 a",
    "sg:city":"P\u00f6\u00dfneck",
    "sg:phone":"+49 3647/416838",
    "sg:postcode":"07381",
    "sg:province":"Th\u00fcringen",
    "wof:name":"K.-h. Wesotowski",
    "wof:placetype":"venue"
},
  "geometry": {"coordinates":[11.5885782242,50.6924629211],"type":"Point"}
}