{
  "type": "Feature",
  "properties": {
    "iso:country":"DE",
    "sg:address":"Alter Postplatz 4",
    "sg:city":"Waiblingen",
    "sg:postcode":"71332",
    "sg:province":"Baden-W\u00fcrttemberg",
    "wof:name":"C. B. C. Erlebnis- Gastronomie Gmbh",
    "wof:placetype":"venue"
},
  "geometry": {"coordinates":[9.31522,48.829769],"type":"Point"}
}