{
  "type": "Feature",
  "properties": {
    "iso:country":"DE",
    "sg:address":"Im Burris 16",
    "sg:city":"Plochingen",
    "sg:phone":"+49 7153/21523",
    "sg:postcode":"73207",
    "sg:province":"Baden-W\u00fcrttemberg",
    "wof:name":"Hans Heller Ulla Heller",
    "wof:placetype":"venue"
},
  "geometry": {"coordinates":[9.424224,48.70813],"type":"Point"}
}