{
  "type": "Feature",
  "properties": {
    "iso:country":"DE",
    "sg:address":"Robert-Bosch-Str. 9",
    "sg:city":"Nagold",
    "sg:phone":"+49 7452/951",
    "sg:postcode":"72202",
    "sg:province":"Baden-W\u00fcrttemberg",
    "wof:name":"H\u00e4fele Gmbh & Co.",
    "wof:placetype":"venue"
},
  "geometry": {"coordinates":[8.7498016357,48.5417175293],"type":"Point"}
}