{
  "type": "Feature",
  "properties": {
    "iso:country":"DE",
    "sg:address":"Berliner Str 66",
    "sg:city":"Halle",
    "sg:phone":"+49 345/568790",
    "sg:postcode":"06116",
    "sg:province":"Sachsen-Anhalt",
    "wof:name":"Impress Offsetdruckerei Gbr",
    "wof:placetype":"venue"
},
  "geometry": {"coordinates":[12.011234,51.496078],"type":"Point"}
}