{
  "type": "Feature",
  "properties": {
    "iso:country":"DE",
    "sg:address":"Graf-Schenk-Str. 9",
    "sg:city":"T\u00fcrkenfeld",
    "sg:phone":"+49 8193/6915",
    "sg:postcode":"82299",
    "sg:province":"Bayern",
    "wof:name":"Emilie Schifferer",
    "wof:placetype":"venue"
},
  "geometry": {"coordinates":[11.0828504562,48.1131362915],"type":"Point"}
}