{
  "type": "Feature",
  "properties": {
    "iso:country":"DE",
    "sg:address":"Geschwister-Scholl-Str. 3",
    "sg:city":"F\u00fcrstenwalde",
    "sg:phone":"+49 3361/303696",
    "sg:postcode":"15517",
    "sg:province":"Brandenburg",
    "wof:name":"K\u00fcchenstudio M\u00fcller & Tederahn Ohg",
    "wof:placetype":"venue"
},
  "geometry": {"coordinates":[14.0677022934,52.358341217],"type":"Point"}
}