{
  "type": "Feature",
  "properties": {
    "iso:country":"DE",
    "sg:address":"Alt\u00f6ttinger Str. 10",
    "sg:city":"Unterneukirchen",
    "sg:phone":"+49 8634/98890",
    "sg:postcode":"84579",
    "sg:province":"Bayern",
    "wof:name":"Abus-fenster Gmbh",
    "wof:placetype":"venue"
},
  "geometry": {"coordinates":[12.6222,48.168468],"type":"Point"}
}