{
  "type": "Feature",
  "properties": {
    "iso:country":"DE",
    "sg:address":"Kr\u00f6peliner Str. 22",
    "sg:city":"Rostock",
    "sg:postcode":"18055",
    "sg:province":"Mecklenburg-Vorpommern",
    "wof:name":"Schnabel Unternehmensbeteiligungen Gmbh",
    "wof:placetype":"venue"
},
  "geometry": {"coordinates":[12.1367321014,54.0883598328],"type":"Point"}
}