{
  "type": "Feature",
  "properties": {
    "iso:country":"DE",
    "sg:address":"Schwalbacher Str. 33",
    "sg:city":"Wiesbaden",
    "sg:phone":"+49 611/376943",
    "sg:postcode":"65183",
    "sg:province":"Hessen",
    "wof:name":"Ann-katrin W\u00e4sche Dr. Kreibich Kg",
    "wof:placetype":"venue"
},
  "geometry": {"coordinates":[8.2366189957,50.0804252625],"type":"Point"}
}