{
  "type": "Feature",
  "properties": {
    "iso:country":"DE",
    "sg:address":"Steingasse 21",
    "sg:city":"Runkel",
    "sg:phone":"+49 4964/8224197",
    "sg:postcode":"65594",
    "sg:province":"Hessen",
    "wof:name":"Nassauische Sparkasse",
    "wof:placetype":"venue"
},
  "geometry": {"coordinates":[8.09888,50.416439],"type":"Point"}
}