{
  "type": "Feature",
  "properties": {
    "iso:country":"DE",
    "sg:address":"Nordring 8",
    "sg:city":"Marktheidenfeld",
    "sg:phone":"+49 9391/98030",
    "sg:postcode":"97828",
    "sg:province":"Bayern",
    "wof:name":"Ufw Immobilien- Verwaltungs- Gmbh",
    "wof:placetype":"venue"
},
  "geometry": {"coordinates":[9.606925,49.854359],"type":"Point"}
}