{
  "type": "Feature",
  "properties": {
    "iso:country":"DE",
    "sg:address":"Altendorfer Str. 15",
    "sg:city":"Fr\u00f6ndenberg",
    "sg:phone":"+49 4923/783686",
    "sg:postcode":"58730",
    "sg:province":"Nordrhein-Westfalen",
    "wof:name":"Agner Garten-undlandschaftsbau Gmbh",
    "wof:placetype":"venue"
},
  "geometry": {"coordinates":[7.768445,51.473171],"type":"Point"}
}