{
  "type": "Feature",
  "properties": {
    "iso:country":"DE",
    "sg:address":"Hauptstr. 7",
    "sg:city":"Bedburg",
    "sg:phone":"+49 2272/4562",
    "sg:postcode":"50181",
    "sg:province":"Nordrhein-Westfalen",
    "wof:name":"Matthias Schiffer",
    "wof:placetype":"venue"
},
  "geometry": {"coordinates":[6.557967,51.009727],"type":"Point"}
}