{
  "type": "Feature",
  "properties": {
    "iso:country":"DE",
    "sg:address":"Hardenbergstr. 4",
    "sg:city":"Hagen",
    "sg:phone":"+49 2331/83338",
    "sg:postcode":"58097",
    "sg:province":"Nordrhein-Westfalen",
    "wof:name":"A. Marx",
    "wof:placetype":"venue"
},
  "geometry": {"coordinates":[7.4849181175,51.3652801514],"type":"Point"}
}