{
  "type": "Feature",
  "properties": {
    "iso:country":"DE",
    "sg:address":"B\u00f6senbrunner Str. 13",
    "sg:city":"Triebel",
    "sg:phone":"+49 37434/80614",
    "sg:postcode":"08606",
    "sg:province":"Sachsen",
    "wof:name":"Manfred Wallner Anlageberater",
    "wof:placetype":"venue"
},
  "geometry": {"coordinates":[12.1188936234,50.373714447],"type":"Point"}
}