{
  "type": "Feature",
  "properties": {
    "iso:country":"DE",
    "sg:address":"Bahnhofstr. 52",
    "sg:city":"Herne",
    "sg:phone":"+49 2323/12773",
    "sg:postcode":"44623",
    "sg:province":"Nordrhein-Westfalen",
    "wof:name":"Dahl-j\u00f6rgensen",
    "wof:placetype":"venue"
},
  "geometry": {"coordinates":[7.2227139473,51.540512085],"type":"Point"}
}