{
  "type": "Feature",
  "properties": {
    "iso:country":"DE",
    "sg:address":"Graf-Wolfegg-Str. 27",
    "sg:city":"Rottenburg",
    "sg:postcode":"72108",
    "sg:province":"Baden-W\u00fcrttemberg",
    "wof:name":"Eurospar",
    "wof:placetype":"venue"
},
  "geometry": {"coordinates":[8.9452905655,48.4796638489],"type":"Point"}
}