{
  "type": "Feature",
  "properties": {
    "iso:country":"DE",
    "sg:address":"Kaulbachplatz 3",
    "sg:city":"N\u00fcrnberg",
    "sg:phone":"+49 911/3651641",
    "sg:postcode":"90408",
    "sg:province":"Bayern",
    "wof:name":"Hans Aicher",
    "wof:placetype":"venue"
},
  "geometry": {"coordinates":[11.076813,49.463455],"type":"Point"}
}