{
  "type": "Feature",
  "properties": {
    "iso:country":"DE",
    "sg:address":"Rohrbacher Str. 13",
    "sg:city":"Espenhain",
    "sg:phone":"+49 34347/50203",
    "sg:postcode":"04579",
    "sg:province":"Sachsen",
    "wof:name":"W. Such",
    "wof:placetype":"venue"
},
  "geometry": {"coordinates":[12.528181,51.218189],"type":"Point"}
}