{
  "type": "Feature",
  "properties": {
    "iso:country":"DE",
    "sg:address":"Kirchgasse 6",
    "sg:city":"Wiesbaden",
    "sg:phone":"+49 611/374647",
    "sg:postcode":"65185",
    "sg:province":"Hessen",
    "wof:name":"Marbert Ag",
    "wof:placetype":"venue"
},
  "geometry": {"coordinates":[8.238052,50.078205],"type":"Point"}
}