{
  "type": "Feature",
  "properties": {
    "iso:country":"DE",
    "sg:address":"Heimatring 6",
    "sg:city":"Frankfurt",
    "sg:phone":"+49 69/637665",
    "sg:postcode":"60596",
    "sg:province":"Hessen",
    "wof:name":"Stand Bau Gmbh",
    "wof:placetype":"venue"
},
  "geometry": {"coordinates":[8.669005,50.089821],"type":"Point"}
}