{
  "type": "Feature",
  "properties": {
    "iso:country":"DE",
    "sg:address":"Rheinstr. 100",
    "sg:city":"Viersen",
    "sg:phone":"+49 2162/81212",
    "sg:postcode":"41749",
    "sg:province":"Nordrhein-Westfalen",
    "wof:name":"R. Meyer",
    "wof:placetype":"venue"
},
  "geometry": {"coordinates":[6.3898901939,51.2733612061],"type":"Point"}
}