{
  "type": "Feature",
  "properties": {
    "iso:country":"DE",
    "sg:address":"Zugspitzstr. 38",
    "sg:city":"Bad W\u00f6rishofen",
    "sg:phone":"+49 8247/7028",
    "sg:postcode":"86825",
    "sg:province":"Bayern",
    "wof:name":"Alois Kusterer Finanzberater",
    "wof:placetype":"venue"
},
  "geometry": {"coordinates":[10.6142778397,48.0072822571],"type":"Point"}
}