{
  "type": "Feature",
  "properties": {
    "iso:country":"DE",
    "sg:address":"Overbergstr. 52",
    "sg:city":"Hagen",
    "sg:phone":"+49 2331/61237",
    "sg:postcode":"58099",
    "sg:province":"Nordrhein-Westfalen",
    "wof:name":"Wolfgang Und G. Nordmann Rechtsanwalt Und Notar",
    "wof:placetype":"venue"
},
  "geometry": {"coordinates":[7.4677858353,51.381072998],"type":"Point"}
}