{
  "type": "Feature",
  "properties": {
    "iso:country":"DE",
    "sg:address":"Arndtstr. 10",
    "sg:city":"Dresden",
    "sg:postcode":"01099",
    "sg:province":"Sachsen",
    "wof:name":"Dresdner Bausachverst\u00e4ndigen- Soziet\u00e4t Mortensen Achatz",
    "wof:placetype":"venue"
},
  "geometry": {"coordinates":[13.7750234604,51.0682258606],"type":"Point"}
}