{
  "type": "Feature",
  "properties": {
    "iso:country":"DE",
    "sg:address":"Oppelner Str. 6",
    "sg:city":"Berlin",
    "sg:phone":"+49 30/6125506",
    "sg:postcode":"10997",
    "sg:province":"Berlin",
    "wof:name":"Hermann Wenning",
    "wof:placetype":"venue"
},
  "geometry": {"coordinates":[13.4405870438,52.4997520447],"type":"Point"}
}