{
  "type": "Feature",
  "properties": {
    "iso:country":"DE",
    "sg:address":"Weberstr. 01",
    "sg:city":"Wadgassen",
    "sg:postcode":"66787",
    "sg:province":"Saarland",
    "wof:name":"Frank L\u00f6wenbr\u00fcck Tranpsorte",
    "wof:placetype":"venue"
},
  "geometry": {"coordinates":[6.81709,49.26572],"type":"Point"}
}