{
  "type": "Feature",
  "properties": {
    "iso:country":"DE",
    "sg:address":"Zur Kapelle 8",
    "sg:city":"Erden",
    "sg:phone":"+49 4965/322267",
    "sg:postcode":"54492",
    "sg:province":"Rheinland-Pfalz",
    "wof:name":"Justen-ehlen-erben Weingut",
    "wof:placetype":"venue"
},
  "geometry": {"coordinates":[7.024085,49.978008],"type":"Point"}
}