{
  "type": "Feature",
  "properties": {
    "iso:country":"DE",
    "sg:address":"Junkermanns Weg 3",
    "sg:city":"Hamm",
    "sg:phone":"+49 2381/880171",
    "sg:postcode":"59071",
    "sg:province":"Nordrhein-Westfalen",
    "wof:name":"Simon B\u00fcrotechnik Vertriebs-gmbh",
    "wof:placetype":"venue"
},
  "geometry": {"coordinates":[7.8888430595,51.6844215393],"type":"Point"}
}