{
  "type": "Feature",
  "properties": {
    "iso:country":"DE",
    "sg:address":"Scheibenstuhlweg 6",
    "sg:city":"Geisingen",
    "sg:phone":"+49 7704/447",
    "sg:postcode":"78187",
    "sg:province":"Baden-W\u00fcrttemberg",
    "wof:name":"Johann Grieshaber",
    "wof:placetype":"venue"
},
  "geometry": {"coordinates":[8.6427030563,47.9249267578],"type":"Point"}
}