{
  "type": "Feature",
  "properties": {
    "iso:country":"DE",
    "sg:address":"Hohen Zollernstr. 11-13 PF 320213",
    "sg:city":"D\u00fcsseldorf",
    "sg:phone":"+49 211/4987201",
    "sg:postcode":"40211",
    "sg:province":"Nordrhein-Westfalen",
    "wof:name":"Deutsch-niederl\u00c4ndische Handelskammer",
    "wof:placetype":"venue"
},
  "geometry": {"coordinates":[6.776055,51.21563],"type":"Point"}
}