{
  "type": "Feature",
  "properties": {
    "iso:country":"DE",
    "sg:address":"Schwarzmoorstr. 48",
    "sg:city":"Rhauderfehn",
    "sg:phone":"+49 4952/1661",
    "sg:postcode":"26817",
    "sg:province":"Niedersachsen",
    "wof:name":"J. Hermann Roskam",
    "wof:placetype":"venue"
},
  "geometry": {"coordinates":[7.529904,53.155945],"type":"Point"}
}