{
  "type": "Feature",
  "properties": {
    "iso:country":"DE",
    "sg:address":"Bramwaldstr. 1",
    "sg:city":"G\u00f6ttingen",
    "sg:phone":"+49 551/96645",
    "sg:postcode":"37081",
    "sg:province":"Niedersachsen",
    "wof:name":"Klaus Launert",
    "wof:placetype":"venue"
},
  "geometry": {"coordinates":[9.8962926865,51.5250358582],"type":"Point"}
}