{
  "type": "Feature",
  "properties": {
    "iso:country":"DE",
    "sg:address":"Bahnhofsvorplatz 11",
    "sg:city":"Ratingen",
    "sg:phone":"+49 2102/6180",
    "sg:postcode":"40883",
    "sg:province":"Nordrhein-Westfalen",
    "wof:name":"Maria-theresien-stift",
    "wof:placetype":"venue"
},
  "geometry": {"coordinates":[6.893671,51.341194],"type":"Point"}
}