{
  "type": "Feature",
  "properties": {
    "iso:country":"DE",
    "sg:address":"Oranienstr. 71",
    "sg:city":"Berlin",
    "sg:postcode":"10969",
    "sg:province":"Berlin",
    "wof:name":"Grieben & Polland Gmbh & Co. Kg",
    "wof:placetype":"venue"
},
  "geometry": {"coordinates":[13.4068994522,52.504863739],"type":"Point"}
}