{
  "type": "Feature",
  "properties": {
    "iso:country":"DE",
    "sg:address":"Pestalozzistr. 15",
    "sg:city":"Ha\u00dfloch",
    "sg:phone":"+49 6324/2080",
    "sg:postcode":"67454",
    "sg:province":"Rheinland-Pfalz",
    "wof:name":"Hans Findeis Masseur",
    "wof:placetype":"venue"
},
  "geometry": {"coordinates":[8.247718,49.358456],"type":"Point"}
}