{
  "type": "Feature",
  "properties": {
    "iso:country":"DE",
    "sg:address":"Schlei\u00dfheimer Str. 201",
    "sg:city":"M\u00fcnchen",
    "sg:phone":"+49 89/3086725",
    "sg:postcode":"80809",
    "sg:province":"Bayern",
    "wof:name":"Claudia Neubauer",
    "wof:placetype":"venue"
},
  "geometry": {"coordinates":[11.5641927719,48.171005249],"type":"Point"}
}