{
  "type": "Feature",
  "properties": {
    "iso:country":"DE",
    "sg:address":"Tegernseer Landstr. 98",
    "sg:city":"M\u00fcnchen",
    "sg:phone":"+49 89/6517250",
    "sg:postcode":"81539",
    "sg:province":"Bayern",
    "wof:name":"Die Videothek",
    "wof:placetype":"venue"
},
  "geometry": {"coordinates":[11.5780248642,48.1138839722],"type":"Point"}
}