{
  "type": "Feature",
  "properties": {
    "iso:country":"DE",
    "sg:address":"Seestr. 46",
    "sg:city":"Filderstadt",
    "sg:phone":"+49 4971/583027",
    "sg:postcode":"70794",
    "sg:province":"Baden-W\u00fcrttemberg",
    "wof:name":"Ebs-bauelemente Gmbh",
    "wof:placetype":"venue"
},
  "geometry": {"coordinates":[9.22822,48.670799],"type":"Point"}
}