{
  "type": "Feature",
  "properties": {
    "iso:country":"DE",
    "sg:address":"Herrlichkeit 25",
    "sg:city":"Weeze",
    "sg:phone":"+49 2837/7109",
    "sg:postcode":"47652",
    "sg:province":"Nordrhein-Westfalen",
    "wof:name":"Matthias Moll",
    "wof:placetype":"venue"
},
  "geometry": {"coordinates":[6.205784,51.624992],"type":"Point"}
}