{
  "type": "Feature",
  "properties": {
    "iso:country":"DE",
    "sg:address":"Wielandstr. 27-28",
    "sg:city":"Berlin",
    "sg:phone":"+49 30/8827381",
    "sg:postcode":"10707",
    "sg:province":"Berlin",
    "wof:name":"Modus M\u00f6bel Gmbh",
    "wof:placetype":"venue"
},
  "geometry": {"coordinates":[13.315172,52.500366],"type":"Point"}
}