{
  "type": "Feature",
  "properties": {
    "iso:country":"DE",
    "sg:address":"Birmecker Weg 13",
    "sg:city":"Meschede",
    "sg:phone":"+49 291/51212",
    "sg:postcode":"59872",
    "sg:province":"Nordrhein-Westfalen",
    "wof:name":"Architektur- U. Ing.-b\u00fcro Schindler Und Partner",
    "wof:placetype":"venue"
},
  "geometry": {"coordinates":[8.33018,51.354912],"type":"Point"}
}