{
  "type": "Feature",
  "properties": {
    "iso:country":"DE",
    "sg:address":"R\u00f6merstr. 8",
    "sg:city":"M\u00fcnstermaifeld",
    "sg:phone":"+49 2605/1417",
    "sg:postcode":"56294",
    "sg:province":"Rheinland-Pfalz",
    "wof:name":"Kurt Sesterhenn",
    "wof:placetype":"venue"
},
  "geometry": {"coordinates":[7.365059,50.244511],"type":"Point"}
}