{
  "type": "Feature",
  "properties": {
    "iso:country":"DE",
    "sg:address":"Br\u00fcckenstr. 19",
    "sg:city":"Nidda",
    "sg:phone":"+49 6043/2733",
    "sg:postcode":"63667",
    "sg:province":"Hessen",
    "wof:name":"Karl-heinz Fischer",
    "wof:placetype":"venue"
},
  "geometry": {"coordinates":[9.022444725,50.4367828369],"type":"Point"}
}