{
  "type": "Feature",
  "properties": {
    "iso:country":"DE",
    "sg:address":"Heinrich-Heine-Str. 28",
    "sg:city":"Hainichen",
    "sg:phone":"+49 37207/3682",
    "sg:postcode":"09661",
    "sg:province":"Sachsen",
    "wof:name":"Dr. W. Weidlich Heilprakiker",
    "wof:placetype":"venue"
},
  "geometry": {"coordinates":[13.1184577942,50.9711952209],"type":"Point"}
}