{
  "type": "Feature",
  "properties": {
    "iso:country":"DE",
    "sg:address":"Hauptstr. 23 a",
    "sg:city":"Pettstadt",
    "sg:phone":"+49 9502/315",
    "sg:postcode":"96175",
    "sg:province":"Bayern",
    "wof:name":"Herbert M\u00fcller-pr\u00f6ls Bildhauer",
    "wof:placetype":"venue"
},
  "geometry": {"coordinates":[10.930383,49.831177],"type":"Point"}
}