{
  "type": "Feature",
  "properties": {
    "iso:country":"DE",
    "sg:address":"Bruckrath 23",
    "sg:city":"Nettetal",
    "sg:phone":"+49 2153/71025",
    "sg:postcode":"41334",
    "sg:province":"Nordrhein-Westfalen",
    "wof:name":"W. Kox",
    "wof:placetype":"venue"
},
  "geometry": {"coordinates":[6.23274,51.28294],"type":"Point"}
}