{
  "type": "Feature",
  "properties": {
    "iso:country":"DE",
    "sg:address":"Rumeyplan 8",
    "sg:city":"Berlin",
    "sg:phone":"+49 30/78703954",
    "sg:postcode":"12101",
    "sg:province":"Berlin",
    "wof:name":"Tuskulum Gmbh",
    "wof:placetype":"venue"
},
  "geometry": {"coordinates":[13.3807458878,52.4763679504],"type":"Point"}
}