{
  "type": "Feature",
  "properties": {
    "iso:country":"DE",
    "sg:address":"Bredstedter Str. 16a",
    "sg:city":"Breklum",
    "sg:phone":"+49 4671/6988",
    "sg:postcode":"25821",
    "sg:province":"Schleswig-Holstein",
    "wof:name":"Gesellschaft F\u00fcr Schall- Schutz Riddorf Mbh",
    "wof:placetype":"venue"
},
  "geometry": {"coordinates":[8.983891,54.614304],"type":"Point"}
}