{
  "type": "Feature",
  "properties": {
    "iso:country":"DE",
    "sg:address":"Hauptstr. 166",
    "sg:city":"K\u00f6ln",
    "sg:phone":"+49 2203/84735",
    "sg:postcode":"51143",
    "sg:province":"Nordrhein-Westfalen",
    "wof:name":"Im B\u00f6\u00f6tche",
    "wof:placetype":"venue"
},
  "geometry": {"coordinates":[7.0452561378,50.8687858582],"type":"Point"}
}