{
  "type": "Feature",
  "properties": {
    "iso:country":"DE",
    "sg:address":"Philadelphiastr. 86",
    "sg:city":"Krefeld",
    "sg:phone":"+49 2151/20905",
    "sg:postcode":"47799",
    "sg:province":"Nordrhein-Westfalen",
    "wof:name":"Garda",
    "wof:placetype":"venue"
},
  "geometry": {"coordinates":[6.5726971626,51.3315467834],"type":"Point"}
}