{
  "type": "Feature",
  "properties": {
    "iso:country":"DE",
    "sg:address":"Tesdorpfstr. 22",
    "sg:city":"Hamburg",
    "sg:phone":"+49 40/4501240",
    "sg:postcode":"20148",
    "sg:province":"Hamburg",
    "wof:name":"L\u00fcders & Partner Ohg",
    "wof:placetype":"venue"
},
  "geometry": {"coordinates":[9.9944248199,53.5649185181],"type":"Point"}
}