{
  "type": "Feature",
  "properties": {
    "iso:country":"DE",
    "sg:address":"Hachener Str. 94",
    "sg:city":"Sundern",
    "sg:phone":"+49 2935/4122",
    "sg:postcode":"59846",
    "sg:province":"Nordrhein-Westfalen",
    "wof:name":"Ulrich Br\u00fcggen",
    "wof:placetype":"venue"
},
  "geometry": {"coordinates":[7.9805188179,51.3741035461],"type":"Point"}
}