{
  "type": "Feature",
  "properties": {
    "iso:country":"DE",
    "sg:address":"Kopernikusplatz 9",
    "sg:city":"N\u00fcrnberg",
    "sg:phone":"+49 911/435799",
    "sg:postcode":"90459",
    "sg:province":"Bayern",
    "wof:name":"Kurt Astel",
    "wof:placetype":"venue"
},
  "geometry": {"coordinates":[11.0812749863,49.439289093],"type":"Point"}
}