{
  "type": "Feature",
  "properties": {
    "iso:country":"DE",
    "sg:address":"Obere Gasse 1",
    "sg:city":"Satteldorf",
    "sg:phone":"+49 7951/5360",
    "sg:postcode":"74589",
    "sg:province":"Baden-W\u00fcrttemberg",
    "wof:name":"H. Palatzky Heiz\u00f6lhandlung",
    "wof:placetype":"venue"
},
  "geometry": {"coordinates":[10.0813417435,49.1706542969],"type":"Point"}
}