{
  "type": "Feature",
  "properties": {
    "iso:country":"DE",
    "sg:address":"Lange Str. 29",
    "sg:city":"Goldberg",
    "sg:phone":"+49 38736/41187",
    "sg:postcode":"19399",
    "sg:province":"Mecklenburg-Vorpommern",
    "wof:name":"G\u00fcnter Ladewig",
    "wof:placetype":"venue"
},
  "geometry": {"coordinates":[12.088838,53.592537],"type":"Point"}
}