{
  "type": "Feature",
  "properties": {
    "iso:country":"DE",
    "sg:address":"Beeskower Chaussee 29",
    "sg:city":"Storkow",
    "sg:phone":"+49 33678/72796",
    "sg:postcode":"15859",
    "sg:province":"Brandenburg",
    "wof:name":"A. Daniel",
    "wof:placetype":"venue"
},
  "geometry": {"coordinates":[13.9361886978,52.2453308105],"type":"Point"}
}