{
  "type": "Feature",
  "properties": {
    "iso:country":"DE",
    "sg:address":"Georgenstr. 10",
    "sg:city":"Meuselwitz",
    "sg:phone":"+49 3448/2138",
    "sg:postcode":"04610",
    "sg:province":"Th\u00fcringen",
    "wof:name":"Helfried Hanisch",
    "wof:placetype":"venue"
},
  "geometry": {"coordinates":[12.2987670898,51.0419044495],"type":"Point"}
}