{
  "type": "Feature",
  "properties": {
    "iso:country":"DE",
    "sg:address":"Friedhofstr. 12",
    "sg:city":"Mackenbach",
    "sg:phone":"+49 6374/6466",
    "sg:postcode":"67686",
    "sg:province":"Rheinland-Pfalz",
    "wof:name":"Magda Thiele",
    "wof:placetype":"venue"
},
  "geometry": {"coordinates":[7.5853128433,49.4732513428],"type":"Point"}
}