{
  "type": "Feature",
  "properties": {
    "iso:country":"DE",
    "sg:address":"Borna 10",
    "sg:city":"Bahretal",
    "sg:phone":"+49 35025/50212",
    "sg:postcode":"01819",
    "sg:province":"Sachsen",
    "wof:name":"S\u00e4chsische Baustoffunion Dresden Ag",
    "wof:placetype":"venue"
},
  "geometry": {"coordinates":[13.8915920258,50.8810806274],"type":"Point"}
}