{
  "type": "Feature",
  "properties": {
    "iso:country":"DE",
    "sg:address":"Meistersingerstr. 15",
    "sg:city":"Bayreuth",
    "sg:phone":"+49 921/84100",
    "sg:postcode":"95444",
    "sg:province":"Bayern",
    "wof:name":"Pflege Zu Hause E. V.",
    "wof:placetype":"venue"
},
  "geometry": {"coordinates":[11.576368,49.954628],"type":"Point"}
}