{
  "type": "Feature",
  "properties": {
    "iso:country":"DE",
    "sg:address":"August-Spindler-Str. 6",
    "sg:city":"G\u00f6ttingen",
    "sg:phone":"+49 551/66224",
    "sg:postcode":"37079",
    "sg:province":"Niedersachsen",
    "wof:name":"Burkhard Hampel",
    "wof:placetype":"venue"
},
  "geometry": {"coordinates":[9.892539978,51.5505218506],"type":"Point"}
}