{
  "type": "Feature",
  "properties": {
    "iso:country":"DE",
    "sg:address":"Am Wochenmarkt 3",
    "sg:city":"Enkirch",
    "sg:phone":"+49 6541/9622",
    "sg:postcode":"56850",
    "sg:province":"Rheinland-Pfalz",
    "wof:name":"Karl Kettermann",
    "wof:placetype":"venue"
},
  "geometry": {"coordinates":[7.1260957718,49.9829711914],"type":"Point"}
}