{
  "type": "Feature",
  "properties": {
    "iso:country":"DE",
    "sg:address":"Hauptstr. 47c",
    "sg:city":"Weitenhagen",
    "sg:phone":"+49 3834/811038",
    "sg:postcode":"17498",
    "sg:province":"Mecklenburg-Vorpommern",
    "wof:name":"D. Fiedler",
    "wof:placetype":"venue"
},
  "geometry": {"coordinates":[13.4173269272,54.0517692566],"type":"Point"}
}