{
  "type": "Feature",
  "properties": {
    "iso:country":"DE",
    "sg:address":"Falkensteiner Str. 35",
    "sg:city":"Mechelgr\u00fcn",
    "sg:phone":"+49 37463/88488",
    "sg:postcode":"08541",
    "sg:province":"Sachsen",
    "wof:name":"Dr. W. Hager Anlageberater",
    "wof:placetype":"venue"
},
  "geometry": {"coordinates":[12.2389326096,50.4852523804],"type":"Point"}
}