{
  "type": "Feature",
  "properties": {
    "iso:country":"DE",
    "sg:address":"Fritz-Stra\u00dfmann-Str. 8",
    "sg:city":"Elmshorn",
    "sg:phone":"+49 4121/47250",
    "sg:postcode":"25337",
    "sg:province":"Schleswig-Holstein",
    "wof:name":"H. Borger & Co. Gmbh",
    "wof:placetype":"venue"
},
  "geometry": {"coordinates":[9.6953668594,53.7436141968],"type":"Point"}
}