{
  "type": "Feature",
  "properties": {
    "iso:country":"DE",
    "sg:address":"Gutenbergstr. 28",
    "sg:city":"Metzingen",
    "sg:phone":"+49 7123/4394",
    "sg:postcode":"72555",
    "sg:province":"Baden-W\u00fcrttemberg",
    "wof:name":"P. Kilgus",
    "wof:placetype":"venue"
},
  "geometry": {"coordinates":[9.275018692,48.5454673767],"type":"Point"}
}