{
  "type": "Feature",
  "properties": {
    "iso:country":"DE",
    "sg:address":"Schanzstr. 2",
    "sg:city":"Lohr",
    "sg:phone":"+49 9355/417",
    "sg:postcode":"97816",
    "sg:province":"Bayern",
    "wof:name":"H. Inderwies",
    "wof:placetype":"venue"
},
  "geometry": {"coordinates":[9.5439500809,50.0819854736],"type":"Point"}
}