{
  "type": "Feature",
  "properties": {
    "iso:country":"DE",
    "sg:address":"M\u00fcnsterstr. 59",
    "sg:city":"Warendorf",
    "sg:phone":"+49 2581/2223",
    "sg:postcode":"48231",
    "sg:province":"Nordrhein-Westfalen",
    "wof:name":"Schulze-schleppinghoff",
    "wof:placetype":"venue"
},
  "geometry": {"coordinates":[7.9812707901,51.9538612366],"type":"Point"}
}