{
  "type": "Feature",
  "properties": {
    "iso:country":"DE",
    "sg:address":"Kirchplatz 8",
    "sg:city":"Pocking",
    "sg:phone":"+49 8531/8445",
    "sg:postcode":"94060",
    "sg:province":"Bayern",
    "wof:name":"Robert Altmann",
    "wof:placetype":"venue"
},
  "geometry": {"coordinates":[13.3091897964,48.4016876221],"type":"Point"}
}