{
  "type": "Feature",
  "properties": {
    "iso:country":"DE",
    "sg:address":"Hagerweg 25",
    "sg:city":"Krefeld",
    "sg:phone":"+49 2151/774100",
    "sg:postcode":"47798",
    "sg:province":"Nordrhein-Westfalen",
    "wof:name":"Barbara Stocken-bernhardt Architektin",
    "wof:placetype":"venue"
},
  "geometry": {"coordinates":[6.551249,51.325512],"type":"Point"}
}