{
  "type": "Feature",
  "properties": {
    "iso:country":"DE",
    "sg:address":"Fehrbacher Str. 42",
    "sg:city":"Pirmasens",
    "sg:phone":"+49 6331/93903",
    "sg:postcode":"66954",
    "sg:province":"Rheinland-Pfalz",
    "wof:name":"Waldesruh",
    "wof:placetype":"venue"
},
  "geometry": {"coordinates":[7.5645480156,49.2224807739],"type":"Point"}
}