{
  "type": "Feature",
  "properties": {
    "iso:country":"DE",
    "sg:address":"Bahnhofstr. 22",
    "sg:city":"Leisnig",
    "sg:postcode":"04703",
    "sg:province":"Sachsen",
    "wof:name":"Wwv Waserwiederverwendungs- Anlagen Gmbh",
    "wof:placetype":"venue"
},
  "geometry": {"coordinates":[12.9357652664,51.1590881348],"type":"Point"}
}