{
  "type": "Feature",
  "properties": {
    "iso:country":"DE",
    "sg:address":"Obere Str. 27",
    "sg:city":"Vahlbruch",
    "sg:phone":"+49 5535/461",
    "sg:postcode":"37647",
    "sg:province":"Niedersachsen",
    "wof:name":"Ferdinand Stukenberg",
    "wof:placetype":"venue"
},
  "geometry": {"coordinates":[9.341608,51.921688],"type":"Point"}
}