{
  "type": "Feature",
  "properties": {
    "iso:country":"DE",
    "sg:address":"Jan-Pallach-Str. 8",
    "sg:city":"Hildesheim",
    "sg:phone":"+49 5121/54910",
    "sg:postcode":"31134",
    "sg:province":"Niedersachsen",
    "wof:name":"Rainher S\u00e4nger Heilpraktiker",
    "wof:placetype":"venue"
},
  "geometry": {"coordinates":[9.9535102844,52.1577529907],"type":"Point"}
}