{
  "type": "Feature",
  "properties": {
    "iso:country":"DE",
    "sg:address":"Heinrich-W\u00f6hler-Str. 16 B",
    "sg:city":"Burgwedel",
    "sg:phone":"+49 5139/893050",
    "sg:postcode":"30938",
    "sg:province":"Niedersachsen",
    "wof:name":"Falke Gmbh",
    "wof:placetype":"venue"
},
  "geometry": {"coordinates":[9.8455600739,52.4914131165],"type":"Point"}
}