{
  "type": "Feature",
  "properties": {
    "iso:country":"DE",
    "sg:address":"Fischzug 1",
    "sg:city":"Salzgitter",
    "sg:postcode":"38226",
    "sg:province":"Niedersachsen",
    "wof:name":"Reise & Touristik C. Gahre Gmbh",
    "wof:placetype":"venue"
},
  "geometry": {"coordinates":[10.3316278458,52.1529769897],"type":"Point"}
}