{
  "type": "Feature",
  "properties": {
    "iso:country":"DE",
    "sg:address":"Amelner Str.",
    "sg:city":"Titz",
    "sg:phone":"+49 2463/8731",
    "sg:postcode":"52445",
    "sg:province":"Nordrhein-Westfalen",
    "wof:name":"Zimmermann",
    "wof:placetype":"venue"
},
  "geometry": {"coordinates":[6.4244,51.00423],"type":"Point"}
}