{
  "type": "Feature",
  "properties": {
    "iso:country":"DE",
    "sg:address":"Friedrichstra\u00dfe 21",
    "sg:city":"Ludwigshafen",
    "sg:phone":"+49 621/651061",
    "sg:postcode":"67069",
    "sg:province":"Rheinland-Pfalz",
    "wof:name":"Dres. Cremonese Und Hoecker",
    "wof:placetype":"venue"
},
  "geometry": {"coordinates":[8.402996,49.518974],"type":"Point"}
}