{
  "type": "Feature",
  "properties": {
    "iso:country":"DE",
    "sg:address":"Hauptstr. 13",
    "sg:city":"Zwickau",
    "sg:phone":"+49 375/291160",
    "sg:postcode":"08056",
    "sg:province":"Sachsen",
    "wof:name":"Lokalanzeiger",
    "wof:placetype":"venue"
},
  "geometry": {"coordinates":[12.4963817596,50.7184181213],"type":"Point"}
}