{
  "type": "Feature",
  "properties": {
    "iso:country":"DE",
    "sg:address":"Wiesenweg 4",
    "sg:city":"Schneeberg",
    "sg:phone":"+49 3772/21812",
    "sg:postcode":"08289",
    "sg:province":"Sachsen",
    "wof:name":"Pension S. Lengerer",
    "wof:placetype":"venue"
},
  "geometry": {"coordinates":[12.6247816086,50.601978302],"type":"Point"}
}