{
  "type": "Feature",
  "properties": {
    "iso:country":"DE",
    "sg:address":"Hohenzollernring 86",
    "sg:city":"K\u00f6ln",
    "sg:phone":"+49 221/1390561",
    "sg:postcode":"50672",
    "sg:province":"Nordrhein-Westfalen",
    "wof:name":"Ivg Immobilien Vermietungsges. Mbh",
    "wof:placetype":"venue"
},
  "geometry": {"coordinates":[6.9405021667,50.9418449402],"type":"Point"}
}