{
  "type": "Feature",
  "properties": {
    "iso:country":"DE",
    "sg:address":"Marienfelder Str. 93",
    "sg:city":"Herzebrock-Clarholz",
    "sg:phone":"+49 5245/9020",
    "sg:postcode":"33442",
    "sg:province":"Nordrhein-Westfalen",
    "wof:name":"P\u00f6tter Verwaltungs Gmbh",
    "wof:placetype":"venue"
},
  "geometry": {"coordinates":[8.200339,51.911163],"type":"Point"}
}