{
  "type": "Feature",
  "properties": {
    "iso:country":"DE",
    "sg:address":"Marktstr. 21",
    "sg:city":"Siegen",
    "sg:phone":"+49 271/870000",
    "sg:postcode":"57078",
    "sg:province":"Nordrhein-Westfalen",
    "wof:name":"Versicherungsb\u00fcro Benfer & M\u00fcller",
    "wof:placetype":"venue"
},
  "geometry": {"coordinates":[8.0112667084,50.9157066345],"type":"Point"}
}