{
  "type": "Feature",
  "properties": {
    "iso:country":"DE",
    "sg:address":"W\u00e4gnerstr. 2",
    "sg:city":"Dresden",
    "sg:phone":"+49 351/8804484",
    "sg:postcode":"01309",
    "sg:province":"Sachsen",
    "wof:name":"Winfried Unger",
    "wof:placetype":"venue"
},
  "geometry": {"coordinates":[13.7967500687,51.0522842407],"type":"Point"}
}