{
  "type": "Feature",
  "properties": {
    "iso:country":"DE",
    "sg:address":"Marburger Str. 6",
    "sg:city":"Wetter",
    "sg:phone":"+49 6423/6467",
    "sg:postcode":"35083",
    "sg:province":"Hessen",
    "wof:name":"J\u00fcrgen Weide",
    "wof:placetype":"venue"
},
  "geometry": {"coordinates":[8.7290859222,50.9044265747],"type":"Point"}
}