{
  "type": "Feature",
  "properties": {
    "iso:country":"DE",
    "sg:address":"Lange Str. 21",
    "sg:city":"Wolgast",
    "sg:phone":"+49 3836/202876",
    "sg:postcode":"17438",
    "sg:province":"Mecklenburg-Vorpommern",
    "wof:name":"Ostsee- Reiseb\u00fcro Wolgast",
    "wof:placetype":"venue"
},
  "geometry": {"coordinates":[13.778063,54.053928],"type":"Point"}
}