{
  "type": "Feature",
  "properties": {
    "iso:country":"DE",
    "sg:address":"Berliner Str. 32",
    "sg:city":"Frankfurt",
    "sg:postcode":"60311",
    "sg:province":"Hessen",
    "wof:name":"Europe Gate Gmbh",
    "wof:placetype":"venue"
},
  "geometry": {"coordinates":[8.6826219559,50.1120300293],"type":"Point"}
}