{
  "type": "Feature",
  "properties": {
    "iso:country":"DE",
    "sg:address":"Balinger Str. 17",
    "sg:city":"Rosenfeld",
    "sg:phone":"+49 7428/93060",
    "sg:postcode":"72348",
    "sg:province":"Baden-W\u00fcrttemberg",
    "wof:name":"H. S\u00fclzle Eisenwaren Gmbh",
    "wof:placetype":"venue"
},
  "geometry": {"coordinates":[8.7250232697,48.2866439819],"type":"Point"}
}