{
  "type": "Feature",
  "properties": {
    "iso:country":"DE",
    "sg:address":"Heidestr. 153",
    "sg:city":"Frankfurt",
    "sg:phone":"+49 69/458647",
    "sg:postcode":"60385",
    "sg:province":"Hessen",
    "wof:name":"Monolyth Kunst Kult & Buch Gmbh",
    "wof:placetype":"venue"
},
  "geometry": {"coordinates":[8.7082805634,50.1276931763],"type":"Point"}
}