{
  "type": "Feature",
  "properties": {
    "iso:country":"DE",
    "sg:address":"Raiffeisenstr. 18",
    "sg:city":"H\u00fcrth",
    "sg:phone":"+49 2233/45027",
    "sg:postcode":"50354",
    "sg:province":"Nordrhein-Westfalen",
    "wof:name":"Theo Bischof",
    "wof:placetype":"venue"
},
  "geometry": {"coordinates":[6.8984928131,50.8616867065],"type":"Point"}
}