{
  "type": "Feature",
  "properties": {
    "iso:country":"DE",
    "sg:address":"Deller Str. 1",
    "sg:city":"Solingen",
    "sg:phone":"+49 212/313492",
    "sg:postcode":"42719",
    "sg:province":"Nordrhein-Westfalen",
    "wof:name":"Artur K\u00f6nig",
    "wof:placetype":"venue"
},
  "geometry": {"coordinates":[7.0497207642,51.1913986206],"type":"Point"}
}