{
  "type": "Feature",
  "properties": {
    "iso:country":"DE",
    "sg:address":"Elisabeth-Walter-Str. 16",
    "sg:city":"Neckargem\u00fcnd",
    "sg:phone":"+49 6223/8888",
    "sg:postcode":"69151",
    "sg:province":"Baden-W\u00fcrttemberg",
    "wof:name":"Erwin Scheerer",
    "wof:placetype":"venue"
},
  "geometry": {"coordinates":[8.793757,49.392052],"type":"Point"}
}