{
  "type": "Feature",
  "properties": {
    "iso:country":"DE",
    "sg:address":"Ratzeburger Allee 83",
    "sg:city":"L\u00fcbeck",
    "sg:phone":"+49 451/594021",
    "sg:postcode":"23562",
    "sg:province":"Schleswig-Holstein",
    "wof:name":"Grill-mahlzeit",
    "wof:placetype":"venue"
},
  "geometry": {"coordinates":[10.708319664,53.8449630737],"type":"Point"}
}