{
  "type": "Feature",
  "properties": {
    "iso:country":"DE",
    "sg:address":"Erdmannstr. 18",
    "sg:city":"Hamburg",
    "sg:phone":"+49 40/3992750",
    "sg:postcode":"22765",
    "sg:province":"Hamburg",
    "wof:name":"F. Brinke & Company Gmbh",
    "wof:placetype":"venue"
},
  "geometry": {"coordinates":[9.9239816666,53.5535736084],"type":"Point"}
}