{
  "type": "Feature",
  "properties": {
    "iso:country":"DE",
    "sg:address":"Dorfstr. 1",
    "sg:city":"N\u00f6rdlingen",
    "sg:phone":"+49 9081/9929",
    "sg:postcode":"86720",
    "sg:province":"Bayern",
    "wof:name":"Gerhard Feldmeier",
    "wof:placetype":"venue"
},
  "geometry": {"coordinates":[10.548229,48.892624],"type":"Point"}
}