{
  "type": "Feature",
  "properties": {
    "iso:country":"DE",
    "sg:address":"Wernsbacher Str. 14",
    "sg:city":"Windsbach",
    "sg:phone":"+49 9871/67170",
    "sg:postcode":"91575",
    "sg:province":"Bayern",
    "wof:name":"N-ergie Aktiengesellschaft",
    "wof:placetype":"venue"
},
  "geometry": {"coordinates":[10.819136,49.253288],"type":"Point"}
}