{
  "type": "Feature",
  "properties": {
    "iso:country":"DE",
    "sg:address":"Hambrinker Heide 27",
    "sg:city":"Bielefeld",
    "sg:phone":"+49 5241/67154",
    "sg:postcode":"33649",
    "sg:province":"Nordrhein-Westfalen",
    "wof:name":"Helmut Aschentrup",
    "wof:placetype":"venue"
},
  "geometry": {"coordinates":[8.4309654236,51.9636535645],"type":"Point"}
}