{
  "type": "Feature",
  "properties": {
    "iso:country":"DE",
    "sg:address":"Laubenweg 1a",
    "sg:city":"Glau",
    "sg:phone":"+49 33731/15693",
    "sg:postcode":"14959",
    "sg:province":"Brandenburg",
    "wof:name":"Bauhof Neumann & M\u00f6ller",
    "wof:placetype":"venue"
},
  "geometry": {"coordinates":[13.162595,52.242016],"type":"Point"}
}