{
  "type": "Feature",
  "properties": {
    "iso:country":"DE",
    "sg:address":"72250",
    "sg:city":"Freudenstadt",
    "sg:phone":"+49 7441/2029",
    "sg:postcode":"72250",
    "sg:province":"Baden-W\u00fcrttemberg",
    "wof:name":"Schwimmhalle",
    "wof:placetype":"venue"
},
  "geometry": {"coordinates":[8.4422302246,48.4904899597],"type":"Point"}
}