{
  "type": "Feature",
  "properties": {
    "iso:country":"DE",
    "sg:address":"Christian-Wei\u00df-Str. 2",
    "sg:city":"Taucha",
    "sg:phone":"+49 34298/66218",
    "sg:postcode":"04425",
    "sg:province":"Sachsen",
    "wof:name":"T. B\u00f6hm & G. Dittrich Gbr.",
    "wof:placetype":"venue"
},
  "geometry": {"coordinates":[12.491778,51.39064],"type":"Point"}
}