{
  "type": "Feature",
  "properties": {
    "iso:country":"DE",
    "sg:address":"Am Steinacker 9",
    "sg:city":"Langen",
    "sg:phone":"+49 4743/5143",
    "sg:postcode":"27607",
    "sg:province":"Niedersachsen",
    "wof:name":"Johann Splitje",
    "wof:placetype":"venue"
},
  "geometry": {"coordinates":[8.63581,53.622299],"type":"Point"}
}