{
  "type": "Feature",
  "properties": {
    "iso:country":"DE",
    "sg:address":"Gartenstr. 13",
    "sg:city":"Gro\u00dfr\u00e4schen",
    "sg:phone":"+49 35753/15797",
    "sg:postcode":"01983",
    "sg:province":"Brandenburg",
    "wof:name":"O. Weise",
    "wof:placetype":"venue"
},
  "geometry": {"coordinates":[14.011534,51.588512],"type":"Point"}
}