{
  "type": "Feature",
  "properties": {
    "iso:country":"DE",
    "sg:address":"Sonnenstr. 48",
    "sg:city":"Waldaschaff",
    "sg:phone":"+49 6095/2302",
    "sg:postcode":"63857",
    "sg:province":"Bayern",
    "wof:name":"Hans Braun",
    "wof:placetype":"venue"
},
  "geometry": {"coordinates":[9.2941417694,49.9745597839],"type":"Point"}
}