{
  "type": "Feature",
  "properties": {
    "iso:country":"DE",
    "sg:address":"Baarsen 29",
    "sg:city":"Bad Pyrmont",
    "sg:phone":"+49 5285/274",
    "sg:postcode":"31812",
    "sg:province":"Niedersachsen",
    "wof:name":"W. Heide",
    "wof:placetype":"venue"
},
  "geometry": {"coordinates":[9.3228607178,51.9458389282],"type":"Point"}
}