{
  "type": "Feature",
  "properties": {
    "iso:country":"DE",
    "sg:address":"K\u00f6lner Str. 59",
    "sg:city":"Troisdorf",
    "sg:phone":"+49 2241/76291",
    "sg:postcode":"53840",
    "sg:province":"Nordrhein-Westfalen",
    "wof:name":"C\u00e4cilie M\u00fcller",
    "wof:placetype":"venue"
},
  "geometry": {"coordinates":[7.157612,50.815147],"type":"Point"}
}