{
  "type": "Feature",
  "properties": {
    "iso:country":"DE",
    "sg:address":"Waldstr. 4-2",
    "sg:city":"Ditzingen",
    "sg:phone":"+49 7156/951523",
    "sg:postcode":"71254",
    "sg:province":"Baden-W\u00fcrttemberg",
    "wof:name":"G. Wei\u00df",
    "wof:placetype":"venue"
},
  "geometry": {"coordinates":[9.0259447098,48.8499107361],"type":"Point"}
}