{
  "type": "Feature",
  "properties": {
    "iso:country":"DE",
    "sg:address":"Ostfrieslandstr. 33",
    "sg:city":"Hamburg",
    "sg:phone":"+49 40/7429002",
    "sg:postcode":"21129",
    "sg:province":"Hamburg",
    "wof:name":"Der Waffenshop",
    "wof:placetype":"venue"
},
  "geometry": {"coordinates":[9.8791151047,53.5294075012],"type":"Point"}
}