{
  "type": "Feature",
  "properties": {
    "iso:country":"DE",
    "sg:address":"M\u00fchlweg 5",
    "sg:city":"Rainau",
    "sg:phone":"+49 7961/53602",
    "sg:postcode":"73492",
    "sg:province":"Baden-W\u00fcrttemberg",
    "wof:name":"Gaab Verwaltungs- Gmbh",
    "wof:placetype":"venue"
},
  "geometry": {"coordinates":[10.144795,48.928669],"type":"Point"}
}