{
  "type": "Feature",
  "properties": {
    "iso:country":"DE",
    "sg:address":"Platz der Jugend 6",
    "sg:city":"Rathenow",
    "sg:phone":"+49 3385/498383",
    "sg:postcode":"14712",
    "sg:province":"Brandenburg",
    "wof:name":"Havelland Druckerei Rathenow Gmbh",
    "wof:placetype":"venue"
},
  "geometry": {"coordinates":[12.3334197998,52.6080513],"type":"Point"}
}