{
  "type": "Feature",
  "properties": {
    "iso:country":"DE",
    "sg:address":"Kreuzhofstr. 2",
    "sg:city":"Neutraubling",
    "sg:phone":"+49 9401/80357",
    "sg:postcode":"93073",
    "sg:province":"Bayern",
    "wof:name":"Herwig Feddersen",
    "wof:placetype":"venue"
},
  "geometry": {"coordinates":[12.1905355453,48.9939842224],"type":"Point"}
}