{
  "type": "Feature",
  "properties": {
    "iso:country":"DE",
    "sg:address":"Hauptstr. 34",
    "sg:city":"Selm",
    "sg:phone":"+49 2592/62833",
    "sg:postcode":"59379",
    "sg:province":"Nordrhein-Westfalen",
    "wof:name":"E. Dahlkamp",
    "wof:placetype":"venue"
},
  "geometry": {"coordinates":[7.4651727676,51.6654319763],"type":"Point"}
}