{
  "type": "Feature",
  "properties": {
    "iso:country":"DE",
    "sg:address":"Zum Sonnenberg 5",
    "sg:city":"Gelnhausen",
    "sg:phone":"+49 6051/962101",
    "sg:postcode":"63571",
    "sg:province":"Hessen",
    "wof:name":"Storeconcept Ladenbau Gmbh",
    "wof:placetype":"venue"
},
  "geometry": {"coordinates":[9.173009,50.186306],"type":"Point"}
}