{
  "type": "Feature",
  "properties": {
    "iso:country":"DE",
    "sg:address":"Hauptstr. 19",
    "sg:city":"Bad W\u00fcnnenberg",
    "sg:phone":"+49 2953/98000",
    "sg:postcode":"33181",
    "sg:province":"Nordrhein-Westfalen",
    "wof:name":"A. Kaiser",
    "wof:placetype":"venue"
},
  "geometry": {"coordinates":[8.656386,51.517879],"type":"Point"}
}