{
  "type": "Feature",
  "properties": {
    "iso:country":"DE",
    "sg:address":"Steimelstr. 8",
    "sg:city":"Langelsheim",
    "sg:phone":"+49 5326/85635",
    "sg:postcode":"38685",
    "sg:province":"Niedersachsen",
    "wof:name":"Heinrich Wilgeroth",
    "wof:placetype":"venue"
},
  "geometry": {"coordinates":[10.332359,51.938496],"type":"Point"}
}