{
  "type": "Feature",
  "properties": {
    "iso:country":"DE",
    "sg:address":"Schanzstr. 98",
    "sg:city":"Ludwigshafen",
    "sg:phone":"+49 621/517756",
    "sg:postcode":"67063",
    "sg:province":"Rheinland-Pfalz",
    "wof:name":"Thessaloniki",
    "wof:placetype":"venue"
},
  "geometry": {"coordinates":[8.4311189651,49.4876327515],"type":"Point"}
}