{
  "type": "Feature",
  "properties": {
    "iso:country":"DE",
    "sg:address":"Hocksteiner Weg 30 POSTFACH 400116",
    "sg:city":"M\u00f6nchengladbach",
    "sg:phone":"+49 4921/6613300",
    "sg:postcode":"41181",
    "sg:province":"Nordrhein-Westfalen",
    "wof:name":"Stahlwerk Stahlschmidt Gmbh",
    "wof:placetype":"venue"
},
  "geometry": {"coordinates":[6.413688,51.137657],"type":"Point"}
}