{
  "type": "Feature",
  "properties": {
    "iso:country":"DE",
    "sg:address":"Wilhelmstr. 10",
    "sg:city":"Reutlingen",
    "sg:phone":"+49 7121/311142",
    "sg:postcode":"72764",
    "sg:province":"Baden-W\u00fcrttemberg",
    "wof:name":"G. Kerassidis \u00dcbersetzungsb\u00fcro",
    "wof:placetype":"venue"
},
  "geometry": {"coordinates":[9.21014,48.493771],"type":"Point"}
}