{
  "type": "Feature",
  "properties": {
    "iso:country":"DE",
    "sg:address":"Turmweg 2",
    "sg:city":"Hankensb\u00fcttel",
    "sg:phone":"+49 5832/6306",
    "sg:postcode":"29386",
    "sg:province":"Niedersachsen",
    "wof:name":"Angelikas Videotreff",
    "wof:placetype":"venue"
},
  "geometry": {"coordinates":[10.593708992,52.7270278931],"type":"Point"}
}