{
  "type": "Feature",
  "properties": {
    "iso:country":"DE",
    "sg:address":"Kaiserin-Augusta-Allee 5",
    "sg:city":"Berlin",
    "sg:phone":"+49 30/3248032",
    "sg:postcode":"10553",
    "sg:province":"Berlin",
    "wof:name":"Ingenieurb\u00fcro F\u00fcr Bauwesen Professor Burkhardt Gmbh",
    "wof:placetype":"venue"
},
  "geometry": {"coordinates":[13.326143,52.52496],"type":"Point"}
}