{
  "type": "Feature",
  "properties": {
    "iso:country":"DE",
    "sg:address":"Am Hohen Berg 15",
    "sg:city":"Biebergem\u00fcnd",
    "sg:phone":"+49 6050/1319",
    "sg:postcode":"63599",
    "sg:province":"Hessen",
    "wof:name":"Pension Haus Wally",
    "wof:placetype":"venue"
},
  "geometry": {"coordinates":[9.2741336823,50.1754570007],"type":"Point"}
}