{
  "type": "Feature",
  "properties": {
    "iso:country":"DE",
    "sg:address":"Kleine Rittergasse 4",
    "sg:city":"Frankfurt",
    "sg:postcode":"60594",
    "sg:province":"Hessen",
    "wof:name":"Gradjevinsko Promentno Preduzece Lord Sa P.o.",
    "wof:placetype":"venue"
},
  "geometry": {"coordinates":[8.690447,50.106007],"type":"Point"}
}