{
  "type": "Feature",
  "properties": {
    "iso:country":"DE",
    "sg:address":"Kurf\u00fcrstenstr. 9",
    "sg:city":"Schwetzingen",
    "sg:phone":"+49 6202/22722",
    "sg:postcode":"68723",
    "sg:province":"Baden-W\u00fcrttemberg",
    "wof:name":"Gerd B. Schornick Masseur",
    "wof:placetype":"venue"
},
  "geometry": {"coordinates":[8.579456,49.385303],"type":"Point"}
}