{
  "type": "Feature",
  "properties": {
    "iso:country":"DE",
    "sg:address":"Clayallee 354",
    "sg:city":"Berlin",
    "sg:phone":"+49 30/8927047",
    "sg:postcode":"14169",
    "sg:province":"Berlin",
    "wof:name":"Meyer Klemke Und Montag",
    "wof:placetype":"venue"
},
  "geometry": {"coordinates":[13.2611036301,52.4356117249],"type":"Point"}
}