{
  "type": "Feature",
  "properties": {
    "iso:country":"DE",
    "sg:address":"Rathausstr. 29",
    "sg:city":"Buchen",
    "sg:phone":"+49 6292/250",
    "sg:postcode":"74722",
    "sg:province":"Baden-W\u00fcrttemberg",
    "wof:name":"Adler",
    "wof:placetype":"venue"
},
  "geometry": {"coordinates":[9.3667764664,49.4775810242],"type":"Point"}
}