{
  "type": "Feature",
  "properties": {
    "iso:country":"DE",
    "sg:address":"Beethovenstr. 25",
    "sg:city":"Solingen",
    "sg:phone":"+49 212/13501",
    "sg:postcode":"42655",
    "sg:province":"Nordrhein-Westfalen",
    "wof:name":"Detlev Ludwig",
    "wof:placetype":"venue"
},
  "geometry": {"coordinates":[7.070726,51.175571],"type":"Point"}
}