{
  "type": "Feature",
  "properties": {
    "iso:country":"DE",
    "sg:address":"Ostuferhafen 9",
    "sg:city":"Kiel",
    "sg:phone":"+49 431/209770",
    "sg:postcode":"24149",
    "sg:province":"Schleswig-Holstein",
    "wof:name":"Ksh Kieler Schrotthandel Gmbh",
    "wof:placetype":"venue"
},
  "geometry": {"coordinates":[10.1737270355,54.3325004578],"type":"Point"}
}