{
  "type": "Feature",
  "properties": {
    "iso:country":"DE",
    "sg:address":"Sandgasse 26",
    "sg:city":"Aschaffenburg",
    "sg:postcode":"63739",
    "sg:province":"Bayern",
    "wof:name":"Sport-shop Kuhn & Weber Gmbh",
    "wof:placetype":"venue"
},
  "geometry": {"coordinates":[9.148317,49.974297],"type":"Point"}
}