{
  "type": "Feature",
  "properties": {
    "iso:country":"DE",
    "sg:address":"Gro\u00dfe Str. 43",
    "sg:city":"Gehrden",
    "sg:phone":"+49 5108/6154",
    "sg:postcode":"30989",
    "sg:province":"Niedersachsen",
    "wof:name":"Dr. Hans-joachim Hackbarth Garten- Und",
    "wof:placetype":"venue"
},
  "geometry": {"coordinates":[9.60234,52.348476],"type":"Point"}
}