{
  "type": "Feature",
  "properties": {
    "iso:country":"DE",
    "sg:address":"Weberstr. 11",
    "sg:city":"Heidelberg",
    "sg:phone":"+49 6221/64240",
    "sg:postcode":"69120",
    "sg:province":"Baden-W\u00fcrttemberg",
    "wof:name":"Herbert Rost",
    "wof:placetype":"venue"
},
  "geometry": {"coordinates":[8.6883220673,49.4183349609],"type":"Point"}
}