{
  "type": "Feature",
  "properties": {
    "iso:country":"DE",
    "sg:address":"Heegbarg 31",
    "sg:city":"Hamburg",
    "sg:phone":"+49 40/6022573",
    "sg:postcode":"22391",
    "sg:province":"Hamburg",
    "wof:name":"Walter Lorenz",
    "wof:placetype":"venue"
},
  "geometry": {"coordinates":[10.092378,53.652729],"type":"Point"}
}