{
  "type": "Feature",
  "properties": {
    "iso:country":"DE",
    "sg:address":"Klopstockstr. 1",
    "sg:city":"Stuttgart",
    "sg:phone":"+49 711/638244",
    "sg:postcode":"70193",
    "sg:province":"Baden-W\u00fcrttemberg",
    "wof:name":"Dr. Horst W\u00f6lpert Rechtsanwalt",
    "wof:placetype":"venue"
},
  "geometry": {"coordinates":[9.1559877396,48.7795372009],"type":"Point"}
}