{
  "type": "Feature",
  "properties": {
    "iso:country":"DE",
    "sg:address":"Siebentischstr. 5",
    "sg:city":"Augsburg",
    "sg:phone":"+49 821/552109",
    "sg:postcode":"86161",
    "sg:province":"Bayern",
    "wof:name":"Hans Holl Elektroinstallation",
    "wof:placetype":"venue"
},
  "geometry": {"coordinates":[10.915514,48.354691],"type":"Point"}
}