{
  "type": "Feature",
  "properties": {
    "iso:country":"DE",
    "sg:address":"Bertha-von-Suttner-Str. 2",
    "sg:city":"Magdeburg",
    "sg:phone":"+49 391/7335692",
    "sg:postcode":"39108",
    "sg:province":"Sachsen-Anhalt",
    "wof:name":"Dieter Ramdohr",
    "wof:placetype":"venue"
},
  "geometry": {"coordinates":[11.625182,52.136642],"type":"Point"}
}