{
  "type": "Feature",
  "properties": {
    "iso:country":"DE",
    "sg:address":"Eschenweg 1",
    "sg:city":"Chieming",
    "sg:postcode":"83339",
    "sg:province":"Bayern",
    "wof:name":"Wolfgang Mock Gmbh",
    "wof:placetype":"venue"
},
  "geometry": {"coordinates":[12.534570694,47.8953971863],"type":"Point"}
}