{
  "type": "Feature",
  "properties": {
    "iso:country":"DE",
    "sg:address":"Tobertitzer Str. 4",
    "sg:city":"Rodau",
    "sg:phone":"+49 37435/5264",
    "sg:postcode":"08539",
    "sg:province":"Sachsen",
    "wof:name":"Walfried Neumeister",
    "wof:placetype":"venue"
},
  "geometry": {"coordinates":[11.991133,50.504486],"type":"Point"}
}