{
  "type": "Feature",
  "properties": {
    "iso:country":"DE",
    "sg:address":"Potosistr. 12",
    "sg:city":"Hamburg",
    "sg:postcode":"22587",
    "sg:province":"Hamburg",
    "wof:name":"Berlina Projektentwicklungs- Gesellschaft Mbh",
    "wof:placetype":"venue"
},
  "geometry": {"coordinates":[9.8043298721,53.5663299561],"type":"Point"}
}