{
  "type": "Feature",
  "properties": {
    "iso:country":"DE",
    "sg:address":"Schwaaner Landstr. 38",
    "sg:city":"Rostock",
    "sg:postcode":"18059",
    "sg:province":"Mecklenburg-Vorpommern",
    "wof:name":"Abacus-sicherheitsunternehmen Rostock Gmbh",
    "wof:placetype":"venue"
},
  "geometry": {"coordinates":[12.1285219193,54.0606956482],"type":"Point"}
}