{
  "type": "Feature",
  "properties": {
    "iso:country":"DE",
    "sg:address":"Tengerner Str. 144",
    "sg:city":"H\u00fcllhorst",
    "sg:phone":"+49 5744/1389",
    "sg:postcode":"32609",
    "sg:province":"Nordrhein-Westfalen",
    "wof:name":"Hermann Knickmeier Gmbh",
    "wof:placetype":"venue"
},
  "geometry": {"coordinates":[8.7013425827,52.2572517395],"type":"Point"}
}