{
  "type": "Feature",
  "properties": {
    "iso:country":"DE",
    "sg:address":"Selerweg 42",
    "sg:city":"Berlin",
    "sg:phone":"+49 30/7959917",
    "sg:postcode":"12169",
    "sg:province":"Berlin",
    "wof:name":"Willi Vogel",
    "wof:placetype":"venue"
},
  "geometry": {"coordinates":[13.3374547958,52.4539833069],"type":"Point"}
}