{
  "type": "Feature",
  "properties": {
    "iso:country":"DE",
    "sg:address":"M\u00f6hringer Str. 14",
    "sg:city":"Unlingen",
    "sg:phone":"+49 7371/7025",
    "sg:postcode":"88527",
    "sg:province":"Baden-W\u00fcrttemberg",
    "wof:name":"Hans App Gmbh",
    "wof:placetype":"venue"
},
  "geometry": {"coordinates":[9.527373,48.16811],"type":"Point"}
}