{
  "type": "Feature",
  "properties": {
    "iso:country":"DE",
    "sg:address":"Dockenhudener Chaussee 96",
    "sg:city":"Halstenbek",
    "sg:phone":"+49 4101/41323",
    "sg:postcode":"25469",
    "sg:province":"Schleswig-Holstein",
    "wof:name":"Arthur Pein",
    "wof:placetype":"venue"
},
  "geometry": {"coordinates":[9.828843,53.625511],"type":"Point"}
}