{
  "type": "Feature",
  "properties": {
    "iso:country":"DE",
    "sg:address":"An der Ringmauer 6",
    "sg:city":"Marienheide",
    "sg:postcode":"51709",
    "sg:province":"Nordrhein-Westfalen",
    "wof:name":"Irene Henning-bieler Heilpraktikerin",
    "wof:placetype":"venue"
},
  "geometry": {"coordinates":[7.5341701508,51.0828285217],"type":"Point"}
}