{
  "type": "Feature",
  "properties": {
    "iso:country":"DE",
    "sg:address":"Ost-West-Str. 12",
    "sg:city":"Rostock",
    "sg:postcode":"18147",
    "sg:province":"Mecklenburg-Vorpommern",
    "wof:name":"Gode Michel Hochseeangeln Und Seetouristik",
    "wof:placetype":"venue"
},
  "geometry": {"coordinates":[12.1144323349,54.1454696655],"type":"Point"}
}