{
  "type": "Feature",
  "properties": {
    "iso:country":"DE",
    "sg:address":"Lange Reihe 83",
    "sg:city":"Hamburg",
    "sg:phone":"+49 40/247582",
    "sg:postcode":"20099",
    "sg:province":"Hamburg",
    "wof:name":"R\u00fcdiger Trepka Ingenieur",
    "wof:placetype":"venue"
},
  "geometry": {"coordinates":[10.0123128891,53.558429718],"type":"Point"}
}