{
  "type": "Feature",
  "properties": {
    "iso:country":"DE",
    "sg:address":"Hauptstr. 7",
    "sg:city":"Riedstadt",
    "sg:phone":"+49 6158/72682",
    "sg:postcode":"64560",
    "sg:province":"Hessen",
    "wof:name":"Anna Arnold",
    "wof:placetype":"venue"
},
  "geometry": {"coordinates":[8.447651,49.858215],"type":"Point"}
}