{
  "type": "Feature",
  "properties": {
    "iso:country":"DE",
    "sg:address":"Spitalhofstr. 18 b",
    "sg:city":"Stuttgart",
    "sg:postcode":"70437",
    "sg:province":"Baden-W\u00fcrttemberg",
    "wof:name":"Ff-theaterbedarf",
    "wof:placetype":"venue"
},
  "geometry": {"coordinates":[9.199189,48.839897],"type":"Point"}
}