{
  "type": "Feature",
  "properties": {
    "iso:country":"DE",
    "sg:address":"Ladestr. 9",
    "sg:city":"Welver",
    "sg:phone":"+49 2384/708",
    "sg:postcode":"59514",
    "sg:province":"Nordrhein-Westfalen",
    "wof:name":"B\u00e4uerliche Bezugs- Und Absatzgenossenschaft Werl Eg",
    "wof:placetype":"venue"
},
  "geometry": {"coordinates":[7.958942,51.616432],"type":"Point"}
}