{
  "type": "Feature",
  "properties": {
    "iso:country":"DE",
    "sg:address":"Friedrich-Wilhelm-Platz",
    "sg:city":"Aachen",
    "sg:phone":"+49 241/48800",
    "sg:postcode":"52062",
    "sg:province":"Nordrhein-Westfalen",
    "wof:name":"Proviro",
    "wof:placetype":"venue"
},
  "geometry": {"coordinates":[6.087395,50.774216],"type":"Point"}
}