{
  "type": "Feature",
  "properties": {
    "iso:country":"DE",
    "sg:address":"Wilhelmstr. 11",
    "sg:city":"Albstadt",
    "sg:phone":"+49 7432/25395",
    "sg:postcode":"72461",
    "sg:province":"Baden-W\u00fcrttemberg",
    "wof:name":"S Kneiple",
    "wof:placetype":"venue"
},
  "geometry": {"coordinates":[9.001832962,48.2845306396],"type":"Point"}
}