{
  "type": "Feature",
  "properties": {
    "iso:country":"DE",
    "sg:address":"Konrad-Celtis-Str. 30",
    "sg:city":"M\u00fcnchen",
    "sg:phone":"+49 89/7602559",
    "sg:postcode":"81369",
    "sg:province":"Bayern",
    "wof:name":"Parf\u00fcmerie Himmer Gmbh",
    "wof:placetype":"venue"
},
  "geometry": {"coordinates":[11.530494,48.111168],"type":"Point"}
}