{
  "type": "Feature",
  "properties": {
    "iso:country":"DE",
    "sg:address":"Belgradstr. 1",
    "sg:city":"M\u00fcnchen",
    "sg:phone":"+49 89/3082991",
    "sg:postcode":"80796",
    "sg:province":"Bayern",
    "wof:name":"M. Baasel",
    "wof:placetype":"venue"
},
  "geometry": {"coordinates":[11.5748605728,48.1606559753],"type":"Point"}
}