{
  "type": "Feature",
  "properties": {
    "iso:country":"DE",
    "sg:address":"Am Jadebusen 14",
    "sg:city":"Bockhorn",
    "sg:phone":"+49 4453/988070",
    "sg:postcode":"26345",
    "sg:province":"Niedersachsen",
    "wof:name":"Carstengerdes Modellbau Gmbh",
    "wof:placetype":"venue"
},
  "geometry": {"coordinates":[8.063175,53.454376],"type":"Point"}
}