{
  "type": "Feature",
  "properties": {
    "iso:country":"DE",
    "sg:address":"Schulzengasse 22a",
    "sg:city":"Eningen",
    "sg:phone":"+49 7121/82952",
    "sg:postcode":"72800",
    "sg:province":"Baden-W\u00fcrttemberg",
    "wof:name":"Manfred Sautter",
    "wof:placetype":"venue"
},
  "geometry": {"coordinates":[9.257094,48.484818],"type":"Point"}
}