{
  "type": "Feature",
  "properties": {
    "iso:country":"DE",
    "sg:address":"Dorfstrasse 29",
    "sg:city":"Leipe",
    "sg:phone":"+49 3542/2234",
    "sg:postcode":"03226",
    "sg:province":"Brandenburg",
    "wof:name":"Spreewaldhotel Leipe; Spreewaldhotel Raddusch",
    "wof:placetype":"venue"
},
  "geometry": {"coordinates":[14.0640296936,51.7741203308],"type":"Point"}
}