{
  "type": "Feature",
  "properties": {
    "iso:country":"DE",
    "sg:address":"Josef-Heeger-Str. 4",
    "sg:city":"Rimpar",
    "sg:phone":"+49 9365/9804",
    "sg:postcode":"97222",
    "sg:province":"Bayern",
    "wof:name":"Alfred Baumeister",
    "wof:placetype":"venue"
},
  "geometry": {"coordinates":[9.96401,49.852283],"type":"Point"}
}