{
  "type": "Feature",
  "properties": {
    "iso:country":"DE",
    "sg:address":"Lange Str. 13",
    "sg:city":"Westerstede",
    "sg:phone":"+49 4488/72181",
    "sg:postcode":"26655",
    "sg:province":"Niedersachsen",
    "wof:name":"Brillenhaus Bruns Inh. Wilfried Bruns E. K.",
    "wof:placetype":"venue"
},
  "geometry": {"coordinates":[7.9249868393,53.2576446533],"type":"Point"}
}