{
  "type": "Feature",
  "properties": {
    "iso:country":"DE",
    "sg:address":"Rurstr. 17",
    "sg:city":"Simmerath",
    "sg:phone":"+49 2485/204",
    "sg:postcode":"52152",
    "sg:province":"Nordrhein-Westfalen",
    "wof:name":"U. Und R. H\u00fcpgen",
    "wof:placetype":"venue"
},
  "geometry": {"coordinates":[6.38012,50.582829],"type":"Point"}
}