{
  "type": "Feature",
  "properties": {
    "iso:country":"DE",
    "sg:address":"Domplatz 1",
    "sg:city":"G\u00fcstrow",
    "sg:phone":"+49 3843/682406",
    "sg:postcode":"18273",
    "sg:province":"Mecklenburg-Vorpommern",
    "wof:name":"Kirchliches Meldeamt G\u00fcstrow",
    "wof:placetype":"venue"
},
  "geometry": {"coordinates":[12.17342,53.790859],"type":"Point"}
}