{
  "type": "Feature",
  "properties": {
    "iso:country":"DE",
    "sg:address":"R\u00f6\u00dflesm\u00fchlestr. 3",
    "sg:city":"Sindelfingen",
    "sg:phone":"+49 7031/760910",
    "sg:postcode":"71063",
    "sg:province":"Baden-W\u00fcrttemberg",
    "wof:name":"J\u00f6rg Schachtschabel",
    "wof:placetype":"venue"
},
  "geometry": {"coordinates":[8.9977321625,48.7094650269],"type":"Point"}
}