{
  "type": "Feature",
  "properties": {
    "iso:country":"DE",
    "sg:address":"Valentin-Becker-Str. 2",
    "sg:city":"W\u00fcrzburg",
    "sg:phone":"+49 931/571213",
    "sg:postcode":"97072",
    "sg:province":"Bayern",
    "wof:name":"Restaurant Pizza Connection",
    "wof:placetype":"venue"
},
  "geometry": {"coordinates":[9.9434518814,49.7909889221],"type":"Point"}
}