{
  "type": "Feature",
  "properties": {
    "iso:country":"DE",
    "sg:address":"Pfarrstr. 14",
    "sg:city":"Dachau",
    "sg:phone":"+49 8131/86167",
    "sg:postcode":"85221",
    "sg:province":"Bayern",
    "wof:name":"Vera Holzer",
    "wof:placetype":"venue"
},
  "geometry": {"coordinates":[11.43588,48.260281],"type":"Point"}
}