{
  "type": "Feature",
  "properties": {
    "iso:country":"DE",
    "sg:address":"Gro\u00dfe Str. 29",
    "sg:city":"Ahlden",
    "sg:phone":"+49 5164/1425",
    "sg:postcode":"29693",
    "sg:province":"Niedersachsen",
    "wof:name":"Friedr.-wilh. Helberg",
    "wof:placetype":"venue"
},
  "geometry": {"coordinates":[9.55356,52.760818],"type":"Point"}
}