{
  "type": "Feature",
  "properties": {
    "iso:country":"DE",
    "sg:address":"Gr\u00fcner Weg 30",
    "sg:city":"Datteln",
    "sg:phone":"+49 2363/31217",
    "sg:postcode":"45711",
    "sg:province":"Nordrhein-Westfalen",
    "wof:name":"Gastst\u00e4tte A. Dickh\u00f6fer",
    "wof:placetype":"venue"
},
  "geometry": {"coordinates":[7.3417887688,51.6575660706],"type":"Point"}
}