{
  "type": "Feature",
  "properties": {
    "iso:country":"DE",
    "sg:address":"Bahnhofstr. 13 c",
    "sg:city":"B\u00fctzow",
    "sg:phone":"+49 38461/3029",
    "sg:postcode":"18246",
    "sg:province":"Mecklenburg-Vorpommern",
    "wof:name":"Ellen Gerigk",
    "wof:placetype":"venue"
},
  "geometry": {"coordinates":[11.9925804138,53.8451271057],"type":"Point"}
}