{
  "type": "Feature",
  "properties": {
    "iso:country":"DE",
    "sg:address":"Charlottenstr. 1",
    "sg:city":"D\u00fcsseldorf",
    "sg:phone":"+49 211/363025",
    "sg:postcode":"40210",
    "sg:province":"Nordrhein-Westfalen",
    "wof:name":"Wmz 24 Immobilien Gmbh",
    "wof:placetype":"venue"
},
  "geometry": {"coordinates":[6.7860770226,51.2192230225],"type":"Point"}
}