{
  "type": "Feature",
  "properties": {
    "iso:country":"DE",
    "sg:address":"Unter den Linden 7",
    "sg:city":"Soltau",
    "sg:phone":"+49 5191/13737",
    "sg:postcode":"29614",
    "sg:province":"Niedersachsen",
    "wof:name":"Behrendt Touristikservice",
    "wof:placetype":"venue"
},
  "geometry": {"coordinates":[9.8361930847,52.989238739],"type":"Point"}
}