{
  "type": "Feature",
  "properties": {
    "iso:country":"DE",
    "sg:address":"Lumdastr. 2",
    "sg:city":"Gr\u00fcnberg",
    "sg:phone":"+49 6401/7289",
    "sg:postcode":"35305",
    "sg:province":"Hessen",
    "wof:name":"Andreas Swoboda",
    "wof:placetype":"venue"
},
  "geometry": {"coordinates":[8.9419803619,50.6343002319],"type":"Point"}
}