{
  "type": "Feature",
  "properties": {
    "iso:country":"DE",
    "sg:address":"Hauptstr. 85",
    "sg:city":"Schutterwald",
    "sg:phone":"+49 781/52422",
    "sg:postcode":"77746",
    "sg:province":"Baden-W\u00fcrttemberg",
    "wof:name":"Fortuna",
    "wof:placetype":"venue"
},
  "geometry": {"coordinates":[7.8845629692,48.4534797668],"type":"Point"}
}