{
  "type": "Feature",
  "properties": {
    "iso:country":"DE",
    "sg:address":"Hochstr. 61",
    "sg:city":"Andernach",
    "sg:phone":"+49 2632/43102",
    "sg:postcode":"56626",
    "sg:province":"Rheinland-Pfalz",
    "wof:name":"M. Reinert",
    "wof:placetype":"venue"
},
  "geometry": {"coordinates":[7.401476,50.439877],"type":"Point"}
}