{
  "type": "Feature",
  "properties": {
    "iso:country":"DE",
    "sg:address":"Hauptstr. 19",
    "sg:city":"Balesfeld",
    "sg:phone":"+49 6553/92700",
    "sg:postcode":"54597",
    "sg:province":"Rheinland-Pfalz",
    "wof:name":"Seniorenhaus St. Josef Gmbh",
    "wof:placetype":"venue"
},
  "geometry": {"coordinates":[6.5311,50.10659],"type":"Point"}
}