{
  "type": "Feature",
  "properties": {
    "iso:country":"DE",
    "sg:address":"Schnerkinger Str. 9",
    "sg:city":"Me\u00dfkirch",
    "sg:phone":"+49 7575/2399",
    "sg:postcode":"88605",
    "sg:province":"Baden-W\u00fcrttemberg",
    "wof:name":"Conradin-kreutzer-stube",
    "wof:placetype":"venue"
},
  "geometry": {"coordinates":[9.1149568558,47.9910087585],"type":"Point"}
}