{
  "type": "Feature",
  "properties": {
    "iso:country":"DE",
    "sg:address":"Wurth 3",
    "sg:city":"Ostrau",
    "sg:phone":"+49 34600/21610",
    "sg:postcode":"06193",
    "sg:province":"Sachsen-Anhalt",
    "wof:name":"Born & Bellmann Musik- Verlag Und Produktion Gmbh",
    "wof:placetype":"venue"
},
  "geometry": {"coordinates":[12.0164318085,51.6174087524],"type":"Point"}
}