{
  "type": "Feature",
  "properties": {
    "iso:country":"DE",
    "sg:address":"Ziegelgasse 19",
    "sg:city":"Freising",
    "sg:phone":"+49 8161/919860",
    "sg:postcode":"85354",
    "sg:province":"Bayern",
    "wof:name":"Irene Burkhardt Ingenieurin",
    "wof:placetype":"venue"
},
  "geometry": {"coordinates":[11.7416887283,48.4010543823],"type":"Point"}
}