{
  "type": "Feature",
  "properties": {
    "iso:country":"DE",
    "sg:address":"Burschlaer Feld 5",
    "sg:city":"Wei\u00dfenborn",
    "sg:phone":"+49 5659/92070",
    "sg:postcode":"37299",
    "sg:province":"Hessen",
    "wof:name":"Theodor Koch",
    "wof:placetype":"venue"
},
  "geometry": {"coordinates":[10.1198797226,51.1258964539],"type":"Point"}
}