{
  "type": "Feature",
  "properties": {
    "iso:country":"DE",
    "sg:address":"Hauptstr. 2",
    "sg:city":"Haimhausen",
    "sg:phone":"+49 8133/2050",
    "sg:postcode":"85778",
    "sg:province":"Bayern",
    "wof:name":"Josef St\u00f6rzer Ohg",
    "wof:placetype":"venue"
},
  "geometry": {"coordinates":[11.5492038727,48.3121910095],"type":"Point"}
}