{
  "type": "Feature",
  "properties": {
    "iso:country":"DE",
    "sg:address":"Eidelstedter Brook 6",
    "sg:city":"Hamburg",
    "sg:phone":"+49 40/5503569",
    "sg:postcode":"22457",
    "sg:province":"Hamburg",
    "wof:name":"Klaus Bulke",
    "wof:placetype":"venue"
},
  "geometry": {"coordinates":[9.907894,53.623081],"type":"Point"}
}