{
  "type": "Feature",
  "properties": {
    "iso:country":"DE",
    "sg:address":"Kapuzinergasse 7-9",
    "sg:city":"Aachen",
    "sg:phone":"+49 241/166949",
    "sg:postcode":"52068",
    "sg:province":"Nordrhein-Westfalen",
    "wof:name":"Deja Vu Bekleidungsfabrikation Gmbh",
    "wof:placetype":"venue"
},
  "geometry": {"coordinates":[6.10393,50.781044],"type":"Point"}
}