{
  "type": "Feature",
  "properties": {
    "iso:country":"DE",
    "sg:address":"Mozartstr. 35",
    "sg:city":"Donzdorf",
    "sg:phone":"+49 7162/23310",
    "sg:postcode":"73072",
    "sg:province":"Baden-W\u00fcrttemberg",
    "wof:name":"Textilmarkt-eisel Gmbh & Co. Kg",
    "wof:placetype":"venue"
},
  "geometry": {"coordinates":[9.796541214,48.6856994629],"type":"Point"}
}