{
  "type": "Feature",
  "properties": {
    "iso:country":"DE",
    "sg:address":"Bachstr. 10",
    "sg:city":"Laer",
    "sg:postcode":"48366",
    "sg:province":"Nordrhein-Westfalen",
    "wof:name":"Dietmar Pfohe",
    "wof:placetype":"venue"
},
  "geometry": {"coordinates":[7.356838,52.053623],"type":"Point"}
}