{
  "type": "Feature",
  "properties": {
    "iso:country":"DE",
    "sg:address":"Lehmgrubenstr. 62",
    "sg:city":"Zell",
    "sg:phone":"+49 931/467043",
    "sg:postcode":"97299",
    "sg:province":"Bayern",
    "wof:name":"Frank Mayer Malerbetrieb Gmbh",
    "wof:placetype":"venue"
},
  "geometry": {"coordinates":[9.866523,49.809887],"type":"Point"}
}