{
  "type": "Feature",
  "properties": {
    "iso:country":"DE",
    "sg:address":"Thomas-M\u00fcntzer-Str. 15a",
    "sg:city":"Strasburg",
    "sg:phone":"+49 39753/21309",
    "sg:postcode":"17335",
    "sg:province":"Mecklenburg-Vorpommern",
    "wof:name":"Strasburger Wohnungsgenossenschaft Eg",
    "wof:placetype":"venue"
},
  "geometry": {"coordinates":[13.7205600739,53.6019935608],"type":"Point"}
}