{
  "type": "Feature",
  "properties": {
    "iso:country":"DE",
    "sg:address":"Wellenburger Str. 41",
    "sg:city":"Augsburg",
    "sg:phone":"+49 821/995510",
    "sg:postcode":"86199",
    "sg:province":"Bayern",
    "wof:name":"Franz X. Schmid",
    "wof:placetype":"venue"
},
  "geometry": {"coordinates":[10.859596,48.338745],"type":"Point"}
}