{
  "type": "Feature",
  "properties": {
    "iso:country":"DE",
    "sg:address":"Wesloer Str. 60-62",
    "sg:city":"L\u00fcbeck",
    "sg:phone":"+49 451/690733",
    "sg:postcode":"23568",
    "sg:province":"Schleswig-Holstein",
    "wof:name":"Fritz Bibow Aral-tankstelle",
    "wof:placetype":"venue"
},
  "geometry": {"coordinates":[10.7878055573,53.8848571777],"type":"Point"}
}