{
  "type": "Feature",
  "properties": {
    "iso:country":"DE",
    "sg:address":"Kirchplatz 4",
    "sg:city":"Oberhausen",
    "sg:phone":"+49 8435/316",
    "sg:postcode":"86697",
    "sg:province":"Bayern",
    "wof:name":"Johann Faigl",
    "wof:placetype":"venue"
},
  "geometry": {"coordinates":[11.112759,48.720039],"type":"Point"}
}