{
  "type": "Feature",
  "properties": {
    "iso:country":"DE",
    "sg:address":"Anne-Frank-Weg 69",
    "sg:city":"Plochingen",
    "sg:phone":"+49 7153/898803",
    "sg:postcode":"73207",
    "sg:province":"Baden-W\u00fcrttemberg",
    "wof:name":"Hans Pollin Heilpraktiker",
    "wof:placetype":"venue"
},
  "geometry": {"coordinates":[9.4348468781,48.7096138],"type":"Point"}
}