{
  "type": "Feature",
  "properties": {
    "iso:country":"DE",
    "sg:address":"K\u00f6nig-Wilhelm-Str. 56",
    "sg:city":"Ilsfeld",
    "sg:phone":"+49 7062/95450",
    "sg:postcode":"74360",
    "sg:province":"Baden-W\u00fcrttemberg",
    "wof:name":"Dr. G\u00fcnter Zecher Rechtsanwalt",
    "wof:placetype":"venue"
},
  "geometry": {"coordinates":[9.2448234558,49.0552635193],"type":"Point"}
}