{
  "type": "Feature",
  "properties": {
    "iso:country":"DE",
    "sg:address":"Zur Feldm\u00fchle 21",
    "sg:city":"Arnsberg",
    "sg:phone":"+49 2931/1875",
    "sg:postcode":"59821",
    "sg:province":"Nordrhein-Westfalen",
    "wof:name":"Bernhard Cruse Gmbh & Co. Kg",
    "wof:placetype":"venue"
},
  "geometry": {"coordinates":[8.0723695755,51.3936347961],"type":"Point"}
}