{
  "type": "Feature",
  "properties": {
    "iso:country":"DE",
    "sg:address":"Hagermarscher Str. 8",
    "sg:city":"Hage",
    "sg:phone":"+49 4931/74095",
    "sg:postcode":"26524",
    "sg:province":"Niedersachsen",
    "wof:name":"Tr\u00f6delhof-caf\u00e9",
    "wof:placetype":"venue"
},
  "geometry": {"coordinates":[7.291962,53.60598],"type":"Point"}
}