{
  "type": "Feature",
  "properties": {
    "iso:country":"DE",
    "sg:address":"Subbelrather Str. 274",
    "sg:city":"K\u00f6ln",
    "sg:phone":"+49 221/5502642",
    "sg:postcode":"50825",
    "sg:province":"Nordrhein-Westfalen",
    "wof:name":"Knobelbecher",
    "wof:placetype":"venue"
},
  "geometry": {"coordinates":[6.9171791077,50.9551124573],"type":"Point"}
}