{
  "type": "Feature",
  "properties": {
    "iso:country":"DE",
    "sg:address":"Obertor 5",
    "sg:city":"Ilfeld",
    "sg:postcode":"99768",
    "sg:province":"Th\u00fcringen",
    "wof:name":"Dr. Winterberg Verm\u00f6gens- Und Beteiligungsgesellschaft Mbh",
    "wof:placetype":"venue"
},
  "geometry": {"coordinates":[10.783963,51.582348],"type":"Point"}
}