{
  "type": "Feature",
  "properties": {
    "iso:country":"DE",
    "sg:address":"M\u00f6wenstr. 25",
    "sg:city":"Friedrichshafen",
    "sg:postcode":"88045",
    "sg:province":"Baden-W\u00fcrttemberg",
    "wof:name":"Cds-commodity Data Systeme Paul Engel & Co. Ohg",
    "wof:placetype":"venue"
},
  "geometry": {"coordinates":[9.4472532272,47.6571502686],"type":"Point"}
}