{
  "type": "Feature",
  "properties": {
    "iso:country":"DE",
    "sg:address":"Michael-Imhof-Str. 16",
    "sg:city":"Donauw\u00f6rth",
    "sg:phone":"+49 906/3372",
    "sg:postcode":"86609",
    "sg:province":"Bayern",
    "wof:name":"Wohnbau-selbsthilfewerk Landkreis Donauries Eg",
    "wof:placetype":"venue"
},
  "geometry": {"coordinates":[10.795316,48.715508],"type":"Point"}
}