{
  "type": "Feature",
  "properties": {
    "iso:country":"DE",
    "sg:address":"Stedtener Str. 10b",
    "sg:city":"Kranichfeld",
    "sg:phone":"+49 36450/31427",
    "sg:postcode":"99448",
    "sg:province":"Th\u00fcringen",
    "wof:name":"Reinhard Schmidt",
    "wof:placetype":"venue"
},
  "geometry": {"coordinates":[11.1957674026,50.8505897522],"type":"Point"}
}