{
  "type": "Feature",
  "properties": {
    "iso:country":"DE",
    "sg:address":"Limesstr. 13",
    "sg:city":"Limeshain",
    "sg:phone":"+49 6047/950566",
    "sg:postcode":"63694",
    "sg:province":"Hessen",
    "wof:name":"Bartsch",
    "wof:placetype":"venue"
},
  "geometry": {"coordinates":[8.9634771347,50.2618103027],"type":"Point"}
}