{
  "type": "Feature",
  "properties": {
    "iso:country":"DE",
    "sg:address":"Lavesstr. 65",
    "sg:city":"Hannover",
    "sg:phone":"+49 511/321997",
    "sg:postcode":"30159",
    "sg:province":"Niedersachsen",
    "wof:name":"Dieter Hoppenworth",
    "wof:placetype":"venue"
},
  "geometry": {"coordinates":[9.749745369,52.3732070923],"type":"Point"}
}