{
  "type": "Feature",
  "properties": {
    "iso:country":"DE",
    "sg:address":"Kaiserstr. 7",
    "sg:city":"Langenfeld",
    "sg:phone":"+49 2173/72343",
    "sg:postcode":"40764",
    "sg:province":"Nordrhein-Westfalen",
    "wof:name":"Paul Patten Architekt",
    "wof:placetype":"venue"
},
  "geometry": {"coordinates":[6.946007,51.128368],"type":"Point"}
}