{
  "type": "Feature",
  "properties": {
    "iso:country":"DE",
    "sg:address":"Lange Str. 24",
    "sg:city":"B\u00f6blingen",
    "sg:phone":"+49 7031/49940",
    "sg:postcode":"71032",
    "sg:province":"Baden-W\u00fcrttemberg",
    "wof:name":"Hydrobar Hydraulik Und Pneumatik Gmbh",
    "wof:placetype":"venue"
},
  "geometry": {"coordinates":[9.0183105469,48.6835289001],"type":"Point"}
}