{
  "type": "Feature",
  "properties": {
    "iso:country":"DE",
    "sg:address":"Moosburger Str. 18",
    "sg:city":"Haag",
    "sg:phone":"+49 8761/61506",
    "sg:postcode":"85410",
    "sg:province":"Bayern",
    "wof:name":"G. Lobenstock",
    "wof:placetype":"venue"
},
  "geometry": {"coordinates":[11.8623819351,48.4643859863],"type":"Point"}
}