{
  "type": "Feature",
  "properties": {
    "iso:country":"DE",
    "sg:address":"Weststr. 34",
    "sg:city":"Aachen",
    "sg:phone":"+49 241/889630",
    "sg:postcode":"52074",
    "sg:province":"Nordrhein-Westfalen",
    "wof:name":"Hydro-soft Software Gmbh",
    "wof:placetype":"venue"
},
  "geometry": {"coordinates":[6.0602521896,50.771320343],"type":"Point"}
}