{
  "type": "Feature",
  "properties": {
    "iso:country":"DE",
    "sg:address":"Ziegelh\u00fcttenweg 1",
    "sg:city":"Frankfurt",
    "sg:postcode":"60598",
    "sg:province":"Hessen",
    "wof:name":"Enter Soft Gmbh",
    "wof:placetype":"venue"
},
  "geometry": {"coordinates":[8.6820878983,50.0949363708],"type":"Point"}
}