{
  "type": "Feature",
  "properties": {
    "iso:country":"DE",
    "sg:address":"Georg-B\u00fcchner-Str. 8",
    "sg:city":"B\u00fcttelborn",
    "sg:postcode":"64572",
    "sg:province":"Hessen",
    "wof:name":"Techres Gmbh",
    "wof:placetype":"venue"
},
  "geometry": {"coordinates":[8.50799,49.898697],"type":"Point"}
}