{
  "type": "Feature",
  "properties": {
    "iso:country":"DE",
    "sg:address":"Bahnhofstr. 27",
    "sg:city":"Aglasterhausen",
    "sg:phone":"+49 6262/3551",
    "sg:postcode":"74858",
    "sg:province":"Baden-W\u00fcrttemberg",
    "wof:name":"B. Scholl",
    "wof:placetype":"venue"
},
  "geometry": {"coordinates":[8.991271019,49.3515968323],"type":"Point"}
}