{
  "type": "Feature",
  "properties": {
    "iso:country":"DE",
    "sg:address":"Friesenweg 5H",
    "sg:city":"Hamburg",
    "sg:phone":"+49 40/88913103",
    "sg:postcode":"22763",
    "sg:province":"Hamburg",
    "wof:name":"Almag Pr\u00e4zisionstechnik Gmbh & Co Kg",
    "wof:placetype":"venue"
},
  "geometry": {"coordinates":[9.909618,53.558895],"type":"Point"}
}