{
  "type": "Feature",
  "properties": {
    "iso:country":"DE",
    "sg:address":"Mittermaierstr. 17",
    "sg:city":"Heidelberg",
    "sg:phone":"+49 6221/181713",
    "sg:postcode":"69115",
    "sg:province":"Baden-W\u00fcrttemberg",
    "wof:name":"W & S B\u00fcro- Und",
    "wof:placetype":"venue"
},
  "geometry": {"coordinates":[8.6771068573,49.4069099426],"type":"Point"}
}