{
  "type": "Feature",
  "properties": {
    "iso:country":"DE",
    "sg:address":"Osterwiesenstr. 9",
    "sg:city":"Iggingen",
    "sg:phone":"+49 7175/8042",
    "sg:postcode":"73574",
    "sg:province":"Baden-W\u00fcrttemberg",
    "wof:name":"Bruno Seibold",
    "wof:placetype":"venue"
},
  "geometry": {"coordinates":[9.867657,48.840534],"type":"Point"}
}