{
  "type": "Feature",
  "properties": {
    "iso:country":"DE",
    "sg:address":"Streitfeldstr. 28",
    "sg:city":"M\u00fcnchen",
    "sg:phone":"+49 89/43489966",
    "sg:postcode":"81673",
    "sg:province":"Bayern",
    "wof:name":"Dr. Ulrich Hocke Rechtsanwalt",
    "wof:placetype":"venue"
},
  "geometry": {"coordinates":[11.6186676025,48.1315078735],"type":"Point"}
}