{
  "type": "Feature",
  "properties": {
    "iso:country":"DE",
    "sg:address":"Maybachstr. 15",
    "sg:city":"Ludwigsburg",
    "sg:phone":"+49 7141/23120",
    "sg:postcode":"71634",
    "sg:province":"Baden-W\u00fcrttemberg",
    "wof:name":"Tobaccoland Gmbh & Co. Kg",
    "wof:placetype":"venue"
},
  "geometry": {"coordinates":[9.1430969238,48.9215049744],"type":"Point"}
}