{
  "type": "Feature",
  "properties": {
    "iso:country":"DE",
    "sg:address":"Glockengie\u00dferwall 26",
    "sg:city":"Hamburg",
    "sg:phone":"+49 40/3202720",
    "sg:postcode":"20095",
    "sg:province":"Hamburg",
    "wof:name":"Jensen An Der Lombardsbr\u00fccke",
    "wof:placetype":"venue"
},
  "geometry": {"coordinates":[10.0013933182,53.5551490784],"type":"Point"}
}