{
  "type": "Feature",
  "properties": {
    "iso:country":"DE",
    "sg:address":"Veilchenweg 74",
    "sg:city":"Esslingen",
    "sg:phone":"+49 711/312643",
    "sg:postcode":"73730",
    "sg:province":"Baden-W\u00fcrttemberg",
    "wof:name":"Beck Neuheiten Werbe- Und Vertriebs-",
    "wof:placetype":"venue"
},
  "geometry": {"coordinates":[9.3420286179,48.7287979126],"type":"Point"}
}