{
  "type": "Feature",
  "properties": {
    "iso:country":"DE",
    "sg:address":"Bl\u00fccherstr. 14",
    "sg:city":"Karlsruhe",
    "sg:phone":"+49 721/984224",
    "sg:postcode":"76185",
    "sg:province":"Baden-W\u00fcrttemberg",
    "wof:name":"Scartec Datensysteme",
    "wof:placetype":"venue"
},
  "geometry": {"coordinates":[8.374744,49.013977],"type":"Point"}
}