{
  "type": "Feature",
  "properties": {
    "iso:country":"DE",
    "sg:address":"Rott am Wald",
    "sg:city":"Eggenfelden",
    "sg:phone":"+49 8721/1650",
    "sg:postcode":"84307",
    "sg:province":"Bayern",
    "wof:name":"Hans Fusseder Architekt",
    "wof:placetype":"venue"
},
  "geometry": {"coordinates":[12.738805,48.4025],"type":"Point"}
}