{
  "type": "Feature",
  "properties": {
    "iso:country":"DE",
    "sg:address":"Zeppelinstr 95",
    "sg:city":"Esslingen",
    "sg:phone":"+49 711/9392020",
    "sg:postcode":"73730",
    "sg:province":"Baden-W\u00fcrttemberg",
    "wof:name":"Mahler Gmbh",
    "wof:placetype":"venue"
},
  "geometry": {"coordinates":[9.36781,48.731861],"type":"Point"}
}