{
  "type": "Feature",
  "properties": {
    "iso:country":"DE",
    "sg:address":"Unterentersbacher Str. 20",
    "sg:city":"Zell",
    "sg:phone":"+49 7835/3069",
    "sg:postcode":"77736",
    "sg:province":"Baden-W\u00fcrttemberg",
    "wof:name":"Theo Kienzler",
    "wof:placetype":"venue"
},
  "geometry": {"coordinates":[8.0586032867,48.343624115],"type":"Point"}
}