{
  "type": "Feature",
  "properties": {
    "iso:country":"DE",
    "sg:address":"Hauptstr. 48",
    "sg:city":"Herdecke",
    "sg:phone":"+49 2330/3639",
    "sg:postcode":"58313",
    "sg:province":"Nordrhein-Westfalen",
    "wof:name":"Gebhard Schwab Heilpraktiker",
    "wof:placetype":"venue"
},
  "geometry": {"coordinates":[7.4324131012,51.399433136],"type":"Point"}
}