{
  "type": "Feature",
  "properties": {
    "iso:country":"DE",
    "sg:address":"Waaghausstr. 4",
    "sg:city":"Biberach",
    "sg:phone":"+49 7351/18300",
    "sg:postcode":"88400",
    "sg:province":"Baden-W\u00fcrttemberg",
    "wof:name":"Johannes Weissbarth Architekt",
    "wof:placetype":"venue"
},
  "geometry": {"coordinates":[9.78882,48.088539],"type":"Point"}
}