{
  "type": "Feature",
  "properties": {
    "iso:country":"DE",
    "sg:address":"Berliner Str. 42 u. 54",
    "sg:city":"Angelburg",
    "sg:phone":"+49 6464/6132",
    "sg:postcode":"35719",
    "sg:province":"Hessen",
    "wof:name":"Re-bau Verwaltungs- Und Beteiligungsgesellschaft Mbh",
    "wof:placetype":"venue"
},
  "geometry": {"coordinates":[8.4475488663,50.8225593567],"type":"Point"}
}