{
  "type": "Feature",
  "properties": {
    "iso:country":"DE",
    "sg:address":"Haslindestr. 36",
    "sg:city":"Dortmund",
    "sg:phone":"+49 231/253313",
    "sg:postcode":"44309",
    "sg:province":"Nordrhein-Westfalen",
    "wof:name":"Willi K\u00f6nen Architekt",
    "wof:placetype":"venue"
},
  "geometry": {"coordinates":[7.560476,51.514999],"type":"Point"}
}