{
  "type": "Feature",
  "properties": {
    "iso:country":"DE",
    "sg:address":"Johannes-Scheele-Str 10",
    "sg:city":"Finnentrop",
    "sg:phone":"+49 2721/95420",
    "sg:postcode":"57413",
    "sg:province":"Nordrhein-Westfalen",
    "wof:name":"Brachth\u00e4user Spedition Gmbh",
    "wof:placetype":"venue"
},
  "geometry": {"coordinates":[7.9799599648,51.1653251648],"type":"Point"}
}