{
  "type": "Feature",
  "properties": {
    "iso:country":"DE",
    "sg:address":"Im Gerstenfeld 11",
    "sg:city":"Auenwald",
    "sg:postcode":"71549",
    "sg:province":"Baden-W\u00fcrttemberg",
    "wof:name":"Flohr Fenster Und T\u00fcren Gmbh",
    "wof:placetype":"venue"
},
  "geometry": {"coordinates":[9.52656,48.927601],"type":"Point"}
}