{
  "type": "Feature",
  "properties": {
    "iso:country":"DE",
    "sg:address":"Wittener Str. 6-8",
    "sg:city":"Dortmund",
    "sg:phone":"+49 231/7217722",
    "sg:postcode":"44149",
    "sg:province":"Nordrhein-Westfalen",
    "wof:name":"Uwe Frintrop Architekt",
    "wof:placetype":"venue"
},
  "geometry": {"coordinates":[7.423164,51.512268],"type":"Point"}
}