{
  "type": "Feature",
  "properties": {
    "iso:country":"DE",
    "sg:address":"Morellstr. 10",
    "sg:city":"Augsburg",
    "sg:phone":"+49 821/585857",
    "sg:postcode":"86159",
    "sg:province":"Bayern",
    "wof:name":"Dr. Christoph Hammerl Rechtsanwalt",
    "wof:placetype":"venue"
},
  "geometry": {"coordinates":[10.8888149261,48.3572044373],"type":"Point"}
}