{
  "type": "Feature",
  "properties": {
    "iso:country":"DE",
    "sg:address":"Ober-Eschbacher Str. 9 A",
    "sg:city":"Bad Homburg",
    "sg:postcode":"61352",
    "sg:province":"Hessen",
    "wof:name":"Fibu Gmbh",
    "wof:placetype":"venue"
},
  "geometry": {"coordinates":[8.647611,50.219524],"type":"Point"}
}