{
  "type": "Feature",
  "properties": {
    "iso:country":"DE",
    "sg:address":"Epplestr. 22 a",
    "sg:city":"Stuttgart",
    "sg:phone":"+49 711/760895",
    "sg:postcode":"70597",
    "sg:province":"Baden-W\u00fcrttemberg",
    "wof:name":"Filder-apotheke",
    "wof:placetype":"venue"
},
  "geometry": {"coordinates":[9.170212,48.747288],"type":"Point"}
}