{
  "type": "Feature",
  "properties": {
    "iso:country":"DE",
    "sg:address":"Ilsetal",
    "sg:city":"Ilsenburg Wernigerode",
    "sg:phone":"+49 39452",
    "sg:postcode":"38872",
    "wof:name":"Waldhotel Ilsestein Harz Ilsenburg",
    "wof:placetype":"venue"
},
  "geometry": {"coordinates":[10.79175,51.838329],"type":"Point"}
}