{
  "type": "Feature",
  "properties": {
    "iso:country":"DE",
    "sg:address":"Alpenstr. 6",
    "sg:city":"Heimertingen",
    "sg:phone":"+49 8335/986228",
    "sg:postcode":"87751",
    "sg:province":"Bayern",
    "wof:name":"Calypso Tanzcafe",
    "wof:placetype":"venue"
},
  "geometry": {"coordinates":[10.153217,48.032742],"type":"Point"}
}