{
  "type": "Feature",
  "properties": {
    "iso:country":"DE",
    "sg:address":"\u00c4u\u00dfere Crimmitschauer Str. 67",
    "sg:city":"Meerane",
    "sg:phone":"+49 3764/48699",
    "sg:postcode":"08393",
    "sg:province":"Sachsen",
    "wof:name":"Restaurant Venezia",
    "wof:placetype":"venue"
},
  "geometry": {"coordinates":[12.4540910721,50.844745636],"type":"Point"}
}