{
  "type": "Feature",
  "properties": {
    "iso:country":"DE",
    "sg:address":"Joachim-Jungius-Str 9",
    "sg:city":"Rostock",
    "sg:phone":"+49 381/4059815",
    "sg:postcode":"18059",
    "sg:province":"Mecklenburg-Vorpommern",
    "wof:name":"Argus Electronic Gmbh",
    "wof:placetype":"venue"
},
  "geometry": {"coordinates":[12.116486,54.075424],"type":"Point"}
}