{
  "type": "Feature",
  "properties": {
    "iso:country":"DE",
    "sg:address":"Flughafenall. 17",
    "sg:city":"Bremen",
    "sg:phone":"+49 4942/12430",
    "sg:postcode":"28199",
    "sg:province":"Bremen",
    "wof:name":"Nordmilch Eg",
    "wof:placetype":"venue"
},
  "geometry": {"coordinates":[8.78318,53.054451],"type":"Point"}
}