{
  "type": "Feature",
  "properties": {
    "iso:country":"DE",
    "sg:address":"Kapellenstr. 3",
    "sg:city":"Riedering",
    "sg:phone":"+49 8036/8239",
    "sg:postcode":"83083",
    "sg:province":"Bayern",
    "wof:name":"Stefan Gmeiner",
    "wof:placetype":"venue"
},
  "geometry": {"coordinates":[12.2541828156,47.8349761963],"type":"Point"}
}