{
  "type": "Feature",
  "properties": {
    "iso:country":"DE",
    "sg:address":"Altonaer Platz 8",
    "sg:city":"K\u00f6ln",
    "sg:phone":"+49 221/743517",
    "sg:postcode":"50737",
    "sg:province":"Nordrhein-Westfalen",
    "wof:name":"Feuerwerk Nellen-cohsmann Gmbh & Co. Kg",
    "wof:placetype":"venue"
},
  "geometry": {"coordinates":[6.9330210686,50.9949264526],"type":"Point"}
}