{
  "type": "Feature",
  "properties": {
    "iso:country":"DE",
    "sg:address":"Etzweiler Str. 19",
    "sg:city":"Elsdorf",
    "sg:phone":"+49 2274/3960",
    "sg:postcode":"50189",
    "sg:province":"Nordrhein-Westfalen",
    "wof:name":"Gerd Wenzel",
    "wof:placetype":"venue"
},
  "geometry": {"coordinates":[6.5706801414,50.9258117676],"type":"Point"}
}