{
  "type": "Feature",
  "properties": {
    "iso:country":"DE",
    "sg:address":"Margaretenh\u00f6he 2",
    "sg:city":"Bergisch Gladbach",
    "sg:phone":"+49 2202/31125",
    "sg:postcode":"51465",
    "sg:province":"Nordrhein-Westfalen",
    "wof:name":"Karl Heinz Weishaupt",
    "wof:placetype":"venue"
},
  "geometry": {"coordinates":[7.1397738457,50.9942245483],"type":"Point"}
}