{
  "type": "Feature",
  "properties": {
    "iso:country":"DE",
    "sg:address":"Untergasse 2",
    "sg:city":"Neukirchen",
    "sg:phone":"+49 6694/296",
    "sg:postcode":"34626",
    "sg:province":"Hessen",
    "wof:name":"Axel Wenzlik",
    "wof:placetype":"venue"
},
  "geometry": {"coordinates":[9.3434057236,50.8687782288],"type":"Point"}
}