{
  "type": "Feature",
  "properties": {
    "iso:country":"DE",
    "sg:address":"Roggenkamp 17",
    "sg:city":"Verden",
    "sg:phone":"+49 4231/64947",
    "sg:postcode":"27283",
    "sg:province":"Niedersachsen",
    "wof:name":"Pdm",
    "wof:placetype":"venue"
},
  "geometry": {"coordinates":[9.2714538574,52.9275741577],"type":"Point"}
}