{
  "type": "Feature",
  "properties": {
    "iso:country":"DE",
    "sg:address":"Sprucker Str. 24",
    "sg:city":"Guben",
    "sg:phone":"+49 3561/66695",
    "sg:postcode":"03172",
    "sg:province":"Brandenburg",
    "wof:name":"G. M}ller",
    "wof:placetype":"venue"
},
  "geometry": {"coordinates":[14.7065019608,51.9489784241],"type":"Point"}
}