{
  "type": "Feature",
  "properties": {
    "iso:country":"DE",
    "sg:address":"Grunewaldstr. 47",
    "sg:city":"Berlin",
    "sg:phone":"+49 30/2112295",
    "sg:postcode":"10825",
    "sg:province":"Berlin",
    "wof:name":"Elena-w\u00e4sche Inh. E. Adler",
    "wof:placetype":"venue"
},
  "geometry": {"coordinates":[13.3391065598,52.4886169434],"type":"Point"}
}