{
  "type": "Feature",
  "properties": {
    "iso:country":"DE",
    "sg:address":"Von-Liebig-Str. 21",
    "sg:city":"Neu-Ulm",
    "sg:phone":"+49 4973/1974880",
    "sg:postcode":"89231",
    "sg:province":"Bayern",
    "wof:name":"Hammer Sport Ag",
    "wof:placetype":"venue"
},
  "geometry": {"coordinates":[10.0340852737,48.3846588135],"type":"Point"}
}