{
  "type": "Feature",
  "properties": {
    "iso:country":"DE",
    "sg:address":"Thomas-Dehler-Str. 22",
    "sg:city":"Germersheim",
    "sg:phone":"+49 7274/779586",
    "sg:postcode":"76726",
    "sg:province":"Rheinland-Pfalz",
    "wof:name":"Vlaznim Bujupi",
    "wof:placetype":"venue"
},
  "geometry": {"coordinates":[8.3579,49.215565],"type":"Point"}
}