{
  "type": "Feature",
  "properties": {
    "iso:country":"DE",
    "sg:address":"Johannes-Spaetgens-Str. 9",
    "sg:city":"Willich",
    "sg:phone":"+49 2154/80968",
    "sg:postcode":"47877",
    "sg:province":"Nordrhein-Westfalen",
    "wof:name":"Mietservice Bernd Mahlitz",
    "wof:placetype":"venue"
},
  "geometry": {"coordinates":[6.539284,51.24733],"type":"Point"}
}