{
  "type": "Feature",
  "properties": {
    "iso:country":"DE",
    "sg:address":"Brunnenstr. 6",
    "sg:city":"Breitscheid",
    "sg:phone":"+49 2638/94331",
    "sg:postcode":"53547",
    "sg:province":"Rheinland-Pfalz",
    "wof:name":"Vera Kirscht",
    "wof:placetype":"venue"
},
  "geometry": {"coordinates":[7.4442791939,50.5838890076],"type":"Point"}
}