{
  "type": "Feature",
  "properties": {
    "iso:country":"DE",
    "sg:address":"Kaltenecker Str. 10",
    "sg:city":"Rimbach",
    "sg:phone":"+49 9941/3180",
    "sg:postcode":"93485",
    "sg:province":"Bayern",
    "wof:name":"Berzl Bau Gmbh",
    "wof:placetype":"venue"
},
  "geometry": {"coordinates":[12.858822,49.230206],"type":"Point"}
}