{
  "type": "Feature",
  "properties": {
    "iso:country":"DE",
    "sg:address":"Ortsstr. 26",
    "sg:city":"Dr\u00f6bischau",
    "sg:phone":"+49 36738/42722",
    "sg:postcode":"07426",
    "sg:province":"Th\u00fcringen",
    "wof:name":"Julius M\u00f6ller",
    "wof:placetype":"venue"
},
  "geometry": {"coordinates":[11.073089,50.629501],"type":"Point"}
}