{
  "type": "Feature",
  "properties": {
    "iso:country":"DE",
    "sg:address":"Tonbachstr. 243",
    "sg:city":"Baiersbronn",
    "sg:phone":"+49 7442/8330",
    "sg:postcode":"72270",
    "sg:province":"Baden-W\u00fcrttemberg",
    "wof:name":"Kurhotel Tanne Tonbach Rudolf M\u00f6rle",
    "wof:placetype":"venue"
},
  "geometry": {"coordinates":[8.3716602325,48.5214309692],"type":"Point"}
}