{
  "type": "Feature",
  "properties": {
    "iso:country":"DE",
    "sg:address":"Industriestr. 12",
    "sg:city":"Steffenberg",
    "sg:postcode":"35239",
    "sg:province":"Hessen",
    "wof:name":"Arnold-beteiligungs- Gmbh",
    "wof:placetype":"venue"
},
  "geometry": {"coordinates":[8.464281,50.840237],"type":"Point"}
}