{
  "type": "Feature",
  "properties": {
    "iso:country":"DE",
    "sg:address":"Waymannskath 43",
    "sg:city":"Voerde",
    "sg:phone":"+49 2855/6686",
    "sg:postcode":"46562",
    "sg:province":"Nordrhein-Westfalen",
    "wof:name":"F.s.d. Marktservice Und Dienstleistung",
    "wof:placetype":"venue"
},
  "geometry": {"coordinates":[6.673572,51.60128],"type":"Point"}
}