{
  "type": "Feature",
  "properties": {
    "iso:country":"DE",
    "sg:address":"N\u00fcrnberger Str. 72",
    "sg:city":"W\u00fcrzburg",
    "sg:phone":"+49 931/72093",
    "sg:postcode":"97076",
    "sg:province":"Bayern",
    "wof:name":"Sixt Gmbh & Co. Autovermietung Kg",
    "wof:placetype":"venue"
},
  "geometry": {"coordinates":[9.969874,49.795773],"type":"Point"}
}