{
  "type": "Feature",
  "properties": {
    "iso:country":"DE",
    "sg:address":"Hermann-L\u00f6ns-Weg 45",
    "sg:city":"Hamburg",
    "sg:phone":"+49 40/595333",
    "sg:postcode":"22335",
    "sg:province":"Hamburg",
    "wof:name":"Baugenossenschaft Fuhlsb\u00fcttel Eg",
    "wof:placetype":"venue"
},
  "geometry": {"coordinates":[10.0159225464,53.6315574646],"type":"Point"}
}