{
  "type": "Feature",
  "properties": {
    "iso:country":"DE",
    "sg:address":"Simonweg 8",
    "sg:city":"Fr\u00f6ndenberg",
    "sg:phone":"+49 2378/913355",
    "sg:postcode":"58730",
    "sg:province":"Nordrhein-Westfalen",
    "wof:name":"C. Und W. Simon Architekten",
    "wof:placetype":"venue"
},
  "geometry": {"coordinates":[7.709201,51.491531],"type":"Point"}
}