{
  "type": "Feature",
  "properties": {
    "iso:country":"DE",
    "sg:address":"Tillystr. 15",
    "sg:city":"Bad Wimpfen",
    "sg:phone":"+49 7063/6288",
    "sg:postcode":"74206",
    "sg:province":"Baden-W\u00fcrttemberg",
    "wof:name":"I. Oster Immobilienmakler",
    "wof:placetype":"venue"
},
  "geometry": {"coordinates":[9.1618204117,49.2238082886],"type":"Point"}
}