{
  "type": "Feature",
  "properties": {
    "iso:country":"DE",
    "sg:address":"Neptunring 96",
    "sg:city":"Wismar",
    "sg:phone":"+49 3841/632842",
    "sg:postcode":"23968",
    "sg:province":"Mecklenburg-Vorpommern",
    "wof:name":"Ihr Finanzdienstleister In Wismar",
    "wof:placetype":"venue"
},
  "geometry": {"coordinates":[11.396974,53.907558],"type":"Point"}
}