{
  "type": "Feature",
  "properties": {
    "iso:country":"DE",
    "sg:address":"Richard-Strauss-Str. 3",
    "sg:city":"Rastede",
    "sg:phone":"+49 4402/3586",
    "sg:postcode":"26180",
    "sg:province":"Niedersachsen",
    "wof:name":"Theodor Und Claus Schmidt Inh. T. Und C. Schmidt Ohg",
    "wof:placetype":"venue"
},
  "geometry": {"coordinates":[8.2005586624,53.2563896179],"type":"Point"}
}