{
  "type": "Feature",
  "properties": {
    "iso:country":"DE",
    "sg:address":"Kronacher Strasse 60",
    "sg:city":"Bamberg",
    "sg:phone":"+49 951/9424222",
    "sg:postcode":"96052",
    "sg:province":"Bayern",
    "wof:name":"Staatliche Lotterie-einnahme",
    "wof:placetype":"venue"
},
  "geometry": {"coordinates":[10.906257,49.921577],"type":"Point"}
}