{
  "type": "Feature",
  "properties": {
    "iso:country":"DE",
    "sg:address":"Bernhard-Wiesch-Str. 8",
    "sg:city":"Gescher",
    "sg:phone":"+49 2863/2246",
    "sg:postcode":"48712",
    "sg:province":"Nordrhein-Westfalen",
    "wof:name":"K. Schlamann",
    "wof:placetype":"venue"
},
  "geometry": {"coordinates":[7.0349211693,51.8962478638],"type":"Point"}
}