{
  "type": "Feature",
  "properties": {
    "iso:country":"DE",
    "sg:address":"S\u00e4gm\u00fchlweg 1-3",
    "sg:city":"Burtenbach",
    "sg:phone":"+49 8285/228",
    "sg:postcode":"89349",
    "sg:province":"Bayern",
    "wof:name":"Ernst Schnitzlein Gmbh",
    "wof:placetype":"venue"
},
  "geometry": {"coordinates":[10.4416847229,48.3397903442],"type":"Point"}
}