{
  "type": "Feature",
  "properties": {
    "iso:country":"DE",
    "sg:address":"Altendorfer Str. 104",
    "sg:city":"Essen",
    "sg:phone":"+49 201/8090",
    "sg:postcode":"45143",
    "sg:province":"Nordrhein-Westfalen",
    "wof:name":"Krupp Gft Gesellschaft F\u00fcr Technik Mbh",
    "wof:placetype":"venue"
},
  "geometry": {"coordinates":[6.993928,51.460373],"type":"Point"}
}