{
  "type": "Feature",
  "properties": {
    "iso:country":"DE",
    "sg:address":"Gloelstr. 3-5",
    "sg:city":"Wetzlar",
    "sg:phone":"+49 6441/4040",
    "sg:postcode":"35576",
    "sg:province":"Hessen",
    "wof:name":"Hensoldt Ag",
    "wof:placetype":"venue"
},
  "geometry": {"coordinates":[8.5008296967,50.5616073608],"type":"Point"}
}