{
  "type": "Feature",
  "properties": {
    "iso:country":"DE",
    "sg:address":"Hauptstr. 30",
    "sg:city":"Ruhstorf",
    "sg:postcode":"94099",
    "sg:province":"Bayern",
    "wof:name":"Marienapotheke Ap. Rosemarie Sommer",
    "wof:placetype":"venue"
},
  "geometry": {"coordinates":[13.337082,48.43771],"type":"Point"}
}