{
  "type": "Feature",
  "properties": {
    "iso:country":"DE",
    "sg:address":"B\u00e4ckergasse 25",
    "sg:city":"Augsburg",
    "sg:phone":"+49 821/516091",
    "sg:postcode":"86150",
    "sg:province":"Bayern",
    "wof:name":"Andreas Hundseder Christine Lauterbach",
    "wof:placetype":"venue"
},
  "geometry": {"coordinates":[10.9029054642,48.3624572754],"type":"Point"}
}