{
  "type": "Feature",
  "properties": {
    "iso:country":"DE",
    "sg:address":"Tulpenstr. 9",
    "sg:city":"Taufkirchen",
    "sg:phone":"+49 8084/946650",
    "sg:postcode":"84416",
    "sg:province":"Bayern",
    "wof:name":"Lsr Laser- Und Showtechnik Vetriebs Gmbh",
    "wof:placetype":"venue"
},
  "geometry": {"coordinates":[12.1168622971,48.3450279236],"type":"Point"}
}