{
  "type": "Feature",
  "properties": {
    "iso:country":"DE",
    "sg:address":"Nelkenstr. 10",
    "sg:city":"Halle",
    "sg:phone":"+49 345/8053381",
    "sg:postcode":"06126",
    "sg:province":"Sachsen-Anhalt",
    "wof:name":"Ingenieurb\u00fcro Pawlak",
    "wof:placetype":"venue"
},
  "geometry": {"coordinates":[11.9084005356,51.4925498962],"type":"Point"}
}