{
  "type": "Feature",
  "properties": {
    "iso:country":"DE",
    "sg:address":"Gellertstr. 24",
    "sg:city":"Hannover",
    "sg:phone":"+49 511/815783",
    "sg:postcode":"30175",
    "sg:province":"Niedersachsen",
    "wof:name":"Prager Hof Gastst\u00e4ttenbetriebs Gmbh",
    "wof:placetype":"venue"
},
  "geometry": {"coordinates":[9.7561216354,52.3753051758],"type":"Point"}
}