{
  "type": "Feature",
  "properties": {
    "iso:country":"DE",
    "sg:address":"Friedenshof",
    "sg:city":"Galmsb\u00fcll",
    "sg:postcode":"25899",
    "sg:province":"Schleswig-Holstein",
    "wof:name":"Nam Nieb\u00fcller Arzneistoff Mikronisierungs Gmbh",
    "wof:placetype":"venue"
},
  "geometry": {"coordinates":[8.7535495758,54.7909317017],"type":"Point"}
}