{
  "type": "Feature",
  "properties": {
    "iso:country":"DE",
    "sg:address":"Belfortstr. 8",
    "sg:city":"M\u00fcnchen",
    "sg:phone":"+49 89/484492",
    "sg:postcode":"81667",
    "sg:province":"Bayern",
    "wof:name":"Body And Face - Visagistenschule",
    "wof:placetype":"venue"
},
  "geometry": {"coordinates":[11.60372,48.129627],"type":"Point"}
}