{
  "type": "Feature",
  "properties": {
    "iso:country":"DE",
    "sg:address":"Jakobusstr. 7",
    "sg:city":"Vettwei\u00df",
    "sg:phone":"+49 2424/1245",
    "sg:postcode":"52391",
    "sg:province":"Nordrhein-Westfalen",
    "wof:name":"En De Holzportz",
    "wof:placetype":"venue"
},
  "geometry": {"coordinates":[6.5566058159,50.7618942261],"type":"Point"}
}