{
  "type": "Feature",
  "properties": {
    "iso:country":"DE",
    "sg:address":"Neue Pforte 27",
    "sg:city":"Neu-Anspach",
    "sg:phone":"+49 6081/7513",
    "sg:postcode":"61267",
    "sg:province":"Hessen",
    "wof:name":"Martin Strauch",
    "wof:placetype":"venue"
},
  "geometry": {"coordinates":[8.504141,50.292934],"type":"Point"}
}