{
  "type": "Feature",
  "properties": {
    "iso:country":"DE",
    "sg:address":"Riesenstr. 7",
    "sg:city":"Kaiserslautern",
    "sg:phone":"+49 631/65944",
    "sg:postcode":"67655",
    "sg:province":"Rheinland-Pfalz",
    "wof:name":"Jones & Jones Classic Jeanswear Clothing",
    "wof:placetype":"venue"
},
  "geometry": {"coordinates":[7.769926,49.442982],"type":"Point"}
}