{
  "type": "Feature",
  "properties": {
    "iso:country":"DE",
    "sg:address":"Untere Hauptstr. 103",
    "sg:city":"Herxheim",
    "sg:phone":"+49 7276/6968",
    "sg:postcode":"76863",
    "sg:province":"Rheinland-Pfalz",
    "wof:name":"Wasgau B\u00e4ckerei Und Konditorei Gmbh",
    "wof:placetype":"venue"
},
  "geometry": {"coordinates":[8.220278,49.147659],"type":"Point"}
}