{
  "type": "Feature",
  "properties": {
    "iso:country":"DE",
    "sg:address":"Urbanstr. 19",
    "sg:city":"N\u00fcrnberg",
    "sg:phone":"+49 911/404222",
    "sg:postcode":"90480",
    "sg:province":"Bayern",
    "wof:name":"Wolfgang Frank",
    "wof:placetype":"venue"
},
  "geometry": {"coordinates":[11.1267557144,49.4430007935],"type":"Point"}
}