{
  "type": "Feature",
  "properties": {
    "iso:country":"DE",
    "sg:address":"Grabenberg 31",
    "sg:city":"Schlitz",
    "sg:phone":"+49 6642/334",
    "sg:postcode":"36110",
    "sg:province":"Hessen",
    "wof:name":"Hans Sauer",
    "wof:placetype":"venue"
},
  "geometry": {"coordinates":[9.558023,50.676785],"type":"Point"}
}