{
  "type": "Feature",
  "properties": {
    "iso:country":"DE",
    "sg:address":"Scho\u00dfberghof",
    "sg:city":"Minfeld",
    "sg:phone":"+49 7275/2565",
    "sg:postcode":"76872",
    "sg:province":"Rheinland-Pfalz",
    "wof:name":"Karl Gro\u00df",
    "wof:placetype":"venue"
},
  "geometry": {"coordinates":[8.14513,49.076534],"type":"Point"}
}