{
  "type": "Feature",
  "properties": {
    "iso:country":"DE",
    "sg:address":"Georg-B\u00fcchner-Str. 7",
    "sg:city":"Griesheim",
    "sg:phone":"+49 6155/66422",
    "sg:postcode":"64347",
    "sg:province":"Hessen",
    "wof:name":"Metall-bau-technik Gmbh",
    "wof:placetype":"venue"
},
  "geometry": {"coordinates":[8.574113,49.862789],"type":"Point"}
}