{
  "type": "Feature",
  "properties": {
    "iso:country":"DE",
    "sg:address":"Bockswinkelhof",
    "sg:city":"Friesenheim",
    "sg:phone":"+49 7821/5575512",
    "sg:postcode":"77948",
    "sg:province":"Baden-W\u00fcrttemberg",
    "wof:name":"Karl Silberer",
    "wof:placetype":"venue"
},
  "geometry": {"coordinates":[7.848309,48.393444],"type":"Point"}
}