{
  "type": "Feature",
  "properties": {
    "iso:country":"DE",
    "sg:address":"Martin-Luther-Str. 30",
    "sg:city":"Bad Vilbel",
    "sg:phone":"+49 6101/84592",
    "sg:postcode":"61118",
    "sg:province":"Hessen",
    "wof:name":"Horst Heinzerling",
    "wof:placetype":"venue"
},
  "geometry": {"coordinates":[8.7127790451,50.1743087769],"type":"Point"}
}