{
  "type": "Feature",
  "properties": {
    "iso:country":"DE",
    "sg:address":"Salzstr. 32",
    "sg:city":"Gommern",
    "sg:phone":"+49 39200/51584",
    "sg:postcode":"39245",
    "sg:province":"Sachsen-Anhalt",
    "wof:name":"Reinhard Bosold",
    "wof:placetype":"venue"
},
  "geometry": {"coordinates":[11.8181438446,52.0680770874],"type":"Point"}
}