{
  "type": "Feature",
  "properties": {
    "iso:country":"DE",
    "sg:address":"Markt 30",
    "sg:city":"Sch\u00f6ningen",
    "sg:phone":"+49 5352/3961",
    "sg:postcode":"38364",
    "sg:province":"Niedersachsen",
    "wof:name":"Adler-apotheke",
    "wof:placetype":"venue"
},
  "geometry": {"coordinates":[10.96765,52.139233],"type":"Point"}
}