{
  "type": "Feature",
  "properties": {
    "iso:country":"DE",
    "sg:address":"Netterdensche Str. 225",
    "sg:city":"Emmerich",
    "sg:phone":"+49 2822/51340",
    "sg:postcode":"46446",
    "sg:province":"Nordrhein-Westfalen",
    "wof:name":"Heinz-josef Arnds",
    "wof:placetype":"venue"
},
  "geometry": {"coordinates":[6.284575,51.841904],"type":"Point"}
}