{
  "type": "Feature",
  "properties": {
    "iso:country":"DE",
    "sg:address":"Altenburger Str. 70",
    "sg:city":"G\u00f6\u00dfnitz",
    "sg:phone":"+49 34493/22678",
    "sg:postcode":"04639",
    "sg:province":"Th\u00fcringen",
    "wof:name":"Reiner M\u00fcller",
    "wof:placetype":"venue"
},
  "geometry": {"coordinates":[12.4336576462,50.8920860291],"type":"Point"}
}