{
  "type": "Feature",
  "properties": {
    "iso:country":"DE",
    "sg:address":"Alter Postweg 9",
    "sg:city":"Friedberg",
    "sg:phone":"+49 8208/959125",
    "sg:postcode":"86316",
    "sg:province":"Bayern",
    "wof:name":"Horst Eichenauer Rechtsanwalt",
    "wof:placetype":"venue"
},
  "geometry": {"coordinates":[11.0470819473,48.3089675903],"type":"Point"}
}