{
  "type": "Feature",
  "properties": {
    "iso:country":"DE",
    "sg:address":"Parkstr. 17",
    "sg:city":"Bad Vilbel",
    "sg:phone":"+49 6101/523333",
    "sg:postcode":"61118",
    "sg:province":"Hessen",
    "wof:name":"Christian Kissel Masseur",
    "wof:placetype":"venue"
},
  "geometry": {"coordinates":[8.741143,50.183559],"type":"Point"}
}