{
  "type": "Feature",
  "properties": {
    "iso:country":"DE",
    "sg:address":"Parkstr. 39",
    "sg:city":"Buchholz",
    "sg:phone":"+49 4181/8784",
    "sg:postcode":"21244",
    "sg:province":"Niedersachsen",
    "wof:name":"Ev. Pfarramt Ii St. Paulus",
    "wof:placetype":"venue"
},
  "geometry": {"coordinates":[9.8663835526,53.3304748535],"type":"Point"}
}