{
  "type": "Feature",
  "properties": {
    "iso:country":"DE",
    "sg:address":"Bahnhofstr. 18",
    "sg:city":"Esslingen",
    "sg:phone":"+49 4971/1359112",
    "sg:postcode":"73728",
    "sg:province":"Baden-W\u00fcrttemberg",
    "wof:name":"Sparkassen-versicherung Ag",
    "wof:placetype":"venue"
},
  "geometry": {"coordinates":[9.303413,48.740524],"type":"Point"}
}