{
  "type": "Feature",
  "properties": {
    "iso:country":"DE",
    "sg:address":"F\u00fcrther Str. 2a",
    "sg:city":"N\u00fcrnberg",
    "sg:phone":"+49 911/286868",
    "sg:postcode":"90429",
    "sg:province":"Bayern",
    "wof:name":"Cafehaus Am Pl\u00e4rrer",
    "wof:placetype":"venue"
},
  "geometry": {"coordinates":[11.064105,49.449409],"type":"Point"}
}