{
  "type": "Feature",
  "properties": {
    "iso:country":"DE",
    "sg:address":"Suhler Str. 4",
    "sg:city":"Ohrdruf",
    "sg:phone":"+49 3624/37540",
    "sg:postcode":"99885",
    "sg:province":"Th\u00fcringen",
    "wof:name":"Brill Stahlbau Konstruktions- Und Vertriebs Gmbh",
    "wof:placetype":"venue"
},
  "geometry": {"coordinates":[10.732019,50.816006],"type":"Point"}
}