{
  "type": "Feature",
  "properties": {
    "iso:country":"DE",
    "sg:address":"Marie-Curie-Str. 2",
    "sg:city":"Hilden",
    "sg:phone":"+49 2103/50016",
    "sg:postcode":"40721",
    "sg:province":"Nordrhein-Westfalen",
    "wof:name":"Liszus Gmbh & Co. Kg",
    "wof:placetype":"venue"
},
  "geometry": {"coordinates":[6.9255328178,51.1627044678],"type":"Point"}
}