{
  "type": "Feature",
  "properties": {
    "iso:country":"DE",
    "sg:address":"Auf der H\u00f6he 22",
    "sg:city":"Kreiensen",
    "sg:phone":"+49 5563/1705",
    "sg:postcode":"37547",
    "sg:province":"Niedersachsen",
    "wof:name":"R. Woitag",
    "wof:placetype":"venue"
},
  "geometry": {"coordinates":[9.9707250595,51.8540916443],"type":"Point"}
}