{
  "type": "Feature",
  "properties": {
    "iso:country":"DE",
    "sg:address":"Neueibauer Str. 9",
    "sg:city":"Eibau",
    "sg:phone":"+49 3586/78140",
    "sg:postcode":"02739",
    "sg:province":"Sachsen",
    "wof:name":"M\u00fcnch-br\u00e4u Eibau Gmbh",
    "wof:placetype":"venue"
},
  "geometry": {"coordinates":[14.664369,50.978134],"type":"Point"}
}