{
  "type": "Feature",
  "properties": {
    "iso:country":"DE",
    "sg:address":"Ulmer Str. 154",
    "sg:city":"Augsburg",
    "sg:phone":"+49 821/401530",
    "sg:postcode":"86156",
    "sg:province":"Bayern",
    "wof:name":"Gertrud Feller Reformhaus",
    "wof:placetype":"venue"
},
  "geometry": {"coordinates":[10.8586425781,48.3803596497],"type":"Point"}
}