{
  "type": "Feature",
  "properties": {
    "iso:country":"DE",
    "sg:address":"Forstenrieder Allee 210",
    "sg:city":"M\u00fcnchen",
    "sg:phone":"+49 89/7455860",
    "sg:postcode":"81476",
    "sg:province":"Bayern",
    "wof:name":"Immodata Ges. F\u00fcr Unternehmensberatung Mbh",
    "wof:placetype":"venue"
},
  "geometry": {"coordinates":[11.4935131073,48.0819091797],"type":"Point"}
}