{
  "type": "Feature",
  "properties": {
    "iso:country":"DE",
    "sg:address":"Murtenstr. 2",
    "sg:city":"B\u00fcsingen",
    "sg:phone":"+49 7734/6152",
    "sg:postcode":"78266",
    "sg:province":"Baden-W\u00fcrttemberg",
    "wof:name":"Otto Sinzinger Architekt",
    "wof:placetype":"venue"
},
  "geometry": {"coordinates":[8.681724,47.691334],"type":"Point"}
}