{
  "type": "Feature",
  "properties": {
    "iso:country":"DE",
    "sg:address":"Z\u00f6bigker Str. 125",
    "sg:city":"Markkleeberg",
    "sg:phone":"+49 341/324234",
    "sg:postcode":"04416",
    "sg:province":"Sachsen",
    "wof:name":"Heinz Barth",
    "wof:placetype":"venue"
},
  "geometry": {"coordinates":[12.353082,51.264347],"type":"Point"}
}