{
  "type": "Feature",
  "properties": {
    "iso:country":"DE",
    "sg:address":"Eickener Str. 168",
    "sg:city":"M\u00f6nchengladbach",
    "sg:phone":"+49 2161/12181",
    "sg:postcode":"41063",
    "sg:province":"Nordrhein-Westfalen",
    "wof:name":"Maler-einkauf Eg Mbh",
    "wof:placetype":"venue"
},
  "geometry": {"coordinates":[6.4470238686,51.2061462402],"type":"Point"}
}