{
  "type": "Feature",
  "properties": {
    "iso:country":"DE",
    "sg:address":"Zeitzer Str. 8",
    "sg:city":"Pegau",
    "sg:phone":"+49 34296/76595",
    "sg:postcode":"04523",
    "sg:province":"Sachsen",
    "wof:name":"T. George",
    "wof:placetype":"venue"
},
  "geometry": {"coordinates":[12.247029,51.168076],"type":"Point"}
}