{
  "type": "Feature",
  "properties": {
    "iso:country":"DE",
    "sg:address":"Weiherstr 23a",
    "sg:city":"Augsburg",
    "sg:phone":"+49 821/411058",
    "sg:postcode":"86154",
    "sg:province":"Bayern",
    "wof:name":"Biberger Gmbh",
    "wof:placetype":"venue"
},
  "geometry": {"coordinates":[10.8840847015,48.389377594],"type":"Point"}
}