{
  "type": "Feature",
  "properties": {
    "iso:country":"DE",
    "sg:address":"Eschborner Landstr. 122",
    "sg:city":"Frankfurt",
    "sg:postcode":"60489",
    "sg:province":"Hessen",
    "wof:name":"Institut F\u00fcr Technologie- Training Gmbh",
    "wof:placetype":"venue"
},
  "geometry": {"coordinates":[8.5968103409,50.1288871765],"type":"Point"}
}