{
  "type": "Feature",
  "properties": {
    "iso:country":"DE",
    "sg:address":"St.-Hubertus-Str. 50",
    "sg:city":"Pforzheim",
    "sg:phone":"+49 7231/97930",
    "sg:postcode":"75181",
    "sg:province":"Baden-W\u00fcrttemberg",
    "wof:name":"B. Nikolaus Immobilienmakler",
    "wof:placetype":"venue"
},
  "geometry": {"coordinates":[8.6956691742,48.8524360657],"type":"Point"}
}