{
  "type": "Feature",
  "properties": {
    "iso:country":"DE",
    "sg:address":"Lofotenstr. 4",
    "sg:city":"Bremerhaven",
    "sg:phone":"+49 471/79850",
    "sg:postcode":"27572",
    "sg:province":"Bremen",
    "wof:name":"E. H. Harms Gmbh & Co.",
    "wof:placetype":"venue"
},
  "geometry": {"coordinates":[8.591037,53.508244],"type":"Point"}
}