{
  "type": "Feature",
  "properties": {
    "iso:country":"DE",
    "sg:address":"Erzh\u00fctter Str. 68",
    "sg:city":"Kaiserslautern",
    "sg:phone":"+49 631/72519",
    "sg:postcode":"67659",
    "sg:province":"Rheinland-Pfalz",
    "wof:name":"Ev. Pfarramt Erzh\u00fctten",
    "wof:placetype":"venue"
},
  "geometry": {"coordinates":[7.7360658646,49.4589805603],"type":"Point"}
}