{
  "type": "Feature",
  "properties": {
    "iso:country":"DE",
    "sg:address":"Bergheimer Str. 37",
    "sg:city":"Heidelberg",
    "sg:phone":"+49 6221/21657",
    "sg:postcode":"69115",
    "sg:province":"Baden-W\u00fcrttemberg",
    "wof:name":"Arras Budo-shop",
    "wof:placetype":"venue"
},
  "geometry": {"coordinates":[8.689021,49.408394],"type":"Point"}
}