{
  "type": "Feature",
  "properties": {
    "iso:country":"DE",
    "sg:address":"Weststr. 14",
    "sg:city":"Regis-Breitingen",
    "sg:postcode":"04565",
    "sg:province":"Sachsen",
    "wof:name":"M\u00fcllers Fliesen Gmbh",
    "wof:placetype":"venue"
},
  "geometry": {"coordinates":[12.44535923,51.0885887146],"type":"Point"}
}