{
  "type": "Feature",
  "properties": {
    "iso:country":"DE",
    "sg:address":"Wartenbergstr. 76",
    "sg:city":"Rheda-Wiedenbr\u00fcck",
    "sg:phone":"+49 5242/2044",
    "sg:postcode":"33378",
    "sg:province":"Nordrhein-Westfalen",
    "wof:name":"Martina Riehm-schmitz Rechtsanw\u00e4ltin",
    "wof:placetype":"venue"
},
  "geometry": {"coordinates":[8.3269071579,51.8358154297],"type":"Point"}
}