{
  "type": "Feature",
  "properties": {
    "iso:country":"DE",
    "sg:address":"Sch\u00f6ne Aussicht 44",
    "sg:city":"Wiesbaden",
    "sg:postcode":"65193",
    "sg:province":"Hessen",
    "wof:name":"Gft Ges. Zur F\u00f6rderung Neuer Transporttechnologien Mbh",
    "wof:placetype":"venue"
},
  "geometry": {"coordinates":[8.251405,50.08746],"type":"Point"}
}