{
  "type": "Feature",
  "properties": {
    "iso:country":"DE",
    "sg:address":"August-Bebel-Str. 48",
    "sg:city":"Zschorlau",
    "sg:postcode":"08321",
    "sg:province":"Sachsen",
    "wof:name":"Ev.-luth. Kirche Zschorlau",
    "wof:placetype":"venue"
},
  "geometry": {"coordinates":[12.6494913101,50.5677185059],"type":"Point"}
}