{
  "type": "Feature",
  "properties": {
    "iso:country":"DE",
    "sg:address":"Kirchstr. 5",
    "sg:city":"Aurich",
    "sg:phone":"+49 4941/958513",
    "sg:postcode":"26603",
    "sg:province":"Niedersachsen",
    "wof:name":"Awo Pflegedienst",
    "wof:placetype":"venue"
},
  "geometry": {"coordinates":[7.479911,53.469849],"type":"Point"}
}