{
  "type": "Feature",
  "properties": {
    "iso:country":"DE",
    "sg:address":"Heegerm\u00fchler Str. 17",
    "sg:city":"Eberswalde",
    "sg:phone":"+49 3334/20110",
    "sg:postcode":"16225",
    "sg:province":"Brandenburg",
    "wof:name":"Eberswalder Eisenhandlung Eduard Eins Gmbh",
    "wof:placetype":"venue"
},
  "geometry": {"coordinates":[13.7891,52.835976],"type":"Point"}
}