{
  "type": "Feature",
  "properties": {
    "iso:country":"DE",
    "sg:address":"Hengsener Str. 8-8a",
    "sg:city":"Dortmund",
    "sg:phone":"+49 231/9250550",
    "sg:postcode":"44309",
    "sg:province":"Nordrhein-Westfalen",
    "wof:name":"Rhein-ruhr Druck Sander Kg",
    "wof:placetype":"venue"
},
  "geometry": {"coordinates":[7.5547618866,51.5205039978],"type":"Point"}
}