{
  "type": "Feature",
  "properties": {
    "iso:country":"DE",
    "sg:address":"Herbergsgasse",
    "sg:city":"Saarbr\u00fccken",
    "sg:postcode":"66111",
    "sg:province":"Saarland",
    "wof:name":"Vend\u00f4me-interieur",
    "wof:placetype":"venue"
},
  "geometry": {"coordinates":[6.99619,49.233582],"type":"Point"}
}