{
  "type": "Feature",
  "properties": {
    "iso:country":"DE",
    "sg:address":"Elberfelder Str. 8",
    "sg:city":"Wuppertal",
    "sg:postcode":"42285",
    "sg:province":"Nordrhein-Westfalen",
    "wof:name":"Wal-mart Supercenter",
    "wof:placetype":"venue"
},
  "geometry": {"coordinates":[7.1656608582,51.2571754456],"type":"Point"}
}