{
  "type": "Feature",
  "properties": {
    "iso:country":"DE",
    "sg:address":"Am R\u00e4schen",
    "sg:city":"Wasungen",
    "sg:phone":"+49 36941/71581",
    "sg:postcode":"98634",
    "sg:province":"Th\u00fcringen",
    "wof:name":"K\u00fcchen Und Wohnparadies Gmbh",
    "wof:placetype":"venue"
},
  "geometry": {"coordinates":[10.3792705536,50.6544761658],"type":"Point"}
}