{
  "type": "Feature",
  "properties": {
    "iso:country":"DE",
    "sg:address":"Edisonstr. 17",
    "sg:city":"Bielefeld",
    "sg:phone":"+49 5205/5688",
    "sg:postcode":"33689",
    "sg:province":"Nordrhein-Westfalen",
    "wof:name":"Ravensberger Druck- Und Verlagsanstalt Gmbh",
    "wof:placetype":"venue"
},
  "geometry": {"coordinates":[8.575586319,51.9562187195],"type":"Point"}
}