{
  "type": "Feature",
  "properties": {
    "iso:country":"DE",
    "sg:address":"Leuzbacher Weg 2",
    "sg:city":"Altenkirchen",
    "sg:phone":"+49 2681/3055",
    "sg:postcode":"57610",
    "sg:province":"Rheinland-Pfalz",
    "wof:name":"Altenkirchener Bestattungs- Haus H. Arbeer",
    "wof:placetype":"venue"
},
  "geometry": {"coordinates":[7.635382,50.685379],"type":"Point"}
}