{
  "type": "Feature",
  "properties": {
    "iso:country":"DE",
    "sg:address":"St.-Leonhard-Str. 23",
    "sg:city":"Vilsheim",
    "sg:phone":"+49 8706/421",
    "sg:postcode":"84186",
    "sg:province":"Bayern",
    "wof:name":"Rgw- R\u00fcckgewinnung Und Wiederverwertung Gmbh",
    "wof:placetype":"venue"
},
  "geometry": {"coordinates":[12.0906457901,48.4525299072],"type":"Point"}
}