{
  "type": "Feature",
  "properties": {
    "iso:country":"DE",
    "sg:address":"Luisenstr. 6",
    "sg:city":"Oftersheim",
    "sg:phone":"+49 6202/51549",
    "sg:postcode":"68723",
    "sg:province":"Baden-W\u00fcrttemberg",
    "wof:name":"Werner Menger",
    "wof:placetype":"venue"
},
  "geometry": {"coordinates":[8.581497,49.371838],"type":"Point"}
}