{
  "type": "Feature",
  "properties": {
    "iso:country":"DE",
    "sg:address":"Dorfanger 31a",
    "sg:city":"Klitzschen",
    "sg:postcode":"04860",
    "sg:province":"Sachsen",
    "wof:name":"Manuela G\u00e4rtner",
    "wof:placetype":"venue"
},
  "geometry": {"coordinates":[12.974857,51.557549],"type":"Point"}
}