{
  "type": "Feature",
  "properties": {
    "iso:country":"DE",
    "sg:address":"Industriestr.",
    "sg:city":"Zella-Mehlis",
    "sg:phone":"+49 3682/46315",
    "sg:postcode":"98544",
    "sg:province":"Th\u00fcringen",
    "wof:name":"Mc Donalds",
    "wof:placetype":"venue"
},
  "geometry": {"coordinates":[10.6881999969,50.6447525024],"type":"Point"}
}