{
  "type": "Feature",
  "properties": {
    "iso:country":"DE",
    "sg:address":"Kempener Str. 8",
    "sg:city":"Krefeld",
    "sg:postcode":"47839",
    "sg:province":"Nordrhein-Westfalen",
    "wof:name":"Ralph H\u00f6fges Gmbh",
    "wof:placetype":"venue"
},
  "geometry": {"coordinates":[6.507931,51.372688],"type":"Point"}
}