{
  "type": "Feature",
  "properties": {
    "iso:country":"DE",
    "sg:address":"Schleusenstr. 25",
    "sg:city":"Rheine",
    "sg:phone":"+49 5971/961511",
    "sg:postcode":"48429",
    "sg:province":"Nordrhein-Westfalen",
    "wof:name":"Dr. Rohrmann",
    "wof:placetype":"venue"
},
  "geometry": {"coordinates":[7.4357128143,52.286857605],"type":"Point"}
}