{
  "type": "Feature",
  "properties": {
    "iso:country":"DE",
    "sg:address":"Parkstr. 8-10",
    "sg:city":"D\u00fcsseldorf",
    "sg:phone":"+49 4921/1494005",
    "sg:postcode":"40477",
    "sg:province":"Nordrhein-Westfalen",
    "wof:name":"Th Hillebrand Kg Gmbh & Co",
    "wof:placetype":"venue"
},
  "geometry": {"coordinates":[6.780368,51.23835],"type":"Point"}
}