{
  "type": "Feature",
  "properties": {
    "iso:country":"DE",
    "sg:address":"Schulstr. 1",
    "sg:city":"Sandhausen",
    "sg:phone":"+49 6224/2463",
    "sg:postcode":"69207",
    "sg:province":"Baden-W\u00fcrttemberg",
    "wof:name":"R. Winnewisser",
    "wof:placetype":"venue"
},
  "geometry": {"coordinates":[8.657608,49.341846],"type":"Point"}
}