{
  "type": "Feature",
  "properties": {
    "iso:country":"DE",
    "sg:address":"Langenheim 2",
    "sg:city":"Petersaurach",
    "sg:phone":"+49 9802/700",
    "sg:postcode":"91580",
    "sg:province":"Bayern",
    "wof:name":"Busch & Co. Hanns Seifert Gmbh & Co.",
    "wof:placetype":"venue"
},
  "geometry": {"coordinates":[10.747345,49.31023],"type":"Point"}
}