{
  "type": "Feature",
  "properties": {
    "iso:country":"DE",
    "sg:address":"Am Busch 15",
    "sg:city":"Detmold",
    "sg:phone":"+49 5232/8389",
    "sg:postcode":"32758",
    "sg:province":"Nordrhein-Westfalen",
    "wof:name":"B. Wirth Ingenieur",
    "wof:placetype":"venue"
},
  "geometry": {"coordinates":[8.7927007675,51.940952301],"type":"Point"}
}