{
  "type": "Feature",
  "properties": {
    "iso:country":"DE",
    "sg:address":"Am Breil 29",
    "sg:city":"Meerbusch",
    "sg:phone":"+49 2132/2843",
    "sg:postcode":"40667",
    "sg:province":"Nordrhein-Westfalen",
    "wof:name":"Prof. Dr. G\u00fcnter Tondorf Rechtsanwalt",
    "wof:placetype":"venue"
},
  "geometry": {"coordinates":[6.6825032234,51.2606658936],"type":"Point"}
}