{
  "type": "Feature",
  "properties": {
    "iso:country":"DE",
    "sg:address":"Gerberstr. 2",
    "sg:city":"Aichstetten",
    "sg:phone":"+49 7565/914191",
    "sg:postcode":"88317",
    "sg:province":"Baden-W\u00fcrttemberg",
    "wof:name":"Pizza-express Da Enzo",
    "wof:placetype":"venue"
},
  "geometry": {"coordinates":[10.0781707764,47.8940048218],"type":"Point"}
}