{
  "type": "Feature",
  "properties": {
    "iso:country":"DE",
    "sg:address":"Kurgartenstr. 125",
    "sg:city":"L\u00fcbeck",
    "sg:phone":"+49 4502/5743",
    "sg:postcode":"23570",
    "sg:province":"Schleswig-Holstein",
    "wof:name":"Volkmar Brecht",
    "wof:placetype":"venue"
},
  "geometry": {"coordinates":[10.872345,53.959335],"type":"Point"}
}