{
  "type": "Feature",
  "properties": {
    "iso:country":"DE",
    "sg:address":"Goethestr. 85",
    "sg:city":"Rathenow",
    "sg:phone":"+49 3385/54300",
    "sg:postcode":"14712",
    "sg:province":"Brandenburg",
    "wof:name":"Erdmanns Reisedienst Gmbh",
    "wof:placetype":"venue"
},
  "geometry": {"coordinates":[12.343091011,52.6068572998],"type":"Point"}
}