{
  "type": "Feature",
  "properties": {
    "iso:country":"DE",
    "sg:address":"Chausseestr. 44",
    "sg:city":"Buchholz",
    "sg:phone":"+49 33204/42206",
    "sg:postcode":"14547",
    "sg:province":"Brandenburg",
    "wof:name":"Metallbau Kaplick",
    "wof:placetype":"venue"
},
  "geometry": {"coordinates":[12.9773797989,52.2322616577],"type":"Point"}
}