{
  "type": "Feature",
  "properties": {
    "iso:country":"DE",
    "sg:address":"Egerlandstr. 52",
    "sg:city":"Geretsried",
    "sg:phone":"+49 8171/60019",
    "sg:postcode":"82538",
    "sg:province":"Bayern",
    "wof:name":"Ristaurante La Trattoria Gmbh",
    "wof:placetype":"venue"
},
  "geometry": {"coordinates":[11.4682369232,47.8748016357],"type":"Point"}
}