{
  "type": "Feature",
  "properties": {
    "iso:country":"DE",
    "sg:address":"Franz-Schubert-Str. 6",
    "sg:city":"Traunreut",
    "sg:phone":"+49 8669/9208",
    "sg:postcode":"83301",
    "sg:province":"Bayern",
    "wof:name":"Franz Schwarz",
    "wof:placetype":"venue"
},
  "geometry": {"coordinates":[12.5994577408,47.9611778259],"type":"Point"}
}