{
  "type": "Feature",
  "properties": {
    "iso:country":"DE",
    "sg:address":"Ernestinenstr. 73",
    "sg:city":"Essen",
    "sg:phone":"+49 201/29855",
    "sg:postcode":"45141",
    "sg:province":"Nordrhein-Westfalen",
    "wof:name":"Br\u00fcning Gmbh & Co.",
    "wof:placetype":"venue"
},
  "geometry": {"coordinates":[7.044401,51.472244],"type":"Point"}
}