{
  "type": "Feature",
  "properties": {
    "iso:country":"DE",
    "sg:address":"Ruhrallee 19",
    "sg:city":"Hattingen",
    "sg:phone":"+49 2324/9180",
    "sg:postcode":"45525",
    "sg:province":"Nordrhein-Westfalen",
    "wof:name":"Bildungswerk Witten- Hattingen Gmbh",
    "wof:placetype":"venue"
},
  "geometry": {"coordinates":[7.18254,51.408039],"type":"Point"}
}