{
  "type": "Feature",
  "properties": {
    "iso:country":"DE",
    "sg:address":"Peter-B\u00f6hm-Str. 36",
    "sg:city":"Eppelheim",
    "sg:phone":"+49 6221/763403",
    "sg:postcode":"69214",
    "sg:province":"Baden-W\u00fcrttemberg",
    "wof:name":"W. Leis",
    "wof:placetype":"venue"
},
  "geometry": {"coordinates":[8.630749,49.397133],"type":"Point"}
}