{
  "type": "Feature",
  "properties": {
    "iso:country":"DE",
    "sg:address":"Krausenstr. 6c",
    "sg:city":"Hannover",
    "sg:phone":"+49 511/885947",
    "sg:postcode":"30171",
    "sg:province":"Niedersachsen",
    "wof:name":"Hermann Bartels Tennislehrer",
    "wof:placetype":"venue"
},
  "geometry": {"coordinates":[9.7512493134,52.3624420166],"type":"Point"}
}