{
  "type": "Feature",
  "properties": {
    "iso:country":"DE",
    "sg:address":"Untergasse 9",
    "sg:city":"Neuwied",
    "sg:phone":"+49 2631/49850",
    "sg:postcode":"56566",
    "sg:province":"Rheinland-Pfalz",
    "wof:name":"Kurt Olk Heizung Sanit\u00e4r",
    "wof:placetype":"venue"
},
  "geometry": {"coordinates":[7.520769,50.458958],"type":"Point"}
}