{
  "type": "Feature",
  "properties": {
    "iso:country":"DE",
    "sg:address":"R\u00f6merstr. 48a",
    "sg:city":"Heidelberg",
    "sg:phone":"+49 4962/2127178",
    "sg:postcode":"69115",
    "sg:province":"Baden-W\u00fcrttemberg",
    "wof:name":"Mms Modulare Microcomputersysteme & Software Gmbh",
    "wof:placetype":"venue"
},
  "geometry": {"coordinates":[8.6846809387,49.4027481079],"type":"Point"}
}