{
  "type": "Feature",
  "properties": {
    "iso:country":"DE",
    "sg:address":"Lindenstr. 3",
    "sg:city":"Wilhelmsthal",
    "sg:phone":"+49 9260/393",
    "sg:postcode":"96352",
    "sg:province":"Bayern",
    "wof:name":"A. V\u00f6lkel",
    "wof:placetype":"venue"
},
  "geometry": {"coordinates":[11.3552675247,50.3209915161],"type":"Point"}
}