{
  "type": "Feature",
  "properties": {
    "iso:country":"DE",
    "sg:address":"Rimbergstr. 1",
    "sg:city":"Biebertal",
    "sg:phone":"+49 6409/6311",
    "sg:postcode":"35444",
    "sg:province":"Hessen",
    "wof:name":"W. Bender",
    "wof:placetype":"venue"
},
  "geometry": {"coordinates":[8.580945,50.625809],"type":"Point"}
}