{
  "type": "Feature",
  "properties": {
    "iso:country":"DE",
    "sg:address":"Poststr. 1a",
    "sg:city":"Ottendorf-Okrilla",
    "sg:phone":"+49 35205/73752",
    "sg:postcode":"01458",
    "sg:province":"Sachsen",
    "wof:name":"Cafe Gnauck Im Neuen Markt",
    "wof:placetype":"venue"
},
  "geometry": {"coordinates":[13.82965,51.185696],"type":"Point"}
}