{
  "type": "Feature",
  "properties": {
    "iso:country":"DE",
    "sg:address":"Lahnstr. 2",
    "sg:city":"Dautphetal",
    "sg:phone":"+49 6466/6868",
    "sg:postcode":"35232",
    "sg:province":"Hessen",
    "wof:name":"N. Aylan",
    "wof:placetype":"venue"
},
  "geometry": {"coordinates":[8.549852,50.869659],"type":"Point"}
}