{
  "type": "Feature",
  "properties": {
    "iso:country":"DE",
    "sg:address":"Luisenstr. 22",
    "sg:city":"Elz",
    "sg:phone":"+49 6431/54818",
    "sg:postcode":"65604",
    "sg:province":"Hessen",
    "wof:name":"Friedrich Gro\u00df",
    "wof:placetype":"venue"
},
  "geometry": {"coordinates":[8.0334358215,50.408405304],"type":"Point"}
}