{
  "type": "Feature",
  "properties": {
    "iso:country":"DE",
    "sg:address":"L\u00f6hrstr. 18",
    "sg:city":"Neunkirchen",
    "sg:phone":"+49 2735/2367",
    "sg:postcode":"57290",
    "sg:province":"Nordrhein-Westfalen",
    "wof:name":"Karl Str\u00f6hmann Elektroinstallation",
    "wof:placetype":"venue"
},
  "geometry": {"coordinates":[7.996425,50.787785],"type":"Point"}
}