{
  "type": "Feature",
  "properties": {
    "iso:country":"DE",
    "sg:address":"Mastener Str. 8",
    "sg:city":"D\u00f6beln",
    "sg:postcode":"04720",
    "sg:province":"Sachsen",
    "wof:name":"Tilo Vaclahovsky Autohandel E. K.",
    "wof:placetype":"venue"
},
  "geometry": {"coordinates":[13.098828,51.124332],"type":"Point"}
}