{
  "type": "Feature",
  "properties": {
    "iso:country":"DE",
    "sg:address":"Kaldenkirchener Str. 68",
    "sg:city":"M\u00f6nchengladbach",
    "sg:phone":"+49 2161/22522",
    "sg:postcode":"41063",
    "sg:province":"Nordrhein-Westfalen",
    "wof:name":"Hans J. Reitschmidt Heilpraktiker",
    "wof:placetype":"venue"
},
  "geometry": {"coordinates":[6.4340977669,51.2123565674],"type":"Point"}
}