{
  "type": "Feature",
  "properties": {
    "iso:country":"DE",
    "sg:address":"Gau\u00dfstra\u00dfe 4",
    "sg:city":"Leinfelden-Echterdingen",
    "sg:phone":"+49 711/902140",
    "sg:postcode":"70771",
    "sg:province":"Baden-W\u00fcrttemberg",
    "wof:name":"Hospes Messebau Gmbh",
    "wof:placetype":"venue"
},
  "geometry": {"coordinates":[9.161942,48.695625],"type":"Point"}
}