{
  "type": "Feature",
  "properties": {
    "iso:country":"DE",
    "sg:address":"R\u00f6ntgenstr. 13",
    "sg:city":"Darmstadt",
    "sg:phone":"+49 6151/423646",
    "sg:postcode":"64291",
    "sg:province":"Hessen",
    "wof:name":"W W Elektronik Gmbh",
    "wof:placetype":"venue"
},
  "geometry": {"coordinates":[8.638745,49.917244],"type":"Point"}
}