{
  "type": "Feature",
  "properties": {
    "iso:country":"DE",
    "sg:address":"M\u00fchlstr. 16",
    "sg:city":"Ramberg",
    "sg:phone":"+49 6345/8220",
    "sg:postcode":"76857",
    "sg:province":"Rheinland-Pfalz",
    "wof:name":"Josef Klein Jr.",
    "wof:placetype":"venue"
},
  "geometry": {"coordinates":[8.0094604492,49.2626113892],"type":"Point"}
}