{
  "type": "Feature",
  "properties": {
    "iso:country":"DE",
    "sg:address":"Erpinghofstr. 68",
    "sg:city":"Dortmund",
    "sg:phone":"+49 231/393131",
    "sg:postcode":"44369",
    "sg:province":"Nordrhein-Westfalen",
    "wof:name":"Diakonische Dienste Dortmund Ggmbh",
    "wof:placetype":"venue"
},
  "geometry": {"coordinates":[7.399133,51.533787],"type":"Point"}
}