{
  "type": "Feature",
  "properties": {
    "iso:country":"DE",
    "sg:address":"Bernhard-Stade-Weg 2",
    "sg:city":"Dortmund",
    "sg:phone":"+49 231/731365",
    "sg:postcode":"44229",
    "sg:province":"Nordrhein-Westfalen",
    "wof:name":"Heinrich Reber",
    "wof:placetype":"venue"
},
  "geometry": {"coordinates":[7.466974,51.45647],"type":"Point"}
}