{
  "type": "Feature",
  "properties": {
    "iso:country":"DE",
    "sg:address":"Vorburggasse 11",
    "sg:city":"Meersburg",
    "sg:phone":"+49 7532/431115",
    "sg:postcode":"88709",
    "sg:province":"Baden-W\u00fcrttemberg",
    "wof:name":"Weinbaumuseum Mersburg",
    "wof:placetype":"venue"
},
  "geometry": {"coordinates":[9.273087,47.693794],"type":"Point"}
}