{
  "type": "Feature",
  "properties": {
    "iso:country":"DE",
    "sg:address":"W\u00fcrzburger Str. 38",
    "sg:city":"Gem\u00fcnden",
    "sg:phone":"+49 9351/90099",
    "sg:postcode":"97737",
    "sg:province":"Bayern",
    "wof:name":"Fitness-world Sonja Fischer",
    "wof:placetype":"venue"
},
  "geometry": {"coordinates":[9.6734924316,50.0604057312],"type":"Point"}
}