{
  "type": "Feature",
  "properties": {
    "iso:country":"DE",
    "sg:address":"Erich-Schlesinger-Str 50",
    "sg:city":"Rostock",
    "sg:phone":"+49 381/4403270",
    "sg:postcode":"18059",
    "sg:province":"Mecklenburg-Vorpommern",
    "wof:name":"Asd Advanced Simulation And Design Gmbh",
    "wof:placetype":"venue"
},
  "geometry": {"coordinates":[12.131978,54.072617],"type":"Point"}
}