{
  "type": "Feature",
  "properties": {
    "iso:country":"DE",
    "sg:address":"Reichenbach 2 /1",
    "sg:city":"Biberach",
    "sg:phone":"+49 7351/22994",
    "sg:postcode":"88400",
    "sg:province":"Baden-W\u00fcrttemberg",
    "wof:name":"K. Maier",
    "wof:placetype":"venue"
},
  "geometry": {"coordinates":[9.8467292786,48.0774002075],"type":"Point"}
}