{
  "type": "Feature",
  "properties": {
    "iso:country":"DE",
    "sg:address":"B\u00fcrgermeister-Trupp-Str. 4",
    "sg:city":"Ludwigshafen",
    "sg:phone":"+49 621/653089",
    "sg:postcode":"67069",
    "sg:province":"Rheinland-Pfalz",
    "wof:name":"Hartmut Patschke Heilpraktiker",
    "wof:placetype":"venue"
},
  "geometry": {"coordinates":[8.4065237045,49.5199356079],"type":"Point"}
}