{
  "type": "Feature",
  "properties": {
    "iso:country":"DE",
    "sg:address":"Im Blecken 28",
    "sg:city":"Sassenburg",
    "sg:phone":"+49 5371/61503",
    "sg:postcode":"38524",
    "sg:province":"Niedersachsen",
    "wof:name":"Uwe Jensen",
    "wof:placetype":"venue"
},
  "geometry": {"coordinates":[10.626112,52.494442],"type":"Point"}
}