{
  "type": "Feature",
  "properties": {
    "iso:country":"DE",
    "sg:address":"Autengr\u00fcner Str. 2a",
    "sg:city":"Oberkotzau",
    "sg:phone":"+49 9286/6221",
    "sg:postcode":"95145",
    "sg:province":"Bayern",
    "wof:name":"Hartmut Zeitler",
    "wof:placetype":"venue"
},
  "geometry": {"coordinates":[11.9284563065,50.2608757019],"type":"Point"}
}