{
  "type": "Feature",
  "properties": {
    "iso:country":"DE",
    "sg:address":"Im Roten Busch 44",
    "sg:city":"Kamen",
    "sg:postcode":"59174",
    "sg:province":"Nordrhein-Westfalen",
    "wof:name":"Merlin Unternehmens- Beratung Gmbh",
    "wof:placetype":"venue"
},
  "geometry": {"coordinates":[7.605977,51.575851],"type":"Point"}
}