{
  "type": "Feature",
  "properties": {
    "iso:country":"DE",
    "sg:address":"Gartenstr. 16",
    "sg:city":"Eschbach",
    "sg:phone":"+49 7667/1510",
    "sg:postcode":"79427",
    "sg:province":"Baden-W\u00fcrttemberg",
    "wof:name":"Manfred Freier",
    "wof:placetype":"venue"
},
  "geometry": {"coordinates":[7.65684,47.887733],"type":"Point"}
}