{
  "type": "Feature",
  "properties": {
    "iso:country":"DE",
    "sg:address":"Im Jagdfeld 8",
    "sg:city":"Neuss",
    "sg:phone":"+49 2131/82294",
    "sg:postcode":"41464",
    "sg:province":"Nordrhein-Westfalen",
    "wof:name":"W. Kemmerling",
    "wof:placetype":"venue"
},
  "geometry": {"coordinates":[6.6773519516,51.1899871826],"type":"Point"}
}