{
  "type": "Feature",
  "properties": {
    "iso:country":"DE",
    "sg:address":"Baiersbronner Str. 23",
    "sg:city":"Freudenstadt",
    "sg:phone":"+49 4974/423070",
    "sg:postcode":"72250",
    "sg:province":"Baden-W\u00fcrttemberg",
    "wof:name":"Kreissparkasse Baiersbronn Eg",
    "wof:placetype":"venue"
},
  "geometry": {"coordinates":[8.314051,48.471592],"type":"Point"}
}