{
  "type": "Feature",
  "properties": {
    "iso:country":"DE",
    "sg:address":"Untertor 25b",
    "sg:city":"Rotenburg",
    "sg:phone":"+49 6623/92420",
    "sg:postcode":"36199",
    "sg:province":"Hessen",
    "wof:name":"Ulrich Martens",
    "wof:placetype":"venue"
},
  "geometry": {"coordinates":[9.72215271,50.9980926514],"type":"Point"}
}