{
  "type": "Feature",
  "properties": {
    "iso:country":"DE",
    "sg:address":"Reinhold-Schick-Platz 3",
    "sg:city":"Herrenberg",
    "sg:phone":"+49 7032/5184",
    "sg:postcode":"71083",
    "sg:province":"Baden-W\u00fcrttemberg",
    "wof:name":"Pub-cafe",
    "wof:placetype":"venue"
},
  "geometry": {"coordinates":[8.867624,48.595531],"type":"Point"}
}