{
  "type": "Feature",
  "properties": {
    "iso:country":"DE",
    "sg:address":"Am Bahnhof 45",
    "sg:city":"Walsrode",
    "sg:phone":"+49 5161/609505",
    "sg:postcode":"29664",
    "sg:province":"Niedersachsen",
    "wof:name":"Wipak Medical",
    "wof:placetype":"venue"
},
  "geometry": {"coordinates":[9.600060463,52.8672714233],"type":"Point"}
}