{
  "type": "Feature",
  "properties": {
    "iso:country":"DE",
    "sg:address":"Woerishofferstr. 4",
    "sg:city":"Karlsruhe",
    "sg:phone":"+49 721/865151",
    "sg:postcode":"76189",
    "sg:province":"Baden-W\u00fcrttemberg",
    "wof:name":"Dr. Med. Christoph Palenga",
    "wof:placetype":"venue"
},
  "geometry": {"coordinates":[8.3691301346,48.9812316895],"type":"Point"}
}