{
  "type": "Feature",
  "properties": {
    "iso:country":"DE",
    "sg:address":"Reinhold-Meyer-Str. 28 b",
    "sg:city":"Hamburg",
    "sg:phone":"+49 40/5551937",
    "sg:postcode":"22455",
    "sg:province":"Hamburg",
    "wof:name":"Hans-joachim Richter Architekt",
    "wof:placetype":"venue"
},
  "geometry": {"coordinates":[9.950099,53.646358],"type":"Point"}
}