{
  "type": "Feature",
  "properties": {
    "iso:country":"DE",
    "sg:address":"Steinbrinkstr. 214",
    "sg:city":"Oberhausen",
    "sg:postcode":"46145",
    "sg:province":"Nordrhein-Westfalen",
    "wof:name":"Champion Sportartikel-handel Gmbh & Co.",
    "wof:placetype":"venue"
},
  "geometry": {"coordinates":[6.848554,51.515366],"type":"Point"}
}