{
  "type": "Feature",
  "properties": {
    "iso:country":"DE",
    "sg:address":"Schulstr. 25",
    "sg:city":"Annaburg",
    "sg:phone":"+49 35385/21163",
    "sg:postcode":"06925",
    "sg:province":"Sachsen-Anhalt",
    "wof:name":"Evelin Grabsch",
    "wof:placetype":"venue"
},
  "geometry": {"coordinates":[13.0525560379,51.7316894531],"type":"Point"}
}