{
  "type": "Feature",
  "properties": {
    "iso:country":"DE",
    "sg:address":"Meederer Str. 14",
    "sg:city":"Lautertal",
    "sg:phone":"+49 9561/630723",
    "sg:postcode":"96486",
    "sg:province":"Bayern",
    "wof:name":"Kubatec Kunststoffbau- Technik Coburg Gmbh",
    "wof:placetype":"venue"
},
  "geometry": {"coordinates":[10.973898,50.301189],"type":"Point"}
}