{
  "type": "Feature",
  "properties": {
    "iso:country":"DE",
    "sg:address":"Marktstr. 10",
    "sg:city":"Teisendorf",
    "sg:phone":"+49 8666/454",
    "sg:postcode":"83317",
    "sg:province":"Bayern",
    "wof:name":"Konrad Kern",
    "wof:placetype":"venue"
},
  "geometry": {"coordinates":[12.823107,47.84993],"type":"Point"}
}