{
  "type": "Feature",
  "properties": {
    "iso:country":"DE",
    "sg:address":"Fichtenweg 1",
    "sg:city":"K\u00e4mpfelbach",
    "sg:phone":"+49 7232/311731",
    "sg:postcode":"75236",
    "sg:province":"Baden-W\u00fcrttemberg",
    "wof:name":"Leo Wessinger",
    "wof:placetype":"venue"
},
  "geometry": {"coordinates":[8.6143522263,48.9497261047],"type":"Point"}
}