{
  "type": "Feature",
  "properties": {
    "iso:country":"DE",
    "sg:address":"Zur Halde 33",
    "sg:city":"\u00d6hningen",
    "sg:phone":"+49 7735/97007",
    "sg:postcode":"78337",
    "sg:province":"Baden-W\u00fcrttemberg",
    "wof:name":"Rudolf Ramisch",
    "wof:placetype":"venue"
},
  "geometry": {"coordinates":[8.9281301498,47.6625976562],"type":"Point"}
}