{
  "type": "Feature",
  "properties": {
    "iso:country":"DE",
    "sg:address":"Dorfplatz 21",
    "sg:city":"Hohenau",
    "sg:phone":"+49 8558/1060",
    "sg:postcode":"94545",
    "sg:province":"Bayern",
    "wof:name":"Gastst\u00e4tte Josef Piser",
    "wof:placetype":"venue"
},
  "geometry": {"coordinates":[13.4880514145,48.8498458862],"type":"Point"}
}