{
  "type": "Feature",
  "properties": {
    "iso:country":"DE",
    "sg:address":"Zeppelinstr. 10",
    "sg:city":"Ostfildern",
    "sg:phone":"+49 711/451220",
    "sg:postcode":"73760",
    "sg:province":"Baden-W\u00fcrttemberg",
    "wof:name":"Kauffmann Architekt",
    "wof:placetype":"venue"
},
  "geometry": {"coordinates":[9.229012,48.723053],"type":"Point"}
}