{
  "type": "Feature",
  "properties": {
    "iso:country":"DE",
    "sg:address":"F\u00e4hrstr. 18",
    "sg:city":"Osterr\u00f6nfeld",
    "sg:phone":"+49 4331/80000",
    "sg:postcode":"24783",
    "sg:province":"Schleswig-Holstein",
    "wof:name":"Atelier Lappann",
    "wof:placetype":"venue"
},
  "geometry": {"coordinates":[9.692240715,54.2916946411],"type":"Point"}
}