{
  "type": "Feature",
  "properties": {
    "iso:country":"DE",
    "sg:address":"Max-Planck-Str. 25",
    "sg:city":"Fellbach",
    "sg:phone":"+49 711/5788330",
    "sg:postcode":"70736",
    "sg:province":"Baden-W\u00fcrttemberg",
    "wof:name":"R. Luithard Gmbh & Co.",
    "wof:placetype":"venue"
},
  "geometry": {"coordinates":[9.262728,48.814159],"type":"Point"}
}