{
  "type": "Feature",
  "properties": {
    "iso:country":"DE",
    "sg:address":"Itterstr. 2",
    "sg:city":"Dormagen",
    "sg:phone":"+49 2133/72452",
    "sg:postcode":"41541",
    "sg:province":"Nordrhein-Westfalen",
    "wof:name":"Hans Heidrich",
    "wof:placetype":"venue"
},
  "geometry": {"coordinates":[6.8130631447,51.1369094849],"type":"Point"}
}