{
  "type": "Feature",
  "properties": {
    "iso:country":"DE",
    "sg:address":"Hauptstr. 57",
    "sg:city":"Kempfeld",
    "sg:phone":"+49 6786/1860",
    "sg:postcode":"55758",
    "sg:province":"Rheinland-Pfalz",
    "wof:name":"Heinz & Erwin Becker",
    "wof:placetype":"venue"
},
  "geometry": {"coordinates":[7.242646,49.788322],"type":"Point"}
}