{
  "type": "Feature",
  "properties": {
    "iso:country":"DE",
    "sg:address":"F\u00fcnfkirchener Str. 8",
    "sg:city":"W\u00e4chtersbach",
    "sg:phone":"+49 6053/2185",
    "sg:postcode":"63607",
    "sg:province":"Hessen",
    "wof:name":"Christel Mecke Krankengymnastin",
    "wof:placetype":"venue"
},
  "geometry": {"coordinates":[9.282137,50.248516],"type":"Point"}
}