{
  "type": "Feature",
  "properties": {
    "iso:country":"DE",
    "sg:address":"Carl-Zeiss-Str. 2",
    "sg:city":"Ramstein-Miesenbach",
    "sg:phone":"+49 6371/57776",
    "sg:postcode":"66877",
    "sg:province":"Rheinland-Pfalz",
    "wof:name":"Marys Grill-treff",
    "wof:placetype":"venue"
},
  "geometry": {"coordinates":[7.5366830826,49.4380111694],"type":"Point"}
}