{
  "type": "Feature",
  "properties": {
    "iso:country":"DE",
    "sg:address":"Bahnhofstr. 56",
    "sg:city":"Helpsen",
    "sg:phone":"+49 4957/243930",
    "sg:postcode":"31691",
    "sg:province":"Niedersachsen",
    "wof:name":"W. Hautau Baubeschlag Gmbh",
    "wof:placetype":"venue"
},
  "geometry": {"coordinates":[9.120816,52.308891],"type":"Point"}
}