{
  "type": "Feature",
  "properties": {
    "iso:country":"DE",
    "sg:address":"Wittelsbachstr. 29",
    "sg:city":"D\u00fcsseldorf",
    "sg:phone":"+49 211/6988986",
    "sg:postcode":"40629",
    "sg:province":"Nordrhein-Westfalen",
    "wof:name":"Dr. Udo Knitter Rechtsanwalt",
    "wof:placetype":"venue"
},
  "geometry": {"coordinates":[6.8338007927,51.2372703552],"type":"Point"}
}