{
  "type": "Feature",
  "properties": {
    "iso:country":"DE",
    "sg:address":"Barbarossastr. 92",
    "sg:city":"Esslingen",
    "sg:phone":"+49 711/373911",
    "sg:postcode":"73732",
    "sg:province":"Baden-W\u00fcrttemberg",
    "wof:name":"Alfred Berner",
    "wof:placetype":"venue"
},
  "geometry": {"coordinates":[9.3078556061,48.7559204102],"type":"Point"}
}