{
  "type": "Feature",
  "properties": {
    "iso:country":"DE",
    "sg:address":"Schlo\u00df Hinnenburg",
    "sg:city":"Brakel",
    "sg:phone":"+49 5272/446",
    "sg:postcode":"33034",
    "sg:province":"Nordrhein-Westfalen",
    "wof:name":"Archiv Des Grafen Von Asseburg-rothkirch",
    "wof:placetype":"venue"
},
  "geometry": {"coordinates":[9.181266,51.739834],"type":"Point"}
}