{
  "type": "Feature",
  "properties": {
    "iso:country":"DE",
    "sg:address":"S\u00fcsterfeldstr. 130",
    "sg:city":"Aachen",
    "sg:phone":"+49 241/88810",
    "sg:postcode":"52072",
    "sg:province":"Nordrhein-Westfalen",
    "wof:name":"Chocoladefabriken Lindt & Spr\u00fcngli Gmbh",
    "wof:placetype":"venue"
},
  "geometry": {"coordinates":[6.0681800842,50.7841873169],"type":"Point"}
}