{
  "type": "Feature",
  "properties": {
    "iso:country":"DE",
    "sg:address":"Langer Kornweg",
    "sg:city":"Kelsterbach",
    "sg:phone":"+49 6107/3922",
    "sg:postcode":"65451",
    "sg:province":"Hessen",
    "wof:name":"A. Reith",
    "wof:placetype":"venue"
},
  "geometry": {"coordinates":[8.5178766251,50.0536613464],"type":"Point"}
}