{
  "type": "Feature",
  "properties": {
    "iso:country":"DE",
    "sg:address":"Marktstr. 31",
    "sg:city":"Neuwied",
    "sg:phone":"+49 2631/25337",
    "sg:postcode":"56564",
    "sg:province":"Rheinland-Pfalz",
    "wof:name":"H. Hinkel",
    "wof:placetype":"venue"
},
  "geometry": {"coordinates":[7.458878,50.42754],"type":"Point"}
}