{
  "type": "Feature",
  "properties": {
    "iso:country":"DE",
    "sg:address":"Klever Str. 26",
    "sg:city":"Uedem",
    "sg:postcode":"47589",
    "sg:province":"Nordrhein-Westfalen",
    "wof:name":"Windenergie Lindchen Gmbh & Co. Kg",
    "wof:placetype":"venue"
},
  "geometry": {"coordinates":[6.234759,51.701027],"type":"Point"}
}