{
  "type": "Feature",
  "properties": {
    "iso:country":"DE",
    "sg:address":"Hauptstr. 62",
    "sg:city":"Plaue",
    "sg:phone":"+49 36207/56309",
    "sg:postcode":"99338",
    "sg:province":"Th\u00fcringen",
    "wof:name":"Norbert Br\u00fcckner",
    "wof:placetype":"venue"
},
  "geometry": {"coordinates":[10.8987693787,50.7793235779],"type":"Point"}
}