{
  "type": "Feature",
  "properties": {
    "iso:country":"DE",
    "sg:address":"Prosperstr. 224",
    "sg:city":"Bottrop",
    "sg:phone":"+49 2041/21506",
    "sg:postcode":"46238",
    "sg:province":"Nordrhein-Westfalen",
    "wof:name":"Gilbomi Gesellschaft F\u00fcr Beratung Und Vermittlung Mbh",
    "wof:placetype":"venue"
},
  "geometry": {"coordinates":[6.9516611099,51.5209960938],"type":"Point"}
}