{
  "type": "Feature",
  "properties": {
    "iso:country":"DE",
    "sg:address":"Pfarrer-Mandl-Str. 14",
    "sg:city":"Cham",
    "sg:phone":"+49 9971/30747",
    "sg:postcode":"93413",
    "sg:province":"Bayern",
    "wof:name":"Franz Stoiber",
    "wof:placetype":"venue"
},
  "geometry": {"coordinates":[12.694575,49.209724],"type":"Point"}
}