{
  "type": "Feature",
  "properties": {
    "iso:country":"DE",
    "sg:address":"Sch\u00e4ferweg 9",
    "sg:city":"Detmold",
    "sg:phone":"+49 5232/88081",
    "sg:postcode":"32758",
    "sg:province":"Nordrhein-Westfalen",
    "wof:name":"P. Nitz Mineral\u00f6l-handlung",
    "wof:placetype":"venue"
},
  "geometry": {"coordinates":[8.793337,51.935665],"type":"Point"}
}