{
  "type": "Feature",
  "properties": {
    "iso:country":"DE",
    "sg:address":"Ebertstr. 44",
    "sg:city":"Bergkamen",
    "sg:phone":"+49 2307/87630",
    "sg:postcode":"59192",
    "sg:province":"Nordrhein-Westfalen",
    "wof:name":"Wilfried Pieper",
    "wof:placetype":"venue"
},
  "geometry": {"coordinates":[7.6347079277,51.614276886],"type":"Point"}
}