{
  "type": "Feature",
  "properties": {
    "iso:country":"DE",
    "sg:address":"Glantalstr. 16",
    "sg:city":"Glanbr\u00fccken",
    "sg:phone":"+49 6387/323",
    "sg:postcode":"66887",
    "sg:province":"Rheinland-Pfalz",
    "wof:name":"Weber & H\u00f6bel Ohg",
    "wof:placetype":"venue"
},
  "geometry": {"coordinates":[7.5310850143,49.6149978638],"type":"Point"}
}