{
  "type": "Feature",
  "properties": {
    "iso:country":"DE",
    "sg:address":"Terminal",
    "sg:city":"M\u00f6nchengladbach",
    "sg:phone":"+49 2161/68980",
    "sg:postcode":"41066",
    "sg:province":"Nordrhein-Westfalen",
    "wof:name":"Flughafengesellschaft M\u00f6nchen- Gladbach Gmbh",
    "wof:placetype":"venue"
},
  "geometry": {"coordinates":[6.468764782,51.2238693237],"type":"Point"}
}