{
  "type": "Feature",
  "properties": {
    "iso:country":"DE",
    "sg:address":"R\u00fcsbergstr. 74",
    "sg:city":"Witten",
    "sg:phone":"+49 2324/33800",
    "sg:postcode":"58456",
    "sg:province":"Nordrhein-Westfalen",
    "wof:name":"Amt Anlagen- Und Maschinen-technik Gmbh",
    "wof:placetype":"venue"
},
  "geometry": {"coordinates":[7.2547178268,51.4027709961],"type":"Point"}
}