{
  "type": "Feature",
  "properties": {
    "iso:country":"DE",
    "sg:address":"Belsenplatz 4",
    "sg:city":"D\u00fcsseldorf",
    "sg:phone":"+49 211/600400",
    "sg:postcode":"40545",
    "sg:province":"Nordrhein-Westfalen",
    "wof:name":"Dresen Autohandel Gmbh",
    "wof:placetype":"venue"
},
  "geometry": {"coordinates":[6.7454490662,51.2321548462],"type":"Point"}
}