{
  "type": "Feature",
  "properties": {
    "iso:country":"DE",
    "sg:address":"Friemersheimer Str. 114",
    "sg:city":"Moers",
    "sg:phone":"+49 2841/50109",
    "sg:postcode":"47441",
    "sg:province":"Nordrhein-Westfalen",
    "wof:name":"Team-bau Reich Gmbh",
    "wof:placetype":"venue"
},
  "geometry": {"coordinates":[6.668604,51.436787],"type":"Point"}
}