{
  "type": "Feature",
  "properties": {
    "iso:country":"DE",
    "sg:address":"Gartenstrasse 7",
    "sg:city":"D\u00f6rverden",
    "sg:phone":"+49 4234",
    "sg:postcode":"27313",
    "sg:province":"Niedersachsen",
    "wof:name":"Strulli`s World - Webdesign",
    "wof:placetype":"venue"
},
  "geometry": {"coordinates":[9.236871,52.843987],"type":"Point"}
}