{
  "type": "Feature",
  "properties": {
    "iso:country":"DE",
    "sg:address":"Bahnhofstr. 19",
    "sg:city":"Obergurig",
    "sg:phone":"+49 3591/305233",
    "sg:postcode":"02692",
    "sg:province":"Sachsen",
    "wof:name":"Richter & Kutschke Haustechnik Gmbh",
    "wof:placetype":"venue"
},
  "geometry": {"coordinates":[14.4065284729,51.1387252808],"type":"Point"}
}