{
  "type": "Feature",
  "properties": {
    "iso:country":"DE",
    "sg:address":"Pommernallee 35",
    "sg:city":"Dormagen",
    "sg:phone":"+49 2133/43078",
    "sg:postcode":"41539",
    "sg:province":"Nordrhein-Westfalen",
    "wof:name":"Reimer Immobilien Gmbh",
    "wof:placetype":"venue"
},
  "geometry": {"coordinates":[6.8346099854,51.0982780457],"type":"Point"}
}