{
  "type": "Feature",
  "properties": {
    "iso:country":"DE",
    "sg:city":"Pelm",
    "sg:phone":"+49 6591/4213",
    "sg:postcode":"54570",
    "sg:province":"Rheinland-Pfalz",
    "wof:name":"Adler- Und Wolfspark Kasselburg",
    "wof:placetype":"venue"
},
  "geometry": {"coordinates":[6.689243,50.231853],"type":"Point"}
}