{
  "type": "Feature",
  "properties": {
    "iso:country":"DE",
    "sg:city":"Diekholzen",
    "sg:phone":"+49 5121/263222",
    "sg:postcode":"31199",
    "sg:province":"Niedersachsen",
    "wof:name":"Kreissparkasse Hildesheim",
    "wof:placetype":"venue"
},
  "geometry": {"coordinates":[9.917547,52.094578],"type":"Point"}
}