{
  "type": "Feature",
  "properties": {
    "iso:country":"DE",
    "sg:address":"Poststr. 7",
    "sg:city":"Berlin",
    "sg:phone":"+49 30/2425013",
    "sg:postcode":"10178",
    "sg:province":"Berlin",
    "wof:name":"Engelhardt",
    "wof:placetype":"venue"
},
  "geometry": {"coordinates":[13.405905,52.516975],"type":"Point"}
}