{
  "type": "Feature",
  "properties": {
    "iso:country":"DE",
    "sg:address":"Sportplatzweg 6 e",
    "sg:city":"Heroldsberg",
    "sg:postcode":"90562",
    "sg:province":"Bayern",
    "wof:name":"Gr\u00fcndlachpark Pflege Service Gmbh",
    "wof:placetype":"venue"
},
  "geometry": {"coordinates":[11.150923,49.530739],"type":"Point"}
}