{
  "type": "Feature",
  "properties": {
    "iso:country":"DE",
    "sg:address":"Steinbachstr. 2",
    "sg:city":"B\u00f6hl-Iggelheim",
    "sg:phone":"+49 6324/64936",
    "sg:postcode":"67459",
    "sg:province":"Rheinland-Pfalz",
    "wof:name":"Heimatpflege- Und Museumsver- Ein E. V.",
    "wof:placetype":"venue"
},
  "geometry": {"coordinates":[8.309772,49.36842],"type":"Point"}
}