{
  "type": "Feature",
  "properties": {
    "iso:country":"DE",
    "sg:address":"Ludwig-Thoma-Str. 3",
    "sg:city":"Weilheim",
    "sg:phone":"+49 881/4667",
    "sg:postcode":"82362",
    "sg:province":"Bayern",
    "wof:name":"Ludwig-heinz M\u00fcller Inh. Peter M\u00fcller",
    "wof:placetype":"venue"
},
  "geometry": {"coordinates":[11.153851,47.853474],"type":"Point"}
}