{
  "type": "Feature",
  "properties": {
    "iso:country":"DE",
    "sg:address":"Martin-Schleyer-Str. 6c",
    "sg:city":"Konstanz",
    "sg:phone":"+49 7531/43339",
    "sg:postcode":"78465",
    "sg:province":"Baden-W\u00fcrttemberg",
    "wof:name":"Radsport Reichl",
    "wof:placetype":"venue"
},
  "geometry": {"coordinates":[9.173467,47.71225],"type":"Point"}
}