{
  "type": "Feature",
  "properties": {
    "iso:country":"DE",
    "sg:address":"Flemingstr 7",
    "sg:city":"Fulda",
    "sg:phone":"+49 661/9709074",
    "sg:postcode":"36041",
    "sg:province":"Hessen",
    "wof:name":"Westenholz Motors",
    "wof:placetype":"venue"
},
  "geometry": {"coordinates":[9.6408252716,50.5515060425],"type":"Point"}
}