{
  "type": "Feature",
  "properties": {
    "iso:country":"DE",
    "sg:address":"Lindemannstr. 94",
    "sg:city":"D\u00fcsseldorf",
    "sg:phone":"+49 211/686389",
    "sg:postcode":"40237",
    "sg:province":"Nordrhein-Westfalen",
    "wof:name":"Otto Kurt K\u00fchnel Architekt",
    "wof:placetype":"venue"
},
  "geometry": {"coordinates":[6.808366,51.233391],"type":"Point"}
}