{
  "type": "Feature",
  "properties": {
    "iso:country":"DE",
    "sg:address":"Herzog-Albrecht-Str. 11",
    "sg:city":"Obertraubling",
    "sg:phone":"+49 9401/5486",
    "sg:postcode":"93083",
    "sg:province":"Bayern",
    "wof:name":"Anton Bauer",
    "wof:placetype":"venue"
},
  "geometry": {"coordinates":[12.152525,48.964394],"type":"Point"}
}