{
  "type": "Feature",
  "properties": {
    "iso:country":"DE",
    "sg:address":"Am Weingarten 7",
    "sg:city":"Altdorf",
    "sg:phone":"+49 9187/41640",
    "sg:postcode":"90518",
    "sg:province":"Bayern",
    "wof:name":"G\u00dcnter Schmidt",
    "wof:placetype":"venue"
},
  "geometry": {"coordinates":[11.330831,49.379391],"type":"Point"}
}