{
  "type": "Feature",
  "properties": {
    "iso:country":"DE",
    "sg:address":"Rupt sur Moselle Str. 1",
    "sg:city":"Stadecken-Elsheim",
    "sg:phone":"+49 6130/1316",
    "sg:postcode":"55271",
    "sg:province":"Rheinland-Pfalz",
    "wof:name":"Spielberg-apotheke",
    "wof:placetype":"venue"
},
  "geometry": {"coordinates":[8.127654,49.914364],"type":"Point"}
}