{
  "type": "Feature",
  "properties": {
    "iso:country":"DE",
    "sg:address":"Printzstr. 2",
    "sg:city":"Karlsruhe",
    "sg:phone":"+49 721/625060",
    "sg:postcode":"76139",
    "sg:province":"Baden-W\u00fcrttemberg",
    "wof:name":"Praktiker Bau- Und Heimwerkermarkt",
    "wof:placetype":"venue"
},
  "geometry": {"coordinates":[8.4611501694,49.0204391479],"type":"Point"}
}