{
  "type": "Feature",
  "properties": {
    "iso:country":"DE",
    "sg:address":"Hauptstr. 16",
    "sg:city":"G\u00e4rtringen",
    "sg:phone":"+49 7034/94030",
    "sg:postcode":"71116",
    "sg:province":"Baden-W\u00fcrttemberg",
    "wof:name":"Volksbank Reiseb\u00fcro",
    "wof:placetype":"venue"
},
  "geometry": {"coordinates":[8.9003458023,48.6418876648],"type":"Point"}
}