{
  "type": "Feature",
  "properties": {
    "iso:country":"DE",
    "sg:address":"Eckstr. 5",
    "sg:city":"Waldkirch",
    "sg:phone":"+49 7681/24844",
    "sg:postcode":"79183",
    "sg:province":"Baden-W\u00fcrttemberg",
    "wof:name":"Adelheid Flach",
    "wof:placetype":"venue"
},
  "geometry": {"coordinates":[7.962242,48.093632],"type":"Point"}
}