{
  "type": "Feature",
  "properties": {
    "iso:country":"DE",
    "sg:address":"Zu Den Schreberg\u00e4rten 4",
    "sg:city":"Arnsberg",
    "sg:phone":"+49 4929/3296060",
    "sg:postcode":"59759",
    "sg:province":"Nordrhein-Westfalen",
    "wof:name":"Expol Speditionsgmbh",
    "wof:placetype":"venue"
},
  "geometry": {"coordinates":[7.9962000847,51.4187316895],"type":"Point"}
}