{
  "type": "Feature",
  "properties": {
    "iso:country":"DE",
    "sg:address":"Dr.-M\u00fcller-Str. 26",
    "sg:city":"Weiden",
    "sg:phone":"+49 961/2070",
    "sg:postcode":"92637",
    "sg:province":"Bayern",
    "wof:name":"Deutsche Exide Standby Gmbh",
    "wof:placetype":"venue"
},
  "geometry": {"coordinates":[12.090183,49.686146],"type":"Point"}
}