{
  "type": "Feature",
  "properties": {
    "iso:country":"DE",
    "sg:address":"Sch\u00fcrer Weg 19",
    "sg:city":"Sulzbach",
    "sg:phone":"+49 6897/840847",
    "sg:postcode":"66280",
    "sg:province":"Saarland",
    "wof:name":"Heller Baugesellschaft Mbh",
    "wof:placetype":"venue"
},
  "geometry": {"coordinates":[7.089078,49.305569],"type":"Point"}
}