{
  "type": "Feature",
  "properties": {
    "iso:country":"DE",
    "sg:address":"Bayernstrasse 155",
    "sg:city":"N\u00fcrnberg",
    "sg:postcode":"90478",
    "sg:province":"Bayern",
    "wof:name":"Easy Entry - The Integration People",
    "wof:placetype":"venue"
},
  "geometry": {"coordinates":[11.117333,49.436028],"type":"Point"}
}