{
  "type": "Feature",
  "properties": {
    "iso:country":"DE",
    "sg:address":"G\u00f6ddeldorf",
    "sg:city":"Heilsbronn",
    "sg:phone":"+49 9872/1550",
    "sg:postcode":"91560",
    "sg:province":"Bayern",
    "wof:name":"Wiesengrund",
    "wof:placetype":"venue"
},
  "geometry": {"coordinates":[10.8169412613,49.3354797363],"type":"Point"}
}