{
  "type": "Feature",
  "properties": {
    "iso:country":"DE",
    "sg:address":"Ro\u00dfbachh\u00f6he 2",
    "sg:city":"Taunusstein",
    "sg:phone":"+49 6128/44228",
    "sg:postcode":"65232",
    "sg:province":"Hessen",
    "wof:name":"G\u00fcnther Rudolph Rechtsanwalt",
    "wof:placetype":"venue"
},
  "geometry": {"coordinates":[8.1279382706,50.1299285889],"type":"Point"}
}