{
  "type": "Feature",
  "properties": {
    "iso:country":"DE",
    "sg:address":"Kolpingstr. 40",
    "sg:city":"Zwickau",
    "sg:phone":"+49 375/370100",
    "sg:postcode":"08058",
    "sg:province":"Sachsen",
    "wof:name":"Technosoft Software Vertriebs Gmbh",
    "wof:placetype":"venue"
},
  "geometry": {"coordinates":[12.493642,50.72784],"type":"Point"}
}