{
  "type": "Feature",
  "properties": {
    "iso:country":"DE",
    "sg:address":"Bahnhofstr. 39",
    "sg:city":"Buxtehude",
    "sg:phone":"+49 4161/512440",
    "sg:postcode":"21614",
    "sg:province":"Niedersachsen",
    "wof:name":"Michael Willkomm Finanzberater",
    "wof:placetype":"venue"
},
  "geometry": {"coordinates":[9.6918010712,53.4717941284],"type":"Point"}
}