{
  "type": "Feature",
  "properties": {
    "iso:country":"DE",
    "sg:address":"Robert-Koch-Str. 5",
    "sg:city":"Burghausen",
    "sg:phone":"+49 8677/98790",
    "sg:postcode":"84489",
    "sg:province":"Bayern",
    "wof:name":"Geith Arbeitsschutz Gmbh",
    "wof:placetype":"venue"
},
  "geometry": {"coordinates":[12.834629,48.171257],"type":"Point"}
}