{
  "type": "Feature",
  "properties": {
    "iso:country":"DE",
    "sg:address":"Regensburger Str. 2",
    "sg:city":"Hagelstadt",
    "sg:phone":"+49 9453/340",
    "sg:postcode":"93095",
    "sg:province":"Bayern",
    "wof:name":"Ludwig Grassinger",
    "wof:placetype":"venue"
},
  "geometry": {"coordinates":[12.2142848969,48.896812439],"type":"Point"}
}