{
  "type": "Feature",
  "properties": {
    "iso:country":"DE",
    "sg:address":"Dammenm\u00fchle",
    "sg:city":"Lahr",
    "sg:phone":"+49 7821/93930",
    "sg:postcode":"77933",
    "sg:province":"Baden-W\u00fcrttemberg",
    "wof:name":"Hotel-restaurant Dammenm\u00fchle",
    "wof:placetype":"venue"
},
  "geometry": {"coordinates":[7.8608760834,48.3246574402],"type":"Point"}
}