{
  "type": "Feature",
  "properties": {
    "iso:country":"DE",
    "sg:address":"Achtermannstr. 53",
    "sg:city":"Berlin",
    "sg:postcode":"13187",
    "sg:province":"Berlin",
    "wof:name":"Dr. Med. Margaret Raskowic",
    "wof:placetype":"venue"
},
  "geometry": {"coordinates":[13.419751,52.577],"type":"Point"}
}