{
  "type": "Feature",
  "properties": {
    "iso:country":"DE",
    "sg:address":"Werftstr. 21",
    "sg:city":"Gelsenkirchen",
    "sg:phone":"+49 209/408030",
    "sg:postcode":"45881",
    "sg:province":"Nordrhein-Westfalen",
    "wof:name":"Siefert Spedition Schwertransporte Gmbh",
    "wof:placetype":"venue"
},
  "geometry": {"coordinates":[7.0722289085,51.5340652466],"type":"Point"}
}