{
  "type": "Feature",
  "properties": {
    "iso:country":"DE",
    "sg:address":"Verdener Landstr. 140",
    "sg:city":"Nienburg",
    "sg:phone":"+49 5021/910066",
    "sg:postcode":"31582",
    "sg:province":"Niedersachsen",
    "wof:name":"Ergotec B\u00fcrosysteme Gmbh",
    "wof:placetype":"venue"
},
  "geometry": {"coordinates":[9.2221899033,52.6631584167],"type":"Point"}
}