{
  "type": "Feature",
  "properties": {
    "iso:country":"DE",
    "sg:address":"Dahner Str. 18",
    "sg:city":"Fischbach",
    "sg:phone":"+49 6393/1338",
    "sg:postcode":"66996",
    "sg:province":"Rheinland-Pfalz",
    "wof:name":"Restaurant Pf\u00e4lzer Eck",
    "wof:placetype":"venue"
},
  "geometry": {"coordinates":[7.6617918015,49.0754318237],"type":"Point"}
}