{
  "type": "Feature",
  "properties": {
    "iso:country":"DE",
    "sg:address":"Im Grund 1",
    "sg:city":"Trittau",
    "sg:phone":"+49 4154/2237",
    "sg:postcode":"22946",
    "sg:province":"Schleswig-Holstein",
    "wof:name":"August Lewels Architekt",
    "wof:placetype":"venue"
},
  "geometry": {"coordinates":[10.406023,53.629555],"type":"Point"}
}