{
  "type": "Feature",
  "properties": {
    "iso:country":"DE",
    "sg:address":"Ohechaussee 79",
    "sg:city":"Norderstedt",
    "sg:phone":"+49 40/52883383",
    "sg:postcode":"22848",
    "sg:province":"Schleswig-Holstein",
    "wof:name":"Trave Korrosionsschutz Gmbh",
    "wof:placetype":"venue"
},
  "geometry": {"coordinates":[9.9676103592,53.6635284424],"type":"Point"}
}