{
  "type": "Feature",
  "properties": {
    "iso:country":"DE",
    "sg:address":"Braunfelser Str. 25",
    "sg:city":"Wetzlar",
    "sg:phone":"+49 6441/24322",
    "sg:postcode":"35578",
    "sg:province":"Hessen",
    "wof:name":"G. Scharfe",
    "wof:placetype":"venue"
},
  "geometry": {"coordinates":[8.484366,50.550018],"type":"Point"}
}