{
  "type": "Feature",
  "properties": {
    "iso:country":"DE",
    "sg:address":"Friedhofstr. 31",
    "sg:city":"Bad Friedrichshall",
    "sg:phone":"+49 7136/8535",
    "sg:postcode":"74177",
    "sg:province":"Baden-W\u00fcrttemberg",
    "wof:name":"R. Dell",
    "wof:placetype":"venue"
},
  "geometry": {"coordinates":[9.189789772,49.2383613586],"type":"Point"}
}