{
  "type": "Feature",
  "properties": {
    "iso:country":"DE",
    "sg:address":"Krumbacher Str. 35",
    "sg:city":"Ottendorf",
    "sg:postcode":"09648",
    "sg:province":"Sachsen",
    "wof:name":"Ducke & Steges",
    "wof:placetype":"venue"
},
  "geometry": {"coordinates":[12.986243248,50.9995040894],"type":"Point"}
}