{
  "type": "Feature",
  "properties": {
    "iso:country":"DE",
    "sg:address":"Sandweg 1",
    "sg:city":"Heusweiler",
    "sg:phone":"+49 6806/81848",
    "sg:postcode":"66265",
    "sg:province":"Saarland",
    "wof:name":"E. Penth",
    "wof:placetype":"venue"
},
  "geometry": {"coordinates":[6.9817738533,49.3483581543],"type":"Point"}
}