{
  "type": "Feature",
  "properties": {
    "iso:country":"DE",
    "sg:address":"Ohlerweg 9",
    "sg:city":"M\u00f6nchengladbach",
    "sg:phone":"+49 2166/390341",
    "sg:postcode":"41239",
    "sg:province":"Nordrhein-Westfalen",
    "wof:name":"M. L. Buchinger",
    "wof:placetype":"venue"
},
  "geometry": {"coordinates":[6.432845,51.170181],"type":"Point"}
}