{
  "type": "Feature",
  "properties": {
    "iso:country":"DE",
    "sg:address":"Von-Miller-Str. 15",
    "sg:city":"Kaiserslautern",
    "sg:phone":"+49 631/99359",
    "sg:postcode":"67661",
    "sg:province":"Rheinland-Pfalz",
    "wof:name":"Ipt Ionen-und Plasmatechnik Gmbh",
    "wof:placetype":"venue"
},
  "geometry": {"coordinates":[7.6674890518,49.4392127991],"type":"Point"}
}