{
  "type": "Feature",
  "properties": {
    "iso:country":"DE",
    "sg:address":"Kirchgasse 6",
    "sg:city":"Nideggen",
    "sg:phone":"+49 2427/262",
    "sg:postcode":"52385",
    "sg:province":"Nordrhein-Westfalen",
    "wof:name":"Kath. Pfarramt St. Johannes Baptist",
    "wof:placetype":"venue"
},
  "geometry": {"coordinates":[6.4810857773,50.689289093],"type":"Point"}
}