{
  "type": "Feature",
  "properties": {
    "iso:country":"DE",
    "sg:address":"Am K\u00f6nigsfeld 8",
    "sg:city":"Brakel",
    "sg:phone":"+49 5272/9519",
    "sg:postcode":"33034",
    "sg:province":"Nordrhein-Westfalen",
    "wof:name":"Manfred Otto Gmbh & Co. Kg",
    "wof:placetype":"venue"
},
  "geometry": {"coordinates":[9.1825819016,51.7095108032],"type":"Point"}
}