{
  "type": "Feature",
  "properties": {
    "iso:country":"DE",
    "sg:address":"Starenweg 63",
    "sg:city":"Bargteheide",
    "sg:phone":"+49 4532/1330",
    "sg:postcode":"22941",
    "sg:province":"Schleswig-Holstein",
    "wof:name":"Lietz-radsport",
    "wof:placetype":"venue"
},
  "geometry": {"coordinates":[10.252469,53.728992],"type":"Point"}
}