{
  "type": "Feature",
  "properties": {
    "iso:country":"DE",
    "sg:address":"Schulstr. 4",
    "sg:city":"Wetzlar",
    "sg:phone":"+49 6441/46523",
    "sg:postcode":"35583",
    "sg:province":"Hessen",
    "wof:name":"K. Hupfeld",
    "wof:placetype":"venue"
},
  "geometry": {"coordinates":[8.528438,50.565525],"type":"Point"}
}