{
  "type": "Feature",
  "properties": {
    "iso:country":"DE",
    "sg:address":"Kufsteinerstr. 20",
    "sg:city":"Kiefersfelden",
    "sg:phone":"+49 8033/97680",
    "sg:postcode":"83088",
    "sg:province":"Bayern",
    "wof:name":"Dr. Menz Gmbh",
    "wof:placetype":"venue"
},
  "geometry": {"coordinates":[12.188654,47.613289],"type":"Point"}
}