{
  "type": "Feature",
  "properties": {
    "iso:country":"DE",
    "sg:address":"Hauptstr. 36",
    "sg:city":"Heuchelheim",
    "sg:postcode":"67259",
    "sg:province":"Rheinland-Pfalz",
    "wof:name":"Eco Naturforschungs- Und Technologie Gesellschaft Mbh",
    "wof:placetype":"venue"
},
  "geometry": {"coordinates":[8.0545749664,49.1463165283],"type":"Point"}
}