{
  "type": "Feature",
  "properties": {
    "iso:country":"DE",
    "sg:address":"In der Burg 7",
    "sg:city":"Felsberg",
    "sg:phone":"+49 5665/7602",
    "sg:postcode":"34587",
    "sg:province":"Hessen",
    "wof:name":"Ambulanter Krankenpflegedienst Hand In Hand",
    "wof:placetype":"venue"
},
  "geometry": {"coordinates":[9.444391,51.182076],"type":"Point"}
}