{
  "type": "Feature",
  "properties": {
    "iso:country":"DE",
    "sg:address":"Langenberger Str. 28",
    "sg:city":"Bochum",
    "sg:phone":"+49 234/493932",
    "sg:postcode":"44879",
    "sg:province":"Nordrhein-Westfalen",
    "wof:name":"Cohiba Connection",
    "wof:placetype":"venue"
},
  "geometry": {"coordinates":[7.1616091728,51.4166984558],"type":"Point"}
}