{
  "type": "Feature",
  "properties": {
    "iso:country":"DE",
    "sg:address":"Wehrmauer 1",
    "sg:city":"Altdorf",
    "sg:phone":"+49 9187/8720",
    "sg:postcode":"90518",
    "sg:province":"Bayern",
    "wof:name":"M. Deschauer",
    "wof:placetype":"venue"
},
  "geometry": {"coordinates":[11.353666,49.385349],"type":"Point"}
}