{
  "type": "Feature",
  "properties": {
    "iso:country":"DE",
    "sg:address":"Koppelstr. 29",
    "sg:city":"Pinneberg",
    "sg:phone":"+49 4101/22202",
    "sg:postcode":"25421",
    "sg:province":"Schleswig-Holstein",
    "wof:name":"Heinrich Ritscher",
    "wof:placetype":"venue"
},
  "geometry": {"coordinates":[9.789724,53.661011],"type":"Point"}
}