{
  "type": "Feature",
  "properties": {
    "iso:country":"DE",
    "sg:address":"Alemannenstr. 36",
    "sg:city":"Lindenberg",
    "sg:phone":"+49 8381/940700",
    "sg:postcode":"88161",
    "sg:province":"Bayern",
    "wof:name":"Atc Auto-technik-center Gmbh",
    "wof:placetype":"venue"
},
  "geometry": {"coordinates":[9.8972034454,47.6052818298],"type":"Point"}
}