{
  "type": "Feature",
  "properties": {
    "iso:country":"DE",
    "sg:address":"Zeppelinstr. 21",
    "sg:city":"Radolfzell",
    "sg:phone":"+49 7732/4629",
    "sg:postcode":"78315",
    "sg:province":"Baden-W\u00fcrttemberg",
    "wof:name":"China-restaurant Yien-yien Bodenseereiter",
    "wof:placetype":"venue"
},
  "geometry": {"coordinates":[8.9475660324,47.7370834351],"type":"Point"}
}