{
  "type": "Feature",
  "properties": {
    "iso:country":"DE",
    "sg:address":"Maximilianstr. 2",
    "sg:city":"Ansbach",
    "sg:postcode":"91522",
    "sg:province":"Bayern",
    "wof:name":"Knl Verm\u00f6gensverwaltung Gmbh",
    "wof:placetype":"venue"
},
  "geometry": {"coordinates":[10.5713100433,49.3009796143],"type":"Point"}
}