{
  "type": "Feature",
  "properties": {
    "iso:country":"DE",
    "sg:address":"B\u00fclt 10",
    "sg:city":"D\u00fclmen",
    "sg:phone":"+49 2594/948909",
    "sg:postcode":"48249",
    "sg:province":"Nordrhein-Westfalen",
    "wof:name":"Vanity-mode- Vertrieb Gmbh & Co.",
    "wof:placetype":"venue"
},
  "geometry": {"coordinates":[7.27846,51.82922],"type":"Point"}
}