{
  "type": "Feature",
  "properties": {
    "iso:country":"DE",
    "sg:address":"Dahlienweg 33",
    "sg:city":"Neuhausen",
    "sg:phone":"+49 7158/940330",
    "sg:postcode":"73765",
    "sg:province":"Baden-W\u00fcrttemberg",
    "wof:name":"Martina Ernst",
    "wof:placetype":"venue"
},
  "geometry": {"coordinates":[9.2749795914,48.6760063171],"type":"Point"}
}