{
  "type": "Feature",
  "properties": {
    "iso:country":"DE",
    "sg:address":"Coburger Allee 44",
    "sg:city":"Sonneberg",
    "sg:phone":"+49 3675/702392",
    "sg:postcode":"96515",
    "sg:province":"Th\u00fcringen",
    "wof:name":"Eberhard Friedel",
    "wof:placetype":"venue"
},
  "geometry": {"coordinates":[11.1668195724,50.3578071594],"type":"Point"}
}