{
  "type": "Feature",
  "properties": {
    "iso:country":"DE",
    "sg:address":"Niederstr. 9",
    "sg:city":"Monheim",
    "sg:phone":"+49 2173/58442",
    "sg:postcode":"40789",
    "sg:province":"Nordrhein-Westfalen",
    "wof:name":"H. Schneider",
    "wof:placetype":"venue"
},
  "geometry": {"coordinates":[6.8896660805,51.0992279053],"type":"Point"}
}