{
  "type": "Feature",
  "properties": {
    "iso:country":"DE",
    "sg:address":"Rudolf-Dyckerhoff-Str. 3",
    "sg:city":"Wiesbaden",
    "sg:phone":"+49 611/67054",
    "sg:postcode":"65203",
    "sg:province":"Hessen",
    "wof:name":"Biesel",
    "wof:placetype":"venue"
},
  "geometry": {"coordinates":[8.2422800064,50.0440597534],"type":"Point"}
}