{
  "type": "Feature",
  "properties": {
    "iso:country":"DE",
    "sg:address":"Platanenstr. 19",
    "sg:city":"Leipzig",
    "sg:phone":"+49 341/2324150",
    "sg:postcode":"04329",
    "sg:province":"Sachsen",
    "wof:name":"Fugentechnik Jatzke Gmbh",
    "wof:placetype":"venue"
},
  "geometry": {"coordinates":[12.462019,51.354588],"type":"Point"}
}