{
  "type": "Feature",
  "properties": {
    "iso:country":"DE",
    "sg:address":"Uhdestr. 7",
    "sg:city":"Dresden",
    "sg:phone":"+49 351/4706797",
    "sg:postcode":"01219",
    "sg:province":"Sachsen",
    "wof:name":"Wilhelm Baade",
    "wof:placetype":"venue"
},
  "geometry": {"coordinates":[13.7663221359,51.0186386108],"type":"Point"}
}