{
  "type": "Feature",
  "properties": {
    "iso:country":"DE",
    "sg:address":"Am Prinzenbuckel 28",
    "sg:city":"Haldenwang",
    "sg:phone":"+49 8304/92010",
    "sg:postcode":"87490",
    "sg:province":"Bayern",
    "wof:name":"Ingenieurb\u00fcro Ammann & B\u00e4umler Gmbh",
    "wof:placetype":"venue"
},
  "geometry": {"coordinates":[10.3624782562,47.7825279236],"type":"Point"}
}