{
  "type": "Feature",
  "properties": {
    "iso:country":"DE",
    "sg:address":"Hauptstr. 7",
    "sg:city":"Eschach",
    "sg:phone":"+49 7175/7325",
    "sg:postcode":"73569",
    "sg:province":"Baden-W\u00fcrttemberg",
    "wof:name":"Wolfgang Pessinger",
    "wof:placetype":"venue"
},
  "geometry": {"coordinates":[9.87355,48.887077],"type":"Point"}
}