{
  "type": "Feature",
  "properties": {
    "iso:country":"DE",
    "sg:address":"Grenzstr. 42",
    "sg:city":"Fichtenau",
    "sg:phone":"+49 7962/428",
    "sg:postcode":"74579",
    "sg:province":"Baden-W\u00fcrttemberg",
    "wof:name":"Tanzmetropole F. Meiser",
    "wof:placetype":"venue"
},
  "geometry": {"coordinates":[10.220055,49.09494],"type":"Point"}
}