{
  "type": "Feature",
  "properties": {
    "iso:country":"DE",
    "sg:address":"Wolfsburger Str. 2",
    "sg:city":"Weyhausen",
    "sg:phone":"+49 5362/7304",
    "sg:postcode":"38554",
    "sg:province":"Niedersachsen",
    "wof:name":"Peter Tietje",
    "wof:placetype":"venue"
},
  "geometry": {"coordinates":[10.7141990662,52.462059021],"type":"Point"}
}