{
  "type": "Feature",
  "properties": {
    "iso:country":"DE",
    "sg:address":"Hauptstr. 52",
    "sg:city":"Bassum",
    "sg:postcode":"27211",
    "sg:province":"Niedersachsen",
    "wof:name":"Maler Ehlers Gmbh",
    "wof:placetype":"venue"
},
  "geometry": {"coordinates":[8.816552,52.841324],"type":"Point"}
}