{
  "type": "Feature",
  "properties": {
    "iso:country":"DE",
    "sg:address":"Tegernseer Landstr. 77",
    "sg:city":"Sauerlach",
    "sg:phone":"+49 8104/1521",
    "sg:postcode":"82054",
    "sg:province":"Bayern",
    "wof:name":"Siegmund Waldhauser",
    "wof:placetype":"venue"
},
  "geometry": {"coordinates":[11.65466,47.963211],"type":"Point"}
}