{
  "type": "Feature",
  "properties": {
    "iso:country":"DE",
    "sg:address":"Meisenstr. 32",
    "sg:city":"Werl",
    "sg:phone":"+49 2922/6642",
    "sg:postcode":"59457",
    "sg:province":"Nordrhein-Westfalen",
    "wof:name":"S. & V. Altewulf Gmbh",
    "wof:placetype":"venue"
},
  "geometry": {"coordinates":[7.918253,51.561417],"type":"Point"}
}