{
  "type": "Feature",
  "properties": {
    "iso:country":"DE",
    "sg:address":"In Der Br\u00fcckenwiese 12",
    "sg:city":"K\u00f6nigswinter",
    "sg:phone":"+49 4922/4491830",
    "sg:postcode":"53639",
    "sg:province":"Nordrhein-Westfalen",
    "wof:name":"B & R Maschinenbau Gmbh",
    "wof:placetype":"venue"
},
  "geometry": {"coordinates":[7.278387,50.71743],"type":"Point"}
}