{
  "type": "Feature",
  "properties": {
    "iso:country":"DE",
    "sg:address":"Julius-H\u00f6lder-Str. 45",
    "sg:city":"Stuttgart",
    "sg:phone":"+49 711/9007530",
    "sg:postcode":"70597",
    "sg:province":"Baden-W\u00fcrttemberg",
    "wof:name":"Oskar Imberger & S\u00f6hne Gmbh",
    "wof:placetype":"venue"
},
  "geometry": {"coordinates":[9.167612,48.736702],"type":"Point"}
}