{
  "type": "Feature",
  "properties": {
    "iso:country":"DE",
    "sg:address":"Hebelstr. 7",
    "sg:city":"Schwaigern",
    "sg:phone":"+49 7138/932163",
    "sg:postcode":"74193",
    "sg:province":"Baden-W\u00fcrttemberg",
    "wof:name":"E. Pleiss Finanzberater",
    "wof:placetype":"venue"
},
  "geometry": {"coordinates":[9.0124607086,49.131942749],"type":"Point"}
}