{
  "type": "Feature",
  "properties": {
    "iso:country":"DE",
    "sg:address":"Puderstra\u00dfe 22",
    "sg:city":"Berlin",
    "sg:phone":"+49 30/53699147",
    "sg:postcode":"12435",
    "sg:province":"Berlin",
    "wof:name":"Hspeed.net - Internet Service F\u00fcr Unternehmen",
    "wof:placetype":"venue"
},
  "geometry": {"coordinates":[13.4647932053,52.4859428406],"type":"Point"}
}