{
  "type": "Feature",
  "properties": {
    "iso:country":"DE",
    "sg:address":"Egestorfer Str. 37",
    "sg:city":"Barsinghausen",
    "sg:phone":"+49 5105/2329",
    "sg:postcode":"30890",
    "sg:province":"Niedersachsen",
    "wof:name":"Erwin L\u00fcer\u00dfen",
    "wof:placetype":"venue"
},
  "geometry": {"coordinates":[9.475921,52.297974],"type":"Point"}
}