{
  "type": "Feature",
  "properties": {
    "iso:country":"DE",
    "sg:address":"Zeller Str. 1",
    "sg:city":"Bensheim",
    "sg:phone":"+49 6251/66770",
    "sg:postcode":"64625",
    "sg:province":"Hessen",
    "wof:name":"Ristorante Ii Pastaio",
    "wof:placetype":"venue"
},
  "geometry": {"coordinates":[8.6221389771,49.6782798767],"type":"Point"}
}