{
  "type": "Feature",
  "properties": {
    "iso:country":"DE",
    "sg:address":"Regierungsplatz 539",
    "sg:city":"Landshut",
    "sg:postcode":"84028",
    "sg:province":"Bayern",
    "wof:name":"Thermo Solar Ag",
    "wof:placetype":"venue"
},
  "geometry": {"coordinates":[12.1555509567,48.5369567871],"type":"Point"}
}