{
  "type": "Feature",
  "properties": {
    "iso:country":"DE",
    "sg:address":"Kirchweg 8",
    "sg:city":"L\u00fcbbow",
    "sg:postcode":"29488",
    "sg:province":"Niedersachsen",
    "wof:name":"Meier-fleisch Gmbh",
    "wof:placetype":"venue"
},
  "geometry": {"coordinates":[11.1827974319,52.9097251892],"type":"Point"}
}