{
  "type": "Feature",
  "properties": {
    "iso:country":"DE",
    "sg:address":"Sonneberger Str. 92",
    "sg:city":"Neuhaus",
    "sg:phone":"+49 3679/723165",
    "sg:postcode":"98724",
    "sg:province":"Th\u00fcringen",
    "wof:name":"P. Heinz",
    "wof:placetype":"venue"
},
  "geometry": {"coordinates":[11.1452569962,50.5045051575],"type":"Point"}
}