{
  "type": "Feature",
  "properties": {
    "iso:country":"DE",
    "sg:address":"Odenwaldstrasse 1",
    "sg:city":"Gross Umstadt",
    "sg:phone":"+49 6078/911494",
    "sg:postcode":"64823",
    "sg:province":"Hessen",
    "wof:name":"Aquastenger - The Waterblast Company",
    "wof:placetype":"venue"
},
  "geometry": {"coordinates":[8.9424476624,49.8222694397],"type":"Point"}
}