{
  "type": "Feature",
  "properties": {
    "iso:country":"DE",
    "sg:address":"Rudolst\u00e4dter Str. 78",
    "sg:city":"Oberwei\u00dfbach",
    "sg:phone":"+49 36705/62011",
    "sg:postcode":"98744",
    "sg:province":"Th\u00fcringen",
    "wof:name":"Dieter Ehle",
    "wof:placetype":"venue"
},
  "geometry": {"coordinates":[11.145449,50.584026],"type":"Point"}
}