{
  "type": "Feature",
  "properties": {
    "iso:country":"DE",
    "sg:address":"Potsdamer Chaussee 15a",
    "sg:city":"Berlin",
    "sg:phone":"+49 30/8027815",
    "sg:postcode":"14163",
    "sg:province":"Berlin",
    "wof:name":"Messalina Gmbh",
    "wof:placetype":"venue"
},
  "geometry": {"coordinates":[13.2309045792,52.4314193726],"type":"Point"}
}