{
  "type": "Feature",
  "properties": {
    "iso:country":"DE",
    "sg:address":"Neuri\u00dfweg 11",
    "sg:city":"M\u00fcnchen",
    "sg:phone":"+49 89/3113123",
    "sg:postcode":"80939",
    "sg:province":"Bayern",
    "wof:name":"Christian G\u00e4rtner Rechtsanwalt",
    "wof:placetype":"venue"
},
  "geometry": {"coordinates":[11.5968065262,48.2039413452],"type":"Point"}
}