{
  "type": "Feature",
  "properties": {
    "iso:country":"DE",
    "sg:address":"Sofienstr. 43",
    "sg:city":"Detmold",
    "sg:phone":"+49 5231/762111",
    "sg:postcode":"32756",
    "sg:province":"Nordrhein-Westfalen",
    "wof:name":"Diakonissenhaus Evangelische Tagespflege",
    "wof:placetype":"venue"
},
  "geometry": {"coordinates":[8.881629,51.941448],"type":"Point"}
}