{
  "type": "Feature",
  "properties": {
    "iso:country":"DE",
    "sg:address":"Charlottenplatz 6",
    "sg:city":"Stuttgart",
    "sg:phone":"+49 711/242501",
    "sg:postcode":"70173",
    "sg:province":"Baden-W\u00fcrttemberg",
    "wof:name":"Deutscher Ring Bausparkasse Ag",
    "wof:placetype":"venue"
},
  "geometry": {"coordinates":[9.183047,48.775417],"type":"Point"}
}