{
  "type": "Feature",
  "properties": {
    "iso:country":"DE",
    "sg:address":"Forstenrieder Weg 13",
    "sg:city":"Baierbrunn",
    "sg:phone":"+49 89/7931649",
    "sg:postcode":"82065",
    "sg:province":"Bayern",
    "wof:name":"Katholisches Pfarramt St. Peter Und Paul",
    "wof:placetype":"venue"
},
  "geometry": {"coordinates":[11.485953331,48.0239257812],"type":"Point"}
}