{
  "type": "Feature",
  "properties": {
    "iso:country":"DE",
    "sg:address":"Neustadt 4",
    "sg:city":"Zittau",
    "sg:postcode":"02763",
    "sg:province":"Sachsen",
    "wof:name":"American Houses",
    "wof:placetype":"venue"
},
  "geometry": {"coordinates":[14.8109102249,50.8953399658],"type":"Point"}
}