{
  "type": "Feature",
  "properties": {
    "iso:country":"DE",
    "sg:address":"Schaftlachstr. 1",
    "sg:city":"M\u00fcnchen",
    "sg:phone":"+49 89/7234133",
    "sg:postcode":"81371",
    "sg:province":"Bayern",
    "wof:name":"E. Zindikus",
    "wof:placetype":"venue"
},
  "geometry": {"coordinates":[11.5492162704,48.110660553],"type":"Point"}
}