{
  "type": "Feature",
  "properties": {
    "iso:country":"DE",
    "sg:address":"Dortmunder Str. 241",
    "sg:city":"Hamm",
    "sg:phone":"+49 2381",
    "sg:postcode":"59067",
    "sg:province":"Nordrhein-Westfalen",
    "wof:name":"Bikers Corner",
    "wof:placetype":"venue"
},
  "geometry": {"coordinates":[7.7606401443,51.6629486084],"type":"Point"}
}