{
  "type": "Feature",
  "properties": {
    "iso:country":"DE",
    "sg:address":"Petersenstr. 15",
    "sg:city":"Darmstadt",
    "sg:phone":"+49 6151/126565",
    "sg:postcode":"64287",
    "sg:province":"Hessen",
    "wof:name":"Fachgebiet Hochbau- Konstruktion I Und Entwerfen",
    "wof:placetype":"venue"
},
  "geometry": {"coordinates":[8.677904129,49.8607139587],"type":"Point"}
}