{
  "type": "Feature",
  "properties": {
    "iso:country":"DE",
    "sg:address":"Schwennestr. 2",
    "sg:city":"Lingen",
    "sg:phone":"+49 591/4221",
    "sg:postcode":"49808",
    "sg:province":"Niedersachsen",
    "wof:name":"August Klukkert Kg",
    "wof:placetype":"venue"
},
  "geometry": {"coordinates":[7.315075,52.518703],"type":"Point"}
}