{
  "type": "Feature",
  "properties": {
    "iso:country":"DE",
    "sg:address":"Ahrenhorst 16",
    "sg:city":"Sendenhorst",
    "sg:postcode":"48324",
    "sg:province":"Nordrhein-Westfalen",
    "wof:name":"Wk Soziale Dienstleistungen Und Service Verwaltungs-gmbh",
    "wof:placetype":"venue"
},
  "geometry": {"coordinates":[7.7388339043,51.8518295288],"type":"Point"}
}