{
  "type": "Feature",
  "properties": {
    "iso:country":"DE",
    "sg:address":"Kaiserdamm 25",
    "sg:city":"Berlin",
    "sg:phone":"+49 30/3021316",
    "sg:postcode":"14057",
    "sg:province":"Berlin",
    "wof:name":"Rosemarie Pekuygun",
    "wof:placetype":"venue"
},
  "geometry": {"coordinates":[13.2822408676,52.5102462769],"type":"Point"}
}