{
  "type": "Feature",
  "properties": {
    "iso:country":"DE",
    "sg:address":"Bahnhofstrasse 6",
    "sg:city":"Lich",
    "sg:phone":"+49 6404/660208",
    "sg:postcode":"35423",
    "sg:province":"Hessen",
    "wof:name":"L\u00f6wchen Von Dem Oderparadies",
    "wof:placetype":"venue"
},
  "geometry": {"coordinates":[8.8207044601,50.5155563354],"type":"Point"}
}