{
  "type": "Feature",
  "properties": {
    "iso:country":"DE",
    "sg:address":"Am Irscher Hof 39",
    "sg:city":"Trier",
    "sg:phone":"+49 651/32777",
    "sg:postcode":"54294",
    "sg:province":"Rheinland-Pfalz",
    "wof:name":"Paul Blau",
    "wof:placetype":"venue"
},
  "geometry": {"coordinates":[6.639702,49.727718],"type":"Point"}
}