{
  "type": "Feature",
  "properties": {
    "iso:country":"DE",
    "sg:address":"Belgradstr 68",
    "sg:city":"M\u00fcnchen",
    "sg:phone":"+49 89/3000880",
    "sg:postcode":"80804",
    "sg:province":"Bayern",
    "wof:name":"Prodomus Vertriebs-gmbh",
    "wof:placetype":"venue"
},
  "geometry": {"coordinates":[11.574174,48.167778],"type":"Point"}
}