{
  "type": "Feature",
  "properties": {
    "iso:country":"DE",
    "sg:address":"Heie 10",
    "sg:city":"Emsb\u00fcren",
    "sg:phone":"+49 5903/7221",
    "sg:postcode":"48488",
    "sg:province":"Niedersachsen",
    "wof:name":"H. Wilming",
    "wof:placetype":"venue"
},
  "geometry": {"coordinates":[7.297331,52.388454],"type":"Point"}
}