{
  "type": "Feature",
  "properties": {
    "iso:country":"DE",
    "sg:address":"Ekkehardstr. 18",
    "sg:city":"Singen",
    "sg:postcode":"78224",
    "sg:province":"Baden-W\u00fcrttemberg",
    "wof:name":"Artur Sauter Beteiligungs Gmbh",
    "wof:placetype":"venue"
},
  "geometry": {"coordinates":[8.8388824463,47.7618331909],"type":"Point"}
}