{
  "type": "Feature",
  "properties": {
    "iso:country":"DE",
    "sg:address":"Kanalstr. 51",
    "sg:city":"Kaiserslautern",
    "sg:phone":"+49 631/61345",
    "sg:postcode":"67655",
    "sg:province":"Rheinland-Pfalz",
    "wof:name":"Burkhard Evers Garten- Und",
    "wof:placetype":"venue"
},
  "geometry": {"coordinates":[7.779228,49.444832],"type":"Point"}
}