{
  "type": "Feature",
  "properties": {
    "iso:country":"DE",
    "sg:address":"Schulstr. 22",
    "sg:city":"Dresden",
    "sg:phone":"+49 351/2691047",
    "sg:postcode":"01328",
    "sg:province":"Sachsen",
    "wof:name":"Dr. Gunter H\u00e4se Tierarzt",
    "wof:placetype":"venue"
},
  "geometry": {"coordinates":[13.8505811691,51.0348510742],"type":"Point"}
}