{
  "type": "Feature",
  "properties": {
    "iso:country":"DE",
    "sg:address":"Haydnstr. 5a",
    "sg:city":"Weiterstadt",
    "sg:phone":"+49 6150/40221",
    "sg:postcode":"64331",
    "sg:province":"Hessen",
    "wof:name":"Funkclub Frank Sutter",
    "wof:placetype":"venue"
},
  "geometry": {"coordinates":[8.5792303085,49.9030265808],"type":"Point"}
}