{
  "type": "Feature",
  "properties": {
    "iso:country":"DE",
    "sg:address":"Am Sailersberg 1",
    "sg:city":"R\u00f6thenbach",
    "sg:phone":"+49 911/577377",
    "sg:postcode":"90552",
    "sg:province":"Bayern",
    "wof:name":"Pension Sonja",
    "wof:placetype":"venue"
},
  "geometry": {"coordinates":[11.2465181351,49.4883155823],"type":"Point"}
}