{
  "type": "Feature",
  "properties": {
    "iso:country":"DE",
    "sg:address":"Hermann-Essig-Str. 35",
    "sg:city":"Schwieberdingen",
    "sg:phone":"+49 7150/33271",
    "sg:postcode":"71701",
    "sg:province":"Baden-W\u00fcrttemberg",
    "wof:name":"Georg Vogel",
    "wof:placetype":"venue"
},
  "geometry": {"coordinates":[9.0760583878,48.8740997314],"type":"Point"}
}