{
  "type": "Feature",
  "properties": {
    "iso:country":"DE",
    "sg:address":"Ringstr. 17",
    "sg:city":"Nideggen",
    "sg:phone":"+49 2425/234",
    "sg:postcode":"52385",
    "sg:province":"Nordrhein-Westfalen",
    "wof:name":"Peter Becker",
    "wof:placetype":"venue"
},
  "geometry": {"coordinates":[6.571966,50.684925],"type":"Point"}
}