{
  "type": "Feature",
  "properties": {
    "iso:country":"DE",
    "sg:address":"Rheingoldstr. 40",
    "sg:city":"Manubach",
    "sg:phone":"+49 6743/2459",
    "sg:postcode":"55413",
    "sg:province":"Rheinland-Pfalz",
    "wof:name":"Helmut Seckler Weinanbau",
    "wof:placetype":"venue"
},
  "geometry": {"coordinates":[7.7634739876,50.0320892334],"type":"Point"}
}