{
  "type": "Feature",
  "properties": {
    "iso:country":"DE",
    "sg:address":"Warder Hof 11",
    "sg:city":"Bergisch Gladbach",
    "sg:phone":"+49 2202/932114",
    "sg:postcode":"51469",
    "sg:province":"Nordrhein-Westfalen",
    "wof:name":"Business To Business Media Gmbh",
    "wof:placetype":"venue"
},
  "geometry": {"coordinates":[7.137375,50.976887],"type":"Point"}
}