{
  "type": "Feature",
  "properties": {
    "iso:country":"DE",
    "sg:address":"Asternweg 7",
    "sg:city":"G\u00f6rlitz",
    "sg:phone":"+49 3581/78691",
    "sg:postcode":"02827",
    "sg:province":"Sachsen",
    "wof:name":"Sieghard M\u00fcller",
    "wof:placetype":"venue"
},
  "geometry": {"coordinates":[14.940288,51.13903],"type":"Point"}
}