{
  "type": "Feature",
  "properties": {
    "iso:country":"DE",
    "sg:address":"Im Wiesental 8",
    "sg:city":"F\u00fcrth",
    "sg:phone":"+49 6253/932493",
    "sg:postcode":"64658",
    "sg:province":"Hessen",
    "wof:name":"Wiesental Wohn- Und Pflegeheim F\u00fcr Psychisch Kranke Gmbh",
    "wof:placetype":"venue"
},
  "geometry": {"coordinates":[8.8008394241,49.6604537964],"type":"Point"}
}