{
  "type": "Feature",
  "properties": {
    "iso:country":"DE",
    "sg:address":"Oppenweher Str. 11",
    "sg:city":"Stemwede",
    "sg:phone":"+49 5773/8144",
    "sg:postcode":"32351",
    "sg:province":"Nordrhein-Westfalen",
    "wof:name":"Gastst\u00e4tte E. Rehburg",
    "wof:placetype":"venue"
},
  "geometry": {"coordinates":[8.504251,52.464558],"type":"Point"}
}