{
  "type": "Feature",
  "properties": {
    "iso:country":"DE",
    "sg:address":"Mainstr. 34",
    "sg:city":"Wiesbaden",
    "sg:phone":"+49 611/62217",
    "sg:postcode":"65203",
    "sg:province":"Hessen",
    "wof:name":"Seipel Feuerschutz Gmbh",
    "wof:placetype":"venue"
},
  "geometry": {"coordinates":[8.2407817841,50.0381889343],"type":"Point"}
}