{
  "type": "Feature",
  "properties": {
    "iso:country":"DE",
    "sg:address":"Arndtstr. 4",
    "sg:city":"Neunkirchen-Seelscheid",
    "sg:phone":"+49 2247/6838",
    "sg:postcode":"53819",
    "sg:province":"Nordrhein-Westfalen",
    "wof:name":"W. Strasskewitz",
    "wof:placetype":"venue"
},
  "geometry": {"coordinates":[7.3223118782,50.8730659485],"type":"Point"}
}