{
  "type": "Feature",
  "properties": {
    "iso:country":"DE",
    "sg:address":"Langenb\u00fcgeler Str. 73",
    "sg:city":"Heiligenhaus",
    "sg:phone":"+49 2056/6723",
    "sg:postcode":"42579",
    "sg:province":"Nordrhein-Westfalen",
    "wof:name":"Helmut Bernsau",
    "wof:placetype":"venue"
},
  "geometry": {"coordinates":[6.964741,51.343136],"type":"Point"}
}