{
  "type": "Feature",
  "properties": {
    "iso:country":"DE",
    "sg:address":"Linzer Str. 9",
    "sg:city":"Bremen",
    "sg:phone":"+49 421/202560",
    "sg:postcode":"28359",
    "sg:province":"Bremen",
    "wof:name":"Siemens Nixdorf Informationssysteme Ag",
    "wof:placetype":"venue"
},
  "geometry": {"coordinates":[8.862938,53.108719],"type":"Point"}
}