{
  "type": "Feature",
  "properties": {
    "iso:country":"DE",
    "sg:address":"R\u00fcdersdorfer Str. 95",
    "sg:city":"Vogelsdorf",
    "sg:postcode":"15370",
    "sg:province":"Brandenburg",
    "wof:name":"Safe Beteiligungsges. Mbh",
    "wof:placetype":"venue"
},
  "geometry": {"coordinates":[13.766081,52.504967],"type":"Point"}
}