{
  "type": "Feature",
  "properties": {
    "iso:country":"DE",
    "sg:address":"Oelstr. 20",
    "sg:city":"Emmerich",
    "sg:phone":"+49 2822/76120",
    "sg:postcode":"46446",
    "sg:province":"Nordrhein-Westfalen",
    "wof:name":"S-provinzial Gmbh",
    "wof:placetype":"venue"
},
  "geometry": {"coordinates":[6.2424798012,51.8321533203],"type":"Point"}
}