{
  "type": "Feature",
  "properties": {
    "iso:country":"DE",
    "sg:address":"Feldstr. 9c",
    "sg:city":"Gr\u00e4felfing",
    "sg:phone":"+49 89/852658",
    "sg:postcode":"82166",
    "sg:province":"Bayern",
    "wof:name":"Gerhard Schmidt",
    "wof:placetype":"venue"
},
  "geometry": {"coordinates":[11.4396276474,48.1231613159],"type":"Point"}
}