{
  "type": "Feature",
  "properties": {
    "iso:country":"DE",
    "sg:address":"Hammer Str. 67",
    "sg:city":"M\u00fcnster",
    "sg:phone":"+49 251/792220",
    "sg:postcode":"48153",
    "sg:province":"Nordrhein-Westfalen",
    "wof:name":"Buddelei-mode Gmbh & Co. Kg",
    "wof:placetype":"venue"
},
  "geometry": {"coordinates":[7.624671,51.949409],"type":"Point"}
}