{
  "type": "Feature",
  "properties": {
    "iso:country":"DE",
    "sg:address":"Lindenweg 10 a",
    "sg:city":"Obergriesbach",
    "sg:phone":"+49 8251/826804",
    "sg:postcode":"86573",
    "sg:province":"Bayern",
    "wof:name":"Reuther-systems E. K.",
    "wof:placetype":"venue"
},
  "geometry": {"coordinates":[11.0669622421,48.4248657227],"type":"Point"}
}