{
  "type": "Feature",
  "properties": {
    "iso:country":"DE",
    "sg:address":"Lohtorstr. 29",
    "sg:city":"Heilbronn",
    "sg:phone":"+49 7131/68123",
    "sg:postcode":"74072",
    "sg:province":"Baden-W\u00fcrttemberg",
    "wof:name":"Fritz Langenfelder",
    "wof:placetype":"venue"
},
  "geometry": {"coordinates":[9.2193899155,49.1432647705],"type":"Point"}
}