{
  "type": "Feature",
  "properties": {
    "iso:country":"DE",
    "sg:address":"Wei\u00dfgasse 5",
    "sg:city":"Kalchreuth",
    "sg:phone":"+49 911/5180953",
    "sg:postcode":"90562",
    "sg:province":"Bayern",
    "wof:name":"Kurt Dennerlein",
    "wof:placetype":"venue"
},
  "geometry": {"coordinates":[11.133181,49.558842],"type":"Point"}
}