{
  "type": "Feature",
  "properties": {
    "iso:country":"DE",
    "sg:address":"Herzog-Georg-Str. 4",
    "sg:city":"Bad Liebenstein",
    "sg:phone":"+49 36961/72507",
    "sg:postcode":"36448",
    "sg:province":"Th\u00fcringen",
    "wof:name":"H. J. Michael",
    "wof:placetype":"venue"
},
  "geometry": {"coordinates":[10.3487329483,50.8157691956],"type":"Point"}
}