{
  "type": "Feature",
  "properties": {
    "iso:country":"DE",
    "sg:address":"Elbstr. 4",
    "sg:city":"Aken",
    "sg:phone":"+49 34909/82473",
    "sg:postcode":"06385",
    "sg:province":"Sachsen-Anhalt",
    "wof:name":"Gustav Sch\u00fctz",
    "wof:placetype":"venue"
},
  "geometry": {"coordinates":[12.045025,51.856247],"type":"Point"}
}