{
  "type": "Feature",
  "properties": {
    "iso:country":"DE",
    "sg:address":"Tullastr. 61",
    "sg:city":"Freiburg",
    "sg:phone":"+49 761/2791",
    "sg:postcode":"79108",
    "sg:province":"Baden-W\u00fcrttemberg",
    "wof:name":"Freiburger W\u00e4rmever- Sorgungs Gmbh",
    "wof:placetype":"venue"
},
  "geometry": {"coordinates":[7.845297,48.028542],"type":"Point"}
}