{
  "type": "Feature",
  "properties": {
    "iso:country":"DE",
    "sg:address":"Marktstr. 18",
    "sg:city":"Harsefeld",
    "sg:phone":"+49 4164/5288",
    "sg:postcode":"21698",
    "sg:province":"Niedersachsen",
    "wof:name":"China Restaurant",
    "wof:placetype":"venue"
},
  "geometry": {"coordinates":[9.5036678314,53.4531784058],"type":"Point"}
}