{
  "type": "Feature",
  "properties": {
    "iso:country":"DE",
    "sg:address":"Friedrichstr. 17",
    "sg:city":"Iserlohn",
    "sg:phone":"+49 2371/12682",
    "sg:postcode":"58636",
    "sg:province":"Nordrhein-Westfalen",
    "wof:name":"Ristorante Bella Italia",
    "wof:placetype":"venue"
},
  "geometry": {"coordinates":[7.7046852112,51.3732872009],"type":"Point"}
}