{
  "type": "Feature",
  "properties": {
    "iso:country":"DE",
    "sg:address":"Tembrinkstr. 8",
    "sg:city":"Ahaus",
    "sg:phone":"+49 2561/2430",
    "sg:postcode":"48683",
    "sg:province":"Nordrhein-Westfalen",
    "wof:name":"A. G\u00f6tz",
    "wof:placetype":"venue"
},
  "geometry": {"coordinates":[7.0089468956,52.0800552368],"type":"Point"}
}