{
  "type": "Feature",
  "properties": {
    "iso:country":"DE",
    "sg:address":"Wilhelm-Danner-Str. 13b",
    "sg:city":"Rheinstetten",
    "sg:phone":"+49 721/510309",
    "sg:postcode":"76287",
    "sg:province":"Baden-W\u00fcrttemberg",
    "wof:name":"Walter Nakovics",
    "wof:placetype":"venue"
},
  "geometry": {"coordinates":[8.3058013916,48.972114563],"type":"Point"}
}