{
  "type": "Feature",
  "properties": {
    "iso:country":"DE",
    "sg:address":"Gr\u00fcner Baum 8",
    "sg:city":"Neustrelitz",
    "sg:phone":"+49 3981",
    "sg:postcode":"17235",
    "sg:province":"Mecklenburg-Vorpommern",
    "wof:name":"Friesen Und Ponyhof Zachmann | Neustrelitz",
    "wof:placetype":"venue"
},
  "geometry": {"coordinates":[13.11983,53.332474],"type":"Point"}
}