{
  "type": "Feature",
  "properties": {
    "iso:country":"DE",
    "sg:address":"Vorhaller Str. 44",
    "sg:city":"Hagen",
    "sg:phone":"+49 2331/303875",
    "sg:postcode":"58089",
    "sg:province":"Nordrhein-Westfalen",
    "wof:name":"Hartmut Stellmacher Masseur",
    "wof:placetype":"venue"
},
  "geometry": {"coordinates":[7.426589,51.382706],"type":"Point"}
}