{
  "type": "Feature",
  "properties": {
    "iso:country":"DE",
    "sg:address":"Burgdorfer Str. 32",
    "sg:city":"Burgdorf",
    "sg:phone":"+49 5136/7580",
    "sg:postcode":"31303",
    "sg:province":"Niedersachsen",
    "wof:name":"H. Braake",
    "wof:placetype":"venue"
},
  "geometry": {"coordinates":[10.0089912415,52.4843063354],"type":"Point"}
}