{
  "type": "Feature",
  "properties": {
    "iso:country":"DE",
    "sg:address":"Bansiner Weg 4",
    "sg:city":"T\u00f6nning",
    "sg:phone":"+49 4861/6555",
    "sg:postcode":"25832",
    "sg:province":"Schleswig-Holstein",
    "wof:name":"Margarete Gebauer",
    "wof:placetype":"venue"
},
  "geometry": {"coordinates":[8.9332790375,54.3134231567],"type":"Point"}
}