{
  "type": "Feature",
  "properties": {
    "iso:country":"DE",
    "sg:address":"Hauptstr. 40",
    "sg:city":"H\u00f6chst\u00e4dt",
    "sg:phone":"+49 9235/236",
    "sg:postcode":"95186",
    "sg:province":"Bayern",
    "wof:name":"Ev. Luth. Pfarramt",
    "wof:placetype":"venue"
},
  "geometry": {"coordinates":[12.0856962204,50.100063324],"type":"Point"}
}