{
  "type": "Feature",
  "properties": {
    "iso:country":"DE",
    "sg:address":"Ammerseestr. 30",
    "sg:city":"Mannheim",
    "sg:phone":"+49 621/8022980",
    "sg:postcode":"68219",
    "sg:province":"Baden-W\u00fcrttemberg",
    "wof:name":"Pmt Pharma Machinery Und Technique Gmbh",
    "wof:placetype":"venue"
},
  "geometry": {"coordinates":[8.532776,49.414852],"type":"Point"}
}