{
  "type": "Feature",
  "properties": {
    "iso:country":"DE",
    "sg:address":"Bergstr. 4",
    "sg:city":"Gau-Bischofsheim",
    "sg:phone":"+49 6135/3137",
    "sg:postcode":"55296",
    "sg:province":"Rheinland-Pfalz",
    "wof:name":"Galerie Jottwedee Im Geiserhof",
    "wof:placetype":"venue"
},
  "geometry": {"coordinates":[8.274119,49.915127],"type":"Point"}
}