{
  "type": "Feature",
  "properties": {
    "iso:country":"DE",
    "sg:address":"Dr.-Max-Ilgner-Str. 1",
    "sg:city":"Espelkamp",
    "sg:phone":"+49 5772/5050",
    "sg:postcode":"32339",
    "sg:province":"Nordrhein-Westfalen",
    "wof:name":"Jelen Gmbh",
    "wof:placetype":"venue"
},
  "geometry": {"coordinates":[8.620758,52.385509],"type":"Point"}
}