{
  "type": "Feature",
  "properties": {
    "iso:country":"DE",
    "sg:address":"Oberstr 112",
    "sg:city":"K\u00f6ln",
    "sg:phone":"+49 2203/13000",
    "sg:postcode":"51149",
    "sg:province":"Nordrhein-Westfalen",
    "wof:name":"Sauer Hygienica Dienstleistungen Gmbh",
    "wof:placetype":"venue"
},
  "geometry": {"coordinates":[7.0185351372,50.9011726379],"type":"Point"}
}