{
  "type": "Feature",
  "properties": {
    "iso:country":"DE",
    "sg:address":"Kappelgasse 10",
    "sg:city":"Schw\u00e4bisch Gm\u00fcnd",
    "sg:phone":"+49 7171/67675",
    "sg:postcode":"73525",
    "sg:province":"Baden-W\u00fcrttemberg",
    "wof:name":"J\u00f6rg Grimminger Gmbh",
    "wof:placetype":"venue"
},
  "geometry": {"coordinates":[9.7981090546,48.8018379211],"type":"Point"}
}