{
  "type": "Feature",
  "properties": {
    "iso:country":"DE",
    "sg:address":"Amselstr. 3",
    "sg:city":"B\u00fchl",
    "sg:phone":"+49 7223/4418",
    "sg:postcode":"77815",
    "sg:province":"Baden-W\u00fcrttemberg",
    "wof:name":"Reiseb\u00fcro Fischer",
    "wof:placetype":"venue"
},
  "geometry": {"coordinates":[8.1238040924,48.6901741028],"type":"Point"}
}