{
  "type": "Feature",
  "properties": {
    "iso:country":"DE",
    "sg:address":"Mittelgasse 10",
    "sg:city":"Alsheim",
    "sg:phone":"+49 6249/4826",
    "sg:postcode":"67577",
    "sg:province":"Rheinland-Pfalz",
    "wof:name":"J\u00fcrgen Wedel",
    "wof:placetype":"venue"
},
  "geometry": {"coordinates":[8.3390750885,49.7655906677],"type":"Point"}
}