{
  "type": "Feature",
  "properties": {
    "iso:country":"DE",
    "sg:address":"Arberger Heerstr. 80",
    "sg:city":"Bremen",
    "sg:phone":"+49 421/438280",
    "sg:postcode":"28307",
    "sg:province":"Bremen",
    "wof:name":"Bk Werkstofft.-pr\u00fcfstelle Gmbh",
    "wof:placetype":"venue"
},
  "geometry": {"coordinates":[8.9204216003,53.0377349854],"type":"Point"}
}