{
  "type": "Feature",
  "properties": {
    "iso:country":"DE",
    "sg:address":"Bergstr. 8",
    "sg:city":"Pastetten",
    "sg:phone":"+49 8124/1682",
    "sg:postcode":"85669",
    "sg:province":"Bayern",
    "wof:name":"Norbert Traublinger",
    "wof:placetype":"venue"
},
  "geometry": {"coordinates":[11.9395284653,48.1972694397],"type":"Point"}
}