{
  "type": "Feature",
  "properties": {
    "iso:country":"DE",
    "sg:address":"Burgstr. 8",
    "sg:city":"Tirschenreuth",
    "sg:phone":"+49 9631/4899",
    "sg:postcode":"95643",
    "sg:province":"Bayern",
    "wof:name":"R. Werner",
    "wof:placetype":"venue"
},
  "geometry": {"coordinates":[12.3364343643,49.8765106201],"type":"Point"}
}