{
  "type": "Feature",
  "properties": {
    "iso:country":"DE",
    "sg:address":"Dorfstr. 29",
    "sg:city":"Blowatz",
    "sg:postcode":"23974",
    "sg:province":"Mecklenburg-Vorpommern",
    "wof:name":"Inge Beyer",
    "wof:placetype":"venue"
},
  "geometry": {"coordinates":[11.544175148,53.9622383118],"type":"Point"}
}