{
  "type": "Feature",
  "properties": {
    "iso:country":"DE",
    "sg:address":"Kreyenstr. 155",
    "sg:city":"Rastede",
    "sg:phone":"+49 4402/970253",
    "sg:postcode":"26180",
    "sg:province":"Niedersachsen",
    "wof:name":"Kernbohr Service Gmbh",
    "wof:placetype":"venue"
},
  "geometry": {"coordinates":[8.1238603592,53.2865104675],"type":"Point"}
}