{
  "type": "Feature",
  "properties": {
    "iso:country":"DE",
    "sg:address":"Schanzweg 15",
    "sg:city":"Eisfeld",
    "sg:phone":"+49 3686/309367",
    "sg:postcode":"98673",
    "sg:province":"Th\u00fcringen",
    "wof:name":"Heiko Jahn",
    "wof:placetype":"venue"
},
  "geometry": {"coordinates":[10.9139890671,50.4309921265],"type":"Point"}
}