{
  "type": "Feature",
  "properties": {
    "iso:country":"DE",
    "sg:address":"Am Bach 38",
    "sg:city":"Oberlungwitz",
    "sg:phone":"+49 4937/3628554",
    "sg:postcode":"09353",
    "sg:province":"Sachsen",
    "wof:name":"Helfried Stephani",
    "wof:placetype":"venue"
},
  "geometry": {"coordinates":[13.4704818726,50.6442871094],"type":"Point"}
}