{
  "type": "Feature",
  "properties": {
    "iso:country":"DE",
    "sg:address":"Comeniusstr. 13",
    "sg:city":"Leipzig",
    "sg:postcode":"04315",
    "sg:province":"Sachsen",
    "wof:name":"Bausanierung Leipzig Gmbh",
    "wof:placetype":"venue"
},
  "geometry": {"coordinates":[12.401638,51.341743],"type":"Point"}
}