{
  "type": "Feature",
  "properties": {
    "iso:country":"DE",
    "sg:address":"Kisseler Str. 68",
    "sg:city":"Schweina",
    "sg:phone":"+49 36961/72873",
    "sg:postcode":"36448",
    "sg:province":"Th\u00fcringen",
    "wof:name":"Sportlerklause",
    "wof:placetype":"venue"
},
  "geometry": {"coordinates":[10.3426771164,50.8334960938],"type":"Point"}
}