{
  "type": "Feature",
  "properties": {
    "iso:country":"DE",
    "sg:address":"Emsteker Str. 137",
    "sg:city":"Cloppenburg",
    "sg:phone":"+49 4471/82999",
    "sg:postcode":"49661",
    "sg:province":"Niedersachsen",
    "wof:name":"Cevau Drinks Clemens Vormoor Gmbh",
    "wof:placetype":"venue"
},
  "geometry": {"coordinates":[8.0981225967,52.8346786499],"type":"Point"}
}