{
  "type": "Feature",
  "properties": {
    "iso:country":"DE",
    "sg:address":"Grosser Hasenpfad 44",
    "sg:city":"Frankfurt",
    "sg:phone":"+49 69/60507219",
    "sg:postcode":"60598",
    "sg:province":"Hessen",
    "wof:name":"Opel Automobile",
    "wof:placetype":"venue"
},
  "geometry": {"coordinates":[8.6862306595,50.0959205627],"type":"Point"}
}