{
  "type": "Feature",
  "properties": {
    "iso:country":"DE",
    "sg:address":"Bahnhof Adelsheim Nord",
    "sg:city":"Seckach",
    "sg:phone":"+49 6291/1450",
    "sg:postcode":"74743",
    "sg:province":"Baden-W\u00fcrttemberg",
    "wof:name":"Gr\u00fcner Baum",
    "wof:placetype":"venue"
},
  "geometry": {"coordinates":[9.3336858749,49.4423828125],"type":"Point"}
}