{
  "type": "Feature",
  "properties": {
    "iso:country":"DE",
    "sg:address":"Erich-Zeigner-Str. 53",
    "sg:city":"Geringswalde",
    "sg:phone":"+49 37382/81704",
    "sg:postcode":"09326",
    "sg:province":"Sachsen",
    "wof:name":"Alfred Winkler",
    "wof:placetype":"venue"
},
  "geometry": {"coordinates":[12.913964,51.075436],"type":"Point"}
}