{
  "type": "Feature",
  "properties": {
    "iso:country":"DE",
    "sg:address":"Ordensmeisterstr. 4",
    "sg:city":"Berlin",
    "sg:phone":"+49 30/7510644",
    "sg:postcode":"12099",
    "sg:province":"Berlin",
    "wof:name":"Marina Rosengarten",
    "wof:placetype":"venue"
},
  "geometry": {"coordinates":[13.3889255524,52.4567489624],"type":"Point"}
}