{
  "type": "Feature",
  "properties": {
    "iso:country":"DE",
    "sg:address":"Postfach 11 04",
    "sg:city":"Gau-Odernheim",
    "sg:phone":"+49 6733/960102",
    "sg:postcode":"55238",
    "sg:province":"Rheinland-Pfalz",
    "wof:name":"A&s Produktion, Firmengruppe",
    "wof:placetype":"venue"
},
  "geometry": {"coordinates":[8.1944103241,49.7832336426],"type":"Point"}
}