{
  "type": "Feature",
  "properties": {
    "iso:country":"DE",
    "sg:address":"Bahnhofstr. 7b",
    "sg:city":"Klostermansfeld",
    "sg:phone":"+49 34772/83873",
    "sg:postcode":"06308",
    "sg:province":"Sachsen-Anhalt",
    "wof:name":"H. Niederges\u00e4\u00df Immobilien E.k.",
    "wof:placetype":"venue"
},
  "geometry": {"coordinates":[11.4940700531,51.5817832947],"type":"Point"}
}