{
  "type": "Feature",
  "properties": {
    "iso:country":"DE",
    "sg:address":"Auf dem G\u00e4nsemarkt 11",
    "sg:city":"Selm",
    "sg:postcode":"59379",
    "sg:province":"Nordrhein-Westfalen",
    "wof:name":"L\u00fcner Grundst\u00fccks- Und Immobiliengesellschaft Mbh",
    "wof:placetype":"venue"
},
  "geometry": {"coordinates":[7.527203,51.659603],"type":"Point"}
}