{
  "type": "Feature",
  "properties": {
    "iso:country":"DE",
    "sg:address":"Talstra\u00dfe 45",
    "sg:city":"Glottertal",
    "sg:postcode":"79286",
    "sg:province":"Baden-W\u00fcrttemberg",
    "wof:name":"Gemeindeverwaltung Glottertal Im Schwarzwald",
    "wof:placetype":"venue"
},
  "geometry": {"coordinates":[7.9701070786,48.0459327698],"type":"Point"}
}