{
  "type": "Feature",
  "properties": {
    "iso:country":"DE",
    "sg:address":"Holl\u00e4ndischer Brook 5",
    "sg:city":"Hamburg",
    "sg:postcode":"20457",
    "sg:province":"Hamburg",
    "wof:name":"Arabgari Handels Gmbh",
    "wof:placetype":"venue"
},
  "geometry": {"coordinates":[9.9981899261,53.5451583862],"type":"Point"}
}