{
  "type": "Feature",
  "properties": {
    "iso:country":"DE",
    "sg:address":"Postfach 204",
    "sg:city":"Gro\u00dfkarolinenfeld",
    "sg:phone":"+49 8031/50220",
    "sg:postcode":"83106",
    "sg:province":"Bayern",
    "wof:name":"Gsg Elektronik Vertriebs Gmbh",
    "wof:placetype":"venue"
},
  "geometry": {"coordinates":[12.0828104019,47.8923835754],"type":"Point"}
}