{
  "type": "Feature",
  "properties": {
    "iso:country":"DE",
    "sg:address":"Brunnenstr. 3",
    "sg:city":"Rinteln",
    "sg:phone":"+49 5152/4369",
    "sg:postcode":"31737",
    "sg:province":"Niedersachsen",
    "wof:name":"Bettina Jung",
    "wof:placetype":"venue"
},
  "geometry": {"coordinates":[9.1661510468,52.2011528015],"type":"Point"}
}