{
  "type": "Feature",
  "properties": {
    "iso:country":"DE",
    "sg:address":"Friedhofstrasse 31-35",
    "sg:city":"M\u00fclheim an der Ruhr",
    "sg:phone":"+49 208/5885923",
    "sg:postcode":"45478",
    "sg:province":"Nordrhein-Westfalen",
    "wof:name":"Farboffice - Farbe Und Architektur",
    "wof:placetype":"venue"
},
  "geometry": {"coordinates":[6.829793,51.415764],"type":"Point"}
}