{
  "type": "Feature",
  "properties": {
    "iso:country":"DE",
    "sg:address":"Wei\u00dfer Str. 4",
    "sg:city":"K\u00f6ln",
    "sg:phone":"+49 221/352044",
    "sg:postcode":"50996",
    "sg:province":"Nordrhein-Westfalen",
    "wof:name":"Real - Contor Ges. F. Lieg.- U. Beteilig. Verwalt. Gmbh",
    "wof:placetype":"venue"
},
  "geometry": {"coordinates":[6.9977231026,50.8906097412],"type":"Point"}
}