{
  "type": "Feature",
  "properties": {
    "iso:country":"DE",
    "sg:address":"Am Kupferberg 20 a",
    "sg:city":"Imsbach",
    "sg:phone":"+49 6302/3212",
    "sg:postcode":"67817",
    "sg:province":"Rheinland-Pfalz",
    "wof:name":"Regina Fr\u00fchauf",
    "wof:placetype":"venue"
},
  "geometry": {"coordinates":[7.889089,49.585419],"type":"Point"}
}