{
  "type": "Feature",
  "properties": {
    "iso:country":"DE",
    "sg:address":"K-Marx Str. 17",
    "sg:city":"Dorfhain",
    "sg:phone":"+49 35055/828",
    "sg:postcode":"01774",
    "sg:province":"Sachsen",
    "wof:name":"Kreissparkasse Freital",
    "wof:placetype":"venue"
},
  "geometry": {"coordinates":[13.582183,50.905472],"type":"Point"}
}