{
  "type": "Feature",
  "properties": {
    "iso:country":"DE",
    "sg:address":"Alte Vaalser Str. 117",
    "sg:city":"Aachen",
    "sg:phone":"+49 241/874514",
    "sg:postcode":"52074",
    "sg:province":"Nordrhein-Westfalen",
    "wof:name":"Mss Moderner Software-service Gmbh",
    "wof:placetype":"venue"
},
  "geometry": {"coordinates":[6.064922,50.770199],"type":"Point"}
}