{
  "type": "Feature",
  "properties": {
    "iso:country":"DE",
    "sg:address":"Niedergasse 51",
    "sg:city":"Stolberg",
    "sg:phone":"+49 34654/502",
    "sg:postcode":"06547",
    "sg:province":"Sachsen-Anhalt",
    "wof:name":"Friwi-werk Stollberg-harz Witte Ohg",
    "wof:placetype":"venue"
},
  "geometry": {"coordinates":[10.957151413,51.5703277588],"type":"Point"}
}