{
  "type": "Feature",
  "properties": {
    "iso:country":"DE",
    "sg:address":"Karweg 10",
    "sg:city":"D\u00fcsseldorf",
    "sg:phone":"+49 211/9997676",
    "sg:postcode":"40589",
    "sg:province":"Nordrhein-Westfalen",
    "wof:name":"Scheren Logistik Gmbh",
    "wof:placetype":"venue"
},
  "geometry": {"coordinates":[6.831442,51.165058],"type":"Point"}
}