{
  "type": "Feature",
  "properties": {
    "iso:country":"DE",
    "sg:city":"Eschweiler",
    "sg:phone":"+49 2403/22761",
    "sg:postcode":"52249",
    "sg:province":"Nordrhein-Westfalen",
    "wof:name":"H. P. Ulbrich Zauberpeter",
    "wof:placetype":"venue"
},
  "geometry": {"coordinates":[6.266255,50.817379],"type":"Point"}
}