{
  "type": "Feature",
  "properties": {
    "iso:country":"DE",
    "sg:address":"Hoher Steg 2",
    "sg:city":"Wallerfing",
    "sg:phone":"+49 9936/236",
    "sg:postcode":"94574",
    "sg:province":"Bayern",
    "wof:name":"Karl Rembeck",
    "wof:placetype":"venue"
},
  "geometry": {"coordinates":[12.8783149719,48.685760498],"type":"Point"}
}