{
  "type": "Feature",
  "properties": {
    "iso:country":"DE",
    "sg:address":"Am Eiderdeich 19",
    "sg:city":"T\u00f6nning",
    "sg:phone":"+49 4861/5529",
    "sg:postcode":"25832",
    "sg:province":"Schleswig-Holstein",
    "wof:name":"Erich Dawartz",
    "wof:placetype":"venue"
},
  "geometry": {"coordinates":[8.944726944,54.3142585754],"type":"Point"}
}