{
  "type": "Feature",
  "properties": {
    "iso:country":"DE",
    "sg:address":"Waldstr. 22",
    "sg:city":"R\u00fcsselsheim",
    "sg:phone":"+49 6142/62339",
    "sg:postcode":"65428",
    "sg:province":"Hessen",
    "wof:name":"Rex-film Gmbh",
    "wof:placetype":"venue"
},
  "geometry": {"coordinates":[8.416926,49.995209],"type":"Point"}
}