{
  "type": "Feature",
  "properties": {
    "iso:country":"DE",
    "sg:address":"Gerhardstr 59-61",
    "sg:city":"Ratingen",
    "sg:phone":"+49 2102/84070",
    "sg:postcode":"40878",
    "sg:province":"Nordrhein-Westfalen",
    "wof:name":"Ernst G. Sch\u00e4fer Gmbh",
    "wof:placetype":"venue"
},
  "geometry": {"coordinates":[6.8432512283,51.2889900208],"type":"Point"}
}