{
  "type": "Feature",
  "properties": {
    "iso:country":"DE",
    "sg:address":"Fliederweg 1",
    "sg:city":"M\u00fcnchen",
    "sg:phone":"+49 89/6421867",
    "sg:postcode":"81545",
    "sg:province":"Bayern",
    "wof:name":"G. Fritzenwanker Ingenieur",
    "wof:placetype":"venue"
},
  "geometry": {"coordinates":[11.5589551926,48.0924568176],"type":"Point"}
}