{
  "type": "Feature",
  "properties": {
    "iso:country":"DE",
    "sg:address":"Ulmer Str. 50",
    "sg:city":"Senden",
    "sg:phone":"+49 7307/850",
    "sg:postcode":"89250",
    "sg:province":"Bayern",
    "wof:name":"Smart-center Inhofer & Mack Verwaltungs- Gmbh",
    "wof:placetype":"venue"
},
  "geometry": {"coordinates":[10.0459003448,48.3224067688],"type":"Point"}
}