{
  "type": "Feature",
  "properties": {
    "iso:country":"DE",
    "sg:address":"Carl-von-Ossietzky-Str. 40",
    "sg:city":"Osnabr\u00fcck",
    "sg:phone":"+49 541/597685",
    "sg:postcode":"49082",
    "sg:province":"Niedersachsen",
    "wof:name":"G.u.u. Silz Immobilienmakler",
    "wof:placetype":"venue"
},
  "geometry": {"coordinates":[8.0283384323,52.2389526367],"type":"Point"}
}