{
  "type": "Feature",
  "properties": {
    "iso:country":"DE",
    "sg:address":"Kaiserstr. 44",
    "sg:city":"Kirkel",
    "sg:phone":"+49 6849/369",
    "sg:postcode":"66459",
    "sg:province":"Saarland",
    "wof:name":"Raimund Breier",
    "wof:placetype":"venue"
},
  "geometry": {"coordinates":[7.21933,49.280182],"type":"Point"}
}