{
  "type": "Feature",
  "properties": {
    "iso:country":"DE",
    "sg:address":"Am Alten Flie\u00df 52",
    "sg:city":"Bergheim",
    "sg:phone":"+49 2238/93028",
    "sg:postcode":"50129",
    "sg:province":"Nordrhein-Westfalen",
    "wof:name":"H.-g. Heusch Transport-unternehmen",
    "wof:placetype":"venue"
},
  "geometry": {"coordinates":[6.7447571754,50.9857940674],"type":"Point"}
}