{
  "type": "Feature",
  "properties": {
    "iso:country":"DE",
    "sg:address":"Wipperf\u00fcrther Str. 51",
    "sg:city":"Bergisch Gladbach",
    "sg:phone":"+49 2204/52286",
    "sg:postcode":"51429",
    "sg:province":"Nordrhein-Westfalen",
    "wof:name":"Heinz Und Helmut Schwamborn Bauunternehmung Gmbh",
    "wof:placetype":"venue"
},
  "geometry": {"coordinates":[7.17499,50.96608],"type":"Point"}
}