{
  "type": "Feature",
  "properties": {
    "iso:country":"DE",
    "sg:address":"Kappelner Str. 9",
    "sg:city":"Flensburg",
    "sg:phone":"+49 461/21427",
    "sg:postcode":"24943",
    "sg:province":"Schleswig-Holstein",
    "wof:name":"Hohenfriedberg",
    "wof:placetype":"venue"
},
  "geometry": {"coordinates":[9.4455652237,54.7826766968],"type":"Point"}
}