{
  "type": "Feature",
  "properties": {
    "iso:country":"DE",
    "sg:address":"Langstr. 1a",
    "sg:city":"Kelkheim",
    "sg:phone":"+49 6195/61980",
    "sg:postcode":"65779",
    "sg:province":"Hessen",
    "wof:name":"B\u00e4ckerei Wittekind Kg",
    "wof:placetype":"venue"
},
  "geometry": {"coordinates":[8.422364,50.151764],"type":"Point"}
}