{
  "type": "Feature",
  "properties": {
    "iso:country":"DE",
    "sg:address":"Mei\u00dfner Str. 2",
    "sg:city":"Lommatzsch",
    "sg:phone":"+49 35241/52337",
    "sg:postcode":"01623",
    "sg:province":"Sachsen",
    "wof:name":"L\u00f6wenapotheke",
    "wof:placetype":"venue"
},
  "geometry": {"coordinates":[13.310284,51.196651],"type":"Point"}
}