{
  "type": "Feature",
  "properties": {
    "iso:country":"DE",
    "sg:address":"Nordendstra\u00dfe 36",
    "sg:city":"M\u00f6rfelden-Walldorf",
    "sg:phone":"+49 6105",
    "sg:postcode":"64546",
    "sg:province":"Hessen",
    "wof:name":"Mdl Messe-dienst Loeffler",
    "wof:placetype":"venue"
},
  "geometry": {"coordinates":[8.582022,50.016369],"type":"Point"}
}