{
  "type": "Feature",
  "properties": {
    "iso:country":"DE",
    "sg:address":"Treuchtlinger Str. 14",
    "sg:city":"Treuchtlingen",
    "sg:phone":"+49 9142/5375",
    "sg:postcode":"91757",
    "sg:province":"Bayern",
    "wof:name":"Tilo Und Frank Beer",
    "wof:placetype":"venue"
},
  "geometry": {"coordinates":[10.8979101181,48.9770469666],"type":"Point"}
}