{
  "type": "Feature",
  "properties": {
    "iso:country":"DE",
    "sg:address":"H\u00fclser Str. 799",
    "sg:city":"Krefeld",
    "sg:phone":"+49 2151/756938",
    "sg:postcode":"47803",
    "sg:province":"Nordrhein-Westfalen",
    "wof:name":"Odysseus",
    "wof:placetype":"venue"
},
  "geometry": {"coordinates":[6.5230312347,51.3613243103],"type":"Point"}
}