{
  "type": "Feature",
  "properties": {
    "iso:country":"DE",
    "sg:address":"Frankfurter Str. 197",
    "sg:city":"D\u00fcsseldorf",
    "sg:phone":"+49 211/7021068",
    "sg:postcode":"40595",
    "sg:province":"Nordrhein-Westfalen",
    "wof:name":"O. Hatscher Tankstellen Gmbh",
    "wof:placetype":"venue"
},
  "geometry": {"coordinates":[6.893899,51.149864],"type":"Point"}
}