{
  "type": "Feature",
  "properties": {
    "iso:country":"DE",
    "sg:address":"Herrenb\u00fchndtstr. 6",
    "sg:city":"Schutterwald",
    "sg:phone":"+49 781/9903730",
    "sg:postcode":"77746",
    "sg:province":"Baden-W\u00fcrttemberg",
    "wof:name":"Spitzm\u00fcller & Klein Gmbh",
    "wof:placetype":"venue"
},
  "geometry": {"coordinates":[7.885363,48.449814],"type":"Point"}
}