{
  "type": "Feature",
  "properties": {
    "iso:country":"DE",
    "sg:address":"Tanneng\u00e4rten 14",
    "sg:city":"Laucha",
    "sg:postcode":"06636",
    "sg:province":"Sachsen-Anhalt",
    "wof:name":"Gerd Beyer Verwaltungs Gmbh",
    "wof:placetype":"venue"
},
  "geometry": {"coordinates":[11.667491,51.221066],"type":"Point"}
}