{
  "type": "Feature",
  "properties": {
    "iso:country":"DE",
    "sg:address":"Am Marienbrunnen 1",
    "sg:city":"Ralbitz-Rosenthal",
    "sg:phone":"+49 35796/95973",
    "sg:postcode":"01920",
    "sg:province":"Sachsen",
    "wof:name":"Sorabia Bau Gmbh",
    "wof:placetype":"venue"
},
  "geometry": {"coordinates":[14.225144,51.284412],"type":"Point"}
}