{
  "type": "Feature",
  "properties": {
    "iso:country":"DE",
    "sg:address":"Hoch\u00e4ckerstr. 106",
    "sg:city":"M\u00fcnchen",
    "sg:phone":"+49 89/63499801",
    "sg:postcode":"81737",
    "sg:province":"Bayern",
    "wof:name":"Informieren Und Sparen Vermittlung Von Finanz-",
    "wof:placetype":"venue"
},
  "geometry": {"coordinates":[11.6252098083,48.1007804871],"type":"Point"}
}