{
  "type": "Feature",
  "properties": {
    "iso:country":"DE",
    "sg:address":"Flugplatz Saarmund",
    "sg:city":"Saarmund",
    "sg:phone":"+49 33200/82424",
    "sg:postcode":"14552",
    "sg:province":"Brandenburg",
    "wof:name":"Flyranch Berlinbrandenburg Flugschule Lukas Bader",
    "wof:placetype":"venue"
},
  "geometry": {"coordinates":[13.0301704407,52.3122367859],"type":"Point"}
}