{
  "type": "Feature",
  "properties": {
    "iso:country":"DE",
    "sg:address":"Dr.-Max-Ilgner-Str. 21",
    "sg:city":"Espelkamp",
    "sg:postcode":"32339",
    "sg:province":"Nordrhein-Westfalen",
    "wof:name":"Ebert & Ebert Ohg",
    "wof:placetype":"venue"
},
  "geometry": {"coordinates":[8.61843,52.387199],"type":"Point"}
}