{
  "type": "Feature",
  "properties": {
    "iso:country":"DE",
    "sg:address":"Illerstr. 27",
    "sg:city":"Regensburg",
    "sg:phone":"+49 941/42824",
    "sg:postcode":"93057",
    "sg:province":"Bayern",
    "wof:name":"Willi Kuchler",
    "wof:placetype":"venue"
},
  "geometry": {"coordinates":[12.115953,49.035252],"type":"Point"}
}