{
  "type": "Feature",
  "properties": {
    "iso:country":"DE",
    "sg:address":"Kirchstra\u00dfe 4",
    "sg:city":"Lohmar",
    "sg:phone":"+49 2246/6919",
    "sg:postcode":"53797",
    "sg:province":"Nordrhein-Westfalen",
    "wof:name":"Versicherungsb\u00fcro Breidenbach - Lvm",
    "wof:placetype":"venue"
},
  "geometry": {"coordinates":[7.2082128525,50.8403892517],"type":"Point"}
}