{
  "type": "Feature",
  "properties": {
    "iso:country":"DE",
    "sg:address":"Haag",
    "sg:city":"Haag",
    "sg:phone":"+49 8167/424",
    "sg:postcode":"85410",
    "sg:province":"Bayern",
    "wof:name":"Raiffeisenbank Freising-moosburg",
    "wof:placetype":"venue"
},
  "geometry": {"coordinates":[11.83297,48.45863],"type":"Point"}
}