{
  "type": "Feature",
  "properties": {
    "iso:country":"DE",
    "sg:address":"Sybelstr. 5",
    "sg:city":"Berlin",
    "sg:phone":"+49 30/3275223",
    "sg:postcode":"10629",
    "sg:province":"Berlin",
    "wof:name":"Manfred Dittrich Architekt",
    "wof:placetype":"venue"
},
  "geometry": {"coordinates":[13.311174,52.502174],"type":"Point"}
}