{
  "type": "Feature",
  "properties": {
    "iso:country":"DE",
    "sg:address":"Buchenweg 10",
    "sg:city":"Weinheim",
    "sg:phone":"+49 6201/62089",
    "sg:postcode":"69469",
    "sg:province":"Baden-W\u00fcrttemberg",
    "wof:name":"Bachmann Und Schmidt Architekten",
    "wof:placetype":"venue"
},
  "geometry": {"coordinates":[8.647694,49.547199],"type":"Point"}
}