{
  "type": "Feature",
  "properties": {
    "iso:country":"DE",
    "sg:address":"Gesmannstr. 6",
    "sg:city":"Hannover",
    "sg:phone":"+49 511/2344042",
    "sg:postcode":"30459",
    "sg:province":"Niedersachsen",
    "wof:name":"Hohlfeldts Disco",
    "wof:placetype":"venue"
},
  "geometry": {"coordinates":[9.722034,52.346024],"type":"Point"}
}