{
  "type": "Feature",
  "properties": {
    "iso:country":"DE",
    "sg:address":"Steinklint",
    "sg:city":"Wendeburg",
    "sg:phone":"+49 5303/91910",
    "sg:postcode":"38176",
    "sg:province":"Niedersachsen",
    "wof:name":"Kalksandsteinwerk Wendeburg Radmacher Kg",
    "wof:placetype":"venue"
},
  "geometry": {"coordinates":[10.3893957138,52.3266372681],"type":"Point"}
}