{
  "type": "Feature",
  "properties": {
    "iso:country":"DE",
    "sg:address":"Schlettstadter Str. 52 c",
    "sg:city":"Berlin",
    "sg:phone":"+49 30/8113610",
    "sg:postcode":"14169",
    "sg:province":"Berlin",
    "wof:name":"Erhard Mahler Garten- Und",
    "wof:placetype":"venue"
},
  "geometry": {"coordinates":[13.271729,52.439922],"type":"Point"}
}