{
  "type": "Feature",
  "properties": {
    "iso:country":"DE",
    "sg:address":"M\u00fchlenstr. 1",
    "sg:city":"Meerbusch",
    "sg:phone":"+49 2150/5569",
    "sg:postcode":"40668",
    "sg:province":"Nordrhein-Westfalen",
    "wof:name":"Pizzeria Pronto Salvatore",
    "wof:placetype":"venue"
},
  "geometry": {"coordinates":[6.6809930801,51.3035774231],"type":"Point"}
}