{
  "type": "Feature",
  "properties": {
    "iso:country":"DE",
    "sg:address":"Landwehr 15",
    "sg:city":"Hamburg",
    "sg:postcode":"22087",
    "sg:province":"Hamburg",
    "wof:name":"Hard To Get",
    "wof:placetype":"venue"
},
  "geometry": {"coordinates":[10.0358190536,53.5631904602],"type":"Point"}
}