{
  "type": "Feature",
  "properties": {
    "iso:country":"DE",
    "sg:address":"Alter Weg 12",
    "sg:city":"Freiburg",
    "sg:phone":"+49 7664/505590",
    "sg:postcode":"79112",
    "sg:province":"Baden-W\u00fcrttemberg",
    "wof:name":"Vogt Et Faller Gmbh",
    "wof:placetype":"venue"
},
  "geometry": {"coordinates":[7.6991000175,47.965839386],"type":"Point"}
}