{
  "type": "Feature",
  "properties": {
    "iso:country":"DE",
    "sg:address":"Alte Werner Str. 35",
    "sg:city":"Bochum",
    "sg:phone":"+49 234/23795",
    "sg:postcode":"44805",
    "sg:province":"Nordrhein-Westfalen",
    "wof:name":"Telefonbau Bekatronic Fernmeldeanlagenbau",
    "wof:placetype":"venue"
},
  "geometry": {"coordinates":[7.2883458138,51.4986114502],"type":"Point"}
}