{
  "type": "Feature",
  "properties": {
    "iso:country":"DE",
    "sg:address":"Severinstr. 77",
    "sg:city":"K\u00f6ln",
    "sg:phone":"+49 221/321913",
    "sg:postcode":"50678",
    "sg:province":"Nordrhein-Westfalen",
    "wof:name":"Severinsfa\u00df",
    "wof:placetype":"venue"
},
  "geometry": {"coordinates":[6.9582209587,50.9252243042],"type":"Point"}
}