{
  "type": "Feature",
  "properties": {
    "iso:country":"DE",
    "sg:address":"Waldkircher Str. 46",
    "sg:city":"Denzlingen",
    "sg:phone":"+49 7666/948490",
    "sg:postcode":"79211",
    "sg:province":"Baden-W\u00fcrttemberg",
    "wof:name":"Hans Beiermeister",
    "wof:placetype":"venue"
},
  "geometry": {"coordinates":[7.890648,48.063396],"type":"Point"}
}