{
  "type": "Feature",
  "properties": {
    "iso:country":"DE",
    "sg:city":"Alflen",
    "sg:phone":"+49 2678/884",
    "sg:postcode":"56828",
    "sg:province":"Rheinland-Pfalz",
    "wof:name":"Anitas Haarmoden",
    "wof:placetype":"venue"
},
  "geometry": {"coordinates":[7.040958,50.177414],"type":"Point"}
}