{
  "type": "Feature",
  "properties": {
    "iso:country":"DE",
    "sg:address":"Ziegelgasse 20",
    "sg:city":"Neckarbischofsheim",
    "sg:phone":"+49 7263/6161",
    "sg:postcode":"74924",
    "sg:province":"Baden-W\u00fcrttemberg",
    "wof:name":"Manfred Hotz",
    "wof:placetype":"venue"
},
  "geometry": {"coordinates":[8.959271,49.294575],"type":"Point"}
}