{
  "type": "Feature",
  "properties": {
    "iso:country":"DE",
    "sg:address":"Hauptstr. 30",
    "sg:city":"Greu\u00dfenheim",
    "sg:phone":"+49 9369/475",
    "sg:postcode":"97259",
    "sg:province":"Bayern",
    "wof:name":"Edgar R\u00fcgamer",
    "wof:placetype":"venue"
},
  "geometry": {"coordinates":[9.759919,49.813541],"type":"Point"}
}