{
  "type": "Feature",
  "properties": {
    "iso:country":"DE",
    "sg:address":"Peutingerstr. 10",
    "sg:city":"Ellwangen",
    "sg:phone":"+49 7961/2387",
    "sg:postcode":"73479",
    "sg:province":"Baden-W\u00fcrttemberg",
    "wof:name":"Heinz Eiberger",
    "wof:placetype":"venue"
},
  "geometry": {"coordinates":[10.134057,48.965889],"type":"Point"}
}