{
  "type": "Feature",
  "properties": {
    "iso:country":"DE",
    "sg:address":"Spittelgartenstr. 15",
    "sg:city":"Erfurt",
    "sg:phone":"+49 361/7360717",
    "sg:postcode":"99089",
    "sg:province":"Th\u00fcringen",
    "wof:name":"Rumpelstilzchen",
    "wof:placetype":"venue"
},
  "geometry": {"coordinates":[11.0247888565,50.9930038452],"type":"Point"}
}