{
  "type": "Feature",
  "properties": {
    "iso:country":"DE",
    "sg:address":"Gro\u00dfe Str. 2",
    "sg:city":"Osnabr\u00fcck",
    "sg:phone":"+49 541/29709",
    "sg:postcode":"49074",
    "sg:province":"Niedersachsen",
    "wof:name":"Imbi\u00df Kochl\u00f6ffel",
    "wof:placetype":"venue"
},
  "geometry": {"coordinates":[8.0487508774,52.2730751038],"type":"Point"}
}