{
  "type": "Feature",
  "properties": {
    "iso:country":"DE",
    "sg:address":"Heisenbergstr 4",
    "sg:city":"Dachau",
    "sg:phone":"+49 8131/51560",
    "sg:postcode":"85221",
    "sg:province":"Bayern",
    "wof:name":"B.s.m. B\u00fcrosysteme Vertriebs Gmbh",
    "wof:placetype":"venue"
},
  "geometry": {"coordinates":[11.4767017365,48.2677307129],"type":"Point"}
}