{
  "type": "Feature",
  "properties": {
    "iso:country":"DE",
    "sg:address":"Sophienstr. 159",
    "sg:city":"Karlsruhe",
    "sg:phone":"+49 721/842064",
    "sg:postcode":"76185",
    "sg:province":"Baden-W\u00fcrttemberg",
    "wof:name":"Wetterauer & Schmitt & Co. Druckerei Gmbh",
    "wof:placetype":"venue"
},
  "geometry": {"coordinates":[8.372537,49.008511],"type":"Point"}
}