{
  "type": "Feature",
  "properties": {
    "iso:country":"DE",
    "sg:address":"Konstantinstr. 387",
    "sg:city":"M\u00f6nchengladbach",
    "sg:phone":"+49 2166/86051",
    "sg:postcode":"41238",
    "sg:province":"Nordrhein-Westfalen",
    "wof:name":"Solventa Wirtschafts- Informationen Gmbh & Co. Kg",
    "wof:placetype":"venue"
},
  "geometry": {"coordinates":[6.503797,51.155071],"type":"Point"}
}