{
  "type": "Feature",
  "properties": {
    "iso:country":"DE",
    "sg:address":"Mittelstr. 111",
    "sg:city":"Horn-Bad Meinberg",
    "sg:phone":"+49 5234/1061",
    "sg:postcode":"32805",
    "sg:province":"Nordrhein-Westfalen",
    "wof:name":"Infodeal Gmbh Richard B\u00fcchter",
    "wof:placetype":"venue"
},
  "geometry": {"coordinates":[8.9492502213,51.8733215332],"type":"Point"}
}