{
  "type": "Feature",
  "properties": {
    "iso:country":"DE",
    "sg:address":"Gr\u00fcner Weg 31",
    "sg:city":"Lippstadt",
    "sg:phone":"+49 2941/94480",
    "sg:postcode":"59556",
    "sg:province":"Nordrhein-Westfalen",
    "wof:name":"Pension Haus Gisela",
    "wof:placetype":"venue"
},
  "geometry": {"coordinates":[8.348110199,51.7124595642],"type":"Point"}
}