{
  "type": "Feature",
  "properties": {
    "iso:country":"DE",
    "sg:address":"Schustergasse 9",
    "sg:city":"Wasserburg",
    "sg:phone":"+49 8071/7471",
    "sg:postcode":"83512",
    "sg:province":"Bayern",
    "wof:name":"Metzgerei Rahm Gmbh",
    "wof:placetype":"venue"
},
  "geometry": {"coordinates":[12.2307758331,48.0614013672],"type":"Point"}
}