{
  "type": "Feature",
  "properties": {
    "iso:country":"DE",
    "sg:address":"Rothenbaumchaussee 101",
    "sg:city":"Hamburg",
    "sg:phone":"+49 40/451362",
    "sg:postcode":"20148",
    "sg:province":"Hamburg",
    "wof:name":"L. Winkler Immobilienmakler",
    "wof:placetype":"venue"
},
  "geometry": {"coordinates":[9.9883298874,53.5711784363],"type":"Point"}
}