{
  "type": "Feature",
  "properties": {
    "iso:country":"DE",
    "sg:address":"Teilestr. 26-28",
    "sg:city":"Berlin",
    "sg:postcode":"12099",
    "sg:province":"Berlin",
    "wof:name":"Transrental-berlin Speditionsges. Mbh",
    "wof:placetype":"venue"
},
  "geometry": {"coordinates":[13.4075307846,52.4601631165],"type":"Point"}
}