{
  "type": "Feature",
  "properties": {
    "iso:country":"DE",
    "sg:address":"Mittelstr. 30",
    "sg:city":"Immenhausen",
    "sg:phone":"+49 5673/2379",
    "sg:postcode":"34376",
    "sg:province":"Hessen",
    "wof:name":"B\u00e4ckerei Und Konditorei H. Und J. Gerlach Gmbh",
    "wof:placetype":"venue"
},
  "geometry": {"coordinates":[9.480713,51.426956],"type":"Point"}
}