{
  "type": "Feature",
  "properties": {
    "iso:country":"DE",
    "sg:address":"W\u00e4chterstr. 63 a",
    "sg:city":"Oyten",
    "sg:phone":"+49 4207/802009",
    "sg:postcode":"28876",
    "sg:province":"Niedersachsen",
    "wof:name":"Amo Im- Und Export Gmbh",
    "wof:placetype":"venue"
},
  "geometry": {"coordinates":[9.018344,53.049511],"type":"Point"}
}