{
  "type": "Feature",
  "properties": {
    "iso:country":"DE",
    "sg:address":"Emscherstr. 46",
    "sg:city":"Gelsenkirchen",
    "sg:phone":"+49 209/70020",
    "sg:postcode":"45891",
    "sg:province":"Nordrhein-Westfalen",
    "wof:name":"Nacanco Verwaltungsges. Mbh",
    "wof:placetype":"venue"
},
  "geometry": {"coordinates":[7.083579,51.547047],"type":"Point"}
}