{
  "type": "Feature",
  "properties": {
    "iso:country":"DE",
    "sg:address":"Hei\u00dfbergstr. 2-4",
    "sg:city":"Aachen",
    "sg:postcode":"52066",
    "sg:province":"Nordrhein-Westfalen",
    "wof:name":"Etm Elektrotechnik R\u00fcdiger Mommertz",
    "wof:placetype":"venue"
},
  "geometry": {"coordinates":[6.092759,50.759468],"type":"Point"}
}