{
  "type": "Feature",
  "properties": {
    "iso:country":"DE",
    "sg:address":"Friesenheimer Hauptstr. 39",
    "sg:city":"Friesenheim",
    "sg:phone":"+49 7821/67911",
    "sg:postcode":"77948",
    "sg:province":"Baden-W\u00fcrttemberg",
    "wof:name":"R. Arnold",
    "wof:placetype":"venue"
},
  "geometry": {"coordinates":[7.878649,48.373192],"type":"Point"}
}