{
  "type": "Feature",
  "properties": {
    "iso:country":"DE",
    "sg:address":"Hanfstr. 29-35",
    "sg:city":"Bielefeld",
    "sg:phone":"+49 4952/1931701",
    "sg:postcode":"33607",
    "sg:province":"Nordrhein-Westfalen",
    "wof:name":"Werner Langenscheidt Hoch-u. Stahlbetonbau Gmbh & Co Kg",
    "wof:placetype":"venue"
},
  "geometry": {"coordinates":[8.563129,52.024265],"type":"Point"}
}