{
  "type": "Feature",
  "properties": {
    "iso:country":"DE",
    "sg:address":"Diefenbachstr. 22",
    "sg:city":"M\u00fcnchen",
    "sg:phone":"+49 89/794275",
    "sg:postcode":"81479",
    "sg:province":"Bayern",
    "wof:name":"Trautel Kirchhoff Rechtsanw\u00e4ltin",
    "wof:placetype":"venue"
},
  "geometry": {"coordinates":[11.5231075287,48.0804786682],"type":"Point"}
}