{
  "type": "Feature",
  "properties": {
    "iso:country":"DE",
    "sg:address":"Kaiserdamm 2",
    "sg:city":"Berlin",
    "sg:phone":"+49 30/3256161",
    "sg:postcode":"14057",
    "sg:province":"Berlin",
    "wof:name":"Anneliese K\u00f6hrich Autovermietung",
    "wof:placetype":"venue"
},
  "geometry": {"coordinates":[13.294722,52.511017],"type":"Point"}
}