{
  "type": "Feature",
  "properties": {
    "iso:country":"DE",
    "sg:address":"Untere Str. 53",
    "sg:city":"Wipperf\u00fcrth",
    "sg:phone":"+49 2267/829242",
    "sg:postcode":"51688",
    "sg:province":"Nordrhein-Westfalen",
    "wof:name":"Restaurant Picasso",
    "wof:placetype":"venue"
},
  "geometry": {"coordinates":[7.3986968994,51.1178817749],"type":"Point"}
}