{
  "type": "Feature",
  "properties": {
    "iso:country":"DE",
    "sg:address":"Niederste Str. 26",
    "sg:city":"Attendorn",
    "sg:phone":"+49 2722/4009",
    "sg:postcode":"57439",
    "sg:province":"Nordrhein-Westfalen",
    "wof:name":"Modehaus Kohl Kg",
    "wof:placetype":"venue"
},
  "geometry": {"coordinates":[7.9066801071,51.1261711121],"type":"Point"}
}