{
  "type": "Feature",
  "properties": {
    "iso:country":"DE",
    "sg:address":"Tanneneck 14",
    "sg:city":"Bochum",
    "sg:phone":"+49 234/73465",
    "sg:postcode":"44799",
    "sg:province":"Nordrhein-Westfalen",
    "wof:name":"Dr. Walter Grahner Ingenieur",
    "wof:placetype":"venue"
},
  "geometry": {"coordinates":[7.2335767746,51.4439353943],"type":"Point"}
}