{
  "type": "Feature",
  "properties": {
    "iso:country":"DE",
    "sg:address":"Raumbacher Str. 3",
    "sg:city":"Meisenheim",
    "sg:phone":"+49 6753/3144",
    "sg:postcode":"55590",
    "sg:province":"Rheinland-Pfalz",
    "wof:name":"G\u00fcnther Kwasny",
    "wof:placetype":"venue"
},
  "geometry": {"coordinates":[7.6673541069,49.7106552124],"type":"Point"}
}