{
  "type": "Feature",
  "properties": {
    "iso:country":"DE",
    "sg:address":"Senefelderstr 2",
    "sg:city":"Mainburg",
    "sg:phone":"+49 8751/86220",
    "sg:postcode":"84048",
    "sg:province":"Bayern",
    "wof:name":"Gebendorfer Innenausbau Gmbh & Co Kg",
    "wof:placetype":"venue"
},
  "geometry": {"coordinates":[11.783652,48.658154],"type":"Point"}
}