{
  "type": "Feature",
  "properties": {
    "iso:country":"DE",
    "sg:address":"Selliner Str. 1",
    "sg:city":"Dresden",
    "sg:phone":"+49 351/8831630",
    "sg:postcode":"01109",
    "sg:province":"Sachsen",
    "wof:name":"Baur Reinert Appy Und Partner",
    "wof:placetype":"venue"
},
  "geometry": {"coordinates":[13.7889232635,51.1191825867],"type":"Point"}
}