{
  "type": "Feature",
  "properties": {
    "iso:country":"DE",
    "sg:address":"Daimlerstr. 33",
    "sg:city":"Walldorf",
    "sg:phone":"+49 6227/30101",
    "sg:postcode":"69190",
    "sg:province":"Baden-W\u00fcrttemberg",
    "wof:name":"Helo Kfz Technik Gmbh",
    "wof:placetype":"venue"
},
  "geometry": {"coordinates":[8.6422643661,49.2919616699],"type":"Point"}
}