{
  "type": "Feature",
  "properties": {
    "iso:country":"DE",
    "sg:address":"Elgersh\u00e4user Str. 9",
    "sg:city":"Baunatal",
    "sg:phone":"+49 5601/8031",
    "sg:postcode":"34225",
    "sg:province":"Hessen",
    "wof:name":"H\u00fcnstein-apotheke",
    "wof:placetype":"venue"
},
  "geometry": {"coordinates":[9.384708,51.249355],"type":"Point"}
}