{
  "type": "Feature",
  "properties": {
    "iso:country":"DE",
    "sg:address":"Br\u00fchler Str. 48",
    "sg:city":"Erfurt",
    "sg:phone":"+49 361/2229741",
    "sg:postcode":"99084",
    "sg:province":"Th\u00fcringen",
    "wof:name":"Kul Gmbh",
    "wof:placetype":"venue"
},
  "geometry": {"coordinates":[11.0165109634,50.9724731445],"type":"Point"}
}