{
  "type": "Feature",
  "properties": {
    "iso:country":"DE",
    "sg:address":"Steinackerstr. 1",
    "sg:city":"Weitersburg",
    "sg:phone":"+49 2622/16460",
    "sg:postcode":"56191",
    "sg:province":"Rheinland-Pfalz",
    "wof:name":"Maletzki",
    "wof:placetype":"venue"
},
  "geometry": {"coordinates":[7.5978307724,50.4111442566],"type":"Point"}
}