{
  "type": "Feature",
  "properties": {
    "iso:country":"DE",
    "sg:address":"Gustav-Werner-Str. 8",
    "sg:city":"Bietigheim-Bissingen",
    "sg:phone":"+49 7142/51150",
    "sg:postcode":"74321",
    "sg:province":"Baden-W\u00fcrttemberg",
    "wof:name":"Herbert M\u00fcller Ingenieur",
    "wof:placetype":"venue"
},
  "geometry": {"coordinates":[9.106713295,48.9623451233],"type":"Point"}
}