{
  "type": "Feature",
  "properties": {
    "iso:country":"DE",
    "sg:address":"Hohenmoorer Str. 62",
    "sg:city":"Asendorf",
    "sg:phone":"+49 4253/470",
    "sg:postcode":"27330",
    "sg:province":"Niedersachsen",
    "wof:name":"Heinrich Henke",
    "wof:placetype":"venue"
},
  "geometry": {"coordinates":[8.946143,52.756905],"type":"Point"}
}