{
  "type": "Feature",
  "properties": {
    "iso:country":"DE",
    "sg:address":"Freibergstr. 28",
    "sg:city":"Berlin",
    "sg:phone":"+49 30/7064830",
    "sg:postcode":"12107",
    "sg:province":"Berlin",
    "wof:name":"Peter Rudolph",
    "wof:placetype":"venue"
},
  "geometry": {"coordinates":[13.3873071671,52.4349555969],"type":"Point"}
}