{
  "type": "Feature",
  "properties": {
    "iso:country":"DE",
    "sg:address":"Raunheimer Str. 21",
    "sg:city":"Fl\u00f6rsheim",
    "sg:phone":"+49 6145/32924",
    "sg:postcode":"65439",
    "sg:province":"Hessen",
    "wof:name":"Willi Wendel",
    "wof:placetype":"venue"
},
  "geometry": {"coordinates":[8.438733,50.044323],"type":"Point"}
}