{
  "type": "Feature",
  "properties": {
    "iso:country":"DE",
    "sg:address":"Auf der Schanz 61",
    "sg:city":"N\u00fcrnberg",
    "sg:phone":"+49 911/6327372",
    "sg:postcode":"90453",
    "sg:province":"Bayern",
    "wof:name":"Prof. Dr. Hans Banski",
    "wof:placetype":"venue"
},
  "geometry": {"coordinates":[11.0212697983,49.3737487793],"type":"Point"}
}