{
  "type": "Feature",
  "properties": {
    "iso:country":"DE",
    "sg:address":"Trierer Str. 35",
    "sg:city":"Hellenthal",
    "sg:phone":"+49 2482/2149",
    "sg:postcode":"53940",
    "sg:province":"Nordrhein-Westfalen",
    "wof:name":"E. H\u00f6rnchen",
    "wof:placetype":"venue"
},
  "geometry": {"coordinates":[6.434486,50.488945],"type":"Point"}
}