{
  "type": "Feature",
  "properties": {
    "iso:country":"DE",
    "sg:address":"Trupermoorer Landstr. 28",
    "sg:city":"Lilienthal",
    "sg:phone":"+49 4298/3610",
    "sg:postcode":"28865",
    "sg:province":"Niedersachsen",
    "wof:name":"Rohdenburg Hotel Und Restaurant Beteiligungs Gmbh",
    "wof:placetype":"venue"
},
  "geometry": {"coordinates":[8.939501,53.161377],"type":"Point"}
}