{
  "type": "Feature",
  "properties": {
    "iso:country":"DE",
    "sg:address":"Hackl\u00e4nderstr. 33",
    "sg:city":"Stuttgart",
    "sg:phone":"+49 711/468402",
    "sg:postcode":"70184",
    "sg:province":"Baden-W\u00fcrttemberg",
    "wof:name":"Siegfried Fischer Innenarchitekt",
    "wof:placetype":"venue"
},
  "geometry": {"coordinates":[9.197006,48.774769],"type":"Point"}
}