{
  "type": "Feature",
  "properties": {
    "iso:country":"DE",
    "sg:address":"Rheinallee 119",
    "sg:city":"D\u00fcsseldorf",
    "sg:phone":"+49 211/575033",
    "sg:postcode":"40545",
    "sg:province":"Nordrhein-Westfalen",
    "wof:name":"Peter Oeking Steuerberater",
    "wof:placetype":"venue"
},
  "geometry": {"coordinates":[6.7450890541,51.2282981873],"type":"Point"}
}