{
  "type": "Feature",
  "properties": {
    "iso:country":"DE",
    "sg:address":"Seelach 16",
    "sg:city":"Kronach",
    "sg:phone":"+49 9261/95250",
    "sg:postcode":"96317",
    "sg:province":"Bayern",
    "wof:name":"Biohof C. Und M. Porzelt",
    "wof:placetype":"venue"
},
  "geometry": {"coordinates":[11.301515,50.251472],"type":"Point"}
}