{
  "type": "Feature",
  "properties": {
    "iso:country":"DE",
    "sg:address":"Im Ohl 18a",
    "sg:city":"Arnsberg",
    "sg:phone":"+49 4929/3263950",
    "sg:postcode":"59757",
    "sg:province":"Nordrhein-Westfalen",
    "wof:name":"Binhold Gmbh",
    "wof:placetype":"venue"
},
  "geometry": {"coordinates":[7.9493308067,51.4616127014],"type":"Point"}
}