{
  "type": "Feature",
  "properties": {
    "iso:country":"DE",
    "sg:address":"Niebendorfer Weg 15",
    "sg:city":"Hohenseefeld",
    "sg:phone":"+49 33744/60423",
    "sg:postcode":"14913",
    "sg:province":"Brandenburg",
    "wof:name":"Erhard Kuhl",
    "wof:placetype":"venue"
},
  "geometry": {"coordinates":[13.3027124405,51.8919906616],"type":"Point"}
}