{
  "type": "Feature",
  "properties": {
    "iso:country":"DE",
    "sg:address":"Dr.-Henkel-Str. 16",
    "sg:city":"Erding",
    "sg:phone":"+49 8122/40688",
    "sg:postcode":"85435",
    "sg:province":"Bayern",
    "wof:name":"Restaurant Delphi",
    "wof:placetype":"venue"
},
  "geometry": {"coordinates":[11.9139890671,48.3077392578],"type":"Point"}
}