{
  "type": "Feature",
  "properties": {
    "iso:country":"DE",
    "sg:address":"Blombachstr. 18",
    "sg:city":"Wuppertal",
    "sg:phone":"+49 202/461415",
    "sg:postcode":"42369",
    "sg:province":"Nordrhein-Westfalen",
    "wof:name":"K\u00fcchenstudio Hans P\u00f6hler",
    "wof:placetype":"venue"
},
  "geometry": {"coordinates":[7.1981339455,51.2277870178],"type":"Point"}
}