{
  "type": "Feature",
  "properties": {
    "iso:country":"DE",
    "sg:address":"Theodor-Storm-Str. 7",
    "sg:city":"Regensburg",
    "sg:phone":"+49 941/90216",
    "sg:postcode":"93051",
    "sg:province":"Bayern",
    "wof:name":"Michael Schmid Gmbh Fleischerei",
    "wof:placetype":"venue"
},
  "geometry": {"coordinates":[12.0835361481,49.0015678406],"type":"Point"}
}