{
  "type": "Feature",
  "properties": {
    "iso:country":"DE",
    "sg:address":"Badstr. 5",
    "sg:city":"Prie\u00dfnitz",
    "sg:phone":"+49 34345/23540",
    "sg:postcode":"04651",
    "sg:province":"Sachsen",
    "wof:name":"B. Busch",
    "wof:placetype":"venue"
},
  "geometry": {"coordinates":[12.6110906601,51.103603363],"type":"Point"}
}