{
  "type": "Feature",
  "properties": {
    "iso:country":"DE",
    "sg:address":"Kornbergstr. 11/11a",
    "sg:city":"Stuttgart",
    "sg:phone":"+49 711/293130",
    "sg:postcode":"70176",
    "sg:province":"Baden-W\u00fcrttemberg",
    "wof:name":"Aldi Gmbh & Co. Kg",
    "wof:placetype":"venue"
},
  "geometry": {"coordinates":[9.1621866226,48.7836456299],"type":"Point"}
}