{
  "type": "Feature",
  "properties": {
    "iso:country":"DE",
    "sg:address":"Hauffstr. 11",
    "sg:city":"Beuren",
    "sg:phone":"+49 7025/5209",
    "sg:postcode":"72660",
    "sg:province":"Baden-W\u00fcrttemberg",
    "wof:name":"Ssh Sich & Schimmer Handelsvertretungen Gmbh",
    "wof:placetype":"venue"
},
  "geometry": {"coordinates":[9.4011850357,48.5716934204],"type":"Point"}
}