{
  "type": "Feature",
  "properties": {
    "iso:country":"DE",
    "sg:address":"H\u00fctzelstr. 16",
    "sg:city":"Bremen",
    "sg:phone":"+49 421/4674161",
    "sg:postcode":"28329",
    "sg:province":"Bremen",
    "wof:name":"Delphi",
    "wof:placetype":"venue"
},
  "geometry": {"coordinates":[8.8809928894,53.0704574585],"type":"Point"}
}