{
  "type": "Feature",
  "properties": {
    "iso:country":"DE",
    "sg:address":"Br\u00fcsseler Ring 93",
    "sg:city":"Aachen",
    "sg:phone":"+49 241/74378",
    "sg:postcode":"52074",
    "sg:province":"Nordrhein-Westfalen",
    "wof:name":"R. Gerlach Architekt",
    "wof:placetype":"venue"
},
  "geometry": {"coordinates":[6.066573,50.755047],"type":"Point"}
}