{
  "type": "Feature",
  "properties": {
    "iso:country":"DE",
    "sg:address":"Mozartstr. 16",
    "sg:city":"Gersheim",
    "sg:phone":"+49 6843/1349",
    "sg:postcode":"66453",
    "sg:province":"Saarland",
    "wof:name":"Monika Und Siegfried Dell",
    "wof:placetype":"venue"
},
  "geometry": {"coordinates":[7.216532,49.16571],"type":"Point"}
}