{
  "type": "Feature",
  "properties": {
    "iso:country":"DE",
    "sg:address":"Hauptstr. 81",
    "sg:city":"Obersontheim",
    "sg:phone":"+49 7973/728",
    "sg:postcode":"74423",
    "sg:province":"Baden-W\u00fcrttemberg",
    "wof:name":"W. Und F. Schaffitzel Gmbh & Co.",
    "wof:placetype":"venue"
},
  "geometry": {"coordinates":[9.9046697617,49.0545310974],"type":"Point"}
}