{
  "type": "Feature",
  "properties": {
    "iso:country":"DE",
    "sg:address":"Hohndorfer Str. 28",
    "sg:city":"Krumhermersdorf",
    "sg:phone":"+49 371/234041",
    "sg:postcode":"09434",
    "sg:province":"Sachsen",
    "wof:name":"Apotheke E. Hentschel",
    "wof:placetype":"venue"
},
  "geometry": {"coordinates":[13.103194,50.733643],"type":"Point"}
}