{
  "type": "Feature",
  "properties": {
    "iso:country":"DE",
    "sg:address":"Weberstr. 25",
    "sg:city":"Zeitz",
    "sg:phone":"+49 3441/250861",
    "sg:postcode":"06712",
    "sg:province":"Sachsen-Anhalt",
    "wof:name":"Heimkehr Gmbh",
    "wof:placetype":"venue"
},
  "geometry": {"coordinates":[12.138802,51.048347],"type":"Point"}
}