{
  "type": "Feature",
  "properties": {
    "iso:country":"DE",
    "sg:address":"Neum\u00fchlenallee 24a",
    "sg:city":"Borken",
    "sg:phone":"+49 2861/3076",
    "sg:postcode":"46325",
    "sg:province":"Nordrhein-Westfalen",
    "wof:name":"Gogoll Isoliertechnik Gmbh",
    "wof:placetype":"venue"
},
  "geometry": {"coordinates":[6.860754,51.86047],"type":"Point"}
}