{
  "type": "Feature",
  "properties": {
    "iso:country":"DE",
    "sg:address":"Ernst-Moritz-Arndt-Str. 33",
    "sg:city":"Neukirchen-Vluyn",
    "sg:phone":"+49 2845/58133",
    "sg:postcode":"47506",
    "sg:province":"Nordrhein-Westfalen",
    "wof:name":"Rita Beckmann",
    "wof:placetype":"venue"
},
  "geometry": {"coordinates":[6.5694317818,51.4402885437],"type":"Point"}
}