{
  "type": "Feature",
  "properties": {
    "iso:country":"DE",
    "sg:address":"Hauptstr. 6",
    "sg:city":"Asbach-B\u00e4umenheim",
    "sg:phone":"+49 906/91086",
    "sg:postcode":"86663",
    "sg:province":"Bayern",
    "wof:name":"G. Scharrer",
    "wof:placetype":"venue"
},
  "geometry": {"coordinates":[10.813779,48.681946],"type":"Point"}
}