{
  "type": "Feature",
  "properties": {
    "iso:country":"DE",
    "sg:address":"Brucknerstr. 5",
    "sg:city":"Blieskastel",
    "sg:phone":"+49 6842/2214",
    "sg:postcode":"66440",
    "sg:province":"Saarland",
    "wof:name":"Metel Handelsges. F. Metallbauelemente Mbh",
    "wof:placetype":"venue"
},
  "geometry": {"coordinates":[7.273268,49.22702],"type":"Point"}
}