{
  "type": "Feature",
  "properties": {
    "iso:country":"DE",
    "sg:address":"Gerberstr. 30",
    "sg:city":"N\u00fcrtingen",
    "sg:phone":"+49 7022/34528",
    "sg:postcode":"72622",
    "sg:province":"Baden-W\u00fcrttemberg",
    "wof:name":"Haussmann",
    "wof:placetype":"venue"
},
  "geometry": {"coordinates":[9.340417,48.622852],"type":"Point"}
}