{
  "type": "Feature",
  "properties": {
    "iso:country":"DE",
    "sg:address":"Am Kanaldamm 1",
    "sg:city":"Kuppenheim",
    "sg:phone":"+49 7222/48400",
    "sg:postcode":"76456",
    "sg:province":"Baden-W\u00fcrttemberg",
    "wof:name":"Egon Link Tennis- Und Squashcentrum",
    "wof:placetype":"venue"
},
  "geometry": {"coordinates":[8.2528877258,48.8329849243],"type":"Point"}
}