{
  "type": "Feature",
  "properties": {
    "iso:country":"DE",
    "sg:address":"Ruhrfelder Str. 36",
    "sg:city":"M\u00f6nchengladbach",
    "sg:phone":"+49 2166/680166",
    "sg:postcode":"41199",
    "sg:province":"Nordrhein-Westfalen",
    "wof:name":"Pizzeria Roma",
    "wof:placetype":"venue"
},
  "geometry": {"coordinates":[6.4473638535,51.1362228394],"type":"Point"}
}