{
  "type": "Feature",
  "properties": {
    "iso:country":"DE",
    "sg:address":"Ruppendorfer Str. 2",
    "sg:city":"Reichst\u00e4dt",
    "sg:phone":"+49 3504/614709",
    "sg:postcode":"01744",
    "sg:province":"Sachsen",
    "wof:name":"Klaus Winkler",
    "wof:placetype":"venue"
},
  "geometry": {"coordinates":[13.639529,50.883514],"type":"Point"}
}