{
  "type": "Feature",
  "properties": {
    "iso:country":"DE",
    "sg:address":"Stra\u00dfburger Str. 23",
    "sg:city":"Bremen",
    "sg:phone":"+49 421/349011",
    "sg:postcode":"28211",
    "sg:province":"Bremen",
    "wof:name":"Hansa Asphalt Gmbh & Co. Kg",
    "wof:placetype":"venue"
},
  "geometry": {"coordinates":[8.8380813599,53.0814476013],"type":"Point"}
}