{
  "type": "Feature",
  "properties": {
    "iso:country":"DE",
    "sg:address":"Am Ullrichsberg 22-24",
    "sg:city":"Mannheim",
    "sg:phone":"+49 621/727760",
    "sg:postcode":"68309",
    "sg:province":"Baden-W\u00fcrttemberg",
    "wof:name":"Hema-maier Gmbh",
    "wof:placetype":"venue"
},
  "geometry": {"coordinates":[8.5262937546,49.5068206787],"type":"Point"}
}