{
  "type": "Feature",
  "properties": {
    "iso:country":"DE",
    "sg:address":"Kornmarkt 3",
    "sg:city":"Bad Windsheim",
    "sg:phone":"+49 9841/651580",
    "sg:postcode":"91438",
    "sg:province":"Bayern",
    "wof:name":"Azba Import Export Gmbh",
    "wof:placetype":"venue"
},
  "geometry": {"coordinates":[10.4162149429,49.5017433167],"type":"Point"}
}