{
  "type": "Feature",
  "properties": {
    "iso:country":"DE",
    "sg:address":"An der Waldstr. 1",
    "sg:city":"Treuen",
    "sg:phone":"+49 37468/6080",
    "sg:postcode":"08233",
    "sg:province":"Sachsen",
    "wof:name":"Kmt Kunststoff-metall- Technologie Gmbh",
    "wof:placetype":"venue"
},
  "geometry": {"coordinates":[12.306895,50.550636],"type":"Point"}
}