{
  "type": "Feature",
  "properties": {
    "iso:country":"DE",
    "sg:address":"Industriestr. 22",
    "sg:city":"Dahn",
    "sg:phone":"+49 6391/92310",
    "sg:postcode":"66994",
    "sg:province":"Rheinland-Pfalz",
    "wof:name":"Fensterbau An Der Reichenbach Gmbh",
    "wof:placetype":"venue"
},
  "geometry": {"coordinates":[7.801633,49.133644],"type":"Point"}
}