{
  "type": "Feature",
  "properties": {
    "iso:country":"DE",
    "sg:address":"Lindenstr. 56",
    "sg:city":"Berlin",
    "sg:phone":"+49 30/6489341",
    "sg:postcode":"12589",
    "sg:province":"Berlin",
    "wof:name":"Hotel-restaurant Lindengarten",
    "wof:placetype":"venue"
},
  "geometry": {"coordinates":[13.7322816849,52.4271812439],"type":"Point"}
}