{
  "type": "Feature",
  "properties": {
    "iso:country":"DE",
    "sg:address":"Eschbachh\u00f6henweg 3",
    "sg:city":"Waldesch",
    "sg:phone":"+49 2628/8173",
    "sg:postcode":"56323",
    "sg:province":"Rheinland-Pfalz",
    "wof:name":"W I K O Automaten- Aufstell Gmbh",
    "wof:placetype":"venue"
},
  "geometry": {"coordinates":[7.5436749458,50.2854003906],"type":"Point"}
}