{
  "type": "Feature",
  "properties": {
    "iso:country":"DE",
    "sg:address":"Klosterstr. 21",
    "sg:city":"Gelsenkirchen",
    "sg:phone":"+49 209/207619",
    "sg:postcode":"45879",
    "sg:province":"Nordrhein-Westfalen",
    "wof:name":"Unsre Grill",
    "wof:placetype":"venue"
},
  "geometry": {"coordinates":[7.0956721306,51.5084762573],"type":"Point"}
}