{
  "type": "Feature",
  "properties": {
    "iso:country":"DE",
    "sg:address":"Osenauer Str. 39",
    "sg:city":"Odenthal",
    "sg:phone":"+49 2202/70260",
    "sg:postcode":"51519",
    "sg:province":"Nordrhein-Westfalen",
    "wof:name":"Inter Select E. K.",
    "wof:placetype":"venue"
},
  "geometry": {"coordinates":[7.1034197807,51.031288147],"type":"Point"}
}