{
  "type": "Feature",
  "properties": {
    "iso:country":"DE",
    "sg:address":"Freienwalder Chaussee 24",
    "sg:city":"Werneuchen",
    "sg:phone":"+49 33398/76030",
    "sg:postcode":"16356",
    "sg:province":"Brandenburg",
    "wof:name":"H. Walkowiak",
    "wof:placetype":"venue"
},
  "geometry": {"coordinates":[13.733512,52.629822],"type":"Point"}
}