{
  "type": "Feature",
  "properties": {
    "iso:country":"DE",
    "sg:address":"Hans-Thoma-Str. 5",
    "sg:city":"Essen",
    "sg:phone":"+49 201/702139",
    "sg:postcode":"45147",
    "sg:province":"Nordrhein-Westfalen",
    "wof:name":"R\u00f6ntgenfilm- Und Zubeh\u00f6r- Vertrieb H. Gunst Gmbh",
    "wof:placetype":"venue"
},
  "geometry": {"coordinates":[6.983288765,51.4420433044],"type":"Point"}
}