{
  "type": "Feature",
  "properties": {
    "iso:country":"DE",
    "sg:address":"Nordring 28",
    "sg:city":"Eilenburg",
    "sg:phone":"+49 3423/4148",
    "sg:postcode":"04838",
    "sg:province":"Sachsen",
    "wof:name":"Bennys Tiershop",
    "wof:placetype":"venue"
},
  "geometry": {"coordinates":[12.62868,51.460285],"type":"Point"}
}