{
  "type": "Feature",
  "properties": {
    "iso:country":"DE",
    "sg:address":"Ober der Schmitte 1",
    "sg:city":"Ruppichteroth",
    "sg:phone":"+49 2295/5540",
    "sg:postcode":"53809",
    "sg:province":"Nordrhein-Westfalen",
    "wof:name":"R. M\u00fchlenhoff Immobilienmakler",
    "wof:placetype":"venue"
},
  "geometry": {"coordinates":[7.4556522369,50.8335952759],"type":"Point"}
}