{
  "type": "Feature",
  "properties": {
    "iso:country":"DE",
    "sg:address":"Lehmkuhlenweg 34",
    "sg:city":"L\u00fcbeck",
    "sg:phone":"+49 451/401208",
    "sg:postcode":"23554",
    "sg:province":"Schleswig-Holstein",
    "wof:name":"Magdalena Galla",
    "wof:placetype":"venue"
},
  "geometry": {"coordinates":[10.6740751266,53.890827179],"type":"Point"}
}