{
  "type": "Feature",
  "properties": {
    "iso:country":"DE",
    "sg:address":"Edergasse 10",
    "sg:city":"V\u00f6hl",
    "sg:phone":"+49 6454/288",
    "sg:postcode":"34516",
    "sg:province":"Hessen",
    "wof:name":"Heinrich Denhof & Co. Bauunternehmung",
    "wof:placetype":"venue"
},
  "geometry": {"coordinates":[8.8953113556,51.1834144592],"type":"Point"}
}