{
  "type": "Feature",
  "properties": {
    "iso:country":"DE",
    "sg:address":"Bahnstr. 28",
    "sg:city":"Steinbach",
    "sg:phone":"+49 6171/85911",
    "sg:postcode":"61449",
    "sg:province":"Hessen",
    "wof:name":"Hotel-restaurant Stadt Steinbach",
    "wof:placetype":"venue"
},
  "geometry": {"coordinates":[8.574968338,50.1690483093],"type":"Point"}
}