{
  "type": "Feature",
  "properties": {
    "iso:country":"DE",
    "sg:address":"Theodor-Heuss-Ring 56",
    "sg:city":"Dietzenbach",
    "sg:phone":"+49 4960/748081",
    "sg:postcode":"63128",
    "sg:province":"Hessen",
    "wof:name":"Phone Partner Gmbh",
    "wof:placetype":"venue"
},
  "geometry": {"coordinates":[8.7890176773,50.0195350647],"type":"Point"}
}