{
  "type": "Feature",
  "properties": {
    "iso:country":"DE",
    "sg:address":"Rathausgasse 4",
    "sg:city":"Sigmaringen",
    "sg:phone":"+49 7571/12115",
    "sg:postcode":"72488",
    "sg:province":"Baden-W\u00fcrttemberg",
    "wof:name":"Albert Biendorfer",
    "wof:placetype":"venue"
},
  "geometry": {"coordinates":[9.2173013687,48.0868606567],"type":"Point"}
}