{
  "type": "Feature",
  "properties": {
    "iso:country":"DE",
    "sg:address":"Sengenholzer Weg 15",
    "sg:city":"Heiligenhaus",
    "sg:phone":"+49 2054/4136",
    "sg:postcode":"42579",
    "sg:province":"Nordrhein-Westfalen",
    "wof:name":"Reisedienst B\u00e4dtker Gmbh & Co.",
    "wof:placetype":"venue"
},
  "geometry": {"coordinates":[6.947453022,51.34740448],"type":"Point"}
}