{
  "type": "Feature",
  "properties": {
    "iso:country":"DE",
    "sg:address":"Sandbergstr. 3",
    "sg:city":"Unteregg",
    "sg:phone":"+49 8269/1430",
    "sg:postcode":"87782",
    "sg:province":"Bayern",
    "wof:name":"Walter Sontheimer",
    "wof:placetype":"venue"
},
  "geometry": {"coordinates":[10.505428,47.962315],"type":"Point"}
}