{
  "type": "Feature",
  "properties": {
    "iso:country":"DE",
    "sg:address":"Pr\u00e4lat-Lutz-Str. 21",
    "sg:city":"Friedrichshafen",
    "sg:phone":"+49 7541/50270",
    "sg:postcode":"88048",
    "sg:province":"Baden-W\u00fcrttemberg",
    "wof:name":"M. Brielmaier",
    "wof:placetype":"venue"
},
  "geometry": {"coordinates":[9.515987,47.693188],"type":"Point"}
}