{
  "type": "Feature",
  "properties": {
    "iso:country":"DE",
    "sg:address":"Am Rilchenberg 41",
    "sg:city":"Idar-Oberstein",
    "sg:phone":"+49 6781/28058",
    "sg:postcode":"55743",
    "sg:province":"Rheinland-Pfalz",
    "wof:name":"Matthias U. Inge Fuhr",
    "wof:placetype":"venue"
},
  "geometry": {"coordinates":[7.305603981,49.7119026184],"type":"Point"}
}