{
  "type": "Feature",
  "properties": {
    "iso:country":"DE",
    "sg:address":"Basler Str. 3 b",
    "sg:city":"L\u00f6rrach",
    "sg:phone":"+49 7621/8545",
    "sg:postcode":"79540",
    "sg:province":"Baden-W\u00fcrttemberg",
    "wof:name":"Dr. Med. Anna J\u00e4ger",
    "wof:placetype":"venue"
},
  "geometry": {"coordinates":[7.6556091309,47.5957260132],"type":"Point"}
}