{
  "type": "Feature",
  "properties": {
    "iso:country":"DE",
    "sg:address":"Arndtstr 2",
    "sg:city":"Karlsruhe",
    "sg:phone":"+49 721/882844",
    "sg:postcode":"76199",
    "sg:province":"Baden-W\u00fcrttemberg",
    "wof:name":"Lettertech Ing.-b\u00fcro Roland Matt",
    "wof:placetype":"venue"
},
  "geometry": {"coordinates":[8.4048,48.970421],"type":"Point"}
}