{
  "type": "Feature",
  "properties": {
    "iso:country":"DE",
    "sg:address":"Hospitalstr. 2",
    "sg:city":"Ruhland",
    "sg:phone":"+49 35752/2336",
    "sg:postcode":"01945",
    "sg:province":"Brandenburg",
    "wof:name":"Werner Kranke",
    "wof:placetype":"venue"
},
  "geometry": {"coordinates":[13.868161,51.458641],"type":"Point"}
}