{
  "type": "Feature",
  "properties": {
    "iso:country":"DE",
    "sg:address":"Niederhagen 6",
    "sg:city":"Wermelskirchen",
    "sg:phone":"+49 2196/80625",
    "sg:postcode":"42929",
    "sg:province":"Nordrhein-Westfalen",
    "wof:name":"Hermann Schmitz",
    "wof:placetype":"venue"
},
  "geometry": {"coordinates":[7.283657074,51.0973052979],"type":"Point"}
}