{
  "type": "Feature",
  "properties": {
    "iso:country":"DE",
    "sg:address":"Alleestr. 13",
    "sg:city":"Bottrop",
    "sg:phone":"+49 2045/408776",
    "sg:postcode":"46244",
    "sg:province":"Nordrhein-Westfalen",
    "wof:name":"Dea Tankstelle",
    "wof:placetype":"venue"
},
  "geometry": {"coordinates":[6.9154319763,51.6048240662],"type":"Point"}
}