{
  "type": "Feature",
  "properties": {
    "iso:country":"DE",
    "sg:address":"Lahnstr. 86",
    "sg:city":"Berlin",
    "sg:phone":"+49 30/6847005",
    "sg:postcode":"12055",
    "sg:province":"Berlin",
    "wof:name":"Paul M\u00fcller Inh. Joachim K\u00e4mmerer",
    "wof:placetype":"venue"
},
  "geometry": {"coordinates":[13.44381,52.468002],"type":"Point"}
}