{
  "type": "Feature",
  "properties": {
    "iso:country":"DE",
    "sg:address":"Arndtstr. 2-6",
    "sg:city":"Trappenkamp",
    "sg:phone":"+49 4943/2391260",
    "sg:postcode":"24610",
    "sg:province":"Schleswig-Holstein",
    "wof:name":"Hako - Werke Gmbh",
    "wof:placetype":"venue"
},
  "geometry": {"coordinates":[10.211565,54.042351],"type":"Point"}
}