{
  "type": "Feature",
  "properties": {
    "iso:country":"DE",
    "sg:address":"Ernststr. 56",
    "sg:city":"Berlin",
    "sg:phone":"+49 30/4326596",
    "sg:postcode":"13509",
    "sg:province":"Berlin",
    "wof:name":"Peter B\u00fcge",
    "wof:placetype":"venue"
},
  "geometry": {"coordinates":[13.300671,52.583275],"type":"Point"}
}