{
  "type": "Feature",
  "properties": {
    "iso:country":"DE",
    "sg:address":"Am Katzenstein 23",
    "sg:city":"We\u00dfling",
    "sg:phone":"+49 8153/1050",
    "sg:postcode":"82234",
    "sg:province":"Bayern",
    "wof:name":"Dieter Maus Ingenieur",
    "wof:placetype":"venue"
},
  "geometry": {"coordinates":[11.2466974258,48.0768966675],"type":"Point"}
}