{
  "type": "Feature",
  "properties": {
    "iso:country":"DE",
    "sg:address":"Ziegeleiweg 16",
    "sg:city":"Sch\u00f6nkirchen",
    "sg:phone":"+49 4348/1091",
    "sg:postcode":"24232",
    "sg:province":"Schleswig-Holstein",
    "wof:name":"Marinex Gmbh",
    "wof:placetype":"venue"
},
  "geometry": {"coordinates":[10.227337,54.341919],"type":"Point"}
}