{
  "type": "Feature",
  "properties": {
    "iso:country":"DE",
    "sg:address":"Alter Hellweg 40 a",
    "sg:city":"Paderborn",
    "sg:phone":"+49 5251/91113",
    "sg:postcode":"33106",
    "sg:province":"Nordrhein-Westfalen",
    "wof:name":"Agatha Hartmann",
    "wof:placetype":"venue"
},
  "geometry": {"coordinates":[8.697117,51.686337],"type":"Point"}
}