{
  "type": "Feature",
  "properties": {
    "iso:country":"DE",
    "sg:address":"Freiberger Str. 1",
    "sg:city":"Niedersch\u00f6na",
    "sg:postcode":"09600",
    "sg:province":"Sachsen",
    "wof:name":"Agrarbau Niedersch\u00f6na Gmbh",
    "wof:placetype":"venue"
},
  "geometry": {"coordinates":[13.4229230881,50.9623641968],"type":"Point"}
}