{
  "type": "Feature",
  "properties": {
    "iso:country":"DE",
    "sg:address":"Hagener Str. 13",
    "sg:city":"Bad Pyrmont",
    "sg:postcode":"31812",
    "sg:province":"Niedersachsen",
    "wof:name":"Meyer Verm\u00f6gens- Verwaltungsges. Mbh",
    "wof:placetype":"venue"
},
  "geometry": {"coordinates":[9.2319116592,51.9864845276],"type":"Point"}
}