{
  "type": "Feature",
  "properties": {
    "iso:country":"DE",
    "sg:address":"Chausseestr. 26",
    "sg:city":"Rauen",
    "sg:phone":"+49 3361/710344",
    "sg:postcode":"15518",
    "sg:province":"Brandenburg",
    "wof:name":"Eberhard Berndt",
    "wof:placetype":"venue"
},
  "geometry": {"coordinates":[14.0250339508,52.3279914856],"type":"Point"}
}