{
  "type": "Feature",
  "properties": {
    "iso:country":"DE",
    "sg:address":"Am Hang 1 b",
    "sg:city":"Molfsee",
    "sg:phone":"+49 431/803407",
    "sg:postcode":"24113",
    "sg:province":"Schleswig-Holstein",
    "wof:name":"Wilfried Rosenkranz E. Kfm.",
    "wof:placetype":"venue"
},
  "geometry": {"coordinates":[10.082599,54.285427],"type":"Point"}
}