{
  "type": "Feature",
  "properties": {
    "iso:country":"DE",
    "sg:address":"Wattstr. 30",
    "sg:city":"Mannheim",
    "sg:phone":"+49 621/854028",
    "sg:postcode":"68199",
    "sg:province":"Baden-W\u00fcrttemberg",
    "wof:name":"Joh. Gieseler Gmbh & Co. Kg",
    "wof:placetype":"venue"
},
  "geometry": {"coordinates":[8.4988775253,49.4635162354],"type":"Point"}
}