{
  "type": "Feature",
  "properties": {
    "iso:country":"DE",
    "sg:address":"Kirchstr. 44",
    "sg:city":"Gau-Algesheim",
    "sg:phone":"+49 6725/2742",
    "sg:postcode":"55435",
    "sg:province":"Rheinland-Pfalz",
    "wof:name":"Theo Mayer",
    "wof:placetype":"venue"
},
  "geometry": {"coordinates":[8.0123023987,49.9519348145],"type":"Point"}
}