{
  "type": "Feature",
  "properties": {
    "iso:country":"DE",
    "sg:address":"Kirchtalstr. 4",
    "sg:city":"V\u00f6hl",
    "sg:phone":"+49 5635/604",
    "sg:postcode":"34516",
    "sg:province":"Hessen",
    "wof:name":"Friedrich Denhof",
    "wof:placetype":"venue"
},
  "geometry": {"coordinates":[8.872486,51.158966],"type":"Point"}
}