{
  "type": "Feature",
  "properties": {
    "iso:country":"DE",
    "sg:address":"Waldstr. 11",
    "sg:city":"Haldensleben",
    "sg:phone":"+49 3904/41361",
    "sg:postcode":"39340",
    "sg:province":"Sachsen-Anhalt",
    "wof:name":"Kurt-j\u00fcrgen Fieseler",
    "wof:placetype":"venue"
},
  "geometry": {"coordinates":[11.4184341431,52.2651023865],"type":"Point"}
}