{
  "type": "Feature",
  "properties": {
    "iso:country":"DE",
    "sg:address":"Rathausstr. 1",
    "sg:city":"Vilgertshofen",
    "sg:phone":"+49 8194/222",
    "sg:postcode":"86946",
    "sg:province":"Bayern",
    "wof:name":"Lorenz Erdt",
    "wof:placetype":"venue"
},
  "geometry": {"coordinates":[10.917864,47.966858],"type":"Point"}
}