{
  "type": "Feature",
  "properties": {
    "iso:country":"DE",
    "sg:address":"Weiherstr. 16a",
    "sg:city":"Pfinztal",
    "sg:phone":"+49 721/460461",
    "sg:postcode":"76327",
    "sg:province":"Baden-W\u00fcrttemberg",
    "wof:name":"Paula Winkler Hebamme",
    "wof:placetype":"venue"
},
  "geometry": {"coordinates":[8.528513,49.00798],"type":"Point"}
}