{
  "type": "Feature",
  "properties": {
    "iso:country":"DE",
    "sg:address":"Am Raupenstein 10",
    "sg:city":"Lindenfels",
    "sg:phone":"+49 6255/788",
    "sg:postcode":"64678",
    "sg:province":"Hessen",
    "wof:name":"Kopp Gmbh Werkzeugschleiferei",
    "wof:placetype":"venue"
},
  "geometry": {"coordinates":[8.7815227509,49.706905365],"type":"Point"}
}