{
  "type": "Feature",
  "properties": {
    "iso:country":"DE",
    "sg:address":"Hauptstr. 54",
    "sg:city":"Blindheim",
    "sg:phone":"+49 9074/1357",
    "sg:postcode":"89434",
    "sg:province":"Bayern",
    "wof:name":"Kath. Pfarramt St. Vitus",
    "wof:placetype":"venue"
},
  "geometry": {"coordinates":[10.6061620712,48.6492118835],"type":"Point"}
}