{
  "type": "Feature",
  "properties": {
    "iso:country":"DE",
    "sg:address":"Sudetenstr. 3",
    "sg:city":"Hadamar",
    "sg:phone":"+49 6433/91066",
    "sg:postcode":"65589",
    "sg:province":"Hessen",
    "wof:name":"A. Dengler",
    "wof:placetype":"venue"
},
  "geometry": {"coordinates":[8.033168,50.432747],"type":"Point"}
}