{
  "type": "Feature",
  "properties": {
    "iso:country":"DE",
    "sg:address":"Herrnstr. 61",
    "sg:city":"Offenbach",
    "sg:phone":"+49 69/816690",
    "sg:postcode":"63065",
    "sg:province":"Hessen",
    "wof:name":"Lothar M\u00fcller",
    "wof:placetype":"venue"
},
  "geometry": {"coordinates":[8.7617731094,50.1085205078],"type":"Point"}
}