{
  "type": "Feature",
  "properties": {
    "iso:country":"DE",
    "sg:address":"Am Einkaufszentrum",
    "sg:city":"Bochum",
    "sg:phone":"+49 234/235131",
    "sg:postcode":"44791",
    "sg:province":"Nordrhein-Westfalen",
    "wof:name":"H & M Hennes & Mauritz Gmbh",
    "wof:placetype":"venue"
},
  "geometry": {"coordinates":[7.277032,51.495064],"type":"Point"}
}