{
  "type": "Feature",
  "properties": {
    "iso:country":"DE",
    "sg:address":"An der Hecke 9",
    "sg:city":"Eppendorf",
    "sg:phone":"+49 37293/472",
    "sg:postcode":"09575",
    "sg:province":"Sachsen",
    "wof:name":"Siegfried R\u00fcger",
    "wof:placetype":"venue"
},
  "geometry": {"coordinates":[13.230218,50.795414],"type":"Point"}
}