{
  "type": "Feature",
  "properties": {
    "iso:country":"DE",
    "sg:address":"M\u00f6llerkamp 20",
    "sg:city":"Seelze",
    "sg:phone":"+49 511/487070",
    "sg:postcode":"30926",
    "sg:province":"Niedersachsen",
    "wof:name":"Appartments Wohnpark Letter",
    "wof:placetype":"venue"
},
  "geometry": {"coordinates":[9.6376438141,52.4005241394],"type":"Point"}
}