{
  "type": "Feature",
  "properties": {
    "iso:country":"DE",
    "sg:address":"Hermann-L\u00f6ns-Str. 17",
    "sg:city":"Magdeburg",
    "sg:phone":"+49 391/6312081",
    "sg:postcode":"39116",
    "sg:province":"Sachsen-Anhalt",
    "wof:name":"Werner Elspa\u00df",
    "wof:placetype":"venue"
},
  "geometry": {"coordinates":[11.589723,52.103298],"type":"Point"}
}