{
  "type": "Feature",
  "properties": {
    "iso:country":"DE",
    "sg:address":"Eiffestr. 612",
    "sg:city":"Hamburg",
    "sg:phone":"+49 40/218063",
    "sg:postcode":"20537",
    "sg:province":"Hamburg",
    "wof:name":"Croque Lagune",
    "wof:placetype":"venue"
},
  "geometry": {"coordinates":[10.0571937561,53.5510101318],"type":"Point"}
}