{
  "type": "Feature",
  "properties": {
    "iso:country":"DE",
    "sg:address":"Schottenstr. 45",
    "sg:city":"Konstanz",
    "sg:phone":"+49 7531/23897",
    "sg:postcode":"78462",
    "sg:province":"Baden-W\u00fcrttemberg",
    "wof:name":"Willi Brugger",
    "wof:placetype":"venue"
},
  "geometry": {"coordinates":[9.171861,47.66465],"type":"Point"}
}