{
  "type": "Feature",
  "properties": {
    "iso:country":"DE",
    "sg:address":"W\u00e4chterstr. 36",
    "sg:city":"Leipzig",
    "sg:phone":"+49 341/9606181",
    "sg:postcode":"04107",
    "sg:province":"Sachsen",
    "wof:name":"Dr. Med. Christine Wolff",
    "wof:placetype":"venue"
},
  "geometry": {"coordinates":[12.363806,51.332985],"type":"Point"}
}