{
  "type": "Feature",
  "properties": {
    "iso:country":"DE",
    "sg:address":"D\u00f6lzschener Str. 47",
    "sg:city":"Dresden",
    "sg:phone":"+49 351/425560",
    "sg:postcode":"01159",
    "sg:province":"Sachsen",
    "wof:name":"Montagewerk Gmbh",
    "wof:placetype":"venue"
},
  "geometry": {"coordinates":[13.6979084015,51.0338592529],"type":"Point"}
}