{
  "type": "Feature",
  "properties": {
    "iso:country":"DE",
    "sg:address":"Bu\u00dfmannshausen",
    "sg:city":"Bu\u00dfmannshausen",
    "sg:phone":"+49 7353/2022",
    "sg:postcode":"88477",
    "sg:province":"Baden-W\u00fcrttemberg",
    "wof:name":"Raiffeisenbank Rottal Eg",
    "wof:placetype":"venue"
},
  "geometry": {"coordinates":[9.954682,48.198257],"type":"Point"}
}