{
  "type": "Feature",
  "properties": {
    "iso:country":"DE",
    "sg:address":"Bismarckstr. 109",
    "sg:city":"Pirmasens",
    "sg:phone":"+49 6331/63367",
    "sg:postcode":"66953",
    "sg:province":"Rheinland-Pfalz",
    "wof:name":"Hans Werner Ulrich Kg Rohako Rohst.-handels-k.",
    "wof:placetype":"venue"
},
  "geometry": {"coordinates":[7.597917,49.211407],"type":"Point"}
}