{
  "type": "Feature",
  "properties": {
    "iso:country":"DE",
    "sg:address":"Steinbeisstr. 3",
    "sg:city":"Leonberg",
    "sg:phone":"+49 7152/22126",
    "sg:postcode":"71229",
    "sg:province":"Baden-W\u00fcrttemberg",
    "wof:name":"Teppich Magazin Fachmarkt F\u00fcr Bodenbel\u00e4ge Und Heim-",
    "wof:placetype":"venue"
},
  "geometry": {"coordinates":[9.0039186478,48.7982254028],"type":"Point"}
}