{
  "type": "Feature",
  "properties": {
    "iso:country":"DE",
    "sg:address":"H\u00fcgelstr. 79",
    "sg:city":"Frankfurt",
    "sg:phone":"+49 69/521280",
    "sg:postcode":"60433",
    "sg:province":"Hessen",
    "wof:name":"Bernd Obe",
    "wof:placetype":"venue"
},
  "geometry": {"coordinates":[8.6726837158,50.1491661072],"type":"Point"}
}