{
  "type": "Feature",
  "properties": {
    "iso:country":"DE",
    "sg:address":"Eulenkamp 11",
    "sg:city":"Gehrden",
    "sg:phone":"+49 5108/2116",
    "sg:postcode":"30989",
    "sg:province":"Niedersachsen",
    "wof:name":"Dorothea Buckenberger Rechtsanw\u00e4ltin",
    "wof:placetype":"venue"
},
  "geometry": {"coordinates":[9.6045446396,52.3175201416],"type":"Point"}
}