{
  "type": "Feature",
  "properties": {
    "iso:country":"DE",
    "sg:address":"Rom 15a",
    "sg:city":"Bocholt",
    "sg:phone":"+49 2871/222243",
    "sg:postcode":"46395",
    "sg:province":"Nordrhein-Westfalen",
    "wof:name":"G. Und R. Iding",
    "wof:placetype":"venue"
},
  "geometry": {"coordinates":[6.59591,51.836117],"type":"Point"}
}