{
  "type": "Feature",
  "properties": {
    "iso:country":"DE",
    "sg:address":"Finkenweg 5",
    "sg:city":"Wertingen",
    "sg:phone":"+49 8272/2642",
    "sg:postcode":"86637",
    "sg:province":"Bayern",
    "wof:name":"Tobias Munz",
    "wof:placetype":"venue"
},
  "geometry": {"coordinates":[10.672155,48.559437],"type":"Point"}
}