{
  "type": "Feature",
  "properties": {
    "iso:country":"DE",
    "sg:address":"Untere Donnerbergstr. 55",
    "sg:city":"Stolberg",
    "sg:phone":"+49 2402/82104",
    "sg:postcode":"52222",
    "sg:province":"Nordrhein-Westfalen",
    "wof:name":"Dr. Wolfgang Textor Und Vliex",
    "wof:placetype":"venue"
},
  "geometry": {"coordinates":[6.2334218025,50.7765769958],"type":"Point"}
}