{
  "type": "Feature",
  "properties": {
    "iso:country":"DE",
    "sg:address":"Richterstr. 37",
    "sg:city":"Erlangen",
    "sg:phone":"+49 9131/52100",
    "sg:postcode":"91052",
    "sg:province":"Bayern",
    "wof:name":"Kupferer Elektronische Regel- Bausteine Gmbh",
    "wof:placetype":"venue"
},
  "geometry": {"coordinates":[11.041076,49.593571],"type":"Point"}
}