{
  "type": "Feature",
  "properties": {
    "iso:country":"DE",
    "sg:address":"Zeiligstr. 2",
    "sg:city":"Forst",
    "sg:phone":"+49 7251/82566",
    "sg:postcode":"76694",
    "sg:province":"Baden-W\u00fcrttemberg",
    "wof:name":"Zenker Hausbau Gmbh & Co.",
    "wof:placetype":"venue"
},
  "geometry": {"coordinates":[8.585425,49.150478],"type":"Point"}
}