{
  "type": "Feature",
  "properties": {
    "iso:country":"DE",
    "sg:address":"Moltrechtstr. 25",
    "sg:city":"Leipzig",
    "sg:phone":"+49 341/6512617",
    "sg:postcode":"04316",
    "sg:province":"Sachsen",
    "wof:name":"Karl-heinz Matthes",
    "wof:placetype":"venue"
},
  "geometry": {"coordinates":[12.43843,51.325275],"type":"Point"}
}