{
  "type": "Feature",
  "properties": {
    "iso:country":"DE",
    "sg:city":"Coppenbr\u00fcgge",
    "sg:phone":"+49 4951/568055",
    "sg:postcode":"31863",
    "sg:province":"Niedersachsen",
    "wof:name":"Kreissparkasse Hameln",
    "wof:placetype":"venue"
},
  "geometry": {"coordinates":[9.549714,52.117485],"type":"Point"}
}