{
  "type": "Feature",
  "properties": {
    "iso:country":"DE",
    "sg:address":"D'horner Str. 37",
    "sg:city":"Langerwehe",
    "sg:phone":"+49 2423/1529",
    "sg:postcode":"52379",
    "sg:province":"Nordrhein-Westfalen",
    "wof:name":"Willi Schrandt",
    "wof:placetype":"venue"
},
  "geometry": {"coordinates":[6.35853,50.796028],"type":"Point"}
}