{
  "type": "Feature",
  "properties": {
    "iso:country":"DE",
    "sg:address":"Obermohrer Str.",
    "sg:city":"Niedermohr",
    "sg:postcode":"66879",
    "sg:province":"Rheinland-Pfalz",
    "wof:name":"Kath. Pfarrb\u00fccherei Reuschbach",
    "wof:placetype":"venue"
},
  "geometry": {"coordinates":[7.529775,49.456398],"type":"Point"}
}