{
  "type": "Feature",
  "properties": {
    "iso:country":"DE",
    "sg:address":"Badstr. 7",
    "sg:city":"Waldshut-Tiengen",
    "sg:phone":"+49 7741/2383",
    "sg:postcode":"79761",
    "sg:province":"Baden-W\u00fcrttemberg",
    "wof:name":"Rita Indlekofer",
    "wof:placetype":"venue"
},
  "geometry": {"coordinates":[8.26694,47.631195],"type":"Point"}
}