{
  "type": "Feature",
  "properties": {
    "iso:country":"DE",
    "sg:address":"Klingleweg 8",
    "sg:city":"Meersburg",
    "sg:phone":"+49 7532/43200",
    "sg:postcode":"88709",
    "sg:province":"Baden-W\u00fcrttemberg",
    "wof:name":"Wolfgang W\u00e4lischmiller Ingenieur",
    "wof:placetype":"venue"
},
  "geometry": {"coordinates":[9.2750272751,47.6950874329],"type":"Point"}
}