{
  "type": "Feature",
  "properties": {
    "iso:country":"DE",
    "sg:address":"Industriestr. 2",
    "sg:city":"Eltmann",
    "sg:phone":"+49 9522/710",
    "sg:postcode":"97483",
    "sg:province":"Bayern",
    "wof:name":"Fag Komponenten Ag",
    "wof:placetype":"venue"
},
  "geometry": {"coordinates":[10.66922,49.98222],"type":"Point"}
}