{
  "type": "Feature",
  "properties": {
    "iso:country":"DE",
    "sg:address":"Am Waldeck 43 A",
    "sg:city":"Kelkheim",
    "sg:phone":"+49 6195/2882",
    "sg:postcode":"65779",
    "sg:province":"Hessen",
    "wof:name":"Hans Peter Michels Architekt",
    "wof:placetype":"venue"
},
  "geometry": {"coordinates":[8.445099,50.131317],"type":"Point"}
}