{
  "type": "Feature",
  "properties": {
    "iso:country":"DE",
    "sg:address":"Burgstr. 16",
    "sg:city":"Pottenstein",
    "sg:phone":"+49 9243/365",
    "sg:postcode":"91278",
    "sg:province":"Bayern",
    "wof:name":"G\u00e4sthaus Harbich",
    "wof:placetype":"venue"
},
  "geometry": {"coordinates":[11.4119768143,49.7685317993],"type":"Point"}
}