{
  "type": "Feature",
  "properties": {
    "iso:country":"DE",
    "sg:address":"Leipziger Str. 1",
    "sg:city":"Koblenz",
    "sg:phone":"+49 261/53488",
    "sg:postcode":"56075",
    "sg:province":"Rheinland-Pfalz",
    "wof:name":"G. Leufgen",
    "wof:placetype":"venue"
},
  "geometry": {"coordinates":[7.564125,50.338242],"type":"Point"}
}