{
  "type": "Feature",
  "properties": {
    "iso:country":"DE",
    "sg:address":"Annweilerstr. 25",
    "sg:city":"Landau",
    "sg:phone":"+49 6341/33449",
    "sg:postcode":"76829",
    "sg:province":"Rheinland-Pfalz",
    "wof:name":"Gertrud Und G\u00fcnter Sees",
    "wof:placetype":"venue"
},
  "geometry": {"coordinates":[8.100462,49.195057],"type":"Point"}
}