{
  "type": "Feature",
  "properties": {
    "iso:country":"DE",
    "sg:address":"Oberndorf",
    "sg:city":"Zeilarn",
    "sg:phone":"+49 8572/8723",
    "sg:postcode":"84367",
    "sg:province":"Bayern",
    "wof:name":"A. Sendl",
    "wof:placetype":"venue"
},
  "geometry": {"coordinates":[12.865125,48.283474],"type":"Point"}
}