{
  "type": "Feature",
  "properties": {
    "iso:country":"DE",
    "sg:address":"Bubendorfer Str. 42",
    "sg:city":"Frohburg",
    "sg:phone":"+49 34348/51631",
    "sg:postcode":"04654",
    "sg:province":"Sachsen",
    "wof:name":"Franke",
    "wof:placetype":"venue"
},
  "geometry": {"coordinates":[12.5680398941,51.0585784912],"type":"Point"}
}