{
  "type": "Feature",
  "properties": {
    "iso:country":"DE",
    "sg:address":"Baalsdorfer Str. 16",
    "sg:city":"Leipzig",
    "sg:phone":"+49 341/6513305",
    "sg:postcode":"04288",
    "sg:province":"Sachsen",
    "wof:name":"E. Scholz",
    "wof:placetype":"venue"
},
  "geometry": {"coordinates":[12.468134,51.312416],"type":"Point"}
}