{
  "type": "Feature",
  "properties": {
    "iso:country":"DE",
    "sg:address":"Industriestr. 4",
    "sg:city":"Sohland",
    "sg:postcode":"02689",
    "sg:province":"Sachsen",
    "wof:name":"Neckermann Versand Ag",
    "wof:placetype":"venue"
},
  "geometry": {"coordinates":[14.4278097153,51.0452690125],"type":"Point"}
}