{
  "type": "Feature",
  "properties": {
    "iso:country":"DE",
    "sg:address":"Hirtenteichstr.",
    "sg:city":"Essingen",
    "sg:phone":"+49 7365/296",
    "sg:postcode":"73457",
    "sg:province":"Baden-W\u00fcrttemberg",
    "wof:name":"Hirtenteich Campingplatz",
    "wof:placetype":"venue"
},
  "geometry": {"coordinates":[9.985615,48.785095],"type":"Point"}
}