{
  "type": "Feature",
  "properties": {
    "iso:country":"DE",
    "sg:address":"Puschkinstr. 6",
    "sg:city":"Basdorf",
    "sg:phone":"+49 33397/21191",
    "sg:postcode":"16352",
    "sg:province":"Brandenburg",
    "wof:name":"K. Tepper",
    "wof:placetype":"venue"
},
  "geometry": {"coordinates":[13.4393873215,52.7170600891],"type":"Point"}
}