{
  "type": "Feature",
  "properties": {
    "iso:country":"DE",
    "sg:address":"Schulstr. 70",
    "sg:city":"L\u00f6rrach",
    "sg:phone":"+49 7621/12601",
    "sg:postcode":"79540",
    "sg:province":"Baden-W\u00fcrttemberg",
    "wof:name":"Seiberle Und Marschner",
    "wof:placetype":"venue"
},
  "geometry": {"coordinates":[7.6614599228,47.6019210815],"type":"Point"}
}