{
  "type": "Feature",
  "properties": {
    "iso:country":"DE",
    "sg:address":"Leher Heerstr. 111 B",
    "sg:city":"Bremen",
    "sg:phone":"+49 421/2047420",
    "sg:postcode":"28359",
    "sg:province":"Bremen",
    "wof:name":"Elfriede Wegner Steuerberaterin",
    "wof:placetype":"venue"
},
  "geometry": {"coordinates":[8.8817243576,53.1009864807],"type":"Point"}
}