{
  "type": "Feature",
  "properties": {
    "iso:country":"DE",
    "sg:address":"Sollingstr. 31",
    "sg:city":"Moringen",
    "sg:phone":"+49 5555/505",
    "sg:postcode":"37186",
    "sg:province":"Niedersachsen",
    "wof:name":"Cafe Zum Backofen",
    "wof:placetype":"venue"
},
  "geometry": {"coordinates":[9.7881689072,51.7354660034],"type":"Point"}
}