{
  "type": "Feature",
  "properties": {
    "iso:country":"DE",
    "sg:address":"Nevinghoff 25",
    "sg:city":"M\u00fcnster",
    "sg:phone":"+49 4925/12880",
    "sg:postcode":"48147",
    "sg:province":"Nordrhein-Westfalen",
    "wof:name":"Sparkasse Informatik Gmbh & Co. Kg",
    "wof:placetype":"venue"
},
  "geometry": {"coordinates":[7.632849,51.985046],"type":"Point"}
}