{
  "type": "Feature",
  "properties": {
    "iso:country":"DE",
    "sg:address":"Am Hang 18",
    "sg:city":"Odelzhausen",
    "sg:phone":"+49 8134/997626",
    "sg:postcode":"85235",
    "sg:province":"Bayern",
    "wof:name":"Ingo Treue",
    "wof:placetype":"venue"
},
  "geometry": {"coordinates":[11.2323465347,48.3306465149],"type":"Point"}
}