{
  "type": "Feature",
  "properties": {
    "iso:country":"DE",
    "sg:address":"Edmund-ter-Meer-Str. 1a",
    "sg:city":"K\u00f6ln",
    "sg:phone":"+49 221/662348",
    "sg:postcode":"51061",
    "sg:province":"Nordrhein-Westfalen",
    "wof:name":"Hans Paffrath Autoreparaturen",
    "wof:placetype":"venue"
},
  "geometry": {"coordinates":[6.9960818291,50.998298645],"type":"Point"}
}