{
  "type": "Feature",
  "properties": {
    "iso:country":"DE",
    "sg:address":"Ball 11",
    "sg:city":"Bergisch Gladbach",
    "sg:phone":"+49 2204/83496",
    "sg:postcode":"51429",
    "sg:province":"Nordrhein-Westfalen",
    "wof:name":"Restaurant Trattoria Napoletana",
    "wof:placetype":"venue"
},
  "geometry": {"coordinates":[7.1906919479,50.9868812561],"type":"Point"}
}