{
  "type": "Feature",
  "properties": {
    "iso:country":"DE",
    "sg:address":"Am Schillerplatz 2",
    "sg:city":"Backnang",
    "sg:phone":"+49 7191/960685",
    "sg:postcode":"71522",
    "sg:province":"Baden-W\u00fcrttemberg",
    "wof:name":"Audens Telecommunications Consulting Gmbh",
    "wof:placetype":"venue"
},
  "geometry": {"coordinates":[9.430521965,48.9455451965],"type":"Point"}
}