{
  "type": "Feature",
  "properties": {
    "iso:country":"DE",
    "sg:address":"P\u00fcttlinger Str.",
    "sg:city":"V\u00f6lklingen",
    "sg:phone":"+49 6898/91110",
    "sg:postcode":"66333",
    "sg:province":"Saarland",
    "wof:name":"Komeg Industrielle Me\u00dftechnik Gmbh",
    "wof:placetype":"venue"
},
  "geometry": {"coordinates":[6.8740549088,49.2688446045],"type":"Point"}
}