{
  "type": "Feature",
  "properties": {
    "iso:country":"DE",
    "sg:address":"Comeniusstr. 68",
    "sg:city":"Dresden",
    "sg:phone":"+49 351/3108322",
    "sg:postcode":"01309",
    "sg:province":"Sachsen",
    "wof:name":"Bruno Sommerfeld",
    "wof:placetype":"venue"
},
  "geometry": {"coordinates":[13.777998,51.038258],"type":"Point"}
}