{
  "type": "Feature",
  "properties": {
    "iso:country":"DE",
    "sg:address":"Goethestr. 1",
    "sg:city":"Moers",
    "sg:phone":"+49 2841/18444",
    "sg:postcode":"47441",
    "sg:province":"Nordrhein-Westfalen",
    "wof:name":"Werner Jungblut Masseur",
    "wof:placetype":"venue"
},
  "geometry": {"coordinates":[6.63527,51.449848],"type":"Point"}
}