{
  "type": "Feature",
  "properties": {
    "iso:country":"DE",
    "sg:address":"Neuengammer Hausdeich 417a",
    "sg:city":"Hamburg",
    "sg:postcode":"21039",
    "sg:province":"Hamburg",
    "wof:name":"Helga Hamester Gmbh",
    "wof:placetype":"venue"
},
  "geometry": {"coordinates":[10.2080307007,53.4568939209],"type":"Point"}
}