{
  "type": "Feature",
  "properties": {
    "iso:country":"DE",
    "sg:address":"Kemnastr. 1",
    "sg:city":"Recklinghausen",
    "sg:phone":"+49 2361/25650",
    "sg:postcode":"45657",
    "sg:province":"Nordrhein-Westfalen",
    "wof:name":"Bernhard Wessels Sen. Kg",
    "wof:placetype":"venue"
},
  "geometry": {"coordinates":[7.193815,51.612427],"type":"Point"}
}