{
  "type": "Feature",
  "properties": {
    "iso:country":"DE",
    "sg:address":"Ihmerter Str. 308",
    "sg:city":"Hemer",
    "sg:phone":"+49 4923/7298990",
    "sg:postcode":"58675",
    "sg:province":"Nordrhein-Westfalen",
    "wof:name":"Escher & Co Gmbh",
    "wof:placetype":"venue"
},
  "geometry": {"coordinates":[7.735949,51.325207],"type":"Point"}
}