{
  "type": "Feature",
  "properties": {
    "iso:country":"DE",
    "sg:address":"Friedrich-Engels-Ring 12",
    "sg:city":"Neubrandenburg",
    "sg:phone":"+49 395/5822483",
    "sg:postcode":"17033",
    "sg:province":"Mecklenburg-Vorpommern",
    "wof:name":"Raiffeisenbank Neubrandenburg Eg",
    "wof:placetype":"venue"
},
  "geometry": {"coordinates":[13.26065,53.561127],"type":"Point"}
}