{
  "type": "Feature",
  "properties": {
    "iso:country":"DE",
    "sg:address":"Angerhofstr. 28",
    "sg:city":"Reichertshausen",
    "sg:phone":"+49 8441/2652",
    "sg:postcode":"85293",
    "sg:province":"Bayern",
    "wof:name":"Werner Fieten Handel Mit Abwasseranlagen",
    "wof:placetype":"venue"
},
  "geometry": {"coordinates":[11.5145225525,48.4670257568],"type":"Point"}
}