{
  "type": "Feature",
  "properties": {
    "iso:country":"DE",
    "sg:address":"Bahnhofstr. 3",
    "sg:city":"Neumarkt-Sankt Veit",
    "sg:phone":"+49 8639/8797",
    "sg:postcode":"84494",
    "sg:province":"Bayern",
    "wof:name":"Preitenwieser Gmbh",
    "wof:placetype":"venue"
},
  "geometry": {"coordinates":[12.507416,48.362125],"type":"Point"}
}