{
  "type": "Feature",
  "properties": {
    "iso:country":"DE",
    "sg:address":"Pontstr. 49",
    "sg:city":"Aachen",
    "sg:phone":"+49 241/803806",
    "sg:postcode":"52062",
    "sg:province":"Nordrhein-Westfalen",
    "wof:name":"Institut F\u00fcr Kunststoffverarbeitung",
    "wof:placetype":"venue"
},
  "geometry": {"coordinates":[6.081442,50.77845],"type":"Point"}
}