{
  "type": "Feature",
  "properties": {
    "iso:country":"DE",
    "sg:address":"Hauptstr. 19",
    "sg:city":"Ostseebad Binz",
    "sg:phone":"+49 38393/2437",
    "sg:postcode":"18609",
    "sg:province":"Mecklenburg-Vorpommern",
    "wof:name":"H. Moldenhauer",
    "wof:placetype":"venue"
},
  "geometry": {"coordinates":[13.613634,54.401291],"type":"Point"}
}