{
  "type": "Feature",
  "properties": {
    "iso:country":"DE",
    "sg:address":"Talstr. 40",
    "sg:city":"Waldfeucht",
    "sg:phone":"+49 2455/1022",
    "sg:postcode":"52525",
    "sg:province":"Nordrhein-Westfalen",
    "wof:name":"Ria Sonntag-blank Architektin",
    "wof:placetype":"venue"
},
  "geometry": {"coordinates":[6.018789,51.08131],"type":"Point"}
}