{
  "type": "Feature",
  "properties": {
    "iso:country":"DE",
    "sg:address":"Landsberger Str. 320",
    "sg:city":"M\u00fcnchen",
    "sg:phone":"+49 89/5467050",
    "sg:postcode":"80687",
    "sg:province":"Bayern",
    "wof:name":"Fernbuch Kg",
    "wof:placetype":"venue"
},
  "geometry": {"coordinates":[11.498388,48.143787],"type":"Point"}
}