{
  "type": "Feature",
  "properties": {
    "iso:country":"DE",
    "sg:address":"Fischerstr. 38",
    "sg:city":"Warendorf",
    "sg:phone":"+49 2581/6956",
    "sg:postcode":"48231",
    "sg:province":"Nordrhein-Westfalen",
    "wof:name":"K. Scholle",
    "wof:placetype":"venue"
},
  "geometry": {"coordinates":[7.9809908867,51.9579353333],"type":"Point"}
}