{
  "type": "Feature",
  "properties": {
    "iso:country":"DE",
    "sg:address":"Ringstr. 37 a",
    "sg:city":"\u00dcbersee",
    "sg:phone":"+49 8642/1231",
    "sg:postcode":"83236",
    "sg:province":"Bayern",
    "wof:name":"Gemeindeb\u00fccherei",
    "wof:placetype":"venue"
},
  "geometry": {"coordinates":[12.479234,47.818928],"type":"Point"}
}