{
  "type": "Feature",
  "properties": {
    "iso:country":"DE",
    "sg:address":"Lindower Str. 18",
    "sg:city":"Berlin",
    "sg:phone":"+49 30/4626161",
    "sg:postcode":"13347",
    "sg:province":"Berlin",
    "wof:name":"Georg Zey Bildhauer",
    "wof:placetype":"venue"
},
  "geometry": {"coordinates":[13.367657,52.543751],"type":"Point"}
}