{
  "type": "Feature",
  "properties": {
    "iso:country":"DE",
    "sg:address":"Altstadt 15",
    "sg:city":"Bad Br\u00fcckenau",
    "sg:phone":"+49 9741/2228",
    "sg:postcode":"97769",
    "sg:province":"Bayern",
    "wof:name":"R. Haydu",
    "wof:placetype":"venue"
},
  "geometry": {"coordinates":[9.7928886414,50.3110466003],"type":"Point"}
}