{
  "type": "Feature",
  "properties": {
    "iso:country":"DE",
    "sg:address":"Am Hochbeh\u00e4lter 3",
    "sg:city":"Wenzenbach",
    "sg:phone":"+49 9407/30357",
    "sg:postcode":"93173",
    "sg:province":"Bayern",
    "wof:name":"Hildebrand Hoch- Und Tiefbau Gmbh",
    "wof:placetype":"venue"
},
  "geometry": {"coordinates":[12.194062,49.058624],"type":"Point"}
}