{
  "type": "Feature",
  "properties": {
    "iso:country":"DE",
    "sg:address":"August-Bebel-Str. 9",
    "sg:city":"Br\u00fcel",
    "sg:phone":"+49 38483/20310",
    "sg:postcode":"19412",
    "sg:province":"Mecklenburg-Vorpommern",
    "wof:name":"Bernd Techentin Immobilienmakler",
    "wof:placetype":"venue"
},
  "geometry": {"coordinates":[11.7146558762,53.7385482788],"type":"Point"}
}