{
  "type": "Feature",
  "properties": {
    "iso:country":"DE",
    "sg:address":"Sattelplatz 7",
    "sg:city":"M\u00fcnster",
    "sg:phone":"+49 2501/5104",
    "sg:postcode":"48163",
    "sg:province":"Nordrhein-Westfalen",
    "wof:name":"Waltermann",
    "wof:placetype":"venue"
},
  "geometry": {"coordinates":[7.6040120125,51.8838729858],"type":"Point"}
}