{
  "type": "Feature",
  "properties": {
    "iso:country":"DE",
    "sg:address":"Bergstr. 90",
    "sg:city":"Dortmund",
    "sg:phone":"+49 231/857774",
    "sg:postcode":"44339",
    "sg:province":"Nordrhein-Westfalen",
    "wof:name":"Gastst\u00e4tte Zum Minister Stein",
    "wof:placetype":"venue"
},
  "geometry": {"coordinates":[7.4537138939,51.5514678955],"type":"Point"}
}