{
  "type": "Feature",
  "properties": {
    "iso:country":"DE",
    "sg:address":"Zellertalstr. 16",
    "sg:city":"Drachselsried",
    "sg:phone":"+49 9945/1002",
    "sg:postcode":"94256",
    "sg:province":"Bayern",
    "wof:name":"Kath. Pfarramt St. \u00c4gidius",
    "wof:placetype":"venue"
},
  "geometry": {"coordinates":[13.0105848312,49.1078262329],"type":"Point"}
}