{
  "type": "Feature",
  "properties": {
    "iso:country":"DE",
    "sg:address":"Bronsartstr. 4",
    "sg:city":"Hannover",
    "sg:phone":"+49 511/33959895",
    "sg:postcode":"30161",
    "sg:province":"Niedersachsen",
    "wof:name":"Heymeier Sanit\u00e4r- Und Heizungs Gmbh",
    "wof:placetype":"venue"
},
  "geometry": {"coordinates":[9.7388544083,52.3829841614],"type":"Point"}
}