{
  "type": "Feature",
  "properties": {
    "iso:country":"DE",
    "sg:address":"Postfach 1223",
    "sg:city":"Denkendorf",
    "sg:phone":"+49 711/3460666",
    "sg:postcode":"73767",
    "sg:province":"Baden-W\u00fcrttemberg",
    "wof:name":"La Dispensa Di Ulisse",
    "wof:placetype":"venue"
},
  "geometry": {"coordinates":[9.3172502518,48.6940994263],"type":"Point"}
}