{
  "type": "Feature",
  "properties": {
    "iso:country":"DE",
    "sg:address":"Seerosenstr. 3",
    "sg:city":"F\u00fcrth",
    "sg:phone":"+49 911/762925",
    "sg:postcode":"90765",
    "sg:province":"Bayern",
    "wof:name":"Leonhard Popp Architekt",
    "wof:placetype":"venue"
},
  "geometry": {"coordinates":[10.98251,49.497719],"type":"Point"}
}