{
  "type": "Feature",
  "properties": {
    "iso:country":"DE",
    "sg:address":"Alte Noer Str 6",
    "sg:city":"Luckau",
    "sg:phone":"+49 35456/6800",
    "sg:postcode":"15926",
    "sg:province":"Brandenburg",
    "wof:name":"Lausitzer Kl\u00e4rtechnik Gmbh",
    "wof:placetype":"venue"
},
  "geometry": {"coordinates":[13.7983779907,51.8763198853],"type":"Point"}
}