{
  "type": "Feature",
  "properties": {
    "iso:country":"DE",
    "sg:address":"34587",
    "sg:city":"Felsberg",
    "sg:phone":"+49 5662/2006",
    "sg:postcode":"34587",
    "sg:province":"Hessen",
    "wof:name":"Deutsche Bahn Ag",
    "wof:placetype":"venue"
},
  "geometry": {"coordinates":[9.4502801895,51.1355285645],"type":"Point"}
}