{
  "type": "Feature",
  "properties": {
    "iso:country":"DE",
    "sg:address":"Pfarrstr. 11",
    "sg:city":"Selb",
    "sg:phone":"+49 9287/70436",
    "sg:postcode":"95100",
    "sg:province":"Bayern",
    "wof:name":"Kornblume Selb",
    "wof:placetype":"venue"
},
  "geometry": {"coordinates":[12.1338787079,50.1703414917],"type":"Point"}
}