{
  "type": "Feature",
  "properties": {
    "iso:country":"DE",
    "sg:address":"Brookstr.",
    "sg:city":"Braak",
    "sg:postcode":"22145",
    "sg:province":"Hamburg",
    "wof:name":"Cgl Handel Gmbh & Co. Immobilien Kg",
    "wof:placetype":"venue"
},
  "geometry": {"coordinates":[-79.0160751343,38.9223251343],"type":"Point"}
}