{
  "type": "Feature",
  "properties": {
    "iso:country":"DE",
    "sg:address":"Wittener Str. 185",
    "sg:city":"Sprockh\u00f6vel",
    "sg:phone":"+49 2339/2817",
    "sg:postcode":"45549",
    "sg:province":"Nordrhein-Westfalen",
    "wof:name":"G.a. Siepmann",
    "wof:placetype":"venue"
},
  "geometry": {"coordinates":[7.28599,51.357761],"type":"Point"}
}