{
  "type": "Feature",
  "properties": {
    "iso:country":"DE",
    "sg:address":"Frankfurter Str. 58",
    "sg:city":"Eisdorf",
    "sg:phone":"+49 5522/82678",
    "sg:postcode":"37534",
    "sg:province":"Niedersachsen",
    "wof:name":"Alfred Kesten",
    "wof:placetype":"venue"
},
  "geometry": {"coordinates":[10.1781215668,51.7604637146],"type":"Point"}
}