{
  "type": "Feature",
  "properties": {
    "iso:country":"DE",
    "sg:address":"Neusalzer Str 12-14",
    "sg:city":"Offenbach",
    "sg:phone":"+49 671/69019",
    "sg:postcode":"63069",
    "sg:province":"Hessen",
    "wof:name":"Gebr\u00fcder Erbach Stahlbau Gmbh",
    "wof:placetype":"venue"
},
  "geometry": {"coordinates":[7.8931059837,49.8542671204],"type":"Point"}
}