{
  "type": "Feature",
  "properties": {
    "iso:country":"DE",
    "sg:address":"Karl-Marx-Str. 90-91",
    "sg:city":"Neuruppin",
    "sg:phone":"+49 3391/650160",
    "sg:postcode":"16816",
    "sg:province":"Brandenburg",
    "wof:name":"Stadtpalais Immobilien Gmbh",
    "wof:placetype":"venue"
},
  "geometry": {"coordinates":[12.8089847565,52.9273910522],"type":"Point"}
}