{
  "type": "Feature",
  "properties": {
    "iso:country":"DE",
    "sg:address":"Hauptstr. 4",
    "sg:city":"Hellingen",
    "sg:phone":"+49 36871/29026",
    "sg:postcode":"98663",
    "sg:province":"Th\u00fcringen",
    "wof:name":"Walfried Zertisch",
    "wof:placetype":"venue"
},
  "geometry": {"coordinates":[10.6828327179,50.2538528442],"type":"Point"}
}