{
  "type": "Feature",
  "properties": {
    "iso:country":"DE",
    "sg:address":"Podbielskistr. 358",
    "sg:city":"Hannover",
    "sg:phone":"+49 511/648074",
    "sg:postcode":"30659",
    "sg:province":"Niedersachsen",
    "wof:name":"Itj-reisen",
    "wof:placetype":"venue"
},
  "geometry": {"coordinates":[9.8020515442,52.4067077637],"type":"Point"}
}