{
  "type": "Feature",
  "properties": {
    "iso:country":"DE",
    "sg:address":"Vetschauer Str. 17",
    "sg:city":"Dresden",
    "sg:postcode":"01237",
    "sg:province":"Sachsen",
    "wof:name":"Gehrisch Unabh\u00e4ngige Schrift- Steller Assoziation Dd E. V.",
    "wof:placetype":"venue"
},
  "geometry": {"coordinates":[13.7949199677,51.0121917725],"type":"Point"}
}