{
  "type": "Feature",
  "properties": {
    "iso:country":"DE",
    "sg:address":"Windweg 7",
    "sg:city":"Detmold",
    "sg:phone":"+49 5232/89760",
    "sg:postcode":"32758",
    "sg:province":"Nordrhein-Westfalen",
    "wof:name":"Burkhard Fr\u00f6hlich",
    "wof:placetype":"venue"
},
  "geometry": {"coordinates":[8.7954874039,51.9431037903],"type":"Point"}
}