{
  "type": "Feature",
  "properties": {
    "iso:country":"DE",
    "sg:address":"Robert-Bosch-Str. 15",
    "sg:city":"Villingendorf",
    "sg:phone":"+49 741/92970",
    "sg:postcode":"78667",
    "sg:province":"Baden-W\u00fcrttemberg",
    "wof:name":"Jauch & Schmider Gmbh",
    "wof:placetype":"venue"
},
  "geometry": {"coordinates":[8.5841846466,48.2107582092],"type":"Point"}
}