{
  "type": "Feature",
  "properties": {
    "iso:country":"DE",
    "sg:address":"Reiterweg 3",
    "sg:city":"Altenstadt",
    "sg:phone":"+49 8861/7287",
    "sg:postcode":"86972",
    "sg:province":"Bayern",
    "wof:name":"T. Pr\u00f6bstl",
    "wof:placetype":"venue"
},
  "geometry": {"coordinates":[10.856625,47.830631],"type":"Point"}
}