{
  "type": "Feature",
  "properties": {
    "iso:country":"DE",
    "sg:address":"Stiegstr 87-91",
    "sg:city":"Br\u00fcggen",
    "sg:phone":"+49 2157/14160",
    "sg:postcode":"41379",
    "sg:province":"Nordrhein-Westfalen",
    "wof:name":"M & V Gesellschaft Zur Projektierung, Fertigung Und Montage Von Sonnenschutz Sonnenschutzsystemem Mbh",
    "wof:placetype":"venue"
},
  "geometry": {"coordinates":[6.1775050163,51.2812957764],"type":"Point"}
}