{
  "type": "Feature",
  "properties": {
    "iso:country":"DE",
    "sg:address":"Kickenstr. 5",
    "sg:city":"Willich",
    "sg:phone":"+49 2156/951717",
    "sg:postcode":"47877",
    "sg:province":"Nordrhein-Westfalen",
    "wof:name":"Universale Parksysteme Verwaltungs Gmbh",
    "wof:placetype":"venue"
},
  "geometry": {"coordinates":[6.479625,51.253304],"type":"Point"}
}