{
  "type": "Feature",
  "properties": {
    "iso:country":"DE",
    "sg:address":"Zobelweg 6",
    "sg:city":"Troisdorf",
    "sg:phone":"+49 2246/5610",
    "sg:postcode":"53842",
    "sg:province":"Nordrhein-Westfalen",
    "wof:name":"Voss & Klebe Beteiligungsgesellschaft Mbh",
    "wof:placetype":"venue"
},
  "geometry": {"coordinates":[7.1059007645,50.8281555176],"type":"Point"}
}