{
  "type": "Feature",
  "properties": {
    "iso:country":"DE",
    "sg:address":"Mainzer Str. 95",
    "sg:city":"Bad Kreuznach",
    "sg:phone":"+49 671/69733",
    "sg:postcode":"55545",
    "sg:province":"Rheinland-Pfalz",
    "wof:name":"Rochus-apotheke Sigrid Spngler",
    "wof:placetype":"venue"
},
  "geometry": {"coordinates":[7.913474,49.864197],"type":"Point"}
}