{
  "type": "Feature",
  "properties": {
    "iso:country":"DE",
    "sg:address":"Sch\u00f6ne Aussicht 5",
    "sg:city":"Niedernhausen",
    "sg:phone":"+49 6127/905222",
    "sg:postcode":"65527",
    "sg:province":"Hessen",
    "wof:name":"Ipg Friedrich W. Vettermann",
    "wof:placetype":"venue"
},
  "geometry": {"coordinates":[8.3106908798,50.1563949585],"type":"Point"}
}