{
  "type": "Feature",
  "properties": {
    "iso:country":"DE",
    "sg:address":"Hauptstr. 55",
    "sg:city":"Macken",
    "sg:phone":"+49 2605/8323",
    "sg:postcode":"56290",
    "sg:province":"Rheinland-Pfalz",
    "wof:name":"Katholisches Pfarramt St. Kastor",
    "wof:placetype":"venue"
},
  "geometry": {"coordinates":[7.3972401619,50.1738891602],"type":"Point"}
}