{
  "type": "Feature",
  "properties": {
    "iso:country":"DE",
    "sg:address":"Marktstr. 7",
    "sg:city":"Einbeck",
    "sg:phone":"+49 5561/4480",
    "sg:postcode":"37574",
    "sg:province":"Niedersachsen",
    "wof:name":"Fritz Gmbh & Co. Kg Modewaren",
    "wof:placetype":"venue"
},
  "geometry": {"coordinates":[9.866215,51.817844],"type":"Point"}
}