{
  "type": "Feature",
  "properties": {
    "iso:country":"DE",
    "sg:city":"Neureichenau",
    "sg:phone":"+49 8583/1420",
    "sg:postcode":"94089",
    "sg:province":"Bayern",
    "wof:name":"P. Fuchs",
    "wof:placetype":"venue"
},
  "geometry": {"coordinates":[13.747728,48.747517],"type":"Point"}
}