{
  "type": "Feature",
  "properties": {
    "iso:country":"DE",
    "sg:address":"Graf-Adolf-Str. 69",
    "sg:city":"D\u00fcsseldorf",
    "sg:phone":"+49 211/3859905",
    "sg:postcode":"40210",
    "sg:province":"Nordrhein-Westfalen",
    "wof:name":"Arns France Gmbh",
    "wof:placetype":"venue"
},
  "geometry": {"coordinates":[6.786989212,51.2190132141],"type":"Point"}
}