{
  "type": "Feature",
  "properties": {
    "iso:country":"DE",
    "sg:address":"Seelenberger Str. 4a",
    "sg:city":"Frankfurt",
    "sg:phone":"+49 69/7896794",
    "sg:postcode":"60489",
    "sg:province":"Hessen",
    "wof:name":"Mediaberatung Saddai-hofer",
    "wof:placetype":"venue"
},
  "geometry": {"coordinates":[8.6173324585,50.1316833496],"type":"Point"}
}