{
  "type": "Feature",
  "properties": {
    "iso:country":"DE",
    "sg:address":"Berliner Str. 14",
    "sg:city":"Seedorf",
    "sg:phone":"+49 4555/487",
    "sg:postcode":"23823",
    "sg:province":"Schleswig-Holstein",
    "wof:name":"Kreissparkasse Segeberg",
    "wof:placetype":"venue"
},
  "geometry": {"coordinates":[10.397269,54.039413],"type":"Point"}
}