{
  "type": "Feature",
  "properties": {
    "iso:country":"DE",
    "sg:address":"Meta-Gadesmann-Str. 7",
    "sg:city":"Rottach-Egern",
    "sg:phone":"+49 8022/66950",
    "sg:postcode":"83700",
    "sg:province":"Bayern",
    "wof:name":"E & E Treuhand Steuerberatungs- Gmbh",
    "wof:placetype":"venue"
},
  "geometry": {"coordinates":[11.7554111481,47.6901855469],"type":"Point"}
}