{
  "type": "Feature",
  "properties": {
    "iso:country":"DE",
    "sg:address":"Baldungstr. 3",
    "sg:city":"Schw\u00e4bisch Gm\u00fcnd",
    "sg:phone":"+49 7171/38231",
    "sg:postcode":"73525",
    "sg:province":"Baden-W\u00fcrttemberg",
    "wof:name":"Uwe K\u00fcssner Produktentwicklung",
    "wof:placetype":"venue"
},
  "geometry": {"coordinates":[9.803368,48.801426],"type":"Point"}
}