{
  "type": "Feature",
  "properties": {
    "iso:country":"DE",
    "sg:address":"Aixheimer Str. 12",
    "sg:city":"Stuttgart",
    "sg:postcode":"70619",
    "sg:province":"Baden-W\u00fcrttemberg",
    "wof:name":"Ifm-solutions Gmbh",
    "wof:placetype":"venue"
},
  "geometry": {"coordinates":[9.215852,48.741039],"type":"Point"}
}