{
  "type": "Feature",
  "properties": {
    "iso:country":"DE",
    "sg:address":"Damm\u00fchlenweg",
    "sg:city":"Haldensleben",
    "sg:phone":"+49 3904/44219",
    "sg:postcode":"39340",
    "sg:province":"Sachsen-Anhalt",
    "wof:name":"Raiffeisen Warengenossenschaft",
    "wof:placetype":"venue"
},
  "geometry": {"coordinates":[11.4276847839,52.2689361572],"type":"Point"}
}