{
  "type": "Feature",
  "properties": {
    "iso:country":"DE",
    "sg:address":"Altenhof 29",
    "sg:city":"Siegen",
    "sg:phone":"+49 271/52100",
    "sg:postcode":"57074",
    "sg:province":"Nordrhein-Westfalen",
    "wof:name":"Alois Nies",
    "wof:placetype":"venue"
},
  "geometry": {"coordinates":[8.03125,50.8750343323],"type":"Point"}
}