{
  "type": "Feature",
  "properties": {
    "iso:country":"DE",
    "sg:city":"Grenderich",
    "sg:phone":"+49 2673/4136",
    "sg:postcode":"56858",
    "sg:province":"Rheinland-Pfalz",
    "wof:name":"Susanne Zirwes",
    "wof:placetype":"venue"
},
  "geometry": {"coordinates":[7.230638,50.067348],"type":"Point"}
}