{
  "type": "Feature",
  "properties": {
    "iso:country":"DE",
    "sg:address":"Industriestr. 3",
    "sg:city":"Kandel",
    "sg:phone":"+49 7275/8201",
    "sg:postcode":"76870",
    "sg:province":"Rheinland-Pfalz",
    "wof:name":"Harms Kartographie",
    "wof:placetype":"venue"
},
  "geometry": {"coordinates":[8.182639,49.09919],"type":"Point"}
}