{
  "type": "Feature",
  "properties": {
    "iso:country":"DE",
    "sg:address":"Pater-Baroffio-Weg 33",
    "sg:city":"Ludwigshafen",
    "sg:phone":"+49 6237/920387",
    "sg:postcode":"67071",
    "sg:province":"Rheinland-Pfalz",
    "wof:name":"Spedition Diehl",
    "wof:placetype":"venue"
},
  "geometry": {"coordinates":[8.3347682953,49.4715461731],"type":"Point"}
}