{
  "type": "Feature",
  "properties": {
    "iso:country":"DE",
    "sg:address":"Ackerweg 29",
    "sg:city":"Neuhof",
    "sg:phone":"+49 6655/2712",
    "sg:postcode":"36119",
    "sg:province":"Hessen",
    "wof:name":"Bernd Adrian",
    "wof:placetype":"venue"
},
  "geometry": {"coordinates":[9.6058959961,50.4580841064],"type":"Point"}
}