{
  "type": "Feature",
  "properties": {
    "iso:country":"DE",
    "sg:address":"Kafkastr. 41",
    "sg:city":"Bielefeld",
    "sg:phone":"+49 521/391750",
    "sg:postcode":"33729",
    "sg:province":"Nordrhein-Westfalen",
    "wof:name":"Wittland Stanztechnik Gmbh",
    "wof:placetype":"venue"
},
  "geometry": {"coordinates":[8.6424570084,52.046836853],"type":"Point"}
}