{
  "type": "Feature",
  "properties": {
    "iso:country":"DE",
    "sg:address":"Pr\u00fcllstr. 12",
    "sg:city":"Donaustauf",
    "sg:phone":"+49 9403/961733",
    "sg:postcode":"93093",
    "sg:province":"Bayern",
    "wof:name":"Max H\u00f6pfl",
    "wof:placetype":"venue"
},
  "geometry": {"coordinates":[12.205231,49.029892],"type":"Point"}
}