{
  "type": "Feature",
  "properties": {
    "iso:country":"DE",
    "sg:address":"Am Gr\u00fcnen Brink 7",
    "sg:city":"Springe",
    "sg:phone":"+49 5041/970043",
    "sg:postcode":"31832",
    "sg:province":"Niedersachsen",
    "wof:name":"Datenrettung Von Computer Massenspeichern",
    "wof:placetype":"venue"
},
  "geometry": {"coordinates":[9.555124,52.211079],"type":"Point"}
}