{
  "type": "Feature",
  "properties": {
    "iso:country":"DE",
    "sg:address":"Ringweg 7",
    "sg:city":"Windeby",
    "sg:phone":"+49 4351/42378",
    "sg:postcode":"24340",
    "sg:province":"Schleswig-Holstein",
    "wof:name":"Manfred Frey",
    "wof:placetype":"venue"
},
  "geometry": {"coordinates":[9.7840938568,54.4577407837],"type":"Point"}
}