{
  "type": "Feature",
  "properties": {
    "iso:country":"DE",
    "sg:address":"Franz-Mehring-Str. 23 c",
    "sg:city":"Frankfurt",
    "sg:postcode":"15230",
    "sg:province":"Brandenburg",
    "wof:name":"Salto Florale E. K.",
    "wof:placetype":"venue"
},
  "geometry": {"coordinates":[14.55432,52.341679],"type":"Point"}
}