{
  "type": "Feature",
  "properties": {
    "iso:country":"DE",
    "sg:address":"Bundesstr. 33",
    "sg:city":"Willich",
    "sg:postcode":"47877",
    "sg:province":"Nordrhein-Westfalen",
    "wof:name":"Oversee Chinees Internationale Trading Gmbh",
    "wof:placetype":"venue"
},
  "geometry": {"coordinates":[6.5598268509,51.228767395],"type":"Point"}
}