{
  "type": "Feature",
  "properties": {
    "iso:country":"DE",
    "sg:address":"P\u00fcttenstr. 15",
    "sg:city":"Sch\u00f6now",
    "sg:phone":"+49 3338/753273",
    "sg:postcode":"16321",
    "sg:province":"Brandenburg",
    "wof:name":"Hardy K. Freitag Treppenbau Gmbh",
    "wof:placetype":"venue"
},
  "geometry": {"coordinates":[13.5828266144,52.6802177429],"type":"Point"}
}