{
  "type": "Feature",
  "properties": {
    "iso:country":"DE",
    "sg:address":"Walchstadter Str. 5",
    "sg:city":"Inning",
    "sg:phone":"+49 8143/326",
    "sg:postcode":"82266",
    "sg:province":"Bayern",
    "wof:name":"Welzm\u00fcller- Raumausstattung Gmbh",
    "wof:placetype":"venue"
},
  "geometry": {"coordinates":[11.152865,48.075588],"type":"Point"}
}