{
  "type": "Feature",
  "properties": {
    "iso:country":"DE",
    "sg:address":"Am Bahnhof 8",
    "sg:city":"Wartenberg",
    "sg:phone":"+49 6641/96190",
    "sg:postcode":"36367",
    "sg:province":"Hessen",
    "wof:name":"Funktronic Gmbh",
    "wof:placetype":"venue"
},
  "geometry": {"coordinates":[9.445517,50.63303],"type":"Point"}
}