{
  "type": "Feature",
  "properties": {
    "iso:country":"DE",
    "sg:address":"Kastanienring 16b",
    "sg:city":"W\u00f6rrstadt",
    "sg:phone":"+49 6732/63373",
    "sg:postcode":"55286",
    "sg:province":"Rheinland-Pfalz",
    "wof:name":"Rolf Graf",
    "wof:placetype":"venue"
},
  "geometry": {"coordinates":[8.1240901947,49.8414535522],"type":"Point"}
}