{
  "type": "Feature",
  "properties": {
    "iso:country":"DE",
    "sg:address":"Schwarzspechtweg 47",
    "sg:city":"Berlin",
    "sg:phone":"+49 30/4319062",
    "sg:postcode":"13505",
    "sg:province":"Berlin",
    "wof:name":"Helmuth Gabriel Binnenschiffahrtsunternehmen",
    "wof:placetype":"venue"
},
  "geometry": {"coordinates":[13.221462,52.580448],"type":"Point"}
}