{
  "type": "Feature",
  "properties": {
    "iso:country":"DE",
    "sg:address":"Rothansch\u00f6ring",
    "sg:city":"Kirchansch\u00f6ring",
    "sg:phone":"+49 8685/384",
    "sg:postcode":"83417",
    "sg:province":"Bayern",
    "wof:name":"L. St\u00f6ckl",
    "wof:placetype":"venue"
},
  "geometry": {"coordinates":[12.83495,47.953049],"type":"Point"}
}