{
  "type": "Feature",
  "properties": {
    "iso:country":"DE",
    "sg:address":"Jenaer Str. 6",
    "sg:city":"Berlin",
    "sg:phone":"+49 30/8542073",
    "sg:postcode":"10717",
    "sg:province":"Berlin",
    "wof:name":"Horst Pasch Architekt",
    "wof:placetype":"venue"
},
  "geometry": {"coordinates":[13.335278,52.490143],"type":"Point"}
}