{
  "type": "Feature",
  "properties": {
    "iso:country":"DE",
    "sg:address":"Weihestr. 9",
    "sg:city":"Bielefeld",
    "sg:phone":"+49 521/884058",
    "sg:postcode":"33613",
    "sg:province":"Nordrhein-Westfalen",
    "wof:name":"Katholisches Pfarramt Christk\u00f6nig",
    "wof:placetype":"venue"
},
  "geometry": {"coordinates":[8.5190982819,52.0451545715],"type":"Point"}
}