{
  "type": "Feature",
  "properties": {
    "iso:country":"DE",
    "sg:address":"Aachener Str. 435",
    "sg:city":"M\u00f6nchengladbach",
    "sg:phone":"+49 2161/540969",
    "sg:postcode":"41069",
    "sg:province":"Nordrhein-Westfalen",
    "wof:name":"Foto-drogerie Hans Windelen",
    "wof:placetype":"venue"
},
  "geometry": {"coordinates":[6.409699,51.181992],"type":"Point"}
}