{
  "type": "Feature",
  "properties": {
    "iso:country":"DE",
    "sg:address":"Demmlerweg 5",
    "sg:city":"Calw",
    "sg:phone":"+49 7051/40423",
    "sg:postcode":"75365",
    "sg:province":"Baden-W\u00fcrttemberg",
    "wof:name":"Herbert Breitling",
    "wof:placetype":"venue"
},
  "geometry": {"coordinates":[8.7637996674,48.7095031738],"type":"Point"}
}