{
  "type": "Feature",
  "properties": {
    "iso:country":"DE",
    "sg:address":"Robert-Schuman-Str. 58",
    "sg:city":"Kr\u00f6v",
    "sg:phone":"+49 6541/6990",
    "sg:postcode":"54536",
    "sg:province":"Rheinland-Pfalz",
    "wof:name":"M. Christoffel Weingut",
    "wof:placetype":"venue"
},
  "geometry": {"coordinates":[7.0883440971,49.9806404114],"type":"Point"}
}