{
  "type": "Feature",
  "properties": {
    "iso:country":"DE",
    "sg:address":"Hauptstr. 50",
    "sg:city":"Hehlen",
    "sg:phone":"+49 5533/2573",
    "sg:postcode":"37619",
    "sg:province":"Niedersachsen",
    "wof:name":"K. Edler",
    "wof:placetype":"venue"
},
  "geometry": {"coordinates":[9.4681386948,51.9842987061],"type":"Point"}
}