{
  "type": "Feature",
  "properties": {
    "iso:country":"DE",
    "sg:address":"Hofer Str. 153",
    "sg:city":"Oberlungwitz",
    "sg:phone":"+49 3723/3134",
    "sg:postcode":"09353",
    "sg:province":"Sachsen",
    "wof:name":"G\u00fcnter H\u00e4rtig",
    "wof:placetype":"venue"
},
  "geometry": {"coordinates":[12.722163,50.78603],"type":"Point"}
}