{
  "type": "Feature",
  "properties": {
    "iso:country":"DE",
    "sg:address":"D\u00f6rpfeldstr. 2",
    "sg:city":"Hamburg",
    "sg:phone":"+49 40/806399",
    "sg:postcode":"22609",
    "sg:province":"Hamburg",
    "wof:name":"Vakuumtechnik Gmbh",
    "wof:placetype":"venue"
},
  "geometry": {"coordinates":[9.842885,53.562164],"type":"Point"}
}