{
  "type": "Feature",
  "properties": {
    "iso:country":"DE",
    "sg:address":"Bauerntanzgasse 18",
    "sg:city":"Aichach",
    "sg:phone":"+49 8251/872424",
    "sg:postcode":"86551",
    "sg:province":"Bayern",
    "wof:name":"Sebastian Apotheke Aichach Inh. Gerhard Scholter E. Kfm.",
    "wof:placetype":"venue"
},
  "geometry": {"coordinates":[11.13013,48.460033],"type":"Point"}
}