{
  "type": "Feature",
  "properties": {
    "iso:country":"DE",
    "sg:address":"Konstantin-Uhde-Str. 13",
    "sg:city":"Braunschweig",
    "sg:postcode":"38106",
    "sg:province":"Niedersachsen",
    "wof:name":"Elterninitiative Down-syndrom Braunschweig E. V.",
    "wof:placetype":"venue"
},
  "geometry": {"coordinates":[10.5326738358,52.2742233276],"type":"Point"}
}