{
  "type": "Feature",
  "properties": {
    "iso:country":"DE",
    "sg:address":"Florian-Geyer-Str. 83",
    "sg:city":"Berlin",
    "sg:postcode":"12489",
    "sg:province":"Berlin",
    "wof:name":"Dauerheim Treptow",
    "wof:placetype":"venue"
},
  "geometry": {"coordinates":[13.5431833267,52.4386787415],"type":"Point"}
}