{
  "type": "Feature",
  "properties": {
    "iso:country":"DE",
    "sg:address":"Poststr. 21",
    "sg:city":"Bad Berleburg",
    "sg:phone":"+49 2751/2222",
    "sg:postcode":"57319",
    "sg:province":"Nordrhein-Westfalen",
    "wof:name":"Apropos",
    "wof:placetype":"venue"
},
  "geometry": {"coordinates":[8.392787,51.050495],"type":"Point"}
}