{
  "type": "Feature",
  "properties": {
    "iso:country":"DE",
    "sg:address":"Bahnhofstr. 1",
    "sg:city":"Bresewitz",
    "sg:phone":"+49 38231/82675",
    "sg:postcode":"18356",
    "sg:province":"Mecklenburg-Vorpommern",
    "wof:name":"K. George & H. Machleidt",
    "wof:placetype":"venue"
},
  "geometry": {"coordinates":[12.676410675,54.4023933411],"type":"Point"}
}