{
  "type": "Feature",
  "properties": {
    "iso:country":"DE",
    "sg:address":"Franz-Heldmann-Str. 64",
    "sg:city":"Tirschenreuth",
    "sg:phone":"+49 9631/3841",
    "sg:postcode":"95643",
    "sg:province":"Bayern",
    "wof:name":"Waldemar Schindler",
    "wof:placetype":"venue"
},
  "geometry": {"coordinates":[12.314199,49.884125],"type":"Point"}
}