{
  "type": "Feature",
  "properties": {
    "iso:country":"DE",
    "sg:address":"Berliner Str. 41",
    "sg:city":"Rheinsberg",
    "sg:phone":"+49 33931/2171",
    "sg:postcode":"16831",
    "sg:province":"Brandenburg",
    "wof:name":"Raiffeisen Hg Eg",
    "wof:placetype":"venue"
},
  "geometry": {"coordinates":[12.8994159698,53.0940551758],"type":"Point"}
}