{
  "type": "Feature",
  "properties": {
    "iso:country":"DE",
    "sg:address":"Ditzenbrunner Str. 49",
    "sg:city":"Ditzingen",
    "sg:postcode":"71254",
    "sg:province":"Baden-W\u00fcrttemberg",
    "wof:name":"Kodokan Ditzingen Uwe Kaschuba",
    "wof:placetype":"venue"
},
  "geometry": {"coordinates":[9.0771808624,48.8291740417],"type":"Point"}
}