{
  "type": "Feature",
  "properties": {
    "iso:country":"DE",
    "sg:address":"Oststr. 3",
    "sg:city":"L\u00fcdenscheid",
    "sg:phone":"+49 2351/81896",
    "sg:postcode":"58511",
    "sg:province":"Nordrhein-Westfalen",
    "wof:name":"U. Schuster",
    "wof:placetype":"venue"
},
  "geometry": {"coordinates":[7.640394,51.217239],"type":"Point"}
}