{
  "type": "Feature",
  "properties": {
    "iso:country":"DE",
    "sg:address":"Papenwiese 5",
    "sg:city":"Haren",
    "sg:phone":"+49 5932/72500",
    "sg:postcode":"49733",
    "sg:province":"Niedersachsen",
    "wof:name":"Mare Schiffahrts Gmbh",
    "wof:placetype":"venue"
},
  "geometry": {"coordinates":[7.235105,52.791821],"type":"Point"}
}