{
  "type": "Feature",
  "properties": {
    "iso:country":"DE",
    "sg:address":"Weihenstephaner Str. 2",
    "sg:city":"Unterschlei\u00dfheim",
    "sg:postcode":"85716",
    "sg:province":"Bayern",
    "wof:name":"Scha\u00dfberger Gmbh",
    "wof:placetype":"venue"
},
  "geometry": {"coordinates":[11.5856809616,48.2862892151],"type":"Point"}
}