{
  "type": "Feature",
  "properties": {
    "iso:country":"DE",
    "sg:address":"Postbrookstr. 38",
    "sg:city":"Bremerhaven",
    "sg:phone":"+49 471/2900689",
    "sg:postcode":"27574",
    "sg:province":"Bremen",
    "wof:name":"A. Burkhardt",
    "wof:placetype":"venue"
},
  "geometry": {"coordinates":[8.632557,53.532482],"type":"Point"}
}