{
  "type": "Feature",
  "properties": {
    "iso:country":"DE",
    "sg:address":"Hermann-Krum-Str 13",
    "sg:city":"Aitrach",
    "sg:phone":"+49 7565/5070",
    "sg:postcode":"88319",
    "sg:province":"Baden-W\u00fcrttemberg",
    "wof:name":"Hm-betonfertigteilwerk Hans Mauthe Gmbh & Co Kg",
    "wof:placetype":"venue"
},
  "geometry": {"coordinates":[10.106462,47.933186],"type":"Point"}
}