{
  "type": "Feature",
  "properties": {
    "iso:country":"DE",
    "sg:address":"Leibnizstr. 35",
    "sg:city":"Magdeburg",
    "sg:postcode":"39104",
    "sg:province":"Sachsen-Anhalt",
    "wof:name":"Prognos Gmbh",
    "wof:placetype":"venue"
},
  "geometry": {"coordinates":[11.6299734116,52.1204681396],"type":"Point"}
}