{
  "type": "Feature",
  "properties": {
    "iso:country":"DE",
    "sg:address":"Grabenstr. 56",
    "sg:city":"Waldbrunn",
    "sg:phone":"+49 9306/2260",
    "sg:postcode":"97295",
    "sg:province":"Bayern",
    "wof:name":"N. Und B. Uehlein",
    "wof:placetype":"venue"
},
  "geometry": {"coordinates":[9.8038692474,49.762386322],"type":"Point"}
}