{
  "type": "Feature",
  "properties": {
    "iso:country":"DE",
    "sg:address":"Am Langgraben 2",
    "sg:city":"Adelsdorf",
    "sg:phone":"+49 9195/94240",
    "sg:postcode":"91325",
    "sg:province":"Bayern",
    "wof:name":"Fristo Getr\u00c4nkemarkt Gmbh",
    "wof:placetype":"venue"
},
  "geometry": {"coordinates":[10.878648,49.706268],"type":"Point"}
}