{
  "type": "Feature",
  "properties": {
    "iso:country":"DE",
    "sg:address":"K\u00f6nigstr. 168",
    "sg:city":"Minden",
    "sg:phone":"+49 571/55525",
    "sg:postcode":"32427",
    "sg:province":"Nordrhein-Westfalen",
    "wof:name":"Seta-seeger",
    "wof:placetype":"venue"
},
  "geometry": {"coordinates":[8.8847799301,52.2914085388],"type":"Point"}
}