{
  "type": "Feature",
  "properties": {
    "iso:country":"DE",
    "sg:address":"Domshof 26",
    "sg:city":"Bremen",
    "sg:phone":"+49 421/36681",
    "sg:postcode":"28195",
    "sg:province":"Bremen",
    "wof:name":"Landesbausparkasse Beratungsstelle",
    "wof:placetype":"venue"
},
  "geometry": {"coordinates":[8.808798,53.076443],"type":"Point"}
}