{
  "type": "Feature",
  "properties": {
    "iso:country":"DE",
    "sg:address":"Am Sandborn 3",
    "sg:city":"Seligenstadt",
    "sg:phone":"+49 6182/67244",
    "sg:postcode":"63500",
    "sg:province":"Hessen",
    "wof:name":"Main-paneele Und Bandprofilier Gmbh",
    "wof:placetype":"venue"
},
  "geometry": {"coordinates":[8.928677,50.051018],"type":"Point"}
}