{
  "type": "Feature",
  "properties": {
    "iso:country":"DE",
    "sg:address":"Mauchener Str. 12",
    "sg:city":"M\u00fcllheim",
    "sg:phone":"+49 7631/8203",
    "sg:postcode":"79379",
    "sg:province":"Baden-W\u00fcrttemberg",
    "wof:name":"Theiss & Harter Gmbh & Co. Kg",
    "wof:placetype":"venue"
},
  "geometry": {"coordinates":[7.6057209969,47.8112258911],"type":"Point"}
}