{
  "type": "Feature",
  "properties": {
    "iso:country":"DE",
    "sg:address":"Bachstr. 5",
    "sg:city":"Schonungen",
    "sg:postcode":"97453",
    "sg:province":"Bayern",
    "wof:name":"Evelin M\u00fcller Steuer- Beratungsgesellschaft Mbh",
    "wof:placetype":"venue"
},
  "geometry": {"coordinates":[10.3036794662,50.0508995056],"type":"Point"}
}