{
  "type": "Feature",
  "properties": {
    "iso:country":"DE",
    "sg:address":"Am Weserberg 19",
    "sg:city":"Achim",
    "sg:phone":"+49 4202/1305",
    "sg:postcode":"28832",
    "sg:province":"Niedersachsen",
    "wof:name":"Henry Seecamp",
    "wof:placetype":"venue"
},
  "geometry": {"coordinates":[8.98106,53.021],"type":"Point"}
}