{
  "type": "Feature",
  "properties": {
    "iso:country":"DE",
    "sg:address":"F\u00e4rberstr. 25",
    "sg:city":"Wuppertal",
    "sg:phone":"+49 202/666006",
    "sg:postcode":"42275",
    "sg:province":"Nordrhein-Westfalen",
    "wof:name":"J\u00fcrgen Hungerbach",
    "wof:placetype":"venue"
},
  "geometry": {"coordinates":[7.2116189003,51.2756958008],"type":"Point"}
}