{
  "type": "Feature",
  "properties": {
    "iso:country":"DE",
    "sg:address":"In Scharnhorst 11",
    "sg:city":"Neustadt",
    "sg:phone":"+49 5032/2880",
    "sg:postcode":"31535",
    "sg:province":"Niedersachsen",
    "wof:name":"Erich Schantl",
    "wof:placetype":"venue"
},
  "geometry": {"coordinates":[9.520980835,52.5405311584],"type":"Point"}
}