{
  "type": "Feature",
  "properties": {
    "iso:country":"DE",
    "sg:address":"Am Pfarrgarten 12",
    "sg:city":"Ensdorf",
    "sg:phone":"+49 6831/53248",
    "sg:postcode":"66806",
    "sg:province":"Saarland",
    "wof:name":"E. Welsch",
    "wof:placetype":"venue"
},
  "geometry": {"coordinates":[6.780505,49.306053],"type":"Point"}
}