{
  "type": "Feature",
  "properties": {
    "iso:country":"DE",
    "sg:address":"Bilsteiner Str. 11",
    "sg:city":"Olpe",
    "sg:phone":"+49 2761/6729",
    "sg:postcode":"57462",
    "sg:province":"Nordrhein-Westfalen",
    "wof:name":"Strach",
    "wof:placetype":"venue"
},
  "geometry": {"coordinates":[7.857453,51.036163],"type":"Point"}
}