{
  "type": "Feature",
  "properties": {
    "iso:country":"DE",
    "sg:address":"Schmiedeberg 25",
    "sg:city":"Klipphausen",
    "sg:phone":"+49 35204/48616",
    "sg:postcode":"01665",
    "sg:province":"Sachsen",
    "wof:name":"Klaus Kn\u00f6fel",
    "wof:placetype":"venue"
},
  "geometry": {"coordinates":[13.561138,51.084251],"type":"Point"}
}