{
  "type": "Feature",
  "properties": {
    "iso:country":"DE",
    "sg:address":"Schleestr. 6",
    "sg:city":"Hamburg",
    "sg:phone":"+49 40/383404",
    "sg:postcode":"22767",
    "sg:province":"Hamburg",
    "wof:name":"Manfred M\u00f6ller",
    "wof:placetype":"venue"
},
  "geometry": {"coordinates":[9.9455652237,53.5468177795],"type":"Point"}
}