{
  "type": "Feature",
  "properties": {
    "iso:country":"DE",
    "sg:address":"Im Gelbstein 17",
    "sg:city":"Breisach",
    "sg:phone":"+49 7667/80002",
    "sg:postcode":"79206",
    "sg:province":"Baden-W\u00fcrttemberg",
    "wof:name":"B U. M Bau- Und Montage Gmbh",
    "wof:placetype":"venue"
},
  "geometry": {"coordinates":[7.595375061,48.0333824158],"type":"Point"}
}