{
  "type": "Feature",
  "properties": {
    "iso:country":"DE",
    "sg:address":"August-L\u00e4mmle-Str. 9",
    "sg:city":"Kusterdingen",
    "sg:phone":"+49 7071/35094",
    "sg:postcode":"72127",
    "sg:province":"Baden-W\u00fcrttemberg",
    "wof:name":"Jutta Br\u00e4unlich Krankengymnastin",
    "wof:placetype":"venue"
},
  "geometry": {"coordinates":[9.11483,48.523979],"type":"Point"}
}