{
  "type": "Feature",
  "properties": {
    "iso:country":"DE",
    "sg:address":"Alpenstr. 1",
    "sg:city":"Altenstadt",
    "sg:phone":"+49 8861/8686",
    "sg:postcode":"86972",
    "sg:province":"Bayern",
    "wof:name":"Karl Socher",
    "wof:placetype":"venue"
},
  "geometry": {"coordinates":[10.875543,47.822659],"type":"Point"}
}