{
  "type": "Feature",
  "properties": {
    "iso:country":"DE",
    "sg:address":"Platter Str. 176",
    "sg:city":"Wiesbaden",
    "sg:phone":"+49 611/598474",
    "sg:postcode":"65193",
    "sg:province":"Hessen",
    "wof:name":"J\u00f6rg Becker",
    "wof:placetype":"venue"
},
  "geometry": {"coordinates":[8.220367,50.0966],"type":"Point"}
}