{
  "type": "Feature",
  "properties": {
    "iso:country":"DE",
    "sg:address":"Auf dem Heiken 3",
    "sg:city":"Dortmund",
    "sg:phone":"+49 231/370953",
    "sg:postcode":"44357",
    "sg:province":"Nordrhein-Westfalen",
    "wof:name":"Milado K\u00e4sewerk Gmbh",
    "wof:placetype":"venue"
},
  "geometry": {"coordinates":[7.3791379929,51.5519523621],"type":"Point"}
}