{
  "type": "Feature",
  "properties": {
    "iso:country":"DE",
    "sg:address":"Greitweg 48 Grone",
    "sg:city":"G\u00f6ttingen",
    "sg:phone":"+49 4955/193026",
    "sg:postcode":"37081",
    "sg:province":"Niedersachsen",
    "wof:name":"Saline Luisen Hall Gmbh",
    "wof:placetype":"venue"
},
  "geometry": {"coordinates":[9.8977603912,51.5307807922],"type":"Point"}
}