{
  "type": "Feature",
  "properties": {
    "iso:country":"DE",
    "sg:address":"Stadtheider Str. 34 a",
    "sg:city":"Bielefeld",
    "sg:phone":"+49 521/800070",
    "sg:postcode":"33609",
    "sg:province":"Nordrhein-Westfalen",
    "wof:name":"Friedrich Wietzke Gmbh",
    "wof:placetype":"venue"
},
  "geometry": {"coordinates":[8.549536705,52.0390739441],"type":"Point"}
}