{
  "type": "Feature",
  "properties": {
    "iso:country":"DE",
    "sg:address":"Kanalstr. Nord 39",
    "sg:city":"Gro\u00dfefehn",
    "sg:phone":"+49 4943/2127",
    "sg:postcode":"26629",
    "sg:province":"Niedersachsen",
    "wof:name":"Dr. Heinrich Hartmann Tierarzt",
    "wof:placetype":"venue"
},
  "geometry": {"coordinates":[7.5865859985,53.403755188],"type":"Point"}
}