{
  "type": "Feature",
  "properties": {
    "iso:country":"DE",
    "sg:address":"Gotha-Allee 19",
    "sg:city":"Berlin",
    "sg:phone":"+49 30/30120808",
    "sg:postcode":"14052",
    "sg:province":"Berlin",
    "wof:name":"Dietmar Liste",
    "wof:placetype":"venue"
},
  "geometry": {"coordinates":[13.2579965591,52.520488739],"type":"Point"}
}