{
  "type": "Feature",
  "properties": {
    "iso:country":"DE",
    "sg:address":"Kornblumengasse 1",
    "sg:city":"Wetzlar",
    "sg:postcode":"35578",
    "sg:province":"Hessen",
    "wof:name":"Palais Papius",
    "wof:placetype":"venue"
},
  "geometry": {"coordinates":[8.502169,50.553371],"type":"Point"}
}