{
  "type": "Feature",
  "properties": {
    "iso:country":"DE",
    "sg:address":"Rathausplatz 1",
    "sg:city":"Tannheim",
    "sg:phone":"+49 8395/9270",
    "sg:postcode":"88459",
    "sg:province":"Baden-W\u00fcrttemberg",
    "wof:name":"Notariat Tannheim",
    "wof:placetype":"venue"
},
  "geometry": {"coordinates":[10.0833616257,47.9993133545],"type":"Point"}
}