{
  "type": "Feature",
  "properties": {
    "iso:country":"DE",
    "sg:address":"M\u00fcllerstr. 51a",
    "sg:city":"Berlin",
    "sg:phone":"+49 30/4524423",
    "sg:postcode":"13349",
    "sg:province":"Berlin",
    "wof:name":"B\u00f6hm-b\u00fcromaschinen Inh. Georg B\u00f6hm",
    "wof:placetype":"venue"
},
  "geometry": {"coordinates":[13.3482313156,52.5528564453],"type":"Point"}
}