{
  "type": "Feature",
  "properties": {
    "iso:country":"DE",
    "sg:address":"Turmstr. 1",
    "sg:city":"Erlensee",
    "sg:phone":"+49 6183/6055",
    "sg:postcode":"63526",
    "sg:province":"Hessen",
    "wof:name":"Dr. Med. Dieter Hanfstingl",
    "wof:placetype":"venue"
},
  "geometry": {"coordinates":[8.9799127579,50.1696128845],"type":"Point"}
}