{
  "type": "Feature",
  "properties": {
    "iso:country":"DE",
    "sg:address":"Schulstr. 17",
    "sg:city":"Sedlitz",
    "sg:phone":"+49 3573/3577",
    "sg:postcode":"01968",
    "sg:province":"Brandenburg",
    "wof:name":"Dieter Franz",
    "wof:placetype":"venue"
},
  "geometry": {"coordinates":[14.057806015,51.5508804321],"type":"Point"}
}