{
  "type": "Feature",
  "properties": {
    "iso:country":"DE",
    "sg:address":"Balkenbornstr. 40",
    "sg:city":"Uetze",
    "sg:phone":"+49 5173/7245",
    "sg:postcode":"31311",
    "sg:province":"Niedersachsen",
    "wof:name":"Wolfgang Seffer",
    "wof:placetype":"venue"
},
  "geometry": {"coordinates":[10.1869249344,52.4639434814],"type":"Point"}
}