{
  "type": "Feature",
  "properties": {
    "iso:country":"DE",
    "sg:address":"Brahmsstr. 27",
    "sg:city":"Cuxhaven",
    "sg:phone":"+49 4721/39011",
    "sg:postcode":"27474",
    "sg:province":"Niedersachsen",
    "wof:name":"Hans-j\u00fcrgen Merkl Ergotherapeutsche Praxis",
    "wof:placetype":"venue"
},
  "geometry": {"coordinates":[8.686457,53.866959],"type":"Point"}
}