{
  "type": "Feature",
  "properties": {
    "iso:country":"DE",
    "sg:address":"Sandweg 49",
    "sg:city":"Frankfurt",
    "sg:phone":"+49 69/444407",
    "sg:postcode":"60316",
    "sg:province":"Hessen",
    "wof:name":"La Cava Inh. Fernando Garcia",
    "wof:placetype":"venue"
},
  "geometry": {"coordinates":[8.6972408295,50.1188621521],"type":"Point"}
}