{
  "type": "Feature",
  "properties": {
    "iso:country":"DE",
    "sg:address":"Liebigstr. 1",
    "sg:city":"Hilden",
    "sg:postcode":"40721",
    "sg:province":"Nordrhein-Westfalen",
    "wof:name":"Label Printers Of Europe Gmbh",
    "wof:placetype":"venue"
},
  "geometry": {"coordinates":[6.915798,51.163738],"type":"Point"}
}