{
  "type": "Feature",
  "properties": {
    "iso:country":"DE",
    "sg:address":"Heiligengrabstr. 12",
    "sg:city":"Hof",
    "sg:postcode":"95028",
    "sg:province":"Bayern",
    "wof:name":"Adelheid Marte",
    "wof:placetype":"venue"
},
  "geometry": {"coordinates":[11.9234027863,50.3217506409],"type":"Point"}
}