{
  "type": "Feature",
  "properties": {
    "iso:country":"DE",
    "sg:address":"Gottfried-Keller-Str. 3",
    "sg:city":"Heilbronn",
    "sg:phone":"+49 7131/177958",
    "sg:postcode":"74076",
    "sg:province":"Baden-W\u00fcrttemberg",
    "wof:name":"Gerhard Boy",
    "wof:placetype":"venue"
},
  "geometry": {"coordinates":[9.225784,49.154255],"type":"Point"}
}