{
  "type": "Feature",
  "properties": {
    "iso:country":"DE",
    "sg:address":"Erzring 18",
    "sg:city":"Lengede",
    "sg:phone":"+49 5344/5505",
    "sg:postcode":"38268",
    "sg:province":"Niedersachsen",
    "wof:name":"H.-u. Heuer",
    "wof:placetype":"venue"
},
  "geometry": {"coordinates":[10.3226366043,52.2014961243],"type":"Point"}
}