{
  "type": "Feature",
  "properties": {
    "iso:country":"DE",
    "sg:address":"Alzenauer Str. 18",
    "sg:city":"Alzenau",
    "sg:phone":"+49 6023/1577",
    "sg:postcode":"63755",
    "sg:province":"Bayern",
    "wof:name":"Gerhard Ehser",
    "wof:placetype":"venue"
},
  "geometry": {"coordinates":[9.070545,50.056828],"type":"Point"}
}