{
  "type": "Feature",
  "properties": {
    "iso:country":"DE",
    "sg:address":"Am M\u00fchlberg 16",
    "sg:city":"Bad Homburg",
    "sg:phone":"+49 6172/928681",
    "sg:postcode":"61348",
    "sg:province":"Hessen",
    "wof:name":"The Cutting Crew Ingenieurb\u00fcro Gmbh",
    "wof:placetype":"venue"
},
  "geometry": {"coordinates":[8.6148328781,50.225276947],"type":"Point"}
}