{
  "type": "Feature",
  "properties": {
    "iso:country":"DE",
    "sg:address":"Hessenweg 11",
    "sg:city":"Sch\u00fcttorf",
    "sg:phone":"+49 5923/990741",
    "sg:postcode":"48465",
    "sg:province":"Niedersachsen",
    "wof:name":"J. R\u00f6nne Immobilienmakler",
    "wof:placetype":"venue"
},
  "geometry": {"coordinates":[7.2222242355,52.3189086914],"type":"Point"}
}