{
  "type": "Feature",
  "properties": {
    "iso:country":"DE",
    "sg:address":"Pixisstr. 14",
    "sg:city":"P\u00f6cking",
    "sg:phone":"+49 8157/2072",
    "sg:postcode":"82343",
    "sg:province":"Bayern",
    "wof:name":"Schafflhuber Gmbh",
    "wof:placetype":"venue"
},
  "geometry": {"coordinates":[11.305951,47.966896],"type":"Point"}
}