{
  "type": "Feature",
  "properties": {
    "iso:country":"DE",
    "sg:address":"Ringstr. 9-11",
    "sg:city":"K\u00f6ln",
    "sg:phone":"+49 221/395151",
    "sg:postcode":"50996",
    "sg:province":"Nordrhein-Westfalen",
    "wof:name":"Tanzschule Thyssen",
    "wof:placetype":"venue"
},
  "geometry": {"coordinates":[6.9912161827,50.8908843994],"type":"Point"}
}