{
  "type": "Feature",
  "properties": {
    "iso:country":"DE",
    "sg:address":"Barbiser Str. 29",
    "sg:city":"Bad Lauterberg",
    "sg:postcode":"37431",
    "sg:province":"Niedersachsen",
    "wof:name":"Malerwerkstatt Wicke Gmbh",
    "wof:placetype":"venue"
},
  "geometry": {"coordinates":[10.4150743484,51.6199493408],"type":"Point"}
}