{
  "type": "Feature",
  "properties": {
    "iso:country":"DE",
    "sg:address":"Tenschstr. 1",
    "sg:city":"Ottweiler",
    "sg:postcode":"66564",
    "sg:province":"Saarland",
    "wof:name":"Ev. Kirchengemeinde",
    "wof:placetype":"venue"
},
  "geometry": {"coordinates":[7.1606020927,49.404209137],"type":"Point"}
}