{
  "type": "Feature",
  "properties": {
    "iso:country":"DE",
    "sg:address":"Berliner Str. 13",
    "sg:city":"Dietzenbach",
    "sg:phone":"+49 6074/26052",
    "sg:postcode":"63128",
    "sg:province":"Hessen",
    "wof:name":"Dr. Med. Amir S. Nadjamabadi",
    "wof:placetype":"venue"
},
  "geometry": {"coordinates":[8.7704162598,49.9960479736],"type":"Point"}
}