{
  "type": "Feature",
  "properties": {
    "iso:country":"DE",
    "sg:address":"Wolf-Hirth-Str 9",
    "sg:city":"Esslingen",
    "sg:phone":"+49 711/31547160",
    "sg:postcode":"73730",
    "sg:province":"Baden-W\u00fcrttemberg",
    "wof:name":"Graver Technologies Europe Gmbh",
    "wof:placetype":"venue"
},
  "geometry": {"coordinates":[9.3474149704,48.7171478271],"type":"Point"}
}