{
  "type": "Feature",
  "properties": {
    "iso:country":"DE",
    "sg:address":"Im Tigg 1",
    "sg:city":"Paderborn",
    "sg:phone":"+49 5251/910434",
    "sg:postcode":"33106",
    "sg:province":"Nordrhein-Westfalen",
    "wof:name":"Wohn- Und Gesch\u00e4ftshaus Th\u00f6ne Gmbh",
    "wof:placetype":"venue"
},
  "geometry": {"coordinates":[8.696841,51.687046],"type":"Point"}
}