{
  "type": "Feature",
  "properties": {
    "iso:country":"DE",
    "sg:address":"Repitzer Weg 1",
    "sg:city":"Torgau",
    "sg:phone":"+49 3421/904484",
    "sg:postcode":"04860",
    "sg:province":"Sachsen",
    "wof:name":"Stube F\u00f6rdertechnik Gmbh",
    "wof:placetype":"venue"
},
  "geometry": {"coordinates":[13.0042457581,51.5732345581],"type":"Point"}
}