{
  "type": "Feature",
  "properties": {
    "iso:country":"DE",
    "sg:address":"Werdauer Allee 3",
    "sg:city":"Meerane",
    "sg:phone":"+49 4937/644040",
    "sg:postcode":"08393",
    "sg:province":"Sachsen",
    "wof:name":"Brose Fahrzeugteile & Co. Kg",
    "wof:placetype":"venue"
},
  "geometry": {"coordinates":[12.4545440674,50.8289794922],"type":"Point"}
}