{
  "type": "Feature",
  "properties": {
    "iso:country":"DE",
    "sg:address":"Poststr 18",
    "sg:city":"Hamburg",
    "sg:phone":"+49 40/3553210",
    "sg:postcode":"20354",
    "sg:province":"Hamburg",
    "wof:name":"Sprint Satz & Litho Produktions Gmbh",
    "wof:placetype":"venue"
},
  "geometry": {"coordinates":[9.989184,53.554096],"type":"Point"}
}