{
  "type": "Feature",
  "properties": {
    "iso:country":"DE",
    "sg:address":"S\u00fcdkamener Str. 33 B",
    "sg:city":"Kamen",
    "sg:phone":"+49 2307/71011",
    "sg:postcode":"59174",
    "sg:province":"Nordrhein-Westfalen",
    "wof:name":"Thiel",
    "wof:placetype":"venue"
},
  "geometry": {"coordinates":[7.657231,51.577145],"type":"Point"}
}