{
  "type": "Feature",
  "properties": {
    "iso:country":"DE",
    "sg:address":"D\u00fcrner Str. 9",
    "sg:city":"Breitenbrunn",
    "sg:phone":"+49 9495/281",
    "sg:postcode":"92363",
    "sg:province":"Bayern",
    "wof:name":"A. Braun",
    "wof:placetype":"venue"
},
  "geometry": {"coordinates":[11.619043,49.083855],"type":"Point"}
}