{
  "type": "Feature",
  "properties": {
    "iso:country":"DE",
    "sg:address":"Schlo\u00dfstr. 32",
    "sg:city":"Ludwigslust",
    "sg:phone":"+49 3874/21630",
    "sg:postcode":"19288",
    "sg:province":"Mecklenburg-Vorpommern",
    "wof:name":"Joachim Witte",
    "wof:placetype":"venue"
},
  "geometry": {"coordinates":[11.4940519333,53.3245506287],"type":"Point"}
}