{
  "type": "Feature",
  "properties": {
    "iso:country":"DE",
    "sg:address":"Im Steinchen 1",
    "sg:city":"Asbach",
    "sg:phone":"+49 2683/43069",
    "sg:postcode":"53567",
    "sg:province":"Rheinland-Pfalz",
    "wof:name":"Fischer",
    "wof:placetype":"venue"
},
  "geometry": {"coordinates":[7.4239997864,50.6606178284],"type":"Point"}
}