{
  "type": "Feature",
  "properties": {
    "iso:country":"DE",
    "sg:address":"Muellerstrasse 41",
    "sg:city":"M\u00fcnchen",
    "sg:phone":"+49 89/26023340",
    "sg:postcode":"80469",
    "sg:province":"Bayern",
    "wof:name":"Sonar Unternehmens- Und Personalberatung Gmbh",
    "wof:placetype":"venue"
},
  "geometry": {"coordinates":[11.5684995651,48.131187439],"type":"Point"}
}