{
  "type": "Feature",
  "properties": {
    "iso:country":"DE",
    "sg:address":"Hinterweg",
    "sg:city":"Steffenberg",
    "sg:postcode":"35239",
    "sg:province":"Hessen",
    "wof:name":"Stich Verwaltungs Gmbh",
    "wof:placetype":"venue"
},
  "geometry": {"coordinates":[8.4861402512,50.815738678],"type":"Point"}
}