{
  "type": "Feature",
  "properties": {
    "iso:country":"DE",
    "sg:address":"Steigstr. 63",
    "sg:city":"Sonnenb\u00fchl",
    "sg:postcode":"72820",
    "sg:province":"Baden-W\u00fcrttemberg",
    "wof:name":"Consensus Textilproduktions- Und Handelsgesellschaft Mbh",
    "wof:placetype":"venue"
},
  "geometry": {"coordinates":[9.184433,48.386864],"type":"Point"}
}