{
  "type": "Feature",
  "properties": {
    "iso:country":"DE",
    "sg:address":"Bochumer Str. 53",
    "sg:city":"Hattingen",
    "sg:phone":"+49 2324/80060",
    "sg:postcode":"45529",
    "sg:province":"Nordrhein-Westfalen",
    "wof:name":"Wurm",
    "wof:placetype":"venue"
},
  "geometry": {"coordinates":[7.169353,51.407501],"type":"Point"}
}