{
  "type": "Feature",
  "properties": {
    "iso:country":"DE",
    "sg:address":"Bleicherstr. 8",
    "sg:city":"Kempten",
    "sg:phone":"+49 831/571150",
    "sg:postcode":"87437",
    "sg:province":"Bayern",
    "wof:name":"Gustav Epple Hoch- Und Tiefbau Gmbh",
    "wof:placetype":"venue"
},
  "geometry": {"coordinates":[10.3268289566,47.7382125854],"type":"Point"}
}