{
  "type": "Feature",
  "properties": {
    "iso:country":"DE",
    "sg:address":"Kr\u00e4nkelsweg 6",
    "sg:city":"Viersen",
    "sg:phone":"+49 2162/936700",
    "sg:postcode":"41748",
    "sg:province":"Nordrhein-Westfalen",
    "wof:name":"Duchell Gmbh",
    "wof:placetype":"venue"
},
  "geometry": {"coordinates":[6.3987579346,51.2656478882],"type":"Point"}
}