{
  "type": "Feature",
  "properties": {
    "iso:country":"DE",
    "sg:address":"Gubener Str. 39",
    "sg:city":"Berlin",
    "sg:postcode":"10243",
    "sg:province":"Berlin",
    "wof:name":"Roon-multimedia Oliver Sch\u00fctt & Co. Kg",
    "wof:placetype":"venue"
},
  "geometry": {"coordinates":[13.4498586655,52.5104980469],"type":"Point"}
}