{
  "type": "Feature",
  "properties": {
    "iso:country":"DE",
    "sg:address":"Vordere Marktstr. 9",
    "sg:city":"N\u00fcrnberg",
    "sg:phone":"+49 911/661769",
    "sg:postcode":"90441",
    "sg:province":"Bayern",
    "wof:name":"I. Binz",
    "wof:placetype":"venue"
},
  "geometry": {"coordinates":[11.046885,49.432636],"type":"Point"}
}