{
  "type": "Feature",
  "properties": {
    "iso:country":"DE",
    "sg:address":"D\u00fcrrer Berg 1",
    "sg:city":"Sosa",
    "sg:phone":"+49 37752/8208",
    "sg:postcode":"08326",
    "sg:province":"Sachsen",
    "wof:name":"Johannes H\u00e4cker",
    "wof:placetype":"venue"
},
  "geometry": {"coordinates":[12.6481866837,50.5022087097],"type":"Point"}
}