{
  "type": "Feature",
  "properties": {
    "iso:country":"DE",
    "sg:address":"Gotenstr. 136",
    "sg:city":"Bonn",
    "sg:phone":"+49 228/375762",
    "sg:postcode":"53175",
    "sg:province":"Nordrhein-Westfalen",
    "wof:name":"Siegfried M\u00fcller Grabdenkm\u00e4ler",
    "wof:placetype":"venue"
},
  "geometry": {"coordinates":[7.147767067,50.6962013245],"type":"Point"}
}