{
  "type": "Feature",
  "properties": {
    "iso:country":"DE",
    "sg:address":"Am Eichwald 39",
    "sg:city":"Homburg",
    "sg:postcode":"66424",
    "sg:province":"Saarland",
    "wof:name":"Koe Sport- Und Sanit\u00e4tshaus Gmbh",
    "wof:placetype":"venue"
},
  "geometry": {"coordinates":[7.3255281448,49.3669128418],"type":"Point"}
}