{
  "type": "Feature",
  "properties": {
    "iso:country":"DE",
    "sg:address":"Industriestr. 13",
    "sg:city":"Sulzbach-Rosenberg",
    "sg:phone":"+49 9661/10520",
    "sg:postcode":"92237",
    "sg:province":"Bayern",
    "wof:name":"Amberger Werkzeugbau Gmbh",
    "wof:placetype":"venue"
},
  "geometry": {"coordinates":[11.793208,49.491661],"type":"Point"}
}