{
  "type": "Feature",
  "properties": {
    "iso:country":"DE",
    "sg:address":"Scharnweberstr. 114",
    "sg:city":"Berlin",
    "sg:phone":"+49 30/6452323",
    "sg:postcode":"12587",
    "sg:province":"Berlin",
    "wof:name":"Bruno Keller",
    "wof:placetype":"venue"
},
  "geometry": {"coordinates":[13.627158165,52.448009491],"type":"Point"}
}