{
  "type": "Feature",
  "properties": {
    "iso:country":"DE",
    "sg:address":"Graf-Stolberg-Str. 81",
    "sg:city":"Bad Bramstedt",
    "sg:phone":"+49 4192/9918",
    "sg:postcode":"24576",
    "sg:province":"Schleswig-Holstein",
    "wof:name":"U. L\u00fcder",
    "wof:placetype":"venue"
},
  "geometry": {"coordinates":[9.8871469498,53.9272041321],"type":"Point"}
}