{
  "type": "Feature",
  "properties": {
    "iso:country":"DE",
    "sg:address":"Glauchauer Str. 2",
    "sg:city":"Waldenburg",
    "sg:postcode":"08396",
    "sg:province":"Sachsen",
    "wof:name":"Golde",
    "wof:placetype":"venue"
},
  "geometry": {"coordinates":[12.602745,50.874001],"type":"Point"}
}