{
  "type": "Feature",
  "properties": {
    "iso:country":"DE",
    "sg:address":"Zum Schankstor 7",
    "sg:city":"Welschbillig",
    "sg:phone":"+49 6506/237",
    "sg:postcode":"54298",
    "sg:province":"Rheinland-Pfalz",
    "wof:name":"Bernhard Jubelius",
    "wof:placetype":"venue"
},
  "geometry": {"coordinates":[6.5679869652,49.8521385193],"type":"Point"}
}