{
  "type": "Feature",
  "properties": {
    "iso:country":"DE",
    "sg:address":"Hindenburgstr. 34",
    "sg:city":"Kirchheim",
    "sg:phone":"+49 7021/984810",
    "sg:postcode":"73230",
    "sg:province":"Baden-W\u00fcrttemberg",
    "wof:name":"Fiskal Steuerberatungsges. Treuhandges. Mbh",
    "wof:placetype":"venue"
},
  "geometry": {"coordinates":[9.4532346725,48.6432571411],"type":"Point"}
}