{
  "type": "Feature",
  "properties": {
    "iso:country":"DE",
    "sg:address":"Am Bahnhof 2",
    "sg:city":"Lentf\u00f6hrden",
    "sg:phone":"+49 4192/2761",
    "sg:postcode":"24632",
    "sg:province":"Schleswig-Holstein",
    "wof:name":"Manfred Katzer",
    "wof:placetype":"venue"
},
  "geometry": {"coordinates":[9.8884878159,53.8762588501],"type":"Point"}
}