{
  "type": "Feature",
  "properties": {
    "iso:country":"DE",
    "sg:address":"Kampstr. 20",
    "sg:city":"D\u00fcsseldorf",
    "sg:phone":"+49 211/763326",
    "sg:postcode":"40591",
    "sg:province":"Nordrhein-Westfalen",
    "wof:name":"Peter Ludes Architekt",
    "wof:placetype":"venue"
},
  "geometry": {"coordinates":[6.817835,51.190849],"type":"Point"}
}