{
  "type": "Feature",
  "properties": {
    "iso:country":"DE",
    "sg:address":"J\u00e4gerstr. 11",
    "sg:city":"Herne",
    "sg:phone":"+49 2325/31304",
    "sg:postcode":"44651",
    "sg:province":"Nordrhein-Westfalen",
    "wof:name":"Renate W\u00f6lfing Steuerberaterin",
    "wof:placetype":"venue"
},
  "geometry": {"coordinates":[7.1669521332,51.5168228149],"type":"Point"}
}