{
  "type": "Feature",
  "properties": {
    "iso:country":"DE",
    "sg:address":"Am Sportplatz 6",
    "sg:city":"Gunzenhausen",
    "sg:phone":"+49 9831/2414",
    "sg:postcode":"91710",
    "sg:province":"Bayern",
    "wof:name":"Gastst\u00e4tte S. Pudewell",
    "wof:placetype":"venue"
},
  "geometry": {"coordinates":[10.7553281784,49.1072998047],"type":"Point"}
}