{
  "type": "Feature",
  "properties": {
    "iso:country":"DE",
    "sg:address":"Kirchplatz 5",
    "sg:city":"Frauenneuharting",
    "sg:phone":"+49 8092/85550",
    "sg:postcode":"83553",
    "sg:province":"Bayern",
    "wof:name":"J. Wieser Elektroinstallation",
    "wof:placetype":"venue"
},
  "geometry": {"coordinates":[12.048094,48.039295],"type":"Point"}
}