{
  "type": "Feature",
  "properties": {
    "iso:country":"DE",
    "sg:address":"Im Rudert 27",
    "sg:city":"Marburg",
    "sg:phone":"+49 6421/41670",
    "sg:postcode":"35043",
    "sg:province":"Hessen",
    "wof:name":"Knobel Und Koch Squash",
    "wof:placetype":"venue"
},
  "geometry": {"coordinates":[8.7639026642,50.7858657837],"type":"Point"}
}