{
  "type": "Feature",
  "properties": {
    "iso:country":"DE",
    "sg:address":"Wittener Str. 13",
    "sg:city":"Gevelsberg",
    "sg:phone":"+49 2332/71256",
    "sg:postcode":"58285",
    "sg:province":"Nordrhein-Westfalen",
    "wof:name":"Kulturverein Gevelsberg E. V. Siegfried Butzkamm",
    "wof:placetype":"venue"
},
  "geometry": {"coordinates":[7.3379740715,51.3209533691],"type":"Point"}
}