{
  "type": "Feature",
  "properties": {
    "iso:country":"DE",
    "sg:address":"Bahnhofstr. 37 a",
    "sg:city":"Raunheim",
    "sg:phone":"+49 6142/21425",
    "sg:postcode":"65479",
    "sg:province":"Hessen",
    "wof:name":"Hessen-stube",
    "wof:placetype":"venue"
},
  "geometry": {"coordinates":[8.4533529282,50.0126991272],"type":"Point"}
}