{
  "type": "Feature",
  "properties": {
    "iso:country":"DE",
    "sg:address":"Rockwinkeler Landstr. 108",
    "sg:city":"Bremen",
    "sg:phone":"+49 421/424143",
    "sg:postcode":"28325",
    "sg:province":"Bremen",
    "wof:name":"Mk Sports Inh. Michael Koch",
    "wof:placetype":"venue"
},
  "geometry": {"coordinates":[8.94057,53.077541],"type":"Point"}
}