{
  "type": "Feature",
  "properties": {
    "iso:country":"DE",
    "sg:address":"Auf dem H\u00fcbel 10",
    "sg:city":"Dienstweiler",
    "sg:phone":"+49 6782/7481",
    "sg:postcode":"55765",
    "sg:province":"Rheinland-Pfalz",
    "wof:name":"Willi Finck",
    "wof:placetype":"venue"
},
  "geometry": {"coordinates":[7.186519,49.638336],"type":"Point"}
}