{
  "type": "Feature",
  "properties": {
    "iso:country":"DE",
    "sg:address":"Harth\u00f6fe 14",
    "sg:city":"Nusplingen",
    "sg:postcode":"72362",
    "sg:province":"Baden-W\u00fcrttemberg",
    "wof:name":"Rk Trading Gmbh",
    "wof:placetype":"venue"
},
  "geometry": {"coordinates":[8.9414405823,48.1188049316],"type":"Point"}
}