{
  "type": "Feature",
  "properties": {
    "iso:country":"DE",
    "sg:address":"Hinter dem Meierhofe 2",
    "sg:city":"Salzhemmendorf",
    "sg:postcode":"31020",
    "sg:province":"Niedersachsen",
    "wof:name":"Tydecks Gesch\u00e4ftsf\u00fchrungs Gmbh",
    "wof:placetype":"venue"
},
  "geometry": {"coordinates":[9.589586,52.06757],"type":"Point"}
}