{
  "type": "Feature",
  "properties": {
    "iso:country":"DE",
    "sg:address":"M\u00fchlener Str. 36",
    "sg:city":"Wiehl",
    "sg:phone":"+49 2262/72270",
    "sg:postcode":"51674",
    "sg:province":"Nordrhein-Westfalen",
    "wof:name":"Truninger Gmbh",
    "wof:placetype":"venue"
},
  "geometry": {"coordinates":[7.513969,50.947277],"type":"Point"}
}