{
  "type": "Feature",
  "properties": {
    "iso:country":"DE",
    "sg:address":"Fichtental",
    "sg:city":"Prackenbach",
    "sg:phone":"+49 9942/8585",
    "sg:postcode":"94267",
    "sg:province":"Bayern",
    "wof:name":"H. Pellkofer",
    "wof:placetype":"venue"
},
  "geometry": {"coordinates":[12.842354,49.104683],"type":"Point"}
}