{
  "type": "Feature",
  "properties": {
    "iso:country":"DE",
    "sg:address":"Teggingerstr. 24",
    "sg:city":"Radolfzell",
    "sg:phone":"+49 7732/972024",
    "sg:postcode":"78315",
    "sg:province":"Baden-W\u00fcrttemberg",
    "wof:name":"J. Rinn",
    "wof:placetype":"venue"
},
  "geometry": {"coordinates":[8.9732522964,47.7383956909],"type":"Point"}
}