{
  "type": "Feature",
  "properties": {
    "iso:country":"DE",
    "sg:address":"Mommsenstr. 64",
    "sg:city":"Berlin",
    "sg:phone":"+49 30/8813950",
    "sg:postcode":"10629",
    "sg:province":"Berlin",
    "wof:name":"Elke \u00dcbermuth",
    "wof:placetype":"venue"
},
  "geometry": {"coordinates":[13.3175106049,52.5029220581],"type":"Point"}
}