{
  "type": "Feature",
  "properties": {
    "iso:country":"DE",
    "sg:address":"Franz-Kleine-Str. 18",
    "sg:city":"Salzkotten",
    "sg:phone":"+49 9725/7070",
    "sg:postcode":"33154",
    "sg:province":"Nordrhein-Westfalen",
    "wof:name":"M\u00dcller Landtechnik Kg",
    "wof:placetype":"venue"
},
  "geometry": {"coordinates":[10.18562,50.118069],"type":"Point"}
}