{
  "type": "Feature",
  "properties": {
    "iso:country":"DE",
    "sg:address":"Nixb\u00f6thestr. 27",
    "sg:city":"Dillenburg",
    "sg:postcode":"35683",
    "sg:province":"Hessen",
    "wof:name":"Nicolo Pitta E. K.",
    "wof:placetype":"venue"
},
  "geometry": {"coordinates":[8.2795505524,50.7430038452],"type":"Point"}
}