{
  "type": "Feature",
  "properties": {
    "iso:country":"DE",
    "sg:address":"Vorburggasse 1-3",
    "sg:city":"Meersburg",
    "sg:phone":"+49 7532/440230",
    "sg:postcode":"88709",
    "sg:province":"Baden-W\u00fcrttemberg",
    "wof:name":"Dr.- Zimmermann-stift",
    "wof:placetype":"venue"
},
  "geometry": {"coordinates":[9.272913,47.69416],"type":"Point"}
}