{
  "type": "Feature",
  "properties": {
    "iso:country":"DE",
    "sg:address":"Schulstr. 8",
    "sg:city":"Grimma",
    "sg:phone":"+49 3437/911160",
    "sg:postcode":"04668",
    "sg:province":"Sachsen",
    "wof:name":"Elfriede Barsuhn",
    "wof:placetype":"venue"
},
  "geometry": {"coordinates":[12.7236785889,51.2341117859],"type":"Point"}
}