{
  "type": "Feature",
  "properties": {
    "iso:country":"DE",
    "sg:address":"Schulzengasse 1",
    "sg:city":"Eningen",
    "sg:phone":"+49 7121/88797",
    "sg:postcode":"72800",
    "sg:province":"Baden-W\u00fcrttemberg",
    "wof:name":"Norma Gmbh & Co. Kg Lebensmittelfilialbetrieb",
    "wof:placetype":"venue"
},
  "geometry": {"coordinates":[9.2580347061,48.4859199524],"type":"Point"}
}