{
  "type": "Feature",
  "properties": {
    "iso:country":"DE",
    "sg:address":"Schlo\u00dfstr. 11",
    "sg:city":"Meitingen",
    "sg:phone":"+49 8271/5113",
    "sg:postcode":"86405",
    "sg:province":"Bayern",
    "wof:name":"Kinlinger Textil- Und Bekleidungshaus Gmbh",
    "wof:placetype":"venue"
},
  "geometry": {"coordinates":[10.851645,48.541363],"type":"Point"}
}