{
  "type": "Feature",
  "properties": {
    "iso:country":"DE",
    "sg:address":"Alberichstr. 9",
    "sg:city":"N\u00fcrnberg",
    "sg:phone":"+49 911/468902",
    "sg:postcode":"90461",
    "sg:province":"Bayern",
    "wof:name":"Comet",
    "wof:placetype":"venue"
},
  "geometry": {"coordinates":[11.0989809036,49.4391288757],"type":"Point"}
}