{
  "type": "Feature",
  "properties": {
    "iso:country":"DE",
    "sg:address":"Auf der Saalbrede 29",
    "sg:city":"Detmold",
    "sg:phone":"+49 5231/870660",
    "sg:postcode":"32756",
    "sg:province":"Nordrhein-Westfalen",
    "wof:name":"Frhr. Dr. Von Ungern-sternberg Arzt F\u00fcr Allgemein Medizin",
    "wof:placetype":"venue"
},
  "geometry": {"coordinates":[8.8481235504,51.9305763245],"type":"Point"}
}