{
  "type": "Feature",
  "properties": {
    "iso:country":"DE",
    "sg:address":"Bahnhofstr. 3",
    "sg:city":"B\u00fcdingen",
    "sg:phone":"+49 6042/7458",
    "sg:postcode":"63654",
    "sg:province":"Hessen",
    "wof:name":"Hans-j\u00fcrgen Brey",
    "wof:placetype":"venue"
},
  "geometry": {"coordinates":[9.1097202301,50.2912445068],"type":"Point"}
}