{
  "type": "Feature",
  "properties": {
    "iso:country":"DE",
    "sg:address":"Biergasse 18",
    "sg:city":"Bad Breisig",
    "sg:phone":"+49 2633/97106",
    "sg:postcode":"53498",
    "sg:province":"Rheinland-Pfalz",
    "wof:name":"Bodo Peters Antiquit\u00e4ten",
    "wof:placetype":"venue"
},
  "geometry": {"coordinates":[7.299941,50.510242],"type":"Point"}
}