{
  "type": "Feature",
  "properties": {
    "iso:country":"DE",
    "sg:address":"D\u00fcsseldorfer Str 28",
    "sg:city":"Ratingen",
    "sg:phone":"+49 2102/203222",
    "sg:postcode":"40878",
    "sg:province":"Nordrhein-Westfalen",
    "wof:name":"Sparkasse",
    "wof:placetype":"venue"
},
  "geometry": {"coordinates":[6.847839,51.296467],"type":"Point"}
}