{
  "type": "Feature",
  "properties": {
    "iso:country":"DE",
    "sg:address":"Burgstr. 19",
    "sg:city":"Sch\u00f6ningen",
    "sg:phone":"+49 5352/8477",
    "sg:postcode":"38364",
    "sg:province":"Niedersachsen",
    "wof:name":"B. Bartels",
    "wof:placetype":"venue"
},
  "geometry": {"coordinates":[10.9620656967,52.1436653137],"type":"Point"}
}