{
  "type": "Feature",
  "properties": {
    "iso:country":"DE",
    "sg:address":"Edellaitsch 16",
    "sg:city":"Himmelkron",
    "sg:phone":"+49 9273/5549",
    "sg:postcode":"95502",
    "sg:province":"Bayern",
    "wof:name":"H. Hahn",
    "wof:placetype":"venue"
},
  "geometry": {"coordinates":[11.596697,50.063484],"type":"Point"}
}