{
  "type": "Feature",
  "properties": {
    "iso:country":"DE",
    "sg:address":"Josef-Meissner-Str. 11",
    "sg:city":"Reil",
    "sg:phone":"+49 6542/21277",
    "sg:postcode":"56861",
    "sg:province":"Rheinland-Pfalz",
    "wof:name":"Friedhelm Heimann",
    "wof:placetype":"venue"
},
  "geometry": {"coordinates":[7.111896,50.012119],"type":"Point"}
}