{
  "type": "Feature",
  "properties": {
    "iso:country":"DE",
    "sg:address":"Lindenstr. 232",
    "sg:city":"Herzebrock-Clarholz",
    "sg:phone":"+49 5245/180170",
    "sg:postcode":"33442",
    "sg:province":"Nordrhein-Westfalen",
    "wof:name":"Albert Ernst Gmbh",
    "wof:placetype":"venue"
},
  "geometry": {"coordinates":[8.19619,51.897518],"type":"Point"}
}