{
  "type": "Feature",
  "properties": {
    "iso:country":"DE",
    "sg:address":"Pinneberger Weg 7",
    "sg:city":"Hamburg",
    "sg:phone":"+49 40/8506567",
    "sg:postcode":"20257",
    "sg:province":"Hamburg",
    "wof:name":"Andrea Jurk Hebamme",
    "wof:placetype":"venue"
},
  "geometry": {"coordinates":[9.948187,53.570145],"type":"Point"}
}