{
  "type": "Feature",
  "properties": {
    "iso:country":"DE",
    "sg:address":"Bahnhofstr. 82",
    "sg:city":"Lemf\u00f6rde",
    "sg:phone":"+49 5443/476",
    "sg:postcode":"49448",
    "sg:province":"Niedersachsen",
    "wof:name":"Fip Tanklager Gmbh",
    "wof:placetype":"venue"
},
  "geometry": {"coordinates":[8.3647136688,52.460609436],"type":"Point"}
}