{
  "type": "Feature",
  "properties": {
    "iso:country":"DE",
    "sg:address":"Ziegelh\u00fcttenstr. 61",
    "sg:city":"Babenhausen",
    "sg:phone":"+49 6073/4405",
    "sg:postcode":"64832",
    "sg:province":"Hessen",
    "wof:name":"Rose & Co. Gmbh",
    "wof:placetype":"venue"
},
  "geometry": {"coordinates":[8.93692,49.959724],"type":"Point"}
}