{
  "type": "Feature",
  "properties": {
    "iso:country":"DE",
    "sg:address":"Rahlstedter Str. 172",
    "sg:city":"Hamburg",
    "sg:phone":"+49 40/6772325",
    "sg:postcode":"22143",
    "sg:province":"Hamburg",
    "wof:name":"Elke Biesel",
    "wof:placetype":"venue"
},
  "geometry": {"coordinates":[10.163264,53.605186],"type":"Point"}
}