{
  "type": "Feature",
  "properties": {
    "iso:country":"DE",
    "sg:address":"Rottstr. 16",
    "sg:city":"B\u00f6hl-Iggelheim",
    "sg:phone":"+49 6324/76898",
    "sg:postcode":"67459",
    "sg:province":"Rheinland-Pfalz",
    "wof:name":"Georg Bohrmann",
    "wof:placetype":"venue"
},
  "geometry": {"coordinates":[8.306402,49.363491],"type":"Point"}
}