{
  "type": "Feature",
  "properties": {
    "iso:country":"DE",
    "sg:address":"Landemerter Weg 44",
    "sg:city":"Plettenberg",
    "sg:phone":"+49 2391/609420",
    "sg:postcode":"58840",
    "sg:province":"Nordrhein-Westfalen",
    "wof:name":"Manfred Rode Gmbh",
    "wof:placetype":"venue"
},
  "geometry": {"coordinates":[7.897437,51.207565],"type":"Point"}
}