{
  "type": "Feature",
  "properties": {
    "iso:country":"DE",
    "sg:address":"Roermonder Bahn",
    "sg:city":"Wegberg",
    "sg:phone":"+49 2436/2103",
    "sg:postcode":"41844",
    "sg:province":"Nordrhein-Westfalen",
    "wof:name":"Rita Giesen Tennisanlage",
    "wof:placetype":"venue"
},
  "geometry": {"coordinates":[6.1966819763,51.154624939],"type":"Point"}
}