{
  "type": "Feature",
  "properties": {
    "iso:country":"DE",
    "sg:address":"Hans-Sch\u00f6neberger-Str. 1",
    "sg:city":"St. Ingbert",
    "sg:phone":"+49 6894/7375",
    "sg:postcode":"66386",
    "sg:province":"Saarland",
    "wof:name":"J\u00f6rg Theobald",
    "wof:placetype":"venue"
},
  "geometry": {"coordinates":[7.1039609909,49.26720047],"type":"Point"}
}