{
  "type": "Feature",
  "properties": {
    "iso:country":"DE",
    "sg:address":"Stammelner Str. 26-28 Heppendorf",
    "sg:city":"Elsdorf",
    "sg:phone":"+49 7121/550037",
    "sg:postcode":"50189",
    "sg:province":"Nordrhein-Westfalen",
    "wof:name":"Zwiener & Partner Werbeagentur Gmbh",
    "wof:placetype":"venue"
},
  "geometry": {"coordinates":[9.191984,48.506805],"type":"Point"}
}