{
  "type": "Feature",
  "properties": {
    "iso:country":"DE",
    "sg:address":"Diepholzer Str. 1",
    "sg:city":"Vechta",
    "sg:phone":"+49 4441/6542",
    "sg:postcode":"49377",
    "sg:province":"Niedersachsen",
    "wof:name":"Margo",
    "wof:placetype":"venue"
},
  "geometry": {"coordinates":[8.287413,52.716816],"type":"Point"}
}