{
  "type": "Feature",
  "properties": {
    "iso:country":"DE",
    "sg:address":"Westend 39",
    "sg:city":"L\u00e4hden",
    "sg:postcode":"49774",
    "sg:province":"Niedersachsen",
    "wof:name":"Immobilien Maue Gmbh",
    "wof:placetype":"venue"
},
  "geometry": {"coordinates":[7.6374530792,52.7522277832],"type":"Point"}
}