{
  "type": "Feature",
  "properties": {
    "iso:country":"DE",
    "sg:address":"Klosterhof 1",
    "sg:city":"Bad W\u00f6rishofen",
    "sg:phone":"+49 8247/350239",
    "sg:postcode":"86825",
    "sg:province":"Bayern",
    "wof:name":"Kneipp-museum",
    "wof:placetype":"venue"
},
  "geometry": {"coordinates":[10.594456,48.003628],"type":"Point"}
}