{
  "type": "Feature",
  "properties": {
    "iso:country":"DE",
    "sg:address":"Im Rudert 6",
    "sg:city":"Marburg",
    "sg:phone":"+49 6421/44908",
    "sg:postcode":"35043",
    "sg:province":"Hessen",
    "wof:name":"Hildebrandt Immobilienmakler",
    "wof:placetype":"venue"
},
  "geometry": {"coordinates":[8.7642755508,50.7844238281],"type":"Point"}
}