{
  "type": "Feature",
  "properties": {
    "iso:country":"DE",
    "sg:address":"Pf\u00e4hlerstr. 2",
    "sg:city":"Saarbr\u00fccken",
    "sg:postcode":"66117",
    "sg:province":"Saarland",
    "wof:name":"St\u00e4dt. Kinderheim Am Ordensgut",
    "wof:placetype":"venue"
},
  "geometry": {"coordinates":[6.9723381996,49.2313346863],"type":"Point"}
}