{
  "type": "Feature",
  "properties": {
    "iso:country":"DE",
    "sg:address":"Zur Nachtheide 131",
    "sg:city":"Berlin",
    "sg:phone":"+49 30/6516788",
    "sg:postcode":"12557",
    "sg:province":"Berlin",
    "wof:name":"Dr. Med. Jutta Parchmann",
    "wof:placetype":"venue"
},
  "geometry": {"coordinates":[13.590994,52.426804],"type":"Point"}
}