{
  "type": "Feature",
  "properties": {
    "iso:country":"DE",
    "sg:address":"Richard-Wagner-Platz 2",
    "sg:city":"N\u00fcrnberg",
    "sg:phone":"+49 911/222232",
    "sg:postcode":"90443",
    "sg:province":"Bayern",
    "wof:name":"Rudolf Hirschmann",
    "wof:placetype":"venue"
},
  "geometry": {"coordinates":[11.0760450363,49.4464645386],"type":"Point"}
}