{
  "type": "Feature",
  "properties": {
    "iso:country":"DE",
    "sg:address":"Rog\u00e4tzer Str. 22",
    "sg:city":"Wolmirstedt",
    "sg:postcode":"39326",
    "sg:province":"Sachsen-Anhalt",
    "wof:name":"Hagebaumarkt Lehrmann",
    "wof:placetype":"venue"
},
  "geometry": {"coordinates":[11.6389570236,52.2623748779],"type":"Point"}
}