{
  "type": "Feature",
  "properties": {
    "iso:country":"DE",
    "sg:address":"Max-Weber-Str. 2",
    "sg:city":"Quickborn",
    "sg:phone":"+49 4941/067070",
    "sg:postcode":"25451",
    "sg:province":"Schleswig-Holstein",
    "wof:name":"Loesch Metallgmbh",
    "wof:placetype":"venue"
},
  "geometry": {"coordinates":[9.895195,53.731945],"type":"Point"}
}