{
  "type": "Feature",
  "properties": {
    "iso:country":"DE",
    "sg:address":"Bahnstr. 16",
    "sg:city":"Solingen",
    "sg:phone":"+49 212/77363",
    "sg:postcode":"42697",
    "sg:province":"Nordrhein-Westfalen",
    "wof:name":"Hotel-restaurant Am Bahnhof",
    "wof:placetype":"venue"
},
  "geometry": {"coordinates":[7.0034618378,51.1625747681],"type":"Point"}
}