{
  "type": "Feature",
  "properties": {
    "iso:country":"DE",
    "sg:address":"Gro\u00dfe Bahnhofstra\u00dfe 29",
    "sg:city":"Niedersachswerfen",
    "sg:postcode":"99762",
    "sg:province":"Th\u00fcringen",
    "wof:name":"Selketalbahn",
    "wof:placetype":"venue"
},
  "geometry": {"coordinates":[10.762408,51.547424],"type":"Point"}
}