{
  "type": "Feature",
  "properties": {
    "iso:country":"DE",
    "sg:address":"Welfenallee 8",
    "sg:city":"Berlin",
    "sg:phone":"+49 30/40101260",
    "sg:postcode":"13465",
    "sg:province":"Berlin",
    "wof:name":"Schickramm Hausbau Gmbh",
    "wof:placetype":"venue"
},
  "geometry": {"coordinates":[13.2892284393,52.6314125061],"type":"Point"}
}