{
  "type": "Feature",
  "properties": {
    "iso:country":"DE",
    "sg:address":"Comeniusstr. 2",
    "sg:city":"Magdeburg",
    "sg:phone":"+49 391/44907",
    "sg:postcode":"39122",
    "sg:province":"Sachsen-Anhalt",
    "wof:name":"Dat Pr\u00fcf- Und Sch\u00e4tzungsstelle",
    "wof:placetype":"venue"
},
  "geometry": {"coordinates":[11.653486,52.091961],"type":"Point"}
}