{
  "type": "Feature",
  "properties": {
    "iso:country":"DE",
    "sg:address":"Middeweg 16",
    "sg:postcode":"46240",
    "sg:province":"Nordrhein-Westfalen",
    "wof:name":"The Blendo Page",
    "wof:placetype":"venue"
},
  "geometry": {"coordinates":[-86.125458,39.904629],"type":"Point"}
}