{
  "type": "Feature",
  "properties": {
    "iso:country":"DE",
    "sg:address":"Bahnhofstr. 1",
    "sg:city":"Dorfen",
    "sg:phone":"+49 8081/2198",
    "sg:postcode":"84405",
    "sg:province":"Bayern",
    "wof:name":"Bahnhofsgastst\u00e4tte G. Streibl",
    "wof:placetype":"venue"
},
  "geometry": {"coordinates":[12.1589431763,48.2674980164],"type":"Point"}
}