{
  "type": "Feature",
  "properties": {
    "iso:country":"DE",
    "sg:address":"Mittelkamp 113",
    "sg:city":"Oldenburg",
    "sg:phone":"+49 4944/139040",
    "sg:postcode":"26125",
    "sg:province":"Niedersachsen",
    "wof:name":"Lackfabrik De Wit & Janssen Gmbh & Co Kg",
    "wof:placetype":"venue"
},
  "geometry": {"coordinates":[8.240272,53.16069],"type":"Point"}
}