{
  "type": "Feature",
  "properties": {
    "iso:country":"DE",
    "sg:address":"Anemonenweg 30",
    "sg:city":"K\u00f6ln",
    "sg:phone":"+49 221/687404",
    "sg:postcode":"51069",
    "sg:province":"Nordrhein-Westfalen",
    "wof:name":"Gerhard Franck Steuerberater",
    "wof:placetype":"venue"
},
  "geometry": {"coordinates":[7.067486763,50.9815368652],"type":"Point"}
}