{
  "type": "Feature",
  "properties": {
    "iso:country":"DE",
    "sg:address":"Von-der-Heydt-Str. 28",
    "sg:city":"Herne",
    "sg:phone":"+49 2323/910140",
    "sg:postcode":"44629",
    "sg:province":"Nordrhein-Westfalen",
    "wof:name":"Fbl Fruchtb\u00f6rse Limberg Gmbh",
    "wof:placetype":"venue"
},
  "geometry": {"coordinates":[7.2113399506,51.5532531738],"type":"Point"}
}