{
  "type": "Feature",
  "properties": {
    "iso:country":"DE",
    "sg:address":"Herforder Str. 60",
    "sg:city":"Melle",
    "sg:phone":"+49 5226/2291",
    "sg:postcode":"49328",
    "sg:province":"Niedersachsen",
    "wof:name":"Alfred Pots",
    "wof:placetype":"venue"
},
  "geometry": {"coordinates":[8.448739,52.177925],"type":"Point"}
}