{
  "type": "Feature",
  "properties": {
    "iso:country":"DE",
    "sg:address":"Dorschstr. 62",
    "sg:city":"Bremerhaven",
    "sg:postcode":"27572",
    "sg:province":"Bremen",
    "wof:name":"Frigolanda Logistik Center Gmbh",
    "wof:placetype":"venue"
},
  "geometry": {"coordinates":[8.5855903625,53.5181312561],"type":"Point"}
}