{
  "type": "Feature",
  "properties": {
    "iso:country":"DE",
    "sg:address":"Nerobergstr. 18",
    "sg:city":"Wiesbaden",
    "sg:phone":"+49 611/9102727",
    "sg:postcode":"65193",
    "sg:province":"Hessen",
    "wof:name":"Screen Team Gesellschaft F\u00fcr Neue Medien",
    "wof:placetype":"venue"
},
  "geometry": {"coordinates":[8.2344894409,50.095249176],"type":"Point"}
}