{
  "type": "Feature",
  "properties": {
    "iso:country":"DE",
    "sg:address":"Magdeburger Str. 1",
    "sg:city":"Quedlinburg",
    "sg:phone":"+49 3946/2993",
    "sg:postcode":"06484",
    "sg:province":"Sachsen-Anhalt",
    "wof:name":"Fleischergenossenschaft Quedlinburg E.g. Eg",
    "wof:placetype":"venue"
},
  "geometry": {"coordinates":[11.1613111496,51.7901611328],"type":"Point"}
}