{
  "type": "Feature",
  "properties": {
    "iso:country":"DE",
    "sg:address":"Postfach",
    "sg:city":"Saalburg",
    "sg:postcode":"61273",
    "sg:province":"Hessen",
    "wof:name":"Metall-bau Gmbh",
    "wof:placetype":"venue"
},
  "geometry": {"coordinates":[8.5700750351,50.3030815125],"type":"Point"}
}