{
  "type": "Feature",
  "properties": {
    "iso:country":"DE",
    "sg:address":"Dornwei\u00dfstra\u00dfe 14",
    "sg:city":"Eschweiler",
    "sg:phone":"+49 177 7987316",
    "sg:postcode":"52249",
    "sg:province":"Nordrhein-Westfalen",
    "wof:name":"Scan2cad - Der Raster Zu Vektor Konverter",
    "wof:placetype":"venue"
},
  "geometry": {"coordinates":[6.274601,50.83292],"type":"Point"}
}