{
  "type": "Feature",
  "properties": {
    "iso:country":"DE",
    "sg:address":"Pauluskirchstr. 2",
    "sg:city":"Sankt Augustin",
    "sg:phone":"+49 2241/29932",
    "sg:postcode":"53757",
    "sg:province":"Nordrhein-Westfalen",
    "wof:name":"Richard R\u00f6ttgerding Ingenieur",
    "wof:placetype":"venue"
},
  "geometry": {"coordinates":[7.1864919662,50.7695465088],"type":"Point"}
}