{
  "type": "Feature",
  "properties": {
    "iso:country":"DE",
    "sg:address":"W\u00fcnnenberger Weg 26",
    "sg:city":"Paderborn",
    "sg:phone":"+49 5251/61959",
    "sg:postcode":"33100",
    "sg:province":"Nordrhein-Westfalen",
    "wof:name":"Hubert Kriegesmann Gmbh",
    "wof:placetype":"venue"
},
  "geometry": {"coordinates":[8.7967710495,51.7093048096],"type":"Point"}
}