{
  "type": "Feature",
  "properties": {
    "iso:country":"DE",
    "sg:address":"M\u00fchlbacher Str. 4",
    "sg:city":"Eppingen",
    "sg:phone":"+49 7262/4011",
    "sg:postcode":"75031",
    "sg:province":"Baden-W\u00fcrttemberg",
    "wof:name":"Bernhard Fessner Anlageberater",
    "wof:placetype":"venue"
},
  "geometry": {"coordinates":[8.9054203033,49.1349487305],"type":"Point"}
}