{
  "type": "Feature",
  "properties": {
    "iso:country":"DE",
    "sg:address":"Max-von-M\u00fcller-Str. 46",
    "sg:city":"Rottenburg",
    "sg:phone":"+49 8781/1042",
    "sg:postcode":"84056",
    "sg:province":"Bayern",
    "wof:name":"Bahnhof",
    "wof:placetype":"venue"
},
  "geometry": {"coordinates":[12.0252046585,48.7062492371],"type":"Point"}
}