{
  "type": "Feature",
  "properties": {
    "iso:country":"DE",
    "sg:address":"Bismarckstr. 48",
    "sg:city":"Bad Mergentheim",
    "sg:phone":"+49 7931/52717",
    "sg:postcode":"97980",
    "sg:province":"Baden-W\u00fcrttemberg",
    "wof:name":"Tanzcafe Hexenkreuz",
    "wof:placetype":"venue"
},
  "geometry": {"coordinates":[9.785986,49.498501],"type":"Point"}
}