{
  "type": "Feature",
  "properties": {
    "iso:country":"DE",
    "sg:address":"Paradeplatz 3",
    "sg:city":"Roding",
    "sg:phone":"+49 9461/1066",
    "sg:postcode":"93426",
    "sg:province":"Bayern",
    "wof:name":"Kath. \u00d6ffentliche B\u00fccherei",
    "wof:placetype":"venue"
},
  "geometry": {"coordinates":[12.517644,49.196789],"type":"Point"}
}