{
  "type": "Feature",
  "properties": {
    "iso:country":"DE",
    "sg:address":"Am Amselberge",
    "sg:city":"Magdala",
    "sg:phone":"+49 36454/5390",
    "sg:postcode":"99441",
    "sg:province":"Th\u00fcringen",
    "wof:name":"Proka Gmbh",
    "wof:placetype":"venue"
},
  "geometry": {"coordinates":[11.3903017044,50.9461593628],"type":"Point"}
}