{
  "type": "Feature",
  "properties": {
    "iso:country":"DE",
    "sg:address":"Steinbachtal 64",
    "sg:city":"W\u00fcrzburg",
    "sg:phone":"+49 931/72394",
    "sg:postcode":"97082",
    "sg:province":"Bayern",
    "wof:name":"Steinbachtalb\u00e4ck",
    "wof:placetype":"venue"
},
  "geometry": {"coordinates":[9.9073762894,49.7713775635],"type":"Point"}
}