{
  "type": "Feature",
  "properties": {
    "iso:country":"DE",
    "sg:address":"Prielmayerstr. 3",
    "sg:city":"M\u00fcnchen",
    "sg:phone":"+49 89/55029704",
    "sg:postcode":"80335",
    "sg:province":"Bayern",
    "wof:name":"House Of Sandwich Gmbh & Co.",
    "wof:placetype":"venue"
},
  "geometry": {"coordinates":[11.5622339249,48.1408538818],"type":"Point"}
}