{
  "type": "Feature",
  "properties": {
    "iso:country":"DE",
    "sg:address":"Scharnweberstr. 58",
    "sg:city":"Berlin",
    "sg:phone":"+49 30/4122749",
    "sg:postcode":"13405",
    "sg:province":"Berlin",
    "wof:name":"Michael Hu\u00df-binting Masseur",
    "wof:placetype":"venue"
},
  "geometry": {"coordinates":[13.313538,52.567745],"type":"Point"}
}