{
  "type": "Feature",
  "properties": {
    "iso:country":"DE",
    "sg:address":"Stakendorfer Str. 7",
    "sg:city":"Wolfen-_Thalheim",
    "sg:postcode":"06766",
    "sg:province":"Sachsen-Anhalt",
    "wof:name":"Arplas Gesellschaft F\u00fcr Plasmatechnologie Mbh",
    "wof:placetype":"venue"
},
  "geometry": {"coordinates":[12.24330616,51.6480751038],"type":"Point"}
}