{
  "type": "Feature",
  "properties": {
    "iso:country":"DE",
    "sg:address":"M\u00fchlenbach 4",
    "sg:city":"K\u00f6ln",
    "sg:phone":"+49 221/231357",
    "sg:postcode":"50676",
    "sg:province":"Nordrhein-Westfalen",
    "wof:name":"W. Bergfeld Werkzeuge",
    "wof:placetype":"venue"
},
  "geometry": {"coordinates":[6.956945,50.932858],"type":"Point"}
}