{
  "type": "Feature",
  "properties": {
    "iso:country":"DE",
    "sg:address":"Hedenkampstr. 20",
    "sg:city":"Ganderkesee",
    "sg:phone":"+49 4223/92190",
    "sg:postcode":"27777",
    "sg:province":"Niedersachsen",
    "wof:name":"Landhaus Hasbruch Hotel Und Gastronomie Gmbh",
    "wof:placetype":"venue"
},
  "geometry": {"coordinates":[8.5101690292,53.0855026245],"type":"Point"}
}