{
  "type": "Feature",
  "properties": {
    "iso:country":"DE",
    "sg:address":"J\u00e4gerweg 4",
    "sg:city":"Berlin",
    "sg:phone":"+49 30/4312610",
    "sg:postcode":"13503",
    "sg:province":"Berlin",
    "wof:name":"Elke Haftaoglu",
    "wof:placetype":"venue"
},
  "geometry": {"coordinates":[13.2352523804,52.6123771667],"type":"Point"}
}