{
  "type": "Feature",
  "properties": {
    "iso:country":"DE",
    "sg:address":"Stolzenhagener Chaussee 2",
    "sg:city":"Zehlendorf",
    "sg:postcode":"16515",
    "sg:province":"Brandenburg",
    "wof:name":"E. Mierau",
    "wof:placetype":"venue"
},
  "geometry": {"coordinates":[13.24443,52.756378],"type":"Point"}
}