{
  "type": "Feature",
  "properties": {
    "iso:country":"DE",
    "sg:address":"Am Stadion 202",
    "sg:city":"Bielefeld",
    "sg:phone":"+49 5205/4469",
    "sg:postcode":"33689",
    "sg:province":"Nordrhein-Westfalen",
    "wof:name":"Heinz Milbradt",
    "wof:placetype":"venue"
},
  "geometry": {"coordinates":[8.5987138748,51.9543457031],"type":"Point"}
}