{
  "type": "Feature",
  "properties": {
    "iso:country":"DE",
    "sg:address":"Forststr. 23",
    "sg:city":"Berlin",
    "sg:phone":"+49 30/80905080",
    "sg:postcode":"14163",
    "sg:province":"Berlin",
    "wof:name":"Rebekka Kaufmann",
    "wof:placetype":"venue"
},
  "geometry": {"coordinates":[13.2431774139,52.4375495911],"type":"Point"}
}