{
  "type": "Feature",
  "properties": {
    "iso:country":"DE",
    "sg:address":"Kronau 15",
    "sg:city":"Emmering",
    "sg:phone":"+49 8067/90380",
    "sg:postcode":"83550",
    "sg:province":"Bayern",
    "wof:name":"Kirschbaum Software Gmbh",
    "wof:placetype":"venue"
},
  "geometry": {"coordinates":[12.0487041473,47.9730529785],"type":"Point"}
}