{
  "type": "Feature",
  "properties": {
    "iso:country":"DE",
    "sg:address":"Kirschweg 3",
    "sg:city":"M\u00f6gelin",
    "sg:postcode":"14715",
    "sg:province":"Brandenburg",
    "wof:name":"Angela Pflanz Krankengymnastin",
    "wof:placetype":"venue"
},
  "geometry": {"coordinates":[12.31067,52.519508],"type":"Point"}
}