{
  "type": "Feature",
  "properties": {
    "iso:country":"DE",
    "sg:address":"H\u00fcbnerstr. 23",
    "sg:city":"M\u00fcnchen",
    "sg:postcode":"80637",
    "sg:province":"Bayern",
    "wof:name":"Dr. Rudolf Schmid Tierarzt",
    "wof:placetype":"venue"
},
  "geometry": {"coordinates":[11.5405397415,48.1592292786],"type":"Point"}
}