{
  "type": "Feature",
  "properties": {
    "iso:country":"DE",
    "sg:address":"Am Planetarium",
    "sg:city":"Jena",
    "sg:phone":"+49 3641/22378",
    "sg:postcode":"07743",
    "sg:province":"Th\u00fcringen",
    "wof:name":"H. Beuerlein",
    "wof:placetype":"venue"
},
  "geometry": {"coordinates":[11.5877847672,50.9355697632],"type":"Point"}
}