{
  "type": "Feature",
  "properties": {
    "iso:country":"DE",
    "sg:address":"Koldingstr. 8",
    "sg:city":"Kiel",
    "sg:phone":"+49 431/567361",
    "sg:postcode":"24105",
    "sg:province":"Schleswig-Holstein",
    "wof:name":"Werner Gruhlke Inh. Bernt Gruhlke",
    "wof:placetype":"venue"
},
  "geometry": {"coordinates":[10.136729,54.329376],"type":"Point"}
}