{
  "type": "Feature",
  "properties": {
    "iso:country":"DE",
    "sg:address":"Hirtenstr. 1 b",
    "sg:city":"Waldfischbach-Burgalben",
    "sg:phone":"+49 6333/2010",
    "sg:postcode":"67714",
    "sg:province":"Rheinland-Pfalz",
    "wof:name":"Horst Heiser",
    "wof:placetype":"venue"
},
  "geometry": {"coordinates":[7.6570267677,49.285358429],"type":"Point"}
}