{
  "type": "Feature",
  "properties": {
    "iso:country":"DE",
    "sg:address":"M\u00fcmmelmannsberg 67",
    "sg:city":"Hamburg",
    "sg:phone":"+49 40/7155667",
    "sg:postcode":"22115",
    "sg:province":"Hamburg",
    "wof:name":"Awo Pflegen & Betreuen Sozialstation M\u00fcmmelmannsberg",
    "wof:placetype":"venue"
},
  "geometry": {"coordinates":[10.146609,53.52264],"type":"Point"}
}