{
  "type": "Feature",
  "properties": {
    "iso:country":"DE",
    "sg:address":"Teutonenstr. 2-4",
    "sg:city":"Bocholt",
    "sg:phone":"+49 2871/2870",
    "sg:postcode":"46395",
    "sg:province":"Nordrhein-Westfalen",
    "wof:name":"Euro-mercant Gesellschaft F\u00fcr Intereurop\u00e4ischen",
    "wof:placetype":"venue"
},
  "geometry": {"coordinates":[6.608966,51.831551],"type":"Point"}
}