{
  "type": "Feature",
  "properties": {
    "iso:country":"DE",
    "sg:address":"Saarstr. 4",
    "sg:city":"Saarbr\u00fccken",
    "sg:phone":"+49 681/3908485",
    "sg:postcode":"66111",
    "sg:province":"Saarland",
    "wof:name":"Pizzeria La Galleria",
    "wof:placetype":"venue"
},
  "geometry": {"coordinates":[6.9958500862,49.2322692871],"type":"Point"}
}