{
  "type": "Feature",
  "properties": {
    "iso:country":"DE",
    "sg:address":"Peldenhofweg 1",
    "sg:city":"Xanten",
    "sg:phone":"+49 2801/1533",
    "sg:postcode":"46509",
    "sg:province":"Nordrhein-Westfalen",
    "wof:name":"D. Janssen",
    "wof:placetype":"venue"
},
  "geometry": {"coordinates":[6.4672050476,51.6712417603],"type":"Point"}
}