{
  "type": "Feature",
  "properties": {
    "iso:country":"DE",
    "sg:address":"Alte Holstenstr. 13",
    "sg:city":"Hamburg",
    "sg:postcode":"21031",
    "sg:province":"Hamburg",
    "wof:name":"Budnikowsky Drogeriemarkt",
    "wof:placetype":"venue"
},
  "geometry": {"coordinates":[10.207382,53.493439],"type":"Point"}
}