{
  "type": "Feature",
  "properties": {
    "iso:country":"DE",
    "sg:address":"Hedwigstr. 1",
    "sg:city":"Berlin",
    "sg:phone":"+49 30/9815328",
    "sg:postcode":"13053",
    "sg:province":"Berlin",
    "wof:name":"Gerhard V\u00f6lker Ingenieur",
    "wof:placetype":"venue"
},
  "geometry": {"coordinates":[13.496301651,52.5493240356],"type":"Point"}
}