{
  "type": "Feature",
  "properties": {
    "iso:country":"DE",
    "sg:address":"Tonndorfer Hauptstr. 53",
    "sg:city":"Hamburg",
    "sg:phone":"+49 40/661875",
    "sg:postcode":"22045",
    "sg:province":"Hamburg",
    "wof:name":"Tonndorfer Apotheke",
    "wof:placetype":"venue"
},
  "geometry": {"coordinates":[10.123035,53.585648],"type":"Point"}
}