{
  "type": "Feature",
  "properties": {
    "iso:country":"DE",
    "sg:address":"Lohrer Stra\u00dfe 13",
    "sg:city":"Lohr-Steinbach",
    "sg:phone":"+49 9352",
    "sg:postcode":"97816",
    "sg:province":"Bayern",
    "wof:name":"Planungsb\u00fcro F\u00fcr Bautechnik - Frank Riedmann - Lohr Am Main",
    "wof:placetype":"venue"
},
  "geometry": {"coordinates":[9.6030311584,50.0061302185],"type":"Point"}
}