{
  "type": "Feature",
  "properties": {
    "iso:country":"DE",
    "sg:address":"pyramidenweg 4-6",
    "sg:city":"Ellerbek",
    "sg:postcode":"25474",
    "sg:province":"Schleswig-Holstein",
    "wof:name":"Tiefziehteile",
    "wof:placetype":"venue"
},
  "geometry": {"coordinates":[9.8872852325,53.6447639465],"type":"Point"}
}