{
  "type": "Feature",
  "properties": {
    "iso:country":"DE",
    "sg:address":"Postfach 190 714",
    "sg:city":"M\u00fcnchen",
    "sg:postcode":"80607",
    "sg:province":"Bayern",
    "wof:name":"Der Ergonomie-katalog Im Internet",
    "wof:placetype":"venue"
},
  "geometry": {"coordinates":[11.58027,48.139099],"type":"Point"}
}