{
  "type": "Feature",
  "properties": {
    "iso:country":"DE",
    "sg:address":"Vo\u00dfstr. 22",
    "sg:city":"Hemer",
    "sg:phone":"+49 2372/964610",
    "sg:postcode":"58675",
    "sg:province":"Nordrhein-Westfalen",
    "wof:name":"Hans-dieter Keim",
    "wof:placetype":"venue"
},
  "geometry": {"coordinates":[7.8018741608,51.3780517578],"type":"Point"}
}