{
  "type": "Feature",
  "properties": {
    "iso:country":"DE",
    "sg:address":"Buchheimer Str. 61",
    "sg:city":"K\u00f6ln",
    "sg:phone":"+49 221/618228",
    "sg:postcode":"51063",
    "sg:province":"Nordrhein-Westfalen",
    "wof:name":"Verena B\u00f6ttcher Heilpraktikerin",
    "wof:placetype":"venue"
},
  "geometry": {"coordinates":[7.0041851997,50.9623908997],"type":"Point"}
}