{
  "type": "Feature",
  "properties": {
    "iso:country":"DE",
    "sg:address":"Westend 31 - 39",
    "sg:city":"Bocholt",
    "sg:phone":"+49 2871/46867",
    "sg:postcode":"46399",
    "sg:province":"Nordrhein-Westfalen",
    "wof:name":"Schr\u00f6der",
    "wof:placetype":"venue"
},
  "geometry": {"coordinates":[6.6030988693,51.8390731812],"type":"Point"}
}