{
  "type": "Feature",
  "properties": {
    "iso:country":"DE",
    "sg:address":"Junkersstr. 1",
    "sg:city":"Hannover",
    "sg:phone":"+49 511/9660980",
    "sg:postcode":"30179",
    "sg:province":"Niedersachsen",
    "wof:name":"Eurospar",
    "wof:placetype":"venue"
},
  "geometry": {"coordinates":[9.7398233414,52.4169692993],"type":"Point"}
}