{
  "type": "Feature",
  "properties": {
    "iso:country":"DE",
    "sg:address":"Obere Hauptstr. 14",
    "sg:city":"Bergtheim",
    "sg:phone":"+49 9367/699",
    "sg:postcode":"97241",
    "sg:province":"Bayern",
    "wof:name":"Kreissparkasse W\u00fcrzburg",
    "wof:placetype":"venue"
},
  "geometry": {"coordinates":[10.065512,49.89925],"type":"Point"}
}