{
  "type": "Feature",
  "properties": {
    "iso:country":"DE",
    "sg:address":"Cuno-Hoffmeister-Str. 22",
    "sg:city":"Sonneberg",
    "sg:postcode":"96515",
    "sg:province":"Th\u00fcringen",
    "wof:name":"Ev.-luth. Kirche",
    "wof:placetype":"venue"
},
  "geometry": {"coordinates":[11.174287796,50.3555641174],"type":"Point"}
}