{
  "type": "Feature",
  "properties": {
    "iso:country":"DE",
    "sg:address":"Odenwaldring 24",
    "sg:city":"Eppertshausen",
    "sg:phone":"+49 6071/36727",
    "sg:postcode":"64859",
    "sg:province":"Hessen",
    "wof:name":"Ds-druck",
    "wof:placetype":"venue"
},
  "geometry": {"coordinates":[8.860759,49.949272],"type":"Point"}
}