{
  "type": "Feature",
  "properties": {
    "iso:country":"DE",
    "sg:address":"Moorhauser Brink 6",
    "sg:city":"Lilienthal",
    "sg:phone":"+49 4298/909800",
    "sg:postcode":"28865",
    "sg:province":"Niedersachsen",
    "wof:name":"Recadimo",
    "wof:placetype":"venue"
},
  "geometry": {"coordinates":[8.918571,53.15086],"type":"Point"}
}