{
  "type": "Feature",
  "properties": {
    "iso:country":"DE",
    "sg:address":"Kapellenstr. 24",
    "sg:city":"Aachen",
    "sg:phone":"+49 241/65994",
    "sg:postcode":"52066",
    "sg:province":"Nordrhein-Westfalen",
    "wof:name":"W. Birk",
    "wof:placetype":"venue"
},
  "geometry": {"coordinates":[6.0925831795,50.7611541748],"type":"Point"}
}