{
  "type": "Feature",
  "properties": {
    "iso:country":"DE",
    "sg:address":"Urbanstr. 70A",
    "sg:city":"Berlin",
    "sg:phone":"+49 30/6938645",
    "sg:postcode":"10967",
    "sg:province":"Berlin",
    "wof:name":"Hessmer & Wercker Gmbh",
    "wof:placetype":"venue"
},
  "geometry": {"coordinates":[13.4226646423,52.488571167],"type":"Point"}
}