{
  "type": "Feature",
  "properties": {
    "iso:country":"DE",
    "sg:address":"Am Sportplatz 3",
    "sg:city":"Stade",
    "sg:phone":"+49 4146/293",
    "sg:postcode":"21683",
    "sg:province":"Niedersachsen",
    "wof:name":"Walter Ahrens Seeschiffahrt-unternehmen",
    "wof:placetype":"venue"
},
  "geometry": {"coordinates":[9.477516,53.652615],"type":"Point"}
}