{
  "type": "Feature",
  "properties": {
    "iso:country":"DE",
    "sg:address":"Hauptstr. 62",
    "sg:city":"Gladenbach",
    "sg:phone":"+49 6462/6229",
    "sg:postcode":"35075",
    "sg:province":"Hessen",
    "wof:name":"Heinz Hof",
    "wof:placetype":"venue"
},
  "geometry": {"coordinates":[8.597165,50.752823],"type":"Point"}
}