{
  "type": "Feature",
  "properties": {
    "iso:country":"DE",
    "sg:address":"St\u00f6lzinger Str. 2",
    "sg:city":"Rotenburg",
    "sg:phone":"+49 6623/919993",
    "sg:postcode":"36199",
    "sg:province":"Hessen",
    "wof:name":"Ernst Parduhn",
    "wof:placetype":"venue"
},
  "geometry": {"coordinates":[9.776878,51.066853],"type":"Point"}
}