{
  "type": "Feature",
  "properties": {
    "iso:country":"DE",
    "sg:address":"Akazienweg 7",
    "sg:city":"Wesseling",
    "sg:phone":"+49 2232/943934",
    "sg:postcode":"50389",
    "sg:province":"Nordrhein-Westfalen",
    "wof:name":"Willemsen Rechtsanwalt",
    "wof:placetype":"venue"
},
  "geometry": {"coordinates":[6.943710804,50.8349227905],"type":"Point"}
}