{
  "type": "Feature",
  "properties": {
    "iso:country":"DE",
    "sg:address":"Steilshooper Str. 235",
    "sg:city":"Hamburg",
    "sg:phone":"+49 40/6300131",
    "sg:postcode":"22307",
    "sg:province":"Hamburg",
    "wof:name":"Eiskafe Jasmin",
    "wof:placetype":"venue"
},
  "geometry": {"coordinates":[10.051044,53.600056],"type":"Point"}
}