{
  "type": "Feature",
  "properties": {
    "iso:country":"DE",
    "sg:address":"Theodor-Storm-Str. 7",
    "sg:city":"Quickborn",
    "sg:phone":"+49 4106/75811",
    "sg:postcode":"25451",
    "sg:province":"Schleswig-Holstein",
    "wof:name":"Bruno Breyer Baugesch\u00e4ft Gmbh",
    "wof:placetype":"venue"
},
  "geometry": {"coordinates":[9.9598531723,53.7463874817],"type":"Point"}
}