{
  "type": "Feature",
  "properties": {
    "iso:country":"DE",
    "sg:address":"Esplanade 6",
    "sg:city":"Hamburg",
    "sg:phone":"+49 40/3576240",
    "sg:postcode":"20354",
    "sg:province":"Hamburg",
    "wof:name":"C. O.-shipping Gmbh",
    "wof:placetype":"venue"
},
  "geometry": {"coordinates":[9.992152,53.557487],"type":"Point"}
}