{
  "type": "Feature",
  "properties": {
    "iso:country":"DE",
    "sg:address":"Ludwig-Thoma-Str. 32",
    "sg:city":"Rottach-Egern",
    "sg:phone":"+49 8022/5741",
    "sg:postcode":"83700",
    "sg:province":"Bayern",
    "wof:name":"Bernd Steinel Malereibetrieb",
    "wof:placetype":"venue"
},
  "geometry": {"coordinates":[11.778271,47.688271],"type":"Point"}
}