{
  "type": "Feature",
  "properties": {
    "iso:country":"DE",
    "sg:address":"Franz-Brombach-Str. 5",
    "sg:city":"Erding",
    "sg:phone":"+49 8122/98360",
    "sg:postcode":"85435",
    "sg:province":"Bayern",
    "wof:name":"Johann Egger",
    "wof:placetype":"venue"
},
  "geometry": {"coordinates":[11.890058,48.313705],"type":"Point"}
}