{
  "type": "Feature",
  "properties": {
    "iso:country":"DE",
    "sg:address":"Achalmstr. 8",
    "sg:city":"Bodelshausen",
    "sg:phone":"+49 7471/71726",
    "sg:postcode":"72411",
    "sg:province":"Baden-W\u00fcrttemberg",
    "wof:name":"Karina Beiter",
    "wof:placetype":"venue"
},
  "geometry": {"coordinates":[8.9791,48.393028],"type":"Point"}
}