{
  "type": "Feature",
  "properties": {
    "iso:country":"DE",
    "sg:address":"Kippenheimer Str 6",
    "sg:city":"Kippenheim",
    "sg:phone":"+49 7825/9010",
    "sg:postcode":"77971",
    "sg:province":"Baden-W\u00fcrttemberg",
    "wof:name":"Hiller Objektm\u00f6bel Gmbh & Co Kg",
    "wof:placetype":"venue"
},
  "geometry": {"coordinates":[7.852271,48.281139],"type":"Point"}
}