{
  "type": "Feature",
  "properties": {
    "iso:country":"DE",
    "sg:address":"Ellmendinger Str. 8",
    "sg:city":"Karlsruhe",
    "sg:phone":"+49 721/42746",
    "sg:postcode":"76227",
    "sg:province":"Baden-W\u00fcrttemberg",
    "wof:name":"Karl D\u00fcrr",
    "wof:placetype":"venue"
},
  "geometry": {"coordinates":[8.4581356049,48.9913978577],"type":"Point"}
}