{
  "type": "Feature",
  "properties": {
    "iso:country":"DE",
    "sg:address":"Emdener Weg 7 b",
    "sg:city":"Magdeburg",
    "sg:phone":"+49 391/7312218",
    "sg:postcode":"39110",
    "sg:province":"Sachsen-Anhalt",
    "wof:name":"Jens Rasel Rechtsanwalt",
    "wof:placetype":"venue"
},
  "geometry": {"coordinates":[11.5737810135,52.1356925964],"type":"Point"}
}