{
  "type": "Feature",
  "properties": {
    "iso:country":"DE",
    "sg:address":"Brahmsstr 1",
    "sg:city":"Ha\u00dfloch",
    "sg:phone":"+49 6324/92090",
    "sg:postcode":"67454",
    "sg:province":"Rheinland-Pfalz",
    "wof:name":"Werner & Schaaf Gbr",
    "wof:placetype":"venue"
},
  "geometry": {"coordinates":[8.247224,49.361526],"type":"Point"}
}