{
  "type": "Feature",
  "properties": {
    "iso:country":"DE",
    "sg:address":"Winternam 443",
    "sg:city":"Kerken",
    "sg:phone":"+49 2831/2173",
    "sg:postcode":"47647",
    "sg:province":"Nordrhein-Westfalen",
    "wof:name":"Hammans Kg",
    "wof:placetype":"venue"
},
  "geometry": {"coordinates":[6.339377,51.471684],"type":"Point"}
}