{
  "type": "Feature",
  "properties": {
    "iso:country":"DE",
    "sg:address":"Industriestr. 1",
    "sg:city":"Gemmingen",
    "sg:phone":"+49 4972/678060",
    "sg:postcode":"75050",
    "sg:province":"Baden-W\u00fcrttemberg",
    "wof:name":"Metallwarenfabrik Gemmingen Gmbh & Co",
    "wof:placetype":"venue"
},
  "geometry": {"coordinates":[8.98016,49.152473],"type":"Point"}
}