{
  "type": "Feature",
  "properties": {
    "iso:country":"DE",
    "sg:address":"Wilhelmstr. 23",
    "sg:city":"Kiel",
    "sg:phone":"+49 431/735757",
    "sg:postcode":"24143",
    "sg:province":"Schleswig-Holstein",
    "wof:name":"Helmut Stahn & Sohn",
    "wof:placetype":"venue"
},
  "geometry": {"coordinates":[10.1421613693,54.3105125427],"type":"Point"}
}