{
  "type": "Feature",
  "properties": {
    "iso:country":"DE",
    "sg:address":"Untere Haspelstra\u00dfe 22",
    "sg:city":"Waldshut",
    "sg:postcode":"79761",
    "sg:province":"Baden-W\u00fcrttemberg",
    "wof:name":"Evangelisch-freikirchliche Gemeinde, Baptisten",
    "wof:placetype":"venue"
},
  "geometry": {"coordinates":[8.206079,47.624134],"type":"Point"}
}