{
  "type": "Feature",
  "properties": {
    "iso:country":"DE",
    "sg:address":"Wilhelm-Schickard-Str. 3",
    "sg:city":"Pliezhausen",
    "sg:phone":"+49 4971/2797740",
    "sg:postcode":"72124",
    "sg:province":"Baden-W\u00fcrttemberg",
    "wof:name":"Bravour Textil Gebr\u00dcder Ammann Gmbh & Co.",
    "wof:placetype":"venue"
},
  "geometry": {"coordinates":[9.175956,48.578453],"type":"Point"}
}