{
  "type": "Feature",
  "properties": {
    "iso:country":"DE",
    "sg:address":"Lerchenfeldstr. 15",
    "sg:city":"M\u00fcnchen",
    "sg:phone":"+49 89/221668",
    "sg:postcode":"80538",
    "sg:province":"Bayern",
    "wof:name":"Dr. Gundula Anke Tier\u00e4rztin",
    "wof:placetype":"venue"
},
  "geometry": {"coordinates":[11.5934152603,48.1470603943],"type":"Point"}
}