{
  "type": "Feature",
  "properties": {
    "iso:country":"DE",
    "sg:address":"Hindenburgplatz 6",
    "sg:city":"Bitz",
    "sg:phone":"+49 7431/800427",
    "sg:postcode":"72475",
    "sg:province":"Baden-W\u00fcrttemberg",
    "wof:name":"Krause",
    "wof:placetype":"venue"
},
  "geometry": {"coordinates":[9.0918426514,48.2432899475],"type":"Point"}
}