{
  "type": "Feature",
  "properties": {
    "iso:country":"DE",
    "sg:address":"Neue Str. 8",
    "sg:city":"Neuenburg",
    "sg:phone":"+49 7634/2233",
    "sg:postcode":"79395",
    "sg:province":"Baden-W\u00fcrttemberg",
    "wof:name":"Hermann L\u00f6sch",
    "wof:placetype":"venue"
},
  "geometry": {"coordinates":[7.56012,47.813931],"type":"Point"}
}