{
  "type": "Feature",
  "properties": {
    "iso:country":"DE",
    "sg:address":"Voltastr. 32",
    "sg:city":"Mannheim",
    "sg:phone":"+49 621/841050",
    "sg:postcode":"68199",
    "sg:province":"Baden-W\u00fcrttemberg",
    "wof:name":"Wieland Metall- Oberfl\u00e4chentechnik Gmbh",
    "wof:placetype":"venue"
},
  "geometry": {"coordinates":[8.4950561523,49.4628677368],"type":"Point"}
}