{
  "type": "Feature",
  "properties": {
    "iso:country":"DE",
    "sg:address":"Nietzschestr. 23",
    "sg:city":"Leipzig",
    "sg:phone":"+49 341/9119396",
    "sg:postcode":"04157",
    "sg:province":"Sachsen",
    "wof:name":"Dr. Med. Volker Thierbach",
    "wof:placetype":"venue"
},
  "geometry": {"coordinates":[12.37925,51.372635],"type":"Point"}
}