{
  "type": "Feature",
  "properties": {
    "iso:country":"DE",
    "sg:address":"St\u00e4tzlinger Str. 24-26",
    "sg:city":"Augsburg",
    "sg:phone":"+49 821/272345",
    "sg:postcode":"86165",
    "sg:province":"Bayern",
    "wof:name":"Kramer Steinmetzbetrieb Gmbh",
    "wof:placetype":"venue"
},
  "geometry": {"coordinates":[10.9260282516,48.3788452148],"type":"Point"}
}