{
  "type": "Feature",
  "properties": {
    "iso:country":"DE",
    "sg:address":"Aachener Str. 13a",
    "sg:city":"W\u00fcrselen",
    "sg:phone":"+49 2405/21767",
    "sg:postcode":"52146",
    "sg:province":"Nordrhein-Westfalen",
    "wof:name":"H. Und D. Gerkens",
    "wof:placetype":"venue"
},
  "geometry": {"coordinates":[6.127437,50.824066],"type":"Point"}
}