{
  "type": "Feature",
  "properties": {
    "iso:country":"DE",
    "sg:address":"Kirchheimer Str. 29",
    "sg:city":"Wernau",
    "sg:phone":"+49 7153/39689",
    "sg:postcode":"73249",
    "sg:province":"Baden-W\u00fcrttemberg",
    "wof:name":"Bar Valle Dei Templi",
    "wof:placetype":"venue"
},
  "geometry": {"coordinates":[9.415351,48.693115],"type":"Point"}
}