{
  "type": "Feature",
  "properties": {
    "iso:country":"DE",
    "sg:address":"Poststr. 25",
    "sg:city":"Trittau",
    "sg:phone":"+49 4154/3081",
    "sg:postcode":"22946",
    "sg:province":"Schleswig-Holstein",
    "wof:name":"Claus Zingelmann",
    "wof:placetype":"venue"
},
  "geometry": {"coordinates":[10.410892,53.608154],"type":"Point"}
}