{
  "type": "Feature",
  "properties": {
    "iso:country":"DE",
    "sg:address":"K\u00fcllenhahner Str. 161",
    "sg:city":"Wuppertal",
    "sg:phone":"+49 4920/2409390",
    "sg:postcode":"42349",
    "sg:province":"Nordrhein-Westfalen",
    "wof:name":"Peter Hermann Jung Kg",
    "wof:placetype":"venue"
},
  "geometry": {"coordinates":[7.137536,51.228661],"type":"Point"}
}