{
  "type": "Feature",
  "properties": {
    "iso:country":"DE",
    "sg:address":"Adlerflychtstr. 4",
    "sg:city":"Frankfurt",
    "sg:postcode":"60318",
    "sg:province":"Hessen",
    "wof:name":"Aba P As Best As Possible Relationchip",
    "wof:placetype":"venue"
},
  "geometry": {"coordinates":[8.6857433319,50.123878479],"type":"Point"}
}