{
  "type": "Feature",
  "properties": {
    "iso:country":"DE",
    "sg:address":"Bergweg 20",
    "sg:city":"Lenggries",
    "sg:postcode":"83661",
    "sg:province":"Bayern",
    "wof:name":"Wagro Handels Gmbh",
    "wof:placetype":"venue"
},
  "geometry": {"coordinates":[11.5783290863,47.6876449585],"type":"Point"}
}