{
  "type": "Feature",
  "properties": {
    "iso:country":"DE",
    "sg:address":"Stallbaumstr. 14 a",
    "sg:city":"Leipzig",
    "sg:postcode":"04155",
    "sg:province":"Sachsen",
    "wof:name":"99 Pro Media Gmbh",
    "wof:placetype":"venue"
},
  "geometry": {"coordinates":[12.3571491241,51.3601341248],"type":"Point"}
}