{
  "type": "Feature",
  "properties": {
    "iso:country":"DE",
    "sg:address":"Albertstr 9/11",
    "sg:city":"Markneukirchen",
    "sg:phone":"+49 7171/351153",
    "sg:postcode":"08258",
    "sg:province":"Sachsen",
    "wof:name":"Bokesch Systemtechnik",
    "wof:placetype":"venue"
},
  "geometry": {"coordinates":[9.782397,48.796745],"type":"Point"}
}