{
  "type": "Feature",
  "properties": {
    "iso:country":"DE",
    "sg:address":"Am Birkenmoos 14",
    "sg:city":"Wiggensbach",
    "sg:phone":"+49 8370/97363",
    "sg:postcode":"87487",
    "sg:province":"Bayern",
    "wof:name":"Hartmut Bockfeld",
    "wof:placetype":"venue"
},
  "geometry": {"coordinates":[10.2544164658,47.727558136],"type":"Point"}
}