{
  "type": "Feature",
  "properties": {
    "iso:country":"DE",
    "sg:address":"Im Riete 3",
    "sg:city":"Marksuhl",
    "sg:phone":"+49 36925/60514",
    "sg:postcode":"99819",
    "sg:province":"Th\u00fcringen",
    "wof:name":"Wartburgfenster Gmbh",
    "wof:placetype":"venue"
},
  "geometry": {"coordinates":[10.20598,50.910782],"type":"Point"}
}