{
  "type": "Feature",
  "properties": {
    "iso:country":"DE",
    "sg:address":"Wittmannstr. 2",
    "sg:city":"Darmstadt",
    "sg:phone":"+49 6151/661944",
    "sg:postcode":"64285",
    "sg:province":"Hessen",
    "wof:name":"A-team",
    "wof:placetype":"venue"
},
  "geometry": {"coordinates":[8.653576,49.861111],"type":"Point"}
}