{
  "type": "Feature",
  "properties": {
    "iso:country":"DE",
    "sg:address":"Salzwedeler Str. 34h",
    "sg:city":"Kl\u00f6tze",
    "sg:phone":"+49 3909/2632",
    "sg:postcode":"38486",
    "sg:province":"Sachsen-Anhalt",
    "wof:name":"Landtechnik-handels Gmbh Kl\u00f6tze",
    "wof:placetype":"venue"
},
  "geometry": {"coordinates":[11.170964,52.632221],"type":"Point"}
}