{
  "type": "Feature",
  "properties": {
    "iso:country":"DE",
    "sg:address":"Offenser Weg 2",
    "sg:city":"Heeslingen",
    "sg:postcode":"27404",
    "sg:province":"Niedersachsen",
    "wof:name":"Baugesellschaft Zeven Mbh",
    "wof:placetype":"venue"
},
  "geometry": {"coordinates":[9.333248,53.315735],"type":"Point"}
}