{
  "type": "Feature",
  "properties": {
    "iso:country":"DE",
    "sg:address":"Egenolffstr. 38",
    "sg:city":"Frankfurt",
    "sg:phone":"+49 69/94414504",
    "sg:postcode":"60316",
    "sg:province":"Hessen",
    "wof:name":"Good Buy",
    "wof:placetype":"venue"
},
  "geometry": {"coordinates":[8.6928482056,50.1264648438],"type":"Point"}
}