{
  "type": "Feature",
  "properties": {
    "iso:country":"DE",
    "sg:address":"Friedenstr. 25",
    "sg:city":"Bergzow",
    "sg:phone":"+49 39349/50531",
    "sg:postcode":"39307",
    "sg:province":"Sachsen-Anhalt",
    "wof:name":"E. G\u00e4rtner",
    "wof:placetype":"venue"
},
  "geometry": {"coordinates":[12.048964,52.396152],"type":"Point"}
}