{
  "type": "Feature",
  "properties": {
    "iso:country":"DE",
    "sg:address":"N\u00e4gelsbachstr. 25a",
    "sg:city":"Erlangen",
    "sg:phone":"+49 9131/88030",
    "sg:postcode":"91052",
    "sg:province":"Bayern",
    "wof:name":"Rechtsanwaltskanzlei Wolfgang A. Ney",
    "wof:placetype":"venue"
},
  "geometry": {"coordinates":[11.004232,49.591862],"type":"Point"}
}