{
  "type": "Feature",
  "properties": {
    "iso:country":"DE",
    "sg:address":"Br\u00fcckstr. 11",
    "sg:city":"Wickede",
    "sg:phone":"+49 2377/515",
    "sg:postcode":"58739",
    "sg:province":"Nordrhein-Westfalen",
    "wof:name":"Uhrmacher Gmbh",
    "wof:placetype":"venue"
},
  "geometry": {"coordinates":[7.85839,51.48909],"type":"Point"}
}