{
  "type": "Feature",
  "properties": {
    "iso:country":"DE",
    "sg:address":"Alter Heuweg 12",
    "sg:city":"Schwarmstedt",
    "sg:phone":"+49 5071/2158",
    "sg:postcode":"29690",
    "sg:province":"Niedersachsen",
    "wof:name":"Kath. Pfarramt Hl. Geist",
    "wof:placetype":"venue"
},
  "geometry": {"coordinates":[9.6164417267,52.6706733704],"type":"Point"}
}