{
  "type": "Feature",
  "properties": {
    "iso:country":"DE",
    "sg:address":"Alt Metelener Weg 37",
    "sg:city":"Ochtrup",
    "sg:phone":"+49 2553/3120",
    "sg:postcode":"48607",
    "sg:province":"Nordrhein-Westfalen",
    "wof:name":"Kramer Gmbh",
    "wof:placetype":"venue"
},
  "geometry": {"coordinates":[7.199534893,52.1991081238],"type":"Point"}
}