{
  "type": "Feature",
  "properties": {
    "iso:country":"DE",
    "sg:address":"Obere Seefeldstr. 50",
    "sg:city":"We\u00dfling",
    "sg:phone":"+49 8153/3635",
    "sg:postcode":"82234",
    "sg:province":"Bayern",
    "wof:name":"G. Kroker Ingenieur",
    "wof:placetype":"venue"
},
  "geometry": {"coordinates":[11.2559099197,48.0705909729],"type":"Point"}
}