{
  "type": "Feature",
  "properties": {
    "iso:country":"DE",
    "sg:address":"Friedensstra\u00dfe 12-18",
    "sg:city":"M\u00f6nchengladbach",
    "sg:phone":"+49 2166/420196",
    "sg:postcode":"41236",
    "sg:province":"Nordrhein-Westfalen",
    "wof:name":"Roos Dental",
    "wof:placetype":"venue"
},
  "geometry": {"coordinates":[6.45619,51.165901],"type":"Point"}
}