{
  "type": "Feature",
  "properties": {
    "iso:country":"DE",
    "sg:address":"Sandstr. 7",
    "sg:city":"Sulingen",
    "sg:phone":"+49 4271/5299",
    "sg:postcode":"27232",
    "sg:province":"Niedersachsen",
    "wof:name":"Rainer Lanitz",
    "wof:placetype":"venue"
},
  "geometry": {"coordinates":[8.82799,52.685001],"type":"Point"}
}