{
  "type": "Feature",
  "properties": {
    "iso:country":"DE",
    "sg:address":"K\u00f6nigstr. 70",
    "sg:city":"Dietenheim",
    "sg:phone":"+49 7347/7579",
    "sg:postcode":"89165",
    "sg:province":"Baden-W\u00fcrttemberg",
    "wof:name":"Anton Rembold",
    "wof:placetype":"venue"
},
  "geometry": {"coordinates":[10.0699892044,48.2118606567],"type":"Point"}
}