{
  "type": "Feature",
  "properties": {
    "iso:country":"DE",
    "sg:address":"Mannheimer Str. 103",
    "sg:city":"Br\u00fchl",
    "sg:phone":"+49 6202/71869",
    "sg:postcode":"68782",
    "sg:province":"Baden-W\u00fcrttemberg",
    "wof:name":"Esso Deutschland Gmbh",
    "wof:placetype":"venue"
},
  "geometry": {"coordinates":[8.5376081467,49.402431488],"type":"Point"}
}