{
  "type": "Feature",
  "properties": {
    "iso:country":"DE",
    "sg:address":"Goethestr. 41b",
    "sg:city":"Hohen Neuendorf",
    "sg:phone":"+49 3303/403005",
    "sg:postcode":"16540",
    "sg:province":"Brandenburg",
    "wof:name":"Havelbaude Inh. Maria Hofer",
    "wof:placetype":"venue"
},
  "geometry": {"coordinates":[13.2584466934,52.6768264771],"type":"Point"}
}