{
  "type": "Feature",
  "properties": {
    "iso:country":"DE",
    "sg:address":"Erblandstr. 3",
    "sg:city":"Gummersbach",
    "sg:phone":"+49 2262/701867",
    "sg:postcode":"51645",
    "sg:province":"Nordrhein-Westfalen",
    "wof:name":"Klaus Dannenberg Immobilienverwaltung Und",
    "wof:placetype":"venue"
},
  "geometry": {"coordinates":[7.5015540123,50.9918937683],"type":"Point"}
}