{
  "type": "Feature",
  "properties": {
    "iso:country":"DE",
    "sg:address":"Bunsenstr. 4",
    "sg:city":"\u00d6stringen",
    "sg:phone":"+49 7253/21608",
    "sg:postcode":"76684",
    "sg:province":"Baden-W\u00fcrttemberg",
    "wof:name":"Raik Hentz",
    "wof:placetype":"venue"
},
  "geometry": {"coordinates":[8.6970529556,49.2125473022],"type":"Point"}
}