{
  "type": "Feature",
  "properties": {
    "iso:country":"DE",
    "sg:address":"Friesdorfer M\u00fchle",
    "sg:city":"Wollin",
    "sg:phone":"+49 33833/255",
    "sg:postcode":"14778",
    "sg:province":"Brandenburg",
    "wof:name":"H. Lahn",
    "wof:placetype":"venue"
},
  "geometry": {"coordinates":[12.438525,52.258015],"type":"Point"}
}