{
  "type": "Feature",
  "properties": {
    "iso:country":"DE",
    "sg:address":"Sichelnsteiner Weg 17",
    "sg:city":"Kassel",
    "sg:phone":"+49 561/524016",
    "sg:postcode":"34123",
    "sg:province":"Hessen",
    "wof:name":"Karl Mai",
    "wof:placetype":"venue"
},
  "geometry": {"coordinates":[9.558391571,51.3055534363],"type":"Point"}
}