{
  "type": "Feature",
  "properties": {
    "iso:country":"DE",
    "sg:address":"Markt",
    "sg:city":"Geithain",
    "sg:postcode":"04643",
    "sg:province":"Sachsen",
    "wof:name":"Konsum",
    "wof:placetype":"venue"
},
  "geometry": {"coordinates":[12.6940050125,51.0543289185],"type":"Point"}
}