{
  "type": "Feature",
  "properties": {
    "iso:country":"DE",
    "sg:address":"Goschwitzstr. 27",
    "sg:city":"Bautzen",
    "sg:phone":"+49 3591/44375",
    "sg:postcode":"02625",
    "sg:province":"Sachsen",
    "wof:name":"Goethe-apotheke",
    "wof:placetype":"venue"
},
  "geometry": {"coordinates":[14.427547,51.178398],"type":"Point"}
}