{
  "type": "Feature",
  "properties": {
    "iso:country":"DE",
    "sg:address":"Dahlienweg 3",
    "sg:city":"Ravensburg",
    "sg:phone":"+49 751/92862",
    "sg:postcode":"88213",
    "sg:province":"Baden-W\u00fcrttemberg",
    "wof:name":"Hans Schr\u00f6der",
    "wof:placetype":"venue"
},
  "geometry": {"coordinates":[9.5897474289,47.778087616],"type":"Point"}
}