{
  "type": "Feature",
  "properties": {
    "iso:country":"DE",
    "sg:address":"Bundesallee 118",
    "sg:city":"Berlin",
    "sg:phone":"+49 30/8525052",
    "sg:postcode":"12161",
    "sg:province":"Berlin",
    "wof:name":"Ellen-moden Eleonore Ballstaedt",
    "wof:placetype":"venue"
},
  "geometry": {"coordinates":[13.328736,52.468491],"type":"Point"}
}