{
  "type": "Feature",
  "properties": {
    "iso:country":"DE",
    "sg:address":"Vogelsbergstr. 19",
    "sg:city":"Frankfurt",
    "sg:phone":"+49 69/431585",
    "sg:postcode":"60316",
    "sg:province":"Hessen",
    "wof:name":"Kronberger Gmbh",
    "wof:placetype":"venue"
},
  "geometry": {"coordinates":[8.695631,50.124279],"type":"Point"}
}