{
  "type": "Feature",
  "properties": {
    "iso:country":"DE",
    "sg:address":"Hamburger Str. 78",
    "sg:city":"Schwarzenbek",
    "sg:phone":"+49 4151/98328",
    "sg:postcode":"21493",
    "sg:province":"Schleswig-Holstein",
    "wof:name":"W. Klein",
    "wof:placetype":"venue"
},
  "geometry": {"coordinates":[10.4647674561,53.5005607605],"type":"Point"}
}