{
  "type": "Feature",
  "properties": {
    "iso:country":"DE",
    "sg:address":"Stra\u00dfe der Arbeit 1e",
    "sg:city":"Schlieben",
    "sg:phone":"+49 35361/690",
    "sg:postcode":"04936",
    "sg:province":"Brandenburg",
    "wof:name":"Dieter Lehmann",
    "wof:placetype":"venue"
},
  "geometry": {"coordinates":[13.38623,51.73806],"type":"Point"}
}