{
  "type": "Feature",
  "properties": {
    "iso:country":"DE",
    "sg:address":"R\u00fcdesheimer Str. 35",
    "sg:city":"Geisenheim",
    "sg:phone":"+49 6722/71791",
    "sg:postcode":"65366",
    "sg:province":"Hessen",
    "wof:name":"G. Bender Weinanbau",
    "wof:placetype":"venue"
},
  "geometry": {"coordinates":[7.9652709961,49.9826850891],"type":"Point"}
}