{
  "type": "Feature",
  "properties": {
    "iso:country":"DE",
    "sg:address":"Sommerhaldenstr. 5",
    "sg:city":"Betzweiler-W\u00e4lde",
    "sg:phone":"+49 7455/94640",
    "sg:postcode":"72291",
    "wof:name":"Omnibus Walter Gmbh",
    "wof:placetype":"venue"
},
  "geometry": {"coordinates":[8.4787502289,48.3802185059],"type":"Point"}
}