{
  "type": "Feature",
  "properties": {
    "iso:country":"DE",
    "sg:address":"Klagenfurter Ring 21",
    "sg:city":"Wiesbaden",
    "sg:phone":"+49 611/841987",
    "sg:postcode":"65187",
    "sg:province":"Hessen",
    "wof:name":"J\u00fcrgen Doege",
    "wof:placetype":"venue"
},
  "geometry": {"coordinates":[8.2233657837,50.0542030334],"type":"Point"}
}