{
  "type": "Feature",
  "properties": {
    "iso:country":"DE",
    "sg:address":"Postfach 41 06 25",
    "sg:city":"Berlin",
    "sg:phone":"+49 30/86409477",
    "sg:postcode":"12116",
    "sg:province":"Berlin",
    "wof:name":"Peter W. Kr\u00fcger Eb-team / Kameramann",
    "wof:placetype":"venue"
},
  "geometry": {"coordinates":[13.4119,52.523781],"type":"Point"}
}