{
  "type": "Feature",
  "properties": {
    "iso:country":"DE",
    "sg:address":"Poppenb\u00fcttler Hauptstr. 15",
    "sg:city":"Hamburg",
    "sg:phone":"+49 40/7242979",
    "sg:postcode":"22399",
    "sg:province":"Hamburg",
    "wof:name":"Ludwig Miller Inh. Ralf Wegener E. K.",
    "wof:placetype":"venue"
},
  "geometry": {"coordinates":[10.0867128372,53.6620483398],"type":"Point"}
}