{
  "type": "Feature",
  "properties": {
    "iso:country":"DE",
    "sg:address":"Ringstr. 10",
    "sg:city":"Gottenheim",
    "sg:phone":"+49 7665/92770",
    "sg:postcode":"79288",
    "sg:province":"Baden-W\u00fcrttemberg",
    "wof:name":"Zimmermann Bauges. Mbh",
    "wof:placetype":"venue"
},
  "geometry": {"coordinates":[7.7343378067,48.0506401062],"type":"Point"}
}