{
  "type": "Feature",
  "properties": {
    "iso:country":"DE",
    "sg:address":"Heideweg 10",
    "sg:city":"Maxdorf",
    "sg:phone":"+49 6237/7372",
    "sg:postcode":"67133",
    "sg:province":"Rheinland-Pfalz",
    "wof:name":"Hallenbad Maxdorf",
    "wof:placetype":"venue"
},
  "geometry": {"coordinates":[8.28627491,49.4832572937],"type":"Point"}
}