{
  "type": "Feature",
  "properties": {
    "iso:country":"DE",
    "sg:address":"Bachstr. 19",
    "sg:city":"M\u00fcnsing",
    "sg:phone":"+49 8177/8015",
    "sg:postcode":"82541",
    "sg:province":"Bayern",
    "wof:name":"Barbara F. Schmitt",
    "wof:placetype":"venue"
},
  "geometry": {"coordinates":[11.3730516434,47.9035491943],"type":"Point"}
}