{
  "type": "Feature",
  "properties": {
    "iso:country":"DE",
    "sg:address":"Sandstr. 4",
    "sg:city":"Freiburg",
    "sg:phone":"+49 761/554205",
    "sg:postcode":"79104",
    "sg:province":"Baden-W\u00fcrttemberg",
    "wof:name":"U. Hensle Immobilienmakler",
    "wof:placetype":"venue"
},
  "geometry": {"coordinates":[7.8633198738,48.0075683594],"type":"Point"}
}