{
  "type": "Feature",
  "properties": {
    "iso:country":"DE",
    "sg:address":"Lindenweg 30",
    "sg:city":"Scharbow",
    "sg:phone":"+49 3883/510190",
    "sg:postcode":"19230",
    "sg:province":"Mecklenburg-Vorpommern",
    "wof:name":"Lts Gmbh",
    "wof:placetype":"venue"
},
  "geometry": {"coordinates":[11.1904401779,53.4727401733],"type":"Point"}
}