{
  "type": "Feature",
  "properties": {
    "iso:country":"DE",
    "sg:address":"Kampstra\u00dfe 5",
    "sg:city":"Winterberg - Niedersfeld",
    "sg:postcode":"59955",
    "sg:province":"Nordrhein-Westfalen",
    "wof:name":"Voss T.i.s. Training F\u00fcr Moderne Kommunikationstechnologien",
    "wof:placetype":"venue"
},
  "geometry": {"coordinates":[8.5277938843,51.2530822754],"type":"Point"}
}