{
  "type": "Feature",
  "properties": {
    "iso:country":"DE",
    "sg:address":"Gerberstr. 10",
    "sg:city":"Vaihingen",
    "sg:postcode":"71665",
    "sg:province":"Baden-W\u00fcrttemberg",
    "wof:name":"Stg S\u00fcddeutsche Telecom Handels Gmbh",
    "wof:placetype":"venue"
},
  "geometry": {"coordinates":[8.9577865601,48.9298400879],"type":"Point"}
}