{
  "type": "Feature",
  "properties": {
    "iso:country":"DE",
    "sg:address":"Schwedenkamp 1",
    "sg:city":"Rotenburg",
    "sg:phone":"+49 4269/5578",
    "sg:postcode":"27356",
    "sg:province":"Niedersachsen",
    "wof:name":"Elektro Fritz M\u00fcller Gmbh",
    "wof:placetype":"venue"
},
  "geometry": {"coordinates":[9.357144,53.078487],"type":"Point"}
}