{
  "type": "Feature",
  "properties": {
    "iso:country":"DE",
    "sg:address":"Eldagser Dorfstr. 68",
    "sg:city":"Petershagen",
    "sg:phone":"+49 5707/728",
    "sg:postcode":"32469",
    "sg:province":"Nordrhein-Westfalen",
    "wof:name":"Damke",
    "wof:placetype":"venue"
},
  "geometry": {"coordinates":[8.954693,52.384922],"type":"Point"}
}