{
  "type": "Feature",
  "properties": {
    "iso:country":"DE",
    "sg:address":"Herforder Str. 91",
    "sg:city":"Bad Salzuflen",
    "sg:postcode":"32105",
    "sg:province":"Nordrhein-Westfalen",
    "wof:name":"Vogt Gmbh",
    "wof:placetype":"venue"
},
  "geometry": {"coordinates":[8.732217,52.088539],"type":"Point"}
}