{
  "type": "Feature",
  "properties": {
    "iso:country":"DE",
    "sg:address":"Unterrather Str. 101",
    "sg:city":"D\u00fcsseldorf",
    "sg:phone":"+49 211/411206",
    "sg:postcode":"40468",
    "sg:province":"Nordrhein-Westfalen",
    "wof:name":"Im Keller",
    "wof:placetype":"venue"
},
  "geometry": {"coordinates":[6.7815828323,51.273525238],"type":"Point"}
}