{
  "type": "Feature",
  "properties": {
    "iso:country":"DE",
    "sg:address":"Sch\u00f6n",
    "sg:city":"Creglingen",
    "sg:phone":"+49 7933/435",
    "sg:postcode":"97993",
    "sg:province":"Baden-W\u00fcrttemberg",
    "wof:name":"Gastst\u00e4tte Wilhelm Hahn",
    "wof:placetype":"venue"
},
  "geometry": {"coordinates":[10.0835924149,49.4563064575],"type":"Point"}
}