{
  "type": "Feature",
  "properties": {
    "iso:country":"DE",
    "sg:address":"Neustadter Ring 5",
    "sg:city":"Ludwigshafen",
    "sg:phone":"+49 621/512464",
    "sg:postcode":"67067",
    "sg:province":"Rheinland-Pfalz",
    "wof:name":"Siegfried Milewski Rechtsanwalt",
    "wof:placetype":"venue"
},
  "geometry": {"coordinates":[8.3819704056,49.4537506104],"type":"Point"}
}