{
  "type": "Feature",
  "properties": {
    "iso:country":"DE",
    "sg:address":"Oberer Kapellberg 31",
    "sg:city":"Hallstadt",
    "sg:phone":"+49 951/73686",
    "sg:postcode":"96103",
    "sg:province":"Bayern",
    "wof:name":"Reinhold Huber Architekt",
    "wof:placetype":"venue"
},
  "geometry": {"coordinates":[10.859466,49.934212],"type":"Point"}
}