{
  "type": "Feature",
  "properties": {
    "iso:country":"DE",
    "sg:address":"L\u00fcssumer Str. 70",
    "sg:city":"Bremen",
    "sg:phone":"+49 421/606041",
    "sg:postcode":"28779",
    "sg:province":"Bremen",
    "wof:name":"Hinrich Wolters Verwaltungs-gmbh & Co. Kg",
    "wof:placetype":"venue"
},
  "geometry": {"coordinates":[8.5770120621,53.1895103455],"type":"Point"}
}