{
  "type": "Feature",
  "properties": {
    "iso:country":"DE",
    "sg:address":"Parkstr. 11",
    "sg:city":"Esslingen",
    "sg:phone":"+49 711/383544",
    "sg:postcode":"73734",
    "sg:province":"Baden-W\u00fcrttemberg",
    "wof:name":"Walkania",
    "wof:placetype":"venue"
},
  "geometry": {"coordinates":[9.2981567383,48.734161377],"type":"Point"}
}