{
  "type": "Feature",
  "properties": {
    "iso:country":"DE",
    "sg:address":"Bullauer Str. 6",
    "sg:city":"Erbach",
    "sg:phone":"+49 6062/94420",
    "sg:postcode":"64711",
    "sg:province":"Hessen",
    "wof:name":"Werner Mader Gmbh",
    "wof:placetype":"venue"
},
  "geometry": {"coordinates":[9.04215,49.624359],"type":"Point"}
}