{
  "type": "Feature",
  "properties": {
    "iso:country":"DE",
    "sg:address":"Tannenbergsthaler Str. 3",
    "sg:city":"Morgenr\u00f6the-Rautenkranz",
    "sg:phone":"+49 37465/2207",
    "sg:postcode":"08262",
    "sg:province":"Sachsen",
    "wof:name":"Ekkehart Roth",
    "wof:placetype":"venue"
},
  "geometry": {"coordinates":[12.4789476395,50.4517097473],"type":"Point"}
}