{
  "type": "Feature",
  "properties": {
    "iso:country":"DE",
    "sg:address":"K\u00f6nigsberger Str. 46",
    "sg:city":"Weiden",
    "sg:phone":"+49 961/28989",
    "sg:postcode":"92637",
    "sg:province":"Bayern",
    "wof:name":"Otto Filchner",
    "wof:placetype":"venue"
},
  "geometry": {"coordinates":[12.1433010101,49.6760406494],"type":"Point"}
}