{
  "type": "Feature",
  "properties": {
    "iso:country":"DE",
    "sg:address":"Polenztalstr. 74",
    "sg:city":"Neustadt",
    "sg:phone":"+49 3596/602234",
    "sg:postcode":"01844",
    "sg:province":"Sachsen",
    "wof:name":"Zum Erbgericht",
    "wof:placetype":"venue"
},
  "geometry": {"coordinates":[14.1847143173,51.0240974426],"type":"Point"}
}