{
  "type": "Feature",
  "properties": {
    "iso:country":"DE",
    "sg:address":"Wohldweg 59",
    "sg:city":"Henstedt-Ulzburg",
    "sg:phone":"+49 4193/3903",
    "sg:postcode":"24558",
    "sg:province":"Schleswig-Holstein",
    "wof:name":"Walter Bruhn",
    "wof:placetype":"venue"
},
  "geometry": {"coordinates":[10.044433,53.77882],"type":"Point"}
}