{
  "type": "Feature",
  "properties": {
    "iso:country":"DE",
    "sg:address":"Hospitalstr. 3",
    "sg:city":"Rees",
    "sg:phone":"+49 2851/97515",
    "sg:postcode":"46459",
    "sg:province":"Nordrhein-Westfalen",
    "wof:name":"Haus Millingen",
    "wof:placetype":"venue"
},
  "geometry": {"coordinates":[6.395664,51.808083],"type":"Point"}
}