{
  "type": "Feature",
  "properties": {
    "iso:country":"DE",
    "sg:address":"Koloniestrasse 34",
    "sg:city":"Berlin",
    "sg:phone":"+49 30",
    "sg:postcode":"13359",
    "sg:province":"Berlin",
    "wof:name":"Sex Porno Erotik Freechat Video, Tabulose Frauen",
    "wof:placetype":"venue"
},
  "geometry": {"coordinates":[13.379909,52.559788],"type":"Point"}
}