{
  "type": "Feature",
  "properties": {
    "iso:country":"DE",
    "sg:address":"L\u00e4rchenstr. 26",
    "sg:city":"Gundelfingen",
    "sg:phone":"+49 761/581161",
    "sg:postcode":"79194",
    "sg:province":"Baden-W\u00fcrttemberg",
    "wof:name":"Prof. Werner Rynski Rechtsanwalt",
    "wof:placetype":"venue"
},
  "geometry": {"coordinates":[7.867787838,48.0463752747],"type":"Point"}
}