{
  "type": "Feature",
  "properties": {
    "iso:country":"DE",
    "sg:address":"An der Hasenjagd 4",
    "sg:city":"Remscheid",
    "sg:phone":"+49 2191/9600",
    "sg:postcode":"42897",
    "sg:province":"Nordrhein-Westfalen",
    "wof:name":"Knebes Wohnungsbau- Und Verwaltungs-gmbh",
    "wof:placetype":"venue"
},
  "geometry": {"coordinates":[7.244428,51.182358],"type":"Point"}
}