{
  "type": "Feature",
  "properties": {
    "iso:country":"DE",
    "sg:address":"88525",
    "sg:city":"D\u00fcrmentingen",
    "sg:phone":"+49 7371/4210",
    "sg:postcode":"88525",
    "sg:province":"Baden-W\u00fcrttemberg",
    "wof:name":"Vereinsgastst\u00e4tte Sportheim Sv",
    "wof:placetype":"venue"
},
  "geometry": {"coordinates":[9.5343837738,48.1129646301],"type":"Point"}
}