{
  "type": "Feature",
  "properties": {
    "iso:country":"DE",
    "sg:address":"S\u00f6lder Str. 109",
    "sg:city":"Dortmund",
    "sg:phone":"+49 231/402448",
    "sg:postcode":"44289",
    "sg:province":"Nordrhein-Westfalen",
    "wof:name":"Helmut Wick",
    "wof:placetype":"venue"
},
  "geometry": {"coordinates":[7.587577,51.496281],"type":"Point"}
}