{
  "type": "Feature",
  "properties": {
    "iso:country":"DE",
    "sg:address":"Gildewart 2",
    "sg:city":"Bersenbr\u00fcck",
    "sg:phone":"+49 5439/2036",
    "sg:postcode":"49593",
    "sg:province":"Niedersachsen",
    "wof:name":"Kolpingfamilie Bersenbr\u00fcck Bernd Mecklenfeld",
    "wof:placetype":"venue"
},
  "geometry": {"coordinates":[7.9523820877,52.5514450073],"type":"Point"}
}