{
  "type": "Feature",
  "properties": {
    "iso:country":"DE",
    "sg:address":"Rosa-Luxemburg-Str. 13",
    "sg:city":"Hohen Neuendorf",
    "sg:phone":"+49 3303/500379",
    "sg:postcode":"16540",
    "sg:province":"Brandenburg",
    "wof:name":"Helmut Gericke",
    "wof:placetype":"venue"
},
  "geometry": {"coordinates":[13.277064,52.667065],"type":"Point"}
}