{
  "type": "Feature",
  "properties": {
    "iso:country":"DE",
    "sg:address":"Friedrich-Ebert-Str. 32-36",
    "sg:city":"Weiden",
    "sg:phone":"+49 961/32526",
    "sg:postcode":"92637",
    "sg:province":"Bayern",
    "wof:name":"Kaspar Heidemarie Kaspar-lohse",
    "wof:placetype":"venue"
},
  "geometry": {"coordinates":[12.1746511459,49.6766891479],"type":"Point"}
}