{
  "type": "Feature",
  "properties": {
    "iso:country":"DE",
    "sg:address":"Breiteichstr. 63",
    "sg:city":"Schw\u00e4bisch Hall",
    "sg:phone":"+49 791/8384",
    "sg:postcode":"74523",
    "sg:province":"Baden-W\u00fcrttemberg",
    "wof:name":"Tennisanlage Teurershof Gmbh",
    "wof:placetype":"venue"
},
  "geometry": {"coordinates":[9.7112140656,49.1133613586],"type":"Point"}
}