{
  "type": "Feature",
  "properties": {
    "iso:country":"DE",
    "sg:address":"Wei\u00dfenburgstr. 9",
    "sg:city":"Stuttgart",
    "sg:phone":"+49 711/6498717",
    "sg:postcode":"70180",
    "sg:province":"Baden-W\u00fcrttemberg",
    "wof:name":"L. Ehleben",
    "wof:placetype":"venue"
},
  "geometry": {"coordinates":[9.175953,48.768967],"type":"Point"}
}