{
  "type": "Feature",
  "properties": {
    "iso:country":"DE",
    "sg:address":"Am Freistein 132",
    "sg:city":"Mettmann",
    "sg:phone":"+49 2104/97940",
    "sg:postcode":"40822",
    "sg:province":"Nordrhein-Westfalen",
    "wof:name":"Bahlmann Und Partner Ingenieur Gmbh",
    "wof:placetype":"venue"
},
  "geometry": {"coordinates":[6.9708299637,51.2450027466],"type":"Point"}
}