{
  "type": "Feature",
  "properties": {
    "iso:country":"DE",
    "sg:address":"Hartingerstr. 13",
    "sg:city":"Wolfersdorf",
    "sg:phone":"+49 8168/96215",
    "sg:postcode":"85395",
    "sg:province":"Bayern",
    "wof:name":"Hlup Gmbh",
    "wof:placetype":"venue"
},
  "geometry": {"coordinates":[11.7106237411,48.4769744873],"type":"Point"}
}