{
  "type": "Feature",
  "properties": {
    "iso:country":"DE",
    "sg:address":"Brahmsweg 21",
    "sg:city":"Norderstedt",
    "sg:phone":"+49 40/5235009",
    "sg:postcode":"22848",
    "sg:province":"Schleswig-Holstein",
    "wof:name":"Erich Struecker",
    "wof:placetype":"venue"
},
  "geometry": {"coordinates":[9.98455,53.668777],"type":"Point"}
}