{
  "type": "Feature",
  "properties": {
    "iso:country":"DE",
    "sg:address":"Schelztorstr. 44",
    "sg:city":"Esslingen",
    "sg:phone":"+49 711/352151",
    "sg:postcode":"73728",
    "sg:province":"Baden-W\u00fcrttemberg",
    "wof:name":"China-restaurant Pagoda",
    "wof:placetype":"venue"
},
  "geometry": {"coordinates":[9.2981834412,48.7424125671],"type":"Point"}
}