{
  "type": "Feature",
  "properties": {
    "iso:country":"DE",
    "sg:address":"Rosental 10",
    "sg:city":"M\u00fcnchen",
    "sg:postcode":"80331",
    "sg:province":"Bayern",
    "wof:name":"Sb Leasing Gmbh",
    "wof:placetype":"venue"
},
  "geometry": {"coordinates":[11.574275,48.13525],"type":"Point"}
}