{
  "type": "Feature",
  "properties": {
    "iso:country":"DE",
    "sg:address":"Postfach 60",
    "sg:city":"Seelbach",
    "sg:phone":"+49 7823/2021",
    "sg:postcode":"77956",
    "sg:province":"Baden-W\u00fcrttemberg",
    "wof:name":"B\u00fccherei Am Rathaus",
    "wof:placetype":"venue"
},
  "geometry": {"coordinates":[7.94017,48.311562],"type":"Point"}
}