{
  "type": "Feature",
  "properties": {
    "iso:country":"DE",
    "sg:address":"Meer\u00e4ckerplatz 2-4",
    "sg:city":"Mannheim",
    "sg:phone":"+49 621/812067",
    "sg:postcode":"68163",
    "sg:province":"Baden-W\u00fcrttemberg",
    "wof:name":"Richard-b\u00f6ttger-heim",
    "wof:placetype":"venue"
},
  "geometry": {"coordinates":[8.470998,49.469227],"type":"Point"}
}