{
  "type": "Feature",
  "properties": {
    "iso:country":"DE",
    "sg:address":"Max-Humpl-Str. 7",
    "sg:city":"Kienberg",
    "sg:phone":"+49 8628/98890",
    "sg:postcode":"83361",
    "sg:province":"Bayern",
    "wof:name":"Manfred Schmidhuber Ingenieur",
    "wof:placetype":"venue"
},
  "geometry": {"coordinates":[12.462531,48.037258],"type":"Point"}
}