{
  "type": "Feature",
  "properties": {
    "iso:country":"DE",
    "sg:address":"Vorwerkstr. 8",
    "sg:city":"Barleben",
    "sg:phone":"+49 39203/60406",
    "sg:postcode":"39179",
    "sg:province":"Sachsen-Anhalt",
    "wof:name":"Seesemann Bautenschutz",
    "wof:placetype":"venue"
},
  "geometry": {"coordinates":[11.6234359741,52.2033119202],"type":"Point"}
}