{
  "type": "Feature",
  "properties": {
    "iso:country":"DE",
    "sg:address":"Lengenfelder Str. 4a",
    "sg:city":"Rodewisch",
    "sg:phone":"+49 3744/32200",
    "sg:postcode":"08228",
    "sg:province":"Sachsen",
    "wof:name":"Werner K\u00f6ckeritz",
    "wof:placetype":"venue"
},
  "geometry": {"coordinates":[12.4035167694,50.5330924988],"type":"Point"}
}