{
  "type": "Feature",
  "properties": {
    "iso:country":"DE",
    "sg:address":"Dismas-Reheis-Str. 4",
    "sg:city":"Kolbermoor",
    "sg:phone":"+49 8031/91566",
    "sg:postcode":"83059",
    "sg:province":"Bayern",
    "wof:name":"Kainz Werbe Gmbh",
    "wof:placetype":"venue"
},
  "geometry": {"coordinates":[12.054977417,47.8545570374],"type":"Point"}
}