{
  "type": "Feature",
  "properties": {
    "iso:country":"DE",
    "sg:address":"In \u00c4gypten 40",
    "sg:city":"Wiltingen",
    "sg:phone":"+49 6501/16668",
    "sg:postcode":"54459",
    "sg:province":"Rheinland-Pfalz",
    "wof:name":"Alfons Pelz",
    "wof:placetype":"venue"
},
  "geometry": {"coordinates":[6.5875148773,49.6594276428],"type":"Point"}
}