{
  "type": "Feature",
  "properties": {
    "iso:country":"DE",
    "sg:address":"Recklinghauser Str. 311",
    "sg:city":"Castrop-Rauxel",
    "sg:phone":"+49 2305/73992",
    "sg:postcode":"44579",
    "sg:province":"Nordrhein-Westfalen",
    "wof:name":"Nord-apotheke",
    "wof:placetype":"venue"
},
  "geometry": {"coordinates":[7.317247,51.592937],"type":"Point"}
}