{
  "type": "Feature",
  "properties": {
    "iso:country":"DE",
    "sg:address":"Hirtenende 3",
    "sg:city":"Biesenbrow",
    "sg:postcode":"16278",
    "sg:province":"Brandenburg",
    "wof:name":"Wi-de-ra Gmbh",
    "wof:placetype":"venue"
},
  "geometry": {"coordinates":[14.015809,53.119038],"type":"Point"}
}