{
  "type": "Feature",
  "properties": {
    "iso:country":"DE",
    "sg:address":"Eisenbahnstr. 9",
    "sg:city":"Halle",
    "sg:postcode":"06132",
    "sg:province":"Sachsen-Anhalt",
    "wof:name":"K\u00f6rner & Krippendorf Vertriebsgesellschaft Mbh",
    "wof:placetype":"venue"
},
  "geometry": {"coordinates":[11.9887676239,51.4361915588],"type":"Point"}
}