{
  "type": "Feature",
  "properties": {
    "iso:country":"DE",
    "sg:address":"Im Rustengut 65",
    "sg:city":"Bad D\u00fcrkheim",
    "sg:phone":"+49 6322/982852",
    "sg:postcode":"67098",
    "sg:province":"Rheinland-Pfalz",
    "wof:name":"Dieter Fruth",
    "wof:placetype":"venue"
},
  "geometry": {"coordinates":[8.182839,49.462887],"type":"Point"}
}