{
  "type": "Feature",
  "properties": {
    "iso:country":"DE",
    "sg:address":"Birgen 5 a",
    "sg:city":"Schwalmtal",
    "sg:phone":"+49 2163/45236",
    "sg:postcode":"41366",
    "sg:province":"Nordrhein-Westfalen",
    "wof:name":"J. K\u00fcppers",
    "wof:placetype":"venue"
},
  "geometry": {"coordinates":[6.289248,51.22501],"type":"Point"}
}