{
  "type": "Feature",
  "properties": {
    "iso:country":"DE",
    "sg:address":"Helgol\u00e4nder Str. 7",
    "sg:city":"Cuxhaven",
    "sg:phone":"+49 4721/24018",
    "sg:postcode":"27472",
    "sg:province":"Niedersachsen",
    "wof:name":"Walter Gl\u00fcsing",
    "wof:placetype":"venue"
},
  "geometry": {"coordinates":[8.709604,53.868889],"type":"Point"}
}