{
  "type": "Feature",
  "properties": {
    "iso:country":"DE",
    "sg:address":"Hanauer Landstr. 507",
    "sg:city":"Frankfurt",
    "sg:phone":"+49 69/417501",
    "sg:postcode":"60386",
    "sg:province":"Hessen",
    "wof:name":"H. Zimmerer",
    "wof:placetype":"venue"
},
  "geometry": {"coordinates":[8.758928299,50.1296577454],"type":"Point"}
}