{
  "type": "Feature",
  "properties": {
    "iso:country":"DE",
    "sg:address":"Esperantostr. 14",
    "sg:city":"D\u00fcsseldorf",
    "sg:phone":"+49 211/428808",
    "sg:postcode":"40468",
    "sg:province":"Nordrhein-Westfalen",
    "wof:name":"Klaus Warmbold",
    "wof:placetype":"venue"
},
  "geometry": {"coordinates":[6.7809419632,51.2566642761],"type":"Point"}
}