{
  "type": "Feature",
  "properties": {
    "iso:country":"DE",
    "sg:address":"Johannes-Acker-Str. 3-5",
    "sg:city":"Marburg",
    "sg:phone":"+49 6420/82340",
    "sg:postcode":"35041",
    "sg:province":"Hessen",
    "wof:name":"Karl Schultze Ingenieur",
    "wof:placetype":"venue"
},
  "geometry": {"coordinates":[8.6895246506,50.8080673218],"type":"Point"}
}