{
  "type": "Feature",
  "properties": {
    "iso:country":"DE",
    "sg:address":"An der Rauns 5",
    "sg:city":"Leutkirch",
    "sg:postcode":"88299",
    "sg:province":"Baden-W\u00fcrttemberg",
    "wof:name":"Gebr. Mayer Gmbh",
    "wof:placetype":"venue"
},
  "geometry": {"coordinates":[10.007319,47.827896],"type":"Point"}
}