{
  "type": "Feature",
  "properties": {
    "iso:country":"DE",
    "sg:address":"Stadionstr 16",
    "sg:city":"Rastatt",
    "sg:phone":"+49 7524/8561",
    "sg:postcode":"76437",
    "sg:province":"Baden-W\u00fcrttemberg",
    "wof:name":"Willi L\u00e4mmle Gmbh",
    "wof:placetype":"venue"
},
  "geometry": {"coordinates":[9.7469005585,47.9151191711],"type":"Point"}
}