{
  "type": "Feature",
  "properties": {
    "iso:country":"DE",
    "sg:address":"B\u00fcrgermeister-Smidt-Str. 92",
    "sg:city":"Bremerhaven",
    "sg:phone":"+49 471/417493",
    "sg:postcode":"27568",
    "sg:province":"Bremen",
    "wof:name":"Eiscafe Durigon",
    "wof:placetype":"venue"
},
  "geometry": {"coordinates":[8.577236,53.545223],"type":"Point"}
}