{
  "type": "Feature",
  "properties": {
    "iso:country":"DE",
    "sg:address":"Am Alten Friedhof 7 a",
    "sg:city":"Kaiserslautern",
    "sg:phone":"+49 631/42188",
    "sg:postcode":"67655",
    "sg:province":"Rheinland-Pfalz",
    "wof:name":"Gesellschaft Fr\u00f6hlich Pfalz E. V.",
    "wof:placetype":"venue"
},
  "geometry": {"coordinates":[7.7866969109,49.4458084106],"type":"Point"}
}