{
  "type": "Feature",
  "properties": {
    "iso:country":"DE",
    "sg:address":"Preu\u00dfenstr. 41",
    "sg:city":"M\u00fcnchen",
    "sg:phone":"+49 89/354021",
    "sg:postcode":"80809",
    "sg:province":"Bayern",
    "wof:name":"Wacker-werke Gmbh & Co. Kg",
    "wof:placetype":"venue"
},
  "geometry": {"coordinates":[11.5571775436,48.1854057312],"type":"Point"}
}