{
  "type": "Feature",
  "properties": {
    "iso:country":"DE",
    "sg:address":"Am Alten Hammer 14",
    "sg:city":"Kirchhundem",
    "sg:phone":"+49 2723/2121",
    "sg:postcode":"57399",
    "sg:province":"Nordrhein-Westfalen",
    "wof:name":"Friedel Plauschinat",
    "wof:placetype":"venue"
},
  "geometry": {"coordinates":[8.079727,51.08857],"type":"Point"}
}