{
  "type": "Feature",
  "properties": {
    "iso:country":"DE",
    "sg:address":"Alter Banter Weg 80",
    "sg:city":"Wilhelmshaven",
    "sg:phone":"+49 4421/202789",
    "sg:postcode":"26389",
    "sg:province":"Niedersachsen",
    "wof:name":"Wichmann",
    "wof:placetype":"venue"
},
  "geometry": {"coordinates":[8.08838,53.51651],"type":"Point"}
}