{
  "type": "Feature",
  "properties": {
    "iso:country":"DE",
    "sg:address":"Inrather Str. 305",
    "sg:city":"Krefeld",
    "sg:phone":"+49 2151/754313",
    "sg:postcode":"47803",
    "sg:province":"Nordrhein-Westfalen",
    "wof:name":"Dieter Huppers",
    "wof:placetype":"venue"
},
  "geometry": {"coordinates":[6.54554,51.34795],"type":"Point"}
}