{
  "type": "Feature",
  "properties": {
    "iso:country":"DE",
    "sg:address":"Am Markt 37",
    "sg:city":"Weismain",
    "sg:phone":"+49 9575/244",
    "sg:postcode":"96260",
    "sg:province":"Bayern",
    "wof:name":"T. Und Herold Trautner",
    "wof:placetype":"venue"
},
  "geometry": {"coordinates":[11.23884,50.084],"type":"Point"}
}