{
  "type": "Feature",
  "properties": {
    "iso:country":"DE",
    "sg:address":"Wiesengarten 7",
    "sg:city":"Kulmbach",
    "sg:phone":"+49 9221/65891",
    "sg:postcode":"95326",
    "sg:province":"Bayern",
    "wof:name":"Josef Albrecht Gardinenweberei",
    "wof:placetype":"venue"
},
  "geometry": {"coordinates":[11.4578037262,50.0958442688],"type":"Point"}
}