{
  "type": "Feature",
  "properties": {
    "iso:country":"DE",
    "sg:address":"Laasener Str. 6",
    "sg:city":"Gera",
    "sg:phone":"+49 365/2900843",
    "sg:postcode":"07545",
    "sg:province":"Th\u00fcringen",
    "wof:name":"Armin Allg\u00e4uer Rechtsanwalt",
    "wof:placetype":"venue"
},
  "geometry": {"coordinates":[12.0861244202,50.8798904419],"type":"Point"}
}