{
  "type": "Feature",
  "properties": {
    "iso:country":"DE",
    "sg:address":"T\u00f6lzerstr. 57",
    "sg:city":"Taufkirchen",
    "sg:phone":"+49 89/6516228",
    "sg:postcode":"82024",
    "sg:province":"Bayern",
    "wof:name":"Alluvial Leichtspiegel",
    "wof:placetype":"venue"
},
  "geometry": {"coordinates":[11.6167888641,48.0387992859],"type":"Point"}
}