{
  "type": "Feature",
  "properties": {
    "iso:country":"DE",
    "sg:address":"St.-Georg-Str. 9",
    "sg:city":"Werl",
    "sg:phone":"+49 2922/2414",
    "sg:postcode":"59457",
    "sg:province":"Nordrhein-Westfalen",
    "wof:name":"Franz Korte",
    "wof:placetype":"venue"
},
  "geometry": {"coordinates":[7.9078698158,51.5474014282],"type":"Point"}
}