{
  "type": "Feature",
  "properties": {
    "iso:country":"DE",
    "sg:address":"Burger Stra\u00dfe 42",
    "sg:city":"Wilster",
    "sg:phone":"+49 4823/92900",
    "sg:postcode":"25554",
    "sg:province":"Schleswig-Holstein",
    "wof:name":"Bernd St\u00f6lting \u00b7 Kampfsport Equipment",
    "wof:placetype":"venue"
},
  "geometry": {"coordinates":[9.375989,53.923546],"type":"Point"}
}