{
  "type": "Feature",
  "properties": {
    "iso:country":"DE",
    "sg:address":"Zum Wasserstein 11",
    "sg:city":"Queidersbach",
    "sg:postcode":"66851",
    "sg:province":"Rheinland-Pfalz",
    "wof:name":"Kibg K\u00fcnstliche Intelligenz Beteiligungen Gmbh",
    "wof:placetype":"venue"
},
  "geometry": {"coordinates":[7.638952,49.372749],"type":"Point"}
}