{
  "type": "Feature",
  "properties": {
    "iso:country":"DE",
    "sg:address":"Fraunhoferstr. 9",
    "sg:city":"M\u00fcnchen",
    "sg:phone":"+49 89",
    "sg:postcode":"80469",
    "sg:province":"Bayern",
    "wof:name":"Fraunhofer Theater Und Wirtshaus",
    "wof:placetype":"venue"
},
  "geometry": {"coordinates":[11.572546,48.130791],"type":"Point"}
}