{
  "type": "Feature",
  "properties": {
    "iso:country":"DE",
    "sg:address":"Altforweiler Str. 19",
    "sg:city":"\u00dcberherrn",
    "sg:phone":"+49 6837/74254",
    "sg:postcode":"66802",
    "sg:province":"Saarland",
    "wof:name":"Jutta Und Christian Robert",
    "wof:placetype":"venue"
},
  "geometry": {"coordinates":[6.703402,49.290028],"type":"Point"}
}