{
  "type": "Feature",
  "properties": {
    "iso:country":"DE",
    "sg:address":"Windstr 4",
    "sg:city":"Steinfurt",
    "sg:phone":"+49 2551/5172",
    "sg:postcode":"48565",
    "sg:province":"Nordrhein-Westfalen",
    "wof:name":"Wilhelm Walterscheid",
    "wof:placetype":"venue"
},
  "geometry": {"coordinates":[7.3325228691,52.1521377563],"type":"Point"}
}