{
  "type": "Feature",
  "properties": {
    "iso:country":"DE",
    "sg:address":"Hans-B\u00f6ckler-Str. 25",
    "sg:city":"M\u00fcnchen",
    "sg:phone":"+49 89/1503235",
    "sg:postcode":"80995",
    "sg:province":"Bayern",
    "wof:name":"Friedel M\u00fcndel Kunstmaler",
    "wof:placetype":"venue"
},
  "geometry": {"coordinates":[11.536325,48.200996],"type":"Point"}
}