{
  "type": "Feature",
  "properties": {
    "iso:country":"DE",
    "sg:address":"Rudolf-Diesel-Str. 3",
    "sg:city":"Wittenburg",
    "sg:phone":"+49 38852/9075",
    "sg:postcode":"19243",
    "sg:province":"Mecklenburg-Vorpommern",
    "wof:name":"Gorapur Gmbh",
    "wof:placetype":"venue"
},
  "geometry": {"coordinates":[11.097881,53.501804],"type":"Point"}
}