{
  "type": "Feature",
  "properties": {
    "iso:country":"DE",
    "sg:address":"Pinnauweg 28",
    "sg:city":"Norderstedt",
    "sg:postcode":"22851",
    "sg:province":"Schleswig-Holstein",
    "wof:name":"Fnv Fitness Network Vertriebs Gmbh",
    "wof:placetype":"venue"
},
  "geometry": {"coordinates":[10.032402,53.688816],"type":"Point"}
}