{
  "type": "Feature",
  "properties": {
    "iso:country":"DE",
    "sg:address":"Von-Mulert-Str. 14",
    "sg:city":"S\u00fcdlohn",
    "sg:phone":"+49 2862/5259",
    "sg:postcode":"46354",
    "sg:province":"Nordrhein-Westfalen",
    "wof:name":"Richard H\u00f6sing",
    "wof:placetype":"venue"
},
  "geometry": {"coordinates":[6.813502,51.930882],"type":"Point"}
}