{
  "type": "Feature",
  "properties": {
    "iso:country":"DE",
    "sg:city":"Buchholz",
    "sg:phone":"+49 4181/290942",
    "sg:postcode":"21244",
    "sg:province":"Niedersachsen",
    "wof:name":"Compoffice",
    "wof:placetype":"venue"
},
  "geometry": {"coordinates":[9.880122,53.328281],"type":"Point"}
}