{
  "type": "Feature",
  "properties": {
    "iso:country":"DE",
    "sg:address":"Markt 12",
    "sg:city":"Aurich",
    "sg:phone":"+49 4941/1710",
    "sg:postcode":"26603",
    "sg:province":"Niedersachsen",
    "wof:name":"Kreissparkasse Aurich",
    "wof:placetype":"venue"
},
  "geometry": {"coordinates":[7.482899,53.469921],"type":"Point"}
}