{
  "type": "Feature",
  "properties": {
    "iso:country":"DE",
    "sg:address":"Leutzestr. 45",
    "sg:city":"Schw\u00e4bisch Gm\u00fcnd",
    "sg:phone":"+49 7171/39084",
    "sg:postcode":"73525",
    "sg:province":"Baden-W\u00fcrttemberg",
    "wof:name":"Max Hammele & S\u00f6hne Gmbh",
    "wof:placetype":"venue"
},
  "geometry": {"coordinates":[9.8084478378,48.8002548218],"type":"Point"}
}