{
  "type": "Feature",
  "properties": {
    "iso:country":"DE",
    "sg:address":"Holl\u00e4nderweg 3",
    "sg:city":"Pfalzgrafenweiler",
    "sg:phone":"+49 7445/81354",
    "sg:postcode":"72285",
    "sg:province":"Baden-W\u00fcrttemberg",
    "wof:name":"Negwer Ledermode Gmbh",
    "wof:placetype":"venue"
},
  "geometry": {"coordinates":[8.490776062,48.5347213745],"type":"Point"}
}