{
  "type": "Feature",
  "properties": {
    "iso:country":"DE",
    "sg:address":"Herrlichkeit 4::",
    "sg:city":"Bremen",
    "sg:phone":"+49 421/5988800",
    "sg:postcode":"28199",
    "sg:province":"Bremen",
    "wof:name":"Gebr\u00dcder Krose",
    "wof:placetype":"venue"
},
  "geometry": {"coordinates":[8.802705,53.073139],"type":"Point"}
}