{
  "type": "Feature",
  "properties": {
    "iso:country":"DE",
    "sg:address":"Forstweg 10",
    "sg:city":"Neustadt",
    "sg:phone":"+49 5032",
    "sg:postcode":"31535",
    "sg:province":"Niedersachsen",
    "wof:name":"Plan Ar Planungsb\u00fcro Architekten",
    "wof:placetype":"venue"
},
  "geometry": {"coordinates":[13.764818,51.067535],"type":"Point"}
}