{
  "type": "Feature",
  "properties": {
    "iso:country":"DE",
    "sg:address":"Sauerfeldstr. 4",
    "sg:city":"Rheinberg",
    "sg:phone":"+49 2843/97370",
    "sg:postcode":"47495",
    "sg:province":"Nordrhein-Westfalen",
    "wof:name":"K-rent Vermietungen Gmbh",
    "wof:placetype":"venue"
},
  "geometry": {"coordinates":[6.6098909378,51.5376815796],"type":"Point"}
}