{
  "type": "Feature",
  "properties": {
    "iso:country":"DE",
    "sg:address":"Am M\u00fchlberg 176",
    "sg:city":"Drosa",
    "sg:phone":"+49 34979/21289",
    "sg:postcode":"06369",
    "sg:province":"Sachsen-Anhalt",
    "wof:name":"K.-d. Hyna",
    "wof:placetype":"venue"
},
  "geometry": {"coordinates":[11.9076538086,51.8141403198],"type":"Point"}
}