{
  "type": "Feature",
  "properties": {
    "iso:country":"DE",
    "sg:address":"Frankfurter Str. 58",
    "sg:city":"Brechen",
    "sg:phone":"+49 6483/7807",
    "sg:postcode":"65611",
    "sg:province":"Hessen",
    "wof:name":"Theo Hasenstab",
    "wof:placetype":"venue"
},
  "geometry": {"coordinates":[8.1944952011,50.3521194458],"type":"Point"}
}