{
  "type": "Feature",
  "properties": {
    "iso:country":"DE",
    "sg:address":"Domstr. 1 a",
    "sg:city":"Erfurt",
    "sg:phone":"+49 361/21430",
    "sg:postcode":"99084",
    "sg:province":"Th\u00fcringen",
    "wof:name":"Ernst & Young Deutsche Allgemeine Treuhand Ag",
    "wof:placetype":"venue"
},
  "geometry": {"coordinates":[11.0244474411,50.9757728577],"type":"Point"}
}