{
  "type": "Feature",
  "properties": {
    "iso:country":"DE",
    "sg:address":"Deichstr. 48-50",
    "sg:city":"Hamburg",
    "sg:postcode":"20459",
    "sg:province":"Hamburg",
    "wof:name":"Buster Systems Handels Gmbh",
    "wof:placetype":"venue"
},
  "geometry": {"coordinates":[9.986587,53.545155],"type":"Point"}
}