{
  "type": "Feature",
  "properties": {
    "iso:country":"DE",
    "sg:address":"Eichwiesen",
    "sg:city":"Melsungen",
    "sg:phone":"+49 5661/4331",
    "sg:postcode":"34212",
    "sg:province":"Hessen",
    "wof:name":"Gastst\u00e4tte Walter Rose",
    "wof:placetype":"venue"
},
  "geometry": {"coordinates":[9.5646190643,51.166595459],"type":"Point"}
}