{
  "type": "Feature",
  "properties": {
    "iso:country":"DE",
    "sg:address":"Flachsland 29/31",
    "sg:city":"Hamburg",
    "sg:postcode":"22083",
    "sg:province":"Hamburg",
    "wof:name":"Einhundertsechsundrei\u00dfigste Verwaltungsges. Flachsland Mbh",
    "wof:placetype":"venue"
},
  "geometry": {"coordinates":[10.0438499451,53.5839576721],"type":"Point"}
}