{
  "type": "Feature",
  "properties": {
    "iso:country":"DE",
    "sg:address":"Clemensstr. 51",
    "sg:city":"Bonn",
    "sg:phone":"+49 228/464867",
    "sg:postcode":"53225",
    "sg:province":"Nordrhein-Westfalen",
    "wof:name":"Siegfried Schulz",
    "wof:placetype":"venue"
},
  "geometry": {"coordinates":[7.122224,50.747784],"type":"Point"}
}