{
  "type": "Feature",
  "properties": {
    "iso:country":"DE",
    "sg:address":"Siegener Str. 10",
    "sg:city":"Hadamar",
    "sg:phone":"+49 6433/3425",
    "sg:postcode":"65589",
    "sg:province":"Hessen",
    "wof:name":"Walter M\u00fcller",
    "wof:placetype":"venue"
},
  "geometry": {"coordinates":[8.0487957001,50.4534263611],"type":"Point"}
}