{
  "type": "Feature",
  "properties": {
    "iso:country":"DE",
    "sg:address":"Max-Roth-Str 3",
    "sg:city":"Gaggenau",
    "sg:phone":"+49 7225/91660",
    "sg:postcode":"76571",
    "sg:province":"Baden-W\u00fcrttemberg",
    "wof:name":"Hurrle Spezial-transporte Gmbh",
    "wof:placetype":"venue"
},
  "geometry": {"coordinates":[8.3408660889,48.7879676819],"type":"Point"}
}