{
  "type": "Feature",
  "properties": {
    "iso:country":"DE",
    "sg:address":"Filderbahnstr. 52",
    "sg:city":"Stuttgart",
    "sg:phone":"+49 711/713526",
    "sg:postcode":"70567",
    "sg:province":"Baden-W\u00fcrttemberg",
    "wof:name":"Foto-edelmann",
    "wof:placetype":"venue"
},
  "geometry": {"coordinates":[9.1466035843,48.7288398743],"type":"Point"}
}