{
  "type": "Feature",
  "properties": {
    "iso:country":"DE",
    "sg:address":"Bertramstr. 7",
    "sg:city":"Lippstadt",
    "sg:phone":"+49 2941/28080",
    "sg:postcode":"59557",
    "sg:province":"Nordrhein-Westfalen",
    "wof:name":"Lippst\u00e4dter Hartschaum- Verarbeitung Gmbh",
    "wof:placetype":"venue"
},
  "geometry": {"coordinates":[8.364102,51.651394],"type":"Point"}
}