{
  "type": "Feature",
  "properties": {
    "iso:country":"DE",
    "sg:address":"Max-Mengeringhausen Str 5",
    "sg:city":"W\u00fcrzburg",
    "sg:phone":"+49 931/6670571",
    "sg:postcode":"97084",
    "sg:province":"Bayern",
    "wof:name":"Mero Gmbh & Co. Kg Ausstellungs-systeme",
    "wof:placetype":"venue"
},
  "geometry": {"coordinates":[9.963908,49.728943],"type":"Point"}
}