{
  "type": "Feature",
  "properties": {
    "iso:country":"DE",
    "sg:address":"Am Silberb\u00fchl 5",
    "sg:city":"Oberstaufen",
    "sg:phone":"+49 8386/93060",
    "sg:postcode":"87534",
    "sg:province":"Bayern",
    "wof:name":"Manfred W\u00f6rner Kosmetiksalon",
    "wof:placetype":"venue"
},
  "geometry": {"coordinates":[10.019316,47.563087],"type":"Point"}
}