{
  "type": "Feature",
  "properties": {
    "iso:country":"DE",
    "sg:address":"Theodolindenstr. 14",
    "sg:city":"Ismaning",
    "sg:phone":"+49 89/969307",
    "sg:postcode":"85737",
    "sg:province":"Bayern",
    "wof:name":"Schaar Gmbh",
    "wof:placetype":"venue"
},
  "geometry": {"coordinates":[11.683921814,48.2231483459],"type":"Point"}
}