{
  "type": "Feature",
  "properties": {
    "iso:country":"DE",
    "sg:address":"Bahnhofstr. 27",
    "sg:city":"Seubersdorf",
    "sg:phone":"+49 9497/1500",
    "sg:postcode":"92358",
    "sg:province":"Bayern",
    "wof:name":"T. M. M\u00fcller",
    "wof:placetype":"venue"
},
  "geometry": {"coordinates":[11.625551,49.167919],"type":"Point"}
}