{
  "type": "Feature",
  "properties": {
    "iso:country":"DE",
    "sg:address":"Buchenbacher Str. 20",
    "sg:city":"Mulfingen",
    "sg:phone":"+49 7938/90220",
    "sg:postcode":"74673",
    "sg:province":"Baden-W\u00fcrttemberg",
    "wof:name":"S\u00e4nger Gmbh",
    "wof:placetype":"venue"
},
  "geometry": {"coordinates":[9.802459,49.306694],"type":"Point"}
}