{
  "type": "Feature",
  "properties": {
    "iso:country":"DE",
    "sg:address":"Leipziger Str. 37",
    "sg:city":"Grimma",
    "sg:phone":"+49 3437/942080",
    "sg:postcode":"04668",
    "sg:province":"Sachsen",
    "wof:name":"Recycling Zentrum Grimma Gmbh",
    "wof:placetype":"venue"
},
  "geometry": {"coordinates":[12.7149553299,51.2312774658],"type":"Point"}
}