{
  "type": "Feature",
  "properties": {
    "iso:country":"DE",
    "sg:address":"Obergasse 11",
    "sg:city":"Volxheim",
    "sg:phone":"+49 6703/1336",
    "sg:postcode":"55546",
    "sg:province":"Rheinland-Pfalz",
    "wof:name":"Hans F. Lechthaler",
    "wof:placetype":"venue"
},
  "geometry": {"coordinates":[7.9270720482,49.8168983459],"type":"Point"}
}