{
  "type": "Feature",
  "properties": {
    "iso:country":"DE",
    "sg:address":"Witzworter Str. 2",
    "sg:city":"Friedrichstadt",
    "sg:phone":"+49 4881/93600",
    "sg:postcode":"25840",
    "sg:province":"Schleswig-Holstein",
    "wof:name":"Helmut Wandmaker Gmbh",
    "wof:placetype":"venue"
},
  "geometry": {"coordinates":[9.0740394592,54.3794708252],"type":"Point"}
}