{
  "type": "Feature",
  "properties": {
    "iso:country":"DE",
    "sg:address":"Ahornweg 40",
    "sg:city":"Neufahrn",
    "sg:phone":"+49 8165/5503",
    "sg:postcode":"85375",
    "sg:province":"Bayern",
    "wof:name":"Albert Zauner Restaurator",
    "wof:placetype":"venue"
},
  "geometry": {"coordinates":[11.6656904221,48.3193435669],"type":"Point"}
}