{
  "type": "Feature",
  "properties": {
    "iso:country":"DE",
    "sg:address":"Kespermarkt 11",
    "sg:city":"Witzenhausen",
    "sg:phone":"+49 5542/3495",
    "sg:postcode":"37213",
    "sg:province":"Hessen",
    "wof:name":"Stefan Knispel Rechtsanwalt",
    "wof:placetype":"venue"
},
  "geometry": {"coordinates":[9.8578796387,51.341178894],"type":"Point"}
}