{
  "type": "Feature",
  "properties": {
    "iso:country":"DE",
    "sg:address":"Schw\u00e4grichenstr. 13",
    "sg:city":"Leipzig",
    "sg:postcode":"04107",
    "sg:province":"Sachsen",
    "wof:name":"Suplion Beteiligungsges. Mbh",
    "wof:placetype":"venue"
},
  "geometry": {"coordinates":[12.364939,51.330002],"type":"Point"}
}