{
  "type": "Feature",
  "properties": {
    "iso:country":"DE",
    "sg:address":"Otterstr. 2",
    "sg:city":"Otterberg",
    "sg:phone":"+49 6301/33008",
    "sg:postcode":"67697",
    "sg:province":"Rheinland-Pfalz",
    "wof:name":"Der Tierische Laden",
    "wof:placetype":"venue"
},
  "geometry": {"coordinates":[7.773109,49.498913],"type":"Point"}
}