{
  "type": "Feature",
  "properties": {
    "iso:country":"DE",
    "sg:address":"Im R\u00fcbenkamp1",
    "sg:city":"Cremlingen",
    "sg:phone":"+49 5306/92900",
    "sg:postcode":"38162",
    "sg:province":"Niedersachsen",
    "wof:name":"Hohrenk Systemtechnik Gmbh",
    "wof:placetype":"venue"
},
  "geometry": {"coordinates":[10.65423,52.248524],"type":"Point"}
}