{
  "type": "Feature",
  "properties": {
    "iso:country":"DE",
    "sg:address":"Annabergstr. 14",
    "sg:city":"Wuppertal",
    "sg:phone":"+49 202/2501703",
    "sg:postcode":"42283",
    "sg:province":"Nordrhein-Westfalen",
    "wof:name":"Agentur Reisenetz",
    "wof:placetype":"venue"
},
  "geometry": {"coordinates":[7.185035,51.274586],"type":"Point"}
}