{
  "type": "Feature",
  "properties": {
    "iso:country":"DE",
    "sg:address":"Friedrichstr. 29",
    "sg:city":"Langen",
    "sg:phone":"+49 6103/27208",
    "sg:postcode":"63225",
    "sg:province":"Hessen",
    "wof:name":"Fels",
    "wof:placetype":"venue"
},
  "geometry": {"coordinates":[8.659702301,49.9910354614],"type":"Point"}
}