{
  "type": "Feature",
  "properties": {
    "iso:country":"DE",
    "sg:address":"Bobenheimer Str.",
    "sg:city":"Worms",
    "sg:phone":"+49 6241/384339",
    "sg:postcode":"67547",
    "sg:province":"Rheinland-Pfalz",
    "wof:name":"G. Br\u00fcckbauer",
    "wof:placetype":"venue"
},
  "geometry": {"coordinates":[8.348843,49.613392],"type":"Point"}
}