{
  "type": "Feature",
  "properties": {
    "iso:country":"DE",
    "sg:address":"Klarastr. 33",
    "sg:city":"Essen",
    "sg:phone":"+49 201/778688",
    "sg:postcode":"45130",
    "sg:province":"Nordrhein-Westfalen",
    "wof:name":"Manfred Menne",
    "wof:placetype":"venue"
},
  "geometry": {"coordinates":[7.0085701942,51.4386825562],"type":"Point"}
}