{
  "type": "Feature",
  "properties": {
    "iso:country":"DE",
    "sg:address":"Ibbenb\u00fcrener Str. 2",
    "sg:city":"H\u00f6rstel",
    "sg:phone":"+49 5459/972027",
    "sg:postcode":"48477",
    "sg:province":"Nordrhein-Westfalen",
    "wof:name":"Restaurant Athen",
    "wof:placetype":"venue"
},
  "geometry": {"coordinates":[7.5896191597,52.3002891541],"type":"Point"}
}