{
  "type": "Feature",
  "properties": {
    "iso:country":"DE",
    "sg:address":"Holstenplatz 6",
    "sg:city":"Schenefeld",
    "sg:phone":"+49 40/8304334",
    "sg:postcode":"22869",
    "sg:province":"Schleswig-Holstein",
    "wof:name":"Dr. Med. J\u00f6rn Cramer",
    "wof:placetype":"venue"
},
  "geometry": {"coordinates":[9.8357419968,53.6005744934],"type":"Point"}
}