{
  "type": "Feature",
  "properties": {
    "iso:country":"DE",
    "sg:address":"Stationsweg 9",
    "sg:city":"Grafschaft",
    "sg:phone":"+49 2225/17663",
    "sg:postcode":"53501",
    "sg:province":"Rheinland-Pfalz",
    "wof:name":"Rolf Helzel Architekt",
    "wof:placetype":"venue"
},
  "geometry": {"coordinates":[7.035683,50.583191],"type":"Point"}
}