{
  "type": "Feature",
  "properties": {
    "iso:country":"DE",
    "sg:address":"Lohgerberstr. 33",
    "sg:city":"Rostock",
    "sg:phone":"+49 381/26026",
    "sg:postcode":"18055",
    "sg:province":"Mecklenburg-Vorpommern",
    "wof:name":"Miami Beach",
    "wof:placetype":"venue"
},
  "geometry": {"coordinates":[12.1475191116,54.0882873535],"type":"Point"}
}