{
  "type": "Feature",
  "properties": {
    "iso:country":"DE",
    "sg:address":"Jakob-Kneip-Str. 42",
    "sg:city":"Nettersheim",
    "sg:phone":"+49 2484/1569",
    "sg:postcode":"53947",
    "sg:province":"Nordrhein-Westfalen",
    "wof:name":"Johann Reger",
    "wof:placetype":"venue"
},
  "geometry": {"coordinates":[6.6929,50.527634],"type":"Point"}
}