{
  "type": "Feature",
  "properties": {
    "iso:country":"DE",
    "sg:address":"Im Dorf 22",
    "sg:city":"Nordrach",
    "sg:phone":"+49 7838/209",
    "sg:postcode":"77787",
    "sg:province":"Baden-W\u00fcrttemberg",
    "wof:name":"Kath. Pfarramt St. Ulrich",
    "wof:placetype":"venue"
},
  "geometry": {"coordinates":[8.0787677765,48.3973007202],"type":"Point"}
}