{
  "type": "Feature",
  "properties": {
    "iso:country":"DE",
    "sg:address":"Im Alth\u00e4user 11",
    "sg:city":"Kronau",
    "sg:phone":"+49 7253/4649",
    "sg:postcode":"76709",
    "sg:province":"Baden-W\u00fcrttemberg",
    "wof:name":"Roschi-metallbau Robert Schimmel",
    "wof:placetype":"venue"
},
  "geometry": {"coordinates":[8.632444,49.210789],"type":"Point"}
}