{
  "type": "Feature",
  "properties": {
    "iso:country":"DE",
    "sg:address":"Budapester Str. 5",
    "sg:city":"Dresden",
    "sg:postcode":"01069",
    "sg:province":"Sachsen",
    "wof:name":"Sassonia Global Trading Gmbh",
    "wof:placetype":"venue"
},
  "geometry": {"coordinates":[13.7325725555,51.0463256836],"type":"Point"}
}