{
  "type": "Feature",
  "properties": {
    "iso:country":"DE",
    "sg:address":"Freiburger Str. 53",
    "sg:city":"Lenzkirch",
    "sg:phone":"+49 7653/240",
    "sg:postcode":"79853",
    "sg:province":"Baden-W\u00fcrttemberg",
    "wof:name":"Pension Daheim",
    "wof:placetype":"venue"
},
  "geometry": {"coordinates":[8.1934547424,47.8768196106],"type":"Point"}
}