{
  "type": "Feature",
  "properties": {
    "iso:country":"DE",
    "sg:address":"Am Lieden 25",
    "sg:city":"Alsfeld",
    "sg:phone":"+49 6631/2122",
    "sg:postcode":"36304",
    "sg:province":"Hessen",
    "wof:name":"Erika Gontarski",
    "wof:placetype":"venue"
},
  "geometry": {"coordinates":[9.2661628723,50.7504272461],"type":"Point"}
}