{
  "type": "Feature",
  "properties": {
    "iso:country":"DE",
    "sg:address":"Mail\u00e4nder Str. 9",
    "sg:city":"M\u00fcnchen",
    "sg:phone":"+49 89/31772916",
    "sg:postcode":"81545",
    "sg:province":"Bayern",
    "wof:name":"Yukon Computer Vertriebs- Gmbh",
    "wof:placetype":"venue"
},
  "geometry": {"coordinates":[11.5621862411,48.0904121399],"type":"Point"}
}