{
  "type": "Feature",
  "properties": {
    "iso:country":"DE",
    "sg:address":"S\u00fcdwall 48",
    "sg:city":"Geldern",
    "sg:phone":"+49 2831/2230",
    "sg:postcode":"47608",
    "sg:province":"Nordrhein-Westfalen",
    "wof:name":"Johann Rayers",
    "wof:placetype":"venue"
},
  "geometry": {"coordinates":[6.3219461441,51.5162467957],"type":"Point"}
}