{
  "type": "Feature",
  "properties": {
    "iso:country":"DE",
    "sg:address":"Akazienstr. 9\u00df",
    "sg:city":"M\u00f6nchengladbach",
    "sg:phone":"+49 2166/935511",
    "sg:postcode":"41239",
    "sg:province":"Nordrhein-Westfalen",
    "wof:name":"Peter Buscher",
    "wof:placetype":"venue"
},
  "geometry": {"coordinates":[6.4291491508,51.1742362976],"type":"Point"}
}