{
  "type": "Feature",
  "properties": {
    "iso:country":"DE",
    "sg:address":"Teichstr. 26",
    "sg:city":"Zschorlau",
    "sg:postcode":"08321",
    "sg:province":"Sachsen",
    "wof:name":"G\u00fcnter Gl\u00e4ser",
    "wof:placetype":"venue"
},
  "geometry": {"coordinates":[12.6496562958,50.5485610962],"type":"Point"}
}