{
  "type": "Feature",
  "properties": {
    "iso:country":"DE",
    "sg:address":"Am Bahnhof 8",
    "sg:city":"Schmelz",
    "sg:phone":"+49 6887/87631",
    "sg:postcode":"66839",
    "sg:province":"Saarland",
    "wof:name":"Anja Heinrich",
    "wof:placetype":"venue"
},
  "geometry": {"coordinates":[6.8574252129,49.4407501221],"type":"Point"}
}