{
  "type": "Feature",
  "properties": {
    "iso:country":"DE",
    "sg:address":"Eichenkehre 5",
    "sg:city":"Heede",
    "sg:postcode":"25355",
    "sg:province":"Schleswig-Holstein",
    "wof:name":"Ott W\u00e4schereitechnik Gmbh",
    "wof:placetype":"venue"
},
  "geometry": {"coordinates":[9.793382,53.786739],"type":"Point"}
}