{
  "type": "Feature",
  "properties": {
    "iso:country":"DE",
    "sg:address":"Krelingen 9",
    "sg:city":"Walsrode",
    "sg:phone":"+49 5167/325",
    "sg:postcode":"29664",
    "sg:province":"Niedersachsen",
    "wof:name":"Gottfried Willenbockel",
    "wof:placetype":"venue"
},
  "geometry": {"coordinates":[9.66515,52.802395],"type":"Point"}
}