{
  "type": "Feature",
  "properties": {
    "iso:country":"DE",
    "sg:address":"Bahnhofstr. 61",
    "sg:city":"G\u00f6rlitz",
    "sg:phone":"+49 3581/400346",
    "sg:postcode":"02826",
    "sg:province":"Sachsen",
    "wof:name":"L & L Immobilien Management Gmbh",
    "wof:placetype":"venue"
},
  "geometry": {"coordinates":[14.9885702133,51.14427948],"type":"Point"}
}