{
  "type": "Feature",
  "properties": {
    "iso:country":"DE",
    "sg:address":"Eisenbahnstr. 16",
    "sg:city":"Albstadt",
    "sg:phone":"+49 7432/70170",
    "sg:postcode":"72461",
    "sg:province":"Baden-W\u00fcrttemberg",
    "wof:name":"Wilhelm Weissmann Maschenmoden Kg",
    "wof:placetype":"venue"
},
  "geometry": {"coordinates":[9.0185422897,48.2524261475],"type":"Point"}
}