{
  "type": "Feature",
  "properties": {
    "iso:country":"DE",
    "sg:address":"Wormser Str. 5",
    "sg:city":"Berlin",
    "sg:phone":"+49 30/2189217",
    "sg:postcode":"10789",
    "sg:province":"Berlin",
    "wof:name":"Helene Wehage Rechtsanw\u00e4ltin",
    "wof:placetype":"venue"
},
  "geometry": {"coordinates":[13.3440828323,52.5003242493],"type":"Point"}
}