{
  "type": "Feature",
  "properties": {
    "iso:country":"DE",
    "sg:address":"Skalitzer Str. 99",
    "sg:city":"Berlin",
    "sg:phone":"+49 30/6187940",
    "sg:postcode":"10997",
    "sg:province":"Berlin",
    "wof:name":"Erhard Gross",
    "wof:placetype":"venue"
},
  "geometry": {"coordinates":[13.4289779663,52.4995346069],"type":"Point"}
}