{
  "type": "Feature",
  "properties": {
    "iso:country":"DE",
    "sg:address":"Bahnhofstr. 24",
    "sg:city":"Neukirchen-Vluyn",
    "sg:phone":"+49 2845/21310",
    "sg:postcode":"47506",
    "sg:province":"Nordrhein-Westfalen",
    "wof:name":"Gossens U. Esselborn",
    "wof:placetype":"venue"
},
  "geometry": {"coordinates":[6.5298628807,51.4366722107],"type":"Point"}
}