{
  "type": "Feature",
  "properties": {
    "iso:country":"DE",
    "sg:address":"M\u00f6ttelinstr. 22",
    "sg:city":"Ravensburg",
    "sg:phone":"+49 751/23692",
    "sg:postcode":"88212",
    "sg:province":"Baden-W\u00fcrttemberg",
    "wof:name":"Mauch",
    "wof:placetype":"venue"
},
  "geometry": {"coordinates":[9.6133022308,47.786895752],"type":"Point"}
}