{
  "type": "Feature",
  "properties": {
    "iso:country":"DE",
    "sg:address":"Vaihinger Markt 30",
    "sg:city":"Stuttgart",
    "sg:phone":"+49 711/731932",
    "sg:postcode":"70563",
    "sg:province":"Baden-W\u00fcrttemberg",
    "wof:name":"Breuning Kg",
    "wof:placetype":"venue"
},
  "geometry": {"coordinates":[9.110965,48.730061],"type":"Point"}
}