{
  "type": "Feature",
  "properties": {
    "iso:country":"DE",
    "sg:address":"Auf Den Gathen 10",
    "sg:city":"D\u00fcsseldorf",
    "sg:phone":"+49 4921/1930170",
    "sg:postcode":"40221",
    "sg:province":"Nordrhein-Westfalen",
    "wof:name":"Hermes Druck & Verlag Gmbh",
    "wof:placetype":"venue"
},
  "geometry": {"coordinates":[6.7396011353,51.2062110901],"type":"Point"}
}