{
  "type": "Feature",
  "properties": {
    "iso:country":"DE",
    "sg:address":"Hinteres \u00d6schle 8",
    "sg:city":"Rietheim-Weilheim",
    "sg:phone":"+49 7461/78219",
    "sg:postcode":"78604",
    "sg:province":"Baden-W\u00fcrttemberg",
    "wof:name":"Astro-hydraulik Gmbh",
    "wof:placetype":"venue"
},
  "geometry": {"coordinates":[8.775948,48.027122],"type":"Point"}
}