{
  "type": "Feature",
  "properties": {
    "iso:country":"DE",
    "sg:address":"Kapellenplatz 4",
    "sg:city":"Feucht",
    "sg:phone":"+49 9128/12152",
    "sg:postcode":"90537",
    "sg:province":"Bayern",
    "wof:name":"Ev. Luth. Pfarramt 2. Pfarrstelle",
    "wof:placetype":"venue"
},
  "geometry": {"coordinates":[11.2130746841,49.37733078],"type":"Point"}
}