{
  "type": "Feature",
  "properties": {
    "iso:country":"DE",
    "sg:address":"Egelseestr. 24",
    "sg:city":"Bamberg",
    "sg:postcode":"96050",
    "sg:province":"Bayern",
    "wof:name":"Basket Bamberg Beteiligungs Gmbh",
    "wof:placetype":"venue"
},
  "geometry": {"coordinates":[10.900001,49.896091],"type":"Point"}
}