{
  "type": "Feature",
  "properties": {
    "iso:country":"DE",
    "sg:address":"Rumannstr. 32",
    "sg:city":"Hannover",
    "sg:phone":"+49 511/341536",
    "sg:postcode":"30161",
    "sg:province":"Niedersachsen",
    "wof:name":"Hahne Und K\u00f6hler Rechtsanw\u00e4lte",
    "wof:placetype":"venue"
},
  "geometry": {"coordinates":[9.7528209686,52.3806495667],"type":"Point"}
}