{
  "type": "Feature",
  "properties": {
    "iso:country":"DE",
    "sg:address":"M\u00fcnsaer Str. 15",
    "sg:city":"Altenburg",
    "sg:postcode":"04600",
    "sg:province":"Th\u00fcringen",
    "wof:name":"Mesa System Gmbh",
    "wof:placetype":"venue"
},
  "geometry": {"coordinates":[12.4468221664,50.9851646423],"type":"Point"}
}