{
  "type": "Feature",
  "properties": {
    "iso:country":"DE",
    "sg:address":"Zum Papenbruch 60",
    "sg:city":"Velbert",
    "sg:phone":"+49 2053/80810",
    "sg:postcode":"42553",
    "sg:province":"Nordrhein-Westfalen",
    "wof:name":"H. Radeck",
    "wof:placetype":"venue"
},
  "geometry": {"coordinates":[7.0607700348,51.3126678467],"type":"Point"}
}