{
  "type": "Feature",
  "properties": {
    "iso:country":"DE",
    "sg:address":"Lange Str. 24",
    "sg:city":"Pferdingsleben",
    "sg:phone":"+49 36258/52254",
    "sg:postcode":"99869",
    "sg:province":"Th\u00fcringen",
    "wof:name":"Gastst\u00e4tte Zur Waldm\u00fchle Inh. Uwe T\u00fcngertal",
    "wof:placetype":"venue"
},
  "geometry": {"coordinates":[10.8194675446,50.9690742493],"type":"Point"}
}