{
  "type": "Feature",
  "properties": {
    "iso:country":"DE",
    "sg:address":"Steig\u00e4ckerstr. 4",
    "sg:city":"Berg",
    "sg:phone":"+49 751/42655",
    "sg:postcode":"88276",
    "sg:province":"Baden-W\u00fcrttemberg",
    "wof:name":"Stefan Gr\u00fcndler",
    "wof:placetype":"venue"
},
  "geometry": {"coordinates":[9.5967512131,47.8045654297],"type":"Point"}
}