{
  "type": "Feature",
  "properties": {
    "iso:country":"DE",
    "sg:address":"Leipziger Str. 17",
    "sg:city":"Geithain",
    "sg:phone":"+49 34341/43168",
    "sg:postcode":"04643",
    "sg:province":"Sachsen",
    "wof:name":"Stadtarchiv",
    "wof:placetype":"venue"
},
  "geometry": {"coordinates":[12.692858,51.054581],"type":"Point"}
}