{
  "type": "Feature",
  "properties": {
    "iso:country":"DE",
    "sg:address":"Theo-Neubauer-Str. 15 b",
    "sg:city":"Wutha-Farnroda",
    "sg:phone":"+49 36921/92423",
    "sg:postcode":"99848",
    "sg:province":"Th\u00fcringen",
    "wof:name":"J\u00fcrgen H\u00f6ch",
    "wof:placetype":"venue"
},
  "geometry": {"coordinates":[10.3658561707,50.9404449463],"type":"Point"}
}