{
  "type": "Feature",
  "properties": {
    "iso:country":"DE",
    "sg:address":"Hohenbachernstr. 42",
    "sg:city":"Kranzberg",
    "sg:phone":"+49 8166/998887",
    "sg:postcode":"85402",
    "sg:province":"Bayern",
    "wof:name":"Alexander Life Gmbh",
    "wof:placetype":"venue"
},
  "geometry": {"coordinates":[11.6275596619,48.4078407288],"type":"Point"}
}