{
  "type": "Feature",
  "properties": {
    "iso:country":"DE",
    "sg:address":"Postfach 51",
    "sg:city":"Hettstedt",
    "sg:postcode":"06321",
    "sg:province":"Sachsen-Anhalt",
    "wof:name":"Steschi Inh. W. Horka",
    "wof:placetype":"venue"
},
  "geometry": {"coordinates":[11.51116,51.644939],"type":"Point"}
}