{
  "type": "Feature",
  "properties": {
    "iso:country":"DE",
    "sg:address":"Georgenstr. 21",
    "sg:city":"Eisenach",
    "sg:phone":"+49 3691/746020",
    "sg:postcode":"99817",
    "sg:province":"Th\u00fcringen",
    "wof:name":"Heinz Grobst",
    "wof:placetype":"venue"
},
  "geometry": {"coordinates":[10.3168106079,50.975566864],"type":"Point"}
}