{
  "type": "Feature",
  "properties": {
    "iso:country":"DE",
    "sg:address":"Hochstr. 28",
    "sg:city":"Alsbach-H\u00e4hnlein",
    "sg:phone":"+49 6257/93190",
    "sg:postcode":"64665",
    "sg:province":"Hessen",
    "wof:name":"Offcom Office- Communication Gmbh",
    "wof:placetype":"venue"
},
  "geometry": {"coordinates":[8.6239547729,49.7367553711],"type":"Point"}
}