{
  "type": "Feature",
  "properties": {
    "iso:country":"DE",
    "sg:address":"Benzstr. 11",
    "sg:city":"Malsch",
    "sg:phone":"+49 7246/4082",
    "sg:postcode":"76316",
    "sg:province":"Baden-W\u00fcrttemberg",
    "wof:name":"S\u00fcddeutsche Teerindustrie Gmbh & Co. Kg",
    "wof:placetype":"venue"
},
  "geometry": {"coordinates":[8.3211641312,48.8897895813],"type":"Point"}
}