{
  "type": "Feature",
  "properties": {
    "iso:country":"DE",
    "sg:address":"Goethestr. 36",
    "sg:city":"Neu-Isenburg",
    "sg:phone":"+49 6102/22498",
    "sg:postcode":"63263",
    "sg:province":"Hessen",
    "wof:name":"Alexander Fogel",
    "wof:placetype":"venue"
},
  "geometry": {"coordinates":[8.6807851791,50.0549812317],"type":"Point"}
}