{
  "type": "Feature",
  "properties": {
    "iso:country":"DE",
    "sg:address":"Kleine Rurstr. 5",
    "sg:city":"J\u00fclich",
    "sg:phone":"+49 2461/2199",
    "sg:postcode":"52428",
    "sg:province":"Nordrhein-Westfalen",
    "wof:name":"Meusers Men - Shop",
    "wof:placetype":"venue"
},
  "geometry": {"coordinates":[6.3575081825,50.9215278625],"type":"Point"}
}