{
  "type": "Feature",
  "properties": {
    "iso:country":"DE",
    "sg:address":"Sollmannweg 13",
    "sg:city":"Berlin",
    "sg:phone":"+49 30/6042687",
    "sg:postcode":"12353",
    "sg:province":"Berlin",
    "wof:name":"Bernd Kubinek Ingenieur",
    "wof:placetype":"venue"
},
  "geometry": {"coordinates":[13.466881752,52.4228553772],"type":"Point"}
}