{
  "type": "Feature",
  "properties": {
    "iso:country":"DE",
    "sg:address":"Diakonissenweg 12",
    "sg:city":"Esslingen",
    "sg:phone":"+49 711/3169240",
    "sg:postcode":"73730",
    "sg:province":"Baden-W\u00fcrttemberg",
    "wof:name":"Gerd Fleischer",
    "wof:placetype":"venue"
},
  "geometry": {"coordinates":[9.3346796036,48.7326393127],"type":"Point"}
}