{
  "type": "Feature",
  "properties": {
    "iso:country":"DE",
    "sg:address":"Belforter Str. 25",
    "sg:city":"Berlin",
    "sg:phone":"+49 30/4410581",
    "sg:postcode":"10405",
    "sg:province":"Berlin",
    "wof:name":"J. H. Ketter Beratungs- Vermittlungs-",
    "wof:placetype":"venue"
},
  "geometry": {"coordinates":[13.418469429,52.532459259],"type":"Point"}
}