{
  "type": "Feature",
  "properties": {
    "iso:country":"DE",
    "sg:address":"Friesenstr. 2",
    "sg:city":"Zeuthen",
    "sg:phone":"+49 33762/72780",
    "sg:postcode":"15738",
    "sg:province":"Brandenburg",
    "wof:name":"S. Schenk",
    "wof:placetype":"venue"
},
  "geometry": {"coordinates":[13.625845,52.349667],"type":"Point"}
}