{
  "type": "Feature",
  "properties": {
    "iso:country":"DE",
    "sg:address":"Lange R\u00f6tterstr. 23",
    "sg:city":"Mannheim",
    "sg:phone":"+49 621/375769",
    "sg:postcode":"68167",
    "sg:province":"Baden-W\u00fcrttemberg",
    "wof:name":"Bosborusimbi\u00df",
    "wof:placetype":"venue"
},
  "geometry": {"coordinates":[8.4779281616,49.4977645874],"type":"Point"}
}