{
  "type": "Feature",
  "properties": {
    "iso:country":"DE",
    "sg:address":"Klosterstrasse 34",
    "sg:city":"\u00dchlingen-Berau",
    "sg:postcode":"79777",
    "sg:province":"Baden-W\u00fcrttemberg",
    "wof:name":"Creative-shop - Pins, Stickereien, Textildruck",
    "wof:placetype":"venue"
},
  "geometry": {"coordinates":[8.259095192,47.6914558411],"type":"Point"}
}