{
  "type": "Feature",
  "properties": {
    "iso:country":"DE",
    "sg:address":"G\u00fcntzelstr. 3",
    "sg:city":"Berlin",
    "sg:phone":"+49 30/2112927",
    "sg:postcode":"10717",
    "sg:province":"Berlin",
    "wof:name":"Nannis Ecke",
    "wof:placetype":"venue"
},
  "geometry": {"coordinates":[13.3351259232,52.4908332825],"type":"Point"}
}