{
  "type": "Feature",
  "properties": {
    "iso:country":"DE",
    "sg:address":"Bergisch Born 162",
    "sg:city":"Remscheid",
    "sg:phone":"+49 2191/96560",
    "sg:postcode":"42897",
    "sg:province":"Nordrhein-Westfalen",
    "wof:name":"Borner Hof",
    "wof:placetype":"venue"
},
  "geometry": {"coordinates":[7.2628831863,51.1534347534],"type":"Point"}
}