{
  "type": "Feature",
  "properties": {
    "iso:country":"DE",
    "sg:address":"Webereiweg 12",
    "sg:city":"Stephanskirchen",
    "sg:phone":"+49 8036/2286",
    "sg:postcode":"83071",
    "sg:province":"Bayern",
    "wof:name":"Veith Verwaltungs Gmbh",
    "wof:placetype":"venue"
},
  "geometry": {"coordinates":[12.1727313995,47.8606987],"type":"Point"}
}