{
  "type": "Feature",
  "properties": {
    "iso:country":"DE",
    "sg:address":"Kapellenstr. 45",
    "sg:city":"Elfershausen",
    "sg:phone":"+49 9704/1780",
    "sg:postcode":"97725",
    "sg:province":"Bayern",
    "wof:name":"Gottfried Gessner",
    "wof:placetype":"venue"
},
  "geometry": {"coordinates":[9.9591264725,50.1483154297],"type":"Point"}
}