{
  "type": "Feature",
  "properties": {
    "iso:country":"DE",
    "sg:address":"Schepp Allee 47",
    "sg:city":"Darmstadt",
    "sg:postcode":"64295",
    "sg:province":"Hessen",
    "wof:name":"Eco Energie International Investors Ag",
    "wof:placetype":"venue"
},
  "geometry": {"coordinates":[8.638747,49.863174],"type":"Point"}
}