{
  "type": "Feature",
  "properties": {
    "iso:country":"DE",
    "sg:address":"In der Buttergrube 1",
    "sg:city":"Legefeld",
    "sg:phone":"+49 3643/232650",
    "sg:postcode":"99438",
    "sg:province":"Th\u00fcringen",
    "wof:name":"Weimar Uhren",
    "wof:placetype":"venue"
},
  "geometry": {"coordinates":[11.2868003845,50.9366340637],"type":"Point"}
}