{
  "type": "Feature",
  "properties": {
    "iso:country":"DE",
    "sg:address":"Ludwigsplatz 3",
    "sg:city":"Alsfeld",
    "sg:phone":"+49 6631/71515",
    "sg:postcode":"36304",
    "sg:province":"Hessen",
    "wof:name":"Rudolf Nau Gmbh",
    "wof:placetype":"venue"
},
  "geometry": {"coordinates":[9.269521,50.75309],"type":"Point"}
}