{
  "type": "Feature",
  "properties": {
    "iso:country":"DE",
    "sg:address":"Warngauer Str. 57",
    "sg:city":"M\u00fcnchen",
    "sg:phone":"+49 89/696314",
    "sg:postcode":"81539",
    "sg:province":"Bayern",
    "wof:name":"Taverne Plaka",
    "wof:placetype":"venue"
},
  "geometry": {"coordinates":[11.5922641754,48.1130485535],"type":"Point"}
}