{
  "type": "Feature",
  "properties": {
    "iso:country":"DE",
    "sg:address":"Plauener Str. 50",
    "sg:city":"Hof",
    "sg:phone":"+49 9281/84866",
    "sg:postcode":"95028",
    "sg:province":"Bayern",
    "wof:name":"Deutsche Flotte",
    "wof:placetype":"venue"
},
  "geometry": {"coordinates":[11.919552803,50.3296852112],"type":"Point"}
}