{
  "type": "Feature",
  "properties": {
    "iso:country":"DE",
    "sg:address":"Paul-Ehrlich-Str. 28",
    "sg:city":"Hamm",
    "sg:phone":"+49 2381/401059",
    "sg:postcode":"59077",
    "sg:province":"Nordrhein-Westfalen",
    "wof:name":"Manfred Sch\u00e4fer",
    "wof:placetype":"venue"
},
  "geometry": {"coordinates":[7.7657852173,51.6409378052],"type":"Point"}
}