{
  "type": "Feature",
  "properties": {
    "iso:country":"DE",
    "sg:address":"Lechm\u00fchlen 2",
    "sg:city":"Fuchstal",
    "sg:phone":"+49 8243/1471",
    "sg:postcode":"86925",
    "sg:province":"Bayern",
    "wof:name":"Siegfried Hafeneder Kunstmaler",
    "wof:placetype":"venue"
},
  "geometry": {"coordinates":[10.866814,47.951908],"type":"Point"}
}