{
  "type": "Feature",
  "properties": {
    "iso:country":"DE",
    "sg:address":"Auf der Horst 7",
    "sg:city":"Messingen",
    "sg:phone":"+49 5905/622",
    "sg:postcode":"49832",
    "sg:province":"Niedersachsen",
    "wof:name":"L. Und J. Sch\u00fclke Architekten",
    "wof:placetype":"venue"
},
  "geometry": {"coordinates":[7.495039,52.471931],"type":"Point"}
}