{
  "type": "Feature",
  "properties": {
    "iso:country":"DE",
    "sg:address":"Bahnhofstr. 40",
    "sg:city":"Maikammer",
    "sg:phone":"+49 6321/5112",
    "sg:postcode":"67487",
    "sg:province":"Rheinland-Pfalz",
    "wof:name":"August Stachel Weinanbau",
    "wof:placetype":"venue"
},
  "geometry": {"coordinates":[8.1399097443,49.3063354492],"type":"Point"}
}