{
  "type": "Feature",
  "properties": {
    "iso:country":"DE",
    "sg:address":"Prager Str. 5",
    "sg:city":"Hersbruck",
    "sg:phone":"+49 9151/2133",
    "sg:postcode":"91217",
    "sg:province":"Bayern",
    "wof:name":"Norbert Kohl",
    "wof:placetype":"venue"
},
  "geometry": {"coordinates":[11.4294109344,49.5091056824],"type":"Point"}
}