{
  "type": "Feature",
  "properties": {
    "iso:country":"DE",
    "sg:address":"Schweppermannstr. 5",
    "sg:city":"Kastl",
    "sg:phone":"+49 9625/1762",
    "sg:postcode":"92280",
    "sg:province":"Bayern",
    "wof:name":"J. Matschiner",
    "wof:placetype":"venue"
},
  "geometry": {"coordinates":[11.6891622543,49.364818573],"type":"Point"}
}