{
  "type": "Feature",
  "properties": {
    "iso:country":"DE",
    "sg:address":"Eiffestr. 426",
    "sg:city":"Hamburg",
    "sg:phone":"+49 40/256010",
    "sg:postcode":"20537",
    "sg:province":"Hamburg",
    "wof:name":"Thomas Hoeltzenbein Architekt",
    "wof:placetype":"venue"
},
  "geometry": {"coordinates":[10.045197,53.552418],"type":"Point"}
}