{
  "type": "Feature",
  "properties": {
    "iso:country":"DE",
    "sg:address":"Nebendahlstr. 1",
    "sg:city":"Hamburg",
    "sg:phone":"+49 40/6521590",
    "sg:postcode":"22041",
    "sg:province":"Hamburg",
    "wof:name":"Anders Tabbert & Co. Gmbh",
    "wof:placetype":"venue"
},
  "geometry": {"coordinates":[10.0659399033,53.5769004822],"type":"Point"}
}