{
  "type": "Feature",
  "properties": {
    "iso:country":"DE",
    "sg:address":"Bismarckstr. 23",
    "sg:city":"Wangerland",
    "sg:phone":"+49 4463/1429",
    "sg:postcode":"26434",
    "sg:province":"Niedersachsen",
    "wof:name":"Elektro Kirschner Gmbh",
    "wof:placetype":"venue"
},
  "geometry": {"coordinates":[7.921595,53.662624],"type":"Point"}
}