{
  "type": "Feature",
  "properties": {
    "iso:country":"DE",
    "sg:address":"Magdeburger Str. 28",
    "sg:city":"Rodgau",
    "sg:phone":"+49 6106/74284",
    "sg:postcode":"63110",
    "sg:province":"Hessen",
    "wof:name":"Heidrun G\u00f6ritz",
    "wof:placetype":"venue"
},
  "geometry": {"coordinates":[8.871118,50.004005],"type":"Point"}
}