{
  "type": "Feature",
  "properties": {
    "iso:country":"DE",
    "sg:address":"Th\u00e4lmannstr. 93",
    "sg:city":"Wandlitz",
    "sg:phone":"+49 33397/7690",
    "sg:postcode":"16348",
    "sg:province":"Brandenburg",
    "wof:name":"Hotel Seeterrassen",
    "wof:placetype":"venue"
},
  "geometry": {"coordinates":[13.4677324295,52.7613143921],"type":"Point"}
}