{
  "type": "Feature",
  "properties": {
    "iso:country":"DE",
    "sg:address":"Parkweg 29",
    "sg:city":"Achim",
    "sg:phone":"+49 4202/84020",
    "sg:postcode":"28832",
    "sg:province":"Niedersachsen",
    "wof:name":"Hans-christian Karstendiek Im-u.export M.rund-u.schnitth.",
    "wof:placetype":"venue"
},
  "geometry": {"coordinates":[9.0521430969,53.0076904297],"type":"Point"}
}