{
  "type": "Feature",
  "properties": {
    "iso:country":"DE",
    "sg:address":"Englschalkinger Str. 200",
    "sg:city":"M\u00fcnchen",
    "sg:phone":"+49 89/931067",
    "sg:postcode":"81927",
    "sg:province":"Bayern",
    "wof:name":"Conceptsatz Gesellschaft F\u00fcr Satztechnik Und Reproduktion",
    "wof:placetype":"venue"
},
  "geometry": {"coordinates":[11.636494,48.154446],"type":"Point"}
}