{
  "type": "Feature",
  "properties": {
    "iso:country":"DE",
    "sg:address":"Im Gewerbegebiet 23",
    "sg:city":"Schortens",
    "sg:phone":"+49 4461/890341",
    "sg:postcode":"26419",
    "sg:province":"Niedersachsen",
    "wof:name":"Frisia-waren-handels Gmbh",
    "wof:placetype":"venue"
},
  "geometry": {"coordinates":[7.9653859138,53.5368423462],"type":"Point"}
}