{
  "type": "Feature",
  "properties": {
    "iso:country":"DE",
    "sg:address":"Gartenstr. 8",
    "sg:city":"Diez",
    "sg:phone":"+49 6432/62717",
    "sg:postcode":"65582",
    "sg:province":"Rheinland-Pfalz",
    "wof:name":"G\u00fcnter Gr\u00fcnewald",
    "wof:placetype":"venue"
},
  "geometry": {"coordinates":[8.027675,50.370083],"type":"Point"}
}