{
  "type": "Feature",
  "properties": {
    "iso:country":"DE",
    "sg:address":"Heinrich-Magnani-Str. 12",
    "sg:city":"Buchen",
    "sg:phone":"+49 6281/8042",
    "sg:postcode":"74722",
    "sg:province":"Baden-W\u00fcrttemberg",
    "wof:name":"R. Hemlein",
    "wof:placetype":"venue"
},
  "geometry": {"coordinates":[9.3651561737,49.5174026489],"type":"Point"}
}