{
  "type": "Feature",
  "properties": {
    "iso:country":"DE",
    "sg:address":"Silgen Bargen 37",
    "sg:city":"Bornh\u00f6ved",
    "sg:phone":"+49 4323/7248",
    "sg:postcode":"24619",
    "sg:province":"Schleswig-Holstein",
    "wof:name":"Helmut Braun",
    "wof:placetype":"venue"
},
  "geometry": {"coordinates":[10.229309,54.061302],"type":"Point"}
}