{
  "type": "Feature",
  "properties": {
    "iso:country":"DE",
    "sg:address":"Rheydter Str. 142",
    "sg:city":"Korschenbroich",
    "sg:phone":"+49 2161/64790",
    "sg:postcode":"41352",
    "sg:province":"Nordrhein-Westfalen",
    "wof:name":"Hans Bolten Bestattungsinstitut",
    "wof:placetype":"venue"
},
  "geometry": {"coordinates":[6.498533,51.182884],"type":"Point"}
}