{
  "type": "Feature",
  "properties": {
    "iso:country":"DE",
    "sg:address":"Gartnerstr. 20",
    "sg:city":"Gundelfingen",
    "sg:phone":"+49 9073/840",
    "sg:postcode":"89423",
    "sg:province":"Bayern",
    "wof:name":"Josef Gartner Gmbh & Co. Kg",
    "wof:placetype":"venue"
},
  "geometry": {"coordinates":[10.381303,48.549046],"type":"Point"}
}