{
  "type": "Feature",
  "properties": {
    "iso:country":"DE",
    "sg:address":"M\u00fchlenstr. 18",
    "sg:city":"Buchholz",
    "sg:phone":"+49 4825/2862",
    "sg:postcode":"25712",
    "sg:province":"Schleswig-Holstein",
    "wof:name":"K. Horstmann",
    "wof:placetype":"venue"
},
  "geometry": {"coordinates":[9.22363,53.986065],"type":"Point"}
}