{
  "type": "Feature",
  "properties": {
    "iso:country":"DE",
    "sg:address":"Turpinstr. 114",
    "sg:city":"Aachen",
    "sg:phone":"+49 241/509537",
    "sg:postcode":"52066",
    "sg:province":"Nordrhein-Westfalen",
    "wof:name":"Alfons Bragard Ingenieur",
    "wof:placetype":"venue"
},
  "geometry": {"coordinates":[6.1112341881,50.7679023743],"type":"Point"}
}