{
  "type": "Feature",
  "properties": {
    "iso:country":"DE",
    "sg:address":"Sours-Allee 2",
    "sg:city":"Dienheim",
    "sg:phone":"+49 6133/3112",
    "sg:postcode":"55276",
    "sg:province":"Rheinland-Pfalz",
    "wof:name":"Herr Immobilienmakler",
    "wof:placetype":"venue"
},
  "geometry": {"coordinates":[8.3535842896,49.8419837952],"type":"Point"}
}