{
  "type": "Feature",
  "properties": {
    "iso:country":"DE",
    "sg:address":"Carl-Zeiss-Str. 7",
    "sg:city":"Ramstein-Miesenbach",
    "sg:phone":"+49 6371/57070",
    "sg:postcode":"66877",
    "sg:province":"Rheinland-Pfalz",
    "wof:name":"H. Dresch",
    "wof:placetype":"venue"
},
  "geometry": {"coordinates":[7.536129,49.434818],"type":"Point"}
}