{
  "type": "Feature",
  "properties": {
    "iso:country":"DE",
    "sg:address":"Bahnhofstr. 24",
    "sg:city":"Georgsmarienh\u00fctte",
    "sg:phone":"+49 5401/86770",
    "sg:postcode":"49124",
    "sg:province":"Niedersachsen",
    "wof:name":"Raiffeisen- Warengenossenschaft Eg",
    "wof:placetype":"venue"
},
  "geometry": {"coordinates":[8.064375,52.2061],"type":"Point"}
}