{
  "type": "Feature",
  "properties": {
    "iso:country":"DE",
    "sg:address":"Im Gersweilerhof 23",
    "sg:city":"Kaiserslautern",
    "sg:phone":"+49 631/3403006",
    "sg:postcode":"67659",
    "sg:province":"Rheinland-Pfalz",
    "wof:name":"Volker Schwenk",
    "wof:placetype":"venue"
},
  "geometry": {"coordinates":[7.785490036,49.4719390869],"type":"Point"}
}