{
  "type": "Feature",
  "properties": {
    "iso:country":"DE",
    "sg:address":"Bahnhofstr. 35",
    "sg:city":"Rheinberg",
    "sg:phone":"+49 2843/3043",
    "sg:postcode":"47495",
    "sg:province":"Nordrhein-Westfalen",
    "wof:name":"Natursteinwerk Schiffer Gmbh",
    "wof:placetype":"venue"
},
  "geometry": {"coordinates":[6.5952701569,51.5428276062],"type":"Point"}
}