{
  "type": "Feature",
  "properties": {
    "iso:country":"DE",
    "sg:address":"Pulverm\u00fchlenweg 3",
    "sg:city":"M\u00fchltal",
    "sg:phone":"+49 6151/148270",
    "sg:postcode":"64367",
    "sg:province":"Hessen",
    "wof:name":"Anneliese Genius Heilpraktikerin",
    "wof:placetype":"venue"
},
  "geometry": {"coordinates":[8.6958723068,49.8223342896],"type":"Point"}
}