{
  "type": "Feature",
  "properties": {
    "iso:country":"DE",
    "sg:address":"D\u00fclmener Str. 2",
    "sg:city":"Nottuln",
    "sg:phone":"+49 2502/25777",
    "sg:postcode":"48301",
    "sg:province":"Nordrhein-Westfalen",
    "wof:name":"Top Fit Studio",
    "wof:placetype":"venue"
},
  "geometry": {"coordinates":[7.3533592224,51.9270896912],"type":"Point"}
}