{
  "type": "Feature",
  "properties": {
    "iso:country":"DE",
    "sg:address":"Mobil-Oil-Str 42",
    "sg:city":"Ampfing",
    "sg:phone":"+49 8636/98350",
    "sg:postcode":"84539",
    "sg:province":"Bayern",
    "wof:name":"Aist Gmbh",
    "wof:placetype":"venue"
},
  "geometry": {"coordinates":[12.404755,48.251789],"type":"Point"}
}