{
  "type": "Feature",
  "properties": {
    "iso:country":"DE",
    "sg:address":"Burkersdorf 34",
    "sg:city":"Saara",
    "sg:phone":"+49 3447/316633",
    "sg:postcode":"04603",
    "sg:province":"Th\u00fcringen",
    "wof:name":"Dietmar Meier",
    "wof:placetype":"venue"
},
  "geometry": {"coordinates":[12.396494,50.949203],"type":"Point"}
}