{
  "type": "Feature",
  "properties": {
    "iso:country":"DE",
    "sg:address":"Johannesstr. 5",
    "sg:city":"Ulm",
    "sg:phone":"+49 731/9387474",
    "sg:postcode":"89081",
    "sg:province":"Baden-W\u00fcrttemberg",
    "wof:name":"Bernecker & Krause",
    "wof:placetype":"venue"
},
  "geometry": {"coordinates":[9.948255,48.400234],"type":"Point"}
}