{
  "type": "Feature",
  "properties": {
    "iso:country":"DE",
    "sg:address":"Eggeweg 6",
    "sg:city":"Schmallenberg",
    "sg:phone":"+49 2975/313",
    "sg:postcode":"57392",
    "sg:province":"Nordrhein-Westfalen",
    "wof:name":"Feldmann-sch\u00fctte",
    "wof:placetype":"venue"
},
  "geometry": {"coordinates":[8.374857,51.158504],"type":"Point"}
}