{
  "type": "Feature",
  "properties": {
    "iso:country":"DE",
    "sg:address":"Am Graswege 29",
    "sg:city":"Hannover",
    "sg:phone":"+49 511/885579",
    "sg:postcode":"30169",
    "sg:province":"Niedersachsen",
    "wof:name":"Erwin Neu Kameramann",
    "wof:placetype":"venue"
},
  "geometry": {"coordinates":[9.7472171783,52.3601760864],"type":"Point"}
}