{
  "type": "Feature",
  "properties": {
    "iso:country":"DE",
    "sg:address":"Kopernikusstr. 20",
    "sg:city":"Berlin",
    "sg:postcode":"10245",
    "sg:province":"Berlin",
    "wof:name":"Kunststofftechnik Ulrike Lapacz E. Kfr.",
    "wof:placetype":"venue"
},
  "geometry": {"coordinates":[13.454851,52.510311],"type":"Point"}
}