{
  "type": "Feature",
  "properties": {
    "iso:country":"DE",
    "sg:address":"Jandelsbrunner Str. 17",
    "sg:city":"Waldkirchen",
    "sg:phone":"+49 8581/3443",
    "sg:postcode":"94065",
    "sg:province":"Bayern",
    "wof:name":"Manfred Werner Bildhauer",
    "wof:placetype":"venue"
},
  "geometry": {"coordinates":[13.603974,48.728863],"type":"Point"}
}