{
  "type": "Feature",
  "properties": {
    "iso:country":"DE",
    "sg:address":"Wittener Str. 23b",
    "sg:city":"Hattingen",
    "sg:phone":"+49 2324/32505",
    "sg:postcode":"45527",
    "sg:province":"Nordrhein-Westfalen",
    "wof:name":"Armin Marian Ingenieur",
    "wof:placetype":"venue"
},
  "geometry": {"coordinates":[7.2354469299,51.4044837952],"type":"Point"}
}