{
  "type": "Feature",
  "properties": {
    "iso:country":"DE",
    "sg:address":"Kieler Str. 4",
    "sg:city":"Schacht-Audorf",
    "sg:postcode":"24790",
    "sg:province":"Schleswig-Holstein",
    "wof:name":"Profunda Verm\u00f6gensverwaltungs- Gesellschaft Mbh",
    "wof:placetype":"venue"
},
  "geometry": {"coordinates":[9.7151269913,54.3118934631],"type":"Point"}
}