{
  "type": "Feature",
  "properties": {
    "iso:country":"DE",
    "sg:address":"Kronberger Str. 17",
    "sg:city":"Bad Soden",
    "sg:phone":"+49 6196/24061",
    "sg:postcode":"65812",
    "sg:province":"Hessen",
    "wof:name":"Kartoffel Haus",
    "wof:placetype":"venue"
},
  "geometry": {"coordinates":[8.5069656372,50.1472396851],"type":"Point"}
}