{
  "type": "Feature",
  "properties": {
    "iso:country":"DE",
    "sg:address":"Bahnhofstr. 14",
    "sg:city":"Thaleischweiler-Fr\u00f6schn",
    "sg:phone":"+49 6334/1288",
    "sg:postcode":"66987",
    "sg:province":"Rheinland-Pfalz",
    "wof:name":"O. Sattler",
    "wof:placetype":"venue"
},
  "geometry": {"coordinates":[-88.258881,38.642708],"type":"Point"}
}