{
  "type": "Feature",
  "properties": {
    "iso:country":"DE",
    "sg:address":"Odenthaler Str. 6",
    "sg:city":"K\u00fcrten",
    "sg:phone":"+49 2207/4096",
    "sg:postcode":"51515",
    "sg:province":"Nordrhein-Westfalen",
    "wof:name":"Dieter M\u00fcller",
    "wof:placetype":"venue"
},
  "geometry": {"coordinates":[7.2065758705,51.0388755798],"type":"Point"}
}