{
  "type": "Feature",
  "properties": {
    "iso:country":"DE",
    "sg:address":"Johann-Stelling-Str. 27",
    "sg:city":"Gadebusch",
    "sg:phone":"+49 3886/711880",
    "sg:postcode":"19205",
    "sg:province":"Mecklenburg-Vorpommern",
    "wof:name":"Blumenladen Gebr. Liebs",
    "wof:placetype":"venue"
},
  "geometry": {"coordinates":[11.110984,53.700588],"type":"Point"}
}