{
  "type": "Feature",
  "properties": {
    "iso:country":"DE",
    "sg:address":"Tiefenbachstr. 7",
    "sg:city":"Marktschellenberg",
    "sg:phone":"+49 8650/585",
    "sg:postcode":"83487",
    "sg:province":"Bayern",
    "wof:name":"Karl Fr\u00f6hlich Ohg",
    "wof:placetype":"venue"
},
  "geometry": {"coordinates":[13.048393,47.692745],"type":"Point"}
}