{
  "type": "Feature",
  "properties": {
    "iso:country":"DE",
    "sg:address":"Neuburger Str. 3",
    "sg:city":"Karlskron",
    "sg:phone":"+49 8454/3361",
    "sg:postcode":"85123",
    "sg:province":"Bayern",
    "wof:name":"Martin Heckner",
    "wof:placetype":"venue"
},
  "geometry": {"coordinates":[11.379116,48.662582],"type":"Point"}
}