{
  "type": "Feature",
  "properties": {
    "iso:country":"DE",
    "sg:address":"Beinestr. 11-13",
    "sg:city":"B\u00fcrstadt",
    "sg:phone":"+49 6206/6114",
    "sg:postcode":"68642",
    "sg:province":"Hessen",
    "wof:name":"Herbert Bauer",
    "wof:placetype":"venue"
},
  "geometry": {"coordinates":[8.4599332809,49.6413154602],"type":"Point"}
}