{
  "type": "Feature",
  "properties": {
    "iso:country":"DE",
    "sg:address":"Burgstr. 36",
    "sg:city":"Lingen",
    "sg:phone":"+49 591/4488",
    "sg:postcode":"49808",
    "sg:province":"Niedersachsen",
    "wof:name":"Klaas Immobilien Gmbh",
    "wof:placetype":"venue"
},
  "geometry": {"coordinates":[7.3213157654,52.5230484009],"type":"Point"}
}