{
  "type": "Feature",
  "properties": {
    "iso:country":"DE",
    "sg:address":"Luisenstr. 36",
    "sg:city":"Baden-Baden",
    "sg:phone":"+49 7221/392139",
    "sg:postcode":"76530",
    "sg:province":"Baden-W\u00fcrttemberg",
    "wof:name":"M. Ott",
    "wof:placetype":"venue"
},
  "geometry": {"coordinates":[8.2371,48.764347],"type":"Point"}
}