{
  "type": "Feature",
  "properties": {
    "iso:country":"DE",
    "sg:address":"August-Bebel-Str. 3",
    "sg:city":"Ronneburg",
    "sg:phone":"+49 36602/34324",
    "sg:postcode":"07580",
    "sg:province":"Th\u00fcringen",
    "wof:name":"J. Krieger",
    "wof:placetype":"venue"
},
  "geometry": {"coordinates":[12.180504,50.863522],"type":"Point"}
}