{
  "type": "Feature",
  "properties": {
    "iso:country":"DE",
    "sg:address":"Am Bahnhof 21",
    "sg:city":"Freyung",
    "sg:phone":"+49 8551/96230",
    "sg:postcode":"94078",
    "sg:province":"Bayern",
    "wof:name":"Technowelt Lindb\u00fcchl Gmbh & Co. Kg",
    "wof:placetype":"venue"
},
  "geometry": {"coordinates":[13.5506715775,48.8001441956],"type":"Point"}
}