{
  "type": "Feature",
  "properties": {
    "iso:country":"DE",
    "sg:address":"Walkm\u00fchlenweg 5",
    "sg:city":"Pirna",
    "sg:phone":"+49 3501/784947",
    "sg:postcode":"01796",
    "sg:province":"Sachsen",
    "wof:name":"Kiosk Geibeltbad",
    "wof:placetype":"venue"
},
  "geometry": {"coordinates":[13.9407892227,50.9473075867],"type":"Point"}
}