{
  "type": "Feature",
  "properties": {
    "iso:country":"DE",
    "sg:address":"Eiskeweg",
    "sg:city":"Emden",
    "sg:phone":"+49 4921/56529",
    "sg:postcode":"26725",
    "sg:province":"Niedersachsen",
    "wof:name":"Otto Goeman",
    "wof:placetype":"venue"
},
  "geometry": {"coordinates":[7.266615,53.355427],"type":"Point"}
}