{
  "type": "Feature",
  "properties": {
    "iso:country":"DE",
    "sg:address":"Alsterdorfer Str. 570",
    "sg:city":"Hamburg",
    "sg:postcode":"22337",
    "sg:province":"Hamburg",
    "wof:name":"Edv-beratung Seehase Gmbh",
    "wof:placetype":"venue"
},
  "geometry": {"coordinates":[10.033241,53.619835],"type":"Point"}
}