{
  "type": "Feature",
  "properties": {
    "iso:country":"DE",
    "sg:address":"Erkelenzer Str. 46",
    "sg:city":"Wegberg",
    "sg:phone":"+49 2434/4125",
    "sg:postcode":"41844",
    "sg:province":"Nordrhein-Westfalen",
    "wof:name":"Wilhelm Langerbeins",
    "wof:placetype":"venue"
},
  "geometry": {"coordinates":[6.286757,51.127029],"type":"Point"}
}