{
  "type": "Feature",
  "properties": {
    "iso:country":"DE",
    "sg:address":"Steinbr\u00fcckstr. 1",
    "sg:city":"Hoyerswerda",
    "sg:postcode":"02977",
    "sg:province":"Sachsen",
    "wof:name":"G. Schulze",
    "wof:placetype":"venue"
},
  "geometry": {"coordinates":[14.2349767685,51.4361152649],"type":"Point"}
}