{
  "type": "Feature",
  "properties": {
    "iso:country":"DE",
    "sg:address":"Eckerngarten 18",
    "sg:city":"L\u00fcbbecke",
    "sg:phone":"+49 5741/5595",
    "sg:postcode":"32312",
    "sg:province":"Nordrhein-Westfalen",
    "wof:name":"Alfons Ramroth Elektroinstallation",
    "wof:placetype":"venue"
},
  "geometry": {"coordinates":[8.615351,52.310371],"type":"Point"}
}