{
  "type": "Feature",
  "properties": {
    "iso:country":"DE",
    "sg:address":"Hans-Watzlik-Str. 7",
    "sg:city":"Maxh\u00fctte-Haidhof",
    "sg:phone":"+49 9471/4691",
    "sg:postcode":"93142",
    "sg:province":"Bayern",
    "wof:name":"Johann Und Ingrid Wenzlick",
    "wof:placetype":"venue"
},
  "geometry": {"coordinates":[12.0755853653,49.1823043823],"type":"Point"}
}