{
  "type": "Feature",
  "properties": {
    "iso:country":"DE",
    "sg:address":"Schwaaner Str. 32a",
    "sg:city":"G\u00fcstrow",
    "sg:phone":"+49 3843/211035",
    "sg:postcode":"18273",
    "sg:province":"Mecklenburg-Vorpommern",
    "wof:name":"Ulrich Schultz",
    "wof:placetype":"venue"
},
  "geometry": {"coordinates":[12.1722011566,53.8087310791],"type":"Point"}
}