{
  "type": "Feature",
  "properties": {
    "iso:country":"DE",
    "sg:address":"Schloenbachstr. 7",
    "sg:city":"Salzgitter",
    "sg:phone":"+49 5341/31314",
    "sg:postcode":"38259",
    "sg:province":"Niedersachsen",
    "wof:name":"Barbara Fischer",
    "wof:placetype":"venue"
},
  "geometry": {"coordinates":[10.3772830963,52.0407104492],"type":"Point"}
}