{
  "type": "Feature",
  "properties": {
    "iso:country":"DE",
    "sg:address":"Sch\u00f6nauer Friede 77",
    "sg:city":"Aachen",
    "sg:phone":"+49 241/174510",
    "sg:postcode":"52072",
    "sg:province":"Nordrhein-Westfalen",
    "wof:name":"Blitzschutzsachverst\u00e4ndiger Kopecky",
    "wof:placetype":"venue"
},
  "geometry": {"coordinates":[6.0637850761,50.8086509705],"type":"Point"}
}