{
  "type": "Feature",
  "properties": {
    "iso:country":"DE",
    "sg:address":"Rotewartestr. 9a",
    "sg:city":"Duderstadt",
    "sg:phone":"+49 5527/6518",
    "sg:postcode":"37115",
    "sg:province":"Niedersachsen",
    "wof:name":"Theodor Oeben Rechtsanwalt",
    "wof:placetype":"venue"
},
  "geometry": {"coordinates":[10.2695531845,51.5139503479],"type":"Point"}
}