{
  "type": "Feature",
  "properties": {
    "iso:country":"DE",
    "sg:address":"Bahnhofstr 21",
    "sg:city":"Sch\u00f6naich",
    "sg:phone":"+49 7031/410940",
    "sg:postcode":"71101",
    "sg:province":"Baden-W\u00fcrttemberg",
    "wof:name":"Gries & Arrey-garcia Werbeagentur Gmbh",
    "wof:placetype":"venue"
},
  "geometry": {"coordinates":[9.059122,48.662006],"type":"Point"}
}