{
  "type": "Feature",
  "properties": {
    "iso:country":"DE",
    "sg:address":"Panoramastr. 2",
    "sg:city":"Nordheim",
    "sg:postcode":"74226",
    "sg:province":"Baden-W\u00fcrttemberg",
    "wof:name":"Ipe Immobilien Partner Engagement Gmbh",
    "wof:placetype":"venue"
},
  "geometry": {"coordinates":[9.1416254044,49.1088829041],"type":"Point"}
}