{
  "type": "Feature",
  "properties": {
    "iso:country":"DE",
    "sg:address":"Tullastr. 9",
    "sg:city":"Teningen",
    "sg:phone":"+49 7641/42171",
    "sg:postcode":"79331",
    "sg:province":"Baden-W\u00fcrttemberg",
    "wof:name":"B. B\u00fchrer Bildhauer",
    "wof:placetype":"venue"
},
  "geometry": {"coordinates":[7.802058,48.131172],"type":"Point"}
}