{
  "type": "Feature",
  "properties": {
    "iso:country":"DE",
    "sg:address":"Paul-Ehrlich-Str. 51",
    "sg:city":"Frankfurt",
    "sg:postcode":"60596",
    "sg:province":"Hessen",
    "wof:name":"Omnid Gmbh",
    "wof:placetype":"venue"
},
  "geometry": {"coordinates":[8.6653690338,50.0946388245],"type":"Point"}
}