{
  "type": "Feature",
  "properties": {
    "iso:country":"DE",
    "sg:address":"Mittelstr. 20",
    "sg:city":"Barntrup",
    "sg:phone":"+49 5263/94740",
    "sg:postcode":"32683",
    "sg:province":"Nordrhein-Westfalen",
    "wof:name":"Fritz T\u00f6neb\u00f6n E. K.",
    "wof:placetype":"venue"
},
  "geometry": {"coordinates":[9.1137123108,51.9908180237],"type":"Point"}
}