{
  "type": "Feature",
  "properties": {
    "iso:country":"DE",
    "sg:address":"Iglersreuth 7",
    "sg:city":"B\u00e4rnau",
    "sg:postcode":"95671",
    "sg:province":"Bayern",
    "wof:name":"Australien Pub Momo",
    "wof:placetype":"venue"
},
  "geometry": {"coordinates":[12.3707265854,49.8145065308],"type":"Point"}
}