{
  "type": "Feature",
  "properties": {
    "iso:country":"DE",
    "sg:address":"Wermingser Str. 5",
    "sg:city":"Iserlohn",
    "sg:phone":"+49 2371/14866",
    "sg:postcode":"58636",
    "sg:province":"Nordrhein-Westfalen",
    "wof:name":"Leos Jeans",
    "wof:placetype":"venue"
},
  "geometry": {"coordinates":[7.698479,51.3745],"type":"Point"}
}