{
  "type": "Feature",
  "properties": {
    "iso:country":"DE",
    "sg:address":"Neugasse 5",
    "sg:city":"Neustadt",
    "sg:phone":"+49 6321/68339",
    "sg:postcode":"67435",
    "sg:province":"Rheinland-Pfalz",
    "wof:name":"Werner Knobloch",
    "wof:placetype":"venue"
},
  "geometry": {"coordinates":[8.167719841,49.3707618713],"type":"Point"}
}