{
  "type": "Feature",
  "properties": {
    "iso:country":"DE",
    "sg:address":"Hardtstr. 110",
    "sg:city":"Heidelberg",
    "sg:phone":"+49 6221/72618",
    "sg:postcode":"69124",
    "sg:province":"Baden-W\u00fcrttemberg",
    "wof:name":"Agm-immobilien- Handels- Gmbh",
    "wof:placetype":"venue"
},
  "geometry": {"coordinates":[8.6731967926,49.3692550659],"type":"Point"}
}