{
  "type": "Feature",
  "properties": {
    "iso:country":"DE",
    "sg:address":"S\u00f6mmerdaer Weg 2",
    "sg:city":"Orlishausen",
    "sg:phone":"+49 3634/620141",
    "sg:postcode":"99610",
    "sg:province":"Th\u00fcringen",
    "wof:name":"Ipe Immovables Project Engineering Gmbh",
    "wof:placetype":"venue"
},
  "geometry": {"coordinates":[11.190936,51.155266],"type":"Point"}
}