{
  "type": "Feature",
  "properties": {
    "iso:country":"DE",
    "sg:address":"Andreas-Limmer-Str. 34",
    "sg:city":"Kronach",
    "sg:phone":"+49 9261/3174",
    "sg:postcode":"96317",
    "sg:province":"Bayern",
    "wof:name":"Dingsda-pub",
    "wof:placetype":"venue"
},
  "geometry": {"coordinates":[11.3293600082,50.2402000427],"type":"Point"}
}