{
  "type": "Feature",
  "properties": {
    "iso:country":"DE",
    "sg:address":"Hauptstr. 64",
    "sg:city":"E\u00dfweiler",
    "sg:phone":"+49 6304/284",
    "sg:postcode":"67754",
    "sg:province":"Rheinland-Pfalz",
    "wof:name":"Reinhold Hollstein",
    "wof:placetype":"venue"
},
  "geometry": {"coordinates":[7.565808773,49.5578384399],"type":"Point"}
}