{
  "type": "Feature",
  "properties": {
    "iso:country":"DE",
    "sg:address":"Hauptstr. 50",
    "sg:city":"Adelmannsfelden",
    "sg:phone":"+49 7963/8374",
    "sg:postcode":"73486",
    "sg:province":"Baden-W\u00fcrttemberg",
    "wof:name":"Nanes Modeladen",
    "wof:placetype":"venue"
},
  "geometry": {"coordinates":[10.006919,48.954708],"type":"Point"}
}