{
  "type": "Feature",
  "properties": {
    "iso:country":"DE",
    "sg:address":"Brunnenweg 2",
    "sg:city":"Morsbach",
    "sg:phone":"+49 2294/7274",
    "sg:postcode":"51597",
    "sg:province":"Nordrhein-Westfalen",
    "wof:name":"Reinhold Schaefers",
    "wof:placetype":"venue"
},
  "geometry": {"coordinates":[7.653439,50.843777],"type":"Point"}
}