{
  "type": "Feature",
  "properties": {
    "iso:country":"DE",
    "sg:address":"Eichenstr. 68",
    "sg:city":"Wittlich",
    "sg:phone":"+49 6571/6122",
    "sg:postcode":"54516",
    "sg:province":"Rheinland-Pfalz",
    "wof:name":"Hans Thullen",
    "wof:placetype":"venue"
},
  "geometry": {"coordinates":[6.9508900642,50.0009880066],"type":"Point"}
}