{
  "type": "Feature",
  "properties": {
    "iso:country":"DE",
    "sg:address":"Friedrichstr. 23",
    "sg:city":"Zaisenhausen",
    "sg:postcode":"75059",
    "sg:province":"Baden-W\u00fcrttemberg",
    "wof:name":"Medi-data-service Gmbh",
    "wof:placetype":"venue"
},
  "geometry": {"coordinates":[8.8170099258,49.1113815308],"type":"Point"}
}