{
  "type": "Feature",
  "properties": {
    "iso:country":"DE",
    "sg:address":"Grindelallee 37",
    "sg:city":"Hamburg",
    "sg:phone":"+49 40/440525",
    "sg:postcode":"20146",
    "sg:province":"Hamburg",
    "wof:name":"B\u00e4der-schr\u00f6der Inh. J\u00f6rg Schr\u00f6der",
    "wof:placetype":"venue"
},
  "geometry": {"coordinates":[9.981941,53.566151],"type":"Point"}
}