{
  "type": "Feature",
  "properties": {
    "iso:country":"DE",
    "sg:address":"Waldstr. 13",
    "sg:city":"H\u00f6chst",
    "sg:phone":"+49 6163/3872",
    "sg:postcode":"64739",
    "sg:province":"Hessen",
    "wof:name":"O. G\u00f6ttmann",
    "wof:placetype":"venue"
},
  "geometry": {"coordinates":[8.9993753433,49.797077179],"type":"Point"}
}