{
  "type": "Feature",
  "properties": {
    "iso:country":"DE",
    "sg:address":"M\u00fchlenstr. 9",
    "sg:city":"L\u00fcdinghausen",
    "sg:phone":"+49 2591/4470",
    "sg:postcode":"59348",
    "sg:province":"Nordrhein-Westfalen",
    "wof:name":"Bernhard Weischer",
    "wof:placetype":"venue"
},
  "geometry": {"coordinates":[7.445259,51.770424],"type":"Point"}
}