{
  "type": "Feature",
  "properties": {
    "iso:country":"DE",
    "sg:address":"Sch\u00f6nhagener Ring 10",
    "sg:city":"Extertal",
    "sg:phone":"+49 5262/727",
    "sg:postcode":"32699",
    "sg:province":"Nordrhein-Westfalen",
    "wof:name":"Helmut Luthe",
    "wof:placetype":"venue"
},
  "geometry": {"coordinates":[9.157906,52.078697],"type":"Point"}
}