{
  "type": "Feature",
  "properties": {
    "iso:country":"DE",
    "sg:address":"Hildesheimerstr.",
    "sg:city":"Hannover",
    "sg:phone":"+49 511/8379394",
    "sg:postcode":"30519",
    "sg:province":"Niedersachsen",
    "wof:name":"Cartsens Assekuranz Und Immobilienvermittlung",
    "wof:placetype":"venue"
},
  "geometry": {"coordinates":[9.76338,52.343876],"type":"Point"}
}