{
  "type": "Feature",
  "properties": {
    "iso:country":"DE",
    "sg:address":"Ludwig-Wucherer-Str. 69",
    "sg:city":"Halle",
    "sg:phone":"+49 345/225160",
    "sg:postcode":"06108",
    "sg:province":"Sachsen-Anhalt",
    "wof:name":"Hermann Josef Heeck Rechtsanwalt",
    "wof:placetype":"venue"
},
  "geometry": {"coordinates":[11.9728288651,51.4923477173],"type":"Point"}
}