{
  "type": "Feature",
  "properties": {
    "iso:country":"DE",
    "sg:address":"Hamburger Str. 35",
    "sg:city":"Bargteheide",
    "sg:phone":"+49 4532/501590",
    "sg:postcode":"22941",
    "sg:province":"Schleswig-Holstein",
    "wof:name":"Bp Tankstelle",
    "wof:placetype":"venue"
},
  "geometry": {"coordinates":[10.2547836304,53.7238349915],"type":"Point"}
}