{
  "type": "Feature",
  "properties": {
    "iso:country":"DE",
    "sg:address":"Bahnhofstr. 16",
    "sg:city":"Nabburg",
    "sg:phone":"+49 9433/1388",
    "sg:postcode":"92507",
    "sg:province":"Bayern",
    "wof:name":"Sozialberatungsstelle Kreis-caritas-verband",
    "wof:placetype":"venue"
},
  "geometry": {"coordinates":[12.179421,49.448086],"type":"Point"}
}