{
  "type": "Feature",
  "properties": {
    "iso:country":"DE",
    "sg:address":"Werkstr. 19",
    "sg:city":"Eisenh\u00fcttenstadt",
    "sg:phone":"+49 3364/413646",
    "sg:postcode":"15890",
    "sg:province":"Brandenburg",
    "wof:name":"Mvs Miet Vertrieb Service Eko Stahl Ag",
    "wof:placetype":"venue"
},
  "geometry": {"coordinates":[14.634043,52.158504],"type":"Point"}
}