{
  "type": "Feature",
  "properties": {
    "iso:country":"DE",
    "sg:address":"Achterstr. 12",
    "sg:city":"Uelzen",
    "sg:phone":"+49 581/5127",
    "sg:postcode":"29525",
    "sg:province":"Niedersachsen",
    "wof:name":"Erich Siems Orthop\u00e4die-schuhmachermeister",
    "wof:placetype":"venue"
},
  "geometry": {"coordinates":[10.5597429276,52.9663658142],"type":"Point"}
}