{
  "type": "Feature",
  "properties": {
    "iso:country":"DE",
    "sg:address":"Gewerbegebiet 1",
    "sg:city":"Thyrnau",
    "sg:phone":"+49 8501/90080",
    "sg:postcode":"94136",
    "sg:province":"Bayern",
    "wof:name":"W. Gell Gmbh & Co. Kg",
    "wof:placetype":"venue"
},
  "geometry": {"coordinates":[13.5371618271,48.614654541],"type":"Point"}
}