{
  "type": "Feature",
  "properties": {
    "iso:country":"DE",
    "sg:address":"Schanzenweg 65",
    "sg:city":"Bad Wildungen",
    "sg:phone":"+49 5621/70180",
    "sg:postcode":"34537",
    "sg:province":"Hessen",
    "wof:name":"Berghotel Garni",
    "wof:placetype":"venue"
},
  "geometry": {"coordinates":[9.1104927063,51.1204986572],"type":"Point"}
}