{
  "type": "Feature",
  "properties": {
    "iso:country":"DE",
    "sg:address":"Tennenweg 2",
    "sg:city":"Stephanskirchen",
    "sg:phone":"+49 8036/568",
    "sg:postcode":"83071",
    "sg:province":"Bayern",
    "wof:name":"Ludwig Weber",
    "wof:placetype":"venue"
},
  "geometry": {"coordinates":[12.1864948273,47.855304718],"type":"Point"}
}