{
  "type": "Feature",
  "properties": {
    "iso:country":"DE",
    "sg:address":"Hauptstr. 10",
    "sg:city":"Waffenbrunn",
    "sg:phone":"+49 9971/2594",
    "sg:postcode":"93494",
    "sg:province":"Bayern",
    "wof:name":"Gastst\u00e4tte Otto G\u00f6ttlinger",
    "wof:placetype":"venue"
},
  "geometry": {"coordinates":[12.6652317047,49.2606582642],"type":"Point"}
}