{
  "type": "Feature",
  "properties": {
    "iso:country":"DE",
    "sg:address":"Berliner Str. 87",
    "sg:city":"Oderberg",
    "sg:phone":"+49 33369/207",
    "sg:postcode":"16248",
    "sg:province":"Brandenburg",
    "wof:name":"Kreissparkasse Eberswalde",
    "wof:placetype":"venue"
},
  "geometry": {"coordinates":[14.044001,52.865803],"type":"Point"}
}