{
  "type": "Feature",
  "properties": {
    "iso:country":"DE",
    "sg:address":"Gro\u00dfe Str. 8",
    "sg:city":"Crivitz",
    "sg:phone":"+49 3863/222981",
    "sg:postcode":"19089",
    "sg:province":"Mecklenburg-Vorpommern",
    "wof:name":"Martina Gasau",
    "wof:placetype":"venue"
},
  "geometry": {"coordinates":[11.6508131027,53.5768966675],"type":"Point"}
}