{
  "type": "Feature",
  "properties": {
    "iso:country":"DE",
    "sg:address":"Zur L\u00fctgenheide 5",
    "sg:city":"Warstein",
    "sg:phone":"+49 2902/97420",
    "sg:postcode":"59581",
    "sg:province":"Nordrhein-Westfalen",
    "wof:name":"Strohdeicher Maschinenbau Gmbh",
    "wof:placetype":"venue"
},
  "geometry": {"coordinates":[8.3808393478,51.4594688416],"type":"Point"}
}