{
  "type": "Feature",
  "properties": {
    "iso:country":"DE",
    "sg:address":"Untere Zeilstr. 36",
    "sg:city":"Sachsenheim",
    "sg:phone":"+49 7147/13133",
    "sg:postcode":"74343",
    "sg:province":"Baden-W\u00fcrttemberg",
    "wof:name":"World Race Selection Spezial J. B. J\u00fcrgen Barth Gmbh",
    "wof:placetype":"venue"
},
  "geometry": {"coordinates":[9.08109,48.96608],"type":"Point"}
}