{
  "type": "Feature",
  "properties": {
    "iso:country":"DE",
    "sg:address":"J\u00e4gerstr. 2",
    "sg:city":"Hirrlingen",
    "sg:phone":"+49 7478/391",
    "sg:postcode":"72145",
    "sg:province":"Baden-W\u00fcrttemberg",
    "wof:name":"Rudi Kurz",
    "wof:placetype":"venue"
},
  "geometry": {"coordinates":[8.8918590546,48.4087295532],"type":"Point"}
}