{
  "type": "Feature",
  "properties": {
    "iso:country":"DE",
    "sg:address":"Frankfurter Str. 430",
    "sg:city":"Voerde",
    "sg:phone":"+49 2855/120",
    "sg:postcode":"46562",
    "sg:province":"Nordrhein-Westfalen",
    "wof:name":"Kraftwerk Voerde Steag-rwe Ohg",
    "wof:placetype":"venue"
},
  "geometry": {"coordinates":[6.644742,51.624603],"type":"Point"}
}