{
  "type": "Feature",
  "properties": {
    "iso:country":"DE",
    "sg:address":"Schulstr. 30",
    "sg:city":"Kiel",
    "sg:phone":"+49 431/731925",
    "sg:postcode":"24143",
    "sg:province":"Schleswig-Holstein",
    "wof:name":"Ev. Pfarramt St. Johannes",
    "wof:placetype":"venue"
},
  "geometry": {"coordinates":[10.1448001862,54.3127555847],"type":"Point"}
}