{
  "type": "Feature",
  "properties": {
    "iso:country":"DE",
    "sg:address":"Schillerstr. 43",
    "sg:city":"Erfurt",
    "sg:phone":"+49 361/3460591",
    "sg:postcode":"99096",
    "sg:province":"Th\u00fcringen",
    "wof:name":"St. Elisabeth-apotheke Bernhard Meyer",
    "wof:placetype":"venue"
},
  "geometry": {"coordinates":[11.024685,50.966297],"type":"Point"}
}