{
  "type": "Feature",
  "properties": {
    "iso:country":"DE",
    "sg:address":"Wilhelminenstr. 33",
    "sg:city":"Wiesbaden",
    "sg:phone":"+49 611/522088",
    "sg:postcode":"65193",
    "sg:province":"Hessen",
    "wof:name":"Arcon Wohn - U. Gewerbebau Gmbh",
    "wof:placetype":"venue"
},
  "geometry": {"coordinates":[8.2283611298,50.0936508179],"type":"Point"}
}