{
  "type": "Feature",
  "properties": {
    "iso:country":"DE",
    "sg:address":"Briloner Strasse 8",
    "sg:city":"R\u00fcthen",
    "sg:phone":"+49 2952/1212",
    "sg:postcode":"59602",
    "sg:province":"Nordrhein-Westfalen",
    "wof:name":"R\u00fcthener Nutzfahrzeugs & Ersatzteilvertriebs Gmbh",
    "wof:placetype":"venue"
},
  "geometry": {"coordinates":[8.452685,51.487591],"type":"Point"}
}