{
  "type": "Feature",
  "properties": {
    "iso:country":"DE",
    "sg:address":"Veer\u00dfer Str. 16",
    "sg:city":"Uelzen",
    "sg:phone":"+49 581/74938",
    "sg:postcode":"29525",
    "sg:province":"Niedersachsen",
    "wof:name":"Fielmann Ag",
    "wof:placetype":"venue"
},
  "geometry": {"coordinates":[10.5595121384,52.9642181396],"type":"Point"}
}