{
  "type": "Feature",
  "properties": {
    "iso:country":"DE",
    "sg:address":"Im Altseiterstal 330",
    "sg:city":"Neunkirchen",
    "sg:phone":"+49 6821/87087",
    "sg:postcode":"66538",
    "sg:province":"Saarland",
    "wof:name":"Michael Linnebacher Ingenieur",
    "wof:placetype":"venue"
},
  "geometry": {"coordinates":[7.1713590622,49.3296928406],"type":"Point"}
}