{
  "type": "Feature",
  "properties": {
    "iso:country":"DE",
    "sg:address":"Talstr. 38",
    "sg:city":"Malsch",
    "sg:phone":"+49 7246/941041",
    "sg:postcode":"76316",
    "sg:province":"Baden-W\u00fcrttemberg",
    "wof:name":"Schr\u00f6der & Schnepf Gmbh",
    "wof:placetype":"venue"
},
  "geometry": {"coordinates":[8.3311834335,48.859916687],"type":"Point"}
}