{
  "type": "Feature",
  "properties": {
    "iso:country":"DE",
    "sg:address":"G\u00e4nsemarkt 21",
    "sg:city":"Essen",
    "sg:phone":"+49 201/221348",
    "sg:postcode":"45127",
    "sg:province":"Nordrhein-Westfalen",
    "wof:name":"Pecunia Finanzierungs- Vermittlungs Und Dienst-",
    "wof:placetype":"venue"
},
  "geometry": {"coordinates":[7.009565,51.45787],"type":"Point"}
}