{
  "type": "Feature",
  "properties": {
    "iso:country":"DE",
    "sg:address":"Ebenhauser Str. 9",
    "sg:city":"Icking",
    "sg:phone":"+49 8178/4705",
    "sg:postcode":"82057",
    "sg:province":"Bayern",
    "wof:name":"Christine Oliv",
    "wof:placetype":"venue"
},
  "geometry": {"coordinates":[11.4358797073,47.9667472839],"type":"Point"}
}