{
  "type": "Feature",
  "properties": {
    "iso:country":"DE",
    "sg:address":"Pickerei 24",
    "sg:city":"Zetel",
    "sg:phone":"+49 4452/918359",
    "sg:postcode":"26340",
    "sg:province":"Niedersachsen",
    "wof:name":"Heinz Sander",
    "wof:placetype":"venue"
},
  "geometry": {"coordinates":[7.938357,53.406918],"type":"Point"}
}