{
  "type": "Feature",
  "properties": {
    "iso:country":"DE",
    "sg:address":"Kurze Str. 7",
    "sg:city":"Bad Oeynhausen",
    "sg:phone":"+49 5734/3888",
    "sg:postcode":"32549",
    "sg:province":"Nordrhein-Westfalen",
    "wof:name":"Maria Stelze Versicherungsvertreter",
    "wof:placetype":"venue"
},
  "geometry": {"coordinates":[8.8295755386,52.226234436],"type":"Point"}
}