{
  "type": "Feature",
  "properties": {
    "iso:country":"DE",
    "sg:address":"Bernauer Str. 6",
    "sg:city":"M\u00fcnchen",
    "sg:phone":"+49 89/683993",
    "sg:postcode":"81669",
    "sg:province":"Bayern",
    "wof:name":"Bio Marktgemeinschaft Eg",
    "wof:placetype":"venue"
},
  "geometry": {"coordinates":[11.6090936661,48.1136322021],"type":"Point"}
}