{
  "type": "Feature",
  "properties": {
    "iso:country":"DE",
    "sg:address":"Thomas-Mann-Str. 72 a",
    "sg:city":"Stuttgart",
    "sg:phone":"+49 711/852821",
    "sg:postcode":"70469",
    "sg:province":"Baden-W\u00fcrttemberg",
    "wof:name":"Heinz Holzenbecher",
    "wof:placetype":"venue"
},
  "geometry": {"coordinates":[9.1400699615,48.8053016663],"type":"Point"}
}