{
  "type": "Feature",
  "properties": {
    "iso:country":"DE",
    "sg:address":"Ihnestr. 57",
    "sg:city":"Berlin",
    "sg:phone":"+49 30/8324086",
    "sg:postcode":"14195",
    "sg:province":"Berlin",
    "wof:name":"Thomas K\u00f6hler Architekt",
    "wof:placetype":"venue"
},
  "geometry": {"coordinates":[13.274662,52.445999],"type":"Point"}
}