{
  "type": "Feature",
  "properties": {
    "iso:country":"DE",
    "sg:address":"S\u00fcdstr. 44",
    "sg:city":"Barntrup",
    "sg:phone":"+49 5263/94690",
    "sg:postcode":"32683",
    "sg:province":"Nordrhein-Westfalen",
    "wof:name":"Bfd Beton-fertig-decken Gmbh",
    "wof:placetype":"venue"
},
  "geometry": {"coordinates":[9.1342411041,51.9854774475],"type":"Point"}
}