{
  "type": "Feature",
  "properties": {
    "iso:country":"DE",
    "sg:address":"Fischerweg 4",
    "sg:city":"Peiting",
    "sg:phone":"+49 8861/6437",
    "sg:postcode":"86971",
    "sg:province":"Bayern",
    "wof:name":"M. R\u00f6s\u00dfle",
    "wof:placetype":"venue"
},
  "geometry": {"coordinates":[10.934763,47.790012],"type":"Point"}
}