{
  "type": "Feature",
  "properties": {
    "iso:country":"DE",
    "sg:address":"Marktplatz 2",
    "sg:city":"Neubeuern",
    "sg:phone":"+49 8035/4892",
    "sg:postcode":"83115",
    "sg:province":"Bayern",
    "wof:name":"O. Grabl",
    "wof:placetype":"venue"
},
  "geometry": {"coordinates":[12.1391601562,47.7740440369],"type":"Point"}
}