{
  "type": "Feature",
  "properties": {
    "iso:country":"DE",
    "sg:address":"Kreuzstr. 60",
    "sg:city":"Braunschweig",
    "sg:phone":"+49 531/56066",
    "sg:postcode":"38118",
    "sg:province":"Niedersachsen",
    "wof:name":"Gerhard Scholz Ingenieur",
    "wof:placetype":"venue"
},
  "geometry": {"coordinates":[10.488574028,52.2616271973],"type":"Point"}
}