{
  "type": "Feature",
  "properties": {
    "iso:country":"DE",
    "sg:address":"Mannheimer Str. 55",
    "sg:city":"Bad D\u00fcrkheim",
    "sg:phone":"+49 6322/95200",
    "sg:postcode":"67098",
    "sg:province":"Rheinland-Pfalz",
    "wof:name":"Ahg Autohandels- Beteiligungs Gmbh",
    "wof:placetype":"venue"
},
  "geometry": {"coordinates":[8.186298,49.463493],"type":"Point"}
}