{
  "type": "Feature",
  "properties": {
    "iso:country":"DE",
    "sg:address":"Roseller Str. 30",
    "sg:city":"Grevenbroich",
    "sg:phone":"+49 2182/884220",
    "sg:postcode":"41516",
    "sg:province":"Nordrhein-Westfalen",
    "wof:name":"Marx & Junck Gmbh",
    "wof:placetype":"venue"
},
  "geometry": {"coordinates":[6.6917,51.12151],"type":"Point"}
}