{
  "type": "Feature",
  "properties": {
    "iso:country":"DE",
    "sg:address":"Cottbuser Str. 4",
    "sg:city":"Neu Zauche",
    "sg:phone":"+49 35475/417",
    "sg:postcode":"15913",
    "sg:province":"Brandenburg",
    "wof:name":"M\u00f6belwerkstatt Gmbh",
    "wof:placetype":"venue"
},
  "geometry": {"coordinates":[14.096945,51.921383],"type":"Point"}
}