{
  "type": "Feature",
  "properties": {
    "iso:country":"DE",
    "sg:address":"Agnes-Bernauer-Str 19",
    "sg:city":"M\u00fcnchen",
    "sg:phone":"+49 89/57966201",
    "sg:postcode":"80687",
    "sg:province":"Bayern",
    "wof:name":"Bike Sport",
    "wof:placetype":"venue"
},
  "geometry": {"coordinates":[11.515349,48.13884],"type":"Point"}
}