{
  "type": "Feature",
  "properties": {
    "iso:country":"DE",
    "sg:address":"Schauinslandstrasse 22",
    "sg:city":"Karlsruhe",
    "sg:phone":"+49 721/9883432",
    "sg:postcode":"76199",
    "sg:province":"Baden-W\u00fcrttemberg",
    "wof:name":"Studio-22",
    "wof:placetype":"venue"
},
  "geometry": {"coordinates":[8.3946399689,48.9828605652],"type":"Point"}
}