{
  "type": "Feature",
  "properties": {
    "iso:country":"DE",
    "sg:address":"Friedrichstr. 29",
    "sg:city":"Herbolzheim",
    "sg:phone":"+49 7643/6590",
    "sg:postcode":"79336",
    "sg:province":"Baden-W\u00fcrttemberg",
    "wof:name":"Alfons Geppert Bildhauer",
    "wof:placetype":"venue"
},
  "geometry": {"coordinates":[7.775538,48.219524],"type":"Point"}
}