{
  "type": "Feature",
  "properties": {
    "iso:country":"DE",
    "sg:address":"An der Hauptstr. 22",
    "sg:city":"Schleusingen",
    "sg:phone":"+49 36841/47450",
    "sg:postcode":"98553",
    "sg:province":"Th\u00fcringen",
    "wof:name":"H. Ehrsam",
    "wof:placetype":"venue"
},
  "geometry": {"coordinates":[10.700829,50.511681],"type":"Point"}
}