{
  "type": "Feature",
  "properties": {
    "iso:country":"DE",
    "sg:address":"Innocentiastr 46",
    "sg:city":"Hamburg",
    "sg:phone":"+49 40/418934",
    "sg:postcode":"20144",
    "sg:province":"Hamburg",
    "wof:name":"Cimline",
    "wof:placetype":"venue"
},
  "geometry": {"coordinates":[9.983493,53.579197],"type":"Point"}
}