{
  "type": "Feature",
  "properties": {
    "iso:country":"DE",
    "sg:address":"Wasserweg 6",
    "sg:city":"Painten",
    "sg:phone":"+49 9499/635",
    "sg:postcode":"93351",
    "sg:province":"Bayern",
    "wof:name":"Karl-heinz Raum Steinmetz",
    "wof:placetype":"venue"
},
  "geometry": {"coordinates":[11.8131837845,48.9965705872],"type":"Point"}
}