{
  "type": "Feature",
  "properties": {
    "iso:country":"DE",
    "sg:address":"Brunnenstr. 3",
    "sg:city":"Rieden",
    "sg:phone":"+49 8362/2093",
    "sg:postcode":"87669",
    "sg:province":"Bayern",
    "wof:name":"Franz Hilpert",
    "wof:placetype":"venue"
},
  "geometry": {"coordinates":[10.713644,47.616409],"type":"Point"}
}