{
  "type": "Feature",
  "properties": {
    "iso:country":"DE",
    "sg:address":"Karl-Marx-Str. 1",
    "sg:city":"Dortmund",
    "sg:phone":"+49 231/524400",
    "sg:postcode":"44141",
    "sg:province":"Nordrhein-Westfalen",
    "wof:name":"J\u00fcrgen Hiddemann",
    "wof:placetype":"venue"
},
  "geometry": {"coordinates":[7.4781928062,51.5059814453],"type":"Point"}
}