{
  "type": "Feature",
  "properties": {
    "iso:country":"DE",
    "sg:address":"Am Kulturheim 11",
    "sg:city":"L\u00f6bau",
    "sg:phone":"+49 3585/468317",
    "sg:postcode":"02708",
    "sg:province":"Sachsen",
    "wof:name":"Estrich P\u00f6schmann Baugesch\u00e4ft",
    "wof:placetype":"venue"
},
  "geometry": {"coordinates":[14.68521,51.077778],"type":"Point"}
}