{
  "type": "Feature",
  "properties": {
    "iso:country":"DE",
    "sg:address":"L\u00fctge Heidestr. 79-81",
    "sg:city":"Dortmund",
    "sg:phone":"+49 231/9851100",
    "sg:postcode":"44147",
    "sg:province":"Nordrhein-Westfalen",
    "wof:name":"Windg\u00e4tter & Sohn Gmbh",
    "wof:placetype":"venue"
},
  "geometry": {"coordinates":[7.4507751465,51.5457954407],"type":"Point"}
}