{
  "type": "Feature",
  "properties": {
    "iso:country":"DE",
    "sg:address":"Herzog-Georg-Str. 10",
    "sg:city":"Bad Liebenstein",
    "sg:postcode":"36448",
    "sg:province":"Th\u00fcringen",
    "wof:name":"Eiscafe T. Wolf",
    "wof:placetype":"venue"
},
  "geometry": {"coordinates":[10.349827,50.815487],"type":"Point"}
}