{
  "type": "Feature",
  "properties": {
    "iso:country":"DE",
    "sg:address":"Lippertor 2",
    "sg:city":"Lippstadt",
    "sg:phone":"+49 2941/57435",
    "sg:postcode":"59555",
    "sg:province":"Nordrhein-Westfalen",
    "wof:name":"M.-l. Herting-korus",
    "wof:placetype":"venue"
},
  "geometry": {"coordinates":[8.346427,51.67765],"type":"Point"}
}