{
  "type": "Feature",
  "properties": {
    "iso:country":"DE",
    "sg:address":"Zum J\u00e4gerberg 2",
    "sg:city":"Hagen",
    "sg:phone":"+49 5401/9332",
    "sg:postcode":"49170",
    "sg:province":"Niedersachsen",
    "wof:name":"C. Stock",
    "wof:placetype":"venue"
},
  "geometry": {"coordinates":[7.9785652161,52.1976470947],"type":"Point"}
}