{
  "type": "Feature",
  "properties": {
    "iso:country":"DE",
    "sg:address":"Krobitzschstr. 13",
    "sg:city":"Markkleeberg",
    "sg:phone":"+49 341/3380179",
    "sg:postcode":"04416",
    "sg:province":"Sachsen",
    "wof:name":"Roland Wetzig",
    "wof:placetype":"venue"
},
  "geometry": {"coordinates":[12.396616,51.273861],"type":"Point"}
}