{
  "type": "Feature",
  "properties": {
    "iso:country":"DE",
    "sg:address":"L\u00fctzner Str. 2 a",
    "sg:city":"Leipzig",
    "sg:phone":"+49 341/4794445",
    "sg:postcode":"04177",
    "sg:province":"Sachsen",
    "wof:name":"Starke & Partner",
    "wof:placetype":"venue"
},
  "geometry": {"coordinates":[12.339217186,51.3355064392],"type":"Point"}
}