{
  "type": "Feature",
  "properties": {
    "iso:country":"DE",
    "sg:address":"Meierkamp 20",
    "sg:city":"Hohenhameln",
    "sg:phone":"+49 5128/960285",
    "sg:postcode":"31249",
    "sg:province":"Niedersachsen",
    "wof:name":"G\u00fcrol's Grillstube",
    "wof:placetype":"venue"
},
  "geometry": {"coordinates":[10.0740737915,52.2625961304],"type":"Point"}
}