{
  "type": "Feature",
  "properties": {
    "iso:country":"DE",
    "sg:address":"Kardinal-Wendel-Str. 90",
    "sg:city":"Wolfratshausen",
    "sg:postcode":"82515",
    "sg:province":"Bayern",
    "wof:name":"Brumaba Kg",
    "wof:placetype":"venue"
},
  "geometry": {"coordinates":[11.448199,47.899899],"type":"Point"}
}