{
  "type": "Feature",
  "properties": {
    "iso:country":"DE",
    "sg:address":"Weimersheim",
    "sg:city":"Ipsheim",
    "sg:phone":"+49 9846/561",
    "sg:postcode":"91472",
    "sg:province":"Bayern",
    "wof:name":"Winzerstube",
    "wof:placetype":"venue"
},
  "geometry": {"coordinates":[10.5058469772,49.5016059875],"type":"Point"}
}