{
  "type": "Feature",
  "properties": {
    "iso:country":"DE",
    "sg:address":"Dornweg 32",
    "sg:city":"Borstorf",
    "sg:phone":"+49 4543/294",
    "sg:postcode":"23881",
    "sg:province":"Schleswig-Holstein",
    "wof:name":"Hans-heinrich Kr\u00fctzmann",
    "wof:placetype":"venue"
},
  "geometry": {"coordinates":[10.557865,53.614857],"type":"Point"}
}