{
  "type": "Feature",
  "properties": {
    "iso:country":"DE",
    "sg:address":"Bgm-Kirschbaum-Platz 7",
    "sg:city":"Bremerhaven",
    "sg:phone":"+49 471/984600",
    "sg:postcode":"27580",
    "sg:province":"Bremen",
    "wof:name":"Hotel Bahnhof Lehe Gmbh",
    "wof:placetype":"venue"
},
  "geometry": {"coordinates":[8.5986204147,53.5666007996],"type":"Point"}
}