{
  "type": "Feature",
  "properties": {
    "iso:country":"DE",
    "sg:address":"Eichenholzstr. 3",
    "sg:city":"Rosenheim",
    "sg:phone":"+49 8031/69311",
    "sg:postcode":"83026",
    "sg:province":"Bayern",
    "wof:name":"Dr. Med. Christiane Riemer",
    "wof:placetype":"venue"
},
  "geometry": {"coordinates":[12.1327638626,47.8383827209],"type":"Point"}
}