{
  "type": "Feature",
  "properties": {
    "iso:country":"DE",
    "sg:address":"Leitenstr. 11",
    "sg:city":"Aichach",
    "sg:phone":"+49 8251/896141",
    "sg:postcode":"86551",
    "sg:province":"Bayern",
    "wof:name":"Sis Hydro Gmbh",
    "wof:placetype":"venue"
},
  "geometry": {"coordinates":[11.157369,48.432121],"type":"Point"}
}