{
  "type": "Feature",
  "properties": {
    "iso:country":"DE",
    "sg:address":"Grevener Str. 248",
    "sg:city":"M\u00fcnster",
    "sg:phone":"+49 251/22168",
    "sg:postcode":"48159",
    "sg:province":"Nordrhein-Westfalen",
    "wof:name":"Franz Und K. Herbsthoff",
    "wof:placetype":"venue"
},
  "geometry": {"coordinates":[7.611878,51.984711],"type":"Point"}
}