{
  "type": "Feature",
  "properties": {
    "iso:country":"DE",
    "sg:address":"Inckusstr. 11",
    "sg:city":"Frankfurt",
    "sg:phone":"+49 4947/4594440",
    "sg:postcode":"60320",
    "sg:province":"Hessen",
    "wof:name":"Forma Baumgarten Kg",
    "wof:placetype":"venue"
},
  "geometry": {"coordinates":[8.8196802139,53.6310806274],"type":"Point"}
}