{
  "type": "Feature",
  "properties": {
    "iso:country":"DE",
    "sg:address":"Barlstr. 46",
    "sg:city":"Zell",
    "sg:phone":"+49 6542/4170",
    "sg:postcode":"56856",
    "sg:province":"Rheinland-Pfalz",
    "wof:name":"Spritzgu\u00df Beteiligungs Gmbh",
    "wof:placetype":"venue"
},
  "geometry": {"coordinates":[7.158876,50.03196],"type":"Point"}
}