{
  "type": "Feature",
  "properties": {
    "iso:country":"DE",
    "sg:address":"Ferdinand-Sauerbruch-Str. 18",
    "sg:city":"Koblenz",
    "sg:phone":"+49 261/4980",
    "sg:postcode":"56073",
    "sg:province":"Rheinland-Pfalz",
    "wof:name":"Sterbekasse Der Debeka Krankenversicherung",
    "wof:placetype":"venue"
},
  "geometry": {"coordinates":[7.568157196,50.3597602844],"type":"Point"}
}