{
  "type": "Feature",
  "properties": {
    "iso:country":"DE",
    "sg:address":"K\u00f6nigsh\u00fctter Str. 6",
    "sg:city":"D\u00fcsseldorf",
    "sg:phone":"+49 211/279612",
    "sg:postcode":"40627",
    "sg:province":"Nordrhein-Westfalen",
    "wof:name":"Josef Und C. P\u00fctz",
    "wof:placetype":"venue"
},
  "geometry": {"coordinates":[6.8477911949,51.2158966064],"type":"Point"}
}