{
  "type": "Feature",
  "properties": {
    "iso:country":"DE",
    "sg:address":"Buchaer Str. 1",
    "sg:city":"Jena",
    "sg:postcode":"07745",
    "sg:province":"Th\u00fcringen",
    "wof:name":"Jat Ver-marketing Gmbh",
    "wof:placetype":"venue"
},
  "geometry": {"coordinates":[11.56725,50.907181],"type":"Point"}
}