{
  "type": "Feature",
  "properties": {
    "iso:country":"DE",
    "sg:address":"Friedensstr. 10",
    "sg:city":"Kleinaitingen",
    "sg:phone":"+49 8203/6157",
    "sg:postcode":"86507",
    "sg:province":"Bayern",
    "wof:name":"K & M Immoblien-verwaltungs Und Vermietungsges. Mbh",
    "wof:placetype":"venue"
},
  "geometry": {"coordinates":[10.8426198959,48.2160835266],"type":"Point"}
}