{
  "type": "Feature",
  "properties": {
    "iso:country":"DE",
    "sg:address":"Backhausstr. 10",
    "sg:city":"Bad Langensalza",
    "sg:phone":"+49 3603/848534",
    "sg:postcode":"99947",
    "sg:province":"Th\u00fcringen",
    "wof:name":"Drei T\u00fcrme Brot Und Backwaren Gmbh",
    "wof:placetype":"venue"
},
  "geometry": {"coordinates":[10.627608,51.04871],"type":"Point"}
}