{
  "type": "Feature",
  "properties": {
    "iso:country":"DE",
    "sg:address":"Wendentorwall 7",
    "sg:city":"Braunschweig",
    "sg:phone":"+49 531/17879",
    "sg:postcode":"38100",
    "sg:province":"Niedersachsen",
    "wof:name":"Wolfgang Boekhoff Architekt",
    "wof:placetype":"venue"
},
  "geometry": {"coordinates":[10.527232,52.271626],"type":"Point"}
}