{
  "type": "Feature",
  "properties": {
    "iso:country":"DE",
    "sg:address":"Im Forsthaus",
    "sg:city":"Ramsen",
    "sg:postcode":"67305",
    "sg:province":"Rheinland-Pfalz",
    "wof:name":"Ev. \u00d6ffentliche Bibliothek",
    "wof:placetype":"venue"
},
  "geometry": {"coordinates":[7.981239,49.514614],"type":"Point"}
}