{
  "type": "Feature",
  "properties": {
    "iso:country":"DE",
    "sg:address":"Dr\u00f6mscher Str. 9",
    "sg:city":"Extertal",
    "sg:phone":"+49 5262/2080",
    "sg:postcode":"32699",
    "sg:province":"Nordrhein-Westfalen",
    "wof:name":"R. Redecker",
    "wof:placetype":"venue"
},
  "geometry": {"coordinates":[9.1195297241,52.0939598083],"type":"Point"}
}