{
  "type": "Feature",
  "properties": {
    "iso:country":"DE",
    "sg:address":"Margaretenstr. 13 a",
    "sg:city":"Budenheim",
    "sg:postcode":"55257",
    "sg:province":"Rheinland-Pfalz",
    "wof:name":"Dienstleistungen Und Hausmeisterservice",
    "wof:placetype":"venue"
},
  "geometry": {"coordinates":[8.1687450409,50.02186203],"type":"Point"}
}