{
  "type": "Feature",
  "properties": {
    "iso:country":"DE",
    "sg:address":"Stahlbachstr. 21",
    "sg:city":"Suderburg",
    "sg:phone":"+49 5826/403",
    "sg:postcode":"29556",
    "sg:province":"Niedersachsen",
    "wof:name":"Bernd Thurau",
    "wof:placetype":"venue"
},
  "geometry": {"coordinates":[10.4624,52.917889],"type":"Point"}
}