{
  "type": "Feature",
  "properties": {
    "iso:country":"DE",
    "sg:address":"Hardtstr. 108",
    "sg:city":"Heidelberg",
    "sg:postcode":"69124",
    "sg:province":"Baden-W\u00fcrttemberg",
    "wof:name":"Fritz Fels M\u00f6belspedition Und",
    "wof:placetype":"venue"
},
  "geometry": {"coordinates":[8.673197,49.369255],"type":"Point"}
}