{
  "type": "Feature",
  "properties": {
    "iso:country":"DE",
    "sg:address":"Bahnhofstr. 49",
    "sg:city":"Langenfeld",
    "sg:phone":"+49 2173/13022",
    "sg:postcode":"40764",
    "sg:province":"Nordrhein-Westfalen",
    "wof:name":"Peter Heinrichs Taxi Heinrichs",
    "wof:placetype":"venue"
},
  "geometry": {"coordinates":[6.9411568642,51.0991706848],"type":"Point"}
}