{
  "type": "Feature",
  "properties": {
    "iso:country":"DE",
    "sg:address":"Eschstr. 51",
    "sg:city":"B\u00fcnde",
    "sg:phone":"+49 5223/188824",
    "sg:postcode":"32257",
    "sg:province":"Nordrhein-Westfalen",
    "wof:name":"Mts-montage-technik-service Mohamed Jami E. K.",
    "wof:placetype":"venue"
},
  "geometry": {"coordinates":[8.588522,52.20013],"type":"Point"}
}