{
  "type": "Feature",
  "properties": {
    "iso:country":"DE",
    "sg:address":"Ennemoserstr. 3",
    "sg:city":"M\u00fcnchen",
    "sg:phone":"+49 89/92379944",
    "sg:postcode":"81927",
    "sg:province":"Bayern",
    "wof:name":"Dr. Ekkehard Heinze Patentanwalt",
    "wof:placetype":"venue"
},
  "geometry": {"coordinates":[11.6295852661,48.1511001587],"type":"Point"}
}