{
  "type": "Feature",
  "properties": {
    "iso:country":"DE",
    "sg:address":"Walporzheimer Str. 19",
    "sg:city":"Bad Neuenahr-Ahrweiler",
    "sg:phone":"+49 2641/34376",
    "sg:postcode":"53474",
    "sg:province":"Rheinland-Pfalz",
    "wof:name":"Ahrweiler Winzer-verein Eg",
    "wof:placetype":"venue"
},
  "geometry": {"coordinates":[7.076229,50.531643],"type":"Point"}
}