{
  "type": "Feature",
  "properties": {
    "iso:country":"DE",
    "sg:address":"Markt 1",
    "sg:city":"Querfurt",
    "sg:postcode":"06268",
    "sg:province":"Sachsen-Anhalt",
    "wof:name":"Stadtarchiv",
    "wof:placetype":"venue"
},
  "geometry": {"coordinates":[11.597417,51.378513],"type":"Point"}
}