{
  "type": "Feature",
  "properties": {
    "iso:country":"DE",
    "sg:address":"K\u00f6lnische Str. 12",
    "sg:city":"Kassel",
    "sg:phone":"+49 561/12160",
    "sg:postcode":"34117",
    "sg:province":"Hessen",
    "wof:name":"Kahn",
    "wof:placetype":"venue"
},
  "geometry": {"coordinates":[9.49467659,51.3163871765],"type":"Point"}
}