{
  "type": "Feature",
  "properties": {
    "iso:country":"DE",
    "sg:address":"Schlehenweg 1",
    "sg:city":"Springe",
    "sg:phone":"+49 5045/6318",
    "sg:postcode":"31832",
    "sg:province":"Niedersachsen",
    "wof:name":"H. Willig",
    "wof:placetype":"venue"
},
  "geometry": {"coordinates":[9.6687250137,52.2565689087],"type":"Point"}
}