{
  "type": "Feature",
  "properties": {
    "iso:country":"DE",
    "sg:address":"M\u00fcllerstr 7",
    "sg:city":"M\u00fcnchen",
    "sg:phone":"+49 89/23615907",
    "sg:postcode":"80469",
    "sg:province":"Bayern",
    "wof:name":"Mnet Telekommunikations Gmbh",
    "wof:placetype":"venue"
},
  "geometry": {"coordinates":[11.573054,48.131989],"type":"Point"}
}