{
  "type": "Feature",
  "properties": {
    "iso:country":"DE",
    "sg:address":"Bahnhofstr. 1",
    "sg:city":"Neuenburg",
    "sg:phone":"+49 7631/72611",
    "sg:postcode":"79395",
    "sg:province":"Baden-W\u00fcrttemberg",
    "wof:name":"Restaurant Ratskeller",
    "wof:placetype":"venue"
},
  "geometry": {"coordinates":[7.5634541512,47.8129005432],"type":"Point"}
}