{
  "type": "Feature",
  "properties": {
    "iso:country":"DE",
    "sg:address":"Chemnitzer Str. 3",
    "sg:city":"Clau\u00dfnitz",
    "sg:postcode":"09236",
    "sg:province":"Sachsen",
    "wof:name":"K. Braun",
    "wof:placetype":"venue"
},
  "geometry": {"coordinates":[12.885534,50.936035],"type":"Point"}
}