{
  "type": "Feature",
  "properties": {
    "iso:country":"DE",
    "sg:address":"Kolkauer Str. 16",
    "sg:city":"Seelitz",
    "sg:phone":"+49 3737/41822",
    "sg:postcode":"09306",
    "sg:province":"Sachsen",
    "wof:name":"R\u00fctz Bedachungs Gmbh",
    "wof:placetype":"venue"
},
  "geometry": {"coordinates":[12.8216953278,51.0307769775],"type":"Point"}
}