{
  "type": "Feature",
  "properties": {
    "iso:country":"DE",
    "sg:address":"Dorfstr. 14",
    "sg:city":"Huje",
    "sg:phone":"+49 4827/509",
    "sg:postcode":"25588",
    "sg:province":"Schleswig-Holstein",
    "wof:name":"Werner Lahann Baggerunternehmen",
    "wof:placetype":"venue"
},
  "geometry": {"coordinates":[9.43685,53.975571],"type":"Point"}
}