{
  "type": "Feature",
  "properties": {
    "iso:country":"DE",
    "sg:address":"Dorfstr. 3 b",
    "sg:city":"Jersbek",
    "sg:phone":"+49 4532/23515",
    "sg:postcode":"22941",
    "sg:province":"Schleswig-Holstein",
    "wof:name":"Klaus-dieter Penno",
    "wof:placetype":"venue"
},
  "geometry": {"coordinates":[10.2143697739,53.7215919495],"type":"Point"}
}