{
  "type": "Feature",
  "properties": {
    "iso:country":"DE",
    "sg:address":"Wiesenstr. 71",
    "sg:city":"Viernheim",
    "sg:phone":"+49 671/889060",
    "sg:postcode":"68519",
    "sg:province":"Hessen",
    "wof:name":"Dieter Guckes Media Service Gmbh",
    "wof:placetype":"venue"
},
  "geometry": {"coordinates":[8.589354,49.544998],"type":"Point"}
}