{
  "type": "Feature",
  "properties": {
    "iso:country":"DE",
    "sg:address":"Barbarossastr. 24",
    "sg:city":"Wiesbaden",
    "sg:phone":"+49 611/711425",
    "sg:postcode":"65205",
    "sg:province":"Hessen",
    "wof:name":"Walter Boscheck",
    "wof:placetype":"venue"
},
  "geometry": {"coordinates":[8.3035678864,50.0520973206],"type":"Point"}
}