{
  "type": "Feature",
  "properties": {
    "iso:country":"DE",
    "sg:address":"Konrad-Adenauer-Str. 19a",
    "sg:city":"Linden",
    "sg:phone":"+49 6403/963277",
    "sg:postcode":"35440",
    "sg:province":"Hessen",
    "wof:name":"R. Von B\u00fcnau",
    "wof:placetype":"venue"
},
  "geometry": {"coordinates":[8.6661081314,50.5257568359],"type":"Point"}
}