{
  "type": "Feature",
  "properties": {
    "iso:country":"DE",
    "sg:address":"F\u00f6rstergasse 3",
    "sg:city":"Hohenhameln",
    "sg:phone":"+49 5128/1391",
    "sg:postcode":"31249",
    "sg:province":"Niedersachsen",
    "wof:name":"Heinrich Ebeling",
    "wof:placetype":"venue"
},
  "geometry": {"coordinates":[10.091868,52.303665],"type":"Point"}
}