{
  "type": "Feature",
  "properties": {
    "iso:country":"DE",
    "sg:address":"Tannenweg 1",
    "sg:city":"Vettelscho\u00df",
    "sg:phone":"+49 2645/683",
    "sg:postcode":"53560",
    "sg:province":"Rheinland-Pfalz",
    "wof:name":"H. Lahr",
    "wof:placetype":"venue"
},
  "geometry": {"coordinates":[7.3134541512,50.6172904968],"type":"Point"}
}