{
  "type": "Feature",
  "properties": {
    "iso:country":"DE",
    "sg:address":"Vor dem Steintor 37",
    "sg:city":"Bremen",
    "sg:phone":"+49 421/790030",
    "sg:postcode":"28203",
    "sg:province":"Bremen",
    "wof:name":"Sanit\u00e4tshaus Heinrich Oesterreich Gmbh",
    "wof:placetype":"venue"
},
  "geometry": {"coordinates":[8.8254108429,53.0729370117],"type":"Point"}
}