{
  "type": "Feature",
  "properties": {
    "iso:country":"DE",
    "sg:address":"Alter Bad Stebener Weg 1",
    "sg:city":"Bad Steben",
    "sg:phone":"+49 9288/9550",
    "sg:postcode":"95138",
    "sg:province":"Bayern",
    "wof:name":"Br\u00fchl & Sippold Gmbh",
    "wof:placetype":"venue"
},
  "geometry": {"coordinates":[11.6273994446,50.3732376099],"type":"Point"}
}