{
  "type": "Feature",
  "properties": {
    "iso:country":"DE",
    "sg:address":"Niederkirchnerstr. 9",
    "sg:city":"Leipzig",
    "sg:postcode":"04107",
    "sg:province":"Sachsen",
    "wof:name":"Diringer & Scheidel Bauunternehmung Gmbh & Co. Kg",
    "wof:placetype":"venue"
},
  "geometry": {"coordinates":[12.369056,51.325943],"type":"Point"}
}