{
  "type": "Feature",
  "properties": {
    "iso:country":"DE",
    "sg:address":"Erpestr. 43",
    "sg:city":"Bielefeld",
    "sg:phone":"+49 521/48071",
    "sg:postcode":"33649",
    "sg:province":"Nordrhein-Westfalen",
    "wof:name":"Potthoff & Korte",
    "wof:placetype":"venue"
},
  "geometry": {"coordinates":[8.4367456436,51.9652481079],"type":"Point"}
}