{
  "type": "Feature",
  "properties": {
    "iso:country":"DE",
    "sg:address":"Marktstr. 14",
    "sg:city":"Burgdorf",
    "sg:phone":"+49 5136/907",
    "sg:postcode":"31303",
    "sg:province":"Niedersachsen",
    "wof:name":"Hannoversche Allgemeine",
    "wof:placetype":"venue"
},
  "geometry": {"coordinates":[10.0082178116,52.4465446472],"type":"Point"}
}