{
  "type": "Feature",
  "properties": {
    "iso:country":"DE",
    "sg:address":"Alte Schlo\u00dfstr. 8",
    "sg:city":"Neuwied",
    "sg:phone":"+49 2622/4226",
    "sg:postcode":"56566",
    "sg:province":"Rheinland-Pfalz",
    "wof:name":"E. Br\u00fccker",
    "wof:placetype":"venue"
},
  "geometry": {"coordinates":[7.544411,50.424187],"type":"Point"}
}