{
  "type": "Feature",
  "properties": {
    "iso:country":"DE",
    "sg:address":"Ellernstr. 10",
    "sg:city":"Springe",
    "sg:postcode":"31832",
    "sg:province":"Niedersachsen",
    "wof:name":"Werner G. Gehring-stiftung",
    "wof:placetype":"venue"
},
  "geometry": {"coordinates":[9.5490036011,52.2089233398],"type":"Point"}
}