{
  "type": "Feature",
  "properties": {
    "iso:country":"DE",
    "sg:address":"M\u00fcnchner Str. 46",
    "sg:city":"Dachau",
    "sg:phone":"+49 8131/72095",
    "sg:postcode":"85221",
    "sg:province":"Bayern",
    "wof:name":"Commerzbank Ag",
    "wof:placetype":"venue"
},
  "geometry": {"coordinates":[11.441009,48.25251],"type":"Point"}
}