{
  "type": "Feature",
  "properties": {
    "iso:country":"DE",
    "sg:address":"Osdorfer Str. 22",
    "sg:city":"Berlin",
    "sg:phone":"+49 30/7125202",
    "sg:postcode":"12207",
    "sg:province":"Berlin",
    "wof:name":"Edward Franke",
    "wof:placetype":"venue"
},
  "geometry": {"coordinates":[13.314965,52.416904],"type":"Point"}
}