{
  "type": "Feature",
  "properties": {
    "iso:country":"DE",
    "sg:address":"Augustastr. 53",
    "sg:city":"Dinslaken",
    "sg:phone":"+49 2064/30581",
    "sg:postcode":"46537",
    "sg:province":"Nordrhein-Westfalen",
    "wof:name":"Heinz-hermann Koch",
    "wof:placetype":"venue"
},
  "geometry": {"coordinates":[6.731657,51.581417],"type":"Point"}
}