{
  "type": "Feature",
  "properties": {
    "iso:country":"DE",
    "sg:address":"G\u00fcterbahnhofstr. 10",
    "sg:city":"G\u00f6ttingen",
    "sg:postcode":"37073",
    "sg:province":"Niedersachsen",
    "wof:name":"Andere Wege E.v.",
    "wof:placetype":"venue"
},
  "geometry": {"coordinates":[9.9309597015,51.5421600342],"type":"Point"}
}