{
  "type": "Feature",
  "properties": {
    "iso:country":"DE",
    "sg:address":"Landshuter Str. 22",
    "sg:city":"Berlin",
    "sg:phone":"+49 30/2350850",
    "sg:postcode":"10779",
    "sg:province":"Berlin",
    "wof:name":"Ntt Chauffeur- & Limousinen- Service",
    "wof:placetype":"venue"
},
  "geometry": {"coordinates":[13.339829,52.490021],"type":"Point"}
}