{
  "type": "Feature",
  "properties": {
    "iso:country":"DE",
    "sg:address":"Seitenkopfstr. 6 a",
    "sg:city":"Wilnsdorf",
    "sg:phone":"+49 2737/91006",
    "sg:postcode":"57234",
    "sg:province":"Nordrhein-Westfalen",
    "wof:name":"Wolf Gmbh",
    "wof:placetype":"venue"
},
  "geometry": {"coordinates":[8.177273,50.843021],"type":"Point"}
}