{
  "type": "Feature",
  "properties": {
    "iso:country":"DE",
    "sg:address":"Maximilian-Kolbe-Str. 8",
    "sg:city":"Alzey",
    "sg:phone":"+49 6731/44363",
    "sg:postcode":"55232",
    "sg:province":"Rheinland-Pfalz",
    "wof:name":"Novotex Gmbh",
    "wof:placetype":"venue"
},
  "geometry": {"coordinates":[8.097178,49.738659],"type":"Point"}
}