{
  "type": "Feature",
  "properties": {
    "iso:country":"DE",
    "sg:address":"Budapester Str. 2",
    "sg:city":"Berlin",
    "sg:phone":"+49 30/26020",
    "sg:postcode":"10787",
    "sg:province":"Berlin",
    "wof:name":"Restaurant Brasserie",
    "wof:placetype":"venue"
},
  "geometry": {"coordinates":[13.3444309235,52.5065460205],"type":"Point"}
}