{
  "type": "Feature",
  "properties": {
    "iso:country":"DE",
    "sg:address":"In der Sandkaul 12",
    "sg:city":"Saarbr\u00fccken",
    "sg:phone":"+49 681/811493",
    "sg:postcode":"66133",
    "sg:province":"Saarland",
    "wof:name":"Ralf Seibert Omnibus- Betrieb Gmbh",
    "wof:placetype":"venue"
},
  "geometry": {"coordinates":[7.0623297691,49.2445144653],"type":"Point"}
}