{
  "type": "Feature",
  "properties": {
    "iso:country":"DE",
    "sg:address":"Bahnhofstr. 12",
    "sg:city":"Steinfurt",
    "sg:phone":"+49 2551/3155",
    "sg:postcode":"48565",
    "sg:province":"Nordrhein-Westfalen",
    "wof:name":"Die Brille R. & O. Optik Ohg",
    "wof:placetype":"venue"
},
  "geometry": {"coordinates":[7.3339691162,52.1492652893],"type":"Point"}
}