{
  "type": "Feature",
  "properties": {
    "iso:country":"DE",
    "sg:address":"Mittelfeldstr. 29",
    "sg:city":"Dillenburg",
    "sg:phone":"+49 2771/7509",
    "sg:postcode":"35683",
    "sg:province":"Hessen",
    "wof:name":"Horst Pfeifer Architekt",
    "wof:placetype":"venue"
},
  "geometry": {"coordinates":[8.282862,50.732346],"type":"Point"}
}