{
  "type": "Feature",
  "properties": {
    "iso:country":"DE",
    "sg:address":"Blumenstr. 5 A",
    "sg:city":"Birkenheide",
    "sg:phone":"+49 6237/7431",
    "sg:postcode":"67134",
    "sg:province":"Rheinland-Pfalz",
    "wof:name":"H. Heck Elektro- Installation Gmbh",
    "wof:placetype":"venue"
},
  "geometry": {"coordinates":[8.265085,49.481579],"type":"Point"}
}