{
  "type": "Feature",
  "properties": {
    "iso:country":"DE",
    "sg:address":"Haubenkopfstr. 16",
    "sg:city":"Karlsruhe",
    "sg:postcode":"76189",
    "sg:province":"Baden-W\u00fcrttemberg",
    "wof:name":"Fkm Verlag Gmbh",
    "wof:placetype":"venue"
},
  "geometry": {"coordinates":[8.3495798111,48.9967041016],"type":"Point"}
}