{
  "type": "Feature",
  "properties": {
    "iso:country":"DE",
    "sg:address":"Schwei\u00dflohstr. 33",
    "sg:city":"Erbendorf",
    "sg:phone":"+49 9682/91205",
    "sg:postcode":"92681",
    "sg:province":"Bayern",
    "wof:name":"Peter Gerolstein Ingenieur",
    "wof:placetype":"venue"
},
  "geometry": {"coordinates":[12.0545606613,49.8440589905],"type":"Point"}
}