{
  "type": "Feature",
  "properties": {
    "iso:country":"DE",
    "sg:address":"Zwingergasse 4 a",
    "sg:city":"Sinsheim",
    "sg:postcode":"74889",
    "sg:province":"Baden-W\u00fcrttemberg",
    "wof:name":"Chemdata Labor- Und Datentechnik",
    "wof:placetype":"venue"
},
  "geometry": {"coordinates":[8.8765726089,49.2518386841],"type":"Point"}
}