{
  "type": "Feature",
  "properties": {
    "iso:country":"DE",
    "sg:address":"Alexanderstr. 19",
    "sg:city":"Kranichfeld",
    "sg:phone":"+49 36450/42698",
    "sg:postcode":"99448",
    "sg:province":"Th\u00fcringen",
    "wof:name":"Gisela Barthel",
    "wof:placetype":"venue"
},
  "geometry": {"coordinates":[11.2019710541,50.8532905579],"type":"Point"}
}