{
  "type": "Feature",
  "properties": {
    "iso:country":"DE",
    "sg:address":"Lengericher Str. 27",
    "sg:city":"Lienen",
    "sg:phone":"+49 5483/77256",
    "sg:postcode":"49536",
    "sg:province":"Nordrhein-Westfalen",
    "wof:name":"Bernhard M\u00fcller",
    "wof:placetype":"venue"
},
  "geometry": {"coordinates":[7.965905,52.147491],"type":"Point"}
}