{
  "type": "Feature",
  "properties": {
    "iso:country":"DE",
    "sg:address":"Kirchstr. 1",
    "sg:city":"Gottmadingen",
    "sg:phone":"+49 7731/71653",
    "sg:postcode":"78244",
    "sg:province":"Baden-W\u00fcrttemberg",
    "wof:name":"Oskar Kramer",
    "wof:placetype":"venue"
},
  "geometry": {"coordinates":[8.775894165,47.7346191406],"type":"Point"}
}