{
  "type": "Feature",
  "properties": {
    "iso:country":"DE",
    "sg:address":"Markneukirchner Str. 52",
    "sg:city":"Zwota",
    "sg:phone":"+49 37467/23378",
    "sg:postcode":"08267",
    "sg:province":"Sachsen",
    "wof:name":"Bernd Hutschenreuter",
    "wof:placetype":"venue"
},
  "geometry": {"coordinates":[12.418883,50.349514],"type":"Point"}
}