{
  "type": "Feature",
  "properties": {
    "iso:country":"DE",
    "sg:address":"Bahnhofstr. 29",
    "sg:city":"Tostedt",
    "sg:phone":"+49 4182/70149",
    "sg:postcode":"21255",
    "sg:province":"Niedersachsen",
    "wof:name":"Klaus-dieter Dittmer",
    "wof:placetype":"venue"
},
  "geometry": {"coordinates":[9.716131,53.278362],"type":"Point"}
}