{
  "type": "Feature",
  "properties": {
    "iso:country":"DE",
    "sg:address":"Am Marstall 5",
    "sg:city":"Hannover",
    "sg:phone":"+49 511/328938",
    "sg:postcode":"30159",
    "sg:province":"Niedersachsen",
    "wof:name":"Cherie",
    "wof:placetype":"venue"
},
  "geometry": {"coordinates":[9.7329978943,52.3741149902],"type":"Point"}
}