{
  "type": "Feature",
  "properties": {
    "iso:country":"DE",
    "sg:address":"Maxstr. 8",
    "sg:city":"Dresden",
    "sg:phone":"+49 351/866910",
    "sg:postcode":"01067",
    "sg:province":"Sachsen",
    "wof:name":"Bdo Deutsche Warentreuhand Ag",
    "wof:placetype":"venue"
},
  "geometry": {"coordinates":[13.7269468307,51.0569839478],"type":"Point"}
}