{
  "type": "Feature",
  "properties": {
    "iso:country":"DE",
    "sg:address":"Hauptstr. 29",
    "sg:city":"Kieselbronn",
    "sg:phone":"+49 7231/52351",
    "sg:postcode":"75249",
    "sg:province":"Baden-W\u00fcrttemberg",
    "wof:name":"Hirsch",
    "wof:placetype":"venue"
},
  "geometry": {"coordinates":[8.7528934479,48.9362564087],"type":"Point"}
}