{
  "type": "Feature",
  "properties": {
    "iso:country":"DE",
    "sg:address":"Zur Alten Ruhr 1",
    "sg:city":"Arnsberg",
    "sg:phone":"+49 2932/83216",
    "sg:postcode":"59755",
    "sg:province":"Nordrhein-Westfalen",
    "wof:name":"Elektrofachmarkt Berlet",
    "wof:placetype":"venue"
},
  "geometry": {"coordinates":[7.9639182091,51.4434547424],"type":"Point"}
}