{
  "type": "Feature",
  "properties": {
    "iso:country":"DE",
    "sg:address":"Dahlmannstr. 6",
    "sg:city":"N\u00fcrnberg",
    "sg:postcode":"90491",
    "sg:province":"Bayern",
    "wof:name":"Complet Service Gmbh",
    "wof:placetype":"venue"
},
  "geometry": {"coordinates":[11.122682,49.471172],"type":"Point"}
}