{
  "type": "Feature",
  "properties": {
    "iso:country":"DE",
    "sg:address":"Bremsen 11",
    "sg:city":"Leichlingen",
    "sg:phone":"+49 2175/1234",
    "sg:postcode":"42799",
    "sg:province":"Nordrhein-Westfalen",
    "wof:name":"Eduard Hartauer",
    "wof:placetype":"venue"
},
  "geometry": {"coordinates":[7.0013670921,51.1036453247],"type":"Point"}
}