{
  "type": "Feature",
  "properties": {
    "iso:country":"DE",
    "sg:address":"Dorfsfeld 1",
    "sg:city":"Scharnhorst",
    "sg:phone":"+49 5142/92083",
    "sg:postcode":"29348",
    "sg:province":"Niedersachsen",
    "wof:name":"Hof Michael Ohg",
    "wof:placetype":"venue"
},
  "geometry": {"coordinates":[10.312925,52.717255],"type":"Point"}
}