{
  "type": "Feature",
  "properties": {
    "iso:country":"DE",
    "sg:address":"Freiheitstr. 124-126",
    "sg:city":"Remscheid",
    "sg:phone":"+49 2191/22001",
    "sg:postcode":"42853",
    "sg:province":"Nordrhein-Westfalen",
    "wof:name":"Erwin Schmachtenberg Gmbh & Co. Kg",
    "wof:placetype":"venue"
},
  "geometry": {"coordinates":[7.1838312149,51.1775398254],"type":"Point"}
}