{
  "type": "Feature",
  "properties": {
    "iso:country":"DE",
    "sg:address":"Zinkmattenstr. 28",
    "sg:city":"Freiburg",
    "sg:phone":"+49 761/53002",
    "sg:postcode":"79108",
    "sg:province":"Baden-W\u00fcrttemberg",
    "wof:name":"Tr\u00f6ller Fahrzeugbau Gmbh",
    "wof:placetype":"venue"
},
  "geometry": {"coordinates":[7.855723,48.025784],"type":"Point"}
}