{
  "type": "Feature",
  "properties": {
    "iso:country":"DE",
    "sg:address":"Pfalzgraf-Otto-Str. 54",
    "sg:city":"Mosbach",
    "sg:phone":"+49 6261/15021",
    "sg:postcode":"74821",
    "sg:province":"Baden-W\u00fcrttemberg",
    "wof:name":"Kamps S\u00fcdwest Gmbh & Co. Kg",
    "wof:placetype":"venue"
},
  "geometry": {"coordinates":[9.122931,49.33955],"type":"Point"}
}