{
  "type": "Feature",
  "properties": {
    "iso:country":"DE",
    "sg:address":"L\u00f6bauer Str. 16",
    "sg:city":"Bautzen",
    "sg:postcode":"02625",
    "sg:province":"Sachsen",
    "wof:name":"Systempartner Computervertriebs Gmbh",
    "wof:placetype":"venue"
},
  "geometry": {"coordinates":[14.4389181137,51.1807022095],"type":"Point"}
}