{
  "type": "Feature",
  "properties": {
    "iso:country":"DE",
    "sg:address":"Achterumsweg",
    "sg:city":"Marienhafe",
    "sg:phone":"+49 4934/1487",
    "sg:postcode":"26529",
    "sg:province":"Niedersachsen",
    "wof:name":"Ewald Fr\u00e4ck G\u00e4rtnerei",
    "wof:placetype":"venue"
},
  "geometry": {"coordinates":[7.274665,53.520863],"type":"Point"}
}