{
  "type": "Feature",
  "properties": {
    "iso:country":"DE",
    "sg:address":"Hesselbacher Str. 21",
    "sg:city":"Bad Laasphe",
    "sg:phone":"+49 2752/5444",
    "sg:postcode":"57334",
    "sg:province":"Nordrhein-Westfalen",
    "wof:name":"Hotel Marburger",
    "wof:placetype":"venue"
},
  "geometry": {"coordinates":[8.3630895615,50.8855361938],"type":"Point"}
}