{
  "type": "Feature",
  "properties": {
    "iso:country":"DE",
    "sg:address":"Unterstaller Weg 3",
    "sg:city":"Egweil",
    "sg:phone":"+49 8424/263",
    "sg:postcode":"85116",
    "sg:province":"Bayern",
    "wof:name":"Vitus Lehenmeier",
    "wof:placetype":"venue"
},
  "geometry": {"coordinates":[11.2292194366,48.784828186],"type":"Point"}
}