{
  "type": "Feature",
  "properties": {
    "iso:country":"DE",
    "sg:address":"Uelzener Str. 15",
    "sg:city":"Rosche",
    "sg:phone":"+49 5803/1230",
    "sg:postcode":"29571",
    "sg:province":"Niedersachsen",
    "wof:name":"Marina Wilhelm Und Marion Helms",
    "wof:placetype":"venue"
},
  "geometry": {"coordinates":[10.7486448288,52.985710144],"type":"Point"}
}