{
  "type": "Feature",
  "properties": {
    "iso:country":"DE",
    "sg:address":"Simbach",
    "sg:city":"Simbach",
    "sg:phone":"+49 9954/204",
    "sg:postcode":"94436",
    "sg:province":"Bayern",
    "wof:name":"Raiffeisenbank Arnstorf Eg",
    "wof:placetype":"venue"
},
  "geometry": {"coordinates":[12.71651,48.561131],"type":"Point"}
}