{
  "type": "Feature",
  "properties": {
    "iso:country":"DE",
    "sg:address":"Hinter dem Dorfe 3 A",
    "sg:city":"Vechelde",
    "sg:phone":"+49 5302/2104",
    "sg:postcode":"38159",
    "sg:province":"Niedersachsen",
    "wof:name":"Securitas Versicherungen Falk Rautmann",
    "wof:placetype":"venue"
},
  "geometry": {"coordinates":[10.3337802887,52.2736473083],"type":"Point"}
}