{
  "type": "Feature",
  "properties": {
    "iso:country":"DE",
    "sg:address":"Schie\u00dfhausstr. 8a",
    "sg:city":"Rottendorf",
    "sg:phone":"+49 9302/4044",
    "sg:postcode":"97228",
    "sg:province":"Bayern",
    "wof:name":"Audax-reisen Gmbh",
    "wof:placetype":"venue"
},
  "geometry": {"coordinates":[10.0339345932,49.7905731201],"type":"Point"}
}