{
  "type": "Feature",
  "properties": {
    "iso:country":"DE",
    "sg:address":"M\u00e4rchenweg 32",
    "sg:city":"Burgwedel",
    "sg:phone":"+49 5130/79997",
    "sg:postcode":"30938",
    "sg:province":"Niedersachsen",
    "wof:name":"Kochs Ingenieur",
    "wof:placetype":"venue"
},
  "geometry": {"coordinates":[9.7953166962,52.5285263062],"type":"Point"}
}