{
  "type": "Feature",
  "properties": {
    "iso:country":"DE",
    "sg:address":"Steinmauerweg 19 a",
    "sg:city":"Lauf",
    "sg:phone":"+49 7841/23023",
    "sg:postcode":"77886",
    "sg:province":"Baden-W\u00fcrttemberg",
    "wof:name":"Anita Eisele",
    "wof:placetype":"venue"
},
  "geometry": {"coordinates":[8.127196312,48.6509284973],"type":"Point"}
}