{
  "type": "Feature",
  "properties": {
    "iso:country":"DE",
    "sg:address":"Liesetal 7",
    "sg:city":"Hallenberg",
    "sg:phone":"+49 2984/667",
    "sg:postcode":"59969",
    "sg:province":"Nordrhein-Westfalen",
    "wof:name":"Pension Maria Dollberg",
    "wof:placetype":"venue"
},
  "geometry": {"coordinates":[8.6112632751,51.1398696899],"type":"Point"}
}