{
  "type": "Feature",
  "properties": {
    "iso:country":"DE",
    "sg:address":"R\u00fcterstr. 68",
    "sg:city":"Hamburg",
    "sg:postcode":"22041",
    "sg:province":"Hamburg",
    "wof:name":"Night-flight Virginia Lazovsky",
    "wof:placetype":"venue"
},
  "geometry": {"coordinates":[10.075549,53.574692],"type":"Point"}
}