{
  "type": "Feature",
  "properties": {
    "iso:country":"DE",
    "sg:address":"Lehmkuhlen 1",
    "sg:city":"Vrees",
    "sg:phone":"+49 4479/636",
    "sg:postcode":"49757",
    "sg:province":"Niedersachsen",
    "wof:name":"Manfred Kaiser Maschinen- Bau Gmbh",
    "wof:placetype":"venue"
},
  "geometry": {"coordinates":[7.783319,52.887806],"type":"Point"}
}