{
  "type": "Feature",
  "properties": {
    "iso:country":"DE",
    "sg:address":"Dunantstr. 6",
    "sg:city":"Zweibr\u00fccken",
    "sg:phone":"+49 6332/44455",
    "sg:postcode":"66482",
    "sg:province":"Rheinland-Pfalz",
    "wof:name":"Reiseb\u00fcro H. Kraunus",
    "wof:placetype":"venue"
},
  "geometry": {"coordinates":[7.3852667809,49.2415771484],"type":"Point"}
}