{
  "type": "Feature",
  "properties": {
    "iso:country":"DE",
    "sg:address":"Mauracher Str. 25",
    "sg:city":"Denzlingen",
    "sg:phone":"+49 7666/5485",
    "sg:postcode":"79211",
    "sg:province":"Baden-W\u00fcrttemberg",
    "wof:name":"G. R\u00f6sch Wohnungs- Und Siedlungsbau",
    "wof:placetype":"venue"
},
  "geometry": {"coordinates":[7.8905777931,48.0732498169],"type":"Point"}
}