{
  "type": "Feature",
  "properties": {
    "iso:country":"DE",
    "sg:address":"Herberger Weg 28",
    "sg:city":"Heiligenhaus",
    "sg:phone":"+49 2056/6405",
    "sg:postcode":"42579",
    "sg:province":"Nordrhein-Westfalen",
    "wof:name":"Walter W\u00fcster",
    "wof:placetype":"venue"
},
  "geometry": {"coordinates":[6.979285,51.336514],"type":"Point"}
}