{
  "type": "Feature",
  "properties": {
    "iso:country":"DE",
    "sg:address":"Pastor-L\u00f6h-Str. 62",
    "sg:city":"Burscheid",
    "sg:phone":"+49 2174/5657",
    "sg:postcode":"51399",
    "sg:province":"Nordrhein-Westfalen",
    "wof:name":"M. Partidou Tennishalle",
    "wof:placetype":"venue"
},
  "geometry": {"coordinates":[7.1169929504,51.0912284851],"type":"Point"}
}