{
  "type": "Feature",
  "properties": {
    "iso:country":"DE",
    "sg:address":"Greiffenklaustr. 27",
    "sg:city":"Gundheim",
    "sg:phone":"+49 6244/4970",
    "sg:postcode":"67599",
    "sg:province":"Rheinland-Pfalz",
    "wof:name":"Peter Dohn",
    "wof:placetype":"venue"
},
  "geometry": {"coordinates":[8.23990345,49.6748466492],"type":"Point"}
}