{
  "type": "Feature",
  "properties": {
    "iso:country":"DE",
    "sg:address":"Obere Str. 11",
    "sg:city":"Villingen-Schwenningen",
    "sg:phone":"+49 7721/504171",
    "sg:postcode":"78050",
    "sg:province":"Baden-W\u00fcrttemberg",
    "wof:name":"Neckermann",
    "wof:placetype":"venue"
},
  "geometry": {"coordinates":[8.459116,48.056671],"type":"Point"}
}