{
  "type": "Feature",
  "properties": {
    "iso:country":"DE",
    "sg:address":"Schulstr. 5",
    "sg:city":"Borgholzhausen",
    "sg:phone":"+49 5425/80717",
    "sg:postcode":"33829",
    "sg:province":"Nordrhein-Westfalen",
    "wof:name":"Stadtarchiv",
    "wof:placetype":"venue"
},
  "geometry": {"coordinates":[8.303854,52.10334],"type":"Point"}
}