{
  "type": "Feature",
  "properties": {
    "iso:country":"DE",
    "sg:address":"Hermann-Ehlers-Str. 40",
    "sg:city":"Reutlingen",
    "sg:phone":"+49 7121/239987",
    "sg:postcode":"72762",
    "sg:province":"Baden-W\u00fcrttemberg",
    "wof:name":"Georg Dikos Architekt",
    "wof:placetype":"venue"
},
  "geometry": {"coordinates":[9.191152,48.48241],"type":"Point"}
}