{
  "type": "Feature",
  "properties": {
    "iso:country":"DE",
    "sg:address":"Philosophenweg 48",
    "sg:city":"Wetzlar",
    "sg:phone":"+49 6441/42577",
    "sg:postcode":"35578",
    "sg:province":"Hessen",
    "wof:name":"Dr. Hans Rau Tierarzt",
    "wof:placetype":"venue"
},
  "geometry": {"coordinates":[8.5118932724,50.5553436279],"type":"Point"}
}