{
  "type": "Feature",
  "properties": {
    "iso:country":"DE",
    "sg:address":"Gittruper Str. 67",
    "sg:city":"M\u00fcnster",
    "sg:phone":"+49 251/32282",
    "sg:postcode":"48157",
    "sg:province":"Nordrhein-Westfalen",
    "wof:name":"Klaus Humborg",
    "wof:placetype":"venue"
},
  "geometry": {"coordinates":[7.672770977,52.0336875916],"type":"Point"}
}