{
  "type": "Feature",
  "properties": {
    "iso:country":"DE",
    "sg:address":"Mitterfeldstr. 40",
    "sg:city":"Biessenhofen",
    "sg:phone":"+49 8341/7993",
    "sg:postcode":"87640",
    "sg:province":"Bayern",
    "wof:name":"Friedrich Fr\u00f6se",
    "wof:placetype":"venue"
},
  "geometry": {"coordinates":[10.6453552246,47.8226013184],"type":"Point"}
}