{
  "type": "Feature",
  "properties": {
    "iso:country":"DE",
    "sg:address":"Werner-Haas-Str. 6",
    "sg:city":"Augsburg",
    "sg:phone":"+49 821/560010",
    "sg:postcode":"86153",
    "sg:province":"Bayern",
    "wof:name":"Schulze Und Partner",
    "wof:placetype":"venue"
},
  "geometry": {"coordinates":[10.908606,48.366718],"type":"Point"}
}