{
  "type": "Feature",
  "properties": {
    "iso:country":"DE",
    "sg:address":"Kirchstr. 22",
    "sg:city":"Aurich",
    "sg:phone":"+49 4941/67042",
    "sg:postcode":"26603",
    "sg:province":"Niedersachsen",
    "wof:name":"Cvjm Aurich E. V.",
    "wof:placetype":"venue"
},
  "geometry": {"coordinates":[7.4808287621,53.4706001282],"type":"Point"}
}