{
  "type": "Feature",
  "properties": {
    "iso:country":"DE",
    "sg:address":"Im Kirberg 8",
    "sg:city":"Leverkusen",
    "sg:phone":"+49 214/93322",
    "sg:postcode":"51377",
    "sg:province":"Nordrhein-Westfalen",
    "wof:name":"F. J. M\u00fcller Elektroinstallation",
    "wof:placetype":"venue"
},
  "geometry": {"coordinates":[7.095794,51.04018],"type":"Point"}
}