{
  "type": "Feature",
  "properties": {
    "iso:country":"DE",
    "sg:address":"Langerstr. 3",
    "sg:city":"M\u00fcnchen",
    "sg:phone":"+49 89/41401",
    "sg:postcode":"81675",
    "sg:province":"Bayern",
    "wof:name":"Psychiatrische Klinik Und Poliklinik Der",
    "wof:placetype":"venue"
},
  "geometry": {"coordinates":[11.5978975296,48.1372871399],"type":"Point"}
}