{
  "type": "Feature",
  "properties": {
    "iso:country":"DE",
    "sg:address":"Rosenheimer Landstr. 44",
    "sg:city":"Ottobrunn",
    "sg:postcode":"85521",
    "sg:province":"Bayern",
    "wof:name":"Auto-bauer Ohg",
    "wof:placetype":"venue"
},
  "geometry": {"coordinates":[11.660539,48.065407],"type":"Point"}
}