{
  "type": "Feature",
  "properties": {
    "iso:country":"DE",
    "sg:address":"Steintor 41",
    "sg:city":"Wittenburg",
    "sg:phone":"+49 38852/52238",
    "sg:postcode":"19243",
    "sg:province":"Mecklenburg-Vorpommern",
    "wof:name":"Automaten-casino-wittenburg Inh. Ulrich Stellmacher",
    "wof:placetype":"venue"
},
  "geometry": {"coordinates":[11.0783224106,53.5073547363],"type":"Point"}
}