{
  "type": "Feature",
  "properties": {
    "iso:country":"DE",
    "sg:address":"Bayreuther Str. 45",
    "sg:city":"Leipzig",
    "sg:postcode":"04207",
    "sg:province":"Sachsen",
    "wof:name":"P. Kopbauer",
    "wof:placetype":"venue"
},
  "geometry": {"coordinates":[12.2986059189,51.3141059875],"type":"Point"}
}