{
  "type": "Feature",
  "properties": {
    "iso:country":"DE",
    "sg:address":"Am Neuendeich 136",
    "sg:city":"Blomesche Wildnis",
    "sg:phone":"+49 4124/8798",
    "sg:postcode":"25348",
    "sg:province":"Schleswig-Holstein",
    "wof:name":"Walter Harnau",
    "wof:placetype":"venue"
},
  "geometry": {"coordinates":[9.4093570709,53.8055343628],"type":"Point"}
}