{
  "type": "Feature",
  "properties": {
    "iso:country":"DE",
    "sg:address":"Bahnstr. 51",
    "sg:city":"Erkrath",
    "sg:phone":"+49 211/245551",
    "sg:postcode":"40699",
    "sg:province":"Nordrhein-Westfalen",
    "wof:name":"Wilhelmus Van Stiphout",
    "wof:placetype":"venue"
},
  "geometry": {"coordinates":[6.911155,51.221394],"type":"Point"}
}