{
  "type": "Feature",
  "properties": {
    "iso:country":"DE",
    "sg:address":"Karl-Martell-Str. 38",
    "sg:city":"N\u00fcrnberg",
    "sg:phone":"+49 911/316504",
    "sg:postcode":"90431",
    "sg:province":"Bayern",
    "wof:name":"Alles Klar Veranstaltungs-service Gmbh",
    "wof:placetype":"venue"
},
  "geometry": {"coordinates":[11.0149526596,49.4563369751],"type":"Point"}
}