{
  "type": "Feature",
  "properties": {
    "iso:country":"DE",
    "sg:address":"Porschestr. 8",
    "sg:city":"Salzgitter",
    "sg:phone":"+49 5341/81740",
    "sg:postcode":"38259",
    "sg:province":"Niedersachsen",
    "wof:name":"Obi Heimwerkermarkt Gmbh & Co. Salzgitter Kg",
    "wof:placetype":"venue"
},
  "geometry": {"coordinates":[10.3805570602,52.0584487915],"type":"Point"}
}