{
  "type": "Feature",
  "properties": {
    "iso:country":"DE",
    "sg:address":"Kelterdell 5",
    "sg:city":"Echternacherbr\u00fcck",
    "sg:phone":"+49 6525/425",
    "sg:postcode":"54668",
    "sg:province":"Rheinland-Pfalz",
    "wof:name":"Erwin Und Irene Thiex",
    "wof:placetype":"venue"
},
  "geometry": {"coordinates":[6.4335827827,49.8154945374],"type":"Point"}
}