{
  "type": "Feature",
  "properties": {
    "iso:country":"DE",
    "sg:address":"Niedere Str. 50",
    "sg:city":"Villingen-Schwenningen",
    "sg:phone":"+49 7721/24870",
    "sg:postcode":"78050",
    "sg:province":"Baden-W\u00fcrttemberg",
    "wof:name":"Conditorei Cafe R\u00f6sch Gmbh",
    "wof:placetype":"venue"
},
  "geometry": {"coordinates":[8.4604349136,48.057762146],"type":"Point"}
}