{
  "type": "Feature",
  "properties": {
    "iso:country":"DE",
    "sg:address":"Albstr. 46",
    "sg:city":"Esslingen",
    "sg:phone":"+49 711/3454989",
    "sg:postcode":"73734",
    "sg:province":"Baden-W\u00fcrttemberg",
    "wof:name":"Dieter Pfitzner",
    "wof:placetype":"venue"
},
  "geometry": {"coordinates":[9.3170690536,48.7175064087],"type":"Point"}
}