{
  "type": "Feature",
  "properties": {
    "iso:country":"DE",
    "sg:address":"Bahnhofstr. 74",
    "sg:city":"Twistringen",
    "sg:phone":"+49 4243/2126",
    "sg:postcode":"27239",
    "sg:province":"Niedersachsen",
    "wof:name":"S. Kramer",
    "wof:placetype":"venue"
},
  "geometry": {"coordinates":[8.6448097229,52.7947006226],"type":"Point"}
}