{
  "type": "Feature",
  "properties": {
    "iso:country":"DE",
    "sg:address":"Jakob-Hammel-Str. 3",
    "sg:city":"Worms",
    "sg:phone":"+49 6242/911849",
    "sg:postcode":"67550",
    "sg:province":"Rheinland-Pfalz",
    "wof:name":"L\u00f6wenherz Gmbh",
    "wof:placetype":"venue"
},
  "geometry": {"coordinates":[8.3514966965,49.7076568604],"type":"Point"}
}