{
  "type": "Feature",
  "properties": {
    "iso:country":"DE",
    "sg:address":"Hauptstr. 18",
    "sg:city":"Dautphetal",
    "sg:phone":"+49 6466/7949",
    "sg:postcode":"35232",
    "sg:province":"Hessen",
    "wof:name":"Bernhardt Bedachung E. K.",
    "wof:placetype":"venue"
},
  "geometry": {"coordinates":[8.545133,50.859226],"type":"Point"}
}