{
  "type": "Feature",
  "properties": {
    "iso:country":"DE",
    "sg:address":"Lange Str. 47",
    "sg:city":"Tangerm\u00fcnde",
    "sg:phone":"+49 39322/9870",
    "sg:postcode":"39590",
    "sg:province":"Sachsen-Anhalt",
    "wof:name":"Hotel Stars",
    "wof:placetype":"venue"
},
  "geometry": {"coordinates":[11.9728441238,52.5422821045],"type":"Point"}
}