{
  "type": "Feature",
  "properties": {
    "iso:country":"DE",
    "sg:address":"Creidlitzer Str. 8",
    "sg:city":"Ahorn",
    "sg:phone":"+49 9561/26622",
    "sg:postcode":"96482",
    "sg:province":"Bayern",
    "wof:name":"Erfi Produktions- Gmbh & Co. Kg",
    "wof:placetype":"venue"
},
  "geometry": {"coordinates":[10.9694795609,50.2317886353],"type":"Point"}
}