{
  "type": "Feature",
  "properties": {
    "iso:country":"DE",
    "sg:address":"luecherstr. 22",
    "sg:city":"Kiel",
    "sg:phone":"+49 431/8066114",
    "sg:postcode":"24105",
    "sg:province":"Schleswig-Holstein",
    "wof:name":"Wilhelm&schlierf Gbr",
    "wof:placetype":"venue"
},
  "geometry": {"coordinates":[10.1360902786,54.3445777893],"type":"Point"}
}