{
  "type": "Feature",
  "properties": {
    "iso:country":"DE",
    "sg:address":"Am Sand 34",
    "sg:city":"Dipperz",
    "sg:phone":"+49 6657/6303",
    "sg:postcode":"36160",
    "sg:province":"Hessen",
    "wof:name":"Harald Baier",
    "wof:placetype":"venue"
},
  "geometry": {"coordinates":[9.828513,50.526073],"type":"Point"}
}