{
  "type": "Feature",
  "properties": {
    "iso:country":"DE",
    "sg:address":"Lindenstr. 40",
    "sg:city":"Bedburg",
    "sg:phone":"+49 2272/81070",
    "sg:postcode":"50181",
    "sg:province":"Nordrhein-Westfalen",
    "wof:name":"Nischik & Frielingsdorf Gmbh",
    "wof:placetype":"venue"
},
  "geometry": {"coordinates":[6.5742368698,50.9936141968],"type":"Point"}
}