{
  "type": "Feature",
  "properties": {
    "iso:country":"DE",
    "sg:address":"Winterfeldtstr. 51",
    "sg:city":"Berlin",
    "sg:phone":"+49 30/2519203",
    "sg:postcode":"10781",
    "sg:province":"Berlin",
    "wof:name":"Bibliophiles Antiquariat Mertens & Pomplun",
    "wof:placetype":"venue"
},
  "geometry": {"coordinates":[13.352864,52.496769],"type":"Point"}
}