{
  "type": "Feature",
  "properties": {
    "iso:country":"DE",
    "sg:address":"Heinrich-Fuchs-Str. 5",
    "sg:city":"Heidelberg",
    "sg:phone":"+49 6221/375328",
    "sg:postcode":"69126",
    "sg:province":"Baden-W\u00fcrttemberg",
    "wof:name":"Weber",
    "wof:placetype":"venue"
},
  "geometry": {"coordinates":[8.6867027283,49.3799362183],"type":"Point"}
}