{
  "type": "Feature",
  "properties": {
    "iso:country":"DE",
    "sg:address":"Im Antsee 13",
    "sg:city":"Gro\u00df-Gerau",
    "sg:phone":"+49 6152/81321",
    "sg:postcode":"64521",
    "sg:province":"Hessen",
    "wof:name":"Maik Diergardt",
    "wof:placetype":"venue"
},
  "geometry": {"coordinates":[8.4963588715,49.9324836731],"type":"Point"}
}