{
  "type": "Feature",
  "properties": {
    "iso:country":"DE",
    "sg:address":"St.-Anton-Str. 31",
    "sg:city":"Friedberg",
    "sg:phone":"+49 821/783337",
    "sg:postcode":"86316",
    "sg:province":"Bayern",
    "wof:name":"Marcus Rabold",
    "wof:placetype":"venue"
},
  "geometry": {"coordinates":[10.974122,48.39003],"type":"Point"}
}