{
  "type": "Feature",
  "properties": {
    "iso:country":"DE",
    "sg:address":"Im Tannenbusch 1",
    "sg:city":"Essen",
    "sg:phone":"+49 201/403144",
    "sg:postcode":"45239",
    "sg:province":"Nordrhein-Westfalen",
    "wof:name":"Wilhelm Lindemann",
    "wof:placetype":"venue"
},
  "geometry": {"coordinates":[7.020936,51.372543],"type":"Point"}
}