{
  "type": "Feature",
  "properties": {
    "iso:country":"DE",
    "sg:address":"Neumarkt 2",
    "sg:city":"Duisburg",
    "sg:phone":"+49 203/872741",
    "sg:postcode":"47119",
    "sg:province":"Nordrhein-Westfalen",
    "wof:name":"Aktas",
    "wof:placetype":"venue"
},
  "geometry": {"coordinates":[6.731749,51.45409],"type":"Point"}
}