{
  "type": "Feature",
  "properties": {
    "iso:country":"DE",
    "sg:address":"Falltorstr. 9",
    "sg:city":"M\u00f6ssingen",
    "sg:phone":"+49 7473/3620",
    "sg:postcode":"72116",
    "sg:province":"Baden-W\u00fcrttemberg",
    "wof:name":"Schuhhaus Luz Gmbh",
    "wof:placetype":"venue"
},
  "geometry": {"coordinates":[9.05831,48.406528],"type":"Point"}
}