{
  "type": "Feature",
  "properties": {
    "iso:country":"DE",
    "sg:address":"Rungestr. 16",
    "sg:city":"Dresden",
    "sg:phone":"+49 351/4728735",
    "sg:postcode":"01217",
    "sg:province":"Sachsen",
    "wof:name":"Ute Schreiber",
    "wof:placetype":"venue"
},
  "geometry": {"coordinates":[13.7484769821,51.0261955261],"type":"Point"}
}