{
  "type": "Feature",
  "properties": {
    "iso:country":"DE",
    "sg:address":"Rostocker Str 13",
    "sg:city":"Hockenheim",
    "sg:phone":"+49 6205/94900",
    "sg:postcode":"68766",
    "sg:province":"Baden-W\u00fcrttemberg",
    "wof:name":"Nie\u00dfner-metall Gmbh & Co Kg",
    "wof:placetype":"venue"
},
  "geometry": {"coordinates":[8.5469961166,49.3297195435],"type":"Point"}
}