{
  "type": "Feature",
  "properties": {
    "iso:country":"DE",
    "sg:address":"Donnerstr. 168",
    "sg:city":"Essen",
    "sg:phone":"+49 201/664323",
    "sg:postcode":"45357",
    "sg:province":"Nordrhein-Westfalen",
    "wof:name":"Natursteinverarbeitung Norbert Janke Gesellschaft",
    "wof:placetype":"venue"
},
  "geometry": {"coordinates":[6.936645031,51.4865150452],"type":"Point"}
}