{
  "type": "Feature",
  "properties": {
    "iso:country":"DE",
    "sg:address":"Im Herrngarten 1",
    "sg:city":"Heusenstamm",
    "sg:phone":"+49 6104/2964",
    "sg:postcode":"63150",
    "sg:province":"Hessen",
    "wof:name":"Schlo\u00dfschenke Zu Heusenstamm",
    "wof:placetype":"venue"
},
  "geometry": {"coordinates":[8.8073959351,50.0625419617],"type":"Point"}
}