{
  "type": "Feature",
  "properties": {
    "iso:country":"DE",
    "sg:address":"Heinrich-Kley-Str. 12",
    "sg:city":"M\u00fcnchen",
    "sg:phone":"+49 89/3561880",
    "sg:postcode":"80807",
    "sg:province":"Bayern",
    "wof:name":"Schultheiss",
    "wof:placetype":"venue"
},
  "geometry": {"coordinates":[11.5881,48.179432],"type":"Point"}
}