{
  "type": "Feature",
  "properties": {
    "iso:country":"DE",
    "sg:address":"Leutkircher Str. 30",
    "sg:city":"Berkheim",
    "sg:phone":"+49 8395/94150",
    "sg:postcode":"88450",
    "sg:province":"Baden-W\u00fcrttemberg",
    "wof:name":"Lederwarenfabrik Edmund G\u00d6ppel",
    "wof:placetype":"venue"
},
  "geometry": {"coordinates":[10.087475,48.031311],"type":"Point"}
}