{
  "type": "Feature",
  "properties": {
    "iso:country":"DE",
    "sg:address":"Harburger Str. 18",
    "sg:city":"Hanstedt",
    "sg:phone":"+49 4184/892031",
    "sg:postcode":"21271",
    "sg:province":"Niedersachsen",
    "wof:name":"R. Melms",
    "wof:placetype":"venue"
},
  "geometry": {"coordinates":[10.013084,53.260155],"type":"Point"}
}