{
  "type": "Feature",
  "properties": {
    "iso:country":"DE",
    "sg:address":"M\u00fchlhauser Str. 21",
    "sg:city":"Oberstadion",
    "sg:phone":"+49 7357/91036",
    "sg:postcode":"89613",
    "sg:province":"Baden-W\u00fcrttemberg",
    "wof:name":"Otto Eggert Inh. F. Eggert",
    "wof:placetype":"venue"
},
  "geometry": {"coordinates":[9.6928901672,48.1865005493],"type":"Point"}
}