{
  "type": "Feature",
  "properties": {
    "iso:country":"DE",
    "sg:address":"Leitenm\u00fchle 40",
    "sg:city":"Hauzenberg",
    "sg:phone":"+49 8586/1035",
    "sg:postcode":"94051",
    "sg:province":"Bayern",
    "wof:name":"Josef Lenz",
    "wof:placetype":"venue"
},
  "geometry": {"coordinates":[13.5903530121,48.6595458984],"type":"Point"}
}