{
  "type": "Feature",
  "properties": {
    "iso:country":"DE",
    "sg:address":"Echemer Str. 2",
    "sg:city":"Scharnebeck",
    "sg:phone":"+49 4136/7189",
    "sg:postcode":"21379",
    "sg:province":"Niedersachsen",
    "wof:name":"Wilhelm Harten",
    "wof:placetype":"venue"
},
  "geometry": {"coordinates":[10.5082559586,53.2937011719],"type":"Point"}
}