{
  "type": "Feature",
  "properties": {
    "iso:country":"DE",
    "sg:address":"Grubenstr. 6 -8",
    "sg:city":"Heiligenhaus",
    "sg:phone":"+49 4920/5691401",
    "sg:postcode":"42579",
    "sg:province":"Nordrhein-Westfalen",
    "wof:name":"Dgth Druckgusstechnik Heiligenhaus Gmbh",
    "wof:placetype":"venue"
},
  "geometry": {"coordinates":[6.951019,51.329605],"type":"Point"}
}