{
  "type": "Feature",
  "properties": {
    "iso:country":"DE",
    "sg:address":"Jahnstr. 21",
    "sg:city":"Nidderau",
    "sg:phone":"+49 6187/27346",
    "sg:postcode":"61130",
    "sg:province":"Hessen",
    "wof:name":"Bundeskegelbahnen",
    "wof:placetype":"venue"
},
  "geometry": {"coordinates":[8.901881218,50.2234115601],"type":"Point"}
}