{
  "type": "Feature",
  "properties": {
    "iso:country":"DE",
    "sg:address":"Gartenstr. 4",
    "sg:city":"Kandel",
    "sg:phone":"+49 7275/5014",
    "sg:postcode":"76870",
    "sg:province":"Rheinland-Pfalz",
    "wof:name":"Ingrid Hoffmann",
    "wof:placetype":"venue"
},
  "geometry": {"coordinates":[8.19728,49.081825],"type":"Point"}
}