{
  "type": "Feature",
  "properties": {
    "iso:country":"DE",
    "sg:address":"Gai\u00dfacher Str. 42",
    "sg:city":"Bad T\u00f6lz",
    "sg:phone":"+49 8041/2767",
    "sg:postcode":"83646",
    "sg:province":"Bayern",
    "wof:name":"Ehrmann Steuerberatungs Gmbh",
    "wof:placetype":"venue"
},
  "geometry": {"coordinates":[11.569899559,47.7574310303],"type":"Point"}
}