{
  "type": "Feature",
  "properties": {
    "iso:country":"DE",
    "sg:address":"Honiggasse 3",
    "sg:city":"Horrweiler",
    "sg:phone":"+49 6727/315",
    "sg:postcode":"55457",
    "sg:province":"Rheinland-Pfalz",
    "wof:name":"Heinz Friedrich Kost",
    "wof:placetype":"venue"
},
  "geometry": {"coordinates":[7.9638018608,49.8984603882],"type":"Point"}
}