{
  "type": "Feature",
  "properties": {
    "iso:country":"DE",
    "sg:address":"Gartenstr. 9",
    "sg:city":"Altenthann",
    "sg:phone":"+49 9408/348",
    "sg:postcode":"93177",
    "sg:province":"Bayern",
    "wof:name":"Karl Aschenbrenner",
    "wof:placetype":"venue"
},
  "geometry": {"coordinates":[12.300632,49.092628],"type":"Point"}
}