{
  "type": "Feature",
  "properties": {
    "iso:country":"DE",
    "sg:address":"Kreypauer Str. 4",
    "sg:city":"Leuna",
    "sg:phone":"+49 3461/811138",
    "sg:postcode":"06237",
    "sg:province":"Sachsen-Anhalt",
    "wof:name":"Ursula Schwalbe Agentur",
    "wof:placetype":"venue"
},
  "geometry": {"coordinates":[12.0340328217,51.3219413757],"type":"Point"}
}