{
  "type": "Feature",
  "properties": {
    "iso:country":"DE",
    "sg:address":"Str\u00fcmpfelbacher Str. 17",
    "sg:city":"Weinstadt",
    "sg:phone":"+49 7151/600096",
    "sg:postcode":"71384",
    "sg:province":"Baden-W\u00fcrttemberg",
    "wof:name":"Cafe Mack",
    "wof:placetype":"venue"
},
  "geometry": {"coordinates":[9.3659,48.812901],"type":"Point"}
}