{
  "type": "Feature",
  "properties": {
    "iso:country":"DE",
    "sg:address":"Carl-Zeiss-Str 65",
    "sg:city":"G\u00fctersloh",
    "sg:phone":"+49 5241/966120",
    "sg:postcode":"33334",
    "sg:province":"Nordrhein-Westfalen",
    "wof:name":"Cats Ges. F\u00fcr Techn. Dv-anwendungen Mbh",
    "wof:placetype":"venue"
},
  "geometry": {"coordinates":[8.417627,51.929382],"type":"Point"}
}