{
  "type": "Feature",
  "properties": {
    "iso:country":"DE",
    "sg:address":"Sendlinger Str. 22",
    "sg:city":"M\u00fcnchen",
    "sg:phone":"+49 89/264040",
    "sg:postcode":"80331",
    "sg:province":"Bayern",
    "wof:name":"Ludwig Und J\u00e4ger Rechtsanw\u00e4lte",
    "wof:placetype":"venue"
},
  "geometry": {"coordinates":[11.5704078674,48.1354827881],"type":"Point"}
}