{
  "type": "Feature",
  "properties": {
    "iso:country":"DE",
    "sg:address":"Am Kr\u00f6kentor 1a",
    "sg:city":"Magdeburg",
    "sg:phone":"+49 391/5611536",
    "sg:postcode":"39104",
    "sg:province":"Sachsen-Anhalt",
    "wof:name":"Annette Tetzlaff Praxis F\u00fcr Physiotherapie",
    "wof:placetype":"venue"
},
  "geometry": {"coordinates":[11.637223,52.137775],"type":"Point"}
}