{
  "type": "Feature",
  "properties": {
    "iso:country":"DE",
    "sg:address":"Ehinger-Tor-Str. 17",
    "sg:city":"Biberach",
    "sg:phone":"+49 7351/6542",
    "sg:postcode":"88400",
    "sg:province":"Baden-W\u00fcrttemberg",
    "wof:name":"Daniel Beck",
    "wof:placetype":"venue"
},
  "geometry": {"coordinates":[9.7880401611,48.1001243591],"type":"Point"}
}