{
  "type": "Feature",
  "properties": {
    "iso:country":"DE",
    "sg:address":"Reichpietschufer 50",
    "sg:city":"Berlin",
    "sg:phone":"+49 30/69041",
    "sg:postcode":"10785",
    "sg:province":"Berlin",
    "wof:name":"Intern. Institut F. Management Und Verw. D.",
    "wof:placetype":"venue"
},
  "geometry": {"coordinates":[13.3650913239,52.5063781738],"type":"Point"}
}