{
  "type": "Feature",
  "properties": {
    "iso:country":"DE",
    "sg:address":"Lausitzer Str. 16",
    "sg:city":"Ludwigshafen",
    "sg:phone":"+49 621/551077",
    "sg:postcode":"67065",
    "sg:province":"Rheinland-Pfalz",
    "wof:name":"Armburster Immobilienmakler",
    "wof:placetype":"venue"
},
  "geometry": {"coordinates":[8.4075317383,49.4526023865],"type":"Point"}
}