{
  "type": "Feature",
  "properties": {
    "iso:country":"DE",
    "sg:address":"Eimsb\u00fctteler Chaussee 47",
    "sg:city":"Hamburg",
    "sg:phone":"+49 40/437888",
    "sg:postcode":"20259",
    "sg:province":"Hamburg",
    "wof:name":"Braun Immobilien",
    "wof:placetype":"venue"
},
  "geometry": {"coordinates":[9.9564409256,53.5675735474],"type":"Point"}
}