{
  "type": "Feature",
  "properties": {
    "iso:country":"DE",
    "sg:address":"Ellernbruch 18",
    "sg:city":"Braunschweig",
    "sg:phone":"+49 531/515202",
    "sg:postcode":"38112",
    "sg:province":"Niedersachsen",
    "wof:name":"Andrea Stolz Tier\u00e4rtzin",
    "wof:placetype":"venue"
},
  "geometry": {"coordinates":[10.4446592331,52.3061676025],"type":"Point"}
}