{
  "type": "Feature",
  "properties": {
    "iso:country":"DE",
    "sg:address":"Almsstr. 50",
    "sg:city":"Hildesheim",
    "sg:postcode":"31134",
    "sg:province":"Niedersachsen",
    "wof:name":"City-pavillon Gmbh",
    "wof:placetype":"venue"
},
  "geometry": {"coordinates":[9.950584,52.153168],"type":"Point"}
}