{
  "type": "Feature",
  "properties": {
    "iso:country":"DE",
    "sg:address":"Scheibenacker 1",
    "sg:city":"Berg",
    "sg:phone":"+49 9293/8080",
    "sg:postcode":"95180",
    "sg:province":"Bayern",
    "wof:name":"Lauterbach Speditions-gmbh",
    "wof:placetype":"venue"
},
  "geometry": {"coordinates":[11.7851581573,50.3730354309],"type":"Point"}
}