{
  "type": "Feature",
  "properties": {
    "iso:country":"DE",
    "sg:address":"Schl\u00f6delsweg 111",
    "sg:city":"Wedel",
    "sg:phone":"+49 4103/919226",
    "sg:postcode":"22880",
    "sg:province":"Schleswig-Holstein",
    "wof:name":"Richard M\u00f6ller Garten- Und",
    "wof:placetype":"venue"
},
  "geometry": {"coordinates":[9.72494,53.600578],"type":"Point"}
}