{
  "type": "Feature",
  "properties": {
    "iso:country":"DE",
    "sg:address":"Bahnhofstr. 1",
    "sg:city":"Ro\u00dfwein",
    "sg:phone":"+49 34322/42280",
    "sg:postcode":"04741",
    "sg:province":"Sachsen",
    "wof:name":"Maler Gmbh",
    "wof:placetype":"venue"
},
  "geometry": {"coordinates":[13.182608,51.061913],"type":"Point"}
}