{
  "type": "Feature",
  "properties": {
    "iso:country":"DE",
    "sg:address":"Barkhovenallee 1",
    "sg:city":"Essen",
    "sg:phone":"+49 201/40880",
    "sg:postcode":"45239",
    "sg:province":"Nordrhein-Westfalen",
    "wof:name":"Intema Ges. F\u00fcr Technischen Handel Und Marktberatung Mbh",
    "wof:placetype":"venue"
},
  "geometry": {"coordinates":[7.0066299438,51.37733078],"type":"Point"}
}