{
  "type": "Feature",
  "properties": {
    "iso:country":"DE",
    "sg:address":"Eitzinger Str.",
    "sg:city":"Stephanskirchen",
    "sg:phone":"+49 8036/1213",
    "sg:postcode":"83071",
    "sg:province":"Bayern",
    "wof:name":"Peter Holzner Gmbh",
    "wof:placetype":"venue"
},
  "geometry": {"coordinates":[12.188684,47.852844],"type":"Point"}
}