{
  "type": "Feature",
  "properties": {
    "iso:country":"DE",
    "sg:address":"Nordh\u00e4user Str. 13 a",
    "sg:city":"Hasselfelde",
    "sg:phone":"+49 39459/76003",
    "sg:postcode":"38899",
    "sg:province":"Sachsen-Anhalt",
    "wof:name":"H. Nelius",
    "wof:placetype":"venue"
},
  "geometry": {"coordinates":[10.847254,51.689964],"type":"Point"}
}