{
  "type": "Feature",
  "properties": {
    "iso:country":"DE",
    "sg:address":"Hauptstr. 24",
    "sg:city":"Egglham",
    "sg:phone":"+49 8543/1565",
    "sg:postcode":"84385",
    "sg:province":"Bayern",
    "wof:name":"Stefan Weber",
    "wof:placetype":"venue"
},
  "geometry": {"coordinates":[13.055989,48.530121],"type":"Point"}
}