{
  "type": "Feature",
  "properties": {
    "iso:country":"DE",
    "sg:city":"K\u00f6ln",
    "sg:phone":"+49 221/733030",
    "sg:postcode":"50829",
    "sg:province":"Nordrhein-Westfalen",
    "wof:name":"Au-pair Vermittlung Hambloch",
    "wof:placetype":"venue"
},
  "geometry": {"coordinates":[6.88093,50.955635],"type":"Point"}
}