{
  "type": "Feature",
  "properties": {
    "iso:country":"DE",
    "sg:address":"Neckarstr. 3",
    "sg:city":"Plochingen",
    "sg:postcode":"73207",
    "sg:province":"Baden-W\u00fcrttemberg",
    "wof:name":"Extra",
    "wof:placetype":"venue"
},
  "geometry": {"coordinates":[9.4156084061,48.7099266052],"type":"Point"}
}