{
  "type": "Feature",
  "properties": {
    "iso:country":"DE",
    "sg:address":"Poppenb\u00fctteler Bogen 17a",
    "sg:city":"Hamburg",
    "sg:phone":"+49 40/6067440",
    "sg:postcode":"22399",
    "sg:province":"Hamburg",
    "wof:name":"Savino Del Bene Gmbh",
    "wof:placetype":"venue"
},
  "geometry": {"coordinates":[10.072603,53.670868],"type":"Point"}
}