{
  "type": "Feature",
  "properties": {
    "iso:country":"DE",
    "sg:address":"84378",
    "sg:city":"Dietersburg",
    "sg:postcode":"84378",
    "sg:province":"Bayern",
    "wof:name":"Raiffeisenbank Baumgarten-n\u00f6ham Eg",
    "wof:placetype":"venue"
},
  "geometry": {"coordinates":[12.928496,48.493813],"type":"Point"}
}