{
  "type": "Feature",
  "properties": {
    "iso:country":"DE",
    "sg:address":"Hauptstr. 26",
    "sg:city":"K\u00fcllstedt",
    "sg:phone":"+49 36075/64718",
    "sg:postcode":"37359",
    "sg:province":"Th\u00fcringen",
    "wof:name":"Gastst\u00e4tte Zur Blume",
    "wof:placetype":"venue"
},
  "geometry": {"coordinates":[10.279045105,51.2762527466],"type":"Point"}
}