{
  "type": "Feature",
  "properties": {
    "iso:country":"DE",
    "sg:address":"Heerdter Landstr. 64",
    "sg:city":"D\u00fcsseldorf",
    "sg:phone":"+49 211/501361",
    "sg:postcode":"40549",
    "sg:province":"Nordrhein-Westfalen",
    "wof:name":"Hermann Lamberty",
    "wof:placetype":"venue"
},
  "geometry": {"coordinates":[6.714873,51.232128],"type":"Point"}
}