{
  "type": "Feature",
  "properties": {
    "iso:country":"DE",
    "sg:address":"Wilhelmstr. 1",
    "sg:city":"Juist",
    "sg:phone":"+49 4935/208",
    "sg:postcode":"26571",
    "sg:province":"Niedersachsen",
    "wof:name":"Hotel Westend",
    "wof:placetype":"venue"
},
  "geometry": {"coordinates":[7.0024991035,53.6768188477],"type":"Point"}
}