{
  "type": "Feature",
  "properties": {
    "iso:country":"DE",
    "sg:address":"Brauhausstr. 2",
    "sg:city":"Herzberg",
    "sg:phone":"+49 209/3609249",
    "sg:postcode":"37412",
    "sg:province":"Niedersachsen",
    "wof:name":"Commerzbank Ag",
    "wof:placetype":"venue"
},
  "geometry": {"coordinates":[7.054961,51.576614],"type":"Point"}
}