{
  "type": "Feature",
  "properties": {
    "iso:country":"DE",
    "sg:address":"Wonnentaler Weg 18",
    "sg:city":"Kenzingen",
    "sg:phone":"+49 7644/4250",
    "sg:postcode":"79341",
    "sg:province":"Baden-W\u00fcrttemberg",
    "wof:name":"H. Melchin Ingenieur",
    "wof:placetype":"venue"
},
  "geometry": {"coordinates":[7.7681899071,48.186870575],"type":"Point"}
}