{
  "type": "Feature",
  "properties": {
    "iso:country":"DE",
    "sg:address":"Steinheide",
    "sg:city":"Kerpen",
    "sg:phone":"+49 2275/911550",
    "sg:postcode":"50170",
    "sg:province":"Nordrhein-Westfalen",
    "wof:name":"Ksn Motorsporthandel Peter Kaiser",
    "wof:placetype":"venue"
},
  "geometry": {"coordinates":[6.6104698181,50.8913497925],"type":"Point"}
}