{
  "type": "Feature",
  "properties": {
    "iso:country":"DE",
    "sg:address":"Hansering 26",
    "sg:city":"Breckerfeld",
    "sg:phone":"+49 2338/2187",
    "sg:postcode":"58339",
    "sg:province":"Nordrhein-Westfalen",
    "wof:name":"Bernd Sander Ingenieur",
    "wof:placetype":"venue"
},
  "geometry": {"coordinates":[7.4644608498,51.2575416565],"type":"Point"}
}