{
  "type": "Feature",
  "properties": {
    "iso:country":"DE",
    "sg:address":"Trierer Str. 2",
    "sg:city":"Losheim",
    "sg:phone":"+49 6872/2494",
    "sg:postcode":"66679",
    "sg:province":"Saarland",
    "wof:name":"Pauline Oswald",
    "wof:placetype":"venue"
},
  "geometry": {"coordinates":[6.7777609825,49.5341377258],"type":"Point"}
}