{
  "type": "Feature",
  "properties": {
    "iso:country":"DE",
    "sg:address":"Beguinenstr. 41",
    "sg:city":"Wesel",
    "sg:phone":"+49 281/22262",
    "sg:postcode":"46483",
    "sg:province":"Nordrhein-Westfalen",
    "wof:name":"C. Mecking",
    "wof:placetype":"venue"
},
  "geometry": {"coordinates":[6.6203999519,51.6585083008],"type":"Point"}
}