{
  "type": "Feature",
  "properties": {
    "iso:country":"DE",
    "sg:address":"Wiesengrund 5",
    "sg:city":"Storkow",
    "sg:postcode":"15859",
    "sg:province":"Brandenburg",
    "wof:name":"Wiesengrund Verm\u00f6gens- Verwaltung Ohg",
    "wof:placetype":"venue"
},
  "geometry": {"coordinates":[13.940779686,52.2537307739],"type":"Point"}
}