{
  "type": "Feature",
  "properties": {
    "iso:country":"DE",
    "sg:address":"Schwarzwaldstr. 1",
    "sg:city":"Haslach",
    "sg:phone":"+49 7832/3021",
    "sg:postcode":"77716",
    "sg:province":"Baden-W\u00fcrttemberg",
    "wof:name":"Raiffeisen Zentralgenossenschaft Eg",
    "wof:placetype":"venue"
},
  "geometry": {"coordinates":[8.110975,48.287071],"type":"Point"}
}