{
  "type": "Feature",
  "properties": {
    "iso:country":"DE",
    "sg:address":"Augustenstr. 53",
    "sg:city":"M\u00fcnchen",
    "sg:phone":"+49 89/522517",
    "sg:postcode":"80333",
    "sg:province":"Bayern",
    "wof:name":"Peter Erben",
    "wof:placetype":"venue"
},
  "geometry": {"coordinates":[11.562795639,48.1492538452],"type":"Point"}
}