{
  "type": "Feature",
  "properties": {
    "iso:country":"DE",
    "sg:address":"Bahnhofstr. 44",
    "sg:city":"Treuchtlingen",
    "sg:phone":"+49 9142/3714",
    "sg:postcode":"91757",
    "sg:province":"Bayern",
    "wof:name":"Hans-j\u00fcrgen Und Gabi Mitzler",
    "wof:placetype":"venue"
},
  "geometry": {"coordinates":[10.88457,48.987251],"type":"Point"}
}