{
  "type": "Feature",
  "properties": {
    "iso:country":"DE",
    "sg:address":"Tuchmarkt 4",
    "sg:city":"Zeulenroda",
    "sg:postcode":"07937",
    "sg:province":"Th\u00fcringen",
    "wof:name":"Karl Zaumsegel",
    "wof:placetype":"venue"
},
  "geometry": {"coordinates":[11.980068,50.649292],"type":"Point"}
}