{
  "type": "Feature",
  "properties": {
    "iso:country":"DE",
    "sg:address":"Lappersdorfer Str. 23",
    "sg:city":"Regensburg",
    "sg:phone":"+49 941/82728",
    "sg:postcode":"93059",
    "sg:province":"Bayern",
    "wof:name":"Albert B\u00e4uml",
    "wof:placetype":"venue"
},
  "geometry": {"coordinates":[12.09811,49.032387],"type":"Point"}
}