{
  "type": "Feature",
  "properties": {
    "iso:country":"DE",
    "sg:address":"Homberger Str. 27",
    "sg:city":"Duisburg",
    "sg:phone":"+49 2065/60021",
    "sg:postcode":"47228",
    "sg:province":"Nordrhein-Westfalen",
    "wof:name":"Einrichtungshaus Willi T\u00f6llner",
    "wof:placetype":"venue"
},
  "geometry": {"coordinates":[6.7110657692,51.4195709229],"type":"Point"}
}