{
  "type": "Feature",
  "properties": {
    "iso:country":"DE",
    "sg:address":"Pilgerweg 8",
    "sg:city":"Hattingen",
    "sg:phone":"+49 2324/26327",
    "sg:postcode":"45525",
    "sg:province":"Nordrhein-Westfalen",
    "wof:name":"Isa International Security Academy Ev",
    "wof:placetype":"venue"
},
  "geometry": {"coordinates":[7.1873369217,51.3901786804],"type":"Point"}
}