{
  "type": "Feature",
  "properties": {
    "iso:country":"DE",
    "sg:address":"B\u00fcrgerm.-Rabus-Str. 16",
    "sg:city":"Memmingerberg",
    "sg:phone":"+49 8331/3820",
    "sg:postcode":"87766",
    "sg:province":"Bayern",
    "wof:name":"Gerhard Metzeler",
    "wof:placetype":"venue"
},
  "geometry": {"coordinates":[10.210952,47.990376],"type":"Point"}
}