{
  "type": "Feature",
  "properties": {
    "iso:country":"DE",
    "sg:address":"Ringstr. 15",
    "sg:city":"Obernzenn",
    "sg:postcode":"91619",
    "sg:province":"Bayern",
    "wof:name":"Fmw-wirtschaftsberatung Gmbh",
    "wof:placetype":"venue"
},
  "geometry": {"coordinates":[10.4568920135,49.4521789551],"type":"Point"}
}