{
  "type": "Feature",
  "properties": {
    "iso:country":"DE",
    "sg:address":"Reitzensteinstr. 12",
    "sg:city":"Recklinghausen",
    "sg:phone":"+49 2361/900710",
    "sg:postcode":"45657",
    "sg:province":"Nordrhein-Westfalen",
    "wof:name":"Klaus Beckmann Rechtsanwalt",
    "wof:placetype":"venue"
},
  "geometry": {"coordinates":[7.1919841766,51.6162643433],"type":"Point"}
}