{
  "type": "Feature",
  "properties": {
    "iso:country":"DE",
    "sg:address":"Untere Freitorstr. 2",
    "sg:city":"B\u00f6singen",
    "sg:phone":"+49 7404/381",
    "sg:postcode":"78662",
    "sg:province":"Baden-W\u00fcrttemberg",
    "wof:name":"Siegfried Bantle",
    "wof:placetype":"venue"
},
  "geometry": {"coordinates":[8.557389,48.239475],"type":"Point"}
}