{
  "type": "Feature",
  "properties": {
    "iso:country":"DE",
    "sg:address":"Moristeig 38",
    "sg:city":"L\u00fcbeck",
    "sg:phone":"+49 451/494586",
    "sg:postcode":"23556",
    "sg:province":"Schleswig-Holstein",
    "wof:name":"Iris Boeckmann",
    "wof:placetype":"venue"
},
  "geometry": {"coordinates":[10.6391839981,53.8782920837],"type":"Point"}
}