{
  "type": "Feature",
  "properties": {
    "iso:country":"DE",
    "sg:address":"Im Dieck 5",
    "sg:city":"Wassenberg",
    "sg:phone":"+49 2432/5893",
    "sg:postcode":"41849",
    "sg:province":"Nordrhein-Westfalen",
    "wof:name":"Valicek Verwaltungs- Gmbh",
    "wof:placetype":"venue"
},
  "geometry": {"coordinates":[6.1616749763,51.0818214417],"type":"Point"}
}