{
  "type": "Feature",
  "properties": {
    "iso:country":"DE",
    "sg:address":"Marzenbruchstr. 4",
    "sg:city":"Torgelow",
    "sg:phone":"+49 3976/433133",
    "sg:postcode":"17358",
    "sg:province":"Mecklenburg-Vorpommern",
    "wof:name":"Bunge & M\u00dcller",
    "wof:placetype":"venue"
},
  "geometry": {"coordinates":[14.008144,53.63599],"type":"Point"}
}