{
  "type": "Feature",
  "properties": {
    "iso:country":"DE",
    "sg:address":"Wilhelm-Weitling-Str. 23a",
    "sg:city":"Dresden",
    "sg:phone":"+49 351/2013511",
    "sg:postcode":"01259",
    "sg:province":"Sachsen",
    "wof:name":"Walter R\u00fcger",
    "wof:placetype":"venue"
},
  "geometry": {"coordinates":[13.863424,51.005272],"type":"Point"}
}