{
  "type": "Feature",
  "properties": {
    "iso:country":"DE",
    "sg:address":"Schliepm\u00fchlenstr. 23",
    "sg:city":"Duisburg",
    "sg:phone":"+49 203/592905",
    "sg:postcode":"47169",
    "sg:province":"Nordrhein-Westfalen",
    "wof:name":"Martin Haas",
    "wof:placetype":"venue"
},
  "geometry": {"coordinates":[6.7715539932,51.5230560303],"type":"Point"}
}