{
  "type": "Feature",
  "properties": {
    "iso:country":"DE",
    "sg:address":"Provinzialstr. 104",
    "sg:city":"Ensdorf",
    "sg:phone":"+49 6831/5171",
    "sg:postcode":"66806",
    "sg:province":"Saarland",
    "wof:name":"Neckura Versicherungen Joseph Rumpler",
    "wof:placetype":"venue"
},
  "geometry": {"coordinates":[6.7780089378,49.3078613281],"type":"Point"}
}