{
  "type": "Feature",
  "properties": {
    "iso:country":"DE",
    "sg:address":"Peiner Str. 136",
    "sg:city":"Braunschweig",
    "sg:phone":"+49 531/514525",
    "sg:postcode":"38112",
    "sg:province":"Niedersachsen",
    "wof:name":"Hotel Deutsches Haus",
    "wof:placetype":"venue"
},
  "geometry": {"coordinates":[10.4405107498,52.303943634],"type":"Point"}
}