{
  "type": "Feature",
  "properties": {
    "iso:country":"DE",
    "sg:city":"Bad S\u00e4ckingen",
    "sg:postcode":"79713",
    "sg:province":"Baden-W\u00fcrttemberg",
    "wof:name":"Hospa Holz- Und Span- Plattenhandel Gmbh",
    "wof:placetype":"venue"
},
  "geometry": {"coordinates":[7.94906,47.555256],"type":"Point"}
}