{
  "type": "Feature",
  "properties": {
    "iso:country":"DE",
    "sg:address":"F\u00fcrther Str. 234",
    "sg:city":"N\u00fcrnberg",
    "sg:phone":"+49 911/311300",
    "sg:postcode":"90429",
    "sg:province":"Bayern",
    "wof:name":"Kafkas",
    "wof:placetype":"venue"
},
  "geometry": {"coordinates":[11.0315389633,49.45911026],"type":"Point"}
}