{
  "type": "Feature",
  "properties": {
    "iso:country":"DE",
    "sg:address":"Norderstr. 76",
    "sg:city":"Flensburg",
    "sg:phone":"+49 461/144080",
    "sg:postcode":"24939",
    "sg:province":"Schleswig-Holstein",
    "wof:name":"Dansk Generalsekretariat",
    "wof:placetype":"venue"
},
  "geometry": {"coordinates":[9.4314260483,54.7931556702],"type":"Point"}
}