{
  "type": "Feature",
  "properties": {
    "iso:country":"DE",
    "sg:address":"Am Windbusch 3",
    "sg:city":"Detmold",
    "sg:phone":"+49 5231/63331",
    "sg:postcode":"32758",
    "sg:province":"Nordrhein-Westfalen",
    "wof:name":"Thyssen Schulte Gmbh",
    "wof:placetype":"venue"
},
  "geometry": {"coordinates":[8.8491764069,51.9544296265],"type":"Point"}
}