{
  "type": "Feature",
  "properties": {
    "iso:country":"DE",
    "sg:address":"Friedrichsh\u00f6he 31",
    "sg:city":"Eilenburg",
    "sg:phone":"+49 3423/602623",
    "sg:postcode":"04838",
    "sg:province":"Sachsen",
    "wof:name":"Dr. Wolfram Gro\u00dfe",
    "wof:placetype":"venue"
},
  "geometry": {"coordinates":[12.624618,51.456429],"type":"Point"}
}