{
  "type": "Feature",
  "properties": {
    "iso:country":"DE",
    "sg:address":"Sportplatzstr. 2",
    "sg:city":"Lauben",
    "sg:postcode":"87761",
    "sg:province":"Bayern",
    "wof:name":"Versicherungsb\u00fcro Lauhues E.k.",
    "wof:placetype":"venue"
},
  "geometry": {"coordinates":[10.287689209,48.0606880188],"type":"Point"}
}