{
  "type": "Feature",
  "properties": {
    "iso:country":"DE",
    "sg:address":"Obergasse 9",
    "sg:city":"Braunfels",
    "sg:phone":"+49 6472/91510",
    "sg:postcode":"35619",
    "sg:province":"Hessen",
    "wof:name":"Richard Weber Gmbh & Co. Kg",
    "wof:placetype":"venue"
},
  "geometry": {"coordinates":[8.402919,50.469006],"type":"Point"}
}