{
  "type": "Feature",
  "properties": {
    "iso:country":"DE",
    "sg:address":"Berggrenze 30",
    "sg:city":"Hettstedt",
    "sg:phone":"+49 3476/812716",
    "sg:postcode":"06333",
    "sg:province":"Sachsen-Anhalt",
    "wof:name":"D. K\u00fchnlenz",
    "wof:placetype":"venue"
},
  "geometry": {"coordinates":[11.513934,51.627331],"type":"Point"}
}