{
  "type": "Feature",
  "properties": {
    "iso:country":"DE",
    "sg:address":"Blasiusstr. 20",
    "sg:city":"D\u00fcsseldorf",
    "sg:phone":"+49 211/305342",
    "sg:postcode":"40221",
    "sg:province":"Nordrhein-Westfalen",
    "wof:name":"Theo K\u00fcpper Jun.",
    "wof:placetype":"venue"
},
  "geometry": {"coordinates":[6.737727,51.207275],"type":"Point"}
}