{
  "type": "Feature",
  "properties": {
    "iso:country":"DE",
    "sg:address":"Germanenstr. 2",
    "sg:city":"Winterlingen",
    "sg:phone":"+49 7577/932000",
    "sg:postcode":"72474",
    "sg:province":"Baden-W\u00fcrttemberg",
    "wof:name":"Mattm\u00fcller Gmbh",
    "wof:placetype":"venue"
},
  "geometry": {"coordinates":[9.1359186172,48.1687316895],"type":"Point"}
}