{
  "type": "Feature",
  "properties": {
    "iso:country":"DE",
    "sg:address":"Heumarkt 3",
    "sg:city":"Eibelstadt",
    "sg:phone":"+49 9303/1237",
    "sg:postcode":"97246",
    "sg:province":"Bayern",
    "wof:name":"Giovanni Spanu",
    "wof:placetype":"venue"
},
  "geometry": {"coordinates":[9.9994211197,49.7248420715],"type":"Point"}
}