{
  "type": "Feature",
  "properties": {
    "iso:country":"DE",
    "sg:address":"Vienenburgerstr. 5",
    "sg:city":"Vienenburg",
    "sg:phone":"+49 5324/6208",
    "sg:postcode":"38690",
    "sg:province":"Niedersachsen",
    "wof:name":"Kubald Klikbedarf",
    "wof:placetype":"venue"
},
  "geometry": {"coordinates":[10.577731,51.957973],"type":"Point"}
}