{
  "type": "Feature",
  "properties": {
    "iso:country":"DE",
    "sg:address":"Am Anfang 2",
    "sg:city":"Rochlitz",
    "sg:phone":"+49 3737/42507",
    "sg:postcode":"09306",
    "sg:province":"Sachsen",
    "wof:name":"Marlies Stein",
    "wof:placetype":"venue"
},
  "geometry": {"coordinates":[12.792643,51.05312],"type":"Point"}
}