{
  "type": "Feature",
  "properties": {
    "iso:country":"DE",
    "sg:address":"Karlstr. 94",
    "sg:city":"Karlsruhe",
    "sg:phone":"+49 721/357757",
    "sg:postcode":"76137",
    "sg:province":"Baden-W\u00fcrttemberg",
    "wof:name":"Verein F\u00fcr Evangelische Heimf\u00fcrsorge E. V.",
    "wof:placetype":"venue"
},
  "geometry": {"coordinates":[8.3938016891,49.0000305176],"type":"Point"}
}