{
  "type": "Feature",
  "properties": {
    "iso:country":"DE",
    "sg:address":"Dammstr. 7",
    "sg:city":"Burgwedel",
    "sg:phone":"+49 5139/895816",
    "sg:postcode":"30938",
    "sg:province":"Niedersachsen",
    "wof:name":"Ambulante Kranken- Und Altenpflege",
    "wof:placetype":"venue"
},
  "geometry": {"coordinates":[9.849672,52.492592],"type":"Point"}
}