{
  "type": "Feature",
  "properties": {
    "iso:country":"DE",
    "sg:address":"Eichenstr. 46",
    "sg:city":"Brunnthal",
    "sg:phone":"+49 8104/7947",
    "sg:postcode":"85649",
    "sg:province":"Bayern",
    "wof:name":"Petra Schmied Anlageberaterin",
    "wof:placetype":"venue"
},
  "geometry": {"coordinates":[11.7053728104,47.9846115112],"type":"Point"}
}