{
  "type": "Feature",
  "properties": {
    "iso:country":"DE",
    "sg:address":"Schlo\u00dfgasse 76",
    "sg:city":"Behringen",
    "sg:phone":"+49 36254/70837",
    "sg:postcode":"99947",
    "sg:province":"Th\u00fcringen",
    "wof:name":"Dieter Drieseberg",
    "wof:placetype":"venue"
},
  "geometry": {"coordinates":[10.647315,51.104912],"type":"Point"}
}