{
  "type": "Feature",
  "properties": {
    "iso:country":"DE",
    "sg:address":"Martin-Luther-Str. 1",
    "sg:city":"Waldbrunn",
    "sg:phone":"+49 6274/302",
    "sg:postcode":"69429",
    "sg:province":"Baden-W\u00fcrttemberg",
    "wof:name":"Ev. Pfarramt Gem. Schollbrunn",
    "wof:placetype":"venue"
},
  "geometry": {"coordinates":[9.0780296326,49.4363021851],"type":"Point"}
}