{
  "type": "Feature",
  "properties": {
    "iso:country":"DE",
    "sg:address":"Holstenwall 13",
    "sg:city":"Hamburg",
    "sg:phone":"+49 40/3480600",
    "sg:postcode":"20355",
    "sg:province":"Hamburg",
    "wof:name":"Restaurant Michelangelo",
    "wof:placetype":"venue"
},
  "geometry": {"coordinates":[9.9765195847,53.5529518127],"type":"Point"}
}