{
  "type": "Feature",
  "properties": {
    "iso:country":"DE",
    "sg:address":"Enzerweis 84",
    "sg:city":"Eichendorf",
    "sg:phone":"+49 9952/2676",
    "sg:postcode":"94428",
    "sg:province":"Bayern",
    "wof:name":"Sport Straubinger -sportkleidung Und Vereinsbedarf",
    "wof:placetype":"venue"
},
  "geometry": {"coordinates":[12.885833,48.629047],"type":"Point"}
}