{
  "type": "Feature",
  "properties": {
    "iso:country":"DE",
    "sg:address":"Schmidtstr. 12",
    "sg:city":"Frankfurt",
    "sg:postcode":"60326",
    "sg:province":"Hessen",
    "wof:name":"Update The Web Ag",
    "wof:placetype":"venue"
},
  "geometry": {"coordinates":[8.618348,50.103729],"type":"Point"}
}