{
  "type": "Feature",
  "properties": {
    "iso:country":"DE",
    "sg:address":"Schlo\u00dfstr. 15",
    "sg:city":"Berlin",
    "sg:phone":"+49 30/3257715",
    "sg:postcode":"14059",
    "sg:province":"Berlin",
    "wof:name":"T. Schwertner Immobilienmakler",
    "wof:placetype":"venue"
},
  "geometry": {"coordinates":[13.2961540222,52.5152893066],"type":"Point"}
}