{
  "type": "Feature",
  "properties": {
    "iso:country":"DE",
    "sg:address":"Mohrenstr. 25",
    "sg:city":"Coburg",
    "sg:phone":"+49 9561/74012",
    "sg:postcode":"96450",
    "sg:province":"Bayern",
    "wof:name":"Eva Grabolus Rechtsanw\u00e4ltin",
    "wof:placetype":"venue"
},
  "geometry": {"coordinates":[10.963760376,50.2608451843],"type":"Point"}
}