{
  "type": "Feature",
  "properties": {
    "iso:country":"DE",
    "sg:address":"Oberf\u00fcrberger Str. 50",
    "sg:city":"F\u00fcrth",
    "sg:phone":"+49 911/772893",
    "sg:postcode":"90768",
    "sg:province":"Bayern",
    "wof:name":"Pferdestadtl",
    "wof:placetype":"venue"
},
  "geometry": {"coordinates":[10.937427,49.469147],"type":"Point"}
}