{
  "type": "Feature",
  "properties": {
    "iso:country":"DE",
    "sg:address":"Rodelandstr. 1",
    "sg:city":"Springe",
    "sg:phone":"+49 5044/4494",
    "sg:postcode":"31832",
    "sg:province":"Niedersachsen",
    "wof:name":"Rudolf Kramer",
    "wof:placetype":"venue"
},
  "geometry": {"coordinates":[9.649842,52.205742],"type":"Point"}
}