{
  "type": "Feature",
  "properties": {
    "iso:country":"DE",
    "sg:address":"Koburger Str. 3",
    "sg:city":"Berlin",
    "sg:phone":"+49 30/78704600",
    "sg:postcode":"10825",
    "sg:province":"Berlin",
    "wof:name":"R\u00fcdiger Gmbh & Co. Kg",
    "wof:placetype":"venue"
},
  "geometry": {"coordinates":[13.3464946747,52.4813346863],"type":"Point"}
}