{
  "type": "Feature",
  "properties": {
    "iso:country":"DE",
    "sg:address":"Ravensburger Str. 9",
    "sg:city":"Bad Waldsee",
    "sg:phone":"+49 7524/6088",
    "sg:postcode":"88339",
    "sg:province":"Baden-W\u00fcrttemberg",
    "wof:name":"Gerhard Keim",
    "wof:placetype":"venue"
},
  "geometry": {"coordinates":[9.754611969,47.9201087952],"type":"Point"}
}