{
  "type": "Feature",
  "properties": {
    "iso:country":"DE",
    "sg:address":"Marthastr. 36",
    "sg:city":"N\u00fcrnberg",
    "sg:phone":"+49 911/5430422",
    "sg:postcode":"90482",
    "sg:province":"Bayern",
    "wof:name":"N. Malter",
    "wof:placetype":"venue"
},
  "geometry": {"coordinates":[11.1140499115,49.4533653259],"type":"Point"}
}