{
  "type": "Feature",
  "properties": {
    "iso:country":"DE",
    "sg:address":"Lintruper Str. 4",
    "sg:city":"Berlin",
    "sg:phone":"+49 30/7435900",
    "sg:postcode":"12305",
    "sg:province":"Berlin",
    "wof:name":"Bernd Lorenz",
    "wof:placetype":"venue"
},
  "geometry": {"coordinates":[13.399649,52.413734],"type":"Point"}
}