{
  "type": "Feature",
  "properties": {
    "iso:country":"DE",
    "sg:address":"K\u00f6lledaer Str. 28",
    "sg:city":"S\u00f6mmerda",
    "sg:phone":"+49 3634/68090",
    "sg:postcode":"99610",
    "sg:province":"Th\u00fcringen",
    "wof:name":"Umweltdienst S\u00f6mmerda Gmbh",
    "wof:placetype":"venue"
},
  "geometry": {"coordinates":[11.125763,51.15868],"type":"Point"}
}