{
  "type": "Feature",
  "properties": {
    "iso:country":"DE",
    "sg:address":"Kanalstr. 28",
    "sg:city":"Frankenthal",
    "sg:phone":"+49 6233/9562",
    "sg:postcode":"67227",
    "sg:province":"Rheinland-Pfalz",
    "wof:name":"D. Schieferdecker Lotterie",
    "wof:placetype":"venue"
},
  "geometry": {"coordinates":[8.351255,49.535027],"type":"Point"}
}