{
  "type": "Feature",
  "properties": {
    "iso:country":"DE",
    "sg:address":"Vastersstr. 27",
    "sg:city":"K\u00f6ln",
    "sg:postcode":"50825",
    "sg:province":"Nordrhein-Westfalen",
    "wof:name":"Compu Count E. K.",
    "wof:placetype":"venue"
},
  "geometry": {"coordinates":[6.9160017967,50.9675674438],"type":"Point"}
}