{
  "type": "Feature",
  "properties": {
    "iso:country":"DE",
    "sg:address":"Gaulsheimer Weg 22",
    "sg:city":"Bingen",
    "sg:phone":"+49 6721/12891",
    "sg:postcode":"55411",
    "sg:province":"Rheinland-Pfalz",
    "wof:name":"Danubia-weinimport Gmbh",
    "wof:placetype":"venue"
},
  "geometry": {"coordinates":[7.9399847984,49.9661102295],"type":"Point"}
}