{
  "type": "Feature",
  "properties": {
    "iso:country":"DE",
    "sg:address":"Hauptstr. 20",
    "sg:city":"Zell",
    "sg:phone":"+49 6542/2821",
    "sg:postcode":"56856",
    "sg:province":"Rheinland-Pfalz",
    "wof:name":"Hugo Treis",
    "wof:placetype":"venue"
},
  "geometry": {"coordinates":[8.1384792328,49.6495018005],"type":"Point"}
}