{
  "type": "Feature",
  "properties": {
    "iso:country":"DE",
    "sg:address":"Niddagaustr. 41a",
    "sg:city":"Frankfurt",
    "sg:phone":"+49 69/97880051",
    "sg:postcode":"60489",
    "sg:province":"Hessen",
    "wof:name":"Herbert Charwat",
    "wof:placetype":"venue"
},
  "geometry": {"coordinates":[8.613312,50.12899],"type":"Point"}
}