{
  "type": "Feature",
  "properties": {
    "iso:country":"DE",
    "sg:address":"Gustav-Heinemann-Ring 230",
    "sg:city":"M\u00fcnchen",
    "sg:postcode":"81739",
    "sg:province":"Bayern",
    "wof:name":"Luxodent Gmbh",
    "wof:placetype":"venue"
},
  "geometry": {"coordinates":[11.6420583725,48.0898895264],"type":"Point"}
}