{
  "type": "Feature",
  "properties": {
    "iso:country":"DE",
    "sg:address":"Rotdornweg 5",
    "sg:city":"Langwedel",
    "sg:phone":"+49 4232/1410",
    "sg:postcode":"27299",
    "sg:province":"Niedersachsen",
    "wof:name":"G. Rotermund",
    "wof:placetype":"venue"
},
  "geometry": {"coordinates":[9.175567,52.980492],"type":"Point"}
}