{
  "type": "Feature",
  "properties": {
    "iso:country":"DE",
    "sg:address":"Paulstr. 9",
    "sg:city":"Berlin",
    "sg:phone":"+49 30/3139909",
    "sg:postcode":"10557",
    "sg:province":"Berlin",
    "wof:name":"Gastst\u00e4tte Schleusenkrug Inh. G. Fistler",
    "wof:placetype":"venue"
},
  "geometry": {"coordinates":[13.3560237885,52.5218887329],"type":"Point"}
}