{
  "type": "Feature",
  "properties": {
    "iso:country":"DE",
    "sg:address":"Br\u00fchl 66",
    "sg:city":"Leipzig",
    "sg:postcode":"04109",
    "sg:province":"Sachsen",
    "wof:name":"Dussmann Ag & Co. Kgaa Zwndl. Leipzig",
    "wof:placetype":"venue"
},
  "geometry": {"coordinates":[12.3791675568,51.3423156738],"type":"Point"}
}