{
  "type": "Feature",
  "properties": {
    "iso:country":"DE",
    "sg:address":"Lindachstr. 11",
    "sg:city":"Reutlingen",
    "sg:phone":"+49 7121/270570",
    "sg:postcode":"72764",
    "sg:province":"Baden-W\u00fcrttemberg",
    "wof:name":"Goldener Schl\u00fcssel",
    "wof:placetype":"venue"
},
  "geometry": {"coordinates":[9.2156839371,48.4877357483],"type":"Point"}
}