{
  "type": "Feature",
  "properties": {
    "iso:country":"DE",
    "sg:address":"Theodor-Schmidt-Str. 37",
    "sg:city":"Ruhland",
    "sg:phone":"+49 35752/2011",
    "sg:postcode":"01945",
    "sg:province":"Brandenburg",
    "wof:name":"Jens-peter Stoyan",
    "wof:placetype":"venue"
},
  "geometry": {"coordinates":[13.8684883118,51.4518699646],"type":"Point"}
}