{
  "type": "Feature",
  "properties": {
    "iso:country":"DE",
    "sg:address":"Oberneulander Heerstr. 40",
    "sg:city":"Bremen",
    "sg:postcode":"28355",
    "sg:province":"Bremen",
    "wof:name":"Comet",
    "wof:placetype":"venue"
},
  "geometry": {"coordinates":[8.9036884308,53.100528717],"type":"Point"}
}