{
  "type": "Feature",
  "properties": {
    "iso:country":"DE",
    "sg:address":"Ellinger Str. 29",
    "sg:city":"Ellingen",
    "sg:phone":"+49 9141/71288",
    "sg:postcode":"91792",
    "sg:province":"Bayern",
    "wof:name":"Alfons Zurwesten",
    "wof:placetype":"venue"
},
  "geometry": {"coordinates":[10.896435,49.071709],"type":"Point"}
}