{
  "type": "Feature",
  "properties": {
    "iso:country":"DE",
    "sg:address":"Am Ziegelbrunn 30",
    "sg:city":"Ha\u00dffurt",
    "sg:phone":"+49 9521/3431",
    "sg:postcode":"97437",
    "sg:province":"Bayern",
    "wof:name":"Baustoffzentrum Menke Gmbh",
    "wof:placetype":"venue"
},
  "geometry": {"coordinates":[10.5174226761,50.0299377441],"type":"Point"}
}