{
  "type": "Feature",
  "properties": {
    "iso:country":"DE",
    "sg:address":"Eschhorn 1",
    "sg:city":"Edewecht",
    "sg:phone":"+49 4405/5457",
    "sg:postcode":"26188",
    "sg:province":"Niedersachsen",
    "wof:name":"Gerold Br\u00fcntjen",
    "wof:placetype":"venue"
},
  "geometry": {"coordinates":[8.003058,53.151726],"type":"Point"}
}