{
  "type": "Feature",
  "properties": {
    "iso:country":"DE",
    "sg:address":"Oesterleystr. 47",
    "sg:city":"Hamburg",
    "sg:postcode":"22587",
    "sg:province":"Hamburg",
    "wof:name":"Liebau Zahntechnik Gmbh",
    "wof:placetype":"venue"
},
  "geometry": {"coordinates":[9.8030080795,53.5631484985],"type":"Point"}
}