{
  "type": "Feature",
  "properties": {
    "iso:country":"DE",
    "sg:address":"Wittenberger Str. 100",
    "sg:city":"Zahna",
    "sg:phone":"+49 34924/20739",
    "sg:postcode":"06895",
    "sg:province":"Sachsen-Anhalt",
    "wof:name":"Waldschenke",
    "wof:placetype":"venue"
},
  "geometry": {"coordinates":[12.768913269,51.904586792],"type":"Point"}
}