{
  "type": "Feature",
  "properties": {
    "iso:country":"DE",
    "sg:address":"Suder\u00f6der Chaussee 34",
    "sg:city":"Quedlinburg",
    "sg:phone":"+49 3946/700447",
    "sg:postcode":"06484",
    "sg:province":"Sachsen-Anhalt",
    "wof:name":"Lobotap",
    "wof:placetype":"venue"
},
  "geometry": {"coordinates":[11.135838,51.76387],"type":"Point"}
}