{
  "type": "Feature",
  "properties": {
    "iso:country":"DE",
    "sg:address":"Friedhofstr. 14",
    "sg:city":"Titisee-Neustadt",
    "sg:phone":"+49 7651/20682",
    "sg:postcode":"79822",
    "sg:province":"Baden-W\u00fcrttemberg",
    "wof:name":"Franz-beckert-halle Mehrzweckhalle",
    "wof:placetype":"venue"
},
  "geometry": {"coordinates":[8.212063,47.91396],"type":"Point"}
}