{
  "type": "Feature",
  "properties": {
    "iso:country":"DE",
    "sg:address":"August-Bebel-Str. 217b",
    "sg:city":"Crottendorf",
    "sg:phone":"+49 37344/8646",
    "sg:postcode":"09474",
    "sg:province":"Sachsen",
    "wof:name":"Karl Gabriel",
    "wof:placetype":"venue"
},
  "geometry": {"coordinates":[12.943907,50.513275],"type":"Point"}
}