{
  "type": "Feature",
  "properties": {
    "iso:country":"DE",
    "sg:address":"Heerstr. 61",
    "sg:city":"Bonn",
    "sg:phone":"+49 228/655451",
    "sg:postcode":"53111",
    "sg:province":"Nordrhein-Westfalen",
    "wof:name":"Josef Noe",
    "wof:placetype":"venue"
},
  "geometry": {"coordinates":[7.093426,50.740005],"type":"Point"}
}