{
  "type": "Feature",
  "properties": {
    "iso:country":"DE",
    "sg:address":"Grindelallee 139",
    "sg:city":"Hamburg",
    "sg:phone":"+49 40/440496",
    "sg:postcode":"20146",
    "sg:province":"Hamburg",
    "wof:name":"R. Mangold",
    "wof:placetype":"venue"
},
  "geometry": {"coordinates":[9.9788074493,53.5700111389],"type":"Point"}
}