{
  "type": "Feature",
  "properties": {
    "iso:country":"DE",
    "sg:address":"Am Rohrbruch 4",
    "sg:city":"Braunschweig",
    "sg:phone":"+49 531/352944",
    "sg:postcode":"38108",
    "sg:province":"Niedersachsen",
    "wof:name":"Klaus Fangmeier Architekt",
    "wof:placetype":"venue"
},
  "geometry": {"coordinates":[10.575672,52.304016],"type":"Point"}
}