{
  "type": "Feature",
  "properties": {
    "iso:country":"DE",
    "sg:address":"Greinstr.",
    "sg:city":"Frechen",
    "sg:phone":"+49 2234/65021",
    "sg:postcode":"50226",
    "sg:province":"Nordrhein-Westfalen",
    "wof:name":"Villeforst Tennis- Und Freizeitpark Verwaltungs Gmbh",
    "wof:placetype":"venue"
},
  "geometry": {"coordinates":[6.7599649429,50.9447631836],"type":"Point"}
}