{
  "type": "Feature",
  "properties": {
    "iso:country":"DE",
    "sg:address":"Engelsbyer Str. 11",
    "sg:city":"Flensburg",
    "sg:phone":"+49 461/65205",
    "sg:postcode":"24943",
    "sg:province":"Schleswig-Holstein",
    "wof:name":"Rehbach Verwaltungs Service Gmbh",
    "wof:placetype":"venue"
},
  "geometry": {"coordinates":[9.4670495987,54.7924194336],"type":"Point"}
}