{
  "type": "Feature",
  "properties": {
    "iso:country":"DE",
    "sg:address":"Grobestr. 31",
    "sg:city":"Siegen",
    "sg:phone":"+49 271/42513",
    "sg:postcode":"57076",
    "sg:province":"Nordrhein-Westfalen",
    "wof:name":"Edgar Ha\u00dfler",
    "wof:placetype":"venue"
},
  "geometry": {"coordinates":[8.03723,50.889339],"type":"Point"}
}