{
  "type": "Feature",
  "properties": {
    "iso:country":"DE",
    "sg:address":"Danziger Str. 50",
    "sg:city":"Karlsbad",
    "sg:phone":"+49 721/615648",
    "sg:postcode":"76307",
    "sg:province":"Baden-W\u00fcrttemberg",
    "wof:name":"Helga Gerisch",
    "wof:placetype":"venue"
},
  "geometry": {"coordinates":[8.533473,48.918663],"type":"Point"}
}