{
  "type": "Feature",
  "properties": {
    "iso:country":"DE",
    "sg:address":"Konradin-Kreutzer-Str. 8",
    "sg:city":"Ettlingen",
    "sg:phone":"+49 7243/29296",
    "sg:postcode":"76275",
    "sg:province":"Baden-W\u00fcrttemberg",
    "wof:name":"Prof. Dr. Harry Thielen Ingenieur",
    "wof:placetype":"venue"
},
  "geometry": {"coordinates":[8.4179058075,48.894405365],"type":"Point"}
}