{
  "type": "Feature",
  "properties": {
    "iso:country":"DE",
    "sg:address":"Karlstr. 46a",
    "sg:city":"Karlsruhe",
    "sg:phone":"+49 721/356306",
    "sg:postcode":"76133",
    "sg:province":"Baden-W\u00fcrttemberg",
    "wof:name":"Aktiv-markt",
    "wof:placetype":"venue"
},
  "geometry": {"coordinates":[8.3942747116,49.0048599243],"type":"Point"}
}