{
  "type": "Feature",
  "properties": {
    "iso:country":"DE",
    "sg:address":"Jevenstedter Str. 51 b",
    "sg:city":"Hamburg",
    "sg:phone":"+49 40/846270",
    "sg:postcode":"22547",
    "sg:province":"Hamburg",
    "wof:name":"B. R. Rutner",
    "wof:placetype":"venue"
},
  "geometry": {"coordinates":[9.8761854172,53.5924987793],"type":"Point"}
}