{
  "type": "Feature",
  "properties": {
    "iso:country":"DE",
    "sg:address":"Wunsiedler Str. 18",
    "sg:city":"Wei\u00dfenstadt",
    "sg:phone":"+49 9253/450",
    "sg:postcode":"95163",
    "sg:province":"Bayern",
    "wof:name":"Erich Ackermann",
    "wof:placetype":"venue"
},
  "geometry": {"coordinates":[11.8864936829,50.1006355286],"type":"Point"}
}