{
  "type": "Feature",
  "properties": {
    "iso:country":"DE",
    "sg:address":"In der Joch 9",
    "sg:city":"Gerolstein",
    "sg:phone":"+49 6591/4874",
    "sg:postcode":"54568",
    "sg:province":"Rheinland-Pfalz",
    "wof:name":"G\u00e4stehaus Margot Bouillon",
    "wof:placetype":"venue"
},
  "geometry": {"coordinates":[6.6811709404,50.1967811584],"type":"Point"}
}