{
  "type": "Feature",
  "properties": {
    "iso:country":"DE",
    "sg:address":"Erfurter Str. 9",
    "sg:city":"Bad Emstal",
    "sg:phone":"+49 5624/99820",
    "sg:postcode":"34308",
    "sg:province":"Hessen",
    "wof:name":"Gds Werbeagentur Inh. Matthias Tari",
    "wof:placetype":"venue"
},
  "geometry": {"coordinates":[9.2605352402,51.2437858582],"type":"Point"}
}