{
  "type": "Feature",
  "properties": {
    "iso:country":"DE",
    "sg:address":"Maria-Ellenrieder-Str. 3",
    "sg:city":"Konstanz",
    "sg:phone":"+49 7531/16583",
    "sg:postcode":"78462",
    "sg:province":"Baden-W\u00fcrttemberg",
    "wof:name":"Betreuungsverein Bodensee/hegau E.v.",
    "wof:placetype":"venue"
},
  "geometry": {"coordinates":[9.167296,47.662388],"type":"Point"}
}