{
  "type": "Feature",
  "properties": {
    "iso:country":"DE",
    "sg:address":"Osningstr. 144",
    "sg:city":"Bielefeld",
    "sg:phone":"+49 521/22199",
    "sg:postcode":"33605",
    "sg:province":"Nordrhein-Westfalen",
    "wof:name":"Schramek",
    "wof:placetype":"venue"
},
  "geometry": {"coordinates":[8.5539598465,51.9921073914],"type":"Point"}
}