{
  "type": "Feature",
  "properties": {
    "iso:country":"DE",
    "sg:address":"Bergmannstr. 43",
    "sg:city":"Maxh\u00fctte-Haidhof",
    "sg:phone":"+49 9471/601172",
    "sg:postcode":"93142",
    "sg:province":"Bayern",
    "wof:name":"Michl's Landgasthof",
    "wof:placetype":"venue"
},
  "geometry": {"coordinates":[12.0881071091,49.1843032837],"type":"Point"}
}