{
  "type": "Feature",
  "properties": {
    "iso:country":"DE",
    "sg:address":"Industriering 41",
    "sg:city":"Viersen",
    "sg:phone":"+49 2162/6333",
    "sg:postcode":"41751",
    "sg:province":"Nordrhein-Westfalen",
    "wof:name":"Spedition Michael Giljam",
    "wof:placetype":"venue"
},
  "geometry": {"coordinates":[6.335445,51.252174],"type":"Point"}
}