{
  "type": "Feature",
  "properties": {
    "iso:country":"DE",
    "sg:address":"Peckateler Str. 16",
    "sg:city":"Raben Steinfeld",
    "sg:phone":"+49 3860/248",
    "sg:postcode":"19065",
    "sg:province":"Mecklenburg-Vorpommern",
    "wof:name":"Rudolf Wunderlich Bauunternehmen",
    "wof:placetype":"venue"
},
  "geometry": {"coordinates":[11.496425,53.592289],"type":"Point"}
}