{
  "type": "Feature",
  "properties": {
    "iso:country":"DE",
    "sg:address":"Rudolf-Diesel-Str. 2",
    "sg:city":"Loxstedt",
    "sg:phone":"+49 4744/92950",
    "sg:postcode":"27612",
    "sg:province":"Niedersachsen",
    "wof:name":"K. Nehlsen Gmbh",
    "wof:placetype":"venue"
},
  "geometry": {"coordinates":[8.6552534103,53.4756851196],"type":"Point"}
}