{
  "type": "Feature",
  "properties": {
    "iso:country":"DE",
    "sg:address":"An den Drei Hasen 22",
    "sg:city":"Oberursel",
    "sg:phone":"+49 6171/56769",
    "sg:postcode":"61440",
    "sg:province":"Hessen",
    "wof:name":"Artur Hammerl",
    "wof:placetype":"venue"
},
  "geometry": {"coordinates":[8.5960273743,50.2045173645],"type":"Point"}
}