{
  "type": "Feature",
  "properties": {
    "iso:country":"DE",
    "sg:address":"Neunstetter Str. 16",
    "sg:city":"Herrieden",
    "sg:phone":"+49 9825/93456",
    "sg:postcode":"91567",
    "sg:province":"Bayern",
    "wof:name":"Erich Wei\u00df Elektroinstallation-hausger\u00e4te",
    "wof:placetype":"venue"
},
  "geometry": {"coordinates":[10.494324,49.235012],"type":"Point"}
}