{
  "type": "Feature",
  "properties": {
    "iso:country":"DE",
    "sg:address":"Hauptstr. 19",
    "sg:city":"Zschortau",
    "sg:phone":"+49 34202/92313",
    "sg:postcode":"04509",
    "sg:province":"Sachsen",
    "wof:name":"Hans-jochen Brosig",
    "wof:placetype":"venue"
},
  "geometry": {"coordinates":[12.353229,51.511105],"type":"Point"}
}