{
  "type": "Feature",
  "properties": {
    "iso:country":"DE",
    "sg:address":"Friedhofstr. 7",
    "sg:city":"Lebach",
    "sg:phone":"+49 6888/8211",
    "sg:postcode":"66822",
    "sg:province":"Saarland",
    "wof:name":"Konrad Und Christel Huppert",
    "wof:placetype":"venue"
},
  "geometry": {"coordinates":[6.961657,49.445087],"type":"Point"}
}