{
  "type": "Feature",
  "properties": {
    "iso:country":"DE",
    "sg:address":"Neuhauser Weg 100",
    "sg:city":"Kempten",
    "sg:phone":"+49 831/93215",
    "sg:postcode":"87439",
    "sg:province":"Bayern",
    "wof:name":"Oskar Bunk",
    "wof:placetype":"venue"
},
  "geometry": {"coordinates":[10.290598,47.751656],"type":"Point"}
}