{
  "type": "Feature",
  "properties": {
    "iso:country":"DE",
    "sg:address":"Heckschenstr. 109",
    "sg:city":"Krefeld",
    "sg:phone":"+49 2151/541516",
    "sg:postcode":"47809",
    "sg:province":"Nordrhein-Westfalen",
    "wof:name":"Helmut Franzen",
    "wof:placetype":"venue"
},
  "geometry": {"coordinates":[6.620327,51.322857],"type":"Point"}
}