{
  "type": "Feature",
  "properties": {
    "iso:country":"DE",
    "sg:address":"Frankfurter Str. 68",
    "sg:city":"Bad Vilbel",
    "sg:phone":"+49 6101/12101",
    "sg:postcode":"61118",
    "sg:province":"Hessen",
    "wof:name":"Cadillac",
    "wof:placetype":"venue"
},
  "geometry": {"coordinates":[8.739798,50.180317],"type":"Point"}
}