{
  "type": "Feature",
  "properties": {
    "iso:country":"DE",
    "sg:address":"S\u00fcdstr. 35",
    "sg:city":"Sankt Augustin",
    "sg:phone":"+49 2241/206073",
    "sg:postcode":"53757",
    "sg:province":"Nordrhein-Westfalen",
    "wof:name":"Deutsche Bau- Und Siedlungs Gmbh",
    "wof:placetype":"venue"
},
  "geometry": {"coordinates":[7.185669899,50.7799491882],"type":"Point"}
}