{
  "type": "Feature",
  "properties": {
    "iso:country":"DE",
    "sg:address":"Stadtplatz 3",
    "sg:city":"Hemau",
    "sg:phone":"+49 9491/1850",
    "sg:postcode":"93155",
    "sg:province":"Bayern",
    "wof:name":"Apotheke Am Rathaus",
    "wof:placetype":"venue"
},
  "geometry": {"coordinates":[11.782559,49.052097],"type":"Point"}
}