{
  "type": "Feature",
  "properties": {
    "iso:country":"DE",
    "sg:address":"Lohnauer Steig 12",
    "sg:city":"Berlin",
    "sg:postcode":"12489",
    "sg:province":"Berlin",
    "wof:name":"Dr. Med. Sohr",
    "wof:placetype":"venue"
},
  "geometry": {"coordinates":[13.552962,52.443001],"type":"Point"}
}