{
  "type": "Feature",
  "properties": {
    "iso:country":"DE",
    "sg:address":"Moosbauerweg 68",
    "sg:city":"Wolfratshausen",
    "sg:phone":"+49 8171/76842",
    "sg:postcode":"82515",
    "sg:province":"Bayern",
    "wof:name":"Hildegard Schultz Ergotherapiepraxis",
    "wof:placetype":"venue"
},
  "geometry": {"coordinates":[11.430628,47.908016],"type":"Point"}
}