{
  "type": "Feature",
  "properties": {
    "iso:country":"DE",
    "sg:address":"Graacher Str. 13",
    "sg:city":"Berlin",
    "sg:phone":"+49 30/7748140",
    "sg:postcode":"12247",
    "sg:province":"Berlin",
    "wof:name":"Klaus Schlingmann Immobilienmakler",
    "wof:placetype":"venue"
},
  "geometry": {"coordinates":[13.351190567,52.4417190552],"type":"Point"}
}