{
  "type": "Feature",
  "properties": {
    "iso:country":"DE",
    "sg:address":"Industriestr 11",
    "sg:city":"Altenstadt",
    "sg:phone":"+49 2224/2131",
    "sg:postcode":"63674",
    "sg:province":"Hessen",
    "wof:name":"Algo Gmbh",
    "wof:placetype":"venue"
},
  "geometry": {"coordinates":[7.219518,50.653286],"type":"Point"}
}