{
  "type": "Feature",
  "properties": {
    "iso:country":"DE",
    "sg:address":"Pfinzingstr. 10",
    "sg:city":"Feucht",
    "sg:phone":"+49 9128/991370",
    "sg:postcode":"90537",
    "sg:province":"Bayern",
    "wof:name":"Psf Projektsteuerung",
    "wof:placetype":"venue"
},
  "geometry": {"coordinates":[11.211643,49.374966],"type":"Point"}
}