{
  "type": "Feature",
  "properties": {
    "iso:country":"DE",
    "sg:address":"Selliner Str. 6",
    "sg:city":"Dresden",
    "sg:phone":"+49 351/4114601",
    "sg:postcode":"01109",
    "sg:province":"Sachsen",
    "wof:name":"Michael Pleickies Architekt",
    "wof:placetype":"venue"
},
  "geometry": {"coordinates":[13.788247,51.119778],"type":"Point"}
}