{
  "type": "Feature",
  "properties": {
    "iso:country":"DE",
    "sg:address":"Gro\u00dfe Str. 6",
    "sg:city":"Emden",
    "sg:phone":"+49 4921/93100",
    "sg:postcode":"26721",
    "sg:province":"Niedersachsen",
    "wof:name":"B\u00fcrohaus Duin Ohg Inh. Hans Morgenweck",
    "wof:placetype":"venue"
},
  "geometry": {"coordinates":[7.2043762207,53.3668632507],"type":"Point"}
}