{
  "type": "Feature",
  "properties": {
    "iso:country":"DE",
    "sg:address":"Pfeifferhannsstr. 19",
    "sg:city":"Dresden",
    "sg:phone":"+49 351/4590027",
    "sg:postcode":"01307",
    "sg:province":"Sachsen",
    "wof:name":"Bruno Dopslaf",
    "wof:placetype":"venue"
},
  "geometry": {"coordinates":[13.763872,51.05822],"type":"Point"}
}