{
  "type": "Feature",
  "properties": {
    "iso:country":"DE",
    "sg:address":"Hermannstr. 20",
    "sg:city":"Neuwied",
    "sg:phone":"+49 2631/8060",
    "sg:postcode":"56564",
    "sg:province":"Rheinland-Pfalz",
    "wof:name":"Bsn Beteiligungsgesellschaft Der Sparkasse Neuwied Mbh",
    "wof:placetype":"venue"
},
  "geometry": {"coordinates":[7.463196,50.429123],"type":"Point"}
}