{
  "type": "Feature",
  "properties": {
    "iso:country":"DE",
    "sg:address":"Bonhoefferstr. 2",
    "sg:city":"K\u00f6ln",
    "sg:phone":"+49 221/5901567",
    "sg:postcode":"50765",
    "sg:province":"Nordrhein-Westfalen",
    "wof:name":"Franz M\u00fcck Steuerberater",
    "wof:placetype":"venue"
},
  "geometry": {"coordinates":[6.8556280136,51.0021591187],"type":"Point"}
}