{
  "type": "Feature",
  "properties": {
    "iso:country":"DE",
    "sg:address":"K\u00f6ln-Berliner-Str. 13",
    "sg:city":"Dortmund",
    "sg:phone":"+49 231/445207",
    "sg:postcode":"44287",
    "sg:province":"Nordrhein-Westfalen",
    "wof:name":"Horst Gabel",
    "wof:placetype":"venue"
},
  "geometry": {"coordinates":[7.5561308861,51.4928512573],"type":"Point"}
}