{
  "type": "Feature",
  "properties": {
    "iso:country":"DE",
    "sg:address":"Tuttlinger Str. 8",
    "sg:city":"Seitingen-Oberflacht",
    "sg:phone":"+49 7464/1302",
    "sg:postcode":"78606",
    "sg:province":"Baden-W\u00fcrttemberg",
    "wof:name":"Karl Welte",
    "wof:placetype":"venue"
},
  "geometry": {"coordinates":[8.7301015854,48.0201721191],"type":"Point"}
}