{
  "type": "Feature",
  "properties": {
    "iso:country":"DE",
    "sg:address":"Niederste Str. 3",
    "sg:city":"Attendorn",
    "sg:phone":"+49 2722/4342",
    "sg:postcode":"57439",
    "sg:province":"Nordrhein-Westfalen",
    "wof:name":"Raring-augenoptik E. K.",
    "wof:placetype":"venue"
},
  "geometry": {"coordinates":[7.9046578407,51.1264038086],"type":"Point"}
}