{
  "type": "Feature",
  "properties": {
    "iso:country":"DE",
    "sg:address":"Merkurstra\u00dfe 32",
    "sg:city":"Heilbronn",
    "sg:phone":"+49 7131/577807",
    "sg:postcode":"74074",
    "sg:province":"Baden-W\u00fcrttemberg",
    "wof:name":"Michael Dangel - Steuerberatung",
    "wof:placetype":"venue"
},
  "geometry": {"coordinates":[9.207728,49.126644],"type":"Point"}
}