{
  "type": "Feature",
  "properties": {
    "iso:country":"DE",
    "sg:address":"Friedensstr. 47",
    "sg:city":"Altlu\u00dfheim",
    "sg:phone":"+49 4962/0533496",
    "sg:postcode":"68804",
    "sg:province":"Baden-W\u00fcrttemberg",
    "wof:name":"Berg-idl Gmbh",
    "wof:placetype":"venue"
},
  "geometry": {"coordinates":[8.508577,49.289532],"type":"Point"}
}