{
  "type": "Feature",
  "properties": {
    "iso:country":"DE",
    "sg:address":"S\u00fcdweststra\u00dfe 13",
    "sg:city":"Bremen",
    "sg:phone":"+49 4942/164950",
    "sg:postcode":"28237",
    "sg:province":"Bremen",
    "wof:name":"Saacke Gmbh & Co. Kg",
    "wof:placetype":"venue"
},
  "geometry": {"coordinates":[8.7345314026,53.1260185242],"type":"Point"}
}