{
  "type": "Feature",
  "properties": {
    "iso:country":"DE",
    "sg:address":"Asbacher Str. 43",
    "sg:city":"Vettelscho\u00df",
    "sg:phone":"+49 2645/2260",
    "sg:postcode":"53560",
    "sg:province":"Rheinland-Pfalz",
    "wof:name":"Robert Sinzig",
    "wof:placetype":"venue"
},
  "geometry": {"coordinates":[7.3093352318,50.6186103821],"type":"Point"}
}