{
  "type": "Feature",
  "properties": {
    "iso:country":"DE",
    "sg:address":"Marktstr. 16",
    "sg:city":"Wehr",
    "sg:phone":"+49 2636/7248",
    "sg:postcode":"56653",
    "sg:province":"Rheinland-Pfalz",
    "wof:name":"Ottilia Gerhartz",
    "wof:placetype":"venue"
},
  "geometry": {"coordinates":[7.2107601166,50.4223594666],"type":"Point"}
}