{
  "type": "Feature",
  "properties": {
    "iso:country":"DE",
    "sg:address":"Eisenbahnstr. 213",
    "sg:city":"Dreieich",
    "sg:phone":"+49 6103/697916",
    "sg:postcode":"63303",
    "sg:province":"Hessen",
    "wof:name":"Armin Harich",
    "wof:placetype":"venue"
},
  "geometry": {"coordinates":[8.673869,50.019062],"type":"Point"}
}