{
  "type": "Feature",
  "properties": {
    "iso:country":"DE",
    "sg:address":"Elberfelder Str. 23-25",
    "sg:city":"Hagen",
    "sg:phone":"+49 2331/9120",
    "sg:postcode":"58095",
    "sg:province":"Nordrhein-Westfalen",
    "wof:name":"Kaufhof Mode Und Sport Gmbh",
    "wof:placetype":"venue"
},
  "geometry": {"coordinates":[7.471859,51.357651],"type":"Point"}
}