{
  "type": "Feature",
  "properties": {
    "iso:country":"DE",
    "sg:address":"B\u00e4renseestr. 6",
    "sg:city":"Kaufbeuren",
    "sg:phone":"+49 8341/12064",
    "sg:postcode":"87600",
    "sg:province":"Bayern",
    "wof:name":"Josef Herb",
    "wof:placetype":"venue"
},
  "geometry": {"coordinates":[10.641364,47.874237],"type":"Point"}
}