{
  "type": "Feature",
  "properties": {
    "iso:country":"DE",
    "sg:address":"Siegburger Str. 31",
    "sg:city":"K\u00f6nigswinter",
    "sg:phone":"+49 2244/2738",
    "sg:postcode":"53639",
    "sg:province":"Nordrhein-Westfalen",
    "wof:name":"F. Vedders",
    "wof:placetype":"venue"
},
  "geometry": {"coordinates":[7.277322,50.711353],"type":"Point"}
}