{
  "type": "Feature",
  "properties": {
    "iso:country":"DE",
    "sg:address":"J\u00e4ckstr. 18",
    "sg:city":"Bamberg",
    "sg:phone":"+49 4927/50245",
    "sg:postcode":"96052",
    "sg:province":"Bayern",
    "wof:name":"Georg Homrighausen Holzwarenfabrik Gmbh",
    "wof:placetype":"venue"
},
  "geometry": {"coordinates":[8.5010414124,51.0738258362],"type":"Point"}
}