{
  "type": "Feature",
  "properties": {
    "iso:country":"DE",
    "sg:address":"Talstr. 24",
    "sg:city":"Rosenthal-Bielatal",
    "sg:phone":"+49 35033/71358",
    "sg:postcode":"01824",
    "sg:province":"Sachsen",
    "wof:name":"S. Wilhelm",
    "wof:placetype":"venue"
},
  "geometry": {"coordinates":[14.046489,50.875317],"type":"Point"}
}