{
  "type": "Feature",
  "properties": {
    "iso:country":"DE",
    "sg:address":"Hindenburgstr. 7",
    "sg:city":"Altenstadt",
    "sg:phone":"+49 8337/267",
    "sg:postcode":"89281",
    "sg:province":"Bayern",
    "wof:name":"Hans Leichtle",
    "wof:placetype":"venue"
},
  "geometry": {"coordinates":[10.111628,48.162872],"type":"Point"}
}