{
  "type": "Feature",
  "properties": {
    "iso:country":"DE",
    "sg:address":"Br\u00fcckenstr. 2",
    "sg:city":"M\u00f6hnesee",
    "sg:phone":"+49 2924/7642",
    "sg:postcode":"59519",
    "sg:province":"Nordrhein-Westfalen",
    "wof:name":"Strandbad K\u00f6rbecke Campingplatz",
    "wof:placetype":"venue"
},
  "geometry": {"coordinates":[8.128688,51.496216],"type":"Point"}
}