{
  "type": "Feature",
  "properties": {
    "iso:country":"DE",
    "sg:address":"Prinzenstr. 10",
    "sg:city":"Hannover",
    "sg:phone":"+49 511/306480",
    "sg:postcode":"30159",
    "sg:province":"Niedersachsen",
    "wof:name":"Haus & Grund Facility Management Gmbh",
    "wof:placetype":"venue"
},
  "geometry": {"coordinates":[9.744436264,52.3732299805],"type":"Point"}
}