{
  "type": "Feature",
  "properties": {
    "iso:country":"DE",
    "sg:address":"Sonnenweg 9",
    "sg:city":"R\u00f6srath",
    "sg:phone":"+49 2205/81494",
    "sg:postcode":"51503",
    "sg:province":"Nordrhein-Westfalen",
    "wof:name":"Friedhelm Kallenbach",
    "wof:placetype":"venue"
},
  "geometry": {"coordinates":[7.178606,50.928173],"type":"Point"}
}