{
  "type": "Feature",
  "properties": {
    "iso:country":"DE",
    "sg:address":"Erwitter Str. 121",
    "sg:city":"Lippstadt",
    "sg:postcode":"59557",
    "sg:province":"Nordrhein-Westfalen",
    "wof:name":"Aldi Gmbh & Co. Kg",
    "wof:placetype":"venue"
},
  "geometry": {"coordinates":[8.3435297012,51.6545639038],"type":"Point"}
}