{
  "type": "Feature",
  "properties": {
    "iso:country":"DE",
    "sg:address":"Croneallee 15",
    "sg:city":"Rhauderfehn",
    "sg:phone":"+49 4967/483",
    "sg:postcode":"26817",
    "sg:province":"Niedersachsen",
    "wof:name":"Jan Woldenga",
    "wof:placetype":"venue"
},
  "geometry": {"coordinates":[7.551577,53.072372],"type":"Point"}
}