{
  "type": "Feature",
  "properties": {
    "iso:country":"DE",
    "sg:address":"Alte Dorfstr. 11",
    "sg:city":"B\u00e4rnau",
    "sg:phone":"+49 9635/427",
    "sg:postcode":"95671",
    "sg:province":"Bayern",
    "wof:name":"Johann Schuller",
    "wof:placetype":"venue"
},
  "geometry": {"coordinates":[12.3857297897,49.8005065918],"type":"Point"}
}