{
  "type": "Feature",
  "properties": {
    "iso:country":"DE",
    "sg:city":"Bad Wiessee",
    "sg:phone":"+49 8022/83938",
    "sg:postcode":"83707",
    "sg:province":"Bayern",
    "wof:name":"H. Bohn",
    "wof:placetype":"venue"
},
  "geometry": {"coordinates":[11.720838,47.715824],"type":"Point"}
}