{
  "type": "Feature",
  "properties": {
    "iso:country":"DE",
    "sg:address":"Grosshandelsrg. 3/22",
    "sg:city":"Osnabr\u00fcck",
    "sg:phone":"+49 4954/190800",
    "sg:postcode":"49084",
    "sg:province":"Niedersachsen",
    "wof:name":"Fuchs + Sanders Schrauben Grosshandel Gmbh & Co. Kg",
    "wof:placetype":"venue"
},
  "geometry": {"coordinates":[8.084522,52.259724],"type":"Point"}
}