{
  "type": "Feature",
  "properties": {
    "iso:country":"DE",
    "sg:address":"Gr\u00fcntenweg 10",
    "sg:city":"Scheidegg",
    "sg:phone":"+49 8381/6723",
    "sg:postcode":"88175",
    "sg:province":"Bayern",
    "wof:name":"D. Sp\u00e4th",
    "wof:placetype":"venue"
},
  "geometry": {"coordinates":[9.858578,47.586933],"type":"Point"}
}