{
  "type": "Feature",
  "properties": {
    "iso:country":"DE",
    "sg:address":"Gsteinacherstra\u00dfe 19",
    "sg:city":"Schwarzenbruck",
    "sg:phone":"+49 9128/991931",
    "sg:postcode":"90592",
    "sg:province":"Bayern",
    "wof:name":"Cs Travel Gmbh",
    "wof:placetype":"venue"
},
  "geometry": {"coordinates":[11.2347078323,49.3565826416],"type":"Point"}
}