{
  "type": "Feature",
  "properties": {
    "iso:country":"DE",
    "sg:address":"Eichenrain 10",
    "sg:city":"Kirchberg",
    "sg:phone":"+49 7144/3166",
    "sg:postcode":"71737",
    "sg:province":"Baden-W\u00fcrttemberg",
    "wof:name":"Karl Reichert Steuerberater",
    "wof:placetype":"venue"
},
  "geometry": {"coordinates":[9.3253898621,48.9363632202],"type":"Point"}
}