{
  "type": "Feature",
  "properties": {
    "iso:country":"DE",
    "sg:address":"Friedrichstr. 1",
    "sg:city":"Minden",
    "sg:postcode":"32427",
    "sg:province":"Nordrhein-Westfalen",
    "wof:name":"Toll Gmbh",
    "wof:placetype":"venue"
},
  "geometry": {"coordinates":[8.907146,52.291214],"type":"Point"}
}