{
  "type": "Feature",
  "properties": {
    "iso:country":"DE",
    "sg:address":"Reiterhof am B\u00e4renfels",
    "sg:city":"Mettlach",
    "sg:postcode":"66693",
    "sg:province":"Saarland",
    "wof:name":"Rho - Reiterhof Orscholz Betriebs Gmbh",
    "wof:placetype":"venue"
},
  "geometry": {"coordinates":[6.4992160797,49.5020103455],"type":"Point"}
}