{
  "type": "Feature",
  "properties": {
    "iso:country":"DE",
    "sg:address":"Hauptstr. 410",
    "sg:city":"Idar-Oberstein",
    "sg:phone":"+49 6781/21120",
    "sg:postcode":"55743",
    "sg:province":"Rheinland-Pfalz",
    "wof:name":"Zum Hakkis",
    "wof:placetype":"venue"
},
  "geometry": {"coordinates":[7.3271379471,49.7044029236],"type":"Point"}
}