{
  "type": "Feature",
  "properties": {
    "iso:country":"DE",
    "sg:address":"Elbringhausen 2-4",
    "sg:city":"Wermelskirchen",
    "sg:phone":"+49 2196/88600",
    "sg:postcode":"42929",
    "sg:province":"Nordrhein-Westfalen",
    "wof:name":"Pisana Orthop\u00e4die Technik Gmbh",
    "wof:placetype":"venue"
},
  "geometry": {"coordinates":[7.2362799644,51.1455001831],"type":"Point"}
}