{
  "type": "Feature",
  "properties": {
    "iso:country":"DE",
    "sg:address":"Kolpingstr. 57",
    "sg:city":"Bexbach",
    "sg:phone":"+49 6826/1460",
    "sg:postcode":"66450",
    "sg:province":"Saarland",
    "wof:name":"Helmut Baschab Ingenieur Gmbh",
    "wof:placetype":"venue"
},
  "geometry": {"coordinates":[7.251523,49.346603],"type":"Point"}
}