{
  "type": "Feature",
  "properties": {
    "iso:country":"DE",
    "sg:address":"Im Aubisch 1 B",
    "sg:city":"Neuwied",
    "sg:postcode":"56567",
    "sg:province":"Rheinland-Pfalz",
    "wof:name":"Tourismusverband Fieberbrunn Uwe Sch\u00f6llkopf",
    "wof:placetype":"venue"
},
  "geometry": {"coordinates":[7.4562211037,50.4709892273],"type":"Point"}
}