{
  "type": "Feature",
  "properties": {
    "iso:country":"DE",
    "sg:address":"Schultenweg 135",
    "sg:city":"Essen",
    "sg:postcode":"45279",
    "sg:province":"Nordrhein-Westfalen",
    "wof:name":"Kath. \u00f6ffentliche Bibliothek Heilige Dreifaltigkeit",
    "wof:placetype":"venue"
},
  "geometry": {"coordinates":[7.12479,51.446018],"type":"Point"}
}