{
  "type": "Feature",
  "properties": {
    "iso:country":"DE",
    "sg:address":"Hauptstr. 169",
    "sg:city":"Stuhr",
    "sg:phone":"+49 421/890818",
    "sg:postcode":"28816",
    "sg:province":"Niedersachsen",
    "wof:name":"M. Martfeld",
    "wof:placetype":"venue"
},
  "geometry": {"coordinates":[8.7447166443,52.9799575806],"type":"Point"}
}