{
  "type": "Feature",
  "properties": {
    "iso:country":"DE",
    "sg:address":"Kapellenweg",
    "sg:city":"Titisee-Neustadt",
    "sg:phone":"+49 7651/8604",
    "sg:postcode":"79822",
    "sg:province":"Baden-W\u00fcrttemberg",
    "wof:name":"Pension Hans Braun",
    "wof:placetype":"venue"
},
  "geometry": {"coordinates":[8.1390647888,47.9051933289],"type":"Point"}
}