{
  "type": "Feature",
  "properties": {
    "iso:country":"DE",
    "sg:address":"Dammstr. 2",
    "sg:city":"Osnabr\u00fcck",
    "sg:phone":"+49 541/22205",
    "sg:postcode":"49084",
    "sg:province":"Niedersachsen",
    "wof:name":"Rolf Krebs Gmbh",
    "wof:placetype":"venue"
},
  "geometry": {"coordinates":[8.0581970215,52.2676391602],"type":"Point"}
}