{
  "type": "Feature",
  "properties": {
    "iso:country":"DE",
    "sg:address":"Brenzlestr. 1",
    "sg:city":"Heidenheim",
    "sg:phone":"+49 7321/62199",
    "sg:postcode":"89520",
    "sg:province":"Baden-W\u00fcrttemberg",
    "wof:name":"Brenzle",
    "wof:placetype":"venue"
},
  "geometry": {"coordinates":[10.1621742249,48.7061271667],"type":"Point"}
}