{
  "type": "Feature",
  "properties": {
    "iso:country":"DE",
    "sg:address":"Alexiusweg 4",
    "sg:city":"Ravensburg",
    "sg:phone":"+49 751/2855",
    "sg:postcode":"88212",
    "sg:province":"Baden-W\u00fcrttemberg",
    "wof:name":"S. Rummler Ingenieur",
    "wof:placetype":"venue"
},
  "geometry": {"coordinates":[9.6264638901,47.7930450439],"type":"Point"}
}