{
  "type": "Feature",
  "properties": {
    "iso:country":"DE",
    "sg:address":"Haagstr. 8",
    "sg:city":"Bad Griesbach",
    "sg:phone":"+49 8532/2020",
    "sg:postcode":"94086",
    "sg:province":"Bayern",
    "wof:name":"Hermann Flingelli",
    "wof:placetype":"venue"
},
  "geometry": {"coordinates":[13.1947374344,48.4504432678],"type":"Point"}
}