{
  "type": "Feature",
  "properties": {
    "iso:country":"DE",
    "sg:address":"Waldheideweg 99",
    "sg:city":"Voerde",
    "sg:phone":"+49 2855/8347",
    "sg:postcode":"46562",
    "sg:province":"Nordrhein-Westfalen",
    "wof:name":"Wilfried Horstmann",
    "wof:placetype":"venue"
},
  "geometry": {"coordinates":[6.696726,51.613403],"type":"Point"}
}