{
  "type": "Feature",
  "properties": {
    "iso:country":"DE",
    "sg:address":"Adendorfer Str. 6",
    "sg:city":"Scharnebeck",
    "sg:phone":"+49 4136/1615",
    "sg:postcode":"21379",
    "sg:province":"Niedersachsen",
    "wof:name":"Sell And More Promotion Services Ohg",
    "wof:placetype":"venue"
},
  "geometry": {"coordinates":[10.5019226074,53.2902603149],"type":"Point"}
}