{
  "type": "Feature",
  "properties": {
    "iso:country":"DE",
    "sg:address":"Schmiedweg 9",
    "sg:city":"Bad F\u00fcssing",
    "sg:phone":"+49 8531/24182",
    "sg:postcode":"94072",
    "sg:province":"Bayern",
    "wof:name":"D. Robl Immobilienmakler",
    "wof:placetype":"venue"
},
  "geometry": {"coordinates":[13.3502321243,48.3561096191],"type":"Point"}
}