{
  "type": "Feature",
  "properties": {
    "iso:country":"DE",
    "sg:address":"Augustastr. 2",
    "sg:city":"Flensburg",
    "sg:phone":"+49 461/144800",
    "sg:postcode":"24937",
    "sg:province":"Schleswig-Holstein",
    "wof:name":"Hotel Handwerkerhaus",
    "wof:placetype":"venue"
},
  "geometry": {"coordinates":[9.4399652481,54.7853355408],"type":"Point"}
}