{
  "type": "Feature",
  "properties": {
    "iso:country":"DE",
    "sg:address":"Wohnbacher Str. 1",
    "sg:city":"Schillingsf\u00fcrst",
    "sg:phone":"+49 9868/98890",
    "sg:postcode":"91583",
    "sg:province":"Bayern",
    "wof:name":"Kamleiter & Sohn Inh. G\u00fcnter Kamleiter",
    "wof:placetype":"venue"
},
  "geometry": {"coordinates":[10.2553157806,49.2919960022],"type":"Point"}
}