{
  "type": "Feature",
  "properties": {
    "iso:country":"DE",
    "sg:address":"Althaushamer Str. 3",
    "sg:city":"Hausham",
    "sg:phone":"+49 8026/3268",
    "sg:postcode":"83734",
    "sg:province":"Bayern",
    "wof:name":"Josef Schuster Eisenwaren",
    "wof:placetype":"venue"
},
  "geometry": {"coordinates":[11.8437690735,47.7478256226],"type":"Point"}
}