{
  "type": "Feature",
  "properties": {
    "iso:country":"DE",
    "sg:address":"Bahnhofstr. 20",
    "sg:city":"Meeder",
    "sg:phone":"+49 9566/321",
    "sg:postcode":"96484",
    "sg:province":"Bayern",
    "wof:name":"Ursula Hochberger",
    "wof:placetype":"venue"
},
  "geometry": {"coordinates":[10.906911,50.317635],"type":"Point"}
}