{
  "type": "Feature",
  "properties": {
    "iso:country":"DE",
    "sg:address":"Mainstr. 22",
    "sg:city":"Hattersheim",
    "sg:phone":"+49 6190/6687",
    "sg:postcode":"65795",
    "sg:province":"Hessen",
    "wof:name":"Regina Preis Krankengymnastin",
    "wof:placetype":"venue"
},
  "geometry": {"coordinates":[8.498942,50.05497],"type":"Point"}
}