{
  "type": "Feature",
  "properties": {
    "iso:country":"DE",
    "sg:address":"Marktstr.1",
    "sg:city":"Luckau",
    "sg:phone":"+49 3544",
    "sg:postcode":"15926",
    "sg:province":"Brandenburg",
    "wof:name":"Jeans&shoesgmbh",
    "wof:placetype":"venue"
},
  "geometry": {"coordinates":[13.7158546448,51.8525161743],"type":"Point"}
}