{
  "type": "Feature",
  "properties": {
    "iso:country":"DE",
    "sg:city":"M\u00fcnchen",
    "sg:postcode":"80539",
    "sg:province":"Bayern",
    "wof:name":"Xtalis Deutschland Gmbh",
    "wof:placetype":"venue"
},
  "geometry": {"coordinates":[11.58313,48.14436],"type":"Point"}
}