{
  "type": "Feature",
  "properties": {
    "iso:country":"DE",
    "sg:address":"\u00c4u\u00dfere Schneebergerstr. 4a",
    "sg:city":"Zwickau",
    "sg:phone":"+49 375",
    "sg:postcode":"08056",
    "sg:province":"Sachsen",
    "wof:name":"Kfz-sachverstaendige-sachsen",
    "wof:placetype":"venue"
},
  "geometry": {"coordinates":[12.496686,50.714157],"type":"Point"}
}