{
  "type": "Feature",
  "properties": {
    "iso:country":"DE",
    "sg:address":"Wilhelmstr. 16/1",
    "sg:city":"Heilbronn",
    "sg:phone":"+49 7131/96470",
    "sg:postcode":"74072",
    "sg:province":"Baden-W\u00fcrttemberg",
    "wof:name":"Ed. Z\u00fcblin Ag",
    "wof:placetype":"venue"
},
  "geometry": {"coordinates":[9.2190971375,49.1367607117],"type":"Point"}
}