{
  "type": "Feature",
  "properties": {
    "iso:country":"DE",
    "sg:address":"Mauchenm\u00fchleweg 2",
    "sg:city":"Eberhardzell",
    "sg:postcode":"88436",
    "sg:province":"Baden-W\u00fcrttemberg",
    "wof:name":"Gebhard Spieler",
    "wof:placetype":"venue"
},
  "geometry": {"coordinates":[9.83394,47.962013],"type":"Point"}
}