{
  "type": "Feature",
  "properties": {
    "iso:country":"DE",
    "sg:address":"Landwehrstr. 46",
    "sg:city":"Salzgitter",
    "sg:phone":"+49 5341/91669",
    "sg:postcode":"38259",
    "sg:province":"Niedersachsen",
    "wof:name":"Johannes Borsutzky",
    "wof:placetype":"venue"
},
  "geometry": {"coordinates":[10.42413,52.099365],"type":"Point"}
}