{
  "type": "Feature",
  "properties": {
    "iso:country":"DE",
    "sg:address":"Diestedder Str. 41",
    "sg:city":"Lippetal",
    "sg:phone":"+49 2923/1441",
    "sg:postcode":"59510",
    "sg:province":"Nordrhein-Westfalen",
    "wof:name":"F. Vorschepoth",
    "wof:placetype":"venue"
},
  "geometry": {"coordinates":[8.1511077881,51.6883392334],"type":"Point"}
}