{
  "type": "Feature",
  "properties": {
    "iso:country":"DE",
    "sg:address":"Schillerstr. 2",
    "sg:city":"Schierling",
    "sg:phone":"+49 9451/3628",
    "sg:postcode":"84069",
    "sg:province":"Bayern",
    "wof:name":"Oskar Sperl",
    "wof:placetype":"venue"
},
  "geometry": {"coordinates":[12.139188,48.83057],"type":"Point"}
}