{
  "type": "Feature",
  "properties": {
    "iso:country":"DE",
    "sg:address":"Adolf-K\u00f6hne-Str. 4",
    "sg:city":"Osnabr\u00fcck",
    "sg:phone":"+49 541/139020",
    "sg:postcode":"49090",
    "sg:province":"Niedersachsen",
    "wof:name":"Helmers Maschinenbau Gmbh",
    "wof:placetype":"venue"
},
  "geometry": {"coordinates":[8.004731,52.30582],"type":"Point"}
}