{
  "type": "Feature",
  "properties": {
    "iso:country":"DE",
    "sg:address":"Sauerlandstr. 5",
    "sg:city":"Wipperf\u00fcrth",
    "sg:phone":"+49 2269/455",
    "sg:postcode":"51688",
    "sg:province":"Nordrhein-Westfalen",
    "wof:name":"Wolfgang L\u00fcbs",
    "wof:placetype":"venue"
},
  "geometry": {"coordinates":[7.4882230759,51.1112785339],"type":"Point"}
}