{
  "type": "Feature",
  "properties": {
    "iso:country":"DE",
    "sg:address":"Ringstr. 99",
    "sg:city":"Kamp-Lintfort",
    "sg:phone":"+49 2842/55331",
    "sg:postcode":"47475",
    "sg:province":"Nordrhein-Westfalen",
    "wof:name":"Annettes Haarstudio",
    "wof:placetype":"venue"
},
  "geometry": {"coordinates":[6.546295166,51.5015335083],"type":"Point"}
}