{
  "type": "Feature",
  "properties": {
    "iso:country":"DE",
    "sg:address":"Tannenhof 3",
    "sg:city":"Deggenhausertal",
    "sg:phone":"+49 7555/5561",
    "sg:postcode":"88693",
    "sg:province":"Baden-W\u00fcrttemberg",
    "wof:name":"Karl Keller",
    "wof:placetype":"venue"
},
  "geometry": {"coordinates":[9.3795,47.751598],"type":"Point"}
}