{
  "type": "Feature",
  "properties": {
    "iso:country":"DE",
    "sg:address":"Neuenweger Reihe 1",
    "sg:city":"Hude",
    "sg:phone":"+49 4484/92800",
    "sg:postcode":"27798",
    "sg:province":"Niedersachsen",
    "wof:name":"Hubert Heinemann Steuerberater",
    "wof:placetype":"venue"
},
  "geometry": {"coordinates":[8.3153600693,53.1280899048],"type":"Point"}
}