{
  "type": "Feature",
  "properties": {
    "iso:country":"DE",
    "sg:address":"Auf'M Wasem 51",
    "sg:city":"Polch",
    "sg:phone":"+49 4952/2298470",
    "sg:postcode":"56751",
    "sg:province":"Rheinland-Pfalz",
    "wof:name":"Lothar A Wolf Spezialmaschinen Gmbh",
    "wof:placetype":"venue"
},
  "geometry": {"coordinates":[8.753662,52.069321],"type":"Point"}
}