{
  "type": "Feature",
  "properties": {
    "iso:country":"DE",
    "sg:address":"Lindenbergstr. 9 A",
    "sg:city":"Emmendingen",
    "sg:phone":"+49 7641/7841",
    "sg:postcode":"79312",
    "sg:province":"Baden-W\u00fcrttemberg",
    "wof:name":"Wieland H. Valasek Whv-dob Handelsvertreter Cdh",
    "wof:placetype":"venue"
},
  "geometry": {"coordinates":[7.8810148239,48.1168174744],"type":"Point"}
}