{
  "type": "Feature",
  "properties": {
    "iso:country":"DE",
    "sg:address":"Junkerstr. 20",
    "sg:city":"Eisenach",
    "sg:phone":"+49 3691/892932",
    "sg:postcode":"99817",
    "sg:province":"Th\u00fcringen",
    "wof:name":"D. Held Immobilienmakler",
    "wof:placetype":"venue"
},
  "geometry": {"coordinates":[10.3114862442,50.9874000549],"type":"Point"}
}