{
  "type": "Feature",
  "properties": {
    "iso:country":"DE",
    "sg:address":"M\u00f6nchstr. 50",
    "sg:city":"Marsberg",
    "sg:phone":"+49 2992/1254",
    "sg:postcode":"34431",
    "sg:province":"Nordrhein-Westfalen",
    "wof:name":"Dietmar Heinemann",
    "wof:placetype":"venue"
},
  "geometry": {"coordinates":[8.8604135513,51.4686737061],"type":"Point"}
}