{
  "type": "Feature",
  "properties": {
    "iso:country":"DE",
    "sg:address":"H\u00f6nnetalstr. 242",
    "sg:city":"Hemer",
    "sg:phone":"+49 271/780180",
    "sg:postcode":"58675",
    "sg:province":"Nordrhein-Westfalen",
    "wof:name":"Ihr-partner.net",
    "wof:placetype":"venue"
},
  "geometry": {"coordinates":[7.7900800705,51.3748397827],"type":"Point"}
}