{
  "type": "Feature",
  "properties": {
    "iso:country":"DE",
    "sg:address":"Hauptstr. 11",
    "sg:city":"Hedeper",
    "sg:phone":"+49 5336/277",
    "sg:postcode":"38322",
    "sg:province":"Niedersachsen",
    "wof:name":"E. Meier",
    "wof:placetype":"venue"
},
  "geometry": {"coordinates":[10.702706337,52.0689468384],"type":"Point"}
}