{
  "type": "Feature",
  "properties": {
    "iso:country":"DE",
    "sg:address":"Blierweg 1",
    "sg:city":"Wiesbaden",
    "sg:phone":"+49 611/182840",
    "sg:postcode":"65201",
    "sg:province":"Hessen",
    "wof:name":"Schiersteiner Blumengrosshandel Gmbh",
    "wof:placetype":"venue"
},
  "geometry": {"coordinates":[8.20633,50.051731],"type":"Point"}
}