{
  "type": "Feature",
  "properties": {
    "iso:country":"DE",
    "sg:address":"F\u00fcrther Str. 20a",
    "sg:city":"Berlin",
    "sg:phone":"+49 30/7443030",
    "sg:postcode":"12309",
    "sg:province":"Berlin",
    "wof:name":"V. Wierzbicki",
    "wof:placetype":"venue"
},
  "geometry": {"coordinates":[13.4199113846,52.3866615295],"type":"Point"}
}