{
  "type": "Feature",
  "properties": {
    "iso:country":"DE",
    "sg:address":"Am Sonnenhang 32",
    "sg:city":"Thyrnau",
    "sg:postcode":"94136",
    "sg:province":"Bayern",
    "wof:name":"Nasca Line Gmbh & Co. Kg",
    "wof:placetype":"venue"
},
  "geometry": {"coordinates":[13.54212,48.592468],"type":"Point"}
}