{
  "type": "Feature",
  "properties": {
    "iso:country":"DE",
    "sg:address":"Mittelstr. 1",
    "sg:city":"Crossen",
    "sg:phone":"+49 375/25664",
    "sg:postcode":"08129",
    "wof:name":"Tanzpalast Crossen Gastst\u00e4tte",
    "wof:placetype":"venue"
},
  "geometry": {"coordinates":[12.486919,50.759403],"type":"Point"}
}