{
  "type": "Feature",
  "properties": {
    "iso:country":"DE",
    "sg:address":"Dorfstr. 20",
    "sg:city":"Papendorf",
    "sg:phone":"+49 381/7611276",
    "sg:postcode":"18059",
    "sg:province":"Mecklenburg-Vorpommern",
    "wof:name":"Esb Computer Gmbh",
    "wof:placetype":"venue"
},
  "geometry": {"coordinates":[12.131599,54.035786],"type":"Point"}
}