{
  "type": "Feature",
  "properties": {
    "iso:country":"DE",
    "sg:address":"Ei\u00dfendorfer Str 118",
    "sg:city":"Hamburg",
    "sg:phone":"+49 40/7901750",
    "sg:postcode":"21073",
    "sg:province":"Hamburg",
    "wof:name":"Ballonwerbung Hamburg Gmbh",
    "wof:placetype":"venue"
},
  "geometry": {"coordinates":[9.95988,53.456909],"type":"Point"}
}