{
  "type": "Feature",
  "properties": {
    "iso:country":"DE",
    "sg:address":"Kirchstr. 29",
    "sg:city":"Heidenrod",
    "sg:phone":"+49 6775/269",
    "sg:postcode":"65321",
    "sg:province":"Hessen",
    "wof:name":"Herbert Ganser Bildhauer",
    "wof:placetype":"venue"
},
  "geometry": {"coordinates":[7.944828,50.146488],"type":"Point"}
}