{
  "type": "Feature",
  "properties": {
    "iso:country":"DE",
    "sg:address":"Drosselstr. 11",
    "sg:city":"Pliezhausen",
    "sg:postcode":"72124",
    "sg:province":"Baden-W\u00fcrttemberg",
    "wof:name":"Kosmetik-salon",
    "wof:placetype":"venue"
},
  "geometry": {"coordinates":[9.179595,48.572201],"type":"Point"}
}