{
  "type": "Feature",
  "properties": {
    "iso:country":"DE",
    "sg:address":"Hessingstr. 8",
    "sg:city":"Augsburg",
    "sg:phone":"+49 821/94972",
    "sg:postcode":"86199",
    "sg:province":"Bayern",
    "wof:name":"Parkcafe",
    "wof:placetype":"venue"
},
  "geometry": {"coordinates":[10.865144,48.339806],"type":"Point"}
}