{
  "type": "Feature",
  "properties": {
    "iso:country":"DE",
    "sg:address":"Maistr. 63",
    "sg:city":"M\u00fcnchen",
    "sg:phone":"+49 89/5401710",
    "sg:postcode":"80337",
    "sg:province":"Bayern",
    "wof:name":"Systembau Gmbh Das Etwas Andere Haus",
    "wof:placetype":"venue"
},
  "geometry": {"coordinates":[11.561412,48.126366],"type":"Point"}
}