{
  "type": "Feature",
  "properties": {
    "iso:country":"DE",
    "sg:address":"Am Milchbornsberg 11",
    "sg:city":"Bergisch Gladbach",
    "sg:phone":"+49 2204/911534",
    "sg:postcode":"51429",
    "sg:province":"Nordrhein-Westfalen",
    "wof:name":"Dr. Gerald Kl\u00f6psch Ingenieur",
    "wof:placetype":"venue"
},
  "geometry": {"coordinates":[7.1584148407,50.9686698914],"type":"Point"}
}