{
  "type": "Feature",
  "properties": {
    "iso:country":"DE",
    "sg:address":"Elisabethenstr. 2",
    "sg:city":"Montabaur",
    "sg:phone":"+49 2602/3376",
    "sg:postcode":"56410",
    "sg:province":"Rheinland-Pfalz",
    "wof:name":"Kremers",
    "wof:placetype":"venue"
},
  "geometry": {"coordinates":[7.8324360847,50.4351577759],"type":"Point"}
}