{
  "type": "Feature",
  "properties": {
    "iso:country":"DE",
    "sg:city":"L\u00fctjenburg",
    "sg:phone":"+49 4381/418663",
    "sg:postcode":"24321",
    "sg:province":"Schleswig-Holstein",
    "wof:name":"F. Donothek",
    "wof:placetype":"venue"
},
  "geometry": {"coordinates":[10.583598,54.288204],"type":"Point"}
}