{
  "type": "Feature",
  "properties": {
    "iso:country":"DE",
    "sg:address":"Am Grundweg 20",
    "sg:city":"Seeheim-Jugenheim",
    "sg:phone":"+49 6257/962485",
    "sg:postcode":"64342",
    "sg:province":"Hessen",
    "wof:name":"Horst Henkel Steuerberater",
    "wof:placetype":"venue"
},
  "geometry": {"coordinates":[8.6422100067,49.769241333],"type":"Point"}
}