{
  "type": "Feature",
  "properties": {
    "iso:country":"DE",
    "sg:address":"Schillerstr. 12",
    "sg:city":"Frankfurt",
    "sg:phone":"+49 69/280786",
    "sg:postcode":"60313",
    "sg:province":"Hessen",
    "wof:name":"Scheich & Partner B\u00f6rsenmakler Gmbh",
    "wof:placetype":"venue"
},
  "geometry": {"coordinates":[8.678646,50.114834],"type":"Point"}
}