{
  "type": "Feature",
  "properties": {
    "iso:country":"DE",
    "sg:address":"B\u00f6hmerstr. 1",
    "sg:city":"R\u00f6tz",
    "sg:phone":"+49 9976/1502",
    "sg:postcode":"92444",
    "sg:province":"Bayern",
    "wof:name":"Schmidt Bank",
    "wof:placetype":"venue"
},
  "geometry": {"coordinates":[12.52924,49.342281],"type":"Point"}
}