{
  "type": "Feature",
  "properties": {
    "iso:country":"DE",
    "sg:address":"St.-Nazairer-Allee 26",
    "sg:city":"Saarlouis",
    "sg:phone":"+49 6831/3691",
    "sg:postcode":"66740",
    "sg:province":"Saarland",
    "wof:name":"Azur Camping Dr. Dadder",
    "wof:placetype":"venue"
},
  "geometry": {"coordinates":[6.740405,49.319523],"type":"Point"}
}