{
  "type": "Feature",
  "properties": {
    "iso:country":"DE",
    "sg:address":"Speckmannstr. 10",
    "sg:city":"Grasberg",
    "sg:phone":"+49 4208/1718",
    "sg:postcode":"28879",
    "sg:province":"Niedersachsen",
    "wof:name":"Horst Schimpf",
    "wof:placetype":"venue"
},
  "geometry": {"coordinates":[8.9831161499,53.1824188232],"type":"Point"}
}