{
  "type": "Feature",
  "properties": {
    "iso:country":"DE",
    "sg:address":"Elbchaussee 359",
    "sg:city":"Hamburg",
    "sg:phone":"+49 40/825644",
    "sg:postcode":"22609",
    "sg:province":"Hamburg",
    "wof:name":"Bisig Gro\u00dfforschungs- Und Informationsb\u00fcro",
    "wof:placetype":"venue"
},
  "geometry": {"coordinates":[9.854013,53.548828],"type":"Point"}
}