{
  "type": "Feature",
  "properties": {
    "iso:country":"DE",
    "sg:address":"Neuer Markt 5",
    "sg:city":"Leinfelden-Echterdingen",
    "sg:phone":"+49 711/752680",
    "sg:postcode":"70771",
    "sg:province":"Baden-W\u00fcrttemberg",
    "wof:name":"M\u00fcller Parf\u00fcmerie Und Mode Gmbh",
    "wof:placetype":"venue"
},
  "geometry": {"coordinates":[9.14308,48.693932],"type":"Point"}
}