{
  "type": "Feature",
  "properties": {
    "iso:country":"DE",
    "sg:address":"Amselstr. 21",
    "sg:city":"Berlin",
    "sg:phone":"+49 30/8325215",
    "sg:postcode":"14195",
    "sg:province":"Berlin",
    "wof:name":"Wolfgang Rabensdorf Steuerberater Und",
    "wof:placetype":"venue"
},
  "geometry": {"coordinates":[13.282579422,52.4673957825],"type":"Point"}
}