{
  "type": "Feature",
  "properties": {
    "iso:country":"DE",
    "sg:address":"Schulstr. 47",
    "sg:city":"Mengersgereuth-H\u00e4mmern",
    "sg:phone":"+49 3675/746140",
    "sg:postcode":"96529",
    "sg:province":"Th\u00fcringen",
    "wof:name":"Helga Seeler",
    "wof:placetype":"venue"
},
  "geometry": {"coordinates":[11.114619,50.412529],"type":"Point"}
}