{
  "type": "Feature",
  "properties": {
    "iso:country":"DE",
    "sg:address":"M\u00e4rkische Str. 115-117",
    "sg:city":"Dortmund",
    "sg:phone":"+49 231/5569190",
    "sg:postcode":"44141",
    "sg:province":"Nordrhein-Westfalen",
    "wof:name":"Pro Data Gmbh",
    "wof:placetype":"venue"
},
  "geometry": {"coordinates":[7.480146,51.502087],"type":"Point"}
}