{
  "type": "Feature",
  "properties": {
    "iso:country":"DE",
    "sg:address":"Jahnstr. 25",
    "sg:city":"Ransbach-Baumbach",
    "sg:phone":"+49 2623/2378",
    "sg:postcode":"56235",
    "sg:province":"Rheinland-Pfalz",
    "wof:name":"Josef Tries Gmbh",
    "wof:placetype":"venue"
},
  "geometry": {"coordinates":[7.73829,50.467171],"type":"Point"}
}