{
  "type": "Feature",
  "properties": {
    "iso:country":"DE",
    "sg:address":"Unterdorf 60",
    "sg:city":"Osterode",
    "sg:phone":"+49 5522/951083",
    "sg:postcode":"37520",
    "sg:province":"Niedersachsen",
    "wof:name":"Sporteck Hausmann",
    "wof:placetype":"venue"
},
  "geometry": {"coordinates":[10.218076,51.746246],"type":"Point"}
}