{
  "type": "Feature",
  "properties": {
    "iso:country":"DE",
    "sg:address":"Im Gr\u00fcn 19",
    "sg:city":"Bad Krozingen",
    "sg:phone":"+49 7633/2752",
    "sg:postcode":"79189",
    "sg:province":"Baden-W\u00fcrttemberg",
    "wof:name":"E. Binz Immobilienmakler",
    "wof:placetype":"venue"
},
  "geometry": {"coordinates":[7.6688499451,47.9542274475],"type":"Point"}
}