{
  "type": "Feature",
  "properties": {
    "iso:country":"DE",
    "sg:address":"Sch\u00fctzenstr. 30",
    "sg:city":"Remscheid",
    "sg:phone":"+49 2191/29925",
    "sg:postcode":"42853",
    "sg:province":"Nordrhein-Westfalen",
    "wof:name":"Benscheid Kraus Und Weckbrodt Rechtsanw\u00e4lte",
    "wof:placetype":"venue"
},
  "geometry": {"coordinates":[7.184445858,51.1834068298],"type":"Point"}
}