{
  "type": "Feature",
  "properties": {
    "iso:country":"DE",
    "sg:address":"Albert-Einstein-Str. 67",
    "sg:city":"F\u00fcrth",
    "sg:phone":"+49 911/758318",
    "sg:postcode":"90766",
    "sg:province":"Bayern",
    "wof:name":"Elisabeth Flaton",
    "wof:placetype":"venue"
},
  "geometry": {"coordinates":[10.950255394,49.4781990051],"type":"Point"}
}