{
  "type": "Feature",
  "properties": {
    "iso:country":"DE",
    "sg:address":"Lessingstr. 20",
    "sg:city":"Leipzig",
    "sg:phone":"+49 341",
    "sg:postcode":"04109",
    "sg:province":"Sachsen",
    "wof:name":"Ferdinand Zierof",
    "wof:placetype":"venue"
},
  "geometry": {"coordinates":[12.364563942,51.3421669006],"type":"Point"}
}