{
  "type": "Feature",
  "properties": {
    "iso:country":"DE",
    "sg:address":"Hauptstr. 5",
    "sg:city":"Hemer",
    "sg:phone":"+49 2372/500003",
    "sg:postcode":"58675",
    "sg:province":"Nordrhein-Westfalen",
    "wof:name":"Pool Touristik Gmbh",
    "wof:placetype":"venue"
},
  "geometry": {"coordinates":[7.7566900253,51.3744773865],"type":"Point"}
}