{
  "type": "Feature",
  "properties": {
    "iso:country":"DE",
    "sg:address":"Bautzner Landstr. 12",
    "sg:city":"Dresden",
    "sg:phone":"+49 351/2684395",
    "sg:postcode":"01324",
    "sg:province":"Sachsen",
    "wof:name":"Klemm",
    "wof:placetype":"venue"
},
  "geometry": {"coordinates":[13.8626537323,51.0603103638],"type":"Point"}
}