{
  "type": "Feature",
  "properties": {
    "iso:country":"DE",
    "sg:address":"Sch\u00fctzenstr. 15",
    "sg:city":"Berlin",
    "sg:phone":"+49 30/7912828",
    "sg:postcode":"12165",
    "sg:province":"Berlin",
    "wof:name":"Thoko Brillenfassungsvertrieb Thomas Konieczny",
    "wof:placetype":"venue"
},
  "geometry": {"coordinates":[13.3226613998,52.4535102844],"type":"Point"}
}