{
  "type": "Feature",
  "properties": {
    "iso:country":"DE",
    "sg:address":"Wandsbeker Marktstr. 20",
    "sg:city":"Hamburg",
    "sg:phone":"+49 40/680606",
    "sg:postcode":"22041",
    "sg:province":"Hamburg",
    "wof:name":"Michael Tauck Rechtsanwalt",
    "wof:placetype":"venue"
},
  "geometry": {"coordinates":[10.0623931885,53.570728302],"type":"Point"}
}