{
  "type": "Feature",
  "properties": {
    "iso:country":"DE",
    "sg:address":"Moselstr. 109b",
    "sg:city":"Troisdorf",
    "sg:phone":"+49 2241/805026",
    "sg:postcode":"53842",
    "sg:province":"Nordrhein-Westfalen",
    "wof:name":"H. Severin",
    "wof:placetype":"venue"
},
  "geometry": {"coordinates":[7.1478910446,50.8070526123],"type":"Point"}
}