{
  "type": "Feature",
  "properties": {
    "iso:country":"DE",
    "sg:address":"Im Eichengrund 34",
    "sg:city":"Berlin",
    "sg:phone":"+49 30/3817834",
    "sg:postcode":"13629",
    "sg:province":"Berlin",
    "wof:name":"Heinr. Bernhard Vo\u00dfeb\u00fcrger Architekt",
    "wof:placetype":"venue"
},
  "geometry": {"coordinates":[13.265571,52.545876],"type":"Point"}
}