{
  "type": "Feature",
  "properties": {
    "iso:country":"DE",
    "sg:address":"Dehnitzer Weg 32",
    "sg:city":"Wurzen",
    "sg:phone":"+49 3425/812422",
    "sg:postcode":"04808",
    "sg:province":"Sachsen",
    "wof:name":"Spartenheim",
    "wof:placetype":"venue"
},
  "geometry": {"coordinates":[12.7328929901,51.3608856201],"type":"Point"}
}