{
  "type": "Feature",
  "properties": {
    "iso:country":"DE",
    "sg:address":"Twistringer Str. 18",
    "sg:city":"Bremen",
    "sg:phone":"+49 421/3961619",
    "sg:postcode":"28217",
    "sg:province":"Bremen",
    "wof:name":"T. Schlingmann Rechtsanwalt",
    "wof:placetype":"venue"
},
  "geometry": {"coordinates":[8.7845439911,53.0953102112],"type":"Point"}
}