{
  "type": "Feature",
  "properties": {
    "iso:country":"DE",
    "sg:address":"Adalbertstr. 24",
    "sg:city":"Frankfurt",
    "sg:phone":"+49 69/778985",
    "sg:postcode":"60486",
    "sg:province":"Hessen",
    "wof:name":"Renate Birckenstaedt Rechtsanwalt",
    "wof:placetype":"venue"
},
  "geometry": {"coordinates":[8.6468305588,50.1198005676],"type":"Point"}
}