{
  "type": "Feature",
  "properties": {
    "iso:country":"DE",
    "sg:address":"Lindenstr. 71",
    "sg:city":"Bad Essen",
    "sg:phone":"+49 5472/1442",
    "sg:postcode":"49152",
    "sg:province":"Niedersachsen",
    "wof:name":"Potthoff",
    "wof:placetype":"venue"
},
  "geometry": {"coordinates":[8.3480873108,52.3187561035],"type":"Point"}
}