{
  "type": "Feature",
  "properties": {
    "iso:country":"DE",
    "sg:address":"Rosenheimer Str 109",
    "sg:city":"M\u00fcnchen",
    "sg:phone":"+49 89/4599590",
    "sg:postcode":"81667",
    "sg:province":"Bayern",
    "wof:name":"Blitz-team Gmbh",
    "wof:placetype":"venue"
},
  "geometry": {"coordinates":[11.5970172882,48.1268959045],"type":"Point"}
}