{
  "type": "Feature",
  "properties": {
    "iso:country":"DE",
    "sg:address":"Jahnstr. 5",
    "sg:city":"Jena",
    "sg:phone":"+49 3641/445353",
    "sg:postcode":"07743",
    "sg:province":"Th\u00fcringen",
    "wof:name":"Heinrich Teichmann",
    "wof:placetype":"venue"
},
  "geometry": {"coordinates":[11.5780754089,50.9285392761],"type":"Point"}
}