{
  "type": "Feature",
  "properties": {
    "iso:country":"DE",
    "sg:address":"Stockweg 9",
    "sg:city":"M\u00fclheim",
    "sg:phone":"+49 208/480000",
    "sg:postcode":"45481",
    "sg:province":"Nordrhein-Westfalen",
    "wof:name":"Wiegand & Partner Gmbh",
    "wof:placetype":"venue"
},
  "geometry": {"coordinates":[6.86211586,51.3661193848],"type":"Point"}
}