{
  "type": "Feature",
  "properties": {
    "iso:country":"DE",
    "sg:address":"Jexm\u00fchle 76",
    "sg:city":"Lohmar",
    "sg:phone":"+49 2206/7296",
    "sg:postcode":"53797",
    "sg:province":"Nordrhein-Westfalen",
    "wof:name":"Norbert Kalsbach",
    "wof:placetype":"venue"
},
  "geometry": {"coordinates":[7.2504601479,50.9105987549],"type":"Point"}
}