{
  "type": "Feature",
  "properties": {
    "iso:country":"DE",
    "sg:address":"Rosenstr. 8",
    "sg:city":"Sch\u00f6naich",
    "sg:phone":"+49 7031/650933",
    "sg:postcode":"71101",
    "sg:province":"Baden-W\u00fcrttemberg",
    "wof:name":"E. Gold",
    "wof:placetype":"venue"
},
  "geometry": {"coordinates":[9.0620298386,48.6571350098],"type":"Point"}
}