{
  "type": "Feature",
  "properties": {
    "iso:country":"DE",
    "sg:address":"Feldstr. 35b",
    "sg:city":"Greifswald",
    "sg:phone":"+49 3834/501830",
    "sg:postcode":"17489",
    "sg:province":"Mecklenburg-Vorpommern",
    "wof:name":"Axel G\u00fcnter",
    "wof:placetype":"venue"
},
  "geometry": {"coordinates":[13.388085,54.085381],"type":"Point"}
}