{
  "type": "Feature",
  "properties": {
    "iso:country":"DE",
    "sg:address":"Trakehner Str 3",
    "sg:city":"Frankfurt",
    "sg:phone":"+49 69/71650",
    "sg:postcode":"60487",
    "sg:province":"Hessen",
    "wof:name":"Chemetall Gmbh Division Sondermetalle",
    "wof:placetype":"venue"
},
  "geometry": {"coordinates":[8.629498,50.126816],"type":"Point"}
}