{
  "type": "Feature",
  "properties": {
    "iso:country":"DE",
    "sg:address":"Salzstr. 14-15",
    "sg:city":"M\u00fcnster",
    "sg:phone":"+49 251/519210",
    "sg:postcode":"48143",
    "sg:province":"Nordrhein-Westfalen",
    "wof:name":"Deutsche Telekom T-punkt",
    "wof:placetype":"venue"
},
  "geometry": {"coordinates":[7.6311340332,51.9618453979],"type":"Point"}
}