{
  "type": "Feature",
  "properties": {
    "iso:country":"DE",
    "sg:address":"Untere Seelenhalde 19",
    "sg:city":"Wildberg",
    "sg:phone":"+49 7054/333",
    "sg:postcode":"72218",
    "sg:province":"Baden-W\u00fcrttemberg",
    "wof:name":"Weber Vermittlungsgesellschaft F\u00fcr Verm\u00f6gensanlagen Und",
    "wof:placetype":"venue"
},
  "geometry": {"coordinates":[8.7701349258,48.6419181824],"type":"Point"}
}