{
  "type": "Feature",
  "properties": {
    "iso:country":"DE",
    "sg:address":"Rehsteig 20",
    "sg:city":"W\u00f6rthsee",
    "sg:phone":"+49 8153/8183",
    "sg:postcode":"82237",
    "sg:province":"Bayern",
    "wof:name":"Dr. Werner Hinze Rechtsanwalt",
    "wof:placetype":"venue"
},
  "geometry": {"coordinates":[11.1996202469,48.0730323792],"type":"Point"}
}