{
  "type": "Feature",
  "properties": {
    "iso:country":"DE",
    "sg:address":"Pfefferhof 1",
    "sg:city":"Dietmannsried",
    "sg:phone":"+49 8374",
    "sg:postcode":"87463",
    "sg:province":"Bayern",
    "wof:name":"Gutachten F\u00fcr Bebaute Und Unbebaute Grundst. Landw./gastgew.",
    "wof:placetype":"venue"
},
  "geometry": {"coordinates":[10.2875614166,47.8527145386],"type":"Point"}
}