{
  "type": "Feature",
  "properties": {
    "iso:country":"DE",
    "sg:address":"B\u00fcchnerweg 16",
    "sg:city":"Berlin",
    "sg:phone":"+49 30/4628110",
    "sg:postcode":"12489",
    "sg:province":"Berlin",
    "wof:name":"Wehrfritz Gmbh",
    "wof:placetype":"venue"
},
  "geometry": {"coordinates":[13.5567455292,52.4366493225],"type":"Point"}
}