{
  "type": "Feature",
  "properties": {
    "iso:country":"DE",
    "sg:address":"W\u00f6rpedahler Str. 50",
    "sg:city":"Bremen",
    "sg:phone":"+49 421/645556",
    "sg:postcode":"28719",
    "sg:province":"Bremen",
    "wof:name":"G\u00fcnter Kadagies",
    "wof:placetype":"venue"
},
  "geometry": {"coordinates":[8.740865,53.163597],"type":"Point"}
}