{
  "type": "Feature",
  "properties": {
    "iso:country":"DE",
    "sg:address":"Kl\u00f6terh\u00f6rn 2",
    "sg:city":"Hitzacker",
    "sg:phone":"+49 5858/231",
    "sg:postcode":"29456",
    "sg:province":"Niedersachsen",
    "wof:name":"Gs Handel Und Consulting Import Export Gmbh",
    "wof:placetype":"venue"
},
  "geometry": {"coordinates":[10.934732,53.184677],"type":"Point"}
}