{
  "type": "Feature",
  "properties": {
    "iso:country":"DE",
    "sg:address":"An der Landwehr 53",
    "sg:city":"Kriftel",
    "sg:phone":"+49 6192/42194",
    "sg:postcode":"65830",
    "sg:province":"Hessen",
    "wof:name":"M. Pfaff Kg Kohlenhandlung",
    "wof:placetype":"venue"
},
  "geometry": {"coordinates":[8.467936,50.078739],"type":"Point"}
}