{
  "type": "Feature",
  "properties": {
    "iso:country":"DE",
    "sg:address":"Schorndorfer Str.",
    "sg:city":"Ludwigsburg",
    "sg:phone":"+49 7141/869730",
    "sg:postcode":"71638",
    "sg:province":"Baden-W\u00fcrttemberg",
    "wof:name":"Siegfried Rothfuss Digitale Printmedien Gmbh",
    "wof:placetype":"venue"
},
  "geometry": {"coordinates":[9.20678,48.896023],"type":"Point"}
}