{
  "type": "Feature",
  "properties": {
    "iso:country":"DE",
    "sg:address":"Polytec Pl 1-7",
    "sg:city":"Waldbronn",
    "sg:phone":"+49 7243/604100",
    "sg:postcode":"76337",
    "sg:province":"Baden-W\u00fcrttemberg",
    "wof:name":"Physik Instrumente Gmbh",
    "wof:placetype":"venue"
},
  "geometry": {"coordinates":[8.4904403687,48.9261207581],"type":"Point"}
}