{
  "type": "Feature",
  "properties": {
    "iso:country":"DE",
    "sg:address":"N\u00f6rdliche Hildapromenade 6",
    "sg:city":"Karlsruhe",
    "sg:phone":"+49 721/845143",
    "sg:postcode":"76133",
    "sg:province":"Baden-W\u00fcrttemberg",
    "wof:name":"Werner Sch\u00e4fer",
    "wof:placetype":"venue"
},
  "geometry": {"coordinates":[8.3791389465,49.0134391785],"type":"Point"}
}