{
  "type": "Feature",
  "properties": {
    "iso:country":"DE",
    "sg:address":"W\u00fcllmersen 10",
    "sg:city":"Mehmke",
    "sg:postcode":"29413",
    "sg:province":"Sachsen-Anhalt",
    "wof:name":"Jens Gromeier Gmbh & Co. Kg",
    "wof:placetype":"venue"
},
  "geometry": {"coordinates":[10.881906,52.752426],"type":"Point"}
}