{
  "type": "Feature",
  "properties": {
    "iso:country":"DE",
    "sg:address":"Am K\u00f6llnischen Park 1",
    "sg:city":"Berlin",
    "sg:phone":"+49 30/5577190",
    "sg:postcode":"10179",
    "sg:province":"Berlin",
    "wof:name":"Ikb Immobilien Leasing Gmbh",
    "wof:placetype":"venue"
},
  "geometry": {"coordinates":[13.415524,52.511887],"type":"Point"}
}