{
  "type": "Feature",
  "properties": {
    "iso:country":"DE",
    "sg:address":"Schlo\u00dfstr. 52",
    "sg:city":"Schw\u00e4bisch Gm\u00fcnd",
    "sg:phone":"+49 7171/72138",
    "sg:postcode":"73527",
    "sg:province":"Baden-W\u00fcrttemberg",
    "wof:name":"Kolb Omnibusverkehr Gmbh",
    "wof:placetype":"venue"
},
  "geometry": {"coordinates":[9.8130102158,48.8299789429],"type":"Point"}
}