{
  "type": "Feature",
  "properties": {
    "iso:country":"DE",
    "sg:address":"Schleienstr. 1",
    "sg:city":"Emden",
    "sg:phone":"+49 4921/31200",
    "sg:postcode":"26725",
    "sg:province":"Niedersachsen",
    "wof:name":"Jan Smidt",
    "wof:placetype":"venue"
},
  "geometry": {"coordinates":[7.251607,53.386127],"type":"Point"}
}