{
  "type": "Feature",
  "properties": {
    "iso:country":"DE",
    "sg:address":"Hackstr. 33",
    "sg:city":"Stuttgart",
    "sg:phone":"+49 711/9254230",
    "sg:postcode":"70190",
    "sg:province":"Baden-W\u00fcrttemberg",
    "wof:name":"Ahorn Trauerhilfe Gmbh",
    "wof:placetype":"venue"
},
  "geometry": {"coordinates":[9.201627,48.789337],"type":"Point"}
}