{
  "type": "Feature",
  "properties": {
    "iso:country":"DE",
    "sg:address":"Am Radacker 11",
    "sg:city":"Freiburg",
    "sg:phone":"+49 761/493000",
    "sg:postcode":"79115",
    "sg:province":"Baden-W\u00fcrttemberg",
    "wof:name":"Broszeit-bedachungen Gmbh",
    "wof:placetype":"venue"
},
  "geometry": {"coordinates":[7.830463,47.986553],"type":"Point"}
}