{
  "type": "Feature",
  "properties": {
    "iso:country":"DE",
    "sg:address":"Kahlertstr. 63",
    "sg:city":"G\u00fctersloh",
    "sg:phone":"+49 5241/36912",
    "sg:postcode":"33330",
    "sg:province":"Nordrhein-Westfalen",
    "wof:name":"Heinrich Hunke",
    "wof:placetype":"venue"
},
  "geometry": {"coordinates":[8.38365,51.916832],"type":"Point"}
}