{
  "type": "Feature",
  "properties": {
    "iso:country":"DE",
    "sg:address":"Kanalstr. 28",
    "sg:city":"M\u00fchlacker",
    "sg:phone":"+49 7041/96390",
    "sg:postcode":"75417",
    "sg:province":"Baden-W\u00fcrttemberg",
    "wof:name":"Wohnland Enzberg M\u00f6beleinrichtungs Gmbh",
    "wof:placetype":"venue"
},
  "geometry": {"coordinates":[8.804801,48.93327],"type":"Point"}
}