{
  "type": "Feature",
  "properties": {
    "iso:country":"DE",
    "sg:address":"Billstr. 28",
    "sg:city":"Hamburg",
    "sg:phone":"+49 40/78942222",
    "sg:postcode":"20539",
    "sg:province":"Hamburg",
    "wof:name":"Multi-b\u00fcro-service T. M. Pfefferkorn",
    "wof:placetype":"venue"
},
  "geometry": {"coordinates":[10.0344944,53.5413894653],"type":"Point"}
}