{
  "type": "Feature",
  "properties": {
    "iso:country":"DE",
    "sg:address":"Am Herrenland 1",
    "sg:city":"Spangenberg",
    "sg:phone":"+49 5663/1029",
    "sg:postcode":"34286",
    "sg:province":"Hessen",
    "wof:name":"Cafe-restaurant Schlo\u00dfblick",
    "wof:placetype":"venue"
},
  "geometry": {"coordinates":[9.6711168289,51.1198997498],"type":"Point"}
}