{
  "type": "Feature",
  "properties": {
    "iso:country":"DE",
    "sg:address":"Brunnenstr. 4",
    "sg:city":"Kleinwallstadt",
    "sg:phone":"+49 6022/21636",
    "sg:postcode":"63839",
    "sg:province":"Bayern",
    "wof:name":"W. Sch\u00f6hl",
    "wof:placetype":"venue"
},
  "geometry": {"coordinates":[9.165728,49.877052],"type":"Point"}
}