{
  "type": "Feature",
  "properties": {
    "iso:country":"DE",
    "sg:address":"Sperberweg 22",
    "sg:city":"Straubing",
    "sg:phone":"+49 9421/61249",
    "sg:postcode":"94315",
    "sg:province":"Bayern",
    "wof:name":"Manfred Neuner Ingenieur",
    "wof:placetype":"venue"
},
  "geometry": {"coordinates":[12.594745636,48.8775558472],"type":"Point"}
}