{
  "type": "Feature",
  "properties": {
    "iso:country":"DE",
    "sg:address":"Fabrikstr. 3",
    "sg:city":"Freigericht",
    "sg:phone":"+49 6055/2011",
    "sg:postcode":"63579",
    "sg:province":"Hessen",
    "wof:name":"Wema Probst Wolfgang Hofmann Kg",
    "wof:placetype":"venue"
},
  "geometry": {"coordinates":[9.1390476227,50.1260604858],"type":"Point"}
}