{
  "type": "Feature",
  "properties": {
    "iso:country":"DE",
    "sg:address":"Talstr. 30",
    "sg:city":"Ingersheim",
    "sg:postcode":"74379",
    "sg:province":"Baden-W\u00fcrttemberg",
    "wof:name":"Gip Gewerbe Und Industrie Park Verwaltungs- Gmbh",
    "wof:placetype":"venue"
},
  "geometry": {"coordinates":[9.1921205521,48.9641456604],"type":"Point"}
}