{
  "type": "Feature",
  "properties": {
    "iso:country":"DE",
    "sg:address":"Am Luftschacht 13",
    "sg:city":"Gelsenkirchen",
    "sg:phone":"+49 209/201222",
    "sg:postcode":"45886",
    "sg:province":"Nordrhein-Westfalen",
    "wof:name":"H. U. Wasiek",
    "wof:placetype":"venue"
},
  "geometry": {"coordinates":[7.130625,51.502205],"type":"Point"}
}