{
  "type": "Feature",
  "properties": {
    "iso:country":"DE",
    "sg:address":"Landwehrstr. 17",
    "sg:city":"Dortmund",
    "sg:phone":"+49 231/7282578",
    "sg:postcode":"44147",
    "sg:province":"Nordrhein-Westfalen",
    "wof:name":"Kanal",
    "wof:placetype":"venue"
},
  "geometry": {"coordinates":[7.4456830025,51.5192871094],"type":"Point"}
}