{
  "type": "Feature",
  "properties": {
    "iso:country":"DE",
    "sg:address":"Marktstr. 21",
    "sg:city":"Bad Ems",
    "sg:phone":"+49 2603/13016",
    "sg:postcode":"56130",
    "sg:province":"Rheinland-Pfalz",
    "wof:name":"Siegfried Hof",
    "wof:placetype":"venue"
},
  "geometry": {"coordinates":[7.7130360603,50.3373565674],"type":"Point"}
}