{
  "type": "Feature",
  "properties": {
    "iso:country":"DE",
    "sg:address":"Jahnstr. 31",
    "sg:city":"Kleinwallstadt",
    "sg:phone":"+49 6022/20775",
    "sg:postcode":"63839",
    "sg:province":"Bayern",
    "wof:name":"Richard Markert",
    "wof:placetype":"venue"
},
  "geometry": {"coordinates":[9.1654167175,49.8664588928],"type":"Point"}
}