{
  "type": "Feature",
  "properties": {
    "iso:country":"DE",
    "sg:address":"Steinrainer Str. 9",
    "sg:city":"Mallersdorf-Pfaffenberg",
    "sg:phone":"+49 8772/239",
    "sg:postcode":"84066",
    "sg:province":"Bayern",
    "wof:name":"Zimmermann",
    "wof:placetype":"venue"
},
  "geometry": {"coordinates":[12.2257966995,48.7687911987],"type":"Point"}
}