{
  "type": "Feature",
  "properties": {
    "iso:country":"DE",
    "sg:address":"Bachstr. 4",
    "sg:city":"Marburg",
    "sg:phone":"+49 6421/82336",
    "sg:postcode":"35043",
    "sg:province":"Hessen",
    "wof:name":"Aloys Kraus",
    "wof:placetype":"venue"
},
  "geometry": {"coordinates":[8.818191,50.840549],"type":"Point"}
}