{
  "type": "Feature",
  "properties": {
    "iso:country":"DE",
    "sg:address":"Hemmerichstr. 8",
    "sg:city":"Bad Kissingen",
    "sg:phone":"+49 971/4650",
    "sg:postcode":"97688",
    "sg:province":"Bayern",
    "wof:name":"Aral Tankstelle",
    "wof:placetype":"venue"
},
  "geometry": {"coordinates":[10.0804214478,50.2019577026],"type":"Point"}
}