{
  "type": "Feature",
  "properties": {
    "iso:country":"DE",
    "sg:address":"Lohbr\u00fcgger Landstr 106a",
    "sg:city":"Hamburg",
    "sg:phone":"+49 40/7399996",
    "sg:postcode":"21031",
    "sg:province":"Hamburg",
    "wof:name":"Heinrich Br\u00fcgmann & Co",
    "wof:placetype":"venue"
},
  "geometry": {"coordinates":[10.193538,53.503227],"type":"Point"}
}