{
  "type": "Feature",
  "properties": {
    "iso:country":"DE",
    "sg:address":"Hauptstr. 236",
    "sg:city":"Hohwald",
    "sg:phone":"+49 3596/504777",
    "sg:postcode":"01844",
    "sg:province":"Sachsen",
    "wof:name":"W. Pietsch",
    "wof:placetype":"venue"
},
  "geometry": {"coordinates":[14.216246,51.03014],"type":"Point"}
}