{
  "type": "Feature",
  "properties": {
    "iso:country":"DE",
    "sg:address":"Baumholderstr. 14",
    "sg:city":"Freisen",
    "sg:phone":"+49 6855/1213",
    "sg:postcode":"66629",
    "sg:province":"Saarland",
    "wof:name":"Batschkapp",
    "wof:placetype":"venue"
},
  "geometry": {"coordinates":[7.250369072,49.5529251099],"type":"Point"}
}