{
  "type": "Feature",
  "properties": {
    "iso:country":"DE",
    "sg:address":"W\u00f6lckernstr. 71",
    "sg:city":"N\u00fcrnberg",
    "sg:phone":"+49 911/440458",
    "sg:postcode":"90459",
    "sg:province":"Bayern",
    "wof:name":"Lederwaren Albrecht E. K.",
    "wof:placetype":"venue"
},
  "geometry": {"coordinates":[11.089392,49.441574],"type":"Point"}
}