{
  "type": "Feature",
  "properties": {
    "iso:country":"DE",
    "sg:address":"Urbanstr. 84",
    "sg:city":"Stuttgart",
    "sg:phone":"+49 711/2265814",
    "sg:postcode":"70182",
    "sg:province":"Baden-W\u00fcrttemberg",
    "wof:name":"S. Sauter Und J. Munzig Architekten",
    "wof:placetype":"venue"
},
  "geometry": {"coordinates":[9.19001,48.782993],"type":"Point"}
}