{
  "type": "Feature",
  "properties": {
    "iso:country":"DE",
    "sg:address":"Heinrich-Heyd-Str. 24",
    "sg:city":"Pforzheim",
    "sg:phone":"+49 7231/765770",
    "sg:postcode":"75180",
    "sg:province":"Baden-W\u00fcrttemberg",
    "wof:name":"Ims Gmbh",
    "wof:placetype":"venue"
},
  "geometry": {"coordinates":[8.6658725739,48.8764877319],"type":"Point"}
}