{
  "type": "Feature",
  "properties": {
    "iso:country":"DE",
    "sg:address":"Hauptstr. 19",
    "sg:city":"Achslach",
    "sg:phone":"+49 9929/902103",
    "sg:postcode":"94250",
    "sg:province":"Bayern",
    "wof:name":"\u00d6ko-power Gmbh",
    "wof:placetype":"venue"
},
  "geometry": {"coordinates":[12.936652,48.970505],"type":"Point"}
}