{
  "type": "Feature",
  "properties": {
    "iso:country":"DE",
    "sg:address":"Herforder Str. 141",
    "sg:city":"Bielefeld",
    "sg:phone":"+49 521/31140",
    "sg:postcode":"33609",
    "sg:province":"Nordrhein-Westfalen",
    "wof:name":"Kleinesdar W\u00e4rmetechnik Gmbh",
    "wof:placetype":"venue"
},
  "geometry": {"coordinates":[8.5467233658,52.0343322754],"type":"Point"}
}