{
  "type": "Feature",
  "properties": {
    "iso:country":"DE",
    "sg:address":"Friedrich-Ebert-Str. 193",
    "sg:city":"Duisburg",
    "sg:phone":"+49 203/491934",
    "sg:postcode":"47179",
    "sg:province":"Nordrhein-Westfalen",
    "wof:name":"L. Depping Und C. Bartholme",
    "wof:placetype":"venue"
},
  "geometry": {"coordinates":[6.7425990105,51.5268096924],"type":"Point"}
}