{
  "type": "Feature",
  "properties": {
    "iso:country":"DE",
    "sg:address":"Riedh\u00f6fe 2",
    "sg:city":"Ihringen",
    "sg:phone":"+49 7668/5511",
    "sg:postcode":"79241",
    "sg:province":"Baden-W\u00fcrttemberg",
    "wof:name":"Horst Schillinger",
    "wof:placetype":"venue"
},
  "geometry": {"coordinates":[7.6477799416,48.0352287292],"type":"Point"}
}