{
  "type": "Feature",
  "properties": {
    "iso:country":"DE",
    "sg:address":"Neue Stra\u00dfe 75",
    "sg:city":"Salzgitter",
    "sg:phone":"+49 5341",
    "sg:postcode":"38259",
    "sg:province":"Niedersachsen",
    "wof:name":"Maschinenfabrik Knaup Gmbh & Co.",
    "wof:placetype":"venue"
},
  "geometry": {"coordinates":[10.4431467056,52.0781784058],"type":"Point"}
}