{
  "type": "Feature",
  "properties": {
    "iso:country":"DE",
    "sg:address":"Tal 46",
    "sg:city":"M\u00fcnchen",
    "sg:phone":"+49 89/222994",
    "sg:postcode":"80331",
    "sg:province":"Bayern",
    "wof:name":"Riesplan Verkaufslandschaften Mit Verkaufsf\u00f6rderung Gmbh",
    "wof:placetype":"venue"
},
  "geometry": {"coordinates":[11.581157,48.135342],"type":"Point"}
}