{
  "type": "Feature",
  "properties": {
    "iso:country":"DE",
    "sg:address":"Dorfstr. 4",
    "sg:city":"Dossow",
    "sg:phone":"+49 3394/441474",
    "sg:postcode":"16909",
    "sg:province":"Brandenburg",
    "wof:name":"E.-g. Hoops",
    "wof:placetype":"venue"
},
  "geometry": {"coordinates":[12.5266542435,53.1214828491],"type":"Point"}
}