{
  "type": "Feature",
  "properties": {
    "iso:country":"DE",
    "sg:address":"Stedinger Str. 1a",
    "sg:city":"Lemwerder",
    "sg:postcode":"27809",
    "sg:province":"Niedersachsen",
    "wof:name":"Fewo Bau Gmbh",
    "wof:placetype":"venue"
},
  "geometry": {"coordinates":[8.617403,53.163422],"type":"Point"}
}