{
  "type": "Feature",
  "properties": {
    "iso:country":"DE",
    "sg:address":"Bernhardsthal",
    "sg:city":"Neuhaus",
    "sg:phone":"+49 3679/722224",
    "sg:postcode":"98724",
    "sg:province":"Th\u00fcringen",
    "wof:name":"Waldbad Bernhardsthal",
    "wof:placetype":"venue"
},
  "geometry": {"coordinates":[11.1161346436,50.5009841919],"type":"Point"}
}