{
  "type": "Feature",
  "properties": {
    "iso:country":"DE",
    "sg:address":"Korveyer Str. 64",
    "sg:city":"D\u00fcsseldorf",
    "sg:phone":"+49 211/410999",
    "sg:postcode":"40468",
    "sg:province":"Nordrhein-Westfalen",
    "wof:name":"Engineering-trade-consulting Qualitytubes Steel-products",
    "wof:placetype":"venue"
},
  "geometry": {"coordinates":[6.788628,51.267445],"type":"Point"}
}