{
  "type": "Feature",
  "properties": {
    "iso:country":"DE",
    "sg:address":"Goethestr. 38",
    "sg:city":"Magdeburg",
    "sg:phone":"+49 391/73803",
    "sg:postcode":"39108",
    "sg:province":"Sachsen-Anhalt",
    "wof:name":"Hotel Geheimer Rat Von G",
    "wof:placetype":"venue"
},
  "geometry": {"coordinates":[11.6102180481,52.1330032349],"type":"Point"}
}