{
  "type": "Feature",
  "properties": {
    "iso:country":"DE",
    "sg:address":"Dreik\u00f6nigstr. 48",
    "sg:city":"Freiburg",
    "sg:phone":"+49 761/73918",
    "sg:postcode":"79102",
    "sg:province":"Baden-W\u00fcrttemberg",
    "wof:name":"Anni Kn\u00f6bel Krankengymnastin",
    "wof:placetype":"venue"
},
  "geometry": {"coordinates":[7.857144,47.986088],"type":"Point"}
}