{
  "type": "Feature",
  "properties": {
    "iso:country":"DE",
    "sg:address":"Nordfeldmark 6",
    "sg:city":"Bad Driburg",
    "sg:phone":"+49 5253/940257",
    "sg:postcode":"33014",
    "sg:province":"Nordrhein-Westfalen",
    "wof:name":"Pension Klaholt",
    "wof:placetype":"venue"
},
  "geometry": {"coordinates":[9.0224742889,51.7456130981],"type":"Point"}
}