{
  "type": "Feature",
  "properties": {
    "iso:country":"DE",
    "sg:address":"H\u00e4user Weg 2",
    "sg:city":"Rodgau",
    "sg:postcode":"63110",
    "sg:province":"Hessen",
    "wof:name":"Walter J\u00e4ger Verm\u00f6gensverwaltungsges. Mbh",
    "wof:placetype":"venue"
},
  "geometry": {"coordinates":[8.8797492981,50.0532913208],"type":"Point"}
}