{
  "type": "Feature",
  "properties": {
    "iso:country":"DE",
    "sg:address":"Rabanus-Maurus-Str. 8",
    "sg:city":"Petersberg",
    "sg:phone":"+49 661/9629250",
    "sg:postcode":"36100",
    "sg:province":"Hessen",
    "wof:name":"Rewe-markt",
    "wof:placetype":"venue"
},
  "geometry": {"coordinates":[9.7123022079,50.5589561462],"type":"Point"}
}