{
  "type": "Feature",
  "properties": {
    "iso:country":"DE",
    "sg:address":"Johannistisch 20",
    "sg:city":"Kleinmachnow",
    "sg:phone":"+49 33203/79263",
    "sg:postcode":"14532",
    "sg:province":"Brandenburg",
    "wof:name":"Theta Promotion Falkhof & Sohre Ohg",
    "wof:placetype":"venue"
},
  "geometry": {"coordinates":[13.214194,52.415394],"type":"Point"}
}