{
  "type": "Feature",
  "properties": {
    "iso:country":"DE",
    "sg:address":"Dorfstr. 5",
    "sg:city":"Oberostendorf",
    "sg:phone":"+49 8344/328",
    "sg:postcode":"86869",
    "sg:province":"Bayern",
    "wof:name":"Herbert G\u00f6ster",
    "wof:placetype":"venue"
},
  "geometry": {"coordinates":[10.731346,47.953468],"type":"Point"}
}