{
  "type": "Feature",
  "properties": {
    "iso:country":"DE",
    "sg:address":"Ottilienstr. 10",
    "sg:city":"Bad Homburg",
    "sg:phone":"+49 6172/86549",
    "sg:postcode":"61348",
    "sg:province":"Hessen",
    "wof:name":"Dr. Markus Jacobi Rechtsanwalt",
    "wof:placetype":"venue"
},
  "geometry": {"coordinates":[8.6158466339,50.2319717407],"type":"Point"}
}