{
  "type": "Feature",
  "properties": {
    "iso:country":"DE",
    "sg:address":"Hoornsfeld 1",
    "sg:city":"Schneverdingen",
    "sg:phone":"+49 5193/98480",
    "sg:postcode":"29640",
    "sg:province":"Niedersachsen",
    "wof:name":"Wisser Dienstleistungsge- Sellschaft Nord",
    "wof:placetype":"venue"
},
  "geometry": {"coordinates":[9.805735,53.123077],"type":"Point"}
}