{
  "type": "Feature",
  "properties": {
    "iso:country":"DE",
    "sg:address":"Potsdamer Str. 24",
    "sg:city":"Falkenrehde",
    "sg:phone":"+49 33233/80485",
    "sg:postcode":"14641",
    "sg:province":"Brandenburg",
    "wof:name":"M. Sommer",
    "wof:placetype":"venue"
},
  "geometry": {"coordinates":[12.9236526489,52.4968605042],"type":"Point"}
}