{
  "type": "Feature",
  "properties": {
    "iso:country":"DE",
    "sg:address":"Wuitzer Str 6",
    "sg:city":"Gera",
    "sg:phone":"+49 365/4205899",
    "sg:postcode":"07546",
    "sg:province":"Th\u00fcringen",
    "wof:name":"W+l Schornstein Gmbh",
    "wof:placetype":"venue"
},
  "geometry": {"coordinates":[12.112509,50.877419],"type":"Point"}
}