{
  "type": "Feature",
  "properties": {
    "iso:country":"DE",
    "sg:address":"Grund 3",
    "sg:city":"Biederbach",
    "sg:phone":"+49 7682/8932",
    "sg:postcode":"79215",
    "sg:province":"Baden-W\u00fcrttemberg",
    "wof:name":"Heinrich Sch\u00e4tzle",
    "wof:placetype":"venue"
},
  "geometry": {"coordinates":[8.004923,48.190121],"type":"Point"}
}