{
  "type": "Feature",
  "properties": {
    "iso:country":"DE",
    "sg:address":"Neustifter Str. 30e",
    "sg:city":"Passau",
    "sg:phone":"+49 851/89301",
    "sg:postcode":"94036",
    "sg:province":"Bayern",
    "wof:name":"Josef-egon Eder Architekt",
    "wof:placetype":"venue"
},
  "geometry": {"coordinates":[13.394186,48.577114],"type":"Point"}
}