{
  "type": "Feature",
  "properties": {
    "iso:country":"DE",
    "sg:address":"Hauptstr. 34",
    "sg:city":"Lohmar",
    "sg:phone":"+49 2246/2044",
    "sg:postcode":"53797",
    "sg:province":"Nordrhein-Westfalen",
    "wof:name":"Reiseb\u00fcro Am Rathaus Lohmar Gmbh",
    "wof:placetype":"venue"
},
  "geometry": {"coordinates":[7.2119369507,50.8412017822],"type":"Point"}
}