{
  "type": "Feature",
  "properties": {
    "iso:country":"DE",
    "sg:address":"S\u00fcdstr. 137",
    "sg:city":"Kevelaer",
    "sg:phone":"+49 2832/4417",
    "sg:postcode":"47623",
    "sg:province":"Nordrhein-Westfalen",
    "wof:name":"Edgar Thoenissen",
    "wof:placetype":"venue"
},
  "geometry": {"coordinates":[6.248816,51.565868],"type":"Point"}
}