{
  "type": "Feature",
  "properties": {
    "iso:country":"DE",
    "sg:address":"Rathausstr. 70",
    "sg:city":"Herne",
    "sg:phone":"+49 2325/70752",
    "sg:postcode":"44649",
    "sg:province":"Nordrhein-Westfalen",
    "wof:name":"Thier-eck",
    "wof:placetype":"venue"
},
  "geometry": {"coordinates":[7.1622757912,51.5384521484],"type":"Point"}
}