{
  "type": "Feature",
  "properties": {
    "iso:country":"DE",
    "sg:address":"August-Deller Str. 1",
    "sg:city":"Palzing",
    "sg:phone":"+49 8167",
    "sg:postcode":"85406",
    "sg:province":"Bayern",
    "wof:name":"Bison Vertriebsgesellschaft Mbh",
    "wof:placetype":"venue"
},
  "geometry": {"coordinates":[11.7083091736,48.4604797363],"type":"Point"}
}