{
  "type": "Feature",
  "properties": {
    "iso:country":"DE",
    "sg:address":"Im Hasental 8",
    "sg:city":"K\u00f6ln",
    "sg:phone":"+49 221/818541",
    "sg:postcode":"50679",
    "sg:province":"Nordrhein-Westfalen",
    "wof:name":"Alfred Adler Steuerberater",
    "wof:placetype":"venue"
},
  "geometry": {"coordinates":[6.9764738083,50.9288673401],"type":"Point"}
}