{
  "type": "Feature",
  "properties": {
    "iso:country":"DE",
    "sg:address":"L\u00f6westr. 28",
    "sg:city":"Berlin",
    "sg:phone":"+49 30/42780580",
    "sg:postcode":"10249",
    "sg:province":"Berlin",
    "wof:name":"Loewe 28 Atelier Gmbh",
    "wof:placetype":"venue"
},
  "geometry": {"coordinates":[13.447222,52.517715],"type":"Point"}
}