{
  "type": "Feature",
  "properties": {
    "iso:country":"DE",
    "sg:address":"Postfach 1761:: 56141 Boppard:: Germany.^^Marktplatz 9::",
    "sg:city":"Boppard",
    "sg:phone":"+49 6742/1060",
    "sg:postcode":"56154",
    "sg:province":"Rheinland-Pfalz",
    "wof:name":"Volksbank Boppard Eg",
    "wof:placetype":"venue"
},
  "geometry": {"coordinates":[7.588005,50.231773],"type":"Point"}
}