{
  "type": "Feature",
  "properties": {
    "iso:country":"DE",
    "sg:address":"Alsterdorfer Str. 513 A",
    "sg:city":"Hamburg",
    "sg:postcode":"22337",
    "sg:province":"Hamburg",
    "wof:name":"Thera Cosm Gmbh",
    "wof:placetype":"venue"
},
  "geometry": {"coordinates":[10.0272912979,53.6177177429],"type":"Point"}
}