{
  "type": "Feature",
  "properties": {
    "iso:country":"DE",
    "sg:address":"Kapellenfeldstr 17",
    "sg:city":"M\u00fcnchen",
    "sg:phone":"+49 89/32212250",
    "sg:postcode":"81549",
    "sg:province":"Bayern",
    "wof:name":"Mash",
    "wof:placetype":"venue"
},
  "geometry": {"coordinates":[11.6145477295,48.0885391235],"type":"Point"}
}