{
  "type": "Feature",
  "properties": {
    "iso:country":"DE",
    "sg:address":"Stadtkamp 13",
    "sg:city":"Sassenberg",
    "sg:phone":"+49 2583/303163",
    "sg:postcode":"48336",
    "sg:province":"Nordrhein-Westfalen",
    "wof:name":"H. E. L. I. Sicherheit Pierre Hennig E. K.",
    "wof:placetype":"venue"
},
  "geometry": {"coordinates":[8.0404949188,51.9840240479],"type":"Point"}
}