{
  "type": "Feature",
  "properties": {
    "iso:country":"DE",
    "sg:address":"Weichselstr. 48",
    "sg:city":"Berlin",
    "sg:phone":"+49 30/6247364",
    "sg:postcode":"12045",
    "sg:province":"Berlin",
    "wof:name":"Deutsche Gesellschaft F\u00fcr Musiktherapie E. V.",
    "wof:placetype":"venue"
},
  "geometry": {"coordinates":[13.4361209869,52.4868812561],"type":"Point"}
}