{
  "type": "Feature",
  "properties": {
    "iso:country":"DE",
    "sg:address":"Kredenbacher Weg 12",
    "sg:city":"Siegen",
    "sg:phone":"+49 271/86482",
    "sg:postcode":"57078",
    "sg:province":"Nordrhein-Westfalen",
    "wof:name":"Heinz Emde",
    "wof:placetype":"venue"
},
  "geometry": {"coordinates":[8.037134,50.940323],"type":"Point"}
}