{
  "type": "Feature",
  "properties": {
    "iso:country":"DE",
    "sg:address":"C.-D.-Magirus-Str. 2",
    "sg:city":"Weisweil",
    "sg:phone":"+49 7646/1383",
    "sg:postcode":"79367",
    "sg:province":"Baden-W\u00fcrttemberg",
    "wof:name":"Gerlindes Cafe-bistro",
    "wof:placetype":"venue"
},
  "geometry": {"coordinates":[7.6820220947,48.2031364441],"type":"Point"}
}