{
  "type": "Feature",
  "properties": {
    "iso:country":"DE",
    "sg:address":"Meisenstr. 19",
    "sg:city":"Hamburg",
    "sg:phone":"+49 40/6119110",
    "sg:postcode":"22305",
    "sg:province":"Hamburg",
    "wof:name":"Johann E. Dechow Gmbh",
    "wof:placetype":"venue"
},
  "geometry": {"coordinates":[10.057301,53.589394],"type":"Point"}
}