{
  "type": "Feature",
  "properties": {
    "iso:country":"DE",
    "sg:address":"Melatenweg 16",
    "sg:city":"Rees",
    "sg:phone":"+49 2851/1511",
    "sg:postcode":"46459",
    "sg:province":"Nordrhein-Westfalen",
    "wof:name":"Klaus Angenendt Kunstmaler",
    "wof:placetype":"venue"
},
  "geometry": {"coordinates":[6.40331,51.763378],"type":"Point"}
}