{
  "type": "Feature",
  "properties": {
    "iso:country":"DE",
    "sg:address":"Postfach 1155",
    "sg:city":"Heilsbronn",
    "sg:postcode":"91556",
    "sg:province":"Bayern",
    "wof:name":"Roland Forkel",
    "wof:placetype":"venue"
},
  "geometry": {"coordinates":[10.7902898788,49.3378181458],"type":"Point"}
}