{
  "type": "Feature",
  "properties": {
    "iso:country":"DE",
    "sg:address":"Ahornweg 1",
    "sg:city":"Oberboihingen",
    "sg:phone":"+49 7022/63095",
    "sg:postcode":"72644",
    "sg:province":"Baden-W\u00fcrttemberg",
    "wof:name":"A. Feige Gmbh",
    "wof:placetype":"venue"
},
  "geometry": {"coordinates":[9.368653,48.64706],"type":"Point"}
}