{
  "type": "Feature",
  "properties": {
    "iso:country":"DE",
    "sg:address":"Herman-Balk-Str. 111a",
    "sg:city":"Hamburg",
    "sg:phone":"+49 40/6445858",
    "sg:postcode":"22147",
    "sg:province":"Hamburg",
    "wof:name":"Praxis Dr. Gisela Delventhal",
    "wof:placetype":"venue"
},
  "geometry": {"coordinates":[10.140246,53.624142],"type":"Point"}
}