{
  "type": "Feature",
  "properties": {
    "iso:country":"DE",
    "sg:address":"Collegienstr. 85",
    "sg:city":"Lutherstadt Wittenberg",
    "sg:phone":"+49 3491/410927",
    "sg:postcode":"06886",
    "sg:province":"Sachsen-Anhalt",
    "wof:name":"R. Eckloff",
    "wof:placetype":"venue"
},
  "geometry": {"coordinates":[12.6455278397,51.8658103943],"type":"Point"}
}