{
  "type": "Feature",
  "properties": {
    "iso:country":"DE",
    "sg:address":"Zielstr. 20",
    "sg:city":"Mannheim",
    "sg:phone":"+49 621/302085",
    "sg:postcode":"68169",
    "sg:province":"Baden-W\u00fcrttemberg",
    "wof:name":"Stm Verwaltungs- Gmbh",
    "wof:placetype":"venue"
},
  "geometry": {"coordinates":[8.4987,49.506542],"type":"Point"}
}