{
  "type": "Feature",
  "properties": {
    "iso:country":"DE",
    "sg:address":"M\u00fchl\u00e4ckerstr. 25",
    "sg:city":"Ludwigsburg",
    "sg:phone":"+49 7144/12567",
    "sg:postcode":"71642",
    "sg:province":"Baden-W\u00fcrttemberg",
    "wof:name":"Giese Pumpentechnik",
    "wof:placetype":"venue"
},
  "geometry": {"coordinates":[9.259962,48.905392],"type":"Point"}
}