{
  "type": "Feature",
  "properties": {
    "iso:country":"DE",
    "sg:address":"Hauptstr. 33",
    "sg:city":"Beltheim",
    "sg:phone":"+49 6762/950131",
    "sg:postcode":"56290",
    "sg:province":"Rheinland-Pfalz",
    "wof:name":"H. P. Sch\u00e4fer",
    "wof:placetype":"venue"
},
  "geometry": {"coordinates":[7.4599499702,50.1066627502],"type":"Point"}
}