{
  "type": "Feature",
  "properties": {
    "iso:country":"DE",
    "sg:address":"Sch\u00fctzenstr. 1",
    "sg:city":"Brilon",
    "sg:phone":"+49 2991/78484",
    "sg:postcode":"59929",
    "sg:province":"Nordrhein-Westfalen",
    "wof:name":"Restaurant Pickert's",
    "wof:placetype":"venue"
},
  "geometry": {"coordinates":[8.5677452087,51.3987083435],"type":"Point"}
}