{
  "type": "Feature",
  "properties": {
    "iso:country":"DE",
    "sg:address":"Pieperstr. 28",
    "sg:city":"Hildesheim",
    "sg:phone":"+49 5121/37128",
    "sg:postcode":"31135",
    "sg:province":"Niedersachsen",
    "wof:name":"Immofond Liegen- Schafts Gmbh & Co.",
    "wof:placetype":"venue"
},
  "geometry": {"coordinates":[9.9592456818,52.1575775146],"type":"Point"}
}