{
  "type": "Feature",
  "properties": {
    "iso:country":"DE",
    "sg:address":"Hans-B\u00f6ckler-Str. 4-8",
    "sg:city":"Unna",
    "sg:phone":"+49 2303/2080",
    "sg:postcode":"59423",
    "sg:province":"Nordrhein-Westfalen",
    "wof:name":"Zurbr\u00fcggen Beteiligungs- Gmbh",
    "wof:placetype":"venue"
},
  "geometry": {"coordinates":[7.6693930626,51.5308303833],"type":"Point"}
}