{
  "type": "Feature",
  "properties": {
    "iso:country":"DE",
    "sg:address":"In Den Sieben St\u00fccken 7 A",
    "sg:city":"Hannover",
    "sg:phone":"+49 4951/164671",
    "sg:postcode":"30655",
    "sg:province":"Niedersachsen",
    "wof:name":"Ges. F\u00dcr Bauen & Wohnen Hannover Mbh (gwh)",
    "wof:placetype":"venue"
},
  "geometry": {"coordinates":[9.809782,52.408028],"type":"Point"}
}