{
  "type": "Feature",
  "properties": {
    "iso:country":"DE",
    "sg:address":"Marstallstr. 8",
    "sg:city":"M\u00fcnchen",
    "sg:phone":"+49 89/290120",
    "sg:postcode":"80539",
    "sg:province":"Bayern",
    "wof:name":"Security Dynamics Technologies Gmbh",
    "wof:placetype":"venue"
},
  "geometry": {"coordinates":[11.5825147629,48.1400375366],"type":"Point"}
}