{
  "type": "Feature",
  "properties": {
    "iso:country":"DE",
    "sg:address":"Bad Essener Str. 21",
    "sg:city":"Bissendorf",
    "sg:phone":"+49 5402/8805",
    "sg:postcode":"49143",
    "sg:province":"Niedersachsen",
    "wof:name":"Klaus Leistikow",
    "wof:placetype":"venue"
},
  "geometry": {"coordinates":[8.248055,52.284756],"type":"Point"}
}