{
  "type": "Feature",
  "properties": {
    "iso:country":"DE",
    "sg:address":"Prinzipalmarkt 13",
    "sg:city":"M\u00fcnster",
    "sg:phone":"+49 251/41880",
    "sg:postcode":"48143",
    "sg:province":"Nordrhein-Westfalen",
    "wof:name":"Prof. Harald Deilmann Architekt",
    "wof:placetype":"venue"
},
  "geometry": {"coordinates":[7.627839,51.961422],"type":"Point"}
}