{
  "type": "Feature",
  "properties": {
    "iso:country":"DE",
    "sg:address":"Im Fahler 9",
    "sg:city":"Haiger",
    "sg:phone":"+49 2773/6807",
    "sg:postcode":"35708",
    "sg:province":"Hessen",
    "wof:name":"Albrecht Stiehl",
    "wof:placetype":"venue"
},
  "geometry": {"coordinates":[8.1994962692,50.7438011169],"type":"Point"}
}