{
  "type": "Feature",
  "properties": {
    "iso:country":"DE",
    "sg:address":"Fuchshohl 1",
    "sg:city":"Frankfurt",
    "sg:phone":"+49 69/524634",
    "sg:postcode":"60431",
    "sg:province":"Hessen",
    "wof:name":"Ev. Pfarramt Bethlehemgemeinde Bz. West",
    "wof:placetype":"venue"
},
  "geometry": {"coordinates":[8.6525745392,50.145275116],"type":"Point"}
}