{
  "type": "Feature",
  "properties": {
    "iso:country":"DE",
    "sg:address":"Hainbuchenstr. 15",
    "sg:city":"Waiblingen",
    "sg:phone":"+49 7151/51545",
    "sg:postcode":"71334",
    "sg:province":"Baden-W\u00fcrttemberg",
    "wof:name":"Lothar M\u00fcller Ingenieur",
    "wof:placetype":"venue"
},
  "geometry": {"coordinates":[9.2971658707,48.8606185913],"type":"Point"}
}