{
  "type": "Feature",
  "properties": {
    "iso:country":"DE",
    "sg:address":"Travem\u00fcnder Str. 2",
    "sg:city":"Leimen",
    "sg:phone":"+49 6224/9800",
    "sg:postcode":"69181",
    "sg:province":"Baden-W\u00fcrttemberg",
    "wof:name":"Weidemaier & Goldschmidt Gmbh",
    "wof:placetype":"venue"
},
  "geometry": {"coordinates":[8.6769065857,49.3582687378],"type":"Point"}
}