{
  "type": "Feature",
  "properties": {
    "iso:country":"DE",
    "sg:address":"Plockhorster Str. 3",
    "sg:city":"Uetze",
    "sg:phone":"+49 5173/7458",
    "sg:postcode":"31311",
    "sg:province":"Niedersachsen",
    "wof:name":"Ca\u00dfau",
    "wof:placetype":"venue"
},
  "geometry": {"coordinates":[10.2631921768,52.452293396],"type":"Point"}
}