{
  "type": "Feature",
  "properties": {
    "iso:country":"DE",
    "sg:address":"Gro\u00dfe Ziegelstr. 4",
    "sg:city":"Kiel",
    "sg:phone":"+49 431/7809216",
    "sg:postcode":"24148",
    "sg:province":"Schleswig-Holstein",
    "wof:name":"Helmut Sch\u00e4ttler Ingenieur",
    "wof:placetype":"venue"
},
  "geometry": {"coordinates":[10.1610851288,54.316619873],"type":"Point"}
}