{
  "type": "Feature",
  "properties": {
    "iso:country":"DE",
    "sg:address":"H\u00f6henstr. 33a",
    "sg:city":"Nonnweiler",
    "sg:phone":"+49 6873/7263",
    "sg:postcode":"66620",
    "sg:province":"Saarland",
    "wof:name":"Christian Malburg",
    "wof:placetype":"venue"
},
  "geometry": {"coordinates":[7.019277,49.597641],"type":"Point"}
}