{
  "type": "Feature",
  "properties": {
    "iso:country":"DE",
    "sg:address":"Finkenstr. 18",
    "sg:city":"Herzberg",
    "sg:phone":"+49 5521/5458",
    "sg:postcode":"37412",
    "sg:province":"Niedersachsen",
    "wof:name":"Finkenklause",
    "wof:placetype":"venue"
},
  "geometry": {"coordinates":[10.3253507614,51.6614685059],"type":"Point"}
}