{
  "type": "Feature",
  "properties": {
    "iso:country":"DE",
    "sg:address":"Friedrichstr. 30",
    "sg:city":"Allendorf",
    "sg:phone":"+49 6407/90066",
    "sg:postcode":"35469",
    "sg:province":"Hessen",
    "wof:name":"Dwl Touristik",
    "wof:placetype":"venue"
},
  "geometry": {"coordinates":[8.8156251907,50.6786766052],"type":"Point"}
}