{
  "type": "Feature",
  "properties": {
    "iso:country":"DE",
    "sg:address":"Universit\u00e4tsstr. 1",
    "sg:city":"Bielefeld",
    "sg:phone":"+49 521/104205",
    "sg:postcode":"33615",
    "sg:province":"Nordrhein-Westfalen",
    "wof:name":"Edwin Jacobs",
    "wof:placetype":"venue"
},
  "geometry": {"coordinates":[8.5003833771,52.0367431641],"type":"Point"}
}