{
  "type": "Feature",
  "properties": {
    "iso:country":"DE",
    "sg:address":"Z\u00e4hringerstr. 84",
    "sg:city":"Karlsruhe",
    "sg:postcode":"76133",
    "sg:province":"Baden-W\u00fcrttemberg",
    "wof:name":"Consileon Business Consultancy Gmbh",
    "wof:placetype":"venue"
},
  "geometry": {"coordinates":[8.406211853,49.0089302063],"type":"Point"}
}