{
  "type": "Feature",
  "properties": {
    "iso:country":"DE",
    "sg:address":"Bahnhofstr. 33",
    "sg:city":"Salzbergen",
    "sg:phone":"+49 5976/94405",
    "sg:postcode":"48499",
    "sg:province":"Niedersachsen",
    "wof:name":"Bernhard Puls",
    "wof:placetype":"venue"
},
  "geometry": {"coordinates":[7.345527,52.321941],"type":"Point"}
}