{
  "type": "Feature",
  "properties": {
    "iso:country":"DE",
    "sg:address":"Schulstr. 17",
    "sg:city":"Trittau",
    "sg:phone":"+49 4154/81240",
    "sg:postcode":"22946",
    "sg:province":"Schleswig-Holstein",
    "wof:name":"Bernd Janssen Rechtsanwalt",
    "wof:placetype":"venue"
},
  "geometry": {"coordinates":[10.4103441238,53.6049194336],"type":"Point"}
}