{
  "type": "Feature",
  "properties": {
    "iso:country":"DE",
    "sg:address":"Waidhauser Str. 46",
    "sg:city":"Vohenstrau\u00df",
    "sg:phone":"+49 9741/91340",
    "sg:postcode":"92648",
    "sg:province":"Bayern",
    "wof:name":"Elektrometall Gmbh",
    "wof:placetype":"venue"
},
  "geometry": {"coordinates":[9.797533989,50.3145446777],"type":"Point"}
}