{
  "type": "Feature",
  "properties": {
    "iso:country":"DE",
    "sg:address":"Markt 11",
    "sg:city":"Greiz",
    "sg:phone":"+49 3661/673060",
    "sg:postcode":"07973",
    "sg:province":"Th\u00fcringen",
    "wof:name":"Horlbeck & Kaiser",
    "wof:placetype":"venue"
},
  "geometry": {"coordinates":[12.2006998062,50.6572113037],"type":"Point"}
}