{
  "type": "Feature",
  "properties": {
    "iso:country":"DE",
    "sg:address":"Lahnstr. 19",
    "sg:city":"Saarbr\u00fccken",
    "sg:phone":"+49 681/971490",
    "sg:postcode":"66113",
    "sg:province":"Saarland",
    "wof:name":"Seniorenwohnanlage Der Arbeiterwohlfahrt",
    "wof:placetype":"venue"
},
  "geometry": {"coordinates":[6.963795,49.247349],"type":"Point"}
}