{
  "type": "Feature",
  "properties": {
    "iso:country":"DE",
    "sg:address":"Ro\u00dfsteinstr. 16",
    "sg:city":"M\u00fcnchen",
    "sg:phone":"+49 89/433101",
    "sg:postcode":"81673",
    "sg:province":"Bayern",
    "wof:name":"Reiseagentur My Travel",
    "wof:placetype":"venue"
},
  "geometry": {"coordinates":[11.641113,48.130749],"type":"Point"}
}