{
  "type": "Feature",
  "properties": {
    "iso:country":"DE",
    "sg:address":"Alpenstr. 70",
    "sg:city":"Memmingen",
    "sg:phone":"+49 8331/87740",
    "sg:postcode":"87700",
    "sg:province":"Bayern",
    "wof:name":"Soul",
    "wof:placetype":"venue"
},
  "geometry": {"coordinates":[10.191776,47.966843],"type":"Point"}
}