{
  "type": "Feature",
  "properties": {
    "iso:country":"DE",
    "sg:address":"Gr\u00fcne Str. 3 a",
    "sg:city":"Delmenhorst",
    "sg:postcode":"27749",
    "sg:province":"Niedersachsen",
    "wof:name":"Mmv - Verlag Gmbh",
    "wof:placetype":"venue"
},
  "geometry": {"coordinates":[8.6385288239,53.0423088074],"type":"Point"}
}