{
  "type": "Feature",
  "properties": {
    "iso:country":"DE",
    "sg:address":"Grenzweg 90",
    "sg:city":"Willich",
    "sg:phone":"+49 2156/2038",
    "sg:postcode":"47877",
    "sg:province":"Nordrhein-Westfalen",
    "wof:name":"K. M\u00f6hlmann",
    "wof:placetype":"venue"
},
  "geometry": {"coordinates":[6.431204,51.263912],"type":"Point"}
}