{
  "type": "Feature",
  "properties": {
    "iso:country":"DE",
    "sg:address":"Pfarrweg 7",
    "sg:city":"Korbach",
    "sg:phone":"+49 2982/8389",
    "sg:postcode":"34497",
    "sg:province":"Hessen",
    "wof:name":"Kath. Pfarramt St. Michael",
    "wof:placetype":"venue"
},
  "geometry": {"coordinates":[8.7494802475,51.2203712463],"type":"Point"}
}