{
  "type": "Feature",
  "properties": {
    "iso:country":"DE",
    "sg:address":"Am Schlangenluch 1",
    "sg:city":"Gr\u00fcnheide",
    "sg:phone":"+49 3362/6170",
    "sg:postcode":"15537",
    "sg:province":"Brandenburg",
    "wof:name":"Dr. Med. Bernhard Pfeil",
    "wof:placetype":"venue"
},
  "geometry": {"coordinates":[13.823581,52.420696],"type":"Point"}
}