{
  "type": "Feature",
  "properties": {
    "iso:country":"DE",
    "sg:address":"Hainkamp 5",
    "sg:city":"Schiffdorf",
    "sg:postcode":"27619",
    "sg:province":"Niedersachsen",
    "wof:name":"Pflegeheim Service Gmbh",
    "wof:placetype":"venue"
},
  "geometry": {"coordinates":[8.794217,53.503117],"type":"Point"}
}