{
  "type": "Feature",
  "properties": {
    "iso:country":"DE",
    "sg:address":"Silvesterweg 63",
    "sg:city":"Berlin",
    "sg:phone":"+49 30/4044359",
    "sg:postcode":"13467",
    "sg:province":"Berlin",
    "wof:name":"Gbo Gesellschaft F\u00fcr B\u00fcro- Und Organisationsservice Mbh",
    "wof:placetype":"venue"
},
  "geometry": {"coordinates":[13.307585,52.625965],"type":"Point"}
}