{
  "type": "Feature",
  "properties": {
    "iso:country":"DE",
    "sg:address":"Langenthonhausen 4",
    "sg:city":"Breitenbrunn",
    "sg:phone":"+49 9495/257",
    "sg:postcode":"92363",
    "sg:province":"Bayern",
    "wof:name":"W. Wittmann",
    "wof:placetype":"venue"
},
  "geometry": {"coordinates":[11.665674,49.083004],"type":"Point"}
}