{
  "type": "Feature",
  "properties": {
    "iso:country":"DE",
    "sg:address":"Bodanstr. 34",
    "sg:city":"Kressbronn",
    "sg:phone":"+49 7543/6785",
    "sg:postcode":"88079",
    "sg:province":"Baden-W\u00fcrttemberg",
    "wof:name":"Deusch",
    "wof:placetype":"venue"
},
  "geometry": {"coordinates":[9.593656,47.589241],"type":"Point"}
}