{
  "type": "Feature",
  "properties": {
    "iso:country":"DE",
    "sg:address":"Stresemannstr. 26",
    "sg:city":"D\u00fcsseldorf",
    "sg:phone":"+49 211/166530",
    "sg:postcode":"40210",
    "sg:province":"Nordrhein-Westfalen",
    "wof:name":"Fdf Landesverband Nrw E. V.",
    "wof:placetype":"venue"
},
  "geometry": {"coordinates":[6.7852449417,51.2206115723],"type":"Point"}
}