{
  "type": "Feature",
  "properties": {
    "iso:country":"DE",
    "sg:address":"Bahnhofstr. 1",
    "sg:city":"Schwerte",
    "sg:phone":"+49 2304/18256",
    "sg:postcode":"58239",
    "sg:province":"Nordrhein-Westfalen",
    "wof:name":"Dieter B\u00f6ker",
    "wof:placetype":"venue"
},
  "geometry": {"coordinates":[7.5647768974,51.4416236877],"type":"Point"}
}