{
  "type": "Feature",
  "properties": {
    "iso:country":"DE",
    "sg:address":"Sandbergstr. 65",
    "sg:city":"Darmstadt",
    "sg:phone":"+49 6151/661048",
    "sg:postcode":"64285",
    "sg:province":"Hessen",
    "wof:name":"Leinberger Und Schneider Architekten",
    "wof:placetype":"venue"
},
  "geometry": {"coordinates":[8.64548,49.857304],"type":"Point"}
}