{
  "type": "Feature",
  "properties": {
    "iso:country":"DE",
    "sg:address":"Unterlippe 14",
    "sg:city":"Waltrop",
    "sg:postcode":"45731",
    "sg:province":"Nordrhein-Westfalen",
    "wof:name":"Ihr Taxi 4444 E. Kfm.",
    "wof:placetype":"venue"
},
  "geometry": {"coordinates":[7.4392948151,51.6500663757],"type":"Point"}
}