{
  "type": "Feature",
  "properties": {
    "iso:country":"DE",
    "sg:address":"Parkstr. 40",
    "sg:city":"Hude",
    "sg:phone":"+49 4944/0899880",
    "sg:postcode":"27798",
    "sg:province":"Niedersachsen",
    "wof:name":"Nordwest-zeitungverlagsges. Mbh & Co. Kg",
    "wof:placetype":"venue"
},
  "geometry": {"coordinates":[8.4572296143,53.1130104065],"type":"Point"}
}