{
  "type": "Feature",
  "properties": {
    "iso:country":"DE",
    "sg:address":"Tunnelstr. 13",
    "sg:city":"Laubach",
    "sg:phone":"+49 6405/6156",
    "sg:postcode":"35321",
    "sg:province":"Hessen",
    "wof:name":"E. Petri",
    "wof:placetype":"venue"
},
  "geometry": {"coordinates":[9.0439519882,50.5599365234],"type":"Point"}
}