{
  "type": "Feature",
  "properties": {
    "iso:country":"DE",
    "sg:address":"Heinkelstra\u00dfe 19",
    "sg:city":"Schorndorf",
    "sg:postcode":"73614",
    "sg:province":"Baden-W\u00fcrttemberg",
    "wof:name":"Tinsel Rohrbiegemaschinen Mingori",
    "wof:placetype":"venue"
},
  "geometry": {"coordinates":[9.529919,48.809208],"type":"Point"}
}