{
  "type": "Feature",
  "properties": {
    "iso:country":"DE",
    "sg:address":"Chemnitzer Str. 1",
    "sg:city":"Wittgensdorf",
    "sg:phone":"+49 37200/88482",
    "sg:postcode":"09228",
    "sg:province":"Sachsen",
    "wof:name":"Gasthof Bergschl\u00f6\u00dfchen",
    "wof:placetype":"venue"
},
  "geometry": {"coordinates":[12.8711204529,50.8763999939],"type":"Point"}
}