{
  "type": "Feature",
  "properties": {
    "iso:country":"DE",
    "sg:address":"Oelbergstr. 2",
    "sg:city":"K\u00f6nigswinter",
    "sg:phone":"+49 2244/80434",
    "sg:postcode":"53639",
    "sg:province":"Nordrhein-Westfalen",
    "wof:name":"Walter Sains",
    "wof:placetype":"venue"
},
  "geometry": {"coordinates":[7.2326211929,50.6960754395],"type":"Point"}
}