{
  "type": "Feature",
  "properties": {
    "iso:country":"DE",
    "sg:address":"Lindenstr. 2",
    "sg:city":"Bienenb\u00fcttel",
    "sg:phone":"+49 5823/952092",
    "sg:postcode":"29553",
    "sg:province":"Niedersachsen",
    "wof:name":"Kurt Kathmann",
    "wof:placetype":"venue"
},
  "geometry": {"coordinates":[10.48825,53.142101],"type":"Point"}
}