{
  "type": "Feature",
  "properties": {
    "iso:country":"DE",
    "sg:address":"Auenweg 173",
    "sg:city":"K\u00f6ln",
    "sg:postcode":"51063",
    "sg:province":"Nordrhein-Westfalen",
    "wof:name":"Hansa Leasing- Factoring- & Consulting Gmbh",
    "wof:placetype":"venue"
},
  "geometry": {"coordinates":[6.982314,50.950481],"type":"Point"}
}