{
  "type": "Feature",
  "properties": {
    "iso:country":"DE",
    "sg:address":"B\u00fcchnerstr 8",
    "sg:city":"Braunschweig",
    "sg:phone":"+49 531/8661250",
    "sg:postcode":"38118",
    "sg:province":"Niedersachsen",
    "wof:name":"Op-klima Gmbh",
    "wof:placetype":"venue"
},
  "geometry": {"coordinates":[10.500718,52.251038],"type":"Point"}
}