{
  "type": "Feature",
  "properties": {
    "iso:country":"DE",
    "sg:address":"Steinweg 4",
    "sg:city":"Felsberg",
    "sg:phone":"+49 5662/3051",
    "sg:postcode":"34587",
    "sg:province":"Hessen",
    "wof:name":"Dr. Schulze & Partner Gmbh",
    "wof:placetype":"venue"
},
  "geometry": {"coordinates":[9.425895,51.134621],"type":"Point"}
}