{
  "type": "Feature",
  "properties": {
    "iso:country":"DE",
    "sg:address":"Goethestr. 79",
    "sg:city":"Berlin",
    "sg:phone":"+49 30/3123418",
    "sg:postcode":"10623",
    "sg:province":"Berlin",
    "wof:name":"Renate Hirschmann",
    "wof:placetype":"venue"
},
  "geometry": {"coordinates":[13.3208227158,52.5087547302],"type":"Point"}
}