{
  "type": "Feature",
  "properties": {
    "iso:country":"DE",
    "sg:address":"Raiffeisenstr. 125",
    "sg:city":"Duisburg",
    "sg:phone":"+49 203/788649",
    "sg:postcode":"47259",
    "sg:province":"Nordrhein-Westfalen",
    "wof:name":"Margarete Bremen",
    "wof:placetype":"venue"
},
  "geometry": {"coordinates":[6.7494258881,51.3661079407],"type":"Point"}
}