{
  "type": "Feature",
  "properties": {
    "iso:country":"DE",
    "sg:address":"Heidestr. 6",
    "sg:city":"Stuttgart",
    "sg:phone":"+49 711/818374",
    "sg:postcode":"70469",
    "sg:province":"Baden-W\u00fcrttemberg",
    "wof:name":"Hans Pikat",
    "wof:placetype":"venue"
},
  "geometry": {"coordinates":[9.1751756668,48.8111305237],"type":"Point"}
}