{
  "type": "Feature",
  "properties": {
    "iso:country":"DE",
    "sg:address":"Scharnh\u00f6lzstr. 266",
    "sg:city":"Bottrop",
    "sg:phone":"+49 2041/31108",
    "sg:postcode":"46238",
    "sg:province":"Nordrhein-Westfalen",
    "wof:name":"Franz Bergendahl Gmbh",
    "wof:placetype":"venue"
},
  "geometry": {"coordinates":[6.950922,51.537716],"type":"Point"}
}