{
  "type": "Feature",
  "properties": {
    "iso:country":"DE",
    "sg:address":"Hans-B\u00f6ckler-Str 15",
    "sg:city":"Kirchheim",
    "sg:phone":"+49 7021/980840",
    "sg:postcode":"73230",
    "sg:province":"Baden-W\u00fcrttemberg",
    "wof:name":"Mr Elektronik Gmbh",
    "wof:placetype":"venue"
},
  "geometry": {"coordinates":[9.474974,48.639664],"type":"Point"}
}