{
  "type": "Feature",
  "properties": {
    "iso:country":"DE",
    "sg:address":"Grube Neue Haardt 1",
    "sg:city":"Siegen",
    "sg:phone":"+49 271/70950",
    "sg:postcode":"57076",
    "sg:province":"Nordrhein-Westfalen",
    "wof:name":"Franke & Fries Kommunik.- Und Meldesysteme",
    "wof:placetype":"venue"
},
  "geometry": {"coordinates":[8.0225410461,50.9045753479],"type":"Point"}
}