{
  "type": "Feature",
  "properties": {
    "iso:country":"DE",
    "sg:address":"Eichwaldstr. 41",
    "sg:city":"Illingen",
    "sg:phone":"+49 7042/24240",
    "sg:postcode":"75428",
    "sg:province":"Baden-W\u00fcrttemberg",
    "wof:name":"Bodo Reich Masseur",
    "wof:placetype":"venue"
},
  "geometry": {"coordinates":[8.929882,48.953072],"type":"Point"}
}