{
  "type": "Feature",
  "properties": {
    "iso:country":"DE",
    "sg:address":"Nagelsbaum 15",
    "sg:city":"Burscheid",
    "sg:phone":"+49 2174/62926",
    "sg:postcode":"51399",
    "sg:province":"Nordrhein-Westfalen",
    "wof:name":"Norbert Quandt Heilpraktiker",
    "wof:placetype":"venue"
},
  "geometry": {"coordinates":[7.0792069435,51.09034729],"type":"Point"}
}