{
  "type": "Feature",
  "properties": {
    "iso:country":"DE",
    "sg:address":"Hahnerberger Str. 257",
    "sg:city":"Wuppertal",
    "sg:phone":"+49 202/403036",
    "sg:postcode":"42349",
    "sg:province":"Nordrhein-Westfalen",
    "wof:name":"Bechtel Gmbh Wuppertal",
    "wof:placetype":"venue"
},
  "geometry": {"coordinates":[7.1501841545,51.2170906067],"type":"Point"}
}