{
  "type": "Feature",
  "properties": {
    "iso:country":"DE",
    "sg:address":"Hannoversche Str. 35",
    "sg:city":"Nienst\u00e4dt",
    "sg:phone":"+49 4957/2173574",
    "sg:postcode":"31688",
    "sg:province":"Niedersachsen",
    "wof:name":"Volksbank Stadthagen Eg",
    "wof:placetype":"venue"
},
  "geometry": {"coordinates":[9.158869,52.290321],"type":"Point"}
}