{
  "type": "Feature",
  "properties": {
    "iso:country":"DE",
    "sg:address":"Dornenkamp 4",
    "sg:city":"Emsdetten",
    "sg:phone":"+49 2572/1031",
    "sg:postcode":"48282",
    "sg:province":"Nordrhein-Westfalen",
    "wof:name":"Hubert W\u00e4ltermann",
    "wof:placetype":"venue"
},
  "geometry": {"coordinates":[7.527061,52.161411],"type":"Point"}
}