{
  "type": "Feature",
  "properties": {
    "iso:country":"DE",
    "sg:address":"Zeller Str. 19",
    "sg:city":"W\u00fcrzburg",
    "sg:phone":"+49 931/411171",
    "sg:postcode":"97082",
    "sg:province":"Bayern",
    "wof:name":"Schuh-reparaturdienst",
    "wof:placetype":"venue"
},
  "geometry": {"coordinates":[9.9234113693,49.7935523987],"type":"Point"}
}