{
  "type": "Feature",
  "properties": {
    "iso:country":"DE",
    "sg:address":"Achternfelde 4",
    "sg:city":"Norderstedt",
    "sg:phone":"+49 40/5231228",
    "sg:postcode":"22850",
    "sg:province":"Schleswig-Holstein",
    "wof:name":"Hubertus-apotheke",
    "wof:placetype":"venue"
},
  "geometry": {"coordinates":[9.980225,53.682602],"type":"Point"}
}