{
  "type": "Feature",
  "properties": {
    "iso:country":"DE",
    "sg:address":"Siemens Str.9::",
    "sg:city":"Neu-Isenburg",
    "sg:href":"http://api.simplegeo.com/1.0/features/SG_5dnD7pUM2dujhzv6jAyCgP_50.046204_8.676292@1306268793.json",
    "sg:phone":"+49 4961/0271070",
    "sg:postcode":"63263",
    "sg:province":"Hessen",
    "wof:name":"Is Schadenversicherung",
    "wof:placetype":"venue"
},
  "geometry": {"coordinates":[8.676292,50.046204],"type":"Point"}
}