{"geometry":{"type":"Point","coordinates":[8.676292,50.046204]},"type":"Feature","id":102560351,"bbox":[8.676292,50.046204,8.676292,50.046204],"properties":{"sg:province":"Hessen","geom:longitude":8.676292,"wof:breaches":[],"sg:href":"http://api.simplegeo.com/1.0/features/SG_5dnD7pUM2dujhzv6jAyCgP_50.046204_8.676292@1306268793.json","sg:owner":"simplegeo","sg:postcode":"63263","geom:latitude":50.046204,"sg:classifiers":[],"sg:address":"Siemens Str.9::","sg:phone":"+49 4961/0271070","wof:hierarchy":[{"region_id":85682531,"venue_id":102560351,"country_id":85633111,"neighbourhood_id":85796369,"county_id":102063589}],"geom:area":0.000000,"sg:city":"Neu-Isenburg","wof:lastmodified":1438093233,"iso:country":"DE","wof:geomhash":"4212473f88b52b5f0d4fe2a1aa3f8f89","wof:name":"Is Schadenversicherung","wof:belongsto":[85682531,85633111,85796369,102063589],"src:geom":"simplegeo","wof:placetype":"venue","wof:supersedes":[],"wof:id":102560351,"wof:superseded_by":[],"wof:concordances":{"sg:id":"SG_5dnD7pUM2dujhzv6jAyCgP_50.046204_8.676292@1306268793"},"wof:parent_id":85796369}}