{
  "type": "Feature",
  "properties": {
    "iso:country":"DE",
    "sg:address":"Zeppelinstr. 9",
    "sg:city":"K\u00f6ln",
    "sg:phone":"+49 221/2570421",
    "sg:postcode":"50667",
    "sg:province":"Nordrhein-Westfalen",
    "wof:name":"H. Kremer Rechtsanwalt",
    "wof:placetype":"venue"
},
  "geometry": {"coordinates":[6.9486451149,50.937046051],"type":"Point"}
}