{
  "type": "Feature",
  "properties": {
    "iso:country":"DE",
    "sg:address":"Am Kamp 1",
    "sg:city":"Stoltenberg",
    "sg:phone":"+49 4303/555",
    "sg:postcode":"24256",
    "sg:province":"Schleswig-Holstein",
    "wof:name":"Karsten Rusch",
    "wof:placetype":"venue"
},
  "geometry": {"coordinates":[10.364185,54.34473],"type":"Point"}
}