{
  "type": "Feature",
  "properties": {
    "iso:country":"DE",
    "sg:address":"Westtor 10",
    "sg:city":"Sendenhorst",
    "sg:phone":"+49 2526/3455",
    "sg:postcode":"48324",
    "sg:province":"Nordrhein-Westfalen",
    "wof:name":"Christine Wiesner",
    "wof:placetype":"venue"
},
  "geometry": {"coordinates":[7.822298,51.843662],"type":"Point"}
}