{
  "type": "Feature",
  "properties": {
    "iso:country":"DE",
    "sg:address":"Lobker Weg 44",
    "sg:city":"Salzhausen",
    "sg:phone":"+49 4172/6386",
    "sg:postcode":"21376",
    "sg:province":"Niedersachsen",
    "wof:name":"Data Consult Daten-service Gmbh",
    "wof:placetype":"venue"
},
  "geometry": {"coordinates":[10.1909227371,53.2268257141],"type":"Point"}
}