{
  "type": "Feature",
  "properties": {
    "iso:country":"DE",
    "sg:address":"Suurheid 20",
    "sg:city":"Hamburg",
    "sg:postcode":"22559",
    "sg:province":"Hamburg",
    "wof:name":"Wks West-klinikum Serviceges. Mbh",
    "wof:placetype":"venue"
},
  "geometry": {"coordinates":[9.770565033,53.5823287964],"type":"Point"}
}