{
  "type": "Feature",
  "properties": {
    "iso:country":"DE",
    "sg:address":"Markt 17 a",
    "sg:city":"Bredstedt",
    "sg:phone":"+49 4671/91410",
    "sg:postcode":"25821",
    "sg:province":"Schleswig-Holstein",
    "wof:name":"Provinzial Versicherung",
    "wof:placetype":"venue"
},
  "geometry": {"coordinates":[8.9644699097,54.6179542542],"type":"Point"}
}