{
  "type": "Feature",
  "properties": {
    "iso:country":"DE",
    "sg:address":"Bundesstr. 7",
    "sg:city":"St\u00fchlingen",
    "sg:phone":"+49 7744/5211",
    "sg:postcode":"79780",
    "sg:province":"Baden-W\u00fcrttemberg",
    "wof:name":"Herbert Leingruber",
    "wof:placetype":"venue"
},
  "geometry": {"coordinates":[8.457736,47.750858],"type":"Point"}
}