{
  "type": "Feature",
  "properties": {
    "iso:country":"DE",
    "sg:address":"Feldstr. 18",
    "sg:city":"Lengefeld",
    "sg:phone":"+49 37367/2348",
    "sg:postcode":"09514",
    "sg:province":"Sachsen",
    "wof:name":"Manfred Dathe Gmbh",
    "wof:placetype":"venue"
},
  "geometry": {"coordinates":[13.194467,50.722275],"type":"Point"}
}