{
  "type": "Feature",
  "properties": {
    "iso:country":"DE",
    "sg:address":"Hagenwinkel 18",
    "sg:city":"Aichhalden",
    "sg:phone":"+49 7444/2707",
    "sg:postcode":"78733",
    "sg:province":"Baden-W\u00fcrttemberg",
    "wof:name":"Willibald Herrmann",
    "wof:placetype":"venue"
},
  "geometry": {"coordinates":[8.4210929871,48.3017883301],"type":"Point"}
}