{
  "type": "Feature",
  "properties": {
    "iso:country":"DE",
    "sg:address":"Kirchstr. 28",
    "sg:city":"Wiltingen",
    "sg:phone":"+49 6501/180370",
    "sg:postcode":"54459",
    "sg:province":"Rheinland-Pfalz",
    "wof:name":"Eduard Beigl",
    "wof:placetype":"venue"
},
  "geometry": {"coordinates":[6.5891828537,49.659576416],"type":"Point"}
}