{
  "type": "Feature",
  "properties": {
    "iso:country":"DE",
    "sg:address":"Gro\u00dfe Str. 26",
    "sg:city":"Kranenburg",
    "sg:phone":"+49 2826/368",
    "sg:postcode":"47559",
    "sg:province":"Nordrhein-Westfalen",
    "wof:name":"J\u00fcrgen Ern",
    "wof:placetype":"venue"
},
  "geometry": {"coordinates":[6.0091738701,51.789642334],"type":"Point"}
}