{
  "type": "Feature",
  "properties": {
    "iso:country":"DE",
    "sg:address":"Sanderring 2",
    "sg:city":"W\u00fcrzburg",
    "sg:phone":"+49 931/311",
    "sg:postcode":"97070",
    "sg:province":"Bayern",
    "wof:name":"Institut F\u00fcr Statistik Bibliothek",
    "wof:placetype":"venue"
},
  "geometry": {"coordinates":[9.935921,49.788113],"type":"Point"}
}