{
  "type": "Feature",
  "properties": {
    "iso:country":"DE",
    "sg:address":"Wolfsl\u00fcckenweg 35",
    "sg:city":"Frohburg",
    "sg:phone":"+49 34348/51414",
    "sg:postcode":"04654",
    "sg:province":"Sachsen",
    "wof:name":"G. Dorawa",
    "wof:placetype":"venue"
},
  "geometry": {"coordinates":[12.55857,51.066654],"type":"Point"}
}