{
  "type": "Feature",
  "properties": {
    "iso:country":"DE",
    "sg:address":"Diedesbach 10",
    "sg:city":"Idar-Oberstein",
    "sg:phone":"+49 6781/35738",
    "sg:postcode":"55743",
    "sg:province":"Rheinland-Pfalz",
    "wof:name":"U. Rathmacher",
    "wof:placetype":"venue"
},
  "geometry": {"coordinates":[7.276157,49.751503],"type":"Point"}
}