{
  "type": "Feature",
  "properties": {
    "iso:country":"DE",
    "sg:address":"Am Flugplatz 4",
    "sg:city":"Bielefeld",
    "sg:phone":"+49 521/49609",
    "sg:postcode":"33659",
    "sg:province":"Nordrhein-Westfalen",
    "wof:name":"Alexander Putsch",
    "wof:placetype":"venue"
},
  "geometry": {"coordinates":[8.553109169,51.963142395],"type":"Point"}
}