{
  "type": "Feature",
  "properties": {
    "iso:country":"DE",
    "sg:address":"Poststr. 24",
    "sg:city":"Zweibr\u00fccken",
    "sg:phone":"+49 6332/74300",
    "sg:postcode":"66482",
    "sg:province":"Rheinland-Pfalz",
    "wof:name":"Emmert",
    "wof:placetype":"venue"
},
  "geometry": {"coordinates":[7.3598542213,49.2487487793],"type":"Point"}
}