{
  "type": "Feature",
  "properties": {
    "iso:country":"DE",
    "sg:address":"Heinrichstr. 36",
    "sg:city":"Reinheim",
    "sg:phone":"+49 6162/913790",
    "sg:postcode":"64354",
    "sg:province":"Hessen",
    "wof:name":"Dorfstadl",
    "wof:placetype":"venue"
},
  "geometry": {"coordinates":[8.836104393,49.8283004761],"type":"Point"}
}