{
  "type": "Feature",
  "properties": {
    "iso:country":"DE",
    "sg:address":"Adlerstr. 1",
    "sg:city":"Essen",
    "sg:phone":"+49 4920/1860600",
    "sg:postcode":"45307",
    "sg:province":"Nordrhein-Westfalen",
    "wof:name":"Rhenisch-druck Gmbh",
    "wof:placetype":"venue"
},
  "geometry": {"coordinates":[7.1007680893,51.4638252258],"type":"Point"}
}