{
  "type": "Feature",
  "properties": {
    "iso:country":"DE",
    "sg:address":"Frankfurter Str. 24",
    "sg:city":"Limburg",
    "sg:phone":"+49 6431/73182",
    "sg:postcode":"65551",
    "sg:province":"Hessen",
    "wof:name":"Ursula Brahm",
    "wof:placetype":"venue"
},
  "geometry": {"coordinates":[8.1206226349,50.3735198975],"type":"Point"}
}