{
  "type": "Feature",
  "properties": {
    "iso:country":"DE",
    "sg:address":"Robert-Koch-Str. 46",
    "sg:city":"Plaidt",
    "sg:phone":"+49 2632/6600",
    "sg:postcode":"56637",
    "sg:province":"Rheinland-Pfalz",
    "wof:name":"Liane Schmitz",
    "wof:placetype":"venue"
},
  "geometry": {"coordinates":[7.40224,50.392975],"type":"Point"}
}