{
  "type": "Feature",
  "properties": {
    "iso:country":"DE",
    "sg:address":"Vehlberger Kirchweg 6",
    "sg:city":"Aurach",
    "sg:phone":"+49 9804/913500",
    "sg:postcode":"91589",
    "sg:province":"Bayern",
    "wof:name":"Peter Reis & Christina L\u00fcpke",
    "wof:placetype":"venue"
},
  "geometry": {"coordinates":[10.338888,49.235516],"type":"Point"}
}