{
  "type": "Feature",
  "properties": {
    "iso:country":"DE",
    "sg:address":"Woltringhausen 16",
    "sg:city":"Uchte",
    "sg:postcode":"31600",
    "sg:province":"Niedersachsen",
    "wof:name":"Windenergie Woltring- Hausen Gmbh",
    "wof:placetype":"venue"
},
  "geometry": {"coordinates":[8.900629,52.550797],"type":"Point"}
}