{
  "type": "Feature",
  "properties": {
    "iso:country":"DE",
    "sg:address":"Brunnenstr. 60",
    "sg:city":"D\u00fcsseldorf",
    "sg:postcode":"40223",
    "sg:province":"Nordrhein-Westfalen",
    "wof:name":"Picturemakers Gmbh",
    "wof:placetype":"venue"
},
  "geometry": {"coordinates":[6.7805929184,51.2045555115],"type":"Point"}
}