{
  "type": "Feature",
  "properties": {
    "iso:country":"DE",
    "sg:address":"Gro\u00dfenseer Str. 15",
    "sg:city":"Trittau",
    "sg:phone":"+49 4154/83462",
    "sg:postcode":"22946",
    "sg:province":"Schleswig-Holstein",
    "wof:name":"J\u00f6rn Witte",
    "wof:placetype":"venue"
},
  "geometry": {"coordinates":[10.38806,53.613468],"type":"Point"}
}