{
  "type": "Feature",
  "properties": {
    "iso:country":"DE",
    "sg:address":"Richard-Byrd-Str. 20",
    "sg:city":"K\u00f6ln",
    "sg:phone":"+49 221/9565530",
    "sg:postcode":"50829",
    "sg:province":"Nordrhein-Westfalen",
    "wof:name":"Josefine Meyer Gmbh",
    "wof:placetype":"venue"
},
  "geometry": {"coordinates":[6.888537,50.989117],"type":"Point"}
}