{
  "type": "Feature",
  "properties": {
    "iso:country":"DE",
    "sg:address":"Stader Str. 12",
    "sg:city":"Bremen",
    "sg:phone":"+49 421/499055",
    "sg:postcode":"28205",
    "sg:province":"Bremen",
    "wof:name":"Vivus Ambulante Pflege Und Betreuung",
    "wof:placetype":"venue"
},
  "geometry": {"coordinates":[8.847982,53.066746],"type":"Point"}
}