{
  "type": "Feature",
  "properties": {
    "iso:country":"DE",
    "sg:address":"G\u00fcthstr. 47",
    "sg:city":"G\u00fctersloh",
    "sg:phone":"+49 5241/7104",
    "sg:postcode":"33335",
    "sg:province":"Nordrhein-Westfalen",
    "wof:name":"Heinz Eusterhus Drogerie",
    "wof:placetype":"venue"
},
  "geometry": {"coordinates":[8.445207,51.933273],"type":"Point"}
}