{
  "type": "Feature",
  "properties": {
    "iso:country":"DE",
    "sg:address":"Thanner Str. 2",
    "sg:city":"Holzkirchen",
    "sg:phone":"+49 8024/2519",
    "sg:postcode":"83607",
    "sg:province":"Bayern",
    "wof:name":"Bertrand Mayer Gmbh Steinmetzbetrieb",
    "wof:placetype":"venue"
},
  "geometry": {"coordinates":[11.7009334564,47.8762245178],"type":"Point"}
}