{
  "type": "Feature",
  "properties": {
    "iso:country":"DE",
    "sg:address":"Bornheimer Landstr. 10",
    "sg:city":"Frankfurt",
    "sg:phone":"+49 69/431084",
    "sg:postcode":"60316",
    "sg:province":"Hessen",
    "wof:name":"Die Hutschachtel Inh. S. Brandenstein",
    "wof:placetype":"venue"
},
  "geometry": {"coordinates":[8.6981725693,50.1220245361],"type":"Point"}
}