{
  "type": "Feature",
  "properties": {
    "iso:country":"DE",
    "sg:address":"K\u00f6nigsdorfer Str. 11",
    "sg:city":"M\u00fcnchen",
    "sg:phone":"+49 89/2021433",
    "sg:postcode":"81371",
    "sg:province":"Bayern",
    "wof:name":"Dr. Korth & Partner Gmbh",
    "wof:placetype":"venue"
},
  "geometry": {"coordinates":[11.5521259308,48.1175270081],"type":"Point"}
}