{
  "type": "Feature",
  "properties": {
    "iso:country":"DE",
    "sg:address":"Schulstr. 39A",
    "sg:city":"St\u00fctzengr\u00fcn",
    "sg:phone":"+49 37462/4744",
    "sg:postcode":"08328",
    "sg:province":"Sachsen",
    "wof:name":"Wolfgang Sch\u00e4dlich",
    "wof:placetype":"venue"
},
  "geometry": {"coordinates":[12.5306167603,50.5260925293],"type":"Point"}
}