{
  "type": "Feature",
  "properties": {
    "iso:country":"DE",
    "sg:address":"Auf den Kellern 22",
    "sg:city":"Forchheim",
    "sg:phone":"+49 9191/729564",
    "sg:postcode":"91301",
    "sg:province":"Bayern",
    "wof:name":"Hebendanzkeller",
    "wof:placetype":"venue"
},
  "geometry": {"coordinates":[11.0748157501,49.7292671204],"type":"Point"}
}