{
  "type": "Feature",
  "properties": {
    "iso:country":"DE",
    "sg:address":"H\u00f6rn 7",
    "sg:city":"Schretstaken",
    "sg:phone":"+49 4156/7148",
    "sg:postcode":"21493",
    "sg:province":"Schleswig-Holstein",
    "wof:name":"G\u00fcnter Michaelis",
    "wof:placetype":"venue"
},
  "geometry": {"coordinates":[10.53853,53.588551],"type":"Point"}
}