{
  "type": "Feature",
  "properties": {
    "iso:country":"DE",
    "sg:address":"Willi-Gall-Str. 15",
    "sg:city":"Oberseifersdorf",
    "sg:phone":"+49 3583/708314",
    "sg:postcode":"02763",
    "sg:province":"Sachsen",
    "wof:name":"Andreas Ritter",
    "wof:placetype":"venue"
},
  "geometry": {"coordinates":[14.7957391739,50.9455375671],"type":"Point"}
}