{
  "type": "Feature",
  "properties": {
    "iso:country":"DE",
    "sg:address":"B\u00fcrgerm.-Hengeler-Str. 7",
    "sg:city":"Waltenhofen",
    "sg:phone":"+49 8303/921064",
    "sg:postcode":"87448",
    "sg:province":"Bayern",
    "wof:name":"M. Kreuzer",
    "wof:placetype":"venue"
},
  "geometry": {"coordinates":[10.3028335571,47.6717414856],"type":"Point"}
}