{
  "type": "Feature",
  "properties": {
    "iso:country":"DE",
    "sg:address":"S\u00e4lzer Str. 18",
    "sg:city":"Ransbach-Baumbach",
    "sg:phone":"+49 2623/881590",
    "sg:postcode":"56235",
    "sg:province":"Rheinland-Pfalz",
    "wof:name":"Rainbow Systems Computer Und Consultings",
    "wof:placetype":"venue"
},
  "geometry": {"coordinates":[7.752937,50.475269],"type":"Point"}
}