{
  "type": "Feature",
  "properties": {
    "iso:country":"DE",
    "sg:address":"Korntaler Str. 133",
    "sg:city":"Stuttgart",
    "sg:phone":"+49 711/802899",
    "sg:postcode":"70439",
    "sg:province":"Baden-W\u00fcrttemberg",
    "wof:name":"Detektiv-agentur Thomas Vollrath Gmbh",
    "wof:placetype":"venue"
},
  "geometry": {"coordinates":[9.146868,48.842041],"type":"Point"}
}