{
  "type": "Feature",
  "properties": {
    "iso:country":"DE",
    "sg:address":"Findorffstr. 105",
    "sg:city":"Bremen",
    "sg:phone":"+49 421/308000",
    "sg:postcode":"28215",
    "sg:province":"Bremen",
    "wof:name":"Btz - Bremer Tourismus Zentrale Gmbh",
    "wof:placetype":"venue"
},
  "geometry": {"coordinates":[8.8113508224,53.089214325],"type":"Point"}
}