{
  "type": "Feature",
  "properties": {
    "iso:country":"DE",
    "sg:address":"Kirchenstr. 2",
    "sg:city":"Bad Rappenau",
    "sg:postcode":"74906",
    "sg:province":"Baden-W\u00fcrttemberg",
    "wof:name":"Ghb Wohnbau Gmbh",
    "wof:placetype":"venue"
},
  "geometry": {"coordinates":[9.1029224396,49.2398605347],"type":"Point"}
}