{
  "type": "Feature",
  "properties": {
    "iso:country":"DE",
    "sg:address":"Breslauer Str 2",
    "sg:city":"Eislingen",
    "sg:phone":"+49 7161/817877",
    "sg:postcode":"73054",
    "sg:province":"Baden-W\u00fcrttemberg",
    "wof:name":"Procoves Industrie Verkaufsleitung Deutschland Wolfgang Persicke",
    "wof:placetype":"venue"
},
  "geometry": {"coordinates":[9.7172794342,48.704460144],"type":"Point"}
}