{
  "type": "Feature",
  "properties": {
    "iso:country":"DE",
    "sg:address":"Bahnhofplatz 4",
    "sg:city":"W\u00fcrzburg",
    "sg:phone":"+49 931/54389",
    "sg:postcode":"97070",
    "sg:province":"Bayern",
    "wof:name":"Josef Strykowski Ohg",
    "wof:placetype":"venue"
},
  "geometry": {"coordinates":[9.9361076355,49.8009719849],"type":"Point"}
}