{
  "type": "Feature",
  "properties": {
    "iso:country":"DE",
    "sg:address":"Morgensternstr. 2",
    "sg:city":"Leipzig",
    "sg:phone":"+49 341/4774223",
    "sg:postcode":"04179",
    "sg:province":"Sachsen",
    "wof:name":"Lutz Tippner",
    "wof:placetype":"venue"
},
  "geometry": {"coordinates":[12.31169,51.334728],"type":"Point"}
}