{
  "type": "Feature",
  "properties": {
    "iso:country":"DE",
    "sg:address":"Auenstr. 19",
    "sg:city":"Kissing",
    "sg:phone":"+49 8233/79010",
    "sg:postcode":"86438",
    "sg:province":"Bayern",
    "wof:name":"Heisserer Bau Gmbh",
    "wof:placetype":"venue"
},
  "geometry": {"coordinates":[10.958793,48.31382],"type":"Point"}
}