{
  "type": "Feature",
  "properties": {
    "iso:country":"DE",
    "sg:address":"Riekenhof 12",
    "sg:city":"Gronau",
    "sg:phone":"+49 2565/97500",
    "sg:postcode":"48599",
    "sg:province":"Nordrhein-Westfalen",
    "wof:name":"Lauf Gmbh",
    "wof:placetype":"venue"
},
  "geometry": {"coordinates":[7.034106,52.186485],"type":"Point"}
}