{
  "type": "Feature",
  "properties": {
    "iso:country":"DE",
    "sg:address":"Moltkestr. 2 a",
    "sg:city":"Kaiserslautern",
    "sg:phone":"+49 631/22648",
    "sg:postcode":"67655",
    "sg:province":"Rheinland-Pfalz",
    "wof:name":"Lido Bar",
    "wof:placetype":"venue"
},
  "geometry": {"coordinates":[7.76227,49.443481],"type":"Point"}
}