{
  "type": "Feature",
  "properties": {
    "iso:country":"DE",
    "sg:address":"R\u00f6merstr. 4",
    "sg:city":"Badenweiler",
    "sg:phone":"+49 7632/82240",
    "sg:postcode":"79410",
    "sg:province":"Baden-W\u00fcrttemberg",
    "wof:name":"Hotel Siegle",
    "wof:placetype":"venue"
},
  "geometry": {"coordinates":[7.6742210388,47.8038635254],"type":"Point"}
}