{
  "type": "Feature",
  "properties": {
    "iso:country":"DE",
    "sg:address":"Marktgasse 8",
    "sg:city":"Bad Br\u00fcckenau",
    "sg:phone":"+49 9741/5198",
    "sg:postcode":"97769",
    "sg:province":"Bayern",
    "wof:name":"E. Eberhardt",
    "wof:placetype":"venue"
},
  "geometry": {"coordinates":[9.79217,50.310558],"type":"Point"}
}