{
  "type": "Feature",
  "properties": {
    "iso:country":"DE",
    "sg:address":"Auf der Rosenh\u00f6he 66",
    "sg:city":"Offenbach",
    "sg:phone":"+49 69/845699",
    "sg:postcode":"63069",
    "sg:province":"Hessen",
    "wof:name":"Biergarten",
    "wof:placetype":"venue"
},
  "geometry": {"coordinates":[8.7556829453,50.0775260925],"type":"Point"}
}