{
  "type": "Feature",
  "properties": {
    "iso:country":"DE",
    "sg:address":"Gertrudenstr. 24-28",
    "sg:city":"K\u00f6ln",
    "sg:phone":"+49 221/2578266",
    "sg:postcode":"50667",
    "sg:province":"Nordrhein-Westfalen",
    "wof:name":"Findeisen K\u00fchn Und Braun Rechtsanw\u00e4lte",
    "wof:placetype":"venue"
},
  "geometry": {"coordinates":[6.9457612038,50.9380493164],"type":"Point"}
}