{
  "type": "Feature",
  "properties": {
    "iso:country":"DE",
    "sg:address":"Hohe Str. 8",
    "sg:city":"Elz",
    "sg:phone":"+49 700 5463 3663",
    "sg:postcode":"65604",
    "sg:province":"Hessen",
    "wof:name":"Wolfgang Lindenmeyer",
    "wof:placetype":"venue"
},
  "geometry": {"coordinates":[7.9977707863,50.4413146973],"type":"Point"}
}