{
  "type": "Feature",
  "properties": {
    "iso:country":"DE",
    "sg:address":"Waldhausener Str. 160",
    "sg:city":"M\u00f6nchengladbach",
    "sg:phone":"+49 2161/406555",
    "sg:postcode":"41061",
    "sg:province":"Nordrhein-Westfalen",
    "wof:name":"Hotel Steffens",
    "wof:placetype":"venue"
},
  "geometry": {"coordinates":[6.4219031334,51.1968803406],"type":"Point"}
}