{
  "type": "Feature",
  "properties": {
    "iso:country":"DE",
    "sg:address":"Obere Hauptstr. 17",
    "sg:city":"Brunnen",
    "sg:phone":"+49 8454/3226",
    "sg:postcode":"86564",
    "sg:province":"Bayern",
    "wof:name":"Josef Kneilling",
    "wof:placetype":"venue"
},
  "geometry": {"coordinates":[11.35981,48.632298],"type":"Point"}
}