{
  "type": "Feature",
  "properties": {
    "iso:country":"DE",
    "sg:address":"Herzog-Ludwig-Str. 60",
    "sg:city":"Zorneding",
    "sg:phone":"+49 8106/247036",
    "sg:postcode":"85604",
    "sg:province":"Bayern",
    "wof:name":"Wolf-r\u00fcdiger Hempel Kunstmaler",
    "wof:placetype":"venue"
},
  "geometry": {"coordinates":[11.835335,48.084488],"type":"Point"}
}