{
  "type": "Feature",
  "properties": {
    "iso:country":"DE",
    "sg:address":"Schustehrusstr. 17",
    "sg:city":"Berlin",
    "sg:phone":"+49 30/3412324",
    "sg:postcode":"10585",
    "sg:province":"Berlin",
    "wof:name":"Bestattungsinstitut Edelgarde Vogt",
    "wof:placetype":"venue"
},
  "geometry": {"coordinates":[13.303358,52.517132],"type":"Point"}
}