{
  "type": "Feature",
  "properties": {
    "iso:country":"DE",
    "sg:address":"Sachsenstr. 100",
    "sg:city":"Oldenburg",
    "sg:phone":"+49 441/86951",
    "sg:postcode":"26121",
    "sg:province":"Niedersachsen",
    "wof:name":"Heino Burhop Gmbh",
    "wof:placetype":"venue"
},
  "geometry": {"coordinates":[8.219147,53.161339],"type":"Point"}
}