{
  "type": "Feature",
  "properties": {
    "iso:country":"DE",
    "sg:address":"Blockstr. 6",
    "sg:city":"M\u00fcnchhausen",
    "sg:phone":"+49 6423/3900",
    "sg:postcode":"35117",
    "sg:province":"Hessen",
    "wof:name":"Katharina Franck",
    "wof:placetype":"venue"
},
  "geometry": {"coordinates":[8.700012,50.932674],"type":"Point"}
}