{
  "type": "Feature",
  "properties": {
    "iso:country":"DE",
    "sg:address":"Nisterbergerweg",
    "sg:city":"Friedewald",
    "sg:phone":"+49 2743/6061",
    "sg:postcode":"57520",
    "sg:province":"Rheinland-Pfalz",
    "wof:name":"Rudolf Lenz Kg",
    "wof:placetype":"venue"
},
  "geometry": {"coordinates":[7.9581289291,50.7081375122],"type":"Point"}
}