{
  "type": "Feature",
  "properties": {
    "iso:country":"DE",
    "sg:address":"Rindenmooser Str. 98",
    "sg:city":"Mittelbiberach",
    "sg:phone":"+49 7351/14440",
    "sg:postcode":"88441",
    "sg:province":"Baden-W\u00fcrttemberg",
    "wof:name":"Donau Immobilien Gmbh",
    "wof:placetype":"venue"
},
  "geometry": {"coordinates":[9.7650108337,48.0666503906],"type":"Point"}
}