{
  "type": "Feature",
  "properties": {
    "iso:country":"DE",
    "sg:address":"Zur Sch\u00f6nen Aussicht 7a",
    "sg:city":"Regensburg",
    "sg:phone":"+49 941/36140",
    "sg:postcode":"93051",
    "sg:province":"Bayern",
    "wof:name":"Prof. Ferdinand Diepold",
    "wof:placetype":"venue"
},
  "geometry": {"coordinates":[12.0529270172,49.0092010498],"type":"Point"}
}