{
  "type": "Feature",
  "properties": {
    "iso:country":"DE",
    "sg:address":"Planetenfeldstr. 97",
    "sg:city":"Dortmund",
    "sg:phone":"+49 231/96300",
    "sg:postcode":"44379",
    "sg:province":"Nordrhein-Westfalen",
    "wof:name":"Cimware Ges. F\u00fcr Rechnerge- St\u00fctzte Konstruktionen Und",
    "wof:placetype":"venue"
},
  "geometry": {"coordinates":[7.394045,51.504734],"type":"Point"}
}