{
  "type": "Feature",
  "properties": {
    "iso:country":"DE",
    "sg:address":"Friedrichstr. 6",
    "sg:city":"Wiesbaden",
    "sg:postcode":"65185",
    "sg:province":"Hessen",
    "wof:name":"Tec International Germany Gmbh",
    "wof:placetype":"venue"
},
  "geometry": {"coordinates":[8.2442359924,50.0804862976],"type":"Point"}
}