{
  "type": "Feature",
  "properties": {
    "iso:country":"DE",
    "sg:address":"Sch\u00f6necker Str. 35",
    "sg:city":"Tirschendorf",
    "sg:phone":"+49 37421/22550",
    "sg:postcode":"08606",
    "sg:province":"Sachsen",
    "wof:name":"Agrargenossenschaft Tirschendorf Eg",
    "wof:placetype":"venue"
},
  "geometry": {"coordinates":[12.23583,50.403381],"type":"Point"}
}