{
  "type": "Feature",
  "properties": {
    "iso:country":"DE",
    "sg:address":"Warendorfer Str. 43",
    "sg:city":"M\u00fcnster",
    "sg:phone":"+49 251/36705",
    "sg:postcode":"48145",
    "sg:province":"Nordrhein-Westfalen",
    "wof:name":"Klaus Overbeck Kg",
    "wof:placetype":"venue"
},
  "geometry": {"coordinates":[7.6422858238,51.9617919922],"type":"Point"}
}