{
  "type": "Feature",
  "properties": {
    "iso:country":"DE",
    "sg:address":"Am R\u00fcten 7c",
    "sg:city":"Bremen",
    "sg:phone":"+49 421/252983",
    "sg:postcode":"28355",
    "sg:province":"Bremen",
    "wof:name":"Thomas Paul Architekt",
    "wof:placetype":"venue"
},
  "geometry": {"coordinates":[8.897006,53.099365],"type":"Point"}
}