{
  "type": "Feature",
  "properties": {
    "iso:country":"DE",
    "sg:address":"Hoopter Str. 13",
    "sg:city":"Winsen",
    "sg:phone":"+49 4171/2466",
    "sg:postcode":"21423",
    "sg:province":"Niedersachsen",
    "wof:name":"M\u00f6bel Boutique Traute Fuierer",
    "wof:placetype":"venue"
},
  "geometry": {"coordinates":[10.199827,53.368069],"type":"Point"}
}