{
  "type": "Feature",
  "properties": {
    "iso:country":"DE",
    "sg:address":"Niederdorf 13",
    "sg:city":"Hameln",
    "sg:phone":"+49 5151/41102",
    "sg:postcode":"31789",
    "sg:province":"Niedersachsen",
    "wof:name":"Friedrich T\u00f6neb\u00f6n",
    "wof:placetype":"venue"
},
  "geometry": {"coordinates":[9.409488,52.100178],"type":"Point"}
}