{
  "type": "Feature",
  "properties": {
    "iso:country":"DE",
    "sg:address":"Mittelstr. 15",
    "sg:city":"Meschede",
    "sg:phone":"+49 291/51170",
    "sg:postcode":"59872",
    "sg:province":"Nordrhein-Westfalen",
    "wof:name":"Hotel Lindenhof",
    "wof:placetype":"venue"
},
  "geometry": {"coordinates":[8.3358831406,51.3650474548],"type":"Point"}
}