{
  "type": "Feature",
  "properties": {
    "iso:country":"DE",
    "sg:address":"Uhlandstr. 72",
    "sg:city":"Bochum",
    "sg:phone":"+49 234/511351",
    "sg:postcode":"44791",
    "sg:province":"Nordrhein-Westfalen",
    "wof:name":"Dr. Dr. Ildefons Neff",
    "wof:placetype":"venue"
},
  "geometry": {"coordinates":[7.220539093,51.4920806885],"type":"Point"}
}