{
  "type": "Feature",
  "properties": {
    "iso:country":"DE",
    "sg:address":"Humboldtallee 115",
    "sg:city":"Salzgitter",
    "sg:postcode":"38228",
    "sg:province":"Niedersachsen",
    "wof:name":"Wiglo-wunderland Vertriebsges. Mbh & Co. Kg",
    "wof:placetype":"venue"
},
  "geometry": {"coordinates":[10.2986001968,52.1614494324],"type":"Point"}
}