{
  "type": "Feature",
  "properties": {
    "iso:country":"DE",
    "sg:address":"Paulmannsh\u00f6her Str. 17",
    "sg:city":"L\u00fcdenscheid",
    "sg:phone":"+49 2351/9450",
    "sg:postcode":"58515",
    "sg:province":"Nordrhein-Westfalen",
    "wof:name":"Krankenhaus F\u00fcr Sportverletzungen",
    "wof:placetype":"venue"
},
  "geometry": {"coordinates":[7.6573958397,51.2079429626],"type":"Point"}
}