{
  "type": "Feature",
  "properties": {
    "iso:country":"DE",
    "sg:address":"Storistr. 7",
    "sg:city":"Garmisch-Partenkirchen",
    "sg:phone":"+49 8821/1422",
    "sg:postcode":"82467",
    "sg:province":"Bayern",
    "wof:name":"Dia Express Bildagentur Gmbh",
    "wof:placetype":"venue"
},
  "geometry": {"coordinates":[11.0788755417,47.4886322021],"type":"Point"}
}