{
  "type": "Feature",
  "properties": {
    "iso:country":"DE",
    "sg:address":"Spitalstr. 10",
    "sg:city":"L\u00f6rrach",
    "sg:phone":"+49 7621/8051",
    "sg:postcode":"79539",
    "sg:province":"Baden-W\u00fcrttemberg",
    "wof:name":"R. Gehrmann",
    "wof:placetype":"venue"
},
  "geometry": {"coordinates":[7.6596751213,47.6132278442],"type":"Point"}
}