{
  "type": "Feature",
  "properties": {
    "iso:country":"DE",
    "sg:address":"Gunzesried",
    "sg:city":"Blaichach",
    "sg:phone":"+49 8321/85896",
    "sg:postcode":"87544",
    "sg:province":"Bayern",
    "wof:name":"Aubachstube",
    "wof:placetype":"venue"
},
  "geometry": {"coordinates":[10.2291402817,47.5223503113],"type":"Point"}
}