{
  "type": "Feature",
  "properties": {
    "iso:country":"DE",
    "sg:address":"Dockstr.",
    "sg:city":"Bremerhaven",
    "sg:phone":"+49 471/71717",
    "sg:postcode":"27572",
    "sg:province":"Bremen",
    "wof:name":"Yachtschule Weser-elbe Inh. Klaus Usner",
    "wof:placetype":"venue"
},
  "geometry": {"coordinates":[8.583402,53.498695],"type":"Point"}
}