{
  "type": "Feature",
  "properties": {
    "iso:country":"DE",
    "sg:address":"Steinbacher Str. 42",
    "sg:city":"Kronberg",
    "sg:postcode":"61476",
    "sg:province":"Hessen",
    "wof:name":"Sportzentrum Kronberg Gmbh",
    "wof:placetype":"venue"
},
  "geometry": {"coordinates":[8.5515708923,50.1777954102],"type":"Point"}
}