{
  "type": "Feature",
  "properties": {
    "iso:country":"DE",
    "sg:address":"Schwaketenstr. 9",
    "sg:city":"Konstanz",
    "sg:phone":"+49 7531/92520",
    "sg:postcode":"78467",
    "sg:province":"Baden-W\u00fcrttemberg",
    "wof:name":"F. Linzer Rechtsanwalt",
    "wof:placetype":"venue"
},
  "geometry": {"coordinates":[9.1489601135,47.6899986267],"type":"Point"}
}