{
  "type": "Feature",
  "properties": {
    "iso:country":"DE",
    "sg:address":"Hodenberger Str. 35",
    "sg:city":"Bremen",
    "sg:phone":"+49 421/259775",
    "sg:postcode":"28355",
    "sg:province":"Bremen",
    "wof:name":"Hydro-norm Planungs- Und Beratungs-gmbh",
    "wof:placetype":"venue"
},
  "geometry": {"coordinates":[8.946471,53.090553],"type":"Point"}
}