{
  "type": "Feature",
  "properties": {
    "iso:country":"DE",
    "sg:address":"Leineweberring 20",
    "sg:city":"Lanken",
    "sg:phone":"+49 4151/896936",
    "sg:postcode":"21493",
    "sg:province":"Schleswig-Holstein",
    "wof:name":"Hmb Hartmut B\u00fcsche Hartmaterialienbearbeitung",
    "wof:placetype":"venue"
},
  "geometry": {"coordinates":[10.509074,53.533886],"type":"Point"}
}