{
  "type": "Feature",
  "properties": {
    "iso:country":"DE",
    "sg:address":"Anton-Woger-Str. 11",
    "sg:city":"Wasserburg",
    "sg:phone":"+49 8071/92300",
    "sg:postcode":"83512",
    "sg:province":"Bayern",
    "wof:name":"Eddi-platic Gmbh",
    "wof:placetype":"venue"
},
  "geometry": {"coordinates":[12.2036275864,48.0645904541],"type":"Point"}
}