{
  "type": "Feature",
  "properties": {
    "iso:country":"DE",
    "sg:address":"Urbanstr. 13",
    "sg:city":"Neckarsulm",
    "sg:phone":"+49 7132/2378",
    "sg:postcode":"74172",
    "sg:province":"Baden-W\u00fcrttemberg",
    "wof:name":"Restaurant Museumstube",
    "wof:placetype":"venue"
},
  "geometry": {"coordinates":[9.2227067947,49.191860199],"type":"Point"}
}