{
  "type": "Feature",
  "properties": {
    "iso:country":"DE",
    "sg:address":"Max-Reimann-Str. 11",
    "sg:city":"Altenkirchen",
    "sg:phone":"+49 38391/277",
    "sg:postcode":"18556",
    "sg:province":"Mecklenburg-Vorpommern",
    "wof:name":"Alfred Schultz",
    "wof:placetype":"venue"
},
  "geometry": {"coordinates":[13.342698,54.636978],"type":"Point"}
}