{
  "type": "Feature",
  "properties": {
    "iso:country":"DE",
    "sg:address":"Dresdener Str. 56",
    "sg:city":"Bad Liebenwerda",
    "sg:phone":"+49 35341/10511",
    "sg:postcode":"04924",
    "sg:province":"Brandenburg",
    "wof:name":"Bernd Herold",
    "wof:placetype":"venue"
},
  "geometry": {"coordinates":[13.415015,51.515381],"type":"Point"}
}