{
  "type": "Feature",
  "properties": {
    "iso:country":"DE",
    "sg:address":"Zweibr\u00fcggen 13",
    "sg:city":"\u00dcbach-Palenberg",
    "sg:phone":"+49 2451/2563",
    "sg:postcode":"52531",
    "sg:province":"Nordrhein-Westfalen",
    "wof:name":"Restaurant G. Houben",
    "wof:placetype":"venue"
},
  "geometry": {"coordinates":[6.1025028229,50.9354476929],"type":"Point"}
}