{
  "type": "Feature",
  "properties": {
    "iso:country":"DE",
    "sg:address":"Eichh\u00f6rnchenweg 22",
    "sg:city":"Jesteburg",
    "sg:phone":"+49 4183/97440",
    "sg:postcode":"21266",
    "sg:province":"Niedersachsen",
    "wof:name":"Gesche Creon Rechtsanw\u00e4ltin",
    "wof:placetype":"venue"
},
  "geometry": {"coordinates":[9.9411287308,53.2955551147],"type":"Point"}
}