{
  "type": "Feature",
  "properties": {
    "iso:country":"DE",
    "sg:address":"Aldekerker Str. 20",
    "sg:city":"Rheurdt",
    "sg:phone":"+49 2845/963135",
    "sg:postcode":"47509",
    "sg:province":"Nordrhein-Westfalen",
    "wof:name":"Restaurant Rusticana",
    "wof:placetype":"venue"
},
  "geometry": {"coordinates":[6.4663128853,51.4669456482],"type":"Point"}
}