{
  "type": "Feature",
  "properties": {
    "iso:country":"DE",
    "sg:address":"Deversdonk 1",
    "sg:city":"Grefrath",
    "sg:phone":"+49 2158/911688",
    "sg:postcode":"47929",
    "sg:province":"Nordrhein-Westfalen",
    "wof:name":"Peter Beck Rechtsanwalt",
    "wof:placetype":"venue"
},
  "geometry": {"coordinates":[6.3421211243,51.337020874],"type":"Point"}
}