{
  "type": "Feature",
  "properties": {
    "iso:country":"DE",
    "sg:address":"Kreuznacher Str. 2",
    "sg:city":"Bad Sobernheim",
    "sg:phone":"+49 6751/3280",
    "sg:postcode":"55566",
    "sg:province":"Rheinland-Pfalz",
    "wof:name":"Wolfgang Bamberger Weinanbau",
    "wof:placetype":"venue"
},
  "geometry": {"coordinates":[7.6708598137,49.8035430908],"type":"Point"}
}