{
  "type": "Feature",
  "properties": {
    "iso:country":"DE",
    "sg:address":"Rosenweg 2",
    "sg:city":"Hilden",
    "sg:phone":"+49 2103/64770",
    "sg:postcode":"40723",
    "sg:province":"Nordrhein-Westfalen",
    "wof:name":"D. Danne Gmbh",
    "wof:placetype":"venue"
},
  "geometry": {"coordinates":[6.943257,51.157459],"type":"Point"}
}