{
  "type": "Feature",
  "properties": {
    "iso:country":"DE",
    "sg:address":"Marktstr. 14",
    "sg:city":"Greven",
    "sg:phone":"+49 2571/97151",
    "sg:postcode":"48268",
    "sg:province":"Nordrhein-Westfalen",
    "wof:name":"Vanity Inh. Carolin Vietmeier",
    "wof:placetype":"venue"
},
  "geometry": {"coordinates":[7.61244,52.092979],"type":"Point"}
}