{
  "type": "Feature",
  "properties": {
    "iso:country":"DE",
    "sg:address":"Paradiesstr. 9",
    "sg:city":"N\u00fcrnberg",
    "sg:phone":"+49 911/444404",
    "sg:postcode":"90459",
    "sg:province":"Bayern",
    "wof:name":"Walter Veit Gmbh",
    "wof:placetype":"venue"
},
  "geometry": {"coordinates":[11.0772342682,49.443523407],"type":"Point"}
}