{
  "type": "Feature",
  "properties": {
    "iso:country":"DE",
    "sg:address":"Oberer Graben 19",
    "sg:city":"Plauen",
    "sg:phone":"+49 3741/226264",
    "sg:postcode":"08527",
    "sg:province":"Sachsen",
    "wof:name":"Thomas Beurich",
    "wof:placetype":"venue"
},
  "geometry": {"coordinates":[12.133108,50.494076],"type":"Point"}
}