{
  "type": "Feature",
  "properties": {
    "iso:country":"DE",
    "sg:address":"Postfach 104239:: 40033 D\u00fcsseldorf:: Germany.^^Hans-B\u00f6ckler-Strasse 33::",
    "sg:city":"D\u00fcsseldorf",
    "sg:phone":"+49 211/517980",
    "sg:postcode":"40476",
    "sg:province":"Nordrhein-Westfalen",
    "wof:name":"Westinvest-gesellschaft F\u00fcr Investmentfonds Mbh",
    "wof:placetype":"venue"
},
  "geometry": {"coordinates":[6.78313,51.248184],"type":"Point"}
}