{
  "type": "Feature",
  "properties": {
    "iso:country":"DE",
    "sg:address":"Neumarkt 17",
    "sg:city":"Zschopau",
    "sg:phone":"+49 3725/22123",
    "sg:postcode":"09405",
    "sg:province":"Sachsen",
    "wof:name":"Eberhard Neubert",
    "wof:placetype":"venue"
},
  "geometry": {"coordinates":[13.069852,50.747684],"type":"Point"}
}