{
  "type": "Feature",
  "properties": {
    "iso:country":"DE",
    "sg:address":"Zeppelinstr. 87",
    "sg:city":"Stuttgart",
    "sg:phone":"+49 711/6369230",
    "sg:postcode":"70193",
    "sg:province":"Baden-W\u00fcrttemberg",
    "wof:name":"Klaus Friedel Ingenieur",
    "wof:placetype":"venue"
},
  "geometry": {"coordinates":[9.1474571228,48.7791290283],"type":"Point"}
}