{
  "type": "Feature",
  "properties": {
    "iso:country":"DE",
    "sg:address":"Ausschl\u00e4ger Weg 41",
    "sg:city":"Hamburg",
    "sg:phone":"+49 40/2513341",
    "sg:postcode":"20537",
    "sg:province":"Hamburg",
    "wof:name":"Julius H\u00fcpeden",
    "wof:placetype":"venue"
},
  "geometry": {"coordinates":[10.0358200073,53.5512123108],"type":"Point"}
}