{
  "type": "Feature",
  "properties": {
    "iso:country":"DE",
    "sg:address":"Mathildenstr. 9",
    "sg:city":"Kellinghusen",
    "sg:phone":"+49 4822/1570",
    "sg:postcode":"25548",
    "sg:province":"Schleswig-Holstein",
    "wof:name":"Otto Ralfs",
    "wof:placetype":"venue"
},
  "geometry": {"coordinates":[9.718083,53.952831],"type":"Point"}
}