{
  "type": "Feature",
  "properties": {
    "iso:country":"DE",
    "sg:address":"Angerberg 12",
    "sg:city":"Marienm\u00fcnster",
    "sg:phone":"+49 5276/8789",
    "sg:postcode":"37696",
    "sg:province":"Nordrhein-Westfalen",
    "wof:name":"Pizzeria Taormina",
    "wof:placetype":"venue"
},
  "geometry": {"coordinates":[9.246635437,51.7908439636],"type":"Point"}
}