{
  "type": "Feature",
  "properties": {
    "iso:country":"DE",
    "sg:address":"Ginsterweg 7",
    "sg:city":"Filderstadt",
    "sg:phone":"+49 711/771971",
    "sg:postcode":"70794",
    "sg:province":"Baden-W\u00fcrttemberg",
    "wof:name":"Siegfried Kopp",
    "wof:placetype":"venue"
},
  "geometry": {"coordinates":[9.2177362442,48.6583328247],"type":"Point"}
}