{
  "type": "Feature",
  "properties": {
    "iso:country":"DE",
    "sg:address":"Augsburger Str. 82",
    "sg:city":"Dresden",
    "sg:phone":"+49 351/337735",
    "sg:postcode":"01277",
    "sg:province":"Sachsen",
    "wof:name":"Schrank Und Schirlitz Vermessungsb\u00fcro",
    "wof:placetype":"venue"
},
  "geometry": {"coordinates":[13.7995843887,51.0446739197],"type":"Point"}
}