{
  "type": "Feature",
  "properties": {
    "iso:country":"DE",
    "sg:address":"Frauenstr. 1",
    "sg:city":"Ulm",
    "sg:phone":"+49 731/967870",
    "sg:postcode":"89073",
    "sg:province":"Baden-W\u00fcrttemberg",
    "wof:name":"Fr\u00f6schl & Co. Gmbh & Co.",
    "wof:placetype":"venue"
},
  "geometry": {"coordinates":[9.9957361221,48.3977088928],"type":"Point"}
}