{
  "type": "Feature",
  "properties": {
    "iso:country":"DE",
    "sg:address":"Heiderstr. 113",
    "sg:city":"Wegberg",
    "sg:phone":"+49 2436/1064",
    "sg:postcode":"41844",
    "sg:province":"Nordrhein-Westfalen",
    "wof:name":"Alfred Schmitz",
    "wof:placetype":"venue"
},
  "geometry": {"coordinates":[6.2079658508,51.1566238403],"type":"Point"}
}