{
  "type": "Feature",
  "properties": {
    "iso:country":"DE",
    "sg:address":"Kleib\u00f6merstr. 21",
    "sg:city":"Hanau",
    "sg:phone":"+49 6181/12342",
    "sg:postcode":"63452",
    "sg:province":"Hessen",
    "wof:name":"Uwe Neunemann",
    "wof:placetype":"venue"
},
  "geometry": {"coordinates":[8.9288978577,50.1390953064],"type":"Point"}
}