{
  "type": "Feature",
  "properties": {
    "iso:country":"DE",
    "sg:address":"Sonnenbuehlstr. 1",
    "sg:city":"Bad Ditzenbach",
    "sg:phone":"+49 7334/96540",
    "sg:postcode":"73342",
    "sg:province":"Baden-W\u00fcrttemberg",
    "wof:name":"Kraeuterhaus Sanct Bernhard Gmbh",
    "wof:placetype":"venue"
},
  "geometry": {"coordinates":[9.694763,48.588207],"type":"Point"}
}