{
  "type": "Feature",
  "properties": {
    "iso:country":"DE",
    "sg:address":"Lutherstr. 6",
    "sg:city":"Ludwigshafen",
    "sg:phone":"+49 621/519435",
    "sg:postcode":"67059",
    "sg:province":"Rheinland-Pfalz",
    "wof:name":"Ev. Pfarramt Mitte 2",
    "wof:placetype":"venue"
},
  "geometry": {"coordinates":[8.445142746,49.4808883667],"type":"Point"}
}