{
  "type": "Feature",
  "properties": {
    "iso:country":"DE",
    "sg:address":"Marrstallstra\u00dfe 25",
    "sg:city":"Schwetzingen",
    "sg:phone":"+49 171 4415442",
    "sg:postcode":"68723",
    "sg:province":"Baden-W\u00fcrttemberg",
    "wof:name":"Helmlinger Bau",
    "wof:placetype":"venue"
},
  "geometry": {"coordinates":[8.5768547058,49.3822937012],"type":"Point"}
}