{
  "type": "Feature",
  "properties": {
    "iso:country":"DE",
    "sg:address":"Schiffertorsstr. 26",
    "sg:city":"Stade",
    "sg:phone":"+49 4141/922030",
    "sg:postcode":"21682",
    "sg:province":"Niedersachsen",
    "wof:name":"Iub Ingenieurb\u00fcro Umwelt Und Bau Gmbh",
    "wof:placetype":"venue"
},
  "geometry": {"coordinates":[9.4660453796,53.604347229],"type":"Point"}
}