{
  "type": "Feature",
  "properties": {
    "iso:country":"DE",
    "sg:address":"Maximilianstr. 47",
    "sg:city":"Wunsiedel",
    "sg:phone":"+49 9232/2573",
    "sg:postcode":"95632",
    "sg:province":"Bayern",
    "wof:name":"Friedhelm Krau\u00df",
    "wof:placetype":"venue"
},
  "geometry": {"coordinates":[12.003472,50.038071],"type":"Point"}
}