{
  "type": "Feature",
  "properties": {
    "iso:country":"DE",
    "sg:address":"Hauptstr. 1",
    "sg:city":"Elze",
    "sg:phone":"+49 5068/2101",
    "sg:postcode":"31008",
    "sg:province":"Niedersachsen",
    "wof:name":"Hotel Deutsches Haus",
    "wof:placetype":"venue"
},
  "geometry": {"coordinates":[9.7356014252,52.1219177246],"type":"Point"}
}