{
  "type": "Feature",
  "properties": {
    "iso:country":"DE",
    "sg:address":"Siedlungsstr. 26",
    "sg:city":"Kaufbeuren",
    "sg:phone":"+49 8341/2732",
    "sg:postcode":"87600",
    "sg:province":"Bayern",
    "wof:name":"D. Und F. Drabke",
    "wof:placetype":"venue"
},
  "geometry": {"coordinates":[10.638718605,47.8754081726],"type":"Point"}
}