{
  "type": "Feature",
  "properties": {
    "iso:country":"DE",
    "sg:address":"Sch\u00f6nblickstr. 13",
    "sg:city":"Backnang",
    "sg:phone":"+49 7191/970621",
    "sg:postcode":"71522",
    "sg:province":"Baden-W\u00fcrttemberg",
    "wof:name":"Die Hand In Hand Werker Gmbh",
    "wof:placetype":"venue"
},
  "geometry": {"coordinates":[9.444041,48.943405],"type":"Point"}
}