{
  "type": "Feature",
  "properties": {
    "iso:country":"DE",
    "sg:address":"Pr\u00e4mienstr. 30",
    "sg:city":"Stolberg",
    "sg:phone":"+49 2402/24678",
    "sg:postcode":"52223",
    "sg:province":"Nordrhein-Westfalen",
    "wof:name":"Elf Oil Ag",
    "wof:placetype":"venue"
},
  "geometry": {"coordinates":[6.2173161507,50.7646903992],"type":"Point"}
}