{
  "type": "Feature",
  "properties": {
    "iso:country":"DE",
    "sg:address":"Schelmenwasenstrasse 37-39",
    "sg:city":"Stuttgart",
    "sg:phone":"+49 4921/1650410",
    "sg:postcode":"70567",
    "sg:province":"Baden-W\u00fcrttemberg",
    "wof:name":"Degussa Ag",
    "wof:placetype":"venue"
},
  "geometry": {"coordinates":[6.7702112198,51.2463340759],"type":"Point"}
}