{
  "type": "Feature",
  "properties": {
    "iso:country":"DE",
    "sg:address":"Am Roten Sand 2",
    "sg:city":"Kirchhain",
    "sg:phone":"+49 6427/2106",
    "sg:postcode":"35274",
    "sg:province":"Hessen",
    "wof:name":"Grunewald",
    "wof:placetype":"venue"
},
  "geometry": {"coordinates":[8.8399982452,50.8581542969],"type":"Point"}
}