{
  "type": "Feature",
  "properties": {
    "iso:country":"DE",
    "sg:address":"Ostlandweg 24",
    "sg:city":"Leichlingen",
    "sg:phone":"+49 2175/98204",
    "sg:postcode":"42799",
    "sg:province":"Nordrhein-Westfalen",
    "wof:name":"Al Dente",
    "wof:placetype":"venue"
},
  "geometry": {"coordinates":[7.0068411827,51.0982398987],"type":"Point"}
}