{
  "type": "Feature",
  "properties": {
    "iso:country":"DE",
    "sg:address":"Bahnhofstr. 24",
    "sg:city":"Prettin",
    "sg:phone":"+49 35386/22333",
    "sg:postcode":"06922",
    "sg:province":"Sachsen-Anhalt",
    "wof:name":"Schladitz Milwa Gmbh",
    "wof:placetype":"venue"
},
  "geometry": {"coordinates":[12.9211902618,51.6638565063],"type":"Point"}
}