{
  "type": "Feature",
  "properties": {
    "iso:country":"DE",
    "sg:address":"Jahnstr. 12",
    "sg:city":"Oberasbach",
    "sg:phone":"+49 911/695786",
    "sg:postcode":"90522",
    "sg:province":"Bayern",
    "wof:name":"Vereinsgastst\u00e4tte Turn- Und Sportverein 1964",
    "wof:placetype":"venue"
},
  "geometry": {"coordinates":[10.965546608,49.4199523926],"type":"Point"}
}