{
  "type": "Feature",
  "properties": {
    "iso:country":"DE",
    "sg:address":"Gartenstr 72",
    "sg:city":"Radebeul",
    "sg:phone":"+49 351/83979648",
    "sg:postcode":"01445",
    "sg:province":"Sachsen",
    "wof:name":"Lasertechnik Und Applikationen Gmbh",
    "wof:placetype":"venue"
},
  "geometry": {"coordinates":[13.6890354156,51.0937919617],"type":"Point"}
}