{
  "type": "Feature",
  "properties": {
    "iso:country":"DE",
    "sg:address":"Metzer Str. 20",
    "sg:city":"K\u00f6ln",
    "sg:phone":"+49 221/312336",
    "sg:postcode":"50677",
    "sg:province":"Nordrhein-Westfalen",
    "wof:name":"Metzer Eck",
    "wof:placetype":"venue"
},
  "geometry": {"coordinates":[6.9540319443,50.9209060669],"type":"Point"}
}