{
  "type": "Feature",
  "properties": {
    "iso:country":"DE",
    "sg:address":"Goethestr. 21",
    "sg:city":"Frankfurt",
    "sg:postcode":"60313",
    "sg:province":"Hessen",
    "wof:name":"Spss Effekten- Und Beteiligungs Ag",
    "wof:placetype":"venue"
},
  "geometry": {"coordinates":[8.674088,50.113895],"type":"Point"}
}