{
  "type": "Feature",
  "properties": {
    "iso:country":"DE",
    "sg:address":"Eisdorfer Str. 1",
    "sg:city":"Bennstedt",
    "sg:postcode":"06179",
    "sg:province":"Sachsen-Anhalt",
    "wof:name":"Metallbau Gmbh",
    "wof:placetype":"venue"
},
  "geometry": {"coordinates":[11.824942,51.480442],"type":"Point"}
}