{
  "type": "Feature",
  "properties": {
    "iso:country":"DE",
    "sg:address":"Lessingstr. 38",
    "sg:city":"Siegen",
    "sg:phone":"+49 271/331955",
    "sg:postcode":"57074",
    "sg:province":"Nordrhein-Westfalen",
    "wof:name":"Siegfried Krause Steuerberater",
    "wof:placetype":"venue"
},
  "geometry": {"coordinates":[8.0255460739,50.8610153198],"type":"Point"}
}