{
  "type": "Feature",
  "properties": {
    "iso:country":"DE",
    "sg:address":"Vogelbach",
    "sg:city":"Dachsberg",
    "sg:phone":"+49 7755/316",
    "sg:postcode":"79875",
    "sg:province":"Baden-W\u00fcrttemberg",
    "wof:name":"Emil Schlegel",
    "wof:placetype":"venue"
},
  "geometry": {"coordinates":[8.10083,47.728458],"type":"Point"}
}