{
  "type": "Feature",
  "properties": {
    "iso:country":"DE",
    "sg:address":"Osterfeldstr. 36",
    "sg:city":"Wetter",
    "sg:phone":"+49 2335/7847",
    "sg:postcode":"58300",
    "sg:province":"Nordrhein-Westfalen",
    "wof:name":"Rolf Raguse",
    "wof:placetype":"venue"
},
  "geometry": {"coordinates":[7.348925,51.398346],"type":"Point"}
}