{
  "type": "Feature",
  "properties": {
    "iso:country":"DE",
    "sg:address":"Wei\u00dfdornweg 2",
    "sg:city":"Hemmingen",
    "sg:phone":"+49 511/422916",
    "sg:postcode":"30966",
    "sg:province":"Niedersachsen",
    "wof:name":"L. F. Euling Eisenwaren",
    "wof:placetype":"venue"
},
  "geometry": {"coordinates":[9.7232522964,52.3235740662],"type":"Point"}
}