{
  "type": "Feature",
  "properties": {
    "iso:country":"DE",
    "sg:address":"August-Bebel-Str. 4",
    "sg:city":"Bad S\u00fclze",
    "sg:phone":"+49 38229/230",
    "sg:postcode":"18334",
    "sg:province":"Mecklenburg-Vorpommern",
    "wof:name":"Ulrich Sch\u00f6nborn",
    "wof:placetype":"venue"
},
  "geometry": {"coordinates":[12.657583,54.109344],"type":"Point"}
}