{
  "type": "Feature",
  "properties": {
    "iso:country":"DE",
    "sg:address":"Dr.-Martin-Luther-Str. 14",
    "sg:city":"Regensburg",
    "sg:phone":"+49 941/561796",
    "sg:postcode":"93047",
    "sg:province":"Bayern",
    "wof:name":"Pizzeria Antico Martini",
    "wof:placetype":"venue"
},
  "geometry": {"coordinates":[12.101565361,49.0151863098],"type":"Point"}
}