{
  "type": "Feature",
  "properties": {
    "iso:country":"DE",
    "sg:address":"Am Gr\u00fcnewald 33",
    "sg:city":"Velbert",
    "sg:phone":"+49 2051/65825",
    "sg:postcode":"42549",
    "sg:province":"Nordrhein-Westfalen",
    "wof:name":"Hans M\u00fcller",
    "wof:placetype":"venue"
},
  "geometry": {"coordinates":[7.0301151276,51.3257904053],"type":"Point"}
}