{
  "type": "Feature",
  "properties": {
    "iso:country":"DE",
    "sg:address":"Robert-Bosch-Str. 39",
    "sg:city":"Unterschlei\u00dfheim",
    "sg:phone":"+49 89/3109463",
    "sg:postcode":"85716",
    "sg:province":"Bayern",
    "wof:name":"Communich",
    "wof:placetype":"venue"
},
  "geometry": {"coordinates":[11.5696878433,48.2843704224],"type":"Point"}
}