{
  "type": "Feature",
  "properties": {
    "iso:country":"DE",
    "sg:address":"Herforder Str. 22",
    "sg:city":"L\u00f6hne",
    "sg:phone":"+49 5732/8682",
    "sg:postcode":"32584",
    "sg:province":"Nordrhein-Westfalen",
    "wof:name":"Harald Brockmann",
    "wof:placetype":"venue"
},
  "geometry": {"coordinates":[8.689415,52.186424],"type":"Point"}
}