{
  "type": "Feature",
  "properties": {
    "iso:country":"DE",
    "sg:address":"Corneliusstr. 195",
    "sg:city":"T\u00f6nisvorst",
    "sg:phone":"+49 2151/970895",
    "sg:postcode":"47918",
    "sg:province":"Nordrhein-Westfalen",
    "wof:name":"Sch\u00fcrgers-aldenkirchs Steuerberater",
    "wof:placetype":"venue"
},
  "geometry": {"coordinates":[6.4952020645,51.3138008118],"type":"Point"}
}