{
  "type": "Feature",
  "properties": {
    "iso:country":"DE",
    "sg:address":"Birnbachstrasse 2",
    "sg:city":"Frontenhausen",
    "sg:postcode":"84160",
    "sg:province":"Bayern",
    "wof:name":"Ortmaier-druck",
    "wof:placetype":"venue"
},
  "geometry": {"coordinates":[12.516763,48.540108],"type":"Point"}
}