{
  "type": "Feature",
  "properties": {
    "iso:country":"DE",
    "sg:address":"Sch\u00e4fersiedlung 3",
    "sg:city":"Elfershausen",
    "sg:phone":"+49 9704/7312",
    "sg:postcode":"97725",
    "sg:province":"Bayern",
    "wof:name":"Wald Gbr",
    "wof:placetype":"venue"
},
  "geometry": {"coordinates":[9.966898,50.144829],"type":"Point"}
}