{
  "type": "Feature",
  "properties": {
    "iso:country":"DE",
    "sg:address":"455 footwear designer street",
    "sg:city":"new-york",
    "sg:phone":"+49 4524/52",
    "sg:postcode":"42523",
    "wof:name":"Footwear Designer ::: Sportwear Design By \u00a9inox",
    "wof:placetype":"venue"
},
  "geometry": {"coordinates":[-74.007133,40.714531],"type":"Point"}
}