{
  "type": "Feature",
  "properties": {
    "iso:country":"DE",
    "sg:address":"Buchenstr. 66",
    "sg:city":"Selm",
    "sg:phone":"+49 2592/21115",
    "sg:postcode":"59379",
    "sg:province":"Nordrhein-Westfalen",
    "wof:name":"D. Jornitz",
    "wof:placetype":"venue"
},
  "geometry": {"coordinates":[7.4750862122,51.6916122437],"type":"Point"}
}