{
  "type": "Feature",
  "properties": {
    "iso:country":"DE",
    "sg:address":"Flie\u00dfhornstr. 10",
    "sg:city":"Konstanz",
    "sg:postcode":"78465",
    "sg:province":"Baden-W\u00fcrttemberg",
    "wof:name":"Ip5 Gmbh",
    "wof:placetype":"venue"
},
  "geometry": {"coordinates":[9.1585102081,47.7391204834],"type":"Point"}
}