{
  "type": "Feature",
  "properties": {
    "iso:country":"DE",
    "sg:address":"Schelmen\u00e4cker 8",
    "sg:city":"Fichtenberg",
    "sg:phone":"+49 7971/21703",
    "sg:postcode":"74427",
    "sg:province":"Baden-W\u00fcrttemberg",
    "wof:name":"Deininger Rohstoffe Gmbh",
    "wof:placetype":"venue"
},
  "geometry": {"coordinates":[9.7116060257,48.9909172058],"type":"Point"}
}