{
  "type": "Feature",
  "properties": {
    "iso:country":"DE",
    "sg:address":"Pastor-Eyme-Str. 14",
    "sg:city":"Bad Harzburg",
    "sg:phone":"+49 5322/52379",
    "sg:postcode":"38667",
    "sg:province":"Niedersachsen",
    "wof:name":"Manfred T\u00f6pfer",
    "wof:placetype":"venue"
},
  "geometry": {"coordinates":[10.5711917877,51.8819236755],"type":"Point"}
}