{
  "type": "Feature",
  "properties": {
    "iso:country":"DE",
    "sg:address":"Lanzstr. 4",
    "sg:city":"Bad Wurzach",
    "sg:phone":"+49 7564/3070",
    "sg:postcode":"88410",
    "sg:province":"Baden-W\u00fcrttemberg",
    "wof:name":"Lissmac Maschinenbau Und Diamantwerkzeuge Gmbh",
    "wof:placetype":"venue"
},
  "geometry": {"coordinates":[9.868543,47.900162],"type":"Point"}
}