{
  "type": "Feature",
  "properties": {
    "iso:country":"DE",
    "sg:address":"An der Luthereiche 7",
    "sg:city":"Rodgau",
    "sg:phone":"+49 6106/21318",
    "sg:postcode":"63110",
    "sg:province":"Hessen",
    "wof:name":"Karl Wolf",
    "wof:placetype":"venue"
},
  "geometry": {"coordinates":[8.8936672211,50.006439209],"type":"Point"}
}