{
  "type": "Feature",
  "properties": {
    "iso:country":"DE",
    "sg:address":"Bahnhofstr. 12",
    "sg:city":"Lautertal",
    "sg:phone":"+49 9561/607",
    "sg:postcode":"96486",
    "sg:province":"Bayern",
    "wof:name":"H. Zapf Antiquit\u00e4ten",
    "wof:placetype":"venue"
},
  "geometry": {"coordinates":[10.969863,50.336597],"type":"Point"}
}