{
  "type": "Feature",
  "properties": {
    "iso:country":"DE",
    "sg:address":"Westerholter Str. 33",
    "sg:city":"Gelsenkirchen",
    "sg:postcode":"45894",
    "sg:province":"Nordrhein-Westfalen",
    "wof:name":"Addian Beteiligungs- Und Beratungs Gmbh",
    "wof:placetype":"venue"
},
  "geometry": {"coordinates":[7.058049202,51.5810089111],"type":"Point"}
}