{
  "type": "Feature",
  "properties": {
    "iso:country":"DE",
    "sg:address":"Goethering 35",
    "sg:city":"Osnabr\u00fcck",
    "sg:phone":"+49 541/27396",
    "sg:postcode":"49074",
    "sg:province":"Niedersachsen",
    "wof:name":"Dreier & Horstmann Moden Gmbh",
    "wof:placetype":"venue"
},
  "geometry": {"coordinates":[8.056079,52.273479],"type":"Point"}
}