{
  "type": "Feature",
  "properties": {
    "iso:country":"DE",
    "sg:address":"Goethestr. 3",
    "sg:city":"Bad F\u00fcssing",
    "sg:phone":"+49 8531/21530",
    "sg:postcode":"94072",
    "sg:province":"Bayern",
    "wof:name":"Abruzzo",
    "wof:placetype":"venue"
},
  "geometry": {"coordinates":[13.3162260056,48.3516235352],"type":"Point"}
}