{
  "type": "Feature",
  "properties": {
    "iso:country":"DE",
    "sg:address":"W\u00fcrzburger Str. 3",
    "sg:city":"Karlstadt",
    "sg:phone":"+49 9353/990040",
    "sg:postcode":"97753",
    "sg:province":"Bayern",
    "wof:name":"Autovermietung Metzger",
    "wof:placetype":"venue"
},
  "geometry": {"coordinates":[9.77226,49.955727],"type":"Point"}
}