{
  "type": "Feature",
  "properties": {
    "iso:country":"DE",
    "sg:address":"Tulpenstr. 42",
    "sg:city":"Rottenburg",
    "sg:phone":"+49 7472/8001",
    "sg:postcode":"72108",
    "sg:province":"Baden-W\u00fcrttemberg",
    "wof:name":"A. Imhoff",
    "wof:placetype":"venue"
},
  "geometry": {"coordinates":[8.971528,48.473763],"type":"Point"}
}