{
  "type": "Feature",
  "properties": {
    "iso:country":"DE",
    "sg:address":"Kochenthal 8",
    "sg:city":"Hemau",
    "sg:phone":"+49 9491/2540",
    "sg:postcode":"93155",
    "sg:province":"Bayern",
    "wof:name":"Hess",
    "wof:placetype":"venue"
},
  "geometry": {"coordinates":[11.8552246094,49.0297279358],"type":"Point"}
}