{
  "type": "Feature",
  "properties": {
    "iso:country":"DE",
    "sg:address":"Am Weserdeich 27",
    "sg:city":"Brake",
    "sg:phone":"+49 4401/72058",
    "sg:postcode":"26919",
    "sg:province":"Niedersachsen",
    "wof:name":"J\u00fcrgen Ehlers",
    "wof:placetype":"venue"
},
  "geometry": {"coordinates":[8.4865751266,53.3077545166],"type":"Point"}
}