{
  "type": "Feature",
  "properties": {
    "iso:country":"DE",
    "sg:address":"Kantstr. 64",
    "sg:city":"Berlin",
    "sg:phone":"+49 30/3232443",
    "sg:postcode":"10627",
    "sg:province":"Berlin",
    "wof:name":"Pms Professional Musik Shop Gmbh",
    "wof:placetype":"venue"
},
  "geometry": {"coordinates":[13.3037796021,52.5069618225],"type":"Point"}
}