{
  "type": "Feature",
  "properties": {
    "iso:country":"DE",
    "sg:address":"Waschgrabenstr. 3",
    "sg:city":"Neustadt",
    "sg:phone":"+49 4561/9065",
    "sg:postcode":"23730",
    "sg:province":"Schleswig-Holstein",
    "wof:name":"Landesbausparkasse Beratungsstelle",
    "wof:placetype":"venue"
},
  "geometry": {"coordinates":[10.885068,54.134293],"type":"Point"}
}