{
  "type": "Feature",
  "properties": {
    "iso:country":"DE",
    "sg:address":"Uellendahler Str. 178",
    "sg:city":"Wuppertal",
    "sg:phone":"+49 202/751008",
    "sg:postcode":"42109",
    "sg:province":"Nordrhein-Westfalen",
    "wof:name":"Bv Bautechnik Vertriebs Gmbh",
    "wof:placetype":"venue"
},
  "geometry": {"coordinates":[7.15009,51.273632],"type":"Point"}
}