{
  "type": "Feature",
  "properties": {
    "iso:country":"DE",
    "sg:address":"Kalkseestr. 71",
    "sg:city":"Woltersdorf",
    "sg:postcode":"15569",
    "sg:province":"Brandenburg",
    "wof:name":"Dr. Med. Hildegard Steuer",
    "wof:placetype":"venue"
},
  "geometry": {"coordinates":[13.764094,52.452824],"type":"Point"}
}