{
  "type": "Feature",
  "properties": {
    "iso:country":"DE",
    "sg:address":"Edmund-J\u00f6rg-Str. 34",
    "sg:city":"Landshut",
    "sg:phone":"+49 871/25616",
    "sg:postcode":"84036",
    "sg:province":"Bayern",
    "wof:name":"Hundhammer Ohg",
    "wof:placetype":"venue"
},
  "geometry": {"coordinates":[12.159997,48.528988],"type":"Point"}
}