{
  "type": "Feature",
  "properties": {
    "iso:country":"DE",
    "sg:address":"Wagenberger Str. 1",
    "sg:city":"Hohenbrunn",
    "sg:phone":"+49 8102/895190",
    "sg:postcode":"85662",
    "sg:province":"Bayern",
    "wof:name":"Aerasec Network Services And Security Gmbh",
    "wof:placetype":"venue"
},
  "geometry": {"coordinates":[11.705269,48.048977],"type":"Point"}
}