{
  "type": "Feature",
  "properties": {
    "iso:country":"DE",
    "sg:address":"Stockau 9",
    "sg:city":"Weidenberg",
    "sg:phone":"+49 9209/841",
    "sg:postcode":"95466",
    "sg:province":"Bayern",
    "wof:name":"Christian Raab",
    "wof:placetype":"venue"
},
  "geometry": {"coordinates":[11.674703,49.919003],"type":"Point"}
}