{
  "type": "Feature",
  "properties": {
    "iso:country":"DE",
    "sg:address":"Gartenstr. 7",
    "sg:city":"Bessenbach",
    "sg:phone":"+49 6095/3546",
    "sg:postcode":"63856",
    "sg:province":"Bayern",
    "wof:name":"Waldemar Neuburger Ingenieur",
    "wof:placetype":"venue"
},
  "geometry": {"coordinates":[9.2387056351,49.9586296082],"type":"Point"}
}