{
  "type": "Feature",
  "properties": {
    "iso:country":"DE",
    "sg:address":"Bismarckstr. 19-21",
    "sg:city":"K\u00f6ln",
    "sg:phone":"+49 221/515084",
    "sg:postcode":"50672",
    "sg:province":"Nordrhein-Westfalen",
    "wof:name":"Hertz Gmbh",
    "wof:placetype":"venue"
},
  "geometry": {"coordinates":[6.937569,50.94194],"type":"Point"}
}