{
  "type": "Feature",
  "properties": {
    "iso:country":"DE",
    "sg:address":"Forstfeldstr. 8",
    "sg:city":"Kassel",
    "sg:phone":"+49 561/512973",
    "sg:postcode":"34123",
    "sg:province":"Hessen",
    "wof:name":"Goldener Engel",
    "wof:placetype":"venue"
},
  "geometry": {"coordinates":[9.5372962952,51.2970352173],"type":"Point"}
}