{
  "type": "Feature",
  "properties": {
    "iso:country":"DE",
    "sg:address":"Alsterdorfer Str. 303",
    "sg:city":"Hamburg",
    "sg:postcode":"22297",
    "sg:province":"Hamburg",
    "wof:name":"Kanghe Handels Gmbh",
    "wof:placetype":"venue"
},
  "geometry": {"coordinates":[10.0108985901,53.6093864441],"type":"Point"}
}