{
  "type": "Feature",
  "properties": {
    "iso:country":"DE",
    "sg:address":"Marienstr. 34",
    "sg:city":"Eschweiler",
    "sg:phone":"+49 2403/22447",
    "sg:postcode":"52249",
    "sg:province":"Nordrhein-Westfalen",
    "wof:name":"Josef Bardenheuer",
    "wof:placetype":"venue"
},
  "geometry": {"coordinates":[6.2639260292,50.8175811768],"type":"Point"}
}