{
  "type": "Feature",
  "properties": {
    "iso:country":"DE",
    "sg:address":"Wilhelm-Zangen-Str. 2",
    "sg:city":"Hausach",
    "sg:phone":"+49 7831/227",
    "sg:postcode":"77756",
    "sg:province":"Baden-W\u00fcrttemberg",
    "wof:name":"W. B\u00e4chle Gmbh Spedition",
    "wof:placetype":"venue"
},
  "geometry": {"coordinates":[8.1889839172,48.2830429077],"type":"Point"}
}