{
  "type": "Feature",
  "properties": {
    "iso:country":"DE",
    "sg:address":"Hinter dem Anger 2",
    "sg:city":"Remscheid",
    "sg:phone":"+49 2191/344738",
    "sg:postcode":"42855",
    "sg:province":"Nordrhein-Westfalen",
    "wof:name":"Hessler Gmbh",
    "wof:placetype":"venue"
},
  "geometry": {"coordinates":[7.22713,51.182899],"type":"Point"}
}