{
  "type": "Feature",
  "properties": {
    "iso:country":"DE",
    "sg:address":"L\u00fcneburger Str. 36",
    "sg:city":"Wendisch Evern",
    "sg:phone":"+49 4131/935656",
    "sg:postcode":"21403",
    "sg:province":"Niedersachsen",
    "wof:name":"Wilhelm Krahn-zembol Rechtsanwalt",
    "wof:placetype":"venue"
},
  "geometry": {"coordinates":[10.4670448303,53.2183227539],"type":"Point"}
}