{
  "type": "Feature",
  "properties": {
    "iso:country":"DE",
    "sg:address":"Valentinskamp 88",
    "sg:city":"Hamburg",
    "sg:postcode":"20355",
    "sg:province":"Hamburg",
    "wof:name":"Beatrice Achtzigste Verm\u00f6gensverwaltungs- Gmbh",
    "wof:placetype":"venue"
},
  "geometry": {"coordinates":[9.9818296432,53.5555992126],"type":"Point"}
}