{
  "type": "Feature",
  "properties": {
    "iso:country":"DE",
    "sg:address":"Ringstr. 6",
    "sg:city":"Pirmasens",
    "sg:phone":"+49 6331/64012",
    "sg:postcode":"66953",
    "sg:province":"Rheinland-Pfalz",
    "wof:name":"Mayer Fuchs Und Gampfer Rechtsanw\u00e4lte",
    "wof:placetype":"venue"
},
  "geometry": {"coordinates":[7.6040229797,49.2043914795],"type":"Point"}
}