{
  "type": "Feature",
  "properties": {
    "iso:country":"DE",
    "sg:address":"Alt Griesheim 86",
    "sg:city":"Frankfurt",
    "sg:phone":"+49 69/393866",
    "sg:postcode":"65933",
    "sg:province":"Hessen",
    "wof:name":"Eks Elektro- Und K\u00e4lteger\u00e4te Import Gmbh",
    "wof:placetype":"venue"
},
  "geometry": {"coordinates":[8.6013689041,50.09116745],"type":"Point"}
}