{
  "type": "Feature",
  "properties": {
    "iso:country":"DE",
    "sg:address":"M\u00fchleberg 13",
    "sg:city":"G\u00f6rwihl",
    "sg:phone":"+49 7754/1212",
    "sg:postcode":"79733",
    "sg:province":"Baden-W\u00fcrttemberg",
    "wof:name":"F. Und M. Huber",
    "wof:placetype":"venue"
},
  "geometry": {"coordinates":[8.0750312805,47.6417617798],"type":"Point"}
}