{
  "type": "Feature",
  "properties": {
    "iso:country":"DE",
    "sg:address":"Kirchstr. 19",
    "sg:city":"Kirrweiler",
    "sg:phone":"+49 6321/59876",
    "sg:postcode":"67489",
    "sg:province":"Rheinland-Pfalz",
    "wof:name":"Alfons Minges",
    "wof:placetype":"venue"
},
  "geometry": {"coordinates":[8.1647405624,49.3004722595],"type":"Point"}
}