{
  "type": "Feature",
  "properties": {
    "iso:country":"DE",
    "sg:address":"Stresemannstr. 32",
    "sg:city":"D\u00fcsseldorf",
    "sg:phone":"+49 211/3613334",
    "sg:postcode":"40210",
    "sg:province":"Nordrhein-Westfalen",
    "wof:name":"Cafe De Paris",
    "wof:placetype":"venue"
},
  "geometry": {"coordinates":[6.7856907845,51.2204170227],"type":"Point"}
}