{
  "type": "Feature",
  "properties": {
    "iso:country":"DE",
    "sg:address":"Philosophenweg 26",
    "sg:city":"Wetzlar",
    "sg:phone":"+49 6441/4121",
    "sg:postcode":"35578",
    "sg:province":"Hessen",
    "wof:name":"Staatsanwaltschaft Bei Dem Landgericht Limburg",
    "wof:placetype":"venue"
},
  "geometry": {"coordinates":[8.5096740723,50.5560531616],"type":"Point"}
}