{
  "type": "Feature",
  "properties": {
    "iso:country":"DE",
    "sg:address":"T\u00fcbinger Str. 83 a",
    "sg:city":"Stuttgart",
    "sg:phone":"+49 711/960486",
    "sg:postcode":"70178",
    "sg:province":"Baden-W\u00fcrttemberg",
    "wof:name":"F. Sener",
    "wof:placetype":"venue"
},
  "geometry": {"coordinates":[9.170246,48.766941],"type":"Point"}
}