{
  "type": "Feature",
  "properties": {
    "iso:country":"DE",
    "sg:address":"R\u00f6merstr. 85",
    "sg:city":"K\u00f6ln",
    "sg:phone":"+49 221/9355970",
    "sg:postcode":"50996",
    "sg:province":"Nordrhein-Westfalen",
    "wof:name":"W. Verweyen Rechtsanwalt",
    "wof:placetype":"venue"
},
  "geometry": {"coordinates":[6.9916491508,50.8835601807],"type":"Point"}
}