{
  "type": "Feature",
  "properties": {
    "iso:country":"DE",
    "sg:address":"Reichsstr. 12",
    "sg:city":"Berlin",
    "sg:phone":"+49 30/3009290",
    "sg:postcode":"14052",
    "sg:province":"Berlin",
    "wof:name":"J\u00fcrgen Pufahl Rechtsanwalt",
    "wof:placetype":"venue"
},
  "geometry": {"coordinates":[13.2668857574,52.5130462646],"type":"Point"}
}