{
  "type": "Feature",
  "properties": {
    "iso:country":"DE",
    "sg:address":"Dorfstr. 28",
    "sg:city":"Behren-L\u00fcbchin",
    "sg:phone":"+49 39971/13413",
    "sg:postcode":"17179",
    "sg:province":"Mecklenburg-Vorpommern",
    "wof:name":"M. Richter",
    "wof:placetype":"venue"
},
  "geometry": {"coordinates":[12.6616239548,54.0261955261],"type":"Point"}
}