{
  "type": "Feature",
  "properties": {
    "iso:country":"DE",
    "sg:address":"Rotlintstr. 64",
    "sg:city":"Frankfurt",
    "sg:phone":"+49 69/437074",
    "sg:postcode":"60316",
    "sg:province":"Hessen",
    "wof:name":"P. Bergerhoff",
    "wof:placetype":"venue"
},
  "geometry": {"coordinates":[8.694465,50.127045],"type":"Point"}
}