{
  "type": "Feature",
  "properties": {
    "iso:country":"DE",
    "sg:address":"B\u00fcrgermeisterwiese 14",
    "sg:city":"Herborn",
    "sg:phone":"+49 2772/92800",
    "sg:postcode":"35745",
    "sg:province":"Hessen",
    "wof:name":"Dr. Hudel & Partner",
    "wof:placetype":"venue"
},
  "geometry": {"coordinates":[8.3031396866,50.6880187988],"type":"Point"}
}