{
  "type": "Feature",
  "properties": {
    "iso:country":"DE",
    "sg:address":"Am L\u00f6bner 1",
    "sg:city":"Lehre",
    "sg:phone":"+49 5308/6597",
    "sg:postcode":"38165",
    "sg:province":"Niedersachsen",
    "wof:name":"Johann Breyvogel",
    "wof:placetype":"venue"
},
  "geometry": {"coordinates":[10.674575,52.326462],"type":"Point"}
}