{
  "type": "Feature",
  "properties": {
    "iso:country":"DE",
    "sg:address":"Dorfstr. 25",
    "sg:city":"Lohe-F\u00f6hrden",
    "sg:phone":"+49 4335/1369",
    "sg:postcode":"24806",
    "sg:province":"Schleswig-Holstein",
    "wof:name":"Rolf Brandmann Logistik Und Vertrieb Gmbh",
    "wof:placetype":"venue"
},
  "geometry": {"coordinates":[9.4884634018,54.3349113464],"type":"Point"}
}