{
  "type": "Feature",
  "properties": {
    "iso:country":"DE",
    "sg:address":"Krummdiek 8",
    "sg:city":"Barnstorf",
    "sg:phone":"+49 5442/565",
    "sg:postcode":"49406",
    "sg:province":"Niedersachsen",
    "wof:name":"Erich Meyer",
    "wof:placetype":"venue"
},
  "geometry": {"coordinates":[8.500465,52.724815],"type":"Point"}
}