{
  "type": "Feature",
  "properties": {
    "iso:country":"DE",
    "sg:address":"Braunhalde 1",
    "sg:city":"Dornhan",
    "sg:phone":"+49 7455/1208",
    "sg:postcode":"72175",
    "sg:province":"Baden-W\u00fcrttemberg",
    "wof:name":"Grand Filou",
    "wof:placetype":"venue"
},
  "geometry": {"coordinates":[8.5158061981,48.3535690308],"type":"Point"}
}