{
  "type": "Feature",
  "properties": {
    "iso:country":"DE",
    "sg:address":"Gutermannstr. 11",
    "sg:city":"Horb",
    "sg:phone":"+49 7451/537620",
    "sg:postcode":"72160",
    "sg:province":"Baden-W\u00fcrttemberg",
    "wof:name":"Alten- Und Pflegeheim Ita Von Toppenburg",
    "wof:placetype":"venue"
},
  "geometry": {"coordinates":[8.691784,48.445602],"type":"Point"}
}