{
  "type": "Feature",
  "properties": {
    "iso:country":"DE",
    "sg:address":"Nordseestr. 2",
    "sg:city":"Norden",
    "sg:phone":"+49 4931/928040",
    "sg:postcode":"26506",
    "sg:province":"Niedersachsen",
    "wof:name":"Planbau Nord Gmbh",
    "wof:placetype":"venue"
},
  "geometry": {"coordinates":[7.190429,53.602978],"type":"Point"}
}