{
  "type": "Feature",
  "properties": {
    "iso:country":"DE",
    "sg:address":"Bahnhofstr. 16",
    "sg:city":"Nalbach",
    "sg:phone":"+49 6838/3440",
    "sg:postcode":"66809",
    "sg:province":"Saarland",
    "wof:name":"Reichert",
    "wof:placetype":"venue"
},
  "geometry": {"coordinates":[6.8355789185,49.3904914856],"type":"Point"}
}