{
  "type": "Feature",
  "properties": {
    "iso:country":"DE",
    "sg:address":"Dortmunder Str. 54",
    "sg:city":"Witten",
    "sg:phone":"+49 2302/1770",
    "sg:postcode":"58455",
    "sg:province":"Nordrhein-Westfalen",
    "wof:name":"Lunke Projektges. Mbh",
    "wof:placetype":"venue"
},
  "geometry": {"coordinates":[7.35327,51.442551],"type":"Point"}
}