{
  "type": "Feature",
  "properties": {
    "iso:country":"DE",
    "sg:address":"Havelstr. 9",
    "sg:city":"Darmstadt",
    "sg:postcode":"64295",
    "sg:province":"Hessen",
    "wof:name":"Bonnier Informatik Gmbh",
    "wof:placetype":"venue"
},
  "geometry": {"coordinates":[8.6370487213,49.8693313599],"type":"Point"}
}