{
  "type": "Feature",
  "properties": {
    "iso:country":"DE",
    "sg:address":"Herbststr. 18",
    "sg:city":"Wackersdorf",
    "sg:phone":"+49 9431/51589",
    "sg:postcode":"92442",
    "sg:province":"Bayern",
    "wof:name":"Johann Wein",
    "wof:placetype":"venue"
},
  "geometry": {"coordinates":[12.182964,49.31638],"type":"Point"}
}