{
  "type": "Feature",
  "properties": {
    "iso:country":"DE",
    "sg:address":"Wilhelmstr. 43",
    "sg:city":"Altenkirchen",
    "sg:phone":"+49 2681/4016",
    "sg:postcode":"57610",
    "sg:province":"Rheinland-Pfalz",
    "wof:name":"Neue Apotheke",
    "wof:placetype":"venue"
},
  "geometry": {"coordinates":[7.643478,50.686203],"type":"Point"}
}