{
  "type": "Feature",
  "properties": {
    "iso:country":"DE",
    "sg:address":"Riedstr. 2",
    "sg:city":"Neuburg",
    "sg:phone":"+49 8283/2634",
    "sg:postcode":"86476",
    "sg:province":"Bayern",
    "wof:name":"H. Weindl",
    "wof:placetype":"venue"
},
  "geometry": {"coordinates":[10.3743267059,48.3155174255],"type":"Point"}
}