{
  "type": "Feature",
  "properties": {
    "iso:country":"DE",
    "sg:address":"Gewerbegebiet",
    "sg:city":"Mehren",
    "sg:phone":"+49 4965/924028",
    "sg:postcode":"54552",
    "sg:province":"Rheinland-Pfalz",
    "wof:name":"Paul Fleschen Gmbh",
    "wof:placetype":"venue"
},
  "geometry": {"coordinates":[6.886655,50.167542],"type":"Point"}
}