{
  "type": "Feature",
  "properties": {
    "iso:country":"DE",
    "sg:address":"Der Sch\u00f6ne Weg 84",
    "sg:city":"Reutlingen",
    "sg:postcode":"72766",
    "sg:province":"Baden-W\u00fcrttemberg",
    "wof:name":"Andreas Kurtz Gmbh",
    "wof:placetype":"venue"
},
  "geometry": {"coordinates":[9.2322120667,48.4929542542],"type":"Point"}
}