{
  "type": "Feature",
  "properties": {
    "iso:country":"DE",
    "sg:address":"Knesing 25",
    "sg:city":"Chieming",
    "sg:phone":"+49 8669/2765",
    "sg:postcode":"83339",
    "sg:province":"Bayern",
    "wof:name":"Anner Kg",
    "wof:placetype":"venue"
},
  "geometry": {"coordinates":[12.549284935,47.9423904419],"type":"Point"}
}