{
  "type": "Feature",
  "properties": {
    "iso:country":"DE",
    "sg:address":"Im Gewerbepark C 25",
    "sg:city":"Regensburg",
    "sg:postcode":"93059",
    "sg:province":"Bayern",
    "wof:name":"Etosha Consult",
    "wof:placetype":"venue"
},
  "geometry": {"coordinates":[12.1257867813,49.0299301147],"type":"Point"}
}