{
  "type": "Feature",
  "properties": {
    "iso:country":"DE",
    "sg:address":"Beim Tivoli 2",
    "sg:city":"Jever",
    "sg:phone":"+49 4461/984688",
    "sg:postcode":"26441",
    "sg:province":"Niedersachsen",
    "wof:name":"\u00d6ko-solar-jever Ein Geschenk Des Himmels!",
    "wof:placetype":"venue"
},
  "geometry": {"coordinates":[7.9121508598,53.5662994385],"type":"Point"}
}