{
  "type": "Feature",
  "properties": {
    "iso:country":"DE",
    "sg:address":"Im Kr\u00f6tenteich 2",
    "sg:city":"Buchen",
    "sg:phone":"+49 6281/4070",
    "sg:postcode":"74722",
    "sg:province":"Baden-W\u00fcrttemberg",
    "wof:name":"Ges. Zur Fabrikat. Fototech. Erzeugnisse Mbh",
    "wof:placetype":"venue"
},
  "geometry": {"coordinates":[9.3367776871,49.5247764587],"type":"Point"}
}