{
  "type": "Feature",
  "properties": {
    "iso:country":"DE",
    "sg:address":"Heidenkampsweg 100",
    "sg:city":"Hamburg",
    "sg:phone":"+49 40/236060",
    "sg:postcode":"20097",
    "sg:province":"Hamburg",
    "wof:name":"Kravag Allgemeine Versicherungs Ag",
    "wof:placetype":"venue"
},
  "geometry": {"coordinates":[10.0307540894,53.54454422],"type":"Point"}
}