{
  "type": "Feature",
  "properties": {
    "iso:country":"DE",
    "sg:address":"Sch\u00fctzenhausweg 1",
    "sg:city":"Penig",
    "sg:phone":"+49 37381/80856",
    "sg:postcode":"09322",
    "sg:province":"Sachsen",
    "wof:name":"Le Coiffeur Gmbh",
    "wof:placetype":"venue"
},
  "geometry": {"coordinates":[12.703546,50.932877],"type":"Point"}
}