{
  "type": "Feature",
  "properties": {
    "iso:country":"DE",
    "sg:address":"Lohseplatz 3",
    "sg:city":"Hamburg",
    "sg:postcode":"20457",
    "sg:province":"Hamburg",
    "wof:name":"Htv Hamburger-teppich Veredelung E. K.",
    "wof:placetype":"venue"
},
  "geometry": {"coordinates":[10.0037670135,53.5431938171],"type":"Point"}
}