{
  "type": "Feature",
  "properties": {
    "iso:country":"DE",
    "sg:address":"Merkenstr 35",
    "sg:city":"Hamburg",
    "sg:phone":"+49 40/7128001",
    "sg:postcode":"22117",
    "sg:province":"Hamburg",
    "wof:name":"John Bahr",
    "wof:placetype":"venue"
},
  "geometry": {"coordinates":[10.127423,53.542957],"type":"Point"}
}