{
  "type": "Feature",
  "properties": {
    "iso:country":"DE",
    "sg:address":"Osningstr. 7",
    "sg:city":"G\u00fctersloh",
    "sg:phone":"+49 4952/414105",
    "sg:postcode":"33332",
    "sg:province":"Nordrhein-Westfalen",
    "wof:name":"Epkenhans + Brockhaus Gmbh",
    "wof:placetype":"venue"
},
  "geometry": {"coordinates":[8.393049,51.879513],"type":"Point"}
}