{
  "type": "Feature",
  "properties": {
    "iso:country":"DE",
    "sg:address":"Wotanstr. 8",
    "sg:city":"M\u00fcnchen",
    "sg:phone":"+49 89/17960",
    "sg:postcode":"80639",
    "sg:province":"Bayern",
    "wof:name":"Mh Bausparkasse Ag",
    "wof:placetype":"venue"
},
  "geometry": {"coordinates":[11.503025,48.144459],"type":"Point"}
}