{
  "type": "Feature",
  "properties": {
    "iso:country":"DE",
    "sg:address":"Schwimmbadstr.",
    "sg:city":"Singhofen",
    "sg:phone":"+49 2604/6635",
    "sg:postcode":"56379",
    "sg:province":"Rheinland-Pfalz",
    "wof:name":"Schwimmbad",
    "wof:placetype":"venue"
},
  "geometry": {"coordinates":[7.8339219093,50.2739143372],"type":"Point"}
}