{
  "type": "Feature",
  "properties": {
    "iso:country":"DE",
    "sg:address":"H\u00e4rterichstr. 12",
    "sg:city":"Bad Mergentheim",
    "sg:phone":"+49 7931/7483",
    "sg:postcode":"97980",
    "sg:province":"Baden-W\u00fcrttemberg",
    "wof:name":"G\u00e4stehaus Alois M\u00fcller",
    "wof:placetype":"venue"
},
  "geometry": {"coordinates":[9.7739667892,49.4929046631],"type":"Point"}
}