{
  "type": "Feature",
  "properties": {
    "iso:country":"DE",
    "sg:address":"Weilimdorfer Str. 6",
    "sg:city":"Korntal-M\u00fcnchingen",
    "sg:phone":"+49 711/833083",
    "sg:postcode":"70825",
    "sg:province":"Baden-W\u00fcrttemberg",
    "wof:name":"Selbin",
    "wof:placetype":"venue"
},
  "geometry": {"coordinates":[9.1219158173,48.8281021118],"type":"Point"}
}