{
  "type": "Feature",
  "properties": {
    "iso:country":"DE",
    "sg:address":"Uferpromenade 11",
    "sg:city":"Meersburg",
    "sg:phone":"+49 7532/80040",
    "sg:postcode":"88709",
    "sg:province":"Baden-W\u00fcrttemberg",
    "wof:name":"Hotel Residenz Am See",
    "wof:placetype":"venue"
},
  "geometry": {"coordinates":[9.2773580551,47.690952301],"type":"Point"}
}