{
  "type": "Feature",
  "properties": {
    "iso:country":"DE",
    "sg:address":"K\u00f6lner Landstr. 225 a",
    "sg:city":"D\u00fcsseldorf",
    "sg:phone":"+49 211/975060",
    "sg:postcode":"40591",
    "sg:province":"Nordrhein-Westfalen",
    "wof:name":"Comfundo Bodenbelags Gmbh",
    "wof:placetype":"venue"
},
  "geometry": {"coordinates":[6.8194279671,51.1859550476],"type":"Point"}
}