{
  "type": "Feature",
  "properties": {
    "iso:country":"DE",
    "sg:address":"Ludwigstr. 45",
    "sg:city":"Selb",
    "sg:phone":"+49 9287/2393",
    "sg:postcode":"95100",
    "sg:province":"Bayern",
    "wof:name":"Arthur Sandner",
    "wof:placetype":"venue"
},
  "geometry": {"coordinates":[12.1327857971,50.1710968018],"type":"Point"}
}