{
  "type": "Feature",
  "properties": {
    "iso:country":"DE",
    "sg:address":"Am End 7b",
    "sg:city":"M\u00f6nchengladbach",
    "sg:phone":"+49 2166/958470",
    "sg:postcode":"41189",
    "sg:province":"Nordrhein-Westfalen",
    "wof:name":"Hans-walter Schraub",
    "wof:placetype":"venue"
},
  "geometry": {"coordinates":[6.3816,51.106731],"type":"Point"}
}