{
  "type": "Feature",
  "properties": {
    "iso:country":"DE",
    "sg:address":"Wiesenstr. 15",
    "sg:city":"Riegelsberg",
    "sg:phone":"+49 6806/3176",
    "sg:postcode":"66292",
    "sg:province":"Saarland",
    "wof:name":"Karl H. Richardt",
    "wof:placetype":"venue"
},
  "geometry": {"coordinates":[6.9342,49.302731],"type":"Point"}
}