{
  "type": "Feature",
  "properties": {
    "iso:country":"DE",
    "sg:address":"L\u00e4mmchesbergstr. 20",
    "sg:city":"Kaiserslautern",
    "sg:phone":"+49 631/16689",
    "sg:postcode":"67663",
    "sg:province":"Rheinland-Pfalz",
    "wof:name":"K. D. Frank",
    "wof:placetype":"venue"
},
  "geometry": {"coordinates":[7.762569,49.432518],"type":"Point"}
}