{
  "type": "Feature",
  "properties": {
    "iso:country":"DE",
    "sg:address":"Rondorfer Hauptstr. 64",
    "sg:city":"K\u00f6ln",
    "sg:phone":"+49 2233/23814",
    "sg:postcode":"50997",
    "sg:province":"Nordrhein-Westfalen",
    "wof:name":"Hans W. Buchm\u00fcller",
    "wof:placetype":"venue"
},
  "geometry": {"coordinates":[6.95431,50.871059],"type":"Point"}
}