{
  "type": "Feature",
  "properties": {
    "iso:country":"DE",
    "sg:address":"Schillerstr. 1",
    "sg:city":"Stuttgart",
    "sg:phone":"+49 711/297298",
    "sg:postcode":"70173",
    "sg:province":"Baden-W\u00fcrttemberg",
    "wof:name":"Alte M\u00fcnze",
    "wof:placetype":"venue"
},
  "geometry": {"coordinates":[9.1780290604,48.7770271301],"type":"Point"}
}