{
  "type": "Feature",
  "properties": {
    "iso:country":"DE",
    "sg:address":"Marktplatz 4",
    "sg:city":"Altom\u00fcnster",
    "sg:phone":"+49 8254/9999",
    "sg:postcode":"85250",
    "sg:province":"Bayern",
    "wof:name":"Raiffeisenbank Eg",
    "wof:placetype":"venue"
},
  "geometry": {"coordinates":[11.256329,48.387413],"type":"Point"}
}