{
  "type": "Feature",
  "properties": {
    "iso:country":"DE",
    "sg:address":"Freisinger Landstr. 28",
    "sg:city":"M\u00fcnchen",
    "sg:phone":"+49 89/3228387",
    "sg:postcode":"80939",
    "sg:province":"Bayern",
    "wof:name":"Moderne Bauelemente Detlef Knechtel Gmbh & Co.",
    "wof:placetype":"venue"
},
  "geometry": {"coordinates":[11.620912,48.191429],"type":"Point"}
}