{
  "type": "Feature",
  "properties": {
    "iso:country":"DE",
    "sg:address":"Selfkantstr. 112",
    "sg:city":"Selfkant",
    "sg:phone":"+49 2455/2665",
    "sg:postcode":"52538",
    "sg:province":"Nordrhein-Westfalen",
    "wof:name":"Wilfried Jansen",
    "wof:placetype":"venue"
},
  "geometry": {"coordinates":[5.94912,51.03009],"type":"Point"}
}