{
  "type": "Feature",
  "properties": {
    "iso:country":"DE",
    "sg:address":"Loher Str. 37",
    "sg:city":"Hamburg",
    "sg:phone":"+49 40/6731295",
    "sg:postcode":"22149",
    "sg:province":"Hamburg",
    "wof:name":"V. Frankenberg Gmbh",
    "wof:placetype":"venue"
},
  "geometry": {"coordinates":[10.1407289505,53.5947685242],"type":"Point"}
}