{
  "type": "Feature",
  "properties": {
    "iso:country":"DE",
    "sg:address":"Allg\u00e4uer Str. 116",
    "sg:city":"M\u00fcnchen",
    "sg:phone":"+49 89/7593518",
    "sg:postcode":"81475",
    "sg:province":"Bayern",
    "wof:name":"Evang. Sozialdienst E. V.",
    "wof:placetype":"venue"
},
  "geometry": {"coordinates":[11.485679,48.079262],"type":"Point"}
}