{
  "type": "Feature",
  "properties": {
    "iso:country":"DE",
    "sg:address":"H\u00f6llweg 3",
    "sg:city":"Ehingen",
    "sg:phone":"+49 7391/53412",
    "sg:postcode":"89584",
    "sg:province":"Baden-W\u00fcrttemberg",
    "wof:name":"Franz Schlecker",
    "wof:placetype":"venue"
},
  "geometry": {"coordinates":[9.724219,48.263008],"type":"Point"}
}