{
  "type": "Feature",
  "properties": {
    "iso:country":"DE",
    "sg:address":"Am Torhaus 1",
    "sg:city":"M\u00fcllheim",
    "sg:phone":"+49 7631/172640",
    "sg:postcode":"79379",
    "sg:province":"Baden-W\u00fcrttemberg",
    "wof:name":"R\u00fcckgrat Sport- Und Gesundheitscenter Gmbh",
    "wof:placetype":"venue"
},
  "geometry": {"coordinates":[7.610811,47.812565],"type":"Point"}
}