{
  "type": "Feature",
  "properties": {
    "iso:country":"DE",
    "sg:address":"Emanuel-Sulger-Str. 23",
    "sg:city":"Riedlingen",
    "sg:phone":"+49 7371/4121",
    "sg:postcode":"88499",
    "sg:province":"Baden-W\u00fcrttemberg",
    "wof:name":"Baronie Verkaufsb\u00fcro",
    "wof:placetype":"venue"
},
  "geometry": {"coordinates":[9.4763050079,48.1246871948],"type":"Point"}
}