{
  "type": "Feature",
  "properties": {
    "iso:country":"DE",
    "sg:address":"Roonstr. 45",
    "sg:city":"Mainz-Kastel",
    "sg:phone":"+49 6134/63363",
    "sg:postcode":"55252",
    "sg:province":"Hessen",
    "wof:name":"Erlebnisgastronomie Merlin",
    "wof:placetype":"venue"
},
  "geometry": {"coordinates":[8.2837400436,50.0120582581],"type":"Point"}
}