{
  "type": "Feature",
  "properties": {
    "iso:country":"DE",
    "sg:address":"Stra\u00dfe der MTS 16",
    "sg:city":"Wasserleben",
    "sg:phone":"+49 39451/4504",
    "sg:postcode":"38871",
    "sg:province":"Sachsen-Anhalt",
    "wof:name":"Horst Riehn",
    "wof:placetype":"venue"
},
  "geometry": {"coordinates":[10.7514352798,51.9268722534],"type":"Point"}
}