{
  "type": "Feature",
  "properties": {
    "iso:country":"DE",
    "sg:address":"Bernrieder Str. 13",
    "sg:city":"Tutzing",
    "sg:postcode":"82327",
    "sg:province":"Bayern",
    "wof:name":"Aldi Gmbh & Co. Kg",
    "wof:placetype":"venue"
},
  "geometry": {"coordinates":[11.2653198242,47.8924407959],"type":"Point"}
}