{
  "type": "Feature",
  "properties": {
    "iso:country":"DE",
    "sg:address":"Esslinger Str. 40",
    "sg:city":"Stuttgart",
    "sg:phone":"+49 711/237350",
    "sg:postcode":"70182",
    "sg:province":"Baden-W\u00fcrttemberg",
    "wof:name":"B\u00fcro Marketing Service",
    "wof:placetype":"venue"
},
  "geometry": {"coordinates":[9.182735,48.774891],"type":"Point"}
}