{
  "type": "Feature",
  "properties": {
    "iso:country":"DE",
    "sg:address":"Sonnborner Str. 91",
    "sg:city":"Wuppertal",
    "sg:phone":"+49 202/740264",
    "sg:postcode":"42327",
    "sg:province":"Nordrhein-Westfalen",
    "wof:name":"Fassbinder",
    "wof:placetype":"venue"
},
  "geometry": {"coordinates":[7.096405,51.238033],"type":"Point"}
}