{
  "type": "Feature",
  "properties": {
    "iso:country":"DE",
    "sg:address":"M\u00fchlweg 13",
    "sg:city":"Glees",
    "sg:phone":"+49 2636/4832",
    "sg:postcode":"56653",
    "sg:province":"Rheinland-Pfalz",
    "wof:name":"Lothar Frings",
    "wof:placetype":"venue"
},
  "geometry": {"coordinates":[7.244093,50.433655],"type":"Point"}
}