{
  "type": "Feature",
  "properties": {
    "iso:country":"DE",
    "sg:address":"Max-Graef-Gasse 10::",
    "sg:city":"Jena",
    "sg:phone":"+49 4936/4146980",
    "sg:postcode":"07743",
    "sg:province":"Th\u00fcringen",
    "wof:name":"Geso - Ges.f. Sensorik, Geotechn. Umweltschutz U. Mathemat. Modellierung Gmbh",
    "wof:placetype":"venue"
},
  "geometry": {"coordinates":[11.616251,50.958187],"type":"Point"}
}