{
  "type": "Feature",
  "properties": {
    "iso:country":"DE",
    "sg:address":"Graf-Egge-Str. 40",
    "sg:city":"Detern",
    "sg:phone":"+49 4957/1763",
    "sg:postcode":"26847",
    "sg:province":"Niedersachsen",
    "wof:name":"Wolfgang Kowalski",
    "wof:placetype":"venue"
},
  "geometry": {"coordinates":[7.680574894,53.2157363892],"type":"Point"}
}