{
  "type": "Feature",
  "properties": {
    "iso:country":"DE",
    "sg:address":"Dreiecksplatz 12",
    "sg:city":"Kiel",
    "sg:phone":"+49 431/554032",
    "sg:postcode":"24103",
    "sg:province":"Schleswig-Holstein",
    "wof:name":"Behrmanns Probierstube",
    "wof:placetype":"venue"
},
  "geometry": {"coordinates":[10.1342611313,54.328338623],"type":"Point"}
}