{
  "type": "Feature",
  "properties": {
    "iso:country":"DE",
    "sg:address":"Alexanderstra\u00dfe 59",
    "sg:city":"Frankfurt/Main",
    "sg:phone":"+49 69",
    "sg:postcode":"60489",
    "sg:province":"Hessen",
    "wof:name":"Hochtief Fertigteilbau Gmbh",
    "wof:placetype":"venue"
},
  "geometry": {"coordinates":[8.6126394272,50.1275558472],"type":"Point"}
}