{
  "type": "Feature",
  "properties": {
    "iso:country":"DE",
    "sg:address":"August-Bebel-Str. 52",
    "sg:city":"Blankenfelde",
    "sg:postcode":"15827",
    "sg:province":"Brandenburg",
    "wof:name":"Wohnungsbaugenossenschaft Aufbau Eg",
    "wof:placetype":"venue"
},
  "geometry": {"coordinates":[13.4008674622,52.3366622925],"type":"Point"}
}