{
  "type": "Feature",
  "properties": {
    "iso:country":"DE",
    "sg:address":"Breite Str. 9",
    "sg:city":"Freital",
    "sg:phone":"+49 351/651130",
    "sg:postcode":"01705",
    "sg:province":"Sachsen",
    "wof:name":"Gwg - Gewerbe- Und Wohnpark Gartenstra\u00dfe Gmbh & Co. Kg",
    "wof:placetype":"venue"
},
  "geometry": {"coordinates":[13.67562,51.01363],"type":"Point"}
}