{
  "type": "Feature",
  "properties": {
    "iso:country":"DE",
    "sg:address":"23936",
    "sg:city":"Wismar",
    "sg:phone":"+49 3475/6730",
    "sg:postcode":"23936",
    "sg:province":"Mecklenburg-Vorpommern",
    "wof:name":"Volks-und Raiffeisenbank Eisleben Eg",
    "wof:placetype":"venue"
},
  "geometry": {"coordinates":[11.56801,51.51318],"type":"Point"}
}