{
  "type": "Feature",
  "properties": {
    "iso:country":"DE",
    "sg:address":"Karlstr. 19",
    "sg:city":"Lampertheim",
    "sg:phone":"+49 6206/57362",
    "sg:postcode":"68623",
    "sg:province":"Hessen",
    "wof:name":"Georg Maurer Fleischerei",
    "wof:placetype":"venue"
},
  "geometry": {"coordinates":[8.4754199982,49.5985794067],"type":"Point"}
}