{
  "type": "Feature",
  "properties": {
    "iso:country":"DE",
    "sg:address":"Udenh\u00e4user Str. 13",
    "sg:city":"Grebenstein",
    "sg:phone":"+49 5674/4910",
    "sg:postcode":"34393",
    "sg:province":"Hessen",
    "wof:name":"Detlef Schmidt",
    "wof:placetype":"venue"
},
  "geometry": {"coordinates":[9.417514801,51.4451446533],"type":"Point"}
}