{
  "type": "Feature",
  "properties": {
    "iso:country":"DE",
    "sg:address":"Tom-Rinck-Str. 9",
    "sg:city":"Oelde",
    "sg:phone":"+49 2522/2410",
    "sg:postcode":"59302",
    "sg:province":"Nordrhein-Westfalen",
    "wof:name":"Hanold Gmbh",
    "wof:placetype":"venue"
},
  "geometry": {"coordinates":[8.1514492035,51.8321685791],"type":"Point"}
}