{
  "type": "Feature",
  "properties": {
    "iso:country":"DE",
    "sg:address":"Rathausstra\u00dfe 2",
    "sg:city":"Sehnde",
    "sg:phone":"+49 5132/93728",
    "sg:postcode":"31319",
    "sg:province":"Niedersachsen",
    "wof:name":"Dipl.-ing. Herbert Trauernicht, Geb\u00e4udemesstechnik",
    "wof:placetype":"venue"
},
  "geometry": {"coordinates":[9.9376058578,52.3462181091],"type":"Point"}
}