{
  "type": "Feature",
  "properties": {
    "iso:country":"DE",
    "sg:address":"Avenida de las naciones",
    "sg:city":"Ciudad Quesada",
    "sg:postcode":"03170",
    "wof:name":"Willkommen In Ciudad Quesada",
    "wof:placetype":"venue"
},
  "geometry": {"coordinates":[-0.706206,38.065266],"type":"Point"}
}