{
  "type": "Feature",
  "properties": {
    "iso:country":"DE",
    "sg:address":"Johanniterstr. 40",
    "sg:city":"Borken",
    "sg:phone":"+49 2861/61960",
    "sg:postcode":"46325",
    "sg:province":"Nordrhein-Westfalen",
    "wof:name":"Johanni-apotheke",
    "wof:placetype":"venue"
},
  "geometry": {"coordinates":[6.859965,51.842823],"type":"Point"}
}