{
  "type": "Feature",
  "properties": {
    "iso:country":"DE",
    "sg:address":"L\u00f6wenstr. 69",
    "sg:city":"Hamburg",
    "sg:phone":"+49 40/485888",
    "sg:postcode":"20251",
    "sg:province":"Hamburg",
    "wof:name":"Kai Schaefer Gmbh",
    "wof:placetype":"venue"
},
  "geometry": {"coordinates":[9.974566,53.585785],"type":"Point"}
}