{
  "type": "Feature",
  "properties": {
    "iso:country":"DE",
    "sg:address":"Ikarusall. 28",
    "sg:city":"Hannover",
    "sg:phone":"+49 4951/1968450",
    "sg:postcode":"30179",
    "sg:province":"Niedersachsen",
    "wof:name":"Tauber Gmbh Bauunternehmung",
    "wof:placetype":"venue"
},
  "geometry": {"coordinates":[9.749555,52.419914],"type":"Point"}
}