{
  "type": "Feature",
  "properties": {
    "iso:country":"DE",
    "sg:address":"K\u00f6ppelsfeld 5",
    "sg:city":"Burbach",
    "sg:phone":"+49 2736/6881",
    "sg:postcode":"57299",
    "sg:province":"Nordrhein-Westfalen",
    "wof:name":"Hans Pinkall Heilpraktiker",
    "wof:placetype":"venue"
},
  "geometry": {"coordinates":[8.0691289902,50.7515068054],"type":"Point"}
}