{
  "type": "Feature",
  "properties": {
    "iso:country":"DE",
    "sg:address":"Erfurter Str. 16",
    "sg:city":"Gotha",
    "sg:phone":"+49 3621/854752",
    "sg:postcode":"99867",
    "sg:province":"Th\u00fcringen",
    "wof:name":"Marianne Haase",
    "wof:placetype":"venue"
},
  "geometry": {"coordinates":[10.7072696686,50.9501533508],"type":"Point"}
}