{
  "type": "Feature",
  "properties": {
    "iso:country":"DE",
    "sg:address":"Licher Str. 38",
    "sg:city":"W\u00f6lfersheim",
    "sg:phone":"+49 6036/3334",
    "sg:postcode":"61200",
    "sg:province":"Hessen",
    "wof:name":"Hubertus-apotheke",
    "wof:placetype":"venue"
},
  "geometry": {"coordinates":[8.816821,50.399441],"type":"Point"}
}