{
  "type": "Feature",
  "properties": {
    "iso:country":"DE",
    "sg:address":"Lindenschmitstr. 27",
    "sg:city":"M\u00fcnchen",
    "sg:phone":"+49 89/766525",
    "sg:postcode":"81371",
    "sg:province":"Bayern",
    "wof:name":"Andreas Huy Btx-agentur",
    "wof:placetype":"venue"
},
  "geometry": {"coordinates":[11.5425720215,48.1182518005],"type":"Point"}
}