{
  "type": "Feature",
  "properties": {
    "iso:country":"DE",
    "sg:address":"Kunigundenweg 1",
    "sg:city":"Staffelstein",
    "sg:phone":"+49 9573/3009",
    "sg:postcode":"96231",
    "sg:province":"Bayern",
    "wof:name":"Pension Meyer",
    "wof:placetype":"venue"
},
  "geometry": {"coordinates":[10.9893712997,50.1042060852],"type":"Point"}
}