{
  "type": "Feature",
  "properties": {
    "iso:country":"DE",
    "sg:address":"Wilhelmstr. 52",
    "sg:city":"Wiesbaden",
    "sg:phone":"+49 611/304300",
    "sg:postcode":"65183",
    "sg:province":"Hessen",
    "wof:name":"Dr. Schrobsdorff Und Dr. Herrmann",
    "wof:placetype":"venue"
},
  "geometry": {"coordinates":[8.2443828583,50.0841255188],"type":"Point"}
}