{
  "type": "Feature",
  "properties": {
    "iso:country":"DE",
    "sg:address":"Clara-Zetkin-Str. 32",
    "sg:city":"Merseburg",
    "sg:postcode":"06217",
    "sg:province":"Sachsen-Anhalt",
    "wof:name":"Luv Lager- Und Verwertungsges. Mbh",
    "wof:placetype":"venue"
},
  "geometry": {"coordinates":[11.960182,51.323906],"type":"Point"}
}