{
  "type": "Feature",
  "properties": {
    "iso:country":"DE",
    "sg:address":"Otto-Volger-Str. 1",
    "sg:city":"Sulzbach",
    "sg:phone":"+49 6196/58490",
    "sg:postcode":"65843",
    "sg:province":"Hessen",
    "wof:name":"Info Ag",
    "wof:placetype":"venue"
},
  "geometry": {"coordinates":[8.5188989639,50.1297302246],"type":"Point"}
}