{
  "type": "Feature",
  "properties": {
    "iso:country":"DE",
    "sg:address":"Hans-B\u00f6ckler-Str. 86",
    "sg:city":"Sonthofen",
    "sg:phone":"+49 8321/619583",
    "sg:postcode":"87527",
    "sg:province":"Bayern",
    "wof:name":"Fly In",
    "wof:placetype":"venue"
},
  "geometry": {"coordinates":[10.2684364319,47.5244598389],"type":"Point"}
}