{
  "type": "Feature",
  "properties": {
    "iso:country":"DE",
    "sg:address":"Sandbergweg 28",
    "sg:city":"Flensburg",
    "sg:phone":"+49 461/63790",
    "sg:postcode":"24943",
    "sg:province":"Schleswig-Holstein",
    "wof:name":"Amphi Trek Radreisen Gmbh",
    "wof:placetype":"venue"
},
  "geometry": {"coordinates":[9.4744529724,54.7840805054],"type":"Point"}
}