{
  "type": "Feature",
  "properties": {
    "iso:country":"DE",
    "sg:address":"Siebertstr. 1",
    "sg:city":"M\u00fcnchen",
    "sg:phone":"+49 89/9973940",
    "sg:postcode":"81675",
    "sg:province":"Bayern",
    "wof:name":"J\u00f6rg Burmeister Rechtsanwalt",
    "wof:placetype":"venue"
},
  "geometry": {"coordinates":[11.5988645554,48.1439361572],"type":"Point"}
}