{
  "type": "Feature",
  "properties": {
    "iso:country":"DE",
    "sg:address":"Am Wiesenbusch 2",
    "sg:city":"Gladbeck",
    "sg:postcode":"45966",
    "sg:province":"Nordrhein-Westfalen",
    "wof:name":"Powder Light Metals Gmbh",
    "wof:placetype":"venue"
},
  "geometry": {"coordinates":[6.93867,51.571613],"type":"Point"}
}