{
  "type": "Feature",
  "properties": {
    "iso:country":"DE",
    "sg:address":"Schirnewitz 6",
    "sg:city":"Altenberga",
    "sg:phone":"+49 36424/24217",
    "sg:postcode":"07768",
    "sg:province":"Th\u00fcringen",
    "wof:name":"R. Kr\u00e4mer",
    "wof:placetype":"venue"
},
  "geometry": {"coordinates":[11.5544300079,50.8446655273],"type":"Point"}
}