{
  "type": "Feature",
  "properties": {
    "iso:country":"DE",
    "sg:address":"Lindenbrink 6",
    "sg:city":"Dohnsen",
    "sg:phone":"+49 5533/3145",
    "sg:postcode":"37620",
    "sg:province":"Niedersachsen",
    "wof:name":"Robert Grupe",
    "wof:placetype":"venue"
},
  "geometry": {"coordinates":[9.57525,52.006821],"type":"Point"}
}