{
  "type": "Feature",
  "properties": {
    "iso:country":"DE",
    "sg:address":"Bunsenstr. 25",
    "sg:city":"Ingolstadt",
    "sg:phone":"+49 841/940525",
    "sg:postcode":"85053",
    "sg:province":"Bayern",
    "wof:name":"Bauka Natursteine Gmbh",
    "wof:placetype":"venue"
},
  "geometry": {"coordinates":[11.4746265411,48.7359542847],"type":"Point"}
}