{
  "type": "Feature",
  "properties": {
    "iso:country":"DE",
    "sg:address":"Kemptener Str. 69",
    "sg:city":"M\u00fcnchen",
    "sg:phone":"+49 89/6140854",
    "sg:postcode":"81475",
    "sg:province":"Bayern",
    "wof:name":"Mmr Management Und Marketing Research",
    "wof:placetype":"venue"
},
  "geometry": {"coordinates":[11.4840841293,48.0790290833],"type":"Point"}
}