{
  "type": "Feature",
  "properties": {
    "iso:country":"DE",
    "sg:address":"Hermannsgarten 29",
    "sg:city":"Lich",
    "sg:phone":"+49 6404/90403",
    "sg:postcode":"35423",
    "sg:province":"Hessen",
    "wof:name":"Becker Mess-steuer- Regeltechnik Gmbh",
    "wof:placetype":"venue"
},
  "geometry": {"coordinates":[8.9004812241,50.5419921875],"type":"Point"}
}