{
  "type": "Feature",
  "properties": {
    "iso:country":"DE",
    "sg:address":"Ringstr. 1",
    "sg:city":"Schnabelwaid",
    "sg:phone":"+49 9270/614",
    "sg:postcode":"91289",
    "sg:province":"Bayern",
    "wof:name":"Werner Sch\u00e4dlich Rundstrickerei Gmbh",
    "wof:placetype":"venue"
},
  "geometry": {"coordinates":[11.5832386017,49.8137283325],"type":"Point"}
}