{
  "type": "Feature",
  "properties": {
    "iso:country":"DE",
    "sg:address":"Braunsdorfer Str. 53",
    "sg:city":"Dresden",
    "sg:phone":"+49 351/4113104",
    "sg:postcode":"01159",
    "sg:province":"Sachsen",
    "wof:name":"Ralf Kerber",
    "wof:placetype":"venue"
},
  "geometry": {"coordinates":[13.6877822876,51.0468406677],"type":"Point"}
}