{
  "type": "Feature",
  "properties": {
    "iso:country":"DE",
    "sg:address":"Weinreihe 14",
    "sg:city":"Bad Sooden-Allendorf",
    "sg:phone":"+49 5652/3371",
    "sg:postcode":"37242",
    "sg:province":"Hessen",
    "wof:name":"Kurparkklause",
    "wof:placetype":"venue"
},
  "geometry": {"coordinates":[9.9632825851,51.2691268921],"type":"Point"}
}