{
  "type": "Feature",
  "properties": {
    "iso:country":"DE",
    "sg:address":"R\u00f6merstr. 3",
    "sg:city":"Leiwen",
    "sg:phone":"+49 6507/3133",
    "sg:postcode":"54340",
    "sg:province":"Rheinland-Pfalz",
    "wof:name":"Peter-josef Scholtes",
    "wof:placetype":"venue"
},
  "geometry": {"coordinates":[6.8816537857,49.8216743469],"type":"Point"}
}