{
  "type": "Feature",
  "properties": {
    "iso:country":"DE",
    "sg:address":"Schrannenplatz 1",
    "sg:city":"Schwabm\u00fcnchen",
    "sg:phone":"+49 8232/903821",
    "sg:postcode":"86830",
    "sg:province":"Bayern",
    "wof:name":"Gasthaus Zum Mohren",
    "wof:placetype":"venue"
},
  "geometry": {"coordinates":[10.7578287125,48.1781921387],"type":"Point"}
}