{
  "type": "Feature",
  "properties": {
    "iso:country":"DE",
    "sg:address":"Adlerstr. 19",
    "sg:city":"Waiblingen",
    "sg:phone":"+49 7151/920444",
    "sg:postcode":"71336",
    "sg:province":"Baden-W\u00fcrttemberg",
    "wof:name":"Gabriela Sperber Steuerberaterin",
    "wof:placetype":"venue"
},
  "geometry": {"coordinates":[9.3233423233,48.8553237915],"type":"Point"}
}