{
  "type": "Feature",
  "properties": {
    "iso:country":"DE",
    "sg:address":"Gladbacher Str. 10",
    "sg:city":"Bergisch Gladbach",
    "sg:phone":"+49 2204/52763",
    "sg:postcode":"51429",
    "sg:province":"Nordrhein-Westfalen",
    "wof:name":"Leanaerts Und Obermann Rechtsanw\u00e4lte",
    "wof:placetype":"venue"
},
  "geometry": {"coordinates":[7.1541590691,50.9666748047],"type":"Point"}
}