{
  "type": "Feature",
  "properties": {
    "iso:country":"DE",
    "sg:address":"Obere Sterkrader Str. 171",
    "sg:city":"Duisburg",
    "sg:postcode":"47167",
    "sg:province":"Nordrhein-Westfalen",
    "wof:name":"Multigast Gmbh",
    "wof:placetype":"venue"
},
  "geometry": {"coordinates":[6.817684,51.506008],"type":"Point"}
}