{
  "type": "Feature",
  "properties": {
    "iso:country":"DE",
    "sg:address":"Homertstr. 10",
    "sg:city":"Hagen",
    "sg:phone":"+49 2337/91850",
    "sg:postcode":"58091",
    "sg:province":"Nordrhein-Westfalen",
    "wof:name":"Ruhrberg Ingenieurgemeinschaft Gehrke Neumann Schmitz",
    "wof:placetype":"venue"
},
  "geometry": {"coordinates":[7.5362358093,51.3028564453],"type":"Point"}
}