{
  "type": "Feature",
  "properties": {
    "iso:country":"DE",
    "sg:address":"Lohbarbeker Weg 16a",
    "sg:city":"Hohenlockstedt",
    "sg:phone":"+49 4826/1751",
    "sg:postcode":"25551",
    "sg:province":"Schleswig-Holstein",
    "wof:name":"Ruthild B\u00f6ckmann-blank Krankengymnastin",
    "wof:placetype":"venue"
},
  "geometry": {"coordinates":[9.624826,53.963951],"type":"Point"}
}