{
  "type": "Feature",
  "properties": {
    "iso:country":"DE",
    "sg:address":"Conertplatz 15",
    "sg:city":"Dresden",
    "sg:phone":"+49 351/4213102",
    "sg:postcode":"01159",
    "sg:province":"Sachsen",
    "wof:name":"Bernd R\u00e4disch",
    "wof:placetype":"venue"
},
  "geometry": {"coordinates":[13.6918077469,51.04637146],"type":"Point"}
}