{
  "type": "Feature",
  "properties": {
    "iso:country":"DE",
    "sg:address":"Grobenweg 6 a",
    "sg:city":"Wegberg",
    "sg:phone":"+49 2434/5107",
    "sg:postcode":"41844",
    "sg:province":"Nordrhein-Westfalen",
    "wof:name":"Wilms",
    "wof:placetype":"venue"
},
  "geometry": {"coordinates":[6.285857,51.122307],"type":"Point"}
}