{
  "type": "Feature",
  "properties": {
    "iso:country":"DE",
    "sg:address":"Rabenhof 19 a",
    "sg:city":"Bielefeld",
    "sg:phone":"+49 521/332656",
    "sg:postcode":"33609",
    "sg:province":"Nordrhein-Westfalen",
    "wof:name":"Erhard Thamm",
    "wof:placetype":"venue"
},
  "geometry": {"coordinates":[8.597158,52.042576],"type":"Point"}
}