{
  "type": "Feature",
  "properties": {
    "iso:country":"DE",
    "sg:address":"Erbacher Str. 119",
    "sg:city":"Darmstadt",
    "sg:phone":"+49 6151/424438",
    "sg:postcode":"64287",
    "sg:province":"Hessen",
    "wof:name":"A. Karakoc",
    "wof:placetype":"venue"
},
  "geometry": {"coordinates":[8.68109,49.873077],"type":"Point"}
}