{
  "type": "Feature",
  "properties": {
    "iso:country":"DE",
    "sg:address":"Oraniendamm 66",
    "sg:city":"Berlin",
    "sg:phone":"+49 30/4020340",
    "sg:postcode":"13469",
    "sg:province":"Berlin",
    "wof:name":"Steuerberaterb\u00fcro Volker Schwandt",
    "wof:placetype":"venue"
},
  "geometry": {"coordinates":[13.3241767883,52.6072616577],"type":"Point"}
}