{
  "type": "Feature",
  "properties": {
    "iso:country":"DE",
    "sg:address":"Mozartstr. 20",
    "sg:city":"Stockelsdorf",
    "sg:phone":"+49 451/492898",
    "sg:postcode":"23617",
    "sg:province":"Schleswig-Holstein",
    "wof:name":"J\u00fcrgen Sauerland Architekt",
    "wof:placetype":"venue"
},
  "geometry": {"coordinates":[10.654423,53.891537],"type":"Point"}
}