{
  "type": "Feature",
  "properties": {
    "iso:country":"DE",
    "sg:address":"Hopfengarten 11",
    "sg:city":"Braunschweig",
    "sg:postcode":"38102",
    "sg:province":"Niedersachsen",
    "wof:name":"Heiko Sievers Gmbh",
    "wof:placetype":"venue"
},
  "geometry": {"coordinates":[10.547151,52.262146],"type":"Point"}
}