{
  "type": "Feature",
  "properties": {
    "iso:country":"DE",
    "sg:address":"Moselstr. 16",
    "sg:city":"Langsur",
    "sg:phone":"+49 6501/12920",
    "sg:postcode":"54308",
    "sg:province":"Rheinland-Pfalz",
    "wof:name":"Helmut Rosner Heilpraktiker",
    "wof:placetype":"venue"
},
  "geometry": {"coordinates":[6.5252118111,49.7147407532],"type":"Point"}
}