{
  "type": "Feature",
  "properties": {
    "iso:country":"DE",
    "sg:address":"Geschwister-Scholl-Str. 7",
    "sg:city":"Wallenhorst",
    "sg:phone":"+49 5407/4723",
    "sg:postcode":"49134",
    "sg:province":"Niedersachsen",
    "wof:name":"Karl-heinz Rethmann Architekt Und Ingenieur",
    "wof:placetype":"venue"
},
  "geometry": {"coordinates":[8.0164642334,52.3500823975],"type":"Point"}
}