{
  "type": "Feature",
  "properties": {
    "iso:country":"DE",
    "sg:address":"Mariahilfstr. 17",
    "sg:city":"Aachen",
    "sg:phone":"+49 241/31271",
    "sg:postcode":"52062",
    "sg:province":"Nordrhein-Westfalen",
    "wof:name":"Dr. Karl-heinz K\u00f6ppinger Rechtsanwalt",
    "wof:placetype":"venue"
},
  "geometry": {"coordinates":[6.0911450386,50.7791824341],"type":"Point"}
}