{
  "type": "Feature",
  "properties": {
    "iso:country":"DE",
    "sg:address":"Zum Oberntor 19",
    "sg:city":"Springe",
    "sg:phone":"+49 5041/2765",
    "sg:postcode":"31832",
    "sg:province":"Niedersachsen",
    "wof:name":"Eiscafe Lito",
    "wof:placetype":"venue"
},
  "geometry": {"coordinates":[9.551835,52.208157],"type":"Point"}
}