{
  "type": "Feature",
  "properties": {
    "iso:country":"DE",
    "sg:address":"Andresenstr. 1a",
    "sg:city":"Wolfen",
    "sg:postcode":"06766",
    "sg:province":"Sachsen-Anhalt",
    "wof:name":"Trovotech Gmbh",
    "wof:placetype":"venue"
},
  "geometry": {"coordinates":[12.2533950806,51.6589813232],"type":"Point"}
}