{
  "type": "Feature",
  "properties": {
    "iso:country":"DE",
    "sg:address":"Hauptstr 5",
    "sg:city":"Kaltental",
    "sg:phone":"+49 8345/741",
    "sg:postcode":"87662",
    "sg:province":"Bayern",
    "wof:name":"Meweka Mechanische Werkst\u00e4tte Kaltental Gmbh",
    "wof:placetype":"venue"
},
  "geometry": {"coordinates":[10.75129,47.890862],"type":"Point"}
}