{
  "type": "Feature",
  "properties": {
    "iso:country":"DE",
    "sg:address":"Waldstr. 84",
    "sg:city":"Andernach",
    "sg:phone":"+49 2632/949346",
    "sg:postcode":"56626",
    "sg:province":"Rheinland-Pfalz",
    "wof:name":"Reiner Meurer",
    "wof:placetype":"venue"
},
  "geometry": {"coordinates":[7.3654270172,50.4506645203],"type":"Point"}
}