{
  "type": "Feature",
  "properties": {
    "iso:country":"DE",
    "sg:address":"Gravensteinstr. 22 c",
    "sg:city":"L\u00fcbeck",
    "sg:phone":"+49 451/46820",
    "sg:postcode":"23556",
    "sg:province":"Schleswig-Holstein",
    "wof:name":"Ferdinand Gude Innenarchitekt",
    "wof:placetype":"venue"
},
  "geometry": {"coordinates":[10.655711,53.874077],"type":"Point"}
}