{
  "type": "Feature",
  "properties": {
    "iso:country":"DE",
    "sg:address":"Wolzenstr. 18",
    "sg:city":"Rathenow",
    "sg:phone":"+49 3385/500840",
    "sg:postcode":"14712",
    "sg:province":"Brandenburg",
    "wof:name":"H.-g. Langangki",
    "wof:placetype":"venue"
},
  "geometry": {"coordinates":[12.3361034393,52.5973434448],"type":"Point"}
}