{
  "type": "Feature",
  "properties": {
    "iso:country":"DE",
    "sg:address":"H\u00fcnenweg 15",
    "sg:city":"Detmold",
    "sg:phone":"+49 5231/870821",
    "sg:postcode":"32760",
    "sg:province":"Nordrhein-Westfalen",
    "wof:name":"Eikel Und Kollegen Patentanw\u00e4lte",
    "wof:placetype":"venue"
},
  "geometry": {"coordinates":[8.8510198593,51.9195861816],"type":"Point"}
}