{
  "type": "Feature",
  "properties": {
    "iso:country":"DE",
    "sg:address":"Hofring 23",
    "sg:city":"Drechow",
    "sg:phone":"+49 38320/80464",
    "sg:postcode":"18465",
    "sg:province":"Mecklenburg-Vorpommern",
    "wof:name":"K. Salge",
    "wof:placetype":"venue"
},
  "geometry": {"coordinates":[12.792864,54.161751],"type":"Point"}
}