{
  "type": "Feature",
  "properties": {
    "iso:country":"DE",
    "sg:address":"Sch\u00f6nbuchstr. 12",
    "sg:city":"Stuttgart",
    "sg:phone":"+49 711/749339",
    "sg:postcode":"70565",
    "sg:province":"Baden-W\u00fcrttemberg",
    "wof:name":"Seiler",
    "wof:placetype":"venue"
},
  "geometry": {"coordinates":[9.1063089371,48.7114906311],"type":"Point"}
}