{
  "type": "Feature",
  "properties": {
    "iso:country":"DE",
    "sg:address":"Weilstr. 229",
    "sg:city":"Esslingen",
    "sg:postcode":"73733",
    "sg:province":"Baden-W\u00fcrttemberg",
    "wof:name":"Continent",
    "wof:placetype":"venue"
},
  "geometry": {"coordinates":[9.2686605453,48.7423782349],"type":"Point"}
}