{
  "type": "Feature",
  "properties": {
    "iso:country":"DE",
    "sg:address":"Roeckstra\u00dfe 54",
    "sg:city":"L\u00fcbeck",
    "sg:phone":"+49 180 5 052549280",
    "sg:postcode":"23568",
    "sg:province":"Schleswig-Holstein",
    "wof:name":"L\u00fcbecker-yacht-club: Jugend",
    "wof:placetype":"venue"
},
  "geometry": {"coordinates":[10.7065248489,53.8746414185],"type":"Point"}
}