{
  "type": "Feature",
  "properties": {
    "iso:country":"DE",
    "sg:address":"Fritz-Nagel-Siedlung 99 a",
    "sg:city":"Jatznick",
    "sg:phone":"+49 39741/80022",
    "sg:postcode":"17309",
    "sg:province":"Mecklenburg-Vorpommern",
    "wof:name":"Jatznicker Hof",
    "wof:placetype":"venue"
},
  "geometry": {"coordinates":[13.9432096481,53.5878791809],"type":"Point"}
}