{
  "type": "Feature",
  "properties": {
    "iso:country":"DE",
    "sg:address":"Marktplatz 4",
    "sg:city":"Mering",
    "sg:phone":"+49 8233/4976",
    "sg:postcode":"86415",
    "sg:province":"Bayern",
    "wof:name":"I. Weber & M. Leiminger",
    "wof:placetype":"venue"
},
  "geometry": {"coordinates":[10.986905,48.267525],"type":"Point"}
}