{
  "type": "Feature",
  "properties": {
    "iso:country":"DE",
    "sg:address":"Schulstra\u00dfe 7",
    "sg:city":"Filderstadt",
    "sg:phone":"+49 711/7359177",
    "sg:postcode":"70794",
    "sg:province":"Baden-W\u00fcrttemberg",
    "wof:name":"Internet & More",
    "wof:placetype":"venue"
},
  "geometry": {"coordinates":[9.1987085342,48.6540336609],"type":"Point"}
}