{
  "type": "Feature",
  "properties": {
    "iso:country":"DE",
    "sg:address":"Lindengasse 1",
    "sg:city":"Grimma",
    "sg:postcode":"04668",
    "sg:province":"Sachsen",
    "wof:name":"Bretschneider & Sohn",
    "wof:placetype":"venue"
},
  "geometry": {"coordinates":[12.798592,51.208496],"type":"Point"}
}