{
  "type": "Feature",
  "properties": {
    "iso:country":"DE",
    "sg:address":"Baumhauser Weg 41",
    "sg:city":"Bremen",
    "sg:phone":"+49 421/833777",
    "sg:postcode":"28279",
    "sg:province":"Bremen",
    "wof:name":"Rosemarie A. L\u00f6scher",
    "wof:placetype":"venue"
},
  "geometry": {"coordinates":[8.857119,53.042912],"type":"Point"}
}