{
  "type": "Feature",
  "properties": {
    "iso:country":"DE",
    "sg:address":"Ahauser Str. 22",
    "sg:city":"Legden",
    "sg:phone":"+49 2566/872",
    "sg:postcode":"48739",
    "sg:province":"Nordrhein-Westfalen",
    "wof:name":"Averkamp Gmbh & Co. Kg",
    "wof:placetype":"venue"
},
  "geometry": {"coordinates":[7.0973300934,52.0311203003],"type":"Point"}
}