{
  "type": "Feature",
  "properties": {
    "iso:country":"DE",
    "sg:address":"Wolfersdorf Hauptstr. 12",
    "sg:city":"Berga",
    "sg:phone":"+49 36623/20211",
    "sg:postcode":"07980",
    "sg:province":"Th\u00fcringen",
    "wof:name":"I. Vetterlein",
    "wof:placetype":"venue"
},
  "geometry": {"coordinates":[12.14415,50.734711],"type":"Point"}
}