{
  "type": "Feature",
  "properties": {
    "iso:country":"DE",
    "sg:address":"Accumer Riege 94",
    "sg:city":"Dornum",
    "sg:phone":"+49 4933/1561",
    "sg:postcode":"26553",
    "sg:province":"Niedersachsen",
    "wof:name":"Hotel Schienfatt",
    "wof:placetype":"venue"
},
  "geometry": {"coordinates":[7.4827132225,53.6439247131],"type":"Point"}
}