{
  "type": "Feature",
  "properties": {
    "iso:country":"DE",
    "sg:address":"Stralsunder Ring 8",
    "sg:city":"Wolfsburg",
    "sg:phone":"+49 5361/772626",
    "sg:postcode":"38444",
    "sg:province":"Niedersachsen",
    "wof:name":"Westhagener Apotheke",
    "wof:placetype":"venue"
},
  "geometry": {"coordinates":[10.743634,52.398628],"type":"Point"}
}