{
  "type": "Feature",
  "properties": {
    "iso:country":"DE",
    "sg:address":"H\u00fcttenstr. 78",
    "sg:city":"D\u00fcsseldorf",
    "sg:phone":"+49 211/383338",
    "sg:postcode":"40215",
    "sg:province":"Nordrhein-Westfalen",
    "wof:name":"Foto Schaefer",
    "wof:placetype":"venue"
},
  "geometry": {"coordinates":[6.7870402336,51.2145614624],"type":"Point"}
}