{
  "type": "Feature",
  "properties": {
    "iso:country":"DE",
    "sg:address":"Franzstr. 40",
    "sg:city":"Bonn",
    "sg:phone":"+49 228/691430",
    "sg:postcode":"53111",
    "sg:province":"Nordrhein-Westfalen",
    "wof:name":"Reinhold Soyka",
    "wof:placetype":"venue"
},
  "geometry": {"coordinates":[7.093143,50.736824],"type":"Point"}
}