{
  "type": "Feature",
  "properties": {
    "iso:country":"DE",
    "sg:address":"Hauptstr. 198",
    "sg:city":"Schwalbach",
    "sg:phone":"+49 6834/51426",
    "sg:postcode":"66773",
    "sg:province":"Saarland",
    "wof:name":"Gl\u00fcckauf-apotheke",
    "wof:placetype":"venue"
},
  "geometry": {"coordinates":[6.815396,49.3036],"type":"Point"}
}