{
  "type": "Feature",
  "properties": {
    "iso:country":"DE",
    "sg:address":"Kremser Str. 3",
    "sg:city":"Passau",
    "sg:phone":"+49 851/36451",
    "sg:postcode":"94032",
    "sg:province":"Bayern",
    "wof:name":"Wei\u00dfer Ring E. V. Gerhard Sagasser",
    "wof:placetype":"venue"
},
  "geometry": {"coordinates":[13.4851694107,48.5695075989],"type":"Point"}
}