{
  "type": "Feature",
  "properties": {
    "iso:country":"DE",
    "sg:address":"D\u00e4nische Str. 17",
    "sg:city":"Kiel",
    "sg:phone":"+49 431/5197250",
    "sg:postcode":"24103",
    "sg:province":"Schleswig-Holstein",
    "wof:name":"Evangelische B\u00fccherstube Gmbh",
    "wof:placetype":"venue"
},
  "geometry": {"coordinates":[10.1410589218,54.3243713379],"type":"Point"}
}