{
  "type": "Feature",
  "properties": {
    "iso:country":"DE",
    "sg:address":"Am Steinbruch 10",
    "sg:city":"Zirndorf",
    "sg:phone":"+49 911/608426",
    "sg:postcode":"90513",
    "sg:province":"Bayern",
    "wof:name":"Renate B\u00fchler",
    "wof:placetype":"venue"
},
  "geometry": {"coordinates":[10.926606,49.454971],"type":"Point"}
}