{
  "type": "Feature",
  "properties": {
    "iso:country":"DE",
    "sg:address":"Dorfstr. 32",
    "sg:city":"Nahe",
    "sg:phone":"+49 4535/51020",
    "sg:postcode":"23866",
    "sg:province":"Schleswig-Holstein",
    "wof:name":"Werbedienst Nahe Service Gmbh",
    "wof:placetype":"venue"
},
  "geometry": {"coordinates":[10.134513,53.798241],"type":"Point"}
}