{
  "type": "Feature",
  "properties": {
    "iso:country":"DE",
    "sg:address":"Hauptstr. 49",
    "sg:city":"Monzingen",
    "sg:phone":"+49 6751/2425",
    "sg:postcode":"55569",
    "sg:province":"Rheinland-Pfalz",
    "wof:name":"W. Alt",
    "wof:placetype":"venue"
},
  "geometry": {"coordinates":[7.5917291641,49.7991371155],"type":"Point"}
}