{
  "type": "Feature",
  "properties": {
    "iso:country":"DE",
    "sg:address":"Tornquiststr. 50 a",
    "sg:city":"Hamburg",
    "sg:phone":"+49 40/4916692",
    "sg:postcode":"20259",
    "sg:province":"Hamburg",
    "wof:name":"Gero Konkel",
    "wof:placetype":"venue"
},
  "geometry": {"coordinates":[9.955099,53.573235],"type":"Point"}
}