{
  "type": "Feature",
  "properties": {
    "iso:country":"DE",
    "sg:address":"W\u00fcstenstein 51",
    "sg:city":"Wiesenttal",
    "sg:phone":"+49 9196/1718",
    "sg:postcode":"91346",
    "sg:province":"Bayern",
    "wof:name":"Neudecker Zimmerei- Dachdeckerei Gmbh",
    "wof:placetype":"venue"
},
  "geometry": {"coordinates":[11.251572,49.850121],"type":"Point"}
}