{
  "type": "Feature",
  "properties": {
    "iso:country":"DE",
    "sg:address":"In Der Steinwiese 4",
    "sg:city":"Siegen",
    "sg:phone":"+49 4927/16725",
    "sg:postcode":"57074",
    "sg:province":"Nordrhein-Westfalen",
    "wof:name":"Klaus D. Neus Maschienenbau & Schweisskonstruktionen",
    "wof:placetype":"venue"
},
  "geometry": {"coordinates":[8.0766105652,50.8694763184],"type":"Point"}
}