{
  "type": "Feature",
  "properties": {
    "iso:country":"DE",
    "sg:address":"Neumattring 7",
    "sg:city":"Baden-Baden",
    "sg:phone":"+49 7221/66105",
    "sg:postcode":"76532",
    "sg:province":"Baden-W\u00fcrttemberg",
    "wof:name":"Kurt Peter Maschinenbau Und Mech. Werkst\u00e4tte Gmbh",
    "wof:placetype":"venue"
},
  "geometry": {"coordinates":[8.211533,48.814358],"type":"Point"}
}