{
  "type": "Feature",
  "properties": {
    "iso:country":"DE",
    "sg:address":"Heinestr. 9",
    "sg:city":"Steinhagen",
    "sg:phone":"+49 5204/7839",
    "sg:postcode":"33803",
    "sg:province":"Nordrhein-Westfalen",
    "wof:name":"Hans-werner Bante",
    "wof:placetype":"venue"
},
  "geometry": {"coordinates":[8.3438997269,51.993019104],"type":"Point"}
}