{
  "type": "Feature",
  "properties": {
    "iso:country":"DE",
    "sg:address":"Kirchweg 4",
    "sg:city":"Thalb\u00fcrgel",
    "sg:phone":"+49 36692/22301",
    "sg:postcode":"07616",
    "sg:province":"Th\u00fcringen",
    "wof:name":"B. Lutz",
    "wof:placetype":"venue"
},
  "geometry": {"coordinates":[11.748015,50.936577],"type":"Point"}
}