{
  "type": "Feature",
  "properties": {
    "iso:country":"DE",
    "sg:address":"Neue Reihe 2",
    "sg:city":"Schackstedt",
    "sg:phone":"+49 34692/21799",
    "sg:postcode":"06425",
    "sg:province":"Sachsen-Anhalt",
    "wof:name":"Bernd Bohlmann Reiseb\u00fcro",
    "wof:placetype":"venue"
},
  "geometry": {"coordinates":[11.6140937805,51.7170944214],"type":"Point"}
}