{
  "type": "Feature",
  "properties": {
    "iso:country":"DE",
    "sg:address":"Von-der-Schulenburg-Str. 11",
    "sg:city":"Bleckede",
    "sg:phone":"+49 5852/3889",
    "sg:postcode":"21354",
    "sg:province":"Niedersachsen",
    "wof:name":"Hgk Bau- Und Immobilien Gmbh",
    "wof:placetype":"venue"
},
  "geometry": {"coordinates":[10.751485,53.282284],"type":"Point"}
}