{
  "type": "Feature",
  "properties": {
    "iso:country":"DE",
    "sg:address":"Bergstr. 50",
    "sg:city":"Medlingen",
    "sg:phone":"+49 9073/407",
    "sg:postcode":"89441",
    "sg:province":"Bayern",
    "wof:name":"Seiler Gmbh",
    "wof:placetype":"venue"
},
  "geometry": {"coordinates":[10.310079,48.602371],"type":"Point"}
}