{
  "type": "Feature",
  "properties": {
    "iso:country":"DE",
    "sg:address":"Brunnenstr. 6",
    "sg:city":"B\u00fcdelsdorf",
    "sg:phone":"+49 4331/31266",
    "sg:postcode":"24782",
    "sg:province":"Schleswig-Holstein",
    "wof:name":"Nikolaus Clausen Ingenieur",
    "wof:placetype":"venue"
},
  "geometry": {"coordinates":[9.6593952179,54.3128890991],"type":"Point"}
}