{
  "type": "Feature",
  "properties": {
    "iso:country":"DE",
    "sg:address":"Aspergstr 17a",
    "sg:city":"Ofterdingen",
    "sg:phone":"+49 7473/6283",
    "sg:postcode":"72131",
    "sg:province":"Baden-W\u00fcrttemberg",
    "wof:name":"Karl Rilling Gmbh & Co Kg",
    "wof:placetype":"venue"
},
  "geometry": {"coordinates":[9.034551,48.418659],"type":"Point"}
}