{
  "type": "Feature",
  "properties": {
    "iso:country":"DE",
    "sg:address":"Heidmarkstr. 8",
    "sg:city":"Bremen",
    "sg:phone":"+49 421/4675853",
    "sg:postcode":"28329",
    "sg:province":"Bremen",
    "wof:name":"Erol Demiray",
    "wof:placetype":"venue"
},
  "geometry": {"coordinates":[8.8740959167,53.0741386414],"type":"Point"}
}