{
  "type": "Feature",
  "properties": {
    "iso:country":"DE",
    "sg:address":"Nordstr. 11",
    "sg:city":"Bocholt",
    "sg:phone":"+49 2871/227637",
    "sg:postcode":"46399",
    "sg:province":"Nordrhein-Westfalen",
    "wof:name":"F. Arens Marien-apotheke",
    "wof:placetype":"venue"
},
  "geometry": {"coordinates":[6.614928,51.839661],"type":"Point"}
}