{
  "type": "Feature",
  "properties": {
    "iso:country":"DE",
    "sg:address":"Kanalstr. 24-30",
    "sg:city":"Senden",
    "sg:phone":"+49 2597/8320",
    "sg:postcode":"48308",
    "sg:province":"Nordrhein-Westfalen",
    "wof:name":"Historisches Schiffsmuseum Senden Gmbh",
    "wof:placetype":"venue"
},
  "geometry": {"coordinates":[7.484761,51.849724],"type":"Point"}
}