{
  "type": "Feature",
  "properties": {
    "iso:country":"DE",
    "sg:address":"Benzmannstr. 10",
    "sg:city":"Berlin",
    "sg:phone":"+49 30/7964502",
    "sg:postcode":"12167",
    "sg:province":"Berlin",
    "wof:name":"Hildegard H\u00fcbner Masseurin",
    "wof:placetype":"venue"
},
  "geometry": {"coordinates":[13.345466,52.448513],"type":"Point"}
}