{
  "type": "Feature",
  "properties": {
    "iso:country":"DE",
    "sg:address":"Mozartstr. 23",
    "sg:city":"Gr\u00e4felfing",
    "sg:phone":"+49 89/884623",
    "sg:postcode":"82166",
    "sg:province":"Bayern",
    "wof:name":"Api Energie- Und Versorgungstechnik Gmbh",
    "wof:placetype":"venue"
},
  "geometry": {"coordinates":[11.431391716,48.137096405],"type":"Point"}
}