{
  "type": "Feature",
  "properties": {
    "iso:country":"DE",
    "sg:address":"Schwetzinger Str. 16",
    "sg:city":"Mannheim",
    "sg:phone":"+49 621/443438",
    "sg:postcode":"68165",
    "sg:province":"Baden-W\u00fcrttemberg",
    "wof:name":"Karl Butzmann",
    "wof:placetype":"venue"
},
  "geometry": {"coordinates":[8.473693,49.481285],"type":"Point"}
}