{
  "type": "Feature",
  "properties": {
    "iso:country":"DE",
    "sg:address":"Industriestr. 26",
    "sg:city":"Leck",
    "sg:phone":"+49 4662/3555",
    "sg:postcode":"25917",
    "sg:province":"Schleswig-Holstein",
    "wof:name":"Favorit-markt",
    "wof:placetype":"venue"
},
  "geometry": {"coordinates":[8.9820365906,54.7778778076],"type":"Point"}
}