{
  "type": "Feature",
  "properties": {
    "iso:country":"DE",
    "sg:address":"Asternweg 10",
    "sg:city":"Fichtenau",
    "sg:postcode":"74579",
    "sg:province":"Baden-W\u00fcrttemberg",
    "wof:name":"Kosmos Glas Gmbh",
    "wof:placetype":"venue"
},
  "geometry": {"coordinates":[10.227268219,49.0499420166],"type":"Point"}
}