{
  "type": "Feature",
  "properties": {
    "iso:country":"DE",
    "sg:city":"Aach",
    "sg:phone":"+49 7774/8317",
    "sg:postcode":"78267",
    "sg:province":"Baden-W\u00fcrttemberg",
    "wof:name":"R. Und A. R\u00f6tzer",
    "wof:placetype":"venue"
},
  "geometry": {"coordinates":[8.849703,47.843075],"type":"Point"}
}