{
  "type": "Feature",
  "properties": {
    "iso:country":"DE",
    "sg:address":"Falderbaumstr. 25",
    "sg:city":"Kassel",
    "sg:phone":"+49 561/95870",
    "sg:postcode":"34123",
    "sg:province":"Hessen",
    "wof:name":"Wagener Fetzer Und Kalveram Dienstleistungs Gmbh",
    "wof:placetype":"venue"
},
  "geometry": {"coordinates":[9.50089,51.277279],"type":"Point"}
}