{
  "type": "Feature",
  "properties": {
    "iso:country":"DE",
    "sg:address":"Bloherfelder Str. 58",
    "sg:city":"Oldenburg",
    "sg:phone":"+49 441/52515",
    "sg:postcode":"26129",
    "sg:province":"Niedersachsen",
    "wof:name":"V. Starken Rechtsanwalt",
    "wof:placetype":"venue"
},
  "geometry": {"coordinates":[8.1839046478,53.1410179138],"type":"Point"}
}