{
  "type": "Feature",
  "properties": {
    "iso:country":"DE",
    "sg:address":"R\u00fcgener Ring 14",
    "sg:city":"Sassnitz",
    "sg:phone":"+49 38392/34061",
    "sg:postcode":"18546",
    "sg:province":"Mecklenburg-Vorpommern",
    "wof:name":"Wohnungsbaugenossenschaft Sa\u00dfnitz Eg",
    "wof:placetype":"venue"
},
  "geometry": {"coordinates":[13.6196632385,54.5170135498],"type":"Point"}
}