{
  "type": "Feature",
  "properties": {
    "iso:country":"DE",
    "sg:address":"Oberstdorfer Str. 11",
    "sg:city":"N\u00fcrnberg",
    "sg:phone":"+49 911/8888558",
    "sg:postcode":"90455",
    "sg:province":"Bayern",
    "wof:name":"Technoplast Gmbh",
    "wof:placetype":"venue"
},
  "geometry": {"coordinates":[11.077503,49.361893],"type":"Point"}
}