{
  "type": "Feature",
  "properties": {
    "iso:country":"DE",
    "sg:address":"Gustav-B\u00f6cker-Str. 1",
    "sg:city":"Rosendahl",
    "sg:phone":"+49 2566/4827",
    "sg:postcode":"48720",
    "sg:province":"Nordrhein-Westfalen",
    "wof:name":"S. Teuber",
    "wof:placetype":"venue"
},
  "geometry": {"coordinates":[7.130177,52.006481],"type":"Point"}
}