{
  "type": "Feature",
  "properties": {
    "iso:country":"DE",
    "sg:address":"Bernauer Str. 115-118",
    "sg:city":"Berlin",
    "sg:phone":"+49 30/467050",
    "sg:postcode":"13355",
    "sg:province":"Berlin",
    "wof:name":"Diakoniestiftung Lazarus Berlin",
    "wof:placetype":"venue"
},
  "geometry": {"coordinates":[13.3890037537,52.5347595215],"type":"Point"}
}