{
  "type": "Feature",
  "properties": {
    "iso:country":"DE",
    "sg:address":"Arnst\u00e4dter Str. 4",
    "sg:city":"Tra\u00dfdorf",
    "sg:phone":"+49 3629/66820",
    "sg:postcode":"99326",
    "sg:province":"Th\u00fcringen",
    "wof:name":"L Und K Land- Und Kraft- Fahrzeugtechnik Gmbh",
    "wof:placetype":"venue"
},
  "geometry": {"coordinates":[11.014199,50.748783],"type":"Point"}
}