{
  "type": "Feature",
  "properties": {
    "iso:country":"DE",
    "sg:address":"Alois-Harrer-Weg 10",
    "sg:city":"Freystadt",
    "sg:phone":"+49 9179/5335",
    "sg:postcode":"92342",
    "sg:province":"Bayern",
    "wof:name":"Fritz Schmidt",
    "wof:placetype":"venue"
},
  "geometry": {"coordinates":[11.3382825851,49.1986808777],"type":"Point"}
}