{
  "type": "Feature",
  "properties": {
    "iso:country":"DE",
    "sg:address":"Luisenstr. 5",
    "sg:city":"Bamberg",
    "sg:phone":"+49 951/965320",
    "sg:postcode":"96047",
    "sg:province":"Bayern",
    "wof:name":"Visit Ambulante Pflege Gmbh & Co. Kg",
    "wof:placetype":"venue"
},
  "geometry": {"coordinates":[10.895208,49.892105],"type":"Point"}
}