{
  "type": "Feature",
  "properties": {
    "iso:country":"DE",
    "sg:address":"Am Sandfeld 17 a",
    "sg:city":"Karlsruhe",
    "sg:postcode":"76149",
    "sg:province":"Baden-W\u00fcrttemberg",
    "wof:name":"Storage Media Gmbh",
    "wof:placetype":"venue"
},
  "geometry": {"coordinates":[8.3921346664,49.0425643921],"type":"Point"}
}