{
  "type": "Feature",
  "properties": {
    "iso:country":"DE",
    "sg:address":"Gro\u00dfe Str. 54",
    "sg:city":"Osnabr\u00fcck",
    "sg:phone":"+49 541/358899",
    "sg:postcode":"49074",
    "sg:province":"Niedersachsen",
    "wof:name":"Tepe Gmbh",
    "wof:placetype":"venue"
},
  "geometry": {"coordinates":[8.045313,52.275131],"type":"Point"}
}