{
  "type": "Feature",
  "properties": {
    "iso:country":"DE",
    "sg:address":"Tostedter Str. 2",
    "sg:city":"Welle",
    "sg:phone":"+49 4188/263",
    "sg:postcode":"21261",
    "sg:province":"Niedersachsen",
    "wof:name":"Volksbank Buchholz Eg",
    "wof:placetype":"venue"
},
  "geometry": {"coordinates":[9.801009,53.240562],"type":"Point"}
}