{
  "type": "Feature",
  "properties": {
    "iso:country":"DE",
    "sg:address":"Uhlandstr. 8",
    "sg:city":"Geislingen",
    "sg:phone":"+49 7433/10578",
    "sg:postcode":"72351",
    "sg:province":"Baden-W\u00fcrttemberg",
    "wof:name":"Systemtec Bautr\u00e4ger Gmbh",
    "wof:placetype":"venue"
},
  "geometry": {"coordinates":[8.814017,48.286625],"type":"Point"}
}