{
  "type": "Feature",
  "properties": {
    "iso:country":"DE",
    "sg:address":"Mittelstr. 4",
    "sg:city":"Halbs",
    "sg:phone":"+49 2663/4441",
    "sg:postcode":"56457",
    "sg:province":"Rheinland-Pfalz",
    "wof:name":"Vienna Gmbh",
    "wof:placetype":"venue"
},
  "geometry": {"coordinates":[7.9641590118,50.5890197754],"type":"Point"}
}