{
  "type": "Feature",
  "properties": {
    "iso:country":"DE",
    "sg:address":"Rheinstr. 11",
    "sg:city":"Recklinghausen",
    "sg:phone":"+49 2361/70610",
    "sg:postcode":"45663",
    "sg:province":"Nordrhein-Westfalen",
    "wof:name":"Pz Sportwagen Verwaltungs- Gmbh",
    "wof:placetype":"venue"
},
  "geometry": {"coordinates":[7.215391,51.579903],"type":"Point"}
}