{
  "type": "Feature",
  "properties": {
    "iso:country":"DE",
    "sg:address":"Ladenburger Str. 49",
    "sg:city":"Heidelberg",
    "sg:phone":"+49 6221/472247",
    "sg:postcode":"69120",
    "sg:province":"Baden-W\u00fcrttemberg",
    "wof:name":"K.-h. K\u00f6gel",
    "wof:placetype":"venue"
},
  "geometry": {"coordinates":[8.68747,49.414078],"type":"Point"}
}