{
  "type": "Feature",
  "properties": {
    "iso:country":"DE",
    "sg:address":"Hauptstr. 52",
    "sg:city":"Muggensturm",
    "sg:phone":"+49 7222/8919",
    "sg:postcode":"76461",
    "sg:province":"Baden-W\u00fcrttemberg",
    "wof:name":"Ahorn-apotheke",
    "wof:placetype":"venue"
},
  "geometry": {"coordinates":[8.276777,48.869911],"type":"Point"}
}