{
  "type": "Feature",
  "properties": {
    "iso:country":"DE",
    "sg:address":"Tucholskystr. 79",
    "sg:city":"Frankfurt",
    "sg:phone":"+49 69/681217",
    "sg:postcode":"60598",
    "sg:province":"Hessen",
    "wof:name":"H. Denk",
    "wof:placetype":"venue"
},
  "geometry": {"coordinates":[8.6873979568,50.0921859741],"type":"Point"}
}