{
  "type": "Feature",
  "properties": {
    "iso:country":"DE",
    "sg:address":"Brunnenstr. 107",
    "sg:city":"Berlin",
    "sg:postcode":"13355",
    "sg:province":"Berlin",
    "wof:name":"Industrie- Wohn- Und Sportst\u00e4ttenbauges. Berlon Mbh",
    "wof:placetype":"venue"
},
  "geometry": {"coordinates":[13.3887166977,52.5481033325],"type":"Point"}
}