{
  "type": "Feature",
  "properties": {
    "iso:country":"DE",
    "sg:address":"Bismarckstr. 82",
    "sg:city":"Lahr",
    "sg:postcode":"77933",
    "sg:province":"Baden-W\u00fcrttemberg",
    "wof:name":"Katholisches Dekanat",
    "wof:placetype":"venue"
},
  "geometry": {"coordinates":[7.880338192,48.3409233093],"type":"Point"}
}