{
  "type": "Feature",
  "properties": {
    "iso:country":"DE",
    "sg:address":"vordere Hauptstra\u00dfe 20",
    "sg:city":"Adelberg",
    "sg:postcode":"73099",
    "sg:province":"Baden-W\u00fcrttemberg",
    "wof:name":"Der Online-shop F\u00fcr Den Transalpfahrer",
    "wof:placetype":"venue"
},
  "geometry": {"coordinates":[9.601881,48.762829],"type":"Point"}
}