{
  "type": "Feature",
  "properties": {
    "iso:country":"DE",
    "sg:address":"M\u00fchlenstr. 67",
    "sg:city":"Jever",
    "sg:postcode":"26441",
    "sg:province":"Niedersachsen",
    "wof:name":"Ev.-luth. Rentamt Des Kirchenkreises Jever",
    "wof:placetype":"venue"
},
  "geometry": {"coordinates":[7.9096860886,53.568271637],"type":"Point"}
}