{
  "type": "Feature",
  "properties": {
    "iso:country":"DE",
    "sg:address":"Wilhelm-von-Polenz-Str. 7",
    "sg:city":"Cunewalde",
    "sg:phone":"+49 35877/2310",
    "sg:postcode":"02733",
    "sg:province":"Sachsen",
    "wof:name":"Christian Hensel Me\u00df- Regel- Und Pr\u00fcftechnik",
    "wof:placetype":"venue"
},
  "geometry": {"coordinates":[14.530878067,51.0976600647],"type":"Point"}
}