{
  "type": "Feature",
  "properties": {
    "iso:country":"DE",
    "sg:address":"Drosselweg 4",
    "sg:city":"Lichtenfels",
    "sg:phone":"+49 6454/811",
    "sg:postcode":"35104",
    "sg:province":"Hessen",
    "wof:name":"Karl-heinz Sch\u00e4fer Masseur",
    "wof:placetype":"venue"
},
  "geometry": {"coordinates":[8.791373,51.12273],"type":"Point"}
}