{
  "type": "Feature",
  "properties": {
    "iso:country":"DE",
    "sg:address":"Pillauer Str. 12",
    "sg:city":"Pforzheim",
    "sg:phone":"+49 7231/67222",
    "sg:postcode":"75181",
    "sg:province":"Baden-W\u00fcrttemberg",
    "wof:name":"Neukauf Markt Gmbh",
    "wof:placetype":"venue"
},
  "geometry": {"coordinates":[8.7345352173,48.8841247559],"type":"Point"}
}