{
  "type": "Feature",
  "properties": {
    "iso:country":"DE",
    "sg:address":"L\u00f6wenzahnweg 35",
    "sg:city":"Berlin",
    "sg:phone":"+49 30/6626509",
    "sg:postcode":"12357",
    "sg:province":"Berlin",
    "wof:name":"Nolte Kantinenbetriebe Gmbh",
    "wof:placetype":"venue"
},
  "geometry": {"coordinates":[13.4857225418,52.4277572632],"type":"Point"}
}