{
  "type": "Feature",
  "properties": {
    "iso:country":"DE",
    "sg:address":"Rosenthaler Str. 40/41",
    "sg:city":"Berlin",
    "sg:phone":"+49 2853/3300",
    "sg:postcode":"10178",
    "sg:province":"Berlin",
    "wof:name":"Ventoura Reisen - St\u00e4dtereisen In Europa",
    "wof:placetype":"venue"
},
  "geometry": {"coordinates":[13.402347,52.523899],"type":"Point"}
}