{
  "type": "Feature",
  "properties": {
    "iso:country":"DE",
    "sg:address":"Hinderpad 10",
    "sg:city":"Hattingen",
    "sg:phone":"+49 2324/21445",
    "sg:postcode":"45525",
    "sg:province":"Nordrhein-Westfalen",
    "wof:name":"Artur Ranft",
    "wof:placetype":"venue"
},
  "geometry": {"coordinates":[7.1902399063,51.3891372681],"type":"Point"}
}