{
  "type": "Feature",
  "properties": {
    "iso:country":"DE",
    "sg:address":"Zum Niederntor 19",
    "sg:city":"Springe",
    "sg:phone":"+49 5041/63678",
    "sg:postcode":"31832",
    "sg:province":"Niedersachsen",
    "wof:name":"Canto Gmbh",
    "wof:placetype":"venue"
},
  "geometry": {"coordinates":[9.556191,52.209106],"type":"Point"}
}