{
  "type": "Feature",
  "properties": {
    "iso:country":"DE",
    "sg:address":"Bahnhofsplatz 1",
    "sg:city":"K\u00f6nigslutter",
    "sg:phone":"+49 5353/2213",
    "sg:postcode":"38154",
    "sg:province":"Niedersachsen",
    "wof:name":"Deutsche Bahn Ag",
    "wof:placetype":"venue"
},
  "geometry": {"coordinates":[10.8122606277,52.2568664551],"type":"Point"}
}