{
  "type": "Feature",
  "properties": {
    "iso:country":"DE",
    "sg:address":"Hohe Str. 34",
    "sg:city":"Schlema",
    "sg:phone":"+49 4961/7197580",
    "sg:postcode":"08301",
    "sg:province":"Sachsen",
    "wof:name":"Tec 5 Ag",
    "wof:placetype":"venue"
},
  "geometry": {"coordinates":[8.5919551849,50.1867103577],"type":"Point"}
}