{
  "type": "Feature",
  "properties": {
    "iso:country":"DE",
    "sg:address":"Bergstr. 2",
    "sg:city":"Ferdinandshof",
    "sg:phone":"+49 39778/20760",
    "sg:postcode":"17379",
    "sg:province":"Mecklenburg-Vorpommern",
    "wof:name":"Heinz-g\u00fcnter Manteuffel Tischlerei",
    "wof:placetype":"venue"
},
  "geometry": {"coordinates":[13.886754,53.666626],"type":"Point"}
}