{
  "type": "Feature",
  "properties": {
    "iso:country":"DE",
    "sg:address":"Ziegeleiweg 2 A",
    "sg:city":"Immenhausen",
    "sg:phone":"+49 5673/6246",
    "sg:postcode":"34376",
    "sg:province":"Hessen",
    "wof:name":"Roma Pizza",
    "wof:placetype":"venue"
},
  "geometry": {"coordinates":[9.4769763947,51.4298667908],"type":"Point"}
}