{
  "type": "Feature",
  "properties": {
    "iso:country":"DE",
    "sg:address":"Elseyer Str. 47-51",
    "sg:city":"Hagen",
    "sg:postcode":"58119",
    "sg:province":"Nordrhein-Westfalen",
    "wof:name":"Gro\u00df Und Niggemeier Gmbh",
    "wof:placetype":"venue"
},
  "geometry": {"coordinates":[7.553691,51.364452],"type":"Point"}
}