{
  "type": "Feature",
  "properties": {
    "iso:country":"DE",
    "sg:address":"Am Seminargarten 2",
    "sg:city":"Ludwigslust",
    "sg:phone":"+49 3874/21164",
    "sg:postcode":"19288",
    "sg:province":"Mecklenburg-Vorpommern",
    "wof:name":"F. Kiecksee",
    "wof:placetype":"venue"
},
  "geometry": {"coordinates":[11.495145,53.32806],"type":"Point"}
}