{
  "type": "Feature",
  "properties": {
    "iso:country":"DE",
    "sg:address":"Stra\u00dfe der Bodenreform 22",
    "sg:city":"Kleinpaschleben",
    "sg:phone":"+49 34979/22226",
    "sg:postcode":"06369",
    "sg:province":"Sachsen-Anhalt",
    "wof:name":"Pfeiffers Holz Und Baustoffe Gmbh",
    "wof:placetype":"venue"
},
  "geometry": {"coordinates":[11.885705,51.787941],"type":"Point"}
}