{
  "type": "Feature",
  "properties": {
    "iso:country":"DE",
    "sg:address":"Anemonenstr. 14",
    "sg:city":"Ingolstadt",
    "sg:phone":"+49 841/36108",
    "sg:postcode":"85055",
    "sg:province":"Bayern",
    "wof:name":"Fritz Meier",
    "wof:placetype":"venue"
},
  "geometry": {"coordinates":[11.485444,48.770939],"type":"Point"}
}