{
  "type": "Feature",
  "properties": {
    "iso:country":"DE",
    "sg:address":"Wexstr. 21",
    "sg:city":"Hamburg",
    "sg:postcode":"20355",
    "sg:province":"Hamburg",
    "wof:name":"Adolph Detmering",
    "wof:placetype":"venue"
},
  "geometry": {"coordinates":[9.9828224182,53.5512123108],"type":"Point"}
}