{
  "type": "Feature",
  "properties": {
    "iso:country":"DE",
    "sg:address":"Marktplatz 32",
    "sg:city":"Fritzlar",
    "sg:phone":"+49 5622/2200",
    "sg:postcode":"34560",
    "sg:province":"Hessen",
    "wof:name":"Der Brillenmacher Inh. Marcus Greiner",
    "wof:placetype":"venue"
},
  "geometry": {"coordinates":[9.273379,51.131729],"type":"Point"}
}