{
  "type": "Feature",
  "properties": {
    "iso:country":"DE",
    "sg:address":"Br\u00fcckenwiesenweg 29",
    "sg:city":"Malsch",
    "sg:phone":"+49 7246/8132",
    "sg:postcode":"76316",
    "sg:province":"Baden-W\u00fcrttemberg",
    "wof:name":"Leo Schr\u00f6der",
    "wof:placetype":"venue"
},
  "geometry": {"coordinates":[8.329688,48.890282],"type":"Point"}
}