{
  "type": "Feature",
  "properties": {
    "iso:country":"DE",
    "sg:address":"Sperlingsweg 14",
    "sg:city":"Hamburg",
    "sg:phone":"+49 40/5526743",
    "sg:postcode":"22453",
    "sg:province":"Hamburg",
    "wof:name":"Toolbox Helle Steppart-flemming",
    "wof:placetype":"venue"
},
  "geometry": {"coordinates":[9.976115,53.645313],"type":"Point"}
}