{
  "type": "Feature",
  "properties": {
    "iso:country":"DE",
    "sg:address":"Elfbuchenstr. 28",
    "sg:city":"Kassel",
    "sg:phone":"+49 561/775719",
    "sg:postcode":"34119",
    "sg:province":"Hessen",
    "wof:name":"Horst Gatzemann",
    "wof:placetype":"venue"
},
  "geometry": {"coordinates":[9.4656047821,51.3176765442],"type":"Point"}
}