{
  "type": "Feature",
  "properties": {
    "iso:country":"DE",
    "sg:city":"Lennestadt",
    "sg:postcode":"57368",
    "sg:province":"Nordrhein-Westfalen",
    "wof:name":"Communications-service-lewe",
    "wof:placetype":"venue"
},
  "geometry": {"coordinates":[8.067655,51.121063],"type":"Point"}
}