{
  "type": "Feature",
  "properties": {
    "iso:country":"DE",
    "sg:address":"Wielandstr. 13",
    "sg:city":"Braunschweig",
    "sg:phone":"+49 531/610317",
    "sg:postcode":"38124",
    "sg:province":"Niedersachsen",
    "wof:name":"Arbeitsgemeinschaft St\u00f6ck- Heimer Vereine",
    "wof:placetype":"venue"
},
  "geometry": {"coordinates":[10.5254077911,52.2174339294],"type":"Point"}
}