{
  "type": "Feature",
  "properties": {
    "iso:country":"DE",
    "sg:address":"Schubertweg 7",
    "sg:city":"Emmendingen",
    "sg:phone":"+49 7641/1713",
    "sg:postcode":"79312",
    "sg:province":"Baden-W\u00fcrttemberg",
    "wof:name":"A. L\u00f6rz",
    "wof:placetype":"venue"
},
  "geometry": {"coordinates":[7.8624358177,48.1196861267],"type":"Point"}
}