{
  "type": "Feature",
  "properties": {
    "iso:country":"DE",
    "sg:address":"Am Pulverturm 3",
    "sg:city":"Wachtendonk",
    "sg:postcode":"47669",
    "sg:province":"Nordrhein-Westfalen",
    "wof:name":"Epsilon Grundst\u00fccksentwicklung Beteiligungs- Gmbh",
    "wof:placetype":"venue"
},
  "geometry": {"coordinates":[6.3374891281,51.4095191956],"type":"Point"}
}