{
  "type": "Feature",
  "properties": {
    "iso:country":"DE",
    "sg:address":"Am Rohrbach 3",
    "sg:city":"Friedrichshafen",
    "sg:phone":"+49 7541/56330",
    "sg:postcode":"88045",
    "sg:province":"Baden-W\u00fcrttemberg",
    "wof:name":"K. Faaber",
    "wof:placetype":"venue"
},
  "geometry": {"coordinates":[9.4801282883,47.6755752563],"type":"Point"}
}