{
  "type": "Feature",
  "properties": {
    "iso:country":"DE",
    "sg:address":"Pferdsfeld 1",
    "sg:city":"Bad Sobernheim",
    "sg:phone":"+49 6756/159719",
    "sg:postcode":"55566",
    "sg:province":"Rheinland-Pfalz",
    "wof:name":"Agro Sys Gmbh & Co. Kg",
    "wof:placetype":"venue"
},
  "geometry": {"coordinates":[7.589996,49.850471],"type":"Point"}
}