{
  "type": "Feature",
  "properties": {
    "iso:country":"DE",
    "sg:address":"Hauptstr. 9",
    "sg:city":"Leidersbach",
    "sg:phone":"+49 6028/6366",
    "sg:postcode":"63849",
    "sg:province":"Bayern",
    "wof:name":"Konrad Sch\u00fc\u00dfler",
    "wof:placetype":"venue"
},
  "geometry": {"coordinates":[9.20956,49.907539],"type":"Point"}
}