{
  "type": "Feature",
  "properties": {
    "iso:country":"DE",
    "sg:address":"Niederweniger Str. 6",
    "sg:city":"Essen",
    "sg:phone":"+49 201/482265",
    "sg:postcode":"45257",
    "sg:province":"Nordrhein-Westfalen",
    "wof:name":"Heribert Unteregge B\u00e4ckerei Und Lebensmittel",
    "wof:placetype":"venue"
},
  "geometry": {"coordinates":[7.10463,51.392563],"type":"Point"}
}