{
  "type": "Feature",
  "properties": {
    "iso:country":"DE",
    "sg:address":"Orlam\u00fcnderstr. 2",
    "sg:city":"Himmelkron",
    "sg:phone":"+49 9227/5245",
    "sg:postcode":"95502",
    "sg:province":"Bayern",
    "wof:name":"H. Teupert",
    "wof:placetype":"venue"
},
  "geometry": {"coordinates":[11.5999326706,50.0654945374],"type":"Point"}
}