{
  "type": "Feature",
  "properties": {
    "iso:country":"DE",
    "sg:address":"Wertachstr 31",
    "sg:city":"N\u00fcrnberg",
    "sg:phone":"+49 911/9628060",
    "sg:postcode":"90451",
    "sg:province":"Bayern",
    "wof:name":"Gfb Ges. F\u00fcr Beleuchtungstechnik Mbh",
    "wof:placetype":"venue"
},
  "geometry": {"coordinates":[11.0483007431,49.4073371887],"type":"Point"}
}