{
  "type": "Feature",
  "properties": {
    "iso:country":"DE",
    "sg:address":"Stettener Stra\u00dfe 16",
    "sg:city":"Hausen/Rh\u00f6n",
    "sg:phone":"+49 9778",
    "sg:postcode":"97647",
    "sg:province":"Bayern",
    "wof:name":"Installation Von Umweltschonende Technologien",
    "wof:placetype":"venue"
},
  "geometry": {"coordinates":[10.156381,50.466511],"type":"Point"}
}