{
  "type": "Feature",
  "properties": {
    "iso:country":"DE",
    "sg:address":"Zie\u00dfau Dorfstr. 8",
    "sg:city":"Arendsee",
    "sg:phone":"+49 39384/27386",
    "sg:postcode":"39619",
    "sg:province":"Sachsen-Anhalt",
    "wof:name":"Pension Zum Schwarzen Kater",
    "wof:placetype":"venue"
},
  "geometry": {"coordinates":[11.4418649673,52.8921432495],"type":"Point"}
}