{
  "type": "Feature",
  "properties": {
    "iso:country":"DE",
    "sg:address":"Friedrich-Ebert-Platz",
    "sg:city":"Leverkusen",
    "sg:phone":"+49 214/3524171",
    "sg:postcode":"51373",
    "sg:province":"Nordrhein-Westfalen",
    "wof:name":"Stadtbibiliothek Stadthaus",
    "wof:placetype":"venue"
},
  "geometry": {"coordinates":[6.98739,51.033661],"type":"Point"}
}