{
  "type": "Feature",
  "properties": {
    "iso:country":"DE",
    "sg:address":"Hofmannstr. 21",
    "sg:city":"M\u00fcnchen",
    "sg:phone":"+49 89/788883",
    "sg:postcode":"81379",
    "sg:province":"Bayern",
    "wof:name":"Heinisch Haus-system Ohg",
    "wof:placetype":"venue"
},
  "geometry": {"coordinates":[11.5291519165,48.0993843079],"type":"Point"}
}