{
  "type": "Feature",
  "properties": {
    "iso:country":"DE",
    "sg:address":"Steinbeisweg 20",
    "sg:city":"Schw\u00e4bisch Hall",
    "sg:phone":"+49 791/5060",
    "sg:postcode":"74523",
    "sg:province":"Baden-W\u00fcrttemberg",
    "wof:name":"Optima Auslands- Beteiligungen Gmbh",
    "wof:placetype":"venue"
},
  "geometry": {"coordinates":[9.705641,49.1049],"type":"Point"}
}