{
  "type": "Feature",
  "properties": {
    "iso:country":"DE",
    "sg:address":"Spitzkrugring 1",
    "sg:city":"Frankfurt",
    "sg:postcode":"15234",
    "sg:province":"Brandenburg",
    "wof:name":"Witold Wisniewski",
    "wof:placetype":"venue"
},
  "geometry": {"coordinates":[14.523914,52.363136],"type":"Point"}
}