{
  "type": "Feature",
  "properties": {
    "iso:country":"DE",
    "sg:address":"Ludolfingerweg 31",
    "sg:city":"Berlin",
    "sg:phone":"+49 30/40105800",
    "sg:postcode":"13465",
    "sg:province":"Berlin",
    "wof:name":"Immodaxx Gmbh",
    "wof:placetype":"venue"
},
  "geometry": {"coordinates":[13.281614,52.632652],"type":"Point"}
}