{
  "type": "Feature",
  "properties": {
    "iso:country":"DE",
    "sg:address":"Hubertus-von-Nell-Str. 19",
    "sg:city":"Perl",
    "sg:phone":"+49 6867/1457",
    "sg:postcode":"66706",
    "sg:province":"Saarland",
    "wof:name":"Perler Pils Pub",
    "wof:placetype":"venue"
},
  "geometry": {"coordinates":[6.3889298439,49.4730567932],"type":"Point"}
}