{
  "type": "Feature",
  "properties": {
    "iso:country":"DE",
    "sg:address":"Weitlingstr. 35",
    "sg:city":"Berlin",
    "sg:phone":"+49 30/5251943",
    "sg:postcode":"10317",
    "sg:province":"Berlin",
    "wof:name":"Lichtenberger Bauernstube",
    "wof:placetype":"venue"
},
  "geometry": {"coordinates":[13.4970884323,52.5076370239],"type":"Point"}
}