{
  "type": "Feature",
  "properties": {
    "iso:country":"DE",
    "sg:address":"Lippertor 6",
    "sg:city":"Lippstadt",
    "sg:phone":"+49 2941/4505",
    "sg:postcode":"59555",
    "sg:province":"Nordrhein-Westfalen",
    "wof:name":"Deutsche Postbank Ag",
    "wof:placetype":"venue"
},
  "geometry": {"coordinates":[8.3463916779,51.6784973145],"type":"Point"}
}