{
  "type": "Feature",
  "properties": {
    "iso:country":"DE",
    "sg:address":"Gelsenkirchener Str. 32",
    "sg:city":"Essen",
    "sg:phone":"+49 201/212652",
    "sg:postcode":"45141",
    "sg:province":"Nordrhein-Westfalen",
    "wof:name":"Hristos Agelou",
    "wof:placetype":"venue"
},
  "geometry": {"coordinates":[7.0378499031,51.4778022766],"type":"Point"}
}