{
  "type": "Feature",
  "properties": {
    "iso:country":"DE",
    "sg:address":"Gertrud-B\u00e4umer-Str. 30",
    "sg:city":"Menden",
    "sg:phone":"+49 2373/62517",
    "sg:postcode":"58708",
    "sg:province":"Nordrhein-Westfalen",
    "wof:name":"P. Kirse",
    "wof:placetype":"venue"
},
  "geometry": {"coordinates":[7.7617659569,51.4400863647],"type":"Point"}
}