{
  "type": "Feature",
  "properties": {
    "iso:country":"DE",
    "sg:address":"Unterer Graben 5",
    "sg:city":"Weilheim",
    "sg:phone":"+49 881/63188",
    "sg:postcode":"82362",
    "sg:province":"Bayern",
    "wof:name":"La Piazzetta",
    "wof:placetype":"venue"
},
  "geometry": {"coordinates":[11.1406002045,47.8405036926],"type":"Point"}
}