{
  "type": "Feature",
  "properties": {
    "iso:country":"DE",
    "sg:address":"Herdfeldstr. 85",
    "sg:city":"Notzingen",
    "sg:phone":"+49 7021/45350",
    "sg:postcode":"73274",
    "sg:province":"Baden-W\u00fcrttemberg",
    "wof:name":"R. Knapp",
    "wof:placetype":"venue"
},
  "geometry": {"coordinates":[9.463946,48.674545],"type":"Point"}
}