{
  "type": "Feature",
  "properties": {
    "iso:country":"DE",
    "sg:address":"Rodder Damm 170",
    "sg:city":"Rheine",
    "sg:phone":"+49 5971/7900",
    "sg:postcode":"48432",
    "sg:province":"Nordrhein-Westfalen",
    "wof:name":"Renk Ag Werk Rheine",
    "wof:placetype":"venue"
},
  "geometry": {"coordinates":[7.485086,52.285809],"type":"Point"}
}