{
  "type": "Feature",
  "properties": {
    "iso:country":"DE",
    "sg:address":"D\u00fcrkheimer Str. 24",
    "sg:city":"Frankfurt",
    "sg:phone":"+49 69/398683",
    "sg:postcode":"65934",
    "sg:province":"Hessen",
    "wof:name":"G. Wolfst\u00e4dter Steinmetz",
    "wof:placetype":"venue"
},
  "geometry": {"coordinates":[8.5741710663,50.0976486206],"type":"Point"}
}