{
  "type": "Feature",
  "properties": {
    "iso:country":"DE",
    "sg:address":"Wolfsgartenstr. 2",
    "sg:city":"Egelsbach",
    "sg:phone":"+49 6103/947416",
    "sg:postcode":"63329",
    "sg:province":"Hessen",
    "wof:name":"H & K Daten\u00fcbertragungs- Anlagen Gmbh",
    "wof:placetype":"venue"
},
  "geometry": {"coordinates":[8.6527013779,49.9690055847],"type":"Point"}
}