{
  "type": "Feature",
  "properties": {
    "iso:country":"DE",
    "sg:address":"B\u00fctzower Str. 1a",
    "sg:city":"Hohen Luckow",
    "sg:postcode":"18239",
    "sg:province":"Mecklenburg-Vorpommern",
    "wof:name":"Eum Energie-umwelt- Messungen Gmbh",
    "wof:placetype":"venue"
},
  "geometry": {"coordinates":[11.9611616135,53.9772605896],"type":"Point"}
}