{
  "type": "Feature",
  "properties": {
    "iso:country":"DE",
    "sg:address":"Lerchenstr. 1B",
    "sg:city":"Heiligenhafen",
    "sg:phone":"+49 4362/2169",
    "sg:postcode":"23774",
    "sg:province":"Schleswig-Holstein",
    "wof:name":"Treffpunkt",
    "wof:placetype":"venue"
},
  "geometry": {"coordinates":[10.9842987061,54.3691139221],"type":"Point"}
}