{
  "type": "Feature",
  "properties": {
    "iso:country":"DE",
    "sg:address":"Ahornstr. 12",
    "sg:city":"Ro\u00dfbach",
    "sg:postcode":"94439",
    "sg:province":"Bayern",
    "wof:name":"Kollbach Verlag E. K.",
    "wof:placetype":"venue"
},
  "geometry": {"coordinates":[12.9454498291,48.5954284668],"type":"Point"}
}