{
  "type": "Feature",
  "properties": {
    "iso:country":"DE",
    "sg:address":"Robert-Bosch-Str. 24",
    "sg:city":"Karben",
    "sg:phone":"+49 6039/6222",
    "sg:postcode":"61184",
    "sg:province":"Hessen",
    "wof:name":"Gebr. De La Rosa Gmbh",
    "wof:placetype":"venue"
},
  "geometry": {"coordinates":[8.7568702698,50.2291755676],"type":"Point"}
}