{
  "type": "Feature",
  "properties": {
    "iso:country":"DE",
    "sg:address":"Eisenbahnstr. 25",
    "sg:city":"Kaiserslautern",
    "sg:phone":"+49 631/3605680",
    "sg:postcode":"67655",
    "sg:province":"Rheinland-Pfalz",
    "wof:name":"Lutrina-apotheke",
    "wof:placetype":"venue"
},
  "geometry": {"coordinates":[7.771384,49.441467],"type":"Point"}
}