{
  "type": "Feature",
  "properties": {
    "iso:country":"DE",
    "sg:address":"Rodalber Str. 30",
    "sg:city":"Pirmasens",
    "sg:phone":"+49 6331/12597",
    "sg:postcode":"66953",
    "sg:province":"Rheinland-Pfalz",
    "wof:name":"Reiner Stadel",
    "wof:placetype":"venue"
},
  "geometry": {"coordinates":[7.606849,49.206078],"type":"Point"}
}