{
  "type": "Feature",
  "properties": {
    "iso:country":"DE",
    "sg:address":"Viktoriastr. 14",
    "sg:city":"Borkum",
    "sg:phone":"+49 4922/3070",
    "sg:postcode":"26757",
    "sg:province":"Niedersachsen",
    "wof:name":"Cvjm",
    "wof:placetype":"venue"
},
  "geometry": {"coordinates":[6.6593990326,53.5901184082],"type":"Point"}
}