{
  "type": "Feature",
  "properties": {
    "iso:country":"DE",
    "sg:address":"Hubertusstr. 2",
    "sg:city":"Dillingen",
    "sg:phone":"+49 9071/3990",
    "sg:postcode":"89407",
    "sg:province":"Bayern",
    "wof:name":"Kleeblattstube",
    "wof:placetype":"venue"
},
  "geometry": {"coordinates":[10.507267952,48.5907974243],"type":"Point"}
}