{
  "type": "Feature",
  "properties": {
    "iso:country":"DE",
    "sg:address":"Holunderstr. 16",
    "sg:city":"Herrenberg",
    "sg:phone":"+49 7032/977966",
    "sg:postcode":"71083",
    "sg:province":"Baden-W\u00fcrttemberg",
    "wof:name":"S. Sch\u00e4fer",
    "wof:placetype":"venue"
},
  "geometry": {"coordinates":[8.8731489182,48.5761451721],"type":"Point"}
}