{
  "type": "Feature",
  "properties": {
    "iso:country":"DE",
    "sg:address":"Robert-Bosch-Str. 10",
    "sg:city":"Weilerswist",
    "sg:phone":"+49 4922/5494120",
    "sg:postcode":"53919",
    "sg:province":"Nordrhein-Westfalen",
    "wof:name":"Vista Alegre Gmbh",
    "wof:placetype":"venue"
},
  "geometry": {"coordinates":[6.853663,50.751377],"type":"Point"}
}