{
  "type": "Feature",
  "properties": {
    "iso:country":"DE",
    "sg:address":"An der Kleinen Str. 13",
    "sg:city":"Neustadt",
    "sg:phone":"+49 5032/7227",
    "sg:postcode":"31535",
    "sg:province":"Niedersachsen",
    "wof:name":"Heinrich Liever",
    "wof:placetype":"venue"
},
  "geometry": {"coordinates":[9.483828,52.531727],"type":"Point"}
}