{
  "type": "Feature",
  "properties": {
    "iso:country":"DE",
    "sg:address":"Hornaustr. 19",
    "sg:city":"Horb",
    "sg:phone":"+49 7451/1661",
    "sg:postcode":"72160",
    "sg:province":"Baden-W\u00fcrttemberg",
    "wof:name":"Erich Pflug Ingenieur",
    "wof:placetype":"venue"
},
  "geometry": {"coordinates":[8.6962194443,48.442691803],"type":"Point"}
}