{
  "type": "Feature",
  "properties": {
    "iso:country":"DE",
    "sg:address":"Habsburgerstr. 88",
    "sg:city":"N\u00fcrnberg",
    "sg:phone":"+49 911/835202",
    "sg:postcode":"90475",
    "sg:province":"Bayern",
    "wof:name":"Bernd Wiedemann",
    "wof:placetype":"venue"
},
  "geometry": {"coordinates":[11.1761684418,49.4015312195],"type":"Point"}
}