{
  "type": "Feature",
  "properties": {
    "iso:country":"DE",
    "sg:address":"Salzmannstr. 3",
    "sg:city":"Augsburg",
    "sg:phone":"+49 821/61258",
    "sg:postcode":"86163",
    "sg:province":"Bayern",
    "wof:name":"M. G\u00fcnther",
    "wof:placetype":"venue"
},
  "geometry": {"coordinates":[10.9457740784,48.3559951782],"type":"Point"}
}