{
  "type": "Feature",
  "properties": {
    "iso:country":"DE",
    "sg:address":"Kleiner Kirchrain 2",
    "sg:city":"Gro\u00dfalmerode",
    "sg:phone":"+49 5604/915136",
    "sg:postcode":"37247",
    "sg:province":"Hessen",
    "wof:name":"Irmtraud Lieberum",
    "wof:placetype":"venue"
},
  "geometry": {"coordinates":[9.7847681046,51.2569313049],"type":"Point"}
}