{
  "type": "Feature",
  "properties": {
    "iso:country":"DE",
    "sg:address":"Helmutstr. 3",
    "sg:city":"Minden",
    "sg:phone":"+49 571/33177",
    "sg:postcode":"32423",
    "sg:province":"Nordrhein-Westfalen",
    "wof:name":"Ruth Wilkening",
    "wof:placetype":"venue"
},
  "geometry": {"coordinates":[8.9550552368,52.289024353],"type":"Point"}
}