{
  "type": "Feature",
  "properties": {
    "iso:country":"DE",
    "sg:address":"Kellerhaus 22",
    "sg:city":"K\u00fcps",
    "sg:phone":"+49 9264/320",
    "sg:postcode":"96328",
    "sg:province":"Bayern",
    "wof:name":"Erwin Wei\u00dfmann",
    "wof:placetype":"venue"
},
  "geometry": {"coordinates":[11.255547,50.18446],"type":"Point"}
}