{
  "type": "Feature",
  "properties": {
    "iso:country":"DE",
    "sg:address":"Austr. 4",
    "sg:city":"Riedenburg",
    "sg:phone":"+49 9442/905223",
    "sg:postcode":"93339",
    "sg:province":"Bayern",
    "wof:name":"R. Pesl Und A. Segerer Rechtsanw\u00e4lte",
    "wof:placetype":"venue"
},
  "geometry": {"coordinates":[11.6826286316,48.9630355835],"type":"Point"}
}