{
  "type": "Feature",
  "properties": {
    "iso:country":"DE",
    "sg:address":"Bergstr. 31",
    "sg:city":"Eckernf\u00f6rde",
    "sg:postcode":"24340",
    "sg:province":"Schleswig-Holstein",
    "wof:name":"K\u00fchllagertechnik Nord E. K.",
    "wof:placetype":"venue"
},
  "geometry": {"coordinates":[9.8368,54.47702],"type":"Point"}
}