{
  "type": "Feature",
  "properties": {
    "iso:country":"DE",
    "sg:address":"Stuckenborsteler Str. 52",
    "sg:city":"Sottrum",
    "sg:postcode":"27367",
    "sg:province":"Niedersachsen",
    "wof:name":"K. & S. Krantz Sozialbau Und Betreuung Verwaltungs Gmbh",
    "wof:placetype":"venue"
},
  "geometry": {"coordinates":[9.1854629517,53.1073417664],"type":"Point"}
}