{
  "type": "Feature",
  "properties": {
    "iso:country":"DE",
    "sg:address":"K\u00f6nigsallee 157",
    "sg:city":"Bochum",
    "sg:phone":"+49 234/771329",
    "sg:postcode":"44799",
    "sg:province":"Nordrhein-Westfalen",
    "wof:name":"Klaus Jacob Ingenieur",
    "wof:placetype":"venue"
},
  "geometry": {"coordinates":[7.2230272293,51.4593200684],"type":"Point"}
}