{
  "type": "Feature",
  "properties": {
    "iso:country":"DE",
    "sg:address":"Marie-Curie-Str. 11",
    "sg:city":"Gronau",
    "sg:phone":"+49 4925/6293390",
    "sg:postcode":"48599",
    "sg:province":"Nordrhein-Westfalen",
    "wof:name":"Gerhard Drost Gmbh & Co.kg",
    "wof:placetype":"venue"
},
  "geometry": {"coordinates":[7.0263299942,52.1889190674],"type":"Point"}
}