{
  "type": "Feature",
  "properties": {
    "iso:country":"DE",
    "sg:address":"Germersheimer Str. 30",
    "sg:city":"M\u00fcnchen",
    "sg:phone":"+49 89/966364",
    "sg:postcode":"81541",
    "sg:province":"Bayern",
    "wof:name":"Canon Euor-photo Handelsges. Mbh",
    "wof:placetype":"venue"
},
  "geometry": {"coordinates":[11.5993366241,48.116569519],"type":"Point"}
}