{
  "type": "Feature",
  "properties": {
    "iso:country":"DE",
    "sg:address":"Eckstr. 37/2",
    "sg:city":"Neu-Ulm",
    "sg:phone":"+49 731/86588",
    "sg:postcode":"89231",
    "sg:province":"Bayern",
    "wof:name":"H. Ecker",
    "wof:placetype":"venue"
},
  "geometry": {"coordinates":[9.9965229034,48.3913955688],"type":"Point"}
}