{
  "type": "Feature",
  "properties": {
    "iso:country":"DE",
    "sg:address":"Marktplatz 4",
    "sg:city":"Pfalzgrafenweiler",
    "sg:phone":"+49 7445/85140",
    "sg:postcode":"72285",
    "sg:province":"Baden-W\u00fcrttemberg",
    "wof:name":"Hartmut Theurer Architekt",
    "wof:placetype":"venue"
},
  "geometry": {"coordinates":[8.5646886826,48.5256080627],"type":"Point"}
}