{
  "type": "Feature",
  "properties": {
    "iso:country":"DE",
    "sg:address":"Stiftstr. 5",
    "sg:city":"Kiel",
    "sg:phone":"+49 431/91880",
    "sg:postcode":"24103",
    "sg:province":"Schleswig-Holstein",
    "wof:name":"Gustav W\u00fcstenberg Ingenieur",
    "wof:placetype":"venue"
},
  "geometry": {"coordinates":[10.1260004044,54.3234062195],"type":"Point"}
}