{
  "type": "Feature",
  "properties": {
    "iso:country":"DE",
    "sg:address":"Kurf\u00fcrstenstr. 83 a",
    "sg:city":"Berlin",
    "sg:phone":"+49 30/2649160",
    "sg:postcode":"10787",
    "sg:province":"Berlin",
    "wof:name":"Klaus Kammann Dipl.-ing. Vfa Ges. Von Architekten Mbh",
    "wof:placetype":"venue"
},
  "geometry": {"coordinates":[13.344792366,52.5044517517],"type":"Point"}
}