{
  "type": "Feature",
  "properties": {
    "iso:country":"DE",
    "sg:address":"Koppersstr 29",
    "sg:city":"D\u00fcsseldorf",
    "sg:phone":"+49 211/501929",
    "sg:postcode":"40549",
    "sg:province":"Nordrhein-Westfalen",
    "wof:name":"Gts Gie\u00df-technische-sonderkeramik Gmbh & Co Kg",
    "wof:placetype":"venue"
},
  "geometry": {"coordinates":[6.7025,51.224781],"type":"Point"}
}