{
  "type": "Feature",
  "properties": {
    "iso:country":"DE",
    "sg:address":"Siegstr. 4",
    "sg:city":"Sankt Augustin",
    "sg:phone":"+49 2241/311579",
    "sg:postcode":"53757",
    "sg:province":"Nordrhein-Westfalen",
    "wof:name":"Karl Josef G\u00f6rtz",
    "wof:placetype":"venue"
},
  "geometry": {"coordinates":[7.1692538261,50.7818336487],"type":"Point"}
}