{
  "type": "Feature",
  "properties": {
    "iso:country":"DE",
    "sg:address":"Freiherr-vom-Stein-Str. 12",
    "sg:city":"M\u00fchlheim",
    "sg:phone":"+49 6108/69799",
    "sg:postcode":"63165",
    "sg:province":"Hessen",
    "wof:name":"W. Adam",
    "wof:placetype":"venue"
},
  "geometry": {"coordinates":[8.855597,50.100594],"type":"Point"}
}