{
  "type": "Feature",
  "properties": {
    "iso:country":"DE",
    "sg:address":"Ro\u00dfbachstr. 17",
    "sg:city":"Ravensburg",
    "sg:postcode":"88212",
    "sg:province":"Baden-W\u00fcrttemberg",
    "wof:name":"Terra Concept Gesellschaft F\u00fcr Grundeigentum Mbh",
    "wof:placetype":"venue"
},
  "geometry": {"coordinates":[9.6163749695,47.7807044983],"type":"Point"}
}