{
  "type": "Feature",
  "properties": {
    "iso:country":"DE",
    "sg:address":"Neukruger Str. 67 a",
    "sg:city":"G\u00fcstrow",
    "sg:postcode":"18273",
    "sg:province":"Mecklenburg-Vorpommern",
    "wof:name":"Volkssolidarit\u00e4t Hotel Strandkrone Gmbh & Co. Kg",
    "wof:placetype":"venue"
},
  "geometry": {"coordinates":[12.1871767044,53.8013839722],"type":"Point"}
}