{
  "type": "Feature",
  "properties": {
    "iso:country":"DE",
    "sg:address":"Hauptstr. 39",
    "sg:city":"M\u00fcnzenberg",
    "sg:phone":"+49 6033/68886",
    "sg:postcode":"35516",
    "sg:province":"Hessen",
    "wof:name":"Heidrun Just-becker Krankengymnastin",
    "wof:placetype":"venue"
},
  "geometry": {"coordinates":[8.730148,50.462749],"type":"Point"}
}