{
  "type": "Feature",
  "properties": {
    "iso:country":"DE",
    "sg:address":"Euskirchener Str. 36",
    "sg:city":"Bonn",
    "sg:phone":"+49 228/623811",
    "sg:postcode":"53121",
    "sg:province":"Nordrhein-Westfalen",
    "wof:name":"Mathias Fa\u00dfbender",
    "wof:placetype":"venue"
},
  "geometry": {"coordinates":[7.0676050186,50.7244529724],"type":"Point"}
}