{
  "type": "Feature",
  "properties": {
    "iso:country":"DE",
    "sg:address":"Rathausplatz 10-12",
    "sg:city":"Ludwigshafen",
    "sg:phone":"+49 621/511017",
    "sg:postcode":"67059",
    "sg:province":"Rheinland-Pfalz",
    "wof:name":"Escom Computer Vertriebs-gmbh",
    "wof:placetype":"venue"
},
  "geometry": {"coordinates":[8.4452753067,49.4855117798],"type":"Point"}
}