{
  "type": "Feature",
  "properties": {
    "iso:country":"DE",
    "sg:address":"Am B\u00fcscherhof 18",
    "sg:city":"Leichlingen",
    "sg:postcode":"42799",
    "sg:province":"Nordrhein-Westfalen",
    "wof:name":"Nemesis Liegenschaften Ag",
    "wof:placetype":"venue"
},
  "geometry": {"coordinates":[7.0182061195,51.1019210815],"type":"Point"}
}