{
  "type": "Feature",
  "properties": {
    "iso:country":"DE",
    "sg:address":"R\u00f6merhof",
    "sg:city":"Piesport",
    "sg:postcode":"54498",
    "sg:province":"Rheinland-Pfalz",
    "wof:name":"Weinkellerei St. Christina Gmbh",
    "wof:placetype":"venue"
},
  "geometry": {"coordinates":[6.9172081947,49.8739585876],"type":"Point"}
}