{
  "type": "Feature",
  "properties": {
    "iso:country":"DE",
    "sg:address":"Schlo\u00dfstr. 7",
    "sg:city":"Rockenhausen",
    "sg:phone":"+49 6361/1020",
    "sg:postcode":"67806",
    "sg:province":"Rheinland-Pfalz",
    "wof:name":"Schlo\u00df-apotheke",
    "wof:placetype":"venue"
},
  "geometry": {"coordinates":[7.819917,49.629333],"type":"Point"}
}