{
  "type": "Feature",
  "properties": {
    "iso:country":"DE",
    "sg:address":"Hintersulgen 12",
    "sg:city":"Schramberg",
    "sg:phone":"+49 7422/8783",
    "sg:postcode":"78713",
    "sg:province":"Baden-W\u00fcrttemberg",
    "wof:name":"M. Pfaff",
    "wof:placetype":"venue"
},
  "geometry": {"coordinates":[8.425624,48.218338],"type":"Point"}
}