{
  "type": "Feature",
  "properties": {
    "iso:country":"DE",
    "sg:address":"Peter-Rosegger-Str. 20",
    "sg:city":"Passau",
    "sg:phone":"+49 851/6626",
    "sg:postcode":"94036",
    "sg:province":"Bayern",
    "wof:name":"Seidl Gmbh",
    "wof:placetype":"venue"
},
  "geometry": {"coordinates":[13.382487,48.576687],"type":"Point"}
}