{
  "type": "Feature",
  "properties": {
    "iso:country":"DE",
    "sg:address":"Cr\u00f6n 18",
    "sg:city":"Krefeld",
    "sg:phone":"+49 2151/540344",
    "sg:postcode":"47809",
    "sg:province":"Nordrhein-Westfalen",
    "wof:name":"G\u00fcnther W\u00e4ckers",
    "wof:placetype":"venue"
},
  "geometry": {"coordinates":[6.613493,51.333321],"type":"Point"}
}