{
  "type": "Feature",
  "properties": {
    "iso:country":"DE",
    "sg:address":"Schwachhauser Heerstr. 361",
    "sg:city":"Bremen",
    "sg:postcode":"28211",
    "sg:province":"Bremen",
    "wof:name":"Avf Anlage- Verm\u00f6gens- Und Finanzberatungs- Ag",
    "wof:placetype":"venue"
},
  "geometry": {"coordinates":[8.8674297333,53.0910186768],"type":"Point"}
}