{
  "type": "Feature",
  "properties": {
    "iso:country":"DE",
    "sg:address":"Leverkuser Str. 21",
    "sg:city":"Frankfurt",
    "sg:phone":"+49 69/30852945",
    "sg:postcode":"65929",
    "sg:province":"Hessen",
    "wof:name":"Suna Backwaren Gmbh",
    "wof:placetype":"venue"
},
  "geometry": {"coordinates":[8.542447,50.101009],"type":"Point"}
}