{
  "type": "Feature",
  "properties": {
    "iso:country":"DE",
    "sg:address":"Griengasse 6",
    "sg:city":"L\u00f6rrach",
    "sg:phone":"+49 7621/10124",
    "sg:postcode":"79540",
    "sg:province":"Baden-W\u00fcrttemberg",
    "wof:name":"Wolfgang Sch\u00e4fer",
    "wof:placetype":"venue"
},
  "geometry": {"coordinates":[7.663336,47.60561],"type":"Point"}
}