{
  "type": "Feature",
  "properties": {
    "iso:country":"DE",
    "sg:address":"Hochschulstr. 1",
    "sg:city":"Darmstadt",
    "sg:phone":"+49 6151/161",
    "sg:postcode":"64289",
    "sg:province":"Hessen",
    "wof:name":"Institut F. Psychologie",
    "wof:placetype":"venue"
},
  "geometry": {"coordinates":[8.6562814713,49.8773155212],"type":"Point"}
}