{
  "type": "Feature",
  "properties": {
    "iso:country":"DE",
    "sg:address":"Birkenacker",
    "sg:city":"Greiz",
    "sg:phone":"+49 3661/675760",
    "sg:postcode":"07973",
    "sg:province":"Th\u00fcringen",
    "wof:name":"Spartenheim",
    "wof:placetype":"venue"
},
  "geometry": {"coordinates":[12.2168807983,50.6489143372],"type":"Point"}
}