{
  "type": "Feature",
  "properties": {
    "iso:country":"DE",
    "sg:address":"Karst\u00e4dter Str. 33",
    "sg:city":"Postlin",
    "sg:phone":"+49 38797/51057",
    "sg:postcode":"19357",
    "sg:province":"Brandenburg",
    "wof:name":"Atk Bau Gmbh",
    "wof:placetype":"venue"
},
  "geometry": {"coordinates":[11.745806,53.17411],"type":"Point"}
}