{
  "type": "Feature",
  "properties": {
    "iso:country":"DE",
    "sg:address":"Fritz-Reuter-Weg 9",
    "sg:city":"Dabel",
    "sg:phone":"+49 38485/3050",
    "sg:postcode":"19406",
    "sg:province":"Mecklenburg-Vorpommern",
    "wof:name":"Frank Teschner",
    "wof:placetype":"venue"
},
  "geometry": {"coordinates":[11.8975610733,53.6644515991],"type":"Point"}
}