{
  "type": "Feature",
  "properties": {
    "iso:country":"DE",
    "sg:address":"Dom\u00e4nenweg 2a",
    "sg:city":"Bad Lauterberg",
    "sg:phone":"+49 5524/92130",
    "sg:postcode":"37431",
    "sg:province":"Niedersachsen",
    "wof:name":"Fouchs Ambiente Exclusive Wohnkonzepte Gmbh",
    "wof:placetype":"venue"
},
  "geometry": {"coordinates":[10.412711,51.622986],"type":"Point"}
}