{
  "type": "Feature",
  "properties": {
    "iso:country":"DE",
    "sg:address":"G\u00fcstower Str. 13",
    "sg:city":"Prenzlau",
    "sg:phone":"+49 3984/718466",
    "sg:postcode":"17291",
    "sg:province":"Brandenburg",
    "wof:name":"Cafeteria",
    "wof:placetype":"venue"
},
  "geometry": {"coordinates":[13.826822,53.308739],"type":"Point"}
}