{
  "type": "Feature",
  "properties": {
    "iso:country":"DE",
    "sg:address":"Moosfelder Ring 2",
    "sg:city":"Arnsberg",
    "sg:phone":"+49 2932/24861",
    "sg:postcode":"59755",
    "sg:province":"Nordrhein-Westfalen",
    "wof:name":"Edith Sch\u00e4fer-wieckowski",
    "wof:placetype":"venue"
},
  "geometry": {"coordinates":[7.9861831665,51.4644966125],"type":"Point"}
}