{
  "type": "Feature",
  "properties": {
    "iso:country":"DE",
    "sg:address":"Hauptstr. 37a",
    "sg:city":"Ohlsbach",
    "sg:phone":"+49 7803/2469",
    "sg:postcode":"77797",
    "sg:province":"Baden-W\u00fcrttemberg",
    "wof:name":"Bekleidungshaus Benz Inh. Diane Huber",
    "wof:placetype":"venue"
},
  "geometry": {"coordinates":[7.994479,48.429546],"type":"Point"}
}