{
  "type": "Feature",
  "properties": {
    "iso:country":"DE",
    "sg:address":"Herrengarten 2",
    "sg:city":"Remptendorf",
    "sg:postcode":"07368",
    "sg:province":"Th\u00fcringen",
    "wof:name":"Der Fr\u00f6hliche Laden Inh. M. Fr\u00f6hlich",
    "wof:placetype":"venue"
},
  "geometry": {"coordinates":[11.658857,50.529755],"type":"Point"}
}