{
  "type": "Feature",
  "properties": {
    "iso:country":"DE",
    "sg:address":"Damerowstra\u00dfe 5-8",
    "sg:city":"Berlin",
    "sg:phone":"+49 30/47530648",
    "sg:postcode":"13857",
    "sg:province":"Berlin",
    "wof:name":"Friseursalon Bea Wendorff",
    "wof:placetype":"venue"
},
  "geometry": {"coordinates":[13.416496,52.572189],"type":"Point"}
}