{
  "type": "Feature",
  "properties": {
    "iso:country":"DE",
    "sg:address":"Isoldestr. 11",
    "sg:city":"Berlin",
    "sg:phone":"+49 30/8592876",
    "sg:postcode":"12159",
    "sg:province":"Berlin",
    "wof:name":"Erwin P\u00f6pplow Inh. Horst P\u00f6ppler",
    "wof:placetype":"venue"
},
  "geometry": {"coordinates":[13.331328392,52.4771003723],"type":"Point"}
}