{
  "type": "Feature",
  "properties": {
    "iso:country":"DE",
    "sg:address":"Schm\u00e4hingen",
    "sg:city":"N\u00f6rdlingen",
    "sg:phone":"+49 9081/9187",
    "sg:postcode":"86720",
    "sg:province":"Bayern",
    "wof:name":"Hans Hubel",
    "wof:placetype":"venue"
},
  "geometry": {"coordinates":[10.4905338287,48.8511695862],"type":"Point"}
}