{
  "type": "Feature",
  "properties": {
    "iso:country":"DE",
    "sg:address":"Gabelsbergerstr. 11",
    "sg:city":"Heppenheim",
    "sg:phone":"+49 6252/3147",
    "sg:postcode":"64646",
    "sg:province":"Hessen",
    "wof:name":"Friedrich Frank",
    "wof:placetype":"venue"
},
  "geometry": {"coordinates":[8.6420536041,49.6376113892],"type":"Point"}
}