{
  "type": "Feature",
  "properties": {
    "iso:country":"DE",
    "sg:address":"Eisenzahnstr. 43",
    "sg:city":"Berlin",
    "sg:phone":"+49 30/8734344",
    "sg:postcode":"10709",
    "sg:province":"Berlin",
    "wof:name":"Mewi Kowalewski & Co.",
    "wof:placetype":"venue"
},
  "geometry": {"coordinates":[13.3049030304,52.4913635254],"type":"Point"}
}