{
  "type": "Feature",
  "properties": {
    "iso:country":"DE",
    "sg:address":"Walter-Flex-Str 5",
    "sg:city":"Bubenreuth",
    "sg:phone":"+49 9131/22411",
    "sg:postcode":"91088",
    "sg:province":"Bayern",
    "wof:name":"Herbert H\u00fcbsch",
    "wof:placetype":"venue"
},
  "geometry": {"coordinates":[11.015776,49.624969],"type":"Point"}
}