{
  "type": "Feature",
  "properties": {
    "iso:country":"DE",
    "sg:address":"An der Tongrube 9",
    "sg:city":"Wunstorf",
    "sg:phone":"+49 5031/73518",
    "sg:postcode":"31515",
    "sg:province":"Niedersachsen",
    "wof:name":"Manfred Tschiersch",
    "wof:placetype":"venue"
},
  "geometry": {"coordinates":[9.47748,52.425037],"type":"Point"}
}