{
  "type": "Feature",
  "properties": {
    "iso:country":"DE",
    "sg:address":"Zum Schacht III 3",
    "sg:city":"Bergkamen",
    "sg:phone":"+49 2389/537057",
    "sg:postcode":"59192",
    "sg:province":"Nordrhein-Westfalen",
    "wof:name":"Heiler Design Gmbh",
    "wof:placetype":"venue"
},
  "geometry": {"coordinates":[7.655103,51.642857],"type":"Point"}
}