{
  "type": "Feature",
  "properties": {
    "iso:country":"DE",
    "sg:address":"Heidter Berg 38",
    "sg:city":"Wuppertal",
    "sg:phone":"+49 202/556613",
    "sg:postcode":"42289",
    "sg:province":"Nordrhein-Westfalen",
    "wof:name":"Pizzeria Apollon",
    "wof:placetype":"venue"
},
  "geometry": {"coordinates":[7.2082500458,51.2695579529],"type":"Point"}
}