{
  "type": "Feature",
  "properties": {
    "iso:country":"DE",
    "sg:address":"Hinrichsdorf 5",
    "sg:city":"Rostock",
    "sg:phone":"+49 381/669601",
    "sg:postcode":"18146",
    "sg:province":"Mecklenburg-Vorpommern",
    "wof:name":"Babke-technik Dr. Ing. Georg Babke",
    "wof:placetype":"venue"
},
  "geometry": {"coordinates":[12.164406,54.139339],"type":"Point"}
}