{
  "type": "Feature",
  "properties": {
    "iso:country":"DE",
    "sg:address":"Werderstr. 23-25",
    "sg:city":"Mannheim",
    "sg:phone":"+49 621/42330",
    "sg:postcode":"68165",
    "sg:province":"Baden-W\u00fcrttemberg",
    "wof:name":"Tema Gesellschaft F\u00fcr Marketing-service Mbh",
    "wof:placetype":"venue"
},
  "geometry": {"coordinates":[8.479549,49.482857],"type":"Point"}
}