{
  "type": "Feature",
  "properties": {
    "iso:country":"DE",
    "sg:address":"Vor Den Siebenburgen 54-66",
    "sg:city":"K\u00f6ln",
    "sg:phone":"+49 4922/1327061",
    "sg:postcode":"50676",
    "sg:province":"Nordrhein-Westfalen",
    "wof:name":"Dhk Fachgro\u00dfhandlung Dio Hemmersbach Gmbh & Co. Kg",
    "wof:placetype":"venue"
},
  "geometry": {"coordinates":[6.9498109818,50.9273986816],"type":"Point"}
}