{
  "type": "Feature",
  "properties": {
    "iso:country":"DE",
    "sg:address":"Friedrich-Ebert-Str. 51",
    "sg:city":"D\u00fcsseldorf",
    "sg:phone":"+49 211/354997",
    "sg:postcode":"40210",
    "sg:province":"Nordrhein-Westfalen",
    "wof:name":"J\u00fcngst-automaten Gmbh",
    "wof:placetype":"venue"
},
  "geometry": {"coordinates":[6.790749073,51.2209968567],"type":"Point"}
}