{
  "type": "Feature",
  "properties": {
    "iso:country":"DE",
    "sg:address":"Bl\u00fctenweg 1",
    "sg:city":"Diedorf",
    "sg:phone":"+49 8238/2732",
    "sg:postcode":"86420",
    "sg:province":"Bayern",
    "wof:name":"Josef Karle",
    "wof:placetype":"venue"
},
  "geometry": {"coordinates":[10.7789287567,48.3549880981],"type":"Point"}
}