{
  "type": "Feature",
  "properties": {
    "iso:country":"DE",
    "sg:address":"Spesbacher Str. 28",
    "sg:city":"Ramstein-Miesenbach",
    "sg:phone":"+49 6371/52556",
    "sg:postcode":"66877",
    "sg:province":"Rheinland-Pfalz",
    "wof:name":"Renate Schneider",
    "wof:placetype":"venue"
},
  "geometry": {"coordinates":[7.552035,49.446217],"type":"Point"}
}