{
  "type": "Feature",
  "properties": {
    "iso:country":"DE",
    "sg:address":"Gesandtenstr. 7",
    "sg:city":"Regensburg",
    "sg:phone":"+49 941/5841463",
    "sg:postcode":"93047",
    "sg:province":"Bayern",
    "wof:name":"Lachseminare",
    "wof:placetype":"venue"
},
  "geometry": {"coordinates":[12.092651,49.01836],"type":"Point"}
}