{
  "type": "Feature",
  "properties": {
    "iso:country":"DE",
    "sg:address":"Steifensandstr. 8",
    "sg:city":"Berlin",
    "sg:postcode":"14057",
    "sg:province":"Berlin",
    "wof:name":"Berliner Presse- Und Informationsdienste",
    "wof:placetype":"venue"
},
  "geometry": {"coordinates":[13.2950296402,52.5081863403],"type":"Point"}
}