{
  "type": "Feature",
  "properties": {
    "iso:country":"DE",
    "sg:address":"Kirchstr. 36",
    "sg:city":"Obertshausen",
    "sg:phone":"+49 6104/42344",
    "sg:postcode":"63179",
    "sg:province":"Hessen",
    "wof:name":"E. Emge",
    "wof:placetype":"venue"
},
  "geometry": {"coordinates":[8.851034,50.070049],"type":"Point"}
}