{
  "type": "Feature",
  "properties": {
    "iso:country":"DE",
    "sg:address":"Westerm\u00fchlstr. 13",
    "sg:city":"M\u00fcnchen",
    "sg:phone":"+49 89/2604866",
    "sg:postcode":"80469",
    "sg:province":"Bayern",
    "wof:name":"Jochen Suppe",
    "wof:placetype":"venue"
},
  "geometry": {"coordinates":[11.570243,48.128498],"type":"Point"}
}