{
  "type": "Feature",
  "properties": {
    "iso:country":"DE",
    "sg:address":"B\u00e4rensteinstr. 20",
    "sg:city":"Berlin",
    "sg:phone":"+49 30/54378303",
    "sg:postcode":"12685",
    "sg:province":"Berlin",
    "wof:name":"Kaisers Verbrauchermarkt",
    "wof:placetype":"venue"
},
  "geometry": {"coordinates":[13.566034317,52.5416641235],"type":"Point"}
}