{
  "type": "Feature",
  "properties": {
    "iso:country":"DE",
    "sg:address":"Hauptstr. 50",
    "sg:city":"Linden",
    "sg:phone":"+49 4836/1656",
    "sg:postcode":"25791",
    "sg:province":"Schleswig-Holstein",
    "wof:name":"K.-d. Vehrs",
    "wof:placetype":"venue"
},
  "geometry": {"coordinates":[9.1881866455,54.2528610229],"type":"Point"}
}