{
  "type": "Feature",
  "properties": {
    "iso:country":"DE",
    "sg:address":"Walk\u00fcrenstr. 13",
    "sg:city":"Germering",
    "sg:phone":"+49 89/842337",
    "sg:postcode":"82110",
    "sg:province":"Bayern",
    "wof:name":"Mittermaier Transporte Germering Gmbh",
    "wof:placetype":"venue"
},
  "geometry": {"coordinates":[11.3890810013,48.1381416321],"type":"Point"}
}