{
  "type": "Feature",
  "properties": {
    "iso:country":"DE",
    "sg:address":"Querfurter Str. 20",
    "sg:city":"Merseburg",
    "sg:phone":"+49 3461/203860",
    "sg:postcode":"06217",
    "sg:province":"Sachsen-Anhalt",
    "wof:name":"Klotz Metallbau Gmbh",
    "wof:placetype":"venue"
},
  "geometry": {"coordinates":[11.975606,51.371738],"type":"Point"}
}