{
  "type": "Feature",
  "properties": {
    "iso:country":"DE",
    "sg:address":"Winterbergstr. 86h",
    "sg:city":"Dresden",
    "sg:phone":"+49 351/2571154",
    "sg:postcode":"01237",
    "sg:province":"Sachsen",
    "wof:name":"Wilfried Schmieder",
    "wof:placetype":"venue"
},
  "geometry": {"coordinates":[13.79455,51.024689],"type":"Point"}
}