{
  "type": "Feature",
  "properties": {
    "iso:country":"DE",
    "sg:address":"Hopfengartenstr. 84",
    "sg:city":"Reutlingen",
    "sg:phone":"+49 7121/43573",
    "sg:postcode":"72766",
    "sg:province":"Baden-W\u00fcrttemberg",
    "wof:name":"M. Und I. R\u00f6sch",
    "wof:placetype":"venue"
},
  "geometry": {"coordinates":[9.2338066101,48.5160446167],"type":"Point"}
}