{
  "type": "Feature",
  "properties": {
    "iso:country":"DE",
    "sg:address":"Haldenstr. 1",
    "sg:city":"Marktredwitz",
    "sg:phone":"+49 9231/4877",
    "sg:postcode":"95615",
    "sg:province":"Bayern",
    "wof:name":"Tbg Transport Gmbh & Co. Kg",
    "wof:placetype":"venue"
},
  "geometry": {"coordinates":[12.0950078964,50.0161895752],"type":"Point"}
}