{
  "type": "Feature",
  "properties": {
    "iso:country":"DE",
    "sg:address":"Eleonorenstr. 2",
    "sg:city":"Heidesheim",
    "sg:phone":"+49 6132/5266",
    "sg:postcode":"55262",
    "sg:province":"Rheinland-Pfalz",
    "wof:name":"Genzler Weinlohnabf\u00fcllung Gmbh",
    "wof:placetype":"venue"
},
  "geometry": {"coordinates":[8.1154,49.994591],"type":"Point"}
}