{
  "type": "Feature",
  "properties": {
    "iso:country":"DE",
    "sg:address":"Jenaische Str. 74",
    "sg:city":"Uhlst\u00e4dt",
    "sg:phone":"+49 36742/62251",
    "sg:postcode":"07407",
    "sg:province":"Th\u00fcringen",
    "wof:name":"S. Bukwaj Immobilienmakler",
    "wof:placetype":"venue"
},
  "geometry": {"coordinates":[11.4733934402,50.743888855],"type":"Point"}
}