{
  "type": "Feature",
  "properties": {
    "iso:country":"DE",
    "sg:address":"K\u00fcpperssteg 1",
    "sg:city":"Geldern",
    "sg:phone":"+49 2831/6447",
    "sg:postcode":"47608",
    "sg:province":"Nordrhein-Westfalen",
    "wof:name":"Paul Vloet",
    "wof:placetype":"venue"
},
  "geometry": {"coordinates":[6.24386,51.496761],"type":"Point"}
}