{
  "type": "Feature",
  "properties": {
    "iso:country":"DE",
    "sg:address":"Osterfeldstr. 90",
    "sg:city":"Ismaning",
    "sg:phone":"+49 89/9607950",
    "sg:postcode":"85737",
    "sg:province":"Bayern",
    "wof:name":"G\u00dcnter Fentsch Tiefdruckformen Gmbh",
    "wof:placetype":"venue"
},
  "geometry": {"coordinates":[11.6848011017,48.2301902771],"type":"Point"}
}