{
  "type": "Feature",
  "properties": {
    "iso:country":"DE",
    "sg:address":"Hellpothstr. 10",
    "sg:city":"Schwerte",
    "sg:phone":"+49 2304/17729",
    "sg:postcode":"58239",
    "sg:province":"Nordrhein-Westfalen",
    "wof:name":"Ased Ambulanter Senioren- Und Familiendienst",
    "wof:placetype":"venue"
},
  "geometry": {"coordinates":[7.572447,51.441158],"type":"Point"}
}