{
  "type": "Feature",
  "properties": {
    "iso:country":"DE",
    "sg:address":"Breitgasse 2a",
    "sg:city":"Langg\u00f6ns",
    "sg:phone":"+49 6403/928780",
    "sg:postcode":"35428",
    "sg:province":"Hessen",
    "wof:name":"Bernhard Lapp Rechtsanwalt",
    "wof:placetype":"venue"
},
  "geometry": {"coordinates":[8.6602525711,50.4975280762],"type":"Point"}
}