{
  "type": "Feature",
  "properties": {
    "iso:country":"DE",
    "sg:address":"Reineckerstr. 4",
    "sg:city":"Chemnitz",
    "sg:postcode":"09126",
    "sg:province":"Sachsen",
    "wof:name":"Mehler U. Co. Inh. Friedhardt R\u00f6hrborn",
    "wof:placetype":"venue"
},
  "geometry": {"coordinates":[12.9431629181,50.8300476074],"type":"Point"}
}