{
  "type": "Feature",
  "properties": {
    "iso:country":"DE",
    "sg:address":"Stellastr. 34",
    "sg:city":"Drensteinfurt",
    "sg:phone":"+49 2538/1572",
    "sg:postcode":"48317",
    "sg:province":"Nordrhein-Westfalen",
    "wof:name":"Heitmann",
    "wof:placetype":"venue"
},
  "geometry": {"coordinates":[7.6875171661,51.8462486267],"type":"Point"}
}