{
  "type": "Feature",
  "properties": {
    "iso:country":"DE",
    "sg:address":"M\u00f6wenweg 2",
    "sg:city":"Braunschweig",
    "sg:phone":"+49 531/351775",
    "sg:postcode":"38108",
    "sg:province":"Niedersachsen",
    "wof:name":"Tennispoint Hondelage",
    "wof:placetype":"venue"
},
  "geometry": {"coordinates":[10.5884637833,52.309337616],"type":"Point"}
}