{
  "type": "Feature",
  "properties": {
    "iso:country":"DE",
    "sg:address":"Kappeler Str. 105",
    "sg:city":"D\u00fcsseldorf",
    "sg:phone":"+49 211/749301",
    "sg:postcode":"40597",
    "sg:province":"Nordrhein-Westfalen",
    "wof:name":"Carborundum Schleifmittelwerke Gmbh",
    "wof:placetype":"venue"
},
  "geometry": {"coordinates":[6.8605661392,51.1693382263],"type":"Point"}
}