{
  "type": "Feature",
  "properties": {
    "iso:country":"DE",
    "sg:address":"Alban-Berg-Str. 6 a",
    "sg:city":"R\u00f6srath",
    "sg:postcode":"51503",
    "sg:province":"Nordrhein-Westfalen",
    "wof:name":"Think Media Manfred Denker Gmbh",
    "wof:placetype":"venue"
},
  "geometry": {"coordinates":[7.1832480431,50.9007568359],"type":"Point"}
}