{
  "type": "Feature",
  "properties": {
    "iso:country":"DE",
    "sg:address":"Donatusstr. 151",
    "sg:city":"Pulheim",
    "sg:phone":"+49 2234/986498",
    "sg:postcode":"50259",
    "sg:province":"Nordrhein-Westfalen",
    "wof:name":"Hans R\u00fc\u00dfmann Industrie- Und Verpackungsservice Gmbh",
    "wof:placetype":"venue"
},
  "geometry": {"coordinates":[6.7990899086,50.9603309631],"type":"Point"}
}