{
  "type": "Feature",
  "properties": {
    "iso:country":"DE",
    "sg:address":"Westendallee 71",
    "sg:city":"Berlin",
    "sg:phone":"+49 30/3055054",
    "sg:postcode":"14052",
    "sg:province":"Berlin",
    "wof:name":"Anlac Consulting Verm\u00f6gens- Anlagevermittlung Gmbh",
    "wof:placetype":"venue"
},
  "geometry": {"coordinates":[13.2539844513,52.5195236206],"type":"Point"}
}