{
  "type": "Feature",
  "properties": {
    "iso:country":"DE",
    "sg:address":"Solitudestr. 235",
    "sg:city":"Stuttgart",
    "sg:phone":"+49 711/9898800",
    "sg:postcode":"70499",
    "sg:province":"Baden-W\u00fcrttemberg",
    "wof:name":"Widmann",
    "wof:placetype":"venue"
},
  "geometry": {"coordinates":[9.112591,48.814877],"type":"Point"}
}