{
  "type": "Feature",
  "properties": {
    "iso:country":"DE",
    "sg:address":"Th\u00fcringer Allee 9",
    "sg:city":"Sankt Augustin",
    "sg:postcode":"53757",
    "sg:province":"Nordrhein-Westfalen",
    "wof:name":"Mmc Markt Und Medien Consulting Gmbh",
    "wof:placetype":"venue"
},
  "geometry": {"coordinates":[7.1933860779,50.7598114014],"type":"Point"}
}