{
  "type": "Feature",
  "properties": {
    "iso:country":"DE",
    "sg:address":"Zschochersche Str 48b",
    "sg:city":"Leipzig",
    "sg:phone":"+49 341/4122021",
    "sg:postcode":"04229",
    "sg:province":"Sachsen",
    "wof:name":"Trident Zahntechnik Gmbh",
    "wof:placetype":"venue"
},
  "geometry": {"coordinates":[12.336565,51.329144],"type":"Point"}
}