{
  "type": "Feature",
  "properties": {
    "iso:country":"DE",
    "sg:address":"Kellerei 3",
    "sg:city":"Wehr",
    "sg:phone":"+49 2636/7104",
    "sg:postcode":"56653",
    "sg:province":"Rheinland-Pfalz",
    "wof:name":"B. Gerhartz",
    "wof:placetype":"venue"
},
  "geometry": {"coordinates":[7.210448,50.421448],"type":"Point"}
}