{
  "type": "Feature",
  "properties": {
    "iso:country":"DE",
    "sg:address":"Grossmarkthalle Am Hauptbahnhof",
    "sg:city":"Kassel",
    "sg:phone":"+49 4956/115211",
    "sg:postcode":"34117",
    "sg:province":"Hessen",
    "wof:name":"Erich Fasshauer Gmbh",
    "wof:placetype":"venue"
},
  "geometry": {"coordinates":[9.491211,51.311787],"type":"Point"}
}