{
  "type": "Feature",
  "properties": {
    "iso:country":"DE",
    "sg:address":"Keithstr. 10",
    "sg:city":"Berlin",
    "sg:phone":"+49 30/2183135",
    "sg:postcode":"10787",
    "sg:province":"Berlin",
    "wof:name":"Yokohama Haus Helmut Tymberg",
    "wof:placetype":"venue"
},
  "geometry": {"coordinates":[13.3461933136,52.5025367737],"type":"Point"}
}