{
  "type": "Feature",
  "properties": {
    "iso:country":"DE",
    "sg:address":"An der Chaussee 5",
    "sg:city":"Gro\u00df Nemerow",
    "sg:phone":"+49 39605/20278",
    "sg:postcode":"17094",
    "sg:province":"Mecklenburg-Vorpommern",
    "wof:name":"J. Kaube",
    "wof:placetype":"venue"
},
  "geometry": {"coordinates":[13.2344236374,53.4855461121],"type":"Point"}
}