{
  "type": "Feature",
  "properties": {
    "iso:country":"DE",
    "sg:address":"Geschwister-Scholl-Str. 24a",
    "sg:city":"Aue",
    "sg:phone":"+49 3771/51486",
    "sg:postcode":"08280",
    "sg:province":"Sachsen",
    "wof:name":"Harald Keller",
    "wof:placetype":"venue"
},
  "geometry": {"coordinates":[12.707531,50.589668],"type":"Point"}
}