{
  "type": "Feature",
  "properties": {
    "iso:country":"DE",
    "sg:address":"Alexanderstr. 167",
    "sg:city":"Stuttgart",
    "sg:phone":"+49 711/609092",
    "sg:postcode":"70180",
    "sg:province":"Baden-W\u00fcrttemberg",
    "wof:name":"Michael Sch\u00fcrmaier Architekt",
    "wof:placetype":"venue"
},
  "geometry": {"coordinates":[9.177542,48.764587],"type":"Point"}
}