{
  "type": "Feature",
  "properties": {
    "iso:country":"DE",
    "sg:address":"Siegener Str. 24 A",
    "sg:city":"Reichshof",
    "sg:phone":"+49 2297/1366",
    "sg:postcode":"51580",
    "sg:province":"Nordrhein-Westfalen",
    "wof:name":"Volker Marienhagen",
    "wof:placetype":"venue"
},
  "geometry": {"coordinates":[7.7421188354,50.9408569336],"type":"Point"}
}