{
  "type": "Feature",
  "properties": {
    "iso:country":"DE",
    "sg:address":"Soester Str. 8",
    "sg:city":"Wadersloh",
    "sg:phone":"+49 2520/1004",
    "sg:postcode":"59329",
    "sg:province":"Nordrhein-Westfalen",
    "wof:name":"Gastst\u00e4tte Helmut Steinhoff",
    "wof:placetype":"venue"
},
  "geometry": {"coordinates":[8.1619548798,51.731300354],"type":"Point"}
}