{
  "type": "Feature",
  "properties": {
    "iso:country":"DE",
    "sg:address":"Ringstr. 26",
    "sg:city":"Dorfprozelten",
    "sg:phone":"+49 9392/7383",
    "sg:postcode":"97904",
    "sg:province":"Bayern",
    "wof:name":"C. Horndasch",
    "wof:placetype":"venue"
},
  "geometry": {"coordinates":[9.3803930283,49.7804222107],"type":"Point"}
}