{
  "type": "Feature",
  "properties": {
    "iso:country":"DE",
    "sg:address":"Schulstr. 16",
    "sg:city":"Geisa",
    "sg:postcode":"36419",
    "sg:province":"Th\u00fcringen",
    "wof:name":"Katholisches Pfarramt Geisa",
    "wof:placetype":"venue"
},
  "geometry": {"coordinates":[9.9488763809,50.7150230408],"type":"Point"}
}