{
  "type": "Feature",
  "properties": {
    "iso:country":"DE",
    "sg:address":"Lindenstr. 14",
    "sg:city":"Niersbach",
    "sg:phone":"+49 6508/476",
    "sg:postcode":"54518",
    "sg:province":"Rheinland-Pfalz",
    "wof:name":"Alfons Follmann Kunststoff- Fabrikation Gmbh",
    "wof:placetype":"venue"
},
  "geometry": {"coordinates":[6.749045,49.928879],"type":"Point"}
}