{
  "type": "Feature",
  "properties": {
    "iso:country":"DE",
    "sg:address":"Nellenbadstr. 10",
    "sg:city":"Stockach",
    "sg:phone":"+49 7771/1235",
    "sg:postcode":"78333",
    "sg:province":"Baden-W\u00fcrttemberg",
    "wof:name":"China-restaurant Tai Fat",
    "wof:placetype":"venue"
},
  "geometry": {"coordinates":[9.0032272339,47.8532104492],"type":"Point"}
}