{
  "type": "Feature",
  "properties": {
    "iso:country":"DE",
    "sg:address":"Ohlerfeldstr. 2",
    "sg:city":"M\u00f6nchengladbach",
    "sg:phone":"+49 2161/541883",
    "sg:postcode":"41069",
    "sg:province":"Nordrhein-Westfalen",
    "wof:name":"Haus Ohlerfeld",
    "wof:placetype":"venue"
},
  "geometry": {"coordinates":[6.4195051193,51.1783180237],"type":"Point"}
}