{
  "type": "Feature",
  "properties": {
    "iso:country":"DE",
    "sg:address":"Bahnhofstr. 47",
    "sg:city":"Penzberg",
    "sg:phone":"+49 8856/7899",
    "sg:postcode":"82377",
    "sg:province":"Bayern",
    "wof:name":"Gasthof Berggeist Gmbh",
    "wof:placetype":"venue"
},
  "geometry": {"coordinates":[11.3783903122,47.7541503906],"type":"Point"}
}