{
  "type": "Feature",
  "properties": {
    "iso:country":"DE",
    "sg:address":"Wolfgangstr. 17",
    "sg:city":"M\u00fcnchen",
    "sg:phone":"+49 89/4483408",
    "sg:postcode":"81667",
    "sg:province":"Bayern",
    "wof:name":"J. Samweber & E. Wimmer",
    "wof:placetype":"venue"
},
  "geometry": {"coordinates":[11.600807,48.133015],"type":"Point"}
}