{
  "type": "Feature",
  "properties": {
    "iso:country":"DE",
    "sg:address":"Ellerndamm 2",
    "sg:city":"Elmshorn",
    "sg:phone":"+49 4121/87315",
    "sg:postcode":"25335",
    "sg:province":"Schleswig-Holstein",
    "wof:name":"Ralf Hegewald",
    "wof:placetype":"venue"
},
  "geometry": {"coordinates":[9.6628952026,53.7643852234],"type":"Point"}
}