{
  "type": "Feature",
  "properties": {
    "iso:country":"DE",
    "sg:address":"Auenstr. 26",
    "sg:city":"M\u00fcnchen",
    "sg:phone":"+49 8807/285",
    "sg:postcode":"80469",
    "sg:province":"Bayern",
    "wof:name":"Robert Richter",
    "wof:placetype":"venue"
},
  "geometry": {"coordinates":[11.5729198456,48.1269607544],"type":"Point"}
}