{
  "type": "Feature",
  "properties": {
    "iso:country":"DE",
    "sg:address":"M\u00fchlbacher Str. 4",
    "sg:city":"Eppingen",
    "sg:phone":"+49 7262/4384",
    "sg:postcode":"75031",
    "sg:province":"Baden-W\u00fcrttemberg",
    "wof:name":"Venezia",
    "wof:placetype":"venue"
},
  "geometry": {"coordinates":[8.90542,49.134949],"type":"Point"}
}