{
  "type": "Feature",
  "properties": {
    "iso:country":"DE",
    "sg:address":"Salinenstr. 17",
    "sg:city":"Bad Kreuznach",
    "sg:phone":"+49 671/31867",
    "sg:postcode":"55543",
    "sg:province":"Rheinland-Pfalz",
    "wof:name":"Cafe Wonsyld Gmbh",
    "wof:placetype":"venue"
},
  "geometry": {"coordinates":[7.8617858887,49.841632843],"type":"Point"}
}