{
  "type": "Feature",
  "properties": {
    "iso:country":"DE",
    "sg:address":"M\u00fchlenstr. 21",
    "sg:city":"Wenzendorf",
    "sg:phone":"+49 4165/21400",
    "sg:postcode":"21279",
    "sg:province":"Niedersachsen",
    "wof:name":"Mms Marine Motor Service Gmbh",
    "wof:placetype":"venue"
},
  "geometry": {"coordinates":[9.77772,53.349388],"type":"Point"}
}