{
  "type": "Feature",
  "properties": {
    "iso:country":"DE",
    "sg:address":"Rheinstr. 22 a",
    "sg:city":"Bocholt",
    "sg:phone":"+49 2871/8519",
    "sg:postcode":"46395",
    "sg:province":"Nordrhein-Westfalen",
    "wof:name":"Rheinsch\u00e4nke",
    "wof:placetype":"venue"
},
  "geometry": {"coordinates":[6.6238641739,51.8287010193],"type":"Point"}
}