{
  "type": "Feature",
  "properties": {
    "iso:country":"DE",
    "sg:address":"Breitenbuscher Weg 7",
    "sg:city":"R\u00fcthen",
    "sg:phone":"+49 2952/1647",
    "sg:postcode":"59602",
    "sg:province":"Nordrhein-Westfalen",
    "wof:name":"Heinrich Kr\u00e4mer",
    "wof:placetype":"venue"
},
  "geometry": {"coordinates":[8.431732,51.494991],"type":"Point"}
}