{
  "type": "Feature",
  "properties": {
    "iso:country":"DE",
    "sg:address":"Unterm Busch2",
    "sg:city":"Radevormwald",
    "sg:phone":"+49 2195/931981",
    "sg:postcode":"42477",
    "sg:province":"Nordrhein-Westfalen",
    "wof:name":"Defcon5",
    "wof:placetype":"venue"
},
  "geometry": {"coordinates":[7.3532252312,51.2249259949],"type":"Point"}
}