{
  "type": "Feature",
  "properties": {
    "iso:country":"DE",
    "sg:address":"Werkstr 1",
    "sg:city":"\u00dcbach-Palenberg",
    "sg:phone":"+49 2451/903000",
    "sg:postcode":"52531",
    "sg:province":"Nordrhein-Westfalen",
    "wof:name":"Willy Schuler Gmbh & Co Kg",
    "wof:placetype":"venue"
},
  "geometry": {"coordinates":[6.138857,50.914539],"type":"Point"}
}