{
  "type": "Feature",
  "properties": {
    "iso:country":"DE",
    "sg:address":"Weidbergstr. 20/22",
    "sg:city":"Suhl",
    "sg:postcode":"98527",
    "sg:province":"Th\u00fcringen",
    "wof:name":"Innovations- Und Technologiepark Suhl Gmbh",
    "wof:placetype":"venue"
},
  "geometry": {"coordinates":[10.7067756653,50.5908889771],"type":"Point"}
}