{
  "type": "Feature",
  "properties": {
    "iso:country":"DE",
    "sg:address":"Mooswiesenweg 16",
    "sg:city":"Landshut",
    "sg:phone":"+49 871/61099",
    "sg:postcode":"84034",
    "sg:province":"Bayern",
    "wof:name":"Franz Widmann Festzeltbetrieb Gmbh",
    "wof:placetype":"venue"
},
  "geometry": {"coordinates":[12.1315326691,48.5417022705],"type":"Point"}
}