{
  "type": "Feature",
  "properties": {
    "iso:country":"DE",
    "sg:address":"Von-der-Pfordten-Str. 9",
    "sg:city":"M\u00fcnchen",
    "sg:phone":"+49 89/581069",
    "sg:postcode":"80687",
    "sg:province":"Bayern",
    "wof:name":"Christian Schmitt Ingenieur",
    "wof:placetype":"venue"
},
  "geometry": {"coordinates":[11.4968490601,48.1425018311],"type":"Point"}
}