{
  "type": "Feature",
  "properties": {
    "iso:country":"DE",
    "sg:address":"Rheinh\u00e4user Str. 18",
    "sg:city":"Altlu\u00dfheim",
    "sg:phone":"+49 6205/32019",
    "sg:postcode":"68804",
    "sg:province":"Baden-W\u00fcrttemberg",
    "wof:name":"Bruno Schmidt",
    "wof:placetype":"venue"
},
  "geometry": {"coordinates":[8.4995126724,49.3010635376],"type":"Point"}
}