{
  "type": "Feature",
  "properties": {
    "iso:country":"DE",
    "sg:address":"Kynastweg 11 b",
    "sg:city":"Radebeul",
    "sg:phone":"+49 351/8383481",
    "sg:postcode":"01445",
    "sg:province":"Sachsen",
    "wof:name":"Bodo Aust",
    "wof:placetype":"venue"
},
  "geometry": {"coordinates":[13.60404,51.124001],"type":"Point"}
}