{
  "type": "Feature",
  "properties": {
    "iso:country":"DE",
    "sg:address":"Hofgut Maxau",
    "sg:city":"Karlsruhe",
    "sg:phone":"+49 721/552269",
    "sg:postcode":"76187",
    "sg:province":"Baden-W\u00fcrttemberg",
    "wof:name":"Windm\u00fchlenberg Karlsruhe",
    "wof:placetype":"venue"
},
  "geometry": {"coordinates":[8.3443698883,49.0303955078],"type":"Point"}
}