{
  "type": "Feature",
  "properties": {
    "iso:country":"DE",
    "sg:address":"Rosa-Luxemburg-Str. 4",
    "sg:city":"Leipzig",
    "sg:postcode":"04103",
    "sg:province":"Sachsen",
    "wof:name":"Meb Bahndienstleistungen Gmbh S\u00fcd",
    "wof:placetype":"venue"
},
  "geometry": {"coordinates":[12.387875,51.343735],"type":"Point"}
}