{
  "type": "Feature",
  "properties": {
    "iso:country":"DE",
    "sg:address":"Biederbacher Str. 9",
    "sg:city":"Wolframs-Eschenbach",
    "sg:phone":"+49 9875/721",
    "sg:postcode":"91639",
    "sg:province":"Bayern",
    "wof:name":"J. Gehret",
    "wof:placetype":"venue"
},
  "geometry": {"coordinates":[10.7252397537,49.2229728699],"type":"Point"}
}