{
  "type": "Feature",
  "properties": {
    "iso:country":"DE",
    "sg:address":"Nossener Str.",
    "sg:city":"Oschatz",
    "sg:phone":"+49 3435/921075",
    "sg:postcode":"04758",
    "sg:province":"Sachsen",
    "wof:name":"Walter Hoche",
    "wof:placetype":"venue"
},
  "geometry": {"coordinates":[13.123855,51.289543],"type":"Point"}
}