{
  "type": "Feature",
  "properties": {
    "iso:country":"DE",
    "sg:address":"Zielheimer Str. 27",
    "sg:city":"Schwandorf",
    "sg:phone":"+49 9431/62481",
    "sg:postcode":"92421",
    "sg:province":"Bayern",
    "wof:name":"Josef Huml",
    "wof:placetype":"venue"
},
  "geometry": {"coordinates":[12.098723,49.271023],"type":"Point"}
}