{
  "type": "Feature",
  "properties": {
    "iso:country":"DE",
    "sg:address":"Tal\u00e4ckerstra\u00dfe",
    "sg:city":"Stuttgart",
    "sg:phone":"+49 711/80608815",
    "sg:postcode":"70437",
    "sg:province":"Baden-W\u00fcrttemberg",
    "wof:name":"Mayer Und M\u00fcller Steuerberater Stuttgart",
    "wof:placetype":"venue"
},
  "geometry": {"coordinates":[9.189855,48.83807],"type":"Point"}
}