{
  "type": "Feature",
  "properties": {
    "iso:country":"DE",
    "sg:address":"Daimlerstr 26",
    "sg:city":"Monheim",
    "sg:phone":"+49 2173/9505",
    "sg:postcode":"40789",
    "sg:province":"Nordrhein-Westfalen",
    "wof:name":"Sunon-schukat Electronic Vertriebs Gmbh",
    "wof:placetype":"venue"
},
  "geometry": {"coordinates":[6.894977,51.105358],"type":"Point"}
}