{
  "type": "Feature",
  "properties": {
    "iso:country":"DE",
    "sg:address":"M\u00fchlenstr. 8",
    "sg:city":"Emlichheim",
    "sg:phone":"+49 5943/82344",
    "sg:postcode":"49824",
    "sg:province":"Niedersachsen",
    "wof:name":"Volzeler Masseur",
    "wof:placetype":"venue"
},
  "geometry": {"coordinates":[6.853198,52.610668],"type":"Point"}
}