{
  "type": "Feature",
  "properties": {
    "iso:country":"DE",
    "sg:address":"Altacher Str. 8",
    "sg:city":"Barbing",
    "sg:phone":"+49 9481/90100",
    "sg:postcode":"93092",
    "sg:province":"Bayern",
    "wof:name":"Wolfgang Werner",
    "wof:placetype":"venue"
},
  "geometry": {"coordinates":[12.3058633804,49.0098228455],"type":"Point"}
}