{
  "type": "Feature",
  "properties": {
    "iso:country":"DE",
    "sg:address":"Unter den Ulmen 75",
    "sg:city":"G\u00fctersloh",
    "sg:phone":"+49 5241/95000",
    "sg:postcode":"33330",
    "sg:province":"Nordrhein-Westfalen",
    "wof:name":"Hunke & Bullmann Gmbh",
    "wof:placetype":"venue"
},
  "geometry": {"coordinates":[8.369118,51.896881],"type":"Point"}
}