{
  "type": "Feature",
  "properties": {
    "iso:country":"DE",
    "sg:address":"Pfarrleite 8",
    "sg:city":"Freudenberg",
    "sg:phone":"+49 9627/284",
    "sg:postcode":"92272",
    "sg:province":"Bayern",
    "wof:name":"Praxis B\u00f6hm Und Gro\u00df",
    "wof:placetype":"venue"
},
  "geometry": {"coordinates":[11.9743938446,49.48097229],"type":"Point"}
}