{
  "type": "Feature",
  "properties": {
    "iso:country":"DE",
    "sg:address":"Freiheit 7",
    "sg:city":"Mei\u00dfen",
    "sg:postcode":"01662",
    "sg:province":"Sachsen",
    "wof:name":"Evang. - Luth. Kirchenvorstand St. Afra Mei\u00dfen",
    "wof:placetype":"venue"
},
  "geometry": {"coordinates":[13.4685411453,51.1636962891],"type":"Point"}
}