{
  "type": "Feature",
  "properties": {
    "iso:country":"DE",
    "sg:address":"Hagener Str. 260",
    "sg:city":"Kreuztal",
    "sg:phone":"+49 2732/82538",
    "sg:postcode":"57223",
    "sg:province":"Nordrhein-Westfalen",
    "wof:name":"Linden-apotheke Krombach Inhaber: Hermann Weyandt E. K.",
    "wof:placetype":"venue"
},
  "geometry": {"coordinates":[7.957582,50.990566],"type":"Point"}
}