{
  "type": "Feature",
  "properties": {
    "iso:country":"DE",
    "sg:address":"Hagener Str. 390",
    "sg:city":"Gevelsberg",
    "sg:phone":"+49 2332/75700",
    "sg:postcode":"58285",
    "sg:province":"Nordrhein-Westfalen",
    "wof:name":"Objektplan Gmbh",
    "wof:placetype":"venue"
},
  "geometry": {"coordinates":[7.386487,51.336739],"type":"Point"}
}