{
  "type": "Feature",
  "properties": {
    "iso:country":"DE",
    "sg:address":"Mittelstr. 30",
    "sg:city":"Altenburg",
    "sg:phone":"+49 3447/505883",
    "sg:postcode":"04600",
    "sg:province":"Th\u00fcringen",
    "wof:name":"Wkv Wohnkauf- Und Verwaltungs Gmbh",
    "wof:placetype":"venue"
},
  "geometry": {"coordinates":[12.416683,50.980431],"type":"Point"}
}