{
  "type": "Feature",
  "properties": {
    "iso:country":"DE",
    "sg:address":"Gerhart-Hauptmann-Str. 1",
    "sg:city":"Heiden",
    "sg:phone":"+49 2867/95268",
    "sg:postcode":"46359",
    "sg:province":"Nordrhein-Westfalen",
    "wof:name":"Detlef Justus Rechtsanwalt",
    "wof:placetype":"venue"
},
  "geometry": {"coordinates":[6.9315347672,51.8311882019],"type":"Point"}
}