{
  "type": "Feature",
  "properties": {
    "iso:country":"DE",
    "sg:address":"Baustr. 24",
    "sg:city":"Wesel",
    "sg:phone":"+49 281/25212",
    "sg:postcode":"46483",
    "sg:province":"Nordrhein-Westfalen",
    "wof:name":"Taverne Funny",
    "wof:placetype":"venue"
},
  "geometry": {"coordinates":[6.6189460754,51.6590080261],"type":"Point"}
}