{
  "type": "Feature",
  "properties": {
    "iso:country":"DE",
    "sg:address":"Hauptstr. 107",
    "sg:city":"Gro\u00dflangheim",
    "sg:phone":"+49 9325/6719",
    "sg:postcode":"97320",
    "sg:province":"Bayern",
    "wof:name":"Malergesch\u00e4ft F\u00f6rth",
    "wof:placetype":"venue"
},
  "geometry": {"coordinates":[10.235825,49.754295],"type":"Point"}
}