{
  "type": "Feature",
  "properties": {
    "iso:country":"DE",
    "sg:address":"Heribertstr. 5",
    "sg:city":"Hallenberg",
    "sg:phone":"+49 2984/8246",
    "sg:postcode":"59969",
    "sg:province":"Nordrhein-Westfalen",
    "wof:name":"U. Gierse Ortsb\u00fcrgermeister Der",
    "wof:placetype":"venue"
},
  "geometry": {"coordinates":[8.6207332611,51.1110115051],"type":"Point"}
}