{
  "type": "Feature",
  "properties": {
    "iso:country":"DE",
    "sg:address":"Gutenbergstr. 4",
    "sg:city":"M\u00fcnzenberg",
    "sg:phone":"+49 6033/744260",
    "sg:postcode":"35516",
    "sg:province":"Hessen",
    "wof:name":"Frank Mann Volksf\u00fcrsorge Versicherungen",
    "wof:placetype":"venue"
},
  "geometry": {"coordinates":[8.7353000641,50.4619636536],"type":"Point"}
}