{
  "type": "Feature",
  "properties": {
    "iso:country":"DE",
    "sg:address":"Hauptstr. 1",
    "sg:city":"Sigmaringendorf",
    "sg:phone":"+49 7571/12381",
    "sg:postcode":"72517",
    "sg:province":"Baden-W\u00fcrttemberg",
    "wof:name":"Josef Aleker",
    "wof:placetype":"venue"
},
  "geometry": {"coordinates":[9.26208,48.067654],"type":"Point"}
}