{
  "type": "Feature",
  "properties": {
    "iso:country":"DE",
    "sg:address":"Maienweg 24",
    "sg:city":"Hamburg",
    "sg:phone":"+49 40/5114350",
    "sg:postcode":"22297",
    "sg:province":"Hamburg",
    "wof:name":"Bioclimatic Nord",
    "wof:placetype":"venue"
},
  "geometry": {"coordinates":[10.003127,53.613644],"type":"Point"}
}