{
  "type": "Feature",
  "properties": {
    "iso:country":"DE",
    "sg:address":"An der Alster 72",
    "sg:city":"Hamburg",
    "sg:phone":"+49 40/2888860",
    "sg:postcode":"20099",
    "sg:province":"Hamburg",
    "wof:name":"Atlantic Grill",
    "wof:placetype":"venue"
},
  "geometry": {"coordinates":[10.0051231384,53.5574150085],"type":"Point"}
}