{
  "type": "Feature",
  "properties": {
    "iso:country":"DE",
    "sg:address":"K\u00f6lner Str. 51",
    "sg:city":"Leverkusen",
    "sg:phone":"+49 2171/1800",
    "sg:postcode":"51379",
    "sg:province":"Nordrhein-Westfalen",
    "wof:name":"Edmund Birkel",
    "wof:placetype":"venue"
},
  "geometry": {"coordinates":[7.003880024,51.0644607544],"type":"Point"}
}