{
  "type": "Feature",
  "properties": {
    "iso:country":"DE",
    "sg:address":"Hauptstr. 123",
    "sg:city":"Wiesmoor",
    "sg:phone":"+49 4944/2324",
    "sg:postcode":"26639",
    "sg:province":"Niedersachsen",
    "wof:name":"Johann Dirks",
    "wof:placetype":"venue"
},
  "geometry": {"coordinates":[7.745366,53.420677],"type":"Point"}
}