{
  "type": "Feature",
  "properties": {
    "iso:country":"DE",
    "sg:address":"Westfalenstr. 101",
    "sg:city":"Iserlohn",
    "sg:phone":"+49 2371/68446",
    "sg:postcode":"58636",
    "sg:province":"Nordrhein-Westfalen",
    "wof:name":"Point",
    "wof:placetype":"venue"
},
  "geometry": {"coordinates":[7.7331361771,51.3744316101],"type":"Point"}
}