{
  "type": "Feature",
  "properties": {
    "iso:country":"DE",
    "sg:address":"Bocholt 7",
    "sg:city":"Nettetal",
    "sg:phone":"+49 2153/4328",
    "sg:postcode":"41334",
    "sg:province":"Nordrhein-Westfalen",
    "wof:name":"Cornelia Van Der Beek Steuerberaterin",
    "wof:placetype":"venue"
},
  "geometry": {"coordinates":[6.3051271439,51.3003883362],"type":"Point"}
}