{
  "type": "Feature",
  "properties": {
    "iso:country":"DE",
    "sg:address":"Am Leveloh 5",
    "sg:city":"Sprockh\u00f6vel",
    "sg:phone":"+49 2324/73464",
    "sg:postcode":"45549",
    "sg:province":"Nordrhein-Westfalen",
    "wof:name":"Cornelia Knaepper",
    "wof:placetype":"venue"
},
  "geometry": {"coordinates":[7.2440681458,51.3461761475],"type":"Point"}
}