{
  "type": "Feature",
  "properties": {
    "iso:country":"DE",
    "sg:address":"Fronderath 68",
    "sg:city":"Erkelenz",
    "sg:phone":"+49 2432/81047",
    "sg:postcode":"41812",
    "sg:province":"Nordrhein-Westfalen",
    "wof:name":"Peter K\u00f6rfer Finanzberater",
    "wof:placetype":"venue"
},
  "geometry": {"coordinates":[6.2233867645,51.1010551453],"type":"Point"}
}