{
  "type": "Feature",
  "properties": {
    "iso:country":"DE",
    "sg:address":"Bruchstr. 19",
    "sg:city":"Stendal",
    "sg:phone":"+49 3931/713924",
    "sg:postcode":"39576",
    "sg:province":"Sachsen-Anhalt",
    "wof:name":"P. Baumann Immobilienmakler",
    "wof:placetype":"venue"
},
  "geometry": {"coordinates":[11.8619947433,52.6069450378],"type":"Point"}
}