{
  "type": "Feature",
  "properties": {
    "iso:country":"DE",
    "sg:address":"Giebelscheidstr. 21",
    "sg:city":"Finnentrop",
    "sg:phone":"+49 2724/264",
    "sg:postcode":"57413",
    "sg:province":"Nordrhein-Westfalen",
    "wof:name":"H\u00fcmmler Verwaltungs Gmbh",
    "wof:placetype":"venue"
},
  "geometry": {"coordinates":[8.045199,51.194931],"type":"Point"}
}