{
  "type": "Feature",
  "properties": {
    "iso:country":"DE",
    "sg:address":"Altdorfer Str. 21a",
    "sg:city":"Landshut",
    "sg:phone":"+49 871/79786",
    "sg:postcode":"84032",
    "sg:province":"Bayern",
    "wof:name":"Georg Friedrich",
    "wof:placetype":"venue"
},
  "geometry": {"coordinates":[12.1381025314,48.5533790588],"type":"Point"}
}