{
  "type": "Feature",
  "properties": {
    "iso:country":"DE",
    "sg:address":"Kossaer Str 2",
    "sg:city":"Leipzig",
    "sg:phone":"+49 341/5242317",
    "sg:postcode":"04356",
    "sg:province":"Sachsen",
    "wof:name":"Asmus Baur\u00fcstung & Hebezeuge Gmbh",
    "wof:placetype":"venue"
},
  "geometry": {"coordinates":[12.3891849518,51.4104995728],"type":"Point"}
}