{
  "type": "Feature",
  "properties": {
    "iso:country":"DE",
    "sg:address":"Obergasse 1a",
    "sg:city":"Gro\u00dfrudestedt",
    "sg:phone":"+49 36204/60406",
    "sg:postcode":"99195",
    "sg:province":"Th\u00fcringen",
    "wof:name":"Vereinte Versicherungen",
    "wof:placetype":"venue"
},
  "geometry": {"coordinates":[11.1012001038,51.0908508301],"type":"Point"}
}