{
  "type": "Feature",
  "properties": {
    "iso:country":"DE",
    "sg:address":"Karl-Marx-Str. 23",
    "sg:city":"Ottweiler",
    "sg:phone":"+49 6824/7872",
    "sg:postcode":"66564",
    "sg:province":"Saarland",
    "wof:name":"Berthold Werth",
    "wof:placetype":"venue"
},
  "geometry": {"coordinates":[7.15261,49.403336],"type":"Point"}
}