{
  "type": "Feature",
  "properties": {
    "iso:country":"DE",
    "sg:address":"Siemensstr. 1-3",
    "sg:city":"Unterschlei\u00dfheim",
    "sg:phone":"+49 89/31779300",
    "sg:postcode":"85716",
    "sg:province":"Bayern",
    "wof:name":"Xp Express Parcel Systems Gmbh",
    "wof:placetype":"venue"
},
  "geometry": {"coordinates":[11.57849,48.289131],"type":"Point"}
}