{
  "type": "Feature",
  "properties": {
    "iso:country":"DE",
    "sg:address":"Sch\u00f6nbrunn am Lusen 321",
    "sg:city":"Hohenau",
    "sg:phone":"+49 8558/2527",
    "sg:postcode":"94545",
    "sg:province":"Bayern",
    "wof:name":"Hs Kfz Service Gmbh",
    "wof:placetype":"venue"
},
  "geometry": {"coordinates":[13.5354728699,48.8665466309],"type":"Point"}
}