{
  "type": "Feature",
  "properties": {
    "iso:country":"DE",
    "sg:address":"Taunusstr. 7",
    "sg:city":"Uhingen",
    "sg:phone":"+49 7161/31177",
    "sg:postcode":"73066",
    "sg:province":"Baden-W\u00fcrttemberg",
    "wof:name":"Rainer Kolb",
    "wof:placetype":"venue"
},
  "geometry": {"coordinates":[9.5811605453,48.686870575],"type":"Point"}
}