{
  "type": "Feature",
  "properties": {
    "iso:country":"DE",
    "sg:address":"Hasselsstr. 69",
    "sg:city":"D\u00fcsseldorf",
    "sg:phone":"+49 211/741738",
    "sg:postcode":"40599",
    "sg:province":"Nordrhein-Westfalen",
    "wof:name":"Ev. Pfarramt Ii Benroth",
    "wof:placetype":"venue"
},
  "geometry": {"coordinates":[6.871076107,51.1752281189],"type":"Point"}
}