{
  "type": "Feature",
  "properties": {
    "iso:country":"DE",
    "sg:address":"Lindenallee 9",
    "sg:city":"Biesendahlshof",
    "sg:postcode":"16306",
    "sg:province":"Brandenburg",
    "wof:name":"Mwm Management Gmbh",
    "wof:placetype":"venue"
},
  "geometry": {"coordinates":[14.2079820633,53.1957893372],"type":"Point"}
}