{
  "type": "Feature",
  "properties": {
    "iso:country":"DE",
    "sg:address":"Friedrich-Ebert-Str. 46",
    "sg:city":"Osthofen",
    "sg:phone":"+49 6242/2230",
    "sg:postcode":"67574",
    "sg:province":"Rheinland-Pfalz",
    "wof:name":"Weingut Arnsteiner G\u00fclt J. Glaser",
    "wof:placetype":"venue"
},
  "geometry": {"coordinates":[8.3214216232,49.703666687],"type":"Point"}
}