{
  "type": "Feature",
  "properties": {
    "iso:country":"DE",
    "sg:address":"Galileistr. 6",
    "sg:city":"Wiesbaden",
    "sg:phone":"+49 611/521139",
    "sg:postcode":"65193",
    "sg:province":"Hessen",
    "wof:name":"Merkur Versicherungsver- Mittlung Hildegard Rittner",
    "wof:placetype":"venue"
},
  "geometry": {"coordinates":[8.2295150757,50.0924034119],"type":"Point"}
}