{
  "type": "Feature",
  "properties": {
    "iso:country":"DE",
    "sg:address":"Lange Str. 52",
    "sg:city":"Liebenau",
    "sg:phone":"+49 5023/2535",
    "sg:postcode":"31618",
    "sg:province":"Niedersachsen",
    "wof:name":"Braukmann Und Graue",
    "wof:placetype":"venue"
},
  "geometry": {"coordinates":[9.097197,52.603065],"type":"Point"}
}