{
  "type": "Feature",
  "properties": {
    "iso:country":"DE",
    "sg:address":"Am Waldbad 4",
    "sg:city":"Lehrte",
    "sg:phone":"+49 5175/3666",
    "sg:postcode":"31275",
    "sg:province":"Niedersachsen",
    "wof:name":"Stadtbibliothek Lehrte Zweigstelle Arpke",
    "wof:placetype":"venue"
},
  "geometry": {"coordinates":[10.091669,52.387104],"type":"Point"}
}