{
  "type": "Feature",
  "properties": {
    "iso:country":"DE",
    "sg:address":"Drahthammerstr. 26",
    "sg:city":"Amberg",
    "sg:phone":"+49 9621/84177",
    "sg:postcode":"92224",
    "sg:province":"Bayern",
    "wof:name":"G. Bauer",
    "wof:placetype":"venue"
},
  "geometry": {"coordinates":[11.871236,49.435425],"type":"Point"}
}