{
  "type": "Feature",
  "properties": {
    "iso:country":"DE",
    "sg:address":"Glockengasse 12",
    "sg:city":"Frankenthal",
    "sg:phone":"+49 6233/26705",
    "sg:postcode":"67227",
    "sg:province":"Rheinland-Pfalz",
    "wof:name":"Claudia Lichtenberg Krankengymnastin",
    "wof:placetype":"venue"
},
  "geometry": {"coordinates":[8.351874,49.535797],"type":"Point"}
}