{
  "type": "Feature",
  "properties": {
    "iso:country":"DE",
    "sg:address":"Sch\u00f6nberger Str. 151",
    "sg:city":"Kiel",
    "sg:phone":"+49 431/727860",
    "sg:postcode":"24148",
    "sg:province":"Schleswig-Holstein",
    "wof:name":"Fiduz Versicherungskontor Wolfgang Beike & Partner",
    "wof:placetype":"venue"
},
  "geometry": {"coordinates":[10.1698551178,54.3232841492],"type":"Point"}
}