{
  "type": "Feature",
  "properties": {
    "iso:country":"DE",
    "sg:address":"Scheidtweilerstr. 17a",
    "sg:city":"K\u00f6ln",
    "sg:phone":"+49 221/541307",
    "sg:postcode":"50933",
    "sg:province":"Nordrhein-Westfalen",
    "wof:name":"Zeleken Gmbh",
    "wof:placetype":"venue"
},
  "geometry": {"coordinates":[6.905719,50.938496],"type":"Point"}
}