{
  "type": "Feature",
  "properties": {
    "iso:country":"DE",
    "sg:address":"Ostrowskistr. 16",
    "sg:city":"Magdeburg",
    "sg:phone":"+49 391/7221079",
    "sg:postcode":"39128",
    "sg:province":"Sachsen-Anhalt",
    "wof:name":"Renate Kolberg",
    "wof:placetype":"venue"
},
  "geometry": {"coordinates":[11.60018,52.14613],"type":"Point"}
}