{
  "type": "Feature",
  "properties": {
    "iso:country":"DE",
    "sg:address":"Hauptstr. 15",
    "sg:city":"Bodman-Ludwigshafen",
    "sg:phone":"+49 7773/344",
    "sg:postcode":"78351",
    "sg:province":"Baden-W\u00fcrttemberg",
    "wof:name":"Alois Kikel",
    "wof:placetype":"venue"
},
  "geometry": {"coordinates":[9.057839,47.818043],"type":"Point"}
}