{
  "type": "Feature",
  "properties": {
    "iso:country":"DE",
    "sg:address":"Nahensteig 182",
    "sg:city":"Landshut",
    "sg:phone":"+49 871/274968",
    "sg:postcode":"84028",
    "sg:province":"Bayern",
    "wof:name":"Adessa Moden Gmbh",
    "wof:placetype":"venue"
},
  "geometry": {"coordinates":[12.150862,48.532909],"type":"Point"}
}