{
  "type": "Feature",
  "properties": {
    "iso:country":"DE",
    "sg:address":"Osterrade 28",
    "sg:city":"Hamburg",
    "sg:phone":"+49 40/7384810",
    "sg:postcode":"21031",
    "sg:province":"Hamburg",
    "wof:name":"Walter Ausborn",
    "wof:placetype":"venue"
},
  "geometry": {"coordinates":[10.1835699081,53.5095252991],"type":"Point"}
}