{
  "type": "Feature",
  "properties": {
    "iso:country":"DE",
    "sg:address":"Neidlinger Str. 2",
    "sg:city":"Ostfildern",
    "sg:phone":"+49 711/454869",
    "sg:postcode":"73760",
    "sg:province":"Baden-W\u00fcrttemberg",
    "wof:name":"Krone",
    "wof:placetype":"venue"
},
  "geometry": {"coordinates":[9.2340230942,48.717502594],"type":"Point"}
}