{
  "type": "Feature",
  "properties": {
    "iso:country":"DE",
    "sg:address":"Azaleenstr.12",
    "sg:city":"Augsburg",
    "sg:phone":"+49 180",
    "sg:postcode":"86179",
    "sg:province":"Bayern",
    "wof:name":"Tb - Kurier Vermittlung B\u00e4rtle",
    "wof:placetype":"venue"
},
  "geometry": {"coordinates":[10.9024009705,48.2976951599],"type":"Point"}
}