{
  "type": "Feature",
  "properties": {
    "iso:country":"DE",
    "sg:address":"Richeyweg 18",
    "sg:city":"Stade",
    "sg:phone":"+49 4141/88310",
    "sg:postcode":"21682",
    "sg:province":"Niedersachsen",
    "wof:name":"Wolfgang Kraushaar",
    "wof:placetype":"venue"
},
  "geometry": {"coordinates":[9.438006,53.596729],"type":"Point"}
}