{
  "type": "Feature",
  "properties": {
    "iso:country":"DE",
    "sg:address":"Zwergenweg 1",
    "sg:city":"Leipzig",
    "sg:phone":"+49 341/8773162",
    "sg:postcode":"04277",
    "sg:province":"Sachsen",
    "wof:name":"Henry Dietze",
    "wof:placetype":"venue"
},
  "geometry": {"coordinates":[12.404621,51.30484],"type":"Point"}
}