{
  "type": "Feature",
  "properties": {
    "iso:country":"DE",
    "sg:address":"Nieder-Ramst\u00e4dter-Str. 45",
    "sg:city":"Ober-Ramstadt",
    "sg:phone":"+49 6154/630044",
    "sg:postcode":"64372",
    "sg:province":"Hessen",
    "wof:name":"Dream Flights Gerd Trautmann",
    "wof:placetype":"venue"
},
  "geometry": {"coordinates":[8.7398939133,49.8316764832],"type":"Point"}
}