{
  "type": "Feature",
  "properties": {
    "iso:country":"DE",
    "sg:address":"Oberberger Str. 54",
    "sg:city":"Meschede",
    "sg:phone":"+49 2903/6060",
    "sg:postcode":"59872",
    "sg:province":"Nordrhein-Westfalen",
    "wof:name":"Franz-josef Kayser-seiten",
    "wof:placetype":"venue"
},
  "geometry": {"coordinates":[8.161388,51.326317],"type":"Point"}
}