{
  "type": "Feature",
  "properties": {
    "iso:country":"DE",
    "sg:address":"Schillerstr. 7",
    "sg:city":"Rosenfeld",
    "sg:phone":"+49 7428/1424",
    "sg:postcode":"72348",
    "sg:province":"Baden-W\u00fcrttemberg",
    "wof:name":"Vereinsgastst\u00e4tte Sportverein Rosenfeld E. V.",
    "wof:placetype":"venue"
},
  "geometry": {"coordinates":[8.7160186768,48.287689209],"type":"Point"}
}