{
  "type": "Feature",
  "properties": {
    "iso:country":"DE",
    "sg:address":"Prager Str. 13",
    "sg:city":"Leipzig",
    "sg:postcode":"04103",
    "sg:province":"Sachsen",
    "wof:name":"Projekt S\u00fcd 9 Gesellschaft Zur Rekonstr.",
    "wof:placetype":"venue"
},
  "geometry": {"coordinates":[12.3930826187,51.3339347839],"type":"Point"}
}