{
  "type": "Feature",
  "properties": {
    "iso:country":"DE",
    "sg:address":"Annetteweg 11",
    "sg:city":"Marienm\u00fcnster",
    "sg:phone":"+49 5276/8724",
    "sg:postcode":"37696",
    "sg:province":"Nordrhein-Westfalen",
    "wof:name":"Helmut Hagel\u00fcken",
    "wof:placetype":"venue"
},
  "geometry": {"coordinates":[9.237455368,51.8193588257],"type":"Point"}
}