{
  "type": "Feature",
  "properties": {
    "iso:country":"DE",
    "sg:address":"Zum Ordenswald 71 a",
    "sg:city":"Neustadt",
    "sg:phone":"+49 6321/6247",
    "sg:postcode":"67435",
    "sg:province":"Rheinland-Pfalz",
    "wof:name":"Fritz Babelotzky",
    "wof:placetype":"venue"
},
  "geometry": {"coordinates":[8.172823,49.365063],"type":"Point"}
}