{
  "type": "Feature",
  "properties": {
    "iso:country":"DE",
    "sg:address":"Bellgasse 5",
    "sg:city":"Flonheim",
    "sg:phone":"+49 6734/8773",
    "sg:postcode":"55237",
    "sg:province":"Rheinland-Pfalz",
    "wof:name":"Ludwig Reitz",
    "wof:placetype":"venue"
},
  "geometry": {"coordinates":[8.0397138596,49.7875289917],"type":"Point"}
}