{
  "type": "Feature",
  "properties": {
    "iso:country":"DE",
    "sg:address":"Pommericher Weg 39",
    "sg:city":"Neidenbach",
    "sg:phone":"+49 6563/8203",
    "sg:postcode":"54657",
    "sg:province":"Rheinland-Pfalz",
    "wof:name":"Harald Kreutz",
    "wof:placetype":"venue"
},
  "geometry": {"coordinates":[6.5568399429,50.0937538147],"type":"Point"}
}