{
  "type": "Feature",
  "properties": {
    "iso:country":"DE",
    "sg:address":"Burgstr. 2",
    "sg:city":"M\u00f6nchengladbach",
    "sg:phone":"+49 2166/601061",
    "sg:postcode":"41199",
    "sg:province":"Nordrhein-Westfalen",
    "wof:name":"E. Gedenk",
    "wof:placetype":"venue"
},
  "geometry": {"coordinates":[6.4522352219,51.1338577271],"type":"Point"}
}