{
  "type": "Feature",
  "properties": {
    "iso:country":"DE",
    "sg:address":"Bernsteinstr. 40",
    "sg:city":"Altdorf",
    "sg:phone":"+49 871/32095",
    "sg:postcode":"84032",
    "sg:province":"Bayern",
    "wof:name":"Hans H. Brandstetter Ingenieur",
    "wof:placetype":"venue"
},
  "geometry": {"coordinates":[12.0936498642,48.5474739075],"type":"Point"}
}