{
  "type": "Feature",
  "properties": {
    "iso:country":"DE",
    "sg:address":"Merscheider Str. 161",
    "sg:city":"Solingen",
    "sg:phone":"+49 212/331150",
    "sg:postcode":"42699",
    "sg:province":"Nordrhein-Westfalen",
    "wof:name":"Merker & Heinzmann Gmbh",
    "wof:placetype":"venue"
},
  "geometry": {"coordinates":[7.0266017914,51.1654319763],"type":"Point"}
}