{
  "type": "Feature",
  "properties": {
    "iso:country":"DE",
    "sg:address":"Industriestr. 12",
    "sg:city":"Melle",
    "sg:phone":"+49 5422/98970",
    "sg:postcode":"49324",
    "sg:province":"Niedersachsen",
    "wof:name":"Frank Rokossa E. K.",
    "wof:placetype":"venue"
},
  "geometry": {"coordinates":[8.3550930023,52.1910743713],"type":"Point"}
}