{
  "type": "Feature",
  "properties": {
    "iso:country":"DE",
    "sg:city":"Br\u00fccken",
    "sg:postcode":"66904",
    "sg:province":"Rheinland-Pfalz",
    "wof:name":"G\u00fcnter Staab Inh. Steffen Seyler",
    "wof:placetype":"venue"
},
  "geometry": {"coordinates":[7.360853,49.432148],"type":"Point"}
}