{
  "type": "Feature",
  "properties": {
    "iso:country":"DE",
    "sg:address":"Senkingstr. 1",
    "sg:city":"Hildesheim",
    "sg:phone":"+49 5121/517048",
    "sg:postcode":"31137",
    "sg:province":"Niedersachsen",
    "wof:name":"Ro-mie Blechbearbeitung Gmbh",
    "wof:placetype":"venue"
},
  "geometry": {"coordinates":[9.940969,52.157883],"type":"Point"}
}