{
  "type": "Feature",
  "properties": {
    "iso:country":"DE",
    "sg:address":"Fontainengr. 150",
    "sg:city":"Bonn",
    "sg:phone":"+49 4922/8625090",
    "sg:postcode":"53125",
    "sg:province":"Nordrhein-Westfalen",
    "wof:name":"Lohmeier-deimel Ohg",
    "wof:placetype":"venue"
},
  "geometry": {"coordinates":[7.074415,50.680462],"type":"Point"}
}