{
  "type": "Feature",
  "properties": {
    "iso:country":"DE",
    "sg:address":"Obere Wallstr. 14",
    "sg:city":"Andernach",
    "sg:phone":"+49 2632/42865",
    "sg:postcode":"56626",
    "sg:province":"Rheinland-Pfalz",
    "wof:name":"Dress In",
    "wof:placetype":"venue"
},
  "geometry": {"coordinates":[7.402529,50.438618],"type":"Point"}
}