{
  "type": "Feature",
  "properties": {
    "iso:country":"DE",
    "sg:address":"Gottlieb-Daimler-Str 1",
    "sg:city":"Forst",
    "sg:phone":"+49 7251/81661",
    "sg:postcode":"76694",
    "sg:province":"Baden-W\u00fcrttemberg",
    "wof:name":"Eurovital L. Gundlach-bleuel",
    "wof:placetype":"venue"
},
  "geometry": {"coordinates":[8.578698,49.154457],"type":"Point"}
}