{
  "type": "Feature",
  "properties": {
    "iso:country":"DE",
    "sg:address":"Rossauer Str. 44",
    "sg:city":"Rossau",
    "sg:phone":"+49 4937/272941",
    "sg:postcode":"09661",
    "sg:province":"Sachsen",
    "wof:name":"Agrargenossenschaftmittweida E.g.",
    "wof:placetype":"venue"
},
  "geometry": {"coordinates":[13.034456,50.983791],"type":"Point"}
}