{
  "type": "Feature",
  "properties": {
    "iso:country":"DE",
    "sg:address":"Salzstr. 6",
    "sg:city":"Neuenburg",
    "sg:phone":"+49 7631/72291",
    "sg:postcode":"79395",
    "sg:province":"Baden-W\u00fcrttemberg",
    "wof:name":"Salmen",
    "wof:placetype":"venue"
},
  "geometry": {"coordinates":[7.5617442131,47.8146972656],"type":"Point"}
}