{
  "type": "Feature",
  "properties": {
    "iso:country":"DE",
    "sg:address":"Marktredwitzer Str.57",
    "sg:city":"Mitterteich",
    "sg:phone":"+49 9633",
    "sg:postcode":"95666",
    "sg:province":"Bayern",
    "wof:name":"Sportverein Mitterteich",
    "wof:placetype":"venue"
},
  "geometry": {"coordinates":[12.226551,49.948563],"type":"Point"}
}