{
  "type": "Feature",
  "properties": {
    "iso:country":"DE",
    "sg:address":"Feringastr.4",
    "sg:city":"Unterf\u00f6hring",
    "sg:phone":"+49 89/4623550",
    "sg:postcode":"85774",
    "sg:province":"Bayern",
    "wof:name":"Ltx (deutschland) Gmbh",
    "wof:placetype":"venue"
},
  "geometry": {"coordinates":[11.632576,48.178967],"type":"Point"}
}