{
  "type": "Feature",
  "properties": {
    "iso:country":"DE",
    "sg:address":"Ubostr. 21",
    "sg:city":"M\u00fcnchen",
    "sg:phone":"+49 89/8633553",
    "sg:postcode":"81245",
    "sg:province":"Bayern",
    "wof:name":"Ulrich K\u00f6bl",
    "wof:placetype":"venue"
},
  "geometry": {"coordinates":[11.4129190445,48.1589584351],"type":"Point"}
}