{
  "type": "Feature",
  "properties": {
    "iso:country":"DE",
    "sg:address":"Buchenberger Weg 2",
    "sg:city":"Kempten",
    "sg:phone":"+49 831/85806",
    "sg:postcode":"87439",
    "sg:province":"Bayern",
    "wof:name":"A. Koch",
    "wof:placetype":"venue"
},
  "geometry": {"coordinates":[10.278644,47.711613],"type":"Point"}
}