{
  "type": "Feature",
  "properties": {
    "iso:country":"DE",
    "sg:address":"Steinhagen 10",
    "sg:city":"Hattingen",
    "sg:phone":"+49 2324/27077",
    "sg:postcode":"45525",
    "sg:province":"Nordrhein-Westfalen",
    "wof:name":"Aktuell Verlags Gmbh",
    "wof:placetype":"venue"
},
  "geometry": {"coordinates":[7.1847548485,51.3971061707],"type":"Point"}
}