{
  "type": "Feature",
  "properties": {
    "iso:country":"DE",
    "sg:address":"Marktg\u00e4\u00dfchen 2",
    "sg:city":"Brand-Erbisdorf",
    "sg:phone":"+49 37322/2711",
    "sg:postcode":"09618",
    "sg:province":"Sachsen",
    "wof:name":"Knuspersch\u00e4nke",
    "wof:placetype":"venue"
},
  "geometry": {"coordinates":[13.3217439651,50.8697128296],"type":"Point"}
}