{
  "type": "Feature",
  "properties": {
    "iso:country":"DE",
    "sg:address":"Eislebener Str. 13",
    "sg:city":"Beesenstedt",
    "sg:phone":"+49 34773/8180",
    "sg:postcode":"06198",
    "sg:province":"Sachsen-Anhalt",
    "wof:name":"H. Boumans",
    "wof:placetype":"venue"
},
  "geometry": {"coordinates":[11.727678,51.56752],"type":"Point"}
}