{
  "type": "Feature",
  "properties": {
    "iso:country":"DE",
    "sg:address":"Gilgenburger Str. 22",
    "sg:city":"Berlin",
    "sg:phone":"+49 30/6458874",
    "sg:postcode":"12587",
    "sg:province":"Berlin",
    "wof:name":"Klaus Berger Architekt",
    "wof:placetype":"venue"
},
  "geometry": {"coordinates":[13.610204,52.454521],"type":"Point"}
}