{
  "type": "Feature",
  "properties": {
    "iso:country":"DE",
    "sg:address":"Zwieselbergsiedlung 5",
    "sg:city":"Zwiesel",
    "sg:phone":"+49 9922/60384",
    "sg:postcode":"94227",
    "sg:province":"Bayern",
    "wof:name":"Karl-h. Wallner",
    "wof:placetype":"venue"
},
  "geometry": {"coordinates":[13.2215356827,49.0056610107],"type":"Point"}
}