{
  "type": "Feature",
  "properties": {
    "iso:country":"DE",
    "sg:address":"Torgauer Str. 23",
    "sg:city":"Wurzen",
    "sg:phone":"+49 3425/90280",
    "sg:postcode":"04808",
    "sg:province":"Sachsen",
    "wof:name":"Ingenieur Wurzen Gmbh",
    "wof:placetype":"venue"
},
  "geometry": {"coordinates":[12.748495,51.370106],"type":"Point"}
}