{
  "type": "Feature",
  "properties": {
    "iso:country":"DE",
    "sg:address":"Hindenburgallee 1",
    "sg:city":"Malente",
    "sg:phone":"+49 4523/3268",
    "sg:postcode":"23714",
    "sg:province":"Schleswig-Holstein",
    "wof:name":"Restaurant La Grotta",
    "wof:placetype":"venue"
},
  "geometry": {"coordinates":[10.5497570038,54.1667900085],"type":"Point"}
}