{
  "type": "Feature",
  "properties": {
    "iso:country":"DE",
    "sg:address":"Mendelssohnstr. 11",
    "sg:city":"Zwenkau",
    "sg:postcode":"04442",
    "sg:province":"Sachsen",
    "wof:name":"Wichardt & Partner Beteiligungs Gmbh",
    "wof:placetype":"venue"
},
  "geometry": {"coordinates":[12.328841,51.22683],"type":"Point"}
}