{
  "type": "Feature",
  "properties": {
    "iso:country":"DE",
    "sg:address":"Vorderdeich 89",
    "sg:city":"Hamburg",
    "sg:phone":"+49 40/7233450",
    "sg:postcode":"21037",
    "sg:province":"Hamburg",
    "wof:name":"Klaus Lohnzweiger Rechtsanwalt",
    "wof:placetype":"venue"
},
  "geometry": {"coordinates":[10.1581449509,53.4688835144],"type":"Point"}
}