{
  "type": "Feature",
  "properties": {
    "iso:country":"DE",
    "sg:address":"Am Stadtwalde 99",
    "sg:city":"Rheine",
    "sg:phone":"+49 5971/986480",
    "sg:postcode":"48432",
    "sg:province":"Nordrhein-Westfalen",
    "wof:name":"Elko-zimmerei Gmbh",
    "wof:placetype":"venue"
},
  "geometry": {"coordinates":[7.4544758797,52.3030395508],"type":"Point"}
}