{
  "type": "Feature",
  "properties": {
    "iso:country":"DE",
    "sg:address":"Finkenweg 1",
    "sg:city":"Niedernberg",
    "sg:phone":"+49 6028/8497",
    "sg:postcode":"63843",
    "sg:province":"Bayern",
    "wof:name":"Rolf Nogaj",
    "wof:placetype":"venue"
},
  "geometry": {"coordinates":[9.1392345428,49.9201583862],"type":"Point"}
}