{
  "type": "Feature",
  "properties": {
    "iso:country":"DE",
    "sg:address":"Kirchplatz 12",
    "sg:city":"L\u00fcdinghausen",
    "sg:phone":"+49 2591/891870",
    "sg:postcode":"59348",
    "sg:province":"Nordrhein-Westfalen",
    "wof:name":"Lvm Versicherung Krebber & Bourichter",
    "wof:placetype":"venue"
},
  "geometry": {"coordinates":[7.4445672035,51.7710647583],"type":"Point"}
}