{
  "type": "Feature",
  "properties": {
    "iso:country":"DE",
    "sg:address":"Otto-Hahn-Str. 13",
    "sg:city":"Lohfelden",
    "sg:phone":"+49 561/950900",
    "sg:postcode":"34253",
    "sg:province":"Hessen",
    "wof:name":"Schnegelsberg Spielmann Verwaltungs-gmbh",
    "wof:placetype":"venue"
},
  "geometry": {"coordinates":[9.52915,51.280033],"type":"Point"}
}