{
  "type": "Feature",
  "properties": {
    "iso:country":"DE",
    "sg:address":"Heidestra\u00dfe 159",
    "sg:city":"Velbert",
    "sg:phone":"+49 2051",
    "sg:postcode":"42549",
    "sg:province":"Nordrhein-Westfalen",
    "wof:name":"Baustoffe Guth Gmbh & Co. Kg",
    "wof:placetype":"venue"
},
  "geometry": {"coordinates":[7.0335559845,51.3318138123],"type":"Point"}
}