{
  "type": "Feature",
  "properties": {
    "iso:country":"DE",
    "sg:address":"Luxemburgerallee 44",
    "sg:city":"Frankfurt",
    "sg:phone":"+49 69/432550",
    "sg:postcode":"60385",
    "sg:province":"Hessen",
    "wof:name":"Iaz Immobilienteam Kiessler & Co. Kg",
    "wof:placetype":"venue"
},
  "geometry": {"coordinates":[8.713968277,50.1174316406],"type":"Point"}
}