{
  "type": "Feature",
  "properties": {
    "iso:country":"DE",
    "sg:address":"Schillerstr. 57 b",
    "sg:city":"Marl",
    "sg:phone":"+49 2365/12858",
    "sg:postcode":"45768",
    "sg:province":"Nordrhein-Westfalen",
    "wof:name":"Gerald Hunger",
    "wof:placetype":"venue"
},
  "geometry": {"coordinates":[7.0813570023,51.6523132324],"type":"Point"}
}