{
  "type": "Feature",
  "properties": {
    "iso:country":"DE",
    "sg:address":"Gut Habbel",
    "sg:city":"Arnsberg",
    "sg:phone":"+49 2932/34255",
    "sg:postcode":"59757",
    "sg:province":"Nordrhein-Westfalen",
    "wof:name":"Ebel Verwaltungsges. Mbh",
    "wof:placetype":"venue"
},
  "geometry": {"coordinates":[7.9685211182,51.4217453003],"type":"Point"}
}