{
  "type": "Feature",
  "properties": {
    "iso:country":"DE",
    "sg:address":"Scherzachstr. 26",
    "sg:city":"Weingarten",
    "sg:phone":"+49 4975/143662",
    "sg:postcode":"88250",
    "sg:province":"Baden-W\u00fcrttemberg",
    "wof:name":"Welfen-verlag A. Gerstmayer & Co.",
    "wof:placetype":"venue"
},
  "geometry": {"coordinates":[9.6438808441,47.8051872253],"type":"Point"}
}