{
  "type": "Feature",
  "properties": {
    "iso:country":"DE",
    "sg:address":"Nordostpark 31",
    "sg:city":"N\u00fcrnberg",
    "sg:phone":"+49 911/9555590",
    "sg:postcode":"90411",
    "sg:province":"Bayern",
    "wof:name":"Graf Rechtsanw\u00e4lte",
    "wof:placetype":"venue"
},
  "geometry": {"coordinates":[11.1268310547,49.485294342],"type":"Point"}
}