{
  "type": "Feature",
  "properties": {
    "iso:country":"DE",
    "sg:address":"Schwelmer Str 20",
    "sg:city":"D\u00fcsseldorf",
    "sg:phone":"+49 211/96870",
    "sg:postcode":"40235",
    "sg:province":"Nordrhein-Westfalen",
    "wof:name":"Leve & Kobs Gmbh",
    "wof:placetype":"venue"
},
  "geometry": {"coordinates":[6.8185248375,51.2304420471],"type":"Point"}
}