{
  "type": "Feature",
  "properties": {
    "iso:country":"DE",
    "sg:address":"Rechterallee 45",
    "sg:city":"Rellingen",
    "sg:phone":"+49 4101/31629",
    "sg:postcode":"25462",
    "sg:province":"Schleswig-Holstein",
    "wof:name":"J. Rateike",
    "wof:placetype":"venue"
},
  "geometry": {"coordinates":[9.8776597977,53.6406135559],"type":"Point"}
}