{
  "type": "Feature",
  "properties": {
    "iso:country":"DE",
    "sg:address":"Stammstr. 7",
    "sg:city":"Bad D\u00fcrrheim",
    "sg:phone":"+49 7706/282",
    "sg:postcode":"78073",
    "sg:province":"Baden-W\u00fcrttemberg",
    "wof:name":"A. Heppler",
    "wof:placetype":"venue"
},
  "geometry": {"coordinates":[8.6353225708,47.991317749],"type":"Point"}
}