{
  "type": "Feature",
  "properties": {
    "iso:country":"DE",
    "sg:address":"Schulstr. 4",
    "sg:city":"R\u00fcdershausen",
    "sg:phone":"+49 5529/999740",
    "sg:postcode":"37434",
    "sg:province":"Niedersachsen",
    "wof:name":"Diedrich Bau Gmbh",
    "wof:placetype":"venue"
},
  "geometry": {"coordinates":[10.2680444717,51.5789337158],"type":"Point"}
}