{
  "type": "Feature",
  "properties": {
    "iso:country":"DE",
    "sg:address":"Am Bannweg 40a",
    "sg:city":"B\u00fchl",
    "sg:phone":"+49 7223/98350",
    "sg:postcode":"77815",
    "sg:province":"Baden-W\u00fcrttemberg",
    "wof:name":"Paula Schmid Steuerberaterin",
    "wof:placetype":"venue"
},
  "geometry": {"coordinates":[8.1391000748,48.6873016357],"type":"Point"}
}