{
  "type": "Feature",
  "properties": {
    "iso:country":"DE",
    "sg:address":"Industriestr. 15-17",
    "sg:city":"M\u00fclheim",
    "sg:phone":"+49 4965/34721",
    "sg:postcode":"54486",
    "sg:province":"Rheinland-Pfalz",
    "wof:name":"Johann M\u00dcller Kg",
    "wof:placetype":"venue"
},
  "geometry": {"coordinates":[7.0272932053,49.9107246399],"type":"Point"}
}