{
  "type": "Feature",
  "properties": {
    "iso:country":"DE",
    "sg:address":"Ohlerkamp 3",
    "sg:city":"M\u00f6nchengladbach",
    "sg:phone":"+49 2161/54523",
    "sg:postcode":"41069",
    "sg:province":"Nordrhein-Westfalen",
    "wof:name":"Konrad Apotheke Inh. Gracy. Kizhakethalackal",
    "wof:placetype":"venue"
},
  "geometry": {"coordinates":[6.422288,51.175797],"type":"Point"}
}