{
  "type": "Feature",
  "properties": {
    "iso:country":"DE",
    "sg:address":"Schleifm\u00fchleweg 30",
    "sg:city":"T\u00fcbingen",
    "sg:phone":"+49 7071/49918",
    "sg:postcode":"72070",
    "sg:province":"Baden-W\u00fcrttemberg",
    "wof:name":"Tina Lang Masseurin",
    "wof:placetype":"venue"
},
  "geometry": {"coordinates":[9.044948,48.520702],"type":"Point"}
}