{
  "type": "Feature",
  "properties": {
    "iso:country":"DE",
    "sg:address":"Oppener Str. 84",
    "sg:city":"W\u00fcrselen",
    "sg:phone":"+49 2405/91143",
    "sg:postcode":"52146",
    "sg:province":"Nordrhein-Westfalen",
    "wof:name":"Cornel Zimmermann",
    "wof:placetype":"venue"
},
  "geometry": {"coordinates":[6.139694,50.812847],"type":"Point"}
}