{
  "type": "Feature",
  "properties": {
    "iso:country":"DE",
    "sg:address":"Remigiusplatz 8",
    "sg:city":"Viersen",
    "sg:phone":"+49 2162/15782",
    "sg:postcode":"41747",
    "sg:province":"Nordrhein-Westfalen",
    "wof:name":"Gerd Frinken",
    "wof:placetype":"venue"
},
  "geometry": {"coordinates":[6.386425972,51.2560806274],"type":"Point"}
}