{
  "type": "Feature",
  "properties": {
    "iso:country":"DE",
    "sg:address":"L\u00fctzowstr 57",
    "sg:city":"Berlin",
    "sg:phone":"+49 30/23628136",
    "sg:postcode":"10785",
    "sg:province":"Berlin",
    "wof:name":"Posso Marketing Berlin!",
    "wof:placetype":"venue"
},
  "geometry": {"coordinates":[13.35412,52.505108],"type":"Point"}
}