{
  "type": "Feature",
  "properties": {
    "iso:country":"DE",
    "sg:address":"Bleckenstedter Str. 23b",
    "sg:city":"Salzgitter",
    "sg:phone":"+49 5341/65363",
    "sg:postcode":"38239",
    "sg:province":"Niedersachsen",
    "wof:name":"M\u00f6belhalle Fedrichs",
    "wof:placetype":"venue"
},
  "geometry": {"coordinates":[10.407306,52.178391],"type":"Point"}
}