{
  "type": "Feature",
  "properties": {
    "iso:country":"DE",
    "sg:address":"Karlstr. 65",
    "sg:city":"Tuttlingen",
    "sg:phone":"+49 7461/3534",
    "sg:postcode":"78532",
    "sg:province":"Baden-W\u00fcrttemberg",
    "wof:name":"Horst Bornemann",
    "wof:placetype":"venue"
},
  "geometry": {"coordinates":[8.8161048889,47.979850769],"type":"Point"}
}