{
  "type": "Feature",
  "properties": {
    "iso:country":"DE",
    "sg:address":"Schortental 24",
    "sg:city":"Eisenberg",
    "sg:phone":"+49 36691/7220",
    "sg:postcode":"07607",
    "sg:province":"Th\u00fcringen",
    "wof:name":"Bauelemente Gmbh F. J. Linzmeier",
    "wof:placetype":"venue"
},
  "geometry": {"coordinates":[11.911248,50.979885],"type":"Point"}
}