{
  "type": "Feature",
  "properties": {
    "iso:country":"DE",
    "sg:address":"H\u00f6nnetalstr. 46",
    "sg:city":"Hemer",
    "sg:phone":"+49 2372/14433",
    "sg:postcode":"58675",
    "sg:province":"Nordrhein-Westfalen",
    "wof:name":"Karl-heinz Stammeyer",
    "wof:placetype":"venue"
},
  "geometry": {"coordinates":[7.7726597786,51.3776626587],"type":"Point"}
}