{
  "type": "Feature",
  "properties": {
    "iso:country":"DE",
    "sg:address":"S\u00fcderquerweg 635",
    "sg:city":"Hamburg",
    "sg:phone":"+49 40/7373721",
    "sg:postcode":"21037",
    "sg:province":"Hamburg",
    "wof:name":"Bernd Tolzien",
    "wof:placetype":"venue"
},
  "geometry": {"coordinates":[10.12893,53.439892],"type":"Point"}
}