{
  "type": "Feature",
  "properties": {
    "iso:country":"DE",
    "sg:address":"Am Dickhaus 7",
    "sg:city":"Ratingen",
    "sg:phone":"+49 2102/896892",
    "sg:postcode":"40883",
    "sg:province":"Nordrhein-Westfalen",
    "wof:name":"C. M. I. Container Masters Gmbh",
    "wof:placetype":"venue"
},
  "geometry": {"coordinates":[6.8997969627,51.3224029541],"type":"Point"}
}