{
  "type": "Feature",
  "properties": {
    "iso:country":"DE",
    "sg:address":"Leopoldstr. 100",
    "sg:city":"M\u00fcnchen",
    "sg:postcode":"80802",
    "sg:province":"Bayern",
    "wof:name":"Igr-gesellschaft F\u00fcr Wohn- Und Gewerbebau Mbh",
    "wof:placetype":"venue"
},
  "geometry": {"coordinates":[11.5867090225,48.1647987366],"type":"Point"}
}