{
  "type": "Feature",
  "properties": {
    "iso:country":"DE",
    "sg:address":"Dr.-Gerlich-Str. 18",
    "sg:city":"Landshut",
    "sg:phone":"+49 871/79762",
    "sg:postcode":"84032",
    "sg:province":"Bayern",
    "wof:name":"Hildegard Radosai Krankengymnastin",
    "wof:placetype":"venue"
},
  "geometry": {"coordinates":[12.134513,48.550957],"type":"Point"}
}