{
  "type": "Feature",
  "properties": {
    "iso:country":"DE",
    "sg:address":"R\u00f6hrenfeldstr. 2",
    "sg:city":"Eging",
    "sg:phone":"+49 8544/8889",
    "sg:postcode":"94535",
    "sg:province":"Bayern",
    "wof:name":"Manfred Kroiss",
    "wof:placetype":"venue"
},
  "geometry": {"coordinates":[13.2640762329,48.7163238525],"type":"Point"}
}