{
  "type": "Feature",
  "properties": {
    "iso:country":"DE",
    "sg:address":"Dinkelsb\u00fchler Str 29",
    "sg:city":"M\u00fcnchen",
    "sg:phone":"+49 89/8712526",
    "sg:postcode":"81243",
    "sg:province":"Bayern",
    "wof:name":"Zelt-verleih Rinner",
    "wof:placetype":"venue"
},
  "geometry": {"coordinates":[11.4278259277,48.1504631042],"type":"Point"}
}