{
  "type": "Feature",
  "properties": {
    "iso:country":"DE",
    "sg:address":"Moltkestr. 2",
    "sg:city":"M\u00fchldorf",
    "sg:phone":"+49 8631/8047",
    "sg:postcode":"84453",
    "sg:province":"Bayern",
    "wof:name":"G\u00fcnther Und Elke Cziczek",
    "wof:placetype":"venue"
},
  "geometry": {"coordinates":[12.521428,48.246338],"type":"Point"}
}