{
  "type": "Feature",
  "properties": {
    "iso:country":"DE",
    "sg:address":"Johann-Walling-Str. 6",
    "sg:city":"Borken",
    "sg:phone":"+49 2861/3114",
    "sg:postcode":"46325",
    "sg:province":"Nordrhein-Westfalen",
    "wof:name":"Johanna S\u00f6hngen",
    "wof:placetype":"venue"
},
  "geometry": {"coordinates":[6.859056,51.844677],"type":"Point"}
}