{
  "type": "Feature",
  "properties": {
    "iso:country":"DE",
    "sg:address":"Karl-Marx-Str. 18",
    "sg:city":"Trier",
    "sg:phone":"+49 651/74522",
    "sg:postcode":"54290",
    "sg:province":"Rheinland-Pfalz",
    "wof:name":"Spinosi Restaurante",
    "wof:placetype":"venue"
},
  "geometry": {"coordinates":[6.6337537766,49.7530136108],"type":"Point"}
}