{
  "type": "Feature",
  "properties": {
    "iso:country":"DE",
    "sg:address":"Endenicher Allee 57",
    "sg:city":"Bonn",
    "sg:phone":"+49 228/622224",
    "sg:postcode":"53121",
    "sg:province":"Nordrhein-Westfalen",
    "wof:name":"Hans B\u00f6linger",
    "wof:placetype":"venue"
},
  "geometry": {"coordinates":[7.0784869194,50.7254905701],"type":"Point"}
}