{
  "type": "Feature",
  "properties": {
    "iso:country":"DE",
    "sg:address":"Fuggerstra\u00dfe 33",
    "sg:city":"Berlin",
    "sg:postcode":"10777",
    "sg:province":"Berlin",
    "wof:name":"Connection-berlin",
    "wof:placetype":"venue"
},
  "geometry": {"coordinates":[13.3427371979,52.4989700317],"type":"Point"}
}