{
  "type": "Feature",
  "properties": {
    "iso:country":"DE",
    "sg:address":"Toeplerstr. 5",
    "sg:city":"Berlin",
    "sg:phone":"+49 30/38399090",
    "sg:postcode":"13627",
    "sg:province":"Berlin",
    "wof:name":"Diakonie-station Charlottenburg Ggmbh",
    "wof:placetype":"venue"
},
  "geometry": {"coordinates":[13.2849798203,52.5380592346],"type":"Point"}
}