{
  "type": "Feature",
  "properties": {
    "iso:country":"DE",
    "sg:address":"Postfach 1461:: 74713 Buchen:: Germany.^^Walld\u00fcrner Str 17::",
    "sg:city":"Buchen",
    "sg:phone":"+49 6281/4060",
    "sg:postcode":"74722",
    "sg:province":"Baden-W\u00fcrttemberg",
    "wof:name":"Volksbank Franken Eg",
    "wof:placetype":"venue"
},
  "geometry": {"coordinates":[9.32316,49.521259],"type":"Point"}
}