{
  "type": "Feature",
  "properties": {
    "iso:country":"DE",
    "sg:address":"Sophienstr. 58",
    "sg:city":"Eisenach",
    "sg:phone":"+49 3691/23970",
    "sg:postcode":"99817",
    "sg:province":"Th\u00fcringen",
    "wof:name":"Thomas Helmboldt",
    "wof:placetype":"venue"
},
  "geometry": {"coordinates":[10.3247413635,50.9766464233],"type":"Point"}
}