{
  "type": "Feature",
  "properties": {
    "iso:country":"DE",
    "sg:address":"Bremer Str. 25",
    "sg:city":"Hohentengen",
    "sg:phone":"+49 7572/1005",
    "sg:postcode":"88367",
    "sg:province":"Baden-W\u00fcrttemberg",
    "wof:name":"Karl Binder",
    "wof:placetype":"venue"
},
  "geometry": {"coordinates":[9.362132,48.027843],"type":"Point"}
}