{
  "type": "Feature",
  "properties": {
    "iso:country":"DE",
    "sg:address":"Neust\u00e4dter Str. 20",
    "sg:city":"Viernheim",
    "sg:phone":"+49 6204/71583",
    "sg:postcode":"68519",
    "sg:province":"Hessen",
    "wof:name":"Katharina Hoock Hebamme",
    "wof:placetype":"venue"
},
  "geometry": {"coordinates":[8.560473,49.533104],"type":"Point"}
}