{
  "type": "Feature",
  "properties": {
    "iso:country":"DE",
    "sg:address":"Weststr. 7",
    "sg:city":"H\u00f6rstel-Dreierwalde",
    "sg:phone":"+49 4959/7891600",
    "sg:postcode":"48477",
    "sg:province":"Nordrhein-Westfalen",
    "wof:name":"Hermann Reckers-maschinenfabrik Gmbh & Co Kg",
    "wof:placetype":"venue"
},
  "geometry": {"coordinates":[7.500794,52.324665],"type":"Point"}
}