{
  "type": "Feature",
  "properties": {
    "iso:country":"DE",
    "sg:address":"Wasserburger Landstr. 254",
    "sg:city":"M\u00fcnchen",
    "sg:phone":"+49 89/4305248",
    "sg:postcode":"81827",
    "sg:province":"Bayern",
    "wof:name":"Reinhard Braun",
    "wof:placetype":"venue"
},
  "geometry": {"coordinates":[11.7073078156,48.1116294861],"type":"Point"}
}