{
  "type": "Feature",
  "properties": {
    "iso:country":"DE",
    "sg:address":"Im Schwarzbroich 1",
    "sg:city":"Odenthal",
    "sg:phone":"+49 4922/027579",
    "sg:postcode":"51519",
    "sg:province":"Nordrhein-Westfalen",
    "wof:name":"Spanier Spezialtransporte Gmbh",
    "wof:placetype":"venue"
},
  "geometry": {"coordinates":[7.1098241806,51.0153503418],"type":"Point"}
}