{
  "type": "Feature",
  "properties": {
    "iso:country":"DE",
    "sg:address":"Am Wald 1",
    "sg:city":"Krauthausen",
    "sg:phone":"+49 36926/90703",
    "sg:postcode":"99819",
    "sg:province":"Th\u00fcringen",
    "wof:name":"Steffen Witzmann",
    "wof:placetype":"venue"
},
  "geometry": {"coordinates":[10.2677812576,51.0175476074],"type":"Point"}
}