{
  "type": "Feature",
  "properties": {
    "iso:country":"DE",
    "sg:address":"Bismarckstr. 76",
    "sg:city":"Herford",
    "sg:postcode":"32049",
    "sg:province":"Nordrhein-Westfalen",
    "wof:name":"Kroatia- Gmbh",
    "wof:placetype":"venue"
},
  "geometry": {"coordinates":[8.6936979294,52.1208877563],"type":"Point"}
}