{
  "type": "Feature",
  "properties": {
    "iso:country":"DE",
    "sg:address":"Ochtmisser Str. 1",
    "sg:city":"L\u00fcneburg",
    "sg:phone":"+49 4131/62952",
    "sg:postcode":"21339",
    "sg:province":"Niedersachsen",
    "wof:name":"Helga Reikowski",
    "wof:placetype":"venue"
},
  "geometry": {"coordinates":[10.3905611038,53.2747459412],"type":"Point"}
}