{
  "type": "Feature",
  "properties": {
    "iso:country":"DE",
    "sg:address":"Wulffstr. 7",
    "sg:city":"Berlin",
    "sg:phone":"+49 30/3918077",
    "sg:postcode":"12165",
    "sg:province":"Berlin",
    "wof:name":"Rechtsanwaltskanzlei Harald Sch\u00e4fer Und",
    "wof:placetype":"venue"
},
  "geometry": {"coordinates":[13.316576004,52.4545211792],"type":"Point"}
}