{
  "type": "Feature",
  "properties": {
    "iso:country":"DE",
    "sg:address":"Ober-Werber-Str. 10",
    "sg:city":"Waldeck",
    "sg:phone":"+49 5634/240",
    "sg:postcode":"34513",
    "sg:province":"Hessen",
    "wof:name":"Wilhelm Neuhaus",
    "wof:placetype":"venue"
},
  "geometry": {"coordinates":[9.061482,51.207039],"type":"Point"}
}