{
  "type": "Feature",
  "properties": {
    "iso:country":"DE",
    "sg:address":"Bergiusstr. 95",
    "sg:city":"Bremen",
    "sg:phone":"+49 421/271042",
    "sg:postcode":"28357",
    "sg:province":"Bremen",
    "wof:name":"Verein F\u00fcr Evang. Mmission. Arbeit Auch Unter Sozial",
    "wof:placetype":"venue"
},
  "geometry": {"coordinates":[8.8962583542,53.1108169556],"type":"Point"}
}