{
  "type": "Feature",
  "properties": {
    "iso:country":"DE",
    "sg:address":"Am Alten Broich 127",
    "sg:city":"Langenfeld",
    "sg:phone":"+49 2173/989666",
    "sg:postcode":"40764",
    "sg:province":"Nordrhein-Westfalen",
    "wof:name":"Struwe Schleiftechnik",
    "wof:placetype":"venue"
},
  "geometry": {"coordinates":[6.935702,51.114731],"type":"Point"}
}