{
  "type": "Feature",
  "properties": {
    "iso:country":"DE",
    "sg:address":"Lorenzer Str. 2",
    "sg:city":"Lappersdorf",
    "sg:phone":"+49 941/80836",
    "sg:postcode":"93138",
    "sg:province":"Bayern",
    "wof:name":"Gasthof Erich Pr\u00f6\u00dfl",
    "wof:placetype":"venue"
},
  "geometry": {"coordinates":[12.0538196564,49.0728912354],"type":"Point"}
}