{
  "type": "Feature",
  "properties": {
    "iso:country":"DE",
    "sg:address":"Hainkopsweg 1 A",
    "sg:city":"Burgwedel",
    "sg:phone":"+49 5139/88588",
    "sg:postcode":"30938",
    "sg:province":"Niedersachsen",
    "wof:name":"Marita Bamberg Steuerberaterin",
    "wof:placetype":"venue"
},
  "geometry": {"coordinates":[9.9057483673,52.4954795837],"type":"Point"}
}