{
  "type": "Feature",
  "properties": {
    "iso:country":"DE",
    "sg:address":"Annastr. 27",
    "sg:city":"Ichenhausen",
    "sg:phone":"+49 8223/5454",
    "sg:postcode":"89335",
    "sg:province":"Bayern",
    "wof:name":"Nuri Altinci",
    "wof:placetype":"venue"
},
  "geometry": {"coordinates":[10.308259964,48.3700294495],"type":"Point"}
}