{
  "type": "Feature",
  "properties": {
    "iso:country":"DE",
    "sg:address":"Semerteichstr. 56",
    "sg:city":"Dortmund",
    "sg:phone":"+49 231/411345",
    "sg:postcode":"44141",
    "sg:province":"Nordrhein-Westfalen",
    "wof:name":"Reifen Reckert Gmbh",
    "wof:placetype":"venue"
},
  "geometry": {"coordinates":[7.4975161552,51.5006370544],"type":"Point"}
}