{
  "type": "Feature",
  "properties": {
    "iso:country":"DE",
    "sg:address":"Dahler Str. 61",
    "sg:city":"Solingen",
    "sg:phone":"+49 212/53759",
    "sg:postcode":"42653",
    "sg:province":"Nordrhein-Westfalen",
    "wof:name":"Hartmut Adolphs",
    "wof:placetype":"venue"
},
  "geometry": {"coordinates":[7.071168,51.196648],"type":"Point"}
}