{
  "type": "Feature",
  "properties": {
    "iso:country":"DE",
    "sg:address":"Breslauer Str. 25",
    "sg:city":"Espelkamp",
    "sg:phone":"+49 5772/91070",
    "sg:postcode":"32339",
    "sg:province":"Nordrhein-Westfalen",
    "wof:name":"Koch Electronics Gmbh",
    "wof:placetype":"venue"
},
  "geometry": {"coordinates":[8.6269016266,52.3776245117],"type":"Point"}
}