{
  "type": "Feature",
  "properties": {
    "iso:country":"DE",
    "sg:address":"Gro\u00dfenhainer Str. 63",
    "sg:city":"Mei\u00dfen",
    "sg:phone":"+49 3521/76180",
    "sg:postcode":"01662",
    "sg:province":"Sachsen",
    "wof:name":"Maler-quaas Gmbh & Co. Kg",
    "wof:placetype":"venue"
},
  "geometry": {"coordinates":[13.49096,51.167824],"type":"Point"}
}