{
  "type": "Feature",
  "properties": {
    "iso:country":"DE",
    "sg:address":"Wieslesweg 25",
    "sg:city":"Albstadt",
    "sg:phone":"+49 7432/984140",
    "sg:postcode":"72461",
    "sg:province":"Baden-W\u00fcrttemberg",
    "wof:name":"Ott-tricot Werner Ott E.k",
    "wof:placetype":"venue"
},
  "geometry": {"coordinates":[9.015272,48.260616],"type":"Point"}
}