{
  "type": "Feature",
  "properties": {
    "iso:country":"DE",
    "sg:address":"Barther Str. 65",
    "sg:city":"Franzburg",
    "sg:postcode":"18461",
    "sg:province":"Mecklenburg-Vorpommern",
    "wof:name":"Holztechnik Franzburg Gmbh",
    "wof:placetype":"venue"
},
  "geometry": {"coordinates":[12.871758461,54.1094665527],"type":"Point"}
}