{
  "type": "Feature",
  "properties": {
    "iso:country":"DE",
    "sg:address":"Lukas-Cranach-Str. 8 a",
    "sg:city":"Berlin",
    "sg:phone":"+49 30/8225204",
    "sg:postcode":"12203",
    "sg:province":"Berlin",
    "wof:name":"Harley-kooso Motorrad- Handelsgesellschaft Mbh",
    "wof:placetype":"venue"
},
  "geometry": {"coordinates":[13.312128067,52.4378242493],"type":"Point"}
}