{
  "type": "Feature",
  "properties": {
    "iso:country":"DE",
    "sg:address":"Schubertstr. 43",
    "sg:city":"Schmelz",
    "sg:phone":"+49 6887/4222",
    "sg:postcode":"66839",
    "sg:province":"Saarland",
    "wof:name":"Johann-gro\u00df",
    "wof:placetype":"venue"
},
  "geometry": {"coordinates":[6.8445649147,49.4463615417],"type":"Point"}
}