{
  "type": "Feature",
  "properties": {
    "iso:country":"DE",
    "sg:address":"Auf dem Pfeffinger 18",
    "sg:city":"Balingen",
    "sg:phone":"+49 7433/8560",
    "sg:postcode":"72336",
    "sg:province":"Baden-W\u00fcrttemberg",
    "wof:name":"F. Rothacher",
    "wof:placetype":"venue"
},
  "geometry": {"coordinates":[8.8825311661,48.2731781006],"type":"Point"}
}