{
  "type": "Feature",
  "properties": {
    "iso:country":"DE",
    "sg:address":"Windsbacher Str. 2",
    "sg:city":"Spalt",
    "sg:phone":"+49 9175/250",
    "sg:postcode":"91174",
    "sg:province":"Bayern",
    "wof:name":"Erich Haberkorn",
    "wof:placetype":"venue"
},
  "geometry": {"coordinates":[10.9229068756,49.1767044067],"type":"Point"}
}