{
  "type": "Feature",
  "properties": {
    "iso:country":"DE",
    "sg:address":"39340",
    "sg:city":"Haldensleben",
    "sg:phone":"+49 3904/71841",
    "sg:postcode":"39340",
    "sg:province":"Sachsen-Anhalt",
    "wof:name":"Haldensleber Bank-raiffeisenbank Eg",
    "wof:placetype":"venue"
},
  "geometry": {"coordinates":[11.43858,52.305511],"type":"Point"}
}