{
  "type": "Feature",
  "properties": {
    "iso:country":"DE",
    "sg:address":"Viehauserstr. 14",
    "sg:city":"Landau",
    "sg:phone":"+49 9951/590740",
    "sg:postcode":"94405",
    "sg:province":"Bayern",
    "wof:name":"Richard Obermeier",
    "wof:placetype":"venue"
},
  "geometry": {"coordinates":[12.6886196136,48.6835823059],"type":"Point"}
}