{
  "type": "Feature",
  "properties": {
    "iso:country":"DE",
    "sg:address":"Ludwigstr. 13",
    "sg:city":"Stuttgart",
    "sg:phone":"+49 711/6154297",
    "sg:postcode":"70176",
    "sg:province":"Baden-W\u00fcrttemberg",
    "wof:name":"F\u00e4ssle",
    "wof:placetype":"venue"
},
  "geometry": {"coordinates":[9.1648836136,48.7749938965],"type":"Point"}
}