{
  "type": "Feature",
  "properties": {
    "iso:country":"DE",
    "sg:address":"Konrad-Adenauer-Platz 3",
    "sg:city":"H\u00fcnfeld",
    "sg:phone":"+49 6652/2512",
    "sg:postcode":"36088",
    "sg:province":"Hessen",
    "wof:name":"Gerhard Heimrich",
    "wof:placetype":"venue"
},
  "geometry": {"coordinates":[9.765592,50.673527],"type":"Point"}
}