{
  "type": "Feature",
  "properties": {
    "iso:country":"DE",
    "sg:address":"K\u00f6nigsallee 1",
    "sg:city":"K\u00f6nigsbrunn",
    "sg:phone":"+49 8231/96280",
    "sg:postcode":"86343",
    "sg:province":"Bayern",
    "wof:name":"K\u00f6nigstherme Bau- Und Betriebsgesellschaft Mbh",
    "wof:placetype":"venue"
},
  "geometry": {"coordinates":[10.885186,48.272137],"type":"Point"}
}