{
  "type": "Feature",
  "properties": {
    "iso:country":"DE",
    "sg:address":"Dorfstr. 24",
    "sg:city":"Kl\u00e4den",
    "sg:phone":"+49 39324/272",
    "sg:postcode":"39579",
    "sg:province":"Sachsen-Anhalt",
    "wof:name":"Friseur Und Kosmetik Gmbh",
    "wof:placetype":"venue"
},
  "geometry": {"coordinates":[11.6577205658,52.6310768127],"type":"Point"}
}