{
  "type": "Feature",
  "properties": {
    "iso:country":"DE",
    "sg:address":"Friedrichstaler Str. 2",
    "sg:city":"Graben-Neudorf",
    "sg:phone":"+49 7255/9436",
    "sg:postcode":"76676",
    "sg:province":"Baden-W\u00fcrttemberg",
    "wof:name":"Manfred Metzger",
    "wof:placetype":"venue"
},
  "geometry": {"coordinates":[8.483961,49.155235],"type":"Point"}
}