{
  "type": "Feature",
  "properties": {
    "iso:country":"DE",
    "sg:address":"Darmst\u00e4dter Str. 3",
    "sg:city":"Zwingenberg",
    "sg:phone":"+49 6251/71478",
    "sg:postcode":"64673",
    "sg:province":"Hessen",
    "wof:name":"Helmut Germann",
    "wof:placetype":"venue"
},
  "geometry": {"coordinates":[8.612619,49.724571],"type":"Point"}
}