{
  "type": "Feature",
  "properties": {
    "iso:country":"DE",
    "sg:address":"Neuhofstr. 19",
    "sg:city":"Frankfurt",
    "sg:phone":"+49 69/594523",
    "sg:postcode":"60318",
    "sg:province":"Hessen",
    "wof:name":"Armagan Konrat",
    "wof:placetype":"venue"
},
  "geometry": {"coordinates":[8.6898174286,50.1257171631],"type":"Point"}
}