{
  "type": "Feature",
  "properties": {
    "iso:country":"DE",
    "sg:address":"Im Sumpf",
    "sg:city":"Halver",
    "sg:phone":"+49 2351/788350",
    "sg:postcode":"58553",
    "sg:province":"Nordrhein-Westfalen",
    "wof:name":"Baberg Gesenkschmiede Nachfolge Gmbh",
    "wof:placetype":"venue"
},
  "geometry": {"coordinates":[7.477283,51.17345],"type":"Point"}
}