{
  "type": "Feature",
  "properties": {
    "iso:country":"DE",
    "sg:address":"Kirchstrasse 28",
    "sg:city":"Wathlingen",
    "sg:postcode":"29339",
    "sg:province":"Niedersachsen",
    "wof:name":"Blue Diamonds Colorguard",
    "wof:placetype":"venue"
},
  "geometry": {"coordinates":[10.149057,52.54007],"type":"Point"}
}