{
  "type": "Feature",
  "properties": {
    "iso:country":"DE",
    "sg:address":"Brunsbergweg 1",
    "sg:city":"Buchholz",
    "sg:phone":"+49 4186/302",
    "sg:postcode":"21244",
    "sg:province":"Niedersachsen",
    "wof:name":"Hans Alvermann Verlagsvertreter",
    "wof:placetype":"venue"
},
  "geometry": {"coordinates":[9.819315,53.3088],"type":"Point"}
}