{
  "type": "Feature",
  "properties": {
    "iso:country":"DE",
    "sg:address":"Domerschulstr. 11",
    "sg:city":"W\u00fcrzburg",
    "sg:phone":"+49 931/3044606",
    "sg:postcode":"97070",
    "sg:province":"Bayern",
    "wof:name":"Martens Rechtsanwalt",
    "wof:placetype":"venue"
},
  "geometry": {"coordinates":[9.9327373505,49.7913398743],"type":"Point"}
}