{
  "type": "Feature",
  "properties": {
    "iso:country":"DE",
    "sg:address":"Oirlich 16",
    "sg:city":"Nettetal",
    "sg:phone":"+49 2153/4167",
    "sg:postcode":"41334",
    "sg:province":"Nordrhein-Westfalen",
    "wof:name":"Willy Kersten",
    "wof:placetype":"venue"
},
  "geometry": {"coordinates":[6.29234,51.325359],"type":"Point"}
}