{
  "type": "Feature",
  "properties": {
    "iso:country":"DE",
    "sg:address":"Langer Weg 6",
    "sg:city":"Bippen",
    "sg:postcode":"49626",
    "sg:province":"Niedersachsen",
    "wof:name":"Arwa Immobilien Gmbh",
    "wof:placetype":"venue"
},
  "geometry": {"coordinates":[7.7447919846,52.5812530518],"type":"Point"}
}