{
  "type": "Feature",
  "properties": {
    "iso:country":"DE",
    "sg:address":"Rodensteinstr. 7",
    "sg:city":"Bensheim",
    "sg:phone":"+49 6251/64388",
    "sg:postcode":"64625",
    "sg:province":"Hessen",
    "wof:name":"Cornelia Busse Krankengymnastin",
    "wof:placetype":"venue"
},
  "geometry": {"coordinates":[8.620105,49.682777],"type":"Point"}
}