{
  "type": "Feature",
  "properties": {
    "iso:country":"DE",
    "sg:address":"Schulstr. 7",
    "sg:city":"Nievern",
    "sg:phone":"+49 2603/12106",
    "sg:postcode":"56132",
    "sg:province":"Rheinland-Pfalz",
    "wof:name":"Ignaz Kratzer Vergn\u00fcgungsst\u00e4tte",
    "wof:placetype":"venue"
},
  "geometry": {"coordinates":[7.679873,50.337059],"type":"Point"}
}