{
  "type": "Feature",
  "properties": {
    "iso:country":"DE",
    "sg:address":"Schulstr 21",
    "sg:city":"Arnstein",
    "sg:phone":"+49 9728/9250",
    "sg:postcode":"97450",
    "sg:province":"Bayern",
    "wof:name":"Wanzel Gmbh",
    "wof:placetype":"venue"
},
  "geometry": {"coordinates":[10.0048933029,50.0218276978],"type":"Point"}
}