{
  "type": "Feature",
  "properties": {
    "iso:country":"DE",
    "sg:address":"Schlo\u00dfstr. 11-15",
    "sg:city":"Berlin",
    "sg:postcode":"12163",
    "sg:province":"Berlin",
    "wof:name":"Small Al Forno E. Kfm.",
    "wof:placetype":"venue"
},
  "geometry": {"coordinates":[13.325750351,52.462474823],"type":"Point"}
}