{
  "type": "Feature",
  "properties": {
    "iso:country":"DE",
    "sg:address":"Hauffstr. 29",
    "sg:city":"Vellmar",
    "sg:phone":"+49 561/828313",
    "sg:postcode":"34246",
    "sg:province":"Hessen",
    "wof:name":"Blumenvertrieb Staude Gmbh",
    "wof:placetype":"venue"
},
  "geometry": {"coordinates":[9.470116,51.361984],"type":"Point"}
}