{
  "type": "Feature",
  "properties": {
    "iso:country":"DE",
    "sg:address":"Hamburger Str. 207",
    "sg:city":"Hamburg",
    "sg:phone":"+49 40/291309",
    "sg:postcode":"22083",
    "sg:province":"Hamburg",
    "wof:name":"Regale Bettenstudio Gmbh",
    "wof:placetype":"venue"
},
  "geometry": {"coordinates":[10.0393409729,53.579574585],"type":"Point"}
}