{
  "type": "Feature",
  "properties": {
    "iso:country":"DE",
    "sg:address":"Wilhelmstr. 18",
    "sg:city":"Nordenham",
    "sg:phone":"+49 4731/21107",
    "sg:postcode":"26954",
    "sg:province":"Niedersachsen",
    "wof:name":"M. Von Lienen",
    "wof:placetype":"venue"
},
  "geometry": {"coordinates":[8.4863996506,53.4853897095],"type":"Point"}
}