{
  "type": "Feature",
  "properties": {
    "iso:country":"DE",
    "sg:address":"Seestr. 9",
    "sg:city":"B\u00f6singen",
    "sg:phone":"+49 7404/417",
    "sg:postcode":"78662",
    "sg:province":"Baden-W\u00fcrttemberg",
    "wof:name":"H. Und P. Ohnmacht",
    "wof:placetype":"venue"
},
  "geometry": {"coordinates":[8.552211,48.238937],"type":"Point"}
}