{
  "type": "Feature",
  "properties": {
    "iso:country":"DE",
    "sg:address":"Stra\u00dfe der Zukunft 3a",
    "sg:city":"Rosenow",
    "sg:phone":"+49 39602/20943",
    "sg:postcode":"17091",
    "sg:province":"Mecklenburg-Vorpommern",
    "wof:name":"Brigitte Kahnke Und Doris Bilinski",
    "wof:placetype":"venue"
},
  "geometry": {"coordinates":[13.0392503738,53.6289901733],"type":"Point"}
}