{
  "type": "Feature",
  "properties": {
    "iso:country":"DE",
    "sg:address":"Blumenthalstra\u00dfe 58",
    "sg:city":"Duisburg",
    "sg:postcode":"47058",
    "sg:province":"Nordrhein-Westfalen",
    "wof:name":"Hauptausschuss Duisburger Karneval E.v.",
    "wof:placetype":"venue"
},
  "geometry": {"coordinates":[6.7861590385,51.4379119873],"type":"Point"}
}