{
  "type": "Feature",
  "properties": {
    "iso:country":"DE",
    "sg:address":"Charlottenstr. 5",
    "sg:city":"Jena",
    "sg:phone":"+49 3641/445299",
    "sg:postcode":"07749",
    "sg:province":"Th\u00fcringen",
    "wof:name":"Peter Ebert",
    "wof:placetype":"venue"
},
  "geometry": {"coordinates":[11.5979204178,50.9322547913],"type":"Point"}
}