{
  "type": "Feature",
  "properties": {
    "iso:country":"DE",
    "sg:address":"H\u00fclzweilerstr. 94",
    "sg:city":"Saarlouis",
    "sg:phone":"+49 6831/85122",
    "sg:postcode":"66740",
    "sg:province":"Saarland",
    "wof:name":"Werbedesign Lombardo",
    "wof:placetype":"venue"
},
  "geometry": {"coordinates":[6.7784771919,49.3235626221],"type":"Point"}
}