{
  "type": "Feature",
  "properties": {
    "iso:country":"DE",
    "sg:address":"Freiherr-Vom-Stein-Str. 31",
    "sg:city":"Nordhausen",
    "sg:phone":"+49 4936/316220",
    "sg:postcode":"99734",
    "sg:province":"Th\u00fcringen",
    "wof:name":"Bike Systemes Gmbh & Co.",
    "wof:placetype":"venue"
},
  "geometry": {"coordinates":[10.7947807312,51.5021743774],"type":"Point"}
}