{
  "type": "Feature",
  "properties": {
    "iso:country":"DE",
    "sg:address":"Am Anger 22",
    "sg:city":"K\u00f6sching",
    "sg:phone":"+49 8456/8629",
    "sg:postcode":"85092",
    "sg:province":"Bayern",
    "wof:name":"Braun Gmbh",
    "wof:placetype":"venue"
},
  "geometry": {"coordinates":[11.498732,48.814178],"type":"Point"}
}