{
  "type": "Feature",
  "properties": {
    "iso:country":"DE",
    "sg:address":"Untere Str. 5",
    "sg:city":"Winnigstedt",
    "sg:phone":"+49 5336/8663",
    "sg:postcode":"38170",
    "sg:province":"Niedersachsen",
    "wof:name":"Thomas Reinkober Antiquit\u00e4ten",
    "wof:placetype":"venue"
},
  "geometry": {"coordinates":[10.772028,52.064823],"type":"Point"}
}