{
  "type": "Feature",
  "properties": {
    "iso:country":"DE",
    "sg:address":"Gr\u00fcner Weg 38",
    "sg:city":"Gelnhausen",
    "sg:phone":"+49 6051/67643",
    "sg:postcode":"63571",
    "sg:province":"Hessen",
    "wof:name":"Christiane Pape-kauder Heilpraktikerin",
    "wof:placetype":"venue"
},
  "geometry": {"coordinates":[9.1623544693,50.1832237244],"type":"Point"}
}