{
  "type": "Feature",
  "properties": {
    "iso:country":"DE",
    "sg:address":"Gro\u00dfe Str. 3",
    "sg:city":"Crivitz",
    "sg:phone":"+49 3863/222601",
    "sg:postcode":"19089",
    "sg:province":"Mecklenburg-Vorpommern",
    "wof:name":"Matthias Schreiter Rechtsanwalt",
    "wof:placetype":"venue"
},
  "geometry": {"coordinates":[11.6508827209,53.5766601562],"type":"Point"}
}