{
  "type": "Feature",
  "properties": {
    "iso:country":"DE",
    "sg:address":"Am Wallgraben 2",
    "sg:city":"Leichlingen",
    "sg:phone":"+49 4921/759710",
    "sg:postcode":"42799",
    "sg:province":"Nordrhein-Westfalen",
    "wof:name":"Precise Pr\u00c4zisionsspindeln Gmbh",
    "wof:placetype":"venue"
},
  "geometry": {"coordinates":[7.013265,51.101959],"type":"Point"}
}