{
  "type": "Feature",
  "properties": {
    "iso:country":"DE",
    "sg:address":"Willy-Mock-Str. 2",
    "sg:city":"Marburg",
    "sg:phone":"+49 6421/92620",
    "sg:postcode":"35037",
    "sg:province":"Hessen",
    "wof:name":"Hs Squash-halle Gmbh",
    "wof:placetype":"venue"
},
  "geometry": {"coordinates":[8.7564725876,50.7950592041],"type":"Point"}
}