{
  "type": "Feature",
  "properties": {
    "iso:country":"DE",
    "sg:address":"Karl-May-Str. 20",
    "sg:city":"Hohenstein-Ernstthal",
    "sg:phone":"+49 3723/42248",
    "sg:postcode":"09337",
    "sg:province":"Sachsen",
    "wof:name":"B. M\u00fcller",
    "wof:placetype":"venue"
},
  "geometry": {"coordinates":[12.7160558701,50.8005371094],"type":"Point"}
}