{
  "type": "Feature",
  "properties": {
    "iso:country":"DE",
    "sg:address":"Reuth",
    "sg:city":"Bad Elster",
    "sg:phone":"+49 37437/2655",
    "sg:postcode":"08645",
    "sg:province":"Sachsen",
    "wof:name":"Luft- Und Schwimmbad",
    "wof:placetype":"venue"
},
  "geometry": {"coordinates":[12.2517690659,50.2782211304],"type":"Point"}
}