{
  "type": "Feature",
  "properties": {
    "iso:country":"DE",
    "sg:address":"Schweinemarkt 8",
    "sg:city":"Arnstein",
    "sg:phone":"+49 9363/99114",
    "sg:postcode":"97450",
    "sg:province":"Bayern",
    "wof:name":"Hans Fenn",
    "wof:placetype":"venue"
},
  "geometry": {"coordinates":[9.967482,49.979321],"type":"Point"}
}