{
  "type": "Feature",
  "properties": {
    "iso:country":"DE",
    "sg:address":"Hauptstr. 8-10",
    "sg:city":"Bergheim",
    "sg:phone":"+49 2271/44431",
    "sg:postcode":"50126",
    "sg:province":"Nordrhein-Westfalen",
    "wof:name":"Norbert Passens",
    "wof:placetype":"venue"
},
  "geometry": {"coordinates":[6.6433568001,50.9538116455],"type":"Point"}
}