{
  "type": "Feature",
  "properties": {
    "iso:country":"DE",
    "sg:address":"Alt Heddernheim 39",
    "sg:city":"Frankfurt",
    "sg:phone":"+49 69/572635",
    "sg:postcode":"60439",
    "sg:province":"Hessen",
    "wof:name":"Katholisches Pfarramt St. Peter Und Paul",
    "wof:placetype":"venue"
},
  "geometry": {"coordinates":[8.6486759186,50.1575813293],"type":"Point"}
}