{
  "type": "Feature",
  "properties": {
    "iso:country":"DE",
    "sg:address":"Irmgardstr. 28",
    "sg:city":"Berlin",
    "sg:phone":"+49 30/8181870",
    "sg:postcode":"14169",
    "sg:province":"Berlin",
    "wof:name":"Huschke Und Partner Steuerberatungsgesellschaft",
    "wof:placetype":"venue"
},
  "geometry": {"coordinates":[13.262377739,52.4476928711],"type":"Point"}
}