{
  "type": "Feature",
  "properties": {
    "iso:country":"DE",
    "sg:address":"Mahlbergstra\u00dfe 1",
    "sg:city":"Straubenhardt",
    "sg:phone":"+49 7082/941413",
    "sg:postcode":"75334",
    "sg:province":"Baden-W\u00fcrttemberg",
    "wof:name":"Telefontarife Info Telefonieren Telefongeb\u00fchren",
    "wof:placetype":"venue"
},
  "geometry": {"coordinates":[8.538858,48.842522],"type":"Point"}
}