{
  "type": "Feature",
  "properties": {
    "iso:country":"DE",
    "sg:address":"Kronenberg 14",
    "sg:city":"Aachen",
    "sg:phone":"+49 241/76861",
    "sg:postcode":"52074",
    "sg:province":"Nordrhein-Westfalen",
    "wof:name":"Schwimmhalle West",
    "wof:placetype":"venue"
},
  "geometry": {"coordinates":[6.0582609177,50.765914917],"type":"Point"}
}