{
  "type": "Feature",
  "properties": {
    "iso:country":"DE",
    "sg:address":"Stein-Hardenberg-Str. 87 a",
    "sg:city":"Hamburg",
    "sg:phone":"+49 40/6407519",
    "sg:postcode":"22045",
    "sg:province":"Hamburg",
    "wof:name":"Ralf Lemke",
    "wof:placetype":"venue"
},
  "geometry": {"coordinates":[10.124747,53.588589],"type":"Point"}
}