{
  "type": "Feature",
  "properties": {
    "iso:country":"DE",
    "sg:address":"Am Heilbrunnen 85-87",
    "sg:city":"Reutlingen",
    "sg:phone":"+49 7121/94490",
    "sg:postcode":"72766",
    "sg:province":"Baden-W\u00fcrttemberg",
    "wof:name":"Fetzer Gmbh",
    "wof:placetype":"venue"
},
  "geometry": {"coordinates":[9.2195034027,48.5061378479],"type":"Point"}
}