{
  "type": "Feature",
  "properties": {
    "iso:country":"DE",
    "sg:address":"Ernst-Th\u00e4lmann-Str. 82",
    "sg:city":"Wustrau",
    "sg:postcode":"16818",
    "sg:province":"Brandenburg",
    "wof:name":"E. W\u00fcst",
    "wof:placetype":"venue"
},
  "geometry": {"coordinates":[12.8573036194,52.8456535339],"type":"Point"}
}