{
  "type": "Feature",
  "properties": {
    "iso:country":"DE",
    "sg:address":"Krayer Str. 232",
    "sg:city":"Essen",
    "sg:phone":"+49 201/555192",
    "sg:postcode":"45307",
    "sg:province":"Nordrhein-Westfalen",
    "wof:name":"Gl\u00fcckauf-apotheke",
    "wof:placetype":"venue"
},
  "geometry": {"coordinates":[7.080458,51.46661],"type":"Point"}
}