{
  "type": "Feature",
  "properties": {
    "iso:country":"DE",
    "sg:address":"Berliner Str. 20",
    "sg:city":"Gr\u00e4fenhainichen",
    "sg:phone":"+49 34953/22337",
    "sg:postcode":"06773",
    "sg:province":"Sachsen-Anhalt",
    "wof:name":"Zimmermann & Bl\u00fcthgen Ohg",
    "wof:placetype":"venue"
},
  "geometry": {"coordinates":[12.4711904526,51.7359428406],"type":"Point"}
}