{
  "type": "Feature",
  "properties": {
    "iso:country":"DE",
    "sg:address":"Unterherrnhauser Str. 4d",
    "sg:city":"Eurasburg",
    "sg:phone":"+49 8179/1552",
    "sg:postcode":"82547",
    "sg:province":"Bayern",
    "wof:name":"Tony Wammetsberger Gmbh & Co. Bauunternehmung Kg",
    "wof:placetype":"venue"
},
  "geometry": {"coordinates":[11.406707,47.852024],"type":"Point"}
}