{
  "type": "Feature",
  "properties": {
    "iso:country":"DE",
    "sg:address":"Burgstr. 2",
    "sg:city":"Kesten",
    "sg:phone":"+49 6535/7403",
    "sg:postcode":"54518",
    "sg:province":"Rheinland-Pfalz",
    "wof:name":"Alfred Kasel",
    "wof:placetype":"venue"
},
  "geometry": {"coordinates":[6.9571638107,49.9025840759],"type":"Point"}
}