{
  "type": "Feature",
  "properties": {
    "iso:country":"DE",
    "sg:address":"Borsigallee 2",
    "sg:city":"Bonn",
    "sg:phone":"+49 228/259433",
    "sg:postcode":"53125",
    "sg:province":"Nordrhein-Westfalen",
    "wof:name":"Fritsch Und Sambeck Rechtsanw\u00e4lte",
    "wof:placetype":"venue"
},
  "geometry": {"coordinates":[7.0572490692,50.6995315552],"type":"Point"}
}