{
  "type": "Feature",
  "properties": {
    "iso:country":"DE",
    "sg:address":"H\u00f6nower Str. 93",
    "sg:city":"Berlin",
    "sg:phone":"+49 30/5636203",
    "sg:postcode":"12623",
    "sg:province":"Berlin",
    "wof:name":"Kork-parkett Studio Kurka & Fiedler",
    "wof:placetype":"venue"
},
  "geometry": {"coordinates":[13.6119804382,52.5132331848],"type":"Point"}
}