{
  "type": "Feature",
  "properties": {
    "iso:country":"DE",
    "sg:address":"L\u00fcnzener Str. 51",
    "sg:city":"Schneverdingen",
    "sg:phone":"+49 4265/713",
    "sg:postcode":"29640",
    "sg:province":"Niedersachsen",
    "wof:name":"Hermann Worthmann",
    "wof:placetype":"venue"
},
  "geometry": {"coordinates":[9.686824,53.121975],"type":"Point"}
}