{
  "type": "Feature",
  "properties": {
    "iso:country":"DE",
    "sg:address":"Maria-Theresia-Str. 5",
    "sg:city":"G\u00fcnzburg",
    "sg:phone":"+49 8221/6548",
    "sg:postcode":"89312",
    "sg:province":"Bayern",
    "wof:name":"Maria Osterlehner",
    "wof:placetype":"venue"
},
  "geometry": {"coordinates":[10.278883,48.458023],"type":"Point"}
}