{
  "type": "Feature",
  "properties": {
    "iso:country":"DE",
    "sg:address":"Uferallee 9",
    "sg:city":"Zeltingen-Rachtig",
    "sg:phone":"+49 6532/2055",
    "sg:postcode":"54492",
    "sg:province":"Rheinland-Pfalz",
    "wof:name":"St. Stephanus Hotelgesell- Schaft Kg",
    "wof:placetype":"venue"
},
  "geometry": {"coordinates":[7.0172848701,49.9523506165],"type":"Point"}
}