{
  "type": "Feature",
  "properties": {
    "iso:country":"DE",
    "sg:address":"Ackerstr. 44",
    "sg:city":"Grevenbroich",
    "sg:postcode":"41516",
    "sg:province":"Nordrhein-Westfalen",
    "wof:name":"Intrac Informations- Systeme Gmbh",
    "wof:placetype":"venue"
},
  "geometry": {"coordinates":[6.680000782,51.122505188],"type":"Point"}
}