{
  "type": "Feature",
  "properties": {
    "iso:country":"DE",
    "sg:address":"Talstr. 61",
    "sg:city":"D\u00fcsseldorf",
    "sg:phone":"+49 4957/3117799",
    "sg:postcode":"40217",
    "sg:province":"Nordrhein-Westfalen",
    "wof:name":"Gustav Klocke Modellbau Gmbh & Co Kg",
    "wof:placetype":"venue"
},
  "geometry": {"coordinates":[8.8324422836,52.2079811096],"type":"Point"}
}