{
  "type": "Feature",
  "properties": {
    "iso:country":"DE",
    "sg:address":"Bachstr. 4 a",
    "sg:city":"Speicher",
    "sg:phone":"+49 6562/2193",
    "sg:postcode":"54662",
    "sg:province":"Rheinland-Pfalz",
    "wof:name":"Pfarrb\u00fccherei Anni Thomsen",
    "wof:placetype":"venue"
},
  "geometry": {"coordinates":[6.633655,49.93364],"type":"Point"}
}