{
  "type": "Feature",
  "properties": {
    "iso:country":"DE",
    "sg:address":"Gewerbestra\u00dfe 18",
    "sg:city":"L\u00f6hne",
    "sg:phone":"+49 5731",
    "sg:postcode":"32584",
    "sg:province":"Nordrhein-Westfalen",
    "wof:name":"Interbel",
    "wof:placetype":"venue"
},
  "geometry": {"coordinates":[8.7569723129,52.180267334],"type":"Point"}
}