{
  "type": "Feature",
  "properties": {
    "iso:country":"DE",
    "sg:address":"Freiheit 36",
    "sg:city":"Dresden",
    "sg:phone":"+49 351/4210749",
    "sg:postcode":"01157",
    "sg:province":"Sachsen",
    "wof:name":"Gerhard K\u00fchne",
    "wof:placetype":"venue"
},
  "geometry": {"coordinates":[13.656853,51.056538],"type":"Point"}
}