{
  "type": "Feature",
  "properties": {
    "iso:country":"DE",
    "sg:address":"Oberroder Str. 1",
    "sg:city":"Westernohe",
    "sg:phone":"+49 2664/5010",
    "sg:postcode":"56479",
    "sg:province":"Rheinland-Pfalz",
    "wof:name":"Zoth Gmbh & Co. Kg",
    "wof:placetype":"venue"
},
  "geometry": {"coordinates":[8.046827,50.575016],"type":"Point"}
}