{
  "type": "Feature",
  "properties": {
    "iso:country":"DE",
    "sg:address":"Prinzenstr. 55",
    "sg:city":"M\u00f6nchengladbach",
    "sg:phone":"+49 2161/461246",
    "sg:postcode":"41065",
    "sg:province":"Nordrhein-Westfalen",
    "wof:name":"M.samnee & G.kolbusz",
    "wof:placetype":"venue"
},
  "geometry": {"coordinates":[6.455605,51.192097],"type":"Point"}
}