{
  "type": "Feature",
  "properties": {
    "iso:country":"DE",
    "sg:address":"Sangenweg 16",
    "sg:city":"Stockstadt",
    "sg:postcode":"64589",
    "sg:province":"Hessen",
    "wof:name":"Vitanatur Naturwaren Gmbh",
    "wof:placetype":"venue"
},
  "geometry": {"coordinates":[8.4774904251,49.8083114624],"type":"Point"}
}