{
  "type": "Feature",
  "properties": {
    "iso:country":"DE",
    "sg:address":"Dorfstr. 7",
    "sg:city":"Grimma",
    "sg:postcode":"04668",
    "sg:province":"Sachsen",
    "wof:name":"Dung Vo Anh",
    "wof:placetype":"venue"
},
  "geometry": {"coordinates":[12.75346,51.209408],"type":"Point"}
}