{
  "type": "Feature",
  "properties": {
    "iso:country":"DE",
    "sg:address":"Eichendorffstr. 11",
    "sg:city":"Wolfsburg",
    "sg:phone":"+49 5361/34840",
    "sg:postcode":"38440",
    "sg:province":"Niedersachsen",
    "wof:name":"Missal Innenausbau Parkett- Und Dielenstudio Gmbh",
    "wof:placetype":"venue"
},
  "geometry": {"coordinates":[10.782017,52.420998],"type":"Point"}
}