{
  "type": "Feature",
  "properties": {
    "iso:country":"DE",
    "sg:address":"Gr\u00fcne Str. 11",
    "sg:city":"Dommitzsch",
    "sg:phone":"+49 34223/40477",
    "sg:postcode":"04880",
    "sg:province":"Sachsen",
    "wof:name":"Richard K\u00fcrsten",
    "wof:placetype":"venue"
},
  "geometry": {"coordinates":[12.8806276321,51.6395950317],"type":"Point"}
}