{
  "type": "Feature",
  "properties": {
    "iso:country":"DE",
    "sg:address":"25938",
    "sg:city":"Wyk",
    "sg:phone":"+49 4681/4230",
    "sg:postcode":"25938",
    "sg:province":"Schleswig-Holstein",
    "wof:name":"Gastst\u00e4tte Pinte",
    "wof:placetype":"venue"
},
  "geometry": {"coordinates":[8.4958000183,54.717628479],"type":"Point"}
}