{
  "type": "Feature",
  "properties": {
    "iso:country":"DE",
    "sg:address":"Hauptstr. 5",
    "sg:city":"D\u00fcrbheim",
    "sg:phone":"+49 4974/2494030",
    "sg:postcode":"78589",
    "sg:province":"Baden-W\u00fcrttemberg",
    "wof:name":"Kapp Chirurgische Instrumente Gmbh",
    "wof:placetype":"venue"
},
  "geometry": {"coordinates":[8.7897224426,48.0539550781],"type":"Point"}
}