{
  "type": "Feature",
  "properties": {
    "iso:country":"DE",
    "sg:address":"Untergasse 51",
    "sg:city":"Felsberg",
    "sg:phone":"+49 5662/2171",
    "sg:postcode":"34587",
    "sg:province":"Hessen",
    "wof:name":"Felsburg-apotheke Dr. Ulrich Ge\u00dfner",
    "wof:placetype":"venue"
},
  "geometry": {"coordinates":[9.41963,51.134701],"type":"Point"}
}