{
  "type": "Feature",
  "properties": {
    "iso:country":"DE",
    "sg:address":"Theodor-Heuss-Str. 67",
    "sg:city":"Leimen",
    "sg:phone":"+49 6224/50723",
    "sg:postcode":"69181",
    "sg:province":"Baden-W\u00fcrttemberg",
    "wof:name":"H. Freisler",
    "wof:placetype":"venue"
},
  "geometry": {"coordinates":[8.6689157486,49.3342132568],"type":"Point"}
}