{
  "type": "Feature",
  "properties": {
    "iso:country":"DE",
    "sg:address":"Markt 36",
    "sg:city":"Lieberose",
    "sg:phone":"+49 33671/2229",
    "sg:postcode":"15868",
    "sg:province":"Brandenburg",
    "wof:name":"K. Strobel",
    "wof:placetype":"venue"
},
  "geometry": {"coordinates":[14.3006277084,51.9886131287],"type":"Point"}
}