{
  "type": "Feature",
  "properties": {
    "iso:country":"DE",
    "sg:address":"Ringstr. 2a",
    "sg:city":"Bad Vilbel",
    "sg:phone":"+49 6101/7222",
    "sg:postcode":"61118",
    "sg:province":"Hessen",
    "wof:name":"Elke Und Wolfgang Patzelt",
    "wof:placetype":"venue"
},
  "geometry": {"coordinates":[8.7543621063,50.2084579468],"type":"Point"}
}