{
  "type": "Feature",
  "properties": {
    "iso:country":"DE",
    "sg:address":"Flurstr. 81",
    "sg:city":"Essen",
    "sg:phone":"+49 201/674428",
    "sg:postcode":"45355",
    "sg:province":"Nordrhein-Westfalen",
    "wof:name":"Rainer Herget",
    "wof:placetype":"venue"
},
  "geometry": {"coordinates":[6.9410691261,51.475479126],"type":"Point"}
}