{
  "type": "Feature",
  "properties": {
    "iso:country":"DE",
    "sg:address":"Schorlemerallee 16",
    "sg:city":"Berlin",
    "sg:phone":"+49 30/8256006",
    "sg:postcode":"14195",
    "sg:province":"Berlin",
    "wof:name":"Ute Nicolai",
    "wof:placetype":"venue"
},
  "geometry": {"coordinates":[13.304235,52.465431],"type":"Point"}
}