{
  "type": "Feature",
  "properties": {
    "iso:country":"DE",
    "sg:address":"Zillestr. 1",
    "sg:city":"Auerbach",
    "sg:phone":"+49 3744/214389",
    "sg:postcode":"08209",
    "sg:province":"Sachsen",
    "wof:name":"Ilse Berger",
    "wof:placetype":"venue"
},
  "geometry": {"coordinates":[12.4044265747,50.5120391846],"type":"Point"}
}