{
  "type": "Feature",
  "properties": {
    "iso:country":"DE",
    "sg:address":"Thomas-M\u00fcntzer-Str. 7",
    "sg:city":"Zwickau",
    "sg:phone":"+49 375/522844",
    "sg:postcode":"08060",
    "sg:province":"Sachsen",
    "wof:name":"T. R\u00f6hlig",
    "wof:placetype":"venue"
},
  "geometry": {"coordinates":[12.4387140274,50.7231292725],"type":"Point"}
}