{
  "type": "Feature",
  "properties": {
    "iso:country":"DE",
    "sg:address":"Am Sennebach 56",
    "sg:city":"Rietberg",
    "sg:phone":"+49 5244/5262",
    "sg:postcode":"33397",
    "sg:province":"Nordrhein-Westfalen",
    "wof:name":"Johannes Wohlgemuth",
    "wof:placetype":"venue"
},
  "geometry": {"coordinates":[8.4605016708,51.8305511475],"type":"Point"}
}