{
  "type": "Feature",
  "properties": {
    "iso:country":"DE",
    "sg:address":"Friedenstr. 86",
    "sg:city":"Kaiserslautern",
    "sg:phone":"+49 631/40786",
    "sg:postcode":"67657",
    "sg:province":"Rheinland-Pfalz",
    "wof:name":"Herbert Closset",
    "wof:placetype":"venue"
},
  "geometry": {"coordinates":[7.7886199951,49.4500007629],"type":"Point"}
}