{
  "type": "Feature",
  "properties": {
    "iso:country":"DE",
    "sg:address":"Marktplatz 1",
    "sg:city":"Fichtenberg",
    "sg:phone":"+49 7971/23002",
    "sg:postcode":"74427",
    "sg:province":"Baden-W\u00fcrttemberg",
    "wof:name":"Reichsadler",
    "wof:placetype":"venue"
},
  "geometry": {"coordinates":[9.7119550705,48.9862251282],"type":"Point"}
}