{
  "type": "Feature",
  "properties": {
    "iso:country":"DE",
    "sg:address":"Jahnstr. 2",
    "sg:city":"Kirrweiler",
    "sg:phone":"+49 6321/5139",
    "sg:postcode":"67489",
    "sg:province":"Rheinland-Pfalz",
    "wof:name":"Willi Stockmayer",
    "wof:placetype":"venue"
},
  "geometry": {"coordinates":[8.161852,49.302498],"type":"Point"}
}