{
  "type": "Feature",
  "properties": {
    "iso:country":"DE",
    "sg:address":"Teplitzer Str.",
    "sg:city":"Geising",
    "sg:postcode":"01778",
    "sg:province":"Sachsen",
    "wof:name":"Ferienh\u00e4user In Geising Im Erzgebirge",
    "wof:placetype":"venue"
},
  "geometry": {"coordinates":[13.793039,50.755985],"type":"Point"}
}