{
  "type": "Feature",
  "properties": {
    "iso:country":"DE",
    "sg:address":"R\u00fchler Str 32",
    "sg:city":"Bodenwerder",
    "sg:phone":"+49 5533/1056",
    "sg:postcode":"37619",
    "sg:province":"Niedersachsen",
    "wof:name":"Elektro Nonn Gmbh & Co Kg",
    "wof:placetype":"venue"
},
  "geometry": {"coordinates":[9.514701,51.969521],"type":"Point"}
}