{
  "type": "Feature",
  "properties": {
    "iso:country":"DE",
    "sg:address":"Obere Dorfstr. 6",
    "sg:city":"Staufenberg",
    "sg:phone":"+49 5543/3918",
    "sg:postcode":"34355",
    "sg:province":"Niedersachsen",
    "wof:name":"Erh. Spengler",
    "wof:placetype":"venue"
},
  "geometry": {"coordinates":[9.5923662186,51.3526496887],"type":"Point"}
}