{
  "type": "Feature",
  "properties": {
    "iso:country":"DE",
    "sg:address":"Thierseifener Str. 13",
    "sg:city":"Waldbr\u00f6l",
    "sg:phone":"+49 2291/7116",
    "sg:postcode":"51545",
    "sg:province":"Nordrhein-Westfalen",
    "wof:name":"Helmut Dresbach",
    "wof:placetype":"venue"
},
  "geometry": {"coordinates":[7.626632,50.901241],"type":"Point"}
}