{
  "type": "Feature",
  "properties": {
    "iso:country":"DE",
    "sg:address":"An der Fischeraue 9",
    "sg:city":"Eilenburg",
    "sg:phone":"+49 3423/603344",
    "sg:postcode":"04838",
    "sg:province":"Sachsen",
    "wof:name":"Joachim Franz",
    "wof:placetype":"venue"
},
  "geometry": {"coordinates":[12.626545,51.4557],"type":"Point"}
}