{
  "type": "Feature",
  "properties": {
    "iso:country":"DE",
    "sg:address":"Bronckhorststr. 6",
    "sg:city":"Dortmund",
    "sg:phone":"+49 231/276253",
    "sg:postcode":"44319",
    "sg:province":"Nordrhein-Westfalen",
    "wof:name":"A. Kleimann & D. Dunaiski",
    "wof:placetype":"venue"
},
  "geometry": {"coordinates":[7.5836977959,51.5286178589],"type":"Point"}
}