{
  "type": "Feature",
  "properties": {
    "iso:country":"DE",
    "sg:address":"Bahnhofstr. 20",
    "sg:city":"Garmisch-Partenkirchen",
    "sg:phone":"+49 8821/52238",
    "sg:postcode":"82467",
    "sg:province":"Bayern",
    "wof:name":"Johann Frischmann",
    "wof:placetype":"venue"
},
  "geometry": {"coordinates":[11.1009998322,47.4925498962],"type":"Point"}
}