{
  "type": "Feature",
  "properties": {
    "iso:country":"DE",
    "sg:address":"Mittelstr. 28",
    "sg:city":"Wesenberg",
    "sg:phone":"+49 39832/21093",
    "sg:postcode":"17255",
    "sg:province":"Mecklenburg-Vorpommern",
    "wof:name":"Neubrandenburger Blumenhandels Und Landschaftsbau Gmbh",
    "wof:placetype":"venue"
},
  "geometry": {"coordinates":[12.967872,53.283039],"type":"Point"}
}