{
  "type": "Feature",
  "properties": {
    "iso:country":"DE",
    "sg:address":"Friedrichstr. 43",
    "sg:city":"Lunden",
    "sg:phone":"+49 4882/5018",
    "sg:postcode":"25774",
    "sg:province":"Schleswig-Holstein",
    "wof:name":"C.-a. Nielsen",
    "wof:placetype":"venue"
},
  "geometry": {"coordinates":[9.023686409,54.3299713135],"type":"Point"}
}