{
  "type": "Feature",
  "properties": {
    "iso:country":"DE",
    "sg:address":"64521",
    "sg:city":"Gro\u00df-Gerau",
    "sg:phone":"+49 6152/910091",
    "sg:postcode":"64521",
    "sg:province":"Hessen",
    "wof:name":"Heuse Bestattungen Gmbh",
    "wof:placetype":"venue"
},
  "geometry": {"coordinates":[8.47779,49.91441],"type":"Point"}
}