{
  "type": "Feature",
  "properties": {
    "iso:country":"DE",
    "sg:address":"Johannisstr. 51",
    "sg:city":"K\u00f6lleda",
    "sg:phone":"+49 3635/403180",
    "sg:postcode":"99625",
    "sg:province":"Th\u00fcringen",
    "wof:name":"Manuela Bruhns",
    "wof:placetype":"venue"
},
  "geometry": {"coordinates":[11.242159,51.187546],"type":"Point"}
}