{
  "type": "Feature",
  "properties": {
    "iso:country":"DE",
    "sg:address":"Steinm\u00fchlenweg 8",
    "sg:city":"Gem\u00fcnden",
    "sg:phone":"+49 2663/3528",
    "sg:postcode":"56459",
    "sg:province":"Rheinland-Pfalz",
    "wof:name":"Schlosser Holzfenster Gmbh",
    "wof:placetype":"venue"
},
  "geometry": {"coordinates":[8.020297,50.558025],"type":"Point"}
}