{
  "type": "Feature",
  "properties": {
    "iso:country":"DE",
    "sg:address":"Lise-Meitner-Str. 17",
    "sg:city":"Flensburg",
    "sg:postcode":"24941",
    "sg:province":"Schleswig-Holstein",
    "wof:name":"Rotermund Grundst\u00fccks- Verwaltungsges. Holm Mbh",
    "wof:placetype":"venue"
},
  "geometry": {"coordinates":[9.4401674271,54.760433197],"type":"Point"}
}