{
  "type": "Feature",
  "properties": {
    "iso:country":"DE",
    "sg:address":"Meiereistr. 3",
    "sg:city":"Leezen",
    "sg:phone":"+49 4945/529090",
    "sg:postcode":"23816",
    "sg:province":"Schleswig-Holstein",
    "wof:name":"Molkereigro\u00dfhandel Schleswig Holstein",
    "wof:placetype":"venue"
},
  "geometry": {"coordinates":[10.249023,53.869518],"type":"Point"}
}