{
  "type": "Feature",
  "properties": {
    "iso:country":"DE",
    "sg:address":"Fortunastr. 6",
    "sg:city":"W\u00fclfrath",
    "sg:phone":"+49 2058/79541",
    "sg:postcode":"42489",
    "sg:province":"Nordrhein-Westfalen",
    "wof:name":"Boefa Cnc-zerspannungstechnik Heinz B\u00f6hm",
    "wof:placetype":"venue"
},
  "geometry": {"coordinates":[7.0148901939,51.2777099609],"type":"Point"}
}