{
  "type": "Feature",
  "properties": {
    "iso:country":"DE",
    "sg:address":"Stauffenstr. 1",
    "sg:city":"Augsburg",
    "sg:phone":"+49 821/61367",
    "sg:postcode":"86163",
    "sg:province":"Bayern",
    "wof:name":"O. Tetikel",
    "wof:placetype":"venue"
},
  "geometry": {"coordinates":[10.9401140213,48.3552589417],"type":"Point"}
}