{
  "type": "Feature",
  "properties": {
    "iso:country":"DE",
    "sg:address":"Weingarts\u00e4cker 5",
    "sg:city":"W\u00fcstenrot",
    "sg:phone":"+49 7945/950982",
    "sg:postcode":"71543",
    "sg:province":"Baden-W\u00fcrttemberg",
    "wof:name":"Dieter Wulle",
    "wof:placetype":"venue"
},
  "geometry": {"coordinates":[9.466502,49.08017],"type":"Point"}
}