{
  "type": "Feature",
  "properties": {
    "iso:country":"DE",
    "sg:address":"Kobelstr. 9",
    "sg:city":"Neus\u00e4\u00df",
    "sg:phone":"+49 821/482398",
    "sg:postcode":"86356",
    "sg:province":"Bayern",
    "wof:name":"Reintex Rudolf Rahm",
    "wof:placetype":"venue"
},
  "geometry": {"coordinates":[10.822895,48.386272],"type":"Point"}
}