{
  "type": "Feature",
  "properties": {
    "iso:country":"DE",
    "sg:address":"Ernst-Th\u00e4lmann-Str. 117 a",
    "sg:city":"F\u00fcrstenwalde",
    "sg:phone":"+49 3361/2094",
    "sg:postcode":"15517",
    "sg:province":"Brandenburg",
    "wof:name":"Wolfgang Poland",
    "wof:placetype":"venue"
},
  "geometry": {"coordinates":[14.0608310699,52.3679122925],"type":"Point"}
}