{
  "type": "Feature",
  "properties": {
    "iso:country":"DE",
    "sg:address":"Schiffbauerstra\u00dfe 5-7",
    "sg:city":"Dorsten",
    "sg:phone":"+49 4923/6299260",
    "sg:postcode":"46282",
    "sg:province":"Nordrhein-Westfalen",
    "wof:name":"Interpartner Coiffeur-einrichtungs-design",
    "wof:placetype":"venue"
},
  "geometry": {"coordinates":[6.967303,51.662788],"type":"Point"}
}