{
  "type": "Feature",
  "properties": {
    "iso:country":"DE",
    "sg:address":"Wichlinghauser Marktstr. 9",
    "sg:city":"Wuppertal",
    "sg:phone":"+49 202/520152",
    "sg:postcode":"42277",
    "sg:province":"Nordrhein-Westfalen",
    "wof:name":"Karl-friedrich Gorsboth",
    "wof:placetype":"venue"
},
  "geometry": {"coordinates":[7.2141990662,51.2833213806],"type":"Point"}
}