{
  "type": "Feature",
  "properties": {
    "iso:country":"DE",
    "sg:address":"Hainer Weg 16",
    "sg:city":"Hofheim",
    "sg:phone":"+49 6192/8362",
    "sg:postcode":"65719",
    "sg:province":"Hessen",
    "wof:name":"Baudekoration E. Vatter",
    "wof:placetype":"venue"
},
  "geometry": {"coordinates":[8.414186,50.114662],"type":"Point"}
}