{
  "type": "Feature",
  "properties": {
    "iso:country":"DE",
    "sg:address":"K\u00f6lner Str. 12",
    "sg:city":"Wuppertal",
    "sg:phone":"+49 202/432356",
    "sg:postcode":"42119",
    "sg:province":"Nordrhein-Westfalen",
    "wof:name":"H.j. Schneider",
    "wof:placetype":"venue"
},
  "geometry": {"coordinates":[7.1432619095,51.2509803772],"type":"Point"}
}