{
  "type": "Feature",
  "properties": {
    "iso:country":"DE",
    "sg:address":"Kranoldstr. 21",
    "sg:city":"Berlin",
    "sg:phone":"+49 4922/0456851",
    "sg:postcode":"12051",
    "sg:province":"Berlin",
    "wof:name":"Volker Sydow",
    "wof:placetype":"venue"
},
  "geometry": {"coordinates":[7.162134,50.96817],"type":"Point"}
}