{
  "type": "Feature",
  "properties": {
    "iso:country":"DE",
    "sg:address":"August-Broemel-Str. 9",
    "sg:city":"Arnstadt",
    "sg:phone":"+49 3628/5980",
    "sg:postcode":"99310",
    "sg:province":"Th\u00fcringen",
    "wof:name":"Hagebaumarkt Centrum Gmbh",
    "wof:placetype":"venue"
},
  "geometry": {"coordinates":[10.9491901398,50.8546409607],"type":"Point"}
}