{
  "type": "Feature",
  "properties": {
    "iso:country":"DE",
    "sg:address":"Ahltener Str. 4-8",
    "sg:city":"Lehrte",
    "sg:phone":"+49 4951/322066",
    "sg:postcode":"31275",
    "sg:province":"Niedersachsen",
    "wof:name":"Carl Graf Kg",
    "wof:placetype":"venue"
},
  "geometry": {"coordinates":[9.974931,52.372627],"type":"Point"}
}