{
  "type": "Feature",
  "properties": {
    "iso:country":"DE",
    "sg:address":"Vormarkt 7",
    "sg:city":"Trostberg",
    "sg:phone":"+49 8621/2034",
    "sg:postcode":"83308",
    "sg:province":"Bayern",
    "wof:name":"Kreissparkasse Traunstein-tros",
    "wof:placetype":"venue"
},
  "geometry": {"coordinates":[12.551714,48.027695],"type":"Point"}
}