{
  "type": "Feature",
  "properties": {
    "iso:country":"DE",
    "sg:address":"Kanalstr 1",
    "sg:city":"Mering",
    "sg:phone":"+49 8233/739960",
    "sg:postcode":"86415",
    "sg:province":"Bayern",
    "wof:name":"Agb Lachner Anlagen-und Ger\u00e4tebau Kg",
    "wof:placetype":"venue"
},
  "geometry": {"coordinates":[10.9804983139,48.2638130188],"type":"Point"}
}