{
  "type": "Feature",
  "properties": {
    "iso:country":"DE",
    "sg:address":"Laurentiusweg 4",
    "sg:city":"Freising",
    "sg:phone":"+49 8161/631",
    "sg:postcode":"85354",
    "sg:province":"Bayern",
    "wof:name":"Kath. Pfarramt",
    "wof:placetype":"venue"
},
  "geometry": {"coordinates":[11.7222166061,48.4397392273],"type":"Point"}
}