{
  "type": "Feature",
  "properties": {
    "iso:country":"DE",
    "sg:address":"Wernsreute 20",
    "sg:city":"Ravensburg",
    "sg:phone":"+49 7546/672",
    "sg:postcode":"88213",
    "sg:province":"Baden-W\u00fcrttemberg",
    "wof:name":"Alfons Bentele",
    "wof:placetype":"venue"
},
  "geometry": {"coordinates":[9.513478,47.751484],"type":"Point"}
}