{
  "type": "Feature",
  "properties": {
    "iso:country":"DE",
    "sg:address":"Grabenstr. 149a",
    "sg:city":"Duisburg",
    "sg:phone":"+49 203/378670",
    "sg:postcode":"47057",
    "sg:province":"Nordrhein-Westfalen",
    "wof:name":"Ipas Ingenieurgesellschaft F\u00fcr Automation Und",
    "wof:placetype":"venue"
},
  "geometry": {"coordinates":[6.7850780487,51.4240951538],"type":"Point"}
}