{
  "type": "Feature",
  "properties": {
    "iso:country":"DE",
    "sg:address":"Asbacher Str. 2",
    "sg:city":"Asbach-Hussen",
    "sg:phone":"+49 2683/7499",
    "sg:postcode":"53567",
    "sg:province":"Rheinland-Pfalz",
    "wof:name":"Fgs-sielemann",
    "wof:placetype":"venue"
},
  "geometry": {"coordinates":[7.392666,50.686394],"type":"Point"}
}