{
  "type": "Feature",
  "properties": {
    "iso:country":"DE",
    "sg:address":"Epkingstr. 13",
    "sg:city":"Dortmund",
    "sg:phone":"+49 231/456135",
    "sg:postcode":"44309",
    "sg:province":"Nordrhein-Westfalen",
    "wof:name":"Gebr. Visscher Ohg",
    "wof:placetype":"venue"
},
  "geometry": {"coordinates":[7.5495929718,51.5320053101],"type":"Point"}
}