{
  "type": "Feature",
  "properties": {
    "iso:country":"DE",
    "sg:address":"Spandauer Str. 112",
    "sg:city":"Falkensee",
    "sg:phone":"+49 3322/206906",
    "sg:postcode":"14612",
    "sg:province":"Brandenburg",
    "wof:name":"T. Auping",
    "wof:placetype":"venue"
},
  "geometry": {"coordinates":[13.12671,52.560665],"type":"Point"}
}