{
  "type": "Feature",
  "properties": {
    "iso:country":"DE",
    "sg:address":"Schellingstr. 131",
    "sg:city":"M\u00fcnchen",
    "sg:phone":"+49 89/525847",
    "sg:postcode":"80798",
    "sg:province":"Bayern",
    "wof:name":"W. Brezina",
    "wof:placetype":"venue"
},
  "geometry": {"coordinates":[11.5629854202,48.1538085938],"type":"Point"}
}