{
  "type": "Feature",
  "properties": {
    "iso:country":"DE",
    "sg:address":"L\u00fcttkamp 30",
    "sg:city":"Hamburg",
    "sg:phone":"+49 40/845774",
    "sg:postcode":"22547",
    "sg:province":"Hamburg",
    "wof:name":"Michael Erdmann",
    "wof:placetype":"venue"
},
  "geometry": {"coordinates":[9.8773269653,53.5921211243],"type":"Point"}
}