{
  "type": "Feature",
  "properties": {
    "iso:country":"DE",
    "sg:address":"Landauer Str. 9",
    "sg:city":"Neustadt",
    "sg:phone":"+49 6321/33238",
    "sg:postcode":"67434",
    "sg:province":"Rheinland-Pfalz",
    "wof:name":"Spielforum",
    "wof:placetype":"venue"
},
  "geometry": {"coordinates":[8.1383647919,49.3506507874],"type":"Point"}
}