{
  "type": "Feature",
  "properties": {
    "iso:country":"DE",
    "sg:address":"Kirchstr. 5",
    "sg:city":"Riedstadt",
    "sg:phone":"+49 6158/71466",
    "sg:postcode":"64560",
    "sg:province":"Hessen",
    "wof:name":"Gg. Wald",
    "wof:placetype":"venue"
},
  "geometry": {"coordinates":[8.46561,49.838013],"type":"Point"}
}