{
  "type": "Feature",
  "properties": {
    "iso:country":"DE",
    "sg:address":"Kirchheimer Str. 10",
    "sg:city":"Stuttgart",
    "sg:phone":"+49 711/473568",
    "sg:postcode":"70619",
    "sg:province":"Baden-W\u00fcrttemberg",
    "wof:name":"Herbert Gebauer Bildhauer",
    "wof:placetype":"venue"
},
  "geometry": {"coordinates":[9.236989,48.736748],"type":"Point"}
}