{
  "type": "Feature",
  "properties": {
    "iso:country":"DE",
    "sg:address":"Knieperstr. 20",
    "sg:city":"Stralsund",
    "sg:phone":"+49 3831/292818",
    "sg:postcode":"18439",
    "sg:province":"Mecklenburg-Vorpommern",
    "wof:name":"Dr. Med. L\u00fcder Stock Arzt F\u00fcr P\u00e4diatrie",
    "wof:placetype":"venue"
},
  "geometry": {"coordinates":[13.0899629593,54.3163108826],"type":"Point"}
}