{
  "type": "Feature",
  "properties": {
    "iso:country":"DE",
    "sg:address":"Marzahner Chaussee 7",
    "sg:city":"Berlin",
    "sg:phone":"+49 30/5101750",
    "sg:postcode":"10315",
    "sg:province":"Berlin",
    "wof:name":"Manfred Worbs",
    "wof:placetype":"venue"
},
  "geometry": {"coordinates":[13.5214776993,52.5108375549],"type":"Point"}
}