{
  "type": "Feature",
  "properties": {
    "iso:country":"DE",
    "sg:address":"Alte R\u00f6hler Str. 13",
    "sg:city":"Bitburg",
    "sg:phone":"+49 6561/3179",
    "sg:postcode":"54634",
    "sg:province":"Rheinland-Pfalz",
    "wof:name":"Wadle& Co. Verwaltungsges. Mbh",
    "wof:placetype":"venue"
},
  "geometry": {"coordinates":[6.564605,49.954407],"type":"Point"}
}