{
  "type": "Feature",
  "properties": {
    "iso:country":"DE",
    "sg:address":"Am Plan 38g",
    "sg:city":"Scharfenstein",
    "sg:phone":"+49 3725/77432",
    "sg:postcode":"09435",
    "sg:province":"Sachsen",
    "wof:name":"H. L\u00f6tzsch",
    "wof:placetype":"venue"
},
  "geometry": {"coordinates":[13.057556,50.70134],"type":"Point"}
}