{
  "type": "Feature",
  "properties": {
    "iso:country":"DE",
    "sg:address":"Zepfenhaner Str. 7",
    "sg:city":"Rottweil",
    "sg:phone":"+49 7427/94850",
    "sg:postcode":"78628",
    "sg:province":"Baden-W\u00fcrttemberg",
    "wof:name":"Roming Werkzeugbau Gmbh",
    "wof:placetype":"venue"
},
  "geometry": {"coordinates":[8.701947,48.197357],"type":"Point"}
}