{
  "type": "Feature",
  "properties": {
    "iso:country":"DE",
    "sg:address":"Kupferhammerstr 89",
    "sg:city":"Guben",
    "sg:phone":"+49 3561/62008",
    "sg:postcode":"03172",
    "sg:province":"Brandenburg",
    "wof:name":"E&k Hansmann Gbr",
    "wof:placetype":"venue"
},
  "geometry": {"coordinates":[14.702265,51.958996],"type":"Point"}
}