{
  "type": "Feature",
  "properties": {
    "iso:country":"DE",
    "sg:address":"Malberger Str. 14",
    "sg:city":"Kyllburg",
    "sg:phone":"+49 6563/2822",
    "sg:postcode":"54655",
    "sg:province":"Rheinland-Pfalz",
    "wof:name":"H. Herzig",
    "wof:placetype":"venue"
},
  "geometry": {"coordinates":[6.5901789665,50.0421867371],"type":"Point"}
}