{
  "type": "Feature",
  "properties": {
    "iso:country":"DE",
    "sg:address":"Schillerstr. 32",
    "sg:city":"M\u00fcnchen",
    "sg:phone":"+49 89/591005",
    "sg:postcode":"80336",
    "sg:province":"Bayern",
    "wof:name":"Lugano Hotelbetriebsges. Mbh",
    "wof:placetype":"venue"
},
  "geometry": {"coordinates":[11.5606927872,48.1360359192],"type":"Point"}
}