{
  "type": "Feature",
  "properties": {
    "iso:country":"DE",
    "sg:address":"Kasseler Str. 40",
    "sg:city":"Melsungen",
    "sg:phone":"+49 5661/3102",
    "sg:postcode":"34212",
    "sg:province":"Hessen",
    "wof:name":"A. Klabunde",
    "wof:placetype":"venue"
},
  "geometry": {"coordinates":[9.541852,51.132809],"type":"Point"}
}