{
  "type": "Feature",
  "properties": {
    "iso:country":"DE",
    "sg:address":"Spitalgasse 2",
    "sg:city":"Weinsberg",
    "sg:postcode":"74189",
    "sg:province":"Baden-W\u00fcrttemberg",
    "wof:name":"Arh Hausverwaltung",
    "wof:placetype":"venue"
},
  "geometry": {"coordinates":[9.2835597992,49.15102005],"type":"Point"}
}