{
  "type": "Feature",
  "properties": {
    "iso:country":"DE",
    "sg:address":"Dehlinger Weg 9",
    "sg:city":"K\u00f6ln",
    "sg:postcode":"50767",
    "sg:province":"Nordrhein-Westfalen",
    "wof:name":"Behindertenwerkstatt",
    "wof:placetype":"venue"
},
  "geometry": {"coordinates":[6.887284,51.003471],"type":"Point"}
}