{
  "type": "Feature",
  "properties": {
    "iso:country":"DE",
    "sg:address":"Am Trinkborn 8",
    "sg:city":"Emmelshausen",
    "sg:phone":"+49 4967/471535",
    "sg:postcode":"56281",
    "sg:province":"Rheinland-Pfalz",
    "wof:name":"Nass Transporte Gmbh Nah- U. Fernverkehr",
    "wof:placetype":"venue"
},
  "geometry": {"coordinates":[7.5569248199,50.1559791565],"type":"Point"}
}