{
  "type": "Feature",
  "properties": {
    "iso:country":"DE",
    "sg:address":"Am Heidenstock 27",
    "sg:city":"Sch\u00f6ffengrund",
    "sg:phone":"+49 6445/848",
    "sg:postcode":"35641",
    "sg:province":"Hessen",
    "wof:name":"M. V\u00f6lk",
    "wof:placetype":"venue"
},
  "geometry": {"coordinates":[8.520558,50.477627],"type":"Point"}
}