{
  "type": "Feature",
  "properties": {
    "iso:country":"DE",
    "sg:address":"Karlstar\u00dfe",
    "sg:city":"Dessau",
    "sg:phone":"+49 340/2303510",
    "sg:postcode":"06844",
    "sg:province":"Sachsen-Anhalt",
    "wof:name":"Formpunkt - Agentur F\u00fcr Visuelle Kommunikation",
    "wof:placetype":"venue"
},
  "geometry": {"coordinates":[12.25712,51.839779],"type":"Point"}
}