{
  "type": "Feature",
  "properties": {
    "iso:country":"DE",
    "sg:address":"Weststr. 4",
    "sg:city":"Minden",
    "sg:postcode":"32425",
    "sg:province":"Nordrhein-Westfalen",
    "wof:name":"Hoffmann Beteiligungen Gmbh",
    "wof:placetype":"venue"
},
  "geometry": {"coordinates":[8.89272,52.338268],"type":"Point"}
}