{
  "type": "Feature",
  "properties": {
    "iso:country":"DE",
    "sg:address":"\u00d6hder Str 4-4 a",
    "sg:city":"Wuppertal",
    "sg:phone":"+49 202/609050",
    "sg:postcode":"42289",
    "sg:province":"Nordrhein-Westfalen",
    "wof:name":"Abacus Gesellschaft F\u00fcr Software- Engineering Mbh",
    "wof:placetype":"venue"
},
  "geometry": {"coordinates":[7.236481,51.266869],"type":"Point"}
}