{
  "type": "Feature",
  "properties": {
    "iso:country":"DE",
    "sg:address":"Bei der Pauluskirche 4",
    "sg:city":"Hamburg",
    "sg:phone":"+49 40/856951",
    "sg:postcode":"22769",
    "sg:province":"Hamburg",
    "wof:name":"Ev. Pfarramt Ii Pauluskirche",
    "wof:placetype":"venue"
},
  "geometry": {"coordinates":[9.9468708038,53.5676345825],"type":"Point"}
}