{
  "type": "Feature",
  "properties": {
    "iso:country":"DE",
    "sg:address":"Im Drostebusch 12c",
    "sg:city":"M\u00fcnster",
    "sg:phone":"+49 251/314154",
    "sg:postcode":"48155",
    "sg:province":"Nordrhein-Westfalen",
    "wof:name":"Dieter Lackmann",
    "wof:placetype":"venue"
},
  "geometry": {"coordinates":[7.6742157936,51.9561958313],"type":"Point"}
}