{
  "type": "Feature",
  "properties": {
    "iso:country":"DE",
    "sg:address":"Filderhauptstr. 44",
    "sg:city":"Stuttgart",
    "sg:phone":"+49 711/4579269",
    "sg:postcode":"70599",
    "sg:province":"Baden-W\u00fcrttemberg",
    "wof:name":"G\u00fcnter Gehrung Kg",
    "wof:placetype":"venue"
},
  "geometry": {"coordinates":[9.208929,48.701691],"type":"Point"}
}