{
  "type": "Feature",
  "properties": {
    "iso:country":"DE",
    "sg:address":"Gro\u00dfe Str. 38",
    "sg:city":"Steinfeld",
    "sg:phone":"+49 5492/747",
    "sg:postcode":"49439",
    "sg:province":"Niedersachsen",
    "wof:name":"Katholisches Pfarramt St. Bonaventura",
    "wof:placetype":"venue"
},
  "geometry": {"coordinates":[8.2181930542,52.5880012512],"type":"Point"}
}