{
  "type": "Feature",
  "properties": {
    "iso:country":"DE",
    "sg:address":"Lennestr. 64",
    "sg:city":"Hagen",
    "sg:phone":"+49 2331/53734",
    "sg:postcode":"58093",
    "sg:province":"Nordrhein-Westfalen",
    "wof:name":"Ernst Brinkmann",
    "wof:placetype":"venue"
},
  "geometry": {"coordinates":[7.51847,51.372532],"type":"Point"}
}