{
  "type": "Feature",
  "properties": {
    "iso:country":"DE",
    "sg:address":"Neue Str. 8",
    "sg:city":"Buchholz",
    "sg:phone":"+49 4181/97521",
    "sg:postcode":"21244",
    "sg:province":"Niedersachsen",
    "wof:name":"Madness",
    "wof:placetype":"venue"
},
  "geometry": {"coordinates":[10.747314,53.731136],"type":"Point"}
}