{
  "type": "Feature",
  "properties": {
    "iso:country":"DE",
    "sg:address":"Zum Nixenteich 18",
    "sg:city":"Sch\u00f6nfeld",
    "sg:phone":"+49 351/4606277",
    "sg:postcode":"01561",
    "sg:province":"Sachsen",
    "wof:name":"Dr. Matthias Aldejohann Rechtsanwalt",
    "wof:placetype":"venue"
},
  "geometry": {"coordinates":[13.8853292465,51.0367126465],"type":"Point"}
}