{
  "type": "Feature",
  "properties": {
    "iso:country":"DE",
    "sg:address":"Auf dem Treppchen 14",
    "sg:city":"Oberkail",
    "sg:postcode":"54533",
    "sg:province":"Rheinland-Pfalz",
    "wof:name":"Martin Lenartz Gmbh",
    "wof:placetype":"venue"
},
  "geometry": {"coordinates":[6.676573,50.036335],"type":"Point"}
}