{
  "type": "Feature",
  "properties": {
    "iso:country":"DE",
    "sg:address":"E\u00dfweiler Str. 154a",
    "sg:city":"Rothselberg",
    "sg:phone":"+49 4963/041323",
    "sg:postcode":"67753",
    "sg:province":"Rheinland-Pfalz",
    "wof:name":"Kreissparkasse Kusel",
    "wof:placetype":"venue"
},
  "geometry": {"coordinates":[7.5905,49.54845],"type":"Point"}
}