{
  "type": "Feature",
  "properties": {
    "iso:country":"DE",
    "sg:address":"Bl\u00fccherstr. 8",
    "sg:city":"M\u00f6nchengladbach",
    "sg:phone":"+49 2161/22583",
    "sg:postcode":"41061",
    "sg:province":"Nordrhein-Westfalen",
    "wof:name":"Dieter Brinks Rechtsanwalt",
    "wof:placetype":"venue"
},
  "geometry": {"coordinates":[6.436606884,51.1973075867],"type":"Point"}
}