{
  "type": "Feature",
  "properties": {
    "iso:country":"DE",
    "sg:address":"Marienh\u00f6he 77",
    "sg:city":"Quickborn",
    "sg:phone":"+49 4106/81356",
    "sg:postcode":"25451",
    "sg:province":"Schleswig-Holstein",
    "wof:name":"Tresor Treuhand Gmbh",
    "wof:placetype":"venue"
},
  "geometry": {"coordinates":[9.9032764435,53.7262077332],"type":"Point"}
}