{
  "type": "Feature",
  "properties": {
    "iso:country":"DE",
    "sg:address":"Kiebitzberg 6",
    "sg:city":"Putlitz",
    "sg:phone":"+49 33981/80292",
    "sg:postcode":"16949",
    "sg:province":"Brandenburg",
    "wof:name":"Putlitzer Bautr\u00e4gerges. Mbh",
    "wof:placetype":"venue"
},
  "geometry": {"coordinates":[12.0409460068,53.247467041],"type":"Point"}
}