{
  "type": "Feature",
  "properties": {
    "iso:country":"DE",
    "sg:address":"Blumenstr. 6",
    "sg:city":"Regensburg",
    "sg:phone":"+49 941/795250",
    "sg:postcode":"93055",
    "sg:province":"Bayern",
    "wof:name":"P. Burkes Rechtsanwalt",
    "wof:placetype":"venue"
},
  "geometry": {"coordinates":[12.111825943,49.0124435425],"type":"Point"}
}