{
  "type": "Feature",
  "properties": {
    "iso:country":"DE",
    "sg:address":"Luisenstr. 8",
    "sg:city":"G\u00f6rlitz",
    "sg:phone":"+49 3581/406528",
    "sg:postcode":"02826",
    "sg:province":"Sachsen",
    "wof:name":"Soziales Arbeitsprojekt Ostsachsen E. V.",
    "wof:placetype":"venue"
},
  "geometry": {"coordinates":[14.983584404,51.1529808044],"type":"Point"}
}