{
  "type": "Feature",
  "properties": {
    "iso:country":"DE",
    "sg:address":"Friedrich-Wilhelm-Platz 13",
    "sg:city":"Berlin",
    "sg:phone":"+49 30/8590950",
    "sg:postcode":"12161",
    "sg:province":"Berlin",
    "wof:name":"Franz J. Schr\u00f6er Steuerberater",
    "wof:placetype":"venue"
},
  "geometry": {"coordinates":[13.3290872574,52.4722824097],"type":"Point"}
}