{
  "type": "Feature",
  "properties": {
    "iso:country":"DE",
    "sg:address":"Wilhelm-Tell-Str. 18",
    "sg:city":"Hannover",
    "sg:phone":"+49 511/586472",
    "sg:postcode":"30629",
    "sg:province":"Niedersachsen",
    "wof:name":"Rolf Kerkhof Architekt",
    "wof:placetype":"venue"
},
  "geometry": {"coordinates":[9.836513,52.396076],"type":"Point"}
}