{
  "type": "Feature",
  "properties": {
    "iso:country":"DE",
    "sg:address":"Berliner Str. 6",
    "sg:city":"Neutraubling",
    "sg:postcode":"93073",
    "sg:province":"Bayern",
    "wof:name":"Guido Kg",
    "wof:placetype":"venue"
},
  "geometry": {"coordinates":[12.1929502487,48.985748291],"type":"Point"}
}