{
  "type": "Feature",
  "properties": {
    "iso:country":"DE",
    "sg:address":"Schlo\u00dfstr. 14",
    "sg:city":"Sonthofen",
    "sg:phone":"+49 8321/1240",
    "sg:postcode":"87527",
    "sg:province":"Bayern",
    "wof:name":"Wirthensohn B\u00e4ckerei- Und Konditorei-betrieb Gmbh",
    "wof:placetype":"venue"
},
  "geometry": {"coordinates":[10.27854,47.510571],"type":"Point"}
}