{
  "type": "Feature",
  "properties": {
    "iso:country":"DE",
    "sg:address":"Widenmayerstr. 46",
    "sg:city":"M\u00fcnchen",
    "sg:phone":"+49 89/224534",
    "sg:postcode":"80538",
    "sg:province":"Bayern",
    "wof:name":"Dr. Med. Gabriele Siebert",
    "wof:placetype":"venue"
},
  "geometry": {"coordinates":[11.595952034,48.1483917236],"type":"Point"}
}