{
  "type": "Feature",
  "properties": {
    "iso:country":"DE",
    "sg:address":"Haller Str. 5",
    "sg:city":"Rosengarten",
    "sg:phone":"+49 791/51256",
    "sg:postcode":"74538",
    "sg:province":"Baden-W\u00fcrttemberg",
    "wof:name":"L. Schade",
    "wof:placetype":"venue"
},
  "geometry": {"coordinates":[9.73205,49.058578],"type":"Point"}
}