{
  "type": "Feature",
  "properties": {
    "iso:country":"DE",
    "sg:address":"Heidelberger Landstr. 306",
    "sg:city":"Darmstadt",
    "sg:phone":"+49 6151/55022",
    "sg:postcode":"64297",
    "sg:province":"Hessen",
    "wof:name":"Hotel Rehm",
    "wof:placetype":"venue"
},
  "geometry": {"coordinates":[8.644276619,49.8115234375],"type":"Point"}
}