{
  "type": "Feature",
  "properties": {
    "iso:country":"DE",
    "sg:address":"Hermannstr. 152",
    "sg:city":"Wei\u00dfwasser",
    "sg:phone":"+49 3576/242379",
    "sg:postcode":"02943",
    "sg:province":"Sachsen",
    "wof:name":"Gerd Schultz",
    "wof:placetype":"venue"
},
  "geometry": {"coordinates":[14.61577034,51.5031890869],"type":"Point"}
}