{
  "type": "Feature",
  "properties": {
    "iso:country":"DE",
    "sg:address":"Flottowenweg 69",
    "sg:city":"Mettingen",
    "sg:phone":"+49 5452/7349",
    "sg:postcode":"49497",
    "sg:province":"Nordrhein-Westfalen",
    "wof:name":"Heitling Haustechnik Gmbh",
    "wof:placetype":"venue"
},
  "geometry": {"coordinates":[7.787265,52.329494],"type":"Point"}
}