{
  "type": "Feature",
  "properties": {
    "iso:country":"DE",
    "sg:address":"Schwalbenweg 5",
    "sg:city":"Neu Woserin",
    "sg:postcode":"19406",
    "sg:province":"Mecklenburg-Vorpommern",
    "wof:name":"Easybau Gmbh",
    "wof:placetype":"venue"
},
  "geometry": {"coordinates":[11.991142,53.657787],"type":"Point"}
}