{
  "type": "Feature",
  "properties": {
    "iso:country":"DE",
    "sg:address":"Am Helgenpfad 17",
    "sg:city":"Wiesbaden",
    "sg:phone":"+49 611/692146",
    "sg:postcode":"65203",
    "sg:province":"Hessen",
    "wof:name":"Kindergarten Am\u00f6neburg E. V.",
    "wof:placetype":"venue"
},
  "geometry": {"coordinates":[8.2601709366,50.0279350281],"type":"Point"}
}