{
  "type": "Feature",
  "properties": {
    "iso:country":"DE",
    "sg:address":"Schindenstr. 3",
    "sg:city":"Bisingen",
    "sg:phone":"+49 7476/7531",
    "sg:postcode":"72406",
    "sg:province":"Baden-W\u00fcrttemberg",
    "wof:name":"Karl-heinz Buckenmaier",
    "wof:placetype":"venue"
},
  "geometry": {"coordinates":[8.9358491898,48.299949646],"type":"Point"}
}