{
  "type": "Feature",
  "properties": {
    "iso:country":"DE",
    "sg:address":"M\u00fchlhoferstr. 8",
    "sg:city":"Daisendorf",
    "sg:phone":"+49 7532/6150",
    "sg:postcode":"88718",
    "sg:province":"Baden-W\u00fcrttemberg",
    "wof:name":"Walter Wegener",
    "wof:placetype":"venue"
},
  "geometry": {"coordinates":[9.265146,47.712936],"type":"Point"}
}