{
  "type": "Feature",
  "properties": {
    "iso:country":"DE",
    "sg:address":"Zum Tellbusch 27",
    "sg:city":"Bad Salzuflen",
    "sg:phone":"+49 5222/797598",
    "sg:postcode":"32107",
    "sg:province":"Nordrhein-Westfalen",
    "wof:name":"Friwo-telekommunikation",
    "wof:placetype":"venue"
},
  "geometry": {"coordinates":[8.7153949738,52.0407028198],"type":"Point"}
}