{
  "type": "Feature",
  "properties": {
    "iso:country":"DE",
    "sg:address":"Heerstr. 145",
    "sg:city":"Bonn",
    "sg:phone":"+49 228/657167",
    "sg:postcode":"53111",
    "sg:province":"Nordrhein-Westfalen",
    "wof:name":"G. Holtmann",
    "wof:placetype":"venue"
},
  "geometry": {"coordinates":[7.090371,50.737377],"type":"Point"}
}