{
  "type": "Feature",
  "properties": {
    "iso:country":"DE",
    "sg:address":"Hof Dicke",
    "sg:city":"Calw",
    "sg:phone":"+49 7051/30700",
    "sg:postcode":"75365",
    "sg:province":"Baden-W\u00fcrttemberg",
    "wof:name":"Michael Adams",
    "wof:placetype":"venue"
},
  "geometry": {"coordinates":[8.741439,48.677921],"type":"Point"}
}