{
  "type": "Feature",
  "properties": {
    "iso:country":"DE",
    "sg:address":"An der Katzenaue",
    "sg:city":"Eisenach",
    "sg:phone":"+49 3691/77123",
    "sg:postcode":"99817",
    "sg:province":"Th\u00fcringen",
    "wof:name":"Sportlerklause",
    "wof:placetype":"venue"
},
  "geometry": {"coordinates":[10.3071651459,50.9860191345],"type":"Point"}
}