{
  "type": "Feature",
  "properties": {
    "iso:country":"DE",
    "sg:address":"Hermannstr. 33",
    "sg:city":"Bonn",
    "sg:phone":"+49 228/461008",
    "sg:postcode":"53225",
    "sg:province":"Nordrhein-Westfalen",
    "wof:name":"Metrovision Film Gmbh",
    "wof:placetype":"venue"
},
  "geometry": {"coordinates":[7.1171898842,50.7373504639],"type":"Point"}
}