{
  "type": "Feature",
  "properties": {
    "iso:country":"DE",
    "sg:address":"Klosterstr. 7",
    "sg:city":"Blaubeuren",
    "sg:phone":"+49 7344/919014",
    "sg:postcode":"89143",
    "sg:province":"Baden-W\u00fcrttemberg",
    "wof:name":"Fahrner",
    "wof:placetype":"venue"
},
  "geometry": {"coordinates":[9.7838821411,48.4133377075],"type":"Point"}
}