{
  "type": "Feature",
  "properties": {
    "iso:country":"DE",
    "sg:address":"Ihlefelder Str. 1",
    "sg:city":"M\u00fclverstedt",
    "sg:phone":"+49 36022/96604",
    "sg:postcode":"99947",
    "sg:province":"Th\u00fcringen",
    "wof:name":"Gemeindeschenke",
    "wof:placetype":"venue"
},
  "geometry": {"coordinates":[10.5052442551,51.1188430786],"type":"Point"}
}