{
  "type": "Feature",
  "properties": {
    "iso:country":"DE",
    "sg:address":"M\u00fchlenweg 14",
    "sg:city":"Oyten",
    "sg:phone":"+49 4207/4704",
    "sg:postcode":"28876",
    "sg:province":"Niedersachsen",
    "wof:name":"Hans Weidemann",
    "wof:placetype":"venue"
},
  "geometry": {"coordinates":[9.031503,53.059402],"type":"Point"}
}