{
  "type": "Feature",
  "properties": {
    "iso:country":"DE",
    "sg:address":"Rosenweg 3",
    "sg:city":"Kremperheide",
    "sg:postcode":"25569",
    "sg:province":"Schleswig-Holstein",
    "wof:name":"Dibog Spielhallen Gmbh",
    "wof:placetype":"venue"
},
  "geometry": {"coordinates":[9.483092308,53.8956451416],"type":"Point"}
}