{
  "type": "Feature",
  "properties": {
    "iso:country":"DE",
    "sg:address":"St.-Peters-Weg 6 a",
    "sg:city":"H\u00fcnstetten",
    "sg:phone":"+49 6126/570824",
    "sg:postcode":"65510",
    "sg:province":"Hessen",
    "wof:name":"Dreku-bau Gmbh",
    "wof:placetype":"venue"
},
  "geometry": {"coordinates":[8.2310190201,50.2690315247],"type":"Point"}
}