{
  "type": "Feature",
  "properties": {
    "iso:country":"DE",
    "sg:address":"Neuenhausplatz 26",
    "sg:city":"Erkrath",
    "sg:phone":"+49 211/253231",
    "sg:postcode":"40699",
    "sg:province":"Nordrhein-Westfalen",
    "wof:name":"Grillparadies Helga Schr\u00f6der",
    "wof:placetype":"venue"
},
  "geometry": {"coordinates":[6.9144067764,51.2024230957],"type":"Point"}
}