{
  "type": "Feature",
  "properties": {
    "iso:country":"DE",
    "sg:address":"In den Auen 77",
    "sg:city":"Baiersbronn",
    "sg:phone":"+49 7447/94660",
    "sg:postcode":"72270",
    "sg:province":"Baden-W\u00fcrttemberg",
    "wof:name":"Innenausbau Michael Klumpp Gmbh & Co.",
    "wof:placetype":"venue"
},
  "geometry": {"coordinates":[8.38008,48.599819],"type":"Point"}
}