{
  "type": "Feature",
  "properties": {
    "iso:country":"DE",
    "sg:address":"Talstr. 25",
    "sg:city":"Trier",
    "sg:phone":"+49 651/67889",
    "sg:postcode":"54293",
    "sg:province":"Rheinland-Pfalz",
    "wof:name":"G. Morbe",
    "wof:placetype":"venue"
},
  "geometry": {"coordinates":[6.661664,49.779377],"type":"Point"}
}