{
  "type": "Feature",
  "properties": {
    "iso:country":"DE",
    "sg:address":"Herxheimerstr. 6",
    "sg:city":"Frankfurt",
    "sg:phone":"+49 69/731997",
    "sg:postcode":"60326",
    "sg:province":"Hessen",
    "wof:name":"Naturfreundehaus Stadtheim Frankfurt",
    "wof:placetype":"venue"
},
  "geometry": {"coordinates":[8.624786377,50.0986251831],"type":"Point"}
}