{
  "type": "Feature",
  "properties": {
    "iso:country":"DE",
    "sg:address":"Thomas-Dehler-Str. 25",
    "sg:city":"M\u00fcnchen",
    "sg:phone":"+49 89/67879453",
    "sg:postcode":"81737",
    "sg:province":"Bayern",
    "wof:name":"Bbv-baubetreuungs- Und Grunderwerbsges. Mbh",
    "wof:placetype":"venue"
},
  "geometry": {"coordinates":[11.645198,48.098305],"type":"Point"}
}