{
  "type": "Feature",
  "properties": {
    "iso:country":"DE",
    "sg:address":"Kempgensweg 42",
    "sg:city":"D\u00fcsseldorf",
    "sg:phone":"+49 211/2293666",
    "sg:postcode":"40231",
    "sg:province":"Nordrhein-Westfalen",
    "wof:name":"A. Bark Finanzberater",
    "wof:placetype":"venue"
},
  "geometry": {"coordinates":[6.8267679214,51.2079429626],"type":"Point"}
}