{
  "type": "Feature",
  "properties": {
    "iso:country":"DE",
    "sg:address":"Widdersdorfer Str 207",
    "sg:city":"K\u00f6ln",
    "sg:phone":"+49 221/9544820",
    "sg:postcode":"50825",
    "sg:province":"Nordrhein-Westfalen",
    "wof:name":"Hablowetz Communications Group Beta Gmbh",
    "wof:placetype":"venue"
},
  "geometry": {"coordinates":[6.9013957977,50.9457244873],"type":"Point"}
}