{
  "type": "Feature",
  "properties": {
    "iso:country":"DE",
    "sg:address":"Waldstr. 5",
    "sg:city":"Sondershausen",
    "sg:phone":"+49 3632/707845",
    "sg:postcode":"99706",
    "sg:province":"Th\u00fcringen",
    "wof:name":"B\u00f6ttger Und Kollegen Rechtsanw\u00e4lte",
    "wof:placetype":"venue"
},
  "geometry": {"coordinates":[10.902094841,51.3530158997],"type":"Point"}
}