{
  "type": "Feature",
  "properties": {
    "iso:country":"DE",
    "sg:address":"Arolser Str. 20",
    "sg:city":"Bad Pyrmont",
    "sg:phone":"+49 5281/609115",
    "sg:postcode":"31812",
    "sg:province":"Niedersachsen",
    "wof:name":"Bautec Bauelemente Und Technik Handels-",
    "wof:placetype":"venue"
},
  "geometry": {"coordinates":[9.267845,51.980507],"type":"Point"}
}