{
  "type": "Feature",
  "properties": {
    "iso:country":"DE",
    "sg:address":"Hersfelder Str.",
    "sg:city":"Bebra",
    "sg:phone":"+49 6622/3998",
    "sg:postcode":"36179",
    "sg:province":"Hessen",
    "wof:name":"H. Knieriem",
    "wof:placetype":"venue"
},
  "geometry": {"coordinates":[9.7951698303,50.9656105042],"type":"Point"}
}