{
  "type": "Feature",
  "properties": {
    "iso:country":"DE",
    "sg:address":"B\u00fccklestr. 7",
    "sg:city":"Konstanz",
    "sg:phone":"+49 7531/61304",
    "sg:postcode":"78467",
    "sg:province":"Baden-W\u00fcrttemberg",
    "wof:name":"Willy Weber",
    "wof:placetype":"venue"
},
  "geometry": {"coordinates":[9.1643695831,47.6795158386],"type":"Point"}
}