{
  "type": "Feature",
  "properties": {
    "iso:country":"DE",
    "sg:address":"Westlicher Stadtgraben 30",
    "sg:city":"Deggendorf",
    "sg:phone":"+49 991/32610",
    "sg:postcode":"94469",
    "sg:province":"Bayern",
    "wof:name":"Irmengard Fritsche Heilpraktikerin",
    "wof:placetype":"venue"
},
  "geometry": {"coordinates":[12.9595355988,48.8334541321],"type":"Point"}
}