{
  "type": "Feature",
  "properties": {
    "iso:country":"DE",
    "sg:address":"Bahnhofstr. 16",
    "sg:city":"Rottenburg",
    "sg:phone":"+49 7472/165351",
    "sg:postcode":"72108",
    "sg:province":"Baden-W\u00fcrttemberg",
    "wof:name":"S\u00fclchgau-museum",
    "wof:placetype":"venue"
},
  "geometry": {"coordinates":[8.935761,48.475525],"type":"Point"}
}