{
  "type": "Feature",
  "properties": {
    "iso:country":"DE",
    "sg:address":"Schandauer Str. 24",
    "sg:city":"Sebnitz",
    "sg:phone":"+49 35971/56412",
    "sg:postcode":"01855",
    "sg:province":"Sachsen",
    "wof:name":"Gerrit Unger Ingenieur",
    "wof:placetype":"venue"
},
  "geometry": {"coordinates":[14.2703485489,50.9701576233],"type":"Point"}
}