{
  "type": "Feature",
  "properties": {
    "iso:country":"DE",
    "sg:address":"Ried 12",
    "sg:city":"Lindenberg",
    "sg:phone":"+49 8381/5159",
    "sg:postcode":"88161",
    "sg:province":"Bayern",
    "wof:name":"G\u00e4stehaus M. Achberger",
    "wof:placetype":"venue"
},
  "geometry": {"coordinates":[9.8816223145,47.5861587524],"type":"Point"}
}