{
  "type": "Feature",
  "properties": {
    "iso:country":"DE",
    "sg:address":"Osthellen 14",
    "sg:city":"Billerbeck",
    "sg:phone":"+49 2543/1071",
    "sg:postcode":"48727",
    "sg:province":"Nordrhein-Westfalen",
    "wof:name":"Thier Eiervertriebs-gmbh",
    "wof:placetype":"venue"
},
  "geometry": {"coordinates":[7.249968,51.971855],"type":"Point"}
}