{
  "type": "Feature",
  "properties": {
    "iso:country":"DE",
    "sg:address":"Postfach 101145",
    "sg:city":"D\u00fcsseldorf",
    "sg:phone":"+49 211/8760",
    "sg:postcode":"40002",
    "sg:province":"Nordrhein-Westfalen",
    "wof:name":"Pensions- Und Sterbekasse Der Provinzial-lebensversicherung-",
    "wof:placetype":"venue"
},
  "geometry": {"coordinates":[6.7756800652,51.2250595093],"type":"Point"}
}