{
  "type": "Feature",
  "properties": {
    "iso:country":"DE",
    "sg:address":"Taunusstr. 139",
    "sg:city":"Friedrichsdorf",
    "sg:phone":"+49 6172/769930",
    "sg:postcode":"61381",
    "sg:province":"Hessen",
    "wof:name":"U. R. Schneider Industriebedarf Gmbh",
    "wof:placetype":"venue"
},
  "geometry": {"coordinates":[8.631166,50.263969],"type":"Point"}
}