{
  "type": "Feature",
  "properties": {
    "iso:country":"DE",
    "sg:address":"Hanauer Landstr. 50",
    "sg:city":"Kahl",
    "sg:phone":"+49 6188/2413",
    "sg:postcode":"63796",
    "sg:province":"Bayern",
    "wof:name":"Metzgerei Preiss Kahl-main",
    "wof:placetype":"venue"
},
  "geometry": {"coordinates":[9.0041856766,50.0730209351],"type":"Point"}
}