{
  "type": "Feature",
  "properties": {
    "iso:country":"DE",
    "sg:address":"Hauptstr. 78",
    "sg:city":"Bernkastel-Kues",
    "sg:phone":"+49 6531/6828",
    "sg:postcode":"54470",
    "sg:province":"Rheinland-Pfalz",
    "wof:name":"Mathias Dietz",
    "wof:placetype":"venue"
},
  "geometry": {"coordinates":[7.0620732307,49.9360389709],"type":"Point"}
}