{
  "type": "Feature",
  "properties": {
    "iso:country":"DE",
    "sg:address":"Frauenstr.",
    "sg:city":"Emsdetten",
    "sg:phone":"+49 2572/2505",
    "sg:postcode":"48282",
    "sg:province":"Nordrhein-Westfalen",
    "wof:name":"Westkamp",
    "wof:placetype":"venue"
},
  "geometry": {"coordinates":[7.527841,52.173103],"type":"Point"}
}