{
  "type": "Feature",
  "properties": {
    "iso:country":"DE",
    "sg:address":"T\u00f6pfergasse 15",
    "sg:city":"Naumburg",
    "sg:phone":"+49 5625/7426",
    "sg:postcode":"34311",
    "sg:province":"Hessen",
    "wof:name":"Karl Ritte",
    "wof:placetype":"venue"
},
  "geometry": {"coordinates":[9.200072,51.232445],"type":"Point"}
}