{
  "type": "Feature",
  "properties": {
    "iso:country":"DE",
    "sg:address":"Adam-Berg-Str. 115 F",
    "sg:city":"M\u00fcnchen",
    "sg:phone":"+49 89/682011",
    "sg:postcode":"81735",
    "sg:province":"Bayern",
    "wof:name":"Tecomp Ges. F\u00fcr Technische Computersysteme Mbh",
    "wof:placetype":"venue"
},
  "geometry": {"coordinates":[11.6412496567,48.1098098755],"type":"Point"}
}