{
  "type": "Feature",
  "properties": {
    "iso:country":"DE",
    "sg:address":"Unter Buschweg 22",
    "sg:city":"K\u00f6ln",
    "sg:phone":"+49 2236/66822",
    "sg:postcode":"50999",
    "sg:province":"Nordrhein-Westfalen",
    "wof:name":"Becker",
    "wof:placetype":"venue"
},
  "geometry": {"coordinates":[7.001926899,50.8662414551],"type":"Point"}
}