{
  "type": "Feature",
  "properties": {
    "iso:country":"DE",
    "sg:address":"Schubertstr. 5",
    "sg:city":"Rosenheim",
    "sg:phone":"+49 8031/83635",
    "sg:postcode":"83024",
    "sg:province":"Bayern",
    "wof:name":"Herbert Paul Ingenieur",
    "wof:placetype":"venue"
},
  "geometry": {"coordinates":[12.1279220581,47.8700218201],"type":"Point"}
}