{
  "type": "Feature",
  "properties": {
    "iso:country":"DE",
    "sg:address":"Kronenstr. 11",
    "sg:city":"Rheinfelden",
    "sg:phone":"+49 7623/2445",
    "sg:postcode":"79618",
    "sg:province":"Baden-W\u00fcrttemberg",
    "wof:name":"Peter Sitterle Sanit\u00e4r- Und Heizungsbaumeister",
    "wof:placetype":"venue"
},
  "geometry": {"coordinates":[7.789351,47.560692],"type":"Point"}
}