{
  "type": "Feature",
  "properties": {
    "iso:country":"DE",
    "sg:address":"Suhrsweg 14",
    "sg:city":"Hamburg",
    "sg:phone":"+49 40/6913629",
    "sg:postcode":"22305",
    "sg:province":"Hamburg",
    "wof:name":"G. Brors",
    "wof:placetype":"venue"
},
  "geometry": {"coordinates":[10.0465450287,53.5921020508],"type":"Point"}
}