{
  "type": "Feature",
  "properties": {
    "iso:country":"DE",
    "sg:address":"Breslauer Str. 1 A",
    "sg:city":"Burgdorf",
    "sg:phone":"+49 5136/894000",
    "sg:postcode":"31303",
    "sg:province":"Niedersachsen",
    "wof:name":"Alfons Kluger Steurberater",
    "wof:placetype":"venue"
},
  "geometry": {"coordinates":[10.0140218735,52.455116272],"type":"Point"}
}