{
  "type": "Feature",
  "properties": {
    "iso:country":"DE",
    "sg:address":"Kanalstr.-Nord 46a",
    "sg:city":"Kamperfehn",
    "sg:phone":"+49 4497/91066",
    "sg:postcode":"26169",
    "sg:province":"Niedersachsen",
    "wof:name":"Spezialversand F\u00fcr Den Hausbrauer",
    "wof:placetype":"venue"
},
  "geometry": {"coordinates":[7.7988648415,53.0884399414],"type":"Point"}
}