{
  "type": "Feature",
  "properties": {
    "iso:country":"DE",
    "sg:address":"Kurf\u00fcrst-Max-Siedlung 19",
    "sg:city":"Penzberg",
    "sg:phone":"+49 8856/91950",
    "sg:postcode":"82377",
    "sg:province":"Bayern",
    "wof:name":"Dipl.ing. Peter Heinisch Architekt",
    "wof:placetype":"venue"
},
  "geometry": {"coordinates":[11.400855,47.769371],"type":"Point"}
}