{
  "type": "Feature",
  "properties": {
    "iso:country":"DE",
    "sg:address":"Unterw\u00e4sser 18",
    "sg:city":"Rottenburg",
    "sg:phone":"+49 7472/1477",
    "sg:postcode":"72108",
    "sg:province":"Baden-W\u00fcrttemberg",
    "wof:name":"Walter Edelmann",
    "wof:placetype":"venue"
},
  "geometry": {"coordinates":[8.937043,48.475414],"type":"Point"}
}