{
  "type": "Feature",
  "properties": {
    "iso:country":"DE",
    "sg:address":"Rheinsberger Str. 20",
    "sg:city":"F\u00fcrstenberg",
    "sg:phone":"+49 33093/38260",
    "sg:postcode":"16798",
    "sg:province":"Brandenburg",
    "wof:name":"J\u00fcrgen Neumann",
    "wof:placetype":"venue"
},
  "geometry": {"coordinates":[13.1355218887,53.1749763489],"type":"Point"}
}