{
  "type": "Feature",
  "properties": {
    "iso:country":"DE",
    "sg:address":"Finkenkamp 5",
    "sg:city":"Sternberg",
    "sg:phone":"+49 3847/43070",
    "sg:postcode":"19406",
    "sg:province":"Mecklenburg-Vorpommern",
    "wof:name":"Stewo Sternberger Wohnungsbaugesellschaft Mbh",
    "wof:placetype":"venue"
},
  "geometry": {"coordinates":[11.8221979141,53.7137260437],"type":"Point"}
}