{
  "type": "Feature",
  "properties": {
    "iso:country":"DE",
    "sg:address":"Hauptstr. 20",
    "sg:city":"Eschborn",
    "sg:phone":"+49 6196/46048",
    "sg:postcode":"65760",
    "sg:province":"Hessen",
    "wof:name":"\u00d6kunemische Zentralstation",
    "wof:placetype":"venue"
},
  "geometry": {"coordinates":[8.568417,50.143261],"type":"Point"}
}