{
  "type": "Feature",
  "properties": {
    "iso:country":"DE",
    "sg:address":"Uhlandstr. 1",
    "sg:city":"M\u00fcnchen",
    "sg:phone":"+49 89/543350",
    "sg:postcode":"80336",
    "sg:province":"Bayern",
    "wof:name":"Hotel-garni Uhland Gmbh",
    "wof:placetype":"venue"
},
  "geometry": {"coordinates":[11.5554504395,48.1343574524],"type":"Point"}
}