{
  "type": "Feature",
  "properties": {
    "iso:country":"DE",
    "sg:address":"L\u00e4rchenweg 6",
    "sg:city":"Ahnatal",
    "sg:phone":"+49 5609/9044",
    "sg:postcode":"34292",
    "sg:province":"Hessen",
    "wof:name":"Klinikdienst Werner Wicker Ohg",
    "wof:placetype":"venue"
},
  "geometry": {"coordinates":[9.4097175598,51.3748855591],"type":"Point"}
}