{
  "type": "Feature",
  "properties": {
    "iso:country":"DE",
    "sg:address":"Kottbusser Damm 16",
    "sg:city":"Berlin",
    "sg:phone":"+49 30/69505393",
    "sg:postcode":"10967",
    "sg:province":"Berlin",
    "wof:name":"Haase & Zabel Gbr",
    "wof:placetype":"venue"
},
  "geometry": {"coordinates":[13.4221725464,52.492351532],"type":"Point"}
}