{
  "type": "Feature",
  "properties": {
    "iso:country":"DE",
    "sg:address":"Am Giebel 9",
    "sg:city":"Oberstaufen",
    "sg:phone":"+49 8386/8142",
    "sg:postcode":"87534",
    "sg:province":"Bayern",
    "wof:name":"G\u00e4stehaus Maria Brunold",
    "wof:placetype":"venue"
},
  "geometry": {"coordinates":[10.0407676697,47.5222396851],"type":"Point"}
}