{
  "type": "Feature",
  "properties": {
    "iso:country":"DE",
    "sg:address":"Gottsberg 36",
    "sg:city":"Z\u00fclpich",
    "sg:phone":"+49 2252/94090",
    "sg:postcode":"53909",
    "sg:province":"Nordrhein-Westfalen",
    "wof:name":"Wilfried Hein Steuerberatungs Gmbh",
    "wof:placetype":"venue"
},
  "geometry": {"coordinates":[6.6505489349,50.6942939758],"type":"Point"}
}