{
  "type": "Feature",
  "properties": {
    "iso:country":"DE",
    "sg:city":"S\u00fc\u00dfenborn",
    "sg:postcode":"99441",
    "sg:province":"Th\u00fcringen",
    "wof:name":"Allkauf Optik Inh. Matthias Kaulen",
    "wof:placetype":"venue"
},
  "geometry": {"coordinates":[11.391305,50.984871],"type":"Point"}
}