{
  "type": "Feature",
  "properties": {
    "iso:country":"DE",
    "sg:address":"Canisiusstr. 12",
    "sg:city":"Ingolstadt",
    "sg:postcode":"85053",
    "sg:province":"Bayern",
    "wof:name":"W. Fastenmeier",
    "wof:placetype":"venue"
},
  "geometry": {"coordinates":[11.4452886581,48.7390556335],"type":"Point"}
}