{
  "type": "Feature",
  "properties": {
    "iso:country":"DE",
    "sg:address":"Silh\u00f6fer Str. 25",
    "sg:city":"Wetzlar",
    "sg:phone":"+49 6441/47047",
    "sg:postcode":"35578",
    "sg:province":"Hessen",
    "wof:name":"Hifi-studio Petra Schneeberg",
    "wof:placetype":"venue"
},
  "geometry": {"coordinates":[8.5006523132,50.5532417297],"type":"Point"}
}