{
  "type": "Feature",
  "properties": {
    "iso:country":"DE",
    "sg:address":"Zum Wei\u00dfenborn 14",
    "sg:city":"Gudensberg",
    "sg:phone":"+49 5603/2246",
    "sg:postcode":"34281",
    "sg:province":"Hessen",
    "wof:name":"Armin Wackerbarth",
    "wof:placetype":"venue"
},
  "geometry": {"coordinates":[9.320245,51.171326],"type":"Point"}
}