{
  "type": "Feature",
  "properties": {
    "iso:country":"DE",
    "sg:address":"Gro\u00dfe Bahnstr. 32",
    "sg:city":"Hamburg",
    "sg:phone":"+49 40/8500799",
    "sg:postcode":"22525",
    "sg:province":"Hamburg",
    "wof:name":"I. Weist H. Rothweiler",
    "wof:placetype":"venue"
},
  "geometry": {"coordinates":[9.9366130829,53.5739746094],"type":"Point"}
}