{
  "type": "Feature",
  "properties": {
    "iso:country":"DE",
    "sg:address":"R\u00f6ntgenstr. 6",
    "sg:city":"Bonn",
    "sg:phone":"+49 228/331230",
    "sg:postcode":"53177",
    "sg:province":"Nordrhein-Westfalen",
    "wof:name":"R\u00f6ntgen-apotheke",
    "wof:placetype":"venue"
},
  "geometry": {"coordinates":[7.15976,50.677513],"type":"Point"}
}