{
  "type": "Feature",
  "properties": {
    "iso:country":"DE",
    "sg:address":"Wilhelm-Backhaus-Str. 1 a",
    "sg:city":"K\u00f6ln",
    "sg:phone":"+49 221/470512",
    "sg:postcode":"50931",
    "sg:province":"Nordrhein-Westfalen",
    "wof:name":"Seminar F\u00fcr Kath. Theologie Der Univesit\u00e4t K\u00f6ln",
    "wof:placetype":"venue"
},
  "geometry": {"coordinates":[6.92276,50.927841],"type":"Point"}
}