{
  "type": "Feature",
  "properties": {
    "iso:country":"DE",
    "sg:address":"Rosenweg 2",
    "sg:city":"W\u00f6lpinghausen",
    "sg:phone":"+49 5037/721",
    "sg:postcode":"31556",
    "sg:province":"Niedersachsen",
    "wof:name":"Wolfgang Fach",
    "wof:placetype":"venue"
},
  "geometry": {"coordinates":[9.257956,52.411236],"type":"Point"}
}