{
  "type": "Feature",
  "properties": {
    "iso:country":"DE",
    "sg:address":"M\u00fcnsterstr.",
    "sg:city":"\u00dcberlingen",
    "sg:phone":"+49 4975/519330",
    "sg:postcode":"88662",
    "sg:province":"Baden-W\u00fcrttemberg",
    "wof:name":"Sparkasse \u00dcberlingen",
    "wof:placetype":"venue"
},
  "geometry": {"coordinates":[9.15957,47.766998],"type":"Point"}
}