{
  "type": "Feature",
  "properties": {
    "iso:country":"DE",
    "sg:address":"Luxemburger Str. 238",
    "sg:city":"K\u00f6ln",
    "sg:phone":"+49 221/415589",
    "sg:postcode":"50937",
    "sg:province":"Nordrhein-Westfalen",
    "wof:name":"Wittekind-apotheke",
    "wof:placetype":"venue"
},
  "geometry": {"coordinates":[6.92782,50.91647],"type":"Point"}
}