{
  "type": "Feature",
  "properties": {
    "iso:country":"DE",
    "sg:address":"Marktstr. 7",
    "sg:city":"Freyenstein",
    "sg:phone":"+49 33967/60207",
    "sg:postcode":"16918",
    "sg:province":"Brandenburg",
    "wof:name":"H.-j. Knorr",
    "wof:placetype":"venue"
},
  "geometry": {"coordinates":[12.3536777496,53.2868003845],"type":"Point"}
}