{
  "type": "Feature",
  "properties": {
    "iso:country":"DE",
    "sg:address":"An der Eiche 15",
    "sg:city":"J\u00fcchen",
    "sg:phone":"+49 2165/431",
    "sg:postcode":"41363",
    "sg:province":"Nordrhein-Westfalen",
    "wof:name":"Karl E. Steinfarz",
    "wof:placetype":"venue"
},
  "geometry": {"coordinates":[6.50396,51.11438],"type":"Point"}
}