{
  "type": "Feature",
  "properties": {
    "iso:country":"DE",
    "sg:address":"D\u00f6rfleser Anger 25",
    "sg:city":"Kronach",
    "sg:phone":"+49 9261/4590",
    "sg:postcode":"96317",
    "sg:province":"Bayern",
    "wof:name":"Schleicher Gmbh",
    "wof:placetype":"venue"
},
  "geometry": {"coordinates":[11.342912,50.255474],"type":"Point"}
}