{
  "type": "Feature",
  "properties": {
    "iso:country":"DE",
    "sg:address":"Mathias-Br\u00fcggen-Str.76",
    "sg:city":"K\u00f6ln",
    "sg:phone":"+49 221/5347007",
    "sg:postcode":"50827",
    "sg:province":"Nordrhein-Westfalen",
    "wof:name":"Pro-net-koeln",
    "wof:placetype":"venue"
},
  "geometry": {"coordinates":[6.891166,50.975506],"type":"Point"}
}