{
  "type": "Feature",
  "properties": {
    "iso:country":"DE",
    "sg:address":"Kroatengrund 3",
    "sg:city":"Radebeul",
    "sg:postcode":"01445",
    "sg:province":"Sachsen",
    "wof:name":"Domasch Bau Gmbh",
    "wof:placetype":"venue"
},
  "geometry": {"coordinates":[13.6190385818,51.1186065674],"type":"Point"}
}