{
  "type": "Feature",
  "properties": {
    "iso:country":"DE",
    "sg:address":"Dorfstr. 21",
    "sg:city":"Bruchm\u00fchlbach-Miesau",
    "sg:phone":"+49 6372/61310",
    "sg:postcode":"66892",
    "sg:province":"Rheinland-Pfalz",
    "wof:name":"W. Mock",
    "wof:placetype":"venue"
},
  "geometry": {"coordinates":[7.429014,49.379486],"type":"Point"}
}