{
  "type": "Feature",
  "properties": {
    "iso:country":"DE",
    "sg:address":"Kirchstr. 2",
    "sg:city":"Bechhofen",
    "sg:phone":"+49 9822/382",
    "sg:postcode":"91572",
    "sg:province":"Bayern",
    "wof:name":"Fritz Maurer Inh. Horst Maurer",
    "wof:placetype":"venue"
},
  "geometry": {"coordinates":[10.550402,49.158054],"type":"Point"}
}