{
  "type": "Feature",
  "properties": {
    "iso:country":"DE",
    "sg:address":"Spohrstr. 9",
    "sg:city":"Dortmund",
    "sg:phone":"+49 231/258510",
    "sg:postcode":"44145",
    "sg:province":"Nordrhein-Westfalen",
    "wof:name":"A. Hilsmann",
    "wof:placetype":"venue"
},
  "geometry": {"coordinates":[7.4623827934,51.5256118774],"type":"Point"}
}