{
  "type": "Feature",
  "properties": {
    "iso:country":"DE",
    "sg:address":"Grorother Str. 1",
    "sg:city":"Wiesbaden",
    "sg:phone":"+49 611/23241",
    "sg:postcode":"65201",
    "sg:province":"Hessen",
    "wof:name":"I. Witherspoon",
    "wof:placetype":"venue"
},
  "geometry": {"coordinates":[8.1761474609,50.045791626],"type":"Point"}
}