{
  "type": "Feature",
  "properties": {
    "iso:country":"DE",
    "sg:address":"Cranachstr. 1",
    "sg:city":"D\u00fcsseldorf",
    "sg:phone":"+49 211/675716",
    "sg:postcode":"40235",
    "sg:province":"Nordrhein-Westfalen",
    "wof:name":"Wolfgang Felsch",
    "wof:placetype":"venue"
},
  "geometry": {"coordinates":[6.8132619858,51.2319297791],"type":"Point"}
}