{
  "type": "Feature",
  "properties": {
    "iso:country":"DE",
    "sg:address":"Friedrich-Engels-Str. 55",
    "sg:city":"Riesa",
    "sg:phone":"+49 3525/738132",
    "sg:postcode":"01587",
    "sg:province":"Sachsen",
    "wof:name":"Horst Pfeiffer",
    "wof:placetype":"venue"
},
  "geometry": {"coordinates":[13.301243782,51.3036956787],"type":"Point"}
}