{
  "type": "Feature",
  "properties": {
    "iso:country":"DE",
    "sg:address":"Auricher Str. 45",
    "sg:city":"Esens",
    "sg:phone":"+49 4971/3756",
    "sg:postcode":"26427",
    "sg:province":"Niedersachsen",
    "wof:name":"Ubbo Lorenz",
    "wof:placetype":"venue"
},
  "geometry": {"coordinates":[7.61382,53.63131],"type":"Point"}
}