{
  "type": "Feature",
  "properties": {
    "iso:country":"DE",
    "sg:address":"Dr.-Beer-Str. 5",
    "sg:city":"Ichenhausen",
    "sg:phone":"+49 8223/1366",
    "sg:postcode":"89335",
    "sg:province":"Bayern",
    "wof:name":"Fritz Scheppach",
    "wof:placetype":"venue"
},
  "geometry": {"coordinates":[10.3146839142,48.371509552],"type":"Point"}
}