{
  "type": "Feature",
  "properties": {
    "iso:country":"DE",
    "sg:address":"Daimlerring 5",
    "sg:city":"R\u00f6dinghausen",
    "sg:phone":"+49 5223/60801",
    "sg:postcode":"32289",
    "sg:province":"Nordrhein-Westfalen",
    "wof:name":"H. W\u00f6rmann Zigarren Und Zigarillo Gmbh",
    "wof:placetype":"venue"
},
  "geometry": {"coordinates":[8.4973421097,52.2118263245],"type":"Point"}
}