{
  "type": "Feature",
  "properties": {
    "iso:country":"DE",
    "sg:address":"Schillerstr. 11",
    "sg:city":"Weiden",
    "sg:phone":"+49 961/418787",
    "sg:postcode":"92637",
    "sg:province":"Bayern",
    "wof:name":"City-center Weiden Management Gmbh",
    "wof:placetype":"venue"
},
  "geometry": {"coordinates":[12.1568307877,49.6746253967],"type":"Point"}
}