{
  "type": "Feature",
  "properties": {
    "iso:country":"DE",
    "sg:address":"W\u00e4ldleinstr. 3",
    "sg:city":"Randersacker",
    "sg:phone":"+49 9303/628",
    "sg:postcode":"97236",
    "sg:province":"Bayern",
    "wof:name":"Hermann Beyer Komponist",
    "wof:placetype":"venue"
},
  "geometry": {"coordinates":[10.0360031128,49.7333374023],"type":"Point"}
}