{
  "type": "Feature",
  "properties": {
    "iso:country":"DE",
    "sg:address":"Adam-Ileborgh-Str. 15",
    "sg:city":"Stendal",
    "sg:phone":"+49 3931/416664",
    "sg:postcode":"39576",
    "sg:province":"Sachsen-Anhalt",
    "wof:name":"Alois Keppler",
    "wof:placetype":"venue"
},
  "geometry": {"coordinates":[11.8454723358,52.6039848328],"type":"Point"}
}