{
  "type": "Feature",
  "properties": {
    "iso:country":"DE",
    "sg:address":"Kiebitzweg 1",
    "sg:city":"Langlingen",
    "sg:phone":"+49 5082/1452",
    "sg:postcode":"29364",
    "sg:province":"Niedersachsen",
    "wof:name":"Lippischewski Und Partner",
    "wof:placetype":"venue"
},
  "geometry": {"coordinates":[10.2729825974,52.5590019226],"type":"Point"}
}