{
  "type": "Feature",
  "properties": {
    "iso:country":"DE",
    "sg:address":"Wettringer Str. 76",
    "sg:city":"Neuenkirchen",
    "sg:phone":"+49 5973/809",
    "sg:postcode":"48485",
    "sg:province":"Nordrhein-Westfalen",
    "wof:name":"Naturfreibad",
    "wof:placetype":"venue"
},
  "geometry": {"coordinates":[7.3552498817,52.2306175232],"type":"Point"}
}