{
  "type": "Feature",
  "properties": {
    "iso:country":"DE",
    "sg:address":"K\u00f6nigstr. 70",
    "sg:city":"Landau",
    "sg:postcode":"76829",
    "sg:province":"Rheinland-Pfalz",
    "wof:name":"Dipl-kfm. Rolf Nunold Gmbh",
    "wof:placetype":"venue"
},
  "geometry": {"coordinates":[8.1152744293,49.1953048706],"type":"Point"}
}