{
  "type": "Feature",
  "properties": {
    "iso:country":"DE",
    "sg:address":"Friesestr. 31",
    "sg:city":"Kirschau",
    "sg:phone":"+49 3592/350",
    "sg:postcode":"02681",
    "sg:province":"Sachsen",
    "wof:name":"Vegro Textilproduktion Gmbh",
    "wof:placetype":"venue"
},
  "geometry": {"coordinates":[14.4212779999,51.093372345],"type":"Point"}
}