{
  "type": "Feature",
  "properties": {
    "iso:country":"DE",
    "sg:address":"Lachenstr. 4",
    "sg:city":"Albstadt",
    "sg:phone":"+49 7432/4437",
    "sg:postcode":"72461",
    "sg:province":"Baden-W\u00fcrttemberg",
    "wof:name":"Alfred Keck Lebensmittel",
    "wof:placetype":"venue"
},
  "geometry": {"coordinates":[9.0268249512,48.2385902405],"type":"Point"}
}