{
  "type": "Feature",
  "properties": {
    "iso:country":"DE",
    "sg:address":"Siegelsdorfer Str. 40",
    "sg:city":"F\u00fcrth",
    "sg:phone":"+49 911/7520229",
    "sg:postcode":"90768",
    "sg:province":"Bayern",
    "wof:name":"Rolf B\u00f6hmer E. K.",
    "wof:placetype":"venue"
},
  "geometry": {"coordinates":[10.91936,49.494804],"type":"Point"}
}