{
  "type": "Feature",
  "properties": {
    "iso:country":"DE",
    "sg:address":"Am Waldsaum 4a",
    "sg:city":"Detmold",
    "sg:phone":"+49 5231/89947",
    "sg:postcode":"32760",
    "sg:province":"Nordrhein-Westfalen",
    "wof:name":"Patricia Und Roco Anzaldo",
    "wof:placetype":"venue"
},
  "geometry": {"coordinates":[8.8323564529,51.9292640686],"type":"Point"}
}