{
  "type": "Feature",
  "properties": {
    "iso:country":"DE",
    "sg:address":"Rathausmarkt 1",
    "sg:city":"Viersen",
    "sg:postcode":"41747",
    "sg:province":"Nordrhein-Westfalen",
    "wof:name":"Kinder- Und Jugendbibliothek",
    "wof:placetype":"venue"
},
  "geometry": {"coordinates":[6.390365,51.257816],"type":"Point"}
}