{
  "type": "Feature",
  "properties": {
    "iso:country":"DE",
    "sg:address":"Geretsrieder Str. 12",
    "sg:city":"Waldkraiburg",
    "sg:phone":"+49 8638/94360",
    "sg:postcode":"84478",
    "sg:province":"Bayern",
    "wof:name":"Gto Gmbh",
    "wof:placetype":"venue"
},
  "geometry": {"coordinates":[12.410142,48.215183],"type":"Point"}
}