{
  "type": "Feature",
  "properties": {
    "iso:country":"DE",
    "sg:address":"Blumenauer Str. 11",
    "sg:city":"Wunstorf",
    "sg:phone":"+49 5031/972410",
    "sg:postcode":"31515",
    "sg:province":"Niedersachsen",
    "wof:name":"Ivr- Gmbh",
    "wof:placetype":"venue"
},
  "geometry": {"coordinates":[9.4489784241,52.4250564575],"type":"Point"}
}