{
  "type": "Feature",
  "properties": {
    "iso:country":"DE",
    "sg:address":"Prof.-Haack-Str. 10",
    "sg:city":"Osnabr\u00fcck",
    "sg:phone":"+49 541/3340324",
    "sg:postcode":"49076",
    "sg:province":"Niedersachsen",
    "wof:name":"Dr. Klaus Neumann Rechtsanwalt",
    "wof:placetype":"venue"
},
  "geometry": {"coordinates":[8.0330076218,52.2820739746],"type":"Point"}
}