{
  "type": "Feature",
  "properties": {
    "iso:country":"DE",
    "sg:address":"Auf dem Aspei 60",
    "sg:city":"Bochum",
    "sg:phone":"+49 234/9789791",
    "sg:postcode":"44801",
    "sg:province":"Nordrhein-Westfalen",
    "wof:name":"Europ\u00e4isches Parlament",
    "wof:placetype":"venue"
},
  "geometry": {"coordinates":[7.2662940025,51.4531364441],"type":"Point"}
}