{
  "type": "Feature",
  "properties": {
    "iso:country":"DE",
    "sg:address":"Kretscham 4 A",
    "sg:city":"Sehmatal-Neudorf",
    "sg:phone":"+49 37342/8334",
    "sg:postcode":"09465",
    "sg:province":"Sachsen",
    "wof:name":"Gerd Baumann Gmbh",
    "wof:placetype":"venue"
},
  "geometry": {"coordinates":[12.986781,50.467159],"type":"Point"}
}