{
  "type": "Feature",
  "properties": {
    "iso:country":"DE",
    "sg:address":"An der Wolfskuhle 28",
    "sg:city":"Bielefeld",
    "sg:phone":"+49 521",
    "sg:postcode":"33619",
    "sg:province":"Nordrhein-Westfalen",
    "wof:name":"Dalibor Communications - Content Ist Our Business",
    "wof:placetype":"venue"
},
  "geometry": {"coordinates":[8.488313,52.02177],"type":"Point"}
}