{
  "type": "Feature",
  "properties": {
    "iso:country":"DE",
    "sg:address":"Jahnstr. 2",
    "sg:city":"Stockstadt",
    "sg:phone":"+49 6027/3468",
    "sg:postcode":"63811",
    "sg:province":"Bayern",
    "wof:name":"Peter Kemmerer",
    "wof:placetype":"venue"
},
  "geometry": {"coordinates":[9.0609302521,49.9777412415],"type":"Point"}
}