{
  "type": "Feature",
  "properties": {
    "iso:country":"DE",
    "sg:address":"Inselstr. 29",
    "sg:city":"Wittd\u00fcn",
    "sg:postcode":"25946",
    "sg:province":"Schleswig-Holstein",
    "wof:name":"J\u00fcrgen Krahmer Drogerie",
    "wof:placetype":"venue"
},
  "geometry": {"coordinates":[8.393924,54.626495],"type":"Point"}
}