{
  "type": "Feature",
  "properties": {
    "iso:country":"DE",
    "sg:address":"Kirchweg 22",
    "sg:city":"N\u00fcrburg",
    "sg:postcode":"53520",
    "sg:province":"Rheinland-Pfalz",
    "wof:name":"Consulting & More Am N\u00fcrburgring",
    "wof:placetype":"venue"
},
  "geometry": {"coordinates":[6.9537210464,50.3420066833],"type":"Point"}
}