{
  "type": "Feature",
  "properties": {
    "iso:country":"DE",
    "sg:address":"Sandgasse 24",
    "sg:city":"Aschaffenburg",
    "sg:phone":"+49 6021/15990",
    "sg:postcode":"63739",
    "sg:province":"Bayern",
    "wof:name":"O. Bauer Ingenieur",
    "wof:placetype":"venue"
},
  "geometry": {"coordinates":[9.1482362747,49.9743843079],"type":"Point"}
}