{
  "type": "Feature",
  "properties": {
    "iso:country":"DE",
    "sg:address":"Am Pa\u00df 10",
    "sg:city":"Dortmund",
    "sg:postcode":"44227",
    "sg:province":"Nordrhein-Westfalen",
    "wof:name":"Tobo-dent Zahntechnik Gmbh",
    "wof:placetype":"venue"
},
  "geometry": {"coordinates":[7.4206309319,51.4871482849],"type":"Point"}
}