{
  "type": "Feature",
  "properties": {
    "iso:country":"DE",
    "sg:address":"Ziegelstr. 30",
    "sg:city":"Essingen",
    "sg:phone":"+49 7365/5131",
    "sg:postcode":"73457",
    "sg:province":"Baden-W\u00fcrttemberg",
    "wof:name":"Vereinsgastst\u00e4tte Tsv Essingen 1893 E. V.",
    "wof:placetype":"venue"
},
  "geometry": {"coordinates":[10.0397167206,48.8139915466],"type":"Point"}
}