{
  "type": "Feature",
  "properties": {
    "iso:country":"DE",
    "sg:address":"Brenscheder Str. 64",
    "sg:city":"Bochum",
    "sg:phone":"+49 234/9731080",
    "sg:postcode":"44799",
    "sg:province":"Nordrhein-Westfalen",
    "wof:name":"Sterner",
    "wof:placetype":"venue"
},
  "geometry": {"coordinates":[7.2305388451,51.450843811],"type":"Point"}
}