{
  "type": "Feature",
  "properties": {
    "iso:country":"DE",
    "sg:address":"Seestr. 1",
    "sg:city":"Gro\u00dfensee",
    "sg:postcode":"22946",
    "sg:province":"Schleswig-Holstein",
    "wof:name":"J\u00fctting Restaurant- Betriebe Gmbh",
    "wof:placetype":"venue"
},
  "geometry": {"coordinates":[10.3555202484,53.622631073],"type":"Point"}
}