{
  "type": "Feature",
  "properties": {
    "iso:country":"DE",
    "sg:address":"Am Sportplatz 7",
    "sg:city":"Limburg",
    "sg:phone":"+49 6433/2942",
    "sg:postcode":"65554",
    "sg:province":"Hessen",
    "wof:name":"Como M\u00f6belzentrum Gmbh & Co. Kg",
    "wof:placetype":"venue"
},
  "geometry": {"coordinates":[8.092611,50.437435],"type":"Point"}
}