{
  "type": "Feature",
  "properties": {
    "iso:country":"DE",
    "sg:address":"Brunnenstr. 7",
    "sg:city":"Karben",
    "sg:phone":"+49 6039/3304",
    "sg:postcode":"61184",
    "sg:province":"Hessen",
    "wof:name":"Restaurant Raquette-bistro",
    "wof:placetype":"venue"
},
  "geometry": {"coordinates":[8.7568693161,50.2376403809],"type":"Point"}
}