{
  "type": "Feature",
  "properties": {
    "iso:country":"DE",
    "sg:address":"Segelckestr. 31",
    "sg:city":"Cuxhaven",
    "sg:phone":"+49 4721/52795",
    "sg:postcode":"27472",
    "sg:province":"Niedersachsen",
    "wof:name":"Textilhaus Kammann Kg Haus- Und K\u00fcchenger. Glas- U.",
    "wof:placetype":"venue"
},
  "geometry": {"coordinates":[8.700255,53.859821],"type":"Point"}
}