{
  "type": "Feature",
  "properties": {
    "iso:country":"DE",
    "sg:address":"Sch\u00f6nblick 24",
    "sg:city":"Albstadt",
    "sg:phone":"+49 7432/22775",
    "sg:postcode":"72461",
    "sg:province":"Baden-W\u00fcrttemberg",
    "wof:name":"Gerhard Maier",
    "wof:placetype":"venue"
},
  "geometry": {"coordinates":[8.9949455261,48.2896308899],"type":"Point"}
}