{
  "type": "Feature",
  "properties": {
    "iso:country":"DE",
    "sg:address":"Helenenstr. 32",
    "sg:city":"Markgr\u00f6ningen",
    "sg:phone":"+49 7145/6604",
    "sg:postcode":"71706",
    "sg:province":"Baden-W\u00fcrttemberg",
    "wof:name":"Sonnenschein",
    "wof:placetype":"venue"
},
  "geometry": {"coordinates":[9.082856,48.905708],"type":"Point"}
}