{
  "type": "Feature",
  "properties": {
    "iso:country":"DE",
    "sg:address":"Steinmetzenweg 3",
    "sg:city":"Bremen",
    "sg:phone":"+49 421/451838",
    "sg:postcode":"28309",
    "sg:province":"Bremen",
    "wof:name":"Hermann Sachmerda",
    "wof:placetype":"venue"
},
  "geometry": {"coordinates":[8.9157543182,53.0613899231],"type":"Point"}
}