{
  "type": "Feature",
  "properties": {
    "iso:country":"DE",
    "sg:address":"Rittergasse 3",
    "sg:city":"Ebern",
    "sg:phone":"+49 9531/6995",
    "sg:postcode":"96106",
    "sg:province":"Bayern",
    "wof:name":"St\u00e4dtisches Freibad",
    "wof:placetype":"venue"
},
  "geometry": {"coordinates":[10.7955932617,50.0940933228],"type":"Point"}
}