{
  "type": "Feature",
  "properties": {
    "iso:country":"DE",
    "sg:address":"Holtenklinker Str. 108 a",
    "sg:city":"Hamburg",
    "sg:phone":"+49 40/7215531",
    "sg:postcode":"21029",
    "sg:province":"Hamburg",
    "wof:name":"Werner Westphal",
    "wof:placetype":"venue"
},
  "geometry": {"coordinates":[10.2245368958,53.4817581177],"type":"Point"}
}