{
  "type": "Feature",
  "properties": {
    "iso:country":"DE",
    "sg:address":"Wigandstr. 17",
    "sg:city":"Kassel",
    "sg:phone":"+49 561/34744",
    "sg:postcode":"34131",
    "sg:province":"Hessen",
    "wof:name":"Brigitte Und Klaus Fauerbach Architekten",
    "wof:placetype":"venue"
},
  "geometry": {"coordinates":[9.426173,51.31123],"type":"Point"}
}