{
  "type": "Feature",
  "properties": {
    "iso:country":"DE",
    "sg:address":"Heinrich-Hertz-Str. 3",
    "sg:city":"Bottrop",
    "sg:phone":"+49 2045/96220",
    "sg:postcode":"46244",
    "sg:province":"Nordrhein-Westfalen",
    "wof:name":"Aquadraulic Wassertechnik Gmbh",
    "wof:placetype":"venue"
},
  "geometry": {"coordinates":[6.928861,51.613388],"type":"Point"}
}