{
  "type": "Feature",
  "properties": {
    "iso:country":"DE",
    "sg:address":"Waldmannshofen",
    "sg:city":"Creglingen",
    "sg:postcode":"97993",
    "sg:province":"Baden-W\u00fcrttemberg",
    "wof:name":"W. Scherer",
    "wof:placetype":"venue"
},
  "geometry": {"coordinates":[10.06772995,49.5332946777],"type":"Point"}
}