{
  "type": "Feature",
  "properties": {
    "iso:country":"DE",
    "sg:address":"Hinter der Eller 2",
    "sg:city":"Friedberg",
    "sg:phone":"+49 6031/15402",
    "sg:postcode":"61169",
    "sg:province":"Hessen",
    "wof:name":"Baudekoration G\u00fcbler Gmbh",
    "wof:placetype":"venue"
},
  "geometry": {"coordinates":[8.806579,50.338242],"type":"Point"}
}