{
  "type": "Feature",
  "properties": {
    "iso:country":"DE",
    "sg:address":"Vorstadt 2",
    "sg:city":"Oberursel",
    "sg:phone":"+49 6171/580605",
    "sg:postcode":"61440",
    "sg:province":"Hessen",
    "wof:name":"Gecko-cafe",
    "wof:placetype":"venue"
},
  "geometry": {"coordinates":[8.582418,50.20076],"type":"Point"}
}