{
  "type": "Feature",
  "properties": {
    "iso:country":"DE",
    "sg:address":"Bachg\u00e4\u00dfle 3",
    "sg:city":"Ebersbach",
    "sg:phone":"+49 7163/7427",
    "sg:postcode":"73061",
    "sg:province":"Baden-W\u00fcrttemberg",
    "wof:name":"Ernst Stahl",
    "wof:placetype":"venue"
},
  "geometry": {"coordinates":[9.52214,48.715839],"type":"Point"}
}