{
  "type": "Feature",
  "properties": {
    "iso:country":"DE",
    "sg:address":"Fliederweg 5",
    "sg:city":"Lingen",
    "sg:phone":"+49 591/74161",
    "sg:postcode":"49811",
    "sg:province":"Niedersachsen",
    "wof:name":"C. Jansen Steuerberater",
    "wof:placetype":"venue"
},
  "geometry": {"coordinates":[7.3542060852,52.5419960022],"type":"Point"}
}