{
  "type": "Feature",
  "properties": {
    "iso:country":"DE",
    "sg:address":"Voosener Str. 61",
    "sg:city":"M\u00f6nchengladbach",
    "sg:phone":"+49 2161/581370",
    "sg:postcode":"41179",
    "sg:province":"Nordrhein-Westfalen",
    "wof:name":"Karsch",
    "wof:placetype":"venue"
},
  "geometry": {"coordinates":[6.385666,51.144596],"type":"Point"}
}