{
  "type": "Feature",
  "properties": {
    "iso:country":"DE",
    "sg:address":"Schulweg 4",
    "sg:city":"Lam",
    "sg:phone":"+49 9943/796",
    "sg:postcode":"93462",
    "sg:province":"Bayern",
    "wof:name":"Gemeindeb\u00fccherei Im Rathaus",
    "wof:placetype":"venue"
},
  "geometry": {"coordinates":[13.051197,49.196682],"type":"Point"}
}