{
  "type": "Feature",
  "properties": {
    "iso:country":"DE",
    "sg:address":"Gewerbestr. 17",
    "sg:city":"Bochum",
    "sg:phone":"+49 2327/69040",
    "sg:postcode":"44866",
    "sg:province":"Nordrhein-Westfalen",
    "wof:name":"Opto-control Quality Management Ag",
    "wof:placetype":"venue"
},
  "geometry": {"coordinates":[7.159717083,51.4890480042],"type":"Point"}
}