{
  "type": "Feature",
  "properties": {
    "iso:country":"DE",
    "sg:address":"Rathausstr. 14",
    "sg:city":"Chemnitz",
    "sg:phone":"+49 371/6446458",
    "sg:postcode":"09111",
    "sg:province":"Sachsen",
    "wof:name":"Dr. Th\u00fcmmel Und Kollegen Rechtsanw\u00e4lte",
    "wof:placetype":"venue"
},
  "geometry": {"coordinates":[12.9220018387,50.8313064575],"type":"Point"}
}