{
  "type": "Feature",
  "properties": {
    "iso:country":"DE",
    "sg:address":"Innviertler Str. 14",
    "sg:city":"Kirchdorf",
    "sg:postcode":"84375",
    "sg:province":"Bayern",
    "wof:name":"Gerhard Kellner E. Kfm.",
    "wof:placetype":"venue"
},
  "geometry": {"coordinates":[12.9815349579,48.2572746277],"type":"Point"}
}