{
  "type": "Feature",
  "properties": {
    "iso:country":"DE",
    "sg:address":"Hofmannstr. 46",
    "sg:city":"Dresden",
    "sg:phone":"+49 351/317230",
    "sg:postcode":"01277",
    "sg:province":"Sachsen",
    "wof:name":"Begleitetes Wohnen Soziale Dienste Gmbh",
    "wof:placetype":"venue"
},
  "geometry": {"coordinates":[13.813798,51.043648],"type":"Point"}
}