{
  "type": "Feature",
  "properties": {
    "iso:country":"DE",
    "sg:address":"Weinbergstr. 32",
    "sg:city":"Wei\u00dfenfels",
    "sg:phone":"+49 3443/300942",
    "sg:postcode":"06667",
    "sg:province":"Sachsen-Anhalt",
    "wof:name":"Pro B\u00fcro Einrichtungs- Und B\u00fcrobedarf Handels Gmbh",
    "wof:placetype":"venue"
},
  "geometry": {"coordinates":[11.97013,51.205608],"type":"Point"}
}