{
  "type": "Feature",
  "properties": {
    "iso:country":"DE",
    "sg:address":"Hochstr. 15",
    "sg:city":"Nettetal",
    "sg:phone":"+49 2153/4664",
    "sg:postcode":"41334",
    "sg:province":"Nordrhein-Westfalen",
    "wof:name":"M. -l. Orbon",
    "wof:placetype":"venue"
},
  "geometry": {"coordinates":[6.275678,51.305672],"type":"Point"}
}