{
  "type": "Feature",
  "properties": {
    "iso:country":"DE",
    "sg:address":"Pointstr.15",
    "sg:city":"Karlstadt",
    "sg:phone":"+49 9360/990611",
    "sg:postcode":"97753",
    "sg:province":"Bayern",
    "wof:name":"Www.eroticwg.de - Die Sex Wg - Big Brother Live",
    "wof:placetype":"venue"
},
  "geometry": {"coordinates":[9.834741,49.943398],"type":"Point"}
}