{
  "type": "Feature",
  "properties": {
    "iso:country":"DE",
    "sg:address":"Am M\u00fchlenberg",
    "sg:city":"Otterndorf",
    "sg:phone":"+49 4751/6592",
    "sg:postcode":"21762",
    "sg:province":"Niedersachsen",
    "wof:name":"T. W\u00fcrtz",
    "wof:placetype":"venue"
},
  "geometry": {"coordinates":[8.903404,53.804909],"type":"Point"}
}