{
  "type": "Feature",
  "properties": {
    "iso:country":"DE",
    "sg:address":"Gustavstr. 2",
    "sg:city":"Wuppertal",
    "sg:phone":"+49 202/734935",
    "sg:postcode":"42329",
    "sg:province":"Nordrhein-Westfalen",
    "wof:name":"Natascha Ksoll Modewaren",
    "wof:placetype":"venue"
},
  "geometry": {"coordinates":[7.070122,51.230591],"type":"Point"}
}