{
  "type": "Feature",
  "properties": {
    "iso:country":"DE",
    "sg:address":"Wunnensteinstr. 47",
    "sg:city":"Ilsfeld",
    "sg:phone":"+49 7062/3324",
    "sg:postcode":"74360",
    "sg:province":"Baden-W\u00fcrttemberg",
    "wof:name":"Gerhard Kl\u00e4sser",
    "wof:placetype":"venue"
},
  "geometry": {"coordinates":[9.272827,49.042],"type":"Point"}
}