{
  "type": "Feature",
  "properties": {
    "iso:country":"DE",
    "sg:address":"Marterlweg 18",
    "sg:city":"Berching",
    "sg:phone":"+49 8462/905101",
    "sg:postcode":"92334",
    "sg:province":"Bayern",
    "wof:name":"Gotthard Seitz Architekt",
    "wof:placetype":"venue"
},
  "geometry": {"coordinates":[11.457174,49.14418],"type":"Point"}
}