{
  "type": "Feature",
  "properties": {
    "iso:country":"DE",
    "sg:address":"Freihofstr. 17",
    "sg:city":"G\u00f6ppingen",
    "sg:phone":"+49 4971/6168095",
    "sg:postcode":"73033",
    "sg:province":"Baden-W\u00fcrttemberg",
    "wof:name":"Hypo-bank Ag",
    "wof:placetype":"venue"
},
  "geometry": {"coordinates":[9.651786,48.702248],"type":"Point"}
}