{
  "type": "Feature",
  "properties": {
    "iso:country":"DE",
    "sg:address":"Kasseler Str. 26",
    "sg:city":"Paderborn",
    "sg:phone":"+49 5251/23166",
    "sg:postcode":"33098",
    "sg:province":"Nordrhein-Westfalen",
    "wof:name":"Tuba",
    "wof:placetype":"venue"
},
  "geometry": {"coordinates":[8.7584171295,51.7176933289],"type":"Point"}
}