{
  "type": "Feature",
  "properties": {
    "iso:country":"DE",
    "sg:address":"Alte Schlettauer Str. 32",
    "sg:city":"Annaberg-Buchholz",
    "sg:phone":"+49 3733/20088",
    "sg:postcode":"09456",
    "sg:province":"Sachsen",
    "wof:name":"Bba Bau- Und Bautr\u00e4gerges. Mbh",
    "wof:placetype":"venue"
},
  "geometry": {"coordinates":[12.9849758148,50.5754585266],"type":"Point"}
}