{
  "type": "Feature",
  "properties": {
    "iso:country":"DE",
    "sg:address":"Gilde 3 a",
    "sg:city":"M\u00fcden",
    "sg:phone":"+49 5375/98170",
    "sg:postcode":"38539",
    "sg:province":"Niedersachsen",
    "wof:name":"Plettke Gesellschaft F\u00fcr Telekommunikation Mbh",
    "wof:placetype":"venue"
},
  "geometry": {"coordinates":[10.4355192184,52.4986076355],"type":"Point"}
}