{
  "type": "Feature",
  "properties": {
    "iso:country":"DE",
    "sg:address":"Sandweg 30",
    "sg:city":"Bad Oeynhausen",
    "sg:phone":"+49 5731/4756",
    "sg:postcode":"32549",
    "sg:province":"Nordrhein-Westfalen",
    "wof:name":"Eichen-carl Vertriebsgesell- Schaft F\u00fcr Massive Eichen-",
    "wof:placetype":"venue"
},
  "geometry": {"coordinates":[8.7727966309,52.2157363892],"type":"Point"}
}