{
  "type": "Feature",
  "properties": {
    "iso:country":"DE",
    "sg:address":"Am Gladeberg 21",
    "sg:city":"Hardegsen",
    "sg:phone":"+49 5505/745",
    "sg:postcode":"37181",
    "sg:province":"Niedersachsen",
    "wof:name":"Nixdorf-fliesen",
    "wof:placetype":"venue"
},
  "geometry": {"coordinates":[9.8313846588,51.6489944458],"type":"Point"}
}