{
  "type": "Feature",
  "properties": {
    "iso:country":"DE",
    "sg:address":"Krayer Str. 239",
    "sg:city":"Essen",
    "sg:phone":"+49 201/552226",
    "sg:postcode":"45307",
    "sg:province":"Nordrhein-Westfalen",
    "wof:name":"Aquadreams Wasserbetten Vertriebs- Und Service Gmbh",
    "wof:placetype":"venue"
},
  "geometry": {"coordinates":[7.0804347992,51.467590332],"type":"Point"}
}