{
  "type": "Feature",
  "properties": {
    "iso:country":"DE",
    "sg:address":"Wilhelmstr. 32",
    "sg:city":"Heilbronn",
    "sg:phone":"+49 7131/68137",
    "sg:postcode":"74072",
    "sg:province":"Baden-W\u00fcrttemberg",
    "wof:name":"Friedrich Zimmermann",
    "wof:placetype":"venue"
},
  "geometry": {"coordinates":[9.2186641693,49.1350326538],"type":"Point"}
}