{
  "type": "Feature",
  "properties": {
    "iso:country":"DE",
    "sg:address":"Klingenthaler Str. 1a",
    "sg:city":"Taunusstein",
    "sg:phone":"+49 6128/84011",
    "sg:postcode":"65232",
    "sg:province":"Hessen",
    "wof:name":"Merlin Software Service Gmbh",
    "wof:placetype":"venue"
},
  "geometry": {"coordinates":[8.2001819611,50.1523666382],"type":"Point"}
}