{
  "type": "Feature",
  "properties": {
    "iso:country":"DE",
    "sg:address":"Horster Str. 407",
    "sg:city":"Gladbeck",
    "sg:phone":"+49 2043/31352",
    "sg:postcode":"45968",
    "sg:province":"Nordrhein-Westfalen",
    "wof:name":"Haus Kamphowe",
    "wof:placetype":"venue"
},
  "geometry": {"coordinates":[7.0177807808,51.543838501],"type":"Point"}
}