{
  "type": "Feature",
  "properties": {
    "iso:country":"DE",
    "sg:address":"Raublinger Str. 15",
    "sg:city":"M\u00fcnchen",
    "sg:phone":"+49 89/5705305",
    "sg:postcode":"80686",
    "sg:province":"Bayern",
    "wof:name":"S\u00fcdland Bautr\u00e4ger- Und Grundst\u00fccksgesellschaft Mbh",
    "wof:placetype":"venue"
},
  "geometry": {"coordinates":[11.51138,48.12851],"type":"Point"}
}