{
  "type": "Feature",
  "properties": {
    "iso:country":"DE",
    "sg:address":"An der Bahn 5",
    "sg:city":"Flintbek",
    "sg:phone":"+49 4347/3341",
    "sg:postcode":"24220",
    "sg:province":"Schleswig-Holstein",
    "wof:name":"Albert Blumenau",
    "wof:placetype":"venue"
},
  "geometry": {"coordinates":[10.044427,54.230938],"type":"Point"}
}