{
  "type": "Feature",
  "properties": {
    "iso:country":"DE",
    "sg:address":"An der Elisabethkirche 29",
    "sg:city":"Krefeld",
    "sg:postcode":"47799",
    "sg:province":"Nordrhein-Westfalen",
    "wof:name":"Provitec Professionelle Videotechnik Gmbh",
    "wof:placetype":"venue"
},
  "geometry": {"coordinates":[6.5780701637,51.3353309631],"type":"Point"}
}