{
  "type": "Feature",
  "properties": {
    "iso:country":"DE",
    "sg:address":"Watzmannstr. 65",
    "sg:city":"Landshut",
    "sg:postcode":"84034",
    "sg:province":"Bayern",
    "wof:name":"Omnico Logistik Verwaltungs Gmbh",
    "wof:placetype":"venue"
},
  "geometry": {"coordinates":[12.1218271255,48.534160614],"type":"Point"}
}