{
  "type": "Feature",
  "properties": {
    "iso:country":"DE",
    "sg:address":"Stadtplatz 10",
    "sg:city":"Neustadt",
    "sg:phone":"+49 9445/1512",
    "sg:postcode":"93333",
    "sg:province":"Bayern",
    "wof:name":"Beates Laden",
    "wof:placetype":"venue"
},
  "geometry": {"coordinates":[11.765545,48.808903],"type":"Point"}
}