{
  "type": "Feature",
  "properties": {
    "iso:country":"DE",
    "sg:address":"Kurze Geismarstr. 22",
    "sg:city":"G\u00f6ttingen",
    "sg:phone":"+49 551/484065",
    "sg:postcode":"37073",
    "sg:province":"Niedersachsen",
    "wof:name":"Prof. Dr. J. Fischer Christa Friedrich",
    "wof:placetype":"venue"
},
  "geometry": {"coordinates":[9.9383926392,51.5309028625],"type":"Point"}
}