{
  "type": "Feature",
  "properties": {
    "iso:country":"DE",
    "sg:address":"Alter L\u00fcneburger Stadtweg 1",
    "sg:city":"Bienenb\u00fcttel",
    "sg:phone":"+49 5823/6247",
    "sg:postcode":"29553",
    "sg:province":"Niedersachsen",
    "wof:name":"Dirk Vo\u00df",
    "wof:placetype":"venue"
},
  "geometry": {"coordinates":[10.432819,53.1371],"type":"Point"}
}