{
  "type": "Feature",
  "properties": {
    "iso:country":"DE",
    "sg:address":"Hauptstr. 13",
    "sg:city":"M\u00fcden",
    "sg:phone":"+49 5375/6040",
    "sg:postcode":"38539",
    "sg:province":"Niedersachsen",
    "wof:name":"Hans Fiest Masseur",
    "wof:placetype":"venue"
},
  "geometry": {"coordinates":[10.357491,52.526623],"type":"Point"}
}