{
  "type": "Feature",
  "properties": {
    "iso:country":"DE",
    "sg:address":"Fontanestr. 9b",
    "sg:city":"Neuglobsow",
    "sg:phone":"+49 33082/70226",
    "sg:postcode":"16775",
    "sg:province":"Brandenburg",
    "wof:name":"Dr. F. Kramer Zahnarzt",
    "wof:placetype":"venue"
},
  "geometry": {"coordinates":[13.04839,53.145103],"type":"Point"}
}