{
  "type": "Feature",
  "properties": {
    "iso:country":"DE",
    "sg:address":"Am Rotenberg 10",
    "sg:city":"Gro\u00dfenl\u00fcder",
    "sg:phone":"+49 6650/919650",
    "sg:postcode":"36137",
    "sg:province":"Hessen",
    "wof:name":"Verlagsbuchbinderei Keller Gmbh",
    "wof:placetype":"venue"
},
  "geometry": {"coordinates":[9.518825,50.546364],"type":"Point"}
}