{
  "type": "Feature",
  "properties": {
    "iso:country":"DE",
    "sg:address":"M\u00fchlbergweg 10",
    "sg:city":"Bad Rappenau",
    "sg:phone":"+49 7268/243",
    "sg:postcode":"74906",
    "sg:province":"Baden-W\u00fcrttemberg",
    "wof:name":"Gerhard Guth\u00f6rle",
    "wof:placetype":"venue"
},
  "geometry": {"coordinates":[9.033112,49.259521],"type":"Point"}
}