{
  "type": "Feature",
  "properties": {
    "iso:country":"DE",
    "sg:address":"Zillestr. 105",
    "sg:city":"Berlin",
    "sg:phone":"+49 30/3419715",
    "sg:postcode":"10585",
    "sg:province":"Berlin",
    "wof:name":"Klaus Rachner",
    "wof:placetype":"venue"
},
  "geometry": {"coordinates":[13.2993078232,52.5134277344],"type":"Point"}
}