{
  "type": "Feature",
  "properties": {
    "iso:country":"DE",
    "sg:address":"Bl\u00fccherstr. 2",
    "sg:city":"Pforzheim",
    "sg:phone":"+49 7231/52154",
    "sg:postcode":"75177",
    "sg:province":"Baden-W\u00fcrttemberg",
    "wof:name":"Willi Maisch Gmbh",
    "wof:placetype":"venue"
},
  "geometry": {"coordinates":[8.7098970413,48.8972015381],"type":"Point"}
}