{
  "type": "Feature",
  "properties": {
    "iso:country":"DE",
    "sg:address":"Mauggen 5",
    "sg:city":"Bockhorn",
    "sg:postcode":"85461",
    "sg:province":"Bayern",
    "wof:name":"Futura Wohnbau Gmbh",
    "wof:placetype":"venue"
},
  "geometry": {"coordinates":[11.982843,48.300835],"type":"Point"}
}