{
  "type": "Feature",
  "properties": {
    "iso:country":"DE",
    "sg:address":"Christian-Seltmann-Str. 43",
    "sg:city":"Weiden",
    "sg:phone":"+49 961/22280",
    "sg:postcode":"92637",
    "sg:province":"Bayern",
    "wof:name":"Druck Leonhardt Gmbh",
    "wof:placetype":"venue"
},
  "geometry": {"coordinates":[12.150522,49.68029],"type":"Point"}
}