{
  "type": "Feature",
  "properties": {
    "iso:country":"DE",
    "sg:address":"An der Wuhlheide 144",
    "sg:city":"Berlin",
    "sg:phone":"+49 30/5370413",
    "sg:postcode":"12459",
    "sg:province":"Berlin",
    "wof:name":"Reinhold Z\u00e4nger Ingenieur",
    "wof:placetype":"venue"
},
  "geometry": {"coordinates":[13.5356340408,52.4601821899],"type":"Point"}
}