{
  "type": "Feature",
  "properties": {
    "iso:country":"DE",
    "sg:address":"Martensallee 10",
    "sg:city":"Hamburg",
    "sg:phone":"+49 40/6682816",
    "sg:postcode":"22045",
    "sg:province":"Hamburg",
    "wof:name":"Make Martens Immobilien Kg",
    "wof:placetype":"venue"
},
  "geometry": {"coordinates":[10.1350746155,53.5896949768],"type":"Point"}
}