{
  "type": "Feature",
  "properties": {
    "iso:country":"DE",
    "sg:address":"Schmeientalstr. 1",
    "sg:city":"Sigmaringen",
    "sg:phone":"+49 7573/2531",
    "sg:postcode":"72488",
    "sg:province":"Baden-W\u00fcrttemberg",
    "wof:name":"Elfriede Hotz",
    "wof:placetype":"venue"
},
  "geometry": {"coordinates":[9.14133,48.109322],"type":"Point"}
}