{
  "type": "Feature",
  "properties": {
    "iso:country":"DE",
    "sg:address":"Husarenstr. 9",
    "sg:city":"Memmingen",
    "sg:phone":"+49 8331/3830",
    "sg:postcode":"87700",
    "sg:province":"Bayern",
    "wof:name":"Rehklau Gmbh",
    "wof:placetype":"venue"
},
  "geometry": {"coordinates":[10.1568584442,48.0163612366],"type":"Point"}
}