{
  "type": "Feature",
  "properties": {
    "iso:country":"DE",
    "sg:address":"Heetwissenweg 23",
    "sg:city":"Raesfeld",
    "sg:phone":"+49 2865/7721",
    "sg:postcode":"46348",
    "sg:province":"Nordrhein-Westfalen",
    "wof:name":"Johannes Wilger",
    "wof:placetype":"venue"
},
  "geometry": {"coordinates":[6.857374,51.784782],"type":"Point"}
}