{
  "type": "Feature",
  "properties": {
    "iso:country":"DE",
    "sg:address":"Dieselstr. 7",
    "sg:city":"Dornstadt",
    "sg:postcode":"89160",
    "sg:province":"Baden-W\u00fcrttemberg",
    "wof:name":"Bluthep Gesellschaft F. Handel U. Dienstleistung M. Beratungs",
    "wof:placetype":"venue"
},
  "geometry": {"coordinates":[9.951404,48.459412],"type":"Point"}
}