{
  "type": "Feature",
  "properties": {
    "iso:country":"DE",
    "sg:address":"Bahnhofstr. 35a",
    "sg:city":"Buxtehude",
    "sg:phone":"+49 4161/50670",
    "sg:postcode":"21614",
    "sg:province":"Niedersachsen",
    "wof:name":"Hartmut Runtemund Und C.-ch. Sedding",
    "wof:placetype":"venue"
},
  "geometry": {"coordinates":[9.6923589706,53.4721603394],"type":"Point"}
}