{
  "type": "Feature",
  "properties": {
    "iso:country":"DE",
    "sg:address":"Weiherbrunnenstr. 11",
    "sg:city":"Blindheim",
    "sg:phone":"+49 9074/5419",
    "sg:postcode":"89434",
    "sg:province":"Bayern",
    "wof:name":"A. B\u00f6hm",
    "wof:placetype":"venue"
},
  "geometry": {"coordinates":[10.6164112091,48.6320648193],"type":"Point"}
}