{
  "type": "Feature",
  "properties": {
    "iso:country":"DE",
    "sg:address":"Johnsallee 9",
    "sg:city":"Hamburg",
    "sg:phone":"+49 40/41466683",
    "sg:postcode":"20148",
    "sg:province":"Hamburg",
    "wof:name":"Andreas Nolte Rechtsanwalt",
    "wof:placetype":"venue"
},
  "geometry": {"coordinates":[9.9947099686,53.5665664673],"type":"Point"}
}