{
  "type": "Feature",
  "properties": {
    "iso:country":"DE",
    "sg:address":"Waldmeisterstr. 11",
    "sg:city":"Berlin",
    "sg:phone":"+49 30/89502763",
    "sg:postcode":"14193",
    "sg:province":"Berlin",
    "wof:name":"Adora Wohnbau- Und Sanierungsges. Mbh",
    "wof:placetype":"venue"
},
  "geometry": {"coordinates":[13.275169,52.475636],"type":"Point"}
}