{
  "type": "Feature",
  "properties": {
    "iso:country":"DE",
    "sg:address":"Bauernstr. 5",
    "sg:city":"Vahldorf",
    "sg:postcode":"39345",
    "sg:province":"Sachsen-Anhalt",
    "wof:name":"Behrens Verwaltungs Gmbh",
    "wof:placetype":"venue"
},
  "geometry": {"coordinates":[11.505054,52.257828],"type":"Point"}
}