{
  "type": "Feature",
  "properties": {
    "iso:country":"DE",
    "sg:address":"Boxbergweg",
    "sg:city":"Aukrug",
    "sg:phone":"+49 4873/625",
    "sg:postcode":"24613",
    "sg:province":"Schleswig-Holstein",
    "wof:name":"Restaurant Am Boxberg",
    "wof:placetype":"venue"
},
  "geometry": {"coordinates":[9.7325801849,54.0699195862],"type":"Point"}
}