{
  "type": "Feature",
  "properties": {
    "iso:country":"DE",
    "sg:address":"Alte Bahnhofstr 20",
    "sg:city":"Bochum",
    "sg:phone":"+49 234/280019",
    "sg:postcode":"44789",
    "sg:province":"Nordrhein-Westfalen",
    "wof:name":"Volksbank Bochum Eg",
    "wof:placetype":"venue"
},
  "geometry": {"coordinates":[7.322176,51.472366],"type":"Point"}
}