{
  "type": "Feature",
  "properties": {
    "iso:country":"DE",
    "sg:address":"Siemensstr 21",
    "sg:city":"Ahaus",
    "sg:phone":"+49 2561/93650",
    "sg:postcode":"48683",
    "sg:province":"Nordrhein-Westfalen",
    "wof:name":"Getr\u00e4nkefachgro\u00dfhandel Gr\u00fcnewald Gmbh & Co Kg",
    "wof:placetype":"venue"
},
  "geometry": {"coordinates":[7.027352,52.079292],"type":"Point"}
}