{
  "type": "Feature",
  "properties": {
    "iso:country":"DE",
    "sg:address":"Heimbachtal 92",
    "sg:city":"Niederheimbach",
    "sg:phone":"+49 6743/6996",
    "sg:postcode":"55413",
    "sg:province":"Rheinland-Pfalz",
    "wof:name":"H. Hartel",
    "wof:placetype":"venue"
},
  "geometry": {"coordinates":[7.800746,50.030327],"type":"Point"}
}