{
  "type": "Feature",
  "properties": {
    "iso:country":"DE",
    "sg:address":"D\u00f6ser Seedeich 6",
    "sg:city":"Cuxhaven",
    "sg:phone":"+49 4721/36497",
    "sg:postcode":"27472",
    "sg:province":"Niedersachsen",
    "wof:name":"Kindererholungsheim D. C. H. Donner-stiftung",
    "wof:placetype":"venue"
},
  "geometry": {"coordinates":[8.6906871796,53.8763122559],"type":"Point"}
}