{
  "type": "Feature",
  "properties": {
    "iso:country":"DE",
    "sg:address":"Buchenkreuzweg 15 a",
    "sg:city":"Bad M\u00fcnstereifel",
    "sg:phone":"+49 2257/4155",
    "sg:postcode":"53902",
    "sg:province":"Nordrhein-Westfalen",
    "wof:name":"Hsb Hoch-stahlbetonbau- Bau Gmbh",
    "wof:placetype":"venue"
},
  "geometry": {"coordinates":[6.863406,50.52906],"type":"Point"}
}