{
  "type": "Feature",
  "properties": {
    "iso:country":"DE",
    "sg:address":"Haldenstieg 7",
    "sg:city":"Hamburg",
    "sg:phone":"+49 40/4806660",
    "sg:postcode":"22453",
    "sg:province":"Hamburg",
    "wof:name":"Collection M R. M\u00fcller & Co.",
    "wof:placetype":"venue"
},
  "geometry": {"coordinates":[9.9722576141,53.6140480042],"type":"Point"}
}