{
  "type": "Feature",
  "properties": {
    "iso:country":"DE",
    "sg:address":"Ansbacher Str. 55",
    "sg:city":"Berlin",
    "sg:phone":"+49 30/2185694",
    "sg:postcode":"10777",
    "sg:province":"Berlin",
    "wof:name":"Ulrich Stoppel Steuerberater",
    "wof:placetype":"venue"
},
  "geometry": {"coordinates":[13.3399963379,52.4977531433],"type":"Point"}
}