{
  "type": "Feature",
  "properties": {
    "iso:country":"DE",
    "sg:address":"Saas 10",
    "sg:city":"Bayreuth",
    "sg:phone":"+49 921/66195",
    "sg:postcode":"95447",
    "sg:province":"Bayern",
    "wof:name":"Richard Kropff",
    "wof:placetype":"venue"
},
  "geometry": {"coordinates":[11.559425,49.916546],"type":"Point"}
}