{
  "type": "Feature",
  "properties": {
    "iso:country":"DE",
    "sg:address":"Max-Eyth-Str. 36",
    "sg:city":"Kirchheim",
    "sg:postcode":"73230",
    "sg:province":"Baden-W\u00fcrttemberg",
    "wof:name":"Claudia Ott",
    "wof:placetype":"venue"
},
  "geometry": {"coordinates":[9.4519500732,48.648273468],"type":"Point"}
}