{
  "type": "Feature",
  "properties": {
    "iso:country":"DE",
    "sg:address":"J\u00e4gerweg 12",
    "sg:city":"Wutach",
    "sg:phone":"+49 7709/394",
    "sg:postcode":"79879",
    "sg:province":"Baden-W\u00fcrttemberg",
    "wof:name":"Walter Keller",
    "wof:placetype":"venue"
},
  "geometry": {"coordinates":[8.4422397614,47.8405303955],"type":"Point"}
}