{
  "type": "Feature",
  "properties": {
    "iso:country":"DE",
    "sg:address":"Hindenburgstr. 26 a",
    "sg:city":"P\u00f6cking",
    "sg:postcode":"82343",
    "sg:province":"Bayern",
    "wof:name":"Kesol Beteiligungs Gmbh & Co. Vermietungs- Kg",
    "wof:placetype":"venue"
},
  "geometry": {"coordinates":[11.304967,47.964485],"type":"Point"}
}