{
  "type": "Feature",
  "properties": {
    "iso:country":"DE",
    "sg:address":"Warnem\u00fcnder Weg 8",
    "sg:city":"Hamburg",
    "sg:phone":"+49 40/6771323",
    "sg:postcode":"22143",
    "sg:province":"Hamburg",
    "wof:name":"Alten- Und Pflegeheim Erica Von Elm Gmbh",
    "wof:placetype":"venue"
},
  "geometry": {"coordinates":[10.164276,53.608765],"type":"Point"}
}