{
  "type": "Feature",
  "properties": {
    "iso:country":"DE",
    "sg:address":"Untere Str. 60",
    "sg:city":"Vahlbruch",
    "sg:phone":"+49 5535/911132",
    "sg:postcode":"37647",
    "sg:province":"Niedersachsen",
    "wof:name":"Home Care",
    "wof:placetype":"venue"
},
  "geometry": {"coordinates":[9.336811,51.919743],"type":"Point"}
}