{
  "type": "Feature",
  "properties": {
    "iso:country":"DE",
    "sg:address":"Peter-B\u00f6hler-Str. 21",
    "sg:city":"Frankfurt",
    "sg:phone":"+49 69/511551",
    "sg:postcode":"60431",
    "sg:province":"Hessen",
    "wof:name":"G\u00fcnter Hessenthaler Steuerberater",
    "wof:placetype":"venue"
},
  "geometry": {"coordinates":[8.651468277,50.1433296204],"type":"Point"}
}