{
  "type": "Feature",
  "properties": {
    "iso:country":"DE",
    "sg:address":"Hauptstr. 96",
    "sg:city":"Oyten",
    "sg:phone":"+49 4207/1283",
    "sg:postcode":"28876",
    "sg:province":"Niedersachsen",
    "wof:name":"Restaurant Zum Alten Krug Familie Bitter",
    "wof:placetype":"venue"
},
  "geometry": {"coordinates":[9.0153846741,53.0592269897],"type":"Point"}
}