{
  "type": "Feature",
  "properties": {
    "iso:country":"DE",
    "sg:address":"Kirschweg 10",
    "sg:city":"Trendelburg",
    "sg:phone":"+49 5675/9404",
    "sg:postcode":"34388",
    "sg:province":"Hessen",
    "wof:name":"B. Und S. Wohlgemuth",
    "wof:placetype":"venue"
},
  "geometry": {"coordinates":[9.376813,51.611919],"type":"Point"}
}