{
  "type": "Feature",
  "properties": {
    "iso:country":"DE",
    "sg:address":"Breite Str. 7",
    "sg:city":"Bovenden",
    "sg:phone":"+49 551/508610",
    "sg:postcode":"37120",
    "sg:province":"Niedersachsen",
    "wof:name":"Walter Seifart",
    "wof:placetype":"venue"
},
  "geometry": {"coordinates":[9.92459,51.587082],"type":"Point"}
}