{
  "type": "Feature",
  "properties": {
    "iso:country":"DE",
    "sg:address":"Pferchleite 16",
    "sg:city":"Ebersdorf",
    "sg:phone":"+49 9560/451",
    "sg:postcode":"96237",
    "sg:province":"Bayern",
    "wof:name":"G. Meier Gmbh",
    "wof:placetype":"venue"
},
  "geometry": {"coordinates":[11.0609769821,50.2338523865],"type":"Point"}
}