{
  "type": "Feature",
  "properties": {
    "iso:country":"DE",
    "sg:address":"Friedensstr. 1a",
    "sg:city":"L\u00fcdersdorf",
    "sg:phone":"+49 33365/243",
    "sg:postcode":"16248",
    "sg:province":"Brandenburg",
    "wof:name":"Klaus Sassenhagen",
    "wof:placetype":"venue"
},
  "geometry": {"coordinates":[14.045297,52.864239],"type":"Point"}
}