{
  "type": "Feature",
  "properties": {
    "iso:country":"DE",
    "sg:address":"Neuer Pferdemarkt 11",
    "sg:city":"Hamburg",
    "sg:phone":"+49 40/4306969",
    "sg:postcode":"20359",
    "sg:province":"Hamburg",
    "wof:name":"Roland Weber Rechtsanwalt",
    "wof:placetype":"venue"
},
  "geometry": {"coordinates":[9.9642677307,53.55859375],"type":"Point"}
}