{
  "type": "Feature",
  "properties": {
    "iso:country":"DE",
    "sg:address":"Charlottenstr. 5",
    "sg:city":"Braubach",
    "sg:phone":"+49 2627/610",
    "sg:postcode":"56338",
    "sg:province":"Rheinland-Pfalz",
    "wof:name":"Hildegard K\u00fcpper Masseurin",
    "wof:placetype":"venue"
},
  "geometry": {"coordinates":[7.641206,50.276333],"type":"Point"}
}