{
  "type": "Feature",
  "properties": {
    "iso:country":"DE",
    "sg:address":"S\u00fcdstr. 1",
    "sg:city":"Lichterfeld",
    "sg:postcode":"03238",
    "sg:province":"Brandenburg",
    "wof:name":"Herbert Quitschke",
    "wof:placetype":"venue"
},
  "geometry": {"coordinates":[13.776143074,51.5952186584],"type":"Point"}
}