{
  "type": "Feature",
  "properties": {
    "iso:country":"DE",
    "sg:address":"Lennestr. 68",
    "sg:city":"Bonn",
    "sg:phone":"+49 228/223288",
    "sg:postcode":"53113",
    "sg:province":"Nordrhein-Westfalen",
    "wof:name":"Richard B\u00f6cking Rechtsanwalt",
    "wof:placetype":"venue"
},
  "geometry": {"coordinates":[7.1078290939,50.7265930176],"type":"Point"}
}