{
  "type": "Feature",
  "properties": {
    "iso:country":"DE",
    "sg:address":"Sch\u00f6nbacher Str. 3",
    "sg:city":"Breitscheid",
    "sg:phone":"+49 2777/6275",
    "sg:postcode":"35767",
    "sg:province":"Hessen",
    "wof:name":"Harry Kuhlmann",
    "wof:placetype":"venue"
},
  "geometry": {"coordinates":[8.1902532578,50.6840667725],"type":"Point"}
}