{
  "type": "Feature",
  "properties": {
    "iso:country":"DE",
    "sg:address":"August-Schmidt-Str. 6",
    "sg:city":"Dortmund",
    "sg:postcode":"44227",
    "sg:province":"Nordrhein-Westfalen",
    "wof:name":"Wiss. Institut Fach Konstruktive Bauphysik",
    "wof:placetype":"venue"
},
  "geometry": {"coordinates":[7.4130468369,51.4847984314],"type":"Point"}
}