{
  "type": "Feature",
  "properties": {
    "iso:country":"DE",
    "sg:address":"Steinweg 11",
    "sg:city":"Bessenbach",
    "sg:phone":"+49 6095/2704",
    "sg:postcode":"63856",
    "sg:province":"Bayern",
    "wof:name":"Hans-peter Lerner",
    "wof:placetype":"venue"
},
  "geometry": {"coordinates":[9.258205,49.971642],"type":"Point"}
}