{
  "type": "Feature",
  "properties": {
    "iso:country":"DE",
    "sg:address":"Debis Haus Am Potsdamer Platz::",
    "sg:city":"Berlin",
    "sg:phone":"+49 4930/2554470",
    "sg:postcode":"10785",
    "sg:province":"Berlin",
    "wof:name":"Debis Assekuranz Makler Gmbh",
    "wof:placetype":"venue"
},
  "geometry": {"coordinates":[13.374745,52.509296],"type":"Point"}
}