{
  "type": "Feature",
  "properties": {
    "iso:country":"DE",
    "sg:address":"Bismarckstr. 90",
    "sg:city":"Ha\u00dfloch",
    "sg:phone":"+49 6324/3483",
    "sg:postcode":"67454",
    "sg:province":"Rheinland-Pfalz",
    "wof:name":"Werner Herrmann",
    "wof:placetype":"venue"
},
  "geometry": {"coordinates":[8.263589,49.367714],"type":"Point"}
}