{
  "type": "Feature",
  "properties": {
    "iso:country":"DE",
    "sg:address":"Jahnstr. 1",
    "sg:city":"Borken",
    "sg:phone":"+49 2861/4160",
    "sg:postcode":"46325",
    "sg:province":"Nordrhein-Westfalen",
    "wof:name":"Gerhard Specht Steuerberater",
    "wof:placetype":"venue"
},
  "geometry": {"coordinates":[6.8504538536,51.8476676941],"type":"Point"}
}