{
  "type": "Feature",
  "properties": {
    "iso:country":"DE",
    "sg:address":"Hauptstr. 89",
    "sg:city":"Viersen",
    "sg:phone":"+49 2162/12953",
    "sg:postcode":"41747",
    "sg:province":"Nordrhein-Westfalen",
    "wof:name":"H. Und E. Heisters",
    "wof:placetype":"venue"
},
  "geometry": {"coordinates":[6.390706,51.255478],"type":"Point"}
}