{
  "type": "Feature",
  "properties": {
    "iso:country":"DE",
    "sg:address":"Br\u00fcckenm\u00fchle",
    "sg:city":"Gro\u00dfenehrich",
    "sg:phone":"+49 36370/40351",
    "sg:postcode":"99718",
    "sg:province":"Th\u00fcringen",
    "wof:name":"Heinz P\u00f6\u00dfel",
    "wof:placetype":"venue"
},
  "geometry": {"coordinates":[10.83012,51.252022],"type":"Point"}
}