{
  "type": "Feature",
  "properties": {
    "iso:country":"DE",
    "sg:address":"Donaustr. 1",
    "sg:city":"Fridingen",
    "sg:phone":"+49 4974/63491",
    "sg:postcode":"78567",
    "sg:province":"Baden-W\u00fcrttemberg",
    "wof:name":"Raiffeisenbank Donau-heuberg Eg",
    "wof:placetype":"venue"
},
  "geometry": {"coordinates":[8.9331,48.02137],"type":"Point"}
}