{
  "type": "Feature",
  "properties": {
    "iso:country":"DE",
    "sg:address":"\u00c4u\u00dfere Reichenbacher Str. 9",
    "sg:city":"Plauen",
    "sg:phone":"+49 3741/431499",
    "sg:postcode":"08529",
    "sg:province":"Sachsen",
    "wof:name":"M. Theege",
    "wof:placetype":"venue"
},
  "geometry": {"coordinates":[12.153418541,50.4941749573],"type":"Point"}
}