{
  "type": "Feature",
  "properties": {
    "iso:country":"DE",
    "sg:address":"Nienburger Str. 4",
    "sg:city":"Marklohe",
    "sg:phone":"+49 5021/2679",
    "sg:postcode":"31608",
    "sg:province":"Niedersachsen",
    "wof:name":"Werner Cunow Rastst\u00e4tte",
    "wof:placetype":"venue"
},
  "geometry": {"coordinates":[9.1603527069,52.6596374512],"type":"Point"}
}