{
  "type": "Feature",
  "properties": {
    "iso:country":"DE",
    "sg:address":"M\u00f6rikestr. 2",
    "sg:city":"G\u00f6ppingen",
    "sg:phone":"+49 7161/70660",
    "sg:postcode":"73033",
    "sg:province":"Baden-W\u00fcrttemberg",
    "wof:name":"Westado",
    "wof:placetype":"venue"
},
  "geometry": {"coordinates":[9.6582040787,48.701210022],"type":"Point"}
}