{
  "type": "Feature",
  "properties": {
    "iso:country":"DE",
    "sg:address":"Fritz-Thiele-Str. 22",
    "sg:city":"Bremen",
    "sg:postcode":"28279",
    "sg:province":"Bremen",
    "wof:name":"Manuel Endler E. K.",
    "wof:placetype":"venue"
},
  "geometry": {"coordinates":[8.845081,53.049171],"type":"Point"}
}