{
  "type": "Feature",
  "properties": {
    "iso:country":"DE",
    "sg:address":"Milchhofstr. 1",
    "sg:city":"Emmendingen",
    "sg:phone":"+49 7641/935836",
    "sg:postcode":"79312",
    "sg:province":"Baden-W\u00fcrttemberg",
    "wof:name":"Wasserbettenstudio An Der Elz Gmbh",
    "wof:placetype":"venue"
},
  "geometry": {"coordinates":[7.8545799255,48.1093406677],"type":"Point"}
}