{
  "type": "Feature",
  "properties": {
    "iso:country":"DE",
    "sg:address":"Am Sulzbogen 58",
    "sg:city":"F\u00fcrstenfeldbruck",
    "sg:phone":"+49 8141/1303",
    "sg:postcode":"82256",
    "sg:province":"Bayern",
    "wof:name":"Univer-textil- Verwaltungsges. Mbh",
    "wof:placetype":"venue"
},
  "geometry": {"coordinates":[11.2271852493,48.1634941101],"type":"Point"}
}