{
  "type": "Feature",
  "properties": {
    "iso:country":"DE",
    "sg:address":"Am Wegfeld 21",
    "sg:city":"N\u00fcrnberg",
    "sg:phone":"+49 911/381184",
    "sg:postcode":"90427",
    "sg:province":"Bayern",
    "wof:name":"H. Link",
    "wof:placetype":"venue"
},
  "geometry": {"coordinates":[11.0446195602,49.4919204712],"type":"Point"}
}