{
  "type": "Feature",
  "properties": {
    "iso:country":"DE",
    "sg:address":"Breslauer Str. 24",
    "sg:city":"Wehrheim",
    "sg:phone":"+49 6081/5000",
    "sg:postcode":"61273",
    "sg:province":"Hessen",
    "wof:name":"Easydata Gmbh",
    "wof:placetype":"venue"
},
  "geometry": {"coordinates":[8.572787,50.302471],"type":"Point"}
}