{
  "type": "Feature",
  "properties": {
    "iso:country":"DE",
    "sg:address":"Bolsterbaum 2",
    "sg:city":"Essen",
    "sg:phone":"+49 201/302281",
    "sg:postcode":"45327",
    "sg:province":"Nordrhein-Westfalen",
    "wof:name":"Karl H. Mohr",
    "wof:placetype":"venue"
},
  "geometry": {"coordinates":[7.0442500114,51.5028495789],"type":"Point"}
}