{
  "type": "Feature",
  "properties": {
    "iso:country":"DE",
    "sg:address":"Neuendorfer Str. 2",
    "sg:city":"Alt-Schadow",
    "sg:phone":"+49 35473/704",
    "sg:postcode":"15910",
    "sg:province":"Brandenburg",
    "wof:name":"Pension",
    "wof:placetype":"venue"
},
  "geometry": {"coordinates":[13.7658214569,51.9795913696],"type":"Point"}
}