{
  "type": "Feature",
  "properties": {
    "iso:country":"DE",
    "sg:address":"M\u00fchlgasse 17",
    "sg:city":"Kirchhain",
    "sg:phone":"+49 6422/922078",
    "sg:postcode":"35274",
    "sg:province":"Hessen",
    "wof:name":"Jugendf\u00f6rderung Stadt Kirchhain",
    "wof:placetype":"venue"
},
  "geometry": {"coordinates":[8.9223003387,50.8211212158],"type":"Point"}
}