{
  "type": "Feature",
  "properties": {
    "iso:country":"DE",
    "sg:address":"Luitpoldstr. 11",
    "sg:city":"Rockenhausen",
    "sg:phone":"+49 6361/3490",
    "sg:postcode":"67806",
    "sg:province":"Rheinland-Pfalz",
    "wof:name":"Carmen Alsentzer Rechtsanw\u00e4ltin",
    "wof:placetype":"venue"
},
  "geometry": {"coordinates":[7.8203411102,49.6286964417],"type":"Point"}
}