{
  "type": "Feature",
  "properties": {
    "iso:country":"DE",
    "sg:address":"Flinsbachstr. 6",
    "sg:city":"Trier",
    "sg:phone":"+49 651/970670",
    "sg:postcode":"54295",
    "sg:province":"Rheinland-Pfalz",
    "wof:name":"Aktiv Kommunikationsdienst",
    "wof:placetype":"venue"
},
  "geometry": {"coordinates":[6.6481890678,49.7348670959],"type":"Point"}
}