{
  "type": "Feature",
  "properties": {
    "iso:country":"DE",
    "sg:address":"Ulmenstr. 29",
    "sg:city":"Sindelfingen",
    "sg:phone":"+49 7031/383005",
    "sg:postcode":"71069",
    "sg:province":"Baden-W\u00fcrttemberg",
    "wof:name":"Foto-schuster",
    "wof:placetype":"venue"
},
  "geometry": {"coordinates":[8.9688463211,48.7297515869],"type":"Point"}
}