{
  "type": "Feature",
  "properties": {
    "iso:country":"DE",
    "sg:address":"Marktplatz 3",
    "sg:city":"Homberg",
    "sg:phone":"+49 5681/2195",
    "sg:postcode":"34576",
    "sg:province":"Hessen",
    "wof:name":"Eiscafe Cortina",
    "wof:placetype":"venue"
},
  "geometry": {"coordinates":[9.40471,51.033794],"type":"Point"}
}