{
  "type": "Feature",
  "properties": {
    "iso:country":"DE",
    "sg:address":"Liedbergweg 9",
    "sg:city":"K\u00f6ln",
    "sg:phone":"+49 221/607632",
    "sg:postcode":"51069",
    "sg:province":"Nordrhein-Westfalen",
    "wof:name":"J\u00fcrgen Brochhaus",
    "wof:placetype":"venue"
},
  "geometry": {"coordinates":[7.031354,51.00193],"type":"Point"}
}