{
  "type": "Feature",
  "properties": {
    "iso:country":"DE",
    "sg:address":"H\u00e4nselstr. 31",
    "sg:city":"Berlin",
    "sg:phone":"+49 30/5328395",
    "sg:postcode":"12437",
    "sg:province":"Berlin",
    "wof:name":"Roland Gr\u00fcnz",
    "wof:placetype":"venue"
},
  "geometry": {"coordinates":[13.4771757126,52.4694633484],"type":"Point"}
}