{
  "type": "Feature",
  "properties": {
    "iso:country":"DE",
    "sg:address":"Gutenbergstr. 9",
    "sg:city":"Selm",
    "sg:postcode":"59379",
    "sg:province":"Nordrhein-Westfalen",
    "wof:name":"Klaus Kahlke Gmbh",
    "wof:placetype":"venue"
},
  "geometry": {"coordinates":[7.460337,51.673008],"type":"Point"}
}