{
  "type": "Feature",
  "properties": {
    "iso:country":"DE",
    "sg:address":"Heinrich-Heine-Str. 1",
    "sg:city":"Kamenz",
    "sg:phone":"+49 35783/02602",
    "sg:postcode":"01917",
    "sg:province":"Sachsen",
    "wof:name":"Lilo Vostry",
    "wof:placetype":"venue"
},
  "geometry": {"coordinates":[14.1038179398,51.2802314758],"type":"Point"}
}