{
  "type": "Feature",
  "properties": {
    "iso:country":"DE",
    "sg:address":"Glockenstr. 18",
    "sg:city":"Solingen",
    "sg:phone":"+49 212/816436",
    "sg:postcode":"42657",
    "sg:province":"Nordrhein-Westfalen",
    "wof:name":"Katholisches Pfarramt St. Suibertus",
    "wof:placetype":"venue"
},
  "geometry": {"coordinates":[7.0735440254,51.159702301],"type":"Point"}
}