{
  "type": "Feature",
  "properties": {
    "iso:country":"DE",
    "sg:address":"G\u00f6gestr. 6",
    "sg:city":"Dortmund",
    "sg:phone":"+49 231/713487",
    "sg:postcode":"44225",
    "sg:province":"Nordrhein-Westfalen",
    "wof:name":"Hanno Meith Ingenieur",
    "wof:placetype":"venue"
},
  "geometry": {"coordinates":[7.4544410706,51.4707450867],"type":"Point"}
}