{
  "type": "Feature",
  "properties": {
    "iso:country":"DE",
    "sg:address":"Homburger Str. 47",
    "sg:city":"Zweibr\u00fccken",
    "sg:phone":"+49 6332/3591",
    "sg:postcode":"66482",
    "sg:province":"Rheinland-Pfalz",
    "wof:name":"Ambos Gmbh",
    "wof:placetype":"venue"
},
  "geometry": {"coordinates":[7.344968,49.253551],"type":"Point"}
}