{
  "type": "Feature",
  "properties": {
    "iso:country":"DE",
    "sg:address":"Unnaer Str. 28",
    "sg:city":"Menden",
    "sg:phone":"+49 2373/12608",
    "sg:postcode":"58706",
    "sg:province":"Nordrhein-Westfalen",
    "wof:name":"Die Zwei",
    "wof:placetype":"venue"
},
  "geometry": {"coordinates":[7.7908368111,51.4407539368],"type":"Point"}
}