{
  "type": "Feature",
  "properties": {
    "iso:country":"DE",
    "sg:address":"M\u00fchlweg 1",
    "sg:city":"Elsenfeld",
    "sg:phone":"+49 6022/9396",
    "sg:postcode":"63820",
    "sg:province":"Bayern",
    "wof:name":"Dieter Eichelsbacher",
    "wof:placetype":"venue"
},
  "geometry": {"coordinates":[9.1618309021,49.8430023193],"type":"Point"}
}