{
  "type": "Feature",
  "properties": {
    "iso:country":"DE",
    "sg:address":"Wittenberger Str. 39",
    "sg:city":"M\u00fchlanger",
    "sg:phone":"+49 34922/60405",
    "sg:postcode":"06888",
    "sg:province":"Sachsen-Anhalt",
    "wof:name":"O. H\u00f6hne",
    "wof:placetype":"venue"
},
  "geometry": {"coordinates":[12.736471,51.856903],"type":"Point"}
}