{
  "type": "Feature",
  "properties": {
    "iso:country":"DE",
    "sg:address":"Bielefelder Str. 39",
    "sg:city":"Steinhagen",
    "sg:phone":"+49 5204/2144",
    "sg:postcode":"33803",
    "sg:province":"Nordrhein-Westfalen",
    "wof:name":"Kurt Beier",
    "wof:placetype":"venue"
},
  "geometry": {"coordinates":[8.424139,52.007915],"type":"Point"}
}