{
  "type": "Feature",
  "properties": {
    "iso:country":"DE",
    "sg:address":"Am Leuchtturm 1",
    "sg:city":"Hamburg",
    "sg:phone":"+49 40/815662",
    "sg:postcode":"22559",
    "sg:province":"Hamburg",
    "wof:name":"Hans-j\u00fcrgen Werner Architekt",
    "wof:placetype":"venue"
},
  "geometry": {"coordinates":[9.741285,53.565388],"type":"Point"}
}