{
  "type": "Feature",
  "properties": {
    "iso:country":"DE",
    "sg:address":"Eckhardwiesenstr. 7",
    "sg:city":"Darmstadt",
    "sg:phone":"+49 6151/712411",
    "sg:postcode":"64289",
    "sg:province":"Hessen",
    "wof:name":"Kehl",
    "wof:placetype":"venue"
},
  "geometry": {"coordinates":[8.681812,49.908089],"type":"Point"}
}