{
  "type": "Feature",
  "properties": {
    "iso:country":"DE",
    "sg:address":"Behlertstr. 5",
    "sg:city":"Potsdam",
    "sg:phone":"+49 331/2800088",
    "sg:postcode":"14469",
    "sg:province":"Brandenburg",
    "wof:name":"Entwicklungsgesellschaft Behlertstr. 5 Mbh & Co. Kg",
    "wof:placetype":"venue"
},
  "geometry": {"coordinates":[13.064803,52.406506],"type":"Point"}
}