{
  "type": "Feature",
  "properties": {
    "iso:country":"DE",
    "sg:address":"Obere Au 7",
    "sg:city":"Bischofsheim",
    "sg:phone":"+49 9775/9208",
    "sg:postcode":"97653",
    "sg:province":"Bayern",
    "wof:name":"Gerhard M\u00fcller",
    "wof:placetype":"venue"
},
  "geometry": {"coordinates":[10.081402,50.396713],"type":"Point"}
}