{
  "type": "Feature",
  "properties": {
    "iso:country":"DE",
    "sg:address":"Baldern",
    "sg:city":"Bopfingen",
    "sg:phone":"+49 7362/3869",
    "sg:postcode":"73441",
    "sg:province":"Baden-W\u00fcrttemberg",
    "wof:name":"Hermann Schmid",
    "wof:placetype":"venue"
},
  "geometry": {"coordinates":[10.3135204315,48.9025917053],"type":"Point"}
}