{
  "type": "Feature",
  "properties": {
    "iso:country":"DE",
    "sg:address":"Hofmarkstr. 38",
    "sg:city":"Nittendorf",
    "sg:phone":"+49 9404/8330",
    "sg:postcode":"93152",
    "sg:province":"Bayern",
    "wof:name":"Hofmark-apotheke Inh. Dr. G. Fr\u00f6hlich E. K.",
    "wof:placetype":"venue"
},
  "geometry": {"coordinates":[11.933322,49.027256],"type":"Point"}
}