{
  "type": "Feature",
  "properties": {
    "iso:country":"DE",
    "sg:address":"Elsternweg 5",
    "sg:city":"K\u00e4mpfelbach-Ersingen",
    "sg:phone":"+49 7231/8008923",
    "sg:postcode":"75236",
    "sg:province":"Baden-W\u00fcrttemberg",
    "wof:name":"Butterfly Inh.g.b\u00e4uerle M.furch",
    "wof:placetype":"venue"
},
  "geometry": {"coordinates":[8.6487131119,48.9297523499],"type":"Point"}
}