{
  "type": "Feature",
  "properties": {
    "iso:country":"DE",
    "sg:address":"Albert-Sch\u00e4ffle-Str. 78",
    "sg:city":"Stuttgart",
    "sg:phone":"+49 711/466786",
    "sg:postcode":"70186",
    "sg:province":"Baden-W\u00fcrttemberg",
    "wof:name":"Horst Dr\u00f6gm\u00f6ller Architekt",
    "wof:placetype":"venue"
},
  "geometry": {"coordinates":[9.200622,48.771416],"type":"Point"}
}