{
  "type": "Feature",
  "properties": {
    "iso:country":"DE",
    "sg:address":"Im Dorfe 19",
    "sg:city":"Bad Nenndorf",
    "sg:phone":"+49 5723/4913",
    "sg:postcode":"31542",
    "sg:province":"Niedersachsen",
    "wof:name":"Hotel Restaurant Schaumburger Hof",
    "wof:placetype":"venue"
},
  "geometry": {"coordinates":[9.350859642,52.3388557434],"type":"Point"}
}