{
  "type": "Feature",
  "properties": {
    "iso:country":"DE",
    "sg:address":"Sebastianstr. 136",
    "sg:city":"K\u00f6ln",
    "sg:phone":"+49 221/7122140",
    "sg:postcode":"50735",
    "sg:province":"Nordrhein-Westfalen",
    "wof:name":"A. Bantuwakis",
    "wof:placetype":"venue"
},
  "geometry": {"coordinates":[6.961602211,50.9884033203],"type":"Point"}
}