{
  "type": "Feature",
  "properties": {
    "iso:country":"DE",
    "sg:address":"Lustgartenstr. 4a",
    "sg:city":"Spremberg",
    "sg:phone":"+49 3563/39070",
    "sg:postcode":"03130",
    "sg:province":"Brandenburg",
    "wof:name":"St\u00e4dtische Werke Spremberg Gmbh",
    "wof:placetype":"venue"
},
  "geometry": {"coordinates":[14.37545,51.564457],"type":"Point"}
}