{
  "type": "Feature",
  "properties": {
    "iso:country":"DE",
    "sg:address":"Eisenacher Str. 1",
    "sg:city":"Michelstadt",
    "sg:phone":"+49 6061/72593",
    "sg:postcode":"64720",
    "sg:province":"Hessen",
    "wof:name":"Ets H.-j.grasm\u00fcck Gmbh",
    "wof:placetype":"venue"
},
  "geometry": {"coordinates":[9.01261,49.674892],"type":"Point"}
}