{
  "type": "Feature",
  "properties": {
    "iso:country":"DE",
    "sg:address":"Nikolaus-Otto-Str. 28",
    "sg:city":"Schwerin",
    "sg:phone":"+49 4938/5646460",
    "sg:postcode":"19061",
    "sg:province":"Mecklenburg-Vorpommern",
    "wof:name":"Rolf Kopsicker Gmbh",
    "wof:placetype":"venue"
},
  "geometry": {"coordinates":[11.384209,53.564766],"type":"Point"}
}