{
  "type": "Feature",
  "properties": {
    "iso:country":"DE",
    "sg:address":"Hannoversche Str. 66",
    "sg:city":"Hannover",
    "sg:phone":"+49 511/580163",
    "sg:postcode":"30629",
    "sg:province":"Niedersachsen",
    "wof:name":"Kuhnke & Kruse Gmbh Elektroanlagen",
    "wof:placetype":"venue"
},
  "geometry": {"coordinates":[9.839873,52.387791],"type":"Point"}
}