{
  "type": "Feature",
  "properties": {
    "iso:country":"DE",
    "sg:address":"In den Sieben St\u00fccken 7 a",
    "sg:city":"Hannover",
    "sg:phone":"+49 511/64671",
    "sg:postcode":"30655",
    "sg:province":"Niedersachsen",
    "wof:name":"Gesellschaft F\u00fcr Bauen Und Wohnen Hannover Mbh",
    "wof:placetype":"venue"
},
  "geometry": {"coordinates":[9.8097820282,52.4080276489],"type":"Point"}
}