{
  "type": "Feature",
  "properties": {
    "iso:country":"DE",
    "sg:address":"M\u00fchlenstr. 7",
    "sg:city":"Niddatal",
    "sg:phone":"+49 6034/5299",
    "sg:postcode":"61194",
    "sg:province":"Hessen",
    "wof:name":"Papp",
    "wof:placetype":"venue"
},
  "geometry": {"coordinates":[8.8136,50.298222],"type":"Point"}
}