{
  "type": "Feature",
  "properties": {
    "iso:country":"DE",
    "sg:address":"Underbergstr. 3",
    "sg:city":"Rheinberg",
    "sg:phone":"+49 2843/8323",
    "sg:postcode":"47495",
    "sg:province":"Nordrhein-Westfalen",
    "wof:name":"Rotherna Spirituosen Gmbh",
    "wof:placetype":"venue"
},
  "geometry": {"coordinates":[6.6016201973,51.5458106995],"type":"Point"}
}