{
  "type": "Feature",
  "properties": {
    "iso:country":"DE",
    "sg:address":"Gartenstr. 1",
    "sg:city":"Trebsen",
    "sg:phone":"+49 34383/41306",
    "sg:postcode":"04687",
    "sg:province":"Sachsen",
    "wof:name":"Eva-maria Kunze",
    "wof:placetype":"venue"
},
  "geometry": {"coordinates":[12.7512426376,51.287361145],"type":"Point"}
}