{
  "type": "Feature",
  "properties": {
    "iso:country":"DE",
    "sg:address":"Dieselstr 3",
    "sg:city":"Sehnde",
    "sg:phone":"+49 5138/60990",
    "sg:postcode":"31319",
    "sg:province":"Niedersachsen",
    "wof:name":"Werther Logistik Gmbh & Co Kg",
    "wof:placetype":"venue"
},
  "geometry": {"coordinates":[9.976105,52.318466],"type":"Point"}
}