{
  "type": "Feature",
  "properties": {
    "iso:country":"DE",
    "sg:address":"Cannstatter Str.81",
    "sg:city":"Fellbach",
    "sg:postcode":"70734",
    "sg:province":"Baden-W\u00fcrttemberg",
    "wof:name":"Skoda Fabia Fanclub Deutschland | Fabiaclub.com",
    "wof:placetype":"venue"
},
  "geometry": {"coordinates":[9.27785,48.811878],"type":"Point"}
}