{
  "type": "Feature",
  "properties": {
    "iso:country":"DE",
    "sg:address":"Knappenweg 15",
    "sg:city":"Neunkirchen",
    "sg:phone":"+49 2735/61254",
    "sg:postcode":"57290",
    "sg:province":"Nordrhein-Westfalen",
    "wof:name":"Stefan Tetzlaff",
    "wof:placetype":"venue"
},
  "geometry": {"coordinates":[8.01259,50.800949],"type":"Point"}
}