{
  "type": "Feature",
  "properties": {
    "iso:country":"DE",
    "sg:address":"Fritz-Tarnow-Str. 15",
    "sg:city":"Frankfurt",
    "sg:phone":"+49 69/56002838",
    "sg:postcode":"60320",
    "sg:province":"Hessen",
    "wof:name":"R. Jelenc \u00dcbersetzungsb\u00fcro",
    "wof:placetype":"venue"
},
  "geometry": {"coordinates":[8.670145,50.142712],"type":"Point"}
}