{
  "type": "Feature",
  "properties": {
    "iso:country":"DE",
    "sg:address":"S\u00fcdlohner Weg 2",
    "sg:city":"Stadtlohn",
    "sg:phone":"+49 2563/1332",
    "sg:postcode":"48703",
    "sg:province":"Nordrhein-Westfalen",
    "wof:name":"Restaurant Korfu",
    "wof:placetype":"venue"
},
  "geometry": {"coordinates":[6.9055500031,51.9871406555],"type":"Point"}
}