{
  "type": "Feature",
  "properties": {
    "iso:country":"DE",
    "sg:address":"Hauptstr. 17",
    "sg:city":"Wenzenbach",
    "sg:phone":"+49 9407/94910",
    "sg:postcode":"93173",
    "sg:province":"Bayern",
    "wof:name":"W. Stierstorfer Gmbh Metzgerei",
    "wof:placetype":"venue"
},
  "geometry": {"coordinates":[12.1980018616,49.0767364502],"type":"Point"}
}