{
  "type": "Feature",
  "properties": {
    "iso:country":"DE",
    "sg:address":"Weigmannstr. 55-61",
    "sg:city":"Lauf",
    "sg:phone":"+49 9123/626390",
    "sg:postcode":"91207",
    "sg:province":"Bayern",
    "wof:name":"Holzwarenfabrik Christof D\u00f6ring Gmbh",
    "wof:placetype":"venue"
},
  "geometry": {"coordinates":[11.2878704071,49.5086517334],"type":"Point"}
}