{
  "type": "Feature",
  "properties": {
    "iso:country":"DE",
    "sg:address":"Am Bauhof 10",
    "sg:city":"Bayreuth",
    "sg:phone":"+49 921/41129",
    "sg:postcode":"95445",
    "sg:province":"Bayern",
    "wof:name":"Ofen Opel Verwaltungs Gmbh",
    "wof:placetype":"venue"
},
  "geometry": {"coordinates":[11.5546207428,49.9553108215],"type":"Point"}
}