{
  "type": "Feature",
  "properties": {
    "iso:country":"DE",
    "sg:address":"Kaiserstr. 46",
    "sg:city":"Trier",
    "sg:phone":"+49 651/43021",
    "sg:postcode":"54290",
    "sg:province":"Rheinland-Pfalz",
    "wof:name":"Schneider Automaten Gmbh & Co. Kg",
    "wof:placetype":"venue"
},
  "geometry": {"coordinates":[6.6393389702,49.7498397827],"type":"Point"}
}