{
  "type": "Feature",
  "properties": {
    "iso:country":"DE",
    "sg:address":"Alte Heerstr. 17",
    "sg:city":"Sehnde",
    "sg:phone":"+49 5138/8832",
    "sg:postcode":"31319",
    "sg:province":"Niedersachsen",
    "wof:name":"Heinrich K\u00f6hler",
    "wof:placetype":"venue"
},
  "geometry": {"coordinates":[10.022898,52.318962],"type":"Point"}
}