{
  "type": "Feature",
  "properties": {
    "iso:country":"DE",
    "sg:address":"Karolinenstr. 8",
    "sg:city":"L\u00fcdenscheid",
    "sg:postcode":"58507",
    "sg:province":"Nordrhein-Westfalen",
    "wof:name":"Iku Institut F\u00fcr Die Mittel- St\u00e4ndische Wirtschaft Gmbh",
    "wof:placetype":"venue"
},
  "geometry": {"coordinates":[7.6255669594,51.2211647034],"type":"Point"}
}