{
  "type": "Feature",
  "properties": {
    "iso:country":"DE",
    "sg:address":"Hauptstr. 131",
    "sg:city":"\u00d6stringen",
    "sg:phone":"+49 4972/5321320",
    "sg:postcode":"76684",
    "sg:province":"Baden-W\u00fcrttemberg",
    "wof:name":"Volksbank Wiesloch Eg",
    "wof:placetype":"venue"
},
  "geometry": {"coordinates":[8.7128,49.219776],"type":"Point"}
}