{
  "type": "Feature",
  "properties": {
    "iso:country":"DE",
    "sg:address":"Bergstr. 4",
    "sg:city":"Bilshausen",
    "sg:phone":"+49 5528/1295",
    "sg:postcode":"37434",
    "sg:province":"Niedersachsen",
    "wof:name":"Malerfachbetrieb W\u00fcstefeld Gmbh",
    "wof:placetype":"venue"
},
  "geometry": {"coordinates":[10.158481,51.628246],"type":"Point"}
}