{
  "type": "Feature",
  "properties": {
    "iso:country":"DE",
    "sg:address":"Fichtenstr. 23",
    "sg:city":"Brunnthal",
    "sg:phone":"+49 8104/66710",
    "sg:postcode":"85649",
    "sg:province":"Bayern",
    "wof:name":"Miva International Visual Audio Vertriebs- Gmbh",
    "wof:placetype":"venue"
},
  "geometry": {"coordinates":[11.6846599579,48.0068855286],"type":"Point"}
}