{
  "type": "Feature",
  "properties": {
    "iso:country":"DE",
    "sg:address":"An der B 1",
    "sg:city":"Jahnsfelde",
    "sg:phone":"+49 33477/310",
    "sg:postcode":"15320",
    "sg:province":"Brandenburg",
    "wof:name":"Pension-restaurant Landhaus",
    "wof:placetype":"venue"
},
  "geometry": {"coordinates":[14.2483778,52.594581604],"type":"Point"}
}