{
  "type": "Feature",
  "properties": {
    "iso:country":"DE",
    "sg:address":"Feldstra\u00dfe 10",
    "sg:city":"Eckardtshausen",
    "sg:phone":"+49 36925/61621",
    "sg:postcode":"99819",
    "sg:province":"Th\u00fcringen",
    "wof:name":"Macholdt Pictures - Grafik, Werbung & Design",
    "wof:placetype":"venue"
},
  "geometry": {"coordinates":[10.265953,50.913437],"type":"Point"}
}