{
  "type": "Feature",
  "properties": {
    "iso:country":"DE",
    "sg:address":"Klosterhof 6",
    "sg:city":"Seligenstadt",
    "sg:phone":"+49 6182/200074",
    "sg:postcode":"63500",
    "sg:province":"Hessen",
    "wof:name":"Stadt- Und Landschaftsb\u00fcch.",
    "wof:placetype":"venue"
},
  "geometry": {"coordinates":[8.978767,50.039661],"type":"Point"}
}