{
  "type": "Feature",
  "properties": {
    "iso:country":"DE",
    "sg:address":"Brunnenberg",
    "sg:city":"Kirchheimbolanden",
    "sg:postcode":"67292",
    "sg:province":"Rheinland-Pfalz",
    "wof:name":"Wilhelm Werhahn Gmbh",
    "wof:placetype":"venue"
},
  "geometry": {"coordinates":[7.959427,49.679489],"type":"Point"}
}