{
  "type": "Feature",
  "properties": {
    "iso:country":"DE",
    "sg:address":"Luisenstr. 18",
    "sg:city":"Baden-Baden",
    "sg:phone":"+49 7221/23249",
    "sg:postcode":"76530",
    "sg:province":"Baden-W\u00fcrttemberg",
    "wof:name":"Reise Ziel B. E. S. T.",
    "wof:placetype":"venue"
},
  "geometry": {"coordinates":[8.2382164001,48.7620315552],"type":"Point"}
}