{
  "type": "Feature",
  "properties": {
    "iso:country":"DE",
    "sg:address":"K\u00e4stleinsm\u00fchlenstr. 16",
    "sg:city":"Treuchtlingen",
    "sg:phone":"+49 9142/8080",
    "sg:postcode":"91757",
    "sg:province":"Bayern",
    "wof:name":"Hans Hirschmann Kg Bauunternehmung Gmbh & Co.",
    "wof:placetype":"venue"
},
  "geometry": {"coordinates":[10.9174766541,48.9595108032],"type":"Point"}
}