{
  "type": "Feature",
  "properties": {
    "iso:country":"DE",
    "sg:address":"Neuer Weg 7",
    "sg:city":"Weberstedt",
    "sg:phone":"+49 36022/778",
    "sg:postcode":"99947",
    "sg:province":"Th\u00fcringen",
    "wof:name":"Gastst\u00e4tte Tennisklause",
    "wof:placetype":"venue"
},
  "geometry": {"coordinates":[10.5137319565,51.106803894],"type":"Point"}
}