{
  "type": "Feature",
  "properties": {
    "iso:country":"DE",
    "sg:address":"Glaner Str. 53",
    "sg:city":"Wildeshausen",
    "sg:phone":"+49 4431/74373",
    "sg:postcode":"27793",
    "sg:province":"Niedersachsen",
    "wof:name":"Elysees",
    "wof:placetype":"venue"
},
  "geometry": {"coordinates":[8.4144573212,52.9026832581],"type":"Point"}
}