{
  "type": "Feature",
  "properties": {
    "iso:country":"DE",
    "sg:address":"Breite Str. 19",
    "sg:city":"Itzehoe",
    "sg:phone":"+49 4821/3880",
    "sg:postcode":"25524",
    "sg:province":"Schleswig-Holstein",
    "wof:name":"Altst\u00e4dter-apotheke",
    "wof:placetype":"venue"
},
  "geometry": {"coordinates":[9.518296,53.92231],"type":"Point"}
}