{
  "type": "Feature",
  "properties": {
    "iso:country":"DE",
    "sg:address":"Goethestr. 24",
    "sg:city":"Rotenburg",
    "sg:phone":"+49 4261/2822",
    "sg:postcode":"27356",
    "sg:province":"Niedersachsen",
    "wof:name":"Carl J. M\u00fcllers Buchhandlung Inh. Mathilde Faust",
    "wof:placetype":"venue"
},
  "geometry": {"coordinates":[9.4039726257,53.1091537476],"type":"Point"}
}