{
  "type": "Feature",
  "properties": {
    "iso:country":"DE",
    "sg:address":"Heygendorfer Str.",
    "sg:city":"Sch\u00f6newerda",
    "sg:phone":"+49 34672/8670",
    "sg:postcode":"06556",
    "sg:province":"Th\u00fcringen",
    "wof:name":"Alpha Tec Gmbh",
    "wof:placetype":"venue"
},
  "geometry": {"coordinates":[11.2894,51.363689],"type":"Point"}
}