{
  "type": "Feature",
  "properties": {
    "iso:country":"DE",
    "sg:address":"S\u00fcderstra\u00dfe 130",
    "sg:city":"Husum",
    "sg:phone":"+49 4841/5656",
    "sg:postcode":"25813",
    "sg:province":"Schleswig-Holstein",
    "wof:name":"Sch\u00f6nheits - Oase",
    "wof:placetype":"venue"
},
  "geometry": {"coordinates":[9.061444,54.47683],"type":"Point"}
}