{
  "type": "Feature",
  "properties": {
    "iso:country":"DE",
    "sg:address":"Teichstr. 8",
    "sg:city":"F\u00fcrth",
    "sg:phone":"+49 911/303116",
    "sg:postcode":"90765",
    "sg:province":"Bayern",
    "wof:name":"Erwin Loos",
    "wof:placetype":"venue"
},
  "geometry": {"coordinates":[11.008435,49.507755],"type":"Point"}
}