{
  "type": "Feature",
  "properties": {
    "iso:country":"DE",
    "sg:address":"Schlo\u00dfplatz 1",
    "sg:city":"Arnstadt",
    "sg:postcode":"99310",
    "sg:province":"Th\u00fcringen",
    "wof:name":"Museumsstiftung Zu Arnstadt",
    "wof:placetype":"venue"
},
  "geometry": {"coordinates":[10.9502515793,50.834903717],"type":"Point"}
}