{
  "type": "Feature",
  "properties": {
    "iso:country":"DE",
    "sg:address":"Im Klosterhof 4-6",
    "sg:city":"Frechen",
    "sg:phone":"+49 2234/9660820",
    "sg:postcode":"50226",
    "sg:province":"Nordrhein-Westfalen",
    "wof:name":"Frankonia Immobilienkontor Verwaltungs Gmbh",
    "wof:placetype":"venue"
},
  "geometry": {"coordinates":[6.756980896,50.9359397888],"type":"Point"}
}