{
  "type": "Feature",
  "properties": {
    "iso:country":"DE",
    "sg:address":"Lindenstr. 41",
    "sg:city":"Carlsberg",
    "sg:phone":"+49 4963/561645",
    "sg:postcode":"67316",
    "sg:province":"Rheinland-Pfalz",
    "wof:name":"Kreissparkasse Gr\u00fcnstadt",
    "wof:placetype":"venue"
},
  "geometry": {"coordinates":[8.041038,49.504215],"type":"Point"}
}