{
  "type": "Feature",
  "properties": {
    "iso:country":"DE",
    "sg:address":"Freisch\u00fctzstr. 92",
    "sg:city":"M\u00fcnchen",
    "sg:phone":"+49 89/9574541",
    "sg:postcode":"81927",
    "sg:province":"Bayern",
    "wof:name":"Wolfgang-amadeus-apotheke",
    "wof:placetype":"venue"
},
  "geometry": {"coordinates":[11.643735,48.168118],"type":"Point"}
}