{
  "type": "Feature",
  "properties": {
    "iso:country":"DE",
    "sg:address":"Bruchstr. 18",
    "sg:city":"Osnabr\u00fcck",
    "sg:phone":"+49 541/22237",
    "sg:postcode":"49074",
    "sg:province":"Niedersachsen",
    "wof:name":"Paco Gro\u00dfe-heitmeyer Ergotherapeutsche Praxis",
    "wof:placetype":"venue"
},
  "geometry": {"coordinates":[8.05884,52.271255],"type":"Point"}
}