{
  "type": "Feature",
  "properties": {
    "iso:country":"DE",
    "sg:address":"Ignatiusstr. 22",
    "sg:city":"Havixbeck",
    "sg:phone":"+49 2507/7432",
    "sg:postcode":"48329",
    "sg:province":"Nordrhein-Westfalen",
    "wof:name":"Heinrich B. Frisch Architekt",
    "wof:placetype":"venue"
},
  "geometry": {"coordinates":[7.414337,51.981495],"type":"Point"}
}