{
  "type": "Feature",
  "properties": {
    "iso:country":"DE",
    "sg:address":"91719",
    "sg:city":"Heidenheim",
    "sg:postcode":"91719",
    "sg:province":"Bayern",
    "wof:name":"Campingplatz",
    "wof:placetype":"venue"
},
  "geometry": {"coordinates":[10.74373,49.016514],"type":"Point"}
}