{
  "type": "Feature",
  "properties": {
    "iso:country":"DE",
    "sg:address":"Marktplatz 6",
    "sg:city":"Oberscheinfeld",
    "sg:phone":"+49 9167/204",
    "sg:postcode":"91483",
    "sg:province":"Bayern",
    "wof:name":"Brauereigasthof M\u00fcnich",
    "wof:placetype":"venue"
},
  "geometry": {"coordinates":[10.431844,49.709438],"type":"Point"}
}