{
  "type": "Feature",
  "properties": {
    "iso:country":"DE",
    "sg:address":"Hermannstr. 17",
    "sg:city":"Gladbeck",
    "sg:phone":"+49 2043/22082",
    "sg:postcode":"45964",
    "sg:province":"Nordrhein-Westfalen",
    "wof:name":"Heinrich Schmidt Gmbh",
    "wof:placetype":"venue"
},
  "geometry": {"coordinates":[6.989777,51.576767],"type":"Point"}
}