{
  "type": "Feature",
  "properties": {
    "iso:country":"DE",
    "sg:address":"Osterwaldstr. 59",
    "sg:city":"M\u00fcnchen",
    "sg:phone":"+49 89/364832",
    "sg:postcode":"80805",
    "sg:province":"Bayern",
    "wof:name":"R. A. Hillebrand",
    "wof:placetype":"venue"
},
  "geometry": {"coordinates":[11.6018018723,48.1687965393],"type":"Point"}
}