{
  "type": "Feature",
  "properties": {
    "iso:country":"DE",
    "sg:address":"Gartenstr. 14",
    "sg:city":"Spremberg",
    "sg:phone":"+49 3563/2342",
    "sg:postcode":"03130",
    "sg:province":"Brandenburg",
    "wof:name":"Deutsches Rotes Kreuz",
    "wof:placetype":"venue"
},
  "geometry": {"coordinates":[14.3707609177,51.5729064941],"type":"Point"}
}