{
  "type": "Feature",
  "properties": {
    "iso:country":"DE",
    "sg:address":"Stolteraer Weg 3",
    "sg:city":"Rostock",
    "sg:phone":"+49 381/52037",
    "sg:postcode":"18119",
    "sg:province":"Mecklenburg-Vorpommern",
    "wof:name":"Landhaus Frommke",
    "wof:placetype":"venue"
},
  "geometry": {"coordinates":[12.0137395859,54.1725997925],"type":"Point"}
}