{
  "type": "Feature",
  "properties": {
    "iso:country":"DE",
    "sg:address":"Whistlerweg 8",
    "sg:city":"M\u00fcnchen",
    "sg:phone":"+49 89/7911510",
    "sg:postcode":"81479",
    "sg:province":"Bayern",
    "wof:name":"Rudolf Gehringer Architekt",
    "wof:placetype":"venue"
},
  "geometry": {"coordinates":[11.524193,48.074917],"type":"Point"}
}