{
  "type": "Feature",
  "properties": {
    "iso:country":"DE",
    "sg:address":"Niedereimerfeld 19",
    "sg:city":"Arnsberg",
    "sg:phone":"+49 2931/96780",
    "sg:postcode":"59823",
    "sg:province":"Nordrhein-Westfalen",
    "wof:name":"Johann Rademacher Gmbh & Co. Kg",
    "wof:placetype":"venue"
},
  "geometry": {"coordinates":[8.0408172607,51.420085907],"type":"Point"}
}