{
  "type": "Feature",
  "properties": {
    "iso:country":"DE",
    "sg:address":"Waldallee 3",
    "sg:city":"Berlin",
    "sg:phone":"+49 30/3654779",
    "sg:postcode":"14089",
    "sg:province":"Berlin",
    "wof:name":"Ev. Pfarramt Am Gross-glienicker-see",
    "wof:placetype":"venue"
},
  "geometry": {"coordinates":[13.1270771027,52.4652137756],"type":"Point"}
}