{
  "type": "Feature",
  "properties": {
    "iso:country":"DE",
    "sg:address":"G\u00f6rlitzer Str 15",
    "sg:city":"Niesky",
    "sg:phone":"+49 3588/210985",
    "sg:postcode":"02906",
    "sg:province":"Sachsen",
    "wof:name":"Architekturb\u00fcro Radisch",
    "wof:placetype":"venue"
},
  "geometry": {"coordinates":[14.821658,51.290825],"type":"Point"}
}