{
  "type": "Feature",
  "properties": {
    "iso:country":"DE",
    "sg:address":"An Der Fliehburg 1",
    "sg:city":"Iserlohn",
    "sg:phone":"+49 4923/743367",
    "sg:postcode":"58642",
    "sg:province":"Nordrhein-Westfalen",
    "wof:name":"B\u00d6rsting Gmbh & Co Kg",
    "wof:placetype":"venue"
},
  "geometry": {"coordinates":[7.636229,51.36964],"type":"Point"}
}