{
  "type": "Feature",
  "properties": {
    "iso:country":"DE",
    "sg:address":"St.-Stephan-Str. 18",
    "sg:city":"Zeltingen-Rachtig",
    "sg:phone":"+49 6532/2408",
    "sg:postcode":"54492",
    "sg:province":"Rheinland-Pfalz",
    "wof:name":"F. Ehses-geller Erben Weinanbau",
    "wof:placetype":"venue"
},
  "geometry": {"coordinates":[7.0209159851,49.9525337219],"type":"Point"}
}