{
  "type": "Feature",
  "properties": {
    "iso:country":"DE",
    "sg:address":"Wassersleben 20",
    "sg:city":"Harrislee",
    "sg:phone":"+49 461/7935",
    "sg:postcode":"24955",
    "sg:province":"Schleswig-Holstein",
    "wof:name":"Gisela Und Bodo Daetz-stiftung Kupferm\u00fchle",
    "wof:placetype":"venue"
},
  "geometry": {"coordinates":[9.4159002304,54.8301887512],"type":"Point"}
}