{
  "type": "Feature",
  "properties": {
    "iso:country":"DE",
    "sg:address":"Zum Fuchsloch 6",
    "sg:city":"Heiligenhaus",
    "sg:phone":"+49 2054/7878",
    "sg:postcode":"42579",
    "sg:province":"Nordrhein-Westfalen",
    "wof:name":"Hans Geerlings Verm\u00f6gensverwaltungs Gmbh",
    "wof:placetype":"venue"
},
  "geometry": {"coordinates":[6.9412732124,51.347782135],"type":"Point"}
}