{
  "type": "Feature",
  "properties": {
    "iso:country":"DE",
    "sg:address":"Bergschlagweg 36",
    "sg:city":"H\u00fcnxe",
    "sg:phone":"+49 2064/32554",
    "sg:postcode":"46569",
    "sg:province":"Nordrhein-Westfalen",
    "wof:name":"G\u00fcnter Vo\u00dfkamp Rechtsanwalt",
    "wof:placetype":"venue"
},
  "geometry": {"coordinates":[6.7650709152,51.6026535034],"type":"Point"}
}