{
  "type": "Feature",
  "properties": {
    "iso:country":"DE",
    "sg:address":"Ortsstr. 12",
    "sg:city":"Oberstenfeld",
    "sg:phone":"+49 7194/766",
    "sg:postcode":"71720",
    "sg:province":"Baden-W\u00fcrttemberg",
    "wof:name":"Paul Wolf",
    "wof:placetype":"venue"
},
  "geometry": {"coordinates":[9.4023542404,49.0502738953],"type":"Point"}
}