{
  "type": "Feature",
  "properties": {
    "iso:country":"DE",
    "sg:address":"Uhlandstr. 34",
    "sg:city":"St. Wendel",
    "sg:postcode":"66606",
    "sg:province":"Saarland",
    "wof:name":"Cancemi Gmbh",
    "wof:placetype":"venue"
},
  "geometry": {"coordinates":[7.1707849503,49.4670066833],"type":"Point"}
}