{
  "type": "Feature",
  "properties": {
    "iso:country":"DE",
    "sg:address":"Heideweg 40",
    "sg:city":"G\u00fcstrow",
    "sg:phone":"+49 3843/69410",
    "sg:postcode":"18273",
    "sg:province":"Mecklenburg-Vorpommern",
    "wof:name":"Toom-baumarkt",
    "wof:placetype":"venue"
},
  "geometry": {"coordinates":[12.1509199142,53.8015556335],"type":"Point"}
}