{
  "type": "Feature",
  "properties": {
    "iso:country":"DE",
    "sg:address":"Zimmerstr.17",
    "sg:city":"Dauchingen",
    "sg:postcode":"78083",
    "sg:province":"Baden-W\u00fcrttemberg",
    "wof:name":"Deutsch-rum\u00e4niesche Partner Vermittlung",
    "wof:placetype":"venue"
},
  "geometry": {"coordinates":[8.54681,48.088341],"type":"Point"}
}