{
  "type": "Feature",
  "properties": {
    "iso:country":"DE",
    "sg:address":"Stembergstr. 37",
    "sg:city":"Arnsberg",
    "sg:phone":"+49 2932/54522",
    "sg:postcode":"59755",
    "sg:province":"Nordrhein-Westfalen",
    "wof:name":"Mhm Massivh\u00e4user R\u00fcdiger Michel",
    "wof:placetype":"venue"
},
  "geometry": {"coordinates":[7.968393,51.444839],"type":"Point"}
}