{
  "type": "Feature",
  "properties": {
    "iso:country":"DE",
    "sg:address":"Sonnenberg 8",
    "sg:city":"Ettenheim",
    "sg:phone":"+49 7822/9675",
    "sg:postcode":"77955",
    "sg:province":"Baden-W\u00fcrttemberg",
    "wof:name":"C. Schaudel",
    "wof:placetype":"venue"
},
  "geometry": {"coordinates":[7.8240880966,48.2562408447],"type":"Point"}
}