{
  "type": "Feature",
  "properties": {
    "iso:country":"DE",
    "sg:address":"Nienkamp 3",
    "sg:city":"Gronau",
    "sg:phone":"+49 2565/1281",
    "sg:postcode":"48599",
    "sg:province":"Nordrhein-Westfalen",
    "wof:name":"K. H. K\u00f6sters",
    "wof:placetype":"venue"
},
  "geometry": {"coordinates":[7.0533781052,52.1739578247],"type":"Point"}
}