{
  "type": "Feature",
  "properties": {
    "iso:country":"DE",
    "sg:address":"Haberkofen 9",
    "sg:city":"Stra\u00dfkirchen",
    "sg:phone":"+49 9424/790",
    "sg:postcode":"94342",
    "sg:province":"Bayern",
    "wof:name":"Rudolf Finkl",
    "wof:placetype":"venue"
},
  "geometry": {"coordinates":[12.699184,48.818855],"type":"Point"}
}