{
  "type": "Feature",
  "properties": {
    "iso:country":"DE",
    "sg:address":"Steinweg 48",
    "sg:city":"Straubing",
    "sg:phone":"+49 9421/2680",
    "sg:postcode":"94315",
    "sg:province":"Bayern",
    "wof:name":"D & W Glashandel Gmbh",
    "wof:placetype":"venue"
},
  "geometry": {"coordinates":[12.582964,48.871525],"type":"Point"}
}