{
  "type": "Feature",
  "properties": {
    "iso:country":"DE",
    "sg:address":"Berliner Platz 1",
    "sg:city":"Bonn",
    "sg:phone":"+49 228/657619",
    "sg:postcode":"53111",
    "sg:province":"Nordrhein-Westfalen",
    "wof:name":"Peter Riemann Architekt",
    "wof:placetype":"venue"
},
  "geometry": {"coordinates":[7.096448,50.736752],"type":"Point"}
}