{
  "type": "Feature",
  "properties": {
    "iso:country":"DE",
    "sg:address":"Jutastr. 24",
    "sg:city":"M\u00fcnchen",
    "sg:phone":"+49 89/181538",
    "sg:postcode":"80636",
    "sg:province":"Bayern",
    "wof:name":"Lubos Josifko Gmbh",
    "wof:placetype":"venue"
},
  "geometry": {"coordinates":[11.538631,48.153931],"type":"Point"}
}