{
  "type": "Feature",
  "properties": {
    "iso:country":"DE",
    "sg:address":"Bachstr. 41",
    "sg:city":"Winningen",
    "sg:phone":"+49 2606/1745",
    "sg:postcode":"56333",
    "sg:province":"Rheinland-Pfalz",
    "wof:name":"J. Barth",
    "wof:placetype":"venue"
},
  "geometry": {"coordinates":[7.517947,50.314266],"type":"Point"}
}