{
  "type": "Feature",
  "properties": {
    "iso:country":"DE",
    "sg:address":"Greizer Str. 55",
    "sg:city":"Hof",
    "sg:postcode":"95028",
    "sg:province":"Bayern",
    "wof:name":"Transfer E. K.",
    "wof:placetype":"venue"
},
  "geometry": {"coordinates":[11.9146051407,50.3361587524],"type":"Point"}
}