{
  "type": "Feature",
  "properties": {
    "iso:country":"DE",
    "sg:address":"Marktstr. 2",
    "sg:city":"Hauzenberg",
    "sg:phone":"+49 8586/91600",
    "sg:postcode":"94051",
    "sg:province":"Bayern",
    "wof:name":"Helmuth Lohschmidt",
    "wof:placetype":"venue"
},
  "geometry": {"coordinates":[13.6244287491,48.650844574],"type":"Point"}
}