{
  "type": "Feature",
  "properties": {
    "iso:country":"DE",
    "sg:address":"Decizer Str. 16",
    "sg:city":"Betzdorf",
    "sg:postcode":"57518",
    "sg:province":"Rheinland-Pfalz",
    "wof:name":"Spd Kreisverband Alten- Kirchen",
    "wof:placetype":"venue"
},
  "geometry": {"coordinates":[7.8733048439,50.7892456055],"type":"Point"}
}