{
  "type": "Feature",
  "properties": {
    "iso:country":"DE",
    "sg:address":"Zwingerstr. 14",
    "sg:city":"Kamenz",
    "sg:phone":"+49 35783/04533",
    "sg:postcode":"01917",
    "sg:province":"Sachsen",
    "wof:name":"Edelwei\u00df",
    "wof:placetype":"venue"
},
  "geometry": {"coordinates":[14.093875,51.270111],"type":"Point"}
}