{
  "type": "Feature",
  "properties": {
    "iso:country":"DE",
    "sg:address":"Gmelinstr. 21",
    "sg:city":"Wyk",
    "sg:phone":"+49 4681/3771",
    "sg:postcode":"25938",
    "sg:province":"Schleswig-Holstein",
    "wof:name":"Detco Verwaltungs Gmbh",
    "wof:placetype":"venue"
},
  "geometry": {"coordinates":[8.550693,54.681801],"type":"Point"}
}