{
  "type": "Feature",
  "properties": {
    "iso:country":"DE",
    "sg:address":"Unseburger Str. 30",
    "sg:city":"Borne",
    "sg:phone":"+49 39263/30844",
    "sg:postcode":"39435",
    "sg:province":"Sachsen-Anhalt",
    "wof:name":"S. Culmsee",
    "wof:placetype":"venue"
},
  "geometry": {"coordinates":[11.5530233383,51.9473457336],"type":"Point"}
}