{
  "type": "Feature",
  "properties": {
    "iso:country":"DE",
    "sg:address":"Kreuzstr. 15",
    "sg:city":"Gladenbach",
    "sg:phone":"+49 6462/1494",
    "sg:postcode":"35075",
    "sg:province":"Hessen",
    "wof:name":"H. Wiessner",
    "wof:placetype":"venue"
},
  "geometry": {"coordinates":[8.583356,50.770794],"type":"Point"}
}