{
  "type": "Feature",
  "properties": {
    "iso:country":"DE",
    "sg:address":"Wetzkeil 4A",
    "sg:city":"Wald-Michelbach",
    "sg:phone":"+49 6207/82847",
    "sg:postcode":"69483",
    "sg:province":"Hessen",
    "wof:name":"Mts-technik In Design Inh. G. Sattler",
    "wof:placetype":"venue"
},
  "geometry": {"coordinates":[8.828184,49.569309],"type":"Point"}
}