{
  "type": "Feature",
  "properties": {
    "iso:country":"DE",
    "sg:address":"Kransburger Str. 23",
    "sg:city":"Bremerhaven",
    "sg:phone":"+49 471/82165",
    "sg:postcode":"27578",
    "sg:province":"Bremen",
    "wof:name":"Joachim-hans Kindermann Ingenieur",
    "wof:placetype":"venue"
},
  "geometry": {"coordinates":[8.5938596725,53.5895500183],"type":"Point"}
}