{
  "type": "Feature",
  "properties": {
    "iso:country":"DE",
    "sg:address":"Oelgasse 8",
    "sg:city":"Heidelberg",
    "sg:phone":"+49 6221/372293",
    "sg:postcode":"69126",
    "sg:province":"Baden-W\u00fcrttemberg",
    "wof:name":"Herbert Sauter",
    "wof:placetype":"venue"
},
  "geometry": {"coordinates":[8.693933,49.378288],"type":"Point"}
}