{
  "type": "Feature",
  "properties": {
    "iso:country":"DE",
    "sg:address":"Hauptstr. 143",
    "sg:city":"Lindenfels",
    "sg:phone":"+49 6255/952273",
    "sg:postcode":"64678",
    "sg:province":"Hessen",
    "wof:name":"Thomas Knapp Steuerberater",
    "wof:placetype":"venue"
},
  "geometry": {"coordinates":[8.7948703766,49.6992111206],"type":"Point"}
}