{
  "type": "Feature",
  "properties": {
    "iso:country":"DE",
    "sg:address":"Hallerstr. 26",
    "sg:city":"Hamburg",
    "sg:postcode":"20146",
    "sg:province":"Hamburg",
    "wof:name":"Euram Trading Gmbh",
    "wof:placetype":"venue"
},
  "geometry": {"coordinates":[9.9808607101,53.5724487305],"type":"Point"}
}