{
  "type": "Feature",
  "properties": {
    "iso:country":"DE",
    "sg:address":"M\u00fchlenstr. 8 a",
    "sg:city":"Berlin",
    "sg:phone":"+49 30/8157070",
    "sg:postcode":"14167",
    "sg:province":"Berlin",
    "wof:name":"Gnauck & Hermenau Druckereibetrieb",
    "wof:placetype":"venue"
},
  "geometry": {"coordinates":[13.261887,52.429985],"type":"Point"}
}