{
  "type": "Feature",
  "properties": {
    "iso:country":"DE",
    "sg:address":"Auf der Jenseite 8",
    "sg:city":"Lennestadt",
    "sg:phone":"+49 2723/8373",
    "sg:postcode":"57368",
    "sg:province":"Nordrhein-Westfalen",
    "wof:name":"Elke Rameil",
    "wof:placetype":"venue"
},
  "geometry": {"coordinates":[8.166185379,51.1162528992],"type":"Point"}
}