{
  "type": "Feature",
  "properties": {
    "iso:country":"DE",
    "sg:address":"S\u00fcdstr. 30",
    "sg:city":"Zaberfeld",
    "sg:phone":"+49 7046/880555",
    "sg:postcode":"74374",
    "sg:province":"Baden-W\u00fcrttemberg",
    "wof:name":"G. Leible",
    "wof:placetype":"venue"
},
  "geometry": {"coordinates":[8.8968276978,49.0730133057],"type":"Point"}
}