{
  "type": "Feature",
  "properties": {
    "iso:country":"DE",
    "sg:address":"Pickertstr. 1",
    "sg:city":"F\u00fcrth",
    "sg:phone":"+49 911/706900",
    "sg:postcode":"90762",
    "sg:province":"Bayern",
    "wof:name":"Edm. Sp\u00e4th",
    "wof:placetype":"venue"
},
  "geometry": {"coordinates":[10.999772,49.468655],"type":"Point"}
}