{
  "type": "Feature",
  "properties": {
    "iso:country":"DE",
    "sg:address":"Herrenstr. 10",
    "sg:city":"Freinsheim",
    "sg:phone":"+49 6353/2845",
    "sg:postcode":"67251",
    "sg:province":"Rheinland-Pfalz",
    "wof:name":"Hartmut Frien",
    "wof:placetype":"venue"
},
  "geometry": {"coordinates":[8.2140073776,49.5075416565],"type":"Point"}
}