{
  "type": "Feature",
  "properties": {
    "iso:country":"DE",
    "sg:address":"Haffnerstr. 7",
    "sg:city":"Stuttgart",
    "sg:phone":"+49 711/854400",
    "sg:postcode":"70469",
    "sg:province":"Baden-W\u00fcrttemberg",
    "wof:name":"Inter Trade Gmbh",
    "wof:placetype":"venue"
},
  "geometry": {"coordinates":[9.1586732864,48.8078231812],"type":"Point"}
}