{
  "type": "Feature",
  "properties": {
    "iso:country":"DE",
    "sg:address":"Kuhstr. 16",
    "sg:city":"T\u00f6nisvorst",
    "sg:phone":"+49 2156/97860",
    "sg:postcode":"47918",
    "sg:province":"Nordrhein-Westfalen",
    "wof:name":"M. Hollenbenders G. Schlubat J. Harder W. Hammerschmidt",
    "wof:placetype":"venue"
},
  "geometry": {"coordinates":[6.4272251129,51.3038711548],"type":"Point"}
}