{
  "type": "Feature",
  "properties": {
    "iso:country":"DE",
    "sg:address":"Maybachstr. 21",
    "sg:city":"G\u00f6ppingen",
    "sg:phone":"+49 7161/73508",
    "sg:postcode":"73037",
    "sg:province":"Baden-W\u00fcrttemberg",
    "wof:name":"Bauer Autolackierbetrieb",
    "wof:placetype":"venue"
},
  "geometry": {"coordinates":[9.6688661575,48.6975975037],"type":"Point"}
}