{
  "type": "Feature",
  "properties": {
    "iso:country":"DE",
    "sg:address":"Karlstr. 32",
    "sg:city":"Crailsheim",
    "sg:phone":"+49 7951/6314",
    "sg:postcode":"74564",
    "sg:province":"Baden-W\u00fcrttemberg",
    "wof:name":"Wilhelm Hagemeyer",
    "wof:placetype":"venue"
},
  "geometry": {"coordinates":[10.0743494034,49.1373825073],"type":"Point"}
}