{
  "type": "Feature",
  "properties": {
    "iso:country":"DE",
    "sg:address":"N\u00fcrnberger Str. 60",
    "sg:city":"Bebra",
    "sg:phone":"+49 6622/92540",
    "sg:postcode":"36179",
    "sg:province":"Hessen",
    "wof:name":"Elch-apotheke",
    "wof:placetype":"venue"
},
  "geometry": {"coordinates":[9.794343,50.970985],"type":"Point"}
}