{
  "type": "Feature",
  "properties": {
    "iso:country":"DE",
    "sg:address":"Wallstr. 23",
    "sg:city":"Sch\u00f6ningen",
    "sg:phone":"+49 5352/2302",
    "sg:postcode":"38364",
    "sg:province":"Niedersachsen",
    "wof:name":"Gerhard Lutz",
    "wof:placetype":"venue"
},
  "geometry": {"coordinates":[10.9673299789,52.1378173828],"type":"Point"}
}