{
  "type": "Feature",
  "properties": {
    "iso:country":"DE",
    "sg:address":"Gr\u00fcner Rasen 10",
    "sg:city":"Buseck",
    "sg:phone":"+49 6408/2331",
    "sg:postcode":"35418",
    "sg:province":"Hessen",
    "wof:name":"Germania",
    "wof:placetype":"venue"
},
  "geometry": {"coordinates":[8.7573108673,50.6200027466],"type":"Point"}
}