{
  "type": "Feature",
  "properties": {
    "iso:country":"DE",
    "sg:address":"Obere Dorfstr. 1",
    "sg:city":"Brand-Erbisdorf",
    "sg:phone":"+49 37322/2157",
    "sg:postcode":"09618",
    "sg:province":"Sachsen",
    "wof:name":"Steffen Helbig",
    "wof:placetype":"venue"
},
  "geometry": {"coordinates":[13.3206377029,50.8596954346],"type":"Point"}
}