{
  "type": "Feature",
  "properties": {
    "iso:country":"DE",
    "sg:address":"Weidenhof",
    "sg:city":"Korschenbroich",
    "sg:phone":"+49 2182/5359",
    "sg:postcode":"41352",
    "sg:province":"Nordrhein-Westfalen",
    "wof:name":"Johannes Erkes",
    "wof:placetype":"venue"
},
  "geometry": {"coordinates":[6.592282,51.172325],"type":"Point"}
}