{
  "type": "Feature",
  "properties": {
    "iso:country":"DE",
    "sg:address":"Buch",
    "sg:city":"Buch",
    "sg:phone":"+49 9867/213",
    "sg:postcode":"91592",
    "sg:province":"Bayern",
    "wof:name":"Raiffeisenbank Rothenburg Ob Der T.",
    "wof:placetype":"venue"
},
  "geometry": {"coordinates":[10.33402,49.329922],"type":"Point"}
}