{
  "type": "Feature",
  "properties": {
    "iso:country":"DE",
    "sg:address":"An der Kegelbahn 104",
    "sg:city":"Gro\u00df Br\u00fctz",
    "sg:postcode":"19071",
    "sg:province":"Mecklenburg-Vorpommern",
    "wof:name":"Gfbr Ges. F\u00fcr Bauabfall Und Recycling Mbh",
    "wof:placetype":"venue"
},
  "geometry": {"coordinates":[11.2536497116,53.6498908997],"type":"Point"}
}