{
  "type": "Feature",
  "properties": {
    "iso:country":"DE",
    "sg:address":"Schlachthofstr. 4-6",
    "sg:city":"Nienburg",
    "sg:phone":"+49 4950/215811",
    "sg:postcode":"31582",
    "sg:province":"Niedersachsen",
    "wof:name":"Peter Peiser Electroanlagen Gmbh",
    "wof:placetype":"venue"
},
  "geometry": {"coordinates":[9.209151,52.648296],"type":"Point"}
}