{
  "type": "Feature",
  "properties": {
    "iso:country":"DE",
    "sg:address":"Erlenhof",
    "sg:city":"Weinbach",
    "sg:phone":"+49 6471/4806",
    "sg:postcode":"35796",
    "sg:province":"Hessen",
    "wof:name":"Heinz Kurz",
    "wof:placetype":"venue"
},
  "geometry": {"coordinates":[8.314991,50.464844],"type":"Point"}
}