{
  "type": "Feature",
  "properties": {
    "iso:country":"DE",
    "sg:address":"Bahnhofstr. 11",
    "sg:city":"Westerkappeln",
    "sg:phone":"+49 5404/2209",
    "sg:postcode":"49492",
    "sg:province":"Nordrhein-Westfalen",
    "wof:name":"Helmut Becker",
    "wof:placetype":"venue"
},
  "geometry": {"coordinates":[7.8774609566,52.3155975342],"type":"Point"}
}