{
  "type": "Feature",
  "properties": {
    "iso:country":"DE",
    "sg:address":"Albstr. 14",
    "sg:city":"Heroldstatt",
    "sg:phone":"+49 7389/1346",
    "sg:postcode":"72535",
    "sg:province":"Baden-W\u00fcrttemberg",
    "wof:name":"Maria Dorn",
    "wof:placetype":"venue"
},
  "geometry": {"coordinates":[9.672515,48.448917],"type":"Point"}
}