{
  "type": "Feature",
  "properties": {
    "iso:country":"DE",
    "sg:address":"Synagogenstr. 6",
    "sg:city":"Nettetal",
    "sg:phone":"+49 2157/897370",
    "sg:postcode":"41334",
    "sg:province":"Nordrhein-Westfalen",
    "wof:name":"Baugesellschaft Nettetal Gemeinn\u00fctziges Wohnungs-",
    "wof:placetype":"venue"
},
  "geometry": {"coordinates":[6.1989459991,51.3207092285],"type":"Point"}
}