{
  "type": "Feature",
  "properties": {
    "iso:country":"DE",
    "sg:address":"Tullaweg 1d",
    "sg:city":"Berlin",
    "sg:phone":"+49 30/8215051",
    "sg:postcode":"12277",
    "sg:province":"Berlin",
    "wof:name":"Gemerskiverwaltungs- Und B\u00fcroservice Gesch\u00e4ftsf\u00fchrungs",
    "wof:placetype":"venue"
},
  "geometry": {"coordinates":[13.3722219467,52.4146842957],"type":"Point"}
}