{
  "type": "Feature",
  "properties": {
    "iso:country":"DE",
    "sg:address":"Steinstr. 4",
    "sg:city":"Mahlow",
    "sg:phone":"+49 3379/373231",
    "sg:postcode":"15831",
    "sg:province":"Brandenburg",
    "wof:name":"I. M\u00fcller Immobilienmakler",
    "wof:placetype":"venue"
},
  "geometry": {"coordinates":[13.4168872833,52.3607330322],"type":"Point"}
}