{
  "type": "Feature",
  "properties": {
    "iso:country":"DE",
    "sg:address":"Werastr. 85",
    "sg:city":"Stuttgart",
    "sg:phone":"+49 711/261704",
    "sg:postcode":"70190",
    "sg:province":"Baden-W\u00fcrttemberg",
    "wof:name":"S. Koenigs",
    "wof:placetype":"venue"
},
  "geometry": {"coordinates":[9.1932163239,48.7850532532],"type":"Point"}
}