{
  "type": "Feature",
  "properties": {
    "iso:country":"DE",
    "sg:address":"Frau-Clara-Str. 18",
    "sg:city":"Eckernf\u00f6rde",
    "sg:phone":"+49 4351/2670",
    "sg:postcode":"24340",
    "sg:province":"Schleswig-Holstein",
    "wof:name":"Irene Ulrich Rechtsanw\u00e4ltin Und Notarin",
    "wof:placetype":"venue"
},
  "geometry": {"coordinates":[9.8362998962,54.4738082886],"type":"Point"}
}