{
  "type": "Feature",
  "properties": {
    "iso:country":"DE",
    "sg:address":"Friedhofstr. 2a",
    "sg:city":"St. Leon-Rot",
    "sg:postcode":"68789",
    "sg:province":"Baden-W\u00fcrttemberg",
    "wof:name":"Old Tornados Club Walldorf",
    "wof:placetype":"venue"
},
  "geometry": {"coordinates":[8.6307020187,49.2650871277],"type":"Point"}
}