{
  "type": "Feature",
  "properties": {
    "iso:country":"DE",
    "sg:address":"Striepenweg 41",
    "sg:city":"Hamburg",
    "sg:phone":"+49 40/7016668",
    "sg:postcode":"21147",
    "sg:province":"Hamburg",
    "wof:name":"Marga Ritscher Massagepraxis",
    "wof:placetype":"venue"
},
  "geometry": {"coordinates":[9.876192,53.473682],"type":"Point"}
}