{
  "type": "Feature",
  "properties": {
    "iso:country":"DE",
    "sg:address":"Sommerberg 9",
    "sg:city":"Reutlingen",
    "sg:phone":"+49 7121/66140",
    "sg:postcode":"72768",
    "sg:province":"Baden-W\u00fcrttemberg",
    "wof:name":"Schwarzer",
    "wof:placetype":"venue"
},
  "geometry": {"coordinates":[9.1987266541,48.5338516235],"type":"Point"}
}