{
  "type": "Feature",
  "properties": {
    "iso:country":"DE",
    "sg:address":"Niederhabbach",
    "sg:city":"Lindlar",
    "sg:phone":"+49 2267/888188",
    "sg:postcode":"51789",
    "sg:province":"Nordrhein-Westfalen",
    "wof:name":"Tischlerei Michael Wurth",
    "wof:placetype":"venue"
},
  "geometry": {"coordinates":[7.4235582352,51.0554161072],"type":"Point"}
}