{
  "type": "Feature",
  "properties": {
    "iso:country":"DE",
    "sg:address":"Gotenstr. 20",
    "sg:city":"Leer",
    "sg:phone":"+49 491/72896",
    "sg:postcode":"26789",
    "sg:province":"Niedersachsen",
    "wof:name":"Dr. Med. Harm Voges",
    "wof:placetype":"venue"
},
  "geometry": {"coordinates":[7.4987568855,53.2380752563],"type":"Point"}
}