{
  "type": "Feature",
  "properties": {
    "iso:country":"DE",
    "sg:address":"Obere Drimbornstr. 46",
    "sg:city":"Aachen",
    "sg:phone":"+49 241/59252",
    "sg:postcode":"52066",
    "sg:province":"Nordrhein-Westfalen",
    "wof:name":"Drimborner W\u00e4ldchen",
    "wof:placetype":"venue"
},
  "geometry": {"coordinates":[6.1181721687,50.7634277344],"type":"Point"}
}