{
  "type": "Feature",
  "properties": {
    "iso:country":"DE",
    "sg:address":"St.-Georg-Str. 7",
    "sg:city":"Hattingen",
    "sg:phone":"+49 2324/51017",
    "sg:postcode":"45525",
    "sg:province":"Nordrhein-Westfalen",
    "wof:name":"Der Weintreff",
    "wof:placetype":"venue"
},
  "geometry": {"coordinates":[7.1842780113,51.3974456787],"type":"Point"}
}