{
  "type": "Feature",
  "properties": {
    "iso:country":"DE",
    "sg:address":"Alte Reichsstr. 14",
    "sg:city":"Lichtenfels",
    "sg:phone":"+49 9571/3134",
    "sg:postcode":"96215",
    "sg:province":"Bayern",
    "wof:name":"Schreinerei Paulus Gmbh",
    "wof:placetype":"venue"
},
  "geometry": {"coordinates":[11.080942,50.151321],"type":"Point"}
}