{
  "type": "Feature",
  "properties": {
    "iso:country":"DE",
    "sg:address":"Ostenfelder Str. 33",
    "sg:city":"Ennigerloh",
    "sg:phone":"+49 2524/7187",
    "sg:postcode":"59320",
    "sg:province":"Nordrhein-Westfalen",
    "wof:name":"Robert Schuler",
    "wof:placetype":"venue"
},
  "geometry": {"coordinates":[8.032935,51.840675],"type":"Point"}
}