{
  "type": "Feature",
  "properties": {
    "iso:country":"DE",
    "sg:address":"Cosch\u00fctzer Str. 89",
    "sg:city":"Freital",
    "sg:phone":"+49 351/6491108",
    "sg:postcode":"01705",
    "sg:province":"Sachsen",
    "wof:name":"Heiner Thiele",
    "wof:placetype":"venue"
},
  "geometry": {"coordinates":[13.679596,51.014603],"type":"Point"}
}