{
  "type": "Feature",
  "properties": {
    "iso:country":"DE",
    "sg:address":"Deller Str. 38",
    "sg:city":"Solingen",
    "sg:phone":"+49 212/312922",
    "sg:postcode":"42719",
    "sg:province":"Nordrhein-Westfalen",
    "wof:name":"De Fazio Gmbh",
    "wof:placetype":"venue"
},
  "geometry": {"coordinates":[7.054436,51.191601],"type":"Point"}
}