{
  "type": "Feature",
  "properties": {
    "iso:country":"DE",
    "sg:address":"Saalfelder Str. 3",
    "sg:city":"Dresden",
    "sg:phone":"+49 351/8908631",
    "sg:postcode":"01109",
    "sg:province":"Sachsen",
    "wof:name":"Holger Will",
    "wof:placetype":"venue"
},
  "geometry": {"coordinates":[13.7680397034,51.1098480225],"type":"Point"}
}