{
  "type": "Feature",
  "properties": {
    "iso:country":"DE",
    "sg:address":"In den Amtmannswiesen 5",
    "sg:city":"Eppstein",
    "sg:phone":"+49 6198/7830",
    "sg:postcode":"65817",
    "sg:province":"Hessen",
    "wof:name":"Paulus Engelhard & Co. Gmbh",
    "wof:placetype":"venue"
},
  "geometry": {"coordinates":[8.40074,50.137539],"type":"Point"}
}