{
  "type": "Feature",
  "properties": {
    "iso:country":"DE",
    "sg:address":"M\u00fchlenkamp 18",
    "sg:city":"Hamburg",
    "sg:phone":"+49 40/273439",
    "sg:postcode":"22303",
    "sg:province":"Hamburg",
    "wof:name":"Cafe Am M\u00fchlenkamp",
    "wof:placetype":"venue"
},
  "geometry": {"coordinates":[10.012252,53.580921],"type":"Point"}
}