{
  "type": "Feature",
  "properties": {
    "iso:country":"DE",
    "sg:address":"Gungstr. 32",
    "sg:city":"Bottrop",
    "sg:phone":"+49 2041/45549",
    "sg:postcode":"46240",
    "sg:province":"Nordrhein-Westfalen",
    "wof:name":"C. Suchan",
    "wof:placetype":"venue"
},
  "geometry": {"coordinates":[6.9770421982,51.5302314758],"type":"Point"}
}