{
  "type": "Feature",
  "properties": {
    "iso:country":"DE",
    "sg:address":"Gro\u00dfe Freiheit 70",
    "sg:city":"Hamburg",
    "sg:postcode":"22767",
    "sg:province":"Hamburg",
    "wof:name":"Vertrieb Trockener Weine Sch\u00f6nberger & Jotter Ohg",
    "wof:placetype":"venue"
},
  "geometry": {"coordinates":[9.9583406448,53.5521583557],"type":"Point"}
}