{
  "type": "Feature",
  "properties": {
    "iso:country":"DE",
    "sg:address":"Heinrich-Hertz-Str. 12",
    "sg:city":"Hermsdorf",
    "sg:postcode":"07629",
    "sg:province":"Th\u00fcringen",
    "wof:name":"Gt-industrie-service Gmbh",
    "wof:placetype":"venue"
},
  "geometry": {"coordinates":[11.849214,50.895706],"type":"Point"}
}