{
  "type": "Feature",
  "properties": {
    "iso:country":"DE",
    "sg:address":"Uerdinger Str. 10-12",
    "sg:city":"Krefeld",
    "sg:postcode":"47799",
    "sg:province":"Nordrhein-Westfalen",
    "wof:name":"Goltherm Gas- Und Oelfeuerungen Gmbh",
    "wof:placetype":"venue"
},
  "geometry": {"coordinates":[6.571928978,51.3352050781],"type":"Point"}
}