{
  "type": "Feature",
  "properties": {
    "iso:country":"DE",
    "sg:address":"Altendorfer Grenzweg 3",
    "sg:city":"Drochtersen",
    "sg:phone":"+49 4775/663",
    "sg:postcode":"21706",
    "sg:province":"Niedersachsen",
    "wof:name":"Peter Schliecker",
    "wof:placetype":"venue"
},
  "geometry": {"coordinates":[9.2621259689,53.7108650208],"type":"Point"}
}