{
  "type": "Feature",
  "properties": {
    "iso:country":"DE",
    "sg:address":"Lynarstr. 25",
    "sg:city":"Berlin",
    "sg:postcode":"14193",
    "sg:province":"Berlin",
    "wof:name":"Berkom Verm\u00f6gens- Verwaltungsgesellschaft Mbh",
    "wof:placetype":"venue"
},
  "geometry": {"coordinates":[13.289104,52.488907],"type":"Point"}
}