{
  "type": "Feature",
  "properties": {
    "iso:country":"DE",
    "sg:address":"Alte Str. 12",
    "sg:city":"Mainleus",
    "sg:phone":"+49 9229/1031",
    "sg:postcode":"95336",
    "sg:province":"Bayern",
    "wof:name":"Rudolf Pondor",
    "wof:placetype":"venue"
},
  "geometry": {"coordinates":[11.375625,50.099903],"type":"Point"}
}