{
  "type": "Feature",
  "properties": {
    "iso:country":"DE",
    "sg:address":"Hauptstr. 22",
    "sg:city":"Kirchtimke",
    "sg:phone":"+49 4289/311",
    "sg:postcode":"27412",
    "sg:province":"Niedersachsen",
    "wof:name":"Blankens",
    "wof:placetype":"venue"
},
  "geometry": {"coordinates":[9.1524066925,53.2517623901],"type":"Point"}
}