{
  "type": "Feature",
  "properties": {
    "iso:country":"DE",
    "sg:address":"C\u00e4ciliastr. 25",
    "sg:city":"Karlsruhe",
    "sg:phone":"+49 721/817778",
    "sg:postcode":"76135",
    "sg:province":"Baden-W\u00fcrttemberg",
    "wof:name":"Amelia Georgescu Architektin",
    "wof:placetype":"venue"
},
  "geometry": {"coordinates":[8.388513,48.992081],"type":"Point"}
}