{
  "type": "Feature",
  "properties": {
    "iso:country":"DE",
    "sg:address":"Leuchte 1 A",
    "sg:city":"Frankfurt",
    "sg:phone":"+49 6109/31188",
    "sg:postcode":"60388",
    "sg:province":"Hessen",
    "wof:name":"Lotex Heimtextilien- Studio Gmbh & Co. Kg",
    "wof:placetype":"venue"
},
  "geometry": {"coordinates":[8.7555208206,50.1431388855],"type":"Point"}
}