{
  "type": "Feature",
  "properties": {
    "iso:country":"DE",
    "sg:address":"Uhlandstr. 131",
    "sg:city":"Berlin",
    "sg:phone":"+49 30/8737924",
    "sg:postcode":"10717",
    "sg:province":"Berlin",
    "wof:name":"Hulahup",
    "wof:placetype":"venue"
},
  "geometry": {"coordinates":[13.3235712051,52.4922218323],"type":"Point"}
}