{
  "type": "Feature",
  "properties": {
    "iso:country":"DE",
    "sg:address":"Vorwerk 10",
    "sg:city":"Stolpen",
    "sg:phone":"+49 35973/24186",
    "sg:postcode":"01833",
    "sg:province":"Sachsen",
    "wof:name":"Silke Hausding",
    "wof:placetype":"venue"
},
  "geometry": {"coordinates":[14.04016,51.03688],"type":"Point"}
}