{
  "type": "Feature",
  "properties": {
    "iso:country":"DE",
    "sg:address":"Westernstr. 1",
    "sg:city":"Paderborn",
    "sg:phone":"+49 5251/103900",
    "sg:postcode":"33098",
    "sg:province":"Nordrhein-Westfalen",
    "wof:name":"Ernst Jacoby",
    "wof:placetype":"venue"
},
  "geometry": {"coordinates":[8.751263,51.716785],"type":"Point"}
}