{
  "type": "Feature",
  "properties": {
    "iso:country":"DE",
    "sg:address":"Daimlerstr 3",
    "sg:city":"M\u00fchlheim",
    "sg:phone":"+49 6108/90910",
    "sg:postcode":"63165",
    "sg:province":"Hessen",
    "wof:name":"Caleffi Armaturen Gmbh",
    "wof:placetype":"venue"
},
  "geometry": {"coordinates":[8.8535404205,50.118850708],"type":"Point"}
}