{
  "type": "Feature",
  "properties": {
    "iso:country":"DE",
    "sg:address":"Hargartstr. 19",
    "sg:city":"Tholey",
    "sg:phone":"+49 6888/91091",
    "sg:postcode":"66636",
    "sg:province":"Saarland",
    "wof:name":"Atlantis Natursteine Gmbh",
    "wof:placetype":"venue"
},
  "geometry": {"coordinates":[6.944642,49.496441],"type":"Point"}
}