{
  "type": "Feature",
  "properties": {
    "iso:country":"DE",
    "sg:address":"Schilfrohr 8",
    "sg:city":"Lengede",
    "sg:postcode":"38268",
    "sg:province":"Niedersachsen",
    "wof:name":"Sch\u00f6bau Gmbh",
    "wof:placetype":"venue"
},
  "geometry": {"coordinates":[10.3185443878,52.2099075317],"type":"Point"}
}