{
  "type": "Feature",
  "properties": {
    "iso:country":"DE",
    "sg:address":"Frankfurter Str. 74",
    "sg:city":"Sankt Augustin",
    "sg:phone":"+49 2241/60233",
    "sg:postcode":"53757",
    "sg:province":"Nordrhein-Westfalen",
    "wof:name":"Gertrud Born",
    "wof:placetype":"venue"
},
  "geometry": {"coordinates":[7.2354822159,50.7833061218],"type":"Point"}
}