{
  "type": "Feature",
  "properties": {
    "iso:country":"DE",
    "sg:address":"Rubensstr. 8",
    "sg:city":"Homburg",
    "sg:phone":"+49 6841/71025",
    "sg:postcode":"66424",
    "sg:province":"Saarland",
    "wof:name":"Schreinerei H\u00f6chst Gmbh",
    "wof:placetype":"venue"
},
  "geometry": {"coordinates":[7.333904,49.341835],"type":"Point"}
}