{
  "type": "Feature",
  "properties": {
    "iso:country":"DE",
    "sg:address":"Am Spinnweg 2",
    "sg:city":"Gelsenkirchen",
    "sg:phone":"+49 209/37361",
    "sg:postcode":"45894",
    "sg:province":"Nordrhein-Westfalen",
    "wof:name":"Hans J. Schreiner Kg",
    "wof:placetype":"venue"
},
  "geometry": {"coordinates":[7.056551,51.581295],"type":"Point"}
}