{
  "type": "Feature",
  "properties": {
    "iso:country":"DE",
    "sg:address":"Beuerner Str. 31",
    "sg:city":"Baden-Baden",
    "sg:phone":"+49 7221/7695",
    "sg:postcode":"76534",
    "sg:province":"Baden-W\u00fcrttemberg",
    "wof:name":"Adolf Heizmann",
    "wof:placetype":"venue"
},
  "geometry": {"coordinates":[8.264979,48.742634],"type":"Point"}
}