{
  "type": "Feature",
  "properties": {
    "iso:country":"DE",
    "sg:address":"Chiemgaustr 109",
    "sg:city":"M\u00fcnchen",
    "sg:phone":"+49 89/680010",
    "sg:postcode":"81549",
    "sg:province":"Bayern",
    "wof:name":"Jahr Top Special Verlag Gmbh & Co Kg",
    "wof:placetype":"venue"
},
  "geometry": {"coordinates":[11.598781,48.107582],"type":"Point"}
}