{
  "type": "Feature",
  "properties": {
    "iso:country":"DE",
    "sg:address":"M\u00fcnchener Str. 16",
    "sg:city":"Geisenfeld",
    "sg:phone":"+49 8452/427",
    "sg:postcode":"85290",
    "sg:province":"Bayern",
    "wof:name":"Mathias Knerr",
    "wof:placetype":"venue"
},
  "geometry": {"coordinates":[11.6130151749,48.6823348999],"type":"Point"}
}