{
  "type": "Feature",
  "properties": {
    "iso:country":"DE",
    "sg:address":"Hauptstr. 43",
    "sg:city":"Ellefeld",
    "sg:phone":"+49 3745/71875",
    "sg:postcode":"08236",
    "sg:province":"Sachsen",
    "wof:name":"C. Tho\u00df",
    "wof:placetype":"venue"
},
  "geometry": {"coordinates":[12.387795,50.483261],"type":"Point"}
}