{
  "type": "Feature",
  "properties": {
    "iso:country":"DE",
    "sg:address":"Schlittweg 16a",
    "sg:city":"Obrigheim",
    "sg:postcode":"67283",
    "sg:province":"Rheinland-Pfalz",
    "wof:name":"Victoria Versicherung Ag",
    "wof:placetype":"venue"
},
  "geometry": {"coordinates":[8.2120857239,49.5963973999],"type":"Point"}
}