{
  "type": "Feature",
  "properties": {
    "iso:country":"DE",
    "sg:address":"Gr\u00fcner Weg 149",
    "sg:city":"Leverkusen",
    "sg:phone":"+49 214/8505341",
    "sg:postcode":"51377",
    "sg:province":"Nordrhein-Westfalen",
    "wof:name":"O. Horst Gefl\u00fcgel Und Feinkost Gmbh",
    "wof:placetype":"venue"
},
  "geometry": {"coordinates":[7.0492081642,51.0500640869],"type":"Point"}
}