{
  "type": "Feature",
  "properties": {
    "iso:country":"DE",
    "sg:address":"Achterstr. 57",
    "sg:city":"K\u00f6ln",
    "sg:phone":"+49 221/329644",
    "sg:postcode":"50678",
    "sg:province":"Nordrhein-Westfalen",
    "wof:name":"G. Grom",
    "wof:placetype":"venue"
},
  "geometry": {"coordinates":[6.958455,50.927116],"type":"Point"}
}