{
  "type": "Feature",
  "properties": {
    "iso:country":"DE",
    "sg:address":"Metzinger Str. 50",
    "sg:city":"Kohlberg",
    "sg:phone":"+49 4970/252038",
    "sg:postcode":"72664",
    "sg:province":"Baden-W\u00fcrttemberg",
    "wof:name":"Raiffeisenbank Kohlberg Eg",
    "wof:placetype":"venue"
},
  "geometry": {"coordinates":[9.331882,48.556927],"type":"Point"}
}