{
  "type": "Feature",
  "properties": {
    "iso:country":"DE",
    "sg:address":"Bonner Talweg 24",
    "sg:city":"Bonn",
    "sg:phone":"+49 228/219397",
    "sg:postcode":"53113",
    "sg:province":"Nordrhein-Westfalen",
    "wof:name":"H. Z\u00fcndorf",
    "wof:placetype":"venue"
},
  "geometry": {"coordinates":[7.100317,50.72694],"type":"Point"}
}