{
  "type": "Feature",
  "properties": {
    "iso:country":"DE",
    "sg:address":"Raiffeisenstr. 3",
    "sg:city":"Schwanfeld",
    "sg:phone":"+49 9384/97100",
    "sg:postcode":"97523",
    "sg:province":"Bayern",
    "wof:name":"Neuhoff Natursteinwerk Gmbh",
    "wof:placetype":"venue"
},
  "geometry": {"coordinates":[10.13347435,49.920463562],"type":"Point"}
}