{
  "type": "Feature",
  "properties": {
    "iso:country":"DE",
    "sg:address":"Ziegelh\u00fcttenstr. 36",
    "sg:city":"Oppenau",
    "sg:phone":"+49 7804/1450",
    "sg:postcode":"77728",
    "sg:province":"Baden-W\u00fcrttemberg",
    "wof:name":"Peter Weinhardt Masseur",
    "wof:placetype":"venue"
},
  "geometry": {"coordinates":[8.155007,48.477806],"type":"Point"}
}