{
  "type": "Feature",
  "properties": {
    "iso:country":"DE",
    "sg:address":"Badstr. 20-22",
    "sg:city":"Bad T\u00f6lz",
    "sg:phone":"+49 8041/5001",
    "sg:postcode":"83646",
    "sg:province":"Bayern",
    "wof:name":"Vereinigte Sparkassen, Im Landkreis Bad T\u00f6lz",
    "wof:placetype":"venue"
},
  "geometry": {"coordinates":[11.553264,47.760094],"type":"Point"}
}