{
  "type": "Feature",
  "properties": {
    "iso:country":"DE",
    "sg:address":"Robert-Bosch-Str. 9",
    "sg:city":"Odelzhausen",
    "sg:phone":"+49 8134/93050",
    "sg:postcode":"85235",
    "sg:province":"Bayern",
    "wof:name":"Johannes Kiehl Kg",
    "wof:placetype":"venue"
},
  "geometry": {"coordinates":[11.204805,48.305321],"type":"Point"}
}