{
  "type": "Feature",
  "properties": {
    "iso:country":"DE",
    "sg:address":"Hauptstr. 38",
    "sg:city":"Langeoog",
    "sg:phone":"+49 4972/6860",
    "sg:postcode":"26465",
    "sg:province":"Niedersachsen",
    "wof:name":"Hotel Upstalsboom",
    "wof:placetype":"venue"
},
  "geometry": {"coordinates":[7.4788851738,53.7471008301],"type":"Point"}
}