{
  "type": "Feature",
  "properties": {
    "iso:country":"DE",
    "sg:address":"Brook 34",
    "sg:city":"Ahaus",
    "sg:phone":"+49 2567/3417",
    "sg:postcode":"48683",
    "sg:province":"Nordrhein-Westfalen",
    "wof:name":"Gastst\u00e4tte Hubert Tenhagen",
    "wof:placetype":"venue"
},
  "geometry": {"coordinates":[6.9114718437,52.148349762],"type":"Point"}
}