{
  "type": "Feature",
  "properties": {
    "iso:country":"DE",
    "sg:address":"Am Kramberg 20",
    "sg:city":"Hann. M\u00fcnden",
    "sg:phone":"+49 5541/12046",
    "sg:postcode":"34346",
    "sg:province":"Niedersachsen",
    "wof:name":"Kathleen M\u00fcller",
    "wof:placetype":"venue"
},
  "geometry": {"coordinates":[9.681125,51.416965],"type":"Point"}
}