{
  "type": "Feature",
  "properties": {
    "iso:country":"DE",
    "sg:address":"Ueckerstr 95",
    "sg:city":"Ueckerm\u00fcnde",
    "sg:phone":"+49 39771/2910",
    "sg:postcode":"17373",
    "sg:province":"Mecklenburg-Vorpommern",
    "wof:name":"Juncker",
    "wof:placetype":"venue"
},
  "geometry": {"coordinates":[14.046394,53.736221],"type":"Point"}
}