{
  "type": "Feature",
  "properties": {
    "iso:country":"DE",
    "sg:address":"Marktstr. 46",
    "sg:city":"Wertach",
    "sg:phone":"+49 8365/706560",
    "sg:postcode":"87497",
    "sg:province":"Bayern",
    "wof:name":"Pizzeria Bibione",
    "wof:placetype":"venue"
},
  "geometry": {"coordinates":[10.4083499908,47.6022148132],"type":"Point"}
}