{
  "type": "Feature",
  "properties": {
    "iso:country":"DE",
    "sg:address":"Am Heckelchen 16",
    "sg:city":"K\u00f6nigsinter",
    "sg:phone":"+49 2244/870940",
    "sg:postcode":"53639",
    "sg:province":"Nordrhein-Westfalen",
    "wof:name":"Hydrosaurus Reptilienzucht",
    "wof:placetype":"venue"
},
  "geometry": {"coordinates":[7.2764520645,50.6919364929],"type":"Point"}
}