{
  "type": "Feature",
  "properties": {
    "iso:country":"DE",
    "sg:address":"Emscher Str. 46",
    "sg:city":"Gelsenkirchen",
    "sg:phone":"+49 4920/970020",
    "sg:postcode":"45891",
    "sg:province":"Nordrhein-Westfalen",
    "wof:name":"Nacanco Gmbh",
    "wof:placetype":"venue"
},
  "geometry": {"coordinates":[7.0835790634,51.5470466614],"type":"Point"}
}