{
  "type": "Feature",
  "properties": {
    "iso:country":"DE",
    "sg:address":"Braunstr. 19",
    "sg:city":"L\u00fcbeck",
    "sg:phone":"+49 451/73732",
    "sg:postcode":"23552",
    "sg:province":"Schleswig-Holstein",
    "wof:name":"Altstadt Bierhaus",
    "wof:placetype":"venue"
},
  "geometry": {"coordinates":[10.681892395,53.8669509888],"type":"Point"}
}