{
  "type": "Feature",
  "properties": {
    "iso:country":"DE",
    "sg:address":"Bleicherstr. 3",
    "sg:city":"Wuppertal",
    "sg:phone":"+49 202/255450",
    "sg:postcode":"42283",
    "sg:province":"Nordrhein-Westfalen",
    "wof:name":"Info-data B\u00fcroorganisations",
    "wof:placetype":"venue"
},
  "geometry": {"coordinates":[7.193168,51.269718],"type":"Point"}
}