{
  "type": "Feature",
  "properties": {
    "iso:country":"DE",
    "sg:address":"Am Industriehafen 3",
    "sg:city":"Flensburg",
    "sg:phone":"+49 461/17811",
    "sg:postcode":"24937",
    "sg:province":"Schleswig-Holstein",
    "wof:name":"Jacob S\u00f6nnichsen Gmbh & Co. Kg",
    "wof:placetype":"venue"
},
  "geometry": {"coordinates":[9.440318,54.800152],"type":"Point"}
}