{
  "type": "Feature",
  "properties": {
    "iso:country":"DE",
    "sg:address":"Eichenkamp 10",
    "sg:city":"Hamburg",
    "sg:phone":"+49 40/5240575",
    "sg:postcode":"22417",
    "sg:province":"Hamburg",
    "wof:name":"Ev. Pfarramt St. J\u00fcrgenkirche",
    "wof:placetype":"venue"
},
  "geometry": {"coordinates":[10.0161428452,53.6794013977],"type":"Point"}
}