{
  "type": "Feature",
  "properties": {
    "iso:country":"DE",
    "sg:address":"Hollerbach 20",
    "sg:city":"Aidenbach",
    "sg:postcode":"94501",
    "sg:province":"Bayern",
    "wof:name":"Bioclot Gmbh",
    "wof:placetype":"venue"
},
  "geometry": {"coordinates":[13.094825,48.552483],"type":"Point"}
}