{
  "type": "Feature",
  "properties": {
    "iso:country":"DE",
    "sg:address":"Hauptstr. 48",
    "sg:city":"Ostrhauderfehn",
    "sg:postcode":"26842",
    "sg:province":"Niedersachsen",
    "wof:name":"Kaufhaus Rolf Wreesmann Beteiligungs Gmbh",
    "wof:placetype":"venue"
},
  "geometry": {"coordinates":[7.60866,53.139103],"type":"Point"}
}