{
  "type": "Feature",
  "properties": {
    "iso:country":"DE",
    "sg:address":"Kirchstr. 7",
    "sg:city":"St Katharinen",
    "sg:phone":"+49 2645/99660",
    "sg:postcode":"53562",
    "sg:province":"Rheinland-Pfalz",
    "wof:name":"Hans-georg Zerwas",
    "wof:placetype":"venue"
},
  "geometry": {"coordinates":[7.354062,50.561474],"type":"Point"}
}