{
  "type": "Feature",
  "properties": {
    "iso:country":"DE",
    "sg:address":"Langheimer Str. 35",
    "sg:city":"Altenkunstadt",
    "sg:phone":"+49 9572/603232",
    "sg:postcode":"96264",
    "sg:province":"Bayern",
    "wof:name":"Mimmo's Pizzaservice Inh. Domenico Randazzo",
    "wof:placetype":"venue"
},
  "geometry": {"coordinates":[11.2455282211,50.1238746643],"type":"Point"}
}