{
  "type": "Feature",
  "properties": {
    "iso:country":"DE",
    "sg:address":"Wissenscher Weg 8",
    "sg:city":"Kevelaer",
    "sg:phone":"+49 2832/6257",
    "sg:postcode":"47623",
    "sg:province":"Nordrhein-Westfalen",
    "wof:name":"Josef Schlusen Ingenieur",
    "wof:placetype":"venue"
},
  "geometry": {"coordinates":[6.2364850044,51.5882225037],"type":"Point"}
}