{
  "type": "Feature",
  "properties": {
    "iso:country":"DE",
    "sg:address":"Meimsheimer Str. 39",
    "sg:city":"B\u00f6nnigheim",
    "sg:phone":"+49 7143/2068",
    "sg:postcode":"74357",
    "sg:province":"Baden-W\u00fcrttemberg",
    "wof:name":"Biedermann Kamine- Und Bau- Gmbh",
    "wof:placetype":"venue"
},
  "geometry": {"coordinates":[9.0924453735,49.0463180542],"type":"Point"}
}