{
  "type": "Feature",
  "properties": {
    "iso:country":"DE",
    "sg:address":"Lohstr. 4a",
    "sg:city":"Pforzen",
    "sg:phone":"+49 8346/1266",
    "sg:postcode":"87666",
    "sg:province":"Bayern",
    "wof:name":"B. Stuber",
    "wof:placetype":"venue"
},
  "geometry": {"coordinates":[10.6201372147,47.9346427917],"type":"Point"}
}