{
  "type": "Feature",
  "properties": {
    "iso:country":"DE",
    "sg:address":"Marienstr. 15",
    "sg:city":"Brachbach",
    "sg:phone":"+49 2745/283",
    "sg:postcode":"57555",
    "sg:province":"Rheinland-Pfalz",
    "wof:name":"Horst Utsch",
    "wof:placetype":"venue"
},
  "geometry": {"coordinates":[7.942117,50.81311],"type":"Point"}
}