{
  "type": "Feature",
  "properties": {
    "iso:country":"DE",
    "sg:address":"Eternitweg 19",
    "sg:city":"Neuburg",
    "sg:phone":"+49 8431/67950",
    "sg:postcode":"86633",
    "sg:province":"Bayern",
    "wof:name":"Johann Koch E. K.",
    "wof:placetype":"venue"
},
  "geometry": {"coordinates":[11.173602,48.723022],"type":"Point"}
}