{
  "type": "Feature",
  "properties": {
    "iso:country":"DE",
    "sg:address":"Berliner Stra\u00dfe 126A",
    "sg:city":"Schwedt",
    "sg:phone":"+49 3332/538926",
    "sg:postcode":"16303",
    "sg:province":"Brandenburg",
    "wof:name":"Www.pigorsch.com - Ein Virtuelles Gewerbegebiet",
    "wof:placetype":"venue"
},
  "geometry": {"coordinates":[14.298495,53.064865],"type":"Point"}
}