{
  "type": "Feature",
  "properties": {
    "iso:country":"DE",
    "sg:address":"Hubert-Wienen-Str.",
    "sg:city":"Aachen",
    "sg:phone":"+49 241/9974315",
    "sg:postcode":"52070",
    "sg:province":"Nordrhein-Westfalen",
    "wof:name":"Zeltbetriebe Azmani Maria Azmani",
    "wof:placetype":"venue"
},
  "geometry": {"coordinates":[6.1005129814,50.7960968018],"type":"Point"}
}