{
  "type": "Feature",
  "properties": {
    "iso:country":"DE",
    "sg:address":"Hegeberg 1",
    "sg:city":"Wettelrode",
    "sg:phone":"+49 3464/582006",
    "sg:postcode":"06528",
    "sg:province":"Sachsen-Anhalt",
    "wof:name":"Manfred Suchanek",
    "wof:placetype":"venue"
},
  "geometry": {"coordinates":[11.294839859,51.42237854],"type":"Point"}
}