{
  "type": "Feature",
  "properties": {
    "iso:country":"DE",
    "sg:address":"Waldstr. 9",
    "sg:city":"Mengerskirchen",
    "sg:phone":"+49 6476/8105",
    "sg:postcode":"35794",
    "sg:province":"Hessen",
    "wof:name":"Johann Eckert Schilder- Und Lichtreklame",
    "wof:placetype":"venue"
},
  "geometry": {"coordinates":[8.18176,50.551899],"type":"Point"}
}