{
  "type": "Feature",
  "properties": {
    "iso:country":"DE",
    "sg:address":"Griedeler Str. 32",
    "sg:city":"Butzbach",
    "sg:postcode":"35510",
    "sg:province":"Hessen",
    "wof:name":"Minder & Bl\u00e4ser Immobilien Gmbh",
    "wof:placetype":"venue"
},
  "geometry": {"coordinates":[8.6746110916,50.4347915649],"type":"Point"}
}