{
  "type": "Feature",
  "properties": {
    "iso:country":"DE",
    "sg:address":"Hauptstr. 114",
    "sg:city":"Haarbach",
    "sg:phone":"+49 8535/204",
    "sg:postcode":"94542",
    "sg:province":"Bayern",
    "wof:name":"Kath. Pfarramt Maria Himmelfahrt",
    "wof:placetype":"venue"
},
  "geometry": {"coordinates":[13.1509552002,48.4989624023],"type":"Point"}
}