{
  "type": "Feature",
  "properties": {
    "iso:country":"DE",
    "sg:address":"Bornwiesenweg 63",
    "sg:city":"Frankfurt",
    "sg:phone":"+49 69/95530073",
    "sg:postcode":"60322",
    "sg:province":"Hessen",
    "wof:name":"Matthias H. E. Hodel Rechtsanwalt",
    "wof:placetype":"venue"
},
  "geometry": {"coordinates":[8.6783571243,50.1222801208],"type":"Point"}
}