{
  "type": "Feature",
  "properties": {
    "iso:country":"DE",
    "sg:address":"Osterstr. 7",
    "sg:city":"L\u00f6ningen",
    "sg:phone":"+49 5432/2146",
    "sg:postcode":"49624",
    "sg:province":"Niedersachsen",
    "wof:name":"Heinrich Wichmann G\u00fcternahverkehr",
    "wof:placetype":"venue"
},
  "geometry": {"coordinates":[7.7863101959,52.7266616821],"type":"Point"}
}