{
  "type": "Feature",
  "properties": {
    "iso:country":"DE",
    "sg:address":"Friedhof vor dem Frauentor",
    "sg:city":"Weimar",
    "sg:postcode":"99425",
    "sg:province":"Th\u00fcringen",
    "wof:name":"Goethe- Und Schiller-gruft",
    "wof:placetype":"venue"
},
  "geometry": {"coordinates":[11.381526,50.950554],"type":"Point"}
}