{
  "type": "Feature",
  "properties": {
    "iso:country":"DE",
    "sg:address":"Platz der Jugend 15",
    "sg:city":"Schwerin",
    "sg:phone":"+49 385/3942160",
    "sg:postcode":"19053",
    "sg:province":"Mecklenburg-Vorpommern",
    "wof:name":"Volkssolidarit\u00e4t Vorsorgeges. Mecklenburg-vorpommern Gmbh",
    "wof:placetype":"venue"
},
  "geometry": {"coordinates":[11.408051,53.620693],"type":"Point"}
}