{
  "type": "Feature",
  "properties": {
    "iso:country":"DE",
    "sg:address":"Heilbronner Str. 1",
    "sg:city":"Leinfelden-Echterdingen",
    "sg:phone":"+49 711/799139",
    "sg:postcode":"70771",
    "sg:province":"Baden-W\u00fcrttemberg",
    "wof:name":"A. Weigand",
    "wof:placetype":"venue"
},
  "geometry": {"coordinates":[9.16763,48.695854],"type":"Point"}
}