{
  "type": "Feature",
  "properties": {
    "iso:country":"DE",
    "sg:address":"Hermsdorfer Damm 149",
    "sg:city":"Berlin",
    "sg:phone":"+49 30/4040633",
    "sg:postcode":"13467",
    "sg:province":"Berlin",
    "wof:name":"Gabriela Auerswald",
    "wof:placetype":"venue"
},
  "geometry": {"coordinates":[13.3012590408,52.6168518066],"type":"Point"}
}