{
  "type": "Feature",
  "properties": {
    "iso:country":"DE",
    "sg:address":"Schlesierstr. 8",
    "sg:city":"Amberg",
    "sg:phone":"+49 9621/15182",
    "sg:postcode":"92224",
    "sg:province":"Bayern",
    "wof:name":"L. Gand",
    "wof:placetype":"venue"
},
  "geometry": {"coordinates":[11.832672,49.448219],"type":"Point"}
}