{
  "type": "Feature",
  "properties": {
    "iso:country":"DE",
    "sg:address":"Basler Str. 4",
    "sg:city":"Bad Krozingen",
    "sg:phone":"+49 7633/806650",
    "sg:postcode":"79189",
    "sg:province":"Baden-W\u00fcrttemberg",
    "wof:name":"Wwk Versicherungen Claus Schindler",
    "wof:placetype":"venue"
},
  "geometry": {"coordinates":[7.6987128258,47.9147567749],"type":"Point"}
}