{
  "type": "Feature",
  "properties": {
    "iso:country":"DE",
    "sg:address":"Am Oelberg 37",
    "sg:city":"Schieder-Schwalenberg",
    "sg:phone":"+49 5282/766",
    "sg:postcode":"32816",
    "sg:province":"Nordrhein-Westfalen",
    "wof:name":"Werner R\u00fccker Ingenieur",
    "wof:placetype":"venue"
},
  "geometry": {"coordinates":[9.1536188126,51.9082641602],"type":"Point"}
}