{
  "type": "Feature",
  "properties": {
    "iso:country":"DE",
    "sg:address":"B\u00fcrgstr. 8",
    "sg:city":"Elztal",
    "sg:phone":"+49 6261/12395",
    "sg:postcode":"74834",
    "sg:province":"Baden-W\u00fcrttemberg",
    "wof:name":"Matthias Strammer",
    "wof:placetype":"venue"
},
  "geometry": {"coordinates":[9.170382,49.376575],"type":"Point"}
}