{
  "type": "Feature",
  "properties": {
    "iso:country":"DE",
    "sg:address":"Domhof 3 c",
    "sg:city":"Osnabr\u00fcck",
    "sg:phone":"+49 541/2022238",
    "sg:postcode":"49074",
    "sg:province":"Niedersachsen",
    "wof:name":"Facorty Design Vertriebs Gmbh",
    "wof:placetype":"venue"
},
  "geometry": {"coordinates":[8.0433826447,52.2773742676],"type":"Point"}
}