{
  "type": "Feature",
  "properties": {
    "iso:country":"DE",
    "sg:address":"Gustav-Heinemann-Str. 1",
    "sg:city":"Korschenbroich",
    "sg:phone":"+49 2161/64764",
    "sg:postcode":"41352",
    "sg:province":"Nordrhein-Westfalen",
    "wof:name":"Hotel St. Andreas",
    "wof:placetype":"venue"
},
  "geometry": {"coordinates":[6.5084700584,51.1862487793],"type":"Point"}
}