{
  "type": "Feature",
  "properties": {
    "iso:country":"DE",
    "sg:address":"Auf der Perds 4",
    "sg:city":"Leiwen",
    "sg:phone":"+49 6507/3287",
    "sg:postcode":"54340",
    "sg:province":"Rheinland-Pfalz",
    "wof:name":"Benedikt Weis Weinanbau",
    "wof:placetype":"venue"
},
  "geometry": {"coordinates":[6.8823280334,49.81873703],"type":"Point"}
}