{
  "type": "Feature",
  "properties": {
    "iso:country":"DE",
    "sg:address":"Deichstr. 28",
    "sg:city":"Bunderhee",
    "sg:phone":"+49 4953/1281",
    "sg:postcode":"26831",
    "sg:province":"Niedersachsen",
    "wof:name":"Jannes Loerts",
    "wof:placetype":"venue"
},
  "geometry": {"coordinates":[7.29931,53.21933],"type":"Point"}
}