{
  "type": "Feature",
  "properties": {
    "iso:country":"DE",
    "sg:address":"Weseler Str. 570",
    "sg:city":"M\u00fcnster",
    "sg:phone":"+49 251/712434",
    "sg:postcode":"48163",
    "sg:province":"Nordrhein-Westfalen",
    "wof:name":"S. Tiehen",
    "wof:placetype":"venue"
},
  "geometry": {"coordinates":[7.5858011246,51.9275398254],"type":"Point"}
}