{
  "type": "Feature",
  "properties": {
    "iso:country":"DE",
    "sg:address":"Im Bruche 31",
    "sg:city":"G\u00f6ttingen",
    "sg:phone":"+49 551/795272",
    "sg:postcode":"37083",
    "sg:province":"Niedersachsen",
    "wof:name":"Fritz-henning Haarnagel",
    "wof:placetype":"venue"
},
  "geometry": {"coordinates":[9.95037,51.500118],"type":"Point"}
}