{
  "type": "Feature",
  "properties": {
    "iso:country":"DE",
    "sg:address":"Genhodder 1 e",
    "sg:city":"M\u00f6nchengladbach",
    "sg:phone":"+49 2161/580851",
    "sg:postcode":"41179",
    "sg:province":"Nordrhein-Westfalen",
    "wof:name":"Willi M\u00fcller",
    "wof:placetype":"venue"
},
  "geometry": {"coordinates":[6.361914,51.148205],"type":"Point"}
}