{
  "type": "Feature",
  "properties": {
    "iso:country":"DE",
    "sg:address":"Kirchstr.",
    "sg:city":"Sebnitz",
    "sg:postcode":"01855",
    "sg:province":"Sachsen",
    "wof:name":"Psg-presseshop",
    "wof:placetype":"venue"
},
  "geometry": {"coordinates":[14.2719249725,50.9712753296],"type":"Point"}
}