{
  "type": "Feature",
  "properties": {
    "iso:country":"DE",
    "sg:address":"Nordring 18",
    "sg:city":"Wittenf\u00f6rden",
    "sg:phone":"+49 385/6470480",
    "sg:postcode":"19073",
    "sg:province":"Mecklenburg-Vorpommern",
    "wof:name":"F. Lindemann",
    "wof:placetype":"venue"
},
  "geometry": {"coordinates":[11.33169,53.635303],"type":"Point"}
}