{
  "type": "Feature",
  "properties": {
    "iso:country":"DE",
    "sg:address":"Burgstr. 130",
    "sg:city":"Schifferstadt",
    "sg:phone":"+49 6235/6404",
    "sg:postcode":"67105",
    "sg:province":"Rheinland-Pfalz",
    "wof:name":"Deutscher Amateur-radio-club Ortsverband Schifferstadt",
    "wof:placetype":"venue"
},
  "geometry": {"coordinates":[8.3740644455,49.378452301],"type":"Point"}
}