{
  "type": "Feature",
  "properties": {
    "iso:country":"DE",
    "sg:address":"Reichenstr. 20",
    "sg:city":"F\u00fcssen",
    "sg:phone":"+49 8362/6109",
    "sg:postcode":"87629",
    "sg:province":"Bayern",
    "wof:name":"Ludwig Niebler Inh. A. Guggemos",
    "wof:placetype":"venue"
},
  "geometry": {"coordinates":[10.7002878189,47.5685119629],"type":"Point"}
}