{
  "type": "Feature",
  "properties": {
    "iso:country":"DE",
    "sg:address":"Junostr. 2",
    "sg:city":"Berlin",
    "sg:phone":"+49 30/4048438",
    "sg:postcode":"13467",
    "sg:province":"Berlin",
    "wof:name":"G\u00fcnter Lau",
    "wof:placetype":"venue"
},
  "geometry": {"coordinates":[13.3239145279,52.6148605347],"type":"Point"}
}