{
  "type": "Feature",
  "properties": {
    "iso:country":"DE",
    "sg:address":"Berghofer Str. 62",
    "sg:city":"Dortmund",
    "sg:phone":"+49 231/948510",
    "sg:postcode":"44269",
    "sg:province":"Nordrhein-Westfalen",
    "wof:name":"Liebeck Gmbh",
    "wof:placetype":"venue"
},
  "geometry": {"coordinates":[7.525241,51.482014],"type":"Point"}
}