{
  "type": "Feature",
  "properties": {
    "iso:country":"DE",
    "sg:address":"Kesselsdorfer Str. 16",
    "sg:city":"Freital",
    "sg:phone":"+49 351/6502491",
    "sg:postcode":"01705",
    "sg:province":"Sachsen",
    "wof:name":"Ulrich Holtsch",
    "wof:placetype":"venue"
},
  "geometry": {"coordinates":[13.6228170395,51.0233459473],"type":"Point"}
}