{
  "type": "Feature",
  "properties": {
    "iso:country":"DE",
    "sg:address":"Kaldauer Str. 35",
    "sg:city":"Siegburg",
    "sg:phone":"+49 2241/382400",
    "sg:postcode":"53721",
    "sg:province":"Nordrhein-Westfalen",
    "wof:name":"A. Pred\u00f6hl",
    "wof:placetype":"venue"
},
  "geometry": {"coordinates":[7.2334470749,50.8072052002],"type":"Point"}
}