{
  "type": "Feature",
  "properties": {
    "iso:country":"DE",
    "sg:address":"Marktplatz 8",
    "sg:city":"Ortenburg",
    "sg:phone":"+49 8542/2521",
    "sg:postcode":"94496",
    "sg:province":"Bayern",
    "wof:name":"Martin H\u00fcmmer",
    "wof:placetype":"venue"
},
  "geometry": {"coordinates":[13.2226486206,48.546546936],"type":"Point"}
}