{
  "type": "Feature",
  "properties": {
    "iso:country":"DE",
    "sg:address":"Imkerweg 8",
    "sg:city":"Wuppertal",
    "sg:phone":"+49 202/522525",
    "sg:postcode":"42279",
    "sg:province":"Nordrhein-Westfalen",
    "wof:name":"Ernst-joachim John Rechtsanwalt",
    "wof:placetype":"venue"
},
  "geometry": {"coordinates":[7.2108521461,51.2981834412],"type":"Point"}
}