{
  "type": "Feature",
  "properties": {
    "iso:country":"DE",
    "sg:address":"S\u00e4lzer Str. 23-25",
    "sg:city":"Ransbach-Baumbach",
    "sg:phone":"+49 2623/8840",
    "sg:postcode":"56235",
    "sg:province":"Rheinland-Pfalz",
    "wof:name":"Kern Erdw\u00e4rme Gmbh & Co. Kg",
    "wof:placetype":"venue"
},
  "geometry": {"coordinates":[7.7529368401,50.4752693176],"type":"Point"}
}