{
  "type": "Feature",
  "properties": {
    "iso:country":"DE",
    "sg:address":"Landwehrgasse 7",
    "sg:city":"Tiefenort",
    "sg:phone":"+49 3695/824112",
    "sg:postcode":"36469",
    "sg:province":"Th\u00fcringen",
    "wof:name":"R. Stiefel",
    "wof:placetype":"venue"
},
  "geometry": {"coordinates":[10.1660470963,50.8417167664],"type":"Point"}
}