{
  "type": "Feature",
  "properties": {
    "iso:country":"DE",
    "sg:address":"Bergheimer Str. 59",
    "sg:city":"Heidelberg",
    "sg:phone":"+49 6221/26422",
    "sg:postcode":"69115",
    "sg:province":"Baden-W\u00fcrttemberg",
    "wof:name":"G\u00f6tz-kieser & Partner Steuerberatungsges. Mbh",
    "wof:placetype":"venue"
},
  "geometry": {"coordinates":[8.6871614456,49.4080810547],"type":"Point"}
}