{
  "type": "Feature",
  "properties": {
    "iso:country":"DE",
    "sg:address":"Oberstr. 6",
    "sg:city":"Freyburg",
    "sg:phone":"+49 34464/27517",
    "sg:postcode":"06632",
    "sg:province":"Sachsen-Anhalt",
    "wof:name":"Lothar Freund",
    "wof:placetype":"venue"
},
  "geometry": {"coordinates":[11.7698230743,51.213596344],"type":"Point"}
}