{
  "type": "Feature",
  "properties": {
    "iso:country":"DE",
    "sg:address":"Zur Bleiche 13",
    "sg:city":"Langenfeld",
    "sg:phone":"+49 2173/22200",
    "sg:postcode":"40764",
    "sg:province":"Nordrhein-Westfalen",
    "wof:name":"E. Kramer",
    "wof:placetype":"venue"
},
  "geometry": {"coordinates":[6.977922,51.115643],"type":"Point"}
}