{
  "type": "Feature",
  "properties": {
    "iso:country":"DE",
    "sg:address":"Weiherstr. 10",
    "sg:city":"Schwalbach",
    "sg:phone":"+49 6834",
    "sg:postcode":"66773",
    "sg:province":"Saarland",
    "wof:name":"Tee - Express",
    "wof:placetype":"venue"
},
  "geometry": {"coordinates":[6.8133239746,49.3061218262],"type":"Point"}
}