{
  "type": "Feature",
  "properties": {
    "iso:country":"DE",
    "sg:address":"Staufenstr. 1",
    "sg:city":"Hofheim",
    "sg:phone":"+49 6192/26701",
    "sg:postcode":"65719",
    "sg:province":"Hessen",
    "wof:name":"E. Honsowitz",
    "wof:placetype":"venue"
},
  "geometry": {"coordinates":[8.4378881454,50.0905570984],"type":"Point"}
}