{
  "type": "Feature",
  "properties": {
    "iso:country":"DE",
    "sg:address":"Am Stuckertsgraben 8",
    "sg:city":"Gro\u00df-Umstadt",
    "sg:phone":"+49 6078/2443",
    "sg:postcode":"64823",
    "sg:province":"Hessen",
    "wof:name":"Heinrich Jungermann",
    "wof:placetype":"venue"
},
  "geometry": {"coordinates":[8.957608,49.888088],"type":"Point"}
}