{
  "type": "Feature",
  "properties": {
    "iso:country":"DE",
    "sg:address":"M\u00f6llhausenufer 13",
    "sg:city":"Berlin",
    "sg:phone":"+49 30/65880190",
    "sg:postcode":"12557",
    "sg:province":"Berlin",
    "wof:name":"Vins De France Weinhandels Gmbh",
    "wof:placetype":"venue"
},
  "geometry": {"coordinates":[13.5927171707,52.4144210815],"type":"Point"}
}