{
  "type": "Feature",
  "properties": {
    "iso:country":"DE",
    "sg:address":"Josefstr. 1",
    "sg:city":"Neuenkirchen",
    "sg:phone":"+49 5973/1898",
    "sg:postcode":"48485",
    "sg:province":"Nordrhein-Westfalen",
    "wof:name":"Tutti Frutty",
    "wof:placetype":"venue"
},
  "geometry": {"coordinates":[7.37275,52.243118],"type":"Point"}
}