{
  "type": "Feature",
  "properties": {
    "iso:country":"DE",
    "sg:address":"Pfandhausstr. 5",
    "sg:city":"Mainz",
    "sg:phone":"+49 6131/26150",
    "sg:postcode":"55116",
    "sg:province":"Rheinland-Pfalz",
    "wof:name":"Deutsche Woolworth Gmbh & Co. Ohg",
    "wof:placetype":"venue"
},
  "geometry": {"coordinates":[8.268501,50.000984],"type":"Point"}
}