{
  "type": "Feature",
  "properties": {
    "iso:country":"DE",
    "sg:address":"Weidestr. 51",
    "sg:city":"Eutin",
    "sg:phone":"+49 4521/72239",
    "sg:postcode":"23701",
    "sg:province":"Schleswig-Holstein",
    "wof:name":"Michael Schmidt Heizungsbau Gmbh",
    "wof:placetype":"venue"
},
  "geometry": {"coordinates":[10.6158466339,54.1299858093],"type":"Point"}
}