{
  "type": "Feature",
  "properties": {
    "iso:country":"DE",
    "sg:address":"Syringenweg 24",
    "sg:city":"Berlin",
    "sg:phone":"+49 30/4213436",
    "sg:postcode":"10407",
    "sg:province":"Berlin",
    "wof:name":"B. Schwierzina",
    "wof:placetype":"venue"
},
  "geometry": {"coordinates":[13.4569578171,52.5320472717],"type":"Point"}
}