{
  "type": "Feature",
  "properties": {
    "iso:country":"DE",
    "sg:address":"Petersbrunner Str 3",
    "sg:city":"Starnberg",
    "sg:phone":"+49 8151/26030",
    "sg:postcode":"82319",
    "sg:province":"Bayern",
    "wof:name":"Clarins Gmbh",
    "wof:placetype":"venue"
},
  "geometry": {"coordinates":[11.352718,48.003952],"type":"Point"}
}