{
  "type": "Feature",
  "properties": {
    "iso:country":"DE",
    "sg:address":"Bahnhofstr. 87",
    "sg:city":"Osterholz-Scharmbeck",
    "sg:phone":"+49 4791/6945",
    "sg:postcode":"27711",
    "sg:province":"Niedersachsen",
    "wof:name":"Hilse Bauunternehmung Gmbh",
    "wof:placetype":"venue"
},
  "geometry": {"coordinates":[8.7912988663,53.2265853882],"type":"Point"}
}