{
  "type": "Feature",
  "properties": {
    "iso:country":"DE",
    "sg:address":"Bahnstra\u00dfe 11",
    "sg:city":"Erbach",
    "sg:phone":"+49 6062",
    "sg:postcode":"64711",
    "sg:province":"Hessen",
    "wof:name":"Uwe Mohr",
    "wof:placetype":"venue"
},
  "geometry": {"coordinates":[8.9927310944,49.6562309265],"type":"Point"}
}