{
  "type": "Feature",
  "properties": {
    "iso:country":"DE",
    "sg:address":"K\u00f6bbingser M\u00fchle 14",
    "sg:city":"Iserlohn",
    "sg:phone":"+49 2371/9450",
    "sg:postcode":"58640",
    "sg:province":"Nordrhein-Westfalen",
    "wof:name":"Pekrun Getriebebau Gmbh",
    "wof:placetype":"venue"
},
  "geometry": {"coordinates":[7.698589,51.421993],"type":"Point"}
}