{
  "type": "Feature",
  "properties": {
    "iso:country":"DE",
    "sg:address":"Futterstr 17",
    "sg:city":"Erfurt",
    "sg:phone":"+49 361/5661272",
    "sg:postcode":"99084",
    "sg:province":"Th\u00fcringen",
    "wof:name":"H\u00f6rger\u00e4tezentrum In Erfurt Gmbh",
    "wof:placetype":"venue"
},
  "geometry": {"coordinates":[11.0337591171,50.9792366028],"type":"Point"}
}