{
  "type": "Feature",
  "properties": {
    "iso:country":"DE",
    "sg:address":"Am Wirthemb\u00f6sch",
    "sg:city":"St. Wendel",
    "sg:phone":"+49 6851/84516",
    "sg:postcode":"66606",
    "sg:province":"Saarland",
    "wof:name":"Kreissparkasse Sankt Wendel",
    "wof:placetype":"venue"
},
  "geometry": {"coordinates":[7.1599411964,49.4646148682],"type":"Point"}
}