{
  "type": "Feature",
  "properties": {
    "iso:country":"DE",
    "sg:address":"Carl-Sonnenschein-Str. 54",
    "sg:city":"Frankfurt",
    "sg:phone":"+49 69/342968",
    "sg:postcode":"65936",
    "sg:province":"Hessen",
    "wof:name":"Alois Wenzlitschke",
    "wof:placetype":"venue"
},
  "geometry": {"coordinates":[8.57346,50.127522],"type":"Point"}
}