{
  "type": "Feature",
  "properties": {
    "iso:country":"DE",
    "sg:address":"Kiefernstr. 14",
    "sg:city":"Schl\u00fcchtern",
    "sg:phone":"+49 6661/6282",
    "sg:postcode":"36381",
    "sg:province":"Hessen",
    "wof:name":"Klaus Gumprecht",
    "wof:placetype":"venue"
},
  "geometry": {"coordinates":[9.559906,50.358742],"type":"Point"}
}