{
  "type": "Feature",
  "properties": {
    "iso:country":"DE",
    "sg:address":"Hanhoff 6",
    "sg:city":"Nottuln",
    "sg:phone":"+49 2502/6637",
    "sg:postcode":"48301",
    "sg:province":"Nordrhein-Westfalen",
    "wof:name":"Termersch",
    "wof:placetype":"venue"
},
  "geometry": {"coordinates":[7.354419,51.92823],"type":"Point"}
}