{
  "type": "Feature",
  "properties": {
    "iso:country":"DE",
    "sg:address":"Koblenzer Str. 56",
    "sg:city":"Wittlich",
    "sg:phone":"+49 6571/3126",
    "sg:postcode":"54516",
    "sg:province":"Rheinland-Pfalz",
    "wof:name":"Staatl. Aufbaugymnasium Und Frauenoberschule",
    "wof:placetype":"venue"
},
  "geometry": {"coordinates":[6.8924641609,49.9934043884],"type":"Point"}
}