{
  "type": "Feature",
  "properties": {
    "iso:country":"DE",
    "sg:address":"Silberstr. 33",
    "sg:city":"Crimmitschau",
    "sg:phone":"+49 3762/3514",
    "sg:postcode":"08451",
    "sg:province":"Sachsen",
    "wof:name":"Lutz Humann",
    "wof:placetype":"venue"
},
  "geometry": {"coordinates":[12.3871831894,50.8143997192],"type":"Point"}
}