{
  "type": "Feature",
  "properties": {
    "iso:country":"DE",
    "sg:address":"Viktor-Scheffel-Str. 23",
    "sg:city":"M\u00fcnchen",
    "sg:phone":"+49 89/397677",
    "sg:postcode":"80803",
    "sg:province":"Bayern",
    "wof:name":"Asado-steak",
    "wof:placetype":"venue"
},
  "geometry": {"coordinates":[11.5753059387,48.1617393494],"type":"Point"}
}