{
  "type": "Feature",
  "properties": {
    "iso:country":"DE",
    "sg:address":"B\u00fcntestr. 27",
    "sg:city":"Brackel",
    "sg:phone":"+49 4185/4273",
    "sg:postcode":"21438",
    "sg:province":"Niedersachsen",
    "wof:name":"Hermann Tsch\u00e4pe",
    "wof:placetype":"venue"
},
  "geometry": {"coordinates":[10.0410957336,53.296661377],"type":"Point"}
}