{
  "type": "Feature",
  "properties": {
    "iso:country":"DE",
    "sg:address":"Neuer Weg 8",
    "sg:city":"Pattensen",
    "sg:phone":"+49 5101/13351",
    "sg:postcode":"30982",
    "sg:province":"Niedersachsen",
    "wof:name":"Aerophot Demuss",
    "wof:placetype":"venue"
},
  "geometry": {"coordinates":[9.7598772049,52.2604866028],"type":"Point"}
}