{
  "type": "Feature",
  "properties": {
    "iso:country":"DE",
    "sg:address":"B\u00fcnder Str. 94",
    "sg:city":"R\u00f6dinghausen",
    "sg:phone":"+49 5746/920034",
    "sg:postcode":"32289",
    "sg:province":"Nordrhein-Westfalen",
    "wof:name":"B. Nehl",
    "wof:placetype":"venue"
},
  "geometry": {"coordinates":[8.50597,52.24538],"type":"Point"}
}