{
  "type": "Feature",
  "properties": {
    "iso:country":"DE",
    "sg:address":"Scheffelstr. 57",
    "sg:city":"Leipzig",
    "sg:postcode":"04277",
    "sg:province":"Sachsen",
    "wof:name":"Erster Deutscher Miniaturbuch- Verein Leipz. Gegr. 1983 E. V.",
    "wof:placetype":"venue"
},
  "geometry": {"coordinates":[12.3804206848,51.3119468689],"type":"Point"}
}