{
  "type": "Feature",
  "properties": {
    "iso:country":"DE",
    "sg:address":"Ludolfingerplatz 1-3",
    "sg:city":"Berlin",
    "sg:phone":"+49 30/4014656",
    "sg:postcode":"13465",
    "sg:province":"Berlin",
    "wof:name":"Betten Winkler",
    "wof:placetype":"venue"
},
  "geometry": {"coordinates":[13.289191246,52.6327323914],"type":"Point"}
}