{
  "type": "Feature",
  "properties": {
    "iso:country":"DE",
    "sg:address":"Innstr. 10",
    "sg:city":"Rosenheim",
    "sg:phone":"+49 8031/14233",
    "sg:postcode":"83022",
    "sg:province":"Bayern",
    "wof:name":"Rudolf Ramthun",
    "wof:placetype":"venue"
},
  "geometry": {"coordinates":[12.129863739,47.8551712036],"type":"Point"}
}