{
  "type": "Feature",
  "properties": {
    "iso:country":"DE",
    "sg:address":"Bahnhofstr. 7",
    "sg:city":"Dinklage",
    "sg:phone":"+49 4443/96360",
    "sg:postcode":"49413",
    "sg:province":"Niedersachsen",
    "wof:name":"Walter Bruning",
    "wof:placetype":"venue"
},
  "geometry": {"coordinates":[8.1219949722,52.6630783081],"type":"Point"}
}