{
  "type": "Feature",
  "properties": {
    "iso:country":"DE",
    "sg:address":"Rosenhaldenweg 4",
    "sg:city":"Diedorf",
    "sg:phone":"+49 8238/1483",
    "sg:postcode":"86420",
    "sg:province":"Bayern",
    "wof:name":"Hema-raj Gmbh",
    "wof:placetype":"venue"
},
  "geometry": {"coordinates":[10.7508916855,48.3519592285],"type":"Point"}
}