{
  "type": "Feature",
  "properties": {
    "iso:country":"DE",
    "sg:address":"Obere Stadt 14",
    "sg:city":"Weilheim",
    "sg:phone":"+49 881/2038",
    "sg:postcode":"82362",
    "sg:province":"Bayern",
    "wof:name":"Dr. S. Kittmann",
    "wof:placetype":"venue"
},
  "geometry": {"coordinates":[11.1463317871,47.8382301331],"type":"Point"}
}