{
  "type": "Feature",
  "properties": {
    "iso:country":"DE",
    "sg:address":"Pestalozzistr. 27",
    "sg:city":"L\u00f6rrach",
    "sg:phone":"+49 7621/10933",
    "sg:postcode":"79540",
    "sg:province":"Baden-W\u00fcrttemberg",
    "wof:name":"Hansj\u00f6rg Stoz",
    "wof:placetype":"venue"
},
  "geometry": {"coordinates":[7.660127,47.600136],"type":"Point"}
}