{
  "type": "Feature",
  "properties": {
    "iso:country":"DE",
    "sg:address":"Hauptstr. 36",
    "sg:city":"Ro\u00dfdorf",
    "sg:phone":"+49 6071/42728",
    "sg:postcode":"64380",
    "sg:province":"Hessen",
    "wof:name":"Karl Hamann",
    "wof:placetype":"venue"
},
  "geometry": {"coordinates":[8.7871627808,49.8713607788],"type":"Point"}
}