{
  "type": "Feature",
  "properties": {
    "iso:country":"DE",
    "sg:address":"Falkenstr. 25",
    "sg:city":"Hannover",
    "sg:phone":"+49 511/9245231",
    "sg:postcode":"30449",
    "sg:province":"Niedersachsen",
    "wof:name":"Andreas J. Ackermann Ingenieur Garten- Und",
    "wof:placetype":"venue"
},
  "geometry": {"coordinates":[9.715608,52.366615],"type":"Point"}
}