{
  "type": "Feature",
  "properties": {
    "iso:country":"DE",
    "sg:address":"Heppinger Str. 78",
    "sg:city":"Grafschaft",
    "sg:phone":"+49 2641/25488",
    "sg:postcode":"53501",
    "sg:province":"Rheinland-Pfalz",
    "wof:name":"Gisbert Kleinertz Obstanbau",
    "wof:placetype":"venue"
},
  "geometry": {"coordinates":[7.1015911102,50.5753898621],"type":"Point"}
}