{
  "type": "Feature",
  "properties": {
    "iso:country":"DE",
    "sg:address":"Kiefernweg 10",
    "sg:city":"Kahl",
    "sg:phone":"+49 6188/81009",
    "sg:postcode":"63796",
    "sg:province":"Bayern",
    "wof:name":"Hardi Hohensee",
    "wof:placetype":"venue"
},
  "geometry": {"coordinates":[9.0013837814,50.0631141663],"type":"Point"}
}