{
  "type": "Feature",
  "properties": {
    "iso:country":"DE",
    "sg:address":"Aspisheimer Str. 26",
    "sg:city":"Horrweiler",
    "sg:phone":"+49 6727/1717",
    "sg:postcode":"55457",
    "sg:province":"Rheinland-Pfalz",
    "wof:name":"Bernd Geyer",
    "wof:placetype":"venue"
},
  "geometry": {"coordinates":[7.969735,49.899616],"type":"Point"}
}