{
  "type": "Feature",
  "properties": {
    "iso:country":"DE",
    "sg:address":"Industriestr. 28",
    "sg:city":"\u00d6tigheim",
    "sg:phone":"+49 7222/21066",
    "sg:postcode":"76470",
    "sg:province":"Baden-W\u00fcrttemberg",
    "wof:name":"Mauceri Gmbh",
    "wof:placetype":"venue"
},
  "geometry": {"coordinates":[8.24358,48.887238],"type":"Point"}
}