{
  "type": "Feature",
  "properties": {
    "iso:country":"DE",
    "sg:address":"Berliner Platz",
    "sg:city":"Hamburg",
    "sg:postcode":"22045",
    "sg:province":"Hamburg",
    "wof:name":"R & S Handelsgesellschaft Mbh",
    "wof:placetype":"venue"
},
  "geometry": {"coordinates":[10.1417446136,53.5844345093],"type":"Point"}
}