{
  "type": "Feature",
  "properties": {
    "iso:country":"DE",
    "sg:address":"Im R\u00f6del 6",
    "sg:city":"Ruppertsweiler",
    "sg:phone":"+49 6395/6227",
    "sg:postcode":"66957",
    "sg:province":"Rheinland-Pfalz",
    "wof:name":"Rainer Schlachter",
    "wof:placetype":"venue"
},
  "geometry": {"coordinates":[7.6880860329,49.1958007812],"type":"Point"}
}