{
  "type": "Feature",
  "properties": {
    "iso:country":"DE",
    "sg:address":"Rathausplatz 3",
    "sg:city":"Monheim",
    "sg:phone":"+49 2173/51261",
    "sg:postcode":"40789",
    "sg:province":"Nordrhein-Westfalen",
    "wof:name":"E. Sch\u00fcckhaus Steuerberater",
    "wof:placetype":"venue"
},
  "geometry": {"coordinates":[10.8562364578,48.842792511],"type":"Point"}
}