{
  "type": "Feature",
  "properties": {
    "iso:country":"DE",
    "sg:address":"Soldnerstr. 10",
    "sg:city":"Augsburg",
    "sg:phone":"+49 821/711106",
    "sg:postcode":"86167",
    "sg:province":"Bayern",
    "wof:name":"Ct Consuldata Treuhand Steuerberatungs Gmbh",
    "wof:placetype":"venue"
},
  "geometry": {"coordinates":[10.9145431519,48.3835487366],"type":"Point"}
}