{
  "type": "Feature",
  "properties": {
    "iso:country":"DE",
    "sg:address":"Geithainer Str. 18",
    "sg:city":"Frankenhain",
    "sg:phone":"+49 34341/43031",
    "sg:postcode":"04643",
    "sg:province":"Sachsen",
    "wof:name":"G. Reiche",
    "wof:placetype":"venue"
},
  "geometry": {"coordinates":[12.641368866,51.086265564],"type":"Point"}
}