{
  "type": "Feature",
  "properties": {
    "iso:country":"DE",
    "sg:address":"Karl-Liebknecht-Str. 4",
    "sg:city":"K\u00f6nigs Wusterhausen",
    "sg:phone":"+49 3375/296919",
    "sg:postcode":"15711",
    "sg:province":"Brandenburg",
    "wof:name":"New Order-bar",
    "wof:placetype":"venue"
},
  "geometry": {"coordinates":[13.626824379,52.2955474854],"type":"Point"}
}