{
  "type": "Feature",
  "properties": {
    "iso:country":"DE",
    "sg:address":"Waldshuter Str. 16",
    "sg:city":"Laufenburg",
    "sg:phone":"+49 7763/4346",
    "sg:postcode":"79725",
    "sg:province":"Baden-W\u00fcrttemberg",
    "wof:name":"J. D\u00f6rflinger",
    "wof:placetype":"venue"
},
  "geometry": {"coordinates":[8.074074,47.565628],"type":"Point"}
}