{
  "type": "Feature",
  "properties": {
    "iso:country":"DE",
    "sg:address":"St.-Annen-Str.",
    "sg:city":"L\u00f6ningen",
    "sg:postcode":"49624",
    "sg:province":"Niedersachsen",
    "wof:name":"Stiftung St. Anna-stift",
    "wof:placetype":"venue"
},
  "geometry": {"coordinates":[7.7567138672,52.7355461121],"type":"Point"}
}