{
  "type": "Feature",
  "properties": {
    "iso:country":"DE",
    "sg:address":"Badstr. 8",
    "sg:city":"Munningen",
    "sg:phone":"+49 9082/3684",
    "sg:postcode":"86754",
    "sg:province":"Bayern",
    "wof:name":"J. Erdle",
    "wof:placetype":"venue"
},
  "geometry": {"coordinates":[10.6050243378,48.9193458557],"type":"Point"}
}