{
  "type": "Feature",
  "properties": {
    "iso:country":"DE",
    "sg:address":"Tengstr 33",
    "sg:city":"M\u00fcnchen",
    "sg:phone":"+49 89/2722472",
    "sg:postcode":"80796",
    "sg:province":"Bayern",
    "wof:name":"Efw Edition Forschung Und Wissenschaft Verlags-gmbh",
    "wof:placetype":"venue"
},
  "geometry": {"coordinates":[11.568944931,48.1593818665],"type":"Point"}
}