{
  "type": "Feature",
  "properties": {
    "iso:country":"DE",
    "sg:address":"Bahnhofstr. 42",
    "sg:city":"Wesseling",
    "sg:phone":"+49 2236/840149",
    "sg:postcode":"50389",
    "sg:province":"Nordrhein-Westfalen",
    "wof:name":"Wesselinger Grill",
    "wof:placetype":"venue"
},
  "geometry": {"coordinates":[6.9793457985,50.8236694336],"type":"Point"}
}