{
  "type": "Feature",
  "properties": {
    "iso:country":"DE",
    "sg:address":"Silcherstr. 12",
    "sg:city":"K\u00f6ln",
    "sg:phone":"+49 221/5879191",
    "sg:postcode":"50827",
    "sg:province":"Nordrhein-Westfalen",
    "wof:name":"Aikido-schule Kirk Kropp",
    "wof:placetype":"venue"
},
  "geometry": {"coordinates":[6.8973708153,50.9559288025],"type":"Point"}
}