{
  "type": "Feature",
  "properties": {
    "iso:country":"DE",
    "sg:address":"Ackerstr. 144",
    "sg:city":"D\u00fcsseldorf",
    "sg:phone":"+49 211/6907960",
    "sg:postcode":"40233",
    "sg:province":"Nordrhein-Westfalen",
    "wof:name":"3s Arbeitsschutz Gmbh",
    "wof:placetype":"venue"
},
  "geometry": {"coordinates":[6.806281,51.229645],"type":"Point"}
}