{
  "type": "Feature",
  "properties": {
    "iso:country":"DE",
    "sg:address":"Herzberger Str. 5 a",
    "sg:city":"Rhumspringe",
    "sg:phone":"+49 5529/919050",
    "sg:postcode":"37434",
    "sg:province":"Niedersachsen",
    "wof:name":"M\u00fchlen-apotheke",
    "wof:placetype":"venue"
},
  "geometry": {"coordinates":[10.296295,51.584274],"type":"Point"}
}