{
  "type": "Feature",
  "properties": {
    "iso:country":"DE",
    "sg:address":"Aschaffenburger Str 50",
    "sg:city":"Goldbach",
    "sg:phone":"+49 6021/540448",
    "sg:postcode":"63773",
    "sg:province":"Bayern",
    "wof:name":"B\u00e4rschneider Inh. Rainer John",
    "wof:placetype":"venue"
},
  "geometry": {"coordinates":[9.1809234619,49.997303009],"type":"Point"}
}