{
  "type": "Feature",
  "properties": {
    "iso:country":"DE",
    "sg:address":"\u00d6denburger Str. 42",
    "sg:city":"Darmstadt",
    "sg:phone":"+49 6151/33133",
    "sg:postcode":"64295",
    "sg:province":"Hessen",
    "wof:name":"I.a.t. Immobilien S. Zackl",
    "wof:placetype":"venue"
},
  "geometry": {"coordinates":[8.6236581802,49.845375061],"type":"Point"}
}