{
  "type": "Feature",
  "properties": {
    "iso:country":"DE",
    "sg:address":"Spitalhof 1-2",
    "sg:city":"Wunsiedel",
    "sg:phone":"+49 9232/2032",
    "sg:postcode":"95632",
    "sg:province":"Bayern",
    "wof:name":"Fichtelgebirgs-museum",
    "wof:placetype":"venue"
},
  "geometry": {"coordinates":[12.004069,50.038815],"type":"Point"}
}