{
  "type": "Feature",
  "properties": {
    "iso:country":"DE",
    "sg:address":"Westendstr. 44",
    "sg:city":"Frankfurt",
    "sg:postcode":"60325",
    "sg:province":"Hessen",
    "wof:name":"Europe Trade Belgrad",
    "wof:placetype":"venue"
},
  "geometry": {"coordinates":[8.66155,50.113804],"type":"Point"}
}