{
  "type": "Feature",
  "properties": {
    "iso:country":"DE",
    "sg:address":"Kleines Feldlein 3",
    "sg:city":"Sinsheim",
    "sg:phone":"+49 7261/6850",
    "sg:postcode":"74889",
    "sg:province":"Baden-W\u00fcrttemberg",
    "wof:name":"Ernst Willaredt Ingenieur",
    "wof:placetype":"venue"
},
  "geometry": {"coordinates":[8.8508529663,49.2493057251],"type":"Point"}
}