{
  "type": "Feature",
  "properties": {
    "iso:country":"DE",
    "sg:address":"Gausebrink 93",
    "sg:city":"Ochtrup",
    "sg:phone":"+49 2553/3707",
    "sg:postcode":"48607",
    "sg:province":"Nordrhein-Westfalen",
    "wof:name":"Hotel Hermann Weitkamp",
    "wof:placetype":"venue"
},
  "geometry": {"coordinates":[7.1712331772,52.2043838501],"type":"Point"}
}