{
  "type": "Feature",
  "properties": {
    "iso:country":"DE",
    "sg:address":"Bahnhofstr.",
    "sg:city":"Ro\u00dfleben",
    "sg:phone":"+49 34672/84802",
    "sg:postcode":"06571",
    "sg:province":"Th\u00fcringen",
    "wof:name":"Hartmut M\u00fcller",
    "wof:placetype":"venue"
},
  "geometry": {"coordinates":[11.40409,51.298302],"type":"Point"}
}