{
  "type": "Feature",
  "properties": {
    "iso:country":"DE",
    "sg:address":"Hermann-L\u00f6ns-Str. 111",
    "sg:city":"Laatzen",
    "sg:phone":"+49 511/826431",
    "sg:postcode":"30880",
    "sg:province":"Niedersachsen",
    "wof:name":"Carla-maria Boldt J\u00fcrgen Boldt",
    "wof:placetype":"venue"
},
  "geometry": {"coordinates":[9.802145,52.294022],"type":"Point"}
}