{
  "type": "Feature",
  "properties": {
    "iso:country":"DE",
    "sg:address":"Hauptstr. 19",
    "sg:city":"Nedlitz",
    "sg:postcode":"39291",
    "sg:province":"Sachsen-Anhalt",
    "wof:name":"Frankenfeld",
    "wof:placetype":"venue"
},
  "geometry": {"coordinates":[11.8314504623,52.1275939941],"type":"Point"}
}