{
  "type": "Feature",
  "properties": {
    "iso:country":"DE",
    "sg:address":"Bahnhofstr. 44",
    "sg:city":"Neustadt",
    "sg:phone":"+49 9161/4548",
    "sg:postcode":"91413",
    "sg:province":"Bayern",
    "wof:name":"Adelheid Hofmann Hebamme",
    "wof:placetype":"venue"
},
  "geometry": {"coordinates":[12.44409,52.85545],"type":"Point"}
}