{
  "type": "Feature",
  "properties": {
    "iso:country":"DE",
    "sg:address":"Lechstr. 5",
    "sg:city":"Backnang",
    "sg:phone":"+49 7191/71311",
    "sg:postcode":"71522",
    "sg:province":"Baden-W\u00fcrttemberg",
    "wof:name":"Mackee-jeans",
    "wof:placetype":"venue"
},
  "geometry": {"coordinates":[9.4294729233,48.9161872864],"type":"Point"}
}