{
  "type": "Feature",
  "properties": {
    "iso:country":"DE",
    "sg:address":"Gewerbering 1",
    "sg:city":"Fritzlar",
    "sg:phone":"+49 5622/9880",
    "sg:postcode":"34560",
    "sg:province":"Hessen",
    "wof:name":"Lemmi-fashion Vertriebs- Gmbh & Co. Bekleidungs Kg",
    "wof:placetype":"venue"
},
  "geometry": {"coordinates":[9.2940540314,51.127872467],"type":"Point"}
}