{
  "type": "Feature",
  "properties": {
    "iso:country":"DE",
    "sg:address":"Mainzer Str. 20a",
    "sg:city":"Bad Kreuznach",
    "sg:phone":"+49 671/69095",
    "sg:postcode":"55545",
    "sg:province":"Rheinland-Pfalz",
    "wof:name":"Eckhard Barwick",
    "wof:placetype":"venue"
},
  "geometry": {"coordinates":[7.9010438919,49.8582038879],"type":"Point"}
}