{
  "type": "Feature",
  "properties": {
    "iso:country":"DE",
    "sg:address":"Watzmann Str. 15",
    "sg:city":"Kraiburg",
    "sg:phone":"+49 8638/7611",
    "sg:postcode":"84559",
    "sg:province":"Bayern",
    "wof:name":"Stenger Holzbau Und Zimmerei - Bauen, Sanieren",
    "wof:placetype":"venue"
},
  "geometry": {"coordinates":[12.436921,48.18996],"type":"Point"}
}