{
  "type": "Feature",
  "properties": {
    "iso:country":"DE",
    "sg:address":"Oberreichenbacher Str. 15",
    "sg:city":"Schwabach",
    "sg:phone":"+49 9122/3259",
    "sg:postcode":"91126",
    "sg:province":"Bayern",
    "wof:name":"G\u00fcnther Korn",
    "wof:placetype":"venue"
},
  "geometry": {"coordinates":[10.991084,49.329277],"type":"Point"}
}