{
  "type": "Feature",
  "properties": {
    "iso:country":"DE",
    "sg:address":"Cottenburgstr. 198",
    "sg:city":"Castrop-Rauxel",
    "sg:phone":"+49 2305/923770",
    "sg:postcode":"44575",
    "sg:province":"Nordrhein-Westfalen",
    "wof:name":"E. Weber Steuerberater",
    "wof:placetype":"venue"
},
  "geometry": {"coordinates":[7.3286499977,51.5443153381],"type":"Point"}
}