{
  "type": "Feature",
  "properties": {
    "iso:country":"DE",
    "sg:address":"Markenstr. 23",
    "sg:city":"Gelsenkirchen",
    "sg:postcode":"45899",
    "sg:province":"Nordrhein-Westfalen",
    "wof:name":"Aldi Gmbh & Co. Kg",
    "wof:placetype":"venue"
},
  "geometry": {"coordinates":[7.0252928734,51.5312767029],"type":"Point"}
}