{
  "type": "Feature",
  "properties": {
    "iso:country":"DE",
    "sg:address":"Hebelstr. 18",
    "sg:city":"L\u00f6ffingen",
    "sg:phone":"+49 7654/237",
    "sg:postcode":"79843",
    "sg:province":"Baden-W\u00fcrttemberg",
    "wof:name":"Werner Mayer Transport-unternehmen",
    "wof:placetype":"venue"
},
  "geometry": {"coordinates":[8.3379592896,47.8825378418],"type":"Point"}
}