{
  "type": "Feature",
  "properties": {
    "iso:country":"DE",
    "sg:address":"Kreillerstr. 63",
    "sg:city":"M\u00fcnchen",
    "sg:phone":"+49 89/4317078",
    "sg:postcode":"81673",
    "sg:province":"Bayern",
    "wof:name":"Ristorante Pizzeria Eboli",
    "wof:placetype":"venue"
},
  "geometry": {"coordinates":[11.641251564,48.1266746521],"type":"Point"}
}