{
  "type": "Feature",
  "properties": {
    "iso:country":"DE",
    "sg:address":"Niederurseler Landstr. 9",
    "sg:city":"Frankfurt",
    "sg:phone":"+49 69/587814",
    "sg:postcode":"60439",
    "sg:province":"Hessen",
    "wof:name":"Reate Nelson Rechtsanwalt",
    "wof:placetype":"venue"
},
  "geometry": {"coordinates":[8.6326789856,50.164100647],"type":"Point"}
}