{
  "type": "Feature",
  "properties": {
    "iso:country":"DE",
    "sg:address":"Frankfurter Str. 183",
    "sg:city":"Bad Vilbel",
    "sg:phone":"+49 6101/83829",
    "sg:postcode":"61118",
    "sg:province":"Hessen",
    "wof:name":"R. Boerckel",
    "wof:placetype":"venue"
},
  "geometry": {"coordinates":[8.7335100174,50.1745681763],"type":"Point"}
}