{
  "type": "Feature",
  "properties": {
    "iso:country":"DE",
    "sg:address":"Haldenstr. 14",
    "sg:city":"Leinfelden-Echterdingen",
    "sg:phone":"+49 711/7979385",
    "sg:postcode":"70771",
    "sg:province":"Baden-W\u00fcrttemberg",
    "wof:name":"T. St\u00fcve-bei\u00dfmann",
    "wof:placetype":"venue"
},
  "geometry": {"coordinates":[9.1680679321,48.6714515686],"type":"Point"}
}