{
  "type": "Feature",
  "properties": {
    "iso:country":"DE",
    "sg:address":"Gelnh\u00e4user Str. 31",
    "sg:city":"W\u00e4chtersbach",
    "sg:phone":"+49 6053/600353",
    "sg:postcode":"63607",
    "sg:province":"Hessen",
    "wof:name":"Ralf Dewald",
    "wof:placetype":"venue"
},
  "geometry": {"coordinates":[9.2874526978,50.2525253296],"type":"Point"}
}