{
  "type": "Feature",
  "properties": {
    "iso:country":"DE",
    "sg:address":"Brinkhofstr 86",
    "sg:city":"Iserlohn",
    "sg:phone":"+49 2374/93730",
    "sg:postcode":"58642",
    "sg:province":"Nordrhein-Westfalen",
    "wof:name":"Verlag F\u00fcr Therapeutische Medien Dr. Stein & Co. Ohg",
    "wof:placetype":"venue"
},
  "geometry": {"coordinates":[7.6340870857,51.3703804016],"type":"Point"}
}