{
  "type": "Feature",
  "properties": {
    "iso:country":"DE",
    "sg:address":"Heinrich-Zille-Str. 51",
    "sg:city":"Cottbus",
    "sg:phone":"+49 355/720720",
    "sg:postcode":"03042",
    "sg:province":"Brandenburg",
    "wof:name":"Kolotreu-bautr\u00e4gerges. Mbh",
    "wof:placetype":"venue"
},
  "geometry": {"coordinates":[14.363923,51.756359],"type":"Point"}
}