{
  "type": "Feature",
  "properties": {
    "iso:country":"DE",
    "sg:address":"Rathausgasse 2",
    "sg:city":"Jena",
    "sg:postcode":"07743",
    "sg:province":"Th\u00fcringen",
    "wof:name":"Bistorante Michelangelo E. K.",
    "wof:placetype":"venue"
},
  "geometry": {"coordinates":[11.5870485306,50.9281463623],"type":"Point"}
}