{
  "type": "Feature",
  "properties": {
    "iso:country":"DE",
    "sg:address":"Kaiserswerther Str. 183",
    "sg:city":"D\u00fcsseldorf",
    "sg:phone":"+49 211/450739",
    "sg:postcode":"40474",
    "sg:province":"Nordrhein-Westfalen",
    "wof:name":"Bellini Warenvertriebs- Gesellschaft Mbh",
    "wof:placetype":"venue"
},
  "geometry": {"coordinates":[6.767918,51.24704],"type":"Point"}
}