{
  "type": "Feature",
  "properties": {
    "iso:country":"DE",
    "sg:address":"Lorchensburg 8",
    "sg:city":"Negenborn",
    "sg:phone":"+49 5532/98230",
    "sg:postcode":"37643",
    "sg:province":"Niedersachsen",
    "wof:name":"F. Klages",
    "wof:placetype":"venue"
},
  "geometry": {"coordinates":[9.5747470856,51.8915939331],"type":"Point"}
}