{
  "type": "Feature",
  "properties": {
    "iso:country":"DE",
    "sg:address":"Talstr. 17",
    "sg:city":"Sontheim",
    "sg:phone":"+49 7325/910030",
    "sg:postcode":"89567",
    "sg:province":"Baden-W\u00fcrttemberg",
    "wof:name":"R. Steinhart",
    "wof:placetype":"venue"
},
  "geometry": {"coordinates":[10.276008,48.55677],"type":"Point"}
}