{
  "type": "Feature",
  "properties": {
    "iso:country":"DE",
    "sg:address":"Riehetalstr. 2",
    "sg:city":"Woltershausen",
    "sg:postcode":"31099",
    "sg:province":"Niedersachsen",
    "wof:name":"Hackerpower.de International-hacker-site",
    "wof:placetype":"venue"
},
  "geometry": {"coordinates":[9.975026,51.98061],"type":"Point"}
}