{
  "type": "Feature",
  "properties": {
    "iso:country":"DE",
    "sg:address":"Weseler Str. 9",
    "sg:city":"D\u00fcsseldorf",
    "sg:phone":"+49 211/635188",
    "sg:postcode":"40239",
    "sg:province":"Nordrhein-Westfalen",
    "wof:name":"R.-ch. Nobis Gmbh",
    "wof:placetype":"venue"
},
  "geometry": {"coordinates":[6.798333,51.240959],"type":"Point"}
}