{
  "type": "Feature",
  "properties": {
    "iso:country":"DE",
    "sg:address":"Niederrheinische Str. 51",
    "sg:city":"Kirchhain",
    "sg:phone":"+49 6422/1010",
    "sg:postcode":"35274",
    "sg:province":"Hessen",
    "wof:name":"W. Felden Kaiser & Roth Kg Handels Gmbh & Co.",
    "wof:placetype":"venue"
},
  "geometry": {"coordinates":[8.9207401276,50.8209838867],"type":"Point"}
}