{
  "type": "Feature",
  "properties": {
    "iso:country":"DE",
    "sg:address":"Hohe Str. 33",
    "sg:city":"Datteln",
    "sg:phone":"+49 2363/53145",
    "sg:postcode":"45711",
    "sg:province":"Nordrhein-Westfalen",
    "wof:name":"Karl Hillenbach",
    "wof:placetype":"venue"
},
  "geometry": {"coordinates":[7.340008,51.652828],"type":"Point"}
}