{
  "type": "Feature",
  "properties": {
    "iso:country":"DE",
    "sg:address":"Stadtplatz 5",
    "sg:city":"Neustadt",
    "sg:phone":"+49 9445/434",
    "sg:postcode":"93333",
    "sg:province":"Bayern",
    "wof:name":"Georg Feigl",
    "wof:placetype":"venue"
},
  "geometry": {"coordinates":[14.260829,51.437004],"type":"Point"}
}