{
  "type": "Feature",
  "properties": {
    "iso:country":"DE",
    "sg:address":"Wilhelm-Pieck-Ring 19",
    "sg:city":"Havelberg",
    "sg:phone":"+49 39387/8143",
    "sg:postcode":"39539",
    "sg:province":"Sachsen-Anhalt",
    "wof:name":"A. Fleischmann",
    "wof:placetype":"venue"
},
  "geometry": {"coordinates":[12.0867967606,52.8301200867],"type":"Point"}
}