{
  "type": "Feature",
  "properties": {
    "iso:country":"DE",
    "sg:address":"Osterstr. 30",
    "sg:city":"Cloppenburg",
    "sg:phone":"+49 4471/3206",
    "sg:postcode":"49661",
    "sg:province":"Niedersachsen",
    "wof:name":"Heinz Heitgerken",
    "wof:placetype":"venue"
},
  "geometry": {"coordinates":[8.045099,52.848507],"type":"Point"}
}