{
  "type": "Feature",
  "properties": {
    "iso:country":"DE",
    "sg:address":"Hattenbergstr 10",
    "sg:city":"Mainz",
    "sg:phone":"+49 6131/663180",
    "sg:postcode":"55122",
    "sg:province":"Rheinland-Pfalz",
    "wof:name":"Fiege Novalogistics Gmbh & Co Kg",
    "wof:placetype":"venue"
},
  "geometry": {"coordinates":[8.243818,50.015591],"type":"Point"}
}