{
  "type": "Feature",
  "properties": {
    "iso:country":"DE",
    "sg:address":"Am Wald 1",
    "sg:city":"Monheim",
    "sg:phone":"+49 2173/53057",
    "sg:postcode":"40789",
    "sg:province":"Nordrhein-Westfalen",
    "wof:name":"Holzmarkt G\u00f6bel Gmbh",
    "wof:placetype":"venue"
},
  "geometry": {"coordinates":[6.911919117,51.0951080322],"type":"Point"}
}