{
  "type": "Feature",
  "properties": {
    "iso:country":"DE",
    "sg:address":"Zeller Str. 18",
    "sg:city":"Ruhpolding",
    "sg:phone":"+49 8663/9213",
    "sg:postcode":"83324",
    "sg:province":"Bayern",
    "wof:name":"Anton Plenk",
    "wof:placetype":"venue"
},
  "geometry": {"coordinates":[12.6542253494,47.7601890564],"type":"Point"}
}