{
  "type": "Feature",
  "properties": {
    "iso:country":"DE",
    "sg:address":"Hanauer Landstr. 35",
    "sg:city":"Rodenbach",
    "sg:phone":"+49 6184/52277",
    "sg:postcode":"63517",
    "sg:province":"Hessen",
    "wof:name":"Michael Zabel Rechtsanwalt Und Notar",
    "wof:placetype":"venue"
},
  "geometry": {"coordinates":[9.0161972046,50.1436882019],"type":"Point"}
}