{
  "type": "Feature",
  "properties": {
    "iso:country":"DE",
    "sg:address":"Schulweg 2",
    "sg:city":"Eckenroth",
    "sg:phone":"+49 6724/3470",
    "sg:postcode":"55444",
    "sg:province":"Rheinland-Pfalz",
    "wof:name":"Gaststube Zur Linde",
    "wof:placetype":"venue"
},
  "geometry": {"coordinates":[7.7833619118,49.9249687195],"type":"Point"}
}