{
  "type": "Feature",
  "properties": {
    "iso:country":"DE",
    "sg:address":"Ferdinand-Porsche-Ring 1",
    "sg:city":"Rodgau",
    "sg:phone":"+49 6106/63011",
    "sg:postcode":"63110",
    "sg:province":"Hessen",
    "wof:name":"Dominion Vertriebs- Gmbh",
    "wof:placetype":"venue"
},
  "geometry": {"coordinates":[8.8984069824,50.022808075],"type":"Point"}
}