{
  "type": "Feature",
  "properties": {
    "iso:country":"DE",
    "sg:address":"Podbielskistr. 21-23",
    "sg:city":"Hannover",
    "sg:phone":"+49 511/39040",
    "sg:postcode":"30163",
    "sg:province":"Niedersachsen",
    "wof:name":"Dorint Hotel Hannover",
    "wof:placetype":"venue"
},
  "geometry": {"coordinates":[9.7529315948,52.3902015686],"type":"Point"}
}