{
  "type": "Feature",
  "properties": {
    "iso:country":"DE",
    "sg:address":"An der Liegend 3",
    "sg:city":"M\u00fcnchenbernsdorf",
    "sg:phone":"+49 36604",
    "sg:postcode":"07589",
    "sg:province":"Th\u00fcringen",
    "wof:name":"Hlb Haustechnik",
    "wof:placetype":"venue"
},
  "geometry": {"coordinates":[11.928614,50.815208],"type":"Point"}
}