{
  "type": "Feature",
  "properties": {
    "iso:country":"DE",
    "sg:address":"Wasserwerksweg 20",
    "sg:city":"D\u00fcsseldorf",
    "sg:phone":"+49 211/402448",
    "sg:postcode":"40489",
    "sg:province":"Nordrhein-Westfalen",
    "wof:name":"Karl H. Bachmann Ingenieur",
    "wof:placetype":"venue"
},
  "geometry": {"coordinates":[6.7298049927,51.33618927],"type":"Point"}
}