{
  "type": "Feature",
  "properties": {
    "iso:country":"DE",
    "sg:address":"Hellweg 46 a",
    "sg:city":"D\u00fcsseldorf",
    "sg:phone":"+49 211/2390980",
    "sg:postcode":"40235",
    "sg:province":"Nordrhein-Westfalen",
    "wof:name":"Gabriele Wilquin",
    "wof:placetype":"venue"
},
  "geometry": {"coordinates":[6.8247528076,51.2296295166],"type":"Point"}
}