{
  "type": "Feature",
  "properties": {
    "iso:country":"DE",
    "sg:address":"Akazienstr.21-23",
    "sg:city":"Mannheim",
    "sg:postcode":"68305",
    "sg:province":"Baden-W\u00fcrttemberg",
    "wof:name":"Erfolgskonzept Nr.1",
    "wof:placetype":"venue"
},
  "geometry": {"coordinates":[8.476437,49.515732],"type":"Point"}
}