{
  "type": "Feature",
  "properties": {
    "iso:country":"DE",
    "sg:address":"Georg-August-Zinn-Str. 3",
    "sg:city":"Gro\u00df-Umstadt",
    "sg:phone":"+49 6078/4310",
    "sg:postcode":"64823",
    "sg:province":"Hessen",
    "wof:name":"Pizzeria Italia Inh. Drenka Pomini",
    "wof:placetype":"venue"
},
  "geometry": {"coordinates":[8.9291696548,49.8667411804],"type":"Point"}
}