{
  "type": "Feature",
  "properties": {
    "iso:country":"DE",
    "sg:address":"Kirchstr. 30",
    "sg:city":"Veitsh\u00f6chheim",
    "sg:phone":"+49 931/91540",
    "sg:postcode":"97209",
    "sg:province":"Bayern",
    "wof:name":"Falken-apotheke Wolfgang Argauer E. Kfm.",
    "wof:placetype":"venue"
},
  "geometry": {"coordinates":[9.872656,49.832706],"type":"Point"}
}