{
  "type": "Feature",
  "properties": {
    "iso:country":"DE",
    "sg:address":"Fritz-Baumg\u00e4rtner-Str. 16",
    "sg:city":"Herrieden",
    "sg:phone":"+49 9825",
    "sg:postcode":"91567",
    "sg:province":"Bayern",
    "wof:name":"Firma Gessler-online",
    "wof:placetype":"venue"
},
  "geometry": {"coordinates":[10.5032310486,49.2381744385],"type":"Point"}
}