{
  "type": "Feature",
  "properties": {
    "iso:country":"DE",
    "sg:address":"Br\u00fcder-Grimm-Str. 144",
    "sg:city":"Steinau",
    "sg:phone":"+49 6663/5806",
    "sg:postcode":"36396",
    "sg:province":"Hessen",
    "wof:name":"Steinauer Steinmetz Gmbh",
    "wof:placetype":"venue"
},
  "geometry": {"coordinates":[9.454703331,50.3115272522],"type":"Point"}
}