{
  "type": "Feature",
  "properties": {
    "iso:country":"DE",
    "sg:address":"Im Forstgarten 11",
    "sg:city":"Bad Harzburg",
    "sg:phone":"+49 5322/81326",
    "sg:postcode":"38667",
    "sg:province":"Niedersachsen",
    "wof:name":"Heinz-otto Ganzer Ingenieur",
    "wof:placetype":"venue"
},
  "geometry": {"coordinates":[10.514547348,51.8932609558],"type":"Point"}
}