{
  "type": "Feature",
  "properties": {
    "iso:country":"DE",
    "sg:address":"Heckenweg 1",
    "sg:city":"Winterberg",
    "sg:phone":"+49 2758/208",
    "sg:postcode":"59955",
    "sg:province":"Nordrhein-Westfalen",
    "wof:name":"D. Spies",
    "wof:placetype":"venue"
},
  "geometry": {"coordinates":[8.463005,51.150768],"type":"Point"}
}