{
  "type": "Feature",
  "properties": {
    "iso:country":"DE",
    "sg:address":"Sophie-Charlotten-Str. 92",
    "sg:city":"Berlin",
    "sg:phone":"+49 30/3009670",
    "sg:postcode":"14059",
    "sg:province":"Berlin",
    "wof:name":"Bau Werke Gesellschaft F\u00fcr Konzeption Planung Und",
    "wof:placetype":"venue"
},
  "geometry": {"coordinates":[13.287737,52.515842],"type":"Point"}
}