{
  "type": "Feature",
  "properties": {
    "iso:country":"DE",
    "sg:address":"Gasse 10",
    "sg:city":"Parthenstein",
    "sg:postcode":"04668",
    "sg:province":"Sachsen",
    "wof:name":"Kowa Handelsgenossenschaft D\u00f6beln Eg",
    "wof:placetype":"venue"
},
  "geometry": {"coordinates":[12.66016,51.233761],"type":"Point"}
}