{
  "type": "Feature",
  "properties": {
    "iso:country":"DE",
    "sg:address":"H\u00f6pingen 77",
    "sg:city":"Rosendahl",
    "sg:phone":"+49 2545/249",
    "sg:postcode":"48720",
    "sg:province":"Nordrhein-Westfalen",
    "wof:name":"Heinrich Reers",
    "wof:placetype":"venue"
},
  "geometry": {"coordinates":[7.311261,52.021507],"type":"Point"}
}