{
  "type": "Feature",
  "properties": {
    "iso:country":"DE",
    "sg:address":"Marktweg 112",
    "sg:city":"Sch\u00f6na",
    "sg:phone":"+49 35028/80342",
    "sg:postcode":"01814",
    "sg:province":"Sachsen",
    "wof:name":"Hotel Waldhof",
    "wof:placetype":"venue"
},
  "geometry": {"coordinates":[14.2106304169,50.8719406128],"type":"Point"}
}