{
  "type": "Feature",
  "properties": {
    "iso:country":"DE",
    "sg:address":"Moerser Landstr. 287",
    "sg:city":"Krefeld",
    "sg:phone":"+49 2151/564821",
    "sg:postcode":"47802",
    "sg:province":"Nordrhein-Westfalen",
    "wof:name":"Schroer & Co. Kg",
    "wof:placetype":"venue"
},
  "geometry": {"coordinates":[6.58543,51.374729],"type":"Point"}
}