{
  "type": "Feature",
  "properties": {
    "iso:country":"DE",
    "sg:address":"Kupferbergstr. 2",
    "sg:city":"Immenstaad",
    "sg:phone":"+49 7545/6784",
    "sg:postcode":"88090",
    "sg:province":"Baden-W\u00fcrttemberg",
    "wof:name":"K. Und Elfriede Siebenhaller",
    "wof:placetype":"venue"
},
  "geometry": {"coordinates":[9.350019455,47.6714172363],"type":"Point"}
}