{
  "type": "Feature",
  "properties": {
    "iso:country":"DE",
    "sg:address":"Hauptstr. 60",
    "sg:city":"Warburg",
    "sg:phone":"+49 5641/60700",
    "sg:postcode":"34414",
    "sg:province":"Nordrhein-Westfalen",
    "wof:name":"Brauhaus Kohlschein",
    "wof:placetype":"venue"
},
  "geometry": {"coordinates":[9.1478662491,51.489074707],"type":"Point"}
}