{
  "type": "Feature",
  "properties": {
    "iso:country":"DE",
    "sg:address":"Schulweg 37",
    "sg:city":"Werlte",
    "sg:phone":"+49 5951/9388",
    "sg:postcode":"49757",
    "sg:province":"Niedersachsen",
    "wof:name":"Wilhelm Goldschmidt",
    "wof:placetype":"venue"
},
  "geometry": {"coordinates":[7.6800918579,52.8523368835],"type":"Point"}
}