{
  "type": "Feature",
  "properties": {
    "iso:country":"DE",
    "sg:address":"Kreuzbichl 1",
    "sg:city":"Grainau",
    "sg:phone":"+49 8821/8594",
    "sg:postcode":"82491",
    "sg:province":"Bayern",
    "wof:name":"Consulenz Egerer Gmbh",
    "wof:placetype":"venue"
},
  "geometry": {"coordinates":[11.0390739441,47.4709358215],"type":"Point"}
}