{
  "type": "Feature",
  "properties": {
    "iso:country":"DE",
    "sg:address":"Westerberg 5",
    "sg:city":"Sickte",
    "sg:phone":"+49 5305/1625",
    "sg:postcode":"38173",
    "sg:province":"Niedersachsen",
    "wof:name":"A. Kunze",
    "wof:placetype":"venue"
},
  "geometry": {"coordinates":[10.6284589767,52.2143936157],"type":"Point"}
}