{
  "type": "Feature",
  "properties": {
    "iso:country":"DE",
    "sg:address":"Haigernhof",
    "sg:city":"Griesheim",
    "sg:phone":"+49 6155/2046",
    "sg:postcode":"64347",
    "sg:province":"Hessen",
    "wof:name":"Weilerhof Gmbh & Co. Kg",
    "wof:placetype":"venue"
},
  "geometry": {"coordinates":[8.5574903488,49.8496704102],"type":"Point"}
}