{
  "type": "Feature",
  "properties": {
    "iso:country":"DE",
    "sg:address":"Bergfriedhof 10",
    "sg:city":"T\u00fcbingen",
    "sg:phone":"+49 7071/34963",
    "sg:postcode":"72072",
    "sg:province":"Baden-W\u00fcrttemberg",
    "wof:name":"C. Schmid",
    "wof:placetype":"venue"
},
  "geometry": {"coordinates":[9.070943,48.503872],"type":"Point"}
}