{
  "type": "Feature",
  "properties": {
    "iso:country":"DE",
    "sg:address":"Landgrafenstr. 14",
    "sg:city":"Berlin",
    "sg:phone":"+49 30/2639910",
    "sg:postcode":"10787",
    "sg:province":"Berlin",
    "wof:name":"Eurotrac Contract Management Gmbh",
    "wof:placetype":"venue"
},
  "geometry": {"coordinates":[13.3491916656,52.5053977966],"type":"Point"}
}