{
  "type": "Feature",
  "properties": {
    "iso:country":"DE",
    "sg:address":"Boschach",
    "sg:city":"Ottobeuren",
    "sg:phone":"+49 8332/1599",
    "sg:postcode":"87724",
    "sg:province":"Bayern",
    "wof:name":"Golfshop Des Allg\u00e4uer Golf- Und Land-clubs",
    "wof:placetype":"venue"
},
  "geometry": {"coordinates":[10.321822,47.917206],"type":"Point"}
}