{
  "type": "Feature",
  "properties": {
    "iso:country":"DE",
    "sg:address":"Breniger Str. 20",
    "sg:city":"Swisttal",
    "sg:phone":"+49 4922/543444",
    "sg:postcode":"53913",
    "sg:province":"Nordrhein-Westfalen",
    "wof:name":"Metallbau J. Trimborn Gmbh",
    "wof:placetype":"venue"
},
  "geometry": {"coordinates":[6.92116,50.720699],"type":"Point"}
}