{
  "type": "Feature",
  "properties": {
    "iso:country":"DE",
    "sg:address":"Marktstr. 33",
    "sg:city":"Otterndorf",
    "sg:phone":"+49 4751/6977",
    "sg:postcode":"21762",
    "sg:province":"Niedersachsen",
    "wof:name":"Dapfne Knossos",
    "wof:placetype":"venue"
},
  "geometry": {"coordinates":[8.9043931961,53.8075485229],"type":"Point"}
}