{
  "type": "Feature",
  "properties": {
    "iso:country":"DE",
    "sg:address":"Talstr. 27",
    "sg:city":"Oberraden",
    "sg:phone":"+49 2634/956140",
    "sg:postcode":"56587",
    "sg:province":"Rheinland-Pfalz",
    "wof:name":"Werner Mertesacker",
    "wof:placetype":"venue"
},
  "geometry": {"coordinates":[7.5361170769,50.5478439331],"type":"Point"}
}