{
  "type": "Feature",
  "properties": {
    "iso:country":"DE",
    "sg:address":"Marschtorstr. 10",
    "sg:city":"Dannenberg",
    "sg:phone":"+49 5861/2582",
    "sg:postcode":"29451",
    "sg:province":"Niedersachsen",
    "wof:name":"Helmut Schulz",
    "wof:placetype":"venue"
},
  "geometry": {"coordinates":[11.0981578827,53.1005935669],"type":"Point"}
}