{
  "type": "Feature",
  "properties": {
    "iso:country":"DE",
    "sg:address":"Bildackerstr. 13",
    "sg:city":"Winnenden",
    "sg:phone":"+49 7195/970356",
    "sg:postcode":"71364",
    "sg:province":"Baden-W\u00fcrttemberg",
    "wof:name":"Weingut Konrad H\u00e4usser",
    "wof:placetype":"venue"
},
  "geometry": {"coordinates":[9.4218149185,48.8742294312],"type":"Point"}
}