{
  "type": "Feature",
  "properties": {
    "iso:country":"DE",
    "sg:address":"Burgwalder Str. 1",
    "sg:city":"Diedorf",
    "sg:phone":"+49 8238/1797",
    "sg:postcode":"86420",
    "sg:province":"Bayern",
    "wof:name":"Vereinsgastst\u00e4tte Ssv",
    "wof:placetype":"venue"
},
  "geometry": {"coordinates":[10.7727661133,48.3378486633],"type":"Point"}
}