{
  "type": "Feature",
  "properties": {
    "iso:country":"DE",
    "sg:address":"Unterdorfstr. 19",
    "sg:city":"Oberotterbach",
    "sg:phone":"+49 6342/7170",
    "sg:postcode":"76889",
    "sg:province":"Rheinland-Pfalz",
    "wof:name":"Paul Daum",
    "wof:placetype":"venue"
},
  "geometry": {"coordinates":[7.973484,49.071091],"type":"Point"}
}