{
  "type": "Feature",
  "properties": {
    "iso:country":"DE",
    "sg:address":"Kreuzteilstr. 26",
    "sg:city":"Dinkelscherben",
    "sg:phone":"+49 8292/951957",
    "sg:postcode":"86424",
    "sg:province":"Bayern",
    "wof:name":"Josef K\u00fchn",
    "wof:placetype":"venue"
},
  "geometry": {"coordinates":[10.6294641495,48.3657188416],"type":"Point"}
}