{
  "type": "Feature",
  "properties": {
    "iso:country":"DE",
    "sg:address":"Benninger Str. 7",
    "sg:city":"Freiberg",
    "sg:phone":"+49 7141/72642",
    "sg:postcode":"71691",
    "sg:province":"Baden-W\u00fcrttemberg",
    "wof:name":"Siegmund B\u00fcrkle",
    "wof:placetype":"venue"
},
  "geometry": {"coordinates":[9.2042722702,48.9380645752],"type":"Point"}
}