{
  "type": "Feature",
  "properties": {
    "iso:country":"DE",
    "sg:address":"Vo\u00dfstr. 83",
    "sg:city":"Goch",
    "sg:phone":"+49 2823/7353",
    "sg:postcode":"47574",
    "sg:province":"Nordrhein-Westfalen",
    "wof:name":"Hubert Peters",
    "wof:placetype":"venue"
},
  "geometry": {"coordinates":[6.161677,51.674431],"type":"Point"}
}