{
  "type": "Feature",
  "properties": {
    "iso:country":"DE",
    "sg:address":"Herrenweiher 14",
    "sg:city":"Dietenheim",
    "sg:phone":"+49 7347/7468",
    "sg:postcode":"89165",
    "sg:province":"Baden-W\u00fcrttemberg",
    "wof:name":"Wei\u00dfenberger Bauunternehmung Manfred Wei\u00dfenberger",
    "wof:placetype":"venue"
},
  "geometry": {"coordinates":[10.057905,48.244759],"type":"Point"}
}