{
  "type": "Feature",
  "properties": {
    "iso:country":"DE",
    "sg:address":"Ulmer Hof 3",
    "sg:city":"W\u00fcrzburg",
    "sg:phone":"+49 931/55716",
    "sg:postcode":"97070",
    "sg:province":"Bayern",
    "wof:name":"Jeans-ecke",
    "wof:placetype":"venue"
},
  "geometry": {"coordinates":[9.928683,49.796223],"type":"Point"}
}