{
  "type": "Feature",
  "properties": {
    "iso:country":"DE",
    "sg:address":"F\u00f6hrenwaldstr. 30 a",
    "sg:city":"Wolfratshausen",
    "sg:phone":"+49 8171/63013",
    "sg:postcode":"82515",
    "sg:province":"Bayern",
    "wof:name":"Sturm Hebrock Kantenaleimmaschinen Gmbh",
    "wof:placetype":"venue"
},
  "geometry": {"coordinates":[11.4434347153,47.8952102661],"type":"Point"}
}