{
  "type": "Feature",
  "properties": {
    "iso:country":"DE",
    "sg:address":"Am Dreispitz 1",
    "sg:city":"Binzen",
    "sg:phone":"+49 7621/96980",
    "sg:postcode":"79589",
    "sg:province":"Baden-W\u00fcrttemberg",
    "wof:name":"Reisser Gmbh",
    "wof:placetype":"venue"
},
  "geometry": {"coordinates":[7.6091809273,47.6258010864],"type":"Point"}
}