{
  "type": "Feature",
  "properties": {
    "iso:country":"DE",
    "sg:address":"Ringstr. 4",
    "sg:city":"Oberriexingen",
    "sg:phone":"+49 7042/92510",
    "sg:postcode":"71739",
    "sg:province":"Baden-W\u00fcrttemberg",
    "wof:name":"Roller & Fischer Gmbh",
    "wof:placetype":"venue"
},
  "geometry": {"coordinates":[9.0221881866,48.9332504272],"type":"Point"}
}