{
  "type": "Feature",
  "properties": {
    "iso:country":"DE",
    "sg:address":"Sperberweg",
    "sg:city":"M\u00f6hnesee",
    "sg:phone":"+49 2924/993250",
    "sg:postcode":"59519",
    "sg:province":"Nordrhein-Westfalen",
    "wof:name":"Amaris Software- Entwicklungsges. Mbh",
    "wof:placetype":"venue"
},
  "geometry": {"coordinates":[8.121019,51.495739],"type":"Point"}
}