{
  "type": "Feature",
  "properties": {
    "iso:country":"DE",
    "sg:address":"Hauptstr. 2",
    "sg:city":"Gimritz",
    "sg:phone":"+49 34607/20494",
    "sg:postcode":"06198",
    "sg:province":"Sachsen-Anhalt",
    "wof:name":"Hartmut Lichtenstein",
    "wof:placetype":"venue"
},
  "geometry": {"coordinates":[11.869286,51.565269],"type":"Point"}
}