{
  "type": "Feature",
  "properties": {
    "iso:country":"DE",
    "sg:address":"Bismarckstr. 2",
    "sg:city":"Trossingen",
    "sg:phone":"+49 7425/5220",
    "sg:postcode":"78647",
    "sg:province":"Baden-W\u00fcrttemberg",
    "wof:name":"Gerhard B\u00f6ck",
    "wof:placetype":"venue"
},
  "geometry": {"coordinates":[8.6409339905,48.0768051147],"type":"Point"}
}