{
  "type": "Feature",
  "properties": {
    "iso:country":"DE",
    "sg:address":"Johannisgraben 8",
    "sg:city":"Altenburg",
    "sg:phone":"+49 3447/500521",
    "sg:postcode":"04600",
    "sg:province":"Th\u00fcringen",
    "wof:name":"Signal Versicherung Dieter Br\u00e4utigam",
    "wof:placetype":"venue"
},
  "geometry": {"coordinates":[12.4289178848,50.9858169556],"type":"Point"}
}