{
  "type": "Feature",
  "properties": {
    "iso:country":"DE",
    "sg:address":"Freier Blick 22",
    "sg:city":"Naumburg",
    "sg:postcode":"06618",
    "sg:province":"Sachsen-Anhalt",
    "wof:name":"Dr. Med. Birgit Metzke",
    "wof:placetype":"venue"
},
  "geometry": {"coordinates":[11.792749,51.148567],"type":"Point"}
}