{
  "type": "Feature",
  "properties": {
    "iso:country":"DE",
    "sg:address":"Kirchgasse 7",
    "sg:city":"Dischingen",
    "sg:phone":"+49 7327/5770",
    "sg:postcode":"89561",
    "sg:province":"Baden-W\u00fcrttemberg",
    "wof:name":"Franz Josef Gr\u00e4ter",
    "wof:placetype":"venue"
},
  "geometry": {"coordinates":[10.362142,48.69751],"type":"Point"}
}