{
  "type": "Feature",
  "properties": {
    "iso:country":"DE",
    "sg:address":"Friedrichstr. 8",
    "sg:city":"Badenweiler",
    "sg:phone":"+49 7632/5104",
    "sg:postcode":"79410",
    "sg:province":"Baden-W\u00fcrttemberg",
    "wof:name":"Villa Martha",
    "wof:placetype":"venue"
},
  "geometry": {"coordinates":[7.6674480438,47.7996368408],"type":"Point"}
}