{
  "type": "Feature",
  "properties": {
    "iso:country":"DE",
    "sg:address":"St.-Vitus-Str. 7",
    "sg:city":"Rehling",
    "sg:phone":"+49 8237/6219",
    "sg:postcode":"86508",
    "sg:province":"Bayern",
    "wof:name":"Kaminbau Kr\u00f6ll Gmbh",
    "wof:placetype":"venue"
},
  "geometry": {"coordinates":[10.9175252914,48.4865455627],"type":"Point"}
}