{
  "type": "Feature",
  "properties": {
    "iso:country":"DE",
    "sg:address":"Von-Kahr-Str. 10",
    "sg:city":"M\u00fcnchen",
    "sg:phone":"+49 89/1409379",
    "sg:postcode":"80997",
    "sg:province":"Bayern",
    "wof:name":"Gerhard Daum",
    "wof:placetype":"venue"
},
  "geometry": {"coordinates":[11.4859857559,48.1792564392],"type":"Point"}
}