{
  "type": "Feature",
  "properties": {
    "iso:country":"DE",
    "sg:address":"Scheffershof 4",
    "sg:city":"Leverkusen",
    "sg:postcode":"51375",
    "sg:province":"Nordrhein-Westfalen",
    "wof:name":"Isaplan Ingenieur Gmbh",
    "wof:placetype":"venue"
},
  "geometry": {"coordinates":[7.0783891678,51.0317649841],"type":"Point"}
}