{
  "type": "Feature",
  "properties": {
    "iso:country":"DE",
    "sg:address":"Bahnhofstr. 41",
    "sg:city":"Neufahrn",
    "sg:phone":"+49 8165/4638",
    "sg:postcode":"85375",
    "sg:province":"Bayern",
    "wof:name":"Georg Stegschuster",
    "wof:placetype":"venue"
},
  "geometry": {"coordinates":[11.661454,48.31881],"type":"Point"}
}