{
  "type": "Feature",
  "properties": {
    "iso:country":"DE",
    "sg:address":"Segringer Str. 46",
    "sg:city":"Dinkelsb\u00fchl",
    "sg:phone":"+49 9851/2306",
    "sg:postcode":"91550",
    "sg:province":"Bayern",
    "wof:name":"Merz Verwaltungs- Gmbh",
    "wof:placetype":"venue"
},
  "geometry": {"coordinates":[10.3150997162,49.0689201355],"type":"Point"}
}