{
  "type": "Feature",
  "properties": {
    "iso:country":"DE",
    "sg:address":"Marktplatz 33",
    "sg:city":"Perlesreut",
    "sg:phone":"+49 8555/8413",
    "sg:postcode":"94157",
    "sg:province":"Bayern",
    "wof:name":"Josef Christoph",
    "wof:placetype":"venue"
},
  "geometry": {"coordinates":[13.440584,48.779419],"type":"Point"}
}