{
  "type": "Feature",
  "properties": {
    "iso:country":"DE",
    "sg:address":"Bahnhofstr. 50",
    "sg:city":"Kolkwitz",
    "sg:phone":"+49 355/28649",
    "sg:postcode":"03099",
    "sg:province":"Brandenburg",
    "wof:name":"Hans-j\u00fcrgen Noack",
    "wof:placetype":"venue"
},
  "geometry": {"coordinates":[14.243227,51.748665],"type":"Point"}
}