{
  "type": "Feature",
  "properties": {
    "iso:country":"DE",
    "sg:address":"Zum Selsberg 43",
    "sg:city":"Beverungen",
    "sg:phone":"+49 5273/1242",
    "sg:postcode":"37688",
    "sg:province":"Nordrhein-Westfalen",
    "wof:name":"C. Hake",
    "wof:placetype":"venue"
},
  "geometry": {"coordinates":[9.368853,51.675606],"type":"Point"}
}