{
  "type": "Feature",
  "properties": {
    "iso:country":"DE",
    "sg:address":"Hauptstr. 15",
    "sg:city":"B\u00e4rnsdorf",
    "sg:phone":"+49 35207/81778",
    "sg:postcode":"01471",
    "sg:province":"Sachsen",
    "wof:name":"Dieter Hempel",
    "wof:placetype":"venue"
},
  "geometry": {"coordinates":[13.723475,51.168346],"type":"Point"}
}