{
  "type": "Feature",
  "properties": {
    "iso:country":"DE",
    "sg:address":"Adolf-Oberl\u00e4nder-Weg 17",
    "sg:city":"M\u00fcnchen",
    "sg:phone":"+49 89/918701",
    "sg:postcode":"81927",
    "sg:province":"Bayern",
    "wof:name":"Gerhard Steuer Steuerberater",
    "wof:placetype":"venue"
},
  "geometry": {"coordinates":[11.6328315735,48.148273468],"type":"Point"}
}