{
  "type": "Feature",
  "properties": {
    "iso:country":"DE",
    "sg:address":"Baarstr. 112",
    "sg:city":"Iserlohn",
    "sg:phone":"+49 2371/978080",
    "sg:postcode":"58636",
    "sg:province":"Nordrhein-Westfalen",
    "wof:name":"Ropasan Armaturen Gmbh",
    "wof:placetype":"venue"
},
  "geometry": {"coordinates":[7.6926431656,51.394317627],"type":"Point"}
}