{
  "type": "Feature",
  "properties": {
    "iso:country":"DE",
    "sg:address":"Bornstr. 48",
    "sg:city":"Dortmund",
    "sg:phone":"+49 231/831083",
    "sg:postcode":"44145",
    "sg:province":"Nordrhein-Westfalen",
    "wof:name":"Helmut Frage",
    "wof:placetype":"venue"
},
  "geometry": {"coordinates":[7.469579,51.520115],"type":"Point"}
}