{
  "type": "Feature",
  "properties": {
    "iso:country":"DE",
    "sg:address":"Dunlopstr. 51",
    "sg:city":"Bielefeld",
    "sg:phone":"+49 5205/950548",
    "sg:postcode":"33689",
    "sg:province":"Nordrhein-Westfalen",
    "wof:name":"Schlingmann Spedition Gmbh",
    "wof:placetype":"venue"
},
  "geometry": {"coordinates":[8.5664081573,51.9394416809],"type":"Point"}
}