{
  "type": "Feature",
  "properties": {
    "iso:country":"DE",
    "sg:address":"Edmund-Lang-Str. 27",
    "sg:city":"Babenhausen",
    "sg:postcode":"64832",
    "sg:province":"Hessen",
    "wof:name":"Mso Schleiftechnik Gmbh",
    "wof:placetype":"venue"
},
  "geometry": {"coordinates":[8.954244,49.953777],"type":"Point"}
}