{
  "type": "Feature",
  "properties": {
    "iso:country":"DE",
    "sg:address":"Barbarastr. 1",
    "sg:city":"Siegelsbach",
    "sg:phone":"+49 7264/3878",
    "sg:postcode":"74936",
    "sg:province":"Baden-W\u00fcrttemberg",
    "wof:name":"C. Binnig",
    "wof:placetype":"venue"
},
  "geometry": {"coordinates":[9.083895,49.272358],"type":"Point"}
}