{
  "type": "Feature",
  "properties": {
    "iso:country":"DE",
    "sg:address":"Noldestr. 5-7",
    "sg:city":"Velbert",
    "sg:phone":"+49 2051/28120",
    "sg:postcode":"42551",
    "sg:province":"Nordrhein-Westfalen",
    "wof:name":"Erich Schlemper Gesch\u00e4ftsf\u00fchrungs-gmbh",
    "wof:placetype":"venue"
},
  "geometry": {"coordinates":[7.049247,51.336308],"type":"Point"}
}