{
  "type": "Feature",
  "properties": {
    "iso:country":"DE",
    "sg:address":"Kaspersweg 146",
    "sg:city":"Oldenburg",
    "sg:phone":"+49 441/53044",
    "sg:postcode":"26131",
    "sg:province":"Niedersachsen",
    "wof:name":"B\u00f6lts-bauunternehmen Gmbh",
    "wof:placetype":"venue"
},
  "geometry": {"coordinates":[8.160498,53.130798],"type":"Point"}
}