{
  "type": "Feature",
  "properties": {
    "iso:country":"DE",
    "sg:address":"Zum Vosh\u00f6vel 22",
    "sg:city":"Hamminkeln",
    "sg:phone":"+49 2856/2546",
    "sg:postcode":"46499",
    "sg:province":"Nordrhein-Westfalen",
    "wof:name":"Helmut Mosch\u00fcring",
    "wof:placetype":"venue"
},
  "geometry": {"coordinates":[6.705934,51.723164],"type":"Point"}
}