{
  "type": "Feature",
  "properties": {
    "iso:country":"DE",
    "sg:address":"Albert-Schneider-Str. 7",
    "sg:city":"Blankenburg",
    "sg:phone":"+49 3944/980357",
    "sg:postcode":"38889",
    "sg:province":"Sachsen-Anhalt",
    "wof:name":"Vdse Gmbh-verwaltungsdienstl. Sozialer Einrichtungen Gmbh",
    "wof:placetype":"venue"
},
  "geometry": {"coordinates":[10.9575967789,51.7938766479],"type":"Point"}
}