{
  "type": "Feature",
  "properties": {
    "iso:country":"DE",
    "sg:address":"Concordienstr. 1",
    "sg:city":"Wuppertal",
    "sg:phone":"+49 202/597172",
    "sg:postcode":"42275",
    "sg:province":"Nordrhein-Westfalen",
    "wof:name":"Helmut Klamra",
    "wof:placetype":"venue"
},
  "geometry": {"coordinates":[7.2014889717,51.2714996338],"type":"Point"}
}