{
  "type": "Feature",
  "properties": {
    "iso:country":"DE",
    "sg:address":"Falkensteinstr. 52",
    "sg:city":"Kassel",
    "sg:phone":"+49 561/41241",
    "sg:postcode":"34132",
    "sg:province":"Hessen",
    "wof:name":"Heinz-j\u00fcrgen R\u00f6der",
    "wof:placetype":"venue"
},
  "geometry": {"coordinates":[9.444828,51.272648],"type":"Point"}
}