{
  "type": "Feature",
  "properties": {
    "iso:country":"DE",
    "sg:address":"Vorgebirgstr. 149",
    "sg:city":"K\u00f6ln",
    "sg:phone":"+49 221/365504",
    "sg:postcode":"50969",
    "sg:province":"Nordrhein-Westfalen",
    "wof:name":"Karl Langel",
    "wof:placetype":"venue"
},
  "geometry": {"coordinates":[6.945943,50.911762],"type":"Point"}
}