{
  "type": "Feature",
  "properties": {
    "iso:country":"DE",
    "sg:address":"Ladestr. 2",
    "sg:city":"Stadland",
    "sg:phone":"+49 4737/1216",
    "sg:postcode":"26936",
    "sg:province":"Niedersachsen",
    "wof:name":"Raiffeisen Warengenossenschaft Egmbh",
    "wof:placetype":"venue"
},
  "geometry": {"coordinates":[8.353763,53.402],"type":"Point"}
}