{
  "type": "Feature",
  "properties": {
    "iso:country":"DE",
    "sg:address":"Am Sachsenring 11 b",
    "sg:city":"Hohenstein-Ernstthal",
    "sg:postcode":"09337",
    "sg:province":"Sachsen",
    "wof:name":"Heyne Holz Holzmarkt Am Sachsenring E. K.",
    "wof:placetype":"venue"
},
  "geometry": {"coordinates":[12.6719512939,50.8003807068],"type":"Point"}
}