{
  "type": "Feature",
  "properties": {
    "iso:country":"DE",
    "sg:address":"Obergasse 4",
    "sg:city":"Idstein",
    "sg:phone":"+49 6126/54168",
    "sg:postcode":"65510",
    "sg:province":"Hessen",
    "wof:name":"Deutsches Haus",
    "wof:placetype":"venue"
},
  "geometry": {"coordinates":[8.2705202103,50.2204208374],"type":"Point"}
}