{
  "type": "Feature",
  "properties": {
    "iso:country":"DE",
    "sg:address":"Bruck 15",
    "sg:city":"Hohenfels",
    "sg:phone":"+49 7557/92100",
    "sg:postcode":"78355",
    "sg:province":"Baden-W\u00fcrttemberg",
    "wof:name":"Ivm Industrievertretungen Meyer Gmbh",
    "wof:placetype":"venue"
},
  "geometry": {"coordinates":[9.1062507629,47.8807754517],"type":"Point"}
}