{
  "type": "Feature",
  "properties": {
    "iso:country":"DE",
    "sg:address":"Wienhellerweg 13",
    "sg:city":"Waldbr\u00f6l",
    "sg:phone":"+49 2291/912155",
    "sg:postcode":"51545",
    "sg:province":"Nordrhein-Westfalen",
    "wof:name":"Ehewunsch Aus Brasilien Eliene",
    "wof:placetype":"venue"
},
  "geometry": {"coordinates":[7.618739,50.883896],"type":"Point"}
}