{
  "type": "Feature",
  "properties": {
    "iso:country":"DE",
    "sg:address":"Ludscheidtstr. 95",
    "sg:city":"Essen",
    "sg:phone":"+49 201/482126",
    "sg:postcode":"45257",
    "sg:province":"Nordrhein-Westfalen",
    "wof:name":"Dieter Todt",
    "wof:placetype":"venue"
},
  "geometry": {"coordinates":[7.050825,51.37241],"type":"Point"}
}