{
  "type": "Feature",
  "properties": {
    "iso:country":"DE",
    "sg:address":"Odernheimer Str. 112",
    "sg:city":"Berlin",
    "sg:phone":"+49 30/6598236",
    "sg:postcode":"12559",
    "sg:province":"Berlin",
    "wof:name":"Werner Tiedke",
    "wof:placetype":"venue"
},
  "geometry": {"coordinates":[13.6780223846,52.4219818115],"type":"Point"}
}