{
  "type": "Feature",
  "properties": {
    "iso:country":"DE",
    "sg:address":"Hanne N\u00fcte 21",
    "sg:city":"Berlin",
    "sg:phone":"+49 30/6063787",
    "sg:postcode":"12359",
    "sg:province":"Berlin",
    "wof:name":"Gerhard Martens",
    "wof:placetype":"venue"
},
  "geometry": {"coordinates":[13.451335907,52.4510231018],"type":"Point"}
}