{
  "type": "Feature",
  "properties": {
    "iso:country":"DE",
    "sg:address":"Ewaldstr. 33",
    "sg:city":"Herten",
    "sg:phone":"+49 2366/31677",
    "sg:postcode":"45699",
    "sg:province":"Nordrhein-Westfalen",
    "wof:name":"Blumen-risse Gmbh & Co. Kg",
    "wof:placetype":"venue"
},
  "geometry": {"coordinates":[7.139422,51.594318],"type":"Point"}
}