{
  "type": "Feature",
  "properties": {
    "iso:country":"DE",
    "sg:address":"Kl\u00f6tzlm\u00fcllerstr. 42",
    "sg:city":"Landshut",
    "sg:phone":"+49 871/69061",
    "sg:postcode":"84034",
    "sg:province":"Bayern",
    "wof:name":"K\u00f6hler & Partner Architekten",
    "wof:placetype":"venue"
},
  "geometry": {"coordinates":[12.135824,48.533901],"type":"Point"}
}