{
  "type": "Feature",
  "properties": {
    "iso:country":"DE",
    "sg:address":"Am Waltenberg 34",
    "sg:city":"Winterberg",
    "sg:phone":"+49 2981/1876",
    "sg:postcode":"59955",
    "sg:province":"Nordrhein-Westfalen",
    "wof:name":"Tanzlokal Tiffanys",
    "wof:placetype":"venue"
},
  "geometry": {"coordinates":[8.5209598541,51.1916542053],"type":"Point"}
}