{
  "type": "Feature",
  "properties": {
    "iso:country":"DE",
    "sg:address":"Schulstr. 11",
    "sg:city":"Pei\u00dfen",
    "sg:phone":"+49 345/564010",
    "sg:postcode":"06188",
    "sg:province":"Sachsen-Anhalt",
    "wof:name":"Hagos Verbund Deutscher Kachelofen - Und Luft -",
    "wof:placetype":"venue"
},
  "geometry": {"coordinates":[12.059129715,51.503276825],"type":"Point"}
}