{
  "type": "Feature",
  "properties": {
    "iso:country":"DE",
    "sg:address":"Am Herrengarten 1",
    "sg:city":"Bielefeld",
    "sg:phone":"+49 521/875965",
    "sg:postcode":"33611",
    "sg:province":"Nordrhein-Westfalen",
    "wof:name":"Wemh\u00f6ner Fleischerei Inh. Uwe Mayer",
    "wof:placetype":"venue"
},
  "geometry": {"coordinates":[8.5475559235,52.0578384399],"type":"Point"}
}