{
  "type": "Feature",
  "properties": {
    "iso:country":"DE",
    "sg:address":"Bahnhofstr. 3",
    "sg:city":"Uhingen",
    "sg:phone":"+49 7161/37877",
    "sg:postcode":"73066",
    "sg:province":"Baden-W\u00fcrttemberg",
    "wof:name":"Allfrisch",
    "wof:placetype":"venue"
},
  "geometry": {"coordinates":[9.5836172104,48.7072677612],"type":"Point"}
}