{
  "type": "Feature",
  "properties": {
    "iso:country":"DE",
    "sg:address":"Kunoweg 6",
    "sg:city":"Stuttgart",
    "sg:phone":"+49 711/538451",
    "sg:postcode":"70378",
    "sg:province":"Baden-W\u00fcrttemberg",
    "wof:name":"S. Bosch",
    "wof:placetype":"venue"
},
  "geometry": {"coordinates":[9.2344379425,48.8458747864],"type":"Point"}
}