{
  "type": "Feature",
  "properties": {
    "iso:country":"DE",
    "sg:address":"Zimmerweg",
    "sg:city":"L\u00f6dderrath",
    "sg:phone":"+49 6889/856593",
    "sg:postcode":"68897",
    "wof:name":"Kreditkarte Ohne Bonit\u00e4tspr\u00fcfung",
    "wof:placetype":"venue"
},
  "geometry": {"coordinates":[-96.1653671265,17.3819007874],"type":"Point"}
}