{
  "type": "Feature",
  "properties": {
    "iso:country":"DE",
    "sg:address":"Falkenstr. 19/2",
    "sg:city":"Ostfildern",
    "sg:phone":"+49 7158/60760",
    "sg:postcode":"73760",
    "sg:province":"Baden-W\u00fcrttemberg",
    "wof:name":"Klaus Allinger",
    "wof:placetype":"venue"
},
  "geometry": {"coordinates":[9.2557277679,48.7057533264],"type":"Point"}
}