{
  "type": "Feature",
  "properties": {
    "iso:country":"DE",
    "sg:address":"Pariser Str. 32",
    "sg:city":"M\u00fcnchen",
    "sg:phone":"+49 89/4487494",
    "sg:postcode":"81667",
    "sg:province":"Bayern",
    "wof:name":"East Side Music Second Hand Gmbh",
    "wof:placetype":"venue"
},
  "geometry": {"coordinates":[11.5992097855,48.1275978088],"type":"Point"}
}