{
  "type": "Feature",
  "properties": {
    "iso:country":"DE",
    "sg:address":"Merziger Str. 1",
    "sg:city":"Losheim",
    "sg:phone":"+49 6872/8739",
    "sg:postcode":"66679",
    "sg:province":"Saarland",
    "wof:name":"B. Demetz",
    "wof:placetype":"venue"
},
  "geometry": {"coordinates":[6.7446050644,49.5081138611],"type":"Point"}
}