{
  "type": "Feature",
  "properties": {
    "iso:country":"DE",
    "sg:address":"Im S\u00e4nder 12",
    "sg:city":"Bad Ditzenbach",
    "sg:phone":"+49 7335/7688",
    "sg:postcode":"73342",
    "sg:province":"Baden-W\u00fcrttemberg",
    "wof:name":"Alb-grill Imbi\u00df",
    "wof:placetype":"venue"
},
  "geometry": {"coordinates":[9.67370224,48.5788421631],"type":"Point"}
}