{
  "type": "Feature",
  "properties": {
    "iso:country":"DE",
    "sg:address":"Lautertalstr. 10",
    "sg:city":"M\u00fcnsingen",
    "sg:phone":"+49 7381/2147",
    "sg:postcode":"72525",
    "sg:province":"Baden-W\u00fcrttemberg",
    "wof:name":"Restaurant Wiesental",
    "wof:placetype":"venue"
},
  "geometry": {"coordinates":[9.4898967743,48.4102592468],"type":"Point"}
}