{
  "type": "Feature",
  "properties": {
    "iso:country":"DE",
    "sg:address":"Gudesstr. 5",
    "sg:city":"Uelzen",
    "sg:phone":"+49 581/30976",
    "sg:postcode":"29525",
    "sg:province":"Niedersachsen",
    "wof:name":"Rossmann Drogeriemarkt",
    "wof:placetype":"venue"
},
  "geometry": {"coordinates":[10.56108,52.965103],"type":"Point"}
}