{
  "type": "Feature",
  "properties": {
    "iso:country":"DE",
    "sg:address":"Camerariusstr. 1",
    "sg:city":"N\u00fcrnberg",
    "sg:phone":"+49 911/222488",
    "sg:postcode":"90443",
    "sg:province":"Bayern",
    "wof:name":"Rock-keller",
    "wof:placetype":"venue"
},
  "geometry": {"coordinates":[11.069338,49.445557],"type":"Point"}
}