{
  "type": "Feature",
  "properties": {
    "iso:country":"DE",
    "sg:address":"Sundische Str. 11",
    "sg:city":"Barth",
    "sg:postcode":"18356",
    "sg:province":"Mecklenburg-Vorpommern",
    "wof:name":"Hbb Holzbau Barth Gmbh & Co. Kg",
    "wof:placetype":"venue"
},
  "geometry": {"coordinates":[12.7267227173,54.3643684387],"type":"Point"}
}