{
  "type": "Feature",
  "properties": {
    "iso:country":"DE",
    "sg:address":"Gartenstr. 34",
    "sg:city":"Lennestadt",
    "sg:phone":"+49 2723/95590",
    "sg:postcode":"57368",
    "sg:province":"Nordrhein-Westfalen",
    "wof:name":"Tob\u00fcren Verwaltungs Gmbh",
    "wof:placetype":"venue"
},
  "geometry": {"coordinates":[8.07546,51.106014],"type":"Point"}
}