{
  "type": "Feature",
  "properties": {
    "iso:country":"DE",
    "sg:address":"Binger Str. 3",
    "sg:city":"Boppard",
    "sg:phone":"+49 6742/60338",
    "sg:postcode":"56154",
    "sg:province":"Rheinland-Pfalz",
    "wof:name":"Antoniusstube",
    "wof:placetype":"venue"
},
  "geometry": {"coordinates":[7.6335501671,50.2056655884],"type":"Point"}
}