{
  "type": "Feature",
  "properties": {
    "iso:country":"DE",
    "sg:address":"Hauptstr. 24",
    "sg:city":"Essen",
    "sg:phone":"+49 2054/15016",
    "sg:postcode":"45219",
    "sg:province":"Nordrhein-Westfalen",
    "wof:name":"W. Herrmann",
    "wof:placetype":"venue"
},
  "geometry": {"coordinates":[6.9436798096,51.3625030518],"type":"Point"}
}