{
  "type": "Feature",
  "properties": {
    "iso:country":"DE",
    "sg:address":"Reichenhaller Str. 30a",
    "sg:city":"M\u00fcnchen",
    "sg:phone":"+49 89/6915063",
    "sg:postcode":"81547",
    "sg:province":"Bayern",
    "wof:name":"Media Concept Gesellschaft F\u00fcr Werbung Mbh",
    "wof:placetype":"venue"
},
  "geometry": {"coordinates":[11.5698127747,48.1066551208],"type":"Point"}
}