{
  "type": "Feature",
  "properties": {
    "iso:country":"DE",
    "sg:address":"Bahnhofstr. 125 a",
    "sg:city":"Biesenthal",
    "sg:phone":"+49 3337/3351",
    "sg:postcode":"16359",
    "sg:province":"Brandenburg",
    "wof:name":"Wegweiser F\u00fcr Kapitalaufbau Firzlaff Und Jeschke",
    "wof:placetype":"venue"
},
  "geometry": {"coordinates":[13.6590089798,52.7601852417],"type":"Point"}
}