{
  "type": "Feature",
  "properties": {
    "iso:country":"DE",
    "sg:address":"Ingendorfer Weg 30",
    "sg:city":"K\u00f6ln",
    "sg:phone":"+49 221/508634",
    "sg:postcode":"50829",
    "sg:province":"Nordrhein-Westfalen",
    "wof:name":"Rolf Rausch",
    "wof:placetype":"venue"
},
  "geometry": {"coordinates":[6.8611340523,50.9801597595],"type":"Point"}
}