{
  "type": "Feature",
  "properties": {
    "iso:country":"DE",
    "sg:address":"Glockenstr. 6",
    "sg:city":"D\u00fcsseldorf",
    "sg:phone":"+49 211/638500",
    "sg:postcode":"40476",
    "sg:province":"Nordrhein-Westfalen",
    "wof:name":"M.k.l. Chauffeur- Und Limousinen-service E. K.",
    "wof:placetype":"venue"
},
  "geometry": {"coordinates":[6.7840957642,51.2450370789],"type":"Point"}
}