{
  "type": "Feature",
  "properties": {
    "iso:country":"DE",
    "sg:address":"Am Wall 12",
    "sg:city":"M\u00fcnster",
    "sg:phone":"+49 2533/1595",
    "sg:postcode":"48161",
    "sg:province":"Nordrhein-Westfalen",
    "wof:name":"Harry G\u00fcnther",
    "wof:placetype":"venue"
},
  "geometry": {"coordinates":[7.5617909431,51.9944572449],"type":"Point"}
}