{
  "type": "Feature",
  "properties": {
    "iso:country":"DE",
    "sg:address":"Sennfelder Weg 7",
    "sg:city":"Birkenfeld",
    "sg:phone":"+49 9398/341",
    "sg:postcode":"97834",
    "sg:province":"Bayern",
    "wof:name":"Bernd Stollberger",
    "wof:placetype":"venue"
},
  "geometry": {"coordinates":[9.7237854004,49.8735771179],"type":"Point"}
}