{
  "type": "Feature",
  "properties": {
    "iso:country":"DE",
    "sg:address":"Aubinger Str. 47",
    "sg:city":"M\u00fcnchen",
    "sg:phone":"+49 89/8344051",
    "sg:postcode":"81243",
    "sg:province":"Bayern",
    "wof:name":"Reiseb\u00fcro Am Westkreuz Gmbh",
    "wof:placetype":"venue"
},
  "geometry": {"coordinates":[11.4422826767,48.1489372253],"type":"Point"}
}