{
  "type": "Feature",
  "properties": {
    "iso:country":"DE",
    "sg:address":"Friesenheimer Hauptstr. 85",
    "sg:city":"Friesenheim",
    "sg:phone":"+49 7821/67129",
    "sg:postcode":"77948",
    "sg:province":"Baden-W\u00fcrttemberg",
    "wof:name":"Eddy B\u00e4hr",
    "wof:placetype":"venue"
},
  "geometry": {"coordinates":[7.8840298653,48.3736343384],"type":"Point"}
}