{
  "type": "Feature",
  "properties": {
    "iso:country":"DE",
    "sg:address":"Bahnhofstr. 1",
    "sg:city":"Bad Honnef",
    "sg:phone":"+49 2224/4426",
    "sg:postcode":"53604",
    "sg:province":"Nordrhein-Westfalen",
    "wof:name":"Josefa Guthy",
    "wof:placetype":"venue"
},
  "geometry": {"coordinates":[7.2249622345,50.6443939209],"type":"Point"}
}