{
  "type": "Feature",
  "properties": {
    "iso:country":"DE",
    "sg:address":"Mailling 4",
    "sg:city":"Tuntenhausen",
    "sg:phone":"+49 8065/1717",
    "sg:postcode":"83104",
    "sg:province":"Bayern",
    "wof:name":"Ignaz Bachmayr Gmbh & Co. Kg",
    "wof:placetype":"venue"
},
  "geometry": {"coordinates":[11.979477,47.938271],"type":"Point"}
}