{
  "type": "Feature",
  "properties": {
    "iso:country":"DE",
    "sg:address":"Langenbochumer Str. 449",
    "sg:city":"Herten",
    "sg:phone":"+49 209/620722",
    "sg:postcode":"45701",
    "sg:province":"Nordrhein-Westfalen",
    "wof:name":"Gastst\u00e4tte Martina Erkan",
    "wof:placetype":"venue"
},
  "geometry": {"coordinates":[7.0923571587,51.6016578674],"type":"Point"}
}