{
  "type": "Feature",
  "properties": {
    "iso:country":"DE",
    "sg:address":"Traberhofstr. 12",
    "sg:city":"Rosenheim",
    "sg:postcode":"83026",
    "sg:province":"Bayern",
    "wof:name":"Odlo Sports Gmbh",
    "wof:placetype":"venue"
},
  "geometry": {"coordinates":[12.1282186508,47.8395957947],"type":"Point"}
}