{
  "type": "Feature",
  "properties": {
    "iso:country":"DE",
    "sg:address":"H\u00f6chster Str. 7a",
    "sg:city":"Breuberg",
    "sg:phone":"+49 6163/4584",
    "sg:postcode":"64747",
    "sg:province":"Hessen",
    "wof:name":"Anni Linke",
    "wof:placetype":"venue"
},
  "geometry": {"coordinates":[9.0174207687,49.8182487488],"type":"Point"}
}