{
  "type": "Feature",
  "properties": {
    "iso:country":"DE",
    "sg:address":"Dr.-Miedel-Str. 16 a",
    "sg:city":"Memmingen",
    "sg:phone":"+49 8331/965726",
    "sg:postcode":"87700",
    "sg:province":"Bayern",
    "wof:name":"Fritz Jende Masseur",
    "wof:placetype":"venue"
},
  "geometry": {"coordinates":[10.165948,47.987812],"type":"Point"}
}