{
  "type": "Feature",
  "properties": {
    "iso:country":"DE",
    "sg:address":"Kirchheimer Str. 27",
    "sg:city":"Holzmaden",
    "sg:phone":"+49 7023/5499",
    "sg:postcode":"73271",
    "sg:province":"Baden-W\u00fcrttemberg",
    "wof:name":"Lutz Kg",
    "wof:placetype":"venue"
},
  "geometry": {"coordinates":[9.5135,48.634197],"type":"Point"}
}