{
  "type": "Feature",
  "properties": {
    "iso:country":"DE",
    "sg:address":"Rudolf-Schmidt-Str. 12",
    "sg:city":"Dinkelsb\u00fchl",
    "sg:phone":"+49 9851/9970",
    "sg:postcode":"91550",
    "sg:province":"Bayern",
    "wof:name":"Esbe Plastic Gmbh",
    "wof:placetype":"venue"
},
  "geometry": {"coordinates":[10.336104,49.06863],"type":"Point"}
}