{
  "type": "Feature",
  "properties": {
    "iso:country":"DE",
    "sg:address":"Hauptstr. 67",
    "sg:city":"N\u00f6da",
    "sg:postcode":"99195",
    "sg:province":"Th\u00fcringen",
    "wof:name":"Ehnes",
    "wof:placetype":"venue"
},
  "geometry": {"coordinates":[11.0199966431,51.0676574707],"type":"Point"}
}