{
  "type": "Feature",
  "properties": {
    "iso:country":"DE",
    "sg:address":"Meisenweg 10",
    "sg:city":"Neuenhaus",
    "sg:phone":"+49 5941/4414",
    "sg:postcode":"49828",
    "sg:province":"Niedersachsen",
    "wof:name":"Sloot Transport Gmbh",
    "wof:placetype":"venue"
},
  "geometry": {"coordinates":[6.9826908112,52.4851074219],"type":"Point"}
}