{
  "type": "Feature",
  "properties": {
    "iso:country":"DE",
    "sg:address":"Gartenstr. 63",
    "sg:city":"Hessigheim",
    "sg:phone":"+49 7143/811316",
    "sg:postcode":"74394",
    "sg:province":"Baden-W\u00fcrttemberg",
    "wof:name":"Karl N\u00e4gele",
    "wof:placetype":"venue"
},
  "geometry": {"coordinates":[9.190203,48.994984],"type":"Point"}
}