{
  "type": "Feature",
  "properties": {
    "iso:country":"DE",
    "sg:city":"Ensdorf",
    "sg:phone":"+49 9624/629",
    "sg:postcode":"92266",
    "sg:province":"Bayern",
    "wof:name":"Kreissparkasse",
    "wof:placetype":"venue"
},
  "geometry": {"coordinates":[11.936931,49.339558],"type":"Point"}
}