{
  "type": "Feature",
  "properties": {
    "iso:country":"DE",
    "sg:address":"Vordamm 19",
    "sg:city":"Horneburg",
    "sg:phone":"+49 4163/811281",
    "sg:postcode":"21640",
    "sg:province":"Niedersachsen",
    "wof:name":"Nr Service- Und Handelsges Mbh",
    "wof:placetype":"venue"
},
  "geometry": {"coordinates":[9.5866956711,53.5084190369],"type":"Point"}
}