{
  "type": "Feature",
  "properties": {
    "iso:country":"DE",
    "sg:address":"Berliner Str. 6",
    "sg:city":"Hilden",
    "sg:phone":"+49 2103/582430",
    "sg:postcode":"40721",
    "sg:province":"Nordrhein-Westfalen",
    "wof:name":"Orga-info Gesellschaft F\u00fcr Edv-organisation Und",
    "wof:placetype":"venue"
},
  "geometry": {"coordinates":[6.929749012,51.1687583923],"type":"Point"}
}