{
  "type": "Feature",
  "properties": {
    "iso:country":"DE",
    "sg:address":"Reindelstr. 14",
    "sg:city":"N\u00fcrnberg",
    "sg:phone":"+49 911/469686",
    "sg:postcode":"90402",
    "sg:province":"Bayern",
    "wof:name":"Hts Reisen",
    "wof:placetype":"venue"
},
  "geometry": {"coordinates":[11.0903139114,49.4485778809],"type":"Point"}
}