{
  "type": "Feature",
  "properties": {
    "iso:country":"DE",
    "sg:address":"Feldtmannstr. 127",
    "sg:city":"Berlin",
    "sg:phone":"+49 30/9252487",
    "sg:postcode":"13088",
    "sg:province":"Berlin",
    "wof:name":"J\u00f6rg Frisch Bau Gmbh",
    "wof:placetype":"venue"
},
  "geometry": {"coordinates":[13.4818744659,52.5628547668],"type":"Point"}
}