{
  "type": "Feature",
  "properties": {
    "iso:country":"DE",
    "sg:address":"Nikolaistr. 42",
    "sg:city":"Leipzig",
    "sg:phone":"+49 341/9805102",
    "sg:postcode":"04109",
    "sg:province":"Sachsen",
    "wof:name":"Leder Kleemann Gmbh",
    "wof:placetype":"venue"
},
  "geometry": {"coordinates":[12.378705,51.343117],"type":"Point"}
}