{
  "type": "Feature",
  "properties": {
    "iso:country":"DE",
    "sg:address":"Pirnaer Str. 14",
    "sg:city":"Heidenau",
    "sg:phone":"+49 3529/517434",
    "sg:postcode":"01809",
    "sg:province":"Sachsen",
    "wof:name":"Michael Kmoch",
    "wof:placetype":"venue"
},
  "geometry": {"coordinates":[13.8723812103,50.9737167358],"type":"Point"}
}