{
  "type": "Feature",
  "properties": {
    "iso:country":"DE",
    "sg:address":"Dieselstr. 17",
    "sg:city":"Hiddenhausen",
    "sg:phone":"+49 5223/83256",
    "sg:postcode":"32120",
    "sg:province":"Nordrhein-Westfalen",
    "wof:name":"Schr\u00f6der M\u00f6bel- Und Elementbau Gmbh",
    "wof:placetype":"venue"
},
  "geometry": {"coordinates":[8.601558,52.168503],"type":"Point"}
}