{
  "type": "Feature",
  "properties": {
    "iso:country":"DE",
    "sg:address":"Fasanenweg 1",
    "sg:city":"Ransbach-Baumbach",
    "sg:postcode":"56235",
    "sg:province":"Rheinland-Pfalz",
    "wof:name":"Vhv-vermietungs- Und Verpachtungs- Haus- Und",
    "wof:placetype":"venue"
},
  "geometry": {"coordinates":[7.7363228798,50.4628715515],"type":"Point"}
}