{
  "type": "Feature",
  "properties": {
    "iso:country":"DE",
    "sg:address":"Am Markt 5",
    "sg:city":"Griesheim",
    "sg:phone":"+49 6155/70090",
    "sg:postcode":"64347",
    "sg:province":"Hessen",
    "wof:name":"Vereinigte Volksbank Griesheim-weiterstadt Eg",
    "wof:placetype":"venue"
},
  "geometry": {"coordinates":[8.5605249405,49.8606452942],"type":"Point"}
}