{
  "type": "Feature",
  "properties": {
    "iso:country":"DE",
    "sg:address":"Im Rosenhag 12",
    "sg:city":"Sta\u00dffurt",
    "sg:phone":"+49 3925/623973",
    "sg:postcode":"39418",
    "sg:province":"Sachsen-Anhalt",
    "wof:name":"Gbur",
    "wof:placetype":"venue"
},
  "geometry": {"coordinates":[11.569366,51.85881],"type":"Point"}
}