{
  "type": "Feature",
  "properties": {
    "iso:country":"DE",
    "sg:address":"Stefanstr. 63",
    "sg:city":"Budenheim",
    "sg:phone":"+49 6139/6083",
    "sg:postcode":"55257",
    "sg:province":"Rheinland-Pfalz",
    "wof:name":"G\u00fcnter Bauer Architekt",
    "wof:placetype":"venue"
},
  "geometry": {"coordinates":[8.17074,50.025581],"type":"Point"}
}