{
  "type": "Feature",
  "properties": {
    "iso:country":"DE",
    "sg:address":"Am Kraftwerk 1",
    "sg:city":"Schleich",
    "sg:phone":"+49 6507/99133",
    "sg:postcode":"54340",
    "sg:province":"Rheinland-Pfalz",
    "wof:name":"Wasserski-verband Rheinland-pfalz",
    "wof:placetype":"venue"
},
  "geometry": {"coordinates":[6.7650499344,49.8083114624],"type":"Point"}
}