{
  "type": "Feature",
  "properties": {
    "iso:country":"DE",
    "sg:address":"Hoher Steg 29",
    "sg:city":"Lauffen",
    "sg:phone":"+49 7133/14383",
    "sg:postcode":"74348",
    "sg:province":"Baden-W\u00fcrttemberg",
    "wof:name":"Sl Stahlbearbeitung Gmbh",
    "wof:placetype":"venue"
},
  "geometry": {"coordinates":[9.182951,49.072186],"type":"Point"}
}