{
  "type": "Feature",
  "properties": {
    "iso:country":"DE",
    "sg:address":"Hirschgraben 11",
    "sg:city":"Hamburg",
    "sg:postcode":"22089",
    "sg:province":"Hamburg",
    "wof:name":"Martin Hildebrandt Gesch\u00e4ftsf\u00fchrungs-gmbh",
    "wof:placetype":"venue"
},
  "geometry": {"coordinates":[10.0424194336,53.5660247803],"type":"Point"}
}