{
  "type": "Feature",
  "properties": {
    "iso:country":"DE",
    "sg:address":"Spohrstr. 41",
    "sg:city":"Frankfurt",
    "sg:phone":"+49 69/595003",
    "sg:postcode":"60318",
    "sg:province":"Hessen",
    "wof:name":"Ram Hoch- Tief- Stahlbeton Bau Gmbh",
    "wof:placetype":"venue"
},
  "geometry": {"coordinates":[8.690315,50.129185],"type":"Point"}
}