{
  "type": "Feature",
  "properties": {
    "iso:country":"DE",
    "sg:address":"Grenzstr. 25",
    "sg:city":"Wilhelmshaven",
    "sg:phone":"+49 4421/13434",
    "sg:postcode":"26382",
    "sg:province":"Niedersachsen",
    "wof:name":"Dr. Med. D\u00f6rte Ganse-dumrath Tier\u00e4rztin",
    "wof:placetype":"venue"
},
  "geometry": {"coordinates":[8.1118574142,53.5229568481],"type":"Point"}
}