{
  "type": "Feature",
  "properties": {
    "iso:country":"DE",
    "sg:address":"Talerweg 19",
    "sg:city":"M\u00fcnchen",
    "sg:phone":"+49 89/43650451",
    "sg:postcode":"81825",
    "sg:province":"Bayern",
    "wof:name":"Josef Maier",
    "wof:placetype":"venue"
},
  "geometry": {"coordinates":[11.653448,48.123493],"type":"Point"}
}