{
  "type": "Feature",
  "properties": {
    "iso:country":"DE",
    "sg:address":"Hildburghauser Str. 41",
    "sg:city":"Berlin",
    "sg:phone":"+49 30/7110488",
    "sg:postcode":"12279",
    "sg:province":"Berlin",
    "wof:name":"J\u00fcrgen Weisse",
    "wof:placetype":"venue"
},
  "geometry": {"coordinates":[13.349123,52.414345],"type":"Point"}
}