{
  "type": "Feature",
  "properties": {
    "iso:country":"DE",
    "sg:address":"Lameystr. 6",
    "sg:city":"Pforzheim",
    "sg:phone":"+49 7231/927311",
    "sg:postcode":"75173",
    "sg:province":"Baden-W\u00fcrttemberg",
    "wof:name":"Dieter Freymark Architekt",
    "wof:placetype":"venue"
},
  "geometry": {"coordinates":[8.693438,48.88522],"type":"Point"}
}