{
  "type": "Feature",
  "properties": {
    "iso:country":"DE",
    "sg:address":"K\u00f6lner Str. 76",
    "sg:city":"Frechen",
    "sg:phone":"+49 2234/18460",
    "sg:postcode":"50226",
    "sg:province":"Nordrhein-Westfalen",
    "wof:name":"Hotel Bartmann Krug",
    "wof:placetype":"venue"
},
  "geometry": {"coordinates":[6.8199491501,50.9111022949],"type":"Point"}
}