{
  "type": "Feature",
  "properties": {
    "iso:country":"DE",
    "sg:address":"Ellenbogengasse 15",
    "sg:city":"Wiesbaden",
    "sg:phone":"+49 611/304868",
    "sg:postcode":"65183",
    "sg:province":"Hessen",
    "wof:name":"Schl\u00fcsselzentrale Kranz Wiesbad. Schl\u00fcsseldienst Gmbh",
    "wof:placetype":"venue"
},
  "geometry": {"coordinates":[8.2400083542,50.0815925598],"type":"Point"}
}