{
  "type": "Feature",
  "properties": {
    "iso:country":"DE",
    "sg:address":"Hauptstr. 5",
    "sg:city":"Obersch\u00f6nau",
    "sg:phone":"+49 36847/30421",
    "sg:postcode":"98587",
    "sg:province":"Th\u00fcringen",
    "wof:name":"Renate Eff",
    "wof:placetype":"venue"
},
  "geometry": {"coordinates":[10.604107,50.716995],"type":"Point"}
}