{
  "type": "Feature",
  "properties": {
    "iso:country":"DE",
    "sg:address":"Murmansker Str. 7",
    "sg:city":"Halle",
    "sg:postcode":"06130",
    "sg:province":"Sachsen-Anhalt",
    "wof:name":"H\u00e4\u00dfler Lift",
    "wof:placetype":"venue"
},
  "geometry": {"coordinates":[11.9918298721,51.4506797791],"type":"Point"}
}