{
  "type": "Feature",
  "properties": {
    "iso:country":"DE",
    "sg:address":"Schmiedegasse 1a",
    "sg:city":"G\u00f6\u00dfnitz",
    "sg:phone":"+49 34493/36546",
    "sg:postcode":"04639",
    "sg:province":"Th\u00fcringen",
    "wof:name":"Creatronic Gesellschaft F\u00fcr Industrie Automation Mbh",
    "wof:placetype":"venue"
},
  "geometry": {"coordinates":[12.4312162399,50.8873023987],"type":"Point"}
}