{
  "type": "Feature",
  "properties": {
    "iso:country":"DE",
    "sg:address":"Am G\u00e4\u00dflein 8",
    "sg:city":"Trogen",
    "sg:phone":"+49 9281/45643",
    "sg:postcode":"95183",
    "sg:province":"Bayern",
    "wof:name":"Hans-j\u00fcrgen Seim",
    "wof:placetype":"venue"
},
  "geometry": {"coordinates":[11.953660965,50.3663635254],"type":"Point"}
}