{
  "type": "Feature",
  "properties": {
    "iso:country":"DE",
    "sg:address":"Landsberger Str 58",
    "sg:city":"Augsburg",
    "sg:phone":"+49 821/8153443",
    "sg:postcode":"86179",
    "sg:province":"Bayern",
    "wof:name":"Quote-direct Ohg",
    "wof:placetype":"venue"
},
  "geometry": {"coordinates":[10.90641,48.309643],"type":"Point"}
}