{
  "type": "Feature",
  "properties": {
    "iso:country":"DE",
    "sg:address":"Ebert-Str.+21a",
    "sg:city":"Auerbach",
    "sg:phone":"+49 251/131",
    "sg:postcode":"08209",
    "sg:province":"Sachsen",
    "wof:name":"Networked",
    "wof:placetype":"venue"
},
  "geometry": {"coordinates":[12.41117,50.501202],"type":"Point"}
}