{
  "type": "Feature",
  "properties": {
    "iso:country":"DE",
    "sg:address":"Neuer Weg 3",
    "sg:city":"G\u00fcntersleben",
    "sg:postcode":"97261",
    "sg:province":"Bayern",
    "wof:name":"Blindenwerkst\u00e4tte",
    "wof:placetype":"venue"
},
  "geometry": {"coordinates":[9.908975,49.870708],"type":"Point"}
}