{
  "type": "Feature",
  "properties": {
    "iso:country":"DE",
    "sg:address":"Seerstr. 6",
    "sg:city":"Wincheringen",
    "sg:phone":"+49 6583/286",
    "sg:postcode":"54457",
    "sg:province":"Rheinland-Pfalz",
    "wof:name":"Margret Georgen Hebamme",
    "wof:placetype":"venue"
},
  "geometry": {"coordinates":[6.427671,49.608608],"type":"Point"}
}