{
  "type": "Feature",
  "properties": {
    "iso:country":"DE",
    "sg:address":"Eppsteiner Str. 16/18",
    "sg:city":"Oberursel",
    "sg:phone":"+49 6171/502475",
    "sg:postcode":"61440",
    "sg:province":"Hessen",
    "wof:name":"Stadtb\u00fccherei",
    "wof:placetype":"venue"
},
  "geometry": {"coordinates":[8.577156,50.203022],"type":"Point"}
}