{
  "type": "Feature",
  "properties": {
    "iso:country":"DE",
    "sg:address":"Schr\u00f6derstr. 24",
    "sg:city":"Rostock",
    "sg:phone":"+49 381/455163",
    "sg:postcode":"18055",
    "sg:province":"Mecklenburg-Vorpommern",
    "wof:name":"Rosimpex Gmbh",
    "wof:placetype":"venue"
},
  "geometry": {"coordinates":[12.127127,54.087254],"type":"Point"}
}