{
  "type": "Feature",
  "properties": {
    "iso:country":"DE",
    "sg:address":"Berliner Str. 5",
    "sg:city":"Oderberg",
    "sg:phone":"+49 33369/310",
    "sg:postcode":"16248",
    "sg:province":"Brandenburg",
    "wof:name":"Erna Zipperrek",
    "wof:placetype":"venue"
},
  "geometry": {"coordinates":[14.0439996719,52.8654975891],"type":"Point"}
}