{
  "type": "Feature",
  "properties": {
    "iso:country":"DE",
    "sg:address":"Industriestr. 7",
    "sg:city":"Ehringshausen",
    "sg:phone":"+49 6443/3396",
    "sg:postcode":"35630",
    "sg:province":"Hessen",
    "wof:name":"Friedrich Huttel & Sohn Kg",
    "wof:placetype":"venue"
},
  "geometry": {"coordinates":[8.3887243271,50.5972442627],"type":"Point"}
}