{
  "type": "Feature",
  "properties": {
    "iso:country":"DE",
    "sg:address":"Frankfurter Str 233",
    "sg:city":"Neu-Isenburg",
    "sg:phone":"+49 6102/785555",
    "sg:postcode":"63263",
    "sg:province":"Hessen",
    "wof:name":"Vanco Gmbh",
    "wof:placetype":"venue"
},
  "geometry": {"coordinates":[8.6950845718,50.0422897339],"type":"Point"}
}