{
  "type": "Feature",
  "properties": {
    "iso:country":"DE",
    "sg:address":"Jakobstr. 214-216",
    "sg:city":"Aachen",
    "sg:phone":"+49 241/27715",
    "sg:postcode":"52064",
    "sg:province":"Nordrhein-Westfalen",
    "wof:name":"Heiner Appel Immobilienmakler",
    "wof:placetype":"venue"
},
  "geometry": {"coordinates":[6.0745420456,50.77003479],"type":"Point"}
}