{
  "type": "Feature",
  "properties": {
    "iso:country":"DE",
    "sg:address":"Herderstr. 34",
    "sg:city":"Hofheim",
    "sg:phone":"+49 6192/5774",
    "sg:postcode":"65719",
    "sg:province":"Hessen",
    "wof:name":"Karlheinz Roch Masseur",
    "wof:placetype":"venue"
},
  "geometry": {"coordinates":[8.433875,50.078884],"type":"Point"}
}