{
  "type": "Feature",
  "properties": {
    "iso:country":"DE",
    "sg:address":"Georg-Friedrich-Hegel-Str. 1a",
    "sg:city":"Eberswalde",
    "sg:phone":"+49 3334/235970",
    "sg:postcode":"16225",
    "sg:province":"Brandenburg",
    "wof:name":"C. Paczyinski",
    "wof:placetype":"venue"
},
  "geometry": {"coordinates":[13.810387,52.840271],"type":"Point"}
}