{
  "type": "Feature",
  "properties": {
    "iso:country":"DE",
    "sg:address":"Bahnhofstr. 33",
    "sg:city":"Peiting",
    "sg:phone":"+49 8861/6271",
    "sg:postcode":"86971",
    "sg:province":"Bayern",
    "wof:name":"Deutsche Bahn Ag",
    "wof:placetype":"venue"
},
  "geometry": {"coordinates":[10.9358081818,47.792755127],"type":"Point"}
}