{
  "type": "Feature",
  "properties": {
    "iso:country":"DE",
    "sg:address":"Gutenbergstr. 94 a",
    "sg:city":"Stuttgart",
    "sg:phone":"+49 711/625837",
    "sg:postcode":"70197",
    "sg:province":"Baden-W\u00fcrttemberg",
    "wof:name":"P. M. R. Drissner",
    "wof:placetype":"venue"
},
  "geometry": {"coordinates":[9.156176,48.771259],"type":"Point"}
}