{
  "type": "Feature",
  "properties": {
    "iso:country":"DE",
    "sg:address":"Herbstberger Weg 4",
    "sg:city":"Traben-Trarbach",
    "sg:phone":"+49 6541/1588",
    "sg:postcode":"56841",
    "sg:province":"Rheinland-Pfalz",
    "wof:name":"Paul-walter Caspari",
    "wof:placetype":"venue"
},
  "geometry": {"coordinates":[7.109972,49.942928],"type":"Point"}
}