{
  "type": "Feature",
  "properties": {
    "iso:country":"DE",
    "sg:address":"Stadtberger Str. 6",
    "sg:city":"Augsburg",
    "sg:phone":"+49 821/524152",
    "sg:postcode":"86157",
    "sg:province":"Bayern",
    "wof:name":"Linden-apotheke Dr. Bernhard Koczian",
    "wof:placetype":"venue"
},
  "geometry": {"coordinates":[10.867973,48.362724],"type":"Point"}
}