{
  "type": "Feature",
  "properties": {
    "iso:country":"DE",
    "sg:address":"Humboldtallee 20",
    "sg:city":"G\u00f6ttingen",
    "sg:phone":"+49 551/45151",
    "sg:postcode":"37073",
    "sg:province":"Niedersachsen",
    "wof:name":"W. V. Heyn G\u00fcternahverkehr Gmbh",
    "wof:placetype":"venue"
},
  "geometry": {"coordinates":[9.941110611,51.5429916382],"type":"Point"}
}