{
  "type": "Feature",
  "properties": {
    "iso:country":"DE",
    "sg:address":"Alexander-Puschkin-Str. 15",
    "sg:city":"Wernshausen",
    "sg:phone":"+49 36848/21852",
    "sg:postcode":"98590",
    "sg:province":"Th\u00fcringen",
    "wof:name":"Regina Storandt",
    "wof:placetype":"venue"
},
  "geometry": {"coordinates":[10.351383,50.719604],"type":"Point"}
}