{
  "type": "Feature",
  "properties": {
    "iso:country":"DE",
    "sg:address":"Woltmershauser Str. 354",
    "sg:city":"Bremen",
    "sg:phone":"+49 421/540870",
    "sg:postcode":"28197",
    "sg:province":"Bremen",
    "wof:name":"Fleischerei Sander Inh. G\u00fcnter Rudolph",
    "wof:placetype":"venue"
},
  "geometry": {"coordinates":[8.7689819336,53.0827789307],"type":"Point"}
}