{
  "type": "Feature",
  "properties": {
    "iso:country":"DE",
    "sg:address":"Osnabr\u00fccker Str. 5",
    "sg:city":"Barnstorf",
    "sg:phone":"+49 5442/1337",
    "sg:postcode":"49406",
    "sg:province":"Niedersachsen",
    "wof:name":"J\u00fcrgen Heinrich",
    "wof:placetype":"venue"
},
  "geometry": {"coordinates":[8.502924,52.709843],"type":"Point"}
}