{
  "type": "Feature",
  "properties": {
    "iso:country":"DE",
    "sg:address":"S\u00e4gem\u00fchlenstr 45",
    "sg:city":"Leer",
    "sg:phone":"+49 491/80020",
    "sg:postcode":"26789",
    "sg:province":"Niedersachsen",
    "wof:name":"Oelm\u00fchle Leer Connemann Gmbh & Cokg",
    "wof:placetype":"venue"
},
  "geometry": {"coordinates":[7.461677,53.222698],"type":"Point"}
}