{
  "type": "Feature",
  "properties": {
    "iso:country":"DE",
    "sg:address":"K\u00fcckesweg 9",
    "sg:city":"Willich",
    "sg:postcode":"47877",
    "sg:province":"Nordrhein-Westfalen",
    "wof:name":"Raytracing",
    "wof:placetype":"venue"
},
  "geometry": {"coordinates":[6.519683,51.26527],"type":"Point"}
}