{
  "type": "Feature",
  "properties": {
    "iso:country":"DE",
    "sg:address":"Fraunhoferstr. 10a",
    "sg:city":"N\u00fcrnberg",
    "sg:phone":"+49 911/513739",
    "sg:postcode":"90409",
    "sg:province":"Bayern",
    "wof:name":"Integra Vital Gesellschaft F\u00fcr Pr\u00e4vention",
    "wof:placetype":"venue"
},
  "geometry": {"coordinates":[11.0978336334,49.4680862427],"type":"Point"}
}