{
  "type": "Feature",
  "properties": {
    "iso:country":"DE",
    "sg:address":"Trettaustr. 13",
    "sg:city":"Hamburg",
    "sg:phone":"+49 40/7534776",
    "sg:postcode":"21107",
    "sg:province":"Hamburg",
    "wof:name":"Christel G\u00f6decken",
    "wof:placetype":"venue"
},
  "geometry": {"coordinates":[9.9912023544,53.4937515259],"type":"Point"}
}