{
  "type": "Feature",
  "properties": {
    "iso:country":"DE",
    "sg:address":"Burgweg 27",
    "sg:city":"Stockach",
    "sg:phone":"+49 7771/62221",
    "sg:postcode":"78333",
    "sg:province":"Baden-W\u00fcrttemberg",
    "wof:name":"E.g. Mohr",
    "wof:placetype":"venue"
},
  "geometry": {"coordinates":[8.9625787735,47.8126792908],"type":"Point"}
}