{
  "type": "Feature",
  "properties": {
    "iso:country":"DE",
    "sg:address":"Sichelweg 6",
    "sg:city":"Bobingen",
    "sg:phone":"+49 8234/902360",
    "sg:postcode":"86399",
    "sg:province":"Bayern",
    "wof:name":"Der Anlagenvermittlung Gmbh",
    "wof:placetype":"venue"
},
  "geometry": {"coordinates":[10.8452854156,48.2823982239],"type":"Point"}
}