{
  "type": "Feature",
  "properties": {
    "iso:country":"DE",
    "sg:address":"Renteilichtung 8",
    "sg:city":"Essen",
    "sg:phone":"+49 201/444148",
    "sg:postcode":"45134",
    "sg:province":"Nordrhein-Westfalen",
    "wof:name":"Jutta Cla\u00dfen",
    "wof:placetype":"venue"
},
  "geometry": {"coordinates":[7.048869,51.421345],"type":"Point"}
}