{
  "type": "Feature",
  "properties": {
    "iso:country":"DE",
    "sg:address":"Franz-Mehring-Str. 15",
    "sg:city":"M\u00fcgeln",
    "sg:phone":"+49 34362/32095",
    "sg:postcode":"04769",
    "sg:province":"Sachsen",
    "wof:name":"Frank Kl\u00f6mich",
    "wof:placetype":"venue"
},
  "geometry": {"coordinates":[13.0403289795,51.2359237671],"type":"Point"}
}