{
  "type": "Feature",
  "properties": {
    "iso:country":"DE",
    "sg:address":"Walpertshofer Str. 2",
    "sg:city":"Mietingen",
    "sg:phone":"+49 7392/93103",
    "sg:postcode":"88487",
    "sg:province":"Baden-W\u00fcrttemberg",
    "wof:name":"Kuso Immobilien Gmbh",
    "wof:placetype":"venue"
},
  "geometry": {"coordinates":[9.9046001434,48.1835899353],"type":"Point"}
}