{
  "type": "Feature",
  "properties": {
    "iso:country":"DE",
    "sg:address":"Wei\u00dfdornweg 1",
    "sg:city":"Nienburg",
    "sg:phone":"+49 5021/14809",
    "sg:postcode":"31582",
    "sg:province":"Niedersachsen",
    "wof:name":"Top-video-palast Filmverleih Gmbh",
    "wof:placetype":"venue"
},
  "geometry": {"coordinates":[9.2148094177,52.6678466797],"type":"Point"}
}