{
  "type": "Feature",
  "properties": {
    "iso:country":"DE",
    "sg:address":"Harpstedter Str 99",
    "sg:city":"Stuhr",
    "sg:phone":"+49 4206/41760",
    "sg:postcode":"28816",
    "sg:province":"Niedersachsen",
    "wof:name":"Johann Klusmeyer U. Sohn G\u00fcterkraftverkehr Spedition Lagerung Gmbh & Co Kg",
    "wof:placetype":"venue"
},
  "geometry": {"coordinates":[8.698849678,52.985408783],"type":"Point"}
}