{
  "type": "Feature",
  "properties": {
    "iso:country":"DE",
    "sg:address":"Lameystr. 67",
    "sg:city":"Pforzheim",
    "sg:postcode":"75173",
    "sg:province":"Baden-W\u00fcrttemberg",
    "wof:name":"Luciole Creative Media Gmbh",
    "wof:placetype":"venue"
},
  "geometry": {"coordinates":[8.6960420609,48.878288269],"type":"Point"}
}