{
  "type": "Feature",
  "properties": {
    "iso:country":"DE",
    "sg:address":"Br\u00fchler Landstr. 407",
    "sg:city":"K\u00f6ln",
    "sg:phone":"+49 2232/68637",
    "sg:postcode":"50997",
    "sg:province":"Nordrhein-Westfalen",
    "wof:name":"Gilsdorf Gmbh",
    "wof:placetype":"venue"
},
  "geometry": {"coordinates":[6.9220042229,50.8532791138],"type":"Point"}
}