{
  "type": "Feature",
  "properties": {
    "iso:country":"DE",
    "sg:address":"Hans-B\u00f6ckler-Str. 57",
    "sg:city":"G\u00fctersloh",
    "sg:phone":"+49 5241/915030",
    "sg:postcode":"33334",
    "sg:province":"Nordrhein-Westfalen",
    "wof:name":"Hornbach-baumarkt- Ag",
    "wof:placetype":"venue"
},
  "geometry": {"coordinates":[8.3543233871,51.8838768005],"type":"Point"}
}