{
  "type": "Feature",
  "properties": {
    "iso:country":"DE",
    "sg:address":"Ewaldstr. 93a",
    "sg:city":"Herten",
    "sg:phone":"+49 2366/85655",
    "sg:postcode":"45699",
    "sg:province":"Nordrhein-Westfalen",
    "wof:name":"C. Gro\u00df",
    "wof:placetype":"venue"
},
  "geometry": {"coordinates":[7.1434049606,51.5873222351],"type":"Point"}
}