{
  "type": "Feature",
  "properties": {
    "iso:country":"DE",
    "sg:address":"Johann-Bunte-Str. 3",
    "sg:city":"Papenburg",
    "sg:phone":"+49 4961/71332",
    "sg:postcode":"26871",
    "sg:province":"Niedersachsen",
    "wof:name":"Hermann Schulze",
    "wof:placetype":"venue"
},
  "geometry": {"coordinates":[7.466522,53.043579],"type":"Point"}
}