{
  "type": "Feature",
  "properties": {
    "iso:country":"DE",
    "sg:address":"Am Alten Kirchplatz 10",
    "sg:city":"Recklinghausen",
    "sg:phone":"+49 2361/8568",
    "sg:postcode":"45665",
    "sg:province":"Nordrhein-Westfalen",
    "wof:name":"Gastst\u00e4tte W. Breuckmann",
    "wof:placetype":"venue"
},
  "geometry": {"coordinates":[7.2608389854,51.6118927002],"type":"Point"}
}