{
  "type": "Feature",
  "properties": {
    "iso:country":"DE",
    "sg:address":"Pastor-B\u00f6hm-Str. 33 a",
    "sg:city":"Troisdorf",
    "sg:phone":"+49 2241/405885",
    "sg:postcode":"53844",
    "sg:province":"Nordrhein-Westfalen",
    "wof:name":"Bistro Village",
    "wof:placetype":"venue"
},
  "geometry": {"coordinates":[7.1270780563,50.8013076782],"type":"Point"}
}