{
  "type": "Feature",
  "properties": {
    "iso:country":"DE",
    "sg:address":"Bahnhofstr. 8",
    "sg:city":"Maxh\u00fctte-Haidhof",
    "sg:phone":"+49 9471/4693",
    "sg:postcode":"93142",
    "sg:province":"Bayern",
    "wof:name":"Gl\u00fcckauf-lichtspiele Kino 13",
    "wof:placetype":"venue"
},
  "geometry": {"coordinates":[12.094678,49.201744],"type":"Point"}
}