{
  "type": "Feature",
  "properties": {
    "iso:country":"DE",
    "sg:address":"Hauptstr. 19",
    "sg:city":"Eltville",
    "sg:phone":"+49 6123/71536",
    "sg:postcode":"65345",
    "sg:province":"Hessen",
    "wof:name":"Jakob Sturm Weinanbau",
    "wof:placetype":"venue"
},
  "geometry": {"coordinates":[8.110244751,50.0590324402],"type":"Point"}
}