{
  "type": "Feature",
  "properties": {
    "iso:country":"DE",
    "sg:address":"Stuttgarter Str. 10",
    "sg:city":"Tuttlingen",
    "sg:phone":"+49 7461/5387",
    "sg:postcode":"78532",
    "sg:province":"Baden-W\u00fcrttemberg",
    "wof:name":"H. Tiny",
    "wof:placetype":"venue"
},
  "geometry": {"coordinates":[8.8187446594,47.9869499207],"type":"Point"}
}