{
  "type": "Feature",
  "properties": {
    "iso:country":"DE",
    "sg:address":"Auf der H\u00f6he 6",
    "sg:city":"Amelinghausen",
    "sg:phone":"+49 4132/8300",
    "sg:postcode":"21385",
    "sg:province":"Niedersachsen",
    "wof:name":"Klemens K\u00e4ndler",
    "wof:placetype":"venue"
},
  "geometry": {"coordinates":[10.209482193,53.1302185059],"type":"Point"}
}