{
  "type": "Feature",
  "properties": {
    "iso:country":"DE",
    "sg:address":"Oberer Grifflenberg 155",
    "sg:city":"Wuppertal",
    "sg:phone":"+49 202/2430011",
    "sg:postcode":"42119",
    "sg:province":"Nordrhein-Westfalen",
    "wof:name":"Feinwerktechnik Dr. Bastian Gmbh",
    "wof:placetype":"venue"
},
  "geometry": {"coordinates":[7.151152,51.246544],"type":"Point"}
}