{
  "type": "Feature",
  "properties": {
    "iso:country":"DE",
    "sg:address":"Hauptmarkt 17",
    "sg:city":"N\u00fcrnberg",
    "sg:phone":"+49 911/230940",
    "sg:postcode":"90403",
    "sg:province":"Bayern",
    "wof:name":"Tomas Fischer Rechtsanwalt",
    "wof:placetype":"venue"
},
  "geometry": {"coordinates":[11.0767087936,49.4541931152],"type":"Point"}
}