{
  "type": "Feature",
  "properties": {
    "iso:country":"DE",
    "sg:address":"Am Barthelwald 40",
    "sg:city":"Wilhelmsdorf",
    "sg:phone":"+49 7503/1337",
    "sg:postcode":"88271",
    "sg:province":"Baden-W\u00fcrttemberg",
    "wof:name":"Cafe Riedblick",
    "wof:placetype":"venue"
},
  "geometry": {"coordinates":[9.391452,47.870323],"type":"Point"}
}