{
  "type": "Feature",
  "properties": {
    "iso:country":"DE",
    "sg:address":"Werner-von-Siemens-Str. 3",
    "sg:city":"Alsdorf",
    "sg:postcode":"52477",
    "sg:province":"Nordrhein-Westfalen",
    "wof:name":"May Verwaltungs- Gmbh",
    "wof:placetype":"venue"
},
  "geometry": {"coordinates":[6.2202649117,50.8683395386],"type":"Point"}
}