{
  "type": "Feature",
  "properties": {
    "iso:country":"DE",
    "sg:address":"S\u00fcdstr. 7",
    "sg:city":"Grasleben",
    "sg:phone":"+49 5357/896",
    "sg:postcode":"38368",
    "sg:province":"Niedersachsen",
    "wof:name":"Heinrich Schrader",
    "wof:placetype":"venue"
},
  "geometry": {"coordinates":[11.014488,52.300926],"type":"Point"}
}