{
  "type": "Feature",
  "properties": {
    "iso:country":"DE",
    "sg:address":"Ruppmannsburg 27 a",
    "sg:city":"Thalm\u00e4ssing",
    "sg:phone":"+49 9173/1893",
    "sg:postcode":"91177",
    "sg:province":"Bayern",
    "wof:name":"R\u00f6ttenbacher Gmbh",
    "wof:placetype":"venue"
},
  "geometry": {"coordinates":[11.187558,49.067024],"type":"Point"}
}