{
  "type": "Feature",
  "properties": {
    "iso:country":"DE",
    "sg:address":"Werner-Heisenberg-Str. 7",
    "sg:city":"Kassel",
    "sg:phone":"+49 561/584061",
    "sg:postcode":"34123",
    "sg:province":"Hessen",
    "wof:name":"Red. Deutscher Hauskalender Thiele & Schwarz",
    "wof:placetype":"venue"
},
  "geometry": {"coordinates":[9.4982328415,51.2803001404],"type":"Point"}
}