{
  "type": "Feature",
  "properties": {
    "iso:country":"DE",
    "sg:address":"Helenenstr. 14",
    "sg:city":"Leipzig",
    "sg:phone":"+49 341/3380666",
    "sg:postcode":"04279",
    "sg:province":"Sachsen",
    "wof:name":"D\u00f6litzer Romantik",
    "wof:placetype":"venue"
},
  "geometry": {"coordinates":[12.389225,51.288929],"type":"Point"}
}