{
  "type": "Feature",
  "properties": {
    "iso:country":"DE",
    "sg:address":"S\u00f6mmiger Weg",
    "sg:city":"Barchfeld",
    "sg:phone":"+49 36961/40143",
    "sg:postcode":"36456",
    "sg:province":"Th\u00fcringen",
    "wof:name":"Exoten",
    "wof:placetype":"venue"
},
  "geometry": {"coordinates":[10.2964448929,50.8037834167],"type":"Point"}
}