{
  "type": "Feature",
  "properties": {
    "iso:country":"DE",
    "sg:address":"S\u00f6gestr. 31-33",
    "sg:city":"Bremen",
    "sg:phone":"+49 421/321627",
    "sg:postcode":"28195",
    "sg:province":"Bremen",
    "wof:name":"Dr. Hammann Volkmann Borttscheller Und Partner",
    "wof:placetype":"venue"
},
  "geometry": {"coordinates":[8.8077173233,53.0776252747],"type":"Point"}
}