{
  "type": "Feature",
  "properties": {
    "iso:country":"DE",
    "sg:address":"Meranierring 37",
    "sg:city":"Bayreuth",
    "sg:phone":"+49 921/42538",
    "sg:postcode":"95445",
    "sg:province":"Bayern",
    "wof:name":"H. Partenfelder",
    "wof:placetype":"venue"
},
  "geometry": {"coordinates":[11.545352,49.950024],"type":"Point"}
}