{
  "type": "Feature",
  "properties": {
    "iso:country":"DE",
    "sg:address":"Allersberger Str. 96",
    "sg:city":"N\u00fcrnberg",
    "sg:phone":"+49 911/449696",
    "sg:postcode":"90461",
    "sg:province":"Bayern",
    "wof:name":"Kosmos-apotheke Roland B\u00fcrner",
    "wof:placetype":"venue"
},
  "geometry": {"coordinates":[11.090089,49.439526],"type":"Point"}
}