{
  "type": "Feature",
  "properties": {
    "iso:country":"DE",
    "sg:address":"Im Kr\u00e4hennest 1",
    "sg:city":"Eutin",
    "sg:phone":"+49 4521/73461",
    "sg:postcode":"23701",
    "sg:province":"Schleswig-Holstein",
    "wof:name":"Bernd Strassburger",
    "wof:placetype":"venue"
},
  "geometry": {"coordinates":[10.607438,54.123363],"type":"Point"}
}