{
  "type": "Feature",
  "properties": {
    "iso:country":"DE",
    "sg:address":"Dossenheimer Landstr. 38",
    "sg:city":"Heidelberg",
    "sg:phone":"+49 6221",
    "sg:postcode":"69121",
    "sg:province":"Baden-W\u00fcrttemberg",
    "wof:name":"Irmgard Barth - Stoffe & Kurzwaren",
    "wof:placetype":"venue"
},
  "geometry": {"coordinates":[8.6832771301,49.4286727905],"type":"Point"}
}