{
  "type": "Feature",
  "properties": {
    "iso:country":"DE",
    "sg:address":"August-Bebel-Str. 9",
    "sg:city":"T\u00fcbingen",
    "sg:phone":"+49 7071/13090",
    "sg:postcode":"72072",
    "sg:province":"Baden-W\u00fcrttemberg",
    "wof:name":"T\u00fcbinger Chronik Druckerei Und Verlagsgenossenschaft Eg",
    "wof:placetype":"venue"
},
  "geometry": {"coordinates":[9.081473,48.519543],"type":"Point"}
}