{
  "type": "Feature",
  "properties": {
    "iso:country":"DE",
    "sg:address":"Schubartstr. 23",
    "sg:city":"Bietigheim-Bissingen",
    "sg:phone":"+49 7142/30600",
    "sg:postcode":"74321",
    "sg:province":"Baden-W\u00fcrttemberg",
    "wof:name":"H. Elbe",
    "wof:placetype":"venue"
},
  "geometry": {"coordinates":[9.106237,48.943806],"type":"Point"}
}