{
  "type": "Feature",
  "properties": {
    "iso:country":"DE",
    "sg:address":"Albert-Schweitzer-Str. 36",
    "sg:city":"Salzgitter",
    "sg:phone":"+49 5341/43131",
    "sg:postcode":"38226",
    "sg:province":"Niedersachsen",
    "wof:name":"M\u00fchl & Erbacher",
    "wof:placetype":"venue"
},
  "geometry": {"coordinates":[10.3278245926,52.1544570923],"type":"Point"}
}