{
  "type": "Feature",
  "properties": {
    "iso:country":"DE",
    "sg:address":"Merzdorfer Str. 12",
    "sg:city":"Petkus",
    "sg:postcode":"14913",
    "sg:province":"Brandenburg",
    "wof:name":"Raumkultur Tischlereigenossenschaft Eg",
    "wof:placetype":"venue"
},
  "geometry": {"coordinates":[13.362337,51.988602],"type":"Point"}
}