{
  "type": "Feature",
  "properties": {
    "iso:country":"DE",
    "sg:address":"Gewerbegebiet",
    "sg:city":"Trierweiler",
    "sg:phone":"+49 651/85080",
    "sg:postcode":"54311",
    "sg:province":"Rheinland-Pfalz",
    "wof:name":"Hubert Schuler",
    "wof:placetype":"venue"
},
  "geometry": {"coordinates":[6.559486,49.761318],"type":"Point"}
}