{
  "type": "Feature",
  "properties": {
    "iso:country":"DE",
    "sg:address":"Kressen 9",
    "sg:city":"Oy-Mittelberg",
    "sg:phone":"+49 8366/793",
    "sg:postcode":"87466",
    "sg:province":"Bayern",
    "wof:name":"Landhaus Ingeborg",
    "wof:placetype":"venue"
},
  "geometry": {"coordinates":[10.4445400238,47.6497917175],"type":"Point"}
}