{
  "type": "Feature",
  "properties": {
    "iso:country":"DE",
    "sg:address":"Am Kaliwerk 1",
    "sg:city":"Sondershausen",
    "sg:postcode":"99706",
    "sg:province":"Th\u00fcringen",
    "wof:name":"S & K Fliesen Gmbh",
    "wof:placetype":"venue"
},
  "geometry": {"coordinates":[10.8517484665,51.3863716125],"type":"Point"}
}