{
  "type": "Feature",
  "properties": {
    "iso:country":"DE",
    "sg:address":"Berliner Freiheit 1 e",
    "sg:city":"Bremen",
    "sg:phone":"+49 421/467000",
    "sg:postcode":"28327",
    "sg:province":"Bremen",
    "wof:name":"Sanit\u00e4tshaus Oesterreich",
    "wof:placetype":"venue"
},
  "geometry": {"coordinates":[8.8925600052,53.0811157227],"type":"Point"}
}