{
  "type": "Feature",
  "properties": {
    "iso:country":"DE",
    "sg:address":"Am Osterbach 11",
    "sg:city":"Bad Oeynhausen",
    "sg:phone":"+49 5731/22567",
    "sg:postcode":"32545",
    "sg:province":"Nordrhein-Westfalen",
    "wof:name":"Haus Osterbach",
    "wof:placetype":"venue"
},
  "geometry": {"coordinates":[8.7871999741,52.1991386414],"type":"Point"}
}