{
  "type": "Feature",
  "properties": {
    "iso:country":"DE",
    "sg:address":"Am Steintor 12",
    "sg:city":"Goch",
    "sg:phone":"+49 2823/86103",
    "sg:postcode":"47574",
    "sg:province":"Nordrhein-Westfalen",
    "wof:name":"H. W. Th\u00fcnnesen",
    "wof:placetype":"venue"
},
  "geometry": {"coordinates":[6.1584730148,51.6758575439],"type":"Point"}
}