{
  "type": "Feature",
  "properties": {
    "iso:country":"DE",
    "sg:address":"Werkstr. 5",
    "sg:city":"Sch\u00fcttorf",
    "sg:phone":"+49 5923/96400",
    "sg:postcode":"48465",
    "sg:province":"Niedersachsen",
    "wof:name":"Lamann & Co. Gmbh",
    "wof:placetype":"venue"
},
  "geometry": {"coordinates":[7.241437,52.329468],"type":"Point"}
}