{
  "type": "Feature",
  "properties": {
    "iso:country":"DE",
    "sg:address":"Steintor 6",
    "sg:city":"Coburg",
    "sg:phone":"+49 9561/29567",
    "sg:postcode":"96450",
    "sg:province":"Bayern",
    "wof:name":"J\u00fcrgen Schumann",
    "wof:placetype":"venue"
},
  "geometry": {"coordinates":[10.9684753418,50.2570228577],"type":"Point"}
}