{
  "type": "Feature",
  "properties": {
    "iso:country":"DE",
    "sg:address":"Auf dem Hainberg 6",
    "sg:city":"Bad Laasphe",
    "sg:phone":"+49 2754/1319",
    "sg:postcode":"57334",
    "sg:province":"Nordrhein-Westfalen",
    "wof:name":"Heinz-otto Wolzenburg",
    "wof:placetype":"venue"
},
  "geometry": {"coordinates":[8.3211765289,50.9450111389],"type":"Point"}
}