{
  "type": "Feature",
  "properties": {
    "iso:country":"DE",
    "sg:address":"Hauptstr. 6",
    "sg:city":"Thurland",
    "sg:phone":"+49 34906/21031",
    "sg:postcode":"06779",
    "sg:province":"Sachsen-Anhalt",
    "wof:name":"Thurl\u00e4nder Salate Und Feinkost Gmbh",
    "wof:placetype":"venue"
},
  "geometry": {"coordinates":[12.2254257202,51.7150650024],"type":"Point"}
}