{
  "type": "Feature",
  "properties": {
    "iso:country":"DE",
    "sg:address":"Burgstr. 8",
    "sg:city":"Bad Essen",
    "sg:phone":"+49 5472/4178",
    "sg:postcode":"49152",
    "sg:province":"Niedersachsen",
    "wof:name":"Julios Video Kiste",
    "wof:placetype":"venue"
},
  "geometry": {"coordinates":[8.3732089996,52.3230056763],"type":"Point"}
}