{
  "type": "Feature",
  "properties": {
    "iso:country":"DE",
    "sg:address":"Gutleutstr 298",
    "sg:city":"Frankfurt",
    "sg:phone":"+49 69/26960",
    "sg:postcode":"60327",
    "sg:province":"Hessen",
    "wof:name":"Verlag Friedrich Bischoff Gmbh",
    "wof:placetype":"venue"
},
  "geometry": {"coordinates":[8.6461,50.097427],"type":"Point"}
}