{
  "type": "Feature",
  "properties": {
    "iso:country":"DE",
    "sg:address":"Z\u00f6llmener Str. 37",
    "sg:city":"Dresden",
    "sg:phone":"+49 351/4213519",
    "sg:postcode":"01157",
    "sg:province":"Sachsen",
    "wof:name":"Karl Z\u00f6ltner",
    "wof:placetype":"venue"
},
  "geometry": {"coordinates":[13.679682,51.050449],"type":"Point"}
}