{
  "type": "Feature",
  "properties": {
    "iso:country":"DE",
    "sg:address":"Hamburger Str. 277",
    "sg:city":"Braunschweig",
    "sg:phone":"+49 4953/1380040",
    "sg:postcode":"38114",
    "sg:province":"Niedersachsen",
    "wof:name":"Thalacker Medien/bernhardt Thalacker Gmbh Co Kg",
    "wof:placetype":"venue"
},
  "geometry": {"coordinates":[10.5207700729,52.2771453857],"type":"Point"}
}