{
  "type": "Feature",
  "properties": {
    "iso:country":"DE",
    "sg:address":"Gochtstr. 32",
    "sg:city":"Zwickau",
    "sg:phone":"+49 375/216461",
    "sg:postcode":"08058",
    "sg:province":"Sachsen",
    "wof:name":"K.-h. Pl\u00f6tner",
    "wof:placetype":"venue"
},
  "geometry": {"coordinates":[12.47551,50.741268],"type":"Point"}
}