{
  "type": "Feature",
  "properties": {
    "iso:country":"DE",
    "sg:address":"Berliner Str. 40",
    "sg:city":"Mettmann",
    "sg:phone":"+49 2104/72626",
    "sg:postcode":"40822",
    "sg:province":"Nordrhein-Westfalen",
    "wof:name":"Heinz Michelitsch",
    "wof:placetype":"venue"
},
  "geometry": {"coordinates":[6.962522,51.257214],"type":"Point"}
}