{
  "type": "Feature",
  "properties": {
    "iso:country":"DE",
    "sg:address":"Feldstr. 5",
    "sg:city":"Glash\u00fctten",
    "sg:phone":"+49 6082/3498",
    "sg:postcode":"61479",
    "sg:province":"Hessen",
    "wof:name":"T. Fischer",
    "wof:placetype":"venue"
},
  "geometry": {"coordinates":[8.400478363,50.2377357483],"type":"Point"}
}