{
  "type": "Feature",
  "properties": {
    "iso:country":"DE",
    "sg:address":"Sch\u00fctzenstr. 1",
    "sg:city":"Lahn",
    "sg:phone":"+49 5951/5821",
    "sg:postcode":"49757",
    "sg:province":"Niedersachsen",
    "wof:name":"Hermann Schomaker Verwaltungs Gmbh",
    "wof:placetype":"venue"
},
  "geometry": {"coordinates":[7.616,52.82233],"type":"Point"}
}