{
  "type": "Feature",
  "properties": {
    "iso:country":"DE",
    "sg:address":"Heinrich-Wieland-Str. 85",
    "sg:city":"M\u00fcnchen",
    "sg:phone":"+49 89/89044980",
    "sg:postcode":"81735",
    "sg:province":"Bayern",
    "wof:name":"Crm Informationsystems Gmbh",
    "wof:placetype":"venue"
},
  "geometry": {"coordinates":[11.6448907852,48.1146278381],"type":"Point"}
}