{
  "type": "Feature",
  "properties": {
    "iso:country":"DE",
    "sg:address":"Bathorner Diek 56",
    "sg:city":"Hoogstede",
    "sg:phone":"+49 5944/1724",
    "sg:postcode":"49846",
    "sg:province":"Niedersachsen",
    "wof:name":"J. Derks",
    "wof:placetype":"venue"
},
  "geometry": {"coordinates":[7.030428,52.610683],"type":"Point"}
}