{
  "type": "Feature",
  "properties": {
    "iso:country":"DE",
    "sg:address":"Bergh\u00e4user Str. 12",
    "sg:city":"Solms",
    "sg:phone":"+49 6442/1092",
    "sg:postcode":"35606",
    "sg:province":"Hessen",
    "wof:name":"Saalbau Sch\u00e4fer Gastst\u00e4tte Und Restaurant",
    "wof:placetype":"venue"
},
  "geometry": {"coordinates":[8.3998203278,50.5598182678],"type":"Point"}
}