{
  "type": "Feature",
  "properties": {
    "iso:country":"DE",
    "sg:address":"Ringstr. 29",
    "sg:city":"Nordstemmen",
    "sg:phone":"+49 5044/8798",
    "sg:postcode":"31171",
    "sg:province":"Niedersachsen",
    "wof:name":"Fliesen Walther Gmbh",
    "wof:placetype":"venue"
},
  "geometry": {"coordinates":[9.730055809,52.1740341187],"type":"Point"}
}