{
  "type": "Feature",
  "properties": {
    "iso:country":"DE",
    "sg:address":"Azorenstr. 10 e",
    "sg:city":"Bielefeld",
    "sg:phone":"+49 521/9774774",
    "sg:postcode":"33729",
    "sg:province":"Nordrhein-Westfalen",
    "wof:name":"Dr. Med. R. H. M\u00fcller",
    "wof:placetype":"venue"
},
  "geometry": {"coordinates":[8.6431903839,52.046749115],"type":"Point"}
}