{
  "type": "Feature",
  "properties": {
    "iso:country":"DE",
    "sg:address":"Schlo\u00dfstr. 3",
    "sg:city":"Chieming",
    "sg:phone":"+49 8667/79369",
    "sg:postcode":"83339",
    "sg:province":"Bayern",
    "wof:name":"Ristorante-pizzeria Il Cavallo",
    "wof:placetype":"venue"
},
  "geometry": {"coordinates":[12.5045604706,47.9235687256],"type":"Point"}
}