{
  "type": "Feature",
  "properties": {
    "iso:country":"DE",
    "sg:address":"Wangenstr. 2 a",
    "sg:city":"Geislingen",
    "sg:phone":"+49 7433/8676",
    "sg:postcode":"72351",
    "sg:province":"Baden-W\u00fcrttemberg",
    "wof:name":"Stadt-apotheke Irmgard Schottenloher",
    "wof:placetype":"venue"
},
  "geometry": {"coordinates":[8.818834,48.288433],"type":"Point"}
}