{
  "type": "Feature",
  "properties": {
    "iso:country":"DE",
    "sg:address":"Fabrikstr. 2",
    "sg:city":"Schopp",
    "sg:phone":"+49 6307/993065",
    "sg:postcode":"67707",
    "sg:province":"Rheinland-Pfalz",
    "wof:name":"El Deko Werbetechnik Gmbh",
    "wof:placetype":"venue"
},
  "geometry": {"coordinates":[7.6937570572,49.3537216187],"type":"Point"}
}