{
  "type": "Feature",
  "properties": {
    "iso:country":"DE",
    "sg:address":"Van-Gogh-Ring 37",
    "sg:city":"Wolfsburg",
    "sg:phone":"+49 5362/51396",
    "sg:postcode":"38442",
    "sg:province":"Niedersachsen",
    "wof:name":"Gerlinde Gundel Heilpraktikerin",
    "wof:placetype":"venue"
},
  "geometry": {"coordinates":[10.7016296387,52.4187355042],"type":"Point"}
}