{
  "type": "Feature",
  "properties": {
    "iso:country":"DE",
    "sg:address":"Im Bangert 2a",
    "sg:city":"Weilburg",
    "sg:phone":"+49 6471/7365",
    "sg:postcode":"35781",
    "sg:province":"Hessen",
    "wof:name":"Dhw Draht Und Extrusion Gmbh",
    "wof:placetype":"venue"
},
  "geometry": {"coordinates":[8.2632513046,50.4827232361],"type":"Point"}
}