{
  "type": "Feature",
  "properties": {
    "iso:country":"DE",
    "sg:address":"Baldhamer Str. 38",
    "sg:city":"Vaterstetten",
    "sg:phone":"+49 8106/302179",
    "sg:postcode":"85591",
    "sg:province":"Bayern",
    "wof:name":"Stephan Ruoff",
    "wof:placetype":"venue"
},
  "geometry": {"coordinates":[11.7773723602,48.1110191345],"type":"Point"}
}