{
  "type": "Feature",
  "properties": {
    "iso:country":"DE",
    "sg:address":"Zum Horstet 7",
    "sg:city":"Nideggen",
    "sg:phone":"+49 2427/8818",
    "sg:postcode":"52385",
    "sg:province":"Nordrhein-Westfalen",
    "wof:name":"U. Horstmann",
    "wof:placetype":"venue"
},
  "geometry": {"coordinates":[6.470507,50.704445],"type":"Point"}
}