{
  "type": "Feature",
  "properties": {
    "iso:country":"DE",
    "sg:address":"Exerzierplatz 26",
    "sg:city":"Kiel",
    "sg:phone":"+49 431/94114",
    "sg:postcode":"24103",
    "sg:province":"Schleswig-Holstein",
    "wof:name":"Dromarkt Kiel Drogerie-markt",
    "wof:placetype":"venue"
},
  "geometry": {"coordinates":[10.127607,54.322094],"type":"Point"}
}