{
  "type": "Feature",
  "properties": {
    "iso:country":"DE",
    "sg:address":"Dickenbruch 38",
    "sg:city":"Arnsberg",
    "sg:phone":"+49 2931/10336",
    "sg:postcode":"59821",
    "sg:province":"Nordrhein-Westfalen",
    "wof:name":"Reinhold K\u00f6per Rechtsanwalt",
    "wof:placetype":"venue"
},
  "geometry": {"coordinates":[8.0718660355,51.380645752],"type":"Point"}
}