{
  "type": "Feature",
  "properties": {
    "iso:country":"DE",
    "sg:address":"Wei\u00dfdornweg 13",
    "sg:city":"Dreieich",
    "sg:phone":"+49 6103/65590",
    "sg:postcode":"63303",
    "sg:province":"Hessen",
    "wof:name":"D. Pl\u00f6tner Ingenieur",
    "wof:placetype":"venue"
},
  "geometry": {"coordinates":[8.6716918945,50.0302886963],"type":"Point"}
}