{
  "type": "Feature",
  "properties": {
    "iso:country":"DE",
    "sg:address":"W\u00fcrzburger Str. 18",
    "sg:city":"Schweinfurt",
    "sg:phone":"+49 9721/22747",
    "sg:postcode":"97424",
    "sg:province":"Bayern",
    "wof:name":"Pfannen Valeri",
    "wof:placetype":"venue"
},
  "geometry": {"coordinates":[10.197426,50.025627],"type":"Point"}
}