{
  "type": "Feature",
  "properties": {
    "iso:country":"DE",
    "sg:address":"Hofst\u00e4dter Str. 9",
    "sg:city":"Sonnefeld",
    "sg:phone":"+49 9562/8134",
    "sg:postcode":"96242",
    "sg:province":"Bayern",
    "wof:name":"P. Fechter & P. Hofknecht",
    "wof:placetype":"venue"
},
  "geometry": {"coordinates":[11.13121,50.21759],"type":"Point"}
}