{
  "type": "Feature",
  "properties": {
    "iso:country":"DE",
    "sg:address":"Corray 8",
    "sg:city":"Zell",
    "sg:phone":"+49 6542/4230",
    "sg:postcode":"56856",
    "sg:province":"Rheinland-Pfalz",
    "wof:name":"Josef Hillan",
    "wof:placetype":"venue"
},
  "geometry": {"coordinates":[7.1807179451,50.0312690735],"type":"Point"}
}