{
  "type": "Feature",
  "properties": {
    "iso:country":"DE",
    "sg:address":"R\u00fcckersdorfer Str. 9",
    "sg:city":"R\u00f6thenbach",
    "sg:phone":"+49 911/578468",
    "sg:postcode":"90552",
    "sg:province":"Bayern",
    "wof:name":"Peter Linhardt",
    "wof:placetype":"venue"
},
  "geometry": {"coordinates":[11.2385854721,49.4826583862],"type":"Point"}
}