{
  "type": "Feature",
  "properties": {
    "iso:country":"DE",
    "sg:address":"Holl\u00e4ndische Str. 69",
    "sg:city":"Kassel",
    "sg:phone":"+49 561/85067",
    "sg:postcode":"34127",
    "sg:province":"Hessen",
    "wof:name":"Wilhelm Fricke Kg",
    "wof:placetype":"venue"
},
  "geometry": {"coordinates":[9.499996,51.325806],"type":"Point"}
}