{
  "type": "Feature",
  "properties": {
    "iso:country":"DE",
    "sg:address":"Rodelweg 1",
    "sg:city":"Hinte",
    "sg:postcode":"26759",
    "sg:province":"Niedersachsen",
    "wof:name":"W. Sch\u00e4fer Industrie Recycling",
    "wof:placetype":"venue"
},
  "geometry": {"coordinates":[7.1716542244,53.4377746582],"type":"Point"}
}