{
  "type": "Feature",
  "properties": {
    "iso:country":"DE",
    "sg:address":"R\u00f6merstr. 17",
    "sg:city":"Kempten",
    "sg:phone":"+49 831/61857",
    "sg:postcode":"87437",
    "sg:province":"Bayern",
    "wof:name":"P. Friesenegger",
    "wof:placetype":"venue"
},
  "geometry": {"coordinates":[10.3360862732,47.7107620239],"type":"Point"}
}