{
  "type": "Feature",
  "properties": {
    "iso:country":"DE",
    "sg:address":"Kleinstr. 1",
    "sg:city":"Zirndorf",
    "sg:phone":"+49 911/605066",
    "sg:postcode":"90513",
    "sg:province":"Bayern",
    "wof:name":"Rasta Sports",
    "wof:placetype":"venue"
},
  "geometry": {"coordinates":[10.955311,49.443577],"type":"Point"}
}