{
  "type": "Feature",
  "properties": {
    "iso:country":"DE",
    "sg:address":"Kleiner Domhof 14",
    "sg:city":"Minden",
    "sg:phone":"+49 571/27853",
    "sg:postcode":"32423",
    "sg:province":"Nordrhein-Westfalen",
    "wof:name":"Restaurant Domsch\u00e4nke",
    "wof:placetype":"venue"
},
  "geometry": {"coordinates":[8.91847229,52.2887001038],"type":"Point"}
}