{
  "type": "Feature",
  "properties": {
    "iso:country":"DE",
    "sg:address":"Industriestr. 32",
    "sg:city":"Mittelbiberach",
    "sg:phone":"+49 7351/9711",
    "sg:postcode":"88441",
    "sg:province":"Baden-W\u00fcrttemberg",
    "wof:name":"Emb-elektromaschinenbau Gmbh",
    "wof:placetype":"venue"
},
  "geometry": {"coordinates":[9.759226,48.092167],"type":"Point"}
}