{
  "type": "Feature",
  "properties": {
    "iso:country":"DE",
    "sg:address":"Bahnhofstra\u00dfe 17a",
    "sg:city":"Merseburg",
    "sg:phone":"+49 3461",
    "sg:postcode":"06114",
    "sg:province":"Sachsen-Anhalt",
    "wof:name":"Physiotherapie Am Tivoli",
    "wof:placetype":"venue"
},
  "geometry": {"coordinates":[-72.669937,41.740601],"type":"Point"}
}