{
  "type": "Feature",
  "properties": {
    "iso:country":"DE",
    "sg:address":"Silberherzstr. 12",
    "sg:city":"Saarlouis",
    "sg:phone":"+49 6831/43581",
    "sg:postcode":"66740",
    "sg:province":"Saarland",
    "wof:name":"M. Gondrom",
    "wof:placetype":"venue"
},
  "geometry": {"coordinates":[6.7498431206,49.3144493103],"type":"Point"}
}