{
  "type": "Feature",
  "properties": {
    "iso:country":"DE",
    "sg:address":"J\u00e4gerstr. 6",
    "sg:city":"Ulm",
    "sg:phone":"+49 731/9365110",
    "sg:postcode":"89081",
    "sg:province":"Baden-W\u00fcrttemberg",
    "wof:name":"Autohaus Michael Eitel E. K.",
    "wof:placetype":"venue"
},
  "geometry": {"coordinates":[9.955232,48.399807],"type":"Point"}
}