{
  "type": "Feature",
  "properties": {
    "iso:country":"DE",
    "sg:address":"Mauerseeweg 9",
    "sg:city":"Cloppenburg",
    "sg:postcode":"49661",
    "sg:province":"Niedersachsen",
    "wof:name":"Elisabeth Langemeyer Verwaltungs Gmbh",
    "wof:placetype":"venue"
},
  "geometry": {"coordinates":[8.00918,52.838703],"type":"Point"}
}