{
  "type": "Feature",
  "properties": {
    "iso:country":"DE",
    "sg:address":"Kronenstr. 61",
    "sg:city":"Pirmasens",
    "sg:phone":"+49 6331/283221",
    "sg:postcode":"66955",
    "sg:province":"Rheinland-Pfalz",
    "wof:name":"Peter Peifer Steuerberater",
    "wof:placetype":"venue"
},
  "geometry": {"coordinates":[7.6017217636,49.1920967102],"type":"Point"}
}