{
  "type": "Feature",
  "properties": {
    "iso:country":"DE",
    "sg:address":"Im Herbrand 14",
    "sg:city":"Ahlen",
    "sg:postcode":"59229",
    "sg:province":"Nordrhein-Westfalen",
    "wof:name":"Horst Gmbh & Co. Kg",
    "wof:placetype":"venue"
},
  "geometry": {"coordinates":[7.9001741409,51.7619400024],"type":"Point"}
}