{
  "type": "Feature",
  "properties": {
    "iso:country":"DE",
    "sg:address":"G\u00f6hrdestr. 1",
    "sg:city":"Bad Bevensen",
    "sg:phone":"+49 5821/43388",
    "sg:postcode":"29549",
    "sg:province":"Niedersachsen",
    "wof:name":"U. Umland Ramlow Modewaren",
    "wof:placetype":"venue"
},
  "geometry": {"coordinates":[10.588576,53.079254],"type":"Point"}
}