{
  "type": "Feature",
  "properties": {
    "iso:country":"DE",
    "sg:address":"Gutleutstr 169-171",
    "sg:city":"Frankfurt",
    "sg:phone":"+49 69/231455",
    "sg:postcode":"60327",
    "sg:province":"Hessen",
    "wof:name":"Erich Hummel Gmbh",
    "wof:placetype":"venue"
},
  "geometry": {"coordinates":[8.65888,50.101189],"type":"Point"}
}