{
  "type": "Feature",
  "properties": {
    "iso:country":"DE",
    "sg:address":"Mathildenstr. 10/1",
    "sg:city":"Ludwigsburg",
    "sg:phone":"+49 7141/906440",
    "sg:postcode":"71638",
    "sg:province":"Baden-W\u00fcrttemberg",
    "wof:name":"Media Cluster Gmbh",
    "wof:placetype":"venue"
},
  "geometry": {"coordinates":[9.189248,48.89399],"type":"Point"}
}