{
  "type": "Feature",
  "properties": {
    "iso:country":"DE",
    "sg:address":"Ringstr. 16",
    "sg:city":"Auhagen",
    "sg:phone":"+49 5033/99040",
    "sg:postcode":"31553",
    "sg:province":"Niedersachsen",
    "wof:name":"Wilhelm Meyer",
    "wof:placetype":"venue"
},
  "geometry": {"coordinates":[9.2890701294,52.3932876587],"type":"Point"}
}