{
  "type": "Feature",
  "properties": {
    "iso:country":"DE",
    "sg:address":"Frankfurter Str. 20",
    "sg:city":"Hattersheim",
    "sg:phone":"+49 6190/919818",
    "sg:postcode":"65795",
    "sg:province":"Hessen",
    "wof:name":"Wiso Datenverarb. F. Wirtsch. & Soziales Gmbh",
    "wof:placetype":"venue"
},
  "geometry": {"coordinates":[8.4911661148,50.0706710815],"type":"Point"}
}