{
  "type": "Feature",
  "properties": {
    "iso:country":"DE",
    "sg:address":"F\u00fcrnsaler Str. 29",
    "sg:city":"Dornhan",
    "sg:phone":"+49 4974/551368",
    "sg:postcode":"72175",
    "sg:province":"Baden-W\u00fcrttemberg",
    "wof:name":"Wilhelm Gr\u00d6zinger Strumpffabrik Gmbh",
    "wof:placetype":"venue"
},
  "geometry": {"coordinates":[8.50959,48.35218],"type":"Point"}
}