{
  "type": "Feature",
  "properties": {
    "iso:country":"DE",
    "sg:address":"Deggingstr. 87",
    "sg:city":"Dortmund",
    "sg:phone":"+49 231/5860119",
    "sg:postcode":"44141",
    "sg:province":"Nordrhein-Westfalen",
    "wof:name":"Wolfgang Schneider Rechtsanwalt U. Notar",
    "wof:placetype":"venue"
},
  "geometry": {"coordinates":[7.4861707687,51.5037918091],"type":"Point"}
}