{
  "type": "Feature",
  "properties": {
    "iso:country":"DE",
    "sg:address":"Bahnhofstr. 9",
    "sg:city":"F\u00fcrstenberg",
    "sg:phone":"+49 33093/38231",
    "sg:postcode":"16798",
    "sg:province":"Brandenburg",
    "wof:name":"Klaus-dieter Biesecke",
    "wof:placetype":"venue"
},
  "geometry": {"coordinates":[13.142611,53.185116],"type":"Point"}
}