{
  "type": "Feature",
  "properties": {
    "iso:country":"DE",
    "sg:address":"Parsevalstr. 20",
    "sg:city":"Bitterfeld",
    "sg:phone":"+49 3493/77777",
    "sg:postcode":"06749",
    "sg:province":"Sachsen-Anhalt",
    "wof:name":"Fsb Fernmeldeanlagen- Service-bitterfeld Gmbh",
    "wof:placetype":"venue"
},
  "geometry": {"coordinates":[12.2983083725,51.6357574463],"type":"Point"}
}