{
  "type": "Feature",
  "properties": {
    "iso:country":"DE",
    "sg:address":"Akazienstr. 8",
    "sg:city":"Bad Zwischenahn",
    "sg:phone":"+49 441/9699094",
    "sg:postcode":"26160",
    "sg:province":"Niedersachsen",
    "wof:name":"Akma Munderloh Gmbh",
    "wof:placetype":"venue"
},
  "geometry": {"coordinates":[8.1295700073,53.1786613464],"type":"Point"}
}