{
  "type": "Feature",
  "properties": {
    "iso:country":"DE",
    "sg:address":"Carl-Benz-Str. 128",
    "sg:city":"Mannheim",
    "sg:phone":"+49 621/331848",
    "sg:postcode":"68167",
    "sg:province":"Baden-W\u00fcrttemberg",
    "wof:name":"Ute Offenbacher",
    "wof:placetype":"venue"
},
  "geometry": {"coordinates":[8.488234,49.498131],"type":"Point"}
}