{
  "type": "Feature",
  "properties": {
    "iso:country":"DE",
    "sg:address":"Am Unteren Marienbach 2",
    "sg:city":"Schweinfurt",
    "sg:phone":"+49 9721/2019170",
    "sg:postcode":"97421",
    "sg:province":"Bayern",
    "wof:name":"Michael Siebenson Gmbh & Co. Kg",
    "wof:placetype":"venue"
},
  "geometry": {"coordinates":[10.2381706238,50.0457267761],"type":"Point"}
}