{
  "type": "Feature",
  "properties": {
    "iso:country":"DE",
    "sg:address":"Brockdorffstr. 16",
    "sg:city":"Hamburg",
    "sg:postcode":"22149",
    "sg:province":"Hamburg",
    "wof:name":"Scientia Consulting Gmbh",
    "wof:placetype":"venue"
},
  "geometry": {"coordinates":[10.1547393799,53.5964546204],"type":"Point"}
}