{
  "type": "Feature",
  "properties": {
    "iso:country":"DE",
    "sg:address":"Schwimmbadweg 30",
    "sg:city":"Gudensberg",
    "sg:postcode":"34281",
    "sg:province":"Hessen",
    "wof:name":"Schulsternwarte Gudensberg",
    "wof:placetype":"venue"
},
  "geometry": {"coordinates":[9.360353,51.172424],"type":"Point"}
}