{
  "type": "Feature",
  "properties": {
    "iso:country":"DE",
    "sg:address":"Hauptstr. 21",
    "sg:city":"Wiesen",
    "sg:phone":"+49 6096/1092",
    "sg:postcode":"63831",
    "sg:province":"Bayern",
    "wof:name":"Beate G\u00f6tz",
    "wof:placetype":"venue"
},
  "geometry": {"coordinates":[9.3686532974,50.1094779968],"type":"Point"}
}