{
  "type": "Feature",
  "properties": {
    "iso:country":"DE",
    "sg:address":"Wakenitzufer 1c",
    "sg:city":"L\u00fcbeck",
    "sg:phone":"+49 451/793885",
    "sg:postcode":"23564",
    "sg:province":"Schleswig-Holstein",
    "wof:name":"Manfred Quandt Binnenschiffahrtsunternehmen",
    "wof:placetype":"venue"
},
  "geometry": {"coordinates":[10.704025,53.868729],"type":"Point"}
}