{
  "type": "Feature",
  "properties": {
    "iso:country":"DE",
    "sg:address":"Leistikowstr. 4",
    "sg:city":"Cottbus",
    "sg:phone":"+49 355/727400",
    "sg:postcode":"03042",
    "sg:province":"Brandenburg",
    "wof:name":"Brigitte Westphal Architektin",
    "wof:placetype":"venue"
},
  "geometry": {"coordinates":[14.363604,51.75539],"type":"Point"}
}