{
  "type": "Feature",
  "properties": {
    "iso:country":"DE",
    "sg:address":"Weberstr. 9",
    "sg:city":"N\u00fcrtingen",
    "sg:phone":"+49 7022/738960",
    "sg:postcode":"72622",
    "sg:province":"Baden-W\u00fcrttemberg",
    "wof:name":"Andreas Str\u00d6bele",
    "wof:placetype":"venue"
},
  "geometry": {"coordinates":[9.33992,48.638371],"type":"Point"}
}