{
  "type": "Feature",
  "properties": {
    "iso:country":"DE",
    "sg:address":"Rathausstr. 24",
    "sg:city":"Neckarsulm",
    "sg:phone":"+49 7132/5335",
    "sg:postcode":"74172",
    "sg:province":"Baden-W\u00fcrttemberg",
    "wof:name":"Simone K\u00f6hl",
    "wof:placetype":"venue"
},
  "geometry": {"coordinates":[9.227254,49.190708],"type":"Point"}
}