{
  "type": "Feature",
  "properties": {
    "iso:country":"DE",
    "sg:address":"Goslarsche Str. 20",
    "sg:city":"Wolfenb\u00fcttel",
    "sg:phone":"+49 5331/44058",
    "sg:postcode":"38304",
    "sg:province":"Niedersachsen",
    "wof:name":"Alex-horst Kreit",
    "wof:placetype":"venue"
},
  "geometry": {"coordinates":[10.522736,52.161739],"type":"Point"}
}