{
  "type": "Feature",
  "properties": {
    "iso:country":"DE",
    "sg:address":"Kaiserswertherstrasse 400",
    "sg:city":"D\u00fcsseldorf",
    "sg:phone":"+49 211/4350103",
    "sg:postcode":"40474",
    "sg:province":"Nordrhein-Westfalen",
    "wof:name":"Triggerfish Design",
    "wof:placetype":"venue"
},
  "geometry": {"coordinates":[6.7543621063,51.2589645386],"type":"Point"}
}