{
  "type": "Feature",
  "properties": {
    "iso:country":"DE",
    "sg:address":"Zollnerstr. 18",
    "sg:city":"Bamberg",
    "sg:phone":"+49 951/31794",
    "sg:postcode":"96052",
    "sg:province":"Bayern",
    "wof:name":"Jeans Shop Helmut Klein",
    "wof:placetype":"venue"
},
  "geometry": {"coordinates":[10.901079,49.902809],"type":"Point"}
}