{
  "type": "Feature",
  "properties": {
    "iso:country":"DE",
    "sg:address":"Karl-Helbig-Str. 14",
    "sg:city":"Leipzig",
    "sg:phone":"+49 341/5852888",
    "sg:postcode":"04159",
    "sg:province":"Sachsen",
    "wof:name":"Christa Nobis",
    "wof:placetype":"venue"
},
  "geometry": {"coordinates":[12.3337831497,51.374130249],"type":"Point"}
}