{
  "type": "Feature",
  "properties": {
    "iso:country":"DE",
    "sg:address":"Holzer Str. 5",
    "sg:city":"Lindlar",
    "sg:phone":"+49 2266/8574",
    "sg:postcode":"51789",
    "sg:province":"Nordrhein-Westfalen",
    "wof:name":"Hugo Stiefelhagen",
    "wof:placetype":"venue"
},
  "geometry": {"coordinates":[7.366406,50.997429],"type":"Point"}
}