{
  "type": "Feature",
  "properties": {
    "iso:country":"DE",
    "sg:address":"Heilsbergweg 32",
    "sg:city":"Gottmadingen",
    "sg:phone":"+49 7731/71511",
    "sg:postcode":"78244",
    "sg:province":"Baden-W\u00fcrttemberg",
    "wof:name":"Reinhard Graf Gmbh & Co. Kg",
    "wof:placetype":"venue"
},
  "geometry": {"coordinates":[8.7792234421,47.7416763306],"type":"Point"}
}