{
  "type": "Feature",
  "properties": {
    "iso:country":"DE",
    "sg:address":"H\u00f6cherbergstr. 14",
    "sg:city":"Neunkirchen",
    "sg:phone":"+49 6821/53303",
    "sg:postcode":"66540",
    "sg:province":"Saarland",
    "wof:name":"Ostertalhalle",
    "wof:placetype":"venue"
},
  "geometry": {"coordinates":[7.214867115,49.3817176819],"type":"Point"}
}