{
  "type": "Feature",
  "properties": {
    "iso:country":"DE",
    "sg:address":"Kaiserstr. 34",
    "sg:city":"St. Ingbert",
    "sg:phone":"+49 6894/2675",
    "sg:postcode":"66386",
    "sg:province":"Saarland",
    "wof:name":"K. Gregorius Inh.reinhard Engel",
    "wof:placetype":"venue"
},
  "geometry": {"coordinates":[7.1143569946,49.2772636414],"type":"Point"}
}