{
  "type": "Feature",
  "properties": {
    "iso:country":"DE",
    "sg:address":"Gro\u00dfe Str. 60",
    "sg:city":"Vechta",
    "sg:phone":"+49 4441/4045",
    "sg:postcode":"49377",
    "sg:province":"Niedersachsen",
    "wof:name":"Ingo Schumacher Ingenieur",
    "wof:placetype":"venue"
},
  "geometry": {"coordinates":[8.2868528366,52.7290763855],"type":"Point"}
}