{
  "type": "Feature",
  "properties": {
    "iso:country":"DE",
    "sg:address":"Residenzplatz 1",
    "sg:city":"W\u00fcrzburg",
    "sg:phone":"+49 931/54670",
    "sg:postcode":"97070",
    "sg:province":"Bayern",
    "wof:name":"Residenz-gastst\u00e4tten",
    "wof:placetype":"venue"
},
  "geometry": {"coordinates":[9.9370031357,49.7920913696],"type":"Point"}
}