{
  "type": "Feature",
  "properties": {
    "iso:country":"DE",
    "sg:address":"Hauptstr. 64",
    "sg:city":"Dillenburg",
    "sg:phone":"+49 2771/32142",
    "sg:postcode":"35684",
    "sg:province":"Hessen",
    "wof:name":"Struth-apotheke Apotheker Heinz Raab E. Kfm.",
    "wof:placetype":"venue"
},
  "geometry": {"coordinates":[8.285884,50.739429],"type":"Point"}
}