{
  "type": "Feature",
  "properties": {
    "iso:country":"DE",
    "sg:address":"Robert-Leicht-Str. 173",
    "sg:city":"Stuttgart",
    "sg:postcode":"70569",
    "sg:province":"Baden-W\u00fcrttemberg",
    "wof:name":"Csa Computer-service- Und Anwendung Gmbh",
    "wof:placetype":"venue"
},
  "geometry": {"coordinates":[9.1110906601,48.7446022034],"type":"Point"}
}