{
  "type": "Feature",
  "properties": {
    "iso:country":"DE",
    "sg:address":"Kreuzstr. 59",
    "sg:city":"Oelde",
    "sg:postcode":"59302",
    "sg:province":"Nordrhein-Westfalen",
    "wof:name":"Aquasystem Wasser- Und Umwelttechnik Gmbh",
    "wof:placetype":"venue"
},
  "geometry": {"coordinates":[8.1575841904,51.8249320984],"type":"Point"}
}