{
  "type": "Feature",
  "properties": {
    "iso:country":"DE",
    "sg:address":"Bahnhofstr. 20",
    "sg:city":"Stuttgart",
    "sg:phone":"+49 711/559377",
    "sg:postcode":"70372",
    "sg:province":"Baden-W\u00fcrttemberg",
    "wof:name":"Istanbul-kebap",
    "wof:placetype":"venue"
},
  "geometry": {"coordinates":[9.2171497345,48.8022232056],"type":"Point"}
}