{
  "type": "Feature",
  "properties": {
    "iso:country":"DE",
    "sg:address":"Abflugebenen",
    "sg:city":"Frankfurt",
    "sg:phone":"+49 69",
    "sg:postcode":"60549",
    "sg:province":"Hessen",
    "wof:name":"Ltur Tourismus Ag Flughafen Frankfurt",
    "wof:placetype":"venue"
},
  "geometry": {"coordinates":[8.57003,50.050705],"type":"Point"}
}