{
  "type": "Feature",
  "properties": {
    "iso:country":"DE",
    "sg:address":"Gerwigplatz 20",
    "sg:city":"Freiburg",
    "sg:phone":"+49 761/75558",
    "sg:postcode":"79102",
    "sg:province":"Baden-W\u00fcrttemberg",
    "wof:name":"Wiehre Bahnhof",
    "wof:placetype":"venue"
},
  "geometry": {"coordinates":[7.8554320335,47.9831695557],"type":"Point"}
}