{
  "type": "Feature",
  "properties": {
    "iso:country":"DE",
    "sg:address":"Lingener Str. 2",
    "sg:city":"L\u00fcnne",
    "sg:phone":"+49 5906/1789",
    "sg:postcode":"48480",
    "sg:province":"Niedersachsen",
    "wof:name":"Hermann Weusthof",
    "wof:placetype":"venue"
},
  "geometry": {"coordinates":[7.42486,52.430267],"type":"Point"}
}