{
  "type": "Feature",
  "properties": {
    "iso:country":"DE",
    "sg:address":"Messingweg 7",
    "sg:city":"Senden",
    "sg:phone":"+49 2597/1558",
    "sg:postcode":"48308",
    "sg:province":"Nordrhein-Westfalen",
    "wof:name":"Udo Schicht Gmbh",
    "wof:placetype":"venue"
},
  "geometry": {"coordinates":[7.4834952354,51.8456001282],"type":"Point"}
}