{
  "type": "Feature",
  "properties": {
    "iso:country":"DE",
    "sg:address":"Stommeler Str. 68",
    "sg:city":"K\u00f6ln",
    "sg:phone":"+49 221/5994102",
    "sg:postcode":"50739",
    "sg:province":"Nordrhein-Westfalen",
    "wof:name":"Karl Heinz Steinig Steuerberater",
    "wof:placetype":"venue"
},
  "geometry": {"coordinates":[6.9073967934,50.9993553162],"type":"Point"}
}