{
  "type": "Feature",
  "properties": {
    "iso:country":"DE",
    "sg:address":"Adolf-Damaschke-Str. 16",
    "sg:city":"G\u00f6ppingen",
    "sg:phone":"+49 7161/79663",
    "sg:postcode":"73037",
    "sg:province":"Baden-W\u00fcrttemberg",
    "wof:name":"Vereinsgastst\u00e4tte Siedler- Und Gartenfreunde G\u00f6ppingen",
    "wof:placetype":"venue"
},
  "geometry": {"coordinates":[9.6769800186,48.6958389282],"type":"Point"}
}