{
  "type": "Feature",
  "properties": {
    "iso:country":"DE",
    "sg:address":"Dungestr 84",
    "sg:city":"Arnsberg",
    "sg:phone":"+49 2932/90210",
    "sg:postcode":"59757",
    "sg:province":"Nordrhein-Westfalen",
    "wof:name":"Bss Beratung Und Software-systeme Gmbh",
    "wof:placetype":"venue"
},
  "geometry": {"coordinates":[7.960018158,51.4264068604],"type":"Point"}
}