{
  "type": "Feature",
  "properties": {
    "iso:country":"DE",
    "sg:address":"Heidberg 2",
    "sg:city":"Sch\u00f6new\u00f6rde",
    "sg:phone":"+49 5835/7842",
    "sg:postcode":"29396",
    "sg:province":"Niedersachsen",
    "wof:name":"A. Und K. K\u00f6hler",
    "wof:placetype":"venue"
},
  "geometry": {"coordinates":[10.6247682571,52.6345939636],"type":"Point"}
}