{
  "type": "Feature",
  "properties": {
    "iso:country":"DE",
    "sg:address":"Bergstr. 70",
    "sg:city":"Hopsten",
    "sg:phone":"+49 4954/57590",
    "sg:postcode":"48496",
    "sg:province":"Nordrhein-Westfalen",
    "wof:name":"Sparkasse Ibbenb\u00fcren",
    "wof:placetype":"venue"
},
  "geometry": {"coordinates":[7.592569,52.431141],"type":"Point"}
}