{
  "type": "Feature",
  "properties": {
    "iso:country":"DE",
    "sg:address":"Altheimer Str. 14",
    "sg:city":"Dieburg",
    "sg:phone":"+49 6071/22608",
    "sg:postcode":"64807",
    "sg:province":"Hessen",
    "wof:name":"Heinrich Kern Stra\u00dfen - Und Tiefbau Gmbh",
    "wof:placetype":"venue"
},
  "geometry": {"coordinates":[8.8579549789,49.9039573669],"type":"Point"}
}