{
  "type": "Feature",
  "properties": {
    "iso:country":"DE",
    "sg:address":"Eppendorfer Landstr. 54",
    "sg:city":"Hamburg",
    "sg:phone":"+49 40/476590",
    "sg:postcode":"20249",
    "sg:province":"Hamburg",
    "wof:name":"Karl-heinz Samrei",
    "wof:placetype":"venue"
},
  "geometry": {"coordinates":[9.986201,53.588318],"type":"Point"}
}