{
  "type": "Feature",
  "properties": {
    "iso:country":"DE",
    "sg:address":"Am B\u00e4renkamp 20 b",
    "sg:city":"D\u00fcsseldorf",
    "sg:phone":"+49 211/754821",
    "sg:postcode":"40589",
    "sg:province":"Nordrhein-Westfalen",
    "wof:name":"K\u00fcnzel Und K\u00fcnzel Rechtsanw\u00e4lte",
    "wof:placetype":"venue"
},
  "geometry": {"coordinates":[6.804090023,51.1710662842],"type":"Point"}
}