{
  "type": "Feature",
  "properties": {
    "iso:country":"DE",
    "sg:address":"Br\u00e4cher Heide 14a",
    "sg:city":"Wiehl",
    "sg:phone":"+49 2262/701135",
    "sg:postcode":"51674",
    "sg:province":"Nordrhein-Westfalen",
    "wof:name":"L\u00fcer & Partner Konstruktions- Und",
    "wof:placetype":"venue"
},
  "geometry": {"coordinates":[7.456715107,50.9527282715],"type":"Point"}
}