{
  "type": "Feature",
  "properties": {
    "iso:country":"DE",
    "sg:address":"Hoher Weg 24",
    "sg:city":"Harsum",
    "sg:phone":"+49 5127/6544",
    "sg:postcode":"31177",
    "sg:province":"Niedersachsen",
    "wof:name":"Bernhard Philipps",
    "wof:placetype":"venue"
},
  "geometry": {"coordinates":[9.9623,52.206276],"type":"Point"}
}