{
  "type": "Feature",
  "properties": {
    "iso:country":"DE",
    "sg:address":"Marktstr. 10",
    "sg:city":"Blaubeuren",
    "sg:phone":"+49 7344/5514",
    "sg:postcode":"89143",
    "sg:province":"Baden-W\u00fcrttemberg",
    "wof:name":"B. Gottselig",
    "wof:placetype":"venue"
},
  "geometry": {"coordinates":[9.7828226089,48.4129600525],"type":"Point"}
}