{
  "type": "Feature",
  "properties": {
    "iso:country":"DE",
    "sg:address":"Lilienthalstr. 29",
    "sg:city":"Mainz",
    "sg:phone":"+49 6131/54557",
    "sg:postcode":"55131",
    "sg:province":"Rheinland-Pfalz",
    "wof:name":"Christa Domschky Masseurin",
    "wof:placetype":"venue"
},
  "geometry": {"coordinates":[8.271878,49.983719],"type":"Point"}
}