{
  "type": "Feature",
  "properties": {
    "iso:country":"DE",
    "sg:address":"Am Elbbach 1",
    "sg:city":"Hadamar",
    "sg:phone":"+49 6433/5610",
    "sg:postcode":"65589",
    "sg:province":"Hessen",
    "wof:name":"Aqua Concept Gmbh",
    "wof:placetype":"venue"
},
  "geometry": {"coordinates":[8.044974,50.449223],"type":"Point"}
}