{
  "type": "Feature",
  "properties": {
    "iso:country":"DE",
    "sg:address":"Albrecht-D\u00fcrer-Str. 15",
    "sg:city":"K\u00f6ngen",
    "sg:phone":"+49 7024/84075",
    "sg:postcode":"73257",
    "sg:province":"Baden-W\u00fcrttemberg",
    "wof:name":"Oliver Niepel",
    "wof:placetype":"venue"
},
  "geometry": {"coordinates":[9.3644094467,48.6891212463],"type":"Point"}
}