{
  "type": "Feature",
  "properties": {
    "iso:country":"DE",
    "sg:address":"Garzer Weg 4",
    "sg:city":"Lindenberg",
    "sg:postcode":"16928",
    "sg:province":"Brandenburg",
    "wof:name":"Agrar-erzeuger-gemeinschaft T\u00fcchen Eg",
    "wof:placetype":"venue"
},
  "geometry": {"coordinates":[12.128453,53.033363],"type":"Point"}
}