{
  "type": "Feature",
  "properties": {
    "iso:country":"DE",
    "sg:address":"Bismarckstr. 41",
    "sg:city":"Borkum",
    "sg:phone":"+49 4922/1314",
    "sg:postcode":"26757",
    "sg:province":"Niedersachsen",
    "wof:name":"W. Stanienda Augenoptiker",
    "wof:placetype":"venue"
},
  "geometry": {"coordinates":[6.6591639519,53.587059021],"type":"Point"}
}