{
  "type": "Feature",
  "properties": {
    "iso:country":"DE",
    "sg:address":"Tulpenweg 1",
    "sg:city":"Malterdingen",
    "sg:phone":"+49 7644/6589",
    "sg:postcode":"79364",
    "sg:province":"Baden-W\u00fcrttemberg",
    "wof:name":"Dieter G\u00f6pel Masseur",
    "wof:placetype":"venue"
},
  "geometry": {"coordinates":[7.784802,48.157524],"type":"Point"}
}