{
  "type": "Feature",
  "properties": {
    "iso:country":"DE",
    "sg:address":"Hamburger Str. 24",
    "sg:city":"Dresden",
    "sg:phone":"+49 351/4920200",
    "sg:postcode":"01067",
    "sg:province":"Sachsen",
    "wof:name":"Volkswagen Zentrum Dresden Ohg",
    "wof:placetype":"venue"
},
  "geometry": {"coordinates":[13.7024822235,51.0592384338],"type":"Point"}
}