{
  "type": "Feature",
  "properties": {
    "iso:country":"DE",
    "sg:address":"Segeberger Str. 1",
    "sg:city":"Wahlstedt",
    "sg:postcode":"23812",
    "sg:province":"Schleswig-Holstein",
    "wof:name":"Presse Service Nord Gmbh",
    "wof:placetype":"venue"
},
  "geometry": {"coordinates":[10.215669632,53.9519615173],"type":"Point"}
}