{
  "type": "Feature",
  "properties": {
    "iso:country":"DE",
    "sg:address":"Burgstr. 33",
    "sg:city":"Alpen",
    "sg:phone":"+49 2802/3508",
    "sg:postcode":"46519",
    "sg:province":"Nordrhein-Westfalen",
    "wof:name":"H. -u. Hermsen",
    "wof:placetype":"venue"
},
  "geometry": {"coordinates":[6.513548,51.5765],"type":"Point"}
}