{
  "type": "Feature",
  "properties": {
    "iso:country":"DE",
    "sg:address":"Grimmstr. 17",
    "sg:city":"Berlin",
    "sg:phone":"+49 30/6919010",
    "sg:postcode":"10967",
    "sg:province":"Berlin",
    "wof:name":"K\u00f6rte-apotheke",
    "wof:placetype":"venue"
},
  "geometry": {"coordinates":[13.413764,52.492115],"type":"Point"}
}