{
  "type": "Feature",
  "properties": {
    "iso:country":"DE",
    "sg:address":"Eichenweg 18",
    "sg:city":"K\u00f6nigs Wusterhausen",
    "sg:postcode":"15711",
    "sg:province":"Brandenburg",
    "wof:name":"K\u00f6ster & Miercke Gmbh",
    "wof:placetype":"venue"
},
  "geometry": {"coordinates":[13.605834,52.299168],"type":"Point"}
}