{
  "type": "Feature",
  "properties": {
    "iso:country":"DE",
    "sg:address":"Fichtenweg 18",
    "sg:city":"Sch\u00f6mberg",
    "sg:phone":"+49 7084/7561",
    "sg:postcode":"75328",
    "sg:province":"Baden-W\u00fcrttemberg",
    "wof:name":"Sch\u00e4fer Krankengymnast",
    "wof:placetype":"venue"
},
  "geometry": {"coordinates":[8.651469,48.786121],"type":"Point"}
}