{
  "type": "Feature",
  "properties": {
    "iso:country":"DE",
    "sg:address":"Wilhelm-Arndt-Weg 1",
    "sg:city":"Seebad Heringsdorf",
    "sg:postcode":"17424",
    "sg:province":"Mecklenburg-Vorpommern",
    "wof:name":"Beste Urlaubsquatiere Auf Der Sonneninsel Usedom",
    "wof:placetype":"venue"
},
  "geometry": {"coordinates":[14.150764,53.953926],"type":"Point"}
}