{
  "type": "Feature",
  "properties": {
    "iso:country":"DE",
    "sg:address":"Goseriede 15",
    "sg:city":"Hannover",
    "sg:phone":"+49 511/131565",
    "sg:postcode":"30159",
    "sg:province":"Niedersachsen",
    "wof:name":"Nieders\u00e4chsischer Heimatbund E. V.",
    "wof:placetype":"venue"
},
  "geometry": {"coordinates":[9.7312602997,52.3780937195],"type":"Point"}
}