{
  "type": "Feature",
  "properties": {
    "iso:country":"DE",
    "sg:address":"Postfach 11 02",
    "sg:city":"Geisenheim",
    "sg:phone":"+49 6722/981043",
    "sg:postcode":"65358",
    "sg:province":"Hessen",
    "wof:name":"Die Netzpartner",
    "wof:placetype":"venue"
},
  "geometry": {"coordinates":[7.9665899277,49.9839706421],"type":"Point"}
}