{
  "type": "Feature",
  "properties": {
    "iso:country":"DE",
    "sg:address":"Hardtstr. 26",
    "sg:city":"Bad Schwalbach",
    "sg:phone":"+49 6124/3622",
    "sg:postcode":"65307",
    "sg:province":"Hessen",
    "wof:name":"Eberhardt Hoffmann Architekt",
    "wof:placetype":"venue"
},
  "geometry": {"coordinates":[8.071644,50.145435],"type":"Point"}
}