{
  "type": "Feature",
  "properties": {
    "iso:country":"DE",
    "sg:address":"Hauptstr. 15",
    "sg:city":"Malbergweich",
    "sg:phone":"+49 6563/2278",
    "sg:postcode":"54655",
    "sg:province":"Rheinland-Pfalz",
    "wof:name":"Mathias Freis & Sohn",
    "wof:placetype":"venue"
},
  "geometry": {"coordinates":[6.5555291176,50.0544395447],"type":"Point"}
}