{
  "type": "Feature",
  "properties": {
    "iso:country":"DE",
    "sg:address":"Forststr. 98",
    "sg:city":"K\u00f6ln",
    "sg:phone":"+49 221/7904089",
    "sg:postcode":"50767",
    "sg:province":"Nordrhein-Westfalen",
    "wof:name":"Rote Funken K\u00f6ln Marketing Gmbh",
    "wof:placetype":"venue"
},
  "geometry": {"coordinates":[6.9086518288,51.0085029602],"type":"Point"}
}