{
  "type": "Feature",
  "properties": {
    "iso:country":"DE",
    "sg:address":"Alte Str. 9",
    "sg:city":"Loburg",
    "sg:phone":"+49 39245/2683",
    "sg:postcode":"39279",
    "sg:province":"Sachsen-Anhalt",
    "wof:name":"Peter G\u00f6rner",
    "wof:placetype":"venue"
},
  "geometry": {"coordinates":[12.075435,52.114784],"type":"Point"}
}