{
  "type": "Feature",
  "properties": {
    "iso:country":"DE",
    "sg:address":"Obere Bahnhofstr. 48",
    "sg:city":"Immenhausen",
    "sg:phone":"+49 5673/7205",
    "sg:postcode":"34376",
    "sg:province":"Hessen",
    "wof:name":"Norbert Bode",
    "wof:placetype":"venue"
},
  "geometry": {"coordinates":[9.474381,51.42767],"type":"Point"}
}