{
  "type": "Feature",
  "properties": {
    "iso:country":"DE",
    "sg:address":"Im Tal 24",
    "sg:city":"Bergheim",
    "sg:phone":"+49 2238/41905",
    "sg:postcode":"50129",
    "sg:province":"Nordrhein-Westfalen",
    "wof:name":"Ferdinand Rams",
    "wof:placetype":"venue"
},
  "geometry": {"coordinates":[6.7525668144,50.9688301086],"type":"Point"}
}