{
  "type": "Feature",
  "properties": {
    "iso:country":"DE",
    "sg:address":"Kattenturmer Heerstr. 136",
    "sg:city":"Bremen",
    "sg:phone":"+49 421/876214",
    "sg:postcode":"28277",
    "sg:province":"Bremen",
    "wof:name":"A. Winter",
    "wof:placetype":"venue"
},
  "geometry": {"coordinates":[8.815145,53.04118],"type":"Point"}
}