{
  "type": "Feature",
  "properties": {
    "iso:country":"DE",
    "sg:address":"Gerberstr. 1",
    "sg:city":"Offenburg",
    "sg:phone":"+49 781/76626",
    "sg:postcode":"77652",
    "sg:province":"Baden-W\u00fcrttemberg",
    "wof:name":"Dkv Deutsche Krankenversicherung Ag",
    "wof:placetype":"venue"
},
  "geometry": {"coordinates":[7.9429979324,48.468421936],"type":"Point"}
}