{
  "type": "Feature",
  "properties": {
    "iso:country":"DE",
    "sg:address":"Messestr. 18",
    "sg:city":"Rostock",
    "sg:phone":"+49 381/7698508",
    "sg:postcode":"18106",
    "sg:province":"Mecklenburg-Vorpommern",
    "wof:name":"K\u00f6nnemann & Schwarz Ohg Bowling-center Rostock",
    "wof:placetype":"venue"
},
  "geometry": {"coordinates":[12.054011,54.114391],"type":"Point"}
}