{
  "type": "Feature",
  "properties": {
    "iso:country":"DE",
    "sg:address":"Malterstr. 14",
    "sg:city":"Koblenz",
    "sg:phone":"+49 261/23286",
    "sg:postcode":"56070",
    "sg:province":"Rheinland-Pfalz",
    "wof:name":"Eduard Herzig",
    "wof:placetype":"venue"
},
  "geometry": {"coordinates":[7.55316,50.379398],"type":"Point"}
}