{
  "type": "Feature",
  "properties": {
    "iso:country":"DE",
    "sg:address":"Hauptstr. 91",
    "sg:city":"Stuttgart",
    "sg:phone":"+49 711/734478",
    "sg:postcode":"70563",
    "sg:province":"Baden-W\u00fcrttemberg",
    "wof:name":"Saunabau Hermann Silgmann Gmbh & Co. Holzbau Kg",
    "wof:placetype":"venue"
},
  "geometry": {"coordinates":[9.10198,48.730019],"type":"Point"}
}