{
  "type": "Feature",
  "properties": {
    "iso:country":"DE",
    "sg:address":"Am Marienbach 6",
    "sg:city":"Fraunberg",
    "sg:postcode":"85447",
    "sg:province":"Bayern",
    "wof:name":"Rampf & Sohn Gmbh",
    "wof:placetype":"venue"
},
  "geometry": {"coordinates":[12.0363101959,48.3669929504],"type":"Point"}
}