{
  "type": "Feature",
  "properties": {
    "iso:country":"DE",
    "sg:address":"Harrogate Allee 10",
    "sg:city":"Bielefeld",
    "sg:phone":"+49 521/22326",
    "sg:postcode":"33604",
    "sg:province":"Nordrhein-Westfalen",
    "wof:name":"Rolf Labey",
    "wof:placetype":"venue"
},
  "geometry": {"coordinates":[8.5587787628,52.011554718],"type":"Point"}
}