{
  "type": "Feature",
  "properties": {
    "iso:country":"DE",
    "sg:address":"Postfach 1480:: 63204 Langen:: Germany.^^Bahnstr 11-15::",
    "sg:city":"Langen",
    "sg:phone":"+49 6103/950",
    "sg:postcode":"63225",
    "sg:province":"Hessen",
    "wof:name":"Volksbank Dreieich Eg",
    "wof:placetype":"venue"
},
  "geometry": {"coordinates":[8.67928,49.989441],"type":"Point"}
}