{
  "type": "Feature",
  "properties": {
    "iso:country":"DE",
    "sg:address":"Robert-Bosch-Str. 12",
    "sg:city":"Radevormwald",
    "sg:phone":"+49 2195/8058",
    "sg:postcode":"42477",
    "sg:province":"Nordrhein-Westfalen",
    "wof:name":"Peter Hardt",
    "wof:placetype":"venue"
},
  "geometry": {"coordinates":[7.3831920624,51.2002601624],"type":"Point"}
}