{
  "type": "Feature",
  "properties": {
    "iso:country":"DE",
    "sg:address":"Hasselsstr. 111",
    "sg:city":"D\u00fcsseldorf",
    "sg:phone":"+49 211/744081",
    "sg:postcode":"40599",
    "sg:province":"Nordrhein-Westfalen",
    "wof:name":"Bestattungsinstitut Rainer Pruss",
    "wof:placetype":"venue"
},
  "geometry": {"coordinates":[6.873491,51.17799],"type":"Point"}
}