{
  "type": "Feature",
  "properties": {
    "iso:country":"DE",
    "sg:address":"Musbacher Str. 1",
    "sg:city":"Baiersbronn",
    "sg:phone":"+49 7442/6438",
    "sg:postcode":"72270",
    "sg:province":"Baden-W\u00fcrttemberg",
    "wof:name":"Rothfuss Mechanik - Homepage",
    "wof:placetype":"venue"
},
  "geometry": {"coordinates":[8.4017496109,48.5275878906],"type":"Point"}
}