{
  "type": "Feature",
  "properties": {
    "iso:country":"DE",
    "sg:address":"Am Hohentorshafen 21",
    "sg:city":"Bremen",
    "sg:postcode":"28197",
    "sg:province":"Bremen",
    "wof:name":"Verein Bremer Baustoffh\u00e4ndler E. V.",
    "wof:placetype":"venue"
},
  "geometry": {"coordinates":[8.7811584473,53.08045578],"type":"Point"}
}