{
  "type": "Feature",
  "properties": {
    "iso:country":"DE",
    "sg:address":"Oberprex",
    "sg:city":"Regnitzlosau",
    "sg:phone":"+49 9294/1378",
    "sg:postcode":"95194",
    "sg:province":"Bayern",
    "wof:name":"Willi K\u00fcnzel",
    "wof:placetype":"venue"
},
  "geometry": {"coordinates":[12.111169,50.299397],"type":"Point"}
}