{
  "type": "Feature",
  "properties": {
    "iso:country":"DE",
    "sg:address":"Am K\u00f6hlerteich 13",
    "sg:city":"Wernigerode",
    "sg:phone":"+49 3943/900020",
    "sg:postcode":"38855",
    "sg:province":"Sachsen-Anhalt",
    "wof:name":"Lindig F\u00f6rdertechnik Gmbh",
    "wof:placetype":"venue"
},
  "geometry": {"coordinates":[10.7710371017,51.8412780762],"type":"Point"}
}