{
  "type": "Feature",
  "properties": {
    "iso:country":"DE",
    "sg:address":"Memeler Str. 46",
    "sg:city":"Nordhorn",
    "sg:phone":"+49 5921/5744",
    "sg:postcode":"48529",
    "sg:province":"Niedersachsen",
    "wof:name":"D. Jansen Steuerberater",
    "wof:placetype":"venue"
},
  "geometry": {"coordinates":[7.061147213,52.415927887],"type":"Point"}
}