{
  "type": "Feature",
  "properties": {
    "iso:country":"DE",
    "sg:address":"Stettiner Str. 3",
    "sg:city":"Unterl\u00fc\u00df",
    "sg:phone":"+49 5827/391",
    "sg:postcode":"29345",
    "sg:province":"Niedersachsen",
    "wof:name":"Glocken-apotheke",
    "wof:placetype":"venue"
},
  "geometry": {"coordinates":[10.295445,52.843307],"type":"Point"}
}