{
  "type": "Feature",
  "properties": {
    "iso:country":"DE",
    "sg:address":"Hauptstra\u00dfe 25",
    "sg:city":"Vierden",
    "sg:phone":"+49 4282/1204",
    "sg:postcode":"27419",
    "sg:province":"Niedersachsen",
    "wof:name":"Behnisch Haust\u00fcren",
    "wof:placetype":"venue"
},
  "geometry": {"coordinates":[9.5019216537,53.3276405334],"type":"Point"}
}