{
  "type": "Feature",
  "properties": {
    "iso:country":"DE",
    "sg:address":"Trendelstr. 16",
    "sg:city":"Feldafing",
    "sg:phone":"+49 8157/5120",
    "sg:postcode":"82340",
    "sg:province":"Bayern",
    "wof:name":"Dr. Peter Gnam Rechtsanwalt",
    "wof:placetype":"venue"
},
  "geometry": {"coordinates":[11.2949314117,47.9418296814],"type":"Point"}
}