{
  "type": "Feature",
  "properties": {
    "iso:country":"DE",
    "sg:address":"Sonnenstr. 4",
    "sg:city":"Neresheim",
    "sg:phone":"+49 7326/6456",
    "sg:postcode":"73450",
    "sg:province":"Baden-W\u00fcrttemberg",
    "wof:name":"Alfons Polten",
    "wof:placetype":"venue"
},
  "geometry": {"coordinates":[10.31206,48.797665],"type":"Point"}
}