{
  "type": "Feature",
  "properties": {
    "iso:country":"DE",
    "sg:address":"Schnegg 108a",
    "sg:city":"Wackersberg",
    "sg:phone":"+49 8041/71516",
    "sg:postcode":"83646",
    "sg:province":"Bayern",
    "wof:name":"Walter M. Wilbert",
    "wof:placetype":"venue"
},
  "geometry": {"coordinates":[11.500751,47.759434],"type":"Point"}
}