{
  "type": "Feature",
  "properties": {
    "iso:country":"DE",
    "sg:address":"Rathausplatz 3",
    "sg:city":"Germering",
    "sg:postcode":"82110",
    "sg:province":"Bayern",
    "wof:name":"Katholisches Pfarramt St. Martin",
    "wof:placetype":"venue"
},
  "geometry": {"coordinates":[11.3629579544,48.1345901489],"type":"Point"}
}