{
  "type": "Feature",
  "properties": {
    "iso:country":"DE",
    "sg:address":"Josefstr.",
    "sg:city":"Bendorf",
    "sg:phone":"+49 2622/15111",
    "sg:postcode":"56170",
    "sg:province":"Rheinland-Pfalz",
    "wof:name":"A. Grohmann",
    "wof:placetype":"venue"
},
  "geometry": {"coordinates":[7.5971250534,50.4578895569],"type":"Point"}
}