{
  "type": "Feature",
  "properties": {
    "iso:country":"DE",
    "sg:address":"Wallerstr. 5",
    "sg:city":"Inning",
    "sg:phone":"+49 8143/7622",
    "sg:postcode":"82266",
    "sg:province":"Bayern",
    "wof:name":"Micheline Hutzler Steuerberaterin",
    "wof:placetype":"venue"
},
  "geometry": {"coordinates":[11.1599693298,48.0587463379],"type":"Point"}
}