{
  "type": "Feature",
  "properties": {
    "iso:country":"DE",
    "sg:address":"Hauptstr. 55",
    "sg:city":"Mahlberg",
    "sg:phone":"+49 7822/9932",
    "sg:postcode":"77972",
    "sg:province":"Baden-W\u00fcrttemberg",
    "wof:name":"K. Paepke",
    "wof:placetype":"venue"
},
  "geometry": {"coordinates":[7.796119,48.276199],"type":"Point"}
}