{
  "type": "Feature",
  "properties": {
    "iso:country":"DE",
    "sg:address":"Schwarzenborn 2",
    "sg:city":"Tann",
    "sg:phone":"+49 6682/8553",
    "sg:postcode":"36142",
    "sg:province":"Hessen",
    "wof:name":"Reiner Kalb",
    "wof:placetype":"venue"
},
  "geometry": {"coordinates":[9.9648456573,50.6199150085],"type":"Point"}
}