{
  "type": "Feature",
  "properties": {
    "iso:country":"DE",
    "sg:address":"Kirchhalde 10",
    "sg:city":"Heimenkirch",
    "sg:phone":"+49 8381/3152",
    "sg:postcode":"88178",
    "sg:province":"Bayern",
    "wof:name":"Renate M\u00fcller Heilpraktiker",
    "wof:placetype":"venue"
},
  "geometry": {"coordinates":[9.9054098129,47.6298980713],"type":"Point"}
}