{
  "type": "Feature",
  "properties": {
    "iso:country":"DE",
    "sg:address":"Mauermer Weg 10",
    "sg:city":"Meckesheim",
    "sg:phone":"+49 6226/991785",
    "sg:postcode":"74909",
    "sg:province":"Baden-W\u00fcrttemberg",
    "wof:name":"Fimmo Bautr\u00e4ger Gmbh",
    "wof:placetype":"venue"
},
  "geometry": {"coordinates":[8.810215,49.330002],"type":"Point"}
}