{
  "type": "Feature",
  "properties": {
    "iso:country":"DE",
    "sg:address":"Scharbke",
    "sg:city":"Extertal",
    "sg:phone":"+49 5262/3293",
    "sg:postcode":"32699",
    "sg:province":"Nordrhein-Westfalen",
    "wof:name":"Ernst Biesemeier",
    "wof:placetype":"venue"
},
  "geometry": {"coordinates":[9.123199,52.055214],"type":"Point"}
}