{
  "type": "Feature",
  "properties": {
    "iso:country":"DE",
    "sg:address":"Otto-Brenner-Str. 8",
    "sg:city":"L\u00fcneburg",
    "sg:phone":"+49 4131/95240",
    "sg:postcode":"21337",
    "sg:province":"Niedersachsen",
    "wof:name":"Lcd L\u00fcneburger Container- Und Muldendienst Gmbh & Co. Kg",
    "wof:placetype":"venue"
},
  "geometry": {"coordinates":[10.477560997,53.2448234558],"type":"Point"}
}