{
  "type": "Feature",
  "properties": {
    "iso:country":"DE",
    "sg:address":"Spessartstr. 20",
    "sg:city":"Frankfurt",
    "sg:phone":"+49 69/439842",
    "sg:postcode":"60385",
    "sg:province":"Hessen",
    "wof:name":"Seref Cikla",
    "wof:placetype":"venue"
},
  "geometry": {"coordinates":[8.7092323303,50.1253204346],"type":"Point"}
}