{
  "type": "Feature",
  "properties": {
    "iso:country":"DE",
    "sg:address":"Lilienstr.4",
    "sg:city":"Bad Sch\u00f6nborn",
    "sg:phone":"+49 7253",
    "sg:postcode":"76669",
    "sg:province":"Baden-W\u00fcrttemberg",
    "wof:name":"Oliver Freund-computertechnik",
    "wof:placetype":"venue"
},
  "geometry": {"coordinates":[8.6354045868,49.2021369934],"type":"Point"}
}