{
  "type": "Feature",
  "properties": {
    "iso:country":"DE",
    "sg:address":"Edenkobener Str. 33",
    "sg:city":"St Martin",
    "sg:phone":"+49 6323/5159",
    "sg:postcode":"67487",
    "sg:province":"Rheinland-Pfalz",
    "wof:name":"Josef R\u00f6\u00dfler",
    "wof:placetype":"venue"
},
  "geometry": {"coordinates":[8.1062650681,49.2980728149],"type":"Point"}
}