{
  "type": "Feature",
  "properties": {
    "iso:country":"DE",
    "sg:address":"Alte Schmiede 3",
    "sg:city":"Hannover",
    "sg:phone":"+49 511/584953",
    "sg:postcode":"30629",
    "sg:province":"Niedersachsen",
    "wof:name":"Werner Maschke",
    "wof:placetype":"venue"
},
  "geometry": {"coordinates":[9.8538246155,52.3903427124],"type":"Point"}
}