{
  "type": "Feature",
  "properties": {
    "iso:country":"DE",
    "sg:address":"Am M\u00fchlenberg 7",
    "sg:city":"Baruth",
    "sg:postcode":"15837",
    "sg:province":"Brandenburg",
    "wof:name":"G\u00fcnther Lehmann",
    "wof:placetype":"venue"
},
  "geometry": {"coordinates":[13.502355,52.043308],"type":"Point"}
}