{
  "type": "Feature",
  "properties": {
    "iso:country":"DE",
    "sg:address":"Fr\u00fchlingstr. 10",
    "sg:city":"Kempten",
    "sg:phone":"+49 831/28078",
    "sg:postcode":"87439",
    "sg:province":"Bayern",
    "wof:name":"Bartelt Tschuske Und Willers",
    "wof:placetype":"venue"
},
  "geometry": {"coordinates":[10.309254,47.724728],"type":"Point"}
}