{
  "type": "Feature",
  "properties": {
    "iso:country":"DE",
    "sg:address":"Neutor 8",
    "sg:city":"Borken",
    "sg:phone":"+49 2861/64469",
    "sg:postcode":"46325",
    "sg:province":"Nordrhein-Westfalen",
    "wof:name":"Altschl\u00f6\u00dfchen",
    "wof:placetype":"venue"
},
  "geometry": {"coordinates":[6.8575639725,51.8437271118],"type":"Point"}
}