{
  "type": "Feature",
  "properties": {
    "iso:country":"DE",
    "sg:address":"Violenstr. 30",
    "sg:city":"Melle",
    "sg:phone":"+49 5428/1398",
    "sg:postcode":"49326",
    "sg:province":"Niedersachsen",
    "wof:name":"K. Polaschke",
    "wof:placetype":"venue"
},
  "geometry": {"coordinates":[8.3552875519,52.1516036987],"type":"Point"}
}