{
  "type": "Feature",
  "properties": {
    "iso:country":"DE",
    "sg:address":"Rosenheimer Str. 46",
    "sg:city":"Miesbach",
    "sg:phone":"+49 8025/7146",
    "sg:postcode":"83714",
    "sg:province":"Bayern",
    "wof:name":"Josef Heid",
    "wof:placetype":"venue"
},
  "geometry": {"coordinates":[11.84146595,47.7883415222],"type":"Point"}
}