{
  "type": "Feature",
  "properties": {
    "iso:country":"DE",
    "sg:address":"Mannichswalder Str. 9",
    "sg:city":"Crimmitschau",
    "sg:phone":"+49 36608/2441",
    "sg:postcode":"08451",
    "sg:province":"Sachsen",
    "wof:name":"M. Wagner",
    "wof:placetype":"venue"
},
  "geometry": {"coordinates":[12.3856363297,50.8172073364],"type":"Point"}
}