{
  "type": "Feature",
  "properties": {
    "iso:country":"DE",
    "sg:address":"Neuer Heidkamp 21 b",
    "sg:city":"M\u00fcnster",
    "sg:phone":"+49 251/213712",
    "sg:postcode":"48159",
    "sg:province":"Nordrhein-Westfalen",
    "wof:name":"Robert Welling Steuerberater",
    "wof:placetype":"venue"
},
  "geometry": {"coordinates":[7.6015582085,51.9931297302],"type":"Point"}
}