{
  "type": "Feature",
  "properties": {
    "iso:country":"DE",
    "sg:address":"Am Schl\u00f6\u00dfle 1",
    "sg:city":"Kempten",
    "sg:phone":"+49 831/540300",
    "sg:postcode":"87435",
    "sg:province":"Bayern",
    "wof:name":"Juwelier Mueller",
    "wof:placetype":"venue"
},
  "geometry": {"coordinates":[10.3148975372,47.7260971069],"type":"Point"}
}