{
  "type": "Feature",
  "properties": {
    "iso:country":"DE",
    "sg:address":"Spitalstr. 19",
    "sg:city":"L\u00f6rrach",
    "sg:phone":"+49 7621/163700",
    "sg:postcode":"79539",
    "sg:province":"Baden-W\u00fcrttemberg",
    "wof:name":"Leschinski & Bender Ohg",
    "wof:placetype":"venue"
},
  "geometry": {"coordinates":[7.6594109535,47.6140899658],"type":"Point"}
}