{
  "type": "Feature",
  "properties": {
    "iso:country":"DE",
    "sg:address":"Hermann-Balk-Str. 99",
    "sg:city":"Hamburg",
    "sg:phone":"+49 40/64428289",
    "sg:postcode":"22147",
    "sg:province":"Hamburg",
    "wof:name":"Amber World Jens Von Holt E. K.",
    "wof:placetype":"venue"
},
  "geometry": {"coordinates":[10.1408100128,53.6228866577],"type":"Point"}
}