{
  "type": "Feature",
  "properties": {
    "iso:country":"DE",
    "sg:address":"Otto-Wehrle-Str. 4",
    "sg:city":"Emmendingen",
    "sg:phone":"+49 7641/1303",
    "sg:postcode":"79312",
    "sg:province":"Baden-W\u00fcrttemberg",
    "wof:name":"Ev. Pfarramt Luthergemeinde",
    "wof:placetype":"venue"
},
  "geometry": {"coordinates":[7.8546380997,48.1222267151],"type":"Point"}
}