{
  "type": "Feature",
  "properties": {
    "iso:country":"DE",
    "sg:address":"Hauptstr. 7",
    "sg:city":"Werkhausen",
    "sg:phone":"+49 2686/8189",
    "sg:postcode":"57635",
    "sg:province":"Rheinland-Pfalz",
    "wof:name":"Walter Schmidt",
    "wof:placetype":"venue"
},
  "geometry": {"coordinates":[7.534194,50.721718],"type":"Point"}
}