{
  "type": "Feature",
  "properties": {
    "iso:country":"DE",
    "sg:address":"Oberehrenbach 45",
    "sg:city":"Leutenbach",
    "sg:postcode":"91359",
    "sg:province":"Bayern",
    "wof:name":"F\u00f6rtschlanger Bauunternehmen",
    "wof:placetype":"venue"
},
  "geometry": {"coordinates":[11.189833,49.679455],"type":"Point"}
}