{
  "type": "Feature",
  "properties": {
    "iso:country":"DE",
    "sg:address":"Kastanienstr. 2",
    "sg:city":"Bielefeld",
    "sg:phone":"+49 521/48320",
    "sg:postcode":"33649",
    "sg:province":"Nordrhein-Westfalen",
    "wof:name":"S. Hellweg Und A. Rammert Gbr",
    "wof:placetype":"venue"
},
  "geometry": {"coordinates":[8.4592933655,51.9731063843],"type":"Point"}
}