{
  "type": "Feature",
  "properties": {
    "iso:country":"DE",
    "sg:address":"Wilhelm-K\u00fclz-Str. 7",
    "sg:city":"Rathenow",
    "sg:phone":"+49 3385/512034",
    "sg:postcode":"14712",
    "sg:province":"Brandenburg",
    "wof:name":"P. Vo\u00df",
    "wof:placetype":"venue"
},
  "geometry": {"coordinates":[12.338888,52.603737],"type":"Point"}
}