{
  "type": "Feature",
  "properties": {
    "iso:country":"DE",
    "sg:address":"Bubenheim 151",
    "sg:city":"Treuchtlingen",
    "sg:postcode":"91757",
    "sg:province":"Bayern",
    "wof:name":"Sob Gmbh",
    "wof:placetype":"venue"
},
  "geometry": {"coordinates":[10.895450592,48.9878349304],"type":"Point"}
}