{
  "type": "Feature",
  "properties": {
    "iso:country":"DE",
    "sg:address":"Adolf-Damaschke-Str. 4B",
    "sg:city":"Pfungstadt",
    "sg:phone":"+49 6157/6185",
    "sg:postcode":"64319",
    "sg:province":"Hessen",
    "wof:name":"Renate Schurig",
    "wof:placetype":"venue"
},
  "geometry": {"coordinates":[8.609433,49.800507],"type":"Point"}
}