{
  "type": "Feature",
  "properties": {
    "iso:country":"DE",
    "sg:address":"Frankenberger Str. 8 A",
    "sg:city":"Frankenberg",
    "sg:phone":"+49 6451/22197",
    "sg:postcode":"35066",
    "sg:province":"Hessen",
    "wof:name":"Heinrich Bornscheuer",
    "wof:placetype":"venue"
},
  "geometry": {"coordinates":[8.7557401657,51.0478363037],"type":"Point"}
}