{
  "type": "Feature",
  "properties": {
    "iso:country":"DE",
    "sg:address":"Schilfweg 53",
    "sg:city":"Delmenhorst",
    "sg:phone":"+49 4221",
    "sg:postcode":"27751",
    "sg:province":"Niedersachsen",
    "wof:name":"Muslim-markt",
    "wof:placetype":"venue"
},
  "geometry": {"coordinates":[8.665105,53.056835],"type":"Point"}
}