{
  "type": "Feature",
  "properties": {
    "iso:country":"DE",
    "sg:address":"Oststr. 26",
    "sg:city":"Kahla",
    "sg:postcode":"07768",
    "sg:province":"Th\u00fcringen",
    "wof:name":"Vereinigte Holzindustrie Lobenstein Gmbh",
    "wof:placetype":"venue"
},
  "geometry": {"coordinates":[11.5893096924,50.8054504395],"type":"Point"}
}