{
  "type": "Feature",
  "properties": {
    "iso:country":"DE",
    "sg:address":"Delsener Heide 36",
    "sg:city":"Telgte",
    "sg:phone":"+49 4925/0470000",
    "sg:postcode":"48291",
    "sg:province":"Nordrhein-Westfalen",
    "wof:name":"Kraege",
    "wof:placetype":"venue"
},
  "geometry": {"coordinates":[7.79867,51.97858],"type":"Point"}
}