{
  "type": "Feature",
  "properties": {
    "iso:country":"DE",
    "sg:address":"Im Flecken 21",
    "sg:city":"Salzhemmendorf",
    "sg:postcode":"31020",
    "sg:province":"Niedersachsen",
    "wof:name":"B\u00e4ckerei Bohne Gmbh",
    "wof:placetype":"venue"
},
  "geometry": {"coordinates":[9.556699,52.077065],"type":"Point"}
}