{
  "type": "Feature",
  "properties": {
    "iso:country":"DE",
    "sg:address":"Marktplatz 23",
    "sg:city":"Neubeuern",
    "sg:phone":"+49 8035/2456",
    "sg:postcode":"83115",
    "sg:province":"Bayern",
    "wof:name":"Hotel-restaurant Burgdacherl",
    "wof:placetype":"venue"
},
  "geometry": {"coordinates":[12.1384572983,47.7737960815],"type":"Point"}
}