{
  "type": "Feature",
  "properties": {
    "iso:country":"DE",
    "sg:address":"Richard-Wagner-Str. 16",
    "sg:city":"Kaiserslautern",
    "sg:phone":"+49 631/16692",
    "sg:postcode":"67655",
    "sg:province":"Rheinland-Pfalz",
    "wof:name":"Restaurant Mekong Vietnam",
    "wof:placetype":"venue"
},
  "geometry": {"coordinates":[7.7656497955,49.4429473877],"type":"Point"}
}