{
  "type": "Feature",
  "properties": {
    "iso:country":"DE",
    "sg:address":"Hofmarkstr. 22",
    "sg:city":"Planegg",
    "sg:phone":"+49 89/8597871",
    "sg:postcode":"82152",
    "sg:province":"Bayern",
    "wof:name":"Ernst Baumann Architekt",
    "wof:placetype":"venue"
},
  "geometry": {"coordinates":[11.417545,48.107933],"type":"Point"}
}