{
  "type": "Feature",
  "properties": {
    "iso:country":"DE",
    "sg:address":"Colonnaden 43",
    "sg:city":"Hamburg",
    "sg:phone":"+49 40/35719380",
    "sg:postcode":"20354",
    "sg:province":"Hamburg",
    "wof:name":"Kultur Kontor Regine Dierse K\u00fcnstler Konzerte Konzepte Ohg",
    "wof:placetype":"venue"
},
  "geometry": {"coordinates":[9.989816,53.557388],"type":"Point"}
}