{
  "type": "Feature",
  "properties": {
    "iso:country":"DE",
    "sg:address":"Dr.-Alfred-Brehm-Str. 5a",
    "sg:city":"Dahlen",
    "sg:phone":"+49 34361/52960",
    "sg:postcode":"04774",
    "sg:province":"Sachsen",
    "wof:name":"Pension Dietze",
    "wof:placetype":"venue"
},
  "geometry": {"coordinates":[12.9865627289,51.3989906311],"type":"Point"}
}