{
  "type": "Feature",
  "properties": {
    "iso:country":"DE",
    "sg:address":"Wilhelmsaue 3",
    "sg:city":"Berlin",
    "sg:phone":"+49 30/8614833",
    "sg:postcode":"10715",
    "sg:province":"Berlin",
    "wof:name":"Siegbert Setsevits Rechtsanwalt",
    "wof:placetype":"venue"
},
  "geometry": {"coordinates":[13.3298864365,52.4852523804],"type":"Point"}
}