{
  "type": "Feature",
  "properties": {
    "iso:country":"DE",
    "sg:address":"Schlo\u00dfstr. 18",
    "sg:city":"Ludwigslust",
    "sg:phone":"+49 3874/49353",
    "sg:postcode":"19288",
    "sg:province":"Mecklenburg-Vorpommern",
    "wof:name":"Eiscafe Diana",
    "wof:placetype":"venue"
},
  "geometry": {"coordinates":[11.49222,53.324528],"type":"Point"}
}