{
  "type": "Feature",
  "properties": {
    "iso:country":"DE",
    "sg:address":"Harthweg 2",
    "sg:city":"Chemnitz",
    "sg:phone":"+49 371/850097",
    "sg:postcode":"09116",
    "sg:province":"Sachsen",
    "wof:name":"Spaten",
    "wof:placetype":"venue"
},
  "geometry": {"coordinates":[12.8847951889,50.831073761],"type":"Point"}
}