{
  "type": "Feature",
  "properties": {
    "iso:country":"DE",
    "sg:address":"Kattrepel 2",
    "sg:city":"Hamburg",
    "sg:postcode":"20095",
    "sg:province":"Hamburg",
    "wof:name":"Assekuranz-kontor Montan Gmbh",
    "wof:placetype":"venue"
},
  "geometry": {"coordinates":[9.999669075,53.5491485596],"type":"Point"}
}