{
  "type": "Feature",
  "properties": {
    "iso:country":"DE",
    "sg:address":"Bahnhofstr. 12a",
    "sg:city":"Rieneck",
    "sg:phone":"+49 9354/1428",
    "sg:postcode":"97794",
    "sg:province":"Bayern",
    "wof:name":"Christiane Bock",
    "wof:placetype":"venue"
},
  "geometry": {"coordinates":[9.661351,50.089771],"type":"Point"}
}