{
  "type": "Feature",
  "properties": {
    "iso:country":"DE",
    "sg:address":"Tieckstr. 17",
    "sg:city":"Berlin",
    "sg:phone":"+49 30/2814072",
    "sg:postcode":"10115",
    "sg:province":"Berlin",
    "wof:name":"Wolfgang Ullmann",
    "wof:placetype":"venue"
},
  "geometry": {"coordinates":[13.390606,52.529865],"type":"Point"}
}