{
  "type": "Feature",
  "properties": {
    "iso:country":"DE",
    "sg:address":"Buchheider Weg 21",
    "sg:city":"D\u00fcren",
    "sg:postcode":"52355",
    "sg:province":"Nordrhein-Westfalen",
    "wof:name":"Induko Industrie- Anlagenbau Gmbh",
    "wof:placetype":"venue"
},
  "geometry": {"coordinates":[6.464506,50.777309],"type":"Point"}
}