{
  "type": "Feature",
  "properties": {
    "iso:country":"DE",
    "sg:address":"Boschweg 2",
    "sg:city":"Salach",
    "sg:phone":"+49 7162/5045",
    "sg:postcode":"73084",
    "sg:province":"Baden-W\u00fcrttemberg",
    "wof:name":"H. J. Vogel Steuerberater",
    "wof:placetype":"venue"
},
  "geometry": {"coordinates":[9.7381010056,48.6927642822],"type":"Point"}
}