{
  "type": "Feature",
  "properties": {
    "iso:country":"DE",
    "sg:city":"Bredstedt",
    "sg:postcode":"25821",
    "sg:province":"Schleswig-Holstein",
    "wof:name":"Werbetechnik Datenbank",
    "wof:placetype":"venue"
},
  "geometry": {"coordinates":[8.96323,54.61869],"type":"Point"}
}