{
  "type": "Feature",
  "properties": {
    "iso:country":"DE",
    "sg:address":"Hauptstr. 63",
    "sg:city":"Neubiberg",
    "sg:postcode":"85579",
    "sg:province":"Bayern",
    "wof:name":"Integrium Gmbh",
    "wof:placetype":"venue"
},
  "geometry": {"coordinates":[11.6730737686,48.0751266479],"type":"Point"}
}