{
  "type": "Feature",
  "properties": {
    "iso:country":"DE",
    "sg:address":"Rheinbergstr. 10",
    "sg:city":"Karlsruhe",
    "sg:postcode":"76187",
    "sg:province":"Baden-W\u00fcrttemberg",
    "wof:name":"D & M Bautr\u00e4ger Gmbh",
    "wof:placetype":"venue"
},
  "geometry": {"coordinates":[8.334567,49.035164],"type":"Point"}
}