{
  "type": "Feature",
  "properties": {
    "iso:country":"DE",
    "sg:address":"Hirtengarten 5",
    "sg:city":"Gesees",
    "sg:phone":"+49 9201/458",
    "sg:postcode":"95494",
    "sg:province":"Bayern",
    "wof:name":"Reinhol F\u00f6rster",
    "wof:placetype":"venue"
},
  "geometry": {"coordinates":[11.544159,49.907398],"type":"Point"}
}