{
  "type": "Feature",
  "properties": {
    "iso:country":"DE",
    "sg:address":"Haupeltshofer Str.",
    "sg:city":"Aletshausen",
    "sg:phone":"+49 8263/269",
    "sg:postcode":"86480",
    "sg:province":"Bayern",
    "wof:name":"Richard Dopfer",
    "wof:placetype":"venue"
},
  "geometry": {"coordinates":[10.3869352341,48.1955680847],"type":"Point"}
}