{
  "type": "Feature",
  "properties": {
    "iso:country":"DE",
    "sg:address":"\u00d6lkamp 1",
    "sg:city":"Werl",
    "sg:postcode":"59457",
    "sg:province":"Nordrhein-Westfalen",
    "wof:name":"Wimmeler Planen Und Bauen Gmbh",
    "wof:placetype":"venue"
},
  "geometry": {"coordinates":[7.871953,51.565117],"type":"Point"}
}