{
  "type": "Feature",
  "properties": {
    "iso:country":"DE",
    "sg:address":"Steinkirchrg. 34",
    "sg:city":"Villingen-Schwenningen",
    "sg:phone":"+49 4977/2063051",
    "sg:postcode":"78056",
    "sg:province":"Baden-W\u00fcrttemberg",
    "wof:name":"Spitzdruck Gmbh",
    "wof:placetype":"venue"
},
  "geometry": {"coordinates":[8.5587787628,48.0668487549],"type":"Point"}
}