{
  "type": "Feature",
  "properties": {
    "iso:country":"DE",
    "sg:address":"Lange Str. 11",
    "sg:city":"Emden",
    "sg:phone":"+49 4921/6477",
    "sg:postcode":"26723",
    "sg:province":"Niedersachsen",
    "wof:name":"Fleischerei Harry Giesenberg",
    "wof:placetype":"venue"
},
  "geometry": {"coordinates":[7.1080508232,53.3461723328],"type":"Point"}
}