{
  "type": "Feature",
  "properties": {
    "iso:country":"DE",
    "sg:address":"Hermannstr. 16",
    "sg:city":"H\u00f6hr-Grenzhausen",
    "sg:phone":"+49 2624/95950",
    "sg:postcode":"56203",
    "sg:province":"Rheinland-Pfalz",
    "wof:name":"Seibert Und R\u00fcdesheim Rechtsanw\u00e4lte",
    "wof:placetype":"venue"
},
  "geometry": {"coordinates":[7.6575222015,50.4365730286],"type":"Point"}
}