{
  "type": "Feature",
  "properties": {
    "iso:country":"DE",
    "sg:address":"Kurze Str. 2/1",
    "sg:city":"Heilbronn",
    "sg:phone":"+49 7131/85795",
    "sg:postcode":"74072",
    "sg:province":"Baden-W\u00fcrttemberg",
    "wof:name":"Hans-j\u00fcrgen Riesmeier",
    "wof:placetype":"venue"
},
  "geometry": {"coordinates":[9.2157802582,49.1379585266],"type":"Point"}
}