{
  "type": "Feature",
  "properties": {
    "iso:country":"DE",
    "sg:address":"Igelh\u00f6hstr. 4",
    "sg:city":"Heppenheim",
    "sg:phone":"+49 6252/4738",
    "sg:postcode":"64646",
    "sg:province":"Hessen",
    "wof:name":"Norbert Engelhardt",
    "wof:placetype":"venue"
},
  "geometry": {"coordinates":[8.6902065277,49.6457633972],"type":"Point"}
}