{
  "type": "Feature",
  "properties": {
    "iso:country":"DE",
    "sg:address":"Birkenweg 10",
    "sg:city":"Gebhardshain",
    "sg:phone":"+49 2747/2104",
    "sg:postcode":"57580",
    "sg:province":"Rheinland-Pfalz",
    "wof:name":"Ursula Schelhaas Heilpraktikerin",
    "wof:placetype":"venue"
},
  "geometry": {"coordinates":[7.824529171,50.7503051758],"type":"Point"}
}