{
  "type": "Feature",
  "properties": {
    "iso:country":"DE",
    "sg:address":"Wolfslochstr. 48 B",
    "sg:city":"Zweibr\u00fccken",
    "sg:phone":"+49 6332/17121",
    "sg:postcode":"66482",
    "sg:province":"Rheinland-Pfalz",
    "wof:name":"Gerhard Cleemann",
    "wof:placetype":"venue"
},
  "geometry": {"coordinates":[7.345831,49.247772],"type":"Point"}
}