{
  "type": "Feature",
  "properties": {
    "iso:country":"DE",
    "sg:address":"Mitteltorstr. 21",
    "sg:city":"Karlsruhe",
    "sg:phone":"+49 721/709943",
    "sg:postcode":"76149",
    "sg:province":"Baden-W\u00fcrttemberg",
    "wof:name":"Eberhard Schmidt",
    "wof:placetype":"venue"
},
  "geometry": {"coordinates":[8.380064,49.050762],"type":"Point"}
}