{
  "type": "Feature",
  "properties": {
    "iso:country":"DE",
    "sg:address":"Paul-Kemp-Str. 36",
    "sg:city":"Bonn",
    "sg:postcode":"53173",
    "sg:province":"Nordrhein-Westfalen",
    "wof:name":"Art Forum Export Import Gmbh",
    "wof:placetype":"venue"
},
  "geometry": {"coordinates":[7.1542668343,50.6879043579],"type":"Point"}
}