{
  "type": "Feature",
  "properties": {
    "iso:country":"DE",
    "sg:address":"Breitenbergstr. 8b",
    "sg:city":"Augsburg",
    "sg:phone":"+49 821/661594",
    "sg:postcode":"86163",
    "sg:province":"Bayern",
    "wof:name":"Kennametal Gmbh",
    "wof:placetype":"venue"
},
  "geometry": {"coordinates":[10.943047,48.351265],"type":"Point"}
}