{
  "type": "Feature",
  "properties": {
    "iso:country":"DE",
    "sg:address":"Ei\u00dfendorfer Str. 167",
    "sg:city":"Hamburg",
    "sg:postcode":"21073",
    "sg:province":"Hamburg",
    "wof:name":"Baudienst In Der Lausitz Kahnert Gmbh",
    "wof:placetype":"venue"
},
  "geometry": {"coordinates":[9.9593906403,53.4565315247],"type":"Point"}
}