{
  "type": "Feature",
  "properties": {
    "iso:country":"DE",
    "sg:address":"Alte Rhinstra\u00dfe 8",
    "sg:city":"Berlin",
    "sg:phone":"+49 30",
    "sg:postcode":"12681",
    "sg:province":"Berlin",
    "wof:name":"Howoge Wohnungsbaugesellschaft Mbh",
    "wof:placetype":"venue"
},
  "geometry": {"coordinates":[13.5195388794,52.5341567993],"type":"Point"}
}