{
  "type": "Feature",
  "properties": {
    "iso:country":"DE",
    "sg:address":"Marktstr. 14",
    "sg:city":"Beratzhausen",
    "sg:phone":"+49 9493/871",
    "sg:postcode":"93176",
    "sg:province":"Bayern",
    "wof:name":"J. Hegelein",
    "wof:placetype":"venue"
},
  "geometry": {"coordinates":[11.8087272644,49.0953102112],"type":"Point"}
}