{
  "type": "Feature",
  "properties": {
    "iso:country":"DE",
    "sg:address":"Buchhorster Str. 35",
    "sg:city":"Erkner",
    "sg:phone":"+49 3362/75845",
    "sg:postcode":"15537",
    "sg:province":"Brandenburg",
    "wof:name":"Birgit Winter",
    "wof:placetype":"venue"
},
  "geometry": {"coordinates":[13.738779068,52.4154777527],"type":"Point"}
}