{
  "type": "Feature",
  "properties": {
    "iso:country":"DE",
    "sg:address":"Hafenstr. 66",
    "sg:city":"Bremerhaven",
    "sg:postcode":"27576",
    "sg:province":"Bremen",
    "wof:name":"Data-point Produktions- Und Handelsges. F\u00fcr Datentechnik",
    "wof:placetype":"venue"
},
  "geometry": {"coordinates":[8.583315,53.554417],"type":"Point"}
}