{
  "type": "Feature",
  "properties": {
    "iso:country":"DE",
    "sg:address":"Im Wiesengrund 6",
    "sg:city":"Argenthal",
    "sg:phone":"+49 6761/7362",
    "sg:postcode":"55496",
    "sg:province":"Rheinland-Pfalz",
    "wof:name":"H.-j. Boldt",
    "wof:placetype":"venue"
},
  "geometry": {"coordinates":[7.600979805,49.9713745117],"type":"Point"}
}