{
  "type": "Feature",
  "properties": {
    "iso:country":"DE",
    "sg:address":"Dielinger Str. 79",
    "sg:city":"Stemwede",
    "sg:phone":"+49 5745/2567",
    "sg:postcode":"32351",
    "sg:province":"Nordrhein-Westfalen",
    "wof:name":"Roetherm-feuerfest- Engineering Und Montagen Gmbh",
    "wof:placetype":"venue"
},
  "geometry": {"coordinates":[8.3518266678,52.4494667053],"type":"Point"}
}