{
  "type": "Feature",
  "properties": {
    "iso:country":"DE",
    "sg:address":"Meller Str. 20",
    "sg:city":"Osnabr\u00fcck",
    "sg:postcode":"49082",
    "sg:province":"Niedersachsen",
    "wof:name":"S. M. Bau Gmbh",
    "wof:placetype":"venue"
},
  "geometry": {"coordinates":[8.056978,52.265213],"type":"Point"}
}