{
  "type": "Feature",
  "properties": {
    "iso:country":"DE",
    "sg:address":"Heisinger Str. 435",
    "sg:city":"Essen",
    "sg:phone":"+49 201/467289",
    "sg:postcode":"45259",
    "sg:province":"Nordrhein-Westfalen",
    "wof:name":"Margrets Sch\u00f6nheitsst\u00fcbchen",
    "wof:placetype":"venue"
},
  "geometry": {"coordinates":[7.062048,51.406944],"type":"Point"}
}