{
  "type": "Feature",
  "properties": {
    "iso:country":"DE",
    "sg:address":"Nordermarren 7",
    "sg:city":"Midlum",
    "sg:phone":"+49 4741/1608",
    "sg:postcode":"27632",
    "sg:province":"Niedersachsen",
    "wof:name":"Otto Bohlen",
    "wof:placetype":"venue"
},
  "geometry": {"coordinates":[8.598222,53.731659],"type":"Point"}
}