{
  "type": "Feature",
  "properties": {
    "iso:country":"DE",
    "sg:address":"Machnower Str. 4",
    "sg:city":"Berlin",
    "sg:phone":"+49 30/8156969",
    "sg:postcode":"14165",
    "sg:province":"Berlin",
    "wof:name":"Heidemarie Haller",
    "wof:placetype":"venue"
},
  "geometry": {"coordinates":[13.2562265396,52.4291038513],"type":"Point"}
}