{
  "type": "Feature",
  "properties": {
    "iso:country":"DE",
    "sg:address":"Wasserstr. 12",
    "sg:city":"Viersen",
    "sg:phone":"+49 4921/6295030",
    "sg:postcode":"41751",
    "sg:province":"Nordrhein-Westfalen",
    "wof:name":"G\u00dcsken Wilhelm Eisengiesserei Gmbh & Co Kg",
    "wof:placetype":"venue"
},
  "geometry": {"coordinates":[6.332206,51.253433],"type":"Point"}
}