{
  "type": "Feature",
  "properties": {
    "iso:country":"DE",
    "sg:address":"Horsthofstr. 41",
    "sg:city":"Bottrop",
    "sg:phone":"+49 2045/2555",
    "sg:postcode":"46244",
    "sg:province":"Nordrhein-Westfalen",
    "wof:name":"Klara Brand Nachf.",
    "wof:placetype":"venue"
},
  "geometry": {"coordinates":[6.933362,51.60392],"type":"Point"}
}