{
  "type": "Feature",
  "properties": {
    "iso:country":"DE",
    "sg:address":"Alte Wallensteinstr. 153",
    "sg:city":"N\u00fcrnberg",
    "sg:phone":"+49 911/614065",
    "sg:postcode":"90431",
    "sg:province":"Bayern",
    "wof:name":"J. Kleinlein",
    "wof:placetype":"venue"
},
  "geometry": {"coordinates":[11.0220861435,49.4344596863],"type":"Point"}
}