{
  "type": "Feature",
  "properties": {
    "iso:country":"DE",
    "sg:address":"Gro\u00dfe Nelkenstr. 39",
    "sg:city":"Frankfurt",
    "sg:postcode":"60488",
    "sg:province":"Hessen",
    "wof:name":"Aldi Gmbh & Co. Kg",
    "wof:placetype":"venue"
},
  "geometry": {"coordinates":[8.6296882629,50.1336975098],"type":"Point"}
}