{
  "type": "Feature",
  "properties": {
    "iso:country":"DE",
    "sg:address":"Adlerstr. 27",
    "sg:city":"Stuttgart",
    "sg:phone":"+49 711/604614",
    "sg:postcode":"70199",
    "sg:province":"Baden-W\u00fcrttemberg",
    "wof:name":"Taverne Dionysos Inh. S. Stavridis",
    "wof:placetype":"venue"
},
  "geometry": {"coordinates":[9.1628751755,48.7636947632],"type":"Point"}
}