{
  "type": "Feature",
  "properties": {
    "iso:country":"DE",
    "sg:address":"Fallersleber Str. 21/22",
    "sg:city":"Braunschweig",
    "sg:postcode":"38100",
    "sg:province":"Niedersachsen",
    "wof:name":"F & C Edv-service Gmbh",
    "wof:placetype":"venue"
},
  "geometry": {"coordinates":[10.5286579132,52.2690391541],"type":"Point"}
}