{
  "type": "Feature",
  "properties": {
    "iso:country":"DE",
    "sg:address":"Bergstr. 15",
    "sg:city":"Clausthal-Zellerfeld",
    "sg:phone":"+49 5323/84265",
    "sg:postcode":"38678",
    "sg:province":"Niedersachsen",
    "wof:name":"Rohstoff Technologie Gmbh Grt Cronj\u00e4ger Kg",
    "wof:placetype":"venue"
},
  "geometry": {"coordinates":[10.332419,51.814838],"type":"Point"}
}