{
  "type": "Feature",
  "properties": {
    "iso:country":"DE",
    "sg:address":"Am Haferst\u00fcck 14",
    "sg:city":"Taunusstein",
    "sg:phone":"+49 6128/72475",
    "sg:postcode":"65232",
    "sg:province":"Hessen",
    "wof:name":"T. Lehmann",
    "wof:placetype":"venue"
},
  "geometry": {"coordinates":[8.2135152817,50.1515007019],"type":"Point"}
}