{
  "type": "Feature",
  "properties": {
    "iso:country":"DE",
    "sg:address":"Lindenstr. 4",
    "sg:city":"Bornheim",
    "sg:phone":"+49 2227/924073",
    "sg:postcode":"53332",
    "sg:province":"Nordrhein-Westfalen",
    "wof:name":"Kurt Blank",
    "wof:placetype":"venue"
},
  "geometry": {"coordinates":[6.93951,50.770302],"type":"Point"}
}