{
  "type": "Feature",
  "properties": {
    "iso:country":"DE",
    "sg:address":"Alt Prielip 6",
    "sg:city":"Rosche",
    "sg:phone":"+49 5803/423",
    "sg:postcode":"29571",
    "sg:province":"Niedersachsen",
    "wof:name":"Helmuth Dietrich",
    "wof:placetype":"venue"
},
  "geometry": {"coordinates":[10.759741,52.985786],"type":"Point"}
}