{
  "type": "Feature",
  "properties": {
    "iso:country":"DE",
    "sg:address":"Bautzner Str. 34",
    "sg:city":"Dresden",
    "sg:phone":"+49 351/809000",
    "sg:postcode":"01099",
    "sg:province":"Sachsen",
    "wof:name":"H. Eichler Immobilienmakler",
    "wof:placetype":"venue"
},
  "geometry": {"coordinates":[13.7554826736,51.0627288818],"type":"Point"}
}