{
  "type": "Feature",
  "properties": {
    "iso:country":"DE",
    "sg:address":"Flensburger Str. 5",
    "sg:city":"Kappeln",
    "sg:postcode":"24376",
    "sg:province":"Schleswig-Holstein",
    "wof:name":"Verm\u00f6gensbeteiligungen Kappeln Gmbh",
    "wof:placetype":"venue"
},
  "geometry": {"coordinates":[9.924686,54.663109],"type":"Point"}
}