{
  "type": "Feature",
  "properties": {
    "iso:country":"DE",
    "sg:address":"Marienplatz 9",
    "sg:city":"Bad Aibling",
    "sg:phone":"+49 8061/1770",
    "sg:postcode":"83043",
    "sg:province":"Bayern",
    "wof:name":"Marien-apotheke Inh. Matthias Gries",
    "wof:placetype":"venue"
},
  "geometry": {"coordinates":[12.01005,47.863651],"type":"Point"}
}