{
  "type": "Feature",
  "properties": {
    "iso:country":"DE",
    "sg:address":"Kaiserstr. 11",
    "sg:city":"Wuppertal",
    "sg:phone":"+49 202/781436",
    "sg:postcode":"42329",
    "sg:province":"Nordrhein-Westfalen",
    "wof:name":"A. W. K\u00fcrten",
    "wof:placetype":"venue"
},
  "geometry": {"coordinates":[7.071182,51.231602],"type":"Point"}
}