{
  "type": "Feature",
  "properties": {
    "iso:country":"DE",
    "sg:address":"Querfurter Str. 4",
    "sg:city":"Bad Lauchst\u00e4dt",
    "sg:phone":"+49 34635/20207",
    "sg:postcode":"06246",
    "sg:province":"Sachsen-Anhalt",
    "wof:name":"Cafe-konditorei R\u00f6hr",
    "wof:placetype":"venue"
},
  "geometry": {"coordinates":[11.8667945862,51.3874549866],"type":"Point"}
}