{
  "type": "Feature",
  "properties": {
    "iso:country":"DE",
    "sg:address":"Schillerstr. 2",
    "sg:city":"Haibach",
    "sg:phone":"+49 6021/68534",
    "sg:postcode":"63808",
    "sg:province":"Bayern",
    "wof:name":"Alfred Lenk Gmbh",
    "wof:placetype":"venue"
},
  "geometry": {"coordinates":[9.2110519409,49.962184906],"type":"Point"}
}