{
  "type": "Feature",
  "properties": {
    "iso:country":"DE",
    "sg:address":"Fabrikenstr. 16",
    "sg:city":"Magdeburg",
    "sg:phone":"+49 391/2527529",
    "sg:postcode":"39124",
    "sg:province":"Sachsen-Anhalt",
    "wof:name":"Manfred Riecke",
    "wof:placetype":"venue"
},
  "geometry": {"coordinates":[11.6360940933,52.1584510803],"type":"Point"}
}