{
  "type": "Feature",
  "properties": {
    "iso:country":"DE",
    "sg:address":"Br\u00fchlstr. 27",
    "sg:city":"Sindelfingen",
    "sg:phone":"+49 7031/382708",
    "sg:postcode":"71069",
    "sg:province":"Baden-W\u00fcrttemberg",
    "wof:name":"Forma Baugesellschaft F\u00fcr Schl\u00fcsselfertiges",
    "wof:placetype":"venue"
},
  "geometry": {"coordinates":[8.9683465958,48.7239227295],"type":"Point"}
}