{
  "type": "Feature",
  "properties": {
    "iso:country":"DE",
    "sg:address":"Sparkassenplatz 11-13",
    "sg:city":"Pfaffenhofen",
    "sg:postcode":"85276",
    "sg:province":"Bayern",
    "wof:name":"Pfaffenhofener Tiefgaragen- Bau- Gmbh",
    "wof:placetype":"venue"
},
  "geometry": {"coordinates":[11.509961,48.529041],"type":"Point"}
}