{
  "type": "Feature",
  "properties": {
    "iso:country":"DE",
    "sg:address":"Markt 12",
    "sg:city":"Schwaan",
    "sg:phone":"+49 3844/811380",
    "sg:postcode":"18258",
    "sg:province":"Mecklenburg-Vorpommern",
    "wof:name":"Elektro Hohensee",
    "wof:placetype":"venue"
},
  "geometry": {"coordinates":[12.10721,53.93943],"type":"Point"}
}