{
  "type": "Feature",
  "properties": {
    "iso:country":"DE",
    "sg:address":"Ihle-Anger 25",
    "sg:city":"Burg",
    "sg:phone":"+49 3921/989516",
    "sg:postcode":"39288",
    "sg:province":"Sachsen-Anhalt",
    "wof:name":"Ims Industrie Montage Service Guido Stelzer",
    "wof:placetype":"venue"
},
  "geometry": {"coordinates":[11.8713388443,52.2727050781],"type":"Point"}
}