{
  "type": "Feature",
  "properties": {
    "iso:country":"DE",
    "sg:address":"Heilgeiststr. 19",
    "sg:city":"Demmin",
    "sg:phone":"+49 3998/222741",
    "sg:postcode":"17109",
    "sg:province":"Mecklenburg-Vorpommern",
    "wof:name":"C. Behrendt",
    "wof:placetype":"venue"
},
  "geometry": {"coordinates":[13.0297822952,53.9078140259],"type":"Point"}
}