{
  "type": "Feature",
  "properties": {
    "iso:country":"DE",
    "sg:address":"Telingskamp 13",
    "sg:city":"Bocholt",
    "sg:postcode":"46395",
    "sg:province":"Nordrhein-Westfalen",
    "wof:name":"Nebo Entsorgungsservice Gmbh",
    "wof:placetype":"venue"
},
  "geometry": {"coordinates":[6.564946,51.808964],"type":"Point"}
}