{
  "type": "Feature",
  "properties": {
    "iso:country":"DE",
    "sg:address":"Gr\u00fcnewaldstr. 18a",
    "sg:city":"Wietmarschen",
    "sg:phone":"+49 5925/1442",
    "sg:postcode":"49835",
    "sg:province":"Niedersachsen",
    "wof:name":"Hans Arling",
    "wof:placetype":"venue"
},
  "geometry": {"coordinates":[7.1298408508,52.5095825195],"type":"Point"}
}