{
  "type": "Feature",
  "properties": {
    "iso:country":"DE",
    "sg:address":"Amtsstr. 5-11",
    "sg:city":"Ludwigshafen",
    "sg:phone":"+49 621/590201",
    "sg:postcode":"67059",
    "sg:province":"Rheinland-Pfalz",
    "wof:name":"Rheinpfalz Verlag Und Druckerei Gmbh & Co. Kg",
    "wof:placetype":"venue"
},
  "geometry": {"coordinates":[8.4463968277,49.4817848206],"type":"Point"}
}