{
  "type": "Feature",
  "properties": {
    "iso:country":"DE",
    "sg:address":"Seeshaupter Str. 66",
    "sg:city":"Penzberg",
    "sg:postcode":"82377",
    "sg:province":"Bayern",
    "wof:name":"Horst Gr\u00fcnert Musikinstrumente E. K.",
    "wof:placetype":"venue"
},
  "geometry": {"coordinates":[11.3619804382,47.7643013],"type":"Point"}
}