{
  "type": "Feature",
  "properties": {
    "iso:country":"DE",
    "sg:address":"Gerberstr. 9",
    "sg:city":"Gunzenhausen",
    "sg:phone":"+49 9831/2453",
    "sg:postcode":"91710",
    "sg:province":"Bayern",
    "wof:name":"Wenk & Prossel Gmbh",
    "wof:placetype":"venue"
},
  "geometry": {"coordinates":[10.7543048859,49.1163215637],"type":"Point"}
}