{
  "type": "Feature",
  "properties": {
    "iso:country":"DE",
    "sg:address":"Zum Laubwald 24",
    "sg:city":"Gro\u00dfefehn",
    "sg:phone":"+49 4943/2260",
    "sg:postcode":"26629",
    "sg:province":"Niedersachsen",
    "wof:name":"Dr. Hans Schmidt Tierarzt",
    "wof:placetype":"venue"
},
  "geometry": {"coordinates":[7.6107611656,53.4321784973],"type":"Point"}
}