{
  "type": "Feature",
  "properties": {
    "iso:country":"DE",
    "sg:address":"Burgweg 17",
    "sg:city":"Lahnstein",
    "sg:phone":"+49 2621/3232",
    "sg:postcode":"56112",
    "sg:province":"Rheinland-Pfalz",
    "wof:name":"Pension-sonneninselder Ruhige Urlab",
    "wof:placetype":"venue"
},
  "geometry": {"coordinates":[7.615974,50.304565],"type":"Point"}
}