{
  "type": "Feature",
  "properties": {
    "iso:country":"DE",
    "sg:address":"Fackenburger Allee 20",
    "sg:city":"L\u00fcbeck",
    "sg:phone":"+49 451/42183",
    "sg:postcode":"23554",
    "sg:province":"Schleswig-Holstein",
    "wof:name":"Aral Ag",
    "wof:placetype":"venue"
},
  "geometry": {"coordinates":[10.6699266434,53.8703651428],"type":"Point"}
}