{
  "type": "Feature",
  "properties": {
    "iso:country":"DE",
    "sg:address":"Holstener Weg 25",
    "sg:city":"Salzbergen",
    "sg:phone":"+49 5976/7211",
    "sg:postcode":"48499",
    "sg:province":"Niedersachsen",
    "wof:name":"Engelbert Venker",
    "wof:placetype":"venue"
},
  "geometry": {"coordinates":[7.3872361183,52.3245048523],"type":"Point"}
}