{
  "type": "Feature",
  "properties": {
    "iso:country":"DE",
    "sg:address":"K\u00f6hlesrain 4",
    "sg:city":"Biberach",
    "sg:phone":"+49 7351/14901",
    "sg:postcode":"88400",
    "sg:province":"Baden-W\u00fcrttemberg",
    "wof:name":"Hans Will",
    "wof:placetype":"venue"
},
  "geometry": {"coordinates":[9.7874526978,48.0844039917],"type":"Point"}
}