{
  "type": "Feature",
  "properties": {
    "iso:country":"DE",
    "sg:address":"Rungholtplatz 1",
    "sg:city":"Kiel",
    "sg:phone":"+49 431/313333",
    "sg:postcode":"24107",
    "sg:province":"Schleswig-Holstein",
    "wof:name":"Co Op Schleswig-holstein Eg",
    "wof:placetype":"venue"
},
  "geometry": {"coordinates":[10.0782032013,54.360660553],"type":"Point"}
}