{
  "type": "Feature",
  "properties": {
    "iso:country":"DE",
    "sg:address":"Kressenstr. 18",
    "sg:city":"N\u00fcrnberg",
    "sg:phone":"+49 911/379902",
    "sg:postcode":"90419",
    "sg:province":"Bayern",
    "wof:name":"Marc Slotta E. K.",
    "wof:placetype":"venue"
},
  "geometry": {"coordinates":[11.0688676834,49.4644241333],"type":"Point"}
}