{
  "type": "Feature",
  "properties": {
    "iso:country":"DE",
    "sg:address":"Neumayerstr. 25",
    "sg:city":"Kirchheimbolanden",
    "sg:phone":"+49 6352/3456",
    "sg:postcode":"67292",
    "sg:province":"Rheinland-Pfalz",
    "wof:name":"E. Brutscher Bildhauer",
    "wof:placetype":"venue"
},
  "geometry": {"coordinates":[8.0100955963,49.6686210632],"type":"Point"}
}