{
  "type": "Feature",
  "properties": {
    "iso:country":"DE",
    "sg:address":"Heinrich-von-Altheim-Str. 40",
    "sg:city":"Dillingen",
    "sg:phone":"+49 9071/6453",
    "sg:postcode":"89407",
    "sg:province":"Bayern",
    "wof:name":"Hermann Sailer",
    "wof:placetype":"venue"
},
  "geometry": {"coordinates":[10.4754400253,48.5958709717],"type":"Point"}
}