{
  "type": "Feature",
  "properties": {
    "iso:country":"DE",
    "sg:address":"Schottengasse 5",
    "sg:city":"N\u00fcrnberg",
    "sg:phone":"+49 911/20070",
    "sg:postcode":"90402",
    "sg:province":"Bayern",
    "wof:name":"Hotel Am Jakobsmarkt",
    "wof:placetype":"venue"
},
  "geometry": {"coordinates":[11.070397377,49.4482307434],"type":"Point"}
}