{
  "type": "Feature",
  "properties": {
    "iso:country":"DE",
    "sg:address":"Kaltenkirchener Str. 20",
    "sg:city":"Oersdorf",
    "sg:postcode":"24568",
    "sg:province":"Schleswig-Holstein",
    "wof:name":"Boomerang Hotel Und Restaurant Betriebsgesellschaft Mbh",
    "wof:placetype":"venue"
},
  "geometry": {"coordinates":[9.986852,53.839584],"type":"Point"}
}