{
  "type": "Feature",
  "properties": {
    "iso:country":"DE",
    "sg:address":"H\u00f6rsteloe 33",
    "sg:city":"Ahaus",
    "sg:phone":"+49 2567/3428",
    "sg:postcode":"48683",
    "sg:province":"Nordrhein-Westfalen",
    "wof:name":"Alfons Berning Steuerberater",
    "wof:placetype":"venue"
},
  "geometry": {"coordinates":[6.9009041786,52.0965194702],"type":"Point"}
}