{
  "type": "Feature",
  "properties": {
    "iso:country":"DE",
    "sg:address":"Ferdinand-Wallbrecht-Str. 13",
    "sg:city":"Hannover",
    "sg:phone":"+49 511/625046",
    "sg:postcode":"30163",
    "sg:province":"Niedersachsen",
    "wof:name":"Jost Doppelfeld Architekt",
    "wof:placetype":"venue"
},
  "geometry": {"coordinates":[9.748754,52.390232],"type":"Point"}
}