{
  "type": "Feature",
  "properties": {
    "iso:country":"DE",
    "sg:address":"Leopoldstra\u00dfe 1",
    "sg:city":"Gaggenau",
    "sg:phone":"+49 7225",
    "sg:postcode":"76571",
    "sg:province":"Baden-W\u00fcrttemberg",
    "wof:name":"Merex Autovertrieb Gmbh; Unimog, 4x4, Gel\u00e4ndefahrzeuge,",
    "wof:placetype":"venue"
},
  "geometry": {"coordinates":[8.3214836121,48.805721283],"type":"Point"}
}