{
  "type": "Feature",
  "properties": {
    "iso:country":"DE",
    "sg:address":"Hafenstr. 38",
    "sg:city":"Lauenburg",
    "sg:phone":"+49 4153/51058",
    "sg:postcode":"21481",
    "sg:province":"Schleswig-Holstein",
    "wof:name":"Tib Technischer Industriebedarf Gmbh",
    "wof:placetype":"venue"
},
  "geometry": {"coordinates":[10.5768566132,53.3731689453],"type":"Point"}
}