{
  "type": "Feature",
  "properties": {
    "iso:country":"DE",
    "sg:address":"Jennerstr. 10",
    "sg:city":"Freilassing",
    "sg:phone":"+49 8654/9398",
    "sg:postcode":"83395",
    "sg:province":"Bayern",
    "wof:name":"Horst Tolks",
    "wof:placetype":"venue"
},
  "geometry": {"coordinates":[12.9740524292,47.8348464966],"type":"Point"}
}