{
  "type": "Feature",
  "properties": {
    "iso:country":"DE",
    "sg:address":"Wriezener Str. 82",
    "sg:city":"Bad Freienwalde",
    "sg:phone":"+49 3344/31686",
    "sg:postcode":"16259",
    "sg:province":"Brandenburg",
    "wof:name":"D. Wieland",
    "wof:placetype":"venue"
},
  "geometry": {"coordinates":[14.0405673981,52.7812385559],"type":"Point"}
}