{
  "type": "Feature",
  "properties": {
    "iso:country":"DE",
    "sg:address":"Gisibodenstr. 17",
    "sg:city":"Todtnau",
    "sg:phone":"+49 7671/292",
    "sg:postcode":"79674",
    "sg:province":"Baden-W\u00fcrttemberg",
    "wof:name":"Helmut Seger Gmbh",
    "wof:placetype":"venue"
},
  "geometry": {"coordinates":[7.94431,47.804165],"type":"Point"}
}