{
  "type": "Feature",
  "properties": {
    "iso:country":"DE",
    "sg:address":"Hohlstr. 13",
    "sg:city":"Ruthweiler",
    "sg:phone":"+49 6381/3846",
    "sg:postcode":"66869",
    "sg:province":"Rheinland-Pfalz",
    "wof:name":"Ulrich Henk",
    "wof:placetype":"venue"
},
  "geometry": {"coordinates":[7.363342762,49.553314209],"type":"Point"}
}