{
  "type": "Feature",
  "properties": {
    "iso:country":"DE",
    "sg:address":"Landhausstr. 44",
    "sg:city":"Stuttgart",
    "sg:phone":"+49 711/2623265",
    "sg:postcode":"70190",
    "sg:province":"Baden-W\u00fcrttemberg",
    "wof:name":"Paula Werner",
    "wof:placetype":"venue"
},
  "geometry": {"coordinates":[9.1942825317,48.7856216431],"type":"Point"}
}