{
  "type": "Feature",
  "properties": {
    "iso:country":"DE",
    "sg:address":"Saarbr\u00fccker Str. 106",
    "sg:city":"Friedrichsthal",
    "sg:phone":"+49 6897/841742",
    "sg:postcode":"66299",
    "sg:province":"Saarland",
    "wof:name":"Vvs-versicherungs-vermittlungs Service Gmbh",
    "wof:placetype":"venue"
},
  "geometry": {"coordinates":[7.0986199379,49.3243598938],"type":"Point"}
}