{
  "type": "Feature",
  "properties": {
    "iso:country":"DE",
    "sg:address":"Hinterbrack 11a",
    "sg:city":"Jork",
    "sg:phone":"+49 40/74527907",
    "sg:postcode":"21635",
    "sg:province":"Niedersachsen",
    "wof:name":"C.-j. Voss Architekt",
    "wof:placetype":"venue"
},
  "geometry": {"coordinates":[9.743965,53.54599],"type":"Point"}
}