{
  "type": "Feature",
  "properties": {
    "iso:country":"DE",
    "sg:address":"Dieselstr. 14",
    "sg:city":"Reichertshofen",
    "sg:postcode":"85084",
    "sg:province":"Bayern",
    "wof:name":"Manfred Weingartner Gmbh",
    "wof:placetype":"venue"
},
  "geometry": {"coordinates":[11.4818925858,48.6572418213],"type":"Point"}
}