{
  "type": "Feature",
  "properties": {
    "iso:country":"DE",
    "sg:address":"Industriestr 13-15",
    "sg:city":"Karlsbad",
    "sg:phone":"+49 7248/91490",
    "sg:postcode":"76307",
    "sg:province":"Baden-W\u00fcrttemberg",
    "wof:name":"Konstandin Gmbh",
    "wof:placetype":"venue"
},
  "geometry": {"coordinates":[8.5052061081,48.883556366],"type":"Point"}
}