{
  "type": "Feature",
  "properties": {
    "iso:country":"DE",
    "sg:address":"Rasenweg 2",
    "sg:city":"Leinefelde",
    "sg:postcode":"37327",
    "sg:province":"Th\u00fcringen",
    "wof:name":"Tanzband Ad Libitum",
    "wof:placetype":"venue"
},
  "geometry": {"coordinates":[10.316235,51.38739],"type":"Point"}
}