{
  "type": "Feature",
  "properties": {
    "iso:country":"DE",
    "sg:address":"Braunm\u00fchlstr. 9",
    "sg:city":"Weiden",
    "sg:phone":"+49 961/32471",
    "sg:postcode":"92637",
    "sg:province":"Bayern",
    "wof:name":"J. Ram",
    "wof:placetype":"venue"
},
  "geometry": {"coordinates":[12.1602420807,49.677532196],"type":"Point"}
}