{
  "type": "Feature",
  "properties": {
    "iso:country":"DE",
    "sg:address":"Schillingerbergstr. 19",
    "sg:city":"Freiamt",
    "sg:phone":"+49 7645/333",
    "sg:postcode":"79348",
    "sg:province":"Baden-W\u00fcrttemberg",
    "wof:name":"Hermann Haas",
    "wof:placetype":"venue"
},
  "geometry": {"coordinates":[7.959678,48.170048],"type":"Point"}
}