{
  "type": "Feature",
  "properties": {
    "iso:country":"DE",
    "sg:address":"Heinrich-Deibel-Str. 10",
    "sg:city":"Lollar",
    "sg:phone":"+49 6406/904124",
    "sg:postcode":"35457",
    "sg:province":"Hessen",
    "wof:name":"S-consult Ges. F\u00fcr Bau- Und Projektorganisation Mbh",
    "wof:placetype":"venue"
},
  "geometry": {"coordinates":[8.7102489471,50.6533660889],"type":"Point"}
}