{
  "type": "Feature",
  "properties": {
    "iso:country":"DE",
    "sg:address":"Dorfstr. 36 b",
    "sg:city":"Brunsbek",
    "sg:phone":"+49 4107/850994",
    "sg:postcode":"22946",
    "sg:province":"Schleswig-Holstein",
    "wof:name":"J\u00fcrgen Tiedemann Steuerberater",
    "wof:placetype":"venue"
},
  "geometry": {"coordinates":[10.2918119431,53.6044654846],"type":"Point"}
}