{
  "type": "Feature",
  "properties": {
    "iso:country":"DE",
    "sg:address":"Endertstr. 150",
    "sg:city":"Cochem",
    "sg:postcode":"56812",
    "sg:province":"Rheinland-Pfalz",
    "wof:name":"Vbc Verkehrsbetrieb Cochem Gmbh",
    "wof:placetype":"venue"
},
  "geometry": {"coordinates":[7.151882,50.155468],"type":"Point"}
}