{
  "type": "Feature",
  "properties": {
    "iso:country":"DE",
    "sg:address":"Denninger Str. 148",
    "sg:city":"M\u00fcnchen",
    "sg:phone":"+49 89/917551",
    "sg:postcode":"81927",
    "sg:province":"Bayern",
    "wof:name":"Ics Clinical Service Gmbh",
    "wof:placetype":"venue"
},
  "geometry": {"coordinates":[11.630101,48.146973],"type":"Point"}
}