{
  "type": "Feature",
  "properties": {
    "iso:country":"DE",
    "sg:address":"Mathildenstr. 21",
    "sg:city":"Offenbach",
    "sg:phone":"+49 69/82376401",
    "sg:postcode":"63065",
    "sg:province":"Hessen",
    "wof:name":"Hd-design Gmbh",
    "wof:placetype":"venue"
},
  "geometry": {"coordinates":[8.774975,50.104156],"type":"Point"}
}