{
  "type": "Feature",
  "properties": {
    "iso:country":"DE",
    "sg:address":"H\u00f6lderlinweg 6",
    "sg:city":"Hann. M\u00fcnden",
    "sg:phone":"+49 5541/73913",
    "sg:postcode":"34346",
    "sg:province":"Niedersachsen",
    "wof:name":"Deutsche Partner Suche",
    "wof:placetype":"venue"
},
  "geometry": {"coordinates":[9.671448,51.41935],"type":"Point"}
}