{
  "type": "Feature",
  "properties": {
    "iso:country":"DE",
    "sg:address":"Gretchenstr. 7",
    "sg:city":"Hannover",
    "sg:phone":"+49 511/3360424",
    "sg:postcode":"30161",
    "sg:province":"Niedersachsen",
    "wof:name":"Looms Textiles Wohnen Hallemann",
    "wof:placetype":"venue"
},
  "geometry": {"coordinates":[9.7458839417,52.3840904236],"type":"Point"}
}