{
  "type": "Feature",
  "properties": {
    "iso:country":"DE",
    "sg:address":"Robert-Kircher-Str. 27",
    "sg:city":"Fulda",
    "sg:postcode":"36037",
    "sg:province":"Hessen",
    "wof:name":"Elektronik-vertrieb",
    "wof:placetype":"venue"
},
  "geometry": {"coordinates":[9.6721897125,50.5495681763],"type":"Point"}
}