{
  "type": "Feature",
  "properties": {
    "iso:country":"DE",
    "sg:address":"Ulmenstr. 11",
    "sg:city":"D\u00fcsseldorf",
    "sg:phone":"+49 211/487126",
    "sg:postcode":"40476",
    "sg:province":"Nordrhein-Westfalen",
    "wof:name":"Blitzschutzanlagen Jules Goossens Gmbh",
    "wof:placetype":"venue"
},
  "geometry": {"coordinates":[6.7864,51.244884],"type":"Point"}
}