{
  "type": "Feature",
  "properties": {
    "iso:country":"DE",
    "sg:address":"Rheinstr. 28",
    "sg:city":"Worms",
    "sg:phone":"+49 6241/921210",
    "sg:postcode":"67547",
    "sg:province":"Rheinland-Pfalz",
    "wof:name":"Sun Shine Touristik Gmbh",
    "wof:placetype":"venue"
},
  "geometry": {"coordinates":[8.3679151535,49.6317138672],"type":"Point"}
}