{
  "type": "Feature",
  "properties": {
    "iso:country":"DE",
    "sg:address":"Graf-Anton-Weg 20",
    "sg:city":"Hamburg",
    "sg:phone":"+49 40/4392006",
    "sg:postcode":"22459",
    "sg:province":"Hamburg",
    "wof:name":"Nell & Riess Gmbh",
    "wof:placetype":"venue"
},
  "geometry": {"coordinates":[9.9477033615,53.6269989014],"type":"Point"}
}