{
  "type": "Feature",
  "properties": {
    "iso:country":"DE",
    "sg:address":"Schlo\u00dfwiese 6",
    "sg:city":"Deidesheim",
    "sg:phone":"+49 6326/980400",
    "sg:postcode":"67146",
    "sg:province":"Rheinland-Pfalz",
    "wof:name":"Weinlabor K. Briegel",
    "wof:placetype":"venue"
},
  "geometry": {"coordinates":[8.1920366287,49.4067497253],"type":"Point"}
}