{
  "type": "Feature",
  "properties": {
    "iso:country":"DE",
    "sg:address":"Im Mittelfeld 10",
    "sg:city":"R\u00f6srath",
    "sg:phone":"+49 2205/5324",
    "sg:postcode":"51503",
    "sg:province":"Nordrhein-Westfalen",
    "wof:name":"Alois M\u00fcller Steuerberater",
    "wof:placetype":"venue"
},
  "geometry": {"coordinates":[7.1928911209,50.8841094971],"type":"Point"}
}