{
  "type": "Feature",
  "properties": {
    "iso:country":"DE",
    "sg:address":"Hirschstr. 11",
    "sg:city":"Immenstadt",
    "sg:phone":"+49 8323/6218",
    "sg:postcode":"87509",
    "sg:province":"Bayern",
    "wof:name":"Hotel Hirsch",
    "wof:placetype":"venue"
},
  "geometry": {"coordinates":[10.2181663513,47.5605773926],"type":"Point"}
}