{
  "type": "Feature",
  "properties": {
    "iso:country":"DE",
    "sg:address":"Urspring 7",
    "sg:city":"Hirschau",
    "sg:phone":"+49 9622/6382",
    "sg:postcode":"92242",
    "sg:province":"Bayern",
    "wof:name":"R. Viehmann",
    "wof:placetype":"venue"
},
  "geometry": {"coordinates":[11.8940038681,49.5158843994],"type":"Point"}
}