{
  "type": "Feature",
  "properties": {
    "iso:country":"DE",
    "sg:address":"Heerstr 6",
    "sg:city":"Kenzingen",
    "sg:phone":"+49 7644/8746",
    "sg:postcode":"79341",
    "sg:province":"Baden-W\u00fcrttemberg",
    "wof:name":"Apparate U. Edelstahlmetallbau Striegel",
    "wof:placetype":"venue"
},
  "geometry": {"coordinates":[7.76584,48.16877],"type":"Point"}
}