{
  "type": "Feature",
  "properties": {
    "iso:country":"DE",
    "sg:address":"Finowstr. 32",
    "sg:city":"Berlin",
    "sg:phone":"+49 30/2934880",
    "sg:postcode":"10247",
    "sg:province":"Berlin",
    "wof:name":"Namos Holding-verwaltungs- Immobilien Gmbh",
    "wof:placetype":"venue"
},
  "geometry": {"coordinates":[13.468506,52.512302],"type":"Point"}
}