{
  "type": "Feature",
  "properties": {
    "iso:country":"DE",
    "sg:address":"Am Strand 2",
    "sg:city":"Ueckerm\u00fcnde",
    "sg:phone":"+49 39771/22660",
    "sg:postcode":"17373",
    "sg:province":"Mecklenburg-Vorpommern",
    "wof:name":"Pecunia Freizeit- Und Sport- Boothafengesellschaft Mbh",
    "wof:placetype":"venue"
},
  "geometry": {"coordinates":[14.071251,53.748161],"type":"Point"}
}