{
  "type": "Feature",
  "properties": {
    "iso:country":"DE",
    "sg:address":"Hafenstr. 15",
    "sg:city":"Kassel",
    "sg:phone":"+49 561/53130",
    "sg:postcode":"34125",
    "sg:province":"Hessen",
    "wof:name":"Ev. Pfarramt Unterstadt",
    "wof:placetype":"venue"
},
  "geometry": {"coordinates":[9.5116882324,51.3147888184],"type":"Point"}
}