{
  "type": "Feature",
  "properties": {
    "iso:country":"DE",
    "sg:address":"Laurentiusstra\u00dfe 49",
    "sg:city":"Brilon",
    "sg:phone":"+49 2963/1689",
    "sg:postcode":"59929",
    "sg:province":"Nordrhein-Westfalen",
    "wof:name":"Architekturb\u00fcro Chomse",
    "wof:placetype":"venue"
},
  "geometry": {"coordinates":[8.6856899261,51.4109992981],"type":"Point"}
}