{
  "type": "Feature",
  "properties": {
    "iso:country":"DE",
    "sg:address":"Grolmanstr. 22",
    "sg:city":"Berlin",
    "sg:phone":"+49 30/3129123",
    "sg:postcode":"10623",
    "sg:province":"Berlin",
    "wof:name":"Surya",
    "wof:placetype":"venue"
},
  "geometry": {"coordinates":[13.3213911057,52.5068664551],"type":"Point"}
}