{
  "type": "Feature",
  "properties": {
    "iso:country":"DE",
    "sg:address":"Rotk\u00e4ppchenstr. 42a",
    "sg:city":"Berlin",
    "sg:postcode":"12555",
    "sg:province":"Berlin",
    "wof:name":"Arga Gesellschaft F\u00fcr Die Verwaltung Von Grund- Und",
    "wof:placetype":"venue"
},
  "geometry": {"coordinates":[13.5866212845,52.4661636353],"type":"Point"}
}