{
  "type": "Feature",
  "properties": {
    "iso:country":"DE",
    "sg:address":"F\u00fcrberger Str. 1",
    "sg:city":"Remscheid",
    "sg:postcode":"42857",
    "sg:province":"Nordrhein-Westfalen",
    "wof:name":"J. D. Dominicus & S\u00f6hne",
    "wof:placetype":"venue"
},
  "geometry": {"coordinates":[7.162443161,51.1822853088],"type":"Point"}
}