{
  "type": "Feature",
  "properties": {
    "iso:country":"DE",
    "sg:address":"Schiffahrter Damm 21",
    "sg:city":"M\u00fcnster",
    "sg:phone":"+49 251/233402",
    "sg:postcode":"48145",
    "sg:province":"Nordrhein-Westfalen",
    "wof:name":"Charlotte 4",
    "wof:placetype":"venue"
},
  "geometry": {"coordinates":[7.655684948,51.9682617188],"type":"Point"}
}