{
  "type": "Feature",
  "properties": {
    "iso:country":"DE",
    "sg:address":"Dommitzscher Str. 12",
    "sg:city":"Torgau",
    "sg:phone":"+49 3421/903239",
    "sg:postcode":"04860",
    "sg:province":"Sachsen",
    "wof:name":"H. Hepe",
    "wof:placetype":"venue"
},
  "geometry": {"coordinates":[12.9859075546,51.562297821],"type":"Point"}
}