{
  "type": "Feature",
  "properties": {
    "iso:country":"DE",
    "sg:address":"Lorsbacher Str. 4",
    "sg:city":"Hofheim",
    "sg:phone":"+49 6192/23206",
    "sg:postcode":"65719",
    "sg:province":"Hessen",
    "wof:name":"Hess",
    "wof:placetype":"venue"
},
  "geometry": {"coordinates":[8.4417791367,50.0854225159],"type":"Point"}
}