{
  "type": "Feature",
  "properties": {
    "iso:country":"DE",
    "sg:address":"Goethestr. 12",
    "sg:city":"M\u00fcnchen",
    "sg:phone":"+49 89/539216",
    "sg:postcode":"80336",
    "sg:province":"Bayern",
    "wof:name":"Bayerische Vereinsbank Ag",
    "wof:placetype":"venue"
},
  "geometry": {"coordinates":[11.558401,48.137833],"type":"Point"}
}