{
  "type": "Feature",
  "properties": {
    "iso:country":"DE",
    "sg:address":"Hagenstr. 11",
    "sg:city":"Blomberg",
    "sg:phone":"+49 5235/994800",
    "sg:postcode":"32825",
    "sg:province":"Nordrhein-Westfalen",
    "wof:name":"Wilfried Korte Und Guk E. V.",
    "wof:placetype":"venue"
},
  "geometry": {"coordinates":[9.0955934525,51.9439811707],"type":"Point"}
}