{
  "type": "Feature",
  "properties": {
    "iso:country":"DE",
    "sg:address":"Darmst\u00e4dter Str. 10",
    "sg:city":"Bickenbach",
    "sg:phone":"+49 6257/61359",
    "sg:postcode":"64404",
    "sg:province":"Hessen",
    "wof:name":"Amiri Und Emig",
    "wof:placetype":"venue"
},
  "geometry": {"coordinates":[8.6127357483,49.7543029785],"type":"Point"}
}