{
  "type": "Feature",
  "properties": {
    "iso:country":"DE",
    "sg:address":"Bethlehem Rechts 51",
    "sg:city":"Papenburg",
    "sg:postcode":"26871",
    "sg:province":"Niedersachsen",
    "wof:name":"Sanierungsgesellschaft Aemg Mbh",
    "wof:placetype":"venue"
},
  "geometry": {"coordinates":[7.4374060631,53.0608024597],"type":"Point"}
}