{
  "type": "Feature",
  "properties": {
    "iso:country":"DE",
    "sg:address":"Sportstr. 5",
    "sg:city":"Benshausen",
    "sg:phone":"+49 36843/60557",
    "sg:postcode":"98554",
    "sg:province":"Th\u00fcringen",
    "wof:name":"Rolf Latuske",
    "wof:placetype":"venue"
},
  "geometry": {"coordinates":[10.599315,50.64967],"type":"Point"}
}