{
  "type": "Feature",
  "properties": {
    "iso:country":"DE",
    "sg:address":"Albrechtstr. 28",
    "sg:city":"Osnabr\u00fcck",
    "sg:postcode":"49076",
    "sg:province":"Niedersachsen",
    "wof:name":"Rechenzentrum",
    "wof:placetype":"venue"
},
  "geometry": {"coordinates":[8.02647686,52.2839584351],"type":"Point"}
}