{
  "type": "Feature",
  "properties": {
    "iso:country":"DE",
    "sg:address":"Weenerstr. 31",
    "sg:city":"Bunde",
    "sg:phone":"+49 4953/6773",
    "sg:postcode":"26831",
    "sg:province":"Niedersachsen",
    "wof:name":"Dienesch Automaten Gmbh",
    "wof:placetype":"venue"
},
  "geometry": {"coordinates":[7.277050972,53.1824645996],"type":"Point"}
}