{
  "type": "Feature",
  "properties": {
    "iso:country":"DE",
    "sg:address":"Am Abtswald 15",
    "sg:city":"Geisenheim",
    "sg:phone":"+49 6722/972782",
    "sg:postcode":"65366",
    "sg:province":"Hessen",
    "wof:name":"E. Und L. Gerling Lebensversicherungs Ag",
    "wof:placetype":"venue"
},
  "geometry": {"coordinates":[7.9708762169,50.0112190247],"type":"Point"}
}