{
  "type": "Feature",
  "properties": {
    "iso:country":"DE",
    "sg:address":"Eydtkuhnenweg 5",
    "sg:city":"Hamburg",
    "sg:postcode":"22047",
    "sg:province":"Hamburg",
    "wof:name":"Baugesch\u00e4ft G\u00fcnther Scheel",
    "wof:placetype":"venue"
},
  "geometry": {"coordinates":[10.090388298,53.5936698914],"type":"Point"}
}