{
  "type": "Feature",
  "properties": {
    "iso:country":"DE",
    "sg:address":"Breite Str. 57",
    "sg:city":"Peine",
    "sg:phone":"+49 5171/72061",
    "sg:postcode":"31224",
    "sg:province":"Niedersachsen",
    "wof:name":"Kochl\u00f6ffel Gmbh",
    "wof:placetype":"venue"
},
  "geometry": {"coordinates":[10.2258863449,52.3225898743],"type":"Point"}
}