{
  "type": "Feature",
  "properties": {
    "iso:country":"DE",
    "sg:address":"Neuer M\u00f6nchhof 1",
    "sg:city":"Euskirchen",
    "sg:phone":"+49 2255/4736",
    "sg:postcode":"53881",
    "sg:province":"Nordrhein-Westfalen",
    "wof:name":"Helmitin Gmbh",
    "wof:placetype":"venue"
},
  "geometry": {"coordinates":[6.846525,50.629955],"type":"Point"}
}