{
  "type": "Feature",
  "properties": {
    "iso:country":"DE",
    "sg:address":"Sonnenstr. 8",
    "sg:city":"Regensburg",
    "sg:phone":"+49 941/45608",
    "sg:postcode":"93059",
    "sg:province":"Bayern",
    "wof:name":"Die Blumenoase",
    "wof:placetype":"venue"
},
  "geometry": {"coordinates":[12.104844,49.034279],"type":"Point"}
}