{
  "type": "Feature",
  "properties": {
    "iso:country":"DE",
    "sg:address":"Wurmberger Str. 30 -",
    "sg:city":"Wiernsheim",
    "sg:phone":"+49 7044/240",
    "sg:postcode":"75446",
    "sg:province":"Baden-W\u00fcrttemberg",
    "wof:name":"Halfen Befestigungstechnik Gmbh",
    "wof:placetype":"venue"
},
  "geometry": {"coordinates":[8.847019,48.890575],"type":"Point"}
}