{
  "type": "Feature",
  "properties": {
    "iso:country":"DE",
    "sg:city":"Enspel",
    "sg:phone":"+49 2661/8809",
    "sg:postcode":"57647",
    "sg:province":"Rheinland-Pfalz",
    "wof:name":"Bar Club Papillon",
    "wof:placetype":"venue"
},
  "geometry": {"coordinates":[7.884094,50.616913],"type":"Point"}
}