{
  "type": "Feature",
  "properties": {
    "iso:country":"DE",
    "sg:address":"Talstr. 22-24",
    "sg:city":"D\u00fcsseldorf",
    "sg:postcode":"40217",
    "sg:province":"Nordrhein-Westfalen",
    "wof:name":"Epag Enter- Price Multimedia Ag",
    "wof:placetype":"venue"
},
  "geometry": {"coordinates":[6.778982,51.216274],"type":"Point"}
}