{
  "type": "Feature",
  "properties": {
    "iso:country":"DE",
    "sg:address":"Nienburger Str. 62",
    "sg:city":"Sulingen",
    "sg:phone":"+49 4271/3427",
    "sg:postcode":"27232",
    "sg:province":"Niedersachsen",
    "wof:name":"Friedhelm Aufderheide",
    "wof:placetype":"venue"
},
  "geometry": {"coordinates":[8.821814,52.683182],"type":"Point"}
}