{
  "type": "Feature",
  "properties": {
    "iso:country":"DE",
    "sg:address":"Schulstr. 16",
    "sg:city":"Rehau",
    "sg:phone":"+49 9283/4515",
    "sg:postcode":"95111",
    "sg:province":"Bayern",
    "wof:name":"Wolfgang Neukirchner",
    "wof:placetype":"venue"
},
  "geometry": {"coordinates":[12.03336,50.248188],"type":"Point"}
}