{
  "type": "Feature",
  "properties": {
    "iso:country":"DE",
    "sg:address":"Hagenauer Str. 42",
    "sg:city":"Wiesbaden",
    "sg:phone":"+49 611/928830",
    "sg:postcode":"65203",
    "sg:province":"Hessen",
    "wof:name":"Hewitt Associates Gmbh",
    "wof:placetype":"venue"
},
  "geometry": {"coordinates":[8.2165470123,50.0485229492],"type":"Point"}
}