{
  "type": "Feature",
  "properties": {
    "iso:country":"DE",
    "sg:address":"Oestricher Str. 11",
    "sg:city":"Ingelheim",
    "sg:phone":"+49 6132/983030",
    "sg:postcode":"55218",
    "sg:province":"Rheinland-Pfalz",
    "wof:name":"Edgar Ferreira-schiebold \u00dcbersetzer Bd\u00dc",
    "wof:placetype":"venue"
},
  "geometry": {"coordinates":[8.023122,49.9856],"type":"Point"}
}