{
  "type": "Feature",
  "properties": {
    "iso:country":"DE",
    "sg:address":"Nordendstr. 18",
    "sg:city":"Schrobenhausen",
    "sg:phone":"+49 8252/1361",
    "sg:postcode":"86529",
    "sg:province":"Bayern",
    "wof:name":"Albert Gumbiller",
    "wof:placetype":"venue"
},
  "geometry": {"coordinates":[11.2502536774,48.5747680664],"type":"Point"}
}