{
  "type": "Feature",
  "properties": {
    "iso:country":"DE",
    "sg:address":"M\u00fchlenstr. 30",
    "sg:city":"L\u00fcdinghausen",
    "sg:phone":"+49 2591/21428",
    "sg:postcode":"59348",
    "sg:province":"Nordrhein-Westfalen",
    "wof:name":"A. Niemeyer",
    "wof:placetype":"venue"
},
  "geometry": {"coordinates":[7.445581913,51.7707366943],"type":"Point"}
}