{
  "type": "Feature",
  "properties": {
    "iso:country":"DE",
    "sg:address":"Hattinger Str. 25",
    "sg:city":"Schwelm",
    "sg:phone":"+49 2336/2079",
    "sg:postcode":"58332",
    "sg:province":"Nordrhein-Westfalen",
    "wof:name":"P. Gilsbach",
    "wof:placetype":"venue"
},
  "geometry": {"coordinates":[7.2875919342,51.2933692932],"type":"Point"}
}