{
  "type": "Feature",
  "properties": {
    "iso:country":"DE",
    "sg:address":"Badallee 2",
    "sg:city":"T\u00f6nning",
    "sg:phone":"+49 4861/1818",
    "sg:postcode":"25832",
    "sg:province":"Schleswig-Holstein",
    "wof:name":"Herbert Vater Heilpraktiker",
    "wof:placetype":"venue"
},
  "geometry": {"coordinates":[8.936917305,54.3140335083],"type":"Point"}
}