{
  "type": "Feature",
  "properties": {
    "iso:country":"DE",
    "sg:address":"Hermannstr. 51",
    "sg:city":"Winterbach",
    "sg:phone":"+49 7181/72540",
    "sg:postcode":"73650",
    "sg:province":"Baden-W\u00fcrttemberg",
    "wof:name":"Strassenbau Uetz Gmbh",
    "wof:placetype":"venue"
},
  "geometry": {"coordinates":[9.486463,48.803017],"type":"Point"}
}