{
  "type": "Feature",
  "properties": {
    "iso:country":"DE",
    "sg:address":"B\u00f6hmische Str. 34",
    "sg:city":"Dresden",
    "sg:phone":"+49 351/8045706",
    "sg:postcode":"01099",
    "sg:province":"Sachsen",
    "wof:name":"Cafe Raskolnikoff",
    "wof:placetype":"venue"
},
  "geometry": {"coordinates":[13.754913,51.064323],"type":"Point"}
}