{
  "type": "Feature",
  "properties": {
    "iso:country":"DE",
    "sg:address":"Groiner Allee 10",
    "sg:city":"Rees",
    "sg:postcode":"46459",
    "sg:province":"Nordrhein-Westfalen",
    "wof:name":"Behindertenwerkstatt",
    "wof:placetype":"venue"
},
  "geometry": {"coordinates":[6.419986,51.777008],"type":"Point"}
}