{
  "type": "Feature",
  "properties": {
    "iso:country":"DE",
    "sg:address":"Friedrichsthalstr. 14",
    "sg:city":"Biebergem\u00fcnd",
    "sg:phone":"+49 4960/507755",
    "sg:postcode":"63599",
    "sg:province":"Hessen",
    "wof:name":"Appel Gmbh & Co Kg Metallbau Edelstahlverarbeitung",
    "wof:placetype":"venue"
},
  "geometry": {"coordinates":[9.27269,50.224003],"type":"Point"}
}