{
  "type": "Feature",
  "properties": {
    "iso:country":"DE",
    "sg:address":"Hohenzollernring 84",
    "sg:city":"K\u00f6ln ",
    "sg:classifiers":[
        {
            "category":"Professional",
            "subcategory":"Business Services",
            "type":"Services"
        }
    ],
    "sg:postcode":"50672",
    "sg:tags":[
        "registration-communication-online-onsite-event-trade-show"
    ],
    "sg:website":"http://www.n200.com",
    "wof:name":"N200",
    "wof:placetype":"venue"
},
  "geometry": {"coordinates":[6.9403629,50.9416654],"type":"Point"}
}