{
  "type": "Feature",
  "properties": {
    "iso:country":"DE",
    "sg:address":"Molkereiweg 10",
    "sg:city":"Dahlen",
    "sg:phone":"+49 34361/55111",
    "sg:postcode":"04774",
    "sg:province":"Sachsen",
    "wof:name":"Dahlener Bau Und Elektro Gmbh",
    "wof:placetype":"venue"
},
  "geometry": {"coordinates":[12.9944648743,51.3583374023],"type":"Point"}
}