{
  "type": "Feature",
  "properties": {
    "iso:country":"DE",
    "sg:address":"Scheplerstr. 6",
    "sg:city":"Hamburg",
    "sg:phone":"+49 40/434680",
    "sg:postcode":"22767",
    "sg:province":"Hamburg",
    "wof:name":"Sun-food",
    "wof:placetype":"venue"
},
  "geometry": {"coordinates":[9.9546432495,53.5549888611],"type":"Point"}
}