{
  "type": "Feature",
  "properties": {
    "iso:country":"DE",
    "sg:address":"Landshuter Str. 6",
    "sg:city":"Hohenthann",
    "sg:phone":"+49 8784/1076",
    "sg:postcode":"84098",
    "sg:province":"Bayern",
    "wof:name":"Hans Zenger Bau Gmbh",
    "wof:placetype":"venue"
},
  "geometry": {"coordinates":[12.093476,48.656788],"type":"Point"}
}