{
  "type": "Feature",
  "properties": {
    "iso:country":"DE",
    "sg:address":"Fasanenstr. 25",
    "sg:city":"Neu-Isenburg",
    "sg:phone":"+49 6102/5438",
    "sg:postcode":"63263",
    "sg:province":"Hessen",
    "wof:name":"W. Sch\u00e4fer Und H. J. Sch\u00e4fer Architekten",
    "wof:placetype":"venue"
},
  "geometry": {"coordinates":[8.747619,50.058365],"type":"Point"}
}