{
  "type": "Feature",
  "properties": {
    "iso:country":"DE",
    "sg:address":"Lustheimer Str. 6",
    "sg:city":"Unterschlei\u00dfheim",
    "sg:phone":"+49 89/3106654",
    "sg:postcode":"85716",
    "sg:province":"Bayern",
    "wof:name":"Georg Hecht Gmbh",
    "wof:placetype":"venue"
},
  "geometry": {"coordinates":[11.587335,48.26178],"type":"Point"}
}