{
  "type": "Feature",
  "properties": {
    "iso:country":"DE",
    "sg:address":"Rottweiler Str. 43",
    "sg:city":"V\u00f6hringen",
    "sg:phone":"+49 7454/2877",
    "sg:postcode":"72189",
    "sg:province":"Baden-W\u00fcrttemberg",
    "wof:name":"August Sch\u00e4uble",
    "wof:placetype":"venue"
},
  "geometry": {"coordinates":[8.658138,48.333385],"type":"Point"}
}