{
  "type": "Feature",
  "properties": {
    "iso:country":"DE",
    "sg:address":"Hardenbergstr. 41",
    "sg:city":"Krefeld",
    "sg:phone":"+49 2151/80710",
    "sg:postcode":"47799",
    "sg:province":"Nordrhein-Westfalen",
    "wof:name":"Dr. Helle & Co. Gmbh & Co. Kg",
    "wof:placetype":"venue"
},
  "geometry": {"coordinates":[6.579870224,51.3321342468],"type":"Point"}
}