{
  "type": "Feature",
  "properties": {
    "iso:country":"DE",
    "sg:address":"Lindenstr. 14",
    "sg:city":"Albershausen",
    "sg:phone":"+49 7161/37118",
    "sg:postcode":"73095",
    "sg:province":"Baden-W\u00fcrttemberg",
    "wof:name":"G\u00fcnter Fischer",
    "wof:placetype":"venue"
},
  "geometry": {"coordinates":[9.5642051697,48.6905174255],"type":"Point"}
}