{
  "type": "Feature",
  "properties": {
    "iso:country":"DE",
    "sg:address":"Pyrmonter Str. 15",
    "sg:city":"H\u00f6xter",
    "sg:phone":"+49 5531/4931",
    "sg:postcode":"37671",
    "sg:province":"Nordrhein-Westfalen",
    "wof:name":"Union-weserkieswerk Gmbh",
    "wof:placetype":"venue"
},
  "geometry": {"coordinates":[9.362358,51.734661],"type":"Point"}
}