{
  "type": "Feature",
  "properties": {
    "iso:country":"DE",
    "sg:address":"Morgengasse 5",
    "sg:city":"Sipplingen",
    "sg:postcode":"78354",
    "sg:province":"Baden-W\u00fcrttemberg",
    "wof:name":"Nav-wirtschaftsdienst F\u00fcr \u00c4rzte Gmbh",
    "wof:placetype":"venue"
},
  "geometry": {"coordinates":[9.1040287018,47.7959251404],"type":"Point"}
}