{
  "type": "Feature",
  "properties": {
    "iso:country":"DE",
    "sg:address":"Ostlandstr. 20",
    "sg:city":"Hamb\u00fchren",
    "sg:phone":"+49 5084/93040",
    "sg:postcode":"29313",
    "sg:province":"Niedersachsen",
    "wof:name":"Ostland Apotheke Inh. Wolfgang Luecke",
    "wof:placetype":"venue"
},
  "geometry": {"coordinates":[9.939217,52.641312],"type":"Point"}
}