{
  "type": "Feature",
  "properties": {
    "iso:country":"DE",
    "sg:address":"Hauptstr. 10",
    "sg:city":"Zwiefalten",
    "sg:phone":"+49 7373/915288",
    "sg:postcode":"88529",
    "sg:province":"Baden-W\u00fcrttemberg",
    "wof:name":"Maximilian Keller Rechtsanwalt",
    "wof:placetype":"venue"
},
  "geometry": {"coordinates":[9.4593954086,48.2319908142],"type":"Point"}
}