{
  "type": "Feature",
  "properties": {
    "iso:country":"DE",
    "sg:address":"Gemarkenstr. 125",
    "sg:city":"Essen",
    "sg:phone":"+49 201/730853",
    "sg:postcode":"45147",
    "sg:province":"Nordrhein-Westfalen",
    "wof:name":"Seibel",
    "wof:placetype":"venue"
},
  "geometry": {"coordinates":[6.9877409935,51.4402923584],"type":"Point"}
}