{
  "type": "Feature",
  "properties": {
    "iso:country":"DE",
    "sg:address":"Gerold Damm 2 -4",
    "sg:city":"Bosau",
    "sg:phone":"+49 4527/9940",
    "sg:postcode":"23715",
    "sg:province":"Schleswig-Holstein",
    "wof:name":"Strauers Hotel Am See",
    "wof:placetype":"venue"
},
  "geometry": {"coordinates":[10.4297056198,54.1065330505],"type":"Point"}
}