{
  "type": "Feature",
  "properties": {
    "iso:country":"DE",
    "sg:address":"Lenneper Str. 130 c",
    "sg:city":"Wuppertal",
    "sg:phone":"+49 202/629011",
    "sg:postcode":"42289",
    "sg:province":"Nordrhein-Westfalen",
    "wof:name":"Kurt Frowein Gmbh & Co. Kg",
    "wof:placetype":"venue"
},
  "geometry": {"coordinates":[7.230006,51.259609],"type":"Point"}
}