{
  "type": "Feature",
  "properties": {
    "iso:country":"DE",
    "sg:address":"Krumme Str. 25",
    "sg:city":"Stadthagen",
    "sg:phone":"+49 5721/2840",
    "sg:postcode":"31655",
    "sg:province":"Niedersachsen",
    "wof:name":"Vorwerk Elektrowerke Stiftung & Co. Kg",
    "wof:placetype":"venue"
},
  "geometry": {"coordinates":[9.2058792114,52.3266983032],"type":"Point"}
}