{
  "type": "Feature",
  "properties": {
    "iso:country":"DE",
    "sg:address":"Bibelstr. 9",
    "sg:city":"Saarlouis",
    "sg:phone":"+49 6831/3084",
    "sg:postcode":"66740",
    "sg:province":"Saarland",
    "wof:name":"Dr. Eckart Berend Rechtsanwalt",
    "wof:placetype":"venue"
},
  "geometry": {"coordinates":[6.7525911331,49.3150253296],"type":"Point"}
}