{
  "type": "Feature",
  "properties": {
    "iso:country":"DE",
    "sg:address":"Wedemeyerstr. 15",
    "sg:city":"Hannover",
    "sg:phone":"+49 511/804859",
    "sg:postcode":"30173",
    "sg:province":"Niedersachsen",
    "wof:name":"Michael Schubert Ingenieur",
    "wof:placetype":"venue"
},
  "geometry": {"coordinates":[9.7489089966,52.356464386],"type":"Point"}
}