{
  "type": "Feature",
  "properties": {
    "iso:country":"DE",
    "sg:address":"Rieggis",
    "sg:city":"Waltenhofen",
    "sg:phone":"+49 8379/7030",
    "sg:postcode":"87448",
    "sg:province":"Bayern",
    "wof:name":"G. & S. \u00dccker",
    "wof:placetype":"venue"
},
  "geometry": {"coordinates":[10.203209877,47.6299705505],"type":"Point"}
}