{
  "type": "Feature",
  "properties": {
    "iso:country":"DE",
    "sg:address":"Leopoldstr. 13",
    "sg:city":"D\u00fcsseldorf",
    "sg:phone":"+49 211/364545",
    "sg:postcode":"40211",
    "sg:province":"Nordrhein-Westfalen",
    "wof:name":"Verlag R. Kr\u00fcger",
    "wof:placetype":"venue"
},
  "geometry": {"coordinates":[6.7900319099,51.2261657715],"type":"Point"}
}