{
  "type": "Feature",
  "properties": {
    "iso:country":"DE",
    "sg:address":"Viktorstr. 17",
    "sg:city":"Xanten",
    "sg:phone":"+49 2801/4044",
    "sg:postcode":"46509",
    "sg:province":"Nordrhein-Westfalen",
    "wof:name":"Kerkmann Und Gr\u00fctters Rechtsanw\u00e4lte",
    "wof:placetype":"venue"
},
  "geometry": {"coordinates":[6.4601349831,51.6573944092],"type":"Point"}
}