{
  "type": "Feature",
  "properties": {
    "iso:country":"DE",
    "sg:address":"Rudolf-Harbig-Str. 1",
    "sg:city":"Wunstorf",
    "sg:phone":"+49 5031/13427",
    "sg:postcode":"31515",
    "sg:province":"Niedersachsen",
    "wof:name":"Calisa",
    "wof:placetype":"venue"
},
  "geometry": {"coordinates":[9.4360904694,52.4096832275],"type":"Point"}
}