{
  "type": "Feature",
  "properties": {
    "iso:country":"DE",
    "sg:address":"Bussardstr 1",
    "sg:city":"Dortmund",
    "sg:phone":"+49 231/9330320",
    "sg:postcode":"44357",
    "sg:province":"Nordrhein-Westfalen",
    "wof:name":"Wilhelm Goldschmidt Gmbh & Co Kg",
    "wof:placetype":"venue"
},
  "geometry": {"coordinates":[7.372035,51.570221],"type":"Point"}
}