{
  "type": "Feature",
  "properties": {
    "iso:country":"DE",
    "sg:address":"Akazienstr. 14",
    "sg:city":"Melchow",
    "sg:phone":"+49 3337/3643",
    "sg:postcode":"16230",
    "sg:province":"Brandenburg",
    "wof:name":"Planungsgesellschaft Dr. Kalanke Mbh",
    "wof:placetype":"venue"
},
  "geometry": {"coordinates":[13.6973600388,52.7729797363],"type":"Point"}
}