{
  "type": "Feature",
  "properties": {
    "iso:country":"DE",
    "sg:address":"Curd-J\u00fcrgens-Str. 4",
    "sg:city":"M\u00fcnchen",
    "sg:phone":"+49 89/6379621",
    "sg:postcode":"81739",
    "sg:province":"Bayern",
    "wof:name":"H. J. Zins Immobilienmakler",
    "wof:placetype":"venue"
},
  "geometry": {"coordinates":[11.64320755,48.0849189758],"type":"Point"}
}