{
  "type": "Feature",
  "properties": {
    "iso:country":"DE",
    "sg:address":"Westliche Karl-Friedrich-Str.",
    "sg:city":"Pforzheim",
    "sg:phone":"+49 7231/1840",
    "sg:postcode":"75172",
    "sg:province":"Baden-W\u00fcrttemberg",
    "wof:name":"Volksbank Pforzheim Verwaltungs-gmbh",
    "wof:placetype":"venue"
},
  "geometry": {"coordinates":[8.68607,48.8923],"type":"Point"}
}