{
  "type": "Feature",
  "properties": {
    "iso:country":"DE",
    "sg:address":"Zusamstr. 14",
    "sg:city":"Augsburg",
    "sg:phone":"+49 821/711363",
    "sg:postcode":"86165",
    "sg:province":"Bayern",
    "wof:name":"Poth Transportger\u00e4te Gmbh",
    "wof:placetype":"venue"
},
  "geometry": {"coordinates":[10.9364843369,48.3758125305],"type":"Point"}
}