{
  "type": "Feature",
  "properties": {
    "iso:country":"DE",
    "sg:address":"Untere M\u00fchlbachstr. 19",
    "sg:city":"Friedrichshafen",
    "sg:phone":"+49 4975/4195200",
    "sg:postcode":"88045",
    "sg:province":"Baden-W\u00fcrttemberg",
    "wof:name":"Schmidt-modellbau Gmbh",
    "wof:placetype":"venue"
},
  "geometry": {"coordinates":[9.4444799423,47.6742935181],"type":"Point"}
}