{
  "type": "Feature",
  "properties": {
    "iso:country":"DE",
    "sg:address":"Panoramaweg 47",
    "sg:city":"M\u00f6glingen",
    "sg:phone":"+49 7141/483059",
    "sg:postcode":"71696",
    "sg:province":"Baden-W\u00fcrttemberg",
    "wof:name":"Friedrich R\u00fchle",
    "wof:placetype":"venue"
},
  "geometry": {"coordinates":[9.1287050247,48.8924446106],"type":"Point"}
}