{
  "type": "Feature",
  "properties": {
    "iso:country":"DE",
    "sg:address":"Br\u00fchler Herrenberg 30",
    "sg:city":"Erfurt",
    "sg:phone":"+49 361/2229714",
    "sg:postcode":"99092",
    "sg:province":"Th\u00fcringen",
    "wof:name":"J. Und H. Wloka",
    "wof:placetype":"venue"
},
  "geometry": {"coordinates":[11.0067062378,50.9717178345],"type":"Point"}
}