{
  "type": "Feature",
  "properties": {
    "iso:country":"DE",
    "sg:address":"Frauenstr. 32",
    "sg:city":"M\u00fcnchen",
    "sg:phone":"+49 89/2123936",
    "sg:postcode":"80469",
    "sg:province":"Bayern",
    "wof:name":"Elite Fashion Vertrieb Gmbh",
    "wof:placetype":"venue"
},
  "geometry": {"coordinates":[11.5797367096,48.1344184875],"type":"Point"}
}