{
  "type": "Feature",
  "properties": {
    "iso:country":"DE",
    "sg:address":"Leonhard-Karl-Str. 24",
    "sg:city":"Wertheim",
    "sg:phone":"+49 4975/247020",
    "sg:postcode":"97877",
    "sg:province":"Baden-W\u00fcrttemberg",
    "wof:name":"Ess Schweisstechnik Gmbh",
    "wof:placetype":"venue"
},
  "geometry": {"coordinates":[9.7563686371,47.9323234558],"type":"Point"}
}