{
  "type": "Feature",
  "properties": {
    "iso:country":"DE",
    "sg:address":"Sonnborner Str. 120",
    "sg:city":"Wuppertal",
    "sg:phone":"+49 202/740472",
    "sg:postcode":"42327",
    "sg:province":"Nordrhein-Westfalen",
    "wof:name":"Manfred Liebisch",
    "wof:placetype":"venue"
},
  "geometry": {"coordinates":[7.0989351273,51.2384757996],"type":"Point"}
}