{
  "type": "Feature",
  "properties": {
    "iso:country":"DE",
    "sg:address":"Ahauser Str.",
    "sg:city":"Legden",
    "sg:postcode":"48739",
    "sg:province":"Nordrhein-Westfalen",
    "wof:name":"Milchliefergenossenschaft Legden Eg",
    "wof:placetype":"venue"
},
  "geometry": {"coordinates":[7.0990381241,52.0304374695],"type":"Point"}
}