{
  "type": "Feature",
  "properties": {
    "iso:country":"DE",
    "sg:address":"Fichtenweg 1",
    "sg:city":"Windhagen",
    "sg:phone":"+49 2645/95010",
    "sg:postcode":"53578",
    "sg:province":"Rheinland-Pfalz",
    "wof:name":"Elbo-tel Eltner & Borsch Ohg",
    "wof:placetype":"venue"
},
  "geometry": {"coordinates":[7.357171,50.647793],"type":"Point"}
}