{
  "type": "Feature",
  "properties": {
    "iso:country":"DE",
    "sg:address":"Am Domhof 14",
    "sg:city":"Pulheim",
    "sg:phone":"+49 2238/54141",
    "sg:postcode":"50259",
    "sg:province":"Nordrhein-Westfalen",
    "wof:name":"Horst Gallwitz Ingenieur Und Architekt",
    "wof:placetype":"venue"
},
  "geometry": {"coordinates":[6.788808,50.983425],"type":"Point"}
}