{
  "type": "Feature",
  "properties": {
    "iso:country":"DE",
    "sg:address":"Alter Dorfweg 30-50",
    "sg:city":"Bremen",
    "sg:phone":"+49 421/576600",
    "sg:postcode":"28259",
    "sg:province":"Bremen",
    "wof:name":"Apotheke Roland-center",
    "wof:placetype":"venue"
},
  "geometry": {"coordinates":[8.740355,53.048374],"type":"Point"}
}