{
  "type": "Feature",
  "properties": {
    "iso:country":"DE",
    "sg:address":"Robert-Blum-Str. 35",
    "sg:city":"Halle",
    "sg:phone":"+49 345/530550",
    "sg:postcode":"06114",
    "sg:province":"Sachsen-Anhalt",
    "wof:name":"Schnelldruckerei U. Dtp-studio Inh.: Hanns-olaf Berthold",
    "wof:placetype":"venue"
},
  "geometry": {"coordinates":[11.969178,51.495186],"type":"Point"}
}