{
  "type": "Feature",
  "properties": {
    "iso:country":"DE",
    "sg:address":"Hohendorfer Weg",
    "sg:city":"Merseburg",
    "sg:phone":"+49 3461/73290",
    "sg:postcode":"06217",
    "sg:province":"Sachsen-Anhalt",
    "wof:name":"Ehl Baustoffwerk Merseburg Gmbh",
    "wof:placetype":"venue"
},
  "geometry": {"coordinates":[11.989615,51.376995],"type":"Point"}
}