{
  "type": "Feature",
  "properties": {
    "iso:country":"DE",
    "sg:address":"Auf der Heide 9",
    "sg:city":"Schwerte",
    "sg:phone":"+49 2304/971230",
    "sg:postcode":"58239",
    "sg:province":"Nordrhein-Westfalen",
    "wof:name":"Rainer Hermes Gmbh & Co. Kg",
    "wof:placetype":"venue"
},
  "geometry": {"coordinates":[7.5766038895,51.4217033386],"type":"Point"}
}