{
  "type": "Feature",
  "properties": {
    "iso:country":"DE",
    "sg:address":"Anwandweg 3",
    "sg:city":"Memmingen",
    "sg:phone":"+49 8331/80593",
    "sg:postcode":"87700",
    "sg:province":"Bayern",
    "wof:name":"Peter Zweifel Steuerberater",
    "wof:placetype":"venue"
},
  "geometry": {"coordinates":[10.1570472717,48.0188217163],"type":"Point"}
}