{
  "type": "Feature",
  "properties": {
    "iso:country":"DE",
    "sg:address":"Robert-Koch-Str. 4",
    "sg:city":"Ahlen",
    "sg:phone":"+49 2382/81900",
    "sg:postcode":"59227",
    "sg:province":"Nordrhein-Westfalen",
    "wof:name":"Kapellenhof",
    "wof:placetype":"venue"
},
  "geometry": {"coordinates":[7.8790459633,51.76537323],"type":"Point"}
}