{
  "type": "Feature",
  "properties": {
    "iso:country":"DE",
    "sg:address":"Kastenbauerstr. 11",
    "sg:city":"M\u00fcnchen",
    "sg:phone":"+49 89/9935570",
    "sg:postcode":"81677",
    "sg:province":"Bayern",
    "wof:name":"Kreutzkamm Gmbh",
    "wof:placetype":"venue"
},
  "geometry": {"coordinates":[11.639314,48.138329],"type":"Point"}
}