{
  "type": "Feature",
  "properties": {
    "iso:country":"DE",
    "sg:address":"Peter-Anders-Str. 4",
    "sg:city":"M\u00fcnchen",
    "sg:phone":"+49 89/8342073",
    "sg:postcode":"81245",
    "sg:province":"Bayern",
    "wof:name":"Sf. Fitness- Und Freizeitcenter Gmbh",
    "wof:placetype":"venue"
},
  "geometry": {"coordinates":[11.4783096313,48.1529006958],"type":"Point"}
}