{
  "type": "Feature",
  "properties": {
    "iso:country":"DE",
    "sg:address":"Industriestr. 9",
    "sg:city":"Hammelburg",
    "sg:phone":"+49 9732/2447",
    "sg:postcode":"97762",
    "sg:province":"Bayern",
    "wof:name":"Elmar Jobst",
    "wof:placetype":"venue"
},
  "geometry": {"coordinates":[9.8798027039,50.1230049133],"type":"Point"}
}