{
  "type": "Feature",
  "properties": {
    "iso:country":"DE",
    "sg:address":"Gr\u00fcnhauser Str. 35",
    "sg:city":"Lauchhammer",
    "sg:phone":"+49 3574/861043",
    "sg:postcode":"01979",
    "sg:province":"Brandenburg",
    "wof:name":"Karin Rischke Steuerbevollm\u00e4chtigte",
    "wof:placetype":"venue"
},
  "geometry": {"coordinates":[13.7909822464,51.5089836121],"type":"Point"}
}