{
  "type": "Feature",
  "properties": {
    "iso:country":"DE",
    "sg:address":"Bahnhofstr. 18",
    "sg:city":"Lemf\u00f6rde",
    "sg:phone":"+49 5443/462",
    "sg:postcode":"49448",
    "sg:province":"Niedersachsen",
    "wof:name":"Heinrich Kreienbrock",
    "wof:placetype":"venue"
},
  "geometry": {"coordinates":[8.372974,52.464092],"type":"Point"}
}