{
  "type": "Feature",
  "properties": {
    "iso:country":"DE",
    "sg:address":"Ke\u00dflerstr. 27",
    "sg:city":"Jena",
    "sg:phone":"+49 3641/607662",
    "sg:postcode":"07745",
    "sg:province":"Th\u00fcringen",
    "wof:name":"Mm Montagesysteme Gmbh",
    "wof:placetype":"venue"
},
  "geometry": {"coordinates":[11.592314,50.897964],"type":"Point"}
}