{
  "type": "Feature",
  "properties": {
    "iso:country":"DE",
    "sg:address":"In der L\u00fch 10-14",
    "sg:city":"Dormagen",
    "sg:postcode":"41542",
    "sg:province":"Nordrhein-Westfalen",
    "wof:name":"Gohr-plan Com Gmbh",
    "wof:placetype":"venue"
},
  "geometry": {"coordinates":[6.719049,51.10899],"type":"Point"}
}