{
  "type": "Feature",
  "properties": {
    "iso:country":"DE",
    "sg:address":"Lahnstr. 12",
    "sg:city":"Bad Camberg",
    "sg:phone":"+49 6434/91610",
    "sg:postcode":"65520",
    "sg:province":"Hessen",
    "wof:name":"Taunus-reisen Gmbh",
    "wof:placetype":"venue"
},
  "geometry": {"coordinates":[8.2603368759,50.299495697],"type":"Point"}
}