{
  "type": "Feature",
  "properties": {
    "iso:country":"DE",
    "sg:address":"Lange Str. 7",
    "sg:city":"Quakenbr\u00fcck",
    "sg:phone":"+49 5431/2500",
    "sg:postcode":"49610",
    "sg:province":"Niedersachsen",
    "wof:name":"H. Lange",
    "wof:placetype":"venue"
},
  "geometry": {"coordinates":[7.955722,52.674698],"type":"Point"}
}