{
  "type": "Feature",
  "properties": {
    "iso:country":"DE",
    "sg:address":"Friedrich-Ebert-Str. 17",
    "sg:city":"Bad Wildungen",
    "sg:phone":"+49 5621/3933",
    "sg:postcode":"34537",
    "sg:province":"Hessen",
    "wof:name":"Herbert Vohland",
    "wof:placetype":"venue"
},
  "geometry": {"coordinates":[9.1254501343,51.1269493103],"type":"Point"}
}