{
  "type": "Feature",
  "properties": {
    "iso:country":"DE",
    "sg:address":"Zeilsheimer Str. 48",
    "sg:city":"Hofheim",
    "sg:phone":"+49 6192/36076",
    "sg:postcode":"65719",
    "sg:province":"Hessen",
    "wof:name":"P. Freiherr Von Werthern",
    "wof:placetype":"venue"
},
  "geometry": {"coordinates":[8.456158638,50.0880737305],"type":"Point"}
}