{
  "type": "Feature",
  "properties": {
    "iso:country":"DE",
    "sg:address":"Herrenweg 2",
    "sg:city":"Neunkirchen-Seelscheid",
    "sg:phone":"+49 2247/6508",
    "sg:postcode":"53819",
    "sg:province":"Nordrhein-Westfalen",
    "wof:name":"Werner Birkenfeld",
    "wof:placetype":"venue"
},
  "geometry": {"coordinates":[7.29269,50.870468],"type":"Point"}
}