{
  "type": "Feature",
  "properties": {
    "iso:country":"DE",
    "sg:address":"Friedrichstr. 18",
    "sg:city":"Hennickendorf",
    "sg:phone":"+49 33434/7810",
    "sg:postcode":"15378",
    "sg:province":"Brandenburg",
    "wof:name":"N. Pose",
    "wof:placetype":"venue"
},
  "geometry": {"coordinates":[13.8444824219,52.504283905],"type":"Point"}
}