{
  "type": "Feature",
  "properties": {
    "iso:country":"DE",
    "sg:address":"Kr\u00e4henweg 3",
    "sg:city":"Wuppertal",
    "sg:phone":"+49 202/421926",
    "sg:postcode":"42119",
    "sg:province":"Nordrhein-Westfalen",
    "wof:name":"Dr. Joachim Von Wussow",
    "wof:placetype":"venue"
},
  "geometry": {"coordinates":[7.1574811935,51.2463340759],"type":"Point"}
}