{
  "type": "Feature",
  "properties": {
    "iso:country":"DE",
    "sg:address":"Hauptstr 82",
    "sg:city":"Cuxhaven",
    "sg:phone":"+49 6322/989724",
    "sg:postcode":"27478",
    "sg:province":"Niedersachsen",
    "wof:name":"Feinschmecker Ester Gmbh",
    "wof:placetype":"venue"
},
  "geometry": {"coordinates":[8.165754,49.460052],"type":"Point"}
}