{
  "type": "Feature",
  "properties": {
    "iso:country":"DE",
    "sg:address":"Am Markt 6",
    "sg:city":"Barnstorf",
    "sg:phone":"+49 5442/9800",
    "sg:postcode":"49406",
    "sg:province":"Niedersachsen",
    "wof:name":"Hotel Roshop",
    "wof:placetype":"venue"
},
  "geometry": {"coordinates":[8.5062561035,52.7101745605],"type":"Point"}
}