{
  "type": "Feature",
  "properties": {
    "iso:country":"DE",
    "sg:address":"Danziger Str. 1",
    "sg:city":"Ludwigsburg",
    "sg:phone":"+49 7141/83080",
    "sg:postcode":"71638",
    "sg:province":"Baden-W\u00fcrttemberg",
    "wof:name":"H. Tepper Immobilienmakler",
    "wof:placetype":"venue"
},
  "geometry": {"coordinates":[9.2071065903,48.8852348328],"type":"Point"}
}