{
  "type": "Feature",
  "properties": {
    "iso:country":"DE",
    "sg:address":"Didierstr. 27-35",
    "sg:city":"Lahnstein",
    "sg:postcode":"56112",
    "sg:province":"Rheinland-Pfalz",
    "wof:name":"Proland Rheinisch-nassauische Lagerhaus Gmbh",
    "wof:placetype":"venue"
},
  "geometry": {"coordinates":[7.593348,50.323227],"type":"Point"}
}