{
  "type": "Feature",
  "properties": {
    "iso:country":"DE",
    "sg:address":"Obersteinbach",
    "sg:city":"Waldenburg",
    "sg:phone":"+49 7949/357",
    "sg:postcode":"74638",
    "sg:province":"Baden-W\u00fcrttemberg",
    "wof:name":"Gastst\u00e4tte M. Potsch",
    "wof:placetype":"venue"
},
  "geometry": {"coordinates":[9.6138496399,49.153301239],"type":"Point"}
}