{
  "type": "Feature",
  "properties": {
    "iso:country":"DE",
    "sg:address":"Gibitzenhofstr. 28",
    "sg:city":"N\u00fcrnberg",
    "sg:phone":"+49 911/421696",
    "sg:postcode":"90443",
    "sg:province":"Bayern",
    "wof:name":"Kirsch",
    "wof:placetype":"venue"
},
  "geometry": {"coordinates":[11.06733,49.440735],"type":"Point"}
}