{
  "type": "Feature",
  "properties": {
    "iso:country":"DE",
    "sg:address":"H\u00f6lderlinstr. 1a",
    "sg:city":"Stuttgart",
    "sg:phone":"+49 711/2263893",
    "sg:postcode":"70174",
    "sg:province":"Baden-W\u00fcrttemberg",
    "wof:name":"Konrad Witz Architekt",
    "wof:placetype":"venue"
},
  "geometry": {"coordinates":[9.166146,48.785095],"type":"Point"}
}