{
  "type": "Feature",
  "properties": {
    "iso:country":"DE",
    "sg:address":"Hauptstr. 22",
    "sg:city":"Wagenfeld",
    "sg:phone":"+49 5444/376",
    "sg:postcode":"49419",
    "sg:province":"Niedersachsen",
    "wof:name":"W. Scheland",
    "wof:placetype":"venue"
},
  "geometry": {"coordinates":[8.5845441818,52.5505752563],"type":"Point"}
}