{
  "type": "Feature",
  "properties": {
    "iso:country":"DE",
    "sg:address":"Kaiserplatz 4",
    "sg:city":"Willich",
    "sg:phone":"+49 2154/2263",
    "sg:postcode":"47877",
    "sg:province":"Nordrhein-Westfalen",
    "wof:name":"Schulmeister Druckerei Gmbh",
    "wof:placetype":"venue"
},
  "geometry": {"coordinates":[6.552237,51.265076],"type":"Point"}
}