{
  "type": "Feature",
  "properties": {
    "iso:country":"DE",
    "sg:address":"Teichmannstr. 28",
    "sg:city":"Leipzig",
    "sg:phone":"+49 34297/48524",
    "sg:postcode":"04288",
    "sg:province":"Sachsen",
    "wof:name":"B. Hinke",
    "wof:placetype":"venue"
},
  "geometry": {"coordinates":[12.4715948105,51.2953414917],"type":"Point"}
}