{
  "type": "Feature",
  "properties": {
    "iso:country":"DE",
    "sg:address":"Norderstr. 1",
    "sg:city":"Haselund",
    "sg:phone":"+49 4843/204460",
    "sg:postcode":"25855",
    "sg:province":"Schleswig-Holstein",
    "wof:name":"Toni Maroni Gmbh",
    "wof:placetype":"venue"
},
  "geometry": {"coordinates":[9.187272,54.59409],"type":"Point"}
}