{
  "type": "Feature",
  "properties": {
    "iso:country":"DE",
    "sg:address":"F\u00e4hrstr. 20",
    "sg:city":"Kobern-Gondorf",
    "sg:phone":"+49 2607/972037",
    "sg:postcode":"56330",
    "sg:province":"Rheinland-Pfalz",
    "wof:name":"Pension Kastor-schenke",
    "wof:placetype":"venue"
},
  "geometry": {"coordinates":[7.4602999687,50.3085670471],"type":"Point"}
}