{
  "type": "Feature",
  "properties": {
    "iso:country":"DE",
    "sg:address":"J\u00fcrgensstr. 16",
    "sg:city":"Goch",
    "sg:phone":"+49 4928/232362",
    "sg:postcode":"47574",
    "sg:province":"Nordrhein-Westfalen",
    "wof:name":"Hermann Sauter",
    "wof:placetype":"venue"
},
  "geometry": {"coordinates":[6.137111187,51.6892280579],"type":"Point"}
}