{
  "type": "Feature",
  "properties": {
    "iso:country":"DE",
    "sg:address":"Locher Str. 6",
    "sg:city":"Stein",
    "sg:phone":"+49 911/677000",
    "sg:postcode":"90547",
    "sg:province":"Bayern",
    "wof:name":"Ec Und C Electronic Concepts Und Consulting Gmbh",
    "wof:placetype":"venue"
},
  "geometry": {"coordinates":[10.9907369614,49.4040679932],"type":"Point"}
}