{
  "type": "Feature",
  "properties": {
    "iso:country":"DE",
    "sg:address":"D\u00f6hrenweg 2",
    "sg:city":"Bleckede",
    "sg:phone":"+49 5854/696",
    "sg:postcode":"21354",
    "sg:province":"Niedersachsen",
    "wof:name":"Siegbert Hartmann",
    "wof:placetype":"venue"
},
  "geometry": {"coordinates":[10.7631902695,53.2552909851],"type":"Point"}
}