{
  "type": "Feature",
  "properties": {
    "iso:country":"DE",
    "sg:address":"Theodor-Storm-Weg 3",
    "sg:city":"Bretten",
    "sg:phone":"+49 7252/4826",
    "sg:postcode":"75015",
    "sg:province":"Baden-W\u00fcrttemberg",
    "wof:name":"Godec Transporte Gmbh",
    "wof:placetype":"venue"
},
  "geometry": {"coordinates":[8.6861820221,49.0412025452],"type":"Point"}
}