{
  "type": "Feature",
  "properties": {
    "iso:country":"DE",
    "sg:address":"Reutestr. 6",
    "sg:city":"Bad D\u00fcrrheim",
    "sg:phone":"+49 7726/977006",
    "sg:postcode":"78073",
    "sg:province":"Baden-W\u00fcrttemberg",
    "wof:name":"G\u00fcnter Glunz",
    "wof:placetype":"venue"
},
  "geometry": {"coordinates":[8.566821,48.028488],"type":"Point"}
}