{
  "type": "Feature",
  "properties": {
    "iso:country":"DE",
    "sg:address":"Jahnstr. 1",
    "sg:city":"Laufenburg",
    "sg:phone":"+49 7763/7917",
    "sg:postcode":"79725",
    "sg:province":"Baden-W\u00fcrttemberg",
    "wof:name":"Wilh. Laule Ingenieur",
    "wof:placetype":"venue"
},
  "geometry": {"coordinates":[8.0475282669,47.5601921082],"type":"Point"}
}