{
  "type": "Feature",
  "properties": {
    "iso:country":"DE",
    "sg:address":"Priamosstr. 1",
    "sg:city":"Bergheim",
    "sg:phone":"+49 2271/92683",
    "sg:postcode":"50127",
    "sg:province":"Nordrhein-Westfalen",
    "wof:name":"Helle",
    "wof:placetype":"venue"
},
  "geometry": {"coordinates":[6.6725640297,50.9342575073],"type":"Point"}
}