{
  "type": "Feature",
  "properties": {
    "iso:country":"DE",
    "sg:address":"Heubergstr. 29",
    "sg:city":"M\u00fcnchen",
    "sg:phone":"+49 89/4311043",
    "sg:postcode":"81825",
    "sg:province":"Bayern",
    "wof:name":"Werner Ohneberg Wom-hydraulik",
    "wof:placetype":"venue"
},
  "geometry": {"coordinates":[11.6415510178,48.1169052124],"type":"Point"}
}