{
  "type": "Feature",
  "properties": {
    "iso:country":"DE",
    "sg:address":"Sch\u00e4ferstr. 20",
    "sg:city":"Friedrichsdorf",
    "sg:phone":"+49 6172/778132",
    "sg:postcode":"61381",
    "sg:province":"Hessen",
    "wof:name":"G\u00fcnter Greskamp",
    "wof:placetype":"venue"
},
  "geometry": {"coordinates":[8.6507263184,50.2425384521],"type":"Point"}
}