{
  "type": "Feature",
  "properties": {
    "iso:country":"DE",
    "sg:address":"Hauptstr. 16",
    "sg:city":"Pressath",
    "sg:phone":"+49 9644/391",
    "sg:postcode":"92690",
    "sg:province":"Bayern",
    "wof:name":"Stadt- Und Pfarrb\u00fccherei",
    "wof:placetype":"venue"
},
  "geometry": {"coordinates":[11.977058,49.80975],"type":"Point"}
}