{
  "type": "Feature",
  "properties": {
    "iso:country":"DE",
    "sg:address":"Buchenbachstr. 29",
    "sg:city":"Berglen",
    "sg:phone":"+49 7195/71771",
    "sg:postcode":"73663",
    "sg:province":"Baden-W\u00fcrttemberg",
    "wof:name":"Eintracht Rettersburg Wolfgang K\u00fchner",
    "wof:placetype":"venue"
},
  "geometry": {"coordinates":[9.4737415314,48.8721008301],"type":"Point"}
}