{
  "type": "Feature",
  "properties": {
    "iso:country":"DE",
    "sg:address":"Deutzener Str. 33",
    "sg:city":"Regis-Breitingen",
    "sg:phone":"+49 34343/51544",
    "sg:postcode":"04565",
    "sg:province":"Sachsen",
    "wof:name":"I. Wagner",
    "wof:placetype":"venue"
},
  "geometry": {"coordinates":[12.440776825,51.0945892334],"type":"Point"}
}