{
  "type": "Feature",
  "properties": {
    "iso:country":"DE",
    "sg:address":"Erzbergerstr. 5",
    "sg:city":"Singen",
    "sg:phone":"+49 7731/66150",
    "sg:postcode":"78224",
    "sg:province":"Baden-W\u00fcrttemberg",
    "wof:name":"Fritz Lutz",
    "wof:placetype":"venue"
},
  "geometry": {"coordinates":[8.8374643326,47.760848999],"type":"Point"}
}