{
  "type": "Feature",
  "properties": {
    "iso:country":"DE",
    "sg:address":"Darmst\u00e4dter Landstr. 264",
    "sg:city":"Frankfurt",
    "sg:phone":"+49 69/682006",
    "sg:postcode":"60598",
    "sg:province":"Hessen",
    "wof:name":"Becker & Partner",
    "wof:placetype":"venue"
},
  "geometry": {"coordinates":[8.6909408569,50.0924911499],"type":"Point"}
}