{
  "type": "Feature",
  "properties": {
    "iso:country":"DE",
    "sg:address":"H\u00f6ggmairstr. 1",
    "sg:city":"Gangkofen",
    "sg:postcode":"84140",
    "sg:province":"Bayern",
    "wof:name":"Schmidhuber Bau Gmbh",
    "wof:placetype":"venue"
},
  "geometry": {"coordinates":[12.558597,48.440044],"type":"Point"}
}