{
  "type": "Feature",
  "properties": {
    "iso:country":"DE",
    "sg:address":"Anna-Birle-Str. 3 A",
    "sg:city":"Mainz-Kastel",
    "sg:phone":"+49 4961/3425947",
    "sg:postcode":"55252",
    "sg:province":"Hessen",
    "wof:name":"Amf Bowling Inc. Niederlassung Deutschland",
    "wof:placetype":"venue"
},
  "geometry": {"coordinates":[8.279577,50.026428],"type":"Point"}
}