{
  "type": "Feature",
  "properties": {
    "iso:country":"DE",
    "sg:address":"St. Wendeler Str. 9",
    "sg:city":"Tholey",
    "sg:phone":"+49 6853/300550",
    "sg:postcode":"66636",
    "sg:province":"Saarland",
    "wof:name":"Baron Und Theobalt Ergotherapeutische Praxis",
    "wof:placetype":"venue"
},
  "geometry": {"coordinates":[7.038619,49.483276],"type":"Point"}
}