{
  "type": "Feature",
  "properties": {
    "iso:country":"DE",
    "sg:address":"Schwalbenbergweg 50\u00a0",
    "sg:city":"Werder / Havel",
    "sg:phone":"+49 3327",
    "sg:postcode":"14542",
    "sg:province":"Brandenburg",
    "wof:name":"Neuer Garten, Gala-bau, Teichanlagen",
    "wof:placetype":"venue"
},
  "geometry": {"coordinates":[12.908344,52.389557],"type":"Point"}
}