{
  "type": "Feature",
  "properties": {
    "iso:country":"DE",
    "sg:address":"Am Waldschl\u00f6\u00dfchen 4",
    "sg:city":"Langelsheim",
    "sg:phone":"+49 5325/4179",
    "sg:postcode":"38685",
    "sg:province":"Niedersachsen",
    "wof:name":"Cafe Restaurant Waldschl\u00f6\u00dfchen",
    "wof:placetype":"venue"
},
  "geometry": {"coordinates":[10.2778787613,51.8610916138],"type":"Point"}
}