{
  "type": "Feature",
  "properties": {
    "iso:country":"DE",
    "sg:address":"Prozessionsweg 46-52",
    "sg:city":"Herzebrock-Clarholz",
    "sg:phone":"+49 5245/872920",
    "sg:postcode":"33442",
    "sg:province":"Nordrhein-Westfalen",
    "wof:name":"Bernhard Becker",
    "wof:placetype":"venue"
},
  "geometry": {"coordinates":[8.2095317841,51.9013252258],"type":"Point"}
}