{
  "type": "Feature",
  "properties": {
    "iso:country":"DE",
    "sg:address":"Bebelstr. 1",
    "sg:city":"Ballenstedt",
    "sg:postcode":"06493",
    "sg:province":"Sachsen-Anhalt",
    "wof:name":"Evangelisches Pfarramt Schlo\u00dfkirchengemeinde",
    "wof:placetype":"venue"
},
  "geometry": {"coordinates":[11.2262039185,51.720123291],"type":"Point"}
}