{
  "type": "Feature",
  "properties": {
    "iso:country":"DE",
    "sg:address":"Heeresbergstr. 8",
    "sg:city":"Gera",
    "sg:phone":"+49 365/7110299",
    "sg:postcode":"07549",
    "sg:province":"Th\u00fcringen",
    "wof:name":"A. Geitel",
    "wof:placetype":"venue"
},
  "geometry": {"coordinates":[12.0767726898,50.8457450867],"type":"Point"}
}