{
  "type": "Feature",
  "properties": {
    "iso:country":"DE",
    "sg:address":"Sandstr. 10",
    "sg:city":"Allersberg",
    "sg:phone":"+49 9176/996990",
    "sg:postcode":"90584",
    "sg:province":"Bayern",
    "wof:name":"Friedinger",
    "wof:placetype":"venue"
},
  "geometry": {"coordinates":[11.251234,49.248745],"type":"Point"}
}