{
  "type": "Feature",
  "properties": {
    "iso:country":"DE",
    "sg:address":"K\u00f6nigsplatz 36a",
    "sg:city":"Kassel",
    "sg:phone":"+49 561/780856",
    "sg:postcode":"34117",
    "sg:province":"Hessen",
    "wof:name":"K\u00f6-grill",
    "wof:placetype":"venue"
},
  "geometry": {"coordinates":[9.4985961914,51.3152503967],"type":"Point"}
}