{
  "type": "Feature",
  "properties": {
    "iso:country":"DE",
    "sg:address":"Theodor-Storm-Str. 7",
    "sg:city":"Leverkusen",
    "sg:phone":"+49 214/402025",
    "sg:postcode":"51373",
    "sg:province":"Nordrhein-Westfalen",
    "wof:name":"Wolfgang Glaser Rechtsanwalt",
    "wof:placetype":"venue"
},
  "geometry": {"coordinates":[6.9960618019,51.0254325867],"type":"Point"}
}