{
  "type": "Feature",
  "properties": {
    "iso:country":"DE",
    "sg:address":"Stresemannring 50",
    "sg:city":"Nordhausen",
    "sg:phone":"+49 3631/600193",
    "sg:postcode":"99734",
    "sg:province":"Th\u00fcringen",
    "wof:name":"Gerda Maschke",
    "wof:placetype":"venue"
},
  "geometry": {"coordinates":[10.814644,51.497231],"type":"Point"}
}