{
  "type": "Feature",
  "properties": {
    "iso:country":"DE",
    "sg:address":"Renauweg 33",
    "sg:city":"Winterberg",
    "sg:phone":"+49 2981/2691",
    "sg:postcode":"59955",
    "sg:province":"Nordrhein-Westfalen",
    "wof:name":"Pension C. Hakenes-leisner",
    "wof:placetype":"venue"
},
  "geometry": {"coordinates":[8.4673624039,51.1927528381],"type":"Point"}
}