{
  "type": "Feature",
  "properties": {
    "iso:country":"DE",
    "sg:address":"Kirchbergstr. 20",
    "sg:city":"V\u00f6lklingen",
    "sg:postcode":"66333",
    "sg:province":"Saarland",
    "wof:name":"Profit-service-trading Balve Gmbh",
    "wof:placetype":"venue"
},
  "geometry": {"coordinates":[6.835978,49.245983],"type":"Point"}
}