{
  "type": "Feature",
  "properties": {
    "iso:country":"DE",
    "sg:address":"Maximilianstr. 12",
    "sg:city":"Starnberg",
    "sg:phone":"+49 8151/744749",
    "sg:postcode":"82319",
    "sg:province":"Bayern",
    "wof:name":"Olympia-apotheke Helge Walter",
    "wof:placetype":"venue"
},
  "geometry": {"coordinates":[11.344074,47.998432],"type":"Point"}
}