{
  "type": "Feature",
  "properties": {
    "iso:country":"DE",
    "sg:address":"Baldinger Str. 11",
    "sg:city":"Riesb\u00fcrg",
    "sg:phone":"+49 9081/7289",
    "sg:postcode":"73469",
    "sg:province":"Baden-W\u00fcrttemberg",
    "wof:name":"Biohof Heinrich Hiesinger",
    "wof:placetype":"venue"
},
  "geometry": {"coordinates":[10.428886,48.869831],"type":"Point"}
}