{
  "type": "Feature",
  "properties": {
    "iso:country":"DE",
    "sg:address":"Fr\u00f6belstr. 4",
    "sg:city":"Wengelsdorf",
    "sg:phone":"+49 34446/20054",
    "sg:postcode":"06688",
    "sg:province":"Sachsen-Anhalt",
    "wof:name":"J. Koch",
    "wof:placetype":"venue"
},
  "geometry": {"coordinates":[12.024474,51.276028],"type":"Point"}
}