{
  "type": "Feature",
  "properties": {
    "iso:country":"DE",
    "sg:address":"Spitalh\u00f6fe 7",
    "sg:city":"Villingen-Schwenningen",
    "sg:phone":"+49 7721/23739",
    "sg:postcode":"78052",
    "sg:province":"Baden-W\u00fcrttemberg",
    "wof:name":"Hubert Straub",
    "wof:placetype":"venue"
},
  "geometry": {"coordinates":[8.3888998032,48.0187797546],"type":"Point"}
}