{
  "type": "Feature",
  "properties": {
    "iso:country":"DE",
    "sg:address":"Ulrichweg 39",
    "sg:city":"Grafenau",
    "sg:phone":"+49 7033/43646",
    "sg:postcode":"71120",
    "sg:province":"Baden-W\u00fcrttemberg",
    "wof:name":"Manfred Berner Architekt",
    "wof:placetype":"venue"
},
  "geometry": {"coordinates":[8.913542,48.715954],"type":"Point"}
}