{
  "type": "Feature",
  "properties": {
    "iso:country":"DE",
    "sg:address":"Sauerlacher Str. 27",
    "sg:city":"Wolfratshausen",
    "sg:phone":"+49 8171/18171",
    "sg:postcode":"82515",
    "sg:province":"Bayern",
    "wof:name":"Fr\u00fcchte- Und Blumenparadies",
    "wof:placetype":"venue"
},
  "geometry": {"coordinates":[11.428185,47.913509],"type":"Point"}
}