{
  "type": "Feature",
  "properties": {
    "iso:country":"DE",
    "sg:address":"K\u00f6lner Str.232",
    "sg:city":"Krefeld",
    "sg:phone":"+49 2151/36061",
    "sg:postcode":"47805",
    "sg:province":"Nordrhein-Westfalen",
    "wof:name":"Dresdner Bank",
    "wof:placetype":"venue"
},
  "geometry": {"coordinates":[6.576053,51.316879],"type":"Point"}
}