{
  "type": "Feature",
  "properties": {
    "iso:country":"DE",
    "sg:address":"Mittlere Str. 18",
    "sg:city":"Brilon",
    "sg:phone":"+49 2961/3778",
    "sg:postcode":"59929",
    "sg:province":"Nordrhein-Westfalen",
    "wof:name":"Karl-clemens B\u00f6ddicker",
    "wof:placetype":"venue"
},
  "geometry": {"coordinates":[8.531561,51.425961],"type":"Point"}
}