{
  "type": "Feature",
  "properties": {
    "iso:country":"DE",
    "sg:address":"Kantstr. 14",
    "sg:city":"Gr\u00fcnberg",
    "sg:phone":"+49 6401/4658",
    "sg:postcode":"35305",
    "sg:province":"Hessen",
    "wof:name":"Ralf Reiner Rudrich Architekt",
    "wof:placetype":"venue"
},
  "geometry": {"coordinates":[8.953878,50.590908],"type":"Point"}
}