{
  "type": "Feature",
  "properties": {
    "iso:country":"DE",
    "sg:address":"Jakob-M\u00fcller-Str. 29",
    "sg:city":"Lampertheim",
    "sg:phone":"+49 6256/831250",
    "sg:postcode":"68623",
    "sg:province":"Hessen",
    "wof:name":"Onlinesport Stephan Gmbh",
    "wof:placetype":"venue"
},
  "geometry": {"coordinates":[8.5868034363,49.5993804932],"type":"Point"}
}