{
  "type": "Feature",
  "properties": {
    "iso:country":"DE",
    "sg:address":"W\u00fcrttembergerstr. 26",
    "sg:city":"Fridingen",
    "sg:phone":"+49 7463/99670",
    "sg:postcode":"78567",
    "sg:province":"Baden-W\u00fcrttemberg",
    "wof:name":"Hans Hermann Gmbh & Co. Kg",
    "wof:placetype":"venue"
},
  "geometry": {"coordinates":[8.919129,48.017628],"type":"Point"}
}