{
  "type": "Feature",
  "properties": {
    "iso:country":"DE",
    "sg:address":"Wertheimer Str. 69",
    "sg:city":"Hardheim",
    "sg:phone":"+49 6283/22480",
    "sg:postcode":"74736",
    "sg:province":"Baden-W\u00fcrttemberg",
    "wof:name":"M\u00fchling Und Winkler Steuerberaterb\u00fcro",
    "wof:placetype":"venue"
},
  "geometry": {"coordinates":[9.4721412659,49.6099243164],"type":"Point"}
}