{
  "type": "Feature",
  "properties": {
    "iso:country":"DE",
    "sg:address":"Waldwinkel 25",
    "sg:city":"Altenholz",
    "sg:phone":"+49 431/324200",
    "sg:postcode":"24161",
    "sg:province":"Schleswig-Holstein",
    "wof:name":"Handels- Und Industrie- Vertretungen",
    "wof:placetype":"venue"
},
  "geometry": {"coordinates":[10.1272535324,54.3857269287],"type":"Point"}
}