{
  "type": "Feature",
  "properties": {
    "iso:country":"DE",
    "sg:address":"Gro\u00dfer Sand 65",
    "sg:city":"Uetersen",
    "sg:phone":"+49 4122/2131",
    "sg:postcode":"25436",
    "sg:province":"Schleswig-Holstein",
    "wof:name":"Elektrohaus-franke",
    "wof:placetype":"venue"
},
  "geometry": {"coordinates":[9.6711320877,53.6818771362],"type":"Point"}
}