{
  "type": "Feature",
  "properties": {
    "iso:country":"DE",
    "sg:address":"Grafenberger Allee 365",
    "sg:city":"D\u00fcsseldorf",
    "sg:postcode":"40235",
    "sg:province":"Nordrhein-Westfalen",
    "wof:name":"Institut F\u00fcr Angewandte Psychoanalyse",
    "wof:placetype":"venue"
},
  "geometry": {"coordinates":[6.825217,51.240276],"type":"Point"}
}