{
  "type": "Feature",
  "properties": {
    "iso:country":"DE",
    "sg:address":"Hartwicusstr. 1a",
    "sg:city":"Hamburg",
    "sg:phone":"+49 40/2205006",
    "sg:postcode":"22087",
    "sg:province":"Hamburg",
    "wof:name":"Werbeservice Layout Roy Boldt",
    "wof:placetype":"venue"
},
  "geometry": {"coordinates":[10.0171365738,53.5660552979],"type":"Point"}
}