{
  "type": "Feature",
  "properties": {
    "iso:country":"DE",
    "sg:address":"R\u00f6ttgen 171",
    "sg:city":"Wuppertal",
    "sg:phone":"+49 202/7054424",
    "sg:postcode":"42109",
    "sg:province":"Nordrhein-Westfalen",
    "wof:name":"Evagelos Kalogeopoulos",
    "wof:placetype":"venue"
},
  "geometry": {"coordinates":[7.1562681198,51.2844352722],"type":"Point"}
}