{
  "type": "Feature",
  "properties": {
    "iso:country":"DE",
    "sg:address":"Kasselberger Weg 109",
    "sg:city":"K\u00f6ln",
    "sg:phone":"+49 221/708386",
    "sg:postcode":"50769",
    "sg:province":"Nordrhein-Westfalen",
    "wof:name":"Monika Br\u00fctt Heilpraktikerin",
    "wof:placetype":"venue"
},
  "geometry": {"coordinates":[6.9505519867,51.0354156494],"type":"Point"}
}