{
  "type": "Feature",
  "properties": {
    "iso:country":"DE",
    "sg:address":"Sonnenstr. 1",
    "sg:city":"Bergtheim",
    "sg:phone":"+49 9367/3956",
    "sg:postcode":"97241",
    "sg:province":"Bayern",
    "wof:name":"Berthold G\u00f6b",
    "wof:placetype":"venue"
},
  "geometry": {"coordinates":[10.0706853867,49.8961791992],"type":"Point"}
}