{
  "type": "Feature",
  "properties": {
    "iso:country":"DE",
    "sg:address":"Hauptstr. 54",
    "sg:city":"Langenenslingen",
    "sg:phone":"+49 7376/880",
    "sg:postcode":"88515",
    "sg:province":"Baden-W\u00fcrttemberg",
    "wof:name":"K\u00e4ppeler & Bold",
    "wof:placetype":"venue"
},
  "geometry": {"coordinates":[9.3807563782,48.1483230591],"type":"Point"}
}