{
  "type": "Feature",
  "properties": {
    "iso:country":"DE",
    "sg:address":"Schanzenstr 20",
    "sg:city":"D\u00fcsseldorf",
    "sg:phone":"+49 211/558240",
    "sg:postcode":"40549",
    "sg:province":"Nordrhein-Westfalen",
    "wof:name":"Frey Beaumont-bennett Gmbh",
    "wof:placetype":"venue"
},
  "geometry": {"coordinates":[6.745159,51.231316],"type":"Point"}
}