{
  "type": "Feature",
  "properties": {
    "iso:country":"DE",
    "sg:address":"Karmelitenstr. 13",
    "sg:city":"W\u00fcrzburg",
    "sg:phone":"+49 931/13042",
    "sg:postcode":"97070",
    "sg:province":"Bayern",
    "wof:name":"Wagner Gmbh",
    "wof:placetype":"venue"
},
  "geometry": {"coordinates":[9.9273233414,49.7939071655],"type":"Point"}
}