{
  "type": "Feature",
  "properties": {
    "iso:country":"DE",
    "sg:address":"Jahnstr. 30",
    "sg:city":"Kaiserslautern",
    "sg:phone":"+49 6301/1464",
    "sg:postcode":"67659",
    "sg:province":"Rheinland-Pfalz",
    "wof:name":"Wolfgang Rei\u00df",
    "wof:placetype":"venue"
},
  "geometry": {"coordinates":[7.712761879,49.4781990051],"type":"Point"}
}