{
  "type": "Feature",
  "properties": {
    "iso:country":"DE",
    "sg:address":"Kapellenstr. 11",
    "sg:city":"Ebernhahn",
    "sg:phone":"+49 2623/6341",
    "sg:postcode":"56424",
    "sg:province":"Rheinland-Pfalz",
    "wof:name":"Robert Quernes Bau Gmbh",
    "wof:placetype":"venue"
},
  "geometry": {"coordinates":[7.771244,50.474365],"type":"Point"}
}