{
  "type": "Feature",
  "properties": {
    "iso:country":"DE",
    "sg:address":"Ostfalenweg 3",
    "sg:city":"Rheda-Wiedenbr\u00fcck",
    "sg:phone":"+49 5242/577380",
    "sg:postcode":"33378",
    "sg:province":"Nordrhein-Westfalen",
    "wof:name":"Dieter Kretschmer Planen- Baubetreuung Gmbh",
    "wof:placetype":"venue"
},
  "geometry": {"coordinates":[8.323371,51.845341],"type":"Point"}
}