{
  "type": "Feature",
  "properties": {
    "iso:country":"DE",
    "sg:address":"Am Hasenrain 17",
    "sg:city":"Bad Hersfeld",
    "sg:phone":"+49 6621/72025",
    "sg:postcode":"36251",
    "sg:province":"Hessen",
    "wof:name":"Schaffert-vereinsbedarf Inh. Karl Schaffert",
    "wof:placetype":"venue"
},
  "geometry": {"coordinates":[9.6777067184,50.8940582275],"type":"Point"}
}