{
  "type": "Feature",
  "properties": {
    "iso:country":"DE",
    "sg:address":"Schillerstr. 16",
    "sg:city":"Donaueschingen",
    "sg:phone":"+49 771/13003",
    "sg:postcode":"78166",
    "sg:province":"Baden-W\u00fcrttemberg",
    "wof:name":"Gerhard Krause",
    "wof:placetype":"venue"
},
  "geometry": {"coordinates":[8.5057973862,47.9549560547],"type":"Point"}
}