{
  "type": "Feature",
  "properties": {
    "iso:country":"DE",
    "sg:address":"Fasanenstr. 72",
    "sg:city":"Berlin",
    "sg:phone":"+49 30/8834422",
    "sg:postcode":"10719",
    "sg:province":"Berlin",
    "wof:name":"W. Panka W. Venedey Und D. Kolloge",
    "wof:placetype":"venue"
},
  "geometry": {"coordinates":[13.3275365829,52.5019493103],"type":"Point"}
}