{
  "type": "Feature",
  "properties": {
    "iso:country":"DE",
    "sg:address":"Eberswalder Str. 23",
    "sg:city":"Berlin",
    "sg:phone":"+49 30/4491456",
    "sg:postcode":"10437",
    "sg:province":"Berlin",
    "wof:name":"Harry Eichstadt",
    "wof:placetype":"venue"
},
  "geometry": {"coordinates":[13.411256,52.54097],"type":"Point"}
}