{
  "type": "Feature",
  "properties": {
    "iso:country":"DE",
    "sg:address":"Otto-Lilienthal-Str. 1",
    "sg:city":"Neuenburg",
    "sg:phone":"+49 4976/317030",
    "sg:postcode":"79395",
    "sg:province":"Baden-W\u00fcrttemberg",
    "wof:name":"Schwarzwaldbrot Gmbh",
    "wof:placetype":"venue"
},
  "geometry": {"coordinates":[7.551122,47.80011],"type":"Point"}
}