{
  "type": "Feature",
  "properties": {
    "iso:country":"DE",
    "sg:address":"K\u00f6ttersweg 20",
    "sg:city":"Schwerte",
    "sg:phone":"+49 2304/80390",
    "sg:postcode":"58239",
    "sg:province":"Nordrhein-Westfalen",
    "wof:name":"G\u00fcnter Flasche",
    "wof:placetype":"venue"
},
  "geometry": {"coordinates":[7.5389389992,51.4406356812],"type":"Point"}
}