{
  "type": "Feature",
  "properties": {
    "iso:country":"DE",
    "sg:address":"Moerser Str. 238",
    "sg:city":"Duisburg",
    "sg:phone":"+49 2066/32892",
    "sg:postcode":"47198",
    "sg:province":"Nordrhein-Westfalen",
    "wof:name":"M. Klose",
    "wof:placetype":"venue"
},
  "geometry": {"coordinates":[6.684979,51.449787],"type":"Point"}
}