{
  "type": "Feature",
  "properties": {
    "iso:country":"DE",
    "sg:address":"Hermeskeiler Str. 2",
    "sg:city":"K\u00f6ln",
    "sg:phone":"+49 221/413807",
    "sg:postcode":"50935",
    "sg:province":"Nordrhein-Westfalen",
    "wof:name":"Hofmann Inh. H. Mielke",
    "wof:placetype":"venue"
},
  "geometry": {"coordinates":[6.9100117683,50.9193687439],"type":"Point"}
}