{
  "type": "Feature",
  "properties": {
    "iso:country":"DE",
    "sg:address":"Steiggasse 1",
    "sg:city":"Oberschwarzach",
    "sg:phone":"+49 9382/7925",
    "sg:postcode":"97516",
    "sg:province":"Bayern",
    "wof:name":"Schwab Bausanierung Gmbh",
    "wof:placetype":"venue"
},
  "geometry": {"coordinates":[10.411740303,49.8584632874],"type":"Point"}
}