{
  "type": "Feature",
  "properties": {
    "iso:country":"DE",
    "sg:address":"Schelpmilser Weg 18",
    "sg:city":"Bielefeld",
    "sg:phone":"+49 6196/6592330",
    "sg:postcode":"33609",
    "sg:province":"Nordrhein-Westfalen",
    "wof:name":"Redline Messe Service Gmbh",
    "wof:placetype":"venue"
},
  "geometry": {"coordinates":[8.4967498779,50.1348686218],"type":"Point"}
}