{
  "type": "Feature",
  "properties": {
    "iso:country":"DE",
    "sg:address":"Kybitzstr. 20",
    "sg:city":"Helmstedt",
    "sg:phone":"+49 5351/41092",
    "sg:postcode":"38350",
    "sg:province":"Niedersachsen",
    "wof:name":"China-restaurant Chu-feng",
    "wof:placetype":"venue"
},
  "geometry": {"coordinates":[11.0106725693,52.2294197083],"type":"Point"}
}