{
  "type": "Feature",
  "properties": {
    "iso:country":"DE",
    "sg:city":"Gro\u00dfbarkau",
    "sg:phone":"+49 4302/9333",
    "sg:postcode":"24245",
    "sg:province":"Schleswig-Holstein",
    "wof:name":"H. Jacobsen Architektin",
    "wof:placetype":"venue"
},
  "geometry": {"coordinates":[10.171006,54.226315],"type":"Point"}
}