{
  "type": "Feature",
  "properties": {
    "iso:country":"DE",
    "sg:address":"Gau-Odernheimer-Str. 38",
    "sg:city":"Alzey",
    "sg:phone":"+49 6731/7186",
    "sg:postcode":"55232",
    "sg:province":"Rheinland-Pfalz",
    "wof:name":"Wolfgang Schuckmann",
    "wof:placetype":"venue"
},
  "geometry": {"coordinates":[8.1527061462,49.7580108643],"type":"Point"}
}