{
  "type": "Feature",
  "properties": {
    "iso:country":"DE",
    "sg:address":"S\u00fcdring 8",
    "sg:city":"Mudau",
    "sg:phone":"+49 6284/211",
    "sg:postcode":"69427",
    "sg:province":"Baden-W\u00fcrttemberg",
    "wof:name":"Veith & Pasour Verwaltungs-gmbh",
    "wof:placetype":"venue"
},
  "geometry": {"coordinates":[9.2007112503,49.5286636353],"type":"Point"}
}