{
  "type": "Feature",
  "properties": {
    "iso:country":"DE",
    "sg:address":"Greitweg 9",
    "sg:city":"G\u00f6ttingen",
    "sg:phone":"+49 551/93830",
    "sg:postcode":"37081",
    "sg:province":"Niedersachsen",
    "wof:name":"Italia",
    "wof:placetype":"venue"
},
  "geometry": {"coordinates":[9.8981409073,51.5366287231],"type":"Point"}
}