{
  "type": "Feature",
  "properties": {
    "iso:country":"DE",
    "sg:address":"Deependahl 1",
    "sg:city":"Stelle",
    "sg:phone":"+49 4174/2344",
    "sg:postcode":"21435",
    "sg:province":"Niedersachsen",
    "wof:name":"H.-h. Henk",
    "wof:placetype":"venue"
},
  "geometry": {"coordinates":[10.102792,53.385216],"type":"Point"}
}