{
  "type": "Feature",
  "properties": {
    "iso:country":"DE",
    "sg:address":"Burgkirchener Str. 143",
    "sg:city":"Burghausen",
    "sg:postcode":"84489",
    "sg:province":"Bayern",
    "wof:name":"Rtk Ticket Plus Reiseservice Gmbh",
    "wof:placetype":"venue"
},
  "geometry": {"coordinates":[12.805729866,48.1637229919],"type":"Point"}
}