{
  "type": "Feature",
  "properties": {
    "iso:country":"DE",
    "sg:address":"Bahnhofstr. 22",
    "sg:city":"Obergurig",
    "sg:phone":"+49 3591/480028",
    "sg:postcode":"02692",
    "sg:province":"Sachsen",
    "wof:name":"H.-j. Milot",
    "wof:placetype":"venue"
},
  "geometry": {"coordinates":[14.4074316025,51.1386222839],"type":"Point"}
}