{
  "type": "Feature",
  "properties": {
    "iso:country":"DE",
    "sg:address":"Kurzackerstr. 4",
    "sg:city":"P\u00f6\u00dfneck",
    "sg:phone":"+49 3647/411630",
    "sg:postcode":"07381",
    "sg:province":"Th\u00fcringen",
    "wof:name":"Freund Kreatives In Fliesen Gmbh",
    "wof:placetype":"venue"
},
  "geometry": {"coordinates":[11.6147470474,50.7007484436],"type":"Point"}
}