{
  "type": "Feature",
  "properties": {
    "iso:country":"DE",
    "sg:address":"Uhlandstr. 39",
    "sg:city":"Berlin",
    "sg:phone":"+49 30/4773923",
    "sg:postcode":"13156",
    "sg:province":"Berlin",
    "wof:name":"Manfred Schwarz",
    "wof:placetype":"venue"
},
  "geometry": {"coordinates":[13.388724,52.585892],"type":"Point"}
}