{
  "type": "Feature",
  "properties": {
    "iso:country":"DE",
    "sg:address":"Friedenstr. 1",
    "sg:city":"Neuenkirchen-V\u00f6rden",
    "sg:phone":"+49 5493/422",
    "sg:postcode":"49434",
    "sg:province":"Niedersachsen",
    "wof:name":"Reitsport Hugenberg",
    "wof:placetype":"venue"
},
  "geometry": {"coordinates":[8.0652551651,52.511100769],"type":"Point"}
}