{
  "type": "Feature",
  "properties": {
    "iso:country":"DE",
    "sg:address":"Sportplatzweg 16",
    "sg:city":"Bad Sachsa",
    "sg:postcode":"37441",
    "sg:province":"Niedersachsen",
    "wof:name":"H & E Projekt Entwicklung Gmbh",
    "wof:placetype":"venue"
},
  "geometry": {"coordinates":[10.5695428848,51.5936508179],"type":"Point"}
}