{
  "type": "Feature",
  "properties": {
    "iso:country":"DE",
    "sg:address":"Stromeyerstr. 2",
    "sg:city":"Hannover",
    "sg:phone":"+49 511/622830",
    "sg:postcode":"30163",
    "sg:province":"Niedersachsen",
    "wof:name":"Herbert K\u00f6nig Architekt",
    "wof:placetype":"venue"
},
  "geometry": {"coordinates":[9.746852,52.391415],"type":"Point"}
}