{
  "type": "Feature",
  "properties": {
    "iso:country":"DE",
    "sg:address":"Querweg 9 a",
    "sg:city":"Winsen",
    "sg:phone":"+49 4171/3388",
    "sg:postcode":"21423",
    "sg:province":"Niedersachsen",
    "wof:name":"Maas S\u00f6hne Bau Und Verkauf Gmbh",
    "wof:placetype":"venue"
},
  "geometry": {"coordinates":[10.193422,53.384895],"type":"Point"}
}