{
  "type": "Feature",
  "properties": {
    "iso:country":"DE",
    "sg:address":"R\u00fcggeberger Str. 26c",
    "sg:city":"Ennepetal",
    "sg:phone":"+49 2333/74460",
    "sg:postcode":"58256",
    "sg:province":"Nordrhein-Westfalen",
    "wof:name":"Klaus Christ",
    "wof:placetype":"venue"
},
  "geometry": {"coordinates":[7.352471,51.29089],"type":"Point"}
}