{
  "type": "Feature",
  "properties": {
    "iso:country":"DE",
    "sg:address":"Schraudolphstr. 15",
    "sg:city":"M\u00fcnchen",
    "sg:phone":"+49 89/2723437",
    "sg:postcode":"80799",
    "sg:province":"Bayern",
    "wof:name":"Margot Wei\u00df",
    "wof:placetype":"venue"
},
  "geometry": {"coordinates":[11.5728158951,48.153175354],"type":"Point"}
}