{
  "type": "Feature",
  "properties": {
    "iso:country":"DE",
    "sg:address":"Schrannenplatz 6",
    "sg:city":"Erding",
    "sg:phone":"+49 8122/3844",
    "sg:postcode":"85435",
    "sg:province":"Bayern",
    "wof:name":"Frieda Ortner",
    "wof:placetype":"venue"
},
  "geometry": {"coordinates":[11.907328,48.30616],"type":"Point"}
}