{
  "type": "Feature",
  "properties": {
    "iso:country":"DE",
    "sg:address":"Gildehauser Str. 184",
    "sg:city":"Gronau",
    "sg:phone":"+49 2562/80999",
    "sg:postcode":"48599",
    "sg:province":"Nordrhein-Westfalen",
    "wof:name":"M. Klar",
    "wof:placetype":"venue"
},
  "geometry": {"coordinates":[7.0461821556,52.2242660522],"type":"Point"}
}