{
  "type": "Feature",
  "properties": {
    "iso:country":"DE",
    "sg:address":"Dresdener Ring 15",
    "sg:city":"Nidderau",
    "sg:phone":"+49 6187/23420",
    "sg:postcode":"61130",
    "sg:province":"Hessen",
    "wof:name":"Rudi U. Elke Leibold",
    "wof:placetype":"venue"
},
  "geometry": {"coordinates":[8.8881969452,50.2227172852],"type":"Point"}
}