{
  "type": "Feature",
  "properties": {
    "iso:country":"DE",
    "sg:address":"Ringstr. 4",
    "sg:city":"Elsenfeld",
    "sg:phone":"+49 4960/22471",
    "sg:postcode":"63820",
    "sg:province":"Bayern",
    "wof:name":"Raiffeisenbank Unteres Elsavatal Eg",
    "wof:placetype":"venue"
},
  "geometry": {"coordinates":[9.236103,49.848591],"type":"Point"}
}