{
  "type": "Feature",
  "properties": {
    "iso:country":"DE",
    "sg:address":"An der Blutfinke 30",
    "sg:city":"Wuppertal",
    "sg:phone":"+49 202/461777",
    "sg:postcode":"42369",
    "sg:province":"Nordrhein-Westfalen",
    "wof:name":"Hans P\u00f6hler",
    "wof:placetype":"venue"
},
  "geometry": {"coordinates":[7.1914901733,51.2212295532],"type":"Point"}
}