{
  "type": "Feature",
  "properties": {
    "iso:country":"DE",
    "sg:address":"Buchbergstr. 37",
    "sg:city":"Blumberg",
    "sg:phone":"+49 7702/3246",
    "sg:postcode":"78176",
    "sg:province":"Baden-W\u00fcrttemberg",
    "wof:name":"Profast Walter Kopisch",
    "wof:placetype":"venue"
},
  "geometry": {"coordinates":[8.5247192383,47.8364334106],"type":"Point"}
}