{
  "type": "Feature",
  "properties": {
    "iso:country":"DE",
    "sg:address":"Dansenberg 18",
    "sg:city":"Diemelsee",
    "sg:phone":"+49 5633/862",
    "sg:postcode":"34519",
    "sg:province":"Hessen",
    "wof:name":"Hans-gerd Schreiber Gmbh",
    "wof:placetype":"venue"
},
  "geometry": {"coordinates":[8.810669,51.363838],"type":"Point"}
}