{
  "type": "Feature",
  "properties": {
    "iso:country":"DE",
    "sg:address":"Hauptstr. 30",
    "sg:city":"Goppeln",
    "sg:phone":"+49 351/2881601",
    "sg:postcode":"01728",
    "sg:province":"Sachsen",
    "wof:name":"Klaus Nobis",
    "wof:placetype":"venue"
},
  "geometry": {"coordinates":[13.716841,50.993298],"type":"Point"}
}