{
  "type": "Feature",
  "properties": {
    "iso:country":"DE",
    "sg:address":"Thal",
    "sg:city":"Halblech",
    "sg:postcode":"87642",
    "sg:province":"Bayern",
    "wof:name":"Trauchgau Pappen Gmbh",
    "wof:placetype":"venue"
},
  "geometry": {"coordinates":[10.7798557281,47.6459007263],"type":"Point"}
}