{
  "type": "Feature",
  "properties": {
    "iso:country":"DE",
    "sg:address":"Hindenburgstr. 40",
    "sg:city":"Hannover",
    "sg:postcode":"30175",
    "sg:province":"Niedersachsen",
    "wof:name":"A. Tietgen Rechtsanwalt",
    "wof:placetype":"venue"
},
  "geometry": {"coordinates":[9.763712883,52.3804588318],"type":"Point"}
}