{
  "type": "Feature",
  "properties": {
    "iso:country":"DE",
    "sg:address":"Saseler Chaussee 128",
    "sg:city":"Hamburg",
    "sg:postcode":"22393",
    "sg:province":"Hamburg",
    "wof:name":"Beteiligungsgesellschaft Ke\u00dfler & Leptien Mbh",
    "wof:placetype":"venue"
},
  "geometry": {"coordinates":[10.102571,53.647541],"type":"Point"}
}