{
  "type": "Feature",
  "properties": {
    "iso:country":"DE",
    "sg:address":"Ackerstr. 11a",
    "sg:city":"Quierschied",
    "sg:phone":"+49 6897/65252",
    "sg:postcode":"66287",
    "sg:province":"Saarland",
    "wof:name":"Gertrud Kirsch",
    "wof:placetype":"venue"
},
  "geometry": {"coordinates":[7.0569519997,49.3353614807],"type":"Point"}
}