{
  "type": "Feature",
  "properties": {
    "iso:country":"DE",
    "sg:address":"Elbeallee 66",
    "sg:city":"Bielefeld",
    "sg:phone":"+49 5205/22577",
    "sg:postcode":"33689",
    "sg:province":"Nordrhein-Westfalen",
    "wof:name":"Klemens L\u00fckewille",
    "wof:placetype":"venue"
},
  "geometry": {"coordinates":[8.5872325897,51.9466285706],"type":"Point"}
}