{
  "type": "Feature",
  "properties": {
    "iso:country":"DE",
    "sg:address":"Wilhelmstr. 35",
    "sg:city":"G\u00fctersloh",
    "sg:phone":"+49 5241/40747",
    "sg:postcode":"33332",
    "sg:province":"Nordrhein-Westfalen",
    "wof:name":"Heinrich R\u00f6hr",
    "wof:placetype":"venue"
},
  "geometry": {"coordinates":[8.396273,51.881878],"type":"Point"}
}