{
  "type": "Feature",
  "properties": {
    "iso:country":"DE",
    "sg:address":"August-Bebel-Platz 19",
    "sg:city":"Bochum",
    "sg:phone":"+49 2327/88330",
    "sg:postcode":"44866",
    "sg:province":"Nordrhein-Westfalen",
    "wof:name":"Landesbausparkasse Beratungsstelle",
    "wof:placetype":"venue"
},
  "geometry": {"coordinates":[7.138724,51.481632],"type":"Point"}
}