{
  "type": "Feature",
  "properties": {
    "iso:country":"DE",
    "sg:address":"Anhalterstra\u00dfe 34",
    "sg:city":"Z\u00f6rbig",
    "sg:phone":"+49 34956",
    "sg:postcode":"06780",
    "sg:province":"Sachsen-Anhalt",
    "wof:name":"Fahrschule Frank Beer",
    "wof:placetype":"venue"
},
  "geometry": {"coordinates":[12.1095504761,51.6328010559],"type":"Point"}
}