{
  "type": "Feature",
  "properties": {
    "iso:country":"DE",
    "sg:address":"Stuttgarter Str. 45",
    "sg:city":"Ebersbach",
    "sg:phone":"+49 7163/8785",
    "sg:postcode":"73061",
    "sg:province":"Baden-W\u00fcrttemberg",
    "wof:name":"Willi H\u00f6fer",
    "wof:placetype":"venue"
},
  "geometry": {"coordinates":[9.5182247162,48.7141456604],"type":"Point"}
}