{
  "type": "Feature",
  "properties": {
    "iso:country":"DE",
    "sg:address":"Lebiener Str. 33 A",
    "sg:city":"Plossig",
    "sg:phone":"+49 35386/22530",
    "sg:postcode":"06922",
    "sg:province":"Sachsen-Anhalt",
    "wof:name":"Daniel Transporte Gmbh Spedition",
    "wof:placetype":"venue"
},
  "geometry": {"coordinates":[12.9245996475,51.6850318909],"type":"Point"}
}