{
  "type": "Feature",
  "properties": {
    "iso:country":"DE",
    "sg:address":"Mittelstr. 9",
    "sg:city":"Peitz",
    "sg:postcode":"03185",
    "sg:province":"Brandenburg",
    "wof:name":"Ev. Kirche",
    "wof:placetype":"venue"
},
  "geometry": {"coordinates":[14.4125452042,51.8574142456],"type":"Point"}
}