{
  "type": "Feature",
  "properties": {
    "iso:country":"DE",
    "sg:address":"Liliencronstr. 130",
    "sg:city":"Hamburg",
    "sg:phone":"+49 40/673770",
    "sg:postcode":"22149",
    "sg:province":"Hamburg",
    "wof:name":"Katholisches Kinderkrankenhaus Wilhelmstift",
    "wof:placetype":"venue"
},
  "geometry": {"coordinates":[10.1631526947,53.5890693665],"type":"Point"}
}