{
  "type": "Feature",
  "properties": {
    "iso:country":"DE",
    "sg:address":"Blumenstr. 26",
    "sg:city":"Celle",
    "sg:phone":"+49 5141/881442",
    "sg:postcode":"29227",
    "sg:province":"Niedersachsen",
    "wof:name":"J. Freitag",
    "wof:placetype":"venue"
},
  "geometry": {"coordinates":[10.0802717209,52.6069602966],"type":"Point"}
}