{
  "type": "Feature",
  "properties": {
    "iso:country":"DE",
    "sg:address":"Wiedelaher Str. 1",
    "sg:city":"Vienenburg",
    "sg:phone":"+49 5324/3331",
    "sg:postcode":"38690",
    "sg:province":"Niedersachsen",
    "wof:name":"Eis Ilsemann",
    "wof:placetype":"venue"
},
  "geometry": {"coordinates":[10.56426,51.954094],"type":"Point"}
}