{
  "type": "Feature",
  "properties": {
    "iso:country":"DE",
    "sg:address":"Kirchbachstr. 95",
    "sg:city":"Bremen",
    "sg:phone":"+49 421/4988880",
    "sg:postcode":"28211",
    "sg:province":"Bremen",
    "wof:name":"Riethm\u00f6ller Ziegler Und Kauert",
    "wof:placetype":"venue"
},
  "geometry": {"coordinates":[8.855104,53.078148],"type":"Point"}
}