{
  "type": "Feature",
  "properties": {
    "iso:country":"DE",
    "sg:address":"Meu\u00dfelsdorfer Str. 31",
    "sg:city":"Marktredwitz",
    "sg:phone":"+49 9231/8557",
    "sg:postcode":"95615",
    "sg:province":"Bayern",
    "wof:name":"Elektro Nickl",
    "wof:placetype":"venue"
},
  "geometry": {"coordinates":[12.066155,49.998566],"type":"Point"}
}