{
  "type": "Feature",
  "properties": {
    "iso:country":"DE",
    "sg:address":"Hochstr. 24",
    "sg:city":"Theisseil",
    "sg:phone":"+49 961/43297",
    "sg:postcode":"92637",
    "sg:province":"Bayern",
    "wof:name":"Veronika Schubert",
    "wof:placetype":"venue"
},
  "geometry": {"coordinates":[12.2369203568,49.6751289368],"type":"Point"}
}