{
  "type": "Feature",
  "properties": {
    "iso:country":"DE",
    "sg:address":"Amisiastr. 10",
    "sg:city":"Haren",
    "sg:phone":"+49 5932/4453",
    "sg:postcode":"49733",
    "sg:province":"Niedersachsen",
    "wof:name":"Zenit Schiffahrts- Gesellschaft Mbh",
    "wof:placetype":"venue"
},
  "geometry": {"coordinates":[7.2463431358,52.7955093384],"type":"Point"}
}