{
  "type": "Feature",
  "properties": {
    "iso:country":"DE",
    "sg:address":"Lister Kirchweg 87",
    "sg:city":"Hannover",
    "sg:phone":"+49 4951/162620",
    "sg:postcode":"30177",
    "sg:province":"Niedersachsen",
    "wof:name":"Bmw Ag",
    "wof:placetype":"venue"
},
  "geometry": {"coordinates":[9.7584028244,52.3961372375],"type":"Point"}
}