{
  "type": "Feature",
  "properties": {
    "iso:country":"DE",
    "sg:address":"Salzstr. 7",
    "sg:city":"Mindelheim",
    "sg:postcode":"87719",
    "sg:province":"Bayern",
    "wof:name":"Katholisches Pfarramt St. Mauritius",
    "wof:placetype":"venue"
},
  "geometry": {"coordinates":[10.4529132843,48.0436248779],"type":"Point"}
}