{
  "type": "Feature",
  "properties": {
    "iso:country":"DE",
    "sg:address":"Ziegelbergweg 31",
    "sg:city":"F\u00fcssen",
    "sg:phone":"+49 8362/6244",
    "sg:postcode":"87629",
    "sg:province":"Bayern",
    "wof:name":"Bambis Delta Technik",
    "wof:placetype":"venue"
},
  "geometry": {"coordinates":[10.6983118057,47.5750007629],"type":"Point"}
}