{
  "type": "Feature",
  "properties": {
    "iso:country":"DE",
    "sg:address":"Rheinmetallstr. 18",
    "sg:city":"S\u00f6mmerda",
    "sg:phone":"+49 3634/603800",
    "sg:postcode":"99610",
    "sg:province":"Th\u00fcringen",
    "wof:name":"Gut Tierproduktion Gmbh",
    "wof:placetype":"venue"
},
  "geometry": {"coordinates":[11.118141,51.169315],"type":"Point"}
}