{
  "type": "Feature",
  "properties": {
    "iso:country":"DE",
    "sg:address":"Filbensteige 1",
    "sg:city":"Zweiflingen",
    "sg:postcode":"74639",
    "sg:province":"Baden-W\u00fcrttemberg",
    "wof:name":"Otto Giebler",
    "wof:placetype":"venue"
},
  "geometry": {"coordinates":[9.54158,49.249481],"type":"Point"}
}