{
  "type": "Feature",
  "properties": {
    "iso:country":"DE",
    "sg:address":"Tarodunumweg 65",
    "sg:city":"Kirchzarten",
    "sg:phone":"+49 7661/99491",
    "sg:postcode":"79199",
    "sg:province":"Baden-W\u00fcrttemberg",
    "wof:name":"Albis \u00c4rztecomputer Gmbh",
    "wof:placetype":"venue"
},
  "geometry": {"coordinates":[7.981637,47.96497],"type":"Point"}
}