{
  "type": "Feature",
  "properties": {
    "iso:country":"DE",
    "sg:address":"Str\u00fcmpfelbrunner Str. 15",
    "sg:city":"Waldbrunn",
    "sg:phone":"+49 6274/206",
    "sg:postcode":"69429",
    "sg:province":"Baden-W\u00fcrttemberg",
    "wof:name":"Willi Sch\u00f6lch",
    "wof:placetype":"venue"
},
  "geometry": {"coordinates":[9.059472084,49.465473175],"type":"Point"}
}