{
  "type": "Feature",
  "properties": {
    "iso:country":"DE",
    "sg:address":"Torstr. 5 a",
    "sg:city":"K\u00f6nigswinter",
    "sg:phone":"+49 2244/81931",
    "sg:postcode":"53639",
    "sg:province":"Nordrhein-Westfalen",
    "wof:name":"Adelbert Ay Kg",
    "wof:placetype":"venue"
},
  "geometry": {"coordinates":[7.235861,50.693932],"type":"Point"}
}