{
  "type": "Feature",
  "properties": {
    "iso:country":"DE",
    "sg:address":"Karlsbader Ring 8",
    "sg:city":"Br\u00fchl",
    "sg:phone":"+49 6202/75348",
    "sg:postcode":"68782",
    "sg:province":"Baden-W\u00fcrttemberg",
    "wof:name":"Walther Immobilienmakler",
    "wof:placetype":"venue"
},
  "geometry": {"coordinates":[8.5328655243,49.4027671814],"type":"Point"}
}