{
  "type": "Feature",
  "properties": {
    "iso:country":"DE",
    "sg:address":"Ehlinger Str. 62",
    "sg:city":"Bad Neuenahr-Ahrweiler",
    "sg:phone":"+49 2641/25324",
    "sg:postcode":"53474",
    "sg:province":"Rheinland-Pfalz",
    "wof:name":"Gottfried H\u00fcrter",
    "wof:placetype":"venue"
},
  "geometry": {"coordinates":[7.1846499443,50.5423469543],"type":"Point"}
}