{
  "type": "Feature",
  "properties": {
    "iso:country":"DE",
    "sg:address":"Rathausplatz 1",
    "sg:city":"Reit im Winkl",
    "sg:postcode":"83242",
    "sg:province":"Bayern",
    "wof:name":"Naturw\u00e4rme Reit Im Winkl Verwaltungs Gmbh",
    "wof:placetype":"venue"
},
  "geometry": {"coordinates":[12.4699707031,47.6774177551],"type":"Point"}
}