{
  "type": "Feature",
  "properties": {
    "iso:country":"DE",
    "sg:address":"B\u00e4rnwinkel 10 a",
    "sg:city":"Trabitz",
    "sg:phone":"+49 9644/92000",
    "sg:postcode":"92724",
    "sg:province":"Bayern",
    "wof:name":"Werner Ke\u00dfl Gie\u00dfereibedarf Gmbh",
    "wof:placetype":"venue"
},
  "geometry": {"coordinates":[11.89704,49.750233],"type":"Point"}
}