{
  "type": "Feature",
  "properties": {
    "iso:country":"DE",
    "sg:address":"Leipziger Str. 11",
    "sg:city":"Michelstadt",
    "sg:phone":"+49 6061/3265",
    "sg:postcode":"64720",
    "sg:province":"Hessen",
    "wof:name":"Inge John",
    "wof:placetype":"venue"
},
  "geometry": {"coordinates":[9.012805,49.676868],"type":"Point"}
}