{
  "type": "Feature",
  "properties": {
    "iso:country":"DE",
    "sg:address":"Fuhrenstieg 3",
    "sg:city":"Celle",
    "sg:phone":"+49 5141/52252",
    "sg:postcode":"29223",
    "sg:province":"Niedersachsen",
    "wof:name":"S\u00f6ren Garner",
    "wof:placetype":"venue"
},
  "geometry": {"coordinates":[10.023396,52.640633],"type":"Point"}
}