{
  "type": "Feature",
  "properties": {
    "iso:country":"DE",
    "sg:address":"Neunkirchener Str.",
    "sg:city":"Weiden",
    "sg:phone":"+49 961/61904",
    "sg:postcode":"92637",
    "sg:province":"Bayern",
    "wof:name":"Pizzeria-restaurant Kummerthof",
    "wof:placetype":"venue"
},
  "geometry": {"coordinates":[12.1057510376,49.6673355103],"type":"Point"}
}