{
  "type": "Feature",
  "properties": {
    "iso:country":"DE",
    "sg:address":"Gr\u00f6pelinger Heerstr. 196",
    "sg:city":"Bremen",
    "sg:phone":"+49 421/6918001",
    "sg:postcode":"28237",
    "sg:province":"Bremen",
    "wof:name":"Handy World Oemer Serin",
    "wof:placetype":"venue"
},
  "geometry": {"coordinates":[8.7589693069,53.1158752441],"type":"Point"}
}