{
  "type": "Feature",
  "properties": {
    "iso:country":"DE",
    "sg:address":"Bauhofstr. 10",
    "sg:city":"Schwaig",
    "sg:phone":"+49 911/500035",
    "sg:postcode":"90571",
    "sg:province":"Bayern",
    "wof:name":"Unix - Rent Autovermietung Und Logistik Gmbh",
    "wof:placetype":"venue"
},
  "geometry": {"coordinates":[11.205396,49.46629],"type":"Point"}
}