{
  "type": "Feature",
  "properties": {
    "iso:country":"DE",
    "sg:address":"Am Kleinbahnhofe 58",
    "sg:city":"Rheine",
    "sg:phone":"+49 5971/70048",
    "sg:postcode":"48429",
    "sg:province":"Nordrhein-Westfalen",
    "wof:name":"I. Hilgenberg",
    "wof:placetype":"venue"
},
  "geometry": {"coordinates":[7.4512319565,52.2868232727],"type":"Point"}
}