{
  "type": "Feature",
  "properties": {
    "iso:country":"DE",
    "sg:address":"Siempelkampstr. 75 POSTFACH 101964",
    "sg:city":"Krefeld",
    "sg:phone":"+49 4921/519230",
    "sg:postcode":"47719",
    "sg:province":"Nordrhein-Westfalen",
    "wof:name":"G. Siempelkamp Ges. F\u00dcr Maschinen Und Anlagenbau Mbh",
    "wof:placetype":"venue"
},
  "geometry": {"coordinates":[6.5289049149,51.3504219055],"type":"Point"}
}