{
  "type": "Feature",
  "properties": {
    "iso:country":"DE",
    "sg:address":"Lobker Str. 9",
    "sg:city":"Sehnde",
    "sg:phone":"+49 5138/2500",
    "sg:postcode":"31319",
    "sg:province":"Niedersachsen",
    "wof:name":"Alten- Und Pflegeheim Klein Lobke",
    "wof:placetype":"venue"
},
  "geometry": {"coordinates":[10.014594,52.286114],"type":"Point"}
}