{
  "type": "Feature",
  "properties": {
    "iso:country":"DE",
    "sg:address":"Zavelsteinstr 2",
    "sg:city":"M\u00fcnchen",
    "sg:phone":"+49 89/7932348",
    "sg:postcode":"81375",
    "sg:province":"Bayern",
    "wof:name":"Westermayer Und Reiske Gmbh",
    "wof:placetype":"venue"
},
  "geometry": {"coordinates":[11.485025,48.115311],"type":"Point"}
}