{
  "type": "Feature",
  "properties": {
    "iso:country":"DE",
    "sg:address":"Keplerstr. 5",
    "sg:city":"Unterschlei\u00dfheim",
    "sg:postcode":"85716",
    "sg:province":"Bayern",
    "wof:name":"Xylan Gmbh",
    "wof:placetype":"venue"
},
  "geometry": {"coordinates":[11.570443,48.280853],"type":"Point"}
}