{
  "type": "Feature",
  "properties": {
    "iso:country":"DE",
    "sg:address":"Siemensstr. 5",
    "sg:city":"Miltenberg",
    "sg:phone":"+49 9371/68494",
    "sg:postcode":"63897",
    "sg:province":"Bayern",
    "wof:name":"Felix Bauer Gmbh",
    "wof:placetype":"venue"
},
  "geometry": {"coordinates":[9.2442798615,49.7098617554],"type":"Point"}
}