{
  "type": "Feature",
  "properties": {
    "iso:country":"DE",
    "sg:address":"Hauptstr. 22",
    "sg:city":"Kirkel",
    "sg:phone":"+49 6841/80250",
    "sg:postcode":"66459",
    "sg:province":"Saarland",
    "wof:name":"Wilhelm Daniel",
    "wof:placetype":"venue"
},
  "geometry": {"coordinates":[7.276503,49.316978],"type":"Point"}
}