{
  "type": "Feature",
  "properties": {
    "iso:country":"DE",
    "sg:address":"Fischerhausstr. 20",
    "sg:city":"Bad Schussenried",
    "sg:phone":"+49 7583/91103",
    "sg:postcode":"88427",
    "sg:province":"Baden-W\u00fcrttemberg",
    "wof:name":"Pc-tecno Gmbh",
    "wof:placetype":"venue"
},
  "geometry": {"coordinates":[9.6532392502,48.0067901611],"type":"Point"}
}