{
  "type": "Feature",
  "properties": {
    "iso:country":"DE",
    "sg:address":"Hubertusstr. 1 a",
    "sg:city":"M\u00fcnchen",
    "sg:phone":"+49 89/176270",
    "sg:postcode":"80639",
    "sg:province":"Bayern",
    "wof:name":"Christoph F. Loheyde Architekt",
    "wof:placetype":"venue"
},
  "geometry": {"coordinates":[11.519883,48.153812],"type":"Point"}
}