{
  "type": "Feature",
  "properties": {
    "iso:country":"DE",
    "sg:address":"Niederwiesenstr. 3",
    "sg:city":"Villingen-Schwenningen",
    "sg:phone":"+49 7721/30469",
    "sg:postcode":"78050",
    "sg:province":"Baden-W\u00fcrttemberg",
    "wof:name":"Rudolf H\u00e4ssler Gmbh",
    "wof:placetype":"venue"
},
  "geometry": {"coordinates":[8.461425,48.051128],"type":"Point"}
}