{
  "type": "Feature",
  "properties": {
    "iso:country":"DE",
    "sg:address":"Langer Rehm 29",
    "sg:city":"Heikendorf",
    "sg:phone":"+49 431/243909",
    "sg:postcode":"24226",
    "sg:province":"Schleswig-Holstein",
    "wof:name":"Christiane Krapp",
    "wof:placetype":"venue"
},
  "geometry": {"coordinates":[10.2041692734,54.3738441467],"type":"Point"}
}