{
  "type": "Feature",
  "properties": {
    "iso:country":"DE",
    "sg:address":"Hauptstr. 40",
    "sg:city":"Haltern",
    "sg:phone":"+49 2364/2535",
    "sg:postcode":"45721",
    "sg:province":"Nordrhein-Westfalen",
    "wof:name":"Gastst\u00e4tte H. Gienau",
    "wof:placetype":"venue"
},
  "geometry": {"coordinates":[7.2881717682,51.7365188599],"type":"Point"}
}