{
  "type": "Feature",
  "properties": {
    "iso:country":"DE",
    "sg:address":"Volkshausstr.",
    "sg:city":"Zw\u00f6nitz",
    "sg:phone":"+49 37296/3312",
    "sg:postcode":"08297",
    "sg:province":"Sachsen",
    "wof:name":"Freibad",
    "wof:placetype":"venue"
},
  "geometry": {"coordinates":[12.8165750504,50.6875534058],"type":"Point"}
}