{
  "type": "Feature",
  "properties": {
    "iso:country":"DE",
    "sg:address":"Ferdinand-Porsche-Str. 3",
    "sg:city":"Denzlingen",
    "sg:phone":"+49 7666/2570",
    "sg:postcode":"79211",
    "sg:province":"Baden-W\u00fcrttemberg",
    "wof:name":"Helmut Huehne",
    "wof:placetype":"venue"
},
  "geometry": {"coordinates":[7.881858,48.074547],"type":"Point"}
}