{
  "type": "Feature",
  "properties": {
    "iso:country":"DE",
    "sg:address":"Grevener Str. 392",
    "sg:city":"M\u00fcnster",
    "sg:phone":"+49 251/211305",
    "sg:postcode":"48159",
    "sg:province":"Nordrhein-Westfalen",
    "wof:name":"Alfred Sieweke",
    "wof:placetype":"venue"
},
  "geometry": {"coordinates":[7.6123299599,51.9923782349],"type":"Point"}
}