{
  "type": "Feature",
  "properties": {
    "iso:country":"DE",
    "sg:address":"Fuhlsb\u00fcttler Str. 731",
    "sg:city":"Hamburg",
    "sg:phone":"+49 40/5002020",
    "sg:postcode":"22337",
    "sg:province":"Hamburg",
    "wof:name":"Valentin Beeken",
    "wof:placetype":"venue"
},
  "geometry": {"coordinates":[10.033941,53.618767],"type":"Point"}
}