{
  "type": "Feature",
  "properties": {
    "iso:country":"DE",
    "sg:address":"Nibelungenstr. 14",
    "sg:city":"M\u00fcnchen",
    "sg:phone":"+49 89/165426",
    "sg:postcode":"80639",
    "sg:province":"Bayern",
    "wof:name":"C\u00e4cilie E. Halbleib",
    "wof:placetype":"venue"
},
  "geometry": {"coordinates":[11.52877,48.153324],"type":"Point"}
}