{
  "type": "Feature",
  "properties": {
    "iso:country":"DE",
    "sg:address":"Mainzer Str. 40",
    "sg:city":"L\u00f6rzweiler",
    "sg:phone":"+49 6138/980490",
    "sg:postcode":"55296",
    "sg:province":"Rheinland-Pfalz",
    "wof:name":"Feengrotten-confiserie",
    "wof:placetype":"venue"
},
  "geometry": {"coordinates":[8.29095,49.899914],"type":"Point"}
}