{
  "type": "Feature",
  "properties": {
    "iso:country":"DE",
    "sg:address":"helene-mayer-ring 7",
    "sg:city":"m\u00fcnchen",
    "sg:phone":"+49 89/35709059",
    "sg:postcode":"80809",
    "sg:province":"Bayern",
    "wof:name":"Getstoked-adrenalin Aus Dem Netz",
    "wof:placetype":"venue"
},
  "geometry": {"coordinates":[11.553437,48.180515],"type":"Point"}
}