{
  "type": "Feature",
  "properties": {
    "iso:country":"DE",
    "sg:address":"Ringstr. 5",
    "sg:city":"Chamerau",
    "sg:phone":"+49 9941/8977",
    "sg:postcode":"93466",
    "sg:province":"Bayern",
    "wof:name":"B. Fischer",
    "wof:placetype":"venue"
},
  "geometry": {"coordinates":[12.802605629,49.1961364746],"type":"Point"}
}