{
  "type": "Feature",
  "properties": {
    "iso:country":"DE",
    "sg:address":"Sudetenstr. 1",
    "sg:city":"Kleinrinderfeld",
    "sg:phone":"+49 9366/7277",
    "sg:postcode":"97271",
    "sg:province":"Bayern",
    "wof:name":"Albert Kastner Ingenieur",
    "wof:placetype":"venue"
},
  "geometry": {"coordinates":[9.8487911224,49.7009429932],"type":"Point"}
}