{
  "type": "Feature",
  "properties": {
    "iso:country":"DE",
    "sg:address":"Schl\u00fcterstr. 6",
    "sg:city":"Hamburg",
    "sg:phone":"+49 40/4502410",
    "sg:postcode":"20146",
    "sg:province":"Hamburg",
    "wof:name":"Johann Schwenn Rechtsanwalt",
    "wof:placetype":"venue"
},
  "geometry": {"coordinates":[9.9871034622,53.5647277832],"type":"Point"}
}