{
  "type": "Feature",
  "properties": {
    "iso:country":"DE",
    "sg:address":"Am Kieselmarkt 4",
    "sg:city":"Heilbronn",
    "sg:phone":"+49 7131/60286",
    "sg:postcode":"74072",
    "sg:province":"Baden-W\u00fcrttemberg",
    "wof:name":"B\u00e4der Studio Ungerer Gmbh",
    "wof:placetype":"venue"
},
  "geometry": {"coordinates":[9.2196950912,49.1427841187],"type":"Point"}
}