{
  "type": "Feature",
  "properties": {
    "iso:country":"DE",
    "sg:address":"Andreasstr. 3a",
    "sg:city":"Erfurt",
    "sg:phone":"+49 361/2128922",
    "sg:postcode":"99084",
    "sg:province":"Th\u00fcringen",
    "wof:name":"Elektrohaus Berger Inh. Rainer Berger",
    "wof:placetype":"venue"
},
  "geometry": {"coordinates":[11.0210227966,50.9825592041],"type":"Point"}
}