{
  "type": "Feature",
  "properties": {
    "iso:country":"DE",
    "sg:address":"N\u00fcrnberger Str. 17",
    "sg:city":"Schnaittach",
    "sg:postcode":"91220",
    "sg:province":"Bayern",
    "wof:name":"B. Gartner Textilhaus",
    "wof:placetype":"venue"
},
  "geometry": {"coordinates":[11.340293,49.557922],"type":"Point"}
}