{
  "type": "Feature",
  "properties": {
    "iso:country":"DE",
    "sg:address":"Heidenburgstr. 30",
    "sg:city":"Stuttgart",
    "sg:phone":"+49 711/5302166",
    "sg:postcode":"70378",
    "sg:province":"Baden-W\u00fcrttemberg",
    "wof:name":"Thomas Juzeler Kg",
    "wof:placetype":"venue"
},
  "geometry": {"coordinates":[9.226504,48.849121],"type":"Point"}
}