{
  "type": "Feature",
  "properties": {
    "iso:country":"DE",
    "sg:address":"Hauptstr. 27",
    "sg:city":"Meschede",
    "sg:phone":"+49 2903/6449",
    "sg:postcode":"59872",
    "sg:province":"Nordrhein-Westfalen",
    "wof:name":"I-punkt",
    "wof:placetype":"venue"
},
  "geometry": {"coordinates":[8.1694002151,51.3751792908],"type":"Point"}
}