{
  "type": "Feature",
  "properties": {
    "iso:country":"DE",
    "sg:address":"Pfingstborn 13",
    "sg:city":"Essen",
    "sg:phone":"+49 201/830350",
    "sg:postcode":"45327",
    "sg:province":"Nordrhein-Westfalen",
    "wof:name":"Rolf Und J\u00f6rg Jacob",
    "wof:placetype":"venue"
},
  "geometry": {"coordinates":[7.0505671501,51.4935722351],"type":"Point"}
}