{
  "type": "Feature",
  "properties": {
    "iso:country":"DE",
    "sg:address":"Anderslebener Str. 1",
    "sg:city":"Oschersleben",
    "sg:phone":"+49 3949/2094",
    "sg:postcode":"39387",
    "sg:province":"Sachsen-Anhalt",
    "wof:name":"Minol Tankstelle",
    "wof:placetype":"venue"
},
  "geometry": {"coordinates":[11.2358179092,52.0293464661],"type":"Point"}
}