{
  "type": "Feature",
  "properties": {
    "iso:country":"DE",
    "sg:address":"Geranienstr. 10",
    "sg:city":"Berlin",
    "sg:phone":"+49 30/8347150",
    "sg:postcode":"12203",
    "sg:province":"Berlin",
    "wof:name":"Rainer Danz",
    "wof:placetype":"venue"
},
  "geometry": {"coordinates":[13.311671257,52.4513587952],"type":"Point"}
}