{
  "type": "Feature",
  "properties": {
    "iso:country":"DE",
    "sg:address":"Dernekamp 76a",
    "sg:city":"D\u00fclmen",
    "sg:phone":"+49 2594/4474",
    "sg:postcode":"48249",
    "sg:province":"Nordrhein-Westfalen",
    "wof:name":"Walter Laerbusch",
    "wof:placetype":"venue"
},
  "geometry": {"coordinates":[7.28719,51.808891],"type":"Point"}
}