{
  "type": "Feature",
  "properties": {
    "iso:country":"DE",
    "sg:address":"Mainzer Str. 13",
    "sg:city":"Heidesheim",
    "sg:phone":"+49 6132/5227",
    "sg:postcode":"55262",
    "sg:province":"Rheinland-Pfalz",
    "wof:name":"Alexander Kirsch",
    "wof:placetype":"venue"
},
  "geometry": {"coordinates":[8.1151561737,49.9953422546],"type":"Point"}
}