{
  "type": "Feature",
  "properties": {
    "iso:country":"DE",
    "sg:address":"Hofstr. 57",
    "sg:city":"Altbach",
    "sg:phone":"+49 7153/22672",
    "sg:postcode":"73776",
    "sg:province":"Baden-W\u00fcrttemberg",
    "wof:name":"Werner Munk Architekt",
    "wof:placetype":"venue"
},
  "geometry": {"coordinates":[9.379478,48.728348],"type":"Point"}
}