{
  "type": "Feature",
  "properties": {
    "iso:country":"DE",
    "sg:address":"Leonhardtstr. 64",
    "sg:city":"Greiz",
    "sg:phone":"+49 3661/434720",
    "sg:postcode":"07973",
    "sg:province":"Th\u00fcringen",
    "wof:name":"E. Wenzel Immobilienmakler",
    "wof:placetype":"venue"
},
  "geometry": {"coordinates":[12.197769165,50.6700325012],"type":"Point"}
}