{
  "type": "Feature",
  "properties": {
    "iso:country":"DE",
    "sg:address":"\u00d6denwald",
    "sg:city":"Lo\u00dfburg",
    "sg:phone":"+49 7446/1443",
    "sg:postcode":"72290",
    "sg:province":"Baden-W\u00fcrttemberg",
    "wof:name":"G\u00e4stehaus Killguss-hof",
    "wof:placetype":"venue"
},
  "geometry": {"coordinates":[8.4089794159,48.4144020081],"type":"Point"}
}