{
  "type": "Feature",
  "properties": {
    "iso:country":"DE",
    "sg:address":"Pfingstrosenstr. 77",
    "sg:city":"M\u00fcnchen",
    "sg:phone":"+49 89/715958",
    "sg:postcode":"81377",
    "sg:province":"Bayern",
    "wof:name":"Eiscafe Pizzeria Etna",
    "wof:placetype":"venue"
},
  "geometry": {"coordinates":[11.478775,48.108543],"type":"Point"}
}