{
  "type": "Feature",
  "properties": {
    "iso:country":"DE",
    "sg:address":"Hellerstr. 49",
    "sg:city":"Dortmund",
    "sg:phone":"+49 231/528024",
    "sg:postcode":"44229",
    "sg:province":"Nordrhein-Westfalen",
    "wof:name":"Peter Und J. Allemann Ingenieure",
    "wof:placetype":"venue"
},
  "geometry": {"coordinates":[7.4477891922,51.4498558044],"type":"Point"}
}