{
  "type": "Feature",
  "properties": {
    "iso:country":"DE",
    "sg:address":"Flensburger Str. 3 a",
    "sg:city":"Kappeln",
    "sg:postcode":"24376",
    "sg:province":"Schleswig-Holstein",
    "wof:name":"Hauptmann & Co. Ohg",
    "wof:placetype":"venue"
},
  "geometry": {"coordinates":[9.9254255295,54.6628112793],"type":"Point"}
}