{
  "type": "Feature",
  "properties": {
    "iso:country":"DE",
    "sg:address":"St.-Georg-Ring 16",
    "sg:city":"Leiblfing",
    "sg:phone":"+49 9426/1386",
    "sg:postcode":"94339",
    "sg:province":"Bayern",
    "wof:name":"Rupert Bogner",
    "wof:placetype":"venue"
},
  "geometry": {"coordinates":[12.589717,48.756763],"type":"Point"}
}