{
  "type": "Feature",
  "properties": {
    "iso:country":"DE",
    "sg:address":"Am Hang 4",
    "sg:city":"Otzberg",
    "sg:postcode":"64853",
    "sg:province":"Hessen",
    "wof:name":"\u00d6ffentliche B\u00fccherei",
    "wof:placetype":"venue"
},
  "geometry": {"coordinates":[8.918119,49.816547],"type":"Point"}
}