{
  "type": "Feature",
  "properties": {
    "iso:country":"DE",
    "sg:address":"Ysenburgstr. 13",
    "sg:city":"W\u00fcrzburg",
    "sg:postcode":"97082",
    "sg:province":"Bayern",
    "wof:name":"Freudenberger Gmbh",
    "wof:placetype":"venue"
},
  "geometry": {"coordinates":[9.9138641357,49.8016319275],"type":"Point"}
}