{
  "type": "Feature",
  "properties": {
    "iso:country":"DE",
    "sg:address":"Blumenthaler Str. 13",
    "sg:city":"Schwanewede",
    "sg:postcode":"28790",
    "sg:province":"Niedersachsen",
    "wof:name":"Rodisch Projektierungs-und Grundst\u00fccksverwaltungs Gmbh",
    "wof:placetype":"venue"
},
  "geometry": {"coordinates":[8.5916900635,53.2214279175],"type":"Point"}
}