{
  "type": "Feature",
  "properties": {
    "iso:country":"DE",
    "sg:address":"Darmst\u00e4dter Str. 66",
    "sg:city":"Reinheim",
    "sg:phone":"+49 6162/2964",
    "sg:postcode":"64354",
    "sg:province":"Hessen",
    "wof:name":"Optik-thoma Augenoptiker",
    "wof:placetype":"venue"
},
  "geometry": {"coordinates":[8.8334321976,49.8330116272],"type":"Point"}
}