{
  "type": "Feature",
  "properties": {
    "iso:country":"DE",
    "sg:address":"Hahnweg 139",
    "sg:city":"Coburg",
    "sg:phone":"+49 7081/954440",
    "sg:postcode":"96450",
    "sg:province":"Bayern",
    "wof:name":"Mawi Gmbh",
    "wof:placetype":"venue"
},
  "geometry": {"coordinates":[8.577897,48.786816],"type":"Point"}
}