{
  "type": "Feature",
  "properties": {
    "iso:country":"DE",
    "sg:address":"In den Buchen 30",
    "sg:city":"Ruppertsweiler",
    "sg:phone":"+49 6395/8130",
    "sg:postcode":"66957",
    "sg:province":"Rheinland-Pfalz",
    "wof:name":"Haber & Partner Bauunternehmung Gmbh",
    "wof:placetype":"venue"
},
  "geometry": {"coordinates":[7.67847,49.195652],"type":"Point"}
}