{
  "type": "Feature",
  "properties": {
    "iso:country":"DE",
    "sg:address":"Hohe Egge H\u00f6henweg 18",
    "sg:city":"Sprockh\u00f6vel",
    "sg:postcode":"45549",
    "sg:province":"Nordrhein-Westfalen",
    "wof:name":"Cnc Elektronik Gmbh",
    "wof:placetype":"venue"
},
  "geometry": {"coordinates":[7.2655072212,51.3686027527],"type":"Point"}
}