{
  "type": "Feature",
  "properties": {
    "iso:country":"DE",
    "sg:address":"Rubensstr. 7",
    "sg:city":"Bottrop",
    "sg:phone":"+49 2041/72080",
    "sg:postcode":"46238",
    "sg:province":"Nordrhein-Westfalen",
    "wof:name":"Bao-chemie Gmbh",
    "wof:placetype":"venue"
},
  "geometry": {"coordinates":[6.946750164,51.5214614868],"type":"Point"}
}