{
  "type": "Feature",
  "properties": {
    "iso:country":"DE",
    "sg:address":"Roter Berg 5",
    "sg:city":"Cremlingen",
    "sg:phone":"+49 5306/2069",
    "sg:postcode":"38162",
    "sg:province":"Niedersachsen",
    "wof:name":"Wilhelm Sch\u00f6nian",
    "wof:placetype":"venue"
},
  "geometry": {"coordinates":[10.711075,52.258862],"type":"Point"}
}