{
  "type": "Feature",
  "properties": {
    "iso:country":"DE",
    "sg:address":"Teichstr. 9",
    "sg:city":"Obertrubach",
    "sg:phone":"+49 9245/226",
    "sg:postcode":"91286",
    "sg:province":"Bayern",
    "wof:name":"Raiffeisenbank Obertrubach Eg",
    "wof:placetype":"venue"
},
  "geometry": {"coordinates":[11.347774,49.695465],"type":"Point"}
}