{
  "type": "Feature",
  "properties": {
    "iso:country":"DE",
    "sg:address":"Geschwister-Scholl-Str. 40",
    "sg:city":"Brandenburg",
    "sg:phone":"+49 3381/223642",
    "sg:postcode":"14776",
    "sg:province":"Brandenburg",
    "wof:name":"Ikl Ingenieurgesellschaft Mbh",
    "wof:placetype":"venue"
},
  "geometry": {"coordinates":[12.5683088303,52.4054527283],"type":"Point"}
}