{
  "type": "Feature",
  "properties": {
    "iso:country":"DE",
    "sg:address":"Gladbacher Str. 24",
    "sg:city":"K\u00f6ln",
    "sg:phone":"+49 221/528888",
    "sg:postcode":"50672",
    "sg:province":"Nordrhein-Westfalen",
    "wof:name":"Maria Fronh\u00f6fer",
    "wof:placetype":"venue"
},
  "geometry": {"coordinates":[6.939786,50.945976],"type":"Point"}
}