{
  "type": "Feature",
  "properties": {
    "iso:country":"DE",
    "sg:address":"Wingertstr. 3",
    "sg:city":"Bad Nauheim",
    "sg:phone":"+49 6032/85447",
    "sg:postcode":"61231",
    "sg:province":"Hessen",
    "wof:name":"Elektro-tries Elektroinstallation",
    "wof:placetype":"venue"
},
  "geometry": {"coordinates":[8.747866,50.400856],"type":"Point"}
}