{
  "type": "Feature",
  "properties": {
    "iso:country":"DE",
    "sg:address":"Am Wassertor 18",
    "sg:city":"Attendorn",
    "sg:phone":"+49 2722/4800",
    "sg:postcode":"57439",
    "sg:province":"Nordrhein-Westfalen",
    "wof:name":"Burkhard Neuhaus Rechtsanwalt Und Notar",
    "wof:placetype":"venue"
},
  "geometry": {"coordinates":[7.9065470695,51.1227722168],"type":"Point"}
}