{
  "type": "Feature",
  "properties": {
    "iso:country":"DE",
    "sg:address":"Ramhorster Str. 1",
    "sg:city":"Lehrte",
    "sg:phone":"+49 5136/892199",
    "sg:postcode":"31275",
    "sg:province":"Niedersachsen",
    "wof:name":"Karsten Steckhan",
    "wof:placetype":"venue"
},
  "geometry": {"coordinates":[9.990741,52.412117],"type":"Point"}
}