{
  "type": "Feature",
  "properties": {
    "iso:country":"DE",
    "sg:address":"Tammer Str. 26",
    "sg:city":"Markgr\u00f6ningen",
    "sg:phone":"+49 7145/26568",
    "sg:postcode":"71706",
    "sg:province":"Baden-W\u00fcrttemberg",
    "wof:name":"A. Loukidou",
    "wof:placetype":"venue"
},
  "geometry": {"coordinates":[9.0859661102,48.9075965881],"type":"Point"}
}