{
  "type": "Feature",
  "properties": {
    "iso:country":"DE",
    "sg:address":"Kunibertistr. 1",
    "sg:city":"Recklinghausen",
    "sg:phone":"+49 2361/17620",
    "sg:postcode":"45657",
    "sg:province":"Nordrhein-Westfalen",
    "wof:name":"Restaurant China-town",
    "wof:placetype":"venue"
},
  "geometry": {"coordinates":[7.198445797,51.6150360107],"type":"Point"}
}