{
  "type": "Feature",
  "properties": {
    "iso:country":"DE",
    "sg:address":"Kirchstr. 67",
    "sg:city":"Brockum",
    "sg:phone":"+49 5443/474",
    "sg:postcode":"49448",
    "sg:province":"Niedersachsen",
    "wof:name":"Thrien Bedachungen Gmbh",
    "wof:placetype":"venue"
},
  "geometry": {"coordinates":[8.415236,52.46513],"type":"Point"}
}