{
  "type": "Feature",
  "properties": {
    "iso:country":"DE",
    "sg:address":"Hauptstr. 35",
    "sg:city":"Wildenbruch",
    "sg:phone":"+49 33205/54662",
    "sg:postcode":"14552",
    "sg:province":"Brandenburg",
    "wof:name":"M. Dettke",
    "wof:placetype":"venue"
},
  "geometry": {"coordinates":[13.061709,52.291702],"type":"Point"}
}