{
  "type": "Feature",
  "properties": {
    "iso:country":"DE",
    "sg:address":"Hovestr. 20",
    "sg:city":"Everswinkel",
    "sg:phone":"+49 2582/65400",
    "sg:postcode":"48351",
    "sg:province":"Nordrhein-Westfalen",
    "wof:name":"Masters M & O",
    "wof:placetype":"venue"
},
  "geometry": {"coordinates":[7.8471078873,51.9271240234],"type":"Point"}
}