{
  "type": "Feature",
  "properties": {
    "iso:country":"DE",
    "sg:address":"Adolfstr. 36",
    "sg:city":"Bad Schwalbach",
    "sg:phone":"+49 6124/4606",
    "sg:postcode":"65307",
    "sg:province":"Hessen",
    "wof:name":"Parkhaus Jahnplatz Betriebsges. Mbh",
    "wof:placetype":"venue"
},
  "geometry": {"coordinates":[8.0708999634,50.1411399841],"type":"Point"}
}