{
  "type": "Feature",
  "properties": {
    "iso:country":"DE",
    "sg:address":"Neurieder Stra\u00dfe 8",
    "sg:city":"Buchendorf",
    "sg:phone":"+49 89",
    "sg:postcode":"82131",
    "sg:province":"Bayern",
    "wof:name":"Irl Hom\u00d6opathie Seminare & Vertrieb",
    "wof:placetype":"venue"
},
  "geometry": {"coordinates":[11.402929,48.058174],"type":"Point"}
}