{
  "type": "Feature",
  "properties": {
    "iso:country":"DE",
    "sg:address":"Im Alten Dorf 20",
    "sg:city":"Bramsche",
    "sg:phone":"+49 5468/352",
    "sg:postcode":"49565",
    "sg:province":"Niedersachsen",
    "wof:name":"Ev. Pfarramt I",
    "wof:placetype":"venue"
},
  "geometry": {"coordinates":[8.0614500046,52.3887748718],"type":"Point"}
}