{
  "type": "Feature",
  "properties": {
    "iso:country":"DE",
    "sg:address":"Bei den Kalk\u00f6fen 2",
    "sg:city":"Ottweiler",
    "sg:phone":"+49 6824/700315",
    "sg:postcode":"66564",
    "sg:province":"Saarland",
    "wof:name":"Monika Baltes-klein",
    "wof:placetype":"venue"
},
  "geometry": {"coordinates":[7.1585950851,49.4177055359],"type":"Point"}
}