{
  "type": "Feature",
  "properties": {
    "iso:country":"DE",
    "sg:address":"Addernhausener Str.",
    "sg:city":"Schortens",
    "sg:phone":"+49 4461/3537",
    "sg:postcode":"26419",
    "sg:province":"Niedersachsen",
    "wof:name":"Waldschl\u00f6sschen",
    "wof:placetype":"venue"
},
  "geometry": {"coordinates":[7.911714077,53.5468444824],"type":"Point"}
}