{
  "type": "Feature",
  "properties": {
    "iso:country":"DE",
    "sg:address":"Waldschulstr. 21",
    "sg:city":"Pforzheim",
    "sg:postcode":"75180",
    "sg:province":"Baden-W\u00fcrttemberg",
    "wof:name":"F. R\u00f6then Ingenieur",
    "wof:placetype":"venue"
},
  "geometry": {"coordinates":[8.6580982208,48.8566627502],"type":"Point"}
}