{
  "type": "Feature",
  "properties": {
    "iso:country":"DE",
    "sg:address":"Steindamm 3",
    "sg:city":"Wilster",
    "sg:phone":"+49 4823/234",
    "sg:postcode":"25554",
    "sg:province":"Schleswig-Holstein",
    "wof:name":"Kai-uwe Pucks",
    "wof:placetype":"venue"
},
  "geometry": {"coordinates":[9.385097,53.924263],"type":"Point"}
}