{
  "type": "Feature",
  "properties": {
    "iso:country":"DE",
    "sg:address":"Dorfstr. 118",
    "sg:city":"Gro\u00dfheide",
    "sg:phone":"+49 4936/7742",
    "sg:postcode":"26532",
    "sg:province":"Niedersachsen",
    "wof:name":"Friedrich L\u00fcthcke",
    "wof:placetype":"venue"
},
  "geometry": {"coordinates":[7.367074,53.562317],"type":"Point"}
}