{
  "type": "Feature",
  "properties": {
    "iso:country":"DE",
    "sg:address":"Adolf-Heim-Str. 12",
    "sg:city":"Bietigheim-Bissingen",
    "sg:phone":"+49 7142/90410",
    "sg:postcode":"74321",
    "sg:province":"Baden-W\u00fcrttemberg",
    "wof:name":"N\u00e4htec Industrien\u00e4hanlagen- Vertriebsgesellschaft Mbh",
    "wof:placetype":"venue"
},
  "geometry": {"coordinates":[9.1252794266,48.9379577637],"type":"Point"}
}