{
  "type": "Feature",
  "properties": {
    "iso:country":"DE",
    "sg:address":"Lengenfelder Str. 19",
    "sg:city":"Zwickau",
    "sg:phone":"+49 375/781162",
    "sg:postcode":"08064",
    "sg:province":"Sachsen",
    "wof:name":"Andreas Thiem",
    "wof:placetype":"venue"
},
  "geometry": {"coordinates":[12.4783592224,50.6790885925],"type":"Point"}
}