{
  "type": "Feature",
  "properties": {
    "iso:country":"DE",
    "sg:address":"Rheiner Hof 2",
    "sg:city":"Nordhorn",
    "sg:phone":"+49 4959/2189360",
    "sg:postcode":"48527",
    "sg:province":"Niedersachsen",
    "wof:name":"H. Vrielmann Gmbh",
    "wof:placetype":"venue"
},
  "geometry": {"coordinates":[7.046473,52.41777],"type":"Point"}
}