{
  "type": "Feature",
  "properties": {
    "iso:country":"DE",
    "sg:address":"Macherstr. 35",
    "sg:city":"Kamenz",
    "sg:phone":"+49 35783/15515",
    "sg:postcode":"01917",
    "sg:province":"Sachsen",
    "wof:name":"Schwimmhalle",
    "wof:placetype":"venue"
},
  "geometry": {"coordinates":[14.1044387817,51.2804412842],"type":"Point"}
}