{
  "type": "Feature",
  "properties": {
    "iso:country":"DE",
    "sg:address":"Vennstr. 16",
    "sg:city":"Waldbr\u00f6l",
    "sg:phone":"+49 2291/2670",
    "sg:postcode":"51545",
    "sg:province":"Nordrhein-Westfalen",
    "wof:name":"H. E. Leroff Ingenieur",
    "wof:placetype":"venue"
},
  "geometry": {"coordinates":[7.612993,50.876247],"type":"Point"}
}