{
  "type": "Feature",
  "properties": {
    "iso:country":"DE",
    "sg:address":"Laubegaster Ufer 17",
    "sg:city":"Dresden",
    "sg:phone":"+49 351/2571108",
    "sg:postcode":"01279",
    "sg:province":"Sachsen",
    "wof:name":"Dipl.-ing. C. Palen Ingenieur",
    "wof:placetype":"venue"
},
  "geometry": {"coordinates":[13.8395824432,51.0255508423],"type":"Point"}
}