{
  "type": "Feature",
  "properties": {
    "iso:country":"DE",
    "sg:address":"Kettelerstr. 2",
    "sg:city":"Emsdetten",
    "sg:phone":"+49 2572/1550",
    "sg:postcode":"48282",
    "sg:province":"Nordrhein-Westfalen",
    "wof:name":"A. K\u00e4rcher Gmbh",
    "wof:placetype":"venue"
},
  "geometry": {"coordinates":[7.549925,52.187218],"type":"Point"}
}