{
  "type": "Feature",
  "properties": {
    "iso:country":"DE",
    "sg:address":"Max-Born-Str 21",
    "sg:city":"Bergheim",
    "sg:phone":"+49 2271/65830",
    "sg:postcode":"50126",
    "sg:province":"Nordrhein-Westfalen",
    "wof:name":"Wiedenbach Apparatebau Gmbh",
    "wof:placetype":"venue"
},
  "geometry": {"coordinates":[6.6345891953,50.9458961487],"type":"Point"}
}