{
  "type": "Feature",
  "properties": {
    "iso:country":"DE",
    "sg:address":"Grunerstr. 18",
    "sg:city":"Idstein",
    "sg:phone":"+49 6126/4001",
    "sg:postcode":"65510",
    "sg:province":"Hessen",
    "wof:name":"Maprotec Maschinen- Und Proze\u00dftechnik Gmbh",
    "wof:placetype":"venue"
},
  "geometry": {"coordinates":[8.267351,50.215981],"type":"Point"}
}