{
  "type": "Feature",
  "properties": {
    "iso:country":"DE",
    "sg:address":"Gugelhammerweg 1",
    "sg:city":"Feucht",
    "sg:postcode":"90537",
    "sg:province":"Bayern",
    "wof:name":"Aldi Gmbh & Co. Kg",
    "wof:placetype":"venue"
},
  "geometry": {"coordinates":[11.2055740356,49.3671035767],"type":"Point"}
}