{
  "type": "Feature",
  "properties": {
    "iso:country":"DE",
    "sg:address":"Ludenberger Str. 15",
    "sg:city":"D\u00fcsseldorf",
    "sg:phone":"+49 211/667444",
    "sg:postcode":"40629",
    "sg:province":"Nordrhein-Westfalen",
    "wof:name":"Wehrhahn & Lucius Gmbh",
    "wof:placetype":"venue"
},
  "geometry": {"coordinates":[6.83176,51.241039],"type":"Point"}
}