{
  "type": "Feature",
  "properties": {
    "iso:country":"DE",
    "sg:address":"Waldseite",
    "sg:city":"Bad Bentheim",
    "sg:postcode":"48455",
    "sg:province":"Niedersachsen",
    "wof:name":"Lemke",
    "wof:placetype":"venue"
},
  "geometry": {"coordinates":[7.0999999046,52.3166999817],"type":"Point"}
}