{
  "type": "Feature",
  "properties": {
    "iso:country":"DE",
    "sg:address":"An der Abtei 6",
    "sg:city":"Duisburg",
    "sg:phone":"+49 4920/3578900",
    "sg:postcode":"47166",
    "sg:province":"Nordrhein-Westfalen",
    "wof:name":"Praemonstratenser-abtei Hamborn, Duisburg",
    "wof:placetype":"venue"
},
  "geometry": {"coordinates":[6.762745,51.490345],"type":"Point"}
}