{
  "type": "Feature",
  "properties": {
    "iso:country":"DE",
    "sg:address":"Frankfurter Str. 93",
    "sg:city":"Fulda",
    "sg:phone":"+49 661/46627",
    "sg:postcode":"36043",
    "sg:province":"Hessen",
    "wof:name":"Pizzeria Pizza Und Pasta",
    "wof:placetype":"venue"
},
  "geometry": {"coordinates":[9.6765441895,50.5357513428],"type":"Point"}
}