{
  "type": "Feature",
  "properties": {
    "iso:country":"DE",
    "sg:address":"Fraunhoferstr. 41",
    "sg:city":"M\u00fcnchen",
    "sg:phone":"+49 89/2014902",
    "sg:postcode":"80469",
    "sg:province":"Bayern",
    "wof:name":"Fraunhofer Schoppenstube",
    "wof:placetype":"venue"
},
  "geometry": {"coordinates":[11.5754127502,48.1286735535],"type":"Point"}
}