{
  "type": "Feature",
  "properties": {
    "iso:country":"DE",
    "sg:address":"Eschenstra\u00dfe 4a",
    "sg:city":"Memmingerberg",
    "sg:phone":"+49 8331",
    "sg:postcode":"87766",
    "sg:province":"Bayern",
    "wof:name":"Onlineshop H-w-r Handyzubeh\u00f6r",
    "wof:placetype":"venue"
},
  "geometry": {"coordinates":[10.209131,47.992844],"type":"Point"}
}