{
  "type": "Feature",
  "properties": {
    "iso:country":"DE",
    "sg:address":"Bahnhofstr. 42",
    "sg:city":"Wedel",
    "sg:phone":"+49 4103/88021",
    "sg:postcode":"22880",
    "sg:province":"Schleswig-Holstein",
    "wof:name":"D. Wolfersdorf",
    "wof:placetype":"venue"
},
  "geometry": {"coordinates":[9.705376,53.5769],"type":"Point"}
}