{
  "type": "Feature",
  "properties": {
    "iso:country":"DE",
    "sg:address":"Fabrikstr. 27",
    "sg:city":"D\u00fcrnau",
    "sg:phone":"+49 7164/909806",
    "sg:postcode":"73105",
    "sg:province":"Baden-W\u00fcrttemberg",
    "wof:name":"H. J. Reich",
    "wof:placetype":"venue"
},
  "geometry": {"coordinates":[9.63975,48.645737],"type":"Point"}
}