{
  "type": "Feature",
  "properties": {
    "iso:country":"DE",
    "sg:address":"Fritz-Elsas-Str. 21",
    "sg:city":"Berlin",
    "sg:phone":"+49 30/78715815",
    "sg:postcode":"10825",
    "sg:province":"Berlin",
    "wof:name":"Don Martin Reisen E. K.",
    "wof:placetype":"venue"
},
  "geometry": {"coordinates":[13.3455286026,52.4824867249],"type":"Point"}
}