{
  "type": "Feature",
  "properties": {
    "iso:country":"DE",
    "sg:address":"Richterstr. 10",
    "sg:city":"Berlin",
    "sg:phone":"+49 30/7066793",
    "sg:postcode":"12105",
    "sg:province":"Berlin",
    "wof:name":"Klaus Lippert",
    "wof:placetype":"venue"
},
  "geometry": {"coordinates":[13.385152,52.442123],"type":"Point"}
}