{
  "type": "Feature",
  "properties": {
    "iso:country":"DE",
    "sg:address":"Treffurter Str.",
    "sg:city":"Falken",
    "sg:phone":"+49 36923/50625",
    "sg:postcode":"99830",
    "sg:province":"Th\u00fcringen",
    "wof:name":"H.-j. B\u00f6hm",
    "wof:placetype":"venue"
},
  "geometry": {"coordinates":[10.2665500641,51.1182365417],"type":"Point"}
}