{
  "type": "Feature",
  "properties": {
    "iso:country":"DE",
    "sg:address":"Ellholzweg 2",
    "sg:city":"Altdorf",
    "sg:phone":"+49 9187/905374",
    "sg:postcode":"90518",
    "sg:province":"Bayern",
    "wof:name":"K. Br\u00e4unlein",
    "wof:placetype":"venue"
},
  "geometry": {"coordinates":[11.3192996979,49.3910751343],"type":"Point"}
}