{
  "type": "Feature",
  "properties": {
    "iso:country":"DE",
    "sg:address":"Hauptstr 53",
    "sg:city":"H\u00fcffenhardt",
    "sg:phone":"+49 6268/321",
    "sg:postcode":"74928",
    "sg:province":"Baden-W\u00fcrttemberg",
    "wof:name":"Sigmann Elektronik Gmbh",
    "wof:placetype":"venue"
},
  "geometry": {"coordinates":[9.086132,49.291763],"type":"Point"}
}