{
  "type": "Feature",
  "properties": {
    "iso:country":"DE",
    "sg:address":"Lindhorstweg 82",
    "sg:city":"Berlin",
    "sg:phone":"+49 30/63979862",
    "sg:postcode":"12487",
    "sg:province":"Berlin",
    "wof:name":"Pylon Bautr\u00e4ger- Und Grundst\u00fccksgesellschaft Mbh",
    "wof:placetype":"venue"
},
  "geometry": {"coordinates":[13.496742,52.441788],"type":"Point"}
}