{
  "type": "Feature",
  "properties": {
    "iso:country":"DE",
    "sg:address":"Tempowerkring 3",
    "sg:city":"Hamburg",
    "sg:phone":"+49 40/79012770",
    "sg:postcode":"21079",
    "sg:province":"Hamburg",
    "wof:name":"Lindschulte & Partner Hamburg Beratene Ingenieure Vbi Gmbh",
    "wof:placetype":"venue"
},
  "geometry": {"coordinates":[9.931974411,53.4732971191],"type":"Point"}
}