{
  "type": "Feature",
  "properties": {
    "iso:country":"DE",
    "sg:address":"Saarner Str. 314",
    "sg:city":"M\u00fclheim",
    "sg:phone":"+49 208/588690",
    "sg:postcode":"45478",
    "sg:province":"Nordrhein-Westfalen",
    "wof:name":"Wilhelm Johannknecht Steuerberater",
    "wof:placetype":"venue"
},
  "geometry": {"coordinates":[6.8432750702,51.4214324951],"type":"Point"}
}