{
  "type": "Feature",
  "properties": {
    "iso:country":"DE",
    "sg:address":"Sinkenbreite 3",
    "sg:city":"Bergh\u00fclen",
    "sg:phone":"+49 7344/7081",
    "sg:postcode":"89180",
    "sg:province":"Baden-W\u00fcrttemberg",
    "wof:name":"Straleit Gmbh",
    "wof:placetype":"venue"
},
  "geometry": {"coordinates":[9.753316,48.464031],"type":"Point"}
}