{
  "type": "Feature",
  "properties": {
    "iso:country":"DE",
    "sg:address":"K\u00f6tzschenbroder Str. 138",
    "sg:city":"Dresden",
    "sg:postcode":"01139",
    "sg:province":"Sachsen",
    "wof:name":"Plan Team Gmbh",
    "wof:placetype":"venue"
},
  "geometry": {"coordinates":[13.685355,51.084763],"type":"Point"}
}