{
  "type": "Feature",
  "properties": {
    "iso:country":"DE",
    "sg:address":"Hauptstr. 24a",
    "sg:city":"Carlsberg",
    "sg:phone":"+49 6356/245",
    "sg:postcode":"67316",
    "sg:province":"Rheinland-Pfalz",
    "wof:name":"I. Heiser Kohlen-handlung",
    "wof:placetype":"venue"
},
  "geometry": {"coordinates":[8.029744,49.494629],"type":"Point"}
}