{
  "type": "Feature",
  "properties": {
    "iso:country":"DE",
    "sg:address":"Rodinger Str. 1",
    "sg:city":"Schorndorf",
    "sg:phone":"+49 9467/990",
    "sg:postcode":"93489",
    "sg:province":"Bayern",
    "wof:name":"Gerhard Br\u00e4u Gmbh",
    "wof:placetype":"venue"
},
  "geometry": {"coordinates":[12.591257,49.158875],"type":"Point"}
}