{
  "type": "Feature",
  "properties": {
    "iso:country":"DE",
    "sg:address":"Amundsenstr. 33",
    "sg:city":"Hamburg",
    "sg:postcode":"22767",
    "sg:province":"Hamburg",
    "wof:name":"Scala-immobilien Alexander Pavlidis E. Kfm.",
    "wof:placetype":"venue"
},
  "geometry": {"coordinates":[9.9465646744,53.5464668274],"type":"Point"}
}