{
  "type": "Feature",
  "properties": {
    "iso:country":"DE",
    "sg:address":"Bruno-Granz-Str. 64",
    "sg:city":"Chemnitz",
    "sg:phone":"+49 371/227836",
    "sg:postcode":"09122",
    "sg:province":"Sachsen",
    "wof:name":"Gerolf D\u00f6hler Ingenieur",
    "wof:placetype":"venue"
},
  "geometry": {"coordinates":[12.8889436722,50.793838501],"type":"Point"}
}