{
  "type": "Feature",
  "properties": {
    "iso:country":"DE",
    "sg:address":"Vaihinger Str. 19",
    "sg:city":"Illingen",
    "sg:phone":"+49 7042/82335",
    "sg:postcode":"75428",
    "sg:province":"Baden-W\u00fcrttemberg",
    "wof:name":"Lamm",
    "wof:placetype":"venue"
},
  "geometry": {"coordinates":[8.9200582504,48.9539222717],"type":"Point"}
}