{
  "type": "Feature",
  "properties": {
    "iso:country":"DE",
    "sg:address":"Caprivistr. 7",
    "sg:city":"Kiel",
    "sg:phone":"+49 431/85094",
    "sg:postcode":"24105",
    "sg:province":"Schleswig-Holstein",
    "wof:name":"Dr. J\u00fcrgen Hacker Rechtsanwalt Und Notar",
    "wof:placetype":"venue"
},
  "geometry": {"coordinates":[10.1490774155,54.340675354],"type":"Point"}
}