{
  "type": "Feature",
  "properties": {
    "iso:country":"DE",
    "sg:address":"Viktoriastr. 10",
    "sg:city":"B\u00fcnde",
    "sg:phone":"+49 5223/2786",
    "sg:postcode":"32257",
    "sg:province":"Nordrhein-Westfalen",
    "wof:name":"H. L\u00fcdeking Immobilienmakler",
    "wof:placetype":"venue"
},
  "geometry": {"coordinates":[8.5874786377,52.1986923218],"type":"Point"}
}