{
  "type": "Feature",
  "properties": {
    "iso:country":"DE",
    "sg:address":"Altreichenau",
    "sg:city":"Neureichenau",
    "sg:phone":"+49 8583/2645",
    "sg:postcode":"94089",
    "sg:province":"Bayern",
    "wof:name":"Gasthof Josef Schmid",
    "wof:placetype":"venue"
},
  "geometry": {"coordinates":[13.7307796478,48.7675094604],"type":"Point"}
}