{
  "type": "Feature",
  "properties": {
    "iso:country":"DE",
    "sg:address":"Saarlandstr. 180",
    "sg:city":"Bingen",
    "sg:phone":"+49 6721/41999",
    "sg:postcode":"55411",
    "sg:province":"Rheinland-Pfalz",
    "wof:name":"Werner Gr\u00fcnewald Architekt",
    "wof:placetype":"venue"
},
  "geometry": {"coordinates":[7.911984,49.949417],"type":"Point"}
}