{
  "type": "Feature",
  "properties": {
    "iso:country":"DE",
    "sg:address":"Biebricher Allee 5",
    "sg:city":"Wiesbaden",
    "sg:phone":"+49 611/85356",
    "sg:postcode":"65187",
    "sg:province":"Hessen",
    "wof:name":"Gabriele Hermes-lennich Rechtsanw\u00e4ltin",
    "wof:placetype":"venue"
},
  "geometry": {"coordinates":[8.239947319,50.0695762634],"type":"Point"}
}