{
  "type": "Feature",
  "properties": {
    "iso:country":"DE",
    "sg:address":"Bucher Hauptstr. 111",
    "sg:city":"N\u00fcrnberg",
    "sg:phone":"+49 911/383003",
    "sg:postcode":"90427",
    "sg:province":"Bayern",
    "wof:name":"G. Lohbauer Industrie- Vertretungen Gmbh",
    "wof:placetype":"venue"
},
  "geometry": {"coordinates":[11.0437059402,49.5003013611],"type":"Point"}
}