{
  "type": "Feature",
  "properties": {
    "iso:country":"DE",
    "sg:address":"Erfurterstrasse19",
    "sg:city":"Stotternheim",
    "sg:postcode":"99195",
    "sg:province":"Th\u00fcringen",
    "wof:name":"Heizung-sanit\u00e4r",
    "wof:placetype":"venue"
},
  "geometry": {"coordinates":[11.1014146805,51.0913963318],"type":"Point"}
}