{
  "type": "Feature",
  "properties": {
    "iso:country":"DE",
    "sg:address":"Lindauer Str. 3",
    "sg:city":"Kaufbeuren",
    "sg:phone":"+49 8341/5161",
    "sg:postcode":"87600",
    "sg:province":"Bayern",
    "wof:name":"M. Kosok",
    "wof:placetype":"venue"
},
  "geometry": {"coordinates":[10.602444,47.873123],"type":"Point"}
}