{
  "type": "Feature",
  "properties": {
    "iso:country":"DE",
    "sg:address":"Marbacher Str 107",
    "sg:city":"D\u00fcsseldorf",
    "sg:phone":"+49 211/998188",
    "sg:postcode":"40597",
    "sg:province":"Nordrhein-Westfalen",
    "wof:name":"Techlog Gbr",
    "wof:placetype":"venue"
},
  "geometry": {"coordinates":[6.859521,51.164394],"type":"Point"}
}