{
  "type": "Feature",
  "properties": {
    "iso:country":"DE",
    "sg:address":"Georg-Sch\u00e4fer-Siedlung 72",
    "sg:city":"Ebern",
    "sg:phone":"+49 9531/6448",
    "sg:postcode":"96106",
    "sg:province":"Bayern",
    "wof:name":"E. Becht Und Baum\u00fcller-becht",
    "wof:placetype":"venue"
},
  "geometry": {"coordinates":[10.795050621,50.1013450623],"type":"Point"}
}