{
  "type": "Feature",
  "properties": {
    "iso:country":"DE",
    "sg:address":"Rasengasse 11",
    "sg:city":"Willingshausen",
    "sg:phone":"+49 6691/4823",
    "sg:postcode":"34628",
    "sg:province":"Hessen",
    "wof:name":"Heinrich Hoos",
    "wof:placetype":"venue"
},
  "geometry": {"coordinates":[9.196523,50.849682],"type":"Point"}
}