{
  "type": "Feature",
  "properties": {
    "iso:country":"DE",
    "sg:address":"Niederwall 23",
    "sg:city":"Bielefeld",
    "sg:phone":"+49 521/179537",
    "sg:postcode":"33602",
    "sg:province":"Nordrhein-Westfalen",
    "wof:name":"Ingrid Riedel",
    "wof:placetype":"venue"
},
  "geometry": {"coordinates":[8.5349206924,52.0206947327],"type":"Point"}
}