{
  "type": "Feature",
  "properties": {
    "iso:country":"DE",
    "sg:address":"Albert-Neupert-Str. 6",
    "sg:city":"Staffelstein",
    "sg:phone":"+49 9573/96660",
    "sg:postcode":"96231",
    "sg:province":"Bayern",
    "wof:name":"Steinwerke Kaider Albert Neupert",
    "wof:placetype":"venue"
},
  "geometry": {"coordinates":[10.9991750717,50.1024131775],"type":"Point"}
}