{
  "type": "Feature",
  "properties": {
    "iso:country":"DE",
    "sg:address":"Friedrichstr. 6",
    "sg:city":"Villingen-Schwenningen",
    "sg:phone":"+49 7721/53030",
    "sg:postcode":"78050",
    "sg:province":"Baden-W\u00fcrttemberg",
    "wof:name":"R\u00fcdiger Sturm",
    "wof:placetype":"venue"
},
  "geometry": {"coordinates":[8.463399,48.060665],"type":"Point"}
}