{
  "type": "Feature",
  "properties": {
    "iso:country":"DE",
    "sg:address":"Sachsenwaldstr. 5",
    "sg:city":"Kuddew\u00f6rde",
    "sg:phone":"+49 4154/82216",
    "sg:postcode":"22958",
    "sg:province":"Schleswig-Holstein",
    "wof:name":"H. Reimers",
    "wof:placetype":"venue"
},
  "geometry": {"coordinates":[10.392056,53.578457],"type":"Point"}
}