{
  "type": "Feature",
  "properties": {
    "iso:country":"DE",
    "sg:address":"Lindenstr. 15",
    "sg:city":"Ellwangen",
    "sg:phone":"+49 7961/562356",
    "sg:postcode":"73479",
    "sg:province":"Baden-W\u00fcrttemberg",
    "wof:name":"Grupp Malerfachbetrieb E. K.",
    "wof:placetype":"venue"
},
  "geometry": {"coordinates":[10.112121582,48.975982666],"type":"Point"}
}