{
  "type": "Feature",
  "properties": {
    "iso:country":"DE",
    "sg:address":"M\u00fcnsterstr. 38",
    "sg:city":"D\u00fclmen",
    "sg:phone":"+49 2594/7860",
    "sg:postcode":"48249",
    "sg:province":"Nordrhein-Westfalen",
    "wof:name":"Spar- Und Darlehnskasse Eg",
    "wof:placetype":"venue"
},
  "geometry": {"coordinates":[7.27984,51.831417],"type":"Point"}
}