{
  "type": "Feature",
  "properties": {
    "iso:country":"DE",
    "sg:address":"Stephanstr. 14",
    "sg:city":"Westerland",
    "sg:phone":"+49 4651/82300",
    "sg:postcode":"25980",
    "sg:province":"Schleswig-Holstein",
    "wof:name":"H. Klamann K.-h. Antrick",
    "wof:placetype":"venue"
},
  "geometry": {"coordinates":[8.3068723679,54.910572052],"type":"Point"}
}