{
  "type": "Feature",
  "properties": {
    "iso:country":"DE",
    "sg:address":"Nordring 8",
    "sg:city":"Hannover",
    "sg:phone":"+49 511/963930",
    "sg:postcode":"30163",
    "sg:province":"Niedersachsen",
    "wof:name":"Gardemann Arbeitsb\u00fchnen-vermietung Gmbh",
    "wof:placetype":"venue"
},
  "geometry": {"coordinates":[9.7451190948,52.4039344788],"type":"Point"}
}