{
  "type": "Feature",
  "properties": {
    "iso:country":"DE",
    "sg:address":"Pfarrer-Baumann-Str. 21",
    "sg:city":"Oberaurach",
    "sg:phone":"+49 9529/220",
    "sg:postcode":"97514",
    "sg:province":"Bayern",
    "wof:name":"Pension Hermann Zenglein",
    "wof:placetype":"venue"
},
  "geometry": {"coordinates":[10.597148,49.948082],"type":"Point"}
}