{
  "type": "Feature",
  "properties": {
    "iso:country":"DE",
    "sg:address":"S\u00fcdrg. 29",
    "sg:city":"Bitburg",
    "sg:phone":"+49 4965/6195710",
    "sg:postcode":"54634",
    "sg:province":"Rheinland-Pfalz",
    "wof:name":"Alfred Kotz Kg",
    "wof:placetype":"venue"
},
  "geometry": {"coordinates":[6.529748,49.960312],"type":"Point"}
}