{
  "type": "Feature",
  "properties": {
    "iso:country":"DE",
    "sg:address":"Humboldtstr. 36",
    "sg:city":"Leinfelden-Echterdingen",
    "sg:postcode":"70771",
    "sg:province":"Baden-W\u00fcrttemberg",
    "wof:name":"Icpdas-europe Gmbh",
    "wof:placetype":"venue"
},
  "geometry": {"coordinates":[9.1605710983,48.6948852539],"type":"Point"}
}