{
  "type": "Feature",
  "properties": {
    "iso:country":"DE",
    "sg:address":"Hanserfeldstr. 7",
    "sg:city":"Rosenheim",
    "sg:phone":"+49 8031/88848",
    "sg:postcode":"83024",
    "sg:province":"Bayern",
    "wof:name":"Sebastian Gschwendtner",
    "wof:placetype":"venue"
},
  "geometry": {"coordinates":[12.112847,47.882107],"type":"Point"}
}