{
  "type": "Feature",
  "properties": {
    "iso:country":"DE",
    "sg:address":"Nageler Str. 3",
    "sg:city":"K\u00fcps",
    "sg:postcode":"96328",
    "sg:province":"Bayern",
    "wof:name":"Lucini Gmbh",
    "wof:placetype":"venue"
},
  "geometry": {"coordinates":[11.25663,50.187077],"type":"Point"}
}