{
  "type": "Feature",
  "properties": {
    "iso:country":"DE",
    "sg:address":"Alte Bundesstr. 3",
    "sg:city":"Rees",
    "sg:phone":"+49 2874/800",
    "sg:postcode":"46459",
    "sg:province":"Nordrhein-Westfalen",
    "wof:name":"Elektro Reinh. Ehringfeld Gmbh",
    "wof:placetype":"venue"
},
  "geometry": {"coordinates":[6.486436,51.811344],"type":"Point"}
}