{
  "type": "Feature",
  "properties": {
    "iso:country":"DE",
    "sg:address":"Riesaer Landstr. 12",
    "sg:city":"Gro\u00dfenhain",
    "sg:phone":"+49 3522/503962",
    "sg:postcode":"01561",
    "sg:province":"Sachsen",
    "wof:name":"Restaurant Marone",
    "wof:placetype":"venue"
},
  "geometry": {"coordinates":[13.506151,51.287525],"type":"Point"}
}