{
  "type": "Feature",
  "properties": {
    "iso:country":"DE",
    "sg:address":"\u00c4u\u00dfere Industriestr. 8b",
    "sg:city":"Friedberg",
    "sg:phone":"+49 821/783361",
    "sg:postcode":"86316",
    "sg:province":"Bayern",
    "wof:name":"Erwin H\u00f6fle",
    "wof:placetype":"venue"
},
  "geometry": {"coordinates":[10.95917,48.408516],"type":"Point"}
}