{
  "type": "Feature",
  "properties": {
    "iso:country":"DE",
    "sg:address":"Gewerbestr.",
    "sg:city":"Kroppach",
    "sg:phone":"+49 2688/8026",
    "sg:postcode":"57612",
    "sg:province":"Rheinland-Pfalz",
    "wof:name":"Meso Touristik Gmbh",
    "wof:placetype":"venue"
},
  "geometry": {"coordinates":[7.7292819023,50.6865119934],"type":"Point"}
}