{
  "type": "Feature",
  "properties": {
    "iso:country":"DE",
    "sg:address":"Bebelstr. 20",
    "sg:city":"Trittau",
    "sg:phone":"+49 4154/81913",
    "sg:postcode":"22946",
    "sg:province":"Schleswig-Holstein",
    "wof:name":"K. Jan\u00dfen",
    "wof:placetype":"venue"
},
  "geometry": {"coordinates":[10.399464,53.621964],"type":"Point"}
}