{
  "type": "Feature",
  "properties": {
    "iso:country":"DE",
    "sg:address":"Gro\u00dfe Str.",
    "sg:city":"Ahrensburg",
    "sg:phone":"+49 4102/57989",
    "sg:postcode":"22926",
    "sg:province":"Schleswig-Holstein",
    "wof:name":"Friedhelm Reich",
    "wof:placetype":"venue"
},
  "geometry": {"coordinates":[10.240032196,53.6766242981],"type":"Point"}
}