{
  "type": "Feature",
  "properties": {
    "iso:country":"DE",
    "sg:address":"Kaufstr. 4",
    "sg:city":"Gr\u00fcnkraut",
    "sg:phone":"+49 751/6526417",
    "sg:postcode":"88287",
    "sg:province":"Baden-W\u00fcrttemberg",
    "wof:name":"T. I. G. Gmbh",
    "wof:placetype":"venue"
},
  "geometry": {"coordinates":[9.656995,47.753586],"type":"Point"}
}