{
  "type": "Feature",
  "properties": {
    "iso:country":"DE",
    "sg:address":"Dechbetten 11",
    "sg:city":"Regensburg",
    "sg:phone":"+49 941/35283",
    "sg:postcode":"93051",
    "sg:province":"Bayern",
    "wof:name":"Hotel-restaurant Dechbettener Hof",
    "wof:placetype":"venue"
},
  "geometry": {"coordinates":[12.0601024628,49.0079460144],"type":"Point"}
}