{
  "type": "Feature",
  "properties": {
    "iso:country":"DE",
    "sg:address":"Schimborner Str. 93",
    "sg:city":"H\u00f6sbach",
    "sg:phone":"+49 6024/9565",
    "sg:postcode":"63768",
    "sg:province":"Bayern",
    "wof:name":"Wolfgang Weinmann",
    "wof:placetype":"venue"
},
  "geometry": {"coordinates":[9.2035169601,50.0415649414],"type":"Point"}
}