{
  "type": "Feature",
  "properties": {
    "iso:country":"DE",
    "sg:address":"Spiekerhof 57",
    "sg:city":"D\u00fclmen",
    "sg:phone":"+49 2594/4985",
    "sg:postcode":"48249",
    "sg:province":"Nordrhein-Westfalen",
    "wof:name":"Mgv S\u00e4ngerbund 1888 D\u00fclmen",
    "wof:placetype":"venue"
},
  "geometry": {"coordinates":[7.3009881973,51.834274292],"type":"Point"}
}