{
  "type": "Feature",
  "properties": {
    "iso:country":"DE",
    "sg:address":"Ebertstr. 22",
    "sg:city":"Bergkamen",
    "sg:phone":"+49 2307/983020",
    "sg:postcode":"59192",
    "sg:province":"Nordrhein-Westfalen",
    "wof:name":"Pflegeb\u00fcro Bahrenberg",
    "wof:placetype":"venue"
},
  "geometry": {"coordinates":[7.635536,51.616409],"type":"Point"}
}