{
  "type": "Feature",
  "properties": {
    "iso:country":"DE",
    "sg:address":"Neuhof 33",
    "sg:city":"Hellenthal",
    "sg:phone":"+49 2448/1548",
    "sg:postcode":"53940",
    "sg:province":"Nordrhein-Westfalen",
    "wof:name":"Djk Udenbreth Manfred Klein",
    "wof:placetype":"venue"
},
  "geometry": {"coordinates":[6.391810894,50.4123458862],"type":"Point"}
}