{
  "type": "Feature",
  "properties": {
    "iso:country":"DE",
    "sg:address":"Am Schafhof 3",
    "sg:city":"Haunetal",
    "sg:phone":"+49 6673/919306",
    "sg:postcode":"36166",
    "sg:province":"Hessen",
    "wof:name":"Wilhelm Lerch",
    "wof:placetype":"venue"
},
  "geometry": {"coordinates":[9.662859,50.741138],"type":"Point"}
}