{
  "type": "Feature",
  "properties": {
    "iso:country":"DE",
    "sg:address":"Theresienplatz 35-36",
    "sg:city":"Straubing",
    "sg:phone":"+49 9421/1378",
    "sg:postcode":"94315",
    "sg:province":"Bayern",
    "wof:name":"Haus Des Kindes Hch. Forchthammer E. K.",
    "wof:placetype":"venue"
},
  "geometry": {"coordinates":[12.5667476654,48.8813095093],"type":"Point"}
}