{
  "type": "Feature",
  "properties": {
    "iso:country":"DE",
    "sg:address":"Heubergweg 18",
    "sg:city":"Tuttlingen",
    "sg:phone":"+49 7461/5358",
    "sg:postcode":"78532",
    "sg:province":"Baden-W\u00fcrttemberg",
    "wof:name":"C. Perez Chirug. Instrumente",
    "wof:placetype":"venue"
},
  "geometry": {"coordinates":[8.813682,47.994247],"type":"Point"}
}