{
  "type": "Feature",
  "properties": {
    "iso:country":"DE",
    "sg:address":"Pfarrer-Sailer-Str. 8",
    "sg:city":"Reut",
    "sg:phone":"+49 8572/639",
    "sg:postcode":"84367",
    "sg:province":"Bayern",
    "wof:name":"Fr. Jetzlsberger",
    "wof:placetype":"venue"
},
  "geometry": {"coordinates":[12.9280691147,48.276134491],"type":"Point"}
}