{
  "type": "Feature",
  "properties": {
    "iso:country":"DE",
    "sg:address":"Max-Eyth-Str. 8",
    "sg:city":"Kornwestheim",
    "sg:phone":"+49 7154/5051",
    "sg:postcode":"70806",
    "sg:province":"Baden-W\u00fcrttemberg",
    "wof:name":"Sts Schwei\u00dftechnische Anlagen Gmbh",
    "wof:placetype":"venue"
},
  "geometry": {"coordinates":[9.179704,48.879742],"type":"Point"}
}