{
  "type": "Feature",
  "properties": {
    "iso:country":"DE",
    "sg:address":"Glonner Str. 34d",
    "sg:city":"Putzbrunn",
    "sg:phone":"+49 89/46200534",
    "sg:postcode":"85640",
    "sg:province":"Bayern",
    "wof:name":"Imfa Gmbh",
    "wof:placetype":"venue"
},
  "geometry": {"coordinates":[11.7183237076,48.0747642517],"type":"Point"}
}