{
  "type": "Feature",
  "properties": {
    "iso:country":"DE",
    "sg:address":"Rahmedestr. 299",
    "sg:city":"Altena",
    "sg:phone":"+49 2352/52276",
    "sg:postcode":"58762",
    "sg:province":"Nordrhein-Westfalen",
    "wof:name":"Hermann Hundt",
    "wof:placetype":"venue"
},
  "geometry": {"coordinates":[7.664376,51.257858],"type":"Point"}
}