{
  "type": "Feature",
  "properties": {
    "iso:country":"DE",
    "sg:address":"Schneeberger Weg 25",
    "sg:city":"Schlema",
    "sg:phone":"+49 3772/20614",
    "sg:postcode":"08301",
    "sg:province":"Sachsen",
    "wof:name":"Hotel Sachsenhof",
    "wof:placetype":"venue"
},
  "geometry": {"coordinates":[12.653673172,50.6006736755],"type":"Point"}
}