{
  "type": "Feature",
  "properties": {
    "iso:country":"DE",
    "sg:address":"Else-Kroner Strasse",
    "sg:city":"Bad Homburg",
    "sg:phone":"+49 4962/01800",
    "sg:postcode":"61346",
    "wof:name":"Freudenberg & Co. Kommanditgesellschaft",
    "wof:placetype":"venue"
},
  "geometry": {"coordinates":[8.6640281677,49.5544281006],"type":"Point"}
}