{
  "type": "Feature",
  "properties": {
    "iso:country":"DE",
    "sg:address":"Am Wasser 6",
    "sg:city":"Wernigerode",
    "sg:phone":"+49 3943/21322",
    "sg:postcode":"38855",
    "sg:province":"Sachsen-Anhalt",
    "wof:name":"Peter Wetzel",
    "wof:placetype":"venue"
},
  "geometry": {"coordinates":[10.825174,51.866108],"type":"Point"}
}