{
  "type": "Feature",
  "properties": {
    "iso:country":"DE",
    "sg:address":"Lutherstr. 16",
    "sg:city":"Sinn",
    "sg:phone":"+49 2772/944211",
    "sg:postcode":"35764",
    "sg:province":"Hessen",
    "wof:name":"Graubner",
    "wof:placetype":"venue"
},
  "geometry": {"coordinates":[8.3331003189,50.6499786377],"type":"Point"}
}