{
  "type": "Feature",
  "properties": {
    "iso:country":"DE",
    "sg:address":"Kirchstr. 16",
    "sg:city":"Rheinm\u00fcnster",
    "sg:phone":"+49 7227/3432",
    "sg:postcode":"77836",
    "sg:province":"Baden-W\u00fcrttemberg",
    "wof:name":"L\u00f6wen",
    "wof:placetype":"venue"
},
  "geometry": {"coordinates":[8.0599346161,48.7782249451],"type":"Point"}
}