{
  "type": "Feature",
  "properties": {
    "iso:country":"DE",
    "sg:address":"Heimhuder Str. 21",
    "sg:city":"Hamburg",
    "sg:phone":"+49 40/4502170",
    "sg:postcode":"20148",
    "sg:province":"Hamburg",
    "wof:name":"Kasto Maschinenbau Gmbh & Co. Kg",
    "wof:placetype":"venue"
},
  "geometry": {"coordinates":[9.9924812317,53.565322876],"type":"Point"}
}