{
  "type": "Feature",
  "properties": {
    "iso:country":"DE",
    "sg:address":"M\u00fcllerweg 9",
    "sg:city":"Goldberg",
    "sg:phone":"+49 38736/41172",
    "sg:postcode":"19399",
    "sg:province":"Mecklenburg-Vorpommern",
    "wof:name":"Bestattungsdienst Goldberg Dieter Schuldt",
    "wof:placetype":"venue"
},
  "geometry": {"coordinates":[12.091489,53.593727],"type":"Point"}
}