{
  "type": "Feature",
  "properties": {
    "iso:country":"DE",
    "sg:address":"Hafenstr. 115",
    "sg:city":"Bremerhaven",
    "sg:postcode":"27576",
    "sg:province":"Bremen",
    "wof:name":"F & F Computersysteme Inh. Bettina Kroner E. K.",
    "wof:placetype":"venue"
},
  "geometry": {"coordinates":[8.585149,53.557831],"type":"Point"}
}