{
  "type": "Feature",
  "properties": {
    "iso:country":"DE",
    "sg:address":"W\u00f6hlerstr. 2",
    "sg:city":"Hamburg",
    "sg:phone":"+49 40/731870",
    "sg:postcode":"22113",
    "sg:province":"Schleswig-Holstein",
    "wof:name":"Hotel B\u00f6ttcherhof",
    "wof:placetype":"venue"
},
  "geometry": {"coordinates":[10.0832118988,53.5371055603],"type":"Point"}
}