{
  "type": "Feature",
  "properties": {
    "iso:country":"DE",
    "sg:address":"Schaardeich 63",
    "sg:city":"Wilhelmshaven",
    "sg:phone":"+49 4421/72479",
    "sg:postcode":"26389",
    "sg:province":"Niedersachsen",
    "wof:name":"Wilfried Langenhorst",
    "wof:placetype":"venue"
},
  "geometry": {"coordinates":[8.06624,53.531349],"type":"Point"}
}