{
  "type": "Feature",
  "properties": {
    "iso:country":"DE",
    "sg:address":"Ostmarkstr. 10",
    "sg:city":"M\u00fcnster",
    "sg:phone":"+49 251/33929",
    "sg:postcode":"48145",
    "sg:province":"Nordrhein-Westfalen",
    "wof:name":"T. Zivotic",
    "wof:placetype":"venue"
},
  "geometry": {"coordinates":[7.646487236,51.9677085876],"type":"Point"}
}