{
  "type": "Feature",
  "properties": {
    "iso:country":"DE",
    "sg:address":"Schulstr. 2",
    "sg:city":"Friedewald",
    "sg:phone":"+49 6629/433",
    "sg:postcode":"36289",
    "sg:province":"Hessen",
    "wof:name":"Gastst\u00e4tte Gerhard Bock",
    "wof:placetype":"venue"
},
  "geometry": {"coordinates":[9.8583898544,50.8508605957],"type":"Point"}
}