{
  "type": "Feature",
  "properties": {
    "iso:country":"DE",
    "sg:address":"Cranger Str. 13",
    "sg:city":"Herne",
    "sg:phone":"+49 2323/21434",
    "sg:postcode":"44629",
    "sg:province":"Nordrhein-Westfalen",
    "wof:name":"K. & W. Kaufen-wohnen Baubetreuungs Kg",
    "wof:placetype":"venue"
},
  "geometry": {"coordinates":[7.2052178383,51.5421333313],"type":"Point"}
}