{
  "type": "Feature",
  "properties": {
    "iso:country":"DE",
    "sg:address":"Gryphiusweg 15",
    "sg:city":"Mannheim",
    "sg:phone":"+49 621/784239",
    "sg:postcode":"68307",
    "sg:province":"Baden-W\u00fcrttemberg",
    "wof:name":"Oskar Angst",
    "wof:placetype":"venue"
},
  "geometry": {"coordinates":[8.472723,49.541988],"type":"Point"}
}