{
  "type": "Feature",
  "properties": {
    "iso:country":"DE",
    "sg:address":"Weinfeldstr. 7",
    "sg:city":"Wiesbaden",
    "sg:phone":"+49 611/843212",
    "sg:postcode":"65187",
    "sg:province":"Hessen",
    "wof:name":"Klaus Zschiegner Ingenieur",
    "wof:placetype":"venue"
},
  "geometry": {"coordinates":[8.2318687439,50.0596961975],"type":"Point"}
}