{
  "type": "Feature",
  "properties": {
    "iso:country":"DE",
    "sg:address":"Hauptstr. 23",
    "sg:city":"Ro\u00dfhaupten",
    "sg:phone":"+49 8367/881",
    "sg:postcode":"87672",
    "sg:province":"Bayern",
    "wof:name":"Raiffeisenbank Ro\u00dfhaupten-halblech, Eg",
    "wof:placetype":"venue"
},
  "geometry": {"coordinates":[10.718727,47.652313],"type":"Point"}
}