{
  "type": "Feature",
  "properties": {
    "iso:country":"DE",
    "sg:address":"Friederikenstr. 38",
    "sg:city":"Papenburg",
    "sg:phone":"+49 4961/5633",
    "sg:postcode":"26871",
    "sg:province":"Niedersachsen",
    "wof:name":"Imbiss Sultan",
    "wof:placetype":"venue"
},
  "geometry": {"coordinates":[7.3893580437,53.077091217],"type":"Point"}
}