{
  "type": "Feature",
  "properties": {
    "iso:country":"DE",
    "sg:address":"Viktoriastr. 15",
    "sg:city":"Wilhelmshaven",
    "sg:phone":"+49 4421/41818",
    "sg:postcode":"26382",
    "sg:province":"Niedersachsen",
    "wof:name":"Gorch-fock-haus",
    "wof:placetype":"venue"
},
  "geometry": {"coordinates":[8.1201753616,53.5229187012],"type":"Point"}
}