{
  "type": "Feature",
  "properties": {
    "iso:country":"DE",
    "sg:address":"Kurhausstr. 1",
    "sg:city":"Kampen",
    "sg:phone":"+49 4651/4951",
    "sg:postcode":"25999",
    "sg:province":"Schleswig-Holstein",
    "wof:name":"Il Ristorante Hamed Kabbani E. K.",
    "wof:placetype":"venue"
},
  "geometry": {"coordinates":[8.3415193558,54.9565544128],"type":"Point"}
}