{
  "type": "Feature",
  "properties": {
    "iso:country":"DE",
    "sg:address":"Rothmundstr. 5",
    "sg:city":"M\u00fcnchen",
    "sg:phone":"+49 89/535015",
    "sg:postcode":"80337",
    "sg:province":"Bayern",
    "wof:name":"Gastst\u00e4tte Rothmund Gmbh",
    "wof:placetype":"venue"
},
  "geometry": {"coordinates":[11.5626821518,48.1305503845],"type":"Point"}
}