{
  "type": "Feature",
  "properties": {
    "iso:country":"DE",
    "sg:address":"Harnackstr. 24",
    "sg:city":"Biederitz",
    "sg:phone":"+49 39292/66987",
    "sg:postcode":"39175",
    "sg:province":"Sachsen-Anhalt",
    "wof:name":"Zur Alten F\u00f6rsterei",
    "wof:placetype":"venue"
},
  "geometry": {"coordinates":[11.71434021,52.1558532715],"type":"Point"}
}