{
  "type": "Feature",
  "properties": {
    "iso:country":"DE",
    "sg:address":"Oelixdorfer Str. 2",
    "sg:city":"Itzehoe",
    "sg:phone":"+49 4821/940388",
    "sg:postcode":"25524",
    "sg:province":"Schleswig-Holstein",
    "wof:name":"B. Reinholz",
    "wof:placetype":"venue"
},
  "geometry": {"coordinates":[9.530054,53.924583],"type":"Point"}
}