{
  "type": "Feature",
  "properties": {
    "iso:country":"DE",
    "sg:address":"M\u00fchlrain 68",
    "sg:city":"Stuttgart",
    "sg:phone":"+49 711/6400388",
    "sg:postcode":"70180",
    "sg:province":"Baden-W\u00fcrttemberg",
    "wof:name":"Docsystems Gmbh",
    "wof:placetype":"venue"
},
  "geometry": {"coordinates":[9.171759,48.759087],"type":"Point"}
}