{
  "type": "Feature",
  "properties": {
    "iso:country":"DE",
    "sg:address":"Delippengasse 6",
    "sg:city":"Altshausen",
    "sg:phone":"+49 7584/1619",
    "sg:postcode":"88361",
    "sg:province":"Baden-W\u00fcrttemberg",
    "wof:name":"Traube",
    "wof:placetype":"venue"
},
  "geometry": {"coordinates":[9.5343503952,47.9347267151],"type":"Point"}
}