{
  "type": "Feature",
  "properties": {
    "iso:country":"DE",
    "sg:address":"Kaiser-Friedrich-Str. 112",
    "sg:city":"Neuss",
    "sg:phone":"+49 2131/274600",
    "sg:postcode":"41460",
    "sg:province":"Nordrhein-Westfalen",
    "wof:name":"Bookline-buchversand",
    "wof:placetype":"venue"
},
  "geometry": {"coordinates":[6.6862468719,51.1943092346],"type":"Point"}
}