{
  "type": "Feature",
  "properties": {
    "iso:country":"DE",
    "sg:address":"Goethestr. 57",
    "sg:city":"Geusa",
    "sg:phone":"+49 3461/507411",
    "sg:postcode":"06217",
    "sg:province":"Sachsen-Anhalt",
    "wof:name":"Z\u00e4tzsch Bau Gmbh",
    "wof:placetype":"venue"
},
  "geometry": {"coordinates":[11.9539518356,51.3376655579],"type":"Point"}
}