{
  "type": "Feature",
  "properties": {
    "iso:country":"DE",
    "sg:address":"Loschwitzer Str. 41",
    "sg:city":"Dresden",
    "sg:postcode":"01309",
    "sg:province":"Sachsen",
    "wof:name":"Smc Generalbau Und Projekt- Entwicklungsges. Mbh",
    "wof:placetype":"venue"
},
  "geometry": {"coordinates":[13.800515,51.052876],"type":"Point"}
}