{
  "type": "Feature",
  "properties": {
    "iso:country":"DE",
    "sg:address":"Osterholzstr. 45",
    "sg:city":"Kassel",
    "sg:phone":"+49 561/50847",
    "sg:postcode":"34123",
    "sg:province":"Hessen",
    "wof:name":"S.t.l. Kassel Spedition Transport Und Logistik Gmbh",
    "wof:placetype":"venue"
},
  "geometry": {"coordinates":[9.5377502441,51.3081932068],"type":"Point"}
}