{
  "type": "Feature",
  "properties": {
    "iso:country":"DE",
    "sg:address":"Klosterstr. 49",
    "sg:city":"Unna",
    "sg:phone":"+49 2303/21436",
    "sg:postcode":"59423",
    "sg:province":"Nordrhein-Westfalen",
    "wof:name":"Peter Ehlert",
    "wof:placetype":"venue"
},
  "geometry": {"coordinates":[7.687702179,51.5360183716],"type":"Point"}
}