{
  "type": "Feature",
  "properties": {
    "iso:country":"DE",
    "sg:address":"Mittelbergstr. 39",
    "sg:city":"Ettlingen",
    "sg:phone":"+49 7243/526090",
    "sg:postcode":"76275",
    "sg:province":"Baden-W\u00fcrttemberg",
    "wof:name":"Bechert Gmbh",
    "wof:placetype":"venue"
},
  "geometry": {"coordinates":[8.4132099152,48.892326355],"type":"Point"}
}