{
  "type": "Feature",
  "properties": {
    "iso:country":"DE",
    "sg:address":"Henschelring 2",
    "sg:city":"Kirchheim",
    "sg:phone":"+49 89/9037504",
    "sg:postcode":"85551",
    "sg:province":"Bayern",
    "wof:name":"Big B\u00fcromaschinen Gmbh",
    "wof:placetype":"venue"
},
  "geometry": {"coordinates":[11.7659883499,48.1757698059],"type":"Point"}
}