{
  "type": "Feature",
  "properties": {
    "iso:country":"DE",
    "sg:address":"Zur Gau",
    "sg:city":"Mettmann",
    "sg:phone":"+49 2104/13066",
    "sg:postcode":"40822",
    "sg:province":"Nordrhein-Westfalen",
    "wof:name":"Sport Box Mettmann",
    "wof:placetype":"venue"
},
  "geometry": {"coordinates":[7.0067138672,51.2529182434],"type":"Point"}
}