{
  "type": "Feature",
  "properties": {
    "iso:country":"DE",
    "sg:address":"Kirchplatz 12",
    "sg:city":"Gescher",
    "sg:phone":"+49 2542/1501",
    "sg:postcode":"48712",
    "sg:province":"Nordrhein-Westfalen",
    "wof:name":"Katholisches Pfarramt St. Pankratius",
    "wof:placetype":"venue"
},
  "geometry": {"coordinates":[7.0046348572,51.9566001892],"type":"Point"}
}