{
  "type": "Feature",
  "properties": {
    "iso:country":"DE",
    "sg:address":"Birkenstr. 10",
    "sg:city":"Bonstetten",
    "sg:phone":"+49 8293/1465",
    "sg:postcode":"86486",
    "sg:province":"Bayern",
    "wof:name":"Gustav Kamsa Anlageberater",
    "wof:placetype":"venue"
},
  "geometry": {"coordinates":[10.7161798477,48.4411392212],"type":"Point"}
}