{
  "type": "Feature",
  "properties": {
    "iso:country":"DE",
    "sg:address":"Domplatz 27",
    "sg:city":"M\u00fcnster",
    "sg:phone":"+49 251/4950",
    "sg:postcode":"48143",
    "sg:province":"Nordrhein-Westfalen",
    "wof:name":"Bistum M\u00fcnster",
    "wof:placetype":"venue"
},
  "geometry": {"coordinates":[7.626103878,51.9633750916],"type":"Point"}
}