{
  "type": "Feature",
  "properties": {
    "iso:country":"DE",
    "sg:address":"Neustr. 26",
    "sg:city":"Velbert",
    "sg:phone":"+49 2053/6234",
    "sg:postcode":"42553",
    "sg:province":"Nordrhein-Westfalen",
    "wof:name":"Ihlo Gmbh",
    "wof:placetype":"venue"
},
  "geometry": {"coordinates":[7.0611929893,51.3149681091],"type":"Point"}
}