{
  "type": "Feature",
  "properties": {
    "iso:country":"DE",
    "sg:address":"Heinrich-von-Stephan-Str. 1",
    "sg:city":"G\u00f6ttingen",
    "sg:phone":"+49 551/547270",
    "sg:postcode":"37073",
    "sg:province":"Niedersachsen",
    "wof:name":"Forum F\u00fcr Wissenschaft Und Technik Gemeinn\u00fctzige Gmbh",
    "wof:placetype":"venue"
},
  "geometry": {"coordinates":[9.9288272858,51.5370635986],"type":"Point"}
}