{
  "type": "Feature",
  "properties": {
    "iso:country":"DE",
    "sg:address":"Hauptstr. 94",
    "sg:city":"Dittelbrunn",
    "sg:phone":"+49 9721/45661",
    "sg:postcode":"97456",
    "sg:province":"Bayern",
    "wof:name":"Erich Hespelein",
    "wof:placetype":"venue"
},
  "geometry": {"coordinates":[10.220811,50.07616],"type":"Point"}
}