{
  "type": "Feature",
  "properties": {
    "iso:country":"DE",
    "sg:address":"Kohrstr. 123",
    "sg:city":"M\u00f6nchengladbach",
    "sg:phone":"+49 2166/17422",
    "sg:postcode":"41199",
    "sg:province":"Nordrhein-Westfalen",
    "wof:name":"R. L\u00fcpges Heissmangelbetrieb",
    "wof:placetype":"venue"
},
  "geometry": {"coordinates":[6.4418058395,51.1462974548],"type":"Point"}
}