{
  "type": "Feature",
  "properties": {
    "iso:country":"DE",
    "sg:address":"Lorenz-Zierl-Str. 4",
    "sg:city":"Furth im Wald",
    "sg:phone":"+49 9973/9237",
    "sg:postcode":"93437",
    "sg:province":"Bayern",
    "wof:name":"Bernhard Reichenberger",
    "wof:placetype":"venue"
},
  "geometry": {"coordinates":[12.8425540924,49.3077697754],"type":"Point"}
}