{
  "type": "Feature",
  "properties": {
    "iso:country":"DE",
    "sg:address":"Hans-Holbein-Str. 4",
    "sg:city":"Meckenbeuren",
    "sg:phone":"+49 7542/4756",
    "sg:postcode":"88074",
    "sg:province":"Baden-W\u00fcrttemberg",
    "wof:name":"E. Ebentheur",
    "wof:placetype":"venue"
},
  "geometry": {"coordinates":[9.5652160645,47.6966094971],"type":"Point"}
}