{
  "type": "Feature",
  "properties": {
    "iso:country":"DE",
    "sg:address":"Am Springborn 1",
    "sg:city":"K\u00f6ln",
    "sg:phone":"+49 221/642002",
    "sg:postcode":"51063",
    "sg:province":"Nordrhein-Westfalen",
    "wof:name":"Sauerstein Gmbh",
    "wof:placetype":"venue"
},
  "geometry": {"coordinates":[7.025797,50.975876],"type":"Point"}
}