{
  "type": "Feature",
  "properties": {
    "iso:country":"DE",
    "sg:address":"Kaistr. 5-6",
    "sg:city":"Bremerhaven",
    "sg:postcode":"27570",
    "sg:province":"Bremen",
    "wof:name":"Ausgleichs- Und B\u00fcrger- Gesellschaft Im Heim- Und",
    "wof:placetype":"venue"
},
  "geometry": {"coordinates":[8.587225914,53.5340881348],"type":"Point"}
}