{
  "type": "Feature",
  "properties": {
    "iso:country":"DE",
    "sg:address":"Emsstr. 15",
    "sg:city":"Telgte",
    "sg:phone":"+49 2504/77329",
    "sg:postcode":"48291",
    "sg:province":"Nordrhein-Westfalen",
    "wof:name":"Takko",
    "wof:placetype":"venue"
},
  "geometry": {"coordinates":[7.787121,51.983887],"type":"Point"}
}