{
  "type": "Feature",
  "properties": {
    "iso:country":"DE",
    "sg:address":"Untergasse 7",
    "sg:city":"Hangen-Weisheim",
    "sg:phone":"+49 6735/8124",
    "sg:postcode":"55234",
    "sg:province":"Rheinland-Pfalz",
    "wof:name":"R. Sch\u00fcrer Immobilienmakler",
    "wof:placetype":"venue"
},
  "geometry": {"coordinates":[8.185382843,49.7097434998],"type":"Point"}
}