{
  "type": "Feature",
  "properties": {
    "iso:country":"DE",
    "sg:address":"Hornungstr. 22",
    "sg:city":"Augsburg",
    "sg:postcode":"86161",
    "sg:province":"Bayern",
    "wof:name":"Dr. Bernd D. Pioch Rechtsanwalt",
    "wof:placetype":"venue"
},
  "geometry": {"coordinates":[10.9261598587,48.3526115417],"type":"Point"}
}