{
  "type": "Feature",
  "properties": {
    "iso:country":"DE",
    "sg:address":"Weserm\u00fcnder Str. 15",
    "sg:city":"D\u00fcsseldorf",
    "sg:phone":"+49 211/390990",
    "sg:postcode":"40221",
    "sg:province":"Nordrhein-Westfalen",
    "wof:name":"B & R Baustoff-handel Und -recycling Gmbh",
    "wof:placetype":"venue"
},
  "geometry": {"coordinates":[6.734849,51.21714],"type":"Point"}
}