{
  "type": "Feature",
  "properties": {
    "iso:country":"DE",
    "sg:address":"Winzerstr. 8",
    "sg:city":"M\u00fcllheim",
    "sg:phone":"+49 7631/4566",
    "sg:postcode":"79379",
    "sg:province":"Baden-W\u00fcrttemberg",
    "wof:name":"Stimex Inh. Karl-heinz Steiniger",
    "wof:placetype":"venue"
},
  "geometry": {"coordinates":[7.654445,47.833206],"type":"Point"}
}