{
  "type": "Feature",
  "properties": {
    "iso:country":"DE",
    "sg:address":"Berckhauserstr. 7",
    "sg:city":"N\u00fcrnberg",
    "sg:phone":"+49 911/355894",
    "sg:postcode":"90409",
    "sg:province":"Bayern",
    "wof:name":"Alfred Mo\u00dfner",
    "wof:placetype":"venue"
},
  "geometry": {"coordinates":[11.088869,49.463856],"type":"Point"}
}