{
  "type": "Feature",
  "properties": {
    "iso:country":"DE",
    "sg:address":"Werkstr. 1",
    "sg:city":"T\u00f6ging",
    "sg:phone":"+49 8631/391420",
    "sg:postcode":"84513",
    "sg:province":"Bayern",
    "wof:name":"Archiv Der Innwerk Ag",
    "wof:placetype":"venue"
},
  "geometry": {"coordinates":[12.588931,48.253139],"type":"Point"}
}