{
  "type": "Feature",
  "properties": {
    "iso:country":"DE",
    "sg:address":"Dieselstr. 8",
    "sg:city":"Adendorf",
    "sg:phone":"+49 4131/188989",
    "sg:postcode":"21365",
    "sg:province":"Niedersachsen",
    "wof:name":"China Restaurant Jade-palast",
    "wof:placetype":"venue"
},
  "geometry": {"coordinates":[10.4304151535,53.2888565063],"type":"Point"}
}