{
  "type": "Feature",
  "properties": {
    "iso:country":"DE",
    "sg:address":"Goethestr. 12",
    "sg:city":"Duisburg",
    "sg:phone":"+49 2065/57045",
    "sg:postcode":"47226",
    "sg:province":"Nordrhein-Westfalen",
    "wof:name":"Gerbert W\u00f6stefeld Steuerberater",
    "wof:placetype":"venue"
},
  "geometry": {"coordinates":[6.7090768814,51.405002594],"type":"Point"}
}