{
  "type": "Feature",
  "properties": {
    "iso:country":"DE",
    "sg:address":"Neureuter Str. 35",
    "sg:city":"Karlsruhe",
    "sg:phone":"+49 721/564897",
    "sg:postcode":"76185",
    "sg:province":"Baden-W\u00fcrttemberg",
    "wof:name":"D. Miotke",
    "wof:placetype":"venue"
},
  "geometry": {"coordinates":[8.356529,49.023613],"type":"Point"}
}