{
  "type": "Feature",
  "properties": {
    "iso:country":"DE",
    "sg:address":"Sandgasse 9",
    "sg:city":"Deuna",
    "sg:phone":"+49 36076/44751",
    "sg:postcode":"37355",
    "sg:province":"Th\u00fcringen",
    "wof:name":"K.-h. Und Brigitte Hilger",
    "wof:placetype":"venue"
},
  "geometry": {"coordinates":[10.4757423401,51.3541183472],"type":"Point"}
}