{
  "type": "Feature",
  "properties": {
    "iso:country":"DE",
    "sg:address":"H\u00fcvener Str. 46",
    "sg:city":"L\u00e4hden",
    "sg:phone":"+49 5964/313",
    "sg:postcode":"49774",
    "sg:province":"Niedersachsen",
    "wof:name":"Hans Focke",
    "wof:placetype":"venue"
},
  "geometry": {"coordinates":[7.573718,52.762383],"type":"Point"}
}