{
  "type": "Feature",
  "properties": {
    "iso:country":"DE",
    "sg:address":"Keimelstr. 3",
    "sg:city":"Weiden",
    "sg:phone":"+49 961/22269",
    "sg:postcode":"92637",
    "sg:province":"Bayern",
    "wof:name":"Horst Meindl",
    "wof:placetype":"venue"
},
  "geometry": {"coordinates":[12.145588,49.681789],"type":"Point"}
}