{
  "type": "Feature",
  "properties": {
    "iso:country":"DE",
    "sg:address":"Hagenbichl 2",
    "sg:city":"Regen",
    "sg:phone":"+49 9921/2367",
    "sg:postcode":"94209",
    "sg:province":"Bayern",
    "wof:name":"Kath. Pfarramt St. Peter Und Paul",
    "wof:placetype":"venue"
},
  "geometry": {"coordinates":[13.0690507889,48.9760856628],"type":"Point"}
}