{
  "type": "Feature",
  "properties": {
    "iso:country":"DE",
    "sg:address":"Antoniusstr. 3",
    "sg:city":"Mechernich",
    "sg:phone":"+49 2256/950005",
    "sg:postcode":"53894",
    "sg:province":"Nordrhein-Westfalen",
    "wof:name":"Bernd Breuer",
    "wof:placetype":"venue"
},
  "geometry": {"coordinates":[6.6886239052,50.6281280518],"type":"Point"}
}