{
  "type": "Feature",
  "properties": {
    "iso:country":"DE",
    "sg:address":"Max-Planck-Str. 17",
    "sg:city":"Ritterhude",
    "sg:phone":"+49 421/632003",
    "sg:postcode":"27721",
    "sg:province":"Niedersachsen",
    "wof:name":"Wohlert-lackfabrik Gmbh",
    "wof:placetype":"venue"
},
  "geometry": {"coordinates":[8.7019271851,53.1919403076],"type":"Point"}
}