{
  "type": "Feature",
  "properties": {
    "iso:country":"DE",
    "sg:address":"Zur Schiffsl\u00e4nde 11",
    "sg:city":"Konstanz",
    "sg:phone":"+49 7533/5190",
    "sg:postcode":"78465",
    "sg:province":"Baden-W\u00fcrttemberg",
    "wof:name":"Restaurant Seeschau",
    "wof:placetype":"venue"
},
  "geometry": {"coordinates":[9.1571617126,47.7405662537],"type":"Point"}
}