{
  "type": "Feature",
  "properties": {
    "iso:country":"DE",
    "sg:address":"Staufenstr. 42",
    "sg:city":"Frankfurt",
    "sg:phone":"+49 69/9714420",
    "sg:postcode":"60323",
    "sg:province":"Hessen",
    "wof:name":"Curtis Mallet-prevost Und Colt Rechtsanw\u00e4lte",
    "wof:placetype":"venue"
},
  "geometry": {"coordinates":[8.6652364731,50.1188545227],"type":"Point"}
}