{
  "type": "Feature",
  "properties": {
    "iso:country":"DE",
    "sg:address":"Hauptstr. 25",
    "sg:city":"Zittau",
    "sg:phone":"+49 3583/706703",
    "sg:postcode":"02763",
    "sg:province":"Sachsen",
    "wof:name":"Joachim Heidig",
    "wof:placetype":"venue"
},
  "geometry": {"coordinates":[14.7676591873,50.9003486633],"type":"Point"}
}