{
  "type": "Feature",
  "properties": {
    "iso:country":"DE",
    "sg:address":"Peterstr 17",
    "sg:city":"Aachen",
    "sg:phone":"+49 241/477940",
    "sg:postcode":"52062",
    "sg:province":"Nordrhein-Westfalen",
    "wof:name":"Exapt Systemtechnik Gmbh",
    "wof:placetype":"venue"
},
  "geometry": {"coordinates":[6.089894,50.776638],"type":"Point"}
}