{
  "type": "Feature",
  "properties": {
    "iso:country":"DE",
    "sg:address":"Oststr. 7",
    "sg:city":"Obersulm",
    "sg:phone":"+49 7134/3321",
    "sg:postcode":"74182",
    "sg:province":"Baden-W\u00fcrttemberg",
    "wof:name":"H. Kossira Heilpraktiker",
    "wof:placetype":"venue"
},
  "geometry": {"coordinates":[9.3667488098,49.1384239197],"type":"Point"}
}