{
  "type": "Feature",
  "properties": {
    "iso:country":"DE",
    "sg:address":"Sch\u00f6nbergstr. 28",
    "sg:city":"Bad Krozingen",
    "sg:phone":"+49 7633/4339",
    "sg:postcode":"79189",
    "sg:province":"Baden-W\u00fcrttemberg",
    "wof:name":"G. M. Stiehl \u00dcbersetzungsb\u00fcro",
    "wof:placetype":"venue"
},
  "geometry": {"coordinates":[7.711803,47.914612],"type":"Point"}
}