{
  "type": "Feature",
  "properties": {
    "iso:country":"DE",
    "sg:address":"Dr.-Friedrich-Wolf-Str. 10",
    "sg:city":"Gera",
    "sg:phone":"+49 365/839600",
    "sg:postcode":"07545",
    "sg:province":"Th\u00fcringen",
    "wof:name":"Victoria Versicherung Ag",
    "wof:placetype":"venue"
},
  "geometry": {"coordinates":[12.0751419067,50.8745689392],"type":"Point"}
}