{
  "type": "Feature",
  "properties": {
    "iso:country":"DE",
    "sg:address":"Kornstr. 243",
    "sg:city":"Bremen",
    "sg:phone":"+49 4942/1535070",
    "sg:postcode":"28201",
    "sg:province":"Bremen",
    "wof:name":"Bukh Bremen Vertriebsges. Mbh",
    "wof:placetype":"venue"
},
  "geometry": {"coordinates":[8.810998,53.057327],"type":"Point"}
}