{
  "type": "Feature",
  "properties": {
    "iso:country":"DE",
    "sg:address":"Dorfstr. 35 a",
    "sg:city":"Stedten a Ettersberg",
    "sg:postcode":"99439",
    "sg:province":"Th\u00fcringen",
    "wof:name":"Kocik Gmbh",
    "wof:placetype":"venue"
},
  "geometry": {"coordinates":[-123.94465599999999,40.088692],"type":"Point"}
}