{
  "type": "Feature",
  "properties": {
    "iso:country":"DE",
    "sg:address":"Johann-Sebastian-Bach-Str. 32",
    "sg:city":"Weiden",
    "sg:phone":"+49 961/32882",
    "sg:postcode":"92637",
    "sg:province":"Bayern",
    "wof:name":"Sebastian Gallersd\u00f6rfer Immobilienmakler",
    "wof:placetype":"venue"
},
  "geometry": {"coordinates":[12.1752195358,49.6942558289],"type":"Point"}
}