{
  "type": "Feature",
  "properties": {
    "iso:country":"DE",
    "sg:address":"Reinhard-Schiestel-Str. 19",
    "sg:city":"Bexbach",
    "sg:phone":"+49 6826/6868",
    "sg:postcode":"66450",
    "sg:province":"Saarland",
    "wof:name":"Wolfgang Frobin Architekt",
    "wof:placetype":"venue"
},
  "geometry": {"coordinates":[7.258276,49.364738],"type":"Point"}
}