{
  "type": "Feature",
  "properties": {
    "iso:country":"DE",
    "sg:address":"Olgastr. 63",
    "sg:city":"Friedrichshafen",
    "sg:phone":"+49 7541/22398",
    "sg:postcode":"88045",
    "sg:province":"Baden-W\u00fcrttemberg",
    "wof:name":"Beller",
    "wof:placetype":"venue"
},
  "geometry": {"coordinates":[9.4712200165,47.6560821533],"type":"Point"}
}