{
  "type": "Feature",
  "properties": {
    "iso:country":"DE",
    "sg:address":"Schleswiger Str. 85",
    "sg:city":"Flensburg",
    "sg:postcode":"24941",
    "sg:province":"Schleswig-Holstein",
    "wof:name":"Bad & Baden Gmbh",
    "wof:placetype":"venue"
},
  "geometry": {"coordinates":[9.435459137,54.7690658569],"type":"Point"}
}