{
  "type": "Feature",
  "properties": {
    "iso:country":"DE",
    "sg:address":"Weierstr. 41",
    "sg:city":"Mechernich",
    "sg:phone":"+49 2443/31138",
    "sg:postcode":"53894",
    "sg:province":"Nordrhein-Westfalen",
    "wof:name":"Silvia Gehlen",
    "wof:placetype":"venue"
},
  "geometry": {"coordinates":[6.6533479691,50.5907287598],"type":"Point"}
}