{
  "type": "Feature",
  "properties": {
    "iso:country":"DE",
    "sg:address":"Grapengie\u00dferstr. 21",
    "sg:city":"L\u00fcbeck",
    "sg:phone":"+49 4945/189070",
    "sg:postcode":"23556",
    "sg:province":"Schleswig-Holstein",
    "wof:name":"Schuett & Grundei Orthopaedietechnik Gmbh",
    "wof:placetype":"venue"
},
  "geometry": {"coordinates":[10.6341161728,53.8614883423],"type":"Point"}
}