{
  "type": "Feature",
  "properties": {
    "iso:country":"DE",
    "sg:address":"Schulstr. 14",
    "sg:city":"Attenkirchen",
    "sg:phone":"+49 8168/265",
    "sg:postcode":"85395",
    "sg:province":"Bayern",
    "wof:name":"Ernst Barthelme",
    "wof:placetype":"venue"
},
  "geometry": {"coordinates":[11.757709,48.504772],"type":"Point"}
}