{
  "type": "Feature",
  "properties": {
    "iso:country":"DE",
    "sg:address":"B\u00fcnder Str. 93",
    "sg:city":"Hiddenhausen",
    "sg:postcode":"32120",
    "sg:province":"Nordrhein-Westfalen",
    "wof:name":"Mws Gmbh",
    "wof:placetype":"venue"
},
  "geometry": {"coordinates":[8.6483898163,52.1421051025],"type":"Point"}
}