{
  "type": "Feature",
  "properties": {
    "iso:country":"DE",
    "sg:address":"In den Bellen 28",
    "sg:city":"Lingenfeld",
    "sg:phone":"+49 6344/939452",
    "sg:postcode":"67360",
    "sg:province":"Rheinland-Pfalz",
    "wof:name":"Volksf\u00fcrsorge Versicherungen Wolfgang Hirschfeld",
    "wof:placetype":"venue"
},
  "geometry": {"coordinates":[8.3462734222,49.2405509949],"type":"Point"}
}