{
  "type": "Feature",
  "properties": {
    "iso:country":"DE",
    "sg:address":"Kleinenhainer Str. 34",
    "sg:city":"Lintig",
    "sg:phone":"+49 4765/1467",
    "sg:postcode":"27624",
    "sg:province":"Niedersachsen",
    "wof:name":"Bernd P\u00fclsch",
    "wof:placetype":"venue"
},
  "geometry": {"coordinates":[8.9522,53.557133],"type":"Point"}
}