{
  "type": "Feature",
  "properties": {
    "iso:country":"DE",
    "sg:address":"\u00dcrdinger Str. 149",
    "sg:city":"Krefeld",
    "sg:phone":"+49 2151/611398",
    "sg:postcode":"47799",
    "sg:province":"Nordrhein-Westfalen",
    "wof:name":"Hubtex Maschinenbau Gmbh",
    "wof:placetype":"venue"
},
  "geometry": {"coordinates":[6.581114,51.337063],"type":"Point"}
}