{
  "type": "Feature",
  "properties": {
    "iso:country":"DE",
    "sg:address":"Lange Str 57-63",
    "sg:city":"B\u00fcnde",
    "sg:phone":"+49 5223/4091",
    "sg:postcode":"32257",
    "sg:province":"Nordrhein-Westfalen",
    "wof:name":"Ebmeier & Co Gmbh",
    "wof:placetype":"venue"
},
  "geometry": {"coordinates":[8.60147,52.182041],"type":"Point"}
}