{
  "type": "Feature",
  "properties": {
    "iso:country":"DE",
    "sg:address":"Bergheimer Str. 560 a",
    "sg:city":"Neuss",
    "sg:phone":"+49 2131/461062",
    "sg:postcode":"41466",
    "sg:province":"Nordrhein-Westfalen",
    "wof:name":"Ewald Kay",
    "wof:placetype":"venue"
},
  "geometry": {"coordinates":[6.6831831932,51.164276123],"type":"Point"}
}