{
  "type": "Feature",
  "properties": {
    "iso:country":"DE",
    "sg:address":"St\u00f6ckener Str. 65",
    "sg:city":"Hannover",
    "sg:phone":"+49 511/792470",
    "sg:postcode":"30419",
    "sg:province":"Niedersachsen",
    "wof:name":"Friedrich-wilhelm Brackmann",
    "wof:placetype":"venue"
},
  "geometry": {"coordinates":[9.668529,52.400276],"type":"Point"}
}