{
  "type": "Feature",
  "properties": {
    "iso:country":"DE",
    "sg:address":"Mariahilfstr. 33",
    "sg:city":"Aachen",
    "sg:phone":"+49 241/37570",
    "sg:postcode":"52062",
    "sg:province":"Nordrhein-Westfalen",
    "wof:name":"Helmut Frambach",
    "wof:placetype":"venue"
},
  "geometry": {"coordinates":[6.091394,50.779602],"type":"Point"}
}