{
  "type": "Feature",
  "properties": {
    "iso:country":"DE",
    "sg:address":"Lange Str. 53",
    "sg:city":"Rodenberg",
    "sg:phone":"+49 5723/2549",
    "sg:postcode":"31552",
    "sg:province":"Niedersachsen",
    "wof:name":"Textilreinigung Sch\u00f6pf",
    "wof:placetype":"venue"
},
  "geometry": {"coordinates":[9.356675,52.311268],"type":"Point"}
}