{
  "type": "Feature",
  "properties": {
    "iso:country":"DE",
    "sg:address":"Nibelungenstr. 7",
    "sg:city":"Passau",
    "sg:phone":"+49 851/72727",
    "sg:postcode":"94032",
    "sg:province":"Bayern",
    "wof:name":"Rt-reiseb\u00fcro Gmbh",
    "wof:placetype":"venue"
},
  "geometry": {"coordinates":[13.4494562149,48.5717468262],"type":"Point"}
}