{
  "type": "Feature",
  "properties": {
    "iso:country":"DE",
    "sg:address":"Hauptstr. 26",
    "sg:city":"Rutesheim",
    "sg:phone":"+49 7152/52941",
    "sg:postcode":"71277",
    "sg:province":"Baden-W\u00fcrttemberg",
    "wof:name":"Karl Simondet",
    "wof:placetype":"venue"
},
  "geometry": {"coordinates":[8.906408,48.814941],"type":"Point"}
}