{
  "type": "Feature",
  "properties": {
    "iso:country":"DE",
    "sg:address":"Mannheimerstr. 24",
    "sg:city":"Konstanz",
    "sg:phone":"+49 7531/698394",
    "sg:postcode":"78467",
    "sg:province":"Baden-W\u00fcrttemberg",
    "wof:name":"Gesundheit-informationen.net! Das Online Gesundheitsportal.",
    "wof:placetype":"venue"
},
  "geometry": {"coordinates":[9.14319,47.686676],"type":"Point"}
}