{
  "type": "Feature",
  "properties": {
    "iso:country":"DE",
    "sg:address":"P\u00f6deldorfer Str. 73",
    "sg:city":"Bamberg",
    "sg:phone":"+49 951/33183",
    "sg:postcode":"96052",
    "sg:province":"Bayern",
    "wof:name":"Schnellkauf Gmbh",
    "wof:placetype":"venue"
},
  "geometry": {"coordinates":[10.9103899002,49.9005966187],"type":"Point"}
}