{
  "type": "Feature",
  "properties": {
    "iso:country":"DE",
    "sg:address":"Fuggerstr. 11",
    "sg:city":"Bielefeld",
    "sg:phone":"+49 5205/9930",
    "sg:postcode":"33689",
    "sg:province":"Nordrhein-Westfalen",
    "wof:name":"Marktkauf Gesch\u00e4ftsf\u00fchrungsges. Mbh",
    "wof:placetype":"venue"
},
  "geometry": {"coordinates":[8.5624914169,51.944984436],"type":"Point"}
}