{
  "type": "Feature",
  "properties": {
    "iso:country":"DE",
    "sg:address":"Kolpingstr. 26",
    "sg:city":"Dieburg",
    "sg:phone":"+49 6071/22116",
    "sg:postcode":"64807",
    "sg:province":"Hessen",
    "wof:name":"Anita Bind-klinger Heilpraktikerin",
    "wof:placetype":"venue"
},
  "geometry": {"coordinates":[8.842130661,49.8950767517],"type":"Point"}
}