{
  "type": "Feature",
  "properties": {
    "iso:country":"DE",
    "sg:address":"Bahnhofstr. 1-3",
    "sg:city":"Celle",
    "sg:phone":"+49 5141/2790",
    "sg:postcode":"29221",
    "sg:province":"Niedersachsen",
    "wof:name":"Redaktion Anzeiger Schweiger & Pick Verlag",
    "wof:placetype":"venue"
},
  "geometry": {"coordinates":[10.076128006,52.6217880249],"type":"Point"}
}