{
  "type": "Feature",
  "properties": {
    "iso:country":"DE",
    "sg:address":"Badeniastr. 13",
    "sg:city":"Weinheim",
    "sg:phone":"+49 6201/860",
    "sg:postcode":"69469",
    "sg:province":"Baden-W\u00fcrttemberg",
    "wof:name":"Naturin Gmbh & Co.",
    "wof:placetype":"venue"
},
  "geometry": {"coordinates":[8.6636199951,49.5502204895],"type":"Point"}
}