{
  "type": "Feature",
  "properties": {
    "iso:country":"DE",
    "sg:address":"Sperberhorst 19",
    "sg:city":"Hamburg",
    "sg:phone":"+49 40/5511145",
    "sg:postcode":"22459",
    "sg:province":"Hamburg",
    "wof:name":"Gerd Heitmann",
    "wof:placetype":"venue"
},
  "geometry": {"coordinates":[9.9583530426,53.6339530945],"type":"Point"}
}