{
  "type": "Feature",
  "properties": {
    "iso:country":"DE",
    "sg:address":"Am Hegefeld 28",
    "sg:city":"Kl\u00f6tze",
    "sg:postcode":"38486",
    "sg:province":"Sachsen-Anhalt",
    "wof:name":"W. Paul",
    "wof:placetype":"venue"
},
  "geometry": {"coordinates":[11.1748590469,52.6281051636],"type":"Point"}
}