{
  "type": "Feature",
  "properties": {
    "iso:country":"DE",
    "sg:address":"Wachtnitzer Str. 21",
    "sg:city":"Lommatzsch",
    "sg:phone":"+49 35241/52765",
    "sg:postcode":"01623",
    "sg:province":"Sachsen",
    "wof:name":"Lutz Voigt",
    "wof:placetype":"venue"
},
  "geometry": {"coordinates":[13.350367,51.190121],"type":"Point"}
}