{
  "type": "Feature",
  "properties": {
    "iso:country":"DE",
    "sg:address":"Mainzer Str. 10",
    "sg:city":"Tholey",
    "sg:phone":"+49 6853/2814",
    "sg:postcode":"66636",
    "sg:province":"Saarland",
    "wof:name":"Dewes Gmbh",
    "wof:placetype":"venue"
},
  "geometry": {"coordinates":[7.0357041359,49.4773521423],"type":"Point"}
}