{
  "type": "Feature",
  "properties": {
    "iso:country":"DE",
    "sg:address":"Jesuitenstr. 11a",
    "sg:city":"Bad Neuenahr-Ahrweiler",
    "sg:postcode":"53474",
    "sg:province":"Rheinland-Pfalz",
    "wof:name":"Es Bautr\u00e4ger- Und Baubetreuungs Gmbh",
    "wof:placetype":"venue"
},
  "geometry": {"coordinates":[7.140289,50.545315],"type":"Point"}
}