{
  "type": "Feature",
  "properties": {
    "iso:country":"DE",
    "sg:address":"Uhlandstr. 5",
    "sg:city":"Florstadt",
    "sg:phone":"+49 6041/4703",
    "sg:postcode":"61197",
    "sg:province":"Hessen",
    "wof:name":"Werner Winkler Steuerberater",
    "wof:placetype":"venue"
},
  "geometry": {"coordinates":[8.9439096451,50.3311462402],"type":"Point"}
}