{
  "type": "Feature",
  "properties": {
    "iso:country":"DE",
    "sg:address":"Leopoldstr. 18",
    "sg:city":"Pforzheim",
    "sg:phone":"+49 7231/314788",
    "sg:postcode":"75172",
    "sg:province":"Baden-W\u00fcrttemberg",
    "wof:name":"Heinrich M\u00f6ser",
    "wof:placetype":"venue"
},
  "geometry": {"coordinates":[8.6985006332,48.8904304504],"type":"Point"}
}