{
  "type": "Feature",
  "properties": {
    "iso:country":"DE",
    "sg:address":"Hildastr. 4",
    "sg:city":"Offenburg",
    "sg:phone":"+49 781/30187",
    "sg:postcode":"77654",
    "sg:province":"Baden-W\u00fcrttemberg",
    "wof:name":"Piepenbrock Beteiligungs Gmbh & Co. Kg",
    "wof:placetype":"venue"
},
  "geometry": {"coordinates":[7.949789,48.472858],"type":"Point"}
}