{
  "type": "Feature",
  "properties": {
    "iso:country":"DE",
    "sg:address":"Lossaustr. 6",
    "sg:city":"Coburg",
    "sg:phone":"+49 9561/73075",
    "sg:postcode":"96450",
    "sg:province":"Bayern",
    "wof:name":"Avis Autovermietung Agentur E. Vogt",
    "wof:placetype":"venue"
},
  "geometry": {"coordinates":[10.958322,50.262318],"type":"Point"}
}