{
  "type": "Feature",
  "properties": {
    "iso:country":"DE",
    "sg:address":"Lindenthaler Allee 35",
    "sg:city":"Berlin",
    "sg:postcode":"14163",
    "sg:province":"Berlin",
    "wof:name":"Elektro-h\u00f6hlich Gmbh",
    "wof:placetype":"venue"
},
  "geometry": {"coordinates":[13.2296447754,52.4311408997],"type":"Point"}
}