{
  "type": "Feature",
  "properties": {
    "iso:country":"DE",
    "sg:address":"Woorteweg 12",
    "sg:city":"S\u00fcdlohn",
    "sg:phone":"+49 2862/95080",
    "sg:postcode":"46354",
    "sg:province":"Nordrhein-Westfalen",
    "wof:name":"Athleticos Fenster- Und T\u00fcrproduktion Gmbh",
    "wof:placetype":"venue"
},
  "geometry": {"coordinates":[6.817304,51.936298],"type":"Point"}
}