{
  "type": "Feature",
  "properties": {
    "iso:country":"DE",
    "sg:address":"Arster Landstr. 50",
    "sg:city":"Bremen",
    "sg:phone":"+49 421/826555",
    "sg:postcode":"28279",
    "sg:province":"Bremen",
    "wof:name":"Arster Automaten Inh. Klaus D. Grotheer",
    "wof:placetype":"venue"
},
  "geometry": {"coordinates":[8.8506822586,53.0316848755],"type":"Point"}
}