{
  "type": "Feature",
  "properties": {
    "iso:country":"DE",
    "sg:address":"Adenauerring 50",
    "sg:city":"Kempten",
    "sg:phone":"+49 831",
    "sg:postcode":"87439",
    "sg:province":"Bayern",
    "wof:name":"Homepage Von Robert Hornung",
    "wof:placetype":"venue"
},
  "geometry": {"coordinates":[10.3067998886,47.7345428467],"type":"Point"}
}