{
  "type": "Feature",
  "properties": {
    "iso:country":"DE",
    "sg:address":"Karlsbader Str. 3",
    "sg:city":"Herten",
    "sg:phone":"+49 2366/81608",
    "sg:postcode":"45699",
    "sg:province":"Nordrhein-Westfalen",
    "wof:name":"Winfried Hemmerling",
    "wof:placetype":"venue"
},
  "geometry": {"coordinates":[7.1540808678,51.6086578369],"type":"Point"}
}