{
  "type": "Feature",
  "properties": {
    "iso:country":"DE",
    "sg:address":"K\u00f6nigsberger Str. 4",
    "sg:city":"M\u00fcnster-Sarmsheim",
    "sg:phone":"+49 6721/43894",
    "sg:postcode":"55424",
    "sg:province":"Rheinland-Pfalz",
    "wof:name":"G\u00fcnther Meyer",
    "wof:placetype":"venue"
},
  "geometry": {"coordinates":[7.894,49.940327],"type":"Point"}
}