{
  "type": "Feature",
  "properties": {
    "iso:country":"DE",
    "sg:address":"Bahnhofstr. 23",
    "sg:city":"Asperg",
    "sg:phone":"+49 7141/660400",
    "sg:postcode":"71679",
    "sg:province":"Baden-W\u00fcrttemberg",
    "wof:name":"Staiger Immobilien Gmbh",
    "wof:placetype":"venue"
},
  "geometry": {"coordinates":[9.1381778717,48.9060287476],"type":"Point"}
}