{
  "type": "Feature",
  "properties": {
    "iso:country":"DE",
    "sg:address":"Wolfsgangstr. 19",
    "sg:city":"Frankfurt",
    "sg:phone":"+49 69/5971944",
    "sg:postcode":"60322",
    "sg:province":"Hessen",
    "wof:name":"G. Utikal",
    "wof:placetype":"venue"
},
  "geometry": {"coordinates":[8.6794147491,50.1245956421],"type":"Point"}
}