{
  "type": "Feature",
  "properties": {
    "iso:country":"DE",
    "sg:address":"Walder Str. 427",
    "sg:city":"Hilden",
    "sg:phone":"+49 2103/243662",
    "sg:postcode":"40724",
    "sg:province":"Nordrhein-Westfalen",
    "wof:name":"Li Dra Gmbh",
    "wof:placetype":"venue"
},
  "geometry": {"coordinates":[6.983952,51.167858],"type":"Point"}
}