{
  "type": "Feature",
  "properties": {
    "iso:country":"DE",
    "sg:address":"Altreichenau",
    "sg:city":"Altreichenau",
    "sg:phone":"+49 8583/479",
    "sg:postcode":"94089",
    "sg:province":"Bayern",
    "wof:name":"Sparkasse Altreichenau",
    "wof:placetype":"venue"
},
  "geometry": {"coordinates":[13.73078,48.767509],"type":"Point"}
}