{
  "type": "Feature",
  "properties": {
    "iso:country":"DE",
    "sg:city":"Flammersfeld",
    "sg:phone":"+49 2685/7585",
    "sg:postcode":"57632",
    "sg:province":"Rheinland-Pfalz",
    "wof:name":"Burgwinkel",
    "wof:placetype":"venue"
},
  "geometry": {"coordinates":[7.526825,50.648224],"type":"Point"}
}