{
  "type": "Feature",
  "properties": {
    "iso:country":"DE",
    "sg:address":"Fichtenweg 8",
    "sg:city":"Gera",
    "sg:phone":"+49 365/7119707",
    "sg:postcode":"07549",
    "sg:province":"Th\u00fcringen",
    "wof:name":"Michael G\u00f6pel",
    "wof:placetype":"venue"
},
  "geometry": {"coordinates":[12.059164,50.852913],"type":"Point"}
}