{
  "type": "Feature",
  "properties": {
    "iso:country":"DE",
    "sg:address":"Hauptstr. 99a",
    "sg:city":"Oyten",
    "sg:phone":"+49 4207/5997",
    "sg:postcode":"28876",
    "sg:province":"Niedersachsen",
    "wof:name":"Stadtb\u00e4ckerei Stadtkonditorei Harris Stadtlander",
    "wof:placetype":"venue"
},
  "geometry": {"coordinates":[9.01307,53.059345],"type":"Point"}
}