{
  "type": "Feature",
  "properties": {
    "iso:country":"DE",
    "sg:address":"Von-der-Tann-Str. 7",
    "sg:city":"M\u00fcnchen",
    "sg:phone":"+49 89/283218",
    "sg:postcode":"80539",
    "sg:province":"Bayern",
    "wof:name":"Christine Gerber",
    "wof:placetype":"venue"
},
  "geometry": {"coordinates":[11.5810680389,48.1450119019],"type":"Point"}
}