{
  "type": "Feature",
  "properties": {
    "iso:country":"DE",
    "sg:address":"Dorfstr. 4",
    "sg:city":"M\u00fcnsingen",
    "sg:phone":"+49 7381/2082",
    "sg:postcode":"72525",
    "sg:province":"Baden-W\u00fcrttemberg",
    "wof:name":"Reinhold Failenschmid",
    "wof:placetype":"venue"
},
  "geometry": {"coordinates":[9.44897,48.434448],"type":"Point"}
}