{
  "type": "Feature",
  "properties": {
    "iso:country":"DE",
    "sg:address":"Folkenbornstr. 44",
    "sg:city":"M\u00fclheim",
    "sg:phone":"+49 208/490779",
    "sg:postcode":"45472",
    "sg:province":"Nordrhein-Westfalen",
    "wof:name":"Mitzscherling Bedachung Gmbh",
    "wof:placetype":"venue"
},
  "geometry": {"coordinates":[6.91283,51.437691],"type":"Point"}
}