{
  "type": "Feature",
  "properties": {
    "iso:country":"DE",
    "sg:address":"Im Hamm 2",
    "sg:city":"Wesel",
    "sg:phone":"+49 2803/4432",
    "sg:postcode":"46487",
    "sg:province":"Nordrhein-Westfalen",
    "wof:name":"M. Asdonk",
    "wof:placetype":"venue"
},
  "geometry": {"coordinates":[6.584759,51.640968],"type":"Point"}
}