{
  "type": "Feature",
  "properties": {
    "iso:country":"DE",
    "sg:address":"Seedammweg 55",
    "sg:city":"Bad Homburg",
    "sg:postcode":"61352",
    "sg:province":"Hessen",
    "wof:name":"Dat Desktop-systeme Gmbh",
    "wof:placetype":"venue"
},
  "geometry": {"coordinates":[8.6396818161,50.2292175293],"type":"Point"}
}