{
  "type": "Feature",
  "properties": {
    "iso:country":"DE",
    "sg:address":"Kirchgasse 19",
    "sg:city":"Gospiteroda",
    "sg:phone":"+49 3622/66536",
    "sg:postcode":"99880",
    "sg:province":"Th\u00fcringen",
    "wof:name":"Arnfried Schubert",
    "wof:placetype":"venue"
},
  "geometry": {"coordinates":[10.6467542648,50.8892555237],"type":"Point"}
}