{
  "type": "Feature",
  "properties": {
    "iso:country":"DE",
    "sg:address":"B\u00f6hlstr. 38",
    "sg:city":"Neustadt",
    "sg:phone":"+49 6321/12970",
    "sg:postcode":"67433",
    "sg:province":"Rheinland-Pfalz",
    "wof:name":"Guntram Kappes Architekt",
    "wof:placetype":"venue"
},
  "geometry": {"coordinates":[8.156617,49.360184],"type":"Point"}
}