{
  "type": "Feature",
  "properties": {
    "iso:country":"DE",
    "sg:address":"Meisenweg 27",
    "sg:city":"Staig",
    "sg:phone":"+49 7346/3104",
    "sg:postcode":"89195",
    "sg:province":"Baden-W\u00fcrttemberg",
    "wof:name":"Manfred Menius Werbegeschenke",
    "wof:placetype":"venue"
},
  "geometry": {"coordinates":[10.0001487732,48.2968864441],"type":"Point"}
}