{
  "type": "Feature",
  "properties": {
    "iso:country":"DE",
    "sg:address":"Talstr. 8",
    "sg:city":"Wolpertshausen",
    "sg:phone":"+49 7907/7634",
    "sg:postcode":"74549",
    "sg:province":"Baden-W\u00fcrttemberg",
    "wof:name":"Esch Gmbh",
    "wof:placetype":"venue"
},
  "geometry": {"coordinates":[9.828366,49.151409],"type":"Point"}
}