{
  "type": "Feature",
  "properties": {
    "iso:country":"DE",
    "sg:address":"Rauer Werth 23a",
    "sg:city":"Wuppertal",
    "sg:phone":"+49 202/551559",
    "sg:postcode":"42275",
    "sg:province":"Nordrhein-Westfalen",
    "wof:name":"Kasprzik & Heynen Gmbh",
    "wof:placetype":"venue"
},
  "geometry": {"coordinates":[7.205733,51.274536],"type":"Point"}
}