{
  "type": "Feature",
  "properties": {
    "iso:country":"DE",
    "sg:address":"R\u00f6genweg 20",
    "sg:city":"Hamburg",
    "sg:phone":"+49 40/6030212",
    "sg:postcode":"22359",
    "sg:province":"Hamburg",
    "wof:name":"Ando Bau-service Gmbh",
    "wof:placetype":"venue"
},
  "geometry": {"coordinates":[10.156335,53.656437],"type":"Point"}
}