{
  "type": "Feature",
  "properties": {
    "iso:country":"DE",
    "sg:address":"Im G\u00fcrtel 8",
    "sg:city":"Kempenich",
    "sg:phone":"+49 2655/960368",
    "sg:postcode":"56746",
    "sg:province":"Rheinland-Pfalz",
    "wof:name":"Shk Gro\u00dfhandel Gmbh",
    "wof:placetype":"venue"
},
  "geometry": {"coordinates":[7.1214652061,50.4203300476],"type":"Point"}
}