{
  "type": "Feature",
  "properties": {
    "iso:country":"DE",
    "sg:address":"Melanchthonstr. 113",
    "sg:city":"Bretten",
    "sg:postcode":"75015",
    "sg:province":"Baden-W\u00fcrttemberg",
    "wof:name":"Cc Capital-contor Immobilien-service Gmbh",
    "wof:placetype":"venue"
},
  "geometry": {"coordinates":[8.6947259903,49.0385856628],"type":"Point"}
}