{
  "type": "Feature",
  "properties": {
    "iso:country":"DE",
    "sg:city":"Winkelbach",
    "sg:phone":"+49 2680/980800",
    "sg:postcode":"57644",
    "sg:province":"Rheinland-Pfalz",
    "wof:name":"Cafe Krambergsm\u00fchle",
    "wof:placetype":"venue"
},
  "geometry": {"coordinates":[7.73153,50.640976],"type":"Point"}
}