{
  "type": "Feature",
  "properties": {
    "iso:country":"DE",
    "sg:address":"Lippe 37",
    "sg:city":"Laubach",
    "sg:phone":"+49 6405/6209",
    "sg:postcode":"35321",
    "sg:province":"Hessen",
    "wof:name":"Retaul Presseteam",
    "wof:placetype":"venue"
},
  "geometry": {"coordinates":[8.9918804169,50.5414505005],"type":"Point"}
}