{
  "type": "Feature",
  "properties": {
    "iso:country":"DE",
    "sg:address":"Bahnhofstr. 30",
    "sg:city":"Senden",
    "sg:phone":"+49 7307/6173",
    "sg:postcode":"89250",
    "sg:province":"Bayern",
    "wof:name":"Ernst Vogl",
    "wof:placetype":"venue"
},
  "geometry": {"coordinates":[10.0498590469,48.3216133118],"type":"Point"}
}