{
  "type": "Feature",
  "properties": {
    "iso:country":"DE",
    "sg:address":"Gemarkenstr. 51",
    "sg:city":"K\u00f6ln",
    "sg:phone":"+49 221/681572",
    "sg:postcode":"51069",
    "sg:province":"Nordrhein-Westfalen",
    "wof:name":"Helmut Beck",
    "wof:placetype":"venue"
},
  "geometry": {"coordinates":[7.079119,50.974792],"type":"Point"}
}