{
  "type": "Feature",
  "properties": {
    "iso:country":"DE",
    "sg:address":"Uelentruper Weg 6",
    "sg:city":"Lippetal",
    "sg:phone":"+49 2923/1220",
    "sg:postcode":"59510",
    "sg:province":"Nordrhein-Westfalen",
    "wof:name":"Tonius Mu\u00dfhoff",
    "wof:placetype":"venue"
},
  "geometry": {"coordinates":[8.169962,51.671989],"type":"Point"}
}