{
  "type": "Feature",
  "properties": {
    "iso:country":"DE",
    "sg:address":"Linsegass 6",
    "sg:city":"Greifenstein",
    "sg:phone":"+49 4964/78490",
    "sg:postcode":"35753",
    "sg:province":"Hessen",
    "wof:name":"Peter Kleffmann",
    "wof:placetype":"venue"
},
  "geometry": {"coordinates":[8.299839,50.583214],"type":"Point"}
}