{
  "type": "Feature",
  "properties": {
    "iso:country":"DE",
    "sg:address":"Markt 1",
    "sg:city":"Essen",
    "sg:phone":"+49 201/10950",
    "sg:postcode":"45127",
    "sg:province":"Nordrhein-Westfalen",
    "wof:name":"Cp/ Compartner Agentur F\u00fcr Kommunikation Gmbh",
    "wof:placetype":"venue"
},
  "geometry": {"coordinates":[7.0119709969,51.4568061829],"type":"Point"}
}