{
  "type": "Feature",
  "properties": {
    "iso:country":"DE",
    "sg:address":"Provinzialstr. 99",
    "sg:city":"Illingen",
    "sg:phone":"+49 6825/3125",
    "sg:postcode":"66557",
    "sg:province":"Saarland",
    "wof:name":"W. Schmitt",
    "wof:placetype":"venue"
},
  "geometry": {"coordinates":[7.072126,49.389782],"type":"Point"}
}