{
  "type": "Feature",
  "properties": {
    "iso:country":"DE",
    "sg:address":"Bachstr. 22",
    "sg:city":"Bad Breisig",
    "sg:phone":"+49 2633/9309",
    "sg:postcode":"53498",
    "sg:province":"Rheinland-Pfalz",
    "wof:name":"Marianne Littauer",
    "wof:placetype":"venue"
},
  "geometry": {"coordinates":[7.296268,50.50922],"type":"Point"}
}