{
  "type": "Feature",
  "properties": {
    "iso:country":"DE",
    "sg:address":"Lockhauser Str. 41",
    "sg:city":"Bad Salzuflen",
    "sg:phone":"+49 5222/73511",
    "sg:postcode":"32107",
    "sg:province":"Nordrhein-Westfalen",
    "wof:name":"Mensendiek Gmbh",
    "wof:placetype":"venue"
},
  "geometry": {"coordinates":[8.7060308456,52.0642623901],"type":"Point"}
}