{
  "type": "Feature",
  "properties": {
    "iso:country":"DE",
    "sg:address":"Mannheimer Str. 9",
    "sg:city":"Graben-Neudorf",
    "sg:postcode":"76676",
    "sg:province":"Baden-W\u00fcrttemberg",
    "wof:name":"Schumacher Gmbh",
    "wof:placetype":"venue"
},
  "geometry": {"coordinates":[8.4932384491,49.1697387695],"type":"Point"}
}