{
  "type": "Feature",
  "properties": {
    "iso:country":"DE",
    "sg:address":"Ringstr. 5",
    "sg:city":"Embsen",
    "sg:phone":"+49 4134/7576",
    "sg:postcode":"21409",
    "sg:province":"Niedersachsen",
    "wof:name":"Hans-hermann Cordes",
    "wof:placetype":"venue"
},
  "geometry": {"coordinates":[10.343666,53.175072],"type":"Point"}
}