{
  "type": "Feature",
  "properties": {
    "iso:country":"DE",
    "sg:address":"Badgasse 2",
    "sg:city":"Volkach",
    "sg:phone":"+49 9381/803670",
    "sg:postcode":"97332",
    "sg:province":"Bayern",
    "wof:name":"Elisabeth Sammartino",
    "wof:placetype":"venue"
},
  "geometry": {"coordinates":[10.225644,49.865395],"type":"Point"}
}