{
  "type": "Feature",
  "properties": {
    "iso:country":"DE",
    "sg:address":"Martin-Luther-King-Str. 4",
    "sg:city":"Hanau",
    "sg:phone":"+49 6181/98610",
    "sg:postcode":"63452",
    "sg:province":"Hessen",
    "wof:name":"Reifen-seher- Und Fahrzeugtechnik Gmbh",
    "wof:placetype":"venue"
},
  "geometry": {"coordinates":[8.922464,50.144875],"type":"Point"}
}