{
  "type": "Feature",
  "properties": {
    "iso:country":"DE",
    "sg:address":"M\u00f6rscher Str. 5",
    "sg:city":"Ettlingen",
    "sg:phone":"+49 7243/54510",
    "sg:postcode":"76275",
    "sg:province":"Baden-W\u00fcrttemberg",
    "wof:name":"Deutsche Verm\u00f6gensberatung Ag",
    "wof:placetype":"venue"
},
  "geometry": {"coordinates":[8.3806428909,48.9477729797],"type":"Point"}
}