{
  "type": "Feature",
  "properties": {
    "iso:country":"DE",
    "sg:address":"Waitzstr. 11",
    "sg:city":"Berlin",
    "sg:phone":"+49 30/310100",
    "sg:postcode":"10629",
    "sg:province":"Berlin",
    "wof:name":"Der Reiseschatz",
    "wof:placetype":"venue"
},
  "geometry": {"coordinates":[13.305401,52.500412],"type":"Point"}
}