{
  "type": "Feature",
  "properties": {
    "iso:country":"DE",
    "sg:address":"Bahnhofstr. 14",
    "sg:city":"Ebersbach",
    "sg:phone":"+49 3586/365365",
    "sg:postcode":"02730",
    "sg:province":"Sachsen",
    "wof:name":"Filmtheater Ebersbach",
    "wof:placetype":"venue"
},
  "geometry": {"coordinates":[14.579359,51.00703],"type":"Point"}
}