{
  "type": "Feature",
  "properties": {
    "iso:country":"DE",
    "sg:address":"In den Hupen",
    "sg:city":"Traben-Trarbach",
    "sg:phone":"+49 6541/6455",
    "sg:postcode":"56841",
    "sg:province":"Rheinland-Pfalz",
    "wof:name":"Krieger Treppen Gmbh",
    "wof:placetype":"venue"
},
  "geometry": {"coordinates":[7.104284,49.974689],"type":"Point"}
}