{
  "type": "Feature",
  "properties": {
    "iso:country":"DE",
    "sg:address":"An der Lahn 4",
    "sg:city":"Kranzberg",
    "sg:phone":"+49 8166/9456",
    "sg:postcode":"85402",
    "sg:province":"Bayern",
    "wof:name":"Forstrestaurant",
    "wof:placetype":"venue"
},
  "geometry": {"coordinates":[11.6627845764,48.4233016968],"type":"Point"}
}