{
  "type": "Feature",
  "properties": {
    "iso:country":"DE",
    "sg:address":"Bahnhofstr. 4",
    "sg:city":"Philippsburg",
    "sg:phone":"+49 7256/944885",
    "sg:postcode":"76661",
    "sg:province":"Baden-W\u00fcrttemberg",
    "wof:name":"Tri System Gmbh",
    "wof:placetype":"venue"
},
  "geometry": {"coordinates":[8.4542760849,49.2319259644],"type":"Point"}
}