{
  "type": "Feature",
  "properties": {
    "iso:country":"DE",
    "sg:address":"Oeldorf 11",
    "sg:city":"K\u00fcrten",
    "sg:phone":"+49 4922/072866",
    "sg:postcode":"51515",
    "sg:province":"Nordrhein-Westfalen",
    "wof:name":"Bfo Gartendesign Undlandschaftsbau Gmbh",
    "wof:placetype":"venue"
},
  "geometry": {"coordinates":[7.27021,51.00425],"type":"Point"}
}