{
  "type": "Feature",
  "properties": {
    "iso:country":"DE",
    "sg:address":"Erlenstr. 3",
    "sg:city":"Fl\u00f6rsheim",
    "sg:phone":"+49 6145/990314",
    "sg:postcode":"65439",
    "sg:province":"Hessen",
    "wof:name":"Nadja Sch\u00fcler Rechtsanw\u00e4ltin",
    "wof:placetype":"venue"
},
  "geometry": {"coordinates":[8.4340400696,50.0423851013],"type":"Point"}
}