{
  "type": "Feature",
  "properties": {
    "iso:country":"DE",
    "sg:address":"In den Harxheimer Wiesen 14",
    "sg:city":"Gau-Bischofsheim",
    "sg:phone":"+49 6135/4813",
    "sg:postcode":"55296",
    "sg:province":"Rheinland-Pfalz",
    "wof:name":"Karin Braun",
    "wof:placetype":"venue"
},
  "geometry": {"coordinates":[8.278681,49.906113],"type":"Point"}
}