{
  "type": "Feature",
  "properties": {
    "iso:country":"DE",
    "sg:address":"Weilerbachweg 20",
    "sg:city":"G\u00f6ppingen",
    "sg:phone":"+49 7161/811673",
    "sg:postcode":"73037",
    "sg:province":"Baden-W\u00fcrttemberg",
    "wof:name":"Ottilie Rapp Heissmangel",
    "wof:placetype":"venue"
},
  "geometry": {"coordinates":[9.690621376,48.6728553772],"type":"Point"}
}