{
  "type": "Feature",
  "properties": {
    "iso:country":"DE",
    "sg:address":"Ketscher Landstr.",
    "sg:city":"Schwetzingen",
    "sg:phone":"+49 6202/93010",
    "sg:postcode":"68723",
    "sg:province":"Baden-W\u00fcrttemberg",
    "wof:name":"Herbert & Krause Immobilien",
    "wof:placetype":"venue"
},
  "geometry": {"coordinates":[8.5573558807,49.3780212402],"type":"Point"}
}