{
  "type": "Feature",
  "properties": {
    "iso:country":"DE",
    "sg:address":"Am Krausen B\u00e4umchen 1",
    "sg:city":"Essen",
    "sg:phone":"+49 201/255646",
    "sg:postcode":"45136",
    "sg:province":"Nordrhein-Westfalen",
    "wof:name":"Gastst\u00e4tte Zum Treffpunkt",
    "wof:placetype":"venue"
},
  "geometry": {"coordinates":[7.0375990868,51.4321327209],"type":"Point"}
}