{
  "type": "Feature",
  "properties": {
    "iso:country":"DE",
    "sg:address":"Olga-Benario-Weg 22",
    "sg:city":"Jena",
    "sg:phone":"+49 3641/331930",
    "sg:postcode":"07747",
    "sg:province":"Th\u00fcringen",
    "wof:name":"R. Sch\u00f6nh\u00fctte",
    "wof:placetype":"venue"
},
  "geometry": {"coordinates":[11.6132249832,50.8934631348],"type":"Point"}
}