{
  "type": "Feature",
  "properties": {
    "iso:country":"DE",
    "sg:address":"Waldstr. 14 a",
    "sg:city":"M\u00f6ckern",
    "sg:phone":"+49 39221/5933",
    "sg:postcode":"39291",
    "sg:province":"Sachsen-Anhalt",
    "wof:name":"A. Schmidtke",
    "wof:placetype":"venue"
},
  "geometry": {"coordinates":[11.9603261948,52.1511688232],"type":"Point"}
}