{
  "type": "Feature",
  "properties": {
    "iso:country":"DE",
    "sg:address":"Augustusburger Stra\u00dfe 3",
    "sg:city":"Leubsdorf",
    "sg:phone":"+49 37291",
    "sg:postcode":"09573",
    "sg:province":"Sachsen",
    "wof:name":"Landtechnik N\u00fcrnberger",
    "wof:placetype":"venue"
},
  "geometry": {"coordinates":[13.126182,50.80714],"type":"Point"}
}