{
  "type": "Feature",
  "properties": {
    "iso:country":"DE",
    "sg:address":"Steckengasse 305",
    "sg:city":"Landshut",
    "sg:phone":"+49 871/273342",
    "sg:postcode":"84028",
    "sg:province":"Bayern",
    "wof:name":"Helga Dreischl",
    "wof:placetype":"venue"
},
  "geometry": {"coordinates":[12.1535253525,48.535484314],"type":"Point"}
}