{
  "type": "Feature",
  "properties": {
    "iso:country":"DE",
    "sg:address":"Hofrichterstr. 20",
    "sg:city":"K\u00f6ln",
    "sg:phone":"+49 221/634454",
    "sg:postcode":"51067",
    "sg:province":"Nordrhein-Westfalen",
    "wof:name":"Kurt Kattwinkel Verwaltungs-gmbh",
    "wof:placetype":"venue"
},
  "geometry": {"coordinates":[7.0413970947,50.9727363586],"type":"Point"}
}