{
  "type": "Feature",
  "properties": {
    "iso:country":"DE",
    "sg:address":"Iburger Str. 2",
    "sg:city":"Hagen",
    "sg:postcode":"49170",
    "sg:province":"Niedersachsen",
    "wof:name":"H & S Ingenieurb\u00fcro Und Heizungsbau Gmbh",
    "wof:placetype":"venue"
},
  "geometry": {"coordinates":[7.979537,52.19595],"type":"Point"}
}