{
  "type": "Feature",
  "properties": {
    "iso:country":"DE",
    "sg:address":"Braasstr. 28",
    "sg:city":"Rinteln",
    "sg:phone":"+49 5751/941630",
    "sg:postcode":"31737",
    "sg:province":"Niedersachsen",
    "wof:name":"Sbs Brenn-und Schneidbetrieb Rinteln Beteiligungs Gmbh",
    "wof:placetype":"venue"
},
  "geometry": {"coordinates":[9.078695,52.168758],"type":"Point"}
}