{
  "type": "Feature",
  "properties": {
    "iso:country":"DE",
    "sg:address":"Holzgraben 1-3",
    "sg:city":"Frankfurt am Main",
    "sg:phone":"+49 69/2193760",
    "sg:postcode":"60313",
    "sg:province":"Hessen",
    "wof:name":"Tower Management Personal & Unternehmensberatung",
    "wof:placetype":"venue"
},
  "geometry": {"coordinates":[8.683265,50.113998],"type":"Point"}
}