{
  "type": "Feature",
  "properties": {
    "iso:country":"DE",
    "sg:address":"Nordstr. 7",
    "sg:city":"Lauchhammer",
    "sg:postcode":"01979",
    "sg:province":"Brandenburg",
    "wof:name":"Lausitzer Kabelbeteiligungs Gesellschaft Mbh",
    "wof:placetype":"venue"
},
  "geometry": {"coordinates":[13.754993,51.513615],"type":"Point"}
}