{
  "type": "Feature",
  "properties": {
    "iso:country":"DE",
    "sg:address":"Adolf-Ludwig-Ring 6 b",
    "sg:city":"Pirmasens",
    "sg:phone":"+49 6331/46844",
    "sg:postcode":"66955",
    "sg:province":"Rheinland-Pfalz",
    "wof:name":"Hans Bachmann Architekt",
    "wof:placetype":"venue"
},
  "geometry": {"coordinates":[7.635089,49.188114],"type":"Point"}
}