{
  "type": "Feature",
  "properties": {
    "iso:country":"DE",
    "sg:address":"Muldenweg 27",
    "sg:city":"N\u00fcrnberg",
    "sg:phone":"+49 911/487404",
    "sg:postcode":"90469",
    "sg:province":"Bayern",
    "wof:name":"Emil Meier Ingenieur",
    "wof:placetype":"venue"
},
  "geometry": {"coordinates":[11.074016571,49.4172554016],"type":"Point"}
}