{
  "type": "Feature",
  "properties": {
    "iso:country":"DE",
    "sg:address":"Hammerbrookstr. 95",
    "sg:city":"Hamburg",
    "sg:phone":"+49 40/2378110",
    "sg:postcode":"20097",
    "sg:province":"Hamburg",
    "wof:name":"Trhs Treuhandgesellschaft Hamburg-s\u00fcd Mbh",
    "wof:placetype":"venue"
},
  "geometry": {"coordinates":[10.0257310867,53.5446052551],"type":"Point"}
}