{
  "type": "Feature",
  "properties": {
    "iso:country":"DE",
    "sg:address":"Oldenburger Str. 28",
    "sg:city":"Vechta",
    "sg:phone":"+49 4441/921990",
    "sg:postcode":"49377",
    "sg:province":"Niedersachsen",
    "wof:name":"Overmeyer Gmbh",
    "wof:placetype":"venue"
},
  "geometry": {"coordinates":[8.288081,52.734356],"type":"Point"}
}