{
  "type": "Feature",
  "properties": {
    "iso:country":"DE",
    "sg:address":"Sudetenstr. 51",
    "sg:city":"Geretsried",
    "sg:phone":"+49 8171/81638",
    "sg:postcode":"82538",
    "sg:province":"Bayern",
    "wof:name":"Annemarie Wenus Krankengymnastin",
    "wof:placetype":"venue"
},
  "geometry": {"coordinates":[11.489927,47.855511],"type":"Point"}
}