{
  "type": "Feature",
  "properties": {
    "iso:country":"DE",
    "sg:address":"Bergalingen 6",
    "sg:city":"Rickenbach",
    "sg:phone":"+49 7765",
    "sg:postcode":"79736",
    "sg:province":"Baden-W\u00fcrttemberg",
    "wof:name":"Art Borderline",
    "wof:placetype":"venue"
},
  "geometry": {"coordinates":[7.957666,47.61272],"type":"Point"}
}