{
  "type": "Feature",
  "properties": {
    "iso:country":"DE",
    "sg:address":"Dr.-Rieth-Str. 13",
    "sg:city":"R\u00f6merberg",
    "sg:phone":"+49 6232/82492",
    "sg:postcode":"67354",
    "sg:province":"Rheinland-Pfalz",
    "wof:name":"Edwin Hoffmann",
    "wof:placetype":"venue"
},
  "geometry": {"coordinates":[8.397593,49.283695],"type":"Point"}
}