{
  "type": "Feature",
  "properties": {
    "iso:country":"DE",
    "sg:address":"Kolpingstr. 7",
    "sg:city":"Aschaffenburg",
    "sg:postcode":"63739",
    "sg:province":"Bayern",
    "wof:name":"Kleffmann & Weese Inh. Kleffmann Gmbh",
    "wof:placetype":"venue"
},
  "geometry": {"coordinates":[9.1397066116,49.9796218872],"type":"Point"}
}