{
  "type": "Feature",
  "properties": {
    "iso:country":"DE",
    "sg:address":"Speersort 4-6",
    "sg:city":"Hamburg",
    "sg:postcode":"20095",
    "sg:province":"Hamburg",
    "wof:name":"Imperial Management Gmbh",
    "wof:placetype":"venue"
},
  "geometry": {"coordinates":[9.99886,53.550045],"type":"Point"}
}