{
  "type": "Feature",
  "properties": {
    "iso:country":"DE",
    "sg:address":"Buchenweg 7",
    "sg:city":"Ehringshausen",
    "sg:phone":"+49 6443/2209",
    "sg:postcode":"35630",
    "sg:province":"Hessen",
    "wof:name":"Werner Schmauch",
    "wof:placetype":"venue"
},
  "geometry": {"coordinates":[8.3788604736,50.6064796448],"type":"Point"}
}