{
  "type": "Feature",
  "properties": {
    "iso:country":"DE",
    "sg:address":"Vestische Str. 157",
    "sg:city":"Oberhausen",
    "sg:phone":"+49 208/632609",
    "sg:postcode":"46117",
    "sg:province":"Nordrhein-Westfalen",
    "wof:name":"Willi H\u00fcsken",
    "wof:placetype":"venue"
},
  "geometry": {"coordinates":[6.8655810356,51.5093193054],"type":"Point"}
}