{
  "type": "Feature",
  "properties": {
    "iso:country":"DE",
    "sg:address":"Friedrich-Rese-Str. 32",
    "sg:city":"Vienenburg",
    "sg:phone":"+49 5324/2982",
    "sg:postcode":"38690",
    "sg:province":"Niedersachsen",
    "wof:name":"Petra Fi\u00df",
    "wof:placetype":"venue"
},
  "geometry": {"coordinates":[10.566282,51.950108],"type":"Point"}
}