{
  "type": "Feature",
  "properties": {
    "iso:country":"DE",
    "sg:address":"Neuburger Str. 118",
    "sg:city":"Augsburg",
    "sg:phone":"+49 821/722855",
    "sg:postcode":"86167",
    "sg:province":"Bayern",
    "wof:name":"M. Baum\u00fcller",
    "wof:placetype":"venue"
},
  "geometry": {"coordinates":[10.917187,48.38673],"type":"Point"}
}