{
  "type": "Feature",
  "properties": {
    "iso:country":"DE",
    "sg:address":"Borgwardstr 12",
    "sg:city":"Bremen",
    "sg:phone":"+49 421/838855",
    "sg:postcode":"28279",
    "sg:province":"Bremen",
    "wof:name":"Buch-und Offsetdruckerei Edmund Ludwig Gmbh & Co",
    "wof:placetype":"venue"
},
  "geometry": {"coordinates":[8.837036,53.047718],"type":"Point"}
}