{
  "type": "Feature",
  "properties": {
    "iso:country":"DE",
    "sg:address":"Lindenweg 33",
    "sg:city":"Haan",
    "sg:phone":"+49 2104/60296",
    "sg:postcode":"42781",
    "sg:province":"Nordrhein-Westfalen",
    "wof:name":"Dr. Heinrich Kraus",
    "wof:placetype":"venue"
},
  "geometry": {"coordinates":[7.0066251755,51.212348938],"type":"Point"}
}