{
  "type": "Feature",
  "properties": {
    "iso:country":"DE",
    "sg:address":"Lengefelder Str. 3",
    "sg:city":"Chemnitz",
    "sg:phone":"+49 371/5384430",
    "sg:postcode":"09125",
    "sg:province":"Sachsen",
    "wof:name":"Berenice K\u00f6hler",
    "wof:placetype":"venue"
},
  "geometry": {"coordinates":[12.935524,50.79686],"type":"Point"}
}