{
  "type": "Feature",
  "properties": {
    "iso:country":"DE",
    "sg:address":"Dorfstr. 17",
    "sg:city":"Bojendorf",
    "sg:phone":"+49 4372",
    "sg:postcode":"23769",
    "sg:province":"Schleswig-Holstein",
    "wof:name":"Ferienwohnungen Haltermann-fehmarn",
    "wof:placetype":"venue"
},
  "geometry": {"coordinates":[11.028885,54.490494],"type":"Point"}
}