{
  "type": "Feature",
  "properties": {
    "iso:country":"DE",
    "sg:address":"Gottlieb-Daimler-Str. 1",
    "sg:city":"Laichingen",
    "sg:phone":"+49 7333/5366",
    "sg:postcode":"89150",
    "sg:province":"Baden-W\u00fcrttemberg",
    "wof:name":"Reinhard K\u00e4ppeler",
    "wof:placetype":"venue"
},
  "geometry": {"coordinates":[9.705295,48.493263],"type":"Point"}
}