{
  "type": "Feature",
  "properties": {
    "iso:country":"DE",
    "sg:address":"Herschelstr. 12",
    "sg:city":"Zwickau",
    "sg:phone":"+49 375/353830",
    "sg:postcode":"08060",
    "sg:province":"Sachsen",
    "wof:name":"Modulair Gmbh & Co. In Sachsen Komponenten F\u00fcr Luft- Und",
    "wof:placetype":"venue"
},
  "geometry": {"coordinates":[12.47083,50.724419],"type":"Point"}
}