{
  "type": "Feature",
  "properties": {
    "iso:country":"DE",
    "sg:address":"Am Rosenrain 13",
    "sg:city":"Rangendingen",
    "sg:phone":"+49 7471/82351",
    "sg:postcode":"72414",
    "sg:province":"Baden-W\u00fcrttemberg",
    "wof:name":"Wilfried Heyden",
    "wof:placetype":"venue"
},
  "geometry": {"coordinates":[8.8839702606,48.3757324219],"type":"Point"}
}