{
  "type": "Feature",
  "properties": {
    "iso:country":"DE",
    "sg:address":"Weiler Weg 3",
    "sg:city":"Neu-Ulm",
    "sg:phone":"+49 7307/21649",
    "sg:postcode":"89233",
    "sg:province":"Bayern",
    "wof:name":"Paul Kaszay Innenarchitekt",
    "wof:placetype":"venue"
},
  "geometry": {"coordinates":[10.100955,48.336002],"type":"Point"}
}