{
  "type": "Feature",
  "properties": {
    "iso:country":"DE",
    "sg:address":"Berkacher Str. 60",
    "sg:city":"Ehingen",
    "sg:phone":"+49 7391/52139",
    "sg:postcode":"89584",
    "sg:province":"Baden-W\u00fcrttemberg",
    "wof:name":"Elmar Denz",
    "wof:placetype":"venue"
},
  "geometry": {"coordinates":[9.726785,48.282387],"type":"Point"}
}