{
  "type": "Feature",
  "properties": {
    "iso:country":"DE",
    "sg:address":"In der R\u00f6th 14",
    "sg:city":"Gr\u00fcnstadt",
    "sg:phone":"+49 6359/85581",
    "sg:postcode":"67269",
    "sg:province":"Rheinland-Pfalz",
    "wof:name":"Cif Gmbh",
    "wof:placetype":"venue"
},
  "geometry": {"coordinates":[8.15653,49.561729],"type":"Point"}
}