{
  "type": "Feature",
  "properties": {
    "iso:country":"DE",
    "sg:address":"Raiffeisenstr. 8",
    "sg:city":"Usingen",
    "sg:postcode":"61250",
    "sg:province":"Hessen",
    "wof:name":"Gastrofun Gmbh",
    "wof:placetype":"venue"
},
  "geometry": {"coordinates":[8.522565,50.332302],"type":"Point"}
}