{
  "type": "Feature",
  "properties": {
    "iso:country":"DE",
    "sg:address":"Berliner Str. 13 A",
    "sg:city":"Bad Homburg",
    "sg:phone":"+49 6172/302984",
    "sg:postcode":"61348",
    "sg:province":"Hessen",
    "wof:name":"Reiner Ott Innenarchitekt",
    "wof:placetype":"venue"
},
  "geometry": {"coordinates":[8.605019,50.221905],"type":"Point"}
}