{
  "type": "Feature",
  "properties": {
    "iso:country":"DE",
    "sg:address":"Auf der Wessel 24",
    "sg:city":"G\u00f6ttingen",
    "sg:phone":"+49 551/7905133",
    "sg:postcode":"37085",
    "sg:province":"Niedersachsen",
    "wof:name":"Gerhard Wilhelm",
    "wof:placetype":"venue"
},
  "geometry": {"coordinates":[9.9622497559,51.5112838745],"type":"Point"}
}