{
  "type": "Feature",
  "properties": {
    "iso:country":"DE",
    "sg:address":"Bahnhofstr. 6",
    "sg:city":"Kell",
    "sg:phone":"+49 6589/1015",
    "sg:postcode":"54427",
    "sg:province":"Rheinland-Pfalz",
    "wof:name":"Hochwald-apotheke",
    "wof:placetype":"venue"
},
  "geometry": {"coordinates":[6.822395,49.634319],"type":"Point"}
}