{
  "type": "Feature",
  "properties": {
    "iso:country":"DE",
    "sg:address":"Mitteldorf 1",
    "sg:city":"Freden",
    "sg:phone":"+49 5184/391",
    "sg:postcode":"31084",
    "sg:province":"Niedersachsen",
    "wof:name":"Adac-hotel Heinrich Steinhoff",
    "wof:placetype":"venue"
},
  "geometry": {"coordinates":[9.8896799088,51.9281654358],"type":"Point"}
}