{
  "type": "Feature",
  "properties": {
    "iso:country":"DE",
    "sg:address":"Im Rosental 8",
    "sg:city":"Much",
    "sg:phone":"+49 2245/890143",
    "sg:postcode":"53804",
    "sg:province":"Nordrhein-Westfalen",
    "wof:name":"Reiner Br\u00fcggemann Psychotherapie",
    "wof:placetype":"venue"
},
  "geometry": {"coordinates":[7.375562191,50.8749504089],"type":"Point"}
}