{
  "type": "Feature",
  "properties": {
    "iso:country":"DE",
    "sg:address":"Eppendorfer Weg 265",
    "sg:city":"Hamburg",
    "sg:postcode":"20251",
    "sg:province":"Hamburg",
    "wof:name":"Niederelbische Treuhand- Und Steuerberatungs Gmbh",
    "wof:placetype":"venue"
},
  "geometry": {"coordinates":[9.9784498215,53.5842819214],"type":"Point"}
}