{
  "type": "Feature",
  "properties": {
    "iso:country":"DE",
    "sg:address":"Postfach 263:: 04662 Grimma:: Germany.^^Strasse des Friedens 25::",
    "sg:city":"Grimma",
    "sg:phone":"+49 3437/99102189",
    "sg:postcode":"04668",
    "sg:province":"Sachsen",
    "wof:name":"Sparkasse Muldental",
    "wof:placetype":"venue"
},
  "geometry": {"coordinates":[12.73623,51.219872],"type":"Point"}
}