{
  "type": "Feature",
  "properties": {
    "iso:country":"DE",
    "sg:address":"Wei\u00dfhofer Str. 22",
    "sg:city":"Bretten",
    "sg:phone":"+49 7252/80635",
    "sg:postcode":"75015",
    "sg:province":"Baden-W\u00fcrttemberg",
    "wof:name":"Gernot Guldner",
    "wof:placetype":"venue"
},
  "geometry": {"coordinates":[8.7093067169,49.0361938477],"type":"Point"}
}