{
  "type": "Feature",
  "properties": {
    "iso:country":"DE",
    "sg:address":"Heerstr. 482",
    "sg:city":"Kerpen",
    "sg:phone":"+49 2237/972056",
    "sg:postcode":"50169",
    "sg:province":"Nordrhein-Westfalen",
    "wof:name":"Clever Ambulante Krankenpflege",
    "wof:placetype":"venue"
},
  "geometry": {"coordinates":[6.76553,50.852699],"type":"Point"}
}