{
  "type": "Feature",
  "properties": {
    "iso:country":"DE",
    "sg:address":"Wettinstr. 3",
    "sg:city":"Ehrenfriedersdorf",
    "sg:phone":"+49 37341/2022",
    "sg:postcode":"09427",
    "sg:province":"Sachsen",
    "wof:name":"A. Seidl",
    "wof:placetype":"venue"
},
  "geometry": {"coordinates":[12.970646,50.647373],"type":"Point"}
}