{
  "type": "Feature",
  "properties": {
    "iso:country":"DE",
    "sg:address":"Romanstr. 149",
    "sg:city":"Freiburg",
    "sg:phone":"+49 7664/2771",
    "sg:postcode":"79112",
    "sg:province":"Baden-W\u00fcrttemberg",
    "wof:name":"Heinz Vogler",
    "wof:placetype":"venue"
},
  "geometry": {"coordinates":[7.7016878128,47.9655723572],"type":"Point"}
}