{
  "type": "Feature",
  "properties": {
    "iso:country":"DE",
    "sg:address":"Immanuelkirchstr.",
    "sg:city":"Berlin",
    "sg:postcode":"10405",
    "sg:province":"Berlin",
    "wof:name":"Dgm Holding Gmbh",
    "wof:placetype":"venue"
},
  "geometry": {"coordinates":[13.42258,52.53307],"type":"Point"}
}