{
  "type": "Feature",
  "properties": {
    "iso:country":"DE",
    "sg:address":"Vor den Eichen 30",
    "sg:city":"Willingen",
    "sg:phone":"+49 5632/69875",
    "sg:postcode":"34508",
    "sg:province":"Hessen",
    "wof:name":"Bernd Hammer Steuerbevollm\u00e4chtigter",
    "wof:placetype":"venue"
},
  "geometry": {"coordinates":[8.5789146423,51.2868614197],"type":"Point"}
}