{
  "type": "Feature",
  "properties": {
    "iso:country":"DE",
    "sg:address":"Kladower Damm 9",
    "sg:city":"Berlin",
    "sg:phone":"+49 30/3615933",
    "sg:postcode":"14089",
    "sg:province":"Berlin",
    "wof:name":"Georg Arenz Drogerie",
    "wof:placetype":"venue"
},
  "geometry": {"coordinates":[13.182077,52.482079],"type":"Point"}
}