{
  "type": "Feature",
  "properties": {
    "iso:country":"DE",
    "sg:address":"Luitpoldplatz 18",
    "sg:city":"Bayreuth",
    "sg:phone":"+49 921/26743",
    "sg:postcode":"95444",
    "sg:province":"Bayern",
    "wof:name":"Helmut Weigel",
    "wof:placetype":"venue"
},
  "geometry": {"coordinates":[11.5779676437,49.9465789795],"type":"Point"}
}