{
  "type": "Feature",
  "properties": {
    "iso:country":"DE",
    "sg:address":"Sonneberger Str. 88",
    "sg:city":"Lichte",
    "sg:phone":"+49 36701/60816",
    "sg:postcode":"98739",
    "sg:province":"Th\u00fcringen",
    "wof:name":"Ute Brzoska",
    "wof:placetype":"venue"
},
  "geometry": {"coordinates":[11.17675,50.518375],"type":"Point"}
}