{
  "type": "Feature",
  "properties": {
    "iso:country":"DE",
    "sg:address":"Sch\u00f6nauergasse 2",
    "sg:city":"Oberwesel",
    "sg:phone":"+49 6744/7492",
    "sg:postcode":"55430",
    "sg:province":"Rheinland-Pfalz",
    "wof:name":"Ernst Henrich",
    "wof:placetype":"venue"
},
  "geometry": {"coordinates":[7.727833,50.106407],"type":"Point"}
}