{
  "type": "Feature",
  "properties": {
    "iso:country":"DE",
    "sg:address":"Bad W\u00f6rishofer Str. 44",
    "sg:city":"Mindelheim",
    "sg:postcode":"87719",
    "sg:province":"Bayern",
    "wof:name":"Uks Klinik-service Gmbh",
    "wof:placetype":"venue"
},
  "geometry": {"coordinates":[10.493349,48.041508],"type":"Point"}
}