{
  "type": "Feature",
  "properties": {
    "iso:country":"DE",
    "sg:address":"Elsenheimerstr. 22",
    "sg:city":"Wolnzach",
    "sg:phone":"+49 8442/1473",
    "sg:postcode":"85283",
    "sg:province":"Bayern",
    "wof:name":"Schechinger Gmbh & Co. Kg",
    "wof:placetype":"venue"
},
  "geometry": {"coordinates":[11.626395,48.605888],"type":"Point"}
}