{
  "type": "Feature",
  "properties": {
    "iso:country":"DE",
    "sg:address":"Hedwig-Kracht-Weg 2",
    "sg:city":"Witten",
    "sg:phone":"+49 2302/77777",
    "sg:postcode":"58456",
    "sg:province":"Nordrhein-Westfalen",
    "wof:name":"Michael Stawiarski",
    "wof:placetype":"venue"
},
  "geometry": {"coordinates":[7.2794828415,51.4216957092],"type":"Point"}
}