{
  "type": "Feature",
  "properties": {
    "iso:country":"DE",
    "sg:address":"Karlsbader Str. 25",
    "sg:city":"Rittersgr\u00fcn",
    "sg:phone":"+49 37757/7332",
    "sg:postcode":"08355",
    "wof:name":"Kurt Fritzsch",
    "wof:placetype":"venue"
},
  "geometry": {"coordinates":[12.79192,50.478756],"type":"Point"}
}