{
  "type": "Feature",
  "properties": {
    "iso:country":"DE",
    "sg:address":"Hans-Wolf-Str. 8",
    "sg:city":"Limburg",
    "sg:phone":"+49 6431/6665",
    "sg:postcode":"65556",
    "sg:province":"Hessen",
    "wof:name":"Klaus Dambmann",
    "wof:placetype":"venue"
},
  "geometry": {"coordinates":[8.0358104706,50.3958625793],"type":"Point"}
}