{
  "type": "Feature",
  "properties": {
    "iso:country":"DE",
    "sg:address":"Schlackenm\u00fchle 1",
    "sg:city":"Seesen",
    "sg:phone":"+49 5381/48543",
    "sg:postcode":"38723",
    "sg:province":"Niedersachsen",
    "wof:name":"Drews Immobilienmakler",
    "wof:placetype":"venue"
},
  "geometry": {"coordinates":[10.1281938553,51.867931366],"type":"Point"}
}