{
  "type": "Feature",
  "properties": {
    "iso:country":"DE",
    "sg:address":"Elise-Kirchner-Str. 15",
    "sg:city":"Wiesbaden",
    "sg:phone":"+49 611/609674",
    "sg:postcode":"65203",
    "sg:province":"Hessen",
    "wof:name":"D. Und W. Schmitz",
    "wof:placetype":"venue"
},
  "geometry": {"coordinates":[8.2417097092,50.0446929932],"type":"Point"}
}