{
  "type": "Feature",
  "properties": {
    "iso:country":"DE",
    "sg:address":"Hasestr. 15",
    "sg:city":"Osnabr\u00fcck",
    "sg:phone":"+49 541/259485",
    "sg:postcode":"49074",
    "sg:province":"Niedersachsen",
    "wof:name":"Hartholz",
    "wof:placetype":"venue"
},
  "geometry": {"coordinates":[8.0434818268,52.2800140381],"type":"Point"}
}