{
  "type": "Feature",
  "properties": {
    "iso:country":"DE",
    "sg:address":"Hohe Str. 7",
    "sg:city":"Struppen",
    "sg:postcode":"01796",
    "sg:province":"Sachsen",
    "wof:name":"Landwirtschaftliche Produktionsgenossenschaft",
    "wof:placetype":"venue"
},
  "geometry": {"coordinates":[14.016886,50.932293],"type":"Point"}
}