{
  "type": "Feature",
  "properties": {
    "iso:country":"DE",
    "sg:address":"Calwer Str. 26",
    "sg:city":"Pforzheim",
    "sg:phone":"+49 7231/650618",
    "sg:postcode":"75175",
    "sg:province":"Baden-W\u00fcrttemberg",
    "wof:name":"Egginton",
    "wof:placetype":"venue"
},
  "geometry": {"coordinates":[8.7016677856,48.8867835999],"type":"Point"}
}