{
  "type": "Feature",
  "properties": {
    "iso:country":"DE",
    "sg:address":"Tanfanastr. 2",
    "sg:city":"Borgholzhausen",
    "sg:phone":"+49 5425/7100",
    "sg:postcode":"33829",
    "sg:province":"Nordrhein-Westfalen",
    "wof:name":"G\u00fcnter Landskron Masseur",
    "wof:placetype":"venue"
},
  "geometry": {"coordinates":[8.301545,52.103065],"type":"Point"}
}