{
  "type": "Feature",
  "properties": {
    "iso:country":"DE",
    "sg:address":"Reeserward 5",
    "sg:city":"Rees",
    "sg:phone":"+49 2851/1852",
    "sg:postcode":"46459",
    "sg:province":"Nordrhein-Westfalen",
    "wof:name":"Landhaus Drei Raben Andreas Und Margareta Koep",
    "wof:placetype":"venue"
},
  "geometry": {"coordinates":[6.3495869637,51.7702140808],"type":"Point"}
}