{
  "type": "Feature",
  "properties": {
    "iso:country":"DE",
    "sg:address":"P\u00fccklerstr. 11",
    "sg:city":"Cottbus",
    "sg:phone":"+49 355/7295000",
    "sg:postcode":"03042",
    "sg:province":"Brandenburg",
    "wof:name":"William G. Schiewek Rechtsanwalt",
    "wof:placetype":"venue"
},
  "geometry": {"coordinates":[14.3686943054,51.7390937805],"type":"Point"}
}