{
  "type": "Feature",
  "properties": {
    "iso:country":"DE",
    "sg:address":"Rheingrafenstr. 51",
    "sg:city":"Bad Kreuznach",
    "sg:phone":"+49 671/72033",
    "sg:postcode":"55543",
    "sg:province":"Rheinland-Pfalz",
    "wof:name":"Hans Und Ilse Staab-stiftung",
    "wof:placetype":"venue"
},
  "geometry": {"coordinates":[7.8605618477,49.829158783],"type":"Point"}
}