{
  "type": "Feature",
  "properties": {
    "iso:country":"DE",
    "sg:address":"Fechtboden 2",
    "sg:city":"Helmstedt",
    "sg:phone":"+49 5351/2422",
    "sg:postcode":"38350",
    "sg:province":"Niedersachsen",
    "wof:name":"Weinert & Schatz Ohg",
    "wof:placetype":"venue"
},
  "geometry": {"coordinates":[11.0115442276,52.2286643982],"type":"Point"}
}