{
  "type": "Feature",
  "properties": {
    "iso:country":"DE",
    "sg:address":"Obertattenbach 24",
    "sg:city":"Bad Birnbach",
    "sg:postcode":"84364",
    "sg:province":"Bayern",
    "wof:name":"Josef Kagerl Gmbh",
    "wof:placetype":"venue"
},
  "geometry": {"coordinates":[13.062127,48.464867],"type":"Point"}
}