{
  "type": "Feature",
  "properties": {
    "iso:country":"DE",
    "sg:address":"Frankfurter Str. 63a",
    "sg:city":"Altenkirchen",
    "sg:phone":"+49 2681/3227",
    "sg:postcode":"57610",
    "sg:province":"Rheinland-Pfalz",
    "wof:name":"Guthaplast Grundst\u00fccks- Verwaltungs Gmbh",
    "wof:placetype":"venue"
},
  "geometry": {"coordinates":[7.6576619148,50.6842803955],"type":"Point"}
}