{
  "type": "Feature",
  "properties": {
    "iso:country":"DE",
    "sg:address":"Stockstr. 8",
    "sg:city":"Leipzig",
    "sg:phone":"+49 341/964610",
    "sg:postcode":"04155",
    "sg:province":"Sachsen",
    "wof:name":"D. M. -finanz Gmbh",
    "wof:placetype":"venue"
},
  "geometry": {"coordinates":[12.36257,51.36113],"type":"Point"}
}