{
  "type": "Feature",
  "properties": {
    "iso:country":"DE",
    "sg:address":"Friedrich-Frank-Bogen 61",
    "sg:city":"Hamburg",
    "sg:phone":"+49 40/7394659",
    "sg:postcode":"21033",
    "sg:province":"Hamburg",
    "wof:name":"Werner Borstelmann",
    "wof:placetype":"venue"
},
  "geometry": {"coordinates":[10.1808214188,53.4892425537],"type":"Point"}
}