{
  "type": "Feature",
  "properties": {
    "iso:country":"DE",
    "sg:address":"Oberer Mattenweg 17",
    "sg:city":"Offenburg",
    "sg:postcode":"77652",
    "sg:province":"Baden-W\u00fcrttemberg",
    "wof:name":"Laempe Medien Virtualworker Gmbh",
    "wof:placetype":"venue"
},
  "geometry": {"coordinates":[7.94903,48.491581],"type":"Point"}
}