{
  "type": "Feature",
  "properties": {
    "iso:country":"DE",
    "sg:address":"Ohorner Str. 5",
    "sg:city":"Bretnig-Hauswalde",
    "sg:phone":"+49 35952/32974",
    "sg:postcode":"01900",
    "sg:province":"Sachsen",
    "wof:name":"Mtm Ausbau Gmbh",
    "wof:placetype":"venue"
},
  "geometry": {"coordinates":[14.02987957,51.1450805664],"type":"Point"}
}