{
  "type": "Feature",
  "properties": {
    "iso:country":"DE",
    "sg:address":"Schmiedgasse 5",
    "sg:city":"Wetzlar",
    "sg:phone":"+49 6441/45629",
    "sg:postcode":"35578",
    "sg:province":"Hessen",
    "wof:name":"Gebr. Schieferstein",
    "wof:placetype":"venue"
},
  "geometry": {"coordinates":[8.5029163361,50.5549545288],"type":"Point"}
}