{
  "type": "Feature",
  "properties": {
    "iso:country":"DE",
    "sg:address":"Karl-Liebknecht-Str. 12",
    "sg:city":"Gr\u00e4fenhainichen",
    "sg:phone":"+49 34953/421",
    "sg:postcode":"06773",
    "sg:province":"Sachsen-Anhalt",
    "wof:name":"Kreisarchiv Au\u00dfenstelle Gr\u00e4fenhainichen",
    "wof:placetype":"venue"
},
  "geometry": {"coordinates":[12.46212,51.728771],"type":"Point"}
}