{
  "type": "Feature",
  "properties": {
    "iso:country":"DE",
    "sg:address":"Limburger Str. 14",
    "sg:city":"Glash\u00fctten",
    "sg:phone":"+49 6174/62000",
    "sg:postcode":"61479",
    "sg:province":"Hessen",
    "wof:name":"Karl Breitung",
    "wof:placetype":"venue"
},
  "geometry": {"coordinates":[8.403106,50.21524],"type":"Point"}
}