{
  "type": "Feature",
  "properties": {
    "iso:country":"DE",
    "sg:address":"Ausschl\u00e4ger Allee 174",
    "sg:city":"Hamburg",
    "sg:phone":"+49 40/786854",
    "sg:postcode":"20539",
    "sg:province":"Hamburg",
    "wof:name":"Fritz Anders Gmbh & Co.",
    "wof:placetype":"venue"
},
  "geometry": {"coordinates":[10.0550479889,53.5316009521],"type":"Point"}
}