{
  "type": "Feature",
  "properties": {
    "iso:country":"DE",
    "sg:address":"Hans-B\u00f6ckler-Str. 11",
    "sg:city":"Aurich",
    "sg:phone":"+49 4941/18557",
    "sg:postcode":"26603",
    "sg:province":"Niedersachsen",
    "wof:name":"Detlef Zwirner",
    "wof:placetype":"venue"
},
  "geometry": {"coordinates":[7.4931359291,53.4623985291],"type":"Point"}
}