{
  "type": "Feature",
  "properties": {
    "iso:country":"DE",
    "sg:address":"Salzstetter Str. 30",
    "sg:city":"Haiterbach",
    "sg:phone":"+49 7456/6218",
    "sg:postcode":"72221",
    "sg:province":"Baden-W\u00fcrttemberg",
    "wof:name":"Hmm Holz- Und Metallm\u00f6bel Gmbh",
    "wof:placetype":"venue"
},
  "geometry": {"coordinates":[8.6463899612,48.5202980042],"type":"Point"}
}