{
  "type": "Feature",
  "properties": {
    "iso:country":"DE",
    "sg:address":"Zum Ikenkamp 3",
    "sg:city":"Haltern",
    "sg:phone":"+49 2364/4424",
    "sg:postcode":"45721",
    "sg:province":"Nordrhein-Westfalen",
    "wof:name":"H. B\u00f6ntert Werbeagentur",
    "wof:placetype":"venue"
},
  "geometry": {"coordinates":[7.1862020493,51.7374649048],"type":"Point"}
}