{
  "type": "Feature",
  "properties": {
    "iso:country":"DE",
    "sg:address":"Sonnenweg 1",
    "sg:city":"Blankenhain",
    "sg:phone":"+49 36459/41037",
    "sg:postcode":"99444",
    "sg:province":"Th\u00fcringen",
    "wof:name":"P. Stanke",
    "wof:placetype":"venue"
},
  "geometry": {"coordinates":[11.3484869003,50.8607368469],"type":"Point"}
}