{
  "type": "Feature",
  "properties": {
    "iso:country":"DE",
    "sg:address":"Kirchplatz",
    "sg:city":"Staffelstein",
    "sg:phone":"+49 9573/4147",
    "sg:postcode":"96231",
    "sg:province":"Bayern",
    "wof:name":"Museum Der Stadt Staffelstein",
    "wof:placetype":"venue"
},
  "geometry": {"coordinates":[11.00062,50.10323],"type":"Point"}
}