{
  "type": "Feature",
  "properties": {
    "iso:country":"DE",
    "sg:address":"Karl-Marx-Str. 11",
    "sg:city":"Doberlug-Kirchhain",
    "sg:phone":"+49 35322/2349",
    "sg:postcode":"03253",
    "sg:province":"Brandenburg",
    "wof:name":"O. Zahn",
    "wof:placetype":"venue"
},
  "geometry": {"coordinates":[13.551141,51.608212],"type":"Point"}
}