{
  "type": "Feature",
  "properties": {
    "iso:country":"DE",
    "sg:address":"Paul-Heyse-Str. 37",
    "sg:city":"M\u00fcnchen",
    "sg:phone":"+49 89/534013",
    "sg:postcode":"80336",
    "sg:province":"Bayern",
    "wof:name":"Georg-hirth Apotheke Marc Friedbichler",
    "wof:placetype":"venue"
},
  "geometry": {"coordinates":[11.555982,48.135075],"type":"Point"}
}