{
  "type": "Feature",
  "properties": {
    "iso:country":"DE",
    "sg:address":"Karlstr. 30",
    "sg:city":"Recklinghausen",
    "sg:phone":"+49 2361/667178",
    "sg:postcode":"45661",
    "sg:province":"Nordrhein-Westfalen",
    "wof:name":"Gotthelf H\u00e4rtel",
    "wof:placetype":"venue"
},
  "geometry": {"coordinates":[7.186915,51.561226],"type":"Point"}
}