{
  "type": "Feature",
  "properties": {
    "iso:country":"DE",
    "sg:address":"Hausmehringer Str. 14",
    "sg:city":"Nandlstadt",
    "sg:phone":"+49 8756/1231",
    "sg:postcode":"85405",
    "sg:province":"Bayern",
    "wof:name":"Georg Huber Gmbh",
    "wof:placetype":"venue"
},
  "geometry": {"coordinates":[11.8074617386,48.5383605957],"type":"Point"}
}