{
  "type": "Feature",
  "properties": {
    "iso:country":"DE",
    "sg:address":"M\u00fchlenkamp 40",
    "sg:city":"D\u00fcsseldorf",
    "sg:phone":"+49 211/2108557",
    "sg:postcode":"40229",
    "sg:province":"Nordrhein-Westfalen",
    "wof:name":"En De M\u00f6hl",
    "wof:placetype":"venue"
},
  "geometry": {"coordinates":[6.8440051079,51.201084137],"type":"Point"}
}