{
  "type": "Feature",
  "properties": {
    "iso:country":"DE",
    "sg:address":"Bahnhofstr. 7",
    "sg:city":"Nabburg",
    "sg:phone":"+49 9433/8434",
    "sg:postcode":"92507",
    "sg:province":"Bayern",
    "wof:name":"Walter Ratzke Rechtsanwalt",
    "wof:placetype":"venue"
},
  "geometry": {"coordinates":[12.1793422699,49.449131012],"type":"Point"}
}