{
  "type": "Feature",
  "properties": {
    "iso:country":"DE",
    "sg:address":"Industriestr. 20",
    "sg:city":"A\u00dflar",
    "sg:phone":"+49 6441/981010",
    "sg:postcode":"35614",
    "sg:province":"Hessen",
    "wof:name":"Bauunternehmung Preiss Gmbh",
    "wof:placetype":"venue"
},
  "geometry": {"coordinates":[8.4772958755,50.5824737549],"type":"Point"}
}