{
  "type": "Feature",
  "properties": {
    "iso:country":"DE",
    "sg:address":"Moorweg 91",
    "sg:city":"Rheda-Wiedenbr\u00fcck",
    "sg:phone":"+49 5242/402815",
    "sg:postcode":"33378",
    "sg:province":"Nordrhein-Westfalen",
    "wof:name":"Biohof Maria Bexten",
    "wof:placetype":"venue"
},
  "geometry": {"coordinates":[8.312998,51.871311],"type":"Point"}
}