{
  "type": "Feature",
  "properties": {
    "iso:country":"DE",
    "sg:address":"Br\u00fceler Str. 11",
    "sg:city":"Warin",
    "sg:postcode":"19417",
    "sg:province":"Mecklenburg-Vorpommern",
    "wof:name":"Ch. Dunkelmann",
    "wof:placetype":"venue"
},
  "geometry": {"coordinates":[11.709734,53.800442],"type":"Point"}
}