{
  "type": "Feature",
  "properties": {
    "iso:country":"DE",
    "sg:address":"Bl\u00fccherstr. 39",
    "sg:city":"Neuwied",
    "sg:phone":"+49 2631/20092",
    "sg:postcode":"56564",
    "sg:province":"Rheinland-Pfalz",
    "wof:name":"Elmas Bau- Und Verputz Gmbh",
    "wof:placetype":"venue"
},
  "geometry": {"coordinates":[7.479972,50.426338],"type":"Point"}
}