{
  "type": "Feature",
  "properties": {
    "iso:country":"DE",
    "sg:address":"Ahornallee 18",
    "sg:city":"Berlin",
    "sg:phone":"+49 30/3026981",
    "sg:postcode":"14050",
    "sg:province":"Berlin",
    "wof:name":"Tanzstudio Finck",
    "wof:placetype":"venue"
},
  "geometry": {"coordinates":[13.2750511169,52.5125198364],"type":"Point"}
}