{
  "type": "Feature",
  "properties": {
    "iso:country":"DE",
    "sg:address":"Wei\u00dfhausstr. 25",
    "sg:city":"K\u00f6ln",
    "sg:phone":"+49 221/4200364",
    "sg:postcode":"50939",
    "sg:province":"Nordrhein-Westfalen",
    "wof:name":"Nomad Reisen In Arabien Juliettea Baums Travel",
    "wof:placetype":"venue"
},
  "geometry": {"coordinates":[6.9334011078,50.9203910828],"type":"Point"}
}