{
  "type": "Feature",
  "properties": {
    "iso:country":"DE",
    "sg:address":"Oberlausitzerstr. 11",
    "sg:city":"Cuhnewalde",
    "sg:phone":"+49 4935/877840",
    "sg:postcode":"02733",
    "sg:province":"Sachsen",
    "wof:name":"H.-j. Kuepper Gmbh & Co. Kg System- U. Modultechnik",
    "wof:placetype":"venue"
},
  "geometry": {"coordinates":[14.4794178009,51.0966453552],"type":"Point"}
}