{
  "type": "Feature",
  "properties": {
    "iso:country":"DE",
    "sg:address":"Goldberg 29",
    "sg:city":"Allendorf",
    "sg:phone":"+49 6452/1051",
    "sg:postcode":"35108",
    "sg:province":"Hessen",
    "wof:name":"Fritz Strieder Hoch- Und Tiefbau Gmbh & Co. Kg",
    "wof:placetype":"venue"
},
  "geometry": {"coordinates":[8.6729698181,51.029838562],"type":"Point"}
}