{
  "type": "Feature",
  "properties": {
    "iso:country":"DE",
    "sg:address":"Hauptstr. 85",
    "sg:city":"Idar-Oberstein",
    "sg:phone":"+49 6781/43022",
    "sg:postcode":"55743",
    "sg:province":"Rheinland-Pfalz",
    "wof:name":"Messerschmidt Optik",
    "wof:placetype":"venue"
},
  "geometry": {"coordinates":[7.3012619019,49.7200279236],"type":"Point"}
}