{
  "type": "Feature",
  "properties": {
    "iso:country":"DE",
    "sg:address":"Essenberger Str. 206",
    "sg:city":"Duisburg",
    "sg:postcode":"47059",
    "sg:province":"Nordrhein-Westfalen",
    "wof:name":"H. Bauer Masseur",
    "wof:placetype":"venue"
},
  "geometry": {"coordinates":[6.730831,51.43219],"type":"Point"}
}