{
  "type": "Feature",
  "properties": {
    "iso:country":"DE",
    "sg:address":"Boselweg 1",
    "sg:city":"Coswig",
    "sg:phone":"+49 3523/63841",
    "sg:postcode":"01640",
    "sg:province":"Sachsen",
    "wof:name":"Hans Kralacek",
    "wof:placetype":"venue"
},
  "geometry": {"coordinates":[13.5174,51.137981],"type":"Point"}
}