{
  "type": "Feature",
  "properties": {
    "iso:country":"DE",
    "sg:address":"Bogenstr. 52",
    "sg:city":"Hamburg",
    "sg:phone":"+49 40/4223350",
    "sg:postcode":"20144",
    "sg:province":"Hamburg",
    "wof:name":"Chateau Du Pape Tonstudio & Tontechnik Norbert Pape",
    "wof:placetype":"venue"
},
  "geometry": {"coordinates":[9.973103,53.574486],"type":"Point"}
}