{
  "type": "Feature",
  "properties": {
    "iso:country":"DE",
    "sg:address":"Bruhnkaten 1",
    "sg:city":"Wesenberg",
    "sg:phone":"+49 4533/4423",
    "sg:postcode":"23858",
    "sg:province":"Schleswig-Holstein",
    "wof:name":"Parkett Schnack Gmbh",
    "wof:placetype":"venue"
},
  "geometry": {"coordinates":[10.521894455,53.8395385742],"type":"Point"}
}