{
  "type": "Feature",
  "properties": {
    "iso:country":"DE",
    "sg:address":"Hauptstr. 60",
    "sg:city":"Bahlingen",
    "sg:phone":"+49 7663/757",
    "sg:postcode":"79353",
    "sg:province":"Baden-W\u00fcrttemberg",
    "wof:name":"Bierh\u00e4usle",
    "wof:placetype":"venue"
},
  "geometry": {"coordinates":[7.7381701469,48.1217803955],"type":"Point"}
}