{
  "type": "Feature",
  "properties": {
    "iso:country":"DE",
    "sg:address":"Schillerstrasse 20",
    "sg:city":"T\u00fcnsdorf",
    "sg:phone":"+49 6868",
    "sg:postcode":"66693",
    "sg:province":"Saarland",
    "wof:name":"Suennen",
    "wof:placetype":"venue"
},
  "geometry": {"coordinates":[6.501477,49.479164],"type":"Point"}
}