{
  "type": "Feature",
  "properties": {
    "iso:country":"DE",
    "sg:address":"Siedlung 1",
    "sg:city":"Sehmatal-Neudorf",
    "sg:postcode":"09465",
    "sg:province":"Sachsen",
    "wof:name":"Dr. Hasso Haustein",
    "wof:placetype":"venue"
},
  "geometry": {"coordinates":[12.9949502945,50.5389404297],"type":"Point"}
}