{
  "type": "Feature",
  "properties": {
    "iso:country":"DE",
    "sg:address":"S\u00f6deler Str. 1c",
    "sg:city":"Bad Nauheim",
    "sg:phone":"+49 6032/82454",
    "sg:postcode":"61231",
    "sg:province":"Hessen",
    "wof:name":"Reinhard Th\u00f6nges",
    "wof:placetype":"venue"
},
  "geometry": {"coordinates":[8.748087,50.399693],"type":"Point"}
}