{
  "type": "Feature",
  "properties": {
    "iso:country":"DE",
    "sg:address":"Zeppelinstr. 3",
    "sg:city":"K\u00f6nigsbrunn",
    "sg:phone":"+49 8231/96870",
    "sg:postcode":"86343",
    "sg:province":"Bayern",
    "wof:name":"Tronic'5 Gesch\u00e4ftsf\u00fchrung Gmbh",
    "wof:placetype":"venue"
},
  "geometry": {"coordinates":[10.873159,48.250748],"type":"Point"}
}