{
  "type": "Feature",
  "properties": {
    "iso:country":"DE",
    "sg:address":"Heideweg 7",
    "sg:city":"Endingen",
    "sg:phone":"+49 7642/1724",
    "sg:postcode":"79346",
    "sg:province":"Baden-W\u00fcrttemberg",
    "wof:name":"Berggastst\u00e4tte Heidehof",
    "wof:placetype":"venue"
},
  "geometry": {"coordinates":[7.6811289787,48.1276664734],"type":"Point"}
}