{
  "type": "Feature",
  "properties": {
    "iso:country":"DE",
    "sg:address":"Klopstockstr. 9",
    "sg:city":"D\u00fcsseldorf",
    "sg:phone":"+49 211/674001",
    "sg:postcode":"40237",
    "sg:province":"Nordrhein-Westfalen",
    "wof:name":"Kern Immobilienmakler",
    "wof:placetype":"venue"
},
  "geometry": {"coordinates":[6.8131132126,51.2409324646],"type":"Point"}
}