{
  "type": "Feature",
  "properties": {
    "iso:country":"DE",
    "sg:address":"Simoniusstr 11",
    "sg:city":"Wangen",
    "sg:phone":"+49 7522/22497",
    "sg:postcode":"88239",
    "sg:province":"Baden-W\u00fcrttemberg",
    "wof:name":"Denany Gmbh",
    "wof:placetype":"venue"
},
  "geometry": {"coordinates":[9.8460178375,47.6801719666],"type":"Point"}
}