{
  "type": "Feature",
  "properties": {
    "iso:country":"DE",
    "sg:address":"Dorfstr. 59a",
    "sg:city":"Tangeln",
    "sg:postcode":"38489",
    "sg:province":"Sachsen-Anhalt",
    "wof:name":"Ilonia Griese Sanit\u00e4rgro\u00dfhandel",
    "wof:placetype":"venue"
},
  "geometry": {"coordinates":[11.0169630051,52.6734390259],"type":"Point"}
}