{
  "type": "Feature",
  "properties": {
    "iso:country":"DE",
    "sg:address":"Meyerstr. 39",
    "sg:city":"Weimar",
    "sg:phone":"+49 3643/851081",
    "sg:postcode":"99423",
    "sg:province":"Th\u00fcringen",
    "wof:name":"Scenario Gastro Gmbh",
    "wof:placetype":"venue"
},
  "geometry": {"coordinates":[11.3260812759,50.9892578125],"type":"Point"}
}