{
  "type": "Feature",
  "properties": {
    "iso:country":"DE",
    "sg:address":"Martin-Luther-Ring 33",
    "sg:city":"Schmalkalden",
    "sg:phone":"+49 3683/7429",
    "sg:postcode":"98574",
    "sg:province":"Th\u00fcringen",
    "wof:name":"Werner Wei\u00df",
    "wof:placetype":"venue"
},
  "geometry": {"coordinates":[10.4709310532,50.7203826904],"type":"Point"}
}