{
  "type": "Feature",
  "properties": {
    "iso:country":"DE",
    "sg:address":"Seekarstr. 8",
    "sg:city":"Bad T\u00f6lz",
    "sg:phone":"+49 8041/41968",
    "sg:postcode":"83646",
    "sg:province":"Bayern",
    "wof:name":"Franz Weber Gmbh",
    "wof:placetype":"venue"
},
  "geometry": {"coordinates":[11.5688009262,47.7447052002],"type":"Point"}
}