{
  "type": "Feature",
  "properties": {
    "iso:country":"DE",
    "sg:address":"Bahnhofsvorplatz",
    "sg:city":"Gelsenkirchen",
    "sg:phone":"+49 209/270690",
    "sg:postcode":"45879",
    "sg:province":"Nordrhein-Westfalen",
    "wof:name":"Alfredo-fashion Angelika Kuczenski",
    "wof:placetype":"venue"
},
  "geometry": {"coordinates":[7.1019,51.50605],"type":"Point"}
}