{
  "type": "Feature",
  "properties": {
    "iso:country":"DE",
    "sg:address":"Wickrathhahner Str. 12",
    "sg:city":"M\u00f6nchengladbach",
    "sg:phone":"+49 2166/51723",
    "sg:postcode":"41189",
    "sg:province":"Nordrhein-Westfalen",
    "wof:name":"Hans-dieter H\u00f6ltgen",
    "wof:placetype":"venue"
},
  "geometry": {"coordinates":[6.410736,51.128201],"type":"Point"}
}