{
  "type": "Feature",
  "properties": {
    "iso:country":"DE",
    "sg:address":"Jarrestr. 66",
    "sg:city":"Hamburg",
    "sg:postcode":"22303",
    "sg:province":"Hamburg",
    "wof:name":"Str Stadtteil- Reinigungsgesellschaft Mbh",
    "wof:placetype":"venue"
},
  "geometry": {"coordinates":[10.0285692215,53.5857162476],"type":"Point"}
}