{
  "type": "Feature",
  "properties": {
    "iso:country":"DE",
    "sg:address":"Dorfstr. 10",
    "sg:city":"Matgendorf",
    "sg:phone":"+49 39976/50219",
    "sg:postcode":"17168",
    "sg:province":"Mecklenburg-Vorpommern",
    "wof:name":"Viktor Offak",
    "wof:placetype":"venue"
},
  "geometry": {"coordinates":[12.50164,53.864132],"type":"Point"}
}