{
  "type": "Feature",
  "properties": {
    "iso:country":"DE",
    "sg:address":"Ebereschenweg 3",
    "sg:city":"Hamburg",
    "sg:phone":"+49 40/8663554",
    "sg:postcode":"22587",
    "sg:province":"Hamburg",
    "wof:name":"Kosegarten Unternehmens- Beratungs Gmbh",
    "wof:placetype":"venue"
},
  "geometry": {"coordinates":[9.814538,53.569912],"type":"Point"}
}