{
  "type": "Feature",
  "properties": {
    "iso:country":"DE",
    "sg:address":"Esslinger Str. 109",
    "sg:city":"Altbach",
    "sg:phone":"+49 7153/26715",
    "sg:postcode":"73776",
    "sg:province":"Baden-W\u00fcrttemberg",
    "wof:name":"L. Schmid",
    "wof:placetype":"venue"
},
  "geometry": {"coordinates":[9.384003,48.721443],"type":"Point"}
}