{
  "type": "Feature",
  "properties": {
    "iso:country":"DE",
    "sg:address":"Ismaninger Str. 136",
    "sg:city":"M\u00fcnchen",
    "sg:phone":"+49 89/92109",
    "sg:postcode":"81675",
    "sg:province":"Bayern",
    "wof:name":"\u00d6sterreichisches Generalkonsulat",
    "wof:placetype":"venue"
},
  "geometry": {"coordinates":[11.6061429977,48.1486091614],"type":"Point"}
}