{
  "type": "Feature",
  "properties": {
    "iso:country":"DE",
    "sg:address":"Frh.-v.-Stein Str. 17",
    "sg:city":"Elz",
    "sg:phone":"+49 6431/955906",
    "sg:postcode":"65604",
    "sg:province":"Hessen",
    "wof:name":"Wecom Werbegrafik & Computerdesign",
    "wof:placetype":"venue"
},
  "geometry": {"coordinates":[8.0356225967,50.4108657837],"type":"Point"}
}