{
  "type": "Feature",
  "properties": {
    "iso:country":"DE",
    "sg:address":"Schillerstr. 13",
    "sg:city":"Demmin",
    "sg:phone":"+49 3998/362290",
    "sg:postcode":"17109",
    "sg:province":"Mecklenburg-Vorpommern",
    "wof:name":"Hsk Haustechnik Gmbh",
    "wof:placetype":"venue"
},
  "geometry": {"coordinates":[13.0455818176,53.9041900635],"type":"Point"}
}