{
  "type": "Feature",
  "properties": {
    "iso:country":"DE",
    "sg:address":"Martin-Luther-Str. 103",
    "sg:city":"Berlin",
    "sg:postcode":"10825",
    "sg:province":"Berlin",
    "wof:name":"Wew\u00dc Verwaltungs Gmbh",
    "wof:placetype":"venue"
},
  "geometry": {"coordinates":[13.3454904556,52.4848098755],"type":"Point"}
}