{
  "type": "Feature",
  "properties": {
    "iso:country":"DE",
    "sg:address":"Hochstr. 10",
    "sg:city":"Ingelbach",
    "sg:phone":"+49 2688/8277",
    "sg:postcode":"57610",
    "sg:province":"Rheinland-Pfalz",
    "wof:name":"G\u00fcnter Jung",
    "wof:placetype":"venue"
},
  "geometry": {"coordinates":[7.705864,50.686371],"type":"Point"}
}