{
  "type": "Feature",
  "properties": {
    "iso:country":"DE",
    "sg:address":"Sch\u00e4ffbr\u00e4ustr. 23",
    "sg:city":"Ingolstadt",
    "sg:phone":"+49 841/32627",
    "sg:postcode":"85049",
    "sg:province":"Bayern",
    "wof:name":"Stadt-cafe",
    "wof:placetype":"venue"
},
  "geometry": {"coordinates":[11.423431,48.761616],"type":"Point"}
}