{
  "type": "Feature",
  "properties": {
    "iso:country":"DE",
    "sg:address":"Melatenweg 9",
    "sg:city":"Rees",
    "sg:postcode":"46459",
    "sg:province":"Nordrhein-Westfalen",
    "wof:name":"Becker Gmbh & Co. Kg",
    "wof:placetype":"venue"
},
  "geometry": {"coordinates":[6.4032421112,51.7640571594],"type":"Point"}
}