{
  "type": "Feature",
  "properties": {
    "iso:country":"DE",
    "sg:address":"Egerl\u00e4nder Str. 35",
    "sg:city":"Kelkheim",
    "sg:phone":"+49 6195/911700",
    "sg:postcode":"65779",
    "sg:province":"Hessen",
    "wof:name":"M. K\u00fcbscholl",
    "wof:placetype":"venue"
},
  "geometry": {"coordinates":[8.4240112305,50.1439361572],"type":"Point"}
}