{
  "type": "Feature",
  "properties": {
    "iso:country":"DE",
    "sg:address":"Ostpreu\u00dfendamm 84 A",
    "sg:city":"Berlin",
    "sg:phone":"+49 30/7122043",
    "sg:postcode":"12207",
    "sg:province":"Berlin",
    "wof:name":"Flauger & Fl\u00e4mig Berliner Spiralfedernfabrik",
    "wof:placetype":"venue"
},
  "geometry": {"coordinates":[13.3042850494,52.4168357849],"type":"Point"}
}