{
  "type": "Feature",
  "properties": {
    "iso:country":"DE",
    "sg:address":"Flurweg 9",
    "sg:city":"Winnen",
    "sg:postcode":"53505",
    "sg:province":"Rheinland-Pfalz",
    "wof:name":"Pension Eifelblick",
    "wof:placetype":"venue"
},
  "geometry": {"coordinates":[6.947208,50.55434],"type":"Point"}
}