{
  "type": "Feature",
  "properties": {
    "iso:country":"DE",
    "sg:address":"Poschingerstr. 17",
    "sg:city":"Berlin",
    "sg:phone":"+49 30/8555002",
    "sg:postcode":"12157",
    "sg:province":"Berlin",
    "wof:name":"Fritz Adam Kg",
    "wof:placetype":"venue"
},
  "geometry": {"coordinates":[13.3380746841,52.4634666443],"type":"Point"}
}