{
  "type": "Feature",
  "properties": {
    "iso:country":"DE",
    "sg:address":"Blumengasse 5",
    "sg:city":"Oberstdorf",
    "sg:phone":"+49 8322/3202",
    "sg:postcode":"87561",
    "sg:province":"Bayern",
    "wof:name":"Fremdenheim Speiser",
    "wof:placetype":"venue"
},
  "geometry": {"coordinates":[10.272064209,47.4102592468],"type":"Point"}
}