{
  "type": "Feature",
  "properties": {
    "iso:country":"DE",
    "sg:address":"Koisdorfer Str. 15a",
    "sg:city":"Sinzig",
    "sg:phone":"+49 2642/41667",
    "sg:postcode":"53489",
    "sg:province":"Rheinland-Pfalz",
    "wof:name":"Sybille Schoroth",
    "wof:placetype":"venue"
},
  "geometry": {"coordinates":[7.244654,50.540936],"type":"Point"}
}