{
  "type": "Feature",
  "properties": {
    "iso:country":"DE",
    "sg:address":"Rochusstr. 253",
    "sg:city":"Bonn",
    "sg:phone":"+49 228/614352",
    "sg:postcode":"53123",
    "sg:province":"Nordrhein-Westfalen",
    "wof:name":"Zohre Khodabandeh",
    "wof:placetype":"venue"
},
  "geometry": {"coordinates":[7.044876,50.713314],"type":"Point"}
}