{
  "type": "Feature",
  "properties": {
    "iso:country":"DE",
    "sg:address":"Feuerbachstr. 4",
    "sg:city":"Wiesbaden",
    "sg:phone":"+49 611/401572",
    "sg:postcode":"65195",
    "sg:province":"Hessen",
    "wof:name":"Martin Lauth Architekt",
    "wof:placetype":"venue"
},
  "geometry": {"coordinates":[8.216053,50.089718],"type":"Point"}
}