{
  "type": "Feature",
  "properties": {
    "iso:country":"DE",
    "sg:address":"Repitzer Weg 1",
    "sg:city":"Torgau",
    "sg:postcode":"04860",
    "sg:province":"Sachsen",
    "wof:name":"Top Team Service Gmbh",
    "wof:placetype":"venue"
},
  "geometry": {"coordinates":[13.004246,51.573235],"type":"Point"}
}