{
  "type": "Feature",
  "properties": {
    "iso:country":"DE",
    "sg:address":"Thomas-M\u00fcntzer-Str. 27",
    "sg:city":"M\u00fchlhausen",
    "sg:postcode":"99974",
    "sg:province":"Th\u00fcringen",
    "wof:name":"Tqf Qualit\u00e4tsferkel Aus Th\u00fcringen Gmbh",
    "wof:placetype":"venue"
},
  "geometry": {"coordinates":[10.4566164017,51.2364654541],"type":"Point"}
}