{
  "type": "Feature",
  "properties": {
    "iso:country":"DE",
    "sg:address":"Isingort 12",
    "sg:city":"Legden",
    "sg:phone":"+49 2566/4985",
    "sg:postcode":"48739",
    "sg:province":"Nordrhein-Westfalen",
    "wof:name":"Felix Rossm\u00f6ller",
    "wof:placetype":"venue"
},
  "geometry": {"coordinates":[7.108287,52.020721],"type":"Point"}
}