{
  "type": "Feature",
  "properties": {
    "iso:country":"DE",
    "sg:address":"K\u00f6lnstr. 11",
    "sg:city":"D\u00fcren",
    "sg:phone":"+49 2421/14143",
    "sg:postcode":"52349",
    "sg:province":"Nordrhein-Westfalen",
    "wof:name":"J. Vogel Strick- Und Wirkwaren",
    "wof:placetype":"venue"
},
  "geometry": {"coordinates":[6.4845051765,50.802936554],"type":"Point"}
}