{
  "type": "Feature",
  "properties": {
    "iso:country":"DE",
    "sg:address":"W\u00fcrzburger Str. 113",
    "sg:city":"Haibach",
    "sg:phone":"+49 6021/60441",
    "sg:postcode":"63808",
    "sg:province":"Bayern",
    "wof:name":"Elektrotechnik G. Roth",
    "wof:placetype":"venue"
},
  "geometry": {"coordinates":[9.2053394318,49.9641036987],"type":"Point"}
}