{
  "type": "Feature",
  "properties": {
    "iso:country":"DE",
    "sg:address":"Ahornstr. 15",
    "sg:city":"Bad Lauchst\u00e4dt",
    "sg:phone":"+49 34635/20563",
    "sg:postcode":"06246",
    "sg:province":"Sachsen-Anhalt",
    "wof:name":"Ulrich Markgraf",
    "wof:placetype":"venue"
},
  "geometry": {"coordinates":[11.881369,51.38586],"type":"Point"}
}