{
  "type": "Feature",
  "properties": {
    "iso:country":"DE",
    "sg:address":"Pettenkoferstr. 22",
    "sg:city":"Mannheim",
    "sg:phone":"+49 621/338181",
    "sg:postcode":"68169",
    "sg:province":"Baden-W\u00fcrttemberg",
    "wof:name":"Ke\u00dfler & Luch Gmbh",
    "wof:placetype":"venue"
},
  "geometry": {"coordinates":[8.4716920853,49.5037536621],"type":"Point"}
}