{
  "type": "Feature",
  "properties": {
    "iso:country":"DE",
    "sg:address":"Marktplatz 5",
    "sg:city":"Rotenburg",
    "sg:phone":"+49 6623/41255",
    "sg:postcode":"36199",
    "sg:province":"Hessen",
    "wof:name":"B. Feltz",
    "wof:placetype":"venue"
},
  "geometry": {"coordinates":[9.726934433,50.9943695068],"type":"Point"}
}