{
  "type": "Feature",
  "properties": {
    "iso:country":"DE",
    "sg:address":"G\u00f6gginger Str. 73",
    "sg:city":"Augsburg",
    "sg:phone":"+49 821",
    "sg:postcode":"86159",
    "sg:province":"Bayern",
    "wof:name":"Ingenieurb\u00fcro Etschel Eichner",
    "wof:placetype":"venue"
},
  "geometry": {"coordinates":[10.882888,48.353802],"type":"Point"}
}