{
  "type": "Feature",
  "properties": {
    "iso:country":"DE",
    "sg:address":"Gutleutstr. 2",
    "sg:city":"Bruchsal",
    "sg:phone":"+49 7251/18400",
    "sg:postcode":"76646",
    "sg:province":"Baden-W\u00fcrttemberg",
    "wof:name":"Kosmetik-aromamassage Rautenberg",
    "wof:placetype":"venue"
},
  "geometry": {"coordinates":[8.602551,49.132446],"type":"Point"}
}