{
  "type": "Feature",
  "properties": {
    "iso:country":"DE",
    "sg:address":"Rhenaniastr. 104",
    "sg:city":"Mannheim",
    "sg:phone":"+49 621/8022416",
    "sg:postcode":"68219",
    "sg:province":"Baden-W\u00fcrttemberg",
    "wof:name":"Thermotech Gmbh",
    "wof:placetype":"venue"
},
  "geometry": {"coordinates":[8.517311,49.437946],"type":"Point"}
}