{
  "type": "Feature",
  "properties": {
    "iso:country":"DE",
    "sg:address":"Kreisstr. 45",
    "sg:city":"H\u00f6xter",
    "sg:phone":"+49 5271/97610",
    "sg:postcode":"37671",
    "sg:province":"Nordrhein-Westfalen",
    "wof:name":"Fr\u00fchst\u00fcckspension Hillebrand",
    "wof:placetype":"venue"
},
  "geometry": {"coordinates":[9.3524045944,51.8032722473],"type":"Point"}
}