{
  "type": "Feature",
  "properties": {
    "iso:country":"DE",
    "sg:address":"Alte Bottroper Str. 81",
    "sg:city":"Essen",
    "sg:phone":"+49 4920/1866050",
    "sg:postcode":"45356",
    "sg:province":"Nordrhein-Westfalen",
    "wof:name":"Kunststofftechnik Dietmar Woyciniuk Gmbh",
    "wof:placetype":"venue"
},
  "geometry": {"coordinates":[6.960255146,51.4869689941],"type":"Point"}
}