{
  "type": "Feature",
  "properties": {
    "iso:country":"DE",
    "sg:address":"Am Rosenbaum 12",
    "sg:city":"Ratingen",
    "sg:phone":"+49 2102/52140",
    "sg:postcode":"40882",
    "sg:province":"Nordrhein-Westfalen",
    "wof:name":"Riepenhausen Tennis- Und Badminton Center",
    "wof:placetype":"venue"
},
  "geometry": {"coordinates":[6.9310688972,51.2987556458],"type":"Point"}
}