{
  "type": "Feature",
  "properties": {
    "iso:country":"DE",
    "sg:address":"Hauptstr. 161",
    "sg:city":"Bad Neustadt",
    "sg:phone":"+49 9771/2242",
    "sg:postcode":"97616",
    "sg:province":"Bayern",
    "wof:name":"Erich Kneuer",
    "wof:placetype":"venue"
},
  "geometry": {"coordinates":[10.198206,50.33073],"type":"Point"}
}