{
  "type": "Feature",
  "properties": {
    "iso:country":"DE",
    "sg:address":"Gerberstr. 9",
    "sg:city":"Halberstadt",
    "sg:phone":"+49 3941/27129",
    "sg:postcode":"38820",
    "sg:province":"Sachsen-Anhalt",
    "wof:name":"W. Schr\u00f6der",
    "wof:placetype":"venue"
},
  "geometry": {"coordinates":[11.051218,51.898323],"type":"Point"}
}