{
  "type": "Feature",
  "properties": {
    "iso:country":"DE",
    "sg:address":"Gottfried-Salz-Str. 3",
    "sg:city":"Sankt Augustin",
    "sg:phone":"+49 2241/330408",
    "sg:postcode":"53757",
    "sg:province":"Nordrhein-Westfalen",
    "wof:name":"Franz Willi Sch\u00fcller Gmbh",
    "wof:placetype":"venue"
},
  "geometry": {"coordinates":[7.199984,50.783825],"type":"Point"}
}