{
  "type": "Feature",
  "properties": {
    "iso:country":"DE",
    "sg:address":"G\u00fcstrower Str. 88",
    "sg:city":"Schwerin",
    "sg:phone":"+49 385/5574137",
    "sg:postcode":"19055",
    "sg:province":"Mecklenburg-Vorpommern",
    "wof:name":"F. Jahns Immobilienmakler",
    "wof:placetype":"venue"
},
  "geometry": {"coordinates":[11.426612854,53.6452178955],"type":"Point"}
}