{
  "type": "Feature",
  "properties": {
    "iso:country":"DE",
    "sg:address":"Eichengrund 33",
    "sg:city":"Hille",
    "sg:phone":"+49 5734/2127",
    "sg:postcode":"32479",
    "sg:province":"Nordrhein-Westfalen",
    "wof:name":"G. Diekmann Gmbh",
    "wof:placetype":"venue"
},
  "geometry": {"coordinates":[8.749036,52.289696],"type":"Point"}
}