{
  "type": "Feature",
  "properties": {
    "iso:country":"DE",
    "sg:address":"Kolnh\u00e4user Str. 6",
    "sg:city":"Lich",
    "sg:postcode":"35423",
    "sg:province":"Hessen",
    "wof:name":"Stadtb\u00fccherei",
    "wof:placetype":"venue"
},
  "geometry": {"coordinates":[8.815155,50.519741],"type":"Point"}
}