{
  "type": "Feature",
  "properties": {
    "iso:country":"DE",
    "sg:address":"Saalg\u00e4rten 7",
    "sg:city":"Rudolstadt",
    "sg:phone":"+49 3672/422554",
    "sg:postcode":"07407",
    "sg:province":"Th\u00fcringen",
    "wof:name":"Rowa W\u00e4scheservice Gmbh",
    "wof:placetype":"venue"
},
  "geometry": {"coordinates":[11.3562955856,50.7206192017],"type":"Point"}
}