{
  "type": "Feature",
  "properties": {
    "iso:country":"DE",
    "sg:address":"Bahnhofstr. 2 Mecklar",
    "sg:city":"Ludwigsau",
    "sg:phone":"+49 4966/2176858",
    "sg:postcode":"36251",
    "sg:province":"Hessen",
    "wof:name":"Asz Transport Gmbh",
    "wof:placetype":"venue"
},
  "geometry": {"coordinates":[9.7436656952,50.8976631165],"type":"Point"}
}