{
  "type": "Feature",
  "properties": {
    "iso:country":"DE",
    "sg:address":"Wilhelmstr. 28",
    "sg:city":"K\u00f6ln",
    "sg:phone":"+49 2203/55857",
    "sg:postcode":"51143",
    "sg:province":"Nordrhein-Westfalen",
    "wof:name":"Cafe International",
    "wof:placetype":"venue"
},
  "geometry": {"coordinates":[7.056314,50.885101],"type":"Point"}
}