{
  "type": "Feature",
  "properties": {
    "iso:country":"DE",
    "sg:address":"Zum Langen See 1",
    "sg:city":"Berlin",
    "sg:phone":"+49 30/6515867",
    "sg:postcode":"12557",
    "sg:province":"Berlin",
    "wof:name":"Generalagentur Ren\u00e9 Wiemann E. Kfm.",
    "wof:placetype":"venue"
},
  "geometry": {"coordinates":[13.5914831161,52.4220848083],"type":"Point"}
}