{
  "type": "Feature",
  "properties": {
    "iso:country":"DE",
    "sg:address":"Ignatiusstr. 43",
    "sg:city":"Havixbeck",
    "sg:phone":"+49 2507/9117",
    "sg:postcode":"48329",
    "sg:province":"Nordrhein-Westfalen",
    "wof:name":"Champagner E. V. Martin Mertens",
    "wof:placetype":"venue"
},
  "geometry": {"coordinates":[7.4116559029,51.982837677],"type":"Point"}
}