{
  "type": "Feature",
  "properties": {
    "iso:country":"DE",
    "sg:address":"Lindenstr. 15",
    "sg:city":"Strehla",
    "sg:phone":"+49 35264/90821",
    "sg:postcode":"01616",
    "sg:province":"Sachsen",
    "wof:name":"Koch-bautischlerei-glaserei Strehla Gmbh",
    "wof:placetype":"venue"
},
  "geometry": {"coordinates":[13.230023,51.350266],"type":"Point"}
}