{
  "type": "Feature",
  "properties": {
    "iso:country":"DE",
    "sg:address":"Kohrbleiche 37",
    "sg:city":"M\u00f6nchengladbach",
    "sg:phone":"+49 2166/680471",
    "sg:postcode":"41199",
    "sg:province":"Nordrhein-Westfalen",
    "wof:name":"Texmash Bar Yoken Textilmaschinen Gmbh",
    "wof:placetype":"venue"
},
  "geometry": {"coordinates":[6.448525,51.138428],"type":"Point"}
}