{
  "type": "Feature",
  "properties": {
    "iso:country":"DE",
    "sg:address":"Auf dem Thie 8",
    "sg:city":"Rheine",
    "sg:phone":"+49 5971/92830",
    "sg:postcode":"48431",
    "sg:province":"Nordrhein-Westfalen",
    "wof:name":"Ludwig M\u00fcller",
    "wof:placetype":"venue"
},
  "geometry": {"coordinates":[7.4367570877,52.2795181274],"type":"Point"}
}