{
  "type": "Feature",
  "properties": {
    "iso:country":"DE",
    "sg:address":"Karlstrasse 28",
    "sg:city":"Bad D\u00fcrrheim",
    "sg:postcode":"78073",
    "sg:province":"Baden-W\u00fcrttemberg",
    "wof:name":"Ferienwohnung Auf Sizilien / Italien",
    "wof:placetype":"venue"
},
  "geometry": {"coordinates":[8.534926,48.021763],"type":"Point"}
}