{
  "type": "Feature",
  "properties": {
    "iso:country":"DE",
    "sg:address":"Rudolf-Heilgers-Str. 22",
    "sg:city":"Worms",
    "sg:phone":"+49 6241/74323",
    "sg:postcode":"67549",
    "sg:province":"Rheinland-Pfalz",
    "wof:name":"Hep Helmut Emler & Partner Gmbh",
    "wof:placetype":"venue"
},
  "geometry": {"coordinates":[8.340051651,49.6417503357],"type":"Point"}
}