{
  "type": "Feature",
  "properties": {
    "iso:country":"DE",
    "sg:address":"V\u00f6lkstr. 2",
    "sg:city":"Sonthofen",
    "sg:phone":"+49 8321/86571",
    "sg:postcode":"87527",
    "sg:province":"Bayern",
    "wof:name":"Albert Herz Gmbh",
    "wof:placetype":"venue"
},
  "geometry": {"coordinates":[10.2798376083,47.5138473511],"type":"Point"}
}