{
  "type": "Feature",
  "properties": {
    "iso:country":"DE",
    "sg:address":"Buchenweg 7",
    "sg:city":"Elsdorf",
    "sg:postcode":"50189",
    "sg:province":"Nordrhein-Westfalen",
    "wof:name":"Empro E. K.",
    "wof:placetype":"venue"
},
  "geometry": {"coordinates":[6.558683,50.934513],"type":"Point"}
}