{
  "type": "Feature",
  "properties": {
    "iso:country":"DE",
    "sg:address":"Eckernf\u00f6rder Str. 345",
    "sg:city":"Kiel",
    "sg:phone":"+49 431/319110",
    "sg:postcode":"24107",
    "sg:province":"Schleswig-Holstein",
    "wof:name":"Brinkmann Und Partner",
    "wof:placetype":"venue"
},
  "geometry": {"coordinates":[10.0909004211,54.3510780334],"type":"Point"}
}