{
  "type": "Feature",
  "properties": {
    "iso:country":"DE",
    "sg:address":"Friedrichstr. 4",
    "sg:city":"Quakenbr\u00fcck",
    "sg:phone":"+49 5431/904760",
    "sg:postcode":"49610",
    "sg:province":"Niedersachsen",
    "wof:name":"Peter Binder-korscow Ergotherapiepraxis",
    "wof:placetype":"venue"
},
  "geometry": {"coordinates":[7.945399,52.675507],"type":"Point"}
}