{
  "type": "Feature",
  "properties": {
    "iso:country":"DE",
    "sg:address":"Silostr. 65",
    "sg:city":"Frankfurt",
    "sg:phone":"+49 69/3140280",
    "sg:postcode":"65929",
    "sg:province":"Hessen",
    "wof:name":"Gebr. Horne Rohrleitungen Und Techn.",
    "wof:placetype":"venue"
},
  "geometry": {"coordinates":[8.5235776901,50.0985183716],"type":"Point"}
}