{
  "type": "Feature",
  "properties": {
    "iso:country":"DE",
    "sg:address":"Wallnerstr. 1",
    "sg:city":"M\u00fcnchen",
    "sg:phone":"+49 89/325061",
    "sg:postcode":"80939",
    "sg:province":"Bayern",
    "wof:name":"Islamische Gemeinschaft In S\u00fcddeutschland E. V.",
    "wof:placetype":"venue"
},
  "geometry": {"coordinates":[11.6338529587,48.2103652954],"type":"Point"}
}