{
  "type": "Feature",
  "properties": {
    "iso:country":"DE",
    "sg:address":"Bahnhofstr. 1",
    "sg:city":"Mettenheim",
    "sg:phone":"+49 6242/2984",
    "sg:postcode":"67582",
    "sg:province":"Rheinland-Pfalz",
    "wof:name":"Herbert Butschbach",
    "wof:placetype":"venue"
},
  "geometry": {"coordinates":[8.3265457153,49.7399940491],"type":"Point"}
}