{
  "type": "Feature",
  "properties": {
    "iso:country":"DE",
    "sg:address":"Grabenstr. 11",
    "sg:city":"Fl\u00f6rsheim",
    "sg:phone":"+49 6145/6403",
    "sg:postcode":"65439",
    "sg:province":"Hessen",
    "wof:name":"Ludwig Gutjahr Eisenwaren",
    "wof:placetype":"venue"
},
  "geometry": {"coordinates":[8.428533,50.013184],"type":"Point"}
}