{
  "type": "Feature",
  "properties": {
    "iso:country":"DE",
    "sg:address":"Marktstr. 3",
    "sg:city":"Gie\u00dfen",
    "sg:phone":"+49 641/394897",
    "sg:postcode":"35390",
    "sg:province":"Hessen",
    "wof:name":"Montanara Meid Gmbh",
    "wof:placetype":"venue"
},
  "geometry": {"coordinates":[8.6739721298,50.586101532],"type":"Point"}
}