{
  "type": "Feature",
  "properties": {
    "iso:country":"DE",
    "sg:address":"Katzenstuhlweg 9",
    "sg:city":"Staufen",
    "sg:postcode":"79219",
    "sg:province":"Baden-W\u00fcrttemberg",
    "wof:name":"Ctv Gmbh",
    "wof:placetype":"venue"
},
  "geometry": {"coordinates":[7.719351,47.87038],"type":"Point"}
}