{
  "type": "Feature",
  "properties": {
    "iso:country":"DE",
    "sg:address":"Br\u00fchlstr. 19",
    "sg:city":"Lachen",
    "sg:phone":"+49 8331/80931",
    "sg:postcode":"87760",
    "sg:province":"Bayern",
    "wof:name":"Knabl",
    "wof:placetype":"venue"
},
  "geometry": {"coordinates":[10.236935,47.935814],"type":"Point"}
}