{
  "type": "Feature",
  "properties": {
    "iso:country":"DE",
    "sg:address":"Burger Hof 2",
    "sg:city":"Halle",
    "sg:phone":"+49 345/641350",
    "sg:postcode":"06124",
    "sg:province":"Sachsen-Anhalt",
    "wof:name":"M. Gollnast",
    "wof:placetype":"venue"
},
  "geometry": {"coordinates":[11.918278,51.472603],"type":"Point"}
}