{
  "type": "Feature",
  "properties": {
    "iso:country":"DE",
    "sg:address":"Verdener Str. 18",
    "sg:city":"Schneverdingen",
    "sg:phone":"+49 5193/3308",
    "sg:postcode":"29640",
    "sg:province":"Niedersachsen",
    "wof:name":"Gastst\u00e4tte Marmaris",
    "wof:placetype":"venue"
},
  "geometry": {"coordinates":[9.7883749008,53.1152381897],"type":"Point"}
}