{
  "type": "Feature",
  "properties": {
    "iso:country":"DE",
    "sg:address":"Kaiserstr. 105",
    "sg:city":"Dortmund",
    "sg:phone":"+49 231/5862895",
    "sg:postcode":"44135",
    "sg:province":"Nordrhein-Westfalen",
    "wof:name":"Verona Pizzeria",
    "wof:placetype":"venue"
},
  "geometry": {"coordinates":[7.4861688614,51.5133514404],"type":"Point"}
}