{
  "type": "Feature",
  "properties": {
    "iso:country":"DE",
    "sg:address":"Ernst-Poensgen-Allee 5",
    "sg:city":"D\u00fcsseldorf",
    "sg:phone":"+49 211/6412944",
    "sg:postcode":"40629",
    "sg:province":"Nordrhein-Westfalen",
    "wof:name":"I. Bagli",
    "wof:placetype":"venue"
},
  "geometry": {"coordinates":[6.826496,51.247475],"type":"Point"}
}