{
  "type": "Feature",
  "properties": {
    "iso:country":"DE",
    "sg:address":"Pl\u00f6rnbacher Str. 3",
    "sg:city":"Haag",
    "sg:phone":"+49 8167/8393",
    "sg:postcode":"85410",
    "sg:province":"Bayern",
    "wof:name":"Siegfried Wagner",
    "wof:placetype":"venue"
},
  "geometry": {"coordinates":[11.832103,48.459007],"type":"Point"}
}