{
  "type": "Feature",
  "properties": {
    "iso:country":"DE",
    "sg:address":"Rosenweg 3",
    "sg:city":"Niederrieden",
    "sg:phone":"+49 8335/8285",
    "sg:postcode":"87767",
    "sg:province":"Bayern",
    "wof:name":"Johannes Maffenbeier Architekt",
    "wof:placetype":"venue"
},
  "geometry": {"coordinates":[10.18488,48.059383],"type":"Point"}
}