{
  "type": "Feature",
  "properties": {
    "iso:country":"DE",
    "sg:address":"Im Br\u00fchl 12",
    "sg:city":"Brigachtal",
    "sg:phone":"+49 7721/24238",
    "sg:postcode":"78086",
    "sg:province":"Baden-W\u00fcrttemberg",
    "wof:name":"Recycling & Service Gmbh",
    "wof:placetype":"venue"
},
  "geometry": {"coordinates":[8.4520940781,48.0131149292],"type":"Point"}
}