{
  "type": "Feature",
  "properties": {
    "iso:country":"DE",
    "sg:address":"Kaiser-Friedrich-Ring 49",
    "sg:city":"Wiesbaden",
    "sg:phone":"+49 611/180820",
    "sg:postcode":"65185",
    "sg:province":"Hessen",
    "wof:name":"Cinetics Corporate Communications Gmbh",
    "wof:placetype":"venue"
},
  "geometry": {"coordinates":[8.2324943542,50.0733146667],"type":"Point"}
}