{
  "type": "Feature",
  "properties": {
    "iso:country":"DE",
    "sg:address":"Am Alten Dreisch 12",
    "sg:city":"Balve",
    "sg:phone":"+49 2375/1234",
    "sg:postcode":"58802",
    "sg:province":"Nordrhein-Westfalen",
    "wof:name":"Concept Wohnbau Gmbh",
    "wof:placetype":"venue"
},
  "geometry": {"coordinates":[7.864957,51.327099],"type":"Point"}
}