{
  "type": "Feature",
  "properties": {
    "iso:country":"DE",
    "sg:address":"Gothaer Str. 4",
    "sg:city":"Ratingen",
    "sg:phone":"+49 2102/20280",
    "sg:postcode":"40880",
    "sg:province":"Nordrhein-Westfalen",
    "wof:name":"Ardo Gmbh",
    "wof:placetype":"venue"
},
  "geometry": {"coordinates":[6.8122000694,51.290222168],"type":"Point"}
}