{
  "type": "Feature",
  "properties": {
    "iso:country":"DE",
    "sg:address":"Sophienstr. 59",
    "sg:city":"Eisenach",
    "sg:phone":"+49 3691/217220",
    "sg:postcode":"99817",
    "sg:province":"Th\u00fcringen",
    "wof:name":"Gerd Pforr",
    "wof:placetype":"venue"
},
  "geometry": {"coordinates":[10.3224620819,50.9766731262],"type":"Point"}
}