{
  "type": "Feature",
  "properties": {
    "iso:country":"DE",
    "sg:address":"Memelstr. 13",
    "sg:city":"R\u00f6dermark",
    "sg:phone":"+49 6074/98247",
    "sg:postcode":"63322",
    "sg:province":"Hessen",
    "wof:name":"Kerbverein Ober-roden Hubert Richter",
    "wof:placetype":"venue"
},
  "geometry": {"coordinates":[8.8454704285,49.970500946],"type":"Point"}
}