{
  "type": "Feature",
  "properties": {
    "iso:country":"DE",
    "sg:address":"Schweizerstr. 62",
    "sg:city":"Balingen",
    "sg:phone":"+49 7433/21811",
    "sg:postcode":"72336",
    "sg:province":"Baden-W\u00fcrttemberg",
    "wof:name":"Alfons Silbernagl",
    "wof:placetype":"venue"
},
  "geometry": {"coordinates":[8.8683176041,48.2959671021],"type":"Point"}
}