{
  "type": "Feature",
  "properties": {
    "iso:country":"DE",
    "sg:address":"Flurstr. 5",
    "sg:city":"Hohentengen",
    "sg:phone":"+49 7572/713900",
    "sg:postcode":"88367",
    "sg:province":"Baden-W\u00fcrttemberg",
    "wof:name":"Alexander Frick Gmbh",
    "wof:placetype":"venue"
},
  "geometry": {"coordinates":[9.375003,48.027035],"type":"Point"}
}