{
  "type": "Feature",
  "properties": {
    "iso:country":"DE",
    "sg:address":"An der Hasenquelle 17",
    "sg:city":"Mainz",
    "sg:phone":"+49 6131/685055",
    "sg:postcode":"55120",
    "sg:province":"Rheinland-Pfalz",
    "wof:name":"Otto Wasmer Rechtsanwalt",
    "wof:placetype":"venue"
},
  "geometry": {"coordinates":[8.2115564346,50.0197372437],"type":"Point"}
}