{
  "type": "Feature",
  "properties": {
    "iso:country":"DE",
    "sg:address":"Neu-Weiher-Str. 4",
    "sg:city":"Pressath",
    "sg:phone":"+49 9644/92080",
    "sg:postcode":"92690",
    "sg:province":"Bayern",
    "wof:name":"Ludwig Schleicher Gmbh",
    "wof:placetype":"venue"
},
  "geometry": {"coordinates":[11.948028,49.760056],"type":"Point"}
}