{
  "type": "Feature",
  "properties": {
    "iso:country":"DE",
    "sg:address":"Scharnhorststr. 11",
    "sg:city":"B\u00fcckeburg",
    "sg:phone":"+49 5722/21125",
    "sg:postcode":"31675",
    "sg:province":"Niedersachsen",
    "wof:name":"G\u00fcnter Lehmann",
    "wof:placetype":"venue"
},
  "geometry": {"coordinates":[9.0488424301,52.265335083],"type":"Point"}
}