{
  "type": "Feature",
  "properties": {
    "iso:country":"DE",
    "sg:address":"Lange Str. 39",
    "sg:city":"Hoya",
    "sg:phone":"+49 4251/92233",
    "sg:postcode":"27318",
    "sg:province":"Niedersachsen",
    "wof:name":"Lothar Bockelmann Steuerberater",
    "wof:placetype":"venue"
},
  "geometry": {"coordinates":[9.1389579773,52.8053398132],"type":"Point"}
}