{
  "type": "Feature",
  "properties": {
    "iso:country":"DE",
    "sg:address":"Sossenheimer Weg 9",
    "sg:city":"Frankfurt",
    "sg:phone":"+49 69/301364",
    "sg:postcode":"65929",
    "sg:province":"Hessen",
    "wof:name":"Gerhard Plochberger",
    "wof:placetype":"venue"
},
  "geometry": {"coordinates":[8.5387163162,50.111907959],"type":"Point"}
}