{
  "type": "Feature",
  "properties": {
    "iso:country":"DE",
    "sg:address":"F\u00fcrstenrieder Str. 82",
    "sg:city":"M\u00fcnchen",
    "sg:phone":"+49 89/54646727",
    "sg:postcode":"80686",
    "sg:province":"Bayern",
    "wof:name":"G\u00fcven Islamisches Beerdigungs- Institut Inh. Rona Dorsan E.k.",
    "wof:placetype":"venue"
},
  "geometry": {"coordinates":[11.502648,48.13364],"type":"Point"}
}