{
  "type": "Feature",
  "properties": {
    "iso:country":"DE",
    "sg:address":"Seeblick 26",
    "sg:city":"W\u00f6rthsee",
    "sg:phone":"+49 8143/1010",
    "sg:postcode":"82237",
    "sg:province":"Bayern",
    "wof:name":"Industrievertrieb M\u00fcller Gmbh",
    "wof:placetype":"venue"
},
  "geometry": {"coordinates":[11.1968412399,48.0744819641],"type":"Point"}
}