{
  "type": "Feature",
  "properties": {
    "iso:country":"DE",
    "sg:address":"Kandelbornweg 13",
    "sg:city":"Bensheim",
    "sg:phone":"+49 6251/68299",
    "sg:postcode":"64625",
    "sg:province":"Hessen",
    "wof:name":"Acm-werbeagentur",
    "wof:placetype":"venue"
},
  "geometry": {"coordinates":[8.6735343933,49.6809692383],"type":"Point"}
}