{
  "type": "Feature",
  "properties": {
    "iso:country":"DE",
    "sg:address":"Augustenstr. 2",
    "sg:city":"L\u00fcbeck",
    "sg:phone":"+49 451/791242",
    "sg:postcode":"23564",
    "sg:province":"Schleswig-Holstein",
    "wof:name":"Wiese Gmbh",
    "wof:placetype":"venue"
},
  "geometry": {"coordinates":[10.698272,53.862141],"type":"Point"}
}