{
  "type": "Feature",
  "properties": {
    "iso:country":"DE",
    "sg:address":"Gerberstr. 37",
    "sg:city":"Viersen",
    "sg:phone":"+49 2162/933800",
    "sg:postcode":"41748",
    "sg:province":"Nordrhein-Westfalen",
    "wof:name":"Fruhen Grundbesitz Gmbh & Co. Kg",
    "wof:placetype":"venue"
},
  "geometry": {"coordinates":[6.3996901512,51.2620925903],"type":"Point"}
}