{
  "type": "Feature",
  "properties": {
    "iso:country":"DE",
    "sg:address":"G\u00f6rlitzstr. 8",
    "sg:city":"Braunschweig",
    "sg:phone":"+49 531/601514",
    "sg:postcode":"38124",
    "sg:province":"Niedersachsen",
    "wof:name":"Atlv Niedersachsen Arbeitsgemein. Der Toto Lotto",
    "wof:placetype":"venue"
},
  "geometry": {"coordinates":[10.5258836746,52.2282905579],"type":"Point"}
}