{
  "type": "Feature",
  "properties": {
    "iso:country":"DE",
    "sg:address":"Dammstr. 4",
    "sg:city":"Bad Salzuflen",
    "sg:phone":"+49 5222/17396",
    "sg:postcode":"32105",
    "sg:province":"Nordrhein-Westfalen",
    "wof:name":"Restaurant Andreas",
    "wof:placetype":"venue"
},
  "geometry": {"coordinates":[8.7483072281,52.0857124329],"type":"Point"}
}