{
  "type": "Feature",
  "properties": {
    "iso:country":"DE",
    "sg:address":"Tannschachstr. 5",
    "sg:city":"Malsch",
    "sg:phone":"+49 7204/345",
    "sg:postcode":"76316",
    "sg:province":"Baden-W\u00fcrttemberg",
    "wof:name":"Rolf Thomas Architekt",
    "wof:placetype":"venue"
},
  "geometry": {"coordinates":[8.392422,48.869179],"type":"Point"}
}