{
  "type": "Feature",
  "properties": {
    "iso:country":"DE",
    "sg:address":"Am Rupertsberg 16",
    "sg:city":"Bingen",
    "sg:phone":"+49 4966/2192420",
    "sg:postcode":"55411",
    "sg:province":"Rheinland-Pfalz",
    "wof:name":"Georg Mattheus Gmbh",
    "wof:placetype":"venue"
},
  "geometry": {"coordinates":[9.7078104019,50.8680877686],"type":"Point"}
}