{
  "type": "Feature",
  "properties": {
    "iso:country":"DE",
    "sg:address":"Nietzschestr. 30",
    "sg:city":"Mannheim",
    "sg:phone":"+49 621/415860",
    "sg:postcode":"68165",
    "sg:province":"Baden-W\u00fcrttemberg",
    "wof:name":"Walter E. Senk",
    "wof:placetype":"venue"
},
  "geometry": {"coordinates":[8.4892406464,49.4796562195],"type":"Point"}
}