{
  "type": "Feature",
  "properties": {
    "iso:country":"DE",
    "sg:address":"Burgstr. 32",
    "sg:city":"Halle",
    "sg:phone":"+49 345/5223442",
    "sg:postcode":"06114",
    "sg:province":"Sachsen-Anhalt",
    "wof:name":"Deg Haus-service Gmbh",
    "wof:placetype":"venue"
},
  "geometry": {"coordinates":[11.9567613602,51.4957733154],"type":"Point"}
}