{
  "type": "Feature",
  "properties": {
    "iso:country":"DE",
    "sg:address":"Am Fresenberg 3a",
    "sg:city":"Eschweiler",
    "sg:phone":"+49 2403/20098",
    "sg:postcode":"52249",
    "sg:province":"Nordrhein-Westfalen",
    "wof:name":"Dammer Gmbh",
    "wof:placetype":"venue"
},
  "geometry": {"coordinates":[6.292156,50.811069],"type":"Point"}
}