{
  "type": "Feature",
  "properties": {
    "iso:country":"DE",
    "sg:address":"Lindauer Str. 11",
    "sg:city":"Kempten",
    "sg:phone":"+49 831/24052",
    "sg:postcode":"87435",
    "sg:province":"Bayern",
    "wof:name":"Hamburg-mannheimer Versicherungsgesellschaften",
    "wof:placetype":"venue"
},
  "geometry": {"coordinates":[10.3095960617,47.7232437134],"type":"Point"}
}