{
  "type": "Feature",
  "properties": {
    "iso:country":"DE",
    "sg:address":"Tonberg 25",
    "sg:city":"Mei\u00dfen",
    "sg:phone":"+49 3521/738783",
    "sg:postcode":"01662",
    "sg:province":"Sachsen",
    "wof:name":"Jochen Streubichen",
    "wof:placetype":"venue"
},
  "geometry": {"coordinates":[13.484477,51.165665],"type":"Point"}
}