{
  "type": "Feature",
  "properties": {
    "iso:country":"DE",
    "sg:address":"Carl-Zeiss-Str. 19",
    "sg:city":"Kamp-Lintfort",
    "sg:phone":"+49 2842/8247",
    "sg:postcode":"47475",
    "sg:province":"Nordrhein-Westfalen",
    "wof:name":"Wolf-peter Dittmer",
    "wof:placetype":"venue"
},
  "geometry": {"coordinates":[6.540218,51.484997],"type":"Point"}
}