{
  "type": "Feature",
  "properties": {
    "iso:country":"DE",
    "sg:address":"Dinscheder Str. 43",
    "sg:city":"Arnsberg",
    "sg:phone":"+49 2937/2366",
    "sg:postcode":"59823",
    "sg:province":"Nordrhein-Westfalen",
    "wof:name":"Pension J. P\u00f6ttgen",
    "wof:placetype":"venue"
},
  "geometry": {"coordinates":[8.1308507919,51.4026145935],"type":"Point"}
}