{
  "type": "Feature",
  "properties": {
    "iso:country":"DE",
    "sg:address":"Hegweg 10",
    "sg:city":"Langen",
    "sg:phone":"+49 6103/21994",
    "sg:postcode":"63225",
    "sg:province":"Hessen",
    "wof:name":"Elfriede Dr\u00f6ll",
    "wof:placetype":"venue"
},
  "geometry": {"coordinates":[8.6818132401,49.9909515381],"type":"Point"}
}