{
  "type": "Feature",
  "properties": {
    "iso:country":"DE",
    "sg:address":"Hindenburgstr. 1",
    "sg:city":"P\u00f6cking",
    "sg:phone":"+49 8157/3626",
    "sg:postcode":"82343",
    "sg:province":"Bayern",
    "wof:name":"P\u00f6ckinger Stuben",
    "wof:placetype":"venue"
},
  "geometry": {"coordinates":[11.3022422791,47.9682350159],"type":"Point"}
}