{
  "type": "Feature",
  "properties": {
    "iso:country":"DE",
    "sg:address":"Albertistr. 8",
    "sg:city":"Reichenbach",
    "sg:phone":"+49 3765/13474",
    "sg:postcode":"08468",
    "sg:province":"Sachsen",
    "wof:name":"M. Krause",
    "wof:placetype":"venue"
},
  "geometry": {"coordinates":[12.301743,50.624512],"type":"Point"}
}