{
  "type": "Feature",
  "properties": {
    "iso:country":"DE",
    "sg:address":"Lokstedter Steindamm 29",
    "sg:city":"Hamburg",
    "sg:phone":"+49 40/5602901",
    "sg:postcode":"22529",
    "sg:province":"Hamburg",
    "wof:name":"Rancka-werbung",
    "wof:placetype":"venue"
},
  "geometry": {"coordinates":[9.966463,53.595715],"type":"Point"}
}