{
  "type": "Feature",
  "properties": {
    "iso:country":"DE",
    "sg:address":"Lindenstr. 23",
    "sg:city":"Mutterstadt",
    "sg:phone":"+49 6234/4675",
    "sg:postcode":"67112",
    "sg:province":"Rheinland-Pfalz",
    "wof:name":"L. Und K. Brose",
    "wof:placetype":"venue"
},
  "geometry": {"coordinates":[8.360676,49.440174],"type":"Point"}
}