{
  "type": "Feature",
  "properties": {
    "iso:country":"DE",
    "sg:address":"Luth.-Kirch-Str. 67",
    "sg:city":"Krefeld",
    "sg:postcode":"47798",
    "sg:province":"Nordrhein-Westfalen",
    "wof:name":"Werbeb\u00fcro Handels- Und Verlagsvertretungen",
    "wof:placetype":"venue"
},
  "geometry": {"coordinates":[6.5623049736,51.333896637],"type":"Point"}
}