{
  "type": "Feature",
  "properties": {
    "iso:country":"DE",
    "sg:address":"Im Erfenbacher Tal 15",
    "sg:city":"Kaiserslautern",
    "sg:phone":"+49 631/55501",
    "sg:postcode":"67661",
    "sg:province":"Rheinland-Pfalz",
    "wof:name":"P. Nikolic",
    "wof:placetype":"venue"
},
  "geometry": {"coordinates":[7.7038598061,49.4213790894],"type":"Point"}
}