{
  "type": "Feature",
  "properties": {
    "iso:country":"DE",
    "sg:address":"Sterzenbacher Str. 45",
    "sg:city":"Hilchenbach",
    "sg:phone":"+49 2733/3180",
    "sg:postcode":"57271",
    "sg:province":"Nordrhein-Westfalen",
    "wof:name":"Gisela Pott",
    "wof:placetype":"venue"
},
  "geometry": {"coordinates":[8.11860466,50.9921875],"type":"Point"}
}