{
  "type": "Feature",
  "properties": {
    "iso:country":"DE",
    "sg:address":"Harpel 10",
    "sg:city":"Wippingen",
    "sg:phone":"+49 4966/685",
    "sg:postcode":"26892",
    "sg:province":"Niedersachsen",
    "wof:name":"Hermann Wolters",
    "wof:placetype":"venue"
},
  "geometry": {"coordinates":[7.414943,52.908928],"type":"Point"}
}