{
  "type": "Feature",
  "properties": {
    "iso:country":"DE",
    "sg:city":"Leimen",
    "sg:phone":"+49 6226/991315",
    "sg:postcode":"69181",
    "sg:province":"Baden-W\u00fcrttemberg",
    "wof:name":"One World \u00dcbersetzungen",
    "wof:placetype":"venue"
},
  "geometry": {"coordinates":[8.68891,49.349026],"type":"Point"}
}