{
  "type": "Feature",
  "properties": {
    "iso:country":"DE",
    "sg:address":"Hauptstr. 35",
    "sg:city":"Grebenhain",
    "sg:phone":"+49 6644/1298",
    "sg:postcode":"36355",
    "sg:province":"Hessen",
    "wof:name":"F. Worner Und K. Twelker",
    "wof:placetype":"venue"
},
  "geometry": {"coordinates":[9.3342075348,50.4887008667],"type":"Point"}
}