{
  "type": "Feature",
  "properties": {
    "iso:country":"DE",
    "sg:address":"M\u00fchlstra\u00dfe34",
    "sg:city":"Schwabenheim",
    "sg:phone":"+49 6130/306",
    "sg:postcode":"55279",
    "wof:name":"Selztal-apotheke",
    "wof:placetype":"venue"
},
  "geometry": {"coordinates":[8.09593,49.932049],"type":"Point"}
}