{
  "type": "Feature",
  "properties": {
    "iso:country":"DE",
    "sg:address":"Annastr 74",
    "sg:city":"Stahnsdorf",
    "sg:phone":"+49 3329/63860",
    "sg:postcode":"14532",
    "sg:province":"Brandenburg",
    "wof:name":"T.e.c. Ingenieurb\u00fcro Troitzsch",
    "wof:placetype":"venue"
},
  "geometry": {"coordinates":[13.217463,52.374588],"type":"Point"}
}