{
  "type": "Feature",
  "properties": {
    "iso:country":"DE",
    "sg:address":"Uhlandstr. 42",
    "sg:city":"Fellbach",
    "sg:phone":"+49 711/5174380",
    "sg:postcode":"70736",
    "sg:province":"Baden-W\u00fcrttemberg",
    "wof:name":"Icfs Institut F\u00fcr Angewandte Chemie- U. Chem. Technol. S\u00fcd-",
    "wof:placetype":"venue"
},
  "geometry": {"coordinates":[9.2664346695,48.8305740356],"type":"Point"}
}