{
  "type": "Feature",
  "properties": {
    "iso:country":"DE",
    "sg:address":"Bollertstr. 20",
    "sg:city":"Uslar",
    "sg:phone":"+49 5573/1664",
    "sg:postcode":"37170",
    "sg:province":"Niedersachsen",
    "wof:name":"Sandra Stadermann Praxis F\u00fcr Krankengymnastik",
    "wof:placetype":"venue"
},
  "geometry": {"coordinates":[9.73805,51.664398],"type":"Point"}
}