{
  "type": "Feature",
  "properties": {
    "iso:country":"DE",
    "sg:address":"Thanhoferstra\u00dfe 101",
    "sg:city":"Lichtentanne",
    "sg:phone":"+49 375/527364",
    "sg:postcode":"08115",
    "sg:province":"Sachsen",
    "wof:name":"Industrieservice Dieter Voigt Seit 1911",
    "wof:placetype":"venue"
},
  "geometry": {"coordinates":[12.4026899338,50.6926002502],"type":"Point"}
}