{
  "type": "Feature",
  "properties": {
    "iso:country":"DE",
    "sg:address":"August-Bebel-Str. 10",
    "sg:city":"Schwerin",
    "sg:phone":"+49 385/43071",
    "sg:postcode":"19055",
    "sg:province":"Mecklenburg-Vorpommern",
    "wof:name":"Wagner & Weinke Gbr Vermessungsb\u00fcro",
    "wof:placetype":"venue"
},
  "geometry": {"coordinates":[11.413936615,53.6322517395],"type":"Point"}
}