{
  "type": "Feature",
  "properties": {
    "iso:country":"DE",
    "sg:address":"Am Rathaus 1",
    "sg:city":"Neukirchen",
    "sg:phone":"+49 9663/91300",
    "sg:postcode":"92259",
    "sg:province":"Bayern",
    "wof:name":"Gemeinde Neukirchen B. Sulzbach-rosenberg",
    "wof:placetype":"venue"
},
  "geometry": {"coordinates":[11.623714447,49.527141571],"type":"Point"}
}