{
  "type": "Feature",
  "properties": {
    "iso:country":"DE",
    "sg:address":"Wasserstr. 11",
    "sg:city":"Freiburg",
    "sg:phone":"+49 761/26342",
    "sg:postcode":"79098",
    "sg:province":"Baden-W\u00fcrttemberg",
    "wof:name":"Ursula Hermle",
    "wof:placetype":"venue"
},
  "geometry": {"coordinates":[7.850336,47.997585],"type":"Point"}
}