{
  "type": "Feature",
  "properties": {
    "iso:country":"DE",
    "sg:address":"K\u00f6nigstr. 10",
    "sg:city":"Rottweil",
    "sg:phone":"+49 741/41177",
    "sg:postcode":"78628",
    "sg:province":"Baden-W\u00fcrttemberg",
    "wof:name":"Dr. Med. Hans-j. G\u00f6rlich Arzt F\u00fcr Allgemeinmedizin",
    "wof:placetype":"venue"
},
  "geometry": {"coordinates":[8.6294488907,48.1639328003],"type":"Point"}
}