{
  "type": "Feature",
  "properties": {
    "iso:country":"DE",
    "sg:address":"Zum Vo\u00dfmeyer 6",
    "sg:city":"Riede",
    "sg:phone":"+49 4294/387",
    "sg:postcode":"27339",
    "sg:province":"Niedersachsen",
    "wof:name":"Friedrich Schweers",
    "wof:placetype":"venue"
},
  "geometry": {"coordinates":[8.968175,52.956177],"type":"Point"}
}