{
  "type": "Feature",
  "properties": {
    "iso:country":"DE",
    "sg:address":"Brensbacher Str. 21",
    "sg:city":"Reinheim",
    "sg:phone":"+49 6162/4521",
    "sg:postcode":"64354",
    "sg:province":"Hessen",
    "wof:name":"G-i-b General\u00fcbernehmer F\u00fcr Integrierte Bauleistungen Gmbh",
    "wof:placetype":"venue"
},
  "geometry": {"coordinates":[8.8471412659,49.8225097656],"type":"Point"}
}