{
  "type": "Feature",
  "properties": {
    "iso:country":"DE",
    "sg:address":"Im Rosengartenkeller",
    "sg:city":"Mannheim",
    "sg:phone":"+49 621/4106404",
    "sg:postcode":"68161",
    "sg:province":"Baden-W\u00fcrttemberg",
    "wof:name":"Fire & Fun The Hottest Place In Town",
    "wof:placetype":"venue"
},
  "geometry": {"coordinates":[8.4764900208,49.4850311279],"type":"Point"}
}