{
  "type": "Feature",
  "properties": {
    "iso:country":"DE",
    "sg:address":"Am Krug 14",
    "sg:city":"M\u00fcnster",
    "sg:phone":"+49 251/797711",
    "sg:postcode":"48151",
    "sg:province":"Nordrhein-Westfalen",
    "wof:name":"F. B\u00fcrling Verm\u00f6gensverwaltung Gmbh",
    "wof:placetype":"venue"
},
  "geometry": {"coordinates":[7.620891,51.949207],"type":"Point"}
}