{
  "type": "Feature",
  "properties": {
    "iso:country":"DE",
    "sg:address":"Altstadt 17",
    "sg:city":"Lengerich",
    "sg:phone":"+49 5481/1030",
    "sg:postcode":"49525",
    "sg:province":"Nordrhein-Westfalen",
    "wof:name":"Tchibo",
    "wof:placetype":"venue"
},
  "geometry": {"coordinates":[7.8497571945,52.1895332336],"type":"Point"}
}