{
  "type": "Feature",
  "properties": {
    "iso:country":"DE",
    "sg:address":"Nersinger Str. 10",
    "sg:city":"Elchingen",
    "sg:phone":"+49 7308/3077",
    "sg:postcode":"89275",
    "sg:province":"Bayern",
    "wof:name":"Eckstein Ohg",
    "wof:placetype":"venue"
},
  "geometry": {"coordinates":[10.100768,48.4529],"type":"Point"}
}