{
  "type": "Feature",
  "properties": {
    "iso:country":"DE",
    "sg:address":"K\u00f6lner Str. 12",
    "sg:city":"Erpel",
    "sg:phone":"+49 2644/2259",
    "sg:postcode":"53579",
    "sg:province":"Rheinland-Pfalz",
    "wof:name":"Sparkasse Neuwied",
    "wof:placetype":"venue"
},
  "geometry": {"coordinates":[7.237985,50.582783],"type":"Point"}
}