{
  "type": "Feature",
  "properties": {
    "iso:country":"DE",
    "sg:address":"Mundsburger Damm 2",
    "sg:city":"Hamburg",
    "sg:phone":"+49 40/2204571",
    "sg:postcode":"22087",
    "sg:province":"Hamburg",
    "wof:name":"Henkel Generalagentur Der N\u00fcrnberger Versicherung",
    "wof:placetype":"venue"
},
  "geometry": {"coordinates":[10.0181980133,53.5644493103],"type":"Point"}
}