{
  "type": "Feature",
  "properties": {
    "iso:country":"DE",
    "sg:address":"Freundallee 13",
    "sg:city":"Hannover",
    "sg:phone":"+49 511/28880",
    "sg:postcode":"30173",
    "sg:province":"Niedersachsen",
    "wof:name":"Bahlo, K\u00f6hnke, Stosberg & Partner Gmbh",
    "wof:placetype":"venue"
},
  "geometry": {"coordinates":[9.7723264694,52.3669815063],"type":"Point"}
}