{
  "type": "Feature",
  "properties": {
    "iso:country":"DE",
    "sg:address":"Verdistra\u00dfe 1",
    "sg:city":"Baldham",
    "sg:phone":"+49 8106/6330",
    "sg:postcode":"85598",
    "sg:province":"Bayern",
    "wof:name":"Musik & Kunst: Oper - Konzerte - Museen - Ausstell",
    "wof:placetype":"venue"
},
  "geometry": {"coordinates":[11.7923593521,48.1066169739],"type":"Point"}
}