{
  "type": "Feature",
  "properties": {
    "iso:country":"DE",
    "sg:address":"Dorfstr. 8",
    "sg:city":"Rimbach",
    "sg:phone":"+49 9941/1372",
    "sg:postcode":"93485",
    "sg:province":"Bayern",
    "wof:name":"Franz Perlinger",
    "wof:placetype":"venue"
},
  "geometry": {"coordinates":[12.8851070404,49.2262611389],"type":"Point"}
}