{
  "type": "Feature",
  "properties": {
    "iso:country":"DE",
    "sg:address":"Kirchweg 80",
    "sg:city":"Kassel",
    "sg:phone":"+49 561/771857",
    "sg:postcode":"34119",
    "sg:province":"Hessen",
    "wof:name":"Thomas Reitze",
    "wof:placetype":"venue"
},
  "geometry": {"coordinates":[9.4623384476,51.3173828125],"type":"Point"}
}