{
  "type": "Feature",
  "properties": {
    "iso:country":"DE",
    "sg:address":"Grundelbachstr. 112 c",
    "sg:city":"Weinheim",
    "sg:postcode":"69469",
    "sg:province":"Baden-W\u00fcrttemberg",
    "wof:name":"H\u00f6rger\u00e4te Von Elm Weinheim Gmbh & Co. Kg",
    "wof:placetype":"venue"
},
  "geometry": {"coordinates":[8.6761817932,49.5525131226],"type":"Point"}
}