{
  "type": "Feature",
  "properties": {
    "iso:country":"DE",
    "sg:address":"Am Lindachsgraben 11",
    "sg:city":"Wiesentheid",
    "sg:phone":"+49 9383/1053",
    "sg:postcode":"97353",
    "sg:province":"Bayern",
    "wof:name":"Alois Kohlert Architekt",
    "wof:placetype":"venue"
},
  "geometry": {"coordinates":[10.34767,49.79517],"type":"Point"}
}