{
  "type": "Feature",
  "properties": {
    "iso:country":"DE",
    "sg:address":"Schulstr.",
    "sg:city":"Nochern",
    "sg:postcode":"56357",
    "sg:province":"Rheinland-Pfalz",
    "wof:name":"Heuser Hei\u00dfmangel",
    "wof:placetype":"venue"
},
  "geometry": {"coordinates":[7.7247300148,50.1765785217],"type":"Point"}
}