{
  "type": "Feature",
  "properties": {
    "iso:country":"DE",
    "sg:address":"Bergstr. 231",
    "sg:city":"Marl",
    "sg:phone":"+49 2365/15604",
    "sg:postcode":"45770",
    "sg:province":"Nordrhein-Westfalen",
    "wof:name":"Dea Mineral\u00f6l Ag",
    "wof:placetype":"venue"
},
  "geometry": {"coordinates":[7.10187006,51.6581687927],"type":"Point"}
}