{
  "type": "Feature",
  "properties": {
    "iso:country":"DE",
    "sg:address":"Silvrettastr. 40",
    "sg:city":"Stuttgart",
    "sg:phone":"+49 711/330619",
    "sg:postcode":"70327",
    "sg:province":"Baden-W\u00fcrttemberg",
    "wof:name":"Dieter Straubert",
    "wof:placetype":"venue"
},
  "geometry": {"coordinates":[9.2501535416,48.7829246521],"type":"Point"}
}