{
  "type": "Feature",
  "properties": {
    "iso:country":"DE",
    "sg:address":"Varnhagenstr. 8",
    "sg:city":"Bad Arolsen",
    "sg:postcode":"34454",
    "sg:province":"Hessen",
    "wof:name":"Aldi Gmbh & Co. Kg",
    "wof:placetype":"venue"
},
  "geometry": {"coordinates":[9.011882782,51.3822364807],"type":"Point"}
}