{
  "type": "Feature",
  "properties": {
    "iso:country":"DE",
    "sg:address":"Au\u00dferhalb 1",
    "sg:city":"Bechtheim",
    "sg:phone":"+49 6242/3227",
    "sg:postcode":"67595",
    "sg:province":"Rheinland-Pfalz",
    "wof:name":"Weinkommission Walter Schmitt Gmbh",
    "wof:placetype":"venue"
},
  "geometry": {"coordinates":[8.2835950851,49.7246856689],"type":"Point"}
}