{
  "type": "Feature",
  "properties": {
    "iso:country":"DE",
    "sg:address":"Haaresgrund 9",
    "sg:city":"Coburg",
    "sg:phone":"+49 9561/25888",
    "sg:postcode":"96450",
    "sg:province":"Bayern",
    "wof:name":"Bernd Winkler Heilpraktiker",
    "wof:placetype":"venue"
},
  "geometry": {"coordinates":[11.01167202,50.2540779114],"type":"Point"}
}