{
  "type": "Feature",
  "properties": {
    "iso:country":"DE",
    "sg:address":"po 2264",
    "sg:city":"bruchsal",
    "sg:phone":"+49 7251/68513",
    "sg:postcode":"76612",
    "sg:province":"Baden-W\u00fcrttemberg",
    "wof:name":"Clairbioreiniger",
    "wof:placetype":"venue"
},
  "geometry": {"coordinates":[8.597700119,49.1257896423],"type":"Point"}
}