{
  "type": "Feature",
  "properties": {
    "iso:country":"DE",
    "sg:address":"Paulistr. 5",
    "sg:city":"Bautzen",
    "sg:phone":"+49 3591/24093",
    "sg:postcode":"02625",
    "sg:province":"Sachsen",
    "wof:name":"Torsten Funke",
    "wof:placetype":"venue"
},
  "geometry": {"coordinates":[14.4407844543,51.1786956787],"type":"Point"}
}