{
  "type": "Feature",
  "properties": {
    "iso:country":"DE",
    "sg:address":"Rochlitzer Str. 5",
    "sg:city":"Geringswalde",
    "sg:phone":"+49 37382/81217",
    "sg:postcode":"09326",
    "sg:province":"Sachsen",
    "wof:name":"Arthur Grohkraftfutterwerk Gmbh",
    "wof:placetype":"venue"
},
  "geometry": {"coordinates":[12.903262,51.072098],"type":"Point"}
}