{
  "type": "Feature",
  "properties": {
    "iso:country":"DE",
    "sg:address":"Grubholzer Str. 4",
    "sg:city":"Rosenheim",
    "sg:phone":"+49 8031/44914",
    "sg:postcode":"83026",
    "sg:province":"Bayern",
    "wof:name":"Bistro Late Night",
    "wof:placetype":"venue"
},
  "geometry": {"coordinates":[12.092354,47.850384],"type":"Point"}
}