{
  "type": "Feature",
  "properties": {
    "iso:country":"DE",
    "sg:address":"Obere Marktstr. 9",
    "sg:city":"Neumarkt",
    "sg:phone":"+49 9181/6373",
    "sg:postcode":"92318",
    "sg:province":"Bayern",
    "wof:name":"Mittlerer Ganskeller",
    "wof:placetype":"venue"
},
  "geometry": {"coordinates":[11.4583330154,49.2808876038],"type":"Point"}
}