{
  "type": "Feature",
  "properties": {
    "iso:country":"DE",
    "sg:address":"Am Dreschplatz 15",
    "sg:city":"Linsburg",
    "sg:phone":"+49 5027/902690",
    "sg:postcode":"31636",
    "sg:province":"Niedersachsen",
    "wof:name":"Schlierf Heizungsbau",
    "wof:placetype":"venue"
},
  "geometry": {"coordinates":[9.3009634018,52.5914611816],"type":"Point"}
}