{
  "type": "Feature",
  "properties": {
    "iso:country":"DE",
    "sg:address":"Morgenstr. 60",
    "sg:city":"Unna",
    "sg:phone":"+49 2303/253120",
    "sg:postcode":"59423",
    "sg:province":"Nordrhein-Westfalen",
    "wof:name":"Schemm Bautenschutz- Vermittlungs-gmbh",
    "wof:placetype":"venue"
},
  "geometry": {"coordinates":[7.7000789642,51.5354156494],"type":"Point"}
}