{
  "type": "Feature",
  "properties": {
    "iso:country":"DE",
    "sg:address":"Lindenall. 27",
    "sg:city":"Wuppertal",
    "sg:phone":"+49 4957/3196363",
    "sg:postcode":"42349",
    "sg:province":"Nordrhein-Westfalen",
    "wof:name":"Eggersmann Metallwaren Gmbh & Co Kg",
    "wof:placetype":"venue"
},
  "geometry": {"coordinates":[8.808847,52.176285],"type":"Point"}
}