{
  "type": "Feature",
  "properties": {
    "iso:country":"DE",
    "sg:address":"Scheidhof",
    "sg:city":"Merzig",
    "sg:postcode":"66663",
    "sg:province":"Saarland",
    "wof:name":"Rudolf Moos",
    "wof:placetype":"venue"
},
  "geometry": {"coordinates":[6.526759,49.451485],"type":"Point"}
}