{
  "type": "Feature",
  "properties": {
    "iso:country":"DE",
    "sg:address":"Sonnenstr. 9",
    "sg:city":"Kirchheim",
    "sg:phone":"+49 7021/46046",
    "sg:postcode":"73230",
    "sg:province":"Baden-W\u00fcrttemberg",
    "wof:name":"Bistro Trotzk\u00f6pfle",
    "wof:placetype":"venue"
},
  "geometry": {"coordinates":[9.8545131683,49.6566886902],"type":"Point"}
}