{
  "type": "Feature",
  "properties": {
    "iso:country":"DE",
    "sg:address":"Passauer Str. 3",
    "sg:city":"Grafenau",
    "sg:postcode":"94481",
    "sg:province":"Bayern",
    "wof:name":"Zambelli Gmbh & Co. Kg",
    "wof:placetype":"venue"
},
  "geometry": {"coordinates":[13.395833,48.807796],"type":"Point"}
}