{
  "type": "Feature",
  "properties": {
    "iso:country":"DE",
    "sg:address":"Hallesche Str. 20",
    "sg:city":"Dortmund",
    "sg:phone":"+49 231/594481",
    "sg:postcode":"44143",
    "sg:province":"Nordrhein-Westfalen",
    "wof:name":"Schwarzer Kamp",
    "wof:placetype":"venue"
},
  "geometry": {"coordinates":[7.4887499809,51.5181503296],"type":"Point"}
}