{
  "type": "Feature",
  "properties": {
    "iso:country":"DE",
    "sg:address":"Stollenweg 4",
    "sg:city":"N\u00fcmbrecht",
    "sg:phone":"+49 2291/6091",
    "sg:postcode":"51588",
    "sg:province":"Nordrhein-Westfalen",
    "wof:name":"Rathgeber Gmbh Marketingservice",
    "wof:placetype":"venue"
},
  "geometry": {"coordinates":[7.5546851158,50.9344329834],"type":"Point"}
}