{
  "type": "Feature",
  "properties": {
    "iso:country":"DE",
    "sg:address":"H\u00f6ster Weg 14",
    "sg:city":"Goch",
    "sg:phone":"+49 2823/98920",
    "sg:postcode":"47574",
    "sg:province":"Nordrhein-Westfalen",
    "wof:name":"Plus Warenhandels Gmbh & Co. Ohg",
    "wof:placetype":"venue"
},
  "geometry": {"coordinates":[6.1712918282,51.6695137024],"type":"Point"}
}