{
  "type": "Feature",
  "properties": {
    "iso:country":"DE",
    "sg:address":"Jurastr. 18",
    "sg:city":"Titting",
    "sg:phone":"+49 9147/318",
    "sg:postcode":"85135",
    "sg:province":"Bayern",
    "wof:name":"Josef Flieger",
    "wof:placetype":"venue"
},
  "geometry": {"coordinates":[11.187825,49.035069],"type":"Point"}
}