{
  "type": "Feature",
  "properties": {
    "iso:country":"DE",
    "sg:address":"Hilpoltsteiner Str. 19c",
    "sg:city":"Roth",
    "sg:phone":"+49 9171/892211",
    "sg:postcode":"91154",
    "sg:province":"Bayern",
    "wof:name":"K. Krausser Glas- Und Porzellanwaren",
    "wof:placetype":"venue"
},
  "geometry": {"coordinates":[11.0947380066,49.2450561523],"type":"Point"}
}