{
  "type": "Feature",
  "properties": {
    "iso:country":"DE",
    "sg:address":"An der Rennbahn 4",
    "sg:city":"Forst",
    "sg:postcode":"03149",
    "sg:province":"Brandenburg",
    "wof:name":"Bundesverband Mittel- St\u00e4ndischer Wirtschaft",
    "wof:placetype":"venue"
},
  "geometry": {"coordinates":[14.6041049957,51.6906814575],"type":"Point"}
}