{
  "type": "Feature",
  "properties": {
    "iso:country":"DE",
    "sg:address":"Alt-Engelbostel 12",
    "sg:city":"Langenhagen",
    "sg:phone":"+49 511/743889",
    "sg:postcode":"30855",
    "sg:province":"Niedersachsen",
    "wof:name":"Fr. Engelke",
    "wof:placetype":"venue"
},
  "geometry": {"coordinates":[9.6484975815,52.4466896057],"type":"Point"}
}