{
  "type": "Feature",
  "properties": {
    "iso:country":"DE",
    "sg:address":"Hemmerder Dorfstr. 44",
    "sg:city":"Unna",
    "sg:postcode":"59427",
    "sg:province":"Nordrhein-Westfalen",
    "wof:name":"Rudolf Herberg",
    "wof:placetype":"venue"
},
  "geometry": {"coordinates":[7.810239,51.548531],"type":"Point"}
}