{
  "type": "Feature",
  "properties": {
    "iso:country":"DE",
    "sg:address":"Robert-Koch-Platz 8",
    "sg:city":"Wuppertal",
    "sg:phone":"+49 202/81396",
    "sg:postcode":"42283",
    "sg:province":"Nordrhein-Westfalen",
    "wof:name":"Lieselotte Anders",
    "wof:placetype":"venue"
},
  "geometry": {"coordinates":[7.180509,51.277832],"type":"Point"}
}