{
  "type": "Feature",
  "properties": {
    "iso:country":"DE",
    "sg:city":"Erlangen",
    "sg:phone":"+49 9131/993750",
    "sg:postcode":"91052",
    "sg:province":"Bayern",
    "wof:name":"Freier Bestattungsredner Bernhard Wieser",
    "wof:placetype":"venue"
},
  "geometry": {"coordinates":[11.002575,49.597954],"type":"Point"}
}