{
  "type": "Feature",
  "properties": {
    "iso:country":"DE",
    "sg:address":"H\u00f6ltenweg 97",
    "sg:city":"M\u00fcnster",
    "sg:phone":"+49 251/962550",
    "sg:postcode":"48155",
    "sg:province":"Nordrhein-Westfalen",
    "wof:name":"Imi-klimatechnik",
    "wof:placetype":"venue"
},
  "geometry": {"coordinates":[7.652617,51.924519],"type":"Point"}
}