{
  "type": "Feature",
  "properties": {
    "iso:country":"DE",
    "sg:address":"Dorfstr. 28",
    "sg:city":"Strullendorf",
    "sg:phone":"+49 9543/850468",
    "sg:postcode":"96129",
    "sg:province":"Bayern",
    "wof:name":"Thomas Pfister S\u00e4gewerk",
    "wof:placetype":"venue"
},
  "geometry": {"coordinates":[10.9944343567,49.8657493591],"type":"Point"}
}