{
  "type": "Feature",
  "properties": {
    "iso:country":"DE",
    "sg:address":"Dobacher Str. 113",
    "sg:city":"W\u00fcrselen",
    "sg:phone":"+49 2405/93106",
    "sg:postcode":"52146",
    "sg:province":"Nordrhein-Westfalen",
    "wof:name":"Wilhelm Keulers",
    "wof:placetype":"venue"
},
  "geometry": {"coordinates":[6.1503229141,50.8135948181],"type":"Point"}
}