{
  "type": "Feature",
  "properties": {
    "iso:country":"DE",
    "sg:address":"Heisinger Str. 27",
    "sg:city":"Essen",
    "sg:postcode":"45134",
    "sg:province":"Nordrhein-Westfalen",
    "wof:name":"Skigemeinschaft Niederrhein E.v.",
    "wof:placetype":"venue"
},
  "geometry": {"coordinates":[7.0251998901,51.4178771973],"type":"Point"}
}