{
  "type": "Feature",
  "properties": {
    "iso:country":"DE",
    "sg:address":"K\u00f6nig-Wilhelm-Str. 99",
    "sg:city":"Ilsfeld",
    "sg:phone":"+49 7062/96647",
    "sg:postcode":"74360",
    "sg:province":"Baden-W\u00fcrttemberg",
    "wof:name":"Roland Braun",
    "wof:placetype":"venue"
},
  "geometry": {"coordinates":[9.2403793335,49.0550575256],"type":"Point"}
}