{
  "type": "Feature",
  "properties": {
    "iso:country":"DE",
    "sg:address":"Humboldtstr. 8 a",
    "sg:city":"Durmersheim",
    "sg:phone":"+49 7245/938602",
    "sg:postcode":"76448",
    "sg:province":"Baden-W\u00fcrttemberg",
    "wof:name":"F. Zimmermann Immobilienmakler",
    "wof:placetype":"venue"
},
  "geometry": {"coordinates":[8.2804632187,48.9413833618],"type":"Point"}
}