{
  "type": "Feature",
  "properties": {
    "iso:country":"DE",
    "sg:address":"Bahnhofstr. 6",
    "sg:city":"Unna",
    "sg:phone":"+49 2303/12332",
    "sg:postcode":"59423",
    "sg:province":"Nordrhein-Westfalen",
    "wof:name":"Gebr. Wigger Inh. Hans-peter Wigger",
    "wof:placetype":"venue"
},
  "geometry": {"coordinates":[7.6903009415,51.5353088379],"type":"Point"}
}