{
  "type": "Feature",
  "properties": {
    "iso:country":"DE",
    "sg:address":"Sperberhorst 6",
    "sg:city":"Hamburg",
    "sg:postcode":"22459",
    "sg:province":"Hamburg",
    "wof:name":"Chat For Free",
    "wof:placetype":"venue"
},
  "geometry": {"coordinates":[9.955533,53.63377],"type":"Point"}
}