{
  "type": "Feature",
  "properties": {
    "iso:country":"DE",
    "sg:address":"Im weissen Holz 7",
    "sg:city":"Eppertshausen",
    "sg:phone":"+49 6071/31080",
    "sg:postcode":"64859",
    "sg:province":"Hessen",
    "wof:name":"Kosmetik Lohnhersteller Cosmetic Service Gmbh",
    "wof:placetype":"venue"
},
  "geometry": {"coordinates":[8.86352,49.945919],"type":"Point"}
}