{
  "type": "Feature",
  "properties": {
    "iso:country":"DE",
    "sg:address":"Friedrichstr. 72",
    "sg:city":"Balingen",
    "sg:phone":"+49 4974/339590",
    "sg:postcode":"72336",
    "sg:province":"Baden-W\u00fcrttemberg",
    "wof:name":"Volksbank Balingen Eg",
    "wof:placetype":"venue"
},
  "geometry": {"coordinates":[8.850346,48.271545],"type":"Point"}
}