{
  "type": "Feature",
  "properties": {
    "iso:country":"DE",
    "sg:address":"Alte Weberei 12",
    "sg:city":"Kaufbeuren",
    "sg:phone":"+49 8341/109597",
    "sg:postcode":"87600",
    "sg:province":"Bayern",
    "wof:name":"Pohl V\u00f6lsch Und Zinner Rechtsanw\u00e4lte",
    "wof:placetype":"venue"
},
  "geometry": {"coordinates":[10.6230382919,47.883228302],"type":"Point"}
}