{
  "type": "Feature",
  "properties": {
    "iso:country":"DE",
    "sg:address":"Lossastr. 19",
    "sg:city":"Eilenburg",
    "sg:postcode":"04838",
    "sg:province":"Sachsen",
    "wof:name":"Regina Werner",
    "wof:placetype":"venue"
},
  "geometry": {"coordinates":[12.650188,51.466843],"type":"Point"}
}