{
  "type": "Feature",
  "properties": {
    "iso:country":"DE",
    "sg:address":"Schlei\u00dfheimer Str. 6",
    "sg:city":"Dachau",
    "sg:phone":"+49 8131/84384",
    "sg:postcode":"85221",
    "sg:province":"Bayern",
    "wof:name":"Robert Reiter Landmaschinen Gmbh",
    "wof:placetype":"venue"
},
  "geometry": {"coordinates":[11.438082,48.256634],"type":"Point"}
}