{
  "type": "Feature",
  "properties": {
    "iso:country":"DE",
    "sg:address":"Olsdorf 9",
    "sg:city":"Alfter",
    "sg:phone":"+49 2222/4270",
    "sg:postcode":"53347",
    "sg:province":"Nordrhein-Westfalen",
    "wof:name":"Wolf & Bergmann",
    "wof:placetype":"venue"
},
  "geometry": {"coordinates":[7.0046010017,50.7335968018],"type":"Point"}
}