{
  "type": "Feature",
  "properties": {
    "iso:country":"DE",
    "sg:address":"Dorfstr. 7",
    "sg:city":"Stolpe",
    "sg:phone":"+49 4326/99740",
    "sg:postcode":"24601",
    "sg:province":"Schleswig-Holstein",
    "wof:name":"Uwe Chojnacki",
    "wof:placetype":"venue"
},
  "geometry": {"coordinates":[10.220721,54.129993],"type":"Point"}
}