{
  "type": "Feature",
  "properties": {
    "iso:country":"DE",
    "sg:address":"Wallerfanger Str. 63",
    "sg:city":"Rehlingen-Siersburg",
    "sg:phone":"+49 6835/2628",
    "sg:postcode":"66780",
    "sg:province":"Saarland",
    "wof:name":"Klotz",
    "wof:placetype":"venue"
},
  "geometry": {"coordinates":[6.6869220734,49.3657836914],"type":"Point"}
}