{
  "type": "Feature",
  "properties": {
    "iso:country":"DE",
    "sg:address":"Alfred-Brodauf-Str. 17",
    "sg:city":"Aue",
    "sg:phone":"+49 3771/22828",
    "sg:postcode":"08280",
    "sg:province":"Sachsen",
    "wof:name":"Italienisches Restaurant",
    "wof:placetype":"venue"
},
  "geometry": {"coordinates":[12.7019729614,50.5846214294],"type":"Point"}
}