{
  "type": "Feature",
  "properties": {
    "iso:country":"DE",
    "sg:address":"Winzererstr. 106",
    "sg:city":"M\u00fcnchen",
    "sg:phone":"+49 89/3077410",
    "sg:postcode":"80797",
    "sg:province":"Bayern",
    "wof:name":"Dr. Gert Schmitt-nilson Patentanwalt",
    "wof:placetype":"venue"
},
  "geometry": {"coordinates":[11.5629920959,48.164352417],"type":"Point"}
}