{
  "type": "Feature",
  "properties": {
    "iso:country":"DE",
    "sg:address":"H\u00e4ldenrain 17",
    "sg:city":"Langenbrettach",
    "sg:phone":"+49 7139/7108",
    "sg:postcode":"74243",
    "sg:province":"Baden-W\u00fcrttemberg",
    "wof:name":"H. B\u00f6hringer",
    "wof:placetype":"venue"
},
  "geometry": {"coordinates":[9.3841848373,49.2226486206],"type":"Point"}
}