{
  "type": "Feature",
  "properties": {
    "iso:country":"DE",
    "sg:address":"Vennebecker Str. 50",
    "sg:city":"Porta Westfalica",
    "sg:phone":"+49 5731/6252",
    "sg:postcode":"32457",
    "sg:province":"Nordrhein-Westfalen",
    "wof:name":"Friedrich Rosemeier Bauunter- Nehmung Verwaltungs Gmbh",
    "wof:placetype":"venue"
},
  "geometry": {"coordinates":[8.870991,52.22261],"type":"Point"}
}