{
  "type": "Feature",
  "properties": {
    "iso:country":"DE",
    "sg:address":"Karlstr. 29",
    "sg:city":"Leipzig",
    "sg:phone":"+49 341/6510239",
    "sg:postcode":"04316",
    "sg:province":"Sachsen",
    "wof:name":"Dr. Med. Ursel Hergenhan",
    "wof:placetype":"venue"
},
  "geometry": {"coordinates":[12.441085,51.324203],"type":"Point"}
}