{
  "type": "Feature",
  "properties": {
    "iso:country":"DE",
    "sg:address":"Marienplatz 44",
    "sg:city":"Ravensburg",
    "sg:phone":"+49 751/88010",
    "sg:postcode":"88212",
    "sg:province":"Baden-W\u00fcrttemberg",
    "wof:name":"Werner Sp\u00e4th Klaus Schneider Und Partner",
    "wof:placetype":"venue"
},
  "geometry": {"coordinates":[9.6137466431,47.7829208374],"type":"Point"}
}