{
  "type": "Feature",
  "properties": {
    "iso:country":"DE",
    "sg:address":"Birkenstr. 5",
    "sg:city":"Langenselbold",
    "sg:phone":"+49 6184/61580",
    "sg:postcode":"63505",
    "sg:province":"Hessen",
    "wof:name":"Erotik Versand & Erotik Chat",
    "wof:placetype":"venue"
},
  "geometry": {"coordinates":[9.0298480988,50.1804733276],"type":"Point"}
}