{
  "type": "Feature",
  "properties": {
    "iso:country":"DE",
    "sg:address":"Zur Grotte 6 c",
    "sg:city":"Olsberg",
    "sg:phone":"+49 2962/2429",
    "sg:postcode":"59939",
    "sg:province":"Nordrhein-Westfalen",
    "wof:name":"Peters Gmbh",
    "wof:placetype":"venue"
},
  "geometry": {"coordinates":[8.507637,51.355015],"type":"Point"}
}