{
  "type": "Feature",
  "properties": {
    "iso:country":"DE",
    "sg:address":"Im Heidlande 22",
    "sg:city":"Celle",
    "sg:phone":"+49 5141/82595",
    "sg:postcode":"29227",
    "sg:province":"Niedersachsen",
    "wof:name":"Gerd M\u00fcller Ofensetzerei",
    "wof:placetype":"venue"
},
  "geometry": {"coordinates":[10.0609645844,52.6008758545],"type":"Point"}
}