{
  "type": "Feature",
  "properties": {
    "iso:country":"DE",
    "sg:address":"Volmerswerther Deich 151",
    "sg:city":"D\u00fcsseldorf",
    "sg:phone":"+49 211/902010",
    "sg:postcode":"40221",
    "sg:province":"Nordrhein-Westfalen",
    "wof:name":"Hotel F\u00e4hrhaus",
    "wof:placetype":"venue"
},
  "geometry": {"coordinates":[6.757021904,51.1841430664],"type":"Point"}
}