{
  "type": "Feature",
  "properties": {
    "iso:country":"DE",
    "sg:address":"Lindenstr. 10",
    "sg:city":"W\u00f6llstadt",
    "sg:phone":"+49 4960/342478",
    "sg:postcode":"61206",
    "sg:province":"Hessen",
    "wof:name":"Weissenborn Gmbh",
    "wof:placetype":"venue"
},
  "geometry": {"coordinates":[8.766683,50.278873],"type":"Point"}
}