{
  "type": "Feature",
  "properties": {
    "iso:country":"DE",
    "sg:address":"Oberhafenstr. 1",
    "sg:city":"Hamburg",
    "sg:postcode":"20097",
    "sg:province":"Hamburg",
    "wof:name":"Interfrucht Beteiligungs- Gesellschaft Mbh",
    "wof:placetype":"venue"
},
  "geometry": {"coordinates":[10.007907,53.54591],"type":"Point"}
}