{
  "type": "Feature",
  "properties": {
    "iso:country":"DE",
    "sg:address":"Garatshausener Str. 15",
    "sg:city":"Muenchen",
    "sg:phone":"+49 89/7488560",
    "sg:postcode":"81479",
    "sg:province":"Bayern",
    "wof:name":"Tyrolis Musik Gmbh",
    "wof:placetype":"venue"
},
  "geometry": {"coordinates":[11.5211811066,48.0884819031],"type":"Point"}
}