{
  "type": "Feature",
  "properties": {
    "iso:country":"DE",
    "sg:address":"Otto-Suhr-Allee 123",
    "sg:city":"Berlin",
    "sg:phone":"+49 30/3482040",
    "sg:postcode":"10585",
    "sg:province":"Berlin",
    "wof:name":"Peter Ebner",
    "wof:placetype":"venue"
},
  "geometry": {"coordinates":[13.3039388657,52.5180130005],"type":"Point"}
}