{
  "type": "Feature",
  "properties": {
    "iso:country":"DE",
    "sg:address":"Rudolf-Diesel-Str. 39",
    "sg:city":"Heinsberg",
    "sg:postcode":"52525",
    "sg:province":"Nordrhein-Westfalen",
    "wof:name":"Ks Kanal- Und Stra\u00dfenbau Tiefbau Gmbh",
    "wof:placetype":"venue"
},
  "geometry": {"coordinates":[6.1061778069,51.0675392151],"type":"Point"}
}