{
  "type": "Feature",
  "properties": {
    "iso:country":"DE",
    "sg:address":"Hohe Str. 46",
    "sg:city":"D\u00fcsseldorf",
    "sg:phone":"+49 211/3237770",
    "sg:postcode":"40213",
    "sg:province":"Nordrhein-Westfalen",
    "wof:name":"Gerd Maubach Gmbh",
    "wof:placetype":"venue"
},
  "geometry": {"coordinates":[6.7743310928,51.2204666138],"type":"Point"}
}