{
  "type": "Feature",
  "properties": {
    "iso:country":"DE",
    "sg:address":"Hoorwaldstr. 73",
    "sg:city":"Burbach",
    "sg:phone":"+49 2736/3751",
    "sg:postcode":"57299",
    "sg:province":"Nordrhein-Westfalen",
    "wof:name":"Heinz Gmbh",
    "wof:placetype":"venue"
},
  "geometry": {"coordinates":[8.1322011948,50.7311477661],"type":"Point"}
}