{
  "type": "Feature",
  "properties": {
    "iso:country":"DE",
    "sg:address":"Hauptstr. 63",
    "sg:city":"Leubnitz",
    "sg:phone":"+49 3761/3540",
    "sg:postcode":"08412",
    "sg:province":"Sachsen",
    "wof:name":"Eberhard Adler",
    "wof:placetype":"venue"
},
  "geometry": {"coordinates":[12.37106,50.731152],"type":"Point"}
}