{
  "type": "Feature",
  "properties": {
    "iso:country":"DE",
    "sg:address":"Mittelstr. 22",
    "sg:city":"Osterwieck",
    "sg:phone":"+49 39421/73918",
    "sg:postcode":"38835",
    "sg:province":"Sachsen-Anhalt",
    "wof:name":"T. Lange",
    "wof:placetype":"venue"
},
  "geometry": {"coordinates":[10.71042,51.970207],"type":"Point"}
}