{
  "type": "Feature",
  "properties": {
    "iso:country":"DE",
    "sg:address":"Murgstr. 11",
    "sg:city":"Straubenhardt",
    "sg:phone":"+49 7082/924975",
    "sg:postcode":"75334",
    "sg:province":"Baden-W\u00fcrttemberg",
    "wof:name":"Easy Gmbh",
    "wof:placetype":"venue"
},
  "geometry": {"coordinates":[8.5459423065,48.8446273804],"type":"Point"}
}