{
  "type": "Feature",
  "properties": {
    "iso:country":"DE",
    "sg:address":"Vorwerkstr. 4",
    "sg:city":"Heynitz",
    "sg:phone":"+49 3521/72050",
    "sg:postcode":"01683",
    "sg:province":"Sachsen",
    "wof:name":"Geho-fenstertechnik Gmbh & Co. Kg",
    "wof:placetype":"venue"
},
  "geometry": {"coordinates":[13.32129,51.067707],"type":"Point"}
}