{
  "type": "Feature",
  "properties": {
    "iso:country":"DE",
    "sg:address":"Hoheluftchaussee 95",
    "sg:city":"Hamburg",
    "sg:phone":"+49 40/4502100",
    "sg:postcode":"20253",
    "sg:province":"Hamburg",
    "wof:name":"Achtung Internet Gmbh",
    "wof:placetype":"venue"
},
  "geometry": {"coordinates":[9.971553,53.582142],"type":"Point"}
}