{
  "type": "Feature",
  "properties": {
    "iso:country":"DE",
    "sg:address":"Riedhirsch 138",
    "sg:city":"Heimenkirch",
    "sg:phone":"+49 8381/6116",
    "sg:postcode":"88178",
    "sg:province":"Bayern",
    "wof:name":"Michael Prinz Holzbau",
    "wof:placetype":"venue"
},
  "geometry": {"coordinates":[9.9366102219,47.6213493347],"type":"Point"}
}