{
  "type": "Feature",
  "properties": {
    "iso:country":"DE",
    "sg:address":"Pullacher Str. 4",
    "sg:city":"Bad Aibling",
    "sg:postcode":"83043",
    "sg:province":"Bayern",
    "wof:name":"Urovision Medical Einmalprodukte F. D. Urologie",
    "wof:placetype":"venue"
},
  "geometry": {"coordinates":[11.989307,47.854195],"type":"Point"}
}