{
  "type": "Feature",
  "properties": {
    "iso:country":"DE",
    "sg:address":"Lindenstr. 4",
    "sg:city":"H\u00fcrth",
    "sg:phone":"+49 2233/942270",
    "sg:postcode":"50354",
    "sg:province":"Nordrhein-Westfalen",
    "wof:name":"Au\u00dfem Heigl Und Rettinger Rechtsanw\u00e4lte",
    "wof:placetype":"venue"
},
  "geometry": {"coordinates":[6.8679637909,50.8709487915],"type":"Point"}
}