{
  "type": "Feature",
  "properties": {
    "iso:country":"DE",
    "sg:address":"Rechbergstr. 52",
    "sg:city":"Aichtal",
    "sg:phone":"+49 7127/50578",
    "sg:postcode":"72631",
    "sg:province":"Baden-W\u00fcrttemberg",
    "wof:name":"Kubern Gmbh",
    "wof:placetype":"venue"
},
  "geometry": {"coordinates":[9.2550477982,48.6292610168],"type":"Point"}
}