{
  "type": "Feature",
  "properties": {
    "iso:country":"DE",
    "sg:address":"Stresemannstr. 18/19",
    "sg:city":"Magdeburg",
    "sg:phone":"+49 391/59630",
    "sg:postcode":"39104",
    "sg:province":"Sachsen-Anhalt",
    "wof:name":"Lotto-toto Gmbh",
    "wof:placetype":"venue"
},
  "geometry": {"coordinates":[11.629908,52.133949],"type":"Point"}
}