{
  "type": "Feature",
  "properties": {
    "iso:country":"DE",
    "sg:address":"Hauptstr. 34",
    "sg:city":"Bad Salzdetfurth",
    "sg:phone":"+49 5064/8130",
    "sg:postcode":"31162",
    "sg:province":"Niedersachsen",
    "wof:name":"Landgasthof Gieseke Gmbh",
    "wof:placetype":"venue"
},
  "geometry": {"coordinates":[10.0378713608,52.102230072],"type":"Point"}
}