{
  "type": "Feature",
  "properties": {
    "iso:country":"DE",
    "sg:address":"Aldenhovener Str. 38",
    "sg:city":"D\u00fcren",
    "sg:phone":"+49 2421/87017",
    "sg:postcode":"52353",
    "sg:province":"Nordrhein-Westfalen",
    "wof:name":"Embe Maschinentechnik Service Und Vertrieb Gmbh",
    "wof:placetype":"venue"
},
  "geometry": {"coordinates":[6.444013,50.816849],"type":"Point"}
}