{
  "type": "Feature",
  "properties": {
    "iso:country":"DE",
    "sg:address":"Kasseler Str. 1",
    "sg:city":"Homberg",
    "sg:phone":"+49 5681/608869",
    "sg:postcode":"34576",
    "sg:province":"Hessen",
    "wof:name":"Ergotherapiepraxis Klutschkow",
    "wof:placetype":"venue"
},
  "geometry": {"coordinates":[9.401073,51.033318],"type":"Point"}
}