{
  "type": "Feature",
  "properties": {
    "iso:country":"DE",
    "sg:address":"Rahlstedter Bahnhofstr. 41",
    "sg:city":"Hamburg",
    "sg:phone":"+49 40/6775702",
    "sg:postcode":"22143",
    "sg:province":"Hamburg",
    "wof:name":"Casa Del \u00c4tna",
    "wof:placetype":"venue"
},
  "geometry": {"coordinates":[10.1545610428,53.6024665833],"type":"Point"}
}