{
  "type": "Feature",
  "properties": {
    "iso:country":"DE",
    "sg:address":"Flugplatzstr. 8",
    "sg:city":"B\u00fcchenbach",
    "sg:phone":"+49 9178/98300",
    "sg:postcode":"91186",
    "sg:province":"Bayern",
    "wof:name":"Georg B\u00e4r Alu-stahlbau Gmbh",
    "wof:placetype":"venue"
},
  "geometry": {"coordinates":[11.006166,49.266598],"type":"Point"}
}