{
  "type": "Feature",
  "properties": {
    "iso:country":"DE",
    "sg:address":"Wiesenstr. 16",
    "sg:city":"Bayreuth",
    "sg:phone":"+49 921/20040",
    "sg:postcode":"95444",
    "sg:province":"Bayern",
    "wof:name":"Karl Wehner",
    "wof:placetype":"venue"
},
  "geometry": {"coordinates":[11.573119,49.948952],"type":"Point"}
}