{
  "type": "Feature",
  "properties": {
    "iso:country":"DE",
    "sg:address":"Hauptstr. 1",
    "sg:city":"Sontheim",
    "sg:phone":"+49 7171/6021",
    "sg:postcode":"89567",
    "sg:province":"Baden-W\u00fcrttemberg",
    "wof:name":"Sparkassen-versicherung",
    "wof:placetype":"venue"
},
  "geometry": {"coordinates":[10.3554954529,48.0060272217],"type":"Point"}
}