{
  "type": "Feature",
  "properties": {
    "iso:country":"DE",
    "sg:address":"Humboldtstr. 65",
    "sg:city":"Bremen",
    "sg:phone":"+49 421/72210",
    "sg:postcode":"28203",
    "sg:province":"Bremen",
    "wof:name":"L\u00fcna Design Kopf- Schmuck- Accessoires",
    "wof:placetype":"venue"
},
  "geometry": {"coordinates":[8.826874733,53.0747642517],"type":"Point"}
}