{
  "type": "Feature",
  "properties": {
    "iso:country":"DE",
    "sg:address":"Oktaviostr 15",
    "sg:city":"Hamburg",
    "sg:phone":"+49 40/6563893",
    "sg:postcode":"22043",
    "sg:province":"Hamburg",
    "wof:name":"Asw Antriebssysteme Witt Gmbh",
    "wof:placetype":"venue"
},
  "geometry": {"coordinates":[10.087577,53.566216],"type":"Point"}
}