{
  "type": "Feature",
  "properties": {
    "iso:country":"DE",
    "sg:address":"Mittlerer Weg 1",
    "sg:city":"Crailsheim",
    "sg:phone":"+49 7951/43546",
    "sg:postcode":"74564",
    "sg:province":"Baden-W\u00fcrttemberg",
    "wof:name":"J\u00fcrgen Melber Masseur",
    "wof:placetype":"venue"
},
  "geometry": {"coordinates":[10.075145,49.137577],"type":"Point"}
}