{
  "type": "Feature",
  "properties": {
    "iso:country":"DE",
    "sg:address":"Abraham-Lincoln-Str. 16",
    "sg:city":"Wiesbaden",
    "sg:phone":"+49 611/778720",
    "sg:postcode":"65189",
    "sg:province":"Hessen",
    "wof:name":"Dr. Ekkehard Helmig Rechtsanwalt Und Notar",
    "wof:placetype":"venue"
},
  "geometry": {"coordinates":[8.2619781494,50.0704498291],"type":"Point"}
}