{
  "type": "Feature",
  "properties": {
    "iso:country":"DE",
    "sg:address":"Landseestr. 15",
    "sg:city":"Rottenburg",
    "sg:phone":"+49 7472/3132",
    "sg:postcode":"72108",
    "sg:province":"Baden-W\u00fcrttemberg",
    "wof:name":"Max Bucher",
    "wof:placetype":"venue"
},
  "geometry": {"coordinates":[8.9454460144,48.4745521545],"type":"Point"}
}