{
  "type": "Feature",
  "properties": {
    "iso:country":"DE",
    "sg:address":"An der Heide 69",
    "sg:city":"Eilenburg",
    "sg:phone":"+49 3423/754001",
    "sg:postcode":"04838",
    "sg:province":"Sachsen",
    "wof:name":"Manfred Herz",
    "wof:placetype":"venue"
},
  "geometry": {"coordinates":[12.668264389,51.4744796753],"type":"Point"}
}