{
  "type": "Feature",
  "properties": {
    "iso:country":"DE",
    "sg:address":"K\u00f6nigstuhlstr. 19",
    "sg:city":"L\u00f6rzweiler",
    "sg:phone":"+49 6138/7027",
    "sg:postcode":"55296",
    "sg:province":"Rheinland-Pfalz",
    "wof:name":"Erich Detzler Architekt",
    "wof:placetype":"venue"
},
  "geometry": {"coordinates":[8.298979,49.898434],"type":"Point"}
}