{
  "type": "Feature",
  "properties": {
    "iso:country":"DE",
    "sg:address":"Kollerbergring 29",
    "sg:city":"Spremberg",
    "sg:phone":"+49 3563/90604",
    "sg:postcode":"03130",
    "sg:province":"Brandenburg",
    "wof:name":"Reinhard Rex",
    "wof:placetype":"venue"
},
  "geometry": {"coordinates":[14.365803,51.564079],"type":"Point"}
}