{
  "type": "Feature",
  "properties": {
    "iso:country":"DE",
    "sg:address":"Wilhelmstr. 42",
    "sg:city":"Dortmund",
    "sg:phone":"+49 231/143970",
    "sg:postcode":"44137",
    "sg:province":"Nordrhein-Westfalen",
    "wof:name":"Kaiser",
    "wof:placetype":"venue"
},
  "geometry": {"coordinates":[7.4539299011,51.5111503601],"type":"Point"}
}