{
  "type": "Feature",
  "properties": {
    "iso:country":"DE",
    "sg:address":"G\u00f6rresstr. 26",
    "sg:city":"Iserlohn",
    "sg:phone":"+49 2371/25723",
    "sg:postcode":"58636",
    "sg:province":"Nordrhein-Westfalen",
    "wof:name":"G\u00fcnther N\u00fclle",
    "wof:placetype":"venue"
},
  "geometry": {"coordinates":[7.7102899551,51.3824234009],"type":"Point"}
}