{
  "type": "Feature",
  "properties": {
    "iso:country":"DE",
    "sg:address":"Hauptstr. 12",
    "sg:city":"Rothenburg",
    "sg:phone":"+49 35891/7223",
    "sg:postcode":"02929",
    "sg:province":"Sachsen",
    "wof:name":"Waldemar Lehmann",
    "wof:placetype":"venue"
},
  "geometry": {"coordinates":[14.961312294,51.379524231],"type":"Point"}
}