{
  "type": "Feature",
  "properties": {
    "iso:country":"DE",
    "sg:address":"F\u00fcrstin-Katharina-Str. 4",
    "sg:city":"Beuron",
    "sg:phone":"+49 7466/218",
    "sg:postcode":"88631",
    "sg:province":"Baden-W\u00fcrttemberg",
    "wof:name":"Franz Kiene",
    "wof:placetype":"venue"
},
  "geometry": {"coordinates":[8.9729032516,48.0493545532],"type":"Point"}
}