{
  "type": "Feature",
  "properties": {
    "iso:country":"DE",
    "sg:address":"Bismarckstrasse 38",
    "sg:city":"Siegen",
    "sg:phone":"+49 271",
    "sg:postcode":"57076",
    "sg:province":"Nordrhein-Westfalen",
    "wof:name":"German Airports",
    "wof:placetype":"venue"
},
  "geometry": {"coordinates":[8.0244617462,50.895236969],"type":"Point"}
}