{
  "type": "Feature",
  "properties": {
    "iso:country":"DE",
    "sg:address":"Saportastr. 4",
    "sg:city":"M\u00fcnchen",
    "sg:phone":"+49 89/152327",
    "sg:postcode":"80637",
    "sg:province":"Bayern",
    "wof:name":"Anton Griesbeck",
    "wof:placetype":"venue"
},
  "geometry": {"coordinates":[11.5435037613,48.1614265442],"type":"Point"}
}