{
  "type": "Feature",
  "properties": {
    "iso:country":"DE",
    "sg:address":"Hainer Weg 16",
    "sg:city":"Frankenberg",
    "sg:phone":"+49 6451/1794",
    "sg:postcode":"35066",
    "sg:province":"Hessen",
    "wof:name":"Heinz Tripp Gmbh",
    "wof:placetype":"venue"
},
  "geometry": {"coordinates":[8.7455253601,51.0462303162],"type":"Point"}
}