{
  "type": "Feature",
  "properties": {
    "iso:country":"DE",
    "sg:address":"Peter-Adolphs-Str. 25",
    "sg:city":"D\u00fcsseldorf",
    "sg:phone":"+49 211/7000482",
    "sg:postcode":"40593",
    "sg:province":"Nordrhein-Westfalen",
    "wof:name":"Gerd Sch\u00f6llgen",
    "wof:placetype":"venue"
},
  "geometry": {"coordinates":[6.8811712265,51.1491737366],"type":"Point"}
}