{
  "type": "Feature",
  "properties": {
    "iso:country":"DE",
    "sg:address":"Alter Markt 11",
    "sg:city":"Balingen",
    "sg:phone":"+49 7433/7915",
    "sg:postcode":"72336",
    "sg:province":"Baden-W\u00fcrttemberg",
    "wof:name":"W\u00fcrttembergische Versicherung",
    "wof:placetype":"venue"
},
  "geometry": {"coordinates":[8.8524417877,48.2752418518],"type":"Point"}
}