{
  "type": "Feature",
  "properties": {
    "iso:country":"DE",
    "sg:address":"Theaterstr. 2",
    "sg:city":"W\u00fcrzburg",
    "sg:phone":"+49 931/18380",
    "sg:postcode":"97070",
    "sg:province":"Bayern",
    "wof:name":"C. \u00d6lk\u00fc",
    "wof:placetype":"venue"
},
  "geometry": {"coordinates":[9.9334802628,49.7972259521],"type":"Point"}
}