{
  "type": "Feature",
  "properties": {
    "iso:country":"DE",
    "sg:address":"Grevener Str. 440",
    "sg:city":"M\u00fcnster",
    "sg:phone":"+49 251/213032",
    "sg:postcode":"48159",
    "sg:province":"Nordrhein-Westfalen",
    "wof:name":"Dr. Med. Klaus Borchard Arzt F\u00fcr Allgemeinmedizin",
    "wof:placetype":"venue"
},
  "geometry": {"coordinates":[7.6134719849,51.9967536926],"type":"Point"}
}