{
  "type": "Feature",
  "properties": {
    "iso:country":"DE",
    "sg:address":"Rosenstr. 42",
    "sg:city":"Filderstadt",
    "sg:phone":"+49 711/702210",
    "sg:postcode":"70794",
    "sg:province":"Baden-W\u00fcrttemberg",
    "wof:name":"Lacerda Lichtpauserei Gmbh",
    "wof:placetype":"venue"
},
  "geometry": {"coordinates":[9.2120771408,48.6779518127],"type":"Point"}
}