{
  "type": "Feature",
  "properties": {
    "iso:country":"DE",
    "sg:address":"Hofmarkstr. 26",
    "sg:city":"Nittendorf",
    "sg:phone":"+49 9404/1893",
    "sg:postcode":"93152",
    "sg:province":"Bayern",
    "wof:name":"Werner Helgath",
    "wof:placetype":"venue"
},
  "geometry": {"coordinates":[11.936061,49.026932],"type":"Point"}
}