{
  "type": "Feature",
  "properties": {
    "iso:country":"DE",
    "sg:address":"Im Wien\u00e4ckern 8",
    "sg:city":"Haltern",
    "sg:phone":"+49 2364/7824",
    "sg:postcode":"45721",
    "sg:province":"Nordrhein-Westfalen",
    "wof:name":"Werner Winkels",
    "wof:placetype":"venue"
},
  "geometry": {"coordinates":[7.1936841011,51.7490921021],"type":"Point"}
}