{
  "type": "Feature",
  "properties": {
    "iso:country":"DE",
    "sg:address":"Bunsenstr. 19",
    "sg:city":"Darmstadt",
    "sg:postcode":"64293",
    "sg:province":"Hessen",
    "wof:name":"Real Projekt Gmbh",
    "wof:placetype":"venue"
},
  "geometry": {"coordinates":[8.6235027313,49.8887023926],"type":"Point"}
}