{
  "type": "Feature",
  "properties": {
    "iso:country":"DE",
    "sg:address":"Dorfstr. 1",
    "sg:city":"K\u00f6ttwitzsch",
    "sg:phone":"+49 3737/42755",
    "sg:postcode":"09306",
    "sg:province":"Sachsen",
    "wof:name":"P. Hentschel",
    "wof:placetype":"venue"
},
  "geometry": {"coordinates":[12.7558002472,51.0532684326],"type":"Point"}
}