{
  "type": "Feature",
  "properties": {
    "iso:country":"DE",
    "sg:address":"Im Kreuzteich 23",
    "sg:city":"Marienfeld",
    "sg:phone":"+49 5247/8322",
    "sg:postcode":"33428",
    "sg:province":"Nordrhein-Westfalen",
    "wof:name":"Adolf Bruns",
    "wof:placetype":"venue"
},
  "geometry": {"coordinates":[8.2800683975,51.9494056702],"type":"Point"}
}