{
  "type": "Feature",
  "properties": {
    "iso:country":"DE",
    "sg:address":"Gopprechts 14",
    "sg:city":"Waltenhofen",
    "sg:phone":"+49 8379/7027",
    "sg:postcode":"87448",
    "sg:province":"Bayern",
    "wof:name":"Trunzer St\u00fcble",
    "wof:placetype":"venue"
},
  "geometry": {"coordinates":[10.2253856659,47.6206474304],"type":"Point"}
}