{
  "type": "Feature",
  "properties": {
    "iso:country":"DE",
    "sg:address":"Hauptstr. 67",
    "sg:city":"Hannover",
    "sg:phone":"+49 511/461663",
    "sg:postcode":"30457",
    "sg:province":"Niedersachsen",
    "wof:name":"Flieger\u00e4rztliche Untersuchungsstelle Hannover",
    "wof:placetype":"venue"
},
  "geometry": {"coordinates":[9.691534,52.331749],"type":"Point"}
}