{
  "type": "Feature",
  "properties": {
    "iso:country":"DE",
    "sg:address":"Hauptstr. 118",
    "sg:city":"Apen",
    "sg:phone":"+49 4489/6626",
    "sg:postcode":"26689",
    "sg:province":"Niedersachsen",
    "wof:name":"Angela Seifert Ergotherapeutsche Praxis",
    "wof:placetype":"venue"
},
  "geometry": {"coordinates":[7.811927,53.22303],"type":"Point"}
}