{
  "type": "Feature",
  "properties": {
    "iso:country":"DE",
    "sg:address":"Gartenstr. 8a",
    "sg:city":"Wiederstedt",
    "sg:phone":"+49 3476/551739",
    "sg:postcode":"06333",
    "sg:province":"Sachsen-Anhalt",
    "wof:name":"Holzbau Andreas Bich",
    "wof:placetype":"venue"
},
  "geometry": {"coordinates":[11.5163803101,51.6645851135],"type":"Point"}
}