{
  "type": "Feature",
  "properties": {
    "iso:country":"DE",
    "sg:address":"Von-M\u00fcller-Str. 30a",
    "sg:city":"Furth im Wald",
    "sg:phone":"+49 9973/9971",
    "sg:postcode":"93437",
    "sg:province":"Bayern",
    "wof:name":"Cadi",
    "wof:placetype":"venue"
},
  "geometry": {"coordinates":[12.8392772675,49.3066978455],"type":"Point"}
}