{
  "type": "Feature",
  "properties": {
    "iso:country":"DE",
    "sg:address":"Massenbuch 7",
    "sg:city":"Gem\u00fcnden",
    "sg:phone":"+49 9351/3650",
    "sg:postcode":"97737",
    "sg:province":"Bayern",
    "wof:name":"Willi Kern",
    "wof:placetype":"venue"
},
  "geometry": {"coordinates":[9.70104,50.035534],"type":"Point"}
}