{
  "type": "Feature",
  "properties": {
    "iso:country":"DE",
    "sg:address":"Stra\u00dfe der Pioniere 3 a",
    "sg:city":"Mittelherwigsdorf",
    "sg:phone":"+49 3583/707011",
    "sg:postcode":"02763",
    "sg:province":"Sachsen",
    "wof:name":"Gerlach Gr\u00fcnbau Gmbh",
    "wof:placetype":"venue"
},
  "geometry": {"coordinates":[14.7692346573,50.9230041504],"type":"Point"}
}