{
  "type": "Feature",
  "properties": {
    "iso:country":"DE",
    "sg:address":"Im Atzelnest 3",
    "sg:city":"Bad Homburg",
    "sg:phone":"+49 6172/94880",
    "sg:postcode":"61352",
    "sg:province":"Hessen",
    "wof:name":"Syzygy Ag",
    "wof:placetype":"venue"
},
  "geometry": {"coordinates":[8.649537,50.212654],"type":"Point"}
}