{
  "type": "Feature",
  "properties": {
    "iso:country":"DE",
    "sg:address":"Schl\u00fcterstr. 58",
    "sg:city":"Ingolstadt",
    "sg:phone":"+49 841/4558",
    "sg:postcode":"85057",
    "sg:province":"Bayern",
    "wof:name":"Deutsche Versicherungsmakler Gmbh",
    "wof:placetype":"venue"
},
  "geometry": {"coordinates":[11.4035663605,48.7702713013],"type":"Point"}
}