{
  "type": "Feature",
  "properties": {
    "iso:country":"DE",
    "sg:address":"Hochberg 3",
    "sg:city":"Landau a. d. Isar",
    "sg:phone":"+49 9951/8679",
    "sg:postcode":"94405",
    "sg:province":"Bayern",
    "wof:name":"Biohof Laurer - Erdbeeren Und Gem\u00fcse Biologisch",
    "wof:placetype":"venue"
},
  "geometry": {"coordinates":[12.7453050613,48.6746139526],"type":"Point"}
}