{
  "type": "Feature",
  "properties": {
    "iso:country":"DE",
    "sg:address":"Innungsstr. 61",
    "sg:city":"Berlin",
    "sg:phone":"+49 30/4113060",
    "sg:postcode":"13509",
    "sg:province":"Berlin",
    "wof:name":"Heinrich Henze",
    "wof:placetype":"venue"
},
  "geometry": {"coordinates":[13.312008,52.581089],"type":"Point"}
}