{
  "type": "Feature",
  "properties": {
    "iso:country":"DE",
    "sg:address":"Lannerstr. 14",
    "sg:city":"Ober-Olm",
    "sg:phone":"+49 6136/997846",
    "sg:postcode":"55270",
    "sg:province":"Rheinland-Pfalz",
    "wof:name":"Hugo Und Norbert Wassermann",
    "wof:placetype":"venue"
},
  "geometry": {"coordinates":[8.194132,49.936268],"type":"Point"}
}