{
  "type": "Feature",
  "properties": {
    "iso:country":"DE",
    "sg:address":"Helmstr. 3-5",
    "sg:city":"Erlangen",
    "sg:postcode":"91054",
    "sg:province":"Bayern",
    "wof:name":"Endres F. Party Service",
    "wof:placetype":"venue"
},
  "geometry": {"coordinates":[11.003098,49.597157],"type":"Point"}
}