{
  "type": "Feature",
  "properties": {
    "iso:country":"DE",
    "sg:address":"Marktplatz 13",
    "sg:city":"Bretten",
    "sg:phone":"+49 7252/1278",
    "sg:postcode":"75015",
    "sg:province":"Baden-W\u00fcrttemberg",
    "wof:name":"E. Dittes",
    "wof:placetype":"venue"
},
  "geometry": {"coordinates":[8.707935,49.03701],"type":"Point"}
}