{
  "type": "Feature",
  "properties": {
    "iso:country":"DE",
    "sg:address":"Untere Vorstadt 14",
    "sg:city":"Wolframs-Eschenbach",
    "sg:phone":"+49 9875/625",
    "sg:postcode":"91639",
    "sg:province":"Bayern",
    "wof:name":"Josef Schweigert",
    "wof:placetype":"venue"
},
  "geometry": {"coordinates":[10.726783,49.225224],"type":"Point"}
}