{
  "type": "Feature",
  "properties": {
    "iso:country":"DE",
    "sg:address":"Nr. 121",
    "sg:city":"Knau",
    "sg:phone":"+49 36484/22318",
    "sg:postcode":"07389",
    "sg:province":"Th\u00fcringen",
    "wof:name":"Konsumgenossenschaft Ostth\u00fcringen Eg",
    "wof:placetype":"venue"
},
  "geometry": {"coordinates":[11.6290502548,50.6598091125],"type":"Point"}
}