{
  "type": "Feature",
  "properties": {
    "iso:country":"DE",
    "sg:address":"Lindenstr. 48",
    "sg:city":"Karben",
    "sg:phone":"+49 6039/92220",
    "sg:postcode":"61184",
    "sg:province":"Hessen",
    "wof:name":"Heinrich Heitz & Partner Architekten",
    "wof:placetype":"venue"
},
  "geometry": {"coordinates":[8.775271,50.241875],"type":"Point"}
}