{
  "type": "Feature",
  "properties": {
    "iso:country":"DE",
    "sg:address":"Steintorweg 8",
    "sg:city":"Hamburg",
    "sg:phone":"+49 40/242438",
    "sg:postcode":"20099",
    "sg:province":"Hamburg",
    "wof:name":"City 14",
    "wof:placetype":"venue"
},
  "geometry": {"coordinates":[10.009927,53.553413],"type":"Point"}
}