{
  "type": "Feature",
  "properties": {
    "iso:country":"DE",
    "sg:address":"Lenaustr. 12",
    "sg:city":"Heidelberg",
    "sg:phone":"+49 6221/602585",
    "sg:postcode":"69115",
    "sg:province":"Baden-W\u00fcrttemberg",
    "wof:name":"Villa Bautr\u00e4ger Gmbh",
    "wof:placetype":"venue"
},
  "geometry": {"coordinates":[8.683898,49.399532],"type":"Point"}
}