{
  "type": "Feature",
  "properties": {
    "iso:country":"DE",
    "sg:address":"Schillerstr. 17-19",
    "sg:city":"Weimar",
    "sg:phone":"+49 3643/61913",
    "sg:postcode":"99423",
    "sg:province":"Th\u00fcringen",
    "wof:name":"Horten Gmbh",
    "wof:placetype":"venue"
},
  "geometry": {"coordinates":[11.326599,50.979439],"type":"Point"}
}