{
  "type": "Feature",
  "properties": {
    "iso:country":"DE",
    "sg:address":"Konrad-Adenauer-Platz 1",
    "sg:city":"Montabaur",
    "sg:phone":"+49 2602/17548",
    "sg:postcode":"56410",
    "sg:province":"Rheinland-Pfalz",
    "wof:name":"Burggraf",
    "wof:placetype":"venue"
},
  "geometry": {"coordinates":[7.829632,50.435501],"type":"Point"}
}