{
  "type": "Feature",
  "properties": {
    "iso:country":"DE",
    "sg:address":"Turmstr. 3",
    "sg:city":"Sonsbeck",
    "sg:phone":"+49 2838/2645",
    "sg:postcode":"47665",
    "sg:province":"Nordrhein-Westfalen",
    "wof:name":"Marlene Th\u00f6nnes",
    "wof:placetype":"venue"
},
  "geometry": {"coordinates":[6.3764967918,51.6154327393],"type":"Point"}
}