{
  "type": "Feature",
  "properties": {
    "iso:country":"DE",
    "sg:address":"Bahnhofstr. 9 a",
    "sg:city":"Kenz-K\u00fcstrow",
    "sg:phone":"+49 38231/81288",
    "sg:postcode":"18314",
    "sg:province":"Mecklenburg-Vorpommern",
    "wof:name":"Handelsagentur Zimmer E. Kfm.",
    "wof:placetype":"venue"
},
  "geometry": {"coordinates":[12.7441720963,54.3258094788],"type":"Point"}
}