{
  "type": "Feature",
  "properties": {
    "iso:country":"DE",
    "sg:address":"Hohegenisterstr. 59",
    "sg:city":"Johanngeorgenstadt",
    "sg:phone":"+49 3773/882525",
    "sg:postcode":"08349",
    "sg:province":"Sachsen",
    "wof:name":"Bauschlosserei G\u00fcnter Wenzel",
    "wof:placetype":"venue"
},
  "geometry": {"coordinates":[12.724595,50.431591],"type":"Point"}
}