{
  "type": "Feature",
  "properties": {
    "iso:country":"DE",
    "sg:address":"Clara-Zetkin-Str. 8",
    "sg:city":"Hohburg",
    "sg:phone":"+49 3425/929544",
    "sg:postcode":"04808",
    "sg:province":"Sachsen",
    "wof:name":"F. Jahn",
    "wof:placetype":"venue"
},
  "geometry": {"coordinates":[12.775727,51.394951],"type":"Point"}
}