{
  "type": "Feature",
  "properties": {
    "iso:country":"DE",
    "sg:address":"Rothaldestr. 45",
    "sg:city":"Schenkenzell",
    "sg:phone":"+49 7836/1704",
    "sg:postcode":"77773",
    "sg:province":"Baden-W\u00fcrttemberg",
    "wof:name":"Gerhard Schmider Anlageberater",
    "wof:placetype":"venue"
},
  "geometry": {"coordinates":[8.367310524,48.3136520386],"type":"Point"}
}