{
  "type": "Feature",
  "properties": {
    "iso:country":"DE",
    "sg:address":"An Der Autobahn 26",
    "sg:city":"Oyten",
    "sg:phone":"+49 4207/804075",
    "sg:postcode":"28876",
    "sg:province":"Niedersachsen",
    "wof:name":"Chiptuning, Tacho, Tachoeinstellung",
    "wof:placetype":"venue"
},
  "geometry": {"coordinates":[9.04632,53.054802],"type":"Point"}
}