{
  "type": "Feature",
  "properties": {
    "iso:country":"DE",
    "sg:address":"Dorfstr. 84",
    "sg:city":"Duisburg",
    "sg:phone":"+49 203/787311",
    "sg:postcode":"47259",
    "sg:province":"Nordrhein-Westfalen",
    "wof:name":"Hugo-wilhelm Gerling",
    "wof:placetype":"venue"
},
  "geometry": {"coordinates":[6.7129387856,51.3495635986],"type":"Point"}
}