{
  "type": "Feature",
  "properties": {
    "iso:country":"DE",
    "sg:address":"Vilbeler Landstr. 218",
    "sg:city":"Frankfurt",
    "sg:phone":"+49 6109/22316",
    "sg:postcode":"60388",
    "sg:province":"Hessen",
    "wof:name":"Genterczewsky Augenoptiker",
    "wof:placetype":"venue"
},
  "geometry": {"coordinates":[8.7487068176,50.1547813416],"type":"Point"}
}