{
  "type": "Feature",
  "properties": {
    "iso:country":"DE",
    "sg:address":"Yorckstr.",
    "sg:city":"Ludwigshafen",
    "sg:postcode":"67061",
    "sg:province":"Rheinland-Pfalz",
    "wof:name":"Real",
    "wof:placetype":"venue"
},
  "geometry": {"coordinates":[8.4547252655,49.4780502319],"type":"Point"}
}