{
  "type": "Feature",
  "properties": {
    "iso:country":"DE",
    "sg:address":"Markt 1",
    "sg:city":"Sch\u00f6ningen",
    "sg:phone":"+49 5352",
    "sg:postcode":"38364",
    "sg:province":"Niedersachsen",
    "wof:name":"Stadt Sch\u00f6ningen",
    "wof:placetype":"venue"
},
  "geometry": {"coordinates":[10.9683160782,52.1392707825],"type":"Point"}
}