{
  "type": "Feature",
  "properties": {
    "iso:country":"DE",
    "sg:address":"Darmst\u00e4dter Str. 147",
    "sg:city":"Biblis",
    "sg:phone":"+49 6245/997549",
    "sg:postcode":"68647",
    "sg:province":"Hessen",
    "wof:name":"Der Mobilfunkladen",
    "wof:placetype":"venue"
},
  "geometry": {"coordinates":[8.4647932053,49.6942443848],"type":"Point"}
}