{
  "type": "Feature",
  "properties": {
    "iso:country":"DE",
    "sg:address":"Augsburger Str. 27",
    "sg:city":"Burgau",
    "sg:phone":"+49 8222/1034",
    "sg:postcode":"89331",
    "sg:province":"Bayern",
    "wof:name":"Alldekor Gmbh",
    "wof:placetype":"venue"
},
  "geometry": {"coordinates":[10.4118289948,48.4255409241],"type":"Point"}
}