{
  "type": "Feature",
  "properties": {
    "iso:country":"DE",
    "sg:address":"Masurenweg 20",
    "sg:city":"Bielefeld",
    "sg:phone":"+49 521/206015",
    "sg:postcode":"33605",
    "sg:province":"Nordrhein-Westfalen",
    "wof:name":"Geisend\u00f6rfer Druck Gmbh",
    "wof:placetype":"venue"
},
  "geometry": {"coordinates":[8.589011,51.999062],"type":"Point"}
}