{
  "type": "Feature",
  "properties": {
    "iso:country":"DE",
    "sg:address":"Salle 83",
    "sg:city":"Warmsen",
    "sg:phone":"+49 5767/202",
    "sg:postcode":"31606",
    "sg:province":"Niedersachsen",
    "wof:name":"Wilhelm K\u00f6nemann",
    "wof:placetype":"venue"
},
  "geometry": {"coordinates":[8.83578,52.478485],"type":"Point"}
}