{
  "type": "Feature",
  "properties": {
    "iso:country":"DE",
    "sg:address":"Hinter dem Hagen 2 c",
    "sg:city":"Drackenstedt",
    "sg:postcode":"39365",
    "sg:province":"Sachsen-Anhalt",
    "wof:name":"Norbert Kramer",
    "wof:placetype":"venue"
},
  "geometry": {"coordinates":[11.347041,52.152878],"type":"Point"}
}