{
  "type": "Feature",
  "properties": {
    "iso:country":"DE",
    "sg:address":"Atzenh\u00fcbelstr. 1",
    "sg:city":"Idar-Oberstein",
    "sg:phone":"+49 6781/44492",
    "sg:postcode":"55743",
    "sg:province":"Rheinland-Pfalz",
    "wof:name":"Renate Kuntz",
    "wof:placetype":"venue"
},
  "geometry": {"coordinates":[7.304046,49.72625],"type":"Point"}
}