{
  "type": "Feature",
  "properties": {
    "iso:country":"DE",
    "sg:address":"Im Unteren Kienle 22",
    "sg:city":"Stuttgart",
    "sg:phone":"+49 711/2361480",
    "sg:postcode":"70184",
    "sg:province":"Baden-W\u00fcrttemberg",
    "wof:name":"E. A. Bieger Ingenieur",
    "wof:placetype":"venue"
},
  "geometry": {"coordinates":[9.191072464,48.7663383484],"type":"Point"}
}