{
  "type": "Feature",
  "properties": {
    "iso:country":"DE",
    "sg:address":"Hauptstr. 12-14",
    "sg:city":"Elsenfeld",
    "sg:phone":"+49 6022/1347",
    "sg:postcode":"63820",
    "sg:province":"Bayern",
    "wof:name":"Willy Luxem Kg Eisenwaren",
    "wof:placetype":"venue"
},
  "geometry": {"coordinates":[9.1604661942,49.8467750549],"type":"Point"}
}