{
  "type": "Feature",
  "properties": {
    "iso:country":"DE",
    "sg:address":"Lange Str. 58",
    "sg:city":"Hoya",
    "sg:phone":"+49 4251/1644",
    "sg:postcode":"27318",
    "sg:province":"Niedersachsen",
    "wof:name":"Marianne Wenzel Lederwaren",
    "wof:placetype":"venue"
},
  "geometry": {"coordinates":[9.137647,52.805492],"type":"Point"}
}