{
  "type": "Feature",
  "properties": {
    "iso:country":"DE",
    "sg:address":"Werastr. 31",
    "sg:city":"Villingen-Schwenningen",
    "sg:phone":"+49 7720/61425",
    "sg:postcode":"78056",
    "sg:province":"Baden-W\u00fcrttemberg",
    "wof:name":"Adolf Schwaderer",
    "wof:placetype":"venue"
},
  "geometry": {"coordinates":[8.5389966965,48.0595932007],"type":"Point"}
}