{
  "type": "Feature",
  "properties": {
    "iso:country":"DE",
    "sg:address":"Mozartstr. 8",
    "sg:city":"Altenburg",
    "sg:phone":"+49 3447/314010",
    "sg:postcode":"04600",
    "sg:province":"Th\u00fcringen",
    "wof:name":"Altenburger Pergament- Und Trommelfell Gmbh",
    "wof:placetype":"venue"
},
  "geometry": {"coordinates":[12.450262,50.996902],"type":"Point"}
}