{
  "type": "Feature",
  "properties": {
    "iso:country":"DE",
    "sg:address":"Freizeitanlage an der B 53",
    "sg:city":"Kr\u00f6v",
    "sg:phone":"+49 6541/9653",
    "sg:postcode":"54536",
    "sg:province":"Rheinland-Pfalz",
    "wof:name":"Freibad",
    "wof:placetype":"venue"
},
  "geometry": {"coordinates":[7.0802521706,49.9767494202],"type":"Point"}
}