{
  "type": "Feature",
  "properties": {
    "iso:country":"DE",
    "sg:address":"Markwerbener Str. 24",
    "sg:city":"Wei\u00dfenfels",
    "sg:postcode":"06667",
    "sg:province":"Sachsen-Anhalt",
    "wof:name":"Trobeck Trockenbau Und T\u00fcren Verwaltungsgesellschaft Mbh",
    "wof:placetype":"venue"
},
  "geometry": {"coordinates":[11.960984,51.208122],"type":"Point"}
}