{
  "type": "Feature",
  "properties": {
    "iso:country":"DE",
    "sg:address":"Entengrabenstr. 2",
    "sg:city":"Esslingen",
    "sg:phone":"+49 711/356136",
    "sg:postcode":"73728",
    "sg:province":"Baden-W\u00fcrttemberg",
    "wof:name":"Bruno Herholz",
    "wof:placetype":"venue"
},
  "geometry": {"coordinates":[9.3124437332,48.7392959595],"type":"Point"}
}