{
  "type": "Feature",
  "properties": {
    "iso:country":"DE",
    "sg:address":"Iggelheimer Str. 40",
    "sg:city":"Schifferstadt",
    "sg:postcode":"67105",
    "sg:province":"Rheinland-Pfalz",
    "wof:name":"J. Und H. Bodlien",
    "wof:placetype":"venue"
},
  "geometry": {"coordinates":[8.363709,49.385063],"type":"Point"}
}