{
  "type": "Feature",
  "properties": {
    "iso:country":"DE",
    "sg:address":"Hanfelder Str. 30",
    "sg:city":"Starnberg",
    "sg:phone":"+49 8151/12209",
    "sg:postcode":"82319",
    "sg:province":"Bayern",
    "wof:name":"Hannes Benker",
    "wof:placetype":"venue"
},
  "geometry": {"coordinates":[11.340327,48.003258],"type":"Point"}
}