{
  "type": "Feature",
  "properties": {
    "iso:country":"DE",
    "sg:address":"Frongasse 3",
    "sg:city":"Bonn",
    "sg:postcode":"53121",
    "sg:province":"Nordrhein-Westfalen",
    "wof:name":"Raymond Searson Gmbh",
    "wof:placetype":"venue"
},
  "geometry": {"coordinates":[7.074546814,50.7276573181],"type":"Point"}
}