{
  "type": "Feature",
  "properties": {
    "iso:country":"DE",
    "sg:address":"Nordrather Str. 218",
    "sg:city":"Velbert",
    "sg:phone":"+49 2052/3352",
    "sg:postcode":"42553",
    "sg:province":"Nordrhein-Westfalen",
    "wof:name":"K. Bergmann",
    "wof:placetype":"venue"
},
  "geometry": {"coordinates":[7.1494297981,51.3240013123],"type":"Point"}
}