{
  "type": "Feature",
  "properties": {
    "iso:country":"DE",
    "sg:address":"Gesmolder Str. 61",
    "sg:city":"Osnabr\u00fcck",
    "sg:phone":"+49 541/9519220",
    "sg:postcode":"49084",
    "sg:province":"Niedersachsen",
    "wof:name":"Josef Belkenheid Nachf Gmbh",
    "wof:placetype":"venue"
},
  "geometry": {"coordinates":[8.081024,52.262005],"type":"Point"}
}