{
  "type": "Feature",
  "properties": {
    "iso:country":"DE",
    "sg:address":"Lukasstr. 3",
    "sg:city":"Dormagen",
    "sg:phone":"+49 2133/72196",
    "sg:postcode":"41541",
    "sg:province":"Nordrhein-Westfalen",
    "wof:name":"B. Hadamitzky Gmbh",
    "wof:placetype":"venue"
},
  "geometry": {"coordinates":[6.8126330376,51.1376419067],"type":"Point"}
}