{
  "type": "Feature",
  "properties": {
    "iso:country":"DE",
    "sg:address":"Carlo-Loos-Str. 11",
    "sg:city":"Gunzenhausen",
    "sg:phone":"+49 9831/2397",
    "sg:postcode":"91710",
    "sg:province":"Bayern",
    "wof:name":"Gemeinn\u00fctzige Wohnungsbau- Genossenschaft Eg",
    "wof:placetype":"venue"
},
  "geometry": {"coordinates":[10.7650403976,49.1192131042],"type":"Point"}
}