{
  "type": "Feature",
  "properties": {
    "iso:country":"DE",
    "sg:address":"Dorfstr. 44",
    "sg:city":"B\u00f6seckendorf",
    "sg:phone":"+49 36071/7189",
    "sg:postcode":"37339",
    "sg:province":"Th\u00fcringen",
    "wof:name":"H. Weise",
    "wof:placetype":"venue"
},
  "geometry": {"coordinates":[10.2039031982,51.4775085449],"type":"Point"}
}