{
  "type": "Feature",
  "properties": {
    "iso:country":"DE",
    "sg:address":"Ernst-Guhr-Str. 1",
    "sg:city":"Leipzig",
    "sg:phone":"+49 341/6516875",
    "sg:postcode":"04319",
    "sg:province":"Sachsen",
    "wof:name":"Monika Horschmann",
    "wof:placetype":"venue"
},
  "geometry": {"coordinates":[12.472323,51.336491],"type":"Point"}
}