{
  "type": "Feature",
  "properties": {
    "iso:country":"DE",
    "sg:address":"Lornsenstr. 66",
    "sg:city":"Schenefeld",
    "sg:phone":"+49 40/83929855",
    "sg:postcode":"22869",
    "sg:province":"Schleswig-Holstein",
    "wof:name":"Ristorante Etna",
    "wof:placetype":"venue"
},
  "geometry": {"coordinates":[9.8448972702,53.6035728455],"type":"Point"}
}