{
  "type": "Feature",
  "properties": {
    "iso:country":"DE",
    "sg:address":"Eisenbahnstr. 6",
    "sg:city":"Eberswalde",
    "sg:phone":"+49 3334/238241",
    "sg:postcode":"16225",
    "sg:province":"Brandenburg",
    "wof:name":"S. Sawasch",
    "wof:placetype":"venue"
},
  "geometry": {"coordinates":[13.815632,52.834648],"type":"Point"}
}