{
  "type": "Feature",
  "properties": {
    "iso:country":"DE",
    "sg:address":"Schillerstr. 8",
    "sg:city":"Bad Liebenwerda",
    "sg:phone":"+49 35341/33923",
    "sg:postcode":"04924",
    "sg:province":"Brandenburg",
    "wof:name":"Dr. Gerhard Kreher Tierarzt",
    "wof:placetype":"venue"
},
  "geometry": {"coordinates":[13.4014062881,51.5233230591],"type":"Point"}
}