{
  "type": "Feature",
  "properties": {
    "iso:country":"DE",
    "sg:address":"Erlbachstr. 41",
    "sg:city":"M\u00fcnchen",
    "sg:phone":"+49 89/8641149",
    "sg:postcode":"81249",
    "sg:province":"Bayern",
    "wof:name":"L. Hagl Immobilienmakler",
    "wof:placetype":"venue"
},
  "geometry": {"coordinates":[11.3897438049,48.1765594482],"type":"Point"}
}