{
  "type": "Feature",
  "properties": {
    "iso:country":"DE",
    "sg:address":"Birkenweg 6",
    "sg:city":"Viechtach",
    "sg:phone":"+49 9942/1066",
    "sg:postcode":"94234",
    "sg:province":"Bayern",
    "wof:name":"Eberhard Ritz Architekt",
    "wof:placetype":"venue"
},
  "geometry": {"coordinates":[12.884363,49.075188],"type":"Point"}
}