{
  "type": "Feature",
  "properties": {
    "iso:country":"DE",
    "sg:address":"Prinzregentenstr. 79",
    "sg:city":"M\u00fcnchen",
    "sg:postcode":"81675",
    "sg:province":"Bayern",
    "wof:name":"Avelion Gmbh",
    "wof:placetype":"venue"
},
  "geometry": {"coordinates":[11.603232,48.140194],"type":"Point"}
}