{
  "type": "Feature",
  "properties": {
    "iso:country":"DE",
    "sg:address":"Grabhorststr. 26",
    "sg:city":"Twistringen",
    "sg:phone":"+49 4243/2811",
    "sg:postcode":"27239",
    "sg:province":"Niedersachsen",
    "wof:name":"Fritz Wichmann",
    "wof:placetype":"venue"
},
  "geometry": {"coordinates":[8.61222,52.810478],"type":"Point"}
}