{
  "type": "Feature",
  "properties": {
    "iso:country":"DE",
    "sg:address":"Asamstr. 6",
    "sg:city":"Rohr",
    "sg:phone":"+49 8783/525",
    "sg:postcode":"93352",
    "sg:province":"Bayern",
    "wof:name":"Raiffeisenbank Rohr-laaberberg Eg",
    "wof:placetype":"venue"
},
  "geometry": {"coordinates":[11.965896,48.768867],"type":"Point"}
}