{
  "type": "Feature",
  "properties": {
    "iso:country":"DE",
    "sg:address":"D\u00fcrerweg 2",
    "sg:city":"Vellmar",
    "sg:phone":"+49 561/8200033",
    "sg:postcode":"34246",
    "sg:province":"Hessen",
    "wof:name":"E. Mosig",
    "wof:placetype":"venue"
},
  "geometry": {"coordinates":[9.4716739655,51.3675003052],"type":"Point"}
}