{
  "type": "Feature",
  "properties": {
    "iso:country":"DE",
    "sg:address":"Bahnhofstr. 41",
    "sg:city":"Zw\u00f6nitz",
    "sg:phone":"+49 37754/3602",
    "sg:postcode":"08297",
    "sg:province":"Sachsen",
    "wof:name":"Manuela Schauer",
    "wof:placetype":"venue"
},
  "geometry": {"coordinates":[12.806225,50.631359],"type":"Point"}
}