{
  "type": "Feature",
  "properties": {
    "iso:country":"DE",
    "sg:address":"Westend 10",
    "sg:city":"Spiekeroog",
    "sg:phone":"+49 4976/230",
    "sg:postcode":"26474",
    "sg:province":"Niedersachsen",
    "wof:name":"G\u00e4stehaus W. Klasing",
    "wof:placetype":"venue"
},
  "geometry": {"coordinates":[7.685256958,53.7698631287],"type":"Point"}
}