{
  "type": "Feature",
  "properties": {
    "iso:country":"DE",
    "sg:address":"R\u00fcdiger 12",
    "sg:city":"Berlin",
    "sg:postcode":"12342",
    "sg:province":"Berlin",
    "wof:name":"Der Einstieg Ins Internet",
    "wof:placetype":"venue"
},
  "geometry": {"coordinates":[13.447447,52.596973],"type":"Point"}
}