{
  "type": "Feature",
  "properties": {
    "iso:country":"DE",
    "sg:address":"Marbacher Str. 46",
    "sg:city":"Freiberg",
    "sg:phone":"+49 7141/72540",
    "sg:postcode":"71691",
    "sg:province":"Baden-W\u00fcrttemberg",
    "wof:name":"W. Schmidt Gmbh",
    "wof:placetype":"venue"
},
  "geometry": {"coordinates":[9.19006,48.932331],"type":"Point"}
}