{
  "type": "Feature",
  "properties": {
    "iso:country":"DE",
    "sg:address":"Hambacher Str. 2 A",
    "sg:city":"Karlsruhe",
    "sg:phone":"+49 721/753242",
    "sg:postcode":"76187",
    "sg:province":"Baden-W\u00fcrttemberg",
    "wof:name":"Hans Van Den Kerkhoff Architekt",
    "wof:placetype":"venue"
},
  "geometry": {"coordinates":[8.366817,49.027634],"type":"Point"}
}