{
  "type": "Feature",
  "properties": {
    "iso:country":"DE",
    "sg:address":"Heinrichstr. 16",
    "sg:city":"Schaafheim",
    "sg:phone":"+49 6073/9387",
    "sg:postcode":"64850",
    "sg:province":"Hessen",
    "wof:name":"Wilhelm Heyl",
    "wof:placetype":"venue"
},
  "geometry": {"coordinates":[9.003895,49.922401],"type":"Point"}
}