{
  "type": "Feature",
  "properties": {
    "iso:country":"DE",
    "sg:address":"Gelleper Str 10",
    "sg:city":"Krefeld",
    "sg:phone":"+49 3723/65060",
    "sg:postcode":"47809",
    "sg:province":"Nordrhein-Westfalen",
    "wof:name":"Hammer Industrieanlagen- Und Werkzeugmaschinen Gmbh",
    "wof:placetype":"venue"
},
  "geometry": {"coordinates":[12.633307,50.80899],"type":"Point"}
}