{
  "type": "Feature",
  "properties": {
    "iso:country":"DE",
    "sg:address":"Fischbrunner Weg 21",
    "sg:city":"Vorra",
    "sg:phone":"+49 9152/8029",
    "sg:postcode":"91247",
    "sg:province":"Bayern",
    "wof:name":"Bernhard Stief",
    "wof:placetype":"venue"
},
  "geometry": {"coordinates":[11.496731,49.556828],"type":"Point"}
}