{
  "type": "Feature",
  "properties": {
    "iso:country":"DE",
    "sg:address":"Neusser Str. 25",
    "sg:city":"Dormagen",
    "sg:phone":"+49 2133/90283",
    "sg:postcode":"41542",
    "sg:province":"Nordrhein-Westfalen",
    "wof:name":"Pizzeria La Locanda",
    "wof:placetype":"venue"
},
  "geometry": {"coordinates":[6.7704768181,51.1158676147],"type":"Point"}
}