{
  "type": "Feature",
  "properties": {
    "iso:country":"DE",
    "sg:address":"Rheinuferstr. 7",
    "sg:city":"Krefeld",
    "sg:phone":"+49 2151/42229",
    "sg:postcode":"47829",
    "sg:province":"Nordrhein-Westfalen",
    "wof:name":"Richard Putzmann Kg Farbenfabriken Bayer",
    "wof:placetype":"venue"
},
  "geometry": {"coordinates":[6.6628398895,51.3686828613],"type":"Point"}
}