{
  "type": "Feature",
  "properties": {
    "iso:country":"DE",
    "sg:address":"M\u00fcnchener Str. 10",
    "sg:city":"Pfaffenhofen",
    "sg:phone":"+49 8441/2409",
    "sg:postcode":"85276",
    "sg:province":"Bayern",
    "wof:name":"Hans P. Burkhart",
    "wof:placetype":"venue"
},
  "geometry": {"coordinates":[11.509042,48.528431],"type":"Point"}
}