{
  "type": "Feature",
  "properties": {
    "iso:country":"DE",
    "sg:address":"Birkenstr. 5",
    "sg:city":"Wiefelstede",
    "sg:phone":"+49 441/9620371",
    "sg:postcode":"26215",
    "sg:province":"Niedersachsen",
    "wof:name":"M & W Informationssysteme Gmbh",
    "wof:placetype":"venue"
},
  "geometry": {"coordinates":[8.1792821884,53.1912269592],"type":"Point"}
}