{
  "type": "Feature",
  "properties": {
    "iso:country":"DE",
    "sg:address":"Marchwitzastr. 29",
    "sg:city":"Berlin",
    "sg:phone":"+49 30/5410120",
    "sg:postcode":"12681",
    "sg:province":"Berlin",
    "wof:name":"Extra",
    "wof:placetype":"venue"
},
  "geometry": {"coordinates":[13.5445804596,52.5231018066],"type":"Point"}
}