{
  "type": "Feature",
  "properties": {
    "iso:country":"DE",
    "sg:address":"Buttst\u00e4dter H\u00f6he 1",
    "sg:city":"Ellersleben",
    "sg:phone":"+49 36372/90894",
    "sg:postcode":"99628",
    "sg:province":"Th\u00fcringen",
    "wof:name":"Roth Gmbh & Co. Kg",
    "wof:placetype":"venue"
},
  "geometry": {"coordinates":[11.333486,51.143387],"type":"Point"}
}