{
  "type": "Feature",
  "properties": {
    "iso:country":"DE",
    "sg:address":"H\u00fcnxer Str. 2",
    "sg:city":"H\u00fcnxe",
    "sg:phone":"+49 2858/7568",
    "sg:postcode":"46569",
    "sg:province":"Nordrhein-Westfalen",
    "wof:name":"P. Franz",
    "wof:placetype":"venue"
},
  "geometry": {"coordinates":[6.774228096,51.6444892883],"type":"Point"}
}