{
  "type": "Feature",
  "properties": {
    "iso:country":"DE",
    "sg:address":"Leibnizstr. 5",
    "sg:city":"Sinsheim",
    "sg:phone":"+49 7261/655970",
    "sg:postcode":"74889",
    "sg:province":"Baden-W\u00fcrttemberg",
    "wof:name":"J. Beisiegel",
    "wof:placetype":"venue"
},
  "geometry": {"coordinates":[8.875441,49.257854],"type":"Point"}
}