{
  "type": "Feature",
  "properties": {
    "iso:country":"DE",
    "sg:address":"Solmser Gewerbepark",
    "sg:city":"Solms",
    "sg:phone":"+49 6442/24211",
    "sg:postcode":"35606",
    "sg:province":"Hessen",
    "wof:name":"Kurt Schweitzer Industrielackierungen",
    "wof:placetype":"venue"
},
  "geometry": {"coordinates":[8.412981,50.543251],"type":"Point"}
}