{
  "type": "Feature",
  "properties": {
    "iso:country":"DE",
    "sg:address":"Ahornweg 7",
    "sg:city":"Kirchentellinsfurt",
    "sg:phone":"+49 7121/96940",
    "sg:postcode":"72138",
    "sg:province":"Baden-W\u00fcrttemberg",
    "wof:name":"Wagner Umwelttechnik Gmbh",
    "wof:placetype":"venue"
},
  "geometry": {"coordinates":[9.1593847275,48.5267372131],"type":"Point"}
}