{
  "type": "Feature",
  "properties": {
    "iso:country":"DE",
    "sg:address":"Albrecht-D\u00fcrer-Str. 1",
    "sg:city":"Bautzen",
    "sg:phone":"+49 3591/304352",
    "sg:postcode":"02625",
    "sg:province":"Sachsen",
    "wof:name":"Architektur- Und Ingenieurb\u00fcro Liebstein Hartmann Und Heinze",
    "wof:placetype":"venue"
},
  "geometry": {"coordinates":[14.417883,51.179855],"type":"Point"}
}