{
  "type": "Feature",
  "properties": {
    "iso:country":"DE",
    "sg:address":"St.-Mang-Platz 14",
    "sg:city":"Kempten",
    "sg:phone":"+49 831/16810",
    "sg:postcode":"87435",
    "sg:province":"Bayern",
    "wof:name":"Miele & Cie. Gmbh & Co.",
    "wof:placetype":"venue"
},
  "geometry": {"coordinates":[10.3191995621,47.725730896],"type":"Point"}
}