{
  "type": "Feature",
  "properties": {
    "iso:country":"DE",
    "sg:address":"Erlanger Str. 29",
    "sg:city":"R\u00f6ttenbach",
    "sg:phone":"+49 9195/992668",
    "sg:postcode":"91341",
    "sg:province":"Bayern",
    "wof:name":"Galeria Wohnbau Gmbh",
    "wof:placetype":"venue"
},
  "geometry": {"coordinates":[10.919456,49.66404],"type":"Point"}
}