{
  "type": "Feature",
  "properties": {
    "iso:country":"DE",
    "sg:address":"Kirchstr. 14",
    "sg:city":"Mastershausen",
    "sg:phone":"+49 6545/1287",
    "sg:postcode":"56869",
    "sg:province":"Rheinland-Pfalz",
    "wof:name":"Hermann Reiter",
    "wof:placetype":"venue"
},
  "geometry": {"coordinates":[7.35423,50.066193],"type":"Point"}
}