{
  "type": "Feature",
  "properties": {
    "iso:country":"DE",
    "sg:address":"Wiesenweg 4",
    "sg:city":"Emden",
    "sg:phone":"+49 4921/21194",
    "sg:postcode":"26725",
    "sg:province":"Niedersachsen",
    "wof:name":"Kg Vhhv Beteiligungs- Verwaltungs- Gmbh & Co.",
    "wof:placetype":"venue"
},
  "geometry": {"coordinates":[7.2289152145,53.3707733154],"type":"Point"}
}