{
  "type": "Feature",
  "properties": {
    "iso:country":"DE",
    "sg:address":"Josef-Schultheis-Str. 9",
    "sg:city":"Hammelburg",
    "sg:phone":"+49 9732/6245",
    "sg:postcode":"97762",
    "sg:province":"Bayern",
    "wof:name":"Kachelofen-studio Hammelburg",
    "wof:placetype":"venue"
},
  "geometry": {"coordinates":[9.891043663,50.116394043],"type":"Point"}
}