{
  "type": "Feature",
  "properties": {
    "iso:country":"DE",
    "sg:address":"Damm 23",
    "sg:city":"Pinneberg",
    "sg:phone":"+49 4101/54340",
    "sg:postcode":"25421",
    "sg:province":"Schleswig-Holstein",
    "wof:name":"Grundst\u00fccksgesellschaft H. Weigelt Mbh",
    "wof:placetype":"venue"
},
  "geometry": {"coordinates":[9.8031139374,53.6606483459],"type":"Point"}
}