{
  "type": "Feature",
  "properties": {
    "iso:country":"DE",
    "sg:address":"Schanzenbachstr. 17",
    "sg:city":"M\u00fcnchen",
    "sg:phone":"+49 89/7251581",
    "sg:postcode":"81371",
    "sg:province":"Bayern",
    "wof:name":"Maria Wittmaier",
    "wof:placetype":"venue"
},
  "geometry": {"coordinates":[11.547741,48.113201],"type":"Point"}
}