{
  "type": "Feature",
  "properties": {
    "iso:country":"DE",
    "sg:address":"Marktplatz 3",
    "sg:city":"Erkrath",
    "sg:phone":"+49 211/243030",
    "sg:postcode":"40699",
    "sg:province":"Nordrhein-Westfalen",
    "wof:name":"Peter Barysch",
    "wof:placetype":"venue"
},
  "geometry": {"coordinates":[6.9118151665,51.2231903076],"type":"Point"}
}