{
  "type": "Feature",
  "properties": {
    "iso:country":"DE",
    "sg:address":"Klingenweg 7",
    "sg:city":"W\u00fcrzburg",
    "sg:phone":"+49 931/95522",
    "sg:postcode":"97080",
    "sg:province":"Bayern",
    "wof:name":"Margarete Krieger",
    "wof:placetype":"venue"
},
  "geometry": {"coordinates":[9.919295311,49.8130912781],"type":"Point"}
}