{
  "type": "Feature",
  "properties": {
    "iso:country":"DE",
    "sg:address":"Altenb\u00fccker Damm 19",
    "sg:city":"B\u00fccken",
    "sg:phone":"+49 4251/6280",
    "sg:postcode":"27333",
    "sg:province":"Niedersachsen",
    "wof:name":"F. Kramer",
    "wof:placetype":"venue"
},
  "geometry": {"coordinates":[9.143017,52.779385],"type":"Point"}
}