{
  "type": "Feature",
  "properties": {
    "iso:country":"DE",
    "sg:address":"An der Nette 2",
    "sg:city":"Holle",
    "sg:phone":"+49 5062/8200",
    "sg:postcode":"31188",
    "sg:province":"Niedersachsen",
    "wof:name":"E. Apelt",
    "wof:placetype":"venue"
},
  "geometry": {"coordinates":[10.1240758896,52.0984954834],"type":"Point"}
}