{
  "type": "Feature",
  "properties": {
    "iso:country":"DE",
    "sg:address":"Wiesengrund 5 a",
    "sg:city":"Lunow",
    "sg:phone":"+49 33365/677",
    "sg:postcode":"16248",
    "sg:province":"Brandenburg",
    "wof:name":"Peter Kriedemann Bau Und Sanierungs Gmbh",
    "wof:placetype":"venue"
},
  "geometry": {"coordinates":[14.120981,52.920609],"type":"Point"}
}