{
  "type": "Feature",
  "properties": {
    "iso:country":"DE",
    "sg:address":"Guerickestr. 25",
    "sg:city":"M\u00fcnchen",
    "sg:phone":"+49 89/3613848",
    "sg:postcode":"80805",
    "sg:province":"Bayern",
    "wof:name":"Alexander H\u00e4ufle Sen. Inhaber Diethelm S. M\u00fcller",
    "wof:placetype":"venue"
},
  "geometry": {"coordinates":[11.596716,48.174774],"type":"Point"}
}