{
  "type": "Feature",
  "properties": {
    "iso:country":"DE",
    "sg:address":"Hafenstr. 182",
    "sg:city":"Bremerhaven",
    "sg:phone":"+49 471/52125",
    "sg:postcode":"27568",
    "sg:province":"Bremen",
    "wof:name":"Pantke",
    "wof:placetype":"venue"
},
  "geometry": {"coordinates":[8.586346,53.563568],"type":"Point"}
}