{
  "type": "Feature",
  "properties": {
    "iso:country":"DE",
    "sg:address":"Kurf\u00fcrstenstr. 47",
    "sg:city":"Bonn",
    "sg:phone":"+49 228/216115",
    "sg:postcode":"53115",
    "sg:province":"Nordrhein-Westfalen",
    "wof:name":"C. Obernolte Immobilienmakler",
    "wof:placetype":"venue"
},
  "geometry": {"coordinates":[7.0971951485,50.7250709534],"type":"Point"}
}