{
  "type": "Feature",
  "properties": {
    "iso:country":"DE",
    "sg:address":"Casterfeldstr. 66-72",
    "sg:city":"Mannheim",
    "sg:phone":"+49 621/860060",
    "sg:postcode":"68199",
    "sg:province":"Baden-W\u00fcrttemberg",
    "wof:name":"Hill & M\u00fcller Gmbh",
    "wof:placetype":"venue"
},
  "geometry": {"coordinates":[8.502827,49.448826],"type":"Point"}
}