{
  "type": "Feature",
  "properties": {
    "iso:country":"DE",
    "sg:address":"Sperberstr. 14",
    "sg:city":"M\u00f6nchengladbach",
    "sg:postcode":"41239",
    "sg:province":"Nordrhein-Westfalen",
    "wof:name":"Symposion Handels Ohg",
    "wof:placetype":"venue"
},
  "geometry": {"coordinates":[6.420352,51.152973],"type":"Point"}
}