{
  "type": "Feature",
  "properties": {
    "iso:country":"DE",
    "sg:address":"K\u00f6nigsberger Str. 14",
    "sg:city":"Espelkamp",
    "sg:postcode":"32339",
    "sg:province":"Nordrhein-Westfalen",
    "wof:name":"Johanna Nitsche",
    "wof:placetype":"venue"
},
  "geometry": {"coordinates":[8.6266803741,52.3847465515],"type":"Point"}
}