{
  "type": "Feature",
  "properties": {
    "iso:country":"DE",
    "sg:address":"Im H\u00f6fchen 5",
    "sg:city":"Neunkirchen-Seelscheid",
    "sg:phone":"+49 4922/478130",
    "sg:postcode":"53819",
    "sg:province":"Nordrhein-Westfalen",
    "wof:name":"Ulrich J\u00dctten",
    "wof:placetype":"venue"
},
  "geometry": {"coordinates":[7.359355,50.847099],"type":"Point"}
}