{
  "type": "Feature",
  "properties": {
    "iso:country":"DE",
    "sg:address":"Fritz-Hintermayr-Str. 7",
    "sg:city":"Augsburg",
    "sg:phone":"+49 821/3242906",
    "sg:postcode":"86159",
    "sg:province":"Bayern",
    "wof:name":"Anna-hintermayr-stift Altenheim",
    "wof:placetype":"venue"
},
  "geometry": {"coordinates":[10.88923,48.351727],"type":"Point"}
}