{
  "type": "Feature",
  "properties": {
    "iso:country":"DE",
    "sg:address":"Forsthausstr. 1",
    "sg:city":"Burghaun",
    "sg:phone":"+49 6652/6232",
    "sg:postcode":"36151",
    "sg:province":"Hessen",
    "wof:name":"R & O Gmbh",
    "wof:placetype":"venue"
},
  "geometry": {"coordinates":[9.707494,50.722839],"type":"Point"}
}