{
  "type": "Feature",
  "properties": {
    "iso:country":"DE",
    "sg:address":"Pforzheimer Str. 17",
    "sg:city":"Neulingen",
    "sg:phone":"+49 7237/274",
    "sg:postcode":"75245",
    "sg:province":"Baden-W\u00fcrttemberg",
    "wof:name":"Helmut Redlinger",
    "wof:placetype":"venue"
},
  "geometry": {"coordinates":[8.728859,48.968372],"type":"Point"}
}