{
  "type": "Feature",
  "properties": {
    "iso:country":"DE",
    "sg:address":"Faberweg 25",
    "sg:city":"Kirchheim",
    "sg:phone":"+49 7021/81015",
    "sg:postcode":"73230",
    "sg:province":"Baden-W\u00fcrttemberg",
    "wof:name":"T\u00dcv S\u00fcdwest",
    "wof:placetype":"venue"
},
  "geometry": {"coordinates":[9.4548654556,48.6349754333],"type":"Point"}
}