{
  "type": "Feature",
  "properties": {
    "iso:country":"DE",
    "sg:address":"Hollenbecker Str. 2",
    "sg:city":"Bargstedt",
    "sg:phone":"+49 4164/4109",
    "sg:postcode":"21698",
    "sg:province":"Niedersachsen",
    "wof:name":"J\u00fcrgen Vogt",
    "wof:placetype":"venue"
},
  "geometry": {"coordinates":[9.450998,53.458462],"type":"Point"}
}