{
  "type": "Feature",
  "properties": {
    "iso:country":"DE",
    "sg:address":"Mauerstr. 48",
    "sg:city":"Lage",
    "sg:phone":"+49 5232/7253",
    "sg:postcode":"32791",
    "sg:province":"Nordrhein-Westfalen",
    "wof:name":"Aug. Watermann",
    "wof:placetype":"venue"
},
  "geometry": {"coordinates":[8.756866,51.985332],"type":"Point"}
}