{
  "type": "Feature",
  "properties": {
    "iso:country":"DE",
    "sg:address":"Wilhelm-Baur-Str. 34",
    "sg:city":"Lindenfels",
    "sg:phone":"+49 6255/2432",
    "sg:postcode":"64678",
    "sg:province":"Hessen",
    "wof:name":"Rest & Schneider Gmbh",
    "wof:placetype":"venue"
},
  "geometry": {"coordinates":[8.77803,49.68087],"type":"Point"}
}