{
  "type": "Feature",
  "properties": {
    "iso:country":"DE",
    "sg:address":"K\u00fcnzeller Str. 47",
    "sg:city":"Fulda",
    "sg:postcode":"36043",
    "sg:province":"Hessen",
    "wof:name":"Stahlhandel Fulda Gmbh",
    "wof:placetype":"venue"
},
  "geometry": {"coordinates":[9.687252,50.547043],"type":"Point"}
}