{
  "type": "Feature",
  "properties": {
    "iso:country":"DE",
    "sg:address":"Hauptstr. 5",
    "sg:city":"Holzwickede",
    "sg:phone":"+49 2301/12338",
    "sg:postcode":"59439",
    "sg:province":"Nordrhein-Westfalen",
    "wof:name":"Bernd Habelmann",
    "wof:placetype":"venue"
},
  "geometry": {"coordinates":[7.617189,51.502651],"type":"Point"}
}