{
  "type": "Feature",
  "properties": {
    "iso:country":"DE",
    "sg:address":"St.-Jakobus-Str. 6",
    "sg:city":"Lennestadt",
    "sg:postcode":"57368",
    "sg:province":"Nordrhein-Westfalen",
    "wof:name":"Hytek Enterprises E. K.",
    "wof:placetype":"venue"
},
  "geometry": {"coordinates":[8.0555143356,51.1533622742],"type":"Point"}
}