{
  "type": "Feature",
  "properties": {
    "iso:country":"DE",
    "sg:address":"Ludwigstr. 16",
    "sg:city":"Dortmund",
    "sg:phone":"+49 231/572188",
    "sg:postcode":"44135",
    "sg:province":"Nordrhein-Westfalen",
    "wof:name":"High Art Dental Gmbh",
    "wof:placetype":"venue"
},
  "geometry": {"coordinates":[7.4669861794,51.5170173645],"type":"Point"}
}