{
  "type": "Feature",
  "properties": {
    "iso:country":"DE",
    "sg:address":"Gaadeberg 2",
    "sg:city":"Hattstedt",
    "sg:phone":"+49 4846/1525",
    "sg:postcode":"25856",
    "sg:province":"Schleswig-Holstein",
    "wof:name":"Hans-j\u00fcrgen Hagge",
    "wof:placetype":"venue"
},
  "geometry": {"coordinates":[9.024810791,54.5271987915],"type":"Point"}
}