{
  "type": "Feature",
  "properties": {
    "iso:country":"DE",
    "sg:address":"Alter Markt 3",
    "sg:city":"Ortenberg",
    "sg:phone":"+49 6046/7881",
    "sg:postcode":"63683",
    "sg:province":"Hessen",
    "wof:name":"B\u00fcrgerspie\u00df",
    "wof:placetype":"venue"
},
  "geometry": {"coordinates":[9.0561065674,50.3576469421],"type":"Point"}
}