{
  "type": "Feature",
  "properties": {
    "iso:country":"DE",
    "sg:address":"Ossietzkystr. 35",
    "sg:city":"Mei\u00dfen",
    "sg:phone":"+49 3521/4660",
    "sg:postcode":"01662",
    "sg:province":"Sachsen",
    "wof:name":"Gmm Glasmaschinenbau",
    "wof:placetype":"venue"
},
  "geometry": {"coordinates":[13.458829,51.137821],"type":"Point"}
}