{
  "type": "Feature",
  "properties": {
    "iso:country":"DE",
    "sg:address":"Heilwigstr. 59",
    "sg:city":"M\u00fcnchen",
    "sg:phone":"+49 89/4309993",
    "sg:postcode":"81827",
    "sg:province":"Bayern",
    "wof:name":"Josef Amberger Gro\u00dfverbraucher-",
    "wof:placetype":"venue"
},
  "geometry": {"coordinates":[11.683968,48.113235],"type":"Point"}
}