{
  "type": "Feature",
  "properties": {
    "iso:country":"DE",
    "sg:address":"Bahnhofstr. 39",
    "sg:city":"Giessen",
    "sg:phone":"+49 641",
    "sg:postcode":"35390",
    "sg:province":"Hessen",
    "wof:name":"Wisa Sanierungs Gmbh",
    "wof:placetype":"venue"
},
  "geometry": {"coordinates":[8.669826,50.584118],"type":"Point"}
}