{
  "type": "Feature",
  "properties": {
    "iso:country":"DE",
    "sg:address":"Dorf 7 1/5",
    "sg:city":"Jachenau",
    "sg:phone":"+49 8043/376",
    "sg:postcode":"83676",
    "sg:province":"Bayern",
    "wof:name":"Fremdenheim Karl Pfund",
    "wof:placetype":"venue"
},
  "geometry": {"coordinates":[11.4347429276,47.6057853699],"type":"Point"}
}