{
  "type": "Feature",
  "properties": {
    "iso:country":"DE",
    "sg:address":"Uhlandstr. 142",
    "sg:city":"Berlin",
    "sg:phone":"+49 30/8613015",
    "sg:postcode":"10719",
    "sg:province":"Berlin",
    "wof:name":"China-restaurant Liu Yuan",
    "wof:placetype":"venue"
},
  "geometry": {"coordinates":[13.3240766525,52.4950141907],"type":"Point"}
}