{
  "type": "Feature",
  "properties": {
    "iso:country":"DE",
    "sg:address":"G\u00f6rau 30",
    "sg:city":"Weismain",
    "sg:phone":"+49 9575/526",
    "sg:postcode":"96260",
    "sg:province":"Bayern",
    "wof:name":"W. Lenke",
    "wof:placetype":"venue"
},
  "geometry": {"coordinates":[11.288484,50.069786],"type":"Point"}
}