{
  "type": "Feature",
  "properties": {
    "iso:country":"DE",
    "sg:address":"Frankenstr. 26",
    "sg:city":"Gro\u00dfrinderfeld",
    "sg:phone":"+49 9349/234",
    "sg:postcode":"97950",
    "sg:province":"Baden-W\u00fcrttemberg",
    "wof:name":"Erich H\u00e4usler",
    "wof:placetype":"venue"
},
  "geometry": {"coordinates":[9.7363491058,49.6636734009],"type":"Point"}
}