{
  "type": "Feature",
  "properties": {
    "iso:country":"DE",
    "sg:address":"Neukirchener Str. 4",
    "sg:city":"Riedering",
    "sg:phone":"+49 8036/9294",
    "sg:postcode":"83083",
    "sg:province":"Bayern",
    "wof:name":"B & S Immobilien Verwertungs-gmbh",
    "wof:placetype":"venue"
},
  "geometry": {"coordinates":[12.2272291183,47.8490371704],"type":"Point"}
}