{
  "type": "Feature",
  "properties": {
    "iso:country":"DE",
    "sg:address":"Heinrich-G\u00f6bel-Str. 34",
    "sg:city":"Springe",
    "sg:phone":"+49 5041/640235",
    "sg:postcode":"31832",
    "sg:province":"Niedersachsen",
    "wof:name":"Erika V\u00f6lkoi",
    "wof:placetype":"venue"
},
  "geometry": {"coordinates":[9.542943,52.207901],"type":"Point"}
}