{
  "type": "Feature",
  "properties": {
    "iso:country":"DE",
    "sg:address":"Heimstr. 25",
    "sg:city":"Meiningen",
    "sg:phone":"+49 3693/75794",
    "sg:postcode":"98617",
    "sg:province":"Th\u00fcringen",
    "wof:name":"R. Fuchs Anlageberater",
    "wof:placetype":"venue"
},
  "geometry": {"coordinates":[10.4163417816,50.5808486938],"type":"Point"}
}