{
  "type": "Feature",
  "properties": {
    "iso:country":"DE",
    "sg:address":"D\u00fcstruper Str. 38",
    "sg:city":"Osnabr\u00fcck",
    "sg:phone":"+49 541/50197",
    "sg:postcode":"49086",
    "sg:province":"Niedersachsen",
    "wof:name":"Helmut Niekamp Komponist",
    "wof:placetype":"venue"
},
  "geometry": {"coordinates":[8.1024923325,52.2558937073],"type":"Point"}
}