{
  "type": "Feature",
  "properties": {
    "iso:country":"DE",
    "sg:address":"Volkartstr. 66",
    "sg:city":"M\u00fcnchen",
    "sg:phone":"+49 89/1238010",
    "sg:postcode":"80636",
    "sg:province":"Bayern",
    "wof:name":"Drost-reidler Hausverwaltungs Gmbh",
    "wof:placetype":"venue"
},
  "geometry": {"coordinates":[11.5412111282,48.1581382751],"type":"Point"}
}