{
  "type": "Feature",
  "properties": {
    "iso:country":"DE",
    "sg:address":"Bismarckstr. 16",
    "sg:city":"Lemgo",
    "sg:phone":"+49 5261/92940",
    "sg:postcode":"32657",
    "sg:province":"Nordrhein-Westfalen",
    "wof:name":"Gudrun Rehme Rechtsanw\u00e4ltin",
    "wof:placetype":"venue"
},
  "geometry": {"coordinates":[8.9094591141,52.0272521973],"type":"Point"}
}