{
  "type": "Feature",
  "properties": {
    "iso:country":"DE",
    "sg:address":"Markt 5",
    "sg:city":"Weimar",
    "sg:postcode":"99423",
    "sg:province":"Th\u00fcringen",
    "wof:name":"Europas Kultur Stadt Marketing Gmbh",
    "wof:placetype":"venue"
},
  "geometry": {"coordinates":[11.3301134109,50.9796714783],"type":"Point"}
}