{
  "type": "Feature",
  "properties": {
    "iso:country":"DE",
    "sg:address":"Bielefelder Str. 113",
    "sg:city":"Rheda-Wiedenbr\u00fcck",
    "sg:phone":"+49 5242/8676",
    "sg:postcode":"33378",
    "sg:province":"Nordrhein-Westfalen",
    "wof:name":"Next Service Inh. Dieter Rolef E. K.",
    "wof:placetype":"venue"
},
  "geometry": {"coordinates":[8.342358,51.868557],"type":"Point"}
}