{
  "type": "Feature",
  "properties": {
    "iso:country":"DE",
    "sg:address":"Jakobgasse 9",
    "sg:city":"Heilbronn",
    "sg:phone":"+49 7131/6560",
    "sg:postcode":"74072",
    "sg:province":"Baden-W\u00fcrttemberg",
    "wof:name":"Hotel Nestor",
    "wof:placetype":"venue"
},
  "geometry": {"coordinates":[9.2221546173,49.1442565918],"type":"Point"}
}