{
  "type": "Feature",
  "properties": {
    "iso:country":"DE",
    "sg:address":"Friedenseiche 4",
    "sg:city":"Leitzkau",
    "sg:phone":"+49 39241/4207",
    "sg:postcode":"39279",
    "sg:province":"Sachsen-Anhalt",
    "wof:name":"Lothar Kr\u00fcger",
    "wof:placetype":"venue"
},
  "geometry": {"coordinates":[12.0708246231,52.1122665405],"type":"Point"}
}