{
  "type": "Feature",
  "properties": {
    "iso:country":"DE",
    "sg:address":"Kanalstr. 47",
    "sg:city":"M\u00fcnster",
    "sg:phone":"+49 251/201954",
    "sg:postcode":"48147",
    "sg:province":"Nordrhein-Westfalen",
    "wof:name":"Cl. Pues",
    "wof:placetype":"venue"
},
  "geometry": {"coordinates":[7.6335,51.97863],"type":"Point"}
}