{
  "type": "Feature",
  "properties": {
    "iso:country":"DE",
    "sg:address":"Philipsstr.",
    "sg:city":"Wetzlar",
    "sg:postcode":"35576",
    "sg:province":"Hessen",
    "wof:name":"Bauhaus Gmbh & Co. Kg",
    "wof:placetype":"venue"
},
  "geometry": {"coordinates":[8.505487442,50.5684204102],"type":"Point"}
}