{
  "type": "Feature",
  "properties": {
    "iso:country":"DE",
    "sg:address":"Sitzenkircher Str. 18",
    "sg:city":"Kandern",
    "sg:phone":"+49 7626/7521",
    "sg:postcode":"79400",
    "sg:province":"Baden-W\u00fcrttemberg",
    "wof:name":"Harald Schweinlin",
    "wof:placetype":"venue"
},
  "geometry": {"coordinates":[7.662051,47.718922],"type":"Point"}
}