{
  "type": "Feature",
  "properties": {
    "iso:country":"DE",
    "sg:address":"Admiralstr. 3",
    "sg:city":"Bremen",
    "sg:phone":"+49 421/352021",
    "sg:postcode":"28215",
    "sg:province":"Bremen",
    "wof:name":"Minden Und Brandt Rechtsanw\u00e4lte",
    "wof:placetype":"venue"
},
  "geometry": {"coordinates":[8.8083734512,53.0883750916],"type":"Point"}
}