{
  "type": "Feature",
  "properties": {
    "iso:country":"DE",
    "sg:address":"Schulstr. 19",
    "sg:city":"Senftenberg",
    "sg:postcode":"01968",
    "sg:province":"Brandenburg",
    "wof:name":"K. Grafe",
    "wof:placetype":"venue"
},
  "geometry": {"coordinates":[14.0013742447,51.5172843933],"type":"Point"}
}