{
  "type": "Feature",
  "properties": {
    "iso:country":"DE",
    "sg:address":"Eggersallee 19",
    "sg:city":"Hamburg",
    "sg:postcode":"22763",
    "sg:province":"Hamburg",
    "wof:name":"Wohnanlage Hamm Beteiligungs-cremon",
    "wof:placetype":"venue"
},
  "geometry": {"coordinates":[9.9189805984,53.5478019714],"type":"Point"}
}