{
  "type": "Feature",
  "properties": {
    "iso:country":"DE",
    "sg:address":"Welserstr. 10f",
    "sg:city":"K\u00f6ln",
    "sg:phone":"+49 2203/38740",
    "sg:postcode":"51149",
    "sg:province":"Nordrhein-Westfalen",
    "wof:name":"Rainer Gindal Bustouristik Gmbh",
    "wof:placetype":"venue"
},
  "geometry": {"coordinates":[7.0608110428,50.9102287292],"type":"Point"}
}