{
  "type": "Feature",
  "properties": {
    "iso:country":"DE",
    "sg:address":"Eickeler Bruch 26 a",
    "sg:city":"Herne",
    "sg:phone":"+49 2325/60206",
    "sg:postcode":"44651",
    "sg:province":"Nordrhein-Westfalen",
    "wof:name":"Konrad Noll Architekt",
    "wof:placetype":"venue"
},
  "geometry": {"coordinates":[7.165928,51.51329],"type":"Point"}
}