{
  "type": "Feature",
  "properties": {
    "iso:country":"DE",
    "sg:address":"Sch\u00f6nerlinder Str. 29 A",
    "sg:city":"Berlin",
    "sg:phone":"+49 4930/4747900",
    "sg:postcode":"13127",
    "sg:province":"Berlin",
    "wof:name":"Pyro-art\u00aefeuerwerke Gmbh",
    "wof:placetype":"venue"
},
  "geometry": {"coordinates":[13.4406929016,52.6316337585],"type":"Point"}
}