{
  "type": "Feature",
  "properties": {
    "iso:country":"DE",
    "sg:address":"Ernst-Th\u00e4lmann-Str. 25",
    "sg:city":"Strausberg",
    "sg:postcode":"15344",
    "sg:province":"Brandenburg",
    "wof:name":"Kaegi Leasing Gmbh",
    "wof:placetype":"venue"
},
  "geometry": {"coordinates":[13.848687,52.536427],"type":"Point"}
}