{
  "type": "Feature",
  "properties": {
    "iso:country":"DE",
    "sg:address":"H\u00f6hnerweg 2-4",
    "sg:city":"Weinheim",
    "sg:postcode":"69469",
    "sg:province":"Baden-W\u00fcrttemberg",
    "wof:name":"Freudenberg Forschungs- Dienste Kg",
    "wof:placetype":"venue"
},
  "geometry": {"coordinates":[8.6640281677,49.5544281006],"type":"Point"}
}