{
  "type": "Feature",
  "properties": {
    "iso:country":"DE",
    "sg:address":"Obere Sch\u00fctzenstr. 11",
    "sg:city":"Burgebrach",
    "sg:phone":"+49 9546/921574",
    "sg:postcode":"96138",
    "sg:province":"Bayern",
    "wof:name":"Edv-beratung Trenz Gmbh",
    "wof:placetype":"venue"
},
  "geometry": {"coordinates":[10.7337331772,49.8218803406],"type":"Point"}
}