{
  "type": "Feature",
  "properties": {
    "iso:country":"DE",
    "sg:address":"Schwalbacher Str. 5",
    "sg:city":"K\u00f6nigstein",
    "sg:phone":"+49 4961/734663",
    "sg:postcode":"61462",
    "sg:province":"Hessen",
    "wof:name":"Getr\u00c4nke Elzenheimer Gmbh",
    "wof:placetype":"venue"
},
  "geometry": {"coordinates":[8.49548,50.170319],"type":"Point"}
}