{
  "type": "Feature",
  "properties": {
    "iso:country":"DE",
    "sg:address":"Lehrte",
    "sg:city":"Lehrte",
    "sg:phone":"+49 5132",
    "sg:postcode":"31275",
    "sg:province":"Niedersachsen",
    "wof:name":"Zoo Klein",
    "wof:placetype":"venue"
},
  "geometry": {"coordinates":[10.02061,52.376621],"type":"Point"}
}