{
  "type": "Feature",
  "properties": {
    "iso:country":"DE",
    "sg:address":"Feldbergstr. 9",
    "sg:city":"St. M\u00e4rgen",
    "sg:phone":"+49 7669/787",
    "sg:postcode":"79274",
    "sg:province":"Baden-W\u00fcrttemberg",
    "wof:name":"Hotel Hirschen",
    "wof:placetype":"venue"
},
  "geometry": {"coordinates":[8.0944318771,48.0083808899],"type":"Point"}
}