{
  "type": "Feature",
  "properties": {
    "iso:country":"DE",
    "sg:address":"Sonnenleite 9",
    "sg:city":"Pollenfeld",
    "sg:phone":"+49 8423/570",
    "sg:postcode":"85131",
    "sg:province":"Bayern",
    "wof:name":"Josef Schneider",
    "wof:placetype":"venue"
},
  "geometry": {"coordinates":[11.228407,48.959717],"type":"Point"}
}