{
  "type": "Feature",
  "properties": {
    "iso:country":"DE",
    "sg:address":"Merianstr. 2",
    "sg:city":"Amberg",
    "sg:phone":"+49 9621/72975",
    "sg:postcode":"92224",
    "sg:province":"Bayern",
    "wof:name":"Griechisches Restaurant Akropolis",
    "wof:placetype":"venue"
},
  "geometry": {"coordinates":[11.8804130554,49.4408950806],"type":"Point"}
}