{
  "type": "Feature",
  "properties": {
    "iso:country":"DE",
    "sg:address":"Elisabethmarkt",
    "sg:city":"M\u00fcnchen",
    "sg:phone":"+49 89/2717779",
    "sg:postcode":"80796",
    "sg:province":"Bayern",
    "wof:name":"A. Z\u00f6hrer",
    "wof:placetype":"venue"
},
  "geometry": {"coordinates":[11.5737848282,48.1569900513],"type":"Point"}
}