{
  "type": "Feature",
  "properties": {
    "iso:country":"DE",
    "sg:address":"Muldstr. 79",
    "sg:city":"Dessau",
    "sg:phone":"+49 340/212948",
    "sg:postcode":"06844",
    "sg:province":"Sachsen-Anhalt",
    "wof:name":"Tanzcafe G\u00fcnther",
    "wof:placetype":"venue"
},
  "geometry": {"coordinates":[12.249250412,51.8348617554],"type":"Point"}
}