{
  "type": "Feature",
  "properties": {
    "iso:country":"DE",
    "sg:address":"Bahnhofstr 68",
    "sg:city":"Eisenh\u00fcttenstadt",
    "sg:phone":"+49 8640/8080",
    "sg:postcode":"15890",
    "sg:province":"Brandenburg",
    "wof:name":"Wimb\u00f6ck Gmbh",
    "wof:placetype":"venue"
},
  "geometry": {"coordinates":[12.4522228241,47.6692390442],"type":"Point"}
}