{
  "type": "Feature",
  "properties": {
    "iso:country":"DE",
    "sg:address":"Schleswiger Str. 82",
    "sg:city":"Satrup",
    "sg:phone":"+49 4633/8592",
    "sg:postcode":"24986",
    "sg:province":"Schleswig-Holstein",
    "wof:name":"Holger Clasen",
    "wof:placetype":"venue"
},
  "geometry": {"coordinates":[9.6040210724,54.6805076599],"type":"Point"}
}