{
  "type": "Feature",
  "properties": {
    "iso:country":"DE",
    "sg:address":"Haydnstr. 29",
    "sg:city":"Ettlingen",
    "sg:phone":"+49 7243/12408",
    "sg:postcode":"76275",
    "sg:province":"Baden-W\u00fcrttemberg",
    "wof:name":"Mosa-bau-gmbh",
    "wof:placetype":"venue"
},
  "geometry": {"coordinates":[8.3943119049,48.941619873],"type":"Point"}
}