{
  "type": "Feature",
  "properties": {
    "iso:country":"DE",
    "sg:address":"Friedrich-M\u00f6schke-Str. 6",
    "sg:city":"M\u00fclheim",
    "sg:phone":"+49 208/496222",
    "sg:postcode":"45472",
    "sg:province":"Nordrhein-Westfalen",
    "wof:name":"Hermann Holtkamp Architekt",
    "wof:placetype":"venue"
},
  "geometry": {"coordinates":[6.94337,51.431858],"type":"Point"}
}