{
  "type": "Feature",
  "properties": {
    "iso:country":"DE",
    "sg:address":"K\u00e4the-Kollwitz-Str. 12",
    "sg:city":"Leipzig",
    "sg:phone":"+49 341/9802166",
    "sg:postcode":"04109",
    "sg:province":"Sachsen",
    "wof:name":"Ines Fiedler",
    "wof:placetype":"venue"
},
  "geometry": {"coordinates":[12.367023468,51.3410606384],"type":"Point"}
}