{
  "type": "Feature",
  "properties": {
    "iso:country":"DE",
    "sg:address":"R\u00f6nneburger Freiheit 50",
    "sg:city":"Hamburg",
    "sg:phone":"+49 40/76899330",
    "sg:postcode":"21079",
    "sg:province":"Hamburg",
    "wof:name":"Norbert Schweda Mobiler Kranservice",
    "wof:placetype":"venue"
},
  "geometry": {"coordinates":[9.999305,53.430809],"type":"Point"}
}