{
  "type": "Feature",
  "properties": {
    "iso:country":"DE",
    "sg:address":"Alleestr. 4 a",
    "sg:city":"Riesa",
    "sg:phone":"+49 3525/736358",
    "sg:postcode":"01591",
    "sg:province":"Sachsen",
    "wof:name":"Beutel Glasatelier Manitz",
    "wof:placetype":"venue"
},
  "geometry": {"coordinates":[13.2786512375,51.3216285706],"type":"Point"}
}