{
  "type": "Feature",
  "properties": {
    "iso:country":"DE",
    "sg:address":"Lange Str. 20",
    "sg:city":"Kelbra",
    "sg:phone":"+49 34651/6530",
    "sg:postcode":"06537",
    "sg:province":"Sachsen-Anhalt",
    "wof:name":"H. Mertens Anlageberater",
    "wof:placetype":"venue"
},
  "geometry": {"coordinates":[11.0643196106,51.4341812134],"type":"Point"}
}