{
  "type": "Feature",
  "properties": {
    "iso:country":"DE",
    "sg:address":"Schulsiedlung 1",
    "sg:city":"Wiesent",
    "sg:phone":"+49 9482/1490",
    "sg:postcode":"93109",
    "sg:province":"Bayern",
    "wof:name":"Dr. Med. Erwin Richter",
    "wof:placetype":"venue"
},
  "geometry": {"coordinates":[12.3750495911,49.0085945129],"type":"Point"}
}