{
  "type": "Feature",
  "properties": {
    "iso:country":"DE",
    "sg:address":"Jeversche Str. 38",
    "sg:city":"Wangerland",
    "sg:phone":"+49 4463/942020",
    "sg:postcode":"26434",
    "sg:province":"Niedersachsen",
    "wof:name":"Karl-heinz Peters",
    "wof:placetype":"venue"
},
  "geometry": {"coordinates":[7.915752,53.659424],"type":"Point"}
}