{
  "type": "Feature",
  "properties": {
    "iso:country":"DE",
    "sg:address":"Feckweilerberg 12",
    "sg:city":"Birkenfeld",
    "sg:phone":"+49 6782/5338",
    "sg:postcode":"55765",
    "sg:province":"Rheinland-Pfalz",
    "wof:name":"Erich Thome Architekt",
    "wof:placetype":"venue"
},
  "geometry": {"coordinates":[7.154405,49.655567],"type":"Point"}
}