{
  "type": "Feature",
  "properties": {
    "iso:country":"DE",
    "sg:address":"Oberelvenicher Str. 73",
    "sg:city":"Z\u00fclpich",
    "sg:phone":"+49 2252/2518",
    "sg:postcode":"53909",
    "sg:province":"Nordrhein-Westfalen",
    "wof:name":"Hubert Wirtz",
    "wof:placetype":"venue"
},
  "geometry": {"coordinates":[6.683633,50.712147],"type":"Point"}
}