{
  "type": "Feature",
  "properties": {
    "iso:country":"DE",
    "sg:address":"Alter Kirchplatz 2a",
    "sg:city":"Plaidt",
    "sg:phone":"+49 2632/73288",
    "sg:postcode":"56637",
    "sg:province":"Rheinland-Pfalz",
    "wof:name":"Kluwig",
    "wof:placetype":"venue"
},
  "geometry": {"coordinates":[7.3906979561,50.390537262],"type":"Point"}
}