{
  "type": "Feature",
  "properties": {
    "iso:country":"DE",
    "sg:address":"Ismaninger Str. 6",
    "sg:city":"M\u00fcnchen",
    "sg:phone":"+49 89/4702221",
    "sg:postcode":"81675",
    "sg:province":"Bayern",
    "wof:name":"Vis-a-vis Modeboutique Zollner Gmbh",
    "wof:placetype":"venue"
},
  "geometry": {"coordinates":[11.598135,48.135986],"type":"Point"}
}