{
  "type": "Feature",
  "properties": {
    "iso:country":"DE",
    "sg:address":"Grindelhof 43",
    "sg:city":"Hamburg",
    "sg:phone":"+49 40/4101305",
    "sg:postcode":"20146",
    "sg:province":"Hamburg",
    "wof:name":"Der Etrusker",
    "wof:placetype":"venue"
},
  "geometry": {"coordinates":[9.9834241867,53.5691604614],"type":"Point"}
}