{
  "type": "Feature",
  "properties": {
    "iso:country":"DE",
    "sg:address":"Berliner Str.",
    "sg:city":"Rinteln",
    "sg:phone":"+49 5751/75873",
    "sg:postcode":"31737",
    "sg:province":"Niedersachsen",
    "wof:name":"Ewald Bredow",
    "wof:placetype":"venue"
},
  "geometry": {"coordinates":[9.11673,52.193485],"type":"Point"}
}