{
  "type": "Feature",
  "properties": {
    "iso:country":"DE",
    "sg:address":"Hainer Weg 144",
    "sg:city":"Frankfurt",
    "sg:phone":"+49 69/685612",
    "sg:postcode":"60599",
    "sg:province":"Hessen",
    "wof:name":"Apotheke Am Hainerberg",
    "wof:placetype":"venue"
},
  "geometry": {"coordinates":[8.69602,50.094807],"type":"Point"}
}