{
  "type": "Feature",
  "properties": {
    "iso:country":"DE",
    "sg:address":"Friedenstr. 33",
    "sg:city":"Siershahn",
    "sg:phone":"+49 2623/5678",
    "sg:postcode":"56427",
    "sg:province":"Rheinland-Pfalz",
    "wof:name":"Fasel",
    "wof:placetype":"venue"
},
  "geometry": {"coordinates":[7.7809867859,50.4844932556],"type":"Point"}
}