{
  "type": "Feature",
  "properties": {
    "iso:country":"DE",
    "sg:address":"Zerndorfer Weg 6",
    "sg:city":"Berlin",
    "sg:phone":"+49 30/4012450",
    "sg:postcode":"13465",
    "sg:province":"Berlin",
    "wof:name":"Wolfgang Sonnenberg K\u00e4lte-klimatechnik Gmbh",
    "wof:placetype":"venue"
},
  "geometry": {"coordinates":[13.293421,52.641605],"type":"Point"}
}