{
  "type": "Feature",
  "properties": {
    "iso:country":"DE",
    "sg:address":"Feldstr. 9",
    "sg:city":"Schiffweiler",
    "sg:phone":"+49 6821/63164",
    "sg:postcode":"66578",
    "sg:province":"Saarland",
    "wof:name":"R. Jakob",
    "wof:placetype":"venue"
},
  "geometry": {"coordinates":[7.122835,49.3722],"type":"Point"}
}