{
  "type": "Feature",
  "properties": {
    "iso:country":"DE",
    "sg:address":"Leinenstr 21",
    "sg:city":"Blaubeuren",
    "sg:phone":"+49 7344/5096",
    "sg:postcode":"89143",
    "sg:province":"Baden-W\u00fcrttemberg",
    "wof:name":"Roesch Fliesen Gmbh",
    "wof:placetype":"venue"
},
  "geometry": {"coordinates":[9.7602777481,48.4284820557],"type":"Point"}
}