{
  "type": "Feature",
  "properties": {
    "iso:country":"DE",
    "sg:address":"Hubertusweg 30",
    "sg:city":"Neuss",
    "sg:phone":"+49 2131/461165",
    "sg:postcode":"41466",
    "sg:province":"Nordrhein-Westfalen",
    "wof:name":"Friedhelm Herkenrath",
    "wof:placetype":"venue"
},
  "geometry": {"coordinates":[6.689698,51.17321],"type":"Point"}
}