{
  "type": "Feature",
  "properties": {
    "iso:country":"DE",
    "sg:address":"Hermann-B\u00f6cker-Str. 13",
    "sg:city":"Olching",
    "sg:phone":"+49 8142/40980",
    "sg:postcode":"82140",
    "sg:province":"Bayern",
    "wof:name":"J. U. W. Sedlmayr Verwaltungs- Gmbh",
    "wof:placetype":"venue"
},
  "geometry": {"coordinates":[11.33401,48.223],"type":"Point"}
}