{
  "type": "Feature",
  "properties": {
    "iso:country":"DE",
    "sg:address":"R\u00fcbekamp 54",
    "sg:city":"Bremen",
    "sg:phone":"+49 421/617063",
    "sg:postcode":"28219",
    "sg:province":"Bremen",
    "wof:name":"Vural",
    "wof:placetype":"venue"
},
  "geometry": {"coordinates":[8.7746171951,53.1116142273],"type":"Point"}
}