{
  "type": "Feature",
  "properties": {
    "iso:country":"DE",
    "sg:address":"Schulstr. 4",
    "sg:city":"Hafenlohr",
    "sg:phone":"+49 9391/6800",
    "sg:postcode":"97840",
    "sg:province":"Bayern",
    "wof:name":"G. Bachmann",
    "wof:placetype":"venue"
},
  "geometry": {"coordinates":[9.580936,49.881996],"type":"Point"}
}