{
  "type": "Feature",
  "properties": {
    "iso:country":"DE",
    "sg:address":"Altenmittlauer Str. 14",
    "sg:city":"Freigericht",
    "sg:phone":"+49 6055/2706",
    "sg:postcode":"63579",
    "sg:province":"Hessen",
    "wof:name":"Antonia Rita Fuchs",
    "wof:placetype":"venue"
},
  "geometry": {"coordinates":[9.145175,50.153419],"type":"Point"}
}