{
  "type": "Feature",
  "properties": {
    "iso:country":"DE",
    "sg:address":"S\u00fcderstr. 75",
    "sg:city":"Harrislee",
    "sg:phone":"+49 461/78200",
    "sg:postcode":"24955",
    "sg:province":"Schleswig-Holstein",
    "wof:name":"Grenz-video E. K.",
    "wof:placetype":"venue"
},
  "geometry": {"coordinates":[9.39848423,54.8000984192],"type":"Point"}
}