{
  "type": "Feature",
  "properties": {
    "iso:country":"DE",
    "sg:address":"Sch\u00e4perdresch 3",
    "sg:city":"Hamburg",
    "sg:postcode":"22399",
    "sg:province":"Hamburg",
    "wof:name":"Europiran Gmbh",
    "wof:placetype":"venue"
},
  "geometry": {"coordinates":[10.0686225891,53.6709671021],"type":"Point"}
}