{
  "type": "Feature",
  "properties": {
    "iso:country":"DE",
    "sg:address":"Herforder Str. 127",
    "sg:city":"Vlotho",
    "sg:phone":"+49 5733/2043",
    "sg:postcode":"32602",
    "sg:province":"Nordrhein-Westfalen",
    "wof:name":"Rost Und Parker Gbr",
    "wof:placetype":"venue"
},
  "geometry": {"coordinates":[8.8428506851,52.1562652588],"type":"Point"}
}