{
  "type": "Feature",
  "properties": {
    "iso:country":"DE",
    "sg:address":"Unterfeldstr. 14",
    "sg:city":"Karlsruhe",
    "sg:phone":"+49 721/786770",
    "sg:postcode":"76149",
    "sg:province":"Baden-W\u00fcrttemberg",
    "wof:name":"Holbein-aotheke",
    "wof:placetype":"venue"
},
  "geometry": {"coordinates":[8.379879,49.047447],"type":"Point"}
}