{
  "type": "Feature",
  "properties": {
    "iso:country":"DE",
    "sg:address":"Wiesenstr. 2",
    "sg:city":"Ulmen",
    "sg:phone":"+49 2676/234",
    "sg:postcode":"56766",
    "sg:province":"Rheinland-Pfalz",
    "wof:name":"Gilles & Partner Internationale Spedition Gmbh",
    "wof:placetype":"venue"
},
  "geometry": {"coordinates":[6.969285965,50.219078064],"type":"Point"}
}