{
  "type": "Feature",
  "properties": {
    "iso:country":"DE",
    "sg:address":"Heimenstein 34",
    "sg:city":"Heilbad Heiligenstadt",
    "sg:phone":"+49 3606/612442",
    "sg:postcode":"37308",
    "sg:province":"Th\u00fcringen",
    "wof:name":"J\u00f6rg Hartmann",
    "wof:placetype":"venue"
},
  "geometry": {"coordinates":[10.141406,51.378376],"type":"Point"}
}