{
  "type": "Feature",
  "properties": {
    "iso:country":"DE",
    "sg:address":"Johann-Dahlem-Str. 50",
    "sg:city":"Mainaschaff",
    "sg:postcode":"63814",
    "sg:province":"Bayern",
    "wof:name":"Ems E-mediaservice Gmbh & Co. Kg",
    "wof:placetype":"venue"
},
  "geometry": {"coordinates":[9.092157,49.983971],"type":"Point"}
}