{
  "type": "Feature",
  "properties": {
    "iso:country":"DE",
    "sg:address":"Hauptstr. 101",
    "sg:city":"Scheibe-Alsbach",
    "sg:phone":"+49 36704/81188",
    "sg:postcode":"98749",
    "sg:province":"Th\u00fcringen",
    "wof:name":"N. Kluge",
    "wof:placetype":"venue"
},
  "geometry": {"coordinates":[11.05882,50.489769],"type":"Point"}
}