{
  "type": "Feature",
  "properties": {
    "iso:country":"DE",
    "sg:address":"Wilderich-Lang-Str. 13",
    "sg:city":"M\u00fcnchen",
    "sg:phone":"+49 89/132530",
    "sg:postcode":"80634",
    "sg:province":"Bayern",
    "wof:name":"Paul Daxenbichler Immobilienmakler",
    "wof:placetype":"venue"
},
  "geometry": {"coordinates":[11.5319290161,48.1474571228],"type":"Point"}
}