{
  "type": "Feature",
  "properties": {
    "iso:country":"DE",
    "sg:address":"Salacher Str. 112",
    "sg:city":"Eislingen",
    "sg:phone":"+49 7161/984510",
    "sg:postcode":"73054",
    "sg:province":"Baden-W\u00fcrttemberg",
    "wof:name":"Zweckverband Eislingen",
    "wof:placetype":"venue"
},
  "geometry": {"coordinates":[9.7216320038,48.6952857971],"type":"Point"}
}