{
  "type": "Feature",
  "properties": {
    "iso:country":"DE",
    "sg:address":"Industriestr. 1",
    "sg:city":"Maxh\u00fctte-Haidhof",
    "sg:phone":"+49 9471/3865",
    "sg:postcode":"93142",
    "sg:province":"Bayern",
    "wof:name":"Ratisbona Gradl & Co.",
    "wof:placetype":"venue"
},
  "geometry": {"coordinates":[12.09163,49.185219],"type":"Point"}
}