{
  "type": "Feature",
  "properties": {
    "iso:country":"DE",
    "sg:address":"Oderstr. 56",
    "sg:city":"Moers",
    "sg:phone":"+49 2841/41758",
    "sg:postcode":"47445",
    "sg:province":"Nordrhein-Westfalen",
    "wof:name":"Manfred Kr\u00fcger",
    "wof:placetype":"venue"
},
  "geometry": {"coordinates":[6.627176,51.483654],"type":"Point"}
}