{
  "type": "Feature",
  "properties": {
    "iso:country":"DE",
    "sg:address":"Zedernweg 7",
    "sg:city":"Neuss",
    "sg:phone":"+49 2137/4966",
    "sg:postcode":"41469",
    "sg:province":"Nordrhein-Westfalen",
    "wof:name":"E & S Eisen Und Stahlhandel Gmbh",
    "wof:placetype":"venue"
},
  "geometry": {"coordinates":[6.7253489494,51.1505966187],"type":"Point"}
}