{
  "type": "Feature",
  "properties": {
    "iso:country":"DE",
    "sg:address":"Konrad-K\u00fcmmel-Str. 7",
    "sg:city":"Schw\u00e4bisch Gm\u00fcnd",
    "sg:phone":"+49 7171/41470",
    "sg:postcode":"73529",
    "sg:province":"Baden-W\u00fcrttemberg",
    "wof:name":"Heise & Wanner Gmbh",
    "wof:placetype":"venue"
},
  "geometry": {"coordinates":[9.7958583832,48.7497787476],"type":"Point"}
}