{
  "type": "Feature",
  "properties": {
    "iso:country":"DE",
    "sg:address":"Hansestr. 35",
    "sg:city":"Emsdetten",
    "sg:phone":"+49 2572/2948",
    "sg:postcode":"48282",
    "sg:province":"Nordrhein-Westfalen",
    "wof:name":"Rudolf Heuing",
    "wof:placetype":"venue"
},
  "geometry": {"coordinates":[7.542287,52.172401],"type":"Point"}
}