{
  "type": "Feature",
  "properties": {
    "iso:country":"DE",
    "sg:city":"Wiesloch",
    "sg:phone":"+49 4962/225890",
    "sg:postcode":"69168",
    "sg:province":"Baden-W\u00fcrttemberg",
    "wof:name":"Volksbank Wiesloch Eg",
    "wof:placetype":"venue"
},
  "geometry": {"coordinates":[8.70179,49.295044],"type":"Point"}
}