{
  "type": "Feature",
  "properties": {
    "iso:country":"DE",
    "sg:address":"Friedhofsweg 5",
    "sg:city":"Oberasbach",
    "sg:phone":"+49 911/694651",
    "sg:postcode":"90522",
    "sg:province":"Bayern",
    "wof:name":"Kranken-altenpflege Diakonie",
    "wof:placetype":"venue"
},
  "geometry": {"coordinates":[10.98738,49.42054],"type":"Point"}
}