{
  "type": "Feature",
  "properties": {
    "iso:country":"DE",
    "sg:address":"Am Teich",
    "sg:city":"Pansdorf",
    "sg:phone":"+49 4504/81700",
    "sg:postcode":"23689",
    "sg:province":"Schleswig-Holstein",
    "wof:name":"Senioren- Und Pflegeheim Gro\u00df Gmbh",
    "wof:placetype":"venue"
},
  "geometry": {"coordinates":[10.710079,53.983582],"type":"Point"}
}