{
  "type": "Feature",
  "properties": {
    "iso:country":"DE",
    "sg:address":"Auf der Lake 1",
    "sg:city":"Schmallenberg",
    "sg:postcode":"57392",
    "sg:province":"Nordrhein-Westfalen",
    "wof:name":"Meiller Gmbh & Co. Verm\u00f6gensverwaltungs Kg",
    "wof:placetype":"venue"
},
  "geometry": {"coordinates":[8.2902202606,51.1561508179],"type":"Point"}
}