{
  "type": "Feature",
  "properties": {
    "iso:country":"DE",
    "sg:address":"Presterstieg 2",
    "sg:city":"Treia",
    "sg:phone":"+49 4626/202",
    "sg:postcode":"24896",
    "sg:province":"Schleswig-Holstein",
    "wof:name":"Ev. Pfarramt Treia",
    "wof:placetype":"venue"
},
  "geometry": {"coordinates":[9.321764946,54.5149154663],"type":"Point"}
}