{
  "type": "Feature",
  "properties": {
    "iso:country":"DE",
    "sg:address":"Haggenmillerstr. 10",
    "sg:city":"Ebersberg",
    "sg:phone":"+49 8092/20250",
    "sg:postcode":"85560",
    "sg:province":"Bayern",
    "wof:name":"Hans Und Ernst Brandl",
    "wof:placetype":"venue"
},
  "geometry": {"coordinates":[11.9612436295,48.0783157349],"type":"Point"}
}