{
  "type": "Feature",
  "properties": {
    "iso:country":"DE",
    "sg:address":"88489",
    "sg:city":"Wain",
    "sg:phone":"+49 7353/3494",
    "sg:postcode":"88489",
    "sg:province":"Baden-W\u00fcrttemberg",
    "wof:name":"Hirsch",
    "wof:placetype":"venue"
},
  "geometry": {"coordinates":[10.0171804428,48.1874198914],"type":"Point"}
}