{
  "type": "Feature",
  "properties": {
    "iso:country":"DE",
    "sg:address":"Staffoller 9",
    "sg:city":"Kn\u00fcllwald",
    "sg:phone":"+49 5681/71721",
    "sg:postcode":"34593",
    "sg:province":"Hessen",
    "wof:name":"Cornelia D\u00f6ring Rechtsanw\u00e4ltin",
    "wof:placetype":"venue"
},
  "geometry": {"coordinates":[9.4756765366,51.0015182495],"type":"Point"}
}