{
  "type": "Feature",
  "properties": {
    "iso:country":"DE",
    "sg:address":"Elsterstr. 13",
    "sg:city":"Moers",
    "sg:phone":"+49 2841/507086",
    "sg:postcode":"47443",
    "sg:province":"Nordrhein-Westfalen",
    "wof:name":"Frank Schulze Finanzberater",
    "wof:placetype":"venue"
},
  "geometry": {"coordinates":[6.6542420387,51.4658126831],"type":"Point"}
}