{
  "type": "Feature",
  "properties": {
    "iso:country":"DE",
    "sg:address":"Plautstr. 80",
    "sg:city":"Leipzig",
    "sg:phone":"+49 3606/613547",
    "sg:postcode":"04179",
    "sg:province":"Sachsen",
    "wof:name":"Lever Agrar-ag",
    "wof:placetype":"venue"
},
  "geometry": {"coordinates":[10.12685,51.388786],"type":"Point"}
}