{
  "type": "Feature",
  "properties": {
    "iso:country":"DE",
    "sg:address":"Poststr. 39",
    "sg:city":"Cuxhaven",
    "sg:phone":"+49 4721/52550",
    "sg:postcode":"27474",
    "sg:province":"Niedersachsen",
    "wof:name":"Horst Kausch",
    "wof:placetype":"venue"
},
  "geometry": {"coordinates":[8.695361,53.865543],"type":"Point"}
}