{
  "type": "Feature",
  "properties": {
    "iso:country":"DE",
    "sg:address":"Maier\u00e4cherstra\u00dfe 1",
    "sg:city":"Rottenburg a. Neckar",
    "sg:phone":"+49 7472/919890",
    "sg:postcode":"72108",
    "sg:province":"Baden-W\u00fcrttemberg",
    "wof:name":"Spe Paul Gmbh Kabelkonfektion",
    "wof:placetype":"venue"
},
  "geometry": {"coordinates":[8.9496002197,48.4784965515],"type":"Point"}
}