{
  "type": "Feature",
  "properties": {
    "iso:country":"DE",
    "sg:address":"Berliner Str 17",
    "sg:city":"Ronnenberg",
    "sg:phone":"+49 4951/1434623",
    "sg:postcode":"30952",
    "sg:province":"Niedersachsen",
    "wof:name":"Kreissparkasse Hannover",
    "wof:placetype":"venue"
},
  "geometry": {"coordinates":[9.668411,52.343304],"type":"Point"}
}