{
  "type": "Feature",
  "properties": {
    "iso:country":"DE",
    "sg:address":"Weinbergstr. 30",
    "sg:city":"M\u00fchlhausen",
    "sg:phone":"+49 36018/73760",
    "sg:postcode":"99974",
    "sg:province":"Th\u00fcringen",
    "wof:name":"Hans-dieter Jahnke",
    "wof:placetype":"venue"
},
  "geometry": {"coordinates":[10.443024,51.206516],"type":"Point"}
}