{
  "type": "Feature",
  "properties": {
    "iso:country":"DE",
    "sg:address":"H\u00f6henweg 14",
    "sg:city":"Aschaffenburg",
    "sg:phone":"+49 6021/60719",
    "sg:postcode":"63743",
    "sg:province":"Bayern",
    "wof:name":"Leander Becker Gmbh",
    "wof:placetype":"venue"
},
  "geometry": {"coordinates":[9.209937,49.943405],"type":"Point"}
}