{
  "type": "Feature",
  "properties": {
    "iso:country":"DE",
    "sg:address":"Voigtl\u00e4nderstr. 1",
    "sg:city":"N\u00fcrnberg",
    "sg:postcode":"90489",
    "sg:province":"Bayern",
    "wof:name":"Schopper Immobilien Verwaltungs- Und",
    "wof:placetype":"venue"
},
  "geometry": {"coordinates":[11.1024990082,49.457244873],"type":"Point"}
}