{
  "type": "Feature",
  "properties": {
    "iso:country":"DE",
    "sg:address":"Kirchstr. 18 a",
    "sg:city":"Solms",
    "sg:phone":"+49 6441/52198",
    "sg:postcode":"35606",
    "sg:province":"Hessen",
    "wof:name":"Christel Kanabaj-lemp",
    "wof:placetype":"venue"
},
  "geometry": {"coordinates":[8.4280061722,50.5521430969],"type":"Point"}
}