{
  "type": "Feature",
  "properties": {
    "iso:country":"DE",
    "sg:city":"Swisttal-Buschhoven",
    "sg:postcode":"53913",
    "sg:province":"Nordrhein-Westfalen",
    "wof:name":"Rechtsanwalt Falk Peters",
    "wof:placetype":"venue"
},
  "geometry": {"coordinates":[6.915384,50.670712],"type":"Point"}
}