{
  "type": "Feature",
  "properties": {
    "iso:country":"DE",
    "sg:address":"Annastr. 83",
    "sg:city":"Geilenkirchen",
    "sg:phone":"+49 2451/2822",
    "sg:postcode":"52511",
    "sg:province":"Nordrhein-Westfalen",
    "wof:name":"Josef Kaulard",
    "wof:placetype":"venue"
},
  "geometry": {"coordinates":[6.125046,50.998833],"type":"Point"}
}