{
  "type": "Feature",
  "properties": {
    "iso:country":"DE",
    "sg:address":"Am Kirchplatz 15",
    "sg:city":"Herzebrock-Clarholz",
    "sg:phone":"+49 5245/2484",
    "sg:postcode":"33442",
    "sg:province":"Nordrhein-Westfalen",
    "wof:name":"H. Krechting Lebensmittel",
    "wof:placetype":"venue"
},
  "geometry": {"coordinates":[8.245194,51.884132],"type":"Point"}
}