{
  "type": "Feature",
  "properties": {
    "iso:country":"DE",
    "sg:address":"Schillerstr. 5",
    "sg:city":"Zweibr\u00fccken",
    "sg:phone":"+49 6332/77944",
    "sg:postcode":"66482",
    "sg:province":"Rheinland-Pfalz",
    "wof:name":"Heinrich Weiler Rechtsanwalt",
    "wof:placetype":"venue"
},
  "geometry": {"coordinates":[7.3573789597,49.2498321533],"type":"Point"}
}