{
  "type": "Feature",
  "properties": {
    "iso:country":"DE",
    "sg:address":"Auf der H\u00fcls 128",
    "sg:city":"Aachen",
    "sg:phone":"+49 241/500074",
    "sg:postcode":"52068",
    "sg:province":"Nordrhein-Westfalen",
    "wof:name":"Mwm Planungsgruppe",
    "wof:placetype":"venue"
},
  "geometry": {"coordinates":[6.13428,50.783249],"type":"Point"}
}