{
  "type": "Feature",
  "properties": {
    "iso:country":"DE",
    "sg:address":"Leinstr. 11",
    "sg:city":"Nienburg",
    "sg:phone":"+49 5021/910766",
    "sg:postcode":"31582",
    "sg:province":"Niedersachsen",
    "wof:name":"Dr. Med. Wolf-dieter Herzog",
    "wof:placetype":"venue"
},
  "geometry": {"coordinates":[9.2082862854,52.6381111145],"type":"Point"}
}