{
  "type": "Feature",
  "properties": {
    "iso:country":"DE",
    "sg:address":"Altenlinde 51",
    "sg:city":"Lindlar",
    "sg:phone":"+49 2266/8087",
    "sg:postcode":"51789",
    "sg:province":"Nordrhein-Westfalen",
    "wof:name":"Zentra-m\u00f6belhof Lindlar Gmbh",
    "wof:placetype":"venue"
},
  "geometry": {"coordinates":[7.362974,51.02726],"type":"Point"}
}