{
  "type": "Feature",
  "properties": {
    "iso:country":"DE",
    "sg:address":"Hittisweiler 27",
    "sg:city":"Bad Waldsee",
    "sg:phone":"+49 7524/1280",
    "sg:postcode":"88339",
    "sg:province":"Baden-W\u00fcrttemberg",
    "wof:name":"Alfred Heber Gmbh",
    "wof:placetype":"venue"
},
  "geometry": {"coordinates":[9.7613983154,47.9184379578],"type":"Point"}
}