{
  "type": "Feature",
  "properties": {
    "iso:country":"DE",
    "sg:address":"Bahnhofstr. 13",
    "sg:city":"Berlin",
    "sg:phone":"+49 30/6528266",
    "sg:postcode":"12555",
    "sg:province":"Berlin",
    "wof:name":"Metamorph Gmbh",
    "wof:placetype":"venue"
},
  "geometry": {"coordinates":[13.577460289,52.4559555054],"type":"Point"}
}