{
  "type": "Feature",
  "properties": {
    "iso:country":"DE",
    "sg:address":"Hauptstr. 4 a",
    "sg:city":"Neuss",
    "sg:phone":"+49 2131/464313",
    "sg:postcode":"41472",
    "sg:province":"Nordrhein-Westfalen",
    "wof:name":"Elektro-krug Gmbh",
    "wof:placetype":"venue"
},
  "geometry": {"coordinates":[6.666191,51.161106],"type":"Point"}
}