{
  "type": "Feature",
  "properties": {
    "iso:country":"DE",
    "sg:address":"Schlickburg 6",
    "sg:city":"Neuendeich",
    "sg:phone":"+49 4125/1000",
    "sg:postcode":"25436",
    "sg:province":"Schleswig-Holstein",
    "wof:name":"J. Wagner",
    "wof:placetype":"venue"
},
  "geometry": {"coordinates":[9.5746984482,53.6846847534],"type":"Point"}
}