{
  "type": "Feature",
  "properties": {
    "iso:country":"DE",
    "sg:address":"Altm\u00fchlweg 23",
    "sg:city":"Hamburg",
    "sg:phone":"+49 40/6400522",
    "sg:postcode":"22393",
    "sg:province":"Hamburg",
    "wof:name":"Klaus-j\u00fcrgen Winkler",
    "wof:placetype":"venue"
},
  "geometry": {"coordinates":[10.1061382294,53.6406021118],"type":"Point"}
}