{
  "type": "Feature",
  "properties": {
    "iso:country":"DE",
    "sg:address":"Ritzenbergstr. 14",
    "sg:city":"Dresden",
    "sg:phone":"+49 351/4962158",
    "sg:postcode":"01067",
    "sg:province":"Sachsen",
    "wof:name":"Im Haus Der Gewerkschaft",
    "wof:placetype":"venue"
},
  "geometry": {"coordinates":[13.7263202667,51.0560112],"type":"Point"}
}