{
  "type": "Feature",
  "properties": {
    "iso:country":"DE",
    "sg:address":"Friedensstr. 2",
    "sg:city":"Ettlingen",
    "sg:phone":"+49 7243/76380",
    "sg:postcode":"76275",
    "sg:province":"Baden-W\u00fcrttemberg",
    "wof:name":"Ev. Alten- Und Altenpflegeheim E. V.",
    "wof:placetype":"venue"
},
  "geometry": {"coordinates":[8.41282,48.942371],"type":"Point"}
}