{
  "type": "Feature",
  "properties": {
    "iso:country":"DE",
    "sg:address":"Polsumer Str. 66",
    "sg:city":"Gelsenkirchen",
    "sg:phone":"+49 209/65867",
    "sg:postcode":"45896",
    "sg:province":"Nordrhein-Westfalen",
    "wof:name":"Mukaddem Karakus",
    "wof:placetype":"venue"
},
  "geometry": {"coordinates":[7.0518708229,51.5930290222],"type":"Point"}
}