{
  "type": "Feature",
  "properties": {
    "iso:country":"DE",
    "sg:address":"Dortelweiler Str. 98-100",
    "sg:city":"Frankfurt",
    "sg:phone":"+49 69/451490",
    "sg:postcode":"60389",
    "sg:province":"Hessen",
    "wof:name":"Marmor-rupp Gmbh",
    "wof:placetype":"venue"
},
  "geometry": {"coordinates":[8.7029352188,50.1358451843],"type":"Point"}
}