{
  "type": "Feature",
  "properties": {
    "iso:country":"DE",
    "sg:address":"Schlo\u00dfweg 4",
    "sg:city":"B\u00e4rnau",
    "sg:phone":"+49 9635/1750",
    "sg:postcode":"95671",
    "sg:province":"Bayern",
    "wof:name":"Modeg\u00fcrtel Keim",
    "wof:placetype":"venue"
},
  "geometry": {"coordinates":[12.429561,49.811024],"type":"Point"}
}