{
  "type": "Feature",
  "properties": {
    "iso:country":"DE",
    "sg:address":"Langgasse 1",
    "sg:city":"Dillenburg",
    "sg:phone":"+49 2771",
    "sg:postcode":"35685",
    "sg:province":"Hessen",
    "wof:name":"World Of Acation & Adventure",
    "wof:placetype":"venue"
},
  "geometry": {"coordinates":[8.2666692734,50.7680397034],"type":"Point"}
}