{
  "type": "Feature",
  "properties": {
    "iso:country":"DE",
    "sg:address":"Mainzer Str. 62",
    "sg:city":"Mainz",
    "sg:phone":"+49 6131/41119",
    "sg:postcode":"55124",
    "sg:province":"Rheinland-Pfalz",
    "wof:name":"Heinz Brandm\u00fcller",
    "wof:placetype":"venue"
},
  "geometry": {"coordinates":[8.2131071091,50.0003967285],"type":"Point"}
}