{
  "type": "Feature",
  "properties": {
    "iso:country":"DE",
    "sg:address":"Beverbrucher Damm 3",
    "sg:city":"Garrel",
    "sg:postcode":"49681",
    "sg:province":"Niedersachsen",
    "wof:name":"Clemens Wulfers Forellenhof K\u00f6nigsm\u00fchle",
    "wof:placetype":"venue"
},
  "geometry": {"coordinates":[8.1062917709,52.9848670959],"type":"Point"}
}