{
  "type": "Feature",
  "properties": {
    "iso:country":"DE",
    "sg:address":"Gartenstr. 22",
    "sg:city":"Rehau",
    "sg:phone":"+49 9283/1280",
    "sg:postcode":"95111",
    "sg:province":"Bayern",
    "wof:name":"Siegfried Steffen",
    "wof:placetype":"venue"
},
  "geometry": {"coordinates":[12.03459,50.247211],"type":"Point"}
}