{
  "type": "Feature",
  "properties": {
    "iso:country":"DE",
    "sg:address":"K\u00f6nigsallee 124",
    "sg:city":"Bochum",
    "sg:phone":"+49 234/9586187",
    "sg:postcode":"44789",
    "sg:province":"Nordrhein-Westfalen",
    "wof:name":"Patrick Ottowell",
    "wof:placetype":"venue"
},
  "geometry": {"coordinates":[7.2196688652,51.4637374878],"type":"Point"}
}