{
  "type": "Feature",
  "properties": {
    "iso:country":"DE",
    "sg:address":"G\u00e4nsheidestr. 21",
    "sg:city":"Stuttgart",
    "sg:postcode":"70184",
    "sg:province":"Baden-W\u00fcrttemberg",
    "wof:name":"Arbeitsgemeinschaft Stuttgarter B\u00fcrgervereine",
    "wof:placetype":"venue"
},
  "geometry": {"coordinates":[9.194618,48.775448],"type":"Point"}
}