{
  "type": "Feature",
  "properties": {
    "iso:country":"DE",
    "sg:address":"Ostbahnstr. 4",
    "sg:city":"Landau",
    "sg:phone":"+49 6341/88800",
    "sg:postcode":"76829",
    "sg:province":"Rheinland-Pfalz",
    "wof:name":"Deutscher Kinderschutzbund, Landesverband Rheinland-pfalz Ev",
    "wof:placetype":"venue"
},
  "geometry": {"coordinates":[8.11594,49.197571],"type":"Point"}
}