{
  "type": "Feature",
  "properties": {
    "iso:country":"DE",
    "sg:address":"Kr\u00e4mergasse 1",
    "sg:city":"Hadamar",
    "sg:phone":"+49 6433/2742",
    "sg:postcode":"65589",
    "sg:province":"Hessen",
    "wof:name":"Anna Egenolf",
    "wof:placetype":"venue"
},
  "geometry": {"coordinates":[8.046551,50.448681],"type":"Point"}
}