{
  "type": "Feature",
  "properties": {
    "iso:country":"DE",
    "sg:address":"Gutleutstr. 153",
    "sg:city":"Frankfurt",
    "sg:postcode":"60327",
    "sg:province":"Hessen",
    "wof:name":"Seungrie Handels- Reisen- Und Service Gmbh",
    "wof:placetype":"venue"
},
  "geometry": {"coordinates":[8.6604137421,50.1019172668],"type":"Point"}
}