{
  "type": "Feature",
  "properties": {
    "iso:country":"DE",
    "sg:address":"Bovenstr. 3",
    "sg:city":"Velbert",
    "sg:phone":"+49 2051/253665",
    "sg:postcode":"42551",
    "sg:province":"Nordrhein-Westfalen",
    "wof:name":"E. Lupp Metallwarengrosshandel",
    "wof:placetype":"venue"
},
  "geometry": {"coordinates":[7.050806,51.338554],"type":"Point"}
}