{
  "type": "Feature",
  "properties": {
    "iso:country":"DE",
    "sg:address":"Alte Landstra\u00dfe 10",
    "sg:city":"Sollerup",
    "sg:phone":"+49 4607/291",
    "sg:postcode":"24852",
    "sg:province":"Schleswig-Holstein",
    "wof:name":"Caodai-germany",
    "wof:placetype":"venue"
},
  "geometry": {"coordinates":[9.315133,54.578194],"type":"Point"}
}