{
  "type": "Feature",
  "properties": {
    "iso:country":"DE",
    "sg:address":"H\u00fcnxer Str. 317",
    "sg:city":"Dinslaken",
    "sg:phone":"+49 2064/30888",
    "sg:postcode":"46537",
    "sg:province":"Nordrhein-Westfalen",
    "wof:name":"Aral Ag",
    "wof:placetype":"venue"
},
  "geometry": {"coordinates":[6.7590641975,51.5780639648],"type":"Point"}
}