{
  "type": "Feature",
  "properties": {
    "iso:country":"DE",
    "sg:address":"Fichtenstr. 34-36",
    "sg:city":"Wuppertal",
    "sg:phone":"+49 202/250610",
    "sg:postcode":"42283",
    "sg:province":"Nordrhein-Westfalen",
    "wof:name":"Ley & Wiegandt Gmbh & Co.",
    "wof:placetype":"venue"
},
  "geometry": {"coordinates":[7.189951,51.275154],"type":"Point"}
}