{
  "type": "Feature",
  "properties": {
    "iso:country":"DE",
    "sg:address":"Claushof",
    "sg:city":"Heidesheim",
    "sg:phone":"+49 6132/59071",
    "sg:postcode":"55262",
    "sg:province":"Rheinland-Pfalz",
    "wof:name":"Herbert Arnold",
    "wof:placetype":"venue"
},
  "geometry": {"coordinates":[8.125954628,49.9952697754],"type":"Point"}
}