{
  "type": "Feature",
  "properties": {
    "iso:country":"DE",
    "sg:address":"Markt 32",
    "sg:city":"Waldershof",
    "sg:phone":"+49 9231/97777",
    "sg:postcode":"95679",
    "sg:province":"Bayern",
    "wof:name":"Dietrich Ackermann Ingenieur",
    "wof:placetype":"venue"
},
  "geometry": {"coordinates":[12.0624761581,49.9775619507],"type":"Point"}
}