{
  "type": "Feature",
  "properties": {
    "iso:country":"DE",
    "sg:address":"Am Kettenbach 7a",
    "sg:city":"Thiendorf",
    "sg:phone":"+49 35248/81238",
    "sg:postcode":"01561",
    "sg:province":"Sachsen",
    "wof:name":"Siegfried H\u00e4nel",
    "wof:placetype":"venue"
},
  "geometry": {"coordinates":[13.7426271439,51.2797317505],"type":"Point"}
}