{
  "type": "Feature",
  "properties": {
    "iso:country":"DE",
    "sg:address":"Mattenm\u00fchle 1",
    "sg:city":"Glottertal",
    "sg:postcode":"79286",
    "sg:province":"Baden-W\u00fcrttemberg",
    "wof:name":"Audiotricks",
    "wof:placetype":"venue"
},
  "geometry": {"coordinates":[7.919952,48.057121],"type":"Point"}
}