{
  "type": "Feature",
  "properties": {
    "iso:country":"DE",
    "sg:address":"Willy-Brandt-Ring 3",
    "sg:city":"Worms",
    "sg:phone":"+49 6241/23978",
    "sg:postcode":"67547",
    "sg:province":"Rheinland-Pfalz",
    "wof:name":"Ev. Pfarramt Magnus Gemeinde West",
    "wof:placetype":"venue"
},
  "geometry": {"coordinates":[8.3575773239,49.6273078918],"type":"Point"}
}