{
  "type": "Feature",
  "properties": {
    "iso:country":"DE",
    "sg:address":"Nebeniusstr. 4-6",
    "sg:city":"Karlsruhe",
    "sg:phone":"+49 721/932710",
    "sg:postcode":"76137",
    "sg:province":"Baden-W\u00fcrttemberg",
    "wof:name":"Bauhaus Gmbh & Co. Kg",
    "wof:placetype":"venue"
},
  "geometry": {"coordinates":[8.4044818878,48.9974555969],"type":"Point"}
}