{
  "type": "Feature",
  "properties": {
    "iso:country":"DE",
    "sg:address":"Pfarrstr. 7",
    "sg:city":"Oberstdorf",
    "sg:phone":"+49 8322/6690",
    "sg:postcode":"87561",
    "sg:province":"Bayern",
    "wof:name":"Prinz Luitpold",
    "wof:placetype":"venue"
},
  "geometry": {"coordinates":[10.2792291641,47.408241272],"type":"Point"}
}