{
  "type": "Feature",
  "properties": {
    "iso:country":"DE",
    "sg:address":"Eberst\u00e4dter Str. 2",
    "sg:city":"Eberstadt",
    "sg:phone":"+49 7134/4318",
    "sg:postcode":"74246",
    "sg:province":"Baden-W\u00fcrttemberg",
    "wof:name":"Guter Trunk",
    "wof:placetype":"venue"
},
  "geometry": {"coordinates":[9.3106136322,49.1888084412],"type":"Point"}
}