{
  "type": "Feature",
  "properties": {
    "iso:country":"DE",
    "sg:address":"Seehofstr. 3a",
    "sg:city":"Lorsch",
    "sg:phone":"+49 6251/57478",
    "sg:postcode":"64653",
    "sg:province":"Hessen",
    "wof:name":"Edur",
    "wof:placetype":"venue"
},
  "geometry": {"coordinates":[8.568102,49.643654],"type":"Point"}
}