{
  "type": "Feature",
  "properties": {
    "iso:country":"DE",
    "sg:address":"B\u00fcrgerbuschweg 7-9",
    "sg:city":"Leverkusen",
    "sg:postcode":"51381",
    "sg:province":"Nordrhein-Westfalen",
    "wof:name":"Groka-markt St\u00fcttgen",
    "wof:placetype":"venue"
},
  "geometry": {"coordinates":[7.0175619125,51.0509147644],"type":"Point"}
}