{
  "type": "Feature",
  "properties": {
    "iso:country":"DE",
    "sg:address":"Bollbr\u00fcgger Weg 38",
    "sg:city":"Goldberg",
    "sg:phone":"+49 38736/41792",
    "sg:postcode":"19399",
    "sg:province":"Mecklenburg-Vorpommern",
    "wof:name":"Gerald Martens",
    "wof:placetype":"venue"
},
  "geometry": {"coordinates":[12.086623,53.594349],"type":"Point"}
}