{
  "type": "Feature",
  "properties": {
    "iso:country":"DE",
    "sg:address":"Heumarkt 2",
    "sg:city":"Hanau",
    "sg:phone":"+49 6181/253370",
    "sg:postcode":"63450",
    "sg:province":"Hessen",
    "wof:name":"Angelika Schnieders Rechtsanw\u00e4ltin",
    "wof:placetype":"venue"
},
  "geometry": {"coordinates":[8.9137144089,50.1325340271],"type":"Point"}
}