{
  "type": "Feature",
  "properties": {
    "iso:country":"DE",
    "sg:address":"Mauerstr. 34-1",
    "sg:city":"Reutlingen",
    "sg:phone":"+49 7121/330542",
    "sg:postcode":"72764",
    "sg:province":"Baden-W\u00fcrttemberg",
    "wof:name":"Sonnenschirm Sportbedarf Gro\u00df- Und Einzelhandels Gmbh",
    "wof:placetype":"venue"
},
  "geometry": {"coordinates":[9.2137546539,48.4921913147],"type":"Point"}
}