{
  "type": "Feature",
  "properties": {
    "iso:country":"DE",
    "sg:address":"Im Grassenberg",
    "sg:city":"Wiesloch",
    "sg:phone":"+49 6222/51793",
    "sg:postcode":"69168",
    "sg:province":"Baden-W\u00fcrttemberg",
    "wof:name":"G\u00fcnther Werner",
    "wof:placetype":"venue"
},
  "geometry": {"coordinates":[8.7011451721,49.2844161987],"type":"Point"}
}