{
  "type": "Feature",
  "properties": {
    "iso:country":"DE",
    "sg:address":"Kirschgartenstr. 66",
    "sg:city":"N\u00fcrnberg",
    "sg:phone":"+49 911/333862",
    "sg:postcode":"90419",
    "sg:province":"Bayern",
    "wof:name":"G. Kolasinski Elektroinstallation",
    "wof:placetype":"venue"
},
  "geometry": {"coordinates":[11.055568,49.462524],"type":"Point"}
}