{
  "type": "Feature",
  "properties": {
    "iso:country":"DE",
    "sg:address":"Schafhofstr. 30",
    "sg:city":"N\u00fcrnberg",
    "sg:phone":"+49 911/95225",
    "sg:postcode":"90411",
    "sg:province":"Bayern",
    "wof:name":"Inter Control Thermostat Gmbh",
    "wof:placetype":"venue"
},
  "geometry": {"coordinates":[11.1176767349,49.4789619446],"type":"Point"}
}