{
  "type": "Feature",
  "properties": {
    "iso:country":"DE",
    "sg:address":"Kurt-Schumacher-Str. 19",
    "sg:city":"Erlensee",
    "sg:phone":"+49 6183/5680",
    "sg:postcode":"63526",
    "sg:province":"Hessen",
    "wof:name":"Margot Walocha-lill Architektin",
    "wof:placetype":"venue"
},
  "geometry": {"coordinates":[8.991351,50.16885],"type":"Point"}
}