{
  "type": "Feature",
  "properties": {
    "iso:country":"DE",
    "sg:address":"Hauptstr. 52",
    "sg:city":"Offenburg",
    "sg:phone":"+49 781/24275",
    "sg:postcode":"77652",
    "sg:province":"Baden-W\u00fcrttemberg",
    "wof:name":"Hotel Rheinischer Hof",
    "wof:placetype":"venue"
},
  "geometry": {"coordinates":[7.9432611465,48.4723777771],"type":"Point"}
}