{
  "type": "Feature",
  "properties": {
    "iso:country":"DE",
    "sg:address":"Oeslauer Str. 35 POSTFACH 1144",
    "sg:city":"R\u00f6dental",
    "sg:phone":"+49 9563/7240",
    "sg:postcode":"96466",
    "sg:province":"Bayern",
    "wof:name":"Saint-gobainindustriekeramikr\u00d6dental Gmbh",
    "wof:placetype":"venue"
},
  "geometry": {"coordinates":[11.041842,50.292156],"type":"Point"}
}