{
  "type": "Feature",
  "properties": {
    "iso:country":"DE",
    "sg:address":"Albiger Str. 3",
    "sg:city":"Alzey",
    "sg:postcode":"55232",
    "sg:province":"Rheinland-Pfalz",
    "wof:name":"Geska Bettenwarenfabrik Gmbh & Co. Kg",
    "wof:placetype":"venue"
},
  "geometry": {"coordinates":[8.118363,49.751232],"type":"Point"}
}