{
  "type": "Feature",
  "properties": {
    "iso:country":"DE",
    "sg:address":"Friemarer Str. 40",
    "sg:city":"Gotha",
    "sg:phone":"+49 4936/2121990",
    "sg:postcode":"99867",
    "sg:province":"Th\u00fcringen",
    "wof:name":"Aalflex Gotha Gmbh",
    "wof:placetype":"venue"
},
  "geometry": {"coordinates":[10.721502,50.955814],"type":"Point"}
}