{
  "type": "Feature",
  "properties": {
    "iso:country":"DE",
    "sg:address":"Passauer Str. 102",
    "sg:city":"Pfarrkirchen",
    "sg:phone":"+49 8561/912771",
    "sg:postcode":"84347",
    "sg:province":"Bayern",
    "wof:name":"Holzscheidl",
    "wof:placetype":"venue"
},
  "geometry": {"coordinates":[12.9525699615,48.4322814941],"type":"Point"}
}