{
  "type": "Feature",
  "properties": {
    "iso:country":"DE",
    "sg:address":"M\u00fchlenstr. 60",
    "sg:city":"Pinneberg",
    "sg:phone":"+49 4101/50050",
    "sg:postcode":"25421",
    "sg:province":"Schleswig-Holstein",
    "wof:name":"Hirz Wohnungsbau Gmbh",
    "wof:placetype":"venue"
},
  "geometry": {"coordinates":[9.7803640366,53.6576385498],"type":"Point"}
}