{
  "type": "Feature",
  "properties": {
    "iso:country":"DE",
    "sg:address":"Washingtonallee 96",
    "sg:city":"Hamburg",
    "sg:phone":"+49 40/7327726",
    "sg:postcode":"22111",
    "sg:province":"Hamburg",
    "wof:name":"Horner Pub",
    "wof:placetype":"venue"
},
  "geometry": {"coordinates":[10.093129158,53.5456886292],"type":"Point"}
}