{
  "type": "Feature",
  "properties": {
    "iso:country":"DE",
    "sg:address":"Wilhelmsh\u00f6he 11",
    "sg:city":"Solingen",
    "sg:phone":"+49 212/203464",
    "sg:postcode":"42655",
    "sg:province":"Nordrhein-Westfalen",
    "wof:name":"Bergische Lackfabrik Gottschalk Gmbh & Co",
    "wof:placetype":"venue"
},
  "geometry": {"coordinates":[7.073875,51.173592],"type":"Point"}
}