{
  "type": "Feature",
  "properties": {
    "iso:country":"DE",
    "sg:address":"Bohlenweg 27",
    "sg:city":"Paderborn",
    "sg:phone":"+49 5254/68012",
    "sg:postcode":"33106",
    "sg:province":"Nordrhein-Westfalen",
    "wof:name":"B\u00fcrgerhaus",
    "wof:placetype":"venue"
},
  "geometry": {"coordinates":[8.6887769699,51.7372894287],"type":"Point"}
}