{
  "type": "Feature",
  "properties": {
    "iso:country":"DE",
    "sg:address":"Lembergstr. 8",
    "sg:city":"Stuttgart",
    "sg:postcode":"70188",
    "sg:province":"Baden-W\u00fcrttemberg",
    "wof:name":"Mmg Decor Gmbh",
    "wof:placetype":"venue"
},
  "geometry": {"coordinates":[9.20179,48.781509],"type":"Point"}
}