{
  "type": "Feature",
  "properties": {
    "iso:country":"DE",
    "sg:address":"Karl-Liebknecht-Str. 14",
    "sg:city":"Eislingen",
    "sg:phone":"+49 7161/816133",
    "sg:postcode":"73054",
    "sg:province":"Baden-W\u00fcrttemberg",
    "wof:name":"Erich Holzapfel",
    "wof:placetype":"venue"
},
  "geometry": {"coordinates":[9.722744,48.691311],"type":"Point"}
}