{
  "type": "Feature",
  "properties": {
    "iso:country":"DE",
    "sg:address":"Buschkrugallee 9",
    "sg:city":"Berlin",
    "sg:phone":"+49 30/6848966",
    "sg:postcode":"12359",
    "sg:province":"Berlin",
    "wof:name":"Manfred Bartz",
    "wof:placetype":"venue"
},
  "geometry": {"coordinates":[13.4448652267,52.4632301331],"type":"Point"}
}