{
  "type": "Feature",
  "properties": {
    "iso:country":"DE",
    "sg:address":"Marienstr. 57",
    "sg:city":"Eisenach",
    "sg:phone":"+49 3691/784513",
    "sg:postcode":"99817",
    "sg:province":"Th\u00fcringen",
    "wof:name":"Frischmen\u00dc Erfurt Gmbh",
    "wof:placetype":"venue"
},
  "geometry": {"coordinates":[10.322252,50.968346],"type":"Point"}
}