{
  "type": "Feature",
  "properties": {
    "iso:country":"DE",
    "sg:address":"Friedrich-Fr\u00f6bel-Str. 67",
    "sg:city":"Rudolstadt",
    "sg:phone":"+49 3672/344444",
    "sg:postcode":"07407",
    "sg:province":"Th\u00fcringen",
    "wof:name":"Lothar Krause Omnibusbetrieb",
    "wof:placetype":"venue"
},
  "geometry": {"coordinates":[11.323322,50.694584],"type":"Point"}
}