{
  "type": "Feature",
  "properties": {
    "iso:country":"DE",
    "sg:address":"Haitzinger",
    "sg:city":"Passau",
    "sg:postcode":"94032",
    "sg:province":"Bayern",
    "wof:name":"Cisg, Wiener Un-kaufrecht, Cvim",
    "wof:placetype":"venue"
},
  "geometry": {"coordinates":[13.438415,48.572762],"type":"Point"}
}