{
  "type": "Feature",
  "properties": {
    "iso:country":"DE",
    "sg:address":"Unterstr. 6",
    "sg:city":"H\u00fcnfelden",
    "sg:phone":"+49 6431/42352",
    "sg:postcode":"65597",
    "sg:province":"Hessen",
    "wof:name":"Ev. Pfarramt Mensfelden",
    "wof:placetype":"venue"
},
  "geometry": {"coordinates":[8.107052803,50.3416557312],"type":"Point"}
}