{
  "type": "Feature",
  "properties": {
    "iso:country":"DE",
    "sg:address":"Emil-Sauer-Str. 13",
    "sg:city":"Neuhof",
    "sg:phone":"+49 6655/71344",
    "sg:postcode":"36119",
    "sg:province":"Hessen",
    "wof:name":"Marion Demmer",
    "wof:placetype":"venue"
},
  "geometry": {"coordinates":[9.613316,50.459858],"type":"Point"}
}