{
  "type": "Feature",
  "properties": {
    "iso:country":"DE",
    "sg:address":"Salzkottener Str. 56",
    "sg:city":"Paderborn",
    "sg:phone":"+49 5251/25598",
    "sg:postcode":"33106",
    "sg:province":"Nordrhein-Westfalen",
    "wof:name":"Margarete Kafsack Antiquit\u00e4ten",
    "wof:placetype":"venue"
},
  "geometry": {"coordinates":[8.684384346,51.6972579956],"type":"Point"}
}