{
  "type": "Feature",
  "properties": {
    "iso:country":"DE",
    "sg:address":"Lettestr. 3a",
    "sg:city":"Plauen",
    "sg:phone":"+49 3741/440663",
    "sg:postcode":"08527",
    "sg:province":"Sachsen",
    "wof:name":"Wolfgang Wietzel",
    "wof:placetype":"venue"
},
  "geometry": {"coordinates":[12.145778656,50.4894218445],"type":"Point"}
}