{
  "type": "Feature",
  "properties": {
    "iso:country":"DE",
    "sg:address":"Bonner Str. 12",
    "sg:city":"K\u00f6ln",
    "sg:phone":"+49 221/3318215",
    "sg:postcode":"50677",
    "sg:province":"Nordrhein-Westfalen",
    "wof:name":"D\u00fcsterwald",
    "wof:placetype":"venue"
},
  "geometry": {"coordinates":[6.959634,50.920296],"type":"Point"}
}