{
  "type": "Feature",
  "properties": {
    "iso:country":"DE",
    "sg:address":"Bonner Str. 4",
    "sg:city":"Berlin",
    "sg:postcode":"14197",
    "sg:province":"Berlin",
    "wof:name":"Zwei Rcw Gesellschaft F\u00fcr Die Verwertung Von Patentrechten",
    "wof:placetype":"venue"
},
  "geometry": {"coordinates":[13.3136816025,52.4684410095],"type":"Point"}
}