{
  "type": "Feature",
  "properties": {
    "iso:country":"DE",
    "sg:address":"Hauptstr. 15",
    "sg:city":"St. Blasien",
    "sg:phone":"+49 7675/225",
    "sg:postcode":"79837",
    "sg:province":"Baden-W\u00fcrttemberg",
    "wof:name":"Cafe Ell Ohg Inh. E. Cl. Und Martin Huber",
    "wof:placetype":"venue"
},
  "geometry": {"coordinates":[8.130198,47.761002],"type":"Point"}
}