{
  "type": "Feature",
  "properties": {
    "iso:country":"DE",
    "sg:address":"Lange Str. 58 a",
    "sg:city":"Loitz",
    "sg:phone":"+49 39998/10286",
    "sg:postcode":"17121",
    "sg:province":"Mecklenburg-Vorpommern",
    "wof:name":"J\u00fcrgen Heiser",
    "wof:placetype":"venue"
},
  "geometry": {"coordinates":[13.126662,53.968632],"type":"Point"}
}