{
  "type": "Feature",
  "properties": {
    "iso:country":"DE",
    "sg:address":"Au",
    "sg:city":"Kirchdorf",
    "sg:phone":"+49 8571/2936",
    "sg:postcode":"84375",
    "sg:province":"Bayern",
    "wof:name":"H. Dubowy Baumschule",
    "wof:placetype":"venue"
},
  "geometry": {"coordinates":[12.968914,48.231949],"type":"Point"}
}