{
  "type": "Feature",
  "properties": {
    "iso:country":"DE",
    "sg:address":"Karlstr. 51",
    "sg:city":"Karlsruhe",
    "sg:phone":"+49 721/28189",
    "sg:postcode":"76133",
    "sg:province":"Baden-W\u00fcrttemberg",
    "wof:name":"Wolfgang Weis Heilpraktiker",
    "wof:placetype":"venue"
},
  "geometry": {"coordinates":[8.394777298,49.0041847229],"type":"Point"}
}