{
  "type": "Feature",
  "properties": {
    "iso:country":"DE",
    "sg:address":"Fliederweg 11",
    "sg:city":"Werlte",
    "sg:phone":"+49 5951/4100",
    "sg:postcode":"49757",
    "sg:province":"Niedersachsen",
    "wof:name":"T. Hansen",
    "wof:placetype":"venue"
},
  "geometry": {"coordinates":[7.689933,52.85957],"type":"Point"}
}