{
  "type": "Feature",
  "properties": {
    "iso:country":"DE",
    "sg:address":"Weiherplatz 4",
    "sg:city":"Kusel",
    "sg:phone":"+49 6381/3023",
    "sg:postcode":"66869",
    "sg:province":"Rheinland-Pfalz",
    "wof:name":"Pizza Heimservice Cusumano",
    "wof:placetype":"venue"
},
  "geometry": {"coordinates":[7.400083,49.536568],"type":"Point"}
}