{
  "type": "Feature",
  "properties": {
    "iso:country":"DE",
    "sg:address":"Industriestr. 4",
    "sg:city":"Monheim",
    "sg:phone":"+49 9091/5932",
    "sg:postcode":"86653",
    "sg:province":"Bayern",
    "wof:name":"Josef Pfefferer Transport Kg",
    "wof:placetype":"venue"
},
  "geometry": {"coordinates":[10.8523454666,48.8429031372],"type":"Point"}
}