{
  "type": "Feature",
  "properties": {
    "iso:country":"DE",
    "sg:address":"Bahnhofstr. 4 e",
    "sg:city":"Haar",
    "sg:phone":"+49 89/4605500",
    "sg:postcode":"85540",
    "sg:province":"Bayern",
    "wof:name":"Doris Hellwig",
    "wof:placetype":"venue"
},
  "geometry": {"coordinates":[11.728955,48.110554],"type":"Point"}
}