{
  "type": "Feature",
  "properties": {
    "iso:country":"DE",
    "sg:address":"Sch\u00fctzenstr. 3 a",
    "sg:city":"Meersburg",
    "sg:phone":"+49 7532/1001",
    "sg:postcode":"88709",
    "sg:province":"Baden-W\u00fcrttemberg",
    "wof:name":"Pension Haus Diana",
    "wof:placetype":"venue"
},
  "geometry": {"coordinates":[9.2697286606,47.6967048645],"type":"Point"}
}