{
  "type": "Feature",
  "properties": {
    "iso:country":"DE",
    "sg:address":"Tempelhofer Damm 177",
    "sg:city":"Berlin",
    "sg:phone":"+49 30/7519035",
    "sg:postcode":"12099",
    "sg:province":"Berlin",
    "wof:name":"Photo Zentrum",
    "wof:placetype":"venue"
},
  "geometry": {"coordinates":[13.3852186203,52.4611968994],"type":"Point"}
}