{
  "type": "Feature",
  "properties": {
    "iso:country":"DE",
    "sg:address":"Bergstr. 13",
    "sg:city":"Schm\u00f6lln",
    "sg:postcode":"04626",
    "sg:province":"Th\u00fcringen",
    "wof:name":"Idl Zimmerei & Holzbau Beteiligungsgesellschaft Mbh",
    "wof:placetype":"venue"
},
  "geometry": {"coordinates":[12.348909,50.897083],"type":"Point"}
}