{
  "type": "Feature",
  "properties": {
    "iso:country":"DE",
    "sg:address":"Bahnhofsstra\u00dfe",
    "sg:city":"Raisting",
    "sg:postcode":"82399",
    "sg:province":"Bayern",
    "wof:name":"Blaskapelle Raisting",
    "wof:placetype":"venue"
},
  "geometry": {"coordinates":[11.109205,47.914089],"type":"Point"}
}