{
  "type": "Feature",
  "properties": {
    "iso:country":"DE",
    "sg:address":"Gladiolenweg 95",
    "sg:city":"Niederkassel",
    "sg:phone":"+49 2208/910461",
    "sg:postcode":"53859",
    "sg:province":"Nordrhein-Westfalen",
    "wof:name":"Odin-systeme",
    "wof:placetype":"venue"
},
  "geometry": {"coordinates":[7.0435872078,50.8129425049],"type":"Point"}
}