{
  "type": "Feature",
  "properties": {
    "iso:country":"DE",
    "sg:address":"Carl-Diem-Weg 26",
    "sg:city":"Einbeck",
    "sg:phone":"+49 5561/74138",
    "sg:postcode":"37574",
    "sg:province":"Niedersachsen",
    "wof:name":"Biotec Medizintechnik Inh. R. Hoffmann-nitschke E.k.",
    "wof:placetype":"venue"
},
  "geometry": {"coordinates":[9.859582,51.830254],"type":"Point"}
}