{
  "type": "Feature",
  "properties": {
    "iso:country":"DE",
    "sg:address":"Atzendorfer Str. 2",
    "sg:city":"Sta\u00dffurt",
    "sg:postcode":"39418",
    "sg:province":"Sachsen-Anhalt",
    "wof:name":"Litfa\u00df",
    "wof:placetype":"venue"
},
  "geometry": {"coordinates":[11.5875597,51.8568000793],"type":"Point"}
}