{
  "type": "Feature",
  "properties": {
    "iso:country":"DE",
    "sg:address":"Saarbr\u00fccker Str. 45",
    "sg:city":"Heusweiler",
    "sg:phone":"+49 6806/79181",
    "sg:postcode":"66265",
    "sg:province":"Saarland",
    "wof:name":"B. Schmidt",
    "wof:placetype":"venue"
},
  "geometry": {"coordinates":[7.0195569992,49.3560905457],"type":"Point"}
}