{
  "type": "Feature",
  "properties": {
    "iso:country":"DE",
    "sg:address":"Zugspitzstr. 28",
    "sg:city":"Brunnthal",
    "sg:postcode":"85649",
    "sg:province":"Bayern",
    "wof:name":"Muk Immobilien + Finanz Gmbh",
    "wof:placetype":"venue"
},
  "geometry": {"coordinates":[11.680362,48.002769],"type":"Point"}
}