{
  "type": "Feature",
  "properties": {
    "iso:country":"DE",
    "sg:address":"Hubertusallee 40",
    "sg:city":"Berlin",
    "sg:phone":"+49 30/8919775",
    "sg:postcode":"14193",
    "sg:province":"Berlin",
    "wof:name":"Wilfried Jensch Architekt",
    "wof:placetype":"venue"
},
  "geometry": {"coordinates":[13.284762,52.488213],"type":"Point"}
}