{
  "type": "Feature",
  "properties": {
    "iso:country":"DE",
    "sg:address":"Friedrich-Mezer-Str. 28",
    "sg:city":"Engen",
    "sg:phone":"+49 4977/337083",
    "sg:postcode":"78234",
    "sg:province":"Baden-W\u00fcrttemberg",
    "wof:name":"Fixtest Pr\u00dcfmittelbau Gmbh",
    "wof:placetype":"venue"
},
  "geometry": {"coordinates":[8.7845592499,47.856590271],"type":"Point"}
}