{
  "type": "Feature",
  "properties": {
    "iso:country":"DE",
    "sg:address":"Leopoldstr. 32",
    "sg:city":"Hagen",
    "sg:phone":"+49 2331/339955",
    "sg:postcode":"58089",
    "sg:province":"Nordrhein-Westfalen",
    "wof:name":"Vzd Volker Zeibig Dental Gmbh",
    "wof:placetype":"venue"
},
  "geometry": {"coordinates":[7.4491090775,51.3602828979],"type":"Point"}
}