{
  "type": "Feature",
  "properties": {
    "iso:country":"DE",
    "sg:address":"Markt 10",
    "sg:city":"Taucha",
    "sg:phone":"+49 34298/4030",
    "sg:postcode":"04425",
    "sg:province":"Sachsen",
    "wof:name":"Ekt Elektroanlagen Und Kabeltiefbau Gmbh",
    "wof:placetype":"venue"
},
  "geometry": {"coordinates":[12.5021152496,51.3798942566],"type":"Point"}
}