{
  "type": "Feature",
  "properties": {
    "iso:country":"DE",
    "sg:address":"Paniersplatz 2",
    "sg:city":"N\u00fcrnberg",
    "sg:phone":"+49 911/222782",
    "sg:postcode":"90403",
    "sg:province":"Bayern",
    "wof:name":"Probau Handelsvertretungsges. Mbh",
    "wof:placetype":"venue"
},
  "geometry": {"coordinates":[11.0797843933,49.4577445984],"type":"Point"}
}