{
  "type": "Feature",
  "properties": {
    "iso:country":"DE",
    "sg:address":"In den Fischermatten 3",
    "sg:city":"Emmendingen",
    "sg:phone":"+49 7641/91000",
    "sg:postcode":"79312",
    "sg:province":"Baden-W\u00fcrttemberg",
    "wof:name":"Hans-peter Markstein Ingenieur",
    "wof:placetype":"venue"
},
  "geometry": {"coordinates":[7.8467960358,48.1154136658],"type":"Point"}
}