{
  "type": "Feature",
  "properties": {
    "iso:country":"DE",
    "sg:address":"Feistkornstr. 33",
    "sg:city":"K\u00f6lleda",
    "sg:postcode":"99625",
    "sg:province":"Th\u00fcringen",
    "wof:name":"H\u00f6r-riese Gmbh",
    "wof:placetype":"venue"
},
  "geometry": {"coordinates":[11.239422,51.18248],"type":"Point"}
}