{
  "type": "Feature",
  "properties": {
    "iso:country":"DE",
    "sg:address":"Kasteienstr. 4",
    "sg:city":"Essen",
    "sg:phone":"+49 201/225320",
    "sg:postcode":"45127",
    "sg:province":"Nordrhein-Westfalen",
    "wof:name":"Beratungsstelle Der Verbraucherzentrale",
    "wof:placetype":"venue"
},
  "geometry": {"coordinates":[7.0124311447,51.45885849],"type":"Point"}
}