{
  "type": "Feature",
  "properties": {
    "iso:country":"DE",
    "sg:address":"Rhinstr. 127",
    "sg:city":"Berlin",
    "sg:phone":"+49 30/5413041",
    "sg:postcode":"10315",
    "sg:province":"Berlin",
    "wof:name":"Aga Bauservice Sp.z.o.o. Zwndl. Berlin",
    "wof:placetype":"venue"
},
  "geometry": {"coordinates":[13.5172233582,52.5298423767],"type":"Point"}
}