{
  "type": "Feature",
  "properties": {
    "iso:country":"DE",
    "sg:address":"Glabbach 17",
    "sg:city":"Nettetal",
    "sg:phone":"+49 2158/2293",
    "sg:postcode":"41334",
    "sg:province":"Nordrhein-Westfalen",
    "wof:name":"J. Hommes",
    "wof:placetype":"venue"
},
  "geometry": {"coordinates":[6.300136,51.347828],"type":"Point"}
}