{
  "type": "Feature",
  "properties": {
    "iso:country":"DE",
    "sg:address":"Johannisstr. 2",
    "sg:city":"L\u00f6bau",
    "sg:phone":"+49 3585/490140",
    "sg:postcode":"02708",
    "sg:province":"Sachsen",
    "wof:name":"Wgo Wohnungsgenossenschaft In Der Oberlausitz Eg",
    "wof:placetype":"venue"
},
  "geometry": {"coordinates":[14.667552948,51.0950546265],"type":"Point"}
}