{
  "type": "Feature",
  "properties": {
    "iso:country":"DE",
    "sg:address":"Luisenstr. 13",
    "sg:city":"Eschwege",
    "sg:postcode":"37269",
    "sg:province":"Hessen",
    "wof:name":"E-nature Online",
    "wof:placetype":"venue"
},
  "geometry": {"coordinates":[10.053572,51.183399],"type":"Point"}
}