{
  "type": "Feature",
  "properties": {
    "iso:country":"DE",
    "sg:address":"Kirchheimer Str. 176",
    "sg:city":"Dettingen",
    "sg:phone":"+49 7021/94180",
    "sg:postcode":"73265",
    "sg:province":"Baden-W\u00fcrttemberg",
    "wof:name":"Ehninger Beteiligungs Gmbh",
    "wof:placetype":"venue"
},
  "geometry": {"coordinates":[9.454206,48.625599],"type":"Point"}
}