{
  "type": "Feature",
  "properties": {
    "iso:country":"DE",
    "sg:address":"Westerstr. 13",
    "sg:city":"Harrislee",
    "sg:phone":"+49 461/72739",
    "sg:postcode":"24955",
    "sg:province":"Schleswig-Holstein",
    "wof:name":"Karl Aulich",
    "wof:placetype":"venue"
},
  "geometry": {"coordinates":[9.3817615509,54.8039932251],"type":"Point"}
}