{
  "type": "Feature",
  "properties": {
    "iso:country":"DE",
    "sg:address":"Unterstr. 20",
    "sg:city":"Gleichen",
    "sg:phone":"+49 5592/1418",
    "sg:postcode":"37130",
    "sg:province":"Niedersachsen",
    "wof:name":"Gerh. Pfl\u00fcger Architekt",
    "wof:placetype":"venue"
},
  "geometry": {"coordinates":[10.0418615341,51.4472885132],"type":"Point"}
}