{
  "type": "Feature",
  "properties": {
    "iso:country":"DE",
    "sg:address":"Mittelstr. 19",
    "sg:city":"Halver",
    "sg:phone":"+49 2353/3939",
    "sg:postcode":"58553",
    "sg:province":"Nordrhein-Westfalen",
    "wof:name":"Brandt-reisen-touristik Inh. Rainer Brandt",
    "wof:placetype":"venue"
},
  "geometry": {"coordinates":[7.5030550957,51.1887321472],"type":"Point"}
}