{
  "type": "Feature",
  "properties": {
    "iso:country":"DE",
    "sg:address":"Dr.-Kurt-Schumacher-Str. 36",
    "sg:city":"Stockstadt",
    "sg:phone":"+49 6158/85323",
    "sg:postcode":"64589",
    "sg:province":"Hessen",
    "wof:name":"Josef Gantner",
    "wof:placetype":"venue"
},
  "geometry": {"coordinates":[8.4640979767,49.8056411743],"type":"Point"}
}