{
  "type": "Feature",
  "properties": {
    "iso:country":"DE",
    "sg:address":"Leonberger Str. 37",
    "sg:city":"Rutesheim",
    "sg:phone":"+49 7152/53863",
    "sg:postcode":"71277",
    "sg:province":"Baden-W\u00fcrttemberg",
    "wof:name":"Epple Gmbh",
    "wof:placetype":"venue"
},
  "geometry": {"coordinates":[8.9502096176,48.8074378967],"type":"Point"}
}