{
  "type": "Feature",
  "properties": {
    "iso:country":"DE",
    "sg:address":"Dausfelder H\u00f6he 1",
    "sg:city":"Pr\u00fcm",
    "sg:phone":"+49 6551/2551",
    "sg:postcode":"54595",
    "sg:province":"Rheinland-Pfalz",
    "wof:name":"A. Gausch Gmbh",
    "wof:placetype":"venue"
},
  "geometry": {"coordinates":[6.4422450066,50.2146148682],"type":"Point"}
}