{
  "type": "Feature",
  "properties": {
    "iso:country":"DE",
    "sg:address":"Lange Str. 4",
    "sg:city":"Dannenberg",
    "sg:phone":"+49 5861/4644",
    "sg:postcode":"29451",
    "sg:province":"Niedersachsen",
    "wof:name":"Tiede Gmbh",
    "wof:placetype":"venue"
},
  "geometry": {"coordinates":[11.0903453827,53.0966796875],"type":"Point"}
}