{
  "type": "Feature",
  "properties": {
    "iso:country":"DE",
    "sg:address":"Fl\u00f6haer Str. 4",
    "sg:city":"Leipzig",
    "sg:phone":"+49 341/9211351",
    "sg:postcode":"04349",
    "sg:province":"Sachsen",
    "wof:name":"E. Czesowski",
    "wof:placetype":"venue"
},
  "geometry": {"coordinates":[12.431487,51.375763],"type":"Point"}
}