{
  "type": "Feature",
  "properties": {
    "iso:country":"DE",
    "sg:address":"Hauptstr. 86",
    "sg:city":"B\u00fchl",
    "sg:phone":"+49 7223/943599",
    "sg:postcode":"77815",
    "sg:province":"Baden-W\u00fcrttemberg",
    "wof:name":"Ams Anlagen Management Service Ag",
    "wof:placetype":"venue"
},
  "geometry": {"coordinates":[8.1374263763,48.6974945068],"type":"Point"}
}