{
  "type": "Feature",
  "properties": {
    "iso:country":"DE",
    "sg:address":"Am Rosengarten 57",
    "sg:city":"Halle",
    "sg:phone":"+49 345/7758181",
    "sg:postcode":"06132",
    "sg:province":"Sachsen-Anhalt",
    "wof:name":"Eberhard Giebel",
    "wof:placetype":"venue"
},
  "geometry": {"coordinates":[11.9775457382,51.4387207031],"type":"Point"}
}