{
  "type": "Feature",
  "properties": {
    "iso:country":"DE",
    "sg:address":"Liebigstr. 9",
    "sg:city":"Weimar",
    "sg:phone":"+49 6421/7215",
    "sg:postcode":"35096",
    "sg:province":"Hessen",
    "wof:name":"Heinrich Grimmelbein Masseur",
    "wof:placetype":"venue"
},
  "geometry": {"coordinates":[8.73537,50.759922],"type":"Point"}
}