{
  "type": "Feature",
  "properties": {
    "iso:country":"DE",
    "sg:address":"Kamenzer Str. 10",
    "sg:city":"Mannheim",
    "sg:phone":"+49 621/716890",
    "sg:postcode":"68309",
    "sg:province":"Baden-W\u00fcrttemberg",
    "wof:name":"Eisele & Zimmermann Gmbh",
    "wof:placetype":"venue"
},
  "geometry": {"coordinates":[8.547931,49.515663],"type":"Point"}
}