{
  "type": "Feature",
  "properties": {
    "iso:country":"DE",
    "sg:address":"Gropiusstr 3",
    "sg:city":"Oranienbaum",
    "sg:phone":"+49 34904/21858",
    "sg:postcode":"06785",
    "sg:province":"Sachsen-Anhalt",
    "wof:name":"Schwartz W\u00e4rmebehandlungs- Anlagen Gmbh",
    "wof:placetype":"venue"
},
  "geometry": {"coordinates":[12.3452949524,51.8109283447],"type":"Point"}
}