{
  "type": "Feature",
  "properties": {
    "iso:country":"DE",
    "sg:address":"Rosenweg 1",
    "sg:city":"Unterthingau",
    "sg:phone":"+49 8377/205",
    "sg:postcode":"87647",
    "sg:province":"Bayern",
    "wof:name":"Elektrotechnik Hartwig Totzauer Gmbh",
    "wof:placetype":"venue"
},
  "geometry": {"coordinates":[10.506015,47.768654],"type":"Point"}
}