{
  "type": "Feature",
  "properties": {
    "iso:country":"DE",
    "sg:address":"Niekampsweg 2",
    "sg:city":"Uplengen",
    "sg:phone":"+49 4956/912829",
    "sg:postcode":"26670",
    "sg:province":"Niedersachsen",
    "wof:name":"Genius Bau Gmbh",
    "wof:placetype":"venue"
},
  "geometry": {"coordinates":[7.819489,53.297764],"type":"Point"}
}