{
  "type": "Feature",
  "properties": {
    "iso:country":"DE",
    "sg:address":"Sch\u00f6nwalder Str. 41",
    "sg:city":"Berlin",
    "sg:phone":"+49 30/3352270",
    "sg:postcode":"13585",
    "sg:province":"Berlin",
    "wof:name":"Karl Sange Maurer- Und Zimmermeister Gmbh & Co. Kg",
    "wof:placetype":"venue"
},
  "geometry": {"coordinates":[13.200528,52.55043],"type":"Point"}
}