{
  "type": "Feature",
  "properties": {
    "iso:country":"DE",
    "sg:address":"Bonner Str. 15",
    "sg:city":"Bornheim",
    "sg:phone":"+49 2222/648984",
    "sg:postcode":"53332",
    "sg:province":"Nordrhein-Westfalen",
    "wof:name":"Helmut H\u00f6velmann Gmbh",
    "wof:placetype":"venue"
},
  "geometry": {"coordinates":[7.0142908096,50.7528762817],"type":"Point"}
}