{
  "type": "Feature",
  "properties": {
    "iso:country":"DE",
    "sg:address":"Au\u00dfenliegend",
    "sg:city":"Rabenau",
    "sg:postcode":"35466",
    "sg:province":"Hessen",
    "wof:name":"Basaltwerk Londorf Gmbh",
    "wof:placetype":"venue"
},
  "geometry": {"coordinates":[8.9241485596,50.683391571],"type":"Point"}
}