{
  "type": "Feature",
  "properties": {
    "iso:country":"DE",
    "sg:address":"Brugg",
    "sg:city":"Gestratz",
    "sg:phone":"+49 8383/921266",
    "sg:postcode":"88167",
    "sg:province":"Bayern",
    "wof:name":"Gasthaus Post",
    "wof:placetype":"venue"
},
  "geometry": {"coordinates":[9.9841003418,47.6540145874],"type":"Point"}
}