{
  "type": "Feature",
  "properties": {
    "iso:country":"DE",
    "sg:address":"Hasestr. 20",
    "sg:city":"Menslage",
    "sg:phone":"+49 5437/701",
    "sg:postcode":"49637",
    "sg:province":"Niedersachsen",
    "wof:name":"Erich Moritz",
    "wof:placetype":"venue"
},
  "geometry": {"coordinates":[7.818341,52.672661],"type":"Point"}
}