{
  "type": "Feature",
  "properties": {
    "iso:country":"DE",
    "sg:address":"August-Bebel-Str. 6",
    "sg:city":"G\u00f6\u00dfnitz",
    "sg:phone":"+49 34493/21518",
    "sg:postcode":"04639",
    "sg:province":"Th\u00fcringen",
    "wof:name":"M. Schmidt",
    "wof:placetype":"venue"
},
  "geometry": {"coordinates":[12.431821,50.888973],"type":"Point"}
}