{
  "type": "Feature",
  "properties": {
    "iso:country":"DE",
    "sg:address":"Alte Salzstr. 189",
    "sg:city":"Leipzig",
    "sg:phone":"+49 341/4221881",
    "sg:postcode":"04207",
    "sg:province":"Sachsen",
    "wof:name":"Jutta Partschefeld",
    "wof:placetype":"venue"
},
  "geometry": {"coordinates":[12.276999,51.3139],"type":"Point"}
}