{
  "type": "Feature",
  "properties": {
    "iso:country":"DE",
    "sg:address":"Aspenweg 40",
    "sg:city":"Neustadt",
    "sg:phone":"+49 6321/84956",
    "sg:postcode":"67433",
    "sg:province":"Rheinland-Pfalz",
    "wof:name":"Rudolf Starck Steuerbevollm\u00e4chtigter",
    "wof:placetype":"venue"
},
  "geometry": {"coordinates":[8.1422605515,49.3603096008],"type":"Point"}
}