{
  "type": "Feature",
  "properties": {
    "iso:country":"DE",
    "sg:address":"M\u00fcnzenberger Str. 6",
    "sg:city":"Lich",
    "sg:phone":"+49 6004/2152",
    "sg:postcode":"35423",
    "sg:province":"Hessen",
    "wof:name":"G. Jaster",
    "wof:placetype":"venue"
},
  "geometry": {"coordinates":[8.761737,50.48093],"type":"Point"}
}