{
  "type": "Feature",
  "properties": {
    "iso:country":"DE",
    "sg:address":"Lerchenweg 25",
    "sg:city":"K\u00f6ln",
    "sg:phone":"+49 221/505051",
    "sg:postcode":"50829",
    "sg:province":"Nordrhein-Westfalen",
    "wof:name":"Alois Schliebs Architekt",
    "wof:placetype":"venue"
},
  "geometry": {"coordinates":[6.867149,50.973667],"type":"Point"}
}