{
  "type": "Feature",
  "properties": {
    "iso:country":"DE",
    "sg:address":"Einbecker Str. 1",
    "sg:city":"Moringen",
    "sg:phone":"+49 5554/2313",
    "sg:postcode":"37186",
    "sg:province":"Niedersachsen",
    "wof:name":"E. Bergmann Tankstelle",
    "wof:placetype":"venue"
},
  "geometry": {"coordinates":[9.8718414307,51.703086853],"type":"Point"}
}