{
  "type": "Feature",
  "properties": {
    "iso:country":"DE",
    "sg:address":"Rheinstr. 27",
    "sg:city":"H\u00f6hr-Grenzhausen",
    "sg:phone":"+49 2624/2416",
    "sg:postcode":"56203",
    "sg:province":"Rheinland-Pfalz",
    "wof:name":"Burggraf",
    "wof:placetype":"venue"
},
  "geometry": {"coordinates":[7.66967,50.432571],"type":"Point"}
}