{
  "type": "Feature",
  "properties": {
    "iso:country":"DE",
    "sg:address":"Sottrumer Str. 51",
    "sg:city":"Ree\u00dfum",
    "sg:phone":"+49 4264/455",
    "sg:postcode":"27367",
    "sg:province":"Niedersachsen",
    "wof:name":"Uwe Windeler",
    "wof:placetype":"venue"
},
  "geometry": {"coordinates":[9.21057,53.12775],"type":"Point"}
}