{
  "type": "Feature",
  "properties": {
    "iso:country":"DE",
    "sg:address":"Nordring 107",
    "sg:city":"G\u00fctersloh",
    "sg:phone":"+49 5241/14110",
    "sg:postcode":"33330",
    "sg:province":"Nordrhein-Westfalen",
    "wof:name":"Deutsche Bp Gmbh",
    "wof:placetype":"venue"
},
  "geometry": {"coordinates":[8.367026329,51.9128417969],"type":"Point"}
}