{
  "type": "Feature",
  "properties": {
    "iso:country":"DE",
    "sg:address":"Fischer-von-Erlach-Str. 56",
    "sg:city":"Halle",
    "sg:postcode":"06114",
    "sg:province":"Sachsen-Anhalt",
    "wof:name":"A. Kursa",
    "wof:placetype":"venue"
},
  "geometry": {"coordinates":[11.968812,51.502445],"type":"Point"}
}