{
  "type": "Feature",
  "properties": {
    "iso:country":"DE",
    "sg:address":"Hauptstr. 105",
    "sg:city":"Kirchworbis",
    "sg:phone":"+49 36074/93333",
    "sg:postcode":"37339",
    "sg:province":"Th\u00fcringen",
    "wof:name":"G. Weber",
    "wof:placetype":"venue"
},
  "geometry": {"coordinates":[10.401545,51.410591],"type":"Point"}
}