{
  "type": "Feature",
  "properties": {
    "iso:country":"DE",
    "sg:address":"Bahnhofstr. 38",
    "sg:city":"Zw\u00f6nitz",
    "sg:phone":"+49 37754/2939",
    "sg:postcode":"08297",
    "sg:province":"Sachsen",
    "wof:name":"Rosemarie Weigel Rechtsanw\u00e4ltin",
    "wof:placetype":"venue"
},
  "geometry": {"coordinates":[12.8067903519,50.6313285828],"type":"Point"}
}