{
  "type": "Feature",
  "properties": {
    "iso:country":"DE",
    "sg:address":"Alt Fermersleben 23",
    "sg:city":"Magdeburg",
    "sg:phone":"+49 391/4014377",
    "sg:postcode":"39122",
    "sg:province":"Sachsen-Anhalt",
    "wof:name":"Jens Langenstein",
    "wof:placetype":"venue"
},
  "geometry": {"coordinates":[11.655721,52.091915],"type":"Point"}
}