{
  "type": "Feature",
  "properties": {
    "iso:country":"DE",
    "sg:address":"Manfred-V-Ardenne-Str. 1",
    "sg:city":"K\u00f6lleda",
    "sg:phone":"+49 4936/3540600",
    "sg:postcode":"99625",
    "sg:province":"Th\u00fcringen",
    "wof:name":"Kr\u00c4uterm\u00dchle E. K.",
    "wof:placetype":"venue"
},
  "geometry": {"coordinates":[11.2493162155,51.18800354],"type":"Point"}
}