{
  "type": "Feature",
  "properties": {
    "iso:country":"DE",
    "sg:address":"Mittlere Ortsstr. 52",
    "sg:city":"R\u00fclzheim",
    "sg:phone":"+49 7272/8359",
    "sg:postcode":"76761",
    "sg:province":"Rheinland-Pfalz",
    "wof:name":"Modehaus Renate Kiekebusch",
    "wof:placetype":"venue"
},
  "geometry": {"coordinates":[8.293989,49.157391],"type":"Point"}
}