{
  "type": "Feature",
  "properties": {
    "iso:country":"DE",
    "sg:address":"Turnstr. 31",
    "sg:city":"Ispringen",
    "sg:postcode":"75228",
    "sg:province":"Baden-W\u00fcrttemberg",
    "wof:name":"Winkelstr\u00f6ter Verwaltungs Gmbh",
    "wof:placetype":"venue"
},
  "geometry": {"coordinates":[8.664278,48.913128],"type":"Point"}
}