{
  "type": "Feature",
  "properties": {
    "iso:country":"DE",
    "sg:address":"Riemenschneiderstr. 18",
    "sg:city":"N\u00fcrnberg",
    "sg:phone":"+49 911/3677250",
    "sg:postcode":"90408",
    "sg:province":"Bayern",
    "wof:name":"Pino-net.de",
    "wof:placetype":"venue"
},
  "geometry": {"coordinates":[11.074118,49.465618],"type":"Point"}
}