{
  "type": "Feature",
  "properties": {
    "iso:country":"DE",
    "sg:address":"M\u00fcnchner Str. 41",
    "sg:city":"Dachau",
    "sg:phone":"+49 8131/81076",
    "sg:postcode":"85221",
    "sg:province":"Bayern",
    "wof:name":"Piller Und Partner Rechtsanw\u00e4lte",
    "wof:placetype":"venue"
},
  "geometry": {"coordinates":[11.4406709671,48.2523612976],"type":"Point"}
}