{
  "type": "Feature",
  "properties": {
    "iso:country":"DE",
    "sg:address":"Neudammstr. 3",
    "sg:city":"Mannheim",
    "sg:phone":"+49 621/857878",
    "sg:postcode":"68199",
    "sg:province":"Baden-W\u00fcrttemberg",
    "wof:name":"B. Eckert-stahl",
    "wof:placetype":"venue"
},
  "geometry": {"coordinates":[8.4950838089,49.4492149353],"type":"Point"}
}