{
  "type": "Feature",
  "properties": {
    "iso:country":"DE",
    "sg:address":"Westring 32",
    "sg:city":"Neuenhagen",
    "sg:phone":"+49 3342/201637",
    "sg:postcode":"15366",
    "sg:province":"Brandenburg",
    "wof:name":"Hermann Gl\u00f6de",
    "wof:placetype":"venue"
},
  "geometry": {"coordinates":[13.6956377029,52.5151557922],"type":"Point"}
}