{
  "type": "Feature",
  "properties": {
    "iso:country":"DE",
    "sg:address":"Dietrichstr. 2",
    "sg:city":"M\u00fcnchen",
    "sg:phone":"+49 89/156664",
    "sg:postcode":"80637",
    "sg:province":"Bayern",
    "wof:name":"Dietrich Von Bern",
    "wof:placetype":"venue"
},
  "geometry": {"coordinates":[11.5329904556,48.1693305969],"type":"Point"}
}