{
  "type": "Feature",
  "properties": {
    "iso:country":"DE",
    "sg:address":"Hauptstr. 83",
    "sg:city":"Berlin",
    "sg:phone":"+49 30/85999260",
    "sg:postcode":"12159",
    "sg:province":"Berlin",
    "wof:name":"Pmm Shoes Consulting Martin Ohg",
    "wof:placetype":"venue"
},
  "geometry": {"coordinates":[13.337868,52.473305],"type":"Point"}
}