{
  "type": "Feature",
  "properties": {
    "iso:country":"DE",
    "sg:address":"Braunauer Str. 10",
    "sg:city":"Waldkraiburg",
    "sg:phone":"+49 8638/959316",
    "sg:postcode":"84478",
    "sg:province":"Bayern",
    "wof:name":"Stadtmuseum Waldkraiburg",
    "wof:placetype":"venue"
},
  "geometry": {"coordinates":[12.406066,48.208122],"type":"Point"}
}