{
  "type": "Feature",
  "properties": {
    "iso:country":"DE",
    "sg:address":"Kurf\u00fcrstenstr. 11",
    "sg:city":"Herford",
    "sg:phone":"+49 5221/15088",
    "sg:postcode":"32052",
    "sg:province":"Nordrhein-Westfalen",
    "wof:name":"Friedrich Ruhe Rechtsanwalt",
    "wof:placetype":"venue"
},
  "geometry": {"coordinates":[8.6666908264,52.1187896729],"type":"Point"}
}