{
  "type": "Feature",
  "properties": {
    "iso:country":"DE",
    "sg:address":"S\u00fcdstr. 23 - 27",
    "sg:city":"Gera",
    "sg:phone":"+49 365/7300710",
    "sg:postcode":"07548",
    "sg:province":"Th\u00fcringen",
    "wof:name":"Eet Elektro-energie-technik Gmbh",
    "wof:placetype":"venue"
},
  "geometry": {"coordinates":[12.0779008865,50.865322113],"type":"Point"}
}