{
  "type": "Feature",
  "properties": {
    "iso:country":"DE",
    "sg:address":"Am Hohlweg 30",
    "sg:city":"Winterhausen",
    "sg:phone":"+49 9333/202",
    "sg:postcode":"97286",
    "sg:province":"Bayern",
    "wof:name":"A. Fischer Immobilienmakler",
    "wof:placetype":"venue"
},
  "geometry": {"coordinates":[10.0105724335,49.7028312683],"type":"Point"}
}