{
  "type": "Feature",
  "properties": {
    "iso:country":"DE",
    "sg:address":"Corbacher Str. 8",
    "sg:city":"Hagen",
    "sg:phone":"+49 2331/41251",
    "sg:postcode":"58135",
    "sg:province":"Nordrhein-Westfalen",
    "wof:name":"Corbacher Sch\u00e4nke",
    "wof:placetype":"venue"
},
  "geometry": {"coordinates":[7.4251141548,51.3469390869],"type":"Point"}
}