{
  "type": "Feature",
  "properties": {
    "iso:country":"DE",
    "sg:address":"Diestedder Str. 4",
    "sg:city":"Wadersloh",
    "sg:phone":"+49 2523/92020",
    "sg:postcode":"59329",
    "sg:province":"Nordrhein-Westfalen",
    "wof:name":"St. Josef",
    "wof:placetype":"venue"
},
  "geometry": {"coordinates":[8.242876,51.735153],"type":"Point"}
}