{
  "type": "Feature",
  "properties": {
    "iso:country":"DE",
    "sg:address":"Kiefernweg 2",
    "sg:city":"Handewitt",
    "sg:phone":"+49 4608/1442",
    "sg:postcode":"24983",
    "sg:province":"Schleswig-Holstein",
    "wof:name":"Helga Brandt",
    "wof:placetype":"venue"
},
  "geometry": {"coordinates":[9.3055305481,54.7934074402],"type":"Point"}
}