{
  "type": "Feature",
  "properties": {
    "iso:country":"DE",
    "sg:address":"Eisenbahnweg 4",
    "sg:city":"Biessenhofen",
    "sg:phone":"+49 8341/3402",
    "sg:postcode":"87640",
    "sg:province":"Bayern",
    "wof:name":"Alte Post",
    "wof:placetype":"venue"
},
  "geometry": {"coordinates":[10.6409759521,47.8312950134],"type":"Point"}
}