{
  "type": "Feature",
  "properties": {
    "iso:country":"DE",
    "sg:address":"M\u00fchlenredder 35",
    "sg:city":"Hamburg",
    "sg:phone":"+49 40/6076680",
    "sg:postcode":"22397",
    "sg:province":"Hamburg",
    "wof:name":"Christian Str\u00f6h Beteiligungs Gmbh",
    "wof:placetype":"venue"
},
  "geometry": {"coordinates":[10.129716,53.709167],"type":"Point"}
}