{
  "type": "Feature",
  "properties": {
    "iso:country":"DE",
    "sg:address":"Industriestr 38",
    "sg:city":"Oyten",
    "sg:phone":"+49 4207/91110",
    "sg:postcode":"28876",
    "sg:province":"Niedersachsen",
    "wof:name":"Inteco Gmbh",
    "wof:placetype":"venue"
},
  "geometry": {"coordinates":[9.0355634689,53.057182312],"type":"Point"}
}