{
  "type": "Feature",
  "properties": {
    "iso:country":"DE",
    "sg:address":"Frankfurter Str. 35",
    "sg:city":"Breckerfeld",
    "sg:phone":"+49 2338/418",
    "sg:postcode":"58339",
    "sg:province":"Nordrhein-Westfalen",
    "wof:name":"K\u00e4ufer & Struwe Gmbh & Co. Kg",
    "wof:placetype":"venue"
},
  "geometry": {"coordinates":[7.4682741165,51.2584571838],"type":"Point"}
}