{
  "type": "Feature",
  "properties": {
    "iso:country":"DE",
    "sg:address":"In den Eichen 7",
    "sg:city":"Werlte",
    "sg:phone":"+49 5951/3583",
    "sg:postcode":"49757",
    "sg:province":"Niedersachsen",
    "wof:name":"Edith Schmidt",
    "wof:placetype":"venue"
},
  "geometry": {"coordinates":[7.661063,52.809685],"type":"Point"}
}