{
  "type": "Feature",
  "properties": {
    "iso:country":"DE",
    "sg:address":"Enge Gasse 9",
    "sg:city":"Erfurt",
    "sg:phone":"+49 361/7968412",
    "sg:postcode":"99094",
    "sg:province":"Th\u00fcringen",
    "wof:name":"S. Und Olaf Kalkkuhl",
    "wof:placetype":"venue"
},
  "geometry": {"coordinates":[10.9923591614,50.9221496582],"type":"Point"}
}