{
  "type": "Feature",
  "properties": {
    "iso:country":"DE",
    "sg:address":"Bonner Str. 43",
    "sg:city":"Bad Neuenahr-Ahrweiler",
    "sg:phone":"+49 2641/25321",
    "sg:postcode":"53474",
    "sg:province":"Rheinland-Pfalz",
    "wof:name":"Johannes Witsch",
    "wof:placetype":"venue"
},
  "geometry": {"coordinates":[7.166894,50.557667],"type":"Point"}
}