{
  "type": "Feature",
  "properties": {
    "iso:country":"DE",
    "sg:address":"Hauptstr. 10",
    "sg:city":"Bidingen",
    "sg:phone":"+49 8348/411",
    "sg:postcode":"87651",
    "sg:province":"Bayern",
    "wof:name":"Karl Fischer",
    "wof:placetype":"venue"
},
  "geometry": {"coordinates":[10.719108,47.796703],"type":"Point"}
}