{
  "type": "Feature",
  "properties": {
    "iso:country":"DE",
    "sg:address":"Zieblandstr. 14",
    "sg:city":"M\u00fcnchen",
    "sg:phone":"+49 89/529823",
    "sg:postcode":"80798",
    "sg:province":"Bayern",
    "wof:name":"Peter Ottovay Architekt",
    "wof:placetype":"venue"
},
  "geometry": {"coordinates":[11.5674,48.153713],"type":"Point"}
}