{
  "type": "Feature",
  "properties": {
    "iso:country":"DE",
    "sg:address":"Friedensstr. 28",
    "sg:city":"Langeneichst\u00e4dt",
    "sg:postcode":"06268",
    "sg:province":"Sachsen-Anhalt",
    "wof:name":"Interessantes \u00fcber Kirche, Gemeinschaft",
    "wof:placetype":"venue"
},
  "geometry": {"coordinates":[11.747117,51.345741],"type":"Point"}
}