{
  "type": "Feature",
  "properties": {
    "iso:country":"DE",
    "sg:address":"Impexstr. 17",
    "sg:city":"Walldorf",
    "sg:phone":"+49 6227/9182",
    "sg:postcode":"69190",
    "sg:province":"Baden-W\u00fcrttemberg",
    "wof:name":"Karl-heinz Ding",
    "wof:placetype":"venue"
},
  "geometry": {"coordinates":[8.6630926132,49.292552948],"type":"Point"}
}