{
  "type": "Feature",
  "properties": {
    "iso:country":"DE",
    "sg:address":"Weilertalstr. 9",
    "sg:city":"M\u00fcllheim",
    "sg:phone":"+49 7631/3518",
    "sg:postcode":"79379",
    "sg:province":"Baden-W\u00fcrttemberg",
    "wof:name":"G\u00e4stehaus Wolfgang Schmidt",
    "wof:placetype":"venue"
},
  "geometry": {"coordinates":[7.6495800018,47.8061904907],"type":"Point"}
}