{
  "type": "Feature",
  "properties": {
    "iso:country":"DE",
    "sg:address":"Eldinger Weg 7",
    "sg:city":"H\u00f6fer",
    "sg:phone":"+49 5145/6059",
    "sg:postcode":"29361",
    "sg:province":"Niedersachsen",
    "wof:name":"Reinhold Walter",
    "wof:placetype":"venue"
},
  "geometry": {"coordinates":[10.254399,52.676689],"type":"Point"}
}