{
  "type": "Feature",
  "properties": {
    "iso:country":"DE",
    "sg:address":"Waldstr. 18",
    "sg:city":"Ried",
    "sg:phone":"+49 8202/1276",
    "sg:postcode":"86510",
    "sg:province":"Bayern",
    "wof:name":"Rene K\u00fchnert",
    "wof:placetype":"venue"
},
  "geometry": {"coordinates":[11.0913448334,48.2775688171],"type":"Point"}
}