{
  "type": "Feature",
  "properties": {
    "iso:country":"DE",
    "sg:address":"Alter Deich 61",
    "sg:city":"Nordholz",
    "sg:phone":"+49 4741/1525",
    "sg:postcode":"27637",
    "sg:province":"Niedersachsen",
    "wof:name":"Peter Sielken",
    "wof:placetype":"venue"
},
  "geometry": {"coordinates":[8.568687,53.763393],"type":"Point"}
}