{
  "type": "Feature",
  "properties": {
    "iso:country":"DE",
    "sg:address":"Basler Str. 20",
    "sg:city":"Bad Krozingen",
    "sg:phone":"+49 7633/9088770",
    "sg:postcode":"79189",
    "sg:province":"Baden-W\u00fcrttemberg",
    "wof:name":"Redaktion Badische Zeitung",
    "wof:placetype":"venue"
},
  "geometry": {"coordinates":[7.6998229027,47.9157104492],"type":"Point"}
}