{
  "type": "Feature",
  "properties": {
    "iso:country":"DE",
    "sg:address":"Hauptstr. 58",
    "sg:city":"Obernfeld",
    "sg:phone":"+49 5527/1438",
    "sg:postcode":"37434",
    "sg:province":"Niedersachsen",
    "wof:name":"M\u00fche Ohg",
    "wof:placetype":"venue"
},
  "geometry": {"coordinates":[10.2340717316,51.5537490845],"type":"Point"}
}