{
  "type": "Feature",
  "properties": {
    "iso:country":"DE",
    "sg:address":"Alter M\u00fchlenweg 63",
    "sg:city":"Dortmund",
    "sg:phone":"+49 231",
    "sg:postcode":"44139",
    "sg:province":"Nordrhein-Westfalen",
    "wof:name":"Fischer Sch\u00f6ne B\u00e4der",
    "wof:placetype":"venue"
},
  "geometry": {"coordinates":[7.461488,51.502201],"type":"Point"}
}