{
  "type": "Feature",
  "properties": {
    "iso:country":"DE",
    "sg:address":"Dorfstr. 45",
    "sg:city":"Breitnau",
    "sg:phone":"+49 7652/5339",
    "sg:postcode":"79874",
    "sg:province":"Baden-W\u00fcrttemberg",
    "wof:name":"S. Und K.-h. Schmidle Masseure",
    "wof:placetype":"venue"
},
  "geometry": {"coordinates":[8.09433,47.939571],"type":"Point"}
}