{
  "type": "Feature",
  "properties": {
    "iso:country":"DE",
    "sg:address":"R\u00f6merberg 17",
    "sg:city":"Frankfurt",
    "sg:phone":"+49 69/287688",
    "sg:postcode":"60311",
    "sg:province":"Hessen",
    "wof:name":"R\u00f6mer-truhe",
    "wof:placetype":"venue"
},
  "geometry": {"coordinates":[8.681784,50.110214],"type":"Point"}
}