{
  "type": "Feature",
  "properties": {
    "iso:country":"DE",
    "sg:address":"M\u00fcnchner Str. 63",
    "sg:city":"Kirchseeon",
    "sg:phone":"+49 8091/9954",
    "sg:postcode":"85614",
    "sg:province":"Bayern",
    "wof:name":"Fritz Martl",
    "wof:placetype":"venue"
},
  "geometry": {"coordinates":[11.8844804764,48.0755386353],"type":"Point"}
}