{
  "type": "Feature",
  "properties": {
    "iso:country":"DE",
    "sg:address":"Borsigstr. 6",
    "sg:city":"N\u00fcrnberg",
    "sg:phone":"+49 911/4780370",
    "sg:postcode":"90478",
    "sg:province":"Bayern",
    "wof:name":"Fr\u00f6hlich & Ziegler Ohg",
    "wof:placetype":"venue"
},
  "geometry": {"coordinates":[11.105911,49.446499],"type":"Point"}
}