{
  "type": "Feature",
  "properties": {
    "iso:country":"DE",
    "sg:address":"Voerder Str. 52",
    "sg:city":"Hagen",
    "sg:phone":"+49 2331/41853",
    "sg:postcode":"58135",
    "sg:province":"Nordrhein-Westfalen",
    "wof:name":"Altes Pfingsten Brauhaus",
    "wof:placetype":"venue"
},
  "geometry": {"coordinates":[7.4275841713,51.340549469],"type":"Point"}
}