{
  "type": "Feature",
  "properties": {
    "iso:country":"DE",
    "sg:address":"Fuerstenwall 66",
    "sg:city":"Duesseldorf",
    "sg:phone":"+49 211/9304798",
    "sg:postcode":"40219",
    "sg:province":"Nordrhein-Westfalen",
    "wof:name":"Atmosphaere",
    "wof:placetype":"venue"
},
  "geometry": {"coordinates":[6.768795,51.214699],"type":"Point"}
}