{
  "type": "Feature",
  "properties": {
    "iso:country":"DE",
    "sg:address":"Marktplatz 8",
    "sg:city":"Vohenstrau\u00df",
    "sg:phone":"+49 9651/736",
    "sg:postcode":"92648",
    "sg:province":"Bayern",
    "wof:name":"F. Kopf",
    "wof:placetype":"venue"
},
  "geometry": {"coordinates":[12.3419828415,49.6234779358],"type":"Point"}
}