{
  "type": "Feature",
  "properties": {
    "iso:country":"DE",
    "sg:address":"Wiederitzscher Str. 19",
    "sg:city":"Leipzig",
    "sg:phone":"+49 341/5662943",
    "sg:postcode":"04155",
    "sg:province":"Sachsen",
    "wof:name":"Karin Monse",
    "wof:placetype":"venue"
},
  "geometry": {"coordinates":[12.358467,51.364311],"type":"Point"}
}