{
  "type": "Feature",
  "properties": {
    "iso:country":"DE",
    "sg:address":"Br\u00fcckstrasse 16::",
    "sg:city":"Saarbr\u00fccken",
    "sg:phone":"+49 4968/93840",
    "sg:postcode":"66131",
    "sg:province":"Saarland",
    "wof:name":"Br\u00dcck Gmbh Ensheim",
    "wof:placetype":"venue"
},
  "geometry": {"coordinates":[7.1079158783,49.1983375549],"type":"Point"}
}