{
  "type": "Feature",
  "properties": {
    "iso:country":"DE",
    "sg:address":"Bochumer Str. 11-15",
    "sg:city":"Recklinghausen",
    "sg:phone":"+49 2361/72055",
    "sg:postcode":"45663",
    "sg:province":"Nordrhein-Westfalen",
    "wof:name":"Lueg Cars Gmbh",
    "wof:placetype":"venue"
},
  "geometry": {"coordinates":[7.2135100365,51.5814094543],"type":"Point"}
}