{
  "type": "Feature",
  "properties": {
    "iso:country":"DE",
    "sg:address":"Am Wasserturm 1",
    "sg:city":"Wallhausen",
    "sg:phone":"+49 7955/926900",
    "sg:postcode":"74599",
    "sg:province":"Baden-W\u00fcrttemberg",
    "wof:name":"Die Renovierer Bau- Betreuungs- Gmbh",
    "wof:placetype":"venue"
},
  "geometry": {"coordinates":[10.073846,49.216927],"type":"Point"}
}