{
  "type": "Feature",
  "properties": {
    "iso:country":"DE",
    "sg:address":"B\u00f6cklerstr. 3",
    "sg:city":"Freiburg",
    "sg:phone":"+49 761/16278",
    "sg:postcode":"79110",
    "sg:province":"Baden-W\u00fcrttemberg",
    "wof:name":"Restaurant Keglerstube",
    "wof:placetype":"venue"
},
  "geometry": {"coordinates":[7.8098750114,48.0287437439],"type":"Point"}
}