{
  "type": "Feature",
  "properties": {
    "iso:country":"DE",
    "sg:address":"Callunaweg 11",
    "sg:city":"Moers",
    "sg:postcode":"47447",
    "sg:province":"Nordrhein-Westfalen",
    "wof:name":"Mbe Elektrotechnik Gmbh",
    "wof:placetype":"venue"
},
  "geometry": {"coordinates":[6.6478247643,51.4235954285],"type":"Point"}
}