{
  "type": "Feature",
  "properties": {
    "iso:country":"DE",
    "sg:address":"Wiesenser Str. 40",
    "sg:city":"Aurich",
    "sg:phone":"+49 4941/3105",
    "sg:postcode":"26605",
    "sg:province":"Niedersachsen",
    "wof:name":"Raiffeisen-warengenossenschaft Wiesens Eg",
    "wof:placetype":"venue"
},
  "geometry": {"coordinates":[7.555022,53.448139],"type":"Point"}
}