{
  "type": "Feature",
  "properties": {
    "iso:country":"DE",
    "sg:address":"Obere W\u00f6rthstr. 22",
    "sg:city":"N\u00fcrnberg",
    "sg:phone":"+49 911/224136",
    "sg:postcode":"90403",
    "sg:province":"Bayern",
    "wof:name":"Hannelore Und Werner Wild",
    "wof:placetype":"venue"
},
  "geometry": {"coordinates":[11.072963,49.452518],"type":"Point"}
}