{
  "type": "Feature",
  "properties": {
    "iso:country":"DE",
    "sg:address":"Sch\u00fctzenstr. 32",
    "sg:city":"L\u00fcdenscheid",
    "sg:phone":"+49 2351/85842",
    "sg:postcode":"58511",
    "sg:province":"Nordrhein-Westfalen",
    "wof:name":"Y. Pankau-lagrave",
    "wof:placetype":"venue"
},
  "geometry": {"coordinates":[7.642272,51.21508],"type":"Point"}
}