{
  "type": "Feature",
  "properties": {
    "iso:country":"DE",
    "sg:address":"Kandelsgasse 14",
    "sg:city":"Wetter",
    "sg:phone":"+49 6423/92087",
    "sg:postcode":"35083",
    "sg:province":"Hessen",
    "wof:name":"Friedhelm Fett Steuerberater",
    "wof:placetype":"venue"
},
  "geometry": {"coordinates":[8.726931572,50.9054489136],"type":"Point"}
}