{
  "type": "Feature",
  "properties": {
    "iso:country":"DE",
    "sg:address":"Wilhelm-Tell-Str. 1a",
    "sg:city":"D\u00fcsseldorf",
    "sg:phone":"+49 211/3985533",
    "sg:postcode":"40219",
    "sg:province":"Nordrhein-Westfalen",
    "wof:name":"Anton Jurek",
    "wof:placetype":"venue"
},
  "geometry": {"coordinates":[6.766283,51.214676],"type":"Point"}
}