{
  "type": "Feature",
  "properties": {
    "iso:country":"DE",
    "sg:address":"Dorfstr. 16",
    "sg:city":"Reinbek",
    "sg:phone":"+49 7281/2477",
    "sg:postcode":"21465",
    "sg:province":"Schleswig-Holstein",
    "wof:name":"Km Direkt Transporte Hamburg - Kurierdienste",
    "wof:placetype":"venue"
},
  "geometry": {"coordinates":[10.2544088364,53.5312614441],"type":"Point"}
}