{
  "type": "Feature",
  "properties": {
    "iso:country":"DE",
    "sg:address":"Strelitzer Str. 2",
    "sg:city":"Berlin",
    "sg:phone":"+49 30/44319330",
    "sg:postcode":"10115",
    "sg:province":"Berlin",
    "wof:name":"Lecefer Licht Gmbh",
    "wof:placetype":"venue"
},
  "geometry": {"coordinates":[13.39682,52.533901],"type":"Point"}
}