{
  "type": "Feature",
  "properties": {
    "iso:country":"DE",
    "sg:address":"Benther Str. 9",
    "sg:city":"Gehrden",
    "sg:phone":"+49 5108/92082",
    "sg:postcode":"30989",
    "sg:province":"Niedersachsen",
    "wof:name":"Vtd Verhandlungs- Und Tagungs-dokumentation Gmbh",
    "wof:placetype":"venue"
},
  "geometry": {"coordinates":[9.603575,52.316357],"type":"Point"}
}