{
  "type": "Feature",
  "properties": {
    "iso:country":"DE",
    "sg:address":"Auf dem Dom 4",
    "sg:city":"N\u00f6rvenich",
    "sg:phone":"+49 2426/6769",
    "sg:postcode":"52388",
    "sg:province":"Nordrhein-Westfalen",
    "wof:name":"Ch. Mevis",
    "wof:placetype":"venue"
},
  "geometry": {"coordinates":[6.5911049843,50.8113555908],"type":"Point"}
}