{
  "type": "Feature",
  "properties": {
    "iso:country":"DE",
    "sg:address":"Waldstr. 11",
    "sg:city":"Heusenstamm",
    "sg:phone":"+49 6106/4188",
    "sg:postcode":"63150",
    "sg:province":"Hessen",
    "wof:name":"Chr. Sch\u00fcler & Sohn Ohg",
    "wof:placetype":"venue"
},
  "geometry": {"coordinates":[8.858781,50.049568],"type":"Point"}
}