{
  "type": "Feature",
  "properties": {
    "iso:country":"DE",
    "sg:address":"Hafenstr.",
    "sg:city":"Drochtersen",
    "sg:phone":"+49 4143/5421",
    "sg:postcode":"21706",
    "sg:province":"Niedersachsen",
    "wof:name":"I&w Verlag",
    "wof:placetype":"venue"
},
  "geometry": {"coordinates":[9.439048,53.693089],"type":"Point"}
}