{
  "type": "Feature",
  "properties": {
    "iso:country":"DE",
    "sg:address":"Hachenstr. 23",
    "sg:city":"Welver",
    "sg:phone":"+49 2384/1594",
    "sg:postcode":"59514",
    "sg:province":"Nordrhein-Westfalen",
    "wof:name":"Hans-dieter Bartmann Architekt",
    "wof:placetype":"venue"
},
  "geometry": {"coordinates":[7.957252,51.612614],"type":"Point"}
}