{
  "type": "Feature",
  "properties": {
    "iso:country":"DE",
    "sg:address":"Breitenbacher Str. 19",
    "sg:city":"Ebermannstadt",
    "sg:phone":"+49 9194/9532",
    "sg:postcode":"91320",
    "sg:province":"Bayern",
    "wof:name":"Josef Wilhelm",
    "wof:placetype":"venue"
},
  "geometry": {"coordinates":[11.184933,49.781597],"type":"Point"}
}