{
  "type": "Feature",
  "properties": {
    "iso:country":"DE",
    "sg:address":"Bahnhofstr. 41",
    "sg:city":"Sickte",
    "sg:postcode":"38173",
    "sg:province":"Niedersachsen",
    "wof:name":"Evangelische Stiftung Neuerkerode",
    "wof:placetype":"venue"
},
  "geometry": {"coordinates":[10.6394376755,52.2168312073],"type":"Point"}
}