{
  "type": "Feature",
  "properties": {
    "iso:country":"DE",
    "sg:address":"D\u00fcppelstr. 7",
    "sg:city":"Gronau",
    "sg:phone":"+49 2562/3055",
    "sg:postcode":"48599",
    "sg:province":"Nordrhein-Westfalen",
    "wof:name":"Gehling & Kiel",
    "wof:placetype":"venue"
},
  "geometry": {"coordinates":[7.0622191429,52.2060813904],"type":"Point"}
}