{
  "type": "Feature",
  "properties": {
    "iso:country":"DE",
    "sg:address":"Poststr. 6",
    "sg:city":"Pforzheim",
    "sg:phone":"+49 7231/351758",
    "sg:postcode":"75172",
    "sg:province":"Baden-W\u00fcrttemberg",
    "wof:name":"Salon Madame",
    "wof:placetype":"venue"
},
  "geometry": {"coordinates":[8.699349,48.892494],"type":"Point"}
}