{
  "type": "Feature",
  "properties": {
    "iso:country":"DE",
    "sg:address":"Heiligendammer Str. 28a",
    "sg:city":"Berlin",
    "sg:phone":"+49 30/8245219",
    "sg:postcode":"14199",
    "sg:province":"Berlin",
    "wof:name":"Hans-j\u00fcrgen F\u00f6rster Dipl.-ingenieur",
    "wof:placetype":"venue"
},
  "geometry": {"coordinates":[13.293443,52.471386],"type":"Point"}
}