{
  "type": "Feature",
  "properties": {
    "iso:country":"DE",
    "sg:address":"Louise-M\u00e4rcker-Str. 27",
    "sg:city":"Hagen",
    "sg:phone":"+49 2331/94960",
    "sg:postcode":"58135",
    "sg:province":"Nordrhein-Westfalen",
    "wof:name":"Industrie - Filter - Service Gmbh",
    "wof:placetype":"venue"
},
  "geometry": {"coordinates":[7.399151,51.345325],"type":"Point"}
}