{
  "type": "Feature",
  "properties": {
    "iso:country":"DE",
    "sg:address":"Landrat-Christians-Str. 110",
    "sg:city":"Bremen",
    "sg:phone":"+49 421/605047",
    "sg:postcode":"28779",
    "sg:province":"Bremen",
    "wof:name":"Joachim Beckmann Und Ko\u00dfmann Steuerberater",
    "wof:placetype":"venue"
},
  "geometry": {"coordinates":[8.5769395828,53.1816062927],"type":"Point"}
}