{
  "type": "Feature",
  "properties": {
    "iso:country":"DE",
    "sg:address":"Gartenstr. 12",
    "sg:city":"B\u00fchl",
    "sg:phone":"+49 7223/98890",
    "sg:postcode":"77815",
    "sg:province":"Baden-W\u00fcrttemberg",
    "wof:name":"Konkordia Verlag Gmbh",
    "wof:placetype":"venue"
},
  "geometry": {"coordinates":[8.1305942535,48.695854187],"type":"Point"}
}