{
  "type": "Feature",
  "properties": {
    "iso:country":"DE",
    "sg:address":"Rankestr. 5-6",
    "sg:city":"Berlin",
    "sg:postcode":"10789",
    "sg:province":"Berlin",
    "wof:name":"Zweite Revisions- Und Treu- Handges. Rankestr. 5-6 Verm.-",
    "wof:placetype":"venue"
},
  "geometry": {"coordinates":[13.334233,52.503216],"type":"Point"}
}