{
  "type": "Feature",
  "properties": {
    "iso:country":"DE",
    "sg:address":"Oststr. 5",
    "sg:city":"Neuenrade",
    "sg:phone":"+49 4923/9296810",
    "sg:postcode":"58809",
    "sg:province":"Nordrhein-Westfalen",
    "wof:name":"Kl\u00c4s Kunststoffe Gmbh",
    "wof:placetype":"venue"
},
  "geometry": {"coordinates":[7.7999801636,51.2846641541],"type":"Point"}
}