{
  "type": "Feature",
  "properties": {
    "iso:country":"DE",
    "sg:address":"Pirmasenser Str. 62 a",
    "sg:city":"Dahn",
    "sg:phone":"+49 6391/92250",
    "sg:postcode":"66994",
    "sg:province":"Rheinland-Pfalz",
    "wof:name":"Hartmut Seibel Rechtsanwalt",
    "wof:placetype":"venue"
},
  "geometry": {"coordinates":[7.7720980644,49.1548538208],"type":"Point"}
}