{
  "type": "Feature",
  "properties": {
    "iso:country":"DE",
    "sg:address":"Schillerstr. 3",
    "sg:city":"Riedstadt",
    "sg:phone":"+49 6158/910000",
    "sg:postcode":"64560",
    "sg:province":"Hessen",
    "wof:name":"B & S Gmbh",
    "wof:placetype":"venue"
},
  "geometry": {"coordinates":[8.4974336624,49.8330497742],"type":"Point"}
}