{
  "type": "Feature",
  "properties": {
    "iso:country":"DE",
    "sg:address":"Georg-B\u00fcchner-Str. 5",
    "sg:city":"Karben",
    "sg:phone":"+49 6039/3260",
    "sg:postcode":"61184",
    "sg:province":"Hessen",
    "wof:name":"Angelika Boerzel Steuerberaterin",
    "wof:placetype":"venue"
},
  "geometry": {"coordinates":[8.7890663147,50.2158660889],"type":"Point"}
}