{
  "type": "Feature",
  "properties": {
    "iso:country":"DE",
    "sg:address":"Flughafen 27",
    "sg:city":"Friedrichshafen",
    "sg:postcode":"88046",
    "sg:province":"Baden-W\u00fcrttemberg",
    "wof:name":"Schilling Ger\u00e4tebau E. K.",
    "wof:placetype":"venue"
},
  "geometry": {"coordinates":[9.5062131882,47.6653709412],"type":"Point"}
}