{
  "type": "Feature",
  "properties": {
    "iso:country":"DE",
    "sg:address":"\u00c4gidiusweg 31",
    "sg:city":"Hellenthal",
    "sg:phone":"+49 2448/436",
    "sg:postcode":"53940",
    "sg:province":"Nordrhein-Westfalen",
    "wof:name":"Katholisches Pfarramt St. \u00c4gidius",
    "wof:placetype":"venue"
},
  "geometry": {"coordinates":[6.4657788277,50.4398345947],"type":"Point"}
}