{
  "type": "Feature",
  "properties": {
    "iso:country":"DE",
    "sg:address":"Friedberger Str. 10",
    "sg:city":"Friedrichsdorf",
    "sg:phone":"+49 6175/7067",
    "sg:postcode":"61381",
    "sg:province":"Hessen",
    "wof:name":"Agip Deutschland Ag",
    "wof:placetype":"venue"
},
  "geometry": {"coordinates":[8.6546516418,50.2781715393],"type":"Point"}
}