{
  "type": "Feature",
  "properties": {
    "iso:country":"DE",
    "sg:address":"Richard-Wagner-Str. 89",
    "sg:city":"Suhl",
    "sg:phone":"+49 3681/306088",
    "sg:postcode":"98529",
    "sg:province":"Th\u00fcringen",
    "wof:name":"Ulrich Brunzel Rechtsanwalt",
    "wof:placetype":"venue"
},
  "geometry": {"coordinates":[10.6622591019,50.6075630188],"type":"Point"}
}