{
  "type": "Feature",
  "properties": {
    "iso:country":"DE",
    "sg:address":"Untere Augasse 3",
    "sg:city":"Pforzheim",
    "sg:phone":"+49 7231/66424",
    "sg:postcode":"75175",
    "sg:province":"Baden-W\u00fcrttemberg",
    "wof:name":"Auerbr\u00fccke",
    "wof:placetype":"venue"
},
  "geometry": {"coordinates":[8.7044687271,48.8881645203],"type":"Point"}
}