{
  "type": "Feature",
  "properties": {
    "iso:country":"DE",
    "sg:address":"Haaner Str. 34",
    "sg:city":"Wuppertal",
    "sg:phone":"+49 202/730608",
    "sg:postcode":"42329",
    "sg:province":"Nordrhein-Westfalen",
    "wof:name":"Aks Maschinenhandels Gmbh",
    "wof:placetype":"venue"
},
  "geometry": {"coordinates":[7.068205,51.229031],"type":"Point"}
}