{
  "type": "Feature",
  "properties": {
    "iso:country":"DE",
    "sg:address":"Veilchenstr. 18",
    "sg:city":"Wagh\u00e4usel",
    "sg:phone":"+49 7254/73947",
    "sg:postcode":"68753",
    "sg:province":"Baden-W\u00fcrttemberg",
    "wof:name":"Heinz Sand Innenarchitekt",
    "wof:placetype":"venue"
},
  "geometry": {"coordinates":[8.554918,49.239174],"type":"Point"}
}