{
  "type": "Feature",
  "properties": {
    "iso:country":"DE",
    "sg:address":"Konrad-Celtis-Str. 77",
    "sg:city":"M\u00fcnchen",
    "sg:postcode":"81369",
    "sg:province":"Bayern",
    "wof:name":"Communic Gmbh",
    "wof:placetype":"venue"
},
  "geometry": {"coordinates":[11.523354,48.110569],"type":"Point"}
}