{
  "type": "Feature",
  "properties": {
    "iso:country":"DE",
    "sg:address":"Krummenhakstr. 14",
    "sg:city":"Duisburg",
    "sg:phone":"+49 203/660394",
    "sg:postcode":"47053",
    "sg:province":"Nordrhein-Westfalen",
    "wof:name":"Martin Sildatke",
    "wof:placetype":"venue"
},
  "geometry": {"coordinates":[6.7620639801,51.4143295288],"type":"Point"}
}