{
  "type": "Feature",
  "properties": {
    "iso:country":"DE",
    "sg:address":"Neckarvorlandstr. 80-86",
    "sg:city":"Mannheim",
    "sg:phone":"+49 621/1298090",
    "sg:postcode":"68159",
    "sg:province":"Baden-W\u00fcrttemberg",
    "wof:name":"Rsw Rohstoffhandel S\u00fcd-west Gmbh",
    "wof:placetype":"venue"
},
  "geometry": {"coordinates":[8.452501297,49.500202179],"type":"Point"}
}