{
  "type": "Feature",
  "properties": {
    "iso:country":"DE",
    "sg:address":"Zaininger Str. 7",
    "sg:city":"R\u00f6merstein",
    "sg:phone":"+49 7382/93730",
    "sg:postcode":"72587",
    "sg:province":"Baden-W\u00fcrttemberg",
    "wof:name":"R\u00fcckle Gmbh",
    "wof:placetype":"venue"
},
  "geometry": {"coordinates":[9.513923,48.494633],"type":"Point"}
}