{
  "type": "Feature",
  "properties": {
    "iso:country":"DE",
    "sg:address":"Nonnenbr\u00fccke 7",
    "sg:city":"Bamberg",
    "sg:phone":"+49 951/201209",
    "sg:postcode":"96047",
    "sg:province":"Bayern",
    "wof:name":"Barbara Dix",
    "wof:placetype":"venue"
},
  "geometry": {"coordinates":[10.8906669617,49.8895301819],"type":"Point"}
}