{
  "type": "Feature",
  "properties": {
    "iso:country":"DE",
    "sg:address":"Clausthaler Str. 19",
    "sg:city":"Wildemann",
    "sg:phone":"+49 5323/96680",
    "sg:postcode":"38709",
    "sg:province":"Niedersachsen",
    "wof:name":"Zollern Bhw Gleitlager Gmbh & Co.",
    "wof:placetype":"venue"
},
  "geometry": {"coordinates":[10.27213,51.820732],"type":"Point"}
}