{
  "type": "Feature",
  "properties": {
    "iso:country":"DE",
    "sg:address":"Sch\u00f6nwalder Str. 78-79",
    "sg:city":"Berlin",
    "sg:phone":"+49 30/3753573",
    "sg:postcode":"13585",
    "sg:province":"Berlin",
    "wof:name":"Eva-apotheke Ohg",
    "wof:placetype":"venue"
},
  "geometry": {"coordinates":[13.200444,52.549274],"type":"Point"}
}