{
  "type": "Feature",
  "properties": {
    "iso:country":"DE",
    "sg:address":"Allee 5",
    "sg:city":"Heusweiler",
    "sg:phone":"+49 4968/068817",
    "sg:postcode":"66265",
    "sg:province":"Saarland",
    "wof:name":"Volksbank Dudweiler Eg",
    "wof:placetype":"venue"
},
  "geometry": {"coordinates":[6.99014,49.331177],"type":"Point"}
}