{
  "type": "Feature",
  "properties": {
    "iso:country":"DE",
    "sg:address":"Hauptstr. 41",
    "sg:city":"K\u00f6nigsbrunn",
    "sg:phone":"+49 8231/2439",
    "sg:postcode":"86343",
    "sg:province":"Bayern",
    "wof:name":"Kath. \u00d6ffentliche B\u00fccherei St. Urich",
    "wof:placetype":"venue"
},
  "geometry": {"coordinates":[10.890975,48.268719],"type":"Point"}
}