{
  "type": "Feature",
  "properties": {
    "iso:country":"DE",
    "sg:address":"Hafenstr. 245",
    "sg:city":"Bremerhaven",
    "sg:postcode":"27568",
    "sg:province":"Bremen",
    "wof:name":"Montage-bau Gotter Gmbh",
    "wof:placetype":"venue"
},
  "geometry": {"coordinates":[8.585528,53.566036],"type":"Point"}
}