{
  "type": "Feature",
  "properties": {
    "iso:country":"DE",
    "sg:address":"K\u00f6nigsberger Str. 20",
    "sg:city":"Berlin",
    "sg:phone":"+49 30/7724822",
    "sg:postcode":"12207",
    "sg:province":"Berlin",
    "wof:name":"Mert Bau Bauunternehmen E. Kfm.",
    "wof:placetype":"venue"
},
  "geometry": {"coordinates":[13.3160066605,52.4308357239],"type":"Point"}
}