{
  "type": "Feature",
  "properties": {
    "iso:country":"DE",
    "sg:address":"Bodenwehrerstr.3",
    "sg:city":"Wackersdorf",
    "sg:phone":"+49 9431/74320",
    "sg:postcode":"92442",
    "sg:province":"Bayern",
    "wof:name":"Schubert Medizinprodukte Gmbh & Co Kg",
    "wof:placetype":"venue"
},
  "geometry": {"coordinates":[12.1734399796,49.3108139038],"type":"Point"}
}