{
  "type": "Feature",
  "properties": {
    "iso:country":"DE",
    "sg:address":"Im Derdel 12",
    "sg:city":"M\u00fcnster",
    "sg:phone":"+49 2534/97370",
    "sg:postcode":"48161",
    "sg:province":"Nordrhein-Westfalen",
    "wof:name":"Hbl-stahlhandel Gmbh & Co. Kg",
    "wof:placetype":"venue"
},
  "geometry": {"coordinates":[7.552113,51.951153],"type":"Point"}
}