{
  "type": "Feature",
  "properties": {
    "iso:country":"DE",
    "sg:address":"Zur Sperrmauer 24",
    "sg:city":"Edertal",
    "sg:phone":"+49 5623/1779",
    "sg:postcode":"34549",
    "sg:province":"Hessen",
    "wof:name":"Petra Und Ursula Becker",
    "wof:placetype":"venue"
},
  "geometry": {"coordinates":[9.055705,51.176723],"type":"Point"}
}