{
  "type": "Feature",
  "properties": {
    "iso:country":"DE",
    "sg:address":"Martin-Schongauer-Str. 10",
    "sg:city":"Rottenburg",
    "sg:phone":"+49 7073/7241",
    "sg:postcode":"72108",
    "sg:province":"Baden-W\u00fcrttemberg",
    "wof:name":"J. Herlemann",
    "wof:placetype":"venue"
},
  "geometry": {"coordinates":[8.9251346588,48.5255279541],"type":"Point"}
}