{
  "type": "Feature",
  "properties": {
    "iso:country":"DE",
    "sg:address":"Veckerhagener Str. 1 c",
    "sg:city":"Immenhausen",
    "sg:phone":"+49 5673/998780",
    "sg:postcode":"34376",
    "sg:province":"Hessen",
    "wof:name":"Norbert Mehlhorn Gmbh",
    "wof:placetype":"venue"
},
  "geometry": {"coordinates":[9.4979496002,51.459072113],"type":"Point"}
}