{
  "type": "Feature",
  "properties": {
    "iso:country":"DE",
    "sg:address":"Friedenstr. 61",
    "sg:city":"Nettetal",
    "sg:phone":"+49 2153/915550",
    "sg:postcode":"41334",
    "sg:province":"Nordrhein-Westfalen",
    "wof:name":"Sebastian-apotheke",
    "wof:placetype":"venue"
},
  "geometry": {"coordinates":[6.274758,51.309746],"type":"Point"}
}