{
  "type": "Feature",
  "properties": {
    "iso:country":"DE",
    "sg:address":"Gro\u00dfe B\u00e4ckerstr. 22",
    "sg:city":"L\u00fcneburg",
    "sg:phone":"+49 4131/27070",
    "sg:postcode":"21335",
    "sg:province":"Niedersachsen",
    "wof:name":"Brunsmeier Erbengemeinschaft",
    "wof:placetype":"venue"
},
  "geometry": {"coordinates":[10.4090280533,53.249080658],"type":"Point"}
}