{
  "type": "Feature",
  "properties": {
    "iso:country":"DE",
    "sg:address":"Kirchstr. 5",
    "sg:city":"Wintersheim",
    "sg:phone":"+49 6733/1556",
    "sg:postcode":"67587",
    "sg:province":"Rheinland-Pfalz",
    "wof:name":"Gerhard Walter",
    "wof:placetype":"venue"
},
  "geometry": {"coordinates":[8.2812643051,49.777633667],"type":"Point"}
}