{
  "type": "Feature",
  "properties": {
    "iso:country":"DE",
    "sg:address":"Meistersingerstr. 69",
    "sg:city":"Essen",
    "sg:phone":"+49 201/594499",
    "sg:postcode":"45307",
    "sg:province":"Nordrhein-Westfalen",
    "wof:name":"Kosmos-apotheke",
    "wof:placetype":"venue"
},
  "geometry": {"coordinates":[7.087323,51.456173],"type":"Point"}
}