{
  "type": "Feature",
  "properties": {
    "iso:country":"DE",
    "sg:address":"Ebersdorfer Str. 37",
    "sg:city":"Ebersdorf",
    "sg:postcode":"96237",
    "sg:province":"Bayern",
    "wof:name":"Andree Thom\u00e4 Malergesch\u00e4ft Gmbh",
    "wof:placetype":"venue"
},
  "geometry": {"coordinates":[11.07443,50.235859],"type":"Point"}
}