{
  "type": "Feature",
  "properties": {
    "iso:country":"DE",
    "sg:address":"Auf dem Hain 1",
    "sg:city":"Rauschenberg",
    "sg:phone":"+49 6425/1249",
    "sg:postcode":"35282",
    "sg:province":"Hessen",
    "wof:name":"Christlieb Ruckert",
    "wof:placetype":"venue"
},
  "geometry": {"coordinates":[8.92847,50.878254],"type":"Point"}
}