{
  "type": "Feature",
  "properties": {
    "iso:country":"DE",
    "sg:address":"Harheimer Weg 2",
    "sg:city":"Frankfurt",
    "sg:phone":"+49 69/503178",
    "sg:postcode":"60437",
    "sg:province":"Hessen",
    "wof:name":"Johann Epp Bauschlosserei",
    "wof:placetype":"venue"
},
  "geometry": {"coordinates":[8.6654,50.183094],"type":"Point"}
}