{
  "type": "Feature",
  "properties": {
    "iso:country":"DE",
    "sg:address":"Schleckheimerstr. 222",
    "sg:city":"Aachen",
    "sg:postcode":"52076",
    "sg:province":"Nordrhein-Westfalen",
    "wof:name":"Scharfe Frauen, Nackt, Willig Und Geil",
    "wof:placetype":"venue"
},
  "geometry": {"coordinates":[6.158725,50.721027],"type":"Point"}
}