{
  "type": "Feature",
  "properties": {
    "iso:country":"DE",
    "sg:address":"Spitalhofstr. 79",
    "sg:city":"Passau",
    "sg:phone":"+49 851/560970",
    "sg:postcode":"94032",
    "sg:province":"Bayern",
    "wof:name":"Akt Informationssysteme Ag",
    "wof:placetype":"venue"
},
  "geometry": {"coordinates":[13.4268217087,48.5700454712],"type":"Point"}
}