{
  "type": "Feature",
  "properties": {
    "iso:country":"DE",
    "sg:address":"Taubenberg",
    "sg:city":"Bodolz",
    "sg:phone":"+49 8382/5519",
    "sg:postcode":"88131",
    "sg:province":"Bayern",
    "wof:name":"Gerald Richter",
    "wof:placetype":"venue"
},
  "geometry": {"coordinates":[9.6534576416,47.5841789246],"type":"Point"}
}