{
  "type": "Feature",
  "properties": {
    "iso:country":"DE",
    "sg:address":"Glockenstr. 29",
    "sg:city":"Herne",
    "sg:phone":"+49 2323/916916",
    "sg:postcode":"44623",
    "sg:province":"Nordrhein-Westfalen",
    "wof:name":"Syntax-bau Gmbh",
    "wof:placetype":"venue"
},
  "geometry": {"coordinates":[7.227645874,51.5399971008],"type":"Point"}
}