{
  "type": "Feature",
  "properties": {
    "iso:country":"DE",
    "sg:address":"M\u00fcggenkampstr. 72",
    "sg:city":"Hamburg",
    "sg:phone":"+49 40/4905191",
    "sg:postcode":"20257",
    "sg:province":"Hamburg",
    "wof:name":"Fotostudio J\u00fcrgen Sch\u00e4fer",
    "wof:placetype":"venue"
},
  "geometry": {"coordinates":[9.940401,53.580441],"type":"Point"}
}