{
  "type": "Feature",
  "properties": {
    "iso:country":"DE",
    "sg:address":"Wilhelm-R\u00f6ntgen-Str. 1",
    "sg:city":"Offenburg",
    "sg:phone":"+49 781/77810",
    "sg:postcode":"77656",
    "sg:province":"Baden-W\u00fcrttemberg",
    "wof:name":"Winfried Heffner",
    "wof:placetype":"venue"
},
  "geometry": {"coordinates":[7.9253001213,48.4722518921],"type":"Point"}
}