{
  "type": "Feature",
  "properties": {
    "iso:country":"DE",
    "sg:address":"Alte Marktstr. 7",
    "sg:city":"Ortenberg",
    "sg:phone":"+49 6046/1267",
    "sg:postcode":"63683",
    "sg:province":"Hessen",
    "wof:name":"Doris Langsdorf Masseurin",
    "wof:placetype":"venue"
},
  "geometry": {"coordinates":[9.055227,50.35693],"type":"Point"}
}