{
  "type": "Feature",
  "properties": {
    "iso:country":"DE",
    "sg:address":"Schulstr. 109",
    "sg:city":"Berlin",
    "sg:phone":"+49 30/4551022",
    "sg:postcode":"13347",
    "sg:province":"Berlin",
    "wof:name":"Gastst\u00e4tte Schultheiss Stube",
    "wof:placetype":"venue"
},
  "geometry": {"coordinates":[13.3655414581,52.5507392883],"type":"Point"}
}