{
  "type": "Feature",
  "properties": {
    "iso:country":"DE",
    "sg:address":"Bergkramerhof",
    "sg:city":"Wolfratshausen",
    "sg:phone":"+49 8171/76168",
    "sg:postcode":"82515",
    "sg:province":"Bayern",
    "wof:name":"Bergkramerhof Gastronomie Gmbh",
    "wof:placetype":"venue"
},
  "geometry": {"coordinates":[11.4020299911,47.9061851501],"type":"Point"}
}