{
  "type": "Feature",
  "properties": {
    "iso:country":"DE",
    "sg:address":"Villinger Str. 39",
    "sg:city":"Villingen-Schwenningen",
    "sg:phone":"+49 7720/37830",
    "sg:postcode":"78054",
    "sg:province":"Baden-W\u00fcrttemberg",
    "wof:name":"Gerhard Sturm",
    "wof:placetype":"venue"
},
  "geometry": {"coordinates":[8.5269069672,48.0621795654],"type":"Point"}
}