{
  "type": "Feature",
  "properties": {
    "iso:country":"DE",
    "sg:address":"Angelstr. 42",
    "sg:city":"Mannheim",
    "sg:phone":"+49 621/851343",
    "sg:postcode":"68199",
    "sg:province":"Baden-W\u00fcrttemberg",
    "wof:name":"Friedrich Gysin",
    "wof:placetype":"venue"
},
  "geometry": {"coordinates":[8.4954004288,49.4511146545],"type":"Point"}
}