{
  "type": "Feature",
  "properties": {
    "iso:country":"DE",
    "sg:address":"Heringskoop 24",
    "sg:city":"Nordleda",
    "sg:phone":"+49 4758/1223",
    "sg:postcode":"21765",
    "sg:province":"Niedersachsen",
    "wof:name":"Hans-j\u00fcrgen Poit",
    "wof:placetype":"venue"
},
  "geometry": {"coordinates":[8.819769,53.761086],"type":"Point"}
}