{
  "type": "Feature",
  "properties": {
    "iso:country":"DE",
    "sg:address":"Hochstr. 5",
    "sg:city":"Datteln",
    "sg:phone":"+49 2363/34386",
    "sg:postcode":"45711",
    "sg:province":"Nordrhein-Westfalen",
    "wof:name":"Hans Gmbh",
    "wof:placetype":"venue"
},
  "geometry": {"coordinates":[7.3074531555,51.6996536255],"type":"Point"}
}