{
  "type": "Feature",
  "properties": {
    "iso:country":"DE",
    "sg:address":"Lindenau 24 a",
    "sg:city":"Issum",
    "sg:phone":"+49 2835/44126",
    "sg:postcode":"47661",
    "sg:province":"Nordrhein-Westfalen",
    "wof:name":"Horn & Sohn Gmbh",
    "wof:placetype":"venue"
},
  "geometry": {"coordinates":[6.417604,51.5452],"type":"Point"}
}