{
  "type": "Feature",
  "properties": {
    "iso:country":"DE",
    "sg:address":"Saynstr. 28",
    "sg:city":"Hachenburg",
    "sg:phone":"+49 2662/7533",
    "sg:postcode":"57627",
    "sg:province":"Rheinland-Pfalz",
    "wof:name":"Karl-artur Hommel",
    "wof:placetype":"venue"
},
  "geometry": {"coordinates":[7.81202,50.66515],"type":"Point"}
}