{
  "type": "Feature",
  "properties": {
    "iso:country":"DE",
    "sg:address":"Flensburger Str. 38",
    "sg:city":"Wuppertal",
    "sg:phone":"+49 202/455527",
    "sg:postcode":"42107",
    "sg:province":"Nordrhein-Westfalen",
    "wof:name":"Spunk",
    "wof:placetype":"venue"
},
  "geometry": {"coordinates":[7.1490020752,51.2643432617],"type":"Point"}
}