{
  "type": "Feature",
  "properties": {
    "iso:country":"DE",
    "sg:address":"An den Winkelwiesen 18",
    "sg:city":"Cossebaude",
    "sg:phone":"+49 351/4537045",
    "sg:postcode":"01462",
    "wof:name":"Claus Biermann Architekt",
    "wof:placetype":"venue"
},
  "geometry": {"coordinates":[13.62081,51.088329],"type":"Point"}
}