{
  "type": "Feature",
  "properties": {
    "iso:country":"DE",
    "sg:address":"An der Kirche 9",
    "sg:city":"Zernien",
    "sg:phone":"+49 5863/1371",
    "sg:postcode":"29499",
    "sg:province":"Niedersachsen",
    "wof:name":"Reiterpension Hans-werner D\u00f6rr",
    "wof:placetype":"venue"
},
  "geometry": {"coordinates":[10.8761701584,53.049911499],"type":"Point"}
}