{
  "type": "Feature",
  "properties": {
    "iso:country":"DE",
    "sg:address":"Greifswalder Str. 25",
    "sg:city":"Wolgast",
    "sg:phone":"+49 3836/203151",
    "sg:postcode":"17438",
    "sg:province":"Mecklenburg-Vorpommern",
    "wof:name":"Peter Wohler",
    "wof:placetype":"venue"
},
  "geometry": {"coordinates":[13.767695,54.058254],"type":"Point"}
}