{
  "type": "Feature",
  "properties": {
    "iso:country":"DE",
    "sg:address":"Tiergartenstr. 9",
    "sg:city":"Pr\u00fcm",
    "sg:phone":"+49 6551/2461",
    "sg:postcode":"54595",
    "sg:province":"Rheinland-Pfalz",
    "wof:name":"Josef J\u00e4nen",
    "wof:placetype":"venue"
},
  "geometry": {"coordinates":[6.4213380814,50.2076797485],"type":"Point"}
}