{
  "type": "Feature",
  "properties": {
    "iso:country":"DE",
    "sg:address":"Friedrich-Ebert-Str. 4",
    "sg:city":"Hofheim",
    "sg:phone":"+49 6122/6692",
    "sg:postcode":"65719",
    "sg:province":"Hessen",
    "wof:name":"Weinkontor Wallau Karlheinz Radtke",
    "wof:placetype":"venue"
},
  "geometry": {"coordinates":[8.4037094116,49.6582527161],"type":"Point"}
}