{
  "type": "Feature",
  "properties": {
    "iso:country":"DE",
    "sg:address":"Reichsst\u00e4dter Str.",
    "sg:city":"Aalen",
    "sg:phone":"+49 7361/66344",
    "sg:postcode":"73430",
    "sg:province":"Baden-W\u00fcrttemberg",
    "wof:name":"A. Zentner Vergn\u00fcgungsst\u00e4tte",
    "wof:placetype":"venue"
},
  "geometry": {"coordinates":[10.094785,48.838264],"type":"Point"}
}