{
  "type": "Feature",
  "properties": {
    "iso:country":"DE",
    "sg:address":"Franz-Konrad-Str. 5",
    "sg:city":"Schw\u00e4bisch Gm\u00fcnd",
    "sg:phone":"+49 7171/30646",
    "sg:postcode":"73527",
    "sg:province":"Baden-W\u00fcrttemberg",
    "wof:name":"Rudolf Schoder",
    "wof:placetype":"venue"
},
  "geometry": {"coordinates":[9.795482,48.80724],"type":"Point"}
}