{
  "type": "Feature",
  "properties": {
    "iso:country":"DE",
    "sg:address":"Unterm-Heilig-Kreuz 11",
    "sg:city":"Fulda",
    "sg:phone":"+49 661/70066",
    "sg:postcode":"36037",
    "sg:province":"Hessen",
    "wof:name":"Sparkassen Versicherung",
    "wof:placetype":"venue"
},
  "geometry": {"coordinates":[9.6764659882,50.5512771606],"type":"Point"}
}