{
  "type": "Feature",
  "properties": {
    "iso:country":"DE",
    "sg:address":"Daniel-Gottlob-T\u00fcrk-Str. 13",
    "sg:city":"Clau\u00dfnitz",
    "sg:phone":"+49 37202/2431",
    "sg:postcode":"09236",
    "sg:province":"Sachsen",
    "wof:name":"Dr. Ullrich Melzer Tierarzt",
    "wof:placetype":"venue"
},
  "geometry": {"coordinates":[12.883312,50.938496],"type":"Point"}
}