{
  "type": "Feature",
  "properties": {
    "iso:country":"DE",
    "sg:address":"Husemannplatz 1",
    "sg:city":"Bochum",
    "sg:phone":"+49 234/15530",
    "sg:postcode":"44787",
    "sg:province":"Nordrhein-Westfalen",
    "wof:name":"Eissalon Antonio Faghera",
    "wof:placetype":"venue"
},
  "geometry": {"coordinates":[7.216881,51.479786],"type":"Point"}
}