{
  "type": "Feature",
  "properties": {
    "iso:country":"DE",
    "sg:address":"Hopmanns Kamp 4",
    "sg:city":"Nordhorn",
    "sg:postcode":"48531",
    "sg:province":"Niedersachsen",
    "wof:name":"Sterbekasse Nachbarschaft Zur Blanke E.v. Nordhorn",
    "wof:placetype":"venue"
},
  "geometry": {"coordinates":[7.093529,52.429173],"type":"Point"}
}