{
  "type": "Feature",
  "properties": {
    "iso:country":"DE",
    "sg:address":"Helsaer Str. 37",
    "sg:city":"Kassel",
    "sg:phone":"+49 561/526699",
    "sg:postcode":"34123",
    "sg:province":"Hessen",
    "wof:name":"Malkusch Gmbh",
    "wof:placetype":"venue"
},
  "geometry": {"coordinates":[9.5575942993,51.3017692566],"type":"Point"}
}