{
  "type": "Feature",
  "properties": {
    "iso:country":"DE",
    "sg:address":"Siedlung 6a",
    "sg:city":"Hohnstein",
    "sg:phone":"+49 35975/81657",
    "sg:postcode":"01848",
    "sg:province":"Sachsen",
    "wof:name":"Hohnsteiner Handspielpuppen",
    "wof:placetype":"venue"
},
  "geometry": {"coordinates":[14.2150201797,50.9595336914],"type":"Point"}
}