{
  "type": "Feature",
  "properties": {
    "iso:country":"DE",
    "sg:address":"Kreuslerstr. 10",
    "sg:city":"Hamburg",
    "sg:phone":"+49 40/327624",
    "sg:postcode":"20095",
    "sg:province":"Hamburg",
    "wof:name":"Hamburger Verm\u00f6gens- Verwaltungsgesellschaft Mbh",
    "wof:placetype":"venue"
},
  "geometry": {"coordinates":[9.9979190826,53.5504188538],"type":"Point"}
}