{
  "type": "Feature",
  "properties": {
    "iso:country":"DE",
    "sg:address":"Henri-Dunant-Str. 67",
    "sg:city":"D\u00fcsseldorf",
    "sg:phone":"+49 211/4350747",
    "sg:postcode":"40474",
    "sg:province":"Nordrhein-Westfalen",
    "wof:name":"Ulrich Horn Fotoarchiv",
    "wof:placetype":"venue"
},
  "geometry": {"coordinates":[6.7313051224,51.2803955078],"type":"Point"}
}