{
  "type": "Feature",
  "properties": {
    "iso:country":"DE",
    "sg:address":"Rheindammstr. 50",
    "sg:city":"Mannheim",
    "sg:phone":"+49 621/823891",
    "sg:postcode":"68163",
    "sg:province":"Baden-W\u00fcrttemberg",
    "wof:name":"U. B\u00fchler-hellinger",
    "wof:placetype":"venue"
},
  "geometry": {"coordinates":[8.465507,49.474899],"type":"Point"}
}