{
  "type": "Feature",
  "properties": {
    "iso:country":"DE",
    "sg:address":"Bahnhofstr. 20",
    "sg:city":"Sch\u00f6nberg",
    "sg:phone":"+49 4344/9103",
    "sg:postcode":"24217",
    "sg:province":"Schleswig-Holstein",
    "wof:name":"Willi Alpen",
    "wof:placetype":"venue"
},
  "geometry": {"coordinates":[10.3732595444,54.3907432556],"type":"Point"}
}