{
  "type": "Feature",
  "properties": {
    "iso:country":"DE",
    "sg:address":"Sonnebergerstr. 21",
    "sg:city":"Steinach",
    "sg:phone":"+49 36762/8305",
    "sg:postcode":"96523",
    "sg:province":"Th\u00fcringen",
    "wof:name":"Sparkasse Hasselbach",
    "wof:placetype":"venue"
},
  "geometry": {"coordinates":[11.162235,50.425617],"type":"Point"}
}