{
  "type": "Feature",
  "properties": {
    "iso:country":"DE",
    "sg:address":"Gustav-Moll-Str. 8",
    "sg:city":"Beckum",
    "sg:phone":"+49 2521/14527",
    "sg:postcode":"59269",
    "sg:province":"Nordrhein-Westfalen",
    "wof:name":"Siegbert Kleinwechter",
    "wof:placetype":"venue"
},
  "geometry": {"coordinates":[8.0245370865,51.7989501953],"type":"Point"}
}