{
  "type": "Feature",
  "properties": {
    "iso:country":"DE",
    "sg:address":"Schillerstr. 1",
    "sg:city":"Wildberg",
    "sg:phone":"+49 7054/490",
    "sg:postcode":"72218",
    "sg:province":"Baden-W\u00fcrttemberg",
    "wof:name":"Ernst Frauer",
    "wof:placetype":"venue"
},
  "geometry": {"coordinates":[8.738022,48.623455],"type":"Point"}
}