{
  "type": "Feature",
  "properties": {
    "iso:country":"DE",
    "sg:address":"Birkenwaldstr. 26",
    "sg:city":"Stuttgart",
    "sg:phone":"+49 711/292176",
    "sg:postcode":"70191",
    "sg:province":"Baden-W\u00fcrttemberg",
    "wof:name":"Ev. Pfarramt Erl\u00f6serkirche",
    "wof:placetype":"venue"
},
  "geometry": {"coordinates":[9.1780395508,48.7899017334],"type":"Point"}
}