{
  "type": "Feature",
  "properties": {
    "iso:country":"DE",
    "sg:address":"Fliederberg 3",
    "sg:city":"Dresden",
    "sg:phone":"+49 351/4162993",
    "sg:postcode":"01169",
    "sg:province":"Sachsen",
    "wof:name":"R. Bunge",
    "wof:placetype":"venue"
},
  "geometry": {"coordinates":[13.6724271774,51.0376625061],"type":"Point"}
}