{
  "type": "Feature",
  "properties": {
    "iso:country":"DE",
    "sg:address":"Am Vorderfl\u00f6\u00df 48",
    "sg:city":"Bad Lippspringe",
    "sg:phone":"+49 5252/98480",
    "sg:postcode":"33175",
    "sg:province":"Nordrhein-Westfalen",
    "wof:name":"Reisedienst Bodo Henker",
    "wof:placetype":"venue"
},
  "geometry": {"coordinates":[8.7934980392,51.776676178],"type":"Point"}
}