{
  "type": "Feature",
  "properties": {
    "iso:country":"DE",
    "sg:address":"Im Grund 11",
    "sg:city":"D\u00fcsseldorf",
    "sg:phone":"+49 211/4360311",
    "sg:postcode":"40474",
    "sg:province":"Nordrhein-Westfalen",
    "wof:name":"Medienb\u00fcro Spinrads & Meier Kg",
    "wof:placetype":"venue"
},
  "geometry": {"coordinates":[6.738036,51.284786],"type":"Point"}
}