{
  "type": "Feature",
  "properties": {
    "iso:country":"DE",
    "sg:address":"Borrom\u00e4weg 4",
    "sg:city":"Glottertal",
    "sg:phone":"+49 7684/230",
    "sg:postcode":"79286",
    "sg:province":"Baden-W\u00fcrttemberg",
    "wof:name":"B\u00fccherei Kath. Pfarramt",
    "wof:placetype":"venue"
},
  "geometry": {"coordinates":[7.9551692009,48.0493240356],"type":"Point"}
}