{
  "type": "Feature",
  "properties": {
    "iso:country":"DE",
    "sg:address":"Hessischer Damm 5",
    "sg:city":"Wunstorf",
    "sg:phone":"+49 5031/16914",
    "sg:postcode":"31515",
    "sg:province":"Niedersachsen",
    "wof:name":"Karl Kuckuck",
    "wof:placetype":"venue"
},
  "geometry": {"coordinates":[9.450609,52.38747],"type":"Point"}
}