{
  "type": "Feature",
  "properties": {
    "iso:country":"DE",
    "sg:address":"Kirchstr. 2",
    "sg:city":"K\u00f6nigstein",
    "sg:phone":"+49 6174/21498",
    "sg:postcode":"61462",
    "sg:province":"Hessen",
    "wof:name":"Emil Hees Gmbh",
    "wof:placetype":"venue"
},
  "geometry": {"coordinates":[8.465205,50.182823],"type":"Point"}
}