{
  "type": "Feature",
  "properties": {
    "iso:country":"DE",
    "sg:address":"Theatinerstr. 36",
    "sg:city":"M\u00fcnchen",
    "sg:phone":"+49 89/2908240",
    "sg:postcode":"80333",
    "sg:province":"Bayern",
    "wof:name":"Bally Deutschland Gmbh",
    "wof:placetype":"venue"
},
  "geometry": {"coordinates":[11.5766563416,48.1405715942],"type":"Point"}
}