{
  "type": "Feature",
  "properties": {
    "iso:country":"DE",
    "sg:address":"Mittelstr. 1",
    "sg:city":"Hohenhameln",
    "sg:phone":"+49 5128/5730",
    "sg:postcode":"31249",
    "sg:province":"Niedersachsen",
    "wof:name":"C & C Grundst\u00fccksges. Mbh",
    "wof:placetype":"venue"
},
  "geometry": {"coordinates":[10.1182546616,52.2442741394],"type":"Point"}
}