{
  "type": "Feature",
  "properties": {
    "iso:country":"DE",
    "sg:address":"Thaininger Str.",
    "sg:city":"Vilgertshofen",
    "sg:phone":"+49 8194/362",
    "sg:postcode":"86946",
    "sg:province":"Bayern",
    "wof:name":"Erich Und Markus M\u00fcller",
    "wof:placetype":"venue"
},
  "geometry": {"coordinates":[10.9553184509,47.9582901001],"type":"Point"}
}