{
  "type": "Feature",
  "properties": {
    "iso:country":"DE",
    "sg:address":"25",
    "sg:city":"PARIS",
    "sg:phone":"+49 146078325",
    "sg:postcode":"75008",
    "wof:name":"Whyfan-club",
    "wof:placetype":"venue"
},
  "geometry": {"coordinates":[2.308933,48.870838],"type":"Point"}
}