{
  "type": "Feature",
  "properties": {
    "iso:country":"DE",
    "sg:address":"Bodelschwinghstr.32",
    "sg:city":"Pforzheim",
    "sg:phone":"+49 7231",
    "sg:postcode":"75179",
    "sg:province":"Baden-W\u00fcrttemberg",
    "wof:name":"Bvbw",
    "wof:placetype":"venue"
},
  "geometry": {"coordinates":[8.675307,48.89489],"type":"Point"}
}