{
  "type": "Feature",
  "properties": {
    "iso:country":"DE",
    "sg:address":"Hauptstr. 89",
    "sg:city":"Mainz-Kostheim",
    "sg:phone":"+49 6134/62119",
    "sg:postcode":"55246",
    "sg:province":"Hessen",
    "wof:name":"Bue\u00df",
    "wof:placetype":"venue"
},
  "geometry": {"coordinates":[8.309939,50.001163],"type":"Point"}
}