{
  "type": "Feature",
  "properties": {
    "iso:country":"DE",
    "sg:address":"Kampweg 11",
    "sg:city":"Sittensen",
    "sg:phone":"+49 4282/2525",
    "sg:postcode":"27419",
    "sg:province":"Niedersachsen",
    "wof:name":"Wilhelm Hinners & Sohn",
    "wof:placetype":"venue"
},
  "geometry": {"coordinates":[9.5010738373,53.2827949524],"type":"Point"}
}