{
  "type": "Feature",
  "properties": {
    "iso:country":"DE",
    "sg:address":"Selhorster Str. 46",
    "sg:city":"Langenberg",
    "sg:postcode":"33449",
    "sg:province":"Nordrhein-Westfalen",
    "wof:name":"Drivex Vertriebs- Gmbh",
    "wof:placetype":"venue"
},
  "geometry": {"coordinates":[8.3171577454,51.7860984802],"type":"Point"}
}