{
  "type": "Feature",
  "properties": {
    "iso:country":"DE",
    "sg:address":"M\u00fcnsterplatz 23",
    "sg:city":"Bonn",
    "sg:phone":"+49 228/985620",
    "sg:postcode":"53111",
    "sg:province":"Nordrhein-Westfalen",
    "wof:name":"Bhw Bausparkasse Ag",
    "wof:placetype":"venue"
},
  "geometry": {"coordinates":[7.099333,50.734982],"type":"Point"}
}