{
  "type": "Feature",
  "properties": {
    "iso:country":"DE",
    "sg:address":"Pilatusring 5",
    "sg:city":"Hausen",
    "sg:phone":"+49 9191/4269",
    "sg:postcode":"91353",
    "sg:province":"Bayern",
    "wof:name":"Dittmar & Straceny Ohg",
    "wof:placetype":"venue"
},
  "geometry": {"coordinates":[11.0422143936,49.6976966858],"type":"Point"}
}