{
  "type": "Feature",
  "properties": {
    "iso:country":"DE",
    "sg:address":"Lehderstr. 10",
    "sg:city":"Berlin",
    "sg:phone":"+49 30/9257324",
    "sg:postcode":"13086",
    "sg:province":"Berlin",
    "wof:name":"Wolfgang Palm Ingenieur",
    "wof:placetype":"venue"
},
  "geometry": {"coordinates":[13.445684433,52.5482406616],"type":"Point"}
}