{
  "type": "Feature",
  "properties": {
    "iso:country":"DE",
    "sg:address":"Mathmeckestr. 37",
    "sg:city":"Eslohe",
    "sg:phone":"+49 2973/81220",
    "sg:postcode":"59889",
    "sg:province":"Nordrhein-Westfalen",
    "wof:name":"Pension Stefan Bornemann",
    "wof:placetype":"venue"
},
  "geometry": {"coordinates":[8.1676330566,51.2858276367],"type":"Point"}
}