{
  "type": "Feature",
  "properties": {
    "iso:country":"DE",
    "sg:address":"Biedersteiner Str. 78",
    "sg:city":"M\u00fcnchen",
    "sg:phone":"+49 89/3614058",
    "sg:postcode":"80802",
    "sg:province":"Bayern",
    "wof:name":"Brunnwart-gasthaus",
    "wof:placetype":"venue"
},
  "geometry": {"coordinates":[11.5929698944,48.1621894836],"type":"Point"}
}