{
  "type": "Feature",
  "properties": {
    "iso:country":"DE",
    "sg:address":"Ribnitzer Str. 41",
    "sg:city":"Berlin",
    "sg:phone":"+49 30/9291069",
    "sg:postcode":"13051",
    "sg:province":"Berlin",
    "wof:name":"Roland Hanke",
    "wof:placetype":"venue"
},
  "geometry": {"coordinates":[13.4934549332,52.5673599243],"type":"Point"}
}