{
  "type": "Feature",
  "properties": {
    "iso:country":"DE",
    "sg:address":"Talstr. 7",
    "sg:city":"Sasbachwalden",
    "sg:phone":"+49 7841/21762",
    "sg:postcode":"77887",
    "sg:province":"Baden-W\u00fcrttemberg",
    "wof:name":"Haus Tal 7",
    "wof:placetype":"venue"
},
  "geometry": {"coordinates":[8.1246118546,48.6194839478],"type":"Point"}
}