{
  "type": "Feature",
  "properties": {
    "iso:country":"DE",
    "sg:address":"Denninger Str. 100",
    "sg:city":"M\u00fcnchen",
    "sg:phone":"+49 89/916524",
    "sg:postcode":"81925",
    "sg:province":"Bayern",
    "wof:name":"Helmut Haucke Architekt",
    "wof:placetype":"venue"
},
  "geometry": {"coordinates":[11.620596,48.148563],"type":"Point"}
}