{
  "type": "Feature",
  "properties": {
    "iso:country":"DE",
    "sg:address":"Mozartstr. 3",
    "sg:city":"Reken",
    "sg:phone":"+49 2864/2837",
    "sg:postcode":"48734",
    "sg:province":"Nordrhein-Westfalen",
    "wof:name":"Ho-auto-modell-club E. V. J\u00fcrgen Freidank",
    "wof:placetype":"venue"
},
  "geometry": {"coordinates":[7.0495138168,51.826675415],"type":"Point"}
}