{
  "type": "Feature",
  "properties": {
    "iso:country":"DE",
    "sg:address":"Bergstr. 21",
    "sg:city":"Seeheim-Jugenheim",
    "sg:phone":"+49 6257/962696",
    "sg:postcode":"64342",
    "sg:province":"Hessen",
    "wof:name":"W. Deuker Immobilienmakler",
    "wof:placetype":"venue"
},
  "geometry": {"coordinates":[8.6472854614,49.7636795044],"type":"Point"}
}