{
  "type": "Feature",
  "properties": {
    "iso:country":"DE",
    "sg:address":"Treskowallee 129",
    "sg:city":"Berlin",
    "sg:phone":"+49 30/500170",
    "sg:postcode":"10318",
    "sg:province":"Berlin",
    "wof:name":"Casino Trabrennbahn",
    "wof:placetype":"venue"
},
  "geometry": {"coordinates":[13.5247449875,52.4780158997],"type":"Point"}
}