{
  "type": "Feature",
  "properties": {
    "iso:country":"DE",
    "sg:address":"Altrheinstr. 9",
    "sg:city":"Worms",
    "sg:postcode":"67550",
    "sg:province":"Rheinland-Pfalz",
    "wof:name":"Fiege Immobilienbeteiligungs- Gesellschaft Worms Mbh",
    "wof:placetype":"venue"
},
  "geometry": {"coordinates":[8.3493461609,49.6892318726],"type":"Point"}
}