{
  "type": "Feature",
  "properties": {
    "iso:country":"DE",
    "sg:address":"Zehntenhofstr 14-16",
    "sg:city":"Wiesbaden",
    "sg:phone":"+49 611/2386750",
    "sg:postcode":"65201",
    "sg:province":"Hessen",
    "wof:name":"Dallmann & Co Fabrik Pharm. Pr\u00e4parate Gmbh",
    "wof:placetype":"venue"
},
  "geometry": {"coordinates":[8.1932268143,50.0429267883],"type":"Point"}
}