{
  "type": "Feature",
  "properties": {
    "iso:country":"DE",
    "sg:address":"Sch\u00fctzenstr. 28",
    "sg:city":"Weilheim",
    "sg:phone":"+49 881/49050",
    "sg:postcode":"82362",
    "sg:province":"Bayern",
    "wof:name":"Ristorante Schie\u00dfst\u00e4tte",
    "wof:placetype":"venue"
},
  "geometry": {"coordinates":[11.1383247375,47.8427772522],"type":"Point"}
}