{
  "type": "Feature",
  "properties": {
    "iso:country":"DE",
    "sg:address":"Schweinfurter Str. 5",
    "sg:city":"Niederwerrn",
    "sg:phone":"+49 9721/803813",
    "sg:postcode":"97464",
    "sg:province":"Bayern",
    "wof:name":"Time-live",
    "wof:placetype":"venue"
},
  "geometry": {"coordinates":[10.1728076935,50.0632591248],"type":"Point"}
}