{
  "type": "Feature",
  "properties": {
    "iso:country":"DE",
    "sg:address":"Bahnhofstr. 4",
    "sg:city":"Henfenfeld",
    "sg:phone":"+49 9151/6283",
    "sg:postcode":"91239",
    "sg:province":"Bayern",
    "wof:name":"Br\u00e4ust\u00fcberl",
    "wof:placetype":"venue"
},
  "geometry": {"coordinates":[11.3900947571,49.5008239746],"type":"Point"}
}