{
  "type": "Feature",
  "properties": {
    "iso:country":"DE",
    "sg:address":"Schliemannstr. 23",
    "sg:city":"Berlin",
    "sg:phone":"+49 30/4471080",
    "sg:postcode":"10437",
    "sg:province":"Berlin",
    "wof:name":"Robert-havemann-archiv Und Matthias-domaschk-archiv",
    "wof:placetype":"venue"
},
  "geometry": {"coordinates":[13.421046,52.544727],"type":"Point"}
}