{
  "type": "Feature",
  "properties": {
    "iso:country":"DE",
    "sg:address":"Behringstr. 2",
    "sg:city":"Berlin",
    "sg:postcode":"12437",
    "sg:province":"Berlin",
    "wof:name":"Konsum",
    "wof:placetype":"venue"
},
  "geometry": {"coordinates":[13.489279747,52.4669456482],"type":"Point"}
}