{
  "type": "Feature",
  "properties": {
    "iso:country":"DE",
    "sg:address":"Klosterstr. 9",
    "sg:city":"Nordhorn",
    "sg:phone":"+49 5921/34051",
    "sg:postcode":"48527",
    "sg:province":"Niedersachsen",
    "wof:name":"Stiftung Kloster Frenswegen",
    "wof:placetype":"venue"
},
  "geometry": {"coordinates":[7.0380368233,52.4548110962],"type":"Point"}
}