{
  "type": "Feature",
  "properties": {
    "iso:country":"DE",
    "sg:address":"Darmst\u00e4dter Landstr. 64",
    "sg:city":"Ginsheim-Gustavsburg",
    "sg:phone":"+49 6134/51283",
    "sg:postcode":"65462",
    "sg:province":"Hessen",
    "wof:name":"Burgklause",
    "wof:placetype":"venue"
},
  "geometry": {"coordinates":[8.3215560913,49.9967536926],"type":"Point"}
}