{
  "type": "Feature",
  "properties": {
    "iso:country":"DE",
    "sg:address":"Untere Dorfstr. 5",
    "sg:city":"Kirchdorf",
    "sg:postcode":"85414",
    "sg:province":"Bayern",
    "wof:name":"Schmidt Und Preisinger Gmbh",
    "wof:placetype":"venue"
},
  "geometry": {"coordinates":[11.674959,48.455788],"type":"Point"}
}