{
  "type": "Feature",
  "properties": {
    "iso:country":"DE",
    "sg:address":"Zu den Erlen 57",
    "sg:city":"Duisburg",
    "sg:phone":"+49 203/7127939",
    "sg:postcode":"47269",
    "sg:province":"Nordrhein-Westfalen",
    "wof:name":"Securitas Versicherung Werner Kernig",
    "wof:placetype":"venue"
},
  "geometry": {"coordinates":[6.7836270332,51.3667984009],"type":"Point"}
}