{
  "type": "Feature",
  "properties": {
    "iso:country":"DE",
    "sg:address":"Hermann-Hesse-Str. 26",
    "sg:city":"Berlin",
    "sg:phone":"+49 30/4772918",
    "sg:postcode":"13156",
    "sg:province":"Berlin",
    "wof:name":"Dieter Boeck",
    "wof:placetype":"venue"
},
  "geometry": {"coordinates":[13.398946,52.580242],"type":"Point"}
}