{
  "type": "Feature",
  "properties": {
    "iso:country":"DE",
    "sg:address":"Palmaille 71",
    "sg:city":"Hamburg",
    "sg:phone":"+49 40/380320",
    "sg:postcode":"22767",
    "sg:province":"Hamburg",
    "wof:name":"Bau-verein Zu Hamburg Eigenheim-immobilien Gmbh",
    "wof:placetype":"venue"
},
  "geometry": {"coordinates":[9.9372358322,53.5460891724],"type":"Point"}
}