{
  "type": "Feature",
  "properties": {
    "iso:country":"DE",
    "sg:address":"Marienhook 33",
    "sg:city":"Vreden",
    "sg:phone":"+49 2564/97811",
    "sg:postcode":"48691",
    "sg:province":"Nordrhein-Westfalen",
    "wof:name":"Tenhumberg",
    "wof:placetype":"venue"
},
  "geometry": {"coordinates":[6.7898578644,52.029510498],"type":"Point"}
}