{
  "type": "Feature",
  "properties": {
    "iso:country":"DE",
    "sg:address":"Barbussestr. 37",
    "sg:city":"Leipzig",
    "sg:phone":"+49 341/4247911",
    "sg:postcode":"04249",
    "sg:province":"Sachsen",
    "wof:name":"Doris Busch",
    "wof:placetype":"venue"
},
  "geometry": {"coordinates":[12.319645,51.305614],"type":"Point"}
}