{
  "type": "Feature",
  "properties": {
    "iso:country":"DE",
    "sg:address":"Spitalgasse 1 a",
    "sg:city":"Stadtsteinach",
    "sg:phone":"+49 9225/700",
    "sg:postcode":"95346",
    "sg:province":"Bayern",
    "wof:name":"Feco Trading Gmbh",
    "wof:placetype":"venue"
},
  "geometry": {"coordinates":[11.506196,50.158276],"type":"Point"}
}