{
  "type": "Feature",
  "properties": {
    "iso:country":"DE",
    "sg:address":"Cappenberger Str. 42",
    "sg:city":"Nordkirchen",
    "sg:phone":"+49 2596/2447",
    "sg:postcode":"59394",
    "sg:province":"Nordrhein-Westfalen",
    "wof:name":"Friedrich Uhlenbrock",
    "wof:placetype":"venue"
},
  "geometry": {"coordinates":[7.551233,51.701958],"type":"Point"}
}