{
  "type": "Feature",
  "properties": {
    "iso:country":"DE",
    "sg:address":"Morassistr. 4",
    "sg:city":"M\u00fcnchen",
    "sg:postcode":"80469",
    "sg:province":"Bayern",
    "wof:name":"W. Burri E. K.",
    "wof:placetype":"venue"
},
  "geometry": {"coordinates":[11.5829620361,48.1327400208],"type":"Point"}
}