{
  "type": "Feature",
  "properties": {
    "iso:country":"DE",
    "sg:address":"Ofenerdieker Str. 34 b",
    "sg:city":"Oldenburg",
    "sg:phone":"+49 441/602956",
    "sg:postcode":"26125",
    "sg:province":"Niedersachsen",
    "wof:name":"M. Harfst",
    "wof:placetype":"venue"
},
  "geometry": {"coordinates":[8.202415,53.18782],"type":"Point"}
}