{
  "type": "Feature",
  "properties": {
    "iso:country":"DE",
    "sg:address":"Reiherwerder",
    "sg:city":"Berlin",
    "sg:postcode":"13505",
    "sg:province":"Berlin",
    "wof:name":"Deutsche Stiftung F\u00fcr Int. Entwicklung",
    "wof:placetype":"venue"
},
  "geometry": {"coordinates":[13.2269515991,52.585193634],"type":"Point"}
}