{
  "type": "Feature",
  "properties": {
    "iso:country":"DE",
    "sg:address":"Erlbacher Str. 12",
    "sg:city":"Markneukirchen",
    "sg:phone":"+49 37422/45796",
    "sg:postcode":"08258",
    "sg:province":"Sachsen",
    "wof:name":"Albert N\u00fcrnberger",
    "wof:placetype":"venue"
},
  "geometry": {"coordinates":[12.3356523514,50.3106651306],"type":"Point"}
}