{
  "type": "Feature",
  "properties": {
    "iso:country":"DE",
    "sg:address":"B\u00f6hringer Str.",
    "sg:city":"Radolfzell",
    "sg:phone":"+49 7732/3317",
    "sg:postcode":"78315",
    "sg:province":"Baden-W\u00fcrttemberg",
    "wof:name":"Hotel Garni G\u00e4stehaus Rickelshausen",
    "wof:placetype":"venue"
},
  "geometry": {"coordinates":[8.9631071091,47.7429618835],"type":"Point"}
}