{
  "type": "Feature",
  "properties": {
    "iso:country":"DE",
    "sg:address":"Burgstr. 49-51",
    "sg:city":"Salzwedel",
    "sg:phone":"+49 3901/422663",
    "sg:postcode":"29410",
    "sg:province":"Sachsen-Anhalt",
    "wof:name":"Das Herrenfachgeschg\u00e4ft Fritz Weiland",
    "wof:placetype":"venue"
},
  "geometry": {"coordinates":[11.1523551941,52.851108551],"type":"Point"}
}