{
  "type": "Feature",
  "properties": {
    "iso:country":"DE",
    "sg:address":"Graf-Adolf-Str. 4",
    "sg:city":"D\u00fcsseldorf",
    "sg:phone":"+49 211/375085",
    "sg:postcode":"40212",
    "sg:province":"Nordrhein-Westfalen",
    "wof:name":"Brillen Mauk Gmbh",
    "wof:placetype":"venue"
},
  "geometry": {"coordinates":[6.7791900635,51.2189903259],"type":"Point"}
}