{
  "type": "Feature",
  "properties": {
    "iso:country":"DE",
    "sg:address":"Schramberger Str. 68",
    "sg:city":"Lauterbach",
    "sg:phone":"+49 7422/92320",
    "sg:postcode":"78730",
    "sg:province":"Baden-W\u00fcrttemberg",
    "wof:name":"E. Pfaff Mech. Werkstatt",
    "wof:placetype":"venue"
},
  "geometry": {"coordinates":[8.357588,48.22562],"type":"Point"}
}