{
  "type": "Feature",
  "properties": {
    "iso:country":"DE",
    "sg:address":"Altenderner Str. 158",
    "sg:city":"Dortmund",
    "sg:phone":"+49 231/890410",
    "sg:postcode":"44329",
    "sg:province":"Nordrhein-Westfalen",
    "wof:name":"J\u00e4gerhof",
    "wof:placetype":"venue"
},
  "geometry": {"coordinates":[7.5076642036,51.5730133057],"type":"Point"}
}