{
  "type": "Feature",
  "properties": {
    "iso:country":"DE",
    "sg:address":"L\u00f6wentaler Str 3",
    "sg:city":"Friedrichshafen",
    "sg:phone":"+49 7541/300220",
    "sg:postcode":"88046",
    "sg:province":"Baden-W\u00fcrttemberg",
    "wof:name":"Landesgirokasse \u00f6ffentliche Bank",
    "wof:placetype":"venue"
},
  "geometry": {"coordinates":[9.476405,47.651951],"type":"Point"}
}