{
  "type": "Feature",
  "properties": {
    "iso:country":"DE",
    "sg:address":"Sanddornweg 3",
    "sg:city":"Bad Hersfeld",
    "sg:phone":"+49 6621/15600",
    "sg:postcode":"36251",
    "sg:province":"Hessen",
    "wof:name":"Ev. Pfarramt Johannes-eichhof-kirchen Gem",
    "wof:placetype":"venue"
},
  "geometry": {"coordinates":[9.7022008896,50.8453598022],"type":"Point"}
}