{
  "type": "Feature",
  "properties": {
    "iso:country":"DE",
    "sg:address":"Niddastr. 2",
    "sg:city":"Karben",
    "sg:phone":"+49 6039/7504",
    "sg:postcode":"61184",
    "sg:province":"Hessen",
    "wof:name":"Norbert Rust",
    "wof:placetype":"venue"
},
  "geometry": {"coordinates":[8.753692627,50.2463569641],"type":"Point"}
}