{
  "type": "Feature",
  "properties": {
    "iso:country":"DE",
    "sg:address":"Brahmsstr. 18",
    "sg:city":"Senden",
    "sg:phone":"+49 7307/932220",
    "sg:postcode":"89250",
    "sg:province":"Bayern",
    "wof:name":"Gert Weiler",
    "wof:placetype":"venue"
},
  "geometry": {"coordinates":[10.0452194214,48.3262901306],"type":"Point"}
}