{
  "type": "Feature",
  "properties": {
    "iso:country":"DE",
    "sg:address":"M\u00fcnchner Str. 3 a",
    "sg:city":"Bad Aibling",
    "sg:phone":"+49 8061/2688",
    "sg:postcode":"83043",
    "sg:province":"Bayern",
    "wof:name":"H. P. Rott",
    "wof:placetype":"venue"
},
  "geometry": {"coordinates":[12.0084972382,47.8642539978],"type":"Point"}
}