{
  "type": "Feature",
  "properties": {
    "iso:country":"DE",
    "sg:address":"Auf der H\u00f6he 13",
    "sg:city":"R\u00f6ttenbach",
    "sg:phone":"+49 9195/993410",
    "sg:postcode":"91341",
    "sg:province":"Bayern",
    "wof:name":"Comfort B\u00fcro F\u00fcr Kommunikation Und Fortbildung E. K.",
    "wof:placetype":"venue"
},
  "geometry": {"coordinates":[10.92994,49.665329],"type":"Point"}
}