{
  "type": "Feature",
  "properties": {
    "iso:country":"DE",
    "sg:address":"Kurpfalzstr. 57",
    "sg:city":"Sinsheim",
    "sg:phone":"+49 7261/13595",
    "sg:postcode":"74889",
    "sg:province":"Baden-W\u00fcrttemberg",
    "wof:name":"Dr. Hans-j\u00f6rg Finck Tierarzt",
    "wof:placetype":"venue"
},
  "geometry": {"coordinates":[8.8938322067,49.2539558411],"type":"Point"}
}