{
  "type": "Feature",
  "properties": {
    "iso:country":"DE",
    "sg:address":"Heinrichstr. 14",
    "sg:city":"Gladbeck",
    "sg:phone":"+49 2043/681679",
    "sg:postcode":"45964",
    "sg:province":"Nordrhein-Westfalen",
    "wof:name":"B. Arda",
    "wof:placetype":"venue"
},
  "geometry": {"coordinates":[6.9989027977,51.574546814],"type":"Point"}
}