{
  "type": "Feature",
  "properties": {
    "iso:country":"DE",
    "sg:address":"Hauptstr. 10",
    "sg:city":"Mutzschen",
    "sg:phone":"+49 34385/51341",
    "sg:postcode":"04688",
    "sg:province":"Sachsen",
    "wof:name":"Werner D\u00f6ge",
    "wof:placetype":"venue"
},
  "geometry": {"coordinates":[12.889715,51.260799],"type":"Point"}
}