{
  "type": "Feature",
  "properties": {
    "iso:country":"DE",
    "sg:address":"Warburger Str. 91",
    "sg:city":"Paderborn",
    "sg:phone":"+49 5251/64590",
    "sg:postcode":"33098",
    "sg:province":"Nordrhein-Westfalen",
    "wof:name":"Bistro Salue",
    "wof:placetype":"venue"
},
  "geometry": {"coordinates":[8.7729549408,51.7115287781],"type":"Point"}
}