{
  "type": "Feature",
  "properties": {
    "iso:country":"DE",
    "sg:address":"Badgasse 9",
    "sg:city":"Wertingen",
    "sg:phone":"+49 8272/4044",
    "sg:postcode":"86637",
    "sg:province":"Bayern",
    "wof:name":"Leonhard Kirner",
    "wof:placetype":"venue"
},
  "geometry": {"coordinates":[10.6820411682,48.560382843],"type":"Point"}
}