{
  "type": "Feature",
  "properties": {
    "iso:country":"DE",
    "sg:address":"Rathausstr. 22",
    "sg:city":"V\u00f6lklingen",
    "sg:phone":"+49 6898/22124",
    "sg:postcode":"66333",
    "sg:province":"Saarland",
    "wof:name":"Kath. Pfarramt St. Eligius",
    "wof:placetype":"venue"
},
  "geometry": {"coordinates":[6.8534870148,49.24949646],"type":"Point"}
}