{
  "type": "Feature",
  "properties": {
    "iso:country":"DE",
    "sg:address":"Herbergerweg 1-3",
    "sg:city":"Berlin",
    "sg:phone":"+49 30/8156087",
    "sg:postcode":"14167",
    "sg:province":"Berlin",
    "wof:name":"Bodenstein & Schnitzer Gmbh",
    "wof:placetype":"venue"
},
  "geometry": {"coordinates":[13.2602577209,52.4301681519],"type":"Point"}
}