{
  "type": "Feature",
  "properties": {
    "iso:country":"DE",
    "sg:address":"Eichelberger Weg 4",
    "sg:city":"Gorxheimertal",
    "sg:phone":"+49 6201/292330",
    "sg:postcode":"69517",
    "sg:province":"Hessen",
    "wof:name":"Hms Hoga Management Systems Edv-systeme F\u00fcr Hotels Und",
    "wof:placetype":"venue"
},
  "geometry": {"coordinates":[8.722779274,49.536895752],"type":"Point"}
}