{
  "type": "Feature",
  "properties": {
    "iso:country":"DE",
    "sg:address":"Leintalstr. 4",
    "sg:city":"Schwaigern",
    "sg:phone":"+49 7138/6583",
    "sg:postcode":"74193",
    "sg:province":"Baden-W\u00fcrttemberg",
    "wof:name":"Otto Heuser",
    "wof:placetype":"venue"
},
  "geometry": {"coordinates":[8.985868,49.111694],"type":"Point"}
}