{
  "type": "Feature",
  "properties": {
    "iso:country":"DE",
    "sg:address":"Hauptstr. 71",
    "sg:city":"Elze",
    "sg:phone":"+49 5068/4055",
    "sg:postcode":"31008",
    "sg:province":"Niedersachsen",
    "wof:name":"Reiseb\u00fcro Tico D\u00f6rrie Und Henne",
    "wof:placetype":"venue"
},
  "geometry": {"coordinates":[9.7361412048,52.1208648682],"type":"Point"}
}