{
  "type": "Feature",
  "properties": {
    "iso:country":"DE",
    "sg:address":"Markt 12",
    "sg:city":"Schweinfurt",
    "sg:phone":"+49 9721/21937",
    "sg:postcode":"97421",
    "sg:province":"Bayern",
    "wof:name":"Leo Becker",
    "wof:placetype":"venue"
},
  "geometry": {"coordinates":[10.2346725464,50.0453605652],"type":"Point"}
}