{
  "type": "Feature",
  "properties": {
    "iso:country":"DE",
    "sg:address":"Rolandstr. 127",
    "sg:city":"Oberhausen",
    "sg:phone":"+49 208/867107",
    "sg:postcode":"46047",
    "sg:province":"Nordrhein-Westfalen",
    "wof:name":"Heinz B\u00fcrgel Architekt",
    "wof:placetype":"venue"
},
  "geometry": {"coordinates":[6.874453,51.467648],"type":"Point"}
}