{
  "type": "Feature",
  "properties": {
    "iso:country":"DE",
    "sg:address":"Feldstr. 13b",
    "sg:city":"T\u00fcrkheim",
    "sg:phone":"+49 8245/90110",
    "sg:postcode":"86842",
    "sg:province":"Bayern",
    "wof:name":"Publicity Folien- Beschriftung Gmbh",
    "wof:placetype":"venue"
},
  "geometry": {"coordinates":[10.6381292343,48.0303077698],"type":"Point"}
}