{
  "type": "Feature",
  "properties": {
    "iso:country":"DE",
    "sg:address":"Bergstr. 4",
    "sg:city":"Klietz",
    "sg:phone":"+49 39327/293",
    "sg:postcode":"39524",
    "sg:province":"Sachsen-Anhalt",
    "wof:name":"Wolfgang Glaser",
    "wof:placetype":"venue"
},
  "geometry": {"coordinates":[12.06548,52.667103],"type":"Point"}
}