{
  "type": "Feature",
  "properties": {
    "iso:country":"DE",
    "sg:address":"Stolzenroth 13",
    "sg:city":"Pommersfelden",
    "sg:phone":"+49 9548/458",
    "sg:postcode":"96178",
    "sg:province":"Bayern",
    "wof:name":"Ingrid Forner",
    "wof:placetype":"venue"
},
  "geometry": {"coordinates":[10.79488,49.76329],"type":"Point"}
}