{
  "type": "Feature",
  "properties": {
    "iso:country":"DE",
    "sg:address":"Lindenplatz 11",
    "sg:city":"R\u00fcdersdorf",
    "sg:postcode":"07586",
    "sg:province":"Th\u00fcringen",
    "wof:name":"Keilhauer & Uhlig Gmbh",
    "wof:placetype":"venue"
},
  "geometry": {"coordinates":[11.9814395905,50.9090805054],"type":"Point"}
}