{
  "type": "Feature",
  "properties": {
    "iso:country":"DE",
    "sg:address":"Holm 58",
    "sg:city":"Flensburg",
    "sg:phone":"+49 461/1404200",
    "sg:postcode":"24937",
    "sg:province":"Schleswig-Holstein",
    "wof:name":"Manfred Ehler Optiker",
    "wof:placetype":"venue"
},
  "geometry": {"coordinates":[9.435503006,54.7840576172],"type":"Point"}
}