{
  "type": "Feature",
  "properties": {
    "iso:country":"DE",
    "sg:address":"Hintergasse 28",
    "sg:city":"Rodgau",
    "sg:phone":"+49 6106/646581",
    "sg:postcode":"63110",
    "sg:province":"Hessen",
    "wof:name":"Evas Dessous",
    "wof:placetype":"venue"
},
  "geometry": {"coordinates":[8.88476,50.025715],"type":"Point"}
}