{
  "type": "Feature",
  "properties": {
    "iso:country":"DE",
    "sg:address":"Kirchstr. 12",
    "sg:city":"Troisdorf",
    "sg:phone":"+49 2241/73280",
    "sg:postcode":"53840",
    "sg:province":"Nordrhein-Westfalen",
    "wof:name":"Michael Baumgarten Massagepraxis",
    "wof:placetype":"venue"
},
  "geometry": {"coordinates":[7.164086,50.813927],"type":"Point"}
}