{
  "type": "Feature",
  "properties": {
    "iso:country":"DE",
    "sg:address":"Trierer Str. 1",
    "sg:city":"Weiskirchen",
    "sg:phone":"+49 6876/252",
    "sg:postcode":"66709",
    "sg:province":"Saarland",
    "wof:name":"Gerhard Johann",
    "wof:placetype":"venue"
},
  "geometry": {"coordinates":[6.8226161003,49.5549316406],"type":"Point"}
}