{
  "type": "Feature",
  "properties": {
    "iso:country":"DE",
    "sg:address":"Oberwies 14",
    "sg:city":"P\u00fcttlingen",
    "sg:phone":"+49 6806/44426",
    "sg:postcode":"66346",
    "sg:province":"Saarland",
    "wof:name":"Alfred Stein",
    "wof:placetype":"venue"
},
  "geometry": {"coordinates":[6.9067292213,49.2935714722],"type":"Point"}
}