{
  "type": "Feature",
  "properties": {
    "iso:country":"DE",
    "sg:address":"Siekkamp 1a",
    "sg:city":"Hamburg",
    "sg:phone":"+49 40/6017081",
    "sg:postcode":"22393",
    "sg:province":"Hamburg",
    "wof:name":"Jungius & Boldt Inh. Peter Boldt",
    "wof:placetype":"venue"
},
  "geometry": {"coordinates":[10.1161909103,53.6542510986],"type":"Point"}
}