{
  "type": "Feature",
  "properties": {
    "iso:country":"DE",
    "sg:address":"Kerpener Str. 74",
    "sg:city":"Elsdorf",
    "sg:phone":"+49 2274/2023",
    "sg:postcode":"50189",
    "sg:province":"Nordrhein-Westfalen",
    "wof:name":"Franz Ehser",
    "wof:placetype":"venue"
},
  "geometry": {"coordinates":[6.587604,50.92181],"type":"Point"}
}