{
  "type": "Feature",
  "properties": {
    "iso:country":"DE",
    "sg:address":"Hellerstr. 17",
    "sg:city":"Herdorf",
    "sg:phone":"+49 2741/4685",
    "sg:postcode":"57562",
    "sg:province":"Rheinland-Pfalz",
    "wof:name":"Papita",
    "wof:placetype":"venue"
},
  "geometry": {"coordinates":[7.945725,50.77906],"type":"Point"}
}