{
  "type": "Feature",
  "properties": {
    "iso:country":"DE",
    "sg:address":"Roncalliplatz 4",
    "sg:city":"K\u00f6ln",
    "sg:phone":"+49 221/2214438",
    "sg:postcode":"50667",
    "sg:province":"Nordrhein-Westfalen",
    "wof:name":"R\u00f6misches-germanisches Museum",
    "wof:placetype":"venue"
},
  "geometry": {"coordinates":[6.958312,50.940395],"type":"Point"}
}