{
  "type": "Feature",
  "properties": {
    "iso:country":"DE",
    "sg:address":"Hauptstr. 28",
    "sg:city":"K\u00f6nigswartha",
    "sg:phone":"+49 35931/20426",
    "sg:postcode":"02699",
    "sg:province":"Sachsen",
    "wof:name":"Dietmar Rachel",
    "wof:placetype":"venue"
},
  "geometry": {"coordinates":[14.3291349411,51.3102111816],"type":"Point"}
}