{
  "type": "Feature",
  "properties": {
    "iso:country":"DE",
    "sg:address":"M\u00f6gglinger Str. 46",
    "sg:city":"B\u00f6bingen",
    "sg:phone":"+49 7173/6224",
    "sg:postcode":"73560",
    "sg:province":"Baden-W\u00fcrttemberg",
    "wof:name":"Bopp Landmaschinen Forst- Und Gartentechnik E. K.",
    "wof:placetype":"venue"
},
  "geometry": {"coordinates":[9.926515,48.821396],"type":"Point"}
}