{
  "type": "Feature",
  "properties": {
    "iso:country":"DE",
    "sg:address":"M\u00fcnsterstr. 34",
    "sg:city":"Rheine",
    "sg:phone":"+49 5971/2082",
    "sg:postcode":"48431",
    "sg:province":"Nordrhein-Westfalen",
    "wof:name":"H. Und H. Koch",
    "wof:placetype":"venue"
},
  "geometry": {"coordinates":[7.4404268265,52.2775421143],"type":"Point"}
}