{
  "type": "Feature",
  "properties": {
    "iso:country":"DE",
    "sg:address":"St.-Georg-Platz 9",
    "sg:city":"Bocholt",
    "sg:postcode":"46399",
    "sg:province":"Nordrhein-Westfalen",
    "wof:name":"Zentralargentur Der Katholischen Kirchengemeinde",
    "wof:placetype":"venue"
},
  "geometry": {"coordinates":[6.6136732101,51.8375244141],"type":"Point"}
}