{
  "type": "Feature",
  "properties": {
    "iso:country":"DE",
    "sg:address":"Freudenst\u00e4dter Str. 2",
    "sg:city":"Enzkl\u00f6sterle",
    "sg:phone":"+49 7085/7565",
    "sg:postcode":"75337",
    "sg:province":"Baden-W\u00fcrttemberg",
    "wof:name":"Kl\u00f6sterle",
    "wof:placetype":"venue"
},
  "geometry": {"coordinates":[8.473169,48.666534],"type":"Point"}
}