{
  "type": "Feature",
  "properties": {
    "iso:country":"DE",
    "sg:address":"Albstr. 59c",
    "sg:city":"Stuttgart",
    "sg:phone":"+49 711/760184",
    "sg:postcode":"70597",
    "sg:province":"Baden-W\u00fcrttemberg",
    "wof:name":"Rainer Wehr Kunstmaler",
    "wof:placetype":"venue"
},
  "geometry": {"coordinates":[9.165559,48.742992],"type":"Point"}
}