{
  "type": "Feature",
  "properties": {
    "iso:country":"DE",
    "sg:address":"Hintergasse 39",
    "sg:city":"Rohrbach",
    "sg:phone":"+49 6349/990990",
    "sg:postcode":"76865",
    "sg:province":"Rheinland-Pfalz",
    "wof:name":"Fu\u00df Brezelb\u00e4ckerei Gmbh",
    "wof:placetype":"venue"
},
  "geometry": {"coordinates":[8.131062,49.137878],"type":"Point"}
}