{
  "type": "Feature",
  "properties": {
    "iso:country":"DE",
    "sg:address":"Pfarrgasse 10",
    "sg:city":"Oettingen",
    "sg:phone":"+49 9082/2281",
    "sg:postcode":"86732",
    "sg:province":"Bayern",
    "wof:name":"Kath. Pfarramt St. Sebastian",
    "wof:placetype":"venue"
},
  "geometry": {"coordinates":[10.6049003601,48.9533424377],"type":"Point"}
}