{
  "type": "Feature",
  "properties": {
    "iso:country":"DE",
    "sg:address":"Ahrensburger Str. 81",
    "sg:city":"Hamburg",
    "sg:phone":"+49 40/6561617",
    "sg:postcode":"22041",
    "sg:province":"Hamburg",
    "wof:name":"Erich Vesting Innenarchitekt",
    "wof:placetype":"venue"
},
  "geometry": {"coordinates":[10.099273,53.579365],"type":"Point"}
}