{
  "type": "Feature",
  "properties": {
    "iso:country":"DE",
    "sg:address":"Einfelder Str. 62",
    "sg:city":"Neum\u00fcnster",
    "sg:phone":"+49 4321/52564",
    "sg:postcode":"24536",
    "sg:province":"Schleswig-Holstein",
    "wof:name":"Apotheke Dietlinde Herbst",
    "wof:placetype":"venue"
},
  "geometry": {"coordinates":[9.990814,54.123116],"type":"Point"}
}