{
  "type": "Feature",
  "properties": {
    "iso:country":"DE",
    "sg:address":"Sch\u00f6nau 1",
    "sg:city":"Steinbach",
    "sg:phone":"+49 9263/7891",
    "sg:postcode":"96361",
    "sg:province":"Bayern",
    "wof:name":"Pub-spielhalle Esendi",
    "wof:placetype":"venue"
},
  "geometry": {"coordinates":[11.3609933853,50.4327812195],"type":"Point"}
}