{
  "type": "Feature",
  "properties": {
    "iso:country":"DE",
    "sg:address":"Boddenblick 5a",
    "sg:city":"Insel Riems",
    "sg:phone":"+49 38351/70",
    "sg:postcode":"17498",
    "sg:province":"Mecklenburg-Vorpommern",
    "wof:name":"Bundesforschungsanstalt F\u00fcr Viruskrankheiten Der Tiere",
    "wof:placetype":"venue"
},
  "geometry": {"coordinates":[13.376079,54.119171],"type":"Point"}
}