{
  "type": "Feature",
  "properties": {
    "iso:country":"DE",
    "sg:address":"Prinzregentenplatz 15",
    "sg:city":"M\u00fcnchen",
    "sg:phone":"+49 89/4194650",
    "sg:postcode":"81675",
    "sg:province":"Bayern",
    "wof:name":"Dr. Andreas Zielcke Rechtsanwalt",
    "wof:placetype":"venue"
},
  "geometry": {"coordinates":[11.6068239212,48.1395835876],"type":"Point"}
}