{
  "type": "Feature",
  "properties": {
    "iso:country":"DE",
    "sg:address":"Am Gew\u00e4nde 14",
    "sg:city":"Unterwellenborn",
    "sg:phone":"+49 3671/67670",
    "sg:postcode":"07333",
    "sg:province":"Th\u00fcringen",
    "wof:name":"Wti Wissenschaftlich- Technisches Institut",
    "wof:placetype":"venue"
},
  "geometry": {"coordinates":[11.4403219223,50.6537590027],"type":"Point"}
}