{
  "type": "Feature",
  "properties": {
    "iso:country":"DE",
    "sg:address":"Auf dem Glockenberg 41",
    "sg:city":"Altenau",
    "sg:phone":"+49 5328/1273",
    "sg:postcode":"38707",
    "sg:province":"Niedersachsen",
    "wof:name":"D. T\u00f6pperwien",
    "wof:placetype":"venue"
},
  "geometry": {"coordinates":[10.4443902969,51.8005981445],"type":"Point"}
}