{
  "type": "Feature",
  "properties": {
    "iso:country":"DE",
    "sg:address":"Palmaille 67",
    "sg:city":"Hamburg",
    "sg:postcode":"22767",
    "sg:province":"Hamburg",
    "wof:name":"Verwaltung F\u00fcnfte Sachwert Rendite-fonds Holland Gmbh",
    "wof:placetype":"venue"
},
  "geometry": {"coordinates":[9.9376554489,53.5460853577],"type":"Point"}
}