{
  "type": "Feature",
  "properties": {
    "iso:country":"DE",
    "sg:address":"Vogteistr. 1",
    "sg:city":"Gummersbach",
    "sg:phone":"+49 2261/27279",
    "sg:postcode":"51647",
    "sg:province":"Nordrhein-Westfalen",
    "wof:name":"Im Rosengarten - Der Music-pub Mit Biergarten Im Bergischen !",
    "wof:placetype":"venue"
},
  "geometry": {"coordinates":[7.504650116,51.0295181274],"type":"Point"}
}