{
  "type": "Feature",
  "properties": {
    "iso:country":"DE",
    "sg:address":"Kurt-Hebach-Str. 5",
    "sg:city":"Mainz-Kastel",
    "sg:phone":"+49 6134/62150",
    "sg:postcode":"55252",
    "sg:province":"Hessen",
    "wof:name":"G + W - Wahler Der Modemarkt Gmbh",
    "wof:placetype":"venue"
},
  "geometry": {"coordinates":[8.2912101746,50.0202903748],"type":"Point"}
}