{
  "type": "Feature",
  "properties": {
    "iso:country":"DE",
    "sg:address":"Prenzlauer Str. 15",
    "sg:city":"Pasewalk",
    "sg:phone":"+49 3973/212247",
    "sg:postcode":"17309",
    "sg:province":"Mecklenburg-Vorpommern",
    "wof:name":"M. Lohde Und T. Israel Masseure",
    "wof:placetype":"venue"
},
  "geometry": {"coordinates":[13.98691,53.500973],"type":"Point"}
}