{
  "type": "Feature",
  "properties": {
    "iso:country":"DE",
    "sg:address":"Caseritzer Weg",
    "sg:city":"R\u00e4ckelwitz",
    "sg:phone":"+49 35796/96711",
    "sg:postcode":"01920",
    "sg:province":"Sachsen",
    "wof:name":"Freibad",
    "wof:placetype":"venue"
},
  "geometry": {"coordinates":[14.2278175354,51.2524414062],"type":"Point"}
}