{
  "type": "Feature",
  "properties": {
    "iso:country":"DE",
    "sg:address":"Stiekelriegweg 40",
    "sg:city":"Aurich",
    "sg:phone":"+49 4941/950786",
    "sg:postcode":"26607",
    "sg:province":"Niedersachsen",
    "wof:name":"Thomas Und Heike Langwald Anlageberater",
    "wof:placetype":"venue"
},
  "geometry": {"coordinates":[7.4685602188,53.5223693848],"type":"Point"}
}