{
  "type": "Feature",
  "properties": {
    "iso:country":"DE",
    "sg:address":"Hauptstr. 10",
    "sg:city":"Garmisch-Partenkirchen",
    "sg:phone":"+49 8821/2345",
    "sg:postcode":"82467",
    "sg:province":"Bayern",
    "wof:name":"Karosseriewerkst\u00e4tte Gruber Gmbh",
    "wof:placetype":"venue"
},
  "geometry": {"coordinates":[11.101874,47.501503],"type":"Point"}
}