{
  "type": "Feature",
  "properties": {
    "iso:country":"DE",
    "sg:address":"Ernst-Abbe-Str 20",
    "sg:city":"Mendig",
    "sg:phone":"+49 2652/5850",
    "sg:postcode":"56743",
    "sg:province":"Rheinland-Pfalz",
    "wof:name":"Amcor Pet Packaging Deutschland Gmbh",
    "wof:placetype":"venue"
},
  "geometry": {"coordinates":[7.2814488411,50.372543335],"type":"Point"}
}