{
  "type": "Feature",
  "properties": {
    "iso:country":"DE",
    "sg:address":"Antoniusstr. 5",
    "sg:city":"Reken",
    "sg:phone":"+49 2864/305",
    "sg:postcode":"48734",
    "sg:province":"Nordrhein-Westfalen",
    "wof:name":"Christa Handel",
    "wof:placetype":"venue"
},
  "geometry": {"coordinates":[7.0464601517,51.7872009277],"type":"Point"}
}