{
  "type": "Feature",
  "properties": {
    "iso:country":"DE",
    "sg:address":"Industriestr. 2",
    "sg:city":"Viernheim",
    "sg:phone":"+49 6204/9890",
    "sg:postcode":"68519",
    "sg:province":"Hessen",
    "wof:name":"Stadtwerke Viernheim Gmbh",
    "wof:placetype":"venue"
},
  "geometry": {"coordinates":[8.583393,49.544289],"type":"Point"}
}