{
  "type": "Feature",
  "properties": {
    "iso:country":"DE",
    "sg:address":"Goethestr. 16",
    "sg:city":"Klingenthal",
    "sg:phone":"+49 37467/22375",
    "sg:postcode":"08248",
    "sg:province":"Sachsen",
    "wof:name":"Bergst\u00fcbl",
    "wof:placetype":"venue"
},
  "geometry": {"coordinates":[12.497344017,50.3851623535],"type":"Point"}
}