{
  "type": "Feature",
  "properties": {
    "iso:country":"DE",
    "sg:address":"Kirchweg 17",
    "sg:city":"Lechbruck",
    "sg:phone":"+49 8862/8235",
    "sg:postcode":"86983",
    "sg:province":"Bayern",
    "wof:name":"Kath. Pfarramt Mari\u00e4 Heimsuchung",
    "wof:placetype":"venue"
},
  "geometry": {"coordinates":[10.7937908173,47.6985702515],"type":"Point"}
}