{
  "type": "Feature",
  "properties": {
    "iso:country":"DE",
    "sg:address":"Gartenstr. 2",
    "sg:city":"Bad Urach",
    "sg:phone":"+49 7125/7711",
    "sg:postcode":"72574",
    "sg:province":"Baden-W\u00fcrttemberg",
    "wof:name":"Falken",
    "wof:placetype":"venue"
},
  "geometry": {"coordinates":[9.4025144577,48.4907302856],"type":"Point"}
}