{
  "type": "Feature",
  "properties": {
    "iso:country":"DE",
    "sg:address":"Riester Weg 26",
    "sg:city":"Bramsche",
    "sg:phone":"+49 5461/4513",
    "sg:postcode":"49565",
    "sg:province":"Niedersachsen",
    "wof:name":"Kurt Diekmann",
    "wof:placetype":"venue"
},
  "geometry": {"coordinates":[7.979242,52.428024],"type":"Point"}
}