{
  "type": "Feature",
  "properties": {
    "iso:country":"DE",
    "sg:address":"Schenkenweg 7",
    "sg:city":"Neukirch",
    "sg:phone":"+49 35951/35270",
    "sg:postcode":"01904",
    "sg:province":"Sachsen",
    "wof:name":"Winfried Schmidt",
    "wof:placetype":"venue"
},
  "geometry": {"coordinates":[14.305168,51.095432],"type":"Point"}
}