{
  "type": "Feature",
  "properties": {
    "iso:country":"DE",
    "sg:address":"Falkenstr. 1",
    "sg:city":"Niederkassel",
    "sg:phone":"+49 2208/72727",
    "sg:postcode":"53859",
    "sg:province":"Nordrhein-Westfalen",
    "wof:name":"Maschenmoden Willy Loew",
    "wof:placetype":"venue"
},
  "geometry": {"coordinates":[7.0359139442,50.8333778381],"type":"Point"}
}