{
  "type": "Feature",
  "properties": {
    "iso:country":"DE",
    "sg:address":"Bussardweg 7",
    "sg:city":"Niederwinkling",
    "sg:phone":"+49 9962/555",
    "sg:postcode":"94559",
    "sg:province":"Bayern",
    "wof:name":"Friedrich Grill",
    "wof:placetype":"venue"
},
  "geometry": {"coordinates":[12.787159,48.889763],"type":"Point"}
}