{
  "type": "Feature",
  "properties": {
    "iso:country":"DE",
    "sg:address":"Etkar-Andre\u00b4-Stra\u00dfe Nr. 2",
    "sg:city":"Berlin",
    "sg:postcode":"12619",
    "sg:province":"Berlin",
    "wof:name":"Bowling-corso In Berlin-hellersdorf",
    "wof:placetype":"venue"
},
  "geometry": {"coordinates":[13.59107,52.529366],"type":"Point"}
}