{
  "type": "Feature",
  "properties": {
    "iso:country":"DE",
    "sg:address":"Herkulan-Schwaiger-Gasse 5",
    "sg:city":"Oberammergau",
    "sg:phone":"+49 8822/597",
    "sg:postcode":"82487",
    "sg:province":"Bayern",
    "wof:name":"Kath. Pfarramt St. Peter Und Paul",
    "wof:placetype":"venue"
},
  "geometry": {"coordinates":[11.0688772202,47.595500946],"type":"Point"}
}