{
  "type": "Feature",
  "properties": {
    "iso:country":"DE",
    "sg:address":"Berliner Str. 14",
    "sg:city":"Sande",
    "sg:phone":"+49 4422/4034",
    "sg:postcode":"26452",
    "sg:province":"Niedersachsen",
    "wof:name":"Bistro-pizzeria Mr. M. Pizzamann",
    "wof:placetype":"venue"
},
  "geometry": {"coordinates":[8.0213842392,53.4942817688],"type":"Point"}
}