{
  "type": "Feature",
  "properties": {
    "iso:country":"DE",
    "sg:address":"Langobardenstr.",
    "sg:city":"Regensburg",
    "sg:postcode":"93053",
    "sg:province":"Bayern",
    "wof:name":"Bauhaus Gmbh & Co. Kg",
    "wof:placetype":"venue"
},
  "geometry": {"coordinates":[12.115568161,48.9943275452],"type":"Point"}
}