{
  "type": "Feature",
  "properties": {
    "iso:country":"DE",
    "sg:address":"Meyers Tannen 38",
    "sg:city":"Papenburg",
    "sg:phone":"+49 4961/3248",
    "sg:postcode":"26871",
    "sg:province":"Niedersachsen",
    "wof:name":"Hermann Michels",
    "wof:placetype":"venue"
},
  "geometry": {"coordinates":[7.406277,53.069855],"type":"Point"}
}