{
  "type": "Feature",
  "properties": {
    "iso:country":"DE",
    "sg:address":"Peugenhammer 1",
    "sg:city":"Pleystein",
    "sg:phone":"+49 9654/262",
    "sg:postcode":"92714",
    "sg:province":"Bayern",
    "wof:name":"Hotel-restaurant Zottbachhaus",
    "wof:placetype":"venue"
},
  "geometry": {"coordinates":[12.3978681564,49.6590003967],"type":"Point"}
}