{
  "type": "Feature",
  "properties": {
    "iso:country":"DE",
    "sg:address":"Weserstr. 3-5",
    "sg:city":"H\u00f6xter",
    "sg:phone":"+49 5271/3999",
    "sg:postcode":"37671",
    "sg:province":"Nordrhein-Westfalen",
    "wof:name":"Altstadt Reiseb\u00fcro",
    "wof:placetype":"venue"
},
  "geometry": {"coordinates":[9.3816308975,51.7741165161],"type":"Point"}
}