{
  "type": "Feature",
  "properties": {
    "iso:country":"DE",
    "sg:address":"Ziegelstr. 12",
    "sg:city":"Osnabr\u00fcck",
    "sg:phone":"+49 541/3382410",
    "sg:postcode":"49088",
    "sg:province":"Niedersachsen",
    "wof:name":"Die Idee Versandhandel Beteiligungsgesellschaft Mbh",
    "wof:placetype":"venue"
},
  "geometry": {"coordinates":[8.046606,52.281414],"type":"Point"}
}