{
  "type": "Feature",
  "properties": {
    "iso:country":"DE",
    "sg:address":"M\u00f6llberger Heide 1",
    "sg:city":"Porta Westfalica",
    "sg:phone":"+49 5706/632",
    "sg:postcode":"32457",
    "sg:province":"Nordrhein-Westfalen",
    "wof:name":"Dieter Gloerfeld",
    "wof:placetype":"venue"
},
  "geometry": {"coordinates":[8.917468,52.20496],"type":"Point"}
}