{
  "type": "Feature",
  "properties": {
    "iso:country":"DE",
    "sg:address":"Wegscheider Str. 10",
    "sg:city":"Berlin",
    "sg:phone":"+49 30/35504550",
    "sg:postcode":"13587",
    "sg:province":"Berlin",
    "wof:name":"Tds Taxidienst In Spandau Gmbh",
    "wof:placetype":"venue"
},
  "geometry": {"coordinates":[13.2056760788,52.5567398071],"type":"Point"}
}