{
  "type": "Feature",
  "properties": {
    "iso:country":"DE",
    "sg:address":"Schlo\u00dfplatz 5",
    "sg:city":"Wiesent",
    "sg:phone":"+49 9482/1758",
    "sg:postcode":"93109",
    "sg:province":"Bayern",
    "wof:name":"Gastst\u00e4tte Franz Fichtl",
    "wof:placetype":"venue"
},
  "geometry": {"coordinates":[12.3788766861,49.0066833496],"type":"Point"}
}