{
  "type": "Feature",
  "properties": {
    "iso:country":"DE",
    "sg:address":"Stettiner Str. 19",
    "sg:city":"Ebermannstadt",
    "sg:phone":"+49 9194/796959",
    "sg:postcode":"91320",
    "sg:province":"Bayern",
    "wof:name":"B\u00e4rbel Stief",
    "wof:placetype":"venue"
},
  "geometry": {"coordinates":[11.1725301743,49.7729873657],"type":"Point"}
}