{
  "type": "Feature",
  "properties": {
    "iso:country":"DE",
    "sg:address":"Amalie-M\u00fcller-Str. 12",
    "sg:city":"B\u00fchl",
    "sg:postcode":"77815",
    "sg:province":"Baden-W\u00fcrttemberg",
    "wof:name":"Logo-bauberatungs Gmbh",
    "wof:placetype":"venue"
},
  "geometry": {"coordinates":[8.137373,48.68885],"type":"Point"}
}