{
  "type": "Feature",
  "properties": {
    "iso:country":"DE",
    "sg:address":"Harzstr. 16",
    "sg:city":"Salzgitter",
    "sg:phone":"+49 5341/27173",
    "sg:postcode":"38229",
    "sg:province":"Niedersachsen",
    "wof:name":"Prosys Software Gmbh",
    "wof:placetype":"venue"
},
  "geometry": {"coordinates":[10.4246044159,52.1225242615],"type":"Point"}
}