{
  "type": "Feature",
  "properties": {
    "iso:country":"DE",
    "sg:address":"Breite Str. 43 b",
    "sg:city":"Liepe",
    "sg:postcode":"14715",
    "sg:province":"Brandenburg",
    "wof:name":"Natur Fisch Gmbh & Co. Kg",
    "wof:placetype":"venue"
},
  "geometry": {"coordinates":[12.310669899,52.5195083618],"type":"Point"}
}