{
  "type": "Feature",
  "properties": {
    "iso:country":"DE",
    "sg:address":"Ziegeleiweg 2",
    "sg:city":"Hagen",
    "sg:phone":"+49 5405/98070",
    "sg:postcode":"49170",
    "sg:province":"Niedersachsen",
    "wof:name":"Bvg E. Niederste-hollenberg Baustoffvertriebsges.",
    "wof:placetype":"venue"
},
  "geometry": {"coordinates":[7.92019,52.211281],"type":"Point"}
}