{
  "type": "Feature",
  "properties": {
    "iso:country":"DE",
    "sg:address":"Robert-Mayer-Str. 17",
    "sg:city":"Frankfurt",
    "sg:phone":"+49 69/700756",
    "sg:postcode":"60486",
    "sg:province":"Hessen",
    "wof:name":"Restaurant Localino",
    "wof:placetype":"venue"
},
  "geometry": {"coordinates":[8.6483697891,50.1168556213],"type":"Point"}
}