{
  "type": "Feature",
  "properties": {
    "iso:country":"DE",
    "sg:address":"Moosweg 20",
    "sg:city":"Prien",
    "sg:phone":"+49 8051/61126",
    "sg:postcode":"83209",
    "sg:province":"Bayern",
    "wof:name":"Matthias K\u00fchnel Architekt",
    "wof:placetype":"venue"
},
  "geometry": {"coordinates":[12.357267,47.844425],"type":"Point"}
}