{
  "type": "Feature",
  "properties": {
    "iso:country":"DE",
    "sg:address":"An der Rietzschke 79",
    "sg:city":"Leipzig",
    "sg:postcode":"04288",
    "sg:province":"Sachsen",
    "wof:name":"Minol-suedtank Gmbh Vertragstankstelle 0414048",
    "wof:placetype":"venue"
},
  "geometry": {"coordinates":[12.4426870346,51.3159751892],"type":"Point"}
}