{
  "type": "Feature",
  "properties": {
    "iso:country":"DE",
    "sg:address":"Dammstr. 32",
    "sg:city":"Waiblingen",
    "sg:phone":"+49 7151/58144",
    "sg:postcode":"71332",
    "sg:province":"Baden-W\u00fcrttemberg",
    "wof:name":"Hans-j\u00f6rg Sch\u00f6ffler",
    "wof:placetype":"venue"
},
  "geometry": {"coordinates":[9.3044633865,48.8299446106],"type":"Point"}
}