{
  "type": "Feature",
  "properties": {
    "iso:country":"DE",
    "sg:address":"Postfach 1161",
    "sg:city":"Winnweiler",
    "sg:postcode":"67719",
    "sg:province":"Rheinland-Pfalz",
    "wof:name":"Gemeindeb\u00fccherei",
    "wof:placetype":"venue"
},
  "geometry": {"coordinates":[7.8525,49.568111],"type":"Point"}
}