{
  "type": "Feature",
  "properties": {
    "iso:country":"DE",
    "sg:address":"Hohenbirker Str. 21",
    "sg:city":"Remscheid",
    "sg:phone":"+49 2191/84450",
    "sg:postcode":"42855",
    "sg:province":"Nordrhein-Westfalen",
    "wof:name":"Stephan Und Anabell Hertel Rechtsanw\u00e4lte",
    "wof:placetype":"venue"
},
  "geometry": {"coordinates":[7.1673440933,51.1989173889],"type":"Point"}
}