{
  "type": "Feature",
  "properties": {
    "iso:country":"DE",
    "sg:address":"Hauptstr. 21a",
    "sg:city":"Cremlingen",
    "sg:phone":"+49 5306/91090",
    "sg:postcode":"38162",
    "sg:province":"Niedersachsen",
    "wof:name":"Rats-apotheke I. Schaller",
    "wof:placetype":"venue"
},
  "geometry": {"coordinates":[10.651284,52.249027],"type":"Point"}
}