{
  "type": "Feature",
  "properties": {
    "iso:country":"DE",
    "sg:address":"Berliner Str. 199",
    "sg:city":"Beelitz",
    "sg:phone":"+49 33204/42256",
    "sg:postcode":"14547",
    "sg:province":"Brandenburg",
    "wof:name":"Hubertus Baganz X",
    "wof:placetype":"venue"
},
  "geometry": {"coordinates":[12.977835,52.23357],"type":"Point"}
}