{
  "type": "Feature",
  "properties": {
    "iso:country":"DE",
    "sg:address":"Franz-Wiedemeier-Str. 95",
    "sg:city":"Ulm",
    "sg:phone":"+49 731/385440",
    "sg:postcode":"89081",
    "sg:province":"Baden-W\u00fcrttemberg",
    "wof:name":"Prof. Med. Reinhard Wodik",
    "wof:placetype":"venue"
},
  "geometry": {"coordinates":[9.9332942963,48.4003181458],"type":"Point"}
}