{
  "type": "Feature",
  "properties": {
    "iso:country":"DE",
    "sg:address":"Talstr. 6",
    "sg:city":"Sulzbach",
    "sg:phone":"+49 7193/314",
    "sg:postcode":"71560",
    "sg:province":"Baden-W\u00fcrttemberg",
    "wof:name":"Rudolf Hindennach",
    "wof:placetype":"venue"
},
  "geometry": {"coordinates":[7.072548,49.315006],"type":"Point"}
}