{
  "type": "Feature",
  "properties": {
    "iso:country":"DE",
    "sg:address":"Hegaustr. 19",
    "sg:city":"Hilzingen",
    "sg:phone":"+49 7731/45429",
    "sg:postcode":"78247",
    "sg:province":"Baden-W\u00fcrttemberg",
    "wof:name":"Gerhardt Sch\u00e4dler Chefkoch",
    "wof:placetype":"venue"
},
  "geometry": {"coordinates":[8.7903318405,47.7911567688],"type":"Point"}
}