{
  "type": "Feature",
  "properties": {
    "iso:country":"DE",
    "sg:address":"Mittelm\u00fchle",
    "sg:city":"Markt Erlbach",
    "sg:postcode":"91459",
    "sg:province":"Bayern",
    "wof:name":"G. K\u00e4ferlein",
    "wof:placetype":"venue"
},
  "geometry": {"coordinates":[10.6884794235,49.499786377],"type":"Point"}
}