{
  "type": "Feature",
  "properties": {
    "iso:country":"DE",
    "sg:address":"Laher-Feld-Str. 4",
    "sg:city":"Hannover",
    "sg:phone":"+49 511/612880",
    "sg:postcode":"30659",
    "sg:province":"Niedersachsen",
    "wof:name":"P. Leichsenring Gmbh",
    "wof:placetype":"venue"
},
  "geometry": {"coordinates":[9.8245182037,52.4129562378],"type":"Point"}
}