{
  "type": "Feature",
  "properties": {
    "iso:country":"DE",
    "sg:address":"Am Brandende 11",
    "sg:city":"Burgdorf",
    "sg:phone":"+49 5136/83259",
    "sg:postcode":"31303",
    "sg:province":"Niedersachsen",
    "wof:name":"Murphys Law",
    "wof:placetype":"venue"
},
  "geometry": {"coordinates":[10.0055913925,52.4469146729],"type":"Point"}
}