{
  "type": "Feature",
  "properties": {
    "iso:country":"DE",
    "sg:address":"Schonachbach 22",
    "sg:city":"Triberg",
    "sg:phone":"+49 7722/866889",
    "sg:postcode":"78098",
    "sg:province":"Baden-W\u00fcrttemberg",
    "wof:name":"Imbisstube",
    "wof:placetype":"venue"
},
  "geometry": {"coordinates":[8.2316045761,48.1303215027],"type":"Point"}
}