{
  "type": "Feature",
  "properties": {
    "iso:country":"DE",
    "sg:address":"Segeberger Chaussee 100",
    "sg:city":"Norderstedt",
    "sg:phone":"+49 451/6934540",
    "sg:postcode":"22850",
    "sg:province":"Schleswig-Holstein",
    "wof:name":"First Class",
    "wof:placetype":"venue"
},
  "geometry": {"coordinates":[10.7164907455,53.9181556702],"type":"Point"}
}