{
  "type": "Feature",
  "properties": {
    "iso:country":"DE",
    "sg:address":"Strelitzer Str. 24",
    "sg:city":"Woldegk",
    "sg:phone":"+49 3964/210232",
    "sg:postcode":"17348",
    "sg:province":"Mecklenburg-Vorpommern",
    "wof:name":"Alfred Gest",
    "wof:placetype":"venue"
},
  "geometry": {"coordinates":[13.4303216934,53.4238815308],"type":"Point"}
}