{
  "type": "Feature",
  "properties": {
    "iso:country":"DE",
    "sg:address":"Ambo\u00dfstr. 1",
    "sg:city":"Werlte",
    "sg:postcode":"49757",
    "sg:province":"Niedersachsen",
    "wof:name":"Wilken Einrichtungs Gmbh & Co. Kg",
    "wof:placetype":"venue"
},
  "geometry": {"coordinates":[7.65951,52.85144],"type":"Point"}
}