{
  "type": "Feature",
  "properties": {
    "iso:country":"DE",
    "sg:address":"Rotenseer Weg 3",
    "sg:city":"Hauneck",
    "sg:phone":"+49 6621/73461",
    "sg:postcode":"36282",
    "sg:province":"Hessen",
    "wof:name":"R. Alles",
    "wof:placetype":"venue"
},
  "geometry": {"coordinates":[9.7234973907,50.8351707458],"type":"Point"}
}