{
  "type": "Feature",
  "properties": {
    "iso:country":"DE",
    "sg:address":"An der Autobahn 1",
    "sg:city":"Reichshof-Hespert",
    "sg:phone":"+49 2265/9930",
    "sg:postcode":"51580",
    "sg:province":"Nordrhein-Westfalen",
    "wof:name":"Emil M\u00fcller Metallwerk Gmbh",
    "wof:placetype":"venue"
},
  "geometry": {"coordinates":[7.7772049904,50.9599494934],"type":"Point"}
}