{
  "type": "Feature",
  "properties": {
    "iso:country":"DE",
    "sg:address":"Heidkamp 4",
    "sg:city":"Meinersen - Seershausen",
    "sg:postcode":"38536",
    "sg:province":"Niedersachsen",
    "wof:name":"Martin Deseke - Gas- Und Wasserinstallateurmeister",
    "wof:placetype":"venue"
},
  "geometry": {"coordinates":[10.323718071,52.4482154846],"type":"Point"}
}