{
  "type": "Feature",
  "properties": {
    "iso:country":"DE",
    "sg:address":"Neugasse 11",
    "sg:city":"Mei\u00dfen",
    "sg:phone":"+49 3521/453384",
    "sg:postcode":"01662",
    "sg:province":"Sachsen",
    "wof:name":"Hahnemann-apotheke Inh. Petra K\u00fcchler",
    "wof:placetype":"venue"
},
  "geometry": {"coordinates":[13.4713,51.160809],"type":"Point"}
}