{
  "type": "Feature",
  "properties": {
    "iso:country":"DE",
    "sg:address":"Obere Fulder Gasse 8",
    "sg:city":"Alsfeld",
    "sg:phone":"+49 6631/4379",
    "sg:postcode":"36304",
    "sg:province":"Hessen",
    "wof:name":"Modetick",
    "wof:placetype":"venue"
},
  "geometry": {"coordinates":[9.272195,50.750778],"type":"Point"}
}