{
  "type": "Feature",
  "properties": {
    "iso:country":"DE",
    "sg:address":"Stra\u00dfe der Einheit 27",
    "sg:city":"Neukieritzsch",
    "sg:phone":"+49 34342/51938",
    "sg:postcode":"04575",
    "sg:province":"Sachsen",
    "wof:name":"Frank Schwartz",
    "wof:placetype":"venue"
},
  "geometry": {"coordinates":[12.407583,51.153801],"type":"Point"}
}