{
  "type": "Feature",
  "properties": {
    "iso:country":"DE",
    "sg:address":"Sch\u00f6nflie\u00dfer Str. 13",
    "sg:city":"Berlin",
    "sg:phone":"+49 30/4458846",
    "sg:postcode":"10439",
    "sg:province":"Berlin",
    "wof:name":"Weinstube Am Arnimplatz Inh. Alexander Schwarz",
    "wof:placetype":"venue"
},
  "geometry": {"coordinates":[13.4081678391,52.55235672],"type":"Point"}
}