{
  "type": "Feature",
  "properties": {
    "iso:country":"DE",
    "sg:address":"Fechenheimer Weg 17",
    "sg:city":"Maintal",
    "sg:phone":"+49 6109/762067",
    "sg:postcode":"63477",
    "sg:province":"Hessen",
    "wof:name":"Gl\u00fcck Fenster Rolladen Technik Vertriebs Gmbh",
    "wof:placetype":"venue"
},
  "geometry": {"coordinates":[8.791287,50.14555],"type":"Point"}
}