{
  "type": "Feature",
  "properties": {
    "iso:country":"DE",
    "sg:address":"Bachstr. 1",
    "sg:city":"Vlotho",
    "sg:phone":"+49 5733/2348",
    "sg:postcode":"32602",
    "sg:province":"Nordrhein-Westfalen",
    "wof:name":"U. Credo-wonneberger",
    "wof:placetype":"venue"
},
  "geometry": {"coordinates":[8.855738,52.163849],"type":"Point"}
}