{
  "type": "Feature",
  "properties": {
    "iso:country":"DE",
    "sg:address":"St\u00f6ckigter Str. 57",
    "sg:city":"Plauen",
    "sg:phone":"+49 3741/472259",
    "sg:postcode":"08527",
    "sg:province":"Sachsen",
    "wof:name":"Lottis Imbi\u00df",
    "wof:placetype":"venue"
},
  "geometry": {"coordinates":[12.1490459442,50.4866714478],"type":"Point"}
}