{
  "type": "Feature",
  "properties": {
    "iso:country":"DE",
    "sg:address":"Karl-G\u00f6tz-Str. 5",
    "sg:city":"Schweinfurt",
    "sg:phone":"+49 9721/78460",
    "sg:postcode":"97424",
    "sg:province":"Bayern",
    "wof:name":"Phs - Electronic Gmbh",
    "wof:placetype":"venue"
},
  "geometry": {"coordinates":[10.195354,50.056412],"type":"Point"}
}