{
  "type": "Feature",
  "properties": {
    "iso:country":"DE",
    "sg:address":"Geranienstr. 42b",
    "sg:city":"Riemerling",
    "sg:phone":"+49 89/6888625",
    "sg:postcode":"85521",
    "sg:province":"Bayern",
    "wof:name":"Schmid Immobilienmakler",
    "wof:placetype":"venue"
},
  "geometry": {"coordinates":[11.6911258698,48.0599708557],"type":"Point"}
}