{
  "type": "Feature",
  "properties": {
    "iso:country":"DE",
    "sg:address":"\u00c4u\u00dfere Weberstr. 35",
    "sg:city":"Zittau",
    "sg:phone":"+49 3583/510894",
    "sg:postcode":"02763",
    "sg:province":"Sachsen",
    "wof:name":"Dr. W. Paschek Immobilienmakler",
    "wof:placetype":"venue"
},
  "geometry": {"coordinates":[14.7964811325,50.898273468],"type":"Point"}
}