{
  "type": "Feature",
  "properties": {
    "iso:country":"DE",
    "sg:address":"Lindenstr. 67",
    "sg:city":"Grevenbroich",
    "sg:phone":"+49 2181/231223",
    "sg:postcode":"41515",
    "sg:province":"Nordrhein-Westfalen",
    "wof:name":"Iso-bausatzsysteme Vertriebs- Gesellschaft Mbh",
    "wof:placetype":"venue"
},
  "geometry": {"coordinates":[6.601701,51.086601],"type":"Point"}
}