{
  "type": "Feature",
  "properties": {
    "iso:country":"DE",
    "sg:address":"Skagerrakufer 10",
    "sg:city":"Kiel",
    "sg:phone":"+49 4943/139930",
    "sg:postcode":"24159",
    "sg:province":"Schleswig-Holstein",
    "wof:name":"Lindenau Gmbh",
    "wof:placetype":"venue"
},
  "geometry": {"coordinates":[10.1743526459,54.3897094727],"type":"Point"}
}