{
  "type": "Feature",
  "properties": {
    "iso:country":"DE",
    "sg:address":"Schnatgang 58",
    "sg:city":"Osnabr\u00fcck",
    "sg:phone":"+49 541/46873",
    "sg:postcode":"49080",
    "sg:province":"Niedersachsen",
    "wof:name":"Oase",
    "wof:placetype":"venue"
},
  "geometry": {"coordinates":[8.0347690582,52.269115448],"type":"Point"}
}