{
  "type": "Feature",
  "properties": {
    "iso:country":"DE",
    "sg:address":"Im Loh 1",
    "sg:city":"Wetter",
    "sg:phone":"+49 2335/7429",
    "sg:postcode":"58300",
    "sg:province":"Nordrhein-Westfalen",
    "wof:name":"Walter Asbeck",
    "wof:placetype":"venue"
},
  "geometry": {"coordinates":[7.366819,51.362865],"type":"Point"}
}