{
  "type": "Feature",
  "properties": {
    "iso:country":"DE",
    "sg:address":"Elberfelder Str. 35",
    "sg:city":"Hagen",
    "sg:phone":"+49 2331/13292",
    "sg:postcode":"58095",
    "sg:province":"Nordrhein-Westfalen",
    "wof:name":"Werner & Kettler Gmbh",
    "wof:placetype":"venue"
},
  "geometry": {"coordinates":[7.470398,51.358089],"type":"Point"}
}