{
  "type": "Feature",
  "properties": {
    "iso:country":"DE",
    "sg:address":"Wassenbergstr. 4",
    "sg:city":"Emmerich",
    "sg:phone":"+49 2822/5646",
    "sg:postcode":"46446",
    "sg:province":"Nordrhein-Westfalen",
    "wof:name":"H. Biermann",
    "wof:placetype":"venue"
},
  "geometry": {"coordinates":[6.249317,51.835785],"type":"Point"}
}