{
  "type": "Feature",
  "properties": {
    "iso:country":"DE",
    "sg:address":"Schlo\u00dfstr. 22",
    "sg:city":"Heusenstamm",
    "sg:phone":"+49 6104/2590",
    "sg:postcode":"63150",
    "sg:province":"Hessen",
    "wof:name":"Brot- Und Feinb\u00e4ckerei Wolfgang Paul Ges. Mbh",
    "wof:placetype":"venue"
},
  "geometry": {"coordinates":[8.806676,50.060688],"type":"Point"}
}