{
  "type": "Feature",
  "properties": {
    "iso:country":"DE",
    "sg:address":"Lindenstr. 12",
    "sg:city":"L\u00fcdinghausen",
    "sg:phone":"+49 2591/3979",
    "sg:postcode":"59348",
    "sg:province":"Nordrhein-Westfalen",
    "wof:name":"Franz K\u00f6hler",
    "wof:placetype":"venue"
},
  "geometry": {"coordinates":[7.4326558113,51.7647972107],"type":"Point"}
}