{
  "type": "Feature",
  "properties": {
    "iso:country":"DE",
    "sg:address":"Grabenstr. 14",
    "sg:city":"Brandenburg",
    "sg:phone":"+49 3381/524509",
    "sg:postcode":"14776",
    "sg:province":"Brandenburg",
    "wof:name":"Split",
    "wof:placetype":"venue"
},
  "geometry": {"coordinates":[12.5561304092,52.408115387],"type":"Point"}
}