{
  "type": "Feature",
  "properties": {
    "iso:country":"DE",
    "sg:address":"\u00d6schelbronner Str. 10",
    "sg:city":"G\u00e4ufelden",
    "sg:phone":"+49 4970/3272146",
    "sg:postcode":"71126",
    "sg:province":"Baden-W\u00fcrttemberg",
    "wof:name":"Kreissparkasse B\u00f6blingen",
    "wof:placetype":"venue"
},
  "geometry": {"coordinates":[8.847631,48.562031],"type":"Point"}
}