{
  "type": "Feature",
  "properties": {
    "iso:country":"DE",
    "sg:address":"Gr\u00fcnderhammer 5",
    "sg:city":"Remscheid",
    "sg:phone":"+49 2191/80587",
    "sg:postcode":"42855",
    "sg:province":"Nordrhein-Westfalen",
    "wof:name":"Titz Schreinerei Gmbh",
    "wof:placetype":"venue"
},
  "geometry": {"coordinates":[7.177882,51.199982],"type":"Point"}
}