{
  "type": "Feature",
  "properties": {
    "iso:country":"DE",
    "sg:address":"Hans-Thoma-Str. 1",
    "sg:city":"Mannheim",
    "sg:phone":"+49 621/422820",
    "sg:postcode":"68163",
    "sg:province":"Baden-W\u00fcrttemberg",
    "wof:name":"Online Productions Ges. Zur Herstellung Von Digitalen",
    "wof:placetype":"venue"
},
  "geometry": {"coordinates":[8.5072555542,49.4653320312],"type":"Point"}
}