{
  "type": "Feature",
  "properties": {
    "iso:country":"DE",
    "sg:address":"Pascalstr. 26",
    "sg:city":"Aachen",
    "sg:phone":"+49 2408/94700",
    "sg:postcode":"52076",
    "sg:province":"Nordrhein-Westfalen",
    "wof:name":"Systaix Gmbh",
    "wof:placetype":"venue"
},
  "geometry": {"coordinates":[6.144313,50.713341],"type":"Point"}
}