{
  "type": "Feature",
  "properties": {
    "iso:country":"DE",
    "sg:address":"Deutsche Str. 61",
    "sg:city":"Dortmund",
    "sg:phone":"+49 231/851860",
    "sg:postcode":"44339",
    "sg:province":"Nordrhein-Westfalen",
    "wof:name":"E. Und H. Witt Damenbekleidung",
    "wof:placetype":"venue"
},
  "geometry": {"coordinates":[7.468869,51.550129],"type":"Point"}
}