{
  "type": "Feature",
  "properties": {
    "iso:country":"DE",
    "sg:address":"Hohenstaufenallee 3",
    "sg:city":"Aachen",
    "sg:phone":"+49 241/72433",
    "sg:postcode":"52064",
    "sg:province":"Nordrhein-Westfalen",
    "wof:name":"Verkehrswacht Aachen E. V.",
    "wof:placetype":"venue"
},
  "geometry": {"coordinates":[6.0798687935,50.7643737793],"type":"Point"}
}