{
  "type": "Feature",
  "properties": {
    "iso:country":"DE",
    "sg:address":"Kaulbachstr. 3",
    "sg:city":"Bad Arolsen",
    "sg:phone":"+49 5691/6041",
    "sg:postcode":"34454",
    "sg:province":"Hessen",
    "wof:name":"Kaulbachmuseum Der Stadt Arolsen",
    "wof:placetype":"venue"
},
  "geometry": {"coordinates":[9.018161,51.379108],"type":"Point"}
}