{
  "type": "Feature",
  "properties": {
    "iso:country":"DE",
    "sg:address":"Neufraer Str.",
    "sg:city":"Riedlingen",
    "sg:postcode":"88499",
    "sg:province":"Baden-W\u00fcrttemberg",
    "wof:name":"Kath. Pfarramt St. Petrus Und Paulus",
    "wof:placetype":"venue"
},
  "geometry": {"coordinates":[9.4844007492,48.147819519],"type":"Point"}
}