{
  "type": "Feature",
  "properties": {
    "iso:country":"DE",
    "sg:address":"Samerstr. 6",
    "sg:city":"Bruckm\u00fchl",
    "sg:phone":"+49 8062/5322",
    "sg:postcode":"83052",
    "sg:province":"Bayern",
    "wof:name":"Roswitha Aichinger Steuerberaterin",
    "wof:placetype":"venue"
},
  "geometry": {"coordinates":[11.9042329788,47.8701095581],"type":"Point"}
}