{
  "type": "Feature",
  "properties": {
    "iso:country":"DE",
    "sg:address":"Detlev-H.-R\u00f6tger-Str. 13",
    "sg:city":"Itzehoe",
    "sg:postcode":"25524",
    "sg:province":"Schleswig-Holstein",
    "wof:name":"Kolbe Technische Anlagen Service Gmbh",
    "wof:placetype":"venue"
},
  "geometry": {"coordinates":[9.480223,53.907673],"type":"Point"}
}