{
  "type": "Feature",
  "properties": {
    "iso:country":"DE",
    "sg:address":"Unterm Hagen 10",
    "sg:city":"Warstein",
    "sg:phone":"+49 2902/2695",
    "sg:postcode":"59581",
    "sg:province":"Nordrhein-Westfalen",
    "wof:name":"Hubert G\u00f6ke",
    "wof:placetype":"venue"
},
  "geometry": {"coordinates":[8.3534879684,51.4484558105],"type":"Point"}
}