{
  "type": "Feature",
  "properties": {
    "iso:country":"DE",
    "sg:address":"Hellbergstr. 18",
    "sg:city":"Eppelborn",
    "sg:phone":"+49 6881/7229",
    "sg:postcode":"66571",
    "sg:province":"Saarland",
    "wof:name":"H.-p. Klingelh\u00f6fer Heilpraktiker",
    "wof:placetype":"venue"
},
  "geometry": {"coordinates":[6.9642419815,49.404876709],"type":"Point"}
}