{
  "type": "Feature",
  "properties": {
    "iso:country":"DE",
    "sg:address":"Bahnhofstr. 12",
    "sg:city":"Freyung",
    "sg:phone":"+49 8551/2323",
    "sg:postcode":"94078",
    "sg:province":"Bayern",
    "wof:name":"Reiseb\u00fcro Edgar Krickl",
    "wof:placetype":"venue"
},
  "geometry": {"coordinates":[13.5474843979,48.8054885864],"type":"Point"}
}