{
  "type": "Feature",
  "properties": {
    "iso:country":"DE",
    "sg:address":"Kneippstr. 2",
    "sg:city":"Isny",
    "sg:phone":"+49 7562/2298",
    "sg:postcode":"88316",
    "sg:province":"Baden-W\u00fcrttemberg",
    "wof:name":"Raimund Holdenried",
    "wof:placetype":"venue"
},
  "geometry": {"coordinates":[10.0455417633,47.6980056763],"type":"Point"}
}