{
  "type": "Feature",
  "properties": {
    "iso:country":"DE",
    "sg:address":"H\u00fclchrath 3",
    "sg:city":"Blankenheim",
    "sg:phone":"+49 2449/1043",
    "sg:postcode":"53945",
    "sg:province":"Nordrhein-Westfalen",
    "wof:name":"Altenheim St. Josef Stift",
    "wof:placetype":"venue"
},
  "geometry": {"coordinates":[6.643101,50.439178],"type":"Point"}
}