{
  "type": "Feature",
  "properties": {
    "iso:country":"DE",
    "sg:address":"Eichenstr. 21b",
    "sg:city":"M\u00fcnchen",
    "sg:postcode":"81375",
    "sg:province":"Bayern",
    "wof:name":"Negar Gmbh",
    "wof:placetype":"venue"
},
  "geometry": {"coordinates":[11.4758272171,48.1185455322],"type":"Point"}
}