{
  "type": "Feature",
  "properties": {
    "iso:country":"DE",
    "sg:address":"Waldsiedlung 23",
    "sg:city":"Wernsdorf",
    "sg:phone":"+49 3362/820001",
    "sg:postcode":"15537",
    "sg:province":"Brandenburg",
    "wof:name":"Klohn",
    "wof:placetype":"venue"
},
  "geometry": {"coordinates":[13.7096099854,52.3685188293],"type":"Point"}
}