{
  "type": "Feature",
  "properties": {
    "iso:country":"DE",
    "sg:address":"Seehauser Str. 42",
    "sg:city":"Ruhpolding",
    "sg:phone":"+49 8663/9601",
    "sg:postcode":"83324",
    "sg:province":"Bayern",
    "wof:name":"G\u00e4stehaus Otto Fuchs",
    "wof:placetype":"venue"
},
  "geometry": {"coordinates":[12.655579567,47.7498855591],"type":"Point"}
}