{
  "type": "Feature",
  "properties": {
    "iso:country":"DE",
    "sg:address":"Wilhelmstr. 14",
    "sg:city":"Asperg",
    "sg:phone":"+49 7141/63160",
    "sg:postcode":"71679",
    "sg:province":"Baden-W\u00fcrttemberg",
    "wof:name":"Ev.-method. Pfarramt Erl\u00f6serkirche",
    "wof:placetype":"venue"
},
  "geometry": {"coordinates":[9.1405649185,48.9068374634],"type":"Point"}
}