{
  "type": "Feature",
  "properties": {
    "iso:country":"DE",
    "sg:address":"Pr\u00e4lat-Ludsteck-Str. 7",
    "sg:city":"Kelheim",
    "sg:phone":"+49 9441/5866",
    "sg:postcode":"93309",
    "sg:province":"Bayern",
    "wof:name":"Dr. Reuthlinger Und Partner Steuerberater Und Wirtschafts-",
    "wof:placetype":"venue"
},
  "geometry": {"coordinates":[11.8826913834,48.924446106],"type":"Point"}
}