{
  "type": "Feature",
  "properties": {
    "iso:country":"DE",
    "sg:address":"Schulze-Delitzsch-Str. 33",
    "sg:city":"Leipzig",
    "sg:phone":"+49 341/6885825",
    "sg:postcode":"04315",
    "sg:province":"Sachsen",
    "wof:name":"Doerffer Sandstrahl- Technik Leipzig Gmbh",
    "wof:placetype":"venue"
},
  "geometry": {"coordinates":[12.405284,51.348389],"type":"Point"}
}