{
  "type": "Feature",
  "properties": {
    "iso:country":"DE",
    "sg:address":"In den H\u00f6fen 3",
    "sg:city":"Steffenberg",
    "sg:phone":"+49 6464/333",
    "sg:postcode":"35239",
    "sg:province":"Hessen",
    "wof:name":"E. Schwarz",
    "wof:placetype":"venue"
},
  "geometry": {"coordinates":[8.480775,50.831066],"type":"Point"}
}