{
  "type": "Feature",
  "properties": {
    "iso:country":"DE",
    "sg:address":"Friedrichstr. 8",
    "sg:city":"Remseck",
    "sg:phone":"+49 7146/91639",
    "sg:postcode":"71686",
    "sg:province":"Baden-W\u00fcrttemberg",
    "wof:name":"Albrecht Und Cygan Gbr",
    "wof:placetype":"venue"
},
  "geometry": {"coordinates":[9.250202179,48.8632469177],"type":"Point"}
}