{
  "type": "Feature",
  "properties": {
    "iso:country":"DE",
    "sg:address":"Edekastr. 1",
    "sg:city":"Offenburg",
    "sg:phone":"+49 781/5026160",
    "sg:postcode":"77656",
    "sg:province":"Baden-W\u00fcrttemberg",
    "wof:name":"Objekt Bau-verwaltungs- Gmbh",
    "wof:placetype":"venue"
},
  "geometry": {"coordinates":[7.9224448204,48.4799766541],"type":"Point"}
}