{
  "type": "Feature",
  "properties": {
    "iso:country":"DE",
    "sg:address":"Sprockh\u00f6veler Str. 97",
    "sg:city":"Witten",
    "sg:phone":"+49 2302/51194",
    "sg:postcode":"58455",
    "sg:province":"Nordrhein-Westfalen",
    "wof:name":"Manis Schlemmergrill",
    "wof:placetype":"venue"
},
  "geometry": {"coordinates":[7.3236317635,51.4427337646],"type":"Point"}
}