{
  "type": "Feature",
  "properties": {
    "iso:country":"DE",
    "sg:address":"Spaldingstr. 74",
    "sg:city":"Hamburg",
    "sg:phone":"+49 40/2388670",
    "sg:postcode":"20097",
    "sg:province":"Hamburg",
    "wof:name":"Tam Maschinentechnik Gmbh",
    "wof:placetype":"venue"
},
  "geometry": {"coordinates":[10.017159,53.54929],"type":"Point"}
}