{
  "type": "Feature",
  "properties": {
    "iso:country":"DE",
    "sg:address":"Herrengasse 11",
    "sg:city":"Ergersheim",
    "sg:phone":"+49 9847/285",
    "sg:postcode":"91465",
    "sg:province":"Bayern",
    "wof:name":"Karl Stahl",
    "wof:placetype":"venue"
},
  "geometry": {"coordinates":[10.324604,49.509926],"type":"Point"}
}