{
  "type": "Feature",
  "properties": {
    "iso:country":"DE",
    "sg:address":"Breite Schneise 5",
    "sg:city":"Altenstadt",
    "sg:phone":"+49 700 2832 4637",
    "sg:postcode":"63674",
    "sg:province":"Hessen",
    "wof:name":"Electronic Opto Components M. B\u00fcchner Beteiligungs Gmbh",
    "wof:placetype":"venue"
},
  "geometry": {"coordinates":[8.949372,50.270645],"type":"Point"}
}