{
  "type": "Feature",
  "properties": {
    "iso:country":"DE",
    "sg:address":"Malerstr. 10",
    "sg:city":"Kaufbeuren",
    "sg:phone":"+49 8341/62279",
    "sg:postcode":"87600",
    "sg:province":"Bayern",
    "wof:name":"Srna & Co. Gmbh",
    "wof:placetype":"venue"
},
  "geometry": {"coordinates":[10.644592,47.916298],"type":"Point"}
}