{
  "type": "Feature",
  "properties": {
    "iso:country":"DE",
    "sg:address":"Untere Str. 3",
    "sg:city":"Zeil",
    "sg:phone":"+49 9524/6852",
    "sg:postcode":"97475",
    "sg:province":"Bayern",
    "wof:name":"Bistro & Pub Schl\u00fcrfzapfen",
    "wof:placetype":"venue"
},
  "geometry": {"coordinates":[10.5867986679,50.0123405457],"type":"Point"}
}