{
  "type": "Feature",
  "properties": {
    "iso:country":"DE",
    "sg:address":"Daimlerstr. 30",
    "sg:city":"Ladenburg",
    "sg:postcode":"68526",
    "sg:province":"Baden-W\u00fcrttemberg",
    "wof:name":"Handwerkerring Ladenburg Gmbh",
    "wof:placetype":"venue"
},
  "geometry": {"coordinates":[8.596503,49.475803],"type":"Point"}
}