{
  "type": "Feature",
  "properties": {
    "iso:country":"DE",
    "sg:address":"Marktstr. 41",
    "sg:city":"Wilhelmshaven",
    "sg:phone":"+49 4421/42135",
    "sg:postcode":"26382",
    "sg:province":"Niedersachsen",
    "wof:name":"Bree",
    "wof:placetype":"venue"
},
  "geometry": {"coordinates":[8.115473,53.519993],"type":"Point"}
}