{
  "type": "Feature",
  "properties": {
    "iso:country":"DE",
    "sg:address":"Alte L\u00fcneburger Str. 5",
    "sg:city":"Toppenstedt",
    "sg:phone":"+49 4173/511192",
    "sg:postcode":"21442",
    "sg:province":"Niedersachsen",
    "wof:name":"Henning Reinhard Architekt",
    "wof:placetype":"venue"
},
  "geometry": {"coordinates":[10.119211,53.264992],"type":"Point"}
}