{
  "type": "Feature",
  "properties": {
    "iso:country":"DE",
    "sg:address":"Wilhelm-Stein-Weg 7",
    "sg:city":"Hamburg",
    "sg:phone":"+49 40/5386058",
    "sg:postcode":"22339",
    "sg:province":"Hamburg",
    "wof:name":"Carl H. M\u00fcller Gmbh",
    "wof:placetype":"venue"
},
  "geometry": {"coordinates":[10.032385,53.645653],"type":"Point"}
}