{
  "type": "Feature",
  "properties": {
    "iso:country":"DE",
    "sg:address":"Borsigstr. 4",
    "sg:city":"Hildesheim",
    "sg:phone":"+49 5121/706611",
    "sg:postcode":"31135",
    "sg:province":"Niedersachsen",
    "wof:name":"Tsn-beton & M\u00f6lders Hildesheim Gmbh & Co. Kg",
    "wof:placetype":"venue"
},
  "geometry": {"coordinates":[9.9773378372,52.1684608459],"type":"Point"}
}