{
  "type": "Feature",
  "properties": {
    "iso:country":"DE",
    "sg:address":"Heinrich-Koehl-Str. 34",
    "sg:city":"Saarbr\u00fccken",
    "sg:phone":"+49 681/45829",
    "sg:postcode":"66113",
    "sg:province":"Saarland",
    "wof:name":"M. Dovidio",
    "wof:placetype":"venue"
},
  "geometry": {"coordinates":[6.9918699265,49.2470817566],"type":"Point"}
}