{
  "type": "Feature",
  "properties": {
    "iso:country":"DE",
    "sg:address":"Fritz-Reuter-Str. 18",
    "sg:city":"Rehna",
    "sg:phone":"+49 38872/53830",
    "sg:postcode":"19217",
    "sg:province":"Mecklenburg-Vorpommern",
    "wof:name":"A. Lange",
    "wof:placetype":"venue"
},
  "geometry": {"coordinates":[11.04832,53.777534],"type":"Point"}
}