{
  "type": "Feature",
  "properties": {
    "iso:country":"DE",
    "sg:address":"Bayreuther Str. 2",
    "sg:city":"Amberg",
    "sg:phone":"+49 9621/13031",
    "sg:postcode":"92224",
    "sg:province":"Bayern",
    "wof:name":"Stadler-beteiligungs-gmbh",
    "wof:placetype":"venue"
},
  "geometry": {"coordinates":[11.855261,49.449291],"type":"Point"}
}