{
  "type": "Feature",
  "properties": {
    "iso:country":"DE",
    "sg:address":"Dammtor 9",
    "sg:city":"Gehrden",
    "sg:postcode":"30989",
    "sg:province":"Niedersachsen",
    "wof:name":"Argos Verm\u00f6gens- Und Verwaltungs Gmbh",
    "wof:placetype":"venue"
},
  "geometry": {"coordinates":[9.6035909653,52.3112411499],"type":"Point"}
}