{
  "type": "Feature",
  "properties": {
    "iso:country":"DE",
    "sg:address":"Bergmannstr. 3",
    "sg:city":"Berlin",
    "sg:phone":"+49 30/6947745",
    "sg:postcode":"10961",
    "sg:province":"Berlin",
    "wof:name":"Parlamento",
    "wof:placetype":"venue"
},
  "geometry": {"coordinates":[13.388053894,52.4897956848],"type":"Point"}
}