{
  "type": "Feature",
  "properties": {
    "iso:country":"DE",
    "sg:address":"Hindenburgstr. 10",
    "sg:city":"Georgsmarienh\u00fctte",
    "sg:phone":"+49 5401/839222",
    "sg:postcode":"49124",
    "sg:province":"Niedersachsen",
    "wof:name":"Karl Niemeyer Eisenwaren",
    "wof:placetype":"venue"
},
  "geometry": {"coordinates":[8.0353164673,52.207824707],"type":"Point"}
}