{
  "type": "Feature",
  "properties": {
    "iso:country":"DE",
    "sg:address":"Stephanusstr. 16 a",
    "sg:city":"Paderborn",
    "sg:phone":"+49 5251/73986",
    "sg:postcode":"33098",
    "sg:province":"Nordrhein-Westfalen",
    "wof:name":"Elektro Epple Gmbh",
    "wof:placetype":"venue"
},
  "geometry": {"coordinates":[8.752593,51.704979],"type":"Point"}
}