{
  "type": "Feature",
  "properties": {
    "iso:country":"DE",
    "sg:address":"Kirchberg 1",
    "sg:city":"Engelskirchen",
    "sg:phone":"+49 2263/47216",
    "sg:postcode":"51766",
    "sg:province":"Nordrhein-Westfalen",
    "wof:name":"Pro & Con G. Burk",
    "wof:placetype":"venue"
},
  "geometry": {"coordinates":[7.4060778618,50.9889373779],"type":"Point"}
}