{
  "type": "Feature",
  "properties": {
    "iso:country":"DE",
    "sg:address":"Alfred-Nobel-Str. 10",
    "sg:city":"Monheim",
    "sg:phone":"+49 911/8955588",
    "sg:postcode":"40789",
    "sg:province":"Nordrhein-Westfalen",
    "wof:name":"Siemens Dematic Ag",
    "wof:placetype":"venue"
},
  "geometry": {"coordinates":[11.0804796219,49.4505195618],"type":"Point"}
}