{
  "type": "Feature",
  "properties": {
    "iso:country":"DE",
    "sg:address":"Bei den Reith\u00f6fen 5",
    "sg:city":"Augsburg",
    "sg:phone":"+49 821/407970",
    "sg:postcode":"86156",
    "sg:province":"Bayern",
    "wof:name":"Ori-con Taxiunternehmen Import-export Handels Gmbh",
    "wof:placetype":"venue"
},
  "geometry": {"coordinates":[10.8638763428,48.3780021667],"type":"Point"}
}