{
  "type": "Feature",
  "properties": {
    "iso:country":"DE",
    "sg:address":"Himmighausen 15",
    "sg:city":"Nieheim",
    "sg:phone":"+49 5238/382",
    "sg:postcode":"33039",
    "sg:province":"Nordrhein-Westfalen",
    "wof:name":"Rainer Papenkordt",
    "wof:placetype":"venue"
},
  "geometry": {"coordinates":[9.10905,51.803928],"type":"Point"}
}