{
  "type": "Feature",
  "properties": {
    "iso:country":"DE",
    "sg:address":"Werner-Siemens-Str. 1",
    "sg:city":"Weingarten",
    "sg:phone":"+49 7244/640",
    "sg:postcode":"76356",
    "sg:province":"Baden-W\u00fcrttemberg",
    "wof:name":"W. L. Schwaab Inh. Gebr. Becker Gmbh & Co.",
    "wof:placetype":"venue"
},
  "geometry": {"coordinates":[8.5207061768,49.0592918396],"type":"Point"}
}