{
  "type": "Feature",
  "properties": {
    "iso:country":"DE",
    "sg:address":"Robert-Bosch-Stra\u00dfe 3",
    "sg:city":"Filderstadt",
    "sg:phone":"+49 7158/90730",
    "sg:postcode":"70794",
    "sg:province":"Baden-W\u00fcrttemberg",
    "wof:name":"M+t Pr\u00e4zis Gmbh & Co. Kg",
    "wof:placetype":"venue"
},
  "geometry": {"coordinates":[9.2543649673,48.6453399658],"type":"Point"}
}