{
  "type": "Feature",
  "properties": {
    "iso:country":"DE",
    "sg:address":"Daimlerstr. 26",
    "sg:city":"Sch\u00f6naich",
    "sg:postcode":"71101",
    "sg:province":"Baden-W\u00fcrttemberg",
    "wof:name":"Igel Ingenieurgesellschaft F\u00fcr Leichtbau Mbh",
    "wof:placetype":"venue"
},
  "geometry": {"coordinates":[9.0702667236,48.668182373],"type":"Point"}
}