{
  "type": "Feature",
  "properties": {
    "iso:country":"DE",
    "sg:address":"Liebigstr. 1",
    "sg:city":"Bad Reichenhall",
    "sg:phone":"+49 8651/690500",
    "sg:postcode":"83435",
    "sg:province":"Bayern",
    "wof:name":"J\u00fcrgen Pirkenseer Rechtsanwalt",
    "wof:placetype":"venue"
},
  "geometry": {"coordinates":[12.877327919,47.7256317139],"type":"Point"}
}