{
  "type": "Feature",
  "properties": {
    "iso:country":"DE",
    "sg:address":"Landstr. 1",
    "sg:city":"Rinteln",
    "sg:phone":"+49 4957/512947",
    "sg:postcode":"31737",
    "sg:province":"Niedersachsen",
    "wof:name":"Gustav Kerker Ohg Spedition",
    "wof:placetype":"venue"
},
  "geometry": {"coordinates":[9.1658496857,52.1697425842],"type":"Point"}
}