{
  "type": "Feature",
  "properties": {
    "iso:country":"DE",
    "sg:address":"Gneisenaustr. 59",
    "sg:city":"Berlin",
    "sg:phone":"+49 30/6913409",
    "sg:postcode":"10961",
    "sg:province":"Berlin",
    "wof:name":"Reinhard B\u00fchlmeyer Architekt",
    "wof:placetype":"venue"
},
  "geometry": {"coordinates":[13.403866,52.490009],"type":"Point"}
}