{
  "type": "Feature",
  "properties": {
    "iso:country":"DE",
    "sg:address":"Wagh\u00e4useler Str. 66",
    "sg:city":"Wagh\u00e4usel",
    "sg:phone":"+49 7254/1717",
    "sg:postcode":"68753",
    "sg:province":"Baden-W\u00fcrttemberg",
    "wof:name":"Redecker Drogerie",
    "wof:placetype":"venue"
},
  "geometry": {"coordinates":[8.543063,49.243729],"type":"Point"}
}