{
  "type": "Feature",
  "properties": {
    "iso:country":"DE",
    "sg:address":"Im Kalten Brunnen 29",
    "sg:city":"Neckartailfingen",
    "sg:phone":"+49 7127/3093",
    "sg:postcode":"72666",
    "sg:province":"Baden-W\u00fcrttemberg",
    "wof:name":"Lfg Luftfilter Gmbh",
    "wof:placetype":"venue"
},
  "geometry": {"coordinates":[9.275733,48.615479],"type":"Point"}
}