{
  "type": "Feature",
  "properties": {
    "iso:country":"DE",
    "sg:address":"Hersfelder Str. 18",
    "sg:city":"Eiterfeld",
    "sg:phone":"+49 6672/456",
    "sg:postcode":"36132",
    "sg:province":"Hessen",
    "wof:name":"H. Fuhrmann",
    "wof:placetype":"venue"
},
  "geometry": {"coordinates":[9.7692136765,50.780456543],"type":"Point"}
}