{
  "type": "Feature",
  "properties": {
    "iso:country":"DE",
    "sg:address":"Kurt-Schumacher-Str. 4",
    "sg:city":"Herten",
    "sg:phone":"+49 2366/31648",
    "sg:postcode":"45699",
    "sg:province":"Nordrhein-Westfalen",
    "wof:name":"Pizzeria Bei Gino",
    "wof:placetype":"venue"
},
  "geometry": {"coordinates":[7.1357159615,51.5936508179],"type":"Point"}
}