{
  "type": "Feature",
  "properties": {
    "iso:country":"DE",
    "sg:address":"Schlo\u00dfstr 6",
    "sg:city":"Chemnitz",
    "sg:phone":"+49 371/538830",
    "sg:postcode":"09111",
    "sg:province":"Sachsen",
    "wof:name":"Klengel B\u00fcro Technik Gmbh",
    "wof:placetype":"venue"
},
  "geometry": {"coordinates":[12.916006,50.838131],"type":"Point"}
}