{
  "type": "Feature",
  "properties": {
    "iso:country":"DE",
    "sg:address":"Gelderner Str. 17",
    "sg:city":"Issum",
    "sg:phone":"+49 2835/4090",
    "sg:postcode":"47661",
    "sg:province":"Nordrhein-Westfalen",
    "wof:name":"Linnenw\u00e4wer",
    "wof:placetype":"venue"
},
  "geometry": {"coordinates":[6.4246358871,51.5341033936],"type":"Point"}
}