{
  "type": "Feature",
  "properties": {
    "iso:country":"DE",
    "sg:address":"Platz am Niedertor 19",
    "sg:city":"Neuss",
    "sg:phone":"+49 2131/222121",
    "sg:postcode":"41460",
    "sg:province":"Nordrhein-Westfalen",
    "wof:name":"Landwehrs Marc O Polo",
    "wof:placetype":"venue"
},
  "geometry": {"coordinates":[6.68734,51.200432],"type":"Point"}
}