{
  "type": "Feature",
  "properties": {
    "iso:country":"DE",
    "sg:address":"Alte Frankfurter Str. 23a",
    "sg:city":"Bad Vilbel",
    "sg:phone":"+49 6101/1449",
    "sg:postcode":"61118",
    "sg:province":"Hessen",
    "wof:name":"G. Seitz",
    "wof:placetype":"venue"
},
  "geometry": {"coordinates":[8.742996,50.181965],"type":"Point"}
}