{
  "type": "Feature",
  "properties": {
    "iso:country":"DE",
    "sg:address":"Neuenhofer Str. 28",
    "sg:city":"K\u00f6nigswinter",
    "sg:phone":"+49 2244/1562",
    "sg:postcode":"53639",
    "sg:province":"Nordrhein-Westfalen",
    "wof:name":"O. L\u00fcmes",
    "wof:placetype":"venue"
},
  "geometry": {"coordinates":[7.3156108856,50.6859283447],"type":"Point"}
}