{
  "type": "Feature",
  "properties": {
    "iso:country":"DE",
    "sg:address":"Im Holderstock 29",
    "sg:city":"Gro\u00dfbottwar",
    "sg:phone":"+49 7148/7018",
    "sg:postcode":"71723",
    "sg:province":"Baden-W\u00fcrttemberg",
    "wof:name":"Kiefel & Stockinger Gbr",
    "wof:placetype":"venue"
},
  "geometry": {"coordinates":[9.295473,49.004173],"type":"Point"}
}