{
  "type": "Feature",
  "properties": {
    "iso:country":"DE",
    "sg:address":"Greifswalder Str. 264",
    "sg:city":"Loitz",
    "sg:phone":"+49 39998/10111",
    "sg:postcode":"17121",
    "sg:province":"Mecklenburg-Vorpommern",
    "wof:name":"Jutta Abraham",
    "wof:placetype":"venue"
},
  "geometry": {"coordinates":[13.1299066544,53.9713935852],"type":"Point"}
}