{
  "type": "Feature",
  "properties": {
    "iso:country":"DE",
    "sg:address":"Schmiedstr. 16",
    "sg:city":"Denkendorf",
    "sg:phone":"+49 8465/686",
    "sg:postcode":"85095",
    "sg:province":"Bayern",
    "wof:name":"Katholisches Pfarramt St. Hippolyt",
    "wof:placetype":"venue"
},
  "geometry": {"coordinates":[11.4364919662,48.9455070496],"type":"Point"}
}