{
  "type": "Feature",
  "properties": {
    "iso:country":"DE",
    "sg:address":"Dorfstr. 44",
    "sg:city":"Gompertshausen",
    "sg:phone":"+49 36875/60101",
    "sg:postcode":"98663",
    "sg:province":"Th\u00fcringen",
    "wof:name":"R. Sakautzky",
    "wof:placetype":"venue"
},
  "geometry": {"coordinates":[10.624266,50.298798],"type":"Point"}
}