{
  "type": "Feature",
  "properties": {
    "iso:country":"DE",
    "sg:address":"Lange Str. 38",
    "sg:city":"Hann. M\u00fcnden",
    "sg:postcode":"34346",
    "sg:province":"Niedersachsen",
    "wof:name":"Diplom Optiker He\u00df Nachf. Gmbh",
    "wof:placetype":"venue"
},
  "geometry": {"coordinates":[9.651599884,51.4172515869],"type":"Point"}
}