{
  "type": "Feature",
  "properties": {
    "iso:country":"DE",
    "sg:address":"Lesumer Heerstr. 76 a",
    "sg:city":"Bremen",
    "sg:phone":"+49 421/622132",
    "sg:postcode":"28717",
    "sg:province":"Bremen",
    "wof:name":"Altenheim Haus Elisabeth",
    "wof:placetype":"venue"
},
  "geometry": {"coordinates":[8.668658,53.17506],"type":"Point"}
}