{
  "type": "Feature",
  "properties": {
    "iso:country":"DE",
    "sg:address":"Schlo\u00dfbergstr. 4",
    "sg:city":"Erfweiler",
    "sg:phone":"+49 4963/911348",
    "sg:postcode":"66996",
    "sg:province":"Rheinland-Pfalz",
    "wof:name":"D\u00c4umling Schuhfabriken Hermann Meyer Gmbh",
    "wof:placetype":"venue"
},
  "geometry": {"coordinates":[7.807453,49.153927],"type":"Point"}
}