{
  "type": "Feature",
  "properties": {
    "iso:country":"DE",
    "sg:address":"Z\u00fclpicher Str. 227",
    "sg:city":"K\u00f6ln",
    "sg:phone":"+49 221/413850",
    "sg:postcode":"50937",
    "sg:province":"Nordrhein-Westfalen",
    "wof:name":"Loreley-apotheke",
    "wof:placetype":"venue"
},
  "geometry": {"coordinates":[6.925749,50.923492],"type":"Point"}
}