{
  "type": "Feature",
  "properties": {
    "iso:country":"DE",
    "sg:address":"Helene-Lange-Str. 9",
    "sg:city":"T\u00fcbingen",
    "sg:phone":"+49 7071/84525",
    "sg:postcode":"72074",
    "sg:province":"Baden-W\u00fcrttemberg",
    "wof:name":"Itas Gmbh",
    "wof:placetype":"venue"
},
  "geometry": {"coordinates":[9.0928487778,48.5321731567],"type":"Point"}
}