{
  "type": "Feature",
  "properties": {
    "iso:country":"DE",
    "sg:address":"Hessische Str. 43",
    "sg:city":"Treffurt",
    "sg:phone":"+49 36923/51222",
    "sg:postcode":"99830",
    "sg:province":"Th\u00fcringen",
    "wof:name":"G\u00fcnter Nortmann",
    "wof:placetype":"venue"
},
  "geometry": {"coordinates":[10.235871315,51.1359443665],"type":"Point"}
}