{
  "type": "Feature",
  "properties": {
    "iso:country":"DE",
    "sg:address":"Gerhart-Hauptmann-Str. 47",
    "sg:city":"Dossenheim",
    "sg:postcode":"69221",
    "sg:province":"Baden-W\u00fcrttemberg",
    "wof:name":"Bc Broadcast Und Communication Service Gmbh",
    "wof:placetype":"venue"
},
  "geometry": {"coordinates":[8.6680631638,49.449886322],"type":"Point"}
}