{
  "type": "Feature",
  "properties": {
    "iso:country":"DE",
    "sg:address":"Sengsbank 27",
    "sg:city":"Dortmund",
    "sg:phone":"+49 231/170859",
    "sg:postcode":"44149",
    "sg:province":"Nordrhein-Westfalen",
    "wof:name":"H. Stollarski",
    "wof:placetype":"venue"
},
  "geometry": {"coordinates":[7.415882,51.500401],"type":"Point"}
}