{
  "type": "Feature",
  "properties": {
    "iso:country":"DE",
    "sg:address":"Altenburger Str. 58",
    "sg:city":"Lunzenau",
    "sg:phone":"+49 37383/6702",
    "sg:postcode":"09328",
    "sg:province":"Sachsen",
    "wof:name":"Dieter Krau\u00dfe",
    "wof:placetype":"venue"
},
  "geometry": {"coordinates":[12.748217,50.961082],"type":"Point"}
}