{
  "type": "Feature",
  "properties": {
    "iso:country":"DE",
    "sg:address":"Steinstr. 26",
    "sg:city":"Rabenau",
    "sg:phone":"+49 6407/6373",
    "sg:postcode":"35466",
    "sg:province":"Hessen",
    "wof:name":"H. Sch\u00e4fer",
    "wof:placetype":"venue"
},
  "geometry": {"coordinates":[8.875298,50.670212],"type":"Point"}
}