{
  "type": "Feature",
  "properties": {
    "iso:country":"DE",
    "sg:address":"Hauptstr. 33",
    "sg:city":"Merkendorf",
    "sg:phone":"+49 9826/460",
    "sg:postcode":"91732",
    "sg:province":"Bayern",
    "wof:name":"Armin Sauber",
    "wof:placetype":"venue"
},
  "geometry": {"coordinates":[10.700630188,49.2018585205],"type":"Point"}
}