{
  "type": "Feature",
  "properties": {
    "iso:country":"DE",
    "sg:address":"Am Sonnenhang 38",
    "sg:city":"Sch\u00f6nfeld",
    "sg:phone":"+49 3733/57494",
    "sg:postcode":"09488",
    "sg:province":"Sachsen",
    "wof:name":"Dr. Med. Hansj\u00f6rg Lutterberg",
    "wof:placetype":"venue"
},
  "geometry": {"coordinates":[12.986776,50.611984],"type":"Point"}
}