{
  "type": "Feature",
  "properties": {
    "iso:country":"DE",
    "sg:address":"Hauptstr. 57",
    "sg:city":"Neuenstadt",
    "sg:phone":"+49 7139/2160",
    "sg:postcode":"74196",
    "sg:province":"Baden-W\u00fcrttemberg",
    "wof:name":"H. Schilp",
    "wof:placetype":"venue"
},
  "geometry": {"coordinates":[9.3268699646,49.236831665],"type":"Point"}
}