{
  "type": "Feature",
  "properties": {
    "iso:country":"DE",
    "sg:address":"Frankfurter Str. 92-30",
    "sg:city":"Rodgau",
    "sg:postcode":"63110",
    "sg:province":"Hessen",
    "wof:name":"Discover Ballooning Gmbh",
    "wof:placetype":"venue"
},
  "geometry": {"coordinates":[8.860565,50.001396],"type":"Point"}
}