{
  "type": "Feature",
  "properties": {
    "iso:country":"DE",
    "sg:address":"Landwehrstr. 18",
    "sg:city":"M\u00fcnchen",
    "sg:phone":"+49 89/5458525",
    "sg:postcode":"80336",
    "sg:province":"Bayern",
    "wof:name":"Hotel Deutsches Theater",
    "wof:placetype":"venue"
},
  "geometry": {"coordinates":[11.5621843338,48.1365432739],"type":"Point"}
}