{
  "type": "Feature",
  "properties": {
    "iso:country":"DE",
    "sg:address":"Strahlenbergerstr. 105-107",
    "sg:city":"Offenbach",
    "sg:phone":"+49 69/82377869",
    "sg:postcode":"63067",
    "sg:province":"Hessen",
    "wof:name":"Lithografik Werbe- Und Reproduktions Gmbh",
    "wof:placetype":"venue"
},
  "geometry": {"coordinates":[8.73438,50.107269],"type":"Point"}
}