{
  "type": "Feature",
  "properties": {
    "iso:country":"DE",
    "sg:address":"Gelnh\u00e4user Str. 1",
    "sg:city":"Linsengericht",
    "sg:phone":"+49 6051/72693",
    "sg:postcode":"63589",
    "sg:province":"Hessen",
    "wof:name":"Hans-e. Klippel",
    "wof:placetype":"venue"
},
  "geometry": {"coordinates":[9.1943206787,50.1877861023],"type":"Point"}
}