{
  "type": "Feature",
  "properties": {
    "iso:country":"DE",
    "sg:address":"Marchlewskistra\u00dfe 25",
    "sg:city":"Berlin",
    "sg:phone":"+49 30/29491380",
    "sg:postcode":"10243",
    "sg:province":"Berlin",
    "wof:name":"Mietmoebel-vertrieb",
    "wof:placetype":"venue"
},
  "geometry": {"coordinates":[13.4433231354,52.5156211853],"type":"Point"}
}