{
  "type": "Feature",
  "properties": {
    "iso:country":"DE",
    "sg:address":"Bahnhofstr. 13",
    "sg:city":"Stuttgart",
    "sg:phone":"+49 711/552245",
    "sg:postcode":"70372",
    "sg:province":"Baden-W\u00fcrttemberg",
    "wof:name":"Gpm Gesellschaft F\u00fcr Personalmanagemt Mbh",
    "wof:placetype":"venue"
},
  "geometry": {"coordinates":[9.2174911499,48.8024597168],"type":"Point"}
}