{
  "type": "Feature",
  "properties": {
    "iso:country":"DE",
    "sg:address":"Bessenbacher Weg 15",
    "sg:city":"Haibach",
    "sg:phone":"+49 6021/60821",
    "sg:postcode":"63808",
    "sg:province":"Bayern",
    "wof:name":"Adam Kunkel",
    "wof:placetype":"venue"
},
  "geometry": {"coordinates":[9.1960811615,49.9672775269],"type":"Point"}
}