{
  "type": "Feature",
  "properties": {
    "iso:country":"DE",
    "sg:address":"Wolfegger Str. 52",
    "sg:city":"Weingarten",
    "sg:phone":"+49 751/54889",
    "sg:postcode":"88250",
    "sg:province":"Baden-W\u00fcrttemberg",
    "wof:name":"Gerhard Huber",
    "wof:placetype":"venue"
},
  "geometry": {"coordinates":[9.6517772675,47.8087997437],"type":"Point"}
}