{
  "type": "Feature",
  "properties": {
    "iso:country":"DE",
    "sg:address":"Ledenburg",
    "sg:city":"Bissendorf",
    "sg:postcode":"49143",
    "sg:province":"Niedersachsen",
    "wof:name":"Helmut Feldmann",
    "wof:placetype":"venue"
},
  "geometry": {"coordinates":[8.238935,52.23468],"type":"Point"}
}