{
  "type": "Feature",
  "properties": {
    "iso:country":"DE",
    "sg:address":"Fischbachstr. 34",
    "sg:city":"Meschede",
    "sg:phone":"+49 2934/466",
    "sg:postcode":"59872",
    "sg:province":"Nordrhein-Westfalen",
    "wof:name":"Helmut Feische",
    "wof:placetype":"venue"
},
  "geometry": {"coordinates":[8.138604,51.332958],"type":"Point"}
}