{
  "type": "Feature",
  "properties": {
    "iso:country":"DE",
    "sg:address":"Wasserloses Tal 58",
    "sg:city":"Hagen",
    "sg:postcode":"58093",
    "sg:province":"Nordrhein-Westfalen",
    "wof:name":"Ausflugsfahrten Und Fernzielreisen",
    "wof:placetype":"venue"
},
  "geometry": {"coordinates":[7.4942560196,51.355091095],"type":"Point"}
}