{
  "type": "Feature",
  "properties": {
    "iso:country":"DE",
    "sg:address":"Obertorstr. 22",
    "sg:city":"Leun",
    "sg:phone":"+49 6473/91050",
    "sg:postcode":"35638",
    "sg:province":"Hessen",
    "wof:name":"Carnetto Und Carnetto Partnerschaft-architekt Und",
    "wof:placetype":"venue"
},
  "geometry": {"coordinates":[8.3570613861,50.5517997742],"type":"Point"}
}