{
  "type": "Feature",
  "properties": {
    "iso:country":"DE",
    "sg:address":"Gerauer Str 34",
    "sg:city":"M\u00f6rfelden-Walldorf",
    "sg:phone":"+49 6105/966757",
    "sg:postcode":"64546",
    "sg:province":"Hessen",
    "wof:name":"K.c.s Brandschutz Gmbh",
    "wof:placetype":"venue"
},
  "geometry": {"coordinates":[8.5634698868,49.9691886902],"type":"Point"}
}