{
  "type": "Feature",
  "properties": {
    "iso:country":"DE",
    "sg:address":"Im Wiesengrund 13",
    "sg:city":"Veitsrodt",
    "sg:postcode":"55758",
    "sg:province":"Rheinland-Pfalz",
    "wof:name":"Av Akustik Baubedarf Gmbh",
    "wof:placetype":"venue"
},
  "geometry": {"coordinates":[7.3028330803,49.7562217712],"type":"Point"}
}