{
  "type": "Feature",
  "properties": {
    "iso:country":"DE",
    "sg:address":"Herrnstr. 20",
    "sg:city":"Amberg",
    "sg:phone":"+49 9621/33326",
    "sg:postcode":"92224",
    "sg:province":"Bayern",
    "wof:name":"Funnys",
    "wof:placetype":"venue"
},
  "geometry": {"coordinates":[11.8580770493,49.446762085],"type":"Point"}
}