{
  "type": "Feature",
  "properties": {
    "iso:country":"DE",
    "sg:address":"Leitsm\u00fchle",
    "sg:city":"Emskirchen",
    "sg:phone":"+49 9104/580",
    "sg:postcode":"91448",
    "sg:province":"Bayern",
    "wof:name":"Fritz Ernst",
    "wof:placetype":"venue"
},
  "geometry": {"coordinates":[10.7663345337,49.5560493469],"type":"Point"}
}