{
  "type": "Feature",
  "properties": {
    "iso:country":"DE",
    "sg:address":"Auf dem Pustel 6",
    "sg:city":"Wagenfeld",
    "sg:phone":"+49 5444/1513",
    "sg:postcode":"49419",
    "sg:province":"Niedersachsen",
    "wof:name":"Friedrich Scheland",
    "wof:placetype":"venue"
},
  "geometry": {"coordinates":[8.639893,52.538521],"type":"Point"}
}