{
  "type": "Feature",
  "properties": {
    "iso:country":"DE",
    "sg:address":"Karlsruhestr. 13",
    "sg:city":"Dortmund",
    "sg:phone":"+49 231/591494",
    "sg:postcode":"44143",
    "sg:province":"Nordrhein-Westfalen",
    "wof:name":"Thomas Marzinek",
    "wof:placetype":"venue"
},
  "geometry": {"coordinates":[7.5040168762,51.5191612244],"type":"Point"}
}