{
  "type": "Feature",
  "properties": {
    "iso:country":"DE",
    "sg:address":"Altlandsberger Chaussee 19",
    "sg:city":"Eggersdorf",
    "sg:phone":"+49 3341/48113",
    "sg:postcode":"15345",
    "sg:province":"Brandenburg",
    "wof:name":"U. Helm",
    "wof:placetype":"venue"
},
  "geometry": {"coordinates":[13.8311367035,52.5556488037],"type":"Point"}
}