{
  "type": "Feature",
  "properties": {
    "iso:country":"DE",
    "sg:address":"Kleines Feld 5",
    "sg:city":"Gleichen",
    "sg:phone":"+49 5508/264",
    "sg:postcode":"37130",
    "sg:province":"Niedersachsen",
    "wof:name":"Scheiter",
    "wof:placetype":"venue"
},
  "geometry": {"coordinates":[10.0101709366,51.4952125549],"type":"Point"}
}