{
  "type": "Feature",
  "properties": {
    "iso:country":"DE",
    "sg:address":"Bahnhofstr. 30",
    "sg:city":"B\u00fcdingen",
    "sg:phone":"+49 6042/4530",
    "sg:postcode":"63654",
    "sg:province":"Hessen",
    "wof:name":"Stadt-apotheke",
    "wof:placetype":"venue"
},
  "geometry": {"coordinates":[9.108345,50.290611],"type":"Point"}
}