{
  "type": "Feature",
  "properties": {
    "iso:country":"DE",
    "sg:address":"Grundstr. 11",
    "sg:city":"Horhausen",
    "sg:phone":"+49 2687/457",
    "sg:postcode":"56593",
    "sg:province":"Rheinland-Pfalz",
    "wof:name":"Bausparkasse W\u00fcstenrot Stefan Birke",
    "wof:placetype":"venue"
},
  "geometry": {"coordinates":[7.504065,50.580383],"type":"Point"}
}