{
  "type": "Feature",
  "properties": {
    "iso:country":"DE",
    "sg:address":"Gr\u00f6pern 5",
    "sg:city":"Helmstedt",
    "sg:phone":"+49 4953/512511",
    "sg:postcode":"38350",
    "sg:province":"Niedersachsen",
    "wof:name":"Commerzbank Ag",
    "wof:placetype":"venue"
},
  "geometry": {"coordinates":[11.005805,52.228416],"type":"Point"}
}