{
  "type": "Feature",
  "properties": {
    "iso:country":"DE",
    "sg:address":"Allensteiner Str. 1",
    "sg:city":"Harpstedt",
    "sg:phone":"+49 4244/1772",
    "sg:postcode":"27243",
    "sg:province":"Niedersachsen",
    "wof:name":"Rudolf Skrotzki Sandstrahlentrostung",
    "wof:placetype":"venue"
},
  "geometry": {"coordinates":[8.596063,52.917309],"type":"Point"}
}