{
  "type": "Feature",
  "properties": {
    "iso:country":"DE",
    "sg:address":"Lennestr. 4",
    "sg:city":"Aachen",
    "sg:phone":"+49 241/889390",
    "sg:postcode":"52074",
    "sg:province":"Nordrhein-Westfalen",
    "wof:name":"Leo F\u00fchren",
    "wof:placetype":"venue"
},
  "geometry": {"coordinates":[6.0599021912,50.770526886],"type":"Point"}
}