{
  "type": "Feature",
  "properties": {
    "iso:country":"DE",
    "sg:address":"Industriestr. 22-24",
    "sg:city":"Birkenfeld",
    "sg:phone":"+49 7231/48345",
    "sg:postcode":"75217",
    "sg:province":"Baden-W\u00fcrttemberg",
    "wof:name":"C & C Gro\u00dfmarkt",
    "wof:placetype":"venue"
},
  "geometry": {"coordinates":[8.6459522247,48.8736610413],"type":"Point"}
}