{
  "type": "Feature",
  "properties": {
    "iso:country":"DE",
    "sg:address":"Wachmannstr. 125",
    "sg:city":"Bremen",
    "sg:phone":"+49 421/344061",
    "sg:postcode":"28209",
    "sg:province":"Bremen",
    "wof:name":"Karl-heinz Wichmann Architekt",
    "wof:placetype":"venue"
},
  "geometry": {"coordinates":[8.836612,53.087101],"type":"Point"}
}