{
  "type": "Feature",
  "properties": {
    "iso:country":"DE",
    "sg:address":"Potsdamer Str. 14",
    "sg:city":"Berlin",
    "sg:phone":"+49 30/8015354",
    "sg:postcode":"14163",
    "sg:province":"Berlin",
    "wof:name":"Hans-peter Mahling",
    "wof:placetype":"venue"
},
  "geometry": {"coordinates":[13.2437868118,52.4336967468],"type":"Point"}
}