{
  "type": "Feature",
  "properties": {
    "iso:country":"DE",
    "sg:address":"Siedenburg",
    "sg:city":"Siedenburg",
    "sg:phone":"+49 4272/7024",
    "sg:postcode":"27254",
    "sg:province":"Niedersachsen",
    "wof:name":"Volksbank Eg",
    "wof:placetype":"venue"
},
  "geometry": {"coordinates":[8.938873,52.693752],"type":"Point"}
}