{
  "type": "Feature",
  "properties": {
    "iso:country":"DE",
    "sg:address":"Klarastr. 8",
    "sg:city":"Heilbronn",
    "sg:phone":"+49 7131/87594",
    "sg:postcode":"74072",
    "sg:province":"Baden-W\u00fcrttemberg",
    "wof:name":"Star Kebap",
    "wof:placetype":"venue"
},
  "geometry": {"coordinates":[9.2204027176,49.1405715942],"type":"Point"}
}