{
  "type": "Feature",
  "properties": {
    "iso:country":"DE",
    "sg:address":"Kirchplatz 18",
    "sg:city":"Grassau",
    "sg:phone":"+49 8641/4050",
    "sg:postcode":"83224",
    "sg:province":"Bayern",
    "wof:name":"Hotel Restaurant In Grassau Am Chiemsee Oberbayern",
    "wof:placetype":"venue"
},
  "geometry": {"coordinates":[12.4490013123,47.7788505554],"type":"Point"}
}