{
  "type": "Feature",
  "properties": {
    "iso:country":"DE",
    "sg:address":"Auf der Obersten Beunde 21",
    "sg:city":"B\u00fcdingen",
    "sg:phone":"+49 6042/3572",
    "sg:postcode":"63654",
    "sg:province":"Hessen",
    "wof:name":"Richard M\u00fcller Architekt",
    "wof:placetype":"venue"
},
  "geometry": {"coordinates":[9.1147356033,50.2952766418],"type":"Point"}
}