{
  "type": "Feature",
  "properties": {
    "iso:country":"DE",
    "sg:address":"M\u00fchlenstr. 29",
    "sg:city":"Rotenburg",
    "sg:phone":"+49 4261/83733",
    "sg:postcode":"27356",
    "sg:province":"Niedersachsen",
    "wof:name":"Wilhelm Stelling",
    "wof:placetype":"venue"
},
  "geometry": {"coordinates":[9.3975334167,53.1045684814],"type":"Point"}
}