{
  "type": "Feature",
  "properties": {
    "iso:country":"DE",
    "sg:address":"Franzstr. 21",
    "sg:city":"Berlin",
    "sg:postcode":"13595",
    "sg:province":"Berlin",
    "wof:name":"Spezial-elektronik-gerbsch Inh. Petra Gerbsch E. Kfr.",
    "wof:placetype":"venue"
},
  "geometry": {"coordinates":[13.2002029419,52.5224685669],"type":"Point"}
}