{
  "type": "Feature",
  "properties": {
    "iso:country":"DE",
    "sg:address":"Wilhelmstr. 67",
    "sg:city":"Aalen",
    "sg:phone":"+49 7361/5021",
    "sg:postcode":"73433",
    "sg:province":"Baden-W\u00fcrttemberg",
    "wof:name":"Ofenplattensammlung D. Schw\u00e4b. H\u00fcttenwerke",
    "wof:placetype":"venue"
},
  "geometry": {"coordinates":[10.10039,48.8535],"type":"Point"}
}