{
  "type": "Feature",
  "properties": {
    "iso:country":"DE",
    "sg:address":"Langenfelder Str. 16",
    "sg:city":"Idar-Oberstein",
    "sg:phone":"+49 6784/6907",
    "sg:postcode":"55743",
    "sg:province":"Rheinland-Pfalz",
    "wof:name":"J. Kloos & S\u00f6hne Inh. G. Kloos",
    "wof:placetype":"venue"
},
  "geometry": {"coordinates":[7.3844799995,49.7274284363],"type":"Point"}
}