{
  "type": "Feature",
  "properties": {
    "iso:country":"DE",
    "sg:address":"Am Sportplatz 6",
    "sg:city":"Reichertshofen",
    "sg:postcode":"85084",
    "sg:province":"Bayern",
    "wof:name":"Deutsche Shell Ag",
    "wof:placetype":"venue"
},
  "geometry": {"coordinates":[11.5128011703,48.6342887878],"type":"Point"}
}