{
  "type": "Feature",
  "properties": {
    "iso:country":"DE",
    "sg:address":"Allersberger Stra\u00dfe 93",
    "sg:city":"Roth",
    "sg:phone":"+49 9171/896156",
    "sg:postcode":"91154",
    "sg:province":"Bayern",
    "wof:name":"Ger\u00e4te-verleih-roth",
    "wof:placetype":"venue"
},
  "geometry": {"coordinates":[11.1065616608,49.2463111877],"type":"Point"}
}