{
  "type": "Feature",
  "properties": {
    "iso:country":"DE",
    "sg:address":"Irisweg 95",
    "sg:city":"K\u00f6ln",
    "sg:phone":"+49 2203/84804",
    "sg:postcode":"51143",
    "sg:province":"Nordrhein-Westfalen",
    "wof:name":"Ernst Ludwig",
    "wof:placetype":"venue"
},
  "geometry": {"coordinates":[7.0531601906,50.8754348755],"type":"Point"}
}