{
  "type": "Feature",
  "properties": {
    "iso:country":"DE",
    "sg:address":"Adenauerallee 115",
    "sg:city":"Gelsenkirchen",
    "sg:phone":"+49 209/9544231",
    "sg:postcode":"45891",
    "sg:province":"Nordrhein-Westfalen",
    "wof:name":"Gelsenrein",
    "wof:placetype":"venue"
},
  "geometry": {"coordinates":[7.071575,51.562977],"type":"Point"}
}