{
  "type": "Feature",
  "properties": {
    "iso:country":"DE",
    "sg:address":"Lister Damm 13",
    "sg:city":"Hannover",
    "sg:phone":"+49 511/392240",
    "sg:postcode":"30163",
    "sg:province":"Niedersachsen",
    "wof:name":"Klose Schriftwerbung",
    "wof:placetype":"venue"
},
  "geometry": {"coordinates":[9.753735,52.398376],"type":"Point"}
}