{
  "type": "Feature",
  "properties": {
    "iso:country":"DE",
    "sg:address":"Max-Planck-Str. 10",
    "sg:city":"Achim",
    "sg:phone":"+49 4202/91640",
    "sg:postcode":"28832",
    "sg:province":"Niedersachsen",
    "wof:name":"Heinrich Staas Gmbh",
    "wof:placetype":"venue"
},
  "geometry": {"coordinates":[9.0608406067,53.0236854553],"type":"Point"}
}