{
  "type": "Feature",
  "properties": {
    "iso:country":"DE",
    "sg:address":"Elseyer Str. 41",
    "sg:city":"Hagen",
    "sg:phone":"+49 2334/961250",
    "sg:postcode":"58119",
    "sg:province":"Nordrhein-Westfalen",
    "wof:name":"Hans-peter Dittrich",
    "wof:placetype":"venue"
},
  "geometry": {"coordinates":[7.554024,51.364101],"type":"Point"}
}