{
  "type": "Feature",
  "properties": {
    "iso:country":"DE",
    "sg:address":"Friedrichstr. 3",
    "sg:city":"Neustadt",
    "sg:phone":"+49 6321/30428",
    "sg:postcode":"67433",
    "sg:province":"Rheinland-Pfalz",
    "wof:name":"Bettis Modeladen",
    "wof:placetype":"venue"
},
  "geometry": {"coordinates":[8.1397,49.351845],"type":"Point"}
}