{
  "type": "Feature",
  "properties": {
    "iso:country":"DE",
    "sg:address":"Waldstr. 3",
    "sg:city":"Bad Kleinen",
    "sg:phone":"+49 38423/50575",
    "sg:postcode":"23996",
    "sg:province":"Mecklenburg-Vorpommern",
    "wof:name":"Ronald Dummer",
    "wof:placetype":"venue"
},
  "geometry": {"coordinates":[11.465024,53.768688],"type":"Point"}
}