{
  "type": "Feature",
  "properties": {
    "iso:country":"DE",
    "sg:address":"Westring 47",
    "sg:city":"Bochum",
    "sg:phone":"+49 234/66067",
    "sg:postcode":"44787",
    "sg:province":"Nordrhein-Westfalen",
    "wof:name":"G\u00fcnter Deffner Rechtsanwalt",
    "wof:placetype":"venue"
},
  "geometry": {"coordinates":[7.2110710144,51.4831733704],"type":"Point"}
}