{
  "type": "Feature",
  "properties": {
    "iso:country":"DE",
    "sg:address":"Postfach 837132",
    "sg:city":"N\u00fcrnberg",
    "sg:phone":"+49 911/3187054",
    "sg:postcode":"90255",
    "sg:province":"Bayern",
    "wof:name":"Kontakt-maedchen, Partner, Partnerwahl, Erotikkont",
    "wof:placetype":"venue"
},
  "geometry": {"coordinates":[11.08048,49.45052],"type":"Point"}
}