{
  "type": "Feature",
  "properties": {
    "iso:country":"DE",
    "sg:address":"Hauptstr. 37",
    "sg:city":"Landstuhl",
    "sg:phone":"+49 6371/15003",
    "sg:postcode":"66849",
    "sg:province":"Rheinland-Pfalz",
    "wof:name":"Servimed - Homecare Gmbh",
    "wof:placetype":"venue"
},
  "geometry": {"coordinates":[7.569836,49.409458],"type":"Point"}
}