{
  "type": "Feature",
  "properties": {
    "iso:country":"DE",
    "sg:address":"Wilhelm-Theodor-R\u00f6mheld-Str.",
    "sg:city":"Mainz",
    "sg:postcode":"55130",
    "sg:province":"Rheinland-Pfalz",
    "wof:name":"Pyrit Grundst\u00fccksverwaltungs Gmbh & Co. Vermietungs Kg",
    "wof:placetype":"venue"
},
  "geometry": {"coordinates":[8.289355278,49.982170105],"type":"Point"}
}