{
  "type": "Feature",
  "properties": {
    "iso:country":"DE",
    "sg:address":"H\u00f6festeig 5",
    "sg:city":"Lensahn",
    "sg:phone":"+49 4363/3483",
    "sg:postcode":"23738",
    "sg:province":"Schleswig-Holstein",
    "wof:name":"Veronika Fick Masseurin",
    "wof:placetype":"venue"
},
  "geometry": {"coordinates":[10.88693,54.219151],"type":"Point"}
}