{
  "type": "Feature",
  "properties": {
    "iso:country":"DE",
    "sg:address":"Kleinwolmsdorfer Str 38",
    "sg:city":"Arnsdorf",
    "sg:phone":"+49 35200/3100",
    "sg:postcode":"01477",
    "sg:province":"Sachsen",
    "wof:name":"Planat Gmbh",
    "wof:placetype":"venue"
},
  "geometry": {"coordinates":[13.973748,51.090687],"type":"Point"}
}