{
  "type": "Feature",
  "properties": {
    "iso:country":"DE",
    "sg:address":"Kirchstr. 83",
    "sg:city":"Mainz",
    "sg:phone":"+49 6131/41254",
    "sg:postcode":"55124",
    "sg:province":"Rheinland-Pfalz",
    "wof:name":"Mady Strutz",
    "wof:placetype":"venue"
},
  "geometry": {"coordinates":[8.204387,50.005417],"type":"Point"}
}