{
  "type": "Feature",
  "properties": {
    "iso:country":"DE",
    "sg:address":"Scheffelstr. 4",
    "sg:city":"Belm",
    "sg:phone":"+49 5406/4979",
    "sg:postcode":"49191",
    "sg:province":"Niedersachsen",
    "wof:name":"Dr. Med. Hagen Wegner",
    "wof:placetype":"venue"
},
  "geometry": {"coordinates":[8.1392498016,52.3108215332],"type":"Point"}
}