{
  "type": "Feature",
  "properties": {
    "iso:country":"DE",
    "sg:address":"Drygalski-Allee 117",
    "sg:city":"M\u00fcnchen",
    "sg:phone":"+49 89/79100130",
    "sg:postcode":"81477",
    "sg:province":"Bayern",
    "wof:name":"Hl-markt",
    "wof:placetype":"venue"
},
  "geometry": {"coordinates":[11.5039796829,48.08253479],"type":"Point"}
}