{
  "type": "Feature",
  "properties": {
    "iso:country":"DE",
    "sg:address":"Ernst-Th\u00e4lmann-Str. 9",
    "sg:city":"Wiesenburg",
    "sg:phone":"+49 33849/50410",
    "sg:postcode":"14827",
    "sg:province":"Brandenburg",
    "wof:name":"C. Fischer",
    "wof:placetype":"venue"
},
  "geometry": {"coordinates":[12.460261,52.112846],"type":"Point"}
}