{
  "type": "Feature",
  "properties": {
    "iso:country":"DE",
    "sg:address":"Scharnhorststr. 1a",
    "sg:city":"Mannheim",
    "sg:phone":"+49 621/793521",
    "sg:postcode":"68259",
    "sg:province":"Baden-W\u00fcrttemberg",
    "wof:name":"Rotes Schaf",
    "wof:placetype":"venue"
},
  "geometry": {"coordinates":[8.5304327011,49.4886398315],"type":"Point"}
}