{
  "type": "Feature",
  "properties": {
    "iso:country":"DE",
    "sg:address":"W\u00fcrfelturmstr. 14",
    "sg:city":"Hofgeismar",
    "sg:phone":"+49 5671/50350",
    "sg:postcode":"34369",
    "sg:province":"Hessen",
    "wof:name":"Axel Manzow",
    "wof:placetype":"venue"
},
  "geometry": {"coordinates":[9.3834543228,51.4955101013],"type":"Point"}
}