{
  "type": "Feature",
  "properties": {
    "iso:country":"DE",
    "sg:address":"Lindenstr. 10",
    "sg:city":"Sontheim",
    "sg:phone":"+49 7325/4573",
    "sg:postcode":"89567",
    "sg:province":"Baden-W\u00fcrttemberg",
    "wof:name":"Alfred Brose",
    "wof:placetype":"venue"
},
  "geometry": {"coordinates":[9.663512,48.442799],"type":"Point"}
}