{
  "type": "Feature",
  "properties": {
    "iso:country":"DE",
    "sg:address":"Siedlerstr. 20",
    "sg:city":"Wendelstein",
    "sg:phone":"+49 9129/8553",
    "sg:postcode":"90530",
    "sg:province":"Bayern",
    "wof:name":"L. Brandl Heissmangel",
    "wof:placetype":"venue"
},
  "geometry": {"coordinates":[11.1094388962,49.348651886],"type":"Point"}
}