{
  "type": "Feature",
  "properties": {
    "iso:country":"DE",
    "sg:address":"Buersche Str. 148",
    "sg:city":"Osnabr\u00fcck",
    "sg:phone":"+49 541/75238",
    "sg:postcode":"49084",
    "sg:province":"Niedersachsen",
    "wof:name":"Restaurant Hong Kong",
    "wof:placetype":"venue"
},
  "geometry": {"coordinates":[8.0752668381,52.2745475769],"type":"Point"}
}