{
  "type": "Feature",
  "properties": {
    "iso:country":"DE",
    "sg:address":"Industriestr. 16",
    "sg:city":"Hagenbach",
    "sg:postcode":"76767",
    "sg:province":"Rheinland-Pfalz",
    "wof:name":"Wendte Verwaltungs- Gmbh",
    "wof:placetype":"venue"
},
  "geometry": {"coordinates":[8.2558259964,49.0105133057],"type":"Point"}
}