{
  "type": "Feature",
  "properties": {
    "iso:country":"DE",
    "sg:address":"Walhallastr. 1",
    "sg:city":"M\u00fcnchen",
    "sg:phone":"+49 89/173766",
    "sg:postcode":"80639",
    "sg:province":"Bayern",
    "wof:name":"Axel Schramm Kameramann",
    "wof:placetype":"venue"
},
  "geometry": {"coordinates":[11.5087680817,48.150226593],"type":"Point"}
}