{
  "type": "Feature",
  "properties": {
    "iso:country":"DE",
    "sg:address":"Hansaring 141",
    "sg:city":"Greven",
    "sg:phone":"+49 2571/1212",
    "sg:postcode":"48268",
    "sg:province":"Nordrhein-Westfalen",
    "wof:name":"Latec Ersatzteil-vertriebs- Gesellschaft Mbh",
    "wof:placetype":"venue"
},
  "geometry": {"coordinates":[7.6145868301,52.1084442139],"type":"Point"}
}