{
  "type": "Feature",
  "properties": {
    "iso:country":"DE",
    "sg:address":"Hugstetter Stra\u00dfe 55",
    "sg:city":"Freiburg",
    "sg:phone":"+49 761/2702732",
    "sg:postcode":"79106",
    "sg:province":"Baden-W\u00fcrttemberg",
    "wof:name":"Deutsche Transplantationsgesellschaft",
    "wof:placetype":"venue"
},
  "geometry": {"coordinates":[7.839419,48.005589],"type":"Point"}
}