{
  "type": "Feature",
  "properties": {
    "iso:country":"DE",
    "sg:address":"Abensberger Str. 50",
    "sg:city":"Mainburg",
    "sg:phone":"+49 8751/2233",
    "sg:postcode":"84048",
    "sg:province":"Bayern",
    "wof:name":"Sanivital Pfaffeneder Gmbh",
    "wof:placetype":"venue"
},
  "geometry": {"coordinates":[11.7847652435,48.6470222473],"type":"Point"}
}