{
  "type": "Feature",
  "properties": {
    "iso:country":"DE",
    "sg:address":"Im Teich 4b",
    "sg:city":"Pforzheim",
    "sg:phone":"+49 7231/72221",
    "sg:postcode":"75180",
    "sg:province":"Baden-W\u00fcrttemberg",
    "wof:name":"Fotostudio Atelier Petite",
    "wof:placetype":"venue"
},
  "geometry": {"coordinates":[8.672783,48.876308],"type":"Point"}
}