{
  "type": "Feature",
  "properties": {
    "iso:country":"DE",
    "sg:address":"Holser Str. 3",
    "sg:city":"B\u00fcnde",
    "sg:phone":"+49 5223/4016",
    "sg:postcode":"32257",
    "sg:province":"Nordrhein-Westfalen",
    "wof:name":"Pacs Handelsgesellschaft Backhaus Gmbh",
    "wof:placetype":"venue"
},
  "geometry": {"coordinates":[8.5669603348,52.2031288147],"type":"Point"}
}