{
  "type": "Feature",
  "properties": {
    "iso:country":"DE",
    "sg:address":"Fichtengrund 1",
    "sg:city":"Biesenthal",
    "sg:phone":"+49 3337/2529",
    "sg:postcode":"16359",
    "sg:province":"Brandenburg",
    "wof:name":"M. K\u00f6ster",
    "wof:placetype":"venue"
},
  "geometry": {"coordinates":[13.662787,52.760078],"type":"Point"}
}