{
  "type": "Feature",
  "properties": {
    "iso:country":"DE",
    "sg:address":"Diedorfer Str. 7",
    "sg:city":"Diedorf",
    "sg:phone":"+49 821/482357",
    "sg:postcode":"86420",
    "sg:province":"Bayern",
    "wof:name":"Rudolf Urian",
    "wof:placetype":"venue"
},
  "geometry": {"coordinates":[10.762144,48.372726],"type":"Point"}
}