{
  "type": "Feature",
  "properties": {
    "iso:country":"DE",
    "sg:address":"Karlstr. 3",
    "sg:city":"M\u00fcnchberg",
    "sg:phone":"+49 9251/928767",
    "sg:postcode":"95213",
    "sg:province":"Bayern",
    "wof:name":"Frank St\u00f6cker",
    "wof:placetype":"venue"
},
  "geometry": {"coordinates":[11.791015625,50.1905937195],"type":"Point"}
}