{
  "type": "Feature",
  "properties": {
    "iso:country":"DE",
    "sg:address":"Konrad-Adenauer-Str. 11 a",
    "sg:city":"Monschau",
    "sg:phone":"+49 2472/5438",
    "sg:postcode":"52156",
    "sg:province":"Nordrhein-Westfalen",
    "wof:name":"Dieter Schmitz Steuerberater",
    "wof:placetype":"venue"
},
  "geometry": {"coordinates":[6.2541117668,50.5863265991],"type":"Point"}
}