{
  "type": "Feature",
  "properties": {
    "iso:country":"DE",
    "sg:address":"Stimbergstr. 207",
    "sg:city":"Oer-Erkenschwick",
    "sg:phone":"+49 2368/60379",
    "sg:postcode":"45739",
    "sg:province":"Nordrhein-Westfalen",
    "wof:name":"Heinz Schwakenberg",
    "wof:placetype":"venue"
},
  "geometry": {"coordinates":[7.255349,51.645588],"type":"Point"}
}