{
  "type": "Feature",
  "properties": {
    "iso:country":"DE",
    "sg:address":"Stiftsweg 10",
    "sg:city":"Goch",
    "sg:postcode":"47574",
    "sg:province":"Nordrhein-Westfalen",
    "wof:name":"Kath. Pfarramt St. Stephanus",
    "wof:placetype":"venue"
},
  "geometry": {"coordinates":[6.0734357834,51.7087135315],"type":"Point"}
}