{
  "type": "Feature",
  "properties": {
    "iso:country":"DE",
    "sg:address":"Borkener Str. 18",
    "sg:city":"Coesfeld",
    "sg:phone":"+49 2541/880990",
    "sg:postcode":"48653",
    "sg:province":"Nordrhein-Westfalen",
    "wof:name":"Gisbert Falk",
    "wof:placetype":"venue"
},
  "geometry": {"coordinates":[7.1585521698,51.9439582825],"type":"Point"}
}