{
  "type": "Feature",
  "properties": {
    "iso:country":"DE",
    "sg:city":"Untergruppenbach",
    "sg:phone":"+49 4971/3170990",
    "sg:postcode":"74199",
    "sg:province":"Baden-W\u00fcrttemberg",
    "wof:name":"Kreissparkasse Heilbronn",
    "wof:placetype":"venue"
},
  "geometry": {"coordinates":[9.277635,49.088093],"type":"Point"}
}