{
  "type": "Feature",
  "properties": {
    "iso:country":"DE",
    "sg:address":"Schrangenstr. 23",
    "sg:city":"Ratzeburg",
    "sg:phone":"+49 4541/3725",
    "sg:postcode":"23909",
    "sg:province":"Schleswig-Holstein",
    "wof:name":"H. Woller",
    "wof:placetype":"venue"
},
  "geometry": {"coordinates":[10.7742395401,53.6974411011],"type":"Point"}
}