{
  "type": "Feature",
  "properties": {
    "iso:country":"DE",
    "sg:address":"Hauptstr. 12",
    "sg:city":"Ottersberg",
    "sg:phone":"+49 4205/8675",
    "sg:postcode":"28870",
    "sg:province":"Niedersachsen",
    "wof:name":"G. Bergstedt",
    "wof:placetype":"venue"
},
  "geometry": {"coordinates":[9.15119,53.130798],"type":"Point"}
}