{
  "type": "Feature",
  "properties": {
    "iso:country":"DE",
    "sg:address":"Neptunstr. 2",
    "sg:city":"Nordenham",
    "sg:phone":"+49 4731/99980",
    "sg:postcode":"26954",
    "sg:province":"Niedersachsen",
    "wof:name":"Elektrotechnik Janssen Gmbh",
    "wof:placetype":"venue"
},
  "geometry": {"coordinates":[8.52858,53.525051],"type":"Point"}
}