{
  "type": "Feature",
  "properties": {
    "iso:country":"DE",
    "sg:address":"Im Henkenhof 2",
    "sg:city":"Hilchenbach",
    "sg:phone":"+49 2733",
    "sg:postcode":"57271",
    "sg:province":"Nordrhein-Westfalen",
    "wof:name":"Glasklar D. Batschun",
    "wof:placetype":"venue"
},
  "geometry": {"coordinates":[8.135589,51.000137],"type":"Point"}
}