{
  "type": "Feature",
  "properties": {
    "iso:country":"DE",
    "sg:address":"Schwangauer Str. 20",
    "sg:city":"F\u00fcssen",
    "sg:phone":"+49 8362/7745",
    "sg:postcode":"87629",
    "sg:province":"Bayern",
    "wof:name":"Hotel Kapuziner",
    "wof:placetype":"venue"
},
  "geometry": {"coordinates":[10.7026691437,47.5653038025],"type":"Point"}
}