{
  "type": "Feature",
  "properties": {
    "iso:country":"DE",
    "sg:address":"Goethestr. 98a",
    "sg:city":"Riesa",
    "sg:phone":"+49 3525/520236",
    "sg:postcode":"01587",
    "sg:province":"Sachsen",
    "wof:name":"Medical Pharma Logistics Gmbh & Co. Kg",
    "wof:placetype":"venue"
},
  "geometry": {"coordinates":[13.3026475906,51.3045578003],"type":"Point"}
}