{
  "type": "Feature",
  "properties": {
    "iso:country":"DE",
    "sg:address":"Kurf\u00fcrstendamm 75",
    "sg:city":"Berlin",
    "sg:phone":"+49 30/2916494",
    "sg:postcode":"10709",
    "sg:province":"Berlin",
    "wof:name":"Jangtse River Handels Gmbh",
    "wof:placetype":"venue"
},
  "geometry": {"coordinates":[13.3036403656,52.4995269775],"type":"Point"}
}