{
  "type": "Feature",
  "properties": {
    "iso:country":"DE",
    "sg:address":"Kl\u00f6renstr. 61",
    "sg:city":"Oberhausen",
    "sg:phone":"+49 208/22715",
    "sg:postcode":"46045",
    "sg:province":"Nordrhein-Westfalen",
    "wof:name":"Gerhard Pascher Gmbh",
    "wof:placetype":"venue"
},
  "geometry": {"coordinates":[6.8599,51.463566],"type":"Point"}
}