{
  "type": "Feature",
  "properties": {
    "iso:country":"DE",
    "sg:address":"Rathenaustr. 57",
    "sg:city":"Neu-Isenburg",
    "sg:postcode":"63263",
    "sg:province":"Hessen",
    "wof:name":"Cosmik Gmbh",
    "wof:placetype":"venue"
},
  "geometry": {"coordinates":[8.6794300079,50.0421066284],"type":"Point"}
}