{
  "type": "Feature",
  "properties": {
    "iso:country":"DE",
    "sg:address":"Dr.-Mack-Str. 81",
    "sg:city":"F\u00fcrth",
    "sg:postcode":"90762",
    "sg:province":"Bayern",
    "wof:name":"Deltronix Gesellschaft F\u00fcr Industrie-elektronik Mbh",
    "wof:placetype":"venue"
},
  "geometry": {"coordinates":[11.01053,49.468449],"type":"Point"}
}