{
  "type": "Feature",
  "properties": {
    "iso:country":"DE",
    "sg:address":"Postfach",
    "sg:city":"Pegau",
    "sg:phone":"+49 34296",
    "sg:postcode":"04521",
    "sg:province":"Sachsen",
    "wof:name":"Sex & Pleasure; Lovetoys And Freepics - Online",
    "wof:placetype":"venue"
},
  "geometry": {"coordinates":[12.253355,51.167225],"type":"Point"}
}