{
  "type": "Feature",
  "properties": {
    "iso:country":"DE",
    "sg:address":"In der Eisenbach 55",
    "sg:city":"Idstein",
    "sg:phone":"+49 6126/6666",
    "sg:postcode":"65510",
    "sg:province":"Hessen",
    "wof:name":"Wilhelm F. Falkenhorst Heilpraktiker",
    "wof:placetype":"venue"
},
  "geometry": {"coordinates":[8.2608375549,50.2108573914],"type":"Point"}
}