{
  "type": "Feature",
  "properties": {
    "iso:country":"DE",
    "sg:address":"Zeller Weg 8",
    "sg:city":"Schrozberg",
    "sg:phone":"+49 7935/919160",
    "sg:postcode":"74575",
    "sg:province":"Baden-W\u00fcrttemberg",
    "wof:name":"Aktiv-markt",
    "wof:placetype":"venue"
},
  "geometry": {"coordinates":[9.9751300812,49.3474502563],"type":"Point"}
}