{
  "type": "Feature",
  "properties": {
    "iso:country":"DE",
    "sg:address":"Ernst-Sachs-Stra\u00dfe 62",
    "sg:city":"Schweinfurt",
    "sg:phone":"+49 9721",
    "sg:postcode":"97419",
    "sg:province":"Bayern",
    "wof:name":"Fichtel & Sachs Ag",
    "wof:placetype":"venue"
},
  "geometry": {"coordinates":[10.2125759125,50.0320510864],"type":"Point"}
}