{
  "type": "Feature",
  "properties": {
    "iso:country":"DE",
    "sg:address":"Volksgartenstr. 10",
    "sg:city":"D\u00fcsseldorf",
    "sg:postcode":"40227",
    "sg:province":"Nordrhein-Westfalen",
    "wof:name":"Tl Management Gmbh",
    "wof:placetype":"venue"
},
  "geometry": {"coordinates":[6.7939162254,51.2118873596],"type":"Point"}
}