{
  "type": "Feature",
  "properties": {
    "iso:country":"DE",
    "sg:address":"Heinrich-Schmidt-Str. 19",
    "sg:city":"Lollar",
    "sg:phone":"+49 6406/1558",
    "sg:postcode":"35457",
    "sg:province":"Hessen",
    "wof:name":"Dr. Helmut Kirschnick Tierarzt",
    "wof:placetype":"venue"
},
  "geometry": {"coordinates":[8.7064828873,50.6424026489],"type":"Point"}
}