{
  "type": "Feature",
  "properties": {
    "iso:country":"DE",
    "sg:address":"August-Bebel-Str. 7",
    "sg:city":"Spremberg",
    "sg:phone":"+49 3563/90083",
    "sg:postcode":"03130",
    "sg:province":"Brandenburg",
    "wof:name":"Michael F\u00f6rster Rechtsanwalt",
    "wof:placetype":"venue"
},
  "geometry": {"coordinates":[14.3859863281,51.565990448],"type":"Point"}
}