{
  "type": "Feature",
  "properties": {
    "iso:country":"DE",
    "sg:address":"Kupfergasse 7-9",
    "sg:city":"Esslingen",
    "sg:phone":"+49 711/353818",
    "sg:postcode":"73728",
    "sg:province":"Baden-W\u00fcrttemberg",
    "wof:name":"Volkmar Onat",
    "wof:placetype":"venue"
},
  "geometry": {"coordinates":[9.3113718033,48.7405166626],"type":"Point"}
}