{
  "type": "Feature",
  "properties": {
    "iso:country":"DE",
    "sg:address":"Kardinal-Wendel-Str. 1",
    "sg:city":"Wolfratshausen",
    "sg:phone":"+49 8171/16850",
    "sg:postcode":"82515",
    "sg:province":"Bayern",
    "wof:name":"Oskar John",
    "wof:placetype":"venue"
},
  "geometry": {"coordinates":[11.4417104721,47.8984794617],"type":"Point"}
}