{
  "type": "Feature",
  "properties": {
    "iso:country":"DE",
    "sg:city":"Neuenkirchen",
    "sg:phone":"+49 4837/209",
    "sg:postcode":"25792",
    "sg:province":"Schleswig-Holstein",
    "wof:name":"Karl-heinz Gehrts B\u00e4ckerei",
    "wof:placetype":"venue"
},
  "geometry": {"coordinates":[8.990545,54.236069],"type":"Point"}
}