{
  "type": "Feature",
  "properties": {
    "iso:country":"DE",
    "sg:address":"Heideweg 22",
    "sg:city":"Brome",
    "sg:phone":"+49 5833",
    "sg:postcode":"38465",
    "sg:province":"Niedersachsen",
    "wof:name":"Internetpr\u00e4sentationen",
    "wof:placetype":"venue"
},
  "geometry": {"coordinates":[10.9311723709,52.597038269],"type":"Point"}
}