{
  "type": "Feature",
  "properties": {
    "iso:country":"DE",
    "sg:address":"Br\u00fccktorstr. 34",
    "sg:city":"Buttst\u00e4dt",
    "sg:phone":"+49 36373/9300",
    "sg:postcode":"99628",
    "sg:province":"Th\u00fcringen",
    "wof:name":"Hans Pfannkuchen",
    "wof:placetype":"venue"
},
  "geometry": {"coordinates":[11.4143209457,51.1205329895],"type":"Point"}
}