{
  "type": "Feature",
  "properties": {
    "iso:country":"DE",
    "sg:address":"Am Dieburger Berg 23",
    "sg:city":"Reinheim",
    "sg:phone":"+49 6162/50239",
    "sg:postcode":"64354",
    "sg:province":"Hessen",
    "wof:name":"Hans Dieter Johst",
    "wof:placetype":"venue"
},
  "geometry": {"coordinates":[8.7926502228,49.8465385437],"type":"Point"}
}