{
  "type": "Feature",
  "properties": {
    "iso:country":"DE",
    "sg:address":"Steinstr. 2",
    "sg:city":"Klingenm\u00fcnster",
    "sg:phone":"+49 6349/3417",
    "sg:postcode":"76889",
    "sg:province":"Rheinland-Pfalz",
    "wof:name":"Gemeindeb\u00fccherei",
    "wof:placetype":"venue"
},
  "geometry": {"coordinates":[8.018272,49.140488],"type":"Point"}
}