{
  "type": "Feature",
  "properties": {
    "iso:country":"DE",
    "sg:address":"Robert-Leicht-Str. 143b",
    "sg:city":"Stuttgart",
    "sg:phone":"+49 711/682460",
    "sg:postcode":"70569",
    "sg:province":"Baden-W\u00fcrttemberg",
    "wof:name":"Zheng Im- Und Export Gmbh",
    "wof:placetype":"venue"
},
  "geometry": {"coordinates":[9.1094913483,48.7434806824],"type":"Point"}
}