{
  "type": "Feature",
  "properties": {
    "iso:country":"DE",
    "sg:address":"Theodor-Heuss-Str. 8",
    "sg:city":"Schwaigern",
    "sg:phone":"+49 7138/5355",
    "sg:postcode":"74193",
    "sg:province":"Baden-W\u00fcrttemberg",
    "wof:name":"W. Bahm",
    "wof:placetype":"venue"
},
  "geometry": {"coordinates":[9.05683,49.140602],"type":"Point"}
}