{
  "type": "Feature",
  "properties": {
    "iso:country":"DE",
    "sg:address":"Hauptstr 31::",
    "sg:city":"Pohlheim",
    "sg:phone":"+49 6004/576577",
    "sg:postcode":"35415",
    "sg:province":"Hessen",
    "wof:name":"Volksbank Holzheim Eg",
    "wof:placetype":"venue"
},
  "geometry": {"coordinates":[8.720394,50.486973],"type":"Point"}
}