{
  "type": "Feature",
  "properties": {
    "iso:country":"DE",
    "sg:address":"Calvinstr. 19",
    "sg:city":"Wuppertal",
    "sg:phone":"+49 202/445160",
    "sg:postcode":"42103",
    "sg:province":"Nordrhein-Westfalen",
    "wof:name":"Optiker Borsch Gmbh",
    "wof:placetype":"venue"
},
  "geometry": {"coordinates":[7.1469650269,51.2560806274],"type":"Point"}
}