{
  "type": "Feature",
  "properties": {
    "iso:country":"DE",
    "sg:address":"Graf-Arno-Str. 2",
    "sg:city":"Arnbruck",
    "sg:phone":"+49 9945/1459",
    "sg:postcode":"93471",
    "sg:province":"Bayern",
    "wof:name":"Alois L\u00f6ssl Drogerie",
    "wof:placetype":"venue"
},
  "geometry": {"coordinates":[12.997732,49.129868],"type":"Point"}
}