{
  "type": "Feature",
  "properties": {
    "iso:country":"DE",
    "sg:address":"Rote Au 43",
    "sg:city":"Hardheim",
    "sg:phone":"+49 6283/22190",
    "sg:postcode":"74736",
    "sg:province":"Baden-W\u00fcrttemberg",
    "wof:name":"Vleugels Gmbh",
    "wof:placetype":"venue"
},
  "geometry": {"coordinates":[9.4766073227,49.6169242859],"type":"Point"}
}