{
  "type": "Feature",
  "properties": {
    "iso:country":"DE",
    "sg:address":"Oberlindelbach",
    "sg:city":"Igensdorf",
    "sg:phone":"+49 9126/1889",
    "sg:postcode":"91338",
    "sg:province":"Bayern",
    "wof:name":"Schwarzes Ro\u00df",
    "wof:placetype":"venue"
},
  "geometry": {"coordinates":[11.1971998215,49.6207313538],"type":"Point"}
}