{
  "type": "Feature",
  "properties": {
    "iso:country":"DE",
    "sg:address":"Am Gro\u00dfmarkt 15",
    "sg:city":"Hannover",
    "sg:phone":"+49 511/946620",
    "sg:postcode":"30453",
    "sg:province":"Niedersachsen",
    "wof:name":"Bauhaus Gmbh & Co. Kg",
    "wof:placetype":"venue"
},
  "geometry": {"coordinates":[9.6958189011,52.3522987366],"type":"Point"}
}