{
  "type": "Feature",
  "properties": {
    "iso:country":"DE",
    "sg:address":"Thauwinkelstr. 19",
    "sg:city":"Biedenkopf",
    "sg:phone":"+49 6461/2886",
    "sg:postcode":"35216",
    "sg:province":"Hessen",
    "wof:name":"K. Und E. Funk",
    "wof:placetype":"venue"
},
  "geometry": {"coordinates":[8.5319623947,50.912853241],"type":"Point"}
}