{
  "type": "Feature",
  "properties": {
    "iso:country":"DE",
    "sg:address":"Lerchenstr. 11/2",
    "sg:city":"Steinenbronn",
    "sg:phone":"+49 7157/9283",
    "sg:postcode":"71144",
    "sg:province":"Baden-W\u00fcrttemberg",
    "wof:name":"H.-j. Sobiecki",
    "wof:placetype":"venue"
},
  "geometry": {"coordinates":[9.1256790161,48.6661453247],"type":"Point"}
}