{
  "type": "Feature",
  "properties": {
    "iso:country":"DE",
    "sg:address":"Hellweg 23a",
    "sg:city":"Erwitte",
    "sg:phone":"+49 2943/2410",
    "sg:postcode":"59597",
    "sg:province":"Nordrhein-Westfalen",
    "wof:name":"H. Jakob Immobilienmakler",
    "wof:placetype":"venue"
},
  "geometry": {"coordinates":[8.3461933136,51.6126251221],"type":"Point"}
}