{
  "type": "Feature",
  "properties": {
    "iso:country":"DE",
    "sg:address":"Eisenbahnstr. 1",
    "sg:city":"Biebesheim",
    "sg:phone":"+49 6258/6770",
    "sg:postcode":"64584",
    "sg:province":"Hessen",
    "wof:name":"Thorsten Reimund",
    "wof:placetype":"venue"
},
  "geometry": {"coordinates":[8.4733123779,49.7820663452],"type":"Point"}
}