{
  "type": "Feature",
  "properties": {
    "iso:country":"DE",
    "sg:address":"Pf\u00e4lzerstr. 25",
    "sg:city":"Pforzheim",
    "sg:phone":"+49 7231/313329",
    "sg:postcode":"75177",
    "sg:province":"Baden-W\u00fcrttemberg",
    "wof:name":"Emil August Schofer",
    "wof:placetype":"venue"
},
  "geometry": {"coordinates":[8.7042722702,48.8969802856],"type":"Point"}
}