{
  "type": "Feature",
  "properties": {
    "iso:country":"DE",
    "sg:address":"Schwetzinger Str. 121",
    "sg:city":"Heidelberg",
    "sg:phone":"+49 6221/716999",
    "sg:postcode":"69124",
    "sg:province":"Baden-W\u00fcrttemberg",
    "wof:name":"Cafe Am Leisberg",
    "wof:placetype":"venue"
},
  "geometry": {"coordinates":[8.672074,49.383099],"type":"Point"}
}