{
  "type": "Feature",
  "properties": {
    "iso:country":"DE",
    "sg:address":"Berge",
    "sg:city":"Anr\u00f6chte",
    "sg:phone":"+49 2947/3329",
    "sg:postcode":"59609",
    "sg:province":"Nordrhein-Westfalen",
    "wof:name":"Theodor Peters",
    "wof:placetype":"venue"
},
  "geometry": {"coordinates":[8.3598203659,51.5253295898],"type":"Point"}
}