{
  "type": "Feature",
  "properties": {
    "iso:country":"DE",
    "sg:address":"Zeiss-Str. 6",
    "sg:city":"K\u00f6nigsbrunn",
    "sg:phone":"+49 8231/2423",
    "sg:postcode":"86343",
    "sg:province":"Bayern",
    "wof:name":"Offsetdruckerei Aldo Marzorati",
    "wof:placetype":"venue"
},
  "geometry": {"coordinates":[10.895975,48.283188],"type":"Point"}
}