{
  "type": "Feature",
  "properties": {
    "iso:country":"DE",
    "sg:address":"Hombergsegge 120",
    "sg:city":"Hattingen",
    "sg:phone":"+49 2324/41307",
    "sg:postcode":"45529",
    "sg:province":"Nordrhein-Westfalen",
    "wof:name":"Wilhelm Kappert",
    "wof:placetype":"venue"
},
  "geometry": {"coordinates":[7.1178498268,51.401058197],"type":"Point"}
}