{
  "type": "Feature",
  "properties": {
    "iso:country":"DE",
    "sg:address":"Wiesenstr. 10",
    "sg:city":"Ammerbuch",
    "sg:phone":"+49 7032/97650",
    "sg:postcode":"72119",
    "sg:province":"Baden-W\u00fcrttemberg",
    "wof:name":"Dc Druck-chemie Holding Gmbh",
    "wof:placetype":"venue"
},
  "geometry": {"coordinates":[8.904118,48.562965],"type":"Point"}
}