{
  "type": "Feature",
  "properties": {
    "iso:country":"DE",
    "sg:address":"Dorfstr. 7",
    "sg:city":"Eichhorst",
    "sg:phone":"+49 39606/20441",
    "sg:postcode":"17099",
    "sg:province":"Mecklenburg-Vorpommern",
    "wof:name":"M. Klohse",
    "wof:placetype":"venue"
},
  "geometry": {"coordinates":[13.4995880127,53.595287323],"type":"Point"}
}