{
  "type": "Feature",
  "properties": {
    "iso:country":"DE",
    "sg:address":"Rutesheimer Str. 10",
    "sg:city":"Ditzingen",
    "sg:phone":"+49 7152/51029",
    "sg:postcode":"71254",
    "sg:province":"Baden-W\u00fcrttemberg",
    "wof:name":"Fridolin Bauer",
    "wof:placetype":"venue"
},
  "geometry": {"coordinates":[8.9814443588,48.8522911072],"type":"Point"}
}