{
  "type": "Feature",
  "properties": {
    "iso:country":"DE",
    "sg:address":"Weberstr. 54",
    "sg:city":"Memmingen",
    "sg:postcode":"87700",
    "sg:province":"Bayern",
    "wof:name":"Mario Massano E. K.",
    "wof:placetype":"venue"
},
  "geometry": {"coordinates":[10.180685997,47.9808311462],"type":"Point"}
}