{
  "type": "Feature",
  "properties": {
    "iso:country":"DE",
    "sg:address":"Eschenallee 35",
    "sg:city":"Ludwigsfelde",
    "sg:phone":"+49 3378/513264",
    "sg:postcode":"14974",
    "sg:province":"Brandenburg",
    "wof:name":"Eiscafe Bernd Schr\u00f6der",
    "wof:placetype":"venue"
},
  "geometry": {"coordinates":[13.263065,52.294991],"type":"Point"}
}