{
  "type": "Feature",
  "properties": {
    "iso:country":"DE",
    "sg:address":"Kopper Str. 7",
    "sg:city":"Wallersheim",
    "sg:phone":"+49 6558/8563",
    "sg:postcode":"54597",
    "sg:province":"Rheinland-Pfalz",
    "wof:name":"Erich Michels",
    "wof:placetype":"venue"
},
  "geometry": {"coordinates":[6.534255,50.189846],"type":"Point"}
}