{
  "type": "Feature",
  "properties": {
    "iso:country":"DE",
    "sg:address":"In der Heth 1",
    "sg:city":"Brechen",
    "sg:phone":"+49 6438/72418",
    "sg:postcode":"65611",
    "sg:province":"Hessen",
    "wof:name":"Gisela F. Roos",
    "wof:placetype":"venue"
},
  "geometry": {"coordinates":[8.160857,50.363953],"type":"Point"}
}