{
  "type": "Feature",
  "properties": {
    "iso:country":"DE",
    "sg:address":"Ringstr. 2",
    "sg:city":"Schopp",
    "sg:phone":"+49 6307/6727",
    "sg:postcode":"67707",
    "sg:province":"Rheinland-Pfalz",
    "wof:name":"Werner Michelbach Finanzberater",
    "wof:placetype":"venue"
},
  "geometry": {"coordinates":[7.6905059814,49.3546676636],"type":"Point"}
}