{
  "type": "Feature",
  "properties": {
    "iso:country":"DE",
    "sg:address":"Schulstr. 16 a",
    "sg:city":"Stetten",
    "sg:phone":"+49 7532/9276",
    "sg:postcode":"88719",
    "sg:province":"Baden-W\u00fcrttemberg",
    "wof:name":"Hermann Kumm",
    "wof:placetype":"venue"
},
  "geometry": {"coordinates":[9.3003311157,47.6916923523],"type":"Point"}
}