{
  "type": "Feature",
  "properties": {
    "iso:country":"DE",
    "sg:address":"Am Sonnenberg 16",
    "sg:city":"Odenthal",
    "sg:postcode":"51519",
    "sg:province":"Nordrhein-Westfalen",
    "wof:name":"Gtt Gmbh",
    "wof:placetype":"venue"
},
  "geometry": {"coordinates":[7.1274900436,51.0158996582],"type":"Point"}
}