{
  "type": "Feature",
  "properties": {
    "iso:country":"DE",
    "sg:address":"M\u00fcnsterwalder Str. 2",
    "sg:city":"Berlin",
    "sg:phone":"+49 30/54912400",
    "sg:postcode":"12621",
    "sg:province":"Berlin",
    "wof:name":"Andr\u00e4 Sicherheitsservice Gmbh",
    "wof:placetype":"venue"
},
  "geometry": {"coordinates":[13.5683708191,52.483505249],"type":"Point"}
}