{
  "type": "Feature",
  "properties": {
    "iso:country":"DE",
    "sg:address":"Zum Vogelherd 16",
    "sg:city":"Oelsnitz",
    "sg:phone":"+49 37421/23529",
    "sg:postcode":"08606",
    "sg:province":"Sachsen",
    "wof:name":"Hartmannsgr\u00fcn",
    "wof:placetype":"venue"
},
  "geometry": {"coordinates":[12.2081613541,50.4260902405],"type":"Point"}
}