{
  "type": "Feature",
  "properties": {
    "iso:country":"DE",
    "sg:address":"Hauptstr. 19",
    "sg:city":"Germerswang",
    "sg:phone":"+49 8141/94141",
    "sg:postcode":"82216",
    "sg:province":"Bayern",
    "wof:name":"Helga Scheibenzuber",
    "wof:placetype":"venue"
},
  "geometry": {"coordinates":[11.2233724594,48.2226409912],"type":"Point"}
}