{
  "type": "Feature",
  "properties": {
    "iso:country":"DE",
    "sg:address":"Neuer Weg 23",
    "sg:city":"G\u00e4dheim",
    "sg:postcode":"97503",
    "sg:province":"Bayern",
    "wof:name":"G. Rummert",
    "wof:placetype":"venue"
},
  "geometry": {"coordinates":[10.347763,50.022804],"type":"Point"}
}