{
  "type": "Feature",
  "properties": {
    "iso:country":"DE",
    "sg:address":"Wilhelmstr. 123",
    "sg:city":"Berlin",
    "sg:phone":"+49 30/2614505",
    "sg:postcode":"10963",
    "sg:province":"Berlin",
    "wof:name":"Bnpo Berlin Gmbh",
    "wof:placetype":"venue"
},
  "geometry": {"coordinates":[13.387381,52.50346],"type":"Point"}
}