{
  "type": "Feature",
  "properties": {
    "iso:country":"DE",
    "sg:address":"Habichtstr. 26",
    "sg:city":"Vlotho",
    "sg:phone":"+49 5733/5535",
    "sg:postcode":"32602",
    "sg:province":"Nordrhein-Westfalen",
    "wof:name":"Hans-dieter Wolf",
    "wof:placetype":"venue"
},
  "geometry": {"coordinates":[8.8585882187,52.1566925049],"type":"Point"}
}