{
  "type": "Feature",
  "properties": {
    "iso:country":"DE",
    "sg:address":"Pagenstecherstr. 38",
    "sg:city":"Osnabr\u00fcck",
    "sg:phone":"+49 541/962360",
    "sg:postcode":"49090",
    "sg:province":"Niedersachsen",
    "wof:name":"Sport Und Mode Gleixner Kg",
    "wof:placetype":"venue"
},
  "geometry": {"coordinates":[8.0306758881,52.2879943848],"type":"Point"}
}