{
  "type": "Feature",
  "properties": {
    "iso:country":"DE",
    "sg:address":"Markfestestr. 21",
    "sg:city":"Aldenhoven",
    "sg:phone":"+49 2464/5379",
    "sg:postcode":"52457",
    "sg:province":"Nordrhein-Westfalen",
    "wof:name":"Ratsschenke",
    "wof:placetype":"venue"
},
  "geometry": {"coordinates":[6.2888951302,50.8955535889],"type":"Point"}
}