{
  "type": "Feature",
  "properties": {
    "iso:country":"DE",
    "sg:address":"Am Weinberg 41",
    "sg:city":"Bad Hersfeld",
    "sg:phone":"+49 6621/162600",
    "sg:postcode":"36251",
    "sg:province":"Hessen",
    "wof:name":"Hermann Kirchner Gesch\u00e4ftsf\u00fchrungs Gmbh",
    "wof:placetype":"venue"
},
  "geometry": {"coordinates":[9.686442,50.852543],"type":"Point"}
}