{
  "type": "Feature",
  "properties": {
    "iso:country":"DE",
    "sg:address":"Hauptstr. 15",
    "sg:city":"Melsungen",
    "sg:phone":"+49 5661/4025",
    "sg:postcode":"34212",
    "sg:province":"Hessen",
    "wof:name":"Barbara Fastenrath Steuerberaterin",
    "wof:placetype":"venue"
},
  "geometry": {"coordinates":[9.5977096558,51.1417808533],"type":"Point"}
}