{
  "type": "Feature",
  "properties": {
    "iso:country":"DE",
    "sg:address":"Tarpenbekstrasse 98",
    "sg:city":"Hamburg",
    "sg:phone":"+49 40/476041",
    "sg:postcode":"20251",
    "sg:province":"Hamburg",
    "wof:name":"Jan Fr. Schulzebeer & Co.",
    "wof:placetype":"venue"
},
  "geometry": {"coordinates":[9.984362,53.597889],"type":"Point"}
}