{
  "type": "Feature",
  "properties": {
    "iso:country":"DE",
    "sg:address":"Rosenhag 1",
    "sg:city":"Stelle",
    "sg:phone":"+49 4174/2410",
    "sg:postcode":"21435",
    "sg:province":"Niedersachsen",
    "wof:name":"Dr. Horst Benthack Tierarzt",
    "wof:placetype":"venue"
},
  "geometry": {"coordinates":[10.0920534134,53.3871154785],"type":"Point"}
}