{
  "type": "Feature",
  "properties": {
    "iso:country":"DE",
    "sg:address":"Markt 3",
    "sg:city":"Moritzburg",
    "sg:phone":"+49 35207/81366",
    "sg:postcode":"01468",
    "sg:province":"Sachsen",
    "wof:name":"Erich Funke",
    "wof:placetype":"venue"
},
  "geometry": {"coordinates":[13.676584,51.162567],"type":"Point"}
}