{
  "type": "Feature",
  "properties": {
    "iso:country":"DE",
    "sg:address":"Escherndorfer Str. 23",
    "sg:city":"Volkach",
    "sg:phone":"+49 9381/1401",
    "sg:postcode":"97332",
    "sg:province":"Bayern",
    "wof:name":"Fred Binzenh\u00f6fer Steuerberater",
    "wof:placetype":"venue"
},
  "geometry": {"coordinates":[10.2124881744,49.8610496521],"type":"Point"}
}