{
  "type": "Feature",
  "properties": {
    "iso:country":"DE",
    "sg:address":"Schlusenkamp 6",
    "sg:city":"Essen",
    "sg:phone":"+49 201/367306",
    "sg:postcode":"45326",
    "sg:province":"Nordrhein-Westfalen",
    "wof:name":"Renate B\u00fcchtmann Immobilien Und",
    "wof:placetype":"venue"
},
  "geometry": {"coordinates":[7.0021700859,51.485786438],"type":"Point"}
}