{
  "type": "Feature",
  "properties": {
    "iso:country":"DE",
    "sg:address":"Feuerbachstr 26-32",
    "sg:city":"Frankfurt",
    "sg:phone":"+49 69/97265210",
    "sg:postcode":"60325",
    "sg:province":"Hessen",
    "wof:name":"Bank Of Boston The",
    "wof:placetype":"venue"
},
  "geometry": {"coordinates":[8.662882,50.114941],"type":"Point"}
}