{
  "type": "Feature",
  "properties": {
    "iso:country":"DE",
    "sg:address":"Bernsbachstr. 3",
    "sg:city":"Brotterode",
    "sg:phone":"+49 36840/3930",
    "sg:postcode":"98599",
    "sg:province":"Th\u00fcringen",
    "wof:name":"Ulrich Piatek",
    "wof:placetype":"venue"
},
  "geometry": {"coordinates":[10.445289,50.825935],"type":"Point"}
}