{
  "type": "Feature",
  "properties": {
    "iso:country":"DE",
    "sg:address":"Herzog-Max-Str. 25",
    "sg:city":"Bamberg",
    "sg:phone":"+49 951/27498",
    "sg:postcode":"96047",
    "sg:province":"Bayern",
    "wof:name":"Hans Trog Rechtsanwalt",
    "wof:placetype":"venue"
},
  "geometry": {"coordinates":[10.8971996307,49.8892402649],"type":"Point"}
}