{
  "type": "Feature",
  "properties": {
    "iso:country":"DE",
    "sg:address":"Gutenbergstr. 43",
    "sg:city":"Lilienthal",
    "sg:phone":"+49 4298/2667",
    "sg:postcode":"28865",
    "sg:province":"Niedersachsen",
    "wof:name":"Ernst H. G. Lucas",
    "wof:placetype":"venue"
},
  "geometry": {"coordinates":[8.901512146,53.1552886963],"type":"Point"}
}