{
  "type": "Feature",
  "properties": {
    "iso:country":"DE",
    "sg:address":"Am Stadtbruch 4",
    "sg:city":"Volkmarsen",
    "sg:phone":"+49 5693/6170",
    "sg:postcode":"34471",
    "sg:province":"Hessen",
    "wof:name":"Baugesellschaft Wachenfeld Mbh",
    "wof:placetype":"venue"
},
  "geometry": {"coordinates":[9.112502,51.40707],"type":"Point"}
}