{
  "type": "Feature",
  "properties": {
    "iso:country":"DE",
    "sg:address":"Hamburger Str. 4",
    "sg:city":"Bad Segeberg",
    "sg:phone":"+49 4551/9060",
    "sg:postcode":"23795",
    "sg:province":"Schleswig-Holstein",
    "wof:name":"Segeberger Eisenhandlung Johann Peter Hass Kg",
    "wof:placetype":"venue"
},
  "geometry": {"coordinates":[10.307306,53.936558],"type":"Point"}
}