{
  "type": "Feature",
  "properties": {
    "iso:country":"DE",
    "sg:address":"Meersburger Str. 24",
    "sg:city":"Mannheim",
    "sg:phone":"+49 621/471112",
    "sg:postcode":"68239",
    "sg:province":"Baden-W\u00fcrttemberg",
    "wof:name":"Kaiserhof",
    "wof:placetype":"venue"
},
  "geometry": {"coordinates":[8.5634508133,49.4631958008],"type":"Point"}
}