{
  "type": "Feature",
  "properties": {
    "iso:country":"DE",
    "sg:address":"Damaschkestr. 6",
    "sg:city":"Strau\u00dffurt",
    "sg:postcode":"99634",
    "sg:province":"Th\u00fcringen",
    "wof:name":"B. Hannaske & K. Wunderlich",
    "wof:placetype":"venue"
},
  "geometry": {"coordinates":[10.991748,51.16114],"type":"Point"}
}