{
  "type": "Feature",
  "properties": {
    "iso:country":"DE",
    "sg:address":"Elektrastr. 12a",
    "sg:city":"M\u00fcnchen",
    "sg:phone":"+49 89/9102444",
    "sg:postcode":"81925",
    "sg:province":"Bayern",
    "wof:name":"Thurn Und Taxis Creationen Christine Barth",
    "wof:placetype":"venue"
},
  "geometry": {"coordinates":[11.6223154068,48.1518554688],"type":"Point"}
}