{
  "type": "Feature",
  "properties": {
    "iso:country":"DE",
    "sg:address":"Am Kalkberg 15",
    "sg:city":"Riesa",
    "sg:phone":"+49 3525/737562",
    "sg:postcode":"01591",
    "sg:province":"Sachsen",
    "wof:name":"G\u00fcnther Zander Ingenieur",
    "wof:placetype":"venue"
},
  "geometry": {"coordinates":[13.2745141983,51.3232727051],"type":"Point"}
}