{
  "type": "Feature",
  "properties": {
    "iso:country":"DE",
    "sg:address":"Freiburger Str. 5",
    "sg:city":"Hinterzarten",
    "sg:phone":"+49 7652/744",
    "sg:postcode":"79856",
    "sg:province":"Baden-W\u00fcrttemberg",
    "wof:name":"Reimer",
    "wof:placetype":"venue"
},
  "geometry": {"coordinates":[8.104407,47.906456],"type":"Point"}
}