{
  "type": "Feature",
  "properties": {
    "iso:country":"DE",
    "sg:address":"Am Gr\u00e4fengericht 5",
    "sg:city":"Jork",
    "sg:phone":"+49 4162/441",
    "sg:postcode":"21635",
    "sg:province":"Niedersachsen",
    "wof:name":"Helmut Saborowski",
    "wof:placetype":"venue"
},
  "geometry": {"coordinates":[9.680711,53.533173],"type":"Point"}
}