{
  "type": "Feature",
  "properties": {
    "iso:country":"DE",
    "sg:address":"Gottorfstr. 11 a",
    "sg:city":"Schleswig",
    "sg:phone":"+49 4621/32598",
    "sg:postcode":"24837",
    "sg:province":"Schleswig-Holstein",
    "wof:name":"Praxis Dr. Med. Thoben \u00c4rzte F\u00fcr Allgemeinmedizin",
    "wof:placetype":"venue"
},
  "geometry": {"coordinates":[9.5415153503,54.5067825317],"type":"Point"}
}