{
  "type": "Feature",
  "properties": {
    "iso:country":"DE",
    "sg:address":"Neue Halberst\u00e4dter Str. 28",
    "sg:city":"Blankenburg",
    "sg:postcode":"38889",
    "sg:province":"Sachsen-Anhalt",
    "wof:name":"Extra",
    "wof:placetype":"venue"
},
  "geometry": {"coordinates":[10.9650793076,51.7987976074],"type":"Point"}
}