{
  "type": "Feature",
  "properties": {
    "iso:country":"DE",
    "sg:address":"Neugasse 20",
    "sg:city":"Kallstadt",
    "sg:phone":"+49 6322/94490",
    "sg:postcode":"67169",
    "sg:province":"Rheinland-Pfalz",
    "wof:name":"Christiane Daut Architektin",
    "wof:placetype":"venue"
},
  "geometry": {"coordinates":[8.180146,49.492764],"type":"Point"}
}