{
  "type": "Feature",
  "properties": {
    "iso:country":"DE",
    "sg:address":"Belgradstr. 16",
    "sg:city":"M\u00fcnchen",
    "sg:phone":"+49 89/391979",
    "sg:postcode":"80796",
    "sg:province":"Bayern",
    "wof:name":"Bonda Tiernahrung Produktions- Und Hdls. Gmbh",
    "wof:placetype":"venue"
},
  "geometry": {"coordinates":[11.574889,48.162659],"type":"Point"}
}