{
  "type": "Feature",
  "properties": {
    "iso:country":"DE",
    "sg:address":"Stefan-Zweig-Str. 8 a",
    "sg:city":"Mahlow",
    "sg:postcode":"15831",
    "sg:province":"Brandenburg",
    "wof:name":"Johann Eibl Gro\u00dfhandel F\u00fcr Medizinische",
    "wof:placetype":"venue"
},
  "geometry": {"coordinates":[13.404355,52.365101],"type":"Point"}
}