{
  "type": "Feature",
  "properties": {
    "iso:country":"DE",
    "sg:address":"Wohlauer Str. 24",
    "sg:city":"Hilden",
    "sg:phone":"+49 2103/40933",
    "sg:postcode":"40721",
    "sg:province":"Nordrhein-Westfalen",
    "wof:name":"Ingomar Poppek Rechtsanwalt",
    "wof:placetype":"venue"
},
  "geometry": {"coordinates":[6.9238247871,51.1855888367],"type":"Point"}
}