{
  "type": "Feature",
  "properties": {
    "iso:country":"DE",
    "sg:address":"Pr\u00e4lat-Neun-Str. 16",
    "sg:city":"Zwiesel",
    "sg:phone":"+49 9922/869944",
    "sg:postcode":"94227",
    "sg:province":"Bayern",
    "wof:name":"Wk Kerzenstubn Gmbh",
    "wof:placetype":"venue"
},
  "geometry": {"coordinates":[13.2336835861,49.0124397278],"type":"Point"}
}