{
  "type": "Feature",
  "properties": {
    "iso:country":"DE",
    "sg:address":"Br\u00fcder-Grimm-Str. 10",
    "sg:city":"Laatzen",
    "sg:phone":"+49 5102/2995",
    "sg:postcode":"30880",
    "sg:province":"Niedersachsen",
    "wof:name":"Lucie Baldin",
    "wof:placetype":"venue"
},
  "geometry": {"coordinates":[9.8099355698,52.2900886536],"type":"Point"}
}