{
  "type": "Feature",
  "properties": {
    "iso:country":"DE",
    "sg:address":"Lindenstr. 31",
    "sg:city":"Gr\u00e4venwiesbach",
    "sg:phone":"+49 6086/969852",
    "sg:postcode":"61279",
    "sg:province":"Hessen",
    "wof:name":"Daniela M\u00fcller Rechtsanw\u00e4ltin",
    "wof:placetype":"venue"
},
  "geometry": {"coordinates":[8.4596729279,50.3932304382],"type":"Point"}
}