{
  "type": "Feature",
  "properties": {
    "iso:country":"DE",
    "sg:address":"Herrenlandstr. 72",
    "sg:city":"Radolfzell",
    "sg:phone":"+49 7732/3883",
    "sg:postcode":"78315",
    "sg:province":"Baden-W\u00fcrttemberg",
    "wof:name":"K. Beierer",
    "wof:placetype":"venue"
},
  "geometry": {"coordinates":[8.9510946274,47.7445335388],"type":"Point"}
}