{
  "type": "Feature",
  "properties": {
    "iso:country":"DE",
    "sg:address":"Pappelstr. 2",
    "sg:city":"Kerpen",
    "sg:phone":"+49 2237/61957",
    "sg:postcode":"50169",
    "sg:province":"Nordrhein-Westfalen",
    "wof:name":"K. Monje",
    "wof:placetype":"venue"
},
  "geometry": {"coordinates":[6.7393097878,50.8661460876],"type":"Point"}
}