{
  "type": "Feature",
  "properties": {
    "iso:country":"DE",
    "sg:address":"T\u00f6pferstr. 3",
    "sg:city":"Neustrelitz",
    "sg:phone":"+49 3981/200565",
    "sg:postcode":"17235",
    "sg:province":"Mecklenburg-Vorpommern",
    "wof:name":"Frank Rieckhoff",
    "wof:placetype":"venue"
},
  "geometry": {"coordinates":[13.0625257492,53.3620033264],"type":"Point"}
}