{
  "type": "Feature",
  "properties": {
    "iso:country":"DE",
    "sg:address":"Steinbrink 75",
    "sg:city":"Diepenau",
    "sg:phone":"+49 5777/475",
    "sg:postcode":"31603",
    "sg:province":"Niedersachsen",
    "wof:name":"Friedhelm Schuchardt",
    "wof:placetype":"venue"
},
  "geometry": {"coordinates":[8.71233,52.504131],"type":"Point"}
}