{
  "type": "Feature",
  "properties": {
    "iso:country":"DE",
    "sg:address":"Tr\u00f6ndlinweg 2",
    "sg:city":"Albbruck",
    "sg:phone":"+49 7755/256",
    "sg:postcode":"79774",
    "sg:province":"Baden-W\u00fcrttemberg",
    "wof:name":"K. Bieselin Kaufhaus",
    "wof:placetype":"venue"
},
  "geometry": {"coordinates":[8.133913,47.6464],"type":"Point"}
}