{
  "type": "Feature",
  "properties": {
    "iso:country":"DE",
    "sg:address":"Bebelplatz 4",
    "sg:city":"K\u00f6ln",
    "sg:phone":"+49 221/881369",
    "sg:postcode":"50679",
    "sg:province":"Nordrhein-Westfalen",
    "wof:name":"W. A. Hassinger",
    "wof:placetype":"venue"
},
  "geometry": {"coordinates":[6.9756608009,50.9299697876],"type":"Point"}
}