{
  "type": "Feature",
  "properties": {
    "iso:country":"DE",
    "sg:address":"D\u00fcsseldorfer Str. 19-23",
    "sg:city":"Frankfurt",
    "sg:phone":"+49 69/2400260",
    "sg:postcode":"60329",
    "sg:province":"Hessen",
    "wof:name":"Interamerican Hellenic Life Insurance Company Sa",
    "wof:placetype":"venue"
},
  "geometry": {"coordinates":[8.66093,50.109062],"type":"Point"}
}