{
  "type": "Feature",
  "properties": {
    "iso:country":"DE",
    "sg:address":"Am Halben Morgen",
    "sg:city":"Stelzenberg",
    "sg:phone":"+49 6306/1766",
    "sg:postcode":"67705",
    "sg:province":"Rheinland-Pfalz",
    "wof:name":"Vereinsgastst\u00e4tte Sportheim Tv Stelzenberg E. V.",
    "wof:placetype":"venue"
},
  "geometry": {"coordinates":[7.7370729446,49.3808860779],"type":"Point"}
}