{
  "type": "Feature",
  "properties": {
    "iso:country":"DE",
    "sg:address":"Orthwiesen 3",
    "sg:city":"G\u00f6ttingen",
    "sg:phone":"+49 551/61655",
    "sg:postcode":"37079",
    "sg:province":"Niedersachsen",
    "wof:name":"Ev. Pfarramt St. Martini Ellishausen",
    "wof:placetype":"venue"
},
  "geometry": {"coordinates":[9.8710813522,51.5535049438],"type":"Point"}
}