{
  "type": "Feature",
  "properties": {
    "iso:country":"DE",
    "sg:address":"Simrockstr. 27",
    "sg:city":"Bonn",
    "sg:phone":"+49 228/265680",
    "sg:postcode":"53113",
    "sg:province":"Nordrhein-Westfalen",
    "wof:name":"Deutscher Spendenrat E. V.",
    "wof:placetype":"venue"
},
  "geometry": {"coordinates":[7.1126461029,50.7203903198],"type":"Point"}
}