{
  "type": "Feature",
  "properties": {
    "iso:country":"DE",
    "sg:address":"Neuer Achterkamp 38",
    "sg:city":"Gro\u00dfhansdorf",
    "sg:phone":"+49 4102/61678",
    "sg:postcode":"22927",
    "sg:province":"Schleswig-Holstein",
    "wof:name":"Heinz Plewka",
    "wof:placetype":"venue"
},
  "geometry": {"coordinates":[10.263651,53.649754],"type":"Point"}
}