{
  "type": "Feature",
  "properties": {
    "iso:country":"DE",
    "sg:address":"Ulmer Str. 123",
    "sg:city":"G\u00f6ppingen",
    "sg:phone":"+49 7161/43210",
    "sg:postcode":"73037",
    "sg:province":"Baden-W\u00fcrttemberg",
    "wof:name":"Stempel Stuhlm\u00fcller Gmbh",
    "wof:placetype":"venue"
},
  "geometry": {"coordinates":[9.6821098328,48.6977005005],"type":"Point"}
}