{
  "type": "Feature",
  "properties": {
    "iso:country":"DE",
    "sg:address":"Wolfhager Str. 36",
    "sg:city":"Habichtswald",
    "sg:phone":"+49 5606/9402",
    "sg:postcode":"34317",
    "sg:province":"Hessen",
    "wof:name":"Rainer Meier",
    "wof:placetype":"venue"
},
  "geometry": {"coordinates":[9.3439435959,51.3420333862],"type":"Point"}
}