{
  "type": "Feature",
  "properties": {
    "iso:country":"DE",
    "sg:address":"Loowstr. 1",
    "sg:city":"Lingen",
    "sg:phone":"+49 591/51368",
    "sg:postcode":"49811",
    "sg:province":"Niedersachsen",
    "wof:name":"H. J. Hilbers Beteiligungs Gmbh",
    "wof:placetype":"venue"
},
  "geometry": {"coordinates":[7.405092,52.51339],"type":"Point"}
}