{
  "type": "Feature",
  "properties": {
    "iso:country":"DE",
    "sg:address":"K\u00f6hlerwaldweg 1",
    "sg:city":"Wilhelmsfeld",
    "sg:phone":"+49 6220/7127",
    "sg:postcode":"69259",
    "sg:province":"Baden-W\u00fcrttemberg",
    "wof:name":"Gastst\u00e4tte Tsg",
    "wof:placetype":"venue"
},
  "geometry": {"coordinates":[8.7527961731,49.4751281738],"type":"Point"}
}