{
  "type": "Feature",
  "properties": {
    "iso:country":"DE",
    "sg:address":"Negeleinstr. 6",
    "sg:city":"Kulmbach",
    "sg:phone":"+49 9221/5904",
    "sg:postcode":"95326",
    "sg:province":"Bayern",
    "wof:name":"Gastst\u00e4tte Marianne Wich",
    "wof:placetype":"venue"
},
  "geometry": {"coordinates":[11.4479255676,50.1112556458],"type":"Point"}
}