{
  "type": "Feature",
  "properties": {
    "iso:country":"DE",
    "sg:address":"W\u00fcrzburger Str. 25",
    "sg:city":"Triefenstein",
    "sg:phone":"+49 9395/307",
    "sg:postcode":"97855",
    "sg:province":"Bayern",
    "wof:name":"Hubert B\u00e4hr Elektro Meister",
    "wof:placetype":"venue"
},
  "geometry": {"coordinates":[9.623991,49.794685],"type":"Point"}
}