{
  "type": "Feature",
  "properties": {
    "iso:country":"DE",
    "sg:address":"Sophienblatt 60",
    "sg:city":"Kiel",
    "sg:phone":"+49 431/6620",
    "sg:postcode":"24114",
    "sg:province":"Schleswig-Holstein",
    "wof:name":"Siemens Nixdorf Informationssysteme Ag",
    "wof:placetype":"venue"
},
  "geometry": {"coordinates":[10.128043,54.312366],"type":"Point"}
}