{
  "type": "Feature",
  "properties": {
    "iso:country":"DE",
    "sg:address":"Riesenfeld 11",
    "sg:city":"Weferlingen",
    "sg:phone":"+49 39061/2568",
    "sg:postcode":"39356",
    "sg:province":"Sachsen-Anhalt",
    "wof:name":"Veronika Kr\u00fcger",
    "wof:placetype":"venue"
},
  "geometry": {"coordinates":[11.049382,52.31535],"type":"Point"}
}