{
  "type": "Feature",
  "properties": {
    "iso:country":"DE",
    "sg:address":"Industriestr. 15",
    "sg:city":"Molbergen",
    "sg:phone":"+49 4475/9400",
    "sg:postcode":"49696",
    "sg:province":"Niedersachsen",
    "wof:name":"Osterhus Gmbh & Co. Leitungsbau Kg",
    "wof:placetype":"venue"
},
  "geometry": {"coordinates":[7.931948185,52.854434967],"type":"Point"}
}