{
  "type": "Feature",
  "properties": {
    "iso:country":"DE",
    "sg:address":"Klinkstr. 13",
    "sg:city":"B\u00fcnde",
    "sg:phone":"+49 5223/5852",
    "sg:postcode":"32257",
    "sg:province":"Nordrhein-Westfalen",
    "wof:name":"Tanzschule Marks",
    "wof:placetype":"venue"
},
  "geometry": {"coordinates":[8.5800428391,52.1956710815],"type":"Point"}
}