{
  "type": "Feature",
  "properties": {
    "iso:country":"DE",
    "sg:address":"Klarenstrecker Damm 7 a",
    "sg:city":"Stade",
    "sg:phone":"+49 4141/63003",
    "sg:postcode":"21684",
    "sg:province":"Niedersachsen",
    "wof:name":"Bausanierung Rieger Gmbh",
    "wof:placetype":"venue"
},
  "geometry": {"coordinates":[9.49297,53.580944],"type":"Point"}
}