{
  "type": "Feature",
  "properties": {
    "iso:country":"DE",
    "sg:address":"Rudolst\u00e4dter Str. 343",
    "sg:city":"Niedernissa",
    "sg:phone":"+49 361/4210025",
    "sg:postcode":"99102",
    "sg:province":"Th\u00fcringen",
    "wof:name":"Andreas K\u00f6nig",
    "wof:placetype":"venue"
},
  "geometry": {"coordinates":[11.1054582596,50.9503707886],"type":"Point"}
}