{
  "type": "Feature",
  "properties": {
    "iso:country":"DE",
    "sg:address":"Weidengrundstr.15",
    "sg:city":"Gr\u00fcndau",
    "sg:phone":"+49 6058/910460",
    "sg:postcode":"63584",
    "sg:province":"Hessen",
    "wof:name":"Ewert-online",
    "wof:placetype":"venue"
},
  "geometry": {"coordinates":[9.1165866852,50.2340011597],"type":"Point"}
}