{
  "type": "Feature",
  "properties": {
    "iso:country":"DE",
    "sg:address":"Hohlstr. 5",
    "sg:city":"Bochum",
    "sg:phone":"+49 234/265880",
    "sg:postcode":"44894",
    "sg:province":"Nordrhein-Westfalen",
    "wof:name":"Dagobert M\u00fcller Dach-wand-abdichtungs Gmbh",
    "wof:placetype":"venue"
},
  "geometry": {"coordinates":[7.310107,51.479927],"type":"Point"}
}