{
  "type": "Feature",
  "properties": {
    "iso:country":"DE",
    "sg:address":"Werner-von-Siemens-Str. 14",
    "sg:city":"Erbach",
    "sg:phone":"+49 6062/5255",
    "sg:postcode":"64711",
    "sg:province":"Hessen",
    "wof:name":"Rosen-apotheke Ekkehard Tichy",
    "wof:placetype":"venue"
},
  "geometry": {"coordinates":[8.990645,49.660103],"type":"Point"}
}