{
  "type": "Feature",
  "properties": {
    "iso:country":"DE",
    "sg:address":"Thurgauer Str. 13 a",
    "sg:city":"Singen",
    "sg:phone":"+49 7731/66171",
    "sg:postcode":"78224",
    "sg:province":"Baden-W\u00fcrttemberg",
    "wof:name":"Apres-keller",
    "wof:placetype":"venue"
},
  "geometry": {"coordinates":[8.86762,47.757111],"type":"Point"}
}