{
  "type": "Feature",
  "properties": {
    "iso:country":"DE",
    "sg:address":"Hackesstr. 79",
    "sg:city":"M\u00f6nchengladbach",
    "sg:phone":"+49 2161/664710",
    "sg:postcode":"41066",
    "sg:province":"Nordrhein-Westfalen",
    "wof:name":"C. Beyers",
    "wof:placetype":"venue"
},
  "geometry": {"coordinates":[6.4422631264,51.2253112793],"type":"Point"}
}