{
  "type": "Feature",
  "properties": {
    "iso:country":"DE",
    "sg:address":"Draisstr. 19",
    "sg:city":"Karlsbad",
    "sg:phone":"+49 7202/93120",
    "sg:postcode":"76307",
    "sg:province":"Baden-W\u00fcrttemberg",
    "wof:name":"Ifutec Ingenieurb\u00fcro F\u00fcr Gmbh",
    "wof:placetype":"venue"
},
  "geometry": {"coordinates":[8.499991,48.922939],"type":"Point"}
}