{
  "type": "Feature",
  "properties": {
    "iso:country":"DE",
    "sg:address":"Steinwendener Str. 5",
    "sg:city":"Kottweiler",
    "sg:phone":"+49 4963/7150532",
    "sg:postcode":"66879",
    "sg:province":"Rheinland-Pfalz",
    "wof:name":"Kreissparkasse Kaiserslautern",
    "wof:placetype":"venue"
},
  "geometry": {"coordinates":[7.529775,49.456398],"type":"Point"}
}