{
  "type": "Feature",
  "properties": {
    "iso:country":"DE",
    "sg:address":"Im Ostereschfeld 3",
    "sg:city":"Garbsen",
    "sg:phone":"+49 5137/72997",
    "sg:postcode":"30823",
    "sg:province":"Niedersachsen",
    "wof:name":"W. Wittenberg Gmbh",
    "wof:placetype":"venue"
},
  "geometry": {"coordinates":[9.593670845,52.4108276367],"type":"Point"}
}