{
  "type": "Feature",
  "properties": {
    "iso:country":"DE",
    "sg:address":"Mittlere Ortsstr. 69",
    "sg:city":"R\u00fclzheim",
    "sg:phone":"+49 7272/8764",
    "sg:postcode":"76761",
    "sg:province":"Rheinland-Pfalz",
    "wof:name":"Werling Und Brandenburg",
    "wof:placetype":"venue"
},
  "geometry": {"coordinates":[8.292463,49.15694],"type":"Point"}
}