{
  "type": "Feature",
  "properties": {
    "iso:country":"DE",
    "sg:address":"Sandfeldstr. 31",
    "sg:city":"Rietberg",
    "sg:phone":"+49 5244/5353",
    "sg:postcode":"33397",
    "sg:province":"Nordrhein-Westfalen",
    "wof:name":"Norbert Schal\u00fcck",
    "wof:placetype":"venue"
},
  "geometry": {"coordinates":[8.42691,51.823593],"type":"Point"}
}