{
  "type": "Feature",
  "properties": {
    "iso:country":"DE",
    "sg:address":"Ackerstr. 8",
    "sg:city":"Minden",
    "sg:phone":"+49 571/52288",
    "sg:postcode":"32429",
    "sg:province":"Nordrhein-Westfalen",
    "wof:name":"Bm Elektrotechnik E. Kfm.",
    "wof:placetype":"venue"
},
  "geometry": {"coordinates":[8.8656320572,52.269317627],"type":"Point"}
}