{
  "type": "Feature",
  "properties": {
    "iso:country":"DE",
    "sg:address":"Hammer Str. 67",
    "sg:city":"M\u00fcnster",
    "sg:phone":"+49 251/73868",
    "sg:postcode":"48153",
    "sg:province":"Nordrhein-Westfalen",
    "wof:name":"Hotel-restaurant Krone",
    "wof:placetype":"venue"
},
  "geometry": {"coordinates":[7.6246709824,51.9494094849],"type":"Point"}
}