{
  "type": "Feature",
  "properties": {
    "iso:country":"DE",
    "sg:address":"Wilthener Str. 13",
    "sg:city":"Obergurig",
    "sg:phone":"+49 35938/50468",
    "sg:postcode":"02692",
    "sg:province":"Sachsen",
    "wof:name":"B\u00e4ckerei Am Kuchenh\u00e4usel Gmbh",
    "wof:placetype":"venue"
},
  "geometry": {"coordinates":[14.412473,51.129288],"type":"Point"}
}