{
  "type": "Feature",
  "properties": {
    "iso:country":"DE",
    "sg:address":"Anton-Heinen-Str. 47",
    "sg:city":"Bedburg",
    "sg:phone":"+49 2272/2086",
    "sg:postcode":"50181",
    "sg:province":"Nordrhein-Westfalen",
    "wof:name":"Roadmaster Transporte Gmbh & Co. Kg",
    "wof:placetype":"venue"
},
  "geometry": {"coordinates":[6.5746598244,50.978729248],"type":"Point"}
}