{
  "type": "Feature",
  "properties": {
    "iso:country":"DE",
    "sg:address":"Kronenstr. 6",
    "sg:city":"Alfter",
    "sg:phone":"+49 2222/62718",
    "sg:postcode":"53347",
    "sg:province":"Nordrhein-Westfalen",
    "wof:name":"Haus Der Gesundheit",
    "wof:placetype":"venue"
},
  "geometry": {"coordinates":[7.0116858482,50.7383918762],"type":"Point"}
}