{
  "type": "Feature",
  "properties": {
    "iso:country":"DE",
    "sg:address":"Robert-Koch-Str. 8",
    "sg:city":"Dielheim",
    "sg:phone":"+49 6222/74652",
    "sg:postcode":"69234",
    "sg:province":"Baden-W\u00fcrttemberg",
    "wof:name":"Wesch & Co. Gmbh",
    "wof:placetype":"venue"
},
  "geometry": {"coordinates":[8.7369680405,49.2869873047],"type":"Point"}
}