{
  "type": "Feature",
  "properties": {
    "iso:country":"DE",
    "sg:address":"Neus\u00e4sser Str. 17",
    "sg:city":"Augsburg",
    "sg:phone":"+49 821/406050",
    "sg:postcode":"86156",
    "sg:province":"Bayern",
    "wof:name":"Hans B\u00f6nsel",
    "wof:placetype":"venue"
},
  "geometry": {"coordinates":[10.848225,48.380917],"type":"Point"}
}