{
  "type": "Feature",
  "properties": {
    "iso:country":"DE",
    "sg:address":"Waldstr. 29",
    "sg:city":"Ostfildern",
    "sg:phone":"+49 711/455596",
    "sg:postcode":"73760",
    "sg:province":"Baden-W\u00fcrttemberg",
    "wof:name":"Klaus Kohler",
    "wof:placetype":"venue"
},
  "geometry": {"coordinates":[9.2253341675,48.7190895081],"type":"Point"}
}