{
  "type": "Feature",
  "properties": {
    "iso:country":"DE",
    "sg:address":"Steinhausstr. 60",
    "sg:city":"Neuss",
    "sg:phone":"+49 2131/58926",
    "sg:postcode":"41462",
    "sg:province":"Nordrhein-Westfalen",
    "wof:name":"Gebr. Schmitz",
    "wof:placetype":"venue"
},
  "geometry": {"coordinates":[6.666623,51.205978],"type":"Point"}
}