{
  "type": "Feature",
  "properties": {
    "iso:country":"DE",
    "sg:address":"Castroper Str. 209",
    "sg:city":"Bochum",
    "sg:phone":"+49 234/594059",
    "sg:postcode":"44791",
    "sg:province":"Nordrhein-Westfalen",
    "wof:name":"J. Beine",
    "wof:placetype":"venue"
},
  "geometry": {"coordinates":[7.243544,51.491791],"type":"Point"}
}