{
  "type": "Feature",
  "properties": {
    "iso:country":"DE",
    "sg:address":"Wagh\u00e4useler Str. 14",
    "sg:city":"Neulu\u00dfheim",
    "sg:phone":"+49 6205/33311",
    "sg:postcode":"68809",
    "sg:province":"Baden-W\u00fcrttemberg",
    "wof:name":"Berthold Siegel",
    "wof:placetype":"venue"
},
  "geometry": {"coordinates":[8.522008,49.292915],"type":"Point"}
}