{
  "type": "Feature",
  "properties": {
    "iso:country":"DE",
    "sg:address":"Schaeferstr. 18",
    "sg:city":"Herne",
    "sg:phone":"+49 2323/95440",
    "sg:postcode":"44623",
    "sg:province":"Nordrhein-Westfalen",
    "wof:name":"Herrmann-trentepohl Und Partne Rechtsanw\u00e4lte",
    "wof:placetype":"venue"
},
  "geometry": {"coordinates":[7.2255749702,51.5407333374],"type":"Point"}
}