{
  "type": "Feature",
  "properties": {
    "iso:country":"DE",
    "sg:address":"Triftweg 35",
    "sg:city":"Belgern",
    "sg:phone":"+49 34224/40494",
    "sg:postcode":"04874",
    "sg:province":"Sachsen",
    "wof:name":"Thomas Vogel",
    "wof:placetype":"venue"
},
  "geometry": {"coordinates":[13.117065,51.48801],"type":"Point"}
}