{
  "type": "Feature",
  "properties": {
    "iso:country":"DE",
    "sg:address":"Ahrweiler Str. 30",
    "sg:city":"Bad M\u00fcnstereifel",
    "sg:phone":"+49 2253/180349",
    "sg:postcode":"53902",
    "sg:province":"Nordrhein-Westfalen",
    "wof:name":"P. Sch\u00e4fer",
    "wof:placetype":"venue"
},
  "geometry": {"coordinates":[6.7734770775,50.5320663452],"type":"Point"}
}