{
  "type": "Feature",
  "properties": {
    "iso:country":"DE",
    "sg:address":"Carl-Zeiss-Str. 17",
    "sg:city":"Hemmingen",
    "sg:postcode":"30966",
    "sg:province":"Niedersachsen",
    "wof:name":"S\u00f6hlmann Gmbh",
    "wof:placetype":"venue"
},
  "geometry": {"coordinates":[9.725847,52.319946],"type":"Point"}
}