{
  "type": "Feature",
  "properties": {
    "iso:country":"DE",
    "sg:address":"Danziger Str. 32",
    "sg:city":"Wittlich",
    "sg:phone":"+49 6571/96280",
    "sg:postcode":"54516",
    "sg:province":"Rheinland-Pfalz",
    "wof:name":"Norbert Zisch",
    "wof:placetype":"venue"
},
  "geometry": {"coordinates":[6.8974080086,49.9910392761],"type":"Point"}
}