{
  "type": "Feature",
  "properties": {
    "iso:country":"DE",
    "sg:address":"Hohgang 3-4",
    "sg:city":"Schlotheim",
    "sg:phone":"+49 36021/84888",
    "sg:postcode":"99994",
    "sg:province":"Th\u00fcringen",
    "wof:name":"M\u00f6belbau Haase Kg",
    "wof:placetype":"venue"
},
  "geometry": {"coordinates":[10.65405,51.245354],"type":"Point"}
}