{
  "type": "Feature",
  "properties": {
    "iso:country":"DE",
    "sg:address":"G\u00fclzower Str. 31",
    "sg:city":"Berlin",
    "sg:phone":"+49 30/5615364",
    "sg:postcode":"12619",
    "sg:province":"Berlin",
    "wof:name":"Hans-dieter Beuthan Rechtsanwalt",
    "wof:placetype":"venue"
},
  "geometry": {"coordinates":[13.5910701752,52.5293655396],"type":"Point"}
}