{
  "type": "Feature",
  "properties": {
    "iso:country":"DE",
    "sg:address":"Rhumeweg 26",
    "sg:city":"Hemmingen",
    "sg:phone":"+49 5341/14214",
    "sg:postcode":"30966",
    "sg:province":"Niedersachsen",
    "wof:name":"Mmm Gmbh \u00c4rztebedarf",
    "wof:placetype":"venue"
},
  "geometry": {"coordinates":[9.7448711395,52.2993812561],"type":"Point"}
}