{
  "type": "Feature",
  "properties": {
    "iso:country":"DE",
    "sg:address":"Am Bahndamm 23",
    "sg:city":"Niederstotzingen",
    "sg:phone":"+49 7325/96080",
    "sg:postcode":"89168",
    "sg:province":"Baden-W\u00fcrttemberg",
    "wof:name":"Smt Schmidt Maschinentechnik Gmbh",
    "wof:placetype":"venue"
},
  "geometry": {"coordinates":[10.245882,48.537498],"type":"Point"}
}