{
  "type": "Feature",
  "properties": {
    "iso:country":"DE",
    "sg:address":"Industriestr. 4",
    "sg:city":"Halver",
    "sg:postcode":"58553",
    "sg:province":"Nordrhein-Westfalen",
    "wof:name":"Rumi Gmbh",
    "wof:placetype":"venue"
},
  "geometry": {"coordinates":[7.504594,51.196609],"type":"Point"}
}