{
  "type": "Feature",
  "properties": {
    "iso:country":"DE",
    "sg:address":"Karl-Marx-Str. 200",
    "sg:city":"Berlin",
    "sg:phone":"+49 30/6873500",
    "sg:postcode":"12055",
    "sg:province":"Berlin",
    "wof:name":"W. Wollek",
    "wof:placetype":"venue"
},
  "geometry": {"coordinates":[13.4409618378,52.4721641541],"type":"Point"}
}