{
  "type": "Feature",
  "properties": {
    "iso:country":"DE",
    "sg:address":"Hauptstr. 35",
    "sg:city":"Binswangen",
    "sg:postcode":"86637",
    "sg:province":"Bayern",
    "wof:name":"Werner Schmid",
    "wof:placetype":"venue"
},
  "geometry": {"coordinates":[10.6441440582,48.5596542358],"type":"Point"}
}