{
  "type": "Feature",
  "properties": {
    "iso:country":"DE",
    "sg:address":"K\u00f6lnische Str 4",
    "sg:city":"Kassel",
    "sg:phone":"+49 561/7016440",
    "sg:postcode":"34117",
    "sg:province":"Hessen",
    "wof:name":"Xpect Media Communication Gmbh",
    "wof:placetype":"venue"
},
  "geometry": {"coordinates":[9.4961338043,51.3162117004],"type":"Point"}
}