{
  "type": "Feature",
  "properties": {
    "iso:country":"DE",
    "sg:address":"Goldenstedter Str. 58",
    "sg:city":"Wildeshausen",
    "sg:phone":"+49 4431/2220",
    "sg:postcode":"27793",
    "sg:province":"Niedersachsen",
    "wof:name":"Thoms & Meyer",
    "wof:placetype":"venue"
},
  "geometry": {"coordinates":[8.43187,52.880356],"type":"Point"}
}