{
  "type": "Feature",
  "properties": {
    "iso:country":"DE",
    "sg:address":"Greifswalder Chaussee 105",
    "sg:city":"Stralsund",
    "sg:phone":"+49 3831/270102",
    "sg:postcode":"18439",
    "sg:province":"Mecklenburg-Vorpommern",
    "wof:name":"Hermann Sack Innenarchitekt",
    "wof:placetype":"venue"
},
  "geometry": {"coordinates":[13.091841,54.295963],"type":"Point"}
}