{
  "type": "Feature",
  "properties": {
    "iso:country":"DE",
    "sg:address":"Am Bienenhof 5",
    "sg:city":"Windeck",
    "sg:phone":"+49 2243/7276",
    "sg:postcode":"51570",
    "sg:province":"Nordrhein-Westfalen",
    "wof:name":"A. Lindemann",
    "wof:placetype":"venue"
},
  "geometry": {"coordinates":[7.538916,50.768272],"type":"Point"}
}