{
  "type": "Feature",
  "properties": {
    "iso:country":"DE",
    "sg:address":"Konrad-Wachsmann-Str. 31",
    "sg:city":"Niesky",
    "sg:phone":"+49 3588/201950",
    "sg:postcode":"02906",
    "sg:province":"Sachsen",
    "wof:name":"J\u00fcrgen Merker",
    "wof:placetype":"venue"
},
  "geometry": {"coordinates":[14.833791,51.288544],"type":"Point"}
}