{
  "type": "Feature",
  "properties": {
    "iso:country":"DE",
    "sg:address":"K\u00f6nigstr 87-89",
    "sg:city":"L\u00fcbeck",
    "sg:phone":"+49 451/799420",
    "sg:postcode":"23552",
    "sg:province":"Schleswig-Holstein",
    "wof:name":"Betten-struve L\u00fcbeck Gmbh & Co Kg",
    "wof:placetype":"venue"
},
  "geometry": {"coordinates":[10.686908,53.865688],"type":"Point"}
}