{
  "type": "Feature",
  "properties": {
    "iso:country":"DE",
    "sg:address":"Oswald-Bleier-Str. 2",
    "sg:city":"Riesa",
    "sg:phone":"+49 3525/872305",
    "sg:postcode":"01591",
    "sg:province":"Sachsen",
    "wof:name":"Marita Schnellbach",
    "wof:placetype":"venue"
},
  "geometry": {"coordinates":[13.251381,51.307461],"type":"Point"}
}