{
  "type": "Feature",
  "properties": {
    "iso:country":"DE",
    "sg:address":"Mainzer Str. 57",
    "sg:city":"Koblenz",
    "sg:phone":"+49 261/12222",
    "sg:postcode":"56068",
    "sg:province":"Rheinland-Pfalz",
    "wof:name":"Gerus-medien Gmbh",
    "wof:placetype":"venue"
},
  "geometry": {"coordinates":[7.596024,50.347668],"type":"Point"}
}