{
  "type": "Feature",
  "properties": {
    "iso:country":"DE",
    "sg:address":"Kreuzstr. 38",
    "sg:city":"Wesel",
    "sg:phone":"+49 281/24632",
    "sg:postcode":"46483",
    "sg:province":"Nordrhein-Westfalen",
    "wof:name":"R\u00f6merstube",
    "wof:placetype":"venue"
},
  "geometry": {"coordinates":[6.6166238785,51.6557388306],"type":"Point"}
}