{
  "type": "Feature",
  "properties": {
    "iso:country":"DE",
    "sg:address":"Kleinmattweg 8",
    "sg:city":"Auggen",
    "sg:phone":"+49 7631/6544",
    "sg:postcode":"79424",
    "sg:province":"Baden-W\u00fcrttemberg",
    "wof:name":"E. Vonthron Gmbh",
    "wof:placetype":"venue"
},
  "geometry": {"coordinates":[7.5920200348,47.7932891846],"type":"Point"}
}