{
  "type": "Feature",
  "properties": {
    "iso:country":"DE",
    "sg:address":"Donnersbergerstr. 47",
    "sg:city":"M\u00fcnchen",
    "sg:phone":"+49 89/160654",
    "sg:postcode":"80634",
    "sg:province":"Bayern",
    "wof:name":"Donnersberger-apotheke Michaela B\u00e4cker",
    "wof:placetype":"venue"
},
  "geometry": {"coordinates":[11.534259,48.147648],"type":"Point"}
}