{
  "type": "Feature",
  "properties": {
    "iso:country":"DE",
    "sg:address":"Trebestr. 2",
    "sg:city":"Bad Berka",
    "sg:postcode":"99438",
    "sg:province":"Th\u00fcringen",
    "wof:name":"Katholisches Pfarramt Bad Berka",
    "wof:placetype":"venue"
},
  "geometry": {"coordinates":[11.2877111435,50.8919563293],"type":"Point"}
}