{
  "type": "Feature",
  "properties": {
    "iso:country":"DE",
    "sg:address":"Leipziger Str. 49",
    "sg:city":"M\u00fchlau",
    "sg:phone":"+49 3722/95154",
    "sg:postcode":"09241",
    "sg:province":"Sachsen",
    "wof:name":"Walter Tauscher",
    "wof:placetype":"venue"
},
  "geometry": {"coordinates":[12.75567,50.903141],"type":"Point"}
}