{
  "type": "Feature",
  "properties": {
    "iso:country":"DE",
    "sg:address":"Teimbergstr. 16",
    "sg:city":"Velbert",
    "sg:phone":"+49 2053/4470",
    "sg:postcode":"42553",
    "sg:province":"Nordrhein-Westfalen",
    "wof:name":"Seibert Gmbh",
    "wof:placetype":"venue"
},
  "geometry": {"coordinates":[7.1059,51.311199],"type":"Point"}
}