{
  "type": "Feature",
  "properties": {
    "iso:country":"DE",
    "sg:address":"Ihlpohler Heerstr. 36",
    "sg:city":"Ritterhude",
    "sg:phone":"+49 421/6363230",
    "sg:postcode":"27721",
    "sg:province":"Niedersachsen",
    "wof:name":"D. Sonnenburg-roth",
    "wof:placetype":"venue"
},
  "geometry": {"coordinates":[8.7071380615,53.1851158142],"type":"Point"}
}