{
  "type": "Feature",
  "properties": {
    "iso:country":"DE",
    "sg:address":"Weststr. 25",
    "sg:city":"Herzogenrath",
    "sg:phone":"+49 2407/4011",
    "sg:postcode":"52134",
    "sg:province":"Nordrhein-Westfalen",
    "wof:name":"Peter Weyer",
    "wof:placetype":"venue"
},
  "geometry": {"coordinates":[6.0866408348,50.8344612122],"type":"Point"}
}