{
  "type": "Feature",
  "properties": {
    "iso:country":"DE",
    "sg:address":"Ringstr. 15",
    "sg:city":"Allendorf",
    "sg:phone":"+49 6452/6228",
    "sg:postcode":"35108",
    "sg:province":"Hessen",
    "wof:name":"Maler Und Lackierbetrieb Bienhaus Gmbh",
    "wof:placetype":"venue"
},
  "geometry": {"coordinates":[8.665967,51.019386],"type":"Point"}
}