{
  "type": "Feature",
  "properties": {
    "iso:country":"DE",
    "sg:address":"K\u00f6nigsberger Str. 1-3",
    "sg:city":"Frankfurt",
    "sg:phone":"+49 69/7949153",
    "sg:postcode":"60487",
    "sg:province":"Hessen",
    "wof:name":"Fachverband G\u00fcterfernverkehr Der Vereinigung Des Verkehrs-",
    "wof:placetype":"venue"
},
  "geometry": {"coordinates":[8.6300497055,50.1278114319],"type":"Point"}
}