{
  "type": "Feature",
  "properties": {
    "iso:country":"DE",
    "sg:address":"Schlo\u00dfberg 2",
    "sg:city":"Mainleus",
    "sg:phone":"+49 9229/1007",
    "sg:postcode":"95336",
    "sg:province":"Bayern",
    "wof:name":"Cafe Burgw\u00e4chter",
    "wof:placetype":"venue"
},
  "geometry": {"coordinates":[11.382753,50.114101],"type":"Point"}
}