{
  "type": "Feature",
  "properties": {
    "iso:country":"DE",
    "sg:address":"Ringstr. 13",
    "sg:city":"Nandlstadt",
    "sg:phone":"+49 8756/96120",
    "sg:postcode":"85405",
    "sg:province":"Bayern",
    "wof:name":"Ansynova Gmbh",
    "wof:placetype":"venue"
},
  "geometry": {"coordinates":[11.808647,48.537193],"type":"Point"}
}