{
  "type": "Feature",
  "properties": {
    "iso:country":"DE",
    "sg:address":"Auf den L\u00fcppen 2",
    "sg:city":"Herborn",
    "sg:phone":"+49 2772/51000",
    "sg:postcode":"35745",
    "sg:province":"Hessen",
    "wof:name":"Ulmer Gmbh",
    "wof:placetype":"venue"
},
  "geometry": {"coordinates":[8.3045063019,50.6802482605],"type":"Point"}
}