{
  "type": "Feature",
  "properties": {
    "iso:country":"DE",
    "sg:address":"Zeppelinstr. 33",
    "sg:city":"Landau",
    "sg:phone":"+49 6341/84698",
    "sg:postcode":"76829",
    "sg:province":"Rheinland-Pfalz",
    "wof:name":"Billardcafe Playland",
    "wof:placetype":"venue"
},
  "geometry": {"coordinates":[8.117194,49.203922],"type":"Point"}
}