{
  "type": "Feature",
  "properties": {
    "iso:country":"DE",
    "sg:address":"K\u00f6nigswinterer Str. 314-319",
    "sg:city":"K\u00f6nigswinter",
    "sg:phone":"+49 2223/21694",
    "sg:postcode":"53639",
    "sg:province":"Nordrhein-Westfalen",
    "wof:name":"Heider Einrichtungs- Und Raumausstattungs Gmbh",
    "wof:placetype":"venue"
},
  "geometry": {"coordinates":[7.2663679123,50.6801567078],"type":"Point"}
}