{
  "type": "Feature",
  "properties": {
    "iso:country":"DE",
    "sg:address":"Schleefstr. 1",
    "sg:city":"Dortmund",
    "sg:phone":"+49 231/945001",
    "sg:postcode":"44287",
    "sg:province":"Nordrhein-Westfalen",
    "wof:name":"Fritz Busche Druckereigesellschaft Mbh",
    "wof:placetype":"venue"
},
  "geometry": {"coordinates":[7.572104,51.501614],"type":"Point"}
}