{
  "type": "Feature",
  "properties": {
    "iso:country":"DE",
    "sg:address":"Gutenbergstr. 6",
    "sg:city":"Straubing",
    "sg:phone":"+49 9421/78340",
    "sg:postcode":"94315",
    "sg:province":"Bayern",
    "wof:name":"Union-\u00d6lfeuerung Schreiber Gmbh & Co. Kg",
    "wof:placetype":"venue"
},
  "geometry": {"coordinates":[12.627159,48.890549],"type":"Point"}
}