{
  "type": "Feature",
  "properties": {
    "iso:country":"DE",
    "sg:address":"Hartlaubstr. 7",
    "sg:city":"Bremen",
    "sg:phone":"+49 421/255200",
    "sg:postcode":"28355",
    "sg:province":"Bremen",
    "wof:name":"S & L Dienstleistung Gmbh",
    "wof:placetype":"venue"
},
  "geometry": {"coordinates":[8.9130802155,53.0897712708],"type":"Point"}
}