{
  "type": "Feature",
  "properties": {
    "iso:country":"DE",
    "sg:address":"Talstr. 3",
    "sg:city":"Oberrothenbach",
    "sg:phone":"+49 37604/2402",
    "sg:postcode":"08129",
    "wof:name":"Eckhard Seifert",
    "wof:placetype":"venue"
},
  "geometry": {"coordinates":[12.47484,50.76709],"type":"Point"}
}