{
  "type": "Feature",
  "properties": {
    "iso:country":"DE",
    "sg:address":"Moosstr. 19",
    "sg:city":"Altdorf",
    "sg:phone":"+49 871/34991",
    "sg:postcode":"84034",
    "sg:province":"Bayern",
    "wof:name":"Sparkasse Landshut",
    "wof:placetype":"venue"
},
  "geometry": {"coordinates":[12.099737,48.549511],"type":"Point"}
}