{
  "type": "Feature",
  "properties": {
    "iso:country":"DE",
    "sg:address":"Cuxhavener Str. 93",
    "sg:city":"Cuxhaven",
    "sg:phone":"+49 4721/47248",
    "sg:postcode":"27476",
    "sg:province":"Niedersachsen",
    "wof:name":"Adolf Und Renate Hillmer Immobilienmakler",
    "wof:placetype":"venue"
},
  "geometry": {"coordinates":[8.644288063,53.8853874207],"type":"Point"}
}