{
  "type": "Feature",
  "properties": {
    "iso:country":"DE",
    "sg:address":"Schweinfurter Str. 14a",
    "sg:city":"Fuchsstadt",
    "sg:phone":"+49 9732/5658",
    "sg:postcode":"97727",
    "sg:province":"Bayern",
    "wof:name":"St\u00f6th Kg",
    "wof:placetype":"venue"
},
  "geometry": {"coordinates":[9.929973,50.107521],"type":"Point"}
}