{
  "type": "Feature",
  "properties": {
    "iso:country":"DE",
    "sg:address":"Ohmstr. 86a",
    "sg:city":"K\u00f6ln",
    "sg:phone":"+49 2203/39684",
    "sg:postcode":"51145",
    "sg:province":"Nordrhein-Westfalen",
    "wof:name":"C. Frechen",
    "wof:placetype":"venue"
},
  "geometry": {"coordinates":[7.0640068054,50.8898773193],"type":"Point"}
}