{
  "type": "Feature",
  "properties": {
    "iso:country":"DE",
    "sg:address":"Hertlingstr. 1",
    "sg:city":"M\u00fcnchen",
    "sg:phone":"+49 89/64270132",
    "sg:postcode":"81545",
    "sg:province":"Bayern",
    "wof:name":"Herbert Ruckd\u00e4schel",
    "wof:placetype":"venue"
},
  "geometry": {"coordinates":[11.570561409,48.0887145996],"type":"Point"}
}