{
  "type": "Feature",
  "properties": {
    "iso:country":"DE",
    "sg:address":"Corresburger Weg 46",
    "sg:city":"M\u00f6nchengladbach",
    "sg:phone":"+49 2166/83437",
    "sg:postcode":"41238",
    "sg:province":"Nordrhein-Westfalen",
    "wof:name":"Rainer Skupin Architekt",
    "wof:placetype":"venue"
},
  "geometry": {"coordinates":[6.516091,51.154758],"type":"Point"}
}