{
  "type": "Feature",
  "properties": {
    "iso:country":"DE",
    "sg:address":"Neuburgerstr. 146",
    "sg:city":"Augsburg",
    "sg:phone":"+49 821",
    "sg:postcode":"86167",
    "sg:province":"Bayern",
    "wof:name":"Mountainbikes",
    "wof:placetype":"venue"
},
  "geometry": {"coordinates":[10.9159412384,48.3884468079],"type":"Point"}
}