{
  "type": "Feature",
  "properties": {
    "iso:country":"DE",
    "sg:address":"Nelkenweg 8",
    "sg:city":"Horstmar",
    "sg:postcode":"48612",
    "sg:province":"Nordrhein-Westfalen",
    "wof:name":"Thm Automatenbe- Und Vertriebsges. Mbh",
    "wof:placetype":"venue"
},
  "geometry": {"coordinates":[7.2953000069,52.0808486938],"type":"Point"}
}