{
  "type": "Feature",
  "properties": {
    "iso:country":"DE",
    "sg:address":"Dorfstr. 62",
    "sg:city":"Heinrichsruh",
    "sg:phone":"+49 39778/20235",
    "sg:postcode":"17379",
    "sg:province":"Mecklenburg-Vorpommern",
    "wof:name":"C. Tank",
    "wof:placetype":"venue"
},
  "geometry": {"coordinates":[13.926967,53.641296],"type":"Point"}
}