{
  "type": "Feature",
  "properties": {
    "iso:country":"DE",
    "sg:address":"Schlangenb\u00fchl 43",
    "sg:city":"Schramberg",
    "sg:phone":"+49 7422/7251",
    "sg:postcode":"78713",
    "sg:province":"Baden-W\u00fcrttemberg",
    "wof:name":"K. Wilhelm Mech. Werkstatt",
    "wof:placetype":"venue"
},
  "geometry": {"coordinates":[8.403361,48.210442],"type":"Point"}
}