{
  "type": "Feature",
  "properties": {
    "iso:country":"DE",
    "sg:address":"Burgratz 7",
    "sg:city":"Sulzberg",
    "sg:phone":"+49 8376/664",
    "sg:postcode":"87477",
    "sg:province":"Bayern",
    "wof:name":"R\u00fcger Gmbh",
    "wof:placetype":"venue"
},
  "geometry": {"coordinates":[10.3261566162,47.6494216919],"type":"Point"}
}