{
  "type": "Feature",
  "properties": {
    "iso:country":"DE",
    "sg:address":"Heuweg 17",
    "sg:city":"Burgthann",
    "sg:postcode":"90559",
    "sg:province":"Bayern",
    "wof:name":"Curamed Wohnbau Gmbh",
    "wof:placetype":"venue"
},
  "geometry": {"coordinates":[11.342448,49.348808],"type":"Point"}
}