{
  "type": "Feature",
  "properties": {
    "iso:country":"DE",
    "sg:address":"Hauptstr. 5",
    "sg:city":"Neckartenzlingen",
    "sg:phone":"+49 7127/33385",
    "sg:postcode":"72654",
    "sg:province":"Baden-W\u00fcrttemberg",
    "wof:name":"Imbi\u00dfstube",
    "wof:placetype":"venue"
},
  "geometry": {"coordinates":[9.2341947556,48.59034729],"type":"Point"}
}