{
  "type": "Feature",
  "properties": {
    "iso:country":"DE",
    "sg:address":"Recklinghauser Str. 28",
    "sg:city":"Sundern",
    "sg:phone":"+49 2933/97400",
    "sg:postcode":"59846",
    "sg:province":"Nordrhein-Westfalen",
    "wof:name":"Kpm-leuchten Inh. Klara Pies",
    "wof:placetype":"venue"
},
  "geometry": {"coordinates":[8.024158,51.308754],"type":"Point"}
}