{
  "type": "Feature",
  "properties": {
    "iso:country":"DE",
    "sg:address":"Alte Str. 23",
    "sg:city":"Brey",
    "sg:postcode":"56321",
    "sg:province":"Rheinland-Pfalz",
    "wof:name":"Kids In Gmbh",
    "wof:placetype":"venue"
},
  "geometry": {"coordinates":[7.618161,50.280445],"type":"Point"}
}