{
  "type": "Feature",
  "properties": {
    "iso:country":"DE",
    "sg:address":"Friedrichstr. 26",
    "sg:city":"Balingen",
    "sg:phone":"+49 7433/21994",
    "sg:postcode":"72336",
    "sg:province":"Baden-W\u00fcrttemberg",
    "wof:name":"G. Schmid Stahl- Und Schneidwaren",
    "wof:placetype":"venue"
},
  "geometry": {"coordinates":[8.8512001038,48.2743873596],"type":"Point"}
}