{
  "type": "Feature",
  "properties": {
    "iso:country":"DE",
    "sg:address":"Wachtelschlag 3",
    "sg:city":"L\u00fcbeck",
    "sg:phone":"+49 451/51594",
    "sg:postcode":"23562",
    "sg:province":"Schleswig-Holstein",
    "wof:name":"Beck Und Meyer",
    "wof:placetype":"venue"
},
  "geometry": {"coordinates":[10.7134485245,53.8519668579],"type":"Point"}
}