{
  "type": "Feature",
  "properties": {
    "iso:country":"DE",
    "sg:address":"Burgstr. 27",
    "sg:city":"Flensburg",
    "sg:postcode":"24939",
    "sg:province":"Schleswig-Holstein",
    "wof:name":"F\u00f6rde-netzwerk E. K.",
    "wof:placetype":"venue"
},
  "geometry": {"coordinates":[9.427226,54.793144],"type":"Point"}
}