{
  "type": "Feature",
  "properties": {
    "iso:country":"DE",
    "sg:address":"Weinreihe 3",
    "sg:city":"Bad Sooden-Allendorf",
    "sg:phone":"+49 5652/1661",
    "sg:postcode":"37242",
    "sg:province":"Hessen",
    "wof:name":"F. Wenderoth",
    "wof:placetype":"venue"
},
  "geometry": {"coordinates":[9.9646654129,51.2689552307],"type":"Point"}
}