{
  "type": "Feature",
  "properties": {
    "iso:country":"DE",
    "sg:address":"\u00c4u\u00dfere Uferstr. 61-73",
    "sg:city":"Augsburg",
    "sg:phone":"+49 821/41030",
    "sg:postcode":"86154",
    "sg:province":"Bayern",
    "wof:name":"Zeuna St\u00e4rker International Gmbh",
    "wof:placetype":"venue"
},
  "geometry": {"coordinates":[10.885775,48.388599],"type":"Point"}
}