{
  "type": "Feature",
  "properties": {
    "iso:country":"DE",
    "sg:address":"Fuhrwegen 24",
    "sg:city":"L\u00fctjensee",
    "sg:postcode":"22952",
    "sg:province":"Schleswig-Holstein",
    "wof:name":"B\u00fcro-organisations-service H.-j. Neudewitz Gmbh",
    "wof:placetype":"venue"
},
  "geometry": {"coordinates":[10.344043,53.642361],"type":"Point"}
}