{
  "type": "Feature",
  "properties": {
    "iso:country":"DE",
    "sg:address":"Jahnstr. 85",
    "sg:city":"Viernheim",
    "sg:phone":"+49 6204/79259",
    "sg:postcode":"68519",
    "sg:province":"Hessen",
    "wof:name":"Jahnecke",
    "wof:placetype":"venue"
},
  "geometry": {"coordinates":[8.5678367615,49.5288391113],"type":"Point"}
}