{
  "type": "Feature",
  "properties": {
    "iso:country":"DE",
    "sg:address":"Marktstr. 2",
    "sg:city":"Oelsnitz",
    "sg:phone":"+49 37421/22833",
    "sg:postcode":"08606",
    "sg:province":"Sachsen",
    "wof:name":"Gerdi Eck Notariat",
    "wof:placetype":"venue"
},
  "geometry": {"coordinates":[12.1720228195,50.4147987366],"type":"Point"}
}