{
  "type": "Feature",
  "properties": {
    "iso:country":"DE",
    "sg:address":"R\u00f6ntgenstr 2A",
    "sg:city":"Reinbek",
    "sg:phone":"+49 40/6569760",
    "sg:postcode":"21465",
    "sg:province":"Schleswig-Holstein",
    "wof:name":"Baltic Kunststoff Handels Gmbh",
    "wof:placetype":"venue"
},
  "geometry": {"coordinates":[10.2377510071,53.5291213989],"type":"Point"}
}