{
  "type": "Feature",
  "properties": {
    "iso:country":"DE",
    "sg:address":"Im S\u00e4nder 14",
    "sg:city":"Bad Ditzenbach",
    "sg:phone":"+49 7335/6505",
    "sg:postcode":"73342",
    "sg:province":"Baden-W\u00fcrttemberg",
    "wof:name":"H. Bosch",
    "wof:placetype":"venue"
},
  "geometry": {"coordinates":[9.673935,48.578819],"type":"Point"}
}