{
  "type": "Feature",
  "properties": {
    "iso:country":"DE",
    "sg:address":"G\u00fcstrower Str. 14",
    "sg:city":"Malchow",
    "sg:phone":"+49 39932/81547",
    "sg:postcode":"17213",
    "sg:province":"Mecklenburg-Vorpommern",
    "wof:name":"M. Landt",
    "wof:placetype":"venue"
},
  "geometry": {"coordinates":[12.425275,53.475311],"type":"Point"}
}