{
  "type": "Feature",
  "properties": {
    "iso:country":"DE",
    "sg:address":"Danziger Str. 35",
    "sg:city":"Wittlich",
    "sg:phone":"+49 6571/5267",
    "sg:postcode":"54516",
    "sg:province":"Rheinland-Pfalz",
    "wof:name":"Helmut Breuer Ingenieur",
    "wof:placetype":"venue"
},
  "geometry": {"coordinates":[6.8935070038,49.9892845154],"type":"Point"}
}