{
  "type": "Feature",
  "properties": {
    "iso:country":"DE",
    "sg:address":"Bergstr. 10",
    "sg:city":"Bischoffen",
    "sg:phone":"+49 6444/321",
    "sg:postcode":"35649",
    "sg:province":"Hessen",
    "wof:name":"G. Sch\u00e4fer",
    "wof:placetype":"venue"
},
  "geometry": {"coordinates":[8.4496326447,50.7039489746],"type":"Point"}
}