{
  "type": "Feature",
  "properties": {
    "iso:country":"DE",
    "sg:address":"Hardisser Str. 80",
    "sg:city":"Lage",
    "sg:phone":"+49 5232/4511",
    "sg:postcode":"32791",
    "sg:province":"Nordrhein-Westfalen",
    "wof:name":"Hans J. Brandsmeier",
    "wof:placetype":"venue"
},
  "geometry": {"coordinates":[8.82409,52.008255],"type":"Point"}
}