{
  "type": "Feature",
  "properties": {
    "iso:country":"DE",
    "sg:address":"Hohenborner Str. 35",
    "sg:city":"Bad Pyrmont",
    "sg:phone":"+49 5281/961358",
    "sg:postcode":"31812",
    "sg:province":"Niedersachsen",
    "wof:name":"Erwin Walter",
    "wof:placetype":"venue"
},
  "geometry": {"coordinates":[9.2312402725,51.9822845459],"type":"Point"}
}