{
  "type": "Feature",
  "properties": {
    "iso:country":"DE",
    "sg:address":"Hohle 89",
    "sg:city":"Behringen",
    "sg:phone":"+49 3629/66850",
    "sg:postcode":"99326",
    "sg:province":"Th\u00fcringen",
    "wof:name":"Franke Gmbh & Co. Kg",
    "wof:placetype":"venue"
},
  "geometry": {"coordinates":[11.01314,50.775181],"type":"Point"}
}