{
  "type": "Feature",
  "properties": {
    "iso:country":"DE",
    "sg:address":"Hollerst\u00fcck 4",
    "sg:city":"Dautphetal",
    "sg:phone":"+49 6466/912970",
    "sg:postcode":"35232",
    "sg:province":"Hessen",
    "wof:name":"M. Henkel",
    "wof:placetype":"venue"
},
  "geometry": {"coordinates":[8.5612478256,50.8501701355],"type":"Point"}
}