{
  "type": "Feature",
  "properties": {
    "iso:country":"DE",
    "sg:address":"Berliner Freiheit 13",
    "sg:city":"Bremen",
    "sg:phone":"+49 421/4673331",
    "sg:postcode":"28327",
    "sg:province":"Bremen",
    "wof:name":"K. Und K. Spielbetriebe Gmbh",
    "wof:placetype":"venue"
},
  "geometry": {"coordinates":[8.892568,53.081184],"type":"Point"}
}