{
  "type": "Feature",
  "properties": {
    "iso:country":"DE",
    "sg:address":"Kumpfm\u00fchler Str. 65",
    "sg:city":"Regensburg",
    "sg:phone":"+49 941/947272",
    "sg:postcode":"93051",
    "sg:province":"Bayern",
    "wof:name":"Reiseb\u00fcro Kumpfm\u00fchl Gmbh",
    "wof:placetype":"venue"
},
  "geometry": {"coordinates":[12.0864839554,49.0060882568],"type":"Point"}
}