{
  "type": "Feature",
  "properties": {
    "iso:country":"DE",
    "sg:address":"Up de Breede 12",
    "sg:city":"Bocholt",
    "sg:phone":"+49 2871/44978",
    "sg:postcode":"46395",
    "sg:province":"Nordrhein-Westfalen",
    "wof:name":"Friedhelm Terweide",
    "wof:placetype":"venue"
},
  "geometry": {"coordinates":[6.573569,51.833004],"type":"Point"}
}