{
  "type": "Feature",
  "properties": {
    "iso:country":"DE",
    "sg:address":"Morgensternstr. 30",
    "sg:city":"Berlin",
    "sg:phone":"+49 30/7722428",
    "sg:postcode":"12207",
    "sg:province":"Berlin",
    "wof:name":"Rita Manthey Heilpraktikerin",
    "wof:placetype":"venue"
},
  "geometry": {"coordinates":[13.324669838,52.4276657104],"type":"Point"}
}