{
  "type": "Feature",
  "properties": {
    "iso:country":"DE",
    "sg:address":"Eichendorffstr. 43 - 45",
    "sg:city":"Ottobrunn",
    "sg:phone":"+49 89/6090461",
    "sg:postcode":"85521",
    "sg:province":"Bayern",
    "wof:name":"Hotel Siegfried",
    "wof:placetype":"venue"
},
  "geometry": {"coordinates":[11.6739368439,48.0629425049],"type":"Point"}
}