{
  "type": "Feature",
  "properties": {
    "iso:country":"DE",
    "sg:address":"Walsdorfer Str. 4",
    "sg:city":"Bischberg",
    "sg:phone":"+49 9549/384",
    "sg:postcode":"96120",
    "sg:province":"Bayern",
    "wof:name":"Heinz Neubauer",
    "wof:placetype":"venue"
},
  "geometry": {"coordinates":[10.773758,49.901417],"type":"Point"}
}