{
  "type": "Feature",
  "properties": {
    "iso:country":"DE",
    "sg:address":"Prinz-Georg-Str. 116",
    "sg:city":"D\u00fcsseldorf",
    "sg:phone":"+49 211/9062300",
    "sg:postcode":"40479",
    "sg:province":"Nordrhein-Westfalen",
    "wof:name":"Fp - Franchise Partner Servicegesellschaft F\u00fcr",
    "wof:placetype":"venue"
},
  "geometry": {"coordinates":[6.787857,51.23243],"type":"Point"}
}