{
  "type": "Feature",
  "properties": {
    "iso:country":"DE",
    "sg:address":"Hiltruper Str. 6",
    "sg:city":"M\u00fcnster",
    "sg:postcode":"48167",
    "sg:province":"Nordrhein-Westfalen",
    "wof:name":"Terra Beteiligungsges. Mbh",
    "wof:placetype":"venue"
},
  "geometry": {"coordinates":[7.7262282372,51.9159507751],"type":"Point"}
}