{
  "type": "Feature",
  "properties": {
    "iso:country":"DE",
    "sg:address":"Bahnhofstr. 20",
    "sg:city":"Schw\u00e4bisch Hall",
    "sg:phone":"+49 791/6392",
    "sg:postcode":"74523",
    "sg:province":"Baden-W\u00fcrttemberg",
    "wof:name":"J\u00fcrgen Zahn Detektei",
    "wof:placetype":"venue"
},
  "geometry": {"coordinates":[9.734529,49.109364],"type":"Point"}
}