{
  "type": "Feature",
  "properties": {
    "iso:country":"DE",
    "sg:address":"Ulmenstr. 27",
    "sg:city":"Chemnitz",
    "sg:postcode":"09112",
    "sg:province":"Sachsen",
    "wof:name":"Dr. Kr\u00fcger Immobilien Gmbh",
    "wof:placetype":"venue"
},
  "geometry": {"coordinates":[12.8989477158,50.8280563354],"type":"Point"}
}