{
  "type": "Feature",
  "properties": {
    "iso:country":"DE",
    "sg:address":"Stievestr. 2",
    "sg:city":"M\u00fcnchen",
    "sg:phone":"+49 89/1503835",
    "sg:postcode":"80638",
    "sg:province":"Bayern",
    "wof:name":"Beatrice Marxreiter Immobilienmaklerin",
    "wof:placetype":"venue"
},
  "geometry": {"coordinates":[11.5144834518,48.1590156555],"type":"Point"}
}