{
  "type": "Feature",
  "properties": {
    "iso:country":"DE",
    "sg:address":"Colmarer Str. 18",
    "sg:city":"Memmingen",
    "sg:phone":"+49 8331/86024",
    "sg:postcode":"87700",
    "sg:province":"Bayern",
    "wof:name":"Heinrich G\u00e4ble",
    "wof:placetype":"venue"
},
  "geometry": {"coordinates":[10.181841,47.992775],"type":"Point"}
}