{
  "type": "Feature",
  "properties": {
    "iso:country":"DE",
    "sg:address":"Schwanthalerallee 5",
    "sg:city":"Ludwigshafen",
    "sg:phone":"+49 621/565188",
    "sg:postcode":"67061",
    "sg:province":"Rheinland-Pfalz",
    "wof:name":"Hermannn Dorner",
    "wof:placetype":"venue"
},
  "geometry": {"coordinates":[8.4574966431,49.4682693481],"type":"Point"}
}