{
  "type": "Feature",
  "properties": {
    "iso:country":"DE",
    "sg:address":"Marienweiher 38",
    "sg:city":"Marktleugast",
    "sg:phone":"+49 9255/445",
    "sg:postcode":"95352",
    "sg:province":"Bayern",
    "wof:name":"G\u00fcnther & Bauer",
    "wof:placetype":"venue"
},
  "geometry": {"coordinates":[11.638453,50.158855],"type":"Point"}
}