{
  "type": "Feature",
  "properties": {
    "iso:country":"DE",
    "sg:address":"Gabelsbergerstr. 14",
    "sg:city":"Landshut",
    "sg:phone":"+49 871/962100",
    "sg:postcode":"84034",
    "sg:province":"Bayern",
    "wof:name":"Bayerische Landessiedlung Gmbh",
    "wof:placetype":"venue"
},
  "geometry": {"coordinates":[12.1433944702,48.5344200134],"type":"Point"}
}