{
  "type": "Feature",
  "properties": {
    "iso:country":"DE",
    "sg:address":"Bavariaring 29",
    "sg:city":"M\u00fcnchen",
    "sg:postcode":"80336",
    "sg:province":"Bayern",
    "wof:name":"Hvb Gesellschaft F\u00fcr Geb\u00e4ude Mbh & Co. Kg",
    "wof:placetype":"venue"
},
  "geometry": {"coordinates":[11.5536594391,48.1306877136],"type":"Point"}
}