{
  "type": "Feature",
  "properties": {
    "iso:country":"DE",
    "sg:address":"Waldstr. 168",
    "sg:city":"Mannheim",
    "sg:phone":"+49 621/745153",
    "sg:postcode":"68305",
    "sg:province":"Baden-W\u00fcrttemberg",
    "wof:name":"Pizzeria Bei Franco",
    "wof:placetype":"venue"
},
  "geometry": {"coordinates":[8.4855699539,49.5301017761],"type":"Point"}
}