{
  "type": "Feature",
  "properties": {
    "iso:country":"DE",
    "sg:address":"Schaarwisch 4",
    "sg:city":"Landkirchen",
    "sg:phone":"+49 4371/9981",
    "sg:postcode":"23769",
    "sg:province":"Schleswig-Holstein",
    "wof:name":"H. Maxe",
    "wof:placetype":"venue"
},
  "geometry": {"coordinates":[11.197016716,54.4362182617],"type":"Point"}
}