{
  "type": "Feature",
  "properties": {
    "iso:country":"DE",
    "sg:address":"Hopfensack 20",
    "sg:city":"Hamburg",
    "sg:postcode":"20457",
    "sg:province":"Hamburg",
    "wof:name":"Spotsn Tunes Inh. Joachim Niesche",
    "wof:placetype":"venue"
},
  "geometry": {"coordinates":[9.9992408752,53.5484466553],"type":"Point"}
}