{
  "type": "Feature",
  "properties": {
    "iso:country":"DE",
    "sg:address":"K\u00f6nigstr. 34",
    "sg:city":"Duisburg",
    "sg:phone":"+49 203/21131",
    "sg:postcode":"47051",
    "sg:province":"Nordrhein-Westfalen",
    "wof:name":"Berndtsen Und Redweik Rechtsanw\u00e4lte",
    "wof:placetype":"venue"
},
  "geometry": {"coordinates":[6.7672338486,51.4330673218],"type":"Point"}
}