{
  "type": "Feature",
  "properties": {
    "iso:country":"DE",
    "sg:address":"K\u00f6nigstr. 3",
    "sg:city":"Ahrensburg",
    "sg:phone":"+49 4102/59649",
    "sg:postcode":"22926",
    "sg:province":"Schleswig-Holstein",
    "wof:name":"Ahrensburger Klaviergalerie Moritz Benecke E. K.",
    "wof:placetype":"venue"
},
  "geometry": {"coordinates":[10.2406759262,53.6744308472],"type":"Point"}
}