{
  "type": "Feature",
  "properties": {
    "iso:country":"DE",
    "sg:address":"Feldbergstr. 24",
    "sg:city":"Heusenstamm",
    "sg:phone":"+49 6104/62361",
    "sg:postcode":"63150",
    "sg:province":"Hessen",
    "wof:name":"M. Banco Architektur Gmbh",
    "wof:placetype":"venue"
},
  "geometry": {"coordinates":[8.784825,50.049725],"type":"Point"}
}