{
  "type": "Feature",
  "properties": {
    "iso:country":"DE",
    "sg:address":"Wittelsbacherstr. 7",
    "sg:city":"Berg",
    "sg:phone":"+49 8151/5680",
    "sg:postcode":"82335",
    "sg:province":"Bayern",
    "wof:name":"Dr. Dieter Pr\u00f6ttel",
    "wof:placetype":"venue"
},
  "geometry": {"coordinates":[11.3525295258,47.9687690735],"type":"Point"}
}