{
  "type": "Feature",
  "properties": {
    "iso:country":"DE",
    "sg:address":"Nahestr. 33",
    "sg:city":"R\u00fcdesheim",
    "sg:phone":"+49 671/28150",
    "sg:postcode":"55593",
    "sg:province":"Rheinland-Pfalz",
    "wof:name":"R\u00fcdesheimer Rosengarten",
    "wof:placetype":"venue"
},
  "geometry": {"coordinates":[7.8118782043,49.8452377319],"type":"Point"}
}