{
  "type": "Feature",
  "properties": {
    "iso:country":"DE",
    "sg:address":"Leipziger Str. 8",
    "sg:city":"St. Wendel",
    "sg:phone":"+49 6851/9090",
    "sg:postcode":"66606",
    "sg:province":"Saarland",
    "wof:name":"Globus Holding Grundst\u00fccks- Verwertung Und Leasing",
    "wof:placetype":"venue"
},
  "geometry": {"coordinates":[7.152619,49.462399],"type":"Point"}
}