{
  "type": "Feature",
  "properties": {
    "iso:country":"DE",
    "sg:address":"Asenburgstr. 1",
    "sg:city":"Bad Salzuflen",
    "sg:phone":"+49 5222/6655",
    "sg:postcode":"32105",
    "sg:province":"Nordrhein-Westfalen",
    "wof:name":"Hotel Stadt Hamburg Willi Menninga",
    "wof:placetype":"venue"
},
  "geometry": {"coordinates":[8.7575101852,52.0854721069],"type":"Point"}
}