{
  "type": "Feature",
  "properties": {
    "iso:country":"DE",
    "sg:address":"An den Dominikanern 2-4",
    "sg:city":"K\u00f6ln",
    "sg:phone":"+49 221/134707",
    "sg:postcode":"50668",
    "sg:province":"Nordrhein-Westfalen",
    "wof:name":"Domino Friseur",
    "wof:placetype":"venue"
},
  "geometry": {"coordinates":[6.9555230141,50.9424819946],"type":"Point"}
}