{
  "type": "Feature",
  "properties": {
    "iso:country":"DE",
    "sg:address":"Bahnhofstr. 12",
    "sg:city":"Schmallenberg",
    "sg:phone":"+49 2971/86717",
    "sg:postcode":"57392",
    "sg:province":"Nordrhein-Westfalen",
    "wof:name":"Feldmann Gmbh",
    "wof:placetype":"venue"
},
  "geometry": {"coordinates":[8.2869844437,51.1549186707],"type":"Point"}
}