{
  "type": "Feature",
  "properties": {
    "iso:country":"DE",
    "sg:address":"J\u00e4gerstra\u00dfe 37",
    "sg:city":"G\u00fctersloh",
    "sg:phone":"+49 5241/212380",
    "sg:postcode":"33330",
    "sg:province":"Nordrhein-Westfalen",
    "wof:name":"Feldbusch Online",
    "wof:placetype":"venue"
},
  "geometry": {"coordinates":[8.362292,51.90873],"type":"Point"}
}