{
  "type": "Feature",
  "properties": {
    "iso:country":"DE",
    "sg:address":"Kleiststr. 20",
    "sg:city":"Rothenburg",
    "sg:phone":"+49 9861/7863",
    "sg:postcode":"91541",
    "sg:province":"Bayern",
    "wof:name":"Dr. Vinzenz Ebner Tierarzt",
    "wof:placetype":"venue"
},
  "geometry": {"coordinates":[10.1951618195,49.3726196289],"type":"Point"}
}