{
  "type": "Feature",
  "properties": {
    "iso:country":"DE",
    "sg:address":"Nove-Mesto-Platz 3E",
    "sg:city":"Hilden",
    "sg:postcode":"40721",
    "sg:province":"Nordrhein-Westfalen",
    "wof:name":"Andere Zeiten Bremer Gmbh",
    "wof:placetype":"venue"
},
  "geometry": {"coordinates":[6.93247,51.169392],"type":"Point"}
}