{
  "type": "Feature",
  "properties": {
    "iso:country":"DE",
    "sg:address":"Ernst-Abbe-Str. 13",
    "sg:city":"Koblenz",
    "sg:phone":"+49 261/43003",
    "sg:postcode":"56070",
    "sg:province":"Rheinland-Pfalz",
    "wof:name":"Jean Schneider Gmbh",
    "wof:placetype":"venue"
},
  "geometry": {"coordinates":[7.552472,50.389565],"type":"Point"}
}