{
  "type": "Feature",
  "properties": {
    "iso:country":"DE",
    "sg:address":"Naumannstr. 20",
    "sg:city":"Berlin",
    "sg:phone":"+49 30",
    "sg:postcode":"10829",
    "sg:province":"Berlin",
    "wof:name":"Pantasubito Berlin Shoppers - Fashion Fun And Furniture Cslt",
    "wof:placetype":"venue"
},
  "geometry": {"coordinates":[13.363286,52.484085],"type":"Point"}
}