{
  "type": "Feature",
  "properties": {
    "iso:country":"DE",
    "sg:address":"Dorfstr. 8",
    "sg:city":"Zootzen",
    "sg:phone":"+49 33087/52254",
    "sg:postcode":"16798",
    "sg:province":"Brandenburg",
    "wof:name":"Fritz Helm",
    "wof:placetype":"venue"
},
  "geometry": {"coordinates":[12.588687,53.138489],"type":"Point"}
}