{
  "type": "Feature",
  "properties": {
    "iso:country":"DE",
    "sg:address":"Jahnstr. 153",
    "sg:city":"Poppenhausen",
    "sg:phone":"+49 9725/6476",
    "sg:postcode":"98663",
    "sg:province":"Th\u00fcringen",
    "wof:name":"Kreissparkasse Schweinfurt",
    "wof:placetype":"venue"
},
  "geometry": {"coordinates":[10.724338,50.281292],"type":"Point"}
}