{
  "type": "Feature",
  "properties": {
    "iso:country":"DE",
    "sg:address":"B\u00f6ttgerstr. 7",
    "sg:city":"Braunschweig",
    "sg:phone":"+49 531/874101",
    "sg:postcode":"38122",
    "sg:province":"Niedersachsen",
    "wof:name":"Rudolf Marth Inh. K.- J\u00fcrgen Kersting Gmbh",
    "wof:placetype":"venue"
},
  "geometry": {"coordinates":[10.494341,52.212166],"type":"Point"}
}