{
  "type": "Feature",
  "properties": {
    "iso:country":"DE",
    "sg:address":"Ravenestr. 45",
    "sg:city":"Cochem",
    "sg:phone":"+49 2671/4520",
    "sg:postcode":"56812",
    "sg:province":"Rheinland-Pfalz",
    "wof:name":"Karl-stefan M\u00f6hlig Bildhauer",
    "wof:placetype":"venue"
},
  "geometry": {"coordinates":[7.166513,50.151161],"type":"Point"}
}