{
  "type": "Feature",
  "properties": {
    "iso:country":"DE",
    "sg:address":"Kinkelstr. 32",
    "sg:city":"Hagen",
    "sg:phone":"+49 2331/83465",
    "sg:postcode":"58097",
    "sg:province":"Nordrhein-Westfalen",
    "wof:name":"Maria Trumpetter Damenschneiderei",
    "wof:placetype":"venue"
},
  "geometry": {"coordinates":[7.4699249268,51.3672637939],"type":"Point"}
}