{
  "type": "Feature",
  "properties": {
    "iso:country":"DE",
    "sg:address":"Friederikenstr. 12",
    "sg:city":"Essen",
    "sg:postcode":"45130",
    "sg:province":"Nordrhein-Westfalen",
    "wof:name":"Deutsche Petanque Agentur",
    "wof:placetype":"venue"
},
  "geometry": {"coordinates":[7.0151357651,51.4412345886],"type":"Point"}
}