{
  "type": "Feature",
  "properties": {
    "iso:country":"DE",
    "sg:address":"R\u00f6ntgenstr. 26",
    "sg:city":"Schwarzenbek",
    "sg:phone":"+49 4151/81050",
    "sg:postcode":"21493",
    "sg:province":"Schleswig-Holstein",
    "wof:name":"Tea Corner - Tee- Verkaufsges. Mbh",
    "wof:placetype":"venue"
},
  "geometry": {"coordinates":[10.5055236816,53.5057945251],"type":"Point"}
}