{
  "type": "Feature",
  "properties": {
    "iso:country":"DE",
    "sg:address":"Ferdinand-Zwack-Str. 14",
    "sg:city":"Freising",
    "sg:phone":"+49 8161/4682",
    "sg:postcode":"85354",
    "sg:province":"Bayern",
    "wof:name":"Karl Huber Kunstmaler",
    "wof:placetype":"venue"
},
  "geometry": {"coordinates":[11.734789,48.400627],"type":"Point"}
}