{
  "type": "Feature",
  "properties": {
    "iso:country":"DE",
    "sg:address":"Alter G\u00f6bricher Weg 82",
    "sg:city":"Pforzheim",
    "sg:phone":"+49 7231/53419",
    "sg:postcode":"75177",
    "sg:province":"Baden-W\u00fcrttemberg",
    "wof:name":"Rolf Schmitt",
    "wof:placetype":"venue"
},
  "geometry": {"coordinates":[8.708654,48.911686],"type":"Point"}
}