{
  "type": "Feature",
  "properties": {
    "iso:country":"DE",
    "sg:address":"Uhlandstr. 57",
    "sg:city":"Fellbach",
    "sg:phone":"+49 711/512228",
    "sg:postcode":"70736",
    "sg:province":"Baden-W\u00fcrttemberg",
    "wof:name":"Erich Sch\u00fcbelin",
    "wof:placetype":"venue"
},
  "geometry": {"coordinates":[9.268723,48.829826],"type":"Point"}
}