{
  "type": "Feature",
  "properties": {
    "iso:country":"DE",
    "sg:address":"Wilhelmsh\u00f6her Allee 99",
    "sg:city":"Kassel",
    "sg:phone":"+49 561/281560",
    "sg:postcode":"34121",
    "sg:province":"Hessen",
    "wof:name":"Christa Baron",
    "wof:placetype":"venue"
},
  "geometry": {"coordinates":[9.4701786041,51.3121185303],"type":"Point"}
}