{
  "type": "Feature",
  "properties": {
    "iso:country":"DE",
    "sg:address":"Kalchstr. 15",
    "sg:city":"Memmingen",
    "sg:phone":"+49 8331/84553",
    "sg:postcode":"87700",
    "sg:province":"Bayern",
    "wof:name":"Claus Gaisser",
    "wof:placetype":"venue"
},
  "geometry": {"coordinates":[10.1829242706,47.9864654541],"type":"Point"}
}