{
  "type": "Feature",
  "properties": {
    "iso:country":"DE",
    "sg:address":"Gewerbehof 12",
    "sg:city":"Bopfingen",
    "sg:phone":"+49 7362/96680",
    "sg:postcode":"73441",
    "sg:province":"Baden-W\u00fcrttemberg",
    "wof:name":"Albert Rechtenbacher Gmbh",
    "wof:placetype":"venue"
},
  "geometry": {"coordinates":[10.3766899109,48.8484687805],"type":"Point"}
}