{
  "type": "Feature",
  "properties": {
    "iso:country":"DE",
    "sg:address":"Kollerm\u00fchlweg 6",
    "sg:city":"Grafenw\u00f6hr",
    "sg:phone":"+49 4977/3292560",
    "sg:postcode":"92655",
    "sg:province":"Bayern",
    "wof:name":"Gerald Sch\u00c4uble",
    "wof:placetype":"venue"
},
  "geometry": {"coordinates":[8.9547243118,47.7432441711],"type":"Point"}
}