{
  "type": "Feature",
  "properties": {
    "iso:country":"DE",
    "sg:address":"Steinweg 2",
    "sg:city":"Oldenburg",
    "sg:phone":"+49 441/12366",
    "sg:postcode":"26122",
    "sg:province":"Niedersachsen",
    "wof:name":"Heinz Nieland",
    "wof:placetype":"venue"
},
  "geometry": {"coordinates":[8.20662117,53.142250061],"type":"Point"}
}