{
  "type": "Feature",
  "properties": {
    "iso:country":"DE",
    "sg:address":"Drosselstr. 28",
    "sg:city":"R\u00f6dermark",
    "sg:phone":"+49 6074/90142",
    "sg:postcode":"63322",
    "sg:province":"Hessen",
    "wof:name":"Hannelore Nysik Dipl.-\u00dcbersetzerin",
    "wof:placetype":"venue"
},
  "geometry": {"coordinates":[8.821023,50.001549],"type":"Point"}
}