{
  "type": "Feature",
  "properties": {
    "iso:country":"DE",
    "sg:address":"Wilhelmstr. 25",
    "sg:city":"Kempten",
    "sg:phone":"+49 831/65535",
    "sg:postcode":"87437",
    "sg:province":"Bayern",
    "wof:name":"Ulrich Semmelmann",
    "wof:placetype":"venue"
},
  "geometry": {"coordinates":[10.3285942078,47.709651947],"type":"Point"}
}