{
  "type": "Feature",
  "properties": {
    "iso:country":"DE",
    "sg:address":"Stieglitzgasse 26",
    "sg:city":"Kirchheim",
    "sg:phone":"+49 89/90468725",
    "sg:postcode":"85551",
    "sg:province":"Bayern",
    "wof:name":"Kohlmann & Mittermeier Ges. F. D. Vertr. U. D. Verm.",
    "wof:placetype":"venue"
},
  "geometry": {"coordinates":[11.753862381,48.1672935486],"type":"Point"}
}