{
  "type": "Feature",
  "properties": {
    "iso:country":"DE",
    "sg:address":"August-Bebel-Str. 7",
    "sg:city":"Woldegk",
    "sg:phone":"+49 3963/210491",
    "sg:postcode":"17348",
    "sg:province":"Mecklenburg-Vorpommern",
    "wof:name":"Peter Wilfarth Gmbh",
    "wof:placetype":"venue"
},
  "geometry": {"coordinates":[13.587919,53.461819],"type":"Point"}
}