{
  "type": "Feature",
  "properties": {
    "iso:country":"DE",
    "sg:address":"Ursulastr. 7",
    "sg:city":"Dorsten",
    "sg:phone":"+49 2362/22832",
    "sg:postcode":"46282",
    "sg:province":"Nordrhein-Westfalen",
    "wof:name":"Bernhard Einhaus",
    "wof:placetype":"venue"
},
  "geometry": {"coordinates":[6.965569,51.661282],"type":"Point"}
}