{
  "type": "Feature",
  "properties": {
    "iso:country":"DE",
    "sg:address":"Stra\u00dfe des Friedens 75",
    "sg:city":"Osterburg",
    "sg:phone":"+49 3937/83784",
    "sg:postcode":"39606",
    "sg:province":"Sachsen-Anhalt",
    "wof:name":"Carola Kulessa",
    "wof:placetype":"venue"
},
  "geometry": {"coordinates":[11.7542695999,52.7869682312],"type":"Point"}
}