{
  "type": "Feature",
  "properties": {
    "iso:country":"DE",
    "sg:address":"Ludwigstr. 90",
    "sg:city":"Hanau",
    "sg:phone":"+49 6181/61360",
    "sg:postcode":"63456",
    "sg:province":"Hessen",
    "wof:name":"Gerold Roth",
    "wof:placetype":"venue"
},
  "geometry": {"coordinates":[8.914669,50.114292],"type":"Point"}
}