{
  "type": "Feature",
  "properties": {
    "iso:country":"DE",
    "sg:address":"Sandweg 4",
    "sg:city":"Frankfurt",
    "sg:phone":"+49 69/432906",
    "sg:postcode":"60316",
    "sg:province":"Hessen",
    "wof:name":"Vereinsgastst\u00e4tte Frankfurter Tv 1860",
    "wof:placetype":"venue"
},
  "geometry": {"coordinates":[8.6955938339,50.1161193848],"type":"Point"}
}