{
  "type": "Feature",
  "properties": {
    "iso:country":"DE",
    "sg:address":"Ortenberger Str. 40",
    "sg:city":"Offenburg",
    "sg:postcode":"77654",
    "sg:province":"Baden-W\u00fcrttemberg",
    "wof:name":"Henco-immobilien Betriebs- Und Verwaltungs Gmbh",
    "wof:placetype":"venue"
},
  "geometry": {"coordinates":[7.9537501335,48.4657974243],"type":"Point"}
}