{
  "type": "Feature",
  "properties": {
    "iso:country":"DE",
    "sg:address":"Langebr\u00fcckstr. 8",
    "sg:city":"Eckernf\u00f6rde",
    "sg:phone":"+49 4351/2160",
    "sg:postcode":"24340",
    "sg:province":"Schleswig-Holstein",
    "wof:name":"H.-h. Makoben",
    "wof:placetype":"venue"
},
  "geometry": {"coordinates":[9.835651,54.472744],"type":"Point"}
}