{
  "type": "Feature",
  "properties": {
    "iso:country":"DE",
    "sg:address":"Friedrich-Wilhelm-Str. 18",
    "sg:city":"Duisburg",
    "sg:postcode":"47051",
    "sg:province":"Nordrhein-Westfalen",
    "wof:name":"Cepro Deutschland Gmbh",
    "wof:placetype":"venue"
},
  "geometry": {"coordinates":[6.763602,51.43137],"type":"Point"}
}