{
  "type": "Feature",
  "properties": {
    "iso:country":"DE",
    "sg:address":"Am Alten Brunnen 9",
    "sg:city":"Werneck",
    "sg:phone":"+49 9722/9263",
    "sg:postcode":"97440",
    "sg:province":"Bayern",
    "wof:name":"Sk-fliesen",
    "wof:placetype":"venue"
},
  "geometry": {"coordinates":[10.0866117477,50.0307884216],"type":"Point"}
}