{
  "type": "Feature",
  "properties": {
    "iso:country":"DE",
    "sg:address":"Hinter der Lieth 26d",
    "sg:city":"Hamburg",
    "sg:phone":"+49 40/584824",
    "sg:postcode":"22529",
    "sg:province":"Hamburg",
    "wof:name":"B.-c. M\u00f6ller",
    "wof:placetype":"venue"
},
  "geometry": {"coordinates":[9.9516086578,53.6055679321],"type":"Point"}
}