{
  "type": "Feature",
  "properties": {
    "iso:country":"DE",
    "sg:address":"Hauptstr. 62",
    "sg:city":"Waldstetten",
    "sg:phone":"+49 7171/42202",
    "sg:postcode":"73550",
    "sg:province":"Baden-W\u00fcrttemberg",
    "wof:name":"Reinhold Wurst E. K.",
    "wof:placetype":"venue"
},
  "geometry": {"coordinates":[9.8223276138,48.7616500854],"type":"Point"}
}