{
  "type": "Feature",
  "properties": {
    "iso:country":"DE",
    "sg:address":"In der Muslen 2",
    "sg:city":"Villingen-Schwenningen",
    "sg:phone":"+49 7720/31929",
    "sg:postcode":"78054",
    "sg:province":"Baden-W\u00fcrttemberg",
    "wof:name":"Hilde Preissler",
    "wof:placetype":"venue"
},
  "geometry": {"coordinates":[8.536286,48.063435],"type":"Point"}
}