{
  "type": "Feature",
  "properties": {
    "iso:country":"DE",
    "sg:address":"Riegelstr. 33",
    "sg:city":"Ostfildern",
    "sg:postcode":"73760",
    "sg:province":"Baden-W\u00fcrttemberg",
    "wof:name":"Fj Reise Service Gmbh",
    "wof:placetype":"venue"
},
  "geometry": {"coordinates":[9.2940664291,48.7136192322],"type":"Point"}
}