{
  "type": "Feature",
  "properties": {
    "iso:country":"DE",
    "sg:address":"Pichlerstr. 15",
    "sg:city":"Laichingen",
    "sg:phone":"+49 7333/5533",
    "sg:postcode":"89150",
    "sg:province":"Baden-W\u00fcrttemberg",
    "wof:name":"Schreinerei Enderle",
    "wof:placetype":"venue"
},
  "geometry": {"coordinates":[9.6903800964,48.488193512],"type":"Point"}
}