{
  "type": "Feature",
  "properties": {
    "iso:country":"DE",
    "sg:address":"Astastr. 68 a",
    "sg:city":"Bielefeld",
    "sg:phone":"+49 521/914010",
    "sg:postcode":"33617",
    "sg:province":"Nordrhein-Westfalen",
    "wof:name":"Kummer Spielsalon Gmbh",
    "wof:placetype":"venue"
},
  "geometry": {"coordinates":[8.5142812729,51.99949646],"type":"Point"}
}