{
  "type": "Feature",
  "properties": {
    "iso:country":"DE",
    "sg:address":"Dresdener Str. 46",
    "sg:city":"Colditz",
    "sg:phone":"+49 34381/40407",
    "sg:postcode":"04680",
    "sg:province":"Sachsen",
    "wof:name":"Ilka M\u00fcller",
    "wof:placetype":"venue"
},
  "geometry": {"coordinates":[12.8115644455,51.1246757507],"type":"Point"}
}