{
  "type": "Feature",
  "properties": {
    "iso:country":"DE",
    "sg:address":"Dresdner Strasse 11/13",
    "sg:city":"Leipzig",
    "sg:phone":"+49 341",
    "sg:postcode":"04103",
    "sg:province":"Sachsen",
    "wof:name":"Mitteldeutsches Bauforum",
    "wof:placetype":"venue"
},
  "geometry": {"coordinates":[12.3912534714,51.3388404846],"type":"Point"}
}