{
  "type": "Feature",
  "properties": {
    "iso:country":"DE",
    "sg:address":"Alte Uhldinger Str. 4",
    "sg:city":"Uhldingen-M\u00fchlhofen",
    "sg:phone":"+49 7556/8629",
    "sg:postcode":"88690",
    "sg:province":"Baden-W\u00fcrttemberg",
    "wof:name":"Willi Gleichauf",
    "wof:placetype":"venue"
},
  "geometry": {"coordinates":[9.237378,47.730045],"type":"Point"}
}