{
  "type": "Feature",
  "properties": {
    "iso:country":"DE",
    "sg:address":"Max-von-Seubert-Str. 8",
    "sg:city":"Mannheim",
    "sg:phone":"+49 621/792907",
    "sg:postcode":"68259",
    "sg:province":"Baden-W\u00fcrttemberg",
    "wof:name":"M. Bieger",
    "wof:placetype":"venue"
},
  "geometry": {"coordinates":[8.5430164337,49.4866142273],"type":"Point"}
}