{
  "type": "Feature",
  "properties": {
    "iso:country":"DE",
    "sg:address":"Rathausplatz 1",
    "sg:city":"Paderborn",
    "sg:phone":"+49 5251/201133",
    "sg:postcode":"33098",
    "sg:province":"Nordrhein-Westfalen",
    "wof:name":"Restaurant Ratskeller",
    "wof:placetype":"venue"
},
  "geometry": {"coordinates":[8.7541208267,51.7174110413],"type":"Point"}
}