{
  "type": "Feature",
  "properties": {
    "iso:country":"DE",
    "sg:address":"In den Steinen 16",
    "sg:city":"Ostfildern",
    "sg:phone":"+49 711/3482461",
    "sg:postcode":"73760",
    "sg:province":"Baden-W\u00fcrttemberg",
    "wof:name":"O. Jeschonnek",
    "wof:placetype":"venue"
},
  "geometry": {"coordinates":[9.293991,48.720093],"type":"Point"}
}