{
  "type": "Feature",
  "properties": {
    "iso:country":"DE",
    "sg:address":"Hildesheimer Str. 67 a",
    "sg:city":"Laatzen",
    "sg:postcode":"30880",
    "sg:province":"Niedersachsen",
    "wof:name":"Gate Ag",
    "wof:placetype":"venue"
},
  "geometry": {"coordinates":[9.7914104462,52.3156585693],"type":"Point"}
}