{
  "type": "Feature",
  "properties": {
    "iso:country":"DE",
    "sg:address":"Hauptstr. 85",
    "sg:city":"Wenden",
    "sg:phone":"+49 2762/1408",
    "sg:postcode":"57482",
    "sg:province":"Nordrhein-Westfalen",
    "wof:name":"Thedor Hochhard",
    "wof:placetype":"venue"
},
  "geometry": {"coordinates":[7.8736200333,50.9692764282],"type":"Point"}
}