{
  "type": "Feature",
  "properties": {
    "iso:country":"DE",
    "sg:address":"bahnhofstr. 44",
    "sg:city":"schweich",
    "sg:phone":"+49 6502/995186",
    "sg:postcode":"54338",
    "sg:province":"Rheinland-Pfalz",
    "wof:name":"Traumhaft Reisen",
    "wof:placetype":"venue"
},
  "geometry": {"coordinates":[6.7477288246,49.8247451782],"type":"Point"}
}