{
  "type": "Feature",
  "properties": {
    "iso:country":"DE",
    "sg:address":"Grasweg 28",
    "sg:city":"Kiel",
    "sg:phone":"+49 431/542006",
    "sg:postcode":"24118",
    "sg:province":"Schleswig-Holstein",
    "wof:name":"Heinrich K. B. Tews",
    "wof:placetype":"venue"
},
  "geometry": {"coordinates":[10.117974,54.337143],"type":"Point"}
}