{
  "type": "Feature",
  "properties": {
    "iso:country":"DE",
    "sg:address":"Marktstr. 10",
    "sg:city":"Mayen",
    "sg:phone":"+49 2651/77357",
    "sg:postcode":"56727",
    "sg:province":"Rheinland-Pfalz",
    "wof:name":"Heinrich Kohlhaas",
    "wof:placetype":"venue"
},
  "geometry": {"coordinates":[7.222837,50.32896],"type":"Point"}
}