{
  "type": "Feature",
  "properties": {
    "iso:country":"DE",
    "sg:address":"Friedrichstr. 3 a",
    "sg:city":"Aschaffenburg",
    "sg:phone":"+49 6021/24734",
    "sg:postcode":"63739",
    "sg:province":"Bayern",
    "wof:name":"Pizzeria Zwiebel",
    "wof:placetype":"venue"
},
  "geometry": {"coordinates":[9.1471128464,49.9766845703],"type":"Point"}
}