{
  "type": "Feature",
  "properties": {
    "iso:country":"DE",
    "sg:address":"Gottschedstr. 2",
    "sg:city":"Leipzig",
    "sg:phone":"+49 341/1260424",
    "sg:postcode":"04109",
    "sg:province":"Sachsen",
    "wof:name":"Zweckverband Kommunale Dv Westsachsen",
    "wof:placetype":"venue"
},
  "geometry": {"coordinates":[12.3707094193,51.3400382996],"type":"Point"}
}