{
  "type": "Feature",
  "properties": {
    "iso:country":"DE",
    "sg:address":"Osterwald 10",
    "sg:city":"Schmallenberg",
    "sg:phone":"+49 2977/1225",
    "sg:postcode":"57392",
    "sg:province":"Nordrhein-Westfalen",
    "wof:name":"Hunau-camping",
    "wof:placetype":"venue"
},
  "geometry": {"coordinates":[8.371674,51.219604],"type":"Point"}
}