{
  "type": "Feature",
  "properties": {
    "iso:country":"DE",
    "sg:address":"Mittlere Bleiche 23",
    "sg:city":"Mainz",
    "sg:phone":"+49 6131/227445",
    "sg:postcode":"55116",
    "sg:province":"Rheinland-Pfalz",
    "wof:name":"Restaurant-pizzeria Ambiente",
    "wof:placetype":"venue"
},
  "geometry": {"coordinates":[8.2647743225,50.0021133423],"type":"Point"}
}