{
  "type": "Feature",
  "properties": {
    "iso:country":"DE",
    "sg:address":"Sudetenstr. 4 u. 6",
    "sg:city":"B\u00fcdingen",
    "sg:phone":"+49 6042/3051",
    "sg:postcode":"63654",
    "sg:province":"Hessen",
    "wof:name":"Hotel Haus Sonnenberg Inh. L. Garbe",
    "wof:placetype":"venue"
},
  "geometry": {"coordinates":[9.1148548126,50.2927780151],"type":"Point"}
}