{
  "type": "Feature",
  "properties": {
    "iso:country":"DE",
    "sg:address":"Panoramaweg 20",
    "sg:city":"Leiwen",
    "sg:postcode":"54340",
    "sg:province":"Rheinland-Pfalz",
    "wof:name":"Herres & Lorth Partnerschaft Steuerberatungs-",
    "wof:placetype":"venue"
},
  "geometry": {"coordinates":[6.8924798965,49.8113288879],"type":"Point"}
}