{
  "type": "Feature",
  "properties": {
    "iso:country":"DE",
    "sg:address":"Podbielskistr. 40",
    "sg:city":"Hannover",
    "sg:phone":"+49 511/620010",
    "sg:postcode":"30177",
    "sg:province":"Niedersachsen",
    "wof:name":"Wohnbau-kirchhorst Gmbh",
    "wof:placetype":"venue"
},
  "geometry": {"coordinates":[9.7561378479,52.3915023804],"type":"Point"}
}