{
  "type": "Feature",
  "properties": {
    "iso:country":"DE",
    "sg:address":"Br\u00f6ckelweg 2",
    "sg:city":"Bienenb\u00fcttel",
    "sg:phone":"+49 5823/249",
    "sg:postcode":"29553",
    "sg:province":"Niedersachsen",
    "wof:name":"Friedhelm Mennerich",
    "wof:placetype":"venue"
},
  "geometry": {"coordinates":[10.533613,53.127094],"type":"Point"}
}