{
  "type": "Feature",
  "properties": {
    "iso:country":"DE",
    "sg:address":"Frankenstr. 11",
    "sg:city":"Steinheim",
    "sg:phone":"+49 5233/3621",
    "sg:postcode":"32839",
    "sg:province":"Nordrhein-Westfalen",
    "wof:name":"Ingo Waldhoff Anlageberater",
    "wof:placetype":"venue"
},
  "geometry": {"coordinates":[9.0864849091,51.8704566956],"type":"Point"}
}