{
  "type": "Feature",
  "properties": {
    "iso:country":"DE",
    "sg:address":"G\u00f6hrener Chaussee",
    "sg:city":"Baabe",
    "sg:postcode":"18586",
    "sg:province":"Mecklenburg-Vorpommern",
    "wof:name":"P. Werner",
    "wof:placetype":"venue"
},
  "geometry": {"coordinates":[13.70506,54.362328],"type":"Point"}
}