{
  "type": "Feature",
  "properties": {
    "iso:country":"DE",
    "sg:address":"Spargelstr. 5",
    "sg:city":"Hannover",
    "sg:phone":"+49 511/8437044",
    "sg:postcode":"30419",
    "sg:province":"Niedersachsen",
    "wof:name":"Gebr. Menge Inh. Manfred Menge",
    "wof:placetype":"venue"
},
  "geometry": {"coordinates":[9.6795549393,52.3943367004],"type":"Point"}
}