{
  "type": "Feature",
  "properties": {
    "iso:country":"DE",
    "sg:address":"Chemnitzer Str. 31",
    "sg:city":"Stollberg",
    "sg:phone":"+49 37296/12274",
    "sg:postcode":"09366",
    "sg:province":"Sachsen",
    "wof:name":"Konrad Heinze",
    "wof:placetype":"venue"
},
  "geometry": {"coordinates":[12.784511,50.715549],"type":"Point"}
}