{
  "type": "Feature",
  "properties": {
    "iso:country":"DE",
    "sg:address":"Am Petersberg 4",
    "sg:city":"Kalbe",
    "sg:phone":"+49 39080/2409",
    "sg:postcode":"39624",
    "sg:province":"Sachsen-Anhalt",
    "wof:name":"Huthmann & Wittrock Gmbh & Co Kg",
    "wof:placetype":"venue"
},
  "geometry": {"coordinates":[11.381007,52.657818],"type":"Point"}
}