{
  "type": "Feature",
  "properties": {
    "iso:country":"DE",
    "sg:address":"Bruchweg 1a",
    "sg:city":"D\u00fclmen",
    "sg:phone":"+49 2594/2829",
    "sg:postcode":"48249",
    "sg:province":"Nordrhein-Westfalen",
    "wof:name":"Willy Messing",
    "wof:placetype":"venue"
},
  "geometry": {"coordinates":[7.2982702255,51.8198509216],"type":"Point"}
}