{
  "type": "Feature",
  "properties": {
    "iso:country":"DE",
    "sg:address":"H\u00f6rder Str. 345",
    "sg:city":"Witten",
    "sg:phone":"+49 2302/47285",
    "sg:postcode":"58454",
    "sg:province":"Nordrhein-Westfalen",
    "wof:name":"Deutsche Shell Ag",
    "wof:placetype":"venue"
},
  "geometry": {"coordinates":[7.3768701553,51.4738311768],"type":"Point"}
}