{
  "type": "Feature",
  "properties": {
    "iso:country":"DE",
    "sg:address":"Am Tollentisch",
    "sg:city":"Geseke",
    "sg:phone":"+49 2942/5595",
    "sg:postcode":"59590",
    "sg:province":"Nordrhein-Westfalen",
    "wof:name":"W. Nolte",
    "wof:placetype":"venue"
},
  "geometry": {"coordinates":[8.5155420303,51.6313552856],"type":"Point"}
}