{
  "type": "Feature",
  "properties": {
    "iso:country":"DE",
    "sg:address":"Emil-M\u00f6rsch-Weg 65",
    "sg:city":"Metzingen",
    "sg:postcode":"72555",
    "sg:province":"Baden-W\u00fcrttemberg",
    "wof:name":"Verein Hauspflege Und Nachbarschaftshilfe",
    "wof:placetype":"venue"
},
  "geometry": {"coordinates":[9.2992544174,48.5379447937],"type":"Point"}
}