{
  "type": "Feature",
  "properties": {
    "iso:country":"DE",
    "sg:address":"Ilkenhansstr. 6",
    "sg:city":"Frankfurt",
    "sg:postcode":"60433",
    "sg:province":"Hessen",
    "wof:name":"Asia-europe Travel Und Trading Gmbh",
    "wof:placetype":"venue"
},
  "geometry": {"coordinates":[8.6643705368,50.1530380249],"type":"Point"}
}