{
  "type": "Feature",
  "properties": {
    "iso:country":"DE",
    "sg:address":"Bollwerkstr. 67",
    "sg:city":"Emden",
    "sg:phone":"+49 4921/20341",
    "sg:postcode":"26725",
    "sg:province":"Niedersachsen",
    "wof:name":"Auffahrt & Sohn Seeschiffahrt-u.",
    "wof:placetype":"venue"
},
  "geometry": {"coordinates":[7.214896,53.369804],"type":"Point"}
}