{
  "type": "Feature",
  "properties": {
    "iso:country":"DE",
    "sg:address":"Nikolaus-Otto-Str.",
    "sg:city":"Mayen",
    "sg:phone":"+49 2651/42025",
    "sg:postcode":"56727",
    "sg:province":"Rheinland-Pfalz",
    "wof:name":"Auto-color-seemann Gmbh",
    "wof:placetype":"venue"
},
  "geometry": {"coordinates":[7.264388,50.333504],"type":"Point"}
}