{
  "type": "Feature",
  "properties": {
    "iso:country":"DE",
    "sg:address":"Iltisstr. 46",
    "sg:city":"Kiel",
    "sg:phone":"+49 431/7396384",
    "sg:postcode":"24143",
    "sg:province":"Schleswig-Holstein",
    "wof:name":"Mittelmeer Antalya Imbiss",
    "wof:placetype":"venue"
},
  "geometry": {"coordinates":[10.1470317841,54.3085441589],"type":"Point"}
}