{
  "type": "Feature",
  "properties": {
    "iso:country":"DE",
    "sg:address":"Wittinger Str. 1A",
    "sg:city":"Hannover",
    "sg:phone":"+49 511/9585147",
    "sg:postcode":"30629",
    "sg:province":"Niedersachsen",
    "wof:name":"Sporthaus G\u00f6sch",
    "wof:placetype":"venue"
},
  "geometry": {"coordinates":[9.8408317566,52.3873634338],"type":"Point"}
}