{
  "type": "Feature",
  "properties": {
    "iso:country":"DE",
    "sg:address":"Backesstr. 12",
    "sg:city":"Hattersheim",
    "sg:postcode":"65795",
    "sg:province":"Hessen",
    "wof:name":"Xxl Gro\u00dfbildtechnik Verwaltungs Gmbh",
    "wof:placetype":"venue"
},
  "geometry": {"coordinates":[8.4724988937,50.0402679443],"type":"Point"}
}