{
  "type": "Feature",
  "properties": {
    "iso:country":"DE",
    "sg:address":"Im Br\u00fchl 76",
    "sg:city":"Lauffen",
    "sg:phone":"+49 7133/974970",
    "sg:postcode":"74348",
    "sg:province":"Baden-W\u00fcrttemberg",
    "wof:name":"Kwk K\u00e4lte W\u00e4rme Klima H. Wurster Gmbh & Co. Kg",
    "wof:placetype":"venue"
},
  "geometry": {"coordinates":[9.1364183426,49.073261261],"type":"Point"}
}