{
  "type": "Feature",
  "properties": {
    "iso:country":"DE",
    "sg:address":"Freiligrathstr. 22",
    "sg:city":"Dorsten",
    "sg:phone":"+49 2362/76111",
    "sg:postcode":"46284",
    "sg:province":"Nordrhein-Westfalen",
    "wof:name":"Cbt B\u00fcroservice Gmbh",
    "wof:placetype":"venue"
},
  "geometry": {"coordinates":[6.991727,51.669994],"type":"Point"}
}