{
  "type": "Feature",
  "properties": {
    "iso:country":"DE",
    "sg:address":"Irmgardstr. 1",
    "sg:city":"M\u00fcnchen",
    "sg:phone":"+49 89/7488660",
    "sg:postcode":"81479",
    "sg:province":"Bayern",
    "wof:name":"Zf Baumanagement Consulting Gmbh",
    "wof:placetype":"venue"
},
  "geometry": {"coordinates":[11.531334,48.080254],"type":"Point"}
}