{
  "type": "Feature",
  "properties": {
    "iso:country":"DE",
    "sg:address":"Mittlerer Hasenpfad 64",
    "sg:city":"Frankfurt",
    "sg:phone":"+49 69/96201816",
    "sg:postcode":"60598",
    "sg:province":"Hessen",
    "wof:name":"Contus Immobilien- Und Beteiligungs Gmbh",
    "wof:placetype":"venue"
},
  "geometry": {"coordinates":[8.6836051941,50.0928115845],"type":"Point"}
}