{
  "type": "Feature",
  "properties": {
    "iso:country":"DE",
    "sg:address":"Laugkfeld 29",
    "sg:city":"Senftenberg",
    "sg:phone":"+49 355/703415",
    "sg:postcode":"01968",
    "sg:province":"Brandenburg",
    "wof:name":"Bsm Sicherheit Gmbh",
    "wof:placetype":"venue"
},
  "geometry": {"coordinates":[14.0127048492,51.527305603],"type":"Point"}
}