{
  "type": "Feature",
  "properties": {
    "iso:country":"DE",
    "sg:address":"Steinfeld 69",
    "sg:city":"Stadelhofen",
    "sg:phone":"+49 9207/259",
    "sg:postcode":"96187",
    "sg:province":"Bayern",
    "wof:name":"Otto H\u00fcbner",
    "wof:placetype":"venue"
},
  "geometry": {"coordinates":[11.166986,49.976944],"type":"Point"}
}