{
  "type": "Feature",
  "properties": {
    "iso:country":"DE",
    "sg:city":"Hamburg",
    "sg:postcode":"20259",
    "sg:province":"Hamburg",
    "wof:name":"Mandala Gallery",
    "wof:placetype":"venue"
},
  "geometry": {"coordinates":[9.95206,53.576054],"type":"Point"}
}