{
  "type": "Feature",
  "properties": {
    "iso:country":"DE",
    "sg:address":"Dr.-Rudolf-Eberle-Str. 38",
    "sg:city":"Albbruck",
    "sg:phone":"+49 8262/96990",
    "sg:postcode":"79774",
    "sg:province":"Baden-W\u00fcrttemberg",
    "wof:name":"Holzprodukte Markt Wald Gmbh",
    "wof:placetype":"venue"
},
  "geometry": {"coordinates":[10.5944890976,48.1490287781],"type":"Point"}
}