{
  "type": "Feature",
  "properties": {
    "iso:country":"DE",
    "sg:address":"Brinkhofstr. 33",
    "sg:city":"Iserlohn",
    "sg:phone":"+49 2374/3396",
    "sg:postcode":"58642",
    "sg:province":"Nordrhein-Westfalen",
    "wof:name":"Hellweg-apotheke",
    "wof:placetype":"venue"
},
  "geometry": {"coordinates":[7.625205,51.368706],"type":"Point"}
}