{
  "type": "Feature",
  "properties": {
    "iso:country":"DE",
    "sg:address":"Herminenstr. 32",
    "sg:city":"B\u00fcckeburg",
    "sg:phone":"+49 5722/4075",
    "sg:postcode":"31675",
    "sg:province":"Niedersachsen",
    "wof:name":"Martens Und Handierk Rechtsanw\u00e4lte",
    "wof:placetype":"venue"
},
  "geometry": {"coordinates":[9.0567378998,52.2558135986],"type":"Point"}
}