{
  "type": "Feature",
  "properties": {
    "iso:country":"DE",
    "sg:address":"Breithornstr. 2",
    "sg:city":"M\u00fcnchen",
    "sg:phone":"+49 89/42018260",
    "sg:postcode":"81825",
    "sg:province":"Bayern",
    "wof:name":"Oliver Pfreimter Rechtsanwalt",
    "wof:placetype":"venue"
},
  "geometry": {"coordinates":[11.6604785919,48.1120491028],"type":"Point"}
}