{
  "type": "Feature",
  "properties": {
    "iso:country":"DE",
    "sg:address":"Dornbachstr. 11",
    "sg:city":"Oberursel",
    "sg:phone":"+49 6171/910559",
    "sg:postcode":"61440",
    "sg:province":"Hessen",
    "wof:name":"Rainer Feix",
    "wof:placetype":"venue"
},
  "geometry": {"coordinates":[8.570888,50.21347],"type":"Point"}
}