{
  "type": "Feature",
  "properties": {
    "iso:country":"DE",
    "sg:address":"Antonstr. 34",
    "sg:city":"Sigmaringen",
    "sg:phone":"+49 7571/12976",
    "sg:postcode":"72488",
    "sg:province":"Baden-W\u00fcrttemberg",
    "wof:name":"Hermann Sch\u00f6n",
    "wof:placetype":"venue"
},
  "geometry": {"coordinates":[9.215073,48.086658],"type":"Point"}
}