{
  "type": "Feature",
  "properties": {
    "iso:country":"DE",
    "sg:address":"Kavalierstr. 15",
    "sg:city":"Berlin",
    "sg:phone":"+49 30/47536742",
    "sg:postcode":"13187",
    "sg:province":"Berlin",
    "wof:name":"Michael Gromnica",
    "wof:placetype":"venue"
},
  "geometry": {"coordinates":[13.410364151,52.5733566284],"type":"Point"}
}