{
  "type": "Feature",
  "properties": {
    "iso:country":"DE",
    "sg:address":"Bernanosweg 8",
    "sg:city":"K\u00f6ln",
    "sg:phone":"+49 221/892117",
    "sg:postcode":"51109",
    "sg:province":"Nordrhein-Westfalen",
    "wof:name":"L\u00e1szl\u00f3 Papp Ingenieur",
    "wof:placetype":"venue"
},
  "geometry": {"coordinates":[7.0590519905,50.9341468811],"type":"Point"}
}