{
  "type": "Feature",
  "properties": {
    "iso:country":"DE",
    "sg:address":"Pariser Str. 21",
    "sg:city":"Berlin",
    "sg:phone":"+49 30/8826757",
    "sg:postcode":"10707",
    "sg:province":"Berlin",
    "wof:name":"Sisyhos Presseb\u00fcro Und Verlag Gmbh",
    "wof:placetype":"venue"
},
  "geometry": {"coordinates":[13.3177957535,52.4985160828],"type":"Point"}
}