{
  "type": "Feature",
  "properties": {
    "iso:country":"DE",
    "sg:address":"Herrmann-Meyer-Str. 20",
    "sg:city":"Leipzig",
    "sg:phone":"+49 341/4217652",
    "sg:postcode":"04207",
    "sg:province":"Sachsen",
    "wof:name":"Dr. Med. Susanne Nordmann",
    "wof:placetype":"venue"
},
  "geometry": {"coordinates":[12.308388,51.313896],"type":"Point"}
}