{
  "type": "Feature",
  "properties": {
    "iso:country":"DE",
    "sg:address":"Kornmarkt 5-7",
    "sg:city":"Nuernberg",
    "sg:phone":"+49 911/241065",
    "sg:postcode":"90402",
    "sg:province":"Bayern",
    "wof:name":"Hbv-franken",
    "wof:placetype":"venue"
},
  "geometry": {"coordinates":[11.0746078491,49.4489860535],"type":"Point"}
}