{
  "type": "Feature",
  "properties": {
    "iso:country":"DE",
    "sg:address":"Austr. 6",
    "sg:city":"Oberursel",
    "sg:phone":"+49 6171/3500",
    "sg:postcode":"61440",
    "sg:province":"Hessen",
    "wof:name":"Wolfgang R\u00f6mmelt Gmbh & Co. Verwaltungs",
    "wof:placetype":"venue"
},
  "geometry": {"coordinates":[8.584211,50.198647],"type":"Point"}
}