{
  "type": "Feature",
  "properties": {
    "iso:country":"DE",
    "sg:address":"Carl-Zei\u00df-Str.4",
    "sg:city":"Stuhr",
    "sg:phone":"+49 4961/735073",
    "sg:postcode":"28816",
    "sg:province":"Niedersachsen",
    "wof:name":"Hemming & Co. Kg",
    "wof:placetype":"venue"
},
  "geometry": {"coordinates":[8.5232982635,50.1762809753],"type":"Point"}
}