{
  "type": "Feature",
  "properties": {
    "iso:country":"DE",
    "sg:address":"Gitschiner Str. 94",
    "sg:city":"Berlin",
    "sg:phone":"+49 30/6165586",
    "sg:postcode":"10969",
    "sg:province":"Berlin",
    "wof:name":"Skilldeal Ag",
    "wof:placetype":"venue"
},
  "geometry": {"coordinates":[13.4005203247,52.4985542297],"type":"Point"}
}