{
  "type": "Feature",
  "properties": {
    "iso:country":"DE",
    "sg:address":"Dankelsbachstr. 1",
    "sg:city":"Pirmasens",
    "sg:phone":"+49 6331/64805",
    "sg:postcode":"66953",
    "sg:province":"Rheinland-Pfalz",
    "wof:name":"Schwarz",
    "wof:placetype":"venue"
},
  "geometry": {"coordinates":[7.604748,49.205112],"type":"Point"}
}