{
  "type": "Feature",
  "properties": {
    "iso:country":"DE",
    "sg:address":"Ackerstr. 1",
    "sg:city":"D\u00fcsseldorf",
    "sg:phone":"+49 211/161857",
    "sg:postcode":"40233",
    "sg:province":"Nordrhein-Westfalen",
    "wof:name":"Sagiroglu Gmbh",
    "wof:placetype":"venue"
},
  "geometry": {"coordinates":[6.7962641716,51.2247924805],"type":"Point"}
}