{
  "type": "Feature",
  "properties": {
    "iso:country":"DE",
    "sg:address":"Maxener Str. 19",
    "sg:city":"Dohna",
    "sg:phone":"+49 3529/511404",
    "sg:postcode":"01809",
    "sg:province":"Sachsen",
    "wof:name":"Matthias Matzka Rechtsanwalt",
    "wof:placetype":"venue"
},
  "geometry": {"coordinates":[13.8691864014,50.9635162354],"type":"Point"}
}