{
  "type": "Feature",
  "properties": {
    "iso:country":"DE",
    "sg:address":"Kleinschwander Str. 20",
    "sg:city":"Vohenstrau\u00df",
    "sg:phone":"+49 9656/890",
    "sg:postcode":"92648",
    "sg:province":"Bayern",
    "wof:name":"Maximilianshof Vermietungs Gmbh",
    "wof:placetype":"venue"
},
  "geometry": {"coordinates":[12.3488769531,49.571521759],"type":"Point"}
}