{
  "type": "Feature",
  "properties": {
    "iso:country":"DE",
    "sg:address":"Untere Hauptstr. 5",
    "sg:city":"Thalheim",
    "sg:phone":"+49 3721/85378",
    "sg:postcode":"09380",
    "sg:province":"Sachsen",
    "wof:name":"Erhard Lohr",
    "wof:placetype":"venue"
},
  "geometry": {"coordinates":[12.8541898727,50.7036247253],"type":"Point"}
}