{
  "type": "Feature",
  "properties": {
    "iso:country":"DE",
    "sg:address":"Hauptstr. 30",
    "sg:city":"B\u00fcdingen",
    "sg:phone":"+49 6041/8347",
    "sg:postcode":"63654",
    "sg:province":"Hessen",
    "wof:name":"E. K\u00f6rner Fotoapparate Und Bedarf",
    "wof:placetype":"venue"
},
  "geometry": {"coordinates":[9.0286331177,50.29347229],"type":"Point"}
}