{
  "type": "Feature",
  "properties": {
    "iso:country":"DE",
    "sg:address":"Am Pichelssee 9",
    "sg:city":"Berlin",
    "sg:phone":"+49 30/3626485",
    "sg:postcode":"13595",
    "sg:province":"Berlin",
    "wof:name":"M\u00f6wert Grundst\u00fccksges. Mbh",
    "wof:placetype":"venue"
},
  "geometry": {"coordinates":[13.1993494034,52.509929657],"type":"Point"}
}