{
  "type": "Feature",
  "properties": {
    "iso:country":"DE",
    "sg:address":"Hofer Str. 10",
    "sg:city":"Regensburg",
    "sg:phone":"+49 941/64040",
    "sg:postcode":"93057",
    "sg:province":"Bayern",
    "wof:name":"G\u00f6tz-service- Verwaltungs- Gmbh",
    "wof:placetype":"venue"
},
  "geometry": {"coordinates":[12.133439064,49.059627533],"type":"Point"}
}