{
  "type": "Feature",
  "properties": {
    "iso:country":"DE",
    "sg:address":"Heegerm\u00fchler Weg 27",
    "sg:city":"Berlin",
    "sg:phone":"+49 30/9167440",
    "sg:postcode":"13158",
    "sg:province":"Berlin",
    "wof:name":"Dr. Med. Lutz Nietsch",
    "wof:placetype":"venue"
},
  "geometry": {"coordinates":[13.374216,52.583981],"type":"Point"}
}