{
  "type": "Feature",
  "properties": {
    "iso:country":"DE",
    "sg:address":"Obere Bergstr. 24",
    "sg:city":"Bullay",
    "sg:phone":"+49 6542/21529",
    "sg:postcode":"56859",
    "sg:province":"Rheinland-Pfalz",
    "wof:name":"Franz Halcour",
    "wof:placetype":"venue"
},
  "geometry": {"coordinates":[7.14712,50.057545],"type":"Point"}
}