{
  "type": "Feature",
  "properties": {
    "iso:country":"DE",
    "sg:address":"Ruiter Str. 2",
    "sg:city":"Bretten",
    "sg:postcode":"75015",
    "sg:province":"Baden-W\u00fcrttemberg",
    "wof:name":"Active Tel Electronic Gmbh",
    "wof:placetype":"venue"
},
  "geometry": {"coordinates":[8.706264,49.031216],"type":"Point"}
}