{
  "type": "Feature",
  "properties": {
    "iso:country":"DE",
    "sg:address":"Gr\u00fcne Twiete 78",
    "sg:city":"Halstenbek",
    "sg:postcode":"25469",
    "sg:province":"Schleswig-Holstein",
    "wof:name":"American Sports Sportartikel Vertriebs- Gmbh",
    "wof:placetype":"venue"
},
  "geometry": {"coordinates":[9.820912,53.623047],"type":"Point"}
}