{
  "type": "Feature",
  "properties": {
    "iso:country":"DE",
    "sg:address":"Meinstr. 9-13",
    "sg:city":"Wolfsburg",
    "sg:phone":"+49 5363/99199",
    "sg:postcode":"38448",
    "sg:province":"Niedersachsen",
    "wof:name":"Behrens Gmbh",
    "wof:placetype":"venue"
},
  "geometry": {"coordinates":[10.839482,52.440292],"type":"Point"}
}