{
  "type": "Feature",
  "properties": {
    "iso:country":"DE",
    "sg:address":"Lilienstr. 4",
    "sg:city":"Stein",
    "sg:phone":"+49 911/6880187",
    "sg:postcode":"90547",
    "sg:province":"Bayern",
    "wof:name":"Ghb Gesellschaft F\u00fcr Hausverwaltung Und",
    "wof:placetype":"venue"
},
  "geometry": {"coordinates":[11.0028934479,49.4138259888],"type":"Point"}
}