{
  "type": "Feature",
  "properties": {
    "iso:country":"DE",
    "sg:address":"Hauptstr. 36",
    "sg:city":"R\u00f6deraue",
    "sg:phone":"+49 35263/3260",
    "sg:postcode":"01609",
    "sg:province":"Sachsen",
    "wof:name":"Modehaus Georg Gmbh",
    "wof:placetype":"venue"
},
  "geometry": {"coordinates":[-71.830437,42.287552],"type":"Point"}
}