{
  "type": "Feature",
  "properties": {
    "iso:country":"DE",
    "sg:address":"M\u00f6nkeburgstr. 27",
    "sg:city":"Burgdorf",
    "sg:phone":"+49 5136/2106",
    "sg:postcode":"31303",
    "sg:province":"Niedersachsen",
    "wof:name":"Hans-georg Raddatz Bauingenieur",
    "wof:placetype":"venue"
},
  "geometry": {"coordinates":[9.997752,52.448997],"type":"Point"}
}