{
  "type": "Feature",
  "properties": {
    "iso:country":"DE",
    "sg:address":"S\u00fcdstr. 19",
    "sg:city":"Wunstorf",
    "sg:phone":"+49 5031/9608080",
    "sg:postcode":"31515",
    "sg:province":"Niedersachsen",
    "wof:name":"Maxicom Computer Und Communication Gmbh",
    "wof:placetype":"venue"
},
  "geometry": {"coordinates":[9.4298763275,52.4249763489],"type":"Point"}
}