{
  "type": "Feature",
  "properties": {
    "iso:country":"DE",
    "sg:address":"Einkaufszentrum Magnet",
    "sg:city":"Gornau",
    "sg:phone":"+49 3725/84953",
    "sg:postcode":"09405",
    "sg:province":"Sachsen",
    "wof:name":"G\u00e4rtnerei- Betriebs- Und Verwaltungs Gmbh",
    "wof:placetype":"venue"
},
  "geometry": {"coordinates":[13.0651,50.74929],"type":"Point"}
}