{
  "type": "Feature",
  "properties": {
    "iso:country":"DE",
    "sg:address":"Vaihinger Markt 24",
    "sg:city":"Stuttgart",
    "sg:postcode":"70563",
    "sg:province":"Baden-W\u00fcrttemberg",
    "wof:name":"Itr Internationale Reisen Gmbh",
    "wof:placetype":"venue"
},
  "geometry": {"coordinates":[9.1109409332,48.73046875],"type":"Point"}
}