{
  "type": "Feature",
  "properties": {
    "iso:country":"DE",
    "sg:address":"Am Hardtbach 29",
    "sg:city":"Alfter",
    "sg:phone":"+49 228/642360",
    "sg:postcode":"53347",
    "sg:province":"Nordrhein-Westfalen",
    "wof:name":"D. K\u00f6hler",
    "wof:placetype":"venue"
},
  "geometry": {"coordinates":[7.020255,50.709373],"type":"Point"}
}