{
  "type": "Feature",
  "properties": {
    "iso:country":"DE",
    "sg:address":"Pfalzring 34",
    "sg:city":"Bobenheim-Roxheim",
    "sg:phone":"+49 6239/929034",
    "sg:postcode":"67240",
    "sg:province":"Rheinland-Pfalz",
    "wof:name":"Reinhold Daubner",
    "wof:placetype":"venue"
},
  "geometry": {"coordinates":[8.3569192886,49.5811882019],"type":"Point"}
}