{
  "type": "Feature",
  "properties": {
    "iso:country":"DE",
    "sg:address":"Cracauer Str. 91",
    "sg:city":"Krefeld",
    "sg:phone":"+49 2151/611884",
    "sg:postcode":"47799",
    "sg:province":"Nordrhein-Westfalen",
    "wof:name":"Kaisers Tengelmann Ag",
    "wof:placetype":"venue"
},
  "geometry": {"coordinates":[6.5745391846,51.3387374878],"type":"Point"}
}