{
  "type": "Feature",
  "properties": {
    "iso:country":"DE",
    "sg:address":"Glockenstr. 24",
    "sg:city":"D\u00fcsseldorf",
    "sg:phone":"+49 211/467695",
    "sg:postcode":"40476",
    "sg:province":"Nordrhein-Westfalen",
    "wof:name":"Kurt K\u00f6ninger",
    "wof:placetype":"venue"
},
  "geometry": {"coordinates":[6.786356926,51.2456245422],"type":"Point"}
}