{
  "type": "Feature",
  "properties": {
    "iso:country":"DE",
    "sg:address":"Mommsenstr. 68",
    "sg:city":"Berlin",
    "sg:phone":"+49 30/8827985",
    "sg:postcode":"10629",
    "sg:province":"Berlin",
    "wof:name":"H. Werder Architekt",
    "wof:placetype":"venue"
},
  "geometry": {"coordinates":[13.319149,52.502831],"type":"Point"}
}