{
  "type": "Feature",
  "properties": {
    "iso:country":"DE",
    "sg:address":"Peter-D\u00f6rfler-Str. 24",
    "sg:city":"Germaringen",
    "sg:phone":"+49 8344/332",
    "sg:postcode":"87656",
    "sg:province":"Bayern",
    "wof:name":"J. Peter",
    "wof:placetype":"venue"
},
  "geometry": {"coordinates":[10.6796483994,47.9361839294],"type":"Point"}
}