{
  "type": "Feature",
  "properties": {
    "iso:country":"DE",
    "sg:address":"Fluderweg 20",
    "sg:city":"Vohenstrau\u00df",
    "sg:phone":"+49 9651/2976",
    "sg:postcode":"92648",
    "sg:province":"Bayern",
    "wof:name":"Joachim Brand",
    "wof:placetype":"venue"
},
  "geometry": {"coordinates":[12.342738,49.625477],"type":"Point"}
}