{
  "type": "Feature",
  "properties": {
    "iso:country":"DE",
    "sg:address":"Neuer Grund 1",
    "sg:city":"Hasel\u00fcnne",
    "sg:phone":"+49 5961/6518",
    "sg:postcode":"49740",
    "sg:province":"Niedersachsen",
    "wof:name":"Rolf Thelen",
    "wof:placetype":"venue"
},
  "geometry": {"coordinates":[7.4854631424,52.6677322388],"type":"Point"}
}