{
  "type": "Feature",
  "properties": {
    "iso:country":"DE",
    "sg:address":"Strassbergerstr. 34",
    "sg:city":"Muenchen",
    "sg:phone":"+49 89/3518848",
    "sg:postcode":"80809",
    "sg:province":"Bayern",
    "wof:name":"Homepage Kumbh-mela-2001",
    "wof:placetype":"venue"
},
  "geometry": {"coordinates":[11.549542,48.185162],"type":"Point"}
}