{
  "type": "Feature",
  "properties": {
    "iso:country":"DE",
    "sg:address":"R\u00f6merstr 64",
    "sg:city":"Michelstadt",
    "sg:phone":"+49 6066/795",
    "sg:postcode":"64720",
    "sg:province":"Hessen",
    "wof:name":"Georg Brohm Gmbh & Co Kg",
    "wof:placetype":"venue"
},
  "geometry": {"coordinates":[9.094581604,49.7218933105],"type":"Point"}
}