{
  "type": "Feature",
  "properties": {
    "iso:country":"DE",
    "sg:address":"Mozartstr. 24",
    "sg:city":"Mellrichstadt",
    "sg:phone":"+49 9776/296",
    "sg:postcode":"97638",
    "sg:province":"Bayern",
    "wof:name":"Wolfgang Weiss",
    "wof:placetype":"venue"
},
  "geometry": {"coordinates":[10.2926702499,50.4236221313],"type":"Point"}
}