{
  "type": "Feature",
  "properties": {
    "iso:country":"DE",
    "sg:address":"Maulbronner Weg 25",
    "sg:city":"Markgr\u00f6ningen",
    "sg:phone":"+49 7145/900023",
    "sg:postcode":"71706",
    "sg:province":"Baden-W\u00fcrttemberg",
    "wof:name":"Ralph Hertfelder",
    "wof:placetype":"venue"
},
  "geometry": {"coordinates":[9.0968551636,48.9032821655],"type":"Point"}
}