{
  "type": "Feature",
  "properties": {
    "iso:country":"DE",
    "sg:address":"Dingelst\u00e4dter Str. 64",
    "sg:city":"Heilbad Heiligenstadt",
    "sg:postcode":"37308",
    "sg:province":"Th\u00fcringen",
    "wof:name":"Kopp & Partner Physiotherapeut Und \u00c4rztin",
    "wof:placetype":"venue"
},
  "geometry": {"coordinates":[10.153437,51.37114],"type":"Point"}
}