{
  "type": "Feature",
  "properties": {
    "iso:country":"DE",
    "sg:address":"Essener Str. 18",
    "sg:city":"Gelsenkirchen",
    "sg:phone":"+49 209/514482",
    "sg:postcode":"45899",
    "sg:province":"Nordrhein-Westfalen",
    "wof:name":"Dm Drogerie-markt Gmbh & Co. Kg",
    "wof:placetype":"venue"
},
  "geometry": {"coordinates":[7.022899,51.538582],"type":"Point"}
}