{
  "type": "Feature",
  "properties": {
    "iso:country":"DE",
    "sg:address":"Goethestr. 6",
    "sg:city":"Lehnin",
    "sg:phone":"+49 3382/700434",
    "sg:postcode":"14797",
    "sg:province":"Brandenburg",
    "wof:name":"J\u00f6rg Ruge Architekt",
    "wof:placetype":"venue"
},
  "geometry": {"coordinates":[12.744646,52.317192],"type":"Point"}
}