{
  "type": "Feature",
  "properties": {
    "iso:country":"DE",
    "sg:address":"Meinbergstr. 85a",
    "sg:city":"Dortmund",
    "sg:phone":"+49 231/437936",
    "sg:postcode":"44269",
    "sg:province":"Nordrhein-Westfalen",
    "wof:name":"Siegfried Urbat",
    "wof:placetype":"venue"
},
  "geometry": {"coordinates":[7.5247559547,51.4891014099],"type":"Point"}
}