{
  "type": "Feature",
  "properties": {
    "iso:country":"DE",
    "sg:address":"Goethestr. 37",
    "sg:city":"Wetter",
    "sg:phone":"+49 6423/7103",
    "sg:postcode":"35083",
    "sg:province":"Hessen",
    "wof:name":"Ivk Industrie-vertretungen Kraus Produkte F. D. Elektro-",
    "wof:placetype":"venue"
},
  "geometry": {"coordinates":[8.7140808105,50.9012184143],"type":"Point"}
}