{
  "type": "Feature",
  "properties": {
    "iso:country":"DE",
    "sg:address":"Kirchrather Str. 141",
    "sg:city":"Herzogenrath",
    "sg:phone":"+49 2406/62343",
    "sg:postcode":"52134",
    "sg:province":"Nordrhein-Westfalen",
    "wof:name":"Lidl Gmbh & Co. Kg",
    "wof:placetype":"venue"
},
  "geometry": {"coordinates":[6.117852211,50.8868255615],"type":"Point"}
}