{
  "type": "Feature",
  "properties": {
    "iso:country":"DE",
    "sg:address":"Hohlstr. 7",
    "sg:city":"Krumbach",
    "sg:phone":"+49 8282/3869",
    "sg:postcode":"86381",
    "sg:province":"Bayern",
    "wof:name":"Xaver Schremmer",
    "wof:placetype":"venue"
},
  "geometry": {"coordinates":[10.3694086075,48.2457542419],"type":"Point"}
}