{
  "type": "Feature",
  "properties": {
    "iso:country":"DE",
    "sg:address":"Wodanstr. 15",
    "sg:city":"N\u00fcrnberg",
    "sg:phone":"+49 911/468882",
    "sg:postcode":"90461",
    "sg:province":"Bayern",
    "wof:name":"Landbierparadies Das Wirtshaus",
    "wof:placetype":"venue"
},
  "geometry": {"coordinates":[11.0934915543,49.4369125366],"type":"Point"}
}