{
  "type": "Feature",
  "properties": {
    "iso:country":"DE",
    "sg:address":"Gonzenheimer Str. 8",
    "sg:city":"Frankfurt",
    "sg:phone":"+49 69/502430",
    "sg:postcode":"60437",
    "sg:province":"Hessen",
    "wof:name":"J\u00fcrgen Nagler Rechtsanwalt",
    "wof:placetype":"venue"
},
  "geometry": {"coordinates":[8.6718397141,50.1836433411],"type":"Point"}
}