{
  "type": "Feature",
  "properties": {
    "iso:country":"DE",
    "sg:address":"Hellenbergstr. 8",
    "sg:city":"Hann. M\u00fcnden",
    "sg:phone":"+49 5541/6399",
    "sg:postcode":"34346",
    "sg:province":"Niedersachsen",
    "wof:name":"Werner R\u00fchl Bau-ing. Und Architekt Bdb",
    "wof:placetype":"venue"
},
  "geometry": {"coordinates":[9.643689,51.414036],"type":"Point"}
}