{
  "type": "Feature",
  "properties": {
    "iso:country":"DE",
    "sg:address":"Saalachstr. 10",
    "sg:city":"Piding",
    "sg:phone":"+49 8651/69821",
    "sg:postcode":"83451",
    "sg:province":"Bayern",
    "wof:name":"Lebenshilfe F\u00fcr Geistig Behinderte Kv.",
    "wof:placetype":"venue"
},
  "geometry": {"coordinates":[12.915635,47.763836],"type":"Point"}
}