{
  "type": "Feature",
  "properties": {
    "iso:country":"DE",
    "sg:address":"Berliner Str. 25",
    "sg:city":"B\u00f6blingen",
    "sg:phone":"+49 7031/222288",
    "sg:postcode":"71034",
    "sg:province":"Baden-W\u00fcrttemberg",
    "wof:name":"China-restaurant Hong Kong",
    "wof:placetype":"venue"
},
  "geometry": {"coordinates":[9.0059204102,48.6806983948],"type":"Point"}
}