{
  "type": "Feature",
  "properties": {
    "iso:country":"DE",
    "sg:address":"Markt 26",
    "sg:city":"H\u00fcckelhoven",
    "sg:phone":"+49 2433/2727",
    "sg:postcode":"41836",
    "sg:province":"Nordrhein-Westfalen",
    "wof:name":"Horst Gruner Mini-car-zentrale",
    "wof:placetype":"venue"
},
  "geometry": {"coordinates":[6.228298,51.053226],"type":"Point"}
}