{
  "type": "Feature",
  "properties": {
    "iso:country":"DE",
    "sg:address":"Drei Schepps 8",
    "sg:city":"Dortmund",
    "sg:phone":"+49 231/770543",
    "sg:postcode":"44227",
    "sg:province":"Nordrhein-Westfalen",
    "wof:name":"Hermann Winter Obst Und Gem\u00fcse",
    "wof:placetype":"venue"
},
  "geometry": {"coordinates":[7.4092178345,51.4581031799],"type":"Point"}
}