{
  "type": "Feature",
  "properties": {
    "iso:country":"DE",
    "sg:address":"Thuner Str. 3",
    "sg:city":"Berlin",
    "sg:phone":"+49 30/8176058",
    "sg:postcode":"12205",
    "sg:province":"Berlin",
    "wof:name":"Andreas Hornfeldt Ingenieur",
    "wof:placetype":"venue"
},
  "geometry": {"coordinates":[13.2961711884,52.4242706299],"type":"Point"}
}