{
  "type": "Feature",
  "properties": {
    "iso:country":"DE",
    "sg:address":"Timmendorf",
    "sg:city":"Insel Poel",
    "sg:phone":"+49 38425/20854",
    "sg:postcode":"23999",
    "sg:province":"Mecklenburg-Vorpommern",
    "wof:name":"Cafe Am Lotsenturm",
    "wof:placetype":"venue"
},
  "geometry": {"coordinates":[11.390295,53.987572],"type":"Point"}
}