{
  "type": "Feature",
  "properties": {
    "iso:country":"DE",
    "sg:address":"S\u00fclfelder Br\u00fccke 3",
    "sg:city":"S\u00fclfeld",
    "sg:phone":"+49 4537/701129",
    "sg:postcode":"23867",
    "sg:province":"Schleswig-Holstein",
    "wof:name":"Iss Individueller Soft-und Hardware-service Gmbh",
    "wof:placetype":"venue"
},
  "geometry": {"coordinates":[10.2399682999,53.7988128662],"type":"Point"}
}