{
  "type": "Feature",
  "properties": {
    "iso:country":"DE",
    "sg:address":"Parkstr. 2",
    "sg:city":"Bad Schwalbach",
    "sg:phone":"+49 6124/12071",
    "sg:postcode":"65307",
    "sg:province":"Hessen",
    "wof:name":"Hotel-kaffeehaus Lutz Gmbh",
    "wof:placetype":"venue"
},
  "geometry": {"coordinates":[8.0627536774,50.1368484497],"type":"Point"}
}