{
  "type": "Feature",
  "properties": {
    "iso:country":"DE",
    "sg:address":"72367",
    "sg:city":"Weilen",
    "sg:postcode":"72367",
    "sg:province":"Baden-W\u00fcrttemberg",
    "wof:name":"Kath. Pfarramt St. Nikolaus",
    "wof:placetype":"venue"
},
  "geometry": {"coordinates":[8.7742500305,48.1882781982],"type":"Point"}
}