{
  "type": "Feature",
  "properties": {
    "iso:country":"DE",
    "sg:address":"Bernhardstr. 105",
    "sg:city":"K\u00f6ln",
    "sg:phone":"+49 221/9349349",
    "sg:postcode":"50968",
    "sg:province":"Nordrhein-Westfalen",
    "wof:name":"Reagil Verwaltungsgesellschaft F\u00fcr Multibiosignaltherapie Mbh",
    "wof:placetype":"venue"
},
  "geometry": {"coordinates":[6.9683580399,50.9091300964],"type":"Point"}
}