{
  "type": "Feature",
  "properties": {
    "iso:country":"DE",
    "sg:address":"Neue Str. 58",
    "sg:city":"Hamburg",
    "sg:phone":"+49 40/772115",
    "sg:postcode":"21073",
    "sg:province":"Hamburg",
    "wof:name":"Altstadt-eiscafe",
    "wof:placetype":"venue"
},
  "geometry": {"coordinates":[9.979331,53.460819],"type":"Point"}
}