{
  "type": "Feature",
  "properties": {
    "iso:country":"DE",
    "sg:address":"Bisamweg 10",
    "sg:city":"Steinhagen",
    "sg:phone":"+49 5204/800626",
    "sg:postcode":"33803",
    "sg:province":"Nordrhein-Westfalen",
    "wof:name":"Cadditec Dreh- Und Konstruktionstechnik Gmbh",
    "wof:placetype":"venue"
},
  "geometry": {"coordinates":[8.4372987747,51.9879417419],"type":"Point"}
}