{
  "type": "Feature",
  "properties": {
    "iso:country":"DE",
    "sg:address":"Bolkerstrasse 44",
    "sg:city":"D\u00fcsseldorf",
    "sg:postcode":"40213",
    "sg:province":"Nordrhein-Westfalen",
    "wof:name":"Rechtsanwalt Helmut Albracht, D\u00fcsseldorf",
    "wof:placetype":"venue"
},
  "geometry": {"coordinates":[6.774843,51.226414],"type":"Point"}
}