{
  "type": "Feature",
  "properties": {
    "iso:country":"DE",
    "sg:address":"Am Anger 12",
    "sg:city":"Altenbach",
    "sg:phone":"+49 3425/811503",
    "sg:postcode":"04828",
    "sg:province":"Sachsen",
    "wof:name":"Wolfgang Klose",
    "wof:placetype":"venue"
},
  "geometry": {"coordinates":[12.6789598465,51.3551216125],"type":"Point"}
}