{
  "type": "Feature",
  "properties": {
    "iso:country":"DE",
    "sg:address":"Kanalstr. 19",
    "sg:city":"Ansbach",
    "sg:phone":"+49 981/94113",
    "sg:postcode":"91522",
    "sg:province":"Bayern",
    "wof:name":"Meyer Hotel- Und Gastst\u00e4tten Gmbh",
    "wof:placetype":"venue"
},
  "geometry": {"coordinates":[10.5707406998,49.2981414795],"type":"Point"}
}