{
  "type": "Feature",
  "properties": {
    "iso:country":"DE",
    "sg:address":"Zunftstr. 8",
    "sg:city":"Buchholz",
    "sg:phone":"+49 4181/283512",
    "sg:postcode":"21244",
    "sg:province":"Niedersachsen",
    "wof:name":"Ensigma Deutschland Ohg",
    "wof:placetype":"venue"
},
  "geometry": {"coordinates":[9.864914,53.34668],"type":"Point"}
}