{
  "type": "Feature",
  "properties": {
    "iso:country":"DE",
    "sg:address":"Johannes-Machern-Str. 33",
    "sg:city":"Hanau",
    "sg:phone":"+49 6181/659661",
    "sg:postcode":"63456",
    "sg:province":"Hessen",
    "wof:name":"Klaus Ellermeier Cnc-werkzeugmaschinen",
    "wof:placetype":"venue"
},
  "geometry": {"coordinates":[8.901801,50.115208],"type":"Point"}
}