{
  "type": "Feature",
  "properties": {
    "iso:country":"DE",
    "sg:address":"L\u00e4rchenweg 11",
    "sg:city":"Erkrath",
    "sg:phone":"+49 2104/40778",
    "sg:postcode":"40699",
    "sg:province":"Nordrhein-Westfalen",
    "wof:name":"Joachim Pawlik Ingenieur",
    "wof:placetype":"venue"
},
  "geometry": {"coordinates":[6.9623708725,51.2141227722],"type":"Point"}
}