{
  "type": "Feature",
  "properties": {
    "iso:country":"DE",
    "sg:address":"Roggemannstr. 13",
    "sg:city":"Oldenburg",
    "sg:phone":"+49 441/72207",
    "sg:postcode":"26122",
    "sg:province":"Niedersachsen",
    "wof:name":"F. J. Von Koenen Heilpraktiker",
    "wof:placetype":"venue"
},
  "geometry": {"coordinates":[8.2078809738,53.1360969543],"type":"Point"}
}