{
  "type": "Feature",
  "properties": {
    "iso:country":"DE",
    "sg:address":"Marktplatz 23",
    "sg:city":"Ortenburg",
    "sg:phone":"+49 8542/91333",
    "sg:postcode":"94496",
    "sg:province":"Bayern",
    "wof:name":"Miedl",
    "wof:placetype":"venue"
},
  "geometry": {"coordinates":[13.223651886,48.5457496643],"type":"Point"}
}