{
  "type": "Feature",
  "properties": {
    "iso:country":"DE",
    "sg:address":"Hauptstr. 33",
    "sg:city":"Olching",
    "sg:phone":"+49 8142/14741",
    "sg:postcode":"82140",
    "sg:province":"Bayern",
    "wof:name":"Hl Hungarian Line Handels Gmbh",
    "wof:placetype":"venue"
},
  "geometry": {"coordinates":[11.3293323517,48.2080116272],"type":"Point"}
}