{
  "type": "Feature",
  "properties": {
    "iso:country":"DE",
    "sg:address":"Seestr. 27",
    "sg:city":"Nonnenhorn",
    "sg:phone":"+49 8382/8602",
    "sg:postcode":"88149",
    "sg:province":"Bayern",
    "wof:name":"M\u00fcnch Handels Gmbh",
    "wof:placetype":"venue"
},
  "geometry": {"coordinates":[9.6089010239,47.5739021301],"type":"Point"}
}