{
  "type": "Feature",
  "properties": {
    "iso:country":"DE",
    "sg:address":"Wilhelmstr. 40a",
    "sg:city":"Diez",
    "sg:phone":"+49 6432/2999",
    "sg:postcode":"65582",
    "sg:province":"Rheinland-Pfalz",
    "wof:name":"Hannelore Wolf Masseurin",
    "wof:placetype":"venue"
},
  "geometry": {"coordinates":[8.012866,50.370758],"type":"Point"}
}