{
  "type": "Feature",
  "properties": {
    "iso:country":"DE",
    "sg:address":"Gro\u00dfe Johannisstr. 15",
    "sg:city":"Hamburg",
    "sg:phone":"+49 40/36090970",
    "sg:postcode":"20457",
    "sg:province":"Hamburg",
    "wof:name":"D. G\u00fcnther",
    "wof:placetype":"venue"
},
  "geometry": {"coordinates":[9.9922370911,53.5492897034],"type":"Point"}
}