{
  "type": "Feature",
  "properties": {
    "iso:country":"DE",
    "sg:address":"Robensstr. 49",
    "sg:city":"Aachen",
    "sg:phone":"+49 241/180250",
    "sg:postcode":"52070",
    "sg:province":"Nordrhein-Westfalen",
    "wof:name":"Deutsches Rotes Kreuz Senioren-zentrum",
    "wof:placetype":"venue"
},
  "geometry": {"coordinates":[6.097661,50.780483],"type":"Point"}
}