{
  "type": "Feature",
  "properties": {
    "iso:country":"DE",
    "sg:address":"Schwanenmarkt 75",
    "sg:city":"Krefeld",
    "sg:phone":"+49 2151/801120",
    "sg:postcode":"47798",
    "sg:province":"Nordrhein-Westfalen",
    "wof:name":"Peter Cleve",
    "wof:placetype":"venue"
},
  "geometry": {"coordinates":[6.562032,51.331596],"type":"Point"}
}