{
  "type": "Feature",
  "properties": {
    "iso:country":"DE",
    "sg:address":"Hoffmannstr. 4",
    "sg:city":"Reutlingen",
    "sg:phone":"+49 7121/5823680",
    "sg:postcode":"72770",
    "sg:province":"Baden-W\u00fcrttemberg",
    "wof:name":"Schwimmhalle Betzingen",
    "wof:placetype":"venue"
},
  "geometry": {"coordinates":[9.1800050735,48.4998779297],"type":"Point"}
}