{
  "type": "Feature",
  "properties": {
    "iso:country":"DE",
    "sg:address":"Im Kornfeld 15",
    "sg:city":"M\u00f6glingen",
    "sg:phone":"+49 7141/482012",
    "sg:postcode":"71696",
    "sg:province":"Baden-W\u00fcrttemberg",
    "wof:name":"Herbert Motz",
    "wof:placetype":"venue"
},
  "geometry": {"coordinates":[9.123792,48.870995],"type":"Point"}
}