{
  "type": "Feature",
  "properties": {
    "iso:country":"DE",
    "sg:address":"Dorfstr. 26",
    "sg:city":"Belgershain",
    "sg:phone":"+49 34293/29739",
    "sg:postcode":"04683",
    "sg:province":"Sachsen",
    "wof:name":"M. Richter",
    "wof:placetype":"venue"
},
  "geometry": {"coordinates":[12.533875,51.257111],"type":"Point"}
}