{
  "type": "Feature",
  "properties": {
    "iso:country":"DE",
    "sg:address":"Oschatzer Str. 21",
    "sg:city":"Dresden",
    "sg:phone":"+49 351/8489562",
    "sg:postcode":"01127",
    "sg:province":"Sachsen",
    "wof:name":"Volker Naumann",
    "wof:placetype":"venue"
},
  "geometry": {"coordinates":[13.7244119644,51.0765266418],"type":"Point"}
}