{
  "type": "Feature",
  "properties": {
    "iso:country":"DE",
    "sg:address":"Dieburger Str. 38",
    "sg:city":"Seeheim-Jugenheim",
    "sg:phone":"+49 6151/592121",
    "sg:postcode":"64342",
    "sg:province":"Hessen",
    "wof:name":"Am Sportplatz",
    "wof:placetype":"venue"
},
  "geometry": {"coordinates":[8.6523399353,49.7936439514],"type":"Point"}
}