{
  "type": "Feature",
  "properties": {
    "iso:country":"DE",
    "sg:address":"An der Pulverm\u00fchle 18 205",
    "sg:city":"K\u00f6ln",
    "sg:postcode":"51105",
    "sg:province":"Nordrhein-Westfalen",
    "wof:name":"G & S K\u00f6lner S\u00fc\u00dfwaren Und Lebensmittel Gmbh",
    "wof:placetype":"venue"
},
  "geometry": {"coordinates":[6.9940361977,50.9338531494],"type":"Point"}
}