{
  "type": "Feature",
  "properties": {
    "iso:country":"DE",
    "sg:address":"Beethovenstr. 8",
    "sg:city":"Bernburg",
    "sg:phone":"+49 3471/370557",
    "sg:postcode":"06406",
    "sg:province":"Sachsen-Anhalt",
    "wof:name":"Sando Gesellschaft F\u00fcr Schl\u00fcsselfertige Bauten Mbh",
    "wof:placetype":"venue"
},
  "geometry": {"coordinates":[11.743403,51.797646],"type":"Point"}
}