{
  "type": "Feature",
  "properties": {
    "iso:country":"DE",
    "sg:address":"Holtbr\u00fcgge 2",
    "sg:city":"Dortmund",
    "sg:phone":"+49 231/464533",
    "sg:postcode":"44265",
    "sg:province":"Nordrhein-Westfalen",
    "wof:name":"D. Kirchhoff",
    "wof:placetype":"venue"
},
  "geometry": {"coordinates":[7.4819550514,51.4700431824],"type":"Point"}
}