{
  "type": "Feature",
  "properties": {
    "iso:country":"DE",
    "sg:address":"Sperlingstr. 6",
    "sg:city":"N\u00fcrnberg",
    "sg:phone":"+49 911/4469302",
    "sg:postcode":"90459",
    "sg:province":"Bayern",
    "wof:name":"Friedewald",
    "wof:placetype":"venue"
},
  "geometry": {"coordinates":[11.077262,49.432461],"type":"Point"}
}