{
  "type": "Feature",
  "properties": {
    "iso:country":"DE",
    "sg:address":"Saselbergweg 48",
    "sg:city":"Hamburg",
    "sg:phone":"+49 40/6024692",
    "sg:postcode":"22395",
    "sg:province":"Hamburg",
    "wof:name":"Manfred K\u00fchnast Ingenieur",
    "wof:placetype":"venue"
},
  "geometry": {"coordinates":[10.0975751877,53.6631889343],"type":"Point"}
}