{
  "type": "Feature",
  "properties": {
    "iso:country":"DE",
    "sg:address":"Krautbergstr. 8",
    "sg:city":"Crailsheim",
    "sg:phone":"+49 7951/8476",
    "sg:postcode":"74564",
    "sg:province":"Baden-W\u00fcrttemberg",
    "wof:name":"E. Kochend\u00f6rfer",
    "wof:placetype":"venue"
},
  "geometry": {"coordinates":[10.1111268997,49.1167526245],"type":"Point"}
}