{
  "type": "Feature",
  "properties": {
    "iso:country":"DE",
    "sg:address":"Ritterstr. 3",
    "sg:city":"Hasel\u00fcnne",
    "sg:postcode":"49740",
    "sg:province":"Niedersachsen",
    "wof:name":"Tonstudio Paul Berentzen Beteiligungs Gmbh",
    "wof:placetype":"venue"
},
  "geometry": {"coordinates":[7.48541,52.6744],"type":"Point"}
}