{
  "type": "Feature",
  "properties": {
    "iso:country":"DE",
    "sg:address":"Kemnath 32",
    "sg:city":"Schnaittenbach",
    "sg:phone":"+49 9604/2267",
    "sg:postcode":"92253",
    "sg:province":"Bayern",
    "wof:name":"Helmut Piehler",
    "wof:placetype":"venue"
},
  "geometry": {"coordinates":[12.001429,49.547844],"type":"Point"}
}