{
  "type": "Feature",
  "properties": {
    "iso:country":"DE",
    "sg:address":"Am Denkmal 26",
    "sg:city":"Bad M\u00fcnder",
    "sg:phone":"+49 5042/1060",
    "sg:postcode":"31848",
    "sg:province":"Niedersachsen",
    "wof:name":"Kurt Heims",
    "wof:placetype":"venue"
},
  "geometry": {"coordinates":[9.427014,52.212784],"type":"Point"}
}