{
  "type": "Feature",
  "properties": {
    "iso:country":"DE",
    "sg:address":"Stra\u00dfe der Volkssolidarit\u00e4t 63",
    "sg:city":"Sangerhausen",
    "sg:phone":"+49 3464/567131",
    "sg:postcode":"06526",
    "sg:province":"Sachsen-Anhalt",
    "wof:name":"Kneisel Und Huber Rechtsanw\u00e4lte",
    "wof:placetype":"venue"
},
  "geometry": {"coordinates":[11.2879934311,51.4613990784],"type":"Point"}
}