{
  "type": "Feature",
  "properties": {
    "iso:country":"DE",
    "sg:address":"In der Marsch 13 B",
    "sg:city":"L\u00fcneburg",
    "sg:phone":"+49 4131/31643",
    "sg:postcode":"21339",
    "sg:province":"Niedersachsen",
    "wof:name":"Herbert Koops",
    "wof:placetype":"venue"
},
  "geometry": {"coordinates":[10.41394,53.272911],"type":"Point"}
}