{
  "type": "Feature",
  "properties": {
    "iso:country":"DE",
    "sg:address":"Am Wieh 4",
    "sg:city":"Harsefeld",
    "sg:phone":"+49 4164/89800",
    "sg:postcode":"21698",
    "sg:province":"Niedersachsen",
    "wof:name":"Reese Reisen Gmbh",
    "wof:placetype":"venue"
},
  "geometry": {"coordinates":[9.4938087463,53.451423645],"type":"Point"}
}