{
  "type": "Feature",
  "properties": {
    "iso:country":"DE",
    "sg:address":"Postfach 1362:: 67803 Rockenhausen:: Germany.^^Kreuznacher Str 27::",
    "sg:city":"Rockenhausen",
    "sg:phone":"+49 6361/92460",
    "sg:postcode":"67806",
    "sg:province":"Rheinland-Pfalz",
    "wof:name":"Vr-bank Nordwestpfalz Eg",
    "wof:placetype":"venue"
},
  "geometry": {"coordinates":[7.815121,49.629913],"type":"Point"}
}