{
  "type": "Feature",
  "properties": {
    "iso:country":"DE",
    "sg:address":"Wefelsestr. 16",
    "sg:city":"Hannover",
    "sg:phone":"+49 511/795916",
    "sg:postcode":"30419",
    "sg:province":"Niedersachsen",
    "wof:name":"Kleinwohnungsgesellschaft Herrenhausen Mbh",
    "wof:placetype":"venue"
},
  "geometry": {"coordinates":[9.6800746918,52.3921432495],"type":"Point"}
}