{
  "type": "Feature",
  "properties": {
    "iso:country":"DE",
    "sg:address":"Im Schanzacker 9",
    "sg:city":"Ehrenkirchen",
    "sg:phone":"+49 7664/6544",
    "sg:postcode":"79238",
    "sg:province":"Baden-W\u00fcrttemberg",
    "wof:name":"Flaig & Kohler",
    "wof:placetype":"venue"
},
  "geometry": {"coordinates":[7.736410141,47.9455909729],"type":"Point"}
}