{
  "type": "Feature",
  "properties": {
    "iso:country":"DE",
    "sg:address":"Eichenm\u00fchleweg 9",
    "sg:city":"Friedrichshafen",
    "sg:phone":"+49 7541/42398",
    "sg:postcode":"88048",
    "sg:province":"Baden-W\u00fcrttemberg",
    "wof:name":"Karl Kekeisen",
    "wof:placetype":"venue"
},
  "geometry": {"coordinates":[9.41038,47.674911],"type":"Point"}
}