{
  "type": "Feature",
  "properties": {
    "iso:country":"DE",
    "sg:address":"Klingeler Weg 3",
    "sg:city":"Borgentreich",
    "sg:phone":"+49 5645/209",
    "sg:postcode":"34434",
    "sg:province":"Nordrhein-Westfalen",
    "wof:name":"Scheideler Verwaltungs Gmbh",
    "wof:placetype":"venue"
},
  "geometry": {"coordinates":[9.260089,51.625065],"type":"Point"}
}