{
  "type": "Feature",
  "properties": {
    "iso:country":"DE",
    "sg:address":"Waldstr. 43b",
    "sg:city":"Stuhr",
    "sg:phone":"+49 4206/7987",
    "sg:postcode":"28816",
    "sg:province":"Niedersachsen",
    "wof:name":"Karin Urbanek",
    "wof:placetype":"venue"
},
  "geometry": {"coordinates":[8.703913,52.956425],"type":"Point"}
}