{
  "type": "Feature",
  "properties": {
    "iso:country":"DE",
    "sg:address":"F-Jos-Baumgartner-Str 58",
    "sg:city":"Emmendingen",
    "sg:phone":"+49 7641/5840",
    "sg:postcode":"79312",
    "sg:province":"Baden-W\u00fcrttemberg",
    "wof:name":"Ramie-seiler Ag",
    "wof:placetype":"venue"
},
  "geometry": {"coordinates":[7.858230114,48.1149597168],"type":"Point"}
}