{
  "type": "Feature",
  "properties": {
    "iso:country":"DE",
    "sg:address":"Bergstr. 1",
    "sg:city":"Hallerndorf",
    "sg:phone":"+49 9545/70607",
    "sg:postcode":"91352",
    "sg:province":"Bayern",
    "wof:name":"Georg Nagengast",
    "wof:placetype":"venue"
},
  "geometry": {"coordinates":[10.999629,49.773643],"type":"Point"}
}