{
  "type": "Feature",
  "properties": {
    "iso:country":"DE",
    "sg:address":"Lindenstr. 28",
    "sg:city":"Obernburg",
    "sg:phone":"+49 6022/1237",
    "sg:postcode":"63785",
    "sg:province":"Bayern",
    "wof:name":"Weimer Klemm & Co. Gmbh",
    "wof:placetype":"venue"
},
  "geometry": {"coordinates":[9.147423,49.843407],"type":"Point"}
}