{
  "type": "Feature",
  "properties": {
    "iso:country":"DE",
    "sg:address":"Krefelder Str. 5",
    "sg:city":"Dormagen",
    "sg:phone":"+49 2133/214150",
    "sg:postcode":"41539",
    "sg:province":"Nordrhein-Westfalen",
    "wof:name":"Regina Hunger",
    "wof:placetype":"venue"
},
  "geometry": {"coordinates":[6.838915,51.096722],"type":"Point"}
}