{
  "type": "Feature",
  "properties": {
    "iso:country":"DE",
    "sg:address":"Mieler Str. 34",
    "sg:city":"Rheinbach",
    "sg:phone":"+49 2226/8455",
    "sg:postcode":"53359",
    "sg:province":"Nordrhein-Westfalen",
    "wof:name":"Erich Henschke Dochtfabrikations Gmbh",
    "wof:placetype":"venue"
},
  "geometry": {"coordinates":[6.9523859024,50.6258163452],"type":"Point"}
}