{
  "type": "Feature",
  "properties": {
    "iso:country":"DE",
    "sg:address":"Pohlitzer Str. 60",
    "sg:city":"Gera",
    "sg:postcode":"07552",
    "sg:province":"Th\u00fcringen",
    "wof:name":"R & T Couture Rupp & Taureck Gmbh",
    "wof:placetype":"venue"
},
  "geometry": {"coordinates":[12.03796,50.922058],"type":"Point"}
}