{
  "type": "Feature",
  "properties": {
    "iso:country":"DE",
    "sg:address":"Lippacherstr. 27",
    "sg:city":"Bayreuth",
    "sg:phone":"+49 921/46774",
    "sg:postcode":"95445",
    "sg:province":"Bayern",
    "wof:name":"Thomas Holzm\u00fcller Architekt",
    "wof:placetype":"venue"
},
  "geometry": {"coordinates":[11.558098,49.94561],"type":"Point"}
}