{
  "type": "Feature",
  "properties": {
    "iso:country":"DE",
    "sg:address":"Hauptstr. 38",
    "sg:city":"Mauderode",
    "sg:phone":"+49 36332/20257",
    "sg:postcode":"99735",
    "sg:province":"Th\u00fcringen",
    "wof:name":"Agrar Gmbh",
    "wof:placetype":"venue"
},
  "geometry": {"coordinates":[10.740726,51.483124],"type":"Point"}
}