{
  "type": "Feature",
  "properties": {
    "iso:country":"DE",
    "sg:address":"Porschestr. 16",
    "sg:city":"Hildesheim",
    "sg:phone":"+49 4957/3129239",
    "sg:postcode":"31135",
    "sg:province":"Niedersachsen",
    "wof:name":"Mahnotyp Formularverlag D\u00d6rrie Gmbh",
    "wof:placetype":"venue"
},
  "geometry": {"coordinates":[8.7895393372,52.2141304016],"type":"Point"}
}