{
  "type": "Feature",
  "properties": {
    "iso:country":"DE",
    "sg:address":"Wiesenstr. 5",
    "sg:city":"Greiz",
    "sg:postcode":"07973",
    "sg:province":"Th\u00fcringen",
    "wof:name":"A. Siegel",
    "wof:placetype":"venue"
},
  "geometry": {"coordinates":[12.19661,50.648537],"type":"Point"}
}