{
  "type": "Feature",
  "properties": {
    "iso:country":"DE",
    "sg:address":"Eiderstr. 15",
    "sg:city":"Bissee",
    "sg:phone":"+49 4322/2500",
    "sg:postcode":"24582",
    "sg:province":"Schleswig-Holstein",
    "wof:name":"Antik-hof Bissee Inh. Renate Stamer",
    "wof:placetype":"venue"
},
  "geometry": {"coordinates":[10.112088,54.190556],"type":"Point"}
}