{
  "type": "Feature",
  "properties": {
    "iso:country":"DE",
    "sg:address":"Schulstr. 7",
    "sg:city":"Landscheid",
    "sg:phone":"+49 6575/4219",
    "sg:postcode":"54526",
    "sg:province":"Rheinland-Pfalz",
    "wof:name":"W. Bayer Haushaltswaren",
    "wof:placetype":"venue"
},
  "geometry": {"coordinates":[6.7675561905,49.9848709106],"type":"Point"}
}