{
  "type": "Feature",
  "properties": {
    "iso:country":"DE",
    "sg:address":"Werkstr. 6",
    "sg:city":"Saal",
    "sg:phone":"+49 9441/68760",
    "sg:postcode":"93342",
    "sg:province":"Bayern",
    "wof:name":"Rewo-druck Gmbh",
    "wof:placetype":"venue"
},
  "geometry": {"coordinates":[11.929213,48.897305],"type":"Point"}
}