{
  "type": "Feature",
  "properties": {
    "iso:country":"DE",
    "sg:address":"Am Oberfeld 15",
    "sg:city":"Krefeld",
    "sg:phone":"+49 2151/43669",
    "sg:postcode":"47829",
    "sg:province":"Nordrhein-Westfalen",
    "wof:name":"Helmut Reintges",
    "wof:placetype":"venue"
},
  "geometry": {"coordinates":[6.6505360603,51.3500137329],"type":"Point"}
}