{
  "type": "Feature",
  "properties": {
    "iso:country":"DE",
    "sg:address":"Silbersteinstr. 64",
    "sg:city":"Berlin",
    "sg:postcode":"12051",
    "sg:province":"Berlin",
    "wof:name":"Pappas Transport Gmbh",
    "wof:placetype":"venue"
},
  "geometry": {"coordinates":[13.432437,52.46661],"type":"Point"}
}