{
  "type": "Feature",
  "properties": {
    "iso:country":"DE",
    "sg:address":"Euskirchener Str. 25",
    "sg:city":"Bonn",
    "sg:phone":"+49 228/625050",
    "sg:postcode":"53121",
    "sg:province":"Nordrhein-Westfalen",
    "wof:name":"A. Linzbach Heissmangel",
    "wof:placetype":"venue"
},
  "geometry": {"coordinates":[7.0680232048,50.724319458],"type":"Point"}
}