{
  "type": "Feature",
  "properties": {
    "iso:country":"DE",
    "sg:address":"Bahnhofstr. 16",
    "sg:city":"Straubing",
    "sg:phone":"+49 9421/80675",
    "sg:postcode":"94315",
    "sg:province":"Bayern",
    "wof:name":"Agnes Bernauer Apotheke Klaus Distler E. K.",
    "wof:placetype":"venue"
},
  "geometry": {"coordinates":[12.570553,48.879246],"type":"Point"}
}