{
  "type": "Feature",
  "properties": {
    "iso:country":"DE",
    "sg:address":"Dahlienweg 6",
    "sg:city":"Sinzig",
    "sg:phone":"+49 2642/43835",
    "sg:postcode":"53489",
    "sg:province":"Rheinland-Pfalz",
    "wof:name":"Hans-josef Sch\u00e4fer",
    "wof:placetype":"venue"
},
  "geometry": {"coordinates":[7.215197,50.547993],"type":"Point"}
}