{
  "type": "Feature",
  "properties": {
    "iso:country":"DE",
    "sg:address":"Kantstr. 66a",
    "sg:city":"Berlin",
    "sg:phone":"+49 30/3235668",
    "sg:postcode":"10627",
    "sg:province":"Berlin",
    "wof:name":"Arian Handels Gmbh",
    "wof:placetype":"venue"
},
  "geometry": {"coordinates":[13.3032264709,52.5069732666],"type":"Point"}
}