{
  "type": "Feature",
  "properties": {
    "iso:country":"DE",
    "sg:address":"Auf der Heide 1",
    "sg:city":"Aachen",
    "sg:phone":"+49 2408/3293",
    "sg:postcode":"52076",
    "sg:province":"Nordrhein-Westfalen",
    "wof:name":"B. Hammers",
    "wof:placetype":"venue"
},
  "geometry": {"coordinates":[6.155684948,50.7192344666],"type":"Point"}
}