{
  "type": "Feature",
  "properties": {
    "iso:country":"DE",
    "sg:address":"Niederstr. 98",
    "sg:city":"Grefrath",
    "sg:phone":"+49 2842/3249",
    "sg:postcode":"47929",
    "sg:province":"Nordrhein-Westfalen",
    "wof:name":"J. Pooth",
    "wof:placetype":"venue"
},
  "geometry": {"coordinates":[6.3812398911,51.3179092407],"type":"Point"}
}