{
  "type": "Feature",
  "properties": {
    "iso:country":"DE",
    "sg:address":"Meisenweg 8",
    "sg:city":"M\u00f6hrendorf",
    "sg:phone":"+49 9131/43269",
    "sg:postcode":"91096",
    "sg:province":"Bayern",
    "wof:name":"Josef Dilk",
    "wof:placetype":"venue"
},
  "geometry": {"coordinates":[10.9942913055,49.6335411072],"type":"Point"}
}