{
  "type": "Feature",
  "properties": {
    "iso:country":"DE",
    "sg:address":"Irenenstr. 12",
    "sg:city":"Darmstadt",
    "sg:phone":"+49 6151/292365",
    "sg:postcode":"64293",
    "sg:province":"Hessen",
    "wof:name":"Achim Stelz Architekt",
    "wof:placetype":"venue"
},
  "geometry": {"coordinates":[8.64975,49.882843],"type":"Point"}
}