{
  "type": "Feature",
  "properties": {
    "iso:country":"DE",
    "sg:address":"Am Vogelsang 18",
    "sg:city":"Burbach",
    "sg:phone":"+49 2736/491610",
    "sg:postcode":"57299",
    "sg:province":"Nordrhein-Westfalen",
    "wof:name":"Cofid Stahl-handelsges. Mbh",
    "wof:placetype":"venue"
},
  "geometry": {"coordinates":[8.0731992722,50.746925354],"type":"Point"}
}