{
  "type": "Feature",
  "properties": {
    "iso:country":"DE",
    "sg:address":"Friedrichstr. 21",
    "sg:city":"Langenselbold",
    "sg:phone":"+49 6184/92420",
    "sg:postcode":"63505",
    "sg:province":"Hessen",
    "wof:name":"Dkv Generalagentur Ritter & Partner",
    "wof:placetype":"venue"
},
  "geometry": {"coordinates":[9.044377327,50.177532196],"type":"Point"}
}