{
  "type": "Feature",
  "properties": {
    "iso:country":"DE",
    "sg:address":"Bildstr. 1",
    "sg:city":"Elsenfeld",
    "sg:phone":"+49 6022/4081",
    "sg:postcode":"63820",
    "sg:province":"Bayern",
    "wof:name":"Adam Zirkel Gmbh & Co. Kg",
    "wof:placetype":"venue"
},
  "geometry": {"coordinates":[9.1566076279,49.8394737244],"type":"Point"}
}