{
  "type": "Feature",
  "properties": {
    "iso:country":"DE",
    "sg:address":"Worphauser Landstr. 31",
    "sg:city":"Lilienthal",
    "sg:phone":"+49 4208/2405",
    "sg:postcode":"28865",
    "sg:province":"Niedersachsen",
    "wof:name":"Fr. Rohdenburg",
    "wof:placetype":"venue"
},
  "geometry": {"coordinates":[8.9126901627,53.1532516479],"type":"Point"}
}