{
  "type": "Feature",
  "properties": {
    "iso:country":"DE",
    "sg:address":"Gartenstr. 14",
    "sg:city":"Rehau",
    "sg:phone":"+49 9283/2508",
    "sg:postcode":"95111",
    "sg:province":"Bayern",
    "wof:name":"Garten-johann Handels Gmbh",
    "wof:placetype":"venue"
},
  "geometry": {"coordinates":[12.0341911316,50.2474784851],"type":"Point"}
}