{
  "type": "Feature",
  "properties": {
    "iso:country":"DE",
    "sg:address":"Im L\u00f6wental 15",
    "sg:city":"Essen",
    "sg:phone":"+49 201/494077",
    "sg:postcode":"45239",
    "sg:province":"Nordrhein-Westfalen",
    "wof:name":"S & H Gastst\u00e4ttenbetriebs Gmbh",
    "wof:placetype":"venue"
},
  "geometry": {"coordinates":[6.9976081848,51.384967804],"type":"Point"}
}