{
  "type": "Feature",
  "properties": {
    "iso:country":"DE",
    "sg:address":"Heynestr. 6",
    "sg:city":"N\u00fcrnberg",
    "sg:phone":"+49 911/412289",
    "sg:postcode":"90443",
    "sg:province":"Bayern",
    "wof:name":"Walter Fett Bauschlosserei",
    "wof:placetype":"venue"
},
  "geometry": {"coordinates":[11.072515,49.440853],"type":"Point"}
}