{
  "type": "Feature",
  "properties": {
    "iso:country":"DE",
    "sg:address":"Edelwei\u00dfstr. 20",
    "sg:city":"Berlin",
    "sg:phone":"+49 30/94113690",
    "sg:postcode":"13158",
    "sg:province":"Berlin",
    "wof:name":"B & W Kassen +computersysteme Gmbh",
    "wof:placetype":"venue"
},
  "geometry": {"coordinates":[13.373728,52.585529],"type":"Point"}
}