{
  "type": "Feature",
  "properties": {
    "iso:country":"DE",
    "sg:address":"R\u00f6schm\u00fchlweg 2",
    "sg:city":"Pegnitz",
    "sg:phone":"+49 9241/2103",
    "sg:postcode":"91257",
    "sg:province":"Bayern",
    "wof:name":"J\u00fcrgen Rupprecht",
    "wof:placetype":"venue"
},
  "geometry": {"coordinates":[11.544131,49.75581],"type":"Point"}
}