{
  "type": "Feature",
  "properties": {
    "iso:country":"DE",
    "sg:address":"Merianstr. 9",
    "sg:city":"Bad Schwalbach",
    "sg:phone":"+49 6124/7030",
    "sg:postcode":"65307",
    "sg:province":"Hessen",
    "wof:name":"Kreisaltenzentrum",
    "wof:placetype":"venue"
},
  "geometry": {"coordinates":[8.06157,50.136742],"type":"Point"}
}