{
  "type": "Feature",
  "properties": {
    "iso:country":"DE",
    "sg:address":"Alt-Moabit 73",
    "sg:city":"Berlin",
    "sg:phone":"+49 30/399980",
    "sg:postcode":"10555",
    "sg:province":"Berlin",
    "wof:name":"Bbj Consult E. V. Gesch\u00e4fsstelle",
    "wof:placetype":"venue"
},
  "geometry": {"coordinates":[13.3327417374,52.5241508484],"type":"Point"}
}