{
  "type": "Feature",
  "properties": {
    "iso:country":"DE",
    "sg:address":"Neulandstr. 5",
    "sg:city":"Biblis",
    "sg:phone":"+49 6245/905773",
    "sg:postcode":"68647",
    "sg:province":"Hessen",
    "wof:name":"W. Karg",
    "wof:placetype":"venue"
},
  "geometry": {"coordinates":[8.390401,49.683342],"type":"Point"}
}