{
  "type": "Feature",
  "properties": {
    "iso:country":"DE",
    "sg:address":"Alpenstr. 3",
    "sg:city":"Memmingen",
    "sg:phone":"+49 8331/2831",
    "sg:postcode":"87700",
    "sg:province":"Bayern",
    "wof:name":"Michael Honold Raumausstattung Bodenbel\u00e4ge",
    "wof:placetype":"venue"
},
  "geometry": {"coordinates":[10.1900968552,47.9777297974],"type":"Point"}
}