{
  "type": "Feature",
  "properties": {
    "iso:country":"DE",
    "sg:address":"Am Engelsholz 15",
    "sg:city":"Saara",
    "sg:phone":"+49 36604/81488",
    "sg:postcode":"07589",
    "sg:province":"Th\u00fcringen",
    "wof:name":"Matthias Lehmann",
    "wof:placetype":"venue"
},
  "geometry": {"coordinates":[11.9631557465,50.8551101685],"type":"Point"}
}