{
  "type": "Feature",
  "properties": {
    "iso:country":"DE",
    "sg:address":"Brookstr. 23",
    "sg:city":"Ochtrup",
    "sg:postcode":"48607",
    "sg:province":"Nordrhein-Westfalen",
    "wof:name":"Br\u00f6ker Verwaltungs-gmbh",
    "wof:placetype":"venue"
},
  "geometry": {"coordinates":[7.1913809776,52.204208374],"type":"Point"}
}