{
  "type": "Feature",
  "properties": {
    "iso:country":"DE",
    "sg:address":"Unterer Siedlerweg 2",
    "sg:city":"Hohendubrau",
    "sg:phone":"+49 35876/951",
    "sg:postcode":"02906",
    "sg:province":"Sachsen",
    "wof:name":"Landfleischerei Gebelzig Gmbh",
    "wof:placetype":"venue"
},
  "geometry": {"coordinates":[14.6690816879,51.2214279175],"type":"Point"}
}