{
  "type": "Feature",
  "properties": {
    "iso:country":"DE",
    "sg:address":"Lichtenbergstr. 4",
    "sg:city":"Asperg",
    "sg:phone":"+49 7141/36335",
    "sg:postcode":"71679",
    "sg:province":"Baden-W\u00fcrttemberg",
    "wof:name":"Christoph Pfeund Ingenieur",
    "wof:placetype":"venue"
},
  "geometry": {"coordinates":[9.1489019394,48.9092597961],"type":"Point"}
}