{
  "type": "Feature",
  "properties": {
    "iso:country":"DE",
    "sg:address":"Blumenstr. 97",
    "sg:city":"G\u00f6ppingen",
    "sg:phone":"+49 7161/73391",
    "sg:postcode":"73033",
    "sg:province":"Baden-W\u00fcrttemberg",
    "wof:name":"H. Und S. Sp\u00e4th",
    "wof:placetype":"venue"
},
  "geometry": {"coordinates":[9.668488,48.708664],"type":"Point"}
}