{
  "type": "Feature",
  "properties": {
    "iso:country":"DE",
    "sg:address":"Rathausplatz 27",
    "sg:city":"Voerde",
    "sg:phone":"+49 2855/7075",
    "sg:postcode":"46562",
    "sg:province":"Nordrhein-Westfalen",
    "wof:name":"St. Martin-apotheke",
    "wof:placetype":"venue"
},
  "geometry": {"coordinates":[6.68258,51.59803],"type":"Point"}
}