{
  "type": "Feature",
  "properties": {
    "iso:country":"DE",
    "sg:address":"Schiffstr. 14",
    "sg:city":"Erlangen",
    "sg:phone":"+49 9131/28527",
    "sg:postcode":"91054",
    "sg:province":"Bayern",
    "wof:name":"Bruno Trattoria",
    "wof:placetype":"venue"
},
  "geometry": {"coordinates":[11.0042238235,49.6003837585],"type":"Point"}
}