{
  "type": "Feature",
  "properties": {
    "iso:country":"DE",
    "sg:address":"Heckerheide 17",
    "sg:city":"Marienfeld",
    "sg:phone":"+49 5247/984555",
    "sg:postcode":"33428",
    "sg:province":"Nordrhein-Westfalen",
    "wof:name":"Rolf Schnitker",
    "wof:placetype":"venue"
},
  "geometry": {"coordinates":[8.226673,51.96254],"type":"Point"}
}