{
  "type": "Feature",
  "properties": {
    "iso:country":"DE",
    "sg:address":"Aachener Str. 63-65",
    "sg:city":"K\u00f6ln",
    "sg:postcode":"50674",
    "sg:province":"Nordrhein-Westfalen",
    "wof:name":"Peter Schlax Gmbh",
    "wof:placetype":"venue"
},
  "geometry": {"coordinates":[6.9317498207,50.9363670349],"type":"Point"}
}