{
  "type": "Feature",
  "properties": {
    "iso:country":"DE",
    "sg:address":"Smetanastr. 30",
    "sg:city":"Marl",
    "sg:phone":"+49 2365/84088",
    "sg:postcode":"45772",
    "sg:province":"Nordrhein-Westfalen",
    "wof:name":"Rainer Krause",
    "wof:placetype":"venue"
},
  "geometry": {"coordinates":[7.150815,51.656029],"type":"Point"}
}