{
  "type": "Feature",
  "properties": {
    "iso:country":"DE",
    "sg:address":"Sternberger Str. 18",
    "sg:city":"Extertal",
    "sg:phone":"+49 5262/3512",
    "sg:postcode":"32699",
    "sg:province":"Nordrhein-Westfalen",
    "wof:name":"Fritz Brand",
    "wof:placetype":"venue"
},
  "geometry": {"coordinates":[9.082376,52.06562],"type":"Point"}
}