{
  "type": "Feature",
  "properties": {
    "iso:country":"DE",
    "sg:address":"Waidstr. 16",
    "sg:city":"M\u00fchlhausen",
    "sg:phone":"+49 36014/22827",
    "sg:postcode":"99974",
    "sg:province":"Th\u00fcringen",
    "wof:name":"Heyers Gastst\u00e4tte",
    "wof:placetype":"venue"
},
  "geometry": {"coordinates":[10.4680461884,51.2084274292],"type":"Point"}
}