{
  "type": "Feature",
  "properties": {
    "iso:country":"DE",
    "sg:address":"Schachtweg 1",
    "sg:city":"Hain",
    "sg:phone":"+49 36334/50551",
    "sg:postcode":"99735",
    "sg:province":"Th\u00fcringen",
    "wof:name":"Ingo Franke Gmbh",
    "wof:placetype":"venue"
},
  "geometry": {"coordinates":[10.7713403702,51.4342918396],"type":"Point"}
}