{
  "type": "Feature",
  "properties": {
    "iso:country":"DE",
    "sg:address":"Foltzring 52",
    "sg:city":"Frankenthal",
    "sg:phone":"+49 6233/61084",
    "sg:postcode":"67227",
    "sg:province":"Rheinland-Pfalz",
    "wof:name":"Spitzbub",
    "wof:placetype":"venue"
},
  "geometry": {"coordinates":[8.3593473434,49.5371627808],"type":"Point"}
}