{
  "type": "Feature",
  "properties": {
    "iso:country":"DE",
    "sg:address":"Am Rosenende 12-13",
    "sg:city":"Doberlug-Kirchhain",
    "sg:phone":"+49 35322/31314",
    "sg:postcode":"03253",
    "sg:province":"Brandenburg",
    "wof:name":"Hotel-restaurant Rose",
    "wof:placetype":"venue"
},
  "geometry": {"coordinates":[13.5607728958,51.6439704895],"type":"Point"}
}