{
  "type": "Feature",
  "properties": {
    "iso:country":"DE",
    "sg:address":"Seestr. 7",
    "sg:city":"Verchen",
    "sg:phone":"+49 39994/79873",
    "sg:postcode":"17111",
    "sg:province":"Mecklenburg-Vorpommern",
    "wof:name":"Bistro Am See",
    "wof:placetype":"venue"
},
  "geometry": {"coordinates":[12.9140491486,53.8434562683],"type":"Point"}
}