{
  "type": "Feature",
  "properties": {
    "iso:country":"DE",
    "sg:address":"Postberg 2",
    "sg:city":"M\u00fcnsingen",
    "sg:phone":"+49 7381/929707",
    "sg:postcode":"72525",
    "sg:province":"Baden-W\u00fcrttemberg",
    "wof:name":"Monika Ragg Ergotherapie",
    "wof:placetype":"venue"
},
  "geometry": {"coordinates":[9.496699,48.412045],"type":"Point"}
}