{
  "type": "Feature",
  "properties": {
    "iso:country":"DE",
    "sg:address":"Neusser Str. 28",
    "sg:city":"Krefeld",
    "sg:phone":"+49 2151/755543",
    "sg:postcode":"47798",
    "sg:province":"Nordrhein-Westfalen",
    "wof:name":"Fit For Life Gesundheits- Dienste Gmbh",
    "wof:placetype":"venue"
},
  "geometry": {"coordinates":[6.5664057732,51.3260803223],"type":"Point"}
}