{
  "type": "Feature",
  "properties": {
    "iso:country":"DE",
    "sg:address":"Feuerstr. 14",
    "sg:city":"Wuppertal",
    "sg:phone":"+49 202/623400",
    "sg:postcode":"42289",
    "sg:province":"Nordrhein-Westfalen",
    "wof:name":"Marcos Schn\u00e4ppchen-markt Benedukt Gmbh",
    "wof:placetype":"venue"
},
  "geometry": {"coordinates":[7.2174358368,51.2715339661],"type":"Point"}
}