{
  "type": "Feature",
  "properties": {
    "iso:country":"DE",
    "sg:address":"Fl\u00f6sswiese 28",
    "sg:city":"Marl",
    "sg:phone":"+49 2365/381465",
    "sg:postcode":"45770",
    "sg:province":"Nordrhein-Westfalen",
    "wof:name":"Harry Wegner",
    "wof:placetype":"venue"
},
  "geometry": {"coordinates":[7.1192498207,51.6598701477],"type":"Point"}
}