{
  "type": "Feature",
  "properties": {
    "iso:country":"DE",
    "sg:address":"Bergstr. 4",
    "sg:city":"K\u00f6ditz",
    "sg:phone":"+49 9281/66427",
    "sg:postcode":"95189",
    "sg:province":"Bayern",
    "wof:name":"Ev. Luth. Pfarramt",
    "wof:placetype":"venue"
},
  "geometry": {"coordinates":[11.8460206985,50.3326568604],"type":"Point"}
}