{
  "type": "Feature",
  "properties": {
    "iso:country":"DE",
    "sg:address":"Bahnhofstr. 13",
    "sg:city":"Xanten",
    "sg:phone":"+49 2801/841",
    "sg:postcode":"46509",
    "sg:province":"Nordrhein-Westfalen",
    "wof:name":"Sparkasse Moers",
    "wof:placetype":"venue"
},
  "geometry": {"coordinates":[6.451152,51.660725],"type":"Point"}
}