{
  "type": "Feature",
  "properties": {
    "iso:country":"DE",
    "sg:address":"Kr\u00e4henstr. 25",
    "sg:city":"L\u00fcbeck",
    "sg:postcode":"23552",
    "sg:province":"Schleswig-Holstein",
    "wof:name":"Freizeit Und Reisen L\u00fcbeck Reiseb\u00fcro Und Bustouristik",
    "wof:placetype":"venue"
},
  "geometry": {"coordinates":[10.6927461624,53.8641738892],"type":"Point"}
}