{
  "type": "Feature",
  "properties": {
    "iso:country":"DE",
    "sg:address":"Theodor-Triebenbacher-Str. 4",
    "sg:city":"Velden",
    "sg:phone":"+49 8742/1786",
    "sg:postcode":"84149",
    "sg:province":"Bayern",
    "wof:name":"Johann Sadlstadter",
    "wof:placetype":"venue"
},
  "geometry": {"coordinates":[12.24611,48.368935],"type":"Point"}
}