{
  "type": "Feature",
  "properties": {
    "iso:country":"DE",
    "sg:address":"Im Timpen 8",
    "sg:city":"Datteln",
    "sg:phone":"+49 2363/34527",
    "sg:postcode":"45711",
    "sg:province":"Nordrhein-Westfalen",
    "wof:name":"Fleischerei Heinrich Bork E.k.",
    "wof:placetype":"venue"
},
  "geometry": {"coordinates":[7.328081131,51.649017334],"type":"Point"}
}