{
  "type": "Feature",
  "properties": {
    "iso:country":"DE",
    "sg:address":"Soesttor 12",
    "sg:city":"Lippstadt",
    "sg:phone":"+49 2941/729012",
    "sg:postcode":"59555",
    "sg:province":"Nordrhein-Westfalen",
    "wof:name":"Gfu-consult Gmbh",
    "wof:placetype":"venue"
},
  "geometry": {"coordinates":[8.336713,51.673325],"type":"Point"}
}