{
  "type": "Feature",
  "properties": {
    "iso:country":"DE",
    "sg:address":"Am Bach 3",
    "sg:city":"Morbach",
    "sg:phone":"+49 6533/2827",
    "sg:postcode":"54497",
    "sg:province":"Rheinland-Pfalz",
    "wof:name":"Angela Dorny",
    "wof:placetype":"venue"
},
  "geometry": {"coordinates":[7.094685,49.790222],"type":"Point"}
}