{
  "type": "Feature",
  "properties": {
    "iso:country":"DE",
    "sg:address":"Rittrumer Kirchweg 5",
    "sg:city":"D\u00f6tlingen",
    "sg:phone":"+49 4433/446",
    "sg:postcode":"27801",
    "sg:province":"Niedersachsen",
    "wof:name":"Cafe-restaurant Kl\u00e4ner-hof",
    "wof:placetype":"venue"
},
  "geometry": {"coordinates":[8.3756885529,52.9418907166],"type":"Point"}
}