{
  "type": "Feature",
  "properties": {
    "iso:country":"DE",
    "sg:address":"Grube Einheit 44",
    "sg:city":"Hohenm\u00f6lsen",
    "sg:phone":"+49 34441/20537",
    "sg:postcode":"06679",
    "sg:province":"Sachsen-Anhalt",
    "wof:name":"Maschinenfabrik Rau Gmbh",
    "wof:placetype":"venue"
},
  "geometry": {"coordinates":[12.094855,51.16877],"type":"Point"}
}