{
  "type": "Feature",
  "properties": {
    "iso:country":"DE",
    "sg:address":"Osterloh 103",
    "sg:city":"Plettenberg",
    "sg:phone":"+49 2391/14285",
    "sg:postcode":"58840",
    "sg:province":"Nordrhein-Westfalen",
    "wof:name":"Wilhelm Groll",
    "wof:placetype":"venue"
},
  "geometry": {"coordinates":[7.8269729614,51.1987266541],"type":"Point"}
}