{
  "type": "Feature",
  "properties": {
    "iso:country":"DE",
    "sg:address":"Erfenbacher Str. 39",
    "sg:city":"Kaiserslautern",
    "sg:phone":"+49 6301/1469",
    "sg:postcode":"67661",
    "sg:province":"Rheinland-Pfalz",
    "wof:name":"General Contract And Sales Inh. Lester L. Wammack",
    "wof:placetype":"venue"
},
  "geometry": {"coordinates":[7.6946787834,49.4715156555],"type":"Point"}
}