{
  "type": "Feature",
  "properties": {
    "iso:country":"DE",
    "sg:city":"Kuchelmi\u00df",
    "sg:postcode":"18292",
    "sg:province":"Mecklenburg-Vorpommern",
    "wof:name":"Produktionsgenossenschaft Eg Zum Nebeltal Kuchelmi\u00df",
    "wof:placetype":"venue"
},
  "geometry": {"coordinates":[12.36573,53.682449],"type":"Point"}
}