{
  "type": "Feature",
  "properties": {
    "iso:country":"DE",
    "sg:address":"Marienburger Str. 30",
    "sg:city":"Berlin",
    "sg:phone":"+49 30/4413613",
    "sg:postcode":"10405",
    "sg:province":"Berlin",
    "wof:name":"Wolfgang Dr\u00e4ger",
    "wof:placetype":"venue"
},
  "geometry": {"coordinates":[13.4277601242,52.5338096619],"type":"Point"}
}