{
  "type": "Feature",
  "properties": {
    "iso:country":"DE",
    "sg:address":"Lindenweg 10",
    "sg:city":"Affing",
    "sg:phone":"+49 8207/1344",
    "sg:postcode":"86444",
    "sg:province":"Bayern",
    "wof:name":"Bleis Gmbh",
    "wof:placetype":"venue"
},
  "geometry": {"coordinates":[10.9820775986,48.4526023865],"type":"Point"}
}