{
  "type": "Feature",
  "properties": {
    "iso:country":"DE",
    "sg:address":"Salzbergener Str. 137",
    "sg:city":"Rheine",
    "sg:phone":"+49 5971/4155",
    "sg:postcode":"48431",
    "sg:province":"Nordrhein-Westfalen",
    "wof:name":"Jet-tankstelle",
    "wof:placetype":"venue"
},
  "geometry": {"coordinates":[7.4248871803,52.2880935669],"type":"Point"}
}