{
  "type": "Feature",
  "properties": {
    "iso:country":"DE",
    "sg:address":"Prinz-Ludwig-Str. 1",
    "sg:city":"Regensburg",
    "sg:phone":"+49 941/794187",
    "sg:postcode":"93055",
    "sg:province":"Bayern",
    "wof:name":"Max Bink Fleisch- Und Innereien-gro\u00dfhandel",
    "wof:placetype":"venue"
},
  "geometry": {"coordinates":[12.1194438934,49.0160102844],"type":"Point"}
}