{
  "type": "Feature",
  "properties": {
    "iso:country":"DE",
    "sg:address":"Morschstr. 15",
    "sg:city":"Mainz",
    "sg:phone":"+49 6131/957010",
    "sg:postcode":"55129",
    "sg:province":"Rheinland-Pfalz",
    "wof:name":"Wabacom Fernmelde- Elektronik Gmbh",
    "wof:placetype":"venue"
},
  "geometry": {"coordinates":[8.280913353,49.9588432312],"type":"Point"}
}