{
  "type": "Feature",
  "properties": {
    "iso:country":"DE",
    "sg:address":"Seitnerstr. 349",
    "sg:city":"Pullach",
    "sg:postcode":"82049",
    "sg:province":"Bayern",
    "wof:name":"Verlag F\u00fcr Juristische Didaktik Gmbh",
    "wof:placetype":"venue"
},
  "geometry": {"coordinates":[11.510052681,48.0461196899],"type":"Point"}
}