{
  "type": "Feature",
  "properties": {
    "iso:country":"DE",
    "sg:address":"Niedersachsenstr. 14",
    "sg:city":"Peine",
    "sg:phone":"+49 5171/53048",
    "sg:postcode":"31226",
    "sg:province":"Niedersachsen",
    "wof:name":"J. Walter Lebensmittel",
    "wof:placetype":"venue"
},
  "geometry": {"coordinates":[10.1695547104,52.3068237305],"type":"Point"}
}