{
  "type": "Feature",
  "properties": {
    "iso:country":"DE",
    "sg:address":"Felix-Dahn-Str. 4",
    "sg:city":"Hamburg",
    "sg:postcode":"20357",
    "sg:province":"Hamburg",
    "wof:name":"Green Card Support Service Nl",
    "wof:placetype":"venue"
},
  "geometry": {"coordinates":[9.9673032761,53.5708351135],"type":"Point"}
}