{
  "type": "Feature",
  "properties": {
    "iso:country":"DE",
    "sg:address":"Krankenhausstr. 26",
    "sg:city":"Ilmenau",
    "sg:phone":"+49 3677/883898",
    "sg:postcode":"98693",
    "sg:province":"Th\u00fcringen",
    "wof:name":"S. Menzel",
    "wof:placetype":"venue"
},
  "geometry": {"coordinates":[10.917023,50.679665],"type":"Point"}
}