{
  "type": "Feature",
  "properties": {
    "iso:country":"DE",
    "sg:address":"Polterdamm 5",
    "sg:city":"Wendeburg",
    "sg:phone":"+49 5302/901082",
    "sg:postcode":"38176",
    "sg:province":"Niedersachsen",
    "wof:name":"J\u00fcrgen Wehmer & Partner Gmbh",
    "wof:placetype":"venue"
},
  "geometry": {"coordinates":[10.403695,52.291763],"type":"Point"}
}