{
  "type": "Feature",
  "properties": {
    "iso:country":"DE",
    "sg:address":"26465",
    "sg:city":"Langeoog",
    "sg:phone":"+49 4972/6051",
    "sg:postcode":"26465",
    "sg:province":"Niedersachsen",
    "wof:name":"Tenniscenter",
    "wof:placetype":"venue"
},
  "geometry": {"coordinates":[7.4844198227,53.739730835],"type":"Point"}
}