{
  "type": "Feature",
  "properties": {
    "iso:country":"DE",
    "sg:address":"Silcherstr. 12",
    "sg:city":"Osthofen",
    "sg:phone":"+49 6242/2229",
    "sg:postcode":"67574",
    "sg:province":"Rheinland-Pfalz",
    "wof:name":"J. Siemssen",
    "wof:placetype":"venue"
},
  "geometry": {"coordinates":[8.3335,49.705765],"type":"Point"}
}