{
  "type": "Feature",
  "properties": {
    "iso:country":"DE",
    "sg:address":"Gro\u00dfer Scharnhorst 7",
    "sg:city":"Reinbek",
    "sg:phone":"+49 40/7224566",
    "sg:postcode":"21465",
    "sg:province":"Schleswig-Holstein",
    "wof:name":"Werner Westphal",
    "wof:placetype":"venue"
},
  "geometry": {"coordinates":[10.2289199829,53.5143013],"type":"Point"}
}