{
  "type": "Feature",
  "properties": {
    "iso:country":"DE",
    "sg:address":"Talstr. 23",
    "sg:city":"Tholey",
    "sg:postcode":"66636",
    "sg:province":"Saarland",
    "wof:name":"Industrieservice Udo Besch E. K.",
    "wof:placetype":"venue"
},
  "geometry": {"coordinates":[7.019812,49.499847],"type":"Point"}
}