{
  "type": "Feature",
  "properties": {
    "iso:country":"DE",
    "sg:address":"Stra\u00df\u00f6sch 10",
    "sg:city":"Durach",
    "sg:phone":"+49 831/63324",
    "sg:postcode":"87471",
    "sg:province":"Bayern",
    "wof:name":"J. H. Anhalt",
    "wof:placetype":"venue"
},
  "geometry": {"coordinates":[10.333335,47.706646],"type":"Point"}
}