{
  "type": "Feature",
  "properties": {
    "iso:country":"DE",
    "sg:address":"Friedensstr. 102",
    "sg:city":"Arendsee",
    "sg:phone":"+49 39384/2514",
    "sg:postcode":"39619",
    "sg:province":"Sachsen-Anhalt",
    "wof:name":"Herbert Kurths",
    "wof:placetype":"venue"
},
  "geometry": {"coordinates":[11.49045,52.882317],"type":"Point"}
}