{
  "type": "Feature",
  "properties": {
    "iso:country":"DE",
    "sg:address":"Lother Str. 5",
    "sg:city":"Steinheim",
    "sg:phone":"+49 4952/3394970",
    "sg:postcode":"32839",
    "sg:province":"Nordrhein-Westfalen",
    "wof:name":"Zimbo Fleisch-wurstwaren Produktion Gmbh & Co. Kg",
    "wof:placetype":"venue"
},
  "geometry": {"coordinates":[9.1051416397,51.866607666],"type":"Point"}
}