{
  "type": "Feature",
  "properties": {
    "iso:country":"DE",
    "sg:address":"Bahnhofstr. 14",
    "sg:city":"Herford",
    "sg:phone":"+49 5221/57512",
    "sg:postcode":"32052",
    "sg:province":"Nordrhein-Westfalen",
    "wof:name":"Manos Grill",
    "wof:placetype":"venue"
},
  "geometry": {"coordinates":[8.6645345688,52.118686676],"type":"Point"}
}