{
  "type": "Feature",
  "properties": {
    "iso:country":"DE",
    "sg:address":"N\u00fcrtinger Str. 63",
    "sg:city":"Metzingen",
    "sg:phone":"+49 7123/41808",
    "sg:postcode":"72555",
    "sg:province":"Baden-W\u00fcrttemberg",
    "wof:name":"Pizzeria Giardino Ditalia",
    "wof:placetype":"venue"
},
  "geometry": {"coordinates":[9.2899188995,48.5436210632],"type":"Point"}
}