{
  "type": "Feature",
  "properties": {
    "iso:country":"DE",
    "sg:address":"Altstadt 295",
    "sg:city":"Landshut",
    "sg:phone":"+49 871/21485",
    "sg:postcode":"84028",
    "sg:province":"Bayern",
    "wof:name":"Elisabeth Rajal",
    "wof:placetype":"venue"
},
  "geometry": {"coordinates":[12.151166,48.535336],"type":"Point"}
}