{
  "type": "Feature",
  "properties": {
    "iso:country":"DE",
    "sg:address":"Schulstr. 40",
    "sg:city":"F\u00fcrth",
    "sg:postcode":"64658",
    "sg:province":"Hessen",
    "wof:name":"Gehbauer Bautr\u00e4ger Gmbh",
    "wof:placetype":"venue"
},
  "geometry": {"coordinates":[8.780679,49.646122],"type":"Point"}
}