{
  "type": "Feature",
  "properties": {
    "iso:country":"DE",
    "sg:address":"Am Hasenh\u00fcbel 2",
    "sg:city":"Bann",
    "sg:phone":"+49 172 6810415",
    "sg:postcode":"66851",
    "sg:province":"Rheinland-Pfalz",
    "wof:name":"Doz Schmuckdesign",
    "wof:placetype":"venue"
},
  "geometry": {"coordinates":[7.615937233,49.3869781494],"type":"Point"}
}