{
  "type": "Feature",
  "properties": {
    "iso:country":"DE",
    "sg:address":"Weiden\u00e4cker 16",
    "sg:city":"Ubstadt-Weiher",
    "sg:phone":"+49 7251/6476",
    "sg:postcode":"76698",
    "sg:province":"Baden-W\u00fcrttemberg",
    "wof:name":"L. Gollda",
    "wof:placetype":"venue"
},
  "geometry": {"coordinates":[8.615597,49.178001],"type":"Point"}
}