{
  "type": "Feature",
  "properties": {
    "iso:country":"DE",
    "sg:address":"Am Rumberg 21",
    "sg:city":"Grimma",
    "sg:phone":"+49 3437/764838",
    "sg:postcode":"04668",
    "sg:province":"Sachsen",
    "wof:name":"Wolfgang Machon",
    "wof:placetype":"venue"
},
  "geometry": {"coordinates":[12.692065239,51.2308616638],"type":"Point"}
}