{
  "type": "Feature",
  "properties": {
    "iso:country":"DE",
    "sg:address":"K\u00f6lnstr. 49",
    "sg:city":"Sankt Augustin",
    "sg:phone":"+49 2241/203093",
    "sg:postcode":"53757",
    "sg:province":"Nordrhein-Westfalen",
    "wof:name":"Michael Stentenbach Heilpraktiker",
    "wof:placetype":"venue"
},
  "geometry": {"coordinates":[7.1730871201,50.7625541687],"type":"Point"}
}