{
  "type": "Feature",
  "properties": {
    "iso:country":"DE",
    "sg:address":"Akazienstr. 1-2",
    "sg:city":"Berlin",
    "sg:phone":"+49 30/7726078",
    "sg:postcode":"12207",
    "sg:province":"Berlin",
    "wof:name":"H\u00f6lter Bau Gmbh",
    "wof:placetype":"venue"
},
  "geometry": {"coordinates":[13.3239002228,52.4269523621],"type":"Point"}
}