{
  "type": "Feature",
  "properties": {
    "iso:country":"DE",
    "sg:address":"Azaleenstr. 15",
    "sg:city":"Halle",
    "sg:phone":"+49 345/8047725",
    "sg:postcode":"06122",
    "sg:province":"Sachsen-Anhalt",
    "wof:name":"Dr. Gertrud Horntrich",
    "wof:placetype":"venue"
},
  "geometry": {"coordinates":[11.934151,51.48241],"type":"Point"}
}