{
  "type": "Feature",
  "properties": {
    "iso:country":"DE",
    "sg:address":"Heimst\u00e4ttenstr. 14",
    "sg:city":"Ulm",
    "sg:phone":"+49 731/384302",
    "sg:postcode":"89077",
    "sg:province":"Baden-W\u00fcrttemberg",
    "wof:name":"K. Wegerer",
    "wof:placetype":"venue"
},
  "geometry": {"coordinates":[9.9630889893,48.3906097412],"type":"Point"}
}