{
  "type": "Feature",
  "properties": {
    "iso:country":"DE",
    "sg:address":"Hauptstr. 56",
    "sg:city":"Aitrach",
    "sg:phone":"+49 7565/5420",
    "sg:postcode":"88319",
    "sg:province":"Baden-W\u00fcrttemberg",
    "wof:name":"H. Sontheimer Und K. Krucker",
    "wof:placetype":"venue"
},
  "geometry": {"coordinates":[10.0912981033,47.9391326904],"type":"Point"}
}