{
  "type": "Feature",
  "properties": {
    "iso:country":"DE",
    "sg:address":"Talstr. 9",
    "sg:city":"Frankfurt",
    "sg:phone":"+49 69/50930050",
    "sg:postcode":"60437",
    "sg:province":"Hessen",
    "wof:name":"No Limit",
    "wof:placetype":"venue"
},
  "geometry": {"coordinates":[8.6377725601,50.1886749268],"type":"Point"}
}