{
  "type": "Feature",
  "properties": {
    "iso:country":"DE",
    "sg:address":"Brauhausstr. 1b",
    "sg:city":"Stendal",
    "sg:phone":"+49 3931/212952",
    "sg:postcode":"39576",
    "sg:province":"Sachsen-Anhalt",
    "wof:name":"Frank Hilse",
    "wof:placetype":"venue"
},
  "geometry": {"coordinates":[11.85654,52.612389],"type":"Point"}
}