{
  "type": "Feature",
  "properties": {
    "iso:country":"DE",
    "sg:address":"Grettstadter Weg 3",
    "sg:city":"Gochsheim",
    "sg:phone":"+49 9721/62051",
    "sg:postcode":"97469",
    "sg:province":"Bayern",
    "wof:name":"Killer Wassertechnik Handels Gmbh",
    "wof:placetype":"venue"
},
  "geometry": {"coordinates":[10.3166103363,50.0202789307],"type":"Point"}
}