{
  "type": "Feature",
  "properties": {
    "iso:country":"DE",
    "sg:address":"Ludwig-Thoma-Str. 15",
    "sg:city":"Pei\u00dfenberg",
    "sg:phone":"+49 8803/3447",
    "sg:postcode":"82380",
    "sg:province":"Bayern",
    "wof:name":"Reinhold Lang",
    "wof:placetype":"venue"
},
  "geometry": {"coordinates":[11.069946,47.782394],"type":"Point"}
}