{
  "type": "Feature",
  "properties": {
    "iso:country":"DE",
    "sg:address":"P\u00fctzchens Chaussee 16-20",
    "sg:city":"Bonn",
    "sg:phone":"+49 228/97260",
    "sg:postcode":"53227",
    "sg:province":"Nordrhein-Westfalen",
    "wof:name":"Kaufhof Warenhaus Ag",
    "wof:placetype":"venue"
},
  "geometry": {"coordinates":[7.136714,50.742256],"type":"Point"}
}