{
  "type": "Feature",
  "properties": {
    "iso:country":"DE",
    "sg:address":"Kurf\u00fcrstendamm 186",
    "sg:city":"Berlin",
    "sg:postcode":"10707",
    "sg:province":"Berlin",
    "wof:name":"Institut F\u00fcr Politische Planung Und Kybernetik Gmbh",
    "wof:placetype":"venue"
},
  "geometry": {"coordinates":[13.3154230118,52.5007629395],"type":"Point"}
}