{
  "type": "Feature",
  "properties": {
    "iso:country":"DE",
    "sg:address":"C\u00e4cilienstr. 6",
    "sg:city":"D\u00fcsseldorf",
    "sg:postcode":"40597",
    "sg:province":"Nordrhein-Westfalen",
    "wof:name":"Hmp Beteiligungsges. Mbh",
    "wof:placetype":"venue"
},
  "geometry": {"coordinates":[6.873517,51.164211],"type":"Point"}
}