{
  "type": "Feature",
  "properties": {
    "iso:country":"DE",
    "sg:address":"Alpenstr 2",
    "sg:city":"Buxheim",
    "sg:phone":"+49 8331/901000",
    "sg:postcode":"87740",
    "sg:province":"Bayern",
    "wof:name":"Horst Harzenetter Stanzformenbau Gmbh",
    "wof:placetype":"venue"
},
  "geometry": {"coordinates":[10.1418209076,47.9955749512],"type":"Point"}
}