{
  "type": "Feature",
  "properties": {
    "iso:country":"DE",
    "sg:address":"Hochkreuzallee 32",
    "sg:city":"Bonn",
    "sg:phone":"+49 228/313698",
    "sg:postcode":"53175",
    "sg:province":"Nordrhein-Westfalen",
    "wof:name":"H. Weber",
    "wof:placetype":"venue"
},
  "geometry": {"coordinates":[7.1379680634,50.695980072],"type":"Point"}
}