{
  "type": "Feature",
  "properties": {
    "iso:country":"DE",
    "sg:address":"Am Kamp",
    "sg:city":"Holm",
    "sg:postcode":"25488",
    "sg:province":"Schleswig-Holstein",
    "wof:name":"Unternehmensberatung Hanno Fecke",
    "wof:placetype":"venue"
},
  "geometry": {"coordinates":[9.679555,53.621601],"type":"Point"}
}