{
  "type": "Feature",
  "properties": {
    "iso:country":"DE",
    "sg:address":"Einsiedler Hauptstr 105",
    "sg:city":"Chemnitz",
    "sg:phone":"+49 37209/2271",
    "sg:postcode":"09123",
    "sg:province":"Sachsen",
    "wof:name":"Elektro Motoren Service Frank Vogelsang",
    "wof:placetype":"venue"
},
  "geometry": {"coordinates":[12.91191,50.761189],"type":"Point"}
}