{
  "type": "Feature",
  "properties": {
    "iso:country":"DE",
    "sg:address":"Pranckhstr. 2",
    "sg:city":"M\u00fcnchen",
    "sg:phone":"+49 89/23335798",
    "sg:postcode":"80335",
    "sg:province":"Bayern",
    "wof:name":"Akademie F\u00fcr Das Graphische Gewerbe H\u00f6here Fachschule",
    "wof:placetype":"venue"
},
  "geometry": {"coordinates":[11.5474710464,48.1455764771],"type":"Point"}
}