{
  "type": "Feature",
  "properties": {
    "iso:country":"DE",
    "sg:address":"Linprunstr. 44",
    "sg:city":"M\u00fcnchen",
    "sg:phone":"+49 89/1240010",
    "sg:postcode":"80335",
    "sg:province":"Bayern",
    "wof:name":"Physiotech Gesellschaft F\u00fcr Technologieorientierte",
    "wof:placetype":"venue"
},
  "geometry": {"coordinates":[11.552174,48.150806],"type":"Point"}
}