{
  "type": "Feature",
  "properties": {
    "iso:country":"DE",
    "sg:address":"Hinter den Kirschkaten 28",
    "sg:city":"L\u00fcbeck",
    "sg:phone":"+49 451/5823011",
    "sg:postcode":"23560",
    "sg:province":"Schleswig-Holstein",
    "wof:name":"Turbo Maxx E. K.",
    "wof:placetype":"venue"
},
  "geometry": {"coordinates":[10.6687507629,53.8434791565],"type":"Point"}
}