{
  "type": "Feature",
  "properties": {
    "iso:country":"DE",
    "sg:address":"Sackstr. 12",
    "sg:city":"Coppenbr\u00fcgge",
    "sg:phone":"+49 5156/315",
    "sg:postcode":"31863",
    "sg:province":"Niedersachsen",
    "wof:name":"Heinz Luchnik",
    "wof:placetype":"venue"
},
  "geometry": {"coordinates":[9.546674,52.1208],"type":"Point"}
}