{
  "type": "Feature",
  "properties": {
    "iso:country":"DE",
    "sg:address":"Sugambrerweg 50",
    "sg:city":"Hamburg",
    "sg:postcode":"22453",
    "sg:province":"Hamburg",
    "wof:name":"Amos Reprotechnik Gmbh",
    "wof:placetype":"venue"
},
  "geometry": {"coordinates":[9.9634532928,53.6255950928],"type":"Point"}
}