{
  "type": "Feature",
  "properties": {
    "iso:country":"DE",
    "sg:address":"Nebenstr. 13",
    "sg:city":"Hasselroth",
    "sg:phone":"+49 4960/5583670",
    "sg:postcode":"63594",
    "sg:province":"Hessen",
    "wof:name":"Sysco Sicherheitssysteme Gmbh",
    "wof:placetype":"venue"
},
  "geometry": {"coordinates":[9.1052436829,50.1547088623],"type":"Point"}
}