{
  "type": "Feature",
  "properties": {
    "iso:country":"DE",
    "sg:address":"M\u00fchlenstr. 10a",
    "sg:city":"B\u00fchl",
    "sg:phone":"+49 7223/24661",
    "sg:postcode":"77815",
    "sg:province":"Baden-W\u00fcrttemberg",
    "wof:name":"Sozialstation Sankt Elisabeth E. V.",
    "wof:placetype":"venue"
},
  "geometry": {"coordinates":[8.139552,48.696014],"type":"Point"}
}