{
  "type": "Feature",
  "properties": {
    "iso:country":"DE",
    "sg:address":"St.-Elisabeth-Str. 55",
    "sg:city":"Wenden",
    "sg:phone":"+49 2762/5078",
    "sg:postcode":"57482",
    "sg:province":"Nordrhein-Westfalen",
    "wof:name":"Dieter Wittemund",
    "wof:placetype":"venue"
},
  "geometry": {"coordinates":[7.909947,50.973335],"type":"Point"}
}