{
  "type": "Feature",
  "properties": {
    "iso:country":"DE",
    "sg:address":"Sprenger Weg",
    "sg:city":"Hoisdorf",
    "sg:phone":"+49 4107/4881",
    "sg:postcode":"22955",
    "sg:province":"Schleswig-Holstein",
    "wof:name":"Stormansches Dorfmuseum Altes Bauernhaus Am Thie",
    "wof:placetype":"venue"
},
  "geometry": {"coordinates":[10.344238,53.660873],"type":"Point"}
}