{
  "type": "Feature",
  "properties": {
    "iso:country":"DE",
    "sg:address":"Gertrud-Schlo\u00df-Str. 46",
    "sg:city":"Trier",
    "sg:phone":"+49 651/37173",
    "sg:postcode":"54294",
    "sg:province":"Rheinland-Pfalz",
    "wof:name":"J\u00fcrgen H. Pferdekamp",
    "wof:placetype":"venue"
},
  "geometry": {"coordinates":[6.62462,49.721992],"type":"Point"}
}