{
  "type": "Feature",
  "properties": {
    "iso:country":"DE",
    "sg:address":"Behaimstr. 13",
    "sg:city":"Berlin",
    "sg:phone":"+49 30/3429010",
    "sg:postcode":"10585",
    "sg:province":"Berlin",
    "wof:name":"Krause Parf\u00fcmerie",
    "wof:placetype":"venue"
},
  "geometry": {"coordinates":[13.304904,52.516472],"type":"Point"}
}