{
  "type": "Feature",
  "properties": {
    "iso:country":"DE",
    "sg:address":"Aalener Str. 40",
    "sg:city":"Bopfingen",
    "sg:phone":"+49 7362/3031",
    "sg:postcode":"73441",
    "sg:province":"Baden-W\u00fcrttemberg",
    "wof:name":"Ingrid Leins Gmbh",
    "wof:placetype":"venue"
},
  "geometry": {"coordinates":[10.347395,48.862217],"type":"Point"}
}