{
  "type": "Feature",
  "properties": {
    "iso:country":"DE",
    "sg:address":"Ringstr. 2",
    "sg:city":"Koblenz",
    "sg:phone":"+49 261/69950",
    "sg:postcode":"56077",
    "sg:province":"Rheinland-Pfalz",
    "wof:name":"Dr. R. Schweigert Rechtsanwalt",
    "wof:placetype":"venue"
},
  "geometry": {"coordinates":[7.6564049721,50.3707504272],"type":"Point"}
}