{
  "type": "Feature",
  "properties": {
    "iso:country":"DE",
    "sg:address":"Kornkamp 23",
    "sg:city":"Ahrensburg",
    "sg:postcode":"22926",
    "sg:province":"Schleswig-Holstein",
    "wof:name":"A. + W. Warenhandelsges. Mbh",
    "wof:placetype":"venue"
},
  "geometry": {"coordinates":[10.2569961548,53.6853370667],"type":"Point"}
}