{
  "type": "Feature",
  "properties": {
    "iso:country":"DE",
    "sg:address":"Industriestrasse 19",
    "sg:city":"Idar-Oberstein",
    "sg:phone":"+49 6784/983549",
    "sg:postcode":"55743",
    "sg:province":"Rheinland-Pfalz",
    "wof:name":"Zone-o - Opelfreunde Gebrauchtwagen H\u00e4ndler Tuner",
    "wof:placetype":"venue"
},
  "geometry": {"coordinates":[7.38376,49.7258],"type":"Point"}
}