{
  "type": "Feature",
  "properties": {
    "iso:country":"DE",
    "sg:address":"Z\u00fclpicher Str. 58",
    "sg:city":"K\u00f6ln",
    "sg:phone":"+49 221/9733925",
    "sg:postcode":"50674",
    "sg:province":"Nordrhein-Westfalen",
    "wof:name":"Diva Hausverwaltungs- Service Gmbh",
    "wof:placetype":"venue"
},
  "geometry": {"coordinates":[6.9352941513,50.9281616211],"type":"Point"}
}