{
  "type": "Feature",
  "properties": {
    "iso:country":"DE",
    "sg:address":"Thalerseestr. 2",
    "sg:city":"Landsberg",
    "sg:phone":"+49 8191/2416",
    "sg:postcode":"86899",
    "sg:province":"Bayern",
    "wof:name":"Lechle-metzgerei- Gmbh",
    "wof:placetype":"venue"
},
  "geometry": {"coordinates":[10.9166002274,48.0431938171],"type":"Point"}
}