{
  "type": "Feature",
  "properties": {
    "iso:country":"DE",
    "sg:address":"Schwabstr. 10",
    "sg:city":"K\u00f6ln",
    "sg:phone":"+49 221/6309625",
    "sg:postcode":"51067",
    "sg:province":"Nordrhein-Westfalen",
    "wof:name":"Haarstudio Kiefernagel Ihr Spezialist F\u00fcr Per\u00fccken",
    "wof:placetype":"venue"
},
  "geometry": {"coordinates":[7.053293,50.971218],"type":"Point"}
}