{
  "type": "Feature",
  "properties": {
    "iso:country":"DE",
    "sg:address":"Hauptstr. 144",
    "sg:city":"Troisdorf",
    "sg:phone":"+49 2241/951910",
    "sg:postcode":"53842",
    "sg:province":"Nordrhein-Westfalen",
    "wof:name":"Atmos Medizintechnik Gmbh",
    "wof:placetype":"venue"
},
  "geometry": {"coordinates":[7.1093,50.832661],"type":"Point"}
}