{
  "type": "Feature",
  "properties": {
    "iso:country":"DE",
    "sg:address":"Heinrich-Zille-Str. 4",
    "sg:city":"Chemnitz",
    "sg:postcode":"09111",
    "sg:province":"Sachsen",
    "wof:name":"Gie\u00dfereimodellbau Gmbh",
    "wof:placetype":"venue"
},
  "geometry": {"coordinates":[12.928377,50.842754],"type":"Point"}
}