{
  "type": "Feature",
  "properties": {
    "iso:country":"DE",
    "sg:address":"Manhagener Allee 79 b",
    "sg:city":"Ahrensburg",
    "sg:postcode":"22926",
    "sg:province":"Schleswig-Holstein",
    "wof:name":"Max K\u00fc\u00dfner Inh. Michael Walter E. K.",
    "wof:placetype":"venue"
},
  "geometry": {"coordinates":[10.2473163605,53.6663322449],"type":"Point"}
}