{
  "type": "Feature",
  "properties": {
    "iso:country":"DE",
    "sg:address":"Markt 17",
    "sg:city":"Stolpen",
    "sg:phone":"+49 35973/26270",
    "sg:postcode":"01833",
    "sg:province":"Sachsen",
    "wof:name":"Regina Fasold",
    "wof:placetype":"venue"
},
  "geometry": {"coordinates":[14.083514,51.04929],"type":"Point"}
}