{
  "type": "Feature",
  "properties": {
    "iso:country":"DE",
    "sg:address":"Springstr. 1",
    "sg:city":"Recklinghausen",
    "sg:phone":"+49 2361/23690",
    "sg:postcode":"45657",
    "sg:province":"Nordrhein-Westfalen",
    "wof:name":"Witte Und Leonhardt Rechtsanw\u00e4lte",
    "wof:placetype":"venue"
},
  "geometry": {"coordinates":[7.2007169724,51.6167068481],"type":"Point"}
}