{
  "type": "Feature",
  "properties": {
    "iso:country":"DE",
    "sg:address":"Welfenstr. 31 a",
    "sg:city":"M\u00fcnchen",
    "sg:phone":"+49 89/459150",
    "sg:postcode":"81541",
    "sg:province":"Bayern",
    "wof:name":"Fritz W. Schubert Gmbh",
    "wof:placetype":"venue"
},
  "geometry": {"coordinates":[11.591043,48.122627],"type":"Point"}
}