{
  "type": "Feature",
  "properties": {
    "iso:country":"DE",
    "sg:address":"Arsenalstr. 8",
    "sg:city":"Trappenkamp",
    "sg:phone":"+49 4323/92610",
    "sg:postcode":"24610",
    "sg:province":"Schleswig-Holstein",
    "wof:name":"B. Sch\u00e4fer",
    "wof:placetype":"venue"
},
  "geometry": {"coordinates":[10.2178468704,54.0444602966],"type":"Point"}
}