{
  "type": "Feature",
  "properties": {
    "iso:country":"DE",
    "sg:address":"Am Bergkamp 39",
    "sg:city":"Lemgo",
    "sg:phone":"+49 5261/71713",
    "sg:postcode":"32657",
    "sg:province":"Nordrhein-Westfalen",
    "wof:name":"Fritz K\u00e4mper",
    "wof:placetype":"venue"
},
  "geometry": {"coordinates":[8.869024,52.006355],"type":"Point"}
}