{
  "type": "Feature",
  "properties": {
    "iso:country":"DE",
    "sg:address":"Am Umfluter 11",
    "sg:city":"Lage",
    "sg:phone":"+49 5232/2571",
    "sg:postcode":"32791",
    "sg:province":"Nordrhein-Westfalen",
    "wof:name":"Kraft Color Labor",
    "wof:placetype":"venue"
},
  "geometry": {"coordinates":[8.7972698212,51.9830093384],"type":"Point"}
}