{
  "type": "Feature",
  "properties": {
    "iso:country":"DE",
    "sg:address":"Schillerstr. 4",
    "sg:city":"Kaiserslautern",
    "sg:phone":"+49 631/64573",
    "sg:postcode":"67655",
    "sg:province":"Rheinland-Pfalz",
    "wof:name":"C. Wiss Gmbh",
    "wof:placetype":"venue"
},
  "geometry": {"coordinates":[7.7699699402,49.4452018738],"type":"Point"}
}