{
  "type": "Feature",
  "properties": {
    "iso:country":"DE",
    "sg:address":"Brunnenstr. 4",
    "sg:city":"Fleringen",
    "sg:phone":"+49 6558/8582",
    "sg:postcode":"54597",
    "sg:province":"Rheinland-Pfalz",
    "wof:name":"Johann Feinen",
    "wof:placetype":"venue"
},
  "geometry": {"coordinates":[6.499671,50.207596],"type":"Point"}
}