{
  "type": "Feature",
  "properties": {
    "iso:country":"DE",
    "sg:address":"Burgstr. 8",
    "sg:city":"Stolberg",
    "sg:phone":"+49 2402/6956",
    "sg:postcode":"52222",
    "sg:province":"Nordrhein-Westfalen",
    "wof:name":"J. Schulz-le Gourmet",
    "wof:placetype":"venue"
},
  "geometry": {"coordinates":[6.232681,50.766411],"type":"Point"}
}