{
  "type": "Feature",
  "properties": {
    "iso:country":"DE",
    "sg:address":"Arnoldusstr. 14",
    "sg:city":"D\u00fcren",
    "sg:phone":"+49 2421/37965",
    "sg:postcode":"52353",
    "sg:province":"Nordrhein-Westfalen",
    "wof:name":"S. Mazsits",
    "wof:placetype":"venue"
},
  "geometry": {"coordinates":[6.4915261269,50.8383789062],"type":"Point"}
}