{
  "type": "Feature",
  "properties": {
    "iso:country":"DE",
    "sg:address":"Max-Planck-Str. 10",
    "sg:city":"Herne",
    "sg:phone":"+49 2325/41606",
    "sg:postcode":"44625",
    "sg:province":"Nordrhein-Westfalen",
    "wof:name":"Siegfried Klomp Architekt",
    "wof:placetype":"venue"
},
  "geometry": {"coordinates":[7.20371,51.536362],"type":"Point"}
}