{
  "type": "Feature",
  "properties": {
    "iso:country":"DE",
    "sg:address":"S\u00fclzg\u00fcrtel 6",
    "sg:city":"K\u00f6ln",
    "sg:phone":"+49 221/94404220",
    "sg:postcode":"50937",
    "sg:province":"Nordrhein-Westfalen",
    "wof:name":"Hinz Gmbh",
    "wof:placetype":"venue"
},
  "geometry": {"coordinates":[6.923629,50.912781],"type":"Point"}
}