{
  "type": "Feature",
  "properties": {
    "iso:country":"DE",
    "sg:address":"Eggenweg 11",
    "sg:city":"F\u00fcrth",
    "sg:phone":"+49 911/930650",
    "sg:postcode":"90765",
    "sg:province":"Bayern",
    "wof:name":"Ney Malerbetrieb Gmbh",
    "wof:placetype":"venue"
},
  "geometry": {"coordinates":[11.015633,49.502747],"type":"Point"}
}