{
  "type": "Feature",
  "properties": {
    "iso:country":"DE",
    "sg:address":"Halskestr. 7",
    "sg:city":"Neustadt",
    "sg:phone":"+49 9568/8580",
    "sg:postcode":"96465",
    "sg:province":"Bayern",
    "wof:name":"Sauer Plastik Gmbh & Co. Kg",
    "wof:placetype":"venue"
},
  "geometry": {"coordinates":[11.112295,50.321358],"type":"Point"}
}