{
  "type": "Feature",
  "properties": {
    "iso:country":"DE",
    "sg:address":"Schusterstr. 30",
    "sg:city":"Freiburg",
    "sg:phone":"+49 761/22662",
    "sg:postcode":"79098",
    "sg:province":"Baden-W\u00fcrttemberg",
    "wof:name":"Martine Lamy",
    "wof:placetype":"venue"
},
  "geometry": {"coordinates":[7.852104,47.994656],"type":"Point"}
}