{
  "type": "Feature",
  "properties": {
    "iso:country":"DE",
    "sg:address":"Postfach 8:: 34377 Calden:: Germany.^^Holl\u00e4ndische Str 35::",
    "sg:city":"Calden",
    "sg:postcode":"34379",
    "sg:province":"Hessen",
    "wof:name":"Raiffeisenbank Eg Dreisen",
    "wof:placetype":"venue"
},
  "geometry": {"coordinates":[8.011535,49.602997],"type":"Point"}
}