{
  "type": "Feature",
  "properties": {
    "iso:country":"DE",
    "sg:address":"Margeritenweg 2",
    "sg:city":"Planegg",
    "sg:phone":"+49 89/8595828",
    "sg:postcode":"82152",
    "sg:province":"Bayern",
    "wof:name":"Hans Bauer",
    "wof:placetype":"venue"
},
  "geometry": {"coordinates":[11.429854,48.101242],"type":"Point"}
}