{
  "type": "Feature",
  "properties": {
    "iso:country":"DE",
    "sg:address":"Hauptstr. 20",
    "sg:city":"Regnitzlosau",
    "sg:phone":"+49 9294/251",
    "sg:postcode":"95194",
    "sg:province":"Bayern",
    "wof:name":"Karl Kaiser",
    "wof:placetype":"venue"
},
  "geometry": {"coordinates":[12.047227,50.300953],"type":"Point"}
}