{
  "type": "Feature",
  "properties": {
    "iso:country":"DE",
    "sg:address":"Styrumstr. 20",
    "sg:city":"Bruchsal",
    "sg:phone":"+49 7251/306930",
    "sg:postcode":"76646",
    "sg:province":"Baden-W\u00fcrttemberg",
    "wof:name":"China Business Service In Germany E. K.",
    "wof:placetype":"venue"
},
  "geometry": {"coordinates":[8.600245,49.127949],"type":"Point"}
}