{
  "type": "Feature",
  "properties": {
    "iso:country":"DE",
    "sg:address":"Westerwieher Str. 6",
    "sg:city":"Rietberg",
    "sg:phone":"+49 5244/974454",
    "sg:postcode":"33397",
    "sg:province":"Nordrhein-Westfalen",
    "wof:name":"Pizzaexpress La Donato",
    "wof:placetype":"venue"
},
  "geometry": {"coordinates":[8.4295940399,51.8116226196],"type":"Point"}
}