{
  "type": "Feature",
  "properties": {
    "iso:country":"DE",
    "sg:address":"Develangring 72 Neukauf",
    "sg:city":"Dannenberg",
    "sg:postcode":"29451",
    "sg:province":"Niedersachsen",
    "wof:name":"Eno Vertriebs Gmbh",
    "wof:placetype":"venue"
},
  "geometry": {"coordinates":[11.0903453827,53.0966796875],"type":"Point"}
}