{
  "type": "Feature",
  "properties": {
    "iso:country":"DE",
    "sg:address":"Pintschallee 10",
    "sg:city":"Berlin",
    "sg:phone":"+49 30/6061699",
    "sg:postcode":"12347",
    "sg:province":"Berlin",
    "wof:name":"Pyrotechnik Gmbh Spezialeffekte F. Film Und",
    "wof:placetype":"venue"
},
  "geometry": {"coordinates":[13.445217,52.456345],"type":"Point"}
}