{
  "type": "Feature",
  "properties": {
    "iso:country":"DE",
    "sg:address":"Schulgasse 121 B",
    "sg:city":"Walthersdorf",
    "sg:phone":"+49 3733/66604",
    "sg:postcode":"09474",
    "sg:province":"Sachsen",
    "wof:name":"Norma Daubner Rechtsanw\u00e4ltin",
    "wof:placetype":"venue"
},
  "geometry": {"coordinates":[12.9539165497,50.5421676636],"type":"Point"}
}