{
  "type": "Feature",
  "properties": {
    "iso:country":"DE",
    "sg:address":"Dorfstr. 17",
    "sg:city":"Pfaffschwende",
    "sg:phone":"+49 4927/515290",
    "sg:postcode":"37308",
    "sg:province":"Th\u00fcringen",
    "wof:name":"Ejot Gmbh & Co Kg Sparte Kunststofftechnik",
    "wof:placetype":"venue"
},
  "geometry": {"coordinates":[8.338036,51.039948],"type":"Point"}
}