{
  "type": "Feature",
  "properties": {
    "iso:country":"DE",
    "sg:address":"Otto-Lilienthal-Str. 2",
    "sg:city":"Alsdorf",
    "sg:phone":"+49 2404/98680",
    "sg:postcode":"52477",
    "sg:province":"Nordrhein-Westfalen",
    "wof:name":"Suzo International D Gmbh",
    "wof:placetype":"venue"
},
  "geometry": {"coordinates":[6.2215328217,50.8743934631],"type":"Point"}
}