{
  "type": "Feature",
  "properties": {
    "iso:country":"DE",
    "sg:address":"Emmenhausener Str. 15",
    "sg:city":"Waal",
    "sg:phone":"+49 8246/969300",
    "sg:postcode":"86875",
    "sg:province":"Bayern",
    "wof:name":"Karin Trischberger Rechtsanw\u00e4ltin",
    "wof:placetype":"venue"
},
  "geometry": {"coordinates":[10.7821092606,47.996131897],"type":"Point"}
}