{
  "type": "Feature",
  "properties": {
    "iso:country":"DE",
    "sg:address":"Arneckestr. 1",
    "sg:city":"Dortmund",
    "sg:phone":"+49 231/127239",
    "sg:postcode":"44139",
    "sg:province":"Nordrhein-Westfalen",
    "wof:name":"Homepage Horst W. Brochhagen",
    "wof:placetype":"venue"
},
  "geometry": {"coordinates":[7.45238,51.506676],"type":"Point"}
}