{
  "type": "Feature",
  "properties": {
    "iso:country":"DE",
    "sg:address":"Freudenst\u00e4dter Str. 20",
    "sg:city":"Fluorn-Winzeln",
    "sg:postcode":"78737",
    "sg:province":"Baden-W\u00fcrttemberg",
    "wof:name":"Gemeindeb\u00fccherei Schulzentrum",
    "wof:placetype":"venue"
},
  "geometry": {"coordinates":[8.493046,48.286594],"type":"Point"}
}