{
  "type": "Feature",
  "properties": {
    "iso:country":"DE",
    "sg:address":"Speckmannstr. 13",
    "sg:city":"Grasberg",
    "sg:phone":"+49 4208/3966",
    "sg:postcode":"28879",
    "sg:province":"Niedersachsen",
    "wof:name":"Gemeindeb\u00fccherei",
    "wof:placetype":"venue"
},
  "geometry": {"coordinates":[8.984836,53.182041],"type":"Point"}
}