{
  "type": "Feature",
  "properties": {
    "iso:country":"DE",
    "sg:address":"Philosophenweg 1",
    "sg:city":"Offenburg",
    "sg:phone":"+49 781/9481103",
    "sg:postcode":"77654",
    "sg:province":"Baden-W\u00fcrttemberg",
    "wof:name":"Wolf During Immobilienmakler",
    "wof:placetype":"venue"
},
  "geometry": {"coordinates":[7.9532899857,48.4661483765],"type":"Point"}
}