{
  "type": "Feature",
  "properties": {
    "iso:country":"DE",
    "sg:address":"Lohbecker Str. 8",
    "sg:city":"Bersenbr\u00fcck",
    "sg:phone":"+49 5439/2428",
    "sg:postcode":"49593",
    "sg:province":"Niedersachsen",
    "wof:name":"Rolfs Fensterbau Beteiligungs-gmbh",
    "wof:placetype":"venue"
},
  "geometry": {"coordinates":[7.9358887672,52.5592956543],"type":"Point"}
}