{
  "type": "Feature",
  "properties": {
    "iso:country":"DE",
    "sg:address":"Landshuter Str. 5",
    "sg:city":"Dingolfing",
    "sg:phone":"+49 8731/73133",
    "sg:postcode":"84130",
    "sg:province":"Bayern",
    "wof:name":"Adam Wrobel",
    "wof:placetype":"venue"
},
  "geometry": {"coordinates":[12.4860534668,48.6451416016],"type":"Point"}
}