{
  "type": "Feature",
  "properties": {
    "iso:country":"DE",
    "sg:address":"Eichenstr. 83",
    "sg:city":"Frankfurt",
    "sg:phone":"+49 69/381070",
    "sg:postcode":"65933",
    "sg:province":"Hessen",
    "wof:name":"Kurt Sperzel Gmbh",
    "wof:placetype":"venue"
},
  "geometry": {"coordinates":[8.594162941,50.0959281921],"type":"Point"}
}