{
  "type": "Feature",
  "properties": {
    "iso:country":"DE",
    "sg:address":"Burgfriedenstr. 23",
    "sg:city":"Friedberg",
    "sg:phone":"+49 821/263800",
    "sg:postcode":"86316",
    "sg:province":"Bayern",
    "wof:name":"J. F. Fuchs & Co. Inh. Liselotte Fuchs",
    "wof:placetype":"venue"
},
  "geometry": {"coordinates":[10.952234,48.358925],"type":"Point"}
}