{
  "type": "Feature",
  "properties": {
    "iso:country":"DE",
    "sg:address":"L\u00fcbecker Str. 51",
    "sg:city":"Schwerin",
    "sg:phone":"+49 385/733935",
    "sg:postcode":"19053",
    "sg:province":"Mecklenburg-Vorpommern",
    "wof:name":"Rkm Consulting Gmbh",
    "wof:placetype":"venue"
},
  "geometry": {"coordinates":[11.4065542221,53.6313247681],"type":"Point"}
}