{
  "type": "Feature",
  "properties": {
    "iso:country":"DE",
    "sg:address":"Oberstr. 1",
    "sg:city":"Bad Salzdetfurth",
    "sg:postcode":"31162",
    "sg:province":"Niedersachsen",
    "wof:name":"Pixel Faktor Inh. Alexander Lebrenz E. K.",
    "wof:placetype":"venue"
},
  "geometry": {"coordinates":[10.006587,52.059277],"type":"Point"}
}