{
  "type": "Feature",
  "properties": {
    "iso:country":"DE",
    "sg:address":"Am Grauen Stein 15",
    "sg:city":"Rockenberg",
    "sg:phone":"+49 6033/71616",
    "sg:postcode":"35519",
    "sg:province":"Hessen",
    "wof:name":"J. Clauberg-weil",
    "wof:placetype":"venue"
},
  "geometry": {"coordinates":[8.741513,50.420765],"type":"Point"}
}