{
  "type": "Feature",
  "properties": {
    "iso:country":"DE",
    "sg:address":"Ganghoferstr 36",
    "sg:city":"Mammendorf",
    "sg:phone":"+49 8145/5232",
    "sg:postcode":"82291",
    "sg:province":"Bayern",
    "wof:name":"Kkw Gmbh",
    "wof:placetype":"venue"
},
  "geometry": {"coordinates":[11.1749534607,48.2107772827],"type":"Point"}
}