{
  "type": "Feature",
  "properties": {
    "iso:country":"DE",
    "sg:address":"Teutonenstrasse 37",
    "sg:city":"Berlin",
    "sg:phone":"+49 30",
    "sg:postcode":"12524",
    "sg:province":"Berlin",
    "wof:name":"Vem - Single Cd-rom | Berlin",
    "wof:placetype":"venue"
},
  "geometry": {"coordinates":[13.549291,52.416977],"type":"Point"}
}