{
  "type": "Feature",
  "properties": {
    "iso:country":"DE",
    "sg:address":"K\u00f6nigsberger Str. 34",
    "sg:city":"Garbsen",
    "sg:phone":"+49 5131/2337",
    "sg:postcode":"30826",
    "sg:province":"Niedersachsen",
    "wof:name":"M. Dallmann Hebamme",
    "wof:placetype":"venue"
},
  "geometry": {"coordinates":[9.545303,52.435844],"type":"Point"}
}