{
  "type": "Feature",
  "properties": {
    "iso:country":"DE",
    "sg:address":"Landgrafenstr. 62",
    "sg:city":"Worms",
    "sg:phone":"+49 6241/75047",
    "sg:postcode":"67549",
    "sg:province":"Rheinland-Pfalz",
    "wof:name":"Otmar Egelhof",
    "wof:placetype":"venue"
},
  "geometry": {"coordinates":[8.321158,49.633892],"type":"Point"}
}