{
  "type": "Feature",
  "properties": {
    "iso:country":"DE",
    "sg:address":"T\u00fcrkisweg 26",
    "sg:city":"Kaarst",
    "sg:phone":"+49 2131/602217",
    "sg:postcode":"41564",
    "sg:province":"Nordrhein-Westfalen",
    "wof:name":"Erhard Enners",
    "wof:placetype":"venue"
},
  "geometry": {"coordinates":[6.61299,51.215549],"type":"Point"}
}