{
  "type": "Feature",
  "properties": {
    "iso:country":"DE",
    "sg:address":"Wetterdeich 24",
    "sg:city":"Oederquart",
    "sg:phone":"+49 4753/236",
    "sg:postcode":"21734",
    "sg:province":"Niedersachsen",
    "wof:name":"Ahrens Und Seebeck-ahrens",
    "wof:placetype":"venue"
},
  "geometry": {"coordinates":[9.1502380371,53.7996025085],"type":"Point"}
}