{
  "type": "Feature",
  "properties": {
    "iso:country":"DE",
    "sg:address":"Marienburger Weg 10",
    "sg:city":"Dortmund",
    "sg:phone":"+49 231/335377",
    "sg:postcode":"44369",
    "sg:province":"Nordrhein-Westfalen",
    "wof:name":"Mes Bau Gmbh",
    "wof:placetype":"venue"
},
  "geometry": {"coordinates":[7.41775,51.523861],"type":"Point"}
}