{
  "type": "Feature",
  "properties": {
    "iso:country":"DE",
    "sg:address":"Verdener Landstr. 234",
    "sg:city":"Nienburg",
    "sg:phone":"+49 5021/2318",
    "sg:postcode":"31582",
    "sg:province":"Niedersachsen",
    "wof:name":"Herm. H\u00fcppe",
    "wof:placetype":"venue"
},
  "geometry": {"coordinates":[9.2262201309,52.6739883423],"type":"Point"}
}