{
  "type": "Feature",
  "properties": {
    "iso:country":"DE",
    "sg:address":"Paul-Gerhardt-Str. 25",
    "sg:city":"Sankt Augustin",
    "sg:phone":"+49 2241/334337",
    "sg:postcode":"53757",
    "sg:province":"Nordrhein-Westfalen",
    "wof:name":"Bestattungshaus Berges",
    "wof:placetype":"venue"
},
  "geometry": {"coordinates":[7.21277,50.773914],"type":"Point"}
}