{
  "type": "Feature",
  "properties": {
    "iso:country":"DE",
    "sg:address":"Wilhelmstr. 37",
    "sg:city":"Merzig",
    "sg:phone":"+49 6861/2737",
    "sg:postcode":"66663",
    "sg:province":"Saarland",
    "wof:name":"Heinz De Roi Gmbh & Co. Kg",
    "wof:placetype":"venue"
},
  "geometry": {"coordinates":[6.6476888657,49.4424667358],"type":"Point"}
}