{
  "type": "Feature",
  "properties": {
    "iso:country":"DE",
    "sg:address":"Lendringser Hauptstr. 8",
    "sg:city":"Menden",
    "sg:phone":"+49 2373/869242",
    "sg:postcode":"58710",
    "sg:province":"Nordrhein-Westfalen",
    "wof:name":"Look Optikstudio Trippe Gmbh",
    "wof:placetype":"venue"
},
  "geometry": {"coordinates":[7.8334622383,51.41198349],"type":"Point"}
}