{
  "type": "Feature",
  "properties": {
    "iso:country":"DE",
    "sg:address":"Parkallee 63",
    "sg:city":"Bremen",
    "sg:phone":"+49 421/342051",
    "sg:postcode":"28209",
    "sg:province":"Bremen",
    "wof:name":"F. L. Michaelis Gmbh",
    "wof:placetype":"venue"
},
  "geometry": {"coordinates":[8.82417202,53.0835418701],"type":"Point"}
}