{
  "type": "Feature",
  "properties": {
    "iso:country":"DE",
    "sg:address":"Kurt-Schumacher-Str. 378 Buer",
    "sg:city":"Gelsenkirchen",
    "sg:phone":"+49 4920/9930980",
    "sg:postcode":"45897",
    "sg:province":"Nordrhein-Westfalen",
    "wof:name":"Color-partner Gmbh Fotofachlabor",
    "wof:placetype":"venue"
},
  "geometry": {"coordinates":[7.05355,51.554119],"type":"Point"}
}