{
  "type": "Feature",
  "properties": {
    "iso:country":"DE",
    "sg:address":"Stralsunder Str. 21",
    "sg:city":"Wesel",
    "sg:phone":"+49 281/24084",
    "sg:postcode":"46483",
    "sg:province":"Nordrhein-Westfalen",
    "wof:name":"Landwirtschaftsverband E. V.",
    "wof:placetype":"venue"
},
  "geometry": {"coordinates":[6.6203479767,51.6503219604],"type":"Point"}
}