{
  "type": "Feature",
  "properties": {
    "iso:country":"DE",
    "sg:address":"Frankfurter Str. 27",
    "sg:city":"Eisenach",
    "sg:phone":"+49 3691/746222",
    "sg:postcode":"99817",
    "sg:province":"Th\u00fcringen",
    "wof:name":"R. Malta",
    "wof:placetype":"venue"
},
  "geometry": {"coordinates":[10.3033981323,50.9764938354],"type":"Point"}
}