{
  "type": "Feature",
  "properties": {
    "iso:country":"DE",
    "sg:address":"Waldstr. 10",
    "sg:city":"Bad Alexandersbad",
    "sg:phone":"+49 9232/3802",
    "sg:postcode":"95680",
    "sg:province":"Bayern",
    "wof:name":"Ralf B\u00fcttner",
    "wof:placetype":"venue"
},
  "geometry": {"coordinates":[12.01414,50.019066],"type":"Point"}
}