{
  "type": "Feature",
  "properties": {
    "iso:country":"DE",
    "sg:address":"Altenessener Str. 252",
    "sg:city":"Essen",
    "sg:phone":"+49 201/341406",
    "sg:postcode":"45326",
    "sg:province":"Nordrhein-Westfalen",
    "wof:name":"B. Gerard",
    "wof:placetype":"venue"
},
  "geometry": {"coordinates":[7.0092840195,51.4886856079],"type":"Point"}
}