{
  "type": "Feature",
  "properties": {
    "iso:country":"DE",
    "sg:address":"Liebknechtstr. 131",
    "sg:city":"Dreieich",
    "sg:phone":"+49 6103/62077",
    "sg:postcode":"63303",
    "sg:province":"Hessen",
    "wof:name":"Wartung Und Vertrieb Haustechnischer Anlagen Gmbh",
    "wof:placetype":"venue"
},
  "geometry": {"coordinates":[8.678008,50.019802],"type":"Point"}
}