{
  "type": "Feature",
  "properties": {
    "iso:country":"DE",
    "sg:address":"Steinbacher Weg 6",
    "sg:city":"Ebelsbach",
    "sg:phone":"+49 9522/80278",
    "sg:postcode":"97500",
    "sg:province":"Bayern",
    "wof:name":"Eco-wohnbau Verwaltung Gmbh",
    "wof:placetype":"venue"
},
  "geometry": {"coordinates":[10.6713180542,49.9839439392],"type":"Point"}
}