{
  "type": "Feature",
  "properties": {
    "iso:country":"DE",
    "sg:address":"Am F\u00fcrstenbrunnen 8",
    "sg:city":"Oberstreu",
    "sg:phone":"+49 9776/1233",
    "sg:postcode":"97640",
    "sg:province":"Bayern",
    "wof:name":"H. Schirber",
    "wof:placetype":"venue"
},
  "geometry": {"coordinates":[10.287107,50.402401],"type":"Point"}
}