{
  "type": "Feature",
  "properties": {
    "iso:country":"DE",
    "sg:address":"Max-Eyth-Str. 4",
    "sg:city":"Ditzingen",
    "sg:phone":"+49 7156/8765",
    "sg:postcode":"71254",
    "sg:province":"Baden-W\u00fcrttemberg",
    "wof:name":"Kompressor-zentrale Albert Reinkunz",
    "wof:placetype":"venue"
},
  "geometry": {"coordinates":[9.044921,48.834297],"type":"Point"}
}