{
  "type": "Feature",
  "properties": {
    "iso:country":"DE",
    "sg:address":"Altenberger Str. 6",
    "sg:city":"Wetzlar",
    "sg:phone":"+49 6441/946146",
    "sg:postcode":"35576",
    "sg:province":"Hessen",
    "wof:name":"Internationaler Gideonbund In Deutschland",
    "wof:placetype":"venue"
},
  "geometry": {"coordinates":[8.49106884,50.5592384338],"type":"Point"}
}