{
  "type": "Feature",
  "properties": {
    "iso:country":"DE",
    "sg:address":"M\u00fchlenstr. 14",
    "sg:city":"Uedem",
    "sg:phone":"+49 2825/437",
    "sg:postcode":"47589",
    "sg:province":"Nordrhein-Westfalen",
    "wof:name":"Georg Van Beek",
    "wof:placetype":"venue"
},
  "geometry": {"coordinates":[6.273554,51.669064],"type":"Point"}
}