{
  "type": "Feature",
  "properties": {
    "iso:country":"DE",
    "sg:address":"D\u00fcrerweg 38",
    "sg:city":"Rheine",
    "sg:phone":"+49 5971/54265",
    "sg:postcode":"48431",
    "sg:province":"Nordrhein-Westfalen",
    "wof:name":"Wolfgang Frieling Ingenieur",
    "wof:placetype":"venue"
},
  "geometry": {"coordinates":[7.451613903,52.2660064697],"type":"Point"}
}