{
  "type": "Feature",
  "properties": {
    "iso:country":"DE",
    "sg:address":"Ortsstr. 16",
    "sg:city":"M\u00fchlingen",
    "sg:phone":"+49 7775/920063",
    "sg:postcode":"78357",
    "sg:province":"Baden-W\u00fcrttemberg",
    "wof:name":"K.-h. Paul Mausini",
    "wof:placetype":"venue"
},
  "geometry": {"coordinates":[9.0406389236,47.9142608643],"type":"Point"}
}