{
  "type": "Feature",
  "properties": {
    "iso:country":"DE",
    "sg:address":"Sch\u00f6mberger Str. 8",
    "sg:city":"Pforzheim",
    "sg:phone":"+49 7231/74192",
    "sg:postcode":"75180",
    "sg:province":"Baden-W\u00fcrttemberg",
    "wof:name":"H. Bernegger",
    "wof:placetype":"venue"
},
  "geometry": {"coordinates":[8.6631240845,48.8538856506],"type":"Point"}
}