{
  "type": "Feature",
  "properties": {
    "iso:country":"DE",
    "sg:address":"Am Alten Gymnasium 12",
    "sg:city":"Neuruppin",
    "sg:postcode":"16816",
    "sg:province":"Brandenburg",
    "wof:name":"Agens Werbung \u00d6ffentlichkeits- Arbeit Neue Medien",
    "wof:placetype":"venue"
},
  "geometry": {"coordinates":[12.8069753647,52.9243011475],"type":"Point"}
}