{
  "type": "Feature",
  "properties": {
    "iso:country":"DE",
    "sg:address":"Lehestener Str. 1",
    "sg:city":"Tschirn",
    "sg:phone":"+49 9268/91170",
    "sg:postcode":"96367",
    "sg:province":"Bayern",
    "wof:name":"S. Str\u00f6hlein",
    "wof:placetype":"venue"
},
  "geometry": {"coordinates":[11.4498548508,50.3968086243],"type":"Point"}
}