{
  "type": "Feature",
  "properties": {
    "iso:country":"DE",
    "sg:address":"Kirchplatz 5",
    "sg:city":"Traunstein",
    "sg:phone":"+49 861/2763",
    "sg:postcode":"83278",
    "sg:province":"Bayern",
    "wof:name":"Franz Hartl",
    "wof:placetype":"venue"
},
  "geometry": {"coordinates":[12.628798,47.860447],"type":"Point"}
}