{
  "type": "Feature",
  "properties": {
    "iso:country":"DE",
    "sg:address":"Imkerweg 6",
    "sg:city":"Mosbach",
    "sg:phone":"+49 6267/776",
    "sg:postcode":"74821",
    "sg:province":"Baden-W\u00fcrttemberg",
    "wof:name":"M. Reinmuth Gmbh",
    "wof:placetype":"venue"
},
  "geometry": {"coordinates":[9.162195,49.41597],"type":"Point"}
}