{
  "type": "Feature",
  "properties": {
    "iso:country":"DE",
    "sg:city":"D\u00e4nischenhagen",
    "sg:phone":"+49 4349/8181",
    "sg:postcode":"24229",
    "sg:province":"Schleswig-Holstein",
    "wof:name":"Apotheke D\u00e4nischenhagen",
    "wof:placetype":"venue"
},
  "geometry": {"coordinates":[10.12836,54.425083],"type":"Point"}
}