{
  "type": "Feature",
  "properties": {
    "iso:country":"DE",
    "sg:address":"Dorfstr. 12 a",
    "sg:city":"Brunau",
    "sg:phone":"+49 39030/2210",
    "sg:postcode":"39624",
    "sg:province":"Sachsen-Anhalt",
    "wof:name":"Lothar Schulz",
    "wof:placetype":"venue"
},
  "geometry": {"coordinates":[11.438882,52.764019],"type":"Point"}
}