{
  "type": "Feature",
  "properties": {
    "iso:country":"DE",
    "sg:address":"Hafenstr. 10",
    "sg:city":"Essen",
    "sg:postcode":"45356",
    "sg:province":"Nordrhein-Westfalen",
    "wof:name":"Verband Deutscher Tennislehrer Vdt E.v.",
    "wof:placetype":"venue"
},
  "geometry": {"coordinates":[6.979414,51.478436],"type":"Point"}
}