{
  "type": "Feature",
  "properties": {
    "iso:country":"DE",
    "sg:address":"Blumengasse 5",
    "sg:city":"Poppenhausen",
    "sg:postcode":"36163",
    "sg:province":"Hessen",
    "wof:name":"Dr. Hans-ulrich Gruss Rechtsanwalt",
    "wof:placetype":"venue"
},
  "geometry": {"coordinates":[9.9233360291,50.5074501038],"type":"Point"}
}