{
  "type": "Feature",
  "properties": {
    "iso:country":"DE",
    "sg:address":"Nollenstr. 11a",
    "sg:city":"Gengenbach",
    "sg:phone":"+49 7803/2477",
    "sg:postcode":"77723",
    "sg:province":"Baden-W\u00fcrttemberg",
    "wof:name":"Rudolf Lehmann",
    "wof:placetype":"venue"
},
  "geometry": {"coordinates":[8.0142993927,48.4069213867],"type":"Point"}
}