{
  "type": "Feature",
  "properties": {
    "iso:country":"DE",
    "sg:address":"Ehrenfeld 9 a",
    "sg:city":"Bergisch Gladbach",
    "sg:phone":"+49 2204/82822",
    "sg:postcode":"51429",
    "sg:province":"Nordrhein-Westfalen",
    "wof:name":"Ehling",
    "wof:placetype":"venue"
},
  "geometry": {"coordinates":[7.2119078636,50.9654312134],"type":"Point"}
}