{
  "type": "Feature",
  "properties": {
    "iso:country":"DE",
    "sg:address":"Darrtorstr. 1",
    "sg:city":"Saalfeld",
    "sg:phone":"+49 3671/461112",
    "sg:postcode":"07318",
    "sg:province":"Th\u00fcringen",
    "wof:name":"Giv Gesellschaft F\u00fcr Immobilienentwicklung",
    "wof:placetype":"venue"
},
  "geometry": {"coordinates":[11.360864,50.648632],"type":"Point"}
}