{
  "type": "Feature",
  "properties": {
    "iso:country":"DE",
    "sg:address":"Blutenburgstr. 86",
    "sg:city":"M\u00fcnchen",
    "sg:postcode":"80636",
    "sg:province":"Bayern",
    "wof:name":"Acf-makler.brd.de",
    "wof:placetype":"venue"
},
  "geometry": {"coordinates":[11.540810585,48.1499099731],"type":"Point"}
}