{
  "type": "Feature",
  "properties": {
    "iso:country":"DE",
    "sg:address":"Savignystr. 42",
    "sg:city":"Frankfurt",
    "sg:phone":"+49 69/746028",
    "sg:postcode":"60325",
    "sg:province":"Hessen",
    "wof:name":"Dr. Hilko Meyer Rechtsanwalt",
    "wof:placetype":"venue"
},
  "geometry": {"coordinates":[8.660528183,50.1131782532],"type":"Point"}
}