{
  "type": "Feature",
  "properties": {
    "iso:country":"DE",
    "sg:address":"Berenbrock 7",
    "sg:city":"L\u00fcdinghausen",
    "sg:phone":"+49 2591/792929",
    "sg:postcode":"59348",
    "sg:province":"Nordrhein-Westfalen",
    "wof:name":"Cafe Indigo",
    "wof:placetype":"venue"
},
  "geometry": {"coordinates":[7.422075,51.779846],"type":"Point"}
}