{
  "type": "Feature",
  "properties": {
    "iso:country":"DE",
    "sg:address":"Neust\u00e4dter Str. 30",
    "sg:city":"Puschendorf",
    "sg:phone":"+49 9101/90960",
    "sg:postcode":"90617",
    "sg:province":"Bayern",
    "wof:name":"Auerochs Verwaltungs Gmbh",
    "wof:placetype":"venue"
},
  "geometry": {"coordinates":[10.8268918991,49.5246925354],"type":"Point"}
}