{
  "type": "Feature",
  "properties": {
    "iso:country":"DE",
    "sg:address":"Hauptstr. 59",
    "sg:city":"Dahme",
    "sg:phone":"+49 35451/90806",
    "sg:postcode":"15936",
    "sg:province":"Brandenburg",
    "wof:name":"Manni Tours",
    "wof:placetype":"venue"
},
  "geometry": {"coordinates":[13.4263687134,51.8695335388],"type":"Point"}
}