{
  "type": "Feature",
  "properties": {
    "iso:country":"DE",
    "sg:address":"Im Bl\u00fctengarten 22",
    "sg:city":"Backnang",
    "sg:phone":"+49 7191/63130",
    "sg:postcode":"71522",
    "sg:province":"Baden-W\u00fcrttemberg",
    "wof:name":"Michael Kroll Gmbh",
    "wof:placetype":"venue"
},
  "geometry": {"coordinates":[9.4425096512,48.9385223389],"type":"Point"}
}