{
  "type": "Feature",
  "properties": {
    "iso:country":"DE",
    "sg:address":"Wilhelm-Hauff-Str. 20",
    "sg:city":"Wiesbaden",
    "sg:phone":"+49 611/843253",
    "sg:postcode":"65187",
    "sg:province":"Hessen",
    "wof:name":"Daniel Wilhelm",
    "wof:placetype":"venue"
},
  "geometry": {"coordinates":[8.2328720093,50.0688705444],"type":"Point"}
}