{
  "type": "Feature",
  "properties": {
    "iso:country":"DE",
    "sg:address":"Benzstr. 3",
    "sg:city":"Geisenhausen",
    "sg:phone":"+49 8743/2452",
    "sg:postcode":"84144",
    "sg:province":"Bayern",
    "wof:name":"Stadler Und Vogler Ingenieurb\u00fcro F\u00fcr",
    "wof:placetype":"venue"
},
  "geometry": {"coordinates":[12.2482719421,48.4795188904],"type":"Point"}
}