{
  "type": "Feature",
  "properties": {
    "iso:country":"DE",
    "sg:address":"Wachtelgarten 3",
    "sg:city":"Lippstadt",
    "sg:phone":"+49 2941/57911",
    "sg:postcode":"59557",
    "sg:province":"Nordrhein-Westfalen",
    "wof:name":"Horst Adams",
    "wof:placetype":"venue"
},
  "geometry": {"coordinates":[8.330701828,51.6702194214],"type":"Point"}
}