{
  "type": "Feature",
  "properties": {
    "iso:country":"DE",
    "sg:address":"Deinerlindenweg 1",
    "sg:city":"Einbeck",
    "sg:phone":"+49 5561/93160",
    "sg:postcode":"37574",
    "sg:province":"Niedersachsen",
    "wof:name":"Alloheim Senioren Zentrum",
    "wof:placetype":"venue"
},
  "geometry": {"coordinates":[9.862154,51.814297],"type":"Point"}
}