{
  "type": "Feature",
  "properties": {
    "iso:country":"DE",
    "sg:address":"Karl-Arnold-Str. 31",
    "sg:city":"Bedburg",
    "sg:phone":"+49 2272/7712",
    "sg:postcode":"50181",
    "sg:province":"Nordrhein-Westfalen",
    "wof:name":"H.-p. Und R. Uerlings",
    "wof:placetype":"venue"
},
  "geometry": {"coordinates":[6.5568208694,51.0029258728],"type":"Point"}
}