{
  "type": "Feature",
  "properties": {
    "iso:country":"DE",
    "sg:address":"Wormser Str. 2",
    "sg:city":"Gr\u00fcnstadt",
    "sg:phone":"+49 6359/6315",
    "sg:postcode":"67269",
    "sg:province":"Rheinland-Pfalz",
    "wof:name":"Pillitterie Treppen- Und Metallbau Gmbh",
    "wof:placetype":"venue"
},
  "geometry": {"coordinates":[8.166809,49.581455],"type":"Point"}
}