{
  "type": "Feature",
  "properties": {
    "iso:country":"DE",
    "sg:address":"Alfred-Nobel-Str. 12",
    "sg:city":"Saarwellingen",
    "sg:phone":"+49 4968/3890090",
    "sg:postcode":"66793",
    "sg:province":"Saarland",
    "wof:name":"Ludwig Logistic Service Gmbh",
    "wof:placetype":"venue"
},
  "geometry": {"coordinates":[6.7716321945,49.362575531],"type":"Point"}
}