{
  "type": "Feature",
  "properties": {
    "iso:country":"DE",
    "sg:address":"Flethmannskamp 8",
    "sg:city":"Hamburg",
    "sg:phone":"+49 40/6032415",
    "sg:postcode":"22359",
    "sg:province":"Hamburg",
    "wof:name":"Jan Howindt Ingenieur",
    "wof:placetype":"venue"
},
  "geometry": {"coordinates":[10.1586532593,53.6504821777],"type":"Point"}
}