{
  "type": "Feature",
  "properties": {
    "iso:country":"DE",
    "sg:address":"Deverweg 13",
    "sg:city":"Papenburg",
    "sg:phone":"+49 4961/941606",
    "sg:postcode":"26871",
    "sg:province":"Niedersachsen",
    "wof:name":"Restaurant Megaron",
    "wof:placetype":"venue"
},
  "geometry": {"coordinates":[7.3876729012,53.0844650269],"type":"Point"}
}