{
  "type": "Feature",
  "properties": {
    "iso:country":"DE",
    "sg:address":"Kirchberg 4",
    "sg:city":"Pfaffenhofen",
    "sg:phone":"+49 8441/76466",
    "sg:postcode":"85276",
    "sg:province":"Bayern",
    "wof:name":"Flowershop Mooiman Gmbh",
    "wof:placetype":"venue"
},
  "geometry": {"coordinates":[11.561476,48.567711],"type":"Point"}
}