{
  "type": "Feature",
  "properties": {
    "iso:country":"DE",
    "sg:address":"Franz\u00f6sische Str. 16",
    "sg:city":"M\u00fcncheberg",
    "sg:phone":"+49 33432/236",
    "sg:postcode":"15374",
    "sg:province":"Brandenburg",
    "wof:name":"Horst Frech",
    "wof:placetype":"venue"
},
  "geometry": {"coordinates":[14.1373567581,52.5037002563],"type":"Point"}
}