{
  "type": "Feature",
  "properties": {
    "iso:country":"DE",
    "sg:address":"Hinterm Dorfe 9",
    "sg:city":"Bad M\u00fcnder",
    "sg:postcode":"31848",
    "sg:province":"Niedersachsen",
    "wof:name":"Dr. Gudjon Kristinsson Tierarzt",
    "wof:placetype":"venue"
},
  "geometry": {"coordinates":[9.3884716034,52.2352218628],"type":"Point"}
}