{
  "type": "Feature",
  "properties": {
    "iso:country":"DE",
    "sg:address":"L\u00f6\u00dfniger Str. 72",
    "sg:city":"Leipzig",
    "sg:postcode":"04275",
    "sg:province":"Sachsen",
    "wof:name":"Lulu Immobilien-vermietung Verkauf Und Handel Mit",
    "wof:placetype":"venue"
},
  "geometry": {"coordinates":[12.3813991547,51.3155288696],"type":"Point"}
}