{
  "type": "Feature",
  "properties": {
    "iso:country":"DE",
    "sg:address":"Neckargartacher Str. 45",
    "sg:city":"Heilbronn",
    "sg:phone":"+49 7131/43764",
    "sg:postcode":"74080",
    "sg:province":"Baden-W\u00fcrttemberg",
    "wof:name":"Carl Gauss Nachf.",
    "wof:placetype":"venue"
},
  "geometry": {"coordinates":[9.193248,49.144623],"type":"Point"}
}