{
  "type": "Feature",
  "properties": {
    "iso:country":"DE",
    "sg:address":"Gartenschauweg 20",
    "sg:city":"Mannheim",
    "sg:phone":"+49 621/411463",
    "sg:postcode":"68165",
    "sg:province":"Baden-W\u00fcrttemberg",
    "wof:name":"Pf\u00e4lzer Weinstube",
    "wof:placetype":"venue"
},
  "geometry": {"coordinates":[8.4989299774,49.4798583984],"type":"Point"}
}