{
  "type": "Feature",
  "properties": {
    "iso:country":"DE",
    "sg:address":"R\u00f6merstr. 20",
    "sg:city":"Oggelshausen",
    "sg:phone":"+49 7582/8160",
    "sg:postcode":"88422",
    "sg:province":"Baden-W\u00fcrttemberg",
    "wof:name":"R. Wild",
    "wof:placetype":"venue"
},
  "geometry": {"coordinates":[9.65047,48.068359],"type":"Point"}
}