{
  "type": "Feature",
  "properties": {
    "iso:country":"DE",
    "sg:address":"L\u00f6bstedter Stra\u00dfe 101",
    "sg:city":"Jena",
    "sg:phone":"+49 3641/487460",
    "sg:postcode":"07749",
    "sg:province":"Th\u00fcringen",
    "wof:name":"New Media Lab Gmbh",
    "wof:placetype":"venue"
},
  "geometry": {"coordinates":[11.610792,50.946831],"type":"Point"}
}