{
  "type": "Feature",
  "properties": {
    "iso:country":"DE",
    "sg:address":"Baumschulenstr. 7",
    "sg:city":"Berlin",
    "sg:phone":"+49 30/5329123",
    "sg:postcode":"12437",
    "sg:province":"Berlin",
    "wof:name":"Zum Deutschen Pilsner",
    "wof:placetype":"venue"
},
  "geometry": {"coordinates":[13.4909000397,52.468536377],"type":"Point"}
}