{
  "type": "Feature",
  "properties": {
    "iso:country":"DE",
    "sg:address":"Rhan 9",
    "sg:city":"Sch\u00f6nthal",
    "sg:phone":"+49 9978/212",
    "sg:postcode":"93488",
    "sg:province":"Bayern",
    "wof:name":"J. Bruckmayer & Sohn",
    "wof:placetype":"venue"
},
  "geometry": {"coordinates":[12.617264,49.336113],"type":"Point"}
}