{
  "type": "Feature",
  "properties": {
    "iso:country":"DE",
    "sg:address":"Bahnhofstra\u00dfe 17a",
    "sg:city":"Merseburg",
    "sg:postcode":"06217",
    "sg:province":"Sachsen-Anhalt",
    "wof:name":"Tagesklinik Am Tivoli",
    "wof:placetype":"venue"
},
  "geometry": {"coordinates":[11.993618,51.356842],"type":"Point"}
}