{
  "type": "Feature",
  "properties": {
    "iso:country":"DE",
    "sg:address":"Poghausen",
    "sg:city":"Uplengen",
    "sg:phone":"+49 4956/1231",
    "sg:postcode":"26670",
    "sg:province":"Niedersachsen",
    "wof:name":"Ubbo Ostendorf",
    "wof:placetype":"venue"
},
  "geometry": {"coordinates":[7.7813501358,53.3376502991],"type":"Point"}
}