{
  "type": "Feature",
  "properties": {
    "iso:country":"DE",
    "sg:address":"Bahnweg 11",
    "sg:city":"Pfarrkirchen",
    "sg:phone":"+49 8561/6271",
    "sg:postcode":"84347",
    "sg:province":"Bayern",
    "wof:name":"Pfeffereder Glasbau Glashandel Gmbh",
    "wof:placetype":"venue"
},
  "geometry": {"coordinates":[12.9358568192,48.4285354614],"type":"Point"}
}