{
  "type": "Feature",
  "properties": {
    "iso:country":"DE",
    "sg:address":"Auenstr. 6",
    "sg:city":"Garmisch-Partenkirchen",
    "sg:phone":"+49 8821/770",
    "sg:postcode":"82467",
    "sg:province":"Bayern",
    "wof:name":"Krankenhausvollapotheke Im Kreiskrankenhaus",
    "wof:placetype":"venue"
},
  "geometry": {"coordinates":[11.127884,47.484146],"type":"Point"}
}