{
  "type": "Feature",
  "properties": {
    "iso:country":"DE",
    "sg:address":"Schlo\u00dfplatz 9",
    "sg:city":"Meiningen",
    "sg:phone":"+49 3693/2351",
    "sg:postcode":"98617",
    "sg:province":"Th\u00fcringen",
    "wof:name":"Hans Lutz",
    "wof:placetype":"venue"
},
  "geometry": {"coordinates":[10.412315,50.569691],"type":"Point"}
}