{
  "type": "Feature",
  "properties": {
    "iso:country":"DE",
    "sg:address":"Parkstr. 250",
    "sg:city":"L\u00fcdenscheid",
    "sg:phone":"+49 2351/79145",
    "sg:postcode":"58515",
    "sg:province":"Nordrhein-Westfalen",
    "wof:name":"Ora-werbung Theo Rademacher",
    "wof:placetype":"venue"
},
  "geometry": {"coordinates":[7.5726690292,51.2129173279],"type":"Point"}
}