{
  "type": "Feature",
  "properties": {
    "iso:country":"DE",
    "sg:address":"Ostheimer Str. 200",
    "sg:city":"K\u00f6ln",
    "sg:phone":"+49 221/891341",
    "sg:postcode":"51107",
    "sg:province":"Nordrhein-Westfalen",
    "wof:name":"Detlev Schneider Steuerberater",
    "wof:placetype":"venue"
},
  "geometry": {"coordinates":[7.0376849174,50.9303016663],"type":"Point"}
}