{
  "type": "Feature",
  "properties": {
    "iso:country":"DE",
    "sg:address":"Hauptstr. 9",
    "sg:city":"Malterdingen",
    "sg:phone":"+49 7644/4001",
    "sg:postcode":"79364",
    "sg:province":"Baden-W\u00fcrttemberg",
    "wof:name":"G. Schmidt Immobilienmakler",
    "wof:placetype":"venue"
},
  "geometry": {"coordinates":[7.7971520424,48.1629600525],"type":"Point"}
}