{
  "type": "Feature",
  "properties": {
    "iso:country":"DE",
    "sg:address":"Vorstadtstr. 35s",
    "sg:city":"Saarbr\u00fccken",
    "sg:phone":"+49 681/927060",
    "sg:postcode":"66117",
    "sg:province":"Saarland",
    "wof:name":"Willy Pabst Gmbh",
    "wof:placetype":"venue"
},
  "geometry": {"coordinates":[6.9866600037,49.2314910889],"type":"Point"}
}