{
  "type": "Feature",
  "properties": {
    "iso:country":"DE",
    "sg:address":"Vordere Str. 44",
    "sg:city":"L\u00fcgde",
    "sg:phone":"+49 5281/7358",
    "sg:postcode":"32676",
    "sg:province":"Nordrhein-Westfalen",
    "wof:name":"M. Z\u00fcnkler",
    "wof:placetype":"venue"
},
  "geometry": {"coordinates":[9.2462425232,51.9562110901],"type":"Point"}
}