{
  "type": "Feature",
  "properties": {
    "iso:country":"DE",
    "sg:address":"Frankenstr 43",
    "sg:city":"Gro\u00dfrinderfeld",
    "sg:phone":"+49 9349/929190",
    "sg:postcode":"97950",
    "sg:province":"Baden-W\u00fcrttemberg",
    "wof:name":"Retec",
    "wof:placetype":"venue"
},
  "geometry": {"coordinates":[9.734961,49.662308],"type":"Point"}
}