{
  "type": "Feature",
  "properties": {
    "iso:country":"DE",
    "sg:address":"Marktstr. 2",
    "sg:city":"Olfen",
    "sg:phone":"+49 2595/9499",
    "sg:postcode":"59399",
    "sg:province":"Nordrhein-Westfalen",
    "wof:name":"Christa Huesmann",
    "wof:placetype":"venue"
},
  "geometry": {"coordinates":[7.3795962334,51.7074737549],"type":"Point"}
}