{
  "type": "Feature",
  "properties": {
    "iso:country":"DE",
    "sg:address":"Tulpenstr. 3 a",
    "sg:city":"Gro\u00dfmaischeid",
    "sg:phone":"+49 2689/98520",
    "sg:postcode":"56276",
    "sg:province":"Rheinland-Pfalz",
    "wof:name":"Klaus Spohr Electronic Gmbh",
    "wof:placetype":"venue"
},
  "geometry": {"coordinates":[7.6303710938,50.5031204224],"type":"Point"}
}