{
  "type": "Feature",
  "properties": {
    "iso:country":"DE",
    "sg:address":"Dorfstr. 15",
    "sg:city":"D\u00f6bern",
    "sg:postcode":"03159",
    "sg:province":"Brandenburg",
    "wof:name":"Ev. Kirche",
    "wof:placetype":"venue"
},
  "geometry": {"coordinates":[14.6182031631,51.6042976379],"type":"Point"}
}