{
  "type": "Feature",
  "properties": {
    "iso:country":"DE",
    "sg:address":"Altheimerstra\u00dfe 42",
    "sg:city":"M\u00fcnster",
    "sg:postcode":"64839",
    "sg:province":"Hessen",
    "wof:name":"Unterwasserspass.de",
    "wof:placetype":"venue"
},
  "geometry": {"coordinates":[8.862949,49.927212],"type":"Point"}
}