{
  "type": "Feature",
  "properties": {
    "iso:country":"DE",
    "sg:address":"Postfach 6",
    "sg:city":"Bornh\u00f6ved",
    "sg:phone":"+49 4323/6567",
    "sg:postcode":"24617",
    "sg:province":"Schleswig-Holstein",
    "wof:name":"Gemeindeb\u00fccherei",
    "wof:placetype":"venue"
},
  "geometry": {"coordinates":[10.22752,54.070522],"type":"Point"}
}