{
  "type": "Feature",
  "properties": {
    "iso:country":"DE",
    "sg:address":"Parkstr. 25",
    "sg:city":"Altenstadt",
    "sg:phone":"+49 6047/1055",
    "sg:postcode":"63674",
    "sg:province":"Hessen",
    "wof:name":"Hannelore Behrens",
    "wof:placetype":"venue"
},
  "geometry": {"coordinates":[8.9291763306,50.2686729431],"type":"Point"}
}