{
  "type": "Feature",
  "properties": {
    "iso:country":"DE",
    "sg:address":"Uelzener Str. 120",
    "sg:city":"Lueneburg",
    "sg:phone":"+49 4941/317250",
    "sg:postcode":"21335",
    "sg:province":"Niedersachsen",
    "wof:name":"Landeskrankenhilfe Vvag",
    "wof:placetype":"venue"
},
  "geometry": {"coordinates":[10.405745,53.221931],"type":"Point"}
}