{
  "type": "Feature",
  "properties": {
    "iso:country":"DE",
    "sg:address":"Lyoner Str. 23",
    "sg:city":"Frankfurt",
    "sg:phone":"+49 69/6611",
    "sg:postcode":"60528",
    "sg:province":"Hessen",
    "wof:name":"Schoko Schokoladen Und S\u00fc\u00dfwaren Gmbh",
    "wof:placetype":"venue"
},
  "geometry": {"coordinates":[8.6260757446,50.0782241821],"type":"Point"}
}