{
  "type": "Feature",
  "properties": {
    "iso:country":"DE",
    "sg:address":"Friedrich-Ebert-Str. 14",
    "sg:city":"Essen",
    "sg:phone":"+49 201/245440",
    "sg:postcode":"45127",
    "sg:province":"Nordrhein-Westfalen",
    "wof:name":"K\u00f6tter Personal Service Verwaltungs- Gmbh",
    "wof:placetype":"venue"
},
  "geometry": {"coordinates":[7.0073690414,51.4587287903],"type":"Point"}
}