{
  "type": "Feature",
  "properties": {
    "iso:country":"DE",
    "sg:address":"Residenzstr. 2",
    "sg:city":"M\u00fcnchen",
    "sg:phone":"+49 89/2423770",
    "sg:postcode":"80333",
    "sg:province":"Bayern",
    "wof:name":"3i Europartners Iii Verwaltungs Gmbh & Co. Kg",
    "wof:placetype":"venue"
},
  "geometry": {"coordinates":[11.577548027,48.1393966675],"type":"Point"}
}