{
  "type": "Feature",
  "properties": {
    "iso:country":"DE",
    "sg:address":"Seekamp 2",
    "sg:city":"L\u00fcrschau",
    "sg:phone":"+49 4621/41128",
    "sg:postcode":"24850",
    "sg:province":"Schleswig-Holstein",
    "wof:name":"W\u00fcrttembergische Versicherung Ag",
    "wof:placetype":"venue"
},
  "geometry": {"coordinates":[9.4959192276,54.5395851135],"type":"Point"}
}