{
  "type": "Feature",
  "properties": {
    "iso:country":"DE",
    "sg:address":"D\u00f6rflinger Str. 2",
    "sg:city":"Gailingen",
    "sg:phone":"+49 7734/6687",
    "sg:postcode":"78262",
    "sg:province":"Baden-W\u00fcrttemberg",
    "wof:name":"H. Restle",
    "wof:placetype":"venue"
},
  "geometry": {"coordinates":[8.748045,47.69862],"type":"Point"}
}