{
  "type": "Feature",
  "properties": {
    "iso:country":"DE",
    "sg:address":"Winsbergring 12",
    "sg:city":"Hamburg",
    "sg:phone":"+49 40/8537520",
    "sg:postcode":"22525",
    "sg:province":"Hamburg",
    "wof:name":"Johs. Marth Gmbh",
    "wof:placetype":"venue"
},
  "geometry": {"coordinates":[9.9154586792,53.5747108459],"type":"Point"}
}