{
  "type": "Feature",
  "properties": {
    "iso:country":"DE",
    "sg:address":"Hainwiesenweg 7",
    "sg:city":"Lautertal",
    "sg:phone":"+49 6643/238",
    "sg:postcode":"36369",
    "sg:province":"Hessen",
    "wof:name":"K. Etling",
    "wof:placetype":"venue"
},
  "geometry": {"coordinates":[9.3115110397,50.5887374878],"type":"Point"}
}