{
  "type": "Feature",
  "properties": {
    "iso:country":"DE",
    "sg:address":"Schafstallstr 27",
    "sg:city":"Reutlingen",
    "sg:phone":"+49 7121/230727",
    "sg:postcode":"72762",
    "sg:province":"Baden-W\u00fcrttemberg",
    "wof:name":"Albert Tilmann Gmbh",
    "wof:placetype":"venue"
},
  "geometry": {"coordinates":[9.190373,48.489685],"type":"Point"}
}