{
  "type": "Feature",
  "properties": {
    "iso:country":"DE",
    "sg:address":"Hegest\u00fcck 20",
    "sg:city":"Iserlohn",
    "sg:postcode":"58640",
    "sg:province":"Nordrhein-Westfalen",
    "wof:name":"Mva-projektgesellschaft M\u00fcllverbrennung Osnabr\u00fcck Mbh",
    "wof:placetype":"venue"
},
  "geometry": {"coordinates":[7.705893,51.427834],"type":"Point"}
}