{
  "type": "Feature",
  "properties": {
    "iso:country":"DE",
    "sg:address":"Boomberge 20",
    "sg:city":"Harsewinkel",
    "sg:phone":"+49 5247/2336",
    "sg:postcode":"33428",
    "sg:province":"Nordrhein-Westfalen",
    "wof:name":"Peter Heitmann",
    "wof:placetype":"venue"
},
  "geometry": {"coordinates":[8.2247982025,51.950378418],"type":"Point"}
}