{
  "type": "Feature",
  "properties": {
    "iso:country":"DE",
    "sg:address":"Ansbacher Str. 16",
    "sg:city":"Weihenzell",
    "sg:postcode":"91629",
    "sg:province":"Bayern",
    "wof:name":"Erich Volland",
    "wof:placetype":"venue"
},
  "geometry": {"coordinates":[10.627669,49.355785],"type":"Point"}
}