{
  "type": "Feature",
  "properties": {
    "iso:country":"DE",
    "sg:address":"Wohldamm 21",
    "sg:city":"Helmstedt",
    "sg:phone":"+49 5351/31347",
    "sg:postcode":"38350",
    "sg:province":"Niedersachsen",
    "wof:name":"Reiner K\u00f6hler",
    "wof:placetype":"venue"
},
  "geometry": {"coordinates":[11.002702713,52.2292022705],"type":"Point"}
}