{
  "type": "Feature",
  "properties": {
    "iso:country":"DE",
    "sg:address":"Lammstr. 35",
    "sg:city":"Kornwestheim",
    "sg:phone":"+49 7154/21965",
    "sg:postcode":"70806",
    "sg:province":"Baden-W\u00fcrttemberg",
    "wof:name":"Stuber & Conradt Gmbh",
    "wof:placetype":"venue"
},
  "geometry": {"coordinates":[9.190545,48.862747],"type":"Point"}
}