{
  "type": "Feature",
  "properties": {
    "iso:country":"DE",
    "sg:address":"Bei der Rose 9",
    "sg:city":"Kempten",
    "sg:phone":"+49 831/23619",
    "sg:postcode":"87435",
    "sg:province":"Bayern",
    "wof:name":"Cafe Am Kornhaus",
    "wof:placetype":"venue"
},
  "geometry": {"coordinates":[10.30961,47.728409],"type":"Point"}
}