{
  "type": "Feature",
  "properties": {
    "iso:country":"DE",
    "sg:address":"Bahnhofstr. 51",
    "sg:city":"Heidelberg",
    "sg:phone":"+49 6221/165103",
    "sg:postcode":"69115",
    "sg:province":"Baden-W\u00fcrttemberg",
    "wof:name":"Rud. W. Seifert",
    "wof:placetype":"venue"
},
  "geometry": {"coordinates":[8.686621666,49.4051704407],"type":"Point"}
}