{
  "type": "Feature",
  "properties": {
    "iso:country":"DE",
    "sg:address":"Herrenstr. 20",
    "sg:city":"Cochem",
    "sg:phone":"+49 2671/3158",
    "sg:postcode":"56812",
    "sg:province":"Rheinland-Pfalz",
    "wof:name":"L. H\u00fcrter Glas- Und Porzellanwaren",
    "wof:placetype":"venue"
},
  "geometry": {"coordinates":[7.1664848328,50.1444778442],"type":"Point"}
}