{
  "type": "Feature",
  "properties": {
    "iso:country":"DE",
    "sg:address":"Prinzenstr. 14",
    "sg:city":"Bielefeld",
    "sg:phone":"+49 521/60457",
    "sg:postcode":"33602",
    "sg:province":"Nordrhein-Westfalen",
    "wof:name":"Conterra Immobilien- Und Bautr\u00e4ger Gesellschaft Mbh",
    "wof:placetype":"venue"
},
  "geometry": {"coordinates":[8.542251,52.026863],"type":"Point"}
}