{
  "type": "Feature",
  "properties": {
    "iso:country":"DE",
    "sg:address":"Bautzener Str. 28",
    "sg:city":"Wittichenau",
    "sg:phone":"+49 35725/71317",
    "sg:postcode":"02997",
    "sg:province":"Sachsen",
    "wof:name":"Pizzeria Roma",
    "wof:placetype":"venue"
},
  "geometry": {"coordinates":[14.2461080551,51.3840026855],"type":"Point"}
}