{
  "type": "Feature",
  "properties": {
    "iso:country":"DE",
    "sg:address":"Kruppstra\u00dfe 46",
    "sg:city":"Stuttgart",
    "sg:phone":"+49 711",
    "sg:postcode":"70469",
    "sg:province":"Baden-W\u00fcrttemberg",
    "wof:name":"Hacker Ag",
    "wof:placetype":"venue"
},
  "geometry": {"coordinates":[9.1745786667,48.8176956177],"type":"Point"}
}