{
  "type": "Feature",
  "properties": {
    "iso:country":"DE",
    "sg:address":"Donauw\u00f6rther Str. 117 A",
    "sg:city":"Augsburg",
    "sg:phone":"+49 821/412515",
    "sg:postcode":"86154",
    "sg:province":"Bayern",
    "wof:name":"Ludwig Gerstlauer",
    "wof:placetype":"venue"
},
  "geometry": {"coordinates":[10.881234169,48.3904571533],"type":"Point"}
}