{
  "type": "Feature",
  "properties": {
    "iso:country":"DE",
    "sg:address":"Scho\u00dfbergstr. 19",
    "sg:city":"Wiesbaden",
    "sg:phone":"+49 4961/1928430",
    "sg:postcode":"65201",
    "sg:province":"Hessen",
    "wof:name":"Gesellschaft F\u00dcr Antriebstechnik Mbh",
    "wof:placetype":"venue"
},
  "geometry": {"coordinates":[8.209656,50.045673],"type":"Point"}
}