{
  "type": "Feature",
  "properties": {
    "iso:country":"DE",
    "sg:address":"Brotmarkt 3",
    "sg:city":"F\u00fcssen",
    "sg:phone":"+49 8362/5250",
    "sg:postcode":"87629",
    "sg:province":"Bayern",
    "wof:name":"F. \u00dcn",
    "wof:placetype":"venue"
},
  "geometry": {"coordinates":[10.7001028061,47.5671463013],"type":"Point"}
}