{
  "type": "Feature",
  "properties": {
    "iso:country":"DE",
    "sg:address":"Damm 25",
    "sg:city":"Schladen",
    "sg:phone":"+49 5335/6567",
    "sg:postcode":"38315",
    "sg:province":"Niedersachsen",
    "wof:name":"G. Riechel",
    "wof:placetype":"venue"
},
  "geometry": {"coordinates":[10.5405044556,52.0219993591],"type":"Point"}
}