{
  "type": "Feature",
  "properties": {
    "iso:country":"DE",
    "sg:address":"Reinhold-Schneider-Str. 57",
    "sg:city":"Freiburg",
    "sg:phone":"+49 761/60577",
    "sg:postcode":"79117",
    "sg:province":"Baden-W\u00fcrttemberg",
    "wof:name":"Reinhard Klein",
    "wof:placetype":"venue"
},
  "geometry": {"coordinates":[7.9025521278,47.9830055237],"type":"Point"}
}