{
  "type": "Feature",
  "properties": {
    "iso:country":"DE",
    "sg:address":"Wohlers Allee 36",
    "sg:city":"Hamburg",
    "sg:phone":"+49 40/4302990",
    "sg:postcode":"22767",
    "sg:province":"Hamburg",
    "wof:name":"Zeykon Im- Und Export Warenhandels Gmbh",
    "wof:placetype":"venue"
},
  "geometry": {"coordinates":[9.9550933838,53.5590324402],"type":"Point"}
}