{
  "type": "Feature",
  "properties": {
    "iso:country":"DE",
    "sg:address":"Gladbacher Str. 35",
    "sg:city":"Langenfeld",
    "sg:phone":"+49 2173/21856",
    "sg:postcode":"40764",
    "sg:province":"Nordrhein-Westfalen",
    "wof:name":"Adolf Ebersberger",
    "wof:placetype":"venue"
},
  "geometry": {"coordinates":[6.971152,51.115765],"type":"Point"}
}