{
  "type": "Feature",
  "properties": {
    "iso:country":"DE",
    "sg:address":"Oldenburger Str. 79 A",
    "sg:city":"Delmenhorst",
    "sg:postcode":"27753",
    "sg:province":"Niedersachsen",
    "wof:name":"Aldi Gmbh & Co. Kg",
    "wof:placetype":"venue"
},
  "geometry": {"coordinates":[8.6070814133,53.0491256714],"type":"Point"}
}