{
  "type": "Feature",
  "properties": {
    "iso:country":"DE",
    "sg:address":"Unter Greut 1",
    "sg:city":"K\u00fcssaberg",
    "sg:phone":"+49 7741/60930",
    "sg:postcode":"79790",
    "sg:province":"Baden-W\u00fcrttemberg",
    "wof:name":"Kpg-kaiser Prozesstechnik Gmbh",
    "wof:placetype":"venue"
},
  "geometry": {"coordinates":[8.272115,47.617664],"type":"Point"}
}