{
  "type": "Feature",
  "properties": {
    "iso:country":"DE",
    "sg:address":"Am Lehester Deich 32a",
    "sg:city":"Bremen",
    "sg:phone":"+49 421/270498",
    "sg:postcode":"28357",
    "sg:province":"Bremen",
    "wof:name":"G\u00fcnther Gl\u00fcckert",
    "wof:placetype":"venue"
},
  "geometry": {"coordinates":[8.9013395309,53.108165741],"type":"Point"}
}