{
  "type": "Feature",
  "properties": {
    "iso:country":"DE",
    "sg:address":"Quadtstr. 7",
    "sg:city":"M\u00f6nchengladbach",
    "sg:phone":"+49 2166/953730",
    "sg:postcode":"41189",
    "sg:province":"Nordrhein-Westfalen",
    "wof:name":"Hannelore Buchholz Rechtsanw\u00e4ltin",
    "wof:placetype":"venue"
},
  "geometry": {"coordinates":[6.412815094,51.1301612854],"type":"Point"}
}