{
  "type": "Feature",
  "properties": {
    "iso:country":"DE",
    "sg:address":"L\u00f6wengasse",
    "sg:city":"Frankfurt",
    "sg:phone":"+49 69/4692924",
    "sg:postcode":"60385",
    "sg:province":"Hessen",
    "wof:name":"Schmidt Kg",
    "wof:placetype":"venue"
},
  "geometry": {"coordinates":[8.7158946991,50.1279907227],"type":"Point"}
}