{
  "type": "Feature",
  "properties": {
    "iso:country":"DE",
    "sg:address":"Burgstr. 3",
    "sg:city":"Wuppertal",
    "sg:phone":"+49 202/455550",
    "sg:postcode":"42103",
    "sg:province":"Nordrhein-Westfalen",
    "wof:name":"Burgsch\u00e4nke",
    "wof:placetype":"venue"
},
  "geometry": {"coordinates":[7.1472392082,51.2574157715],"type":"Point"}
}