{
  "type": "Feature",
  "properties": {
    "iso:country":"DE",
    "sg:address":"Clara-Zetkin-Str. 16",
    "sg:city":"Zwickau",
    "sg:phone":"+49 375/300189",
    "sg:postcode":"08058",
    "sg:province":"Sachsen",
    "wof:name":"Arnd Meyer",
    "wof:placetype":"venue"
},
  "geometry": {"coordinates":[12.48926,50.727493],"type":"Point"}
}