{
  "type": "Feature",
  "properties": {
    "iso:country":"DE",
    "sg:address":"Rothenbaumchaussee 161-163",
    "sg:city":"Hamburg",
    "sg:postcode":"20149",
    "sg:province":"Hamburg",
    "wof:name":"Verwaltungsgesellschaft Volker Fischer Bauges. Mbh",
    "wof:placetype":"venue"
},
  "geometry": {"coordinates":[9.9885921478,53.5762023926],"type":"Point"}
}