{
  "type": "Feature",
  "properties": {
    "iso:country":"DE",
    "sg:address":"Birkenweg 3",
    "sg:city":"Pfakofen",
    "sg:phone":"+49 9451/4185",
    "sg:postcode":"93101",
    "sg:province":"Bayern",
    "wof:name":"Brigitta Holzer",
    "wof:placetype":"venue"
},
  "geometry": {"coordinates":[12.2182540894,48.8591918945],"type":"Point"}
}