{
  "type": "Feature",
  "properties": {
    "iso:country":"DE",
    "sg:address":"Rh\u00f6nstr. 2",
    "sg:city":"Ebersburg",
    "sg:phone":"+49 6656/426",
    "sg:postcode":"36157",
    "sg:province":"Hessen",
    "wof:name":"Lothar Sch\u00f6n",
    "wof:placetype":"venue"
},
  "geometry": {"coordinates":[9.8011741638,50.4859886169],"type":"Point"}
}