{
  "type": "Feature",
  "properties": {
    "iso:country":"DE",
    "sg:address":"Altenrodaer Str.",
    "sg:city":"Bad Bibra",
    "sg:phone":"+49 34465/20323",
    "sg:postcode":"06647",
    "sg:province":"Sachsen-Anhalt",
    "wof:name":"J\u00fcrgen Grunert Gmbh",
    "wof:placetype":"venue"
},
  "geometry": {"coordinates":[11.584175,51.21336],"type":"Point"}
}