{
  "type": "Feature",
  "properties": {
    "iso:country":"DE",
    "sg:address":"Hafenstr. 5",
    "sg:city":"Laboe",
    "sg:phone":"+49 4943/431225",
    "sg:postcode":"24235",
    "sg:province":"Schleswig-Holstein",
    "wof:name":"Meyborn Segelmacherei",
    "wof:placetype":"venue"
},
  "geometry": {"coordinates":[10.219774,54.403034],"type":"Point"}
}