{
  "type": "Feature",
  "properties": {
    "iso:country":"DE",
    "sg:address":"Wiesenweg 5",
    "sg:city":"Bebra",
    "sg:phone":"+49 4966/2292990",
    "sg:postcode":"36179",
    "sg:province":"Hessen",
    "wof:name":"Ullrich Bad-design Gmbh",
    "wof:placetype":"venue"
},
  "geometry": {"coordinates":[9.7973041534,50.9615364075],"type":"Point"}
}