{
  "type": "Feature",
  "properties": {
    "iso:country":"DE",
    "sg:address":"Radolfzeller Str. 56",
    "sg:city":"Allensbach",
    "sg:phone":"+49 7533/1611",
    "sg:postcode":"78476",
    "sg:province":"Baden-W\u00fcrttemberg",
    "wof:name":"Meco Energie-kollektoren Gmbh",
    "wof:placetype":"venue"
},
  "geometry": {"coordinates":[9.058706,47.71912],"type":"Point"}
}