{
  "type": "Feature",
  "properties": {
    "iso:country":"DE",
    "sg:address":"Br\u00fcckenstr. 8",
    "sg:city":"Obersulm",
    "sg:phone":"+49 7134/7060",
    "sg:postcode":"74182",
    "sg:province":"Baden-W\u00fcrttemberg",
    "wof:name":"Inge Planke",
    "wof:placetype":"venue"
},
  "geometry": {"coordinates":[9.3578538895,49.1368331909],"type":"Point"}
}