{
  "type": "Feature",
  "properties": {
    "iso:country":"DE",
    "sg:address":"Kirchr\u00f6der Str. 10",
    "sg:city":"Hannover",
    "sg:phone":"+49 511/559758",
    "sg:postcode":"30625",
    "sg:province":"Niedersachsen",
    "wof:name":"Kurt Oppermann Steuerberater",
    "wof:placetype":"venue"
},
  "geometry": {"coordinates":[9.7895307541,52.3717651367],"type":"Point"}
}