{
  "type": "Feature",
  "properties": {
    "iso:country":"DE",
    "sg:address":"K\u00f6nigssee",
    "sg:city":"Sch\u00f6nau",
    "sg:phone":"+49 8652/63007",
    "sg:postcode":"83471",
    "sg:province":"Bayern",
    "wof:name":"Alpengastst\u00e4tte Saletalm",
    "wof:placetype":"venue"
},
  "geometry": {"coordinates":[12.9519577026,47.6141929626],"type":"Point"}
}