{
  "type": "Feature",
  "properties": {
    "iso:country":"DE",
    "sg:address":"Forchheimer 8",
    "sg:city":"Rheinstetten",
    "sg:phone":"+49 7242/700671",
    "sg:postcode":"76287",
    "sg:province":"Baden-W\u00fcrttemberg",
    "wof:name":"Denario De Comodo",
    "wof:placetype":"venue"
},
  "geometry": {"coordinates":[8.295262,48.960068],"type":"Point"}
}