{
  "type": "Feature",
  "properties": {
    "iso:country":"DE",
    "sg:address":"Columbusstr. 96",
    "sg:city":"Mannheim",
    "sg:phone":"+49 621/735687",
    "sg:postcode":"68309",
    "sg:province":"Baden-W\u00fcrttemberg",
    "wof:name":"Pizzeria Palermo",
    "wof:placetype":"venue"
},
  "geometry": {"coordinates":[8.5285205841,49.5132255554],"type":"Point"}
}