{
  "type": "Feature",
  "properties": {
    "iso:country":"DE",
    "sg:address":"Neumarkt 1",
    "sg:city":"Hoyerswerda",
    "sg:phone":"+49 3571/426504",
    "sg:postcode":"02977",
    "sg:province":"Sachsen",
    "wof:name":"Bausparkasse Schw\u00e4bisch Hall Ag",
    "wof:placetype":"venue"
},
  "geometry": {"coordinates":[14.24033,51.439007],"type":"Point"}
}