{
  "type": "Feature",
  "properties": {
    "iso:country":"DE",
    "sg:address":"Keplerstr. 5-7",
    "sg:city":"Langenhagen",
    "sg:phone":"+49 511/7260930",
    "sg:postcode":"30853",
    "sg:province":"Niedersachsen",
    "wof:name":"B\u00fcrotec Gmbh",
    "wof:placetype":"venue"
},
  "geometry": {"coordinates":[9.731711,52.456879],"type":"Point"}
}