{
  "type": "Feature",
  "properties": {
    "iso:country":"DE",
    "sg:address":"Beindstr. 33",
    "sg:city":"Heddesheim",
    "sg:phone":"+49 6203/42764",
    "sg:postcode":"68542",
    "sg:province":"Baden-W\u00fcrttemberg",
    "wof:name":"Gottlieb Kr\u00e4mer",
    "wof:placetype":"venue"
},
  "geometry": {"coordinates":[8.603441,49.507244],"type":"Point"}
}