{
  "type": "Feature",
  "properties": {
    "iso:country":"DE",
    "sg:address":"Odenwaldstr. 27",
    "sg:city":"Otzberg",
    "sg:phone":"+49 6162/72344",
    "sg:postcode":"64853",
    "sg:province":"Hessen",
    "wof:name":"Georg Koch",
    "wof:placetype":"venue"
},
  "geometry": {"coordinates":[8.9151506424,49.8199272156],"type":"Point"}
}