{
  "type": "Feature",
  "properties": {
    "iso:country":"DE",
    "sg:address":"Dunantstr. 4",
    "sg:city":"Worms",
    "sg:phone":"+49 6241/76047",
    "sg:postcode":"67549",
    "sg:province":"Rheinland-Pfalz",
    "wof:name":"A. Perl-donsbach",
    "wof:placetype":"venue"
},
  "geometry": {"coordinates":[8.3107652664,49.6425056458],"type":"Point"}
}