{
  "type": "Feature",
  "properties": {
    "iso:country":"DE",
    "sg:address":"F\u00fcssener Str. 84",
    "sg:city":"Kaufbeuren",
    "sg:phone":"+49 8341/95300",
    "sg:postcode":"87600",
    "sg:province":"Bayern",
    "wof:name":"Tla Transport Logistik Allg\u00e4u Int. Speditions-gmbh",
    "wof:placetype":"venue"
},
  "geometry": {"coordinates":[10.6307811737,47.8628311157],"type":"Point"}
}