{
  "type": "Feature",
  "properties": {
    "iso:country":"DE",
    "sg:address":"Hoher Weg 4",
    "sg:city":"Hildesheim",
    "sg:phone":"+49 5121/130230",
    "sg:postcode":"31134",
    "sg:province":"Niedersachsen",
    "wof:name":"Reinald Schwerdtfeger Rechtsanwalt",
    "wof:placetype":"venue"
},
  "geometry": {"coordinates":[9.9504861832,52.1525230408],"type":"Point"}
}