{
  "type": "Feature",
  "properties": {
    "iso:country":"DE",
    "sg:address":"Gartenstr. 7",
    "sg:city":"Schonungen",
    "sg:phone":"+49 9721/58485",
    "sg:postcode":"97453",
    "sg:province":"Bayern",
    "wof:name":"H. G. Wahler",
    "wof:placetype":"venue"
},
  "geometry": {"coordinates":[10.3143196106,50.0436973572],"type":"Point"}
}