{
  "type": "Feature",
  "properties": {
    "iso:country":"DE",
    "sg:address":"Von-Liebig-Str. 7",
    "sg:city":"Neu-Ulm",
    "sg:phone":"+49 731/978020",
    "sg:postcode":"89231",
    "sg:province":"Bayern",
    "wof:name":"Ulrich Gmbh & Co. Kg",
    "wof:placetype":"venue"
},
  "geometry": {"coordinates":[10.03023,48.384747],"type":"Point"}
}