{
  "type": "Feature",
  "properties": {
    "iso:country":"DE",
    "sg:address":"R\u00f6merweg 16",
    "sg:city":"Oberndorf",
    "sg:phone":"+49 7423/86960",
    "sg:postcode":"78727",
    "sg:province":"Baden-W\u00fcrttemberg",
    "wof:name":"Karl-heinz Baier Landtechnik Verwaltungs Gmbh",
    "wof:placetype":"venue"
},
  "geometry": {"coordinates":[8.540592,48.310081],"type":"Point"}
}