{
  "type": "Feature",
  "properties": {
    "iso:country":"DE",
    "sg:address":"Heinz-Herbert-Karry-Str. 4",
    "sg:city":"Frankfurt",
    "sg:phone":"+49 69/472982",
    "sg:postcode":"60389",
    "sg:province":"Hessen",
    "wof:name":"C. J\u00e4ckel-loewenstein",
    "wof:placetype":"venue"
},
  "geometry": {"coordinates":[8.7163085938,50.1389312744],"type":"Point"}
}