{
  "type": "Feature",
  "properties": {
    "iso:country":"DE",
    "sg:address":"Platanenweg 34",
    "sg:city":"Bochum",
    "sg:phone":"+49 234/73398",
    "sg:postcode":"44801",
    "sg:province":"Nordrhein-Westfalen",
    "wof:name":"Ruth Jancik Steuerberaterin",
    "wof:placetype":"venue"
},
  "geometry": {"coordinates":[7.2406549454,51.4475212097],"type":"Point"}
}