{
  "type": "Feature",
  "properties": {
    "iso:country":"DE",
    "sg:address":"Steinacker 39",
    "sg:city":"Bergisch Gladbach",
    "sg:phone":"+49 2204/81523",
    "sg:postcode":"51429",
    "sg:province":"Nordrhein-Westfalen",
    "wof:name":"Wilh. Schl\u00f6sser Gmbh",
    "wof:placetype":"venue"
},
  "geometry": {"coordinates":[7.1974520683,50.9633750916],"type":"Point"}
}