{
  "type": "Feature",
  "properties": {
    "iso:country":"DE",
    "sg:address":"Wattgraben 3",
    "sg:city":"Immenstaad",
    "sg:phone":"+49 7545/6239",
    "sg:postcode":"88090",
    "sg:province":"Baden-W\u00fcrttemberg",
    "wof:name":"Krone",
    "wof:placetype":"venue"
},
  "geometry": {"coordinates":[9.3642158508,47.6647377014],"type":"Point"}
}