{
  "type": "Feature",
  "properties": {
    "iso:country":"DE",
    "sg:address":"Flughafenstr 52",
    "sg:city":"M\u00f6rfelden-Walldorf",
    "sg:phone":"+49 6105/951970",
    "sg:postcode":"64546",
    "sg:province":"Hessen",
    "wof:name":"Idea Force International Entwicklungs- + Beschaffungsagentur",
    "wof:placetype":"venue"
},
  "geometry": {"coordinates":[8.577364,50.006828],"type":"Point"}
}