{
  "type": "Feature",
  "properties": {
    "iso:country":"DE",
    "sg:address":"R\u00f6merstr. 7",
    "sg:city":"Asbach-B\u00e4umenheim",
    "sg:phone":"+49 906/9301",
    "sg:postcode":"86663",
    "sg:province":"Bayern",
    "wof:name":"Unterwirt",
    "wof:placetype":"venue"
},
  "geometry": {"coordinates":[10.8199167252,48.6825408936],"type":"Point"}
}