{
  "type": "Feature",
  "properties": {
    "iso:country":"DE",
    "sg:address":"Am Kreienwinkel 5",
    "sg:city":"Enger",
    "sg:phone":"+49 5224/2199",
    "sg:postcode":"32130",
    "sg:province":"Nordrhein-Westfalen",
    "wof:name":"Helmut Gieselmann",
    "wof:placetype":"venue"
},
  "geometry": {"coordinates":[8.514971,52.14267],"type":"Point"}
}