{
  "type": "Feature",
  "properties": {
    "iso:country":"DE",
    "sg:address":"Kegelheim 4",
    "sg:city":"Birgland",
    "sg:phone":"+49 9157/1444",
    "sg:postcode":"92262",
    "sg:province":"Bayern",
    "wof:name":"F. Kugler",
    "wof:placetype":"venue"
},
  "geometry": {"coordinates":[11.5635452271,49.4300003052],"type":"Point"}
}