{
  "type": "Feature",
  "properties": {
    "iso:country":"DE",
    "sg:address":"Bachstr. 22",
    "sg:city":"Hennef",
    "sg:phone":"+49 2242/81867",
    "sg:postcode":"53773",
    "sg:province":"Nordrhein-Westfalen",
    "wof:name":"Hermann-josef Buchholz Ingenieur",
    "wof:placetype":"venue"
},
  "geometry": {"coordinates":[7.2910609245,50.7691459656],"type":"Point"}
}