{
  "type": "Feature",
  "properties": {
    "iso:country":"DE",
    "sg:address":"Leitenstr. 1",
    "sg:city":"Riedenburg",
    "sg:phone":"+49 9442/92030",
    "sg:postcode":"93339",
    "sg:province":"Bayern",
    "wof:name":"Jura-holzbau Gmbh",
    "wof:placetype":"venue"
},
  "geometry": {"coordinates":[11.703045,48.99147],"type":"Point"}
}