{
  "type": "Feature",
  "properties": {
    "iso:country":"DE",
    "sg:address":"Zechenstr. 2",
    "sg:city":"Sinzing",
    "sg:postcode":"93161",
    "sg:province":"Bayern",
    "wof:name":"Intercommerz Gmbh",
    "wof:placetype":"venue"
},
  "geometry": {"coordinates":[11.947782,48.968853],"type":"Point"}
}