{
  "type": "Feature",
  "properties": {
    "iso:country":"DE",
    "sg:address":"Dresdener Str. 10",
    "sg:city":"Konstanz",
    "sg:phone":"+49 7531/77498",
    "sg:postcode":"78467",
    "sg:province":"Baden-W\u00fcrttemberg",
    "wof:name":"Hugo Spengler Ingenieur",
    "wof:placetype":"venue"
},
  "geometry": {"coordinates":[9.1517953873,47.6822242737],"type":"Point"}
}