{
  "type": "Feature",
  "properties": {
    "iso:country":"DE",
    "sg:address":"Friedrich-List-Str. 10",
    "sg:city":"Oberndorf",
    "sg:postcode":"78727",
    "sg:province":"Baden-W\u00fcrttemberg",
    "wof:name":"Maxi-service",
    "wof:placetype":"venue"
},
  "geometry": {"coordinates":[8.5525417328,48.2950592041],"type":"Point"}
}