{
  "type": "Feature",
  "properties": {
    "iso:country":"DE",
    "sg:address":"Ernst-Barlach-Str.",
    "sg:city":"Cottbus",
    "sg:phone":"+49 355/700675",
    "sg:postcode":"03046",
    "sg:province":"Brandenburg",
    "wof:name":"Gastst\u00e4tte Am Landgraben",
    "wof:placetype":"venue"
},
  "geometry": {"coordinates":[14.3122596741,51.7602081299],"type":"Point"}
}