{
  "type": "Feature",
  "properties": {
    "iso:country":"DE",
    "sg:address":"Stiegelsgasse 9",
    "sg:city":"Keula",
    "sg:phone":"+49 3632/603748",
    "sg:postcode":"99713",
    "sg:province":"Th\u00fcringen",
    "wof:name":"B. Kaden",
    "wof:placetype":"venue"
},
  "geometry": {"coordinates":[10.529251,51.329906],"type":"Point"}
}