{
  "type": "Feature",
  "properties": {
    "iso:country":"DE",
    "sg:address":"M\u00fchlenstr. 21a",
    "sg:city":"Pinneberg",
    "sg:phone":"+49 4101/512312",
    "sg:postcode":"25421",
    "sg:province":"Schleswig-Holstein",
    "wof:name":"R. Rieprich",
    "wof:placetype":"venue"
},
  "geometry": {"coordinates":[9.78577,53.658447],"type":"Point"}
}