{
  "type": "Feature",
  "properties": {
    "iso:country":"DE",
    "sg:address":"Kanzler-St\u00fcrtzel-Str. 8",
    "sg:city":"Kitzingen",
    "sg:phone":"+49 9321/7238",
    "sg:postcode":"97318",
    "sg:province":"Bayern",
    "wof:name":"Albert Fresz Rechtsanwalt",
    "wof:placetype":"venue"
},
  "geometry": {"coordinates":[10.1605653763,49.7315788269],"type":"Point"}
}