{
  "type": "Feature",
  "properties": {
    "iso:country":"DE",
    "sg:address":"Schulstr. 13a",
    "sg:city":"Schwarzenbruck",
    "sg:phone":"+49 9183/8487",
    "sg:postcode":"90592",
    "sg:province":"Bayern",
    "wof:name":"Fhs Immobilien",
    "wof:placetype":"venue"
},
  "geometry": {"coordinates":[11.2804689407,49.3318023682],"type":"Point"}
}