{
  "type": "Feature",
  "properties": {
    "iso:country":"DE",
    "sg:address":"Wiesenstr. 11",
    "sg:city":"Steinen",
    "sg:phone":"+49 7627/8021",
    "sg:postcode":"79585",
    "sg:province":"Baden-W\u00fcrttemberg",
    "wof:name":"Kr\u00f6ber Mineral\u00f6l Und Landesprodukte Gmbh",
    "wof:placetype":"venue"
},
  "geometry": {"coordinates":[7.7394590378,47.6408882141],"type":"Point"}
}