{
  "type": "Feature",
  "properties": {
    "iso:country":"DE",
    "sg:address":"Schuckertstr. 17",
    "sg:city":"Ditzingen",
    "sg:phone":"+49 7156/93510",
    "sg:postcode":"71254",
    "sg:province":"Baden-W\u00fcrttemberg",
    "wof:name":"Steuerberatung Treuhand Revisions- Und Beratungs-ges.",
    "wof:placetype":"venue"
},
  "geometry": {"coordinates":[9.0706911087,48.8204612732],"type":"Point"}
}