{
  "type": "Feature",
  "properties": {
    "iso:country":"DE",
    "sg:address":"M\u00fchlweg 1b",
    "sg:city":"Arnstadt",
    "sg:phone":"+49 3628/61660",
    "sg:postcode":"99310",
    "sg:province":"Th\u00fcringen",
    "wof:name":"H. Hossfeld Inh. Joachim Hossfeld",
    "wof:placetype":"venue"
},
  "geometry": {"coordinates":[10.956147,50.839298],"type":"Point"}
}