{
  "type": "Feature",
  "properties": {
    "iso:country":"DE",
    "sg:address":"M\u00fcnchener Str. 21",
    "sg:city":"N\u00fcrnberg",
    "sg:phone":"+49 911/474849",
    "sg:postcode":"90478",
    "sg:province":"Bayern",
    "wof:name":"Restaurant Meistersingerhalle",
    "wof:placetype":"venue"
},
  "geometry": {"coordinates":[11.1036300659,49.4375076294],"type":"Point"}
}