{
  "type": "Feature",
  "properties": {
    "iso:country":"DE",
    "sg:address":"Barbarastr. 14",
    "sg:city":"Ronnenberg",
    "sg:postcode":"30952",
    "sg:province":"Niedersachsen",
    "wof:name":"Dr. Med. Friedrich Hey Fabrik Pharmazeutischer",
    "wof:placetype":"venue"
},
  "geometry": {"coordinates":[9.6581354141,52.3368415833],"type":"Point"}
}