{
  "type": "Feature",
  "properties": {
    "iso:country":"DE",
    "sg:address":"M\u00fchlweg 14",
    "sg:city":"Fichtelberg",
    "sg:phone":"+49 9272/1257",
    "sg:postcode":"95686",
    "sg:province":"Bayern",
    "wof:name":"Erich Markhof",
    "wof:placetype":"venue"
},
  "geometry": {"coordinates":[11.8536434174,50.0081672668],"type":"Point"}
}