{
  "type": "Feature",
  "properties": {
    "iso:country":"DE",
    "sg:address":"Ringstr. 5",
    "sg:city":"Dossenheim",
    "sg:phone":"+49 6221/13059",
    "sg:postcode":"69221",
    "sg:province":"Baden-W\u00fcrttemberg",
    "wof:name":"Innovation Academy Heidelberg Gmbh",
    "wof:placetype":"venue"
},
  "geometry": {"coordinates":[8.6744880676,49.4458732605],"type":"Point"}
}