{
  "type": "Feature",
  "properties": {
    "iso:country":"DE",
    "sg:address":"Blumenstr. 30",
    "sg:city":"D\u00fcsseldorf",
    "sg:phone":"+49 211/4920863",
    "sg:postcode":"40212",
    "sg:province":"Nordrhein-Westfalen",
    "wof:name":"Ficon Immobilien- Beteiligungsges. Mbh & Co.",
    "wof:placetype":"venue"
},
  "geometry": {"coordinates":[6.781608,51.224739],"type":"Point"}
}