{
  "type": "Feature",
  "properties": {
    "iso:country":"DE",
    "sg:address":"Schnetzlerstr. 4",
    "sg:city":"Karlsruhe",
    "sg:phone":"+49 721/33637",
    "sg:postcode":"76137",
    "sg:province":"Baden-W\u00fcrttemberg",
    "wof:name":"G\u00fcnter Magenreute Elektroinstallation",
    "wof:placetype":"venue"
},
  "geometry": {"coordinates":[8.398665,48.995941],"type":"Point"}
}