{
  "type": "Feature",
  "properties": {
    "iso:country":"DE",
    "sg:address":"Klaerwerkstr. 1",
    "sg:city":"Berlin",
    "sg:phone":"+49 30/35183280",
    "sg:postcode":"13597",
    "sg:province":"Berlin",
    "wof:name":"Trapp Tief- U. Gleisbau Gmbh",
    "wof:placetype":"venue"
},
  "geometry": {"coordinates":[13.23297,52.529163],"type":"Point"}
}