{
  "type": "Feature",
  "properties": {
    "iso:country":"DE",
    "sg:address":"Eisenbahnstr. 142",
    "sg:city":"F\u00fcrstenwalde",
    "sg:phone":"+49 3361/4664",
    "sg:postcode":"15517",
    "sg:province":"Brandenburg",
    "wof:name":"Gerhard Schuck",
    "wof:placetype":"venue"
},
  "geometry": {"coordinates":[14.0615577698,52.3619804382],"type":"Point"}
}