{
  "type": "Feature",
  "properties": {
    "iso:country":"DE",
    "sg:address":"Herzog-Wilhelm-Str. 78",
    "sg:city":"Bad Harzburg",
    "sg:postcode":"38667",
    "sg:province":"Niedersachsen",
    "wof:name":"Fr\u00fcchte Gro\u00df- U. Einzel- Handel In Bad Harzburg Gmbh",
    "wof:placetype":"venue"
},
  "geometry": {"coordinates":[10.5598831177,51.8791275024],"type":"Point"}
}