{
  "type": "Feature",
  "properties": {
    "iso:country":"DE",
    "sg:address":"Gartenstr. 16",
    "sg:city":"Schwieberdingen",
    "sg:phone":"+49 7150/32858",
    "sg:postcode":"71701",
    "sg:province":"Baden-W\u00fcrttemberg",
    "wof:name":"Verein Der Stanischitscher Schwaben",
    "wof:placetype":"venue"
},
  "geometry": {"coordinates":[9.0776233673,48.8773994446],"type":"Point"}
}