{
  "type": "Feature",
  "properties": {
    "iso:country":"DE",
    "sg:address":"Alte Kasseler Str. 15",
    "sg:city":"Wabern",
    "sg:phone":"+49 5683/200",
    "sg:postcode":"34590",
    "sg:province":"Hessen",
    "wof:name":"Reifen Klotz Vulkan. Anstalt",
    "wof:placetype":"venue"
},
  "geometry": {"coordinates":[9.349386,51.104565],"type":"Point"}
}