{
  "type": "Feature",
  "properties": {
    "iso:country":"DE",
    "sg:address":"Hansastr. 133",
    "sg:city":"M\u00fcnchen",
    "sg:postcode":"81373",
    "sg:province":"Bayern",
    "wof:name":"Pro Contra 24 Security Service E. K.",
    "wof:placetype":"venue"
},
  "geometry": {"coordinates":[11.5350408554,48.1207427979],"type":"Point"}
}