{
  "type": "Feature",
  "properties": {
    "iso:country":"DE",
    "sg:address":"Birkenstr. 25",
    "sg:city":"Siegenburg",
    "sg:phone":"+49 9444/88229",
    "sg:postcode":"93354",
    "sg:province":"Bayern",
    "wof:name":"T. Rieth Ingenieur",
    "wof:placetype":"venue"
},
  "geometry": {"coordinates":[11.8545675278,48.7492332458],"type":"Point"}
}