{
  "type": "Feature",
  "properties": {
    "iso:country":"DE",
    "sg:address":"Dorfstr. 5",
    "sg:city":"Haselau",
    "sg:phone":"+49 4122/85930",
    "sg:postcode":"25489",
    "sg:province":"Schleswig-Holstein",
    "wof:name":"Jan Behrens",
    "wof:placetype":"venue"
},
  "geometry": {"coordinates":[9.62283,53.660961],"type":"Point"}
}