{
  "type": "Feature",
  "properties": {
    "iso:country":"DE",
    "sg:address":"R\u00f6merstr. 4",
    "sg:city":"Lambsheim",
    "sg:postcode":"67245",
    "sg:province":"Rheinland-Pfalz",
    "wof:name":"Holos - Institut Privates Forschungs- Und Beratungs-",
    "wof:placetype":"venue"
},
  "geometry": {"coordinates":[8.2849502563,49.5069656372],"type":"Point"}
}