{
  "type": "Feature",
  "properties": {
    "iso:country":"DE",
    "sg:address":"Harkotten 2",
    "sg:city":"Sassenberg",
    "sg:phone":"+49 5426/3277",
    "sg:postcode":"48336",
    "sg:province":"Nordrhein-Westfalen",
    "wof:name":"Vladimir Lischnewski Architekt",
    "wof:placetype":"venue"
},
  "geometry": {"coordinates":[8.029789,52.062054],"type":"Point"}
}