{
  "type": "Feature",
  "properties": {
    "iso:country":"DE",
    "sg:address":"Zur Worbelsheide 9",
    "sg:city":"Monschau",
    "sg:phone":"+49 2472/2583",
    "sg:postcode":"52156",
    "sg:province":"Nordrhein-Westfalen",
    "wof:name":"Gottfried M\u00fcller",
    "wof:placetype":"venue"
},
  "geometry": {"coordinates":[6.2248902321,50.5786705017],"type":"Point"}
}