{
  "type": "Feature",
  "properties": {
    "iso:country":"DE",
    "sg:address":"Landgrafenstr. 17",
    "sg:city":"Hessisch Lichtenau",
    "sg:phone":"+49 5602/2021",
    "sg:postcode":"37235",
    "sg:province":"Hessen",
    "wof:name":"Ratskeller",
    "wof:placetype":"venue"
},
  "geometry": {"coordinates":[9.7213420868,51.1973686218],"type":"Point"}
}