{
  "type": "Feature",
  "properties": {
    "iso:country":"DE",
    "sg:address":"Industriestr. 6",
    "sg:city":"Nottuln",
    "sg:phone":"+49 2509/8268",
    "sg:postcode":"48301",
    "sg:province":"Nordrhein-Westfalen",
    "wof:name":"Karl-h. Wolken",
    "wof:placetype":"venue"
},
  "geometry": {"coordinates":[7.4322829247,51.8924484253],"type":"Point"}
}