{
  "type": "Feature",
  "properties": {
    "iso:country":"DE",
    "sg:address":"C\u00e4cilienstr. 4",
    "sg:city":"Lohmar",
    "sg:postcode":"53797",
    "sg:province":"Nordrhein-Westfalen",
    "wof:name":"Ipb Ingenieurplanung Und Baugesellschaft Mbh",
    "wof:placetype":"venue"
},
  "geometry": {"coordinates":[7.2774128914,50.9016952515],"type":"Point"}
}