{
  "type": "Feature",
  "properties": {
    "iso:country":"DE",
    "sg:address":"Freiligrathstra\u00dfe 5",
    "sg:city":"Dorsten",
    "sg:phone":"+49 2362",
    "sg:postcode":"46284",
    "sg:province":"Nordrhein-Westfalen",
    "wof:name":"Friseursalon Guido Richter",
    "wof:placetype":"venue"
},
  "geometry": {"coordinates":[6.991982,51.671253],"type":"Point"}
}