{
  "type": "Feature",
  "properties": {
    "iso:country":"DE",
    "sg:address":"Loipersdorf 11",
    "sg:city":"Schweitenkirchen",
    "sg:phone":"+49 8444/91173",
    "sg:postcode":"85301",
    "sg:province":"Bayern",
    "wof:name":"Acosoft Unternehmensberatung Handel Und Systemtechnik Gmbh",
    "wof:placetype":"venue"
},
  "geometry": {"coordinates":[11.6364526749,48.5067710876],"type":"Point"}
}