{
  "type": "Feature",
  "properties": {
    "iso:country":"DE",
    "sg:address":"Wupperstr. 13",
    "sg:city":"Remscheid",
    "sg:phone":"+49 2191/668177",
    "sg:postcode":"42897",
    "sg:province":"Nordrhein-Westfalen",
    "wof:name":"Peter Berthold",
    "wof:placetype":"venue"
},
  "geometry": {"coordinates":[7.260048,51.189854],"type":"Point"}
}