{
  "type": "Feature",
  "properties": {
    "iso:country":"DE",
    "sg:address":"Marktgasse 10",
    "sg:city":"Eichst\u00e4tt",
    "sg:phone":"+49 8421/909440",
    "sg:postcode":"85072",
    "sg:province":"Bayern",
    "wof:name":"Trio Mode Gmbh",
    "wof:placetype":"venue"
},
  "geometry": {"coordinates":[11.1849031448,48.8928642273],"type":"Point"}
}