{
  "type": "Feature",
  "properties": {
    "iso:country":"DE",
    "sg:address":"Ludwigstr. 17",
    "sg:city":"M\u00f6rfelden-Walldorf",
    "sg:phone":"+49 6105/76965",
    "sg:postcode":"64546",
    "sg:province":"Hessen",
    "wof:name":"E. Theisinger",
    "wof:placetype":"venue"
},
  "geometry": {"coordinates":[8.5788316727,50.0020866394],"type":"Point"}
}