{
  "type": "Feature",
  "properties": {
    "iso:country":"DE",
    "sg:address":"Niggeln",
    "sg:city":"Jachenau",
    "sg:phone":"+49 8043/437",
    "sg:postcode":"83676",
    "sg:province":"Bayern",
    "wof:name":"Franz Gerg",
    "wof:placetype":"venue"
},
  "geometry": {"coordinates":[11.469081,47.602013],"type":"Point"}
}