{
  "type": "Feature",
  "properties": {
    "iso:country":"DE",
    "sg:address":"Werderstr 13",
    "sg:city":"Genthin",
    "sg:phone":"+49 3933/87050",
    "sg:postcode":"39307",
    "sg:province":"Sachsen-Anhalt",
    "wof:name":"H. & T. Planungsgesellschaft Mbh",
    "wof:placetype":"venue"
},
  "geometry": {"coordinates":[12.1652698517,52.4082183838],"type":"Point"}
}