{
  "type": "Feature",
  "properties": {
    "iso:country":"DE",
    "sg:address":"Bahnhofstr. 21",
    "sg:city":"Neueng\u00f6rs",
    "sg:phone":"+49 4550/205",
    "sg:postcode":"23818",
    "sg:province":"Schleswig-Holstein",
    "wof:name":"G. Kiel",
    "wof:placetype":"venue"
},
  "geometry": {"coordinates":[10.3582267761,53.8979263306],"type":"Point"}
}