{
  "type": "Feature",
  "properties": {
    "iso:country":"DE",
    "sg:address":"An der Ziegelei 9",
    "sg:city":"Radeberg",
    "sg:phone":"+49 8121/2575203",
    "sg:postcode":"01454",
    "sg:province":"Sachsen",
    "wof:name":"Superior Cables Gmbh",
    "wof:placetype":"venue"
},
  "geometry": {"coordinates":[11.851949,48.193195],"type":"Point"}
}