{
  "type": "Feature",
  "properties": {
    "iso:country":"DE",
    "sg:address":"M\u00fchlstr. 51",
    "sg:city":"Pfungstadt",
    "sg:phone":"+49 6157/990061",
    "sg:postcode":"64319",
    "sg:province":"Hessen",
    "wof:name":"Karl-heinz Ahl",
    "wof:placetype":"venue"
},
  "geometry": {"coordinates":[8.6062068939,49.8013114929],"type":"Point"}
}