{
  "type": "Feature",
  "properties": {
    "iso:country":"DE",
    "sg:address":"Flemerskamp 112",
    "sg:city":"Dortmund",
    "sg:phone":"+49 231/283833",
    "sg:postcode":"44319",
    "sg:province":"Nordrhein-Westfalen",
    "wof:name":"Ev. Pfarramt Husen-kurl",
    "wof:placetype":"venue"
},
  "geometry": {"coordinates":[7.5959367752,51.5544281006],"type":"Point"}
}