{
  "type": "Feature",
  "properties": {
    "iso:country":"DE",
    "sg:address":"S\u00fcdallee 7a",
    "sg:city":"Sankt Peter-Ording",
    "sg:phone":"+49 4863/2957",
    "sg:postcode":"25826",
    "sg:province":"Schleswig-Holstein",
    "wof:name":"Peter Hansen",
    "wof:placetype":"venue"
},
  "geometry": {"coordinates":[8.634188,54.304604],"type":"Point"}
}