{
  "type": "Feature",
  "properties": {
    "iso:country":"DE",
    "sg:address":"B\u00e4renhof 34",
    "sg:city":"Garbsen",
    "sg:phone":"+49 5137/77775",
    "sg:postcode":"30823",
    "sg:province":"Niedersachsen",
    "wof:name":"Baubecon Holding Ag",
    "wof:placetype":"venue"
},
  "geometry": {"coordinates":[9.6106977463,52.4183807373],"type":"Point"}
}