{
  "type": "Feature",
  "properties": {
    "iso:country":"DE",
    "sg:address":"Sporenstr. 3",
    "sg:city":"Altenburg",
    "sg:phone":"+49 3447/55290",
    "sg:postcode":"04600",
    "sg:province":"Th\u00fcringen",
    "wof:name":"C & A",
    "wof:placetype":"venue"
},
  "geometry": {"coordinates":[12.434848,50.9856],"type":"Point"}
}