{
  "type": "Feature",
  "properties": {
    "iso:country":"DE",
    "sg:address":"Friedl\u00e4nder Weg 19",
    "sg:city":"sdfgsd",
    "sg:postcode":"32432",
    "wof:name":"Hainberg-gymnasium G\u00f6ttingen",
    "wof:placetype":"venue"
},
  "geometry": {"coordinates":[-85.079079,30.71312],"type":"Point"}
}