{
  "type": "Feature",
  "properties": {
    "iso:country":"DE",
    "sg:address":"Feursstr. 25",
    "sg:city":"Olching",
    "sg:phone":"+49 8142/12198",
    "sg:postcode":"82140",
    "sg:province":"Bayern",
    "wof:name":"Daxerhof",
    "wof:placetype":"venue"
},
  "geometry": {"coordinates":[11.3377475739,48.2127456665],"type":"Point"}
}