{
  "type": "Feature",
  "properties": {
    "iso:country":"DE",
    "sg:address":"Bahnhofstr. 11",
    "sg:city":"Goldbach",
    "sg:phone":"+49 6021/51655",
    "sg:postcode":"63773",
    "sg:province":"Bayern",
    "wof:name":"Erwin Albert",
    "wof:placetype":"venue"
},
  "geometry": {"coordinates":[9.1828098297,49.9962501526],"type":"Point"}
}