{
  "type": "Feature",
  "properties": {
    "iso:country":"DE",
    "sg:address":"Ortsstr. 36",
    "sg:city":"Hirschendorf",
    "sg:phone":"+49 3686/309230",
    "sg:postcode":"98678",
    "sg:province":"Th\u00fcringen",
    "wof:name":"M. Krau\u00dfe",
    "wof:placetype":"venue"
},
  "geometry": {"coordinates":[10.948054,50.447147],"type":"Point"}
}