{
  "type": "Feature",
  "properties": {
    "iso:country":"DE",
    "sg:address":"In der Krim 19",
    "sg:city":"Wuppertal",
    "sg:phone":"+49 202/2461998",
    "sg:postcode":"42369",
    "sg:province":"Nordrhein-Westfalen",
    "wof:name":"City",
    "wof:placetype":"venue"
},
  "geometry": {"coordinates":[7.201912,51.228737],"type":"Point"}
}