{
  "type": "Feature",
  "properties": {
    "iso:country":"DE",
    "sg:address":"Danziger Weg 15",
    "sg:city":"Offenburg",
    "sg:phone":"+49 781/65525",
    "sg:postcode":"77656",
    "sg:province":"Baden-W\u00fcrttemberg",
    "wof:name":"B. Galland Elektroinstallation",
    "wof:placetype":"venue"
},
  "geometry": {"coordinates":[7.922272,48.45956],"type":"Point"}
}