{
  "type": "Feature",
  "properties": {
    "iso:country":"DE",
    "sg:address":"Am F\u00f6rsterweg 13",
    "sg:city":"Strausberg",
    "sg:postcode":"15344",
    "sg:province":"Brandenburg",
    "wof:name":"Walter Wieczorek",
    "wof:placetype":"venue"
},
  "geometry": {"coordinates":[13.8290195465,52.5346260071],"type":"Point"}
}