{
  "type": "Feature",
  "properties": {
    "iso:country":"DE",
    "sg:address":"N\u00f6rdliche Auffahrtsallee 69",
    "sg:city":"M\u00fcnchen",
    "sg:phone":"+49 89/170470",
    "sg:postcode":"80638",
    "sg:province":"Bayern",
    "wof:name":"Metzgerwirt",
    "wof:placetype":"venue"
},
  "geometry": {"coordinates":[11.5118961334,48.1589164734],"type":"Point"}
}