{
  "type": "Feature",
  "properties": {
    "iso:country":"DE",
    "sg:address":"Frankfurter Str. 314",
    "sg:city":"Kassel",
    "sg:phone":"+49 561/45769",
    "sg:postcode":"34134",
    "sg:province":"Hessen",
    "wof:name":"Aqua Pub",
    "wof:placetype":"venue"
},
  "geometry": {"coordinates":[9.467048645,51.2829475403],"type":"Point"}
}