{
  "type": "Feature",
  "properties": {
    "iso:country":"DE",
    "sg:address":"Franz-Mehring-Str. 1a",
    "sg:city":"Gera",
    "sg:phone":"+49 365/833370",
    "sg:postcode":"07545",
    "sg:province":"Th\u00fcringen",
    "wof:name":"Spedition Conrad Gmbh",
    "wof:placetype":"venue"
},
  "geometry": {"coordinates":[12.0811347961,50.8847732544],"type":"Point"}
}