{
  "type": "Feature",
  "properties": {
    "iso:country":"DE",
    "sg:address":"Am Oberbach 50",
    "sg:city":"Meerbusch",
    "sg:phone":"+49 2150/1093",
    "sg:postcode":"40668",
    "sg:province":"Nordrhein-Westfalen",
    "wof:name":"Gudrun Rath Heilpraktikerin",
    "wof:placetype":"venue"
},
  "geometry": {"coordinates":[6.7123641968,51.2916221619],"type":"Point"}
}