{
  "type": "Feature",
  "properties": {
    "iso:country":"DE",
    "sg:address":"Kamerland 19",
    "sg:city":"Sommerland",
    "sg:postcode":"25358",
    "sg:province":"Schleswig-Holstein",
    "wof:name":"Baugesellschaft Sommerland Mbh",
    "wof:placetype":"venue"
},
  "geometry": {"coordinates":[9.5493097305,53.7937316895],"type":"Point"}
}