{
  "type": "Feature",
  "properties": {
    "iso:country":"DE",
    "sg:address":"Ditzenbrunner Str. 46",
    "sg:city":"Ditzingen",
    "sg:postcode":"71254",
    "sg:province":"Baden-W\u00fcrttemberg",
    "wof:name":"Av Armierung Und Verlege Gmbh",
    "wof:placetype":"venue"
},
  "geometry": {"coordinates":[9.0774278641,48.8289260864],"type":"Point"}
}