{
  "type": "Feature",
  "properties": {
    "iso:country":"DE",
    "sg:address":"In Der Dreispitz 3",
    "sg:city":"Hofheim",
    "sg:phone":"+49 4961/925093",
    "sg:postcode":"65719",
    "sg:province":"Hessen",
    "wof:name":"Kofra Industrie Anlagen Bau Gmbh",
    "wof:placetype":"venue"
},
  "geometry": {"coordinates":[8.458488,50.095367],"type":"Point"}
}