{
  "type": "Feature",
  "properties": {
    "iso:country":"DE",
    "sg:address":"Ro\u00dfplatz 5",
    "sg:city":"Delitzsch",
    "sg:phone":"+49 34202/385010",
    "sg:postcode":"04509",
    "sg:province":"Sachsen",
    "wof:name":"Leipziger Verlags- Und Druckerei-verwaltungs- Gmbh",
    "wof:placetype":"venue"
},
  "geometry": {"coordinates":[12.3367834091,51.5239982605],"type":"Point"}
}