{
  "type": "Feature",
  "properties": {
    "iso:country":"DE",
    "sg:address":"Siemensallee 75",
    "sg:city":"Karlsruhe",
    "sg:phone":"+49 721/863021",
    "sg:postcode":"76187",
    "sg:province":"Baden-W\u00fcrttemberg",
    "wof:name":"Tela Versicherung Ag",
    "wof:placetype":"venue"
},
  "geometry": {"coordinates":[8.3487033844,49.0283203125],"type":"Point"}
}