{
  "type": "Feature",
  "properties": {
    "iso:country":"DE",
    "sg:address":"Zur Benderm\u00fchle 4",
    "sg:city":"Wehrheim",
    "sg:phone":"+49 6081/59949",
    "sg:postcode":"61273",
    "sg:province":"Hessen",
    "wof:name":"Edith Bender",
    "wof:placetype":"venue"
},
  "geometry": {"coordinates":[8.5472536087,50.2809448242],"type":"Point"}
}