{
  "type": "Feature",
  "properties": {
    "iso:country":"DE",
    "sg:address":"\u00d6stlicher Dammweg 24",
    "sg:city":"Bruckm\u00fchl",
    "sg:phone":"+49 8062/8471",
    "sg:postcode":"83052",
    "sg:province":"Bayern",
    "wof:name":"Rohner",
    "wof:placetype":"venue"
},
  "geometry": {"coordinates":[11.921159,47.876408],"type":"Point"}
}