{
  "type": "Feature",
  "properties": {
    "iso:country":"DE",
    "sg:address":"Kirchberg 1",
    "sg:city":"Sornzig-Abla\u00df",
    "sg:postcode":"04769",
    "sg:province":"Sachsen",
    "wof:name":"Ev. Luth. Pfarramt Abla\u00df Mit B\u00f6rtewitz",
    "wof:placetype":"venue"
},
  "geometry": {"coordinates":[12.9474201202,51.2258644104],"type":"Point"}
}