{
  "type": "Feature",
  "properties": {
    "iso:country":"DE",
    "sg:address":"Im Weiher 21",
    "sg:city":"Heidelberg",
    "sg:postcode":"69121",
    "sg:province":"Baden-W\u00fcrttemberg",
    "wof:name":"Simon Weber And Friends Gmbh",
    "wof:placetype":"venue"
},
  "geometry": {"coordinates":[8.67775,49.43721],"type":"Point"}
}