{
  "type": "Feature",
  "properties": {
    "iso:country":"DE",
    "sg:address":"Nordstr. 22",
    "sg:city":"Abstatt",
    "sg:phone":"+49 7062/61633",
    "sg:postcode":"74232",
    "sg:province":"Baden-W\u00fcrttemberg",
    "wof:name":"Hermann Lietz Steuerberater",
    "wof:placetype":"venue"
},
  "geometry": {"coordinates":[9.2990913391,49.0874671936],"type":"Point"}
}