{
  "type": "Feature",
  "properties": {
    "iso:country":"DE",
    "sg:address":"Christian-Westphal-Str. 33",
    "sg:city":"Gr\u00f6mitz",
    "sg:phone":"+49 4562/9954",
    "sg:postcode":"23743",
    "sg:province":"Schleswig-Holstein",
    "wof:name":"Delphin Hotel Garni",
    "wof:placetype":"venue"
},
  "geometry": {"coordinates":[10.95616436,54.1468086243],"type":"Point"}
}