{
  "type": "Feature",
  "properties": {
    "iso:country":"DE",
    "sg:address":"Frankfurter Str. 74",
    "sg:city":"Bad Vilbel",
    "sg:postcode":"61118",
    "sg:province":"Hessen",
    "wof:name":"Akb Baumanagement Gmbh",
    "wof:placetype":"venue"
},
  "geometry": {"coordinates":[8.739372,50.180199],"type":"Point"}
}