{
  "type": "Feature",
  "properties": {
    "iso:country":"DE",
    "sg:address":"Rurstr. 40",
    "sg:city":"Linnich",
    "sg:phone":"+49 2462/6585",
    "sg:postcode":"52441",
    "sg:province":"Nordrhein-Westfalen",
    "wof:name":"Dr. Leo Dolfen Steuerberater",
    "wof:placetype":"venue"
},
  "geometry": {"coordinates":[6.2713928223,50.9803695679],"type":"Point"}
}