{
  "type": "Feature",
  "properties": {
    "iso:country":"DE",
    "sg:address":"Nobelstr. 2",
    "sg:city":"Ettlingen",
    "sg:phone":"+49 7243/536760",
    "sg:postcode":"76275",
    "sg:province":"Baden-W\u00fcrttemberg",
    "wof:name":"Opticon Gesellschaft F\u00dcr Optik & Elektronik Mbh",
    "wof:placetype":"venue"
},
  "geometry": {"coordinates":[8.376579,48.938541],"type":"Point"}
}