{
  "type": "Feature",
  "properties": {
    "iso:country":"DE",
    "sg:address":"Hafenstr. 16",
    "sg:city":"K\u00f6nigs Wusterhausen",
    "sg:phone":"+49 3375/202290",
    "sg:postcode":"15711",
    "sg:province":"Brandenburg",
    "wof:name":"Drucklufttechnik Haase & Held Ohg",
    "wof:placetype":"venue"
},
  "geometry": {"coordinates":[13.63869,52.30172],"type":"Point"}
}