{
  "type": "Feature",
  "properties": {
    "iso:country":"DE",
    "sg:address":"Eichelgrund 44",
    "sg:city":"Oberhausen",
    "sg:phone":"+49 8431/42868",
    "sg:postcode":"86697",
    "sg:province":"Bayern",
    "wof:name":"Freibad",
    "wof:placetype":"venue"
},
  "geometry": {"coordinates":[11.1112480164,48.7193527222],"type":"Point"}
}