{
  "type": "Feature",
  "properties": {
    "iso:country":"DE",
    "sg:address":"Tachover Ring 26",
    "sg:city":"Stadtroda",
    "sg:phone":"+49 36428/42491",
    "sg:postcode":"07646",
    "sg:province":"Th\u00fcringen",
    "wof:name":"Ingenieurb\u00fcro Zeiger",
    "wof:placetype":"venue"
},
  "geometry": {"coordinates":[11.731005,50.860447],"type":"Point"}
}