{
  "type": "Feature",
  "properties": {
    "iso:country":"DE",
    "sg:address":"Moosstr. 2",
    "sg:city":"Friedberg",
    "sg:phone":"+49 821/781349",
    "sg:postcode":"86316",
    "sg:province":"Bayern",
    "wof:name":"Karl Metzger",
    "wof:placetype":"venue"
},
  "geometry": {"coordinates":[10.98388,48.379139],"type":"Point"}
}