{
  "type": "Feature",
  "properties": {
    "iso:country":"DE",
    "sg:address":"Opsener Str. 2",
    "sg:city":"Hamm",
    "sg:phone":"+49 2385/8152",
    "sg:postcode":"59069",
    "sg:province":"Nordrhein-Westfalen",
    "wof:name":"Ernst Wulf",
    "wof:placetype":"venue"
},
  "geometry": {"coordinates":[7.849141,51.610741],"type":"Point"}
}