{
  "type": "Feature",
  "properties": {
    "iso:country":"DE",
    "sg:address":"Carolinengl\u00fcckstr. 31",
    "sg:city":"Bochum",
    "sg:postcode":"44793",
    "sg:province":"Nordrhein-Westfalen",
    "wof:name":"Bvb Beteiligumgs- Verwaltungs- Und Besitzgesellschaft Mbh",
    "wof:placetype":"venue"
},
  "geometry": {"coordinates":[7.179583,51.490238],"type":"Point"}
}