{
  "type": "Feature",
  "properties": {
    "iso:country":"DE",
    "sg:address":"Leuschnerstr. 72",
    "sg:city":"Bayreuth",
    "sg:phone":"+49 921/764600",
    "sg:postcode":"95447",
    "sg:province":"Bayern",
    "wof:name":"Reuter & Schneider Ing.-b\u00fcro",
    "wof:placetype":"venue"
},
  "geometry": {"coordinates":[11.5664138794,49.9333953857],"type":"Point"}
}