{
  "type": "Feature",
  "properties": {
    "iso:country":"DE",
    "sg:address":"Carl-Koenen-Str. 37",
    "sg:city":"Euskirchen",
    "sg:phone":"+49 2251/4568",
    "sg:postcode":"53881",
    "sg:province":"Nordrhein-Westfalen",
    "wof:name":"Erich Wershoven",
    "wof:placetype":"venue"
},
  "geometry": {"coordinates":[6.82177,50.648903],"type":"Point"}
}