{
  "type": "Feature",
  "properties": {
    "iso:country":"DE",
    "sg:address":"Bremke 1",
    "sg:city":"Iserlohn",
    "sg:phone":"+49 2371/33888",
    "sg:postcode":"58638",
    "sg:province":"Nordrhein-Westfalen",
    "wof:name":"Cafe Hilbrand",
    "wof:placetype":"venue"
},
  "geometry": {"coordinates":[7.67769,51.384319],"type":"Point"}
}