{
  "type": "Feature",
  "properties": {
    "iso:country":"DE",
    "sg:address":"Ballindamm 37",
    "sg:city":"Hamburg",
    "sg:phone":"+49 40/3258750",
    "sg:postcode":"20095",
    "sg:province":"Hamburg",
    "wof:name":"Cmc Consulting Gmbh",
    "wof:placetype":"venue"
},
  "geometry": {"coordinates":[9.9953956604,53.5520515442],"type":"Point"}
}