{
  "type": "Feature",
  "properties": {
    "iso:country":"DE",
    "sg:address":"Herrenstr. 12",
    "sg:city":"Sontra",
    "sg:phone":"+49 5653/421",
    "sg:postcode":"36205",
    "sg:province":"Hessen",
    "wof:name":"E. Wieland",
    "wof:placetype":"venue"
},
  "geometry": {"coordinates":[9.9335603714,51.0694274902],"type":"Point"}
}