{
  "type": "Feature",
  "properties": {
    "iso:country":"DE",
    "sg:address":"Baumstr. 22",
    "sg:city":"Dortmund",
    "sg:postcode":"44147",
    "sg:province":"Nordrhein-Westfalen",
    "wof:name":"Phoenix Bau Gmbh",
    "wof:placetype":"venue"
},
  "geometry": {"coordinates":[7.456469059,51.5203704834],"type":"Point"}
}