{
  "type": "Feature",
  "properties": {
    "iso:country":"DE",
    "sg:city":"Usingen",
    "sg:phone":"+49 6081/12722",
    "sg:postcode":"61250",
    "sg:province":"Hessen",
    "wof:name":"Diskothek Fun",
    "wof:placetype":"venue"
},
  "geometry": {"coordinates":[8.534775,50.335411],"type":"Point"}
}