{
  "type": "Feature",
  "properties": {
    "iso:country":"DE",
    "sg:address":"Auf der H\u00fcchte",
    "sg:city":"Rheine",
    "sg:phone":"+49 5971/10677",
    "sg:postcode":"48432",
    "sg:province":"Nordrhein-Westfalen",
    "wof:name":"Grill",
    "wof:placetype":"venue"
},
  "geometry": {"coordinates":[7.4481449127,52.2378959656],"type":"Point"}
}