{
  "type": "Feature",
  "properties": {
    "iso:country":"DE",
    "sg:address":"Limburger Str. 4",
    "sg:city":"Elz",
    "sg:phone":"+49 6431/51199",
    "sg:postcode":"65604",
    "sg:province":"Hessen",
    "wof:name":"Pilsstube Laternchen",
    "wof:placetype":"venue"
},
  "geometry": {"coordinates":[8.0354480743,50.4094238281],"type":"Point"}
}