{
  "type": "Feature",
  "properties": {
    "iso:country":"DE",
    "sg:address":"Kirchbrombacher Str. 1 a",
    "sg:city":"Brombachtal",
    "sg:postcode":"64753",
    "sg:province":"Hessen",
    "wof:name":"Stra\u00dfe Und Pflaster Gmbh",
    "wof:placetype":"venue"
},
  "geometry": {"coordinates":[8.9200344086,49.7389831543],"type":"Point"}
}