{
  "type": "Feature",
  "properties": {
    "iso:country":"DE",
    "sg:address":"Wellinghofer Str. 198",
    "sg:city":"Dortmund",
    "sg:phone":"+49 231/462547",
    "sg:postcode":"44263",
    "sg:province":"Nordrhein-Westfalen",
    "wof:name":"O. D\u00fcmpelmann",
    "wof:placetype":"venue"
},
  "geometry": {"coordinates":[7.492234,51.476273],"type":"Point"}
}