{
  "type": "Feature",
  "properties": {
    "iso:country":"DE",
    "sg:address":"Hohenzollernstr. 36",
    "sg:city":"D\u00fcsseldorf",
    "sg:phone":"+49 211/354417",
    "sg:postcode":"40211",
    "sg:province":"Nordrhein-Westfalen",
    "wof:name":"Hans-georg Noack Immobilienmakler",
    "wof:placetype":"venue"
},
  "geometry": {"coordinates":[6.7910141945,51.2252426147],"type":"Point"}
}