{
  "type": "Feature",
  "properties": {
    "iso:country":"DE",
    "sg:address":"Nordrg. 1",
    "sg:city":"G\u00fctersloh",
    "sg:phone":"+49 5241/235378",
    "sg:postcode":"33330",
    "sg:province":"Nordrhein-Westfalen",
    "wof:name":"Bruno Kadritzke Edelstahlgitterroste",
    "wof:placetype":"venue"
},
  "geometry": {"coordinates":[8.38688,51.913132],"type":"Point"}
}