{
  "type": "Feature",
  "properties": {
    "iso:country":"DE",
    "sg:address":"Diedesheimer Str. 37",
    "sg:city":"Mosbach",
    "sg:phone":"+49 6261/7767",
    "sg:postcode":"74821",
    "sg:province":"Baden-W\u00fcrttemberg",
    "wof:name":"Agip Deutschland Ag",
    "wof:placetype":"venue"
},
  "geometry": {"coordinates":[9.1191501617,49.3585014343],"type":"Point"}
}