{
  "type": "Feature",
  "properties": {
    "iso:country":"DE",
    "sg:address":"Im Gleisdreieck 13",
    "sg:city":"L\u00fcbeck",
    "sg:phone":"+49 451/63282",
    "sg:postcode":"23566",
    "sg:province":"Schleswig-Holstein",
    "wof:name":"Futternapf Tierbedarfs Gmbh & Co. Kg",
    "wof:placetype":"venue"
},
  "geometry": {"coordinates":[10.743099,53.869419],"type":"Point"}
}