{
  "type": "Feature",
  "properties": {
    "iso:country":"DE",
    "sg:address":"Am Lindener Berg 2",
    "sg:city":"Holle",
    "sg:postcode":"31188",
    "sg:province":"Niedersachsen",
    "wof:name":"Quadriga Gmbh",
    "wof:placetype":"venue"
},
  "geometry": {"coordinates":[10.1677,52.11079],"type":"Point"}
}