{
  "type": "Feature",
  "properties": {
    "iso:country":"DE",
    "sg:address":"Egestorfer Str. 36 a",
    "sg:city":"Barsinghausen",
    "sg:phone":"+49 5105/61818",
    "sg:postcode":"30890",
    "sg:province":"Niedersachsen",
    "wof:name":"Marmite",
    "wof:placetype":"venue"
},
  "geometry": {"coordinates":[9.4816503525,52.2940292358],"type":"Point"}
}