{
  "type": "Feature",
  "properties": {
    "iso:country":"DE",
    "sg:address":"Dr.-Schott-Str. 12",
    "sg:city":"Burglengenfeld",
    "sg:phone":"+49 9471/8344",
    "sg:postcode":"93133",
    "sg:province":"Bayern",
    "wof:name":"Theo Preihsl Architekt",
    "wof:placetype":"venue"
},
  "geometry": {"coordinates":[12.045029,49.198689],"type":"Point"}
}