{
  "type": "Feature",
  "properties": {
    "iso:country":"DE",
    "sg:address":"Jocketaer Str 92",
    "sg:city":"Plauen",
    "sg:phone":"+49 3741/55870",
    "sg:postcode":"08525",
    "sg:province":"Sachsen",
    "wof:name":"Aquapart Schwimmbadtechnik Gmbh",
    "wof:placetype":"venue"
},
  "geometry": {"coordinates":[12.149603,50.52602],"type":"Point"}
}