{
  "type": "Feature",
  "properties": {
    "iso:country":"DE",
    "sg:address":"Hintere Dorfstr. 14",
    "sg:city":"Hetzles",
    "sg:phone":"+49 9134/5920",
    "sg:postcode":"91077",
    "sg:province":"Bayern",
    "wof:name":"Michlwirt",
    "wof:placetype":"venue"
},
  "geometry": {"coordinates":[11.1301050186,49.633682251],"type":"Point"}
}