{
  "type": "Feature",
  "properties": {
    "iso:country":"DE",
    "sg:address":"Industriestr. 17",
    "sg:city":"Heusenstamm",
    "sg:phone":"+49 6104/6453",
    "sg:postcode":"63150",
    "sg:province":"Hessen",
    "wof:name":"Pmk Me\u00df- Und Kommunikations- Technik Gmbh",
    "wof:placetype":"venue"
},
  "geometry": {"coordinates":[8.79743,50.048012],"type":"Point"}
}