{
  "type": "Feature",
  "properties": {
    "iso:country":"DE",
    "sg:address":"Sudetenstr. 78",
    "sg:city":"Geretsried",
    "sg:phone":"+49 8171/81955",
    "sg:postcode":"82538",
    "sg:province":"Bayern",
    "wof:name":"Teppich-welt Gmbh",
    "wof:placetype":"venue"
},
  "geometry": {"coordinates":[11.4967689514,47.8522567749],"type":"Point"}
}