{
  "type": "Feature",
  "properties": {
    "iso:country":"DE",
    "sg:address":"Halterner Str. 393",
    "sg:city":"Marl",
    "sg:phone":"+49 2365/81161",
    "sg:postcode":"45770",
    "sg:province":"Nordrhein-Westfalen",
    "wof:name":"Halter Pforte",
    "wof:placetype":"venue"
},
  "geometry": {"coordinates":[7.1839938164,51.6532402039],"type":"Point"}
}