{
  "type": "Feature",
  "properties": {
    "iso:country":"DE",
    "sg:address":"Heinrich-Hertz-Str 11",
    "sg:city":"Walldorf",
    "sg:phone":"+49 6227/62016",
    "sg:postcode":"69190",
    "sg:province":"Baden-W\u00fcrttemberg",
    "wof:name":"Hagelauer",
    "wof:placetype":"venue"
},
  "geometry": {"coordinates":[8.649023,49.285976],"type":"Point"}
}