{
  "type": "Feature",
  "properties": {
    "iso:country":"DE",
    "sg:address":"Erlenstr. 22",
    "sg:city":"Hamburg",
    "sg:phone":"+49 40/564652",
    "sg:postcode":"22529",
    "sg:province":"Hamburg",
    "wof:name":"Volker Schmidt",
    "wof:placetype":"venue"
},
  "geometry": {"coordinates":[9.954966,53.597904],"type":"Point"}
}