{
  "type": "Feature",
  "properties": {
    "iso:country":"DE",
    "sg:address":"Wiesenstr. 14",
    "sg:city":"Feucht",
    "sg:phone":"+49 9128/8157",
    "sg:postcode":"90537",
    "sg:province":"Bayern",
    "wof:name":"Homepage Der Dav Sektion Feucht",
    "wof:placetype":"venue"
},
  "geometry": {"coordinates":[11.217878,49.372585],"type":"Point"}
}