{
  "type": "Feature",
  "properties": {
    "iso:country":"DE",
    "sg:address":"Gau\u00dfstr. 12",
    "sg:city":"Mannheim",
    "sg:phone":"+49 621/4310862",
    "sg:postcode":"68165",
    "sg:province":"Baden-W\u00fcrttemberg",
    "wof:name":"Hartmut Schmidtke",
    "wof:placetype":"venue"
},
  "geometry": {"coordinates":[8.479369,49.475914],"type":"Point"}
}