{
  "type": "Feature",
  "properties": {
    "iso:country":"DE",
    "sg:address":"Niendorfer Gehege 39",
    "sg:city":"Hamburg",
    "sg:postcode":"22453",
    "sg:province":"Hamburg",
    "wof:name":"S & G Teevertriebsgesellschaft F\u00fcr Apotheken Mbh",
    "wof:placetype":"venue"
},
  "geometry": {"coordinates":[9.9283542633,53.6123542786],"type":"Point"}
}