{
  "type": "Feature",
  "properties": {
    "iso:country":"DE",
    "sg:address":"Unter den Linden 18",
    "sg:city":"Werder",
    "sg:postcode":"14542",
    "sg:province":"Brandenburg",
    "wof:name":"Fitness Studio Swing",
    "wof:placetype":"venue"
},
  "geometry": {"coordinates":[12.9376296997,52.3772697449],"type":"Point"}
}