{
  "type": "Feature",
  "properties": {
    "iso:country":"DE",
    "sg:address":"Schulgasse 15",
    "sg:city":"Arzberg",
    "sg:phone":"+49 9233/5392",
    "sg:postcode":"95659",
    "sg:province":"Bayern",
    "wof:name":"Karl Burkert",
    "wof:placetype":"venue"
},
  "geometry": {"coordinates":[12.187465,50.057796],"type":"Point"}
}