{
  "type": "Feature",
  "properties": {
    "iso:country":"DE",
    "sg:address":"Plenterstr. 62",
    "sg:city":"Kr\u00f6v",
    "sg:phone":"+49 6541/9685",
    "sg:postcode":"54536",
    "sg:province":"Rheinland-Pfalz",
    "wof:name":"Helga Kneib-schneiders Fremdenheim",
    "wof:placetype":"venue"
},
  "geometry": {"coordinates":[7.0833158493,49.9755249023],"type":"Point"}
}