{
  "type": "Feature",
  "properties": {
    "iso:country":"DE",
    "sg:address":"H\u00f6henweg 17",
    "sg:city":"Rickenbach",
    "sg:phone":"+49 7765/490",
    "sg:postcode":"79736",
    "sg:province":"Baden-W\u00fcrttemberg",
    "wof:name":"Treuwerk Gmbh",
    "wof:placetype":"venue"
},
  "geometry": {"coordinates":[7.976373,47.622684],"type":"Point"}
}