{
  "type": "Feature",
  "properties": {
    "iso:country":"DE",
    "sg:address":"Bochumer Str. 9",
    "sg:city":"Berlin",
    "sg:phone":"+49 30/3924446",
    "sg:postcode":"10555",
    "sg:province":"Berlin",
    "wof:name":"I. Prytula Und M. Wellenbrock-fl\u00fcgge",
    "wof:placetype":"venue"
},
  "geometry": {"coordinates":[13.338052,52.522568],"type":"Point"}
}