{
  "type": "Feature",
  "properties": {
    "iso:country":"DE",
    "sg:address":"Hochstr. 45",
    "sg:city":"Zwiesel",
    "sg:phone":"+49 9922/2811",
    "sg:postcode":"94227",
    "sg:province":"Bayern",
    "wof:name":"F. Kufner Masseur",
    "wof:placetype":"venue"
},
  "geometry": {"coordinates":[13.23479,49.020145],"type":"Point"}
}