{
  "type": "Feature",
  "properties": {
    "iso:country":"DE",
    "sg:address":"Birkenstr. 41",
    "sg:city":"Augsburg",
    "sg:phone":"+49 821/96097",
    "sg:postcode":"86199",
    "sg:province":"Bayern",
    "wof:name":"Dr. Gerhard Liebau Patentanwalt",
    "wof:placetype":"venue"
},
  "geometry": {"coordinates":[10.8641605377,48.3307037354],"type":"Point"}
}