{
  "type": "Feature",
  "properties": {
    "iso:country":"DE",
    "sg:address":"Borsigstr. 70",
    "sg:city":"Heinsberg",
    "sg:phone":"+49 2452/22426",
    "sg:postcode":"52525",
    "sg:province":"Nordrhein-Westfalen",
    "wof:name":"Fitness-treff Berthold Gmbh",
    "wof:placetype":"venue"
},
  "geometry": {"coordinates":[6.1174731255,51.0666007996],"type":"Point"}
}