{
  "type": "Feature",
  "properties": {
    "iso:country":"DE",
    "sg:address":"Ziegelstr. 7",
    "sg:city":"L\u00f6hnberg",
    "sg:phone":"+49 6471/98033",
    "sg:postcode":"35792",
    "sg:province":"Hessen",
    "wof:name":"Nano-optik Beschichtungs Gmbh",
    "wof:placetype":"venue"
},
  "geometry": {"coordinates":[8.2703647614,50.5099143982],"type":"Point"}
}