{
  "type": "Feature",
  "properties": {
    "iso:country":"DE",
    "sg:address":"Schulstr. 1",
    "sg:city":"Possendorf",
    "sg:phone":"+49 35206/5729",
    "sg:postcode":"01728",
    "sg:province":"Sachsen",
    "wof:name":"J. Arnoldt Architekt",
    "wof:placetype":"venue"
},
  "geometry": {"coordinates":[13.715336,50.966042],"type":"Point"}
}