{
  "type": "Feature",
  "properties": {
    "iso:country":"DE",
    "sg:address":"Hauptstr. 53",
    "sg:city":"Offenburg",
    "sg:phone":"+49 781/9237690",
    "sg:postcode":"77652",
    "sg:province":"Baden-W\u00fcrttemberg",
    "wof:name":"Edy Weber Parfum Kosmetik Und Dessous Sabine Sp\u00f6rle E. Kfr.",
    "wof:placetype":"venue"
},
  "geometry": {"coordinates":[7.94308,48.470657],"type":"Point"}
}