{
  "type": "Feature",
  "properties": {
    "iso:country":"DE",
    "sg:address":"Barle 35",
    "sg:city":"Ahaus",
    "sg:phone":"+49 2561/81397",
    "sg:postcode":"48683",
    "sg:province":"Nordrhein-Westfalen",
    "wof:name":"B. V\u00f6cker",
    "wof:placetype":"venue"
},
  "geometry": {"coordinates":[6.932296,52.062305],"type":"Point"}
}