{
  "type": "Feature",
  "properties": {
    "iso:country":"DE",
    "sg:address":"Landstr. 22",
    "sg:city":"Friedland",
    "sg:phone":"+49 5504/430",
    "sg:postcode":"37133",
    "sg:province":"Niedersachsen",
    "wof:name":"B\u00e4ckerei K\u00f6nnecke Gmbh",
    "wof:placetype":"venue"
},
  "geometry": {"coordinates":[9.929491,51.435856],"type":"Point"}
}