{
  "type": "Feature",
  "properties": {
    "iso:country":"DE",
    "sg:address":"Industriestr. 45",
    "sg:city":"Wegberg",
    "sg:phone":"+49 2434/7909",
    "sg:postcode":"41844",
    "sg:province":"Nordrhein-Westfalen",
    "wof:name":"Cohnen & Buschen",
    "wof:placetype":"venue"
},
  "geometry": {"coordinates":[6.291092,51.145824],"type":"Point"}
}