{
  "type": "Feature",
  "properties": {
    "iso:country":"DE",
    "sg:address":"Haller Str. 81",
    "sg:city":"Abtsgm\u00fcnd",
    "sg:phone":"+49 7975/861",
    "sg:postcode":"73453",
    "sg:province":"Baden-W\u00fcrttemberg",
    "wof:name":"Friedrich Aspacher",
    "wof:placetype":"venue"
},
  "geometry": {"coordinates":[9.885312,48.918507],"type":"Point"}
}