{
  "type": "Feature",
  "properties": {
    "iso:country":"DE",
    "sg:address":"Siemensstr 5",
    "sg:city":"Erlensee",
    "sg:phone":"+49 6183/8090",
    "sg:postcode":"63526",
    "sg:province":"Hessen",
    "wof:name":"Stahlbau Main Gmbh",
    "wof:placetype":"venue"
},
  "geometry": {"coordinates":[8.9757385254,50.1539649963],"type":"Point"}
}