{
  "type": "Feature",
  "properties": {
    "iso:country":"DE",
    "sg:address":"Hauptstr. 86",
    "sg:city":"Lambrecht",
    "sg:phone":"+49 6325/2486",
    "sg:postcode":"67466",
    "sg:province":"Rheinland-Pfalz",
    "wof:name":"Bayrischer Hof",
    "wof:placetype":"venue"
},
  "geometry": {"coordinates":[8.0683422089,49.3732261658],"type":"Point"}
}