{
  "type": "Feature",
  "properties": {
    "iso:country":"DE",
    "sg:address":"In den Pfalzwiesen 1",
    "sg:city":"Birkenheide",
    "sg:phone":"+49 6237/2552",
    "sg:postcode":"67134",
    "sg:province":"Rheinland-Pfalz",
    "wof:name":"Vereinsgastst\u00e4tte Asv Birkenheide 1946 E. V.",
    "wof:placetype":"venue"
},
  "geometry": {"coordinates":[8.2675943375,49.4800071716],"type":"Point"}
}