{
  "type": "Feature",
  "properties": {
    "iso:country":"DE",
    "sg:address":"Gro\u00dfer Stellweg 19",
    "sg:city":"Viernheim",
    "sg:phone":"+49 6204/96850",
    "sg:postcode":"68519",
    "sg:province":"Hessen",
    "wof:name":"Moco Maschinen- Und Apparatebau Beteilig. Gmbh",
    "wof:placetype":"venue"
},
  "geometry": {"coordinates":[8.580154,49.547379],"type":"Point"}
}