{
  "type": "Feature",
  "properties": {
    "iso:country":"DE",
    "sg:address":"Benno-Strau\u00df-Str. 19",
    "sg:city":"F\u00fcrth",
    "sg:phone":"+49 911",
    "sg:postcode":"90763",
    "sg:province":"Bayern",
    "wof:name":"Roadstar Motorcycles Gmbh In Nuernberg/fuerth",
    "wof:placetype":"venue"
},
  "geometry": {"coordinates":[10.992694,49.447838],"type":"Point"}
}