{
  "type": "Feature",
  "properties": {
    "iso:country":"DE",
    "sg:address":"Sonnenl\u00e4ngstr. 36",
    "sg:city":"Dietramszell",
    "sg:phone":"+49 8027/90660",
    "sg:postcode":"83623",
    "sg:province":"Bayern",
    "wof:name":"Dtl Datentechnik Launicke Gmbh",
    "wof:placetype":"venue"
},
  "geometry": {"coordinates":[11.5488452911,47.8209114075],"type":"Point"}
}