{
  "type": "Feature",
  "properties": {
    "iso:country":"DE",
    "sg:address":"Jakob-Bleyer-Weg 23",
    "sg:city":"Backnang",
    "sg:phone":"+49 7191/88483",
    "sg:postcode":"71522",
    "sg:province":"Baden-W\u00fcrttemberg",
    "wof:name":"W. Und H. Hein Architekten",
    "wof:placetype":"venue"
},
  "geometry": {"coordinates":[9.449412,48.954418],"type":"Point"}
}