{
  "type": "Feature",
  "properties": {
    "iso:country":"DE",
    "sg:address":"Grenzstr.15",
    "sg:city":"Solingen",
    "sg:postcode":"42697",
    "sg:province":"Nordrhein-Westfalen",
    "wof:name":"Die Homepage Der Adam\u00b4s Familie",
    "wof:placetype":"venue"
},
  "geometry": {"coordinates":[6.985725,51.168892],"type":"Point"}
}