{
  "type": "Feature",
  "properties": {
    "iso:country":"DE",
    "sg:address":"Am Osterrech 5",
    "sg:city":"Kirchberg",
    "sg:phone":"+49 6763/93200",
    "sg:postcode":"55481",
    "sg:province":"Rheinland-Pfalz",
    "wof:name":"Evangelischer Kirchenkreis Simmern-trarbach",
    "wof:placetype":"venue"
},
  "geometry": {"coordinates":[7.3840098381,49.9248313904],"type":"Point"}
}