{
  "type": "Feature",
  "properties": {
    "iso:country":"DE",
    "sg:address":"Hauptstr. 4",
    "sg:city":"Jagstzell",
    "sg:phone":"+49 7967/6967",
    "sg:postcode":"73489",
    "sg:province":"Baden-W\u00fcrttemberg",
    "wof:name":"M. Dziwisch",
    "wof:placetype":"venue"
},
  "geometry": {"coordinates":[10.0978393555,49.0309677124],"type":"Point"}
}