{
  "type": "Feature",
  "properties": {
    "iso:country":"DE",
    "sg:address":"Jahnstr. 11 a",
    "sg:city":"Herten",
    "sg:phone":"+49 2366/4437",
    "sg:postcode":"45701",
    "sg:province":"Nordrhein-Westfalen",
    "wof:name":"Klaus Heisterkamp",
    "wof:placetype":"venue"
},
  "geometry": {"coordinates":[7.14044,51.61845],"type":"Point"}
}