{
  "type": "Feature",
  "properties": {
    "iso:country":"DE",
    "sg:address":"Stehfenstr. 69 a",
    "sg:city":"Holzwickede",
    "sg:postcode":"59439",
    "sg:province":"Nordrhein-Westfalen",
    "wof:name":"L\u00f6do Gmbh",
    "wof:placetype":"venue"
},
  "geometry": {"coordinates":[7.6288671494,51.5095443726],"type":"Point"}
}