{
  "type": "Feature",
  "properties": {
    "iso:country":"DE",
    "sg:address":"Linkenboldstr. 67",
    "sg:city":"Albstadt",
    "sg:phone":"+49 7432/21963",
    "sg:postcode":"72461",
    "sg:province":"Baden-W\u00fcrttemberg",
    "wof:name":"Bernd Dietsche Masseur",
    "wof:placetype":"venue"
},
  "geometry": {"coordinates":[9.0081,48.28492],"type":"Point"}
}