{
  "type": "Feature",
  "properties": {
    "iso:country":"DE",
    "sg:address":"Dorfstr. 14 A",
    "sg:city":"Sarstedt",
    "sg:phone":"+49 5066/3239",
    "sg:postcode":"31157",
    "sg:province":"Niedersachsen",
    "wof:name":"Winfried Blume",
    "wof:placetype":"venue"
},
  "geometry": {"coordinates":[9.851449,52.257641],"type":"Point"}
}