{
  "type": "Feature",
  "properties": {
    "iso:country":"DE",
    "sg:address":"Hofstattstr. 161",
    "sg:city":"V\u00f6lklingen",
    "sg:phone":"+49 6898/24832",
    "sg:postcode":"66333",
    "sg:province":"Saarland",
    "wof:name":"Rottmanns Eck",
    "wof:placetype":"venue"
},
  "geometry": {"coordinates":[6.8449950218,49.2585716248],"type":"Point"}
}