{
  "type": "Feature",
  "properties": {
    "iso:country":"DE",
    "sg:address":"Hauptstr. 47",
    "sg:city":"Holzdorf",
    "sg:phone":"+49 35389/484",
    "sg:postcode":"06926",
    "sg:province":"Sachsen-Anhalt",
    "wof:name":"Kreissparkasse",
    "wof:placetype":"venue"
},
  "geometry": {"coordinates":[13.11253,51.779072],"type":"Point"}
}