{
  "type": "Feature",
  "properties": {
    "iso:country":"DE",
    "sg:address":"Im Stillen Winkel 17",
    "sg:city":"Burgdorf",
    "sg:phone":"+49 5136/1274",
    "sg:postcode":"31303",
    "sg:province":"Niedersachsen",
    "wof:name":"Gude-inkasso-gmbh",
    "wof:placetype":"venue"
},
  "geometry": {"coordinates":[10.0112943649,52.4581642151],"type":"Point"}
}