{
  "type": "Feature",
  "properties": {
    "iso:country":"DE",
    "sg:address":"Max-Schwaiger-Str. 8",
    "sg:city":"Kraiburg",
    "sg:phone":"+49 8638/719685",
    "sg:postcode":"84559",
    "sg:province":"Bayern",
    "wof:name":"Apotheke Am Inn Wilhelmine Angstwurm",
    "wof:placetype":"venue"
},
  "geometry": {"coordinates":[12.428091,48.185284],"type":"Point"}
}