{
  "type": "Feature",
  "properties": {
    "iso:country":"DE",
    "sg:address":"Haller Str. 8",
    "sg:city":"Nortrup",
    "sg:phone":"+49 5436/242",
    "sg:postcode":"49638",
    "sg:province":"Niedersachsen",
    "wof:name":"Heinrich Busselmann",
    "wof:placetype":"venue"
},
  "geometry": {"coordinates":[7.884134,52.597485],"type":"Point"}
}