{
  "type": "Feature",
  "properties": {
    "iso:country":"DE",
    "sg:address":"B\u00f6blinger Str. 33",
    "sg:city":"Stuttgart",
    "sg:phone":"+49 711/6406240",
    "sg:postcode":"70178",
    "sg:province":"Baden-W\u00fcrttemberg",
    "wof:name":"Lidija Alagic",
    "wof:placetype":"venue"
},
  "geometry": {"coordinates":[9.1640081406,48.7634963989],"type":"Point"}
}