{
  "type": "Feature",
  "properties": {
    "iso:country":"DE",
    "sg:address":"Barbyer Str. 1",
    "sg:city":"Sch\u00f6nebeck",
    "sg:postcode":"39218",
    "sg:province":"Sachsen-Anhalt",
    "wof:name":"Kohlehandel Gmbh",
    "wof:placetype":"venue"
},
  "geometry": {"coordinates":[11.744716,52.019108],"type":"Point"}
}