{
  "type": "Feature",
  "properties": {
    "iso:country":"DE",
    "sg:address":"Alter Postweg 41",
    "sg:city":"Buxtehude",
    "sg:phone":"+49 4161/86680",
    "sg:postcode":"21614",
    "sg:province":"Niedersachsen",
    "wof:name":"Gogolin & Co Edv-handels- U. Dienstleistungs Kg",
    "wof:placetype":"venue"
},
  "geometry": {"coordinates":[9.7208852768,53.4605064392],"type":"Point"}
}