{
  "type": "Feature",
  "properties": {
    "iso:country":"DE",
    "sg:address":"T\u00fcrkism\u00fchler Str.",
    "sg:city":"Nohfelden",
    "sg:phone":"+49 6852/460",
    "sg:postcode":"66625",
    "sg:province":"Saarland",
    "wof:name":"Gottfried Willems",
    "wof:placetype":"venue"
},
  "geometry": {"coordinates":[7.1275701523,49.561504364],"type":"Point"}
}