{
  "type": "Feature",
  "properties": {
    "iso:country":"DE",
    "sg:address":"Burgdorfer Str. 24",
    "sg:city":"Burgwedel",
    "sg:postcode":"30938",
    "sg:province":"Niedersachsen",
    "wof:name":"Ggm Gesellschaft F\u00fcr Guten M\u00f6belbau Mbh",
    "wof:placetype":"venue"
},
  "geometry": {"coordinates":[9.8807086945,52.4830093384],"type":"Point"}
}