{
  "type": "Feature",
  "properties": {
    "iso:country":"DE",
    "sg:address":"Kirchberg 2",
    "sg:city":"Schwarzenbach a d Saale",
    "sg:phone":"+49 9284/6401",
    "sg:postcode":"95126",
    "sg:province":"Bayern",
    "wof:name":"Ev. Luth. Pfarramt",
    "wof:placetype":"venue"
},
  "geometry": {"coordinates":[9.074760437,47.4425811768],"type":"Point"}
}