{
  "type": "Feature",
  "properties": {
    "iso:country":"DE",
    "sg:address":"Kirchtal 17",
    "sg:city":"R\u00fcthen",
    "sg:phone":"+49 2952/89161",
    "sg:postcode":"59602",
    "sg:province":"Nordrhein-Westfalen",
    "wof:name":"B. Und F. Lenze",
    "wof:placetype":"venue"
},
  "geometry": {"coordinates":[8.403864,51.496426],"type":"Point"}
}