{
  "type": "Feature",
  "properties": {
    "iso:country":"DE",
    "sg:address":"Bahnhofstr. 188 a",
    "sg:city":"Kirchheilingen",
    "sg:phone":"+49 36043/70576",
    "sg:postcode":"99947",
    "sg:province":"Th\u00fcringen",
    "wof:name":"Eiscafe H. Konrad",
    "wof:placetype":"venue"
},
  "geometry": {"coordinates":[10.709483,51.180988],"type":"Point"}
}