{
  "type": "Feature",
  "properties": {
    "iso:country":"DE",
    "sg:address":"Stadtstr. 87a",
    "sg:city":"Freiburg",
    "sg:phone":"+49 761/35051",
    "sg:postcode":"79104",
    "sg:province":"Baden-W\u00fcrttemberg",
    "wof:name":"Dr. H. Bittiger",
    "wof:placetype":"venue"
},
  "geometry": {"coordinates":[7.864751,48.006199],"type":"Point"}
}