{
  "type": "Feature",
  "properties": {
    "iso:country":"DE",
    "sg:address":"Kloppstr. 30",
    "sg:city":"Schmelz",
    "sg:phone":"+49 6887/2971",
    "sg:postcode":"66839",
    "sg:province":"Saarland",
    "wof:name":"Eva Trampert",
    "wof:placetype":"venue"
},
  "geometry": {"coordinates":[6.89814,49.475044],"type":"Point"}
}