{
  "type": "Feature",
  "properties": {
    "iso:country":"DE",
    "sg:address":"Schulstr. 101",
    "sg:city":"Recklinghausen",
    "sg:phone":"+49 2361/81149",
    "sg:postcode":"45665",
    "sg:province":"Nordrhein-Westfalen",
    "wof:name":"Omnibusbetrieb Auto Kunz Inh. Karl-heinz Kunz E. K.",
    "wof:placetype":"venue"
},
  "geometry": {"coordinates":[7.2630801201,51.6094245911],"type":"Point"}
}