{
  "type": "Feature",
  "properties": {
    "iso:country":"DE",
    "sg:address":"An der Strandpromenade 24",
    "sg:city":"Dahme",
    "sg:phone":"+49 4364/284",
    "sg:postcode":"23747",
    "sg:province":"Schleswig-Holstein",
    "wof:name":"W. Dreyer",
    "wof:placetype":"venue"
},
  "geometry": {"coordinates":[11.0875015259,54.2240486145],"type":"Point"}
}