{
  "type": "Feature",
  "properties": {
    "iso:country":"DE",
    "sg:address":"Am R\u00fcppurrer Schlo\u00df 5",
    "sg:city":"Karlsruhe",
    "sg:phone":"+49 721/886600",
    "sg:postcode":"76199",
    "sg:province":"Baden-W\u00fcrttemberg",
    "wof:name":"Rose-marie Larsson-koch Krankengymnastin",
    "wof:placetype":"venue"
},
  "geometry": {"coordinates":[8.405791,48.981125],"type":"Point"}
}