{
  "type": "Feature",
  "properties": {
    "iso:country":"DE",
    "sg:address":"Rosenstr. 17",
    "sg:city":"Wershofen",
    "sg:phone":"+49 2694/306",
    "sg:postcode":"53520",
    "sg:province":"Rheinland-Pfalz",
    "wof:name":"Wilhelm Zeyen Schmiede",
    "wof:placetype":"venue"
},
  "geometry": {"coordinates":[6.810686,50.442905],"type":"Point"}
}