{
  "type": "Feature",
  "properties": {
    "iso:country":"DE",
    "sg:address":"Bamenohler Str. 58",
    "sg:city":"Finnentrop",
    "sg:phone":"+49 2721/70510",
    "sg:postcode":"57413",
    "sg:province":"Nordrhein-Westfalen",
    "wof:name":"Nebeling & Feldmann Kg",
    "wof:placetype":"venue"
},
  "geometry": {"coordinates":[7.984149,51.165565],"type":"Point"}
}