{
  "type": "Feature",
  "properties": {
    "iso:country":"DE",
    "sg:address":"Moororter Str. 12",
    "sg:city":"Rahden",
    "sg:phone":"+49 5776/9490",
    "sg:postcode":"32369",
    "sg:province":"Nordrhein-Westfalen",
    "wof:name":"Altek Hebetechnik Gmbh",
    "wof:placetype":"venue"
},
  "geometry": {"coordinates":[8.643557,52.527855],"type":"Point"}
}