{
  "type": "Feature",
  "properties": {
    "iso:country":"DE",
    "sg:address":"Am Hardtwald 3",
    "sg:city":"Ettlingen",
    "sg:phone":"+49 4973/21370",
    "sg:postcode":"76275",
    "sg:province":"Baden-W\u00fcrttemberg",
    "wof:name":"J.m. Voith Ag",
    "wof:placetype":"venue"
},
  "geometry": {"coordinates":[10.1568698883,48.6741104126],"type":"Point"}
}