{
  "type": "Feature",
  "properties": {
    "iso:country":"DE",
    "sg:address":"Steineiche 1",
    "sg:city":"Hessisch Oldendorf",
    "sg:phone":"+49 5152/2623",
    "sg:postcode":"31840",
    "sg:province":"Niedersachsen",
    "wof:name":"Schlemmer Neitz Gmbh",
    "wof:placetype":"venue"
},
  "geometry": {"coordinates":[9.2427911758,52.1934814453],"type":"Point"}
}