{
  "type": "Feature",
  "properties": {
    "iso:country":"DE",
    "sg:address":"Lahnstr. 21",
    "sg:city":"Wettenberg",
    "sg:phone":"+49 641/86691",
    "sg:postcode":"35435",
    "sg:province":"Hessen",
    "wof:name":"Hofmann & Leib",
    "wof:placetype":"venue"
},
  "geometry": {"coordinates":[8.6599788666,50.6220092773],"type":"Point"}
}