{
  "type": "Feature",
  "properties": {
    "iso:country":"DE",
    "sg:address":"Stechbahn 4",
    "sg:city":"Korbach",
    "sg:phone":"+49 5631/2428",
    "sg:postcode":"34497",
    "sg:province":"Hessen",
    "wof:name":"H. W. Urspruch Inh. A. V\u00f6cklinghaus",
    "wof:placetype":"venue"
},
  "geometry": {"coordinates":[8.8704128265,51.2721786499],"type":"Point"}
}