{
  "type": "Feature",
  "properties": {
    "iso:country":"DE",
    "sg:address":"Gadelheimer M\u00fchle",
    "sg:city":"Elbtal",
    "sg:phone":"+49 6436/4554",
    "sg:postcode":"65627",
    "sg:province":"Hessen",
    "wof:name":"Untere Gadelheimer M\u00fchle",
    "wof:placetype":"venue"
},
  "geometry": {"coordinates":[8.0766305923,50.5062561035],"type":"Point"}
}