{
  "type": "Feature",
  "properties": {
    "iso:country":"DE",
    "sg:address":"Unter den Weiden 1",
    "sg:city":"Gro\u00df B\u00f6rnecke",
    "sg:phone":"+49 39267/701",
    "sg:postcode":"39435",
    "sg:province":"Sachsen-Anhalt",
    "wof:name":"Petra Klaperoth",
    "wof:placetype":"venue"
},
  "geometry": {"coordinates":[11.465022,51.884762],"type":"Point"}
}