{
  "type": "Feature",
  "properties": {
    "iso:country":"DE",
    "sg:address":"K\u00f6nigstr. 13",
    "sg:city":"Berlin",
    "sg:phone":"+49 30/80903337",
    "sg:postcode":"14163",
    "sg:province":"Berlin",
    "wof:name":"Zetel Bautr\u00e4ger- Und Baubetreuungsgesellschaft Mbh",
    "wof:placetype":"venue"
},
  "geometry": {"coordinates":[13.2500743866,52.4329223633],"type":"Point"}
}