{
  "type": "Feature",
  "properties": {
    "iso:country":"DE",
    "sg:address":"Eisenhartstr. 9",
    "sg:city":"Potsdam",
    "sg:phone":"+49 331/292185",
    "sg:postcode":"14469",
    "sg:province":"Brandenburg",
    "wof:name":"Hooss Und R.-h. Walter Rechtsanw\u00e4lte",
    "wof:placetype":"venue"
},
  "geometry": {"coordinates":[13.0612382889,52.4085693359],"type":"Point"}
}