{
  "type": "Feature",
  "properties": {
    "iso:country":"DE",
    "sg:address":"Anton-Riemerschmid-Str. 41",
    "sg:city":"Burghausen",
    "sg:phone":"+49 8677/62284",
    "sg:postcode":"84489",
    "sg:province":"Bayern",
    "wof:name":"M\u00fchldorfer Gmbh & Co. Kg",
    "wof:placetype":"venue"
},
  "geometry": {"coordinates":[12.8203487396,48.1663665771],"type":"Point"}
}