{
  "type": "Feature",
  "properties": {
    "iso:country":"DE",
    "sg:address":"Harxb\u00fctteler Str.",
    "sg:city":"Schw\u00fclper",
    "sg:postcode":"38179",
    "sg:province":"Niedersachsen",
    "wof:name":"Immobilien Lothar A. Metz",
    "wof:placetype":"venue"
},
  "geometry": {"coordinates":[10.4656047821,52.3473243713],"type":"Point"}
}