{
  "type": "Feature",
  "properties": {
    "iso:country":"DE",
    "sg:address":"Gr\u00fcne Aue 26",
    "sg:city":"Fl\u00f6ha",
    "sg:phone":"+49 3726/3219",
    "sg:postcode":"09557",
    "sg:province":"Sachsen",
    "wof:name":"Dr. Med. Dieter Reuther",
    "wof:placetype":"venue"
},
  "geometry": {"coordinates":[13.068203,50.855137],"type":"Point"}
}