{
  "type": "Feature",
  "properties": {
    "iso:country":"DE",
    "sg:address":"Grabitzer Str. 39",
    "sg:city":"Furth im Wald",
    "sg:phone":"+49 9973/9433",
    "sg:postcode":"93437",
    "sg:province":"Bayern",
    "wof:name":"Bms Baumaschinen Service Gmbh",
    "wof:placetype":"venue"
},
  "geometry": {"coordinates":[12.830829,49.303986],"type":"Point"}
}