{
  "type": "Feature",
  "properties": {
    "iso:country":"DE",
    "sg:address":"Casinostr. 6",
    "sg:city":"Traben-Trarbach",
    "sg:phone":"+49 6541/3694",
    "sg:postcode":"56841",
    "sg:province":"Rheinland-Pfalz",
    "wof:name":"B\u00e4rbel Waxmann",
    "wof:placetype":"venue"
},
  "geometry": {"coordinates":[7.112095,49.948952],"type":"Point"}
}