{
  "type": "Feature",
  "properties": {
    "iso:country":"DE",
    "sg:address":"Keltenstr. 2",
    "sg:city":"Idar-Oberstein",
    "sg:postcode":"55743",
    "sg:province":"Rheinland-Pfalz",
    "wof:name":"Gems Center E. K.",
    "wof:placetype":"venue"
},
  "geometry": {"coordinates":[7.3034920692,49.7251472473],"type":"Point"}
}