{
  "type": "Feature",
  "properties": {
    "iso:country":"DE",
    "sg:address":"Hartmannsdorfer Str. 14",
    "sg:city":"Neukirchen",
    "sg:phone":"+49 3763/14996",
    "sg:postcode":"08459",
    "sg:province":"Sachsen",
    "wof:name":"F.-j. Schubert Anlageberater",
    "wof:placetype":"venue"
},
  "geometry": {"coordinates":[12.38667202,50.7888565063],"type":"Point"}
}