{
  "type": "Feature",
  "properties": {
    "iso:country":"DE",
    "sg:address":"R\u00f6merstr.48",
    "sg:city":"Schwabm\u00fcnchen",
    "sg:phone":"+49 8232/905145",
    "sg:postcode":"86830",
    "sg:province":"Bayern",
    "wof:name":"Megaline Software Development",
    "wof:placetype":"venue"
},
  "geometry": {"coordinates":[10.7557725906,48.1914291382],"type":"Point"}
}