{
  "type": "Feature",
  "properties": {
    "iso:country":"DE",
    "sg:address":"Ludwigstr. 47",
    "sg:city":"Linden",
    "sg:phone":"+49 6403/2681",
    "sg:postcode":"35440",
    "sg:province":"Hessen",
    "wof:name":"Manfred Nepp Architekt",
    "wof:placetype":"venue"
},
  "geometry": {"coordinates":[8.654651,50.530201],"type":"Point"}
}