{
  "type": "Feature",
  "properties": {
    "iso:country":"DE",
    "sg:address":"Auf dem Loh 5",
    "sg:city":"Rotenburg",
    "sg:phone":"+49 4261/62748",
    "sg:postcode":"27356",
    "sg:province":"Niedersachsen",
    "wof:name":"Gerda Michaelis Textilwaren",
    "wof:placetype":"venue"
},
  "geometry": {"coordinates":[9.4155235291,53.1120071411],"type":"Point"}
}