{
  "type": "Feature",
  "properties": {
    "iso:country":"DE",
    "sg:address":"Wiehagen 7",
    "sg:city":"M\u00fclheim",
    "sg:phone":"+49 208/495660",
    "sg:postcode":"45472",
    "sg:province":"Nordrhein-Westfalen",
    "wof:name":"Georg Springmann Industrie- Und Bergbautechnik Gmbh",
    "wof:placetype":"venue"
},
  "geometry": {"coordinates":[6.943639,51.442337],"type":"Point"}
}