{
  "type": "Feature",
  "properties": {
    "iso:country":"DE",
    "sg:address":"Dorfstr. 26",
    "sg:city":"Laucha",
    "sg:phone":"+49 34462/22100",
    "sg:postcode":"06636",
    "sg:province":"Sachsen-Anhalt",
    "wof:name":"K. Cario",
    "wof:placetype":"venue"
},
  "geometry": {"coordinates":[11.681803,51.236721],"type":"Point"}
}