{
  "type": "Feature",
  "properties": {
    "iso:country":"DE",
    "sg:address":"Lauenburger Str. 4",
    "sg:city":"Bremen",
    "sg:phone":"+49 421/6918450",
    "sg:postcode":"28219",
    "sg:province":"Bremen",
    "wof:name":"Teas Bauprojekt Gmbh",
    "wof:placetype":"venue"
},
  "geometry": {"coordinates":[8.785681,53.102715],"type":"Point"}
}