{
  "type": "Feature",
  "properties": {
    "iso:country":"DE",
    "sg:address":"Wei\u00dfdornpfad 26 A",
    "sg:city":"Bremen",
    "sg:phone":"+49 421/253585",
    "sg:postcode":"28355",
    "sg:province":"Bremen",
    "wof:name":"Marion Aritim Rechtsanw\u00e4ltin",
    "wof:placetype":"venue"
},
  "geometry": {"coordinates":[8.9021930695,53.0979881287],"type":"Point"}
}