{
  "type": "Feature",
  "properties": {
    "iso:country":"DE",
    "sg:address":"Im Rohr 1",
    "sg:city":"Holzheim",
    "sg:postcode":"89438",
    "sg:province":"Bayern",
    "wof:name":"Weisinger Freizeitanlagen Gmbh",
    "wof:placetype":"venue"
},
  "geometry": {"coordinates":[10.528782,48.512287],"type":"Point"}
}