{
  "type": "Feature",
  "properties": {
    "iso:country":"DE",
    "sg:address":"Ludwig-Mitterer-Str 9",
    "sg:city":"Pfarrkirchen",
    "sg:phone":"+49 8561/985976",
    "sg:postcode":"84347",
    "sg:province":"Bayern",
    "wof:name":"Tekaef Edv-zubeh\u00f6r Gmbh",
    "wof:placetype":"venue"
},
  "geometry": {"coordinates":[12.940428,48.436611],"type":"Point"}
}