{
  "type": "Feature",
  "properties": {
    "iso:country":"DE",
    "sg:address":"Mesmeroder Str. 2",
    "sg:city":"Wunstorf",
    "sg:phone":"+49 5031/2376",
    "sg:postcode":"31515",
    "sg:province":"Niedersachsen",
    "wof:name":"Klaus Fischer",
    "wof:placetype":"venue"
},
  "geometry": {"coordinates":[9.3761816025,52.4171867371],"type":"Point"}
}