{
  "type": "Feature",
  "properties": {
    "iso:country":"DE",
    "sg:address":"Alte Poststr. 21",
    "sg:city":"Siegen",
    "sg:phone":"+49 271/52008",
    "sg:postcode":"57072",
    "sg:province":"Nordrhein-Westfalen",
    "wof:name":"Beerdigungs-institut Piet\u00e4t Louis Heinz Nachf.",
    "wof:placetype":"venue"
},
  "geometry": {"coordinates":[8.023365,50.873802],"type":"Point"}
}