{
  "type": "Feature",
  "properties": {
    "iso:country":"DE",
    "sg:address":"Landsberger Str. 20",
    "sg:city":"Leipzig",
    "sg:phone":"+49 341/9117091",
    "sg:postcode":"04157",
    "sg:province":"Sachsen",
    "wof:name":"R. Moser",
    "wof:placetype":"venue"
},
  "geometry": {"coordinates":[12.365884,51.369156],"type":"Point"}
}