{
  "type": "Feature",
  "properties": {
    "iso:country":"DE",
    "sg:address":"Ballenstedter Str. 16 A",
    "sg:city":"Berlin",
    "sg:postcode":"10709",
    "sg:province":"Berlin",
    "wof:name":"Atm United Technologies Gmbh",
    "wof:placetype":"venue"
},
  "geometry": {"coordinates":[13.3076877594,52.4950447083],"type":"Point"}
}