{
  "type": "Feature",
  "properties": {
    "iso:country":"DE",
    "sg:address":"Klosterstr. 16",
    "sg:city":"Rinteln",
    "sg:phone":"+49 5751/2607",
    "sg:postcode":"31737",
    "sg:province":"Niedersachsen",
    "wof:name":"Restaurant Fischpfanne",
    "wof:placetype":"venue"
},
  "geometry": {"coordinates":[9.0793457031,52.1864204407],"type":"Point"}
}