{
  "type": "Feature",
  "properties": {
    "iso:country":"DE",
    "sg:address":"Westerkampstr. 1",
    "sg:city":"Osnabr\u00fcck",
    "sg:phone":"+49 541/586745",
    "sg:postcode":"49082",
    "sg:province":"Niedersachsen",
    "wof:name":"Brigittes Salon",
    "wof:placetype":"venue"
},
  "geometry": {"coordinates":[8.0695829391,52.2578201294],"type":"Point"}
}