{
  "type": "Feature",
  "properties": {
    "iso:country":"DE",
    "sg:address":"Kurt-Moosdorf-Str. 13",
    "sg:city":"Limeshain",
    "sg:phone":"+49 6047/4307",
    "sg:postcode":"63694",
    "sg:province":"Hessen",
    "wof:name":"Klaus Conradi Architekt",
    "wof:placetype":"venue"
},
  "geometry": {"coordinates":[8.971448,50.257408],"type":"Point"}
}