{
  "type": "Feature",
  "properties": {
    "iso:country":"DE",
    "sg:address":"R\u00f6merring 43",
    "sg:city":"Mommenheim",
    "sg:phone":"+49 6138/97660",
    "sg:postcode":"55278",
    "sg:province":"Rheinland-Pfalz",
    "wof:name":"Velten Gmbh",
    "wof:placetype":"venue"
},
  "geometry": {"coordinates":[8.2640237808,49.8882675171],"type":"Point"}
}