{
  "type": "Feature",
  "properties": {
    "iso:country":"DE",
    "sg:address":"Krohnskamp 33",
    "sg:city":"Hamburg",
    "sg:phone":"+49 40/276937",
    "sg:postcode":"22301",
    "sg:province":"Hamburg",
    "wof:name":"Tribell Gmbh",
    "wof:placetype":"venue"
},
  "geometry": {"coordinates":[10.0090494156,53.5878944397],"type":"Point"}
}