{
  "type": "Feature",
  "properties": {
    "iso:country":"DE",
    "sg:address":"Stra\u00dfe des Friedens 61",
    "sg:city":"Merseburg",
    "sg:phone":"+49 3461/503713",
    "sg:postcode":"06217",
    "sg:province":"Sachsen-Anhalt",
    "wof:name":"Andrea Pfennighaus",
    "wof:placetype":"venue"
},
  "geometry": {"coordinates":[11.9862909317,51.3367462158],"type":"Point"}
}