{
  "type": "Feature",
  "properties": {
    "iso:country":"DE",
    "sg:address":"M\u00f6hnestr. 37",
    "sg:city":"Brilon",
    "sg:phone":"+49 2961/8353",
    "sg:postcode":"59929",
    "sg:province":"Nordrhein-Westfalen",
    "wof:name":"D. Aust",
    "wof:placetype":"venue"
},
  "geometry": {"coordinates":[8.574094,51.404758],"type":"Point"}
}