{
  "type": "Feature",
  "properties": {
    "iso:country":"DE",
    "sg:address":"Schulstr. 20",
    "sg:city":"Vienenburg",
    "sg:phone":"+49 5324/1836",
    "sg:postcode":"38690",
    "sg:province":"Niedersachsen",
    "wof:name":"Gerhard Vetter",
    "wof:placetype":"venue"
},
  "geometry": {"coordinates":[10.565205,51.951832],"type":"Point"}
}