{
  "type": "Feature",
  "properties": {
    "iso:country":"DE",
    "sg:address":"Am Mantelsgraben 39::",
    "sg:city":"H\u00f6pfingen",
    "sg:phone":"+49 4962/8322000",
    "sg:postcode":"74746",
    "sg:province":"Baden-W\u00fcrttemberg",
    "wof:name":"Egid M\u00dcnch Gmbh & Co Holzbearbeitungs Maschinen",
    "wof:placetype":"venue"
},
  "geometry": {"coordinates":[9.420444,49.592949],"type":"Point"}
}