{
  "type": "Feature",
  "properties": {
    "iso:country":"DE",
    "sg:address":"Drosselweg 1",
    "sg:city":"Esens",
    "sg:phone":"+49 4971/858",
    "sg:postcode":"26427",
    "sg:province":"Niedersachsen",
    "wof:name":"Sepp Kleinheinz Architekt",
    "wof:placetype":"venue"
},
  "geometry": {"coordinates":[7.610945,53.629032],"type":"Point"}
}