{
  "type": "Feature",
  "properties": {
    "iso:country":"DE",
    "sg:address":"Emetzheimer Str. 1",
    "sg:city":"Wei\u00dfenburg",
    "sg:phone":"+49 9141/2432",
    "sg:postcode":"91781",
    "sg:province":"Bayern",
    "wof:name":"Gutmann E. K.",
    "wof:placetype":"venue"
},
  "geometry": {"coordinates":[10.961221,49.02795],"type":"Point"}
}