{
  "type": "Feature",
  "properties": {
    "iso:country":"DE",
    "sg:address":"Hof\u00e4ckerstr. 5",
    "sg:city":"Wendelstein",
    "sg:phone":"+49 9129/8393",
    "sg:postcode":"90530",
    "sg:province":"Bayern",
    "wof:name":"Georg L\u00f6sch",
    "wof:placetype":"venue"
},
  "geometry": {"coordinates":[11.197367,49.326313],"type":"Point"}
}