{
  "type": "Feature",
  "properties": {
    "iso:country":"DE",
    "sg:address":"Bolzhurststr. 58",
    "sg:city":"Willst\u00e4tt",
    "sg:phone":"+49 7852/7679",
    "sg:postcode":"77731",
    "sg:province":"Baden-W\u00fcrttemberg",
    "wof:name":"Heuwagen",
    "wof:placetype":"venue"
},
  "geometry": {"coordinates":[7.9226818085,48.5778541565],"type":"Point"}
}