{
  "type": "Feature",
  "properties": {
    "iso:country":"DE",
    "sg:address":"Stein\u00e4cker 37",
    "sg:city":"Ilshofen",
    "sg:phone":"+49 7904/8414",
    "sg:postcode":"74532",
    "sg:province":"Baden-W\u00fcrttemberg",
    "wof:name":"Br\u00f6llos Gmbh Inh. Felix D Hooghe",
    "wof:placetype":"venue"
},
  "geometry": {"coordinates":[9.928219,49.155869],"type":"Point"}
}