{
  "type": "Feature",
  "properties": {
    "iso:country":"DE",
    "sg:address":"Odenwaldstr. 88",
    "sg:city":"Otzberg",
    "sg:phone":"+49 6162/71762",
    "sg:postcode":"64853",
    "sg:province":"Hessen",
    "wof:name":"Gastst\u00e4tte Waldeck",
    "wof:placetype":"venue"
},
  "geometry": {"coordinates":[8.9249315262,49.8196678162],"type":"Point"}
}