{
  "type": "Feature",
  "properties": {
    "iso:country":"DE",
    "sg:address":"Am Augarten 11",
    "sg:city":"Wettenberg",
    "sg:phone":"+49 641/85885",
    "sg:postcode":"35435",
    "sg:province":"Hessen",
    "wof:name":"Lutz Dort",
    "wof:placetype":"venue"
},
  "geometry": {"coordinates":[8.640247,50.60894],"type":"Point"}
}