{
  "type": "Feature",
  "properties": {
    "iso:country":"DE",
    "sg:address":"Wilhelm-Raabe-Weg 17a",
    "sg:city":"Buchholz",
    "sg:phone":"+49 4181/30336",
    "sg:postcode":"21244",
    "sg:province":"Niedersachsen",
    "wof:name":"Hrd Import Und Export Gmbh",
    "wof:placetype":"venue"
},
  "geometry": {"coordinates":[9.866091,53.340054],"type":"Point"}
}