{
  "type": "Feature",
  "properties": {
    "iso:country":"DE",
    "sg:address":"Am Steinbruch 8",
    "sg:city":"Bretten",
    "sg:phone":"+49 7252/7239",
    "sg:postcode":"75015",
    "sg:province":"Baden-W\u00fcrttemberg",
    "wof:name":"Walter Pfitzenmeier",
    "wof:placetype":"venue"
},
  "geometry": {"coordinates":[8.7099294662,49.0318527222],"type":"Point"}
}