{
  "type": "Feature",
  "properties": {
    "iso:country":"DE",
    "sg:address":"Rathausstr. 10",
    "sg:city":"Breitungen",
    "sg:phone":"+49 36848/87149",
    "sg:postcode":"98597",
    "sg:province":"Th\u00fcringen",
    "wof:name":"Thomas Schlesinger",
    "wof:placetype":"venue"
},
  "geometry": {"coordinates":[10.3279094696,50.7584724426],"type":"Point"}
}