{
  "type": "Feature",
  "properties": {
    "iso:country":"DE",
    "sg:address":"Go\u00dfweg 24",
    "sg:city":"Kupferberg",
    "sg:postcode":"95362",
    "sg:province":"Bayern",
    "wof:name":"Heidi Blinninger",
    "wof:placetype":"venue"
},
  "geometry": {"coordinates":[11.57297,50.135616],"type":"Point"}
}