{
  "type": "Feature",
  "properties": {
    "iso:country":"DE",
    "sg:address":"Im K\u00f6nigsbusch 73",
    "sg:city":"Duisburg",
    "sg:postcode":"47249",
    "sg:province":"Nordrhein-Westfalen",
    "wof:name":"Kwadsart: Internetgalerie F\u00fcr Sponane \u00d6lmalerei",
    "wof:placetype":"venue"
},
  "geometry": {"coordinates":[6.77347,51.386444],"type":"Point"}
}