{
  "type": "Feature",
  "properties": {
    "iso:country":"DE",
    "sg:address":"T\u00f6pferstr. 15",
    "sg:city":"Springe",
    "sg:phone":"+49 5041/2522",
    "sg:postcode":"31832",
    "sg:province":"Niedersachsen",
    "wof:name":"W. H\u00f6lscher",
    "wof:placetype":"venue"
},
  "geometry": {"coordinates":[9.518266,52.166584],"type":"Point"}
}