{
  "type": "Feature",
  "properties": {
    "iso:country":"DE",
    "sg:address":"Augustinerstr. 46",
    "sg:city":"Mainz",
    "sg:phone":"+49 6131/22706",
    "sg:postcode":"55116",
    "sg:province":"Rheinland-Pfalz",
    "wof:name":"A. Herlitzius",
    "wof:placetype":"venue"
},
  "geometry": {"coordinates":[8.2743310928,49.9972877502],"type":"Point"}
}