{
  "type": "Feature",
  "properties": {
    "iso:country":"DE",
    "sg:address":"Neusser Str. 14",
    "sg:city":"K\u00f6ln",
    "sg:phone":"+49 221/131441",
    "sg:postcode":"50670",
    "sg:province":"Nordrhein-Westfalen",
    "wof:name":"Bsb Datentechnik Gmbh",
    "wof:placetype":"venue"
},
  "geometry": {"coordinates":[6.9573030472,50.9516906738],"type":"Point"}
}