{
  "type": "Feature",
  "properties": {
    "iso:country":"DE",
    "sg:address":"Rathausstr. 26",
    "sg:city":"Schwerte",
    "sg:phone":"+49 2304/16548",
    "sg:postcode":"58239",
    "sg:province":"Nordrhein-Westfalen",
    "wof:name":"H. O. Bovensmann",
    "wof:placetype":"venue"
},
  "geometry": {"coordinates":[7.564753,51.444538],"type":"Point"}
}