{
  "type": "Feature",
  "properties": {
    "iso:country":"DE",
    "sg:address":"Lange Str. 66",
    "sg:city":"Haren",
    "sg:phone":"+49 5932/2011",
    "sg:postcode":"49733",
    "sg:province":"Niedersachsen",
    "wof:name":"Hako Immobilien- Verwaltung Gmbh",
    "wof:placetype":"venue"
},
  "geometry": {"coordinates":[7.2449297905,52.7900390625],"type":"Point"}
}