{
  "type": "Feature",
  "properties": {
    "iso:country":"DE",
    "sg:address":"Hauptstr. 61",
    "sg:city":"Leer",
    "sg:phone":"+49 491/7032",
    "sg:postcode":"26789",
    "sg:province":"Niedersachsen",
    "wof:name":"T. Rulffes",
    "wof:placetype":"venue"
},
  "geometry": {"coordinates":[7.484028,53.235958],"type":"Point"}
}