{
  "type": "Feature",
  "properties": {
    "iso:country":"DE",
    "sg:address":"Raiffeisenstr. 25",
    "sg:city":"Veitsh\u00f6chheim",
    "sg:phone":"+49 931/900780",
    "sg:postcode":"97209",
    "sg:province":"Bayern",
    "wof:name":"Wkt D\u00e4mmstoffe Gmbh & Co. Holding Ohg",
    "wof:placetype":"venue"
},
  "geometry": {"coordinates":[9.902354,49.833828],"type":"Point"}
}