{
  "type": "Feature",
  "properties": {
    "iso:country":"DE",
    "sg:address":"Narzissenweg 12",
    "sg:city":"Weissach",
    "sg:phone":"+49 7191/310658",
    "sg:postcode":"71554",
    "sg:province":"Baden-W\u00fcrttemberg",
    "wof:name":"M. Klopka",
    "wof:placetype":"venue"
},
  "geometry": {"coordinates":[9.500947,48.926247],"type":"Point"}
}