{
  "type": "Feature",
  "properties": {
    "iso:country":"DE",
    "sg:address":"Schachendorf 43",
    "sg:city":"Cham",
    "sg:phone":"+49 9944/497",
    "sg:postcode":"93413",
    "sg:province":"Bayern",
    "wof:name":"Ignaz Kernbichl",
    "wof:placetype":"venue"
},
  "geometry": {"coordinates":[12.696844101,49.1685218811],"type":"Point"}
}