{
  "type": "Feature",
  "properties": {
    "iso:country":"DE",
    "sg:address":"56112",
    "sg:city":"Lahnstein",
    "sg:phone":"+49 2621/17080",
    "sg:postcode":"56112",
    "sg:province":"Rheinland-Pfalz",
    "wof:name":"Volksbank Rhein-lahn Eg",
    "wof:placetype":"venue"
},
  "geometry": {"coordinates":[7.67221,50.300289],"type":"Point"}
}