{
  "type": "Feature",
  "properties": {
    "iso:country":"DE",
    "sg:address":"Siegener Str. 3",
    "sg:city":"Kreuztal",
    "sg:phone":"+49 4927/325970",
    "sg:postcode":"57223",
    "sg:province":"Nordrhein-Westfalen",
    "wof:name":"Stadtsparkasse Kreuztal",
    "wof:placetype":"venue"
},
  "geometry": {"coordinates":[7.990407,50.959404],"type":"Point"}
}