{
  "type": "Feature",
  "properties": {
    "iso:country":"DE",
    "sg:address":"Semmelweisstr. 17",
    "sg:city":"Potsdam",
    "sg:phone":"+49 331/7481440",
    "sg:postcode":"14482",
    "sg:province":"Brandenburg",
    "wof:name":"Martys Pizzaservice",
    "wof:placetype":"venue"
},
  "geometry": {"coordinates":[13.0981,52.397873],"type":"Point"}
}