{
  "type": "Feature",
  "properties": {
    "iso:country":"DE",
    "sg:address":"Pottenstein",
    "sg:city":"Pottenstein",
    "sg:phone":"+49 9243/474",
    "sg:postcode":"91278",
    "sg:province":"Bayern",
    "wof:name":"Raiffeisenbank G\u00f6\u00dfweinstein Eg",
    "wof:placetype":"venue"
},
  "geometry": {"coordinates":[11.41921,49.768311],"type":"Point"}
}