{
  "type": "Feature",
  "properties": {
    "iso:country":"DE",
    "sg:address":"Falkenweg 1",
    "sg:city":"Ennepetal",
    "sg:phone":"+49 2333/62451",
    "sg:postcode":"58256",
    "sg:province":"Nordrhein-Westfalen",
    "wof:name":"Markus Eicker",
    "wof:placetype":"venue"
},
  "geometry": {"coordinates":[7.3838601112,51.3136711121],"type":"Point"}
}