{
  "type": "Feature",
  "properties": {
    "iso:country":"DE",
    "sg:address":"Ostsee Raiffeisenstr 1::",
    "sg:city":"Kiel",
    "sg:postcode":"24103",
    "sg:province":"Schleswig-Holstein",
    "wof:name":"Landkreditbank Schleswig-holstein Ag",
    "wof:placetype":"venue"
},
  "geometry": {"coordinates":[10.133549,54.323654],"type":"Point"}
}