{
  "type": "Feature",
  "properties": {
    "iso:country":"DE",
    "sg:address":"Mittelweg 1",
    "sg:city":"Northeim",
    "sg:phone":"+49 5551/53655",
    "sg:postcode":"37154",
    "sg:province":"Niedersachsen",
    "wof:name":"Kraftstofftanks F\u00fcr Boote",
    "wof:placetype":"venue"
},
  "geometry": {"coordinates":[9.9826059341,51.7182884216],"type":"Point"}
}