{
  "type": "Feature",
  "properties": {
    "iso:country":"DE",
    "sg:address":"B\u00fcrgermeister-Smidt-Str. 37",
    "sg:city":"Bremerhaven",
    "sg:phone":"+49 471/9413490",
    "sg:postcode":"27568",
    "sg:province":"Bremen",
    "wof:name":"Optiker Bode",
    "wof:placetype":"venue"
},
  "geometry": {"coordinates":[8.5796489716,53.5432777405],"type":"Point"}
}