{
  "type": "Feature",
  "properties": {
    "iso:country":"DE",
    "sg:address":"Karlstr. 8",
    "sg:city":"Hamburg",
    "sg:phone":"+49 40/2202614",
    "sg:postcode":"22085",
    "sg:province":"Hamburg",
    "wof:name":"Anahita Azad Textilien Design & Vertrieb",
    "wof:placetype":"venue"
},
  "geometry": {"coordinates":[10.010412,53.574085],"type":"Point"}
}