{
  "type": "Feature",
  "properties": {
    "iso:country":"DE",
    "sg:address":"Schulstr. 1",
    "sg:city":"Lengefeld",
    "sg:phone":"+49 37367/83030",
    "sg:postcode":"09514",
    "sg:province":"Sachsen",
    "wof:name":"Ruth M\u00fcller",
    "wof:placetype":"venue"
},
  "geometry": {"coordinates":[13.195837,50.717995],"type":"Point"}
}