{
  "type": "Feature",
  "properties": {
    "iso:country":"DE",
    "sg:address":"Dachtelstr. 10",
    "sg:city":"M\u00f6ssingen",
    "sg:phone":"+49 7473/8851",
    "sg:postcode":"72116",
    "sg:province":"Baden-W\u00fcrttemberg",
    "wof:name":"Willy Nill",
    "wof:placetype":"venue"
},
  "geometry": {"coordinates":[9.0530977249,48.4102325439],"type":"Point"}
}