{
  "type": "Feature",
  "properties": {
    "iso:country":"DE",
    "sg:address":"B\u00e4uminghausstr. 80",
    "sg:city":"Essen",
    "sg:phone":"+49 201/312437",
    "sg:postcode":"45326",
    "sg:province":"Nordrhein-Westfalen",
    "wof:name":"Wetzchewald Inh. Karakosta Gmbh",
    "wof:placetype":"venue"
},
  "geometry": {"coordinates":[7.0035758018,51.4792137146],"type":"Point"}
}