{
  "type": "Feature",
  "properties": {
    "iso:country":"DE",
    "sg:address":"Josef-Schneider-Str. 2",
    "sg:city":"W\u00fcrzburg",
    "sg:postcode":"97080",
    "sg:province":"Bayern",
    "wof:name":"Wiss. Institut Abt. Nuklearmedizin",
    "wof:placetype":"venue"
},
  "geometry": {"coordinates":[9.9535655975,49.8009414673],"type":"Point"}
}