{
  "type": "Feature",
  "properties": {
    "iso:country":"DE",
    "sg:address":"Vareler Str. 6 a",
    "sg:city":"Bockhorn",
    "sg:phone":"+49 4453/7559",
    "sg:postcode":"26345",
    "sg:province":"Niedersachsen",
    "wof:name":"Georg Ahlhorn E. K.",
    "wof:placetype":"venue"
},
  "geometry": {"coordinates":[8.0312728882,53.3919563293],"type":"Point"}
}