{
  "type": "Feature",
  "properties": {
    "iso:country":"DE",
    "sg:address":"Sudetenstr. 6",
    "sg:city":"Kaufbeuren",
    "sg:phone":"+49 8341/97960",
    "sg:postcode":"87600",
    "sg:province":"Bayern",
    "wof:name":"Expert Techno Markt Kaufbeuren Gmbh & Co. Kg",
    "wof:placetype":"venue"
},
  "geometry": {"coordinates":[10.6462221146,47.8977890015],"type":"Point"}
}