{
  "type": "Feature",
  "properties": {
    "iso:country":"DE",
    "sg:address":"Robert-Bosch-Str. 2",
    "sg:city":"Konstanz",
    "sg:phone":"+49 7531/59120",
    "sg:postcode":"78467",
    "sg:province":"Baden-W\u00fcrttemberg",
    "wof:name":"E-center",
    "wof:placetype":"venue"
},
  "geometry": {"coordinates":[9.1495037079,47.6759796143],"type":"Point"}
}