{
  "type": "Feature",
  "properties": {
    "iso:country":"DE",
    "sg:address":"Am Knippchen 54a",
    "sg:city":"Bonn",
    "sg:phone":"+49 228/484126",
    "sg:postcode":"53229",
    "sg:province":"Nordrhein-Westfalen",
    "wof:name":"D. Folde",
    "wof:placetype":"venue"
},
  "geometry": {"coordinates":[7.1480789185,50.7380828857],"type":"Point"}
}