{
  "type": "Feature",
  "properties": {
    "iso:country":"DE",
    "sg:address":"Oberbreitenau 1",
    "sg:city":"Bischofsmais",
    "sg:phone":"+49 9920/255",
    "sg:postcode":"94253",
    "sg:province":"Bayern",
    "wof:name":"Landshuter Haus",
    "wof:placetype":"venue"
},
  "geometry": {"coordinates":[13.0346803665,48.916103363],"type":"Point"}
}