{
  "type": "Feature",
  "properties": {
    "iso:country":"DE",
    "sg:address":"Lungwitzer Str. 41",
    "sg:city":"Hohenstein-Ernstthal",
    "sg:phone":"+49 3723/3020",
    "sg:postcode":"09337",
    "sg:province":"Sachsen",
    "wof:name":"T. Knoof Immobilienmakler",
    "wof:placetype":"venue"
},
  "geometry": {"coordinates":[12.7140798569,50.8000564575],"type":"Point"}
}