{
  "type": "Feature",
  "properties": {
    "iso:country":"DE",
    "sg:address":"An der Gonna 26",
    "sg:city":"Sangerhausen",
    "sg:postcode":"06526",
    "sg:province":"Sachsen-Anhalt",
    "wof:name":"Leinetahler Hochbau Gmbh",
    "wof:placetype":"venue"
},
  "geometry": {"coordinates":[11.3002786636,51.4758605957],"type":"Point"}
}