{
  "type": "Feature",
  "properties": {
    "iso:country":"DE",
    "sg:address":"Arthur-Hausmann-Str. 7",
    "sg:city":"Leipzig",
    "sg:phone":"+49 341/582393",
    "sg:postcode":"04129",
    "sg:province":"Sachsen",
    "wof:name":"Lutz Von Bosse",
    "wof:placetype":"venue"
},
  "geometry": {"coordinates":[12.392172,51.361961],"type":"Point"}
}