{
  "type": "Feature",
  "properties": {
    "iso:country":"DE",
    "sg:address":"Hauptmann-Boelcke-Weg 1",
    "sg:city":"Bad Pyrmont",
    "sg:phone":"+49 5281/2539",
    "sg:postcode":"31812",
    "sg:province":"Niedersachsen",
    "wof:name":"Gerhard Gr\u00fcne Vergn\u00fcgungsst\u00e4tte",
    "wof:placetype":"venue"
},
  "geometry": {"coordinates":[9.252292,51.980412],"type":"Point"}
}