{
  "type": "Feature",
  "properties": {
    "iso:country":"DE",
    "sg:address":"Bertramstr. 8",
    "sg:city":"Frankfurt",
    "sg:phone":"+49 4969/15091",
    "sg:postcode":"60320",
    "sg:province":"Hessen",
    "wof:name":"Hr Werbung Gmbh",
    "wof:placetype":"venue"
},
  "geometry": {"coordinates":[8.675299,50.135849],"type":"Point"}
}