{
  "type": "Feature",
  "properties": {
    "iso:country":"DE",
    "sg:address":"T\u00f6lzer Str. 30-30 a",
    "sg:city":"Gr\u00fcnwald",
    "sg:phone":"+49 89/641430",
    "sg:postcode":"82031",
    "sg:province":"Bayern",
    "wof:name":"Alcas Gmbh",
    "wof:placetype":"venue"
},
  "geometry": {"coordinates":[11.5208816528,48.0343704224],"type":"Point"}
}