{
  "type": "Feature",
  "properties": {
    "iso:country":"DE",
    "sg:address":"Miraustr. 62-80",
    "sg:city":"Berlin",
    "sg:phone":"+49 30/43566841",
    "sg:postcode":"13509",
    "sg:province":"Berlin",
    "wof:name":"Cart-connection Betriebs Gmbh",
    "wof:placetype":"venue"
},
  "geometry": {"coordinates":[13.308435,52.585125],"type":"Point"}
}