{
  "type": "Feature",
  "properties": {
    "iso:country":"DE",
    "sg:address":"Baersberg 28",
    "sg:city":"Kleve",
    "sg:phone":"+49 2821/93557",
    "sg:postcode":"47533",
    "sg:province":"Nordrhein-Westfalen",
    "wof:name":"Franz-josef Van Den Berg",
    "wof:placetype":"venue"
},
  "geometry": {"coordinates":[6.197812,51.795834],"type":"Point"}
}