{
  "type": "Feature",
  "properties": {
    "iso:country":"DE",
    "sg:address":"Schumannstr. 21",
    "sg:city":"Haan",
    "sg:phone":"+49 212/91027",
    "sg:postcode":"42781",
    "sg:province":"Nordrhein-Westfalen",
    "wof:name":"Dr. E. Voosholz Ingenieur",
    "wof:placetype":"venue"
},
  "geometry": {"coordinates":[7.0123147964,51.1846160889],"type":"Point"}
}