{
  "type": "Feature",
  "properties": {
    "iso:country":"DE",
    "sg:address":"Lange Str. 17",
    "sg:city":"Waren",
    "sg:phone":"+49 3991/667625",
    "sg:postcode":"17192",
    "sg:province":"Mecklenburg-Vorpommern",
    "wof:name":"Hans-ulrich Schneidler",
    "wof:placetype":"venue"
},
  "geometry": {"coordinates":[12.7829904556,53.5109405518],"type":"Point"}
}