{
  "type": "Feature",
  "properties": {
    "iso:country":"DE",
    "sg:address":"Willibrordusstrasse 6",
    "sg:city":"Bad Neuenahr-Ahrweiler",
    "sg:phone":"+49 2641/94050",
    "sg:postcode":"53474",
    "sg:province":"Rheinland-Pfalz",
    "wof:name":"Kr\u00f6lls G\u00e4stehaus Am Kurpark.",
    "wof:placetype":"venue"
},
  "geometry": {"coordinates":[7.1365962029,50.5398178101],"type":"Point"}
}