{
  "type": "Feature",
  "properties": {
    "iso:country":"DE",
    "sg:address":"Lange Str. 37",
    "sg:city":"Grimma",
    "sg:phone":"+49 3437/911366",
    "sg:postcode":"04668",
    "sg:province":"Sachsen",
    "wof:name":"Adler-apotheke",
    "wof:placetype":"venue"
},
  "geometry": {"coordinates":[12.727784,51.234802],"type":"Point"}
}