{
  "type": "Feature",
  "properties": {
    "iso:country":"DE",
    "sg:address":"Vierradener Str. 47",
    "sg:city":"Schwedt",
    "sg:phone":"+49 3332/524375",
    "sg:postcode":"16303",
    "sg:province":"Brandenburg",
    "wof:name":"J\u00e4gerhof",
    "wof:placetype":"venue"
},
  "geometry": {"coordinates":[14.2855796814,53.0571632385],"type":"Point"}
}