{
  "type": "Feature",
  "properties": {
    "iso:country":"DE",
    "sg:address":"Maximilian-Philipp-Str. 16",
    "sg:city":"T\u00fcrkheim",
    "sg:phone":"+49 8245/3999",
    "sg:postcode":"86842",
    "sg:province":"Bayern",
    "wof:name":"Albert Bedic Architekt",
    "wof:placetype":"venue"
},
  "geometry": {"coordinates":[10.640008,48.062012],"type":"Point"}
}