{
  "type": "Feature",
  "properties": {
    "iso:country":"DE",
    "sg:address":"Am Birkenbusch 9a",
    "sg:city":"Bochum",
    "sg:phone":"+49 234/935630",
    "sg:postcode":"44803",
    "sg:province":"Nordrhein-Westfalen",
    "wof:name":"Georg Gotthardt Ingenieur",
    "wof:placetype":"venue"
},
  "geometry": {"coordinates":[7.2403302193,51.4699630737],"type":"Point"}
}