{
  "type": "Feature",
  "properties": {
    "iso:country":"DE",
    "sg:address":"Wanheimer Str. 616",
    "sg:city":"Duisburg",
    "sg:phone":"+49 203/708401",
    "sg:postcode":"47249",
    "sg:province":"Nordrhein-Westfalen",
    "wof:name":"W. Linke",
    "wof:placetype":"venue"
},
  "geometry": {"coordinates":[6.7416119576,51.3857574463],"type":"Point"}
}