{
  "type": "Feature",
  "properties": {
    "iso:country":"DE",
    "sg:address":"Bei Maria Schray 30",
    "sg:city":"Pfullendorf",
    "sg:phone":"+49 7552/8330",
    "sg:postcode":"88630",
    "sg:province":"Baden-W\u00fcrttemberg",
    "wof:name":"Gerhard Stanischewski Ingenieur",
    "wof:placetype":"venue"
},
  "geometry": {"coordinates":[9.258496,47.928452],"type":"Point"}
}