{
  "type": "Feature",
  "properties": {
    "iso:country":"DE",
    "sg:address":"Burgwindheim",
    "sg:city":"Burgwindheim",
    "sg:phone":"+49 9551/205",
    "sg:postcode":"96154",
    "sg:province":"Bayern",
    "wof:name":"Raiffeisenbank Burgebrach Eg",
    "wof:placetype":"venue"
},
  "geometry": {"coordinates":[10.597,49.827202],"type":"Point"}
}