{
  "type": "Feature",
  "properties": {
    "iso:country":"DE",
    "sg:address":"Engersgaustr. 95",
    "sg:city":"Neuwied",
    "sg:phone":"+49 2622/83658",
    "sg:postcode":"56566",
    "sg:province":"Rheinland-Pfalz",
    "wof:name":"Johann Geisler",
    "wof:placetype":"venue"
},
  "geometry": {"coordinates":[7.5452260971,50.43932724],"type":"Point"}
}