{
  "type": "Feature",
  "properties": {
    "iso:country":"DE",
    "sg:address":"An der Molkerei 7",
    "sg:city":"Bedburg-Hau",
    "sg:phone":"+49 2821/69781",
    "sg:postcode":"47551",
    "sg:province":"Nordrhein-Westfalen",
    "wof:name":"N. Huismann Gmbh",
    "wof:placetype":"venue"
},
  "geometry": {"coordinates":[6.195939,51.768024],"type":"Point"}
}