{
  "type": "Feature",
  "properties": {
    "iso:country":"DE",
    "sg:address":"Roitzheimer Str. 113",
    "sg:city":"Euskirchen",
    "sg:phone":"+49 2251/64056",
    "sg:postcode":"53879",
    "sg:province":"Nordrhein-Westfalen",
    "wof:name":"Media-lager Bielinsky Gmbh",
    "wof:placetype":"venue"
},
  "geometry": {"coordinates":[6.7995820045,50.6526908875],"type":"Point"}
}