{
  "type": "Feature",
  "properties": {
    "iso:country":"DE",
    "sg:address":"Gutleutstr. 96",
    "sg:city":"Frankfurt",
    "sg:phone":"+49 4969/6660681",
    "sg:postcode":"60329",
    "sg:province":"Hessen",
    "wof:name":"Sysma Marketing Gmbh",
    "wof:placetype":"venue"
},
  "geometry": {"coordinates":[8.663895,50.10371],"type":"Point"}
}