{
  "type": "Feature",
  "properties": {
    "iso:country":"DE",
    "sg:address":"Hauptstr. 27",
    "sg:city":"Zell",
    "sg:phone":"+49 7835/477",
    "sg:postcode":"77736",
    "sg:province":"Baden-W\u00fcrttemberg",
    "wof:name":"Franz Nock",
    "wof:placetype":"venue"
},
  "geometry": {"coordinates":[8.064739,48.346935],"type":"Point"}
}