{
  "type": "Feature",
  "properties": {
    "iso:country":"DE",
    "sg:address":"Fabrikgasse 3",
    "sg:city":"Marktredwitz",
    "sg:phone":"+49 9231/3452",
    "sg:postcode":"95615",
    "sg:province":"Bayern",
    "wof:name":"M. Hensel Elektro-install.",
    "wof:placetype":"venue"
},
  "geometry": {"coordinates":[12.087005,49.998276],"type":"Point"}
}