{
  "type": "Feature",
  "properties": {
    "iso:country":"DE",
    "sg:address":"Talblick 35",
    "sg:city":"Regensburg",
    "sg:phone":"+49 941/400552",
    "sg:postcode":"93055",
    "sg:province":"Bayern",
    "wof:name":"H. Segerer Architekt",
    "wof:placetype":"venue"
},
  "geometry": {"coordinates":[12.157085,49.034908],"type":"Point"}
}