{
  "type": "Feature",
  "properties": {
    "iso:country":"DE",
    "sg:address":"Felix-Klein-Str. 77",
    "sg:city":"Erlangen",
    "sg:phone":"+49 9131/13366",
    "sg:postcode":"91058",
    "sg:province":"Bayern",
    "wof:name":"H. Adrian",
    "wof:placetype":"venue"
},
  "geometry": {"coordinates":[11.000186,49.572651],"type":"Point"}
}