{
  "type": "Feature",
  "properties": {
    "iso:country":"DE",
    "sg:address":"Hauptstr. 3",
    "sg:city":"Suhl",
    "sg:phone":"+49 3681/303771",
    "sg:postcode":"98529",
    "sg:province":"Th\u00fcringen",
    "wof:name":"H. Schott",
    "wof:placetype":"venue"
},
  "geometry": {"coordinates":[10.6306600571,50.6042900085],"type":"Point"}
}