{
  "type": "Feature",
  "properties": {
    "iso:country":"DE",
    "sg:address":"Ludgerusstr. 2",
    "sg:city":"D\u00fcsseldorf",
    "sg:phone":"+49 211/335795",
    "sg:postcode":"40225",
    "sg:province":"Nordrhein-Westfalen",
    "wof:name":"Katholisches Pfarramt St. Suitbertus",
    "wof:placetype":"venue"
},
  "geometry": {"coordinates":[6.7820501328,51.2038154602],"type":"Point"}
}