{
  "type": "Feature",
  "properties": {
    "iso:country":"DE",
    "sg:address":"Pfarrgasse 73",
    "sg:city":"Ramsla",
    "sg:phone":"+49 36452/72693",
    "sg:postcode":"99439",
    "sg:province":"Th\u00fcringen",
    "wof:name":"Malerbetrieb Gert K\u00fchn Gmbh",
    "wof:placetype":"venue"
},
  "geometry": {"coordinates":[11.28641,51.049595],"type":"Point"}
}