{
  "type": "Feature",
  "properties": {
    "iso:country":"DE",
    "sg:address":"Griesheimer Str. 13",
    "sg:city":"Weiterstadt",
    "sg:phone":"+49 6150/10930",
    "sg:postcode":"64331",
    "sg:province":"Hessen",
    "wof:name":"1a Last Minute Reisen Fl\u00fcge Online Buchen",
    "wof:placetype":"venue"
},
  "geometry": {"coordinates":[8.5804281235,49.9045753479],"type":"Point"}
}