{
  "type": "Feature",
  "properties": {
    "iso:country":"DE",
    "sg:address":"Windm\u00fchlenstr 4",
    "sg:city":"L\u00f6bichau",
    "sg:phone":"+49 36602/3860",
    "sg:postcode":"04626",
    "sg:province":"Th\u00fcringen",
    "wof:name":"Frigotechnik Handels Gmbh",
    "wof:placetype":"venue"
},
  "geometry": {"coordinates":[12.223793,50.875389],"type":"Point"}
}