{
  "type": "Feature",
  "properties": {
    "iso:country":"DE",
    "sg:address":"Untere Hauptstra\u00dfe 13",
    "sg:city":"Hohenried",
    "sg:phone":"+49 8454",
    "sg:postcode":"86564",
    "sg:province":"Bayern",
    "wof:name":"Hohenrieder Musibuam",
    "wof:placetype":"venue"
},
  "geometry": {"coordinates":[11.358961,48.632534],"type":"Point"}
}