{
  "type": "Feature",
  "properties": {
    "iso:country":"DE",
    "sg:address":"Dresdener Str. 2",
    "sg:city":"Esslingen",
    "sg:phone":"+49 711/311075",
    "sg:postcode":"73730",
    "sg:province":"Baden-W\u00fcrttemberg",
    "wof:name":"Besemer Wohnbau Gmbh & Co.",
    "wof:placetype":"venue"
},
  "geometry": {"coordinates":[9.340441,48.734924],"type":"Point"}
}