{
  "type": "Feature",
  "properties": {
    "iso:country":"DE",
    "sg:address":"H\u00fclsenweg 21",
    "sg:city":"Detmold",
    "sg:phone":"+49 5231/88205",
    "sg:postcode":"32760",
    "sg:province":"Nordrhein-Westfalen",
    "wof:name":"Hans Mengedoht Architekt",
    "wof:placetype":"venue"
},
  "geometry": {"coordinates":[8.836014,51.92157],"type":"Point"}
}