{
  "type": "Feature",
  "properties": {
    "iso:country":"DE",
    "sg:address":"R\u00f6ntgenstr. 26 - 30",
    "sg:city":"Reutlingen",
    "sg:phone":"+49 7121/54809",
    "sg:postcode":"72770",
    "sg:province":"Baden-W\u00fcrttemberg",
    "wof:name":"Horst Kern",
    "wof:placetype":"venue"
},
  "geometry": {"coordinates":[9.1850013733,48.4996757507],"type":"Point"}
}