{
  "type": "Feature",
  "properties": {
    "iso:country":"DE",
    "sg:address":"Am Kippgarten 46",
    "sg:city":"Oer-Erkenschwick",
    "sg:postcode":"45739",
    "sg:province":"Nordrhein-Westfalen",
    "wof:name":"Akv Autokran-vermietung Gmbh & Co. Kg",
    "wof:placetype":"venue"
},
  "geometry": {"coordinates":[7.2410311699,51.6501846313],"type":"Point"}
}