{
  "type": "Feature",
  "properties": {
    "iso:country":"DE",
    "sg:address":"Alte B311 Nr.4",
    "sg:city":"Riedlingen-Neufra",
    "sg:phone":"+49 7371/95990",
    "sg:postcode":"88499",
    "sg:province":"Baden-W\u00fcrttemberg",
    "wof:name":"Baisch Gmbh",
    "wof:placetype":"venue"
},
  "geometry": {"coordinates":[9.4463853836,48.1459388733],"type":"Point"}
}