{
  "type": "Feature",
  "properties": {
    "iso:country":"DE",
    "sg:address":"Portiastr. 2",
    "sg:city":"M\u00fcnchen",
    "sg:postcode":"81545",
    "sg:province":"Bayern",
    "wof:name":"Rgw-termindienst- Gmbh",
    "wof:placetype":"venue"
},
  "geometry": {"coordinates":[11.562014,48.089123],"type":"Point"}
}