{
  "type": "Feature",
  "properties": {
    "iso:country":"DE",
    "sg:address":"Angel\u00e4cker 5-1",
    "sg:city":"Bodelshausen",
    "sg:phone":"+49 7471/71015",
    "sg:postcode":"72411",
    "sg:province":"Baden-W\u00fcrttemberg",
    "wof:name":"S. Trippler",
    "wof:placetype":"venue"
},
  "geometry": {"coordinates":[8.974822,48.385998],"type":"Point"}
}