{
  "type": "Feature",
  "properties": {
    "iso:country":"DE",
    "sg:address":"Haimendorfer Str. 10",
    "sg:city":"Schwaig",
    "sg:phone":"+49 911/500472",
    "sg:postcode":"90571",
    "sg:province":"Bayern",
    "wof:name":"Elektro T.u.m. Gmbh",
    "wof:placetype":"venue"
},
  "geometry": {"coordinates":[11.202339,49.466366],"type":"Point"}
}