{
  "type": "Feature",
  "properties": {
    "iso:country":"DE",
    "sg:address":"Dorfstr. 80",
    "sg:city":"Duisburg",
    "sg:phone":"+49 203/787934",
    "sg:postcode":"47259",
    "sg:province":"Nordrhein-Westfalen",
    "wof:name":"Dorfsch\u00e4nke",
    "wof:placetype":"venue"
},
  "geometry": {"coordinates":[6.7132620811,51.3496398926],"type":"Point"}
}