{
  "type": "Feature",
  "properties": {
    "iso:country":"DE",
    "sg:address":"Bockhorner Heide 29",
    "sg:city":"Telgte",
    "sg:phone":"+49 2504/2095",
    "sg:postcode":"48291",
    "sg:province":"Nordrhein-Westfalen",
    "wof:name":"Tonius Hertleif",
    "wof:placetype":"venue"
},
  "geometry": {"coordinates":[7.803278,51.9939],"type":"Point"}
}