{
  "type": "Feature",
  "properties": {
    "iso:country":"DE",
    "sg:address":"Basler Str. 23a",
    "sg:city":"L\u00f6rrach",
    "sg:phone":"+49 7621/2075",
    "sg:postcode":"79540",
    "sg:province":"Baden-W\u00fcrttemberg",
    "wof:name":"Dr. K. H. Eberle Immobilienmakler",
    "wof:placetype":"venue"
},
  "geometry": {"coordinates":[7.6584858894,47.6012649536],"type":"Point"}
}