{
  "type": "Feature",
  "properties": {
    "iso:country":"DE",
    "sg:address":"Alzeyer Str.",
    "sg:city":"Bad Kreuznach",
    "sg:postcode":"55543",
    "sg:province":"Rheinland-Pfalz",
    "wof:name":"City Car Sylvia Axer",
    "wof:placetype":"venue"
},
  "geometry": {"coordinates":[7.8784060478,49.8348617554],"type":"Point"}
}