{
  "type": "Feature",
  "properties": {
    "iso:country":"DE",
    "sg:address":"Heinrich-Heine-Str. 16",
    "sg:city":"Soltau",
    "sg:phone":"+49 5191/979230",
    "sg:postcode":"29614",
    "sg:province":"Niedersachsen",
    "wof:name":"Translation Andreas",
    "wof:placetype":"venue"
},
  "geometry": {"coordinates":[9.841318,52.986729],"type":"Point"}
}