{
  "type": "Feature",
  "properties": {
    "iso:country":"DE",
    "sg:address":"Ketschengasse 47",
    "sg:city":"Coburg",
    "sg:phone":"+49 9561/94114",
    "sg:postcode":"96450",
    "sg:province":"Bayern",
    "wof:name":"Trachten Ferschl Inh. Carolin Henze E. K.",
    "wof:placetype":"venue"
},
  "geometry": {"coordinates":[10.9645252228,50.2554893494],"type":"Point"}
}