{
  "type": "Feature",
  "properties": {
    "iso:country":"DE",
    "sg:address":"Bundesstr. 52",
    "sg:city":"Gundelfingen",
    "sg:phone":"+49 761/580218",
    "sg:postcode":"79194",
    "sg:province":"Baden-W\u00fcrttemberg",
    "wof:name":"Sozialstation N\u00f6rdlicher Breisgau E. V.",
    "wof:placetype":"venue"
},
  "geometry": {"coordinates":[7.866271,48.04089],"type":"Point"}
}