{
  "type": "Feature",
  "properties": {
    "iso:country":"DE",
    "sg:address":"Fasanenweg 27",
    "sg:city":"Kiebitzreihe",
    "sg:phone":"+49 4121/5960",
    "sg:postcode":"25368",
    "sg:province":"Schleswig-Holstein",
    "wof:name":"Waltraud Walter",
    "wof:placetype":"venue"
},
  "geometry": {"coordinates":[9.619387,53.784389],"type":"Point"}
}