{
  "type": "Feature",
  "properties": {
    "iso:country":"DE",
    "sg:address":"Minslebener Str. 81",
    "sg:city":"Wernigerode",
    "sg:postcode":"38855",
    "sg:province":"Sachsen-Anhalt",
    "wof:name":"Hms Haussanierungen Modernisierungen Schwarz Gmbh",
    "wof:placetype":"venue"
},
  "geometry": {"coordinates":[10.803852,51.842636],"type":"Point"}
}