{
  "type": "Feature",
  "properties": {
    "iso:country":"DE",
    "sg:address":"Am Heilholz 5",
    "sg:city":"Bad Feilnbach",
    "sg:phone":"+49 8066/437",
    "sg:postcode":"83075",
    "sg:province":"Bayern",
    "wof:name":"Fremdenheim Helmut Hanke",
    "wof:placetype":"venue"
},
  "geometry": {"coordinates":[12.0147647858,47.7728652954],"type":"Point"}
}