{
  "type": "Feature",
  "properties": {
    "iso:country":"DE",
    "sg:address":"Frankfurter Str. 31b",
    "sg:city":"Karben",
    "sg:phone":"+49 6039/3337",
    "sg:postcode":"61184",
    "sg:province":"Hessen",
    "wof:name":"International Bookstore Clemens Becker",
    "wof:placetype":"venue"
},
  "geometry": {"coordinates":[8.7432508469,50.2312698364],"type":"Point"}
}