{
  "type": "Feature",
  "properties": {
    "iso:country":"DE",
    "sg:address":"An der F\u00f6rsterei",
    "sg:city":"Ottendorf-Okrilla",
    "sg:phone":"+49 35205/52718",
    "sg:postcode":"01458",
    "sg:province":"Sachsen",
    "wof:name":"Karsten Grafe Transport Gmbh",
    "wof:placetype":"venue"
},
  "geometry": {"coordinates":[13.8338699341,51.1964836121],"type":"Point"}
}