{
  "type": "Feature",
  "properties": {
    "iso:country":"DE",
    "sg:address":"Spitalstr. 18",
    "sg:city":"Grafenau",
    "sg:phone":"+49 8552/96420",
    "sg:postcode":"94481",
    "sg:province":"Bayern",
    "wof:name":"Brk Altenheim",
    "wof:placetype":"venue"
},
  "geometry": {"coordinates":[13.394631,48.853031],"type":"Point"}
}