{
  "type": "Feature",
  "properties": {
    "iso:country":"DE",
    "sg:address":"Froitscheidter Str. 53",
    "sg:city":"Nideggen",
    "sg:postcode":"52385",
    "sg:province":"Nordrhein-Westfalen",
    "wof:name":"Lauf Mit In Schmidt",
    "wof:placetype":"venue"
},
  "geometry": {"coordinates":[6.4095511436,50.6702537537],"type":"Point"}
}