{
  "type": "Feature",
  "properties": {
    "iso:country":"DE",
    "sg:address":"Ring 4",
    "sg:city":"Rotenburg",
    "sg:phone":"+49 6623/1510",
    "sg:postcode":"36199",
    "sg:province":"Hessen",
    "wof:name":"Martin Fischer",
    "wof:placetype":"venue"
},
  "geometry": {"coordinates":[9.728908,50.994362],"type":"Point"}
}