{
  "type": "Feature",
  "properties": {
    "iso:country":"DE",
    "sg:address":"Asbacher Str. 105",
    "sg:city":"Eitorf",
    "sg:phone":"+49 2243/2820",
    "sg:postcode":"53783",
    "sg:province":"Nordrhein-Westfalen",
    "wof:name":"Rolf Schreuer Grabdenkm\u00e4ler",
    "wof:placetype":"venue"
},
  "geometry": {"coordinates":[7.4460101128,50.7634735107],"type":"Point"}
}