{
  "type": "Feature",
  "properties": {
    "iso:country":"DE",
    "sg:address":"Oberndorf",
    "sg:city":"Waldkirchen",
    "sg:phone":"+49 8581/4970",
    "sg:postcode":"94065",
    "sg:province":"Bayern",
    "wof:name":"Gastst\u00e4tte Ernst Altenstrasser",
    "wof:placetype":"venue"
},
  "geometry": {"coordinates":[13.6415262222,48.7276687622],"type":"Point"}
}