{
  "type": "Feature",
  "properties": {
    "iso:country":"DE",
    "sg:address":"K\u00f6nigsteinstr. 17",
    "sg:city":"Leipzig",
    "sg:phone":"+49 341/9414664",
    "sg:postcode":"04207",
    "sg:province":"Sachsen",
    "wof:name":"T. Bauer",
    "wof:placetype":"venue"
},
  "geometry": {"coordinates":[12.2635450363,51.3061943054],"type":"Point"}
}