{
  "type": "Feature",
  "properties": {
    "iso:country":"DE",
    "sg:address":"Allerseelenstr. 7",
    "sg:city":"K\u00f6ln",
    "sg:phone":"+49 221/8307747",
    "sg:postcode":"51105",
    "sg:province":"Nordrhein-Westfalen",
    "wof:name":"Sis Gesellschaft F\u00fcr Haus & Grundbesitz Mbh",
    "wof:placetype":"venue"
},
  "geometry": {"coordinates":[6.985475,50.92202],"type":"Point"}
}