{
  "type": "Feature",
  "properties": {
    "iso:country":"DE",
    "sg:address":"Twedter Holz 15c",
    "sg:city":"Flensburg",
    "sg:postcode":"24944",
    "sg:province":"Schleswig-Holstein",
    "wof:name":"Axel Schr\u00f6der Verwaltungs Gmbh",
    "wof:placetype":"venue"
},
  "geometry": {"coordinates":[9.475568,54.818764],"type":"Point"}
}