{
  "type": "Feature",
  "properties": {
    "iso:country":"DE",
    "sg:address":"Spandauer Str 49-51",
    "sg:city":"Luckenwalde",
    "sg:phone":"+49 3371/632580",
    "sg:postcode":"14943",
    "sg:province":"Brandenburg",
    "wof:name":"Hilu-brunnenfilterbau Dipl.-ing. Peter Oppermann",
    "wof:placetype":"venue"
},
  "geometry": {"coordinates":[13.1638879776,52.0970726013],"type":"Point"}
}