{
  "type": "Feature",
  "properties": {
    "iso:country":"DE",
    "sg:address":"Mittelstr. 28",
    "sg:city":"Neustadt",
    "sg:phone":"+49 5032/3403",
    "sg:postcode":"31535",
    "sg:province":"Niedersachsen",
    "wof:name":"Adolf K\u00f6ster",
    "wof:placetype":"venue"
},
  "geometry": {"coordinates":[9.4611148834,52.5050392151],"type":"Point"}
}