{
  "type": "Feature",
  "properties": {
    "iso:country":"DE",
    "sg:address":"Wilhelmstr. 94",
    "sg:city":"Heidenheim",
    "sg:phone":"+49 7321/44088",
    "sg:postcode":"89518",
    "sg:province":"Baden-W\u00fcrttemberg",
    "wof:name":"Ziegler Kg",
    "wof:placetype":"venue"
},
  "geometry": {"coordinates":[10.1388702393,48.6794090271],"type":"Point"}
}