{
  "type": "Feature",
  "properties": {
    "iso:country":"DE",
    "sg:address":"Friedrich-Engels-Str. 7",
    "sg:city":"Hohenstein-Ernstthal",
    "sg:phone":"+49 3723/411258",
    "sg:postcode":"09337",
    "sg:province":"Sachsen",
    "wof:name":"Ic Immissionsschutz Consulting Gmbh",
    "wof:placetype":"venue"
},
  "geometry": {"coordinates":[12.7058906555,50.8015556335],"type":"Point"}
}