{
  "type": "Feature",
  "properties": {
    "iso:country":"DE",
    "sg:address":"Landstr. 2",
    "sg:city":"Ettlingen",
    "sg:phone":"+49 7243/90085",
    "sg:postcode":"76275",
    "sg:province":"Baden-W\u00fcrttemberg",
    "wof:name":"Graphcom Gesellschaft F\u00fcr Me\u00dftechnik Computer Und",
    "wof:placetype":"venue"
},
  "geometry": {"coordinates":[8.368262,48.926201],"type":"Point"}
}