{
  "type": "Feature",
  "properties": {
    "iso:country":"DE",
    "sg:address":"Friedrichstr. 35",
    "sg:city":"Hanau",
    "sg:phone":"+49 6181/93710",
    "sg:postcode":"63450",
    "sg:province":"Hessen",
    "wof:name":"Heim & W\u00f6lk Gmbh Architekten",
    "wof:placetype":"venue"
},
  "geometry": {"coordinates":[8.920289,50.127361],"type":"Point"}
}