{
  "type": "Feature",
  "properties": {
    "iso:country":"DE",
    "sg:address":"Vilshofener Str. 2",
    "sg:city":"Eging",
    "sg:phone":"+49 8544/1766",
    "sg:postcode":"94535",
    "sg:province":"Bayern",
    "wof:name":"Adolf Klampfl",
    "wof:placetype":"venue"
},
  "geometry": {"coordinates":[13.2652578354,48.7121124268],"type":"Point"}
}