{
  "type": "Feature",
  "properties": {
    "iso:country":"DE",
    "sg:address":"Theaterstr. 2",
    "sg:city":"Hannover",
    "sg:phone":"+49 511/304220",
    "sg:postcode":"30159",
    "sg:province":"Niedersachsen",
    "wof:name":"Grundeigent\u00fcmer-versicherung Versicherungsagentur Wag",
    "wof:placetype":"venue"
},
  "geometry": {"coordinates":[9.7423257828,52.3737792969],"type":"Point"}
}