{
  "type": "Feature",
  "properties": {
    "iso:country":"DE",
    "sg:address":"Friedhofstr. 6",
    "sg:city":"Kleinmaischeid",
    "sg:postcode":"56271",
    "sg:province":"Rheinland-Pfalz",
    "wof:name":"Prime Service Germany Gmbh",
    "wof:placetype":"venue"
},
  "geometry": {"coordinates":[7.6085290909,50.5127258301],"type":"Point"}
}