{
  "type": "Feature",
  "properties": {
    "iso:country":"DE",
    "sg:address":"leitenstrasse 40",
    "sg:city":"geretsried",
    "sg:postcode":"82538",
    "sg:province":"Bayern",
    "wof:name":"Telefonkosten.de",
    "wof:placetype":"venue"
},
  "geometry": {"coordinates":[11.439526,47.888756],"type":"Point"}
}