{
  "type": "Feature",
  "properties": {
    "iso:country":"DE",
    "sg:address":"Eugen-S\u00e4nger-Str.",
    "sg:city":"Brunnthal",
    "sg:postcode":"85649",
    "sg:province":"Bayern",
    "wof:name":"Deborate Gmbh",
    "wof:placetype":"venue"
},
  "geometry": {"coordinates":[11.6646080017,48.0396232605],"type":"Point"}
}