{
  "type": "Feature",
  "properties": {
    "iso:country":"DE",
    "sg:address":"Wischenstr. 17",
    "sg:city":"Edewecht",
    "sg:phone":"+49 4486/2802",
    "sg:postcode":"26188",
    "sg:province":"Niedersachsen",
    "wof:name":"Rolf Hegeler",
    "wof:placetype":"venue"
},
  "geometry": {"coordinates":[8.044286,53.103378],"type":"Point"}
}