{
  "type": "Feature",
  "properties": {
    "iso:country":"DE",
    "sg:address":"Am Kalkbrunnen 16",
    "sg:city":"Neckargem\u00fcnd",
    "sg:postcode":"69151",
    "sg:province":"Baden-W\u00fcrttemberg",
    "wof:name":"Fit For Fun",
    "wof:placetype":"venue"
},
  "geometry": {"coordinates":[8.8008775711,49.3806266785],"type":"Point"}
}