{
  "type": "Feature",
  "properties": {
    "iso:country":"DE",
    "sg:address":"Am M\u00fchlenweg 58",
    "sg:city":"Remagen",
    "sg:phone":"+49 2642/20060",
    "sg:postcode":"53424",
    "sg:province":"Rheinland-Pfalz",
    "wof:name":"Petra Ossenberg",
    "wof:placetype":"venue"
},
  "geometry": {"coordinates":[7.196723938,50.6006660461],"type":"Point"}
}