{
  "type": "Feature",
  "properties": {
    "iso:country":"DE",
    "sg:address":"Berenbosteler Strasse 72",
    "sg:city":"Garbsen",
    "sg:phone":"+49 5131",
    "sg:postcode":"30823",
    "sg:province":"Niedersachsen",
    "wof:name":"Smart Center Hannover-garbsen",
    "wof:placetype":"venue"
},
  "geometry": {"coordinates":[9.5932807922,52.4229621887],"type":"Point"}
}