{
  "type": "Feature",
  "properties": {
    "iso:country":"DE",
    "sg:address":"Weinerstr. 10",
    "sg:city":"Ochtrup",
    "sg:phone":"+49 2553/2532",
    "sg:postcode":"48607",
    "sg:province":"Nordrhein-Westfalen",
    "wof:name":"Gustav Hues",
    "wof:placetype":"venue"
},
  "geometry": {"coordinates":[7.188288,52.209576],"type":"Point"}
}