{
  "type": "Feature",
  "properties": {
    "iso:country":"DE",
    "sg:city":"Teising",
    "sg:phone":"+49 8633/7915",
    "sg:postcode":"84576",
    "sg:province":"Bayern",
    "wof:name":"Georg Kojer",
    "wof:placetype":"venue"
},
  "geometry": {"coordinates":[12.60954,48.22699],"type":"Point"}
}