{
  "type": "Feature",
  "properties": {
    "iso:country":"DE",
    "sg:address":"Donnersbergweg 1",
    "sg:city":"Ludwigshafen",
    "sg:postcode":"67059",
    "sg:province":"Rheinland-Pfalz",
    "wof:name":"Hmh Bautr\u00e4ger F\u00fcr \u00f6kologische Sanierungsmethoden Gmbh",
    "wof:placetype":"venue"
},
  "geometry": {"coordinates":[8.423874,49.472637],"type":"Point"}
}