{
  "type": "Feature",
  "properties": {
    "iso:country":"DE",
    "sg:address":"Stuttgarter Str. 48",
    "sg:city":"Steinenbronn",
    "sg:postcode":"71144",
    "sg:province":"Baden-W\u00fcrttemberg",
    "wof:name":"Testra Gesellschaft F\u00fcr Elastische",
    "wof:placetype":"venue"
},
  "geometry": {"coordinates":[9.1204357147,48.6636047363],"type":"Point"}
}