{
  "type": "Feature",
  "properties": {
    "iso:country":"DE",
    "sg:address":"Imbuschweg 40",
    "sg:city":"Berlin",
    "sg:phone":"+49 30/6031069",
    "sg:postcode":"12353",
    "sg:province":"Berlin",
    "wof:name":"Sport-gr\u00f6ger Gmbh",
    "wof:placetype":"venue"
},
  "geometry": {"coordinates":[13.457616,52.430161],"type":"Point"}
}