{
  "type": "Feature",
  "properties": {
    "iso:country":"DE",
    "sg:address":"Industriestr. 34 a",
    "sg:city":"Kissing",
    "sg:phone":"+49 8233/5055",
    "sg:postcode":"86438",
    "sg:province":"Bayern",
    "wof:name":"Staible Holding Gmbh",
    "wof:placetype":"venue"
},
  "geometry": {"coordinates":[10.961439,48.300076],"type":"Point"}
}