{
  "type": "Feature",
  "properties": {
    "iso:country":"DE",
    "sg:address":"Vorbecker Landweg 8",
    "sg:city":"Schwaan",
    "sg:phone":"+49 3844/813410",
    "sg:postcode":"18258",
    "sg:province":"Mecklenburg-Vorpommern",
    "wof:name":"Horst Schneider",
    "wof:placetype":"venue"
},
  "geometry": {"coordinates":[12.091478,53.932922],"type":"Point"}
}