{
  "type": "Feature",
  "properties": {
    "iso:country":"DE",
    "sg:address":"Hauptstr. 61",
    "sg:city":"Waiblingen",
    "sg:phone":"+49 7151/563211",
    "sg:postcode":"71334",
    "sg:province":"Baden-W\u00fcrttemberg",
    "wof:name":"Hegnachers Bierpub",
    "wof:placetype":"venue"
},
  "geometry": {"coordinates":[9.2982263565,48.8577919006],"type":"Point"}
}