{
  "type": "Feature",
  "properties": {
    "iso:country":"DE",
    "sg:address":"Menizhofer Weg 15",
    "sg:city":"Meersburg",
    "sg:phone":"+49 4975/329436",
    "sg:postcode":"88709",
    "sg:province":"Baden-W\u00fcrttemberg",
    "wof:name":"Goldbrunner Ohg",
    "wof:placetype":"venue"
},
  "geometry": {"coordinates":[9.279359,47.692345],"type":"Point"}
}