{
  "type": "Feature",
  "properties": {
    "iso:country":"DE",
    "sg:address":"Petershauser Str. 6",
    "sg:city":"Hohenkammer",
    "sg:phone":"+49 8137/9979551",
    "sg:postcode":"85411",
    "sg:province":"Bayern",
    "wof:name":"Steinbearbeitungsmaschinen Gebraucht",
    "wof:placetype":"venue"
},
  "geometry": {"coordinates":[11.521381,48.423553],"type":"Point"}
}