{
  "type": "Feature",
  "properties": {
    "iso:country":"DE",
    "sg:address":"Heidingsfelder Str. 25",
    "sg:city":"Winterhausen",
    "sg:phone":"+49 9333/90172",
    "sg:postcode":"97286",
    "sg:province":"Bayern",
    "wof:name":"Max Wolf",
    "wof:placetype":"venue"
},
  "geometry": {"coordinates":[10.010134697,49.7118606567],"type":"Point"}
}