{
  "type": "Feature",
  "properties": {
    "iso:country":"DE",
    "sg:address":"Geigelsteinstr. 13b",
    "sg:city":"Prien",
    "sg:phone":"+49 8051/61833",
    "sg:postcode":"83209",
    "sg:province":"Bayern",
    "wof:name":"H. Und R. Mutke",
    "wof:placetype":"venue"
},
  "geometry": {"coordinates":[12.346571,47.853313],"type":"Point"}
}