{
  "type": "Feature",
  "properties": {
    "iso:country":"DE",
    "sg:address":"Im Kirchtal 25",
    "sg:city":"Troisdorf",
    "sg:phone":"+49 2241/42144",
    "sg:postcode":"53844",
    "sg:province":"Nordrhein-Westfalen",
    "wof:name":"M. Reuschenbach",
    "wof:placetype":"venue"
},
  "geometry": {"coordinates":[7.120586,50.795193],"type":"Point"}
}