{
  "type": "Feature",
  "properties": {
    "iso:country":"DE",
    "sg:address":"Altzschillen 23",
    "sg:city":"Wechselburg",
    "sg:phone":"+49 37384/303",
    "sg:postcode":"09306",
    "sg:province":"Sachsen",
    "wof:name":"Horst Friedemann",
    "wof:placetype":"venue"
},
  "geometry": {"coordinates":[12.77029,50.994179],"type":"Point"}
}