{
  "type": "Feature",
  "properties": {
    "iso:country":"DE",
    "sg:address":"K\u00f6lner Str. 72",
    "sg:city":"Frechen",
    "sg:phone":"+49 2234/57077",
    "sg:postcode":"50226",
    "sg:province":"Nordrhein-Westfalen",
    "wof:name":"Segerkegelgesellschaft Dr. Gottfried Cremer Ohg",
    "wof:placetype":"venue"
},
  "geometry": {"coordinates":[6.8195381165,50.9109992981],"type":"Point"}
}