{
  "type": "Feature",
  "properties": {
    "iso:country":"DE",
    "sg:address":"Talbr\u00fcckstr. 1",
    "sg:city":"Freisen",
    "sg:phone":"+49 6855/237",
    "sg:postcode":"66629",
    "sg:province":"Saarland",
    "wof:name":"Ostertal-apotheke Inh. Peter Bergmann",
    "wof:placetype":"venue"
},
  "geometry": {"coordinates":[7.261164,49.525623],"type":"Point"}
}