{
  "type": "Feature",
  "properties": {
    "iso:country":"DE",
    "sg:address":"Heimgartenstr. 1",
    "sg:city":"Planegg",
    "sg:phone":"+49 89/8596481",
    "sg:postcode":"82152",
    "sg:province":"Bayern",
    "wof:name":"Michael Hallinger",
    "wof:placetype":"venue"
},
  "geometry": {"coordinates":[11.4180088043,48.1061477661],"type":"Point"}
}