{
  "type": "Feature",
  "properties": {
    "iso:country":"DE",
    "sg:address":"Untere Bergerheide 30",
    "sg:city":"Wuppertal",
    "sg:phone":"+49 202/722738",
    "sg:postcode":"42113",
    "sg:province":"Nordrhein-Westfalen",
    "wof:name":"Dr. Teja Boedicker Steuerberater",
    "wof:placetype":"venue"
},
  "geometry": {"coordinates":[7.1078782082,51.2676353455],"type":"Point"}
}