{
  "type": "Feature",
  "properties": {
    "iso:country":"DE",
    "sg:address":"Oldenburger Str. 91",
    "sg:city":"Delmenhorst",
    "sg:phone":"+49 4221/81882",
    "sg:postcode":"27753",
    "sg:province":"Niedersachsen",
    "wof:name":"A. Ackermann",
    "wof:placetype":"venue"
},
  "geometry": {"coordinates":[8.6050319672,53.049156189],"type":"Point"}
}