{
  "type": "Feature",
  "properties": {
    "iso:country":"DE",
    "sg:address":"Kloberstr. 5",
    "sg:city":"Mainz-Kastel",
    "sg:postcode":"55252",
    "sg:province":"Hessen",
    "wof:name":"Evangelisches Pfarramt",
    "wof:placetype":"venue"
},
  "geometry": {"coordinates":[8.284901619,50.0073471069],"type":"Point"}
}