{
  "type": "Feature",
  "properties": {
    "iso:country":"DE",
    "sg:address":"Hagenstr. 21c",
    "sg:city":"Pritzwalk",
    "sg:phone":"+49 3395/302475",
    "sg:postcode":"16928",
    "sg:province":"Brandenburg",
    "wof:name":"Klaus G\u00e4dke Gmbh",
    "wof:placetype":"venue"
},
  "geometry": {"coordinates":[12.177817,53.144745],"type":"Point"}
}