{
  "type": "Feature",
  "properties": {
    "iso:country":"DE",
    "sg:address":"Bessinger Str. 14",
    "sg:city":"Lich",
    "sg:phone":"+49 6404/5618",
    "sg:postcode":"35423",
    "sg:province":"Hessen",
    "wof:name":"Walter Roth",
    "wof:placetype":"venue"
},
  "geometry": {"coordinates":[8.829984,50.525764],"type":"Point"}
}