{
  "type": "Feature",
  "properties": {
    "iso:country":"DE",
    "sg:address":"G\u00e4rtnerstr. 41",
    "sg:city":"M\u00fcnchen",
    "sg:phone":"+49 89/1411074",
    "sg:postcode":"80992",
    "sg:province":"Bayern",
    "wof:name":"Bruno Romer Elektroinstallation",
    "wof:placetype":"venue"
},
  "geometry": {"coordinates":[11.531666,48.177959],"type":"Point"}
}