{
  "type": "Feature",
  "properties": {
    "iso:country":"DE",
    "sg:address":"Dellbr\u00fccker Hauptstr. 170",
    "sg:city":"K\u00f6ln",
    "sg:phone":"+49 221/683650",
    "sg:postcode":"51069",
    "sg:province":"Nordrhein-Westfalen",
    "wof:name":"Delmondo",
    "wof:placetype":"venue"
},
  "geometry": {"coordinates":[7.069307,50.980064],"type":"Point"}
}