{
  "type": "Feature",
  "properties": {
    "iso:country":"DE",
    "sg:address":"Fehrbellinstr. 14",
    "sg:city":"K\u00f6ln",
    "sg:phone":"+49 221/741266",
    "sg:postcode":"50737",
    "sg:province":"Nordrhein-Westfalen",
    "wof:name":"Werner Goldberg Ingenieur",
    "wof:placetype":"venue"
},
  "geometry": {"coordinates":[6.9489388466,50.9833564758],"type":"Point"}
}