{
  "type": "Feature",
  "properties": {
    "iso:country":"DE",
    "sg:address":"K\u00f6nigswiese 2",
    "sg:city":"Gelsenkirchen",
    "sg:phone":"+49 209/395581",
    "sg:postcode":"45894",
    "sg:province":"Nordrhein-Westfalen",
    "wof:name":"Norbert Temminghoff",
    "wof:placetype":"venue"
},
  "geometry": {"coordinates":[7.052185,51.582413],"type":"Point"}
}