{
  "type": "Feature",
  "properties": {
    "iso:country":"DE",
    "sg:address":"Siechenstr. 66",
    "sg:city":"Bamberg",
    "sg:phone":"+49 951/61892",
    "sg:postcode":"96052",
    "sg:province":"Bayern",
    "wof:name":"Rudi Lendner",
    "wof:placetype":"venue"
},
  "geometry": {"coordinates":[10.889275,49.901142],"type":"Point"}
}