{
  "type": "Feature",
  "properties": {
    "iso:country":"DE",
    "sg:address":"Werkstr. 14",
    "sg:city":"Wissen",
    "sg:phone":"+49 2742/5753",
    "sg:postcode":"57537",
    "sg:province":"Rheinland-Pfalz",
    "wof:name":"Berger & S\u00f6hne Bauunternehmen Gmbh",
    "wof:placetype":"venue"
},
  "geometry": {"coordinates":[7.749809,50.764416],"type":"Point"}
}