{
  "type": "Feature",
  "properties": {
    "iso:country":"DE",
    "sg:address":"Im Horn 2",
    "sg:city":"Wagenfeld",
    "sg:phone":"+49 5444/368",
    "sg:postcode":"49419",
    "sg:province":"Niedersachsen",
    "wof:name":"Wilhelm Nackenhorst",
    "wof:placetype":"venue"
},
  "geometry": {"coordinates":[8.536817,52.549454],"type":"Point"}
}