{
  "type": "Feature",
  "properties": {
    "iso:country":"DE",
    "sg:address":"Wilhelmstr. 19",
    "sg:city":"Juist",
    "sg:phone":"+49 4935/447",
    "sg:postcode":"26571",
    "sg:province":"Niedersachsen",
    "wof:name":"Pension J. Heuer",
    "wof:placetype":"venue"
},
  "geometry": {"coordinates":[6.9984760284,53.6775588989],"type":"Point"}
}