{
  "type": "Feature",
  "properties": {
    "iso:country":"DE",
    "sg:address":"Klosterstr. 4",
    "sg:city":"Wolfenb\u00fcttel",
    "sg:phone":"+49 5331/1224",
    "sg:postcode":"38300",
    "sg:province":"Niedersachsen",
    "wof:name":"Ev. Pfarramt Pfarrbez. Ii Gem. Hauptkirche Bmv",
    "wof:placetype":"venue"
},
  "geometry": {"coordinates":[10.5363292694,52.1628799438],"type":"Point"}
}