{
  "type": "Feature",
  "properties": {
    "iso:country":"DE",
    "sg:address":"Drosselweg 14",
    "sg:city":"Dettingen",
    "sg:phone":"+49 7123/71201",
    "sg:postcode":"72581",
    "sg:province":"Baden-W\u00fcrttemberg",
    "wof:name":"Heinz Krohmer",
    "wof:placetype":"venue"
},
  "geometry": {"coordinates":[9.355456,48.531403],"type":"Point"}
}