{
  "type": "Feature",
  "properties": {
    "iso:country":"DE",
    "sg:address":"Poisentalstr. 106",
    "sg:city":"Freital",
    "sg:phone":"+49 351/6494540",
    "sg:postcode":"01705",
    "sg:province":"Sachsen",
    "wof:name":"Christian Grafe",
    "wof:placetype":"venue"
},
  "geometry": {"coordinates":[13.6695518494,50.9876861572],"type":"Point"}
}