{
  "type": "Feature",
  "properties": {
    "iso:country":"DE",
    "sg:address":"Friesoyther Str. 8",
    "sg:city":"B\u00f6sel",
    "sg:phone":"+49 4494/86211",
    "sg:postcode":"26219",
    "sg:province":"Niedersachsen",
    "wof:name":"Touristica Reisen Gmbh",
    "wof:placetype":"venue"
},
  "geometry": {"coordinates":[7.9523711205,53.0062942505],"type":"Point"}
}