{
  "type": "Feature",
  "properties": {
    "iso:country":"DE",
    "sg:address":"Siegfriedstr. 67",
    "sg:city":"Wuppertal",
    "sg:phone":"+49 202/745045",
    "sg:postcode":"42117",
    "sg:province":"Nordrhein-Westfalen",
    "wof:name":"Am Zoo Kosmetik Doris Urhausen",
    "wof:placetype":"venue"
},
  "geometry": {"coordinates":[7.105786,51.242008],"type":"Point"}
}