{
  "type": "Feature",
  "properties": {
    "iso:country":"DE",
    "sg:address":"Jacobsohnstr. 10",
    "sg:city":"Berlin",
    "sg:phone":"+49 30/4788050",
    "sg:postcode":"13086",
    "sg:province":"Berlin",
    "wof:name":"Wei\u00dfenseer Glashaus- Produktions- Und",
    "wof:placetype":"venue"
},
  "geometry": {"coordinates":[13.432872,52.554893],"type":"Point"}
}