{
  "type": "Feature",
  "properties": {
    "iso:country":"DE",
    "sg:address":"Mettmannerstr. 56-64",
    "sg:city":"Velbert",
    "sg:phone":"+49 4920/5120810",
    "sg:postcode":"42549",
    "sg:province":"Nordrhein-Westfalen",
    "wof:name":"Wilka Schliesstechnik Gmbh",
    "wof:placetype":"venue"
},
  "geometry": {"coordinates":[7.0498361588,51.3315887451],"type":"Point"}
}