{
  "type": "Feature",
  "properties": {
    "iso:country":"DE",
    "sg:address":"L\u00f6wentorstr. 7",
    "sg:city":"Elze",
    "sg:phone":"+49 5068/2345",
    "sg:postcode":"31008",
    "sg:province":"Niedersachsen",
    "wof:name":"Heinrich Lehnhoff",
    "wof:placetype":"venue"
},
  "geometry": {"coordinates":[9.736509,52.115204],"type":"Point"}
}