{
  "type": "Feature",
  "properties": {
    "iso:country":"DE",
    "sg:address":"Lisztstr.",
    "sg:city":"Berlin",
    "sg:phone":"+49 30/5081054",
    "sg:postcode":"10318",
    "sg:province":"Berlin",
    "wof:name":"Mouseevent",
    "wof:placetype":"venue"
},
  "geometry": {"coordinates":[13.520108223,52.4889526367],"type":"Point"}
}