{
  "type": "Feature",
  "properties": {
    "iso:country":"DE",
    "sg:address":"Haseler Str. 43",
    "sg:city":"Wehr",
    "sg:phone":"+49 7762/522900",
    "sg:postcode":"79664",
    "sg:province":"Baden-W\u00fcrttemberg",
    "wof:name":"Boris Rapp",
    "wof:placetype":"venue"
},
  "geometry": {"coordinates":[7.9011301994,47.6364898682],"type":"Point"}
}