{
  "type": "Feature",
  "properties": {
    "iso:country":"DE",
    "sg:address":"Klotenstr. 275",
    "sg:city":"Kamp-Lintfort",
    "sg:phone":"+49 2842/41700",
    "sg:postcode":"47475",
    "sg:province":"Nordrhein-Westfalen",
    "wof:name":"Heinrich Biesemann",
    "wof:placetype":"venue"
},
  "geometry": {"coordinates":[6.484098,51.485851],"type":"Point"}
}