{
  "type": "Feature",
  "properties": {
    "iso:country":"DE",
    "sg:address":"Marktplatz 11",
    "sg:city":"Obernzenn",
    "sg:phone":"+49 9844/1213",
    "sg:postcode":"91619",
    "sg:province":"Bayern",
    "wof:name":"Raiffeisenbank Obernzenn Eg",
    "wof:placetype":"venue"
},
  "geometry": {"coordinates":[10.467774,49.450516],"type":"Point"}
}