{
  "type": "Feature",
  "properties": {
    "iso:country":"DE",
    "sg:address":"M\u00f6hlstr. 19",
    "sg:city":"M\u00fcnchen",
    "sg:phone":"+49 89/986000",
    "sg:postcode":"81675",
    "sg:province":"Bayern",
    "wof:name":"Weinkontor Baron Von Stain Gmbh",
    "wof:placetype":"venue"
},
  "geometry": {"coordinates":[11.6002454758,48.1443443298],"type":"Point"}
}