{
  "type": "Feature",
  "properties": {
    "iso:country":"DE",
    "sg:address":"Ruppendorfer Weg 7",
    "sg:city":"Dresden",
    "sg:phone":"+49 351/2581780",
    "sg:postcode":"01277",
    "sg:province":"Sachsen",
    "wof:name":"Klaus Kn\u00f6fler",
    "wof:placetype":"venue"
},
  "geometry": {"coordinates":[13.79321,51.03059],"type":"Point"}
}