{
  "type": "Feature",
  "properties": {
    "iso:country":"DE",
    "sg:address":"Rudolf-Diesel-Str 20",
    "sg:city":"G\u00fcnzburg",
    "sg:phone":"+49 8221/36530",
    "sg:postcode":"89312",
    "sg:province":"Bayern",
    "wof:name":"Al Luible Speditionsgesellschaft Mbh",
    "wof:placetype":"venue"
},
  "geometry": {"coordinates":[10.271481,48.475735],"type":"Point"}
}