{
  "type": "Feature",
  "properties": {
    "iso:country":"DE",
    "sg:address":"Elisabethstr. 13",
    "sg:city":"Marburg",
    "sg:phone":"+49 6421/67847",
    "sg:postcode":"35037",
    "sg:province":"Hessen",
    "wof:name":"Adler-apotheke",
    "wof:placetype":"venue"
},
  "geometry": {"coordinates":[8.769063,50.815701],"type":"Point"}
}