{
  "type": "Feature",
  "properties": {
    "iso:country":"DE",
    "sg:address":"Kirschbaumwasen 16",
    "sg:city":"Forbach",
    "sg:phone":"+49 7228/2131",
    "sg:postcode":"76596",
    "sg:province":"Baden-W\u00fcrttemberg",
    "wof:name":"Motodrom",
    "wof:placetype":"venue"
},
  "geometry": {"coordinates":[8.3546648026,48.6238174438],"type":"Point"}
}