{
  "type": "Feature",
  "properties": {
    "iso:country":"DE",
    "sg:address":"W\u00f6rishofer Str. 7",
    "sg:city":"T\u00fcrkheim",
    "sg:phone":"+49 8245/652",
    "sg:postcode":"86842",
    "sg:province":"Bayern",
    "wof:name":"Toni Port",
    "wof:placetype":"venue"
},
  "geometry": {"coordinates":[10.6397981644,48.057964325],"type":"Point"}
}