{
  "type": "Feature",
  "properties": {
    "iso:country":"DE",
    "sg:address":"Bucher Str. 14",
    "sg:city":"N\u00fcrnberg",
    "sg:phone":"+49 911/358897",
    "sg:postcode":"90408",
    "sg:province":"Bayern",
    "wof:name":"Udo Wolf",
    "wof:placetype":"venue"
},
  "geometry": {"coordinates":[11.0730314255,49.4599151611],"type":"Point"}
}