{
  "type": "Feature",
  "properties": {
    "iso:country":"DE",
    "sg:address":"Am Kalk",
    "sg:city":"Hadamar",
    "sg:phone":"+49 6433/2181",
    "sg:postcode":"65589",
    "sg:province":"Hessen",
    "wof:name":"Werner Horn Bauschlosserei",
    "wof:placetype":"venue"
},
  "geometry": {"coordinates":[8.044227,50.469116],"type":"Point"}
}