{
  "type": "Feature",
  "properties": {
    "iso:country":"DE",
    "sg:address":"Karl-Marx-Str. 5",
    "sg:city":"Trier",
    "sg:phone":"+49 651/73646",
    "sg:postcode":"54290",
    "sg:province":"Rheinland-Pfalz",
    "wof:name":"Bio-bau-bedarf",
    "wof:placetype":"venue"
},
  "geometry": {"coordinates":[6.6343421936,49.7529296875],"type":"Point"}
}