{
  "type": "Feature",
  "properties": {
    "iso:country":"DE",
    "sg:address":"Unter der Linde 11",
    "sg:city":"Dautphetal",
    "sg:phone":"+49 6468/255",
    "sg:postcode":"35232",
    "sg:province":"Hessen",
    "wof:name":"L\u00fchrig",
    "wof:placetype":"venue"
},
  "geometry": {"coordinates":[8.5252027512,50.8145904541],"type":"Point"}
}