{
  "type": "Feature",
  "properties": {
    "iso:country":"DE",
    "sg:address":"Krumbachweg 11",
    "sg:city":"Emmendingen",
    "sg:phone":"+49 7641/1239",
    "sg:postcode":"79312",
    "sg:province":"Baden-W\u00fcrttemberg",
    "wof:name":"Bernd Huttmann",
    "wof:placetype":"venue"
},
  "geometry": {"coordinates":[7.8864817619,48.1155433655],"type":"Point"}
}