{
  "type": "Feature",
  "properties": {
    "iso:country":"DE",
    "sg:address":"Wohnsig 11",
    "sg:city":"Weismain",
    "sg:phone":"+49 9575/7417",
    "sg:postcode":"96260",
    "sg:province":"Bayern",
    "wof:name":"Georg Schreppel",
    "wof:placetype":"venue"
},
  "geometry": {"coordinates":[11.2406587601,50.0614013672],"type":"Point"}
}