{
  "type": "Feature",
  "properties": {
    "iso:country":"DE",
    "sg:address":"Ludwig-Thoma-Str. 16",
    "sg:city":"Deisenhofen",
    "sg:phone":"+49 89/6651860",
    "sg:postcode":"82041",
    "sg:province":"Bayern",
    "wof:name":"Hotel-garni Abendruhe",
    "wof:placetype":"venue"
},
  "geometry": {"coordinates":[11.5868492126,48.0172805786],"type":"Point"}
}