{
  "type": "Feature",
  "properties": {
    "iso:country":"DE",
    "sg:address":"Siebenbornstr. 5",
    "sg:city":"Simmern",
    "sg:phone":"+49 2620/8482",
    "sg:postcode":"56337",
    "sg:province":"Rheinland-Pfalz",
    "wof:name":"J\u00fcrgen Schneider",
    "wof:placetype":"venue"
},
  "geometry": {"coordinates":[7.671841,50.390785],"type":"Point"}
}