{
  "type": "Feature",
  "properties": {
    "iso:country":"DE",
    "sg:address":"Bahnhof Triefenried 2",
    "sg:city":"Regen",
    "sg:phone":"+49 9921/6313",
    "sg:postcode":"94209",
    "sg:province":"Bayern",
    "wof:name":"Mega-sports-vertriebs Gmbh",
    "wof:placetype":"venue"
},
  "geometry": {"coordinates":[13.0535287857,48.9694595337],"type":"Point"}
}