{
  "type": "Feature",
  "properties": {
    "iso:country":"DE",
    "sg:address":"Paulinstr. 17",
    "sg:city":"Trier",
    "sg:phone":"+49 651/146790",
    "sg:postcode":"54292",
    "sg:province":"Rheinland-Pfalz",
    "wof:name":"Hamburg-mannheimer Versicherungs Ag",
    "wof:placetype":"venue"
},
  "geometry": {"coordinates":[6.6462678909,49.7608642578],"type":"Point"}
}