{
  "type": "Feature",
  "properties": {
    "iso:country":"DE",
    "sg:address":"Barer Str. 70",
    "sg:city":"M\u00fcnchen",
    "sg:phone":"+49 89/2722407",
    "sg:postcode":"80799",
    "sg:province":"Bayern",
    "wof:name":"H. Br\u00f6se Kunstmaler",
    "wof:placetype":"venue"
},
  "geometry": {"coordinates":[11.573868,48.151775],"type":"Point"}
}