{
  "type": "Feature",
  "properties": {
    "iso:country":"DE",
    "sg:address":"Hartstr. 2a",
    "sg:city":"Seefeld",
    "sg:phone":"+49 8152/76280",
    "sg:postcode":"82229",
    "sg:province":"Bayern",
    "wof:name":"C.-c. Prester Immobilienmakler",
    "wof:placetype":"venue"
},
  "geometry": {"coordinates":[11.216635704,48.0392532349],"type":"Point"}
}