{
  "type": "Feature",
  "properties": {
    "iso:country":"DE",
    "sg:address":"Rostocker Str. 2",
    "sg:city":"Sankt Augustin",
    "sg:phone":"+49 2241/332755",
    "sg:postcode":"53757",
    "sg:province":"Nordrhein-Westfalen",
    "wof:name":"Vijitha Abeysinghe Ratnayake",
    "wof:placetype":"venue"
},
  "geometry": {"coordinates":[7.1978449821,50.778629303],"type":"Point"}
}