{
  "type": "Feature",
  "properties": {
    "iso:country":"DE",
    "sg:address":"Leipziger Str. 6",
    "sg:city":"M\u00fchlau",
    "sg:phone":"+49 3722/95396",
    "sg:postcode":"09241",
    "sg:province":"Sachsen",
    "wof:name":"Rosensch\u00e4nke",
    "wof:placetype":"venue"
},
  "geometry": {"coordinates":[12.7588300705,50.9014701843],"type":"Point"}
}