{
  "type": "Feature",
  "properties": {
    "iso:country":"DE",
    "sg:address":"Am Donnersberg 1",
    "sg:city":"Halle",
    "sg:phone":"+49 345/5400182",
    "sg:postcode":"06120",
    "sg:province":"Sachsen-Anhalt",
    "wof:name":"B. A. U. B\u00fcro F\u00fcr Angewandten Umweltschutz Gmbh",
    "wof:placetype":"venue"
},
  "geometry": {"coordinates":[11.9481573105,51.5112228394],"type":"Point"}
}