{
  "type": "Feature",
  "properties": {
    "iso:country":"DE",
    "sg:address":"Bergstr. 17",
    "sg:city":"Roxheim",
    "sg:phone":"+49 671/845222",
    "sg:postcode":"55595",
    "sg:province":"Rheinland-Pfalz",
    "wof:name":"Schaller",
    "wof:placetype":"venue"
},
  "geometry": {"coordinates":[7.813764,49.866165],"type":"Point"}
}