{
  "type": "Feature",
  "properties": {
    "iso:country":"DE",
    "sg:address":"Geilenkirchener Str. 5",
    "sg:city":"Heinsberg",
    "sg:phone":"+49 2452/22955",
    "sg:postcode":"52525",
    "sg:province":"Nordrhein-Westfalen",
    "wof:name":"Heitzer Busch Und Gottschalk",
    "wof:placetype":"venue"
},
  "geometry": {"coordinates":[6.0920600891,51.058139801],"type":"Point"}
}