{
  "type": "Feature",
  "properties": {
    "iso:country":"DE",
    "sg:address":"Bergham 4",
    "sg:city":"Miesbach",
    "sg:postcode":"83714",
    "sg:province":"Bayern",
    "wof:name":"T. Kirzeder",
    "wof:placetype":"venue"
},
  "geometry": {"coordinates":[11.857066,47.792824],"type":"Point"}
}