{
  "type": "Feature",
  "properties": {
    "iso:country":"DE",
    "sg:address":"Sautierstr. 31",
    "sg:city":"Freiburg",
    "sg:phone":"+49 761/33177",
    "sg:postcode":"79104",
    "sg:province":"Baden-W\u00fcrttemberg",
    "wof:name":"Friedrichshof",
    "wof:placetype":"venue"
},
  "geometry": {"coordinates":[7.8529682159,48.0051879883],"type":"Point"}
}