{
  "type": "Feature",
  "properties": {
    "iso:country":"DE",
    "sg:address":"Strelitzer Chaussee 55a",
    "sg:city":"Neustrelitz",
    "sg:postcode":"17235",
    "sg:province":"Mecklenburg-Vorpommern",
    "wof:name":"Bahr Baumarkt",
    "wof:placetype":"venue"
},
  "geometry": {"coordinates":[13.0633001328,53.3623046875],"type":"Point"}
}