{
  "type": "Feature",
  "properties": {
    "iso:country":"DE",
    "sg:address":"Erlanger Str. 25",
    "sg:city":"Wilhelmsdorf",
    "sg:phone":"+49 9104/734",
    "sg:postcode":"91489",
    "sg:province":"Bayern",
    "wof:name":"Helmut Riedel Metallveredelung Gmbh",
    "wof:placetype":"venue"
},
  "geometry": {"coordinates":[10.7427883148,49.5619850159],"type":"Point"}
}