{
  "type": "Feature",
  "properties": {
    "iso:country":"DE",
    "sg:address":"N\u00fcrnberger Str. 34",
    "sg:city":"Bebra",
    "sg:phone":"+49 6622/2840",
    "sg:postcode":"36179",
    "sg:province":"Hessen",
    "wof:name":"Gleim",
    "wof:placetype":"venue"
},
  "geometry": {"coordinates":[9.792876,50.969761],"type":"Point"}
}