{
  "type": "Feature",
  "properties": {
    "iso:country":"DE",
    "sg:address":"Gustav-Fr\u00f6hlich-Allee 18",
    "sg:city":"Dummerstorf",
    "sg:phone":"+49 38208/60544",
    "sg:postcode":"18196",
    "sg:province":"Mecklenburg-Vorpommern",
    "wof:name":"D. Radant",
    "wof:placetype":"venue"
},
  "geometry": {"coordinates":[12.2311220169,54.0148544312],"type":"Point"}
}