{
  "type": "Feature",
  "properties": {
    "iso:country":"DE",
    "sg:address":"Dorfstr. 75",
    "sg:city":"Haren",
    "sg:phone":"+49 5934/1731",
    "sg:postcode":"49733",
    "sg:province":"Niedersachsen",
    "wof:name":"Heinrich Meyer",
    "wof:placetype":"venue"
},
  "geometry": {"coordinates":[7.140146,52.817539],"type":"Point"}
}