{
  "type": "Feature",
  "properties": {
    "iso:country":"DE",
    "sg:address":"Zum Hohehan 20",
    "sg:city":"Aurich",
    "sg:phone":"+49 4947/451",
    "sg:postcode":"26607",
    "sg:province":"Niedersachsen",
    "wof:name":"Anton Schipper",
    "wof:placetype":"venue"
},
  "geometry": {"coordinates":[7.555217,53.539925],"type":"Point"}
}