{
  "type": "Feature",
  "properties": {
    "iso:country":"DE",
    "sg:address":"Sch\u00fctzenstr. 35",
    "sg:city":"Solingen",
    "sg:phone":"+49 212/2442750",
    "sg:postcode":"42659",
    "sg:province":"Nordrhein-Westfalen",
    "wof:name":"Svg Strassenverkehrsgen. Nordrhein Egmbh",
    "wof:placetype":"venue"
},
  "geometry": {"coordinates":[7.092116,51.164795],"type":"Point"}
}