{
  "type": "Feature",
  "properties": {
    "iso:country":"DE",
    "sg:address":"Schlo\u00dfbergstr. 16",
    "sg:city":"Bingen",
    "sg:phone":"+49 6721/15089",
    "sg:postcode":"55411",
    "sg:province":"Rheinland-Pfalz",
    "wof:name":"Josef Winter",
    "wof:placetype":"venue"
},
  "geometry": {"coordinates":[7.8943891525,49.9644813538],"type":"Point"}
}