{
  "type": "Feature",
  "properties": {
    "iso:country":"DE",
    "sg:address":"Unterer Backertsweg 7",
    "sg:city":"Aachen",
    "sg:postcode":"52074",
    "sg:province":"Nordrhein-Westfalen",
    "wof:name":"Kath. Kinderheim Stadtwald Maria Im Tann",
    "wof:placetype":"venue"
},
  "geometry": {"coordinates":[6.0499448776,50.7420539856],"type":"Point"}
}