{
  "type": "Feature",
  "properties": {
    "iso:country":"DE",
    "sg:address":"Alte Str. 42",
    "sg:city":"Olbernhau",
    "sg:phone":"+49 37360/72178",
    "sg:postcode":"09526",
    "sg:province":"Sachsen",
    "wof:name":"J\u00fcrgen H\u00fcbsch",
    "wof:placetype":"venue"
},
  "geometry": {"coordinates":[13.382497,50.648846],"type":"Point"}
}