{
  "type": "Feature",
  "properties": {
    "iso:country":"DE",
    "sg:address":"Auf'm Herz 1",
    "sg:city":"Am\u00f6neburg",
    "sg:phone":"+49 6422/3882",
    "sg:postcode":"35287",
    "sg:province":"Hessen",
    "wof:name":"Aerobic Und Fitness",
    "wof:placetype":"venue"
},
  "geometry": {"coordinates":[8.8806638718,50.8057518005],"type":"Point"}
}