{
  "type": "Feature",
  "properties": {
    "iso:country":"DE",
    "sg:address":"Thurnauer Str. 6",
    "sg:city":"Kasendorf",
    "sg:phone":"+49 9228/5648",
    "sg:postcode":"95359",
    "sg:province":"Bayern",
    "wof:name":"Mulzerstube Pizzeria",
    "wof:placetype":"venue"
},
  "geometry": {"coordinates":[11.3508520126,50.0354042053],"type":"Point"}
}