{
  "type": "Feature",
  "properties": {
    "iso:country":"DE",
    "sg:address":"Finkenstr. 5",
    "sg:city":"Rattenberg",
    "sg:postcode":"94371",
    "sg:province":"Bayern",
    "wof:name":"M. Kranz Hebamme",
    "wof:placetype":"venue"
},
  "geometry": {"coordinates":[12.751608,49.084785],"type":"Point"}
}