{
  "type": "Feature",
  "properties": {
    "iso:country":"DE",
    "sg:address":"Bauernstr. 9",
    "sg:city":"Laugna",
    "sg:phone":"+49 8272/2728",
    "sg:postcode":"86502",
    "sg:province":"Bayern",
    "wof:name":"Erich Sindl",
    "wof:placetype":"venue"
},
  "geometry": {"coordinates":[10.7240886688,48.5131645203],"type":"Point"}
}