{
  "type": "Feature",
  "properties": {
    "iso:country":"DE",
    "sg:address":"Im Sande 21",
    "sg:city":"Egestorf",
    "sg:phone":"+49 4175/782",
    "sg:postcode":"21272",
    "sg:province":"Niedersachsen",
    "wof:name":"Treppenbau Frank M. Trapper Aps Gmbh",
    "wof:placetype":"venue"
},
  "geometry": {"coordinates":[10.0673475266,53.196762085],"type":"Point"}
}