{
  "type": "Feature",
  "properties": {
    "iso:country":"DE",
    "sg:address":"M\u00fcnchener Str. 11",
    "sg:city":"Karlskron",
    "sg:phone":"+49 8450/7031",
    "sg:postcode":"85123",
    "sg:province":"Bayern",
    "wof:name":"Havit Hydraulik Beteiligungs Gmbh",
    "wof:placetype":"venue"
},
  "geometry": {"coordinates":[11.453059,48.695915],"type":"Point"}
}