{
  "type": "Feature",
  "properties": {
    "iso:country":"DE",
    "sg:address":"Sonnenweg 6",
    "sg:city":"Gro\u00dfmaischeid",
    "sg:phone":"+49 2689/6502",
    "sg:postcode":"56276",
    "sg:province":"Rheinland-Pfalz",
    "wof:name":"L. Schaaf",
    "wof:placetype":"venue"
},
  "geometry": {"coordinates":[7.659813,50.49548],"type":"Point"}
}