{
  "type": "Feature",
  "properties": {
    "iso:country":"DE",
    "sg:address":"Fackelstr. 23",
    "sg:city":"Kaiserslautern",
    "sg:phone":"+49 631/696977",
    "sg:postcode":"67655",
    "sg:province":"Rheinland-Pfalz",
    "wof:name":"Java Kaffee Gmbh",
    "wof:placetype":"venue"
},
  "geometry": {"coordinates":[7.7670321465,49.4439697266],"type":"Point"}
}