{
  "type": "Feature",
  "properties": {
    "iso:country":"DE",
    "sg:address":"Daimlerstr 7",
    "sg:city":"Geeste",
    "sg:phone":"+49 5937/97770",
    "sg:postcode":"49744",
    "sg:province":"Niedersachsen",
    "wof:name":"Teschke Rohrleitungs- Und Anlagenbau Gmbh",
    "wof:placetype":"venue"
},
  "geometry": {"coordinates":[7.2145900726,52.5869865417],"type":"Point"}
}