{
  "type": "Feature",
  "properties": {
    "iso:country":"DE",
    "sg:address":"Lange Str. 10",
    "sg:city":"Haren",
    "sg:phone":"+49 5932/2753",
    "sg:postcode":"49733",
    "sg:province":"Niedersachsen",
    "wof:name":"Kath. Pfarramt",
    "wof:placetype":"venue"
},
  "geometry": {"coordinates":[7.152504921,52.7920227051],"type":"Point"}
}