{
  "type": "Feature",
  "properties": {
    "iso:country":"DE",
    "sg:address":"Glasschleiferstr. 14",
    "sg:city":"Kaufbeuren",
    "sg:phone":"+49 8341/62087",
    "sg:postcode":"87600",
    "sg:province":"Bayern",
    "wof:name":"Sussmann & Steinhauser Gmbh",
    "wof:placetype":"venue"
},
  "geometry": {"coordinates":[10.639933,47.914249],"type":"Point"}
}