{
  "type": "Feature",
  "properties": {
    "iso:country":"DE",
    "sg:address":"Theodor-Heuss-Ring 38-42",
    "sg:city":"Dietzenbach",
    "sg:phone":"+49 6074/8550",
    "sg:postcode":"63128",
    "sg:province":"Hessen",
    "wof:name":"Compendata Service Gmbh",
    "wof:placetype":"venue"
},
  "geometry": {"coordinates":[8.789393,50.02161],"type":"Point"}
}