{
  "type": "Feature",
  "properties": {
    "iso:country":"DE",
    "sg:address":"H\u00fcndekausen 71",
    "sg:city":"Much",
    "sg:phone":"+49 2245/890411",
    "sg:postcode":"53804",
    "sg:province":"Nordrhein-Westfalen",
    "wof:name":"Armin Siebertz",
    "wof:placetype":"venue"
},
  "geometry": {"coordinates":[7.4564781189,50.9274253845],"type":"Point"}
}