{
  "type": "Feature",
  "properties": {
    "iso:country":"DE",
    "sg:address":"Max-Emanuel-Str. 3",
    "sg:city":"Passau",
    "sg:postcode":"94036",
    "sg:province":"Bayern",
    "wof:name":"Fischer & L\u00f6ffler Deutschland Gmbh",
    "wof:placetype":"venue"
},
  "geometry": {"coordinates":[13.4088277817,48.567199707],"type":"Point"}
}