{
  "type": "Feature",
  "properties": {
    "iso:country":"DE",
    "sg:address":"Kirchstr. 7",
    "sg:city":"Staufen",
    "sg:phone":"+49 7633/6962",
    "sg:postcode":"79219",
    "sg:province":"Baden-W\u00fcrttemberg",
    "wof:name":"Berthold Keil",
    "wof:placetype":"venue"
},
  "geometry": {"coordinates":[9.6167430878,51.3711128235],"type":"Point"}
}