{
  "type": "Feature",
  "properties": {
    "iso:country":"DE",
    "sg:address":"M\u00f6nchstr. 3",
    "sg:city":"Straubenhardt",
    "sg:phone":"+49 7082/7024",
    "sg:postcode":"75334",
    "sg:province":"Baden-W\u00fcrttemberg",
    "wof:name":"Bambi",
    "wof:placetype":"venue"
},
  "geometry": {"coordinates":[8.547863,48.838531],"type":"Point"}
}