{
  "type": "Feature",
  "properties": {
    "iso:country":"DE",
    "sg:address":"Gierather Str. 84a",
    "sg:city":"Bergisch Gladbach",
    "sg:phone":"+49 2202/52686",
    "sg:postcode":"51469",
    "sg:province":"Nordrhein-Westfalen",
    "wof:name":"K. Hamm",
    "wof:placetype":"venue"
},
  "geometry": {"coordinates":[7.110049,50.980103],"type":"Point"}
}