{
  "type": "Feature",
  "properties": {
    "iso:country":"DE",
    "sg:address":"Lindenallee 7",
    "sg:city":"Gro\u00df Oesingen",
    "sg:phone":"+49 5838/332",
    "sg:postcode":"29393",
    "sg:province":"Niedersachsen",
    "wof:name":"Gerhard D\u00fcvel",
    "wof:placetype":"venue"
},
  "geometry": {"coordinates":[10.501178,52.661308],"type":"Point"}
}