{
  "type": "Feature",
  "properties": {
    "iso:country":"DE",
    "sg:address":"Veilchenweg 12",
    "sg:city":"V\u00f6hringen",
    "sg:phone":"+49 7454/92701",
    "sg:postcode":"72189",
    "sg:province":"Baden-W\u00fcrttemberg",
    "wof:name":"Huonker",
    "wof:placetype":"venue"
},
  "geometry": {"coordinates":[8.663110733,48.3298873901],"type":"Point"}
}