{
  "type": "Feature",
  "properties": {
    "iso:country":"DE",
    "sg:address":"Marsstr. 10",
    "sg:city":"Xanten",
    "sg:phone":"+49 2801/1035",
    "sg:postcode":"46509",
    "sg:province":"Nordrhein-Westfalen",
    "wof:name":"A. Engbers",
    "wof:placetype":"venue"
},
  "geometry": {"coordinates":[6.454708,51.660709],"type":"Point"}
}