{
  "type": "Feature",
  "properties": {
    "iso:country":"DE",
    "sg:address":"Untere G\u00e4rten 13",
    "sg:city":"Horb-Ahldorf",
    "sg:phone":"+49 4974/5153930",
    "sg:postcode":"72160",
    "sg:province":"Baden-W\u00fcrttemberg",
    "wof:name":"Tehla Pr\u00c4zesionswerkzeuge Gmbh",
    "wof:placetype":"venue"
},
  "geometry": {"coordinates":[8.691031,48.445351],"type":"Point"}
}