{
  "type": "Feature",
  "properties": {
    "iso:country":"DE",
    "sg:address":"Bahnhofstr. 2",
    "sg:city":"Stade",
    "sg:postcode":"21682",
    "sg:province":"Niedersachsen",
    "wof:name":"Extracta Beratungs Gmbh",
    "wof:placetype":"venue"
},
  "geometry": {"coordinates":[9.4756498337,53.5977783203],"type":"Point"}
}