{
  "type": "Feature",
  "properties": {
    "iso:country":"DE",
    "sg:address":"Schnackenburgallee 41",
    "sg:city":"Hamburg",
    "sg:phone":"+49 40/85374900",
    "sg:postcode":"22525",
    "sg:province":"Hamburg",
    "wof:name":"Ek-team Elektronik- Und Kunststoff-technik Gmbh",
    "wof:placetype":"venue"
},
  "geometry": {"coordinates":[9.918213,53.578117],"type":"Point"}
}