{
  "type": "Feature",
  "properties": {
    "iso:country":"DE",
    "sg:address":"Bahnhofplatz 1",
    "sg:city":"Bad Reichenhall",
    "sg:phone":"+49 8651/64212",
    "sg:postcode":"83435",
    "sg:province":"Bayern",
    "wof:name":"Sonja Moden Gmbh",
    "wof:placetype":"venue"
},
  "geometry": {"coordinates":[12.882915,47.731865],"type":"Point"}
}