{
  "type": "Feature",
  "properties": {
    "iso:country":"DE",
    "sg:address":"Hinterstr. 2",
    "sg:city":"Selters",
    "sg:phone":"+49 6483/911384",
    "sg:postcode":"65618",
    "sg:province":"Hessen",
    "wof:name":"Gastst\u00e4tte Schabernack",
    "wof:placetype":"venue"
},
  "geometry": {"coordinates":[8.2661123276,50.3701934814],"type":"Point"}
}