{
  "type": "Feature",
  "properties": {
    "iso:country":"DE",
    "sg:address":"Motterstr. 1",
    "sg:city":"N\u00fcrnberg",
    "sg:phone":"+49 911/646035",
    "sg:postcode":"90451",
    "sg:province":"Bayern",
    "wof:name":"Ev. Luth. Pfarramt Eibach Iii",
    "wof:placetype":"venue"
},
  "geometry": {"coordinates":[11.0360250473,49.4024925232],"type":"Point"}
}