{
  "type": "Feature",
  "properties": {
    "iso:country":"DE",
    "sg:address":"Holzweg 20",
    "sg:city":"Oberursel",
    "sg:phone":"+49 6171/56081",
    "sg:postcode":"61440",
    "sg:province":"Hessen",
    "wof:name":"Hotel Central",
    "wof:placetype":"venue"
},
  "geometry": {"coordinates":[8.5802049637,50.2032661438],"type":"Point"}
}