{
  "type": "Feature",
  "properties": {
    "iso:country":"DE",
    "sg:address":"Friedrichsplatz 19",
    "sg:city":"Mannheim",
    "sg:phone":"+49 621/414699",
    "sg:postcode":"68165",
    "sg:province":"Baden-W\u00fcrttemberg",
    "wof:name":"G. Briesemeister",
    "wof:placetype":"venue"
},
  "geometry": {"coordinates":[8.478332,49.48341],"type":"Point"}
}