{
  "type": "Feature",
  "properties": {
    "iso:country":"DE",
    "sg:address":"Industriestr. 2",
    "sg:city":"Lemwerder",
    "sg:phone":"+49 421/67330",
    "sg:postcode":"27809",
    "sg:province":"Niedersachsen",
    "wof:name":"Abeking & Rasmussen Rotec Gmbh",
    "wof:placetype":"venue"
},
  "geometry": {"coordinates":[8.6093,53.167725],"type":"Point"}
}