{
  "type": "Feature",
  "properties": {
    "iso:country":"DE",
    "sg:address":"Holl\u00e4ndische Reihe 8",
    "sg:city":"Hamburg",
    "sg:phone":"+49 40/397638",
    "sg:postcode":"22765",
    "sg:province":"Hamburg",
    "wof:name":"G\u00fcnter Runge",
    "wof:placetype":"venue"
},
  "geometry": {"coordinates":[9.9311132431,53.5479812622],"type":"Point"}
}