{
  "type": "Feature",
  "properties": {
    "iso:country":"DE",
    "sg:address":"B\u00f6hmerstr. 10",
    "sg:city":"R\u00f6tz",
    "sg:phone":"+49 9976/90010",
    "sg:postcode":"92444",
    "sg:province":"Bayern",
    "wof:name":"Johann Maier",
    "wof:placetype":"venue"
},
  "geometry": {"coordinates":[12.5303211212,49.3422431946],"type":"Point"}
}