{
  "type": "Feature",
  "properties": {
    "iso:country":"DE",
    "sg:address":"Am Krummensee 24",
    "sg:city":"Zeesen",
    "sg:phone":"+49 3375/900026",
    "sg:postcode":"15711",
    "sg:province":"Brandenburg",
    "wof:name":"Helmut Lehmann",
    "wof:placetype":"venue"
},
  "geometry": {"coordinates":[13.613563,52.26265],"type":"Point"}
}