{
  "type": "Feature",
  "properties": {
    "iso:country":"DE",
    "sg:address":"Kyffh\u00e4userstr. 39",
    "sg:city":"Wuppertal",
    "sg:phone":"+49 202/710088",
    "sg:postcode":"42115",
    "sg:province":"Nordrhein-Westfalen",
    "wof:name":"J\u00fcrgen Milchereit Steuerberater",
    "wof:placetype":"venue"
},
  "geometry": {"coordinates":[7.1171011925,51.2513008118],"type":"Point"}
}