{
  "type": "Feature",
  "properties": {
    "iso:country":"DE",
    "sg:address":"Landweg 26",
    "sg:city":"B\u00fcsum",
    "sg:phone":"+49 4834/8261",
    "sg:postcode":"25761",
    "sg:province":"Schleswig-Holstein",
    "wof:name":"Pension Nordseekrabbe",
    "wof:placetype":"venue"
},
  "geometry": {"coordinates":[8.8616132736,54.1366729736],"type":"Point"}
}