{
  "type": "Feature",
  "properties": {
    "iso:country":"DE",
    "sg:address":"Hauptstr. 84",
    "sg:city":"Inzigkofen",
    "sg:phone":"+49 7575/3196",
    "sg:postcode":"72514",
    "sg:province":"Baden-W\u00fcrttemberg",
    "wof:name":"Gastst\u00e4tte Ewald Reck",
    "wof:placetype":"venue"
},
  "geometry": {"coordinates":[9.1299495697,48.0400009155],"type":"Point"}
}