{
  "type": "Feature",
  "properties": {
    "iso:country":"DE",
    "sg:address":"Jugenheimer Str. 20",
    "sg:city":"Frankfurt",
    "sg:phone":"+49 69/679931",
    "sg:postcode":"60528",
    "sg:province":"Hessen",
    "wof:name":"Manfred Wegner Detektei",
    "wof:placetype":"venue"
},
  "geometry": {"coordinates":[8.64152,50.084084],"type":"Point"}
}