{
  "type": "Feature",
  "properties": {
    "iso:country":"DE",
    "sg:address":"Hattorfer Str. 7",
    "sg:city":"Philippsthal",
    "sg:phone":"+49 6620/455",
    "sg:postcode":"36269",
    "sg:province":"Hessen",
    "wof:name":"Kurt H\u00fchne",
    "wof:placetype":"venue"
},
  "geometry": {"coordinates":[9.9645872116,50.8452262878],"type":"Point"}
}