{
  "type": "Feature",
  "properties": {
    "iso:country":"DE",
    "sg:address":"Grupenstr. 2",
    "sg:city":"Hannover",
    "sg:phone":"+49 511/3076090",
    "sg:postcode":"30159",
    "sg:province":"Niedersachsen",
    "wof:name":"Aachener Bausparkasse Ag",
    "wof:placetype":"venue"
},
  "geometry": {"coordinates":[9.737081,52.372711],"type":"Point"}
}