{
  "type": "Feature",
  "properties": {
    "iso:country":"DE",
    "sg:address":"Siegener Str. 1",
    "sg:city":"Lennestadt",
    "sg:phone":"+49 2721/92570",
    "sg:postcode":"57368",
    "sg:province":"Nordrhein-Westfalen",
    "wof:name":"Rheinkalk Grevenbr\u00fcck Gmbh",
    "wof:placetype":"venue"
},
  "geometry": {"coordinates":[8.022087,51.140148],"type":"Point"}
}