{
  "type": "Feature",
  "properties": {
    "iso:country":"DE",
    "sg:address":"Allee 47",
    "sg:city":"Heilbronn",
    "sg:phone":"+49 4971/3189235",
    "sg:postcode":"74072",
    "sg:province":"Baden-W\u00fcrttemberg",
    "wof:name":"Sparda Bank Stuttgart Eg",
    "wof:placetype":"venue"
},
  "geometry": {"coordinates":[9.222625,49.143906],"type":"Point"}
}