{
  "type": "Feature",
  "properties": {
    "iso:country":"DE",
    "sg:address":"Klausenweg 20",
    "sg:city":"Balingen",
    "sg:phone":"+49 7433/96900",
    "sg:postcode":"72336",
    "sg:province":"Baden-W\u00fcrttemberg",
    "wof:name":"Hotel Thum Gmbh",
    "wof:placetype":"venue"
},
  "geometry": {"coordinates":[8.8581485748,48.2764511108],"type":"Point"}
}