{
  "type": "Feature",
  "properties": {
    "iso:country":"DE",
    "sg:address":"In der Webel",
    "sg:city":"Stemwede",
    "sg:postcode":"32351",
    "sg:province":"Nordrhein-Westfalen",
    "wof:name":"Net-trad",
    "wof:placetype":"venue"
},
  "geometry": {"coordinates":[8.393295,52.440678],"type":"Point"}
}