{
  "type": "Feature",
  "properties": {
    "iso:country":"DE",
    "sg:address":"Zum Bildchen 20",
    "sg:city":"Wadern",
    "sg:phone":"+49 6871/91030",
    "sg:postcode":"66687",
    "sg:province":"Saarland",
    "wof:name":"Patrick Mohm",
    "wof:placetype":"venue"
},
  "geometry": {"coordinates":[6.8617401123,49.5555000305],"type":"Point"}
}