{
  "type": "Feature",
  "properties": {
    "iso:country":"DE",
    "sg:address":"M\u00fchltorring 6",
    "sg:city":"Maintal",
    "sg:phone":"+49 6181/850277",
    "sg:postcode":"63477",
    "sg:province":"Hessen",
    "wof:name":"Ellen Kehl",
    "wof:placetype":"venue"
},
  "geometry": {"coordinates":[8.8539772034,50.1699905396],"type":"Point"}
}