{
  "type": "Feature",
  "properties": {
    "iso:country":"DE",
    "sg:address":"Bl\u00fccherplatz 15",
    "sg:city":"Kiel",
    "sg:phone":"+49 431/87475",
    "sg:postcode":"24105",
    "sg:province":"Schleswig-Holstein",
    "wof:name":"Reformhaus Hintz Kg",
    "wof:placetype":"venue"
},
  "geometry": {"coordinates":[10.1383876801,54.3424224854],"type":"Point"}
}