{
  "type": "Feature",
  "properties": {
    "iso:country":"DE",
    "sg:address":"Parkstr. 6",
    "sg:city":"Ha\u00dfloch",
    "sg:phone":"+49 6324/3571",
    "sg:postcode":"67454",
    "sg:province":"Rheinland-Pfalz",
    "wof:name":"Friedr. Kreidemacher Ingenieur",
    "wof:placetype":"venue"
},
  "geometry": {"coordinates":[8.2601060867,49.3635787964],"type":"Point"}
}