{
  "type": "Feature",
  "properties": {
    "iso:country":"DE",
    "sg:address":"Technologiepark 34",
    "sg:city":"Paderborn",
    "sg:postcode":"33100",
    "sg:province":"Nordrhein-Westfalen",
    "wof:name":"Incony Ag",
    "wof:placetype":"venue"
},
  "geometry": {"coordinates":[8.766931,51.701397],"type":"Point"}
}