{
  "type": "Feature",
  "properties": {
    "iso:country":"DE",
    "sg:address":"Bahnhofstr. 72",
    "sg:city":"Reken",
    "sg:phone":"+49 2864/2579",
    "sg:postcode":"48734",
    "sg:province":"Nordrhein-Westfalen",
    "wof:name":"Reinhold Schlaghecke",
    "wof:placetype":"venue"
},
  "geometry": {"coordinates":[7.04567,51.798351],"type":"Point"}
}