{
  "type": "Feature",
  "properties": {
    "iso:country":"DE",
    "sg:address":"Sebastianusstr. 30",
    "sg:city":"Korschenbroich",
    "sg:phone":"+49 2161/642674",
    "sg:postcode":"41352",
    "sg:province":"Nordrhein-Westfalen",
    "wof:name":"Kathi Schmitz",
    "wof:placetype":"venue"
},
  "geometry": {"coordinates":[6.512275219,51.1901245117],"type":"Point"}
}