{
  "type": "Feature",
  "properties": {
    "iso:country":"DE",
    "sg:address":"Schwindstr. 15",
    "sg:city":"Bayreuth",
    "sg:phone":"+49 921/54479",
    "sg:postcode":"95447",
    "sg:province":"Bayern",
    "wof:name":"Schmidt Fotostudio",
    "wof:placetype":"venue"
},
  "geometry": {"coordinates":[11.5639877319,49.9386329651],"type":"Point"}
}