{
  "type": "Feature",
  "properties": {
    "iso:country":"DE",
    "sg:address":"Wernsdorfer Str. 31",
    "sg:city":"Glauchau",
    "sg:phone":"+49 3763/2585",
    "sg:postcode":"08371",
    "sg:province":"Sachsen",
    "wof:name":"G\u00fcnter Metzner",
    "wof:placetype":"venue"
},
  "geometry": {"coordinates":[12.5371265411,50.8098564148],"type":"Point"}
}