{
  "type": "Feature",
  "properties": {
    "iso:country":"DE",
    "sg:address":"Klosterstr. 5",
    "sg:city":"Rinteln",
    "sg:phone":"+49 5751/919068",
    "sg:postcode":"31737",
    "sg:province":"Niedersachsen",
    "wof:name":"Sascha Gomolzig",
    "wof:placetype":"venue"
},
  "geometry": {"coordinates":[9.0781116486,52.1863517761],"type":"Point"}
}