{
  "type": "Feature",
  "properties": {
    "iso:country":"DE",
    "sg:address":"Osterstr. 16",
    "sg:city":"Udenheim",
    "sg:phone":"+49 6732/4913",
    "sg:postcode":"55288",
    "sg:province":"Rheinland-Pfalz",
    "wof:name":"Hans-g\u00fcnter Lahr",
    "wof:placetype":"venue"
},
  "geometry": {"coordinates":[8.1713142395,49.8665542603],"type":"Point"}
}