{
  "type": "Feature",
  "properties": {
    "iso:country":"DE",
    "sg:address":"Am Rottersberg 33",
    "sg:city":"Worbis",
    "sg:phone":"+49 36074/92803",
    "sg:postcode":"37339",
    "sg:province":"Th\u00fcringen",
    "wof:name":"Tischlerei Brodmann Gmbh",
    "wof:placetype":"venue"
},
  "geometry": {"coordinates":[10.359918,51.431225],"type":"Point"}
}