{
  "type": "Feature",
  "properties": {
    "iso:country":"DE",
    "sg:address":"Klein Schwa\u00dfer Weg 20",
    "sg:city":"Kritzmow",
    "sg:phone":"+49 38207/510",
    "sg:postcode":"18198",
    "sg:province":"Mecklenburg-Vorpommern",
    "wof:name":"M. Fitzer",
    "wof:placetype":"venue"
},
  "geometry": {"coordinates":[12.048633,54.076336],"type":"Point"}
}