{
  "type": "Feature",
  "properties": {
    "iso:country":"DE",
    "sg:address":"Schlegldorf 91a",
    "sg:city":"Lenggries",
    "sg:phone":"+49 8042/9145413",
    "sg:postcode":"83661",
    "sg:province":"Bayern",
    "wof:name":"Fuchs Baut G\u00e4rten",
    "wof:placetype":"venue"
},
  "geometry": {"coordinates":[11.55987,47.697769],"type":"Point"}
}