{
  "type": "Feature",
  "properties": {
    "iso:country":"DE",
    "sg:address":"Wiesenhof 2",
    "sg:city":"Oberarnbach",
    "sg:phone":"+49 6371/15559",
    "sg:postcode":"66851",
    "sg:province":"Rheinland-Pfalz",
    "wof:name":"G\u00fcnther Breitenborn",
    "wof:placetype":"venue"
},
  "geometry": {"coordinates":[7.5876288414,49.3829536438],"type":"Point"}
}