{
  "type": "Feature",
  "properties": {
    "iso:country":"DE",
    "sg:address":"Georg-Weinhart-Str. 5",
    "sg:city":"Gundelfingen",
    "sg:phone":"+49 9073/2214",
    "sg:postcode":"89423",
    "sg:province":"Bayern",
    "wof:name":"Immobilien- Und Baubetreuungs Gmbh",
    "wof:placetype":"venue"
},
  "geometry": {"coordinates":[10.3793821335,48.5553512573],"type":"Point"}
}