{
  "type": "Feature",
  "properties": {
    "iso:country":"DE",
    "sg:address":"Glash\u00fctter Damm 199",
    "sg:city":"Norderstedt",
    "sg:phone":"+49 40/52985555",
    "sg:postcode":"22851",
    "sg:province":"Schleswig-Holstein",
    "wof:name":"Gauger Und Hintz Rechtsanw\u00e4lte",
    "wof:placetype":"venue"
},
  "geometry": {"coordinates":[10.0277833939,53.6935005188],"type":"Point"}
}