{
  "type": "Feature",
  "properties": {
    "iso:country":"DE",
    "sg:address":"Freiberger Str. 6",
    "sg:city":"Wolkenstein",
    "sg:phone":"+49 37369/5048",
    "sg:postcode":"09429",
    "sg:province":"Sachsen",
    "wof:name":"Baldy",
    "wof:placetype":"venue"
},
  "geometry": {"coordinates":[13.068649,50.656448],"type":"Point"}
}