{
  "type": "Feature",
  "properties": {
    "iso:country":"DE",
    "sg:address":"Barf\u00fc\u00dferstr. 12",
    "sg:city":"G\u00f6ttingen",
    "sg:phone":"+49 551/57886",
    "sg:postcode":"37073",
    "sg:province":"Niedersachsen",
    "wof:name":"Siegfried Bohm Antiquit\u00e4ten",
    "wof:placetype":"venue"
},
  "geometry": {"coordinates":[9.93585,51.533344],"type":"Point"}
}