{
  "type": "Feature",
  "properties": {
    "iso:country":"DE",
    "sg:address":"Berliner Platz 20",
    "sg:city":"R\u00fcsselsheim",
    "sg:phone":"+49 6142/998097",
    "sg:postcode":"65428",
    "sg:province":"Hessen",
    "wof:name":"Y. Tunali",
    "wof:placetype":"venue"
},
  "geometry": {"coordinates":[8.4294719696,49.9988288879],"type":"Point"}
}