{
  "type": "Feature",
  "properties": {
    "iso:country":"DE",
    "sg:address":"Mendelssohnstr. 14",
    "sg:city":"D\u00fcsseldorf",
    "sg:postcode":"40233",
    "sg:province":"Nordrhein-Westfalen",
    "wof:name":"Vigo Trust Gmbh",
    "wof:placetype":"venue"
},
  "geometry": {"coordinates":[6.8006129265,51.2295455933],"type":"Point"}
}