{
  "type": "Feature",
  "properties": {
    "iso:country":"DE",
    "sg:address":"Forchenweg 19",
    "sg:city":"Schwangau",
    "sg:phone":"+49 8362/8322",
    "sg:postcode":"87645",
    "sg:province":"Bayern",
    "wof:name":"Ludwig Gingele Gmbh & Co. Kg",
    "wof:placetype":"venue"
},
  "geometry": {"coordinates":[10.718977,47.570747],"type":"Point"}
}