{
  "type": "Feature",
  "properties": {
    "iso:country":"DE",
    "sg:address":"Rathausstr. 3",
    "sg:city":"Pulheim",
    "sg:phone":"+49 2238/56488",
    "sg:postcode":"50259",
    "sg:province":"Nordrhein-Westfalen",
    "wof:name":"Bistro Apropo",
    "wof:placetype":"venue"
},
  "geometry": {"coordinates":[6.8002619743,50.9981994629],"type":"Point"}
}