{
  "type": "Feature",
  "properties": {
    "iso:country":"DE",
    "sg:address":"Neum\u00fchle",
    "sg:city":"Alzey",
    "sg:phone":"+49 6731/43267",
    "sg:postcode":"55232",
    "sg:province":"Rheinland-Pfalz",
    "wof:name":"Ludwig Bauer",
    "wof:placetype":"venue"
},
  "geometry": {"coordinates":[8.066265,49.72681],"type":"Point"}
}