{
  "type": "Feature",
  "properties": {
    "iso:country":"DE",
    "sg:address":"Ostmoorweg 9",
    "sg:city":"Buxtehude",
    "sg:phone":"+49 4161/80292",
    "sg:postcode":"21614",
    "sg:province":"Niedersachsen",
    "wof:name":"Schlosserei Meyer Gmbh",
    "wof:placetype":"venue"
},
  "geometry": {"coordinates":[9.719928,53.465401],"type":"Point"}
}