{
  "type": "Feature",
  "properties": {
    "iso:country":"DE",
    "sg:address":"Elbenauer Str. 13",
    "sg:city":"Sch\u00f6nebeck",
    "sg:phone":"+49 3928/403938",
    "sg:postcode":"39218",
    "sg:province":"Sachsen-Anhalt",
    "wof:name":"Gunar Belling",
    "wof:placetype":"venue"
},
  "geometry": {"coordinates":[11.7451543808,52.0312767029],"type":"Point"}
}