{
  "type": "Feature",
  "properties": {
    "iso:country":"DE",
    "sg:address":"Obernstr. 56",
    "sg:city":"Stadthagen",
    "sg:phone":"+49 5721/77094",
    "sg:postcode":"31655",
    "sg:province":"Niedersachsen",
    "wof:name":"Hirschfeld Und Hirschfeld Rechtsanw\u00e4lte Und Notar",
    "wof:placetype":"venue"
},
  "geometry": {"coordinates":[9.2060270309,52.3235054016],"type":"Point"}
}