{
  "type": "Feature",
  "properties": {
    "iso:country":"DE",
    "sg:address":"Neanderstr. 5-7",
    "sg:city":"Mettmann",
    "sg:postcode":"40822",
    "sg:province":"Nordrhein-Westfalen",
    "wof:name":"Aldi Gmbh & Co. Kg",
    "wof:placetype":"venue"
},
  "geometry": {"coordinates":[6.9750051498,51.2505149841],"type":"Point"}
}