{
  "type": "Feature",
  "properties": {
    "iso:country":"DE",
    "sg:address":"Bernter\u00f6der Str. 11",
    "sg:city":"Niederorschel",
    "sg:phone":"+49 36076/44091",
    "sg:postcode":"37355",
    "sg:province":"Th\u00fcringen",
    "wof:name":"Gerald Hesse",
    "wof:placetype":"venue"
},
  "geometry": {"coordinates":[10.430237,51.37384],"type":"Point"}
}