{
  "type": "Feature",
  "properties": {
    "iso:country":"DE",
    "sg:address":"Burgvogtstr. 5",
    "sg:city":"Singen",
    "sg:phone":"+49 7731/45593",
    "sg:postcode":"78224",
    "sg:province":"Baden-W\u00fcrttemberg",
    "wof:name":"Eckhard Gutke Ingenieur",
    "wof:placetype":"venue"
},
  "geometry": {"coordinates":[8.8388252258,47.8067474365],"type":"Point"}
}