{
  "type": "Feature",
  "properties": {
    "iso:country":"DE",
    "sg:address":"Horstweg 28a",
    "sg:city":"Peine",
    "sg:phone":"+49 5171/52280",
    "sg:postcode":"31226",
    "sg:province":"Niedersachsen",
    "wof:name":"D. Loke",
    "wof:placetype":"venue"
},
  "geometry": {"coordinates":[10.210272789,52.3202819824],"type":"Point"}
}