{
  "type": "Feature",
  "properties": {
    "iso:country":"DE",
    "sg:address":"Hubertusplatz 1",
    "sg:city":"Halle",
    "sg:phone":"+49 345/5510598",
    "sg:postcode":"06120",
    "sg:province":"Sachsen-Anhalt",
    "wof:name":"Andrea Struck",
    "wof:placetype":"venue"
},
  "geometry": {"coordinates":[11.932479,51.499607],"type":"Point"}
}