{
  "type": "Feature",
  "properties": {
    "iso:country":"DE",
    "sg:address":"Goethestr. 6",
    "sg:city":"Gro\u00df\u00f6rner",
    "sg:postcode":"06348",
    "wof:name":"Taja Warenhandelsges. Mbh",
    "wof:placetype":"venue"
},
  "geometry": {"coordinates":[11.4870786667,51.612903595],"type":"Point"}
}