{
  "type": "Feature",
  "properties": {
    "iso:country":"DE",
    "sg:address":"F\u00fcrstenbergstr. 13",
    "sg:city":"Remagen",
    "sg:phone":"+49 2642/22228",
    "sg:postcode":"53424",
    "sg:province":"Rheinland-Pfalz",
    "wof:name":"B. Aarhuus Kg",
    "wof:placetype":"venue"
},
  "geometry": {"coordinates":[7.225008,50.579079],"type":"Point"}
}