{
  "type": "Feature",
  "properties": {
    "iso:country":"DE",
    "sg:address":"PF 601234",
    "sg:city":"Potsdam",
    "sg:phone":"+49 331/23700236",
    "sg:postcode":"14412",
    "sg:province":"Brandenburg",
    "wof:name":"Pro-artist, Modellagentur Und K\u00fcnstleragentur (potsdam)",
    "wof:placetype":"venue"
},
  "geometry": {"coordinates":[13.03983,52.395069],"type":"Point"}
}