{
  "type": "Feature",
  "properties": {
    "iso:country":"DE",
    "sg:address":"Gr\u00fcner Talstr. 71",
    "sg:city":"Iserlohn",
    "sg:phone":"+49 2371/52502",
    "sg:postcode":"58644",
    "sg:province":"Nordrhein-Westfalen",
    "wof:name":"Sporttreff Iserlohn",
    "wof:placetype":"venue"
},
  "geometry": {"coordinates":[7.6758008003,51.3608512878],"type":"Point"}
}