{
  "type": "Feature",
  "properties": {
    "iso:country":"DE",
    "sg:address":"Im Dorfe 31",
    "sg:city":"Barsinghausen",
    "sg:phone":"+49 5105/9153",
    "sg:postcode":"30890",
    "sg:province":"Niedersachsen",
    "wof:name":"Friedrich Meyer",
    "wof:placetype":"venue"
},
  "geometry": {"coordinates":[9.407333,52.326904],"type":"Point"}
}