{
  "type": "Feature",
  "properties": {
    "iso:country":"DE",
    "sg:address":"Hallesche Str. 26",
    "sg:city":"Wolfsburg",
    "sg:phone":"+49 5361/774791",
    "sg:postcode":"38444",
    "sg:province":"Niedersachsen",
    "wof:name":"H\u00e4rke Kate",
    "wof:placetype":"venue"
},
  "geometry": {"coordinates":[10.7385215759,52.4049987793],"type":"Point"}
}