{
  "type": "Feature",
  "properties": {
    "iso:country":"DE",
    "sg:address":"Am Greinberg 2",
    "sg:city":"Ochsenfurt",
    "sg:phone":"+49 9331/2759",
    "sg:postcode":"97199",
    "sg:province":"Bayern",
    "wof:name":"Bernhard Spenkuch",
    "wof:placetype":"venue"
},
  "geometry": {"coordinates":[10.085273,49.664024],"type":"Point"}
}