{
  "type": "Feature",
  "properties": {
    "iso:country":"DE",
    "sg:address":"Im Alten Dorf 4",
    "sg:city":"Bremen",
    "sg:phone":"+49 421/403369",
    "sg:postcode":"28307",
    "sg:province":"Bremen",
    "wof:name":"G\u00fcnter Volbers",
    "wof:placetype":"venue"
},
  "geometry": {"coordinates":[8.951255,53.047478],"type":"Point"}
}