{
  "type": "Feature",
  "properties": {
    "iso:country":"DE",
    "sg:address":"Erste Flie\u00dfstr. 3",
    "sg:city":"Essen",
    "sg:phone":"+49 201/861040",
    "sg:postcode":"45356",
    "sg:province":"Nordrhein-Westfalen",
    "wof:name":"M U. E Kranbedarfshandels Gmbh",
    "wof:placetype":"venue"
},
  "geometry": {"coordinates":[6.9772171974,51.4762763977],"type":"Point"}
}