{
  "type": "Feature",
  "properties": {
    "iso:country":"DE",
    "sg:address":"Alte Braunschweiger Str. 19",
    "sg:city":"Wolfsburg",
    "sg:phone":"+49 5361/76365",
    "sg:postcode":"38442",
    "sg:province":"Niedersachsen",
    "wof:name":"Joachim Velthuis Architekt",
    "wof:placetype":"venue"
},
  "geometry": {"coordinates":[10.732408,52.388893],"type":"Point"}
}