{
  "type": "Feature",
  "properties": {
    "iso:country":"DE",
    "sg:address":"Gro\u00dfe Rainstr. 44",
    "sg:city":"Hamburg",
    "sg:phone":"+49 40/391711",
    "sg:postcode":"22765",
    "sg:province":"Hamburg",
    "wof:name":"Ag Horizont Architektur Und Kunst",
    "wof:placetype":"venue"
},
  "geometry": {"coordinates":[9.931959,53.553345],"type":"Point"}
}