{
  "type": "Feature",
  "properties": {
    "iso:country":"DE",
    "sg:address":"Heimendahlstr. 57",
    "sg:city":"Krefeld",
    "sg:phone":"+49 2151/753738",
    "sg:postcode":"47803",
    "sg:province":"Nordrhein-Westfalen",
    "wof:name":"Georg Flesch",
    "wof:placetype":"venue"
},
  "geometry": {"coordinates":[6.543069,51.342564],"type":"Point"}
}