{
  "type": "Feature",
  "properties": {
    "iso:country":"DE",
    "sg:address":"Letter Str. 34",
    "sg:city":"Coesfeld",
    "sg:phone":"+49 2541/87927",
    "sg:postcode":"48653",
    "sg:province":"Nordrhein-Westfalen",
    "wof:name":"Kinobetriebe Dr. H. Und A Hoffmeister",
    "wof:placetype":"venue"
},
  "geometry": {"coordinates":[7.1671519279,51.9420700073],"type":"Point"}
}