{
  "type": "Feature",
  "properties": {
    "iso:country":"DE",
    "sg:address":"Oberneulander Heerstr. 25",
    "sg:city":"Bremen",
    "sg:phone":"+49 421/251540",
    "sg:postcode":"28355",
    "sg:province":"Bremen",
    "wof:name":"Georg Voigts",
    "wof:placetype":"venue"
},
  "geometry": {"coordinates":[8.9005861282,53.099445343],"type":"Point"}
}