{
  "type": "Feature",
  "properties": {
    "iso:country":"DE",
    "sg:address":"Nunzenrieder Str. 60",
    "sg:city":"Oberviechtach",
    "sg:phone":"+49 9671/3150",
    "sg:postcode":"92526",
    "sg:province":"Bayern",
    "wof:name":"Josef Herzog",
    "wof:placetype":"venue"
},
  "geometry": {"coordinates":[12.4308843613,49.4566192627],"type":"Point"}
}