{
  "type": "Feature",
  "properties": {
    "iso:country":"DE",
    "sg:address":"Schillerstr. 37",
    "sg:city":"M\u00fcnchen",
    "sg:phone":"+49 89/54505564",
    "sg:postcode":"80336",
    "sg:province":"Bayern",
    "wof:name":"Heinz Michalke Steuerberater",
    "wof:placetype":"venue"
},
  "geometry": {"coordinates":[11.5610179901,48.1353416443],"type":"Point"}
}