{
  "type": "Feature",
  "properties": {
    "iso:country":"DE",
    "sg:address":"Maximilianstr. 38",
    "sg:city":"Pforzheim",
    "sg:phone":"+49 7231/33631",
    "sg:postcode":"75172",
    "sg:province":"Baden-W\u00fcrttemberg",
    "wof:name":"Ev. Pfarramt Lukasgemeinde",
    "wof:placetype":"venue"
},
  "geometry": {"coordinates":[8.6852273941,48.8935852051],"type":"Point"}
}