{
  "type": "Feature",
  "properties": {
    "iso:country":"DE",
    "sg:address":"Gilbachstr. 23",
    "sg:city":"K\u00f6ln",
    "sg:postcode":"50672",
    "sg:province":"Nordrhein-Westfalen",
    "wof:name":"Gesamtverband Kath. Kirchengemeinde",
    "wof:placetype":"venue"
},
  "geometry": {"coordinates":[6.937915802,50.9459114075],"type":"Point"}
}