{
  "type": "Feature",
  "properties": {
    "iso:country":"DE",
    "sg:address":"Am Sonnenberg 15",
    "sg:city":"Angelbachtal",
    "sg:phone":"+49 7265/269",
    "sg:postcode":"74918",
    "sg:province":"Baden-W\u00fcrttemberg",
    "wof:name":"W. Dreher Obstanbau",
    "wof:placetype":"venue"
},
  "geometry": {"coordinates":[8.7823095322,49.2324295044],"type":"Point"}
}