{
  "type": "Feature",
  "properties": {
    "iso:country":"DE",
    "sg:address":"Pitzling 5",
    "sg:city":"Eichendorf",
    "sg:phone":"+49 9952/1215",
    "sg:postcode":"94428",
    "sg:province":"Bayern",
    "wof:name":"Gasthof Alois Reichenwallner",
    "wof:placetype":"venue"
},
  "geometry": {"coordinates":[12.8787994385,48.6517105103],"type":"Point"}
}