{
  "type": "Feature",
  "properties": {
    "iso:country":"DE",
    "sg:address":"Industriestr. 10",
    "sg:city":"Finnentrop",
    "sg:phone":"+49 4927/2195433",
    "sg:postcode":"57413",
    "sg:province":"Nordrhein-Westfalen",
    "wof:name":"Herbert Thun Gmbh",
    "wof:placetype":"venue"
},
  "geometry": {"coordinates":[7.970757,51.184917],"type":"Point"}
}