{
  "type": "Feature",
  "properties": {
    "iso:country":"DE",
    "sg:address":"Eibenweg 2",
    "sg:city":"Burgthann",
    "sg:phone":"+49 9183/7576",
    "sg:postcode":"90559",
    "sg:province":"Bayern",
    "wof:name":"Walter Heinemann",
    "wof:placetype":"venue"
},
  "geometry": {"coordinates":[11.3269643784,49.3250083923],"type":"Point"}
}