{
  "type": "Feature",
  "properties": {
    "iso:country":"DE",
    "sg:address":"Hanauer Landstrasse 423a",
    "sg:city":"Frankfurt",
    "sg:phone":"+49 69/4209900",
    "sg:postcode":"60314",
    "sg:province":"Hessen",
    "wof:name":"Kraus Baudekoration Gmbh",
    "wof:placetype":"venue"
},
  "geometry": {"coordinates":[8.737369,50.121525],"type":"Point"}
}