{
  "type": "Feature",
  "properties": {
    "iso:country":"DE",
    "sg:address":"Stockacher Str. 5",
    "sg:city":"Muenchen",
    "sg:phone":"+49 89",
    "sg:postcode":"81243",
    "sg:province":"Bayern",
    "wof:name":"Rollpalast",
    "wof:placetype":"venue"
},
  "geometry": {"coordinates":[11.4427442551,48.1500205994],"type":"Point"}
}