{
  "type": "Feature",
  "properties": {
    "iso:country":"DE",
    "sg:address":"Wilhelmstr. 3",
    "sg:city":"Klingenthal",
    "sg:phone":"+49 37467/25193",
    "sg:postcode":"08248",
    "sg:province":"Sachsen",
    "wof:name":"A. Herrmann Physiotherapie",
    "wof:placetype":"venue"
},
  "geometry": {"coordinates":[12.468523,50.358868],"type":"Point"}
}