{
  "type": "Feature",
  "properties": {
    "iso:country":"DE",
    "sg:address":"Eisenh\u00e4mmerstr. 9",
    "sg:city":"Sulzbach-Rosenberg",
    "sg:postcode":"92237",
    "sg:province":"Bayern",
    "wof:name":"Jason Holding Gmbh",
    "wof:placetype":"venue"
},
  "geometry": {"coordinates":[11.7793560028,49.4961929321],"type":"Point"}
}