{
  "type": "Feature",
  "properties": {
    "iso:country":"DE",
    "sg:address":"Kreisstr. 9",
    "sg:city":"Itterbeck",
    "sg:phone":"+49 5948/218",
    "sg:postcode":"49847",
    "sg:province":"Niedersachsen",
    "wof:name":"Steven Ekelhoff",
    "wof:placetype":"venue"
},
  "geometry": {"coordinates":[6.762348,52.535793],"type":"Point"}
}