{
  "type": "Feature",
  "properties": {
    "iso:country":"DE",
    "sg:address":"Hellingst",
    "sg:city":"Holste",
    "sg:phone":"+49 4748/514",
    "sg:postcode":"27729",
    "sg:province":"Niedersachsen",
    "wof:name":"Karl H. Meier",
    "wof:placetype":"venue"
},
  "geometry": {"coordinates":[8.8617095947,53.3790016174],"type":"Point"}
}