{
  "type": "Feature",
  "properties": {
    "iso:country":"DE",
    "sg:address":"Industriestr. 37",
    "sg:city":"Wuppertal",
    "sg:phone":"+49 4920/2740078",
    "sg:postcode":"42327",
    "sg:province":"Nordrhein-Westfalen",
    "wof:name":"Rainer Schildberg Gmbh",
    "wof:placetype":"venue"
},
  "geometry": {"coordinates":[7.089721,51.245792],"type":"Point"}
}