{
  "type": "Feature",
  "properties": {
    "iso:country":"DE",
    "sg:address":"Colmantstr. 20",
    "sg:city":"Bendorf",
    "sg:phone":"+49 2622/3494",
    "sg:postcode":"56170",
    "sg:province":"Rheinland-Pfalz",
    "wof:name":"Franz Daum",
    "wof:placetype":"venue"
},
  "geometry": {"coordinates":[7.5737748146,50.4261856079],"type":"Point"}
}