{
  "type": "Feature",
  "properties": {
    "iso:country":"DE",
    "sg:address":"Bemeroder Str. 67",
    "sg:city":"Hannover",
    "sg:postcode":"30559",
    "sg:province":"Niedersachsen",
    "wof:name":"Bpr Dipl. -ing. Bernd F. K\u00fcnne Und Partner",
    "wof:placetype":"venue"
},
  "geometry": {"coordinates":[9.8089504242,52.3491744995],"type":"Point"}
}