{
  "type": "Feature",
  "properties": {
    "iso:country":"DE",
    "sg:address":"Maximinerhof 3",
    "sg:city":"Longuich",
    "sg:phone":"+49 6502/2759",
    "sg:postcode":"54340",
    "sg:province":"Rheinland-Pfalz",
    "wof:name":"V. Grans",
    "wof:placetype":"venue"
},
  "geometry": {"coordinates":[6.7706971169,49.8087501526],"type":"Point"}
}