{
  "type": "Feature",
  "properties": {
    "iso:country":"DE",
    "sg:address":"Horst-Menzel-Str. 28",
    "sg:city":"Chemnitz",
    "sg:phone":"+49 371/361814",
    "sg:postcode":"09112",
    "sg:province":"Sachsen",
    "wof:name":"Olaf Biermann",
    "wof:placetype":"venue"
},
  "geometry": {"coordinates":[12.895187,50.832054],"type":"Point"}
}