{
  "type": "Feature",
  "properties": {
    "iso:country":"DE",
    "sg:address":"Kaiserstr. 11",
    "sg:city":"Bad Sassendorf",
    "sg:phone":"+49 2921/53052",
    "sg:postcode":"59505",
    "sg:province":"Nordrhein-Westfalen",
    "wof:name":"Hans-j\u00fcrgen Elmenhorst Rechtsanwalt Und Notar",
    "wof:placetype":"venue"
},
  "geometry": {"coordinates":[8.1691579819,51.5860786438],"type":"Point"}
}