{
  "type": "Feature",
  "properties": {
    "iso:country":"DE",
    "sg:address":"Auenweg 2",
    "sg:city":"Eberhardzell",
    "sg:phone":"+49 7355/91111",
    "sg:postcode":"88436",
    "sg:province":"Baden-W\u00fcrttemberg",
    "wof:name":"Manfred Dautel",
    "wof:placetype":"venue"
},
  "geometry": {"coordinates":[9.826113,48.00457],"type":"Point"}
}