{
  "type": "Feature",
  "properties": {
    "iso:country":"DE",
    "sg:address":"Am Solnhofer Weg 6::",
    "sg:city":"Pappenheim-Bieswang",
    "sg:phone":"+49 9143/1480",
    "sg:postcode":"91788",
    "sg:province":"Bayern",
    "wof:name":"Gebr. Krause-straeten Gmbh",
    "wof:placetype":"venue"
},
  "geometry": {"coordinates":[11.030561,48.922062],"type":"Point"}
}