{
  "type": "Feature",
  "properties": {
    "iso:country":"DE",
    "sg:address":"Dorfstr. 70",
    "sg:city":"Schm\u00f6lln",
    "sg:phone":"+49 39862/2121",
    "sg:postcode":"17291",
    "sg:province":"Brandenburg",
    "wof:name":"J. Gutzke",
    "wof:placetype":"venue"
},
  "geometry": {"coordinates":[14.0987138748,53.2961158752],"type":"Point"}
}