{
  "type": "Feature",
  "properties": {
    "iso:country":"DE",
    "sg:address":"Streiblstr. 34",
    "sg:city":"Hengersberg",
    "sg:phone":"+49 9901/3449",
    "sg:postcode":"94491",
    "sg:province":"Bayern",
    "wof:name":"A. M\u00fchlbauer",
    "wof:placetype":"venue"
},
  "geometry": {"coordinates":[13.048949,48.775555],"type":"Point"}
}