{
  "type": "Feature",
  "properties": {
    "iso:country":"DE",
    "sg:address":"Alt Sievershagen 105",
    "sg:city":"Lambrechtshagen",
    "sg:phone":"+49 381/8003914",
    "sg:postcode":"18069",
    "sg:province":"Mecklenburg-Vorpommern",
    "wof:name":"Hkl Baumaschinen Handelsgesellschaft Mbh",
    "wof:placetype":"venue"
},
  "geometry": {"coordinates":[12.035104,54.114864],"type":"Point"}
}