{
  "type": "Feature",
  "properties": {
    "iso:country":"DE",
    "sg:address":"Gr\u00e4fendorfer Str. 4",
    "sg:city":"Wartmannsroth",
    "sg:phone":"+49 9357/212",
    "sg:postcode":"97797",
    "sg:province":"Bayern",
    "wof:name":"Gl\u00fcck-mativo Gmbh",
    "wof:placetype":"venue"
},
  "geometry": {"coordinates":[9.7786931992,50.1453552246],"type":"Point"}
}