{
  "type": "Feature",
  "properties": {
    "iso:country":"DE",
    "sg:address":"Eichendorffstr. 1",
    "sg:city":"Traunreut",
    "sg:postcode":"83301",
    "sg:province":"Bayern",
    "wof:name":"Alberta Grundst\u00fccks- Verwaltungs Gmbh & Co. Kg",
    "wof:placetype":"venue"
},
  "geometry": {"coordinates":[12.5916213989,47.9634284973],"type":"Point"}
}