{
  "type": "Feature",
  "properties": {
    "iso:country":"DE",
    "sg:address":"Dorfstr. 81",
    "sg:city":"Rot am See",
    "sg:phone":"+49 7958/407",
    "sg:postcode":"74585",
    "sg:province":"Baden-W\u00fcrttemberg",
    "wof:name":"Theo Rohn",
    "wof:placetype":"venue"
},
  "geometry": {"coordinates":[10.0862998962,49.2766494751],"type":"Point"}
}