{
  "type": "Feature",
  "properties": {
    "iso:country":"DE",
    "sg:address":"Pattenser Feldweg 5",
    "sg:city":"Hemmingen",
    "sg:phone":"+49 5101/3555",
    "sg:postcode":"30966",
    "sg:province":"Niedersachsen",
    "wof:name":"Aquatec Ges. F. Mess- Regel- Und Steuerungstechnik",
    "wof:placetype":"venue"
},
  "geometry": {"coordinates":[9.7404880524,52.298500061],"type":"Point"}
}