{
  "type": "Feature",
  "properties": {
    "iso:country":"DE",
    "sg:address":"Pfarrgasse 6",
    "sg:city":"Dieburg",
    "sg:phone":"+49 6071/22377",
    "sg:postcode":"64807",
    "sg:province":"Hessen",
    "wof:name":"Kath. Pfarramt St. Peter Und Paul",
    "wof:placetype":"venue"
},
  "geometry": {"coordinates":[8.8406877518,49.8986701965],"type":"Point"}
}