{
  "type": "Feature",
  "properties": {
    "iso:country":"DE",
    "sg:address":"Stockach 189",
    "sg:city":"Buchenberg",
    "sg:phone":"+49 4908/3789795",
    "sg:postcode":"87474",
    "sg:province":"Bayern",
    "wof:name":"Renergie Allg\u00e4u E.v.",
    "wof:placetype":"venue"
},
  "geometry": {"coordinates":[10.263817,47.705639],"type":"Point"}
}