{
  "type": "Feature",
  "properties": {
    "iso:country":"DE",
    "sg:address":"Schlo\u00dfwender Str. 1",
    "sg:city":"Hannover",
    "sg:postcode":"30159",
    "sg:province":"Niedersachsen",
    "wof:name":"Institut F\u00fcr Raumakustik Bibliothek",
    "wof:placetype":"venue"
},
  "geometry": {"coordinates":[9.722539,52.378933],"type":"Point"}
}