{
  "type": "Feature",
  "properties": {
    "iso:country":"DE",
    "sg:address":"Gasstr. 38-42",
    "sg:city":"Wuppertal",
    "sg:phone":"+49 202/2461701",
    "sg:postcode":"42369",
    "sg:province":"Nordrhein-Westfalen",
    "wof:name":"Bilstein Recycling Gmbh",
    "wof:placetype":"venue"
},
  "geometry": {"coordinates":[7.2140450478,51.2243728638],"type":"Point"}
}