{
  "type": "Feature",
  "properties": {
    "iso:country":"DE",
    "sg:address":"Parsickstr.",
    "sg:city":"Moers",
    "sg:phone":"+49 2841/18583",
    "sg:postcode":"47441",
    "sg:province":"Nordrhein-Westfalen",
    "wof:name":"W. Seif",
    "wof:placetype":"venue"
},
  "geometry": {"coordinates":[6.605365,51.446224],"type":"Point"}
}