{
  "type": "Feature",
  "properties": {
    "iso:country":"DE",
    "sg:address":"Frauenstr. 29",
    "sg:city":"Emsdetten",
    "sg:phone":"+49 2572/89326",
    "sg:postcode":"48282",
    "sg:province":"Nordrhein-Westfalen",
    "wof:name":"Restaurant Schlemmergrill",
    "wof:placetype":"venue"
},
  "geometry": {"coordinates":[7.5281047821,52.1733322144],"type":"Point"}
}