{
  "type": "Feature",
  "properties": {
    "iso:country":"DE",
    "sg:address":"Westendhof 8",
    "sg:city":"Essen",
    "sg:phone":"+49 201/247480",
    "sg:postcode":"45143",
    "sg:province":"Nordrhein-Westfalen",
    "wof:name":"Johnson Controls Integrated Facility Management",
    "wof:placetype":"venue"
},
  "geometry": {"coordinates":[6.996917,51.453602],"type":"Point"}
}