{
  "type": "Feature",
  "properties": {
    "iso:country":"DE",
    "sg:address":"Christ-K\u00f6nig-Str. 28",
    "sg:city":"Bonn",
    "sg:phone":"+49 228/482945",
    "sg:postcode":"53229",
    "sg:province":"Nordrhein-Westfalen",
    "wof:name":"Charlotte Henseler Heilpraktikerin",
    "wof:placetype":"venue"
},
  "geometry": {"coordinates":[7.1824598312,50.7444458008],"type":"Point"}
}