{
  "type": "Feature",
  "properties": {
    "iso:country":"DE",
    "sg:address":"Hauptstr. 206",
    "sg:city":"Schwalbach",
    "sg:phone":"+49 6834/52292",
    "sg:postcode":"66773",
    "sg:province":"Saarland",
    "wof:name":"Kath. Pfarramt St. Martin",
    "wof:placetype":"venue"
},
  "geometry": {"coordinates":[6.8160581589,49.3039093018],"type":"Point"}
}