{
  "type": "Feature",
  "properties": {
    "iso:country":"DE",
    "sg:address":"Friedrichstr. 52 a",
    "sg:city":"Linkenheim-Hochstetten",
    "sg:phone":"+49 7247/5343",
    "sg:postcode":"76351",
    "sg:province":"Baden-W\u00fcrttemberg",
    "wof:name":"M. Und Paul Ret",
    "wof:placetype":"venue"
},
  "geometry": {"coordinates":[8.41121,49.124702],"type":"Point"}
}