{
  "type": "Feature",
  "properties": {
    "iso:country":"DE",
    "sg:address":"Seiffertstr. 95",
    "sg:city":"Bremen",
    "sg:phone":"+49 421/20400",
    "sg:postcode":"28359",
    "sg:province":"Bremen",
    "wof:name":"Johanniterhaus Bremen Ggmbh",
    "wof:placetype":"venue"
},
  "geometry": {"coordinates":[8.879137,53.099651],"type":"Point"}
}