{
  "type": "Feature",
  "properties": {
    "iso:country":"DE",
    "sg:address":"Semperstr. 79",
    "sg:city":"Hamburg",
    "sg:phone":"+49 40/2706880",
    "sg:postcode":"22303",
    "sg:province":"Hamburg",
    "wof:name":"S. Warns Steuerberater",
    "wof:placetype":"venue"
},
  "geometry": {"coordinates":[10.0206317902,53.5881156921],"type":"Point"}
}