{
  "type": "Feature",
  "properties": {
    "iso:country":"DE",
    "sg:address":"Eichkamp 16",
    "sg:city":"Garrel",
    "sg:phone":"+49 4474/98980",
    "sg:postcode":"49681",
    "sg:province":"Niedersachsen",
    "wof:name":"Eichkamp Fleisch- Und Wurstwaren Gmbh & Co. Kg",
    "wof:placetype":"venue"
},
  "geometry": {"coordinates":[8.0312414169,52.9431152344],"type":"Point"}
}