{
  "type": "Feature",
  "properties": {
    "iso:country":"DE",
    "sg:address":"Apfelallee 22",
    "sg:city":"Kruge",
    "sg:phone":"+49 33451/57470",
    "sg:postcode":"16259",
    "sg:province":"Brandenburg",
    "wof:name":"Gebr. Hertling Gmbh & Co.",
    "wof:placetype":"venue"
},
  "geometry": {"coordinates":[13.8767232895,52.7525901794],"type":"Point"}
}