{
  "type": "Feature",
  "properties": {
    "iso:country":"DE",
    "sg:address":"Posener Str. 55",
    "sg:city":"Wilhelmshaven",
    "sg:phone":"+49 4421/53983",
    "sg:postcode":"26388",
    "sg:province":"Niedersachsen",
    "wof:name":"Bistro Adena",
    "wof:placetype":"venue"
},
  "geometry": {"coordinates":[8.0907096863,53.5744895935],"type":"Point"}
}