{
  "type": "Feature",
  "properties": {
    "iso:country":"DE",
    "sg:address":"Stra\u00dfe des Friedens 25",
    "sg:city":"Satzkorn",
    "sg:phone":"+49 331/500634",
    "sg:postcode":"14476",
    "sg:province":"Brandenburg",
    "wof:name":"B. H\u00fcgli",
    "wof:placetype":"venue"
},
  "geometry": {"coordinates":[12.9866447449,52.4770507812],"type":"Point"}
}