{
  "type": "Feature",
  "properties": {
    "iso:country":"DE",
    "sg:address":"Orangeriestr. 9",
    "sg:city":"Ludwigshafen",
    "sg:phone":"+49 621/680300",
    "sg:postcode":"67071",
    "sg:province":"Rheinland-Pfalz",
    "wof:name":"\u00d6kumenische Sozialstation Oggersheim-ruchheim E. V.",
    "wof:placetype":"venue"
},
  "geometry": {"coordinates":[8.3795824051,49.49243927],"type":"Point"}
}