{
  "type": "Feature",
  "properties": {
    "iso:country":"DE",
    "sg:address":"Bahnhofstr.",
    "sg:city":"Wermelskirchen",
    "sg:phone":"+49 2196/4444",
    "sg:postcode":"42929",
    "sg:province":"Nordrhein-Westfalen",
    "wof:name":"Taxi-ruf Taxi",
    "wof:placetype":"venue"
},
  "geometry": {"coordinates":[7.2176251411,51.1436195374],"type":"Point"}
}