{
  "type": "Feature",
  "properties": {
    "iso:country":"DE",
    "sg:address":"Vincenzstr. 29a",
    "sg:city":"Hofheim",
    "sg:phone":"+49 6192/6951",
    "sg:postcode":"65719",
    "sg:province":"Hessen",
    "wof:name":"Eltern- Und Jugendberatung Caritasverband",
    "wof:placetype":"venue"
},
  "geometry": {"coordinates":[8.437777,50.086136],"type":"Point"}
}