{
  "type": "Feature",
  "properties": {
    "iso:country":"DE",
    "sg:address":"Bahnhofstr.",
    "sg:city":"Verden",
    "sg:phone":"+49 4231/2760",
    "sg:postcode":"27283",
    "sg:province":"Niedersachsen",
    "wof:name":"Jonas Kg",
    "wof:placetype":"venue"
},
  "geometry": {"coordinates":[9.2373552322,52.9199638367],"type":"Point"}
}