{
  "type": "Feature",
  "properties": {
    "iso:country":"DE",
    "sg:address":"Markt 4",
    "sg:city":"Lassan",
    "sg:phone":"+49 38374/80360",
    "sg:postcode":"17440",
    "sg:province":"Mecklenburg-Vorpommern",
    "wof:name":"Hartmut Bolljahn",
    "wof:placetype":"venue"
},
  "geometry": {"coordinates":[13.7521953583,54.1185073853],"type":"Point"}
}