{
  "type": "Feature",
  "properties": {
    "iso:country":"DE",
    "sg:address":"Schwabstr 20",
    "sg:city":"Stuttgart",
    "sg:phone":"+49 4971/1619810",
    "sg:postcode":"70197",
    "sg:province":"Baden-W\u00fcrttemberg",
    "wof:name":"Bayerische Landesbank Girozentrale",
    "wof:placetype":"venue"
},
  "geometry": {"coordinates":[9.158623,48.77005],"type":"Point"}
}