{
  "type": "Feature",
  "properties": {
    "iso:country":"DE",
    "sg:address":"Beltgensgarten 2",
    "sg:city":"Hamburg",
    "sg:phone":"+49 40/82222950",
    "sg:postcode":"20537",
    "sg:province":"Hamburg",
    "wof:name":"Consilium Gmbh",
    "wof:placetype":"venue"
},
  "geometry": {"coordinates":[10.0431613922,53.5550308228],"type":"Point"}
}