{
  "type": "Feature",
  "properties": {
    "iso:country":"DE",
    "sg:city":"Pusemuckel",
    "sg:postcode":"12231",
    "wof:name":"Alligator-park",
    "wof:placetype":"venue"
},
  "geometry": {"coordinates":[-73.755257,42.651421],"type":"Point"}
}