{
  "type": "Feature",
  "properties": {
    "iso:country":"DE",
    "sg:address":"Mozartstr. 41",
    "sg:city":"Schwerin",
    "sg:phone":"+49 385/733835",
    "sg:postcode":"19053",
    "sg:province":"Mecklenburg-Vorpommern",
    "wof:name":"Rutsch Und Richter Architekten",
    "wof:placetype":"venue"
},
  "geometry": {"coordinates":[11.398617,53.632011],"type":"Point"}
}