{
  "type": "Feature",
  "properties": {
    "iso:country":"DE",
    "sg:address":"Freiherr-vom-Stein-Str. 2",
    "sg:city":"Walzbachtal",
    "sg:phone":"+49 7203/5722",
    "sg:postcode":"75045",
    "sg:province":"Baden-W\u00fcrttemberg",
    "wof:name":"E. Kuld",
    "wof:placetype":"venue"
},
  "geometry": {"coordinates":[8.5779953003,49.02917099],"type":"Point"}
}