{
  "type": "Feature",
  "properties": {
    "iso:country":"DE",
    "sg:address":"Bahnhofstr. 1",
    "sg:city":"Rheine",
    "sg:postcode":"48431",
    "sg:province":"Nordrhein-Westfalen",
    "wof:name":"Vertrauens\u00e4rztlicher-dienst Der Lva Westfalen",
    "wof:placetype":"venue"
},
  "geometry": {"coordinates":[7.4359989166,52.2773551941],"type":"Point"}
}