{
  "type": "Feature",
  "properties": {
    "iso:country":"DE",
    "sg:address":"Stockmeyerstr 41",
    "sg:city":"Hamburg",
    "sg:phone":"+49 40/3096700",
    "sg:postcode":"20457",
    "sg:province":"Hamburg",
    "wof:name":"Fritz Leckband Hausger\u00e4te-logistik Ek",
    "wof:placetype":"venue"
},
  "geometry": {"coordinates":[10.0073070526,53.5444107056],"type":"Point"}
}