{
  "type": "Feature",
  "properties": {
    "iso:country":"DE",
    "sg:address":"Ringstr. 1",
    "sg:city":"Wachenheim",
    "sg:phone":"+49 6322/1062",
    "sg:postcode":"67157",
    "sg:province":"Rheinland-Pfalz",
    "wof:name":"Emil Diehl",
    "wof:placetype":"venue"
},
  "geometry": {"coordinates":[8.184523,49.437485],"type":"Point"}
}