{
  "type": "Feature",
  "properties": {
    "iso:country":"DE",
    "sg:address":"Am Markt 6",
    "sg:city":"Bad Doberan",
    "sg:phone":"+49 38203/62144",
    "sg:postcode":"18209",
    "sg:province":"Mecklenburg-Vorpommern",
    "wof:name":"Ingrid Bade",
    "wof:placetype":"venue"
},
  "geometry": {"coordinates":[11.898328,54.106754],"type":"Point"}
}