{
  "type": "Feature",
  "properties": {
    "iso:country":"DE",
    "sg:address":"Stadtplatz 43",
    "sg:city":"Zwiesel",
    "sg:phone":"+49 9922/718",
    "sg:postcode":"94227",
    "sg:province":"Bayern",
    "wof:name":"Hypo-bank Ag",
    "wof:placetype":"venue"
},
  "geometry": {"coordinates":[13.231964,49.013939],"type":"Point"}
}