{
  "type": "Feature",
  "properties": {
    "iso:country":"DE",
    "sg:address":"Fuchswinkel 37",
    "sg:city":"Celle",
    "sg:phone":"+49 5141/51550",
    "sg:postcode":"29229",
    "sg:province":"Niedersachsen",
    "wof:name":"Euro Industrie-filmothek 71 Av",
    "wof:placetype":"venue"
},
  "geometry": {"coordinates":[10.0523347855,52.6580505371],"type":"Point"}
}