{
  "type": "Feature",
  "properties": {
    "iso:country":"DE",
    "sg:address":"Rudolf-Diesel-Str. 8",
    "sg:city":"Wiesloch",
    "sg:phone":"+49 6222/71069",
    "sg:postcode":"69168",
    "sg:province":"Baden-W\u00fcrttemberg",
    "wof:name":"Benno Sauer",
    "wof:placetype":"venue"
},
  "geometry": {"coordinates":[8.7462396622,49.2970542908],"type":"Point"}
}