{
  "type": "Feature",
  "properties": {
    "iso:country":"DE",
    "sg:address":"Hanne-Mertens-Weg 9",
    "sg:city":"Hamburg",
    "sg:phone":"+49 40/5553495",
    "sg:postcode":"22455",
    "sg:province":"Hamburg",
    "wof:name":"R. Habermann",
    "wof:placetype":"venue"
},
  "geometry": {"coordinates":[9.9509897232,53.6448059082],"type":"Point"}
}