{
  "type": "Feature",
  "properties": {
    "iso:country":"DE",
    "sg:address":"Hauptstr. 340",
    "sg:city":"Idar-Oberstein",
    "sg:phone":"+49 6781/23044",
    "sg:postcode":"55743",
    "sg:province":"Rheinland-Pfalz",
    "wof:name":"K\u00fcnzer",
    "wof:placetype":"venue"
},
  "geometry": {"coordinates":[7.3225259781,49.7022171021],"type":"Point"}
}