{
  "type": "Feature",
  "properties": {
    "iso:country":"DE",
    "sg:address":"Hochkalterstr. 10",
    "sg:city":"N\u00fcrnberg",
    "sg:phone":"+49 911/862510",
    "sg:postcode":"90471",
    "sg:province":"Bayern",
    "wof:name":"Bernd Roth Architekt",
    "wof:placetype":"venue"
},
  "geometry": {"coordinates":[11.121456,49.409904],"type":"Point"}
}