{
  "type": "Feature",
  "properties": {
    "iso:country":"DE",
    "sg:address":"Schlo\u00dfstr. 12",
    "sg:city":"Kevelaer",
    "sg:phone":"+49 2825/251",
    "sg:postcode":"47627",
    "sg:province":"Nordrhein-Westfalen",
    "wof:name":"Stadtsch\u00e4nke",
    "wof:placetype":"venue"
},
  "geometry": {"coordinates":[6.2770318985,51.6327514648],"type":"Point"}
}