{
  "type": "Feature",
  "properties": {
    "iso:country":"DE",
    "sg:address":"Bahnhofstr. 4",
    "sg:city":"Apolda",
    "sg:phone":"+49 3644/552261",
    "sg:postcode":"99510",
    "sg:province":"Th\u00fcringen",
    "wof:name":"Herbert Scheer",
    "wof:placetype":"venue"
},
  "geometry": {"coordinates":[11.516236,51.023857],"type":"Point"}
}