{
  "type": "Feature",
  "properties": {
    "iso:country":"DE",
    "sg:address":"Ernst-Bihl-Str. 5",
    "sg:city":"Waiblingen",
    "sg:phone":"+49 4971/5195401",
    "sg:postcode":"71332",
    "sg:province":"Baden-W\u00fcrttemberg",
    "wof:name":"Kramer Medien Gmbh",
    "wof:placetype":"venue"
},
  "geometry": {"coordinates":[9.2987346649,48.8315696716],"type":"Point"}
}