{
  "type": "Feature",
  "properties": {
    "iso:country":"DE",
    "sg:address":"Kirchstr. 13",
    "sg:city":"Neuried",
    "sg:phone":"+49 7807/2108",
    "sg:postcode":"77743",
    "sg:province":"Baden-W\u00fcrttemberg",
    "wof:name":"Rainer Marx",
    "wof:placetype":"venue"
},
  "geometry": {"coordinates":[7.809889,48.464539],"type":"Point"}
}