{
  "type": "Feature",
  "properties": {
    "iso:country":"DE",
    "sg:address":"Augustaweg 5",
    "sg:city":"Konstanz",
    "sg:phone":"+49 7531/44200",
    "sg:postcode":"78465",
    "sg:province":"Baden-W\u00fcrttemberg",
    "wof:name":"Hermann Fuchs Architekt",
    "wof:placetype":"venue"
},
  "geometry": {"coordinates":[9.174069,47.710716],"type":"Point"}
}