{
  "type": "Feature",
  "properties": {
    "iso:country":"DE",
    "sg:address":"Sandbachstr.33",
    "sg:city":"Wallenhorst",
    "sg:phone":"+49 5407/349540",
    "sg:postcode":"49134",
    "sg:province":"Niedersachsen",
    "wof:name":"Vikotel-onlineshop",
    "wof:placetype":"venue"
},
  "geometry": {"coordinates":[7.974592,52.331993],"type":"Point"}
}