{
  "type": "Feature",
  "properties": {
    "iso:country":"DE",
    "sg:address":"Marktplatz 36",
    "sg:city":"P\u00f6ttmes",
    "sg:phone":"+49 8253/6000",
    "sg:postcode":"86554",
    "sg:province":"Bayern",
    "wof:name":"Josef Wernhard",
    "wof:placetype":"venue"
},
  "geometry": {"coordinates":[11.0880794525,48.5818901062],"type":"Point"}
}