{
  "type": "Feature",
  "properties": {
    "iso:country":"DE",
    "sg:address":"Gr\u00fcntaler Str. 29",
    "sg:city":"Berlin",
    "sg:phone":"+49 30/4361497",
    "sg:postcode":"13357",
    "sg:province":"Berlin",
    "wof:name":"Haus Gr\u00fcntal Wohnheim Gmbh",
    "wof:placetype":"venue"
},
  "geometry": {"coordinates":[13.3908376694,52.5544624329],"type":"Point"}
}