{
  "type": "Feature",
  "properties": {
    "iso:country":"DE",
    "sg:address":"Hauptstr. 172",
    "sg:city":"Schiffweiler",
    "sg:phone":"+49 6821/962222",
    "sg:postcode":"66578",
    "sg:province":"Saarland",
    "wof:name":"Schramm Und Freichel Rechtanw\u00e4lte",
    "wof:placetype":"venue"
},
  "geometry": {"coordinates":[7.1301679611,49.3612594604],"type":"Point"}
}