{
  "type": "Feature",
  "properties": {
    "iso:country":"DE",
    "sg:address":"Scheiffartsweg 31",
    "sg:city":"Weilerswist",
    "sg:phone":"+49 4922/545566",
    "sg:postcode":"53919",
    "sg:province":"Nordrhein-Westfalen",
    "wof:name":"Email-cover R. Scholz Gmbh",
    "wof:placetype":"venue"
},
  "geometry": {"coordinates":[6.836883,50.76046],"type":"Point"}
}