{
  "type": "Feature",
  "properties": {
    "iso:country":"DE",
    "sg:address":"Sch\u00fctzstr. 5",
    "sg:city":"Trossingen",
    "sg:phone":"+49 7425/6791",
    "sg:postcode":"78647",
    "sg:province":"Baden-W\u00fcrttemberg",
    "wof:name":"Peter Hartwich Textilien",
    "wof:placetype":"venue"
},
  "geometry": {"coordinates":[8.6362104416,48.0791168213],"type":"Point"}
}