{
  "type": "Feature",
  "properties": {
    "iso:country":"DE",
    "sg:address":"Sigmund-Freud-Str. 25",
    "sg:city":"Bonn",
    "sg:phone":"+49 228/2802003",
    "sg:postcode":"53127",
    "sg:province":"Nordrhein-Westfalen",
    "wof:name":"Medizinhistorisches Institut Bibliothek",
    "wof:placetype":"venue"
},
  "geometry": {"coordinates":[7.1032361984,50.7005004883],"type":"Point"}
}