{
  "type": "Feature",
  "properties": {
    "iso:country":"DE",
    "sg:address":"Dietweg 5",
    "sg:city":"Gaimersheim",
    "sg:phone":"+49 8458/2112",
    "sg:postcode":"85080",
    "sg:province":"Bayern",
    "wof:name":"Johann Fleischmann",
    "wof:placetype":"venue"
},
  "geometry": {"coordinates":[11.3774261475,48.811756134],"type":"Point"}
}