{
  "type": "Feature",
  "properties": {
    "iso:country":"DE",
    "sg:address":"Schm\u00fccker Str. 112",
    "sg:city":"Manebach",
    "sg:phone":"+49 3677/849880",
    "sg:postcode":"98693",
    "sg:province":"Th\u00fcringen",
    "wof:name":"Hotel Moosbach",
    "wof:placetype":"venue"
},
  "geometry": {"coordinates":[10.8542747498,50.6658744812],"type":"Point"}
}