{
  "type": "Feature",
  "properties": {
    "iso:country":"DE",
    "sg:address":"An der Dorndelle 8",
    "sg:city":"Kamen",
    "sg:postcode":"59174",
    "sg:province":"Nordrhein-Westfalen",
    "wof:name":"Albert H\u00f6pner Lederwarenfabrik Gmbh & Co. Kg",
    "wof:placetype":"venue"
},
  "geometry": {"coordinates":[7.656093,51.591305],"type":"Point"}
}