{
  "type": "Feature",
  "properties": {
    "iso:country":"DE",
    "sg:address":"Seligenst\u00e4dter Str. 100",
    "sg:city":"Karlstein",
    "sg:phone":"+49 6188/991435",
    "sg:postcode":"63791",
    "sg:province":"Bayern",
    "wof:name":"Inconet-informationssysteme, Communication Und",
    "wof:placetype":"venue"
},
  "geometry": {"coordinates":[9.0199232101,50.0490455627],"type":"Point"}
}