{
  "type": "Feature",
  "properties": {
    "iso:country":"DE",
    "sg:address":"Beethovenstr. 6",
    "sg:city":"Plankstadt",
    "sg:phone":"+49 6202/13084",
    "sg:postcode":"68723",
    "sg:province":"Baden-W\u00fcrttemberg",
    "wof:name":"Karlheinz Renkert Architekt",
    "wof:placetype":"venue"
},
  "geometry": {"coordinates":[8.59379,49.390392],"type":"Point"}
}