{
  "type": "Feature",
  "properties": {
    "iso:country":"DE",
    "sg:address":"St.-Ingberter-Str.",
    "sg:city":"Sulzbach",
    "sg:phone":"+49 6897/3553",
    "sg:postcode":"66280",
    "sg:province":"Saarland",
    "wof:name":"K. Blinn",
    "wof:placetype":"venue"
},
  "geometry": {"coordinates":[7.0737628937,49.2788276672],"type":"Point"}
}