{
  "type": "Feature",
  "properties": {
    "iso:country":"DE",
    "sg:address":"Heilig-Geist-Str. 23",
    "sg:city":"Rosenheim",
    "sg:phone":"+49 8031/13463",
    "sg:postcode":"83022",
    "sg:province":"Bayern",
    "wof:name":"Hans Jung Hunde- Und Katzenbedarf",
    "wof:placetype":"venue"
},
  "geometry": {"coordinates":[12.123539,47.857174],"type":"Point"}
}