{
  "type": "Feature",
  "properties": {
    "iso:country":"DE",
    "sg:address":"Geisfelder Str 131",
    "sg:city":"Bamberg",
    "sg:phone":"+49 951/915510",
    "sg:postcode":"96050",
    "sg:province":"Bayern",
    "wof:name":"Andreas Renner Kg",
    "wof:placetype":"venue"
},
  "geometry": {"coordinates":[10.9273509979,49.8896484375],"type":"Point"}
}