{
  "type": "Feature",
  "properties": {
    "iso:country":"DE",
    "sg:address":"Lerchenb\u00fchl 8",
    "sg:city":"Eckental",
    "sg:phone":"+49 9126/7474",
    "sg:postcode":"90542",
    "sg:province":"Bayern",
    "wof:name":"Union-post Verlags-gmbh",
    "wof:placetype":"venue"
},
  "geometry": {"coordinates":[11.2210674286,49.5726165771],"type":"Point"}
}