{
  "type": "Feature",
  "properties": {
    "iso:country":"DE",
    "sg:address":"Gro\u00dfe Str. 7",
    "sg:city":"Osnabr\u00fcck",
    "sg:phone":"+49 541/29045",
    "sg:postcode":"49074",
    "sg:province":"Niedersachsen",
    "wof:name":"Sal\u00fc",
    "wof:placetype":"venue"
},
  "geometry": {"coordinates":[8.048498,52.273369],"type":"Point"}
}