{
  "type": "Feature",
  "properties": {
    "iso:country":"DE",
    "sg:address":"R\u00f6merstr. 4",
    "sg:city":"Euskirchen",
    "sg:phone":"+49 2251/80481",
    "sg:postcode":"53879",
    "sg:province":"Nordrhein-Westfalen",
    "wof:name":"R\u00f6merimbi\u00df Giovanni",
    "wof:placetype":"venue"
},
  "geometry": {"coordinates":[6.7990550995,50.6539268494],"type":"Point"}
}