{
  "type": "Feature",
  "properties": {
    "iso:country":"DE",
    "sg:address":"Winsener Str. 57",
    "sg:city":"Hamburg",
    "sg:phone":"+49 40/7640020",
    "sg:postcode":"21077",
    "sg:province":"Hamburg",
    "wof:name":"Ingeborg Timmler",
    "wof:placetype":"venue"
},
  "geometry": {"coordinates":[9.990561,53.447437],"type":"Point"}
}