{
  "type": "Feature",
  "properties": {
    "iso:country":"DE",
    "sg:address":"Sch\u00f6ne Aussicht 14",
    "sg:city":"Bad Camberg",
    "sg:phone":"+49 6434/8439",
    "sg:postcode":"65520",
    "sg:province":"Hessen",
    "wof:name":"Maria Eichhorn Hebamme",
    "wof:placetype":"venue"
},
  "geometry": {"coordinates":[8.280372,50.286213],"type":"Point"}
}