{
  "type": "Feature",
  "properties": {
    "iso:country":"DE",
    "sg:address":"K\u00f6lnstr. 18",
    "sg:city":"D\u00fcren",
    "sg:phone":"+49 2421/14254",
    "sg:postcode":"52349",
    "sg:province":"Nordrhein-Westfalen",
    "wof:name":"W. Hensch Herrenmoden Gmbh",
    "wof:placetype":"venue"
},
  "geometry": {"coordinates":[6.4851708412,50.8028259277],"type":"Point"}
}