{
  "type": "Feature",
  "properties": {
    "iso:country":"DE",
    "sg:address":"Am Heiligen Stock 7",
    "sg:city":"M\u00fcnzenberg",
    "sg:phone":"+49 6033/60117",
    "sg:postcode":"35516",
    "sg:province":"Hessen",
    "wof:name":"Liesel Kristen",
    "wof:placetype":"venue"
},
  "geometry": {"coordinates":[8.7269201279,50.4572296143],"type":"Point"}
}