{
  "type": "Feature",
  "properties": {
    "iso:country":"DE",
    "sg:address":"Franzosenberg 13",
    "sg:city":"Linnich",
    "sg:phone":"+49 2462/6557",
    "sg:postcode":"52441",
    "sg:province":"Nordrhein-Westfalen",
    "wof:name":"Geschichtsverein K\u00f6rrenzig 1992 E. V.",
    "wof:placetype":"venue"
},
  "geometry": {"coordinates":[6.2796411514,51.0068511963],"type":"Point"}
}