{
  "type": "Feature",
  "properties": {
    "iso:country":"DE",
    "sg:address":"Krummacherstr. 3",
    "sg:city":"Essen",
    "sg:phone":"+49 2054/82374",
    "sg:postcode":"45219",
    "sg:province":"Nordrhein-Westfalen",
    "wof:name":"Manfred Bongards",
    "wof:placetype":"venue"
},
  "geometry": {"coordinates":[6.9423031807,51.3653411865],"type":"Point"}
}