{
  "type": "Feature",
  "properties": {
    "iso:country":"DE",
    "sg:address":"Winzler Str. 130",
    "sg:city":"Pirmasens",
    "sg:phone":"+49 6331/516730",
    "sg:postcode":"66955",
    "sg:province":"Rheinland-Pfalz",
    "wof:name":"Stegner & Marx Gmbh",
    "wof:placetype":"venue"
},
  "geometry": {"coordinates":[7.594581,49.194302],"type":"Point"}
}