{
  "type": "Feature",
  "properties": {
    "iso:country":"DE",
    "sg:address":"Koppelweg 2",
    "sg:city":"S\u00fcdbrookmerland",
    "sg:phone":"+49 4942/4424",
    "sg:postcode":"26624",
    "sg:province":"Niedersachsen",
    "wof:name":"R. Hainke Gmbh",
    "wof:placetype":"venue"
},
  "geometry": {"coordinates":[7.360699,53.491173],"type":"Point"}
}