{
  "type": "Feature",
  "properties": {
    "iso:country":"DE",
    "sg:address":"Ellerbeker Weg",
    "sg:city":"Kiel",
    "sg:postcode":"24147",
    "sg:province":"Schleswig-Holstein",
    "wof:name":"S Und T Fassaden Gmbh",
    "wof:placetype":"venue"
},
  "geometry": {"coordinates":[10.17723,54.305592],"type":"Point"}
}