{
  "type": "Feature",
  "properties": {
    "iso:country":"DE",
    "sg:address":"Erwin-Rommel-Str. 60",
    "sg:city":"Erlangen",
    "sg:phone":"+49 9131/850",
    "sg:postcode":"91058",
    "sg:province":"Bayern",
    "wof:name":"Universit\u00e4tsbibliothek Ingenieurwissenschaftliche",
    "wof:placetype":"venue"
},
  "geometry": {"coordinates":[11.030808,49.574768],"type":"Point"}
}