{
  "type": "Feature",
  "properties": {
    "iso:country":"DE",
    "sg:address":"Friedrich-H\u00f6lderlin-Weg 19",
    "sg:city":"Speyer",
    "sg:phone":"+49 6232/95592",
    "sg:postcode":"67346",
    "sg:province":"Rheinland-Pfalz",
    "wof:name":"Richard Hoffmann Gmbh",
    "wof:placetype":"venue"
},
  "geometry": {"coordinates":[8.4137573242,49.3234901428],"type":"Point"}
}