{
  "type": "Feature",
  "properties": {
    "iso:country":"DE",
    "sg:address":"Brunnenstr. 18",
    "sg:city":"Bad Pyrmont",
    "sg:phone":"+49 5281/8669",
    "sg:postcode":"31812",
    "sg:province":"Niedersachsen",
    "wof:name":"Pension Blume W. Und D. Bartkus",
    "wof:placetype":"venue"
},
  "geometry": {"coordinates":[9.2599697113,51.985370636],"type":"Point"}
}