{
  "type": "Feature",
  "properties": {
    "iso:country":"DE",
    "sg:address":"Treffauerstr. 46",
    "sg:city":"M\u00fcnchen",
    "sg:phone":"+49 89/7434560",
    "sg:postcode":"81373",
    "sg:province":"Bayern",
    "wof:name":"Schilling & Partner Service Gmbh",
    "wof:placetype":"venue"
},
  "geometry": {"coordinates":[11.5190906525,48.1176490784],"type":"Point"}
}