{
  "type": "Feature",
  "properties": {
    "iso:country":"DE",
    "sg:address":"Burgplatz 1",
    "sg:city":"Reutlingen",
    "sg:phone":"+49 7121/338023",
    "sg:postcode":"72764",
    "sg:province":"Baden-W\u00fcrttemberg",
    "wof:name":"Warsteiner Turm",
    "wof:placetype":"venue"
},
  "geometry": {"coordinates":[9.216629982,48.490398407],"type":"Point"}
}