{
  "type": "Feature",
  "properties": {
    "iso:country":"DE",
    "sg:address":"Rebgasse 1",
    "sg:city":"Ballrechten-Dottingen",
    "sg:phone":"+49 7634/8909",
    "sg:postcode":"79282",
    "sg:province":"Baden-W\u00fcrttemberg",
    "wof:name":"Sonnenbergschule",
    "wof:placetype":"venue"
},
  "geometry": {"coordinates":[7.698937,47.858452],"type":"Point"}
}