{
  "type": "Feature",
  "properties": {
    "iso:country":"DE",
    "sg:address":"Kornstr. 2",
    "sg:city":"Mindelheim",
    "sg:phone":"+49 8261/8447",
    "sg:postcode":"87719",
    "sg:province":"Bayern",
    "wof:name":"Erich Zimmer",
    "wof:placetype":"venue"
},
  "geometry": {"coordinates":[10.4880037308,48.0466156006],"type":"Point"}
}