{
  "type": "Feature",
  "properties": {
    "iso:country":"DE",
    "sg:address":"Neue Heimat 25",
    "sg:city":"V\u00f6hrenbach",
    "sg:phone":"+49 7727/7154",
    "sg:postcode":"78147",
    "sg:province":"Baden-W\u00fcrttemberg",
    "wof:name":"Trimmschnecken Claus Niedermann",
    "wof:placetype":"venue"
},
  "geometry": {"coordinates":[8.2978610992,48.0464172363],"type":"Point"}
}