{
  "type": "Feature",
  "properties": {
    "iso:country":"DE",
    "sg:address":"Reindorfer Weg 15",
    "sg:city":"Buchholz",
    "sg:phone":"+49 4181/5236",
    "sg:postcode":"21244",
    "sg:province":"Niedersachsen",
    "wof:name":"Joachim Maack",
    "wof:placetype":"venue"
},
  "geometry": {"coordinates":[9.898972,53.31506],"type":"Point"}
}