{
  "type": "Feature",
  "properties": {
    "iso:country":"DE",
    "sg:address":"Hausener Str. 38",
    "sg:city":"Mauerstetten",
    "sg:phone":"+49 8341/7613",
    "sg:postcode":"87665",
    "sg:province":"Bayern",
    "wof:name":"K\u00fcnneth Holz Und Logistik Kg",
    "wof:placetype":"venue"
},
  "geometry": {"coordinates":[10.672339,47.887302],"type":"Point"}
}