{
  "type": "Feature",
  "properties": {
    "iso:country":"DE",
    "sg:address":"Fritz-Peters-Str. 42",
    "sg:city":"Moers",
    "sg:postcode":"47447",
    "sg:province":"Nordrhein-Westfalen",
    "wof:name":"F.c.g. Finanz & Home Consulting Gmbh",
    "wof:placetype":"venue"
},
  "geometry": {"coordinates":[6.596115,51.418049],"type":"Point"}
}