{
  "type": "Feature",
  "properties": {
    "iso:country":"DE",
    "sg:address":"Zillhauser Str.",
    "sg:city":"Albstadt",
    "sg:phone":"+49 7432/14605",
    "sg:postcode":"72459",
    "sg:province":"Baden-W\u00fcrttemberg",
    "wof:name":"Tennishalle Pfeffingen",
    "wof:placetype":"venue"
},
  "geometry": {"coordinates":[8.955324173,48.2539329529],"type":"Point"}
}