{
  "type": "Feature",
  "properties": {
    "iso:country":"DE",
    "sg:address":"Allmandstr. 9",
    "sg:city":"Sch\u00f6mberg",
    "sg:phone":"+49 7427/2607",
    "sg:postcode":"72355",
    "sg:province":"Baden-W\u00fcrttemberg",
    "wof:name":"Karl Koch",
    "wof:placetype":"venue"
},
  "geometry": {"coordinates":[8.7562913895,48.20885849],"type":"Point"}
}