{
  "type": "Feature",
  "properties": {
    "iso:country":"DE",
    "sg:address":"Berzdorfer Str. 28",
    "sg:city":"Dresden",
    "sg:phone":"+49 351/2880343",
    "sg:postcode":"01239",
    "sg:province":"Sachsen",
    "wof:name":"Speer Internationale Speditions-gmbh",
    "wof:placetype":"venue"
},
  "geometry": {"coordinates":[13.8007450104,51.0089225769],"type":"Point"}
}