{
  "type": "Feature",
  "properties": {
    "iso:country":"DE",
    "sg:address":"Weningser Str. 10",
    "sg:city":"Gedern",
    "sg:phone":"+49 6045/2998",
    "sg:postcode":"63688",
    "sg:province":"Hessen",
    "wof:name":"Nie\u00dflein",
    "wof:placetype":"venue"
},
  "geometry": {"coordinates":[9.197592,50.420643],"type":"Point"}
}