{
  "type": "Feature",
  "properties": {
    "iso:country":"DE",
    "sg:address":"Gartenstr. 51",
    "sg:city":"Heilbronn",
    "sg:phone":"+49 7131/85185",
    "sg:postcode":"74072",
    "sg:province":"Baden-W\u00fcrttemberg",
    "wof:name":"Lorenz Bachmann",
    "wof:placetype":"venue"
},
  "geometry": {"coordinates":[9.225075,49.14576],"type":"Point"}
}