{
  "type": "Feature",
  "properties": {
    "iso:country":"DE",
    "sg:address":"Niederkircher Str. 18",
    "sg:city":"Trier",
    "sg:phone":"+49 651/81010",
    "sg:postcode":"54294",
    "sg:province":"Rheinland-Pfalz",
    "wof:name":"Hft Elektro-grosshandel",
    "wof:placetype":"venue"
},
  "geometry": {"coordinates":[6.6024360657,49.7267189026],"type":"Point"}
}