{
  "type": "Feature",
  "properties": {
    "iso:country":"DE",
    "sg:address":"Hauptstr. 19",
    "sg:city":"Oberschneiding",
    "sg:phone":"+49 9426/355",
    "sg:postcode":"94363",
    "sg:province":"Bayern",
    "wof:name":"Wilhelm H\u00f6sl",
    "wof:placetype":"venue"
},
  "geometry": {"coordinates":[12.642876,48.75573],"type":"Point"}
}