{
  "type": "Feature",
  "properties": {
    "iso:country":"DE",
    "sg:address":"Saarbr\u00fccker Str. 44",
    "sg:city":"Friedrichsthal",
    "sg:phone":"+49 6897/841404",
    "sg:postcode":"66299",
    "sg:province":"Saarland",
    "wof:name":"Viviane Weber",
    "wof:placetype":"venue"
},
  "geometry": {"coordinates":[7.093296,49.321053],"type":"Point"}
}