{
  "type": "Feature",
  "properties": {
    "iso:country":"DE",
    "sg:address":"Berliner Str 34",
    "sg:city":"Gelnhausen",
    "sg:phone":"+49 6051/2998",
    "sg:postcode":"63571",
    "sg:province":"Hessen",
    "wof:name":"Walter Hiller Gmbh",
    "wof:placetype":"venue"
},
  "geometry": {"coordinates":[9.185791,50.203079],"type":"Point"}
}