{
  "type": "Feature",
  "properties": {
    "iso:country":"DE",
    "sg:address":"Am Leitzelbach 13-15",
    "sg:city":"Sinsheim",
    "sg:postcode":"74889",
    "sg:province":"Baden-W\u00fcrttemberg",
    "wof:name":"Amis Maschinen-vertriebs-gmbh",
    "wof:placetype":"venue"
},
  "geometry": {"coordinates":[8.846944,49.249451],"type":"Point"}
}