{
  "type": "Feature",
  "properties": {
    "iso:country":"DE",
    "sg:address":"Sterkrader Str. 280",
    "sg:city":"Dinslaken",
    "sg:phone":"+49 2064/91198",
    "sg:postcode":"46539",
    "sg:province":"Nordrhein-Westfalen",
    "wof:name":"H. Pahl",
    "wof:placetype":"venue"
},
  "geometry": {"coordinates":[6.763549,51.563038],"type":"Point"}
}