{
  "type": "Feature",
  "properties": {
    "iso:country":"DE",
    "sg:address":"Kreuzstr. 10",
    "sg:city":"Traunstein",
    "sg:phone":"+49 861/13265",
    "sg:postcode":"83278",
    "sg:province":"Bayern",
    "wof:name":"Behr Gmbh",
    "wof:placetype":"venue"
},
  "geometry": {"coordinates":[12.621468544,47.8701820374],"type":"Point"}
}