{
  "type": "Feature",
  "properties": {
    "iso:country":"DE",
    "sg:address":"Echternacher Str. 12",
    "sg:city":"Troisdorf",
    "sg:phone":"+49 2241/406027",
    "sg:postcode":"53842",
    "sg:province":"Nordrhein-Westfalen",
    "wof:name":"Huber Gmbh Produktion Von",
    "wof:placetype":"venue"
},
  "geometry": {"coordinates":[7.11548,50.817558],"type":"Point"}
}