{
  "type": "Feature",
  "properties": {
    "iso:country":"DE",
    "sg:address":"Lindestr. 3",
    "sg:city":"Wilnsdorf",
    "sg:phone":"+49 2737/981090",
    "sg:postcode":"57234",
    "sg:province":"Nordrhein-Westfalen",
    "wof:name":"Gebr. D\u00fcber Kg",
    "wof:placetype":"venue"
},
  "geometry": {"coordinates":[8.1281757355,50.8454627991],"type":"Point"}
}