{
  "type": "Feature",
  "properties": {
    "iso:country":"DE",
    "sg:address":"Hofmattstr. 2",
    "sg:city":"Freiburg",
    "sg:phone":"+49 7664/2762",
    "sg:postcode":"79112",
    "sg:province":"Baden-W\u00fcrttemberg",
    "wof:name":"Dieter K\u00f6nig Unternehmensberater",
    "wof:placetype":"venue"
},
  "geometry": {"coordinates":[7.7175889015,48.0001144409],"type":"Point"}
}