{
  "type": "Feature",
  "properties": {
    "iso:country":"DE",
    "sg:address":"K\u00f6lner Str. 120",
    "sg:city":"Ennepetal",
    "sg:phone":"+49 2333/72220",
    "sg:postcode":"58256",
    "sg:province":"Nordrhein-Westfalen",
    "wof:name":"Wappen-apotheke",
    "wof:placetype":"venue"
},
  "geometry": {"coordinates":[7.342303,51.299236],"type":"Point"}
}