{
  "type": "Feature",
  "properties": {
    "iso:country":"DE",
    "sg:address":"In der Schlade 13",
    "sg:city":"Sundern",
    "sg:postcode":"59846",
    "sg:province":"Nordrhein-Westfalen",
    "wof:name":"Inway Import-export Gmbh",
    "wof:placetype":"venue"
},
  "geometry": {"coordinates":[8.0031461716,51.3218727112],"type":"Point"}
}