{
  "type": "Feature",
  "properties": {
    "iso:country":"DE",
    "sg:address":"Lutherstr. 1",
    "sg:city":"Stendal",
    "sg:phone":"+49 3931/212014",
    "sg:postcode":"39576",
    "sg:province":"Sachsen-Anhalt",
    "wof:name":"Herfried Fahrholz",
    "wof:placetype":"venue"
},
  "geometry": {"coordinates":[11.856959343,52.591545105],"type":"Point"}
}