{
  "type": "Feature",
  "properties": {
    "iso:country":"DE",
    "sg:address":"H\u00f6rsterstr. 52",
    "sg:city":"M\u00fcnster",
    "sg:phone":"+49 251/518774",
    "sg:postcode":"48143",
    "sg:province":"Nordrhein-Westfalen",
    "wof:name":"Heuschneider",
    "wof:placetype":"venue"
},
  "geometry": {"coordinates":[7.630657,51.964424],"type":"Point"}
}