{
  "type": "Feature",
  "properties": {
    "iso:country":"DE",
    "sg:address":"Auf der Heide 19",
    "sg:city":"Nottuln",
    "sg:phone":"+49 2502/9257",
    "sg:postcode":"48301",
    "sg:province":"Nordrhein-Westfalen",
    "wof:name":"H. Und L. Eschhaus",
    "wof:placetype":"venue"
},
  "geometry": {"coordinates":[7.361375,51.931515],"type":"Point"}
}