{
  "type": "Feature",
  "properties": {
    "iso:country":"DE",
    "sg:address":"Wallstr. 22",
    "sg:city":"L\u00fcchow",
    "sg:phone":"+49 5841/1270",
    "sg:postcode":"29439",
    "sg:province":"Niedersachsen",
    "wof:name":"Druck- Und Verlagsgesellschaft K\u00f6hring Gmbh & Co. Kg",
    "wof:placetype":"venue"
},
  "geometry": {"coordinates":[11.1525220871,52.9665145874],"type":"Point"}
}