{
  "type": "Feature",
  "properties": {
    "iso:country":"DE",
    "sg:address":"Am Stellbrink 25",
    "sg:city":"G\u00fctersloh",
    "sg:phone":"+49 5241/92290",
    "sg:postcode":"33334",
    "sg:province":"Nordrhein-Westfalen",
    "wof:name":"Kompotec Kompostierungsanlagen Gmbh",
    "wof:placetype":"venue"
},
  "geometry": {"coordinates":[8.327498,51.926048],"type":"Point"}
}