{
  "type": "Feature",
  "properties": {
    "iso:country":"DE",
    "sg:address":"Brockhauser Weg 52",
    "sg:city":"Plettenberg",
    "sg:phone":"+49 2391/51907",
    "sg:postcode":"58840",
    "sg:province":"Nordrhein-Westfalen",
    "wof:name":"Wilfried Fr\u00fctel",
    "wof:placetype":"venue"
},
  "geometry": {"coordinates":[7.8789539337,51.2297935486],"type":"Point"}
}