{
  "type": "Feature",
  "properties": {
    "iso:country":"DE",
    "sg:address":"Hoyaer Str. 18",
    "sg:city":"Wietzen",
    "sg:phone":"+49 5022/574",
    "sg:postcode":"31613",
    "sg:province":"Niedersachsen",
    "wof:name":"Helmut Plinke",
    "wof:placetype":"venue"
},
  "geometry": {"coordinates":[9.042624,52.702839],"type":"Point"}
}