{
  "type": "Feature",
  "properties": {
    "iso:country":"DE",
    "sg:address":"Widdigerstra\u00dfe 2",
    "sg:city":"Wesseling",
    "sg:postcode":"50389",
    "sg:province":"Nordrhein-Westfalen",
    "wof:name":"Pussytraumland - Katzenbedarf",
    "wof:placetype":"venue"
},
  "geometry": {"coordinates":[6.994055,50.803326],"type":"Point"}
}