{
  "type": "Feature",
  "properties": {
    "iso:country":"DE",
    "sg:address":"Alter Markt 9",
    "sg:city":"M\u00f6nchengladbach",
    "sg:phone":"+49 2161/930920",
    "sg:postcode":"41061",
    "sg:province":"Nordrhein-Westfalen",
    "wof:name":"First Reiseb\u00fcro M\u00f6nchengladbach Gmbh",
    "wof:placetype":"venue"
},
  "geometry": {"coordinates":[6.4315137863,51.1942481995],"type":"Point"}
}