{
  "type": "Feature",
  "properties": {
    "iso:country":"DE",
    "sg:address":"Eisenbahnstr. 7",
    "sg:city":"Mainz-Kastel",
    "sg:phone":"+49 6134/23922",
    "sg:postcode":"55252",
    "sg:province":"Hessen",
    "wof:name":"F. Kayser",
    "wof:placetype":"venue"
},
  "geometry": {"coordinates":[8.2820949554,50.0075836182],"type":"Point"}
}