{
  "type": "Feature",
  "properties": {
    "iso:country":"DE",
    "sg:address":"Wiesbadener Str. 20",
    "sg:city":"Wiesbaden",
    "sg:phone":"+49 611/420212",
    "sg:postcode":"65199",
    "sg:province":"Hessen",
    "wof:name":"Achim Oppermann Gmbh",
    "wof:placetype":"venue"
},
  "geometry": {"coordinates":[8.197995,50.07526],"type":"Point"}
}