{
  "type": "Feature",
  "properties": {
    "iso:country":"DE",
    "sg:address":"Driesener Str 27",
    "sg:city":"Berlin",
    "sg:phone":"+49 30/44650046",
    "sg:postcode":"10439",
    "sg:province":"Berlin",
    "wof:name":"Lias Gmbh",
    "wof:placetype":"venue"
},
  "geometry": {"coordinates":[13.405331,52.550621],"type":"Point"}
}