{
  "type": "Feature",
  "properties": {
    "iso:country":"DE",
    "sg:address":"M\u00f6hringer Str. 64a",
    "sg:city":"Stuttgart",
    "sg:phone":"+49 711/600464",
    "sg:postcode":"70199",
    "sg:province":"Baden-W\u00fcrttemberg",
    "wof:name":"Blaustrumpf",
    "wof:placetype":"venue"
},
  "geometry": {"coordinates":[9.1587162018,48.7616004944],"type":"Point"}
}