{
  "type": "Feature",
  "properties": {
    "iso:country":"DE",
    "sg:address":"Karolastr. 11",
    "sg:city":"Koblenz",
    "sg:phone":"+49 2606/323",
    "sg:postcode":"56073",
    "sg:province":"Rheinland-Pfalz",
    "wof:name":"R. K. L. Spedition - Logistik Gmbh",
    "wof:placetype":"venue"
},
  "geometry": {"coordinates":[7.5399742126,50.3200302124],"type":"Point"}
}