{
  "type": "Feature",
  "properties": {
    "iso:country":"DE",
    "sg:address":"Lederergasse 28",
    "sg:city":"Dingolfing",
    "sg:phone":"+49 8731/2627",
    "sg:postcode":"84130",
    "sg:province":"Bayern",
    "wof:name":"Oskar G. Ulm Steuerberater",
    "wof:placetype":"venue"
},
  "geometry": {"coordinates":[12.4989652634,48.6302833557],"type":"Point"}
}