{
  "type": "Feature",
  "properties": {
    "iso:country":"DE",
    "sg:address":"Hoppe 3",
    "sg:city":"Sprockh\u00f6vel",
    "sg:phone":"+49 2339/914550",
    "sg:postcode":"45549",
    "sg:province":"Nordrhein-Westfalen",
    "wof:name":"R\u00fcther Gmbh & Co Kg",
    "wof:placetype":"venue"
},
  "geometry": {"coordinates":[7.298019,51.346413],"type":"Point"}
}