{
  "type": "Feature",
  "properties": {
    "iso:country":"DE",
    "sg:address":"Bodelschwinghstr. 50",
    "sg:city":"Wesseling",
    "sg:postcode":"50389",
    "sg:province":"Nordrhein-Westfalen",
    "wof:name":"Yildiz Lade- Und L\u00f6schbetrieb Gmbh",
    "wof:placetype":"venue"
},
  "geometry": {"coordinates":[6.9614191055,50.8120498657],"type":"Point"}
}