{
  "type": "Feature",
  "properties": {
    "iso:country":"DE",
    "sg:address":"Guerickestra\u00dfe 7",
    "sg:city":"Frankfurt / M.",
    "sg:postcode":"60488",
    "sg:province":"Hessen",
    "wof:name":"Itt Automotive Europe Gmbh",
    "wof:placetype":"venue"
},
  "geometry": {"coordinates":[8.5976324081,50.1372451782],"type":"Point"}
}