{
  "type": "Feature",
  "properties": {
    "iso:country":"DE",
    "sg:address":"Alersfelde 38",
    "sg:city":"Nieheim",
    "sg:phone":"+49 5274/1261",
    "sg:postcode":"33039",
    "sg:province":"Nordrhein-Westfalen",
    "wof:name":"August Br\u00e4kling Bohr- Und Sprengunternehmen",
    "wof:placetype":"venue"
},
  "geometry": {"coordinates":[9.1268386841,51.8080215454],"type":"Point"}
}