{
  "type": "Feature",
  "properties": {
    "iso:country":"DE",
    "sg:address":"Hindenburgstr. 1",
    "sg:city":"M\u00fccke",
    "sg:phone":"+49 6400/7137",
    "sg:postcode":"35325",
    "sg:province":"Hessen",
    "wof:name":"Josef Knopp",
    "wof:placetype":"venue"
},
  "geometry": {"coordinates":[9.0881223679,50.6219444275],"type":"Point"}
}