{
  "type": "Feature",
  "properties": {
    "iso:country":"DE",
    "sg:address":"Hauptstr. 184",
    "sg:city":"Gorxheimertal",
    "sg:phone":"+49 6201/23258",
    "sg:postcode":"69517",
    "sg:province":"Hessen",
    "wof:name":"Maier",
    "wof:placetype":"venue"
},
  "geometry": {"coordinates":[8.7261762619,49.5336227417],"type":"Point"}
}