{
  "type": "Feature",
  "properties": {
    "iso:country":"DE",
    "sg:address":"Rostocker Str. 26",
    "sg:city":"Kavelstorf",
    "sg:phone":"+49 38208/60131",
    "sg:postcode":"18196",
    "sg:province":"Mecklenburg-Vorpommern",
    "wof:name":"Kurt Drawert",
    "wof:placetype":"venue"
},
  "geometry": {"coordinates":[12.193869,54.007359],"type":"Point"}
}