{
  "type": "Feature",
  "properties": {
    "iso:country":"DE",
    "sg:address":"Schauinslandstr. 9",
    "sg:city":"Sexau",
    "sg:phone":"+49 7641/7039",
    "sg:postcode":"79350",
    "sg:province":"Baden-W\u00fcrttemberg",
    "wof:name":"Horst \u00d6hlgass Gmbh",
    "wof:placetype":"venue"
},
  "geometry": {"coordinates":[7.8934049606,48.0912361145],"type":"Point"}
}