{
  "type": "Feature",
  "properties": {
    "iso:country":"DE",
    "sg:address":"Hufelandstr. 16",
    "sg:city":"Wolgast",
    "sg:phone":"+49 3836/289530",
    "sg:postcode":"17438",
    "sg:province":"Mecklenburg-Vorpommern",
    "wof:name":"Wohnungsgenossenschaft Wolgast Eg",
    "wof:placetype":"venue"
},
  "geometry": {"coordinates":[13.7592077255,54.0541610718],"type":"Point"}
}