{
  "type": "Feature",
  "properties": {
    "iso:country":"DE",
    "sg:address":"Am Brauhaus 8b",
    "sg:city":"Dresden",
    "sg:phone":"+49 351/811990",
    "sg:postcode":"01099",
    "sg:province":"Sachsen",
    "wof:name":"Brauhaus Am Wald- Schl\u00f6\u00dfchen Gmbh",
    "wof:placetype":"venue"
},
  "geometry": {"coordinates":[13.7784929276,51.0683250427],"type":"Point"}
}