{
  "type": "Feature",
  "properties": {
    "iso:country":"DE",
    "sg:address":"Eppendorfer Landstr. 106 a",
    "sg:city":"Hamburg",
    "sg:phone":"+49 40/4804794",
    "sg:postcode":"20249",
    "sg:province":"Hamburg",
    "wof:name":"Feb - Institut F\u00fcr Forschung, Entwicklung Und Beratung Gmbh",
    "wof:placetype":"venue"
},
  "geometry": {"coordinates":[9.9885559082,53.5922546387],"type":"Point"}
}