{
  "type": "Feature",
  "properties": {
    "iso:country":"DE",
    "sg:address":"Fr\u00fchlingstr 9a-11",
    "sg:city":"Trostberg",
    "sg:phone":"+49 8621/2706",
    "sg:postcode":"83308",
    "sg:province":"Bayern",
    "wof:name":"Tosa-sportartikel Kg",
    "wof:placetype":"venue"
},
  "geometry": {"coordinates":[12.573471,48.043896],"type":"Point"}
}