{
  "type": "Feature",
  "properties": {
    "iso:country":"DE",
    "sg:address":"Burgplatz 52",
    "sg:city":"Plochingen",
    "sg:phone":"+49 7153/7005441",
    "sg:postcode":"73207",
    "sg:province":"Baden-W\u00fcrttemberg",
    "wof:name":"Stadtbad Plochingen",
    "wof:placetype":"venue"
},
  "geometry": {"coordinates":[9.4185304642,48.7136611938],"type":"Point"}
}