{
  "type": "Feature",
  "properties": {
    "iso:country":"DE",
    "sg:address":"Hattinger Str. 453",
    "sg:city":"Bochum",
    "sg:postcode":"44795",
    "sg:province":"Nordrhein-Westfalen",
    "wof:name":"Aktiv-markt",
    "wof:placetype":"venue"
},
  "geometry": {"coordinates":[7.1935329437,51.4431800842],"type":"Point"}
}