{
  "type": "Feature",
  "properties": {
    "iso:country":"DE",
    "sg:address":"Hansaring 111-113",
    "sg:city":"K\u00f6ln",
    "sg:postcode":"50670",
    "sg:province":"Nordrhein-Westfalen",
    "wof:name":"Tamburi Gmbh",
    "wof:placetype":"venue"
},
  "geometry": {"coordinates":[6.9524359703,50.9493408203],"type":"Point"}
}