{
  "type": "Feature",
  "properties": {
    "iso:country":"DE",
    "sg:address":"Ulmer Str. 28",
    "sg:city":"R\u00f6merstein",
    "sg:phone":"+49 7382/354",
    "sg:postcode":"72587",
    "sg:province":"Baden-W\u00fcrttemberg",
    "wof:name":"Bolai Tankstelle",
    "wof:placetype":"venue"
},
  "geometry": {"coordinates":[9.5139226913,48.4946327209],"type":"Point"}
}