{
  "type": "Feature",
  "properties": {
    "iso:country":"DE",
    "sg:address":"Martinusstr. 9",
    "sg:city":"Mertesdorf",
    "sg:phone":"+49 651/958880",
    "sg:postcode":"54318",
    "sg:province":"Rheinland-Pfalz",
    "wof:name":"Herbert M\u00fcller Bau-gmbh",
    "wof:placetype":"venue"
},
  "geometry": {"coordinates":[6.733554,49.771477],"type":"Point"}
}