{
  "type": "Feature",
  "properties": {
    "iso:country":"DE",
    "sg:address":"Ludwigstr. 2",
    "sg:city":"Arzberg",
    "sg:phone":"+49 9233/8151",
    "sg:postcode":"95659",
    "sg:province":"Bayern",
    "wof:name":"Alte Hufschmiede",
    "wof:placetype":"venue"
},
  "geometry": {"coordinates":[12.1866502762,50.0569915771],"type":"Point"}
}