{
  "type": "Feature",
  "properties": {
    "iso:country":"DE",
    "sg:address":"Obertaxetweg 14",
    "sg:city":"Gauting",
    "sg:phone":"+49 89/8507414",
    "sg:postcode":"82131",
    "sg:province":"Bayern",
    "wof:name":"Malerbetrieb Niedermann Gmbh",
    "wof:placetype":"venue"
},
  "geometry": {"coordinates":[11.388859,48.062706],"type":"Point"}
}