{
  "type": "Feature",
  "properties": {
    "iso:country":"DE",
    "sg:address":"Fasanenweg 20",
    "sg:city":"Friedrichshafen",
    "sg:phone":"+49 7541/56030",
    "sg:postcode":"88048",
    "sg:province":"Baden-W\u00fcrttemberg",
    "wof:name":"H. M\u00fcller Immobilienmakler",
    "wof:placetype":"venue"
},
  "geometry": {"coordinates":[9.4968385696,47.6916694641],"type":"Point"}
}