{
  "type": "Feature",
  "properties": {
    "iso:country":"DE",
    "sg:address":"K\u00f6nigsteiner Str. 41",
    "sg:city":"Frankfurt",
    "sg:postcode":"65929",
    "sg:province":"Hessen",
    "wof:name":"Krewer Hausverwaltungs- Kg",
    "wof:placetype":"venue"
},
  "geometry": {"coordinates":[8.5447750092,50.1048698425],"type":"Point"}
}