{
  "type": "Feature",
  "properties": {
    "iso:country":"DE",
    "sg:address":"Breite Str. 26",
    "sg:city":"S\u00fcpplingen",
    "sg:phone":"+49 5355/377",
    "sg:postcode":"38373",
    "sg:province":"Niedersachsen",
    "wof:name":"Kath. Pfarramt St. Bonifatius",
    "wof:placetype":"venue"
},
  "geometry": {"coordinates":[10.9061336517,52.2218818665],"type":"Point"}
}