{
  "type": "Feature",
  "properties": {
    "iso:country":"DE",
    "sg:address":"Riekau 32",
    "sg:city":"Dannenberg",
    "sg:phone":"+49 5861",
    "sg:postcode":"29451",
    "sg:province":"Niedersachsen",
    "wof:name":"Edv-fischer",
    "wof:placetype":"venue"
},
  "geometry": {"coordinates":[11.050679,53.072315],"type":"Point"}
}