{
  "type": "Feature",
  "properties": {
    "iso:country":"DE",
    "sg:address":"Siedlerweg 4",
    "sg:city":"Schorndorf",
    "sg:phone":"+49 7181/41436",
    "sg:postcode":"73614",
    "sg:province":"Baden-W\u00fcrttemberg",
    "wof:name":"G. Strohwald Steuerbevollm\u00e4chtigter",
    "wof:placetype":"venue"
},
  "geometry": {"coordinates":[9.5262079239,48.7971763611],"type":"Point"}
}