{
  "type": "Feature",
  "properties": {
    "iso:country":"DE",
    "sg:address":"Uerdinger Str. 128",
    "sg:city":"Moers",
    "sg:phone":"+49 2841/31117",
    "sg:postcode":"47441",
    "sg:province":"Nordrhein-Westfalen",
    "wof:name":"K. Bl\u00e4ser Steuerberater",
    "wof:placetype":"venue"
},
  "geometry": {"coordinates":[6.6413378716,51.4416427612],"type":"Point"}
}