{
  "type": "Feature",
  "properties": {
    "iso:country":"DE",
    "sg:address":"Bl\u00f6cktacher Str.",
    "sg:city":"Friesenried",
    "sg:phone":"+49 8347/270",
    "sg:postcode":"87654",
    "sg:province":"Bayern",
    "wof:name":"Franz Kaiser",
    "wof:placetype":"venue"
},
  "geometry": {"coordinates":[10.53274,47.875946],"type":"Point"}
}