{
  "type": "Feature",
  "properties": {
    "iso:country":"DE",
    "sg:address":"Grabenstr. 48",
    "sg:city":"Stadtlohn",
    "sg:phone":"+49 2563/3255",
    "sg:postcode":"48703",
    "sg:province":"Nordrhein-Westfalen",
    "wof:name":"M\u00f6bel-mensing Inh. Bernhard Mensing",
    "wof:placetype":"venue"
},
  "geometry": {"coordinates":[6.915049,51.993156],"type":"Point"}
}