{
  "type": "Feature",
  "properties": {
    "iso:country":"DE",
    "sg:address":"An den Teichen 9-11",
    "sg:city":"Seesen",
    "sg:phone":"+49 5381/93760",
    "sg:postcode":"38723",
    "sg:province":"Niedersachsen",
    "wof:name":"Altenzentrum St. Vitus Ev. Alten- Und Pflegeheim",
    "wof:placetype":"venue"
},
  "geometry": {"coordinates":[10.170628,51.893524],"type":"Point"}
}