{
  "type": "Feature",
  "properties": {
    "iso:country":"DE",
    "sg:address":"Zschortauer Str. 39-41",
    "sg:city":"Leipzig",
    "sg:phone":"+49 341/91790",
    "sg:postcode":"04129",
    "sg:province":"Sachsen",
    "wof:name":"Raab Karcher Baustoffe",
    "wof:placetype":"venue"
},
  "geometry": {"coordinates":[12.3953924179,51.374622345],"type":"Point"}
}