{
  "type": "Feature",
  "properties": {
    "iso:country":"DE",
    "sg:address":"Johannes-Kepler-Str. 12",
    "sg:city":"Herrenberg",
    "sg:phone":"+49 7032/93680",
    "sg:postcode":"71083",
    "sg:province":"Baden-W\u00fcrttemberg",
    "wof:name":"W\u00fcrttembergische All- Plastik Gmbh",
    "wof:placetype":"venue"
},
  "geometry": {"coordinates":[8.858556,48.601521],"type":"Point"}
}