{
  "type": "Feature",
  "properties": {
    "iso:country":"DE",
    "sg:address":"Ro\u00dfbergweg 20",
    "sg:city":"Chamerau",
    "sg:phone":"+49 9944/759",
    "sg:postcode":"93466",
    "sg:province":"Bayern",
    "wof:name":"M\u00fchlbauer-bau Gmbh",
    "wof:placetype":"venue"
},
  "geometry": {"coordinates":[12.75498,49.196804],"type":"Point"}
}