{
  "type": "Feature",
  "properties": {
    "iso:country":"DE",
    "sg:address":"Wilhelmstr. 3",
    "sg:city":"Ilsede",
    "sg:phone":"+49 5172/13856",
    "sg:postcode":"31241",
    "sg:province":"Niedersachsen",
    "wof:name":"Holger Merkel",
    "wof:placetype":"venue"
},
  "geometry": {"coordinates":[10.189965,52.261681],"type":"Point"}
}