{
  "type": "Feature",
  "properties": {
    "iso:country":"DE",
    "sg:address":"Scheibenfelsenweg 2",
    "sg:city":"Bernau",
    "sg:phone":"+49 7675/1599",
    "sg:postcode":"79872",
    "sg:province":"Baden-W\u00fcrttemberg",
    "wof:name":"Guido Wasmer",
    "wof:placetype":"venue"
},
  "geometry": {"coordinates":[8.0322122574,47.8110237122],"type":"Point"}
}