{
  "type": "Feature",
  "properties": {
    "iso:country":"DE",
    "sg:address":"Bautzener Str. 102A",
    "sg:city":"Neusalza-Spremberg",
    "sg:phone":"+49 35872/3090",
    "sg:postcode":"02742",
    "sg:province":"Sachsen",
    "wof:name":"Ssb Schmidt Stra\u00dfenbau Gmbh",
    "wof:placetype":"venue"
},
  "geometry": {"coordinates":[14.5110301971,51.0483436584],"type":"Point"}
}