{
  "type": "Feature",
  "properties": {
    "iso:country":"DE",
    "sg:address":"Clemens\u00e4ngerring 2",
    "sg:city":"Freising",
    "sg:postcode":"85356",
    "sg:province":"Bayern",
    "wof:name":"Obi Bau- Und Heimwerkermarkt",
    "wof:placetype":"venue"
},
  "geometry": {"coordinates":[11.7552452087,48.3803482056],"type":"Point"}
}