{
  "type": "Feature",
  "properties": {
    "iso:country":"DE",
    "sg:address":"Oberasbacher Str. 17",
    "sg:city":"Zirndorf",
    "sg:phone":"+49 911/969630",
    "sg:postcode":"90513",
    "sg:province":"Bayern",
    "wof:name":"Kurt R\u00f6sch Beteiligungs Gmbh",
    "wof:placetype":"venue"
},
  "geometry": {"coordinates":[10.957666,49.431805],"type":"Point"}
}