{
  "type": "Feature",
  "properties": {
    "iso:country":"DE",
    "sg:address":"Antoniusstr. 3",
    "sg:city":"Wernau",
    "sg:phone":"+49 7153/30010",
    "sg:postcode":"73249",
    "sg:province":"Baden-W\u00fcrttemberg",
    "wof:name":"Bund Deutsche Kath. Jugend",
    "wof:placetype":"venue"
},
  "geometry": {"coordinates":[9.4142723083,48.6988983154],"type":"Point"}
}