{
  "type": "Feature",
  "properties": {
    "iso:country":"DE",
    "sg:address":"Jakobstr. 1",
    "sg:city":"Gr\u00fcnstadt",
    "sg:phone":"+49 6359/5633",
    "sg:postcode":"67269",
    "sg:province":"Rheinland-Pfalz",
    "wof:name":"U. Jahn",
    "wof:placetype":"venue"
},
  "geometry": {"coordinates":[8.1624946594,49.5667114258],"type":"Point"}
}