{
  "type": "Feature",
  "properties": {
    "iso:country":"DE",
    "sg:address":"Feldstr. 28",
    "sg:city":"Saarbr\u00fccken",
    "sg:phone":"+49 681/897175",
    "sg:postcode":"66132",
    "sg:province":"Saarland",
    "wof:name":"Peter Symanski Architekt",
    "wof:placetype":"venue"
},
  "geometry": {"coordinates":[7.0724,49.22348],"type":"Point"}
}