{
  "type": "Feature",
  "properties": {
    "iso:country":"DE",
    "sg:address":"Handstr. 107",
    "sg:city":"Bergisch Gladbach",
    "sg:phone":"+49 2202/51625",
    "sg:postcode":"51469",
    "sg:province":"Nordrhein-Westfalen",
    "wof:name":"Lenertz & Wehowsky Fu\u00dfbodenverlegegesellschaft",
    "wof:placetype":"venue"
},
  "geometry": {"coordinates":[7.094217,50.989178],"type":"Point"}
}