{
  "type": "Feature",
  "properties": {
    "iso:country":"DE",
    "sg:address":"Staufenstr. 16",
    "sg:city":"Freilassing",
    "sg:phone":"+49 8654/65567",
    "sg:postcode":"83395",
    "sg:province":"Bayern",
    "wof:name":"Dr. Franz Von Rennenkampff Tierarzt",
    "wof:placetype":"venue"
},
  "geometry": {"coordinates":[12.9701700211,47.8340034485],"type":"Point"}
}