{
  "type": "Feature",
  "properties": {
    "iso:country":"DE",
    "sg:address":"Weinbergweg 1",
    "sg:city":"Neckarzimmern",
    "sg:phone":"+49 6261/92970",
    "sg:postcode":"74865",
    "sg:province":"Baden-W\u00fcrttemberg",
    "wof:name":"Redaktion S\u00fcdwestdeutsche Illustrierte",
    "wof:placetype":"venue"
},
  "geometry": {"coordinates":[9.130068779,49.3206863403],"type":"Point"}
}