{
  "type": "Feature",
  "properties": {
    "iso:country":"DE",
    "sg:address":"Albrecht-D\u00fcrer-Str. 84",
    "sg:city":"Stollberg",
    "sg:phone":"+49 37296/87210",
    "sg:postcode":"09366",
    "sg:province":"Sachsen",
    "wof:name":"Franziska Hoffamann",
    "wof:placetype":"venue"
},
  "geometry": {"coordinates":[12.768384,50.714062],"type":"Point"}
}