{
  "type": "Feature",
  "properties": {
    "iso:country":"DE",
    "sg:address":"G\u00f6ttschieder Str. 39",
    "sg:city":"Idar-Oberstein",
    "sg:phone":"+49 6781/900396",
    "sg:postcode":"55743",
    "sg:province":"Rheinland-Pfalz",
    "wof:name":"Apotheke Am Pfaffenwald E. K.",
    "wof:placetype":"venue"
},
  "geometry": {"coordinates":[7.334187,49.72168],"type":"Point"}
}