{
  "type": "Feature",
  "properties": {
    "iso:country":"DE",
    "sg:address":"Karlstr. 2 POSTFACH 1760",
    "sg:city":"Greven",
    "sg:phone":"+49 4971/2514410",
    "sg:postcode":"48256",
    "sg:province":"Mecklenburg-Vorpommern",
    "wof:name":"Viventy Bernd Berger",
    "wof:placetype":"venue"
},
  "geometry": {"coordinates":[9.400324,48.50024],"type":"Point"}
}