{
  "type": "Feature",
  "properties": {
    "iso:country":"DE",
    "sg:address":"Gro\u00dfe Str. 17-19",
    "sg:city":"Emden",
    "sg:phone":"+49 4921/91440",
    "sg:postcode":"26721",
    "sg:province":"Niedersachsen",
    "wof:name":"Einhorn-apotheke Eberhard Eschlauer-hefter E.k.",
    "wof:placetype":"venue"
},
  "geometry": {"coordinates":[7.203854,53.366711],"type":"Point"}
}