{
  "type": "Feature",
  "properties": {
    "iso:country":"DE",
    "sg:address":"Seewaldweg 9",
    "sg:city":"Korntal-M\u00fcnchingen",
    "sg:phone":"+49 711/8380005",
    "sg:postcode":"70825",
    "sg:province":"Baden-W\u00fcrttemberg",
    "wof:name":"Kegel & Co. Hausverwaltungen Gmbh",
    "wof:placetype":"venue"
},
  "geometry": {"coordinates":[9.1255083084,48.8344841003],"type":"Point"}
}