{
  "type": "Feature",
  "properties": {
    "iso:country":"DE",
    "sg:address":"Naumburger Str. 46",
    "sg:city":"Leipzig",
    "sg:phone":"+49 341/4801978",
    "sg:postcode":"04229",
    "sg:province":"Sachsen",
    "wof:name":"Dach- Und Fassadenbau Wertheim Gmbh",
    "wof:placetype":"venue"
},
  "geometry": {"coordinates":[12.3249101639,51.3271217346],"type":"Point"}
}