{
  "type": "Feature",
  "properties": {
    "iso:country":"DE",
    "sg:address":"Westwinkel 2",
    "sg:city":"Calbe",
    "sg:postcode":"39240",
    "sg:province":"Sachsen-Anhalt",
    "wof:name":"Saale-kraftwerke Calbe Beteiligungs Gmbh",
    "wof:placetype":"venue"
},
  "geometry": {"coordinates":[11.886902,51.915764],"type":"Point"}
}