{
  "type": "Feature",
  "properties": {
    "iso:country":"DE",
    "sg:address":"Wilhelmstr. 3",
    "sg:city":"Ludwigsburg",
    "sg:postcode":"71638",
    "sg:province":"Baden-W\u00fcrttemberg",
    "wof:name":"Beratungsstelle Der Verbraucherzentrale",
    "wof:placetype":"venue"
},
  "geometry": {"coordinates":[9.19339,48.895924],"type":"Point"}
}