{
  "type": "Feature",
  "properties": {
    "iso:country":"DE",
    "sg:address":"Nordring 202",
    "sg:city":"N\u00fcrnberg",
    "sg:phone":"+49 911/512255",
    "sg:postcode":"90409",
    "sg:province":"Bayern",
    "wof:name":"W. Jarosch",
    "wof:placetype":"venue"
},
  "geometry": {"coordinates":[11.098069,49.470898],"type":"Point"}
}