{
  "type": "Feature",
  "properties": {
    "iso:country":"DE",
    "sg:address":"Ludwig-Freese-Str. 14",
    "sg:city":"Oldenburg",
    "sg:phone":"+49 441/204066",
    "sg:postcode":"26133",
    "sg:province":"Niedersachsen",
    "wof:name":"Interaktio Gesellschaft F\u00fcr Kooperationsvermittlung Und",
    "wof:placetype":"venue"
},
  "geometry": {"coordinates":[8.2283449173,53.0949935913],"type":"Point"}
}