{
  "type": "Feature",
  "properties": {
    "iso:country":"DE",
    "sg:address":"Ga\u00dfnerstr. 19",
    "sg:city":"M\u00fcnchen",
    "sg:postcode":"80639",
    "sg:province":"Bayern",
    "wof:name":"Euro Holding Ag",
    "wof:placetype":"venue"
},
  "geometry": {"coordinates":[11.507398,48.154797],"type":"Point"}
}