{
  "type": "Feature",
  "properties": {
    "iso:country":"DE",
    "sg:address":"Bahnhofstr. 15",
    "sg:city":"Ochsenhausen",
    "sg:postcode":"88416",
    "sg:province":"Baden-W\u00fcrttemberg",
    "wof:name":"Altenzentrum Goldbach Gmbh",
    "wof:placetype":"venue"
},
  "geometry": {"coordinates":[9.950337,48.070389],"type":"Point"}
}