{
  "type": "Feature",
  "properties": {
    "iso:country":"DE",
    "sg:address":"Westfalendamm 84-86",
    "sg:city":"Dortmund",
    "sg:postcode":"44141",
    "sg:province":"Nordrhein-Westfalen",
    "wof:name":"Securitas Gilde Lebensversicherung Ag",
    "wof:placetype":"venue"
},
  "geometry": {"coordinates":[7.490522,51.502686],"type":"Point"}
}