{
  "type": "Feature",
  "properties": {
    "iso:country":"DE",
    "sg:address":"Bahnhofplatz 1",
    "sg:city":"Beckum",
    "sg:phone":"+49 2521/2002",
    "sg:postcode":"59269",
    "sg:province":"Nordrhein-Westfalen",
    "wof:name":"Westfalen Bus Gmbh",
    "wof:placetype":"venue"
},
  "geometry": {"coordinates":[8.0417585373,51.7601318359],"type":"Point"}
}