{
  "type": "Feature",
  "properties": {
    "iso:country":"DE",
    "sg:address":"Im Wingert 9",
    "sg:city":"Nidda",
    "sg:phone":"+49 6043/591",
    "sg:postcode":"63667",
    "sg:province":"Hessen",
    "wof:name":"Schenk Und Bartel Schallschutztechnik Gmbh",
    "wof:placetype":"venue"
},
  "geometry": {"coordinates":[9.007078,50.425369],"type":"Point"}
}