{
  "type": "Feature",
  "properties": {
    "iso:country":"DE",
    "sg:address":"Niebuhrstr. 9",
    "sg:city":"Berlin",
    "sg:phone":"+49 30/3245136",
    "sg:postcode":"10629",
    "sg:province":"Berlin",
    "wof:name":"Lotti Benn",
    "wof:placetype":"venue"
},
  "geometry": {"coordinates":[13.314777,52.50449],"type":"Point"}
}