{
  "type": "Feature",
  "properties": {
    "iso:country":"DE",
    "sg:address":"Pfeffingen",
    "sg:city":"Bad D\u00fcrkheim",
    "sg:phone":"+49 6322/8607",
    "sg:postcode":"67098",
    "sg:province":"Rheinland-Pfalz",
    "wof:name":"Karl Fuhrmann Weinanbau",
    "wof:placetype":"venue"
},
  "geometry": {"coordinates":[8.1761512756,49.4703178406],"type":"Point"}
}