{
  "type": "Feature",
  "properties": {
    "iso:country":"DE",
    "sg:address":"Birkenweg 28",
    "sg:city":"Bad Bramstedt",
    "sg:phone":"+49 4192/50000",
    "sg:postcode":"24576",
    "sg:province":"Schleswig-Holstein",
    "wof:name":"Hotel Tanneneck Inh. Eberhard Kapahnke",
    "wof:placetype":"venue"
},
  "geometry": {"coordinates":[9.8920545578,53.9000701904],"type":"Point"}
}