{
  "type": "Feature",
  "properties": {
    "iso:country":"DE",
    "sg:address":"Teltower Damm 46",
    "sg:city":"Berlin",
    "sg:phone":"+49 30/8151884",
    "sg:postcode":"14167",
    "sg:province":"Berlin",
    "wof:name":"A Und A",
    "wof:placetype":"venue"
},
  "geometry": {"coordinates":[13.2595176697,52.4297065735],"type":"Point"}
}