{
  "type": "Feature",
  "properties": {
    "iso:country":"DE",
    "sg:address":"Im Gr\u00f6rach 21",
    "sg:city":"Aichtal",
    "sg:phone":"+49 7127/81190",
    "sg:postcode":"72631",
    "sg:province":"Baden-W\u00fcrttemberg",
    "wof:name":"Eberhard Von Au",
    "wof:placetype":"venue"
},
  "geometry": {"coordinates":[9.2129259109,48.625377655],"type":"Point"}
}