{
  "type": "Feature",
  "properties": {
    "iso:country":"DE",
    "sg:address":"Lausicker Str. 13 c",
    "sg:city":"Grimma",
    "sg:phone":"+49 3437/919847",
    "sg:postcode":"04668",
    "sg:province":"Sachsen",
    "wof:name":"Dmv Deininger Medien Vertriebs Gmbh",
    "wof:placetype":"venue"
},
  "geometry": {"coordinates":[12.7110214233,51.22108078],"type":"Point"}
}