{
  "type": "Feature",
  "properties": {
    "iso:country":"DE",
    "sg:address":"Voigtlandstr. 13",
    "sg:city":"Hohensaaten",
    "sg:phone":"+49 33368/70610",
    "sg:postcode":"16248",
    "sg:province":"Brandenburg",
    "wof:name":"Holzbau Hohensaaten Gmbh",
    "wof:placetype":"venue"
},
  "geometry": {"coordinates":[14.139609,52.872547],"type":"Point"}
}