{
  "type": "Feature",
  "properties": {
    "iso:country":"DE",
    "sg:address":"Alarichstr. 17",
    "sg:city":"Stuttgart",
    "sg:phone":"+49 711/8965240",
    "sg:postcode":"70469",
    "sg:province":"Baden-W\u00fcrttemberg",
    "wof:name":"Kopper & Schenkel Architekten",
    "wof:placetype":"venue"
},
  "geometry": {"coordinates":[9.175548,48.810558],"type":"Point"}
}