{
  "type": "Feature",
  "properties": {
    "iso:country":"DE",
    "sg:address":"Weinstr. 40",
    "sg:city":"Siebeldingen",
    "sg:phone":"+49 6345/1671",
    "sg:postcode":"76833",
    "sg:province":"Rheinland-Pfalz",
    "wof:name":"Adolf Anlag",
    "wof:placetype":"venue"
},
  "geometry": {"coordinates":[8.0492649078,49.2087554932],"type":"Point"}
}