{
  "type": "Feature",
  "properties": {
    "iso:country":"DE",
    "sg:address":"Kroog 3",
    "sg:city":"Kellinghusen",
    "sg:phone":"+49 4822/5838",
    "sg:postcode":"25548",
    "sg:province":"Schleswig-Holstein",
    "wof:name":"Dr. Hans-peter Mannhardt Tierarzt",
    "wof:placetype":"venue"
},
  "geometry": {"coordinates":[9.7304410934,53.948425293],"type":"Point"}
}