{
  "type": "Feature",
  "properties": {
    "iso:country":"DE",
    "sg:address":"Ulrichstr. 6",
    "sg:city":"W\u00fcrzburg",
    "sg:phone":"+49 931/886866",
    "sg:postcode":"97074",
    "sg:province":"Bayern",
    "wof:name":"Romantica",
    "wof:placetype":"venue"
},
  "geometry": {"coordinates":[9.9466371536,49.7878761292],"type":"Point"}
}