{
  "type": "Feature",
  "properties": {
    "iso:country":"DE",
    "sg:address":"Glockengasse 12",
    "sg:city":"Regensburg",
    "sg:phone":"+49 941/54714",
    "sg:postcode":"93047",
    "sg:province":"Bayern",
    "wof:name":"T. Rembold",
    "wof:placetype":"venue"
},
  "geometry": {"coordinates":[12.091515,49.01886],"type":"Point"}
}