{
  "type": "Feature",
  "properties": {
    "iso:country":"DE",
    "sg:address":"Langenfeldstr. 4",
    "sg:city":"M\u00fclheim",
    "sg:phone":"+49 208/485884",
    "sg:postcode":"45481",
    "sg:province":"Nordrhein-Westfalen",
    "wof:name":"Aus Dem Siepen",
    "wof:placetype":"venue"
},
  "geometry": {"coordinates":[6.87454,51.404968],"type":"Point"}
}