{
  "type": "Feature",
  "properties": {
    "iso:country":"DE",
    "sg:address":"Haus-Horl-Str. 70",
    "sg:city":"Essen",
    "sg:phone":"+49 201/668405",
    "sg:postcode":"45357",
    "sg:province":"Nordrhein-Westfalen",
    "wof:name":"Johannes Bauer",
    "wof:placetype":"venue"
},
  "geometry": {"coordinates":[6.9413700104,51.491733551],"type":"Point"}
}