{
  "type": "Feature",
  "properties": {
    "iso:country":"DE",
    "sg:address":"Neu-L\u00f6h 49a",
    "sg:city":"Wermelskirchen",
    "sg:phone":"+49 2196/92778",
    "sg:postcode":"42929",
    "sg:province":"Nordrhein-Westfalen",
    "wof:name":"Ernst Chemische Erzeugnisse Handelsges. Mbh",
    "wof:placetype":"venue"
},
  "geometry": {"coordinates":[7.1789331436,51.1073875427],"type":"Point"}
}