{
  "type": "Feature",
  "properties": {
    "iso:country":"DE",
    "sg:address":"Zwingenburgstr. 2",
    "sg:city":"Mosbach",
    "sg:phone":"+49 6261/9430",
    "sg:postcode":"74821",
    "sg:province":"Baden-W\u00fcrttemberg",
    "wof:name":"Autozentrale Gmbh",
    "wof:placetype":"venue"
},
  "geometry": {"coordinates":[9.1208906174,49.3385124207],"type":"Point"}
}