{
  "type": "Feature",
  "properties": {
    "iso:country":"DE",
    "sg:address":"Ruhrstr. 36",
    "sg:city":"Erfurt",
    "sg:phone":"+49 361/5660780",
    "sg:postcode":"99085",
    "sg:province":"Th\u00fcringen",
    "wof:name":"Dms Druckmaschinenservice Gmbh",
    "wof:placetype":"venue"
},
  "geometry": {"coordinates":[11.04339,50.977268],"type":"Point"}
}