{
  "type": "Feature",
  "properties": {
    "iso:country":"DE",
    "sg:address":"Menchau 17",
    "sg:city":"Thurnau",
    "sg:phone":"+49 9228/328",
    "sg:postcode":"95349",
    "sg:province":"Bayern",
    "wof:name":"Dorle T\u00e4uber",
    "wof:placetype":"venue"
},
  "geometry": {"coordinates":[11.3764648438,50.0121192932],"type":"Point"}
}