{
  "type": "Feature",
  "properties": {
    "iso:country":"DE",
    "sg:address":"Hinterstr. 55",
    "sg:city":"Bad Wildungen",
    "sg:phone":"+49 5621/3846",
    "sg:postcode":"34537",
    "sg:province":"Hessen",
    "wof:name":"Wilhelm Oppermann",
    "wof:placetype":"venue"
},
  "geometry": {"coordinates":[9.126539,51.119678],"type":"Point"}
}