{
  "type": "Feature",
  "properties": {
    "iso:country":"DE",
    "sg:address":"Metjenkamp 11",
    "sg:city":"Wunstorf",
    "sg:phone":"+49 5033/5248",
    "sg:postcode":"31515",
    "sg:province":"Niedersachsen",
    "wof:name":"Fremdenheim Wilma Borcherding",
    "wof:placetype":"venue"
},
  "geometry": {"coordinates":[9.3636026382,52.4594078064],"type":"Point"}
}