{
  "type": "Feature",
  "properties": {
    "iso:country":"DE",
    "sg:address":"Schlo\u00dfstr. 59",
    "sg:city":"Pirmasens",
    "sg:phone":"+49 6331/77838",
    "sg:postcode":"66953",
    "sg:province":"Rheinland-Pfalz",
    "wof:name":"T. Drumm",
    "wof:placetype":"venue"
},
  "geometry": {"coordinates":[7.6060271263,49.2001876831],"type":"Point"}
}