{
  "type": "Feature",
  "properties": {
    "iso:country":"DE",
    "sg:address":"Adlerstr. 25",
    "sg:city":"Friesenheim",
    "sg:phone":"+49 7821/96550",
    "sg:postcode":"77948",
    "sg:province":"Baden-W\u00fcrttemberg",
    "wof:name":"Wieber Baustoffe Gmbh",
    "wof:placetype":"venue"
},
  "geometry": {"coordinates":[7.873341,48.371025],"type":"Point"}
}