{
  "type": "Feature",
  "properties": {
    "iso:country":"DE",
    "sg:address":"Biefangstr. 53",
    "sg:city":"Oberhausen",
    "sg:phone":"+49 208/665652",
    "sg:postcode":"46149",
    "sg:province":"Nordrhein-Westfalen",
    "wof:name":"Heinz Vester",
    "wof:placetype":"venue"
},
  "geometry": {"coordinates":[6.830003,51.511909],"type":"Point"}
}