{
  "type": "Feature",
  "properties": {
    "iso:country":"DE",
    "sg:address":"Billwerder Ring 12",
    "sg:city":"Hamburg",
    "sg:phone":"+49 40/7347240",
    "sg:postcode":"21035",
    "sg:province":"Hamburg",
    "wof:name":"Rts Transport-service J\u00fcrgen Klein Gmbh",
    "wof:placetype":"venue"
},
  "geometry": {"coordinates":[10.119564,53.496357],"type":"Point"}
}