{
  "type": "Feature",
  "properties": {
    "iso:country":"DE",
    "sg:address":"Keplerstr. 32",
    "sg:city":"Oberndorf",
    "sg:phone":"+49 7423/4732",
    "sg:postcode":"78727",
    "sg:province":"Baden-W\u00fcrttemberg",
    "wof:name":"Wbg Wierzbitzki Beteiligungs Gmbh",
    "wof:placetype":"venue"
},
  "geometry": {"coordinates":[8.560096,48.294964],"type":"Point"}
}