{
  "type": "Feature",
  "properties": {
    "iso:country":"DE",
    "sg:address":"Mainzer Str. 370",
    "sg:city":"Bingen",
    "sg:phone":"+49 6721/16686",
    "sg:postcode":"55411",
    "sg:province":"Rheinland-Pfalz",
    "wof:name":"Alfons R\u00f6sch",
    "wof:placetype":"venue"
},
  "geometry": {"coordinates":[7.9567489624,49.9668197632],"type":"Point"}
}