{
  "type": "Feature",
  "properties": {
    "iso:country":"DE",
    "sg:address":"Dorfstr. 35",
    "sg:city":"Nei\u00dfeaue",
    "sg:phone":"+49 35820/60170",
    "sg:postcode":"02829",
    "sg:province":"Sachsen",
    "wof:name":"Joachim Schwonnek",
    "wof:placetype":"venue"
},
  "geometry": {"coordinates":[14.9103336334,51.0969581604],"type":"Point"}
}