{
  "type": "Feature",
  "properties": {
    "iso:country":"DE",
    "sg:address":"Herschelberg 4",
    "sg:city":"Patersberg",
    "sg:phone":"+49 6771/2518",
    "sg:postcode":"56348",
    "sg:province":"Rheinland-Pfalz",
    "wof:name":"Pension Emil Schaub",
    "wof:placetype":"venue"
},
  "geometry": {"coordinates":[7.7287302017,50.1568603516],"type":"Point"}
}