{
  "type": "Feature",
  "properties": {
    "iso:country":"DE",
    "sg:address":"Grundweg 5A",
    "sg:city":"Malter",
    "sg:phone":"+49 3504/619307",
    "sg:postcode":"01744",
    "sg:province":"Sachsen",
    "wof:name":"Juristisches Repetitorium Im Internet",
    "wof:placetype":"venue"
},
  "geometry": {"coordinates":[13.65725,50.91951],"type":"Point"}
}