{
  "type": "Feature",
  "properties": {
    "iso:country":"DE",
    "sg:address":"Landstr. 11",
    "sg:city":"Windeck",
    "sg:phone":"+49 2292/7392",
    "sg:postcode":"51570",
    "sg:province":"Nordrhein-Westfalen",
    "wof:name":"Restaurant Helmut Vogel",
    "wof:placetype":"venue"
},
  "geometry": {"coordinates":[7.5982499123,50.7675285339],"type":"Point"}
}