{
  "type": "Feature",
  "properties": {
    "iso:country":"DE",
    "sg:address":"Am Fleth 40",
    "sg:city":"Gl\u00fcckstadt",
    "sg:postcode":"25348",
    "sg:province":"Schleswig-Holstein",
    "wof:name":"Marion Oberender Rechtsanw\u00e4ltin",
    "wof:placetype":"venue"
},
  "geometry": {"coordinates":[9.4211368561,53.7894744873],"type":"Point"}
}