{
  "type": "Feature",
  "properties": {
    "iso:country":"DE",
    "sg:address":"Im Dau 14",
    "sg:city":"K\u00f6ln",
    "sg:postcode":"50678",
    "sg:province":"Nordrhein-Westfalen",
    "wof:name":"Architektur Und Umwelttechnik Dr.-ing. Schnappinger Und Par.",
    "wof:placetype":"venue"
},
  "geometry": {"coordinates":[6.956194,50.927273],"type":"Point"}
}