{
  "type": "Feature",
  "properties": {
    "iso:country":"DE",
    "sg:address":"Leopoldstr. 1",
    "sg:city":"Riegel",
    "sg:phone":"+49 4976/423675",
    "sg:postcode":"79359",
    "sg:province":"Baden-W\u00fcrttemberg",
    "wof:name":"Raiffeisenbank Volksbank Kaiserst., March Eg",
    "wof:placetype":"venue"
},
  "geometry": {"coordinates":[7.751518,48.150688],"type":"Point"}
}