{
  "type": "Feature",
  "properties": {
    "iso:country":"DE",
    "sg:address":"Am Anger 13",
    "sg:city":"Toba",
    "sg:phone":"+49 36330/459",
    "sg:postcode":"99713",
    "sg:province":"Th\u00fcringen",
    "wof:name":"Wolfgang Melneck",
    "wof:placetype":"venue"
},
  "geometry": {"coordinates":[10.680688858,51.3180084229],"type":"Point"}
}