{
  "type": "Feature",
  "properties": {
    "iso:country":"DE",
    "sg:address":"Kolumbusstr 1",
    "sg:city":"Sindelfingen",
    "sg:phone":"+49 7031/936965",
    "sg:postcode":"71063",
    "sg:province":"Baden-W\u00fcrttemberg",
    "wof:name":"Mawag Gmbh & Co Kg Machines And Equipment For The Paper Industry",
    "wof:placetype":"venue"
},
  "geometry": {"coordinates":[8.985325,48.707642],"type":"Point"}
}