{
  "type": "Feature",
  "properties": {
    "iso:country":"DE",
    "sg:address":"Rheinallee 8-11",
    "sg:city":"K\u00f6nigswinter",
    "sg:phone":"+49 2223/21021",
    "sg:postcode":"53639",
    "sg:province":"Nordrhein-Westfalen",
    "wof:name":"Orgas Gmbh",
    "wof:placetype":"venue"
},
  "geometry": {"coordinates":[7.1926379204,50.6730880737],"type":"Point"}
}