{
  "type": "Feature",
  "properties": {
    "iso:country":"DE",
    "sg:address":"Weidenauer Str. 72",
    "sg:city":"Siegen",
    "sg:phone":"+49 271/73495",
    "sg:postcode":"57076",
    "sg:province":"Nordrhein-Westfalen",
    "wof:name":"Hees Gmbh",
    "wof:placetype":"venue"
},
  "geometry": {"coordinates":[8.0207252502,50.9033164978],"type":"Point"}
}