{
  "type": "Feature",
  "properties": {
    "iso:country":"DE",
    "sg:address":"Lerchenhain 60",
    "sg:city":"Nottuln",
    "sg:postcode":"48301",
    "sg:province":"Nordrhein-Westfalen",
    "wof:name":"Obst Und Gem\u00fcse",
    "wof:placetype":"venue"
},
  "geometry": {"coordinates":[7.3561820984,51.9190330505],"type":"Point"}
}