{
  "type": "Feature",
  "properties": {
    "iso:country":"DE",
    "sg:address":"Hauptstr. 22",
    "sg:city":"Emlichheim",
    "sg:phone":"+49 5943/4488",
    "sg:postcode":"49824",
    "sg:province":"Niedersachsen",
    "wof:name":"Gerhard Warsen",
    "wof:placetype":"venue"
},
  "geometry": {"coordinates":[6.8498997688,52.6057701111],"type":"Point"}
}