{
  "type": "Feature",
  "properties": {
    "iso:country":"DE",
    "sg:address":"Dickfeitzen 4 a",
    "sg:city":"Waddeweitz",
    "sg:postcode":"29496",
    "sg:province":"Niedersachsen",
    "wof:name":"Zimmerei Drobek Schulz Gmbh",
    "wof:placetype":"venue"
},
  "geometry": {"coordinates":[10.9388408661,52.9884757996],"type":"Point"}
}