{
  "type": "Feature",
  "properties": {
    "iso:country":"DE",
    "sg:address":"Sennelagerstr. 157",
    "sg:city":"Paderborn",
    "sg:phone":"+49 5254/7211",
    "sg:postcode":"33104",
    "sg:province":"Nordrhein-Westfalen",
    "wof:name":"M. Wecker",
    "wof:placetype":"venue"
},
  "geometry": {"coordinates":[8.69148,51.766102],"type":"Point"}
}