{
  "type": "Feature",
  "properties": {
    "iso:country":"DE",
    "sg:address":"Weinstr. 24",
    "sg:city":"Kirchheim",
    "sg:phone":"+49 6359/1339",
    "sg:postcode":"67281",
    "sg:province":"Rheinland-Pfalz",
    "wof:name":"Weingut Leiningerhof Inh. V. Benzinger",
    "wof:placetype":"venue"
},
  "geometry": {"coordinates":[8.1854248047,49.538318634],"type":"Point"}
}