{
  "type": "Feature",
  "properties": {
    "iso:country":"DE",
    "sg:address":"Grevener Str. 61 c",
    "sg:city":"M\u00fcnster",
    "sg:postcode":"48149",
    "sg:province":"Nordrhein-Westfalen",
    "wof:name":"Teufel Schl\u00fcsseldienst Inh. J\u00f6rg Mehlis E. K.",
    "wof:placetype":"venue"
},
  "geometry": {"coordinates":[7.5934200287,51.9564552307],"type":"Point"}
}