{
  "type": "Feature",
  "properties": {
    "iso:country":"DE",
    "sg:address":"Oberhofer Str. 36a",
    "sg:city":"Steinbach-Hallenberg",
    "sg:phone":"+49 36847/3414",
    "sg:postcode":"98587",
    "sg:province":"Th\u00fcringen",
    "wof:name":"W. Tautenhain",
    "wof:placetype":"venue"
},
  "geometry": {"coordinates":[10.577485,50.714024],"type":"Point"}
}