{
  "type": "Feature",
  "properties": {
    "iso:country":"DE",
    "sg:address":"H\u00fcttfeldstr. 28",
    "sg:city":"Aalen",
    "sg:phone":"+49 7361/62117",
    "sg:postcode":"73430",
    "sg:province":"Baden-W\u00fcrttemberg",
    "wof:name":"Peter Flad Heilpraktiker",
    "wof:placetype":"venue"
},
  "geometry": {"coordinates":[10.0806770325,48.836517334],"type":"Point"}
}