{
  "type": "Feature",
  "properties": {
    "iso:country":"DE",
    "sg:address":"Tristlstr. 10",
    "sg:city":"Vilsheim",
    "sg:phone":"+49 8706/1675",
    "sg:postcode":"84186",
    "sg:province":"Bayern",
    "wof:name":"A. Schachtner",
    "wof:placetype":"venue"
},
  "geometry": {"coordinates":[12.08843,48.448101],"type":"Point"}
}