{
  "type": "Feature",
  "properties": {
    "iso:country":"DE",
    "sg:address":"G\u00fclichstr. 13 a",
    "sg:city":"Bad M\u00fcnder",
    "sg:phone":"+49 5042/5501",
    "sg:postcode":"31848",
    "sg:province":"Niedersachsen",
    "wof:name":"Reinhard Dumke",
    "wof:placetype":"venue"
},
  "geometry": {"coordinates":[9.440208,52.156796],"type":"Point"}
}