{
  "type": "Feature",
  "properties": {
    "iso:country":"DE",
    "sg:address":"Krumme Str. 10",
    "sg:city":"Berlin",
    "sg:phone":"+49 30/34303214",
    "sg:postcode":"10585",
    "sg:province":"Berlin",
    "wof:name":"Stadtbad I",
    "wof:placetype":"venue"
},
  "geometry": {"coordinates":[13.3094749451,52.5145072937],"type":"Point"}
}