{
  "type": "Feature",
  "properties": {
    "iso:country":"DE",
    "sg:address":"Eschenwasen 5",
    "sg:city":"Spaichingen",
    "sg:phone":"+49 7424/94860",
    "sg:postcode":"78549",
    "sg:province":"Baden-W\u00fcrttemberg",
    "wof:name":"Vhw-metallpre\u00dfwerk Gmbh",
    "wof:placetype":"venue"
},
  "geometry": {"coordinates":[8.7198972702,48.0676460266],"type":"Point"}
}