{
  "type": "Feature",
  "properties": {
    "iso:country":"DE",
    "sg:address":"Rohrbrunner Str. 32",
    "sg:city":"Schollbrunn",
    "sg:postcode":"97852",
    "sg:province":"Bayern",
    "wof:name":"Absolut Versand Ohg",
    "wof:placetype":"venue"
},
  "geometry": {"coordinates":[9.4642572403,49.8348808289],"type":"Point"}
}