{
  "type": "Feature",
  "properties": {
    "iso:country":"DE",
    "sg:address":"Am Forstbann 24",
    "sg:city":"Lorsch",
    "sg:phone":"+49 6251/53259",
    "sg:postcode":"64653",
    "sg:province":"Hessen",
    "wof:name":"Paul Massoth",
    "wof:placetype":"venue"
},
  "geometry": {"coordinates":[8.573393,49.640556],"type":"Point"}
}