{
  "type": "Feature",
  "properties": {
    "iso:country":"DE",
    "sg:address":"W\u00f6rnitzstr. 15",
    "sg:city":"Schnelldorf",
    "sg:phone":"+49 7950/320",
    "sg:postcode":"91625",
    "sg:province":"Bayern",
    "wof:name":"Schreinerei Lehr Gmbh",
    "wof:placetype":"venue"
},
  "geometry": {"coordinates":[10.20771,49.20097],"type":"Point"}
}