{
  "type": "Feature",
  "properties": {
    "iso:country":"DE",
    "sg:address":"Ludwigsburger Str. 45",
    "sg:city":"Benningen",
    "sg:phone":"+49 7144/840513",
    "sg:postcode":"71726",
    "sg:province":"Baden-W\u00fcrttemberg",
    "wof:name":"Sarggenossenschaft Heilbronn Eg",
    "wof:placetype":"venue"
},
  "geometry": {"coordinates":[9.2426452637,48.9442520142],"type":"Point"}
}