{
  "type": "Feature",
  "properties": {
    "iso:country":"DE",
    "sg:address":"Nestorstr 58-59",
    "sg:city":"Berlin",
    "sg:phone":"+49 30/22494610",
    "sg:postcode":"10711",
    "sg:province":"Berlin",
    "wof:name":"Net:impaqt Deutschland Gmbh",
    "wof:placetype":"venue"
},
  "geometry": {"coordinates":[13.30051,52.499519],"type":"Point"}
}