{
  "type": "Feature",
  "properties": {
    "iso:country":"DE",
    "sg:address":"Marienstr. 82",
    "sg:city":"Recklinghausen",
    "sg:phone":"+49 2361/652023",
    "sg:postcode":"45663",
    "sg:province":"Nordrhein-Westfalen",
    "wof:name":"Dieter B\u00f6nnighaus Tier- Und Gartenmarkt",
    "wof:placetype":"venue"
},
  "geometry": {"coordinates":[7.223573,51.57122],"type":"Point"}
}