{
  "type": "Feature",
  "properties": {
    "iso:country":"DE",
    "sg:address":"Lammweg 1",
    "sg:city":"Neusalza-Spremberg",
    "sg:phone":"+49 35872/38930",
    "sg:postcode":"02742",
    "sg:province":"Sachsen",
    "wof:name":"Werner W\u00fcnsche",
    "wof:placetype":"venue"
},
  "geometry": {"coordinates":[14.5382671356,51.039264679],"type":"Point"}
}