{
  "type": "Feature",
  "properties": {
    "iso:country":"DE",
    "sg:address":"Ludwig-Jahn-Str. 11",
    "sg:city":"Ostheim",
    "sg:phone":"+49 9777/9265",
    "sg:postcode":"97645",
    "sg:province":"Bayern",
    "wof:name":"Hugo Streck Brauerei Ek",
    "wof:placetype":"venue"
},
  "geometry": {"coordinates":[10.22015,50.45731],"type":"Point"}
}