{
  "type": "Feature",
  "properties": {
    "iso:country":"DE",
    "sg:address":"Ernst-Th\u00e4lmann-Platz 10",
    "sg:city":"D\u00f6llnitz",
    "sg:postcode":"06184",
    "sg:province":"Sachsen-Anhalt",
    "wof:name":"I. H. R. I. S. Bautr\u00e4ger Und Projektbetreuung Gmbh",
    "wof:placetype":"venue"
},
  "geometry": {"coordinates":[12.0270614624,51.4059486389],"type":"Point"}
}