{
  "type": "Feature",
  "properties": {
    "iso:country":"DE",
    "sg:address":"Siegesstr. 2",
    "sg:city":"Bornheim",
    "sg:phone":"+49 2222/3303",
    "sg:postcode":"53332",
    "sg:province":"Nordrhein-Westfalen",
    "wof:name":"Inge Hamich",
    "wof:placetype":"venue"
},
  "geometry": {"coordinates":[7.005161,50.752968],"type":"Point"}
}