{
  "type": "Feature",
  "properties": {
    "iso:country":"DE",
    "sg:address":"Eichenb\u00fchler Str. 19",
    "sg:city":"Miltenberg",
    "sg:phone":"+49 9371/99856",
    "sg:postcode":"63897",
    "sg:province":"Bayern",
    "wof:name":"Piet\u00e4t Kempf",
    "wof:placetype":"venue"
},
  "geometry": {"coordinates":[9.26557,49.704445],"type":"Point"}
}