{
  "type": "Feature",
  "properties": {
    "iso:country":"DE",
    "sg:address":"Kapellenstr. 39",
    "sg:city":"Aachen",
    "sg:phone":"+49 241/603241",
    "sg:postcode":"52066",
    "sg:province":"Nordrhein-Westfalen",
    "wof:name":"Imbi\u00df Ninas Grill",
    "wof:placetype":"venue"
},
  "geometry": {"coordinates":[6.0936422348,50.7606201172],"type":"Point"}
}