{
  "type": "Feature",
  "properties": {
    "iso:country":"DE",
    "sg:address":"Ahrhutstr. 2",
    "sg:city":"Bad Neuenahr-Ahrweiler",
    "sg:phone":"+49 2641/36129",
    "sg:postcode":"53474",
    "sg:province":"Rheinland-Pfalz",
    "wof:name":"Ahrtor-apotheke",
    "wof:placetype":"venue"
},
  "geometry": {"coordinates":[7.096823,50.540783],"type":"Point"}
}