{
  "type": "Feature",
  "properties": {
    "iso:country":"DE",
    "sg:address":"Steinweg 8",
    "sg:city":"Braunschweig",
    "sg:phone":"+49 531/125511",
    "sg:postcode":"38100",
    "sg:province":"Niedersachsen",
    "wof:name":"Fr\u00f6se Architekt",
    "wof:placetype":"venue"
},
  "geometry": {"coordinates":[10.527564,52.26553],"type":"Point"}
}