{
  "type": "Feature",
  "properties": {
    "iso:country":"DE",
    "sg:address":"Auer Str. 17",
    "sg:city":"Schneeberg",
    "sg:phone":"+49 3772/28269",
    "sg:postcode":"08289",
    "sg:province":"Sachsen",
    "wof:name":"Weickert",
    "wof:placetype":"venue"
},
  "geometry": {"coordinates":[12.644584,50.597958],"type":"Point"}
}