{
  "type": "Feature",
  "properties": {
    "iso:country":"DE",
    "sg:address":"Graf-Konrad-Str. 20",
    "sg:city":"M\u00fcnchen",
    "sg:phone":"+49 89/3508211",
    "sg:postcode":"80809",
    "sg:province":"Bayern",
    "wof:name":"Bierst\u00fcberl Marlies Kuhnert",
    "wof:placetype":"venue"
},
  "geometry": {"coordinates":[11.5642089844,48.1825065613],"type":"Point"}
}