{
  "type": "Feature",
  "properties": {
    "iso:country":"DE",
    "sg:address":"Schulstr. 20",
    "sg:city":"Gr\u00e4felfing",
    "sg:phone":"+49 89/851207",
    "sg:postcode":"82166",
    "sg:province":"Bayern",
    "wof:name":"Marianne Zorn Heilpraktikerin",
    "wof:placetype":"venue"
},
  "geometry": {"coordinates":[11.4363307953,48.1199455261],"type":"Point"}
}