{
  "type": "Feature",
  "properties": {
    "iso:country":"DE",
    "sg:address":"Am Himmelsweiher 35",
    "sg:city":"F\u00fcrth",
    "sg:phone":"+49 911/979830",
    "sg:postcode":"90768",
    "sg:province":"Bayern",
    "wof:name":"Karl Gs\u00e4nger Gmbh",
    "wof:placetype":"venue"
},
  "geometry": {"coordinates":[10.958723,49.46109],"type":"Point"}
}