{
  "type": "Feature",
  "properties": {
    "iso:country":"DE",
    "sg:address":"St.-Vitus-Str. 25a",
    "sg:city":"Brilon",
    "sg:phone":"+49 2963/1844",
    "sg:postcode":"59929",
    "sg:province":"Nordrhein-Westfalen",
    "wof:name":"Josef Lange Architekt",
    "wof:placetype":"venue"
},
  "geometry": {"coordinates":[8.656298,51.352158],"type":"Point"}
}