{
  "type": "Feature",
  "properties": {
    "iso:country":"DE",
    "sg:address":"Zum Kappelsberg 9a",
    "sg:city":"Salzkotten",
    "sg:phone":"+49 4929/5579444",
    "sg:postcode":"33154",
    "sg:province":"Nordrhein-Westfalen",
    "wof:name":"Inventive Medien Friedhelm Ahle",
    "wof:placetype":"venue"
},
  "geometry": {"coordinates":[8.6834354401,51.6329536438],"type":"Point"}
}