{
  "type": "Feature",
  "properties": {
    "iso:country":"DE",
    "sg:address":"Am Ginnheimer W\u00e4ldchen 3",
    "sg:city":"Frankfurt",
    "sg:phone":"+49 69/532005",
    "sg:postcode":"60431",
    "sg:province":"Hessen",
    "wof:name":"Redaktion Sportpost Post-sportverein",
    "wof:placetype":"venue"
},
  "geometry": {"coordinates":[8.6390266418,50.1410522461],"type":"Point"}
}