{
  "type": "Feature",
  "properties": {
    "iso:country":"DE",
    "sg:address":"B\u00f6ttcherstr. 8-10",
    "sg:city":"Bremen",
    "sg:phone":"+49 421/338820",
    "sg:postcode":"28195",
    "sg:province":"Bremen",
    "wof:name":"B\u00f6ttcherstra\u00dfe Gmbh",
    "wof:placetype":"venue"
},
  "geometry": {"coordinates":[8.8060903549,53.0750694275],"type":"Point"}
}