{
  "type": "Feature",
  "properties": {
    "iso:country":"DE",
    "sg:address":"K\u00f6lner Str. 6",
    "sg:city":"Euskirchen",
    "sg:phone":"+49 2251/71627",
    "sg:postcode":"53879",
    "sg:province":"Nordrhein-Westfalen",
    "wof:name":"Heike F\u00fcrst Gmbh",
    "wof:placetype":"venue"
},
  "geometry": {"coordinates":[6.791121006,50.6600761414],"type":"Point"}
}