{
  "type": "Feature",
  "properties": {
    "iso:country":"DE",
    "sg:address":"Sch\u00fctzenstr. 5",
    "sg:city":"Mengkofen",
    "sg:phone":"+49 8733/267",
    "sg:postcode":"84152",
    "sg:province":"Bayern",
    "wof:name":"Otto Schmideder",
    "wof:placetype":"venue"
},
  "geometry": {"coordinates":[12.4464321136,48.7223625183],"type":"Point"}
}