{
  "type": "Feature",
  "properties": {
    "iso:country":"DE",
    "sg:address":"Sylvesterallee 1",
    "sg:city":"Hamburg",
    "sg:phone":"+49 40/41550",
    "sg:postcode":"22525",
    "sg:province":"Hamburg",
    "wof:name":"Hsv Sport Ag",
    "wof:placetype":"venue"
},
  "geometry": {"coordinates":[9.903985,53.587521],"type":"Point"}
}