{
  "type": "Feature",
  "properties": {
    "iso:country":"DE",
    "sg:address":"Sonnenburger Str. 3b",
    "sg:city":"Bad Freienwalde",
    "sg:postcode":"16259",
    "sg:province":"Brandenburg",
    "wof:name":"Werkstatt F\u00fcr Behinderte Waldh\u00f6he",
    "wof:placetype":"venue"
},
  "geometry": {"coordinates":[14.031426,52.777702],"type":"Point"}
}