{
  "type": "Feature",
  "properties": {
    "iso:country":"DE",
    "sg:address":"Sch\u00f6nhauser Allee 173",
    "sg:city":"Berlin",
    "sg:phone":"+49 30/4491893",
    "sg:postcode":"10119",
    "sg:province":"Berlin",
    "wof:name":"Modeboutique Am Pfefferberg",
    "wof:placetype":"venue"
},
  "geometry": {"coordinates":[13.412187,52.532539],"type":"Point"}
}