{
  "type": "Feature",
  "properties": {
    "iso:country":"DE",
    "sg:address":"Wilhelmstr. 9",
    "sg:city":"Wiesbaden",
    "sg:phone":"+49 611/9102727",
    "sg:postcode":"65185",
    "sg:province":"Hessen",
    "wof:name":"Screen Team Beteiligungs- Gesellschaft Mbh & Co. Kg",
    "wof:placetype":"venue"
},
  "geometry": {"coordinates":[8.2452478409,50.0795974731],"type":"Point"}
}