{
  "type": "Feature",
  "properties": {
    "iso:country":"DE",
    "sg:address":"D\u00f6rrmorsbacher Str. 18",
    "sg:city":"Aschaffenburg",
    "sg:phone":"+49 6021/60763",
    "sg:postcode":"63743",
    "sg:province":"Bayern",
    "wof:name":"Michael Fay",
    "wof:placetype":"venue"
},
  "geometry": {"coordinates":[9.210398674,49.9449501038],"type":"Point"}
}