{
  "type": "Feature",
  "properties": {
    "iso:country":"DE",
    "sg:address":"Pleinfelder Str. 16",
    "sg:city":"Georgensgm\u00fcnd",
    "sg:phone":"+49 9172/7882",
    "sg:postcode":"91166",
    "sg:province":"Bayern",
    "wof:name":"Kosmetikst\u00fcbchen Sabine Pamer",
    "wof:placetype":"venue"
},
  "geometry": {"coordinates":[11.014168,49.183147],"type":"Point"}
}