{
  "type": "Feature",
  "properties": {
    "iso:country":"DE",
    "sg:address":"Max-Reger-Str. 21",
    "sg:city":"Weiden",
    "sg:phone":"+49 961/7706",
    "sg:postcode":"92637",
    "sg:province":"Bayern",
    "wof:name":"Master-optic Verwaltungs Gmbh",
    "wof:placetype":"venue"
},
  "geometry": {"coordinates":[12.1566734314,49.6739349365],"type":"Point"}
}