{
  "type": "Feature",
  "properties": {
    "iso:country":"DE",
    "sg:address":"August-Thyssen-Str. 51",
    "sg:city":"Essen",
    "sg:phone":"+49 2054/12040",
    "sg:postcode":"45219",
    "sg:province":"Nordrhein-Westfalen",
    "wof:name":"Schlo\u00df Hugenpoet",
    "wof:placetype":"venue"
},
  "geometry": {"coordinates":[6.9155302048,51.3618774414],"type":"Point"}
}