{
  "type": "Feature",
  "properties": {
    "iso:country":"DE",
    "sg:address":"Mainkurstr. 29",
    "sg:city":"Frankfurt",
    "sg:phone":"+49 69/4909709",
    "sg:postcode":"60385",
    "sg:province":"Hessen",
    "wof:name":"Klatsch",
    "wof:placetype":"venue"
},
  "geometry": {"coordinates":[8.709765,50.124218],"type":"Point"}
}