{
  "type": "Feature",
  "properties": {
    "iso:country":"DE",
    "sg:address":"Emsdettener Str. 72",
    "sg:city":"Neuenkirchen",
    "sg:phone":"+49 5973/2470",
    "sg:postcode":"48485",
    "sg:province":"Nordrhein-Westfalen",
    "wof:name":"Stilm\u00f6bel Nefe Gmbh",
    "wof:placetype":"venue"
},
  "geometry": {"coordinates":[7.37575,52.238564],"type":"Point"}
}