{
  "type": "Feature",
  "properties": {
    "iso:country":"DE",
    "sg:address":"Ebersdorf",
    "sg:city":"Ebersdorf",
    "sg:phone":"+49 4765/266",
    "sg:postcode":"27432",
    "sg:province":"Niedersachsen",
    "wof:name":"Volksbank Bremerv\u00f6rde Eg",
    "wof:placetype":"venue"
},
  "geometry": {"coordinates":[9.05305,53.525665],"type":"Point"}
}