{
  "type": "Feature",
  "properties": {
    "iso:country":"DE",
    "sg:address":"Heilbrunnen",
    "sg:city":"Brohl-L\u00fctzing",
    "sg:phone":"+49 2633/4230",
    "sg:postcode":"56656",
    "sg:province":"Rheinland-Pfalz",
    "wof:name":"Privatbrunnen T\u00f6nissteiner Sprudel Dr. C. Kerstiens Gmbh",
    "wof:placetype":"venue"
},
  "geometry": {"coordinates":[7.3100838661,50.4646873474],"type":"Point"}
}