{
  "type": "Feature",
  "properties": {
    "iso:country":"DE",
    "sg:address":"Marktplatz 12",
    "sg:city":"Philippsburg",
    "sg:phone":"+49 7256/1283",
    "sg:postcode":"76661",
    "sg:province":"Baden-W\u00fcrttemberg",
    "wof:name":"Gehrer",
    "wof:placetype":"venue"
},
  "geometry": {"coordinates":[8.4536304474,49.2366943359],"type":"Point"}
}