{
  "type": "Feature",
  "properties": {
    "iso:country":"DE",
    "sg:address":"Schlo\u00dfbergstr. 3",
    "sg:city":"Badenweiler",
    "sg:phone":"+49 7632/82180",
    "sg:postcode":"79410",
    "sg:province":"Baden-W\u00fcrttemberg",
    "wof:name":"Hotel Schlo\u00dfberg",
    "wof:placetype":"venue"
},
  "geometry": {"coordinates":[7.6683759689,47.8043022156],"type":"Point"}
}