{
  "type": "Feature",
  "properties": {
    "iso:country":"DE",
    "sg:address":"Lange Wand 26",
    "sg:city":"Bassum",
    "sg:phone":"+49 4241/2687",
    "sg:postcode":"27211",
    "sg:province":"Niedersachsen",
    "wof:name":"Erich Trenner",
    "wof:placetype":"venue"
},
  "geometry": {"coordinates":[8.7314014435,52.8490982056],"type":"Point"}
}