{
  "type": "Feature",
  "properties": {
    "iso:country":"DE",
    "sg:address":"Kirchplatz 8",
    "sg:city":"Freudenberg",
    "sg:phone":"+49 9627/282",
    "sg:postcode":"92272",
    "sg:province":"Bayern",
    "wof:name":"Kath. Pfarramt St. Martin",
    "wof:placetype":"venue"
},
  "geometry": {"coordinates":[11.9432458878,49.4410476685],"type":"Point"}
}