{
  "type": "Feature",
  "properties": {
    "iso:country":"DE",
    "sg:address":"Marktplatz 9",
    "sg:city":"Grafing",
    "sg:phone":"+49 8092/7603",
    "sg:postcode":"85567",
    "sg:province":"Bayern",
    "wof:name":"Mayer Mode Gmbh",
    "wof:placetype":"venue"
},
  "geometry": {"coordinates":[11.907346,48.020782],"type":"Point"}
}