{
  "type": "Feature",
  "properties": {
    "iso:country":"DE",
    "sg:address":"Ahornweg 39",
    "sg:city":"Bad Laer",
    "sg:phone":"+49 5424/9931",
    "sg:postcode":"49196",
    "sg:province":"Niedersachsen",
    "wof:name":"Hans-joachim Witt",
    "wof:placetype":"venue"
},
  "geometry": {"coordinates":[8.0914106369,52.1092643738],"type":"Point"}
}