{
  "type": "Feature",
  "properties": {
    "iso:country":"DE",
    "sg:address":"Banatstr. 21",
    "sg:city":"Esslingen",
    "sg:phone":"+49 711/311447",
    "sg:postcode":"73730",
    "sg:province":"Baden-W\u00fcrttemberg",
    "wof:name":"Hans Ruof",
    "wof:placetype":"venue"
},
  "geometry": {"coordinates":[9.33945,48.731476],"type":"Point"}
}