{
  "type": "Feature",
  "properties": {
    "iso:country":"DE",
    "sg:address":"Rheinstr. 97",
    "sg:city":"M\u00fclheim",
    "sg:postcode":"45478",
    "sg:province":"Nordrhein-Westfalen",
    "wof:name":"Metimex Metal Trading Und Services Gmbh",
    "wof:placetype":"venue"
},
  "geometry": {"coordinates":[6.848358,51.436539],"type":"Point"}
}