{
  "type": "Feature",
  "properties": {
    "iso:country":"DE",
    "sg:address":"Nachthutstr. 2a",
    "sg:city":"Haldensleben",
    "sg:phone":"+49 3904/71505",
    "sg:postcode":"39340",
    "sg:province":"Sachsen-Anhalt",
    "wof:name":"Friedrich Guderian",
    "wof:placetype":"venue"
},
  "geometry": {"coordinates":[11.4069786072,52.2863693237],"type":"Point"}
}