{
  "type": "Feature",
  "properties": {
    "iso:country":"DE",
    "sg:address":"Friedrich-Alfred-Str. 87",
    "sg:city":"Duisburg",
    "sg:phone":"+49 2065/313782",
    "sg:postcode":"47226",
    "sg:province":"Nordrhein-Westfalen",
    "wof:name":"Galerie Teufel-holze Gmbh",
    "wof:placetype":"venue"
},
  "geometry": {"coordinates":[6.717657,51.409119],"type":"Point"}
}