{
  "type": "Feature",
  "properties": {
    "iso:country":"DE",
    "sg:address":"Zur Alten Kolonie 12",
    "sg:city":"Holzwickede",
    "sg:phone":"+49 2301/941420",
    "sg:postcode":"59439",
    "sg:province":"Nordrhein-Westfalen",
    "wof:name":"Digi Communication Systeme Gmbh",
    "wof:placetype":"venue"
},
  "geometry": {"coordinates":[7.6208782196,51.5162658691],"type":"Point"}
}