{
  "type": "Feature",
  "properties": {
    "iso:country":"DE",
    "sg:address":"Hauptstr. 17",
    "sg:city":"Zweibr\u00fccken",
    "sg:phone":"+49 6332/18781",
    "sg:postcode":"66482",
    "sg:province":"Rheinland-Pfalz",
    "wof:name":"H. Ecker",
    "wof:placetype":"venue"
},
  "geometry": {"coordinates":[7.363495,49.247757],"type":"Point"}
}