{
  "type": "Feature",
  "properties": {
    "iso:country":"DE",
    "sg:address":"Nennsdorf 3",
    "sg:city":"Bucha",
    "sg:phone":"+49 3641/607478",
    "sg:postcode":"07751",
    "sg:province":"Th\u00fcringen",
    "wof:name":"I. B\u00e4rschneider",
    "wof:placetype":"venue"
},
  "geometry": {"coordinates":[11.5409469604,50.891204834],"type":"Point"}
}