{
  "type": "Feature",
  "properties": {
    "iso:country":"DE",
    "sg:address":"Fasanenweg 8",
    "sg:city":"Gerolsbach",
    "sg:phone":"+49 8250/588",
    "sg:postcode":"85302",
    "sg:province":"Bayern",
    "wof:name":"Georg Denz",
    "wof:placetype":"venue"
},
  "geometry": {"coordinates":[11.338596344,48.4563751221],"type":"Point"}
}