{
  "type": "Feature",
  "properties": {
    "iso:country":"DE",
    "sg:address":"Rheing\u00f6nheimer Str. 106",
    "sg:city":"Ludwigshafen",
    "sg:phone":"+49 621/571839",
    "sg:postcode":"67065",
    "sg:province":"Rheinland-Pfalz",
    "wof:name":"Eiscafe Taormina Asaro Giocamo",
    "wof:placetype":"venue"
},
  "geometry": {"coordinates":[8.428771,49.461811],"type":"Point"}
}