{
  "type": "Feature",
  "properties": {
    "iso:country":"DE",
    "sg:address":"Kirchstr. 6",
    "sg:city":"Stetten",
    "sg:phone":"+49 8269/1022",
    "sg:postcode":"87778",
    "sg:province":"Bayern",
    "wof:name":"Franz H\u00f6\u00df",
    "wof:placetype":"venue"
},
  "geometry": {"coordinates":[10.433306,48.005638],"type":"Point"}
}