{
  "type": "Feature",
  "properties": {
    "iso:country":"DE",
    "sg:address":"Richard-Sch\u00f6ne-Weg 9",
    "sg:city":"Wedemark",
    "sg:phone":"+49 5131/52476",
    "sg:postcode":"30900",
    "sg:province":"Niedersachsen",
    "wof:name":"Dr. Hermann Bader Tierarzt",
    "wof:placetype":"venue"
},
  "geometry": {"coordinates":[9.6267538071,52.5057640076],"type":"Point"}
}