{
  "type": "Feature",
  "properties": {
    "iso:country":"DE",
    "sg:address":"Im Gewerbegebiet 13",
    "sg:city":"Hohenm\u00f6lsen",
    "sg:phone":"+49 34441/20183",
    "sg:postcode":"06679",
    "sg:province":"Sachsen-Anhalt",
    "wof:name":"Pulverbeschichtung Busch Gmbh",
    "wof:placetype":"venue"
},
  "geometry": {"coordinates":[12.1196403503,51.1531715393],"type":"Point"}
}