{
  "type": "Feature",
  "properties": {
    "iso:country":"DE",
    "sg:address":"Gustav-Hoch-Str. 37",
    "sg:city":"Hanau",
    "sg:phone":"+49 6181/83929",
    "sg:postcode":"63452",
    "sg:province":"Hessen",
    "wof:name":"Listmann + Partner Ohg",
    "wof:placetype":"venue"
},
  "geometry": {"coordinates":[8.8981466293,50.1425247192],"type":"Point"}
}