{
  "type": "Feature",
  "properties": {
    "iso:country":"DE",
    "sg:address":"Friedrichstr. 13",
    "sg:city":"Furtwangen",
    "sg:phone":"+49 4977/236530",
    "sg:postcode":"78120",
    "sg:province":"Baden-W\u00fcrttemberg",
    "wof:name":"Bezirkssparkasse Furtwangen",
    "wof:placetype":"venue"
},
  "geometry": {"coordinates":[8.205085,48.053249],"type":"Point"}
}