{
  "type": "Feature",
  "properties": {
    "iso:country":"DE",
    "sg:address":"Bahnhofstr. 84",
    "sg:city":"Schifferstadt",
    "sg:phone":"+49 6235/1340",
    "sg:postcode":"67105",
    "sg:province":"Rheinland-Pfalz",
    "wof:name":"Vier Jahreszeiten",
    "wof:placetype":"venue"
},
  "geometry": {"coordinates":[8.3694171906,49.3904190063],"type":"Point"}
}