{
  "type": "Feature",
  "properties": {
    "iso:country":"DE",
    "sg:address":"Langenstr. 25",
    "sg:city":"Twistringen",
    "sg:phone":"+49 4243/4933",
    "sg:postcode":"27239",
    "sg:province":"Niedersachsen",
    "wof:name":"H. Rickers",
    "wof:placetype":"venue"
},
  "geometry": {"coordinates":[8.635091,52.800163],"type":"Point"}
}