{
  "type": "Feature",
  "properties": {
    "iso:country":"DE",
    "sg:address":"Estetalstr. 45-47",
    "sg:city":"Buxtehude",
    "sg:phone":"+49 4161/7280",
    "sg:postcode":"21614",
    "sg:province":"Niedersachsen",
    "wof:name":"K\u00f6ver Gmbh & Co. Kg",
    "wof:placetype":"venue"
},
  "geometry": {"coordinates":[9.6887178421,53.4619026184],"type":"Point"}
}