{
  "type": "Feature",
  "properties": {
    "iso:country":"DE",
    "sg:address":"Lange Reihe 72",
    "sg:city":"Krummesse",
    "sg:phone":"+49 4508/862",
    "sg:postcode":"23628",
    "sg:province":"Schleswig-Holstein",
    "wof:name":"W. Lembcke Ingenieur",
    "wof:placetype":"venue"
},
  "geometry": {"coordinates":[10.6418132782,53.7734489441],"type":"Point"}
}