{
  "type": "Feature",
  "properties": {
    "iso:country":"DE",
    "sg:address":"Eichendorffstr. 7",
    "sg:city":"Roth",
    "sg:phone":"+49 9171/1781",
    "sg:postcode":"91154",
    "sg:province":"Bayern",
    "wof:name":"Siegfried Kummerer",
    "wof:placetype":"venue"
},
  "geometry": {"coordinates":[11.103385,49.249138],"type":"Point"}
}