{
  "type": "Feature",
  "properties": {
    "iso:country":"DE",
    "sg:address":"Karl-Liebknecht-Str. 37",
    "sg:city":"Halle",
    "sg:phone":"+49 345/2021356",
    "sg:postcode":"06114",
    "sg:province":"Sachsen-Anhalt",
    "wof:name":"Luthe Ladenbau",
    "wof:placetype":"venue"
},
  "geometry": {"coordinates":[11.96501,51.49926],"type":"Point"}
}