{
  "type": "Feature",
  "properties": {
    "iso:country":"DE",
    "sg:address":"Porschestra\u00dfe 38",
    "sg:city":"Wolfsburg",
    "sg:phone":"+49 5361",
    "sg:postcode":"38440",
    "sg:province":"Niedersachsen",
    "wof:name":"Profly Luftbild-service Gmbh",
    "wof:placetype":"venue"
},
  "geometry": {"coordinates":[10.788178,52.424175],"type":"Point"}
}