{
  "type": "Feature",
  "properties": {
    "iso:country":"DE",
    "sg:address":"K\u00f6lner Str. 19-21",
    "sg:city":"Schleiden",
    "sg:phone":"+49 2444/2003",
    "sg:postcode":"53937",
    "sg:province":"Nordrhein-Westfalen",
    "wof:name":"Poensgen Scheibler Gmbh & Co.",
    "wof:placetype":"venue"
},
  "geometry": {"coordinates":[6.508275032,50.5704727173],"type":"Point"}
}