{
  "type": "Feature",
  "properties": {
    "iso:country":"DE",
    "sg:address":"Warschauer Str. 57",
    "sg:city":"Berlin",
    "sg:phone":"+49 30/2910685",
    "sg:postcode":"10243",
    "sg:province":"Berlin",
    "wof:name":"Uhrmachermeister Matthias Budtke Gmbh",
    "wof:placetype":"venue"
},
  "geometry": {"coordinates":[13.4515867233,52.5092887878],"type":"Point"}
}