{
  "type": "Feature",
  "properties": {
    "iso:country":"DE",
    "sg:address":"Am Bahnhof 9",
    "sg:city":"Kirrweiler",
    "sg:phone":"+49 6321/95700",
    "sg:postcode":"67489",
    "sg:province":"Rheinland-Pfalz",
    "wof:name":"D. Pfirrmann Immobilienmakler",
    "wof:placetype":"venue"
},
  "geometry": {"coordinates":[8.1469326019,49.305557251],"type":"Point"}
}