{
  "type": "Feature",
  "properties": {
    "iso:country":"DE",
    "sg:address":"Selchower Str. 32",
    "sg:city":"Berlin",
    "sg:phone":"+49 30/62840903",
    "sg:postcode":"12049",
    "sg:province":"Berlin",
    "wof:name":"Horst Grundmann Und B. Und C. Steudel Gbr",
    "wof:placetype":"venue"
},
  "geometry": {"coordinates":[13.424423,52.478928],"type":"Point"}
}