{
  "type": "Feature",
  "properties": {
    "iso:country":"DE",
    "sg:address":"Adam-R\u00fcckert-Str. 21",
    "sg:city":"Ober-Ramstadt",
    "sg:phone":"+49 6154/630070",
    "sg:postcode":"64372",
    "sg:province":"Hessen",
    "wof:name":"G. Gr\u00e4ser Gmbh",
    "wof:placetype":"venue"
},
  "geometry": {"coordinates":[8.7395267487,49.8299827576],"type":"Point"}
}