{
  "type": "Feature",
  "properties": {
    "iso:country":"DE",
    "sg:address":"Franz-Habich-Str. 1",
    "sg:city":"Borkum",
    "sg:phone":"+49 4922/4701",
    "sg:postcode":"26757",
    "sg:province":"Niedersachsen",
    "wof:name":"Kirsten Tebbens",
    "wof:placetype":"venue"
},
  "geometry": {"coordinates":[6.66378,53.586182],"type":"Point"}
}