{
  "type": "Feature",
  "properties": {
    "iso:country":"DE",
    "sg:address":"G\u00f6ttelmannstr. 17",
    "sg:city":"Mainz",
    "sg:phone":"+49 6131/982420",
    "sg:postcode":"55130",
    "sg:province":"Rheinland-Pfalz",
    "wof:name":"Bauer Und Schnatterer Notare",
    "wof:placetype":"venue"
},
  "geometry": {"coordinates":[8.291975975,49.9840011597],"type":"Point"}
}