{
  "type": "Feature",
  "properties": {
    "iso:country":"DE",
    "sg:address":"H\u00fcttengasse 53",
    "sg:city":"Heiligkreuzsteinach",
    "sg:postcode":"69253",
    "sg:province":"Baden-W\u00fcrttemberg",
    "wof:name":"Contronic Datenanzeige- Systeme Gmbh",
    "wof:placetype":"venue"
},
  "geometry": {"coordinates":[8.790705,49.478275],"type":"Point"}
}