{
  "type": "Feature",
  "properties": {
    "iso:country":"DE",
    "sg:address":"Odersh\u00e4user Str. 41",
    "sg:city":"Bad Wildungen",
    "sg:phone":"+49 5621/962003",
    "sg:postcode":"34537",
    "sg:province":"Hessen",
    "wof:name":"Huta Hotel-gastst\u00e4tten- Und Unterhaltungsbetriebe Gmbh",
    "wof:placetype":"venue"
},
  "geometry": {"coordinates":[9.1190357208,51.1115150452],"type":"Point"}
}