{
  "type": "Feature",
  "properties": {
    "iso:country":"DE",
    "sg:address":"B\u00f6hlaustr. 1",
    "sg:city":"M\u00fcnchen",
    "sg:phone":"+49 89/8117137",
    "sg:postcode":"81247",
    "sg:province":"Bayern",
    "wof:name":"J\u00fcrgen Bogun",
    "wof:placetype":"venue"
},
  "geometry": {"coordinates":[11.4688901901,48.1716880798],"type":"Point"}
}