{
  "type": "Feature",
  "properties": {
    "iso:country":"DE",
    "sg:address":"Rathaustorstr. 13",
    "sg:city":"Bockenau",
    "sg:phone":"+49 6758/6517",
    "sg:postcode":"55595",
    "sg:province":"Rheinland-Pfalz",
    "wof:name":"Oskar Und Klaus Schwarz",
    "wof:placetype":"venue"
},
  "geometry": {"coordinates":[7.680879,49.835255],"type":"Point"}
}