{
  "type": "Feature",
  "properties": {
    "iso:country":"DE",
    "sg:address":"Am Wasen 11",
    "sg:city":"R\u00f6llbach",
    "sg:phone":"+49 9372/3184",
    "sg:postcode":"63934",
    "sg:province":"Bayern",
    "wof:name":"Rosa-maria Buhleier",
    "wof:placetype":"venue"
},
  "geometry": {"coordinates":[9.2510251999,49.7695426941],"type":"Point"}
}