{
  "type": "Feature",
  "properties": {
    "iso:country":"DE",
    "sg:address":"Gartenstr. 55",
    "sg:city":"Wilnsdorf",
    "sg:phone":"+49 271/3937391",
    "sg:postcode":"57234",
    "sg:province":"Nordrhein-Westfalen",
    "wof:name":"Erich Schneider",
    "wof:placetype":"venue"
},
  "geometry": {"coordinates":[8.0821323395,50.8555412292],"type":"Point"}
}