{
  "type": "Feature",
  "properties": {
    "iso:country":"DE",
    "sg:address":"Fasanenweg 5",
    "sg:city":"Leutkirch",
    "sg:phone":"+49 7561/6055",
    "sg:postcode":"88299",
    "sg:province":"Baden-W\u00fcrttemberg",
    "wof:name":"E. Zimmermann",
    "wof:placetype":"venue"
},
  "geometry": {"coordinates":[10.0372810364,47.8307762146],"type":"Point"}
}