{
  "type": "Feature",
  "properties": {
    "iso:country":"DE",
    "sg:address":"Netzeweg 40",
    "sg:city":"Bielefeld",
    "sg:phone":"+49 5205/91280",
    "sg:postcode":"33689",
    "sg:province":"Nordrhein-Westfalen",
    "wof:name":"Wissmann Bestattungen",
    "wof:placetype":"venue"
},
  "geometry": {"coordinates":[8.590055,51.946388],"type":"Point"}
}