{
  "type": "Feature",
  "properties": {
    "iso:country":"DE",
    "sg:address":"Am Johannisberg 10",
    "sg:city":"Oelsnitz",
    "sg:phone":"+49 37421/5610",
    "sg:postcode":"08606",
    "sg:province":"Sachsen",
    "wof:name":"J. K. Effektzwirnerei Gmbh",
    "wof:placetype":"venue"
},
  "geometry": {"coordinates":[12.182471,50.427479],"type":"Point"}
}