{
  "type": "Feature",
  "properties": {
    "iso:country":"DE",
    "sg:address":"Hirtenberg 20",
    "sg:city":"Lebach",
    "sg:phone":"+49 6881/897179",
    "sg:postcode":"66822",
    "sg:province":"Saarland",
    "wof:name":"J. Schmidt",
    "wof:placetype":"venue"
},
  "geometry": {"coordinates":[6.9546990395,49.4310684204],"type":"Point"}
}