{
  "type": "Feature",
  "properties": {
    "iso:country":"DE",
    "sg:address":"Prenzlauer Chaussee 173",
    "sg:city":"Wandlitz",
    "sg:phone":"+49 33397/21327",
    "sg:postcode":"16348",
    "sg:province":"Brandenburg",
    "wof:name":"Bahnhof-drogerie Inh. Ursula Rotermund",
    "wof:placetype":"venue"
},
  "geometry": {"coordinates":[13.473235,52.757217],"type":"Point"}
}