{
  "type": "Feature",
  "properties": {
    "iso:country":"DE",
    "sg:address":"Leopoldstr. 1",
    "sg:city":"St. Georgen",
    "sg:postcode":"78112",
    "sg:province":"Baden-W\u00fcrttemberg",
    "wof:name":"Ringwald Gmbh",
    "wof:placetype":"venue"
},
  "geometry": {"coordinates":[8.33772,48.12302],"type":"Point"}
}