{
  "type": "Feature",
  "properties": {
    "iso:country":"DE",
    "sg:address":"Biberkopfstr. 2",
    "sg:city":"Mindelheim",
    "sg:phone":"+49 8261/3502",
    "sg:postcode":"87719",
    "sg:province":"Bayern",
    "wof:name":"Bernd O. Dort",
    "wof:placetype":"venue"
},
  "geometry": {"coordinates":[10.5046520233,48.0377197266],"type":"Point"}
}