{
  "type": "Feature",
  "properties": {
    "iso:country":"DE",
    "sg:address":"Tulpenstr. 16",
    "sg:city":"Sprendlingen",
    "sg:phone":"+49 6701/2767",
    "sg:postcode":"55576",
    "sg:province":"Rheinland-Pfalz",
    "wof:name":"Peter Scherer Innenarchitekt",
    "wof:placetype":"venue"
},
  "geometry": {"coordinates":[7.9927120209,49.8590316772],"type":"Point"}
}