{
  "type": "Feature",
  "properties": {
    "iso:country":"DE",
    "sg:address":"Calmbacher Str. 46",
    "sg:city":"B\u00f6blingen",
    "sg:phone":"+49 7031/72800",
    "sg:postcode":"71034",
    "sg:province":"Baden-W\u00fcrttemberg",
    "wof:name":"Renate K\u00fcchler Steuerberaterin",
    "wof:placetype":"venue"
},
  "geometry": {"coordinates":[8.995677948,48.6700172424],"type":"Point"}
}