{
  "type": "Feature",
  "properties": {
    "iso:country":"DE",
    "sg:address":"Friedericistr. 8",
    "sg:city":"Gera",
    "sg:phone":"+49 365/823230",
    "sg:postcode":"07545",
    "sg:province":"Th\u00fcringen",
    "wof:name":"Ke Karl-h. Engelhardt Kg",
    "wof:placetype":"venue"
},
  "geometry": {"coordinates":[12.074179,50.877583],"type":"Point"}
}