{
  "type": "Feature",
  "properties": {
    "iso:country":"DE",
    "sg:address":"Flurstr. 2",
    "sg:city":"Schnelldorf",
    "sg:phone":"+49 7950/98110",
    "sg:postcode":"91625",
    "sg:province":"Bayern",
    "wof:name":"Bayer Gmbh",
    "wof:placetype":"venue"
},
  "geometry": {"coordinates":[10.175401,49.196915],"type":"Point"}
}