{
  "type": "Feature",
  "properties": {
    "iso:country":"DE",
    "sg:address":"Von-Bronsart-Str. 14",
    "sg:city":"Barsb\u00fcttel",
    "sg:phone":"+49 40/6708840",
    "sg:postcode":"22885",
    "sg:province":"Schleswig-Holstein",
    "wof:name":"Beteiligungsgesellschaft Bluhm & Plate & Co. Kg",
    "wof:placetype":"venue"
},
  "geometry": {"coordinates":[10.188384,53.572197],"type":"Point"}
}