{
  "type": "Feature",
  "properties": {
    "iso:country":"DE",
    "sg:address":"Leuzhof 1",
    "sg:city":"Insingen",
    "sg:postcode":"91610",
    "sg:province":"Bayern",
    "wof:name":"Hermann Walter Gmbh",
    "wof:placetype":"venue"
},
  "geometry": {"coordinates":[10.1713848114,49.3494682312],"type":"Point"}
}