{
  "type": "Feature",
  "properties": {
    "iso:country":"DE",
    "sg:address":"Blumenstr. 11",
    "sg:city":"Lich",
    "sg:phone":"+49 4964/047433",
    "sg:postcode":"35423",
    "sg:province":"Hessen",
    "wof:name":"Rainer Bausch Gmbh",
    "wof:placetype":"venue"
},
  "geometry": {"coordinates":[8.8578805923,50.4890136719],"type":"Point"}
}