{
  "type": "Feature",
  "properties": {
    "iso:country":"DE",
    "sg:address":"Burgstr. 32",
    "sg:city":"Ahaus",
    "sg:phone":"+49 2561/8587",
    "sg:postcode":"48683",
    "sg:province":"Nordrhein-Westfalen",
    "wof:name":"Heiner Dechering Gmbh",
    "wof:placetype":"venue"
},
  "geometry": {"coordinates":[6.9175667763,52.0769500732],"type":"Point"}
}