{
  "type": "Feature",
  "properties": {
    "iso:country":"DE",
    "sg:address":"Gilgaustr. 49",
    "sg:city":"K\u00f6ln",
    "sg:phone":"+49 2203/15074",
    "sg:postcode":"51149",
    "sg:province":"Nordrhein-Westfalen",
    "wof:name":"Wilhelm Bauer",
    "wof:placetype":"venue"
},
  "geometry": {"coordinates":[7.030622,50.899323],"type":"Point"}
}