{
  "type": "Feature",
  "properties": {
    "iso:country":"DE",
    "sg:address":"Zwickauer Str. 208",
    "sg:city":"Chemnitz",
    "sg:phone":"+49 371/91230",
    "sg:postcode":"09116",
    "sg:province":"Sachsen",
    "wof:name":"Texprojekt Industrieanlagen Gmbh",
    "wof:placetype":"venue"
},
  "geometry": {"coordinates":[12.882424,50.820984],"type":"Point"}
}