{
  "type": "Feature",
  "properties": {
    "iso:country":"DE",
    "sg:address":"Nordwall 18",
    "sg:city":"Straelen",
    "sg:phone":"+49 2834/8011",
    "sg:postcode":"47638",
    "sg:province":"Nordrhein-Westfalen",
    "wof:name":"Murmann Und Schmitz Rechtsanw\u00e4lte",
    "wof:placetype":"venue"
},
  "geometry": {"coordinates":[6.265750885,51.4455795288],"type":"Point"}
}