{
  "type": "Feature",
  "properties": {
    "iso:country":"DE",
    "sg:address":"Tacitusweg 37",
    "sg:city":"Krefeld",
    "sg:phone":"+49 2151/570818",
    "sg:postcode":"47809",
    "sg:province":"Nordrhein-Westfalen",
    "wof:name":"Hartmut Fabianke Ingenieur",
    "wof:placetype":"venue"
},
  "geometry": {"coordinates":[6.6732931137,51.3327026367],"type":"Point"}
}