{
  "type": "Feature",
  "properties": {
    "iso:country":"DE",
    "sg:address":"Feldstr. 38",
    "sg:city":"Gro\u00df Quenstedt",
    "sg:phone":"+49 39424/5825",
    "sg:postcode":"38822",
    "sg:province":"Sachsen-Anhalt",
    "wof:name":"Siegfried Harig",
    "wof:placetype":"venue"
},
  "geometry": {"coordinates":[11.1117954254,51.9293823242],"type":"Point"}
}