{
  "type": "Feature",
  "properties": {
    "iso:country":"DE",
    "sg:address":"Reisstr. 79",
    "sg:city":"Dresden",
    "sg:phone":"+49 351/2038891",
    "sg:postcode":"01257",
    "sg:province":"Sachsen",
    "wof:name":"Wolf-j\u00fcrgen Freund Ingenieur",
    "wof:placetype":"venue"
},
  "geometry": {"coordinates":[13.8188371658,50.9991149902],"type":"Point"}
}