{
  "type": "Feature",
  "properties": {
    "iso:country":"DE",
    "sg:address":"Clayallee 335",
    "sg:city":"Berlin",
    "sg:phone":"+49 30/3928021",
    "sg:postcode":"14169",
    "sg:province":"Berlin",
    "wof:name":"Rainer Kurzan Rechtsanwalt",
    "wof:placetype":"venue"
},
  "geometry": {"coordinates":[13.2614440918,52.4373664856],"type":"Point"}
}