{
  "type": "Feature",
  "properties": {
    "iso:country":"DE",
    "sg:address":"Str d Jugend 2",
    "sg:city":"Eldena",
    "sg:phone":"+49 38755/240",
    "sg:postcode":"19294",
    "sg:province":"Mecklenburg-Vorpommern",
    "wof:name":"Kreissparkasse Ludwigslust",
    "wof:placetype":"venue"
},
  "geometry": {"coordinates":[11.423456,53.229549],"type":"Point"}
}