{
  "type": "Feature",
  "properties": {
    "iso:country":"DE",
    "sg:address":"M\u00fchlgasse 17",
    "sg:city":"Naumburg",
    "sg:phone":"+49 3445/201536",
    "sg:postcode":"06618",
    "sg:province":"Sachsen-Anhalt",
    "wof:name":"Sanit\u00e4tshaus In Der M\u00fchlgasse",
    "wof:placetype":"venue"
},
  "geometry": {"coordinates":[11.8092126846,51.1538696289],"type":"Point"}
}