{
  "type": "Feature",
  "properties": {
    "iso:country":"DE",
    "sg:address":"Am Wiesenrain 15",
    "sg:city":"Frankfurt",
    "sg:phone":"+49 69/94414949",
    "sg:postcode":"60431",
    "sg:province":"Hessen",
    "wof:name":"Solar Innovation",
    "wof:placetype":"venue"
},
  "geometry": {"coordinates":[8.6475362778,50.1430015564],"type":"Point"}
}