{
  "type": "Feature",
  "properties": {
    "iso:country":"DE",
    "sg:address":"Marienburger Str. 19",
    "sg:city":"K\u00f6ln",
    "sg:postcode":"50968",
    "sg:province":"Nordrhein-Westfalen",
    "wof:name":"Otto Wolff Drei Gmbh",
    "wof:placetype":"venue"
},
  "geometry": {"coordinates":[6.9760727882,50.9013938904],"type":"Point"}
}