{
  "type": "Feature",
  "properties": {
    "iso:country":"DE",
    "sg:address":"Tiergartenstr. 53",
    "sg:city":"B\u00f6blingen",
    "sg:phone":"+49 7031/278241",
    "sg:postcode":"71032",
    "sg:province":"Baden-W\u00fcrttemberg",
    "wof:name":"Adelheid Mommer Rechtsanw\u00e4ltin",
    "wof:placetype":"venue"
},
  "geometry": {"coordinates":[9.0186538696,48.6722679138],"type":"Point"}
}