{
  "type": "Feature",
  "properties": {
    "iso:country":"DE",
    "sg:address":"Abst\u00e4berhof 9",
    "sg:city":"Kirkel",
    "sg:phone":"+49 6849/779",
    "sg:postcode":"66459",
    "sg:province":"Saarland",
    "wof:name":"Achilles Grill",
    "wof:placetype":"venue"
},
  "geometry": {"coordinates":[7.2474279404,49.2950935364],"type":"Point"}
}