{
  "type": "Feature",
  "properties": {
    "iso:country":"DE",
    "sg:address":"Nachtigallenweg 9",
    "sg:city":"Wiesbaden",
    "sg:phone":"+49 6127/968004",
    "sg:postcode":"65207",
    "sg:province":"Hessen",
    "wof:name":"Venturis Gesellschaft F\u00fcr Internationales",
    "wof:placetype":"venue"
},
  "geometry": {"coordinates":[8.301198,50.132652],"type":"Point"}
}