{
  "type": "Feature",
  "properties": {
    "iso:country":"DE",
    "sg:address":"Hauptstr. 58",
    "sg:city":"Weinheim",
    "sg:phone":"+49 6201/62847",
    "sg:postcode":"69469",
    "sg:province":"Baden-W\u00fcrttemberg",
    "wof:name":"Stadt-apotheke Beatrix Kn\u00fcttel E. Kfr.",
    "wof:placetype":"venue"
},
  "geometry": {"coordinates":[8.672363,49.551193],"type":"Point"}
}