{
  "type": "Feature",
  "properties": {
    "iso:country":"DE",
    "sg:address":"Im Hohlen Seifen 19",
    "sg:city":"Winterberg",
    "sg:postcode":"59955",
    "sg:province":"Nordrhein-Westfalen",
    "wof:name":"Evelin Brieden Verwaltungs- Gmbh",
    "wof:placetype":"venue"
},
  "geometry": {"coordinates":[8.527795,51.195324],"type":"Point"}
}