{
  "type": "Feature",
  "properties": {
    "iso:country":"DE",
    "sg:address":"Danziger Str. 9",
    "sg:city":"Neustadt",
    "sg:phone":"+49 5032/2181",
    "sg:postcode":"31535",
    "sg:province":"Niedersachsen",
    "wof:name":"Dr. Frithjof Kuhse",
    "wof:placetype":"venue"
},
  "geometry": {"coordinates":[9.4529438019,52.5035934448],"type":"Point"}
}