{
  "type": "Feature",
  "properties": {
    "iso:country":"DE",
    "sg:address":"Dorfstr. 31",
    "sg:city":"Premsendorf",
    "sg:phone":"+49 35389/81027",
    "sg:postcode":"06926",
    "sg:province":"Sachsen-Anhalt",
    "wof:name":"Gim Glasbau Gmbh",
    "wof:placetype":"venue"
},
  "geometry": {"coordinates":[13.0843753815,51.8040161133],"type":"Point"}
}