{
  "type": "Feature",
  "properties": {
    "iso:country":"DE",
    "sg:address":"Primsstr. 43",
    "sg:city":"Saarlouis",
    "sg:phone":"+49 6831/460095",
    "sg:postcode":"66740",
    "sg:province":"Saarland",
    "wof:name":"Elcon Werbe- Und Marketing Gmbh",
    "wof:placetype":"venue"
},
  "geometry": {"coordinates":[6.735309124,49.3204689026],"type":"Point"}
}