{
  "type": "Feature",
  "properties": {
    "iso:country":"DE",
    "sg:address":"Geistenstr. 27",
    "sg:city":"D\u00fcsseldorf",
    "sg:phone":"+49 211/444965",
    "sg:postcode":"40476",
    "sg:province":"Nordrhein-Westfalen",
    "wof:name":"Behmer & Wirtz",
    "wof:placetype":"venue"
},
  "geometry": {"coordinates":[6.787693,51.246895],"type":"Point"}
}