{
  "type": "Feature",
  "properties": {
    "iso:country":"DE",
    "sg:address":"Pleurtuitstr. 12-14",
    "sg:city":"Ransbach-Baumbach",
    "sg:phone":"+49 2623/4615",
    "sg:postcode":"56235",
    "sg:province":"Rheinland-Pfalz",
    "wof:name":"Hark Gmbh & Co. Kg",
    "wof:placetype":"venue"
},
  "geometry": {"coordinates":[7.7220201492,50.4636611938],"type":"Point"}
}