{
  "type": "Feature",
  "properties": {
    "iso:country":"DE",
    "sg:address":"Dorfstr. 17",
    "sg:city":"Kirchentellinsfurt",
    "sg:phone":"+49 7121/601663",
    "sg:postcode":"72138",
    "sg:province":"Baden-W\u00fcrttemberg",
    "wof:name":"Anton Biggel",
    "wof:placetype":"venue"
},
  "geometry": {"coordinates":[9.147561,48.532715],"type":"Point"}
}