{
  "type": "Feature",
  "properties": {
    "iso:country":"DE",
    "sg:address":"Rathausstr. 37",
    "sg:city":"Stolberg",
    "sg:phone":"+49 2402/91021",
    "sg:postcode":"52222",
    "sg:province":"Nordrhein-Westfalen",
    "wof:name":"Colorfoto Wolters",
    "wof:placetype":"venue"
},
  "geometry": {"coordinates":[6.2275538445,50.771282196],"type":"Point"}
}