{
  "type": "Feature",
  "properties": {
    "iso:country":"DE",
    "sg:address":"Ueddinger Str. 167",
    "sg:city":"M\u00f6nchengladbach",
    "sg:phone":"+49 4921/6160006",
    "sg:postcode":"41066",
    "sg:province":"Nordrhein-Westfalen",
    "wof:name":"Hps - Antriebstechnische Elemente Volker Heymanns",
    "wof:placetype":"venue"
},
  "geometry": {"coordinates":[6.482545,51.214825],"type":"Point"}
}