{
  "type": "Feature",
  "properties": {
    "iso:country":"DE",
    "sg:address":"Auerbachs Hof 8",
    "sg:city":"Markkleeberg",
    "sg:postcode":"04416",
    "sg:province":"Sachsen",
    "wof:name":"Softmark",
    "wof:placetype":"venue"
},
  "geometry": {"coordinates":[12.355615,51.279266],"type":"Point"}
}