{
  "type": "Feature",
  "properties": {
    "iso:country":"DE",
    "sg:address":"Marktplatz 16",
    "sg:city":"Bad Neustadt",
    "sg:phone":"+49 9771/61240",
    "sg:postcode":"97616",
    "sg:province":"Bayern",
    "wof:name":"G\u00fcnter Pfennig Und Walter Wiener",
    "wof:placetype":"venue"
},
  "geometry": {"coordinates":[10.2159452438,50.323097229],"type":"Point"}
}