{
  "type": "Feature",
  "properties": {
    "iso:country":"DE",
    "sg:address":"Hohe Str. 30",
    "sg:city":"Gr\u00e4fenhain",
    "sg:phone":"+49 3624/311696",
    "sg:postcode":"99887",
    "sg:province":"Th\u00fcringen",
    "wof:name":"Mario Und Corinne Keil",
    "wof:placetype":"venue"
},
  "geometry": {"coordinates":[10.695486,50.816044],"type":"Point"}
}