{
  "type": "Feature",
  "properties": {
    "iso:country":"DE",
    "sg:address":"Turmstr. 15",
    "sg:city":"Osterburken",
    "sg:phone":"+49 6291/8121",
    "sg:postcode":"74706",
    "sg:province":"Baden-W\u00fcrttemberg",
    "wof:name":"M. R\u00fcdinger",
    "wof:placetype":"venue"
},
  "geometry": {"coordinates":[9.4271383286,49.4312477112],"type":"Point"}
}