{
  "type": "Feature",
  "properties": {
    "iso:country":"DE",
    "sg:address":"Eschberger Weg 4",
    "sg:city":"Saarbr\u00fccken",
    "sg:postcode":"66121",
    "sg:province":"Saarland",
    "wof:name":"Heider & Schmitt Teldi Gmbh",
    "wof:placetype":"venue"
},
  "geometry": {"coordinates":[7.02451,49.226822],"type":"Point"}
}