{
  "type": "Feature",
  "properties": {
    "iso:country":"DE",
    "sg:address":"Geschwister-Scholl-Str 38",
    "sg:city":"Potsdam",
    "sg:phone":"+49 331/979180",
    "sg:postcode":"14471",
    "sg:province":"Brandenburg",
    "wof:name":"Letsmobile.de Gmbh",
    "wof:placetype":"venue"
},
  "geometry": {"coordinates":[13.0173902512,52.3940582275],"type":"Point"}
}