{
  "type": "Feature",
  "properties": {
    "iso:country":"DE",
    "sg:address":"Sackstr. 4",
    "sg:city":"Adelebsen",
    "sg:phone":"+49 5506/462",
    "sg:postcode":"37139",
    "sg:province":"Niedersachsen",
    "wof:name":"Tanzschule Rausch",
    "wof:placetype":"venue"
},
  "geometry": {"coordinates":[9.7731170654,51.54920578],"type":"Point"}
}