{
  "type": "Feature",
  "properties": {
    "iso:country":"DE",
    "sg:address":"Traubenstr. 10",
    "sg:city":"Apen",
    "sg:phone":"+49 4489/5935",
    "sg:postcode":"26689",
    "sg:province":"Niedersachsen",
    "wof:name":"Werbeverein Apen Karl Lamken",
    "wof:placetype":"venue"
},
  "geometry": {"coordinates":[7.8118200302,53.1987380981],"type":"Point"}
}