{
  "type": "Feature",
  "properties": {
    "iso:country":"DE",
    "sg:address":"Boverter Kirchweg 8",
    "sg:city":"Meerbusch",
    "sg:postcode":"40670",
    "sg:province":"Nordrhein-Westfalen",
    "wof:name":"Ralf Dollase Kg",
    "wof:placetype":"venue"
},
  "geometry": {"coordinates":[6.638698101,51.2659950256],"type":"Point"}
}