{
  "type": "Feature",
  "properties": {
    "iso:country":"DE",
    "sg:address":"Liebenauer Weg 10",
    "sg:city":"Asendorf",
    "sg:phone":"+49 4253/1274",
    "sg:postcode":"27330",
    "sg:province":"Niedersachsen",
    "wof:name":"Johann Hocke",
    "wof:placetype":"venue"
},
  "geometry": {"coordinates":[9.027852,52.731194],"type":"Point"}
}