{
  "type": "Feature",
  "properties": {
    "iso:country":"DE",
    "sg:address":"Am Pl\u00e4rrer 35",
    "sg:city":"N\u00fcrnberg",
    "sg:phone":"+49 911/929204",
    "sg:postcode":"90443",
    "sg:province":"Bayern",
    "wof:name":"Helmsauer & Preuss Gmbh",
    "wof:placetype":"venue"
},
  "geometry": {"coordinates":[11.0635509491,49.448009491],"type":"Point"}
}