{
  "type": "Feature",
  "properties": {
    "iso:country":"DE",
    "sg:address":"M\u00fchlenbach 8-10",
    "sg:city":"K\u00f6ln",
    "sg:phone":"+49 221/234374",
    "sg:postcode":"50676",
    "sg:province":"Nordrhein-Westfalen",
    "wof:name":"Vvs Video Verleih Service Gmbh",
    "wof:placetype":"venue"
},
  "geometry": {"coordinates":[6.9571537971,50.9329452515],"type":"Point"}
}