{
  "type": "Feature",
  "properties": {
    "iso:country":"DE",
    "sg:address":"Braunschweiger Str. 17 a",
    "sg:city":"Laatzen",
    "sg:phone":"+49 5102/2347",
    "sg:postcode":"30880",
    "sg:province":"Niedersachsen",
    "wof:name":"Urich Nehl Gartenbau",
    "wof:placetype":"venue"
},
  "geometry": {"coordinates":[9.829411,52.284763],"type":"Point"}
}