{
  "type": "Feature",
  "properties": {
    "iso:country":"DE",
    "sg:address":"Weckbacher Str. 12",
    "sg:city":"Weilbach",
    "sg:phone":"+49 9373/8008",
    "sg:postcode":"63937",
    "sg:province":"Bayern",
    "wof:name":"Deuchert Fleisch- Und Wurstwaren Gmbh & Co. Kg",
    "wof:placetype":"venue"
},
  "geometry": {"coordinates":[9.2043628693,49.66929245],"type":"Point"}
}