{
  "type": "Feature",
  "properties": {
    "iso:country":"DE",
    "sg:address":"Ortsstr. 32",
    "sg:city":"Langenorla",
    "sg:phone":"+49 3647/417690",
    "sg:postcode":"07381",
    "sg:province":"Th\u00fcringen",
    "wof:name":"Gr\u00fcner Wald",
    "wof:placetype":"venue"
},
  "geometry": {"coordinates":[11.5794744492,50.7394828796],"type":"Point"}
}