{
  "type": "Feature",
  "properties": {
    "iso:country":"DE",
    "sg:address":"Oberdresselhof 20",
    "sg:city":"Weissach",
    "sg:phone":"+49 7191/57529",
    "sg:postcode":"71554",
    "sg:province":"Baden-W\u00fcrttemberg",
    "wof:name":"Biohof Michael Steinat",
    "wof:placetype":"venue"
},
  "geometry": {"coordinates":[9.478571,48.941277],"type":"Point"}
}