{
  "type": "Feature",
  "properties": {
    "iso:country":"DE",
    "sg:address":"D\u00fcppelstr. 34",
    "sg:city":"Berlin",
    "sg:phone":"+49 30/7914544",
    "sg:postcode":"12163",
    "sg:province":"Berlin",
    "wof:name":"Gardinen Atelier Schameitis",
    "wof:placetype":"venue"
},
  "geometry": {"coordinates":[13.3242645264,52.4580192566],"type":"Point"}
}