{
  "type": "Feature",
  "properties": {
    "iso:country":"DE",
    "sg:address":"Wielandstr. 6",
    "sg:city":"Berlin",
    "sg:phone":"+49 30/3129929",
    "sg:postcode":"10625",
    "sg:province":"Berlin",
    "wof:name":"El Borriquito Spanisches Speiserestaurant",
    "wof:placetype":"venue"
},
  "geometry": {"coordinates":[13.3155622482,52.5059432983],"type":"Point"}
}