{
  "type": "Feature",
  "properties": {
    "iso:country":"DE",
    "sg:address":"Hannoversche Neustadt 27 b",
    "sg:city":"Burgdorf",
    "sg:phone":"+49 5136/85777",
    "sg:postcode":"31303",
    "sg:province":"Niedersachsen",
    "wof:name":"Rosis Blumen-boutique",
    "wof:placetype":"venue"
},
  "geometry": {"coordinates":[10.011045,52.448429],"type":"Point"}
}