{
  "type": "Feature",
  "properties": {
    "iso:country":"DE",
    "sg:address":"Pfarrg\u00e4\u00dfle 9",
    "sg:city":"Calw",
    "sg:phone":"+49 7051/40380",
    "sg:postcode":"75365",
    "sg:province":"Baden-W\u00fcrttemberg",
    "wof:name":"Ev. Pfarramt Stammheim",
    "wof:placetype":"venue"
},
  "geometry": {"coordinates":[8.769112587,48.6948356628],"type":"Point"}
}