{
  "type": "Feature",
  "properties": {
    "iso:country":"DE",
    "sg:address":"Zwinglistr. 19",
    "sg:city":"Wuppertal",
    "sg:phone":"+49 202/2546713",
    "sg:postcode":"42275",
    "sg:province":"Nordrhein-Westfalen",
    "wof:name":"Drillisch Vertriebs Und Service Gmbh",
    "wof:placetype":"venue"
},
  "geometry": {"coordinates":[7.1991481781,51.2716941833],"type":"Point"}
}