{
  "type": "Feature",
  "properties": {
    "iso:country":"DE",
    "sg:address":"Kirchenstr. 3",
    "sg:city":"Buchholz",
    "sg:phone":"+49 4181/290628",
    "sg:postcode":"21244",
    "sg:province":"Niedersachsen",
    "wof:name":"Gik Ges. F. Information Kommunikation Und",
    "wof:placetype":"venue"
},
  "geometry": {"coordinates":[9.8822507858,53.3288917542],"type":"Point"}
}