{
  "type": "Feature",
  "properties": {
    "iso:country":"DE",
    "sg:address":"Grabenstr. 8",
    "sg:city":"Kleinmaischeid",
    "sg:phone":"+49 2689/98560",
    "sg:postcode":"56271",
    "sg:province":"Rheinland-Pfalz",
    "wof:name":"Elektro Werner Gmbh",
    "wof:placetype":"venue"
},
  "geometry": {"coordinates":[7.605347,50.510014],"type":"Point"}
}