{
  "type": "Feature",
  "properties": {
    "iso:country":"DE",
    "sg:address":"Poststr. 28",
    "sg:city":"Heidelberg",
    "sg:phone":"+49 6221/168910",
    "sg:postcode":"69115",
    "sg:province":"Baden-W\u00fcrttemberg",
    "wof:name":"Alm Jostock & Weber Gesellschaft F\u00fcr Immobilien-",
    "wof:placetype":"venue"
},
  "geometry": {"coordinates":[8.6899023056,49.4080047607],"type":"Point"}
}