{
  "type": "Feature",
  "properties": {
    "iso:country":"DE",
    "sg:address":"Dreieichstr. 54",
    "sg:city":"Friedrichsdorf",
    "sg:phone":"+49 6175/941370",
    "sg:postcode":"61381",
    "sg:province":"Hessen",
    "wof:name":"Ulf Matthias Kr\u00f6ger",
    "wof:placetype":"venue"
},
  "geometry": {"coordinates":[8.6458969116,50.2725486755],"type":"Point"}
}