{
  "type": "Feature",
  "properties": {
    "iso:country":"DE",
    "sg:address":"Feuerleinstr. 28",
    "sg:city":"Hohen Neuendorf",
    "sg:phone":"+49 3303/504555",
    "sg:postcode":"16540",
    "sg:province":"Brandenburg",
    "wof:name":"Brandenburger Kranken Pflegeteam",
    "wof:placetype":"venue"
},
  "geometry": {"coordinates":[13.272619,52.660625],"type":"Point"}
}