{
  "type": "Feature",
  "properties": {
    "iso:country":"DE",
    "sg:address":"Heisterbacher Str. 89",
    "sg:city":"K\u00f6nigswinter",
    "sg:phone":"+49 2223/21118",
    "sg:postcode":"53639",
    "sg:province":"Nordrhein-Westfalen",
    "wof:name":"Anneliese Wierz-lachart",
    "wof:placetype":"venue"
},
  "geometry": {"coordinates":[7.186867,50.696774],"type":"Point"}
}