{
  "type": "Feature",
  "properties": {
    "iso:country":"DE",
    "sg:address":"Maillingerstr. 24",
    "sg:city":"W\u00fcrzburg",
    "sg:phone":"+49 931/414779",
    "sg:postcode":"97082",
    "sg:province":"Bayern",
    "wof:name":"Pilsst\u00fcberl Mariandl",
    "wof:placetype":"venue"
},
  "geometry": {"coordinates":[9.9143180847,49.8007698059],"type":"Point"}
}