{
  "type": "Feature",
  "properties": {
    "iso:country":"DE",
    "sg:address":"Ring Str.09",
    "sg:city":"Kassel",
    "sg:postcode":"34003",
    "sg:province":"Hessen",
    "wof:name":"Andre Ebert",
    "wof:placetype":"venue"
},
  "geometry": {"coordinates":[9.2764072418,50.2107200623],"type":"Point"}
}