{
  "type": "Feature",
  "properties": {
    "iso:country":"DE",
    "sg:address":"An der Zinkh\u00fctte 13",
    "sg:city":"Bergisch Gladbach",
    "sg:phone":"+49 2202/936600",
    "sg:postcode":"51469",
    "sg:province":"Nordrhein-Westfalen",
    "wof:name":"Hagedorn Gmbh",
    "wof:placetype":"venue"
},
  "geometry": {"coordinates":[7.1282858849,50.9762153625],"type":"Point"}
}