{
  "type": "Feature",
  "properties": {
    "iso:country":"DE",
    "sg:address":"Bilser Str. 55",
    "sg:city":"Hamburg",
    "sg:phone":"+49 40/516828",
    "sg:postcode":"22297",
    "sg:province":"Hamburg",
    "wof:name":"H. Weber",
    "wof:placetype":"venue"
},
  "geometry": {"coordinates":[10.007445,53.606918],"type":"Point"}
}