{
  "type": "Feature",
  "properties": {
    "iso:country":"DE",
    "sg:address":"Yorckstr. 57",
    "sg:city":"Celle",
    "sg:phone":"+49 5141/560240",
    "sg:postcode":"29223",
    "sg:province":"Niedersachsen",
    "wof:name":"H. N. C. Hair-nail-cosmetic- Vertriebsgesellschaft Mbh",
    "wof:placetype":"venue"
},
  "geometry": {"coordinates":[10.035103,52.63863],"type":"Point"}
}