{
  "type": "Feature",
  "properties": {
    "iso:country":"DE",
    "sg:address":"Karl-Marx-Str. 34",
    "sg:city":"Hartha",
    "sg:phone":"+49 34328/39292",
    "sg:postcode":"04746",
    "sg:province":"Sachsen",
    "wof:name":"K. Slotwinski",
    "wof:placetype":"venue"
},
  "geometry": {"coordinates":[12.9714584351,51.0979728699],"type":"Point"}
}