{
  "type": "Feature",
  "properties": {
    "iso:country":"DE",
    "sg:address":"Steinbr\u00fcchener Weg 2",
    "sg:city":"Geu\u00dfnitz",
    "sg:phone":"+49 34423/21630",
    "sg:postcode":"06712",
    "sg:province":"Sachsen-Anhalt",
    "wof:name":"Fks Baugesellschaft Mbh",
    "wof:placetype":"venue"
},
  "geometry": {"coordinates":[12.1846551895,51.016658783],"type":"Point"}
}