{
  "type": "Feature",
  "properties": {
    "iso:country":"DE",
    "sg:address":"Ilser Brink 4",
    "sg:city":"Petershagen",
    "sg:phone":"+49 5705/1700",
    "sg:postcode":"32469",
    "sg:province":"Nordrhein-Westfalen",
    "wof:name":"Ernst R\u00f6bke Verlag",
    "wof:placetype":"venue"
},
  "geometry": {"coordinates":[9.0474081039,52.4028663635],"type":"Point"}
}