{
  "type": "Feature",
  "properties": {
    "iso:country":"DE",
    "sg:address":"K\u00f6lner Str. 256",
    "sg:city":"Bergneustadt",
    "sg:phone":"+49 2261/4040",
    "sg:postcode":"51702",
    "sg:province":"Nordrhein-Westfalen",
    "wof:name":"Wasserwerk Der Stadt Bergneustadt",
    "wof:placetype":"venue"
},
  "geometry": {"coordinates":[7.6539258957,51.0203781128],"type":"Point"}
}