{
  "type": "Feature",
  "properties": {
    "iso:country":"DE",
    "sg:address":"M\u00fcller-Breslau-Str. 4",
    "sg:city":"Essen",
    "sg:phone":"+49 201/771049",
    "sg:postcode":"45130",
    "sg:province":"Nordrhein-Westfalen",
    "wof:name":"Heinz Heise Und H. Winterpacht",
    "wof:placetype":"venue"
},
  "geometry": {"coordinates":[7.014471,51.433525],"type":"Point"}
}