{
  "type": "Feature",
  "properties": {
    "iso:country":"DE",
    "sg:address":"Darmst\u00e4dter Str. 15",
    "sg:city":"Gro\u00df-Gerau",
    "sg:phone":"+49 6152/2510",
    "sg:postcode":"64521",
    "sg:province":"Hessen",
    "wof:name":"Otto Berning",
    "wof:placetype":"venue"
},
  "geometry": {"coordinates":[8.4834566116,49.9202384949],"type":"Point"}
}