{
  "type": "Feature",
  "properties": {
    "iso:country":"DE",
    "sg:address":"Colonnaden 47",
    "sg:city":"Hamburg",
    "sg:phone":"+49 40/345884",
    "sg:postcode":"20354",
    "sg:province":"Hamburg",
    "wof:name":"Colon Gmbh & Co. Kg",
    "wof:placetype":"venue"
},
  "geometry": {"coordinates":[9.989753,53.557579],"type":"Point"}
}