{
  "type": "Feature",
  "properties": {
    "iso:country":"DE",
    "sg:address":"Turmfalkenweg 3",
    "sg:city":"Bonn",
    "sg:phone":"+49 228/283858",
    "sg:postcode":"53127",
    "sg:province":"Nordrhein-Westfalen",
    "wof:name":"Prof. Dr. Armin Rojahn Tierarzt",
    "wof:placetype":"venue"
},
  "geometry": {"coordinates":[7.083067894,50.6942596436],"type":"Point"}
}