{
  "type": "Feature",
  "properties": {
    "iso:country":"DE",
    "sg:address":"Wildenberg 7",
    "sg:city":"Selbitz",
    "sg:phone":"+49 9280/1300",
    "sg:postcode":"95152",
    "sg:province":"Bayern",
    "wof:name":"Alois Bannert",
    "wof:placetype":"venue"
},
  "geometry": {"coordinates":[11.757276,50.319134],"type":"Point"}
}