{
  "type": "Feature",
  "properties": {
    "iso:country":"DE",
    "sg:address":"Bunzlaustr. 60",
    "sg:city":"Dortmund",
    "sg:phone":"+49 231/417410",
    "sg:postcode":"44263",
    "sg:province":"Nordrhein-Westfalen",
    "wof:name":"Lebensmittel Boos Gmbh & Co. Kg",
    "wof:placetype":"venue"
},
  "geometry": {"coordinates":[7.505961895,51.4977722168],"type":"Point"}
}