{
  "type": "Feature",
  "properties": {
    "iso:country":"DE",
    "sg:address":"Freisenstr. 2",
    "sg:city":"Herne",
    "sg:phone":"+49 2325/56322",
    "sg:postcode":"44649",
    "sg:province":"Nordrhein-Westfalen",
    "wof:name":"Heihoff Und Hermeler Ergotherapeutische Praxis",
    "wof:placetype":"venue"
},
  "geometry": {"coordinates":[7.159191,51.528545],"type":"Point"}
}