{
  "type": "Feature",
  "properties": {
    "iso:country":"DE",
    "sg:address":"Kr\u00fcgerstr. 34",
    "sg:city":"Kassel",
    "sg:phone":"+49 561/64043",
    "sg:postcode":"34130",
    "sg:province":"Hessen",
    "wof:name":"R\u00fcdiger Albrecht Ingenieur",
    "wof:placetype":"venue"
},
  "geometry": {"coordinates":[9.4494714737,51.3238487244],"type":"Point"}
}