{
  "type": "Feature",
  "properties": {
    "iso:country":"DE",
    "sg:address":"Meisenweg 14",
    "sg:city":"Langenburg",
    "sg:phone":"+49 7905/5276",
    "sg:postcode":"74595",
    "sg:province":"Baden-W\u00fcrttemberg",
    "wof:name":"Inkatec Gmbh",
    "wof:placetype":"venue"
},
  "geometry": {"coordinates":[9.8658876419,49.2596931458],"type":"Point"}
}