{
  "type": "Feature",
  "properties": {
    "iso:country":"DE",
    "sg:address":"Eugenstr. 11",
    "sg:city":"Bochum",
    "sg:phone":"+49 234/15261",
    "sg:postcode":"44793",
    "sg:province":"Nordrhein-Westfalen",
    "wof:name":"K.-h. Schlegel",
    "wof:placetype":"venue"
},
  "geometry": {"coordinates":[7.1908631325,51.4771652222],"type":"Point"}
}