{
  "type": "Feature",
  "properties": {
    "iso:country":"DE",
    "sg:address":"Hauptstr. 17",
    "sg:city":"Friedewald",
    "sg:phone":"+49 6674/92220",
    "sg:postcode":"36289",
    "sg:province":"Hessen",
    "wof:name":"Hotel Zum L\u00f6wen",
    "wof:placetype":"venue"
},
  "geometry": {"coordinates":[9.85846138,50.8823509216],"type":"Point"}
}