{
  "type": "Feature",
  "properties": {
    "iso:country":"DE",
    "sg:address":"Hauptstr. 72",
    "sg:city":"Senden",
    "sg:phone":"+49 7307/5564",
    "sg:postcode":"89250",
    "sg:province":"Bayern",
    "wof:name":"Josef Albert",
    "wof:placetype":"venue"
},
  "geometry": {"coordinates":[10.038438797,48.322467804],"type":"Point"}
}