{
  "type": "Feature",
  "properties": {
    "iso:country":"DE",
    "sg:address":"Max-Planck-Str. 13",
    "sg:city":"H\u00fcrth",
    "sg:phone":"+49 4922/3379890",
    "sg:postcode":"50354",
    "sg:province":"Nordrhein-Westfalen",
    "wof:name":"Paul Vollrath Gmbh & Co. Kg",
    "wof:placetype":"venue"
},
  "geometry": {"coordinates":[6.90391,50.884068],"type":"Point"}
}