{
  "type": "Feature",
  "properties": {
    "iso:country":"DE",
    "sg:address":"Rotachstr. 46",
    "sg:city":"Deggenhausertal",
    "sg:phone":"+49 7555/91094",
    "sg:postcode":"88693",
    "sg:province":"Baden-W\u00fcrttemberg",
    "wof:name":"Richter Studioger\u00e4te Gmbh",
    "wof:placetype":"venue"
},
  "geometry": {"coordinates":[9.4350481033,47.7621154785],"type":"Point"}
}