{
  "type": "Feature",
  "properties": {
    "iso:country":"DE",
    "sg:address":"Bremer Str. 57",
    "sg:city":"Osnabr\u00fcck",
    "sg:phone":"+49 541/72109",
    "sg:postcode":"49084",
    "sg:province":"Niedersachsen",
    "wof:name":"Avm Maler- Und Bauunternehmen Gmbh",
    "wof:placetype":"venue"
},
  "geometry": {"coordinates":[8.076543,52.28426],"type":"Point"}
}