{
  "type": "Feature",
  "properties": {
    "iso:country":"DE",
    "sg:address":"Am Haidhof 16",
    "sg:city":"Wangen",
    "sg:phone":"+49 7522/912524",
    "sg:postcode":"88239",
    "sg:province":"Baden-W\u00fcrttemberg",
    "wof:name":"Bistro Downtown",
    "wof:placetype":"venue"
},
  "geometry": {"coordinates":[9.825586319,47.6966896057],"type":"Point"}
}