{
  "type": "Feature",
  "properties": {
    "iso:country":"DE",
    "sg:address":"Pfarrstr. 19",
    "sg:city":"Kassel",
    "sg:phone":"+49 561/57070",
    "sg:postcode":"34123",
    "sg:province":"Hessen",
    "wof:name":"Klinik Dr. Koch Gmbh & Co. Kg",
    "wof:placetype":"venue"
},
  "geometry": {"coordinates":[9.534817,51.304726],"type":"Point"}
}