{
  "type": "Feature",
  "properties": {
    "iso:country":"DE",
    "sg:address":"Wildenauer Str. 4",
    "sg:city":"Steinberg",
    "sg:phone":"+49 37462/4345",
    "sg:postcode":"08237",
    "sg:province":"Sachsen",
    "wof:name":"Hutzenst\u00fcbl",
    "wof:placetype":"venue"
},
  "geometry": {"coordinates":[12.4970064163,50.5379257202],"type":"Point"}
}