{
  "type": "Feature",
  "properties": {
    "iso:country":"DE",
    "sg:address":"Werkstr. 11",
    "sg:city":"Weinstadt",
    "sg:phone":"+49 7151/967619",
    "sg:postcode":"71384",
    "sg:province":"Baden-W\u00fcrttemberg",
    "wof:name":"Mack Natursteine Gmbh",
    "wof:placetype":"venue"
},
  "geometry": {"coordinates":[9.3715276718,48.8160095215],"type":"Point"}
}