{
  "type": "Feature",
  "properties": {
    "iso:country":"DE",
    "sg:address":"Industriestr. 20",
    "sg:city":"Gr\u00f6benzell",
    "sg:postcode":"82194",
    "sg:province":"Bayern",
    "wof:name":"Betonpumpendienst Zehentner Inh. Erika Kohlmann E. Kfr.",
    "wof:placetype":"venue"
},
  "geometry": {"coordinates":[11.3831300735,48.189037323],"type":"Point"}
}