{
  "type": "Feature",
  "properties": {
    "iso:country":"DE",
    "sg:address":"Rath 17-18",
    "sg:city":"Remscheid",
    "sg:phone":"+49 2191/23344",
    "sg:postcode":"42855",
    "sg:province":"Nordrhein-Westfalen",
    "wof:name":"Helmut Epe Gmbh & Co. Kg",
    "wof:placetype":"venue"
},
  "geometry": {"coordinates":[7.184345,51.195679],"type":"Point"}
}