{
  "type": "Feature",
  "properties": {
    "iso:country":"DE",
    "sg:address":"Frankfurter Str. 7",
    "sg:city":"Neuhof",
    "sg:phone":"+49 6655/1765",
    "sg:postcode":"36119",
    "sg:province":"Hessen",
    "wof:name":"Bajazzo",
    "wof:placetype":"venue"
},
  "geometry": {"coordinates":[9.6160516739,50.4521064758],"type":"Point"}
}