{
  "type": "Feature",
  "properties": {
    "iso:country":"DE",
    "sg:address":"Hebelstr. 23",
    "sg:city":"Frankfurt",
    "sg:phone":"+49 69/591539",
    "sg:postcode":"60318",
    "sg:province":"Hessen",
    "wof:name":"A. Guhl",
    "wof:placetype":"venue"
},
  "geometry": {"coordinates":[8.6866598129,50.1212043762],"type":"Point"}
}