{
  "type": "Feature",
  "properties": {
    "iso:country":"DE",
    "sg:address":"G\u00fcnterslebener Str. 6",
    "sg:city":"Rimpar",
    "sg:phone":"+49 9365/80830",
    "sg:postcode":"97222",
    "sg:province":"Bayern",
    "wof:name":"Pension Kraus",
    "wof:placetype":"venue"
},
  "geometry": {"coordinates":[9.9536819458,49.8569488525],"type":"Point"}
}