{
  "type": "Feature",
  "properties": {
    "iso:country":"DE",
    "sg:address":"Feuerdornstr. 108",
    "sg:city":"Hamm",
    "sg:phone":"+49 2381/82229",
    "sg:postcode":"59071",
    "sg:province":"Nordrhein-Westfalen",
    "wof:name":"Brigitte Jeuschede",
    "wof:placetype":"venue"
},
  "geometry": {"coordinates":[7.8746042252,51.6824760437],"type":"Point"}
}