{
  "type": "Feature",
  "properties": {
    "iso:country":"DE",
    "sg:address":"Herbert-Weichmann-Str. 19",
    "sg:city":"Hamburg",
    "sg:postcode":"22085",
    "sg:province":"Hamburg",
    "wof:name":"Klaus Peter Beckmann Immobilien E. K.",
    "wof:placetype":"venue"
},
  "geometry": {"coordinates":[10.0143909454,53.5706939697],"type":"Point"}
}