{
  "type": "Feature",
  "properties": {
    "iso:country":"DE",
    "sg:address":"An der Rehbocksweide 22",
    "sg:city":"Hann. M\u00fcnden",
    "sg:phone":"+49 5541/31023",
    "sg:postcode":"34346",
    "sg:province":"Niedersachsen",
    "wof:name":"Roland Trappmann Kg",
    "wof:placetype":"venue"
},
  "geometry": {"coordinates":[9.6668100357,51.4058647156],"type":"Point"}
}