{
  "type": "Feature",
  "properties": {
    "iso:country":"DE",
    "sg:address":"Lohfelder Weg 91",
    "sg:city":"Duisburg",
    "sg:phone":"+49 2151/403747",
    "sg:postcode":"47239",
    "sg:province":"Nordrhein-Westfalen",
    "wof:name":"Wasserski/ Freizeitanlage Kleiner Toeppersee Gmbh",
    "wof:placetype":"venue"
},
  "geometry": {"coordinates":[6.6687397957,51.4022903442],"type":"Point"}
}