{
  "type": "Feature",
  "properties": {
    "iso:country":"DE",
    "sg:address":"Sch\u00f6rzinger Str. 50",
    "sg:city":"Wellendingen",
    "sg:phone":"+49 7426/8827",
    "sg:postcode":"78669",
    "sg:province":"Baden-W\u00fcrttemberg",
    "wof:name":"Gastst\u00e4tte Mehrzweckhalle",
    "wof:placetype":"venue"
},
  "geometry": {"coordinates":[8.729467392,48.1568450928],"type":"Point"}
}