{
  "type": "Feature",
  "properties": {
    "iso:country":"DE",
    "sg:address":"Karlsplatz 4",
    "sg:city":"Ludwigsburg",
    "sg:phone":"+49 7141/923400",
    "sg:postcode":"71638",
    "sg:province":"Baden-W\u00fcrttemberg",
    "wof:name":"Gerhard Schlaich",
    "wof:placetype":"venue"
},
  "geometry": {"coordinates":[9.187078,48.891594],"type":"Point"}
}