{
  "type": "Feature",
  "properties": {
    "iso:country":"DE",
    "sg:address":"Myliusstr. 4",
    "sg:city":"Ludwigsburg",
    "sg:phone":"+49 7141/923028",
    "sg:postcode":"71638",
    "sg:province":"Baden-W\u00fcrttemberg",
    "wof:name":"Erwin Schelle",
    "wof:placetype":"venue"
},
  "geometry": {"coordinates":[9.186992,48.89386],"type":"Point"}
}