{
  "type": "Feature",
  "properties": {
    "iso:country":"DE",
    "sg:address":"Gro\u00dfe Str. 22",
    "sg:city":"Sottrum",
    "sg:postcode":"27367",
    "sg:province":"Niedersachsen",
    "wof:name":"Beg-baugrund Und Erschlie\u00dfungs Gmbh",
    "wof:placetype":"venue"
},
  "geometry": {"coordinates":[9.230514,53.115303],"type":"Point"}
}