{
  "type": "Feature",
  "properties": {
    "iso:country":"DE",
    "sg:address":"Sturmstr. 7",
    "sg:city":"Landau",
    "sg:phone":"+49 9951/59329",
    "sg:postcode":"94405",
    "sg:province":"Bayern",
    "wof:name":"Gastst\u00e4tte Helmut Ring",
    "wof:placetype":"venue"
},
  "geometry": {"coordinates":[12.6469154358,48.6610031128],"type":"Point"}
}