{
  "type": "Feature",
  "properties": {
    "iso:country":"DE",
    "sg:address":"Hauptstr. 12",
    "sg:city":"H\u00f6chst\u00e4dt",
    "sg:phone":"+49 9235/473",
    "sg:postcode":"95186",
    "sg:province":"Bayern",
    "wof:name":"Walter Gr\u00e4f",
    "wof:placetype":"venue"
},
  "geometry": {"coordinates":[12.0852842331,50.0954284668],"type":"Point"}
}