{
  "type": "Feature",
  "properties": {
    "iso:country":"DE",
    "sg:address":"Zungenstr. 4",
    "sg:city":"Barsinghausen",
    "sg:phone":"+49 5105/1264",
    "sg:postcode":"30890",
    "sg:province":"Niedersachsen",
    "wof:name":"Fritz Voges",
    "wof:placetype":"venue"
},
  "geometry": {"coordinates":[9.5211191177,52.3440093994],"type":"Point"}
}