{
  "type": "Feature",
  "properties": {
    "iso:country":"DE",
    "sg:address":"Ulmer Str. 123",
    "sg:city":"G\u00f6ppingen",
    "sg:postcode":"73037",
    "sg:province":"Baden-W\u00fcrttemberg",
    "wof:name":"Lsb Grundst\u00fccksverwaltung Objekt Bielefeld Am Metallwerk",
    "wof:placetype":"venue"
},
  "geometry": {"coordinates":[9.68211,48.697701],"type":"Point"}
}