{
  "type": "Feature",
  "properties": {
    "iso:country":"DE",
    "sg:address":"Breiter Weg 38",
    "sg:city":"Seehausen",
    "sg:phone":"+49 39407/9120",
    "sg:postcode":"39365",
    "sg:province":"Sachsen-Anhalt",
    "wof:name":"Immobilien-und Anlageges. Mbh",
    "wof:placetype":"venue"
},
  "geometry": {"coordinates":[11.2904338837,52.1023406982],"type":"Point"}
}