{
  "type": "Feature",
  "properties": {
    "iso:country":"DE",
    "sg:address":"Naumburger Str. 20",
    "sg:city":"Grana",
    "sg:phone":"+49 3441/214165",
    "sg:postcode":"06712",
    "sg:province":"Sachsen-Anhalt",
    "wof:name":"A & W Klotz Automobile",
    "wof:placetype":"venue"
},
  "geometry": {"coordinates":[12.1019210815,51.054889679],"type":"Point"}
}