{
  "type": "Feature",
  "properties": {
    "iso:country":"DE",
    "sg:address":"Lange Str. 57",
    "sg:city":"Castrop-Rauxel",
    "sg:phone":"+49 2305/73984",
    "sg:postcode":"44579",
    "sg:province":"Nordrhein-Westfalen",
    "wof:name":"Marlies Scholz",
    "wof:placetype":"venue"
},
  "geometry": {"coordinates":[7.311244,51.584488],"type":"Point"}
}