{
  "type": "Feature",
  "properties": {
    "iso:country":"DE",
    "sg:address":"Heinrich-Heine-Str. 63",
    "sg:city":"Bremen",
    "sg:phone":"+49 421/232880",
    "sg:postcode":"28211",
    "sg:province":"Bremen",
    "wof:name":"Hannelore Lipowski-schomaker Rechtsanw\u00e4ltin",
    "wof:placetype":"venue"
},
  "geometry": {"coordinates":[8.865401268,53.0861167908],"type":"Point"}
}