{
  "type": "Feature",
  "properties": {
    "iso:country":"DE",
    "sg:address":"Frankenthaler Str. 61",
    "sg:city":"Gera",
    "sg:phone":"+49 365/810450",
    "sg:postcode":"07548",
    "sg:province":"Th\u00fcringen",
    "wof:name":"Gastst\u00e4tte Dix",
    "wof:placetype":"venue"
},
  "geometry": {"coordinates":[12.0136833191,50.8774795532],"type":"Point"}
}