{
  "type": "Feature",
  "properties": {
    "iso:country":"DE",
    "sg:address":"Bahnhofstr. 13",
    "sg:city":"Rieste",
    "sg:phone":"+49 5464/969685",
    "sg:postcode":"49597",
    "sg:province":"Niedersachsen",
    "wof:name":"M. Schulze",
    "wof:placetype":"venue"
},
  "geometry": {"coordinates":[8.009844,52.48365],"type":"Point"}
}