{
  "type": "Feature",
  "properties": {
    "iso:country":"DE",
    "sg:address":"Deverhafen 1",
    "sg:city":"Papenburg",
    "sg:phone":"+49 4961/8060",
    "sg:postcode":"26871",
    "sg:province":"Niedersachsen",
    "wof:name":"Dever Baustoffhandel Gmbh",
    "wof:placetype":"venue"
},
  "geometry": {"coordinates":[7.3777050972,53.0874862671],"type":"Point"}
}