{
  "type": "Feature",
  "properties": {
    "iso:country":"DE",
    "sg:address":"Rosenweg 6",
    "sg:city":"Bodman-Ludwigshafen",
    "sg:phone":"+49 7773/920890",
    "sg:postcode":"78351",
    "sg:province":"Baden-W\u00fcrttemberg",
    "wof:name":"Senioren-residenz Saxonia Gmbh",
    "wof:placetype":"venue"
},
  "geometry": {"coordinates":[9.055175,47.820042],"type":"Point"}
}