{
  "type": "Feature",
  "properties": {
    "iso:country":"DE",
    "sg:address":"Gottschalkstr. 32",
    "sg:city":"Kassel",
    "sg:phone":"+49 561/8900751",
    "sg:postcode":"34127",
    "sg:province":"Hessen",
    "wof:name":"F. Matkovic",
    "wof:placetype":"venue"
},
  "geometry": {"coordinates":[9.503985405,51.3262252808],"type":"Point"}
}