{
  "type": "Feature",
  "properties": {
    "iso:country":"DE",
    "sg:address":"malterstrasse",
    "sg:city":"dresden",
    "sg:postcode":"01159",
    "sg:province":"Sachsen",
    "wof:name":"Stefan Frischke - B\u00fchneninspektor",
    "wof:placetype":"venue"
},
  "geometry": {"coordinates":[13.6908,51.043896],"type":"Point"}
}