{
  "type": "Feature",
  "properties": {
    "iso:country":"DE",
    "sg:address":"Habenhauser Landstr. 277",
    "sg:city":"Bremen",
    "sg:phone":"+49 421/833255",
    "sg:postcode":"28279",
    "sg:province":"Bremen",
    "wof:name":"Karl K\u00fcnneke",
    "wof:placetype":"venue"
},
  "geometry": {"coordinates":[8.8556365967,53.0504646301],"type":"Point"}
}