{
  "type": "Feature",
  "properties": {
    "iso:country":"DE",
    "sg:address":"Raiffeisenstr. 49",
    "sg:city":"Bruchk\u00f6bel",
    "sg:phone":"+49 6183/3580",
    "sg:postcode":"63486",
    "sg:province":"Hessen",
    "wof:name":"Roswitha Unger",
    "wof:placetype":"venue"
},
  "geometry": {"coordinates":[8.950918,50.199188],"type":"Point"}
}