{
  "type": "Feature",
  "properties": {
    "iso:country":"DE",
    "sg:address":"Neue Str. 9",
    "sg:city":"Erlbach-Kirchberg",
    "sg:phone":"+49 37295/54952",
    "sg:postcode":"09385",
    "sg:province":"Sachsen",
    "wof:name":"Andreas Und Karin Piasta",
    "wof:placetype":"venue"
},
  "geometry": {"coordinates":[12.7566776276,50.7555198669],"type":"Point"}
}