{
  "type": "Feature",
  "properties": {
    "iso:country":"DE",
    "sg:address":"R\u00fcckertstr. 8",
    "sg:city":"W\u00fcrzburg",
    "sg:phone":"+49 931/77927",
    "sg:postcode":"97072",
    "sg:province":"Bayern",
    "wof:name":"Knierim Datentechnik Gmbh",
    "wof:placetype":"venue"
},
  "geometry": {"coordinates":[9.932812,49.779861],"type":"Point"}
}