{
  "type": "Feature",
  "properties": {
    "iso:country":"DE",
    "sg:address":"Hardtstr 13",
    "sg:city":"Medebach",
    "sg:phone":"+49 791/54009",
    "sg:postcode":"59964",
    "sg:province":"Nordrhein-Westfalen",
    "wof:name":"Walter Sommer",
    "wof:placetype":"venue"
},
  "geometry": {"coordinates":[9.6987895966,49.1021385193],"type":"Point"}
}