{
  "type": "Feature",
  "properties": {
    "iso:country":"DE",
    "sg:address":"Reuthgasse 22",
    "sg:city":"Kulmbach",
    "sg:phone":"+49 9221/97651",
    "sg:postcode":"95326",
    "sg:province":"Bayern",
    "wof:name":"Lindauer Dornier Gmbh",
    "wof:placetype":"venue"
},
  "geometry": {"coordinates":[11.4603509903,50.0983352661],"type":"Point"}
}