{
  "type": "Feature",
  "properties": {
    "iso:country":"DE",
    "sg:address":"Thomas-Schwarz-Str. 17",
    "sg:city":"Dachau",
    "sg:phone":"+49 8131/4258",
    "sg:postcode":"85221",
    "sg:province":"Bayern",
    "wof:name":"Eduard Schrall",
    "wof:placetype":"venue"
},
  "geometry": {"coordinates":[11.433928,48.251244],"type":"Point"}
}