{
  "type": "Feature",
  "properties": {
    "iso:country":"DE",
    "sg:address":"Hohenloher Str. 10",
    "sg:city":"Neckarsulm",
    "sg:phone":"+49 7132/16212",
    "sg:postcode":"74172",
    "sg:province":"Baden-W\u00fcrttemberg",
    "wof:name":"O. Und C. Morlock",
    "wof:placetype":"venue"
},
  "geometry": {"coordinates":[9.2288103104,49.1837463379],"type":"Point"}
}