{
  "type": "Feature",
  "properties": {
    "iso:country":"DE",
    "sg:address":"Humboldtstr. 52",
    "sg:city":"Pforzheim",
    "sg:phone":"+49 7231/650065",
    "sg:postcode":"75175",
    "sg:province":"Baden-W\u00fcrttemberg",
    "wof:name":"Peter Wenz Ingenieur",
    "wof:placetype":"venue"
},
  "geometry": {"coordinates":[8.705573082,48.8849525452],"type":"Point"}
}