{
  "type": "Feature",
  "properties": {
    "iso:country":"DE",
    "sg:address":"Stresemannstr. 8",
    "sg:city":"Bochum",
    "sg:phone":"+49 2327/82037",
    "sg:postcode":"44866",
    "sg:province":"Nordrhein-Westfalen",
    "wof:name":"G\u00fcnter Sibbe",
    "wof:placetype":"venue"
},
  "geometry": {"coordinates":[7.1379990578,51.4845733643],"type":"Point"}
}