{
  "type": "Feature",
  "properties": {
    "iso:country":"DE",
    "sg:address":"Am Alten Weg 33",
    "sg:city":"Mainz",
    "sg:phone":"+49 6131",
    "sg:postcode":"55127",
    "sg:province":"Rheinland-Pfalz",
    "wof:name":"Www-3000",
    "wof:placetype":"venue"
},
  "geometry": {"coordinates":[8.2340688705,49.9623298645],"type":"Point"}
}