{
  "type": "Feature",
  "properties": {
    "iso:country":"DE",
    "sg:address":"Bourg-de-Peage-Str.",
    "sg:city":"Mindelheim",
    "sg:phone":"+49 8261/700310",
    "sg:postcode":"87719",
    "sg:province":"Bayern",
    "wof:name":"De-te-mobil Deutsche Telekom Mobilfunk Gmbh",
    "wof:placetype":"venue"
},
  "geometry": {"coordinates":[10.5044546127,48.05128479],"type":"Point"}
}