{
  "type": "Feature",
  "properties": {
    "iso:country":"DE",
    "sg:address":"Dieker Str. 76",
    "sg:city":"Haan",
    "sg:phone":"+49 212/98383",
    "sg:postcode":"42781",
    "sg:province":"Nordrhein-Westfalen",
    "wof:name":"Kurt Neumann-kl\u00f6ckner",
    "wof:placetype":"venue"
},
  "geometry": {"coordinates":[7.0083389282,51.1943855286],"type":"Point"}
}