{
  "type": "Feature",
  "properties": {
    "iso:country":"DE",
    "sg:address":"A.-Roemer-Str. 39",
    "sg:city":"Clausthal Zellerfeld",
    "sg:phone":"+49 4953/237058",
    "sg:postcode":"38678",
    "sg:province":"Niedersachsen",
    "wof:name":"Deutsche Bank Ag",
    "wof:placetype":"venue"
},
  "geometry": {"coordinates":[10.335493,51.806561],"type":"Point"}
}