{
  "type": "Feature",
  "properties": {
    "iso:country":"DE",
    "sg:address":"Sanktustorstr. 1",
    "sg:city":"Langenzenn",
    "sg:phone":"+49 9101/8764",
    "sg:postcode":"90579",
    "sg:province":"Bayern",
    "wof:name":"G. Ulrich Haus- Und K\u00fcchenger\u00e4te",
    "wof:placetype":"venue"
},
  "geometry": {"coordinates":[10.7953081131,49.4952926636],"type":"Point"}
}