{
  "type": "Feature",
  "properties": {
    "iso:country":"DE",
    "sg:address":"Tannenweg 10",
    "sg:city":"Rostock",
    "sg:phone":"+49 381/4001215",
    "sg:postcode":"18059",
    "sg:province":"Mecklenburg-Vorpommern",
    "wof:name":"Altenbetreuung Hauskrankpfl. Sigrid L\u00f6hndorf",
    "wof:placetype":"venue"
},
  "geometry": {"coordinates":[12.064267,54.075691],"type":"Point"}
}