{
  "type": "Feature",
  "properties": {
    "iso:country":"DE",
    "sg:address":"Elsa-Br\u00e4ndstr\u00f6m-Str. 34",
    "sg:city":"N\u00fcrnberg",
    "sg:phone":"+49 911/614497",
    "sg:postcode":"90431",
    "sg:province":"Bayern",
    "wof:name":"Keydata Computer Systems Europe Gmbh",
    "wof:placetype":"venue"
},
  "geometry": {"coordinates":[11.030828476,49.4395904541],"type":"Point"}
}