{
  "type": "Feature",
  "properties": {
    "iso:country":"DE",
    "sg:address":"Erbacher Str. 2",
    "sg:city":"Eltville",
    "sg:phone":"+49 6123/2483",
    "sg:postcode":"65343",
    "sg:province":"Hessen",
    "wof:name":"Aral Ag",
    "wof:placetype":"venue"
},
  "geometry": {"coordinates":[8.1160135269,50.0241508484],"type":"Point"}
}