{
  "type": "Feature",
  "properties": {
    "iso:country":"DE",
    "sg:address":"Kaiserstr.",
    "sg:city":"Bruchsal",
    "sg:phone":"+49 7251/16411",
    "sg:postcode":"76646",
    "sg:province":"Baden-W\u00fcrttemberg",
    "wof:name":"Parkgarage",
    "wof:placetype":"venue"
},
  "geometry": {"coordinates":[8.5992803574,49.1233596802],"type":"Point"}
}