{
  "type": "Feature",
  "properties": {
    "iso:country":"DE",
    "sg:address":"Berggartenweg 2",
    "sg:city":"W\u00f6lfersheim",
    "sg:phone":"+49 6036/97030",
    "sg:postcode":"61200",
    "sg:province":"Hessen",
    "wof:name":"Erwin Fertig Gmbh",
    "wof:placetype":"venue"
},
  "geometry": {"coordinates":[8.8277950287,50.4269828796],"type":"Point"}
}