{
  "type": "Feature",
  "properties": {
    "iso:country":"DE",
    "sg:address":"Klus 3",
    "sg:city":"Blomberg",
    "sg:phone":"+49 5263/1763",
    "sg:postcode":"32825",
    "sg:province":"Nordrhein-Westfalen",
    "wof:name":"Gerhard Klusmeier",
    "wof:placetype":"venue"
},
  "geometry": {"coordinates":[9.167263,51.976189],"type":"Point"}
}