{
  "type": "Feature",
  "properties": {
    "iso:country":"DE",
    "sg:address":"R\u00f6ntgenstr. 17",
    "sg:city":"Landshut",
    "sg:phone":"+49 871/74021",
    "sg:postcode":"84030",
    "sg:province":"Bayern",
    "wof:name":"Iwan Koslow Beteiligungs-gmbh",
    "wof:placetype":"venue"
},
  "geometry": {"coordinates":[12.145381,48.549889],"type":"Point"}
}