{
  "type": "Feature",
  "properties": {
    "iso:country":"DE",
    "sg:address":"Bahnhofstr 14",
    "sg:city":"Kranenburg",
    "sg:phone":"+49 2826/513133",
    "sg:postcode":"47559",
    "sg:province":"Nordrhein-Westfalen",
    "wof:name":"Akkerman Gmbh",
    "wof:placetype":"venue"
},
  "geometry": {"coordinates":[6.002805,51.787197],"type":"Point"}
}