{
  "type": "Feature",
  "properties": {
    "iso:country":"DE",
    "sg:address":"In der Au 12",
    "sg:city":"Windeck",
    "sg:postcode":"51570",
    "sg:province":"Nordrhein-Westfalen",
    "wof:name":"Hadis Handel Und Dienstleist. F\u00fcr Sozialeinrichtungen Gmbh",
    "wof:placetype":"venue"
},
  "geometry": {"coordinates":[7.5218458176,50.7737884521],"type":"Point"}
}