{
  "type": "Feature",
  "properties": {
    "iso:country":"DE",
    "sg:address":"Dompfaffweg 4",
    "sg:city":"M\u00fcnchen",
    "sg:phone":"+49 89/6704839",
    "sg:postcode":"81827",
    "sg:province":"Bayern",
    "wof:name":"J. Stahl-drescher Immobilienmakler",
    "wof:placetype":"venue"
},
  "geometry": {"coordinates":[11.6984634399,48.1160087585],"type":"Point"}
}