{
  "type": "Feature",
  "properties": {
    "iso:country":"DE",
    "sg:address":"Laboer Weg 1",
    "sg:city":"Heikendorf",
    "sg:phone":"+49 431/241160",
    "sg:postcode":"24226",
    "sg:province":"Schleswig-Holstein",
    "wof:name":"Jochen Steffen",
    "wof:placetype":"venue"
},
  "geometry": {"coordinates":[10.206483,54.371269],"type":"Point"}
}