{
  "type": "Feature",
  "properties": {
    "iso:country":"DE",
    "sg:address":"Urnenfeldstr. 8",
    "sg:city":"Hamm",
    "sg:phone":"+49 2389/52588",
    "sg:postcode":"59077",
    "sg:province":"Nordrhein-Westfalen",
    "wof:name":"Ferdinand Kortmann Gmbh & Co. Kg",
    "wof:placetype":"venue"
},
  "geometry": {"coordinates":[7.689905,51.656708],"type":"Point"}
}