{
  "type": "Feature",
  "properties": {
    "iso:country":"DE",
    "sg:address":"Hinterm Hofe 9",
    "sg:city":"Gl\u00fcckstadt",
    "sg:phone":"+49 4124/7112",
    "sg:postcode":"25348",
    "sg:province":"Schleswig-Holstein",
    "wof:name":"R\u00f6ttger",
    "wof:placetype":"venue"
},
  "geometry": {"coordinates":[9.437282,53.777149],"type":"Point"}
}