{
  "type": "Feature",
  "properties": {
    "iso:country":"DE",
    "sg:address":"Hauptstr. 12",
    "sg:city":"Ilvesheim",
    "sg:phone":"+49 621/494788",
    "sg:postcode":"68549",
    "sg:province":"Baden-W\u00fcrttemberg",
    "wof:name":"Restaurant Hufeisen",
    "wof:placetype":"venue"
},
  "geometry": {"coordinates":[8.5656576157,49.4715232849],"type":"Point"}
}