{
  "type": "Feature",
  "properties": {
    "iso:country":"DE",
    "sg:address":"Josefstaler Str. 17a",
    "sg:city":"Schliersee",
    "sg:phone":"+49 8026/7031",
    "sg:postcode":"83727",
    "sg:province":"Bayern",
    "wof:name":"Heinz Blees Architekt",
    "wof:placetype":"venue"
},
  "geometry": {"coordinates":[11.882932,47.692928],"type":"Point"}
}