{
  "type": "Feature",
  "properties": {
    "iso:country":"DE",
    "sg:address":"Georg-Schumann-Str. 87-89",
    "sg:city":"Leipzig",
    "sg:phone":"+49 341/52784",
    "sg:postcode":"04155",
    "sg:province":"Sachsen",
    "wof:name":"Orthop\u00e4die-chirurgie- Mechanik Gmbh",
    "wof:placetype":"venue"
},
  "geometry": {"coordinates":[12.3648366928,51.3624458313],"type":"Point"}
}