{
  "type": "Feature",
  "properties": {
    "iso:country":"DE",
    "sg:address":"Niederlosheimer Str. 116",
    "sg:city":"Losheim",
    "sg:phone":"+49 6872/993200",
    "sg:postcode":"66679",
    "sg:province":"Saarland",
    "wof:name":"Birgit Kl\u00f6pper Und Saman Weeraslinghe",
    "wof:placetype":"venue"
},
  "geometry": {"coordinates":[6.7777609825,49.5341377258],"type":"Point"}
}