{
  "type": "Feature",
  "properties": {
    "iso:country":"DE",
    "sg:address":"Johann-Althaus-Str. 3",
    "sg:city":"Sonthofen",
    "sg:phone":"+49 8321/83053",
    "sg:postcode":"87527",
    "sg:province":"Bayern",
    "wof:name":"Dipl.-kfm. Reiner Fuhrmann Generalv. D. Agrippina Ver.-ag",
    "wof:placetype":"venue"
},
  "geometry": {"coordinates":[10.277633667,47.5116920471],"type":"Point"}
}