{
  "type": "Feature",
  "properties": {
    "iso:country":"DE",
    "sg:address":"Werner-John-Siedlung 3",
    "sg:city":"Rudolstadt",
    "sg:phone":"+49 3672/410239",
    "sg:postcode":"07407",
    "sg:province":"Th\u00fcringen",
    "wof:name":"Hans-joachim Schreyer Architekt",
    "wof:placetype":"venue"
},
  "geometry": {"coordinates":[11.308845,50.707924],"type":"Point"}
}