{
  "type": "Feature",
  "properties": {
    "iso:country":"DE",
    "sg:address":"Wiesenstr. 36",
    "sg:city":"Goch",
    "sg:phone":"+49 2823/41276",
    "sg:postcode":"47574",
    "sg:province":"Nordrhein-Westfalen",
    "wof:name":"M. Trietz Masseur",
    "wof:placetype":"venue"
},
  "geometry": {"coordinates":[6.157159,51.679226],"type":"Point"}
}