{
  "type": "Feature",
  "properties": {
    "iso:country":"DE",
    "sg:address":"Wilhelm-K\u00fclz-Str. 7",
    "sg:city":"Vacha",
    "sg:phone":"+49 36962/24324",
    "sg:postcode":"36404",
    "sg:province":"Th\u00fcringen",
    "wof:name":"Bernd Ehmer Rechtsanwalt",
    "wof:placetype":"venue"
},
  "geometry": {"coordinates":[10.0246067047,50.8273468018],"type":"Point"}
}