{
  "type": "Feature",
  "properties": {
    "iso:country":"DE",
    "sg:address":"Brandst\u00e4tterstr. 58",
    "sg:city":"Ruhpolding",
    "sg:phone":"+49 8663/1278",
    "sg:postcode":"83324",
    "sg:province":"Bayern",
    "wof:name":"Herbert Weidler Rechtsanwalt",
    "wof:placetype":"venue"
},
  "geometry": {"coordinates":[12.6427745819,47.7555007935],"type":"Point"}
}