{
  "type": "Feature",
  "properties": {
    "iso:country":"DE",
    "sg:address":"Am Haarbach 19",
    "sg:city":"Hessisch Oldendorf",
    "sg:phone":"+49 5158/740",
    "sg:postcode":"31840",
    "sg:province":"Niedersachsen",
    "wof:name":"Thomas L\u00fccke",
    "wof:placetype":"venue"
},
  "geometry": {"coordinates":[9.269719,52.139194],"type":"Point"}
}