{
  "type": "Feature",
  "properties": {
    "iso:country":"DE",
    "sg:address":"Ringstr. 16a",
    "sg:city":"Wiesloch",
    "sg:phone":"+49 6222/4545",
    "sg:postcode":"69168",
    "sg:province":"Baden-W\u00fcrttemberg",
    "wof:name":"China-restaurant Ph\u00f6nix",
    "wof:placetype":"venue"
},
  "geometry": {"coordinates":[8.7010774612,49.2935447693],"type":"Point"}
}