{
  "type": "Feature",
  "properties": {
    "iso:country":"DE",
    "sg:address":"Bahnstr 2",
    "sg:city":"D\u00fcsseldorf",
    "sg:phone":"+49 211/940010",
    "sg:postcode":"40212",
    "sg:province":"Nordrhein-Westfalen",
    "wof:name":"Bob Bomlitz Group Hamburg Gmbh",
    "wof:placetype":"venue"
},
  "geometry": {"coordinates":[6.779738,51.219898],"type":"Point"}
}