{
  "type": "Feature",
  "properties": {
    "iso:country":"DE",
    "sg:address":"St.-Anton-Str. 69-71",
    "sg:city":"Krefeld",
    "sg:phone":"+49 2151/912760",
    "sg:postcode":"47798",
    "sg:province":"Nordrhein-Westfalen",
    "wof:name":"Hdi Haftpflichtverband Der Deutschen Industrie",
    "wof:placetype":"venue"
},
  "geometry": {"coordinates":[6.5598897934,51.3334846497],"type":"Point"}
}