{
  "type": "Feature",
  "properties": {
    "iso:country":"DE",
    "sg:address":"Steglitzer Damm 13",
    "sg:city":"Berlin",
    "sg:phone":"+49 30/7959204",
    "sg:postcode":"12169",
    "sg:province":"Berlin",
    "wof:name":"Manuela Potschies",
    "wof:placetype":"venue"
},
  "geometry": {"coordinates":[13.3387184143,52.4511222839],"type":"Point"}
}