{
  "type": "Feature",
  "properties": {
    "iso:country":"DE",
    "sg:address":"Uhlandstr. 31",
    "sg:city":"Linkenheim-Hochstetten",
    "sg:phone":"+49 7247/4284",
    "sg:postcode":"76351",
    "sg:province":"Baden-W\u00fcrttemberg",
    "wof:name":"Gerhard F\u00fcrniss Elektr.-anlagen",
    "wof:placetype":"venue"
},
  "geometry": {"coordinates":[8.419197,49.133961],"type":"Point"}
}