{
  "type": "Feature",
  "properties": {
    "iso:country":"DE",
    "sg:address":"August-Bebel-Str. 183",
    "sg:city":"Bielefeld",
    "sg:phone":"+49 521/61583",
    "sg:postcode":"33602",
    "sg:province":"Nordrhein-Westfalen",
    "wof:name":"Lorenz Bornh\u00fctter Friseurbedarfs-grosshandel",
    "wof:placetype":"venue"
},
  "geometry": {"coordinates":[8.5391731262,52.0159683228],"type":"Point"}
}