{
  "type": "Feature",
  "properties": {
    "iso:country":"DE",
    "sg:address":"Karlstr. 14",
    "sg:city":"Dietzenbach",
    "sg:phone":"+49 6074/23542",
    "sg:postcode":"63128",
    "sg:province":"Hessen",
    "wof:name":"K. Wolf",
    "wof:placetype":"venue"
},
  "geometry": {"coordinates":[8.782417,50.008041],"type":"Point"}
}