{
  "type": "Feature",
  "properties": {
    "iso:country":"DE",
    "sg:address":"Schmiedestr. 1",
    "sg:city":"Pattensen",
    "sg:phone":"+49 5069/7386",
    "sg:postcode":"30982",
    "sg:province":"Niedersachsen",
    "wof:name":"Erich Rasch Architekt",
    "wof:placetype":"venue"
},
  "geometry": {"coordinates":[9.778722,52.193039],"type":"Point"}
}