{
  "type": "Feature",
  "properties": {
    "iso:country":"DE",
    "sg:address":"Vogtstr. 15",
    "sg:city":"Kempten",
    "sg:phone":"+49 831/18313",
    "sg:postcode":"87435",
    "sg:province":"Bayern",
    "wof:name":"Hannelore Agostoni",
    "wof:placetype":"venue"
},
  "geometry": {"coordinates":[10.3174285889,47.7255477905],"type":"Point"}
}