{
  "type": "Feature",
  "properties": {
    "iso:country":"DE",
    "sg:address":"Birkenstr. 32",
    "sg:city":"Neuental",
    "sg:postcode":"34599",
    "sg:province":"Hessen",
    "wof:name":"Gertrude Dr\u00f6fke",
    "wof:placetype":"venue"
},
  "geometry": {"coordinates":[9.232712,51.011612],"type":"Point"}
}