{
  "type": "Feature",
  "properties": {
    "iso:country":"DE",
    "sg:address":"Hauptstr. 31",
    "sg:city":"\u00dchlingen-Birkendorf",
    "sg:phone":"+49 7743/492",
    "sg:postcode":"79777",
    "sg:province":"Baden-W\u00fcrttemberg",
    "wof:name":"Edgar Probst",
    "wof:placetype":"venue"
},
  "geometry": {"coordinates":[8.31777668,47.7185935974],"type":"Point"}
}