{
  "type": "Feature",
  "properties": {
    "iso:country":"DE",
    "sg:address":"Industriestr. 8",
    "sg:city":"Berching",
    "sg:postcode":"92334",
    "sg:province":"Bayern",
    "wof:name":"Thrige Electric Gmbh",
    "wof:placetype":"venue"
},
  "geometry": {"coordinates":[11.435693,49.121338],"type":"Point"}
}