{
  "type": "Feature",
  "properties": {
    "iso:country":"DE",
    "sg:address":"Voithstr. 4",
    "sg:city":"Renningen",
    "sg:phone":"+49 7159/925010",
    "sg:postcode":"71272",
    "sg:province":"Baden-W\u00fcrttemberg",
    "wof:name":"Adolf Burger Gmbh",
    "wof:placetype":"venue"
},
  "geometry": {"coordinates":[8.901146,48.781925],"type":"Point"}
}