{
  "type": "Feature",
  "properties": {
    "iso:country":"DE",
    "sg:address":"Fuggerstr. 1",
    "sg:city":"Amberg",
    "sg:phone":"+49 9621/47160",
    "sg:postcode":"92224",
    "sg:province":"Bayern",
    "wof:name":"Quelle Ag",
    "wof:placetype":"venue"
},
  "geometry": {"coordinates":[11.8407278061,49.4426841736],"type":"Point"}
}