{
  "type": "Feature",
  "properties": {
    "iso:country":"DE",
    "sg:address":"Maybachstr. 3",
    "sg:city":"Aschaffenburg",
    "sg:phone":"+49 6021/423016",
    "sg:postcode":"63741",
    "sg:province":"Bayern",
    "wof:name":"Sperle Computersysteme Gmbh",
    "wof:placetype":"venue"
},
  "geometry": {"coordinates":[9.1125011444,49.9857063293],"type":"Point"}
}