{
  "type": "Feature",
  "properties": {
    "iso:country":"DE",
    "sg:address":"Ufke-Cremer-Str. 7",
    "sg:city":"Norden",
    "sg:phone":"+49 4931/3306",
    "sg:postcode":"26506",
    "sg:province":"Niedersachsen",
    "wof:name":"Herbert M\u00fcller",
    "wof:placetype":"venue"
},
  "geometry": {"coordinates":[7.1914668083,53.5975379944],"type":"Point"}
}