{
  "type": "Feature",
  "properties": {
    "iso:country":"DE",
    "sg:address":"Bahnhofstr. 5",
    "sg:city":"Welzow",
    "sg:postcode":"03119",
    "sg:province":"Brandenburg",
    "wof:name":"B. Mietzner",
    "wof:placetype":"venue"
},
  "geometry": {"coordinates":[14.1723966599,51.5802192688],"type":"Point"}
}