{
  "type": "Feature",
  "properties": {
    "iso:country":"DE",
    "sg:address":"Sonnenstr. 36",
    "sg:city":"Veitsh\u00f6chheim",
    "sg:phone":"+49 931/92537",
    "sg:postcode":"97209",
    "sg:province":"Bayern",
    "wof:name":"Georg Manninger Ingenieur",
    "wof:placetype":"venue"
},
  "geometry": {"coordinates":[9.8898258209,49.8336448669],"type":"Point"}
}