{
  "type": "Feature",
  "properties": {
    "iso:country":"DE",
    "sg:address":"Friedberger Str. 21",
    "sg:city":"Nidderau",
    "sg:phone":"+49 6187/21731",
    "sg:postcode":"61130",
    "sg:province":"Hessen",
    "wof:name":"Wolfgang Trajgermann",
    "wof:placetype":"venue"
},
  "geometry": {"coordinates":[8.8602304459,50.2414894104],"type":"Point"}
}