{
  "type": "Feature",
  "properties": {
    "iso:country":"DE",
    "sg:address":"Pfauenstr. 58",
    "sg:city":"Karlsruhe",
    "sg:phone":"+49 721/885234",
    "sg:postcode":"76199",
    "sg:province":"Baden-W\u00fcrttemberg",
    "wof:name":"O. We\u00dfbecher",
    "wof:placetype":"venue"
},
  "geometry": {"coordinates":[8.400786,48.968391],"type":"Point"}
}