{
  "type": "Feature",
  "properties": {
    "iso:country":"DE",
    "sg:address":"Nieper Str. 242",
    "sg:city":"Krefeld",
    "sg:phone":"+49 2151/561519",
    "sg:postcode":"47802",
    "sg:province":"Nordrhein-Westfalen",
    "wof:name":"Cafe-restaurant Lus Bell Inh. Kurt Tendick",
    "wof:placetype":"venue"
},
  "geometry": {"coordinates":[6.5571899414,51.3837928772],"type":"Point"}
}