{
  "type": "Feature",
  "properties": {
    "iso:country":"DE",
    "sg:address":"Mellumweg 6",
    "sg:city":"Wangerland",
    "sg:phone":"+49 4426/880",
    "sg:postcode":"26434",
    "sg:province":"Niedersachsen",
    "wof:name":"Apart-hotel Upstalsboom",
    "wof:placetype":"venue"
},
  "geometry": {"coordinates":[8.0244445801,53.7043609619],"type":"Point"}
}