{
  "type": "Feature",
  "properties": {
    "iso:country":"DE",
    "sg:address":"Schwarzerlenweg 85",
    "sg:city":"K\u00f6ln",
    "sg:phone":"+49 221/351095",
    "sg:postcode":"50999",
    "sg:province":"Nordrhein-Westfalen",
    "wof:name":"T\u00fcrk\u00fcfon Musikverlags Gmbh",
    "wof:placetype":"venue"
},
  "geometry": {"coordinates":[7.0000247955,50.8663635254],"type":"Point"}
}