{
  "type": "Feature",
  "properties": {
    "iso:country":"DE",
    "sg:address":"Bielefelder Str. 62-64",
    "sg:city":"Herford",
    "sg:phone":"+49 4927/363114",
    "sg:postcode":"32051",
    "sg:province":"Nordrhein-Westfalen",
    "wof:name":"Wemano Polsterm\u00d6belfabrik Gmbh",
    "wof:placetype":"venue"
},
  "geometry": {"coordinates":[7.8271131516,50.7154769897],"type":"Point"}
}