{
  "type": "Feature",
  "properties": {
    "iso:country":"DE",
    "sg:address":"Landauer Str. 106",
    "sg:city":"Zweibr\u00fccken",
    "sg:phone":"+49 6332/981240",
    "sg:postcode":"66482",
    "sg:province":"Rheinland-Pfalz",
    "wof:name":"U. Dubois Immobilien- Und Bautr\u00e4ger",
    "wof:placetype":"venue"
},
  "geometry": {"coordinates":[7.376395,49.251339],"type":"Point"}
}