{
  "type": "Feature",
  "properties": {
    "iso:country":"DE",
    "sg:address":"M\u00fcnchener Str. 50",
    "sg:city":"Essen",
    "sg:phone":"+49 201/821310",
    "sg:postcode":"45145",
    "sg:province":"Nordrhein-Westfalen",
    "wof:name":"Iga Architekturbaustoffe Gmbh & Co. Handels Kg",
    "wof:placetype":"venue"
},
  "geometry": {"coordinates":[6.994569,51.448292],"type":"Point"}
}