{
  "type": "Feature",
  "properties": {
    "iso:country":"DE",
    "sg:address":"Kupferstr. 67",
    "sg:city":"L\u00fcnen",
    "sg:phone":"+49 2306/25151",
    "sg:postcode":"44532",
    "sg:province":"Nordrhein-Westfalen",
    "wof:name":"Imo",
    "wof:placetype":"venue"
},
  "geometry": {"coordinates":[7.515748,51.605759],"type":"Point"}
}