{
  "type": "Feature",
  "properties": {
    "iso:country":"DE",
    "sg:address":"Damaschkestr. 4",
    "sg:city":"Berlin",
    "sg:phone":"+49 30/32709717",
    "sg:postcode":"10711",
    "sg:province":"Berlin",
    "wof:name":"Wolfgang Steinert Rechtsanwalt",
    "wof:placetype":"venue"
},
  "geometry": {"coordinates":[13.3019304276,52.49974823],"type":"Point"}
}