{
  "type": "Feature",
  "properties": {
    "iso:country":"DE",
    "sg:address":"Rigaer Str. 30",
    "sg:city":"Hennigsdorf",
    "sg:phone":"+49 3302/801008",
    "sg:postcode":"16761",
    "sg:province":"Brandenburg",
    "wof:name":"Sabine Weber",
    "wof:placetype":"venue"
},
  "geometry": {"coordinates":[13.196998,52.655628],"type":"Point"}
}