{
  "type": "Feature",
  "properties": {
    "iso:country":"DE",
    "sg:address":"Steingasse 16",
    "sg:city":"Heidelberg",
    "sg:phone":"+49 6221/23057",
    "sg:postcode":"69117",
    "sg:province":"Baden-W\u00fcrttemberg",
    "wof:name":"Luise Matthes",
    "wof:placetype":"venue"
},
  "geometry": {"coordinates":[8.7094287872,49.4125099182],"type":"Point"}
}