{
  "type": "Feature",
  "properties": {
    "iso:country":"DE",
    "sg:address":"W\u00fcllener Str. 21",
    "sg:city":"Vreden",
    "sg:phone":"+49 2564/4111",
    "sg:postcode":"48691",
    "sg:province":"Nordrhein-Westfalen",
    "wof:name":"Hannelore Roth",
    "wof:placetype":"venue"
},
  "geometry": {"coordinates":[6.8261160851,52.0360946655],"type":"Point"}
}