{
  "type": "Feature",
  "properties": {
    "iso:country":"DE",
    "sg:address":"Grabenschmiede 1",
    "sg:city":"Berchtesgaden",
    "sg:phone":"+49 8652/2031",
    "sg:postcode":"83471",
    "sg:province":"Bayern",
    "wof:name":"Michael Scheifler",
    "wof:placetype":"venue"
},
  "geometry": {"coordinates":[13.012773,47.639481],"type":"Point"}
}