{
  "type": "Feature",
  "properties": {
    "iso:country":"DE",
    "sg:address":"August-Bebel-Str. 46",
    "sg:city":"R\u00f6tha",
    "sg:postcode":"04571",
    "sg:province":"Sachsen",
    "wof:name":"Mediclean Home Care Service Gmbh",
    "wof:placetype":"venue"
},
  "geometry": {"coordinates":[12.41633,51.198803],"type":"Point"}
}