{
  "type": "Feature",
  "properties": {
    "iso:country":"DE",
    "sg:address":"Hansacker 26",
    "sg:city":"Westerstede",
    "sg:phone":"+49 4488/861802",
    "sg:postcode":"26655",
    "sg:province":"Niedersachsen",
    "wof:name":"Bohlen & Doyen Gmbh",
    "wof:placetype":"venue"
},
  "geometry": {"coordinates":[7.940680027,53.2687110901],"type":"Point"}
}