{
  "type": "Feature",
  "properties": {
    "iso:country":"DE",
    "sg:address":"Am Stadion 3b",
    "sg:city":"Ratingen",
    "sg:phone":"+49 2102/23001",
    "sg:postcode":"40878",
    "sg:province":"Nordrhein-Westfalen",
    "wof:name":"Lesaco Gesellschaft F\u00fcr Personalberatung Mbh",
    "wof:placetype":"venue"
},
  "geometry": {"coordinates":[6.8396549225,51.2945861816],"type":"Point"}
}