{
  "type": "Feature",
  "properties": {
    "iso:country":"DE",
    "sg:address":"Redmannstr. 7",
    "sg:city":"Dogern",
    "sg:phone":"+49 7751/4128",
    "sg:postcode":"79804",
    "sg:province":"Baden-W\u00fcrttemberg",
    "wof:name":"Heinz Francois",
    "wof:placetype":"venue"
},
  "geometry": {"coordinates":[8.1627178192,47.6075057983],"type":"Point"}
}