{
  "type": "Feature",
  "properties": {
    "iso:country":"DE",
    "sg:address":"Letterhausstr. 15",
    "sg:city":"Braunschweig",
    "sg:phone":"+49 531/514473",
    "sg:postcode":"38116",
    "sg:province":"Niedersachsen",
    "wof:name":"Wilfried Stauner",
    "wof:placetype":"venue"
},
  "geometry": {"coordinates":[10.4511528015,52.2810325623],"type":"Point"}
}