{
  "type": "Feature",
  "properties": {
    "iso:country":"DE",
    "sg:address":"Dieselstr. 5",
    "sg:city":"Neus\u00e4\u00df",
    "sg:phone":"+49 821/207600",
    "sg:postcode":"86356",
    "sg:province":"Bayern",
    "wof:name":"Megatronic Schwei\u00dfmaschinenbau Gmbh",
    "wof:placetype":"venue"
},
  "geometry": {"coordinates":[10.825215,48.39632],"type":"Point"}
}