{
  "type": "Feature",
  "properties": {
    "iso:country":"DE",
    "sg:address":"Amselweg 6",
    "sg:city":"M\u00f6rfelden-Walldorf",
    "sg:phone":"+49 6105/717417",
    "sg:postcode":"64546",
    "sg:province":"Hessen",
    "wof:name":"J\u00f6rg Heuser Rechtsanwalt",
    "wof:placetype":"venue"
},
  "geometry": {"coordinates":[8.5869483948,50.0009078979],"type":"Point"}
}