{
  "type": "Feature",
  "properties": {
    "iso:country":"DE",
    "sg:address":"Sportstr. 2",
    "sg:city":"Erftstadt",
    "sg:postcode":"50374",
    "sg:province":"Nordrhein-Westfalen",
    "wof:name":"Cac Dienstleistungsges. Mbh",
    "wof:placetype":"venue"
},
  "geometry": {"coordinates":[6.7704920769,50.8248519897],"type":"Point"}
}