{
  "type": "Feature",
  "properties": {
    "iso:country":"DE",
    "sg:address":"Heiligkreuzstr. 10",
    "sg:city":"Hechingen",
    "sg:postcode":"72379",
    "sg:province":"Baden-W\u00fcrttemberg",
    "wof:name":"Verkehrsverbund Neckar- Alb-donau Gmbh",
    "wof:placetype":"venue"
},
  "geometry": {"coordinates":[8.9641180038,48.3484840393],"type":"Point"}
}