{
  "type": "Feature",
  "properties": {
    "iso:country":"DE",
    "sg:address":"Bahnhofstr. 8",
    "sg:city":"Wolsfeld",
    "sg:phone":"+49 6568/7166",
    "sg:postcode":"54636",
    "sg:province":"Rheinland-Pfalz",
    "wof:name":"Ludwig Fuxen",
    "wof:placetype":"venue"
},
  "geometry": {"coordinates":[6.468432,49.908939],"type":"Point"}
}