{
  "type": "Feature",
  "properties": {
    "iso:country":"DE",
    "sg:address":"Vennstr. 51",
    "sg:city":"H\u00fcckelhoven",
    "sg:phone":"+49 2433/5566",
    "sg:postcode":"41836",
    "sg:province":"Nordrhein-Westfalen",
    "wof:name":"Gl\u00fcckauf-apotheke Peter Wsssing",
    "wof:placetype":"venue"
},
  "geometry": {"coordinates":[6.183828,51.064819],"type":"Point"}
}