{
  "type": "Feature",
  "properties": {
    "iso:country":"DE",
    "sg:address":"Mescheder Str. 24",
    "sg:city":"Sundern",
    "sg:phone":"+49 2933/3087",
    "sg:postcode":"59846",
    "sg:province":"Nordrhein-Westfalen",
    "wof:name":"Wkr-leuchten Werkst\u00e4tten F\u00fcr Kunsthandwerkliche",
    "wof:placetype":"venue"
},
  "geometry": {"coordinates":[8.009674,51.329857],"type":"Point"}
}