{
  "type": "Feature",
  "properties": {
    "iso:country":"DE",
    "sg:address":"Lister Meile 56",
    "sg:city":"Hannover",
    "sg:phone":"+49 511/317448",
    "sg:postcode":"30161",
    "sg:province":"Niedersachsen",
    "wof:name":"Blumen Wolf",
    "wof:placetype":"venue"
},
  "geometry": {"coordinates":[9.747896,52.385834],"type":"Point"}
}