{
  "type": "Feature",
  "properties": {
    "iso:country":"DE",
    "sg:address":"M\u00f6gendorf",
    "sg:city":"Bruck",
    "sg:phone":"+49 9434/1400",
    "sg:postcode":"92436",
    "sg:province":"Bayern",
    "wof:name":"J. Janka",
    "wof:placetype":"venue"
},
  "geometry": {"coordinates":[12.295608,49.262207],"type":"Point"}
}