{
  "type": "Feature",
  "properties": {
    "iso:country":"DE",
    "sg:address":"Hegeler-Wald-Str. 1 A",
    "sg:city":"Gro\u00dfenkneten",
    "sg:phone":"+49 4487/7090",
    "sg:postcode":"26197",
    "sg:province":"Niedersachsen",
    "wof:name":"Wz-bauunternehmen Gmbh",
    "wof:placetype":"venue"
},
  "geometry": {"coordinates":[8.266231,52.9897],"type":"Point"}
}