{
  "type": "Feature",
  "properties": {
    "iso:country":"DE",
    "sg:address":"Heyestr. 123",
    "sg:city":"D\u00fcsseldorf",
    "sg:phone":"+49 4921/1283669",
    "sg:postcode":"40625",
    "sg:province":"Nordrhein-Westfalen",
    "wof:name":"Herbert Stengel Gmbh",
    "wof:placetype":"venue"
},
  "geometry": {"coordinates":[6.8637490273,51.224647522],"type":"Point"}
}