{
  "type": "Feature",
  "properties": {
    "iso:country":"DE",
    "sg:address":"Mainstr. 111",
    "sg:city":"Neuss",
    "sg:phone":"+49 2137/999747",
    "sg:postcode":"41469",
    "sg:province":"Nordrhein-Westfalen",
    "wof:name":"K\u00fchlhaus D\u00fcsseldorf",
    "wof:placetype":"venue"
},
  "geometry": {"coordinates":[6.744884,51.151394],"type":"Point"}
}