{
  "type": "Feature",
  "properties": {
    "iso:country":"DE",
    "sg:address":"Hauptstr. 16",
    "sg:city":"\u00dcberlingen",
    "sg:phone":"+49 7553/408",
    "sg:postcode":"88662",
    "sg:province":"Baden-W\u00fcrttemberg",
    "wof:name":"Manfred K\u00f6bach",
    "wof:placetype":"venue"
},
  "geometry": {"coordinates":[9.2403097153,47.8007011414],"type":"Point"}
}