{
  "type": "Feature",
  "properties": {
    "iso:country":"DE",
    "sg:address":"Leierndorfer Str. 45",
    "sg:city":"Langquaid",
    "sg:phone":"+49 9452/1055",
    "sg:postcode":"84085",
    "sg:province":"Bayern",
    "wof:name":"Lauerer Planungs- Gmbh",
    "wof:placetype":"venue"
},
  "geometry": {"coordinates":[12.0572004318,48.8247795105],"type":"Point"}
}