{
  "type": "Feature",
  "properties": {
    "iso:country":"DE",
    "sg:address":"Oelsnitzer Str. 40",
    "sg:city":"Neustadt",
    "sg:phone":"+49 3745/73210",
    "sg:postcode":"08223",
    "sg:province":"Sachsen",
    "wof:name":"A & F Bautr\u00e4ger- Und Baubetreuungsgesellschaft Mbh",
    "wof:placetype":"venue"
},
  "geometry": {"coordinates":[12.332458,50.461346],"type":"Point"}
}