{
  "type": "Feature",
  "properties": {
    "iso:country":"DE",
    "sg:address":"Rudolf-Diesel-Str. 37",
    "sg:city":"Murr",
    "sg:phone":"+49 7144/894954",
    "sg:postcode":"71711",
    "sg:province":"Baden-W\u00fcrttemberg",
    "wof:name":"Ktl Kaczmarek Und Logistik Gmbh",
    "wof:placetype":"venue"
},
  "geometry": {"coordinates":[9.236063,48.953991],"type":"Point"}
}