{
  "type": "Feature",
  "properties": {
    "iso:country":"DE",
    "sg:address":"Bernburger Str. 9",
    "sg:city":"Halle",
    "sg:phone":"+49 345/5231851",
    "sg:postcode":"06108",
    "sg:province":"Sachsen-Anhalt",
    "wof:name":"Horst Brohmer",
    "wof:placetype":"venue"
},
  "geometry": {"coordinates":[11.96372,51.490509],"type":"Point"}
}