{
  "type": "Feature",
  "properties": {
    "iso:country":"DE",
    "sg:address":"Lengenfelder Str. 4",
    "sg:city":"Hirschfeld",
    "sg:phone":"+49 37607/5291",
    "sg:postcode":"08144",
    "sg:province":"Sachsen",
    "wof:name":"Voigtsgr\u00fcn",
    "wof:placetype":"venue"
},
  "geometry": {"coordinates":[12.4323425293,50.6339988708],"type":"Point"}
}