{
  "type": "Feature",
  "properties": {
    "iso:country":"DE",
    "sg:address":"Am Brill 18",
    "sg:city":"Bremen",
    "sg:phone":"+49 421/1633802",
    "sg:postcode":"28195",
    "sg:province":"Bremen",
    "wof:name":"Schnebbe Heuser Und Partner",
    "wof:placetype":"venue"
},
  "geometry": {"coordinates":[8.7995853424,53.0790405273],"type":"Point"}
}