{
  "type": "Feature",
  "properties": {
    "iso:country":"DE",
    "sg:address":"Ernst-Th\u00e4lmann-Str. 19",
    "sg:city":"Unterwellenborn",
    "sg:phone":"+49 3671/461496",
    "sg:postcode":"07333",
    "sg:province":"Th\u00fcringen",
    "wof:name":"Nowinform Gmbh",
    "wof:placetype":"venue"
},
  "geometry": {"coordinates":[11.432512,50.657581],"type":"Point"}
}