{
  "type": "Feature",
  "properties": {
    "iso:country":"DE",
    "sg:address":"Hauptstr. 118",
    "sg:city":"Warnstedt",
    "sg:phone":"+49 3947/41050",
    "sg:postcode":"06502",
    "sg:province":"Sachsen-Anhalt",
    "wof:name":"Hotel Warnstedter Krug",
    "wof:placetype":"venue"
},
  "geometry": {"coordinates":[11.0570030212,51.7733078003],"type":"Point"}
}