{
  "type": "Feature",
  "properties": {
    "iso:country":"DE",
    "sg:address":"Uferstr. 46",
    "sg:city":"Chemnitz",
    "sg:phone":"+49 371/55894",
    "sg:postcode":"09126",
    "sg:province":"Sachsen",
    "wof:name":"Strago-technikhandelsges. Mbh",
    "wof:placetype":"venue"
},
  "geometry": {"coordinates":[12.938385,50.830158],"type":"Point"}
}