{
  "type": "Feature",
  "properties": {
    "iso:country":"DE",
    "sg:address":"Lotter Str. 102",
    "sg:city":"Osnabr\u00fcck",
    "sg:phone":"+49 541/42100",
    "sg:postcode":"49078",
    "sg:province":"Niedersachsen",
    "wof:name":"Klekamp Gmbh & Co. Kg",
    "wof:placetype":"venue"
},
  "geometry": {"coordinates":[8.029455,52.274643],"type":"Point"}
}