{
  "type": "Feature",
  "properties": {
    "iso:country":"DE",
    "sg:address":"Bahnhofstr. 2",
    "sg:city":"Gerabronn",
    "sg:phone":"+49 7952/925050",
    "sg:postcode":"74582",
    "sg:province":"Baden-W\u00fcrttemberg",
    "wof:name":"Gerabronn-apotheke",
    "wof:placetype":"venue"
},
  "geometry": {"coordinates":[9.922311,49.253517],"type":"Point"}
}