{
  "type": "Feature",
  "properties": {
    "iso:country":"DE",
    "sg:address":"Biebricher Str. 69",
    "sg:city":"Wiesbaden",
    "sg:phone":"+49 611/6760",
    "sg:postcode":"65205",
    "sg:province":"Hessen",
    "wof:name":"Dyckerhoff Rhein-main Beteiligungsges. Mbh & Co. Kg",
    "wof:placetype":"venue"
},
  "geometry": {"coordinates":[8.241671,50.06255],"type":"Point"}
}