{
  "type": "Feature",
  "properties": {
    "iso:country":"DE",
    "sg:address":"Weinbergstr. 8",
    "sg:city":"Ettenheim",
    "sg:phone":"+49 7822/1593",
    "sg:postcode":"77955",
    "sg:province":"Baden-W\u00fcrttemberg",
    "wof:name":"Rolf Scherer",
    "wof:placetype":"venue"
},
  "geometry": {"coordinates":[7.862734,48.265663],"type":"Point"}
}