{
  "type": "Feature",
  "properties": {
    "iso:country":"DE",
    "sg:address":"Kulmstr. 3",
    "sg:city":"Seebad Heringsdorf",
    "sg:postcode":"17424",
    "sg:province":"Mecklenburg-Vorpommern",
    "wof:name":"Hoffmann & Laggner Weinhandel Und Feinkost Gmbh",
    "wof:placetype":"venue"
},
  "geometry": {"coordinates":[14.1660823822,53.957408905],"type":"Point"}
}