{
  "type": "Feature",
  "properties": {
    "iso:country":"DE",
    "sg:address":"Schlo\u00dfplatz 8 b",
    "sg:city":"B\u00fcckeburg",
    "sg:phone":"+49 5722/917114",
    "sg:postcode":"31675",
    "sg:province":"Niedersachsen",
    "wof:name":"Philipps Gmbh",
    "wof:placetype":"venue"
},
  "geometry": {"coordinates":[9.04570961,52.2604789734],"type":"Point"}
}