{
  "type": "Feature",
  "properties": {
    "iso:country":"DE",
    "sg:address":"M\u00f6hlerstr. 7",
    "sg:city":"Herzebrock-Clarholz",
    "sg:phone":"+49 5245/2037",
    "sg:postcode":"33442",
    "sg:province":"Nordrhein-Westfalen",
    "wof:name":"Heinrich Schnitker",
    "wof:placetype":"venue"
},
  "geometry": {"coordinates":[8.2153902054,51.8739356995],"type":"Point"}
}