{
  "type": "Feature",
  "properties": {
    "iso:country":"DE",
    "sg:address":"Saseler Chaussee 49",
    "sg:city":"Hamburg",
    "sg:phone":"+49 40/6327410",
    "sg:postcode":"22391",
    "sg:province":"Hamburg",
    "wof:name":"Wolfgang Friedberg",
    "wof:placetype":"venue"
},
  "geometry": {"coordinates":[10.0931873322,53.6373405457],"type":"Point"}
}