{
  "type": "Feature",
  "properties": {
    "iso:country":"DE",
    "sg:address":"Weiherweg 3",
    "sg:city":"Bad W\u00f6rishofen",
    "sg:phone":"+49 8247/96930",
    "sg:postcode":"86825",
    "sg:province":"Bayern",
    "wof:name":"Christian Reisberger Masseur",
    "wof:placetype":"venue"
},
  "geometry": {"coordinates":[10.592197,47.996162],"type":"Point"}
}