{
  "type": "Feature",
  "properties": {
    "iso:country":"DE",
    "sg:address":"Schanzenstr. 93",
    "sg:city":"Hamburg",
    "sg:phone":"+49 40/434803",
    "sg:postcode":"20357",
    "sg:province":"Hamburg",
    "wof:name":"Frank Und Frei",
    "wof:placetype":"venue"
},
  "geometry": {"coordinates":[9.9652662277,53.5631752014],"type":"Point"}
}