{
  "type": "Feature",
  "properties": {
    "iso:country":"DE",
    "sg:address":"Dorfring 2",
    "sg:city":"Georgensgm\u00fcnd",
    "sg:phone":"+49 9172/929",
    "sg:postcode":"91166",
    "sg:province":"Bayern",
    "wof:name":"Wolfgang Gsaenger Architekt",
    "wof:placetype":"venue"
},
  "geometry": {"coordinates":[11.023165,49.186504],"type":"Point"}
}