{
  "type": "Feature",
  "properties": {
    "iso:country":"DE",
    "sg:address":"Kieler Str. 41",
    "sg:city":"Raisdorf",
    "sg:phone":"+49 4307/6981",
    "sg:postcode":"24223",
    "sg:province":"Schleswig-Holstein",
    "wof:name":"\u00d6re Bio-protect Biologischer Pflanzenschutz Gmbh",
    "wof:placetype":"venue"
},
  "geometry": {"coordinates":[10.231505394,54.2868499756],"type":"Point"}
}