{
  "type": "Feature",
  "properties": {
    "iso:country":"DE",
    "sg:address":"Steinweg 5",
    "sg:city":"Hachenburg",
    "sg:phone":"+49 2662/6335",
    "sg:postcode":"57627",
    "sg:province":"Rheinland-Pfalz",
    "wof:name":"Kurt Sartor",
    "wof:placetype":"venue"
},
  "geometry": {"coordinates":[7.8212981224,50.6606674194],"type":"Point"}
}