{
  "type": "Feature",
  "properties": {
    "iso:country":"DE",
    "sg:address":"Schwalbenweg 3",
    "sg:city":"Br\u00fcggen",
    "sg:phone":"+49 2163/59536",
    "sg:postcode":"41379",
    "sg:province":"Nordrhein-Westfalen",
    "wof:name":"Heco Putz- Und Stuck Gmbh",
    "wof:placetype":"venue"
},
  "geometry": {"coordinates":[6.172357,51.243771],"type":"Point"}
}