{
  "type": "Feature",
  "properties": {
    "iso:country":"DE",
    "sg:address":"Schilfgrund 5",
    "sg:city":"Hamburg",
    "sg:phone":"+49 40/6932099",
    "sg:postcode":"22047",
    "sg:province":"Hamburg",
    "wof:name":"Heinz Moeller Gmbh, Hamburg - Wandsbek",
    "wof:placetype":"venue"
},
  "geometry": {"coordinates":[10.0945034027,53.5953407288],"type":"Point"}
}