{
  "type": "Feature",
  "properties": {
    "iso:country":"DE",
    "sg:address":"Westendstr. 51",
    "sg:city":"M\u00fcnchen",
    "sg:phone":"+49 89/501007",
    "sg:postcode":"80339",
    "sg:province":"Bayern",
    "wof:name":"The Art Of Plants Handels Gmbh",
    "wof:placetype":"venue"
},
  "geometry": {"coordinates":[11.544317,48.138248],"type":"Point"}
}