{
  "type": "Feature",
  "properties": {
    "iso:country":"DE",
    "sg:address":"Kirrberger Str.",
    "sg:city":"Homburg",
    "sg:phone":"+49 6841/5393",
    "sg:postcode":"66424",
    "sg:province":"Saarland",
    "wof:name":"Emilienruhe",
    "wof:placetype":"venue"
},
  "geometry": {"coordinates":[7.3427929878,49.3153266907],"type":"Point"}
}