{
  "type": "Feature",
  "properties": {
    "iso:country":"DE",
    "sg:address":"Hauptstr. 87",
    "sg:city":"M\u00fcllheim",
    "sg:phone":"+49 7631/14334",
    "sg:postcode":"79379",
    "sg:province":"Baden-W\u00fcrttemberg",
    "wof:name":"Giovanni Falcone",
    "wof:placetype":"venue"
},
  "geometry": {"coordinates":[7.6235508919,47.8075752258],"type":"Point"}
}