{
  "type": "Feature",
  "properties": {
    "iso:country":"DE",
    "sg:address":"Hildenbrandstr 18",
    "sg:city":"G\u00f6ppingen",
    "sg:phone":"+49 7161/2060",
    "sg:postcode":"73035",
    "sg:province":"Baden-W\u00fcrttemberg",
    "wof:name":"Kleemann + Reiner Maschinen- Und Anlagenbau Vertriebs Gmbh",
    "wof:placetype":"venue"
},
  "geometry": {"coordinates":[9.667134,48.718693],"type":"Point"}
}