{
  "type": "Feature",
  "properties": {
    "iso:country":"DE",
    "sg:address":"Weinmarkt 14",
    "sg:city":"Memmingen",
    "sg:phone":"+49 8331/47111",
    "sg:postcode":"87700",
    "sg:province":"Bayern",
    "wof:name":"G\u00f6ppel Lederwaren",
    "wof:placetype":"venue"
},
  "geometry": {"coordinates":[10.180917,47.984833],"type":"Point"}
}