{
  "type": "Feature",
  "properties": {
    "iso:country":"DE",
    "sg:address":"Marienborner Str. 134",
    "sg:city":"Siegen",
    "sg:phone":"+49 271/62553",
    "sg:postcode":"57074",
    "sg:province":"Nordrhein-Westfalen",
    "wof:name":"Ulrike B\u00fcdenbender Verwaltungs Gmbh",
    "wof:placetype":"venue"
},
  "geometry": {"coordinates":[8.035949707,50.8752670288],"type":"Point"}
}