{
  "type": "Feature",
  "properties": {
    "iso:country":"DE",
    "sg:address":"Ursulastr. 3",
    "sg:city":"M\u00fcnchen",
    "sg:phone":"+49 89/332100",
    "sg:postcode":"80802",
    "sg:province":"Bayern",
    "wof:name":"Restaurant Schwabinger Stube",
    "wof:placetype":"venue"
},
  "geometry": {"coordinates":[11.5905151367,48.1612930298],"type":"Point"}
}