{
  "type": "Feature",
  "properties": {
    "iso:country":"DE",
    "sg:address":"Marktgasse 3",
    "sg:city":"W\u00fcrzburg",
    "sg:phone":"+49 931/354880",
    "sg:postcode":"97070",
    "sg:province":"Bayern",
    "wof:name":"Karl Brandstetter Kg",
    "wof:placetype":"venue"
},
  "geometry": {"coordinates":[9.92836,49.794807],"type":"Point"}
}