{
  "type": "Feature",
  "properties": {
    "iso:country":"DE",
    "sg:address":"Stubenstr. 3",
    "sg:city":"Heilbad Heiligenstadt",
    "sg:phone":"+49 3606/2956",
    "sg:postcode":"37308",
    "sg:province":"Th\u00fcringen",
    "wof:name":"Fleischerei",
    "wof:placetype":"venue"
},
  "geometry": {"coordinates":[10.1348991394,51.3787574768],"type":"Point"}
}