{
  "type": "Feature",
  "properties": {
    "iso:country":"DE",
    "sg:address":"Pestalozzistr. 33a",
    "sg:city":"Angerm\u00fcnde",
    "sg:postcode":"16278",
    "sg:province":"Brandenburg",
    "wof:name":"Wohnungsgenossenschaft Uckermark Eg",
    "wof:placetype":"venue"
},
  "geometry": {"coordinates":[13.9814949036,53.0165901184],"type":"Point"}
}