{
  "type": "Feature",
  "properties": {
    "iso:country":"DE",
    "sg:address":"Cranachweg 5",
    "sg:city":"G\u00f6ppingen",
    "sg:phone":"+49 7161/979635",
    "sg:postcode":"73033",
    "sg:province":"Baden-W\u00fcrttemberg",
    "wof:name":"Daniel Maurer",
    "wof:placetype":"venue"
},
  "geometry": {"coordinates":[9.6767244339,48.7044563293],"type":"Point"}
}