{
  "type": "Feature",
  "properties": {
    "iso:country":"DE",
    "sg:address":"Pariser Str. 44",
    "sg:city":"W\u00f6rrstadt",
    "sg:phone":"+49 6732/2621",
    "sg:postcode":"55286",
    "sg:province":"Rheinland-Pfalz",
    "wof:name":"Kath. Pfarramt St. Philipp Und Jakob",
    "wof:placetype":"venue"
},
  "geometry": {"coordinates":[8.1187801361,49.8386764526],"type":"Point"}
}