{
  "type": "Feature",
  "properties": {
    "iso:country":"DE",
    "sg:address":"Am Wei\u00dfen Berg 11",
    "sg:city":"H\u00fcnfelden",
    "sg:phone":"+49 6438/6036",
    "sg:postcode":"65597",
    "sg:province":"Hessen",
    "wof:name":"Eugen Chojnicki",
    "wof:placetype":"venue"
},
  "geometry": {"coordinates":[8.1615247726,50.3120918274],"type":"Point"}
}