{
  "type": "Feature",
  "properties": {
    "iso:country":"DE",
    "sg:address":"Schlo\u00df 5",
    "sg:city":"Philippsthal",
    "sg:phone":"+49 6620/6100",
    "sg:postcode":"36269",
    "sg:province":"Hessen",
    "wof:name":"Optik Am Schlo\u00df Lotz Kg",
    "wof:placetype":"venue"
},
  "geometry": {"coordinates":[10.0059108734,50.8416290283],"type":"Point"}
}