{
  "type": "Feature",
  "properties": {
    "iso:country":"DE",
    "sg:address":"Am Anger 2",
    "sg:city":"Krauschwitz",
    "sg:postcode":"06682",
    "sg:province":"Sachsen-Anhalt",
    "wof:name":"Evangelisch-lutherische Kirche Kistritz",
    "wof:placetype":"venue"
},
  "geometry": {"coordinates":[11.9670343399,51.1044921875],"type":"Point"}
}