{
  "type": "Feature",
  "properties": {
    "iso:country":"DE",
    "sg:address":"D\u00fcppelstr. 22",
    "sg:city":"Berlin",
    "sg:phone":"+49 30/8558650",
    "sg:postcode":"12163",
    "sg:province":"Berlin",
    "wof:name":"Lehmberg Elektroinstallations Gmbh",
    "wof:placetype":"venue"
},
  "geometry": {"coordinates":[13.32804,52.460995],"type":"Point"}
}