{
  "type": "Feature",
  "properties": {
    "iso:country":"DE",
    "sg:address":"Hundsm\u00fchler Str. 95",
    "sg:city":"Oldenburg",
    "sg:phone":"+49 441/503707",
    "sg:postcode":"26131",
    "sg:province":"Niedersachsen",
    "wof:name":"Ingomar Lenz Elektro",
    "wof:placetype":"venue"
},
  "geometry": {"coordinates":[8.190582,53.126041],"type":"Point"}
}