{
  "type": "Feature",
  "properties": {
    "iso:country":"DE",
    "sg:address":"Hauptstr. 14",
    "sg:city":"Bad Soden-Salm\u00fcnster",
    "sg:phone":"+49 6056/8573",
    "sg:postcode":"63628",
    "sg:province":"Hessen",
    "wof:name":"Friedrich Weber",
    "wof:placetype":"venue"
},
  "geometry": {"coordinates":[9.37266922,50.3208503723],"type":"Point"}
}