{
  "type": "Feature",
  "properties": {
    "iso:country":"DE",
    "sg:address":"Klammenstr. 11",
    "sg:city":"Sternenfels",
    "sg:phone":"+49 7043/8879",
    "sg:postcode":"75447",
    "sg:province":"Baden-W\u00fcrttemberg",
    "wof:name":"Brennerei Steinle",
    "wof:placetype":"venue"
},
  "geometry": {"coordinates":[8.8542470932,49.0271263123],"type":"Point"}
}