{
  "type": "Feature",
  "properties": {
    "iso:country":"DE",
    "sg:address":"Dorfplatz 3",
    "sg:city":"Ammerthal",
    "sg:phone":"+49 9628/91313",
    "sg:postcode":"92260",
    "sg:province":"Bayern",
    "wof:name":"Weber",
    "wof:placetype":"venue"
},
  "geometry": {"coordinates":[11.7594022751,49.4402427673],"type":"Point"}
}