{
  "type": "Feature",
  "properties": {
    "iso:country":"DE",
    "sg:address":"Max-Planck-Str. 24",
    "sg:city":"Heilbronn",
    "sg:phone":"+49 7131/577547",
    "sg:postcode":"74081",
    "sg:province":"Baden-W\u00fcrttemberg",
    "wof:name":"Horst Sch\u00fcdde",
    "wof:placetype":"venue"
},
  "geometry": {"coordinates":[9.204899,49.121166],"type":"Point"}
}