{
  "type": "Feature",
  "properties": {
    "iso:country":"DE",
    "sg:address":"Herrngartenstr. 26",
    "sg:city":"Schlitz",
    "sg:phone":"+49 6642/1501",
    "sg:postcode":"36110",
    "sg:province":"Hessen",
    "wof:name":"Gerhard Kalmbach",
    "wof:placetype":"venue"
},
  "geometry": {"coordinates":[9.556663,50.670254],"type":"Point"}
}