{
  "type": "Feature",
  "properties": {
    "iso:country":"DE",
    "sg:address":"Tenterweg 126",
    "sg:city":"Ratingen",
    "sg:phone":"+49 2102/49646",
    "sg:postcode":"40885",
    "sg:province":"Nordrhein-Westfalen",
    "wof:name":"Magicx Gmbh",
    "wof:placetype":"venue"
},
  "geometry": {"coordinates":[6.851041,51.35952],"type":"Point"}
}