{
  "type": "Feature",
  "properties": {
    "iso:country":"DE",
    "sg:address":"S\u00fcdliche M\u00fcnchner Str. 30",
    "sg:city":"Gr\u00fcnwald",
    "sg:phone":"+49 89/6490600",
    "sg:postcode":"82031",
    "sg:province":"Bayern",
    "wof:name":"Ail Beteiligungs- Verwaltungs Gmbh",
    "wof:placetype":"venue"
},
  "geometry": {"coordinates":[11.5295448303,48.0460891724],"type":"Point"}
}