{
  "type": "Feature",
  "properties": {
    "iso:country":"DE",
    "sg:address":"Gartenstr. 15",
    "sg:city":"Gengenbach",
    "sg:phone":"+49 7803/3791",
    "sg:postcode":"77723",
    "sg:province":"Baden-W\u00fcrttemberg",
    "wof:name":"Rosel Pertschy",
    "wof:placetype":"venue"
},
  "geometry": {"coordinates":[8.012154,48.40519],"type":"Point"}
}