{
  "type": "Feature",
  "properties": {
    "iso:country":"DE",
    "sg:address":"Heinrich-L\u00fcbke-Str. 7",
    "sg:city":"Frankfurt",
    "sg:phone":"+49 69/761054",
    "sg:postcode":"60488",
    "sg:province":"Hessen",
    "wof:name":"Ebelfeld-apotheke",
    "wof:placetype":"venue"
},
  "geometry": {"coordinates":[8.610688,50.141556],"type":"Point"}
}