{
  "type": "Feature",
  "properties": {
    "iso:country":"DE",
    "sg:address":"Unter der Herrenbr\u00fccke 1",
    "sg:city":"L\u00fcbeck",
    "sg:phone":"+49 451/394397",
    "sg:postcode":"23569",
    "sg:province":"Schleswig-Holstein",
    "wof:name":"Hotel Zum Wei\u00dfen Stein",
    "wof:placetype":"venue"
},
  "geometry": {"coordinates":[10.7764129639,53.9023208618],"type":"Point"}
}