{
  "type": "Feature",
  "properties": {
    "iso:country":"DE",
    "sg:address":"Am Holzplatz 7",
    "sg:city":"Kleinblittersdorf",
    "sg:phone":"+49 6805/4048",
    "sg:postcode":"66271",
    "sg:province":"Saarland",
    "wof:name":"S.u.g. Ries Gmbh",
    "wof:placetype":"venue"
},
  "geometry": {"coordinates":[7.0497899055,49.1195602417],"type":"Point"}
}