{
  "type": "Feature",
  "properties": {
    "iso:country":"DE",
    "sg:address":"Weitzm\u00fchlener Str. 66",
    "sg:city":"Verden",
    "sg:phone":"+49 4231/63037",
    "sg:postcode":"27283",
    "sg:province":"Niedersachsen",
    "wof:name":"Herbert Grimme",
    "wof:placetype":"venue"
},
  "geometry": {"coordinates":[9.283433,52.912132],"type":"Point"}
}