{
  "type": "Feature",
  "properties": {
    "iso:country":"DE",
    "sg:address":"Cleveschestr. 8",
    "sg:city":"Lippstadt",
    "sg:phone":"+49 2941/60104",
    "sg:postcode":"59555",
    "sg:province":"Nordrhein-Westfalen",
    "wof:name":"K. S\u00fcwolto",
    "wof:placetype":"venue"
},
  "geometry": {"coordinates":[8.32882,51.679531],"type":"Point"}
}