{
  "type": "Feature",
  "properties": {
    "iso:country":"DE",
    "sg:address":"Achter de Weiden 22",
    "sg:city":"Schenefeld",
    "sg:phone":"+49 40/8302684",
    "sg:postcode":"22869",
    "sg:province":"Schleswig-Holstein",
    "wof:name":"Ohlsen",
    "wof:placetype":"venue"
},
  "geometry": {"coordinates":[9.828504,53.60619],"type":"Point"}
}