{
  "type": "Feature",
  "properties": {
    "iso:country":"DE",
    "sg:address":"Sch\u00e4ubleweg 4",
    "sg:city":"Ehrenkirchen",
    "sg:phone":"+49 7633/5229",
    "sg:postcode":"79238",
    "sg:province":"Baden-W\u00fcrttemberg",
    "wof:name":"Hans Reiff Architekt",
    "wof:placetype":"venue"
},
  "geometry": {"coordinates":[7.76041,47.91116],"type":"Point"}
}