{
  "type": "Feature",
  "properties": {
    "iso:country":"DE",
    "sg:city":"Eichenbarleben",
    "sg:phone":"+49 39206/53582",
    "sg:postcode":"39167",
    "sg:province":"Sachsen-Anhalt",
    "wof:name":"Eiscafe Adria Gmbh",
    "wof:placetype":"venue"
},
  "geometry": {"coordinates":[11.402654,52.16748],"type":"Point"}
}