{
  "type": "Feature",
  "properties": {
    "iso:country":"DE",
    "sg:address":"Bauernstr. 20",
    "sg:city":"Schirgiswalde",
    "sg:phone":"+49 3592/32121",
    "sg:postcode":"02681",
    "sg:province":"Sachsen",
    "wof:name":"Fup Ag",
    "wof:placetype":"venue"
},
  "geometry": {"coordinates":[14.4200372696,51.0763130188],"type":"Point"}
}