{
  "type": "Feature",
  "properties": {
    "iso:country":"DE",
    "sg:address":"Seestr. 6",
    "sg:city":"Sternberg",
    "sg:phone":"+49 3847/2817",
    "sg:postcode":"19406",
    "sg:province":"Mecklenburg-Vorpommern",
    "wof:name":"Adelheid Pilz",
    "wof:placetype":"venue"
},
  "geometry": {"coordinates":[11.830425,53.714348],"type":"Point"}
}