{
  "type": "Feature",
  "properties": {
    "iso:country":"DE",
    "sg:address":"Vorderorbroich 99",
    "sg:city":"Krefeld",
    "sg:phone":"+49 2151/734193",
    "sg:postcode":"47839",
    "sg:province":"Nordrhein-Westfalen",
    "wof:name":"Willi Korff",
    "wof:placetype":"venue"
},
  "geometry": {"coordinates":[6.4847240448,51.3888053894],"type":"Point"}
}