{
  "type": "Feature",
  "properties": {
    "iso:country":"DE",
    "sg:address":"Hintergasse 18",
    "sg:city":"Roschbach",
    "sg:phone":"+49 6323/3201",
    "sg:postcode":"76835",
    "sg:province":"Rheinland-Pfalz",
    "wof:name":"Manfred Schlegel",
    "wof:placetype":"venue"
},
  "geometry": {"coordinates":[8.1169881821,49.2471504211],"type":"Point"}
}