{
  "type": "Feature",
  "properties": {
    "iso:country":"DE",
    "sg:address":"Bucher Str. 61",
    "sg:city":"N\u00fcrnberg",
    "sg:phone":"+49 911/339689",
    "sg:postcode":"90419",
    "sg:province":"Bayern",
    "wof:name":"Costei Kaffee Und Tee Gmbh & Co.",
    "wof:placetype":"venue"
},
  "geometry": {"coordinates":[11.0707015991,49.462890625],"type":"Point"}
}