{
  "type": "Feature",
  "properties": {
    "iso:country":"DE",
    "sg:address":"Dr.-Patt-Str. 3",
    "sg:city":"Stockstadt",
    "sg:phone":"+49 6027/208740",
    "sg:postcode":"63811",
    "sg:province":"Bayern",
    "wof:name":"Baake & Bartosch Gmbh Druckereibetrieb",
    "wof:placetype":"venue"
},
  "geometry": {"coordinates":[9.079208,49.970833],"type":"Point"}
}