{
  "type": "Feature",
  "properties": {
    "iso:country":"DE",
    "sg:address":"Ringmarkt 13",
    "sg:city":"Neuwied",
    "sg:phone":"+49 2631/21606",
    "sg:postcode":"56564",
    "sg:province":"Rheinland-Pfalz",
    "wof:name":"Dr. Med. Bernd Paulus",
    "wof:placetype":"venue"
},
  "geometry": {"coordinates":[7.4682998657,50.4336395264],"type":"Point"}
}