{
  "type": "Feature",
  "properties": {
    "iso:country":"DE",
    "sg:address":"Dauner Str. 14",
    "sg:city":"H\u00f6rschhausen",
    "sg:phone":"+49 2692/8261",
    "sg:postcode":"54552",
    "sg:province":"Rheinland-Pfalz",
    "wof:name":"Peter Ueberhofen",
    "wof:placetype":"venue"
},
  "geometry": {"coordinates":[6.934825,50.243309],"type":"Point"}
}