{
  "type": "Feature",
  "properties": {
    "iso:country":"DE",
    "sg:address":"Gleinaer Str. 42",
    "sg:city":"Zeitz",
    "sg:postcode":"06712",
    "sg:province":"Sachsen-Anhalt",
    "wof:name":"Fitness Und Fun Im Biber Gym Fitnessclub",
    "wof:placetype":"venue"
},
  "geometry": {"coordinates":[12.14777,51.045448],"type":"Point"}
}