{
  "type": "Feature",
  "properties": {
    "iso:country":"DE",
    "sg:address":"Ammonstr. 70",
    "sg:city":"Dresden",
    "sg:phone":"+49 351/4906062",
    "sg:postcode":"01067",
    "sg:province":"Sachsen",
    "wof:name":"R. Winkler",
    "wof:placetype":"venue"
},
  "geometry": {"coordinates":[13.7214622498,51.048122406],"type":"Point"}
}