{
  "type": "Feature",
  "properties": {
    "iso:country":"DE",
    "sg:address":"Walter-Markov-Ring 28",
    "sg:city":"Leipzig",
    "sg:phone":"+49 34297/43406",
    "sg:postcode":"04288",
    "sg:province":"Sachsen",
    "wof:name":"Ortwin Kober",
    "wof:placetype":"venue"
},
  "geometry": {"coordinates":[12.454273,51.312695],"type":"Point"}
}