{
  "type": "Feature",
  "properties": {
    "iso:country":"DE",
    "sg:address":"Nachtweide 1a",
    "sg:city":"Nauheim",
    "sg:phone":"+49 6152/58025",
    "sg:postcode":"64569",
    "sg:province":"Hessen",
    "wof:name":"La Fattonia",
    "wof:placetype":"venue"
},
  "geometry": {"coordinates":[8.4697265625,49.9595718384],"type":"Point"}
}