{
  "type": "Feature",
  "properties": {
    "iso:country":"DE",
    "sg:address":"Gie\u00dfener Str. 24",
    "sg:city":"Butzbach",
    "sg:phone":"+49 6033/63136",
    "sg:postcode":"35510",
    "sg:province":"Hessen",
    "wof:name":"Ewald Damm",
    "wof:placetype":"venue"
},
  "geometry": {"coordinates":[8.651495,50.46352],"type":"Point"}
}