{
  "type": "Feature",
  "properties": {
    "iso:country":"DE",
    "sg:address":"Geusaer Str.",
    "sg:city":"Merseburg",
    "sg:postcode":"06217",
    "sg:province":"Sachsen-Anhalt",
    "wof:name":"Verein Sachzeugen Der Chemi. Industrie E. V.",
    "wof:placetype":"venue"
},
  "geometry": {"coordinates":[11.9730167389,51.343082428],"type":"Point"}
}