{
  "type": "Feature",
  "properties": {
    "iso:country":"DE",
    "sg:address":"Lange Str. 18",
    "sg:city":"Offenburg",
    "sg:phone":"+49 781/79070",
    "sg:postcode":"77652",
    "sg:province":"Baden-W\u00fcrttemberg",
    "wof:name":"Creditreform Offenburg Wagner Kg",
    "wof:placetype":"venue"
},
  "geometry": {"coordinates":[7.94517,48.470413],"type":"Point"}
}