{
  "type": "Feature",
  "properties": {
    "iso:country":"DE",
    "sg:address":"Sch\u00f6nbergstr. 3",
    "sg:city":"T\u00fcbingen",
    "sg:postcode":"72072",
    "sg:province":"Baden-W\u00fcrttemberg",
    "wof:name":"City I Und Ii Kino",
    "wof:placetype":"venue"
},
  "geometry": {"coordinates":[9.059698,48.512909],"type":"Point"}
}