{
  "type": "Feature",
  "properties": {
    "iso:country":"DE",
    "sg:address":"Wagh\u00e4usler Str. 40",
    "sg:city":"Wagh\u00e4usel",
    "sg:phone":"+49 4972/541064",
    "sg:postcode":"68753",
    "sg:province":"Baden-W\u00fcrttemberg",
    "wof:name":"Volksbank Wagh\u00e4usel Eg",
    "wof:placetype":"venue"
},
  "geometry": {"coordinates":[8.50947,49.255035],"type":"Point"}
}