{
  "type": "Feature",
  "properties": {
    "iso:country":"DE",
    "sg:address":"Moselstr. 39",
    "sg:city":"Osann-Monzel",
    "sg:phone":"+49 6535/433",
    "sg:postcode":"54518",
    "sg:province":"Rheinland-Pfalz",
    "wof:name":"Pension Klaus Br\u00f6sch-kiebel",
    "wof:placetype":"venue"
},
  "geometry": {"coordinates":[6.9542388916,49.9115371704],"type":"Point"}
}