{
  "type": "Feature",
  "properties": {
    "iso:country":"DE",
    "sg:address":"Marktplatz 2",
    "sg:city":"Zwingenberg",
    "sg:phone":"+49 6251/77536",
    "sg:postcode":"64673",
    "sg:province":"Hessen",
    "wof:name":"Altstadtschenke",
    "wof:placetype":"venue"
},
  "geometry": {"coordinates":[8.613653183,49.7227287292],"type":"Point"}
}