{
  "type": "Feature",
  "properties": {
    "iso:country":"DE",
    "sg:address":"G\u00f6rlinger-Zentrum 30a/b",
    "sg:city":"K\u00f6ln",
    "sg:phone":"+49 221/95033322",
    "sg:postcode":"50829",
    "sg:province":"Nordrhein-Westfalen",
    "wof:name":"Seniorenzentrum Der Stadt K\u00f6ln H\u00e4uslicher Pflegedienst",
    "wof:placetype":"venue"
},
  "geometry": {"coordinates":[6.88093,50.955635],"type":"Point"}
}