{
  "type": "Feature",
  "properties": {
    "iso:country":"DE",
    "sg:address":"Steinkampring 30",
    "sg:city":"Bad Harzburg",
    "sg:phone":"+49 5322/83221",
    "sg:postcode":"38667",
    "sg:province":"Niedersachsen",
    "wof:name":"Hartung Bau Gmbh",
    "wof:placetype":"venue"
},
  "geometry": {"coordinates":[10.5278978348,51.9099769592],"type":"Point"}
}