{
  "type": "Feature",
  "properties": {
    "iso:country":"DE",
    "sg:address":"Fringsstr. 23",
    "sg:city":"D\u00fcsseldorf",
    "sg:phone":"+49 211/393973",
    "sg:postcode":"40221",
    "sg:province":"Nordrhein-Westfalen",
    "wof:name":"Tts International E. K.",
    "wof:placetype":"venue"
},
  "geometry": {"coordinates":[6.7339258194,51.2108268738],"type":"Point"}
}