{
  "type": "Feature",
  "properties": {
    "iso:country":"DE",
    "sg:address":"Wallstr. 42",
    "sg:city":"Ratingen",
    "sg:postcode":"40878",
    "sg:province":"Nordrhein-Westfalen",
    "wof:name":"Tanzschule Am Wall",
    "wof:placetype":"venue"
},
  "geometry": {"coordinates":[6.8495907784,51.2960968018],"type":"Point"}
}