{
  "type": "Feature",
  "properties": {
    "iso:country":"DE",
    "sg:address":"Oderberger Str. 10",
    "sg:city":"Bralitz",
    "sg:postcode":"16259",
    "sg:province":"Brandenburg",
    "wof:name":"Olh Ost Lagerhaus Gesch\u00e4ftsf\u00fchrung Bralitz Mbh",
    "wof:placetype":"venue"
},
  "geometry": {"coordinates":[14.0102910995,52.8392906189],"type":"Point"}
}