{
  "type": "Feature",
  "properties": {
    "iso:country":"DE",
    "sg:address":"Lindenallee 44",
    "sg:city":"Heilbad Heiligenstadt",
    "sg:postcode":"37308",
    "sg:province":"Th\u00fcringen",
    "wof:name":"Katholisches Pfarramt St. Marien",
    "wof:placetype":"venue"
},
  "geometry": {"coordinates":[10.1379127502,51.3792648315],"type":"Point"}
}