{
  "type": "Feature",
  "properties": {
    "iso:country":"DE",
    "sg:address":"Katharinenfriedhofstr. 31",
    "sg:city":"Amberg",
    "sg:phone":"+49 9621/37210",
    "sg:postcode":"92224",
    "sg:province":"Bayern",
    "wof:name":"Wolfgang Herzing",
    "wof:placetype":"venue"
},
  "geometry": {"coordinates":[11.832591,49.44894],"type":"Point"}
}