{
  "type": "Feature",
  "properties": {
    "iso:country":"DE",
    "sg:address":"Am Diek 2",
    "sg:city":"Merzen",
    "sg:phone":"+49 5466/1412",
    "sg:postcode":"49586",
    "sg:province":"Niedersachsen",
    "wof:name":"Paul Voss Gmbh Antiquit\u00e4ten",
    "wof:placetype":"venue"
},
  "geometry": {"coordinates":[7.829098,52.472534],"type":"Point"}
}