{
  "type": "Feature",
  "properties": {
    "iso:country":"DE",
    "sg:address":"Rotgerweg 37",
    "sg:city":"Dortmund",
    "sg:phone":"+49 231/4940110",
    "sg:postcode":"44229",
    "sg:province":"Nordrhein-Westfalen",
    "wof:name":"Bip Beratungsgesellschaft F\u00fcr Informationstechnologie",
    "wof:placetype":"venue"
},
  "geometry": {"coordinates":[7.465981,51.462814],"type":"Point"}
}