{
  "type": "Feature",
  "properties": {
    "iso:country":"DE",
    "sg:address":"Thielenplatz 1",
    "sg:city":"Hannover",
    "sg:phone":"+49 511/329539",
    "sg:postcode":"30159",
    "sg:province":"Niedersachsen",
    "wof:name":"Ackenhausen Inh. Gustav Mumme",
    "wof:placetype":"venue"
},
  "geometry": {"coordinates":[9.7449245453,52.3745231628],"type":"Point"}
}