{
  "type": "Feature",
  "properties": {
    "iso:country":"DE",
    "sg:address":"Beuthstr. 161",
    "sg:city":"Leipzig",
    "sg:postcode":"04357",
    "sg:province":"Sachsen",
    "wof:name":"Isoftrans Gmbh",
    "wof:placetype":"venue"
},
  "geometry": {"coordinates":[12.4124965668,51.3726425171],"type":"Point"}
}