{
  "type": "Feature",
  "properties": {
    "iso:country":"DE",
    "sg:address":"Weilautstr. 53",
    "sg:city":"Ochtrup",
    "sg:phone":"+49 2553/3182",
    "sg:postcode":"48607",
    "sg:province":"Nordrhein-Westfalen",
    "wof:name":"A. Volkery",
    "wof:placetype":"venue"
},
  "geometry": {"coordinates":[7.1736731529,52.2051277161],"type":"Point"}
}