{
  "type": "Feature",
  "properties": {
    "iso:country":"DE",
    "sg:address":"Obere Hauptstr. 14",
    "sg:city":"Weiden",
    "sg:phone":"+49 961/481040",
    "sg:postcode":"92637",
    "sg:province":"Bayern",
    "wof:name":"H. G. Allertseder Ludwig Pl\u00f6dt",
    "wof:placetype":"venue"
},
  "geometry": {"coordinates":[12.1389923096,49.6348991394],"type":"Point"}
}