{
  "type": "Feature",
  "properties": {
    "iso:country":"DE",
    "sg:address":"Fasanenweg 12",
    "sg:city":"Kelsterbach",
    "sg:phone":"+49 6107/3054",
    "sg:postcode":"65451",
    "sg:province":"Hessen",
    "wof:name":"Mrg Heinz Mitteldorf Recycl. U. Baustoff-verwertung",
    "wof:placetype":"venue"
},
  "geometry": {"coordinates":[8.5404806137,50.0494194031],"type":"Point"}
}