{
  "type": "Feature",
  "properties": {
    "iso:country":"DE",
    "sg:address":"Alzeyer Str. 21",
    "sg:city":"Worms",
    "sg:phone":"+49 6241/591753",
    "sg:postcode":"67549",
    "sg:province":"Rheinland-Pfalz",
    "wof:name":"Hans R. Matzner",
    "wof:placetype":"venue"
},
  "geometry": {"coordinates":[8.351991,49.630886],"type":"Point"}
}