{
  "type": "Feature",
  "properties": {
    "iso:country":"DE",
    "sg:address":"Obere Torstr. 15",
    "sg:city":"Dornhan",
    "sg:phone":"+49 7455/8900",
    "sg:postcode":"72175",
    "sg:province":"Baden-W\u00fcrttemberg",
    "wof:name":"Schwanzer & Glatthaar Gmbh",
    "wof:placetype":"venue"
},
  "geometry": {"coordinates":[8.5106658936,48.3497467041],"type":"Point"}
}