{
  "type": "Feature",
  "properties": {
    "iso:country":"DE",
    "sg:address":"Alter Markt 36-42",
    "sg:city":"K\u00f6ln",
    "sg:phone":"+49 221/650070",
    "sg:postcode":"50667",
    "sg:province":"Nordrhein-Westfalen",
    "wof:name":"Sevenval Ag",
    "wof:placetype":"venue"
},
  "geometry": {"coordinates":[6.960426,50.938358],"type":"Point"}
}