{
  "type": "Feature",
  "properties": {
    "iso:country":"DE",
    "sg:address":"Mittweidaer Str. 44",
    "sg:city":"Frankenberg",
    "sg:phone":"+49 37206/70644",
    "sg:postcode":"09669",
    "sg:province":"Sachsen",
    "wof:name":"M. Rudelt & Dennert",
    "wof:placetype":"venue"
},
  "geometry": {"coordinates":[13.0558996201,50.9122314453],"type":"Point"}
}