{
  "type": "Feature",
  "properties": {
    "iso:country":"DE",
    "sg:address":"Baumertstr. 1",
    "sg:city":"Frankfurt",
    "sg:phone":"+49 69/415845",
    "sg:postcode":"60386",
    "sg:province":"Hessen",
    "wof:name":"Chinarestaurant Lotosgarten",
    "wof:placetype":"venue"
},
  "geometry": {"coordinates":[8.7682933807,50.1249351501],"type":"Point"}
}