{
  "type": "Feature",
  "properties": {
    "iso:country":"DE",
    "sg:address":"Eberhardstr. 24",
    "sg:city":"Remscheid",
    "sg:phone":"+49 2191/22741",
    "sg:postcode":"42853",
    "sg:province":"Nordrhein-Westfalen",
    "wof:name":"Elektrotechnik Ernst Flesche Inh. Armin Hoppmann E. K.",
    "wof:placetype":"venue"
},
  "geometry": {"coordinates":[7.181847,51.188499],"type":"Point"}
}