{
  "type": "Feature",
  "properties": {
    "iso:country":"DE",
    "sg:address":"Maximilianstr. 22",
    "sg:city":"Speyer",
    "sg:phone":"+49 6232/73730",
    "sg:postcode":"67346",
    "sg:province":"Rheinland-Pfalz",
    "wof:name":"Hussel Ag",
    "wof:placetype":"venue"
},
  "geometry": {"coordinates":[8.4369087219,49.3173141479],"type":"Point"}
}