{
  "type": "Feature",
  "properties": {
    "iso:country":"DE",
    "sg:address":"Sch\u00f6pfurter Str. 13",
    "sg:city":"Eberswalde",
    "sg:phone":"+49 3334/24551",
    "sg:postcode":"16225",
    "sg:province":"Brandenburg",
    "wof:name":"Schultheissklause",
    "wof:placetype":"venue"
},
  "geometry": {"coordinates":[13.7922706604,52.8341140747],"type":"Point"}
}