{
  "type": "Feature",
  "properties": {
    "iso:country":"DE",
    "sg:address":"W\u00f6llergasse 2",
    "sg:city":"W\u00fcrzburg",
    "sg:phone":"+49 931/573106",
    "sg:postcode":"97070",
    "sg:province":"Bayern",
    "wof:name":"Marmara Flugreisen Ag",
    "wof:placetype":"venue"
},
  "geometry": {"coordinates":[9.9332914352,49.7964706421],"type":"Point"}
}