{
  "type": "Feature",
  "properties": {
    "iso:country":"DE",
    "sg:address":"N\u00f6ttenstr. 32",
    "sg:city":"Soest",
    "sg:phone":"+49 2921/17017",
    "sg:postcode":"59494",
    "sg:province":"Nordrhein-Westfalen",
    "wof:name":"Arndt Timmerberg Rechtsanwalt",
    "wof:placetype":"venue"
},
  "geometry": {"coordinates":[8.1012773514,51.5725975037],"type":"Point"}
}