{
  "type": "Feature",
  "properties": {
    "iso:country":"DE",
    "sg:address":"Berliner Str. 4",
    "sg:city":"Kolkwitz",
    "sg:phone":"+49 355/28348",
    "sg:postcode":"03099",
    "sg:province":"Brandenburg",
    "wof:name":"Manfred Borchel",
    "wof:placetype":"venue"
},
  "geometry": {"coordinates":[14.25261,51.749619],"type":"Point"}
}