{
  "type": "Feature",
  "properties": {
    "iso:country":"DE",
    "sg:address":"Schmalegger Str. 15",
    "sg:city":"Ravensburg",
    "sg:phone":"+49 751/9090",
    "sg:postcode":"88213",
    "sg:province":"Baden-W\u00fcrttemberg",
    "wof:name":"Zwerger System Gmbh & Co.",
    "wof:placetype":"venue"
},
  "geometry": {"coordinates":[9.585315,47.779739],"type":"Point"}
}