{
  "type": "Feature",
  "properties": {
    "iso:country":"DE",
    "sg:address":"Wei\u00dfiger Str. 53",
    "sg:city":"Freital",
    "sg:phone":"+49 351/6491521",
    "sg:postcode":"01705",
    "sg:province":"Sachsen",
    "wof:name":"Peter Reichelt",
    "wof:placetype":"venue"
},
  "geometry": {"coordinates":[13.634129,51.00494],"type":"Point"}
}