{
  "type": "Feature",
  "properties": {
    "iso:country":"DE",
    "sg:address":"Bei der Sandsteige 4",
    "sg:city":"Satteldorf",
    "sg:phone":"+49 7950/925047",
    "sg:postcode":"74589",
    "sg:province":"Baden-W\u00fcrttemberg",
    "wof:name":"Flexima Packaging Systems Gmbh",
    "wof:placetype":"venue"
},
  "geometry": {"coordinates":[10.15383,49.182056],"type":"Point"}
}