{
  "type": "Feature",
  "properties": {
    "iso:country":"DE",
    "sg:address":"P\u00fcttbergeweg 3-5",
    "sg:city":"Berlin",
    "sg:phone":"+49 30/65489940",
    "sg:postcode":"12589",
    "sg:province":"Berlin",
    "wof:name":"Junge & G\u00e4pel Swimming- Pool Und Fitness Gmbh",
    "wof:placetype":"venue"
},
  "geometry": {"coordinates":[13.689736,52.441235],"type":"Point"}
}