{
  "type": "Feature",
  "properties": {
    "iso:country":"DE",
    "sg:address":"Schanzenweg 31",
    "sg:city":"Villingen-Schwenningen",
    "sg:postcode":"78050",
    "sg:province":"Baden-W\u00fcrttemberg",
    "wof:name":"Industriebau Rohrer Gmbh",
    "wof:placetype":"venue"
},
  "geometry": {"coordinates":[8.4347324371,48.0646781921],"type":"Point"}
}