{
  "type": "Feature",
  "properties": {
    "iso:country":"DE",
    "sg:address":"Breite Str. 59",
    "sg:city":"Neuss",
    "sg:phone":"+49 2131/276588",
    "sg:postcode":"41460",
    "sg:province":"Nordrhein-Westfalen",
    "wof:name":"Gerichtsstube",
    "wof:placetype":"venue"
},
  "geometry": {"coordinates":[6.6891331673,51.1955566406],"type":"Point"}
}