{
  "type": "Feature",
  "properties": {
    "iso:country":"DE",
    "sg:address":"Masurenweg 26",
    "sg:city":"Wedemark",
    "sg:phone":"+49 5130/3893",
    "sg:postcode":"30900",
    "sg:province":"Niedersachsen",
    "wof:name":"Uwe Stoffers",
    "wof:placetype":"venue"
},
  "geometry": {"coordinates":[9.7406949997,52.5410385132],"type":"Point"}
}