{
  "type": "Feature",
  "properties": {
    "iso:country":"DE",
    "sg:address":"Geranienweg 7-9",
    "sg:city":"Brandenburg",
    "sg:phone":"+49 3381/702236",
    "sg:postcode":"14772",
    "sg:province":"Brandenburg",
    "wof:name":"Horst Rath",
    "wof:placetype":"venue"
},
  "geometry": {"coordinates":[12.509592,52.42551],"type":"Point"}
}