{
  "type": "Feature",
  "properties": {
    "iso:country":"DE",
    "sg:address":"Breslauer Weg 75",
    "sg:city":"Geretsried",
    "sg:phone":"+49 8171/8620",
    "sg:postcode":"82538",
    "sg:province":"Bayern",
    "wof:name":"Mark Kompressoren Gmbh",
    "wof:placetype":"venue"
},
  "geometry": {"coordinates":[11.49003,47.859081],"type":"Point"}
}