{
  "type": "Feature",
  "properties": {
    "iso:country":"DE",
    "sg:address":"Staffelstein",
    "sg:city":"Staffelstein",
    "sg:phone":"+49 9573/5811",
    "sg:postcode":"96231",
    "sg:province":"Bayern",
    "wof:name":"Raiffeisenbank Staffelstein Eg",
    "wof:placetype":"venue"
},
  "geometry": {"coordinates":[11.0208,50.104599],"type":"Point"}
}