{
  "type": "Feature",
  "properties": {
    "iso:country":"DE",
    "sg:address":"Kirchstr. 225",
    "sg:city":"Geislingen",
    "sg:phone":"+49 7428/8137",
    "sg:postcode":"72351",
    "sg:province":"Baden-W\u00fcrttemberg",
    "wof:name":"Kath. Pfarramt St. Silvester",
    "wof:placetype":"venue"
},
  "geometry": {"coordinates":[8.7816495895,48.3041687012],"type":"Point"}
}