{
  "type": "Feature",
  "properties": {
    "iso:country":"DE",
    "sg:address":"Hebbelstr. 57",
    "sg:city":"Ingolstadt",
    "sg:phone":"+49 841/954770",
    "sg:postcode":"85055",
    "sg:province":"Bayern",
    "wof:name":"Tengler Match",
    "wof:placetype":"venue"
},
  "geometry": {"coordinates":[11.4581766129,48.7735366821],"type":"Point"}
}