{
  "type": "Feature",
  "properties": {
    "iso:country":"DE",
    "sg:address":"Wolfsweg 9",
    "sg:city":"Wardenburg",
    "sg:phone":"+49 441/500450",
    "sg:postcode":"26203",
    "sg:province":"Niedersachsen",
    "wof:name":"Vau Na - Bau Gmbh",
    "wof:placetype":"venue"
},
  "geometry": {"coordinates":[8.18523,53.110191],"type":"Point"}
}