{
  "type": "Feature",
  "properties": {
    "iso:country":"DE",
    "sg:address":"Gut Kleehof",
    "sg:city":"Bad Lippspringe",
    "sg:phone":"+49 5252/5829",
    "sg:postcode":"33175",
    "sg:province":"Nordrhein-Westfalen",
    "wof:name":"Klaus Z\u00fcndorf",
    "wof:placetype":"venue"
},
  "geometry": {"coordinates":[8.8191137314,51.7827072144],"type":"Point"}
}