{
  "type": "Feature",
  "properties": {
    "iso:country":"DE",
    "sg:address":"Ludwigstr. 28",
    "sg:city":"M\u00fcnchen",
    "sg:postcode":"80539",
    "sg:province":"Bayern",
    "wof:name":"Universit\u00e4t M\u00fcnchen Inst. F. Empirische P\u00e4dagogik",
    "wof:placetype":"venue"
},
  "geometry": {"coordinates":[11.582234,48.15181],"type":"Point"}
}