{
  "type": "Feature",
  "properties": {
    "iso:country":"DE",
    "sg:address":"Ahornweg 6",
    "sg:city":"Weikersheim",
    "sg:phone":"+49 4979/3491260",
    "sg:postcode":"97990",
    "sg:province":"Baden-W\u00fcrttemberg",
    "wof:name":"Alfred Trenker Diamant-anlagen-technik",
    "wof:placetype":"venue"
},
  "geometry": {"coordinates":[9.900362,49.488651],"type":"Point"}
}