{
  "type": "Feature",
  "properties": {
    "iso:country":"DE",
    "sg:address":"Gosewehr 16",
    "sg:city":"Sulingen",
    "sg:phone":"+49 4271/2460",
    "sg:postcode":"27232",
    "sg:province":"Niedersachsen",
    "wof:name":"Ludwig Ihlo",
    "wof:placetype":"venue"
},
  "geometry": {"coordinates":[8.8027105331,52.6769981384],"type":"Point"}
}