{
  "type": "Feature",
  "properties": {
    "iso:country":"DE",
    "sg:address":"Birkenweg 4",
    "sg:city":"Drachselsried",
    "sg:phone":"+49 9945/1091",
    "sg:postcode":"94256",
    "sg:province":"Bayern",
    "wof:name":"R. M\u00fcnch",
    "wof:placetype":"venue"
},
  "geometry": {"coordinates":[13.0097169876,49.1095848083],"type":"Point"}
}