{
  "type": "Feature",
  "properties": {
    "iso:country":"DE",
    "sg:address":"Herrenstr. 31",
    "sg:city":"Wangen",
    "sg:phone":"+49 7522/97730",
    "sg:postcode":"88239",
    "sg:province":"Baden-W\u00fcrttemberg",
    "wof:name":"Seifried Burkhard Czech Rechtsanw\u00e4lte",
    "wof:placetype":"venue"
},
  "geometry": {"coordinates":[9.8335723877,47.6873931885],"type":"Point"}
}