{
  "type": "Feature",
  "properties": {
    "iso:country":"DE",
    "sg:address":"Pretzener Str. 10",
    "sg:city":"Erding",
    "sg:phone":"+49 8122/41624",
    "sg:postcode":"85435",
    "sg:province":"Bayern",
    "wof:name":"Asb Sport Sperk Gmbh & Co. Kg",
    "wof:placetype":"venue"
},
  "geometry": {"coordinates":[11.900928,48.271915],"type":"Point"}
}