{
  "type": "Feature",
  "properties": {
    "iso:country":"DE",
    "sg:address":"Krapfberg 4",
    "sg:city":"Gauting",
    "sg:postcode":"82131",
    "sg:province":"Bayern",
    "wof:name":"Help Dienstleistungen F\u00fcr Private Haushalte Und",
    "wof:placetype":"venue"
},
  "geometry": {"coordinates":[11.377824,48.0676],"type":"Point"}
}