{
  "type": "Feature",
  "properties": {
    "iso:country":"DE",
    "sg:address":"Siepenstr. 20",
    "sg:city":"Kreuztal",
    "sg:phone":"+49 2732/28111",
    "sg:postcode":"57223",
    "sg:province":"Nordrhein-Westfalen",
    "wof:name":"Bernd Schmidt Edv-beratungsgesellschaft Mbh",
    "wof:placetype":"venue"
},
  "geometry": {"coordinates":[8.0136833191,50.9611549377],"type":"Point"}
}