{
  "type": "Feature",
  "properties": {
    "iso:country":"DE",
    "sg:address":"Am Seitenweg 2",
    "sg:city":"Marienberg/lauterbach",
    "sg:phone":"+49 3735",
    "sg:postcode":"09496",
    "sg:province":"Sachsen",
    "wof:name":"Krantransporte Baldauf",
    "wof:placetype":"venue"
},
  "geometry": {"coordinates":[13.20967,50.632179],"type":"Point"}
}