{
  "type": "Feature",
  "properties": {
    "iso:country":"DE",
    "sg:address":"Bahnhofsvorplatz 1",
    "sg:city":"K\u00f6ln",
    "sg:phone":"+49 221/131917",
    "sg:postcode":"50667",
    "sg:province":"Nordrhein-Westfalen",
    "wof:name":"Boutique 88 Am Dom Ch. Krakau",
    "wof:placetype":"venue"
},
  "geometry": {"coordinates":[6.957449,50.942875],"type":"Point"}
}