{
  "type": "Feature",
  "properties": {
    "iso:country":"DE",
    "sg:address":"Breitscheidstr. 38",
    "sg:city":"Dresden",
    "sg:phone":"+49 351/2680930",
    "sg:postcode":"01237",
    "sg:province":"Sachsen",
    "wof:name":"Gebr\u00fcder Otto Gmbh",
    "wof:placetype":"venue"
},
  "geometry": {"coordinates":[13.8111000061,51.013458252],"type":"Point"}
}