{
  "type": "Feature",
  "properties": {
    "iso:country":"DE",
    "sg:address":"Bergstr. 7",
    "sg:city":"Nerchau",
    "sg:postcode":"04685",
    "sg:province":"Sachsen",
    "wof:name":"Ines Gr\u00fcndel",
    "wof:placetype":"venue"
},
  "geometry": {"coordinates":[12.785334,51.247456],"type":"Point"}
}