{
  "type": "Feature",
  "properties": {
    "iso:country":"DE",
    "sg:address":"Hermannstr. 53",
    "sg:city":"Bielefeld",
    "sg:phone":"+49 521/69621",
    "sg:postcode":"33602",
    "sg:province":"Nordrhein-Westfalen",
    "wof:name":"Gota Tapetenmarkt Georg Goldkuhle",
    "wof:placetype":"venue"
},
  "geometry": {"coordinates":[8.5408983231,52.0182685852],"type":"Point"}
}