{
  "type": "Feature",
  "properties": {
    "iso:country":"DE",
    "sg:address":"Frillendorfer Str. 139",
    "sg:city":"Essen",
    "sg:phone":"+49 201/2806572",
    "sg:postcode":"45139",
    "sg:province":"Nordrhein-Westfalen",
    "wof:name":"Horst Lieder",
    "wof:placetype":"venue"
},
  "geometry": {"coordinates":[7.0353121758,51.4597816467],"type":"Point"}
}