{
  "type": "Feature",
  "properties": {
    "iso:country":"DE",
    "sg:address":"Kiefernstr. 14",
    "sg:city":"Eichenau",
    "sg:phone":"+49 8141/72609",
    "sg:postcode":"82223",
    "sg:province":"Bayern",
    "wof:name":"Otto Wimmer",
    "wof:placetype":"venue"
},
  "geometry": {"coordinates":[11.3253936768,48.1632041931],"type":"Point"}
}