{
  "type": "Feature",
  "properties": {
    "iso:country":"DE",
    "sg:address":"Alte Dresdener Str 4",
    "sg:city":"Bautzen",
    "sg:phone":"+49 3591/305427",
    "sg:postcode":"02625",
    "sg:province":"Sachsen",
    "wof:name":"Herzog Elektromotoren Und Pumpenservice Gmbh",
    "wof:placetype":"venue"
},
  "geometry": {"coordinates":[14.4187803268,51.1837997437],"type":"Point"}
}