{
  "type": "Feature",
  "properties": {
    "iso:country":"DE",
    "sg:address":"Elberfelder Str. 48",
    "sg:city":"Velbert",
    "sg:postcode":"42553",
    "sg:province":"Nordrhein-Westfalen",
    "wof:name":"Nevigeser Wollst\u00fcbchen",
    "wof:placetype":"venue"
},
  "geometry": {"coordinates":[7.09112,51.30117],"type":"Point"}
}