{
  "type": "Feature",
  "properties": {
    "iso:country":"DE",
    "sg:address":"Geilsheim 155",
    "sg:city":"Wassertr\u00fcdingen",
    "sg:phone":"+49 9832/518",
    "sg:postcode":"91717",
    "sg:province":"Bayern",
    "wof:name":"August Doberer",
    "wof:placetype":"venue"
},
  "geometry": {"coordinates":[10.65564,49.030258],"type":"Point"}
}