{
  "type": "Feature",
  "properties": {
    "iso:country":"DE",
    "sg:address":"Schillerstr. 1 a",
    "sg:city":"Neubrandenburg",
    "sg:phone":"+49 395/5661178",
    "sg:postcode":"17033",
    "sg:province":"Mecklenburg-Vorpommern",
    "wof:name":"Data Kassa B\u00fcro F\u00fcr Unternehmensberatung Und",
    "wof:placetype":"venue"
},
  "geometry": {"coordinates":[13.254115,53.554939],"type":"Point"}
}