{
  "type": "Feature",
  "properties": {
    "iso:country":"DE",
    "sg:address":"Angerstr. 36",
    "sg:city":"Zwiesel",
    "sg:phone":"+49 9922/2390",
    "sg:postcode":"94227",
    "sg:province":"Bayern",
    "wof:name":"F. Pietsch",
    "wof:placetype":"venue"
},
  "geometry": {"coordinates":[13.224911,49.011745],"type":"Point"}
}