{
  "type": "Feature",
  "properties": {
    "iso:country":"DE",
    "sg:address":"Hamburger Str. 66",
    "sg:city":"Bad Bramstedt",
    "sg:phone":"+49 4192/7863",
    "sg:postcode":"24576",
    "sg:province":"Schleswig-Holstein",
    "wof:name":"Ina Und Hans-georg Ohly Ferienwohnungen",
    "wof:placetype":"venue"
},
  "geometry": {"coordinates":[9.8816699982,53.9088096619],"type":"Point"}
}