{
  "type": "Feature",
  "properties": {
    "iso:country":"DE",
    "sg:address":"Kapuzinergraben 9",
    "sg:city":"Aachen",
    "sg:phone":"+49 241/32068",
    "sg:postcode":"52062",
    "sg:province":"Nordrhein-Westfalen",
    "wof:name":"Brillen-demmer Gmbh",
    "wof:placetype":"venue"
},
  "geometry": {"coordinates":[6.086776,50.773125],"type":"Point"}
}