{
  "type": "Feature",
  "properties": {
    "iso:country":"DE",
    "sg:address":"Alter Graben 23",
    "sg:city":"Karlsruhe",
    "sg:phone":"+49 721/43177",
    "sg:postcode":"76227",
    "sg:province":"Baden-W\u00fcrttemberg",
    "wof:name":"Udo Metz Architekt",
    "wof:placetype":"venue"
},
  "geometry": {"coordinates":[8.463729,48.99345],"type":"Point"}
}