{
  "type": "Feature",
  "properties": {
    "iso:country":"DE",
    "sg:address":"Hauptstr. 67",
    "sg:city":"Maxdorf",
    "sg:phone":"+49 6237/7843",
    "sg:postcode":"67133",
    "sg:province":"Rheinland-Pfalz",
    "wof:name":"Bp Tankstelle",
    "wof:placetype":"venue"
},
  "geometry": {"coordinates":[8.2929925919,49.4824256897],"type":"Point"}
}