{
  "type": "Feature",
  "properties": {
    "iso:country":"DE",
    "sg:address":"Felmicke 30",
    "sg:city":"Olpe",
    "sg:phone":"+49 2761/96550",
    "sg:postcode":"57462",
    "sg:province":"Nordrhein-Westfalen",
    "wof:name":"Bestattungshaus Heinrich Langemann",
    "wof:placetype":"venue"
},
  "geometry": {"coordinates":[7.850315,51.030655],"type":"Point"}
}