{
  "type": "Feature",
  "properties": {
    "iso:country":"DE",
    "sg:address":"Schillingstr. 12",
    "sg:city":"Idar-Oberstein",
    "sg:phone":"+49 6781/46449",
    "sg:postcode":"55743",
    "sg:province":"Rheinland-Pfalz",
    "wof:name":"Georg A. Becker Gmbh",
    "wof:placetype":"venue"
},
  "geometry": {"coordinates":[7.301761,49.717957],"type":"Point"}
}