{
  "type": "Feature",
  "properties": {
    "iso:country":"DE",
    "sg:address":"Genstr. 22",
    "sg:city":"Heinsberg",
    "sg:phone":"+49 2452/904763",
    "sg:postcode":"52525",
    "sg:province":"Nordrhein-Westfalen",
    "wof:name":"C. G\u00f6rtz",
    "wof:placetype":"venue"
},
  "geometry": {"coordinates":[6.1106281281,51.0557327271],"type":"Point"}
}