{
  "type": "Feature",
  "properties": {
    "iso:country":"DE",
    "sg:address":"Steinweg 56 - 58",
    "sg:city":"Gifhorn",
    "sg:phone":"+49 5371/98700",
    "sg:postcode":"38518",
    "sg:province":"Niedersachsen",
    "wof:name":"Fritz Becker",
    "wof:placetype":"venue"
},
  "geometry": {"coordinates":[10.546864,52.484852],"type":"Point"}
}