{
  "type": "Feature",
  "properties": {
    "iso:country":"DE",
    "sg:address":"Dorfstr. 4",
    "sg:city":"Niederaula",
    "sg:phone":"+49 6625/230",
    "sg:postcode":"36272",
    "sg:province":"Hessen",
    "wof:name":"Georg Schneider",
    "wof:placetype":"venue"
},
  "geometry": {"coordinates":[9.559694,50.804241],"type":"Point"}
}