{
  "type": "Feature",
  "properties": {
    "iso:country":"DE",
    "sg:address":"Gro\u00dfe Eschenheimer Str. 16-18",
    "sg:city":"Frankfurt",
    "sg:phone":"+49 69/9133580",
    "sg:postcode":"60313",
    "sg:province":"Hessen",
    "wof:name":"Gwf Ges. F\u00fcr Wirtschafts- Fernsehen Und",
    "wof:placetype":"venue"
},
  "geometry": {"coordinates":[8.679756,50.115669],"type":"Point"}
}