{
  "type": "Feature",
  "properties": {
    "iso:country":"DE",
    "sg:address":"Obere Bahnhofstr. 7",
    "sg:city":"Ro\u00dftal",
    "sg:phone":"+49 9127/57526",
    "sg:postcode":"90574",
    "sg:province":"Bayern",
    "wof:name":"W. Schifferm\u00fcller",
    "wof:placetype":"venue"
},
  "geometry": {"coordinates":[10.8979930878,49.4008865356],"type":"Point"}
}