{
  "type": "Feature",
  "properties": {
    "iso:country":"DE",
    "sg:address":"H\u00f6chster Str. 18",
    "sg:city":"Schwalbach",
    "sg:postcode":"65824",
    "sg:province":"Hessen",
    "wof:name":"Dutch Power Inh. Henrica Buijvoets",
    "wof:placetype":"venue"
},
  "geometry": {"coordinates":[8.5433740616,50.1477470398],"type":"Point"}
}