{
  "type": "Feature",
  "properties": {
    "iso:country":"DE",
    "sg:address":"Friedensstr. 43",
    "sg:city":"Dorndorf",
    "sg:phone":"+49 36963/4292",
    "sg:postcode":"36460",
    "sg:province":"Th\u00fcringen",
    "wof:name":"Franke Kanal- U. Schacht- Sanierung Gmbh",
    "wof:placetype":"venue"
},
  "geometry": {"coordinates":[10.1154699326,50.8254127502],"type":"Point"}
}