{
  "type": "Feature",
  "properties": {
    "iso:country":"DE",
    "sg:address":"Odilienstr. 9",
    "sg:city":"Eichenzell",
    "sg:phone":"+49 6656/443",
    "sg:postcode":"36124",
    "sg:province":"Hessen",
    "wof:name":"Ernst Roth",
    "wof:placetype":"venue"
},
  "geometry": {"coordinates":[9.7340087891,50.4385261536],"type":"Point"}
}