{
  "type": "Feature",
  "properties": {
    "iso:country":"DE",
    "sg:address":"Zscherbener Str. 9",
    "sg:city":"Angersdorf",
    "sg:phone":"+49 345/6131020",
    "sg:postcode":"06179",
    "sg:province":"Sachsen-Anhalt",
    "wof:name":"H\u00fcnert Metallbau Gmbh",
    "wof:placetype":"venue"
},
  "geometry": {"coordinates":[11.88263,51.456402],"type":"Point"}
}