{
  "type": "Feature",
  "properties": {
    "iso:country":"DE",
    "sg:address":"Sonnenluger",
    "sg:city":"Mengen",
    "sg:phone":"+49 7572/8840",
    "sg:postcode":"88512",
    "sg:province":"Baden-W\u00fcrttemberg",
    "wof:name":"Lehrschwimmbecken",
    "wof:placetype":"venue"
},
  "geometry": {"coordinates":[9.329832077,48.0450134277],"type":"Point"}
}