{
  "type": "Feature",
  "properties": {
    "iso:country":"DE",
    "sg:address":"Augsburger Str. 8",
    "sg:city":"Neu-Ulm",
    "sg:phone":"+49 731/77006",
    "sg:postcode":"89231",
    "sg:province":"Bayern",
    "wof:name":"Werner Dannenhauer Rechtsanwalt",
    "wof:placetype":"venue"
},
  "geometry": {"coordinates":[9.999707222,48.3951187134],"type":"Point"}
}