{
  "type": "Feature",
  "properties": {
    "iso:country":"DE",
    "sg:address":"Kloschinskystr. 58",
    "sg:city":"Trier",
    "sg:phone":"+49 651/140444",
    "sg:postcode":"54292",
    "sg:province":"Rheinland-Pfalz",
    "wof:name":"F. Hermesdorf",
    "wof:placetype":"venue"
},
  "geometry": {"coordinates":[6.645307,49.765858],"type":"Point"}
}