{
  "type": "Feature",
  "properties": {
    "iso:country":"DE",
    "sg:address":"Sepp-Sontheim-Str. 10b",
    "sg:city":"Miesbach",
    "sg:phone":"+49 8025/91965",
    "sg:postcode":"83714",
    "sg:province":"Bayern",
    "wof:name":"Martina Jacobs",
    "wof:placetype":"venue"
},
  "geometry": {"coordinates":[11.853918,47.789204],"type":"Point"}
}