{
  "type": "Feature",
  "properties": {
    "iso:country":"DE",
    "sg:address":"Westerstr. 24",
    "sg:city":"B\u00fcsum",
    "sg:phone":"+49 4834/93285",
    "sg:postcode":"25761",
    "sg:province":"Schleswig-Holstein",
    "wof:name":"A. Stabenow",
    "wof:placetype":"venue"
},
  "geometry": {"coordinates":[8.8571128845,54.1310577393],"type":"Point"}
}