{
  "type": "Feature",
  "properties": {
    "iso:country":"DE",
    "sg:address":"Berliner Str. 3",
    "sg:city":"Angerm\u00fcnde",
    "sg:phone":"+49 3331/32473",
    "sg:postcode":"16278",
    "sg:province":"Brandenburg",
    "wof:name":"Wolfgang Rodebarrth",
    "wof:placetype":"venue"
},
  "geometry": {"coordinates":[13.9875488281,53.0008583069],"type":"Point"}
}