{
  "type": "Feature",
  "properties": {
    "iso:country":"DE",
    "sg:address":"Prenzlauer Allee 223",
    "sg:city":"Berlin",
    "sg:phone":"+49 30/44008706",
    "sg:postcode":"10405",
    "sg:province":"Berlin",
    "wof:name":"Elke Drescher-herndl",
    "wof:placetype":"venue"
},
  "geometry": {"coordinates":[13.4208488464,52.5341491699],"type":"Point"}
}