{
  "type": "Feature",
  "properties": {
    "iso:country":"DE",
    "sg:address":"Letten 1",
    "sg:city":"Igensdorf",
    "sg:phone":"+49 9192",
    "sg:postcode":"91338",
    "sg:province":"Bayern",
    "wof:name":"E-allround.de",
    "wof:placetype":"venue"
},
  "geometry": {"coordinates":[11.210566,49.633518],"type":"Point"}
}