{
  "type": "Feature",
  "properties": {
    "iso:country":"DE",
    "sg:address":"Hauptstr. 8",
    "sg:city":"Aderstedt",
    "sg:postcode":"06408",
    "sg:province":"Sachsen-Anhalt",
    "wof:name":"Windpark Walkh\u00fcgel Gmbh & Co. Aderstedt Ii Kg",
    "wof:placetype":"venue"
},
  "geometry": {"coordinates":[11.698057,51.781895],"type":"Point"}
}