{
  "type": "Feature",
  "properties": {
    "iso:country":"DE",
    "sg:address":"Bahnhofstr. 101 a",
    "sg:city":"Geltendorf",
    "sg:phone":"+49 8193/6999",
    "sg:postcode":"82269",
    "sg:province":"Bayern",
    "wof:name":"Josef Tr\u00f6ndle",
    "wof:placetype":"venue"
},
  "geometry": {"coordinates":[11.035892,48.113052],"type":"Point"}
}