{
  "type": "Feature",
  "properties": {
    "iso:country":"DE",
    "sg:address":"M\u00fcndener Str. 16",
    "sg:city":"Bad Karlshafen",
    "sg:phone":"+49 5672/802",
    "sg:postcode":"34385",
    "sg:province":"Hessen",
    "wof:name":"Kath. Pfarramt St. Michael",
    "wof:placetype":"venue"
},
  "geometry": {"coordinates":[9.4562072754,51.6451263428],"type":"Point"}
}