{
  "type": "Feature",
  "properties": {
    "iso:country":"DE",
    "sg:address":"Rechenstra\u00dfe 32",
    "sg:city":"Bodenmais",
    "sg:phone":"+49 9924/952300",
    "sg:postcode":"94249",
    "sg:province":"Bayern",
    "wof:name":"Ferien-hotel Zum Arber",
    "wof:placetype":"venue"
},
  "geometry": {"coordinates":[13.108709,49.070766],"type":"Point"}
}