{
  "type": "Feature",
  "properties": {
    "iso:country":"DE",
    "sg:address":"Goetheplatz 1",
    "sg:city":"Freiburg",
    "sg:phone":"+49 761/7075415",
    "sg:postcode":"79100",
    "sg:province":"Baden-W\u00fcrttemberg",
    "wof:name":"Accento",
    "wof:placetype":"venue"
},
  "geometry": {"coordinates":[7.844826,47.989952],"type":"Point"}
}