{
  "type": "Feature",
  "properties": {
    "iso:country":"DE",
    "sg:address":"M\u00fchlenstr. 19",
    "sg:city":"Damme",
    "sg:phone":"+49 5491/2988",
    "sg:postcode":"49401",
    "sg:province":"Niedersachsen",
    "wof:name":"Johannes Buschatz",
    "wof:placetype":"venue"
},
  "geometry": {"coordinates":[8.1939659119,52.5223503113],"type":"Point"}
}