{
  "type": "Feature",
  "properties": {
    "iso:country":"DE",
    "sg:address":"In der Talwiese 2",
    "sg:city":"Sigmaringen",
    "sg:phone":"+49 7571/62315",
    "sg:postcode":"72488",
    "sg:province":"Baden-W\u00fcrttemberg",
    "wof:name":"Frank Lorenz",
    "wof:placetype":"venue"
},
  "geometry": {"coordinates":[9.2235784531,48.0936317444],"type":"Point"}
}