{
  "type": "Feature",
  "properties": {
    "iso:country":"DE",
    "sg:address":"Lotschstr. 6",
    "sg:city":"Landau",
    "sg:phone":"+49 6341/60239",
    "sg:postcode":"76829",
    "sg:province":"Rheinland-Pfalz",
    "wof:name":"H. Gieselmann Kg",
    "wof:placetype":"venue"
},
  "geometry": {"coordinates":[8.1139678955,49.2100868225],"type":"Point"}
}