{
  "type": "Feature",
  "properties": {
    "iso:country":"DE",
    "sg:address":"Bahnhofstr. 8",
    "sg:city":"Ennigerloh",
    "sg:phone":"+49 2524/7706",
    "sg:postcode":"59320",
    "sg:province":"Nordrhein-Westfalen",
    "wof:name":"Austermann Augenoptiker",
    "wof:placetype":"venue"
},
  "geometry": {"coordinates":[8.0257024765,51.8362846375],"type":"Point"}
}