{
  "type": "Feature",
  "properties": {
    "iso:country":"DE",
    "sg:address":"Langer Brauck 17",
    "sg:city":"Iserlohn",
    "sg:phone":"+49 7164/909360",
    "sg:postcode":"58640",
    "sg:province":"Nordrhein-Westfalen",
    "wof:name":"Pewamat Gmbh",
    "wof:placetype":"venue"
},
  "geometry": {"coordinates":[9.571324,48.653877],"type":"Point"}
}