{
  "type": "Feature",
  "properties": {
    "iso:country":"DE",
    "sg:address":"Tetzlawstr. 46",
    "sg:city":"Stralsund",
    "sg:phone":"+49 3831/494983",
    "sg:postcode":"18437",
    "sg:province":"Mecklenburg-Vorpommern",
    "wof:name":"K. Kaczke",
    "wof:placetype":"venue"
},
  "geometry": {"coordinates":[13.067405,54.30154],"type":"Point"}
}