{
  "type": "Feature",
  "properties": {
    "iso:country":"DE",
    "sg:address":"Am Weinberg 24",
    "sg:city":"Reinfeld",
    "sg:postcode":"23858",
    "sg:province":"Schleswig-Holstein",
    "wof:name":"Contract Baumanament Gmbh",
    "wof:placetype":"venue"
},
  "geometry": {"coordinates":[10.480056,53.835411],"type":"Point"}
}