{
  "type": "Feature",
  "properties": {
    "iso:country":"DE",
    "sg:address":"Karlstr. 41",
    "sg:city":"Ulm",
    "sg:postcode":"89073",
    "sg:province":"Baden-W\u00fcrttemberg",
    "wof:name":"Ndorado Gmbh",
    "wof:placetype":"venue"
},
  "geometry": {"coordinates":[9.991178,48.4053],"type":"Point"}
}