{
  "type": "Feature",
  "properties": {
    "iso:country":"DE",
    "sg:address":"Markgrafenstr. 16",
    "sg:city":"Grenzach-Wyhlen",
    "sg:phone":"+49 7624/8293",
    "sg:postcode":"79639",
    "sg:province":"Baden-W\u00fcrttemberg",
    "wof:name":"Karl Willimann",
    "wof:placetype":"venue"
},
  "geometry": {"coordinates":[7.6626977921,47.5522918701],"type":"Point"}
}