{
  "type": "Feature",
  "properties": {
    "iso:country":"DE",
    "sg:address":"Hauffstr. 21",
    "sg:city":"Dornstadt",
    "sg:phone":"+49 7348/21527",
    "sg:postcode":"89160",
    "sg:province":"Baden-W\u00fcrttemberg",
    "wof:name":"Josef Schweizer Finanzberater",
    "wof:placetype":"venue"
},
  "geometry": {"coordinates":[9.940243721,48.4730606079],"type":"Point"}
}