{
  "type": "Feature",
  "properties": {
    "iso:country":"DE",
    "sg:address":"Werftweg 71",
    "sg:city":"Neckarsteinach",
    "sg:phone":"+49 6229/2302",
    "sg:postcode":"69239",
    "sg:province":"Hessen",
    "wof:name":"Bsb Binnenschiffahrts- Betriebsgesellschaft Mbh",
    "wof:placetype":"venue"
},
  "geometry": {"coordinates":[8.842692,49.402359],"type":"Point"}
}