{
  "type": "Feature",
  "properties": {
    "iso:country":"DE",
    "sg:address":"Alter Postweg 14",
    "sg:city":"Buxtehude",
    "sg:phone":"+49 4161/71870",
    "sg:postcode":"21614",
    "sg:province":"Niedersachsen",
    "wof:name":"Kalksandsteinwerke Busch & D\u00f6rlitz Gmbh & Co. Kg",
    "wof:placetype":"venue"
},
  "geometry": {"coordinates":[9.7144098282,53.463470459],"type":"Point"}
}