{
  "type": "Feature",
  "properties": {
    "iso:country":"DE",
    "sg:address":"Auf dem Damm 18 a",
    "sg:city":"Moisburg",
    "sg:postcode":"21647",
    "sg:province":"Niedersachsen",
    "wof:name":"Cuba Products Im- Und Export Ohg",
    "wof:placetype":"venue"
},
  "geometry": {"coordinates":[9.6939029694,53.4046936035],"type":"Point"}
}