{
  "type": "Feature",
  "properties": {
    "iso:country":"DE",
    "sg:address":"Nobelstr. 7",
    "sg:city":"Ettlingen",
    "sg:phone":"+49 7243/761770",
    "sg:postcode":"76275",
    "sg:province":"Baden-W\u00fcrttemberg",
    "wof:name":"Smeg-hausger\u00e4te Gmbh",
    "wof:placetype":"venue"
},
  "geometry": {"coordinates":[8.37694,48.936382],"type":"Point"}
}