{
  "type": "Feature",
  "properties": {
    "iso:country":"DE",
    "sg:address":"August-Burberg-Str. 21",
    "sg:city":"Mettmann",
    "sg:phone":"+49 2104/71924",
    "sg:postcode":"40822",
    "sg:province":"Nordrhein-Westfalen",
    "wof:name":"Westerheide Werbemittlung E.k.",
    "wof:placetype":"venue"
},
  "geometry": {"coordinates":[6.964749,51.250652],"type":"Point"}
}