{
  "type": "Feature",
  "properties": {
    "iso:country":"DE",
    "sg:address":"Hauptstr. 45",
    "sg:city":"Merxheim",
    "sg:phone":"+49 6754/8448",
    "sg:postcode":"55627",
    "sg:province":"Rheinland-Pfalz",
    "wof:name":"Ralf Spahn Masseur",
    "wof:placetype":"venue"
},
  "geometry": {"coordinates":[7.558515,49.794464],"type":"Point"}
}