{
  "type": "Feature",
  "properties": {
    "iso:country":"DE",
    "sg:city":"M\u00fcnchen",
    "sg:postcode":"80689",
    "sg:province":"Bayern",
    "wof:name":"Marcus Schwemer Netzwerkberatung",
    "wof:placetype":"venue"
},
  "geometry": {"coordinates":[11.501365,48.135426],"type":"Point"}
}