{
  "type": "Feature",
  "properties": {
    "iso:country":"DE",
    "sg:address":"In Huk 14",
    "sg:city":"Sophienhamm",
    "sg:phone":"+49 4335/392",
    "sg:postcode":"24806",
    "sg:province":"Schleswig-Holstein",
    "wof:name":"Thiedemann",
    "wof:placetype":"venue"
},
  "geometry": {"coordinates":[9.470288,54.285637],"type":"Point"}
}