{
  "type": "Feature",
  "properties": {
    "iso:country":"DE",
    "sg:address":"Nordhorner Str. 23",
    "sg:city":"Neuenhaus",
    "sg:phone":"+49 5941/8855",
    "sg:postcode":"49828",
    "sg:province":"Niedersachsen",
    "wof:name":"Fr. Tausch",
    "wof:placetype":"venue"
},
  "geometry": {"coordinates":[6.9750699997,52.4955787659],"type":"Point"}
}