{
  "type": "Feature",
  "properties": {
    "iso:country":"DE",
    "sg:address":"Elbuferstr. 191",
    "sg:city":"Marschacht",
    "sg:phone":"+49 4176/278",
    "sg:postcode":"21436",
    "sg:province":"Niedersachsen",
    "wof:name":"Horst Pfaffenbach",
    "wof:placetype":"venue"
},
  "geometry": {"coordinates":[10.344038,53.418201],"type":"Point"}
}