{
  "type": "Feature",
  "properties": {
    "iso:country":"DE",
    "sg:address":"Augustastr. 24",
    "sg:city":"Schwetzingen",
    "sg:phone":"+49 6202/4910",
    "sg:postcode":"68723",
    "sg:province":"Baden-W\u00fcrttemberg",
    "wof:name":"Rudi Duttenhofer",
    "wof:placetype":"venue"
},
  "geometry": {"coordinates":[8.568901,49.389385],"type":"Point"}
}