{
  "type": "Feature",
  "properties": {
    "iso:country":"DE",
    "sg:address":"H\u00f6farten 17",
    "sg:city":"Schiltberg",
    "sg:phone":"+49 8445/92600",
    "sg:postcode":"86576",
    "sg:province":"Bayern",
    "wof:name":"Riedlberger Bau Gmbh",
    "wof:placetype":"venue"
},
  "geometry": {"coordinates":[11.240655,48.453182],"type":"Point"}
}