{
  "type": "Feature",
  "properties": {
    "iso:country":"DE",
    "sg:address":"Mitterfeldstr. 61 a",
    "sg:city":"M\u00fcnchen",
    "sg:phone":"+49 89/54612106",
    "sg:postcode":"80689",
    "sg:province":"Bayern",
    "wof:name":"Bayern Haus & Grund Gmbh",
    "wof:placetype":"venue"
},
  "geometry": {"coordinates":[11.484384,48.137131],"type":"Point"}
}