{
  "type": "Feature",
  "properties": {
    "iso:country":"DE",
    "sg:address":"Eickhof 34",
    "sg:city":"Minden",
    "sg:phone":"+49 571/44880",
    "sg:postcode":"32425",
    "sg:province":"Nordrhein-Westfalen",
    "wof:name":"Friedrich Blanke",
    "wof:placetype":"venue"
},
  "geometry": {"coordinates":[8.910707,52.321156],"type":"Point"}
}