{
  "type": "Feature",
  "properties": {
    "iso:country":"DE",
    "sg:address":"Ro\u00dfkampffstr. 15-17",
    "sg:city":"Heilbronn",
    "sg:phone":"+49 7131/62420",
    "sg:postcode":"74072",
    "sg:province":"Baden-W\u00fcrttemberg",
    "wof:name":"Hotel Central",
    "wof:placetype":"venue"
},
  "geometry": {"coordinates":[9.2099666595,49.1416282654],"type":"Point"}
}