{
  "type": "Feature",
  "properties": {
    "iso:country":"DE",
    "sg:address":"Keltenweg 13",
    "sg:city":"Kaiserslautern",
    "sg:phone":"+49 631/59613",
    "sg:postcode":"67663",
    "sg:province":"Rheinland-Pfalz",
    "wof:name":"Adolf Raab",
    "wof:placetype":"venue"
},
  "geometry": {"coordinates":[7.730661869,49.4365463257],"type":"Point"}
}