{
  "type": "Feature",
  "properties": {
    "iso:country":"DE",
    "sg:address":"Kantelberg 13a",
    "sg:city":"Hennef",
    "sg:phone":"+49 2248/3700",
    "sg:postcode":"53773",
    "sg:province":"Nordrhein-Westfalen",
    "wof:name":"Reiner Schmitz",
    "wof:placetype":"venue"
},
  "geometry": {"coordinates":[7.369827,50.726803],"type":"Point"}
}