{
  "type": "Feature",
  "properties": {
    "iso:country":"DE",
    "sg:address":"Industriestr. 40",
    "sg:city":"Heinsberg",
    "sg:phone":"+49 2452/91150",
    "sg:postcode":"52525",
    "sg:province":"Nordrhein-Westfalen",
    "wof:name":"H. Hausmann Rechtsanwalt",
    "wof:placetype":"venue"
},
  "geometry": {"coordinates":[6.1088871956,51.0633773804],"type":"Point"}
}