{
  "type": "Feature",
  "properties": {
    "iso:country":"DE",
    "sg:address":"Kirmaierstr. 2",
    "sg:city":"Unterneukirchen",
    "sg:phone":"+49 8634/5242",
    "sg:postcode":"84579",
    "sg:province":"Bayern",
    "wof:name":"Sebastian Reisinger",
    "wof:placetype":"venue"
},
  "geometry": {"coordinates":[12.623845,48.164879],"type":"Point"}
}