{
  "type": "Feature",
  "properties": {
    "iso:country":"DE",
    "sg:address":"Sudetendeutsche Str. 55",
    "sg:city":"Regensburg",
    "sg:phone":"+49 941/6400877",
    "sg:postcode":"93057",
    "sg:province":"Bayern",
    "wof:name":"Hans Meier Heilpraktiker",
    "wof:placetype":"venue"
},
  "geometry": {"coordinates":[12.1222696304,49.0375823975],"type":"Point"}
}