{
  "type": "Feature",
  "properties": {
    "iso:country":"DE",
    "sg:address":"K\u00fcckstr. 21",
    "sg:city":"Baesweiler",
    "sg:phone":"+49 2401/4212",
    "sg:postcode":"52499",
    "sg:province":"Nordrhein-Westfalen",
    "wof:name":"Juliane Timmermanns",
    "wof:placetype":"venue"
},
  "geometry": {"coordinates":[6.17944,50.908958],"type":"Point"}
}