{
  "type": "Feature",
  "properties": {
    "iso:country":"DE",
    "sg:address":"Gallweg 55",
    "sg:city":"Meerbeck",
    "sg:phone":"+49 5721/77001",
    "sg:postcode":"31715",
    "sg:province":"Niedersachsen",
    "wof:name":"Betonsteinwerk Volksdorf Gmbh",
    "wof:placetype":"venue"
},
  "geometry": {"coordinates":[9.1350831985,52.3411216736],"type":"Point"}
}