{
  "type": "Feature",
  "properties": {
    "iso:country":"DE",
    "sg:address":"Einer Str. 10",
    "sg:city":"Goldenstedt",
    "sg:phone":"+49 4434/1237",
    "sg:postcode":"49424",
    "sg:province":"Niedersachsen",
    "wof:name":"Hermann Marischen",
    "wof:placetype":"venue"
},
  "geometry": {"coordinates":[8.449819,52.80122],"type":"Point"}
}