{
  "type": "Feature",
  "properties": {
    "iso:country":"DE",
    "sg:address":"Batzengschwenden",
    "sg:city":"R\u00fcckholz",
    "sg:phone":"+49 8369/207",
    "sg:postcode":"87494",
    "sg:province":"Bayern",
    "wof:name":"Georg Reichart",
    "wof:placetype":"venue"
},
  "geometry": {"coordinates":[10.5626039505,47.6557579041],"type":"Point"}
}