{
  "type": "Feature",
  "properties": {
    "iso:country":"DE",
    "sg:address":"H\u00f6herweg 252 A",
    "sg:city":"D\u00fcsseldorf",
    "sg:phone":"+49 211/7337371",
    "sg:postcode":"40231",
    "sg:province":"Nordrhein-Westfalen",
    "wof:name":"Mawa Metall Gmbh",
    "wof:placetype":"venue"
},
  "geometry": {"coordinates":[6.82585,51.221554],"type":"Point"}
}