{
  "type": "Feature",
  "properties": {
    "iso:country":"DE",
    "sg:address":"Kohnenweg 2",
    "sg:city":"Wassenberg",
    "sg:phone":"+49 2432/80972",
    "sg:postcode":"41849",
    "sg:province":"Nordrhein-Westfalen",
    "wof:name":"Tms Bautz Tischlerei- Und Montageservice Gmbh",
    "wof:placetype":"venue"
},
  "geometry": {"coordinates":[6.196492,51.100952],"type":"Point"}
}