{
  "type": "Feature",
  "properties": {
    "iso:country":"DE",
    "sg:address":"Mozartstr. 31",
    "sg:city":"Balingen",
    "sg:phone":"+49 7433/7787",
    "sg:postcode":"72336",
    "sg:province":"Baden-W\u00fcrttemberg",
    "wof:name":"Peter F\u00e4rber",
    "wof:placetype":"venue"
},
  "geometry": {"coordinates":[8.865873,48.276718],"type":"Point"}
}