{
  "type": "Feature",
  "properties": {
    "iso:country":"DE",
    "sg:address":"Schulstr. 16",
    "sg:city":"Gro\u00dfhartmannsdorf",
    "sg:phone":"+49 37329/4116",
    "sg:postcode":"09618",
    "sg:province":"Sachsen",
    "wof:name":"Holzhandel Neubert Gmbh",
    "wof:placetype":"venue"
},
  "geometry": {"coordinates":[13.30338,50.761639],"type":"Point"}
}