{
  "type": "Feature",
  "properties": {
    "iso:country":"DE",
    "sg:address":"Ahornweg 8",
    "sg:city":"Gaimersheim",
    "sg:phone":"+49 8406/91104",
    "sg:postcode":"85080",
    "sg:province":"Bayern",
    "wof:name":"Edeltraud Warg",
    "wof:placetype":"venue"
},
  "geometry": {"coordinates":[11.36923,48.838455],"type":"Point"}
}