{
  "type": "Feature",
  "properties": {
    "iso:country":"DE",
    "sg:address":"Rudolf-Diesel-Str 25",
    "sg:city":"Vechta",
    "sg:phone":"+49 4441/4066",
    "sg:postcode":"49377",
    "sg:province":"Niedersachsen",
    "wof:name":"Pro-pac Ostendorf Plastic Thermoformfolien Und Verpackungen Gmbh & Co Kg",
    "wof:placetype":"venue"
},
  "geometry": {"coordinates":[8.274219,52.750275],"type":"Point"}
}