{
  "type": "Feature",
  "properties": {
    "iso:country":"DE",
    "sg:address":"Trattendorfer Str. 5",
    "sg:city":"Cottbus",
    "sg:phone":"+49 355/522237",
    "sg:postcode":"03048",
    "sg:province":"Brandenburg",
    "wof:name":"Dr. Med. Brunhilde Israel",
    "wof:placetype":"venue"
},
  "geometry": {"coordinates":[14.3233757019,51.7321090698],"type":"Point"}
}