{
  "type": "Feature",
  "properties": {
    "iso:country":"DE",
    "sg:address":"St.-Maternus-Str. 7",
    "sg:city":"Wegberg",
    "sg:phone":"+49 2434/4515",
    "sg:postcode":"41844",
    "sg:province":"Nordrhein-Westfalen",
    "wof:name":"Intersmitten",
    "wof:placetype":"venue"
},
  "geometry": {"coordinates":[6.278690815,51.1415596008],"type":"Point"}
}