{
  "type": "Feature",
  "properties": {
    "iso:country":"DE",
    "sg:address":"Neugasse 5",
    "sg:city":"Ober-M\u00f6rlen",
    "sg:phone":"+49 6002/92216",
    "sg:postcode":"61239",
    "sg:province":"Hessen",
    "wof:name":"T. Fritz",
    "wof:placetype":"venue"
},
  "geometry": {"coordinates":[8.692519,50.373497],"type":"Point"}
}