{
  "type": "Feature",
  "properties": {
    "iso:country":"DE",
    "sg:address":"Am Bruckweg 118",
    "sg:city":"N\u00fcrnberg",
    "sg:phone":"+49 9129/3455",
    "sg:postcode":"90455",
    "sg:province":"Bayern",
    "wof:name":"Arbeitsgemeinschaft Allergie- Krankes Kind E. V.",
    "wof:placetype":"venue"
},
  "geometry": {"coordinates":[11.104675293,49.3592681885],"type":"Point"}
}