{
  "type": "Feature",
  "properties": {
    "iso:country":"DE",
    "sg:address":"Wachtbergweg 30",
    "sg:city":"Bad Brambach",
    "sg:phone":"+49 37438/20278",
    "sg:postcode":"08648",
    "sg:province":"Sachsen",
    "wof:name":"Stelu Bau Gmbh",
    "wof:placetype":"venue"
},
  "geometry": {"coordinates":[12.304612,50.20837],"type":"Point"}
}