{
  "type": "Feature",
  "properties": {
    "iso:country":"DE",
    "sg:address":"Bajuwarenring 19",
    "sg:city":"Oberhaching",
    "sg:phone":"+49 89/6660960",
    "sg:postcode":"82041",
    "sg:province":"Bayern",
    "wof:name":"Inonet Computer Gmbh",
    "wof:placetype":"venue"
},
  "geometry": {"coordinates":[11.5834636688,48.0328712463],"type":"Point"}
}