{
  "type": "Feature",
  "properties": {
    "iso:country":"DE",
    "sg:address":"Ludwig-Chronegk-Str. 4",
    "sg:city":"Meiningen",
    "sg:phone":"+49 3693/476666",
    "sg:postcode":"98617",
    "sg:province":"Th\u00fcringen",
    "wof:name":"Igm Immobilien Gmbh",
    "wof:placetype":"venue"
},
  "geometry": {"coordinates":[10.4141016006,50.5687026978],"type":"Point"}
}