{
  "type": "Feature",
  "properties": {
    "iso:country":"DE",
    "sg:address":"Liebigstr 26a",
    "sg:city":"Solingen",
    "sg:phone":"+49 212/204905",
    "sg:postcode":"42719",
    "sg:province":"Nordrhein-Westfalen",
    "wof:name":"Galvano Gestellbau Ocaktan Gmbh",
    "wof:placetype":"venue"
},
  "geometry": {"coordinates":[7.031173,51.176189],"type":"Point"}
}