{
  "type": "Feature",
  "properties": {
    "iso:country":"DE",
    "sg:address":"Waldweg 17",
    "sg:city":"Quickborn",
    "sg:phone":"+49 4106/72165",
    "sg:postcode":"25451",
    "sg:province":"Schleswig-Holstein",
    "wof:name":"Charly Textilhandel Publishing Gmbh & Co. Kg",
    "wof:placetype":"venue"
},
  "geometry": {"coordinates":[9.971894,53.752254],"type":"Point"}
}