{
  "type": "Feature",
  "properties": {
    "iso:country":"DE",
    "sg:address":"Wiesensteiger Weg 1/1",
    "sg:city":"Lenningen",
    "sg:postcode":"73252",
    "sg:province":"Baden-W\u00fcrttemberg",
    "wof:name":"Media 3 Werbeagentur E. K.",
    "wof:placetype":"venue"
},
  "geometry": {"coordinates":[9.533914566,48.5405540466],"type":"Point"}
}