{
  "type": "Feature",
  "properties": {
    "iso:country":"DE",
    "sg:address":"T\u00f6pfergrube 7",
    "sg:city":"Kiel",
    "sg:phone":"+49 431/6470110",
    "sg:postcode":"24113",
    "sg:province":"Schleswig-Holstein",
    "wof:name":"A S S - Kiel",
    "wof:placetype":"venue"
},
  "geometry": {"coordinates":[10.104081,54.29863],"type":"Point"}
}