{
  "type": "Feature",
  "properties": {
    "iso:country":"DE",
    "sg:address":"Markt 18",
    "sg:city":"Glauchau",
    "sg:phone":"+49 3763/2528",
    "sg:postcode":"08371",
    "sg:province":"Sachsen",
    "wof:name":"E. A. Sch\u00f6ltzke",
    "wof:placetype":"venue"
},
  "geometry": {"coordinates":[12.5414590836,50.818031311],"type":"Point"}
}