{
  "type": "Feature",
  "properties": {
    "iso:country":"DE",
    "sg:address":"Carl-von-Linde-Str. 4",
    "sg:city":"K\u00f6ln",
    "sg:phone":"+49 2234/946570",
    "sg:postcode":"50999",
    "sg:province":"Nordrhein-Westfalen",
    "wof:name":"Ipn-institut F\u00fcr Pr\u00e4vention U. Nachsorge Ges. F. Gesund-",
    "wof:placetype":"venue"
},
  "geometry": {"coordinates":[7.0182647705,50.8670730591],"type":"Point"}
}