{
  "type": "Feature",
  "properties": {
    "iso:country":"DE",
    "sg:address":"Rosenheimer Str. 18",
    "sg:city":"Gro\u00dfhelfendorf",
    "sg:phone":"+49 8095/870214",
    "sg:postcode":"85655",
    "wof:name":"Hans Bitzer Handelsvertretungs Gmbh",
    "wof:placetype":"venue"
},
  "geometry": {"coordinates":[11.79442,47.941975],"type":"Point"}
}