{
  "type": "Feature",
  "properties": {
    "iso:country":"DE",
    "sg:address":"Schlattweg 16",
    "sg:city":"Salzstetten",
    "sg:phone":"+49 7486/7079",
    "sg:postcode":"72178",
    "sg:province":"Baden-W\u00fcrttemberg",
    "wof:name":"Optiquick Knieschoner Knieschutz",
    "wof:placetype":"venue"
},
  "geometry": {"coordinates":[8.598923,48.493389],"type":"Point"}
}