{
  "type": "Feature",
  "properties": {
    "iso:country":"DE",
    "sg:address":"Brink 10",
    "sg:city":"Telgte",
    "sg:phone":"+49 2504/8519",
    "sg:postcode":"48291",
    "sg:province":"Nordrhein-Westfalen",
    "wof:name":"Dr. Helmut Mersmann Arzt F\u00fcr Tierheilkunde",
    "wof:placetype":"venue"
},
  "geometry": {"coordinates":[7.7522640228,52.0349502563],"type":"Point"}
}