{
  "type": "Feature",
  "properties": {
    "iso:country":"DE",
    "sg:address":"Widdersdorfer Str. 403",
    "sg:city":"K\u00f6ln",
    "sg:phone":"+49 221/499660",
    "sg:postcode":"50933",
    "sg:province":"Nordrhein-Westfalen",
    "wof:name":"Schufa-schutzgemeinschaft F\u00fcr Allgemeine Kreditsicherung",
    "wof:placetype":"venue"
},
  "geometry": {"coordinates":[6.886442,50.947155],"type":"Point"}
}