{
  "type": "Feature",
  "properties": {
    "iso:country":"DE",
    "sg:address":"Warendorfer Landweg 10",
    "sg:city":"Sassenberg",
    "sg:postcode":"48336",
    "sg:province":"Nordrhein-Westfalen",
    "wof:name":"August Korte",
    "wof:placetype":"venue"
},
  "geometry": {"coordinates":[8.055395,51.96236],"type":"Point"}
}