{
  "type": "Feature",
  "properties": {
    "iso:country":"DE",
    "sg:address":"Hofackerweg 4",
    "sg:city":"Lohr",
    "sg:phone":"+49 9352/4522",
    "sg:postcode":"97816",
    "sg:province":"Bayern",
    "wof:name":"Friederike Scherg",
    "wof:placetype":"venue"
},
  "geometry": {"coordinates":[9.570424,49.982044],"type":"Point"}
}