{
  "type": "Feature",
  "properties": {
    "iso:country":"DE",
    "sg:address":"Neue Strasse 2",
    "sg:city":"Ober-Hainbrunn",
    "sg:phone":"+49 6275/1355",
    "sg:postcode":"64757",
    "sg:province":"Hessen",
    "wof:name":"Minitruckstore",
    "wof:placetype":"venue"
},
  "geometry": {"coordinates":[8.9034948349,49.4875411987],"type":"Point"}
}