{
  "type": "Feature",
  "properties": {
    "iso:country":"DE",
    "sg:address":"Hansaring 9",
    "sg:city":"Lotte",
    "sg:phone":"+49 5404/1473",
    "sg:postcode":"49504",
    "sg:province":"Nordrhein-Westfalen",
    "wof:name":"Werner Temme",
    "wof:placetype":"venue"
},
  "geometry": {"coordinates":[7.916088,52.282391],"type":"Point"}
}