{
  "type": "Feature",
  "properties": {
    "iso:country":"DE",
    "sg:address":"Lindenstr 26",
    "sg:city":"Obernburg",
    "sg:phone":"+49 6022/623680",
    "sg:postcode":"63785",
    "sg:province":"Bayern",
    "wof:name":"Ela-flockteam Siegfried Fuchs",
    "wof:placetype":"venue"
},
  "geometry": {"coordinates":[9.1470832825,49.8431930542],"type":"Point"}
}