{
  "type": "Feature",
  "properties": {
    "iso:country":"DE",
    "sg:address":"Bertholdstr. 3",
    "sg:city":"Duisburg",
    "sg:phone":"+49 2065/51442",
    "sg:postcode":"47226",
    "sg:province":"Nordrhein-Westfalen",
    "wof:name":"Dagmar Reuter",
    "wof:placetype":"venue"
},
  "geometry": {"coordinates":[6.7142710686,51.4100112915],"type":"Point"}
}