{
  "type": "Feature",
  "properties": {
    "iso:country":"DE",
    "sg:address":"Nycolaistr. 9",
    "sg:city":"Paderborn",
    "sg:phone":"+49 5293/8376",
    "sg:postcode":"33100",
    "sg:province":"Nordrhein-Westfalen",
    "wof:name":"Margarita Malinowska",
    "wof:placetype":"venue"
},
  "geometry": {"coordinates":[8.84531,51.69923],"type":"Point"}
}