{
  "type": "Feature",
  "properties": {
    "iso:country":"DE",
    "sg:address":"Wilhelmstr. 21",
    "sg:city":"Obermoschel",
    "sg:phone":"+49 6362/1290",
    "sg:postcode":"67823",
    "sg:province":"Rheinland-Pfalz",
    "wof:name":"Rudolf Gauch",
    "wof:placetype":"venue"
},
  "geometry": {"coordinates":[7.7732901573,49.7275924683],"type":"Point"}
}