{
  "type": "Feature",
  "properties": {
    "iso:country":"DE",
    "sg:address":"Uracher Str. 3",
    "sg:city":"Leonberg",
    "sg:phone":"+49 7152/46655",
    "sg:postcode":"71229",
    "sg:province":"Baden-W\u00fcrttemberg",
    "wof:name":"Niemeier",
    "wof:placetype":"venue"
},
  "geometry": {"coordinates":[8.998380661,48.7901687622],"type":"Point"}
}