{
  "type": "Feature",
  "properties": {
    "iso:country":"DE",
    "sg:address":"L\u00e4mmkenstatt 40",
    "sg:city":"Bielefeld",
    "sg:phone":"+49 521/761278",
    "sg:postcode":"33729",
    "sg:province":"Nordrhein-Westfalen",
    "wof:name":"F. Neumann",
    "wof:placetype":"venue"
},
  "geometry": {"coordinates":[8.6085758209,52.076675415],"type":"Point"}
}