{
  "type": "Feature",
  "properties": {
    "iso:country":"DE",
    "sg:address":"Oberbalzheimer Str. 17",
    "sg:city":"Altenstadt",
    "sg:phone":"+49 8337/310",
    "sg:postcode":"89281",
    "sg:province":"Bayern",
    "wof:name":"Illerst\u00fcble",
    "wof:placetype":"venue"
},
  "geometry": {"coordinates":[10.1054401398,48.1591796875],"type":"Point"}
}