{
  "type": "Feature",
  "properties": {
    "iso:country":"DE",
    "sg:address":"St\u00e4dtlerstr. 3",
    "sg:city":"Roth",
    "sg:phone":"+49 9171/2682",
    "sg:postcode":"91154",
    "sg:province":"Bayern",
    "wof:name":"J\u00fcrgen Meier",
    "wof:placetype":"venue"
},
  "geometry": {"coordinates":[11.0911417007,49.244682312],"type":"Point"}
}