{
  "type": "Feature",
  "properties": {
    "iso:country":"DE",
    "sg:address":"Elfsaal 20",
    "sg:city":"Hamburg",
    "sg:phone":"+49 40/20224977",
    "sg:postcode":"22043",
    "sg:province":"Hamburg",
    "wof:name":"Pflegen & Wohnen Ambulante Pflege",
    "wof:placetype":"venue"
},
  "geometry": {"coordinates":[10.119425,53.568665],"type":"Point"}
}