{
  "type": "Feature",
  "properties": {
    "iso:country":"DE",
    "sg:address":"Humperdinck Str. 4",
    "sg:city":"Berlin",
    "sg:phone":"+49 30/72324476",
    "sg:postcode":"12247",
    "sg:province":"Berlin",
    "wof:name":"Freepic.de",
    "wof:placetype":"venue"
},
  "geometry": {"coordinates":[13.334376,52.435577],"type":"Point"}
}