{
  "type": "Feature",
  "properties": {
    "iso:country":"DE",
    "sg:address":"Bahnhofstr. 2",
    "sg:city":"Bad Bevensen",
    "sg:phone":"+49 5821/41610",
    "sg:postcode":"29549",
    "sg:province":"Niedersachsen",
    "wof:name":"Bernhard Ludwig",
    "wof:placetype":"venue"
},
  "geometry": {"coordinates":[10.5778331757,53.0800094604],"type":"Point"}
}