{
  "type": "Feature",
  "properties": {
    "iso:country":"DE",
    "sg:address":"Burgbergweg 13",
    "sg:city":"Balve",
    "sg:phone":"+49 2375/910342",
    "sg:postcode":"58802",
    "sg:province":"Nordrhein-Westfalen",
    "wof:name":"Horst Walkhoff",
    "wof:placetype":"venue"
},
  "geometry": {"coordinates":[7.8979420662,51.3283348083],"type":"Point"}
}