{
  "type": "Feature",
  "properties": {
    "iso:country":"DE",
    "sg:address":"M\u00fchlenbreite 8",
    "sg:city":"Obernkirchen",
    "sg:phone":"+49 5724/6311",
    "sg:postcode":"31683",
    "sg:province":"Niedersachsen",
    "wof:name":"Astor Lederwaren-handels- Gmbh",
    "wof:placetype":"venue"
},
  "geometry": {"coordinates":[9.1373720169,52.2755775452],"type":"Point"}
}