{
  "type": "Feature",
  "properties": {
    "iso:country":"DE",
    "sg:address":"Barkhausenstr. 13",
    "sg:city":"Langeoog",
    "sg:phone":"+49 4972/6514",
    "sg:postcode":"26465",
    "sg:province":"Niedersachsen",
    "wof:name":"Cafe Heinrich Leiss Inh. Brigit Kolb-binder",
    "wof:placetype":"venue"
},
  "geometry": {"coordinates":[7.480013,53.747795],"type":"Point"}
}