{
  "type": "Feature",
  "properties": {
    "iso:country":"DE",
    "sg:address":"Voglerstr.40",
    "sg:city":"Dresden",
    "sg:postcode":"01277",
    "sg:province":"Sachsen",
    "wof:name":"Willkommen In Der Homezone Von By Your Site",
    "wof:placetype":"venue"
},
  "geometry": {"coordinates":[13.802914,51.042351],"type":"Point"}
}