{
  "type": "Feature",
  "properties": {
    "iso:country":"DE",
    "sg:address":"H\u00fclsbree 3",
    "sg:city":"Borken",
    "sg:phone":"+49 2861/1767",
    "sg:postcode":"46325",
    "sg:province":"Nordrhein-Westfalen",
    "wof:name":"Heinrich Kappenhagen",
    "wof:placetype":"venue"
},
  "geometry": {"coordinates":[6.797333,51.829411],"type":"Point"}
}