{
  "type": "Feature",
  "properties": {
    "iso:country":"DE",
    "sg:address":"Bergstr. 45",
    "sg:city":"Horb",
    "sg:postcode":"72160",
    "sg:province":"Baden-W\u00fcrttemberg",
    "wof:name":"Barbara Staudacher Verlag E.k.",
    "wof:placetype":"venue"
},
  "geometry": {"coordinates":[8.6492357254,48.441078186],"type":"Point"}
}