{
  "type": "Feature",
  "properties": {
    "iso:country":"DE",
    "sg:address":"Crispinstr. 73",
    "sg:city":"Dortmund",
    "sg:phone":"+49 231/735425",
    "sg:postcode":"44229",
    "sg:province":"Nordrhein-Westfalen",
    "wof:name":"Ernst Radtke",
    "wof:placetype":"venue"
},
  "geometry": {"coordinates":[7.460035,51.445427],"type":"Point"}
}