{
  "type": "Feature",
  "properties": {
    "iso:country":"DE",
    "sg:address":"Ritterstr. 30-31",
    "sg:city":"D\u00f6beln",
    "sg:phone":"+49 3431/711400",
    "sg:postcode":"04720",
    "sg:province":"Sachsen",
    "wof:name":"Harro Fassbinder",
    "wof:placetype":"venue"
},
  "geometry": {"coordinates":[13.1229705811,51.1229133606],"type":"Point"}
}