{
  "type": "Feature",
  "properties": {
    "iso:country":"DE",
    "sg:address":"Pferdemarkt 2",
    "sg:city":"Pr\u00fcm",
    "sg:phone":"+49 6551/985101",
    "sg:postcode":"54595",
    "sg:province":"Rheinland-Pfalz",
    "wof:name":"Petermann Gmbh",
    "wof:placetype":"venue"
},
  "geometry": {"coordinates":[6.424091,50.210556],"type":"Point"}
}