{
  "type": "Feature",
  "properties": {
    "iso:country":"DE",
    "sg:address":"Am Ohlenberg 4",
    "sg:city":"Elz",
    "sg:phone":"+49 6431/51435",
    "sg:postcode":"65604",
    "sg:province":"Hessen",
    "wof:name":"Ernst Und Georg Klersy",
    "wof:placetype":"venue"
},
  "geometry": {"coordinates":[8.029445,50.413029],"type":"Point"}
}