{
  "type": "Feature",
  "properties": {
    "iso:country":"DE",
    "sg:address":"Unterer Kirchweg 9",
    "sg:city":"Badenweiler",
    "sg:phone":"+49 7632/82080",
    "sg:postcode":"79410",
    "sg:province":"Baden-W\u00fcrttemberg",
    "wof:name":"Hotel Sonnhalde",
    "wof:placetype":"venue"
},
  "geometry": {"coordinates":[7.6712498665,47.8049087524],"type":"Point"}
}