{
  "type": "Feature",
  "properties": {
    "iso:country":"DE",
    "sg:address":"Hauptstuhler Str. 1",
    "sg:city":"H\u00fctschenhausen",
    "sg:phone":"+49 6372/1494",
    "sg:postcode":"66882",
    "sg:province":"Rheinland-Pfalz",
    "wof:name":"Hans-peter Cappel",
    "wof:placetype":"venue"
},
  "geometry": {"coordinates":[7.481958,49.419235],"type":"Point"}
}