{
  "type": "Feature",
  "properties": {
    "iso:country":"DE",
    "sg:address":"Roseggerweg 17",
    "sg:city":"Rosenheim",
    "sg:phone":"+49 8031/66387",
    "sg:postcode":"83026",
    "sg:province":"Bayern",
    "wof:name":"T. Gruber Anlageberater",
    "wof:placetype":"venue"
},
  "geometry": {"coordinates":[12.0979003906,47.8275413513],"type":"Point"}
}