{
  "type": "Feature",
  "properties": {
    "iso:country":"DE",
    "sg:address":"Sternstr. 22",
    "sg:city":"M\u00fcnchen",
    "sg:phone":"+49 89/221108",
    "sg:postcode":"80538",
    "sg:province":"Bayern",
    "wof:name":"Redaktion Autokauf Hofer Verlag",
    "wof:placetype":"venue"
},
  "geometry": {"coordinates":[11.5912322998,48.1398086548],"type":"Point"}
}