{
  "type": "Feature",
  "properties": {
    "iso:country":"DE",
    "sg:address":"Hauptstr. 25",
    "sg:city":"Ettringen",
    "sg:phone":"+49 2651/2543",
    "sg:postcode":"56729",
    "sg:province":"Rheinland-Pfalz",
    "wof:name":"B\u00e4ckerei Hans Lenartz",
    "wof:placetype":"venue"
},
  "geometry": {"coordinates":[7.221119,50.355984],"type":"Point"}
}