{
  "type": "Feature",
  "properties": {
    "iso:country":"DE",
    "sg:address":"In den Kirchenmatten 34",
    "sg:city":"Freiburg",
    "sg:phone":"+49 761/892324",
    "sg:postcode":"79110",
    "sg:province":"Baden-W\u00fcrttemberg",
    "wof:name":"Dieter Keppeler",
    "wof:placetype":"venue"
},
  "geometry": {"coordinates":[7.795853138,48.0235404968],"type":"Point"}
}