{
  "type": "Feature",
  "properties": {
    "iso:country":"DE",
    "sg:address":"N\u00fcrnberger Str. 15",
    "sg:city":"Pegnitz",
    "sg:phone":"+49 9241/80751",
    "sg:postcode":"91257",
    "sg:province":"Bayern",
    "wof:name":"Eugen Pflaum",
    "wof:placetype":"venue"
},
  "geometry": {"coordinates":[11.5381698608,49.7530593872],"type":"Point"}
}