{
  "type": "Feature",
  "properties": {
    "iso:country":"DE",
    "sg:address":"Schweriner Str. 39",
    "sg:city":"Pampow",
    "sg:phone":"+49 3865/75418",
    "sg:postcode":"19075",
    "sg:province":"Mecklenburg-Vorpommern",
    "wof:name":"Pizzeria Mit Wintergarten",
    "wof:placetype":"venue"
},
  "geometry": {"coordinates":[11.3574409485,53.5671272278],"type":"Point"}
}