{
  "type": "Feature",
  "properties": {
    "iso:country":"DE",
    "sg:address":"Gabelsbergerstr. 16",
    "sg:city":"Trostberg",
    "sg:phone":"+49 8621/62777",
    "sg:postcode":"83308",
    "sg:province":"Bayern",
    "wof:name":"Hubert Ober",
    "wof:placetype":"venue"
},
  "geometry": {"coordinates":[12.5577602386,48.0266494751],"type":"Point"}
}