{
  "type": "Feature",
  "properties": {
    "iso:country":"DE",
    "sg:address":"Schierlingsfeld 1",
    "sg:city":"Cappeln",
    "sg:postcode":"49692",
    "sg:province":"Niedersachsen",
    "wof:name":"Caribu Travel Gmbh",
    "wof:placetype":"venue"
},
  "geometry": {"coordinates":[8.1237821579,52.802116394],"type":"Point"}
}