{
  "type": "Feature",
  "properties": {
    "iso:country":"DE",
    "sg:address":"Friedrichstr. 43",
    "sg:city":"Aalen",
    "sg:phone":"+49 7361/680102",
    "sg:postcode":"73430",
    "sg:province":"Baden-W\u00fcrttemberg",
    "wof:name":"Georg Gruszka",
    "wof:placetype":"venue"
},
  "geometry": {"coordinates":[10.0887336731,48.838470459],"type":"Point"}
}