{
  "type": "Feature",
  "properties": {
    "iso:country":"DE",
    "sg:address":"Energiestr. 5",
    "sg:city":"Tuttlingen",
    "sg:phone":"+49 7461/71286",
    "sg:postcode":"78532",
    "sg:province":"Baden-W\u00fcrttemberg",
    "wof:name":"Gerhard Klappenecker",
    "wof:placetype":"venue"
},
  "geometry": {"coordinates":[8.853835,48.007221],"type":"Point"}
}