{
  "type": "Feature",
  "properties": {
    "iso:country":"DE",
    "sg:address":"Wiesenstr. 13",
    "sg:city":"B\u00f6hen",
    "sg:phone":"+49 8338/1061",
    "sg:postcode":"87736",
    "sg:province":"Bayern",
    "wof:name":"Klemens Albrecht",
    "wof:placetype":"venue"
},
  "geometry": {"coordinates":[10.300766,47.882412],"type":"Point"}
}