{
  "type": "Feature",
  "properties": {
    "iso:country":"DE",
    "sg:address":"Nachtwaidstr. 1a",
    "sg:city":"B\u00f6tzingen",
    "sg:phone":"+49 7663/5678",
    "sg:postcode":"79268",
    "sg:province":"Baden-W\u00fcrttemberg",
    "wof:name":"Bernd Krumm Rechtsanwalt",
    "wof:placetype":"venue"
},
  "geometry": {"coordinates":[7.7175111771,48.0695381165],"type":"Point"}
}