{
  "type": "Feature",
  "properties": {
    "iso:country":"DE",
    "sg:address":"Lange Str. 24",
    "sg:city":"Offenburg",
    "sg:phone":"+49 781/76903",
    "sg:postcode":"77652",
    "sg:province":"Baden-W\u00fcrttemberg",
    "wof:name":"Engel-apotheke Inh. Gabriele Engel",
    "wof:placetype":"venue"
},
  "geometry": {"coordinates":[7.94541,48.470135],"type":"Point"}
}