{
  "type": "Feature",
  "properties": {
    "iso:country":"DE",
    "sg:address":"Prellerstr. 62",
    "sg:city":"Leipzig",
    "sg:phone":"+49 341/593590",
    "sg:postcode":"04155",
    "sg:province":"Sachsen",
    "wof:name":"Kreitz Und Partner",
    "wof:placetype":"venue"
},
  "geometry": {"coordinates":[12.373736,51.358879],"type":"Point"}
}