{
  "type": "Feature",
  "properties": {
    "iso:country":"DE",
    "sg:address":"Ubierring 11",
    "sg:city":"K\u00f6ln",
    "sg:phone":"+49 221/33020",
    "sg:postcode":"50678",
    "sg:province":"Nordrhein-Westfalen",
    "wof:name":"Datatransit Gesellschaft F\u00fcr Elektronischen Datenaus-",
    "wof:placetype":"venue"
},
  "geometry": {"coordinates":[6.960823,50.921509],"type":"Point"}
}