{
  "type": "Feature",
  "properties": {
    "iso:country":"DE",
    "sg:address":"R\u00f6hre 4",
    "sg:city":"Sundern",
    "sg:phone":"+49 2933/5373",
    "sg:postcode":"59846",
    "sg:province":"Nordrhein-Westfalen",
    "wof:name":"Gerken & Schulte-huermann Metallwaren Gmbh",
    "wof:placetype":"venue"
},
  "geometry": {"coordinates":[8.007172,51.318684],"type":"Point"}
}