{
  "type": "Feature",
  "properties": {
    "iso:country":"DE",
    "sg:address":"Klaus-Groth-Str. 23",
    "sg:city":"Gl\u00fcckstadt",
    "sg:phone":"+49 4124/2710",
    "sg:postcode":"25348",
    "sg:province":"Schleswig-Holstein",
    "wof:name":"Gl\u00fcckst\u00e4dter Wohnungsbau Gmbh",
    "wof:placetype":"venue"
},
  "geometry": {"coordinates":[9.4210996628,53.7957344055],"type":"Point"}
}