{
  "type": "Feature",
  "properties": {
    "iso:country":"DE",
    "sg:address":"Binger Str. 173",
    "sg:city":"Ingelheim",
    "sg:phone":"+49 6132/770",
    "sg:postcode":"55218",
    "sg:province":"Rheinland-Pfalz",
    "wof:name":"Boehringer Backmittel Gmbh",
    "wof:placetype":"venue"
},
  "geometry": {"coordinates":[8.03816,49.972961],"type":"Point"}
}