{
  "type": "Feature",
  "properties": {
    "iso:country":"DE",
    "sg:address":"Dovestr 1",
    "sg:city":"Berlin",
    "sg:phone":"+49 30/39805400",
    "sg:postcode":"10587",
    "sg:province":"Berlin",
    "wof:name":"Novacom Gesellschaft F\u00fcr Internet Services Software Engineering Und Consulting Mbh",
    "wof:placetype":"venue"
},
  "geometry": {"coordinates":[13.319784,52.519966],"type":"Point"}
}