{
  "type": "Feature",
  "properties": {
    "iso:country":"DE",
    "sg:address":"Weingartsgreuth 55",
    "sg:city":"Wachenroth",
    "sg:phone":"+49 9548/364",
    "sg:postcode":"96193",
    "sg:province":"Bayern",
    "wof:name":"Pension M. Klaus",
    "wof:placetype":"venue"
},
  "geometry": {"coordinates":[10.7287902832,49.7309608459],"type":"Point"}
}