{
  "type": "Feature",
  "properties": {
    "iso:country":"DE",
    "sg:address":"Gladbacher Str. 238",
    "sg:city":"Elsdorf",
    "sg:phone":"+49 2274/905974",
    "sg:postcode":"50189",
    "sg:province":"Nordrhein-Westfalen",
    "wof:name":"F. N\u00f6thgen",
    "wof:placetype":"venue"
},
  "geometry": {"coordinates":[6.5441198349,50.9425621033],"type":"Point"}
}