{
  "type": "Feature",
  "properties": {
    "iso:country":"DE",
    "sg:address":"Glemsgaustr. 16",
    "sg:city":"Stuttgart",
    "sg:phone":"+49 711/8666610",
    "sg:postcode":"70499",
    "sg:province":"Baden-W\u00fcrttemberg",
    "wof:name":"Gutekunst",
    "wof:placetype":"venue"
},
  "geometry": {"coordinates":[9.1114521027,48.8152236938],"type":"Point"}
}