{
  "type": "Feature",
  "properties": {
    "iso:country":"DE",
    "sg:address":"Wollmatinger Str. 57",
    "sg:city":"Konstanz",
    "sg:phone":"+49 7531/67410",
    "sg:postcode":"78467",
    "sg:province":"Baden-W\u00fcrttemberg",
    "wof:name":"Christina Beck",
    "wof:placetype":"venue"
},
  "geometry": {"coordinates":[9.1741933823,47.6776351929],"type":"Point"}
}