{
  "type": "Feature",
  "properties": {
    "iso:country":"DE",
    "sg:address":"Hauptstr. 12",
    "sg:city":"Wienhausen",
    "sg:phone":"+49 5149/350",
    "sg:postcode":"29342",
    "sg:province":"Niedersachsen",
    "wof:name":"Alfred Schmidt Kg",
    "wof:placetype":"venue"
},
  "geometry": {"coordinates":[10.1897964478,52.5802459717],"type":"Point"}
}