{
  "type": "Feature",
  "properties": {
    "iso:country":"DE",
    "sg:address":"Balderstr. 39",
    "sg:city":"Leipzig",
    "sg:phone":"+49 341/9217133",
    "sg:postcode":"04349",
    "sg:province":"Sachsen",
    "wof:name":"Wolfgang Funke",
    "wof:placetype":"venue"
},
  "geometry": {"coordinates":[12.4510526657,51.3800354004],"type":"Point"}
}