{
  "type": "Feature",
  "properties": {
    "iso:country":"DE",
    "sg:address":"Weinbrennerstr. 58",
    "sg:city":"Karlsruhe",
    "sg:phone":"+49 721/853400",
    "sg:postcode":"76185",
    "sg:province":"Baden-W\u00fcrttemberg",
    "wof:name":"Kfo - Fachlabor Kranefu\u00df Zahntechnik Gmbh",
    "wof:placetype":"venue"
},
  "geometry": {"coordinates":[8.3700647354,49.0078926086],"type":"Point"}
}