{
  "type": "Feature",
  "properties": {
    "iso:country":"DE",
    "sg:address":"Geistb\u00fchelstr. 5",
    "sg:city":"Weilheim",
    "sg:phone":"+49 881/3533",
    "sg:postcode":"82362",
    "sg:province":"Bayern",
    "wof:name":"Wolfgang Kuhnert Steuerberater",
    "wof:placetype":"venue"
},
  "geometry": {"coordinates":[11.1385326385,47.8359909058],"type":"Point"}
}