{
  "type": "Feature",
  "properties": {
    "iso:country":"DE",
    "sg:address":"Anger 11",
    "sg:city":"Silkerode",
    "sg:phone":"+49 36072/542",
    "sg:postcode":"37345",
    "sg:province":"Th\u00fcringen",
    "wof:name":"R. Hartmann",
    "wof:placetype":"venue"
},
  "geometry": {"coordinates":[10.398259,51.566704],"type":"Point"}
}