{
  "type": "Feature",
  "properties": {
    "iso:country":"DE",
    "sg:address":"74635",
    "sg:city":"Kupferzell",
    "sg:postcode":"74635",
    "sg:province":"Baden-W\u00fcrttemberg",
    "wof:name":"Volksbank Kupferzell Eg",
    "wof:placetype":"venue"
},
  "geometry": {"coordinates":[9.69449,49.213879],"type":"Point"}
}