{
  "type": "Feature",
  "properties": {
    "iso:country":"DE",
    "sg:address":"B 273",
    "sg:city":"Wandlitz",
    "sg:postcode":"16348",
    "sg:province":"Brandenburg",
    "wof:name":"Heim Gmbh",
    "wof:placetype":"venue"
},
  "geometry": {"coordinates":[13.455692,52.742493],"type":"Point"}
}