{
  "type": "Feature",
  "properties": {
    "iso:country":"DE",
    "sg:address":"Hohenlohestr. 17",
    "sg:city":"Forchtenberg",
    "sg:phone":"+49 7947/508",
    "sg:postcode":"74670",
    "sg:province":"Baden-W\u00fcrttemberg",
    "wof:name":"H. Grobh\u00e4user",
    "wof:placetype":"venue"
},
  "geometry": {"coordinates":[9.5766582489,49.2631835938],"type":"Point"}
}