{
  "type": "Feature",
  "properties": {
    "iso:country":"DE",
    "sg:address":"Auf der Balsterh\u00f6he 7",
    "sg:city":"Lemgo",
    "sg:phone":"+49 5261/14888",
    "sg:postcode":"32657",
    "sg:province":"Nordrhein-Westfalen",
    "wof:name":"Friedrich-wilhelm G\u00fcse Steuerberater",
    "wof:placetype":"venue"
},
  "geometry": {"coordinates":[8.8818368912,52.0289993286],"type":"Point"}
}