{
  "type": "Feature",
  "properties": {
    "iso:country":"DE",
    "sg:address":"Sch\u00fctzenallee",
    "sg:city":"Katlenburg-Lindau",
    "sg:postcode":"37191",
    "sg:province":"Niedersachsen",
    "wof:name":"Mehrzweckhalle Lindau",
    "wof:placetype":"venue"
},
  "geometry": {"coordinates":[10.127186,51.65469],"type":"Point"}
}