{
  "type": "Feature",
  "properties": {
    "iso:country":"DE",
    "sg:address":"Leopoldstr. 2",
    "sg:city":"Lemgo",
    "sg:phone":"+49 5261/94460",
    "sg:postcode":"32657",
    "sg:province":"Nordrhein-Westfalen",
    "wof:name":"Leopold-apotheke",
    "wof:placetype":"venue"
},
  "geometry": {"coordinates":[8.901112,52.030083],"type":"Point"}
}