{
  "type": "Feature",
  "properties": {
    "iso:country":"DE",
    "sg:address":"Papenwiese 12",
    "sg:city":"Haren",
    "sg:phone":"+49 5932/2776",
    "sg:postcode":"49733",
    "sg:province":"Niedersachsen",
    "wof:name":"Tim Schepers Ms Heinrich Schepers",
    "wof:placetype":"venue"
},
  "geometry": {"coordinates":[7.237269,52.793068],"type":"Point"}
}