{
  "type": "Feature",
  "properties": {
    "iso:country":"DE",
    "sg:address":"Im Langenst\u00fcck 16",
    "sg:city":"Hagen",
    "sg:phone":"+49 2331/77200",
    "sg:postcode":"58093",
    "sg:province":"Nordrhein-Westfalen",
    "wof:name":"Paul Wegner Beteiligungs Gmbh",
    "wof:placetype":"venue"
},
  "geometry": {"coordinates":[7.506236,51.345409],"type":"Point"}
}