{
  "type": "Feature",
  "properties": {
    "iso:country":"DE",
    "sg:address":"Krantorweg 47",
    "sg:city":"Berlin",
    "sg:phone":"+49 30/4314062",
    "sg:postcode":"13503",
    "sg:province":"Berlin",
    "wof:name":"Heinz Haarig \u00d6lbrennerwartung",
    "wof:placetype":"venue"
},
  "geometry": {"coordinates":[13.2290153503,52.6219406128],"type":"Point"}
}