{
  "type": "Feature",
  "properties": {
    "iso:country":"DE",
    "sg:address":"Stroblstrasse 34",
    "sg:city":"Muenchen",
    "sg:phone":"+49 89/54642787",
    "sg:postcode":"80689",
    "sg:province":"Bayern",
    "wof:name":"Siteseeing Connection",
    "wof:placetype":"venue"
},
  "geometry": {"coordinates":[11.4922170639,48.1347045898],"type":"Point"}
}