{
  "type": "Feature",
  "properties": {
    "iso:country":"DE",
    "sg:address":"Albrechtstr. 49",
    "sg:city":"Castrop-Rauxel",
    "sg:phone":"+49 2305/27299",
    "sg:postcode":"44575",
    "sg:province":"Nordrhein-Westfalen",
    "wof:name":"Cornelia Bochynek Anlageberatung",
    "wof:placetype":"venue"
},
  "geometry": {"coordinates":[7.3211650848,51.5358924866],"type":"Point"}
}