{
  "type": "Feature",
  "properties": {
    "iso:country":"DE",
    "sg:address":"Am Exerzierplatz 14",
    "sg:city":"Mannheim",
    "sg:phone":"+49 621/39280",
    "sg:postcode":"68167",
    "sg:province":"Baden-W\u00fcrttemberg",
    "wof:name":"Epimetric Gmbh",
    "wof:placetype":"venue"
},
  "geometry": {"coordinates":[8.497467041,49.5043334961],"type":"Point"}
}