{
  "type": "Feature",
  "properties": {
    "iso:country":"DE",
    "sg:address":"H\u00f6lderlinweg 9",
    "sg:city":"G\u00f6ppingen",
    "sg:phone":"+49 7161/12977",
    "sg:postcode":"73033",
    "sg:province":"Baden-W\u00fcrttemberg",
    "wof:name":"Madness Gmbh",
    "wof:placetype":"venue"
},
  "geometry": {"coordinates":[9.6429977417,48.706993103],"type":"Point"}
}