{
  "type": "Feature",
  "properties": {
    "iso:country":"DE",
    "sg:address":"Herzberger Str. 2",
    "sg:city":"Doberlug-Kirchhain",
    "sg:postcode":"03253",
    "sg:province":"Brandenburg",
    "wof:name":"Gwf Mbh",
    "wof:placetype":"venue"
},
  "geometry": {"coordinates":[13.559378624,51.6414833069],"type":"Point"}
}