{
  "type": "Feature",
  "properties": {
    "iso:country":"DE",
    "sg:address":"Mindener Str. 13",
    "sg:city":"Osnabr\u00fcck",
    "sg:phone":"+49 541/79272",
    "sg:postcode":"49084",
    "sg:province":"Niedersachsen",
    "wof:name":"Edith Und Helmut Tonkel",
    "wof:placetype":"venue"
},
  "geometry": {"coordinates":[8.0770816803,52.2744674683],"type":"Point"}
}