{
  "type": "Feature",
  "properties": {
    "iso:country":"DE",
    "sg:address":"M\u00fchlbachstr. 11",
    "sg:city":"Filderstadt",
    "sg:phone":"+49 711/776530",
    "sg:postcode":"70794",
    "sg:province":"Baden-W\u00fcrttemberg",
    "wof:name":"Kornm\u00fchle",
    "wof:placetype":"venue"
},
  "geometry": {"coordinates":[9.2134475708,48.6510009766],"type":"Point"}
}