{
  "type": "Feature",
  "properties": {
    "iso:country":"DE",
    "sg:address":"Br\u00fchler Str. 104",
    "sg:city":"Solingen",
    "sg:phone":"+49 212/817665",
    "sg:postcode":"42657",
    "sg:province":"Nordrhein-Westfalen",
    "wof:name":"Irler Grill",
    "wof:placetype":"venue"
},
  "geometry": {"coordinates":[7.0842399597,51.1596183777],"type":"Point"}
}