{
  "type": "Feature",
  "properties": {
    "iso:country":"DE",
    "sg:address":"Schillerstr. 36",
    "sg:city":"Erfurt",
    "sg:phone":"+49 361/3454015",
    "sg:postcode":"99096",
    "sg:province":"Th\u00fcringen",
    "wof:name":"Martina Von Ludwig Rechtsanw\u00e4ltin",
    "wof:placetype":"venue"
},
  "geometry": {"coordinates":[11.031662941,50.9681587219],"type":"Point"}
}