{
  "type": "Feature",
  "properties": {
    "iso:country":"DE",
    "sg:address":"Im Martelacker 8",
    "sg:city":"Efringen-Kirchen",
    "sg:phone":"+49 7628/1206",
    "sg:postcode":"79588",
    "sg:province":"Baden-W\u00fcrttemberg",
    "wof:name":"Schachenmeier Gmbh",
    "wof:placetype":"venue"
},
  "geometry": {"coordinates":[7.5741691589,47.6551246643],"type":"Point"}
}