{
  "type": "Feature",
  "properties": {
    "iso:country":"DE",
    "sg:address":"Kleine Twiete 112",
    "sg:city":"Uetersen",
    "sg:phone":"+49 4941/2290350",
    "sg:postcode":"25436",
    "sg:province":"Schleswig-Holstein",
    "wof:name":"H. L\u00dcder Gmbh",
    "wof:placetype":"venue"
},
  "geometry": {"coordinates":[9.693689,53.680916],"type":"Point"}
}