{
  "type": "Feature",
  "properties": {
    "iso:country":"DE",
    "sg:address":"Unteraltenburg 27",
    "sg:city":"Merseburg",
    "sg:phone":"+49 3461/203009",
    "sg:postcode":"06217",
    "sg:province":"Sachsen-Anhalt",
    "wof:name":"Steffen Kabisch",
    "wof:placetype":"venue"
},
  "geometry": {"coordinates":[11.9980745316,51.3609199524],"type":"Point"}
}