{
  "type": "Feature",
  "properties": {
    "iso:country":"DE",
    "sg:address":"Diepenbroich 46",
    "sg:city":"Willich",
    "sg:phone":"+49 2154/5162",
    "sg:postcode":"47877",
    "sg:province":"Nordrhein-Westfalen",
    "wof:name":"Kamphausen Ingenieur",
    "wof:placetype":"venue"
},
  "geometry": {"coordinates":[6.5301918983,51.2464599609],"type":"Point"}
}