{
  "type": "Feature",
  "properties": {
    "iso:country":"DE",
    "sg:address":"Magdeburger Allee 47",
    "sg:city":"Erfurt",
    "sg:phone":"+49 361/2112510",
    "sg:postcode":"99086",
    "sg:province":"Th\u00fcringen",
    "wof:name":"Franz Langer",
    "wof:placetype":"venue"
},
  "geometry": {"coordinates":[11.0262098312,50.9896583557],"type":"Point"}
}