{
  "type": "Feature",
  "properties": {
    "iso:country":"DE",
    "sg:address":"Turfstr. 17",
    "sg:city":"M\u00fcnchen",
    "sg:phone":"+49 89/69373019",
    "sg:postcode":"81929",
    "sg:province":"Bayern",
    "wof:name":"Markus Thiel Productions Gmbh",
    "wof:placetype":"venue"
},
  "geometry": {"coordinates":[11.6599111557,48.1412200928],"type":"Point"}
}