{
  "type": "Feature",
  "properties": {
    "iso:country":"DE",
    "sg:address":"Conradin-Kreutzer-Str. 13",
    "sg:city":"Me\u00dfkirch",
    "sg:phone":"+49 7575/926111",
    "sg:postcode":"88605",
    "sg:province":"Baden-W\u00fcrttemberg",
    "wof:name":"Wwk Agenturb\u00fcro J. Stadler Und Partner",
    "wof:placetype":"venue"
},
  "geometry": {"coordinates":[9.1135339737,47.9946517944],"type":"Point"}
}