{
  "type": "Feature",
  "properties": {
    "iso:country":"DE",
    "sg:address":"Lohstr. 14",
    "sg:city":"Herzogenaurach",
    "sg:phone":"+49 9132/8898",
    "sg:postcode":"91074",
    "sg:province":"Bayern",
    "wof:name":"Klaus Lorenz",
    "wof:placetype":"venue"
},
  "geometry": {"coordinates":[10.8549165726,49.5926589966],"type":"Point"}
}