{
  "type": "Feature",
  "properties": {
    "iso:country":"DE",
    "sg:address":"Oberanger 35",
    "sg:city":"M\u00fcnchen",
    "sg:phone":"+49 89/266696",
    "sg:postcode":"80331",
    "sg:province":"Bayern",
    "wof:name":"Bp Tankstelle",
    "wof:placetype":"venue"
},
  "geometry": {"coordinates":[11.5705709457,48.1342506409],"type":"Point"}
}