{
  "type": "Feature",
  "properties": {
    "iso:country":"DE",
    "sg:address":"Teichkoppel 63",
    "sg:city":"D\u00e4nischenhagen",
    "sg:phone":"+49 431/329130",
    "sg:postcode":"24229",
    "sg:province":"Schleswig-Holstein",
    "wof:name":"Blokland-w\u00e4rmetauscher-weihe Gmbh Gewerbegebiet Lehmkaten",
    "wof:placetype":"venue"
},
  "geometry": {"coordinates":[10.129637,54.41293],"type":"Point"}
}