{
  "type": "Feature",
  "properties": {
    "iso:country":"DE",
    "sg:address":"Montfortstr. 11",
    "sg:city":"Immenstaad",
    "sg:phone":"+49 7545/1379",
    "sg:postcode":"88090",
    "sg:province":"Baden-W\u00fcrttemberg",
    "wof:name":"Berthold Manz Kg",
    "wof:placetype":"venue"
},
  "geometry": {"coordinates":[9.352288,47.672668],"type":"Point"}
}