{
  "type": "Feature",
  "properties": {
    "iso:country":"DE",
    "sg:address":"Zittelstr. 11",
    "sg:city":"M\u00fcnchen",
    "sg:phone":"+49 89/304078",
    "sg:postcode":"80796",
    "sg:province":"Bayern",
    "wof:name":"A. G\u00f6rig Bildhauer",
    "wof:placetype":"venue"
},
  "geometry": {"coordinates":[11.573573,48.161888],"type":"Point"}
}