{
  "type": "Feature",
  "properties": {
    "iso:country":"DE",
    "sg:address":"August-Bebel-Str.",
    "sg:city":"Wallwitz",
    "sg:postcode":"39291",
    "sg:province":"Sachsen-Anhalt",
    "wof:name":"Gemeindeschwesterstation",
    "wof:placetype":"venue"
},
  "geometry": {"coordinates":[11.91362,52.118713],"type":"Point"}
}