{
  "type": "Feature",
  "properties": {
    "iso:country":"DE",
    "sg:address":"Birkenstr. 37",
    "sg:city":"Bremen",
    "sg:phone":"+49 421/14910",
    "sg:postcode":"28195",
    "sg:province":"Bremen",
    "wof:name":"Wm. H. M\u00fcller & Co. Gmbh",
    "wof:placetype":"venue"
},
  "geometry": {"coordinates":[8.8083257675,53.0810623169],"type":"Point"}
}