{
  "type": "Feature",
  "properties": {
    "iso:country":"DE",
    "sg:address":"Walther-Rathenau-Str. 22",
    "sg:city":"Herborn",
    "sg:phone":"+49 2772/41310",
    "sg:postcode":"35745",
    "sg:province":"Hessen",
    "wof:name":"Theo Rink Steuerberater",
    "wof:placetype":"venue"
},
  "geometry": {"coordinates":[8.3064069748,50.6842498779],"type":"Point"}
}