{
  "type": "Feature",
  "properties": {
    "iso:country":"DE",
    "sg:address":"Marktplatz 1",
    "sg:city":"Sch\u00f6nberg",
    "sg:phone":"+49 8554/752",
    "sg:postcode":"94513",
    "sg:province":"Bayern",
    "wof:name":"Max Pleintinger Metzgerei",
    "wof:placetype":"venue"
},
  "geometry": {"coordinates":[13.3372211456,48.8405532837],"type":"Point"}
}