{
  "type": "Feature",
  "properties": {
    "iso:country":"DE",
    "sg:address":"Rungestr. 31",
    "sg:city":"M\u00fcnchen",
    "sg:phone":"+49 89/7916276",
    "sg:postcode":"81479",
    "sg:province":"Bayern",
    "wof:name":"Mia Jahn Sai Collection Handels Gmbh",
    "wof:placetype":"venue"
},
  "geometry": {"coordinates":[11.5242338181,48.0691184998],"type":"Point"}
}