{
  "type": "Feature",
  "properties": {
    "iso:country":"DE",
    "sg:address":"Stegerwaldring 19",
    "sg:city":"Hamburg",
    "sg:phone":"+49 40/8512227",
    "sg:postcode":"22119",
    "sg:province":"Hamburg",
    "wof:name":"Willco A. Cords D. Willhardt",
    "wof:placetype":"venue"
},
  "geometry": {"coordinates":[10.0999288559,53.5509185791],"type":"Point"}
}