{
  "type": "Feature",
  "properties": {
    "iso:country":"DE",
    "sg:address":"Kirchstr. 87",
    "sg:city":"Mainz",
    "sg:postcode":"55124",
    "sg:province":"Rheinland-Pfalz",
    "wof:name":"Infatec Institut F\u00fcr Produkt- Und Verfahrensentwicklung Gmbh",
    "wof:placetype":"venue"
},
  "geometry": {"coordinates":[8.2040634155,50.0057830811],"type":"Point"}
}