{
  "type": "Feature",
  "properties": {
    "iso:country":"DE",
    "sg:address":"Martin-Schwantes-Str. 57",
    "sg:city":"Gommern",
    "sg:phone":"+49 39200/51343",
    "sg:postcode":"39245",
    "sg:province":"Sachsen-Anhalt",
    "wof:name":"Babette Arndt",
    "wof:placetype":"venue"
},
  "geometry": {"coordinates":[11.8256454468,52.073348999],"type":"Point"}
}