{
  "type": "Feature",
  "properties": {
    "iso:country":"DE",
    "sg:address":"Daxberger Str. 5",
    "sg:city":"M\u00f6mbris",
    "sg:phone":"+49 6029/1816",
    "sg:postcode":"63776",
    "sg:province":"Bayern",
    "wof:name":"Josef Bauer",
    "wof:placetype":"venue"
},
  "geometry": {"coordinates":[9.189413,50.053654],"type":"Point"}
}