{
  "type": "Feature",
  "properties": {
    "iso:country":"DE",
    "sg:address":"Br\u00fcckenstr. 9 a",
    "sg:city":"Memmingen",
    "sg:phone":"+49 8331/84081",
    "sg:postcode":"87700",
    "sg:province":"Bayern",
    "wof:name":"Hans-dieter Schauenburg",
    "wof:placetype":"venue"
},
  "geometry": {"coordinates":[10.190198,47.984325],"type":"Point"}
}