{
  "type": "Feature",
  "properties": {
    "iso:country":"DE",
    "sg:address":"R\u00f6merstr. 6",
    "sg:city":"Briedel",
    "sg:phone":"+49 6542/5151",
    "sg:postcode":"56867",
    "sg:province":"Rheinland-Pfalz",
    "wof:name":"Rhein-mosel-verlag Inhaber A. Houben E. K.",
    "wof:placetype":"venue"
},
  "geometry": {"coordinates":[7.148458004,50.0225028992],"type":"Point"}
}