{
  "type": "Feature",
  "properties": {
    "iso:country":"DE",
    "sg:address":"Schwabh\u00e4user Str. 10",
    "sg:city":"Gotha",
    "sg:phone":"+49 3621/52159",
    "sg:postcode":"99867",
    "sg:province":"Th\u00fcringen",
    "wof:name":"O.t.e. Orthop\u00e4die- Und Reha- Technik Gmbh",
    "wof:placetype":"venue"
},
  "geometry": {"coordinates":[10.7052001953,50.9485282898],"type":"Point"}
}