{
  "type": "Feature",
  "properties": {
    "iso:country":"DE",
    "sg:address":"Kernerstr. 52",
    "sg:city":"Stuttgart",
    "sg:phone":"+49 711/228610",
    "sg:postcode":"70182",
    "sg:province":"Baden-W\u00fcrttemberg",
    "wof:name":"Dr. Maier & Partner Gmbh",
    "wof:placetype":"venue"
},
  "geometry": {"coordinates":[9.1901607513,48.7785186768],"type":"Point"}
}