{
  "type": "Feature",
  "properties": {
    "iso:country":"DE",
    "sg:address":"Rheinstr. 1",
    "sg:city":"Ludwigsfelde",
    "sg:phone":"+49 3378/803517",
    "sg:postcode":"14974",
    "sg:province":"Brandenburg",
    "wof:name":"Lohnsteuerhilfeverein Abc E. V.",
    "wof:placetype":"venue"
},
  "geometry": {"coordinates":[13.2413711548,52.3091278076],"type":"Point"}
}