{
  "type": "Feature",
  "properties": {
    "iso:country":"DE",
    "sg:address":"Niehler Str. 92-116",
    "sg:city":"K\u00f6ln",
    "sg:postcode":"50733",
    "sg:province":"Nordrhein-Westfalen",
    "wof:name":"Gemeinsame Stiftung Der Firmen Land Und Seekabelwerk Ag Und",
    "wof:placetype":"venue"
},
  "geometry": {"coordinates":[6.958591938,50.9635505676],"type":"Point"}
}