{
  "type": "Feature",
  "properties": {
    "iso:country":"DE",
    "sg:address":"Theo-Neubauer-Str. 11",
    "sg:city":"Wutha-Farnroda",
    "sg:postcode":"99848",
    "sg:province":"Th\u00fcringen",
    "wof:name":"Elektroanlagen Frank Wallenstein Gmbh",
    "wof:placetype":"venue"
},
  "geometry": {"coordinates":[10.3677272797,50.9411239624],"type":"Point"}
}