{
  "type": "Feature",
  "properties": {
    "iso:country":"DE",
    "sg:address":"Ehenfeld 3",
    "sg:city":"Hirschau",
    "sg:phone":"+49 9622/2253",
    "sg:postcode":"92242",
    "sg:province":"Bayern",
    "wof:name":"Josef Kummer",
    "wof:placetype":"venue"
},
  "geometry": {"coordinates":[11.949502,49.545872],"type":"Point"}
}