{
  "type": "Feature",
  "properties": {
    "iso:country":"DE",
    "sg:address":"Peiner Str. 17",
    "sg:city":"Peine",
    "sg:phone":"+49 5171/9980",
    "sg:postcode":"31228",
    "sg:province":"Niedersachsen",
    "wof:name":"Sch\u00f6nau",
    "wof:placetype":"venue"
},
  "geometry": {"coordinates":[10.2414951324,52.3459815979],"type":"Point"}
}