{
  "type": "Feature",
  "properties": {
    "iso:country":"DE",
    "sg:address":"Baulandstr. 76",
    "sg:city":"Walld\u00fcrn",
    "sg:phone":"+49 6285/235",
    "sg:postcode":"74731",
    "sg:province":"Baden-W\u00fcrttemberg",
    "wof:name":"Katholisches Pfarramt St. Valentin",
    "wof:placetype":"venue"
},
  "geometry": {"coordinates":[9.4434690475,49.519115448],"type":"Point"}
}