{
  "type": "Feature",
  "properties": {
    "iso:country":"DE",
    "sg:address":"Schillerstr. 18",
    "sg:city":"Kleinostheim",
    "sg:phone":"+49 6027/8127",
    "sg:postcode":"63801",
    "sg:province":"Bayern",
    "wof:name":"Fritz Stoss",
    "wof:placetype":"venue"
},
  "geometry": {"coordinates":[9.059458,50.003624],"type":"Point"}
}