{
  "type": "Feature",
  "properties": {
    "iso:country":"DE",
    "sg:address":"Oberdorfstr. 11",
    "sg:city":"H\u00fcnfeld",
    "sg:phone":"+49 6652/74141",
    "sg:postcode":"36088",
    "sg:province":"Hessen",
    "wof:name":"Rh\u00f6n-konzert",
    "wof:placetype":"venue"
},
  "geometry": {"coordinates":[9.8029499054,50.6673927307],"type":"Point"}
}