{
  "type": "Feature",
  "properties": {
    "iso:country":"DE",
    "sg:address":"Feldkircher Str. 101",
    "sg:city":"Hartheim",
    "sg:phone":"+49 7633/3121",
    "sg:postcode":"79258",
    "sg:province":"Baden-W\u00fcrttemberg",
    "wof:name":"Zipfel Ohg",
    "wof:placetype":"venue"
},
  "geometry": {"coordinates":[7.6382341385,47.9352760315],"type":"Point"}
}