{
  "type": "Feature",
  "properties": {
    "iso:country":"DE",
    "sg:address":"Fichtestr. 56",
    "sg:city":"Heilbronn",
    "sg:phone":"+49 7131/173948",
    "sg:postcode":"74074",
    "sg:province":"Baden-W\u00fcrttemberg",
    "wof:name":"Wolfgang Pettendorfer",
    "wof:placetype":"venue"
},
  "geometry": {"coordinates":[9.2398176193,49.132976532],"type":"Point"}
}