{
  "type": "Feature",
  "properties": {
    "iso:country":"DE",
    "sg:address":"Deichstr. 4",
    "sg:city":"Neuhaus",
    "sg:postcode":"21785",
    "sg:province":"Niedersachsen",
    "wof:name":"Weinhof Privelack Handelsgesellschaft Mbh",
    "wof:placetype":"venue"
},
  "geometry": {"coordinates":[9.033118248,53.8043556213],"type":"Point"}
}