{
  "type": "Feature",
  "properties": {
    "iso:country":"DE",
    "sg:address":"Hauptstr. 213",
    "sg:city":"Alfter",
    "sg:phone":"+49 228/649399",
    "sg:postcode":"53347",
    "sg:province":"Nordrhein-Westfalen",
    "wof:name":"Fr\u00fcchtehaus Klein Inh. Karin Klein",
    "wof:placetype":"venue"
},
  "geometry": {"coordinates":[7.0238218307,50.6986503601],"type":"Point"}
}