{
  "type": "Feature",
  "properties": {
    "iso:country":"DE",
    "sg:address":"Seeweg 13",
    "sg:city":"Regen",
    "sg:phone":"+49 9921/3622",
    "sg:postcode":"94209",
    "sg:province":"Bayern",
    "wof:name":"Wilhelm Fischer",
    "wof:placetype":"venue"
},
  "geometry": {"coordinates":[13.1427564621,48.973815918],"type":"Point"}
}