{
  "type": "Feature",
  "properties": {
    "iso:country":"DE",
    "sg:address":"Habichtweg 5",
    "sg:city":"Marienberg",
    "sg:phone":"+49 3735/65251",
    "sg:postcode":"09496",
    "sg:province":"Sachsen",
    "wof:name":"Inge Schulz",
    "wof:placetype":"venue"
},
  "geometry": {"coordinates":[13.1420087814,50.6474876404],"type":"Point"}
}