{
  "type": "Feature",
  "properties": {
    "iso:country":"DE",
    "sg:address":"Wiesenstr. 9",
    "sg:city":"Damme",
    "sg:phone":"+49 5491/95620",
    "sg:postcode":"49401",
    "sg:province":"Niedersachsen",
    "wof:name":"Hagebaumarkt Damme Verwaltungsges. Mbh",
    "wof:placetype":"venue"
},
  "geometry": {"coordinates":[8.1991300583,52.5184593201],"type":"Point"}
}