{
  "type": "Feature",
  "properties": {
    "iso:country":"DE",
    "sg:address":"Stadtstr. 16",
    "sg:city":"Gl\u00fcckstadt",
    "sg:phone":"+49 4124/91102",
    "sg:postcode":"25348",
    "sg:province":"Schleswig-Holstein",
    "wof:name":"Buckeye Holdings Gmbh",
    "wof:placetype":"venue"
},
  "geometry": {"coordinates":[9.428082,53.782795],"type":"Point"}
}