{
  "type": "Feature",
  "properties": {
    "iso:country":"DE",
    "sg:address":"Berliner Str. 29",
    "sg:city":"St. Georgen",
    "sg:phone":"+49 7724/2340",
    "sg:postcode":"78112",
    "sg:province":"Baden-W\u00fcrttemberg",
    "wof:name":"F. Demme",
    "wof:placetype":"venue"
},
  "geometry": {"coordinates":[8.3250398636,48.1324806213],"type":"Point"}
}