{
  "type": "Feature",
  "properties": {
    "iso:country":"DE",
    "sg:address":"Am Heidchen 31",
    "sg:city":"Raubach",
    "sg:phone":"+49 2684/5103",
    "sg:postcode":"56316",
    "sg:province":"Rheinland-Pfalz",
    "wof:name":"R. Menges Steuerberater",
    "wof:placetype":"venue"
},
  "geometry": {"coordinates":[7.6265759468,50.5700874329],"type":"Point"}
}