{
  "type": "Feature",
  "properties": {
    "iso:country":"DE",
    "sg:address":"Rinnigstr. 1",
    "sg:city":"Ebensfeld",
    "sg:postcode":"96250",
    "sg:province":"Bayern",
    "wof:name":"A. Hergenr\u00f6der Gmbh & Co. Kg",
    "wof:placetype":"venue"
},
  "geometry": {"coordinates":[10.9624357224,50.0699806213],"type":"Point"}
}