{
  "type": "Feature",
  "properties": {
    "iso:country":"DE",
    "sg:address":"Friedenstr. 12",
    "sg:city":"Johannesberg",
    "sg:phone":"+49 6021/423339",
    "sg:postcode":"63867",
    "sg:province":"Bayern",
    "wof:name":"Siegfried Kraus Gmbh & Co. Kg",
    "wof:placetype":"venue"
},
  "geometry": {"coordinates":[9.1472835541,50.0321083069],"type":"Point"}
}