{
  "type": "Feature",
  "properties": {
    "iso:country":"DE",
    "sg:address":"Arnstorfer Str.",
    "sg:city":"Pfarrkirchen",
    "sg:phone":"+49 8561/6080",
    "sg:postcode":"84347",
    "sg:province":"Bayern",
    "wof:name":"Alois Bischof",
    "wof:placetype":"venue"
},
  "geometry": {"coordinates":[12.9369792938,48.4369773865],"type":"Point"}
}