{
  "type": "Feature",
  "properties": {
    "iso:country":"DE",
    "sg:address":"Fliederweg 2",
    "sg:city":"Villingen-Schwenningen",
    "sg:phone":"+49 7721/23734",
    "sg:postcode":"78052",
    "sg:province":"Baden-W\u00fcrttemberg",
    "wof:name":"Egon Kunz",
    "wof:placetype":"venue"
},
  "geometry": {"coordinates":[8.414446,48.03376],"type":"Point"}
}