{
  "type": "Feature",
  "properties": {
    "iso:country":"DE",
    "sg:address":"Chamer Str. 1",
    "sg:city":"Glei\u00dfenberg",
    "sg:phone":"+49 9975/8254",
    "sg:postcode":"93477",
    "sg:province":"Bayern",
    "wof:name":"Josef Klein",
    "wof:placetype":"venue"
},
  "geometry": {"coordinates":[12.741132,49.316727],"type":"Point"}
}