{
  "type": "Feature",
  "properties": {
    "iso:country":"DE",
    "sg:address":"Nixweg 15",
    "sg:city":"Herzberg",
    "sg:phone":"+49 3535/3493",
    "sg:postcode":"04916",
    "sg:province":"Brandenburg",
    "wof:name":"Lothar Weigel",
    "wof:placetype":"venue"
},
  "geometry": {"coordinates":[13.231535,51.694115],"type":"Point"}
}