{
  "type": "Feature",
  "properties": {
    "iso:country":"DE",
    "sg:address":"Peter-Hecker-Str. 23",
    "sg:city":"Odenthal",
    "sg:postcode":"51519",
    "sg:province":"Nordrhein-Westfalen",
    "wof:name":"Naumann & Pegel Handelsges. Mbh",
    "wof:placetype":"venue"
},
  "geometry": {"coordinates":[7.1754698753,51.0378684998],"type":"Point"}
}