{
  "type": "Feature",
  "properties": {
    "iso:country":"DE",
    "sg:address":"Dampfschiffsweg 21",
    "sg:city":"Hamburg",
    "sg:phone":"+49 40/770294",
    "sg:postcode":"21079",
    "sg:province":"Hamburg",
    "wof:name":"Harburger F\u00e4hrhaus",
    "wof:placetype":"venue"
},
  "geometry": {"coordinates":[9.9834718704,53.4729347229],"type":"Point"}
}