{
  "type": "Feature",
  "properties": {
    "iso:country":"DE",
    "sg:address":"Parkstr. 1",
    "sg:city":"Bad Soden",
    "sg:postcode":"65812",
    "sg:province":"Hessen",
    "wof:name":"Smart Bot Technologies Gmbh",
    "wof:placetype":"venue"
},
  "geometry": {"coordinates":[8.500712,50.147655],"type":"Point"}
}