{
  "type": "Feature",
  "properties": {
    "iso:country":"DE",
    "sg:address":"Fabrikstr. 3",
    "sg:city":"Brieske",
    "sg:phone":"+49 3573/65275",
    "sg:postcode":"01968",
    "sg:province":"Brandenburg",
    "wof:name":"J. Melke Ingenieur",
    "wof:placetype":"venue"
},
  "geometry": {"coordinates":[13.9650268555,51.5027809143],"type":"Point"}
}