{
  "type": "Feature",
  "properties": {
    "iso:country":"DE",
    "sg:address":"Im Reitstiegel 7",
    "sg:city":"Enger",
    "sg:phone":"+49 5224/790694",
    "sg:postcode":"32130",
    "sg:province":"Nordrhein-Westfalen",
    "wof:name":"Sven Gerds",
    "wof:placetype":"venue"
},
  "geometry": {"coordinates":[8.5558786392,52.1374816895],"type":"Point"}
}