{
  "type": "Feature",
  "properties": {
    "iso:country":"DE",
    "sg:address":"Paul-von-Schoenaich-Str. 2",
    "sg:city":"Reinfeld",
    "sg:phone":"+49 4533/4579",
    "sg:postcode":"23858",
    "sg:province":"Schleswig-Holstein",
    "wof:name":"Bines",
    "wof:placetype":"venue"
},
  "geometry": {"coordinates":[10.539872,53.819065],"type":"Point"}
}