{
  "type": "Feature",
  "properties": {
    "iso:country":"DE",
    "sg:address":"Hohenzollernstr. 11",
    "sg:city":"Nagold",
    "sg:phone":"+49 7459/8455",
    "sg:postcode":"72202",
    "sg:province":"Baden-W\u00fcrttemberg",
    "wof:name":"Claudius Wollensack",
    "wof:placetype":"venue"
},
  "geometry": {"coordinates":[8.75440979,48.5125999451],"type":"Point"}
}