{
  "type": "Feature",
  "properties": {
    "iso:country":"DE",
    "sg:address":"Rendsburger Landstr. 51",
    "sg:city":"Kiel",
    "sg:phone":"+49 431/681945",
    "sg:postcode":"24113",
    "sg:province":"Schleswig-Holstein",
    "wof:name":"Joachim Damlos",
    "wof:placetype":"venue"
},
  "geometry": {"coordinates":[10.1108388901,54.305606842],"type":"Point"}
}