{
  "type": "Feature",
  "properties": {
    "iso:country":"DE",
    "sg:address":"Schlavenhorst",
    "sg:city":"Bocholt",
    "sg:phone":"+49 2871/960",
    "sg:postcode":"46395",
    "sg:province":"Nordrhein-Westfalen",
    "wof:name":"Gottfried Hehemann Verwaltungsgesellschaft Mbh",
    "wof:placetype":"venue"
},
  "geometry": {"coordinates":[6.539224,51.815292],"type":"Point"}
}