{
  "type": "Feature",
  "properties": {
    "iso:country":"DE",
    "sg:address":"Spreckelweg 28",
    "sg:city":"Wohnste",
    "sg:postcode":"27419",
    "sg:province":"Niedersachsen",
    "wof:name":"T\u00f6ste Grundst\u00fccks- Und Wohnungsbaugesellschaft Mbh",
    "wof:placetype":"venue"
},
  "geometry": {"coordinates":[9.539685,53.361702],"type":"Point"}
}