{
  "type": "Feature",
  "properties": {
    "iso:country":"DE",
    "sg:address":"Bildh\u00e4user Str. 3",
    "sg:city":"M\u00fcnnerstadt",
    "sg:phone":"+49 9766/626",
    "sg:postcode":"97702",
    "sg:province":"Bayern",
    "wof:name":"Mario Uhlein",
    "wof:placetype":"venue"
},
  "geometry": {"coordinates":[10.313699,50.25758],"type":"Point"}
}