{
  "type": "Feature",
  "properties": {
    "iso:country":"DE",
    "sg:address":"Dresdener Str. 63",
    "sg:city":"Geringswalde",
    "sg:phone":"+49 37382/81483",
    "sg:postcode":"09326",
    "sg:province":"Sachsen",
    "wof:name":"Wolfgang Wittgruber",
    "wof:placetype":"venue"
},
  "geometry": {"coordinates":[12.9083414078,51.0789451599],"type":"Point"}
}