{
  "type": "Feature",
  "properties": {
    "iso:country":"DE",
    "sg:address":"Ruhrdeich 6-8",
    "sg:city":"Hattingen",
    "sg:phone":"+49 2324/951296",
    "sg:postcode":"45525",
    "sg:province":"Nordrhein-Westfalen",
    "wof:name":"Grums Partyservice Gmbh",
    "wof:placetype":"venue"
},
  "geometry": {"coordinates":[7.1756272316,51.4035873413],"type":"Point"}
}