{
  "type": "Feature",
  "properties": {
    "iso:country":"DE",
    "sg:address":"Dreherg\u00e4ssle 5",
    "sg:city":"Daugendorf",
    "sg:phone":"+49 7371/93210",
    "sg:postcode":"88499",
    "sg:province":"Baden-W\u00fcrttemberg",
    "wof:name":"Michael Richter - Internationale Vertriebs- Und Marketingberatung",
    "wof:placetype":"venue"
},
  "geometry": {"coordinates":[9.489148,48.183723],"type":"Point"}
}