{
  "type": "Feature",
  "properties": {
    "iso:country":"DE",
    "sg:address":"Hauptstr. 16",
    "sg:city":"Lienen",
    "sg:phone":"+49 5483/1065",
    "sg:postcode":"49536",
    "sg:province":"Nordrhein-Westfalen",
    "wof:name":"F. Bendrig",
    "wof:placetype":"venue"
},
  "geometry": {"coordinates":[7.973751,52.146011],"type":"Point"}
}