{
  "type": "Feature",
  "properties": {
    "iso:country":"DE",
    "sg:address":"Kieferstr. 22",
    "sg:city":"Dillingen",
    "sg:phone":"+49 6831/73664",
    "sg:postcode":"66763",
    "sg:province":"Saarland",
    "wof:name":"Otto Sprunck",
    "wof:placetype":"venue"
},
  "geometry": {"coordinates":[6.729364872,49.3560714722],"type":"Point"}
}