{
  "type": "Feature",
  "properties": {
    "iso:country":"DE",
    "sg:address":"Am Sandb\u00fchl 7",
    "sg:city":"Stockach",
    "sg:phone":"+49 7771/93340",
    "sg:postcode":"78333",
    "sg:province":"Baden-W\u00fcrttemberg",
    "wof:name":"Biller Bau Bautr\u00e4ger Gmbh",
    "wof:placetype":"venue"
},
  "geometry": {"coordinates":[9.0078401566,47.8643302917],"type":"Point"}
}