{
  "type": "Feature",
  "properties": {
    "iso:country":"DE",
    "sg:address":"Bierstadter Str. 12",
    "sg:city":"Wiesbaden",
    "sg:postcode":"65189",
    "sg:province":"Hessen",
    "wof:name":"Ataxus Grundst\u00fccksverwaltungs- Gesellschaft Mbh & Co.",
    "wof:placetype":"venue"
},
  "geometry": {"coordinates":[8.2491836548,50.0807037354],"type":"Point"}
}