{
  "type": "Feature",
  "properties": {
    "iso:country":"DE",
    "sg:address":"Spessartstr. 55",
    "sg:city":"Goldbach",
    "sg:phone":"+49 6021/74304",
    "sg:postcode":"63773",
    "sg:province":"Bayern",
    "wof:name":"Manfred R\u00fcckert Baustahl- Armierungen Verwaltungs- Gmbh",
    "wof:placetype":"venue"
},
  "geometry": {"coordinates":[9.189891,49.994835],"type":"Point"}
}