{
  "type": "Feature",
  "properties": {
    "iso:country":"DE",
    "sg:address":"Marienhofstr. 1",
    "sg:city":"Mainz",
    "sg:phone":"+49 6131/86107",
    "sg:postcode":"55130",
    "sg:province":"Rheinland-Pfalz",
    "wof:name":"Ralf G\u00f6hlen",
    "wof:placetype":"venue"
},
  "geometry": {"coordinates":[8.3098869324,49.9601554871],"type":"Point"}
}