{
  "type": "Feature",
  "properties": {
    "iso:country":"DE",
    "sg:address":"Up de Woorden 20",
    "sg:city":"Ahlen",
    "sg:phone":"+49 2382/2926",
    "sg:postcode":"59227",
    "sg:province":"Nordrhein-Westfalen",
    "wof:name":"Friedhelm Zielken",
    "wof:placetype":"venue"
},
  "geometry": {"coordinates":[7.96628,51.790401],"type":"Point"}
}