{
  "type": "Feature",
  "properties": {
    "iso:country":"DE",
    "sg:address":"Friedensallee 43",
    "sg:city":"Bernburg",
    "sg:phone":"+49 3471/23976",
    "sg:postcode":"06406",
    "sg:province":"Sachsen-Anhalt",
    "wof:name":"Iprex",
    "wof:placetype":"venue"
},
  "geometry": {"coordinates":[11.7463006973,51.7972373962],"type":"Point"}
}