{
  "type": "Feature",
  "properties": {
    "iso:country":"DE",
    "sg:address":"M\u00fchlstr. 15",
    "sg:city":"Elz",
    "sg:phone":"+49 6431/51174",
    "sg:postcode":"65604",
    "sg:province":"Hessen",
    "wof:name":"Heinz Schenk",
    "wof:placetype":"venue"
},
  "geometry": {"coordinates":[8.037861,50.410419],"type":"Point"}
}