{
  "type": "Feature",
  "properties": {
    "iso:country":"DE",
    "sg:address":"Roteb\u00fchlstr. 116",
    "sg:city":"Stuttgart",
    "sg:phone":"+49 711/610284",
    "sg:postcode":"70197",
    "sg:province":"Baden-W\u00fcrttemberg",
    "wof:name":"Kebap Haus Eurasien",
    "wof:placetype":"venue"
},
  "geometry": {"coordinates":[9.1568336487,48.7704391479],"type":"Point"}
}