{
  "type": "Feature",
  "properties": {
    "iso:country":"DE",
    "sg:address":"Rubensstr 6",
    "sg:city":"Kassel",
    "sg:phone":"+49 8041/809877",
    "sg:postcode":"34121",
    "sg:province":"Hessen",
    "wof:name":"Netswitch-internet",
    "wof:placetype":"venue"
},
  "geometry": {"coordinates":[11.5630989075,47.7635307312],"type":"Point"}
}