{
  "type": "Feature",
  "properties": {
    "iso:country":"DE",
    "sg:address":"Angergasse 129",
    "sg:city":"W\u00f6rlitz",
    "sg:phone":"+49 34905/21206",
    "sg:postcode":"06786",
    "sg:province":"Sachsen-Anhalt",
    "wof:name":"Gerolf Burger Architekt",
    "wof:placetype":"venue"
},
  "geometry": {"coordinates":[12.415809,51.843262],"type":"Point"}
}