{
  "type": "Feature",
  "properties": {
    "iso:country":"DE",
    "sg:address":"Florianweg 21",
    "sg:city":"Frankfurt am Main",
    "sg:phone":"+49 6109/36273",
    "sg:postcode":"60388",
    "sg:province":"Hessen",
    "wof:name":"Asap Office Service",
    "wof:placetype":"venue"
},
  "geometry": {"coordinates":[8.7508525848,50.1482086182],"type":"Point"}
}