{
  "type": "Feature",
  "properties": {
    "iso:country":"DE",
    "sg:address":"Am Hochacker 3",
    "sg:city":"Grasbrunn",
    "sg:phone":"+49 89/461080",
    "sg:postcode":"85630",
    "sg:province":"Bayern",
    "wof:name":"Silicon Graphics Gmbh",
    "wof:placetype":"venue"
},
  "geometry": {"coordinates":[11.7621936798,48.1013832092],"type":"Point"}
}