{
  "type": "Feature",
  "properties": {
    "iso:country":"DE",
    "sg:address":"Stadtplatz 11",
    "sg:city":"Kemnath",
    "sg:phone":"+49 9642/604",
    "sg:postcode":"95478",
    "sg:province":"Bayern",
    "wof:name":"Landesbausparkasse Beratungsstelle",
    "wof:placetype":"venue"
},
  "geometry": {"coordinates":[11.887452,49.870556],"type":"Point"}
}