{
  "type": "Feature",
  "properties": {
    "iso:country":"DE",
    "sg:address":"Krusenweg 7",
    "sg:city":"Dorsten",
    "sg:phone":"+49 2362/81260",
    "sg:postcode":"46284",
    "sg:province":"Nordrhein-Westfalen",
    "wof:name":"Hermann B\u00f6ntert, Gro\u00df- Und Einzelhandel",
    "wof:placetype":"venue"
},
  "geometry": {"coordinates":[6.9452319145,51.6794281006],"type":"Point"}
}