{
  "type": "Feature",
  "properties": {
    "iso:country":"DE",
    "sg:address":"Sendlinger Str. 48",
    "sg:city":"M\u00fcnchen",
    "sg:phone":"+49 89/2604969",
    "sg:postcode":"80331",
    "sg:province":"Bayern",
    "wof:name":"Ingrid Neichsner",
    "wof:placetype":"venue"
},
  "geometry": {"coordinates":[11.568619,48.134624],"type":"Point"}
}