{
  "type": "Feature",
  "properties": {
    "iso:country":"DE",
    "sg:address":"Rosenauer Str. 86",
    "sg:city":"Coburg",
    "sg:phone":"+49 9561/861058",
    "sg:postcode":"96450",
    "sg:province":"Bayern",
    "wof:name":"Langenstein Datentechnik",
    "wof:placetype":"venue"
},
  "geometry": {"coordinates":[10.9807271957,50.2734031677],"type":"Point"}
}