{
  "type": "Feature",
  "properties": {
    "iso:country":"DE",
    "sg:address":"Franziskanerstr. 4",
    "sg:city":"Boppard",
    "sg:phone":"+49 6742/3010",
    "sg:postcode":"56154",
    "sg:province":"Rheinland-Pfalz",
    "wof:name":"Josef H\u00f6ffling",
    "wof:placetype":"venue"
},
  "geometry": {"coordinates":[7.5950732231,50.2321777344],"type":"Point"}
}