{
  "type": "Feature",
  "properties": {
    "iso:country":"DE",
    "sg:address":"Eintrachtstr 33",
    "sg:city":"Ahlen",
    "sg:phone":"+49 2382/9899921",
    "sg:postcode":"59227",
    "sg:province":"Nordrhein-Westfalen",
    "wof:name":"Zinc-art\u00ae",
    "wof:placetype":"venue"
},
  "geometry": {"coordinates":[7.8986010551,51.7701377869],"type":"Point"}
}