{
  "type": "Feature",
  "properties": {
    "iso:country":"DE",
    "sg:address":"Paderwall 1",
    "sg:city":"Paderborn",
    "sg:postcode":"33102",
    "sg:province":"Nordrhein-Westfalen",
    "wof:name":"Mlp Finazdienstleistungen Ag",
    "wof:placetype":"venue"
},
  "geometry": {"coordinates":[8.7487430573,51.7209777832],"type":"Point"}
}