{
  "type": "Feature",
  "properties": {
    "iso:country":"DE",
    "sg:address":"Etzelstr. 44",
    "sg:city":"Heilbronn",
    "sg:postcode":"74076",
    "sg:province":"Baden-W\u00fcrttemberg",
    "wof:name":"Obi Bau- Und Heimwerkermarkt",
    "wof:placetype":"venue"
},
  "geometry": {"coordinates":[9.213681221,49.1531181335],"type":"Point"}
}