{
  "type": "Feature",
  "properties": {
    "iso:country":"DE",
    "sg:address":"Ammerstr. 2",
    "sg:city":"N\u00fcrtingen",
    "sg:phone":"+49 7022/64685",
    "sg:postcode":"72622",
    "sg:province":"Baden-W\u00fcrttemberg",
    "wof:name":"S. Gall",
    "wof:placetype":"venue"
},
  "geometry": {"coordinates":[9.341926,48.626637],"type":"Point"}
}