{
  "type": "Feature",
  "properties": {
    "iso:country":"DE",
    "sg:address":"Kanzleigasse 30",
    "sg:city":"Villingen-Schwenningen",
    "sg:phone":"+49 7721/51080",
    "sg:postcode":"78050",
    "sg:province":"Baden-W\u00fcrttemberg",
    "wof:name":"Katholisches Bildungswerk",
    "wof:placetype":"venue"
},
  "geometry": {"coordinates":[8.4568395615,48.0606994629],"type":"Point"}
}