{
  "type": "Feature",
  "properties": {
    "iso:country":"DE",
    "sg:address":"Eichenheege 10",
    "sg:city":"Maintal",
    "sg:phone":"+49 6181/494651",
    "sg:postcode":"63477",
    "sg:province":"Hessen",
    "wof:name":"Werner Schmitz Architekt",
    "wof:placetype":"venue"
},
  "geometry": {"coordinates":[8.847175,50.140606],"type":"Point"}
}