{
  "type": "Feature",
  "properties": {
    "iso:country":"DE",
    "sg:address":"D\u00fcrrnbuch 15",
    "sg:city":"Emskirchen",
    "sg:postcode":"91448",
    "sg:province":"Bayern",
    "wof:name":"Rainer Sch\u00fchlein E. K.",
    "wof:placetype":"venue"
},
  "geometry": {"coordinates":[10.7186412811,49.5149993896],"type":"Point"}
}