{
  "type": "Feature",
  "properties": {
    "iso:country":"DE",
    "sg:address":"Im Oberdorf 9",
    "sg:city":"Nonnweiler",
    "sg:phone":"+49 6873/7947",
    "sg:postcode":"66620",
    "sg:province":"Saarland",
    "wof:name":"Leonhard Klein",
    "wof:placetype":"venue"
},
  "geometry": {"coordinates":[6.916275,49.605087],"type":"Point"}
}