{
  "type": "Feature",
  "properties": {
    "iso:country":"DE",
    "sg:address":"Huven 19",
    "sg:city":"Much",
    "sg:phone":"+49 2245/3618",
    "sg:postcode":"53804",
    "sg:province":"Nordrhein-Westfalen",
    "wof:name":"Richard Br\u00fcckner",
    "wof:placetype":"venue"
},
  "geometry": {"coordinates":[7.349812,50.883255],"type":"Point"}
}