{
  "type": "Feature",
  "properties": {
    "iso:country":"DE",
    "sg:address":"Giesekestr. 2",
    "sg:city":"Mauth",
    "sg:phone":"+49 8557/246",
    "sg:postcode":"94151",
    "sg:province":"Bayern",
    "wof:name":"Gemeindeb\u00fccherei",
    "wof:placetype":"venue"
},
  "geometry": {"coordinates":[13.582978,48.889835],"type":"Point"}
}