{
  "type": "Feature",
  "properties": {
    "iso:country":"DE",
    "sg:address":"Akazienweg 7",
    "sg:city":"Pl\u00f6tzky",
    "sg:phone":"+49 39200/51194",
    "sg:postcode":"39245",
    "sg:province":"Sachsen-Anhalt",
    "wof:name":"Doehring Gmbh",
    "wof:placetype":"venue"
},
  "geometry": {"coordinates":[11.800888,52.054745],"type":"Point"}
}