{
  "type": "Feature",
  "properties": {
    "iso:country":"DE",
    "sg:address":"Rechener Str. 2a",
    "sg:city":"Bochum",
    "sg:phone":"+49 2327/945335",
    "sg:postcode":"44787",
    "sg:province":"Nordrhein-Westfalen",
    "wof:name":"Form In Form",
    "wof:placetype":"venue"
},
  "geometry": {"coordinates":[7.2194991112,51.4783096313],"type":"Point"}
}