{
  "type": "Feature",
  "properties": {
    "iso:country":"DE",
    "sg:address":"Herzog-Friedrich-Str. 41-45::",
    "sg:city":"Kiel",
    "sg:phone":"+49 4943/166320",
    "sg:postcode":"24103",
    "sg:province":"Schleswig-Holstein",
    "wof:name":"Ev Darlehnsgenossenschaft Eg",
    "wof:placetype":"venue"
},
  "geometry": {"coordinates":[10.129859,54.317753],"type":"Point"}
}