{
  "type": "Feature",
  "properties": {
    "iso:country":"DE",
    "sg:address":"Gau\u00dfstr. 1",
    "sg:city":"Neuss",
    "sg:phone":"+49 2131/80260",
    "sg:postcode":"41464",
    "sg:province":"Nordrhein-Westfalen",
    "wof:name":"Friedrich Werner",
    "wof:placetype":"venue"
},
  "geometry": {"coordinates":[6.6750421524,51.1860809326],"type":"Point"}
}