{
  "type": "Feature",
  "properties": {
    "iso:country":"DE",
    "sg:address":"R\u00f6ntgenweg 35",
    "sg:city":"D\u00fcsseldorf",
    "sg:postcode":"40591",
    "sg:province":"Nordrhein-Westfalen",
    "wof:name":"Holowski",
    "wof:placetype":"venue"
},
  "geometry": {"coordinates":[6.8151950836,51.1874923706],"type":"Point"}
}