{
  "type": "Feature",
  "properties": {
    "iso:country":"DE",
    "sg:address":"Im Br\u00fchl 36",
    "sg:city":"Dannstadt-Schauernheim",
    "sg:postcode":"67125",
    "sg:province":"Rheinland-Pfalz",
    "wof:name":"Cda Berlejung Gmbh",
    "wof:placetype":"venue"
},
  "geometry": {"coordinates":[8.31113,49.435982],"type":"Point"}
}