{
  "type": "Feature",
  "properties": {
    "iso:country":"DE",
    "sg:address":"Neumarkt 4",
    "sg:city":"Gro\u00dfenhain",
    "sg:postcode":"01558",
    "sg:province":"Sachsen",
    "wof:name":"Simon K\u00f6ppler Gmbh",
    "wof:placetype":"venue"
},
  "geometry": {"coordinates":[13.5294017792,51.2918281555],"type":"Point"}
}