{
  "type": "Feature",
  "properties": {
    "iso:country":"DE",
    "sg:address":"Pfeddersheimer Str. 95",
    "sg:city":"Worms",
    "sg:phone":"+49 6241/54973",
    "sg:postcode":"67549",
    "sg:province":"Rheinland-Pfalz",
    "wof:name":"Mitech Minius Technologie Gmbh",
    "wof:placetype":"venue"
},
  "geometry": {"coordinates":[8.30919,49.639633],"type":"Point"}
}