{
  "type": "Feature",
  "properties": {
    "iso:country":"DE",
    "sg:address":"Hofer Str. 2a",
    "sg:city":"Gefrees",
    "sg:phone":"+49 9254/91193",
    "sg:postcode":"95482",
    "sg:province":"Bayern",
    "wof:name":"Vereinte Krankenversicherung Wolfgang Geigner",
    "wof:placetype":"venue"
},
  "geometry": {"coordinates":[11.7408361435,50.0956535339],"type":"Point"}
}