{
  "type": "Feature",
  "properties": {
    "iso:country":"DE",
    "sg:address":"Gunninger Str. 1",
    "sg:city":"Spaichingen",
    "sg:phone":"+49 7424/7135",
    "sg:postcode":"78549",
    "sg:province":"Baden-W\u00fcrttemberg",
    "wof:name":"R. Grimm",
    "wof:placetype":"venue"
},
  "geometry": {"coordinates":[8.7337722778,48.0692825317],"type":"Point"}
}