{
  "type": "Feature",
  "properties": {
    "iso:country":"DE",
    "sg:address":"Goethestr. 10",
    "sg:city":"Gotha",
    "sg:phone":"+49 3621/750743",
    "sg:postcode":"99867",
    "sg:province":"Th\u00fcringen",
    "wof:name":"S. Stra\u00dfer",
    "wof:placetype":"venue"
},
  "geometry": {"coordinates":[10.694122,50.941952],"type":"Point"}
}