{
  "type": "Feature",
  "properties": {
    "iso:country":"DE",
    "sg:address":"Hauptstr. 22",
    "sg:city":"Rauenberg",
    "sg:phone":"+49 6222/62902",
    "sg:postcode":"69231",
    "sg:province":"Baden-W\u00fcrttemberg",
    "wof:name":"Josef Rimmele",
    "wof:placetype":"venue"
},
  "geometry": {"coordinates":[8.707388,49.267193],"type":"Point"}
}