{
  "type": "Feature",
  "properties": {
    "iso:country":"DE",
    "sg:address":"Kirchenstr. 26",
    "sg:city":"Merzig",
    "sg:phone":"+49 6861/75769",
    "sg:postcode":"66663",
    "sg:province":"Saarland",
    "wof:name":"Austgen Werbeagentur Gmbh",
    "wof:placetype":"venue"
},
  "geometry": {"coordinates":[6.6803851128,49.4412117004],"type":"Point"}
}