{
  "type": "Feature",
  "properties": {
    "iso:country":"DE",
    "sg:address":"Mittelweg 14",
    "sg:city":"Sylt-Ost",
    "sg:phone":"+49 4651/3451",
    "sg:postcode":"25980",
    "sg:province":"Schleswig-Holstein",
    "wof:name":"Kurt Hirschberger",
    "wof:placetype":"venue"
},
  "geometry": {"coordinates":[8.342,54.899399],"type":"Point"}
}