{
  "type": "Feature",
  "properties": {
    "iso:country":"DE",
    "sg:address":"Wilhelm-Kraut-Str. 111",
    "sg:city":"Balingen",
    "sg:phone":"+49 7433/4278",
    "sg:postcode":"72336",
    "sg:province":"Baden-W\u00fcrttemberg",
    "wof:name":"Aral Ag",
    "wof:placetype":"venue"
},
  "geometry": {"coordinates":[8.8523578644,48.2641677856],"type":"Point"}
}