{
  "type": "Feature",
  "properties": {
    "iso:country":"DE",
    "sg:address":"Fischbacher Str. 58",
    "sg:city":"Kelkheim",
    "sg:phone":"+49 6195/74541",
    "sg:postcode":"65779",
    "sg:province":"Hessen",
    "wof:name":"Thermograph W\u00e4rme- Bildtechnik Gmbh",
    "wof:placetype":"venue"
},
  "geometry": {"coordinates":[8.43926,50.140766],"type":"Point"}
}