{
  "type": "Feature",
  "properties": {
    "iso:country":"DE",
    "sg:city":"B\u00fchlerzell",
    "sg:phone":"+49 4979/74488",
    "sg:postcode":"74426",
    "sg:province":"Baden-W\u00fcrttemberg",
    "wof:name":"Raiffeisenbank B\u00fchlerzell Eg",
    "wof:placetype":"venue"
},
  "geometry": {"coordinates":[9.918382,49.003448],"type":"Point"}
}