{
  "type": "Feature",
  "properties": {
    "iso:country":"DE",
    "sg:address":"Friedastr. 9",
    "sg:city":"M\u00fcnchen",
    "sg:phone":"+49 89/798848",
    "sg:postcode":"81479",
    "sg:province":"Bayern",
    "wof:name":"Edwin Von Nieciecki Architekt",
    "wof:placetype":"venue"
},
  "geometry": {"coordinates":[11.531613,48.080368],"type":"Point"}
}