{
  "type": "Feature",
  "properties": {
    "iso:country":"DE",
    "sg:address":"Gro\u00dfe Str. 86",
    "sg:city":"Kleve",
    "sg:phone":"+49 2821/17624",
    "sg:postcode":"47533",
    "sg:province":"Nordrhein-Westfalen",
    "wof:name":"B. Van Brakel",
    "wof:placetype":"venue"
},
  "geometry": {"coordinates":[6.137788,51.787163],"type":"Point"}
}