{
  "type": "Feature",
  "properties": {
    "iso:country":"DE",
    "sg:address":"Eythstr. 99",
    "sg:city":"K\u00f6ln",
    "sg:phone":"+49 221/854034",
    "sg:postcode":"51103",
    "sg:province":"Nordrhein-Westfalen",
    "wof:name":"Zur Sportklause",
    "wof:placetype":"venue"
},
  "geometry": {"coordinates":[7.0097098351,50.9438552856],"type":"Point"}
}