{
  "type": "Feature",
  "properties": {
    "iso:country":"DE",
    "sg:address":"Richard-Wagner-Str. 61",
    "sg:city":"Singen",
    "sg:phone":"+49 7731/48133",
    "sg:postcode":"78224",
    "sg:province":"Baden-W\u00fcrttemberg",
    "wof:name":"Norma Lebensmittel- Filialbetrieb Gmbh & Co. Kg",
    "wof:placetype":"venue"
},
  "geometry": {"coordinates":[8.844329834,47.7735786438],"type":"Point"}
}