{
  "type": "Feature",
  "properties": {
    "iso:country":"DE",
    "sg:address":"Pfalzeler Str. 6 a",
    "sg:city":"Trier",
    "sg:phone":"+49 651/69031",
    "sg:postcode":"54293",
    "sg:province":"Rheinland-Pfalz",
    "wof:name":"Ortwin Harings Drogerie",
    "wof:placetype":"venue"
},
  "geometry": {"coordinates":[6.690142,49.780502],"type":"Point"}
}