{
  "type": "Feature",
  "properties": {
    "iso:country":"DE",
    "sg:address":"Allinger Str. 59",
    "sg:city":"Puchheim",
    "sg:phone":"+49 89/8005243",
    "sg:postcode":"82178",
    "sg:province":"Bayern",
    "wof:name":"R. Smit Immobilienmakler",
    "wof:placetype":"venue"
},
  "geometry": {"coordinates":[11.3424453735,48.1677093506],"type":"Point"}
}