{
  "type": "Feature",
  "properties": {
    "iso:country":"DE",
    "sg:address":"Bauernweg 2 b",
    "sg:city":"Frankfurt",
    "sg:phone":"+49 335/5212113",
    "sg:postcode":"15234",
    "sg:province":"Brandenburg",
    "wof:name":"Kuhlmann Und Marquardt",
    "wof:placetype":"venue"
},
  "geometry": {"coordinates":[14.441656,52.310474],"type":"Point"}
}