{
  "type": "Feature",
  "properties": {
    "iso:country":"DE",
    "sg:address":"Hauptstr. 24",
    "sg:city":"Kirchheim",
    "sg:phone":"+49 8266/1777",
    "sg:postcode":"87757",
    "sg:province":"Bayern",
    "wof:name":"Gerald Kriegl",
    "wof:placetype":"venue"
},
  "geometry": {"coordinates":[10.48064,48.172077],"type":"Point"}
}