{
  "type": "Feature",
  "properties": {
    "iso:country":"DE",
    "sg:address":"Kieler Str. 25",
    "sg:city":"Bilsen",
    "sg:phone":"+49 4106/68453",
    "sg:postcode":"25485",
    "sg:province":"Schleswig-Holstein",
    "wof:name":"Hotel-gastst\u00e4tte Zur Bilsener M\u00fchle",
    "wof:placetype":"venue"
},
  "geometry": {"coordinates":[9.875743866,53.7724723816],"type":"Point"}
}