{
  "type": "Feature",
  "properties": {
    "iso:country":"DE",
    "sg:address":"Hauptstr. 308",
    "sg:city":"M\u00fcnsingen",
    "sg:phone":"+49 7381/2243",
    "sg:postcode":"72525",
    "sg:province":"Baden-W\u00fcrttemberg",
    "wof:name":"Heinz Bopp",
    "wof:placetype":"venue"
},
  "geometry": {"coordinates":[9.5331001282,48.4120407104],"type":"Point"}
}