{
  "type": "Feature",
  "properties": {
    "iso:country":"DE",
    "sg:address":"Lutherstr. 12",
    "sg:city":"Ludwigshafen",
    "sg:phone":"+49 621/598090",
    "sg:postcode":"67059",
    "sg:province":"Rheinland-Pfalz",
    "wof:name":"Wei\u00df & Hameier Verwaltungs Gmbh",
    "wof:placetype":"venue"
},
  "geometry": {"coordinates":[8.444247,49.480976],"type":"Point"}
}