{
  "type": "Feature",
  "properties": {
    "iso:country":"DE",
    "sg:address":"Kaiserstr. 75",
    "sg:city":"Dortmund",
    "sg:phone":"+49 231/523696",
    "sg:postcode":"44135",
    "sg:province":"Nordrhein-Westfalen",
    "wof:name":"Bambolina",
    "wof:placetype":"venue"
},
  "geometry": {"coordinates":[7.4814572334,51.5130882263],"type":"Point"}
}