{
  "type": "Feature",
  "properties": {
    "iso:country":"DE",
    "sg:address":"Hagenau 19",
    "sg:city":"Mengkofen",
    "sg:phone":"+49 8774/376",
    "sg:postcode":"84152",
    "sg:province":"Bayern",
    "wof:name":"Daxenberger Schreinerei Gmbh",
    "wof:placetype":"venue"
},
  "geometry": {"coordinates":[12.350158,48.713314],"type":"Point"}
}