{
  "type": "Feature",
  "properties": {
    "iso:country":"DE",
    "sg:address":"Wilhelmstr. 20",
    "sg:city":"Kreiensen",
    "sg:phone":"+49 5563/222",
    "sg:postcode":"37547",
    "sg:province":"Niedersachsen",
    "wof:name":"Hans-joachim Mateika",
    "wof:placetype":"venue"
},
  "geometry": {"coordinates":[9.96165,51.856197],"type":"Point"}
}