{
  "type": "Feature",
  "properties": {
    "iso:country":"DE",
    "sg:address":"Am Huchtinger See 12",
    "sg:city":"Bremen",
    "sg:phone":"+49 421/581539",
    "sg:postcode":"28259",
    "sg:province":"Bremen",
    "wof:name":"Bernhard Boumann Grundst\u00fccks- Verwaltungs-gmbh",
    "wof:placetype":"venue"
},
  "geometry": {"coordinates":[8.7450532913,53.0609779358],"type":"Point"}
}