{
  "type": "Feature",
  "properties": {
    "iso:country":"DE",
    "sg:address":"Georgenstr. 22",
    "sg:city":"Amberg",
    "sg:postcode":"92224",
    "sg:province":"Bayern",
    "wof:name":"Fielmann Augenoptik Ag & Co. Ohg",
    "wof:placetype":"venue"
},
  "geometry": {"coordinates":[11.855461,49.444798],"type":"Point"}
}