{
  "type": "Feature",
  "properties": {
    "iso:country":"DE",
    "sg:address":"Schulweg 7",
    "sg:city":"Neckarsteinach",
    "sg:phone":"+49 6229/7814",
    "sg:postcode":"69239",
    "sg:province":"Hessen",
    "wof:name":"Sam Schiffahrtssges. Mbh",
    "wof:placetype":"venue"
},
  "geometry": {"coordinates":[8.878043,49.41713],"type":"Point"}
}