{
  "type": "Feature",
  "properties": {
    "iso:country":"DE",
    "sg:address":"Marktstr. 189",
    "sg:city":"Oberhausen",
    "sg:phone":"+49 208/209697",
    "sg:postcode":"46045",
    "sg:province":"Nordrhein-Westfalen",
    "wof:name":"Adriatic",
    "wof:placetype":"venue"
},
  "geometry": {"coordinates":[6.8550748825,51.4694519043],"type":"Point"}
}