{
  "type": "Feature",
  "properties": {
    "iso:country":"DE",
    "sg:address":"Schellingstr 14",
    "sg:city":"Hamburg",
    "sg:phone":"+49 40/2008447",
    "sg:postcode":"22089",
    "sg:province":"Hamburg",
    "wof:name":"Druckerei May",
    "wof:placetype":"venue"
},
  "geometry": {"coordinates":[10.046125,53.568756],"type":"Point"}
}