{
  "type": "Feature",
  "properties": {
    "iso:country":"DE",
    "sg:address":"Kaiserstr. 43",
    "sg:city":"W\u00fcrselen",
    "sg:phone":"+49 2405/21222",
    "sg:postcode":"52146",
    "sg:province":"Nordrhein-Westfalen",
    "wof:name":"Vogelsberg Gmbh Adamo Mode F\u00fcr M\u00e4nner",
    "wof:placetype":"venue"
},
  "geometry": {"coordinates":[6.131070137,50.820186615],"type":"Point"}
}