{
  "type": "Feature",
  "properties": {
    "iso:country":"DE",
    "sg:address":"Steintor",
    "sg:city":"Gehrden",
    "sg:postcode":"30989",
    "sg:province":"Niedersachsen",
    "wof:name":"Volksbank Rosenfeld Eg",
    "wof:placetype":"venue"
},
  "geometry": {"coordinates":[8.723455,48.28624],"type":"Point"}
}