{
  "type": "Feature",
  "properties": {
    "iso:country":"DE",
    "sg:address":"Grube 9",
    "sg:city":"Paderborn",
    "sg:phone":"+49 5251/25444",
    "sg:postcode":"33098",
    "sg:province":"Nordrhein-Westfalen",
    "wof:name":"Janssen",
    "wof:placetype":"venue"
},
  "geometry": {"coordinates":[8.756358,51.717274],"type":"Point"}
}