{
  "type": "Feature",
  "properties": {
    "iso:country":"DE",
    "sg:address":"Riegelhofweg 17",
    "sg:city":"Ostfildern",
    "sg:postcode":"73760",
    "sg:province":"Baden-W\u00fcrttemberg",
    "wof:name":"Donaubauer Hebetechnik Gmbh",
    "wof:placetype":"venue"
},
  "geometry": {"coordinates":[9.292711,48.713947],"type":"Point"}
}