{
  "type": "Feature",
  "properties": {
    "iso:country":"DE",
    "sg:address":"Kanalstr. 3",
    "sg:city":"Homburg",
    "sg:phone":"+49 6841/120546",
    "sg:postcode":"66424",
    "sg:province":"Saarland",
    "wof:name":"P.-l. Lass Immobilienmakler",
    "wof:placetype":"venue"
},
  "geometry": {"coordinates":[7.3408942223,49.3247833252],"type":"Point"}
}