{
  "type": "Feature",
  "properties": {
    "iso:country":"DE",
    "sg:address":"Kattenberg 1",
    "sg:city":"Goslar",
    "sg:phone":"+49 5321/81233",
    "sg:postcode":"38640",
    "sg:province":"Niedersachsen",
    "wof:name":"Hygienia Medizinische Fachhandels Gmbh",
    "wof:placetype":"venue"
},
  "geometry": {"coordinates":[10.4177303314,51.9177894592],"type":"Point"}
}