{
  "type": "Feature",
  "properties": {
    "iso:country":"DE",
    "sg:address":"Maxh\u00fctter Str. 29",
    "sg:city":"Burglengenfeld",
    "sg:phone":"+49 9471/5808",
    "sg:postcode":"93133",
    "sg:province":"Bayern",
    "wof:name":"K. Nicklas",
    "wof:placetype":"venue"
},
  "geometry": {"coordinates":[12.0486049652,49.2047386169],"type":"Point"}
}