{
  "type": "Feature",
  "properties": {
    "iso:country":"DE",
    "sg:address":"Raboisen 101",
    "sg:city":"Hamburg",
    "sg:phone":"+49 40/330315",
    "sg:postcode":"20095",
    "sg:province":"Hamburg",
    "wof:name":"Hans-peter Stiller Masseur",
    "wof:placetype":"venue"
},
  "geometry": {"coordinates":[9.997237,53.55159],"type":"Point"}
}