{
  "type": "Feature",
  "properties": {
    "iso:country":"DE",
    "sg:address":"Lipper Hellweg 32",
    "sg:city":"Bielefeld",
    "sg:phone":"+49 521/92130",
    "sg:postcode":"33604",
    "sg:province":"Nordrhein-Westfalen",
    "wof:name":"Wilhelm-augusta-stift Alten- Und Pflegeheim",
    "wof:placetype":"venue"
},
  "geometry": {"coordinates":[8.555211,52.003548],"type":"Point"}
}