{
  "type": "Feature",
  "properties": {
    "iso:country":"DE",
    "sg:address":"Arnimallee 23-27",
    "sg:city":"Berlin",
    "sg:phone":"+49 30/20355503",
    "sg:postcode":"14195",
    "sg:province":"Berlin",
    "wof:name":"Skulpturensammlung",
    "wof:placetype":"venue"
},
  "geometry": {"coordinates":[13.293767,52.455547],"type":"Point"}
}