{
  "type": "Feature",
  "properties": {
    "iso:country":"DE",
    "sg:address":"Hauptstr. 12",
    "sg:city":"Lengenfeld unterm Stein",
    "sg:phone":"+49 36027/70286",
    "sg:postcode":"99976",
    "sg:province":"Th\u00fcringen",
    "wof:name":"Hildegunde Morgenthal",
    "wof:placetype":"venue"
},
  "geometry": {"coordinates":[10.215185,51.2159],"type":"Point"}
}