{
  "type": "Feature",
  "properties": {
    "iso:country":"DE",
    "sg:address":"Karl-Liebknecht-Str. 30",
    "sg:city":"Leipzig",
    "sg:phone":"+49 341/3011807",
    "sg:postcode":"04107",
    "sg:province":"Sachsen",
    "wof:name":"Instruct Gmbh",
    "wof:placetype":"venue"
},
  "geometry": {"coordinates":[12.3733901978,51.3276939392],"type":"Point"}
}