{
  "type": "Feature",
  "properties": {
    "iso:country":"DE",
    "sg:address":"Terminalstr-Mitte. 18",
    "sg:city":"M\u00fcnchen",
    "sg:phone":"+49 89",
    "sg:postcode":"85356",
    "sg:province":"Bayern",
    "wof:name":"Lastminute Reisen Weltweit \u00fcber 10000 Aktuelle Angebote",
    "wof:placetype":"venue"
},
  "geometry": {"coordinates":[11.787436,48.353054],"type":"Point"}
}