{
  "type": "Feature",
  "properties": {
    "iso:country":"DE",
    "sg:address":"Birkenweg 24",
    "sg:city":"Hemslingen",
    "sg:phone":"+49 4266/618",
    "sg:postcode":"27386",
    "sg:province":"Niedersachsen",
    "wof:name":"Hans-hinnerk Schr\u00f6der",
    "wof:placetype":"venue"
},
  "geometry": {"coordinates":[9.595855,53.08477],"type":"Point"}
}