{
  "type": "Feature",
  "properties": {
    "iso:country":"DE",
    "sg:address":"Eppmannsweg 23",
    "sg:city":"Gelsenkirchen",
    "sg:phone":"+49 209/65497",
    "sg:postcode":"45896",
    "sg:province":"Nordrhein-Westfalen",
    "wof:name":"D. K\u00f6rber",
    "wof:placetype":"venue"
},
  "geometry": {"coordinates":[7.0537071228,51.6097831726],"type":"Point"}
}