{
  "type": "Feature",
  "properties": {
    "iso:country":"DE",
    "sg:address":"Hintergasse 25",
    "sg:city":"Biblis",
    "sg:phone":"+49 6245/3596",
    "sg:postcode":"68647",
    "sg:province":"Hessen",
    "wof:name":"C. Reis",
    "wof:placetype":"venue"
},
  "geometry": {"coordinates":[8.455141,49.685101],"type":"Point"}
}