{
  "type": "Feature",
  "properties": {
    "iso:country":"DE",
    "sg:address":"Lehmgrubenweg 2",
    "sg:city":"Albertshausen",
    "sg:phone":"+49 171",
    "sg:postcode":"97234",
    "sg:province":"Bayern",
    "wof:name":"Www.der-bilanzbuchhalter.de",
    "wof:placetype":"venue"
},
  "geometry": {"coordinates":[9.92699,49.693287],"type":"Point"}
}