{
  "type": "Feature",
  "properties": {
    "iso:country":"DE",
    "sg:city":"Oberhambach",
    "sg:phone":"+49 6782/1010",
    "sg:postcode":"55765",
    "sg:province":"Rheinland-Pfalz",
    "wof:name":"Hunsr\u00fcck-ferienpark-hambachtal Beteiligungsgesellschaft Mbh",
    "wof:placetype":"venue"
},
  "geometry": {"coordinates":[7.156591,49.686165],"type":"Point"}
}