{
  "type": "Feature",
  "properties": {
    "iso:country":"DE",
    "sg:address":"Am Oberberg 5",
    "sg:city":"Kronberg",
    "sg:phone":"+49 6173/63041",
    "sg:postcode":"61476",
    "sg:province":"Hessen",
    "wof:name":"Prof. Wolfgang Heiermann Rechtsanwalt",
    "wof:placetype":"venue"
},
  "geometry": {"coordinates":[8.5213689804,50.1867599487],"type":"Point"}
}