{
  "type": "Feature",
  "properties": {
    "iso:country":"DE",
    "sg:address":"R\u00fcnther Str. 97",
    "sg:city":"Bergkamen",
    "sg:phone":"+49 2389/1663",
    "sg:postcode":"59192",
    "sg:province":"Nordrhein-Westfalen",
    "wof:name":"Steffanie-moden Inh. Gabriele Humpert",
    "wof:placetype":"venue"
},
  "geometry": {"coordinates":[7.662477,51.6465],"type":"Point"}
}