{
  "type": "Feature",
  "properties": {
    "iso:country":"DE",
    "sg:address":"Klemensstr.",
    "sg:city":"Meitingen",
    "sg:phone":"+49 8271/40404",
    "sg:postcode":"86405",
    "sg:province":"Bayern",
    "wof:name":"Schmid",
    "wof:placetype":"venue"
},
  "geometry": {"coordinates":[10.8503751755,48.5309104919],"type":"Point"}
}