{
  "type": "Feature",
  "properties": {
    "iso:country":"DE",
    "sg:address":"Hans-Urmiller-Ring 55",
    "sg:city":"Wolfratshausen",
    "sg:phone":"+49 8171/42170",
    "sg:postcode":"82515",
    "sg:province":"Bayern",
    "wof:name":"Forrest Comp-computer & Software Kg",
    "wof:placetype":"venue"
},
  "geometry": {"coordinates":[11.4316396713,47.9048728943],"type":"Point"}
}