{
  "type": "Feature",
  "properties": {
    "iso:country":"DE",
    "sg:address":"Stockder Str. 12 Ot Vieringhausen",
    "sg:city":"Remscheid",
    "sg:phone":"+49 4921/9197420",
    "sg:postcode":"42857",
    "sg:province":"Nordrhein-Westfalen",
    "wof:name":"Loose-durach Kunst- U. Graphische Werkst\u00c4tten-gmbh",
    "wof:placetype":"venue"
},
  "geometry": {"coordinates":[7.1441159248,51.1881103516],"type":"Point"}
}