{
  "type": "Feature",
  "properties": {
    "iso:country":"DE",
    "sg:address":"T\u00fcrkheimer Str. 3a",
    "sg:city":"Bad W\u00f6rishofen",
    "sg:phone":"+49 8247/34220",
    "sg:postcode":"86825",
    "sg:province":"Bayern",
    "wof:name":"Schneider Immobilienmakler",
    "wof:placetype":"venue"
},
  "geometry": {"coordinates":[10.5970573425,48.0082359314],"type":"Point"}
}