{
  "type": "Feature",
  "properties": {
    "iso:country":"DE",
    "sg:address":"Judengasse 9",
    "sg:city":"Abenberg",
    "sg:phone":"+49 9178/904642",
    "sg:postcode":"91183",
    "sg:province":"Bayern",
    "wof:name":"Regina K\u00f6ster Rechtsanw\u00e4ltin",
    "wof:placetype":"venue"
},
  "geometry": {"coordinates":[10.9629421234,49.2425460815],"type":"Point"}
}