{
  "type": "Feature",
  "properties": {
    "iso:country":"DE",
    "sg:address":"Gartenstr. 9",
    "sg:city":"Hameln",
    "sg:phone":"+49 5151/21230",
    "sg:postcode":"31785",
    "sg:province":"Niedersachsen",
    "wof:name":"Georgia Geppert Hebamme",
    "wof:placetype":"venue"
},
  "geometry": {"coordinates":[9.360667,52.108852],"type":"Point"}
}