{
  "type": "Feature",
  "properties": {
    "iso:country":"DE",
    "sg:address":"Westmarkstr. 28",
    "sg:city":"Karlsruhe",
    "sg:phone":"+49 721/406127",
    "sg:postcode":"76227",
    "sg:province":"Baden-W\u00fcrttemberg",
    "wof:name":"Manfred Felber",
    "wof:placetype":"venue"
},
  "geometry": {"coordinates":[8.459159,48.991333],"type":"Point"}
}