{
  "type": "Feature",
  "properties": {
    "iso:country":"DE",
    "sg:address":"Berberitzenweg 6",
    "sg:city":"Bad Zwischenahn",
    "sg:phone":"+49 4403/5633",
    "sg:postcode":"26160",
    "sg:province":"Niedersachsen",
    "wof:name":"Gal Ger\u00e4te-anlagen-leasing Rolf Grimm Gmbh & Co. Kg",
    "wof:placetype":"venue"
},
  "geometry": {"coordinates":[8.0119829178,53.1787643433],"type":"Point"}
}