{
  "type": "Feature",
  "properties": {
    "iso:country":"DE",
    "sg:address":"Marinestr. 36",
    "sg:city":"Hamm",
    "sg:phone":"+49 2381/73288",
    "sg:postcode":"59075",
    "sg:province":"Nordrhein-Westfalen",
    "wof:name":"B\u00f6hm",
    "wof:placetype":"venue"
},
  "geometry": {"coordinates":[7.7588558197,51.6963691711],"type":"Point"}
}