{
  "type": "Feature",
  "properties": {
    "iso:country":"DE",
    "sg:address":"Finkenwerder Norderdeich 53",
    "sg:city":"Hamburg",
    "sg:phone":"+49 40/7426672",
    "sg:postcode":"21129",
    "sg:province":"Hamburg",
    "wof:name":"Carl Uhrbrock & Sohn Inh. Peter Uhrbrock",
    "wof:placetype":"venue"
},
  "geometry": {"coordinates":[9.8608179092,53.5191574097],"type":"Point"}
}