{
  "type": "Feature",
  "properties": {
    "iso:country":"DE",
    "sg:address":"Dornierstr. 35",
    "sg:city":"Tuttlingen",
    "sg:phone":"+49 7461/3183",
    "sg:postcode":"78532",
    "sg:province":"Baden-W\u00fcrttemberg",
    "wof:name":"Egon Hilzinger",
    "wof:placetype":"venue"
},
  "geometry": {"coordinates":[8.789691925,47.9710960388],"type":"Point"}
}