{
  "type": "Feature",
  "properties": {
    "iso:country":"DE",
    "sg:address":"Sohrstr. 7",
    "sg:city":"Sch\u00f6neck",
    "sg:phone":"+49 37464/88340",
    "sg:postcode":"08261",
    "sg:province":"Sachsen",
    "wof:name":"Frank Schuster",
    "wof:placetype":"venue"
},
  "geometry": {"coordinates":[12.3320436478,50.395149231],"type":"Point"}
}