{
  "type": "Feature",
  "properties": {
    "iso:country":"DE",
    "sg:address":"Bernauer Str. 108",
    "sg:city":"Oranienburg",
    "sg:phone":"+49 3301/802564",
    "sg:postcode":"16515",
    "sg:province":"Brandenburg",
    "wof:name":"Schreibwaren Thur",
    "wof:placetype":"venue"
},
  "geometry": {"coordinates":[13.25461483,52.758682251],"type":"Point"}
}