{
  "type": "Feature",
  "properties": {
    "iso:country":"DE",
    "sg:address":"K\u00f6ttinger Weg 118",
    "sg:city":"Wissen",
    "sg:phone":"+49 2742/3900",
    "sg:postcode":"57537",
    "sg:province":"Rheinland-Pfalz",
    "wof:name":"Cosytronic Computer-system- Elektronik Gmbh",
    "wof:placetype":"venue"
},
  "geometry": {"coordinates":[7.7341880798,50.77003479],"type":"Point"}
}