{
  "type": "Feature",
  "properties": {
    "iso:country":"DE",
    "sg:address":"Neuwieder Str. 16",
    "sg:city":"Neuwied",
    "sg:phone":"+49 2622/7435",
    "sg:postcode":"56566",
    "sg:province":"Rheinland-Pfalz",
    "wof:name":"Johann P. Neckenig",
    "wof:placetype":"venue"
},
  "geometry": {"coordinates":[7.542333,50.424854],"type":"Point"}
}