{
  "type": "Feature",
  "properties": {
    "iso:country":"DE",
    "sg:address":"Depenkamp 2",
    "sg:city":"Hamburg",
    "sg:phone":"+49 40/8324773",
    "sg:postcode":"22549",
    "sg:province":"Hamburg",
    "wof:name":"Hamburger Lehrer-feuerkasse",
    "wof:placetype":"venue"
},
  "geometry": {"coordinates":[9.8670701981,53.5884361267],"type":"Point"}
}