{
  "type": "Feature",
  "properties": {
    "iso:country":"DE",
    "sg:address":"Nittenauer Str. 60",
    "sg:city":"Steinberg",
    "sg:phone":"+49 9431/742050",
    "sg:postcode":"92449",
    "sg:province":"Bayern",
    "wof:name":"Pcbcad Elektronik Gmbh",
    "wof:placetype":"venue"
},
  "geometry": {"coordinates":[12.1880989075,49.2659454346],"type":"Point"}
}