{
  "type": "Feature",
  "properties": {
    "iso:country":"DE",
    "sg:address":"Jahnstr. 19",
    "sg:city":"Rodewisch",
    "sg:phone":"+49 3744/48061",
    "sg:postcode":"08228",
    "sg:province":"Sachsen",
    "wof:name":"Quo Vadis",
    "wof:placetype":"venue"
},
  "geometry": {"coordinates":[12.4156112671,50.5311012268],"type":"Point"}
}