{
  "type": "Feature",
  "properties": {
    "iso:country":"DE",
    "sg:address":"Austr. 28",
    "sg:city":"Oberriexingen",
    "sg:phone":"+49 7042/9480",
    "sg:postcode":"71739",
    "sg:province":"Baden-W\u00fcrttemberg",
    "wof:name":"Intek Gesellschaft F\u00fcr Moderne Innenbautechnik Mbh",
    "wof:placetype":"venue"
},
  "geometry": {"coordinates":[9.0336122513,48.9308662415],"type":"Point"}
}