{
  "type": "Feature",
  "properties": {
    "iso:country":"DE",
    "sg:address":"Hohenzaunstr. 13",
    "sg:city":"Teistungen",
    "sg:phone":"+49 36071/96502",
    "sg:postcode":"37339",
    "sg:province":"Th\u00fcringen",
    "wof:name":"Gerald Gatzemeier",
    "wof:placetype":"venue"
},
  "geometry": {"coordinates":[10.266125,51.47044],"type":"Point"}
}