{
  "type": "Feature",
  "properties": {
    "iso:country":"DE",
    "sg:address":"Pfarrstr. 1-3",
    "sg:city":"Stuttgart",
    "sg:phone":"+49 711/239360",
    "sg:postcode":"70182",
    "sg:province":"Baden-W\u00fcrttemberg",
    "wof:name":"Otra S\u00fcd Gmbh",
    "wof:placetype":"venue"
},
  "geometry": {"coordinates":[9.1814441681,48.7736129761],"type":"Point"}
}