{
  "type": "Feature",
  "properties": {
    "iso:country":"DE",
    "sg:address":"Ortstra\u00dfe 53",
    "sg:city":"Crispendorf",
    "sg:phone":"+49 3663/404344",
    "sg:postcode":"07924",
    "sg:province":"Th\u00fcringen",
    "wof:name":"Truckpromotion,us-showtrucks",
    "wof:placetype":"venue"
},
  "geometry": {"coordinates":[11.73492,50.592136],"type":"Point"}
}