{
  "type": "Feature",
  "properties": {
    "iso:country":"DE",
    "sg:address":"T\u00fcrrschmidtstr. 2",
    "sg:city":"Berlin",
    "sg:phone":"+49 30/5578493",
    "sg:postcode":"10317",
    "sg:province":"Berlin",
    "wof:name":"Hauskrankenpflege Ines P\u00fcttcher Gmbh",
    "wof:placetype":"venue"
},
  "geometry": {"coordinates":[13.47598,52.502621],"type":"Point"}
}