{
  "type": "Feature",
  "properties": {
    "iso:country":"DE",
    "sg:address":"Nikolaus-Otto-Str. 2",
    "sg:city":"Meerbusch",
    "sg:postcode":"40670",
    "sg:province":"Nordrhein-Westfalen",
    "wof:name":"K. Hager Gmbh",
    "wof:placetype":"venue"
},
  "geometry": {"coordinates":[6.6170730591,51.274646759],"type":"Point"}
}