{
  "type": "Feature",
  "properties": {
    "iso:country":"DE",
    "sg:address":"Blumenthaler Str. 20",
    "sg:city":"Schleiden",
    "sg:phone":"+49 2445/7933",
    "sg:postcode":"53937",
    "sg:province":"Nordrhein-Westfalen",
    "wof:name":"A. Hachenberg",
    "wof:placetype":"venue"
},
  "geometry": {"coordinates":[6.4728531837,50.5264167786],"type":"Point"}
}