{
  "type": "Feature",
  "properties": {
    "iso:country":"DE",
    "sg:address":"An der Stadtmauer 3",
    "sg:city":"Heidenheim",
    "sg:phone":"+49 7321/21932",
    "sg:postcode":"89522",
    "sg:province":"Baden-W\u00fcrttemberg",
    "wof:name":"Horst Braun",
    "wof:placetype":"venue"
},
  "geometry": {"coordinates":[10.1567678452,48.6765174866],"type":"Point"}
}