{
  "type": "Feature",
  "properties": {
    "iso:country":"DE",
    "sg:address":"Bookhagen 8",
    "sg:city":"Elmenhorst",
    "sg:phone":"+49 38327/305",
    "sg:postcode":"18510",
    "sg:province":"Mecklenburg-Vorpommern",
    "wof:name":"Th. Degler",
    "wof:placetype":"venue"
},
  "geometry": {"coordinates":[13.1081314087,54.2075233459],"type":"Point"}
}