{
  "type": "Feature",
  "properties": {
    "iso:country":"DE",
    "sg:address":"Pastor-Simon-Str. 16",
    "sg:city":"Koblenz",
    "sg:phone":"+49 2606/366",
    "sg:postcode":"56073",
    "sg:province":"Rheinland-Pfalz",
    "wof:name":"L\u00f6hr Gmbh Ger\u00fcstbau",
    "wof:placetype":"venue"
},
  "geometry": {"coordinates":[7.5420451164,50.322555542],"type":"Point"}
}