{
  "type": "Feature",
  "properties": {
    "iso:country":"DE",
    "sg:address":"Bahnhofstr. 55a",
    "sg:city":"Plettenberg",
    "sg:phone":"+49 2391/2615",
    "sg:postcode":"58840",
    "sg:province":"Nordrhein-Westfalen",
    "wof:name":"Alfred Cordes",
    "wof:placetype":"venue"
},
  "geometry": {"coordinates":[7.873237133,51.2215118408],"type":"Point"}
}