{
  "type": "Feature",
  "properties": {
    "iso:country":"DE",
    "sg:address":"Nibelungenstr. 39",
    "sg:city":"Lorsch",
    "sg:phone":"+49 6251/55411",
    "sg:postcode":"64653",
    "sg:province":"Hessen",
    "wof:name":"Am Kloster",
    "wof:placetype":"venue"
},
  "geometry": {"coordinates":[8.568392,49.654175],"type":"Point"}
}