{
  "type": "Feature",
  "properties": {
    "iso:country":"DE",
    "sg:address":"M\u00e4rkische Str. 1",
    "sg:city":"Kamen",
    "sg:phone":"+49 2307/40453",
    "sg:postcode":"59174",
    "sg:province":"Nordrhein-Westfalen",
    "wof:name":"Gastst\u00e4tte M. Olschonski",
    "wof:placetype":"venue"
},
  "geometry": {"coordinates":[7.7103881836,51.5775642395],"type":"Point"}
}