{
  "type": "Feature",
  "properties": {
    "iso:country":"DE",
    "sg:address":"Friedenstr. 44",
    "sg:city":"Ostheim",
    "sg:phone":"+49 9777/911311",
    "sg:postcode":"97645",
    "sg:province":"Bayern",
    "wof:name":"Uwe Trabert",
    "wof:placetype":"venue"
},
  "geometry": {"coordinates":[10.222816,50.460621],"type":"Point"}
}