{
  "type": "Feature",
  "properties": {
    "iso:country":"DE",
    "sg:address":"Bruchstr. 28",
    "sg:city":"Willich",
    "sg:phone":"+49 2154/80665",
    "sg:postcode":"47877",
    "sg:province":"Nordrhein-Westfalen",
    "wof:name":"Kamphausen",
    "wof:placetype":"venue"
},
  "geometry": {"coordinates":[6.464908,51.256138],"type":"Point"}
}