{
  "type": "Feature",
  "properties": {
    "iso:country":"DE",
    "sg:address":"Worringer Str. 30",
    "sg:city":"K\u00f6ln",
    "sg:phone":"+49 221/731926",
    "sg:postcode":"50668",
    "sg:province":"Nordrhein-Westfalen",
    "wof:name":"Kitchen House Co. Ltd.",
    "wof:placetype":"venue"
},
  "geometry": {"coordinates":[6.9690937996,50.9529838562],"type":"Point"}
}