{
  "type": "Feature",
  "properties": {
    "iso:country":"DE",
    "sg:address":"Teichstr. 47",
    "sg:city":"J\u00fclich",
    "sg:phone":"+49 2461/56661",
    "sg:postcode":"52428",
    "sg:province":"Nordrhein-Westfalen",
    "wof:name":"Th. Loevenich Masseur",
    "wof:placetype":"venue"
},
  "geometry": {"coordinates":[6.3562,50.897243],"type":"Point"}
}