{
  "type": "Feature",
  "properties": {
    "iso:country":"DE",
    "sg:address":"Hauptstr. 50",
    "sg:city":"Nennhausen",
    "sg:phone":"+49 33878/60475",
    "sg:postcode":"14715",
    "sg:province":"Brandenburg",
    "wof:name":"G\u00fcnter Klimpel Masseur",
    "wof:placetype":"venue"
},
  "geometry": {"coordinates":[12.497391,52.598183],"type":"Point"}
}