{
  "type": "Feature",
  "properties": {
    "iso:country":"DE",
    "sg:address":"Moorchaussee 34",
    "sg:city":"Wischhafen",
    "sg:phone":"+49 4770/7171",
    "sg:postcode":"21737",
    "sg:province":"Niedersachsen",
    "wof:name":"Heinrich A. Von Allw\u00f6rden",
    "wof:placetype":"venue"
},
  "geometry": {"coordinates":[9.312881,53.770069],"type":"Point"}
}