{
  "type": "Feature",
  "properties": {
    "iso:country":"DE",
    "sg:address":"Ev. Gemeindehaus",
    "sg:city":"Asendorf",
    "sg:phone":"+49 4253/362",
    "sg:postcode":"27330",
    "sg:province":"Niedersachsen",
    "wof:name":"Ev. \u00d6ffentliche Bibliothek",
    "wof:placetype":"venue"
},
  "geometry": {"coordinates":[9.004535,52.772572],"type":"Point"}
}