{
  "type": "Feature",
  "properties": {
    "iso:country":"DE",
    "sg:address":"Marienloher Str. 20",
    "sg:city":"Paderborn",
    "sg:phone":"+49 5254/940652",
    "sg:postcode":"33104",
    "sg:province":"Nordrhein-Westfalen",
    "wof:name":"Badgalerie Blome Gmbh",
    "wof:placetype":"venue"
},
  "geometry": {"coordinates":[8.7329101562,51.7431106567],"type":"Point"}
}