{
  "type": "Feature",
  "properties": {
    "iso:country":"DE",
    "sg:address":"Am Weilsberg 15",
    "sg:city":"Lindlar",
    "sg:phone":"+49 2266/459966",
    "sg:postcode":"51789",
    "sg:province":"Nordrhein-Westfalen",
    "wof:name":"Thomas Stolte",
    "wof:placetype":"venue"
},
  "geometry": {"coordinates":[7.3924818039,51.0254096985],"type":"Point"}
}