{
  "type": "Feature",
  "properties": {
    "iso:country":"DE",
    "sg:address":"Am Kronenschlatt 35a",
    "sg:city":"Ganderkesee",
    "sg:phone":"+49 4222/1801",
    "sg:postcode":"27777",
    "sg:province":"Niedersachsen",
    "wof:name":"Georg Sonntag",
    "wof:placetype":"venue"
},
  "geometry": {"coordinates":[8.518049,53.008457],"type":"Point"}
}