{
  "type": "Feature",
  "properties": {
    "iso:country":"DE",
    "sg:address":"Kart\u00e4usergasse 1",
    "sg:city":"N\u00fcrnberg",
    "sg:phone":"+49 911/13310",
    "sg:postcode":"90402",
    "sg:province":"Bayern",
    "wof:name":"Kunstp\u00e4dagogisches Zentrum I. Germ. Nationalmuseum",
    "wof:placetype":"venue"
},
  "geometry": {"coordinates":[11.075434,49.448784],"type":"Point"}
}