{
  "type": "Feature",
  "properties": {
    "iso:country":"DE",
    "sg:address":"Wehrgasse 1",
    "sg:city":"Bad Mergentheim",
    "sg:phone":"+49 7931/45418",
    "sg:postcode":"97980",
    "sg:province":"Baden-W\u00fcrttemberg",
    "wof:name":"Biohof Albert Retzbach",
    "wof:placetype":"venue"
},
  "geometry": {"coordinates":[9.7512,49.444469],"type":"Point"}
}