{
  "type": "Feature",
  "properties": {
    "iso:country":"DE",
    "sg:address":"Schulstr. 1",
    "sg:city":"K\u00fcnzell",
    "sg:phone":"+49 661/61742",
    "sg:postcode":"36093",
    "sg:province":"Hessen",
    "wof:name":"Katholisches Pfarramt Maria Hilf",
    "wof:placetype":"venue"
},
  "geometry": {"coordinates":[9.7031412125,50.5389213562],"type":"Point"}
}