{
  "type": "Feature",
  "properties": {
    "iso:country":"DE",
    "sg:address":"Zur Altenau 9",
    "sg:city":"Tauberbischofsheim",
    "sg:phone":"+49 9341/12708",
    "sg:postcode":"97941",
    "sg:province":"Baden-W\u00fcrttemberg",
    "wof:name":"Morris Fr\u00f6hlich",
    "wof:placetype":"venue"
},
  "geometry": {"coordinates":[9.6543159485,49.6346588135],"type":"Point"}
}