{
  "type": "Feature",
  "properties": {
    "iso:country":"DE",
    "sg:address":"Elly-Beinhorn-Str 4",
    "sg:city":"Eppelheim",
    "sg:phone":"+49 6221/768677",
    "sg:postcode":"69214",
    "sg:province":"Baden-W\u00fcrttemberg",
    "wof:name":"Software Tools & Technology Gmbh",
    "wof:placetype":"venue"
},
  "geometry": {"coordinates":[8.6324710846,49.4134941101],"type":"Point"}
}