{
  "type": "Feature",
  "properties": {
    "iso:country":"DE",
    "sg:address":"Wiesenweg 1",
    "sg:city":"Sch\u00f6newalde",
    "sg:phone":"+49 35362/523",
    "sg:postcode":"04916",
    "sg:province":"Brandenburg",
    "wof:name":"R. Rieger Anlageberater",
    "wof:placetype":"venue"
},
  "geometry": {"coordinates":[13.3486051559,51.8217315674],"type":"Point"}
}