{
  "type": "Feature",
  "properties": {
    "iso:country":"DE",
    "sg:address":"Herrnsheimer Str. 20",
    "sg:city":"Osthofen",
    "sg:phone":"+49 6242/99917",
    "sg:postcode":"67574",
    "sg:province":"Rheinland-Pfalz",
    "wof:name":"Erika Eller",
    "wof:placetype":"venue"
},
  "geometry": {"coordinates":[8.3255805969,49.6993980408],"type":"Point"}
}