{
  "type": "Feature",
  "properties": {
    "iso:country":"DE",
    "sg:address":"Domplatz 5",
    "sg:city":"Speyer",
    "sg:phone":"+49 6232/1091",
    "sg:postcode":"67346",
    "sg:province":"Rheinland-Pfalz",
    "wof:name":"Ev. Kirche Der Pfalz",
    "wof:placetype":"venue"
},
  "geometry": {"coordinates":[8.4420604706,49.3157157898],"type":"Point"}
}