{
  "type": "Feature",
  "properties": {
    "iso:country":"DE",
    "sg:address":"Dorotheenstr. 128",
    "sg:city":"Hamburg",
    "sg:phone":"+49 40/2701363",
    "sg:postcode":"22301",
    "sg:province":"Hamburg",
    "wof:name":"Mehmet Ari",
    "wof:placetype":"venue"
},
  "geometry": {"coordinates":[10.0051374435,53.5874557495],"type":"Point"}
}