{
  "type": "Feature",
  "properties": {
    "iso:country":"DE",
    "sg:address":"Kiefernweg 19",
    "sg:city":"Hemsbach",
    "sg:phone":"+49 6201/492029",
    "sg:postcode":"69502",
    "sg:province":"Baden-W\u00fcrttemberg",
    "wof:name":"Pro Hemsbach",
    "wof:placetype":"venue"
},
  "geometry": {"coordinates":[8.640183,49.595482],"type":"Point"}
}