{
  "type": "Feature",
  "properties": {
    "iso:country":"DE",
    "sg:address":"Am Schlo\u00dfberg 14",
    "sg:city":"Grettstadt",
    "sg:phone":"+49 9729/204",
    "sg:postcode":"97508",
    "sg:province":"Bayern",
    "wof:name":"Friedrich Scheuring",
    "wof:placetype":"venue"
},
  "geometry": {"coordinates":[10.3660526276,50.0009117126],"type":"Point"}
}