{
  "type": "Feature",
  "properties": {
    "iso:country":"DE",
    "sg:address":"Teckstr. 1",
    "sg:city":"N\u00fcrtingen",
    "sg:phone":"+49 7022/932430",
    "sg:postcode":"72622",
    "sg:province":"Baden-W\u00fcrttemberg",
    "wof:name":"Lothar Bauer Ingenieur",
    "wof:placetype":"venue"
},
  "geometry": {"coordinates":[9.34593,48.618309],"type":"Point"}
}