{
  "type": "Feature",
  "properties": {
    "iso:country":"DE",
    "sg:address":"Hauptstr. 132",
    "sg:city":"Weil am Rhein",
    "sg:phone":"+49 7621/71544",
    "sg:postcode":"79576",
    "sg:province":"Baden-W\u00fcrttemberg",
    "wof:name":"G. Dittes",
    "wof:placetype":"venue"
},
  "geometry": {"coordinates":[7.6303510666,47.5947189331],"type":"Point"}
}