{
  "type": "Feature",
  "properties": {
    "iso:country":"DE",
    "sg:address":"Dorfstr. 57",
    "sg:city":"Blankenhagen",
    "sg:phone":"+49 4938/201270",
    "sg:postcode":"18182",
    "sg:province":"Mecklenburg-Vorpommern",
    "wof:name":"Am Wallbach Gmbh & Co Kg Vogtshagen",
    "wof:placetype":"venue"
},
  "geometry": {"coordinates":[12.34104,54.175564],"type":"Point"}
}