{
  "type": "Feature",
  "properties": {
    "iso:country":"DE",
    "sg:address":"Bismarckstr. 32",
    "sg:city":"Bitterfeld",
    "sg:phone":"+49 3493/400063",
    "sg:postcode":"06749",
    "sg:province":"Sachsen-Anhalt",
    "wof:name":"Thuringia Versicherungs-ag",
    "wof:placetype":"venue"
},
  "geometry": {"coordinates":[12.3205814362,51.6195983887],"type":"Point"}
}