{
  "type": "Feature",
  "properties": {
    "iso:country":"DE",
    "sg:address":"Wildweg 14",
    "sg:city":"Erftstadt",
    "sg:phone":"+49 2235/71220",
    "sg:postcode":"50374",
    "sg:province":"Nordrhein-Westfalen",
    "wof:name":"Giesler",
    "wof:placetype":"venue"
},
  "geometry": {"coordinates":[6.775924,50.749363],"type":"Point"}
}