{
  "type": "Feature",
  "properties": {
    "iso:country":"DE",
    "sg:address":"M\u00f6nchenstr. 48",
    "sg:city":"J\u00fcterbog",
    "sg:phone":"+49 3372/439313",
    "sg:postcode":"14913",
    "sg:province":"Brandenburg",
    "wof:name":"Uwe Schlomach Anlageberater",
    "wof:placetype":"venue"
},
  "geometry": {"coordinates":[13.0762033463,51.9906539917],"type":"Point"}
}