{
  "type": "Feature",
  "properties": {
    "iso:country":"DE",
    "sg:address":"Ringstr. 7",
    "sg:city":"Kranzberg",
    "sg:phone":"+49 8166/68680",
    "sg:postcode":"85402",
    "sg:province":"Bayern",
    "wof:name":"Dr. J\u00f6rg Schaller Ingenieur",
    "wof:placetype":"venue"
},
  "geometry": {"coordinates":[11.609471,48.406425],"type":"Point"}
}