{
  "type": "Feature",
  "properties": {
    "iso:country":"DE",
    "sg:address":"Bahnhofstr. 17-19",
    "sg:city":"M\u00fchlheim",
    "sg:phone":"+49 6108/67421",
    "sg:postcode":"63165",
    "sg:province":"Hessen",
    "wof:name":"Windm\u00fchle Naturkost",
    "wof:placetype":"venue"
},
  "geometry": {"coordinates":[8.8336858749,50.1237678528],"type":"Point"}
}