{
  "type": "Feature",
  "properties": {
    "iso:country":"DE",
    "sg:address":"Dr.-Martin-Luther-Str. 69",
    "sg:city":"Sch\u00f6nebeck",
    "sg:phone":"+49 3928/69857",
    "sg:postcode":"39218",
    "sg:province":"Sachsen-Anhalt",
    "wof:name":"Karl-heinz Preu\u00df",
    "wof:placetype":"venue"
},
  "geometry": {"coordinates":[11.7296104431,52.0141944885],"type":"Point"}
}