{
  "type": "Feature",
  "properties": {
    "iso:country":"DE",
    "sg:address":"Bernstein 1",
    "sg:city":"Sulz",
    "sg:phone":"+49 7454/8314",
    "sg:postcode":"72172",
    "sg:province":"Baden-W\u00fcrttemberg",
    "wof:name":"Agnes Kewitz Pension",
    "wof:placetype":"venue"
},
  "geometry": {"coordinates":[8.7233543396,48.3467330933],"type":"Point"}
}