{
  "type": "Feature",
  "properties": {
    "iso:country":"DE",
    "sg:address":"Gro\u00dfe Friedberger Str. 32",
    "sg:city":"Frankfurt",
    "sg:phone":"+49 69/285171",
    "sg:postcode":"60313",
    "sg:province":"Hessen",
    "wof:name":"Das Spielzimmer H. Und C. Wiechert Gmbh",
    "wof:placetype":"venue"
},
  "geometry": {"coordinates":[8.6863641739,50.1160736084],"type":"Point"}
}