{
  "type": "Feature",
  "properties": {
    "iso:country":"DE",
    "sg:address":"Rathausplatz 13",
    "sg:city":"Blankenheim",
    "sg:phone":"+49 2449/1784",
    "sg:postcode":"53945",
    "sg:province":"Nordrhein-Westfalen",
    "wof:name":"Musikhaus Elke Und Jochen",
    "wof:placetype":"venue"
},
  "geometry": {"coordinates":[6.650976181,50.436416626],"type":"Point"}
}