{
  "type": "Feature",
  "properties": {
    "iso:country":"DE",
    "sg:address":"Darmst\u00e4dter Str. 2",
    "sg:city":"Zwingenberg",
    "sg:phone":"+49 4962/5171238",
    "sg:postcode":"64673",
    "sg:province":"Hessen",
    "wof:name":"Volksbank Bergstr. Eg",
    "wof:placetype":"venue"
},
  "geometry": {"coordinates":[8.612755,49.724216],"type":"Point"}
}