{
  "type": "Feature",
  "properties": {
    "iso:country":"DE",
    "sg:address":"Kreuzkamp 12",
    "sg:city":"Sassenburg",
    "sg:postcode":"38524",
    "sg:province":"Niedersachsen",
    "wof:name":"Maschinenring Gifhorn E. V.",
    "wof:placetype":"venue"
},
  "geometry": {"coordinates":[10.621864,52.495491],"type":"Point"}
}