{
  "type": "Feature",
  "properties": {
    "iso:country":"DE",
    "sg:address":"Leopoldstr. 1",
    "sg:city":"Hockenheim",
    "sg:phone":"+49 6205/16405",
    "sg:postcode":"68766",
    "sg:province":"Baden-W\u00fcrttemberg",
    "wof:name":"Raiku",
    "wof:placetype":"venue"
},
  "geometry": {"coordinates":[8.550614,49.316811],"type":"Point"}
}