{
  "type": "Feature",
  "properties": {
    "iso:country":"DE",
    "sg:address":"Solitudestr. 7-17",
    "sg:city":"Eislingen",
    "sg:postcode":"73054",
    "sg:province":"Baden-W\u00fcrttemberg",
    "wof:name":"Frischbeton Eislingen Gmbh",
    "wof:placetype":"venue"
},
  "geometry": {"coordinates":[9.689324,48.698376],"type":"Point"}
}