{
  "type": "Feature",
  "properties": {
    "iso:country":"DE",
    "sg:address":"Alter Weg 19",
    "sg:city":"Rodgau",
    "sg:postcode":"63110",
    "sg:province":"Hessen",
    "wof:name":"Trotex Ges. F. Texter- Fassung Und Textverarb. Mbh",
    "wof:placetype":"venue"
},
  "geometry": {"coordinates":[8.8802165985,50.0284385681],"type":"Point"}
}