{
  "type": "Feature",
  "properties": {
    "iso:country":"DE",
    "sg:address":"Spangerstr. 4",
    "sg:city":"D\u00fcsseldorf",
    "sg:phone":"+49 211/998020",
    "sg:postcode":"40599",
    "sg:province":"Nordrhein-Westfalen",
    "wof:name":"Kopa Vereinigte Papier- Und Verpackungs- Gmbh & Co. Kg",
    "wof:placetype":"venue"
},
  "geometry": {"coordinates":[6.8634500504,51.1799354553],"type":"Point"}
}