{
  "type": "Feature",
  "properties": {
    "iso:country":"DE",
    "sg:address":"Auf der H\u00f6he 3 b",
    "sg:city":"Herford",
    "sg:phone":"+49 5221/930940",
    "sg:postcode":"32051",
    "sg:province":"Nordrhein-Westfalen",
    "wof:name":"Marianne Br\u00fcnger-welzel Architektin",
    "wof:placetype":"venue"
},
  "geometry": {"coordinates":[8.62506,52.125637],"type":"Point"}
}