{
  "type": "Feature",
  "properties": {
    "iso:country":"DE",
    "sg:address":"Bergstr. 15",
    "sg:city":"W\u00f6rth",
    "sg:phone":"+49 9372/98850",
    "sg:postcode":"63939",
    "sg:province":"Bayern",
    "wof:name":"Arnheiter Betonsteinwerke Gmbh",
    "wof:placetype":"venue"
},
  "geometry": {"coordinates":[11.90348,48.246964],"type":"Point"}
}