{
  "type": "Feature",
  "properties": {
    "iso:country":"DE",
    "sg:address":"M\u00fchlgrabenstr. 17",
    "sg:city":"Wallenfels",
    "sg:phone":"+49 9262/285",
    "sg:postcode":"96346",
    "sg:province":"Bayern",
    "wof:name":"Fritz K\u00f6hlmann",
    "wof:placetype":"venue"
},
  "geometry": {"coordinates":[11.47517,50.266689],"type":"Point"}
}