{
  "type": "Feature",
  "properties": {
    "iso:country":"DE",
    "sg:city":"Heppenheim",
    "sg:phone":"+49 6252/68288",
    "sg:postcode":"64646",
    "sg:province":"Hessen",
    "wof:name":"Leonardo Da Vinci Eiscafe",
    "wof:placetype":"venue"
},
  "geometry": {"coordinates":[8.65968,49.646488],"type":"Point"}
}