{
  "type": "Feature",
  "properties": {
    "iso:country":"DE",
    "sg:address":"Hildebrandtstr. 4-24",
    "sg:city":"D\u00fcsseldorf",
    "sg:phone":"+49 211/310910",
    "sg:postcode":"40215",
    "sg:province":"Nordrhein-Westfalen",
    "wof:name":"Ingrid Rennen Gmbh",
    "wof:placetype":"venue"
},
  "geometry": {"coordinates":[6.785063,51.210789],"type":"Point"}
}