{
  "type": "Feature",
  "properties": {
    "iso:country":"DE",
    "sg:address":"Bayreuther Str. 10",
    "sg:city":"Marktredwitz",
    "sg:phone":"+49 9231/81077",
    "sg:postcode":"95615",
    "sg:province":"Bayern",
    "wof:name":"B\u00e4ko-marktredewitz Eg",
    "wof:placetype":"venue"
},
  "geometry": {"coordinates":[12.0777568817,50.0064239502],"type":"Point"}
}