{
  "type": "Feature",
  "properties": {
    "iso:country":"DE",
    "sg:address":"Hermanstr. 5",
    "sg:city":"Augsburg",
    "sg:phone":"+49 821/38007",
    "sg:postcode":"86150",
    "sg:province":"Bayern",
    "wof:name":"Benedikt Probst Rechtsanwalt",
    "wof:placetype":"venue"
},
  "geometry": {"coordinates":[10.8936319351,48.3644332886],"type":"Point"}
}