{
  "type": "Feature",
  "properties": {
    "iso:country":"DE",
    "sg:address":"Am Zedernholz 4",
    "sg:city":"Frankfurt",
    "sg:phone":"+49 69/502646",
    "sg:postcode":"60437",
    "sg:province":"Hessen",
    "wof:name":"Transpo-rent Gmbh",
    "wof:placetype":"venue"
},
  "geometry": {"coordinates":[8.6526079178,50.1854362488],"type":"Point"}
}