{
  "type": "Feature",
  "properties": {
    "iso:country":"DE",
    "sg:address":"Eschborner Landstr. 130-132",
    "sg:city":"Frankfurt",
    "sg:phone":"+49 69/79290",
    "sg:postcode":"60489",
    "sg:province":"Hessen",
    "wof:name":"Wayss & Freytag Schl\u00fcsselfertigbau Ag",
    "wof:placetype":"venue"
},
  "geometry": {"coordinates":[8.596026,50.129078],"type":"Point"}
}