{
  "type": "Feature",
  "properties": {
    "iso:country":"DE",
    "sg:address":"Apenrader Str. 22",
    "sg:city":"Flensburg",
    "sg:postcode":"24939",
    "sg:province":"Schleswig-Holstein",
    "wof:name":"Aktiv Bus Flensburg Gmbh",
    "wof:placetype":"venue"
},
  "geometry": {"coordinates":[9.4246253967,54.8021430969],"type":"Point"}
}