{
  "type": "Feature",
  "properties": {
    "iso:country":"DE",
    "sg:address":"Heinrich-Horten-Str. 50",
    "sg:city":"Kempen",
    "sg:phone":"+49 2152/14960",
    "sg:postcode":"47906",
    "sg:province":"Nordrhein-Westfalen",
    "wof:name":"Stadtwerke Kempen Gmbh",
    "wof:placetype":"venue"
},
  "geometry": {"coordinates":[6.439691,51.37114],"type":"Point"}
}