{
  "type": "Feature",
  "properties": {
    "iso:country":"DE",
    "sg:address":"B\u00fclowstr. 93",
    "sg:city":"Datteln",
    "sg:phone":"+49 2363/32383",
    "sg:postcode":"45711",
    "sg:province":"Nordrhein-Westfalen",
    "wof:name":"Fitness Moving Lady Van Almsick",
    "wof:placetype":"venue"
},
  "geometry": {"coordinates":[7.3471498489,51.6650657654],"type":"Point"}
}