{
  "type": "Feature",
  "properties": {
    "iso:country":"DE",
    "sg:address":"Heimhuder Str. 39 a",
    "sg:city":"Hamburg",
    "sg:phone":"+49 40/451651",
    "sg:postcode":"20148",
    "sg:province":"Hamburg",
    "wof:name":"Dr. Med. Peter Wiedemann",
    "wof:placetype":"venue"
},
  "geometry": {"coordinates":[9.992521286,53.5662956238],"type":"Point"}
}