{
  "type": "Feature",
  "properties": {
    "iso:country":"DE",
    "sg:address":"Bahnhofstr. 9",
    "sg:city":"Pfeffenhausen",
    "sg:phone":"+49 8782/304",
    "sg:postcode":"84076",
    "sg:province":"Bayern",
    "wof:name":"Niedermeier Textil Und Mode Inh. Friedl",
    "wof:placetype":"venue"
},
  "geometry": {"coordinates":[11.9657449722,48.6653175354],"type":"Point"}
}