{
  "type": "Feature",
  "properties": {
    "iso:country":"DE",
    "sg:address":"Mengeder Schulstr. 23",
    "sg:city":"Dortmund",
    "sg:phone":"+49 231/335429",
    "sg:postcode":"44359",
    "sg:province":"Nordrhein-Westfalen",
    "wof:name":"Vedder Gmbh",
    "wof:placetype":"venue"
},
  "geometry": {"coordinates":[7.389988,51.570881],"type":"Point"}
}