{
  "type": "Feature",
  "properties": {
    "iso:country":"DE",
    "sg:address":"Eichenweg 2a",
    "sg:city":"Bentwisch",
    "sg:phone":"+49 3877/79055",
    "sg:postcode":"19322",
    "sg:province":"Brandenburg",
    "wof:name":"Scheuten",
    "wof:placetype":"venue"
},
  "geometry": {"coordinates":[11.733775,53.040001],"type":"Point"}
}