{
  "type": "Feature",
  "properties": {
    "iso:country":"DE",
    "sg:address":"Grabenstr. 9",
    "sg:city":"Heidenheim",
    "sg:phone":"+49 4973/2135880",
    "sg:postcode":"89597",
    "sg:province":"Baden-W\u00fcrttemberg",
    "wof:name":"Landesgirokasse",
    "wof:placetype":"venue"
},
  "geometry": {"coordinates":[9.64461,48.23555],"type":"Point"}
}