{
  "type": "Feature",
  "properties": {
    "iso:country":"DE",
    "sg:address":"Burgplatz 8",
    "sg:city":"Backnang",
    "sg:phone":"+49 7191/980088",
    "sg:postcode":"71522",
    "sg:province":"Baden-W\u00fcrttemberg",
    "wof:name":"Kath. Sozialstation",
    "wof:placetype":"venue"
},
  "geometry": {"coordinates":[9.434188,48.945023],"type":"Point"}
}