{
  "type": "Feature",
  "properties": {
    "iso:country":"DE",
    "sg:address":"Bennostr. 16",
    "sg:city":"Schopfloch",
    "sg:phone":"+49 9857/225",
    "sg:postcode":"91626",
    "sg:province":"Bayern",
    "wof:name":"Friedrich Eduard Grimm",
    "wof:placetype":"venue"
},
  "geometry": {"coordinates":[10.30718,49.123863],"type":"Point"}
}