{
  "type": "Feature",
  "properties": {
    "iso:country":"DE",
    "sg:address":"Unterer Markt 10",
    "sg:city":"Altdorf",
    "sg:phone":"+49 9187/2520",
    "sg:postcode":"90518",
    "sg:province":"Bayern",
    "wof:name":"Raiffeisenbank Altdorf-feucht Eg",
    "wof:placetype":"venue"
},
  "geometry": {"coordinates":[11.38631,49.393188],"type":"Point"}
}