{
  "type": "Feature",
  "properties": {
    "iso:country":"DE",
    "sg:address":"Zum Achimer Bahnhof 29",
    "sg:city":"Achim",
    "sg:phone":"+49 4202/2033",
    "sg:postcode":"28832",
    "sg:province":"Niedersachsen",
    "wof:name":"E. Beermann",
    "wof:placetype":"venue"
},
  "geometry": {"coordinates":[9.032638,53.013634],"type":"Point"}
}