{
  "type": "Feature",
  "properties": {
    "iso:country":"DE",
    "sg:address":"Mosenthinstr. 10",
    "sg:city":"Leipzig",
    "sg:phone":"+49 341/585800",
    "sg:postcode":"04129",
    "sg:province":"Sachsen",
    "wof:name":"Still Gmbh",
    "wof:placetype":"venue"
},
  "geometry": {"coordinates":[12.386677742,51.3725891113],"type":"Point"}
}