{
  "type": "Feature",
  "properties": {
    "iso:country":"DE",
    "sg:address":"Bahnhofstr. 14",
    "sg:city":"Heddesheim",
    "sg:phone":"+49 6203/41646",
    "sg:postcode":"68542",
    "sg:province":"Baden-W\u00fcrttemberg",
    "wof:name":"Gastst\u00e4tte Luftschiff",
    "wof:placetype":"venue"
},
  "geometry": {"coordinates":[8.5969896317,49.5052490234],"type":"Point"}
}