{
  "type": "Feature",
  "properties": {
    "iso:country":"DE",
    "sg:address":"Borselstr. 7",
    "sg:city":"Hamburg",
    "sg:phone":"+49 40/394827",
    "sg:postcode":"22765",
    "sg:province":"Hamburg",
    "wof:name":"Rainer Steffen Architekt",
    "wof:placetype":"venue"
},
  "geometry": {"coordinates":[9.925526,53.556122],"type":"Point"}
}