{
  "type": "Feature",
  "properties": {
    "iso:country":"DE",
    "sg:address":"Schlesischer Ring 5 A",
    "sg:city":"Gelsenkirchen",
    "sg:phone":"+49 209/33234",
    "sg:postcode":"45894",
    "sg:province":"Nordrhein-Westfalen",
    "wof:name":"Auto Wilmsen Gmbh",
    "wof:placetype":"venue"
},
  "geometry": {"coordinates":[7.042103,51.581402],"type":"Point"}
}