{
  "type": "Feature",
  "properties": {
    "iso:country":"DE",
    "sg:address":"Eisenbahnstr. 6",
    "sg:city":"Ludwigsburg",
    "sg:phone":"+49 7141/1470",
    "sg:postcode":"71636",
    "sg:province":"Baden-W\u00fcrttemberg",
    "wof:name":"H\u00fcndersdorff Gmbh",
    "wof:placetype":"venue"
},
  "geometry": {"coordinates":[9.187905,48.888447],"type":"Point"}
}