{
  "type": "Feature",
  "properties": {
    "iso:country":"DE",
    "sg:address":"Aiblinger Str. 3",
    "sg:city":"Bad Feilnbach",
    "sg:phone":"+49 8066/412",
    "sg:postcode":"83075",
    "sg:province":"Bayern",
    "wof:name":"G. Kurz",
    "wof:placetype":"venue"
},
  "geometry": {"coordinates":[12.055347,47.761993],"type":"Point"}
}