{
  "type": "Feature",
  "properties": {
    "iso:country":"DE",
    "sg:address":"Drei Linden 7",
    "sg:city":"Markranst\u00e4dt",
    "sg:postcode":"04420",
    "sg:province":"Sachsen",
    "wof:name":"Richard Kr\u00e4tzer Gmbh",
    "wof:placetype":"venue"
},
  "geometry": {"coordinates":[12.2450704575,51.2937431335],"type":"Point"}
}