{
  "type": "Feature",
  "properties": {
    "iso:country":"DE",
    "sg:address":"Birlenbacher Str. 1",
    "sg:city":"Fachingen",
    "sg:phone":"+49 6432/81383",
    "sg:postcode":"65626",
    "sg:province":"Rheinland-Pfalz",
    "wof:name":"K. Und G. Wolf",
    "wof:placetype":"venue"
},
  "geometry": {"coordinates":[7.994327,50.362148],"type":"Point"}
}