{
  "type": "Feature",
  "properties": {
    "iso:country":"DE",
    "sg:address":"Gartenstr. 13",
    "sg:city":"Landau",
    "sg:phone":"+49 6341/63576",
    "sg:postcode":"76829",
    "sg:province":"Rheinland-Pfalz",
    "wof:name":"Kurt Hochd\u00f6rffer Weinanbau",
    "wof:placetype":"venue"
},
  "geometry": {"coordinates":[8.1070127487,49.2236633301],"type":"Point"}
}