{
  "type": "Feature",
  "properties": {
    "iso:country":"DE",
    "sg:address":"Boltenhagener Str. 8a",
    "sg:city":"Dresden",
    "sg:phone":"+49 351/8804168",
    "sg:postcode":"01109",
    "sg:province":"Sachsen",
    "wof:name":"Wolfgang Porstendorfer- Dachdeckermeister E. K.",
    "wof:placetype":"venue"
},
  "geometry": {"coordinates":[13.7854633331,51.1160736084],"type":"Point"}
}