{
  "type": "Feature",
  "properties": {
    "iso:country":"DE",
    "sg:address":"Breslauer Str. 5",
    "sg:city":"Schleiden",
    "sg:phone":"+49 2444/2408",
    "sg:postcode":"53937",
    "sg:province":"Nordrhein-Westfalen",
    "wof:name":"Anna Jenniches",
    "wof:placetype":"venue"
},
  "geometry": {"coordinates":[6.4977841377,50.5651245117],"type":"Point"}
}