{
  "type": "Feature",
  "properties": {
    "iso:country":"DE",
    "sg:address":"Vogelsanger Str. 273",
    "sg:city":"K\u00f6ln",
    "sg:phone":"+49 221/9544260",
    "sg:postcode":"50825",
    "sg:province":"Nordrhein-Westfalen",
    "wof:name":"Hotel Regina Garni",
    "wof:placetype":"venue"
},
  "geometry": {"coordinates":[6.9015479088,50.9520225525],"type":"Point"}
}