{
  "type": "Feature",
  "properties": {
    "iso:country":"DE",
    "sg:address":"Walther-Rathenau-Str. 38",
    "sg:city":"Herborn",
    "sg:postcode":"35745",
    "sg:province":"Hessen",
    "wof:name":"Thomas Janssen E. K.",
    "wof:placetype":"venue"
},
  "geometry": {"coordinates":[8.3074951172,50.682559967],"type":"Point"}
}