{
  "type": "Feature",
  "properties": {
    "iso:country":"DE",
    "sg:address":"Wilhelm-Bockelmann-Str. 5",
    "sg:city":"Munster",
    "sg:phone":"+49 5192/3191",
    "sg:postcode":"29633",
    "sg:province":"Niedersachsen",
    "wof:name":"E. Siegfried Irion Rechtsanwalt Und Notar",
    "wof:placetype":"venue"
},
  "geometry": {"coordinates":[10.0892114639,52.986000061],"type":"Point"}
}