{
  "type": "Feature",
  "properties": {
    "iso:country":"DE",
    "sg:address":"Florianstr. 1::",
    "sg:city":"Dortmund",
    "sg:phone":"+49 4923/11082",
    "sg:postcode":"44139",
    "sg:province":"Nordrhein-Westfalen",
    "wof:name":"Westfaelische Hypothekenbank Aktiengesellschaft",
    "wof:placetype":"venue"
},
  "geometry": {"coordinates":[7.47624,51.497795],"type":"Point"}
}