{
  "type": "Feature",
  "properties": {
    "iso:country":"DE",
    "sg:address":"Austr. 32",
    "sg:city":"Dettingen",
    "sg:phone":"+49 7021/98490",
    "sg:postcode":"73265",
    "sg:province":"Baden-W\u00fcrttemberg",
    "wof:name":"Hotel-restaurant R\u00f6\u00dfle",
    "wof:placetype":"venue"
},
  "geometry": {"coordinates":[8.6351690292,48.4189567566],"type":"Point"}
}