{
  "type": "Feature",
  "properties": {
    "iso:country":"DE",
    "sg:address":"Dorfstr. 4",
    "sg:city":"Kletzke",
    "sg:phone":"+49 38796/40508",
    "sg:postcode":"19336",
    "sg:province":"Brandenburg",
    "wof:name":"H.-j. Br\u00fctt",
    "wof:placetype":"venue"
},
  "geometry": {"coordinates":[12.0636768341,53.0006484985],"type":"Point"}
}