{
  "type": "Feature",
  "properties": {
    "iso:country":"DE",
    "sg:address":"Mittenwalder Str. 16",
    "sg:city":"Motzen",
    "sg:postcode":"15741",
    "sg:province":"Brandenburg",
    "wof:name":"Eff-eff Baudienst- Leistungs Gmbh",
    "wof:placetype":"venue"
},
  "geometry": {"coordinates":[13.583871,52.208355],"type":"Point"}
}