{
  "type": "Feature",
  "properties": {
    "iso:country":"DE",
    "sg:address":"Feldstr. 37",
    "sg:city":"Rees",
    "sg:phone":"+49 2850/7121",
    "sg:postcode":"46459",
    "sg:province":"Nordrhein-Westfalen",
    "wof:name":"Heinz Terlinde",
    "wof:placetype":"venue"
},
  "geometry": {"coordinates":[6.465163,51.773132],"type":"Point"}
}