{
  "type": "Feature",
  "properties": {
    "iso:country":"DE",
    "sg:address":"Roermonder Str. 124",
    "sg:city":"M\u00f6nchengladbach",
    "sg:phone":"+49 2161/88841",
    "sg:postcode":"41068",
    "sg:province":"Nordrhein-Westfalen",
    "wof:name":"H.t. Brouns",
    "wof:placetype":"venue"
},
  "geometry": {"coordinates":[6.4106240273,51.1979637146],"type":"Point"}
}