{
  "type": "Feature",
  "properties": {
    "iso:country":"DE",
    "sg:address":"Frauenstr. 9",
    "sg:city":"Anklam",
    "sg:phone":"+49 3971/245980",
    "sg:postcode":"17389",
    "sg:province":"Mecklenburg-Vorpommern",
    "wof:name":"H. Pobanz",
    "wof:placetype":"venue"
},
  "geometry": {"coordinates":[13.6858072281,53.8564071655],"type":"Point"}
}