{
  "type": "Feature",
  "properties": {
    "iso:country":"DE",
    "sg:address":"An den Geestbergen 14",
    "sg:city":"Buxtehude",
    "sg:phone":"+49 4161/63200",
    "sg:postcode":"21614",
    "sg:province":"Niedersachsen",
    "wof:name":"P\u00f6hland Transporte Gmbh & Co. Kg",
    "wof:placetype":"venue"
},
  "geometry": {"coordinates":[9.7144603729,53.4613685608],"type":"Point"}
}