{
  "type": "Feature",
  "properties": {
    "iso:country":"DE",
    "sg:address":"Frankfurter Str. 23",
    "sg:city":"Gedern",
    "sg:phone":"+49 6045/1302",
    "sg:postcode":"63688",
    "sg:province":"Hessen",
    "wof:name":"D. Oberheim",
    "wof:placetype":"venue"
},
  "geometry": {"coordinates":[9.1966772079,50.4219856262],"type":"Point"}
}