{
  "type": "Feature",
  "properties": {
    "iso:country":"DE",
    "sg:address":"Ringstr. 3",
    "sg:city":"Weiden",
    "sg:phone":"+49 961/7880",
    "sg:postcode":"92637",
    "sg:province":"Bayern",
    "wof:name":"Heinz Heindl",
    "wof:placetype":"venue"
},
  "geometry": {"coordinates":[12.1587781906,49.6749153137],"type":"Point"}
}