{
  "type": "Feature",
  "properties": {
    "iso:country":"DE",
    "sg:address":"H\u00f6b\u00e4ckerweg 7",
    "sg:city":"Schl\u00fcchtern",
    "sg:phone":"+49 6661/3089",
    "sg:postcode":"36381",
    "sg:province":"Hessen",
    "wof:name":"Dwa-medizintechnik Inh. Ilse Aderhold",
    "wof:placetype":"venue"
},
  "geometry": {"coordinates":[9.519551,50.342022],"type":"Point"}
}