{
  "type": "Feature",
  "properties": {
    "iso:country":"DE",
    "sg:address":"Marienstr. 5a",
    "sg:city":"Bestwig",
    "sg:phone":"+49 2904/97070",
    "sg:postcode":"59909",
    "sg:province":"Nordrhein-Westfalen",
    "wof:name":"Josef Middel B\u00fcrom\u00f6belfabrik Gmbh & Co. Kg",
    "wof:placetype":"venue"
},
  "geometry": {"coordinates":[8.402541,51.359024],"type":"Point"}
}