{
  "type": "Feature",
  "properties": {
    "iso:country":"DE",
    "sg:address":"Oberste Weide",
    "sg:city":"Greifenstein",
    "sg:postcode":"35753",
    "sg:province":"Hessen",
    "wof:name":"Fusch'sche Tongrube",
    "wof:placetype":"venue"
},
  "geometry": {"coordinates":[8.2907037735,50.6226882935],"type":"Point"}
}