{
  "type": "Feature",
  "properties": {
    "iso:country":"DE",
    "sg:address":"Sturzstr. 5",
    "sg:city":"Heilbronn",
    "sg:phone":"+49 7131/42604",
    "sg:postcode":"74080",
    "sg:province":"Baden-W\u00fcrttemberg",
    "wof:name":"G\u00fcnter Krach",
    "wof:placetype":"venue"
},
  "geometry": {"coordinates":[9.187707,49.14323],"type":"Point"}
}