{
  "type": "Feature",
  "properties": {
    "iso:country":"DE",
    "sg:address":"Am Heyerberg 9",
    "sg:city":"Koblenz",
    "sg:phone":"+49 261/47744",
    "sg:postcode":"56072",
    "sg:province":"Rheinland-Pfalz",
    "wof:name":"Bautec Hermann Liesenfeld",
    "wof:placetype":"venue"
},
  "geometry": {"coordinates":[7.5463051796,50.3452224731],"type":"Point"}
}