{
  "type": "Feature",
  "properties": {
    "iso:country":"DE",
    "sg:address":"Annahofstr. 1",
    "sg:city":"Regensburg",
    "sg:phone":"+49 941/36588",
    "sg:postcode":"93049",
    "sg:province":"Bayern",
    "wof:name":"Dr. Med. Franz Xaver Schmid",
    "wof:placetype":"venue"
},
  "geometry": {"coordinates":[12.0441198349,49.0132598877],"type":"Point"}
}