{
  "type": "Feature",
  "properties": {
    "iso:country":"DE",
    "sg:address":"Hauptstr. 33",
    "sg:city":"Beilngries",
    "sg:phone":"+49 8461/223",
    "sg:postcode":"92339",
    "sg:province":"Bayern",
    "wof:name":"G\u00fcnther Lindner Notar",
    "wof:placetype":"venue"
},
  "geometry": {"coordinates":[11.473367691,49.0353317261],"type":"Point"}
}