{
  "type": "Feature",
  "properties": {
    "iso:country":"DE",
    "sg:address":"Feringastr. 6",
    "sg:city":"Unterf\u00f6hring",
    "sg:postcode":"85774",
    "sg:province":"Bayern",
    "wof:name":"Wombat Gastst\u00e4tten- Betriebs Gmbh",
    "wof:placetype":"venue"
},
  "geometry": {"coordinates":[11.6332349777,48.1788024902],"type":"Point"}
}