{
  "type": "Feature",
  "properties": {
    "iso:country":"DE",
    "sg:address":"Kapellenweg 115",
    "sg:city":"Schermbeck",
    "sg:phone":"+49 2853/2494",
    "sg:postcode":"46514",
    "sg:province":"Nordrhein-Westfalen",
    "wof:name":"Gardiner",
    "wof:placetype":"venue"
},
  "geometry": {"coordinates":[6.880223,51.682407],"type":"Point"}
}