{
  "type": "Feature",
  "properties": {
    "iso:country":"DE",
    "sg:address":"Gartenweg 5",
    "sg:city":"Pemfling",
    "sg:phone":"+49 9975/500",
    "sg:postcode":"93482",
    "sg:province":"Bayern",
    "wof:name":"Jakob Paulus",
    "wof:placetype":"venue"
},
  "geometry": {"coordinates":[12.61105,49.311676],"type":"Point"}
}