{
  "type": "Feature",
  "properties": {
    "iso:country":"DE",
    "sg:address":"Mozartstr. 18",
    "sg:city":"Unna",
    "sg:phone":"+49 180 1 002880",
    "sg:postcode":"59423",
    "sg:province":"Nordrhein-Westfalen",
    "wof:name":"Diakoniestation Unna",
    "wof:placetype":"venue"
},
  "geometry": {"coordinates":[7.685323,51.537689],"type":"Point"}
}