{
  "type": "Feature",
  "properties": {
    "iso:country":"DE",
    "sg:address":"Cortendorfer Str. 37",
    "sg:city":"Coburg",
    "sg:phone":"+49 9561/861000",
    "sg:postcode":"96450",
    "sg:province":"Bayern",
    "wof:name":"Eki-wohnungsbau-gmbh",
    "wof:placetype":"venue"
},
  "geometry": {"coordinates":[10.9902610779,50.2724266052],"type":"Point"}
}