{
  "type": "Feature",
  "properties": {
    "iso:country":"DE",
    "sg:address":"Berliner Str. 223",
    "sg:city":"Offenbach",
    "sg:phone":"+49 69/810814",
    "sg:postcode":"63065",
    "sg:province":"Hessen",
    "wof:name":"Wiedemann Und Reompke Rechtsanw\u00e4lte",
    "wof:placetype":"venue"
},
  "geometry": {"coordinates":[8.7665548325,50.1052932739],"type":"Point"}
}