{
  "type": "Feature",
  "properties": {
    "iso:country":"DE",
    "sg:address":"Nibelungenstr. 25",
    "sg:city":"Bad Griesbach",
    "sg:phone":"+49 8532/3166",
    "sg:postcode":"94086",
    "sg:province":"Bayern",
    "wof:name":"Max Huber Architekt",
    "wof:placetype":"venue"
},
  "geometry": {"coordinates":[13.192784,48.438797],"type":"Point"}
}