{
  "type": "Feature",
  "properties": {
    "iso:country":"DE",
    "sg:address":"Gartenstr. 44 A",
    "sg:city":"Seesen",
    "sg:phone":"+49 5381/2586",
    "sg:postcode":"38723",
    "sg:province":"Niedersachsen",
    "wof:name":"Rudolf Zimmerman Kunstmaler",
    "wof:placetype":"venue"
},
  "geometry": {"coordinates":[10.168272,51.886585],"type":"Point"}
}