{
  "type": "Feature",
  "properties": {
    "iso:country":"DE",
    "sg:address":"G\u00fcnter-Eich-Str. 7",
    "sg:city":"M\u00fcnchen",
    "sg:phone":"+49 89/93930646",
    "sg:postcode":"81927",
    "sg:province":"Bayern",
    "wof:name":"Christine Gitschmann",
    "wof:placetype":"venue"
},
  "geometry": {"coordinates":[11.635358,48.153751],"type":"Point"}
}