{
  "type": "Feature",
  "properties": {
    "iso:country":"DE",
    "sg:address":"Masurenweg 9",
    "sg:city":"Borgholzhausen",
    "sg:phone":"+49 5425/930103",
    "sg:postcode":"33829",
    "sg:province":"Nordrhein-Westfalen",
    "wof:name":"Micom Mikroprozessor- Und Computersysteme Gmbh",
    "wof:placetype":"venue"
},
  "geometry": {"coordinates":[8.29159832,52.0970420837],"type":"Point"}
}