{
  "type": "Feature",
  "properties": {
    "iso:country":"DE",
    "sg:address":"Domselwitzer G\u00e4\u00dfchen 7",
    "sg:city":"Lommatzsch",
    "sg:phone":"+49 35241/51046",
    "sg:postcode":"01623",
    "sg:province":"Sachsen",
    "wof:name":"R. Und J\u00fcrgen Weber",
    "wof:placetype":"venue"
},
  "geometry": {"coordinates":[13.3129119873,51.1981811523],"type":"Point"}
}