{
  "type": "Feature",
  "properties": {
    "iso:country":"DE",
    "sg:address":"Mainzerhofstr. 12",
    "sg:city":"Erfurt",
    "sg:phone":"+49 361/56030",
    "sg:postcode":"99084",
    "sg:province":"Th\u00fcringen",
    "wof:name":"Landesentwicklungsgesellschaft Th\u00fcringen Mbh",
    "wof:placetype":"venue"
},
  "geometry": {"coordinates":[11.0210990906,50.9755477905],"type":"Point"}
}