{
  "type": "Feature",
  "properties": {
    "iso:country":"DE",
    "sg:address":"Schwitter Dorfstr. 17",
    "sg:city":"Menden",
    "sg:phone":"+49 2373/2877",
    "sg:postcode":"58708",
    "sg:province":"Nordrhein-Westfalen",
    "wof:name":"Adam Schulte-filthaut",
    "wof:placetype":"venue"
},
  "geometry": {"coordinates":[7.789628,51.461391],"type":"Point"}
}