{
  "type": "Feature",
  "properties": {
    "iso:country":"DE",
    "sg:address":"Prager Str. 1",
    "sg:city":"Waldkraiburg",
    "sg:phone":"+49 8638/5042",
    "sg:postcode":"84478",
    "sg:province":"Bayern",
    "wof:name":"O. Fritsch",
    "wof:placetype":"venue"
},
  "geometry": {"coordinates":[12.4007730484,48.2060699463],"type":"Point"}
}