{
  "type": "Feature",
  "properties": {
    "iso:country":"DE",
    "sg:address":"Rosenstra\u00dfe 37",
    "sg:city":"Ravensburg",
    "sg:phone":"+49 751",
    "sg:postcode":"88212",
    "sg:province":"Baden-W\u00fcrttemberg",
    "wof:name":"Infracommund Baulanderschlie\u00dfung Gmbh",
    "wof:placetype":"venue"
},
  "geometry": {"coordinates":[9.6127557755,47.783870697],"type":"Point"}
}