{
  "type": "Feature",
  "properties": {
    "iso:country":"DE",
    "sg:address":"Heisterer Weg 7a",
    "sg:city":"Unkel",
    "sg:phone":"+49 2224/93820",
    "sg:postcode":"53572",
    "sg:province":"Rheinland-Pfalz",
    "wof:name":"Gerhard Von Essen",
    "wof:placetype":"venue"
},
  "geometry": {"coordinates":[7.2208142281,50.5990638733],"type":"Point"}
}