{
  "type": "Feature",
  "properties": {
    "iso:country":"DE",
    "sg:address":"Magdeburger Str. 3",
    "sg:city":"Belzig",
    "sg:phone":"+49 33841/34812",
    "sg:postcode":"14806",
    "sg:province":"Brandenburg",
    "wof:name":"C. Bartels",
    "wof:placetype":"venue"
},
  "geometry": {"coordinates":[12.5872812271,52.1404914856],"type":"Point"}
}