{
  "type": "Feature",
  "properties": {
    "iso:country":"DE",
    "sg:address":"Neuer Markt 8",
    "sg:city":"Meckenheim",
    "sg:phone":"+49 2225/13037",
    "sg:postcode":"53340",
    "sg:province":"Nordrhein-Westfalen",
    "wof:name":"China-restaurant Tai Sin",
    "wof:placetype":"venue"
},
  "geometry": {"coordinates":[7.0402898788,50.6257019043],"type":"Point"}
}