{
  "type": "Feature",
  "properties": {
    "iso:country":"DE",
    "sg:address":"Rittersweg 1",
    "sg:city":"Elsfleth",
    "sg:postcode":"26931",
    "sg:province":"Niedersachsen",
    "wof:name":"Rudolf Schepers Gmbh",
    "wof:placetype":"venue"
},
  "geometry": {"coordinates":[8.4602336884,53.2355117798],"type":"Point"}
}