{
  "type": "Feature",
  "properties": {
    "iso:country":"DE",
    "sg:address":"D\u00f6ffinger Str. 110",
    "sg:city":"Grafenau",
    "sg:phone":"+49 7033/43296",
    "sg:postcode":"71120",
    "sg:province":"Baden-W\u00fcrttemberg",
    "wof:name":"H. Nagel",
    "wof:placetype":"venue"
},
  "geometry": {"coordinates":[8.877942,48.72208],"type":"Point"}
}