{
  "type": "Feature",
  "properties": {
    "iso:country":"DE",
    "sg:address":"Panoramastr. 10",
    "sg:city":"Seitingen-Oberflacht",
    "sg:phone":"+49 7464/1314",
    "sg:postcode":"78606",
    "sg:province":"Baden-W\u00fcrttemberg",
    "wof:name":"Erich Und Christa Merkt",
    "wof:placetype":"venue"
},
  "geometry": {"coordinates":[8.73298,48.022476],"type":"Point"}
}