{
  "type": "Feature",
  "properties": {
    "iso:country":"DE",
    "sg:address":"Werdauer Weg 12",
    "sg:city":"Berlin",
    "sg:phone":"+49 30/7824034",
    "sg:postcode":"10829",
    "sg:province":"Berlin",
    "wof:name":"Raab Karcher",
    "wof:placetype":"venue"
},
  "geometry": {"coordinates":[13.3506793976,52.4773902893],"type":"Point"}
}