{
  "type": "Feature",
  "properties": {
    "iso:country":"DE",
    "sg:address":"Bahnhofstr. 49",
    "sg:city":"Bahrdorf",
    "sg:phone":"+49 5364/7112",
    "sg:postcode":"38459",
    "sg:province":"Niedersachsen",
    "wof:name":"Eckhard Gifhorn",
    "wof:placetype":"venue"
},
  "geometry": {"coordinates":[10.99331,52.38139],"type":"Point"}
}