{
  "type": "Feature",
  "properties": {
    "iso:country":"DE",
    "sg:address":"Wehlm\u00e4usel",
    "sg:city":"Feuchtwangen",
    "sg:phone":"+49 9852/531",
    "sg:postcode":"91555",
    "sg:province":"Bayern",
    "wof:name":"H. M\u00e4ckler",
    "wof:placetype":"venue"
},
  "geometry": {"coordinates":[10.387932,49.126907],"type":"Point"}
}