{
  "type": "Feature",
  "properties": {
    "iso:country":"DE",
    "sg:address":"Amsterdamer Str. 6",
    "sg:city":"Berlin",
    "sg:phone":"+49 30/45083933",
    "sg:postcode":"13347",
    "sg:province":"Berlin",
    "wof:name":"Dirk Nowak",
    "wof:placetype":"venue"
},
  "geometry": {"coordinates":[13.3555755615,52.5501937866],"type":"Point"}
}