{
  "type": "Feature",
  "properties": {
    "iso:country":"DE",
    "sg:address":"Mohrmannsweg 25",
    "sg:city":"Schwanewede",
    "sg:phone":"+49 4209/2576",
    "sg:postcode":"28790",
    "sg:province":"Niedersachsen",
    "wof:name":"Re Chem Services Gmbh",
    "wof:placetype":"venue"
},
  "geometry": {"coordinates":[8.582444,53.245567],"type":"Point"}
}