{
  "type": "Feature",
  "properties": {
    "iso:country":"DE",
    "sg:address":"Brohltalstr. 42",
    "sg:city":"Oberzissen",
    "sg:phone":"+49 2636/6578",
    "sg:postcode":"56651",
    "sg:province":"Rheinland-Pfalz",
    "wof:name":"Gerhard Meid",
    "wof:placetype":"venue"
},
  "geometry": {"coordinates":[7.196197,50.45533],"type":"Point"}
}