{
  "type": "Feature",
  "properties": {
    "iso:country":"DE",
    "sg:address":"Hauptstr. 89",
    "sg:city":"Weinheim",
    "sg:phone":"+49 6201/185475",
    "sg:postcode":"69469",
    "sg:province":"Baden-W\u00fcrttemberg",
    "wof:name":"Scarlett Stoltenhoff",
    "wof:placetype":"venue"
},
  "geometry": {"coordinates":[8.672814,49.547897],"type":"Point"}
}