{
  "type": "Feature",
  "properties": {
    "iso:country":"DE",
    "sg:address":"Stover Str. 40",
    "sg:city":"Drage",
    "sg:phone":"+49 4176/270",
    "sg:postcode":"21423",
    "sg:province":"Niedersachsen",
    "wof:name":"Hans W. Otte Gmbh",
    "wof:placetype":"venue"
},
  "geometry": {"coordinates":[10.3067712784,53.4266853333],"type":"Point"}
}