{
  "type": "Feature",
  "properties": {
    "iso:country":"DE",
    "sg:address":"Lichtenau",
    "sg:city":"Lichtenau",
    "sg:postcode":"91586",
    "sg:province":"Bayern",
    "wof:name":"Raiffeisenbank Sachsen-immeldorf Eg",
    "wof:placetype":"venue"
},
  "geometry": {"coordinates":[10.668002,49.28466],"type":"Point"}
}