{
  "type": "Feature",
  "properties": {
    "iso:country":"DE",
    "sg:address":"Grot Sahl 34",
    "sg:city":"Hamburg",
    "sg:phone":"+49 40/817717",
    "sg:postcode":"22559",
    "sg:province":"Hamburg",
    "wof:name":"Fromm & Vollmer Hausmakler",
    "wof:placetype":"venue"
},
  "geometry": {"coordinates":[9.7616291046,53.5893173218],"type":"Point"}
}