{
  "type": "Feature",
  "properties": {
    "iso:country":"DE",
    "sg:address":"Von-der-Recke-Str. 5 a",
    "sg:city":"Bochum",
    "sg:phone":"+49 234/524206",
    "sg:postcode":"44809",
    "sg:province":"Nordrhein-Westfalen",
    "wof:name":"Marlies Schmitt",
    "wof:placetype":"venue"
},
  "geometry": {"coordinates":[7.192924,51.492733],"type":"Point"}
}