{
  "type": "Feature",
  "properties": {
    "iso:country":"DE",
    "sg:address":"Marienfelder Str. 123",
    "sg:city":"Koblenz",
    "sg:phone":"+49 261/984420",
    "sg:postcode":"56070",
    "sg:province":"Rheinland-Pfalz",
    "wof:name":"Lat Lagerungs- Und Antriebstechnik Gmbh",
    "wof:placetype":"venue"
},
  "geometry": {"coordinates":[7.590367,50.384907],"type":"Point"}
}