{
  "type": "Feature",
  "properties": {
    "iso:country":"DE",
    "sg:address":"Wandsbeker Zollstr. 71",
    "sg:city":"Hamburg",
    "sg:postcode":"22041",
    "sg:province":"Hamburg",
    "wof:name":"Wls Spedition Vermittlungsgesellschaft Mbh",
    "wof:placetype":"venue"
},
  "geometry": {"coordinates":[10.0787172318,53.5760154724],"type":"Point"}
}