{
  "type": "Feature",
  "properties": {
    "iso:country":"DE",
    "sg:address":"Kr\u00f6llstr. 9",
    "sg:city":"Grafenau",
    "sg:phone":"+49 8552/1893",
    "sg:postcode":"94481",
    "sg:province":"Bayern",
    "wof:name":"Ludwig Meininger",
    "wof:placetype":"venue"
},
  "geometry": {"coordinates":[13.3955049515,48.854724884],"type":"Point"}
}