{
  "type": "Feature",
  "properties": {
    "iso:country":"DE",
    "sg:address":"Deinselsgasse 8",
    "sg:city":"Ulm",
    "sg:phone":"+49 731/68510",
    "sg:postcode":"89073",
    "sg:province":"Baden-W\u00fcrttemberg",
    "wof:name":"Stadt N\u00fcrnberg",
    "wof:placetype":"venue"
},
  "geometry": {"coordinates":[9.9893245697,48.4005012512],"type":"Point"}
}