{
  "type": "Feature",
  "properties": {
    "iso:country":"DE",
    "sg:address":"Freiberger Str. 75",
    "sg:city":"Wilsdruff",
    "sg:phone":"+49 35204/6470",
    "sg:postcode":"01723",
    "sg:province":"Sachsen",
    "wof:name":"Kinon - Spiegel Wilsdruff Gmbh",
    "wof:placetype":"venue"
},
  "geometry": {"coordinates":[13.5428438187,51.0410690308],"type":"Point"}
}