{
  "type": "Feature",
  "properties": {
    "iso:country":"DE",
    "sg:address":"L\u00fcbecker Str. 32",
    "sg:city":"Schwerin",
    "sg:phone":"+49 385/864751",
    "sg:postcode":"19053",
    "sg:province":"Mecklenburg-Vorpommern",
    "wof:name":"Zweirad Nord Gmbh",
    "wof:placetype":"venue"
},
  "geometry": {"coordinates":[11.408088,53.629452],"type":"Point"}
}