{
  "type": "Feature",
  "properties": {
    "iso:country":"DE",
    "sg:address":"St\u00e4tzlinger Str. 53",
    "sg:city":"Augsburg",
    "sg:phone":"+49 821/79050",
    "sg:postcode":"86165",
    "sg:province":"Bayern",
    "wof:name":"Leop Siegle Gmbh & Co. Kg",
    "wof:placetype":"venue"
},
  "geometry": {"coordinates":[10.9310760498,48.3773956299],"type":"Point"}
}