{
  "type": "Feature",
  "properties": {
    "iso:country":"DE",
    "sg:address":"Hauptstr. 34",
    "sg:city":"Schallodenbach",
    "sg:phone":"+49 6363/1781",
    "sg:postcode":"67701",
    "sg:province":"Rheinland-Pfalz",
    "wof:name":"Haagen",
    "wof:placetype":"venue"
},
  "geometry": {"coordinates":[7.7139248848,49.5446243286],"type":"Point"}
}