{
  "type": "Feature",
  "properties": {
    "iso:country":"DE",
    "sg:address":"Weidenweg 47",
    "sg:city":"Burscheid",
    "sg:phone":"+49 2174/2136",
    "sg:postcode":"51399",
    "sg:province":"Nordrhein-Westfalen",
    "wof:name":"G. D\u00fcrre Anlageberater",
    "wof:placetype":"venue"
},
  "geometry": {"coordinates":[7.1355338097,51.0993614197],"type":"Point"}
}