{
  "type": "Feature",
  "properties": {
    "iso:country":"DE",
    "sg:address":"Frankfurter Str. 222",
    "sg:city":"Gie\u00dfen",
    "sg:phone":"+49 641/25359",
    "sg:postcode":"35398",
    "sg:province":"Hessen",
    "wof:name":"Binding Eck",
    "wof:placetype":"venue"
},
  "geometry": {"coordinates":[8.6508436203,50.5650024414],"type":"Point"}
}