{
  "type": "Feature",
  "properties": {
    "iso:country":"DE",
    "sg:address":"Universit\u00e4tskliniken",
    "sg:city":"Homburg",
    "sg:phone":"+49 6841/3529",
    "sg:postcode":"66424",
    "sg:province":"Saarland",
    "wof:name":"Restaurant Karlsberg Am Tor",
    "wof:placetype":"venue"
},
  "geometry": {"coordinates":[7.3462939262,49.3051071167],"type":"Point"}
}