{
  "type": "Feature",
  "properties": {
    "iso:country":"DE",
    "sg:address":"Dillinger Str. 32",
    "sg:city":"Friedrichsdorf",
    "sg:phone":"+49 6172/71860",
    "sg:postcode":"61381",
    "sg:province":"Hessen",
    "wof:name":"Ev. Jugendb\u00fcro",
    "wof:placetype":"venue"
},
  "geometry": {"coordinates":[8.630729,50.263206],"type":"Point"}
}