{
  "type": "Feature",
  "properties": {
    "iso:country":"DE",
    "sg:address":"Schweitenkirchener Str. 17",
    "sg:city":"Pfaffenhofen",
    "sg:postcode":"85276",
    "sg:province":"Bayern",
    "wof:name":"Walter Grundbesitz Gmbh & Co. Kg",
    "wof:placetype":"venue"
},
  "geometry": {"coordinates":[11.5364665985,48.5280189514],"type":"Point"}
}