{
  "type": "Feature",
  "properties": {
    "iso:country":"DE",
    "sg:address":"Kerzerweg 2",
    "sg:city":"R\u00fcdesheim am Rhein",
    "sg:phone":"+49 6726/680",
    "sg:postcode":"65385",
    "sg:province":"Hessen",
    "wof:name":"Georg Schuster",
    "wof:placetype":"venue"
},
  "geometry": {"coordinates":[7.891689,50.055077],"type":"Point"}
}