{
  "type": "Feature",
  "properties": {
    "iso:country":"DE",
    "sg:address":"Lorenz-Zierl-Str. 23",
    "sg:city":"Furth im Wald",
    "sg:phone":"+49 9973/1026",
    "sg:postcode":"93437",
    "sg:province":"Bayern",
    "wof:name":"Stefan Altmann Gmbh",
    "wof:placetype":"venue"
},
  "geometry": {"coordinates":[12.8442382812,49.3066940308],"type":"Point"}
}