{
  "type": "Feature",
  "properties": {
    "iso:country":"DE",
    "sg:address":"Am Pilsholz 12b",
    "sg:city":"Hamm",
    "sg:phone":"+49 2381/541944",
    "sg:postcode":"59063",
    "sg:province":"Nordrhein-Westfalen",
    "wof:name":"Noel Software Gmbh",
    "wof:placetype":"venue"
},
  "geometry": {"coordinates":[7.8380508423,51.6627159119],"type":"Point"}
}