{
  "type": "Feature",
  "properties": {
    "iso:country":"DE",
    "sg:address":"Bayerwald",
    "sg:city":"Kreuth",
    "sg:phone":"+49 8029/681",
    "sg:postcode":"83708",
    "sg:province":"Bayern",
    "wof:name":"Trift-h\u00fctte",
    "wof:placetype":"venue"
},
  "geometry": {"coordinates":[11.6806049347,47.6160163879],"type":"Point"}
}