{
  "type": "Feature",
  "properties": {
    "iso:country":"DE",
    "sg:address":"Heidener Str. 1",
    "sg:city":"Reken",
    "sg:phone":"+49 2864/1273",
    "sg:postcode":"48734",
    "sg:province":"Nordrhein-Westfalen",
    "wof:name":"Zweiradfachgesch\u00e4ft",
    "wof:placetype":"venue"
},
  "geometry": {"coordinates":[7.04013,51.831783],"type":"Point"}
}