{
  "type": "Feature",
  "properties": {
    "iso:country":"DE",
    "sg:address":"Hafenstr. 42 A",
    "sg:city":"Nordenham",
    "sg:phone":"+49 4731/88413",
    "sg:postcode":"26954",
    "sg:province":"Niedersachsen",
    "wof:name":"Blumenhaus Jutta Schniebs",
    "wof:placetype":"venue"
},
  "geometry": {"coordinates":[8.481787,53.488209],"type":"Point"}
}