{
  "type": "Feature",
  "properties": {
    "iso:country":"DE",
    "sg:address":"Ro\u00dfd\u00f6rfer Str. 40",
    "sg:city":"Darmstadt",
    "sg:phone":"+49 6151/48579",
    "sg:postcode":"64287",
    "sg:province":"Hessen",
    "wof:name":"Elektro- Winkelmann Gmbh",
    "wof:placetype":"venue"
},
  "geometry": {"coordinates":[8.6664857864,49.8696975708],"type":"Point"}
}