{
  "type": "Feature",
  "properties": {
    "iso:country":"DE",
    "sg:address":"Saarlouiser Str. 37",
    "sg:city":"Eisenh\u00fcttenstadt",
    "sg:phone":"+49 3364/740243",
    "sg:postcode":"15890",
    "sg:province":"Brandenburg",
    "wof:name":"Outdoor Reisen Und Expeditionen Gmbh",
    "wof:placetype":"venue"
},
  "geometry": {"coordinates":[14.62613,52.144939],"type":"Point"}
}