{
  "type": "Feature",
  "properties": {
    "iso:country":"DE",
    "sg:address":"Breslauer Str. 15",
    "sg:city":"Heidelberg",
    "sg:postcode":"69124",
    "sg:province":"Baden-W\u00fcrttemberg",
    "wof:name":"Imtron Splitsysteme Gmbh",
    "wof:placetype":"venue"
},
  "geometry": {"coordinates":[8.6654586792,49.3843841553],"type":"Point"}
}