{
  "type": "Feature",
  "properties": {
    "iso:country":"DE",
    "sg:address":"Gowenser Weg 21",
    "sg:city":"Malente",
    "sg:phone":"+49 4523/4310",
    "sg:postcode":"23714",
    "sg:province":"Schleswig-Holstein",
    "wof:name":"Hans Heincke",
    "wof:placetype":"venue"
},
  "geometry": {"coordinates":[10.558903,54.220451],"type":"Point"}
}