{
  "type": "Feature",
  "properties": {
    "iso:country":"DE",
    "sg:address":"Hauptstr. 36",
    "sg:city":"Ostenfeld",
    "sg:postcode":"25872",
    "sg:province":"Schleswig-Holstein",
    "wof:name":"Maicomp International Computer Trading Gmbh",
    "wof:placetype":"venue"
},
  "geometry": {"coordinates":[9.2399349213,54.4606285095],"type":"Point"}
}