{
  "type": "Feature",
  "properties": {
    "iso:country":"DE",
    "sg:address":"Zum S\u00fcldsberg 23",
    "sg:city":"Marxen",
    "sg:phone":"+49 4185/4262",
    "sg:postcode":"21439",
    "sg:province":"Niedersachsen",
    "wof:name":"Ram-nord Gmbh",
    "wof:placetype":"venue"
},
  "geometry": {"coordinates":[9.995059967,53.3124351501],"type":"Point"}
}