{
  "type": "Feature",
  "properties": {
    "iso:country":"DE",
    "sg:address":"Am Hang 2",
    "sg:city":"Odelzhausen",
    "sg:phone":"+49 8134/6791",
    "sg:postcode":"85235",
    "sg:province":"Bayern",
    "wof:name":"Tekma Kinomat Horst Holinka",
    "wof:placetype":"venue"
},
  "geometry": {"coordinates":[11.231453,48.331158],"type":"Point"}
}