{
  "type": "Feature",
  "properties": {
    "iso:country":"DE",
    "sg:address":"Hartweg 49",
    "sg:city":"Waldfeucht",
    "sg:phone":"+49 2455/2212",
    "sg:postcode":"52525",
    "sg:province":"Nordrhein-Westfalen",
    "wof:name":"Str\u00f6ckens Immobilienmakler",
    "wof:placetype":"venue"
},
  "geometry": {"coordinates":[5.9975152016,51.0528831482],"type":"Point"}
}