{
  "type": "Feature",
  "properties": {
    "iso:country":"DE",
    "sg:address":"Wei\u00dfenfelser Str.",
    "sg:city":"Naumburg",
    "sg:phone":"+49 3445/70590",
    "sg:postcode":"06618",
    "sg:province":"Sachsen-Anhalt",
    "wof:name":"Kaufland",
    "wof:placetype":"venue"
},
  "geometry": {"coordinates":[11.8173799515,51.1502876282],"type":"Point"}
}