{
  "type": "Feature",
  "properties": {
    "iso:country":"DE",
    "sg:address":"Altostr. 36",
    "sg:city":"M\u00fcnchen",
    "sg:phone":"+49 89/8631176",
    "sg:postcode":"81245",
    "sg:province":"Bayern",
    "wof:name":"Vera Jahnke",
    "wof:placetype":"venue"
},
  "geometry": {"coordinates":[11.4152832031,48.1598625183],"type":"Point"}
}