{
  "type": "Feature",
  "properties": {
    "iso:country":"DE",
    "sg:address":"Helmholtzstr. 9",
    "sg:city":"Chemnitz",
    "sg:phone":"+49 371/415279",
    "sg:postcode":"09131",
    "sg:province":"Sachsen",
    "wof:name":"Wolfgang Mehnert",
    "wof:placetype":"venue"
},
  "geometry": {"coordinates":[12.95337677,50.8522949219],"type":"Point"}
}