{
  "type": "Feature",
  "properties": {
    "iso:country":"DE",
    "sg:address":"Salzstr. 96 - 98",
    "sg:city":"Heilbronn",
    "sg:phone":"+49 7131/953226",
    "sg:postcode":"74076",
    "sg:province":"Baden-W\u00fcrttemberg",
    "wof:name":"Atlantic International Gmbh",
    "wof:placetype":"venue"
},
  "geometry": {"coordinates":[9.216238,49.157665],"type":"Point"}
}