{
  "type": "Feature",
  "properties": {
    "iso:country":"DE",
    "sg:address":"Wasserkr\u00fcger Weg 58a",
    "sg:city":"M\u00f6lln",
    "sg:phone":"+49 4542/4556",
    "sg:postcode":"23879",
    "sg:province":"Schleswig-Holstein",
    "wof:name":"Helga Rick",
    "wof:placetype":"venue"
},
  "geometry": {"coordinates":[10.687224,53.621475],"type":"Point"}
}