{
  "type": "Feature",
  "properties": {
    "iso:country":"DE",
    "sg:address":"Sandh\u00f6velstr. 10 a",
    "sg:city":"Rheine",
    "sg:phone":"+49 5971/64522",
    "sg:postcode":"48429",
    "sg:province":"Nordrhein-Westfalen",
    "wof:name":"Am Damm",
    "wof:placetype":"venue"
},
  "geometry": {"coordinates":[7.4644808769,52.2676734924],"type":"Point"}
}