{
  "type": "Feature",
  "properties": {
    "iso:country":"DE",
    "sg:address":"Steifensandstr. 5",
    "sg:city":"Berlin",
    "sg:phone":"+49 30/3219975",
    "sg:postcode":"14057",
    "sg:province":"Berlin",
    "wof:name":"Gardinen-expre\u00df D\u00f6bler Inh. Detlef Navrath",
    "wof:placetype":"venue"
},
  "geometry": {"coordinates":[13.294090271,52.5084877014],"type":"Point"}
}