{
  "type": "Feature",
  "properties": {
    "iso:country":"DE",
    "sg:address":"Ledermarkt 2",
    "sg:city":"Dinkelsb\u00fchl",
    "sg:phone":"+49 9851/2101",
    "sg:postcode":"91550",
    "sg:province":"Bayern",
    "wof:name":"Wilhelm Haagen",
    "wof:placetype":"venue"
},
  "geometry": {"coordinates":[10.320127,49.069061],"type":"Point"}
}