{
  "type": "Feature",
  "properties": {
    "iso:country":"DE",
    "sg:address":"Bruckmatten 37",
    "sg:city":"Eichstetten",
    "sg:postcode":"79356",
    "sg:province":"Baden-W\u00fcrttemberg",
    "wof:name":"E. R. T. Gmbh",
    "wof:placetype":"venue"
},
  "geometry": {"coordinates":[7.753104,48.092621],"type":"Point"}
}