{
  "type": "Feature",
  "properties": {
    "iso:country":"DE",
    "sg:address":"Aartalstr. 2a",
    "sg:city":"Hohenahr",
    "sg:phone":"+49 6444/8746",
    "sg:postcode":"35644",
    "sg:province":"Hessen",
    "wof:name":"Hermann Cloos",
    "wof:placetype":"venue"
},
  "geometry": {"coordinates":[8.490886,50.685455],"type":"Point"}
}