{
  "type": "Feature",
  "properties": {
    "iso:country":"DE",
    "sg:address":"Leipziger Str. 73",
    "sg:city":"Ringgau",
    "sg:phone":"+49 5658/243",
    "sg:postcode":"37296",
    "sg:province":"Hessen",
    "wof:name":"Tischlerei Beck Gmbh",
    "wof:placetype":"venue"
},
  "geometry": {"coordinates":[10.019717,51.11937],"type":"Point"}
}