{
  "type": "Feature",
  "properties": {
    "iso:country":"DE",
    "sg:address":"Rosenstr. 13",
    "sg:city":"Kronau",
    "sg:phone":"+49 7253/5666",
    "sg:postcode":"76709",
    "sg:province":"Baden-W\u00fcrttemberg",
    "wof:name":"Alfred Dickemann",
    "wof:placetype":"venue"
},
  "geometry": {"coordinates":[8.6265773773,49.2178153992],"type":"Point"}
}