{
  "type": "Feature",
  "properties": {
    "iso:country":"DE",
    "sg:address":"Kunzweg 15",
    "sg:city":"M\u00fcnchen",
    "sg:phone":"+49 89/838886",
    "sg:postcode":"81243",
    "sg:province":"Bayern",
    "wof:name":"Deas Concept Gmbh Grafik Und Werbung",
    "wof:placetype":"venue"
},
  "geometry": {"coordinates":[11.443312645,48.1410636902],"type":"Point"}
}