{
  "type": "Feature",
  "properties": {
    "iso:country":"DE",
    "sg:address":"Vor dem Obertor 4",
    "sg:city":"Wanfried",
    "sg:phone":"+49 5655/395",
    "sg:postcode":"37281",
    "sg:province":"Hessen",
    "wof:name":"Kath. Pfarramt St. Nikolaus",
    "wof:placetype":"venue"
},
  "geometry": {"coordinates":[10.1738758087,51.1797637939],"type":"Point"}
}