{
  "type": "Feature",
  "properties": {
    "iso:country":"DE",
    "sg:address":"Dorfstr. 44a",
    "sg:city":"Niestetal",
    "sg:phone":"+49 561/523386",
    "sg:postcode":"34266",
    "sg:province":"Hessen",
    "wof:name":"Rose",
    "wof:placetype":"venue"
},
  "geometry": {"coordinates":[9.5810003281,51.3073692322],"type":"Point"}
}