{
  "type": "Feature",
  "properties": {
    "iso:country":"DE",
    "sg:address":"Stra\u00dfe der Republik 36",
    "sg:city":"Oderwitz",
    "sg:phone":"+49 35842/25377",
    "sg:postcode":"02791",
    "sg:province":"Sachsen",
    "wof:name":"P. Stieber Anlageberater",
    "wof:placetype":"venue"
},
  "geometry": {"coordinates":[14.7460098267,50.938331604],"type":"Point"}
}