{
  "type": "Feature",
  "properties": {
    "iso:country":"DE",
    "sg:address":"Montanusstr. 90",
    "sg:city":"Grevenbroich",
    "sg:phone":"+49 2181",
    "sg:postcode":"41515",
    "sg:province":"Nordrhein-Westfalen",
    "wof:name":"Kontaktlinsenwelt",
    "wof:placetype":"venue"
},
  "geometry": {"coordinates":[6.595425,51.088772],"type":"Point"}
}