{
  "type": "Feature",
  "properties": {
    "iso:country":"DE",
    "sg:address":"Zugspitzstr. 20",
    "sg:city":"Augsburg",
    "sg:phone":"+49 821/667373",
    "sg:postcode":"86163",
    "sg:province":"Bayern",
    "wof:name":"Baupartner K & L Baubetreuungs- Und",
    "wof:placetype":"venue"
},
  "geometry": {"coordinates":[10.94345,48.356655],"type":"Point"}
}