{
  "type": "Feature",
  "properties": {
    "iso:country":"DE",
    "sg:address":"Vivaldistr. 21",
    "sg:city":"Northeim",
    "sg:phone":"+49 5551/51361",
    "sg:postcode":"37154",
    "sg:province":"Niedersachsen",
    "wof:name":"Marianne Deerberg",
    "wof:placetype":"venue"
},
  "geometry": {"coordinates":[9.984983,51.726433],"type":"Point"}
}