{
  "type": "Feature",
  "properties": {
    "iso:country":"DE",
    "sg:address":"Beethovenstr. 18",
    "sg:city":"Schwalmtal",
    "sg:phone":"+49 2163/948930",
    "sg:postcode":"41366",
    "sg:province":"Nordrhein-Westfalen",
    "wof:name":"Sycon Beratungs-gmbh",
    "wof:placetype":"venue"
},
  "geometry": {"coordinates":[6.2796359062,51.2178688049],"type":"Point"}
}