{
  "type": "Feature",
  "properties": {
    "iso:country":"DE",
    "sg:address":"Behlertstr. 7",
    "sg:city":"Potsdam",
    "sg:phone":"+49 331/2707175",
    "sg:postcode":"14469",
    "sg:province":"Brandenburg",
    "wof:name":"Luftbild Und Planung Ges. F\u00fcr Landschafts- Landes-",
    "wof:placetype":"venue"
},
  "geometry": {"coordinates":[13.0629863739,52.4064292908],"type":"Point"}
}