{
  "type": "Feature",
  "properties": {
    "iso:country":"DE",
    "sg:address":"Charlottenstr. 73",
    "sg:city":"D\u00fcsseldorf",
    "sg:phone":"+49 211/173620",
    "sg:postcode":"40210",
    "sg:province":"Nordrhein-Westfalen",
    "wof:name":"Eka W\u00e4lzlager Gro\u00dfhandel Erich K\u00fchn",
    "wof:placetype":"venue"
},
  "geometry": {"coordinates":[6.790492,51.223106],"type":"Point"}
}