{
  "type": "Feature",
  "properties": {
    "iso:country":"DE",
    "sg:address":"Freiligrathstr. 213",
    "sg:city":"Wilhelmshaven",
    "sg:phone":"+49 4421/64484",
    "sg:postcode":"26386",
    "sg:province":"Niedersachsen",
    "wof:name":"Wapo Warenposten Handelsgesellschaft Mbh",
    "wof:placetype":"venue"
},
  "geometry": {"coordinates":[8.1170377731,53.5465545654],"type":"Point"}
}