{
  "type": "Feature",
  "properties": {
    "iso:country":"DE",
    "sg:address":"Stra\u00dfe des Friedens 20",
    "sg:city":"Espenhain",
    "sg:phone":"+49 34206/55288",
    "sg:postcode":"04579",
    "sg:province":"Sachsen",
    "wof:name":"Werner Sch\u00f6nberg",
    "wof:placetype":"venue"
},
  "geometry": {"coordinates":[12.4724235535,51.190738678],"type":"Point"}
}