{
  "type": "Feature",
  "properties": {
    "iso:country":"DE",
    "sg:address":"Werdener Str. 17",
    "sg:city":"Velbert",
    "sg:phone":"+49 2051/85185",
    "sg:postcode":"42551",
    "sg:province":"Nordrhein-Westfalen",
    "wof:name":"Klaus Oeffling",
    "wof:placetype":"venue"
},
  "geometry": {"coordinates":[7.031193,51.345955],"type":"Point"}
}