{
  "type": "Feature",
  "properties": {
    "iso:country":"DE",
    "sg:address":"Waldschulstr. 30",
    "sg:city":"M\u00fcnchen",
    "sg:postcode":"81827",
    "sg:province":"Bayern",
    "wof:name":"Ways Gmbh",
    "wof:placetype":"venue"
},
  "geometry": {"coordinates":[11.6936292648,48.1086120605],"type":"Point"}
}