{
  "type": "Feature",
  "properties": {
    "iso:country":"DE",
    "sg:address":"Hegaustr. 11",
    "sg:city":"Balingen",
    "sg:phone":"+49 7433/381915",
    "sg:postcode":"72336",
    "sg:province":"Baden-W\u00fcrttemberg",
    "wof:name":"Alpirsbacher Klosterbr\u00e4u Glauner Gmbh & Co.",
    "wof:placetype":"venue"
},
  "geometry": {"coordinates":[8.849268,48.273102],"type":"Point"}
}