{
  "type": "Feature",
  "properties": {
    "iso:country":"DE",
    "sg:address":"H\u00e4ndelstr. 10",
    "sg:city":"Markkleeberg",
    "sg:phone":"+49 341/3383102",
    "sg:postcode":"04416",
    "sg:province":"Sachsen",
    "wof:name":"Prof. Dr. Med. Wolfgang Klimm",
    "wof:placetype":"venue"
},
  "geometry": {"coordinates":[12.400959,51.281235],"type":"Point"}
}