{
  "type": "Feature",
  "properties": {
    "iso:country":"DE",
    "sg:address":"Marienstr. 142",
    "sg:city":"Minden",
    "sg:phone":"+49 571/41517",
    "sg:postcode":"32425",
    "sg:province":"Nordrhein-Westfalen",
    "wof:name":"Heinrich Giese Gmbh",
    "wof:placetype":"venue"
},
  "geometry": {"coordinates":[8.915409,52.309448],"type":"Point"}
}