{
  "type": "Feature",
  "properties": {
    "iso:country":"DE",
    "sg:address":"Hildesheimer Str. 124h",
    "sg:city":"Laatzen",
    "sg:phone":"+49 511/868646",
    "sg:postcode":"30880",
    "sg:province":"Niedersachsen",
    "wof:name":"Heinz-dieter Gebhardt",
    "wof:placetype":"venue"
},
  "geometry": {"coordinates":[9.7967300415,52.3105239868],"type":"Point"}
}