{
  "type": "Feature",
  "properties": {
    "iso:country":"DE",
    "sg:address":"Ehrenbergstr. 19",
    "sg:city":"Berlin",
    "sg:phone":"+49 30/2936336",
    "sg:postcode":"10245",
    "sg:province":"Berlin",
    "wof:name":"Ivistar Kommunikations- Systeme Ag",
    "wof:placetype":"venue"
},
  "geometry": {"coordinates":[13.451536,52.503345],"type":"Point"}
}