{
  "type": "Feature",
  "properties": {
    "iso:country":"DE",
    "sg:address":"Panzweiler- Stra\u00dfe 1",
    "sg:city":"Gem\u00fcnden",
    "sg:phone":"+49 6765",
    "sg:postcode":"55490",
    "sg:province":"Rheinland-Pfalz",
    "wof:name":"Familie Bu\u00df, Edeka Lebensmittel Lieferservice",
    "wof:placetype":"venue"
},
  "geometry": {"coordinates":[7.479809,49.896034],"type":"Point"}
}