{
  "type": "Feature",
  "properties": {
    "iso:country":"DE",
    "sg:address":"Neuh\u00e4user Kirchstr. 19",
    "sg:city":"Paderborn",
    "sg:phone":"+49 5254/2297",
    "sg:postcode":"33104",
    "sg:province":"Nordrhein-Westfalen",
    "wof:name":"Hotel Hellmann",
    "wof:placetype":"venue"
},
  "geometry": {"coordinates":[8.7120800018,51.7428588867],"type":"Point"}
}