{
  "type": "Feature",
  "properties": {
    "iso:country":"DE",
    "sg:address":"Casumer Str. 31",
    "sg:city":"Versmold",
    "sg:phone":"+49 5423/8825",
    "sg:postcode":"33775",
    "sg:province":"Nordrhein-Westfalen",
    "wof:name":"Paul Leimk\u00fchler",
    "wof:placetype":"venue"
},
  "geometry": {"coordinates":[8.2472391129,52.0437507629],"type":"Point"}
}