{
  "type": "Feature",
  "properties": {
    "iso:country":"DE",
    "sg:address":"Plei\u00dfenstr. 8",
    "sg:city":"Markkleeberg",
    "sg:phone":"+49 341/320850",
    "sg:postcode":"04416",
    "sg:province":"Sachsen",
    "wof:name":"Werner Sonntag Und Partner",
    "wof:placetype":"venue"
},
  "geometry": {"coordinates":[12.3757219315,51.2891960144],"type":"Point"}
}