{
  "type": "Feature",
  "properties": {
    "iso:country":"DE",
    "sg:address":"Neuer Weg 14",
    "sg:city":"Laubach",
    "sg:phone":"+49 6401/4700",
    "sg:postcode":"35321",
    "sg:province":"Hessen",
    "wof:name":"W. Schmidt Und H. Seebruch Anlageberater",
    "wof:placetype":"venue"
},
  "geometry": {"coordinates":[8.9715518951,50.5727043152],"type":"Point"}
}