{
  "type": "Feature",
  "properties": {
    "iso:country":"DE",
    "sg:address":"Markt 32",
    "sg:city":"Waldershof",
    "sg:phone":"+49 9231/97750",
    "sg:postcode":"95679",
    "sg:province":"Bayern",
    "wof:name":"H\u00e4usliche Kranken- Und Altenpflege E. V.",
    "wof:placetype":"venue"
},
  "geometry": {"coordinates":[12.062476,49.977562],"type":"Point"}
}