{
  "type": "Feature",
  "properties": {
    "iso:country":"DE",
    "sg:address":"Schlosserstr. 2",
    "sg:city":"Breidenbach",
    "sg:phone":"+49 6465/92600",
    "sg:postcode":"35236",
    "sg:province":"Hessen",
    "wof:name":"Elisabeth Wagner Gmbh",
    "wof:placetype":"venue"
},
  "geometry": {"coordinates":[8.446598053,50.8899650574],"type":"Point"}
}