{
  "type": "Feature",
  "properties": {
    "iso:country":"DE",
    "sg:address":"Sommerheck 7",
    "sg:city":"Neuwied",
    "sg:phone":"+49 2631/5108",
    "sg:postcode":"56567",
    "sg:province":"Rheinland-Pfalz",
    "wof:name":"E.m.c. Handelsgesellschaft F. Holz, Stahl Und Beton Mbh",
    "wof:placetype":"venue"
},
  "geometry": {"coordinates":[7.471278,50.462364],"type":"Point"}
}