{
  "type": "Feature",
  "properties": {
    "iso:country":"DE",
    "sg:address":"Wuthenowstr. 31",
    "sg:city":"Hamburg",
    "sg:phone":"+49 40/6530254",
    "sg:postcode":"22043",
    "sg:province":"Hamburg",
    "wof:name":"Manfred Kr\u00fcger",
    "wof:placetype":"venue"
},
  "geometry": {"coordinates":[10.11208,53.572598],"type":"Point"}
}