{
  "type": "Feature",
  "properties": {
    "iso:country":"DE",
    "sg:address":"Heidestr. 38",
    "sg:city":"W\u00fcrselen",
    "sg:phone":"+49 2405/87454",
    "sg:postcode":"52146",
    "sg:province":"Nordrhein-Westfalen",
    "wof:name":"Triangle Im Haus Steinbusch",
    "wof:placetype":"venue"
},
  "geometry": {"coordinates":[6.1109762192,50.8399620056],"type":"Point"}
}