{
  "type": "Feature",
  "properties": {
    "iso:country":"DE",
    "sg:address":"J\u00e4gersweg 4",
    "sg:city":"Leidersbach",
    "sg:phone":"+49 6092/7908",
    "sg:postcode":"63849",
    "sg:province":"Bayern",
    "wof:name":"Reinhard Monz Ingenieur",
    "wof:placetype":"venue"
},
  "geometry": {"coordinates":[9.2687072754,49.8965873718],"type":"Point"}
}