{
  "type": "Feature",
  "properties": {
    "iso:country":"DE",
    "sg:address":"Wittenburger Str. 29",
    "sg:city":"Renzow",
    "sg:phone":"+49 38874/22318",
    "sg:postcode":"19209",
    "sg:province":"Mecklenburg-Vorpommern",
    "wof:name":"Container Service Peter Brandt",
    "wof:placetype":"venue"
},
  "geometry": {"coordinates":[11.151076,53.619244],"type":"Point"}
}