{
  "type": "Feature",
  "properties": {
    "iso:country":"DE",
    "sg:address":"Kaiser-Wilhelm-Ring 38",
    "sg:city":"K\u00f6ln",
    "sg:phone":"+49 221/133713",
    "sg:postcode":"50672",
    "sg:province":"Nordrhein-Westfalen",
    "wof:name":"Frielingsdorf Und Partner",
    "wof:placetype":"venue"
},
  "geometry": {"coordinates":[6.94104,50.94289],"type":"Point"}
}