{
  "type": "Feature",
  "properties": {
    "iso:country":"DE",
    "sg:address":"Hainholzstr. 18",
    "sg:city":"Hagenburg",
    "sg:phone":"+49 5033/69224",
    "sg:postcode":"31558",
    "sg:province":"Niedersachsen",
    "wof:name":"S. Kleine",
    "wof:placetype":"venue"
},
  "geometry": {"coordinates":[9.321434021,52.4309234619],"type":"Point"}
}