{
  "type": "Feature",
  "properties": {
    "iso:country":"DE",
    "sg:address":"Ortsstr. 19",
    "sg:city":"Miesitz",
    "sg:postcode":"07819",
    "sg:province":"Th\u00fcringen",
    "wof:name":"Vato Gmbh",
    "wof:placetype":"venue"
},
  "geometry": {"coordinates":[11.8330564499,50.7399330139],"type":"Point"}
}