{
  "type": "Feature",
  "properties": {
    "iso:country":"DE",
    "sg:address":"Venloer Str. 160",
    "sg:city":"K\u00f6ln",
    "sg:postcode":"50823",
    "sg:province":"Nordrhein-Westfalen",
    "wof:name":"T\u00fcrkisch Islamische Union Der Anstalt F\u00fcr Religion",
    "wof:placetype":"venue"
},
  "geometry": {"coordinates":[6.9279279709,50.9453086853],"type":"Point"}
}