{
  "type": "Feature",
  "properties": {
    "iso:country":"DE",
    "sg:address":"Zur Pankokenm\u00fchle 2",
    "sg:city":"Lichtenau",
    "sg:phone":"+49 5295/7247",
    "sg:postcode":"33165",
    "sg:province":"Nordrhein-Westfalen",
    "wof:name":"Stadtwerke Paderborn Gmbh",
    "wof:placetype":"venue"
},
  "geometry": {"coordinates":[8.902853,51.620594],"type":"Point"}
}