{
  "type": "Feature",
  "properties": {
    "iso:country":"DE",
    "sg:address":"Untergasse 4",
    "sg:city":"Buseck",
    "sg:phone":"+49 6408/965066",
    "sg:postcode":"35418",
    "sg:province":"Hessen",
    "wof:name":"M. Dort",
    "wof:placetype":"venue"
},
  "geometry": {"coordinates":[8.8244419098,50.6282920837],"type":"Point"}
}