{
  "type": "Feature",
  "properties": {
    "iso:country":"DE",
    "sg:address":"Hohweg 22",
    "sg:city":"Weissach",
    "sg:phone":"+49 7044/32565",
    "sg:postcode":"71287",
    "sg:province":"Baden-W\u00fcrttemberg",
    "wof:name":"Waltraud Ziehmann",
    "wof:placetype":"venue"
},
  "geometry": {"coordinates":[8.911841,48.837566],"type":"Point"}
}