{
  "type": "Feature",
  "properties": {
    "iso:country":"DE",
    "sg:address":"Borchsh\u00f6her Str. 62",
    "sg:city":"Bremen",
    "sg:phone":"+49 421/651787",
    "sg:postcode":"28757",
    "sg:province":"Bremen",
    "wof:name":"Lothar M\u00fcller",
    "wof:placetype":"venue"
},
  "geometry": {"coordinates":[8.6335315704,53.1823616028],"type":"Point"}
}