{
  "type": "Feature",
  "properties": {
    "iso:country":"DE",
    "sg:address":"Dorfstr. 9",
    "sg:city":"Hamdorf",
    "sg:postcode":"24805",
    "sg:province":"Schleswig-Holstein",
    "wof:name":"Renate Und Karl-h. J\u00fcrgensen",
    "wof:placetype":"venue"
},
  "geometry": {"coordinates":[9.5191984177,54.2241249084],"type":"Point"}
}