{
  "type": "Feature",
  "properties": {
    "iso:country":"DE",
    "sg:address":"Untenende West 28",
    "sg:city":"Uplengen",
    "sg:phone":"+49 4957/216",
    "sg:postcode":"26670",
    "sg:province":"Niedersachsen",
    "wof:name":"G. H. De Vries",
    "wof:placetype":"venue"
},
  "geometry": {"coordinates":[7.6848111153,53.2557983398],"type":"Point"}
}