{
  "type": "Feature",
  "properties": {
    "iso:country":"DE",
    "sg:address":"Oberamteistr. 13",
    "sg:city":"K\u00fcnzelsau",
    "sg:phone":"+49 7940/3561",
    "sg:postcode":"74653",
    "sg:province":"Baden-W\u00fcrttemberg",
    "wof:name":"I. Kacner",
    "wof:placetype":"venue"
},
  "geometry": {"coordinates":[9.686937,49.278576],"type":"Point"}
}