{
  "type": "Feature",
  "properties": {
    "iso:country":"DE",
    "sg:address":"Am Hetgesborn 15",
    "sg:city":"Butzbach",
    "sg:phone":"+49 6033/96520",
    "sg:postcode":"35510",
    "sg:province":"Hessen",
    "wof:name":"Hoyer Gmbh",
    "wof:placetype":"venue"
},
  "geometry": {"coordinates":[8.681184,50.431351],"type":"Point"}
}