{
  "type": "Feature",
  "properties": {
    "iso:country":"DE",
    "sg:address":"Untere Dorfstr. 68",
    "sg:city":"Siegen",
    "sg:phone":"+49 271/62249",
    "sg:postcode":"57074",
    "sg:province":"Nordrhein-Westfalen",
    "wof:name":"Kaiser Gmbh",
    "wof:placetype":"venue"
},
  "geometry": {"coordinates":[8.0532302856,50.8862113953],"type":"Point"}
}