{
  "type": "Feature",
  "properties": {
    "iso:country":"DE",
    "sg:address":"Fasanenstr. 11 A",
    "sg:city":"Karlsfeld",
    "sg:phone":"+49 8131/59500",
    "sg:postcode":"85757",
    "sg:province":"Bayern",
    "wof:name":"Process Control Regel-u. Masch.technik Gmbh",
    "wof:placetype":"venue"
},
  "geometry": {"coordinates":[11.483609,48.230251],"type":"Point"}
}