{
  "type": "Feature",
  "properties": {
    "iso:country":"DE",
    "sg:address":"Scheyerer Str. 42",
    "sg:city":"Pfaffenhofen",
    "sg:phone":"+49 8441/803742",
    "sg:postcode":"85276",
    "sg:province":"Bayern",
    "wof:name":"Sabine Engwitz Ergotherapiepraxis",
    "wof:placetype":"venue"
},
  "geometry": {"coordinates":[11.501177,48.527542],"type":"Point"}
}