{
  "type": "Feature",
  "properties": {
    "iso:country":"DE",
    "sg:address":"Birkhuhnweg 19",
    "sg:city":"Berlin",
    "sg:phone":"+49 30/50575635",
    "sg:postcode":"12351",
    "sg:province":"Berlin",
    "wof:name":"Mobile Discothek",
    "wof:placetype":"venue"
},
  "geometry": {"coordinates":[13.468142,52.437248],"type":"Point"}
}