{
  "type": "Feature",
  "properties": {
    "iso:country":"DE",
    "sg:address":"Hansastr. 9",
    "sg:city":"Emden",
    "sg:phone":"+49 4921/23849",
    "sg:postcode":"26723",
    "sg:province":"Niedersachsen",
    "wof:name":"Johann Dennh\u00f6fer",
    "wof:placetype":"venue"
},
  "geometry": {"coordinates":[7.196055,53.362606],"type":"Point"}
}