{
  "type": "Feature",
  "properties": {
    "iso:country":"DE",
    "sg:address":"St\u00f6ckenstr. 11 b",
    "sg:city":"Leverkusen",
    "sg:postcode":"51371",
    "sg:province":"Nordrhein-Westfalen",
    "wof:name":"Gdm Gesellschaft Digitaler Medien Mbh",
    "wof:placetype":"venue"
},
  "geometry": {"coordinates":[6.9116101265,51.0677566528],"type":"Point"}
}