{
  "type": "Feature",
  "properties": {
    "iso:country":"DE",
    "sg:address":"Kanderner Str. 2",
    "sg:city":"Steinen",
    "sg:phone":"+49 7627/8071",
    "sg:postcode":"79585",
    "sg:province":"Baden-W\u00fcrttemberg",
    "wof:name":"Stern Drogerie Gmbh",
    "wof:placetype":"venue"
},
  "geometry": {"coordinates":[7.740095,47.64344],"type":"Point"}
}