{
  "type": "Feature",
  "properties": {
    "iso:country":"DE",
    "sg:address":"Kr\u00f6peliner Str. 49",
    "sg:city":"Rostock",
    "sg:phone":"+49 381/452666",
    "sg:postcode":"18055",
    "sg:province":"Mecklenburg-Vorpommern",
    "wof:name":"Depfa Bank Ag",
    "wof:placetype":"venue"
},
  "geometry": {"coordinates":[12.1297130585,54.0883483887],"type":"Point"}
}