{
  "type": "Feature",
  "properties": {
    "iso:country":"DE",
    "sg:address":"Hauptstr. 19",
    "sg:city":"Taura",
    "sg:phone":"+49 3724/2542",
    "sg:postcode":"09249",
    "sg:province":"Sachsen",
    "wof:name":"Rolf B\u00f6hl",
    "wof:placetype":"venue"
},
  "geometry": {"coordinates":[12.851491,50.923347],"type":"Point"}
}