{
  "type": "Feature",
  "properties": {
    "iso:country":"DE",
    "sg:address":"Stephensonstr. 4",
    "sg:city":"Potsdam",
    "sg:postcode":"14482",
    "sg:province":"Brandenburg",
    "wof:name":"Gkma Gesellschaft Kommunaler Mevag - Aktion\u00e4re Mbh",
    "wof:placetype":"venue"
},
  "geometry": {"coordinates":[13.098118782,52.3904457092],"type":"Point"}
}