{
  "type": "Feature",
  "properties": {
    "iso:country":"DE",
    "sg:address":"Max-Stromeyer-Str. 31",
    "sg:city":"Konstanz",
    "sg:phone":"+49 7531/63038",
    "sg:postcode":"78467",
    "sg:province":"Baden-W\u00fcrttemberg",
    "wof:name":"Senger & Butz Gmbh",
    "wof:placetype":"venue"
},
  "geometry": {"coordinates":[9.1592006683,47.6764793396],"type":"Point"}
}