{
  "type": "Feature",
  "properties": {
    "iso:country":"DE",
    "sg:address":"Marktplatz 4",
    "sg:city":"Gschwend",
    "sg:phone":"+49 7972/393",
    "sg:postcode":"74417",
    "sg:province":"Baden-W\u00fcrttemberg",
    "wof:name":"Weller",
    "wof:placetype":"venue"
},
  "geometry": {"coordinates":[9.743973,48.933834],"type":"Point"}
}