{
  "type": "Feature",
  "properties": {
    "iso:country":"DE",
    "sg:address":"L\u00fcbecker Str. 64-67",
    "sg:city":"Magdeburg",
    "sg:phone":"+49 391/2515390",
    "sg:postcode":"39124",
    "sg:province":"Sachsen-Anhalt",
    "wof:name":"Hagebaumarkt Magdeburg Verwaltungsgesellschaft Mbh",
    "wof:placetype":"venue"
},
  "geometry": {"coordinates":[11.6331138611,52.164932251],"type":"Point"}
}