{
  "type": "Feature",
  "properties": {
    "iso:country":"DE",
    "sg:address":"Segeten 52",
    "sg:city":"G\u00f6rwihl",
    "sg:phone":"+49 7764/349",
    "sg:postcode":"79733",
    "sg:province":"Baden-W\u00fcrttemberg",
    "wof:name":"Pension Bisam-pelz",
    "wof:placetype":"venue"
},
  "geometry": {"coordinates":[8.0189857483,47.6577949524],"type":"Point"}
}