{
  "type": "Feature",
  "properties": {
    "iso:country":"DE",
    "sg:address":"K\u00f6lner Str 23",
    "sg:city":"D\u00fcsseldorf",
    "sg:phone":"+49 211/354033",
    "sg:postcode":"40211",
    "sg:province":"Nordrhein-Westfalen",
    "wof:name":"Alfred Kaut Gmbh & Co",
    "wof:placetype":"venue"
},
  "geometry": {"coordinates":[6.792723,51.227234],"type":"Point"}
}