{
  "type": "Feature",
  "properties": {
    "iso:country":"DE",
    "sg:address":"Korngasse 23",
    "sg:city":"Speyer",
    "sg:phone":"+49 6232/290283",
    "sg:postcode":"67346",
    "sg:province":"Rheinland-Pfalz",
    "wof:name":"Klaus Bereswill",
    "wof:placetype":"venue"
},
  "geometry": {"coordinates":[8.4347896576,49.3177909851],"type":"Point"}
}