{
  "type": "Feature",
  "properties": {
    "iso:country":"DE",
    "sg:address":"Kanalstr. 10",
    "sg:city":"Seebad Heringsdorf",
    "sg:phone":"+49 38378/30754",
    "sg:postcode":"17424",
    "sg:province":"Mecklenburg-Vorpommern",
    "wof:name":"M. Beier",
    "wof:placetype":"venue"
},
  "geometry": {"coordinates":[14.145892,53.95813],"type":"Point"}
}