{
  "type": "Feature",
  "properties": {
    "iso:country":"DE",
    "sg:address":"Hauptstr. 3",
    "sg:city":"Lalendorf",
    "sg:phone":"+49 38452/20542",
    "sg:postcode":"18279",
    "sg:province":"Mecklenburg-Vorpommern",
    "wof:name":"Im Wiesengrund",
    "wof:placetype":"venue"
},
  "geometry": {"coordinates":[12.4155111313,53.7610397339],"type":"Point"}
}