{
  "type": "Feature",
  "properties": {
    "iso:country":"DE",
    "sg:address":"Marktplatz 14",
    "sg:city":"Berchtesgaden",
    "sg:phone":"+49 8652/957970",
    "sg:postcode":"83471",
    "sg:province":"Bayern",
    "wof:name":"Hagemann Gmbh",
    "wof:placetype":"venue"
},
  "geometry": {"coordinates":[13.001276,47.63282],"type":"Point"}
}