{
  "type": "Feature",
  "properties": {
    "iso:country":"DE",
    "sg:address":"Patriotischer Weg 19",
    "sg:city":"Rostock",
    "sg:phone":"+49 381/491080",
    "sg:postcode":"18057",
    "sg:province":"Mecklenburg-Vorpommern",
    "wof:name":"Biemann K\u00fchne Und Partner Rechtsanw\u00e4lte",
    "wof:placetype":"venue"
},
  "geometry": {"coordinates":[12.122833252,54.0906448364],"type":"Point"}
}