{
  "type": "Feature",
  "properties": {
    "iso:country":"DE",
    "sg:address":"Am Fritzenberg 19",
    "sg:city":"N\u00fcsttal",
    "sg:phone":"+49 6652/72406",
    "sg:postcode":"36167",
    "sg:province":"Hessen",
    "wof:name":"A. Janka",
    "wof:placetype":"venue"
},
  "geometry": {"coordinates":[9.8100061417,50.634853363],"type":"Point"}
}