{
  "type": "Feature",
  "properties": {
    "iso:country":"DE",
    "sg:address":"K\u00fchnhofener Str. 42",
    "sg:city":"Hersbruck",
    "sg:phone":"+49 9151/6000",
    "sg:postcode":"91217",
    "sg:province":"Bayern",
    "wof:name":"Reilo Gmbh Reifenrunder- Neuerung",
    "wof:placetype":"venue"
},
  "geometry": {"coordinates":[11.4176893234,49.5146446228],"type":"Point"}
}