{
  "type": "Feature",
  "properties": {
    "iso:country":"DE",
    "sg:address":"Obere Hauptstr. 4",
    "sg:city":"Wartenberg",
    "sg:phone":"+49 8762/1212",
    "sg:postcode":"85456",
    "sg:province":"Bayern",
    "wof:name":"Gustav Weltrichsche Apotheke",
    "wof:placetype":"venue"
},
  "geometry": {"coordinates":[11.989746,48.404125],"type":"Point"}
}