{
  "type": "Feature",
  "properties": {
    "iso:country":"DE",
    "sg:address":"Bergerstr. 2",
    "sg:city":"Br\u00fchl",
    "sg:phone":"+49 2232/42373",
    "sg:postcode":"50321",
    "sg:province":"Nordrhein-Westfalen",
    "wof:name":"Gustav Schmitz",
    "wof:placetype":"venue"
},
  "geometry": {"coordinates":[6.9224948883,50.829864502],"type":"Point"}
}