{
  "type": "Feature",
  "properties": {
    "iso:country":"DE",
    "sg:address":"Bevenser Str. 4",
    "sg:city":"Emmendorf",
    "sg:phone":"+49 4958/75233",
    "sg:postcode":"29579",
    "sg:province":"Niedersachsen",
    "wof:name":"Sparkasse Uelzen",
    "wof:placetype":"venue"
},
  "geometry": {"coordinates":[10.568359,53.02457],"type":"Point"}
}