{
  "type": "Feature",
  "properties": {
    "iso:country":"DE",
    "sg:address":"Breitfurter Str. 76",
    "sg:city":"Blieskastel",
    "sg:phone":"+49 6842/5876",
    "sg:postcode":"66440",
    "sg:province":"Saarland",
    "wof:name":"Joachim G\u00f6tz",
    "wof:placetype":"venue"
},
  "geometry": {"coordinates":[7.2671918869,49.2267570496],"type":"Point"}
}