{
  "type": "Feature",
  "properties": {
    "iso:country":"DE",
    "sg:address":"S\u00fcdring 40",
    "sg:city":"Bielefeld",
    "sg:phone":"+49 521/950330",
    "sg:postcode":"33647",
    "sg:province":"Nordrhein-Westfalen",
    "wof:name":"Pkb Plan K\u00fcchen-b\u00e4der M\u00f6belvertriebs Gmbh",
    "wof:placetype":"venue"
},
  "geometry": {"coordinates":[8.504447937,51.9796714783],"type":"Point"}
}