{
  "type": "Feature",
  "properties": {
    "iso:country":"DE",
    "sg:address":"Burscheider Str. 61",
    "sg:city":"Leverkusen",
    "sg:phone":"+49 2171/31929",
    "sg:postcode":"51381",
    "sg:province":"Nordrhein-Westfalen",
    "wof:name":"Moll",
    "wof:placetype":"venue"
},
  "geometry": {"coordinates":[7.030945,51.076035],"type":"Point"}
}