{
  "type": "Feature",
  "properties": {
    "iso:country":"DE",
    "sg:address":"Pleicherkirchgasse 8",
    "sg:city":"W\u00fcrzburg",
    "sg:phone":"+49 931/53343",
    "sg:postcode":"97070",
    "sg:province":"Bayern",
    "wof:name":"Willi Vormwald",
    "wof:placetype":"venue"
},
  "geometry": {"coordinates":[9.928023,49.797226],"type":"Point"}
}