{
  "type": "Feature",
  "properties": {
    "iso:country":"DE",
    "sg:address":"Luisenstr. 8",
    "sg:city":"Rostock",
    "sg:phone":"+49 381/52829",
    "sg:postcode":"18119",
    "sg:province":"Mecklenburg-Vorpommern",
    "wof:name":"Restaurant Strandst\u00fcbchen Inh. Hildegard Bu\u00df",
    "wof:placetype":"venue"
},
  "geometry": {"coordinates":[12.1247968674,54.089641571],"type":"Point"}
}