{
  "type": "Feature",
  "properties": {
    "iso:country":"DE",
    "sg:address":"Redder Str. 48",
    "sg:city":"Datteln",
    "sg:phone":"+49 2363/31781",
    "sg:postcode":"45711",
    "sg:province":"Nordrhein-Westfalen",
    "wof:name":"Elektro B\u00fccker Elektro Wilhelm B\u00fccker E. Kfm.",
    "wof:placetype":"venue"
},
  "geometry": {"coordinates":[7.331421,51.657871],"type":"Point"}
}