{
  "type": "Feature",
  "properties": {
    "iso:country":"DE",
    "sg:address":"Jahnstr. 23 a",
    "sg:city":"Queidersbach",
    "sg:postcode":"66851",
    "sg:province":"Rheinland-Pfalz",
    "wof:name":"Gemeindeb\u00fccherei Queidersbach",
    "wof:placetype":"venue"
},
  "geometry": {"coordinates":[7.637817,49.374916],"type":"Point"}
}