{
  "type": "Feature",
  "properties": {
    "iso:country":"DE",
    "sg:address":"Bahnstr. 5",
    "sg:city":"Kelkheim",
    "sg:postcode":"65779",
    "sg:province":"Hessen",
    "wof:name":"Verband Deutscher Makler",
    "wof:placetype":"venue"
},
  "geometry": {"coordinates":[8.4482746124,50.1406517029],"type":"Point"}
}