{
  "type": "Feature",
  "properties": {
    "iso:country":"DE",
    "sg:address":"Im Kleinen M\u00f6lchen 36",
    "sg:city":"Wesseling",
    "sg:phone":"+49 2232/43018",
    "sg:postcode":"50389",
    "sg:province":"Nordrhein-Westfalen",
    "wof:name":"Sport-oase Berzdorf Martina Kautz-luy",
    "wof:placetype":"venue"
},
  "geometry": {"coordinates":[6.941551,50.828579],"type":"Point"}
}