{
  "type": "Feature",
  "properties": {
    "iso:country":"DE",
    "sg:address":"Uhlandstr. 24-28",
    "sg:city":"Chemnitz",
    "sg:phone":"+49 371/4015525",
    "sg:postcode":"09130",
    "sg:province":"Sachsen",
    "wof:name":"Emil Friedmann",
    "wof:placetype":"venue"
},
  "geometry": {"coordinates":[12.9367198944,50.8385887146],"type":"Point"}
}