{
  "type": "Feature",
  "properties": {
    "iso:country":"DE",
    "sg:address":"Farbenweg 4",
    "sg:city":"Detmold",
    "sg:phone":"+49 5231/91490",
    "sg:postcode":"32758",
    "sg:province":"Nordrhein-Westfalen",
    "wof:name":"Teg Technischer Elektro- Gro\u00dfhandel Gmbh",
    "wof:placetype":"venue"
},
  "geometry": {"coordinates":[8.8539047241,51.9442977905],"type":"Point"}
}