{
  "type": "Feature",
  "properties": {
    "iso:country":"DE",
    "sg:address":"Br\u00fccke 3",
    "sg:city":"H\u00fcckeswagen",
    "sg:phone":"+49 2192/92140",
    "sg:postcode":"42499",
    "sg:province":"Nordrhein-Westfalen",
    "wof:name":"H\u00e4ckerstahl Willy H\u00e4cker Gmbh",
    "wof:placetype":"venue"
},
  "geometry": {"coordinates":[7.342771,51.154247],"type":"Point"}
}