{
  "type": "Feature",
  "properties": {
    "iso:country":"DE",
    "sg:address":"Helwigstr. 11",
    "sg:city":"Gro\u00df-Gerau",
    "sg:phone":"+49 6152/4706",
    "sg:postcode":"64521",
    "sg:province":"Hessen",
    "wof:name":"Dorle Thei\u00df",
    "wof:placetype":"venue"
},
  "geometry": {"coordinates":[8.48508358,49.9213180542],"type":"Point"}
}