{
  "type": "Feature",
  "properties": {
    "iso:country":"DE",
    "sg:address":"Mindener Str. 5",
    "sg:city":"Wagenfeld",
    "sg:phone":"+49 5444/241",
    "sg:postcode":"49419",
    "sg:province":"Niedersachsen",
    "wof:name":"Helmut Hartmann",
    "wof:placetype":"venue"
},
  "geometry": {"coordinates":[8.5921649933,52.5468521118],"type":"Point"}
}