{
  "type": "Feature",
  "properties": {
    "iso:country":"DE",
    "sg:address":"Kurpromenade 1",
    "sg:city":"Timmendorfer Strand",
    "sg:postcode":"23669",
    "sg:province":"Schleswig-Holstein",
    "wof:name":"Renata Moden Gmbh",
    "wof:placetype":"venue"
},
  "geometry": {"coordinates":[10.7810678482,53.999206543],"type":"Point"}
}