{
  "type": "Feature",
  "properties": {
    "iso:country":"DE",
    "sg:address":"K\u00f6nigsteiner Str. 1a",
    "sg:city":"Frankfurt",
    "sg:postcode":"65929",
    "sg:province":"Hessen",
    "wof:name":"Metago Handels Gmbh",
    "wof:placetype":"venue"
},
  "geometry": {"coordinates":[8.5495710373,50.1005592346],"type":"Point"}
}