{
  "type": "Feature",
  "properties": {
    "iso:country":"DE",
    "sg:address":"Von-Vincke-Str. 73",
    "sg:city":"Bad Driburg",
    "sg:phone":"+49 5253/2836",
    "sg:postcode":"33014",
    "sg:province":"Nordrhein-Westfalen",
    "wof:name":"Herbert Altmann Steuerbevollm\u00e4chtigter",
    "wof:placetype":"venue"
},
  "geometry": {"coordinates":[9.0186815262,51.7373695374],"type":"Point"}
}