{
  "type": "Feature",
  "properties": {
    "iso:country":"DE",
    "sg:address":"Otto-Carl-Schulz-Str. 1",
    "sg:city":"Amberg",
    "sg:phone":"+49 9621/71702",
    "sg:postcode":"92224",
    "sg:province":"Bayern",
    "wof:name":"Rauh Logistik Gmbh",
    "wof:placetype":"venue"
},
  "geometry": {"coordinates":[11.8854427338,49.439617157],"type":"Point"}
}