{
  "type": "Feature",
  "properties": {
    "iso:country":"DE",
    "sg:address":"M\u00fchlheimer Str. 209",
    "sg:city":"Offenbach",
    "sg:phone":"+49 69/861111",
    "sg:postcode":"63075",
    "sg:province":"Hessen",
    "wof:name":"Fitness-point Inh. Norbert Faller",
    "wof:placetype":"venue"
},
  "geometry": {"coordinates":[8.7948694229,50.109085083],"type":"Point"}
}