{
  "type": "Feature",
  "properties": {
    "iso:country":"DE",
    "sg:address":"Uhlandstr. 37",
    "sg:city":"Niederkr\u00fcchten",
    "sg:phone":"+49 2163/983060",
    "sg:postcode":"41372",
    "sg:province":"Nordrhein-Westfalen",
    "wof:name":"Altenheim St. Laurentius",
    "wof:placetype":"venue"
},
  "geometry": {"coordinates":[6.16577,51.215481],"type":"Point"}
}