{
  "type": "Feature",
  "properties": {
    "iso:country":"DE",
    "sg:address":"Am Bogen 42",
    "sg:city":"M\u00fcnchen-Ottobrunn",
    "sg:phone":"+49 89/6084582",
    "sg:postcode":"85521",
    "sg:province":"Bayern",
    "wof:name":"Kresimir Mikelic - Kameramann",
    "wof:placetype":"venue"
},
  "geometry": {"coordinates":[11.67929,48.061321],"type":"Point"}
}