{
  "type": "Feature",
  "properties": {
    "iso:country":"DE",
    "sg:address":"F\u00e4rbergasse 3",
    "sg:city":"Tittling",
    "sg:phone":"+49 8504/93325",
    "sg:postcode":"94104",
    "sg:province":"Bayern",
    "wof:name":"Karin Baumann",
    "wof:placetype":"venue"
},
  "geometry": {"coordinates":[13.380274,48.727005],"type":"Point"}
}