{
  "type": "Feature",
  "properties": {
    "iso:country":"DE",
    "sg:address":"Hans-B\u00f6ckler-Platz 4",
    "sg:city":"M\u00fclheim",
    "sg:phone":"+49 208/36237",
    "sg:postcode":"45468",
    "sg:province":"Nordrhein-Westfalen",
    "wof:name":"H. Peter Gass Vergn\u00fcgungsst\u00e4tte",
    "wof:placetype":"venue"
},
  "geometry": {"coordinates":[6.887891,51.428917],"type":"Point"}
}