{
  "type": "Feature",
  "properties": {
    "iso:country":"DE",
    "sg:address":"Schillerstr. 9",
    "sg:city":"Herxheim",
    "sg:phone":"+49 7276/1241",
    "sg:postcode":"76863",
    "sg:province":"Rheinland-Pfalz",
    "wof:name":"Valentin Bullinger",
    "wof:placetype":"venue"
},
  "geometry": {"coordinates":[8.2069835663,49.151348114],"type":"Point"}
}