{
  "type": "Feature",
  "properties": {
    "iso:country":"DE",
    "sg:address":"Werkeler Str. 16",
    "sg:city":"Fritzlar",
    "sg:phone":"+49 5622/3165",
    "sg:postcode":"34560",
    "sg:province":"Hessen",
    "wof:name":"Eckhard Berfelde",
    "wof:placetype":"venue"
},
  "geometry": {"coordinates":[9.3184242249,51.1302032471],"type":"Point"}
}