{
  "type": "Feature",
  "properties": {
    "iso:country":"DE",
    "sg:address":"Philipp-Fleck-Str. 15",
    "sg:city":"Frankfurt",
    "sg:phone":"+49 69/775425",
    "sg:postcode":"60486",
    "sg:province":"Hessen",
    "wof:name":"Katholisches Pfarramt St. Pius",
    "wof:placetype":"venue"
},
  "geometry": {"coordinates":[8.6323537827,50.1119155884],"type":"Point"}
}