{
  "type": "Feature",
  "properties": {
    "iso:country":"DE",
    "sg:address":"Gisselberger Str. 27",
    "sg:city":"Marburg",
    "sg:phone":"+49 6421/27745",
    "sg:postcode":"35037",
    "sg:province":"Hessen",
    "wof:name":"Pizzeria Pie",
    "wof:placetype":"venue"
},
  "geometry": {"coordinates":[8.7608108521,50.7963104248],"type":"Point"}
}