{
  "type": "Feature",
  "properties": {
    "iso:country":"DE",
    "sg:address":"Hauptstr. 23",
    "sg:city":"M\u00fcgeln",
    "sg:phone":"+49 35384/412",
    "sg:postcode":"06928",
    "sg:province":"Sachsen-Anhalt",
    "wof:name":"J. Wendt",
    "wof:placetype":"venue"
},
  "geometry": {"coordinates":[13.0298252106,51.8523674011],"type":"Point"}
}