{
  "type": "Feature",
  "properties": {
    "iso:country":"DE",
    "sg:address":"Anton-Flettner-Str.",
    "sg:city":"Raunheim",
    "sg:phone":"+49 6142/94740",
    "sg:postcode":"65479",
    "sg:province":"Hessen",
    "wof:name":"Toom-baumarkt",
    "wof:placetype":"venue"
},
  "geometry": {"coordinates":[8.4423475266,50.0114784241],"type":"Point"}
}