{
  "type": "Feature",
  "properties": {
    "iso:country":"DE",
    "sg:address":"Baaderplatz 2",
    "sg:city":"M\u00fcnchen",
    "sg:phone":"+49 89/220071",
    "sg:postcode":"80469",
    "sg:province":"Bayern",
    "wof:name":"K\u00f6nigsquelle",
    "wof:placetype":"venue"
},
  "geometry": {"coordinates":[11.580247879,48.1321601868],"type":"Point"}
}