{
  "type": "Feature",
  "properties": {
    "iso:country":"DE",
    "sg:address":"Junggasse 13",
    "sg:city":"Grabenstetten",
    "sg:phone":"+49 7382/1065",
    "sg:postcode":"72582",
    "sg:province":"Baden-W\u00fcrttemberg",
    "wof:name":"Raphael Habel Bildhauer",
    "wof:placetype":"venue"
},
  "geometry": {"coordinates":[9.461658,48.524982],"type":"Point"}
}