{
  "type": "Feature",
  "properties": {
    "iso:country":"DE",
    "sg:address":"Marktplatz 17",
    "sg:city":"R\u00f6ttingen",
    "sg:phone":"+49 9338/8282",
    "sg:postcode":"97285",
    "sg:province":"Bayern",
    "wof:name":"Domica Gmbh",
    "wof:placetype":"venue"
},
  "geometry": {"coordinates":[9.96814,49.509529],"type":"Point"}
}