{
  "type": "Feature",
  "properties": {
    "iso:country":"DE",
    "sg:address":"Lilienthalstr. 6",
    "sg:city":"Bielefeld",
    "sg:phone":"+49 5205/3688",
    "sg:postcode":"33689",
    "sg:province":"Nordrhein-Westfalen",
    "wof:name":"Malermeister Kraatz",
    "wof:placetype":"venue"
},
  "geometry": {"coordinates":[8.58316,51.956188],"type":"Point"}
}