{
  "type": "Feature",
  "properties": {
    "iso:country":"DE",
    "sg:address":"Am Wei\u00dfenhof 34",
    "sg:city":"Stuttgart",
    "sg:postcode":"70191",
    "sg:province":"Baden-W\u00fcrttemberg",
    "wof:name":"Chr. Helfferich",
    "wof:placetype":"venue"
},
  "geometry": {"coordinates":[9.1777276993,48.8018074036],"type":"Point"}
}