{
  "type": "Feature",
  "properties": {
    "iso:country":"DE",
    "sg:address":"Falkensteiner Str. 4",
    "sg:city":"Wald",
    "sg:phone":"+49 9408/242",
    "sg:postcode":"93192",
    "sg:province":"Bayern",
    "wof:name":"Josef Meindl",
    "wof:placetype":"venue"
},
  "geometry": {"coordinates":[12.372944,49.105408],"type":"Point"}
}