{
  "type": "Feature",
  "properties": {
    "iso:country":"DE",
    "sg:address":"In der Helle 18 A",
    "sg:city":"Kierspe",
    "sg:phone":"+49 2359/7064",
    "sg:postcode":"58566",
    "sg:province":"Nordrhein-Westfalen",
    "wof:name":"M\u00fcrmann Formenbau Gmbh",
    "wof:placetype":"venue"
},
  "geometry": {"coordinates":[7.587048,51.122608],"type":"Point"}
}