{
  "type": "Feature",
  "properties": {
    "iso:country":"DE",
    "sg:address":"Borchertstr. 48",
    "sg:city":"D\u00fcren",
    "sg:phone":"+49 2421/37040",
    "sg:postcode":"52353",
    "sg:province":"Nordrhein-Westfalen",
    "wof:name":"Pia Berg",
    "wof:placetype":"venue"
},
  "geometry": {"coordinates":[6.48256,50.838848],"type":"Point"}
}