{
  "type": "Feature",
  "properties": {
    "iso:country":"DE",
    "sg:address":"Schiffahrter Damm 21 a",
    "sg:city":"M\u00fcnster",
    "sg:phone":"+49 251/2841164",
    "sg:postcode":"48145",
    "sg:province":"Nordrhein-Westfalen",
    "wof:name":"Hesel-bautr\u00e4ger Gmbh",
    "wof:placetype":"venue"
},
  "geometry": {"coordinates":[7.655685,51.968262],"type":"Point"}
}