{
  "type": "Feature",
  "properties": {
    "iso:country":"DE",
    "sg:address":"Br\u00fcnststr. 10",
    "sg:city":"Hauzenberg",
    "sg:phone":"+49 8586/96090",
    "sg:postcode":"94051",
    "sg:province":"Bayern",
    "wof:name":"Baustoffe Zankl & Co. Ohg",
    "wof:placetype":"venue"
},
  "geometry": {"coordinates":[13.6350698471,48.6239624023],"type":"Point"}
}