{
  "type": "Feature",
  "properties": {
    "iso:country":"DE",
    "sg:address":"Inselstr. 22-26",
    "sg:city":"Leipzig",
    "sg:phone":"+49 341/995950",
    "sg:postcode":"04103",
    "sg:province":"Sachsen",
    "wof:name":"Max-plank-institut F\u00fcr Neuropsychologische",
    "wof:placetype":"venue"
},
  "geometry": {"coordinates":[12.3910779953,51.3414535522],"type":"Point"}
}