{
  "type": "Feature",
  "properties": {
    "iso:country":"DE",
    "sg:address":"Hauptstr. 107",
    "sg:city":"Wunstorf",
    "sg:phone":"+49 5031/71677",
    "sg:postcode":"31515",
    "sg:province":"Niedersachsen",
    "wof:name":"H. Helfers",
    "wof:placetype":"venue"
},
  "geometry": {"coordinates":[9.460341,52.426373],"type":"Point"}
}