{
  "type": "Feature",
  "properties": {
    "iso:country":"DE",
    "sg:address":"K\u00e4rrnergasse 34",
    "sg:city":"Karlstadt",
    "sg:phone":"+49 9353/7018",
    "sg:postcode":"97753",
    "sg:province":"Bayern",
    "wof:name":"L. Henneberger",
    "wof:placetype":"venue"
},
  "geometry": {"coordinates":[9.7627296448,49.9619178772],"type":"Point"}
}