{
  "type": "Feature",
  "properties": {
    "iso:country":"DE",
    "sg:address":"G\u00e4nsefurth",
    "sg:city":"Hecklingen",
    "sg:postcode":"39444",
    "sg:province":"Sachsen-Anhalt",
    "wof:name":"Sport Und Freizeitpark G\u00e4nsefurth Gmbh",
    "wof:placetype":"venue"
},
  "geometry": {"coordinates":[11.5334329605,51.8656463623],"type":"Point"}
}