{
  "type": "Feature",
  "properties": {
    "iso:country":"DE",
    "sg:address":"W\u00fcstenhagener Str. 15a",
    "sg:city":"Remscheid",
    "sg:phone":"+49 2191/31227",
    "sg:postcode":"42855",
    "sg:province":"Nordrhein-Westfalen",
    "wof:name":"Wohnungsbaugenossenschaft Remscheid Egmbh",
    "wof:placetype":"venue"
},
  "geometry": {"coordinates":[7.2289719582,51.1813583374],"type":"Point"}
}