{
  "type": "Feature",
  "properties": {
    "iso:country":"DE",
    "sg:address":"Mittelstr. 21a",
    "sg:city":"Langeoog",
    "sg:phone":"+49 4972/990010",
    "sg:postcode":"26465",
    "sg:province":"Niedersachsen",
    "wof:name":"G\u00e4stehaus Dr. Meyer",
    "wof:placetype":"venue"
},
  "geometry": {"coordinates":[7.4797239304,53.7455825806],"type":"Point"}
}