{
  "type": "Feature",
  "properties": {
    "iso:country":"DE",
    "sg:address":"Hirschbachstr. 40",
    "sg:city":"Aalen",
    "sg:phone":"+49 7361/61478",
    "sg:postcode":"73431",
    "sg:province":"Baden-W\u00fcrttemberg",
    "wof:name":"Karl K\u00f6hler S\u00fc\u00dfwaren- Gro\u00dfhandlung E. K.",
    "wof:placetype":"venue"
},
  "geometry": {"coordinates":[10.0997800827,48.8427658081],"type":"Point"}
}