{
  "type": "Feature",
  "properties": {
    "iso:country":"DE",
    "sg:address":"Linderner Str. 17",
    "sg:city":"Heinsberg",
    "sg:phone":"+49 2452/66982",
    "sg:postcode":"52525",
    "sg:province":"Nordrhein-Westfalen",
    "wof:name":"Sabine Faupel",
    "wof:placetype":"venue"
},
  "geometry": {"coordinates":[6.094702,51.05788],"type":"Point"}
}