{
  "type": "Feature",
  "properties": {
    "iso:country":"DE",
    "sg:address":"Am Spascher Sand 5a",
    "sg:city":"Wildeshausen",
    "sg:postcode":"27793",
    "sg:province":"Niedersachsen",
    "wof:name":"Hc Hilgartner & Partner Gmbh",
    "wof:placetype":"venue"
},
  "geometry": {"coordinates":[8.395484,52.900154],"type":"Point"}
}