{
  "type": "Feature",
  "properties": {
    "iso:country":"DE",
    "sg:address":"Alte Gasse 27-29",
    "sg:city":"Frankfurt",
    "sg:phone":"+49 69/283580",
    "sg:postcode":"60313",
    "sg:province":"Hessen",
    "wof:name":"Gerhard Kempf",
    "wof:placetype":"venue"
},
  "geometry": {"coordinates":[8.6857433319,50.1173591614],"type":"Point"}
}