{
  "type": "Feature",
  "properties": {
    "iso:country":"DE",
    "sg:address":"Bahnhofstr. 26",
    "sg:city":"Wolfratshausen",
    "sg:phone":"+49 8171/41963",
    "sg:postcode":"82515",
    "sg:province":"Bayern",
    "wof:name":"Going Public Media Ag",
    "wof:placetype":"venue"
},
  "geometry": {"coordinates":[11.4261045456,47.9147911072],"type":"Point"}
}