{
  "type": "Feature",
  "properties": {
    "iso:country":"DE",
    "sg:address":"Dr.-B\u00fchner-Str. 15",
    "sg:city":"Sandberg",
    "sg:phone":"+49 9701/1051",
    "sg:postcode":"97657",
    "sg:province":"Bayern",
    "wof:name":"Josef Herbert",
    "wof:placetype":"venue"
},
  "geometry": {"coordinates":[9.9980297089,50.3372154236],"type":"Point"}
}