{
  "type": "Feature",
  "properties": {
    "iso:country":"DE",
    "sg:address":"Neuendorfer Str. 5",
    "sg:city":"Sperenberg",
    "sg:phone":"+49 33703/7271",
    "sg:postcode":"15838",
    "sg:province":"Brandenburg",
    "wof:name":"Klaus Schulze",
    "wof:placetype":"venue"
},
  "geometry": {"coordinates":[13.366294,52.136978],"type":"Point"}
}