{
  "type": "Feature",
  "properties": {
    "iso:country":"DE",
    "sg:address":"Im Schenkelsberg 5",
    "sg:city":"Koblenz",
    "sg:phone":"+49 261/71722",
    "sg:postcode":"56076",
    "sg:province":"Rheinland-Pfalz",
    "wof:name":"Franz-josef Pauly Architekt Und Ingenieur",
    "wof:placetype":"venue"
},
  "geometry": {"coordinates":[7.607834,50.3438],"type":"Point"}
}