{
  "type": "Feature",
  "properties": {
    "iso:country":"DE",
    "sg:address":"Neue Str. 8 Heuberg",
    "sg:city":"Reichenbach",
    "sg:phone":"+49 4974/293940",
    "sg:postcode":"78564",
    "sg:province":"Baden-W\u00fcrttemberg",
    "wof:name":"Fx Marquart Gmbh Pr\u00c4zisions-spannwerkzeuge",
    "wof:placetype":"venue"
},
  "geometry": {"coordinates":[8.791701,48.145863],"type":"Point"}
}