{
  "type": "Feature",
  "properties": {
    "iso:country":"DE",
    "sg:address":"Marktplatz 22",
    "sg:city":"Kastellaun",
    "sg:phone":"+49 6762/8359",
    "sg:postcode":"56288",
    "sg:province":"Rheinland-Pfalz",
    "wof:name":"Markt-apotheke",
    "wof:placetype":"venue"
},
  "geometry": {"coordinates":[7.441712,50.070671],"type":"Point"}
}