{
  "type": "Feature",
  "properties": {
    "iso:country":"DE",
    "sg:address":"Schumannstr. 60",
    "sg:city":"Frankfurt",
    "sg:phone":"+49 69/7982288",
    "sg:postcode":"60325",
    "sg:province":"Hessen",
    "wof:name":"Universit\u00e4t Frankfurt Abt. Verkehrswissenschaft",
    "wof:placetype":"venue"
},
  "geometry": {"coordinates":[8.655464,50.119282],"type":"Point"}
}