{
  "type": "Feature",
  "properties": {
    "iso:country":"DE",
    "sg:address":"Dr.-Hartlaub-Ring 1",
    "sg:city":"Markt Schwaben",
    "sg:phone":"+49 8121/417610",
    "sg:postcode":"85570",
    "sg:province":"Bayern",
    "wof:name":"Pils-pub Didldum",
    "wof:placetype":"venue"
},
  "geometry": {"coordinates":[11.8657951355,48.1951599121],"type":"Point"}
}