{
  "type": "Feature",
  "properties": {
    "iso:country":"DE",
    "sg:address":"Stresemannstr. 52",
    "sg:city":"Bad Wildungen",
    "sg:phone":"+49 5621/4539",
    "sg:postcode":"34537",
    "sg:province":"Hessen",
    "wof:name":"G\u00e4stehaus Stresemann Inh. U. Vaupel",
    "wof:placetype":"venue"
},
  "geometry": {"coordinates":[9.1101751328,51.1090965271],"type":"Point"}
}