{
  "type": "Feature",
  "properties": {
    "iso:country":"DE",
    "sg:address":"Zur Feldm\u00fchle 20",
    "sg:city":"Arnsberg",
    "sg:phone":"+49 2931/10341",
    "sg:postcode":"59821",
    "sg:province":"Nordrhein-Westfalen",
    "wof:name":"Gerhard Brasch",
    "wof:placetype":"venue"
},
  "geometry": {"coordinates":[8.071424,51.39439],"type":"Point"}
}