{
  "type": "Feature",
  "properties": {
    "iso:country":"DE",
    "sg:address":"Reichertstr. 10",
    "sg:city":"G\u00f6rlitz",
    "sg:phone":"+49 3581/401737",
    "sg:postcode":"02826",
    "sg:province":"Sachsen",
    "wof:name":"Blumengesch\u00e4fte Der Nei\u00dfestadt G\u00f6rlitz",
    "wof:placetype":"venue"
},
  "geometry": {"coordinates":[14.969707,51.143738],"type":"Point"}
}