{
  "type": "Feature",
  "properties": {
    "iso:country":"DE",
    "sg:address":"R\u00f6dgener Str. 2",
    "sg:city":"Wegberg",
    "sg:phone":"+49 2436/888",
    "sg:postcode":"41844",
    "sg:province":"Nordrhein-Westfalen",
    "wof:name":"Wolfgang Gott Steuerberater",
    "wof:placetype":"venue"
},
  "geometry": {"coordinates":[6.1879720688,51.1431427002],"type":"Point"}
}