{
  "type": "Feature",
  "properties": {
    "iso:country":"DE",
    "sg:address":"G\u00fcterbahnhofstr 48",
    "sg:city":"Kamenz",
    "sg:phone":"+49 2224/94560",
    "sg:postcode":"01917",
    "sg:province":"Sachsen",
    "wof:name":"T\u00fcren Fenster Wiedmann Gmbh",
    "wof:placetype":"venue"
},
  "geometry": {"coordinates":[7.228112,50.628803],"type":"Point"}
}