{
  "type": "Feature",
  "properties": {
    "iso:country":"DE",
    "sg:address":"Ro\u00dfbergstr. 13",
    "sg:city":"Kusterdingen",
    "sg:phone":"+49 7071/34470",
    "sg:postcode":"72127",
    "sg:province":"Baden-W\u00fcrttemberg",
    "wof:name":"W. Braun",
    "wof:placetype":"venue"
},
  "geometry": {"coordinates":[9.1300315857,48.5033340454],"type":"Point"}
}