{
  "type": "Feature",
  "properties": {
    "iso:country":"DE",
    "sg:address":"Hans-B\u00f6ckler-Str. 15",
    "sg:city":"Willich",
    "sg:phone":"+49 2154/428491",
    "sg:postcode":"47877",
    "sg:province":"Nordrhein-Westfalen",
    "wof:name":"Deutsche Wheelabrator Strahlmittel Gmbh",
    "wof:placetype":"venue"
},
  "geometry": {"coordinates":[6.513655,51.277012],"type":"Point"}
}