{
  "type": "Feature",
  "properties": {
    "iso:country":"DE",
    "sg:address":"Sch\u00f6nrather Str. 141",
    "sg:city":"R\u00f6srath",
    "sg:phone":"+49 2205/7817",
    "sg:postcode":"51503",
    "sg:province":"Nordrhein-Westfalen",
    "wof:name":"Hotel Zum H\u00e4uschen",
    "wof:placetype":"venue"
},
  "geometry": {"coordinates":[7.1959409714,50.8895606995],"type":"Point"}
}