{
  "type": "Feature",
  "properties": {
    "iso:country":"DE",
    "sg:address":"Kreuzstr. 2",
    "sg:city":"Odelzhausen",
    "sg:phone":"+49 8134/99880",
    "sg:postcode":"85235",
    "sg:province":"Bayern",
    "wof:name":"Golfanlage M\u00fcnchen-west Odelzhausen Gmbh & Co.",
    "wof:placetype":"venue"
},
  "geometry": {"coordinates":[11.2101612091,48.2969894409],"type":"Point"}
}