{
  "type": "Feature",
  "properties": {
    "iso:country":"DE",
    "sg:address":"Erbprinzenstr. 1",
    "sg:city":"Karlsruhe",
    "sg:postcode":"76133",
    "sg:province":"Baden-W\u00fcrttemberg",
    "wof:name":"Generic.de Gesellschaft F\u00fcr Networking Und Internet",
    "wof:placetype":"venue"
},
  "geometry": {"coordinates":[8.4030704498,49.0069236755],"type":"Point"}
}