{
  "type": "Feature",
  "properties": {
    "iso:country":"DE",
    "sg:address":"Hundersingerstr. 21",
    "sg:city":"Emerkingen",
    "sg:phone":"+49 7393/1095",
    "sg:postcode":"89607",
    "sg:province":"Baden-W\u00fcrttemberg",
    "wof:name":"Albert Fiderer Lebensmittel",
    "wof:placetype":"venue"
},
  "geometry": {"coordinates":[9.658654213,48.2122612],"type":"Point"}
}