{
  "type": "Feature",
  "properties": {
    "iso:country":"DE",
    "sg:address":"Me\u00dfkircher Str. 34",
    "sg:city":"Krauchenwies",
    "sg:phone":"+49 7576/7135",
    "sg:postcode":"72505",
    "sg:province":"Baden-W\u00fcrttemberg",
    "wof:name":"Hermann Kern",
    "wof:placetype":"venue"
},
  "geometry": {"coordinates":[9.1925315857,48.0032501221],"type":"Point"}
}