{
  "type": "Feature",
  "properties": {
    "iso:country":"DE",
    "sg:address":"In Viehberg 6",
    "sg:city":"Ammerthal",
    "sg:phone":"+49 9628/370",
    "sg:postcode":"92260",
    "sg:province":"Bayern",
    "wof:name":"C & C Berg Beteiligungs- Gesellschaft Mbh",
    "wof:placetype":"venue"
},
  "geometry": {"coordinates":[11.75771,49.431736],"type":"Point"}
}