{
  "type": "Feature",
  "properties": {
    "iso:country":"DE",
    "sg:address":"Emsstr. 13",
    "sg:city":"Oldenburg",
    "sg:phone":"+49 441/925770",
    "sg:postcode":"26135",
    "sg:province":"Niedersachsen",
    "wof:name":"Who Beteiligungs- Verwaltungs- Und Vertriebs Gmbh",
    "wof:placetype":"venue"
},
  "geometry": {"coordinates":[8.230389595,53.1381111145],"type":"Point"}
}