{
  "type": "Feature",
  "properties": {
    "iso:country":"DE",
    "sg:address":"Sch\u00f6nborner Str. 10",
    "sg:city":"Liegau-Augustusbad",
    "sg:phone":"+49 3528/447297",
    "sg:postcode":"01465",
    "sg:province":"Sachsen",
    "wof:name":"G\u00fcnther Just",
    "wof:placetype":"venue"
},
  "geometry": {"coordinates":[13.8782672882,51.1373138428],"type":"Point"}
}