{
  "type": "Feature",
  "properties": {
    "iso:country":"DE",
    "sg:address":"Bahnhofstr. 32",
    "sg:city":"Wesseling",
    "sg:phone":"+49 2236/42979",
    "sg:postcode":"50389",
    "sg:province":"Nordrhein-Westfalen",
    "wof:name":"Karl Grabowski",
    "wof:placetype":"venue"
},
  "geometry": {"coordinates":[6.979786,50.824032],"type":"Point"}
}