{
  "type": "Feature",
  "properties": {
    "iso:country":"DE",
    "sg:address":"Kamenzer Str. 5",
    "sg:city":"Bernsdorf",
    "sg:phone":"+49 35723/29689",
    "sg:postcode":"02994",
    "sg:province":"Sachsen",
    "wof:name":"H. Anders",
    "wof:placetype":"venue"
},
  "geometry": {"coordinates":[14.065359,51.368465],"type":"Point"}
}