{
  "type": "Feature",
  "properties": {
    "iso:country":"DE",
    "sg:address":"Ottonenstr.1",
    "sg:city":"Geldersheim",
    "sg:postcode":"97505",
    "sg:province":"Bayern",
    "wof:name":"Bauchtanz - Kunst Mit Naime",
    "wof:placetype":"venue"
},
  "geometry": {"coordinates":[10.161717,50.039917],"type":"Point"}
}