{
  "type": "Feature",
  "properties": {
    "iso:country":"DE",
    "sg:address":"Meisenweg 36",
    "sg:city":"Ahrensburg",
    "sg:phone":"+49 4102/53876",
    "sg:postcode":"22926",
    "sg:province":"Schleswig-Holstein",
    "wof:name":"G\u00fcnter Siegmund Mineral\u00f6le Gmbh",
    "wof:placetype":"venue"
},
  "geometry": {"coordinates":[10.2305736542,53.6469039917],"type":"Point"}
}