{
  "type": "Feature",
  "properties": {
    "iso:country":"DE",
    "sg:address":"Wachauer Str. 1",
    "sg:city":"Leipzig",
    "sg:postcode":"04299",
    "sg:province":"Sachsen",
    "wof:name":"Dr. Med. Brigitte Krosse",
    "wof:placetype":"venue"
},
  "geometry": {"coordinates":[12.418144,51.312954],"type":"Point"}
}