{
  "type": "Feature",
  "properties": {
    "iso:country":"DE",
    "sg:address":"Wesloer Landstr. 76",
    "sg:city":"L\u00fcbeck",
    "sg:phone":"+49 451/63985",
    "sg:postcode":"23566",
    "sg:province":"Schleswig-Holstein",
    "wof:name":"Gr\u00fcner Winkel",
    "wof:placetype":"venue"
},
  "geometry": {"coordinates":[10.7622337341,53.8745536804],"type":"Point"}
}