{
  "type": "Feature",
  "properties": {
    "iso:country":"DE",
    "sg:address":"Hagenbrook 2",
    "sg:city":"Steinfurt",
    "sg:phone":"+49 2552/3238",
    "sg:postcode":"48565",
    "sg:province":"Nordrhein-Westfalen",
    "wof:name":"Alfred Fl\u00fcgemann",
    "wof:placetype":"venue"
},
  "geometry": {"coordinates":[7.396461,52.120731],"type":"Point"}
}