{
  "type": "Feature",
  "properties": {
    "iso:country":"DE",
    "sg:address":"Gehrenberg 16",
    "sg:city":"Herford",
    "sg:phone":"+49 5221/57892",
    "sg:postcode":"32052",
    "sg:province":"Nordrhein-Westfalen",
    "wof:name":"Leos Jeans",
    "wof:placetype":"venue"
},
  "geometry": {"coordinates":[8.6729640961,52.1149215698],"type":"Point"}
}