{
  "type": "Feature",
  "properties": {
    "iso:country":"DE",
    "sg:address":"Kreisstr. 258",
    "sg:city":"Selm",
    "sg:phone":"+49 2592/61555",
    "sg:postcode":"59379",
    "sg:province":"Nordrhein-Westfalen",
    "wof:name":"Alfred Eschenmann Rechtsanwalt Und Notar",
    "wof:placetype":"venue"
},
  "geometry": {"coordinates":[7.4691700935,51.6704406738],"type":"Point"}
}