{
  "type": "Feature",
  "properties": {
    "iso:country":"DE",
    "sg:address":"Schlo\u00dfstr. 3",
    "sg:city":"Haigerloch",
    "sg:phone":"+49 7474/6930",
    "sg:postcode":"72401",
    "sg:province":"Baden-W\u00fcrttemberg",
    "wof:name":"Hotel Gastschlo\u00df Haigerloch",
    "wof:placetype":"venue"
},
  "geometry": {"coordinates":[8.8042860031,48.3695144653],"type":"Point"}
}