{
  "type": "Feature",
  "properties": {
    "iso:country":"DE",
    "sg:address":"Osterort 18",
    "sg:city":"Stemwede",
    "sg:phone":"+49 5474/369",
    "sg:postcode":"32351",
    "sg:province":"Nordrhein-Westfalen",
    "wof:name":"Wilhelm Meyer",
    "wof:placetype":"venue"
},
  "geometry": {"coordinates":[8.387888,52.434917],"type":"Point"}
}