{
  "type": "Feature",
  "properties": {
    "iso:country":"DE",
    "sg:address":"Wacholderweg 23",
    "sg:city":"Waldenbuch",
    "sg:phone":"+49 7157/7169",
    "sg:postcode":"71111",
    "sg:province":"Baden-W\u00fcrttemberg",
    "wof:name":"Albrecht Wezel",
    "wof:placetype":"venue"
},
  "geometry": {"coordinates":[9.156355,48.630878],"type":"Point"}
}