{
  "type": "Feature",
  "properties": {
    "iso:country":"DE",
    "sg:address":"N\u00fcrnberger Str. 35",
    "sg:city":"Hanau",
    "sg:phone":"+49 6181/927182",
    "sg:postcode":"63450",
    "sg:province":"Hessen",
    "wof:name":"Rancon Gmbh",
    "wof:placetype":"venue"
},
  "geometry": {"coordinates":[8.918962,50.132252],"type":"Point"}
}