{
  "type": "Feature",
  "properties": {
    "iso:country":"DE",
    "sg:address":"S\u00e4ntisstr. 68",
    "sg:city":"Berlin",
    "sg:phone":"+49 661/73985",
    "sg:postcode":"12277",
    "sg:province":"Berlin",
    "wof:name":"Ludwig Will Steuerbevollm\u00e4chtigter",
    "wof:placetype":"venue"
},
  "geometry": {"coordinates":[13.3881511688,52.4186439514],"type":"Point"}
}