{
  "type": "Feature",
  "properties": {
    "iso:country":"DE",
    "sg:address":"Handorfer Str. 13",
    "sg:city":"M\u00fcnster",
    "sg:phone":"+49 251/329242",
    "sg:postcode":"48157",
    "sg:province":"Nordrhein-Westfalen",
    "wof:name":"Volksbank M\u00fcnster Eg",
    "wof:placetype":"venue"
},
  "geometry": {"coordinates":[7.70309,51.981091],"type":"Point"}
}