{
  "type": "Feature",
  "properties": {
    "iso:country":"DE",
    "sg:address":"Gro\u00dfe Schmiedestr. 18",
    "sg:city":"Stade",
    "sg:phone":"+49 4141/2467",
    "sg:postcode":"21682",
    "sg:province":"Niedersachsen",
    "wof:name":"Buchholz Pelze Inh. Gottfried Sass",
    "wof:placetype":"venue"
},
  "geometry": {"coordinates":[9.477234,53.599998],"type":"Point"}
}