{
  "type": "Feature",
  "properties": {
    "iso:country":"DE",
    "sg:address":"Papierstr. 10",
    "sg:city":"Berlin",
    "sg:phone":"+49 30/4919095",
    "sg:postcode":"13409",
    "sg:province":"Berlin",
    "wof:name":"Kryolan Gmbh",
    "wof:placetype":"venue"
},
  "geometry": {"coordinates":[13.3796653748,52.564666748],"type":"Point"}
}