{
  "type": "Feature",
  "properties": {
    "iso:country":"DE",
    "sg:address":"Eichenweg 2",
    "sg:city":"Kevelaer",
    "sg:phone":"+49 2832/3536",
    "sg:postcode":"47625",
    "sg:province":"Nordrhein-Westfalen",
    "wof:name":"Ernst Roeling",
    "wof:placetype":"venue"
},
  "geometry": {"coordinates":[6.256455,51.540737],"type":"Point"}
}