{
  "type": "Feature",
  "properties": {
    "iso:country":"DE",
    "sg:address":"Am D\u00fcsterbarg 1b",
    "sg:city":"Wittenbeck",
    "sg:phone":"+49 38293/15550",
    "sg:postcode":"18209",
    "sg:province":"Mecklenburg-Vorpommern",
    "wof:name":"D\u00fcsterbarg Bautr\u00e4ger- Und Grundst\u00fccks Gmbh",
    "wof:placetype":"venue"
},
  "geometry": {"coordinates":[11.789432,54.131561],"type":"Point"}
}