{
  "type": "Feature",
  "properties": {
    "iso:country":"DE",
    "sg:address":"Otto-Braun-Str. 90",
    "sg:city":"Berlin",
    "sg:phone":"+49 30/24744228",
    "sg:postcode":"10249",
    "sg:province":"Berlin",
    "wof:name":"Ostdeutsche Sparkassenstiftung",
    "wof:placetype":"venue"
},
  "geometry": {"coordinates":[13.4231681824,52.5273971558],"type":"Point"}
}