{
  "type": "Feature",
  "properties": {
    "iso:country":"DE",
    "sg:address":"Luitpoldstr. 7",
    "sg:city":"Erlangen",
    "sg:phone":"+49 9131/206584",
    "sg:postcode":"91054",
    "sg:province":"Bayern",
    "wof:name":"Sigrid Oriwol Krankengymnastin",
    "wof:placetype":"venue"
},
  "geometry": {"coordinates":[11.013967,49.596542],"type":"Point"}
}