{
  "type": "Feature",
  "properties": {
    "iso:country":"DE",
    "sg:address":"Stettiner Chaussee 12",
    "sg:city":"Penkun",
    "sg:phone":"+49 39751/60392",
    "sg:postcode":"17328",
    "sg:province":"Mecklenburg-Vorpommern",
    "wof:name":"Siegfried Zuppke",
    "wof:placetype":"venue"
},
  "geometry": {"coordinates":[14.242438,53.299011],"type":"Point"}
}