{
  "type": "Feature",
  "properties": {
    "iso:country":"DE",
    "sg:address":"Steilshooper Str. 27",
    "sg:city":"Hamburg",
    "sg:phone":"+49 40/297293",
    "sg:postcode":"22305",
    "sg:province":"Hamburg",
    "wof:name":"Badczong & Rinck Gmbh",
    "wof:placetype":"venue"
},
  "geometry": {"coordinates":[10.048243,53.586044],"type":"Point"}
}