{
  "type": "Feature",
  "properties": {
    "iso:country":"DE",
    "sg:address":"Gaster Landweg 6",
    "sg:city":"Lotte",
    "sg:phone":"+49 5405/94256",
    "sg:postcode":"49504",
    "sg:province":"Nordrhein-Westfalen",
    "wof:name":"Landcaf\u00e9 Am Goldbach",
    "wof:placetype":"venue"
},
  "geometry": {"coordinates":[7.940318,52.267208],"type":"Point"}
}