{
  "type": "Feature",
  "properties": {
    "iso:country":"DE",
    "sg:address":"Ahren 40",
    "sg:city":"M\u00f6nchengladbach",
    "sg:phone":"+49 2166/82136",
    "sg:postcode":"41238",
    "sg:province":"Nordrhein-Westfalen",
    "wof:name":"Dietmar Schilz Gmbh",
    "wof:placetype":"venue"
},
  "geometry": {"coordinates":[6.4806790352,51.153175354],"type":"Point"}
}