{
  "type": "Feature",
  "properties": {
    "iso:country":"DE",
    "sg:city":"M\u00fcnchen",
    "sg:phone":"+49 89/64289189",
    "sg:postcode":"81545",
    "sg:province":"Bayern",
    "wof:name":"Fotos-online.de, Koch & Wolf, Fotografie & Archiv",
    "wof:placetype":"venue"
},
  "geometry": {"coordinates":[11.562337,48.095711],"type":"Point"}
}