{
  "type": "Feature",
  "properties": {
    "iso:country":"DE",
    "sg:address":"Bahnhofstr. 66",
    "sg:city":"Gro\u00dfenkneten",
    "sg:phone":"+49 4487/7005",
    "sg:postcode":"26197",
    "sg:province":"Niedersachsen",
    "wof:name":"Doris Spreckelmeyer",
    "wof:placetype":"venue"
},
  "geometry": {"coordinates":[8.279687,52.990406],"type":"Point"}
}