{
  "type": "Feature",
  "properties": {
    "iso:country":"DE",
    "sg:address":"Gustav-Schwab-Str. 41",
    "sg:city":"Reutlingen",
    "sg:phone":"+49 7121/239286",
    "sg:postcode":"72762",
    "sg:province":"Baden-W\u00fcrttemberg",
    "wof:name":"Agip Deutschland Ag",
    "wof:placetype":"venue"
},
  "geometry": {"coordinates":[9.1936635971,48.4874382019],"type":"Point"}
}