{
  "type": "Feature",
  "properties": {
    "iso:country":"DE",
    "sg:address":"Wallstr 34",
    "sg:city":"Velbert",
    "sg:phone":"+49 2051/252142",
    "sg:postcode":"42551",
    "sg:province":"Nordrhein-Westfalen",
    "wof:name":"Walitzki Gmbh & Co Kg",
    "wof:placetype":"venue"
},
  "geometry": {"coordinates":[7.056028,51.333702],"type":"Point"}
}