{
  "type": "Feature",
  "properties": {
    "iso:country":"DE",
    "sg:address":"Am Holzbach 46",
    "sg:city":"Rheda-Wiedenbr\u00fcck",
    "sg:phone":"+49 5242/967077",
    "sg:postcode":"33378",
    "sg:province":"Nordrhein-Westfalen",
    "wof:name":"Karl-heinz Mettenborg Steuerberater",
    "wof:placetype":"venue"
},
  "geometry": {"coordinates":[8.2887992859,51.8610572815],"type":"Point"}
}