{
  "type": "Feature",
  "properties": {
    "iso:country":"DE",
    "sg:address":"Auf der Worth 11",
    "sg:city":"Liebenburg",
    "sg:phone":"+49 5346/94135",
    "sg:postcode":"38704",
    "sg:province":"Niedersachsen",
    "wof:name":"Ralf Bienwald",
    "wof:placetype":"venue"
},
  "geometry": {"coordinates":[10.398105,51.970592],"type":"Point"}
}