{
  "type": "Feature",
  "properties": {
    "iso:country":"DE",
    "sg:address":"Ziegelstr. 3a",
    "sg:city":"Kandern",
    "sg:phone":"+49 7626/971716",
    "sg:postcode":"79400",
    "sg:province":"Baden-W\u00fcrttemberg",
    "wof:name":"Thomas Krauss",
    "wof:placetype":"venue"
},
  "geometry": {"coordinates":[7.661764,47.715057],"type":"Point"}
}