{
  "type": "Feature",
  "properties": {
    "iso:country":"DE",
    "sg:address":"Spiesheimer Weg",
    "sg:city":"R\u00f6thlein",
    "sg:postcode":"97520",
    "sg:province":"Bayern",
    "wof:name":"Bas Baustoff-aufbereitung Schweinfurt Gmbh",
    "wof:placetype":"venue"
},
  "geometry": {"coordinates":[10.2210950851,49.9852867126],"type":"Point"}
}