{
  "type": "Feature",
  "properties": {
    "iso:country":"DE",
    "sg:address":"Osteriede 12",
    "sg:city":"Hannover / Garbsen",
    "sg:phone":"+49 5131",
    "sg:postcode":"30449",
    "sg:province":"Niedersachsen",
    "wof:name":"Inegenieurb\u00fcro Schmidtke",
    "wof:placetype":"venue"
},
  "geometry": {"coordinates":[9.71561,52.36182],"type":"Point"}
}