{
  "type": "Feature",
  "properties": {
    "iso:country":"DE",
    "sg:address":"Westiger Str. 62",
    "sg:city":"Altena",
    "sg:phone":"+49 2352/20190",
    "sg:postcode":"58762",
    "sg:province":"Nordrhein-Westfalen",
    "wof:name":"Nedschroef Altena Gmbh",
    "wof:placetype":"venue"
},
  "geometry": {"coordinates":[7.694427,51.300442],"type":"Point"}
}