{
  "type": "Feature",
  "properties": {
    "iso:country":"DE",
    "sg:address":"Postfach 2120",
    "sg:city":"Meinerzhagen",
    "sg:postcode":"58534",
    "sg:province":"Nordrhein-Westfalen",
    "wof:name":"Quelle Gro\u00dfversandhaus",
    "wof:placetype":"venue"
},
  "geometry": {"coordinates":[7.6401700974,51.1067085266],"type":"Point"}
}