{
  "type": "Feature",
  "properties": {
    "iso:country":"DE",
    "sg:address":"Sch\u00f6mbsstr. 19",
    "sg:city":"R\u00f6dermark",
    "sg:phone":"+49 6074/67271",
    "sg:postcode":"63322",
    "sg:province":"Hessen",
    "wof:name":"Erich Rosskopf Architekt",
    "wof:placetype":"venue"
},
  "geometry": {"coordinates":[8.802019,49.966354],"type":"Point"}
}