{
  "type": "Feature",
  "properties": {
    "iso:country":"DE",
    "sg:address":"Hermannstr. 81",
    "sg:city":"Dortmund",
    "sg:phone":"+49 231/432714",
    "sg:postcode":"44263",
    "sg:province":"Nordrhein-Westfalen",
    "wof:name":"Cnc Gmbh Communication And Network Consulting",
    "wof:placetype":"venue"
},
  "geometry": {"coordinates":[7.5044398308,51.4894866943],"type":"Point"}
}