{
  "type": "Feature",
  "properties": {
    "iso:country":"DE",
    "sg:address":"In der Laier 9",
    "sg:city":"Neuenb\u00fcrg",
    "sg:phone":"+49 7082/3435",
    "sg:postcode":"75305",
    "sg:province":"Baden-W\u00fcrttemberg",
    "wof:name":"Otto Wankm\u00fcller Architekt",
    "wof:placetype":"venue"
},
  "geometry": {"coordinates":[8.570763,48.860359],"type":"Point"}
}