{
  "type": "Feature",
  "properties": {
    "iso:country":"DE",
    "sg:address":"Carl-Friedrich-Benz-Str 11-13",
    "sg:city":"Delitzsch",
    "sg:phone":"+49 34202/64999",
    "sg:postcode":"04509",
    "sg:province":"Sachsen",
    "wof:name":"Silbertaler Fleischwaren Gmbh",
    "wof:placetype":"venue"
},
  "geometry": {"coordinates":[12.354651,51.529301],"type":"Point"}
}