{
  "type": "Feature",
  "properties": {
    "iso:country":"DE",
    "sg:address":"Stra\u00dfe der Einheit 169",
    "sg:city":"Gelenau",
    "sg:phone":"+49 37297/7365",
    "sg:postcode":"09423",
    "sg:province":"Sachsen",
    "wof:name":"Gelenauer Baufachmarkt M\u00fcller & Duus Gbr",
    "wof:placetype":"venue"
},
  "geometry": {"coordinates":[12.9599637985,50.7097129822],"type":"Point"}
}