{
  "type": "Feature",
  "properties": {
    "iso:country":"DE",
    "sg:address":"Holtenklinker Str. 104",
    "sg:city":"Hamburg",
    "sg:postcode":"21029",
    "sg:province":"Hamburg",
    "wof:name":"Hiba Hamburger Immobilien Und Bautr\u00e4ger Ag",
    "wof:placetype":"venue"
},
  "geometry": {"coordinates":[10.224107,53.481903],"type":"Point"}
}