{
  "type": "Feature",
  "properties": {
    "iso:country":"DE",
    "sg:address":"Martinistr. 12",
    "sg:city":"Greven",
    "sg:phone":"+49 2571/3461",
    "sg:postcode":"48268",
    "sg:province":"Nordrhein-Westfalen",
    "wof:name":"M\u00f6ller & Fieker Ohg Jeans- U. Freizeitbekleidung",
    "wof:placetype":"venue"
},
  "geometry": {"coordinates":[7.610195,52.093491],"type":"Point"}
}