{
  "type": "Feature",
  "properties": {
    "iso:country":"DE",
    "sg:address":"David-Ricardo-Str. 16",
    "sg:city":"Achim",
    "sg:phone":"+49 4942/1483211",
    "sg:postcode":"28832",
    "sg:province":"Niedersachsen",
    "wof:name":"Carl Klatt",
    "wof:placetype":"venue"
},
  "geometry": {"coordinates":[8.976907,53.040058],"type":"Point"}
}