{
  "type": "Feature",
  "properties": {
    "iso:country":"DE",
    "sg:address":"L\u00fcdinghauser Strasse 24 a",
    "sg:city":"M\u00fcnster",
    "sg:phone":"+49 251",
    "sg:postcode":"48163",
    "sg:province":"Nordrhein-Westfalen",
    "wof:name":"Professional Call Center",
    "wof:placetype":"venue"
},
  "geometry": {"coordinates":[7.605222,51.93449],"type":"Point"}
}