{
  "type": "Feature",
  "properties": {
    "iso:country":"DE",
    "sg:address":"Meringer Str. 1",
    "sg:city":"Weil",
    "sg:phone":"+49 8195/231",
    "sg:postcode":"86947",
    "sg:province":"Bayern",
    "wof:name":"Ulrich Probst Heigl",
    "wof:placetype":"venue"
},
  "geometry": {"coordinates":[10.9219970703,48.1172981262],"type":"Point"}
}