{
  "type": "Feature",
  "properties": {
    "iso:country":"DE",
    "sg:address":"Ligusterweg 4",
    "sg:city":"Sontra",
    "sg:phone":"+49 5653/5948",
    "sg:postcode":"36205",
    "sg:province":"Hessen",
    "wof:name":"Elke R\u00f6ssler",
    "wof:placetype":"venue"
},
  "geometry": {"coordinates":[9.9286737442,51.106464386],"type":"Point"}
}