{
  "type": "Feature",
  "properties": {
    "iso:country":"DE",
    "sg:address":"Weinbrunn 1",
    "sg:city":"Hasselfelde",
    "sg:postcode":"38899",
    "sg:province":"Sachsen-Anhalt",
    "wof:name":"Einfamilienh\u00e4user - H 110",
    "wof:placetype":"venue"
},
  "geometry": {"coordinates":[10.851332,51.692162],"type":"Point"}
}