{
  "type": "Feature",
  "properties": {
    "iso:country":"DE",
    "sg:address":"Gro\u00dfe Gasse 14",
    "sg:city":"Sch\u00f6naich",
    "sg:phone":"+49 7031/653544",
    "sg:postcode":"71101",
    "sg:province":"Baden-W\u00fcrttemberg",
    "wof:name":"Gerhard Ratz",
    "wof:placetype":"venue"
},
  "geometry": {"coordinates":[9.062283,48.655975],"type":"Point"}
}