{
  "type": "Feature",
  "properties": {
    "iso:country":"DE",
    "sg:address":"Bucher Weg",
    "sg:city":"Wanzleben",
    "sg:phone":"+49 39209/4790",
    "sg:postcode":"39164",
    "sg:province":"Sachsen-Anhalt",
    "wof:name":"Wanzleber Agrar-service Und Transport Gmbh",
    "wof:placetype":"venue"
},
  "geometry": {"coordinates":[11.4508800507,52.0627784729],"type":"Point"}
}