{
  "type": "Feature",
  "properties": {
    "iso:country":"DE",
    "sg:address":"Wittelsbacherallee 26",
    "sg:city":"Frankfurt",
    "sg:phone":"+49 69/4909747",
    "sg:postcode":"60316",
    "sg:province":"Hessen",
    "wof:name":"Detlev Louis Motorrad- Vertriebsgesellschaft Mbh",
    "wof:placetype":"venue"
},
  "geometry": {"coordinates":[8.7030134201,50.1192474365],"type":"Point"}
}