{
  "type": "Feature",
  "properties": {
    "iso:country":"DE",
    "sg:address":"Haselweg 5",
    "sg:city":"Gerstetten",
    "sg:phone":"+49 7324/8989",
    "sg:postcode":"89547",
    "sg:province":"Baden-W\u00fcrttemberg",
    "wof:name":"Manfred Sch\u00f6fer",
    "wof:placetype":"venue"
},
  "geometry": {"coordinates":[10.1182432175,48.5980529785],"type":"Point"}
}