{
  "type": "Feature",
  "properties": {
    "iso:country":"DE",
    "sg:address":"Friedrichsfelder Str. 28",
    "sg:city":"Voerde",
    "sg:phone":"+49 2855/96320",
    "sg:postcode":"46562",
    "sg:province":"Nordrhein-Westfalen",
    "wof:name":"Deutsche Verm\u00f6gensberatung Ag",
    "wof:placetype":"venue"
},
  "geometry": {"coordinates":[6.6836028099,51.5982322693],"type":"Point"}
}