{
  "type": "Feature",
  "properties": {
    "iso:country":"DE",
    "sg:address":"Bachzimmerer Str. 36",
    "sg:city":"Immendingen",
    "sg:phone":"+49 7462/1799",
    "sg:postcode":"78194",
    "sg:province":"Baden-W\u00fcrttemberg",
    "wof:name":"B. Zeller-jochum",
    "wof:placetype":"venue"
},
  "geometry": {"coordinates":[8.705124855,47.9578399658],"type":"Point"}
}