{
  "type": "Feature",
  "properties": {
    "iso:country":"DE",
    "sg:address":"Wachtendonker Str. 3",
    "sg:city":"Wachtendonk",
    "sg:phone":"+49 2836/224",
    "sg:postcode":"47669",
    "sg:province":"Nordrhein-Westfalen",
    "wof:name":"Haus Peuten",
    "wof:placetype":"venue"
},
  "geometry": {"coordinates":[6.3068008423,51.4014587402],"type":"Point"}
}