{
  "type": "Feature",
  "properties": {
    "iso:country":"DE",
    "sg:address":"Hochstr. 214",
    "sg:city":"Duisburg",
    "sg:phone":"+49 2065/76364",
    "sg:postcode":"47228",
    "sg:province":"Nordrhein-Westfalen",
    "wof:name":"Dirk Theisejans Gmbh",
    "wof:placetype":"venue"
},
  "geometry": {"coordinates":[6.6854438782,51.4210586548],"type":"Point"}
}