{
  "type": "Feature",
  "properties": {
    "iso:country":"DE",
    "sg:address":"Steinstr. 11",
    "sg:city":"Brandenburg",
    "sg:phone":"+49 3381/225276",
    "sg:postcode":"14776",
    "sg:province":"Brandenburg",
    "wof:name":"Foto Erhardt Gmbh",
    "wof:placetype":"venue"
},
  "geometry": {"coordinates":[12.562376976,52.408531189],"type":"Point"}
}