{
  "type": "Feature",
  "properties": {
    "iso:country":"DE",
    "sg:address":"Horster Str. 341",
    "sg:city":"Gladbeck",
    "sg:postcode":"45968",
    "sg:province":"Nordrhein-Westfalen",
    "wof:name":"Kath. \u00f6ffentliche Bibliothek St. Marien",
    "wof:placetype":"venue"
},
  "geometry": {"coordinates":[7.012061,51.547745],"type":"Point"}
}