{
  "type": "Feature",
  "properties": {
    "iso:country":"DE",
    "sg:address":"Friesenstr. 1",
    "sg:city":"Ludwigsburg",
    "sg:phone":"+49 7141/862149",
    "sg:postcode":"71640",
    "sg:province":"Baden-W\u00fcrttemberg",
    "wof:name":"Kunzi",
    "wof:placetype":"venue"
},
  "geometry": {"coordinates":[9.227054,48.893139],"type":"Point"}
}