{
  "type": "Feature",
  "properties": {
    "iso:country":"DE",
    "sg:address":"Philippsburger Str. 2",
    "sg:city":"Philippsburg",
    "sg:phone":"+49 7256/286",
    "sg:postcode":"76661",
    "sg:province":"Baden-W\u00fcrttemberg",
    "wof:name":"Kath. Pfarramt St. Peter",
    "wof:placetype":"venue"
},
  "geometry": {"coordinates":[8.4661817551,49.1968345642],"type":"Point"}
}