{
  "type": "Feature",
  "properties": {
    "iso:country":"DE",
    "sg:address":"Seelhofenstr. 76",
    "sg:city":"Mundelsheim",
    "sg:postcode":"74395",
    "sg:province":"Baden-W\u00fcrttemberg",
    "wof:name":"Knirsch Computer E. K.",
    "wof:placetype":"venue"
},
  "geometry": {"coordinates":[9.210524559,48.9923553467],"type":"Point"}
}