{
  "type": "Feature",
  "properties": {
    "iso:country":"DE",
    "sg:address":"Steinweg 3",
    "sg:city":"Frankfurt",
    "sg:phone":"+49 69/290711",
    "sg:postcode":"60313",
    "sg:province":"Hessen",
    "wof:name":"Ahmed Arabisch-farrag \u00dcbersetzungsb\u00fcro",
    "wof:placetype":"venue"
},
  "geometry": {"coordinates":[8.67772,50.113335],"type":"Point"}
}