{
  "type": "Feature",
  "properties": {
    "iso:country":"DE",
    "sg:address":"Pevelingstr. 32",
    "sg:city":"Datteln",
    "sg:phone":"+49 2363/4811",
    "sg:postcode":"45711",
    "sg:province":"Nordrhein-Westfalen",
    "wof:name":"H\u00e4rle Und Ewert Rechtsanw\u00e4lte Und Notare",
    "wof:placetype":"venue"
},
  "geometry": {"coordinates":[7.3404960632,51.6508522034],"type":"Point"}
}