{
  "type": "Feature",
  "properties": {
    "iso:country":"DE",
    "sg:address":"Strandstr. 32",
    "sg:city":"Baabe",
    "sg:postcode":"18586",
    "sg:province":"Mecklenburg-Vorpommern",
    "wof:name":"Hero Projekt- Gesellschaft Mbh & Co. Kg",
    "wof:placetype":"venue"
},
  "geometry": {"coordinates":[13.7116804123,54.361743927],"type":"Point"}
}