{
  "type": "Feature",
  "properties": {
    "iso:country":"DE",
    "sg:address":"Charlottenstr. 16",
    "sg:city":"Ansbach",
    "sg:phone":"+49 981/17340",
    "sg:postcode":"91522",
    "sg:province":"Bayern",
    "wof:name":"Ernst-g\u00fcnther Kroha",
    "wof:placetype":"venue"
},
  "geometry": {"coordinates":[10.5884027481,49.3023338318],"type":"Point"}
}