{
  "type": "Feature",
  "properties": {
    "iso:country":"DE",
    "sg:address":"Am T\u00f6mp 14",
    "sg:city":"Wegberg",
    "sg:phone":"+49 2434/24656",
    "sg:postcode":"41844",
    "sg:province":"Nordrhein-Westfalen",
    "wof:name":"Heinz-josef Peters",
    "wof:placetype":"venue"
},
  "geometry": {"coordinates":[6.26205,51.137367],"type":"Point"}
}