{
  "type": "Feature",
  "properties": {
    "iso:country":"DE",
    "sg:address":"Im Wiesenfeld 9",
    "sg:city":"Rodenberg",
    "sg:phone":"+49 5723/4792",
    "sg:postcode":"31552",
    "sg:province":"Niedersachsen",
    "wof:name":"Helmut Matthias",
    "wof:placetype":"venue"
},
  "geometry": {"coordinates":[9.345054,52.324352],"type":"Point"}
}