{
  "type": "Feature",
  "properties": {
    "iso:country":"DE",
    "sg:address":"Radolfzeller Str 101",
    "sg:city":"Allensbach",
    "sg:phone":"+49 7533/94970",
    "sg:postcode":"78476",
    "sg:province":"Baden-W\u00fcrttemberg",
    "wof:name":"Gradient Systemintegration Gmbh",
    "wof:placetype":"venue"
},
  "geometry": {"coordinates":[9.052901268,47.7205047607],"type":"Point"}
}