{
  "type": "Feature",
  "properties": {
    "iso:country":"DE",
    "sg:address":"Dobenaustr 69",
    "sg:city":"Plauen",
    "sg:phone":"+49 3741/225967",
    "sg:postcode":"08523",
    "sg:province":"Sachsen",
    "wof:name":"Baumg\u00e4rtel",
    "wof:placetype":"venue"
},
  "geometry": {"coordinates":[12.1269989014,50.4981994629],"type":"Point"}
}