{
  "type": "Feature",
  "properties": {
    "iso:country":"DE",
    "sg:address":"Marktstr. 58",
    "sg:city":"Winnenden",
    "sg:phone":"+49 7195/690625",
    "sg:postcode":"71364",
    "sg:province":"Baden-W\u00fcrttemberg",
    "wof:name":"Zeitungsverlag Und Druckerei Kreh Gmbh & Co.",
    "wof:placetype":"venue"
},
  "geometry": {"coordinates":[9.40072,48.875198],"type":"Point"}
}