{
  "type": "Feature",
  "properties": {
    "iso:country":"DE",
    "sg:address":"Im Pfirsichgarten 6",
    "sg:city":"Kandel",
    "sg:phone":"+49 7275/95383",
    "sg:postcode":"76870",
    "sg:province":"Rheinland-Pfalz",
    "wof:name":"Brandschutztechniker, Brandschutzberater",
    "wof:placetype":"venue"
},
  "geometry": {"coordinates":[8.193709,49.080482],"type":"Point"}
}