{
  "type": "Feature",
  "properties": {
    "iso:country":"DE",
    "sg:address":"Kennedyallee 76",
    "sg:city":"Frankfurt",
    "sg:postcode":"60596",
    "sg:province":"Hessen",
    "wof:name":"Immotrans Office Berliner Stra\u00dfe 220-224",
    "wof:placetype":"venue"
},
  "geometry": {"coordinates":[8.668466568,50.0961761475],"type":"Point"}
}