{
  "type": "Feature",
  "properties": {
    "iso:country":"DE",
    "sg:address":"Schlo\u00dfstr. 6",
    "sg:city":"Ahorn",
    "sg:phone":"+49 6296/251",
    "sg:postcode":"74744",
    "sg:province":"Baden-W\u00fcrttemberg",
    "wof:name":"Fritz Frank",
    "wof:placetype":"venue"
},
  "geometry": {"coordinates":[9.536519,49.499683],"type":"Point"}
}