{
  "type": "Feature",
  "properties": {
    "iso:country":"DE",
    "sg:address":"Gladbacher Str. 43",
    "sg:city":"K\u00f6ln",
    "sg:phone":"+49 221/517760",
    "sg:postcode":"50672",
    "sg:province":"Nordrhein-Westfalen",
    "wof:name":"Medius",
    "wof:placetype":"venue"
},
  "geometry": {"coordinates":[6.9382739067,50.946269989],"type":"Point"}
}