{
  "type": "Feature",
  "properties": {
    "iso:country":"DE",
    "sg:address":"Kleingem\u00fcnder Str. 91",
    "sg:city":"Heidelberg",
    "sg:phone":"+49 6221/800989",
    "sg:postcode":"69118",
    "sg:province":"Baden-W\u00fcrttemberg",
    "wof:name":"Hds",
    "wof:placetype":"venue"
},
  "geometry": {"coordinates":[8.7666730881,49.4161643982],"type":"Point"}
}