{
  "type": "Feature",
  "properties": {
    "iso:country":"DE",
    "sg:address":"Preu\u00dfenallee 21",
    "sg:city":"Berlin",
    "sg:phone":"+49 30/89091477",
    "sg:postcode":"14052",
    "sg:province":"Berlin",
    "wof:name":"E & S Bautr\u00e4gergesellschaft Mbh",
    "wof:placetype":"venue"
},
  "geometry": {"coordinates":[13.258981,52.51292],"type":"Point"}
}