{
  "type": "Feature",
  "properties": {
    "iso:country":"DE",
    "sg:address":"Eichenstr. 34",
    "sg:city":"Weissach",
    "sg:phone":"+49 7044/930399",
    "sg:postcode":"71287",
    "sg:province":"Baden-W\u00fcrttemberg",
    "wof:name":"Brigitte Pegrisch Krankengymnastin",
    "wof:placetype":"venue"
},
  "geometry": {"coordinates":[8.928393,48.845181],"type":"Point"}
}