{
  "type": "Feature",
  "properties": {
    "iso:country":"DE",
    "sg:address":"Bantorfer Brink 58",
    "sg:city":"Barsinghausen",
    "sg:phone":"+49 5105/515509",
    "sg:postcode":"30890",
    "sg:province":"Niedersachsen",
    "wof:name":"P. Kolodziej Immmobilienmakler",
    "wof:placetype":"venue"
},
  "geometry": {"coordinates":[9.4145231247,52.3288917542],"type":"Point"}
}