{
  "type": "Feature",
  "properties": {
    "iso:country":"DE",
    "sg:address":"J\u00fchengrund 24",
    "sg:city":"B\u00fcren",
    "sg:phone":"+49 2951/91900",
    "sg:postcode":"33142",
    "sg:province":"Nordrhein-Westfalen",
    "wof:name":"Gebr\u00fcder Pape Inh. Eberhard Pape",
    "wof:placetype":"venue"
},
  "geometry": {"coordinates":[8.571746,51.550224],"type":"Point"}
}