{
  "type": "Feature",
  "properties": {
    "iso:country":"DE",
    "sg:address":"Eduard-Rhein-Str. 3",
    "sg:city":"Mayen",
    "sg:phone":"+49 2651/95990",
    "sg:postcode":"56727",
    "sg:province":"Rheinland-Pfalz",
    "wof:name":"Louis Schreder Gmbh",
    "wof:placetype":"venue"
},
  "geometry": {"coordinates":[7.250084,50.325798],"type":"Point"}
}