{
  "type": "Feature",
  "properties": {
    "iso:country":"DE",
    "sg:address":"Marktstr. 27",
    "sg:city":"Salzkotten",
    "sg:phone":"+49 5258/4760",
    "sg:postcode":"33154",
    "sg:province":"Nordrhein-Westfalen",
    "wof:name":"Restaurant Il Terrazzo",
    "wof:placetype":"venue"
},
  "geometry": {"coordinates":[8.6040735245,51.6703834534],"type":"Point"}
}