{
  "type": "Feature",
  "properties": {
    "iso:country":"DE",
    "sg:address":"Johann-Sebastian-Bach-Str. 28",
    "sg:city":"Giengen",
    "sg:phone":"+49 7322/3344",
    "sg:postcode":"89537",
    "sg:province":"Baden-W\u00fcrttemberg",
    "wof:name":"G. Mack",
    "wof:placetype":"venue"
},
  "geometry": {"coordinates":[10.236205101,48.6281547546],"type":"Point"}
}