{
  "type": "Feature",
  "properties": {
    "iso:country":"DE",
    "sg:address":"Bahnhofstr.",
    "sg:city":"Albisheim",
    "sg:phone":"+49 6355/442",
    "sg:postcode":"67308",
    "sg:province":"Rheinland-Pfalz",
    "wof:name":"Raiffeisen Waren-zentrale Rhein-main Eg",
    "wof:placetype":"venue"
},
  "geometry": {"coordinates":[8.094585,49.645103],"type":"Point"}
}