{
  "type": "Feature",
  "properties": {
    "iso:country":"DE",
    "sg:address":"Bahnhofstr. 17",
    "sg:city":"Lissendorf",
    "sg:phone":"+49 6597/2418",
    "sg:postcode":"54587",
    "sg:province":"Rheinland-Pfalz",
    "wof:name":"H. Wolff",
    "wof:placetype":"venue"
},
  "geometry": {"coordinates":[6.613967,50.317471],"type":"Point"}
}