{
  "type": "Feature",
  "properties": {
    "iso:country":"DE",
    "sg:address":"Hackl\u00e4nderstr. 16",
    "sg:city":"Stuttgart",
    "sg:postcode":"70184",
    "sg:province":"Baden-W\u00fcrttemberg",
    "wof:name":"Sabine Schoeffel-stiftung",
    "wof:placetype":"venue"
},
  "geometry": {"coordinates":[9.1979322433,48.7758865356],"type":"Point"}
}