{
  "type": "Feature",
  "properties": {
    "iso:country":"DE",
    "sg:address":"Wolffsgasse 6",
    "sg:city":"D\u00fcren",
    "sg:phone":"+49 2421/57687",
    "sg:postcode":"52355",
    "sg:province":"Nordrhein-Westfalen",
    "wof:name":"Brigitte Kurth",
    "wof:placetype":"venue"
},
  "geometry": {"coordinates":[6.4757628441,50.7672157288],"type":"Point"}
}