{
  "type": "Feature",
  "properties": {
    "iso:country":"DE",
    "sg:address":"Am Anger 8",
    "sg:city":"Sta\u00dffurt",
    "sg:phone":"+49 3925/322623",
    "sg:postcode":"39418",
    "sg:province":"Sachsen-Anhalt",
    "wof:name":"Kaufmann Speditionsges. Mbh",
    "wof:placetype":"venue"
},
  "geometry": {"coordinates":[11.5842266083,51.8444366455],"type":"Point"}
}