{
  "type": "Feature",
  "properties": {
    "iso:country":"DE",
    "sg:address":"Ortsstr. 18",
    "sg:city":"Rohrenfels",
    "sg:phone":"+49 8431/2270",
    "sg:postcode":"86701",
    "sg:province":"Bayern",
    "wof:name":"Johann Kaiser",
    "wof:placetype":"venue"
},
  "geometry": {"coordinates":[11.166157,48.69556],"type":"Point"}
}