{
  "type": "Feature",
  "properties": {
    "iso:country":"DE",
    "sg:address":"Brunnenstr. 7",
    "sg:city":"\u00dcdersdorf",
    "sg:phone":"+49 6596/818",
    "sg:postcode":"54552",
    "sg:province":"Rheinland-Pfalz",
    "wof:name":"B\u00e4ckerei Steinebach E. K. G\u00fcnter Steinebach",
    "wof:placetype":"venue"
},
  "geometry": {"coordinates":[6.802676,50.154068],"type":"Point"}
}