{
  "type": "Feature",
  "properties": {
    "iso:country":"DE",
    "sg:address":"Ettersburger Str. 19",
    "sg:city":"Weimar",
    "sg:phone":"+49 3643/419897",
    "sg:postcode":"99427",
    "sg:province":"Th\u00fcringen",
    "wof:name":"Joerg Schneider Edelstahlverarbeitung, Weimar",
    "wof:placetype":"venue"
},
  "geometry": {"coordinates":[11.3194665909,50.9947166443],"type":"Point"}
}