{
  "type": "Feature",
  "properties": {
    "iso:country":"DE",
    "sg:address":"Eichenstr. 5",
    "sg:city":"Asendorf",
    "sg:postcode":"21271",
    "sg:province":"Niedersachsen",
    "wof:name":"Molkerei Grafschaft Hoya Eg",
    "wof:placetype":"venue"
},
  "geometry": {"coordinates":[9.9819660187,53.2910308838],"type":"Point"}
}