{
  "type": "Feature",
  "properties": {
    "iso:country":"DE",
    "sg:address":"Amalienstr. 11",
    "sg:city":"Bamberg",
    "sg:phone":"+49 951/980580",
    "sg:postcode":"96047",
    "sg:province":"Bayern",
    "wof:name":"Zeitwerk Verlag Gmbh",
    "wof:placetype":"venue"
},
  "geometry": {"coordinates":[10.8979911804,49.8897018433],"type":"Point"}
}