{
  "type": "Feature",
  "properties": {
    "iso:country":"DE",
    "sg:address":"Gro\u00dfe Diesdorfer Str. 186-187",
    "sg:city":"Magdeburg",
    "sg:phone":"+49 391/7348968",
    "sg:postcode":"39110",
    "sg:province":"Sachsen-Anhalt",
    "wof:name":"Elfen-apotheke E. K. Inh. Annett Kinne",
    "wof:placetype":"venue"
},
  "geometry": {"coordinates":[11.59943,52.129009],"type":"Point"}
}