{
  "type": "Feature",
  "properties": {
    "iso:country":"DE",
    "sg:address":"Rudolf-Diesel-Str. 1",
    "sg:city":"Ansbach",
    "sg:phone":"+49 981/971210",
    "sg:postcode":"91522",
    "sg:province":"Bayern",
    "wof:name":"Fleissner Nonwovens Gmbh & Co Kg",
    "wof:placetype":"venue"
},
  "geometry": {"coordinates":[10.613722,49.260212],"type":"Point"}
}