{
  "type": "Feature",
  "properties": {
    "iso:country":"DE",
    "sg:address":"Dillberg 8",
    "sg:city":"Marktheidenfeld",
    "sg:phone":"+49 9391/3950",
    "sg:postcode":"97828",
    "sg:province":"Bayern",
    "wof:name":"Manfred Reger Gmbh",
    "wof:placetype":"venue"
},
  "geometry": {"coordinates":[9.5990972519,49.8322257996],"type":"Point"}
}