{
  "type": "Feature",
  "properties": {
    "iso:country":"DE",
    "sg:address":"Postdamm 166",
    "sg:city":"G\u00fctersloh",
    "sg:phone":"+49 5241/6439",
    "sg:postcode":"33334",
    "sg:province":"Nordrhein-Westfalen",
    "wof:name":"Gasthof M\u00fchlenstroth",
    "wof:placetype":"venue"
},
  "geometry": {"coordinates":[8.4050941467,51.9333496094],"type":"Point"}
}