{
  "type": "Feature",
  "properties": {
    "iso:country":"DE",
    "sg:address":"Riehler Str. 30",
    "sg:city":"K\u00f6ln",
    "sg:phone":"+49 221/732227",
    "sg:postcode":"50668",
    "sg:province":"Nordrhein-Westfalen",
    "wof:name":"Rechtsanwaltskammer K\u00f6ln",
    "wof:placetype":"venue"
},
  "geometry": {"coordinates":[6.962846,50.953178],"type":"Point"}
}