{
  "type": "Feature",
  "properties": {
    "iso:country":"DE",
    "sg:address":"Peutingerstr. 5",
    "sg:city":"Augsburg",
    "sg:phone":"+49 821/31660",
    "sg:postcode":"86152",
    "sg:province":"Bayern",
    "wof:name":"Aktion Hoffnung- Hilfe F\u00fcr Die Mission- Gmbh",
    "wof:placetype":"venue"
},
  "geometry": {"coordinates":[10.8968229294,48.3718795776],"type":"Point"}
}