{
  "type": "Feature",
  "properties": {
    "iso:country":"DE",
    "sg:address":"Am Helleberg 5",
    "sg:city":"Goslar",
    "sg:phone":"+49 5321/80701",
    "sg:postcode":"38644",
    "sg:province":"Niedersachsen",
    "wof:name":"Richard Kohl Gmbh & Co. Kommanditgesellschaft",
    "wof:placetype":"venue"
},
  "geometry": {"coordinates":[10.415099,51.921436],"type":"Point"}
}