{
  "type": "Feature",
  "properties": {
    "iso:country":"DE",
    "sg:address":"Meisenweg 2",
    "sg:city":"Schmallenberg",
    "sg:phone":"+49 2975/449",
    "sg:postcode":"57392",
    "sg:province":"Nordrhein-Westfalen",
    "wof:name":"Walter Didam",
    "wof:placetype":"venue"
},
  "geometry": {"coordinates":[8.289825,51.141193],"type":"Point"}
}