{
  "type": "Feature",
  "properties": {
    "iso:country":"DE",
    "sg:address":"G\u00fcterbahnhofstr. 1",
    "sg:city":"Kornwestheim",
    "sg:phone":"+49 4971/546305",
    "sg:postcode":"70806",
    "sg:province":"Baden-W\u00fcrttemberg",
    "wof:name":"Volksbank Kornwestheim",
    "wof:placetype":"venue"
},
  "geometry": {"coordinates":[9.182283,48.865101],"type":"Point"}
}