{
  "type": "Feature",
  "properties": {
    "iso:country":"DE",
    "sg:address":"Wanheimer Str. 44",
    "sg:city":"Duisburg",
    "sg:phone":"+49 203/661730",
    "sg:postcode":"47053",
    "sg:province":"Nordrhein-Westfalen",
    "wof:name":"B\u00e4ckerei Thomas Sowa",
    "wof:placetype":"venue"
},
  "geometry": {"coordinates":[6.754052,51.420727],"type":"Point"}
}