{
  "type": "Feature",
  "properties": {
    "iso:country":"DE",
    "sg:address":"Gustav-Freytag-Str. 23-25",
    "sg:city":"Fredersdorf",
    "sg:postcode":"15370",
    "sg:province":"Brandenburg",
    "wof:name":"Evangelische Kirche",
    "wof:placetype":"venue"
},
  "geometry": {"coordinates":[13.7455940247,52.5152816772],"type":"Point"}
}