{
  "type": "Feature",
  "properties": {
    "iso:country":"DE",
    "sg:address":"Bahnhofstr. 1 a",
    "sg:city":"Ruhla",
    "sg:phone":"+49 36929/89702",
    "sg:postcode":"99842",
    "sg:province":"Th\u00fcringen",
    "wof:name":"Vereinssch\u00e4nke Kulturhaus",
    "wof:placetype":"venue"
},
  "geometry": {"coordinates":[10.3644294739,50.8989944458],"type":"Point"}
}