{
  "type": "Feature",
  "properties": {
    "iso:country":"DE",
    "sg:address":"Hoheluftchaussee 2",
    "sg:city":"Hamburg",
    "sg:phone":"+49 40/4209915",
    "sg:postcode":"20253",
    "sg:province":"Hamburg",
    "wof:name":"Gefa Christa Bastein",
    "wof:placetype":"venue"
},
  "geometry": {"coordinates":[9.975419,53.579239],"type":"Point"}
}