{
  "type": "Feature",
  "properties": {
    "iso:country":"DE",
    "sg:address":"Widenmayerstr. 48",
    "sg:city":"M\u00fcnchen",
    "sg:phone":"+49 89/298892",
    "sg:postcode":"80538",
    "sg:province":"Bayern",
    "wof:name":"Walther H. Sch\u00fcnemann Gmbh",
    "wof:placetype":"venue"
},
  "geometry": {"coordinates":[11.596232,48.148701],"type":"Point"}
}