{
  "type": "Feature",
  "properties": {
    "iso:country":"DE",
    "sg:address":"Werkstattstr.",
    "sg:city":"Deuben",
    "sg:phone":"+49 34443/6020",
    "sg:postcode":"06682",
    "sg:province":"Sachsen-Anhalt",
    "wof:name":"Gr\u00f6bener Logistik Gmbh",
    "wof:placetype":"venue"
},
  "geometry": {"coordinates":[12.0899620056,51.1157150269],"type":"Point"}
}