{
  "type": "Feature",
  "properties": {
    "iso:country":"DE",
    "sg:address":"Bachstr. 11",
    "sg:city":"Mitterteich",
    "sg:phone":"+49 9633/8254",
    "sg:postcode":"95666",
    "sg:province":"Bayern",
    "wof:name":"Zeitler Kommunikationssysteme",
    "wof:placetype":"venue"
},
  "geometry": {"coordinates":[12.244846344,49.9506340027],"type":"Point"}
}