{
  "type": "Feature",
  "properties": {
    "iso:country":"DE",
    "sg:address":"Pallaswiesenstr. 146",
    "sg:city":"Darmstadt",
    "sg:phone":"+49 6151/896351",
    "sg:postcode":"64293",
    "sg:province":"Hessen",
    "wof:name":"Reweda Kurt Heiderich Gmbh",
    "wof:placetype":"venue"
},
  "geometry": {"coordinates":[8.634328,49.884045],"type":"Point"}
}