{
  "type": "Feature",
  "properties": {
    "iso:country":"DE",
    "sg:address":"Hessengasse 1",
    "sg:city":"Leimen",
    "sg:phone":"+49 6224/75522",
    "sg:postcode":"69181",
    "sg:province":"Baden-W\u00fcrttemberg",
    "wof:name":"P\u00fcnktchen Und Anton Kindermode Anna-maria Michelsen",
    "wof:placetype":"venue"
},
  "geometry": {"coordinates":[8.7017316818,49.3509025574],"type":"Point"}
}