{
  "type": "Feature",
  "properties": {
    "iso:country":"DE",
    "sg:address":"Sioner Str. 15",
    "sg:city":"Mauchenheim",
    "sg:phone":"+49 6352/4706",
    "sg:postcode":"67294",
    "sg:province":"Rheinland-Pfalz",
    "wof:name":"Otto Knobloch",
    "wof:placetype":"venue"
},
  "geometry": {"coordinates":[8.045221,49.715908],"type":"Point"}
}