{
  "type": "Feature",
  "properties": {
    "iso:country":"DE",
    "sg:address":"An der Marburger Str. 92",
    "sg:city":"M\u00fcnchhausen",
    "sg:phone":"+49 6423/7340",
    "sg:postcode":"35117",
    "sg:province":"Hessen",
    "wof:name":"R. O. Brechnitz",
    "wof:placetype":"venue"
},
  "geometry": {"coordinates":[8.7066679001,50.9424476624],"type":"Point"}
}