{
  "type": "Feature",
  "properties": {
    "iso:country":"DE",
    "sg:address":"Parksteiner Str. 51",
    "sg:city":"Weiden",
    "sg:phone":"+49 961/25024",
    "sg:postcode":"92637",
    "sg:province":"Bayern",
    "wof:name":"Baustoff-handels Gmbh",
    "wof:placetype":"venue"
},
  "geometry": {"coordinates":[12.139087,49.693626],"type":"Point"}
}