{
  "type": "Feature",
  "properties": {
    "iso:country":"DE",
    "sg:address":"Werner-Von-Siemens-Str. 13",
    "sg:city":"Ellerau",
    "sg:phone":"+49 4941/0677730",
    "sg:postcode":"25479",
    "sg:province":"Schleswig-Holstein",
    "wof:name":"Romwell Ges. F\u00dcr Umweltvertr\u00c4gliche Verpackung",
    "wof:placetype":"venue"
},
  "geometry": {"coordinates":[9.9461021423,53.7587165833],"type":"Point"}
}