{
  "type": "Feature",
  "properties": {
    "iso:country":"DE",
    "sg:address":"Hudeweg 16",
    "sg:city":"Sundern",
    "sg:phone":"+49 2393/227",
    "sg:postcode":"59846",
    "sg:province":"Nordrhein-Westfalen",
    "wof:name":"Karl Meisterjahn",
    "wof:placetype":"venue"
},
  "geometry": {"coordinates":[7.944441,51.301559],"type":"Point"}
}