{
  "type": "Feature",
  "properties": {
    "iso:country":"DE",
    "sg:address":"Osnabr\u00fccker Str. 75",
    "sg:city":"Bielefeld",
    "sg:phone":"+49 521/450131",
    "sg:postcode":"33649",
    "sg:province":"Nordrhein-Westfalen",
    "wof:name":"Peter Leiss",
    "wof:placetype":"venue"
},
  "geometry": {"coordinates":[8.4914073944,52.0001182556],"type":"Point"}
}