{
  "type": "Feature",
  "properties": {
    "iso:country":"DE",
    "sg:address":"Karl-Evang-Str. 19",
    "sg:city":"Remscheid",
    "sg:phone":"+49 2191/663310",
    "sg:postcode":"42897",
    "sg:province":"Nordrhein-Westfalen",
    "wof:name":"Ulrich Bunse",
    "wof:placetype":"venue"
},
  "geometry": {"coordinates":[7.2754731178,51.1906852722],"type":"Point"}
}