{
  "type": "Feature",
  "properties": {
    "iso:country":"DE",
    "sg:address":"Waitzstr. 23",
    "sg:city":"Berlin",
    "sg:phone":"+49 30/3232909",
    "sg:postcode":"10629",
    "sg:province":"Berlin",
    "wof:name":"Frank Wojnorowicz Immobilienmakler",
    "wof:placetype":"venue"
},
  "geometry": {"coordinates":[13.3059387207,52.5026626587],"type":"Point"}
}