{
  "type": "Feature",
  "properties": {
    "iso:country":"DE",
    "sg:address":"Eichholzbahn 152",
    "sg:city":"Berlin",
    "sg:postcode":"13591",
    "sg:province":"Berlin",
    "wof:name":"Dr. Med. Karl-h. Diedrich",
    "wof:placetype":"venue"
},
  "geometry": {"coordinates":[13.133608,52.538609],"type":"Point"}
}