{
  "type": "Feature",
  "properties": {
    "iso:country":"DE",
    "sg:address":"Curslacker Deich 284",
    "sg:city":"Hamburg",
    "sg:phone":"+49 40/7231223",
    "sg:postcode":"21039",
    "sg:province":"Hamburg",
    "wof:name":"Rieck-haus Vierl\u00e4nder Freilichtmuseum",
    "wof:placetype":"venue"
},
  "geometry": {"coordinates":[10.213787,53.460159],"type":"Point"}
}