{
  "type": "Feature",
  "properties": {
    "iso:country":"DE",
    "sg:address":"Rixener Stra\u00dfe 24",
    "sg:city":"Brilon",
    "sg:phone":"+49 2961/50832",
    "sg:postcode":"59929",
    "sg:province":"Nordrhein-Westfalen",
    "wof:name":"Vereinte-versicherung In Brilon Bei Annette Ne\u00df",
    "wof:placetype":"venue"
},
  "geometry": {"coordinates":[8.560588,51.397121],"type":"Point"}
}