{
  "type": "Feature",
  "properties": {
    "iso:country":"DE",
    "sg:address":"Gro\u00dfe Bauerngasse 62",
    "sg:city":"H\u00f6chstadt",
    "sg:phone":"+49 9193/63580",
    "sg:postcode":"91315",
    "sg:province":"Bayern",
    "wof:name":"Eugen Werner Vogel",
    "wof:placetype":"venue"
},
  "geometry": {"coordinates":[10.8188858032,49.7033462524],"type":"Point"}
}