{
  "type": "Feature",
  "properties": {
    "iso:country":"DE",
    "sg:address":"Salinstr. 9",
    "sg:city":"Rosenheim",
    "sg:phone":"+49 8031/37544",
    "sg:postcode":"83022",
    "sg:province":"Bayern",
    "wof:name":"Heimo Hauch Heilpraktiker",
    "wof:placetype":"venue"
},
  "geometry": {"coordinates":[12.1240406036,47.8514785767],"type":"Point"}
}