{
  "type": "Feature",
  "properties": {
    "iso:country":"DE",
    "sg:address":"Knupperweg 22",
    "sg:city":"Werder",
    "sg:phone":"+49 3327/730556",
    "sg:postcode":"14542",
    "sg:province":"Brandenburg",
    "wof:name":"Tk Industrievertrieb Inh. T\u00fclay Kr\u00fcger",
    "wof:placetype":"venue"
},
  "geometry": {"coordinates":[12.9334363937,52.3603210449],"type":"Point"}
}