{
  "type": "Feature",
  "properties": {
    "iso:country":"DE",
    "sg:address":"Ettinger Str. 21",
    "sg:city":"Gaimersheim",
    "sg:phone":"+49 8458/2657",
    "sg:postcode":"85080",
    "sg:province":"Bayern",
    "wof:name":"Franz Brandl",
    "wof:placetype":"venue"
},
  "geometry": {"coordinates":[11.373597,48.808266],"type":"Point"}
}