{
  "type": "Feature",
  "properties": {
    "iso:country":"DE",
    "sg:address":"Terofalstr. 21",
    "sg:city":"M\u00fcnchen",
    "sg:phone":"+49 89/7001553",
    "sg:postcode":"80689",
    "sg:province":"Bayern",
    "wof:name":"G. Schellenschl\u00e4ger Kunstmaler",
    "wof:placetype":"venue"
},
  "geometry": {"coordinates":[11.476161,48.125523],"type":"Point"}
}