{
  "type": "Feature",
  "properties": {
    "iso:country":"DE",
    "sg:address":"Bahnhofstr. 25",
    "sg:city":"Konz",
    "sg:phone":"+49 6501/92670",
    "sg:postcode":"54329",
    "sg:province":"Rheinland-Pfalz",
    "wof:name":"Elektro Kugel Gmbh",
    "wof:placetype":"venue"
},
  "geometry": {"coordinates":[6.5744252205,49.6967201233],"type":"Point"}
}