{
  "type": "Feature",
  "properties": {
    "iso:country":"DE",
    "sg:address":"Melsbacher Str. 10",
    "sg:city":"Rengsdorf",
    "sg:phone":"+49 2634/921270",
    "sg:postcode":"56579",
    "sg:province":"Rheinland-Pfalz",
    "wof:name":"Vogel & Lorenz Gmbh",
    "wof:placetype":"venue"
},
  "geometry": {"coordinates":[7.486058,50.500721],"type":"Point"}
}