{
  "type": "Feature",
  "properties": {
    "iso:country":"DE",
    "sg:address":"Adlerstr. 3",
    "sg:city":"Besigheim",
    "sg:phone":"+49 7143/50586",
    "sg:postcode":"74354",
    "sg:province":"Baden-W\u00fcrttemberg",
    "wof:name":"T. Schwandner",
    "wof:placetype":"venue"
},
  "geometry": {"coordinates":[9.2012081146,49.0160903931],"type":"Point"}
}