{
  "type": "Feature",
  "properties": {
    "iso:country":"DE",
    "sg:address":"Barnerstr. 28",
    "sg:city":"Hamburg",
    "sg:phone":"+49 40/3903824",
    "sg:postcode":"22765",
    "sg:province":"Hamburg",
    "wof:name":"Hoch & Oesmann",
    "wof:placetype":"venue"
},
  "geometry": {"coordinates":[9.929824,53.556698],"type":"Point"}
}