{
  "type": "Feature",
  "properties": {
    "iso:country":"DE",
    "sg:address":"Duvenwischen 35",
    "sg:city":"Hamburg",
    "sg:phone":"+49 40/6035678",
    "sg:postcode":"22359",
    "sg:province":"Hamburg",
    "wof:name":"Helmut Kr\u00f6ger Rechtsanwalt",
    "wof:placetype":"venue"
},
  "geometry": {"coordinates":[10.1654148102,53.6625976562],"type":"Point"}
}