{
  "type": "Feature",
  "properties": {
    "iso:country":"DE",
    "sg:address":"Kirchweg 92",
    "sg:city":"Moers",
    "sg:phone":"+49 2841/396382",
    "sg:postcode":"47447",
    "sg:province":"Nordrhein-Westfalen",
    "wof:name":"A. H\u00fcsken",
    "wof:placetype":"venue"
},
  "geometry": {"coordinates":[6.662571,51.41975],"type":"Point"}
}