{
  "type": "Feature",
  "properties": {
    "iso:country":"DE",
    "sg:address":"Oldershausener Hauptstr. 23",
    "sg:city":"Marschacht",
    "sg:phone":"+49 4133/6137",
    "sg:postcode":"21436",
    "sg:province":"Niedersachsen",
    "wof:name":"Alfred Dittmer",
    "wof:placetype":"venue"
},
  "geometry": {"coordinates":[10.33965,53.360443],"type":"Point"}
}