{
  "type": "Feature",
  "properties": {
    "iso:country":"DE",
    "sg:address":"Schulstr. 96",
    "sg:city":"Bielefeld",
    "sg:phone":"+49 521/431296",
    "sg:postcode":"33647",
    "sg:province":"Nordrhein-Westfalen",
    "wof:name":"Klaus-dieter Stiegert Steuerberater Und",
    "wof:placetype":"venue"
},
  "geometry": {"coordinates":[8.5053110123,51.998588562],"type":"Point"}
}