{
  "type": "Feature",
  "properties": {
    "iso:country":"DE",
    "sg:address":"Dorfstr. 9",
    "sg:city":"Sch\u00f6nwolde",
    "sg:postcode":"19205",
    "sg:province":"Mecklenburg-Vorpommern",
    "wof:name":"Lbb Landwirtschaftliche Beratungs- Und",
    "wof:placetype":"venue"
},
  "geometry": {"coordinates":[11.026843,53.641266],"type":"Point"}
}