{
  "type": "Feature",
  "properties": {
    "iso:country":"DE",
    "sg:address":"Dorfstr. 7",
    "sg:city":"Bayerisch Eisenstein",
    "sg:phone":"+49 9925/94150",
    "sg:postcode":"94252",
    "sg:province":"Bayern",
    "wof:name":"Technische Werkst\u00e4tten Regenh\u00fctte Gmbh",
    "wof:placetype":"venue"
},
  "geometry": {"coordinates":[13.205739,49.076996],"type":"Point"}
}