{
  "type": "Feature",
  "properties": {
    "iso:country":"DE",
    "sg:address":"Weidestrasse 118A",
    "sg:city":"Hamburg",
    "sg:phone":"+49 40/270760",
    "sg:postcode":"22083",
    "sg:province":"Hamburg",
    "wof:name":"Fielmann Aktiengesellschaft",
    "wof:placetype":"venue"
},
  "geometry": {"coordinates":[10.0293998718,53.5803604126],"type":"Point"}
}