{
  "type": "Feature",
  "properties": {
    "iso:country":"DE",
    "sg:address":"Wiebelsbacher Str. 2",
    "sg:city":"L\u00fctzelbach",
    "sg:phone":"+49 9372/944794",
    "sg:postcode":"64750",
    "sg:province":"Hessen",
    "wof:name":"H. Und W. Verst Gmbh",
    "wof:placetype":"venue"
},
  "geometry": {"coordinates":[9.11933,49.788677],"type":"Point"}
}