{
  "type": "Feature",
  "properties": {
    "iso:country":"DE",
    "sg:address":"Auf der Heide 2",
    "sg:city":"Nettersheim",
    "sg:phone":"+49 2486/8090",
    "sg:postcode":"53947",
    "sg:province":"Nordrhein-Westfalen",
    "wof:name":"Hayward Industrial Gmbh",
    "wof:placetype":"venue"
},
  "geometry": {"coordinates":[6.6583142281,50.5074462891],"type":"Point"}
}