{
  "type": "Feature",
  "properties": {
    "iso:country":"DE",
    "sg:address":"Gartenstr. 4",
    "sg:city":"Freiensteinau",
    "sg:phone":"+49 6644/271",
    "sg:postcode":"36399",
    "sg:province":"Hessen",
    "wof:name":"M\u00f6ller Gmbh",
    "wof:placetype":"venue"
},
  "geometry": {"coordinates":[9.383284,50.471619],"type":"Point"}
}