{
  "type": "Feature",
  "properties": {
    "iso:country":"DE",
    "sg:address":"Von-Richthofen-Str. 6",
    "sg:city":"Landstuhl",
    "sg:phone":"+49 6371/2503",
    "sg:postcode":"66849",
    "sg:province":"Rheinland-Pfalz",
    "wof:name":"Dr. Gerhard Und Wolf Kuhn Rechtsanw\u00e4lte",
    "wof:placetype":"venue"
},
  "geometry": {"coordinates":[7.5703210831,49.4126930237],"type":"Point"}
}