{
  "type": "Feature",
  "properties": {
    "iso:country":"DE",
    "sg:address":"Hofmarkstr. 12",
    "sg:city":"Aichach",
    "sg:phone":"+49 8251/5908",
    "sg:postcode":"86551",
    "sg:province":"Bayern",
    "wof:name":"Georg Sigl",
    "wof:placetype":"venue"
},
  "geometry": {"coordinates":[11.1893472672,48.428150177],"type":"Point"}
}