{
  "type": "Feature",
  "properties": {
    "iso:country":"DE",
    "sg:address":"G\u00fcnther-Wagner-Allee 13",
    "sg:city":"Hannover",
    "sg:phone":"+49 511/280070",
    "sg:postcode":"30177",
    "sg:province":"Niedersachsen",
    "wof:name":"Hf-fonds Vii Unternehmens- Beteiligungsgesellschaft Mbh",
    "wof:placetype":"venue"
},
  "geometry": {"coordinates":[9.769105,52.398178],"type":"Point"}
}