{
  "type": "Feature",
  "properties": {
    "iso:country":"DE",
    "sg:address":"Heidelberger Str. 16",
    "sg:city":"Wald-Michelbach",
    "sg:phone":"+49 6207/3246",
    "sg:postcode":"69483",
    "sg:province":"Hessen",
    "wof:name":"Pension Falter",
    "wof:placetype":"venue"
},
  "geometry": {"coordinates":[8.8644647598,49.5328903198],"type":"Point"}
}