{
  "type": "Feature",
  "properties": {
    "iso:country":"DE",
    "sg:address":"Engelbertstr. 19",
    "sg:city":"Essen",
    "sg:phone":"+49 201/2486320",
    "sg:postcode":"45127",
    "sg:province":"Nordrhein-Westfalen",
    "wof:name":"Audiatur Et Altera Pars Gmbh",
    "wof:placetype":"venue"
},
  "geometry": {"coordinates":[7.0218391418,51.4574508667],"type":"Point"}
}