{
  "type": "Feature",
  "properties": {
    "iso:country":"DE",
    "sg:address":"Altm\u00fchlenfeld 247",
    "sg:city":"Krefeld",
    "sg:phone":"+49 2151/301657",
    "sg:postcode":"47807",
    "sg:province":"Nordrhein-Westfalen",
    "wof:name":"Therapiezentrum Massorz Gmbh",
    "wof:placetype":"venue"
},
  "geometry": {"coordinates":[6.5834622383,51.3052635193],"type":"Point"}
}