{
  "type": "Feature",
  "properties": {
    "iso:country":"DE",
    "sg:address":"M\u00f6serstr 26",
    "sg:city":"Osnabr\u00fcck",
    "sg:phone":"+49 4954/1324342",
    "sg:postcode":"49074",
    "sg:province":"Niedersachsen",
    "wof:name":"Stadtsparkasse",
    "wof:placetype":"venue"
},
  "geometry": {"coordinates":[8.05162,52.273727],"type":"Point"}
}