{
  "type": "Feature",
  "properties": {
    "iso:country":"DE",
    "sg:address":"Fr\u00fchme\u00dfstr. 15",
    "sg:city":"Thannhausen",
    "sg:phone":"+49 8281/3413",
    "sg:postcode":"86470",
    "sg:province":"Bayern",
    "wof:name":"Gerhard Leberl",
    "wof:placetype":"venue"
},
  "geometry": {"coordinates":[10.4679613113,48.2829742432],"type":"Point"}
}