{
  "type": "Feature",
  "properties": {
    "iso:country":"DE",
    "sg:address":"Schwarzwaldstr. 5",
    "sg:city":"Sinzheim",
    "sg:phone":"+49 7223/52319",
    "sg:postcode":"76547",
    "sg:province":"Baden-W\u00fcrttemberg",
    "wof:name":"Fidele-jehle-runde E. V. Leiberstung",
    "wof:placetype":"venue"
},
  "geometry": {"coordinates":[8.0974607468,48.7504615784],"type":"Point"}
}