{
  "type": "Feature",
  "properties": {
    "iso:country":"DE",
    "sg:address":"Markt 15",
    "sg:city":"Pl\u00f6n",
    "sg:phone":"+49 4522/4275",
    "sg:postcode":"24306",
    "sg:province":"Schleswig-Holstein",
    "wof:name":"Hans-peter Zaardt",
    "wof:placetype":"venue"
},
  "geometry": {"coordinates":[10.416235,54.158016],"type":"Point"}
}