{
  "type": "Feature",
  "properties": {
    "iso:country":"DE",
    "sg:address":"Beesenweide 2",
    "sg:city":"Moorrege",
    "sg:phone":"+49 4122/81705",
    "sg:postcode":"25436",
    "sg:province":"Schleswig-Holstein",
    "wof:name":"Gerhard Holzs Ladenausbau Gmbh & Co. Kg",
    "wof:placetype":"venue"
},
  "geometry": {"coordinates":[9.680228,53.671104],"type":"Point"}
}