{
  "type": "Feature",
  "properties": {
    "iso:country":"DE",
    "sg:address":"Heisinger Str. 379",
    "sg:city":"Essen",
    "sg:phone":"+49 201/466211",
    "sg:postcode":"45259",
    "sg:province":"Nordrhein-Westfalen",
    "wof:name":"Hans Stiene",
    "wof:placetype":"venue"
},
  "geometry": {"coordinates":[7.0586738586,51.4093284607],"type":"Point"}
}