{
  "type": "Feature",
  "properties": {
    "iso:country":"DE",
    "sg:address":"Industriestr. 3",
    "sg:city":"Westoverledingen",
    "sg:phone":"+49 4955/5410",
    "sg:postcode":"26810",
    "sg:province":"Niedersachsen",
    "wof:name":"H. Und M. Von Lengen",
    "wof:placetype":"venue"
},
  "geometry": {"coordinates":[7.466246,53.170048],"type":"Point"}
}