{
  "type": "Feature",
  "properties": {
    "iso:country":"DE",
    "sg:address":"Arthur-Piechler-Str. 12",
    "sg:city":"Augsburg",
    "sg:postcode":"86161",
    "sg:province":"Bayern",
    "wof:name":"Free-media Gmbh",
    "wof:placetype":"venue"
},
  "geometry": {"coordinates":[10.918431,48.36013],"type":"Point"}
}