{
  "type": "Feature",
  "properties": {
    "iso:country":"DE",
    "sg:address":"Obere Bergstr. 2",
    "sg:city":"Leuterod",
    "sg:phone":"+49 2602/7771",
    "sg:postcode":"56244",
    "sg:province":"Rheinland-Pfalz",
    "wof:name":"W. Hardy Gmbh",
    "wof:placetype":"venue"
},
  "geometry": {"coordinates":[7.826598,50.489891],"type":"Point"}
}