{
  "type": "Feature",
  "properties": {
    "iso:country":"DE",
    "sg:address":"Steinachstr. 12",
    "sg:city":"Schriesheim",
    "sg:phone":"+49 6203/61445",
    "sg:postcode":"69198",
    "sg:province":"Baden-W\u00fcrttemberg",
    "wof:name":"G\u00e4stehaus U. Weinstuben Hauser",
    "wof:placetype":"venue"
},
  "geometry": {"coordinates":[8.6623926163,49.4771347046],"type":"Point"}
}