{
  "type": "Feature",
  "properties": {
    "iso:country":"DE",
    "sg:address":"Riegelackerweg 3",
    "sg:city":"Seefeld",
    "sg:phone":"+49 8152/70299",
    "sg:postcode":"82229",
    "sg:province":"Bayern",
    "wof:name":"Erwin Schroll Elektroinstallation",
    "wof:placetype":"venue"
},
  "geometry": {"coordinates":[11.231146,48.02076],"type":"Point"}
}