{
  "type": "Feature",
  "properties": {
    "iso:country":"DE",
    "sg:address":"Gewerbestr. S\u00fcd 46",
    "sg:city":"Erkelenz",
    "sg:phone":"+49 2431/73569",
    "sg:postcode":"41812",
    "sg:province":"Nordrhein-Westfalen",
    "wof:name":"Derichs Maschinenbau",
    "wof:placetype":"venue"
},
  "geometry": {"coordinates":[6.307638,51.068073],"type":"Point"}
}