{
  "type": "Feature",
  "properties": {
    "iso:country":"DE",
    "sg:address":"Unter der Tonne 25c",
    "sg:city":"Brilon",
    "sg:phone":"+49 2961/4304",
    "sg:postcode":"59929",
    "sg:province":"Nordrhein-Westfalen",
    "wof:name":"Jan-albrecht.de",
    "wof:placetype":"venue"
},
  "geometry": {"coordinates":[8.583118,51.394978],"type":"Point"}
}