{
  "type": "Feature",
  "properties": {
    "iso:country":"DE",
    "sg:address":"Bramfelder Chaussee 97c",
    "sg:city":"Hamburg",
    "sg:phone":"+49 40/613440",
    "sg:postcode":"22177",
    "sg:province":"Hamburg",
    "wof:name":"Christa Gerhard",
    "wof:placetype":"venue"
},
  "geometry": {"coordinates":[10.0676879883,53.6002807617],"type":"Point"}
}