{
  "type": "Feature",
  "properties": {
    "iso:country":"DE",
    "sg:address":"Am Bahnhof 1",
    "sg:city":"Syke",
    "sg:phone":"+49 4242/50555",
    "sg:postcode":"28857",
    "sg:province":"Niedersachsen",
    "wof:name":"Deutsche Bahn Ag",
    "wof:placetype":"venue"
},
  "geometry": {"coordinates":[8.810043335,52.9161872864],"type":"Point"}
}