{
  "type": "Feature",
  "properties": {
    "iso:country":"DE",
    "sg:address":"Am Markt 38",
    "sg:city":"Saalburg",
    "sg:phone":"+49 36647/267",
    "sg:postcode":"07929",
    "sg:province":"Th\u00fcringen",
    "wof:name":"Raiffeisenbank-volksbank Schleiz, E. G.",
    "wof:placetype":"venue"
},
  "geometry": {"coordinates":[11.730914,50.501331],"type":"Point"}
}