{
  "type": "Feature",
  "properties": {
    "iso:country":"DE",
    "sg:address":"An der Kammerstatt 9a",
    "sg:city":"Wartenberg",
    "sg:phone":"+49 8762/3853",
    "sg:postcode":"85456",
    "sg:province":"Bayern",
    "wof:name":"Wolfgang Langfellner",
    "wof:placetype":"venue"
},
  "geometry": {"coordinates":[11.984416008,48.410446167],"type":"Point"}
}