{
  "type": "Feature",
  "properties": {
    "iso:country":"DE",
    "sg:address":"Gutenpaarener Str. 4",
    "sg:city":"Wachow",
    "sg:phone":"+49 33239/70318",
    "sg:postcode":"14641",
    "sg:province":"Brandenburg",
    "wof:name":"Genossenschaft Wachower Landwirte (gwl) Eg",
    "wof:placetype":"venue"
},
  "geometry": {"coordinates":[12.75985,52.53051],"type":"Point"}
}