{
  "type": "Feature",
  "properties": {
    "iso:country":"DE",
    "sg:address":"Ernststr. 8",
    "sg:city":"Neustadt",
    "sg:phone":"+49 9568/5196",
    "sg:postcode":"96465",
    "sg:province":"Bayern",
    "wof:name":"Armin Wohlleben Inh. Gerda Stricker",
    "wof:placetype":"venue"
},
  "geometry": {"coordinates":[11.123493,50.327831],"type":"Point"}
}