{
  "type": "Feature",
  "properties": {
    "iso:country":"DE",
    "sg:address":"Hauptstr. 107",
    "sg:city":"Klotten",
    "sg:phone":"+49 2671/8650",
    "sg:postcode":"56818",
    "sg:province":"Rheinland-Pfalz",
    "wof:name":"Hans Castor",
    "wof:placetype":"venue"
},
  "geometry": {"coordinates":[7.2008509636,50.165019989],"type":"Point"}
}