{
  "type": "Feature",
  "properties": {
    "iso:country":"DE",
    "sg:address":"Tomatshalde 2",
    "sg:city":"Winnenden",
    "sg:phone":"+49 7195/3841",
    "sg:postcode":"71364",
    "sg:province":"Baden-W\u00fcrttemberg",
    "wof:name":"Stefan Kratz Steuerberater",
    "wof:placetype":"venue"
},
  "geometry": {"coordinates":[9.426361084,48.8847694397],"type":"Point"}
}