{
  "type": "Feature",
  "properties": {
    "iso:country":"DE",
    "sg:address":"Allmendstr. 12",
    "sg:city":"Lahr",
    "sg:phone":"+49 7821/51128",
    "sg:postcode":"77933",
    "sg:province":"Baden-W\u00fcrttemberg",
    "wof:name":"Klaus Isenmann",
    "wof:placetype":"venue"
},
  "geometry": {"coordinates":[7.833506,48.32896],"type":"Point"}
}