{
  "type": "Feature",
  "properties": {
    "iso:country":"DE",
    "sg:address":"St.-Lorenz-Str. 21",
    "sg:city":"Oberasbach",
    "sg:phone":"+49 911/694956",
    "sg:postcode":"90522",
    "sg:province":"Bayern",
    "wof:name":"Richard R\u00f6hling",
    "wof:placetype":"venue"
},
  "geometry": {"coordinates":[10.964757,49.428352],"type":"Point"}
}