{
  "type": "Feature",
  "properties": {
    "iso:country":"DE",
    "sg:address":"Mittlerer Weg 4",
    "sg:city":"Crailsheim",
    "sg:phone":"+49 7951/7040",
    "sg:postcode":"74564",
    "sg:province":"Baden-W\u00fcrttemberg",
    "wof:name":"Hans G\u00f6gelein",
    "wof:placetype":"venue"
},
  "geometry": {"coordinates":[10.075205,49.137291],"type":"Point"}
}