{
  "type": "Feature",
  "properties": {
    "iso:country":"DE",
    "sg:address":"Vorderstr. 31",
    "sg:city":"K\u00f6nigstein",
    "sg:phone":"+49 6173",
    "sg:postcode":"61462",
    "sg:province":"Hessen",
    "wof:name":"Allfinanzkontor: G\u00fcnstige Kfz-versicherungen",
    "wof:placetype":"venue"
},
  "geometry": {"coordinates":[8.491822,50.1716],"type":"Point"}
}