{
  "type": "Feature",
  "properties": {
    "iso:country":"DE",
    "sg:address":"Hauptstr. 115a",
    "sg:city":"Frechen",
    "sg:phone":"+49 2234/271700",
    "sg:postcode":"50226",
    "sg:province":"Nordrhein-Westfalen",
    "wof:name":"Johannes Schuster",
    "wof:placetype":"venue"
},
  "geometry": {"coordinates":[6.8076701164,50.9097366333],"type":"Point"}
}