{
  "type": "Feature",
  "properties": {
    "iso:country":"DE",
    "sg:address":"Junkerstr. 1",
    "sg:city":"L\u00fcchow",
    "sg:phone":"+49 5841/2229",
    "sg:postcode":"29439",
    "sg:province":"Niedersachsen",
    "wof:name":"Werner Kreschel Rechtsanwalt Und Notar",
    "wof:placetype":"venue"
},
  "geometry": {"coordinates":[11.1542129517,52.96692276],"type":"Point"}
}