{
  "type": "Feature",
  "properties": {
    "iso:country":"DE",
    "sg:address":"Erasmusstr. 20",
    "sg:city":"Neuss",
    "sg:phone":"+49 2131/745753",
    "sg:postcode":"41466",
    "sg:province":"Nordrhein-Westfalen",
    "wof:name":"Franz Hoffmann Steuerberater",
    "wof:placetype":"venue"
},
  "geometry": {"coordinates":[6.6873941422,51.1630439758],"type":"Point"}
}