{
  "type": "Feature",
  "properties": {
    "iso:country":"DE",
    "sg:address":"Schlangenweg 8",
    "sg:city":"Freiburg",
    "sg:postcode":"79104",
    "sg:province":"Baden-W\u00fcrttemberg",
    "wof:name":"Suermondt Beteiligungs-gmbh",
    "wof:placetype":"venue"
},
  "geometry": {"coordinates":[7.872232,48.002975],"type":"Point"}
}