{
  "type": "Feature",
  "properties": {
    "iso:country":"DE",
    "sg:address":"Schm\u00e4hinger Str. 1",
    "sg:city":"Reimlingen",
    "sg:phone":"+49 9081/3333",
    "sg:postcode":"86756",
    "sg:province":"Bayern",
    "wof:name":"Johann Braun",
    "wof:placetype":"venue"
},
  "geometry": {"coordinates":[10.5168352127,48.8167228699],"type":"Point"}
}