{
  "type": "Feature",
  "properties": {
    "iso:country":"DE",
    "sg:address":"Bessenbacher Weg 8",
    "sg:city":"Haibach",
    "sg:phone":"+49 6021/23155",
    "sg:postcode":"63808",
    "sg:province":"Bayern",
    "wof:name":"Franz Kolb Gmbh",
    "wof:placetype":"venue"
},
  "geometry": {"coordinates":[9.1962509155,49.967502594],"type":"Point"}
}