{
  "type": "Feature",
  "properties": {
    "iso:country":"DE",
    "sg:address":"Holperdorper Str. 46",
    "sg:city":"Lienen",
    "sg:phone":"+49 5483/388",
    "sg:postcode":"49536",
    "sg:province":"Nordrhein-Westfalen",
    "wof:name":"Holperst\u00fcbchen Inh. H. P. Kr\u00f6plin",
    "wof:placetype":"venue"
},
  "geometry": {"coordinates":[7.9809889793,52.1661758423],"type":"Point"}
}