{
  "type": "Feature",
  "properties": {
    "iso:country":"DE",
    "sg:address":"Steinstr. 1 -3",
    "sg:city":"D\u00fcsseldorf",
    "sg:phone":"+49 211/324888",
    "sg:postcode":"40212",
    "sg:province":"Nordrhein-Westfalen",
    "wof:name":"Laurel",
    "wof:placetype":"venue"
},
  "geometry": {"coordinates":[6.779604,51.222893],"type":"Point"}
}