{
  "type": "Feature",
  "properties": {
    "iso:country":"DE",
    "sg:address":"Blankensteiner Str. 245",
    "sg:city":"Bochum",
    "sg:phone":"+49 234/47746",
    "sg:postcode":"44797",
    "sg:province":"Nordrhein-Westfalen",
    "wof:name":"Procom-plus Gesellschaft F\u00fcr",
    "wof:placetype":"venue"
},
  "geometry": {"coordinates":[7.2008500099,51.4267082214],"type":"Point"}
}