{
  "type": "Feature",
  "properties": {
    "iso:country":"DE",
    "sg:address":"Hellbrookstr. 83",
    "sg:city":"Hamburg",
    "sg:phone":"+49 40/616054",
    "sg:postcode":"22305",
    "sg:province":"Hamburg",
    "wof:name":"Dieter Feldtmann",
    "wof:placetype":"venue"
},
  "geometry": {"coordinates":[10.049314,53.591824],"type":"Point"}
}