{
  "type": "Feature",
  "properties": {
    "iso:country":"DE",
    "sg:address":"Eulenspiegelstr. 104",
    "sg:city":"M\u00fcnchen",
    "sg:phone":"+49 89/6014293",
    "sg:postcode":"81739",
    "sg:province":"Bayern",
    "wof:name":"Veronika Gr\u00e4fin Von Matuschka Heilpraktikerin",
    "wof:placetype":"venue"
},
  "geometry": {"coordinates":[11.6646842957,48.0794715881],"type":"Point"}
}