{
  "type": "Feature",
  "properties": {
    "iso:country":"DE",
    "sg:address":"Neuer Wall 9",
    "sg:city":"Hamburg",
    "sg:phone":"+49 40/3510530",
    "sg:postcode":"20354",
    "sg:province":"Hamburg",
    "wof:name":"Richter Und Pock Rechtsanw\u00e4lte",
    "wof:placetype":"venue"
},
  "geometry": {"coordinates":[9.9926099777,53.5523605347],"type":"Point"}
}