{
  "type": "Feature",
  "properties": {
    "iso:country":"DE",
    "sg:address":"Hierbach",
    "sg:city":"Hierbach",
    "sg:phone":"+49 7755/8768",
    "sg:postcode":"79875",
    "sg:province":"Baden-W\u00fcrttemberg",
    "wof:name":"Hotzenwald-bank Eg",
    "wof:placetype":"venue"
},
  "geometry": {"coordinates":[8.09123,47.686001],"type":"Point"}
}