{
  "type": "Feature",
  "properties": {
    "iso:country":"DE",
    "sg:address":"Eicherstr. 7",
    "sg:city":"Karlskron",
    "sg:phone":"+49 8453/7480",
    "sg:postcode":"85123",
    "sg:province":"Bayern",
    "wof:name":"Gabriele Schlesinger Hebamme",
    "wof:placetype":"venue"
},
  "geometry": {"coordinates":[11.43903,48.67131],"type":"Point"}
}