{
  "type": "Feature",
  "properties": {
    "iso:country":"DE",
    "sg:address":"Otto-Hahn-Str. 9",
    "sg:city":"M\u00fchlheim",
    "sg:phone":"+49 6108/78244",
    "sg:postcode":"63165",
    "sg:province":"Hessen",
    "wof:name":"Pt-chemie Gmbh",
    "wof:placetype":"venue"
},
  "geometry": {"coordinates":[8.845867157,50.1126289368],"type":"Point"}
}