{
  "type": "Feature",
  "properties": {
    "iso:country":"DE",
    "sg:address":"F\u00e4hrstr. 14",
    "sg:city":"Duisburg",
    "sg:phone":"+49 203/340681",
    "sg:postcode":"47058",
    "sg:province":"Nordrhein-Westfalen",
    "wof:name":"Pflanzkunst Garten- Und Landschaftsbau Gmbh",
    "wof:placetype":"venue"
},
  "geometry": {"coordinates":[6.788454,51.448605],"type":"Point"}
}