{
  "type": "Feature",
  "properties": {
    "iso:country":"DE",
    "sg:address":"Hannoversche Heerstr. 44",
    "sg:city":"Peine",
    "sg:phone":"+49 5171/23772",
    "sg:postcode":"31228",
    "sg:province":"Niedersachsen",
    "wof:name":"Manfred Schl\u00fcter Gmbh & Co. Kg",
    "wof:placetype":"venue"
},
  "geometry": {"coordinates":[10.2041940689,52.3266181946],"type":"Point"}
}