{
  "type": "Feature",
  "properties": {
    "iso:country":"DE",
    "sg:address":"Monschauer Str. 203a",
    "sg:city":"D\u00fcren",
    "sg:phone":"+49 2421/63889",
    "sg:postcode":"52355",
    "sg:province":"Nordrhein-Westfalen",
    "wof:name":"Ch. Knillmann",
    "wof:placetype":"venue"
},
  "geometry": {"coordinates":[6.465233,50.78706],"type":"Point"}
}