{
  "type": "Feature",
  "properties": {
    "iso:country":"DE",
    "sg:address":"Kiebitzhof 9a",
    "sg:city":"Hamburg",
    "sg:phone":"+49 40/2518714",
    "sg:postcode":"22089",
    "sg:province":"Hamburg",
    "wof:name":"Happy Help H\u00e4usliche Krankenpflege",
    "wof:placetype":"venue"
},
  "geometry": {"coordinates":[10.036642,53.563416],"type":"Point"}
}