{
  "type": "Feature",
  "properties": {
    "iso:country":"DE",
    "sg:address":"Harth\u00f6fe 34",
    "sg:city":"Nusplingen",
    "sg:phone":"+49 7429/672",
    "sg:postcode":"72362",
    "sg:province":"Baden-W\u00fcrttemberg",
    "wof:name":"Josef Stier",
    "wof:placetype":"venue"
},
  "geometry": {"coordinates":[8.936788,48.124554],"type":"Point"}
}