{
  "type": "Feature",
  "properties": {
    "iso:country":"DE",
    "sg:address":"Schwabstr. 19",
    "sg:city":"Heilbronn",
    "sg:phone":"+49 7131/173853",
    "sg:postcode":"74074",
    "sg:province":"Baden-W\u00fcrttemberg",
    "wof:name":"Andreas M\u00fcller",
    "wof:placetype":"venue"
},
  "geometry": {"coordinates":[9.229552269,49.1321487427],"type":"Point"}
}