{
  "type": "Feature",
  "properties": {
    "iso:country":"DE",
    "sg:address":"Malensteinweg",
    "sg:city":"Oberammergau",
    "sg:phone":"+49 8822/3955",
    "sg:postcode":"82487",
    "sg:province":"Bayern",
    "wof:name":"Jochen R\u00f6sner",
    "wof:placetype":"venue"
},
  "geometry": {"coordinates":[11.0640153885,47.5934257507],"type":"Point"}
}