{
  "type": "Feature",
  "properties": {
    "iso:country":"DE",
    "sg:address":"B\u00fcrgerm.-Fichtner-Str. 1",
    "sg:city":"Pleinfeld",
    "sg:postcode":"91785",
    "sg:province":"Bayern",
    "wof:name":"Ev. Luth. Pfarramt",
    "wof:placetype":"venue"
},
  "geometry": {"coordinates":[10.983379364,49.1064758301],"type":"Point"}
}