{
  "type": "Feature",
  "properties": {
    "iso:country":"DE",
    "sg:address":"Martin-Schleyer-Str. 38",
    "sg:city":"Konstanz",
    "sg:phone":"+49 7531/43244",
    "sg:postcode":"78465",
    "sg:province":"Baden-W\u00fcrttemberg",
    "wof:name":"Heinrich Bottlang",
    "wof:placetype":"venue"
},
  "geometry": {"coordinates":[9.172189,47.715397],"type":"Point"}
}