{
  "type": "Feature",
  "properties": {
    "iso:country":"DE",
    "sg:address":"Kiefernweg 14",
    "sg:city":"Kleinmachnow",
    "sg:phone":"+49 33203/20631",
    "sg:postcode":"14532",
    "sg:province":"Brandenburg",
    "wof:name":"Ejs Ingenieurges. Mbh",
    "wof:placetype":"venue"
},
  "geometry": {"coordinates":[13.240454,52.406464],"type":"Point"}
}