{
  "type": "Feature",
  "properties": {
    "iso:country":"DE",
    "sg:address":"Gerhard-Rohlfs-Str. 23",
    "sg:city":"Bremen",
    "sg:phone":"+49 421/661619",
    "sg:postcode":"28757",
    "sg:province":"Bremen",
    "wof:name":"Benetton Vegesack",
    "wof:placetype":"venue"
},
  "geometry": {"coordinates":[8.618081,53.173046],"type":"Point"}
}