{
  "type": "Feature",
  "properties": {
    "iso:country":"DE",
    "sg:address":"Troschenreuth 8",
    "sg:city":"Emtmannsberg",
    "sg:phone":"+49 9209/291",
    "sg:postcode":"95517",
    "sg:province":"Bayern",
    "wof:name":"Hans Schwenk",
    "wof:placetype":"venue"
},
  "geometry": {"coordinates":[11.653121,49.894848],"type":"Point"}
}