{
  "type": "Feature",
  "properties": {
    "iso:country":"DE",
    "sg:address":"Friedhofstr. 3",
    "sg:city":"Selzen",
    "sg:phone":"+49 6737/9399",
    "sg:postcode":"55278",
    "sg:province":"Rheinland-Pfalz",
    "wof:name":"Andreas Kalbfu\u00df",
    "wof:placetype":"venue"
},
  "geometry": {"coordinates":[8.255828,49.861107],"type":"Point"}
}