{
  "type": "Feature",
  "properties": {
    "iso:country":"DE",
    "sg:address":"Gartenweg 1a",
    "sg:city":"Halberstadt",
    "sg:phone":"+49 3941/603587",
    "sg:postcode":"38820",
    "sg:province":"Sachsen-Anhalt",
    "wof:name":"A. Paulmann",
    "wof:placetype":"venue"
},
  "geometry": {"coordinates":[11.047859,51.892727],"type":"Point"}
}