{
  "type": "Feature",
  "properties": {
    "iso:country":"DE",
    "sg:address":"Rutenstr. 1",
    "sg:city":"Crailsheim",
    "sg:phone":"+49 7951/28647",
    "sg:postcode":"74564",
    "sg:province":"Baden-W\u00fcrttemberg",
    "wof:name":"Bernd Friedrich",
    "wof:placetype":"venue"
},
  "geometry": {"coordinates":[10.026015,49.141205],"type":"Point"}
}