{
  "type": "Feature",
  "properties": {
    "iso:country":"DE",
    "sg:address":"Hauptstr. 195",
    "sg:city":"Krombach",
    "sg:phone":"+49 6024/3139",
    "sg:postcode":"63829",
    "sg:province":"Bayern",
    "wof:name":"Alfred Glaab",
    "wof:placetype":"venue"
},
  "geometry": {"coordinates":[9.20606,50.094471],"type":"Point"}
}