{
  "type": "Feature",
  "properties": {
    "iso:country":"DE",
    "sg:address":"Nauener Str. 28",
    "sg:city":"Friesack",
    "sg:phone":"+49 4933/2351332",
    "sg:postcode":"14662",
    "sg:province":"Brandenburg",
    "wof:name":"Joachim Hansen",
    "wof:placetype":"venue"
},
  "geometry": {"coordinates":[12.5825605392,52.7409210205],"type":"Point"}
}