{
  "type": "Feature",
  "properties": {
    "iso:country":"DE",
    "sg:address":"Sch\u00e4fersteig 20",
    "sg:city":"Villingen-Schwenningen",
    "sg:phone":"+49 7721/27471",
    "sg:postcode":"78048",
    "sg:province":"Baden-W\u00fcrttemberg",
    "wof:name":"Gerhard V\u00f6gele",
    "wof:placetype":"venue"
},
  "geometry": {"coordinates":[8.473512,48.055187],"type":"Point"}
}