{
  "type": "Feature",
  "properties": {
    "iso:country":"DE",
    "sg:address":"Bistard 40",
    "sg:city":"Viersen",
    "sg:phone":"+49 2162/95400",
    "sg:postcode":"41751",
    "sg:province":"Nordrhein-Westfalen",
    "wof:name":"Gotzes Internationale Personenbef\u00f6rderung Gmbh",
    "wof:placetype":"venue"
},
  "geometry": {"coordinates":[6.3343200684,51.2760887146],"type":"Point"}
}