{
  "type": "Feature",
  "properties": {
    "iso:country":"DE",
    "sg:address":"Vogelsangstr. 25",
    "sg:city":"Stolberg",
    "sg:phone":"+49 2402/87770",
    "sg:postcode":"52222",
    "sg:province":"Nordrhein-Westfalen",
    "wof:name":"H. Heinen",
    "wof:placetype":"venue"
},
  "geometry": {"coordinates":[6.2352571487,50.7673683167],"type":"Point"}
}