{
  "type": "Feature",
  "properties": {
    "iso:country":"DE",
    "sg:address":"Am Flie\u00df 10",
    "sg:city":"N\u00f6rvenich",
    "sg:phone":"+49 2426/5457",
    "sg:postcode":"52388",
    "sg:province":"Nordrhein-Westfalen",
    "wof:name":"Karl-heinz M\u00fcller",
    "wof:placetype":"venue"
},
  "geometry": {"coordinates":[6.679595,50.813477],"type":"Point"}
}