{
  "type": "Feature",
  "properties": {
    "iso:country":"DE",
    "sg:address":"Kappel 28",
    "sg:city":"Eberhardzell",
    "sg:phone":"+49 4973/5593200",
    "sg:postcode":"88436",
    "sg:province":"Baden-W\u00fcrttemberg",
    "wof:name":"Holzwerk Gebr. Schneider",
    "wof:placetype":"venue"
},
  "geometry": {"coordinates":[9.8195848465,47.9906578064],"type":"Point"}
}