{
  "type": "Feature",
  "properties": {
    "iso:country":"DE",
    "sg:address":"Zefersgrund 1a",
    "sg:city":"Bad Peterstal-Griesbach",
    "sg:phone":"+49 7806/8068",
    "sg:postcode":"77740",
    "sg:province":"Baden-W\u00fcrttemberg",
    "wof:name":"Josef Zimmermann",
    "wof:placetype":"venue"
},
  "geometry": {"coordinates":[8.2091646194,48.4303283691],"type":"Point"}
}