{
  "type": "Feature",
  "properties": {
    "iso:country":"DE",
    "sg:address":"Ludwigstr. 44a",
    "sg:city":"Kaiserslautern",
    "sg:phone":"+49 631/68315",
    "sg:postcode":"67657",
    "sg:province":"Rheinland-Pfalz",
    "wof:name":"A-z Immobilien Buchwald & Co. Ohg",
    "wof:placetype":"venue"
},
  "geometry": {"coordinates":[7.7751970291,49.4482078552],"type":"Point"}
}