{
  "type": "Feature",
  "properties": {
    "iso:country":"DE",
    "sg:address":"Wilhelmsh\u00f6her Allee 116",
    "sg:city":"Kassel",
    "sg:phone":"+49 561/776649",
    "sg:postcode":"34119",
    "sg:province":"Hessen",
    "wof:name":"Cafe-restaurant Limerick",
    "wof:placetype":"venue"
},
  "geometry": {"coordinates":[9.4666996002,51.3127174377],"type":"Point"}
}