{
  "type": "Feature",
  "properties": {
    "iso:country":"DE",
    "sg:address":"Gotenstr. 1",
    "sg:city":"Bochum",
    "sg:phone":"+49 234/681448",
    "sg:postcode":"44793",
    "sg:province":"Nordrhein-Westfalen",
    "wof:name":"B. Fitz",
    "wof:placetype":"venue"
},
  "geometry": {"coordinates":[7.188706,51.476799],"type":"Point"}
}