{
  "type": "Feature",
  "properties": {
    "iso:country":"DE",
    "sg:address":"91567",
    "sg:city":"Herrieden",
    "sg:postcode":"91567",
    "sg:province":"Bayern",
    "wof:name":"Raiffeisenbank Herrieden Eg",
    "wof:placetype":"venue"
},
  "geometry": {"coordinates":[10.48197,49.230461],"type":"Point"}
}