{
  "type": "Feature",
  "properties": {
    "iso:country":"DE",
    "sg:address":"Bockshard 1",
    "sg:city":"Reichshof",
    "sg:phone":"+49 2261/55708",
    "sg:postcode":"51580",
    "sg:province":"Nordrhein-Westfalen",
    "wof:name":"Hans-joachim Hufschmidt Ingenieur",
    "wof:placetype":"venue"
},
  "geometry": {"coordinates":[7.6101732254,50.9833564758],"type":"Point"}
}