{
  "type": "Feature",
  "properties": {
    "iso:country":"DE",
    "sg:address":"Schlo\u00dfstr. 22",
    "sg:city":"Marquartstein",
    "sg:phone":"+49 8641/63267",
    "sg:postcode":"83250",
    "sg:province":"Bayern",
    "wof:name":"Pannonconsult Vertriebs- Und",
    "wof:placetype":"venue"
},
  "geometry": {"coordinates":[12.441815,47.763306],"type":"Point"}
}