{
  "type": "Feature",
  "properties": {
    "iso:country":"DE",
    "sg:address":"Triftstr. 28",
    "sg:city":"Bad M\u00fcnster-Ebernburg",
    "sg:phone":"+49 6708/2241",
    "sg:postcode":"55583",
    "sg:province":"Rheinland-Pfalz",
    "wof:name":"Rudolf Wohlleben",
    "wof:placetype":"venue"
},
  "geometry": {"coordinates":[7.83562,49.809418],"type":"Point"}
}