{
  "type": "Feature",
  "properties": {
    "iso:country":"DE",
    "sg:address":"Burginatium 3",
    "sg:city":"Kalkar",
    "sg:phone":"+49 2824/3259",
    "sg:postcode":"47546",
    "sg:province":"Nordrhein-Westfalen",
    "wof:name":"G. Martens",
    "wof:placetype":"venue"
},
  "geometry": {"coordinates":[6.319478,51.712204],"type":"Point"}
}