{
  "type": "Feature",
  "properties": {
    "iso:country":"DE",
    "sg:address":"Alte Poststr. 17",
    "sg:city":"Pfalzgrafenweiler",
    "sg:phone":"+49 7445/6482",
    "sg:postcode":"72285",
    "sg:province":"Baden-W\u00fcrttemberg",
    "wof:name":"R\u00e4ucherspezialit\u00e4ten Pfau Gmbh",
    "wof:placetype":"venue"
},
  "geometry": {"coordinates":[8.5257816315,48.5064125061],"type":"Point"}
}