{
  "type": "Feature",
  "properties": {
    "iso:country":"DE",
    "sg:address":"Krahnendonk 121",
    "sg:city":"M\u00f6nchengladbach",
    "sg:phone":"+49 2161/664011",
    "sg:postcode":"41066",
    "sg:province":"Nordrhein-Westfalen",
    "wof:name":"Konrad Busche Gmbh & Co. Kg",
    "wof:placetype":"venue"
},
  "geometry": {"coordinates":[6.4698290825,51.2295646667],"type":"Point"}
}