{
  "type": "Feature",
  "properties": {
    "iso:country":"DE",
    "sg:address":"Ripsd\u00f6rnestr. 36a",
    "sg:city":"Oberhausen",
    "sg:phone":"+49 208/601818",
    "sg:postcode":"46119",
    "sg:province":"Nordrhein-Westfalen",
    "wof:name":"Edeltrud Eitner-ott",
    "wof:placetype":"venue"
},
  "geometry": {"coordinates":[6.8961191177,51.5139732361],"type":"Point"}
}