{
  "type": "Feature",
  "properties": {
    "iso:country":"DE",
    "sg:address":"Elsterweg 101",
    "sg:city":"Pfullingen",
    "sg:phone":"+49 7121/79658",
    "sg:postcode":"72793",
    "sg:province":"Baden-W\u00fcrttemberg",
    "wof:name":"H. Platzek Steuerberater",
    "wof:placetype":"venue"
},
  "geometry": {"coordinates":[9.2126264572,48.4574584961],"type":"Point"}
}