{
  "type": "Feature",
  "properties": {
    "iso:country":"DE",
    "sg:address":"Polcher Str. 103",
    "sg:city":"Mayen",
    "sg:phone":"+49 2651/5051",
    "sg:postcode":"56727",
    "sg:province":"Rheinland-Pfalz",
    "wof:name":"Maschinenvertrieb Alois Kast Gmbh & Co.",
    "wof:placetype":"venue"
},
  "geometry": {"coordinates":[7.230476,50.321316],"type":"Point"}
}