{
  "type": "Feature",
  "properties": {
    "iso:country":"DE",
    "sg:address":"Marliring 44",
    "sg:city":"L\u00fcbeck",
    "sg:phone":"+49 451/8092047",
    "sg:postcode":"23566",
    "sg:province":"Schleswig-Holstein",
    "wof:name":"Stefan Schirrmacher",
    "wof:placetype":"venue"
},
  "geometry": {"coordinates":[10.7203083038,53.8702888489],"type":"Point"}
}