{
  "type": "Feature",
  "properties": {
    "iso:country":"DE",
    "sg:address":"Vorderstr. 12",
    "sg:city":"Stockstadt",
    "sg:phone":"+49 6158/85293",
    "sg:postcode":"64589",
    "sg:province":"Hessen",
    "wof:name":"Ria Kabey P\u00e4chter: Wedel",
    "wof:placetype":"venue"
},
  "geometry": {"coordinates":[8.4668102264,49.8110313416],"type":"Point"}
}