{
  "type": "Feature",
  "properties": {
    "iso:country":"DE",
    "sg:address":"Hagenbeckallee 2",
    "sg:city":"Hamburg",
    "sg:phone":"+49 40/545661",
    "sg:postcode":"22527",
    "sg:province":"Hamburg",
    "wof:name":"Britta Nielsen",
    "wof:placetype":"venue"
},
  "geometry": {"coordinates":[9.933227,53.59425],"type":"Point"}
}