{
  "type": "Feature",
  "properties": {
    "iso:country":"DE",
    "sg:address":"Ottostr. 26",
    "sg:city":"Schwandorf",
    "sg:phone":"+49 9431/51157",
    "sg:postcode":"92421",
    "sg:province":"Bayern",
    "wof:name":"Johann Kammerl",
    "wof:placetype":"venue"
},
  "geometry": {"coordinates":[12.1024770737,49.3160018921],"type":"Point"}
}