{
  "type": "Feature",
  "properties": {
    "iso:country":"DE",
    "sg:address":"Kantstr. 9",
    "sg:city":"Ravensburg",
    "sg:phone":"+49 751/92833",
    "sg:postcode":"88213",
    "sg:province":"Baden-W\u00fcrttemberg",
    "wof:name":"Brigitte Streif Heilpraktikerin",
    "wof:placetype":"venue"
},
  "geometry": {"coordinates":[9.5813064575,47.7802124023],"type":"Point"}
}