{
  "type": "Feature",
  "properties": {
    "iso:country":"DE",
    "sg:address":"Beethovenweg 37",
    "sg:city":"Horn-Bad Meinberg",
    "sg:phone":"+49 5234/99979",
    "sg:postcode":"32805",
    "sg:province":"Nordrhein-Westfalen",
    "wof:name":"Klaus R\u00e4ker",
    "wof:placetype":"venue"
},
  "geometry": {"coordinates":[8.968449,51.913025],"type":"Point"}
}