{
  "type": "Feature",
  "properties": {
    "iso:country":"DE",
    "sg:address":"Lohweg 35",
    "sg:city":"Neufahrn",
    "sg:phone":"+49 8165/65839",
    "sg:postcode":"85375",
    "sg:province":"Bayern",
    "wof:name":"Classic Arts Gmbh",
    "wof:placetype":"venue"
},
  "geometry": {"coordinates":[11.6558151245,48.3071327209],"type":"Point"}
}