{
  "type": "Feature",
  "properties": {
    "iso:country":"DE",
    "sg:address":"Rheinstr. 38",
    "sg:city":"Langen",
    "sg:phone":"+49 6103/28298",
    "sg:postcode":"63225",
    "sg:province":"Hessen",
    "wof:name":"Pinguin",
    "wof:placetype":"venue"
},
  "geometry": {"coordinates":[8.6758842468,49.9887084961],"type":"Point"}
}