{
  "type": "Feature",
  "properties": {
    "iso:country":"DE",
    "sg:address":"Lindenstr. 4",
    "sg:city":"Sonsbeck",
    "sg:phone":"+49 2838/2517",
    "sg:postcode":"47665",
    "sg:province":"Nordrhein-Westfalen",
    "wof:name":"H.-p. Stamsen",
    "wof:placetype":"venue"
},
  "geometry": {"coordinates":[6.3733949661,51.6055107117],"type":"Point"}
}