{
  "type": "Feature",
  "properties": {
    "iso:country":"DE",
    "sg:address":"Bel\u00dfstr. 51",
    "sg:city":"Berlin",
    "sg:phone":"+49 30/7754350",
    "sg:postcode":"12249",
    "sg:province":"Berlin",
    "wof:name":"Esso Deutschland Gmbh",
    "wof:placetype":"venue"
},
  "geometry": {"coordinates":[13.3651628494,52.4273681641],"type":"Point"}
}