{
  "type": "Feature",
  "properties": {
    "iso:country":"DE",
    "sg:address":"Berg 12",
    "sg:city":"Schwalmtal",
    "sg:phone":"+49 2163/45206",
    "sg:postcode":"41366",
    "sg:province":"Nordrhein-Westfalen",
    "wof:name":"Johannes Berg",
    "wof:placetype":"venue"
},
  "geometry": {"coordinates":[6.301084,51.214249],"type":"Point"}
}