{
  "type": "Feature",
  "properties": {
    "iso:country":"DE",
    "sg:address":"Rodaer Str. 20",
    "sg:city":"Lippersdorf-Erdmannsdorf",
    "sg:phone":"+49 36426/50238",
    "sg:postcode":"07646",
    "sg:province":"Th\u00fcringen",
    "wof:name":"Heike Herold",
    "wof:placetype":"venue"
},
  "geometry": {"coordinates":[11.75468,50.847301],"type":"Point"}
}