{
  "type": "Feature",
  "properties": {
    "iso:country":"DE",
    "sg:address":"Altcosch\u00fctz 15",
    "sg:city":"Dresden",
    "sg:phone":"+49 351/4014979",
    "sg:postcode":"01189",
    "sg:province":"Sachsen",
    "wof:name":"Uwe Naumann",
    "wof:placetype":"venue"
},
  "geometry": {"coordinates":[13.6934757233,51.0187225342],"type":"Point"}
}