{
  "type": "Feature",
  "properties": {
    "iso:country":"DE",
    "sg:address":"Dieterskircher Str.23-25",
    "sg:city":"Uttenweiler",
    "sg:phone":"+49 7374",
    "sg:postcode":"88524",
    "sg:province":"Baden-W\u00fcrttemberg",
    "wof:name":"Bauunternehmen Fritschle Gmbh",
    "wof:placetype":"venue"
},
  "geometry": {"coordinates":[9.610619545,48.1516036987],"type":"Point"}
}