{
  "type": "Feature",
  "properties": {
    "iso:country":"DE",
    "sg:address":"Nordring 210",
    "sg:city":"Borken",
    "sg:phone":"+49 2861/5113",
    "sg:postcode":"46325",
    "sg:province":"Nordrhein-Westfalen",
    "wof:name":"Total Fina Elf Mineral\u00f6l Und Chemie Gmbh",
    "wof:placetype":"venue"
},
  "geometry": {"coordinates":[6.8381671906,51.8421554565],"type":"Point"}
}