{
  "type": "Feature",
  "properties": {
    "iso:country":"DE",
    "sg:address":"Seestr. 68",
    "sg:city":"Seefeld",
    "sg:phone":"+49 8152/79293",
    "sg:postcode":"82229",
    "sg:province":"Bayern",
    "wof:name":"Strandbad Hechendorf",
    "wof:placetype":"venue"
},
  "geometry": {"coordinates":[11.1826400757,48.0272407532],"type":"Point"}
}