{
  "type": "Feature",
  "properties": {
    "iso:country":"DE",
    "sg:address":"Hauptstr. 47",
    "sg:city":"Pirmasens",
    "sg:phone":"+49 6331/41871",
    "sg:postcode":"66953",
    "sg:province":"Rheinland-Pfalz",
    "wof:name":"Reformhaus Joachim Escher",
    "wof:placetype":"venue"
},
  "geometry": {"coordinates":[7.6053609848,49.1982307434],"type":"Point"}
}