{
  "type": "Feature",
  "properties": {
    "iso:country":"DE",
    "sg:address":"Dieckstr. 6",
    "sg:city":"M\u00fcnster",
    "sg:postcode":"48145",
    "sg:province":"Nordrhein-Westfalen",
    "wof:name":"Mgr Grundst\u00fccks- Gesellschaft Mbh & Co. Kg",
    "wof:placetype":"venue"
},
  "geometry": {"coordinates":[7.6480169296,51.9684677124],"type":"Point"}
}