{
  "type": "Feature",
  "properties": {
    "iso:country":"DE",
    "sg:address":"Kronengasse 1",
    "sg:city":"\u00dcberlingen",
    "sg:phone":"+49 7551/2244",
    "sg:postcode":"88662",
    "sg:province":"Baden-W\u00fcrttemberg",
    "wof:name":"Marianne Steinmann Praxis F\u00fcr Ergotherapie",
    "wof:placetype":"venue"
},
  "geometry": {"coordinates":[9.159525,47.766499],"type":"Point"}
}