{
  "type": "Feature",
  "properties": {
    "iso:country":"DE",
    "sg:address":"Im Grund 4",
    "sg:city":"Mei\u00dfenheim",
    "sg:postcode":"77974",
    "sg:province":"Baden-W\u00fcrttemberg",
    "wof:name":"Urban Direkt Gmbh",
    "wof:placetype":"venue"
},
  "geometry": {"coordinates":[7.776528,48.415703],"type":"Point"}
}