{
  "type": "Feature",
  "properties": {
    "iso:country":"DE",
    "sg:address":"Steinstr. 48",
    "sg:city":"Dortmund",
    "sg:phone":"+49 231/5022150",
    "sg:postcode":"44147",
    "sg:province":"Nordrhein-Westfalen",
    "wof:name":"Mahn- Und Gedenkst\u00e4tte Steinwache",
    "wof:placetype":"venue"
},
  "geometry": {"coordinates":[7.460673,51.519943],"type":"Point"}
}