{
  "type": "Feature",
  "properties": {
    "iso:country":"DE",
    "sg:address":"Sulzgrieser Str. 49",
    "sg:city":"Esslingen",
    "sg:phone":"+49 711/371721",
    "sg:postcode":"73733",
    "sg:province":"Baden-W\u00fcrttemberg",
    "wof:name":"Wilhelm Schneider",
    "wof:placetype":"venue"
},
  "geometry": {"coordinates":[9.298911,48.754799],"type":"Point"}
}