{
  "type": "Feature",
  "properties": {
    "iso:country":"DE",
    "sg:address":"Dechant-R\u00f6mer-Str. 29",
    "sg:city":"Rheine",
    "sg:phone":"+49 5975/1232",
    "sg:postcode":"48432",
    "sg:province":"Nordrhein-Westfalen",
    "wof:name":"Josef Gronotte",
    "wof:placetype":"venue"
},
  "geometry": {"coordinates":[7.489526,52.226288],"type":"Point"}
}