{
  "type": "Feature",
  "properties": {
    "iso:country":"DE",
    "sg:address":"Hochdorfer Str. 32",
    "sg:city":"Nagold",
    "sg:postcode":"72202",
    "sg:province":"Baden-W\u00fcrttemberg",
    "wof:name":"Mcm Tondach Gmbh",
    "wof:placetype":"venue"
},
  "geometry": {"coordinates":[8.744433,48.511768],"type":"Point"}
}