{
  "type": "Feature",
  "properties": {
    "iso:country":"DE",
    "sg:address":"Kaiserstr. 11",
    "sg:city":"Pirmasens",
    "sg:phone":"+49 6331/24820",
    "sg:postcode":"66955",
    "sg:province":"Rheinland-Pfalz",
    "wof:name":"Martin Oden Steuerberater",
    "wof:placetype":"venue"
},
  "geometry": {"coordinates":[7.6076102257,49.1941070557],"type":"Point"}
}