{
  "type": "Feature",
  "properties": {
    "iso:country":"DE",
    "sg:address":"Dorfstr. 23",
    "sg:city":"Kakerbeck",
    "sg:phone":"+49 39081/503",
    "sg:postcode":"39624",
    "sg:province":"Sachsen-Anhalt",
    "wof:name":"Torsten Kaufmann",
    "wof:placetype":"venue"
},
  "geometry": {"coordinates":[11.275238,52.673725],"type":"Point"}
}