{
  "type": "Feature",
  "properties": {
    "iso:country":"DE",
    "sg:address":"Schlo\u00dfberg 5",
    "sg:city":"Bad Reichenhall",
    "sg:phone":"+49 8651/70050",
    "sg:postcode":"83435",
    "sg:province":"Bayern",
    "wof:name":"Sanatorium Schlo\u00dfberghof Marzoll Gmbh",
    "wof:placetype":"venue"
},
  "geometry": {"coordinates":[12.932059288,47.7494850159],"type":"Point"}
}