{
  "type": "Feature",
  "properties": {
    "iso:country":"DE",
    "sg:address":"Auf der Lage 2",
    "sg:city":"Ankum",
    "sg:phone":"+49 5462/1624",
    "sg:postcode":"49577",
    "sg:province":"Niedersachsen",
    "wof:name":"A. Zumdohme",
    "wof:placetype":"venue"
},
  "geometry": {"coordinates":[7.870655,52.540997],"type":"Point"}
}