{
  "type": "Feature",
  "properties": {
    "iso:country":"DE",
    "sg:address":"Schockenriedstr. 6",
    "sg:city":"Stuttgart",
    "sg:phone":"+49 711/78440",
    "sg:postcode":"70565",
    "sg:province":"Baden-W\u00fcrttemberg",
    "wof:name":"Gustav Lauser Gmbh",
    "wof:placetype":"venue"
},
  "geometry": {"coordinates":[9.116897,48.726566],"type":"Point"}
}