{
  "type": "Feature",
  "properties": {
    "iso:country":"DE",
    "sg:address":"Tiergartenstr. 8",
    "sg:city":"Duisburg",
    "sg:phone":"+49 203/23355",
    "sg:postcode":"47053",
    "sg:province":"Nordrhein-Westfalen",
    "wof:name":"Restaurant Il Piccolo",
    "wof:placetype":"venue"
},
  "geometry": {"coordinates":[6.7605957985,51.4269485474],"type":"Point"}
}