{
  "type": "Feature",
  "properties": {
    "iso:country":"DE",
    "sg:address":"L\u00fcttensee 36",
    "sg:city":"Bergenhusen",
    "sg:phone":"+49 4885/1277",
    "sg:postcode":"24861",
    "sg:province":"Schleswig-Holstein",
    "wof:name":"Realtime-software Solutions International Gmbh",
    "wof:placetype":"venue"
},
  "geometry": {"coordinates":[9.334396,54.37278],"type":"Point"}
}