{
  "type": "Feature",
  "properties": {
    "iso:country":"DE",
    "sg:address":"Wachmannstr. 42",
    "sg:city":"Bremen",
    "sg:phone":"+49 421/342312",
    "sg:postcode":"28209",
    "sg:province":"Bremen",
    "wof:name":"Top Parf\u00fcmerie Gmbh & Co. Kg",
    "wof:placetype":"venue"
},
  "geometry": {"coordinates":[8.829627,53.08535],"type":"Point"}
}