{
  "type": "Feature",
  "properties": {
    "iso:country":"DE",
    "sg:address":"Theodor-K\u00f6rner-Str. 22",
    "sg:city":"Rostock",
    "sg:phone":"+49 4938/1715130",
    "sg:postcode":"18106",
    "sg:province":"Mecklenburg-Vorpommern",
    "wof:name":"Rostocker Obst Gmbh",
    "wof:placetype":"venue"
},
  "geometry": {"coordinates":[12.057179,54.122978],"type":"Point"}
}