{
  "type": "Feature",
  "properties": {
    "iso:country":"DE",
    "sg:address":"Zierenbergstr. 56",
    "sg:city":"Hildesheim",
    "sg:phone":"+49 5121/27183",
    "sg:postcode":"31137",
    "sg:province":"Niedersachsen",
    "wof:name":"Hans Markfeld",
    "wof:placetype":"venue"
},
  "geometry": {"coordinates":[9.923505,52.155888],"type":"Point"}
}