{
  "type": "Feature",
  "properties": {
    "iso:country":"DE",
    "sg:address":"Petersburg 53",
    "sg:city":"Hameln",
    "sg:phone":"+49 5151/12236",
    "sg:postcode":"31789",
    "sg:province":"Niedersachsen",
    "wof:name":"Hildegard Hahlbrock",
    "wof:placetype":"venue"
},
  "geometry": {"coordinates":[9.4203796387,52.0812759399],"type":"Point"}
}