{
  "type": "Feature",
  "properties": {
    "iso:country":"DE",
    "sg:address":"Asternweg 7",
    "sg:city":"Emmelshausen",
    "sg:phone":"+49 6747/8087",
    "sg:postcode":"56281",
    "sg:province":"Rheinland-Pfalz",
    "wof:name":"Sabine Helmcke Heilpraktikerin",
    "wof:placetype":"venue"
},
  "geometry": {"coordinates":[7.5498070717,50.1522979736],"type":"Point"}
}