{
  "type": "Feature",
  "properties": {
    "iso:country":"DE",
    "sg:address":"An der Schmiede 23",
    "sg:city":"Quickborn",
    "sg:phone":"+49 4106/60107",
    "sg:postcode":"25451",
    "sg:province":"Schleswig-Holstein",
    "wof:name":"Helix Medizintechnik- Vertrieb E. K.",
    "wof:placetype":"venue"
},
  "geometry": {"coordinates":[9.933275,53.749367],"type":"Point"}
}