{
  "type": "Feature",
  "properties": {
    "iso:country":"DE",
    "sg:address":"S\u00fcdlicher Stadtgraben 11",
    "sg:city":"Aalen",
    "sg:phone":"+49 7361/610311",
    "sg:postcode":"73430",
    "sg:province":"Baden-W\u00fcrttemberg",
    "wof:name":"Wwk Versicherungen Hans-j\u00fcrgen Spitzner",
    "wof:placetype":"venue"
},
  "geometry": {"coordinates":[10.0933218002,48.8398361206],"type":"Point"}
}