{
  "type": "Feature",
  "properties": {
    "iso:country":"DE",
    "sg:address":"Lindenstr. 7",
    "sg:city":"Rotenburg",
    "sg:phone":"+49 6623/2061",
    "sg:postcode":"36199",
    "sg:province":"Hessen",
    "wof:name":"Immobilienb\u00fcro Vaupel Gmbh",
    "wof:placetype":"venue"
},
  "geometry": {"coordinates":[9.7297925949,50.9980773926],"type":"Point"}
}