{
  "type": "Feature",
  "properties": {
    "iso:country":"DE",
    "sg:address":"Heegstr. 16",
    "sg:city":"Hasselroth",
    "sg:phone":"+49 6055/7751",
    "sg:postcode":"63594",
    "sg:province":"Hessen",
    "wof:name":"Ruth Hellmuth-mai Steuerberaterin",
    "wof:placetype":"venue"
},
  "geometry": {"coordinates":[9.12844944,50.1672859192],"type":"Point"}
}