{
  "type": "Feature",
  "properties": {
    "iso:country":"DE",
    "sg:address":"Teutonenstr. 49",
    "sg:city":"Berlin",
    "sg:phone":"+49 30/6721515",
    "sg:postcode":"12524",
    "sg:province":"Berlin",
    "wof:name":"Hannelore Noack",
    "wof:placetype":"venue"
},
  "geometry": {"coordinates":[13.55094,52.416615],"type":"Point"}
}