{
  "type": "Feature",
  "properties": {
    "iso:country":"DE",
    "sg:address":"Hainerberg",
    "sg:city":"Wiesbaden",
    "sg:phone":"+49 611/731624",
    "sg:postcode":"65189",
    "sg:province":"Hessen",
    "wof:name":"R. Tabert",
    "wof:placetype":"venue"
},
  "geometry": {"coordinates":[8.2613019943,50.072807312],"type":"Point"}
}