{
  "type": "Feature",
  "properties": {
    "iso:country":"DE",
    "sg:address":"Kirchstr. 13",
    "sg:city":"Freigericht",
    "sg:phone":"+49 6055/900037",
    "sg:postcode":"63579",
    "sg:province":"Hessen",
    "wof:name":"Benzing Und M\u00e4rz Rechtsanw\u00e4lte",
    "wof:placetype":"venue"
},
  "geometry": {"coordinates":[9.1459512711,50.1533279419],"type":"Point"}
}