{
  "type": "Feature",
  "properties": {
    "iso:country":"DE",
    "sg:address":"Hauptstr. 89",
    "sg:city":"M\u00fchlhausen",
    "sg:phone":"+49 6222/64275",
    "sg:postcode":"69242",
    "sg:province":"Baden-W\u00fcrttemberg",
    "wof:name":"Angelbach-apotheke",
    "wof:placetype":"venue"
},
  "geometry": {"coordinates":[8.728452,49.248138],"type":"Point"}
}