{
  "type": "Feature",
  "properties": {
    "iso:country":"DE",
    "sg:address":"Hauptbahnhof",
    "sg:city":"Lippstadt",
    "sg:phone":"+49 2941/58720",
    "sg:postcode":"59555",
    "sg:province":"Nordrhein-Westfalen",
    "wof:name":"Mc Donalds",
    "wof:placetype":"venue"
},
  "geometry": {"coordinates":[8.345954895,51.6700363159],"type":"Point"}
}