{
  "type": "Feature",
  "properties": {
    "iso:country":"DE",
    "sg:address":"Mazillisstr. 146",
    "sg:city":"Neuburg",
    "sg:phone":"+49 8431/67220",
    "sg:postcode":"86633",
    "sg:province":"Bayern",
    "wof:name":"Heinrich Leinfelder",
    "wof:placetype":"venue"
},
  "geometry": {"coordinates":[11.1832275391,48.7355651855],"type":"Point"}
}