{
  "type": "Feature",
  "properties": {
    "iso:country":"DE",
    "sg:address":"Hanhoopsfeld 15",
    "sg:city":"Hamburg",
    "sg:phone":"+49 40/7633610",
    "sg:postcode":"21079",
    "sg:province":"Hamburg",
    "wof:name":"Karl Bender",
    "wof:placetype":"venue"
},
  "geometry": {"coordinates":[9.9905891418,53.4400138855],"type":"Point"}
}