{
  "type": "Feature",
  "properties": {
    "iso:country":"DE",
    "sg:address":"Hochstr. 95",
    "sg:city":"Heinsberg",
    "sg:phone":"+49 2452/4669",
    "sg:postcode":"52525",
    "sg:province":"Nordrhein-Westfalen",
    "wof:name":"Az-automaten Rosenbaum Gmbh & Co. Kg",
    "wof:placetype":"venue"
},
  "geometry": {"coordinates":[6.095056,51.062012],"type":"Point"}
}