{
  "type": "Feature",
  "properties": {
    "iso:country":"DE",
    "sg:address":"Graseweg 21",
    "sg:city":"Bovenden",
    "sg:phone":"+49 5593/8888",
    "sg:postcode":"37120",
    "sg:province":"Niedersachsen",
    "wof:name":"Medak Freter & Co. Kg",
    "wof:placetype":"venue"
},
  "geometry": {"coordinates":[9.868158,51.585148],"type":"Point"}
}