{
  "type": "Feature",
  "properties": {
    "iso:country":"DE",
    "sg:address":"Gro\u00dfe Freiheit 25",
    "sg:city":"Hamburg",
    "sg:phone":"+49 40/3195956",
    "sg:postcode":"22767",
    "sg:province":"Hamburg",
    "wof:name":"Gastst\u00e4tte Globetrotter",
    "wof:placetype":"venue"
},
  "geometry": {"coordinates":[9.9574108124,53.5507507324],"type":"Point"}
}