{
  "type": "Feature",
  "properties": {
    "iso:country":"DE",
    "sg:address":"Friedrich-Ebert-Str. 9",
    "sg:city":"Gaggenau",
    "sg:phone":"+49 7225/1711",
    "sg:postcode":"76571",
    "sg:province":"Baden-W\u00fcrttemberg",
    "wof:name":"Haus Und Gartenmarkt Bedarfsartikel F\u00fcr Hobby-",
    "wof:placetype":"venue"
},
  "geometry": {"coordinates":[8.32076,48.803562],"type":"Point"}
}