{
  "type": "Feature",
  "properties": {
    "iso:country":"DE",
    "sg:address":"Graf-Otto-Str. 12",
    "sg:city":"Grafschaft",
    "sg:phone":"+49 2225/5086",
    "sg:postcode":"53501",
    "sg:province":"Rheinland-Pfalz",
    "wof:name":"Midcom Gmbh",
    "wof:placetype":"venue"
},
  "geometry": {"coordinates":[7.0570459366,50.5925941467],"type":"Point"}
}