{
  "type": "Feature",
  "properties": {
    "iso:country":"DE",
    "sg:address":"Adolf-G\u00f6bel-Str. 3",
    "sg:city":"Gro\u00df-Gerau",
    "sg:phone":"+49 6152/2640",
    "sg:postcode":"64521",
    "sg:province":"Hessen",
    "wof:name":"Wilhelm Engeroff Gmbh",
    "wof:placetype":"venue"
},
  "geometry": {"coordinates":[8.4832162857,49.9230461121],"type":"Point"}
}