{
  "type": "Feature",
  "properties": {
    "iso:country":"DE",
    "sg:address":"Albstr. 92",
    "sg:city":"Ulm",
    "sg:phone":"+49 731/1740",
    "sg:postcode":"89081",
    "sg:province":"Baden-W\u00fcrttemberg",
    "wof:name":"Drogerie-dienst Ulm Gmbh",
    "wof:placetype":"venue"
},
  "geometry": {"coordinates":[9.985203,48.428307],"type":"Point"}
}