{
  "type": "Feature",
  "properties": {
    "iso:country":"DE",
    "sg:address":"Florian-Geyer-Str. 60",
    "sg:city":"Zirndorf",
    "sg:phone":"+49 911/607244",
    "sg:postcode":"90513",
    "sg:province":"Bayern",
    "wof:name":"Bernd Eckstein Gmbh",
    "wof:placetype":"venue"
},
  "geometry": {"coordinates":[10.9744253159,49.45054245],"type":"Point"}
}