{
  "type": "Feature",
  "properties": {
    "iso:country":"DE",
    "sg:address":"Kirchhofstr. 17",
    "sg:city":"Brandenburg",
    "sg:postcode":"14776",
    "sg:province":"Brandenburg",
    "wof:name":"Fred Kreitlow",
    "wof:placetype":"venue"
},
  "geometry": {"coordinates":[12.5606403351,52.4046058655],"type":"Point"}
}