{
  "type": "Feature",
  "properties": {
    "iso:country":"DE",
    "sg:address":"Ton Wendb\u00fcdel 3",
    "sg:city":"D\u00f6tlingen",
    "sg:phone":"+49 4432/583",
    "sg:postcode":"27801",
    "sg:province":"Niedersachsen",
    "wof:name":"Uwe Krebs",
    "wof:placetype":"venue"
},
  "geometry": {"coordinates":[8.509623,52.965214],"type":"Point"}
}