{
  "type": "Feature",
  "properties": {
    "iso:country":"DE",
    "sg:address":"Johann-Strau\u00df-Str. 3",
    "sg:city":"Bexbach",
    "sg:phone":"+49 6826/4755",
    "sg:postcode":"66450",
    "sg:province":"Saarland",
    "wof:name":"Elisabeth Stark Hebamme",
    "wof:placetype":"venue"
},
  "geometry": {"coordinates":[7.262255,49.350697],"type":"Point"}
}