{
  "type": "Feature",
  "properties": {
    "iso:country":"DE",
    "sg:address":"Emil-Amer-Str. 4",
    "sg:city":"Wartenberg",
    "sg:phone":"+49 8762/1443",
    "sg:postcode":"85456",
    "sg:province":"Bayern",
    "wof:name":"K. Neumaier Gmbh",
    "wof:placetype":"venue"
},
  "geometry": {"coordinates":[11.994764328,48.4021530151],"type":"Point"}
}