{
  "type": "Feature",
  "properties": {
    "iso:country":"DE",
    "sg:address":"Hauptstr. 155a",
    "sg:city":"Denzlingen",
    "sg:phone":"+49 7666/4321",
    "sg:postcode":"79211",
    "sg:province":"Baden-W\u00fcrttemberg",
    "wof:name":"Suzanne Pauls Krankengymnastin",
    "wof:placetype":"venue"
},
  "geometry": {"coordinates":[7.882125,48.067657],"type":"Point"}
}