{
  "type": "Feature",
  "properties": {
    "iso:country":"DE",
    "sg:address":"Gewerbestr. 11",
    "sg:city":"N\u00f6rdlingen",
    "sg:phone":"+49 9081/6075",
    "sg:postcode":"86720",
    "sg:province":"Bayern",
    "wof:name":"Pfannen Valeri",
    "wof:placetype":"venue"
},
  "geometry": {"coordinates":[10.513444,48.859257],"type":"Point"}
}