{
  "type": "Feature",
  "properties": {
    "iso:country":"DE",
    "sg:address":"Poststeig 7",
    "sg:city":"Nabburg",
    "sg:phone":"+49 9433/545",
    "sg:postcode":"92507",
    "sg:province":"Bayern",
    "wof:name":"Wei\u00df Gmbh",
    "wof:placetype":"venue"
},
  "geometry": {"coordinates":[12.1775598526,49.4478988647],"type":"Point"}
}