{
  "type": "Feature",
  "properties": {
    "iso:country":"DE",
    "sg:address":"Stra\u00df\u00e4cker 3",
    "sg:city":"Mainburg",
    "sg:phone":"+49 8751/844988",
    "sg:postcode":"84048",
    "sg:province":"Bayern",
    "wof:name":"Nutrishop",
    "wof:placetype":"venue"
},
  "geometry": {"coordinates":[11.776639,48.632462],"type":"Point"}
}