{
  "type": "Feature",
  "properties": {
    "iso:country":"DE",
    "sg:address":"L\u00fcckenweg 5",
    "sg:city":"Celle",
    "sg:postcode":"29227",
    "sg:province":"Niedersachsen",
    "wof:name":"Berkal Filtration Gmbh",
    "wof:placetype":"venue"
},
  "geometry": {"coordinates":[10.117,52.601131],"type":"Point"}
}