{
  "type": "Feature",
  "properties": {
    "iso:country":"DE",
    "sg:address":"Hauptstr. 15",
    "sg:city":"Hallenberg",
    "sg:phone":"+49 2984/2360",
    "sg:postcode":"59969",
    "sg:province":"Nordrhein-Westfalen",
    "wof:name":"Franz Guntermann",
    "wof:placetype":"venue"
},
  "geometry": {"coordinates":[8.625416,51.147789],"type":"Point"}
}