{
  "type": "Feature",
  "properties": {
    "iso:country":"DE",
    "sg:address":"Siedl. Wilhelmstrand 162",
    "sg:city":"Berlin",
    "sg:phone":"+49 30/6551563",
    "sg:postcode":"12459",
    "sg:province":"Berlin",
    "wof:name":"Ingrid Burde",
    "wof:placetype":"venue"
},
  "geometry": {"coordinates":[13.515495,52.462124],"type":"Point"}
}