{
  "type": "Feature",
  "properties": {
    "iso:country":"DE",
    "sg:address":"Eichenhof",
    "sg:city":"Heilbronn",
    "sg:phone":"+49 7131/84317",
    "sg:postcode":"74080",
    "sg:province":"Baden-W\u00fcrttemberg",
    "wof:name":"Music Pool Vertriebs Gmbh",
    "wof:placetype":"venue"
},
  "geometry": {"coordinates":[9.1823749542,49.1499786377],"type":"Point"}
}