{
  "type": "Feature",
  "properties": {
    "iso:country":"DE",
    "sg:address":"Unter den Eichen 21",
    "sg:city":"Syke",
    "sg:phone":"+49 4240/292",
    "sg:postcode":"28857",
    "sg:province":"Niedersachsen",
    "wof:name":"St\u00f6ver Tischlerei",
    "wof:placetype":"venue"
},
  "geometry": {"coordinates":[8.862171,52.869919],"type":"Point"}
}