{
  "type": "Feature",
  "properties": {
    "iso:country":"DE",
    "sg:address":"Wolfener Str. 21",
    "sg:city":"Greppin",
    "sg:phone":"+49 3493/42262",
    "sg:postcode":"06803",
    "sg:province":"Sachsen-Anhalt",
    "wof:name":"Schiebel",
    "wof:placetype":"venue"
},
  "geometry": {"coordinates":[12.2981023788,51.6436691284],"type":"Point"}
}