{
  "type": "Feature",
  "properties": {
    "iso:country":"DE",
    "sg:address":"Marktplatz 7",
    "sg:city":"Ebersbach",
    "sg:phone":"+49 7163/7181",
    "sg:postcode":"73061",
    "sg:province":"Baden-W\u00fcrttemberg",
    "wof:name":"Karl Hermann Heilpraktiker",
    "wof:placetype":"venue"
},
  "geometry": {"coordinates":[9.5242233276,48.7141456604],"type":"Point"}
}