{
  "type": "Feature",
  "properties": {
    "iso:country":"DE",
    "sg:address":"Torgauer Str. 20",
    "sg:city":"Herzberg",
    "sg:phone":"+49 3535/5839",
    "sg:postcode":"04916",
    "sg:province":"Brandenburg",
    "wof:name":"Bernd Schr\u00f6ter",
    "wof:placetype":"venue"
},
  "geometry": {"coordinates":[13.2312316895,51.69115448],"type":"Point"}
}