{
  "type": "Feature",
  "properties": {
    "iso:country":"DE",
    "sg:address":"Adolf-Kolping-Str. 15",
    "sg:city":"Bad Endorf",
    "sg:phone":"+49 8053/9717",
    "sg:postcode":"83093",
    "sg:province":"Bayern",
    "wof:name":"Dr. Med. Birgitta Boye",
    "wof:placetype":"venue"
},
  "geometry": {"coordinates":[12.302523613,47.9075012207],"type":"Point"}
}