{
  "type": "Feature",
  "properties": {
    "iso:country":"DE",
    "sg:address":"Schwabacher Str. 46",
    "sg:city":"N\u00fcrnberg",
    "sg:phone":"+49 911/6589871",
    "sg:postcode":"90439",
    "sg:province":"Bayern",
    "wof:name":"Fr\u00e4nkischer Hof",
    "wof:placetype":"venue"
},
  "geometry": {"coordinates":[11.0532283783,49.440284729],"type":"Point"}
}