{
  "type": "Feature",
  "properties": {
    "iso:country":"DE",
    "sg:address":"Christoph-Schwarz-Str. 5",
    "sg:city":"Ingolstadt",
    "sg:phone":"+49 841/68664",
    "sg:postcode":"85053",
    "sg:province":"Bayern",
    "wof:name":"Pharma Wittmann E. K.",
    "wof:placetype":"venue"
},
  "geometry": {"coordinates":[11.4458827972,48.7399101257],"type":"Point"}
}