{
  "type": "Feature",
  "properties": {
    "iso:country":"DE",
    "sg:address":"Normannenweg 12",
    "sg:city":"Hamburg",
    "sg:postcode":"20537",
    "sg:province":"Hamburg",
    "wof:name":"Nordwest- Immobiliengesellschaft",
    "wof:placetype":"venue"
},
  "geometry": {"coordinates":[10.0305528641,53.5513687134],"type":"Point"}
}