{
  "type": "Feature",
  "properties": {
    "iso:country":"DE",
    "sg:address":"Im Grund 91",
    "sg:city":"M\u00f6nchengladbach",
    "sg:phone":"+49 2166/33993",
    "sg:postcode":"41239",
    "sg:province":"Nordrhein-Westfalen",
    "wof:name":"Lankes Verwaltungs Gmbh",
    "wof:placetype":"venue"
},
  "geometry": {"coordinates":[6.41861,51.149769],"type":"Point"}
}