{
  "type": "Feature",
  "properties": {
    "iso:country":"DE",
    "sg:address":"Bergblick 99",
    "sg:city":"Bergholz-Rehbr\u00fccke",
    "sg:postcode":"14558",
    "sg:province":"Brandenburg",
    "wof:name":"Greuzinger & Partner Ges. F\u00fcr Urbanes Bauen Mbh",
    "wof:placetype":"venue"
},
  "geometry": {"coordinates":[13.10182,52.348652],"type":"Point"}
}