{
  "type": "Feature",
  "properties": {
    "iso:country":"DE",
    "sg:address":"Aloys-Nesseler-Platz 3",
    "sg:city":"Bexbach",
    "sg:postcode":"66450",
    "sg:province":"Saarland",
    "wof:name":"Bschab Immobilien Gmbh",
    "wof:placetype":"venue"
},
  "geometry": {"coordinates":[7.2562241554,49.3478507996],"type":"Point"}
}