{
  "type": "Feature",
  "properties": {
    "iso:country":"DE",
    "sg:address":"Jahnstr. 4",
    "sg:city":"Aidenbach",
    "sg:phone":"+49 8543/916017",
    "sg:postcode":"94501",
    "sg:province":"Bayern",
    "wof:name":"Franz Kern",
    "wof:placetype":"venue"
},
  "geometry": {"coordinates":[13.077943,48.571453],"type":"Point"}
}