{
  "type": "Feature",
  "properties": {
    "iso:country":"DE",
    "sg:address":"Spitzkuhner Str. 6",
    "sg:city":"Bollewick",
    "sg:phone":"+49 39931/51917",
    "sg:postcode":"17207",
    "sg:province":"Mecklenburg-Vorpommern",
    "wof:name":"Bruno Wilke",
    "wof:placetype":"venue"
},
  "geometry": {"coordinates":[12.60458,53.373363],"type":"Point"}
}