{
  "type": "Feature",
  "properties": {
    "iso:country":"DE",
    "sg:address":"Hauptstr. 54",
    "sg:city":"Havixbeck",
    "sg:phone":"+49 2507/9401",
    "sg:postcode":"48329",
    "sg:province":"Nordrhein-Westfalen",
    "wof:name":"Baumberg Apotheke Birgit Schipke",
    "wof:placetype":"venue"
},
  "geometry": {"coordinates":[7.411981,51.975704],"type":"Point"}
}