{
  "type": "Feature",
  "properties": {
    "iso:country":"DE",
    "sg:address":"Kaiser-Friedrich-Str. 3",
    "sg:city":"Braunfels",
    "sg:phone":"+49 6442/5411",
    "sg:postcode":"35619",
    "sg:province":"Hessen",
    "wof:name":"Irmgard Czeranski",
    "wof:placetype":"venue"
},
  "geometry": {"coordinates":[8.389934,50.517574],"type":"Point"}
}