{
  "type": "Feature",
  "properties": {
    "iso:country":"DE",
    "sg:address":"Am Klingenweg 2",
    "sg:city":"Walluf",
    "sg:phone":"+49 6123/71136",
    "sg:postcode":"65396",
    "sg:province":"Hessen",
    "wof:name":"Minimal",
    "wof:placetype":"venue"
},
  "geometry": {"coordinates":[8.1620903015,50.0448913574],"type":"Point"}
}