{
  "type": "Feature",
  "properties": {
    "iso:country":"DE",
    "sg:address":"Hamburger Str. 133",
    "sg:city":"Elmshorn",
    "sg:phone":"+49 4121/77078",
    "sg:postcode":"25337",
    "sg:province":"Schleswig-Holstein",
    "wof:name":"Rickert Und Albrecht Rechtsanw\u00e4lte Und Notare",
    "wof:placetype":"venue"
},
  "geometry": {"coordinates":[9.6791601181,53.7497940063],"type":"Point"}
}