{
  "type": "Feature",
  "properties": {
    "iso:country":"DE",
    "sg:address":"Faulenberger Hof",
    "sg:city":"Ottweiler",
    "sg:phone":"+49 6824/4491",
    "sg:postcode":"66564",
    "sg:province":"Saarland",
    "wof:name":"Hans Rose",
    "wof:placetype":"venue"
},
  "geometry": {"coordinates":[7.100601,49.417339],"type":"Point"}
}