{
  "type": "Feature",
  "properties": {
    "iso:country":"DE",
    "sg:address":"Unterstr. 10",
    "sg:city":"Waldbrunn",
    "sg:phone":"+49 6436/941951",
    "sg:postcode":"65620",
    "sg:province":"Hessen",
    "wof:name":"Regina Dickopf-brell Krankengymnastin",
    "wof:placetype":"venue"
},
  "geometry": {"coordinates":[8.117772,50.521648],"type":"Point"}
}