{
  "type": "Feature",
  "properties": {
    "iso:country":"DE",
    "sg:address":"Hilderser Str. 9",
    "sg:city":"Schwallungen",
    "sg:postcode":"98590",
    "sg:province":"Th\u00fcringen",
    "wof:name":"Johann Wilfer-stiftung",
    "wof:placetype":"venue"
},
  "geometry": {"coordinates":[10.358956337,50.6990432739],"type":"Point"}
}