{
  "type": "Feature",
  "properties": {
    "iso:country":"DE",
    "sg:address":"Peutenhausener Str.",
    "sg:city":"Gachenbach",
    "sg:phone":"+49 8252/1888",
    "sg:postcode":"86565",
    "sg:province":"Bayern",
    "wof:name":"Bayerische Asphaltmischwerke Gmbh & Co. Kg",
    "wof:placetype":"venue"
},
  "geometry": {"coordinates":[11.2338352203,48.5262260437],"type":"Point"}
}