{
  "type": "Feature",
  "properties": {
    "iso:country":"DE",
    "sg:address":"Am Brutberg 2",
    "sg:city":"Lastrup",
    "sg:postcode":"49688",
    "sg:province":"Niedersachsen",
    "wof:name":"Etk Verwaltungs- Gmbh",
    "wof:placetype":"venue"
},
  "geometry": {"coordinates":[7.945769,52.81749],"type":"Point"}
}