{
  "type": "Feature",
  "properties": {
    "iso:country":"DE",
    "sg:address":"Greifenhagener Str. 48",
    "sg:city":"Berlin",
    "sg:phone":"+49 30/44736482",
    "sg:postcode":"10437",
    "sg:province":"Berlin",
    "wof:name":"Oxon Gmbh",
    "wof:placetype":"venue"
},
  "geometry": {"coordinates":[13.4161014557,52.5487251282],"type":"Point"}
}