{
  "type": "Feature",
  "properties": {
    "iso:country":"DE",
    "sg:address":"Einhornstr. 120",
    "sg:city":"Schw\u00e4bisch Gm\u00fcnd",
    "sg:phone":"+49 7171/44758",
    "sg:postcode":"73529",
    "sg:province":"Baden-W\u00fcrttemberg",
    "wof:name":"Wedo Fenster- Und T\u00fcrentechnik Gmbh",
    "wof:placetype":"venue"
},
  "geometry": {"coordinates":[9.7983703613,48.7863006592],"type":"Point"}
}