{
  "type": "Feature",
  "properties": {
    "iso:country":"DE",
    "sg:address":"Schwabenstr. 18",
    "sg:city":"Burgsinn",
    "sg:phone":"+49 9356/1447",
    "sg:postcode":"97775",
    "sg:province":"Bayern",
    "wof:name":"Hans Laudenbach",
    "wof:placetype":"venue"
},
  "geometry": {"coordinates":[9.637271,50.14938],"type":"Point"}
}