{
  "type": "Feature",
  "properties": {
    "iso:country":"DE",
    "sg:address":"Binger Str.",
    "sg:city":"Gensingen",
    "sg:phone":"+49 6727/93010",
    "sg:postcode":"55457",
    "sg:province":"Rheinland-Pfalz",
    "wof:name":"Kientzler Gartenbaubetriebe Gmbh & Co. Kg",
    "wof:placetype":"venue"
},
  "geometry": {"coordinates":[7.9195098877,49.9038391113],"type":"Point"}
}