{
  "type": "Feature",
  "properties": {
    "iso:country":"DE",
    "sg:city":"Kochel am See",
    "sg:postcode":"82431",
    "sg:province":"Bayern",
    "wof:name":"Gasthof-hotel Herzogstand In Kochel/obb.",
    "wof:placetype":"venue"
},
  "geometry": {"coordinates":[11.36807,47.658932],"type":"Point"}
}