{
  "type": "Feature",
  "properties": {
    "iso:country":"DE",
    "sg:address":"Am Kr\u00e4henbusch 11",
    "sg:city":"B\u00fcnde",
    "sg:phone":"+49 5223/8920",
    "sg:postcode":"32257",
    "sg:province":"Nordrhein-Westfalen",
    "wof:name":"W. Dinski & S. Hartschwager",
    "wof:placetype":"venue"
},
  "geometry": {"coordinates":[8.619716,52.189091],"type":"Point"}
}