{
  "type": "Feature",
  "properties": {
    "iso:country":"DE",
    "sg:address":"Pflockenstr. 28",
    "sg:city":"Oelsnitz",
    "sg:phone":"+49 37298/14003",
    "sg:postcode":"09376",
    "sg:province":"Sachsen",
    "wof:name":"Westsachsen M\u00f6bel Gmbh",
    "wof:placetype":"venue"
},
  "geometry": {"coordinates":[12.725848,50.722076],"type":"Point"}
}