{
  "type": "Feature",
  "properties": {
    "iso:country":"DE",
    "sg:address":"Frauenbergstr. 49",
    "sg:city":"Bad Waldsee",
    "sg:phone":"+49 7524/8734",
    "sg:postcode":"88339",
    "sg:province":"Baden-W\u00fcrttemberg",
    "wof:name":"Steiner & Kuhn Heizungsbau Gmbh",
    "wof:placetype":"venue"
},
  "geometry": {"coordinates":[9.7491798401,47.9161224365],"type":"Point"}
}