{
  "type": "Feature",
  "properties": {
    "iso:country":"DE",
    "sg:address":"Kreisstr. 13",
    "sg:city":"Hamburg",
    "sg:phone":"+49 40/89070404",
    "sg:postcode":"22607",
    "sg:province":"Hamburg",
    "wof:name":"Mail House Rock Warenhandels Gmbh",
    "wof:placetype":"venue"
},
  "geometry": {"coordinates":[9.8808946609,53.5664520264],"type":"Point"}
}