{
  "type": "Feature",
  "properties": {
    "iso:country":"DE",
    "sg:address":"N\u00fcrnberger Str. 2",
    "sg:city":"Stein",
    "sg:phone":"+49 911/99650",
    "sg:postcode":"90547",
    "sg:province":"Bayern",
    "wof:name":"A. W. Faber Castell Sand- Verwertung Verwaltungs Gmbh",
    "wof:placetype":"venue"
},
  "geometry": {"coordinates":[11.0193023682,49.4165992737],"type":"Point"}
}