{
  "type": "Feature",
  "properties": {
    "iso:country":"DE",
    "sg:address":"Krefelder Str. 89",
    "sg:city":"K\u00f6ln",
    "sg:phone":"+49 221/736080",
    "sg:postcode":"50670",
    "sg:province":"Nordrhein-Westfalen",
    "wof:name":"Richard Grah Gmbh",
    "wof:placetype":"venue"
},
  "geometry": {"coordinates":[6.950879,50.953285],"type":"Point"}
}