{
  "type": "Feature",
  "properties": {
    "iso:country":"DE",
    "sg:address":"Waldperlacher Str. 33",
    "sg:city":"M\u00fcnchen",
    "sg:phone":"+49 89/6016973",
    "sg:postcode":"81739",
    "sg:province":"Bayern",
    "wof:name":"Gewes Gesellschaft Zur Projektierung Wassertechnisch.",
    "wof:placetype":"venue"
},
  "geometry": {"coordinates":[11.671273,48.081501],"type":"Point"}
}