{
  "type": "Feature",
  "properties": {
    "iso:country":"DE",
    "sg:address":"Ziegelh\u00fcttenstr. 40",
    "sg:city":"Burgthann",
    "sg:phone":"+49 9183/8477",
    "sg:postcode":"90559",
    "sg:province":"Bayern",
    "wof:name":"Fleischmann",
    "wof:placetype":"venue"
},
  "geometry": {"coordinates":[11.2723236084,49.3533401489],"type":"Point"}
}