{
  "type": "Feature",
  "properties": {
    "iso:country":"DE",
    "sg:address":"Auf dem Hessel 12",
    "sg:city":"Erlensee",
    "sg:phone":"+49 6183/3457",
    "sg:postcode":"63526",
    "sg:province":"Hessen",
    "wof:name":"Fas Gesellschaft F.f\u00f6rdertechn Automation Und Sonder-",
    "wof:placetype":"venue"
},
  "geometry": {"coordinates":[8.9769325256,50.1642990112],"type":"Point"}
}