{
  "type": "Feature",
  "properties": {
    "iso:country":"DE",
    "sg:address":"L\u00fcbecker Str. 85",
    "sg:city":"Hamburg",
    "sg:phone":"+49 40/2513972",
    "sg:postcode":"22087",
    "sg:province":"Hamburg",
    "wof:name":"Christian Knudsen",
    "wof:placetype":"venue"
},
  "geometry": {"coordinates":[10.03085,53.561218],"type":"Point"}
}