{
  "type": "Feature",
  "properties": {
    "iso:country":"DE",
    "sg:address":"Kirchstr. 25",
    "sg:city":"D\u00f6rverden",
    "sg:phone":"+49 4234/1318",
    "sg:postcode":"27313",
    "sg:province":"Niedersachsen",
    "wof:name":"Bruno Degen",
    "wof:placetype":"venue"
},
  "geometry": {"coordinates":[9.22265625,52.8453063965],"type":"Point"}
}