{
  "type": "Feature",
  "properties": {
    "iso:country":"DE",
    "sg:address":"Berkaer Str. 2 a",
    "sg:city":"Weimar",
    "sg:phone":"+49 3643/513040",
    "sg:postcode":"99425",
    "sg:province":"Th\u00fcringen",
    "wof:name":"Gz Gartenzentrum Weimar Gmbh",
    "wof:placetype":"venue"
},
  "geometry": {"coordinates":[11.323446,50.968586],"type":"Point"}
}