{
  "type": "Feature",
  "properties": {
    "iso:country":"DE",
    "sg:address":"H\u00f6lschen Dyk 22",
    "sg:city":"Krefeld",
    "sg:phone":"+49 2151/733574",
    "sg:postcode":"47839",
    "sg:province":"Nordrhein-Westfalen",
    "wof:name":"Freibad H\u00fcls",
    "wof:placetype":"venue"
},
  "geometry": {"coordinates":[6.5211901665,51.376285553],"type":"Point"}
}