{
  "type": "Feature",
  "properties": {
    "iso:country":"DE",
    "sg:address":"Hauptstr. 121",
    "sg:city":"Grevenbroich",
    "sg:phone":"+49 2181/212572",
    "sg:postcode":"41517",
    "sg:province":"Nordrhein-Westfalen",
    "wof:name":"Karlsruher Lebens- Versicherung Ag",
    "wof:placetype":"venue"
},
  "geometry": {"coordinates":[6.5950798988,51.0747413635],"type":"Point"}
}