{
  "type": "Feature",
  "properties": {
    "iso:country":"DE",
    "sg:address":"Ewaldstr. 130",
    "sg:city":"Oer-Erkenschwick",
    "sg:phone":"+49 2368/1824",
    "sg:postcode":"45739",
    "sg:province":"Nordrhein-Westfalen",
    "wof:name":"Heinz Kettler Gmbh",
    "wof:placetype":"venue"
},
  "geometry": {"coordinates":[7.277798,51.64159],"type":"Point"}
}