{
  "type": "Feature",
  "properties": {
    "iso:country":"DE",
    "sg:address":"Hauptstr. 11",
    "sg:city":"Dierbach",
    "sg:phone":"+49 6340/277",
    "sg:postcode":"76889",
    "sg:province":"Rheinland-Pfalz",
    "wof:name":"Karlheinz W\u00fcst",
    "wof:placetype":"venue"
},
  "geometry": {"coordinates":[8.0651626587,49.0837669373],"type":"Point"}
}