{
  "type": "Feature",
  "properties": {
    "iso:country":"DE",
    "sg:address":"Gro\u00dfe Str. 42",
    "sg:city":"Emden",
    "sg:phone":"+49 4921/33645",
    "sg:postcode":"26721",
    "sg:province":"Niedersachsen",
    "wof:name":"Weinstein",
    "wof:placetype":"venue"
},
  "geometry": {"coordinates":[7.2020611763,53.3668136597],"type":"Point"}
}