{
  "type": "Feature",
  "properties": {
    "iso:country":"DE",
    "sg:address":"Oberer Fahrbachweg 28",
    "sg:city":"Aschaffenburg",
    "sg:phone":"+49 6021/423103",
    "sg:postcode":"63741",
    "sg:province":"Bayern",
    "wof:name":"Karl Zang",
    "wof:placetype":"venue"
},
  "geometry": {"coordinates":[9.1346549988,49.9958190918],"type":"Point"}
}