{
  "type": "Feature",
  "properties": {
    "iso:country":"DE",
    "sg:address":"Langelohstr. 151",
    "sg:city":"Hamburg",
    "sg:phone":"+49 40/803835",
    "sg:postcode":"22549",
    "sg:province":"Hamburg",
    "wof:name":"Wilhelm Gloe",
    "wof:placetype":"venue"
},
  "geometry": {"coordinates":[9.846326828,53.5725364685],"type":"Point"}
}