{
  "type": "Feature",
  "properties": {
    "iso:country":"DE",
    "sg:address":"Halener Str. 61",
    "sg:city":"Duisburg",
    "sg:phone":"+49 2066/10343",
    "sg:postcode":"47198",
    "sg:province":"Nordrhein-Westfalen",
    "wof:name":"Intracon Handelsges. F\u00fcr Industriebedarf Mbh",
    "wof:placetype":"venue"
},
  "geometry": {"coordinates":[6.692438,51.45961],"type":"Point"}
}