{
  "type": "Feature",
  "properties": {
    "iso:country":"DE",
    "sg:address":"Gartenstra\u00dfe 45",
    "sg:city":"Gusterath",
    "sg:phone":"+49 6588/992211",
    "sg:postcode":"54317",
    "sg:province":"Rheinland-Pfalz",
    "wof:name":"Private Homepage Von Thomas Weber Aus Gusterath",
    "wof:placetype":"venue"
},
  "geometry": {"coordinates":[6.712035,49.698711],"type":"Point"}
}