{
  "type": "Feature",
  "properties": {
    "iso:country":"DE",
    "sg:address":"Heckenpfad 6",
    "sg:city":"Krefeld",
    "sg:phone":"+49 2151/714446",
    "sg:postcode":"47804",
    "sg:province":"Nordrhein-Westfalen",
    "wof:name":"Uwe Rips",
    "wof:placetype":"venue"
},
  "geometry": {"coordinates":[6.531201,51.316261],"type":"Point"}
}