{
  "type": "Feature",
  "properties": {
    "iso:country":"DE",
    "sg:address":"Am Markt",
    "sg:city":"Saarbr\u00fccken",
    "sg:phone":"+49 681/399793",
    "sg:postcode":"66125",
    "sg:province":"Saarland",
    "wof:name":"Immobilien",
    "wof:placetype":"venue"
},
  "geometry": {"coordinates":[7.0364289284,49.2753181458],"type":"Point"}
}