{
  "type": "Feature",
  "properties": {
    "iso:country":"DE",
    "sg:address":"Friedrichsh\u00e4userstra\u00dfe 4",
    "sg:city":"Frankenberg-Haubern",
    "sg:phone":"+49 6455/80550",
    "sg:postcode":"35066",
    "sg:province":"Hessen",
    "wof:name":"Fine Wood Holzbau Gmbh",
    "wof:placetype":"venue"
},
  "geometry": {"coordinates":[8.8854751587,51.0508117676],"type":"Point"}
}