{
  "type": "Feature",
  "properties": {
    "iso:country":"DE",
    "sg:address":"Uferstr. 67",
    "sg:city":"Niederkassel",
    "sg:phone":"+49 2208/6480",
    "sg:postcode":"53859",
    "sg:province":"Nordrhein-Westfalen",
    "wof:name":"G. Bodewald Heissmangel",
    "wof:placetype":"venue"
},
  "geometry": {"coordinates":[7.0044798851,50.8265113831],"type":"Point"}
}