{
  "type": "Feature",
  "properties": {
    "iso:country":"DE",
    "sg:address":"Industriegebiet 2",
    "sg:city":"Breitscheid",
    "sg:phone":"+49 2638/93200",
    "sg:postcode":"53547",
    "sg:province":"Rheinland-Pfalz",
    "wof:name":"Welba Elektronischer Steuerungsbau Gmbh",
    "wof:placetype":"venue"
},
  "geometry": {"coordinates":[7.4606451988,50.5725746155],"type":"Point"}
}