{
  "type": "Feature",
  "properties": {
    "iso:country":"DE",
    "sg:address":"Kirchstr. 5",
    "sg:city":"Flemlingen",
    "sg:phone":"+49 6323/2754",
    "sg:postcode":"76835",
    "sg:province":"Rheinland-Pfalz",
    "wof:name":"Katholisches Pfarramt St. Alban",
    "wof:placetype":"venue"
},
  "geometry": {"coordinates":[8.0971469879,49.2437286377],"type":"Point"}
}