{
  "type": "Feature",
  "properties": {
    "iso:country":"DE",
    "sg:address":"Obere Dorngartenstr. 11",
    "sg:city":"Bad Hersfeld",
    "sg:phone":"+49 6621/15414",
    "sg:postcode":"36251",
    "sg:province":"Hessen",
    "wof:name":"Heinrich Bock",
    "wof:placetype":"venue"
},
  "geometry": {"coordinates":[9.7650594711,50.8768615723],"type":"Point"}
}