{
  "type": "Feature",
  "properties": {
    "iso:country":"DE",
    "sg:address":"Krausstr 22",
    "sg:city":"Ismaning",
    "sg:phone":"+49 89/380060",
    "sg:postcode":"85737",
    "sg:province":"Bayern",
    "wof:name":"Allianz-zentrum F\u00fcr Technik Gmbh",
    "wof:placetype":"venue"
},
  "geometry": {"coordinates":[11.6664686203,48.2188262939],"type":"Point"}
}