{
  "type": "Feature",
  "properties": {
    "iso:country":"DE",
    "sg:address":"Kirchstr. 3",
    "sg:city":"H\u00fcrth",
    "sg:phone":"+49 2233/47030",
    "sg:postcode":"50354",
    "sg:province":"Nordrhein-Westfalen",
    "wof:name":"Johann Josef Ohrem",
    "wof:placetype":"venue"
},
  "geometry": {"coordinates":[6.8518090248,50.8807563782],"type":"Point"}
}