{
  "type": "Feature",
  "properties": {
    "iso:country":"DE",
    "sg:address":"Hofsteg 1",
    "sg:city":"Priborn",
    "sg:phone":"+49 39923/2239",
    "sg:postcode":"17209",
    "sg:province":"Mecklenburg-Vorpommern",
    "wof:name":"H. Kr\u00fcger",
    "wof:placetype":"venue"
},
  "geometry": {"coordinates":[12.664693,53.302486],"type":"Point"}
}