{
  "type": "Feature",
  "properties": {
    "iso:country":"DE",
    "sg:address":"Barfu\u00dfg\u00e4\u00dfchen 2 - 8",
    "sg:city":"Leipzig",
    "sg:postcode":"04109",
    "sg:province":"Sachsen",
    "wof:name":"Feldkeller Und Klemm Architekten",
    "wof:placetype":"venue"
},
  "geometry": {"coordinates":[12.37407,51.340916],"type":"Point"}
}