{
  "type": "Feature",
  "properties": {
    "iso:country":"DE",
    "sg:address":"Zum Bahnhof 28",
    "sg:city":"Uetze",
    "sg:phone":"+49 5173/7069",
    "sg:postcode":"31311",
    "sg:province":"Niedersachsen",
    "wof:name":"Ralf Rubart",
    "wof:placetype":"venue"
},
  "geometry": {"coordinates":[10.234309,52.432289],"type":"Point"}
}