{
  "type": "Feature",
  "properties": {
    "iso:country":"DE",
    "sg:address":"Waldhornstr. 19",
    "sg:city":"Karlsruhe",
    "sg:phone":"+49 721/60526",
    "sg:postcode":"76131",
    "sg:province":"Baden-W\u00fcrttemberg",
    "wof:name":"Fu\u00df- Und Sportbodenbelag- Handel Keil Gmbh",
    "wof:placetype":"venue"
},
  "geometry": {"coordinates":[8.4098243713,49.010093689],"type":"Point"}
}