{
  "type": "Feature",
  "properties": {
    "iso:country":"DE",
    "sg:address":"Pater-Kolbe-Str. 21",
    "sg:city":"Markkleeberg",
    "sg:phone":"+49 341/3584745",
    "sg:postcode":"04416",
    "sg:province":"Sachsen",
    "wof:name":"Konrad M\u00fcller",
    "wof:placetype":"venue"
},
  "geometry": {"coordinates":[12.367729187,51.2833976746],"type":"Point"}
}