{
  "type": "Feature",
  "properties": {
    "iso:country":"DE",
    "sg:address":"Reisertstr. 2",
    "sg:city":"Hennef",
    "sg:phone":"+49 2242/1434",
    "sg:postcode":"53773",
    "sg:province":"Nordrhein-Westfalen",
    "wof:name":"Bahr Baumarkt",
    "wof:placetype":"venue"
},
  "geometry": {"coordinates":[7.2598490715,50.7830047607],"type":"Point"}
}