{
  "type": "Feature",
  "properties": {
    "iso:country":"DE",
    "sg:address":"Stra\u00dfberger Str. 2",
    "sg:city":"Plauen",
    "sg:phone":"+49 3741/227033",
    "sg:postcode":"08527",
    "sg:province":"Sachsen",
    "wof:name":"Rossig Schenk Und Partner Architekten",
    "wof:placetype":"venue"
},
  "geometry": {"coordinates":[12.1355648041,50.4934654236],"type":"Point"}
}