{
  "type": "Feature",
  "properties": {
    "iso:country":"DE",
    "sg:address":"Bahnhofstr. 4",
    "sg:city":"Rhens",
    "sg:phone":"+49 2628/987164",
    "sg:postcode":"56321",
    "sg:province":"Rheinland-Pfalz",
    "wof:name":"Kaisersaal",
    "wof:placetype":"venue"
},
  "geometry": {"coordinates":[7.6202301979,50.2807312012],"type":"Point"}
}