{
  "type": "Feature",
  "properties": {
    "iso:country":"DE",
    "sg:city":"d\u00fcsseldorf",
    "sg:postcode":"40479",
    "sg:province":"Nordrhein-Westfalen",
    "wof:name":"Samson Tabak",
    "wof:placetype":"venue"
},
  "geometry": {"coordinates":[6.784165,51.233959],"type":"Point"}
}