{
  "type": "Feature",
  "properties": {
    "iso:country":"DE",
    "sg:address":"Bahnstr. 25",
    "sg:city":"Schwalbach",
    "sg:phone":"+49 6196/1031",
    "sg:postcode":"65824",
    "sg:province":"Hessen",
    "wof:name":"Erich P\u00f6hls Architekt",
    "wof:placetype":"venue"
},
  "geometry": {"coordinates":[8.542354,50.152702],"type":"Point"}
}