{
  "type": "Feature",
  "properties": {
    "iso:country":"DE",
    "sg:address":"Sonnenbergstr. 58",
    "sg:city":"Bretzfeld",
    "sg:phone":"+49 7946/95510",
    "sg:postcode":"74626",
    "sg:province":"Baden-W\u00fcrttemberg",
    "wof:name":"W. Glaser",
    "wof:placetype":"venue"
},
  "geometry": {"coordinates":[9.3901224136,49.1691818237],"type":"Point"}
}