{
  "type": "Feature",
  "properties": {
    "iso:country":"DE",
    "sg:address":"Zum Schmiedebrink 19",
    "sg:city":"Einbeck",
    "sg:phone":"+49 5561/81020",
    "sg:postcode":"37574",
    "sg:province":"Niedersachsen",
    "wof:name":"Hans S\u00f6lter",
    "wof:placetype":"venue"
},
  "geometry": {"coordinates":[9.859697,51.768452],"type":"Point"}
}