{
  "type": "Feature",
  "properties": {
    "iso:country":"DE",
    "sg:address":"Hammelburger Str. 21::",
    "sg:city":"Euerdorf",
    "sg:phone":"+49 9704/6090",
    "sg:postcode":"97717",
    "sg:province":"Bayern",
    "wof:name":"Perma-tec Gmbh & Co. Kg Perma-schmiersysteme:",
    "wof:placetype":"venue"
},
  "geometry": {"coordinates":[10.020472,50.147869],"type":"Point"}
}