{
  "type": "Feature",
  "properties": {
    "iso:country":"DE",
    "sg:address":"Horather Str. 180",
    "sg:city":"Wuppertal",
    "sg:phone":"+49 202/77691",
    "sg:postcode":"42111",
    "sg:province":"Nordrhein-Westfalen",
    "wof:name":"Br\u00fcck",
    "wof:placetype":"venue"
},
  "geometry": {"coordinates":[7.1621141434,51.3000946045],"type":"Point"}
}