{
  "type": "Feature",
  "properties": {
    "iso:country":"DE",
    "sg:address":"N\u00fcrnberger Str. 12",
    "sg:city":"Bayreuth",
    "sg:phone":"+49 921/69707",
    "sg:postcode":"95448",
    "sg:province":"Bayern",
    "wof:name":"Dr. Werner Grundmann Tierarzt",
    "wof:placetype":"venue"
},
  "geometry": {"coordinates":[11.5886831284,49.9378242493],"type":"Point"}
}