{
  "type": "Feature",
  "properties": {
    "iso:country":"DE",
    "sg:address":"Stresemannstr. 12",
    "sg:city":"Duisburg",
    "sg:phone":"+49 203/378690",
    "sg:postcode":"47051",
    "sg:province":"Nordrhein-Westfalen",
    "wof:name":"Steuerberatung Ecker-sarassa",
    "wof:placetype":"venue"
},
  "geometry": {"coordinates":[6.769475,51.438641],"type":"Point"}
}