{
  "type": "Feature",
  "properties": {
    "iso:country":"DE",
    "sg:address":"Quellenstr. 96",
    "sg:city":"Swisttal",
    "sg:phone":"+49 2254/2313",
    "sg:postcode":"53913",
    "sg:province":"Nordrhein-Westfalen",
    "wof:name":"Kur-club Franz Rais Gemeinsame Gesunde Aktiv",
    "wof:placetype":"venue"
},
  "geometry": {"coordinates":[6.9099998474,50.721736908],"type":"Point"}
}