{
  "type": "Feature",
  "properties": {
    "iso:country":"DE",
    "sg:address":"Untere Karlstr. 1",
    "sg:city":"Erlangen",
    "sg:phone":"+49 9131/22524",
    "sg:postcode":"91054",
    "sg:province":"Bayern",
    "wof:name":"A. J. L\u00f6ffler",
    "wof:placetype":"venue"
},
  "geometry": {"coordinates":[11.0052232742,49.5961647034],"type":"Point"}
}