{
  "type": "Feature",
  "properties": {
    "iso:country":"DE",
    "sg:address":"S\u00fcdstr. 141",
    "sg:city":"Herzogenrath",
    "sg:phone":"+49 2407/7142",
    "sg:postcode":"52134",
    "sg:province":"Nordrhein-Westfalen",
    "wof:name":"Gastst\u00e4tte Ewald Hannes",
    "wof:placetype":"venue"
},
  "geometry": {"coordinates":[6.0929307938,50.8286590576],"type":"Point"}
}