{
  "type": "Feature",
  "properties": {
    "iso:country":"DE",
    "sg:address":"Basler Str. 27",
    "sg:city":"L\u00f6rrach",
    "sg:phone":"+49 7621/10099",
    "sg:postcode":"79540",
    "sg:province":"Baden-W\u00fcrttemberg",
    "wof:name":"Tox Gmbh",
    "wof:placetype":"venue"
},
  "geometry": {"coordinates":[7.658575,47.601433],"type":"Point"}
}