{
  "type": "Feature",
  "properties": {
    "iso:country":"DE",
    "sg:address":"Am M\u00fcrel 11",
    "sg:city":"Blankenheim",
    "sg:phone":"+49 2449/7979",
    "sg:postcode":"53945",
    "sg:province":"Nordrhein-Westfalen",
    "wof:name":"Karl Lippertz Gmbh",
    "wof:placetype":"venue"
},
  "geometry": {"coordinates":[6.6624741554,50.4495811462],"type":"Point"}
}