{
  "type": "Feature",
  "properties": {
    "iso:country":"DE",
    "sg:address":"Mandichostra\u00dfe 18",
    "sg:city":"Merching",
    "sg:phone":"+49 8233",
    "sg:postcode":"86504",
    "sg:province":"Bayern",
    "wof:name":"Mustertexte.de",
    "wof:placetype":"venue"
},
  "geometry": {"coordinates":[10.985512,48.251282],"type":"Point"}
}