{
  "type": "Feature",
  "properties": {
    "iso:country":"DE",
    "sg:address":"Sandstr. 111",
    "sg:city":"Detmold",
    "sg:phone":"+49 5232/8350",
    "sg:postcode":"32758",
    "sg:province":"Nordrhein-Westfalen",
    "wof:name":"Georg Hoffmann",
    "wof:placetype":"venue"
},
  "geometry": {"coordinates":[8.773282,51.935192],"type":"Point"}
}