{
  "type": "Feature",
  "properties": {
    "iso:country":"DE",
    "sg:address":"Semmelweisstr. 43",
    "sg:city":"Plauen",
    "sg:phone":"+49 3741/440115",
    "sg:postcode":"08529",
    "sg:province":"Sachsen",
    "wof:name":"C. Wei\u00df",
    "wof:placetype":"venue"
},
  "geometry": {"coordinates":[12.1782608032,50.4946975708],"type":"Point"}
}