{
  "type": "Feature",
  "properties": {
    "iso:country":"DE",
    "sg:address":"H\u00f6henstr. 101",
    "sg:city":"Wasserburg",
    "sg:phone":"+49 8382/949990",
    "sg:postcode":"88142",
    "sg:province":"Bayern",
    "wof:name":"Otto Baumgartner",
    "wof:placetype":"venue"
},
  "geometry": {"coordinates":[9.641041,47.568684],"type":"Point"}
}