{
  "type": "Feature",
  "properties": {
    "iso:country":"DE",
    "sg:address":"Herrenstr. 62",
    "sg:city":"Freiburg",
    "sg:phone":"+49 761/2022033",
    "sg:postcode":"79098",
    "sg:province":"Baden-W\u00fcrttemberg",
    "wof:name":"Ludwig Holderied Inh. Frank Ernst",
    "wof:placetype":"venue"
},
  "geometry": {"coordinates":[7.8539800644,47.9934310913],"type":"Point"}
}