{
  "type": "Feature",
  "properties": {
    "iso:country":"DE",
    "sg:address":"Heimhuder Str. 92",
    "sg:city":"Hamburg",
    "sg:phone":"+49 40/444547",
    "sg:postcode":"20148",
    "sg:province":"Hamburg",
    "wof:name":"Sozialstation Harvestehude- Rothenbaum",
    "wof:placetype":"venue"
},
  "geometry": {"coordinates":[9.993091,53.570515],"type":"Point"}
}