{
  "type": "Feature",
  "properties": {
    "iso:country":"DE",
    "sg:address":"Ziegelh\u00fctte 17",
    "sg:city":"Hohenfels",
    "sg:phone":"+49 9472/340",
    "sg:postcode":"92366",
    "sg:province":"Bayern",
    "wof:name":"Gastst\u00e4tte Karl Schmidt",
    "wof:placetype":"venue"
},
  "geometry": {"coordinates":[11.8573999405,49.1995048523],"type":"Point"}
}