{
  "type": "Feature",
  "properties": {
    "iso:country":"DE",
    "sg:address":"Amselweg 11",
    "sg:city":"Kirchberg",
    "sg:phone":"+49 7354/91901",
    "sg:postcode":"88486",
    "sg:province":"Baden-W\u00fcrttemberg",
    "wof:name":"Franz Bail Architekt",
    "wof:placetype":"venue"
},
  "geometry": {"coordinates":[10.075297,48.132969],"type":"Point"}
}