{
  "type": "Feature",
  "properties": {
    "iso:country":"DE",
    "sg:address":"Forstweg 13",
    "sg:city":"Taufkirchen",
    "sg:phone":"+49 89/6124335",
    "sg:postcode":"82024",
    "sg:province":"Bayern",
    "wof:name":"Volpp Malerei-betrieb Gmbh",
    "wof:placetype":"venue"
},
  "geometry": {"coordinates":[11.594246,48.044189],"type":"Point"}
}