{
  "type": "Feature",
  "properties": {
    "iso:country":"DE",
    "sg:address":"Lange Str. 46",
    "sg:city":"Essen",
    "sg:phone":"+49 201/551201",
    "sg:postcode":"45307",
    "sg:province":"Nordrhein-Westfalen",
    "wof:name":"Evelyn Falkenstein",
    "wof:placetype":"venue"
},
  "geometry": {"coordinates":[7.079365,51.463566],"type":"Point"}
}