{
  "type": "Feature",
  "properties": {
    "iso:country":"DE",
    "sg:address":"Melanchthonstr. 33",
    "sg:city":"Bretten",
    "sg:phone":"+49 7252/957123",
    "sg:postcode":"75015",
    "sg:province":"Baden-W\u00fcrttemberg",
    "wof:name":"Ulrike Mendel-gentischer Und Heidrun Kirchge\u00dfner",
    "wof:placetype":"venue"
},
  "geometry": {"coordinates":[8.7046537399,49.0375137329],"type":"Point"}
}