{
  "type": "Feature",
  "properties": {
    "iso:country":"DE",
    "sg:address":"Helenenstr. 37",
    "sg:city":"Hannover",
    "sg:phone":"+49 511/8437929",
    "sg:postcode":"30519",
    "sg:province":"Niedersachsen",
    "wof:name":"Ristorante Pizzeria La Civetta",
    "wof:placetype":"venue"
},
  "geometry": {"coordinates":[9.7654247284,52.3388328552],"type":"Point"}
}