{
  "type": "Feature",
  "properties": {
    "iso:country":"DE",
    "sg:address":"Johannisplatz 11",
    "sg:city":"M\u00fcnchen",
    "sg:phone":"+49 89/482157",
    "sg:postcode":"81667",
    "sg:province":"Bayern",
    "wof:name":"Johannisquelle",
    "wof:placetype":"venue"
},
  "geometry": {"coordinates":[11.5975666046,48.1329650879],"type":"Point"}
}