{
  "type": "Feature",
  "properties": {
    "iso:country":"DE",
    "sg:address":"Schlitzer Str. 17",
    "sg:city":"Lauterbach",
    "sg:postcode":"36341",
    "sg:province":"Hessen",
    "wof:name":"Schmitt-lift- Schwarz Gmbh",
    "wof:placetype":"venue"
},
  "geometry": {"coordinates":[9.409988,50.642895],"type":"Point"}
}