{
  "type": "Feature",
  "properties": {
    "iso:country":"DE",
    "sg:address":"Zur Lindenh\u00f6he 6",
    "sg:city":"Leipzig",
    "sg:phone":"+49 341/4615950",
    "sg:postcode":"04158",
    "sg:province":"Sachsen",
    "wof:name":"Thomas Gr\u00e4fe",
    "wof:placetype":"venue"
},
  "geometry": {"coordinates":[12.3384790421,51.392616272],"type":"Point"}
}