{
  "type": "Feature",
  "properties": {
    "iso:country":"DE",
    "sg:address":"Markt 12",
    "sg:city":"Preetz",
    "sg:phone":"+49 4342/2829",
    "sg:postcode":"24211",
    "sg:province":"Schleswig-Holstein",
    "wof:name":"Wolfgang Kretschmer Masseur",
    "wof:placetype":"venue"
},
  "geometry": {"coordinates":[10.281418,54.234722],"type":"Point"}
}