{
  "type": "Feature",
  "properties": {
    "iso:country":"DE",
    "sg:address":"Hauptstr. 76",
    "sg:city":"Schiffweiler",
    "sg:phone":"+49 6821/64404",
    "sg:postcode":"66578",
    "sg:province":"Saarland",
    "wof:name":"A. Und M. Freynhofer",
    "wof:placetype":"venue"
},
  "geometry": {"coordinates":[7.1306700706,49.3659362793],"type":"Point"}
}