{
  "type": "Feature",
  "properties": {
    "iso:country":"DE",
    "sg:address":"An der Elster 4a",
    "sg:city":"Doberlug-Kirchhain",
    "sg:phone":"+49 35322/2295",
    "sg:postcode":"03253",
    "sg:province":"Brandenburg",
    "wof:name":"T. Mammitzsch",
    "wof:placetype":"venue"
},
  "geometry": {"coordinates":[13.5649,51.642136],"type":"Point"}
}