{
  "type": "Feature",
  "properties": {
    "iso:country":"DE",
    "sg:address":"Wangener Str 19",
    "sg:city":"Starnberg",
    "sg:phone":"+49 8151/2338",
    "sg:postcode":"82319",
    "sg:province":"Bayern",
    "wof:name":"J.b. Hoenning",
    "wof:placetype":"venue"
},
  "geometry": {"coordinates":[11.370497,48.02755],"type":"Point"}
}