{
  "type": "Feature",
  "properties": {
    "iso:country":"DE",
    "sg:address":"Kesseltobelstr. 11",
    "sg:city":"G\u00f6ppingen",
    "sg:phone":"+49 7161/26239",
    "sg:postcode":"73035",
    "sg:province":"Baden-W\u00fcrttemberg",
    "wof:name":"O. Ziegler",
    "wof:placetype":"venue"
},
  "geometry": {"coordinates":[9.6244630814,48.7164382935],"type":"Point"}
}