{
  "type": "Feature",
  "properties": {
    "iso:country":"DE",
    "sg:address":"Hervorster Str. 111",
    "sg:city":"Goch",
    "sg:phone":"+49 2823/417317",
    "sg:postcode":"47574",
    "sg:province":"Nordrhein-Westfalen",
    "wof:name":"Inplan Gmbh",
    "wof:placetype":"venue"
},
  "geometry": {"coordinates":[6.147111,51.684872],"type":"Point"}
}