{
  "type": "Feature",
  "properties": {
    "iso:country":"DE",
    "sg:address":"Grabiger Weg 3",
    "sg:city":"Unsleben",
    "sg:phone":"+49 9773/91210",
    "sg:postcode":"97618",
    "sg:province":"Bayern",
    "wof:name":"G\u00e4stehaus Wei\u00df",
    "wof:placetype":"venue"
},
  "geometry": {"coordinates":[10.2488851547,50.3794898987],"type":"Point"}
}