{
  "type": "Feature",
  "properties": {
    "iso:country":"DE",
    "sg:address":"Pfeifenofen 19",
    "sg:city":"Stadtlohn",
    "sg:phone":"+49 2563/4411",
    "sg:postcode":"48703",
    "sg:province":"Nordrhein-Westfalen",
    "wof:name":"Bhb Tischlerei Gmbh",
    "wof:placetype":"venue"
},
  "geometry": {"coordinates":[6.913981,51.993488],"type":"Point"}
}