{
  "type": "Feature",
  "properties": {
    "iso:country":"DE",
    "sg:address":"Rotterdamer Str. 24",
    "sg:city":"N\u00fcrnberg",
    "sg:phone":"+49 911/645250",
    "sg:postcode":"90451",
    "sg:province":"Bayern",
    "wof:name":"Alcatal Sel Ag",
    "wof:placetype":"venue"
},
  "geometry": {"coordinates":[11.066245079,49.4006462097],"type":"Point"}
}