{
  "type": "Feature",
  "properties": {
    "iso:country":"DE",
    "sg:address":"Sollingstr. 108",
    "sg:city":"Holzminden",
    "sg:phone":"+49 5531/7289",
    "sg:postcode":"37603",
    "sg:province":"Niedersachsen",
    "wof:name":"Friedrich Sch\u00fctte",
    "wof:placetype":"venue"
},
  "geometry": {"coordinates":[9.460574,51.827793],"type":"Point"}
}