{
  "type": "Feature",
  "properties": {
    "iso:country":"DE",
    "sg:address":"Simon-Dach-Str. 35",
    "sg:city":"Berlin",
    "sg:postcode":"10245",
    "sg:province":"Berlin",
    "wof:name":"Helga Truhn",
    "wof:placetype":"venue"
},
  "geometry": {"coordinates":[13.45651,52.510075],"type":"Point"}
}