{
  "type": "Feature",
  "properties": {
    "iso:country":"DE",
    "sg:address":"Bonner Str. 91",
    "sg:city":"Wesseling",
    "sg:phone":"+49 2236/841244",
    "sg:postcode":"50389",
    "sg:province":"Nordrhein-Westfalen",
    "wof:name":"M. Fricke",
    "wof:placetype":"venue"
},
  "geometry": {"coordinates":[6.987094,50.822205],"type":"Point"}
}