{
  "type": "Feature",
  "properties": {
    "iso:country":"DE",
    "sg:address":"Kuppenheimer Str. 8",
    "sg:city":"Bischweier",
    "sg:phone":"+49 7222/47009",
    "sg:postcode":"76476",
    "sg:province":"Baden-W\u00fcrttemberg",
    "wof:name":"Groitl",
    "wof:placetype":"venue"
},
  "geometry": {"coordinates":[8.278446,48.834572],"type":"Point"}
}