{
  "type": "Feature",
  "properties": {
    "iso:country":"DE",
    "sg:address":"Durmersheimer Str. 192",
    "sg:city":"Karlsruhe",
    "sg:phone":"+49 721/575738",
    "sg:postcode":"76189",
    "sg:province":"Baden-W\u00fcrttemberg",
    "wof:name":"Maxi Markt",
    "wof:placetype":"venue"
},
  "geometry": {"coordinates":[8.3451776505,48.9963188171],"type":"Point"}
}