{
  "type": "Feature",
  "properties": {
    "iso:country":"DE",
    "sg:address":"Beckergrube 76",
    "sg:city":"L\u00fcbeck",
    "sg:phone":"+49 451/73931",
    "sg:postcode":"23552",
    "sg:province":"Schleswig-Holstein",
    "wof:name":"August Rentzow",
    "wof:placetype":"venue"
},
  "geometry": {"coordinates":[10.681328,53.869778],"type":"Point"}
}