{
  "type": "Feature",
  "properties": {
    "iso:country":"DE",
    "sg:address":"Kleine Hohl 23",
    "sg:city":"Lahnstein",
    "sg:phone":"+49 2621/610458",
    "sg:postcode":"56112",
    "sg:province":"Rheinland-Pfalz",
    "wof:name":"Christine Und J\u00fcrgen Kauth",
    "wof:placetype":"venue"
},
  "geometry": {"coordinates":[7.6117091179,50.3135414124],"type":"Point"}
}