{
  "type": "Feature",
  "properties": {
    "iso:country":"DE",
    "sg:address":"Ritterstr. 7",
    "sg:city":"Hasel\u00fcnne",
    "sg:phone":"+49 5961/5020",
    "sg:postcode":"49740",
    "sg:province":"Niedersachsen",
    "wof:name":"Berentzen Brennereien Gmbh & Co. Kg",
    "wof:placetype":"venue"
},
  "geometry": {"coordinates":[7.48541,52.6744],"type":"Point"}
}