{
  "type": "Feature",
  "properties": {
    "iso:country":"DE",
    "sg:address":"Porschestr. 52",
    "sg:city":"Wolfsburg",
    "sg:phone":"+49 5361/23952",
    "sg:postcode":"38440",
    "sg:province":"Niedersachsen",
    "wof:name":"Fercher Betriebs Gmbh & Co. Kg",
    "wof:placetype":"venue"
},
  "geometry": {"coordinates":[10.7878036499,52.4235191345],"type":"Point"}
}