{
  "type": "Feature",
  "properties": {
    "iso:country":"DE",
    "sg:address":"Fehrsstr. 3",
    "sg:city":"Kellinghusen",
    "sg:phone":"+49 4822/90010",
    "sg:postcode":"25548",
    "sg:province":"Schleswig-Holstein",
    "wof:name":"Hyper-d\u00e4mmtechnik Kellinghusen Gmbh",
    "wof:placetype":"venue"
},
  "geometry": {"coordinates":[9.7142524719,53.947429657],"type":"Point"}
}