{
  "type": "Feature",
  "properties": {
    "iso:country":"DE",
    "sg:address":"Dieselstr. 6",
    "sg:city":"Haren",
    "sg:phone":"+49 5932/69669",
    "sg:postcode":"49733",
    "sg:province":"Niedersachsen",
    "wof:name":"Hermann Lammers Fitnesscenter",
    "wof:placetype":"venue"
},
  "geometry": {"coordinates":[7.2353029251,52.8015136719],"type":"Point"}
}