{
  "type": "Feature",
  "properties": {
    "iso:country":"DE",
    "sg:address":"Hochdorfer Str. 30",
    "sg:city":"Gr\u00f6mbach",
    "sg:phone":"+49 7453/3423",
    "sg:postcode":"72294",
    "sg:province":"Baden-W\u00fcrttemberg",
    "wof:name":"St. Georg Stube",
    "wof:placetype":"venue"
},
  "geometry": {"coordinates":[8.5427427292,48.5734176636],"type":"Point"}
}