{
  "type": "Feature",
  "properties": {
    "iso:country":"DE",
    "sg:address":"Scharrenbroicher Str. 106",
    "sg:city":"R\u00f6srath",
    "sg:phone":"+49 2205/2437",
    "sg:postcode":"51503",
    "sg:province":"Nordrhein-Westfalen",
    "wof:name":"M. Schl\u00f6sser",
    "wof:placetype":"venue"
},
  "geometry": {"coordinates":[7.1832480431,50.9007568359],"type":"Point"}
}