{
  "type": "Feature",
  "properties": {
    "iso:country":"DE",
    "sg:address":"Gewerbeallee 34",
    "sg:city":"Elmenhorst/Lichtenhagen",
    "sg:phone":"+49 381/7696070",
    "sg:postcode":"18107",
    "sg:province":"Mecklenburg-Vorpommern",
    "wof:name":"Hans-j\u00fcrgen Zielke",
    "wof:placetype":"venue"
},
  "geometry": {"coordinates":[12.016057,54.153091],"type":"Point"}
}