{
  "type": "Feature",
  "properties": {
    "iso:country":"DE",
    "sg:address":"Ludwig-Eckert-Str. 5-7",
    "sg:city":"Regensburg",
    "sg:phone":"+49 941/296710",
    "sg:postcode":"93049",
    "sg:province":"Bayern",
    "wof:name":"Bayer Viebacher & Kellner Planungs Gmbh",
    "wof:placetype":"venue"
},
  "geometry": {"coordinates":[12.082429,49.017185],"type":"Point"}
}