{
  "type": "Feature",
  "properties": {
    "iso:country":"DE",
    "sg:address":"Alt-Treptow 14",
    "sg:city":"Berlin",
    "sg:phone":"+49 30/5337211",
    "sg:postcode":"12435",
    "sg:province":"Berlin",
    "wof:name":"Zenner-restauration Gmbh",
    "wof:placetype":"venue"
},
  "geometry": {"coordinates":[13.4774923325,52.486946106],"type":"Point"}
}