{
  "type": "Feature",
  "properties": {
    "iso:country":"DE",
    "sg:address":"Schulstr. 8",
    "sg:city":"Bischofsheim",
    "sg:phone":"+49 6144/7243",
    "sg:postcode":"65474",
    "sg:province":"Hessen",
    "wof:name":"Heidaker Textil Mode Gmbh",
    "wof:placetype":"venue"
},
  "geometry": {"coordinates":[8.35816,49.990459],"type":"Point"}
}