{
  "type": "Feature",
  "properties": {
    "iso:country":"DE",
    "sg:address":"Siedlungsstr. 24",
    "sg:city":"Peitz",
    "sg:phone":"+49 35601/23115",
    "sg:postcode":"03185",
    "sg:province":"Brandenburg",
    "wof:name":"Manfred Liebo",
    "wof:placetype":"venue"
},
  "geometry": {"coordinates":[14.41864,51.851486],"type":"Point"}
}