{
  "type": "Feature",
  "properties": {
    "iso:country":"DE",
    "sg:address":"Karl-Marx-Str. 2",
    "sg:city":"Selb",
    "sg:phone":"+49 9287/870220",
    "sg:postcode":"95100",
    "sg:province":"Bayern",
    "wof:name":"Eden-bar",
    "wof:placetype":"venue"
},
  "geometry": {"coordinates":[12.13344,50.17033],"type":"Point"}
}