{
  "type": "Feature",
  "properties": {
    "iso:country":"DE",
    "sg:address":"An den Stadtwerken 5",
    "sg:city":"Pasewalk",
    "sg:phone":"+49 3973/20810",
    "sg:postcode":"17309",
    "sg:province":"Mecklenburg-Vorpommern",
    "wof:name":"Gemeinn\u00fctzige Werk- Und Wohnst\u00e4tten Gmbh",
    "wof:placetype":"venue"
},
  "geometry": {"coordinates":[14.015514,53.510654],"type":"Point"}
}