{
  "type": "Feature",
  "properties": {
    "iso:country":"DE",
    "sg:address":"Staudingstr. 1",
    "sg:city":"T\u00fcrkenfeld",
    "sg:phone":"+49 8193/1767",
    "sg:postcode":"82299",
    "sg:province":"Bayern",
    "wof:name":"Edwin Thienel",
    "wof:placetype":"venue"
},
  "geometry": {"coordinates":[11.086598,48.10767],"type":"Point"}
}