{
  "type": "Feature",
  "properties": {
    "iso:country":"DE",
    "sg:address":"Heideweg 5",
    "sg:city":"Lahn",
    "sg:phone":"+49 5951/4525",
    "sg:postcode":"49757",
    "sg:province":"Niedersachsen",
    "wof:name":"Heinrich Timmer",
    "wof:placetype":"venue"
},
  "geometry": {"coordinates":[7.603173,52.814205],"type":"Point"}
}