{
  "type": "Feature",
  "properties": {
    "iso:country":"DE",
    "sg:address":"Sundgauallee 15",
    "sg:city":"Freiburg",
    "sg:phone":"+49 761/84303",
    "sg:postcode":"79114",
    "sg:province":"Baden-W\u00fcrttemberg",
    "wof:name":"M. N\u00f6ller Kunstmaler",
    "wof:placetype":"venue"
},
  "geometry": {"coordinates":[7.817962,48.006741],"type":"Point"}
}