{
  "type": "Feature",
  "properties": {
    "iso:country":"DE",
    "sg:address":"Spitzgarten 20",
    "sg:city":"Veitsrodt",
    "sg:phone":"+49 6781/31553",
    "sg:postcode":"55758",
    "sg:province":"Rheinland-Pfalz",
    "wof:name":"Hans Marx",
    "wof:placetype":"venue"
},
  "geometry": {"coordinates":[7.300625,49.757801],"type":"Point"}
}