{
  "type": "Feature",
  "properties": {
    "iso:country":"DE",
    "sg:address":"Auweg 7",
    "sg:city":"Ha\u00dfmersheim",
    "sg:phone":"+49 6266/1407",
    "sg:postcode":"74855",
    "sg:province":"Baden-W\u00fcrttemberg",
    "wof:name":"K. Raudenbusch Binnenschiffahrtsunternehmen",
    "wof:placetype":"venue"
},
  "geometry": {"coordinates":[9.150457,49.303246],"type":"Point"}
}