{
  "type": "Feature",
  "properties": {
    "iso:country":"DE",
    "sg:address":"Sch\u00f6nbornstr. 35",
    "sg:city":"Bruchsal",
    "sg:phone":"+49 7251/85003",
    "sg:postcode":"76646",
    "sg:province":"Baden-W\u00fcrttemberg",
    "wof:name":"Dammert Immobilienmakler",
    "wof:placetype":"venue"
},
  "geometry": {"coordinates":[8.6010398865,49.1309013367],"type":"Point"}
}