{
  "type": "Feature",
  "properties": {
    "iso:country":"DE",
    "sg:address":"Friedensstr. 1",
    "sg:city":"Oschatz",
    "sg:phone":"+49 3435/624633",
    "sg:postcode":"04758",
    "sg:province":"Sachsen",
    "wof:name":"Bruno Sch\u00f6ne Gmbh",
    "wof:placetype":"venue"
},
  "geometry": {"coordinates":[13.105874,51.305401],"type":"Point"}
}