{
  "type": "Feature",
  "properties": {
    "iso:country":"DE",
    "sg:address":"Schmidener Str. 18",
    "sg:city":"Waiblingen",
    "sg:phone":"+49 7151/905157",
    "sg:postcode":"71332",
    "sg:province":"Baden-W\u00fcrttemberg",
    "wof:name":"Baby Paradies",
    "wof:placetype":"venue"
},
  "geometry": {"coordinates":[9.3141803741,48.8328056335],"type":"Point"}
}