{
  "type": "Feature",
  "properties": {
    "iso:country":"DE",
    "sg:address":"Hauptstr. 37",
    "sg:city":"Hohentengen",
    "sg:phone":"+49 7742/8590",
    "sg:postcode":"79801",
    "sg:province":"Baden-W\u00fcrttemberg",
    "wof:name":"Royal-tortendekor Gmbh",
    "wof:placetype":"venue"
},
  "geometry": {"coordinates":[9.3805885315,48.0271186829],"type":"Point"}
}