{
  "type": "Feature",
  "properties": {
    "iso:country":"DE",
    "sg:address":"B\u00fcrgergasse 7",
    "sg:city":"Du\u00dflingen",
    "sg:phone":"+49 7072/3286",
    "sg:postcode":"72144",
    "sg:province":"Baden-W\u00fcrttemberg",
    "wof:name":"Walter G\u00fcnther",
    "wof:placetype":"venue"
},
  "geometry": {"coordinates":[9.0572071075,48.4502677917],"type":"Point"}
}