{
  "type": "Feature",
  "properties": {
    "iso:country":"DE",
    "sg:address":"Rixdorfer Str. 71",
    "sg:city":"Berlin",
    "sg:postcode":"12109",
    "sg:province":"Berlin",
    "wof:name":"Herbert Knigge Ingenieurb\u00fcro",
    "wof:placetype":"venue"
},
  "geometry": {"coordinates":[13.4035139084,52.4477996826],"type":"Point"}
}