{
  "type": "Feature",
  "properties": {
    "iso:country":"DE",
    "sg:address":"Merkenfritzer Str. 10",
    "sg:city":"Gedern",
    "sg:phone":"+49 6045/8560",
    "sg:postcode":"63688",
    "sg:province":"Hessen",
    "wof:name":"J.s. Porter",
    "wof:placetype":"venue"
},
  "geometry": {"coordinates":[9.149879,50.409237],"type":"Point"}
}