{
  "type": "Feature",
  "properties": {
    "iso:country":"DE",
    "sg:address":"Sportplatzring 85",
    "sg:city":"Hamburg",
    "sg:phone":"+49 40/54763303",
    "sg:postcode":"22527",
    "sg:province":"Hamburg",
    "wof:name":"Hanseatic Business Services Babette Petersen",
    "wof:placetype":"venue"
},
  "geometry": {"coordinates":[9.9322099686,53.594379425],"type":"Point"}
}