{
  "type": "Feature",
  "properties": {
    "iso:country":"DE",
    "sg:address":"Eidinghausener Str. 5",
    "sg:city":"Bad Oeynhausen",
    "sg:phone":"+49 5731/28666",
    "sg:postcode":"32549",
    "sg:province":"Nordrhein-Westfalen",
    "wof:name":"Bistro Colombage",
    "wof:placetype":"venue"
},
  "geometry": {"coordinates":[8.8037490845,52.2089881897],"type":"Point"}
}