{
  "type": "Feature",
  "properties": {
    "iso:country":"DE",
    "sg:address":"Gartenstr. 20",
    "sg:city":"R\u00f6fingen",
    "sg:phone":"+49 8222/5591",
    "sg:postcode":"89365",
    "sg:province":"Bayern",
    "wof:name":"T. Kast Antiquit\u00e4ten",
    "wof:placetype":"venue"
},
  "geometry": {"coordinates":[10.474191,48.430355],"type":"Point"}
}