{
  "type": "Feature",
  "properties": {
    "iso:country":"DE",
    "sg:address":"Sudermanplatz 8",
    "sg:city":"K\u00f6ln",
    "sg:phone":"+49 221/733511",
    "sg:postcode":"50670",
    "sg:province":"Nordrhein-Westfalen",
    "wof:name":"Dr. J\u00fcrgen Metka Rechtsanwalt",
    "wof:placetype":"venue"
},
  "geometry": {"coordinates":[6.9554309845,50.9513893127],"type":"Point"}
}