{
  "type": "Feature",
  "properties": {
    "iso:country":"DE",
    "sg:address":"Illerberger Str. 6a",
    "sg:city":"Wei\u00dfenhorn",
    "sg:phone":"+49 7309/96100",
    "sg:postcode":"89264",
    "sg:province":"Bayern",
    "wof:name":"Elektrizit\u00e4tswerk Wei\u00dfenhorn Ag",
    "wof:placetype":"venue"
},
  "geometry": {"coordinates":[10.158506,48.303486],"type":"Point"}
}