{
  "type": "Feature",
  "properties": {
    "iso:country":"DE",
    "sg:address":"Poststr. 25 a",
    "sg:city":"Buxtehude",
    "sg:phone":"+49 4161/2830",
    "sg:postcode":"21614",
    "sg:province":"Niedersachsen",
    "wof:name":"Dr. Stefan Schwarz Steuerberater",
    "wof:placetype":"venue"
},
  "geometry": {"coordinates":[9.6920604706,53.4756774902],"type":"Point"}
}