{
  "type": "Feature",
  "properties": {
    "iso:country":"DE",
    "sg:address":"Neue Str. 6",
    "sg:city":"Varel",
    "sg:phone":"+49 4451/85658",
    "sg:postcode":"26316",
    "sg:province":"Niedersachsen",
    "wof:name":"H. Ulbrich",
    "wof:placetype":"venue"
},
  "geometry": {"coordinates":[8.1393947601,53.394821167],"type":"Point"}
}