{
  "type": "Feature",
  "properties": {
    "iso:country":"DE",
    "sg:address":"Landgraf-Karl-Str. 8",
    "sg:city":"Kassel",
    "sg:phone":"+49 561/3160251",
    "sg:postcode":"34131",
    "sg:province":"Hessen",
    "wof:name":"Hasselmann Und M\u00fcller Planungs Gmbh",
    "wof:placetype":"venue"
},
  "geometry": {"coordinates":[9.4432458878,51.3128547668],"type":"Point"}
}