{
  "type": "Feature",
  "properties": {
    "iso:country":"DE",
    "sg:address":"Tannenstr. 8",
    "sg:city":"Wissen",
    "sg:phone":"+49 2742/71772",
    "sg:postcode":"57537",
    "sg:province":"Rheinland-Pfalz",
    "wof:name":"Karl Kr\u00e4mer",
    "wof:placetype":"venue"
},
  "geometry": {"coordinates":[7.735762,50.775093],"type":"Point"}
}