{
  "type": "Feature",
  "properties": {
    "iso:country":"DE",
    "sg:address":"Berliner Str. 31",
    "sg:city":"K\u00f6ln",
    "sg:phone":"+49 221/6402530",
    "sg:postcode":"51063",
    "sg:province":"Nordrhein-Westfalen",
    "wof:name":"Clorinda Lucignano",
    "wof:placetype":"venue"
},
  "geometry": {"coordinates":[7.0084400177,50.9705200195],"type":"Point"}
}