{
  "type": "Feature",
  "properties": {
    "iso:country":"DE",
    "sg:address":"Prenzlauer Promenade 41-42",
    "sg:city":"Berlin",
    "sg:phone":"+49 4930/2817148",
    "sg:postcode":"13089",
    "sg:province":"Berlin",
    "wof:name":"Ags Secura Handels Gmbh",
    "wof:placetype":"venue"
},
  "geometry": {"coordinates":[13.4285163879,52.5599555969],"type":"Point"}
}