{
  "type": "Feature",
  "properties": {
    "iso:country":"DE",
    "sg:address":"Panoramastr. 8",
    "sg:city":"Aichtal",
    "sg:phone":"+49 7127/50714",
    "sg:postcode":"72631",
    "sg:province":"Baden-W\u00fcrttemberg",
    "wof:name":"Hans-peter Maushardt Steuerberater",
    "wof:placetype":"venue"
},
  "geometry": {"coordinates":[9.2029819489,48.621547699],"type":"Point"}
}