{
  "type": "Feature",
  "properties": {
    "iso:country":"DE",
    "sg:address":"Pferdemarkt 18",
    "sg:city":"Bad Oldesloe",
    "sg:phone":"+49 4531/7517",
    "sg:postcode":"23843",
    "sg:province":"Schleswig-Holstein",
    "wof:name":"Restaurant Mykonos",
    "wof:placetype":"venue"
},
  "geometry": {"coordinates":[10.3753499985,53.8121757507],"type":"Point"}
}