{
  "type": "Feature",
  "properties": {
    "iso:country":"DE",
    "sg:address":"Fahrgasse 11",
    "sg:city":"Frankfurt",
    "sg:postcode":"60311",
    "sg:province":"Hessen",
    "wof:name":"H.h.j. Beteiligungs Gmbh",
    "wof:placetype":"venue"
},
  "geometry": {"coordinates":[8.686965,50.110477],"type":"Point"}
}