{
  "type": "Feature",
  "properties": {
    "iso:country":"DE",
    "sg:address":"Hub\u00e4ckerstr. 17",
    "sg:city":"Schw\u00e4bisch Gm\u00fcnd",
    "sg:phone":"+49 7171/946170",
    "sg:postcode":"73529",
    "sg:province":"Baden-W\u00fcrttemberg",
    "wof:name":"Trutz Loeffler Steuerberater",
    "wof:placetype":"venue"
},
  "geometry": {"coordinates":[9.799115181,48.7834739685],"type":"Point"}
}