{
  "type": "Feature",
  "properties": {
    "iso:country":"DE",
    "sg:address":"L\u00fcnener Str. 37",
    "sg:city":"Werne",
    "sg:postcode":"59368",
    "sg:province":"Nordrhein-Westfalen",
    "wof:name":"Omnium Versicherungs- Agentur Gmbh",
    "wof:placetype":"venue"
},
  "geometry": {"coordinates":[7.6280388832,51.6566734314],"type":"Point"}
}