{
  "type": "Feature",
  "properties": {
    "iso:country":"DE",
    "sg:address":"Richrather Str. 156",
    "sg:city":"Hilden",
    "sg:phone":"+49 2103/62526",
    "sg:postcode":"40723",
    "sg:province":"Nordrhein-Westfalen",
    "wof:name":"Restaurant Haus Tillmann",
    "wof:placetype":"venue"
},
  "geometry": {"coordinates":[6.9393749237,51.155960083],"type":"Point"}
}