{
  "type": "Feature",
  "properties": {
    "iso:country":"DE",
    "sg:address":"Wiehesche Str. 7",
    "sg:city":"Ro\u00dfleben",
    "sg:postcode":"06571",
    "sg:province":"Th\u00fcringen",
    "wof:name":"Gpg Unstruttal",
    "wof:placetype":"venue"
},
  "geometry": {"coordinates":[11.431088,51.294445],"type":"Point"}
}