{
  "type": "Feature",
  "properties": {
    "iso:country":"DE",
    "sg:address":"Chemiestr. 2-6",
    "sg:city":"Gernsheim",
    "sg:postcode":"64579",
    "sg:province":"Hessen",
    "wof:name":"H. Itzh\u00f6fer Ohg",
    "wof:placetype":"venue"
},
  "geometry": {"coordinates":[8.4833650589,49.7646942139],"type":"Point"}
}