{
  "type": "Feature",
  "properties": {
    "iso:country":"DE",
    "sg:address":"Wiefelsteder Str. 9",
    "sg:city":"Bad Zwischenahn",
    "sg:phone":"+49 4403/2560",
    "sg:postcode":"26160",
    "sg:province":"Niedersachsen",
    "wof:name":"Como M\u00f6belzentrum Gmbh & Co. Kg",
    "wof:placetype":"venue"
},
  "geometry": {"coordinates":[8.032081,53.182468],"type":"Point"}
}