{
  "type": "Feature",
  "properties": {
    "iso:country":"DE",
    "sg:address":"Gewerbering 43",
    "sg:city":"Pocking",
    "sg:phone":"+49 8531/12505",
    "sg:postcode":"94060",
    "sg:province":"Bayern",
    "wof:name":"Erhard Heinrich",
    "wof:placetype":"venue"
},
  "geometry": {"coordinates":[13.2981758118,48.4079475403],"type":"Point"}
}