{
  "type": "Feature",
  "properties": {
    "iso:country":"DE",
    "sg:address":"Eberhardstr. 35",
    "sg:city":"Stuttgart",
    "sg:phone":"+49 711/245422",
    "sg:postcode":"70173",
    "sg:province":"Baden-W\u00fcrttemberg",
    "wof:name":"W. Hafend\u00f6rfer",
    "wof:placetype":"venue"
},
  "geometry": {"coordinates":[9.17847,48.773659],"type":"Point"}
}