{
  "type": "Feature",
  "properties": {
    "iso:country":"DE",
    "sg:address":"Westenhellweg 1",
    "sg:city":"Soest",
    "sg:postcode":"59494",
    "sg:province":"Nordrhein-Westfalen",
    "wof:name":"Volksbank Hellweg Immobilien Verwaltungsges. Mbh",
    "wof:placetype":"venue"
},
  "geometry": {"coordinates":[8.1002044678,51.5678749084],"type":"Point"}
}