{
  "type": "Feature",
  "properties": {
    "iso:country":"DE",
    "sg:address":"Eisenbahnstr. 8",
    "sg:city":"M\u00fcllheim",
    "sg:phone":"+49 7631/5531",
    "sg:postcode":"79379",
    "sg:province":"Baden-W\u00fcrttemberg",
    "wof:name":"Raiffeisen-zentralgenossen- Schaft Eg",
    "wof:placetype":"venue"
},
  "geometry": {"coordinates":[7.602457,47.810226],"type":"Point"}
}