{
  "type": "Feature",
  "properties": {
    "iso:country":"DE",
    "sg:address":"Hopfenstr. 23",
    "sg:city":"Bad Harzburg",
    "sg:phone":"+49 5322/83433",
    "sg:postcode":"38667",
    "sg:province":"Niedersachsen",
    "wof:name":"Wolfgang Grieger Tichlerei",
    "wof:placetype":"venue"
},
  "geometry": {"coordinates":[10.537521,51.893166],"type":"Point"}
}