{
  "type": "Feature",
  "properties": {
    "iso:country":"DE",
    "sg:address":"M\u00fchlbaurstr. 1",
    "sg:city":"M\u00fcnchen",
    "sg:phone":"+49 89/475111",
    "sg:postcode":"81677",
    "sg:province":"Bayern",
    "wof:name":"Hans Schelle & S\u00f6hne Bauunternehmung Gmbh",
    "wof:placetype":"venue"
},
  "geometry": {"coordinates":[11.6072158813,48.1396331787],"type":"Point"}
}