{
  "type": "Feature",
  "properties": {
    "iso:country":"DE",
    "sg:address":"Kantstr.",
    "sg:city":"Berlin",
    "sg:postcode":"12169",
    "sg:province":"Berlin",
    "wof:name":"Lloyd Industrie Leasing Gmbh",
    "wof:placetype":"venue"
},
  "geometry": {"coordinates":[13.3339347839,52.4566383362],"type":"Point"}
}