{
  "type": "Feature",
  "properties": {
    "iso:country":"DE",
    "sg:address":"Zeitzer Str. 25",
    "sg:city":"Hohenm\u00f6lsen",
    "sg:phone":"+49 34441/22707",
    "sg:postcode":"06679",
    "sg:province":"Sachsen-Anhalt",
    "wof:name":"Schenk & Sohn Gmbh",
    "wof:placetype":"venue"
},
  "geometry": {"coordinates":[12.0952033997,51.1546592712],"type":"Point"}
}