{
  "type": "Feature",
  "properties": {
    "iso:country":"DE",
    "sg:address":"Kiefernstr. 2",
    "sg:city":"Leichlingen",
    "sg:phone":"+49 2175/6016",
    "sg:postcode":"42799",
    "sg:province":"Nordrhein-Westfalen",
    "wof:name":"Ludwig Schmitz Beteiligungsgesellschaft Mbh",
    "wof:placetype":"venue"
},
  "geometry": {"coordinates":[7.005258,51.116119],"type":"Point"}
}