{
  "type": "Feature",
  "properties": {
    "iso:country":"DE",
    "sg:address":"Schlo\u00dfseestr. 3",
    "sg:city":"Bad Endorf",
    "sg:phone":"+49 8053/555",
    "sg:postcode":"83093",
    "sg:province":"Bayern",
    "wof:name":"Franz Singhammer",
    "wof:placetype":"venue"
},
  "geometry": {"coordinates":[12.3064985275,47.9122238159],"type":"Point"}
}