{
  "type": "Feature",
  "properties": {
    "iso:country":"DE",
    "sg:address":"Stuttgarter Platz 1 a",
    "sg:city":"Berlin",
    "sg:postcode":"10627",
    "sg:province":"Berlin",
    "wof:name":"Werbeagentur Lehmann Gmbh",
    "wof:placetype":"venue"
},
  "geometry": {"coordinates":[13.306915,52.505703],"type":"Point"}
}