{
  "type": "Feature",
  "properties": {
    "iso:country":"DE",
    "sg:address":"Hauptstr. 71",
    "sg:city":"Bensheim",
    "sg:phone":"+49 6251/2033",
    "sg:postcode":"64625",
    "sg:province":"Hessen",
    "wof:name":"D. Faix Spiel Und Freizeit Gmbh",
    "wof:placetype":"venue"
},
  "geometry": {"coordinates":[8.6213436127,49.6793746948],"type":"Point"}
}