{
  "type": "Feature",
  "properties": {
    "iso:country":"DE",
    "sg:address":"Speyerer Str. 12",
    "sg:city":"Frankenthal",
    "sg:phone":"+49 6233/319300",
    "sg:postcode":"67227",
    "sg:province":"Rheinland-Pfalz",
    "wof:name":"Tchibo Frisch-r\u00f6st-kaffee Gmbh",
    "wof:placetype":"venue"
},
  "geometry": {"coordinates":[8.3537712097,49.5347328186],"type":"Point"}
}