{
  "type": "Feature",
  "properties": {
    "iso:country":"DE",
    "sg:address":"Hauptstr. 4",
    "sg:city":"Pegnitz",
    "sg:phone":"+49 9241/2219",
    "sg:postcode":"91257",
    "sg:province":"Bayern",
    "wof:name":"Martin Wacker",
    "wof:placetype":"venue"
},
  "geometry": {"coordinates":[11.5437097549,49.7564315796],"type":"Point"}
}