{
  "type": "Feature",
  "properties": {
    "iso:country":"DE",
    "sg:address":"Mispelweg 2",
    "sg:city":"erfurt",
    "sg:postcode":"99097",
    "sg:province":"Th\u00fcringen",
    "wof:name":"Judo",
    "wof:placetype":"venue"
},
  "geometry": {"coordinates":[11.06686,50.950504],"type":"Point"}
}