{
  "type": "Feature",
  "properties": {
    "iso:country":"DE",
    "sg:address":"Winzinger Str. 13",
    "sg:city":"Donzdorf",
    "sg:phone":"+49 7162/24829",
    "sg:postcode":"73072",
    "sg:province":"Baden-W\u00fcrttemberg",
    "wof:name":"Heinrich Blessing",
    "wof:placetype":"venue"
},
  "geometry": {"coordinates":[9.7998142242,48.7091217041],"type":"Point"}
}