{
  "type": "Feature",
  "properties": {
    "iso:country":"DE",
    "sg:address":"Brinkstr. 34",
    "sg:city":"Heek",
    "sg:phone":"+49 2568/769",
    "sg:postcode":"48619",
    "sg:province":"Nordrhein-Westfalen",
    "wof:name":"Baugesch\u00e4ft Terwolbeck Und Sohn Gmbh",
    "wof:placetype":"venue"
},
  "geometry": {"coordinates":[7.10693,52.11356],"type":"Point"}
}