{
  "type": "Feature",
  "properties": {
    "iso:country":"DE",
    "sg:address":"Celsiusstr. 43",
    "sg:city":"Bonn",
    "sg:postcode":"53125",
    "sg:province":"Nordrhein-Westfalen",
    "wof:name":"Artheco Art Health Und Communication Gmbh",
    "wof:placetype":"venue"
},
  "geometry": {"coordinates":[7.0579161644,50.6998405457],"type":"Point"}
}