{
  "type": "Feature",
  "properties": {
    "iso:country":"DE",
    "sg:address":"Hohe Str. 2",
    "sg:city":"Bad Nauheim",
    "sg:phone":"+49 6032/96030",
    "sg:postcode":"61231",
    "sg:province":"Hessen",
    "wof:name":"Lehmann Kabel Gmbh",
    "wof:placetype":"venue"
},
  "geometry": {"coordinates":[8.7513904572,50.3743782043],"type":"Point"}
}