{
  "type": "Feature",
  "properties": {
    "iso:country":"DE",
    "sg:address":"Breslauer Str. 10",
    "sg:city":"Katlenburg-Lindau",
    "sg:phone":"+49 5556/1808",
    "sg:postcode":"37191",
    "sg:province":"Niedersachsen",
    "wof:name":"Wisscom Gmbh",
    "wof:placetype":"venue"
},
  "geometry": {"coordinates":[10.1180124283,51.6580848694],"type":"Point"}
}