{
  "type": "Feature",
  "properties": {
    "iso:country":"DE",
    "sg:address":"Raiffeisenpl. 37",
    "sg:city":"Brohl L\u00fctzing",
    "sg:phone":"+49 2636/2281",
    "sg:postcode":"56656",
    "sg:province":"Rheinland-Pfalz",
    "wof:name":"Volksbank Andernach-bad-breisi",
    "wof:placetype":"venue"
},
  "geometry": {"coordinates":[7.328806,50.482624],"type":"Point"}
}