{
  "type": "Feature",
  "properties": {
    "iso:country":"DE",
    "sg:address":"Remsaer Str. 27a",
    "sg:city":"Altenburg",
    "sg:phone":"+49 3447/836038",
    "sg:postcode":"04600",
    "sg:province":"Th\u00fcringen",
    "wof:name":"Mvs Altenburg",
    "wof:placetype":"venue"
},
  "geometry": {"coordinates":[12.4644441605,51.0027236938],"type":"Point"}
}