{
  "type": "Feature",
  "properties": {
    "iso:country":"DE",
    "sg:address":"Didostr. 4 a",
    "sg:city":"Berlin",
    "sg:phone":"+49 30/3126210",
    "sg:postcode":"12109",
    "sg:province":"Berlin",
    "wof:name":"Joachim D\u00f6ring",
    "wof:placetype":"venue"
},
  "geometry": {"coordinates":[13.398413,52.446777],"type":"Point"}
}