{
  "type": "Feature",
  "properties": {
    "iso:country":"DE",
    "sg:address":"An der Windm\u00fchle 15",
    "sg:city":"Hamm",
    "sg:phone":"+49 2385/444",
    "sg:postcode":"59069",
    "sg:province":"Nordrhein-Westfalen",
    "wof:name":"U. Und Walter J. L\u00fctkhoff",
    "wof:placetype":"venue"
},
  "geometry": {"coordinates":[7.854754,51.627899],"type":"Point"}
}