{
  "type": "Feature",
  "properties": {
    "iso:country":"DE",
    "sg:address":"Schwalbenberg 31",
    "sg:city":"Dingolfing",
    "sg:postcode":"84130",
    "sg:province":"Bayern",
    "wof:name":"La Vie",
    "wof:placetype":"venue"
},
  "geometry": {"coordinates":[12.484664,48.626335],"type":"Point"}
}