{
  "type": "Feature",
  "properties": {
    "iso:country":"DE",
    "sg:address":"Gartenstadt 10",
    "sg:city":"Chemnitz",
    "sg:phone":"+49 371/772158",
    "sg:postcode":"09128",
    "sg:province":"Sachsen",
    "wof:name":"G. D\u00f6schner Kleinolbersdorf-altenhain",
    "wof:placetype":"venue"
},
  "geometry": {"coordinates":[12.99535,50.796345],"type":"Point"}
}