{
  "type": "Feature",
  "properties": {
    "iso:country":"DE",
    "sg:address":"Segeberger Str. 15",
    "sg:city":"Wensin",
    "sg:phone":"+49 4559/1083",
    "sg:postcode":"23827",
    "sg:province":"Schleswig-Holstein",
    "wof:name":"Helmut Knuth",
    "wof:placetype":"venue"
},
  "geometry": {"coordinates":[10.418647,54.00111],"type":"Point"}
}