{
  "type": "Feature",
  "properties": {
    "iso:country":"DE",
    "sg:address":"Wideystr. 12a",
    "sg:city":"Witten",
    "sg:phone":"+49 2302/56188",
    "sg:postcode":"58452",
    "sg:province":"Nordrhein-Westfalen",
    "wof:name":"Julius Moll Ingenieur",
    "wof:placetype":"venue"
},
  "geometry": {"coordinates":[7.3336291313,51.4412117004],"type":"Point"}
}