{
  "type": "Feature",
  "properties": {
    "iso:country":"DE",
    "sg:address":"Ludwig-Thoma-Str. 14",
    "sg:city":"Ainring",
    "sg:phone":"+49 8654/48420",
    "sg:postcode":"83404",
    "sg:province":"Bayern",
    "wof:name":"Allinea Design Beschlag Verwaltungs Gmbh",
    "wof:placetype":"venue"
},
  "geometry": {"coordinates":[12.953855,47.815872],"type":"Point"}
}