{
  "type": "Feature",
  "properties": {
    "iso:country":"DE",
    "sg:address":"J\u00e4gerstr. 12",
    "sg:city":"Pyrbaum",
    "sg:postcode":"90602",
    "sg:province":"Bayern",
    "wof:name":"Kleintierzuchtverein B 429 Peter Vasall",
    "wof:placetype":"venue"
},
  "geometry": {"coordinates":[11.3104753494,49.2630691528],"type":"Point"}
}