{
  "type": "Feature",
  "properties": {
    "iso:country":"DE",
    "sg:address":"Dorfstr. 9a",
    "sg:city":"Henningen",
    "sg:postcode":"29413",
    "sg:province":"Sachsen-Anhalt",
    "wof:name":"As Interieur Planungs- Und Vertriebsges. Mbh",
    "wof:placetype":"venue"
},
  "geometry": {"coordinates":[10.96788,52.8409],"type":"Point"}
}