{
  "type": "Feature",
  "properties": {
    "iso:country":"DE",
    "sg:address":"Zeresweg 39",
    "sg:city":"Viersen",
    "sg:postcode":"41749",
    "sg:province":"Nordrhein-Westfalen",
    "wof:name":"Kreutzer Baumaschinen-verschleissteile",
    "wof:placetype":"venue"
},
  "geometry": {"coordinates":[6.336078,51.306843],"type":"Point"}
}