{
  "type": "Feature",
  "properties": {
    "iso:country":"DE",
    "sg:address":"Kasseler Str. 33",
    "sg:city":"Staufenberg",
    "sg:phone":"+49 5543/4045",
    "sg:postcode":"34355",
    "sg:province":"Niedersachsen",
    "wof:name":"M\u00fcller & H\u00f6ttermann-aderholz",
    "wof:placetype":"venue"
},
  "geometry": {"coordinates":[9.6215982437,51.32970047],"type":"Point"}
}