{
  "type": "Feature",
  "properties": {
    "iso:country":"DE",
    "sg:city":"Ehestetten",
    "sg:phone":"+49 4973/831213",
    "sg:postcode":"72534",
    "sg:province":"Baden-W\u00fcrttemberg",
    "wof:name":"Kreissparkasse Reutlingen",
    "wof:placetype":"venue"
},
  "geometry": {"coordinates":[9.432861,48.321056],"type":"Point"}
}