{
  "type": "Feature",
  "properties": {
    "iso:country":"DE",
    "sg:address":"Kirchweg 15",
    "sg:city":"Simmerath",
    "sg:phone":"+49 2473/6288",
    "sg:postcode":"52152",
    "sg:province":"Nordrhein-Westfalen",
    "wof:name":"K\u00fcpper",
    "wof:placetype":"venue"
},
  "geometry": {"coordinates":[6.3007559776,50.578327179],"type":"Point"}
}