{
  "type": "Feature",
  "properties": {
    "iso:country":"DE",
    "sg:address":"Im Rott 11d",
    "sg:city":"Ratingen",
    "sg:phone":"+49 2102/445308",
    "sg:postcode":"40880",
    "sg:province":"Nordrhein-Westfalen",
    "wof:name":"T. Fank Immobilienmakler",
    "wof:placetype":"venue"
},
  "geometry": {"coordinates":[6.8188300133,51.301486969],"type":"Point"}
}