{
  "type": "Feature",
  "properties": {
    "iso:country":"DE",
    "sg:address":"Ortsstr. 17",
    "sg:city":"Arnsgereuth",
    "sg:phone":"+49 36736/243",
    "sg:postcode":"07318",
    "sg:province":"Th\u00fcringen",
    "wof:name":"F. V\u00f6gele",
    "wof:placetype":"venue"
},
  "geometry": {"coordinates":[11.3160848618,50.6101722717],"type":"Point"}
}