{
  "type": "Feature",
  "properties": {
    "iso:country":"DE",
    "sg:address":"Albertstr. 13",
    "sg:city":"Rhens",
    "sg:phone":"+49 4926/28728",
    "sg:postcode":"56321",
    "sg:province":"Rheinland-Pfalz",
    "wof:name":"Hero Schlauchleitungen Gmbh",
    "wof:placetype":"venue"
},
  "geometry": {"coordinates":[7.6206698418,50.2800712585],"type":"Point"}
}