{
  "type": "Feature",
  "properties": {
    "iso:country":"DE",
    "sg:address":"Heideweg 52",
    "sg:city":"Kerpen",
    "sg:postcode":"50169",
    "sg:province":"Nordrhein-Westfalen",
    "wof:name":"Gedv Gesellschaft F\u00fcr Elektronische Ger\u00e4te Und",
    "wof:placetype":"venue"
},
  "geometry": {"coordinates":[6.721349,50.90675],"type":"Point"}
}