{
  "type": "Feature",
  "properties": {
    "iso:country":"DE",
    "sg:city":"Kutenholz",
    "sg:phone":"+49 4762/1342",
    "sg:postcode":"27449",
    "sg:province":"Niedersachsen",
    "wof:name":"Sporthaus Mulsum",
    "wof:placetype":"venue"
},
  "geometry": {"coordinates":[9.323275,53.481686],"type":"Point"}
}