{
  "type": "Feature",
  "properties": {
    "iso:country":"DE",
    "sg:address":"An der Kirche 5",
    "sg:city":"Schinne",
    "sg:phone":"+49 39320/331",
    "sg:postcode":"39579",
    "sg:province":"Sachsen-Anhalt",
    "wof:name":"Eisdiele Schirmacher",
    "wof:placetype":"venue"
},
  "geometry": {"coordinates":[11.730628,52.658199],"type":"Point"}
}