{
  "type": "Feature",
  "properties": {
    "iso:country":"DE",
    "sg:address":"Saargem\u00fcnder Str. 66",
    "sg:city":"Saarbr\u00fccken",
    "sg:phone":"+49 681/855521",
    "sg:postcode":"66119",
    "sg:province":"Saarland",
    "wof:name":"A. Meyer",
    "wof:placetype":"venue"
},
  "geometry": {"coordinates":[7.0099411011,49.219581604],"type":"Point"}
}