{
  "type": "Feature",
  "properties": {
    "iso:country":"DE",
    "sg:address":"Offerhausweg 2",
    "sg:city":"Soest",
    "sg:phone":"+49 2921/2770",
    "sg:postcode":"59494",
    "sg:province":"Nordrhein-Westfalen",
    "wof:name":"Friedhelm Kowalewicz",
    "wof:placetype":"venue"
},
  "geometry": {"coordinates":[8.093151,51.573139],"type":"Point"}
}