{
  "type": "Feature",
  "properties": {
    "iso:country":"DE",
    "sg:address":"Carl-Zeiss-Str 36",
    "sg:city":"Schorndorf",
    "sg:phone":"+49 7181/489787",
    "sg:postcode":"73614",
    "sg:province":"Baden-W\u00fcrttemberg",
    "wof:name":"Vmz Verpackungs- & Montagezentrum Carina B\u00fcche E.k.",
    "wof:placetype":"venue"
},
  "geometry": {"coordinates":[9.502728,48.791245],"type":"Point"}
}