{
  "type": "Feature",
  "properties": {
    "iso:country":"DE",
    "sg:address":"Vogt-K\u00f6lln-Str. 108",
    "sg:city":"Hamburg",
    "sg:phone":"+49 40/544547",
    "sg:postcode":"22527",
    "sg:province":"Hamburg",
    "wof:name":"Helga Breitschuh Anlageberaterin",
    "wof:placetype":"venue"
},
  "geometry": {"coordinates":[9.9295148849,53.6051673889],"type":"Point"}
}