{
  "type": "Feature",
  "properties": {
    "iso:country":"DE",
    "sg:address":"Mannheimer Str. 31",
    "sg:city":"Berlin",
    "sg:phone":"+49 30/7811088",
    "sg:postcode":"10713",
    "sg:province":"Berlin",
    "wof:name":"Kleinz-holz",
    "wof:placetype":"venue"
},
  "geometry": {"coordinates":[13.3158168793,52.4871482849],"type":"Point"}
}