{
  "type": "Feature",
  "properties": {
    "iso:country":"DE",
    "sg:address":"les V\u00e9gias",
    "sg:city":"Grospierres",
    "sg:phone":"+49 4753/90485",
    "sg:postcode":"07120",
    "wof:name":"Editions-credel",
    "wof:placetype":"venue"
},
  "geometry": {"coordinates":[4.32925,44.446442],"type":"Point"}
}