{
  "type": "Feature",
  "properties": {
    "iso:country":"DE",
    "sg:address":"F\u00fcnf Linden 29",
    "sg:city":"Biberach",
    "sg:phone":"+49 7351/827077",
    "sg:postcode":"88400",
    "sg:province":"Baden-W\u00fcrttemberg",
    "wof:name":"F\u00fcnf Linden Apotheke Apotheker",
    "wof:placetype":"venue"
},
  "geometry": {"coordinates":[9.765441,48.098682],"type":"Point"}
}