{
  "type": "Feature",
  "properties": {
    "iso:country":"DE",
    "sg:address":"Langefeldstr. 13",
    "sg:city":"Barsinghausen",
    "sg:phone":"+49 5105/63539",
    "sg:postcode":"30890",
    "sg:province":"Niedersachsen",
    "wof:name":"Albert Schaper",
    "wof:placetype":"venue"
},
  "geometry": {"coordinates":[9.517589,52.343857],"type":"Point"}
}