{
  "type": "Feature",
  "properties": {
    "iso:country":"DE",
    "sg:address":"B\u00f6hmzwiesel 71",
    "sg:city":"Waldkirchen",
    "sg:phone":"+49 8581/1770",
    "sg:postcode":"94065",
    "sg:province":"Bayern",
    "wof:name":"Dr. Herbert Kittl Steuerberater",
    "wof:placetype":"venue"
},
  "geometry": {"coordinates":[13.6195201874,48.7616043091],"type":"Point"}
}