{
  "type": "Feature",
  "properties": {
    "iso:country":"DE",
    "sg:address":"Mainleite 4",
    "sg:city":"Hallstadt",
    "sg:phone":"+49 951/7001000",
    "sg:postcode":"96103",
    "sg:province":"Bayern",
    "wof:name":"Norbert Lodes",
    "wof:placetype":"venue"
},
  "geometry": {"coordinates":[10.864747,49.933537],"type":"Point"}
}