{
  "type": "Feature",
  "properties": {
    "iso:country":"DE",
    "sg:address":"Herrengarten 18",
    "sg:city":"Remptendorf",
    "sg:phone":"+49 36640/26090",
    "sg:postcode":"07368",
    "sg:province":"Th\u00fcringen",
    "wof:name":"Ralf Ruder",
    "wof:placetype":"venue"
},
  "geometry": {"coordinates":[11.6574687958,50.5302772522],"type":"Point"}
}