{
  "type": "Feature",
  "properties": {
    "iso:country":"DE",
    "sg:address":"Luisenstr. 28",
    "sg:city":"Offenbach",
    "sg:phone":"+49 69/887846",
    "sg:postcode":"63067",
    "sg:province":"Hessen",
    "wof:name":"Heinz Winter",
    "wof:placetype":"venue"
},
  "geometry": {"coordinates":[8.7581348419,50.1013336182],"type":"Point"}
}