{
  "type": "Feature",
  "properties": {
    "iso:country":"DE",
    "sg:address":"Max-Planck-Strasse 9",
    "sg:city":"Friedrichsdorf",
    "sg:phone":"+49 6172/599833",
    "sg:postcode":"61381",
    "sg:province":"Hessen",
    "wof:name":"Mediagruppe *** Web Arts / Fixdruck",
    "wof:placetype":"venue"
},
  "geometry": {"coordinates":[8.6568889618,50.2588882446],"type":"Point"}
}