{
  "type": "Feature",
  "properties": {
    "iso:country":"DE",
    "sg:address":"Im Haagfeld 12",
    "sg:city":"Duisburg",
    "sg:phone":"+49 203/751955",
    "sg:postcode":"47259",
    "sg:province":"Nordrhein-Westfalen",
    "wof:name":"Tmc Thomas Michel Consulting Gmbh",
    "wof:placetype":"venue"
},
  "geometry": {"coordinates":[6.746655941,51.362411499],"type":"Point"}
}