{
  "type": "Feature",
  "properties": {
    "iso:country":"DE",
    "sg:address":"Kernerstr. 47",
    "sg:city":"Bad Wildbad",
    "sg:phone":"+49 7081/2463",
    "sg:postcode":"75323",
    "sg:province":"Baden-W\u00fcrttemberg",
    "wof:name":"Kurgarten-hotel Gmbh",
    "wof:placetype":"venue"
},
  "geometry": {"coordinates":[8.5319004059,48.7209014893],"type":"Point"}
}