{
  "type": "Feature",
  "properties": {
    "iso:country":"DE",
    "sg:address":"Goethestr. 3",
    "sg:city":"Erlangen",
    "sg:phone":"+49 9131/26454",
    "sg:postcode":"91054",
    "sg:province":"Bayern",
    "wof:name":"Fischer-rundfunk- Fernseh-hi Fi-reparatur-",
    "wof:placetype":"venue"
},
  "geometry": {"coordinates":[11.0020694733,49.5984268188],"type":"Point"}
}