{
  "type": "Feature",
  "properties": {
    "iso:country":"DE",
    "sg:address":"Zollernblickstr. 8 H\u00e4slach",
    "sg:city":"Walddorfh\u00e4slach",
    "sg:phone":"+49 7127/33548",
    "sg:postcode":"72141",
    "sg:province":"Baden-W\u00fcrttemberg",
    "wof:name":"R. Und W. Wolf",
    "wof:placetype":"venue"
},
  "geometry": {"coordinates":[9.184848,48.586254],"type":"Point"}
}