{
  "type": "Feature",
  "properties": {
    "iso:country":"DE",
    "sg:address":"Betzisried 3",
    "sg:city":"Ottobeuren",
    "sg:phone":"+49 8332/6788",
    "sg:postcode":"87724",
    "sg:province":"Bayern",
    "wof:name":"Dr. Hans Kleinschmidt Tierarzt",
    "wof:placetype":"venue"
},
  "geometry": {"coordinates":[10.3539619446,47.9477424622],"type":"Point"}
}