{
  "type": "Feature",
  "properties": {
    "iso:country":"DE",
    "sg:address":"Brunnenstr. 4",
    "sg:city":"Braubach",
    "sg:phone":"+49 2627/559",
    "sg:postcode":"56338",
    "sg:province":"Rheinland-Pfalz",
    "wof:name":"Erich Kunz",
    "wof:placetype":"venue"
},
  "geometry": {"coordinates":[7.625291,50.574581],"type":"Point"}
}