{
  "type": "Feature",
  "properties": {
    "iso:country":"DE",
    "sg:address":"An den Eichen 10",
    "sg:city":"Minden",
    "sg:phone":"+49 571/43311",
    "sg:postcode":"32425",
    "sg:province":"Nordrhein-Westfalen",
    "wof:name":"Wilhelm Kahre",
    "wof:placetype":"venue"
},
  "geometry": {"coordinates":[8.875619,52.340454],"type":"Point"}
}