{
  "type": "Feature",
  "properties": {
    "iso:country":"DE",
    "sg:address":"Ahsener Str. 3",
    "sg:city":"Datteln",
    "sg:postcode":"45711",
    "sg:province":"Nordrhein-Westfalen",
    "wof:name":"Hs Schach-centrum Datteln E. K.",
    "wof:placetype":"venue"
},
  "geometry": {"coordinates":[7.338554,51.653011],"type":"Point"}
}