{
  "type": "Feature",
  "properties": {
    "iso:country":"DE",
    "sg:address":"Auf dem Stumpelrott 36",
    "sg:city":"K\u00f6ln",
    "sg:phone":"+49 221/353350",
    "sg:postcode":"50999",
    "sg:province":"Nordrhein-Westfalen",
    "wof:name":"Helmut Tietz Architekt",
    "wof:placetype":"venue"
},
  "geometry": {"coordinates":[7.018457,50.882397],"type":"Point"}
}