{
  "type": "Feature",
  "properties": {
    "iso:country":"DE",
    "sg:address":"Konrad-Adenauer-Str. 4",
    "sg:city":"Oberkirch",
    "sg:phone":"+49 7802/4621",
    "sg:postcode":"77704",
    "sg:province":"Baden-W\u00fcrttemberg",
    "wof:name":"J\u00fclg-ziegler Gmbh",
    "wof:placetype":"venue"
},
  "geometry": {"coordinates":[8.0618448257,48.5381584167],"type":"Point"}
}