{
  "type": "Feature",
  "properties": {
    "iso:country":"DE",
    "sg:address":"Otto-Hahn-Str. 247",
    "sg:city":"D\u00fcsseldorf",
    "sg:phone":"+49 211/750467",
    "sg:postcode":"40591",
    "sg:province":"Nordrhein-Westfalen",
    "wof:name":"Wolfgang Barth",
    "wof:placetype":"venue"
},
  "geometry": {"coordinates":[6.811733,51.179382],"type":"Point"}
}