{
  "type": "Feature",
  "properties": {
    "iso:country":"DE",
    "sg:address":"Brunnenstr. 20",
    "sg:city":"Neunkirchen",
    "sg:phone":"+49 6821/180",
    "sg:postcode":"66538",
    "sg:province":"Saarland",
    "wof:name":"Krankenhaus Neunkirchen Gemeinn\u00fctzige Gmbh",
    "wof:placetype":"venue"
},
  "geometry": {"coordinates":[7.182924,49.341724],"type":"Point"}
}