{
  "type": "Feature",
  "properties": {
    "iso:country":"DE",
    "sg:address":"Grabenstr. 23",
    "sg:city":"Weil der Stadt",
    "sg:phone":"+49 7033/7172",
    "sg:postcode":"71263",
    "sg:province":"Baden-W\u00fcrttemberg",
    "wof:name":"Dea Tankstelle",
    "wof:placetype":"venue"
},
  "geometry": {"coordinates":[8.8673973083,48.7501754761],"type":"Point"}
}