{
  "type": "Feature",
  "properties": {
    "iso:country":"DE",
    "sg:address":"Neuer Markt 11",
    "sg:city":"Meckenheim",
    "sg:phone":"+49 2225/15959",
    "sg:postcode":"53340",
    "sg:province":"Nordrhein-Westfalen",
    "wof:name":"Neurologische Arztpraxis Dr. Martin Ruppenthal",
    "wof:placetype":"venue"
},
  "geometry": {"coordinates":[7.0397,50.625481],"type":"Point"}
}