{
  "type": "Feature",
  "properties": {
    "iso:country":"DE",
    "sg:address":"Sterndamm 8",
    "sg:city":"Berlin",
    "sg:phone":"+49 30/63979034",
    "sg:postcode":"12487",
    "sg:province":"Berlin",
    "wof:name":"Norbert Schwarz & Gerald D\u00fcwel",
    "wof:placetype":"venue"
},
  "geometry": {"coordinates":[13.5094242096,52.4533843994],"type":"Point"}
}