{
  "type": "Feature",
  "properties": {
    "iso:country":"DE",
    "sg:address":"Schellingstr. 40",
    "sg:city":"N\u00fcrtingen",
    "sg:phone":"+49 7022/8102",
    "sg:postcode":"72622",
    "sg:province":"Baden-W\u00fcrttemberg",
    "wof:name":"Siegfried Bader Steuerberater",
    "wof:placetype":"venue"
},
  "geometry": {"coordinates":[9.3505144119,48.6269416809],"type":"Point"}
}