{
  "type": "Feature",
  "properties": {
    "iso:country":"DE",
    "sg:address":"Pl\u00f6nlein 4",
    "sg:city":"Rothenburg",
    "sg:phone":"+49 9861/4555",
    "sg:postcode":"91541",
    "sg:province":"Bayern",
    "wof:name":"Pl\u00f6nlein",
    "wof:placetype":"venue"
},
  "geometry": {"coordinates":[10.1801252365,49.3742523193],"type":"Point"}
}