{
  "type": "Feature",
  "properties": {
    "iso:country":"DE",
    "sg:address":"Leipziger Str. 44 - 46",
    "sg:city":"Liebertwolkwitz",
    "sg:phone":"+49 34297/42261",
    "sg:postcode":"04445",
    "wof:name":"Hotel-restaurant Liebethal",
    "wof:placetype":"venue"
},
  "geometry": {"coordinates":[12.4643497467,51.2824897766],"type":"Point"}
}