{
  "type": "Feature",
  "properties": {
    "iso:country":"DE",
    "sg:address":"Trifelsstr. 10",
    "sg:city":"Leinsweiler",
    "sg:phone":"+49 6345/919186",
    "sg:postcode":"76829",
    "sg:province":"Rheinland-Pfalz",
    "wof:name":"Weingut Arthur \u00dcbel",
    "wof:placetype":"venue"
},
  "geometry": {"coordinates":[8.0181798935,49.1833763123],"type":"Point"}
}