{
  "type": "Feature",
  "properties": {
    "iso:country":"DE",
    "sg:address":"Vordere Schnaid 27",
    "sg:city":"Wallenfels",
    "sg:phone":"+49 9262/1325",
    "sg:postcode":"96346",
    "sg:province":"Bayern",
    "wof:name":"V. Engelhardt",
    "wof:placetype":"venue"
},
  "geometry": {"coordinates":[11.540038,50.284412],"type":"Point"}
}