{
  "type": "Feature",
  "properties": {
    "iso:country":"DE",
    "sg:address":"Rote-Hahnen-Gasse 4",
    "sg:city":"Regensburg",
    "sg:phone":"+49 941/55641",
    "sg:postcode":"93047",
    "sg:province":"Bayern",
    "wof:name":"Ludwig Schifferl",
    "wof:placetype":"venue"
},
  "geometry": {"coordinates":[12.092684,49.019241],"type":"Point"}
}