{
  "type": "Feature",
  "properties": {
    "iso:country":"DE",
    "sg:address":"Robert-Leicht-Str. 97",
    "sg:city":"Stuttgart",
    "sg:phone":"+49 711/6797550",
    "sg:postcode":"70563",
    "sg:province":"Baden-W\u00fcrttemberg",
    "wof:name":"Datentechnik Krehl Gmbh",
    "wof:placetype":"venue"
},
  "geometry": {"coordinates":[9.1070213318,48.7391166687],"type":"Point"}
}