{
  "type": "Feature",
  "properties": {
    "iso:country":"DE",
    "sg:address":"Auchtweg 19",
    "sg:city":"Esslingen",
    "sg:phone":"+49 711/381649",
    "sg:postcode":"73734",
    "sg:province":"Baden-W\u00fcrttemberg",
    "wof:name":"A. Und W. Scheuring",
    "wof:placetype":"venue"
},
  "geometry": {"coordinates":[9.300083,48.727497],"type":"Point"}
}