{
  "type": "Feature",
  "properties": {
    "iso:country":"DE",
    "sg:address":"An der Badeanstalt 3",
    "sg:city":"Bad Laer",
    "sg:phone":"+49 5424/9403",
    "sg:postcode":"49196",
    "sg:province":"Niedersachsen",
    "wof:name":"B. Pohlmann-maus",
    "wof:placetype":"venue"
},
  "geometry": {"coordinates":[8.0811672211,52.1035804749],"type":"Point"}
}