{
  "type": "Feature",
  "properties": {
    "iso:country":"DE",
    "sg:address":"Hohenstaufenstr. 2 -4",
    "sg:city":"D\u00fcsseldorf",
    "sg:phone":"+49 211/490033",
    "sg:postcode":"40547",
    "sg:province":"Nordrhein-Westfalen",
    "wof:name":"Idee Werbekonzeption Gmbh",
    "wof:placetype":"venue"
},
  "geometry": {"coordinates":[6.7601981163,51.2361755371],"type":"Point"}
}