{
  "type": "Feature",
  "properties": {
    "iso:country":"DE",
    "sg:address":"Karl-Marx-Allee 6",
    "sg:city":"Berlin",
    "sg:postcode":"10178",
    "sg:province":"Berlin",
    "wof:name":"Renate Harnack",
    "wof:placetype":"venue"
},
  "geometry": {"coordinates":[13.41783,52.521297],"type":"Point"}
}