{
  "type": "Feature",
  "properties": {
    "iso:country":"DE",
    "sg:address":"Marxnweg 4",
    "sg:city":"Sauerlach",
    "sg:postcode":"82054",
    "sg:province":"Bayern",
    "wof:name":"M-tec Ag",
    "wof:placetype":"venue"
},
  "geometry": {"coordinates":[11.595607,47.961678],"type":"Point"}
}