{
  "type": "Feature",
  "properties": {
    "iso:country":"DE",
    "sg:address":"Kirchenweg 15",
    "sg:city":"Gmund",
    "sg:phone":"+49 8022/76700",
    "sg:postcode":"83703",
    "sg:province":"Bayern",
    "wof:name":"Evang. Pfarrb\u00fccherei",
    "wof:placetype":"venue"
},
  "geometry": {"coordinates":[11.741479,47.749893],"type":"Point"}
}