{
  "type": "Feature",
  "properties": {
    "iso:country":"DE",
    "sg:address":"Adolf-Ludwig-Ring 78",
    "sg:city":"Pirmasens",
    "sg:phone":"+49 6331/47622",
    "sg:postcode":"66955",
    "sg:province":"Rheinland-Pfalz",
    "wof:name":"Uwe Wenger",
    "wof:placetype":"venue"
},
  "geometry": {"coordinates":[7.6322979927,49.1891326904],"type":"Point"}
}