{
  "type": "Feature",
  "properties": {
    "iso:country":"DE",
    "sg:address":"Katharinenstr. 4",
    "sg:city":"Herbsleben",
    "sg:phone":"+49 36041/56192",
    "sg:postcode":"99955",
    "sg:province":"Th\u00fcringen",
    "wof:name":"E. Oberender",
    "wof:placetype":"venue"
},
  "geometry": {"coordinates":[10.8314094543,51.1168899536],"type":"Point"}
}