{
  "type": "Feature",
  "properties": {
    "iso:country":"DE",
    "sg:address":"Tylerstr. 7b",
    "sg:city":"Augsburg",
    "sg:phone":"+49 821/4444255",
    "sg:postcode":"86156",
    "sg:province":"Bayern",
    "wof:name":"U. Wirth",
    "wof:placetype":"venue"
},
  "geometry": {"coordinates":[10.850274086,48.3730201721],"type":"Point"}
}