{
  "type": "Feature",
  "properties": {
    "iso:country":"DE",
    "sg:address":"Maria-Hilf-Str. 5",
    "sg:city":"K\u00f6ln",
    "sg:phone":"+49 221/319152",
    "sg:postcode":"50677",
    "sg:province":"Nordrhein-Westfalen",
    "wof:name":"Vico Pohl Gmbh",
    "wof:placetype":"venue"
},
  "geometry": {"coordinates":[6.956198,50.920033],"type":"Point"}
}