{
  "type": "Feature",
  "properties": {
    "iso:country":"DE",
    "sg:address":"Hauptstr. 60",
    "sg:city":"Windehausen",
    "sg:phone":"+49 36333/70298",
    "sg:postcode":"99765",
    "sg:province":"Th\u00fcringen",
    "wof:name":"Anton Deutl",
    "wof:placetype":"venue"
},
  "geometry": {"coordinates":[10.870648,51.464058],"type":"Point"}
}