{
  "type": "Feature",
  "properties": {
    "iso:country":"DE",
    "sg:address":"Kocheler Str. 26",
    "sg:city":"Schlehdorf",
    "sg:phone":"+49 8851/1339",
    "sg:postcode":"82444",
    "sg:province":"Bayern",
    "wof:name":"Kammerlochner Gmbh",
    "wof:placetype":"venue"
},
  "geometry": {"coordinates":[11.315452,47.65699],"type":"Point"}
}