{
  "type": "Feature",
  "properties": {
    "iso:country":"DE",
    "sg:address":"Am Klettbach 2",
    "sg:city":"Morbach",
    "sg:postcode":"54497",
    "sg:province":"Rheinland-Pfalz",
    "wof:name":"Klein Ag",
    "wof:placetype":"venue"
},
  "geometry": {"coordinates":[7.1214160919,49.8085746765],"type":"Point"}
}