{
  "type": "Feature",
  "properties": {
    "iso:country":"DE",
    "sg:address":"Belgradstr. 34",
    "sg:city":"M\u00fcnchen",
    "sg:phone":"+49 89/30657887",
    "sg:postcode":"80796",
    "sg:province":"Bayern",
    "wof:name":"Dkv Versicherung Ag Leutner Und Neisser",
    "wof:placetype":"venue"
},
  "geometry": {"coordinates":[11.5745992661,48.164352417],"type":"Point"}
}