{
  "type": "Feature",
  "properties": {
    "iso:country":"DE",
    "sg:address":"Walbecker Str. 155",
    "sg:city":"Geldern",
    "sg:phone":"+49 2831/3798",
    "sg:postcode":"47608",
    "sg:province":"Nordrhein-Westfalen",
    "wof:name":"Berkels Gartenbau Kg",
    "wof:placetype":"venue"
},
  "geometry": {"coordinates":[6.287034,51.513153],"type":"Point"}
}