{
  "type": "Feature",
  "properties": {
    "iso:country":"DE",
    "sg:address":"Adam-Opel-Str. 5",
    "sg:city":"G\u00fctersloh",
    "sg:phone":"+49 5241/68645",
    "sg:postcode":"33334",
    "sg:province":"Nordrhein-Westfalen",
    "wof:name":"Karl-heinz Viebrock",
    "wof:placetype":"venue"
},
  "geometry": {"coordinates":[8.4340200424,51.9424781799],"type":"Point"}
}