{
  "type": "Feature",
  "properties": {
    "iso:country":"DE",
    "sg:address":"Am Gymnasium 1",
    "sg:city":"Rendsburg",
    "sg:postcode":"24768",
    "sg:province":"Schleswig-Holstein",
    "wof:name":"Immac Objektmanagement Gmbh",
    "wof:placetype":"venue"
},
  "geometry": {"coordinates":[9.665586,54.303593],"type":"Point"}
}