{
  "type": "Feature",
  "properties": {
    "iso:country":"DE",
    "sg:address":"Am Streuerkamp 5",
    "sg:city":"Bad Harzburg",
    "sg:phone":"+49 5322/82432",
    "sg:postcode":"38667",
    "sg:province":"Niedersachsen",
    "wof:name":"Harzer Lederst\u00fcbchen Inh. Brigitte Raab",
    "wof:placetype":"venue"
},
  "geometry": {"coordinates":[10.566156,51.892857],"type":"Point"}
}