{
  "type": "Feature",
  "properties": {
    "iso:country":"DE",
    "sg:address":"Feldstr. 15",
    "sg:city":"Kelsterbach",
    "sg:phone":"+49 6107/8223",
    "sg:postcode":"65451",
    "sg:province":"Hessen",
    "wof:name":"Theodor Becker Bauunternehmen",
    "wof:placetype":"venue"
},
  "geometry": {"coordinates":[8.533123,50.070015],"type":"Point"}
}