{
  "type": "Feature",
  "properties": {
    "iso:country":"DE",
    "sg:address":"Mozartstr. 40",
    "sg:city":"Bad D\u00fcrkheim",
    "sg:phone":"+49 6322/920260",
    "sg:postcode":"67098",
    "sg:province":"Rheinland-Pfalz",
    "wof:name":"Transport Industriels Luxembourgeois Gmbh",
    "wof:placetype":"venue"
},
  "geometry": {"coordinates":[8.163687706,49.4531860352],"type":"Point"}
}