{
  "type": "Feature",
  "properties": {
    "iso:country":"DE",
    "sg:address":"Albert-Schweitzer-Str. 13",
    "sg:city":"Cottbus",
    "sg:phone":"+49 355/24630",
    "sg:postcode":"03050",
    "sg:province":"Brandenburg",
    "wof:name":"Siegfried Scholle",
    "wof:placetype":"venue"
},
  "geometry": {"coordinates":[14.328885,51.72826],"type":"Point"}
}