{
  "type": "Feature",
  "properties": {
    "iso:country":"DE",
    "sg:address":"Moosstr. 64",
    "sg:city":"Bamberg",
    "sg:phone":"+49 951/15551",
    "sg:postcode":"96050",
    "sg:province":"Bayern",
    "wof:name":"Kugellager Denkhaus Ohg",
    "wof:placetype":"venue"
},
  "geometry": {"coordinates":[10.91636,49.893421],"type":"Point"}
}