{
  "type": "Feature",
  "properties": {
    "iso:country":"DE",
    "sg:address":"Hauptstr. 9",
    "sg:city":"Dietenheim",
    "sg:phone":"+49 4973/472520",
    "sg:postcode":"89165",
    "sg:province":"Baden-W\u00fcrttemberg",
    "wof:name":"Raiffeisenbank Wain Eg",
    "wof:placetype":"venue"
},
  "geometry": {"coordinates":[10.069192,48.213943],"type":"Point"}
}