{
  "type": "Feature",
  "properties": {
    "iso:country":"DE",
    "sg:address":"Erdinger Str. 21",
    "sg:city":"Reichshof",
    "sg:phone":"+49 2296/1831",
    "sg:postcode":"51580",
    "sg:province":"Nordrhein-Westfalen",
    "wof:name":"A. Mattersberger",
    "wof:placetype":"venue"
},
  "geometry": {"coordinates":[7.691082,50.918224],"type":"Point"}
}