{
  "type": "Feature",
  "properties": {
    "iso:country":"DE",
    "sg:address":"Nettetaler Str. 160",
    "sg:city":"Viersen",
    "sg:phone":"+49 2153/2791",
    "sg:postcode":"41751",
    "sg:province":"Nordrhein-Westfalen",
    "wof:name":"H. Ungerechts",
    "wof:placetype":"venue"
},
  "geometry": {"coordinates":[6.271742,51.273384],"type":"Point"}
}