{
  "type": "Feature",
  "properties": {
    "iso:country":"DE",
    "sg:address":"Veillodterstr. 9",
    "sg:city":"N\u00fcrnberg",
    "sg:phone":"+49 911/532223",
    "sg:postcode":"90409",
    "sg:province":"Bayern",
    "wof:name":"Gerhard Riedel Ingenieur",
    "wof:placetype":"venue"
},
  "geometry": {"coordinates":[11.0878839493,49.4595832825],"type":"Point"}
}