{
  "type": "Feature",
  "properties": {
    "iso:country":"DE",
    "sg:address":"Lange H\u00e4lden 4",
    "sg:city":"Nordheim",
    "sg:postcode":"74226",
    "sg:province":"Baden-W\u00fcrttemberg",
    "wof:name":"Kmh Kunststoff Und Maschinen Handels Gmbh",
    "wof:placetype":"venue"
},
  "geometry": {"coordinates":[9.1287584305,49.1044998169],"type":"Point"}
}