{
  "type": "Feature",
  "properties": {
    "iso:country":"DE",
    "sg:address":"Thiergartenstr. 76",
    "sg:city":"Argenthal",
    "sg:phone":"+49 6761/94500",
    "sg:postcode":"55496",
    "sg:province":"Rheinland-Pfalz",
    "wof:name":"Baumgarten Verwaltungs-gmbh",
    "wof:placetype":"venue"
},
  "geometry": {"coordinates":[7.601253,49.969456],"type":"Point"}
}