{
  "type": "Feature",
  "properties": {
    "iso:country":"DE",
    "sg:address":"Pastorendamm 97e",
    "sg:city":"Tornesch",
    "sg:phone":"+49 4122/961661",
    "sg:postcode":"25436",
    "sg:province":"Schleswig-Holstein",
    "wof:name":"Katrin Cl\u00fcver Rechtsanw\u00e4ltin",
    "wof:placetype":"venue"
},
  "geometry": {"coordinates":[9.721619606,53.7096481323],"type":"Point"}
}