{
  "type": "Feature",
  "properties": {
    "iso:country":"DE",
    "sg:address":"Bergstr. 57",
    "sg:city":"Neudenau",
    "sg:phone":"+49 4962/64566",
    "sg:postcode":"74861",
    "sg:province":"Baden-W\u00fcrttemberg",
    "wof:name":"Ehrenfried Ungerer",
    "wof:placetype":"venue"
},
  "geometry": {"coordinates":[9.273776,49.298302],"type":"Point"}
}