{
  "type": "Feature",
  "properties": {
    "iso:country":"DE",
    "sg:address":"Gotenstr. 22",
    "sg:city":"Berlin",
    "sg:phone":"+49 30/7812002",
    "sg:postcode":"10829",
    "sg:province":"Berlin",
    "wof:name":"Taxicom Gmbh",
    "wof:placetype":"venue"
},
  "geometry": {"coordinates":[13.360015,52.480412],"type":"Point"}
}