{
  "type": "Feature",
  "properties": {
    "iso:country":"DE",
    "sg:address":"Haigerlocher Str. 2",
    "sg:city":"Hechingen",
    "sg:phone":"+49 7471/13753",
    "sg:postcode":"72379",
    "sg:province":"Baden-W\u00fcrttemberg",
    "wof:name":"M. Creuzberger",
    "wof:placetype":"venue"
},
  "geometry": {"coordinates":[8.9632148743,48.3562316895],"type":"Point"}
}