{
  "type": "Feature",
  "properties": {
    "iso:country":"DE",
    "sg:address":"Ludwigstr. 3",
    "sg:city":"Dahn",
    "sg:phone":"+49 6391/5622",
    "sg:postcode":"66994",
    "sg:province":"Rheinland-Pfalz",
    "wof:name":"B\u00fcttelwoog Campingplatz",
    "wof:placetype":"venue"
},
  "geometry": {"coordinates":[7.77652,49.148781],"type":"Point"}
}