{
  "type": "Feature",
  "properties": {
    "iso:country":"DE",
    "sg:address":"Braunschweiger Str. 18",
    "sg:city":"Gifhorn",
    "sg:phone":"+49 5371/95725",
    "sg:postcode":"38518",
    "sg:province":"Niedersachsen",
    "wof:name":"Job & Fun",
    "wof:placetype":"venue"
},
  "geometry": {"coordinates":[10.5440349579,52.4793968201],"type":"Point"}
}