{
  "type": "Feature",
  "properties": {
    "iso:country":"DE",
    "sg:address":"Hochbergstr. 42",
    "sg:city":"Horb",
    "sg:phone":"+49 7482/506",
    "sg:postcode":"72160",
    "sg:province":"Baden-W\u00fcrttemberg",
    "wof:name":"Ernst Rapp",
    "wof:placetype":"venue"
},
  "geometry": {"coordinates":[8.589803,48.43037],"type":"Point"}
}