{
  "type": "Feature",
  "properties": {
    "iso:country":"DE",
    "sg:address":"Hauptstr. 80 b",
    "sg:city":"Wietmarschen",
    "sg:phone":"+49 5908/969196",
    "sg:postcode":"49835",
    "sg:province":"Niedersachsen",
    "wof:name":"Sms T\u00fcrenstudio Gmbh",
    "wof:placetype":"venue"
},
  "geometry": {"coordinates":[7.227674,52.499275],"type":"Point"}
}