{
  "type": "Feature",
  "properties": {
    "iso:country":"DE",
    "sg:address":"Holzkirchener Str. 33",
    "sg:city":"Helmstadt",
    "sg:phone":"+49 9369/502",
    "sg:postcode":"97264",
    "sg:province":"Bayern",
    "wof:name":"Anton Und Erika Ament",
    "wof:placetype":"venue"
},
  "geometry": {"coordinates":[9.6992645264,49.7646598816],"type":"Point"}
}