{
  "type": "Feature",
  "properties": {
    "iso:country":"DE",
    "sg:address":"Daimlerstr 13-15",
    "sg:city":"L\u00fcbbecke",
    "sg:phone":"+49 5741/31866",
    "sg:postcode":"32312",
    "sg:province":"Nordrhein-Westfalen",
    "wof:name":"Grewing",
    "wof:placetype":"venue"
},
  "geometry": {"coordinates":[8.626848,52.3269],"type":"Point"}
}