{
  "type": "Feature",
  "properties": {
    "iso:country":"DE",
    "sg:address":"Rintelner Str. 10",
    "sg:city":"Kalletal",
    "sg:phone":"+49 5264/258",
    "sg:postcode":"32689",
    "sg:province":"Nordrhein-Westfalen",
    "wof:name":"Paul Hieronymus Inh. Renate Gresmeier",
    "wof:placetype":"venue"
},
  "geometry": {"coordinates":[8.949559,52.107265],"type":"Point"}
}