{
  "type": "Feature",
  "properties": {
    "iso:country":"DE",
    "sg:address":"Eltinger Str. 5",
    "sg:city":"Leonberg",
    "sg:phone":"+49 7152/28004",
    "sg:postcode":"71229",
    "sg:province":"Baden-W\u00fcrttemberg",
    "wof:name":"Dr. Med. Ulrich Rabes Arzt F\u00fcr Dermatologie",
    "wof:placetype":"venue"
},
  "geometry": {"coordinates":[9.0173177719,48.7998886108],"type":"Point"}
}