{
  "type": "Feature",
  "properties": {
    "iso:country":"DE",
    "sg:address":"Stodthagener Weg 10a",
    "sg:city":"Felm",
    "sg:phone":"+49 4349/919600",
    "sg:postcode":"24244",
    "sg:province":"Schleswig-Holstein",
    "wof:name":"Horst Schiebur",
    "wof:placetype":"venue"
},
  "geometry": {"coordinates":[10.0758304596,54.4169311523],"type":"Point"}
}