{
  "type": "Feature",
  "properties": {
    "iso:country":"DE",
    "sg:address":"Fockenbrocksheide",
    "sg:city":"Telgte",
    "sg:phone":"+49 700 0437 8537",
    "sg:postcode":"48291",
    "sg:province":"Nordrhein-Westfalen",
    "wof:name":"Tele Vision Gmbh - Tv, Video, Multimedia",
    "wof:placetype":"venue"
},
  "geometry": {"coordinates":[7.824238,51.998428],"type":"Point"}
}