{
  "type": "Feature",
  "properties": {
    "iso:country":"DE",
    "sg:address":"K\u00f6lnstr. 5",
    "sg:city":"Bonn",
    "sg:phone":"+49 228/631788",
    "sg:postcode":"53111",
    "sg:province":"Nordrhein-Westfalen",
    "wof:name":"Herbert Wagner",
    "wof:placetype":"venue"
},
  "geometry": {"coordinates":[7.1009540558,50.7382583618],"type":"Point"}
}