{
  "type": "Feature",
  "properties": {
    "iso:country":"DE",
    "sg:address":"R\u00f6mermauer 3",
    "sg:city":"Bitburg",
    "sg:phone":"+49 6561/140",
    "sg:postcode":"54634",
    "sg:province":"Rheinland-Pfalz",
    "wof:name":"Bitburger Getr\u00e4nke Verwaltungsges. Mbh",
    "wof:placetype":"venue"
},
  "geometry": {"coordinates":[6.523283,49.974365],"type":"Point"}
}