{
  "type": "Feature",
  "properties": {
    "iso:country":"DE",
    "sg:address":"Keilbergstr. 29",
    "sg:city":"Kurort Oberwiesenthal",
    "sg:phone":"+49 37348/7489",
    "sg:postcode":"09484",
    "sg:province":"Sachsen",
    "wof:name":"Herms Schmidt",
    "wof:placetype":"venue"
},
  "geometry": {"coordinates":[12.9653921127,50.4161872864],"type":"Point"}
}