{
  "type": "Feature",
  "properties": {
    "iso:country":"DE",
    "sg:address":"Traunsteiner Str. 50",
    "sg:city":"Altenmarkt",
    "sg:phone":"+49 8621/2807",
    "sg:postcode":"83352",
    "sg:province":"Bayern",
    "wof:name":"Silvia Brinninger Boutique",
    "wof:placetype":"venue"
},
  "geometry": {"coordinates":[12.536548,47.991859],"type":"Point"}
}