{
  "type": "Feature",
  "properties": {
    "iso:country":"DE",
    "sg:address":"Hauptstr. 85",
    "sg:city":"Holzappel",
    "sg:phone":"+49 6439/264",
    "sg:postcode":"56379",
    "sg:province":"Rheinland-Pfalz",
    "wof:name":"Wolfgang Schnatz",
    "wof:placetype":"venue"
},
  "geometry": {"coordinates":[7.897379,50.353233],"type":"Point"}
}