{
  "type": "Feature",
  "properties": {
    "iso:country":"DE",
    "sg:address":"Delmenhorster Str. 152",
    "sg:city":"Stuhr",
    "sg:phone":"+49 4206/1062",
    "sg:postcode":"28816",
    "sg:province":"Niedersachsen",
    "wof:name":"Gasthaus St\u00fchrmann",
    "wof:placetype":"venue"
},
  "geometry": {"coordinates":[8.7106895447,52.9960403442],"type":"Point"}
}