{
  "type": "Feature",
  "properties": {
    "iso:country":"DE",
    "sg:address":"Bredenbekermoor",
    "sg:city":"Bredenbek",
    "sg:phone":"+49 4334/221",
    "sg:postcode":"24796",
    "sg:province":"Schleswig-Holstein",
    "wof:name":"Rudolf Obermeier",
    "wof:placetype":"venue"
},
  "geometry": {"coordinates":[9.856716156,54.3175888062],"type":"Point"}
}