{
  "type": "Feature",
  "properties": {
    "iso:country":"DE",
    "sg:address":"August-Bebel-Str. 28",
    "sg:city":"Oelsnitz",
    "sg:phone":"+49 37298/93200",
    "sg:postcode":"09376",
    "sg:province":"Sachsen",
    "wof:name":"Hausverwaltung & Service Heinz Schwalbe-mothes",
    "wof:placetype":"venue"
},
  "geometry": {"coordinates":[12.707950592,50.7277030945],"type":"Point"}
}