{
  "type": "Feature",
  "properties": {
    "iso:country":"DE",
    "sg:address":"Gruitener Str. 17",
    "sg:city":"D\u00fcsseldorf",
    "sg:phone":"+49 211/7334450",
    "sg:postcode":"40233",
    "sg:province":"Nordrhein-Westfalen",
    "wof:name":"G\u00fcl-der Taxiservice Gmbh",
    "wof:placetype":"venue"
},
  "geometry": {"coordinates":[6.8133058548,51.2126617432],"type":"Point"}
}