{
  "type": "Feature",
  "properties": {
    "iso:country":"DE",
    "sg:address":"Schillingsstr. 52",
    "sg:city":"D\u00fcren",
    "sg:phone":"+49 2421/62420",
    "sg:postcode":"52355",
    "sg:province":"Nordrhein-Westfalen",
    "wof:name":"Manfred Ludwig Steuerberater",
    "wof:placetype":"venue"
},
  "geometry": {"coordinates":[6.4491930008,50.796749115],"type":"Point"}
}