{
  "type": "Feature",
  "properties": {
    "iso:country":"DE",
    "sg:address":"Ferdinand-Hofmann-Str. 68",
    "sg:city":"Frankfurt",
    "sg:phone":"+49 69/374998",
    "sg:postcode":"65931",
    "sg:province":"Hessen",
    "wof:name":"Heinz Hess",
    "wof:placetype":"venue"
},
  "geometry": {"coordinates":[8.5104465485,50.0904159546],"type":"Point"}
}