{
  "type": "Feature",
  "properties": {
    "iso:country":"DE",
    "sg:address":"Schwabenstr. 12",
    "sg:city":"Buchloe",
    "sg:phone":"+49 8241/5513",
    "sg:postcode":"86807",
    "sg:province":"Bayern",
    "wof:name":"A. Henkel",
    "wof:placetype":"venue"
},
  "geometry": {"coordinates":[10.71106,48.029259],"type":"Point"}
}