{
  "type": "Feature",
  "properties": {
    "iso:country":"DE",
    "sg:address":"Wi\u00dfstr. 41",
    "sg:city":"Gaggenau",
    "sg:phone":"+49 7225/78034",
    "sg:postcode":"76571",
    "sg:province":"Baden-W\u00fcrttemberg",
    "wof:name":"U. Castano",
    "wof:placetype":"venue"
},
  "geometry": {"coordinates":[8.3109998703,48.8041381836],"type":"Point"}
}