{
  "type": "Feature",
  "properties": {
    "iso:country":"DE",
    "sg:address":"Waldh\u00fcterstr. 34",
    "sg:city":"M\u00fcnchen",
    "sg:phone":"+49 89/706406",
    "sg:postcode":"81375",
    "sg:province":"Bayern",
    "wof:name":"K. D. Graf",
    "wof:placetype":"venue"
},
  "geometry": {"coordinates":[11.4670953751,48.1153640747],"type":"Point"}
}