{
  "type": "Feature",
  "properties": {
    "iso:country":"DE",
    "sg:address":"Bahnhofstr. 17",
    "sg:city":"Bordesholm",
    "sg:phone":"+49 4322/3885",
    "sg:postcode":"24582",
    "sg:province":"Schleswig-Holstein",
    "wof:name":"Stadtb\u00e4ckerei Gabrielsen & Schmahl Gmbh",
    "wof:placetype":"venue"
},
  "geometry": {"coordinates":[10.047797,54.174191],"type":"Point"}
}