{
  "type": "Feature",
  "properties": {
    "iso:country":"DE",
    "sg:address":"B\u00fcdericher Str. 19",
    "sg:city":"Wesel",
    "sg:phone":"+49 2803/4441",
    "sg:postcode":"46487",
    "sg:province":"Nordrhein-Westfalen",
    "wof:name":"Richard Rayermann",
    "wof:placetype":"venue"
},
  "geometry": {"coordinates":[6.543839,51.640495],"type":"Point"}
}