{
  "type": "Feature",
  "properties": {
    "iso:country":"DE",
    "sg:address":"Lange Str. 69-71",
    "sg:city":"Walsrode",
    "sg:postcode":"29664",
    "sg:province":"Niedersachsen",
    "wof:name":"Ewg Spielhallenbetriebe Gmbh",
    "wof:placetype":"venue"
},
  "geometry": {"coordinates":[9.587745,52.861073],"type":"Point"}
}