{
  "type": "Feature",
  "properties": {
    "iso:country":"DE",
    "sg:address":"Kopper Str. 39",
    "sg:city":"Birresborn",
    "sg:postcode":"54574",
    "sg:province":"Rheinland-Pfalz",
    "wof:name":"Peter Gerhardy",
    "wof:placetype":"venue"
},
  "geometry": {"coordinates":[6.6209249496,50.1758460999],"type":"Point"}
}