{
  "type": "Feature",
  "properties": {
    "iso:country":"DE",
    "sg:address":"Hauptstr. 3",
    "sg:city":"J\u00fcchen",
    "sg:phone":"+49 2164/2334",
    "sg:postcode":"41363",
    "sg:province":"Nordrhein-Westfalen",
    "wof:name":"Wilhelm Beckers",
    "wof:placetype":"venue"
},
  "geometry": {"coordinates":[6.4524,51.10611],"type":"Point"}
}