{
  "type": "Feature",
  "properties": {
    "iso:country":"DE",
    "sg:address":"Bendschenweg 9",
    "sg:city":"Neukirchen-Vluyn",
    "sg:phone":"+49 2845/794070",
    "sg:postcode":"47506",
    "sg:province":"Nordrhein-Westfalen",
    "wof:name":"J. Weber",
    "wof:placetype":"venue"
},
  "geometry": {"coordinates":[6.553369,51.437717],"type":"Point"}
}