{
  "type": "Feature",
  "properties": {
    "iso:country":"DE",
    "sg:address":"Lessingstr. 37",
    "sg:city":"Schwetzingen",
    "sg:phone":"+49 6202/4588",
    "sg:postcode":"68723",
    "sg:province":"Baden-W\u00fcrttemberg",
    "wof:name":"Roland Blaess",
    "wof:placetype":"venue"
},
  "geometry": {"coordinates":[8.583211,49.385117],"type":"Point"}
}