{
  "type": "Feature",
  "properties": {
    "iso:country":"DE",
    "sg:address":"Hoheluftstr. 8",
    "sg:city":"Oldenburg",
    "sg:postcode":"23758",
    "sg:province":"Schleswig-Holstein",
    "wof:name":"Leonhard Chodkiewicz Rechtsanwalt",
    "wof:placetype":"venue"
},
  "geometry": {"coordinates":[-85.206237793,39.3398132324],"type":"Point"}
}