{
  "type": "Feature",
  "properties": {
    "iso:country":"DE",
    "sg:address":"Schulstr. 24",
    "sg:city":"Rodgau",
    "sg:phone":"+49 6106/886743",
    "sg:postcode":"63110",
    "sg:province":"Hessen",
    "wof:name":"Zweiradsport Gmbh Radoi & Schrod",
    "wof:placetype":"venue"
},
  "geometry": {"coordinates":[8.871905,49.996216],"type":"Point"}
}