{
  "type": "Feature",
  "properties": {
    "iso:country":"DE",
    "sg:address":"L\u00fctjenweg 1",
    "sg:city":"Moormerland",
    "sg:phone":"+49 4954/2152",
    "sg:postcode":"26802",
    "sg:province":"Niedersachsen",
    "wof:name":"Hinderk Boelsen",
    "wof:placetype":"venue"
},
  "geometry": {"coordinates":[7.427897,53.306126],"type":"Point"}
}