{
  "type": "Feature",
  "properties": {
    "iso:country":"DE",
    "sg:address":"Ahornstr. 9",
    "sg:city":"Gilching",
    "sg:phone":"+49 8105/24354",
    "sg:postcode":"82205",
    "sg:province":"Bayern",
    "wof:name":"Hau Stahlhandel Gmbh",
    "wof:placetype":"venue"
},
  "geometry": {"coordinates":[11.324091,48.110558],"type":"Point"}
}