{
  "type": "Feature",
  "properties": {
    "iso:country":"DE",
    "sg:address":"Industriestr 1",
    "sg:city":"L\u00fcnen",
    "sg:phone":"+49 7081/1770",
    "sg:postcode":"44534",
    "sg:province":"Nordrhein-Westfalen",
    "wof:name":"Berthold Technologys Gmbh & Co Kg",
    "wof:placetype":"venue"
},
  "geometry": {"coordinates":[8.5524206161,48.7567176819],"type":"Point"}
}