{
  "type": "Feature",
  "properties": {
    "iso:country":"DE",
    "sg:address":"Sch\u00fcrmannstr. 39",
    "sg:city":"Essen",
    "sg:phone":"+49 4920/1256065",
    "sg:postcode":"45136",
    "sg:province":"Nordrhein-Westfalen",
    "wof:name":"Biesler Beschilderungen Gmbh",
    "wof:placetype":"venue"
},
  "geometry": {"coordinates":[7.030293,51.432945],"type":"Point"}
}