{
  "type": "Feature",
  "properties": {
    "iso:country":"DE",
    "sg:address":"Mottenstr. 6",
    "sg:city":"Oldenburg",
    "sg:phone":"+49 441/2488865",
    "sg:postcode":"26122",
    "sg:province":"Niedersachsen",
    "wof:name":"Madison",
    "wof:placetype":"venue"
},
  "geometry": {"coordinates":[8.2117319107,53.1410522461],"type":"Point"}
}