{
  "type": "Feature",
  "properties": {
    "iso:country":"DE",
    "sg:address":"Heinrich-L\u00fcbke-Str. 32",
    "sg:city":"Frankfurt",
    "sg:phone":"+49 69/763053",
    "sg:postcode":"60488",
    "sg:province":"Hessen",
    "wof:name":"Altenwohnanlage",
    "wof:placetype":"venue"
},
  "geometry": {"coordinates":[8.61099,50.141754],"type":"Point"}
}