{
  "type": "Feature",
  "properties": {
    "iso:country":"DE",
    "sg:address":"Wettinh\u00f6he 15",
    "sg:city":"Kurort Seiffen",
    "sg:phone":"+49 37362/76336",
    "sg:postcode":"09548",
    "sg:province":"Sachsen",
    "wof:name":"E.-m. Tischendorf",
    "wof:placetype":"venue"
},
  "geometry": {"coordinates":[13.438123703,50.6494522095],"type":"Point"}
}