{
  "type": "Feature",
  "properties": {
    "iso:country":"DE",
    "sg:address":"Wasserschiederstr. 46",
    "sg:city":"Birkenfeld",
    "sg:phone":"+49 6782/6326",
    "sg:postcode":"55765",
    "sg:province":"Rheinland-Pfalz",
    "wof:name":"Herbert Weirich",
    "wof:placetype":"venue"
},
  "geometry": {"coordinates":[7.1762962341,49.6522521973],"type":"Point"}
}