{
  "type": "Feature",
  "properties": {
    "iso:country":"DE",
    "sg:address":"Richard-Wagner-Str. 10",
    "sg:city":"Elsdorf",
    "sg:postcode":"50189",
    "sg:province":"Nordrhein-Westfalen",
    "wof:name":"Lutter Gmbh",
    "wof:placetype":"venue"
},
  "geometry": {"coordinates":[6.567152,50.939243],"type":"Point"}
}