{
  "type": "Feature",
  "properties": {
    "iso:country":"DE",
    "sg:address":"Gartenstr. 25",
    "sg:city":"Beilstein",
    "sg:phone":"+49 7062/3224",
    "sg:postcode":"71717",
    "sg:province":"Baden-W\u00fcrttemberg",
    "wof:name":"Pfizenmayer & S\u00f6hne",
    "wof:placetype":"venue"
},
  "geometry": {"coordinates":[9.3137626648,49.0397644043],"type":"Point"}
}