{
  "type": "Feature",
  "properties": {
    "iso:country":"DE",
    "sg:address":"Friedensallee 43",
    "sg:city":"Hamburg",
    "sg:phone":"+49 40/3984360",
    "sg:postcode":"22765",
    "sg:province":"Hamburg",
    "wof:name":"Malermeister Andree Antosch",
    "wof:placetype":"venue"
},
  "geometry": {"coordinates":[9.923192,53.555637],"type":"Point"}
}