{
  "type": "Feature",
  "properties": {
    "iso:country":"DE",
    "sg:address":"Meisenweg 7",
    "sg:city":"Lohmar",
    "sg:phone":"+49 2246/4748",
    "sg:postcode":"53797",
    "sg:province":"Nordrhein-Westfalen",
    "wof:name":"Ingenieurges. Keller Mbh",
    "wof:placetype":"venue"
},
  "geometry": {"coordinates":[7.2288770676,50.8479881287],"type":"Point"}
}