{
  "type": "Feature",
  "properties": {
    "iso:country":"DE",
    "sg:address":"800480",
    "sg:city":"Hamburg",
    "sg:postcode":"21004",
    "sg:province":"Hamburg",
    "wof:name":"Baumarkt Behr Gmbh",
    "wof:placetype":"venue"
},
  "geometry": {"coordinates":[9.9732999802,53.5498313904],"type":"Point"}
}