{
  "type": "Feature",
  "properties": {
    "iso:country":"DE",
    "sg:address":"Holzheimer Str. 13",
    "sg:city":"Langg\u00f6ns",
    "sg:phone":"+49 6403/2463",
    "sg:postcode":"35428",
    "sg:province":"Hessen",
    "wof:name":"Helmut Neubrand",
    "wof:placetype":"venue"
},
  "geometry": {"coordinates":[8.669207,50.496666],"type":"Point"}
}