{
  "type": "Feature",
  "properties": {
    "iso:country":"DE",
    "sg:address":"Fuchswinkel 8",
    "sg:city":"Mengen",
    "sg:phone":"+49 7572/8649",
    "sg:postcode":"88512",
    "sg:province":"Baden-W\u00fcrttemberg",
    "wof:name":"Josef Luib",
    "wof:placetype":"venue"
},
  "geometry": {"coordinates":[9.344433,48.069565],"type":"Point"}
}