{
  "type": "Feature",
  "properties": {
    "iso:country":"DE",
    "sg:address":"Im Bruch 16",
    "sg:city":"Weyhe",
    "sg:phone":"+49 4203/790790",
    "sg:postcode":"28844",
    "sg:province":"Niedersachsen",
    "wof:name":"Autohaus Johann Brandt Gmbh",
    "wof:placetype":"venue"
},
  "geometry": {"coordinates":[8.8433303833,52.984500885],"type":"Point"}
}