{
  "type": "Feature",
  "properties": {
    "iso:country":"DE",
    "sg:address":"Prinzenstr. 23",
    "sg:city":"Hannover",
    "sg:postcode":"30159",
    "sg:province":"Niedersachsen",
    "wof:name":"Herrenhausen Beteiligungsgesellschaft Mbh",
    "wof:placetype":"venue"
},
  "geometry": {"coordinates":[9.743895,52.371731],"type":"Point"}
}