{
  "type": "Feature",
  "properties": {
    "iso:country":"DE",
    "sg:address":"Wildbader Str. 9",
    "sg:city":"Sindelfingen",
    "sg:phone":"+49 7031/730979",
    "sg:postcode":"71069",
    "sg:province":"Baden-W\u00fcrttemberg",
    "wof:name":"Jiri Vokoun",
    "wof:placetype":"venue"
},
  "geometry": {"coordinates":[8.9603042603,48.71534729],"type":"Point"}
}