{
  "type": "Feature",
  "properties": {
    "iso:country":"DE",
    "sg:address":"Lohwasenweg 17",
    "sg:city":"Spraitbach",
    "sg:phone":"+49 7176/6505",
    "sg:postcode":"73565",
    "sg:province":"Baden-W\u00fcrttemberg",
    "wof:name":"Adelheid Lang Hebamme",
    "wof:placetype":"venue"
},
  "geometry": {"coordinates":[9.763093,48.891399],"type":"Point"}
}