{
  "type": "Feature",
  "properties": {
    "iso:country":"DE",
    "sg:address":"Weltistr. 48i",
    "sg:city":"M\u00fcnchen",
    "sg:phone":"+49 89/797409",
    "sg:postcode":"81477",
    "sg:province":"Bayern",
    "wof:name":"Hans Anthofer Architekt",
    "wof:placetype":"venue"
},
  "geometry": {"coordinates":[11.507425,48.082844],"type":"Point"}
}