{
  "type": "Feature",
  "properties": {
    "iso:country":"DE",
    "sg:address":"Bonndorfer Str. 17",
    "sg:city":"Lenzkirch",
    "sg:phone":"+49 7653/585",
    "sg:postcode":"79853",
    "sg:province":"Baden-W\u00fcrttemberg",
    "wof:name":"E. Lehmann",
    "wof:placetype":"venue"
},
  "geometry": {"coordinates":[8.2135648727,47.8648757935],"type":"Point"}
}