{
  "type": "Feature",
  "properties": {
    "iso:country":"DE",
    "sg:address":"Kirchstr. 3",
    "sg:city":"Holzheim",
    "sg:phone":"+49 7302/6212",
    "sg:postcode":"89291",
    "sg:province":"Bayern",
    "wof:name":"Xaver Schweigart",
    "wof:placetype":"venue"
},
  "geometry": {"coordinates":[10.1033,48.380989],"type":"Point"}
}