{
  "type": "Feature",
  "properties": {
    "iso:country":"DE",
    "sg:address":"Bismarckstr. 18",
    "sg:city":"Krefeld",
    "sg:phone":"+49 2151/69879",
    "sg:postcode":"47799",
    "sg:province":"Nordrhein-Westfalen",
    "wof:name":"Molenaar Lawaczeck & Co.",
    "wof:placetype":"venue"
},
  "geometry": {"coordinates":[6.5773220062,51.3387374878],"type":"Point"}
}