{
  "type": "Feature",
  "properties": {
    "iso:country":"DE",
    "sg:address":"Europaplatz 20",
    "sg:city":"Bocholt",
    "sg:postcode":"46399",
    "sg:province":"Nordrhein-Westfalen",
    "wof:name":"Stadtbus Bocholt Gmbh",
    "wof:placetype":"venue"
},
  "geometry": {"coordinates":[6.613403,51.839928],"type":"Point"}
}