{
  "type": "Feature",
  "properties": {
    "iso:country":"DE",
    "sg:address":"Dorfstr. 11",
    "sg:city":"L\u00fcbben",
    "sg:phone":"+49 3546/7394",
    "sg:postcode":"15907",
    "sg:province":"Brandenburg",
    "wof:name":"B. Stahmann",
    "wof:placetype":"venue"
},
  "geometry": {"coordinates":[13.806869,53.448658],"type":"Point"}
}