{
  "type": "Feature",
  "properties": {
    "iso:country":"DE",
    "sg:address":"Friedrichsdorfer Str. 53",
    "sg:city":"G\u00fctersloh",
    "sg:phone":"+49 5241/75080",
    "sg:postcode":"33335",
    "sg:province":"Nordrhein-Westfalen",
    "wof:name":"Restaurante Il Nurage",
    "wof:placetype":"venue"
},
  "geometry": {"coordinates":[8.4427127838,51.9389572144],"type":"Point"}
}