{
  "type": "Feature",
  "properties": {
    "iso:country":"DE",
    "sg:address":"Fraunhoferstr. 10",
    "sg:city":"M\u00fcnchen",
    "sg:phone":"+49 89/2603326",
    "sg:postcode":"80469",
    "sg:province":"Bayern",
    "wof:name":"Barbara Meister",
    "wof:placetype":"venue"
},
  "geometry": {"coordinates":[11.572243,48.130611],"type":"Point"}
}