{
  "type": "Feature",
  "properties": {
    "iso:country":"DE",
    "sg:address":"Bayreuther Str. 13",
    "sg:city":"Wuppertal",
    "sg:phone":"+49 202/301366",
    "sg:postcode":"42115",
    "sg:province":"Nordrhein-Westfalen",
    "wof:name":"H. U. F. K\u00f6cher",
    "wof:placetype":"venue"
},
  "geometry": {"coordinates":[7.1315159798,51.2619819641],"type":"Point"}
}