{
  "type": "Feature",
  "properties": {
    "iso:country":"DE",
    "sg:address":"Altenschlirfer Str. 19",
    "sg:city":"Grebenhain",
    "sg:phone":"+49 6644/7227",
    "sg:postcode":"36355",
    "sg:province":"Hessen",
    "wof:name":"Horst Fischer",
    "wof:placetype":"venue"
},
  "geometry": {"coordinates":[9.3739442825,50.5167732239],"type":"Point"}
}