{
  "type": "Feature",
  "properties": {
    "iso:country":"DE",
    "sg:address":"J\u00fclicher Str. 336-340",
    "sg:city":"Aachen",
    "sg:phone":"+49 241/165655",
    "sg:postcode":"52070",
    "sg:province":"Nordrhein-Westfalen",
    "wof:name":"Hoffmann & Westphal Handelsgesellschaft F\u00fcr",
    "wof:placetype":"venue"
},
  "geometry": {"coordinates":[6.115073,50.788441],"type":"Point"}
}