{
  "type": "Feature",
  "properties": {
    "iso:country":"DE",
    "sg:address":"Lerchenstr. 18",
    "sg:city":"Bad Endbach",
    "sg:phone":"+49 2776/7044",
    "sg:postcode":"35080",
    "sg:province":"Hessen",
    "wof:name":"Interkli Au\u00dfenhandelsges. Mbh",
    "wof:placetype":"venue"
},
  "geometry": {"coordinates":[8.5026321411,50.756690979],"type":"Point"}
}