{
  "type": "Feature",
  "properties": {
    "iso:country":"DE",
    "sg:address":"Boekholter Weg 1 c",
    "sg:city":"Straelen",
    "sg:phone":"+49 2834/414",
    "sg:postcode":"47638",
    "sg:province":"Nordrhein-Westfalen",
    "wof:name":"F. Bollen Abschleppdienst",
    "wof:placetype":"venue"
},
  "geometry": {"coordinates":[6.2697949409,51.4344940186],"type":"Point"}
}