{
  "type": "Feature",
  "properties": {
    "iso:country":"DE",
    "sg:address":"Offenbacher Landstr. 368",
    "sg:city":"Frankfurt",
    "sg:phone":"+49 4969/9652380",
    "sg:postcode":"60599",
    "sg:province":"Hessen",
    "wof:name":"Profab Gmbh",
    "wof:placetype":"venue"
},
  "geometry": {"coordinates":[8.7262220383,50.1002120972],"type":"Point"}
}