{
  "type": "Feature",
  "properties": {
    "iso:country":"DE",
    "sg:address":"Kirchweg 3",
    "sg:city":"Kessin",
    "sg:phone":"+49 38208/60290",
    "sg:postcode":"18196",
    "sg:province":"Mecklenburg-Vorpommern",
    "wof:name":"Dr. Frank Rehbock",
    "wof:placetype":"venue"
},
  "geometry": {"coordinates":[12.1759738922,54.0654754639],"type":"Point"}
}