{
  "type": "Feature",
  "properties": {
    "iso:country":"DE",
    "sg:address":"Pappritzer Str. 8",
    "sg:city":"Dresden",
    "sg:postcode":"01326",
    "sg:province":"Sachsen",
    "wof:name":"Saf Wachwitzer Verm\u00f6gens- Verwaltungs Ohg",
    "wof:placetype":"venue"
},
  "geometry": {"coordinates":[13.8466081619,51.0296821594],"type":"Point"}
}