{
  "type": "Feature",
  "properties": {
    "iso:country":"DE",
    "sg:address":"Pra\u00dfbergstr. 15",
    "sg:city":"Wangen",
    "sg:phone":"+49 7522/6633",
    "sg:postcode":"88239",
    "sg:province":"Baden-W\u00fcrttemberg",
    "wof:name":"Arnulf Sohler Verwaltungs Gmbh",
    "wof:placetype":"venue"
},
  "geometry": {"coordinates":[9.832964,47.692474],"type":"Point"}
}