{
  "type": "Feature",
  "properties": {
    "iso:country":"DE",
    "sg:address":"Industriestr. 2",
    "sg:city":"Lohne",
    "sg:phone":"+49 4944/4292680",
    "sg:postcode":"49393",
    "sg:province":"Niedersachsen",
    "wof:name":"Atka Kunststoffverarbeitung Gmbh",
    "wof:placetype":"venue"
},
  "geometry": {"coordinates":[8.19288,52.659615],"type":"Point"}
}