{
  "type": "Feature",
  "properties": {
    "iso:country":"DE",
    "sg:address":"Zittauer Str. 17",
    "sg:city":"Kurort Jonsdorf",
    "sg:phone":"+49 35844/70592",
    "sg:postcode":"02796",
    "sg:province":"Sachsen",
    "wof:name":"G\u00fcnter Noack",
    "wof:placetype":"venue"
},
  "geometry": {"coordinates":[14.7189035416,50.8611679077],"type":"Point"}
}