{
  "type": "Feature",
  "properties": {
    "iso:country":"DE",
    "sg:address":"Rathausstr. 9",
    "sg:city":"Aglasterhausen",
    "sg:phone":"+49 6262/3624",
    "sg:postcode":"74858",
    "sg:province":"Baden-W\u00fcrttemberg",
    "wof:name":"Georg Reinmuth",
    "wof:placetype":"venue"
},
  "geometry": {"coordinates":[9.005053,49.346657],"type":"Point"}
}