{
  "type": "Feature",
  "properties": {
    "iso:country":"DE",
    "sg:address":"Brauhausstr. 15",
    "sg:city":"Schwandorf",
    "sg:phone":"+49 9431/21228",
    "sg:postcode":"92421",
    "sg:province":"Bayern",
    "wof:name":"Pirnke",
    "wof:placetype":"venue"
},
  "geometry": {"coordinates":[12.106235,49.330238],"type":"Point"}
}