{
  "type": "Feature",
  "properties": {
    "iso:country":"DE",
    "sg:address":"Hans- B\u00f6ckler- Weg 18",
    "sg:city":"Hildesheim",
    "sg:phone":"+49 5555/5555",
    "sg:postcode":"31141",
    "sg:province":"Niedersachsen",
    "wof:name":"Krankewebseiten",
    "wof:placetype":"venue"
},
  "geometry": {"coordinates":[9.993253,52.12981],"type":"Point"}
}