{
  "type": "Feature",
  "properties": {
    "iso:country":"DE",
    "sg:address":"Hauptstr. 28",
    "sg:city":"Offenburg",
    "sg:phone":"+49 781/24891",
    "sg:postcode":"77652",
    "sg:province":"Baden-W\u00fcrttemberg",
    "wof:name":"Badenia",
    "wof:placetype":"venue"
},
  "geometry": {"coordinates":[7.9453468323,48.4764289856],"type":"Point"}
}