{
  "type": "Feature",
  "properties": {
    "iso:country":"DE",
    "sg:address":"Kirchberg 3",
    "sg:city":"Wolfegg",
    "sg:phone":"+49 7527/4157",
    "sg:postcode":"88364",
    "sg:province":"Baden-W\u00fcrttemberg",
    "wof:name":"Pension Alfred J\u00e4ger",
    "wof:placetype":"venue"
},
  "geometry": {"coordinates":[9.7910909653,47.8375816345],"type":"Point"}
}