{
  "type": "Feature",
  "properties": {
    "iso:country":"DE",
    "sg:address":"Brielower Landstr. 19",
    "sg:city":"Brandenburg",
    "sg:phone":"+49 3381/75860",
    "sg:postcode":"14772",
    "sg:province":"Brandenburg",
    "wof:name":"Beetzsee-center",
    "wof:placetype":"venue"
},
  "geometry": {"coordinates":[12.554234,52.429482],"type":"Point"}
}