{
  "type": "Feature",
  "properties": {
    "iso:country":"DE",
    "sg:address":"Bakumer Str 73",
    "sg:city":"Lohne",
    "sg:phone":"+49 4442/982395",
    "sg:postcode":"49393",
    "sg:province":"Niedersachsen",
    "wof:name":"Famac",
    "wof:placetype":"venue"
},
  "geometry": {"coordinates":[8.2262706757,52.6756439209],"type":"Point"}
}