{
  "type": "Feature",
  "properties": {
    "iso:country":"DE",
    "sg:address":"Kirchstr. 18",
    "sg:city":"Schwarzenbach a Wald",
    "sg:phone":"+49 9289/356",
    "sg:postcode":"95131",
    "sg:province":"Bayern",
    "wof:name":"Schuh - Rudi Ortlam",
    "wof:placetype":"venue"
},
  "geometry": {"coordinates":[11.624666214,50.2843589783],"type":"Point"}
}