{
  "type": "Feature",
  "properties": {
    "iso:country":"DE",
    "sg:address":"Herzbachweg 6",
    "sg:city":"Gelnhausen",
    "sg:phone":"+49 6051/17966",
    "sg:postcode":"63571",
    "sg:province":"Hessen",
    "wof:name":"Jacubowsky & Compagnie Gmbh",
    "wof:placetype":"venue"
},
  "geometry": {"coordinates":[9.1833963394,50.2052307129],"type":"Point"}
}