{
  "type": "Feature",
  "properties": {
    "iso:country":"DE",
    "sg:address":"Eichenweg 5",
    "sg:city":"Hallenberg",
    "sg:phone":"+49 2984/8208",
    "sg:postcode":"59969",
    "sg:province":"Nordrhein-Westfalen",
    "wof:name":"Pension E. Heinzel",
    "wof:placetype":"venue"
},
  "geometry": {"coordinates":[8.625702858,51.1126365662],"type":"Point"}
}