{
  "type": "Feature",
  "properties": {
    "iso:country":"DE",
    "sg:address":"Bgm-Schlickenried-Str 20",
    "sg:city":"Friedberg",
    "sg:phone":"+49 821/784021",
    "sg:postcode":"86316",
    "sg:province":"Bayern",
    "wof:name":"Hotel-g\u00e4stehaus Kastl Garni",
    "wof:placetype":"venue"
},
  "geometry": {"coordinates":[10.9783449173,48.3550720215],"type":"Point"}
}