{
  "type": "Feature",
  "properties": {
    "iso:country":"DE",
    "sg:address":"Sieversdorf 31",
    "sg:city":"Malente",
    "sg:phone":"+49 4523/1728",
    "sg:postcode":"23714",
    "sg:province":"Schleswig-Holstein",
    "wof:name":"Gastst\u00e4tte Gerd Koch",
    "wof:placetype":"venue"
},
  "geometry": {"coordinates":[10.5542879105,54.1701507568],"type":"Point"}
}