{
  "type": "Feature",
  "properties": {
    "iso:country":"DE",
    "sg:address":"Okatreute 1",
    "sg:city":"Ravensburg",
    "sg:postcode":"88213",
    "sg:province":"Baden-W\u00fcrttemberg",
    "wof:name":"Hugo Adler Gmbh",
    "wof:placetype":"venue"
},
  "geometry": {"coordinates":[9.5503454208,47.7977867126],"type":"Point"}
}