{
  "type": "Feature",
  "properties": {
    "iso:country":"DE",
    "sg:address":"Ahle 121",
    "sg:city":"Heek",
    "sg:phone":"+49 2568/660",
    "sg:postcode":"48619",
    "sg:province":"Nordrhein-Westfalen",
    "wof:name":"Holzbau Bockhold Gmbh",
    "wof:placetype":"venue"
},
  "geometry": {"coordinates":[7.0625839233,52.1019134521],"type":"Point"}
}