{
  "type": "Feature",
  "properties": {
    "iso:country":"DE",
    "sg:address":"Dresdner Str. 302",
    "sg:city":"Freital",
    "sg:phone":"+49 351/6495121",
    "sg:postcode":"01705",
    "sg:province":"Sachsen",
    "wof:name":"Peter Kaube",
    "wof:placetype":"venue"
},
  "geometry": {"coordinates":[13.63615,50.985691],"type":"Point"}
}