{
  "type": "Feature",
  "properties": {
    "iso:country":"DE",
    "sg:address":"Seestr. 22",
    "sg:city":"Stockach",
    "sg:phone":"+49 7771/2906",
    "sg:postcode":"78333",
    "sg:province":"Baden-W\u00fcrttemberg",
    "wof:name":"Johannes Kuppel",
    "wof:placetype":"venue"
},
  "geometry": {"coordinates":[9.0175123215,47.8184585571],"type":"Point"}
}