{
  "type": "Feature",
  "properties": {
    "iso:country":"DE",
    "sg:address":"Kirchheimer Str. 106",
    "sg:city":"Wernau",
    "sg:postcode":"73249",
    "sg:province":"Baden-W\u00fcrttemberg",
    "wof:name":"Ski Und Tennis Zink Inh. Heike Buntz",
    "wof:placetype":"venue"
},
  "geometry": {"coordinates":[9.422172,48.689182],"type":"Point"}
}