{
  "type": "Feature",
  "properties": {
    "iso:country":"DE",
    "sg:address":"Philippsthaler Str. 12",
    "sg:city":"Unterbreizbach",
    "sg:phone":"+49 36962/24725",
    "sg:postcode":"36414",
    "sg:province":"Th\u00fcringen",
    "wof:name":"Sell & Hohmann Gmbh",
    "wof:placetype":"venue"
},
  "geometry": {"coordinates":[9.979363,50.819973],"type":"Point"}
}