{
  "type": "Feature",
  "properties": {
    "iso:country":"DE",
    "sg:address":"Gest\u00fctsallee 5",
    "sg:city":"Zweibr\u00fccken",
    "sg:phone":"+49 6332/75538",
    "sg:postcode":"66482",
    "sg:province":"Rheinland-Pfalz",
    "wof:name":"Reiterklause",
    "wof:placetype":"venue"
},
  "geometry": {"coordinates":[7.366065979,49.2514381409],"type":"Point"}
}