{
  "type": "Feature",
  "properties": {
    "iso:country":"DE",
    "sg:address":"Bahnhofstr. 51",
    "sg:city":"M\u00fchlacker",
    "sg:phone":"+49 7041/6701",
    "sg:postcode":"75417",
    "sg:province":"Baden-W\u00fcrttemberg",
    "wof:name":"L. Neu",
    "wof:placetype":"venue"
},
  "geometry": {"coordinates":[8.840768,48.94997],"type":"Point"}
}