{
  "type": "Feature",
  "properties": {
    "iso:country":"DE",
    "sg:address":"Alter Hof 1",
    "sg:city":"R\u00fcmmelsheim",
    "sg:phone":"+49 6721/46564",
    "sg:postcode":"55452",
    "sg:province":"Rheinland-Pfalz",
    "wof:name":"Christel Te\u00dfmer-wrege",
    "wof:placetype":"venue"
},
  "geometry": {"coordinates":[7.8609490395,49.9335708618],"type":"Point"}
}