{
  "type": "Feature",
  "properties": {
    "iso:country":"DE",
    "sg:address":"Adelsbergstr 11b",
    "sg:city":"M\u00fcnchen",
    "sg:phone":"+49 89/89198748",
    "sg:postcode":"81247",
    "sg:province":"Bayern",
    "wof:name":"Dr. Paul Conlon Transjuris Ek",
    "wof:placetype":"venue"
},
  "geometry": {"coordinates":[11.4773397446,48.1715316772],"type":"Point"}
}