{
  "type": "Feature",
  "properties": {
    "iso:country":"DE",
    "sg:address":"Rudolf-Diesel-Str. 2a",
    "sg:city":"Koblenz",
    "sg:postcode":"56070",
    "sg:province":"Rheinland-Pfalz",
    "wof:name":"Global Medical Service Ag",
    "wof:placetype":"venue"
},
  "geometry": {"coordinates":[7.598347,50.389225],"type":"Point"}
}