{
  "type": "Feature",
  "properties": {
    "iso:country":"DE",
    "sg:address":"H\u00f6henberg 1",
    "sg:city":"Dormagen",
    "sg:phone":"+49 2133/477358",
    "sg:postcode":"41539",
    "sg:province":"Nordrhein-Westfalen",
    "wof:name":"Pink Panther",
    "wof:placetype":"venue"
},
  "geometry": {"coordinates":[6.8448801041,51.0896873474],"type":"Point"}
}