{
  "type": "Feature",
  "properties": {
    "iso:country":"DE",
    "sg:address":"Culitzscher Str. 4",
    "sg:city":"Wilkau-Ha\u00dflau",
    "sg:phone":"+49 375/61449",
    "sg:postcode":"08112",
    "sg:province":"Sachsen",
    "wof:name":"Stefan K\u00f6lbel",
    "wof:placetype":"venue"
},
  "geometry": {"coordinates":[12.509084,50.67487],"type":"Point"}
}