{
  "type": "Feature",
  "properties": {
    "iso:country":"DE",
    "sg:address":"Karl-Stieler-Weg 4",
    "sg:city":"Lenggries",
    "sg:phone":"+49 8042/8493",
    "sg:postcode":"83661",
    "sg:province":"Bayern",
    "wof:name":"Willy Huber Ingenieur",
    "wof:placetype":"venue"
},
  "geometry": {"coordinates":[11.5840835571,47.6777496338],"type":"Point"}
}