{
  "type": "Feature",
  "properties": {
    "iso:country":"DE",
    "sg:address":"Bleicherstr. 3",
    "sg:city":"Hildesheim",
    "sg:phone":"+49 5121/42655",
    "sg:postcode":"31137",
    "sg:province":"Niedersachsen",
    "wof:name":"Georg Hipler",
    "wof:placetype":"venue"
},
  "geometry": {"coordinates":[9.9382972717,52.1523933411],"type":"Point"}
}