{
  "type": "Feature",
  "properties": {
    "iso:country":"DE",
    "sg:address":"Am Sandberg 40",
    "sg:city":"Frankfurt",
    "sg:phone":"+49 69/682944",
    "sg:postcode":"60599",
    "sg:province":"Hessen",
    "wof:name":"Klaus H. Arnold",
    "wof:placetype":"venue"
},
  "geometry": {"coordinates":[8.698554039,50.0930252075],"type":"Point"}
}