{
  "type": "Feature",
  "properties": {
    "iso:country":"DE",
    "sg:address":"Heeper Str. 2",
    "sg:city":"Bad Salzuflen",
    "sg:phone":"+49 5208/7415",
    "sg:postcode":"32107",
    "sg:province":"Nordrhein-Westfalen",
    "wof:name":"Kusenbaum",
    "wof:placetype":"venue"
},
  "geometry": {"coordinates":[8.6614093781,52.0451698303],"type":"Point"}
}