{
  "type": "Feature",
  "properties": {
    "iso:country":"DE",
    "sg:address":"Wiesenweg 4",
    "sg:city":"Kodersdorf",
    "sg:phone":"+49 35825/5345",
    "sg:postcode":"02923",
    "sg:province":"Sachsen",
    "wof:name":"Sonja Seifert",
    "wof:placetype":"venue"
},
  "geometry": {"coordinates":[14.897506,51.226841],"type":"Point"}
}