{
  "type": "Feature",
  "properties": {
    "iso:country":"DE",
    "sg:address":"Am M\u00fchlh\u00e4user Weg 4",
    "sg:city":"Rodeberg",
    "sg:phone":"+49 36026/9530",
    "sg:postcode":"99976",
    "sg:province":"Th\u00fcringen",
    "wof:name":"S & T Hochbau Gmbh",
    "wof:placetype":"venue"
},
  "geometry": {"coordinates":[10.310313,51.217075],"type":"Point"}
}