{
  "type": "Feature",
  "properties": {
    "iso:country":"DE",
    "sg:address":"Amtsstr. 4",
    "sg:city":"Bochum",
    "sg:phone":"+49 234/524330",
    "sg:postcode":"44809",
    "sg:province":"Nordrhein-Westfalen",
    "wof:name":"Ev. Pfarramt Hamme",
    "wof:placetype":"venue"
},
  "geometry": {"coordinates":[7.1966881752,51.4914855957],"type":"Point"}
}