{
  "type": "Feature",
  "properties": {
    "iso:country":"DE",
    "sg:address":"Zum Gutswald 18",
    "sg:city":"Essen",
    "sg:phone":"+49 201/510287",
    "sg:postcode":"45307",
    "sg:province":"Nordrhein-Westfalen",
    "wof:name":"Albert Hohmann",
    "wof:placetype":"venue"
},
  "geometry": {"coordinates":[7.0704340935,51.4529457092],"type":"Point"}
}