{
  "type": "Feature",
  "properties": {
    "iso:country":"DE",
    "sg:address":"Im Amtmann 16a",
    "sg:city":"Wetzlar",
    "sg:phone":"+49 4964/4197700",
    "sg:postcode":"35578",
    "sg:province":"Hessen",
    "wof:name":"Sporleder Gmbh",
    "wof:placetype":"venue"
},
  "geometry": {"coordinates":[8.5293083191,50.5472793579],"type":"Point"}
}