{
  "type": "Feature",
  "properties": {
    "iso:country":"DE",
    "sg:address":"Lortzingstr. 5",
    "sg:city":"Hannover",
    "sg:phone":"+49 511/3940680",
    "sg:postcode":"30177",
    "sg:province":"Niedersachsen",
    "wof:name":"Spiegel",
    "wof:placetype":"venue"
},
  "geometry": {"coordinates":[9.758977,52.392532],"type":"Point"}
}