{
  "type": "Feature",
  "properties": {
    "iso:country":"DE",
    "sg:address":"Kirchsiek 4",
    "sg:city":"Porta Westfalica",
    "sg:phone":"+49 571/76889",
    "sg:postcode":"32457",
    "sg:province":"Nordrhein-Westfalen",
    "wof:name":"Manfred Schulten",
    "wof:placetype":"venue"
},
  "geometry": {"coordinates":[8.9231271744,52.2393417358],"type":"Point"}
}