{
  "type": "Feature",
  "properties": {
    "iso:country":"DE",
    "sg:address":"Am Heidelbach 25",
    "sg:city":"Langenreichenbach",
    "sg:phone":"+49 34221/50424",
    "sg:postcode":"04889",
    "sg:province":"Sachsen",
    "wof:name":"Agrargenossenschaft Langenreichenbach E.g.",
    "wof:placetype":"venue"
},
  "geometry": {"coordinates":[12.905612,51.479118],"type":"Point"}
}