{
  "type": "Feature",
  "properties": {
    "iso:country":"DE",
    "sg:address":"Rohrauerstr. 40",
    "sg:city":"M\u00fcnchen",
    "sg:postcode":"81477",
    "sg:province":"Bayern",
    "wof:name":"Volker Herbst",
    "wof:placetype":"venue"
},
  "geometry": {"coordinates":[11.511026,48.091694],"type":"Point"}
}