{
  "type": "Feature",
  "properties": {
    "iso:country":"DE",
    "sg:address":"Alt Sossenheim 8",
    "sg:city":"Frankfurt",
    "sg:phone":"+49 69/345941",
    "sg:postcode":"65936",
    "sg:province":"Hessen",
    "wof:name":"H. Bernhard Augenoptiker",
    "wof:placetype":"venue"
},
  "geometry": {"coordinates":[8.5682668686,50.1222648621],"type":"Point"}
}