{
  "type": "Feature",
  "properties": {
    "iso:country":"DE",
    "sg:address":"Dorfstrasse 9",
    "sg:city":"Goldbeck",
    "sg:phone":"+49 4673",
    "sg:postcode":"25862",
    "sg:province":"Schleswig-Holstein",
    "wof:name":"Kinder- Und Jugendbuchversand B\u00fcchermaus",
    "wof:placetype":"venue"
},
  "geometry": {"coordinates":[-81.03285980219999,38.1086196899],"type":"Point"}
}