{
  "type": "Feature",
  "properties": {
    "iso:country":"DE",
    "sg:address":"Richard-Wagner-Str. 5",
    "sg:city":"Ha\u00dfloch",
    "sg:phone":"+49 6324/3449",
    "sg:postcode":"67454",
    "sg:province":"Rheinland-Pfalz",
    "wof:name":"Karl Babelotzky",
    "wof:placetype":"venue"
},
  "geometry": {"coordinates":[8.247316,49.364048],"type":"Point"}
}