{
  "type": "Feature",
  "properties": {
    "iso:country":"DE",
    "sg:address":"Schwarzer Weg 21",
    "sg:city":"Pantelitz",
    "sg:phone":"+49 38321/60441",
    "sg:postcode":"18442",
    "sg:province":"Mecklenburg-Vorpommern",
    "wof:name":"Ludwig Wenzel",
    "wof:placetype":"venue"
},
  "geometry": {"coordinates":[12.9713697433,54.3011283875],"type":"Point"}
}