{
  "type": "Feature",
  "properties": {
    "iso:country":"DE",
    "sg:address":"Marktplatz 24",
    "sg:city":"Berchtesgaden",
    "sg:phone":"+49 8652/66090",
    "sg:postcode":"83471",
    "sg:province":"Bayern",
    "wof:name":"Manfred K\u00fchnhauser Steuerberater",
    "wof:placetype":"venue"
},
  "geometry": {"coordinates":[13.0003452301,47.6324234009],"type":"Point"}
}