{
  "type": "Feature",
  "properties": {
    "iso:country":"DE",
    "sg:address":"Ringstr. 1",
    "sg:city":"Wolfhagen",
    "sg:phone":"+49 5692/6800",
    "sg:postcode":"34466",
    "sg:province":"Hessen",
    "wof:name":"Unser Laden",
    "wof:placetype":"venue"
},
  "geometry": {"coordinates":[9.2311811447,51.3405914307],"type":"Point"}
}