{
  "type": "Feature",
  "properties": {
    "iso:country":"DE",
    "sg:address":"Heimdallstr. 4",
    "sg:city":"M\u00fcnchen",
    "sg:phone":"+49 89/60600687",
    "sg:postcode":"81739",
    "sg:province":"Bayern",
    "wof:name":"Syntesome-gesellschaft F\u00fcr Medizinische Biochemie Mbh",
    "wof:placetype":"venue"
},
  "geometry": {"coordinates":[11.6808023453,48.0837059021],"type":"Point"}
}