{
  "type": "Feature",
  "properties": {
    "iso:country":"DE",
    "sg:address":"Goethestr. 59",
    "sg:city":"Gladbeck",
    "sg:phone":"+49 2043/22777",
    "sg:postcode":"45964",
    "sg:province":"Nordrhein-Westfalen",
    "wof:name":"Foto Ullrich Gmbh",
    "wof:placetype":"venue"
},
  "geometry": {"coordinates":[6.9915719032,51.572971344],"type":"Point"}
}