{
  "type": "Feature",
  "properties": {
    "iso:country":"DE",
    "sg:address":"Zum Springbruch 1",
    "sg:city":"Bergholz-Rehbr\u00fccke",
    "sg:phone":"+49 33200/82888",
    "sg:postcode":"14558",
    "sg:province":"Brandenburg",
    "wof:name":"237 Oxhoft",
    "wof:placetype":"venue"
},
  "geometry": {"coordinates":[13.1015806198,52.3493614197],"type":"Point"}
}