{
  "type": "Feature",
  "properties": {
    "iso:country":"DE",
    "sg:address":"Am Gewerbepark 12",
    "sg:city":"Bruchm\u00fchle",
    "sg:phone":"+49 33439/8932",
    "sg:postcode":"15370",
    "sg:province":"Brandenburg",
    "wof:name":"Gms Ger\u00e4te- Und Mietservice Gmbh",
    "wof:placetype":"venue"
},
  "geometry": {"coordinates":[13.7471065521,52.5422897339],"type":"Point"}
}