{
  "type": "Feature",
  "properties": {
    "iso:country":"DE",
    "sg:address":"Niederb\u00f6rry 16",
    "sg:city":"Emmerthal",
    "sg:phone":"+49 5157/209",
    "sg:postcode":"31860",
    "sg:province":"Niedersachsen",
    "wof:name":"Museum F\u00fcr Landtechnik Und Landarbeit",
    "wof:placetype":"venue"
},
  "geometry": {"coordinates":[9.457679,52.029812],"type":"Point"}
}