{
  "type": "Feature",
  "properties": {
    "iso:country":"DE",
    "sg:address":"Heinrichstr. 4",
    "sg:city":"B\u00fcrstadt",
    "sg:phone":"+49 6206/6630",
    "sg:postcode":"68642",
    "sg:province":"Hessen",
    "wof:name":"Margot Mathias-behrendt Heilpraktikerin",
    "wof:placetype":"venue"
},
  "geometry": {"coordinates":[8.4572963715,49.6417198181],"type":"Point"}
}