{
  "type": "Feature",
  "properties": {
    "iso:country":"DE",
    "sg:address":"Lauterbacher Str. 8",
    "sg:city":"Gedern",
    "sg:phone":"+49 6045/2080",
    "sg:postcode":"63688",
    "sg:province":"Hessen",
    "wof:name":"Apotheke Zur Alten Post",
    "wof:placetype":"venue"
},
  "geometry": {"coordinates":[9.198223,50.424076],"type":"Point"}
}