{
  "type": "Feature",
  "properties": {
    "iso:country":"DE",
    "sg:address":"Pilsener Str. 10",
    "sg:city":"Waidhaus",
    "sg:phone":"+49 9652/238",
    "sg:postcode":"92726",
    "sg:province":"Bayern",
    "wof:name":"Lina Hilpert",
    "wof:placetype":"venue"
},
  "geometry": {"coordinates":[12.5002412796,49.642250061],"type":"Point"}
}