{
  "type": "Feature",
  "properties": {
    "iso:country":"DE",
    "sg:address":"Lindenweg 3",
    "sg:city":"Saarbr\u00fccken",
    "sg:phone":"+49 681/989010",
    "sg:postcode":"66132",
    "sg:province":"Saarland",
    "wof:name":"Seniorenheim Haus Berghof",
    "wof:placetype":"venue"
},
  "geometry": {"coordinates":[7.072927,49.220554],"type":"Point"}
}