{
  "type": "Feature",
  "properties": {
    "iso:country":"DE",
    "sg:address":"Dr.-Sieglitz-Str. 17",
    "sg:city":"Bingen",
    "sg:phone":"+49 6721/17157",
    "sg:postcode":"55411",
    "sg:province":"Rheinland-Pfalz",
    "wof:name":"Karl-heinz Wenglein Elektroinstallation",
    "wof:placetype":"venue"
},
  "geometry": {"coordinates":[7.895523,49.963089],"type":"Point"}
}