{
  "type": "Feature",
  "properties": {
    "iso:country":"DE",
    "sg:address":"Steinkopfstr. 20",
    "sg:city":"Friedberg",
    "sg:phone":"+49 6031/2732",
    "sg:postcode":"61169",
    "sg:province":"Hessen",
    "wof:name":"Rudolf Zimmermann Architekt",
    "wof:placetype":"venue"
},
  "geometry": {"coordinates":[8.742764,50.33157],"type":"Point"}
}