{
  "type": "Feature",
  "properties": {
    "iso:country":"DE",
    "sg:address":"Enggasse 3",
    "sg:city":"Gotha",
    "sg:phone":"+49 3621/702622",
    "sg:postcode":"99867",
    "sg:province":"Th\u00fcringen",
    "wof:name":"G. Kaltenborn",
    "wof:placetype":"venue"
},
  "geometry": {"coordinates":[10.6718835831,50.9302101135],"type":"Point"}
}