{
  "type": "Feature",
  "properties": {
    "iso:country":"DE",
    "sg:address":"Hamburger Allee 14",
    "sg:city":"Frankfurt",
    "sg:postcode":"60486",
    "sg:province":"Hessen",
    "wof:name":"Gdw Revision Ag",
    "wof:placetype":"venue"
},
  "geometry": {"coordinates":[8.6491146088,50.1148147583],"type":"Point"}
}