{
  "type": "Feature",
  "properties": {
    "iso:country":"DE",
    "sg:address":"Langer Weg 9b",
    "sg:city":"Lobenstein",
    "sg:phone":"+49 36651/2450",
    "sg:postcode":"07356",
    "sg:province":"Th\u00fcringen",
    "wof:name":"Raiffeisen Und Warengenossenschaft Eg",
    "wof:placetype":"venue"
},
  "geometry": {"coordinates":[11.650555,50.450199],"type":"Point"}
}