{
  "type": "Feature",
  "properties": {
    "iso:country":"DE",
    "sg:address":"B\u00fcndtenfeldstr. 8",
    "sg:city":"Wehr",
    "sg:phone":"+49 7762/7850",
    "sg:postcode":"79664",
    "sg:province":"Baden-W\u00fcrttemberg",
    "wof:name":"W. Meier",
    "wof:placetype":"venue"
},
  "geometry": {"coordinates":[7.9028549194,47.6225967407],"type":"Point"}
}