{
  "type": "Feature",
  "properties": {
    "iso:country":"DE",
    "sg:address":"Werftweg 13",
    "sg:city":"Neckarsteinach",
    "sg:phone":"+49 6229/527",
    "sg:postcode":"69239",
    "sg:province":"Hessen",
    "wof:name":"J. C. \u00d6stereicher Binnenschiffahrt",
    "wof:placetype":"venue"
},
  "geometry": {"coordinates":[8.83936,49.406174],"type":"Point"}
}