{
  "type": "Feature",
  "properties": {
    "iso:country":"DE",
    "sg:address":"Hauptstr. 34",
    "sg:city":"Kraichtal",
    "sg:phone":"+49 7258/293",
    "sg:postcode":"76703",
    "sg:province":"Baden-W\u00fcrttemberg",
    "wof:name":"W. Mannherz",
    "wof:placetype":"venue"
},
  "geometry": {"coordinates":[8.7495832443,49.1038360596],"type":"Point"}
}