{
  "type": "Feature",
  "properties": {
    "iso:country":"DE",
    "sg:address":"Ferdinand-von-Schill-Str. 4",
    "sg:city":"Possendorf",
    "sg:phone":"+49 35206/22609",
    "sg:postcode":"01728",
    "sg:province":"Sachsen",
    "wof:name":"Golfrestaurant Schillstube",
    "wof:placetype":"venue"
},
  "geometry": {"coordinates":[13.707159996,50.9699134827],"type":"Point"}
}