{
  "type": "Feature",
  "properties": {
    "iso:country":"DE",
    "sg:address":"Hofmattenweg 18",
    "sg:city":"Ehrenkirchen",
    "sg:phone":"+49 7633/5703",
    "sg:postcode":"79238",
    "sg:province":"Baden-W\u00fcrttemberg",
    "wof:name":"Udo Schulte",
    "wof:placetype":"venue"
},
  "geometry": {"coordinates":[7.740876,47.92308],"type":"Point"}
}