{
  "type": "Feature",
  "properties": {
    "iso:country":"DE",
    "sg:address":"Richard-Wagner-Str. 50",
    "sg:city":"Bremen",
    "sg:phone":"+49 421/3477540",
    "sg:postcode":"28209",
    "sg:province":"Bremen",
    "wof:name":"Medya-schneiderei",
    "wof:placetype":"venue"
},
  "geometry": {"coordinates":[8.8274717331,53.0826759338],"type":"Point"}
}