{
  "type": "Feature",
  "properties": {
    "iso:country":"DE",
    "sg:address":"Kamenzer Str. 10",
    "sg:city":"Bischofswerda",
    "sg:phone":"+49 3594/703225",
    "sg:postcode":"01877",
    "sg:province":"Sachsen",
    "wof:name":"Rudi Kl\u00fcnder",
    "wof:placetype":"venue"
},
  "geometry": {"coordinates":[14.1791095734,51.1285171509],"type":"Point"}
}