{
  "type": "Feature",
  "properties": {
    "iso:country":"DE",
    "sg:address":"Schulstr. 2",
    "sg:city":"Zwochau",
    "sg:postcode":"04509",
    "sg:province":"Sachsen",
    "wof:name":"Ev. Pfarramt Zwochau",
    "wof:placetype":"venue"
},
  "geometry": {"coordinates":[12.2694244385,51.4652481079],"type":"Point"}
}