{
  "type": "Feature",
  "properties": {
    "iso:country":"DE",
    "sg:address":"Auf dem Beerenkamp 2",
    "sg:city":"Dorsten",
    "sg:phone":"+49 2362/99020",
    "sg:postcode":"46282",
    "sg:province":"Nordrhein-Westfalen",
    "wof:name":"Dr. Kohl Gmbh",
    "wof:placetype":"venue"
},
  "geometry": {"coordinates":[6.956507206,51.6460151672],"type":"Point"}
}