{
  "type": "Feature",
  "properties": {
    "iso:country":"DE",
    "sg:address":"Wetzlarer Str. 43",
    "sg:city":"Sch\u00f6ffengrund",
    "sg:phone":"+49 6445/256",
    "sg:postcode":"35641",
    "sg:province":"Hessen",
    "wof:name":"Karl Lauber Ingenieur",
    "wof:placetype":"venue"
},
  "geometry": {"coordinates":[8.497879982,50.4865188599],"type":"Point"}
}