{
  "type": "Feature",
  "properties": {
    "iso:country":"DE",
    "sg:address":"Am Bahnhof 1",
    "sg:city":"Wittenhagen",
    "sg:postcode":"18510",
    "sg:province":"Mecklenburg-Vorpommern",
    "wof:name":"Neues Holz Contor Gmbh",
    "wof:placetype":"venue"
},
  "geometry": {"coordinates":[13.0771493912,54.1843795776],"type":"Point"}
}