{
  "type": "Feature",
  "properties": {
    "iso:country":"DE",
    "sg:address":"Kalchenstr. 6",
    "sg:city":"Tettnang",
    "sg:postcode":"88069",
    "sg:province":"Baden-W\u00fcrttemberg",
    "wof:name":"Erich Schmidt",
    "wof:placetype":"venue"
},
  "geometry": {"coordinates":[9.5885229111,47.6748008728],"type":"Point"}
}