{
  "type": "Feature",
  "properties": {
    "iso:country":"DE",
    "sg:address":"Geraer Ring 6",
    "sg:city":"Mannheim",
    "sg:phone":"+49 621/712290",
    "sg:postcode":"68309",
    "sg:province":"Baden-W\u00fcrttemberg",
    "wof:name":"Gebr\u00fcder Zorn Ohg",
    "wof:placetype":"venue"
},
  "geometry": {"coordinates":[8.538356781,49.5110435486],"type":"Point"}
}