{
  "type": "Feature",
  "properties": {
    "iso:country":"DE",
    "sg:address":"Ossecker Str. 33",
    "sg:city":"Hof",
    "sg:phone":"+49 9281/93344",
    "sg:postcode":"95030",
    "sg:province":"Bayern",
    "wof:name":"H. K\u00e4kenmeister Kg Autolackiererei",
    "wof:placetype":"venue"
},
  "geometry": {"coordinates":[11.904093,50.311516],"type":"Point"}
}