{
  "type": "Feature",
  "properties": {
    "iso:country":"DE",
    "sg:address":"Eichenstr. 38",
    "sg:city":"Walsrode",
    "sg:postcode":"29664",
    "sg:province":"Niedersachsen",
    "wof:name":"Kr\u00fcger-kr\u00e4uterversand",
    "wof:placetype":"venue"
},
  "geometry": {"coordinates":[9.5829544067,52.8519248962],"type":"Point"}
}