{
  "type": "Feature",
  "properties": {
    "iso:country":"DE",
    "sg:address":"Johann-Philipp-Reis-Str. 6",
    "sg:city":"Simmern",
    "sg:phone":"+49 6761/94140",
    "sg:postcode":"55469",
    "sg:province":"Rheinland-Pfalz",
    "wof:name":"Live Gmbh & Co. Kg",
    "wof:placetype":"venue"
},
  "geometry": {"coordinates":[7.479887,49.974373],"type":"Point"}
}