{
  "type": "Feature",
  "properties": {
    "iso:country":"DE",
    "sg:address":"Ermelinghofstr. 37",
    "sg:city":"Hamm",
    "sg:phone":"+49 2381/780200",
    "sg:postcode":"59075",
    "sg:province":"Nordrhein-Westfalen",
    "wof:name":"Deutsches Haus",
    "wof:placetype":"venue"
},
  "geometry": {"coordinates":[7.7685551643,51.7022171021],"type":"Point"}
}