{
  "type": "Feature",
  "properties": {
    "iso:country":"DE",
    "sg:address":"Redinghovenstr. 9",
    "sg:city":"D\u00fcsseldorf",
    "sg:postcode":"40225",
    "sg:province":"Nordrhein-Westfalen",
    "wof:name":"D\u00fcsseldorfer Verein F\u00fcr Berufsp\u00e4dagogik E. V.",
    "wof:placetype":"venue"
},
  "geometry": {"coordinates":[6.7889838219,51.2055587769],"type":"Point"}
}