{
  "type": "Feature",
  "properties": {
    "iso:country":"DE",
    "sg:address":"Rosenstr. 15",
    "sg:city":"Gr\u00f6mitz",
    "sg:phone":"+49 4562/6677",
    "sg:postcode":"23743",
    "sg:province":"Schleswig-Holstein",
    "wof:name":"G\u00e4stehaus Haus Rosenstra\u00dfe",
    "wof:placetype":"venue"
},
  "geometry": {"coordinates":[10.9510011673,54.143535614],"type":"Point"}
}