{
  "type": "Feature",
  "properties": {
    "iso:country":"DE",
    "sg:address":"Steinstr. 28",
    "sg:city":"Kaiserslautern",
    "sg:phone":"+49 631/3628521",
    "sg:postcode":"67657",
    "sg:province":"Rheinland-Pfalz",
    "wof:name":"Hans-bernhard Raab Innenarchitekt",
    "wof:placetype":"venue"
},
  "geometry": {"coordinates":[7.77356,49.446709],"type":"Point"}
}