{
  "type": "Feature",
  "properties": {
    "iso:country":"DE",
    "sg:address":"Ziegelstr. 3",
    "sg:city":"Stralsund",
    "sg:phone":"+49 3831/298980",
    "sg:postcode":"18439",
    "sg:province":"Mecklenburg-Vorpommern",
    "wof:name":"Geo Ingenieurservice Beraten Planen Vermessen",
    "wof:placetype":"venue"
},
  "geometry": {"coordinates":[13.1056222916,54.307144165],"type":"Point"}
}