{
  "type": "Feature",
  "properties": {
    "iso:country":"DE",
    "sg:address":"Am Markt 1",
    "sg:city":"Schneverdingen",
    "sg:phone":"+49 5193/52538",
    "sg:postcode":"29640",
    "sg:province":"Niedersachsen",
    "wof:name":"Ihr Platz Drogeriemarkt",
    "wof:placetype":"venue"
},
  "geometry": {"coordinates":[9.786937,53.118515],"type":"Point"}
}