{
  "type": "Feature",
  "properties": {
    "iso:country":"DE",
    "sg:address":"Wildemannschlucht 3",
    "sg:city":"Hann. M\u00fcnden",
    "sg:phone":"+49 5541/71564",
    "sg:postcode":"34346",
    "sg:province":"Niedersachsen",
    "wof:name":"Pro Spiel- Und Freizeit Gmbh",
    "wof:placetype":"venue"
},
  "geometry": {"coordinates":[9.642879,51.411263],"type":"Point"}
}