{
  "type": "Feature",
  "properties": {
    "iso:country":"DE",
    "sg:address":"Hauptstr. 14",
    "sg:city":"Oberstdorf",
    "sg:phone":"+49 8322/5218",
    "sg:postcode":"87561",
    "sg:province":"Bayern",
    "wof:name":"E. Panschik",
    "wof:placetype":"venue"
},
  "geometry": {"coordinates":[10.27761,47.41021],"type":"Point"}
}