{
  "type": "Feature",
  "properties": {
    "iso:country":"DE",
    "sg:address":"Am Wiesaer Weg 59h",
    "sg:city":"Annaberg-Buchholz",
    "sg:postcode":"09456",
    "sg:province":"Sachsen",
    "wof:name":"Elisabeth Rei\u00dfig",
    "wof:placetype":"venue"
},
  "geometry": {"coordinates":[13.017763,50.596455],"type":"Point"}
}