{
  "type": "Feature",
  "properties": {
    "iso:country":"DE",
    "sg:address":"Weiherheide 12",
    "sg:city":"Hamburg",
    "sg:phone":"+49 40/76969640",
    "sg:postcode":"21079",
    "sg:province":"Hamburg",
    "wof:name":"Okee-bau Gmbh",
    "wof:placetype":"venue"
},
  "geometry": {"coordinates":[9.989518,53.424152],"type":"Point"}
}