{
  "type": "Feature",
  "properties": {
    "iso:country":"DE",
    "sg:address":"Paul-Neck-Str. 139",
    "sg:city":"Bautzen",
    "sg:postcode":"02625",
    "sg:province":"Sachsen",
    "wof:name":"Rnv Verkehrsges. Mbh",
    "wof:placetype":"venue"
},
  "geometry": {"coordinates":[14.4469165802,51.1735191345],"type":"Point"}
}