{
  "type": "Feature",
  "properties": {
    "iso:country":"DE",
    "sg:address":"Lenkerweg 3",
    "sg:city":"Oberotterbach",
    "sg:phone":"+49 6342/919030",
    "sg:postcode":"76889",
    "sg:province":"Rheinland-Pfalz",
    "wof:name":"Reiner Miedel Steuerberater",
    "wof:placetype":"venue"
},
  "geometry": {"coordinates":[7.9683699608,49.0716819763],"type":"Point"}
}