{
  "type": "Feature",
  "properties": {
    "iso:country":"DE",
    "sg:address":"Kirchstr. 11",
    "sg:city":"Murg",
    "sg:postcode":"79730",
    "sg:province":"Baden-W\u00fcrttemberg",
    "wof:name":"Pfarrb\u00fccherei Borrom\u00e4us-b\u00fccherei",
    "wof:placetype":"venue"
},
  "geometry": {"coordinates":[8.02125,47.55534],"type":"Point"}
}