{
  "type": "Feature",
  "properties": {
    "iso:country":"DE",
    "sg:address":"Badstr. 34",
    "sg:city":"Bad Brambach",
    "sg:phone":"+49 37438/20468",
    "sg:postcode":"08648",
    "sg:province":"Sachsen",
    "wof:name":"Christa Lenk Steuerberaterin",
    "wof:placetype":"venue"
},
  "geometry": {"coordinates":[12.3052101135,50.2224121094],"type":"Point"}
}