{
  "type": "Feature",
  "properties": {
    "iso:country":"DE",
    "sg:address":"Pionierstr. 8",
    "sg:city":"Ulm",
    "sg:phone":"+49 731/24362",
    "sg:postcode":"89073",
    "sg:province":"Baden-W\u00fcrttemberg",
    "wof:name":"Klaus Schumann Innenarchitekt",
    "wof:placetype":"venue"
},
  "geometry": {"coordinates":[10.005526,48.401981],"type":"Point"}
}