{
  "type": "Feature",
  "properties": {
    "iso:country":"DE",
    "sg:address":"An der Netter Heide 4",
    "sg:city":"Osnabr\u00fcck",
    "sg:phone":"+49 541/61846",
    "sg:postcode":"49090",
    "sg:province":"Niedersachsen",
    "wof:name":"E. Bartling",
    "wof:placetype":"venue"
},
  "geometry": {"coordinates":[8.0347280502,52.2980461121],"type":"Point"}
}