{
  "type": "Feature",
  "properties": {
    "iso:country":"DE",
    "sg:address":"T\u00fcrkenstr. 31/IV",
    "sg:city":"M\u00fcnchen",
    "sg:phone":"+49 89/280157",
    "sg:postcode":"80799",
    "sg:province":"Bayern",
    "wof:name":"Suckf\u00fcll Verm\u00f6gens- Verwaltung Gmbh",
    "wof:placetype":"venue"
},
  "geometry": {"coordinates":[11.5748901367,48.1520118713],"type":"Point"}
}