{
  "type": "Feature",
  "properties": {
    "iso:country":"DE",
    "sg:address":"Reichsstr. 4",
    "sg:city":"Saarbr\u00fccken",
    "sg:phone":"+49 681/390070",
    "sg:postcode":"66111",
    "sg:province":"Saarland",
    "wof:name":"Redaktion Deutsches Wandern Verband Dt. Gebirgs- Und",
    "wof:placetype":"venue"
},
  "geometry": {"coordinates":[6.9909858704,49.2388458252],"type":"Point"}
}