{
  "type": "Feature",
  "properties": {
    "iso:country":"DE",
    "sg:address":"Pfalzstr 17",
    "sg:city":"D\u00fcsseldorf",
    "sg:phone":"+49 211/484501",
    "sg:postcode":"40477",
    "sg:province":"Nordrhein-Westfalen",
    "wof:name":"Transservice Internationale Spedition Gmbh",
    "wof:placetype":"venue"
},
  "geometry": {"coordinates":[6.77876091,51.2399787903],"type":"Point"}
}