{
  "type": "Feature",
  "properties": {
    "iso:country":"DE",
    "sg:address":"Paulsbergstr. 22",
    "sg:city":"Achim",
    "sg:postcode":"28832",
    "sg:province":"Niedersachsen",
    "wof:name":"Teufelsmoor Baumaschinen Gmbh",
    "wof:placetype":"venue"
},
  "geometry": {"coordinates":[9.030624,53.01347],"type":"Point"}
}