{
  "type": "Feature",
  "properties": {
    "iso:country":"DE",
    "sg:address":"Schl\u00fcterstr. 58",
    "sg:city":"Hamburg",
    "sg:phone":"+49 40/4101458",
    "sg:postcode":"20146",
    "sg:province":"Hamburg",
    "wof:name":"O Und S Verwaltungs- Und Beteiligungsgesellschaft Mbh",
    "wof:placetype":"venue"
},
  "geometry": {"coordinates":[9.9866352081,53.5687026978],"type":"Point"}
}