{
  "type": "Feature",
  "properties": {
    "iso:country":"DE",
    "sg:address":"Gr\u00fcne Str. 40",
    "sg:city":"Lindau",
    "sg:phone":"+49 39246/7076",
    "sg:postcode":"39264",
    "sg:province":"Sachsen-Anhalt",
    "wof:name":"Margitta Kubik",
    "wof:placetype":"venue"
},
  "geometry": {"coordinates":[12.0970888138,52.0357246399],"type":"Point"}
}