{
  "type": "Feature",
  "properties": {
    "iso:country":"DE",
    "sg:address":"Frankfurter Landstr. 130",
    "sg:city":"Darmstadt",
    "sg:phone":"+49 6151/933466",
    "sg:postcode":"64291",
    "sg:province":"Hessen",
    "wof:name":"R. Renker Heilpraktiker",
    "wof:placetype":"venue"
},
  "geometry": {"coordinates":[8.6569480896,49.9094543457],"type":"Point"}
}