{
  "type": "Feature",
  "properties": {
    "iso:country":"DE",
    "sg:address":"Ankergasse 14",
    "sg:city":"Klingenberg",
    "sg:phone":"+49 9372/2772",
    "sg:postcode":"63911",
    "sg:province":"Bayern",
    "wof:name":"Gastst\u00e4tte E. Baumeister",
    "wof:placetype":"venue"
},
  "geometry": {"coordinates":[9.1766424179,49.7747650146],"type":"Point"}
}