{
  "type": "Feature",
  "properties": {
    "iso:country":"DE",
    "sg:address":"Thiewall 8",
    "sg:city":"Hessisch Oldendorf",
    "sg:phone":"+49 5158/98048",
    "sg:postcode":"31840",
    "sg:province":"Niedersachsen",
    "wof:name":"Avsb Gmbh",
    "wof:placetype":"venue"
},
  "geometry": {"coordinates":[9.2732152939,52.1399116516],"type":"Point"}
}