{
  "type": "Feature",
  "properties": {
    "iso:country":"DE",
    "sg:address":"Bahnhofstr. 2",
    "sg:city":"Neumarkt",
    "sg:phone":"+49 9181/8831",
    "sg:postcode":"92318",
    "sg:province":"Bayern",
    "wof:name":"Deutsche Bank Ag",
    "wof:placetype":"venue"
},
  "geometry": {"coordinates":[11.459763,49.27663],"type":"Point"}
}