{
  "type": "Feature",
  "properties": {
    "iso:country":"DE",
    "sg:address":"Vilsstr. 25",
    "sg:city":"Velden",
    "sg:phone":"+49 8742/8943",
    "sg:postcode":"84149",
    "sg:province":"Bayern",
    "wof:name":"Martin Steckenbiller",
    "wof:placetype":"venue"
},
  "geometry": {"coordinates":[12.250102,48.366112],"type":"Point"}
}