{
  "type": "Feature",
  "properties": {
    "iso:country":"DE",
    "sg:address":"Dorfstr. 6",
    "sg:city":"Tramm",
    "sg:postcode":"21516",
    "sg:province":"Schleswig-Holstein",
    "wof:name":"Horst Borgsm\u00fcller Gmbh",
    "wof:placetype":"venue"
},
  "geometry": {"coordinates":[10.611817,53.564011],"type":"Point"}
}