{
  "type": "Feature",
  "properties": {
    "iso:country":"DE",
    "sg:address":"Kurvenstr. 4",
    "sg:city":"Hamburg",
    "sg:phone":"+49 40/684262",
    "sg:postcode":"22043",
    "sg:province":"Hamburg",
    "wof:name":"Dirk Meyer Rechtsanwalt",
    "wof:placetype":"venue"
},
  "geometry": {"coordinates":[10.0737390518,53.5675582886],"type":"Point"}
}