{
  "type": "Feature",
  "properties": {
    "iso:country":"DE",
    "sg:address":"Friedrich-Ebert-Str. 9",
    "sg:city":"Erbach",
    "sg:phone":"+49 6062/3278",
    "sg:postcode":"64711",
    "sg:province":"Hessen",
    "wof:name":"Wilhelm Dexheimer Kohlen-handlung",
    "wof:placetype":"venue"
},
  "geometry": {"coordinates":[8.9928531647,49.6546630859],"type":"Point"}
}