{
  "type": "Feature",
  "properties": {
    "iso:country":"DE",
    "sg:address":"Gewerbestr. 1",
    "sg:city":"Sch\u00f6mberg",
    "sg:phone":"+49 7084/4228",
    "sg:postcode":"75328",
    "sg:province":"Baden-W\u00fcrttemberg",
    "wof:name":"Wild Thing",
    "wof:placetype":"venue"
},
  "geometry": {"coordinates":[8.640361,48.806782],"type":"Point"}
}