{
  "type": "Feature",
  "properties": {
    "iso:country":"DE",
    "sg:address":"Winzerstr. 3",
    "sg:city":"Radebeul",
    "sg:phone":"+49 351/8387141",
    "sg:postcode":"01445",
    "sg:province":"Sachsen",
    "wof:name":"Eberhard K\u00e4ppler",
    "wof:placetype":"venue"
},
  "geometry": {"coordinates":[13.658693,51.108463],"type":"Point"}
}