{
  "type": "Feature",
  "properties": {
    "iso:country":"DE",
    "sg:address":"Im Fl\u00fcrchen 12a",
    "sg:city":"Rittersdorf",
    "sg:phone":"+49 6561/12879",
    "sg:postcode":"54636",
    "sg:province":"Rheinland-Pfalz",
    "wof:name":"Walter Heyen",
    "wof:placetype":"venue"
},
  "geometry": {"coordinates":[6.4920611382,49.9968490601],"type":"Point"}
}