{
  "type": "Feature",
  "properties": {
    "iso:country":"DE",
    "sg:address":"Riesaer Str 165",
    "sg:city":"Leipzig",
    "sg:phone":"+49 341/259650",
    "sg:postcode":"04319",
    "sg:province":"Sachsen",
    "wof:name":"Feinmechanik Ralf K\u00f6gel",
    "wof:placetype":"venue"
},
  "geometry": {"coordinates":[12.501012,51.34919],"type":"Point"}
}