{
  "type": "Feature",
  "properties": {
    "iso:country":"DE",
    "sg:address":"Heinickestr. 11",
    "sg:city":"Hamburg",
    "sg:postcode":"20249",
    "sg:province":"Hamburg",
    "wof:name":"Kommanditgesellschaft R & S Reupke Immobilien Gmbh & Co.",
    "wof:placetype":"venue"
},
  "geometry": {"coordinates":[9.9903936386,53.5931549072],"type":"Point"}
}