{
  "type": "Feature",
  "properties": {
    "iso:country":"DE",
    "sg:address":"Cottenau 15",
    "sg:city":"Wirsberg",
    "sg:phone":"+49 9227/73272",
    "sg:postcode":"95339",
    "sg:province":"Bayern",
    "wof:name":"Irma Wei\u00df",
    "wof:placetype":"venue"
},
  "geometry": {"coordinates":[11.6274280548,50.1297645569],"type":"Point"}
}