{
  "type": "Feature",
  "properties": {
    "iso:country":"DE",
    "sg:address":"Danziger Str. 82",
    "sg:city":"Berlin",
    "sg:postcode":"10405",
    "sg:province":"Berlin",
    "wof:name":"Wizard Ag",
    "wof:placetype":"venue"
},
  "geometry": {"coordinates":[13.4259128571,52.5383224487],"type":"Point"}
}