{
  "type": "Feature",
  "properties": {
    "iso:country":"DE",
    "sg:address":"Mindener Str. 78",
    "sg:city":"Hille",
    "sg:phone":"+49 5703/890",
    "sg:postcode":"32479",
    "sg:province":"Nordrhein-Westfalen",
    "wof:name":"Pizzeria Da Pippo",
    "wof:placetype":"venue"
},
  "geometry": {"coordinates":[8.7450180054,52.3361282349],"type":"Point"}
}