{
  "type": "Feature",
  "properties": {
    "iso:country":"DE",
    "sg:address":"Bahnstr. 18",
    "sg:city":"Augsburg",
    "sg:phone":"+49 821/995741",
    "sg:postcode":"86199",
    "sg:province":"Bayern",
    "wof:name":"Titus Bernhard Architekt",
    "wof:placetype":"venue"
},
  "geometry": {"coordinates":[10.872513,48.337669],"type":"Point"}
}