{
  "type": "Feature",
  "properties": {
    "iso:country":"DE",
    "sg:address":"Maybachstr.21",
    "sg:city":"Waiblingen",
    "sg:phone":"+49 7151/58322",
    "sg:postcode":"71332",
    "sg:province":"Baden-W\u00fcrttemberg",
    "wof:name":"Labor Gutmayer",
    "wof:placetype":"venue"
},
  "geometry": {"coordinates":[9.2958402634,48.8307952881],"type":"Point"}
}