{
  "type": "Feature",
  "properties": {
    "iso:country":"DE",
    "sg:address":"Karlstr. 17",
    "sg:city":"Crailsheim",
    "sg:phone":"+49 7951/5624",
    "sg:postcode":"74564",
    "sg:province":"Baden-W\u00fcrttemberg",
    "wof:name":"Jakob M\u00f6bus Nachf. Gmbh & Co. Kg",
    "wof:placetype":"venue"
},
  "geometry": {"coordinates":[10.0721092224,49.1374588013],"type":"Point"}
}