{
  "type": "Feature",
  "properties": {
    "iso:country":"DE",
    "sg:address":"Elisabeth Str 44-46::",
    "sg:city":"D\u00fcsseldorf",
    "sg:postcode":"40217",
    "sg:province":"Nordrhein-Westfalen",
    "wof:name":"Westlb Research Gmbh",
    "wof:placetype":"venue"
},
  "geometry": {"coordinates":[6.775603,51.214508],"type":"Point"}
}