{
  "type": "Feature",
  "properties": {
    "iso:country":"DE",
    "sg:address":"Blutenburgstr. 53",
    "sg:city":"M\u00fcnchen",
    "sg:phone":"+49 89/1291254",
    "sg:postcode":"80636",
    "sg:province":"Bayern",
    "wof:name":"China-restaurant Kam Lung",
    "wof:placetype":"venue"
},
  "geometry": {"coordinates":[11.5396280289,48.1498756409],"type":"Point"}
}