{
  "type": "Feature",
  "properties": {
    "iso:country":"DE",
    "sg:address":"Bismarckstr. 5",
    "sg:city":"Schwelm",
    "sg:phone":"+49 2336/3110",
    "sg:postcode":"58332",
    "sg:province":"Nordrhein-Westfalen",
    "wof:name":"Johannes \u00dcbbing",
    "wof:placetype":"venue"
},
  "geometry": {"coordinates":[7.292292,51.286613],"type":"Point"}
}