{
  "type": "Feature",
  "properties": {
    "iso:country":"DE",
    "sg:address":"Bahnstr. 7",
    "sg:city":"Rommerskirchen",
    "sg:phone":"+49 2183/81583",
    "sg:postcode":"41569",
    "sg:province":"Nordrhein-Westfalen",
    "wof:name":"Zur Post",
    "wof:placetype":"venue"
},
  "geometry": {"coordinates":[6.7002120018,51.0387001038],"type":"Point"}
}