{
  "type": "Feature",
  "properties": {
    "iso:country":"DE",
    "sg:address":"Altenbochumer Str. 28",
    "sg:city":"Bochum",
    "sg:phone":"+49 234/313144",
    "sg:postcode":"44803",
    "sg:province":"Nordrhein-Westfalen",
    "wof:name":"Sportklause",
    "wof:placetype":"venue"
},
  "geometry": {"coordinates":[7.2382979393,51.476108551],"type":"Point"}
}