{
  "type": "Feature",
  "properties": {
    "iso:country":"DE",
    "sg:address":"Kirchstr. 14",
    "sg:city":"Beckum",
    "sg:phone":"+49 2525/2288",
    "sg:postcode":"59269",
    "sg:province":"Nordrhein-Westfalen",
    "wof:name":"T. Erdbories",
    "wof:placetype":"venue"
},
  "geometry": {"coordinates":[8.0255403519,51.8013305664],"type":"Point"}
}