{
  "type": "Feature",
  "properties": {
    "iso:country":"DE",
    "sg:address":"Industriestr. 2",
    "sg:city":"Holzkirchen",
    "sg:phone":"+49 8024/3080",
    "sg:postcode":"83607",
    "sg:province":"Bayern",
    "wof:name":"Steinbeis Packaging Gmbh & Co Kg",
    "wof:placetype":"venue"
},
  "geometry": {"coordinates":[11.7174863815,47.8780212402],"type":"Point"}
}