{
  "type": "Feature",
  "properties": {
    "iso:country":"DE",
    "sg:address":"Ittmecker Weg 2-4",
    "sg:city":"Meschede",
    "sg:phone":"+49 291/1614",
    "sg:postcode":"59872",
    "sg:province":"Nordrhein-Westfalen",
    "wof:name":"Bestattungsistitut Bernd Mertens",
    "wof:placetype":"venue"
},
  "geometry": {"coordinates":[8.296113,51.346714],"type":"Point"}
}