{
  "type": "Feature",
  "properties": {
    "iso:country":"DE",
    "sg:address":"Aktienstr. 53",
    "sg:city":"M\u00f6nchengladbach",
    "sg:phone":"+49 2161/15280",
    "sg:postcode":"41069",
    "sg:province":"Nordrhein-Westfalen",
    "wof:name":"Erika Br\u00fcchner",
    "wof:placetype":"venue"
},
  "geometry": {"coordinates":[6.4295301437,51.18201828],"type":"Point"}
}