{
  "type": "Feature",
  "properties": {
    "iso:country":"DE",
    "sg:address":"Gustavstr. 3",
    "sg:city":"Gelnhausen",
    "sg:phone":"+49 6051/68618",
    "sg:postcode":"63571",
    "sg:province":"Hessen",
    "wof:name":"Wilhelm Malsam",
    "wof:placetype":"venue"
},
  "geometry": {"coordinates":[9.1507740021,50.1863288879],"type":"Point"}
}