{
  "type": "Feature",
  "properties": {
    "iso:country":"DE",
    "sg:address":"Bertolt-Brecht-Str. 8",
    "sg:city":"Zschopau",
    "sg:phone":"+49 3725/22965",
    "sg:postcode":"09405",
    "sg:province":"Sachsen",
    "wof:name":"Uwe Seyfert",
    "wof:placetype":"venue"
},
  "geometry": {"coordinates":[13.0804262161,50.7442588806],"type":"Point"}
}