{
  "type": "Feature",
  "properties": {
    "iso:country":"DE",
    "sg:address":"Ulrichstr. 10",
    "sg:city":"Altshausen",
    "sg:phone":"+49 4975/8491161",
    "sg:postcode":"88361",
    "sg:province":"Baden-W\u00fcrttemberg",
    "wof:name":"Tools Zerspanungstechnik Gmbh",
    "wof:placetype":"venue"
},
  "geometry": {"coordinates":[9.539531,47.927799],"type":"Point"}
}