{
  "type": "Feature",
  "properties": {
    "iso:country":"DE",
    "sg:address":"Linzgaustr. 1",
    "sg:city":"Wald",
    "sg:phone":"+49 7578/770",
    "sg:postcode":"88639",
    "sg:province":"Baden-W\u00fcrttemberg",
    "wof:name":"Josef Endres",
    "wof:placetype":"venue"
},
  "geometry": {"coordinates":[9.186894,47.917732],"type":"Point"}
}