{
  "type": "Feature",
  "properties": {
    "iso:country":"DE",
    "sg:address":"D\u00f6llingerstr. 19",
    "sg:city":"M\u00fcnchen",
    "sg:phone":"+49 89/175011",
    "sg:postcode":"80639",
    "sg:province":"Bayern",
    "wof:name":"Max Fochler Steuerberater",
    "wof:placetype":"venue"
},
  "geometry": {"coordinates":[11.5145149231,48.1553001404],"type":"Point"}
}