{
  "type": "Feature",
  "properties": {
    "iso:country":"DE",
    "sg:address":"Marktstr. 3",
    "sg:city":"G\u00f6ppingen",
    "sg:phone":"+49 7161/74200",
    "sg:postcode":"73033",
    "sg:province":"Baden-W\u00fcrttemberg",
    "wof:name":"Fritz Klein B\u00e4ckerei",
    "wof:placetype":"venue"
},
  "geometry": {"coordinates":[9.653521,48.701],"type":"Point"}
}