{
  "type": "Feature",
  "properties": {
    "iso:country":"DE",
    "sg:address":"Bahnhofstr. 39",
    "sg:city":"Lauenbr\u00fcck",
    "sg:phone":"+49 4267/1026",
    "sg:postcode":"27389",
    "sg:province":"Niedersachsen",
    "wof:name":"Volksbank Sittensen Eg",
    "wof:placetype":"venue"
},
  "geometry": {"coordinates":[9.555833,53.198601],"type":"Point"}
}