{
  "type": "Feature",
  "properties": {
    "iso:country":"DE",
    "sg:address":"Lingener Str. 13",
    "sg:city":"Nordhorn",
    "sg:phone":"+49 5921/39979",
    "sg:postcode":"48531",
    "sg:province":"Niedersachsen",
    "wof:name":"Gastst\u00e4tte Jever-fa\u00df",
    "wof:placetype":"venue"
},
  "geometry": {"coordinates":[7.0838499069,52.4407310486],"type":"Point"}
}