{
  "type": "Feature",
  "properties": {
    "iso:country":"DE",
    "sg:address":"Ludwigstr. 2",
    "sg:city":"Zittau",
    "sg:phone":"+49 3583/510936",
    "sg:postcode":"02763",
    "sg:province":"Sachsen",
    "wof:name":"Kebapstube Picknick",
    "wof:placetype":"venue"
},
  "geometry": {"coordinates":[14.8108797073,50.8949928284],"type":"Point"}
}