{
  "type": "Feature",
  "properties": {
    "iso:country":"DE",
    "sg:address":"Kurf\u00fcrstendamm 186",
    "sg:city":"Berlin",
    "sg:postcode":"10707",
    "sg:province":"Berlin",
    "wof:name":"Finanzkonzept Wirtschafts- Beratungs-und Beteiligungs",
    "wof:placetype":"venue"
},
  "geometry": {"coordinates":[13.315423,52.500763],"type":"Point"}
}