{
  "type": "Feature",
  "properties": {
    "iso:country":"DE",
    "sg:address":"D\u00f6inghauser Str. 38",
    "sg:city":"Schwelm",
    "sg:phone":"+49 2336/914538",
    "sg:postcode":"58332",
    "sg:province":"Nordrhein-Westfalen",
    "wof:name":"Latech Elastic Gmbh",
    "wof:placetype":"venue"
},
  "geometry": {"coordinates":[7.2845678329,51.2893257141],"type":"Point"}
}