{
  "type": "Feature",
  "properties": {
    "iso:country":"DE",
    "sg:address":"Berliner Str. 17",
    "sg:city":"Berlin",
    "sg:phone":"+49 30/8609980",
    "sg:postcode":"10715",
    "sg:province":"Berlin",
    "wof:name":"Wolfgang Wustrack Ohg",
    "wof:placetype":"venue"
},
  "geometry": {"coordinates":[13.328373909,52.4870223999],"type":"Point"}
}