{
  "type": "Feature",
  "properties": {
    "iso:country":"DE",
    "sg:address":"Eckhardstr. 33",
    "sg:city":"N\u00fcrnberg",
    "sg:phone":"+49 911/445634",
    "sg:postcode":"90461",
    "sg:province":"Bayern",
    "wof:name":"H. F\u00f6rg E. Schwarz",
    "wof:placetype":"venue"
},
  "geometry": {"coordinates":[11.0901088715,49.4307403564],"type":"Point"}
}