{
  "type": "Feature",
  "properties": {
    "iso:country":"DE",
    "sg:address":"Zum Rebstockbad",
    "sg:city":"Frankfurt",
    "sg:phone":"+49 69/773337",
    "sg:postcode":"60486",
    "sg:province":"Hessen",
    "wof:name":"Restaurant Rebstockbad",
    "wof:placetype":"venue"
},
  "geometry": {"coordinates":[8.617811203,50.1144790649],"type":"Point"}
}