{
  "type": "Feature",
  "properties": {
    "iso:country":"DE",
    "sg:address":"Am Bilten 5 b",
    "sg:city":"Wuppertal",
    "sg:phone":"+49 202/520142",
    "sg:postcode":"42277",
    "sg:province":"Nordrhein-Westfalen",
    "wof:name":"Kurt Teckenberg Radio Fernsehen",
    "wof:placetype":"venue"
},
  "geometry": {"coordinates":[7.207656,51.288258],"type":"Point"}
}