{
  "type": "Feature",
  "properties": {
    "iso:country":"DE",
    "sg:address":"Alte J\u00fclicher Str. 26",
    "sg:city":"D\u00fcren",
    "sg:phone":"+49 2421/41200",
    "sg:postcode":"52353",
    "sg:province":"Nordrhein-Westfalen",
    "wof:name":"B. Prinz",
    "wof:placetype":"venue"
},
  "geometry": {"coordinates":[6.4783058167,50.811756134],"type":"Point"}
}