{
  "type": "Feature",
  "properties": {
    "iso:country":"DE",
    "sg:address":"Bielefelder Str. 108",
    "sg:city":"Herne",
    "sg:phone":"+49 2325/43737",
    "sg:postcode":"44625",
    "sg:province":"Nordrhein-Westfalen",
    "wof:name":"Kurt Witzer Masseur",
    "wof:placetype":"venue"
},
  "geometry": {"coordinates":[7.188363,51.531349],"type":"Point"}
}