{
  "type": "Feature",
  "properties": {
    "iso:country":"DE",
    "sg:address":"Bahnhofstr. 18",
    "sg:city":"Offenbach",
    "sg:phone":"+49 69/815832",
    "sg:postcode":"63067",
    "sg:province":"Hessen",
    "wof:name":"Fahrradges. H. U. D. Meyer Ohg",
    "wof:placetype":"venue"
},
  "geometry": {"coordinates":[8.756595,50.1059],"type":"Point"}
}