{
  "type": "Feature",
  "properties": {
    "iso:country":"DE",
    "sg:address":"Bokeler Landstr.",
    "sg:city":"Wiefelstede",
    "sg:phone":"+49 4944/026304",
    "sg:postcode":"26215",
    "sg:province":"Niedersachsen",
    "wof:name":"E. Duis",
    "wof:placetype":"venue"
},
  "geometry": {"coordinates":[8.136674881,53.2413063049],"type":"Point"}
}