{
  "type": "Feature",
  "properties": {
    "iso:country":"DE",
    "sg:address":"Marktplatz 4",
    "sg:city":"Hauzenberg",
    "sg:phone":"+49 8586/2433",
    "sg:postcode":"94051",
    "sg:province":"Bayern",
    "wof:name":"Raiffeisenbank S\u00fcdlich Bayer. Wald",
    "wof:placetype":"venue"
},
  "geometry": {"coordinates":[13.623854,48.651432],"type":"Point"}
}