{
  "type": "Feature",
  "properties": {
    "iso:country":"DE",
    "sg:address":"Asamstr. 21",
    "sg:city":"Freising",
    "sg:phone":"+49 8161/63291",
    "sg:postcode":"85356",
    "sg:province":"Bayern",
    "wof:name":"Dieter Sch\u00f6negge",
    "wof:placetype":"venue"
},
  "geometry": {"coordinates":[11.752685,48.413269],"type":"Point"}
}