{
  "type": "Feature",
  "properties": {
    "iso:country":"DE",
    "sg:address":"H\u00f6rnsheimer Eck 5",
    "sg:city":"Wetzlar",
    "sg:phone":"+49 6441/71696",
    "sg:postcode":"35578",
    "sg:province":"Hessen",
    "wof:name":"Elektro-center-lahn",
    "wof:placetype":"venue"
},
  "geometry": {"coordinates":[8.5378494263,50.5381507874],"type":"Point"}
}