{
  "type": "Feature",
  "properties": {
    "iso:country":"DE",
    "sg:address":"Hofstr. 19",
    "sg:city":"Zwiefalten",
    "sg:phone":"+49 4973/7391181",
    "sg:postcode":"88529",
    "sg:province":"Baden-W\u00fcrttemberg",
    "wof:name":"Mfz-metallform Gmbh",
    "wof:placetype":"venue"
},
  "geometry": {"coordinates":[9.458491,48.236118],"type":"Point"}
}