{
  "type": "Feature",
  "properties": {
    "iso:country":"DE",
    "sg:address":"Zur Rampe 1",
    "sg:city":"Hammelburg",
    "sg:phone":"+49 9732/913270",
    "sg:postcode":"97762",
    "sg:province":"Bayern",
    "wof:name":"Bay Wa Bau- Und Gartenmarkt",
    "wof:placetype":"venue"
},
  "geometry": {"coordinates":[9.8840713501,50.1201438904],"type":"Point"}
}