{
  "type": "Feature",
  "properties": {
    "iso:country":"DE",
    "sg:address":"Langebr\u00fcgger Str. 5",
    "sg:city":"Westerstede",
    "sg:postcode":"26655",
    "sg:province":"Niedersachsen",
    "wof:name":"Ok Offerten Kauf In Westerstede Gmbh",
    "wof:placetype":"venue"
},
  "geometry": {"coordinates":[7.959742,53.254879],"type":"Point"}
}