{
  "type": "Feature",
  "properties": {
    "iso:country":"DE",
    "sg:address":"Postweg 3",
    "sg:city":"Lohberg",
    "sg:phone":"+49 9943/1261",
    "sg:postcode":"93470",
    "sg:province":"Bayern",
    "wof:name":"Albert Wiesm\u00fcller",
    "wof:placetype":"venue"
},
  "geometry": {"coordinates":[13.106545,49.175648],"type":"Point"}
}