{
  "type": "Feature",
  "properties": {
    "iso:country":"DE",
    "sg:address":"Oberbruchstr. 52",
    "sg:city":"Krefeld",
    "sg:phone":"+49 2151/311982",
    "sg:postcode":"47807",
    "sg:province":"Nordrhein-Westfalen",
    "wof:name":"G\u00fcnter Wiefels",
    "wof:placetype":"venue"
},
  "geometry": {"coordinates":[6.59565,51.310539],"type":"Point"}
}