{
  "type": "Feature",
  "properties": {
    "iso:country":"DE",
    "sg:address":"Markt 1",
    "sg:city":"Finsterwalde",
    "sg:phone":"+49 3531/2070",
    "sg:postcode":"03238",
    "sg:province":"Brandenburg",
    "wof:name":"Stadt- Und Kreisbibliothek",
    "wof:placetype":"venue"
},
  "geometry": {"coordinates":[13.708556,51.629768],"type":"Point"}
}