{
  "type": "Feature",
  "properties": {
    "iso:country":"DE",
    "sg:address":"Am Zwenger 1",
    "sg:city":"Hungen",
    "sg:phone":"+49 6402/6970",
    "sg:postcode":"35410",
    "sg:province":"Hessen",
    "wof:name":"F. A. Wobst Gmbh & Co. Kg",
    "wof:placetype":"venue"
},
  "geometry": {"coordinates":[8.900868,50.476376],"type":"Point"}
}