{
  "type": "Feature",
  "properties": {
    "iso:country":"DE",
    "sg:address":"Wilhelm-Cohrs-Weg 6",
    "sg:city":"Seevetal",
    "sg:phone":"+49 4105/159635",
    "sg:postcode":"21217",
    "sg:province":"Niedersachsen",
    "wof:name":"Bernhard Scheer Versicherungsmakler",
    "wof:placetype":"venue"
},
  "geometry": {"coordinates":[9.9977998734,53.4055633545],"type":"Point"}
}