{
  "type": "Feature",
  "properties": {
    "iso:country":"DE",
    "sg:address":"Klausheide 59",
    "sg:city":"Enger",
    "sg:phone":"+49 5225/1728",
    "sg:postcode":"32130",
    "sg:province":"Nordrhein-Westfalen",
    "wof:name":"Werner Bartling",
    "wof:placetype":"venue"
},
  "geometry": {"coordinates":[8.517498,52.145725],"type":"Point"}
}