{
  "type": "Feature",
  "properties": {
    "iso:country":"DE",
    "sg:address":"Dorfstr. 8",
    "sg:city":"Sch\u00f6nermark",
    "sg:postcode":"17291",
    "sg:province":"Brandenburg",
    "wof:name":"Evangelisch-lutherische Kirche",
    "wof:placetype":"venue"
},
  "geometry": {"coordinates":[13.9495954514,53.3646392822],"type":"Point"}
}