{
  "type": "Feature",
  "properties": {
    "iso:country":"DE",
    "sg:address":"Riedstr. 24",
    "sg:city":"Pfungstadt",
    "sg:phone":"+49 6157/990449",
    "sg:postcode":"64319",
    "sg:province":"Hessen",
    "wof:name":"Dollfu\u00df & Sinsis Ohg",
    "wof:placetype":"venue"
},
  "geometry": {"coordinates":[8.5600070953,49.8024902344],"type":"Point"}
}