{
  "type": "Feature",
  "properties": {
    "iso:country":"DE",
    "sg:address":"Sasbacher Str. 30",
    "sg:city":"Wyhl",
    "sg:phone":"+49 7642/3828",
    "sg:postcode":"79369",
    "sg:province":"Baden-W\u00fcrttemberg",
    "wof:name":"J. Und N. H\u00e4mmerle",
    "wof:placetype":"venue"
},
  "geometry": {"coordinates":[7.6467218399,48.1642951965],"type":"Point"}
}