{
  "type": "Feature",
  "properties": {
    "iso:country":"DE",
    "sg:address":"Oststr. 10",
    "sg:city":"D\u00fcsseldorf",
    "sg:phone":"+49 211/3559450",
    "sg:postcode":"40211",
    "sg:province":"Nordrhein-Westfalen",
    "wof:name":"Bgi Gewerbe-immobilien Gmbh",
    "wof:placetype":"venue"
},
  "geometry": {"coordinates":[6.789657,51.227417],"type":"Point"}
}