{
  "type": "Feature",
  "properties": {
    "iso:country":"DE",
    "sg:address":"Kirchstr. 154",
    "sg:city":"Dinslaken",
    "sg:phone":"+49 2064/91257",
    "sg:postcode":"46539",
    "sg:province":"Nordrhein-Westfalen",
    "wof:name":"Heinrich H\u00f6ffner Versich.",
    "wof:placetype":"venue"
},
  "geometry": {"coordinates":[6.7773180008,51.5712852478],"type":"Point"}
}