{
  "type": "Feature",
  "properties": {
    "iso:country":"DE",
    "sg:address":"An der Harth 14",
    "sg:city":"Markkleeberg",
    "sg:phone":"+49 341/356270",
    "sg:postcode":"04416",
    "sg:province":"Sachsen",
    "wof:name":"Trockenbau & Stuck Gmbh",
    "wof:placetype":"venue"
},
  "geometry": {"coordinates":[12.3816051483,51.2727088928],"type":"Point"}
}