{
  "type": "Feature",
  "properties": {
    "iso:country":"DE",
    "sg:address":"Eisenbahnstr. 24a",
    "sg:city":"Bad Liebenstein",
    "sg:phone":"+49 36961/30823",
    "sg:postcode":"36448",
    "sg:province":"Th\u00fcringen",
    "wof:name":"G. Schneider Steuerberater",
    "wof:placetype":"venue"
},
  "geometry": {"coordinates":[10.3419179916,50.8157730103],"type":"Point"}
}