{
  "type": "Feature",
  "properties": {
    "iso:country":"DE",
    "sg:address":"Hauptstr. 22",
    "sg:city":"Denzlingen",
    "sg:postcode":"79211",
    "sg:province":"Baden-W\u00fcrttemberg",
    "wof:name":"Schattat Wohnbau Gmbh",
    "wof:placetype":"venue"
},
  "geometry": {"coordinates":[7.867833,48.071289],"type":"Point"}
}