{
  "type": "Feature",
  "properties": {
    "iso:country":"DE",
    "sg:address":"Herberzstr. 19",
    "sg:city":"K\u00f6ln",
    "sg:phone":"+49 221/781021",
    "sg:postcode":"50769",
    "sg:province":"Nordrhein-Westfalen",
    "wof:name":"Horst Jansen Gmbh & Co. Kg Baustoffe Transporte",
    "wof:placetype":"venue"
},
  "geometry": {"coordinates":[6.8618488312,51.0653686523],"type":"Point"}
}