{
  "type": "Feature",
  "properties": {
    "iso:country":"DE",
    "sg:address":"Markt 15",
    "sg:city":"Frankenberg",
    "sg:phone":"+49 37206/6428",
    "sg:postcode":"09669",
    "sg:province":"Sachsen",
    "wof:name":"Stadtarchiv",
    "wof:placetype":"venue"
},
  "geometry": {"coordinates":[13.032766,50.912098],"type":"Point"}
}