{
  "type": "Feature",
  "properties": {
    "iso:country":"DE",
    "sg:address":"Martinstr. 8",
    "sg:city":"Blaustein",
    "sg:phone":"+49 7304/41559",
    "sg:postcode":"89134",
    "sg:province":"Baden-W\u00fcrttemberg",
    "wof:name":"Serhan Balci",
    "wof:placetype":"venue"
},
  "geometry": {"coordinates":[9.9207954407,48.4162025452],"type":"Point"}
}