{
  "type": "Feature",
  "properties": {
    "iso:country":"DE",
    "sg:address":"Lipperoder Str. 35",
    "sg:city":"Lippstadt",
    "sg:postcode":"59555",
    "sg:province":"Nordrhein-Westfalen",
    "wof:name":"Js Verm\u00f6gensverwaltungs- Gmbh",
    "wof:placetype":"venue"
},
  "geometry": {"coordinates":[8.3543071747,51.6819953918],"type":"Point"}
}