{
  "type": "Feature",
  "properties": {
    "iso:country":"DE",
    "sg:address":"Lindenplatz 4",
    "sg:city":"Lupendorf",
    "sg:phone":"+49 39953/283",
    "sg:postcode":"17194",
    "sg:province":"Mecklenburg-Vorpommern",
    "wof:name":"J. Steinhagen",
    "wof:placetype":"venue"
},
  "geometry": {"coordinates":[12.642829895,53.6395454407],"type":"Point"}
}