{
  "type": "Feature",
  "properties": {
    "iso:country":"DE",
    "sg:address":"S\u00fcllbergstr. 1",
    "sg:city":"Springe",
    "sg:phone":"+49 5045/8588",
    "sg:postcode":"31832",
    "sg:province":"Niedersachsen",
    "wof:name":"Chinarestaurant Dynastie",
    "wof:placetype":"venue"
},
  "geometry": {"coordinates":[9.6566295624,52.2391242981],"type":"Point"}
}