{
  "type": "Feature",
  "properties": {
    "iso:country":"DE",
    "sg:address":"Bussardstr. 40",
    "sg:city":"Voerde",
    "sg:phone":"+49 2855/2401",
    "sg:postcode":"46562",
    "sg:province":"Nordrhein-Westfalen",
    "wof:name":"Karl Lemm Architekt",
    "wof:placetype":"venue"
},
  "geometry": {"coordinates":[6.705164,51.592136],"type":"Point"}
}