{
  "type": "Feature",
  "properties": {
    "iso:country":"DE",
    "sg:address":"Bahnhofstr. 5",
    "sg:city":"Northeim",
    "sg:phone":"+49 5551/3181",
    "sg:postcode":"37154",
    "sg:province":"Niedersachsen",
    "wof:name":"B\u00e4derparadies Sanit\u00e4rfachhandels Gmbh",
    "wof:placetype":"venue"
},
  "geometry": {"coordinates":[9.9888038635,51.7048568726],"type":"Point"}
}