{
  "type": "Feature",
  "properties": {
    "iso:country":"DE",
    "sg:address":"Tibarg 32 c",
    "sg:city":"Hamburg",
    "sg:phone":"+49 40/580305",
    "sg:postcode":"22459",
    "sg:province":"Hamburg",
    "wof:name":"J\u00f6rg Bahrenfu\u00df Rechtsanwalt",
    "wof:placetype":"venue"
},
  "geometry": {"coordinates":[9.9519052505,53.6199531555],"type":"Point"}
}