{
  "type": "Feature",
  "properties": {
    "iso:country":"DE",
    "sg:address":"Crayerstr. 18",
    "sg:city":"Amberg",
    "sg:phone":"+49 9621/74844",
    "sg:postcode":"92224",
    "sg:province":"Bayern",
    "wof:name":"Spangler Gmbh",
    "wof:placetype":"venue"
},
  "geometry": {"coordinates":[11.873034,49.439545],"type":"Point"}
}