{
  "type": "Feature",
  "properties": {
    "iso:country":"DE",
    "sg:address":"Hauptstr. 11",
    "sg:city":"Stockstadt",
    "sg:phone":"+49 6027/1318",
    "sg:postcode":"63811",
    "sg:province":"Bayern",
    "wof:name":"Theo Fuchs",
    "wof:placetype":"venue"
},
  "geometry": {"coordinates":[9.064475,49.978783],"type":"Point"}
}