{
  "type": "Feature",
  "properties": {
    "iso:country":"DE",
    "sg:address":"Bessinger Str. 20",
    "sg:city":"Bad Oeynhausen",
    "sg:phone":"+49 5731/22272",
    "sg:postcode":"32547",
    "sg:province":"Nordrhein-Westfalen",
    "wof:name":"Ev. Pfarramt Nord Wichern",
    "wof:placetype":"venue"
},
  "geometry": {"coordinates":[8.8111886978,52.2007827759],"type":"Point"}
}