{
  "type": "Feature",
  "properties": {
    "iso:country":"DE",
    "sg:address":"Lornsenstr. 54",
    "sg:city":"Elmshorn",
    "sg:phone":"+49 4121/3009",
    "sg:postcode":"25335",
    "sg:province":"Schleswig-Holstein",
    "wof:name":"Kantine",
    "wof:placetype":"venue"
},
  "geometry": {"coordinates":[9.6535291672,53.7600135803],"type":"Point"}
}