{
  "type": "Feature",
  "properties": {
    "iso:country":"DE",
    "sg:address":"Hogenb\u00f6gen 97",
    "sg:city":"Visbek",
    "sg:phone":"+49 4445/1425",
    "sg:postcode":"49429",
    "sg:province":"Niedersachsen",
    "wof:name":"Gefl\u00fcgelzuchtverein Visbek Alfred Meyer",
    "wof:placetype":"venue"
},
  "geometry": {"coordinates":[8.3589248657,52.8404922485],"type":"Point"}
}