{
  "type": "Feature",
  "properties": {
    "iso:country":"DE",
    "sg:address":"Am Seewege 1",
    "sg:city":"Gro\u00dfschwabhausen",
    "sg:phone":"+49 36454/50662",
    "sg:postcode":"99441",
    "sg:province":"Th\u00fcringen",
    "wof:name":"Blankenhain Friseur Gmbh",
    "wof:placetype":"venue"
},
  "geometry": {"coordinates":[11.4877500534,50.941318512],"type":"Point"}
}