{
  "type": "Feature",
  "properties": {
    "iso:country":"DE",
    "sg:address":"Polsumer Str. 11",
    "sg:city":"Herten",
    "sg:phone":"+49 2366/4504",
    "sg:postcode":"45701",
    "sg:province":"Nordrhein-Westfalen",
    "wof:name":"Johannes D\u00f6rtelmann",
    "wof:placetype":"venue"
},
  "geometry": {"coordinates":[7.141718,51.616364],"type":"Point"}
}