{
  "type": "Feature",
  "properties": {
    "iso:country":"DE",
    "sg:address":"Im Ammertal 3",
    "sg:city":"M\u00f6glingen",
    "sg:phone":"+49 7141/481487",
    "sg:postcode":"71696",
    "sg:province":"Baden-W\u00fcrttemberg",
    "wof:name":"Kurt Pflugfelder",
    "wof:placetype":"venue"
},
  "geometry": {"coordinates":[9.11458,48.882393],"type":"Point"}
}