{
  "type": "Feature",
  "properties": {
    "iso:country":"DE",
    "sg:address":"Castroper Str. 31",
    "sg:city":"Datteln",
    "sg:phone":"+49 2363/559451",
    "sg:postcode":"45711",
    "sg:province":"Nordrhein-Westfalen",
    "wof:name":"Reiseinsel Ohg",
    "wof:placetype":"venue"
},
  "geometry": {"coordinates":[7.3389649391,51.649974823],"type":"Point"}
}