{
  "type": "Feature",
  "properties": {
    "iso:country":"DE",
    "sg:address":"Boerholz 65",
    "sg:city":"Br\u00fcggen",
    "sg:phone":"+49 2157/871687",
    "sg:postcode":"41379",
    "sg:province":"Nordrhein-Westfalen",
    "wof:name":"Gvb - Grundbesitz Verwaltungs- Und Beratungs Gmbh",
    "wof:placetype":"venue"
},
  "geometry": {"coordinates":[6.221449852,51.2767753601],"type":"Point"}
}