{
  "type": "Feature",
  "properties": {
    "iso:country":"DE",
    "sg:address":"Franz-Savels-Str. 39",
    "sg:city":"Gangelt",
    "sg:phone":"+49 2454/1080",
    "sg:postcode":"52538",
    "sg:province":"Nordrhein-Westfalen",
    "wof:name":"Rene Stegemann",
    "wof:placetype":"venue"
},
  "geometry": {"coordinates":[5.9931650162,50.9881668091],"type":"Point"}
}