{
  "type": "Feature",
  "properties": {
    "iso:country":"DE",
    "sg:address":"Im Mitterfeld 5",
    "sg:city":"Taufkirchen",
    "sg:phone":"+49 89/61279287",
    "sg:postcode":"82024",
    "sg:province":"Bayern",
    "wof:name":"Dieter Turra Altbausanierung Gmbh",
    "wof:placetype":"venue"
},
  "geometry": {"coordinates":[11.622234,48.041126],"type":"Point"}
}