{
  "type": "Feature",
  "properties": {
    "iso:country":"DE",
    "sg:address":"Solothurner Weg 4",
    "sg:city":"K\u00f6ln",
    "sg:phone":"+49 221/645101",
    "sg:postcode":"51063",
    "sg:province":"Nordrhein-Westfalen",
    "wof:name":"Georg Neumann",
    "wof:placetype":"venue"
},
  "geometry": {"coordinates":[7.009596,50.981884],"type":"Point"}
}