{
  "type": "Feature",
  "properties": {
    "iso:country":"DE",
    "sg:address":"Rolandstr. 58",
    "sg:city":"Aachen",
    "sg:phone":"+49 241/152342",
    "sg:postcode":"52070",
    "sg:province":"Nordrhein-Westfalen",
    "wof:name":"G\u00fcnter Verhufen",
    "wof:placetype":"venue"
},
  "geometry": {"coordinates":[6.093848,50.785748],"type":"Point"}
}