{
  "type": "Feature",
  "properties": {
    "iso:country":"DE",
    "sg:address":"Lippst\u00e4dter Str. 75",
    "sg:city":"Langenberg",
    "sg:phone":"+49 5248/368",
    "sg:postcode":"33449",
    "sg:province":"Nordrhein-Westfalen",
    "wof:name":"Kr\u00e4henhorst Baugesch\u00e4ft Gmbh",
    "wof:placetype":"venue"
},
  "geometry": {"coordinates":[8.3239164352,51.7733688354],"type":"Point"}
}