{
  "type": "Feature",
  "properties": {
    "iso:country":"DE",
    "sg:address":"M\u00fchlwiesenstr. 26",
    "sg:city":"Filderstadt",
    "sg:phone":"+49 7158/69775",
    "sg:postcode":"70794",
    "sg:province":"Baden-W\u00fcrttemberg",
    "wof:name":"Getr\u00e4nke Schweizer Gmbh",
    "wof:placetype":"venue"
},
  "geometry": {"coordinates":[9.2296676636,48.6734352112],"type":"Point"}
}