{
  "type": "Feature",
  "properties": {
    "iso:country":"DE",
    "sg:address":"Hauptstr. 21",
    "sg:city":"Helbra",
    "sg:phone":"+49 34772/27380",
    "sg:postcode":"06311",
    "sg:province":"Sachsen-Anhalt",
    "wof:name":"Smr Helbra Ingenieurgesellschaft Mbh",
    "wof:placetype":"venue"
},
  "geometry": {"coordinates":[11.4872045517,51.5526809692],"type":"Point"}
}