{
  "type": "Feature",
  "properties": {
    "iso:country":"DE",
    "sg:address":"Lehmker Str. 1",
    "sg:city":"Uelzen",
    "sg:phone":"+49 5804/970010",
    "sg:postcode":"29525",
    "sg:province":"Niedersachsen",
    "wof:name":"Dieter Licht",
    "wof:placetype":"venue"
},
  "geometry": {"coordinates":[10.6687049866,52.9570846558],"type":"Point"}
}