{
  "type": "Feature",
  "properties": {
    "iso:country":"DE",
    "sg:address":"blasewitzer Str. 41",
    "sg:city":"dresden",
    "sg:phone":"+49 351/4504440",
    "sg:postcode":"01307",
    "sg:province":"Sachsen",
    "wof:name":"Tip-per-news",
    "wof:placetype":"venue"
},
  "geometry": {"coordinates":[13.780168,51.053284],"type":"Point"}
}