{
  "type": "Feature",
  "properties": {
    "iso:country":"DE",
    "sg:address":"Marienring 18",
    "sg:city":"Landau",
    "sg:phone":"+49 6341/80817",
    "sg:postcode":"76829",
    "sg:province":"Rheinland-Pfalz",
    "wof:name":"Heuberger Verwaltungs Gmbh",
    "wof:placetype":"venue"
},
  "geometry": {"coordinates":[8.11801,49.194328],"type":"Point"}
}