{
  "type": "Feature",
  "properties": {
    "iso:country":"DE",
    "sg:address":"Domstr. 40",
    "sg:city":"Greifswald",
    "sg:phone":"+49 3834/799143",
    "sg:postcode":"17489",
    "sg:province":"Mecklenburg-Vorpommern",
    "wof:name":"Caruso",
    "wof:placetype":"venue"
},
  "geometry": {"coordinates":[13.3813657761,54.0949554443],"type":"Point"}
}