{
  "type": "Feature",
  "properties": {
    "iso:country":"DE",
    "sg:address":"Iverslund 7",
    "sg:city":"S\u00f6rup",
    "sg:phone":"+49 4635/2287",
    "sg:postcode":"24966",
    "sg:province":"Schleswig-Holstein",
    "wof:name":"Tewa Betonwerk- Und Naturstein Gmbh",
    "wof:placetype":"venue"
},
  "geometry": {"coordinates":[9.6751890182,54.725315094],"type":"Point"}
}