{
  "type": "Feature",
  "properties": {
    "iso:country":"DE",
    "sg:address":"St.-Josef-Spital-Str. 5",
    "sg:city":"Oberaudorf",
    "sg:phone":"+49 8033/2551",
    "sg:postcode":"83080",
    "sg:province":"Bayern",
    "wof:name":"Kath. \u00d6ffentliche Bibliothek Kath. Pfarramt",
    "wof:placetype":"venue"
},
  "geometry": {"coordinates":[12.17124,47.646252],"type":"Point"}
}