{
  "type": "Feature",
  "properties": {
    "iso:country":"DE",
    "sg:address":"Burgstr. 19",
    "sg:city":"Halle",
    "sg:phone":"+49 345/2030872",
    "sg:postcode":"06114",
    "sg:province":"Sachsen-Anhalt",
    "wof:name":"Dieter Breidenbach",
    "wof:placetype":"venue"
},
  "geometry": {"coordinates":[11.955619812,51.4985198975],"type":"Point"}
}