{
  "type": "Feature",
  "properties": {
    "iso:country":"DE",
    "sg:address":"Ebertstr. 49",
    "sg:city":"Bergkamen",
    "sg:phone":"+49 2307/80232",
    "sg:postcode":"59192",
    "sg:province":"Nordrhein-Westfalen",
    "wof:name":"Lange Und Heinz Rechtsanw\u00e4lte Und Notar",
    "wof:placetype":"venue"
},
  "geometry": {"coordinates":[7.6352109909,51.615196228],"type":"Point"}
}