{
  "type": "Feature",
  "properties": {
    "iso:country":"DE",
    "sg:address":"M\u00fcnstermannweg 11",
    "sg:city":"M\u00fcnster",
    "sg:phone":"+49 251/797877",
    "sg:postcode":"48153",
    "sg:province":"Nordrhein-Westfalen",
    "wof:name":"Dr. Heiko Delorme Tierarzt",
    "wof:placetype":"venue"
},
  "geometry": {"coordinates":[7.6265039444,51.9399185181],"type":"Point"}
}