{
  "type": "Feature",
  "properties": {
    "iso:country":"DE",
    "sg:address":"Humboldtstr. 9",
    "sg:city":"N\u00fcrnberg",
    "sg:phone":"+49 911/411423",
    "sg:postcode":"90443",
    "sg:province":"Bayern",
    "wof:name":"Kirby",
    "wof:placetype":"venue"
},
  "geometry": {"coordinates":[11.068824,49.436951],"type":"Point"}
}