{
  "type": "Feature",
  "properties": {
    "iso:country":"DE",
    "sg:address":"Saarbr\u00fccker Str. 6",
    "sg:city":"Lauterecken",
    "sg:phone":"+49 6382/3367",
    "sg:postcode":"67742",
    "sg:province":"Rheinland-Pfalz",
    "wof:name":"Uwe Ulrich Gmbh",
    "wof:placetype":"venue"
},
  "geometry": {"coordinates":[7.5902757645,49.6557655334],"type":"Point"}
}