{
  "type": "Feature",
  "properties": {
    "iso:country":"DE",
    "sg:address":"M\u00fchlweg 3",
    "sg:city":"Laichingen",
    "sg:phone":"+49 7333/21164",
    "sg:postcode":"89150",
    "sg:province":"Baden-W\u00fcrttemberg",
    "wof:name":"Gregor Kg",
    "wof:placetype":"venue"
},
  "geometry": {"coordinates":[9.6927433014,48.4954299927],"type":"Point"}
}