{
  "type": "Feature",
  "properties": {
    "iso:country":"DE",
    "sg:address":"Kleine Gasse 87",
    "sg:city":"Breitenstein",
    "sg:phone":"+49 34654/793",
    "sg:postcode":"06547",
    "sg:province":"Sachsen-Anhalt",
    "wof:name":"Pension Goldener Hirsch",
    "wof:placetype":"venue"
},
  "geometry": {"coordinates":[10.9475698471,51.6196212769],"type":"Point"}
}