{
  "type": "Feature",
  "properties": {
    "iso:country":"DE",
    "sg:address":"Fasanenweg 31",
    "sg:city":"Finsing",
    "sg:phone":"+49 8123/1243",
    "sg:postcode":"85464",
    "sg:province":"Bayern",
    "wof:name":"Johann Mair",
    "wof:placetype":"venue"
},
  "geometry": {"coordinates":[11.789448,48.23156],"type":"Point"}
}