{
  "type": "Feature",
  "properties": {
    "iso:country":"DE",
    "sg:address":"Im Wildfang 3",
    "sg:city":"Saarbr\u00fccken",
    "sg:phone":"+49 6893/1307",
    "sg:postcode":"66131",
    "sg:province":"Saarland",
    "wof:name":"G\u00fcnther Walter",
    "wof:placetype":"venue"
},
  "geometry": {"coordinates":[7.105506,49.19735],"type":"Point"}
}