{
  "type": "Feature",
  "properties": {
    "iso:country":"DE",
    "sg:address":"Kramerstr. 5",
    "sg:city":"Memmingen",
    "sg:phone":"+49 8331/983538",
    "sg:postcode":"87700",
    "sg:province":"Bayern",
    "wof:name":"Zeile",
    "wof:placetype":"venue"
},
  "geometry": {"coordinates":[10.1810045242,47.9861450195],"type":"Point"}
}