{
  "type": "Feature",
  "properties": {
    "iso:country":"DE",
    "sg:address":"Auf der Schulbrede 18",
    "sg:city":"Paderborn",
    "sg:postcode":"33098",
    "sg:province":"Nordrhein-Westfalen",
    "wof:name":"Baugenossenschaft Post Und Telegraphie Eg",
    "wof:placetype":"venue"
},
  "geometry": {"coordinates":[8.7688894272,51.714176178],"type":"Point"}
}