{
  "type": "Feature",
  "properties": {
    "iso:country":"DE",
    "sg:address":"Ritterstr. 32",
    "sg:city":"K\u00f6ln",
    "sg:phone":"+49 221/133733",
    "sg:postcode":"50668",
    "sg:province":"Nordrhein-Westfalen",
    "wof:name":"W. Salcher",
    "wof:placetype":"venue"
},
  "geometry": {"coordinates":[6.9520459175,50.9476051331],"type":"Point"}
}