{
  "type": "Feature",
  "properties": {
    "iso:country":"DE",
    "sg:address":"Kothigenbibersbach",
    "sg:city":"Thiersheim",
    "sg:phone":"+49 9233/9670",
    "sg:postcode":"95707",
    "sg:province":"Bayern",
    "wof:name":"Roland Kastner",
    "wof:placetype":"venue"
},
  "geometry": {"coordinates":[12.1585645676,50.0810203552],"type":"Point"}
}