{
  "type": "Feature",
  "properties": {
    "iso:country":"DE",
    "sg:address":"Randstr. 72",
    "sg:city":"Hamburg",
    "sg:phone":"+49 40/543281",
    "sg:postcode":"22525",
    "sg:province":"Hamburg",
    "wof:name":"Big Belitz Gmbh",
    "wof:placetype":"venue"
},
  "geometry": {"coordinates":[9.922744,53.588604],"type":"Point"}
}