{
  "type": "Feature",
  "properties": {
    "iso:country":"DE",
    "sg:address":"St.-Ansgar-Str. 2 a",
    "sg:city":"Minden",
    "sg:phone":"+49 571/62646",
    "sg:postcode":"32425",
    "sg:province":"Nordrhein-Westfalen",
    "wof:name":"Huk-coburg",
    "wof:placetype":"venue"
},
  "geometry": {"coordinates":[8.8965320587,52.3079376221],"type":"Point"}
}