{
  "type": "Feature",
  "properties": {
    "iso:country":"DE",
    "sg:address":"Poststr. 15",
    "sg:city":"Bad Kreuznach",
    "sg:phone":"+49 671/4820499",
    "sg:postcode":"55545",
    "sg:province":"Rheinland-Pfalz",
    "wof:name":"Pontis Bistro",
    "wof:placetype":"venue"
},
  "geometry": {"coordinates":[7.8570389748,49.8470954895],"type":"Point"}
}