{
  "type": "Feature",
  "properties": {
    "iso:country":"DE",
    "sg:address":"Kippingstr. 24",
    "sg:city":"Hamburg",
    "sg:phone":"+49 40/447751",
    "sg:postcode":"20144",
    "sg:province":"Hamburg",
    "wof:name":"Friedrich A.j. Bostelmann Gmbh",
    "wof:placetype":"venue"
},
  "geometry": {"coordinates":[9.972883,53.570889],"type":"Point"}
}