{
  "type": "Feature",
  "properties": {
    "iso:country":"DE",
    "sg:address":"Heinrich-Heine-Str. 12",
    "sg:city":"Demitz-Thumitz",
    "sg:postcode":"01877",
    "sg:province":"Sachsen",
    "wof:name":"Gemeinn\u00fctzige Wohnungsgenossenschaft Eg",
    "wof:placetype":"venue"
},
  "geometry": {"coordinates":[14.2423629761,51.143157959],"type":"Point"}
}