{
  "type": "Feature",
  "properties": {
    "iso:country":"DE",
    "sg:address":"Beim Andreasbrunnen 2",
    "sg:city":"Hamburg",
    "sg:phone":"+49 40/476247",
    "sg:postcode":"20249",
    "sg:province":"Hamburg",
    "wof:name":"Dr. Siemsgl\u00dcssvitachemie Gmbh",
    "wof:placetype":"venue"
},
  "geometry": {"coordinates":[9.98532,53.586044],"type":"Point"}
}