{
  "type": "Feature",
  "properties": {
    "iso:country":"DE",
    "sg:address":"Leonberger Str. 25",
    "sg:city":"Ludwigsburg",
    "sg:phone":"+49 7141/923154",
    "sg:postcode":"71638",
    "sg:province":"Baden-W\u00fcrttemberg",
    "wof:name":"Kurt Vogel",
    "wof:placetype":"venue"
},
  "geometry": {"coordinates":[9.1907281876,48.8908805847],"type":"Point"}
}