{
  "type": "Feature",
  "properties": {
    "iso:country":"DE",
    "sg:address":"Carl-Theodor-Str. 8",
    "sg:city":"Schwetzingen",
    "sg:phone":"+49 6202/3001",
    "sg:postcode":"68723",
    "sg:province":"Baden-W\u00fcrttemberg",
    "wof:name":"Die Eisenecke Theodor Wirsing",
    "wof:placetype":"venue"
},
  "geometry": {"coordinates":[8.5750341415,49.3844833374],"type":"Point"}
}