{
  "type": "Feature",
  "properties": {
    "iso:country":"DE",
    "sg:address":"Blumenstr. 26",
    "sg:city":"Tespe",
    "sg:phone":"+49 4176/7739",
    "sg:postcode":"21395",
    "sg:province":"Niedersachsen",
    "wof:name":"Larralde Transport Gmbh",
    "wof:placetype":"venue"
},
  "geometry": {"coordinates":[10.4214048386,53.3907165527],"type":"Point"}
}