{
  "type": "Feature",
  "properties": {
    "iso:country":"DE",
    "sg:address":"Backhaushohl 6",
    "sg:city":"Mainz",
    "sg:phone":"+49 6131/34526",
    "sg:postcode":"55128",
    "sg:province":"Rheinland-Pfalz",
    "wof:name":"Kath. Pfarramt St. Achatus",
    "wof:placetype":"venue"
},
  "geometry": {"coordinates":[8.2529020309,49.988483429],"type":"Point"}
}