{
  "type": "Feature",
  "properties": {
    "iso:country":"DE",
    "sg:address":"Bergwerkstr. 38",
    "sg:city":"Berchtesgaden",
    "sg:phone":"+49 8652/2156",
    "sg:postcode":"83471",
    "sg:province":"Bayern",
    "wof:name":"Franz Konrad",
    "wof:placetype":"venue"
},
  "geometry": {"coordinates":[13.0074892044,47.6331672668],"type":"Point"}
}