{
  "type": "Feature",
  "properties": {
    "iso:country":"DE",
    "sg:address":"Westendstr. 44",
    "sg:city":"Frankfurt",
    "sg:phone":"+49 69/747894",
    "sg:postcode":"60325",
    "sg:province":"Hessen",
    "wof:name":"Mutual Contracting Gesell- Schaft F\u00fcr Koordination Von",
    "wof:placetype":"venue"
},
  "geometry": {"coordinates":[8.6615495682,50.1138038635],"type":"Point"}
}