{
  "type": "Feature",
  "properties": {
    "iso:country":"DE",
    "sg:address":"Dickenhardtstr 59",
    "sg:city":"Villingen-Schwenningen",
    "sg:phone":"+49 7720/33076",
    "sg:postcode":"78054",
    "sg:province":"Baden-W\u00fcrttemberg",
    "wof:name":"E. Jauch + Sohn Kg",
    "wof:placetype":"venue"
},
  "geometry": {"coordinates":[8.5199050903,48.0521392822],"type":"Point"}
}