{
  "type": "Feature",
  "properties": {
    "iso:country":"DE",
    "sg:address":"Am Graswege 1",
    "sg:city":"Hannover",
    "sg:phone":"+49 511/802408",
    "sg:postcode":"30169",
    "sg:province":"Niedersachsen",
    "wof:name":"Ml Wiesel-druck Russland Gmbh",
    "wof:placetype":"venue"
},
  "geometry": {"coordinates":[9.749776,52.360626],"type":"Point"}
}