{
  "type": "Feature",
  "properties": {
    "iso:country":"DE",
    "sg:address":"Evinger Berg 11",
    "sg:city":"Dortmund",
    "sg:phone":"+49 231/7284030",
    "sg:postcode":"44339",
    "sg:province":"Nordrhein-Westfalen",
    "wof:name":"Peter Pfefferkuch",
    "wof:placetype":"venue"
},
  "geometry": {"coordinates":[7.453274,51.551186],"type":"Point"}
}