{
  "type": "Feature",
  "properties": {
    "iso:country":"DE",
    "sg:address":"In der Mutte 1",
    "sg:city":"Witten",
    "sg:phone":"+49 2302/73406",
    "sg:postcode":"58456",
    "sg:province":"Nordrhein-Westfalen",
    "wof:name":"Holz & Kunststofftechnik Gerd Finkensiep Gmbh & Co. Kg",
    "wof:placetype":"venue"
},
  "geometry": {"coordinates":[7.286838,51.388218],"type":"Point"}
}