{
  "type": "Feature",
  "properties": {
    "iso:country":"DE",
    "sg:address":"G\u00e4rtnerstr. 2",
    "sg:city":"L\u00fcbbecke",
    "sg:phone":"+49 5741/4166",
    "sg:postcode":"32312",
    "sg:province":"Nordrhein-Westfalen",
    "wof:name":"Heinrich Bode",
    "wof:placetype":"venue"
},
  "geometry": {"coordinates":[8.565555,52.303478],"type":"Point"}
}