{
  "type": "Feature",
  "properties": {
    "iso:country":"DE",
    "sg:address":"Taunusstr. 15",
    "sg:city":"Geisenheim",
    "sg:phone":"+49 6722/8180",
    "sg:postcode":"65366",
    "sg:province":"Hessen",
    "wof:name":"R. Sohns",
    "wof:placetype":"venue"
},
  "geometry": {"coordinates":[7.9720029831,49.9885025024],"type":"Point"}
}