{
  "type": "Feature",
  "properties": {
    "iso:country":"DE",
    "sg:address":"Gie\u00dferstr. 53",
    "sg:city":"Leipzig",
    "sg:phone":"+49 341/4247743",
    "sg:postcode":"04229",
    "sg:province":"Sachsen",
    "wof:name":"Dr. Med. Dieter Maiwald",
    "wof:placetype":"venue"
},
  "geometry": {"coordinates":[12.3264980316,51.3219642639],"type":"Point"}
}