{
  "type": "Feature",
  "properties": {
    "iso:country":"DE",
    "sg:address":"Mariannenthaler Str. 5",
    "sg:city":"Sulzbach",
    "sg:phone":"+49 6897/87597",
    "sg:postcode":"66280",
    "sg:province":"Saarland",
    "wof:name":"H. G\u00f6ttel",
    "wof:placetype":"venue"
},
  "geometry": {"coordinates":[7.084017,49.307281],"type":"Point"}
}