{
  "type": "Feature",
  "properties": {
    "iso:country":"DE",
    "sg:address":"kanalstrasse9",
    "sg:city":"hamburg",
    "sg:postcode":"22085",
    "sg:province":"Hamburg",
    "wof:name":"Phatmusic",
    "wof:placetype":"venue"
},
  "geometry": {"coordinates":[10.01578,53.572109],"type":"Point"}
}