{
  "type": "Feature",
  "properties": {
    "iso:country":"DE",
    "sg:address":"Zusamstrasse 27",
    "sg:city":"Villenbach",
    "sg:phone":"+49 8296/909605",
    "sg:postcode":"86637",
    "sg:province":"Bayern",
    "wof:name":"Profinal Schmierstoffe - Spezial Schmierstoffe",
    "wof:placetype":"venue"
},
  "geometry": {"coordinates":[10.606641,48.497715],"type":"Point"}
}