{
  "type": "Feature",
  "properties": {
    "iso:country":"DE",
    "sg:address":"Taunusstr. 3 A",
    "sg:city":"Eppstein",
    "sg:postcode":"65817",
    "sg:province":"Hessen",
    "wof:name":"Freund Gmbh & Co. Kg",
    "wof:placetype":"venue"
},
  "geometry": {"coordinates":[8.377689,50.147537],"type":"Point"}
}