{
  "type": "Feature",
  "properties": {
    "iso:country":"DE",
    "sg:address":"S\u00fcdstr. 33",
    "sg:city":"Rietberg",
    "sg:phone":"+49 2944/6216",
    "sg:postcode":"33397",
    "sg:province":"Nordrhein-Westfalen",
    "wof:name":"Hans Wiesbrock",
    "wof:placetype":"venue"
},
  "geometry": {"coordinates":[8.38531,51.718288],"type":"Point"}
}