{
  "type": "Feature",
  "properties": {
    "iso:country":"DE",
    "sg:address":"Friedensstr. 17",
    "sg:city":"Laucha",
    "sg:phone":"+49 3622/902888",
    "sg:postcode":"99880",
    "sg:province":"Th\u00fcringen",
    "wof:name":"Zum Lauchatal",
    "wof:placetype":"venue"
},
  "geometry": {"coordinates":[10.5434732437,50.9268035889],"type":"Point"}
}