{
  "type": "Feature",
  "properties": {
    "iso:country":"DE",
    "sg:address":"Mechersstr. 290",
    "sg:city":"St. Wendel",
    "sg:postcode":"66606",
    "sg:province":"Saarland",
    "wof:name":"Norbert Hassel",
    "wof:placetype":"venue"
},
  "geometry": {"coordinates":[7.0979590416,49.4724464417],"type":"Point"}
}