{
  "type": "Feature",
  "properties": {
    "iso:country":"DE",
    "sg:address":"Mushardstr. 14",
    "sg:city":"Bremerhaven",
    "sg:phone":"+49 471/33051",
    "sg:postcode":"27570",
    "sg:province":"Bremen",
    "wof:name":"Karl Lenz Gmbh",
    "wof:placetype":"venue"
},
  "geometry": {"coordinates":[8.592075,53.528866],"type":"Point"}
}