{
  "type": "Feature",
  "properties": {
    "iso:country":"DE",
    "sg:address":"Mittelallee 4",
    "sg:city":"Strausberg",
    "sg:phone":"+49 3341/27739",
    "sg:postcode":"15344",
    "sg:province":"Brandenburg",
    "wof:name":"Heinz Eisemann Elektro",
    "wof:placetype":"venue"
},
  "geometry": {"coordinates":[13.89282,52.571835],"type":"Point"}
}