{
  "type": "Feature",
  "properties": {
    "iso:country":"DE",
    "sg:address":"Magdeburger Str. 1",
    "sg:city":"Oebisfelde",
    "sg:phone":"+49 39002/43637",
    "sg:postcode":"39646",
    "sg:province":"Sachsen-Anhalt",
    "wof:name":"Kaisers Markt",
    "wof:placetype":"venue"
},
  "geometry": {"coordinates":[10.9857273102,52.429233551],"type":"Point"}
}