{
  "type": "Feature",
  "properties": {
    "iso:country":"DE",
    "sg:address":"Seelower Str. 12",
    "sg:city":"Berlin",
    "sg:phone":"+49 30/4459900",
    "sg:postcode":"10439",
    "sg:province":"Berlin",
    "wof:name":"Peter Pretzel",
    "wof:placetype":"venue"
},
  "geometry": {"coordinates":[13.4110546112,52.5529899597],"type":"Point"}
}