{
  "type": "Feature",
  "properties": {
    "iso:country":"DE",
    "sg:address":"Hohenzollernstra\u00dfe 32-34",
    "sg:city":"Gelsenkirchen",
    "sg:phone":"+49 209/272737",
    "sg:postcode":"45888",
    "sg:province":"Nordrhein-Westfalen",
    "wof:name":"Der B\u00fcrger-sch\u00fctzenverein Bulmke-h\u00fcllen 1900 E.v.",
    "wof:placetype":"venue"
},
  "geometry": {"coordinates":[7.11192,51.511154],"type":"Point"}
}