{
  "type": "Feature",
  "properties": {
    "iso:country":"DE",
    "sg:address":"Oberer Anger 18",
    "sg:city":"Aerzen",
    "sg:phone":"+49 5154/603",
    "sg:postcode":"31855",
    "sg:province":"Niedersachsen",
    "wof:name":"Kurt Meyer",
    "wof:placetype":"venue"
},
  "geometry": {"coordinates":[9.205882,52.012669],"type":"Point"}
}