{
  "type": "Feature",
  "properties": {
    "iso:country":"DE",
    "sg:address":"Unionstr. 8",
    "sg:city":"Wuppertal",
    "sg:phone":"+49 202/80111",
    "sg:postcode":"42285",
    "sg:province":"Nordrhein-Westfalen",
    "wof:name":"Heinz Behrens Steuerberater",
    "wof:placetype":"venue"
},
  "geometry": {"coordinates":[7.1753649712,51.2615509033],"type":"Point"}
}