{
  "type": "Feature",
  "properties": {
    "iso:country":"DE",
    "sg:address":"Borgfelder Landstr. 4",
    "sg:city":"Bremen",
    "sg:phone":"+49 421/270135",
    "sg:postcode":"28357",
    "sg:province":"Bremen",
    "wof:name":"Heinz-adolf Klatte",
    "wof:placetype":"venue"
},
  "geometry": {"coordinates":[8.90858,53.127171],"type":"Point"}
}