{
  "type": "Feature",
  "properties": {
    "iso:country":"DE",
    "sg:address":"Lortzingstr. 16",
    "sg:city":"Langen",
    "sg:phone":"+49 4961/0379078",
    "sg:postcode":"63225",
    "sg:province":"Hessen",
    "wof:name":"Carl Kiesel Vertriebs Kg",
    "wof:placetype":"venue"
},
  "geometry": {"coordinates":[8.652608,49.987083],"type":"Point"}
}