{
  "type": "Feature",
  "properties": {
    "iso:country":"DE",
    "sg:address":"Adolphstr. 36",
    "sg:city":"K\u00f6ln",
    "sg:phone":"+49 221/882946",
    "sg:postcode":"50679",
    "sg:province":"Nordrhein-Westfalen",
    "wof:name":"Wolfgang Abeln",
    "wof:placetype":"venue"
},
  "geometry": {"coordinates":[6.9763159752,50.9351882935],"type":"Point"}
}