{
  "type": "Feature",
  "properties": {
    "iso:country":"DE",
    "sg:address":"Reuterstr. 56",
    "sg:city":"Leverkusen",
    "sg:phone":"+49 214/55333",
    "sg:postcode":"51375",
    "sg:province":"Nordrhein-Westfalen",
    "wof:name":"Kruse & Herweg- Verwaltungsgesellschaft Mbh",
    "wof:placetype":"venue"
},
  "geometry": {"coordinates":[7.041715,51.028084],"type":"Point"}
}