{
  "type": "Feature",
  "properties": {
    "iso:country":"DE",
    "sg:address":"Gluckstr. 27",
    "sg:city":"Frankfurt",
    "sg:phone":"+49 69/5962053",
    "sg:postcode":"60318",
    "sg:province":"Hessen",
    "wof:name":"Film- Und Fernsehwerbung- Fife Gmbh",
    "wof:placetype":"venue"
},
  "geometry": {"coordinates":[8.6876459122,50.1273765564],"type":"Point"}
}