{
  "type": "Feature",
  "properties": {
    "iso:country":"DE",
    "sg:address":"Hauptstr. 226",
    "sg:city":"Neukirchen",
    "sg:phone":"+49 371/221819",
    "sg:postcode":"09221",
    "sg:province":"Sachsen",
    "wof:name":"Dieter Gr\u00fcndel",
    "wof:placetype":"venue"
},
  "geometry": {"coordinates":[12.840562,50.789764],"type":"Point"}
}