{
  "type": "Feature",
  "properties": {
    "iso:country":"DE",
    "sg:address":"Luisenweg 40",
    "sg:city":"Hamburg",
    "sg:phone":"+49 40/258825",
    "sg:postcode":"20537",
    "sg:province":"Hamburg",
    "wof:name":"Schaller & Brandes Gmbh",
    "wof:placetype":"venue"
},
  "geometry": {"coordinates":[10.0478,53.551006],"type":"Point"}
}