{
  "type": "Feature",
  "properties": {
    "iso:country":"DE",
    "sg:address":"Bachstr. 28",
    "sg:city":"S\u00fcderbrarup",
    "sg:phone":"+49 4641/2555",
    "sg:postcode":"24392",
    "sg:province":"Schleswig-Holstein",
    "wof:name":"Gerlinde Leidt Masseurin",
    "wof:placetype":"venue"
},
  "geometry": {"coordinates":[9.77653,54.640743],"type":"Point"}
}