{
  "type": "Feature",
  "properties": {
    "iso:country":"DE",
    "sg:address":"Panoramastr 17",
    "sg:city":"Moosbach",
    "sg:phone":"+49 8376/974028",
    "sg:postcode":"87477",
    "sg:province":"Bayern",
    "wof:name":"Delphin-brunnen.de",
    "wof:placetype":"venue"
},
  "geometry": {"coordinates":[10.3605337143,47.641254425],"type":"Point"}
}