{
  "type": "Feature",
  "properties": {
    "iso:country":"DE",
    "sg:address":"Akazienstr. 3",
    "sg:city":"Magdeburg",
    "sg:phone":"+49 391/5095870",
    "sg:postcode":"39126",
    "sg:province":"Sachsen-Anhalt",
    "wof:name":"Dieter Schuchardt",
    "wof:placetype":"venue"
},
  "geometry": {"coordinates":[11.662998,52.184586],"type":"Point"}
}