{
  "type": "Feature",
  "properties": {
    "iso:country":"DE",
    "sg:address":"Am Escheugraben 20",
    "sg:city":"Neu-Ulm",
    "sg:phone":"+49 731/974380",
    "sg:postcode":"89231",
    "sg:province":"Bayern",
    "wof:name":"Altenheim St. Albertus-magnus",
    "wof:placetype":"venue"
},
  "geometry": {"coordinates":[10.006522,48.386486],"type":"Point"}
}