{
  "type": "Feature",
  "properties": {
    "iso:country":"DE",
    "sg:address":"Petersbergstr. 31",
    "sg:city":"Rosenheim",
    "sg:phone":"+49 8031/43586",
    "sg:postcode":"83026",
    "sg:province":"Bayern",
    "wof:name":"Tecnia Import-export Atef Mari",
    "wof:placetype":"venue"
},
  "geometry": {"coordinates":[12.1114501953,47.8483695984],"type":"Point"}
}