{
  "type": "Feature",
  "properties": {
    "iso:country":"DE",
    "sg:address":"Falckenbergstr. 1",
    "sg:city":"Emmering",
    "sg:phone":"+49 8141/44400",
    "sg:postcode":"82275",
    "sg:province":"Bayern",
    "wof:name":"Gerhard Gerstberger",
    "wof:placetype":"venue"
},
  "geometry": {"coordinates":[11.2760190964,48.1878356934],"type":"Point"}
}