{
  "type": "Feature",
  "properties": {
    "iso:country":"DE",
    "sg:address":"Larstr. 154",
    "sg:city":"Troisdorf",
    "sg:phone":"+49 2241/409735",
    "sg:postcode":"53844",
    "sg:province":"Nordrhein-Westfalen",
    "wof:name":"Hans Tombers",
    "wof:placetype":"venue"
},
  "geometry": {"coordinates":[7.127534,50.799114],"type":"Point"}
}