{
  "type": "Feature",
  "properties": {
    "iso:country":"DE",
    "sg:address":"Plauensche Str. 34",
    "sg:city":"Werdau",
    "sg:phone":"+49 3761/2528",
    "sg:postcode":"08412",
    "sg:province":"Sachsen",
    "wof:name":"M. Wohlrath",
    "wof:placetype":"venue"
},
  "geometry": {"coordinates":[12.374376297,50.7291870117],"type":"Point"}
}