{
  "type": "Feature",
  "properties": {
    "iso:country":"DE",
    "sg:address":"Kupferdreher Str. 144",
    "sg:city":"Essen",
    "sg:phone":"+49 201/483707",
    "sg:postcode":"45257",
    "sg:province":"Nordrhein-Westfalen",
    "wof:name":"Lady-chic Dietrich Textil-gmbh",
    "wof:placetype":"venue"
},
  "geometry": {"coordinates":[7.082144,51.392509],"type":"Point"}
}