{
  "type": "Feature",
  "properties": {
    "iso:country":"DE",
    "sg:address":"Saarpfalzstr.13",
    "sg:city":"Mandelbachtal",
    "sg:phone":"+49 6803",
    "sg:postcode":"66399",
    "sg:province":"Saarland",
    "wof:name":"Architekturb\u00fcro Alfred Toussaint Architekt Aks",
    "wof:placetype":"venue"
},
  "geometry": {"coordinates":[7.1618061066,49.2188072205],"type":"Point"}
}