{
  "type": "Feature",
  "properties": {
    "iso:country":"DE",
    "sg:address":"Waldmeisterring 13",
    "sg:city":"Mannheim",
    "sg:phone":"+49 621/758430",
    "sg:postcode":"68305",
    "sg:province":"Baden-W\u00fcrttemberg",
    "wof:name":"Karl D\u00f6ringers Backhaus",
    "wof:placetype":"venue"
},
  "geometry": {"coordinates":[8.509951,49.533245],"type":"Point"}
}