{
  "type": "Feature",
  "properties": {
    "iso:country":"DE",
    "sg:address":"D\u00fcnenstr. 3 b",
    "sg:city":"Ostseebad Binz",
    "sg:postcode":"18609",
    "sg:province":"Mecklenburg-Vorpommern",
    "wof:name":"Ohlhoff",
    "wof:placetype":"venue"
},
  "geometry": {"coordinates":[13.6082201004,54.4029693604],"type":"Point"}
}