{
  "type": "Feature",
  "properties": {
    "iso:country":"DE",
    "sg:address":"Amperstr. 7a",
    "sg:city":"Rosenheim",
    "sg:phone":"+49 8031",
    "sg:postcode":"83026",
    "sg:province":"Bayern",
    "wof:name":"Re/max Rosenheim/simssee",
    "wof:placetype":"venue"
},
  "geometry": {"coordinates":[12.1334981918,47.8413047791],"type":"Point"}
}