{
  "type": "Feature",
  "properties": {
    "iso:country":"DE",
    "sg:address":"Tisinstr. 52",
    "sg:city":"Deisenhofen",
    "sg:phone":"+49 89/6132345",
    "sg:postcode":"82041",
    "sg:province":"Bayern",
    "wof:name":"Kunze-k\u00fchlk\u00f6rper Gmbh",
    "wof:placetype":"venue"
},
  "geometry": {"coordinates":[11.591331,48.019154],"type":"Point"}
}