{
  "type": "Feature",
  "properties": {
    "iso:country":"DE",
    "sg:address":"Eberswalder Chaussee 3",
    "sg:city":"Waldsieversdorf",
    "sg:phone":"+49 33436/35298",
    "sg:postcode":"15377",
    "sg:province":"Brandenburg",
    "wof:name":"H. M\u00fcller",
    "wof:placetype":"venue"
},
  "geometry": {"coordinates":[14.0567169189,52.5401535034],"type":"Point"}
}