{
  "type": "Feature",
  "properties": {
    "iso:country":"DE",
    "sg:address":"Dubbenwinkel 7",
    "sg:city":"Hamburg",
    "sg:phone":"+49 40/7960669",
    "sg:postcode":"21147",
    "sg:province":"Hamburg",
    "wof:name":"H. Facklam",
    "wof:placetype":"venue"
},
  "geometry": {"coordinates":[9.899014,53.474537],"type":"Point"}
}