{
  "type": "Feature",
  "properties": {
    "iso:country":"DE",
    "sg:address":"August-Bebel-Str. 7",
    "sg:city":"Gro\u00df-Gerau",
    "sg:phone":"+49 6152/84626",
    "sg:postcode":"64521",
    "sg:province":"Hessen",
    "wof:name":"Logan Systemberatung Gmbh",
    "wof:placetype":"venue"
},
  "geometry": {"coordinates":[8.4858121872,49.9237365723],"type":"Point"}
}