{
  "type": "Feature",
  "properties": {
    "iso:country":"DE",
    "sg:address":"Gr\u00fcntenstr. 5",
    "sg:city":"Lauben",
    "sg:phone":"+49 8336/81070",
    "sg:postcode":"87761",
    "sg:province":"Bayern",
    "wof:name":"Dieter H\u00e4ring",
    "wof:placetype":"venue"
},
  "geometry": {"coordinates":[10.3144378662,48.0698547363],"type":"Point"}
}