{
  "type": "Feature",
  "properties": {
    "iso:country":"DE",
    "sg:address":"F\u00f6hrenstr. 76-78",
    "sg:city":"Bremen",
    "sg:postcode":"28207",
    "sg:province":"Bremen",
    "wof:name":"Dr. Rigo Trendelburg Grundst\u00fccksverwaltungs- Und",
    "wof:placetype":"venue"
},
  "geometry": {"coordinates":[8.8750762939,53.0612792969],"type":"Point"}
}