{
  "type": "Feature",
  "properties": {
    "iso:country":"DE",
    "sg:address":"Torneestr. 5",
    "sg:city":"Lilienthal",
    "sg:phone":"+49 4942/981036",
    "sg:postcode":"28865",
    "sg:province":"Niedersachsen",
    "wof:name":"Poliboy-werk Emigholz & Brandt Gmbh",
    "wof:placetype":"venue"
},
  "geometry": {"coordinates":[8.901395,53.139927],"type":"Point"}
}