{
  "type": "Feature",
  "properties": {
    "iso:country":"DE",
    "sg:address":"Pastoratstr. 6",
    "sg:city":"H\u00fcrth",
    "sg:phone":"+49 2233/1363",
    "sg:postcode":"50354",
    "sg:province":"Nordrhein-Westfalen",
    "wof:name":"Neuk\u00f6ln Au\u00dfenhandels- Gesellschaft Mbh",
    "wof:placetype":"venue"
},
  "geometry": {"coordinates":[6.866096,50.869015],"type":"Point"}
}