{
  "type": "Feature",
  "properties": {
    "iso:country":"DE",
    "sg:address":"An den Reh\u00e4ckern 27",
    "sg:city":"Kassel",
    "sg:postcode":"34132",
    "sg:province":"Hessen",
    "wof:name":"Dr. Sch\u00f6nberger Gmbh",
    "wof:placetype":"venue"
},
  "geometry": {"coordinates":[9.44733,51.270523],"type":"Point"}
}