{
  "type": "Feature",
  "properties": {
    "iso:country":"DE",
    "sg:address":"Im Kr\u00fcgele 11",
    "sg:city":"Wiernsheim",
    "sg:phone":"+49 7044/8553",
    "sg:postcode":"75446",
    "sg:province":"Baden-W\u00fcrttemberg",
    "wof:name":"Rudolf",
    "wof:placetype":"venue"
},
  "geometry": {"coordinates":[8.8510522842,48.8858947754],"type":"Point"}
}