{
  "type": "Feature",
  "properties": {
    "iso:country":"DE",
    "sg:address":"Verdener Str. 157",
    "sg:city":"Achim",
    "sg:phone":"+49 4202/979197",
    "sg:postcode":"28832",
    "sg:province":"Niedersachsen",
    "wof:name":"Weser-apotheke",
    "wof:placetype":"venue"
},
  "geometry": {"coordinates":[9.08074,52.998096],"type":"Point"}
}