{
  "type": "Feature",
  "properties": {
    "iso:country":"DE",
    "sg:address":"Johann-Brenk-Str. 4",
    "sg:city":"Kulmbach",
    "sg:phone":"+49 9221/908646",
    "sg:postcode":"95326",
    "sg:province":"Bayern",
    "wof:name":"Karl-herold-altenwohnanlage",
    "wof:placetype":"venue"
},
  "geometry": {"coordinates":[11.451868,50.101322],"type":"Point"}
}