{
  "type": "Feature",
  "properties": {
    "iso:country":"DE",
    "sg:address":"Siemensstr 13",
    "sg:city":"Eggenstein-Leopoldshafen",
    "sg:phone":"+49 721/706061",
    "sg:postcode":"76344",
    "sg:province":"Baden-W\u00fcrttemberg",
    "wof:name":"Stolz & Co Gmbh",
    "wof:placetype":"venue"
},
  "geometry": {"coordinates":[8.3897037506,49.0708312988],"type":"Point"}
}