{
  "type": "Feature",
  "properties": {
    "iso:country":"DE",
    "sg:address":"Kreutfeld 44",
    "sg:city":"Gottfrieding",
    "sg:phone":"+49 8731/71876",
    "sg:postcode":"84177",
    "sg:province":"Bayern",
    "wof:name":"Wolfgang Majunke",
    "wof:placetype":"venue"
},
  "geometry": {"coordinates":[12.5265893936,48.6489448547],"type":"Point"}
}