{
  "type": "Feature",
  "properties": {
    "iso:country":"DE",
    "sg:address":"Hochstr. 13",
    "sg:city":"Merdingen",
    "sg:phone":"+49 7668/902388",
    "sg:postcode":"79291",
    "sg:province":"Baden-W\u00fcrttemberg",
    "wof:name":"Herud Kg",
    "wof:placetype":"venue"
},
  "geometry": {"coordinates":[7.6923389435,48.0183105469],"type":"Point"}
}