{
  "type": "Feature",
  "properties": {
    "iso:country":"DE",
    "sg:address":"T\u00fcrkheimer Str. 22",
    "sg:city":"Landau",
    "sg:phone":"+49 6341/30397",
    "sg:postcode":"76829",
    "sg:province":"Rheinland-Pfalz",
    "wof:name":"Ulf-r\u00fcdiger Scholz Innenarchitekt",
    "wof:placetype":"venue"
},
  "geometry": {"coordinates":[8.087461,49.189964],"type":"Point"}
}