{
  "type": "Feature",
  "properties": {
    "iso:country":"DE",
    "sg:address":"Eifelstr. 2",
    "sg:city":"Mainaschaff",
    "sg:phone":"+49 6021/75438",
    "sg:postcode":"63814",
    "sg:province":"Bayern",
    "wof:name":"W. Fries",
    "wof:placetype":"venue"
},
  "geometry": {"coordinates":[9.0938434601,49.9778366089],"type":"Point"}
}