{
  "type": "Feature",
  "properties": {
    "iso:country":"DE",
    "sg:address":"Am Schulfeld 1",
    "sg:city":"Dresden",
    "sg:phone":"+49 351/8804404",
    "sg:postcode":"01109",
    "sg:province":"Sachsen",
    "wof:name":"Wilfried K\u00f6hler",
    "wof:placetype":"venue"
},
  "geometry": {"coordinates":[13.7611503601,51.113609314],"type":"Point"}
}