{
  "type": "Feature",
  "properties": {
    "iso:country":"DE",
    "sg:address":"K\u00e4sterweg 43",
    "sg:city":"Aschaffenburg",
    "sg:phone":"+49 6021/424802",
    "sg:postcode":"63741",
    "sg:province":"Bayern",
    "wof:name":"Egon Haab",
    "wof:placetype":"venue"
},
  "geometry": {"coordinates":[9.1257095337,49.9822502136],"type":"Point"}
}