{
  "type": "Feature",
  "properties": {
    "iso:country":"DE",
    "sg:address":"Harbigstr. 36",
    "sg:city":"B\u00f6blingen",
    "sg:phone":"+49 7031/225259",
    "sg:postcode":"71032",
    "sg:province":"Baden-W\u00fcrttemberg",
    "wof:name":"H. Sch\u00f6ll",
    "wof:placetype":"venue"
},
  "geometry": {"coordinates":[9.0202178955,48.6931114197],"type":"Point"}
}