{
  "type": "Feature",
  "properties": {
    "iso:country":"DE",
    "sg:address":"Friedrich-Ebert-Str. 115",
    "sg:city":"Leuna",
    "sg:phone":"+49 3461/810659",
    "sg:postcode":"06237",
    "sg:province":"Sachsen-Anhalt",
    "wof:name":"Farbenhaus Wendorf",
    "wof:placetype":"venue"
},
  "geometry": {"coordinates":[11.999916,51.332905],"type":"Point"}
}