{
  "type": "Feature",
  "properties": {
    "iso:country":"DE",
    "sg:address":"Landolinusplatz 3",
    "sg:city":"Delbr\u00fcck",
    "sg:phone":"+49 5250/1575",
    "sg:postcode":"33129",
    "sg:province":"Nordrhein-Westfalen",
    "wof:name":"Gastst\u00e4tte H. B. Deppe",
    "wof:placetype":"venue"
},
  "geometry": {"coordinates":[8.5649585724,51.7290878296],"type":"Point"}
}