{
  "type": "Feature",
  "properties": {
    "iso:country":"DE",
    "sg:address":"Welschnonnenstr. 15",
    "sg:city":"Bonn",
    "sg:postcode":"53111",
    "sg:province":"Nordrhein-Westfalen",
    "wof:name":"Kasino- Und Party-service Lohmeier & Deimel Ohg",
    "wof:placetype":"venue"
},
  "geometry": {"coordinates":[7.1014428139,50.7402076721],"type":"Point"}
}