{
  "type": "Feature",
  "properties": {
    "iso:country":"DE",
    "sg:address":"Calwer Str. 30",
    "sg:city":"Calw",
    "sg:phone":"+49 7051/58006",
    "sg:postcode":"75365",
    "sg:province":"Baden-W\u00fcrttemberg",
    "wof:name":"Baugesch\u00e4ft Hans Weber Gmbh & Co. Kg",
    "wof:placetype":"venue"
},
  "geometry": {"coordinates":[8.7352514267,48.7328567505],"type":"Point"}
}