{
  "type": "Feature",
  "properties": {
    "iso:country":"DE",
    "sg:address":"Siegersbusch 19",
    "sg:city":"Wuppertal",
    "sg:phone":"+49 202/781937",
    "sg:postcode":"42327",
    "sg:province":"Nordrhein-Westfalen",
    "wof:name":"Wilh. Willschrei",
    "wof:placetype":"venue"
},
  "geometry": {"coordinates":[7.066461,51.237995],"type":"Point"}
}