{
  "type": "Feature",
  "properties": {
    "iso:country":"DE",
    "sg:address":"Lanenholzersteig 24",
    "sg:city":"Berlin",
    "sg:phone":"+49 37485/67",
    "sg:postcode":"14089",
    "sg:province":"Berlin",
    "wof:name":"Teen Cams Erotik Bilder Amateur Liveshow",
    "wof:placetype":"venue"
},
  "geometry": {"coordinates":[13.142568,52.453018],"type":"Point"}
}