{
  "type": "Feature",
  "properties": {
    "iso:country":"DE",
    "sg:address":"Am Haag 17",
    "sg:city":"Aidhausen",
    "sg:phone":"+49 9526/333",
    "sg:postcode":"97491",
    "sg:province":"Bayern",
    "wof:name":"Adalbert R\u00f6hner",
    "wof:placetype":"venue"
},
  "geometry": {"coordinates":[10.435298,50.155598],"type":"Point"}
}