{
  "type": "Feature",
  "properties": {
    "iso:country":"DE",
    "sg:address":"Adolph-Kolping-Str. 1",
    "sg:city":"Walbeck",
    "sg:phone":"+49 3476/553992",
    "sg:postcode":"06333",
    "sg:province":"Sachsen-Anhalt",
    "wof:name":"Kolping-berufsbildungswerk Hettstedt Ggmbh",
    "wof:placetype":"venue"
},
  "geometry": {"coordinates":[11.4903249741,51.6574401855],"type":"Point"}
}