{
  "type": "Feature",
  "properties": {
    "iso:country":"DE",
    "sg:address":"Kochstr. 22",
    "sg:city":"Berlin",
    "sg:phone":"+49 30/25342900",
    "sg:postcode":"10969",
    "sg:province":"Berlin",
    "wof:name":"Bundesingenieurkammer E. V.",
    "wof:placetype":"venue"
},
  "geometry": {"coordinates":[13.388506,52.506725],"type":"Point"}
}