{
  "type": "Feature",
  "properties": {
    "iso:country":"DE",
    "sg:address":"Ziegelh\u00fctte 3",
    "sg:city":"Pegnitz",
    "sg:phone":"+49 9241/91333",
    "sg:postcode":"91257",
    "sg:province":"Bayern",
    "wof:name":"Lothes Kauz Gmbh",
    "wof:placetype":"venue"
},
  "geometry": {"coordinates":[11.4581079483,49.726020813],"type":"Point"}
}