{
  "type": "Feature",
  "properties": {
    "iso:country":"DE",
    "sg:address":"Lavastr. 7",
    "sg:city":"\u00dcdersdorf",
    "sg:phone":"+49 6596/7132",
    "sg:postcode":"54552",
    "sg:province":"Rheinland-Pfalz",
    "wof:name":"Pension Johann Roos",
    "wof:placetype":"venue"
},
  "geometry": {"coordinates":[6.8279647827,50.1461753845],"type":"Point"}
}