{
  "type": "Feature",
  "properties": {
    "iso:country":"DE",
    "sg:address":"Nordel 1",
    "sg:city":"Hilter",
    "sg:phone":"+49 5424/216422",
    "sg:postcode":"49176",
    "sg:province":"Niedersachsen",
    "wof:name":"Hpf Gross- Und Einzelhandels Gmbh",
    "wof:placetype":"venue"
},
  "geometry": {"coordinates":[8.154302597,52.1312828064],"type":"Point"}
}