{
  "type": "Feature",
  "properties": {
    "iso:country":"DE",
    "sg:address":"K\u00f6nigstr. 8",
    "sg:city":"Schleusingen",
    "sg:phone":"+49 36841/40597",
    "sg:postcode":"98553",
    "sg:province":"Th\u00fcringen",
    "wof:name":"B\u00fcro & Technik Schleusingen Gmbh",
    "wof:placetype":"venue"
},
  "geometry": {"coordinates":[10.7553262711,50.5118179321],"type":"Point"}
}