{
  "type": "Feature",
  "properties": {
    "iso:country":"DE",
    "sg:address":"Thomas-Mann-Str. 5",
    "sg:city":"Porta Westfalica",
    "sg:phone":"+49 5731/6732",
    "sg:postcode":"32457",
    "sg:province":"Nordrhein-Westfalen",
    "wof:name":"Inge M\u00fcnzer",
    "wof:placetype":"venue"
},
  "geometry": {"coordinates":[8.8666820526,52.2170295715],"type":"Point"}
}