{
  "type": "Feature",
  "properties": {
    "iso:country":"DE",
    "sg:address":"Kreutzstr. 25",
    "sg:city":"Herzogenrath",
    "sg:phone":"+49 2407/2514",
    "sg:postcode":"52134",
    "sg:province":"Nordrhein-Westfalen",
    "wof:name":"Karl Radermacher Architekt",
    "wof:placetype":"venue"
},
  "geometry": {"coordinates":[6.088961,50.837418],"type":"Point"}
}