{
  "type": "Feature",
  "properties": {
    "iso:country":"DE",
    "sg:address":"Harvestehuder Weg 45",
    "sg:city":"Hamburg",
    "sg:postcode":"20148",
    "sg:province":"Hamburg",
    "wof:name":"Sports Com Gmbh",
    "wof:placetype":"venue"
},
  "geometry": {"coordinates":[9.99932,53.573292],"type":"Point"}
}