{
  "type": "Feature",
  "properties": {
    "iso:country":"DE",
    "sg:address":"Havelmatensteig 15",
    "sg:city":"Berlin",
    "sg:phone":"+49 30/3654828",
    "sg:postcode":"14089",
    "sg:province":"Berlin",
    "wof:name":"Heinz Neumann",
    "wof:placetype":"venue"
},
  "geometry": {"coordinates":[13.1779870987,52.4753265381],"type":"Point"}
}