{
  "type": "Feature",
  "properties": {
    "iso:country":"DE",
    "sg:address":"Korbacher Str. 1",
    "sg:city":"Edertal",
    "sg:phone":"+49 5623/1020",
    "sg:postcode":"34549",
    "sg:province":"Hessen",
    "wof:name":"Zur Post",
    "wof:placetype":"venue"
},
  "geometry": {"coordinates":[9.1232385635,51.1570854187],"type":"Point"}
}