{
  "type": "Feature",
  "properties": {
    "iso:country":"DE",
    "sg:address":"Gesundbrunnenstr. 3",
    "sg:city":"Augsburg",
    "sg:phone":"+49 821/37057",
    "sg:postcode":"86152",
    "sg:province":"Bayern",
    "wof:name":"Schuller Und Tham Architekten",
    "wof:placetype":"venue"
},
  "geometry": {"coordinates":[10.887673,48.371857],"type":"Point"}
}