{
  "type": "Feature",
  "properties": {
    "iso:country":"DE",
    "sg:address":"Birkenfelder Str. 2",
    "sg:city":"Morbach",
    "sg:phone":"+49 6533/5261",
    "sg:postcode":"54497",
    "sg:province":"Rheinland-Pfalz",
    "wof:name":"R. Stein Lotterie",
    "wof:placetype":"venue"
},
  "geometry": {"coordinates":[7.119912,49.810493],"type":"Point"}
}