{
  "type": "Feature",
  "properties": {
    "iso:country":"DE",
    "sg:address":"Unter den Eichen 2",
    "sg:city":"Schwarmstedt",
    "sg:postcode":"29690",
    "sg:province":"Niedersachsen",
    "wof:name":"B\u00fccherei Schwarmstedt",
    "wof:placetype":"venue"
},
  "geometry": {"coordinates":[9.618148,52.675907],"type":"Point"}
}