{
  "type": "Feature",
  "properties": {
    "iso:country":"DE",
    "sg:address":"Hasel\u00fcnner Str. 3",
    "sg:city":"Bawinkel",
    "sg:phone":"+49 5963/1833",
    "sg:postcode":"49844",
    "sg:province":"Niedersachsen",
    "wof:name":"Englische Stilm\u00f6bel",
    "wof:placetype":"venue"
},
  "geometry": {"coordinates":[7.4106202126,52.59948349],"type":"Point"}
}