{
  "type": "Feature",
  "properties": {
    "iso:country":"DE",
    "sg:address":"Barlachstr 25",
    "sg:city":"Nu\u00dfloch",
    "sg:phone":"+49 6224/73380",
    "sg:postcode":"69226",
    "sg:province":"Baden-W\u00fcrttemberg",
    "wof:name":"Ingenieurb\u00fcro Weese & Zuber Gmbh",
    "wof:placetype":"venue"
},
  "geometry": {"coordinates":[8.6884260178,49.3219985962],"type":"Point"}
}