{
  "type": "Feature",
  "properties": {
    "iso:country":"DE",
    "sg:address":"Am R\u00fcckersberg 41",
    "sg:city":"Gelnhausen",
    "sg:phone":"+49 6051/75829",
    "sg:postcode":"63571",
    "sg:province":"Hessen",
    "wof:name":"S & R Fliesenverlegung Gmbh",
    "wof:placetype":"venue"
},
  "geometry": {"coordinates":[9.2292289734,50.2026176453],"type":"Point"}
}