{
  "type": "Feature",
  "properties": {
    "iso:country":"DE",
    "sg:address":"Triftweg",
    "sg:city":"Ehrenfriedersdorf",
    "sg:phone":"+49 37341/2730",
    "sg:postcode":"09427",
    "sg:province":"Sachsen",
    "wof:name":"Gartenheim Sparte Klein- G\u00e4rtner Am Greifenstein",
    "wof:placetype":"venue"
},
  "geometry": {"coordinates":[12.9598588943,50.642288208],"type":"Point"}
}