{
  "type": "Feature",
  "properties": {
    "iso:country":"DE",
    "sg:address":"Gartenstr. 9 a",
    "sg:city":"Wackersdorf",
    "sg:phone":"+49 9431/50377",
    "sg:postcode":"92442",
    "sg:province":"Bayern",
    "wof:name":"Alfred Vogl",
    "wof:placetype":"venue"
},
  "geometry": {"coordinates":[12.18303,49.319576],"type":"Point"}
}