{
  "type": "Feature",
  "properties": {
    "iso:country":"DE",
    "sg:address":"Elterleiner Str. 6",
    "sg:city":"Gr\u00fcnhain",
    "sg:phone":"+49 3774/62534",
    "sg:postcode":"08358",
    "wof:name":"Untere M\u00fchle",
    "wof:placetype":"venue"
},
  "geometry": {"coordinates":[12.8151006699,50.579914093],"type":"Point"}
}