{
  "type": "Feature",
  "properties": {
    "iso:country":"DE",
    "sg:address":"Am Rehsprung 19",
    "sg:city":"Bonn",
    "sg:phone":"+49 228/485575",
    "sg:postcode":"53229",
    "sg:province":"Nordrhein-Westfalen",
    "wof:name":"Wm Wohnungsbau R. Mirgel Und Partner",
    "wof:placetype":"venue"
},
  "geometry": {"coordinates":[7.1681399345,50.7432594299],"type":"Point"}
}