{
  "type": "Feature",
  "properties": {
    "iso:country":"DE",
    "sg:address":"Westring 5 a",
    "sg:city":"Hohenhameln",
    "sg:phone":"+49 5128/5956",
    "sg:postcode":"31249",
    "sg:province":"Niedersachsen",
    "wof:name":"Ernst Scholz",
    "wof:placetype":"venue"
},
  "geometry": {"coordinates":[10.070843,52.273708],"type":"Point"}
}