{
  "type": "Feature",
  "properties": {
    "iso:country":"DE",
    "sg:address":"Gartenstr. 7",
    "sg:city":"Zepernick",
    "sg:postcode":"16341",
    "sg:province":"Brandenburg",
    "wof:name":"Allianz Hauptvertretung",
    "wof:placetype":"venue"
},
  "geometry": {"coordinates":[13.5495328903,52.6462936401],"type":"Point"}
}