{
  "type": "Feature",
  "properties": {
    "iso:country":"DE",
    "sg:address":"Krefelder Str. 81",
    "sg:city":"D\u00fcsseldorf",
    "sg:phone":"+49 211/501011",
    "sg:postcode":"40549",
    "sg:province":"Nordrhein-Westfalen",
    "wof:name":"Hans J. Holl\u00e4nder",
    "wof:placetype":"venue"
},
  "geometry": {"coordinates":[6.715502,51.234825],"type":"Point"}
}