{
  "type": "Feature",
  "properties": {
    "iso:country":"DE",
    "sg:address":"Tannenstr. 26",
    "sg:city":"Puchheim",
    "sg:phone":"+49 89/806960",
    "sg:postcode":"82178",
    "sg:province":"Bayern",
    "wof:name":"Graf & Stahl Verlagsb\u00fcro Gmbh",
    "wof:placetype":"venue"
},
  "geometry": {"coordinates":[11.35181427,48.1787643433],"type":"Point"}
}