{
  "type": "Feature",
  "properties": {
    "iso:country":"DE",
    "sg:address":"Siedlerweg 10",
    "sg:city":"Neuhofen",
    "sg:phone":"+49 6236/52911",
    "sg:postcode":"67141",
    "sg:province":"Rheinland-Pfalz",
    "wof:name":"Gerhard Sturm",
    "wof:placetype":"venue"
},
  "geometry": {"coordinates":[8.4219808578,49.4225006104],"type":"Point"}
}