{
  "type": "Feature",
  "properties": {
    "iso:country":"DE",
    "sg:address":"Weingartenstr. 110",
    "sg:city":"Offenburg",
    "sg:phone":"+49 781/31720",
    "sg:postcode":"77654",
    "sg:province":"Baden-W\u00fcrttemberg",
    "wof:name":"Rainer Rabold Architekt",
    "wof:placetype":"venue"
},
  "geometry": {"coordinates":[7.971641,48.471329],"type":"Point"}
}