{
  "type": "Feature",
  "properties": {
    "iso:country":"DE",
    "sg:address":"Crivitzer Chaussee 32",
    "sg:city":"Demen",
    "sg:phone":"+49 38488/21995",
    "sg:postcode":"19089",
    "sg:province":"Mecklenburg-Vorpommern",
    "wof:name":"Hans M. W. Spreth Gmbh",
    "wof:placetype":"venue"
},
  "geometry": {"coordinates":[11.71433,53.620338],"type":"Point"}
}