{
  "type": "Feature",
  "properties": {
    "iso:country":"DE",
    "sg:address":"Markt 8",
    "sg:city":"Xanten",
    "sg:phone":"+49 2801/3024",
    "sg:postcode":"46509",
    "sg:province":"Nordrhein-Westfalen",
    "wof:name":"Hirsch-apotheke",
    "wof:placetype":"venue"
},
  "geometry": {"coordinates":[6.454985,51.662334],"type":"Point"}
}