{
  "type": "Feature",
  "properties": {
    "iso:country":"DE",
    "sg:address":"Hamburger Str. 22",
    "sg:city":"Bad Oldesloe",
    "sg:phone":"+49 4531/2974",
    "sg:postcode":"23843",
    "sg:province":"Schleswig-Holstein",
    "wof:name":"Dr. Med. J\u00f6rn Krull",
    "wof:placetype":"venue"
},
  "geometry": {"coordinates":[10.3685598373,53.8076019287],"type":"Point"}
}