{
  "type": "Feature",
  "properties": {
    "iso:country":"DE",
    "sg:address":"Westpreu\u00dfenstr. 38",
    "sg:city":"M\u00fcnchen",
    "sg:phone":"+49 89/93940508",
    "sg:postcode":"81927",
    "sg:province":"Bayern",
    "wof:name":"Mawe - Yuour It Sales Agency E. K.",
    "wof:placetype":"venue"
},
  "geometry": {"coordinates":[11.6376361847,48.1535148621],"type":"Point"}
}