{
  "type": "Feature",
  "properties": {
    "iso:country":"DE",
    "sg:address":"Wielandstr. 34",
    "sg:city":"Berlin",
    "sg:phone":"+49 30/8594617",
    "sg:postcode":"12159",
    "sg:province":"Berlin",
    "wof:name":"Klaus-peter Hillebrand Rechtsanwalt",
    "wof:placetype":"venue"
},
  "geometry": {"coordinates":[13.3393688202,52.4722290039],"type":"Point"}
}