{
  "type": "Feature",
  "properties": {
    "iso:country":"DE",
    "sg:address":"Esenhauser Str. 20",
    "sg:city":"Wilhelmsdorf",
    "sg:phone":"+49 7503/597",
    "sg:postcode":"88271",
    "sg:province":"Baden-W\u00fcrttemberg",
    "wof:name":"Josef Schelshorn",
    "wof:placetype":"venue"
},
  "geometry": {"coordinates":[9.427364,47.866337],"type":"Point"}
}