{
  "type": "Feature",
  "properties": {
    "iso:country":"DE",
    "sg:address":"Hospitalstr. 5",
    "sg:city":"Halberstadt",
    "sg:phone":"+49 3941/68610",
    "sg:postcode":"38820",
    "sg:province":"Sachsen-Anhalt",
    "wof:name":"Feierabendheim Nord",
    "wof:placetype":"venue"
},
  "geometry": {"coordinates":[11.04846,51.902664],"type":"Point"}
}