{
  "type": "Feature",
  "properties": {
    "iso:country":"DE",
    "sg:address":"M\u00f6hringer Str. 14",
    "sg:city":"Filderstadt",
    "sg:phone":"+49 7158/909130",
    "sg:postcode":"70794",
    "sg:province":"Baden-W\u00fcrttemberg",
    "wof:name":"Galaxy No 1 Distribution And Media Woldswide Gmbh",
    "wof:placetype":"venue"
},
  "geometry": {"coordinates":[9.236661911,48.6759033203],"type":"Point"}
}