{
  "type": "Feature",
  "properties": {
    "iso:country":"DE",
    "sg:address":"Aachener Str. 532",
    "sg:city":"Frechen-K\u00f6nigsdorf",
    "sg:phone":"+49 2234/657979",
    "sg:postcode":"50226",
    "sg:province":"Nordrhein-Westfalen",
    "wof:name":"Rechtsanwalt Minwegen",
    "wof:placetype":"venue"
},
  "geometry": {"coordinates":[6.8093,50.910751],"type":"Point"}
}