{
  "type": "Feature",
  "properties": {
    "iso:country":"DE",
    "sg:address":"Immenhof 12",
    "sg:city":"Mainz",
    "sg:phone":"+49 6131/330810",
    "sg:postcode":"55128",
    "sg:province":"Rheinland-Pfalz",
    "wof:name":"Redaktion Jahrbuch F\u00fcr Eisenbahnliteratur",
    "wof:placetype":"venue"
},
  "geometry": {"coordinates":[8.2351179123,49.9724121094],"type":"Point"}
}