{
  "type": "Feature",
  "properties": {
    "iso:country":"DE",
    "sg:address":"Ringstr. 4",
    "sg:city":"Nusse",
    "sg:phone":"+49 4543/339",
    "sg:postcode":"23896",
    "sg:province":"Schleswig-Holstein",
    "wof:name":"Rach & Rach Restauration",
    "wof:placetype":"venue"
},
  "geometry": {"coordinates":[10.5909109116,53.6549186707],"type":"Point"}
}