{
  "type": "Feature",
  "properties": {
    "iso:country":"DE",
    "sg:address":"Bockhorner Weg 108a",
    "sg:city":"Bremen",
    "sg:phone":"+49 421/603777",
    "sg:postcode":"28779",
    "sg:province":"Bremen",
    "wof:name":"Harald Thiemann Architekt",
    "wof:placetype":"venue"
},
  "geometry": {"coordinates":[8.584045,53.203014],"type":"Point"}
}