{
  "type": "Feature",
  "properties": {
    "iso:country":"DE",
    "sg:address":"Am Wald 2",
    "sg:city":"Manching",
    "sg:phone":"+49 8459/6909",
    "sg:postcode":"85077",
    "sg:province":"Bayern",
    "wof:name":"Josef Elsd\u00f6rfer",
    "wof:placetype":"venue"
},
  "geometry": {"coordinates":[11.512611,48.709694],"type":"Point"}
}