{
  "type": "Feature",
  "properties": {
    "iso:country":"DE",
    "sg:address":"Gehnbergstr. 12",
    "sg:city":"Biedenkopf",
    "sg:phone":"+49 6461/8424",
    "sg:postcode":"35216",
    "sg:province":"Hessen",
    "wof:name":"Herbert Petri",
    "wof:placetype":"venue"
},
  "geometry": {"coordinates":[8.479746,50.932022],"type":"Point"}
}