{
  "type": "Feature",
  "properties": {
    "iso:country":"DE",
    "sg:address":"Kaiser-Friedrich-Str. 2",
    "sg:city":"Braunfels",
    "sg:phone":"+49 6442/5364",
    "sg:postcode":"35619",
    "sg:province":"Hessen",
    "wof:name":"L\u00f6wen-apotheke",
    "wof:placetype":"venue"
},
  "geometry": {"coordinates":[8.392714,50.517998],"type":"Point"}
}