{
  "type": "Feature",
  "properties": {
    "iso:country":"DE",
    "sg:address":"Worblinger Str. 70",
    "sg:city":"Singen",
    "sg:phone":"+49 7731/22388",
    "sg:postcode":"78224",
    "sg:province":"Baden-W\u00fcrttemberg",
    "wof:name":"Th. Sch\u00f6nle",
    "wof:placetype":"venue"
},
  "geometry": {"coordinates":[8.8676204681,47.7571105957],"type":"Point"}
}