{
  "type": "Feature",
  "properties": {
    "iso:country":"DE",
    "sg:address":"Abraham-Lincoln-Str. 21",
    "sg:city":"Wiesbaden",
    "sg:postcode":"65189",
    "sg:province":"Hessen",
    "wof:name":"Heylandt Gesellschaft F\u00fcr Apparatebau Gmbh",
    "wof:placetype":"venue"
},
  "geometry": {"coordinates":[8.274736,50.065483],"type":"Point"}
}