{
  "type": "Feature",
  "properties": {
    "iso:country":"DE",
    "sg:address":"Lammstr. 1",
    "sg:city":"Renningen",
    "sg:phone":"+49 7159/902083",
    "sg:postcode":"71272",
    "sg:province":"Baden-W\u00fcrttemberg",
    "wof:name":"Kurt Kohler Fleischerei",
    "wof:placetype":"venue"
},
  "geometry": {"coordinates":[8.9044437408,48.7732162476],"type":"Point"}
}