{
  "type": "Feature",
  "properties": {
    "iso:country":"DE",
    "sg:address":"Kackertstr. 22",
    "sg:city":"Aachen",
    "sg:phone":"+49 241/38350",
    "sg:postcode":"52072",
    "sg:province":"Nordrhein-Westfalen",
    "wof:name":"Geobit Ingenieur-ges. Mbh",
    "wof:placetype":"venue"
},
  "geometry": {"coordinates":[6.0606179237,50.7908287048],"type":"Point"}
}