{
  "type": "Feature",
  "properties": {
    "iso:country":"DE",
    "sg:address":"Osterbrink 1",
    "sg:city":"Elze",
    "sg:phone":"+49 5182/6609",
    "sg:postcode":"31008",
    "sg:province":"Niedersachsen",
    "wof:name":"G\u00fcnter Ihle",
    "wof:placetype":"venue"
},
  "geometry": {"coordinates":[9.738541,52.120106],"type":"Point"}
}