{
  "type": "Feature",
  "properties": {
    "iso:country":"DE",
    "sg:address":"Rathausmarkt",
    "sg:city":"Hamburg",
    "sg:phone":"+49 40/335911",
    "sg:postcode":"20095",
    "sg:province":"Hamburg",
    "wof:name":"Hanseaten Treff",
    "wof:placetype":"venue"
},
  "geometry": {"coordinates":[9.9939346313,53.5508956909],"type":"Point"}
}