{
  "type": "Feature",
  "properties": {
    "iso:country":"DE",
    "sg:address":"Vorderhagen 6",
    "sg:city":"Meinerzhagen",
    "sg:phone":"+49 2358/90850",
    "sg:postcode":"58540",
    "sg:province":"Nordrhein-Westfalen",
    "wof:name":"Carl Wittkop Kg",
    "wof:placetype":"venue"
},
  "geometry": {"coordinates":[7.767227,51.12418],"type":"Point"}
}