{
  "type": "Feature",
  "properties": {
    "iso:country":"DE",
    "sg:address":"St.-Oswald-Str. 4",
    "sg:city":"Traunstein",
    "sg:phone":"+49 861/2546",
    "sg:postcode":"83278",
    "sg:province":"Bayern",
    "wof:name":"Nanu",
    "wof:placetype":"venue"
},
  "geometry": {"coordinates":[12.6431016922,47.865776062],"type":"Point"}
}