{
  "type": "Feature",
  "properties": {
    "iso:country":"DE",
    "sg:address":"Rehbockstr. 26",
    "sg:city":"Hannover",
    "sg:phone":"+49 511/7010236",
    "sg:postcode":"30167",
    "sg:province":"Niedersachsen",
    "wof:name":"Energiekontor-hannover",
    "wof:placetype":"venue"
},
  "geometry": {"coordinates":[9.717901,52.386799],"type":"Point"}
}