{
  "type": "Feature",
  "properties": {
    "iso:country":"DE",
    "sg:address":"Lisdorfer Str. 2",
    "sg:city":"Saarlouis",
    "sg:phone":"+49 6831/460055",
    "sg:postcode":"66740",
    "sg:province":"Saarland",
    "wof:name":"Ianua G. P. S. Gesellschaft F\u00fcr Pr\u00e4vention Und Sozial-",
    "wof:placetype":"venue"
},
  "geometry": {"coordinates":[6.753809,49.313004],"type":"Point"}
}