{
  "type": "Feature",
  "properties": {
    "iso:country":"DE",
    "sg:address":"Auf dem Ahrenberg 4",
    "sg:city":"Bad Sooden-Allendorf",
    "sg:phone":"+49 5652",
    "sg:postcode":"37242",
    "sg:province":"Hessen",
    "wof:name":"Landhaus Am Ahrenberg",
    "wof:placetype":"venue"
},
  "geometry": {"coordinates":[9.9504051208,51.282169342],"type":"Point"}
}