{
  "type": "Feature",
  "properties": {
    "iso:country":"DE",
    "sg:address":"Fleiner Str. 17",
    "sg:city":"Heilbronn",
    "sg:phone":"+49 7131/930296",
    "sg:postcode":"74072",
    "sg:province":"Baden-W\u00fcrttemberg",
    "wof:name":"Framode Gmbh",
    "wof:placetype":"venue"
},
  "geometry": {"coordinates":[9.218595,49.140331],"type":"Point"}
}