{
  "type": "Feature",
  "properties": {
    "iso:country":"DE",
    "sg:address":"Brandst\u00fccken 27",
    "sg:city":"Hamburg",
    "sg:phone":"+49 40/80090502",
    "sg:postcode":"22549",
    "sg:province":"Hamburg",
    "wof:name":"Teamdress Stein Gmbh",
    "wof:placetype":"venue"
},
  "geometry": {"coordinates":[9.8492546082,53.5811691284],"type":"Point"}
}