{
  "type": "Feature",
  "properties": {
    "iso:country":"DE",
    "sg:address":"Schillerplatz",
    "sg:city":"Stuttgart",
    "sg:phone":"+49 711/2260303",
    "sg:postcode":"70173",
    "sg:province":"Baden-W\u00fcrttemberg",
    "wof:name":"Apcoa Autoparking Gmbh",
    "wof:placetype":"venue"
},
  "geometry": {"coordinates":[9.1787948608,48.7771034241],"type":"Point"}
}