{
  "type": "Feature",
  "properties": {
    "iso:country":"DE",
    "sg:address":"August-Schanz-Stra\u00dfe 80",
    "sg:city":"Frankfurt",
    "sg:phone":"+49 69",
    "sg:postcode":"60433",
    "sg:province":"Hessen",
    "wof:name":"Beiersdorf Herzhauser Planung Gmbh F\u00fcr Elektro- Und F\u00f6rderte",
    "wof:placetype":"venue"
},
  "geometry": {"coordinates":[8.689345,50.16087],"type":"Point"}
}