{
  "type": "Feature",
  "properties": {
    "iso:country":"DE",
    "sg:address":"Bahnhofstr. 66",
    "sg:city":"Hambergen",
    "sg:phone":"+49 4793/2395",
    "sg:postcode":"27729",
    "sg:province":"Niedersachsen",
    "wof:name":"Heidi Salewski Verleihbetrieb",
    "wof:placetype":"venue"
},
  "geometry": {"coordinates":[8.8190698624,53.2974510193],"type":"Point"}
}