{
  "type": "Feature",
  "properties": {
    "iso:country":"DE",
    "sg:address":"Friedensallee 14",
    "sg:city":"Hamburg",
    "sg:phone":"+49 40/3905727",
    "sg:postcode":"22765",
    "sg:province":"Hamburg",
    "wof:name":"Peter Wiesner Architekt",
    "wof:placetype":"venue"
},
  "geometry": {"coordinates":[9.927629,53.55463],"type":"Point"}
}