{
  "type": "Feature",
  "properties": {
    "iso:country":"DE",
    "sg:address":"Tannenhofallee 25a",
    "sg:city":"M\u00fcnster",
    "sg:phone":"+49 251/31097",
    "sg:postcode":"48155",
    "sg:province":"Nordrhein-Westfalen",
    "wof:name":"Karl Siegener Gmbh",
    "wof:placetype":"venue"
},
  "geometry": {"coordinates":[7.681456,51.970238],"type":"Point"}
}