{
  "type": "Feature",
  "properties": {
    "iso:country":"DE",
    "sg:address":"Schlei\u00dfbergstr. 21",
    "sg:city":"Ohorn",
    "sg:phone":"+49 35955/8380",
    "sg:postcode":"01896",
    "sg:province":"Sachsen",
    "wof:name":"F.-j. Rammer Gmbh",
    "wof:placetype":"venue"
},
  "geometry": {"coordinates":[14.0549211502,51.1777915955],"type":"Point"}
}