{
  "type": "Feature",
  "properties": {
    "iso:country":"DE",
    "sg:address":"Lichtendorfer Str. 129",
    "sg:city":"Schwerte",
    "sg:phone":"+49 2304/96620",
    "sg:postcode":"58239",
    "sg:province":"Nordrhein-Westfalen",
    "wof:name":"Lichtendorfer Baumschulen Gmbh",
    "wof:placetype":"venue"
},
  "geometry": {"coordinates":[7.59251,51.463799],"type":"Point"}
}