{
  "type": "Feature",
  "properties": {
    "iso:country":"DE",
    "sg:address":"Obere Gel\u00e4nderstr.",
    "sg:city":"Neuenburg",
    "sg:phone":"+49 7631/73814",
    "sg:postcode":"79395",
    "sg:province":"Baden-W\u00fcrttemberg",
    "wof:name":"A. Schlageter",
    "wof:placetype":"venue"
},
  "geometry": {"coordinates":[7.5601201057,47.8139305115],"type":"Point"}
}