{
  "type": "Feature",
  "properties": {
    "iso:country":"DE",
    "sg:address":"Fischbacher Hauptstr. 193",
    "sg:city":"N\u00fcrnberg",
    "sg:phone":"+49 911/830400",
    "sg:postcode":"90475",
    "sg:province":"Bayern",
    "wof:name":"M.u.heinz R\u00e4bel",
    "wof:placetype":"venue"
},
  "geometry": {"coordinates":[11.1935434341,49.4202346802],"type":"Point"}
}