{
  "type": "Feature",
  "properties": {
    "iso:country":"DE",
    "sg:address":"Ebelingstr. 37",
    "sg:city":"Hannover",
    "sg:phone":"+49 511/6477441",
    "sg:postcode":"30659",
    "sg:province":"Niedersachsen",
    "wof:name":"Gerd Wille Gmbh",
    "wof:placetype":"venue"
},
  "geometry": {"coordinates":[9.795163,52.411869],"type":"Point"}
}