{
  "type": "Feature",
  "properties": {
    "iso:country":"DE",
    "sg:address":"\u00d6nkfeld 10",
    "sg:city":"Radevormwald",
    "sg:phone":"+49 2195/2886",
    "sg:postcode":"42477",
    "sg:province":"Nordrhein-Westfalen",
    "wof:name":"Bernd Uphoff",
    "wof:placetype":"venue"
},
  "geometry": {"coordinates":[7.350662,51.222321],"type":"Point"}
}