{
  "type": "Feature",
  "properties": {
    "iso:country":"DE",
    "sg:address":"Bahnhofstr. 55",
    "sg:city":"Rohrbach",
    "sg:phone":"+49 8442/8428",
    "sg:postcode":"85296",
    "sg:province":"Bayern",
    "wof:name":"Karl Zeidlmaier",
    "wof:placetype":"venue"
},
  "geometry": {"coordinates":[11.5747308731,48.6048660278],"type":"Point"}
}