{
  "type": "Feature",
  "properties": {
    "iso:country":"DE",
    "sg:address":"Kelberger Str. 40",
    "sg:city":"Cochem",
    "sg:phone":"+49 2671/7168",
    "sg:postcode":"56812",
    "sg:province":"Rheinland-Pfalz",
    "wof:name":"Haus Sch\u00f6nblick Ursula Rademacher-reichow",
    "wof:placetype":"venue"
},
  "geometry": {"coordinates":[7.1671309471,50.1455383301],"type":"Point"}
}