{
  "type": "Feature",
  "properties": {
    "iso:country":"DE",
    "sg:address":"Bruchsaler Str. 43",
    "sg:city":"Eppingen",
    "sg:phone":"+49 7262/4486",
    "sg:postcode":"75031",
    "sg:province":"Baden-W\u00fcrttemberg",
    "wof:name":"Hermann Ries",
    "wof:placetype":"venue"
},
  "geometry": {"coordinates":[8.9098,49.137039],"type":"Point"}
}