{
  "type": "Feature",
  "properties": {
    "iso:country":"DE",
    "sg:address":"Langer Steinweg 24",
    "sg:city":"Blomberg",
    "sg:phone":"+49 5235/5800",
    "sg:postcode":"32825",
    "sg:province":"Nordrhein-Westfalen",
    "wof:name":"Wiegands Videothek",
    "wof:placetype":"venue"
},
  "geometry": {"coordinates":[9.0919303894,51.9418983459],"type":"Point"}
}