{
  "type": "Feature",
  "properties": {
    "iso:country":"DE",
    "sg:address":"Im Nebenroth 3",
    "sg:city":"Bellingen",
    "sg:phone":"+49 2663/968808",
    "sg:postcode":"56459",
    "sg:province":"Rheinland-Pfalz",
    "wof:name":"Joachim Schuth",
    "wof:placetype":"venue"
},
  "geometry": {"coordinates":[7.9082188606,50.5895996094],"type":"Point"}
}