{
  "type": "Feature",
  "properties": {
    "iso:country":"DE",
    "sg:address":"Norden am Dorf 4",
    "sg:city":"Cuxhaven",
    "sg:phone":"+49 4721/24211",
    "sg:postcode":"27476",
    "sg:province":"Niedersachsen",
    "wof:name":"Gerhard Mangliers Ingenieur",
    "wof:placetype":"venue"
},
  "geometry": {"coordinates":[8.6510066986,53.8739891052],"type":"Point"}
}