{
  "type": "Feature",
  "properties": {
    "iso:country":"DE",
    "sg:address":"Heintzmannsheide 80",
    "sg:city":"Bochum",
    "sg:postcode":"44797",
    "sg:province":"Nordrhein-Westfalen",
    "wof:name":"Geb Ges. F. Erwachsenen- Bildung Mbh",
    "wof:placetype":"venue"
},
  "geometry": {"coordinates":[7.223399,51.436653],"type":"Point"}
}