{
  "type": "Feature",
  "properties": {
    "iso:country":"DE",
    "sg:address":"Zur Seewiese 4",
    "sg:city":"S\u00fcsel",
    "sg:postcode":"23701",
    "sg:province":"Schleswig-Holstein",
    "wof:name":"Block Import-export Eurotrans Zwdl. Einer Beschr\u00e4nkt Haft.",
    "wof:placetype":"venue"
},
  "geometry": {"coordinates":[10.7170248032,54.0822486877],"type":"Point"}
}