{
  "type": "Feature",
  "properties": {
    "iso:country":"DE",
    "sg:address":"Liebensteiner Str. 3",
    "sg:city":"Barchfeld",
    "sg:phone":"+49 36961/44355",
    "sg:postcode":"36456",
    "sg:province":"Th\u00fcringen",
    "wof:name":"R. Anacker",
    "wof:placetype":"venue"
},
  "geometry": {"coordinates":[10.299059,50.800213],"type":"Point"}
}