{
  "type": "Feature",
  "properties": {
    "iso:country":"DE",
    "sg:address":"Hauptstr. 202",
    "sg:city":"Rheda-Wiedenbr\u00fcck",
    "sg:phone":"+49 5242/94500",
    "sg:postcode":"33378",
    "sg:province":"Nordrhein-Westfalen",
    "wof:name":"Overkott & Keil Gmbh",
    "wof:placetype":"venue"
},
  "geometry": {"coordinates":[8.2932758331,51.848449707],"type":"Point"}
}