{
  "type": "Feature",
  "properties": {
    "iso:country":"DE",
    "sg:address":"Obere Gasse 7",
    "sg:city":"Zeitlarn",
    "sg:phone":"+49 941/65276",
    "sg:postcode":"93197",
    "sg:province":"Bayern",
    "wof:name":"Joseph Frank",
    "wof:placetype":"venue"
},
  "geometry": {"coordinates":[12.108552,49.07766],"type":"Point"}
}