{
  "type": "Feature",
  "properties": {
    "iso:country":"DE",
    "sg:address":"Alois-von-Brinz-Str. 26",
    "sg:city":"Weiler-Simmerberg",
    "sg:phone":"+49 8387/92320",
    "sg:postcode":"88171",
    "sg:province":"Bayern",
    "wof:name":"Hutfabrik Seeberger Gmbh & Co.",
    "wof:placetype":"venue"
},
  "geometry": {"coordinates":[9.92121315,47.5839500427],"type":"Point"}
}