{
  "type": "Feature",
  "properties": {
    "iso:country":"DE",
    "sg:address":"Dorfstr. 1",
    "sg:city":"Lambrechtshagen",
    "sg:phone":"+49 381/8099828",
    "sg:postcode":"18069",
    "sg:province":"Mecklenburg-Vorpommern",
    "wof:name":"E. Dethloff",
    "wof:placetype":"venue"
},
  "geometry": {"coordinates":[12.0152397156,54.1026992798],"type":"Point"}
}