{
  "type": "Feature",
  "properties": {
    "iso:country":"DE",
    "sg:address":"Silberbachstr. 10",
    "sg:city":"Taunusstein",
    "sg:phone":"+49 4961/289631",
    "sg:postcode":"65232",
    "sg:province":"Hessen",
    "wof:name":"Tetronik Gmbh",
    "wof:placetype":"venue"
},
  "geometry": {"coordinates":[8.202893,50.15295],"type":"Point"}
}