{
  "type": "Feature",
  "properties": {
    "iso:country":"DE",
    "sg:address":"Thomas-Mann-Str. 22",
    "sg:city":"Bebra",
    "sg:phone":"+49 6622/919914",
    "sg:postcode":"36179",
    "sg:province":"Hessen",
    "wof:name":"J\u00fcrgen Gillmann",
    "wof:placetype":"venue"
},
  "geometry": {"coordinates":[9.8020458221,50.9718360901],"type":"Point"}
}