{
  "type": "Feature",
  "properties": {
    "iso:country":"DE",
    "sg:address":"Hauptstr. 14",
    "sg:city":"Stadtsteinach",
    "sg:phone":"+49 9225/6487",
    "sg:postcode":"95346",
    "sg:province":"Bayern",
    "wof:name":"Ludwig Kleinheinz",
    "wof:placetype":"venue"
},
  "geometry": {"coordinates":[11.5040473938,50.1624794006],"type":"Point"}
}