{
  "type": "Feature",
  "properties": {
    "iso:country":"DE",
    "sg:address":"Eggener Weg 13",
    "sg:city":"Waltenhofen",
    "sg:phone":"+49 8379/7203",
    "sg:postcode":"87448",
    "sg:province":"Bayern",
    "wof:name":"Welz & Ziegler Gmbh",
    "wof:placetype":"venue"
},
  "geometry": {"coordinates":[10.28117,47.628407],"type":"Point"}
}