{
  "type": "Feature",
  "properties": {
    "iso:country":"DE",
    "sg:address":"Hainstr. 32",
    "sg:city":"Erlensee",
    "sg:phone":"+49 6183/72140",
    "sg:postcode":"63526",
    "sg:province":"Hessen",
    "wof:name":"Sven Tr\u00fcbenbach",
    "wof:placetype":"venue"
},
  "geometry": {"coordinates":[8.9820241928,50.1573448181],"type":"Point"}
}