{
  "type": "Feature",
  "properties": {
    "iso:country":"DE",
    "sg:address":"Windthorststr. 22",
    "sg:city":"Speyer",
    "sg:phone":"+49 6232/70825",
    "sg:postcode":"67346",
    "sg:province":"Rheinland-Pfalz",
    "wof:name":"Rudolf Daum Ingenieur",
    "wof:placetype":"venue"
},
  "geometry": {"coordinates":[8.4313230515,49.3044433594],"type":"Point"}
}