{
  "type": "Feature",
  "properties": {
    "iso:country":"DE",
    "sg:address":"Meppener Str. 1",
    "sg:city":"Hasel\u00fcnne",
    "sg:phone":"+49 5961/4000",
    "sg:postcode":"49740",
    "sg:province":"Niedersachsen",
    "wof:name":"Elektro Vocke",
    "wof:placetype":"venue"
},
  "geometry": {"coordinates":[7.48415,52.67403],"type":"Point"}
}