{
  "type": "Feature",
  "properties": {
    "iso:country":"DE",
    "sg:address":"Hauptstr. 90",
    "sg:city":"Rommerskirchen",
    "sg:phone":"+49 2183/1479",
    "sg:postcode":"41569",
    "sg:province":"Nordrhein-Westfalen",
    "wof:name":"Dornieden",
    "wof:placetype":"venue"
},
  "geometry": {"coordinates":[6.661373,51.029179],"type":"Point"}
}