{
  "type": "Feature",
  "properties": {
    "iso:country":"DE",
    "sg:address":"Virngrundstr. 2",
    "sg:city":"Neuler",
    "sg:phone":"+49 7961/4268",
    "sg:postcode":"73491",
    "sg:province":"Baden-W\u00fcrttemberg",
    "wof:name":"M. Brenner",
    "wof:placetype":"venue"
},
  "geometry": {"coordinates":[10.072201,48.929726],"type":"Point"}
}