{
  "type": "Feature",
  "properties": {
    "iso:country":"DE",
    "sg:address":"In Gripekoven 16",
    "sg:city":"Wegberg",
    "sg:postcode":"41844",
    "sg:province":"Nordrhein-Westfalen",
    "wof:name":"Thomas Brieden Innenausbau Gmbh",
    "wof:placetype":"venue"
},
  "geometry": {"coordinates":[6.324582,51.142498],"type":"Point"}
}