{
  "type": "Feature",
  "properties": {
    "iso:country":"DE",
    "sg:address":"Stadener Str. 15",
    "sg:city":"Hopsten",
    "sg:phone":"+49 5458/7325",
    "sg:postcode":"48496",
    "sg:province":"Nordrhein-Westfalen",
    "wof:name":"Franz Johannemann",
    "wof:placetype":"venue"
},
  "geometry": {"coordinates":[7.62128,52.382408],"type":"Point"}
}