{
  "type": "Feature",
  "properties": {
    "iso:country":"DE",
    "sg:address":"Alter Markt 14",
    "sg:city":"Emmerich",
    "sg:phone":"+49 2822/70802",
    "sg:postcode":"46446",
    "sg:province":"Nordrhein-Westfalen",
    "wof:name":"Jean Meenen Inh. G\u00fcnter B\u00fcrger",
    "wof:placetype":"venue"
},
  "geometry": {"coordinates":[6.2426590919,51.8301124573],"type":"Point"}
}