{
  "type": "Feature",
  "properties": {
    "iso:country":"DE",
    "sg:address":"Raiffeisenallee 6a",
    "sg:city":"Oberhaching",
    "sg:phone":"+49 89/6138720",
    "sg:postcode":"82041",
    "sg:province":"Bayern",
    "wof:name":"Intega Innovative Technologie F\u00fcr Gase Und Anlagenbau",
    "wof:placetype":"venue"
},
  "geometry": {"coordinates":[11.5826387405,48.0308151245],"type":"Point"}
}