{
  "type": "Feature",
  "properties": {
    "iso:country":"DE",
    "sg:address":"Hafenbad 31",
    "sg:city":"Ulm",
    "sg:phone":"+49 731/14140",
    "sg:postcode":"89073",
    "sg:province":"Baden-W\u00fcrttemberg",
    "wof:name":"Wohnbau Keifl Gmbh & Co. Kg",
    "wof:placetype":"venue"
},
  "geometry": {"coordinates":[9.993735,48.401054],"type":"Point"}
}