{
  "type": "Feature",
  "properties": {
    "iso:country":"DE",
    "sg:address":"Possartstr. 11",
    "sg:city":"M\u00fcnchen",
    "sg:phone":"+49 89/9989090",
    "sg:postcode":"81679",
    "sg:province":"Bayern",
    "wof:name":"Apax Partners & Co. Corporate Finance",
    "wof:placetype":"venue"
},
  "geometry": {"coordinates":[11.6064224243,48.1412086487],"type":"Point"}
}