{
  "type": "Feature",
  "properties": {
    "iso:country":"DE",
    "sg:address":"Am Hellerhof 4",
    "sg:city":"Dresden",
    "sg:phone":"+49 351/8582846",
    "sg:postcode":"01129",
    "sg:province":"Sachsen",
    "wof:name":"Imz Dresden Gmbh",
    "wof:placetype":"venue"
},
  "geometry": {"coordinates":[13.734294,51.094124],"type":"Point"}
}