{
  "type": "Feature",
  "properties": {
    "iso:country":"DE",
    "sg:address":"Eppendorfer Weg 175",
    "sg:city":"Hamburg",
    "sg:phone":"+49 40/4915711",
    "sg:postcode":"20253",
    "sg:province":"Hamburg",
    "wof:name":"Hunde Und Katzenshop",
    "wof:placetype":"venue"
},
  "geometry": {"coordinates":[9.96719,53.579868],"type":"Point"}
}