{
  "type": "Feature",
  "properties": {
    "iso:country":"DE",
    "sg:address":"Schubartstr. 70",
    "sg:city":"Blaustein",
    "sg:phone":"+49 731/551154",
    "sg:postcode":"89134",
    "sg:province":"Baden-W\u00fcrttemberg",
    "wof:name":"Erika Wa\u00dfmer",
    "wof:placetype":"venue"
},
  "geometry": {"coordinates":[9.936249733,48.4085197449],"type":"Point"}
}