{
  "type": "Feature",
  "properties": {
    "iso:country":"DE",
    "sg:address":"Stadtwaldstr. 25",
    "sg:city":"M\u00f6nchengladbach",
    "sg:phone":"+49 2161/583404",
    "sg:postcode":"41179",
    "sg:province":"Nordrhein-Westfalen",
    "wof:name":"Friedrich K. Sch\u00f6ning",
    "wof:placetype":"venue"
},
  "geometry": {"coordinates":[6.3717498779,51.1475601196],"type":"Point"}
}