{
  "type": "Feature",
  "properties": {
    "iso:country":"DE",
    "sg:city":"Essen",
    "sg:postcode":"45130",
    "sg:province":"Nordrhein-Westfalen",
    "wof:name":"The Queen Of Table Dance",
    "wof:placetype":"venue"
},
  "geometry": {"coordinates":[7.007945,51.438381],"type":"Point"}
}