{
  "type": "Feature",
  "properties": {
    "iso:country":"DE",
    "sg:address":"Scharn 1-3",
    "sg:city":"Minden",
    "sg:postcode":"32423",
    "sg:province":"Nordrhein-Westfalen",
    "wof:name":"Prater Spielhallen Gmbh",
    "wof:placetype":"venue"
},
  "geometry": {"coordinates":[8.916653,52.288548],"type":"Point"}
}