{
  "type": "Feature",
  "properties": {
    "iso:country":"DE",
    "sg:address":"Am Markt 11",
    "sg:city":"Leutershausen",
    "sg:phone":"+49 9823/278",
    "sg:postcode":"91578",
    "sg:province":"Bayern",
    "wof:name":"Hammerder Und Sorg",
    "wof:placetype":"venue"
},
  "geometry": {"coordinates":[10.408000946,49.3000793457],"type":"Point"}
}