{
  "type": "Feature",
  "properties": {
    "iso:country":"DE",
    "sg:address":"Gr\u00fclshofstr. 7",
    "sg:city":"K\u00f6ln",
    "sg:phone":"+49 221/692712",
    "sg:postcode":"51109",
    "sg:province":"Nordrhein-Westfalen",
    "wof:name":"Helmut Egink",
    "wof:placetype":"venue"
},
  "geometry": {"coordinates":[7.0455107689,50.9510536194],"type":"Point"}
}