{
  "type": "Feature",
  "properties": {
    "iso:country":"DE",
    "sg:address":"Alandsgrund",
    "sg:city":"W\u00fcrzburg",
    "sg:phone":"+49 931/72038",
    "sg:postcode":"97074",
    "sg:province":"Bayern",
    "wof:name":"Beuschlein Gmbh",
    "wof:placetype":"venue"
},
  "geometry": {"coordinates":[9.9671726227,49.7742881775],"type":"Point"}
}