{
  "type": "Feature",
  "properties": {
    "iso:country":"DE",
    "sg:address":"Erftstr. 7",
    "sg:city":"Euskirchen",
    "sg:phone":"+49 2251/3718",
    "sg:postcode":"53879",
    "sg:province":"Nordrhein-Westfalen",
    "wof:name":"Wolfgang Zdrzallek",
    "wof:placetype":"venue"
},
  "geometry": {"coordinates":[6.7951321602,50.6629676819],"type":"Point"}
}