{
  "type": "Feature",
  "properties": {
    "iso:country":"DE",
    "sg:address":"Kolbornstr. 2",
    "sg:city":"Aschaffenburg",
    "sg:phone":"+49 6021/23288",
    "sg:postcode":"63739",
    "sg:province":"Bayern",
    "wof:name":"H. Bardtenschlager",
    "wof:placetype":"venue"
},
  "geometry": {"coordinates":[9.1516246796,49.9800453186],"type":"Point"}
}