{
  "type": "Feature",
  "properties": {
    "iso:country":"DE",
    "sg:address":"M\u00fchlenstr. 32-44",
    "sg:city":"Siegburg",
    "sg:phone":"+49 4922/415470",
    "sg:postcode":"53721",
    "sg:province":"Nordrhein-Westfalen",
    "wof:name":"Kranz Parkhotel",
    "wof:placetype":"venue"
},
  "geometry": {"coordinates":[7.209131,50.794495],"type":"Point"}
}