{
  "type": "Feature",
  "properties": {
    "iso:country":"DE",
    "sg:address":"Vollmerhauser Str. 57",
    "sg:city":"Gummersbach",
    "sg:phone":"+49 2261/77429",
    "sg:postcode":"51645",
    "sg:province":"Nordrhein-Westfalen",
    "wof:name":"Restaurant Homburger Hof",
    "wof:placetype":"venue"
},
  "geometry": {"coordinates":[7.5510978699,50.9885025024],"type":"Point"}
}