{
  "type": "Feature",
  "properties": {
    "iso:country":"DE",
    "sg:address":"An der Windm\u00fchle 28 a",
    "sg:city":"Hamminkeln",
    "sg:phone":"+49 2852/711494",
    "sg:postcode":"46499",
    "sg:province":"Nordrhein-Westfalen",
    "wof:name":"Tanjus D\u00f6ner",
    "wof:placetype":"venue"
},
  "geometry": {"coordinates":[6.5947890282,51.7343902588],"type":"Point"}
}