{
  "type": "Feature",
  "properties": {
    "iso:country":"DE",
    "sg:address":"Kirnbachstr. 39",
    "sg:city":"Schramberg",
    "sg:postcode":"78713",
    "sg:province":"Baden-W\u00fcrttemberg",
    "wof:name":"Kopp",
    "wof:placetype":"venue"
},
  "geometry": {"coordinates":[8.391749,48.216434],"type":"Point"}
}