{
  "type": "Feature",
  "properties": {
    "iso:country":"DE",
    "sg:address":"\u00d6sterholzstr.",
    "sg:city":"Nohra",
    "sg:phone":"+49 3643/809126",
    "sg:postcode":"99428",
    "sg:province":"Th\u00fcringen",
    "wof:name":"Night Star Express",
    "wof:placetype":"venue"
},
  "geometry": {"coordinates":[11.256043,50.958782],"type":"Point"}
}