{
  "type": "Feature",
  "properties": {
    "iso:country":"DE",
    "sg:address":"schwarzkopfstr. 4",
    "sg:city":"philippsreut",
    "sg:phone":"+49 8550",
    "sg:postcode":"94158",
    "sg:province":"Bayern",
    "wof:name":"Haus Baerbel",
    "wof:placetype":"venue"
},
  "geometry": {"coordinates":[13.6776018143,48.8615875244],"type":"Point"}
}