{
  "type": "Feature",
  "properties": {
    "iso:country":"DE",
    "sg:address":"Am Erlbach 1",
    "sg:city":"Eching",
    "sg:phone":"+49 8709/1741",
    "sg:postcode":"84174",
    "sg:province":"Bayern",
    "wof:name":"Eder-transporte Inh. Christa Sandl",
    "wof:placetype":"venue"
},
  "geometry": {"coordinates":[12.02272892,48.486530304],"type":"Point"}
}