{
  "type": "Feature",
  "properties": {
    "iso:country":"DE",
    "sg:address":"Hochrad 7 a",
    "sg:city":"Hamburg",
    "sg:phone":"+49 40/828835",
    "sg:postcode":"22605",
    "sg:province":"Hamburg",
    "wof:name":"Dr. Peter J. Blumenthal Rechtsanwalt",
    "wof:placetype":"venue"
},
  "geometry": {"coordinates":[9.876543045,53.5535926819],"type":"Point"}
}