{
  "type": "Feature",
  "properties": {
    "iso:country":"DE",
    "sg:address":"Mozartstr. 1",
    "sg:city":"Leipzig",
    "sg:postcode":"04107",
    "sg:province":"Sachsen",
    "wof:name":"Zweigbibliothek S\u00fcd",
    "wof:placetype":"venue"
},
  "geometry": {"coordinates":[12.369742,51.331692],"type":"Point"}
}