{
  "type": "Feature",
  "properties": {
    "iso:country":"DE",
    "sg:address":"Talstr. 6",
    "sg:city":"Mettmann",
    "sg:phone":"+49 2104/27936",
    "sg:postcode":"40822",
    "sg:province":"Nordrhein-Westfalen",
    "wof:name":"Fernost",
    "wof:placetype":"venue"
},
  "geometry": {"coordinates":[6.97828722,51.2491722107],"type":"Point"}
}