{
  "type": "Feature",
  "properties": {
    "iso:country":"DE",
    "sg:address":"Schulstr. 6",
    "sg:city":"Lahntal",
    "sg:phone":"+49 6420/480",
    "sg:postcode":"35094",
    "sg:province":"Hessen",
    "wof:name":"Gemeindeb\u00fccherei Ortst.sterzenhausen",
    "wof:placetype":"venue"
},
  "geometry": {"coordinates":[8.70284,50.863411],"type":"Point"}
}