{
  "type": "Feature",
  "properties": {
    "iso:country":"DE",
    "sg:address":"Oberndorfer Str. 14",
    "sg:city":"Weihmichl",
    "sg:phone":"+49 8704/8828",
    "sg:postcode":"84107",
    "sg:province":"Bayern",
    "wof:name":"W. Sandleitner",
    "wof:placetype":"venue"
},
  "geometry": {"coordinates":[12.04016,48.606247],"type":"Point"}
}