{
  "type": "Feature",
  "properties": {
    "iso:country":"DE",
    "sg:address":"Schlo\u00dfpark",
    "sg:city":"Bad Kreuznach",
    "sg:postcode":"55543",
    "sg:province":"Rheinland-Pfalz",
    "wof:name":"Kur-apotheke",
    "wof:placetype":"venue"
},
  "geometry": {"coordinates":[7.859044,49.841026],"type":"Point"}
}