{
  "type": "Feature",
  "properties": {
    "iso:country":"DE",
    "sg:address":"Potsdamer Str. 102",
    "sg:city":"Berlin",
    "sg:phone":"+49 30/2617722",
    "sg:postcode":"10785",
    "sg:province":"Berlin",
    "wof:name":"Video World",
    "wof:placetype":"venue"
},
  "geometry": {"coordinates":[13.3641986847,52.5016784668],"type":"Point"}
}