{
  "type": "Feature",
  "properties": {
    "iso:country":"DE",
    "sg:address":"Altk\u00f6nigstr. 16",
    "sg:city":"Bad Homburg",
    "sg:phone":"+49 6172/36207",
    "sg:postcode":"61350",
    "sg:province":"Hessen",
    "wof:name":"Harald Eisenhauer Masseur",
    "wof:placetype":"venue"
},
  "geometry": {"coordinates":[8.599946,50.237926],"type":"Point"}
}