{
  "type": "Feature",
  "properties": {
    "iso:country":"DE",
    "sg:address":"Hauptstr. 33",
    "sg:city":"Birkenh\u00f6rdt",
    "sg:phone":"+49 6343/8170",
    "sg:postcode":"76889",
    "sg:province":"Rheinland-Pfalz",
    "wof:name":"E. Stengel",
    "wof:placetype":"venue"
},
  "geometry": {"coordinates":[7.933157,49.114456],"type":"Point"}
}