{
  "type": "Feature",
  "properties": {
    "iso:country":"DE",
    "sg:address":"Schrobenhausener Str. 56 e",
    "sg:city":"P\u00f6ttmes",
    "sg:postcode":"86554",
    "sg:province":"Bayern",
    "wof:name":"Martin Ziegler Gmbh & Co. Kg",
    "wof:placetype":"venue"
},
  "geometry": {"coordinates":[11.092997,48.582787],"type":"Point"}
}