{
  "type": "Feature",
  "properties": {
    "iso:country":"DE",
    "sg:address":"Dorfstr. 76",
    "sg:city":"Wredenhagen",
    "sg:phone":"+49 39925/2315",
    "sg:postcode":"17209",
    "sg:province":"Mecklenburg-Vorpommern",
    "wof:name":"F. Bussiahn",
    "wof:placetype":"venue"
},
  "geometry": {"coordinates":[12.515653,53.289307],"type":"Point"}
}