{
  "type": "Feature",
  "properties": {
    "iso:country":"DE",
    "sg:address":"Florastr. 3",
    "sg:city":"Berlin",
    "sg:phone":"+49 30/5628006",
    "sg:postcode":"12623",
    "sg:province":"Berlin",
    "wof:name":"Pension Flora",
    "wof:placetype":"venue"
},
  "geometry": {"coordinates":[13.6176204681,52.5154075623],"type":"Point"}
}