{
  "type": "Feature",
  "properties": {
    "iso:country":"DE",
    "sg:address":"Kaiserbauerstr. 5",
    "sg:city":"Neuburg",
    "sg:postcode":"86476",
    "sg:province":"Bayern",
    "wof:name":"Pp Private Protecting E. K.",
    "wof:placetype":"venue"
},
  "geometry": {"coordinates":[10.3748283386,48.3109550476],"type":"Point"}
}