{
  "type": "Feature",
  "properties": {
    "iso:country":"DE",
    "sg:address":"F\u00f6ssestr. 77a",
    "sg:city":"Hannover",
    "sg:phone":"+49 511/2104062",
    "sg:postcode":"30451",
    "sg:province":"Niedersachsen",
    "wof:name":"K P H-ingenieurb\u00fcro Gmbh",
    "wof:placetype":"venue"
},
  "geometry": {"coordinates":[9.704574585,52.3695449829],"type":"Point"}
}