{
  "type": "Feature",
  "properties": {
    "iso:country":"DE",
    "sg:address":"Alfred-Sch\u00fctte-All. 76",
    "sg:city":"K\u00f6ln",
    "sg:phone":"+49 4922/183990",
    "sg:postcode":"51105",
    "sg:province":"Nordrhein-Westfalen",
    "wof:name":"Sch\u00dctte Gmbh & Co. Kg",
    "wof:placetype":"venue"
},
  "geometry": {"coordinates":[6.982581,50.914146],"type":"Point"}
}