{
  "type": "Feature",
  "properties": {
    "iso:country":"DE",
    "sg:address":"Burloer Weg 111",
    "sg:city":"Bocholt",
    "sg:phone":"+49 2871/39405",
    "sg:postcode":"46397",
    "sg:province":"Nordrhein-Westfalen",
    "wof:name":"A. Gildhuis",
    "wof:placetype":"venue"
},
  "geometry": {"coordinates":[6.629987,51.849075],"type":"Point"}
}