{
  "type": "Feature",
  "properties": {
    "iso:country":"DE",
    "sg:address":"Schmieheimer Str. 12",
    "sg:city":"Ettenheim",
    "sg:phone":"+49 7822/5675",
    "sg:postcode":"77955",
    "sg:province":"Baden-W\u00fcrttemberg",
    "wof:name":"Abseits",
    "wof:placetype":"venue"
},
  "geometry": {"coordinates":[7.8144721985,48.2665710449],"type":"Point"}
}