{
  "type": "Feature",
  "properties": {
    "iso:country":"DE",
    "sg:address":"Berliner Str. 10",
    "sg:city":"Herdecke",
    "sg:phone":"+49 2330/4173",
    "sg:postcode":"58313",
    "sg:province":"Nordrhein-Westfalen",
    "wof:name":"G. Kleibrink",
    "wof:placetype":"venue"
},
  "geometry": {"coordinates":[7.429307,51.411411],"type":"Point"}
}