{
  "type": "Feature",
  "properties": {
    "iso:country":"DE",
    "sg:address":"Langenbick 69",
    "sg:city":"Wipperf\u00fcrth",
    "sg:phone":"+49 2267/880362",
    "sg:postcode":"51688",
    "sg:province":"Nordrhein-Westfalen",
    "wof:name":"Ingenieurb\u00fcro Madjd Planungs- Und Ingenieur Gmbh",
    "wof:placetype":"venue"
},
  "geometry": {"coordinates":[7.39646101,51.1114768982],"type":"Point"}
}