{
  "type": "Feature",
  "properties": {
    "iso:country":"DE",
    "sg:address":"Hardeweg 28",
    "sg:city":"Salzgitter",
    "sg:phone":"+49 5341/71540",
    "sg:postcode":"38229",
    "sg:province":"Niedersachsen",
    "wof:name":"C. Huth",
    "wof:placetype":"venue"
},
  "geometry": {"coordinates":[10.3538408279,52.1064376831],"type":"Point"}
}