{
  "type": "Feature",
  "properties": {
    "iso:country":"DE",
    "sg:address":"Lengericher Str.15 a",
    "sg:city":"Bawinkel",
    "sg:phone":"+49 5963/980360",
    "sg:postcode":"49844",
    "sg:province":"Niedersachsen",
    "wof:name":"Schroeder-wohnhaus",
    "wof:placetype":"venue"
},
  "geometry": {"coordinates":[7.449603,52.599957],"type":"Point"}
}