{
  "type": "Feature",
  "properties": {
    "iso:country":"DE",
    "sg:address":"Schlo\u00dfstr. 12",
    "sg:city":"Ratekau",
    "sg:phone":"+49 4502/4287",
    "sg:postcode":"23626",
    "sg:province":"Schleswig-Holstein",
    "wof:name":"Alfina Gesellschaft F\u00fcr Vermittlung Und Projektierung",
    "wof:placetype":"venue"
},
  "geometry": {"coordinates":[10.8077983856,53.9663238525],"type":"Point"}
}