{
  "type": "Feature",
  "properties": {
    "iso:country":"DE",
    "sg:address":"Bramfelder Chaussee",
    "sg:city":"Hamburg",
    "sg:phone":"+49 40/8904150",
    "sg:postcode":"22177",
    "sg:province":"Hamburg",
    "wof:name":"Is Industriemaschinen- Und Stahlwarenhandel Ali Firat",
    "wof:placetype":"venue"
},
  "geometry": {"coordinates":[10.05906,53.593552],"type":"Point"}
}