{
  "type": "Feature",
  "properties": {
    "iso:country":"DE",
    "sg:city":"Frankfurt",
    "sg:postcode":"60437",
    "sg:province":"Hessen",
    "wof:name":"Asteromed E.v.",
    "wof:placetype":"venue"
},
  "geometry": {"coordinates":[8.673598,50.199566],"type":"Point"}
}