{
  "type": "Feature",
  "properties": {
    "iso:country":"DE",
    "sg:address":"W\u00fcrzburger Str. 14",
    "sg:city":"Laatzen",
    "sg:phone":"+49 511/983530",
    "sg:postcode":"30880",
    "sg:province":"Niedersachsen",
    "wof:name":"Wvg Dipl. Kfm. Siegfr.lehmann Wohnungswirtschaftliche",
    "wof:placetype":"venue"
},
  "geometry": {"coordinates":[9.8061714172,52.3078041077],"type":"Point"}
}