{
  "type": "Feature",
  "properties": {
    "iso:country":"DE",
    "sg:address":"Herthastr. 27",
    "sg:city":"Bergfelde",
    "sg:phone":"+49 3303/501776",
    "sg:postcode":"16562",
    "sg:province":"Brandenburg",
    "wof:name":"Ferienhaus N\u00f6rdlich Von Berlin",
    "wof:placetype":"venue"
},
  "geometry": {"coordinates":[13.309633,52.661633],"type":"Point"}
}