{
  "type": "Feature",
  "properties": {
    "iso:country":"DE",
    "sg:address":"Reischplatz 1",
    "sg:city":"K\u00f6ln",
    "sg:phone":"+49 221/811538",
    "sg:postcode":"50679",
    "sg:province":"Nordrhein-Westfalen",
    "wof:name":"Karl Hammer",
    "wof:placetype":"venue"
},
  "geometry": {"coordinates":[6.9766259193,50.9367866516],"type":"Point"}
}