{
  "type": "Feature",
  "properties": {
    "iso:country":"DE",
    "sg:address":"Nr. 22",
    "sg:city":"Weischlitz",
    "sg:postcode":"08538",
    "sg:province":"Sachsen",
    "wof:name":"Gastst\u00e4tte Tobertitz",
    "wof:placetype":"venue"
},
  "geometry": {"coordinates":[12.0192060471,50.4428939819],"type":"Point"}
}