{
  "type": "Feature",
  "properties": {
    "iso:country":"DE",
    "sg:address":"Oestereiden",
    "sg:city":"R\u00fcthen",
    "sg:phone":"+49 2954/1089",
    "sg:postcode":"59602",
    "sg:province":"Nordrhein-Westfalen",
    "wof:name":"B. Biermann",
    "wof:placetype":"venue"
},
  "geometry": {"coordinates":[8.435715,51.490055],"type":"Point"}
}