{
  "type": "Feature",
  "properties": {
    "iso:country":"DE",
    "sg:address":"Schlo\u00dfb\u00fchl 6/3",
    "sg:city":"Bad Saulgau",
    "sg:phone":"+49 7583/3850",
    "sg:postcode":"88348",
    "sg:province":"Baden-W\u00fcrttemberg",
    "wof:name":"Franz Stankalla Gmbh",
    "wof:placetype":"venue"
},
  "geometry": {"coordinates":[9.588332,48.011024],"type":"Point"}
}