{
  "type": "Feature",
  "properties": {
    "iso:country":"DE",
    "sg:address":"Schl\u00e4gelstr. 11",
    "sg:city":"Herne",
    "sg:phone":"+49 2323/33197",
    "sg:postcode":"44628",
    "sg:province":"Nordrhein-Westfalen",
    "wof:name":"Blau-gelb Holthausen E. V. Herr Zauke",
    "wof:placetype":"venue"
},
  "geometry": {"coordinates":[7.2736949921,51.549156189],"type":"Point"}
}