{
  "type": "Feature",
  "properties": {
    "iso:country":"DE",
    "sg:address":"M\u00fcnzstr. 1",
    "sg:city":"Schwerin",
    "sg:postcode":"19055",
    "sg:province":"Mecklenburg-Vorpommern",
    "wof:name":"Hanse-merkur Versicherungsgruppe",
    "wof:placetype":"venue"
},
  "geometry": {"coordinates":[11.4190921783,53.6318321228],"type":"Point"}
}