{
  "type": "Feature",
  "properties": {
    "iso:country":"DE",
    "sg:address":"Burgstr. 33",
    "sg:city":"Nottuln",
    "sg:phone":"+49 2502/6156",
    "sg:postcode":"48301",
    "sg:province":"Nordrhein-Westfalen",
    "wof:name":"Gastst\u00e4tte Herbert Fels",
    "wof:placetype":"venue"
},
  "geometry": {"coordinates":[7.3566579819,51.931060791],"type":"Point"}
}