{
  "type": "Feature",
  "properties": {
    "iso:country":"DE",
    "sg:address":"Wernleitenstr. 3",
    "sg:city":"Siegsdorf",
    "sg:phone":"+49 8662/2543",
    "sg:postcode":"83313",
    "sg:province":"Bayern",
    "wof:name":"Willi Geistanger",
    "wof:placetype":"venue"
},
  "geometry": {"coordinates":[12.6495790482,47.8297767639],"type":"Point"}
}