{
  "type": "Feature",
  "properties": {
    "iso:country":"DE",
    "sg:address":"Vordere Gasse 4",
    "sg:city":"Wildberg",
    "sg:phone":"+49 7054/8974",
    "sg:postcode":"72218",
    "sg:province":"Baden-W\u00fcrttemberg",
    "wof:name":"Weinkauf",
    "wof:placetype":"venue"
},
  "geometry": {"coordinates":[8.7158870697,48.6238174438],"type":"Point"}
}