{
  "type": "Feature",
  "properties": {
    "iso:country":"DE",
    "sg:address":"Heinrich-Haanen-Str. 18",
    "sg:city":"Nettetal",
    "sg:phone":"+49 2153/912899",
    "sg:postcode":"41334",
    "sg:province":"Nordrhein-Westfalen",
    "wof:name":"Zimmerei Und Holzbau Fritz Schiffer Gmbh & Co. Kg",
    "wof:placetype":"venue"
},
  "geometry": {"coordinates":[6.2895498276,51.3135261536],"type":"Point"}
}