{
  "type": "Feature",
  "properties": {
    "iso:country":"DE",
    "sg:address":"Asbeckstr. 18",
    "sg:city":"Hamburg",
    "sg:phone":"+49 40/76750729",
    "sg:postcode":"21073",
    "sg:province":"Hamburg",
    "wof:name":"Udo Schwarz Architekt",
    "wof:placetype":"venue"
},
  "geometry": {"coordinates":[9.9768,53.456955],"type":"Point"}
}