{
  "type": "Feature",
  "properties": {
    "iso:country":"DE",
    "sg:address":"Fasanenweg 11",
    "sg:city":"B\u00fchlertann",
    "sg:phone":"+49 7973/889",
    "sg:postcode":"74424",
    "sg:province":"Baden-W\u00fcrttemberg",
    "wof:name":"Eckhardt Steinhauer Innenarchitekt",
    "wof:placetype":"venue"
},
  "geometry": {"coordinates":[9.920657,49.042515],"type":"Point"}
}