{
  "type": "Feature",
  "properties": {
    "iso:country":"DE",
    "sg:address":"Oberkasseler Ufer 4",
    "sg:city":"Bonn",
    "sg:phone":"+49 228/441103",
    "sg:postcode":"53227",
    "sg:province":"Nordrhein-Westfalen",
    "wof:name":"Cafe-restaurant Bundesh\u00e4uschen",
    "wof:placetype":"venue"
},
  "geometry": {"coordinates":[7.1566672325,50.7219734192],"type":"Point"}
}