{
  "type": "Feature",
  "properties": {
    "iso:country":"DE",
    "sg:address":"Nachtigallenweg 1",
    "sg:city":"Niederkr\u00fcchten",
    "sg:phone":"+49 2163/984129",
    "sg:postcode":"41372",
    "sg:province":"Nordrhein-Westfalen",
    "wof:name":"Norbert Schr\u00f6der",
    "wof:placetype":"venue"
},
  "geometry": {"coordinates":[6.1749081612,51.2097015381],"type":"Point"}
}