{
  "type": "Feature",
  "properties": {
    "iso:country":"DE",
    "sg:address":"Hauptstr. 83",
    "sg:city":"Offenburg",
    "sg:phone":"+49 781/23061",
    "sg:postcode":"77652",
    "sg:province":"Baden-W\u00fcrttemberg",
    "wof:name":"Top Reisen Zimmermann Gmbh",
    "wof:placetype":"venue"
},
  "geometry": {"coordinates":[7.9429831505,48.4689979553],"type":"Point"}
}