{
  "type": "Feature",
  "properties": {
    "iso:country":"DE",
    "sg:address":"Bahnhofstr. 85 a",
    "sg:city":"Herne",
    "sg:phone":"+49 2323/50980",
    "sg:postcode":"44623",
    "sg:province":"Nordrhein-Westfalen",
    "wof:name":"Lucky Playtime Automaten Gmbh",
    "wof:placetype":"venue"
},
  "geometry": {"coordinates":[7.2198719978,51.5432052612],"type":"Point"}
}