{
  "type": "Feature",
  "properties": {
    "iso:country":"DE",
    "sg:address":"Von-Graba-Str. 1",
    "sg:city":"Gl\u00fcckstadt",
    "sg:phone":"+49 4124/2263",
    "sg:postcode":"25348",
    "sg:province":"Schleswig-Holstein",
    "wof:name":"Dieter Mohrbach Masseur",
    "wof:placetype":"venue"
},
  "geometry": {"coordinates":[9.429016,53.792274],"type":"Point"}
}