{
  "type": "Feature",
  "properties": {
    "iso:country":"DE",
    "sg:address":"Schillerstr. 10",
    "sg:city":"Emden",
    "sg:phone":"+49 4921/45381",
    "sg:postcode":"26721",
    "sg:province":"Niedersachsen",
    "wof:name":"Herbert Baltrusch",
    "wof:placetype":"venue"
},
  "geometry": {"coordinates":[7.207186,53.377991],"type":"Point"}
}