{
  "type": "Feature",
  "properties": {
    "iso:country":"DE",
    "sg:address":"An der Kluse 13",
    "sg:city":"Hopsten",
    "sg:phone":"+49 5458/93260",
    "sg:postcode":"48496",
    "sg:province":"Nordrhein-Westfalen",
    "wof:name":"Paul Uphaus Ingenieur",
    "wof:placetype":"venue"
},
  "geometry": {"coordinates":[7.5995731354,52.3805274963],"type":"Point"}
}