{
  "type": "Feature",
  "properties": {
    "iso:country":"DE",
    "sg:address":"Magalettigasse 7",
    "sg:city":"Passau",
    "sg:phone":"+49 851/52158",
    "sg:postcode":"94032",
    "sg:province":"Bayern",
    "wof:name":"Elektrowickelei J. Koloczek Inh. Peter Koloczek",
    "wof:placetype":"venue"
},
  "geometry": {"coordinates":[13.4493093491,48.5745658875],"type":"Point"}
}