{
  "type": "Feature",
  "properties": {
    "iso:country":"DE",
    "sg:address":"Rammersberg 17",
    "sg:city":"Hunderdorf",
    "sg:phone":"+49 9961/359",
    "sg:postcode":"94336",
    "sg:province":"Bayern",
    "wof:name":"Marianne Maier",
    "wof:placetype":"venue"
},
  "geometry": {"coordinates":[12.688729,48.95055],"type":"Point"}
}