{
  "type": "Feature",
  "properties": {
    "iso:country":"DE",
    "sg:address":"Birkenweg 12",
    "sg:city":"Stephansposching",
    "sg:phone":"+49 9935/903171",
    "sg:postcode":"94569",
    "sg:province":"Bayern",
    "wof:name":"Acv-coscmetics.de Ihr Parfumshop Im Internet",
    "wof:placetype":"venue"
},
  "geometry": {"coordinates":[12.7957191467,48.8183021545],"type":"Point"}
}