{
  "type": "Feature",
  "properties": {
    "iso:country":"DE",
    "sg:address":"Stra\u00dfe 9 3 Ecke T\u00f6pchin.W.",
    "sg:city":"Berlin",
    "sg:phone":"+49 30/7456041",
    "sg:postcode":"12309",
    "sg:province":"Berlin",
    "wof:name":"Dynamic Fitness-studio Inh. Ingo Freier",
    "wof:placetype":"venue"
},
  "geometry": {"coordinates":[13.4124746323,52.3915939331],"type":"Point"}
}