{
  "type": "Feature",
  "properties": {
    "iso:country":"DE",
    "sg:address":"Wiesentweg 3",
    "sg:city":"Wiesenttal",
    "sg:phone":"+49 9196/233",
    "sg:postcode":"91346",
    "sg:province":"Bayern",
    "wof:name":"H. W. Prager Rechtsanwalt",
    "wof:placetype":"venue"
},
  "geometry": {"coordinates":[11.2613830566,49.8026313782],"type":"Point"}
}