{
  "type": "Feature",
  "properties": {
    "iso:country":"DE",
    "sg:address":"Poststr. 1",
    "sg:city":"Schwaf\u00f6rden",
    "sg:phone":"+49 4277/963020",
    "sg:postcode":"27252",
    "sg:province":"Niedersachsen",
    "wof:name":"Grafik Und Design Prillwitz E. K.",
    "wof:placetype":"venue"
},
  "geometry": {"coordinates":[8.823291,52.736691],"type":"Point"}
}