{
  "type": "Feature",
  "properties": {
    "iso:country":"DE",
    "sg:address":"Amundsenstr. 13",
    "sg:city":"Delmenhorst",
    "sg:phone":"+49 4221/61595",
    "sg:postcode":"27749",
    "sg:province":"Niedersachsen",
    "wof:name":"Hans-joachim Hespos",
    "wof:placetype":"venue"
},
  "geometry": {"coordinates":[8.6487779617,53.0385131836],"type":"Point"}
}