{
  "type": "Feature",
  "properties": {
    "iso:country":"DE",
    "sg:address":"Buchhornplatz 5",
    "sg:city":"Friedrichshafen",
    "sg:phone":"+49 7541/24551",
    "sg:postcode":"88045",
    "sg:province":"Baden-W\u00fcrttemberg",
    "wof:name":"Geselligkeitsverein Frohsinn E. V.",
    "wof:placetype":"venue"
},
  "geometry": {"coordinates":[9.48133564,47.6512413025],"type":"Point"}
}