{
  "type": "Feature",
  "properties": {
    "iso:country":"DE",
    "sg:address":"Schenkendorfstr. 20",
    "sg:city":"Stuttgart",
    "sg:phone":"+49 711/653849",
    "sg:postcode":"70193",
    "sg:province":"Baden-W\u00fcrttemberg",
    "wof:name":"Karl Reichle",
    "wof:placetype":"venue"
},
  "geometry": {"coordinates":[9.142353,48.775764],"type":"Point"}
}