{
  "type": "Feature",
  "properties": {
    "iso:country":"DE",
    "sg:address":"Stuttgarter Str. 18",
    "sg:city":"Ebersbach",
    "sg:phone":"+49 7163/3144",
    "sg:postcode":"73061",
    "sg:province":"Baden-W\u00fcrttemberg",
    "wof:name":"Ernst Held",
    "wof:placetype":"venue"
},
  "geometry": {"coordinates":[9.521285,48.714397],"type":"Point"}
}