{
  "type": "Feature",
  "properties": {
    "iso:country":"DE",
    "sg:address":"Hauptstr. 18",
    "sg:city":"Nu\u00dfbaum",
    "sg:phone":"+49 6751/6232",
    "sg:postcode":"55569",
    "sg:province":"Rheinland-Pfalz",
    "wof:name":"Systembau Kappen Gmbh",
    "wof:placetype":"venue"
},
  "geometry": {"coordinates":[7.612419,49.799236],"type":"Point"}
}