{
  "type": "Feature",
  "properties": {
    "iso:country":"DE",
    "sg:address":"Wieher Kirchweg 31",
    "sg:city":"Mettingen",
    "sg:phone":"+49 5452/98505",
    "sg:postcode":"49497",
    "sg:province":"Nordrhein-Westfalen",
    "wof:name":"Ulrich Kr\u00f6ner",
    "wof:placetype":"venue"
},
  "geometry": {"coordinates":[7.776093,52.306995],"type":"Point"}
}