{
  "type": "Feature",
  "properties": {
    "iso:country":"DE",
    "sg:address":"Kohlenstr. 12",
    "sg:city":"Essen",
    "sg:phone":"+49 201/571116",
    "sg:postcode":"45289",
    "sg:province":"Nordrhein-Westfalen",
    "wof:name":"H. Jablonowski Gmbh",
    "wof:placetype":"venue"
},
  "geometry": {"coordinates":[7.11697,51.410301],"type":"Point"}
}