{
  "type": "Feature",
  "properties": {
    "iso:country":"DE",
    "sg:address":"Kittelbachstr. 20",
    "sg:city":"D\u00fcsseldorf",
    "sg:phone":"+49 211/4790789",
    "sg:postcode":"40489",
    "sg:province":"Nordrhein-Westfalen",
    "wof:name":"Dr. Med. H. Niederschlag \u00c4rztin F\u00fcr Allgemeinmedizin",
    "wof:placetype":"venue"
},
  "geometry": {"coordinates":[6.7413311005,51.2935333252],"type":"Point"}
}