{
  "type": "Feature",
  "properties": {
    "iso:country":"DE",
    "sg:address":"Meidericher Str. 6-8",
    "sg:city":"Duisburg",
    "sg:phone":"+49 4920/330020",
    "sg:postcode":"47058",
    "sg:province":"Nordrhein-Westfalen",
    "wof:name":"Friemann & Wolf Batterietechnik Gmbh",
    "wof:placetype":"venue"
},
  "geometry": {"coordinates":[6.79462,51.443542],"type":"Point"}
}