{
  "type": "Feature",
  "properties": {
    "iso:country":"DE",
    "sg:address":"Hauptstr. 78",
    "sg:city":"Weibersbrunn",
    "sg:phone":"+49 6094/984933",
    "sg:postcode":"63879",
    "sg:province":"Bayern",
    "wof:name":"Erich Buhr",
    "wof:placetype":"venue"
},
  "geometry": {"coordinates":[9.3685741425,49.9304122925],"type":"Point"}
}