{
  "type": "Feature",
  "properties": {
    "iso:country":"DE",
    "sg:address":"Gro\u00dfe Bergstr. 229",
    "sg:city":"Hamburg",
    "sg:phone":"+49 40/384539",
    "sg:postcode":"22767",
    "sg:province":"Hamburg",
    "wof:name":"Sanit\u00e4tshaus Emil Funcke",
    "wof:placetype":"venue"
},
  "geometry": {"coordinates":[9.9416570663,53.551940918],"type":"Point"}
}