{
  "type": "Feature",
  "properties": {
    "iso:country":"DE",
    "sg:address":"Schlangenbader Str. 25",
    "sg:city":"Berlin",
    "sg:phone":"+49 30/8236042",
    "sg:postcode":"14197",
    "sg:province":"Berlin",
    "wof:name":"St. Rochus-apotheke Inhaber Susan Kalisz E. K.",
    "wof:placetype":"venue"
},
  "geometry": {"coordinates":[13.307878,52.472706],"type":"Point"}
}