{
  "type": "Feature",
  "properties": {
    "iso:country":"DE",
    "sg:address":"Leipziger Str. 11",
    "sg:city":"Hessisch Lichtenau",
    "sg:phone":"+49 5602/93440",
    "sg:postcode":"37235",
    "sg:province":"Hessen",
    "wof:name":"Gerhard Eysert",
    "wof:placetype":"venue"
},
  "geometry": {"coordinates":[9.6951503754,51.2122993469],"type":"Point"}
}