{
  "type": "Feature",
  "properties": {
    "iso:country":"DE",
    "sg:address":"Lehmingen",
    "sg:city":"Oettingen",
    "sg:phone":"+49 9082/2763",
    "sg:postcode":"86732",
    "sg:province":"Bayern",
    "wof:name":"K. Meyer",
    "wof:placetype":"venue"
},
  "geometry": {"coordinates":[10.61056,48.98045],"type":"Point"}
}