{
  "type": "Feature",
  "properties": {
    "iso:country":"DE",
    "sg:address":"Oberstr. 20",
    "sg:city":"Darmstadt",
    "sg:postcode":"64297",
    "sg:province":"Hessen",
    "wof:name":"Eberst\u00e4dter B\u00fcrgerverein Von 1980 E. V.",
    "wof:placetype":"venue"
},
  "geometry": {"coordinates":[8.6461696625,49.8180274963],"type":"Point"}
}