{
  "type": "Feature",
  "properties": {
    "iso:country":"DE",
    "sg:address":"B\u00fcttnerstr 15",
    "sg:city":"Hannover",
    "sg:phone":"+49 511/939370",
    "sg:postcode":"30165",
    "sg:province":"Niedersachsen",
    "wof:name":"Benatzky Druck Und Medien Gmbh",
    "wof:placetype":"venue"
},
  "geometry": {"coordinates":[9.729423,52.408974],"type":"Point"}
}