{
  "type": "Feature",
  "properties": {
    "iso:country":"DE",
    "sg:address":"Ingolst\u00e4dter Str. 70",
    "sg:city":"Pfaffenhofen",
    "sg:phone":"+49 8441/1377",
    "sg:postcode":"85276",
    "sg:province":"Bayern",
    "wof:name":"Schwimmbad",
    "wof:placetype":"venue"
},
  "geometry": {"coordinates":[11.5104675293,48.5372505188],"type":"Point"}
}