{
  "type": "Feature",
  "properties": {
    "iso:country":"DE",
    "sg:address":"Isarstr. 17a",
    "sg:city":"Marzling",
    "sg:phone":"+49 8161/64440",
    "sg:postcode":"85417",
    "sg:province":"Bayern",
    "wof:name":"Josef Gi\u00dfibl",
    "wof:placetype":"venue"
},
  "geometry": {"coordinates":[11.7925987244,48.4072227478],"type":"Point"}
}