{
  "type": "Feature",
  "properties": {
    "iso:country":"DE",
    "sg:address":"Markgr\u00f6ninger Str. 23",
    "sg:city":"M\u00f6glingen",
    "sg:phone":"+49 7141/481092",
    "sg:postcode":"71696",
    "sg:province":"Baden-W\u00fcrttemberg",
    "wof:name":"Willi S\u00fclzle",
    "wof:placetype":"venue"
},
  "geometry": {"coordinates":[9.124595,48.887951],"type":"Point"}
}