{
  "type": "Feature",
  "properties": {
    "iso:country":"DE",
    "sg:address":"Maistr. 69",
    "sg:city":"M\u00fcnchen",
    "sg:phone":"+49 89/988747",
    "sg:postcode":"80337",
    "sg:province":"Bayern",
    "wof:name":"Abes Gesellschaft F\u00fcr Allgemeine Elektromechanische",
    "wof:placetype":"venue"
},
  "geometry": {"coordinates":[11.561287,48.125984],"type":"Point"}
}