{
  "type": "Feature",
  "properties": {
    "iso:country":"DE",
    "sg:address":"Wilhelm-Rinkens-Str. 8",
    "sg:city":"Eisenach",
    "sg:phone":"+49 3691/624624",
    "sg:postcode":"99817",
    "sg:province":"Th\u00fcringen",
    "wof:name":"Hertz Th\u00fcringer Auto-rent Gmbh",
    "wof:placetype":"venue"
},
  "geometry": {"coordinates":[10.318767,50.980701],"type":"Point"}
}