{
  "type": "Feature",
  "properties": {
    "iso:country":"DE",
    "sg:address":"Ratzeburger Allee 38",
    "sg:city":"L\u00fcbeck",
    "sg:phone":"+49 451/596622",
    "sg:postcode":"23562",
    "sg:province":"Schleswig-Holstein",
    "wof:name":"Itzehoer Versicherungen",
    "wof:placetype":"venue"
},
  "geometry": {"coordinates":[10.7020282745,53.8515586853],"type":"Point"}
}