{
  "type": "Feature",
  "properties": {
    "iso:country":"DE",
    "sg:address":"Am Ring 2",
    "sg:city":"Fuchshain",
    "sg:phone":"+49 34297/43077",
    "sg:postcode":"04683",
    "sg:province":"Sachsen",
    "wof:name":"R. Hepner",
    "wof:placetype":"venue"
},
  "geometry": {"coordinates":[12.534927,51.281895],"type":"Point"}
}