{
  "type": "Feature",
  "properties": {
    "iso:country":"DE",
    "sg:address":"Neufelder Weg 1a",
    "sg:city":"Schleswig",
    "sg:phone":"+49 4621/53269",
    "sg:postcode":"24837",
    "sg:province":"Schleswig-Holstein",
    "wof:name":"Ev. Pfarramt Landeskrankenhaus",
    "wof:placetype":"venue"
},
  "geometry": {"coordinates":[9.5659608841,54.5307579041],"type":"Point"}
}