{
  "type": "Feature",
  "properties": {
    "iso:country":"DE",
    "sg:address":"Kolumbusstr. 121",
    "sg:city":"M\u00fclheim",
    "sg:phone":"+49 208/498517",
    "sg:postcode":"45472",
    "sg:province":"Nordrhein-Westfalen",
    "wof:name":"Norbert Hippler Architekt",
    "wof:placetype":"venue"
},
  "geometry": {"coordinates":[6.947596,51.430367],"type":"Point"}
}