{
  "type": "Feature",
  "properties": {
    "iso:country":"DE",
    "sg:address":"Sonnenstrasse 38",
    "sg:city":"Hohenstein-Ernstthal",
    "sg:phone":"+49 3723",
    "sg:postcode":"09337",
    "sg:province":"Sachsen",
    "wof:name":"Steffens Homepage!",
    "wof:placetype":"venue"
},
  "geometry": {"coordinates":[12.729114,50.797619],"type":"Point"}
}