{
  "type": "Feature",
  "properties": {
    "iso:country":"DE",
    "sg:address":"Hauptstr. 28",
    "sg:city":"Langensendelbach",
    "sg:phone":"+49 9133/4600",
    "sg:postcode":"91094",
    "sg:province":"Bayern",
    "wof:name":"Johann Mirsberger",
    "wof:placetype":"venue"
},
  "geometry": {"coordinates":[11.0682067871,49.6408462524],"type":"Point"}
}