{
  "type": "Feature",
  "properties": {
    "iso:country":"DE",
    "sg:address":"Kleeweg 24",
    "sg:city":"Tecklenburg",
    "sg:phone":"+49 5455/1082",
    "sg:postcode":"49545",
    "sg:province":"Nordrhein-Westfalen",
    "wof:name":"G\u00fcnter Sellmeier Architekt",
    "wof:placetype":"venue"
},
  "geometry": {"coordinates":[7.738636,52.225552],"type":"Point"}
}