{
  "type": "Feature",
  "properties": {
    "iso:country":"DE",
    "sg:address":"Lindenstr. 37",
    "sg:city":"Pinneberg",
    "sg:phone":"+49 4101/514999",
    "sg:postcode":"25421",
    "sg:province":"Schleswig-Holstein",
    "wof:name":"Michael Behling",
    "wof:placetype":"venue"
},
  "geometry": {"coordinates":[9.7988595963,53.6604385376],"type":"Point"}
}