{
  "type": "Feature",
  "properties": {
    "iso:country":"DE",
    "sg:address":"Baalborner Weg 11",
    "sg:city":"Kaiserslautern",
    "sg:phone":"+49 631/42319",
    "sg:postcode":"67657",
    "sg:province":"Rheinland-Pfalz",
    "wof:name":"E. Morell",
    "wof:placetype":"venue"
},
  "geometry": {"coordinates":[7.782033,49.453026],"type":"Point"}
}