{
  "type": "Feature",
  "properties": {
    "iso:country":"DE",
    "sg:address":"Thomas-M\u00fcntzer-Str. 7",
    "sg:city":"Lutherstadt Wittenberg",
    "sg:phone":"+49 3491/410625",
    "sg:postcode":"06886",
    "sg:province":"Sachsen-Anhalt",
    "wof:name":"D. Bullmann",
    "wof:placetype":"venue"
},
  "geometry": {"coordinates":[12.6318330765,51.8785171509],"type":"Point"}
}