{
  "type": "Feature",
  "properties": {
    "iso:country":"DE",
    "sg:address":"Sch\u00fctzenstr. 10",
    "sg:city":"Lauf",
    "sg:phone":"+49 9123/2415",
    "sg:postcode":"91207",
    "sg:province":"Bayern",
    "wof:name":"Restaurant Schie\u00dfhaus",
    "wof:placetype":"venue"
},
  "geometry": {"coordinates":[11.2678747177,49.507610321],"type":"Point"}
}