{
  "type": "Feature",
  "properties": {
    "iso:country":"DE",
    "sg:address":"Carnotstr. 6",
    "sg:city":"Berlin",
    "sg:phone":"+49 30/3999110",
    "sg:postcode":"10587",
    "sg:province":"Berlin",
    "wof:name":"Gravis Beteiligungs Ag",
    "wof:placetype":"venue"
},
  "geometry": {"coordinates":[13.320246,52.523666],"type":"Point"}
}