{
  "type": "Feature",
  "properties": {
    "iso:country":"DE",
    "sg:address":"Am Oberwald",
    "sg:city":"Callenberg",
    "sg:postcode":"09337",
    "sg:province":"Sachsen",
    "wof:name":"Campingplatz",
    "wof:placetype":"venue"
},
  "geometry": {"coordinates":[12.688083,50.815411],"type":"Point"}
}