{
  "type": "Feature",
  "properties": {
    "iso:country":"DE",
    "sg:address":"Industriering Ost 85",
    "sg:city":"Kempen",
    "sg:phone":"+49 2152/91950",
    "sg:postcode":"47906",
    "sg:province":"Nordrhein-Westfalen",
    "wof:name":"Johannes Hupperten Transport Gmbh",
    "wof:placetype":"venue"
},
  "geometry": {"coordinates":[6.4312348366,51.3755111694],"type":"Point"}
}