{
  "type": "Feature",
  "properties": {
    "iso:country":"DE",
    "sg:address":"Asperdener Str. 8",
    "sg:city":"Goch",
    "sg:postcode":"47574",
    "sg:province":"Nordrhein-Westfalen",
    "wof:name":"Heinrich Schmitz Kiesbaggerei E. K.",
    "wof:placetype":"venue"
},
  "geometry": {"coordinates":[6.1437678337,51.6812515259],"type":"Point"}
}