{
  "type": "Feature",
  "properties": {
    "iso:country":"DE",
    "sg:address":"Margarethe-von-Wrangell-Weg 1",
    "sg:city":"Ulm",
    "sg:phone":"+49 731/385070",
    "sg:postcode":"89075",
    "sg:province":"Baden-W\u00fcrttemberg",
    "wof:name":"Biotrend Ag",
    "wof:placetype":"venue"
},
  "geometry": {"coordinates":[9.9493083954,48.4130859375],"type":"Point"}
}