{
  "type": "Feature",
  "properties": {
    "iso:country":"DE",
    "sg:address":"Lindenstr. 18",
    "sg:city":"Priestewitz",
    "sg:postcode":"01561",
    "sg:province":"Sachsen",
    "wof:name":"Zottewitzer Bautr\u00e4gergesellschaft Mbh",
    "wof:placetype":"venue"
},
  "geometry": {"coordinates":[13.44632,51.249119],"type":"Point"}
}