{
  "type": "Feature",
  "properties": {
    "iso:country":"DE",
    "sg:address":"Fasanenallee 4",
    "sg:city":"Gro\u00dfheubach",
    "sg:postcode":"63920",
    "sg:province":"Bayern",
    "wof:name":"H. Umscheid",
    "wof:placetype":"venue"
},
  "geometry": {"coordinates":[9.2239103317,49.7336425781],"type":"Point"}
}