{
  "type": "Feature",
  "properties": {
    "iso:country":"DE",
    "sg:address":"Bahnhofstr. 58",
    "sg:city":"Kusel",
    "sg:phone":"+49 6381/3011",
    "sg:postcode":"66869",
    "sg:province":"Rheinland-Pfalz",
    "wof:name":"Reidel Und Knapp Rechtsanw\u00e4lte",
    "wof:placetype":"venue"
},
  "geometry": {"coordinates":[7.4081788063,49.5372962952],"type":"Point"}
}