{
  "type": "Feature",
  "properties": {
    "iso:country":"DE",
    "sg:address":"Kl\u00e4ngeweg 2",
    "sg:city":"Eiterfeld",
    "sg:phone":"+49 6676/1510",
    "sg:postcode":"36132",
    "sg:province":"Hessen",
    "wof:name":"R. Abel",
    "wof:placetype":"venue"
},
  "geometry": {"coordinates":[9.86266,50.777786],"type":"Point"}
}