{
  "type": "Feature",
  "properties": {
    "iso:country":"DE",
    "sg:address":"Gr\u00f6pelinger Heerstr. 60",
    "sg:city":"Bremen",
    "sg:phone":"+49 421/6164240",
    "sg:postcode":"28237",
    "sg:province":"Bremen",
    "wof:name":"Birgit Grahl",
    "wof:placetype":"venue"
},
  "geometry": {"coordinates":[8.7694063187,53.1104621887],"type":"Point"}
}