{
  "type": "Feature",
  "properties": {
    "iso:country":"DE",
    "sg:address":"Kellm\u00fcnzer Str. 9",
    "sg:city":"Dettingen",
    "sg:phone":"+49 7354/8207",
    "sg:postcode":"88451",
    "sg:province":"Baden-W\u00fcrttemberg",
    "wof:name":"Molkereigenossenschaft Unterdettingen Eg",
    "wof:placetype":"venue"
},
  "geometry": {"coordinates":[10.1106176376,48.1097984314],"type":"Point"}
}