{
  "type": "Feature",
  "properties": {
    "iso:country":"DE",
    "sg:address":"Am Markt 23",
    "sg:city":"Storkow",
    "sg:postcode":"15859",
    "sg:province":"Brandenburg",
    "wof:name":"Generalvertretung Hans-j\u00fcrgen Schreiter E. Kfm.",
    "wof:placetype":"venue"
},
  "geometry": {"coordinates":[13.9314632416,52.2556495667],"type":"Point"}
}