{
  "type": "Feature",
  "properties": {
    "iso:country":"DE",
    "sg:address":"W\u00f6lflkofen 15",
    "sg:city":"Adlkofen",
    "sg:phone":"+49 8707/8334",
    "sg:postcode":"84166",
    "sg:province":"Bayern",
    "wof:name":"Ha-ra Cleaning-express Adlm\u00fcller Vertriebs Gmbh",
    "wof:placetype":"venue"
},
  "geometry": {"coordinates":[12.2454919815,48.5444869995],"type":"Point"}
}