{
  "type": "Feature",
  "properties": {
    "iso:country":"DE",
    "sg:address":"Sparkassenplatz 11",
    "sg:city":"Pfaffenhofen",
    "sg:phone":"+49 8441/4688",
    "sg:postcode":"85276",
    "sg:province":"Bayern",
    "wof:name":"Bellanca Gmbh",
    "wof:placetype":"venue"
},
  "geometry": {"coordinates":[11.5099611282,48.5290412903],"type":"Point"}
}