{
  "type": "Feature",
  "properties": {
    "iso:country":"DE",
    "sg:address":"Markdorfer Str. 8",
    "sg:city":"Bermatingen",
    "sg:phone":"+49 7544/71710",
    "sg:postcode":"88697",
    "sg:province":"Baden-W\u00fcrttemberg",
    "wof:name":"F. Kutter",
    "wof:placetype":"venue"
},
  "geometry": {"coordinates":[9.3504247665,47.7298736572],"type":"Point"}
}