{
  "type": "Feature",
  "properties": {
    "iso:country":"DE",
    "sg:address":"Rudolf-Breitscheid-Str. 21 A",
    "sg:city":"Wismar",
    "sg:phone":"+49 3841/636661",
    "sg:postcode":"23968",
    "sg:province":"Mecklenburg-Vorpommern",
    "wof:name":"China Restaurant Tschang",
    "wof:placetype":"venue"
},
  "geometry": {"coordinates":[11.4214630127,53.9004325867],"type":"Point"}
}