{
  "type": "Feature",
  "properties": {
    "iso:country":"DE",
    "sg:address":"Hauptstr. 27",
    "sg:city":"Woosmer",
    "sg:phone":"+49 38759/20456",
    "sg:postcode":"19303",
    "sg:province":"Mecklenburg-Vorpommern",
    "wof:name":"Lange Gbr Inh. Ilse Und Peter Lange",
    "wof:placetype":"venue"
},
  "geometry": {"coordinates":[11.179792,53.201614],"type":"Point"}
}