{
  "type": "Feature",
  "properties": {
    "iso:country":"DE",
    "sg:address":"Ortsstr. 20",
    "sg:city":"Kirkel",
    "sg:phone":"+49 6841/8743",
    "sg:postcode":"66459",
    "sg:province":"Saarland",
    "wof:name":"Karl Hussong",
    "wof:placetype":"venue"
},
  "geometry": {"coordinates":[7.2819471359,49.3181991577],"type":"Point"}
}