{
  "type": "Feature",
  "properties": {
    "iso:country":"DE",
    "sg:address":"Oberherrlinger Str. 20",
    "sg:city":"Blaustein",
    "sg:phone":"+49 7304/6669",
    "sg:postcode":"89134",
    "sg:province":"Baden-W\u00fcrttemberg",
    "wof:name":"Kath. Pfarramt St. Andreas",
    "wof:placetype":"venue"
},
  "geometry": {"coordinates":[9.8961610794,48.4211921692],"type":"Point"}
}