{
  "type": "Feature",
  "properties": {
    "iso:country":"DE",
    "sg:address":"Industriestr. 19",
    "sg:city":"Verl",
    "sg:phone":"+49 4952/463211",
    "sg:postcode":"33415",
    "sg:province":"Nordrhein-Westfalen",
    "wof:name":"Sb-markt U. Bierverlag Westerbarkey Gmbh & Co. Kg",
    "wof:placetype":"venue"
},
  "geometry": {"coordinates":[8.466798,51.896084],"type":"Point"}
}