{
  "type": "Feature",
  "properties": {
    "iso:country":"DE",
    "sg:address":"Binderslebener Landstr. 131",
    "sg:city":"Erfurt",
    "sg:phone":"+49 361/2256435",
    "sg:postcode":"99092",
    "sg:province":"Th\u00fcringen",
    "wof:name":"Arno Rudolph",
    "wof:placetype":"venue"
},
  "geometry": {"coordinates":[10.986215,50.971962],"type":"Point"}
}