{
  "type": "Feature",
  "properties": {
    "iso:country":"DE",
    "sg:address":"Hirschstr. 18",
    "sg:city":"Pirmasens",
    "sg:phone":"+49 6331/13091",
    "sg:postcode":"66953",
    "sg:province":"Rheinland-Pfalz",
    "wof:name":"Andreas Motsch",
    "wof:placetype":"venue"
},
  "geometry": {"coordinates":[7.608632,49.20842],"type":"Point"}
}