{
  "type": "Feature",
  "properties": {
    "iso:country":"DE",
    "sg:address":"Elsa-Br\u00e4ndstr\u00f6m-Str. 6",
    "sg:city":"Bremen",
    "sg:phone":"+49 421/232271",
    "sg:postcode":"28359",
    "sg:province":"Bremen",
    "wof:name":"Sigrid Herlyn \u00c4rztin F\u00fcr Psychiatrie",
    "wof:placetype":"venue"
},
  "geometry": {"coordinates":[8.8637046814,53.095199585],"type":"Point"}
}