{
  "type": "Feature",
  "properties": {
    "iso:country":"DE",
    "sg:address":"Molkereistr.",
    "sg:city":"Sittensen",
    "sg:postcode":"27419",
    "sg:province":"Niedersachsen",
    "wof:name":"Hoga Grundst\u00fccksankauf Und -verwaltungs Gmbh",
    "wof:placetype":"venue"
},
  "geometry": {"coordinates":[9.5058031082,53.2893676758],"type":"Point"}
}