{
  "type": "Feature",
  "properties": {
    "iso:country":"DE",
    "sg:address":"Heinersdorf",
    "sg:city":"Bechhofen",
    "sg:phone":"+49 9822/5159",
    "sg:postcode":"91572",
    "sg:province":"Bayern",
    "wof:name":"Milan Vaclavik Heilpraktiker",
    "wof:placetype":"venue"
},
  "geometry": {"coordinates":[10.5769748688,49.1567955017],"type":"Point"}
}