{
  "type": "Feature",
  "properties": {
    "iso:country":"DE",
    "sg:address":"St\u00fcvestr. 1",
    "sg:city":"Hannover",
    "sg:phone":"+49 511/888163",
    "sg:postcode":"30173",
    "sg:province":"Niedersachsen",
    "wof:name":"H.-d. Kneuertz",
    "wof:placetype":"venue"
},
  "geometry": {"coordinates":[9.75615,52.360268],"type":"Point"}
}