{
  "type": "Feature",
  "properties": {
    "iso:country":"DE",
    "sg:address":"Hintere Sch\u00f6bstr. 2",
    "sg:city":"Albersweiler",
    "sg:postcode":"76857",
    "sg:province":"Rheinland-Pfalz",
    "wof:name":"Zitra-fol - G\u00fcnter Klau\u00df Klebebandfabrikation",
    "wof:placetype":"venue"
},
  "geometry": {"coordinates":[8.030106,49.219875],"type":"Point"}
}