{
  "type": "Feature",
  "properties": {
    "iso:country":"DE",
    "sg:address":"Josef-Schregel-Str. 32",
    "sg:city":"D\u00fcren",
    "sg:phone":"+49 2421/13326",
    "sg:postcode":"52349",
    "sg:province":"Nordrhein-Westfalen",
    "wof:name":"Optik Bruno Hilden Gmbh",
    "wof:placetype":"venue"
},
  "geometry": {"coordinates":[6.4819860458,50.8066291809],"type":"Point"}
}