{
  "type": "Feature",
  "properties": {
    "iso:country":"DE",
    "sg:address":"Simmling 25",
    "sg:city":"Deggendorf",
    "sg:phone":"+49 991/32651",
    "sg:postcode":"94469",
    "sg:province":"Bayern",
    "wof:name":"Wilhelm Haberl",
    "wof:placetype":"venue"
},
  "geometry": {"coordinates":[12.9880809784,48.8341064453],"type":"Point"}
}