{
  "type": "Feature",
  "properties": {
    "iso:country":"DE",
    "sg:address":"Gaisbergstr. 9",
    "sg:city":"Tittmoning",
    "sg:phone":"+49 8683/1377",
    "sg:postcode":"84529",
    "sg:province":"Bayern",
    "wof:name":"Str\u00f6ber Gmbh",
    "wof:placetype":"venue"
},
  "geometry": {"coordinates":[12.774208,48.055603],"type":"Point"}
}