{
  "type": "Feature",
  "properties": {
    "iso:country":"DE",
    "sg:address":"Bahnhofsweg 6 a",
    "sg:city":"Mechernich",
    "sg:phone":"+49 2256/952003",
    "sg:postcode":"53894",
    "sg:province":"Nordrhein-Westfalen",
    "wof:name":"Complan Beratungs- Und Handels Gmbh",
    "wof:placetype":"venue"
},
  "geometry": {"coordinates":[6.7100019455,50.6220283508],"type":"Point"}
}