{
  "type": "Feature",
  "properties": {
    "iso:country":"DE",
    "sg:address":"Meinekestr. 22",
    "sg:city":"Berlin",
    "sg:phone":"+49 30/8871470",
    "sg:postcode":"10719",
    "sg:province":"Berlin",
    "wof:name":"Pul Express Gmbh",
    "wof:placetype":"venue"
},
  "geometry": {"coordinates":[13.329249382,52.50182724],"type":"Point"}
}