{
  "type": "Feature",
  "properties": {
    "iso:country":"DE",
    "sg:address":"Parkstrasse 20",
    "sg:city":"Bad Vilbel",
    "sg:phone":"+49 6101/600700",
    "sg:postcode":"61118",
    "sg:province":"Hessen",
    "wof:name":"Am Kurpark, Hotel",
    "wof:placetype":"venue"
},
  "geometry": {"coordinates":[8.7413673401,50.1833305359],"type":"Point"}
}