{
  "type": "Feature",
  "properties": {
    "iso:country":"DE",
    "sg:address":"Dornrosenstr. 16",
    "sg:city":"Faulbach",
    "sg:phone":"+49 9392/8577",
    "sg:postcode":"97906",
    "sg:province":"Bayern",
    "wof:name":"E. Meder",
    "wof:placetype":"venue"
},
  "geometry": {"coordinates":[9.4416923523,49.7878723145],"type":"Point"}
}