{
  "type": "Feature",
  "properties": {
    "iso:country":"DE",
    "sg:address":"Von-Burgstr. 24",
    "sg:city":"Garmisch-Partenkirchen",
    "sg:postcode":"82467",
    "sg:province":"Bayern",
    "wof:name":"Hotel Wittelsbacher Hof",
    "wof:placetype":"venue"
},
  "geometry": {"coordinates":[11.0970258713,47.4959106445],"type":"Point"}
}