{
  "type": "Feature",
  "properties": {
    "iso:country":"DE",
    "sg:address":"Baumannstr. 11",
    "sg:city":"Furtwangen",
    "sg:phone":"+49 7723/93150",
    "sg:postcode":"78120",
    "sg:province":"Baden-W\u00fcrttemberg",
    "wof:name":"G\u00fcnter Niesen Steuerberater",
    "wof:placetype":"venue"
},
  "geometry": {"coordinates":[8.2054796219,48.0495071411],"type":"Point"}
}