{
  "type": "Feature",
  "properties": {
    "iso:country":"DE",
    "sg:address":"Gehrenbergstr. 16",
    "sg:city":"Oberteuringen",
    "sg:phone":"+49 7546/9220",
    "sg:postcode":"88094",
    "sg:province":"Baden-W\u00fcrttemberg",
    "wof:name":"G\u00e4stehaus Am Obstgarten",
    "wof:placetype":"venue"
},
  "geometry": {"coordinates":[9.4618196487,47.7377243042],"type":"Point"}
}