{
  "type": "Feature",
  "properties": {
    "iso:country":"DE",
    "sg:address":"Steinweg 17",
    "sg:city":"M\u00fchlhausen",
    "sg:phone":"+49 36018/74782",
    "sg:postcode":"99974",
    "sg:province":"Th\u00fcringen",
    "wof:name":"Manfred Schulze",
    "wof:placetype":"venue"
},
  "geometry": {"coordinates":[10.4642744064,51.2093162537],"type":"Point"}
}