{
  "type": "Feature",
  "properties": {
    "iso:country":"DE",
    "sg:address":"Kalkseestr. 33",
    "sg:city":"Woltersdorf",
    "sg:phone":"+49 3362/5402",
    "sg:postcode":"15569",
    "sg:province":"Brandenburg",
    "wof:name":"Dr. Med. Gerhard Lenke",
    "wof:placetype":"venue"
},
  "geometry": {"coordinates":[13.764067,52.451458],"type":"Point"}
}