{
  "type": "Feature",
  "properties": {
    "iso:country":"DE",
    "sg:address":"Sch\u00f6nermarker Str. 5 A",
    "sg:city":"Gr\u00fcnow",
    "sg:phone":"+49 33336/55381",
    "sg:postcode":"16278",
    "sg:province":"Brandenburg",
    "wof:name":"Agrarbetriebe Gr\u00fcnow Gmbh & Co.",
    "wof:placetype":"venue"
},
  "geometry": {"coordinates":[14.069841,53.121902],"type":"Point"}
}