{
  "type": "Feature",
  "properties": {
    "iso:country":"DE",
    "sg:address":"Buchenstr. 1",
    "sg:city":"Fredersdorf",
    "sg:phone":"+49 33439/80711",
    "sg:postcode":"15370",
    "sg:province":"Brandenburg",
    "wof:name":"Owa Ost-west-agrarhandels Gmbh",
    "wof:placetype":"venue"
},
  "geometry": {"coordinates":[13.754706,52.531178],"type":"Point"}
}