{
  "type": "Feature",
  "properties": {
    "iso:country":"DE",
    "sg:address":"Oberehring 4",
    "sg:city":"Riekofen",
    "sg:phone":"+49 9480/308",
    "sg:postcode":"93104",
    "sg:province":"Bayern",
    "wof:name":"Karl Steindl",
    "wof:placetype":"venue"
},
  "geometry": {"coordinates":[12.333467,48.897026],"type":"Point"}
}