{
  "type": "Feature",
  "properties": {
    "iso:country":"DE",
    "sg:address":"Lappenkamp 7",
    "sg:city":"Ascheberg",
    "sg:phone":"+49 2599/550",
    "sg:postcode":"59387",
    "sg:province":"Nordrhein-Westfalen",
    "wof:name":"Theodor Schroer Ingenieur",
    "wof:placetype":"venue"
},
  "geometry": {"coordinates":[7.665331,51.740673],"type":"Point"}
}