{
  "type": "Feature",
  "properties": {
    "iso:country":"DE",
    "sg:address":"Rapsweg 53",
    "sg:city":"Berlin",
    "sg:phone":"+49 30/5632133",
    "sg:postcode":"12683",
    "sg:province":"Berlin",
    "wof:name":"Gruschka & Wiermann",
    "wof:placetype":"venue"
},
  "geometry": {"coordinates":[13.56384,52.518848],"type":"Point"}
}