{
  "type": "Feature",
  "properties": {
    "iso:country":"DE",
    "sg:address":"Rappenstr. 18",
    "sg:city":"H\u00f6rdt",
    "sg:phone":"+49 7272/919404",
    "sg:postcode":"76771",
    "sg:province":"Rheinland-Pfalz",
    "wof:name":"Karlsruher Versicherung Uwe Auer",
    "wof:placetype":"venue"
},
  "geometry": {"coordinates":[8.3269119263,49.1613235474],"type":"Point"}
}