{
  "type": "Feature",
  "properties": {
    "iso:country":"DE",
    "sg:address":"Marktplatz 7",
    "sg:city":"Olfen",
    "sg:phone":"+49 2595/3547",
    "sg:postcode":"59399",
    "sg:province":"Nordrhein-Westfalen",
    "wof:name":"Korfu-grill",
    "wof:placetype":"venue"
},
  "geometry": {"coordinates":[7.3788318634,51.7076034546],"type":"Point"}
}