{
  "type": "Feature",
  "properties": {
    "iso:country":"DE",
    "sg:address":"Lindenstr. 82-84",
    "sg:city":"Bramsche",
    "sg:phone":"+49 5461/63212",
    "sg:postcode":"49565",
    "sg:province":"Niedersachsen",
    "wof:name":"Revex Industrie- Vertretungen Gmbh",
    "wof:placetype":"venue"
},
  "geometry": {"coordinates":[7.975230217,52.4177703857],"type":"Point"}
}