{
  "type": "Feature",
  "properties": {
    "iso:country":"DE",
    "sg:address":"Weinstr. 1",
    "sg:city":"Birkweiler",
    "sg:phone":"+49 6345/3131",
    "sg:postcode":"76831",
    "sg:province":"Rheinland-Pfalz",
    "wof:name":"Riwa Tec Gmbh",
    "wof:placetype":"venue"
},
  "geometry": {"coordinates":[8.043708,49.208633],"type":"Point"}
}