{
  "type": "Feature",
  "properties": {
    "iso:country":"DE",
    "sg:address":"Markgrafenstr. 12-14",
    "sg:city":"Berlin",
    "sg:postcode":"10969",
    "sg:province":"Berlin",
    "wof:name":"Expotec Gesellschaft F\u00fcr Messeleistungen Mbh",
    "wof:placetype":"venue"
},
  "geometry": {"coordinates":[13.3948545456,52.5054244995],"type":"Point"}
}