{
  "type": "Feature",
  "properties": {
    "iso:country":"DE",
    "sg:address":"Reichenberger Str. 2",
    "sg:city":"Bad Honnef",
    "sg:phone":"+49 2224/92490",
    "sg:postcode":"53604",
    "sg:province":"Nordrhein-Westfalen",
    "wof:name":"F. Klehn Und Sommerh\u00e4user",
    "wof:placetype":"venue"
},
  "geometry": {"coordinates":[7.2301249504,50.6496543884],"type":"Point"}
}