{
  "type": "Feature",
  "properties": {
    "iso:country":"DE",
    "sg:address":"Auerweg 5",
    "sg:city":"Landshut",
    "sg:phone":"+49 871/73486",
    "sg:postcode":"84030",
    "sg:province":"Bayern",
    "wof:name":"G. Sander",
    "wof:placetype":"venue"
},
  "geometry": {"coordinates":[12.1560907364,48.5517578125],"type":"Point"}
}