{
  "type": "Feature",
  "properties": {
    "iso:country":"DE",
    "sg:address":"D\u00fcsseldorfer Stra\u00dfe 67",
    "sg:city":"Berlin",
    "sg:phone":"+49 30",
    "sg:postcode":"10719",
    "sg:province":"Berlin",
    "wof:name":"Rekord Geb\u00e4ude Service",
    "wof:placetype":"venue"
},
  "geometry": {"coordinates":[13.32086,52.495747],"type":"Point"}
}