{
  "type": "Feature",
  "properties": {
    "iso:country":"DE",
    "sg:address":"Herrenwiesenstr. 23",
    "sg:city":"Dortmund",
    "sg:postcode":"44225",
    "sg:province":"Nordrhein-Westfalen",
    "wof:name":"Qwer Gmbh",
    "wof:placetype":"venue"
},
  "geometry": {"coordinates":[7.4346580505,51.4668235779],"type":"Point"}
}