{
  "type": "Feature",
  "properties": {
    "iso:country":"DE",
    "sg:address":"Eutiner Str. 9",
    "sg:city":"Bad Schwartau",
    "sg:phone":"+49 451/24288",
    "sg:postcode":"23611",
    "sg:province":"Schleswig-Holstein",
    "wof:name":"Gerd Eisermann",
    "wof:placetype":"venue"
},
  "geometry": {"coordinates":[10.6969938278,53.9210319519],"type":"Point"}
}