{
  "type": "Feature",
  "properties": {
    "iso:country":"DE",
    "sg:address":"Bahnhofstr. 12",
    "sg:city":"Hergensweiler",
    "sg:phone":"+49 8388/891",
    "sg:postcode":"88138",
    "sg:province":"Bayern",
    "wof:name":"Dental Studio Edgar E. Vosseler Gmbh",
    "wof:placetype":"venue"
},
  "geometry": {"coordinates":[9.7744998932,47.6105422974],"type":"Point"}
}