{
  "type": "Feature",
  "properties": {
    "iso:country":"DE",
    "sg:address":"Altes Stadttor 7",
    "sg:city":"Cloppenburg",
    "sg:phone":"+49 4471/931828",
    "sg:postcode":"49661",
    "sg:province":"Niedersachsen",
    "wof:name":"Restaurant \u00c4g\u00e4is",
    "wof:placetype":"venue"
},
  "geometry": {"coordinates":[8.0416269302,52.8460159302],"type":"Point"}
}