{
  "type": "Feature",
  "properties": {
    "iso:country":"DE",
    "sg:address":"Fichtenweg 8",
    "sg:city":"Rimbach",
    "sg:phone":"+49 9941/3244",
    "sg:postcode":"93485",
    "sg:province":"Bayern",
    "wof:name":"Gastst\u00e4tte Bachl-ulrich",
    "wof:placetype":"venue"
},
  "geometry": {"coordinates":[12.8710012436,49.2327690125],"type":"Point"}
}