{
  "type": "Feature",
  "properties": {
    "iso:country":"DE",
    "sg:address":"Ziegelh\u00fcttenweg 54",
    "sg:city":"Frankfurt",
    "sg:postcode":"60598",
    "sg:province":"Hessen",
    "wof:name":"Em Hoch- Und Tiefbau Gmbh",
    "wof:placetype":"venue"
},
  "geometry": {"coordinates":[8.6762552261,50.0894317627],"type":"Point"}
}