{
  "type": "Feature",
  "properties": {
    "iso:country":"DE",
    "sg:address":"Auf dem Rott 9",
    "sg:city":"Pulheim",
    "sg:phone":"+49 2238/14664",
    "sg:postcode":"50259",
    "sg:province":"Nordrhein-Westfalen",
    "wof:name":"Wolf J\u00fcrgen Flach Ingenieur",
    "wof:placetype":"venue"
},
  "geometry": {"coordinates":[6.7659611702,51.0178871155],"type":"Point"}
}