{
  "type": "Feature",
  "properties": {
    "iso:country":"DE",
    "sg:address":"Hauptstr. 28",
    "sg:city":"Denkendorf",
    "sg:phone":"+49 8466/413",
    "sg:postcode":"85095",
    "sg:province":"Bayern",
    "wof:name":"Geyer Gmbh",
    "wof:placetype":"venue"
},
  "geometry": {"coordinates":[11.4556064606,48.9280014038],"type":"Point"}
}