{
  "type": "Feature",
  "properties": {
    "iso:country":"DE",
    "sg:address":"Alte Weberei 4",
    "sg:city":"Kaufbeuren",
    "sg:phone":"+49 8341/994276",
    "sg:postcode":"87600",
    "sg:province":"Bayern",
    "wof:name":"Feneberg Lebensmittel Gmbh",
    "wof:placetype":"venue"
},
  "geometry": {"coordinates":[10.6238021851,47.8826293945],"type":"Point"}
}