{
  "type": "Feature",
  "properties": {
    "iso:country":"DE",
    "sg:address":"Am Sportplatz 6",
    "sg:city":"Gorden",
    "sg:phone":"+49 35325/380",
    "sg:postcode":"03238",
    "sg:province":"Brandenburg",
    "wof:name":"Sportlerklause",
    "wof:placetype":"venue"
},
  "geometry": {"coordinates":[13.6207532883,51.5325584412],"type":"Point"}
}