{
  "type": "Feature",
  "properties": {
    "iso:country":"DE",
    "sg:address":"Ebersteinburger Str. 26",
    "sg:city":"Baden-Baden",
    "sg:phone":"+49 7221/38858",
    "sg:postcode":"76530",
    "sg:province":"Baden-W\u00fcrttemberg",
    "wof:name":"Hans Hornung",
    "wof:placetype":"venue"
},
  "geometry": {"coordinates":[8.274951,48.774529],"type":"Point"}
}