{
  "type": "Feature",
  "properties": {
    "iso:country":"DE",
    "sg:address":"Wilsdruffer Str. 15",
    "sg:city":"Tharandt",
    "sg:phone":"+49 35203/37208",
    "sg:postcode":"01737",
    "sg:province":"Sachsen",
    "wof:name":"Volkmar Rauh",
    "wof:placetype":"venue"
},
  "geometry": {"coordinates":[13.547301,50.982521],"type":"Point"}
}