{
  "type": "Feature",
  "properties": {
    "iso:country":"DE",
    "sg:address":"Heinrich-B\u00f6cking-Str. 6-8",
    "sg:city":"Saarbr\u00fccken",
    "sg:phone":"+49 681/68105",
    "sg:postcode":"66121",
    "sg:province":"Saarland",
    "wof:name":"C. P. F. Chemisch- Pharmazeutische Fabrik Gmbh",
    "wof:placetype":"venue"
},
  "geometry": {"coordinates":[7.011548996,49.227016449],"type":"Point"}
}