{
  "type": "Feature",
  "properties": {
    "iso:country":"DE",
    "sg:address":"Hauptstr. 12",
    "sg:city":"Ettinghausen",
    "sg:phone":"+49 6435/2079",
    "sg:postcode":"56244",
    "sg:province":"Rheinland-Pfalz",
    "wof:name":"G. Zell Und H. Zerfas",
    "wof:placetype":"venue"
},
  "geometry": {"coordinates":[7.8725199699,50.5155296326],"type":"Point"}
}