{
  "type": "Feature",
  "properties": {
    "iso:country":"DE",
    "sg:address":"Fiedelerstr. 31",
    "sg:city":"Hannover",
    "sg:phone":"+49 511/8386898",
    "sg:postcode":"30519",
    "sg:province":"Niedersachsen",
    "wof:name":"Cordula Aue",
    "wof:placetype":"venue"
},
  "geometry": {"coordinates":[9.7636432648,52.3385887146],"type":"Point"}
}