{
  "type": "Feature",
  "properties": {
    "iso:country":"DE",
    "sg:address":"Reiherbergstr. 33",
    "sg:city":"Golm",
    "sg:phone":"+49 331/503674",
    "sg:postcode":"14476",
    "sg:province":"Brandenburg",
    "wof:name":"Thomas M\u00fcntzer",
    "wof:placetype":"venue"
},
  "geometry": {"coordinates":[12.966012001,52.4068374634],"type":"Point"}
}