{
  "type": "Feature",
  "properties": {
    "iso:country":"DE",
    "sg:address":"Hohenstaufenstr.",
    "sg:city":"G\u00f6ppingen",
    "sg:postcode":"73033",
    "sg:province":"Baden-W\u00fcrttemberg",
    "wof:name":"Waldcafe Wannenhof Edgar Schwegler",
    "wof:placetype":"venue"
},
  "geometry": {"coordinates":[9.6612739563,48.7027702332],"type":"Point"}
}