{
  "type": "Feature",
  "properties": {
    "iso:country":"DE",
    "sg:address":"Douglasstr. 9",
    "sg:city":"Aschersleben",
    "sg:phone":"+49 3473/807413",
    "sg:postcode":"06449",
    "sg:province":"Sachsen-Anhalt",
    "wof:name":"Kanne Werkzeugtechnik Gmbh",
    "wof:placetype":"venue"
},
  "geometry": {"coordinates":[11.455251,51.758293],"type":"Point"}
}