{
  "type": "Feature",
  "properties": {
    "iso:country":"DE",
    "sg:address":"Hafenstr. 35",
    "sg:city":"Schw\u00fclper",
    "sg:phone":"+49 5303/5813",
    "sg:postcode":"38179",
    "sg:province":"Niedersachsen",
    "wof:name":"Wilhelm Schrader",
    "wof:placetype":"venue"
},
  "geometry": {"coordinates":[10.458990097,52.3332099915],"type":"Point"}
}