{
  "type": "Feature",
  "properties": {
    "iso:country":"DE",
    "sg:address":"In der Aue 1",
    "sg:city":"Hagen",
    "sg:phone":"+49 5405/999966",
    "sg:postcode":"49170",
    "sg:province":"Niedersachsen",
    "wof:name":"Helmut Dierker",
    "wof:placetype":"venue"
},
  "geometry": {"coordinates":[7.93342,52.200249],"type":"Point"}
}