{
  "type": "Feature",
  "properties": {
    "iso:country":"DE",
    "sg:address":"Georg-Deschler-Platz 1",
    "sg:city":"M\u00fcnchen",
    "sg:phone":"+49 89/8341394",
    "sg:postcode":"81245",
    "sg:province":"Bayern",
    "wof:name":"Michael Krau\u00dfe",
    "wof:placetype":"venue"
},
  "geometry": {"coordinates":[11.4690408707,48.1485137939],"type":"Point"}
}