{
  "type": "Feature",
  "properties": {
    "iso:country":"DE",
    "sg:address":"Hangstr. 42",
    "sg:city":"Aachen",
    "sg:phone":"+49 241/64112",
    "sg:postcode":"52076",
    "sg:province":"Nordrhein-Westfalen",
    "wof:name":"Dem Marketing Gmbh",
    "wof:placetype":"venue"
},
  "geometry": {"coordinates":[6.0849018097,50.7482528687],"type":"Point"}
}