{
  "type": "Feature",
  "properties": {
    "iso:country":"DE",
    "sg:address":"Nigen R\u00e4gen 7",
    "sg:city":"Hamburg",
    "sg:phone":"+49 40/64551199",
    "sg:postcode":"22159",
    "sg:province":"Hamburg",
    "wof:name":"A-z Versicherungs- Dienst Gmbh",
    "wof:placetype":"venue"
},
  "geometry": {"coordinates":[10.1005163193,53.6112251282],"type":"Point"}
}