{
  "type": "Feature",
  "properties": {
    "iso:country":"DE",
    "sg:address":"K\u00f6rler Str. 8",
    "sg:city":"Floh-Seligenthal",
    "sg:phone":"+49 3683/62220",
    "sg:postcode":"98593",
    "sg:province":"Th\u00fcringen",
    "wof:name":"H\u00f6hnberg-bau Gmbh",
    "wof:placetype":"venue"
},
  "geometry": {"coordinates":[10.4761695862,50.756187439],"type":"Point"}
}