{
  "type": "Feature",
  "properties": {
    "iso:country":"DE",
    "sg:address":"Sulzbacher Str. 61",
    "sg:city":"Lauterbach",
    "sg:phone":"+49 7422/922041",
    "sg:postcode":"78730",
    "sg:province":"Baden-W\u00fcrttemberg",
    "wof:name":"Inlis Gmbh",
    "wof:placetype":"venue"
},
  "geometry": {"coordinates":[8.3270397186,48.2459220886],"type":"Point"}
}