{
  "type": "Feature",
  "properties": {
    "iso:country":"DE",
    "sg:address":"Baumener Str. 4",
    "sg:city":"Waldbr\u00f6l",
    "sg:phone":"+49 2291/807539",
    "sg:postcode":"51545",
    "sg:province":"Nordrhein-Westfalen",
    "wof:name":"Esko Trading Und Consulting Gmbh",
    "wof:placetype":"venue"
},
  "geometry": {"coordinates":[7.612706,50.862457],"type":"Point"}
}