{
  "type": "Feature",
  "properties": {
    "iso:country":"DE",
    "sg:address":"Am Sandtorkai 26",
    "sg:city":"Hamburg",
    "sg:phone":"+49 40/338478",
    "sg:postcode":"20457",
    "sg:province":"Hamburg",
    "wof:name":"Aht Afghan House Trading Gmbh",
    "wof:placetype":"venue"
},
  "geometry": {"coordinates":[9.9920358658,53.5434341431],"type":"Point"}
}