{
  "type": "Feature",
  "properties": {
    "iso:country":"DE",
    "sg:address":"Meisenweg 73",
    "sg:city":"Altena",
    "sg:phone":"+49 2352/953038",
    "sg:postcode":"58762",
    "sg:province":"Nordrhein-Westfalen",
    "wof:name":"Reuber Handel Und Verwaltung Gmbh",
    "wof:placetype":"venue"
},
  "geometry": {"coordinates":[7.676657,51.282845],"type":"Point"}
}