{
  "type": "Feature",
  "properties": {
    "iso:country":"DE",
    "sg:address":"Stollbergstr. 22",
    "sg:city":"M\u00fcnchen",
    "sg:phone":"+49 89/292979",
    "sg:postcode":"80539",
    "sg:province":"Bayern",
    "wof:name":"Elsa Monaco",
    "wof:placetype":"venue"
},
  "geometry": {"coordinates":[11.583445549,48.1382408142],"type":"Point"}
}