{
  "type": "Feature",
  "properties": {
    "iso:country":"DE",
    "sg:city":"P\u00fcrgen",
    "sg:phone":"+49 8196/7193",
    "sg:postcode":"86932",
    "sg:province":"Bayern",
    "wof:name":"Raiffeisenbank Lech-ammersee Eg",
    "wof:placetype":"venue"
},
  "geometry": {"coordinates":[10.921386,48.025455],"type":"Point"}
}