{
  "type": "Feature",
  "properties": {
    "iso:country":"DE",
    "sg:address":"Fasanenstrasse 8",
    "sg:city":"Vechelde",
    "sg:phone":"+49 5302",
    "sg:postcode":"38159",
    "sg:province":"Niedersachsen",
    "wof:name":"Renovierungs-service-hudson",
    "wof:placetype":"venue"
},
  "geometry": {"coordinates":[10.3745718002,52.2625961304],"type":"Point"}
}