{
  "type": "Feature",
  "properties": {
    "iso:country":"DE",
    "sg:address":"Oberscharam 3",
    "sg:city":"Siegsdorf",
    "sg:phone":"+49 8662/7803",
    "sg:postcode":"83313",
    "sg:province":"Bayern",
    "wof:name":"G\u00f6belhof, Erlebnisreiche Reitferien In Siegsdorf",
    "wof:placetype":"venue"
},
  "geometry": {"coordinates":[12.6290836334,47.7981414795],"type":"Point"}
}