{
  "type": "Feature",
  "properties": {
    "iso:country":"DE",
    "sg:address":"Heereweg 5",
    "sg:city":"Moormerland",
    "sg:phone":"+49 4924/864",
    "sg:postcode":"26802",
    "sg:province":"Niedersachsen",
    "wof:name":"Katholisches Pfarramt Mari\u00e4 Himmelfahrt",
    "wof:placetype":"venue"
},
  "geometry": {"coordinates":[7.3375878334,53.3299102783],"type":"Point"}
}