{
  "type": "Feature",
  "properties": {
    "iso:country":"DE",
    "sg:address":"Schwelmer Str. 98",
    "sg:city":"Wuppertal",
    "sg:phone":"+49 202/602102",
    "sg:postcode":"42389",
    "sg:province":"Nordrhein-Westfalen",
    "wof:name":"Alfred Fischer",
    "wof:placetype":"venue"
},
  "geometry": {"coordinates":[7.2547140121,51.2758483887],"type":"Point"}
}