{
  "type": "Feature",
  "properties": {
    "iso:country":"DE",
    "sg:address":"Trakehner Weg 52",
    "sg:city":"Norderstedt",
    "sg:phone":"+49 4941/06",
    "sg:postcode":"22844",
    "sg:province":"Schleswig-Holstein",
    "wof:name":"Briefk\u00e4sten Im Onlineshop Des Gitte-versand",
    "wof:placetype":"venue"
},
  "geometry": {"coordinates":[10.01632,53.703506],"type":"Point"}
}