{
  "type": "Feature",
  "properties": {
    "iso:country":"DE",
    "sg:address":"H\u00f6rnlestr. 13",
    "sg:city":"Schongau",
    "sg:phone":"+49 8861/90354",
    "sg:postcode":"86956",
    "sg:province":"Bayern",
    "wof:name":"A. Beer",
    "wof:placetype":"venue"
},
  "geometry": {"coordinates":[10.8764629364,47.8044891357],"type":"Point"}
}