{
  "type": "Feature",
  "properties": {
    "iso:country":"DE",
    "sg:address":"Marktstr. 51",
    "sg:city":"Pasewalk",
    "sg:postcode":"17309",
    "sg:province":"Mecklenburg-Vorpommern",
    "wof:name":"I. Schr\u00f6der",
    "wof:placetype":"venue"
},
  "geometry": {"coordinates":[13.990874,53.507107],"type":"Point"}
}