{
  "type": "Feature",
  "properties": {
    "iso:country":"DE",
    "sg:address":"Theodor-Heuss-Platz 2",
    "sg:city":"Osnabr\u00fcck",
    "sg:phone":"+49 541/345391",
    "sg:postcode":"49074",
    "sg:province":"Niedersachsen",
    "wof:name":"Deutsche Bahn Ag",
    "wof:placetype":"venue"
},
  "geometry": {"coordinates":[8.0600728989,52.2724304199],"type":"Point"}
}