{
  "type": "Feature",
  "properties": {
    "iso:country":"DE",
    "sg:address":"Faradaystr. 30",
    "sg:city":"Leipzig",
    "sg:phone":"+49 341/9110861",
    "sg:postcode":"04159",
    "sg:province":"Sachsen",
    "wof:name":"Mecklenburger Hof",
    "wof:placetype":"venue"
},
  "geometry": {"coordinates":[12.3488235474,51.3678627014],"type":"Point"}
}