{
  "type": "Feature",
  "properties": {
    "iso:country":"DE",
    "sg:address":"Zur Kaule 1",
    "sg:city":"Overath",
    "sg:phone":"+49 2206/3057",
    "sg:postcode":"51491",
    "sg:province":"Nordrhein-Westfalen",
    "wof:name":"Schindler Planungsgruppe Vertriebsgesellschaft Mbh",
    "wof:placetype":"venue"
},
  "geometry": {"coordinates":[7.3278841972,50.9640808105],"type":"Point"}
}