{
  "type": "Feature",
  "properties": {
    "iso:country":"DE",
    "sg:address":"Eichenb\u00fchler Str. 58",
    "sg:city":"Miltenberg",
    "sg:phone":"+49 9371/2393",
    "sg:postcode":"63897",
    "sg:province":"Bayern",
    "wof:name":"Friedrich Frankenberger",
    "wof:placetype":"venue"
},
  "geometry": {"coordinates":[9.267722,49.70454],"type":"Point"}
}