{
  "type": "Feature",
  "properties": {
    "iso:country":"DE",
    "sg:address":"Unterstr. 9",
    "sg:city":"Winningen",
    "sg:phone":"+49 34745/286",
    "sg:postcode":"06449",
    "sg:province":"Sachsen-Anhalt",
    "wof:name":"Kreissparkasse Aschersleben",
    "wof:placetype":"venue"
},
  "geometry": {"coordinates":[11.469683,51.764027],"type":"Point"}
}