{
  "type": "Feature",
  "properties": {
    "iso:country":"DE",
    "sg:address":"Hauptstr. 51",
    "sg:city":"Struckum",
    "sg:phone":"+49 4671/6639",
    "sg:postcode":"25821",
    "sg:province":"Schleswig-Holstein",
    "wof:name":"Shell-station",
    "wof:placetype":"venue"
},
  "geometry": {"coordinates":[8.9939174652,54.5894317627],"type":"Point"}
}