{
  "type": "Feature",
  "properties": {
    "iso:country":"DE",
    "sg:address":"Hammer Str. 92",
    "sg:city":"Beckum",
    "sg:phone":"+49 2521/93430",
    "sg:postcode":"59269",
    "sg:province":"Nordrhein-Westfalen",
    "wof:name":"Josef Tenkhoff Gmbh",
    "wof:placetype":"venue"
},
  "geometry": {"coordinates":[8.022941,51.749706],"type":"Point"}
}