{
  "type": "Feature",
  "properties": {
    "iso:country":"DE",
    "sg:address":"Schadowstr. 30",
    "sg:city":"D\u00fcsseldorf",
    "sg:phone":"+49 211/9357070",
    "sg:postcode":"40212",
    "sg:province":"Nordrhein-Westfalen",
    "wof:name":"Thorsten Hollmann Rechtsanwalt",
    "wof:placetype":"venue"
},
  "geometry": {"coordinates":[6.7820329666,51.2262954712],"type":"Point"}
}