{
  "type": "Feature",
  "properties": {
    "iso:country":"DE",
    "sg:address":"W\u00fcrttemberger Str. 1",
    "sg:city":"Postbauer-Heng",
    "sg:phone":"+49 9188/3530",
    "sg:postcode":"92353",
    "sg:province":"Bayern",
    "wof:name":"Andys Videothek",
    "wof:placetype":"venue"
},
  "geometry": {"coordinates":[11.353676796,49.3023681641],"type":"Point"}
}