{
  "type": "Feature",
  "properties": {
    "iso:country":"DE",
    "sg:address":"Argenstr. 78",
    "sg:city":"Kressbronn",
    "sg:phone":"+49 7543/8678",
    "sg:postcode":"88079",
    "sg:province":"Baden-W\u00fcrttemberg",
    "wof:name":"Wundel Autokrane Kg",
    "wof:placetype":"venue"
},
  "geometry": {"coordinates":[9.5852384567,47.5980949402],"type":"Point"}
}