{
  "type": "Feature",
  "properties": {
    "iso:country":"DE",
    "sg:address":"Dorfstr. 46",
    "sg:city":"Niederdorf",
    "sg:phone":"+49 37296/3389",
    "sg:postcode":"09366",
    "sg:province":"Sachsen",
    "wof:name":"Roland Schulz",
    "wof:placetype":"venue"
},
  "geometry": {"coordinates":[12.787409,50.722366],"type":"Point"}
}