{
  "type": "Feature",
  "properties": {
    "iso:country":"DE",
    "sg:address":"Finkenweg 15",
    "sg:city":"Furth im Wald",
    "sg:phone":"+49 9973/1605",
    "sg:postcode":"93437",
    "sg:province":"Bayern",
    "wof:name":"J. M\u00fcller",
    "wof:placetype":"venue"
},
  "geometry": {"coordinates":[12.8572454453,49.308216095],"type":"Point"}
}