{
  "type": "Feature",
  "properties": {
    "iso:country":"DE",
    "sg:address":"An der Kaveln 2",
    "sg:city":"\u00dcckeritz",
    "sg:postcode":"17459",
    "sg:province":"Mecklenburg-Vorpommern",
    "wof:name":"Tischlerei Hans Uwe Petersen Gmbh",
    "wof:placetype":"venue"
},
  "geometry": {"coordinates":[14.042628,54.014477],"type":"Point"}
}