{
  "type": "Feature",
  "properties": {
    "iso:country":"DE",
    "sg:address":"B\u00f6rsenstr. 123",
    "sg:city":"Solingen",
    "sg:phone":"+49 212/870409",
    "sg:postcode":"42657",
    "sg:province":"Nordrhein-Westfalen",
    "wof:name":"Ludwig Fenten",
    "wof:placetype":"venue"
},
  "geometry": {"coordinates":[7.069398,51.139355],"type":"Point"}
}