{
  "type": "Feature",
  "properties": {
    "iso:country":"DE",
    "sg:address":"Fiskusstr. 4",
    "sg:city":"Duisburg",
    "sg:phone":"+49 203/581997",
    "sg:postcode":"47167",
    "sg:province":"Nordrhein-Westfalen",
    "wof:name":"Schr\u00f6er",
    "wof:placetype":"venue"
},
  "geometry": {"coordinates":[6.818500042,51.5037689209],"type":"Point"}
}