{
  "type": "Feature",
  "properties": {
    "iso:country":"DE",
    "sg:address":"Hardeckstr. 8a",
    "sg:city":"Karlsruhe",
    "sg:phone":"+49 721/574796",
    "sg:postcode":"76185",
    "sg:province":"Baden-W\u00fcrttemberg",
    "wof:name":"Freie Tankstelle",
    "wof:placetype":"venue"
},
  "geometry": {"coordinates":[8.3618574142,48.9982223511],"type":"Point"}
}