{
  "type": "Feature",
  "properties": {
    "iso:country":"DE",
    "sg:address":"K\u00f6nigsdorfer Str. 53",
    "sg:city":"Wolfratshausen",
    "sg:phone":"+49 8171/16714",
    "sg:postcode":"82515",
    "sg:province":"Bayern",
    "wof:name":"Italy-pizzeria",
    "wof:placetype":"venue"
},
  "geometry": {"coordinates":[11.4293909073,47.9077606201],"type":"Point"}
}