{
  "type": "Feature",
  "properties": {
    "iso:country":"DE",
    "sg:address":"Kreutzerstr. 7",
    "sg:city":"Hamm",
    "sg:phone":"+49 2381/5555",
    "sg:postcode":"59063",
    "sg:province":"Nordrhein-Westfalen",
    "wof:name":"Baubedarf Pr\u00f6psting Ohg",
    "wof:placetype":"venue"
},
  "geometry": {"coordinates":[7.815658,51.671341],"type":"Point"}
}