{
  "type": "Feature",
  "properties": {
    "iso:country":"DE",
    "sg:address":"Hamburger Str. 54",
    "sg:city":"Kaltenkirchen",
    "sg:postcode":"24568",
    "sg:province":"Schleswig-Holstein",
    "wof:name":"Stylix - Gesellschaft F\u00fcr Internetdienstleistungen Mbh",
    "wof:placetype":"venue"
},
  "geometry": {"coordinates":[9.965707,53.83403],"type":"Point"}
}