{
  "type": "Feature",
  "properties": {
    "iso:country":"DE",
    "sg:address":"Wildenbruchstr. 55",
    "sg:city":"Frankfurt",
    "sg:phone":"+49 69/515286",
    "sg:postcode":"60431",
    "sg:province":"Hessen",
    "wof:name":"Ernst M. Weidenbach",
    "wof:placetype":"venue"
},
  "geometry": {"coordinates":[8.663767,50.146214],"type":"Point"}
}