{
  "type": "Feature",
  "properties": {
    "iso:country":"DE",
    "sg:address":"Grabenstr. 41",
    "sg:city":"Stadtlohn",
    "sg:phone":"+49 2563/1877",
    "sg:postcode":"48703",
    "sg:province":"Nordrhein-Westfalen",
    "wof:name":"Kettelerhaus",
    "wof:placetype":"venue"
},
  "geometry": {"coordinates":[6.9146590233,51.9929389954],"type":"Point"}
}