{
  "type": "Feature",
  "properties": {
    "iso:country":"DE",
    "sg:address":"Reinsburgstr. 44A",
    "sg:city":"Stuttgart",
    "sg:phone":"+49 711/6152524",
    "sg:postcode":"70178",
    "sg:province":"Baden-W\u00fcrttemberg",
    "wof:name":"Thilo Mitschele Rechtsanwalt",
    "wof:placetype":"venue"
},
  "geometry": {"coordinates":[9.1658248901,48.7703208923],"type":"Point"}
}