{
  "type": "Feature",
  "properties": {
    "iso:country":"DE",
    "sg:address":"Talstr. 1",
    "sg:city":"Bad Schussenried",
    "sg:phone":"+49 7583/2578",
    "sg:postcode":"88427",
    "sg:province":"Baden-W\u00fcrttemberg",
    "wof:name":"R. Lutz",
    "wof:placetype":"venue"
},
  "geometry": {"coordinates":[9.618031,48.021111],"type":"Point"}
}