{
  "type": "Feature",
  "properties": {
    "iso:country":"DE",
    "sg:address":"Z\u00e4hringerplatz 22",
    "sg:city":"Konstanz",
    "sg:phone":"+49 7531/61711",
    "sg:postcode":"78464",
    "sg:province":"Baden-W\u00fcrttemberg",
    "wof:name":"Siegfried Haas",
    "wof:placetype":"venue"
},
  "geometry": {"coordinates":[9.183826,47.672646],"type":"Point"}
}