{
  "type": "Feature",
  "properties": {
    "iso:country":"DE",
    "sg:address":"Herzberger Str. 50",
    "sg:city":"Eberg\u00f6tzen",
    "sg:phone":"+49 5507/1672",
    "sg:postcode":"37136",
    "sg:province":"Niedersachsen",
    "wof:name":"Alte Bauernkate",
    "wof:placetype":"venue"
},
  "geometry": {"coordinates":[10.1086606979,51.5720062256],"type":"Point"}
}