{
  "type": "Feature",
  "properties": {
    "iso:country":"DE",
    "sg:address":"Julius-H\u00f6lder-Str 36",
    "sg:city":"Stuttgart",
    "sg:phone":"+49 711/720670",
    "sg:postcode":"70597",
    "sg:province":"Baden-W\u00fcrttemberg",
    "wof:name":"Stihler Electronic Gmbh",
    "wof:placetype":"venue"
},
  "geometry": {"coordinates":[9.1673994064,48.7378692627],"type":"Point"}
}