{
  "type": "Feature",
  "properties": {
    "iso:country":"DE",
    "sg:address":"Friedrichstr. 3",
    "sg:city":"Stumsdorf",
    "sg:phone":"+49 34956/21160",
    "sg:postcode":"06780",
    "sg:province":"Sachsen-Anhalt",
    "wof:name":"Elektroanlagenbau Jarschke Gmbh",
    "wof:placetype":"venue"
},
  "geometry": {"coordinates":[12.1207466125,51.6329650879],"type":"Point"}
}