{
  "type": "Feature",
  "properties": {
    "iso:country":"DE",
    "sg:address":"Rathausweg 10",
    "sg:city":"Horgenzell",
    "sg:phone":"+49 7504/1405",
    "sg:postcode":"88263",
    "sg:province":"Baden-W\u00fcrttemberg",
    "wof:name":"Mdm Gesellschaft F\u00fcr Montage Von Bauelementen Mbh",
    "wof:placetype":"venue"
},
  "geometry": {"coordinates":[9.497342,47.803802],"type":"Point"}
}