{
  "type": "Feature",
  "properties": {
    "iso:country":"DE",
    "sg:address":"Untere Marktstr. 6 a",
    "sg:city":"K\u00f6sching",
    "sg:phone":"+49 8456/7033",
    "sg:postcode":"85092",
    "sg:province":"Bayern",
    "wof:name":"Funk Eikam Und Danner Rechtsanw\u00e4lte",
    "wof:placetype":"venue"
},
  "geometry": {"coordinates":[11.5019330978,48.8109855652],"type":"Point"}
}