{
  "type": "Feature",
  "properties": {
    "iso:country":"DE",
    "sg:address":"Wollankstr. 32-39",
    "sg:city":"Berlin",
    "sg:phone":"+49 30/4977730",
    "sg:postcode":"13359",
    "sg:province":"Berlin",
    "wof:name":"Kaisers Markt",
    "wof:placetype":"venue"
},
  "geometry": {"coordinates":[13.390171051,52.5629959106],"type":"Point"}
}