{
  "type": "Feature",
  "properties": {
    "iso:country":"DE",
    "sg:address":"Alter Ortsweg 41",
    "sg:city":"Meersburg",
    "sg:phone":"+49 7532/495544",
    "sg:postcode":"88709",
    "sg:province":"Baden-W\u00fcrttemberg",
    "wof:name":"K Planing & Projects Ursula Rimmele-konzelmann",
    "wof:placetype":"venue"
},
  "geometry": {"coordinates":[9.2929897308,47.7048568726],"type":"Point"}
}