{
  "type": "Feature",
  "properties": {
    "iso:country":"DE",
    "sg:address":"Kirchstr. 29",
    "sg:city":"Wiltingen",
    "sg:phone":"+49 6501/16450",
    "sg:postcode":"54459",
    "sg:province":"Rheinland-Pfalz",
    "wof:name":"Hans Resch",
    "wof:placetype":"venue"
},
  "geometry": {"coordinates":[6.5888171196,49.659702301],"type":"Point"}
}