{
  "type": "Feature",
  "properties": {
    "iso:country":"DE",
    "sg:address":"Bahnhofspassage 4",
    "sg:city":"Wolfsburg",
    "sg:phone":"+49 5361/21981",
    "sg:postcode":"38440",
    "sg:province":"Niedersachsen",
    "wof:name":"Reiseb\u00fcro Derpart Gmbh",
    "wof:placetype":"venue"
},
  "geometry": {"coordinates":[10.7883405685,52.4273223877],"type":"Point"}
}