{
  "type": "Feature",
  "properties": {
    "iso:country":"DE",
    "sg:address":"Hengelesm\u00fchle 1",
    "sg:city":"Isny",
    "sg:phone":"+49 7562/2021",
    "sg:postcode":"88316",
    "sg:province":"Baden-W\u00fcrttemberg",
    "wof:name":"Schneider & S\u00f6hne Gmbh",
    "wof:placetype":"venue"
},
  "geometry": {"coordinates":[10.079013,47.679012],"type":"Point"}
}