{
  "type": "Feature",
  "properties": {
    "iso:country":"DE",
    "sg:address":"M\u00fchlstr. 14",
    "sg:city":"Schlangenbad",
    "sg:phone":"+49 6129/8178",
    "sg:postcode":"65388",
    "sg:province":"Hessen",
    "wof:name":"Modehaus Benz",
    "wof:placetype":"venue"
},
  "geometry": {"coordinates":[8.104565,50.092731],"type":"Point"}
}