{
  "type": "Feature",
  "properties": {
    "iso:country":"DE",
    "sg:address":"Zum Sonnentau 1a",
    "sg:city":"Ganderkesee",
    "sg:phone":"+49 4222/951193",
    "sg:postcode":"27777",
    "sg:province":"Niedersachsen",
    "wof:name":"Detlev Siemer Gmbh",
    "wof:placetype":"venue"
},
  "geometry": {"coordinates":[8.549823,53.025368],"type":"Point"}
}