{
  "type": "Feature",
  "properties": {
    "iso:country":"DE",
    "sg:address":"Gladbacher Str. 157",
    "sg:city":"Elsdorf",
    "sg:phone":"+49 2274/3932",
    "sg:postcode":"50189",
    "sg:province":"Nordrhein-Westfalen",
    "wof:name":"Arnold Schnitzler",
    "wof:placetype":"venue"
},
  "geometry": {"coordinates":[6.554928,50.941948],"type":"Point"}
}