{
  "type": "Feature",
  "properties": {
    "iso:country":"DE",
    "sg:address":"Marktplatz 3::",
    "sg:city":"Amberg",
    "sg:phone":"+49 9621/3100",
    "sg:postcode":"92224",
    "sg:province":"Bayern",
    "wof:name":"Sparkasse Amberg-sulzbach",
    "wof:placetype":"venue"
},
  "geometry": {"coordinates":[11.857965,49.444935],"type":"Point"}
}