{
  "type": "Feature",
  "properties": {
    "iso:country":"DE",
    "sg:address":"Niederborn 9",
    "sg:city":"Bad Salzungen",
    "sg:phone":"+49 3695/622278",
    "sg:postcode":"36433",
    "sg:province":"Th\u00fcringen",
    "wof:name":"Reiseb\u00fcro Relax Tours Ferdinand Blum",
    "wof:placetype":"venue"
},
  "geometry": {"coordinates":[10.2352266312,50.8137893677],"type":"Point"}
}