{
  "type": "Feature",
  "properties": {
    "iso:country":"DE",
    "sg:address":"Rothkreuz",
    "sg:city":"Wei\u00dfensberg",
    "sg:phone":"+49 8389/483",
    "sg:postcode":"88138",
    "sg:province":"Bayern",
    "wof:name":"G\u00e4stehaus M.-l. Schmid",
    "wof:placetype":"venue"
},
  "geometry": {"coordinates":[9.7315139771,47.5917625427],"type":"Point"}
}