{
  "type": "Feature",
  "properties": {
    "iso:country":"DE",
    "sg:address":"Kurrstr. 3 b",
    "sg:city":"Herzogenaurach",
    "sg:phone":"+49 9132/78670",
    "sg:postcode":"91074",
    "sg:province":"Bayern",
    "wof:name":"Gerhard Fink Steuerberater",
    "wof:placetype":"venue"
},
  "geometry": {"coordinates":[10.8696537018,49.5742416382],"type":"Point"}
}