{
  "type": "Feature",
  "properties": {
    "iso:country":"DE",
    "sg:address":"Frankfurter Str. 19",
    "sg:city":"W\u00f6llstadt",
    "sg:phone":"+49 6034/1027",
    "sg:postcode":"61206",
    "sg:province":"Hessen",
    "wof:name":"W. Warkotz",
    "wof:placetype":"venue"
},
  "geometry": {"coordinates":[8.75832,50.27232],"type":"Point"}
}