{
  "type": "Feature",
  "properties": {
    "iso:country":"DE",
    "sg:address":"Borchertring 19",
    "sg:city":"Hamburg",
    "sg:phone":"+49 40/6306001",
    "sg:postcode":"22309",
    "sg:province":"Hamburg",
    "wof:name":"Hab Hausverwaltung",
    "wof:placetype":"venue"
},
  "geometry": {"coordinates":[10.0665359497,53.6164016724],"type":"Point"}
}