{
  "type": "Feature",
  "properties": {
    "iso:country":"DE",
    "sg:address":"Bahnhofstr. 32",
    "sg:city":"Tostedt",
    "sg:phone":"+49 4182/1493",
    "sg:postcode":"21255",
    "sg:province":"Niedersachsen",
    "wof:name":"Blumen-st\u00f6ver Inh. Ida St\u00f6ver",
    "wof:placetype":"venue"
},
  "geometry": {"coordinates":[9.716916,53.276978],"type":"Point"}
}