{
  "type": "Feature",
  "properties": {
    "iso:country":"DE",
    "sg:address":"Cottbuser Str. 8 a",
    "sg:city":"Gro\u00dfr\u00e4schen",
    "sg:phone":"+49 35753/12303",
    "sg:postcode":"01983",
    "sg:province":"Brandenburg",
    "wof:name":"Hamburg-mannheimer Sachversicherungs-ag",
    "wof:placetype":"venue"
},
  "geometry": {"coordinates":[14.004404068,51.6043777466],"type":"Point"}
}