{
  "type": "Feature",
  "properties": {
    "iso:country":"DE",
    "sg:address":"Gunterstr. 39",
    "sg:city":"Ludwigshafen",
    "sg:phone":"+49 621/661076",
    "sg:postcode":"67069",
    "sg:province":"Rheinland-Pfalz",
    "wof:name":"Kurt Massar Gbr",
    "wof:placetype":"venue"
},
  "geometry": {"coordinates":[8.395387,49.527027],"type":"Point"}
}