{
  "type": "Feature",
  "properties": {
    "iso:country":"DE",
    "sg:address":"Heinrich-von-Brentano-Weg 9",
    "sg:city":"Elmshorn",
    "sg:phone":"+49 4121/75582",
    "sg:postcode":"25337",
    "sg:province":"Schleswig-Holstein",
    "wof:name":"Mich@el.kom",
    "wof:placetype":"venue"
},
  "geometry": {"coordinates":[9.6824092865,53.7461929321],"type":"Point"}
}