{
  "type": "Feature",
  "properties": {
    "iso:country":"DE",
    "sg:address":"Bebelstr. 3a",
    "sg:city":"Ostseebad Prerow",
    "sg:phone":"+49 38233/69785",
    "sg:postcode":"18375",
    "sg:province":"Mecklenburg-Vorpommern",
    "wof:name":"G. Rank",
    "wof:placetype":"venue"
},
  "geometry": {"coordinates":[12.572165,54.44569],"type":"Point"}
}