{
  "type": "Feature",
  "properties": {
    "iso:country":"DE",
    "sg:address":"Twentmannstrasse Nr. 106",
    "sg:city":"Essen Ruhr",
    "sg:phone":"+49 201/313139",
    "sg:postcode":"45326",
    "sg:province":"Nordrhein-Westfalen",
    "wof:name":"Horstellis Unterhaltungsprogramme",
    "wof:placetype":"venue"
},
  "geometry": {"coordinates":[7.0038700104,51.4852218628],"type":"Point"}
}