{
  "type": "Feature",
  "properties": {
    "iso:country":"DE",
    "sg:address":"Tschifflick 2",
    "sg:city":"Zweibr\u00fccken",
    "sg:phone":"+49 6332/49916",
    "sg:postcode":"66482",
    "sg:province":"Rheinland-Pfalz",
    "wof:name":"Havanna",
    "wof:placetype":"venue"
},
  "geometry": {"coordinates":[7.3967051506,49.2517662048],"type":"Point"}
}