{
  "type": "Feature",
  "properties": {
    "iso:country":"DE",
    "sg:address":"Hauptstr. 49",
    "sg:city":"Lauterbach",
    "sg:postcode":"36341",
    "sg:province":"Hessen",
    "wof:name":"Walter Sch\u00fcttler",
    "wof:placetype":"venue"
},
  "geometry": {"coordinates":[9.330019,50.627125],"type":"Point"}
}