{
  "type": "Feature",
  "properties": {
    "iso:country":"DE",
    "sg:address":"Gerhardstr. 6",
    "sg:city":"M\u00fcnchen",
    "sg:phone":"+49 89/661533",
    "sg:postcode":"81543",
    "sg:province":"Bayern",
    "wof:name":"A. Janik",
    "wof:placetype":"venue"
},
  "geometry": {"coordinates":[11.567489624,48.1158447266],"type":"Point"}
}