{
  "type": "Feature",
  "properties": {
    "iso:country":"DE",
    "sg:address":"H\u00f6lzlweg 8",
    "sg:city":"Mindelstetten",
    "sg:phone":"+49 8404/1332",
    "sg:postcode":"93349",
    "sg:province":"Bayern",
    "wof:name":"H. Hengl",
    "wof:placetype":"venue"
},
  "geometry": {"coordinates":[11.6416196823,48.8351631165],"type":"Point"}
}