{
  "type": "Feature",
  "properties": {
    "iso:country":"DE",
    "sg:address":"Predd\u00f6hler Weg",
    "sg:city":"Pritzwalk",
    "sg:phone":"+49 3395/4484",
    "sg:postcode":"16928",
    "sg:province":"Brandenburg",
    "wof:name":"Zechbau Bauleitung Gmbh",
    "wof:placetype":"venue"
},
  "geometry": {"coordinates":[12.175412,53.159138],"type":"Point"}
}