{
  "type": "Feature",
  "properties": {
    "iso:country":"DE",
    "sg:address":"Br\u00fcnestr. 11",
    "sg:city":"\u00dcbach-Palenberg",
    "sg:postcode":"52531",
    "sg:province":"Nordrhein-Westfalen",
    "wof:name":"Ivb-marketing Gmbh",
    "wof:placetype":"venue"
},
  "geometry": {"coordinates":[6.1384291649,50.9129295349],"type":"Point"}
}