{
  "type": "Feature",
  "properties": {
    "iso:country":"DE",
    "sg:address":"Lange Str. 25",
    "sg:city":"Walsdorf",
    "sg:phone":"+49 9549/646",
    "sg:postcode":"96194",
    "sg:province":"Bayern",
    "wof:name":"Heinrich Faatz",
    "wof:placetype":"venue"
},
  "geometry": {"coordinates":[10.782343,49.870239],"type":"Point"}
}