{
  "type": "Feature",
  "properties": {
    "iso:country":"DE",
    "sg:address":"Martinistr. 41",
    "sg:city":"Greven",
    "sg:phone":"+49 2571/93300",
    "sg:postcode":"48268",
    "sg:province":"Nordrhein-Westfalen",
    "wof:name":"Bernhard Ahlert Jun. Kg",
    "wof:placetype":"venue"
},
  "geometry": {"coordinates":[7.608664,52.093517],"type":"Point"}
}