{
  "type": "Feature",
  "properties": {
    "iso:country":"DE",
    "sg:address":"Goethestr. 8",
    "sg:city":"Marne",
    "sg:phone":"+49 4851/4602",
    "sg:postcode":"25709",
    "sg:province":"Schleswig-Holstein",
    "wof:name":"Werner Dohrn",
    "wof:placetype":"venue"
},
  "geometry": {"coordinates":[9.015985,53.947609],"type":"Point"}
}