{
  "type": "Feature",
  "properties": {
    "iso:country":"DE",
    "sg:address":"Cesar-Klein-Ring 40",
    "sg:city":"Hamburg",
    "sg:phone":"+49 40/6308672",
    "sg:postcode":"22309",
    "sg:province":"Hamburg",
    "wof:name":"Myrto",
    "wof:placetype":"venue"
},
  "geometry": {"coordinates":[10.0600233078,53.6102867126],"type":"Point"}
}