{
  "type": "Feature",
  "properties": {
    "iso:country":"DE",
    "sg:address":"Sch\u00f6nbergerstr. 8",
    "sg:city":"G\u00f6rlitz",
    "sg:phone":"+49 3581/78834",
    "sg:postcode":"02827",
    "sg:province":"Sachsen",
    "wof:name":"Friedrich Linke",
    "wof:placetype":"venue"
},
  "geometry": {"coordinates":[14.9382743835,51.131477356],"type":"Point"}
}