{
  "type": "Feature",
  "properties": {
    "iso:country":"DE",
    "sg:address":"Deuzer Weg 15",
    "sg:city":"Netphen",
    "sg:phone":"+49 2737/3338",
    "sg:postcode":"57250",
    "sg:province":"Nordrhein-Westfalen",
    "wof:name":"Hartmut B\u00fcdenbender Architekt",
    "wof:placetype":"venue"
},
  "geometry": {"coordinates":[8.162691,50.872795],"type":"Point"}
}