{
  "type": "Feature",
  "properties": {
    "iso:country":"DE",
    "sg:address":"Postfach 1207",
    "sg:city":"F\u00fcrstenwalde",
    "sg:phone":"+49 3361/4584",
    "sg:postcode":"15502",
    "sg:province":"Brandenburg",
    "wof:name":"Ksb Oder-spree",
    "wof:placetype":"venue"
},
  "geometry": {"coordinates":[14.0617904663,52.3616981506],"type":"Point"}
}