{
  "type": "Feature",
  "properties": {
    "iso:country":"DE",
    "sg:address":"Isernhagenerstr.98",
    "sg:city":"Hannover",
    "sg:phone":"+49 511/3970652",
    "sg:postcode":"30163",
    "sg:province":"Niedersachsen",
    "wof:name":"Playstation Modchip",
    "wof:placetype":"venue"
},
  "geometry": {"coordinates":[9.741598,52.397331],"type":"Point"}
}