{
  "type": "Feature",
  "properties": {
    "iso:country":"DE",
    "sg:address":"Kokenstr. 5",
    "sg:city":"Hannover",
    "sg:phone":"+49 511/281089",
    "sg:postcode":"30159",
    "sg:province":"Niedersachsen",
    "wof:name":"Karsten Und Christina Mai Rechtsanw\u00e4lte",
    "wof:placetype":"venue"
},
  "geometry": {"coordinates":[9.7530860901,52.3708152771],"type":"Point"}
}