{
  "type": "Feature",
  "properties": {
    "iso:country":"DE",
    "sg:address":"Rathausstr. 15a",
    "sg:city":"Leimen",
    "sg:phone":"+49 6224/76154",
    "sg:postcode":"69181",
    "sg:province":"Baden-W\u00fcrttemberg",
    "wof:name":"Kurt Rust Rechtsanwalt",
    "wof:placetype":"venue"
},
  "geometry": {"coordinates":[8.6900873184,49.3489112854],"type":"Point"}
}