{
  "type": "Feature",
  "properties": {
    "iso:country":"DE",
    "sg:address":"Paunsdorfer Allee",
    "sg:city":"Leipzig",
    "sg:phone":"+49 341/2518903",
    "sg:postcode":"04329",
    "sg:province":"Sachsen",
    "wof:name":"Bonita Mode Handels- Gesellschaft Mbh & Co. Kg",
    "wof:placetype":"venue"
},
  "geometry": {"coordinates":[12.47291,51.359501],"type":"Point"}
}