{
  "type": "Feature",
  "properties": {
    "iso:country":"DE",
    "sg:address":"Kurt-Schumacher-Allee 46",
    "sg:city":"Bremen",
    "sg:phone":"+49 421/4674646",
    "sg:postcode":"28327",
    "sg:province":"Bremen",
    "wof:name":"Dr. Med. Hans Thiesen Arzt F\u00fcr Allgemeinmedizin",
    "wof:placetype":"venue"
},
  "geometry": {"coordinates":[8.8981542587,53.0794487],"type":"Point"}
}