{
  "type": "Feature",
  "properties": {
    "iso:country":"DE",
    "sg:address":"Am Umspannwerk 7",
    "sg:city":"Altdorf",
    "sg:phone":"+49 9187/905105",
    "sg:postcode":"90518",
    "sg:province":"Bayern",
    "wof:name":"Wagner Formentechnik Gmbh",
    "wof:placetype":"venue"
},
  "geometry": {"coordinates":[11.3307876587,49.3935546875],"type":"Point"}
}