{
  "type": "Feature",
  "properties": {
    "iso:country":"DE",
    "sg:address":"Ortsstr. 9",
    "sg:city":"D\u00f6rrmoschel",
    "sg:phone":"+49 6361/7322",
    "sg:postcode":"67806",
    "sg:province":"Rheinland-Pfalz",
    "wof:name":"K. Gintz Und W. Schmidt",
    "wof:placetype":"venue"
},
  "geometry": {"coordinates":[7.7543611526,49.6183395386],"type":"Point"}
}