{
  "type": "Feature",
  "properties": {
    "iso:country":"DE",
    "sg:address":"Bachstr. 3",
    "sg:city":"Plettenberg",
    "sg:phone":"+49 2391/580215",
    "sg:postcode":"58840",
    "sg:province":"Nordrhein-Westfalen",
    "wof:name":"Ernst-a. Schmellenkamp",
    "wof:placetype":"venue"
},
  "geometry": {"coordinates":[7.87232,51.232475],"type":"Point"}
}