{
  "type": "Feature",
  "properties": {
    "iso:country":"DE",
    "sg:address":"Friedberger Str. 101",
    "sg:city":"Bad Homburg",
    "sg:phone":"+49 6172/82366",
    "sg:postcode":"61350",
    "sg:province":"Hessen",
    "wof:name":"Bund Ev.-freikirchl. Gemeinden In Deutschland",
    "wof:placetype":"venue"
},
  "geometry": {"coordinates":[8.6190900803,50.2469596863],"type":"Point"}
}