{
  "type": "Feature",
  "properties": {
    "iso:country":"DE",
    "sg:address":"Friedrich-Engels-Ring 52",
    "sg:city":"Neubrandenburg",
    "sg:phone":"+49 395/5441246",
    "sg:postcode":"17033",
    "sg:province":"Mecklenburg-Vorpommern",
    "wof:name":"R. Hirschmann Finanzberater",
    "wof:placetype":"venue"
},
  "geometry": {"coordinates":[13.2670497894,53.5558242798],"type":"Point"}
}