{
  "type": "Feature",
  "properties": {
    "iso:country":"DE",
    "sg:address":"Weizenkamp 18",
    "sg:city":"Damme",
    "sg:phone":"+49 5491/2111",
    "sg:postcode":"49401",
    "sg:province":"Niedersachsen",
    "wof:name":"Ev. Pfarramt Damme",
    "wof:placetype":"venue"
},
  "geometry": {"coordinates":[8.1897192001,52.524772644],"type":"Point"}
}