{
  "type": "Feature",
  "properties": {
    "iso:country":"DE",
    "sg:address":"Karolingerstr. 44",
    "sg:city":"Erftstadt",
    "sg:postcode":"50374",
    "sg:province":"Nordrhein-Westfalen",
    "wof:name":"Berrenrather Hof",
    "wof:placetype":"venue"
},
  "geometry": {"coordinates":[6.8146691322,50.7825584412],"type":"Point"}
}