{
  "type": "Feature",
  "properties": {
    "iso:country":"DE",
    "sg:address":"Marktplatz 9-10",
    "sg:city":"Tauberbischofsheim",
    "sg:phone":"+49 9341/4047",
    "sg:postcode":"97941",
    "sg:province":"Baden-W\u00fcrttemberg",
    "wof:name":"Karlheinz B\u00f6digheimer Steuerberater",
    "wof:placetype":"venue"
},
  "geometry": {"coordinates":[9.6629543304,49.6231689453],"type":"Point"}
}