{
  "type": "Feature",
  "properties": {
    "iso:country":"DE",
    "sg:address":"Steinweg 5",
    "sg:city":"Dieburg",
    "sg:phone":"+49 6071/81333",
    "sg:postcode":"64807",
    "sg:province":"Hessen",
    "wof:name":"Bettina Steinmetz",
    "wof:placetype":"venue"
},
  "geometry": {"coordinates":[8.8360118866,49.8970146179],"type":"Point"}
}