{
  "type": "Feature",
  "properties": {
    "iso:country":"DE",
    "sg:address":"Plettstr. 11",
    "sg:city":"M\u00fcnchen",
    "sg:phone":"+49 89/6703238",
    "sg:postcode":"81735",
    "sg:province":"Bayern",
    "wof:name":"Red. Neuperlacher Post Spd Ortsverein M\u00fcnchen-",
    "wof:placetype":"venue"
},
  "geometry": {"coordinates":[11.6433649063,48.1080780029],"type":"Point"}
}