{
  "type": "Feature",
  "properties": {
    "iso:country":"DE",
    "sg:address":"Marktg\u00f6litzer Str. 28",
    "sg:city":"Probstzella",
    "sg:phone":"+49 36735/72270",
    "sg:postcode":"07330",
    "sg:province":"Th\u00fcringen",
    "wof:name":"Auto-r\u00fcmpler",
    "wof:placetype":"venue"
},
  "geometry": {"coordinates":[11.376789,50.537685],"type":"Point"}
}