{
  "type": "Feature",
  "properties": {
    "iso:country":"DE",
    "sg:address":"Durlacher Allee 56a",
    "sg:city":"Karlsruhe",
    "sg:phone":"+49 721/6600",
    "sg:postcode":"76131",
    "sg:province":"Baden-W\u00fcrttemberg",
    "wof:name":"Union Krankenversicherung Ag",
    "wof:placetype":"venue"
},
  "geometry": {"coordinates":[8.4260940552,49.0071029663],"type":"Point"}
}