{
  "type": "Feature",
  "properties": {
    "iso:country":"DE",
    "sg:address":"Hollerallee 67",
    "sg:city":"Bremen",
    "sg:phone":"+49 421/345244",
    "sg:postcode":"28209",
    "sg:province":"Bremen",
    "wof:name":"Cutting Crew",
    "wof:placetype":"venue"
},
  "geometry": {"coordinates":[8.8251667023,53.0839881897],"type":"Point"}
}