{
  "type": "Feature",
  "properties": {
    "iso:country":"DE",
    "sg:address":"Birkwitzer Str. 10",
    "sg:city":"Pirna",
    "sg:postcode":"01796",
    "sg:province":"Sachsen",
    "wof:name":"Bauservice Klein Gmbh",
    "wof:placetype":"venue"
},
  "geometry": {"coordinates":[13.929039,50.978531],"type":"Point"}
}