{
  "type": "Feature",
  "properties": {
    "iso:country":"DE",
    "sg:address":"Rothenburgsorter Marktplatz 8",
    "sg:city":"Hamburg",
    "sg:phone":"+49 40/7892918",
    "sg:postcode":"20539",
    "sg:province":"Hamburg",
    "wof:name":"H.-r. Witt",
    "wof:placetype":"venue"
},
  "geometry": {"coordinates":[10.039155,53.534214],"type":"Point"}
}