{
  "type": "Feature",
  "properties": {
    "iso:country":"DE",
    "sg:address":"Osterodaer Str. 3",
    "sg:city":"Herzberg",
    "sg:phone":"+49 3535/3025",
    "sg:postcode":"04916",
    "sg:province":"Brandenburg",
    "wof:name":"Merkur M\u00f6bel-vertrieb Gmbh",
    "wof:placetype":"venue"
},
  "geometry": {"coordinates":[13.301615,51.680336],"type":"Point"}
}