{
  "type": "Feature",
  "properties": {
    "iso:country":"DE",
    "sg:address":"Bauhofstr. 2",
    "sg:city":"Schwaig",
    "sg:phone":"+49 911/5067768",
    "sg:postcode":"90571",
    "sg:province":"Bayern",
    "wof:name":"Nhb Nu\u00df & Hoffmann Bauelemente Vertriebsgesellschaft Mbh",
    "wof:placetype":"venue"
},
  "geometry": {"coordinates":[11.202452,49.465794],"type":"Point"}
}