{
  "type": "Feature",
  "properties": {
    "iso:country":"DE",
    "sg:address":"Ahmser Str. 20",
    "sg:city":"Herford",
    "sg:phone":"+49 5221/70414",
    "sg:postcode":"32052",
    "sg:province":"Nordrhein-Westfalen",
    "wof:name":"G\u00fcnter Strauch",
    "wof:placetype":"venue"
},
  "geometry": {"coordinates":[8.6750659943,52.107875824],"type":"Point"}
}