{
  "type": "Feature",
  "properties": {
    "iso:country":"DE",
    "sg:address":"Hauptstr. 6",
    "sg:city":"Gars",
    "sg:phone":"+49 8073/2550",
    "sg:postcode":"83536",
    "sg:province":"Bayern",
    "wof:name":"Lambda Verlags Gmbh",
    "wof:placetype":"venue"
},
  "geometry": {"coordinates":[12.2768383026,48.1528320312],"type":"Point"}
}