{
  "type": "Feature",
  "properties": {
    "iso:country":"DE",
    "sg:address":"Im Hock 20",
    "sg:city":"Hilden",
    "sg:phone":"+49 2103/53361",
    "sg:postcode":"40721",
    "sg:province":"Nordrhein-Westfalen",
    "wof:name":"Sankyo Speditions Gmbh",
    "wof:placetype":"venue"
},
  "geometry": {"coordinates":[6.902525,51.172993],"type":"Point"}
}