{
  "type": "Feature",
  "properties": {
    "iso:country":"DE",
    "sg:address":"Mittelseeweg 14",
    "sg:city":"Wangen",
    "sg:phone":"+49 7528/7998",
    "sg:postcode":"88239",
    "sg:province":"Baden-W\u00fcrttemberg",
    "wof:name":"Anton Posawatz",
    "wof:placetype":"venue"
},
  "geometry": {"coordinates":[9.7641239166,47.6641578674],"type":"Point"}
}