{
  "type": "Feature",
  "properties": {
    "iso:country":"DE",
    "sg:address":"Karl-Liebknecht-Str. 53",
    "sg:city":"Eggersdorf",
    "sg:phone":"+49 3341/473477",
    "sg:postcode":"15345",
    "sg:province":"Brandenburg",
    "wof:name":"Christina U. Bernd Sawatzki",
    "wof:placetype":"venue"
},
  "geometry": {"coordinates":[13.8226442337,52.5389595032],"type":"Point"}
}