{
  "type": "Feature",
  "properties": {
    "iso:country":"DE",
    "sg:address":"Hintergasse 35",
    "sg:city":"Rohrbach",
    "sg:phone":"+49 6349/5206",
    "sg:postcode":"76865",
    "sg:province":"Rheinland-Pfalz",
    "wof:name":"Norbert Schneider",
    "wof:placetype":"venue"
},
  "geometry": {"coordinates":[8.130638,49.137966],"type":"Point"}
}