{
  "type": "Feature",
  "properties": {
    "iso:country":"DE",
    "sg:address":"Victor-Slotosch-Str. 19",
    "sg:city":"Frankfurt",
    "sg:phone":"+49 6109/731293",
    "sg:postcode":"60388",
    "sg:province":"Hessen",
    "wof:name":"Cleho-tec Gmbh",
    "wof:placetype":"venue"
},
  "geometry": {"coordinates":[8.7449226379,50.1432762146],"type":"Point"}
}