{
  "type": "Feature",
  "properties": {
    "iso:country":"DE",
    "sg:address":"Spitzweidenweg 107",
    "sg:city":"Jena",
    "sg:phone":"+49 3641/45170",
    "sg:postcode":"07743",
    "sg:province":"Th\u00fcringen",
    "wof:name":"B\u00e4rbel Erdmann Steuerberatungsges. Mbh",
    "wof:placetype":"venue"
},
  "geometry": {"coordinates":[11.5959911346,50.9415969849],"type":"Point"}
}