{
  "type": "Feature",
  "properties": {
    "iso:country":"DE",
    "sg:address":"Aspertshofen 16 Aspertshofen",
    "sg:city":"Kirchensittenbach",
    "sg:phone":"+49 9151/94648",
    "sg:postcode":"91241",
    "sg:province":"Bayern",
    "wof:name":"Ernst Seiler Architekt",
    "wof:placetype":"venue"
},
  "geometry": {"coordinates":[11.423415,49.555305],"type":"Point"}
}