{
  "type": "Feature",
  "properties": {
    "iso:country":"DE",
    "sg:address":"K\u00f6nigstr. 53",
    "sg:city":"Bornheim",
    "sg:phone":"+49 2222/5071",
    "sg:postcode":"53332",
    "sg:province":"Nordrhein-Westfalen",
    "wof:name":"Hans Hausen",
    "wof:placetype":"venue"
},
  "geometry": {"coordinates":[6.991762,50.762169],"type":"Point"}
}