{
  "type": "Feature",
  "properties": {
    "iso:country":"DE",
    "sg:address":"Ludwigstr. 8",
    "sg:city":"Johannesberg",
    "sg:phone":"+49 6021/411316",
    "sg:postcode":"63867",
    "sg:province":"Bayern",
    "wof:name":"Ffk Gastronomiebetriebs- Gmbh",
    "wof:placetype":"venue"
},
  "geometry": {"coordinates":[9.136166,50.026936],"type":"Point"}
}