{
  "type": "Feature",
  "properties": {
    "iso:country":"DE",
    "sg:address":"Hinter den H\u00f6fen 123",
    "sg:city":"Rotenburg",
    "sg:phone":"+49 4268/92000",
    "sg:postcode":"27356",
    "sg:province":"Niedersachsen",
    "wof:name":"Malkus Elektronik Gmbh",
    "wof:placetype":"venue"
},
  "geometry": {"coordinates":[9.31674,53.117111],"type":"Point"}
}