{
  "type": "Feature",
  "properties": {
    "iso:country":"DE",
    "sg:address":"Dieselstr. 24",
    "sg:city":"Schwaigern",
    "sg:phone":"+49 7138/7816",
    "sg:postcode":"74193",
    "sg:province":"Baden-W\u00fcrttemberg",
    "wof:name":"Hans Weidner",
    "wof:placetype":"venue"
},
  "geometry": {"coordinates":[9.0736627579,49.1387405396],"type":"Point"}
}