{
  "type": "Feature",
  "properties": {
    "iso:country":"DE",
    "sg:address":"Obere Kanalstr. 9",
    "sg:city":"N\u00fcrnberg",
    "sg:phone":"+49 911/262891",
    "sg:postcode":"90429",
    "sg:province":"Bayern",
    "wof:name":"Armin Heitzenr\u00f6ther Gmbh",
    "wof:placetype":"venue"
},
  "geometry": {"coordinates":[11.058777,49.448723],"type":"Point"}
}