{
  "type": "Feature",
  "properties": {
    "iso:country":"DE",
    "sg:address":"Lindenstr. 3",
    "sg:city":"Werder",
    "sg:phone":"+49 38720/80781",
    "sg:postcode":"19386",
    "sg:province":"Mecklenburg-Vorpommern",
    "wof:name":"H.-p. Erdmann",
    "wof:placetype":"venue"
},
  "geometry": {"coordinates":[11.9913330078,53.5292549133],"type":"Point"}
}