{
  "type": "Feature",
  "properties": {
    "iso:country":"DE",
    "sg:address":"Kranstr. 2-4",
    "sg:city":"Stuttgart",
    "sg:phone":"+49 711/833067",
    "sg:postcode":"70499",
    "sg:province":"Baden-W\u00fcrttemberg",
    "wof:name":"Adam Gmbh",
    "wof:placetype":"venue"
},
  "geometry": {"coordinates":[9.1036272049,48.8253250122],"type":"Point"}
}