{
  "type": "Feature",
  "properties": {
    "iso:country":"DE",
    "sg:address":"Wilhelmstr. 42",
    "sg:city":"Beckum",
    "sg:phone":"+49 2521/82050",
    "sg:postcode":"59269",
    "sg:province":"Nordrhein-Westfalen",
    "wof:name":"Theodor Holtkamp Gmbh",
    "wof:placetype":"venue"
},
  "geometry": {"coordinates":[8.0452804565,51.7576828003],"type":"Point"}
}