{
  "type": "Feature",
  "properties": {
    "iso:country":"DE",
    "sg:address":"Loerfeldstr. 24",
    "sg:city":"Herdecke",
    "sg:phone":"+49 2330/71091",
    "sg:postcode":"58313",
    "sg:province":"Nordrhein-Westfalen",
    "wof:name":"Willi Jeuschede Apparatebau Gmbh",
    "wof:placetype":"venue"
},
  "geometry": {"coordinates":[7.436978817,51.4243049622],"type":"Point"}
}