{
  "type": "Feature",
  "properties": {
    "iso:country":"DE",
    "sg:address":"Mirabellenstr. 42",
    "sg:city":"Stuttgart",
    "sg:phone":"+49 711/9183146",
    "sg:postcode":"70329",
    "sg:province":"Baden-W\u00fcrttemberg",
    "wof:name":"D. H\u00fcbner",
    "wof:placetype":"venue"
},
  "geometry": {"coordinates":[9.2676038742,48.7674865723],"type":"Point"}
}