{
  "type": "Feature",
  "properties": {
    "iso:country":"DE",
    "sg:address":"Bahnhofstr. 30",
    "sg:city":"Goch",
    "sg:phone":"+49 2823/2056",
    "sg:postcode":"47574",
    "sg:province":"Nordrhein-Westfalen",
    "wof:name":"Carl Nassmacher Gmbh",
    "wof:placetype":"venue"
},
  "geometry": {"coordinates":[6.160490036,51.6787109375],"type":"Point"}
}