{
  "type": "Feature",
  "properties": {
    "iso:country":"DE",
    "sg:address":"Kreuzbergstr. 3",
    "sg:city":"Bad Kissingen",
    "sg:phone":"+49 9736/81880",
    "sg:postcode":"97688",
    "sg:province":"Bayern",
    "wof:name":"Christian Keul Wohntextilia Gmbh Import Ex-",
    "wof:placetype":"venue"
},
  "geometry": {"coordinates":[9.9954452515,50.2086143494],"type":"Point"}
}