{
  "type": "Feature",
  "properties": {
    "iso:country":"DE",
    "sg:address":"M\u00fcckernscher Weg 63",
    "sg:city":"Schm\u00f6lln",
    "sg:phone":"+49 34491/80860",
    "sg:postcode":"04626",
    "sg:province":"Th\u00fcringen",
    "wof:name":"E. Junghanns",
    "wof:placetype":"venue"
},
  "geometry": {"coordinates":[12.375627,50.907261],"type":"Point"}
}