{
  "type": "Feature",
  "properties": {
    "iso:country":"DE",
    "sg:address":"Industriestr. 1",
    "sg:city":"Schenefeld",
    "sg:phone":"+49 40/8308369",
    "sg:postcode":"22869",
    "sg:province":"Schleswig-Holstein",
    "wof:name":"Heinz Biemann",
    "wof:placetype":"venue"
},
  "geometry": {"coordinates":[9.8380384445,53.6009597778],"type":"Point"}
}