{
  "type": "Feature",
  "properties": {
    "iso:country":"DE",
    "sg:address":"Am Markt 13",
    "sg:city":"Colmberg",
    "sg:phone":"+49 9803/200",
    "sg:postcode":"91598",
    "sg:province":"Bayern",
    "wof:name":"W. Schober",
    "wof:placetype":"venue"
},
  "geometry": {"coordinates":[10.410022,49.353886],"type":"Point"}
}