{
  "type": "Feature",
  "properties": {
    "iso:country":"DE",
    "sg:address":"Hildebrandstr. 17",
    "sg:city":"Dortmund",
    "sg:phone":"+49 4923/1138020",
    "sg:postcode":"44319",
    "sg:province":"Nordrhein-Westfalen",
    "wof:name":"Caso Beleuchtungsmasten Gmbh",
    "wof:placetype":"venue"
},
  "geometry": {"coordinates":[7.626372,51.530285],"type":"Point"}
}