{
  "type": "Feature",
  "properties": {
    "iso:country":"DE",
    "sg:address":"Hamburger Str. 12",
    "sg:city":"Hagenow",
    "sg:phone":"+49 3883/722828",
    "sg:postcode":"19230",
    "sg:province":"Mecklenburg-Vorpommern",
    "wof:name":"E. Ritschel",
    "wof:placetype":"venue"
},
  "geometry": {"coordinates":[11.18233,53.436729],"type":"Point"}
}