{
  "type": "Feature",
  "properties": {
    "iso:country":"DE",
    "sg:address":"Zur Abtsk\u00fcche 68",
    "sg:city":"Velbert",
    "sg:postcode":"42549",
    "sg:province":"Nordrhein-Westfalen",
    "wof:name":"N. Koudsi Masseur",
    "wof:placetype":"venue"
},
  "geometry": {"coordinates":[7.012916,51.337238],"type":"Point"}
}