{
  "type": "Feature",
  "properties": {
    "iso:country":"DE",
    "sg:address":"Gro\u00dfe Ulrichstr. 54",
    "sg:city":"Halle",
    "sg:postcode":"06108",
    "sg:province":"Sachsen-Anhalt",
    "wof:name":"Lichtquelle Inh. Barbara J\u00e4hnig",
    "wof:placetype":"venue"
},
  "geometry": {"coordinates":[11.9692306519,51.4848442078],"type":"Point"}
}