{
  "type": "Feature",
  "properties": {
    "iso:country":"DE",
    "sg:address":"Heinrich-L\u00fcbke-Str. 22",
    "sg:city":"Trier",
    "sg:phone":"+49 651/21745",
    "sg:postcode":"54296",
    "sg:province":"Rheinland-Pfalz",
    "wof:name":"Kyffh\u00e4user- Und Finanzsport- Stiftung Rheinland Pfalz B. R.",
    "wof:placetype":"venue"
},
  "geometry": {"coordinates":[6.6829152107,49.742767334],"type":"Point"}
}