{
  "type": "Feature",
  "properties": {
    "iso:country":"DE",
    "sg:address":"Kempenicher Str. 7",
    "sg:city":"Spessart",
    "sg:phone":"+49 2655/4107",
    "sg:postcode":"56746",
    "sg:province":"Rheinland-Pfalz",
    "wof:name":"Johannes Schulz Architekt",
    "wof:placetype":"venue"
},
  "geometry": {"coordinates":[7.114199,50.43969],"type":"Point"}
}