{
  "type": "Feature",
  "properties": {
    "iso:country":"DE",
    "sg:address":"Sprenger Weg 2",
    "sg:city":"Schwedeneck",
    "sg:phone":"+49 4308/666",
    "sg:postcode":"24229",
    "sg:province":"Schleswig-Holstein",
    "wof:name":"Hotel Tannenhof",
    "wof:placetype":"venue"
},
  "geometry": {"coordinates":[10.0753498077,54.4690208435],"type":"Point"}
}