{
  "type": "Feature",
  "properties": {
    "iso:country":"DE",
    "sg:address":"Fichtestr. 9",
    "sg:city":"Plauen",
    "sg:phone":"+49 3741/224217",
    "sg:postcode":"08527",
    "sg:province":"Sachsen",
    "wof:name":"Hartwig Valtin",
    "wof:placetype":"venue"
},
  "geometry": {"coordinates":[12.1405439377,50.4805984497],"type":"Point"}
}