{
  "type": "Feature",
  "properties": {
    "iso:country":"DE",
    "sg:address":"Alte Dorfstr. 18",
    "sg:city":"Grove",
    "sg:phone":"+49 4151/895839",
    "sg:postcode":"21493",
    "sg:province":"Schleswig-Holstein",
    "wof:name":"Fisch & Rick",
    "wof:placetype":"venue"
},
  "geometry": {"coordinates":[10.496531,53.529018],"type":"Point"}
}