{
  "type": "Feature",
  "properties": {
    "iso:country":"DE",
    "sg:address":"Bl\u00fccherstr 108",
    "sg:city":"M\u00fclheim",
    "sg:phone":"+49 208/495780",
    "sg:postcode":"45472",
    "sg:province":"Nordrhein-Westfalen",
    "wof:name":"Spedition Fabry Gmbh",
    "wof:placetype":"venue"
},
  "geometry": {"coordinates":[6.938436985,51.4364204407],"type":"Point"}
}