{
  "type": "Feature",
  "properties": {
    "iso:country":"DE",
    "sg:address":"Altk\u00f6nigweg 4",
    "sg:city":"Eschborn",
    "sg:phone":"+49 6173/61562",
    "sg:postcode":"65760",
    "sg:province":"Hessen",
    "wof:name":"D. Jerger Immobilienmakler",
    "wof:placetype":"venue"
},
  "geometry": {"coordinates":[8.5463790894,50.1554946899],"type":"Point"}
}