{
  "type": "Feature",
  "properties": {
    "iso:country":"DE",
    "sg:address":"Hinter dem Busch 55",
    "sg:city":"Loxstedt",
    "sg:phone":"+49 4744/1081",
    "sg:postcode":"27612",
    "sg:province":"Niedersachsen",
    "wof:name":"Werner Grotheer",
    "wof:placetype":"venue"
},
  "geometry": {"coordinates":[8.62154,53.415699],"type":"Point"}
}