{
  "type": "Feature",
  "properties": {
    "iso:country":"DE",
    "sg:address":"Glindenberger Weg 5",
    "sg:city":"Magdeburg",
    "sg:postcode":"39126",
    "sg:province":"Sachsen-Anhalt",
    "wof:name":"Winter Abfallwirtschaft Und Recycling Gmbh",
    "wof:placetype":"venue"
},
  "geometry": {"coordinates":[11.674864769,52.213848114],"type":"Point"}
}