{
  "type": "Feature",
  "properties": {
    "iso:country":"DE",
    "sg:address":"Am Schlo\u00df 3",
    "sg:city":"Dresden",
    "sg:postcode":"01328",
    "sg:province":"Sachsen",
    "wof:name":"Christine Dorn",
    "wof:placetype":"venue"
},
  "geometry": {"coordinates":[13.8944597244,51.0327644348],"type":"Point"}
}