{
  "type": "Feature",
  "properties": {
    "iso:country":"DE",
    "sg:address":"Lochfeldstr. 30",
    "sg:city":"Rastatt",
    "sg:phone":"+49 7222/5055630",
    "sg:postcode":"76437",
    "sg:province":"Baden-W\u00fcrttemberg",
    "wof:name":"Modelling-pro Gmbh",
    "wof:placetype":"venue"
},
  "geometry": {"coordinates":[8.230639,48.854496],"type":"Point"}
}