{
  "type": "Feature",
  "properties": {
    "iso:country":"DE",
    "sg:address":"Wandsbeker Zollstr. 92-98",
    "sg:city":"Hamburg",
    "sg:phone":"+49 40/656620",
    "sg:postcode":"22041",
    "sg:province":"Hamburg",
    "wof:name":"Hzk-krankenkasse F. Bau- Und Holzberufe",
    "wof:placetype":"venue"
},
  "geometry": {"coordinates":[10.07963,53.57592],"type":"Point"}
}