{
  "type": "Feature",
  "properties": {
    "iso:country":"DE",
    "sg:address":"Luitpoldstr. 7",
    "sg:city":"Hirschaid",
    "sg:phone":"+49 9543/5472",
    "sg:postcode":"96114",
    "sg:province":"Bayern",
    "wof:name":"Norbert Postler",
    "wof:placetype":"venue"
},
  "geometry": {"coordinates":[10.9875249863,49.8161506653],"type":"Point"}
}