{
  "type": "Feature",
  "properties": {
    "iso:country":"DE",
    "sg:address":"Jamlitzer Str. 71",
    "sg:city":"Cottbus",
    "sg:phone":"+49 355/700172",
    "sg:postcode":"03046",
    "sg:province":"Brandenburg",
    "wof:name":"Test-fuchs Fritz Fuchs Gmbh & Co. Kg",
    "wof:placetype":"venue"
},
  "geometry": {"coordinates":[14.3277196884,51.7598495483],"type":"Point"}
}