{
  "type": "Feature",
  "properties": {
    "iso:country":"DE",
    "sg:address":"Glehner Weg 25",
    "sg:city":"Neuss",
    "sg:phone":"+49 2131/85372",
    "sg:postcode":"41464",
    "sg:province":"Nordrhein-Westfalen",
    "wof:name":"E. Linnemann",
    "wof:placetype":"venue"
},
  "geometry": {"coordinates":[6.671718,51.19672],"type":"Point"}
}