{
  "type": "Feature",
  "properties": {
    "iso:country":"DE",
    "sg:address":"Ausbau 2",
    "sg:city":"Marihn",
    "sg:phone":"+49 3962/210797",
    "sg:postcode":"17219",
    "sg:province":"Mecklenburg-Vorpommern",
    "wof:name":"Marihn Inh. Fritz Ro\u00df",
    "wof:placetype":"venue"
},
  "geometry": {"coordinates":[12.9285020828,53.5231781006],"type":"Point"}
}