{
  "type": "Feature",
  "properties": {
    "iso:country":"DE",
    "sg:address":"Steinbuck 5",
    "sg:city":"Klettgau",
    "sg:phone":"+49 7742/7313",
    "sg:postcode":"79771",
    "sg:province":"Baden-W\u00fcrttemberg",
    "wof:name":"Jochen Just",
    "wof:placetype":"venue"
},
  "geometry": {"coordinates":[8.427347,47.659233],"type":"Point"}
}