{
  "type": "Feature",
  "properties": {
    "iso:country":"DE",
    "sg:address":"Hauptstr. 46",
    "sg:city":"Kirchlinteln",
    "sg:phone":"+49 4236/777",
    "sg:postcode":"27308",
    "sg:province":"Niedersachsen",
    "wof:name":"Geest-apotheke",
    "wof:placetype":"venue"
},
  "geometry": {"coordinates":[9.324482,52.941456],"type":"Point"}
}