{
  "type": "Feature",
  "properties": {
    "iso:country":"DE",
    "sg:address":"Beeskower Str. 36",
    "sg:city":"Eisenh\u00fcttenstadt",
    "sg:phone":"+49 3364/43473",
    "sg:postcode":"15890",
    "sg:province":"Brandenburg",
    "wof:name":"Irmgard Holz",
    "wof:placetype":"venue"
},
  "geometry": {"coordinates":[14.6395292282,52.1504554749],"type":"Point"}
}