{
  "type": "Feature",
  "properties": {
    "iso:country":"DE",
    "sg:address":"Richard-Friedrich-Str 2",
    "sg:city":"Schlema",
    "sg:phone":"+49 3772/381770",
    "sg:postcode":"08301",
    "sg:province":"Sachsen",
    "wof:name":"Luftbildservice B\u00fcschel",
    "wof:placetype":"venue"
},
  "geometry": {"coordinates":[12.656981,50.600739],"type":"Point"}
}