{
  "type": "Feature",
  "properties": {
    "iso:country":"DE",
    "sg:address":"Industriestr. 49",
    "sg:city":"Gundelfingen",
    "sg:phone":"+49 761/589265",
    "sg:postcode":"79194",
    "sg:province":"Baden-W\u00fcrttemberg",
    "wof:name":"Restaurant Suwadee",
    "wof:placetype":"venue"
},
  "geometry": {"coordinates":[7.8587861061,48.0454788208],"type":"Point"}
}