{
  "type": "Feature",
  "properties": {
    "iso:country":"DE",
    "sg:address":"An den Teichen 40",
    "sg:city":"Dresden",
    "sg:phone":"+49 351/8804526",
    "sg:postcode":"01108",
    "sg:province":"Sachsen",
    "wof:name":"Siegfried Ziller",
    "wof:placetype":"venue"
},
  "geometry": {"coordinates":[13.8069133759,51.1478042603],"type":"Point"}
}