{
  "type": "Feature",
  "properties": {
    "iso:country":"DE",
    "sg:address":"Schinnergasse 22",
    "sg:city":"Nidderau",
    "sg:phone":"+49 6187/25087",
    "sg:postcode":"61130",
    "sg:province":"Hessen",
    "wof:name":"Gerd Und Heinz Brodt",
    "wof:placetype":"venue"
},
  "geometry": {"coordinates":[8.911444,50.226784],"type":"Point"}
}