{
  "type": "Feature",
  "properties": {
    "iso:country":"DE",
    "sg:address":"Unterer Steinberg 19",
    "sg:city":"Langen",
    "sg:phone":"+49 6103/928450",
    "sg:postcode":"63225",
    "sg:province":"Hessen",
    "wof:name":"A. K\u00f6rner",
    "wof:placetype":"venue"
},
  "geometry": {"coordinates":[8.6862316132,49.9854278564],"type":"Point"}
}