{
  "type": "Feature",
  "properties": {
    "iso:country":"DE",
    "sg:address":"Grenzstr. 200",
    "sg:city":"Voerde",
    "sg:postcode":"46562",
    "sg:province":"Nordrhein-Westfalen",
    "wof:name":"Real",
    "wof:placetype":"venue"
},
  "geometry": {"coordinates":[6.6806430817,51.6164550781],"type":"Point"}
}