{
  "type": "Feature",
  "properties": {
    "iso:country":"DE",
    "sg:address":"Fleischstr. 8",
    "sg:city":"Trier",
    "sg:phone":"+49 651/4360371",
    "sg:postcode":"54290",
    "sg:province":"Rheinland-Pfalz",
    "wof:name":"Fix & Foto Bilder-service Gmbh",
    "wof:placetype":"venue"
},
  "geometry": {"coordinates":[6.640059948,49.7560920715],"type":"Point"}
}