{
  "type": "Feature",
  "properties": {
    "iso:country":"DE",
    "sg:address":"Lychener Str. 7",
    "sg:city":"Berlin",
    "sg:phone":"+49 30/4427495",
    "sg:postcode":"10437",
    "sg:province":"Berlin",
    "wof:name":"J\u00fcrgen Abraham Gmbh",
    "wof:placetype":"venue"
},
  "geometry": {"coordinates":[13.414885,52.541584],"type":"Point"}
}