{
  "type": "Feature",
  "properties": {
    "iso:country":"DE",
    "sg:address":"Breite Str. 47",
    "sg:city":"Itzehoe",
    "sg:phone":"+49 4821/3303",
    "sg:postcode":"25524",
    "sg:province":"Schleswig-Holstein",
    "wof:name":"Elke Maier",
    "wof:placetype":"venue"
},
  "geometry": {"coordinates":[9.5171575546,53.9214782715],"type":"Point"}
}