{
  "type": "Feature",
  "properties": {
    "iso:country":"DE",
    "sg:address":"R\u00f6merstr. 31",
    "sg:city":"Pollenfeld",
    "sg:phone":"+49 8421/1851",
    "sg:postcode":"85131",
    "sg:province":"Bayern",
    "wof:name":"Peter Enhuber",
    "wof:placetype":"venue"
},
  "geometry": {"coordinates":[11.20161,48.919769],"type":"Point"}
}