{
  "type": "Feature",
  "properties": {
    "iso:country":"DE",
    "sg:address":"Marktplatz 4",
    "sg:city":"Hengersberg",
    "sg:phone":"+49 9901/6103",
    "sg:postcode":"94491",
    "sg:province":"Bayern",
    "wof:name":"Georg Loibl",
    "wof:placetype":"venue"
},
  "geometry": {"coordinates":[13.0514745712,48.7738113403],"type":"Point"}
}