{
  "type": "Feature",
  "properties": {
    "iso:country":"DE",
    "sg:address":"Schlo\u00dfplatz 3",
    "sg:city":"Jever",
    "sg:phone":"+49 4461/9150",
    "sg:postcode":"26441",
    "sg:province":"Niedersachsen",
    "wof:name":"Immobilien-service Raiffeisen-volksbank",
    "wof:placetype":"venue"
},
  "geometry": {"coordinates":[7.9041490555,53.5727539062],"type":"Point"}
}