{
  "type": "Feature",
  "properties": {
    "iso:country":"DE",
    "sg:address":"Beulertweg 4",
    "sg:city":"M\u00fcrlenbach",
    "sg:phone":"+49 6594/393",
    "sg:postcode":"54570",
    "sg:province":"Rheinland-Pfalz",
    "wof:name":"Chr. Dornbusch",
    "wof:placetype":"venue"
},
  "geometry": {"coordinates":[6.6019320488,50.1485939026],"type":"Point"}
}