{
  "type": "Feature",
  "properties": {
    "iso:country":"DE",
    "sg:address":"Elfter Tor 20",
    "sg:city":"Hille",
    "sg:phone":"+49 5734/2283",
    "sg:postcode":"32479",
    "sg:province":"Nordrhein-Westfalen",
    "wof:name":"G\u00fcnter Schrader",
    "wof:placetype":"venue"
},
  "geometry": {"coordinates":[8.7750806808,52.284450531],"type":"Point"}
}