{
  "type": "Feature",
  "properties": {
    "iso:country":"DE",
    "sg:address":"Max-Wenzel-Str. 20",
    "sg:city":"Ehrenfriedersdorf",
    "sg:phone":"+49 37341/46139",
    "sg:postcode":"09427",
    "sg:province":"Sachsen",
    "wof:name":"Entsorgungsgesellschaft Zschopau Gmbh",
    "wof:placetype":"venue"
},
  "geometry": {"coordinates":[12.96634,50.64608],"type":"Point"}
}