{
  "type": "Feature",
  "properties": {
    "iso:country":"DE",
    "sg:address":"Im Sand 10",
    "sg:city":"Bad Sch\u00f6nborn",
    "sg:postcode":"76669",
    "sg:province":"Baden-W\u00fcrttemberg",
    "wof:name":"Kvm Edelstahlverarbeitung Gmbh",
    "wof:placetype":"venue"
},
  "geometry": {"coordinates":[8.633405,49.204075],"type":"Point"}
}