{
  "type": "Feature",
  "properties": {
    "iso:country":"DE",
    "sg:address":"Altendorfer Str. 323",
    "sg:city":"Essen",
    "sg:phone":"+49 201/641850",
    "sg:postcode":"45143",
    "sg:province":"Nordrhein-Westfalen",
    "wof:name":"Nordmann",
    "wof:placetype":"venue"
},
  "geometry": {"coordinates":[6.976934,51.461246],"type":"Point"}
}