{
  "type": "Feature",
  "properties": {
    "iso:country":"DE",
    "sg:address":"Wasserburger Str. 15",
    "sg:city":"Altenmarkt",
    "sg:phone":"+49 8621/2434",
    "sg:postcode":"83352",
    "sg:province":"Bayern",
    "wof:name":"Siegfried Auer",
    "wof:placetype":"venue"
},
  "geometry": {"coordinates":[12.532202,48.004379],"type":"Point"}
}