{
  "type": "Feature",
  "properties": {
    "iso:country":"DE",
    "sg:address":"Stra\u00dfe der AWG 5",
    "sg:city":"Dorndorf-Steudnitz",
    "sg:phone":"+49 36427/71221",
    "sg:postcode":"07778",
    "sg:province":"Th\u00fcringen",
    "wof:name":"H. Und S. Waltinger",
    "wof:placetype":"venue"
},
  "geometry": {"coordinates":[11.689348,51.010159],"type":"Point"}
}