{
  "type": "Feature",
  "properties": {
    "iso:country":"DE",
    "sg:address":"In der Steinbach 56",
    "sg:city":"Laubach",
    "sg:phone":"+49 6405/1008",
    "sg:postcode":"35321",
    "sg:province":"Hessen",
    "wof:name":"C. Hundeborn",
    "wof:placetype":"venue"
},
  "geometry": {"coordinates":[8.997905,50.538876],"type":"Point"}
}