{
  "type": "Feature",
  "properties": {
    "iso:country":"DE",
    "sg:address":"Westenhellweg 24",
    "sg:city":"Dortmund",
    "sg:phone":"+49 231/572061",
    "sg:postcode":"44137",
    "sg:province":"Nordrhein-Westfalen",
    "wof:name":"Schwanen-apotheke",
    "wof:placetype":"venue"
},
  "geometry": {"coordinates":[7.465092,51.514137],"type":"Point"}
}