{
  "type": "Feature",
  "properties": {
    "iso:country":"DE",
    "sg:address":"Markt 34-38",
    "sg:city":"Marktredwitz",
    "sg:phone":"+49 9231/5080",
    "sg:postcode":"95615",
    "sg:province":"Bayern",
    "wof:name":"Freiwahl Kaufhaus Gmbh & Co. Zentrum Kg",
    "wof:placetype":"venue"
},
  "geometry": {"coordinates":[12.08606,50.000835],"type":"Point"}
}