{
  "type": "Feature",
  "properties": {
    "iso:country":"DE",
    "sg:address":"Elisabethstr. 18",
    "sg:city":"Hannover",
    "sg:phone":"+49 511/527184",
    "sg:postcode":"30559",
    "sg:province":"Niedersachsen",
    "wof:name":"Tiergarten Immobilien Gmbh",
    "wof:placetype":"venue"
},
  "geometry": {"coordinates":[9.8356304169,52.3610343933],"type":"Point"}
}