{
  "type": "Feature",
  "properties": {
    "iso:country":"DE",
    "sg:address":"Hauptstr. 100",
    "sg:city":"Lichtenberg",
    "sg:phone":"+49 37323/1275",
    "sg:postcode":"09638",
    "sg:province":"Sachsen",
    "wof:name":"Karsten Braune",
    "wof:placetype":"venue"
},
  "geometry": {"coordinates":[13.397399,50.837406],"type":"Point"}
}