{
  "type": "Feature",
  "properties": {
    "iso:country":"DE",
    "sg:address":"Kommenderiestr. 43",
    "sg:city":"Osnabr\u00fcck",
    "sg:phone":"+49 541/23476",
    "sg:postcode":"49074",
    "sg:province":"Niedersachsen",
    "wof:name":"Georg Giersch",
    "wof:placetype":"venue"
},
  "geometry": {"coordinates":[8.0491924286,52.2687606812],"type":"Point"}
}