{
  "type": "Feature",
  "properties": {
    "iso:country":"DE",
    "sg:address":"Im Erlengrund 2",
    "sg:city":"Bietigheim-Bissingen",
    "sg:phone":"+49 7142/30318",
    "sg:postcode":"74321",
    "sg:province":"Baden-W\u00fcrttemberg",
    "wof:name":"Gerhard Kiemle Gem\u00fcsebau",
    "wof:placetype":"venue"
},
  "geometry": {"coordinates":[9.1101112366,48.9341278076],"type":"Point"}
}