{
  "type": "Feature",
  "properties": {
    "iso:country":"DE",
    "sg:address":"Mainzer Str. 10",
    "sg:city":"Emden",
    "sg:phone":"+49 4921/942717",
    "sg:postcode":"26721",
    "sg:province":"Niedersachsen",
    "wof:name":"Peters",
    "wof:placetype":"venue"
},
  "geometry": {"coordinates":[7.198141098,53.3812255859],"type":"Point"}
}