{
  "type": "Feature",
  "properties": {
    "iso:country":"DE",
    "sg:address":"Postfach 1264:: 67802 Rockenhausen:: Germany.^^Br\u00fchlgasse 3::",
    "sg:city":"Rockenhausen",
    "sg:phone":"+49 6361/4530",
    "sg:postcode":"67806",
    "sg:province":"Rheinland-Pfalz",
    "wof:name":"Sparkasse Donnersberg",
    "wof:placetype":"venue"
},
  "geometry": {"coordinates":[7.815121,49.629913],"type":"Point"}
}