{
  "type": "Feature",
  "properties": {
    "iso:country":"DE",
    "sg:address":"Paffenl\u00f6h 30",
    "sg:city":"Burscheid",
    "sg:phone":"+49 2174/62821",
    "sg:postcode":"51399",
    "sg:province":"Nordrhein-Westfalen",
    "wof:name":"R. Seydholdt Immobilienmakler",
    "wof:placetype":"venue"
},
  "geometry": {"coordinates":[7.1125302315,51.0994300842],"type":"Point"}
}