{
  "type": "Feature",
  "properties": {
    "iso:country":"DE",
    "sg:address":"Am Strande 3a",
    "sg:city":"Rostock",
    "sg:phone":"+49 381/4901363",
    "sg:postcode":"18055",
    "sg:province":"Mecklenburg-Vorpommern",
    "wof:name":"Shin Shin Restaurations- Betriebe Rostock Gmbh",
    "wof:placetype":"venue"
},
  "geometry": {"coordinates":[12.1443376541,54.0930137634],"type":"Point"}
}