{
  "type": "Feature",
  "properties": {
    "iso:country":"DE",
    "sg:address":"Hauptstr. 21",
    "sg:city":"Oberrot",
    "sg:phone":"+49 7977/262",
    "sg:postcode":"74420",
    "sg:province":"Baden-W\u00fcrttemberg",
    "wof:name":"Kath. Pfarramt St. Michael",
    "wof:placetype":"venue"
},
  "geometry": {"coordinates":[9.6788635254,49.0045661926],"type":"Point"}
}