{
  "type": "Feature",
  "properties": {
    "iso:country":"DE",
    "sg:address":"Lange Str. 63",
    "sg:city":"Osnabr\u00fcck",
    "sg:phone":"+49 541/87612",
    "sg:postcode":"49080",
    "sg:province":"Niedersachsen",
    "wof:name":"Hans-georg Dieckmann",
    "wof:placetype":"venue"
},
  "geometry": {"coordinates":[8.042601,52.267128],"type":"Point"}
}