{
  "type": "Feature",
  "properties": {
    "iso:country":"DE",
    "sg:address":"Ulmer Str. 139",
    "sg:city":"Augsburg",
    "sg:phone":"+49 821/401320",
    "sg:postcode":"86156",
    "sg:province":"Bayern",
    "wof:name":"M. Khodayari",
    "wof:placetype":"venue"
},
  "geometry": {"coordinates":[10.8605079651,48.3802528381],"type":"Point"}
}