{
  "type": "Feature",
  "properties": {
    "iso:country":"DE",
    "sg:address":"Bentlager Weg",
    "sg:city":"Rheine",
    "sg:phone":"+49 5971/15366",
    "sg:postcode":"48431",
    "sg:province":"Nordrhein-Westfalen",
    "wof:name":"Tiergartenrestaurant Marianne Schneiders",
    "wof:placetype":"venue"
},
  "geometry": {"coordinates":[7.4334959984,52.2868309021],"type":"Point"}
}