{
  "type": "Feature",
  "properties": {
    "iso:country":"DE",
    "sg:address":"Risserkogelstr. 8",
    "sg:city":"M\u00fcnchen",
    "sg:phone":"+49 89/594888",
    "sg:postcode":"81673",
    "sg:province":"Bayern",
    "wof:name":"Amann Ohg A & H Contacts",
    "wof:placetype":"venue"
},
  "geometry": {"coordinates":[11.6410503387,48.1255264282],"type":"Point"}
}