{
  "type": "Feature",
  "properties": {
    "iso:country":"DE",
    "sg:address":"Auf dem Knapp 36",
    "sg:city":"Remscheid",
    "sg:phone":"+49 2191/341059",
    "sg:postcode":"42855",
    "sg:province":"Nordrhein-Westfalen",
    "wof:name":"Beitzel Gmbh & Co. Lager Und Logistik Kg",
    "wof:placetype":"venue"
},
  "geometry": {"coordinates":[7.22873,51.186447],"type":"Point"}
}