{
  "type": "Feature",
  "properties": {
    "iso:country":"DE",
    "sg:address":"Amselweg 10",
    "sg:city":"Thierhaupten",
    "sg:phone":"+49 8271/2739",
    "sg:postcode":"86672",
    "sg:province":"Bayern",
    "wof:name":"Wolfgang Klaus",
    "wof:placetype":"venue"
},
  "geometry": {"coordinates":[10.922055,48.561489],"type":"Point"}
}