{
  "type": "Feature",
  "properties": {
    "iso:country":"DE",
    "sg:address":"Nunsdorfer Ring 14",
    "sg:city":"Berlin",
    "sg:phone":"+49 30/6659040",
    "sg:postcode":"12277",
    "sg:province":"Berlin",
    "wof:name":"Kessel Technische Dienste Gmbh",
    "wof:placetype":"venue"
},
  "geometry": {"coordinates":[13.382013,52.407719],"type":"Point"}
}