{
  "type": "Feature",
  "properties": {
    "iso:country":"DE",
    "sg:address":"M\u00fchlweg 2",
    "sg:city":"Gro\u00df-Gerau",
    "sg:phone":"+49 6152/950126",
    "sg:postcode":"64521",
    "sg:province":"Hessen",
    "wof:name":"Kuhn Gmbh",
    "wof:placetype":"venue"
},
  "geometry": {"coordinates":[8.49334,49.921715],"type":"Point"}
}