{
  "type": "Feature",
  "properties": {
    "iso:country":"DE",
    "sg:address":"Baumhauser Weg 48C",
    "sg:city":"Bremen",
    "sg:phone":"+49 421/832511",
    "sg:postcode":"28279",
    "sg:province":"Bremen",
    "wof:name":"Hans-j\u00fcrgen Lange Architekt",
    "wof:placetype":"venue"
},
  "geometry": {"coordinates":[8.857074,53.041992],"type":"Point"}
}