{
  "type": "Feature",
  "properties": {
    "iso:country":"DE",
    "sg:address":"Im Grund 3",
    "sg:city":"Neu-Ulm",
    "sg:phone":"+49 7307/24411",
    "sg:postcode":"89233",
    "sg:province":"Bayern",
    "wof:name":"Bernhard Dobler",
    "wof:placetype":"venue"
},
  "geometry": {"coordinates":[10.095441,48.347607],"type":"Point"}
}