{
  "type": "Feature",
  "properties": {
    "iso:country":"DE",
    "sg:address":"Sulmaring 16",
    "sg:city":"Vogtareuth",
    "sg:phone":"+49 8038/848",
    "sg:postcode":"83569",
    "sg:province":"Bayern",
    "wof:name":"Leonhardiverein Leonhardspfunzen E. V.",
    "wof:placetype":"venue"
},
  "geometry": {"coordinates":[12.1635637283,47.9296569824],"type":"Point"}
}