{
  "type": "Feature",
  "properties": {
    "iso:country":"DE",
    "sg:address":"Hauptstr. 26",
    "sg:city":"Heek",
    "sg:phone":"+49 2568/1253",
    "sg:postcode":"48619",
    "sg:province":"Nordrhein-Westfalen",
    "wof:name":"Werner Lammers",
    "wof:placetype":"venue"
},
  "geometry": {"coordinates":[7.1022610664,52.1333618164],"type":"Point"}
}