{
  "type": "Feature",
  "properties": {
    "iso:country":"DE",
    "sg:address":"Kelterstr. 31",
    "sg:city":"Wurmberg",
    "sg:phone":"+49 7041/861352",
    "sg:postcode":"75449",
    "sg:province":"Baden-W\u00fcrttemberg",
    "wof:name":"Schurr Microelektronik",
    "wof:placetype":"venue"
},
  "geometry": {"coordinates":[8.8151464462,48.8742752075],"type":"Point"}
}