{
  "type": "Feature",
  "properties": {
    "iso:country":"DE",
    "sg:address":"Wandalenweg 24-26",
    "sg:city":"Hamburg",
    "sg:phone":"+49 40/23520400",
    "sg:postcode":"20097",
    "sg:province":"Hamburg",
    "wof:name":"Bsd-communication Center Gmbh",
    "wof:placetype":"venue"
},
  "geometry": {"coordinates":[10.025312,53.550243],"type":"Point"}
}