{
  "type": "Feature",
  "properties": {
    "iso:country":"DE",
    "sg:address":"Bremer Str. 7",
    "sg:city":"Laatzen",
    "sg:phone":"+49 5102/826",
    "sg:postcode":"30880",
    "sg:province":"Niedersachsen",
    "wof:name":"Friedrich-karl Hoffmann Kg",
    "wof:placetype":"venue"
},
  "geometry": {"coordinates":[9.8275566101,52.2917251587],"type":"Point"}
}