{
  "type": "Feature",
  "properties": {
    "iso:country":"DE",
    "sg:address":"Gutenbergstr. 24",
    "sg:city":"Giesen",
    "sg:phone":"+49 9973/9303",
    "sg:postcode":"31180",
    "sg:province":"Niedersachsen",
    "wof:name":"Sepp Hofer Gmbh",
    "wof:placetype":"venue"
},
  "geometry": {"coordinates":[12.8599128723,49.3086051941],"type":"Point"}
}