{
  "type": "Feature",
  "properties": {
    "iso:country":"DE",
    "sg:address":"Prinz-Ludwig-Str. 20",
    "sg:city":"Freising",
    "sg:phone":"+49 8161/92317",
    "sg:postcode":"85354",
    "sg:province":"Bayern",
    "wof:name":"R. Gottlieb",
    "wof:placetype":"venue"
},
  "geometry": {"coordinates":[11.740528,48.402637],"type":"Point"}
}