{
  "type": "Feature",
  "properties": {
    "iso:country":"DE",
    "sg:address":"Mohnstr. 29",
    "sg:city":"Neuss",
    "sg:phone":"+49 2131/463117",
    "sg:postcode":"41466",
    "sg:province":"Nordrhein-Westfalen",
    "wof:name":"Willi Kr\u00fcger",
    "wof:placetype":"venue"
},
  "geometry": {"coordinates":[6.691169,51.16925],"type":"Point"}
}