{
  "type": "Feature",
  "properties": {
    "iso:country":"DE",
    "sg:address":"Schlo\u00dfstr. 13",
    "sg:city":"Eutin",
    "sg:postcode":"23701",
    "sg:province":"Schleswig-Holstein",
    "wof:name":"Landeskirche Eutin Bibliothek",
    "wof:placetype":"venue"
},
  "geometry": {"coordinates":[10.617823,54.137611],"type":"Point"}
}