{
  "type": "Feature",
  "properties": {
    "iso:country":"DE",
    "sg:address":"Holderbuschweg 69",
    "sg:city":"Schwaigern-Massenbach",
    "sg:phone":"+49 7138/94090",
    "sg:postcode":"74193",
    "sg:province":"Baden-W\u00fcrttemberg",
    "wof:name":"Sks-thermoplast Inh. Volker Schuster",
    "wof:placetype":"venue"
},
  "geometry": {"coordinates":[9.06421,49.16399],"type":"Point"}
}