{
  "type": "Feature",
  "properties": {
    "iso:country":"DE",
    "sg:address":"Dorfstr. 27",
    "sg:city":"Sankt Peter-Ording",
    "sg:phone":"+49 4863/3030",
    "sg:postcode":"25826",
    "sg:province":"Schleswig-Holstein",
    "wof:name":"Wanlik-h\u00fcs Inh. O. Braun",
    "wof:placetype":"venue"
},
  "geometry": {"coordinates":[8.6393976212,54.3023834229],"type":"Point"}
}