{
  "type": "Feature",
  "properties": {
    "iso:country":"DE",
    "sg:address":"Goethestr. 9",
    "sg:city":"D\u00fcren",
    "sg:phone":"+49 2421/43035",
    "sg:postcode":"52349",
    "sg:province":"Nordrhein-Westfalen",
    "wof:name":"Dr. Wilhelm Kaiser Rechtsanwalt",
    "wof:placetype":"venue"
},
  "geometry": {"coordinates":[6.47651577,50.8003997803],"type":"Point"}
}