{
  "type": "Feature",
  "properties": {
    "iso:country":"DE",
    "sg:address":"Gr\u00fcner Weg 4",
    "sg:city":"St Katharinen",
    "sg:phone":"+49 2645/2371",
    "sg:postcode":"53562",
    "sg:province":"Rheinland-Pfalz",
    "wof:name":"U. Auer",
    "wof:placetype":"venue"
},
  "geometry": {"coordinates":[7.354062,50.561474],"type":"Point"}
}