{
  "type": "Feature",
  "properties": {
    "iso:country":"DE",
    "sg:address":"Zeppelinstr. 35",
    "sg:city":"Dingolfing",
    "sg:phone":"+49 8731/71465",
    "sg:postcode":"84130",
    "sg:province":"Bayern",
    "wof:name":"N. Riedmayr",
    "wof:placetype":"venue"
},
  "geometry": {"coordinates":[12.5000019073,48.6455345154],"type":"Point"}
}