{
  "type": "Feature",
  "properties": {
    "iso:country":"DE",
    "sg:address":"Hochstr. 45",
    "sg:city":"Hagen",
    "sg:phone":"+49 2331/10980",
    "sg:postcode":"58095",
    "sg:province":"Nordrhein-Westfalen",
    "wof:name":"Dr. Werner Rausch Steuerberater",
    "wof:placetype":"venue"
},
  "geometry": {"coordinates":[7.4763441086,51.3540992737],"type":"Point"}
}