{
  "type": "Feature",
  "properties": {
    "iso:country":"DE",
    "sg:address":"Im Hummerholz 36",
    "sg:city":"Leutenbach",
    "sg:phone":"+49 7195/3464",
    "sg:postcode":"71397",
    "sg:province":"Baden-W\u00fcrttemberg",
    "wof:name":"Bernd Loch",
    "wof:placetype":"venue"
},
  "geometry": {"coordinates":[9.3643217087,48.9002037048],"type":"Point"}
}