{
  "type": "Feature",
  "properties": {
    "iso:country":"DE",
    "sg:address":"Breitscheidstr. 55",
    "sg:city":"Dresden",
    "sg:phone":"+49 351/2015697",
    "sg:postcode":"01237",
    "sg:province":"Sachsen",
    "wof:name":"Meier",
    "wof:placetype":"venue"
},
  "geometry": {"coordinates":[13.811685,51.012875],"type":"Point"}
}