{
  "type": "Feature",
  "properties": {
    "iso:country":"DE",
    "sg:address":"Kalver Str. 20",
    "sg:city":"L\u00fcdenscheid",
    "sg:phone":"+49 2351/477300",
    "sg:postcode":"58515",
    "sg:province":"Nordrhein-Westfalen",
    "wof:name":"Europagrill",
    "wof:placetype":"venue"
},
  "geometry": {"coordinates":[7.6669039726,51.2114944458],"type":"Point"}
}