{
  "type": "Feature",
  "properties": {
    "iso:country":"DE",
    "sg:address":"Hauptstr. 61",
    "sg:city":"Ladenburg",
    "sg:phone":"+49 6203/181201",
    "sg:postcode":"68526",
    "sg:province":"Baden-W\u00fcrttemberg",
    "wof:name":"Backmulde",
    "wof:placetype":"venue"
},
  "geometry": {"coordinates":[8.6117677689,49.4726715088],"type":"Point"}
}