{
  "type": "Feature",
  "properties": {
    "iso:country":"DE",
    "sg:address":"Siebenmorgen 47",
    "sg:city":"Bergisch Gladbach",
    "sg:phone":"+49 2204/61485",
    "sg:postcode":"51427",
    "sg:province":"Nordrhein-Westfalen",
    "wof:name":"W. Nolte",
    "wof:placetype":"venue"
},
  "geometry": {"coordinates":[7.1146,50.958092],"type":"Point"}
}