{
  "type": "Feature",
  "properties": {
    "iso:country":"DE",
    "sg:address":"Moosacher Str. 80",
    "sg:city":"M\u00fcnchen",
    "sg:postcode":"80809",
    "sg:province":"Bayern",
    "wof:name":"Volmarsteiner Vertriebs- Gesellschaft F\u00fcr Automatische",
    "wof:placetype":"venue"
},
  "geometry": {"coordinates":[11.546500206,48.1862678528],"type":"Point"}
}