{
  "type": "Feature",
  "properties": {
    "iso:country":"DE",
    "sg:address":"Erich-Weinert-Str. 30",
    "sg:city":"Pretzschendorf",
    "sg:phone":"+49 35058/41908",
    "sg:postcode":"01774",
    "sg:province":"Sachsen",
    "wof:name":"Werner Leiteritz",
    "wof:placetype":"venue"
},
  "geometry": {"coordinates":[13.5219621658,50.8769607544],"type":"Point"}
}