{
  "type": "Feature",
  "properties": {
    "iso:country":"DE",
    "sg:address":"Rankestr. 56",
    "sg:city":"Dresden",
    "sg:phone":"+49 351/851130",
    "sg:postcode":"01139",
    "sg:province":"Sachsen",
    "wof:name":"Mineral\u00f6lhandel Heinrich Steinborn Kg",
    "wof:placetype":"venue"
},
  "geometry": {"coordinates":[13.69397,51.089844],"type":"Point"}
}