{
  "type": "Feature",
  "properties": {
    "iso:country":"DE",
    "sg:address":"Rosenauer Str. 30-32",
    "sg:city":"D\u00f6rfles-Esbach",
    "sg:postcode":"96487",
    "sg:province":"Bayern",
    "wof:name":"Reichenbacher Verwaltungs Gmbh & Co. Kg",
    "wof:placetype":"venue"
},
  "geometry": {"coordinates":[11.002833,50.287308],"type":"Point"}
}