{
  "type": "Feature",
  "properties": {
    "iso:country":"DE",
    "sg:address":"Sudetenstr. 2",
    "sg:city":"M\u00f6mlingen",
    "sg:phone":"+49 6022/30505",
    "sg:postcode":"63853",
    "sg:province":"Bayern",
    "wof:name":"Gunter Muth Rechtsanwalt",
    "wof:placetype":"venue"
},
  "geometry": {"coordinates":[9.0883264542,49.8518943787],"type":"Point"}
}