{
  "type": "Feature",
  "properties": {
    "iso:country":"DE",
    "sg:address":"Harburger Str. 27",
    "sg:city":"Soltau",
    "sg:phone":"+49 5191/2349",
    "sg:postcode":"29614",
    "sg:province":"Niedersachsen",
    "wof:name":"Gebr. Otte Zweigniederl. Der Schneider Mineral\u00f6l Gmbh & Co.",
    "wof:placetype":"venue"
},
  "geometry": {"coordinates":[9.8413181305,52.9867286682],"type":"Point"}
}