{
  "type": "Feature",
  "properties": {
    "iso:country":"DE",
    "sg:address":"Malteserstr. 12",
    "sg:city":"Bad Sobernheim",
    "sg:phone":"+49 6751/4870",
    "sg:postcode":"55566",
    "sg:province":"Rheinland-Pfalz",
    "wof:name":"Olaf Spahn Masseur",
    "wof:placetype":"venue"
},
  "geometry": {"coordinates":[7.651532,49.786598],"type":"Point"}
}