{
  "type": "Feature",
  "properties": {
    "iso:country":"DE",
    "sg:address":"Hermannstr. 3",
    "sg:city":"Herne",
    "sg:phone":"+49 2325/70568",
    "sg:postcode":"44649",
    "sg:province":"Nordrhein-Westfalen",
    "wof:name":"Beerdigungsinstitut Gebr. Quellmelz",
    "wof:placetype":"venue"
},
  "geometry": {"coordinates":[7.157325,51.534702],"type":"Point"}
}