{
  "type": "Feature",
  "properties": {
    "iso:country":"DE",
    "sg:address":"K\u00f6lner Str. 227",
    "sg:city":"Neunkirchen",
    "sg:phone":"+49 2735/2235",
    "sg:postcode":"57290",
    "sg:province":"Nordrhein-Westfalen",
    "wof:name":"F\u00fcnfsinn",
    "wof:placetype":"venue"
},
  "geometry": {"coordinates":[8.000556,50.790073],"type":"Point"}
}