{
  "type": "Feature",
  "properties": {
    "iso:country":"DE",
    "sg:address":"Lindenstr. 17",
    "sg:city":"Muggensturm",
    "sg:phone":"+49 7222/53795",
    "sg:postcode":"76461",
    "sg:province":"Baden-W\u00fcrttemberg",
    "wof:name":"Peter Morstadt",
    "wof:placetype":"venue"
},
  "geometry": {"coordinates":[8.27949,48.868656],"type":"Point"}
}