{
  "type": "Feature",
  "properties": {
    "iso:country":"DE",
    "sg:address":"S\u00e4ggasse 9",
    "sg:city":"Schaftlach",
    "sg:phone":"+49 8021/508910",
    "sg:postcode":"83666",
    "sg:province":"Bayern",
    "wof:name":"Home Suite",
    "wof:placetype":"venue"
},
  "geometry": {"coordinates":[11.683647,47.796406],"type":"Point"}
}