{
  "type": "Feature",
  "properties": {
    "iso:country":"DE",
    "sg:address":"Blausteinstr. 24",
    "sg:city":"Korschenbroich",
    "sg:phone":"+49 2182/4297",
    "sg:postcode":"41352",
    "sg:province":"Nordrhein-Westfalen",
    "wof:name":"Dieter Gums",
    "wof:placetype":"venue"
},
  "geometry": {"coordinates":[6.595516,51.166958],"type":"Point"}
}