{
  "type": "Feature",
  "properties": {
    "iso:country":"DE",
    "sg:address":"Grandkaule 8-10",
    "sg:city":"Niederkassel",
    "sg:phone":"+49 4922/0894550",
    "sg:postcode":"53859",
    "sg:province":"Nordrhein-Westfalen",
    "wof:name":"Gelbau Gmbh & Co. Kg",
    "wof:placetype":"venue"
},
  "geometry": {"coordinates":[7.026331,50.831165],"type":"Point"}
}