{
  "type": "Feature",
  "properties": {
    "iso:country":"DE",
    "sg:address":"Vogelsbergerstr. 30a",
    "sg:city":"Altenstadt",
    "sg:phone":"+49 6047/952660",
    "sg:postcode":"63674",
    "sg:province":"Hessen",
    "wof:name":"Abekra-verband",
    "wof:placetype":"venue"
},
  "geometry": {"coordinates":[8.946263,50.286148],"type":"Point"}
}