{
  "type": "Feature",
  "properties": {
    "iso:country":"DE",
    "sg:address":"Wasserweg 2",
    "sg:city":"Veltheim",
    "sg:phone":"+49 5305/416",
    "sg:postcode":"38173",
    "sg:province":"Niedersachsen",
    "wof:name":"Kath. Pfarramt Heilig Kreuz",
    "wof:placetype":"venue"
},
  "geometry": {"coordinates":[10.6876621246,52.2174110413],"type":"Point"}
}