{
  "type": "Feature",
  "properties": {
    "iso:country":"DE",
    "sg:address":"Alte Volksparkstr. 14 a",
    "sg:city":"Hamburg",
    "sg:phone":"+49 40/54768900",
    "sg:postcode":"22525",
    "sg:province":"Hamburg",
    "wof:name":"Matthias Von Corvin E. K.",
    "wof:placetype":"venue"
},
  "geometry": {"coordinates":[9.926286,53.592648],"type":"Point"}
}