{
  "type": "Feature",
  "properties": {
    "iso:country":"DE",
    "sg:address":"Dorfstr. 62",
    "sg:city":"Tangstedt",
    "sg:phone":"+49 4101/591039",
    "sg:postcode":"25499",
    "sg:province":"Schleswig-Holstein",
    "wof:name":"Reinecke & Co.",
    "wof:placetype":"venue"
},
  "geometry": {"coordinates":[9.841721,53.675037],"type":"Point"}
}