{
  "type": "Feature",
  "properties": {
    "iso:country":"DE",
    "sg:address":"Martinstr. 9",
    "sg:city":"Ensch",
    "sg:phone":"+49 6507/3491",
    "sg:postcode":"54340",
    "sg:province":"Rheinland-Pfalz",
    "wof:name":"Hotel Breidbach",
    "wof:placetype":"venue"
},
  "geometry": {"coordinates":[6.833835125,49.8253440857],"type":"Point"}
}