{
  "type": "Feature",
  "properties": {
    "iso:country":"DE",
    "sg:address":"Obere Hardt 3",
    "sg:city":"Bietigheim",
    "sg:phone":"+49 7245/4055",
    "sg:postcode":"76467",
    "sg:province":"Baden-W\u00fcrttemberg",
    "wof:name":"M\u00f6bel Creativ",
    "wof:placetype":"venue"
},
  "geometry": {"coordinates":[8.267061,48.889965],"type":"Point"}
}