{
  "type": "Feature",
  "properties": {
    "iso:country":"DE",
    "sg:address":"Klosterweg 1",
    "sg:city":"Grevenbroich",
    "sg:phone":"+49 2181/27020",
    "sg:postcode":"41516",
    "sg:province":"Nordrhein-Westfalen",
    "wof:name":"Lebenshilfe F\u00fcr Geistig Behinderte",
    "wof:placetype":"venue"
},
  "geometry": {"coordinates":[6.618715,51.113266],"type":"Point"}
}