{
  "type": "Feature",
  "properties": {
    "iso:country":"DE",
    "sg:address":"Hirschstr. 13",
    "sg:city":"Geislingen",
    "sg:phone":"+49 7433/8734",
    "sg:postcode":"72351",
    "sg:province":"Baden-W\u00fcrttemberg",
    "wof:name":"Roland Joos",
    "wof:placetype":"venue"
},
  "geometry": {"coordinates":[8.807933,48.286587],"type":"Point"}
}