{
  "type": "Feature",
  "properties": {
    "iso:country":"DE",
    "sg:address":"Remscheider Str. 150-160",
    "sg:city":"Remscheid",
    "sg:phone":"+49 4921/9193970",
    "sg:postcode":"42899",
    "sg:province":"Nordrhein-Westfalen",
    "wof:name":"Remscheider Walz- U. Hammerwerke B\u00d6llinghaus & Co",
    "wof:placetype":"venue"
},
  "geometry": {"coordinates":[7.218627,51.199242],"type":"Point"}
}