{
  "type": "Feature",
  "properties": {
    "iso:country":"DE",
    "sg:address":"Stra\u00dfe der Einheit 23 b",
    "sg:city":"Gleina",
    "sg:phone":"+49 34462/21482",
    "sg:postcode":"06632",
    "sg:province":"Sachsen-Anhalt",
    "wof:name":"Mona Lisa",
    "wof:placetype":"venue"
},
  "geometry": {"coordinates":[11.720939,51.259235],"type":"Point"}
}