{
  "type": "Feature",
  "properties": {
    "iso:country":"DE",
    "sg:address":"Hospitalstr. 42",
    "sg:city":"Biedenkopf",
    "sg:phone":"+49 6461/2143",
    "sg:postcode":"35216",
    "sg:province":"Hessen",
    "wof:name":"Franz Buchberger",
    "wof:placetype":"venue"
},
  "geometry": {"coordinates":[8.5317630768,50.9090003967],"type":"Point"}
}