{
  "type": "Feature",
  "properties": {
    "iso:country":"DE",
    "sg:address":"Waisenhausstr. 33",
    "sg:city":"M\u00f6nchengladbach",
    "sg:phone":"+49 2166/42696",
    "sg:postcode":"41236",
    "sg:province":"Nordrhein-Westfalen",
    "wof:name":"Karl D\u00fcrselen",
    "wof:placetype":"venue"
},
  "geometry": {"coordinates":[6.4448518753,51.1648216248],"type":"Point"}
}