{
  "type": "Feature",
  "properties": {
    "iso:country":"DE",
    "sg:address":"Kirchstr. 16",
    "sg:city":"Wustrow",
    "sg:phone":"+49 5843/250",
    "sg:postcode":"29462",
    "sg:province":"Niedersachsen",
    "wof:name":"Friedel Plette",
    "wof:placetype":"venue"
},
  "geometry": {"coordinates":[11.118439,52.924614],"type":"Point"}
}