{
  "type": "Feature",
  "properties": {
    "iso:country":"DE",
    "sg:address":"Schillerstr. 14",
    "sg:city":"Welzheim",
    "sg:phone":"+49 7182/7297",
    "sg:postcode":"73642",
    "sg:province":"Baden-W\u00fcrttemberg",
    "wof:name":"Gerhard Munz Und Greiner",
    "wof:placetype":"venue"
},
  "geometry": {"coordinates":[9.6340646744,48.8781433105],"type":"Point"}
}