{
  "type": "Feature",
  "properties": {
    "iso:country":"DE",
    "sg:address":"Seehalde 41",
    "sg:city":"Winnenden",
    "sg:phone":"+49 7195/8404",
    "sg:postcode":"71364",
    "sg:province":"Baden-W\u00fcrttemberg",
    "wof:name":"Gerd Wesp",
    "wof:placetype":"venue"
},
  "geometry": {"coordinates":[9.404736,48.877396],"type":"Point"}
}