{
  "type": "Feature",
  "properties": {
    "iso:country":"DE",
    "sg:address":"L\u00f6rracher Str. 5a",
    "sg:city":"Freiburg",
    "sg:postcode":"79115",
    "sg:province":"Baden-W\u00fcrttemberg",
    "wof:name":"Freinet Ges. F\u00fcr Informations- Dienste Mbh",
    "wof:placetype":"venue"
},
  "geometry": {"coordinates":[7.8277301788,47.9843177795],"type":"Point"}
}