{
  "type": "Feature",
  "properties": {
    "iso:country":"DE",
    "sg:address":"Ludwig-Schwamb-Str. 19",
    "sg:city":"Osthofen",
    "sg:phone":"+49 6242/3374",
    "sg:postcode":"67574",
    "sg:province":"Rheinland-Pfalz",
    "wof:name":"E. Miklitz",
    "wof:placetype":"venue"
},
  "geometry": {"coordinates":[8.3215169907,49.7054901123],"type":"Point"}
}