{
  "type": "Feature",
  "properties": {
    "iso:country":"DE",
    "sg:address":"Schachter Str. 15-16",
    "sg:city":"Calden",
    "sg:phone":"+49 5674/70010",
    "sg:postcode":"34379",
    "sg:province":"Hessen",
    "wof:name":"Landkost-konserven Reinhold Klemme Kg",
    "wof:placetype":"venue"
},
  "geometry": {"coordinates":[9.3990411758,51.4121704102],"type":"Point"}
}