{
  "type": "Feature",
  "properties": {
    "iso:country":"DE",
    "sg:address":"Flotowstr. 20",
    "sg:city":"Hamburg",
    "sg:phone":"+49 40/2298779",
    "sg:postcode":"22083",
    "sg:province":"Hamburg",
    "wof:name":"H. Berg",
    "wof:placetype":"venue"
},
  "geometry": {"coordinates":[10.0267677307,53.5793380737],"type":"Point"}
}