{
  "type": "Feature",
  "properties": {
    "iso:country":"DE",
    "sg:address":"Mainstr 85",
    "sg:city":"Neuss",
    "sg:phone":"+49 2137/12340",
    "sg:postcode":"41469",
    "sg:province":"Nordrhein-Westfalen",
    "wof:name":"Yame Metallbearbeitung Gmbh",
    "wof:placetype":"venue"
},
  "geometry": {"coordinates":[6.744884,51.151394],"type":"Point"}
}