{
  "type": "Feature",
  "properties": {
    "iso:country":"DE",
    "sg:address":"Adlerstr. 30",
    "sg:city":"Geislingen",
    "sg:phone":"+49 7331/40445",
    "sg:postcode":"73312",
    "sg:province":"Baden-W\u00fcrttemberg",
    "wof:name":"G. Bifano",
    "wof:placetype":"venue"
},
  "geometry": {"coordinates":[9.8437242508,48.6114807129],"type":"Point"}
}