{
  "type": "Feature",
  "properties": {
    "iso:country":"DE",
    "sg:address":"Sebaldstr. 5",
    "sg:city":"Schw\u00e4bisch Gm\u00fcnd",
    "sg:phone":"+49 7171/939344",
    "sg:postcode":"73525",
    "sg:province":"Baden-W\u00fcrttemberg",
    "wof:name":"Laser Kosmetik Point Gmbh",
    "wof:placetype":"venue"
},
  "geometry": {"coordinates":[9.798235,48.797318],"type":"Point"}
}