{
  "type": "Feature",
  "properties": {
    "iso:country":"DE",
    "sg:address":"Parallelstr. 8-10",
    "sg:city":"Remscheid",
    "sg:phone":"+49 2191/385691",
    "sg:postcode":"42857",
    "sg:province":"Nordrhein-Westfalen",
    "wof:name":"Dr. Med. Helmut Fuchs",
    "wof:placetype":"venue"
},
  "geometry": {"coordinates":[7.187584877,51.1751441956],"type":"Point"}
}