{
  "type": "Feature",
  "properties": {
    "iso:country":"DE",
    "sg:address":"Unterer Markt 5",
    "sg:city":"Breitenbrunn",
    "sg:phone":"+49 9495/272",
    "sg:postcode":"92363",
    "sg:province":"Bayern",
    "wof:name":"G. Weigl",
    "wof:placetype":"venue"
},
  "geometry": {"coordinates":[11.6206264496,49.0822105408],"type":"Point"}
}