{
  "type": "Feature",
  "properties": {
    "iso:country":"DE",
    "sg:address":"Hauptstr. 27",
    "sg:city":"Hessisch Lichtenau",
    "sg:phone":"+49 5602/1220",
    "sg:postcode":"37235",
    "sg:province":"Hessen",
    "wof:name":"Ernst D\u00f6ring",
    "wof:placetype":"venue"
},
  "geometry": {"coordinates":[9.74114,51.15443],"type":"Point"}
}