{
  "type": "Feature",
  "properties": {
    "iso:country":"DE",
    "sg:address":"Molanusweg 1",
    "sg:city":"Hannover",
    "sg:phone":"+49 511/525976",
    "sg:postcode":"30559",
    "sg:province":"Niedersachsen",
    "wof:name":"Erika Kiep-busche Innenarchitektin",
    "wof:placetype":"venue"
},
  "geometry": {"coordinates":[9.820732,52.359138],"type":"Point"}
}