{
  "type": "Feature",
  "properties": {
    "iso:country":"DE",
    "sg:address":"Ringstr. 3",
    "sg:city":"Beckdorf",
    "sg:phone":"+49 4167/890",
    "sg:postcode":"21643",
    "sg:province":"Niedersachsen",
    "wof:name":"Johann Bowe",
    "wof:placetype":"venue"
},
  "geometry": {"coordinates":[9.6276311874,53.4046897888],"type":"Point"}
}