{
  "type": "Feature",
  "properties": {
    "iso:country":"DE",
    "sg:address":"Lornsenstr. 24",
    "sg:city":"Rendsburg",
    "sg:phone":"+49 4331/72430",
    "sg:postcode":"24768",
    "sg:province":"Schleswig-Holstein",
    "wof:name":"J\u00f6rg Boyens",
    "wof:placetype":"venue"
},
  "geometry": {"coordinates":[9.65503,54.309761],"type":"Point"}
}