{
  "type": "Feature",
  "properties": {
    "iso:country":"DE",
    "sg:address":"Hauptstr. 16",
    "sg:city":"Neuburg",
    "sg:phone":"+49 7273/1360",
    "sg:postcode":"76776",
    "sg:province":"Rheinland-Pfalz",
    "wof:name":"Gasthaus Zur Sonne Gmbh",
    "wof:placetype":"venue"
},
  "geometry": {"coordinates":[11.589012146,53.945438385],"type":"Point"}
}