{
  "type": "Feature",
  "properties": {
    "iso:country":"DE",
    "sg:address":"Im Flecken 59",
    "sg:city":"Geisenheim",
    "sg:phone":"+49 6722/996888",
    "sg:postcode":"65366",
    "sg:province":"Hessen",
    "wof:name":"Elektro Kreis Gmbh",
    "wof:placetype":"venue"
},
  "geometry": {"coordinates":[7.978249,50.004257],"type":"Point"}
}