{
  "type": "Feature",
  "properties": {
    "iso:country":"DE",
    "sg:address":"Radeberger Str. 12",
    "sg:city":"Dresden",
    "sg:phone":"+49 351/816000",
    "sg:postcode":"01099",
    "sg:province":"Sachsen",
    "wof:name":"Brandt Partnerschaft Rechtsanw\u00e4lte",
    "wof:placetype":"venue"
},
  "geometry": {"coordinates":[13.7673816681,51.0663223267],"type":"Point"}
}