{
  "type": "Feature",
  "properties": {
    "iso:country":"DE",
    "sg:address":"Schwarzschildstr. 8",
    "sg:city":"Berlin",
    "sg:phone":"+49 4930/670536",
    "sg:postcode":"12489",
    "sg:province":"Berlin",
    "wof:name":"Laser Medizintechnologie Gmbh Berlin",
    "wof:placetype":"venue"
},
  "geometry": {"coordinates":[13.523554,52.430065],"type":"Point"}
}