{
  "type": "Feature",
  "properties": {
    "iso:country":"DE",
    "sg:address":"Molkereistr. 9",
    "sg:city":"Esens",
    "sg:phone":"+49 4971/1636",
    "sg:postcode":"26427",
    "sg:province":"Niedersachsen",
    "wof:name":"Ubben Ihnken Und Ufken Architekten",
    "wof:placetype":"venue"
},
  "geometry": {"coordinates":[7.610736,53.64489],"type":"Point"}
}