{
  "type": "Feature",
  "properties": {
    "iso:country":"DE",
    "sg:address":"Marktweg 6",
    "sg:city":"Pfronstetten",
    "sg:phone":"+49 7388/282",
    "sg:postcode":"72539",
    "sg:province":"Baden-W\u00fcrttemberg",
    "wof:name":"Egon Buck",
    "wof:placetype":"venue"
},
  "geometry": {"coordinates":[9.389929,48.272446],"type":"Point"}
}