{
  "type": "Feature",
  "properties": {
    "iso:country":"DE",
    "sg:address":"Eichigweg 5",
    "sg:city":"Neunkirchen",
    "sg:phone":"+49 9153/7253",
    "sg:postcode":"91233",
    "sg:province":"Bayern",
    "wof:name":"Kost-kamm",
    "wof:placetype":"venue"
},
  "geometry": {"coordinates":[11.34471,49.545975],"type":"Point"}
}