{
  "type": "Feature",
  "properties": {
    "iso:country":"DE",
    "sg:address":"Lindenplatz 9",
    "sg:city":"Schongau",
    "sg:phone":"+49 8861/7245",
    "sg:postcode":"86956",
    "sg:province":"Bayern",
    "wof:name":"Josef Biber",
    "wof:placetype":"venue"
},
  "geometry": {"coordinates":[10.897366,47.810375],"type":"Point"}
}