{
  "type": "Feature",
  "properties": {
    "iso:country":"DE",
    "sg:address":"Gartenweg 30",
    "sg:city":"Sierksdorf",
    "sg:phone":"+49 4563/47770",
    "sg:postcode":"23730",
    "sg:province":"Schleswig-Holstein",
    "wof:name":"Joachim Kallmorgen Kg",
    "wof:placetype":"venue"
},
  "geometry": {"coordinates":[10.7714176178,54.0657730103],"type":"Point"}
}