{
  "type": "Feature",
  "properties": {
    "iso:country":"DE",
    "sg:address":"Gymnasiumstr. 34",
    "sg:city":"Heilbronn",
    "sg:phone":"+49 7131/85010",
    "sg:postcode":"74072",
    "sg:province":"Baden-W\u00fcrttemberg",
    "wof:name":"Psycho-soziale Beratungs-u. Ambulante Behandlungsstelle",
    "wof:placetype":"venue"
},
  "geometry": {"coordinates":[9.223447,49.139668],"type":"Point"}
}