{
  "type": "Feature",
  "properties": {
    "iso:country":"DE",
    "sg:address":"Siemensstr 23",
    "sg:city":"Hiddenhausen",
    "sg:phone":"+49 5223/491140",
    "sg:postcode":"32120",
    "sg:province":"Nordrhein-Westfalen",
    "wof:name":"Wildf\u00f6rster Formteile Gmbh",
    "wof:placetype":"venue"
},
  "geometry": {"coordinates":[8.598906,52.169094],"type":"Point"}
}