{
  "type": "Feature",
  "properties": {
    "iso:country":"DE",
    "sg:address":"Bachstr. 4",
    "sg:city":"Wachtberg",
    "sg:phone":"+49 2225/6196",
    "sg:postcode":"53343",
    "sg:province":"Nordrhein-Westfalen",
    "wof:name":"Johanne Merzenich",
    "wof:placetype":"venue"
},
  "geometry": {"coordinates":[7.0623831749,50.6124420166],"type":"Point"}
}