{
  "type": "Feature",
  "properties": {
    "iso:country":"DE",
    "sg:address":"Karlsplatz 3",
    "sg:city":"Schorndorf",
    "sg:phone":"+49 7181/62527",
    "sg:postcode":"73614",
    "sg:province":"Baden-W\u00fcrttemberg",
    "wof:name":"Moser",
    "wof:placetype":"venue"
},
  "geometry": {"coordinates":[9.527003,48.806805],"type":"Point"}
}