{
  "type": "Feature",
  "properties": {
    "iso:country":"DE",
    "sg:address":"Am Sommerbad 22",
    "sg:city":"Gera",
    "sg:phone":"+49 4936/5855940",
    "sg:postcode":"07548",
    "sg:province":"Th\u00fcringen",
    "wof:name":"Gwg Elektro Gmbh",
    "wof:placetype":"venue"
},
  "geometry": {"coordinates":[12.073221,50.873383],"type":"Point"}
}