{
  "type": "Feature",
  "properties": {
    "iso:country":"DE",
    "sg:address":"Ostende 18",
    "sg:city":"Brockel",
    "sg:phone":"+49 4266/954550",
    "sg:postcode":"27386",
    "sg:province":"Niedersachsen",
    "wof:name":"Bernd Tewes",
    "wof:placetype":"venue"
},
  "geometry": {"coordinates":[9.527602,53.089817],"type":"Point"}
}