{
  "type": "Feature",
  "properties": {
    "iso:country":"DE",
    "sg:address":"Friedenheimer Str. 121 a",
    "sg:city":"M\u00fcnchen",
    "sg:phone":"+49 89/57969003",
    "sg:postcode":"80686",
    "sg:province":"Bayern",
    "wof:name":"Leben Daheim",
    "wof:placetype":"venue"
},
  "geometry": {"coordinates":[11.508977,48.132183],"type":"Point"}
}