{
  "type": "Feature",
  "properties": {
    "iso:country":"DE",
    "sg:city":"Soest",
    "sg:phone":"+49 2921/12180",
    "sg:postcode":"59494",
    "sg:province":"Nordrhein-Westfalen",
    "wof:name":"Famila-passage",
    "wof:placetype":"venue"
},
  "geometry": {"coordinates":[8.108315,51.572514],"type":"Point"}
}