{
  "type": "Feature",
  "properties": {
    "iso:country":"DE",
    "sg:address":"Dr.-Beuermann-Str. 9",
    "sg:city":"Eschwege",
    "sg:phone":"+49 5651/6639",
    "sg:postcode":"37269",
    "sg:province":"Hessen",
    "wof:name":"Hessberger Gmbh & Co. Bekleidungs Kg",
    "wof:placetype":"venue"
},
  "geometry": {"coordinates":[10.0530548096,51.1869239807],"type":"Point"}
}