{
  "type": "Feature",
  "properties": {
    "iso:country":"DE",
    "sg:address":"Karlstr. 65",
    "sg:city":"B\u00f6nnigheim",
    "sg:phone":"+49 7143/23094",
    "sg:postcode":"74357",
    "sg:province":"Baden-W\u00fcrttemberg",
    "wof:name":"Wilhelm Wachter Maschinen-werkzeuge",
    "wof:placetype":"venue"
},
  "geometry": {"coordinates":[9.088375,49.042492],"type":"Point"}
}