{
  "type": "Feature",
  "properties": {
    "iso:country":"DE",
    "sg:address":"Uetzer Str. 17",
    "sg:city":"Burgdorf",
    "sg:phone":"+49 5136/83366",
    "sg:postcode":"31303",
    "sg:province":"Niedersachsen",
    "wof:name":"Shell-tankstelle",
    "wof:placetype":"venue"
},
  "geometry": {"coordinates":[10.015838623,52.444278717],"type":"Point"}
}