{
  "type": "Feature",
  "properties": {
    "iso:country":"DE",
    "sg:address":"G\u00f6rlitzer Str. 4",
    "sg:city":"M\u00fcnster",
    "sg:phone":"+49 251/248613",
    "sg:postcode":"48157",
    "sg:province":"Nordrhein-Westfalen",
    "wof:name":"Eva Maria Bracht",
    "wof:placetype":"venue"
},
  "geometry": {"coordinates":[7.640493,51.990906],"type":"Point"}
}