{
  "type": "Feature",
  "properties": {
    "iso:country":"DE",
    "sg:address":"Richard-Wagner-Str. 53",
    "sg:city":"Halle",
    "sg:phone":"+49 345/5233773",
    "sg:postcode":"06114",
    "sg:province":"Sachsen-Anhalt",
    "wof:name":"Lutz Moser",
    "wof:placetype":"venue"
},
  "geometry": {"coordinates":[11.9647655487,51.4964752197],"type":"Point"}
}