{
  "type": "Feature",
  "properties": {
    "iso:country":"DE",
    "sg:address":"Moltkestr. 9",
    "sg:city":"T\u00fcbingen",
    "sg:phone":"+49 7071/74250",
    "sg:postcode":"72072",
    "sg:province":"Baden-W\u00fcrttemberg",
    "wof:name":"Wolff Gmbh",
    "wof:placetype":"venue"
},
  "geometry": {"coordinates":[9.055936,48.511936],"type":"Point"}
}