{
  "type": "Feature",
  "properties": {
    "iso:country":"DE",
    "sg:address":"Eichenweg 4",
    "sg:city":"Fischach",
    "sg:phone":"+49 8236/96040",
    "sg:postcode":"86850",
    "sg:province":"Bayern",
    "wof:name":"Georg Fischer Steuerberater",
    "wof:placetype":"venue"
},
  "geometry": {"coordinates":[10.6605434418,48.2899856567],"type":"Point"}
}