{
  "type": "Feature",
  "properties": {
    "iso:country":"DE",
    "sg:address":"S\u00f6ltener Landweg 150",
    "sg:city":"Dorsten",
    "sg:phone":"+49 2362/94151",
    "sg:postcode":"46286",
    "sg:province":"Nordrhein-Westfalen",
    "wof:name":"Annegret T\u00fcshaus",
    "wof:placetype":"venue"
},
  "geometry": {"coordinates":[6.9648561478,51.6951522827],"type":"Point"}
}