{
  "type": "Feature",
  "properties": {
    "iso:country":"DE",
    "sg:address":"Karlsbader Str. 32",
    "sg:city":"Steinberg",
    "sg:phone":"+49 37462/3514",
    "sg:postcode":"08237",
    "sg:province":"Sachsen",
    "wof:name":"Heinz Unger",
    "wof:placetype":"venue"
},
  "geometry": {"coordinates":[12.507644,50.536034],"type":"Point"}
}