{
  "type": "Feature",
  "properties": {
    "iso:country":"DE",
    "sg:address":"Lauerweg 28",
    "sg:city":"B\u00f6nnigheim",
    "sg:phone":"+49 7143/21174",
    "sg:postcode":"74357",
    "sg:province":"Baden-W\u00fcrttemberg",
    "wof:name":"P. K\u00e4hler Steuerberater",
    "wof:placetype":"venue"
},
  "geometry": {"coordinates":[9.0872793198,49.0437355042],"type":"Point"}
}