{
  "type": "Feature",
  "properties": {
    "iso:country":"DE",
    "sg:address":"Lindauer Str. 3",
    "sg:city":"Wangen",
    "sg:phone":"+49 7522/20354",
    "sg:postcode":"88239",
    "sg:province":"Baden-W\u00fcrttemberg",
    "wof:name":"Werner Sohler Gmbh",
    "wof:placetype":"venue"
},
  "geometry": {"coordinates":[9.8317604065,47.6854019165],"type":"Point"}
}