{
  "type": "Feature",
  "properties": {
    "iso:country":"DE",
    "sg:address":"Grevenkamp 82",
    "sg:city":"Herzebrock-Clarholz",
    "sg:phone":"+49 5245/2829",
    "sg:postcode":"33442",
    "sg:province":"Nordrhein-Westfalen",
    "wof:name":"B. F\u00fcchtenhans Elektroinstallation",
    "wof:placetype":"venue"
},
  "geometry": {"coordinates":[8.231718,51.888279],"type":"Point"}
}