{
  "type": "Feature",
  "properties": {
    "iso:country":"DE",
    "sg:address":"Piesberger Str. 70",
    "sg:city":"Osnabr\u00fcck",
    "sg:phone":"+49 541/123767",
    "sg:postcode":"49090",
    "sg:province":"Niedersachsen",
    "wof:name":"R. Brinkmann",
    "wof:placetype":"venue"
},
  "geometry": {"coordinates":[8.0131864548,52.2998275757],"type":"Point"}
}