{
  "type": "Feature",
  "properties": {
    "iso:country":"DE",
    "sg:address":"Saydaer Str. 13",
    "sg:city":"Chemnitz",
    "sg:postcode":"09125",
    "sg:province":"Sachsen",
    "wof:name":"Super Heat Gmbh",
    "wof:placetype":"venue"
},
  "geometry": {"coordinates":[12.9301099777,50.7989311218],"type":"Point"}
}