{
  "type": "Feature",
  "properties": {
    "iso:country":"DE",
    "sg:address":"Zum Th\u00fcl 6",
    "sg:city":"Lengerich",
    "sg:phone":"+49 5904/337",
    "sg:postcode":"49838",
    "sg:province":"Niedersachsen",
    "wof:name":"Franz Schonhoff",
    "wof:placetype":"venue"
},
  "geometry": {"coordinates":[7.53079,52.5634],"type":"Point"}
}