{
  "type": "Feature",
  "properties": {
    "iso:country":"DE",
    "sg:address":"Lillengasse 42",
    "sg:city":"Schifferstadt",
    "sg:phone":"+49 6235/2810",
    "sg:postcode":"67105",
    "sg:province":"Rheinland-Pfalz",
    "wof:name":"Ottmar Huber Steuerbevollm\u00e4chtigter",
    "wof:placetype":"venue"
},
  "geometry": {"coordinates":[8.3805103302,49.3818092346],"type":"Point"}
}