{
  "type": "Feature",
  "properties": {
    "iso:country":"DE",
    "sg:address":"Hauptstr. 132",
    "sg:city":"Frechen",
    "sg:phone":"+49 2234/16474",
    "sg:postcode":"50226",
    "sg:province":"Nordrhein-Westfalen",
    "wof:name":"C. Thonhauser",
    "wof:placetype":"venue"
},
  "geometry": {"coordinates":[6.8064050674,50.9093399048],"type":"Point"}
}