{
  "type": "Feature",
  "properties": {
    "iso:country":"DE",
    "sg:address":"Ostcharweg 41",
    "sg:city":"Recklinghausen",
    "sg:phone":"+49 2361/42213",
    "sg:postcode":"45665",
    "sg:province":"Nordrhein-Westfalen",
    "wof:name":"Johann Vortmann",
    "wof:placetype":"venue"
},
  "geometry": {"coordinates":[7.227058,51.626163],"type":"Point"}
}