{
  "type": "Feature",
  "properties": {
    "iso:country":"DE",
    "sg:address":"Lillengasse 11",
    "sg:city":"Schifferstadt",
    "sg:phone":"+49 6235/81495",
    "sg:postcode":"67105",
    "sg:province":"Rheinland-Pfalz",
    "wof:name":"Hoock & Schwind Wohnbau Gmbh",
    "wof:placetype":"venue"
},
  "geometry": {"coordinates":[8.3768081665,49.3845748901],"type":"Point"}
}