{
  "type": "Feature",
  "properties": {
    "iso:country":"DE",
    "sg:address":"Ulzburger Str. 593",
    "sg:city":"Norderstedt",
    "sg:phone":"+49 40/5225492",
    "sg:postcode":"22844",
    "sg:province":"Schleswig-Holstein",
    "wof:name":"China Restaurant Peking",
    "wof:placetype":"venue"
},
  "geometry": {"coordinates":[9.996380806,53.7332000732],"type":"Point"}
}