{
  "type": "Feature",
  "properties": {
    "iso:country":"DE",
    "sg:address":"Friedrich-Ebert-Platz 2a",
    "sg:city":"V\u00f6lklingen",
    "sg:phone":"+49 6898/400495",
    "sg:postcode":"66333",
    "sg:province":"Saarland",
    "wof:name":"Dieter Manville Rechtsanwalt",
    "wof:placetype":"venue"
},
  "geometry": {"coordinates":[6.8085451126,49.2217140198],"type":"Point"}
}