{
  "type": "Feature",
  "properties": {
    "iso:country":"DE",
    "sg:address":"D\u00fcmmlinghauser Str. 11",
    "sg:city":"Gummersbach",
    "sg:phone":"+49 2261/52499",
    "sg:postcode":"51647",
    "sg:province":"Nordrhein-Westfalen",
    "wof:name":"M. Dittmann",
    "wof:placetype":"venue"
},
  "geometry": {"coordinates":[7.606012,51.024513],"type":"Point"}
}