{
  "type": "Feature",
  "properties": {
    "iso:country":"DE",
    "sg:address":"Friedrich-Naumann-Str. 18",
    "sg:city":"Reutlingen",
    "sg:phone":"+49 7121/270982",
    "sg:postcode":"72762",
    "sg:province":"Baden-W\u00fcrttemberg",
    "wof:name":"Biener Gmbh",
    "wof:placetype":"venue"
},
  "geometry": {"coordinates":[9.190320015,48.4880027771],"type":"Point"}
}