{
  "type": "Feature",
  "properties": {
    "iso:country":"DE",
    "sg:address":"Horster Str. 154",
    "sg:city":"Gelsenkirchen",
    "sg:phone":"+49 209/592019",
    "sg:postcode":"45897",
    "sg:province":"Nordrhein-Westfalen",
    "wof:name":"G. Und E. Taormina",
    "wof:placetype":"venue"
},
  "geometry": {"coordinates":[7.0462708473,51.5675201416],"type":"Point"}
}