{
  "type": "Feature",
  "properties": {
    "iso:country":"DE",
    "sg:address":"Bergkammstr. 13",
    "sg:city":"Hannover",
    "sg:phone":"+49 511/482013",
    "sg:postcode":"30453",
    "sg:province":"Niedersachsen",
    "wof:name":"E. Hornung",
    "wof:placetype":"venue"
},
  "geometry": {"coordinates":[9.6640701294,52.3745193481],"type":"Point"}
}