{
  "type": "Feature",
  "properties": {
    "iso:country":"DE",
    "sg:address":"Hochstr. 32",
    "sg:city":"Kruft",
    "sg:phone":"+49 2652/8090",
    "sg:postcode":"56642",
    "sg:province":"Rheinland-Pfalz",
    "wof:name":"Raiffeisen-warenges. Pellenz Mbh",
    "wof:placetype":"venue"
},
  "geometry": {"coordinates":[7.338186,50.384212],"type":"Point"}
}