{
  "type": "Feature",
  "properties": {
    "iso:country":"DE",
    "sg:address":"Holzhauser Str. 177",
    "sg:city":"Berlin",
    "sg:phone":"+49 30/4360060",
    "sg:postcode":"13509",
    "sg:province":"Berlin",
    "wof:name":"Microlog Solutions Gmbh",
    "wof:placetype":"venue"
},
  "geometry": {"coordinates":[13.3183698654,52.5876541138],"type":"Point"}
}