{
  "type": "Feature",
  "properties": {
    "iso:country":"DE",
    "sg:address":"Am Zubringer 1",
    "sg:city":"Bad Salzuflen",
    "sg:phone":"+49 5222/59689",
    "sg:postcode":"32107",
    "sg:province":"Nordrhein-Westfalen",
    "wof:name":"R. Nitsch",
    "wof:placetype":"venue"
},
  "geometry": {"coordinates":[8.714315,52.084064],"type":"Point"}
}