{
  "type": "Feature",
  "properties": {
    "iso:country":"DE",
    "sg:address":"Preysingstr. 22",
    "sg:city":"M\u00fcnchen",
    "sg:phone":"+49 89/4890220",
    "sg:postcode":"81667",
    "sg:province":"Bayern",
    "wof:name":"Daniela Giller Geb. Wagner Photographers Gmbh",
    "wof:placetype":"venue"
},
  "geometry": {"coordinates":[11.5948953629,48.1320762634],"type":"Point"}
}