{
  "type": "Feature",
  "properties": {
    "iso:country":"DE",
    "sg:address":"Johann-Lange-Str. 25",
    "sg:city":"Bremen",
    "sg:phone":"+49 421/666769",
    "sg:postcode":"28757",
    "sg:province":"Bremen",
    "wof:name":"Auto-schilder Vegesack Gmbh",
    "wof:placetype":"venue"
},
  "geometry": {"coordinates":[8.6280794144,53.1767501831],"type":"Point"}
}