{
  "type": "Feature",
  "properties": {
    "iso:country":"DE",
    "sg:address":"Helene-Mayer-Ring 14",
    "sg:city":"M\u00fcnchen",
    "sg:phone":"+49 89/3516488",
    "sg:postcode":"80809",
    "sg:province":"Bayern",
    "wof:name":"Christel Breunig Steuerberaterin",
    "wof:placetype":"venue"
},
  "geometry": {"coordinates":[11.5530061722,48.1824455261],"type":"Point"}
}