{
  "type": "Feature",
  "properties": {
    "iso:country":"DE",
    "sg:address":"M\u00fchlenstr. 5",
    "sg:city":"R\u00f6dinghausen",
    "sg:phone":"+49 5226/5275",
    "sg:postcode":"32289",
    "sg:province":"Nordrhein-Westfalen",
    "wof:name":"Gustav Hassel",
    "wof:placetype":"venue"
},
  "geometry": {"coordinates":[8.4597578049,52.2275314331],"type":"Point"}
}