{
  "type": "Feature",
  "properties": {
    "iso:country":"DE",
    "sg:address":"Sommerrain 16",
    "sg:city":"Wendlingen",
    "sg:phone":"+49 7024/51530",
    "sg:postcode":"73240",
    "sg:province":"Baden-W\u00fcrttemberg",
    "wof:name":"I. Fr\u00fch Immobilienmakler",
    "wof:placetype":"venue"
},
  "geometry": {"coordinates":[9.3796892166,48.6680297852],"type":"Point"}
}