{
  "type": "Feature",
  "properties": {
    "iso:country":"DE",
    "sg:address":"Axstr. 33",
    "sg:city":"Bochum",
    "sg:phone":"+49 234/941941",
    "sg:postcode":"44879",
    "sg:province":"Nordrhein-Westfalen",
    "wof:name":"Taxiunternehmen Hans-werner Bednarz",
    "wof:placetype":"venue"
},
  "geometry": {"coordinates":[7.1557011604,51.4255523682],"type":"Point"}
}