{
  "type": "Feature",
  "properties": {
    "iso:country":"DE",
    "sg:address":"Spitzwegstr. 19",
    "sg:city":"Recklinghausen",
    "sg:phone":"+49 2361/59918",
    "sg:postcode":"45659",
    "sg:province":"Nordrhein-Westfalen",
    "wof:name":"Textilpflege Laue Kg",
    "wof:placetype":"venue"
},
  "geometry": {"coordinates":[7.185145,51.608143],"type":"Point"}
}