{
  "type": "Feature",
  "properties": {
    "iso:country":"DE",
    "sg:address":"Marderweg 21",
    "sg:city":"Neum\u00fcnster",
    "sg:phone":"+49 4321/81152",
    "sg:postcode":"24539",
    "sg:province":"Schleswig-Holstein",
    "wof:name":"Erzgebirgs-st\u00fcbchen",
    "wof:placetype":"venue"
},
  "geometry": {"coordinates":[9.9619493484,54.0469207764],"type":"Point"}
}