{
  "type": "Feature",
  "properties": {
    "iso:country":"DE",
    "sg:address":"Am Kronenhof 3",
    "sg:city":"Esslingen",
    "sg:phone":"+49 711/353915",
    "sg:postcode":"73728",
    "sg:province":"Baden-W\u00fcrttemberg",
    "wof:name":"Stadtsch\u00e4nke",
    "wof:placetype":"venue"
},
  "geometry": {"coordinates":[9.3036756516,48.7387771606],"type":"Point"}
}