{
  "type": "Feature",
  "properties": {
    "iso:country":"DE",
    "sg:address":"D\u00f6bberner Weg",
    "sg:city":"Drebkau",
    "sg:postcode":"03116",
    "sg:province":"Brandenburg",
    "wof:name":"L\u00fcma Schweinemast Gmbh",
    "wof:placetype":"venue"
},
  "geometry": {"coordinates":[14.2359666824,51.6550331116],"type":"Point"}
}