{
  "type": "Feature",
  "properties": {
    "iso:country":"DE",
    "sg:address":"Bergstr. 42",
    "sg:city":"Billerbeck",
    "sg:phone":"+49 2543/1892",
    "sg:postcode":"48727",
    "sg:province":"Nordrhein-Westfalen",
    "wof:name":"Prause Gmbh",
    "wof:placetype":"venue"
},
  "geometry": {"coordinates":[7.305937767,51.973903656],"type":"Point"}
}