{
  "type": "Feature",
  "properties": {
    "iso:country":"DE",
    "sg:address":"Von-Quadt-Str. 9",
    "sg:city":"K\u00f6ln",
    "sg:phone":"+49 221/681595",
    "sg:postcode":"51069",
    "sg:province":"Nordrhein-Westfalen",
    "wof:name":"Feuerschutz Sch\u00f6ler Handels- Gesellschaft Mbh",
    "wof:placetype":"venue"
},
  "geometry": {"coordinates":[7.068558,50.975658],"type":"Point"}
}