{
  "type": "Feature",
  "properties": {
    "iso:country":"DE",
    "sg:address":"Am Rauen Strauch 7",
    "sg:city":"Gladenbach",
    "sg:phone":"+49 6462/5501",
    "sg:postcode":"35075",
    "sg:province":"Hessen",
    "wof:name":"Kreide",
    "wof:placetype":"venue"
},
  "geometry": {"coordinates":[8.5605278015,50.7914848328],"type":"Point"}
}