{
  "type": "Feature",
  "properties": {
    "iso:country":"DE",
    "sg:address":"Zum Wintersberg 69",
    "sg:city":"Bispingen",
    "sg:phone":"+49 5194/1383",
    "sg:postcode":"29646",
    "sg:province":"Niedersachsen",
    "wof:name":"Heidrun Tacke",
    "wof:placetype":"venue"
},
  "geometry": {"coordinates":[10.0128240585,53.0938034058],"type":"Point"}
}