{
  "type": "Feature",
  "properties": {
    "iso:country":"DE",
    "sg:address":"Friedrich-Engels-Allee 20",
    "sg:city":"Wuppertal",
    "sg:phone":"+49 202/49320",
    "sg:postcode":"42103",
    "sg:province":"Nordrhein-Westfalen",
    "wof:name":"Devk Deutsche Eisenbahn Versicherung Sach- Und Huk-",
    "wof:placetype":"venue"
},
  "geometry": {"coordinates":[7.161149025,51.2560539246],"type":"Point"}
}