{
  "type": "Feature",
  "properties": {
    "iso:country":"DE",
    "sg:address":"Noppdorf 6",
    "sg:city":"Viersen",
    "sg:phone":"+49 2162/22630",
    "sg:postcode":"41747",
    "sg:province":"Nordrhein-Westfalen",
    "wof:name":"Klaus Hoffmann Ingenieur",
    "wof:placetype":"venue"
},
  "geometry": {"coordinates":[6.3775172234,51.2587165833],"type":"Point"}
}