{
  "type": "Feature",
  "properties": {
    "iso:country":"DE",
    "sg:address":"Ermelinghofstr. 18",
    "sg:city":"Hamm",
    "sg:phone":"+49 2381/79940",
    "sg:postcode":"59075",
    "sg:province":"Nordrhein-Westfalen",
    "wof:name":"Seniorenstift Ludgeri Inh. J\u00fcrgen Metz E. K.",
    "wof:placetype":"venue"
},
  "geometry": {"coordinates":[7.7652049065,51.7024765015],"type":"Point"}
}