{
  "type": "Feature",
  "properties": {
    "iso:country":"DE",
    "sg:address":"Untere Grabenstr. 28",
    "sg:city":"Weilheim",
    "sg:phone":"+49 7023/2910",
    "sg:postcode":"73235",
    "sg:province":"Baden-W\u00fcrttemberg",
    "wof:name":"W. Kautter",
    "wof:placetype":"venue"
},
  "geometry": {"coordinates":[9.539748,48.613819],"type":"Point"}
}