{
  "type": "Feature",
  "properties": {
    "iso:country":"DE",
    "sg:address":"Tulpenstr. 8",
    "sg:city":"Villingen-Schwenningen",
    "sg:phone":"+49 7721/4550",
    "sg:postcode":"78052",
    "sg:province":"Baden-W\u00fcrttemberg",
    "wof:name":"Robert Preisinger",
    "wof:placetype":"venue"
},
  "geometry": {"coordinates":[8.4127912521,48.0325965881],"type":"Point"}
}