{
  "type": "Feature",
  "properties": {
    "iso:country":"DE",
    "sg:address":"Oberstr. 106",
    "sg:city":"Hamburg",
    "sg:phone":"+49 40/449452",
    "sg:postcode":"20149",
    "sg:province":"Hamburg",
    "wof:name":"A. S\u00f6hlke Handels-gmbh",
    "wof:placetype":"venue"
},
  "geometry": {"coordinates":[9.989694,53.57753],"type":"Point"}
}