{
  "type": "Feature",
  "properties": {
    "iso:country":"DE",
    "sg:address":"Steinweg 1",
    "sg:city":"S\u00fcpplingen",
    "sg:phone":"+49 5355/433",
    "sg:postcode":"38373",
    "sg:province":"Niedersachsen",
    "wof:name":"Wahnschaffe Beteiligungsgesellschaft Mbh",
    "wof:placetype":"venue"
},
  "geometry": {"coordinates":[10.909663,52.226982],"type":"Point"}
}