{
  "type": "Feature",
  "properties": {
    "iso:country":"DE",
    "sg:address":"Martin-Kollar-Str. 13",
    "sg:city":"M\u00fcnchen",
    "sg:phone":"+49 89/4207920",
    "sg:postcode":"81829",
    "sg:province":"Bayern",
    "wof:name":"Fairad Ag",
    "wof:placetype":"venue"
},
  "geometry": {"coordinates":[11.6594734192,48.1357116699],"type":"Point"}
}