{
  "type": "Feature",
  "properties": {
    "iso:country":"DE",
    "sg:address":"Heinrichstr. 7",
    "sg:city":"Laichingen",
    "sg:phone":"+49 7333/7040",
    "sg:postcode":"89150",
    "sg:province":"Baden-W\u00fcrttemberg",
    "wof:name":"Albrecht Straub",
    "wof:placetype":"venue"
},
  "geometry": {"coordinates":[9.6892156601,48.4888038635],"type":"Point"}
}