{
  "type": "Feature",
  "properties": {
    "iso:country":"DE",
    "sg:address":"B\u00f6cklerstr. 2",
    "sg:city":"Ettlingen",
    "sg:phone":"+49 7243/39130",
    "sg:postcode":"76275",
    "sg:province":"Baden-W\u00fcrttemberg",
    "wof:name":"Letermann Immobilien",
    "wof:placetype":"venue"
},
  "geometry": {"coordinates":[8.4039888382,48.9514732361],"type":"Point"}
}