{
  "type": "Feature",
  "properties": {
    "iso:country":"DE",
    "sg:address":"Wallstr. 37",
    "sg:city":"D\u00fcsseldorf",
    "sg:phone":"+49 211/325453",
    "sg:postcode":"40213",
    "sg:province":"Nordrhein-Westfalen",
    "wof:name":"Metatool Gmbh",
    "wof:placetype":"venue"
},
  "geometry": {"coordinates":[6.7751660347,51.224773407],"type":"Point"}
}