{
  "type": "Feature",
  "properties": {
    "iso:country":"DE",
    "sg:address":"Freiheitstr. 28",
    "sg:city":"Mettmann",
    "sg:phone":"+49 2104/27779",
    "sg:postcode":"40822",
    "sg:province":"Nordrhein-Westfalen",
    "wof:name":"K\u00f6nigshof-apotheke",
    "wof:placetype":"venue"
},
  "geometry": {"coordinates":[6.97619,51.250771],"type":"Point"}
}