{
  "type": "Feature",
  "properties": {
    "iso:country":"DE",
    "sg:address":"Meereweg 1",
    "sg:city":"Hamm",
    "sg:postcode":"59077",
    "sg:province":"Nordrhein-Westfalen",
    "wof:name":"Hartmann Gmbh",
    "wof:placetype":"venue"
},
  "geometry": {"coordinates":[7.7417941093,51.6372528076],"type":"Point"}
}