{
  "type": "Feature",
  "properties": {
    "iso:country":"DE",
    "sg:address":"Klausenweg 21",
    "sg:city":"Rabenau",
    "sg:phone":"+49 6407/6277",
    "sg:postcode":"35466",
    "sg:province":"Hessen",
    "wof:name":"H. Wallenfels Inh. G. Fritsch",
    "wof:placetype":"venue"
},
  "geometry": {"coordinates":[8.8947563171,50.6486816406],"type":"Point"}
}