{
  "type": "Feature",
  "properties": {
    "iso:country":"DE",
    "sg:address":"R\u00f6merstr. 123",
    "sg:city":"Lampertheim",
    "sg:phone":"+49 6206/13357",
    "sg:postcode":"68623",
    "sg:province":"Hessen",
    "wof:name":"Alte Kelter",
    "wof:placetype":"venue"
},
  "geometry": {"coordinates":[8.4634628296,49.5956344604],"type":"Point"}
}