{
  "type": "Feature",
  "properties": {
    "iso:country":"DE",
    "sg:address":"Feldkirchener Str. 16",
    "sg:city":"Ingolstadt",
    "sg:phone":"+49 841/58736",
    "sg:postcode":"85055",
    "sg:province":"Bayern",
    "wof:name":"Lipp Gmbh",
    "wof:placetype":"venue"
},
  "geometry": {"coordinates":[11.4401845932,48.7676811218],"type":"Point"}
}