{
  "type": "Feature",
  "properties": {
    "iso:country":"DE",
    "sg:address":"Hagenstr. 36-38",
    "sg:city":"Hannover",
    "sg:phone":"+49 511/990400",
    "sg:postcode":"30161",
    "sg:province":"Niedersachsen",
    "wof:name":"Zentrale Beratungsstelle",
    "wof:placetype":"venue"
},
  "geometry": {"coordinates":[9.7359399796,52.3835067749],"type":"Point"}
}