{
  "type": "Feature",
  "properties": {
    "iso:country":"DE",
    "sg:address":"Biberacher Str. 101",
    "sg:city":"Mittelbiberach",
    "sg:phone":"+49 7351/14215",
    "sg:postcode":"88441",
    "sg:province":"Baden-W\u00fcrttemberg",
    "wof:name":"Bs Automation Gmbh",
    "wof:placetype":"venue"
},
  "geometry": {"coordinates":[9.7512149811,48.0882797241],"type":"Point"}
}