{
  "type": "Feature",
  "properties": {
    "iso:country":"DE",
    "sg:address":"Wittenweierer Str. 49",
    "sg:city":"Schwanau",
    "sg:phone":"+49 4978/242623",
    "sg:postcode":"77963",
    "sg:province":"Baden-W\u00fcrttemberg",
    "wof:name":"Erwin Schiff Gmbh",
    "wof:placetype":"venue"
},
  "geometry": {"coordinates":[7.759756,48.343426],"type":"Point"}
}