{
  "type": "Feature",
  "properties": {
    "iso:country":"DE",
    "sg:address":"D\u00f6rpplatz 1",
    "sg:city":"G\u00f6nnebek",
    "sg:phone":"+49 4323/2422",
    "sg:postcode":"24610",
    "sg:province":"Schleswig-Holstein",
    "wof:name":"Paul Bl\u00f6cker",
    "wof:placetype":"venue"
},
  "geometry": {"coordinates":[10.174311,54.049263],"type":"Point"}
}