{
  "type": "Feature",
  "properties": {
    "iso:country":"DE",
    "sg:address":"Kieler Str 101b",
    "sg:city":"B\u00f6nningstedt",
    "sg:phone":"+49 40/5550533",
    "sg:postcode":"25474",
    "sg:province":"Schleswig-Holstein",
    "wof:name":"Coralis Consulting Gmbh",
    "wof:placetype":"venue"
},
  "geometry": {"coordinates":[9.8706064224,53.6575889587],"type":"Point"}
}