{
  "type": "Feature",
  "properties": {
    "iso:country":"DE",
    "sg:address":"Balduinstr. 74",
    "sg:city":"Zell",
    "sg:phone":"+49 6542/4372",
    "sg:postcode":"56856",
    "sg:province":"Rheinland-Pfalz",
    "wof:name":"Mosel-apotheke",
    "wof:placetype":"venue"
},
  "geometry": {"coordinates":[7.181787,50.027012],"type":"Point"}
}