{
  "type": "Feature",
  "properties": {
    "iso:country":"DE",
    "sg:address":"Bei der Pilzbuche 9",
    "sg:city":"Ulm",
    "sg:phone":"+49 7171/63221",
    "sg:postcode":"89075",
    "sg:province":"Baden-W\u00fcrttemberg",
    "wof:name":"H. Henseler",
    "wof:placetype":"venue"
},
  "geometry": {"coordinates":[10.031048,48.431919],"type":"Point"}
}