{
  "type": "Feature",
  "properties": {
    "iso:country":"DE",
    "sg:address":"Lange Reihe 45",
    "sg:city":"Hamburg",
    "sg:postcode":"20099",
    "sg:province":"Hamburg",
    "wof:name":"Men-su Gmbh",
    "wof:placetype":"venue"
},
  "geometry": {"coordinates":[10.0106706619,53.5571975708],"type":"Point"}
}