{
  "type": "Feature",
  "properties": {
    "iso:country":"DE",
    "sg:address":"Hafnerweg 4",
    "sg:city":"Odelzhausen",
    "sg:postcode":"85235",
    "sg:province":"Bayern",
    "wof:name":"Restore Ges. F\u00fcr Netzwerke Und Kommunikationstechnik Mbh",
    "wof:placetype":"venue"
},
  "geometry": {"coordinates":[11.1913499832,48.3107528687],"type":"Point"}
}