{
  "type": "Feature",
  "properties": {
    "iso:country":"DE",
    "sg:address":"Parkstr. 5",
    "sg:city":"Hude",
    "sg:phone":"+49 4408/923106",
    "sg:postcode":"27798",
    "sg:province":"Niedersachsen",
    "wof:name":"Bedruckt Inh. Hans-j. Behrends E. Kfm.",
    "wof:placetype":"venue"
},
  "geometry": {"coordinates":[8.460684,53.110844],"type":"Point"}
}