{
  "type": "Feature",
  "properties": {
    "iso:country":"DE",
    "sg:address":"Bergwerkstr. 1",
    "sg:city":"Pegnitz",
    "sg:phone":"+49 9241/9880",
    "sg:postcode":"91257",
    "sg:province":"Bayern",
    "wof:name":"Nordbayerische St\u00e4dtereinigung Altvater Verwaltungs-gmbh",
    "wof:placetype":"venue"
},
  "geometry": {"coordinates":[11.5524463654,49.7641868591],"type":"Point"}
}