{
  "type": "Feature",
  "properties": {
    "iso:country":"DE",
    "sg:address":"Augustenhof 10",
    "sg:city":"Burglengenfeld",
    "sg:phone":"+49 9471/1567",
    "sg:postcode":"93133",
    "sg:province":"Bayern",
    "wof:name":"Johann Seidl Architekt",
    "wof:placetype":"venue"
},
  "geometry": {"coordinates":[12.064281,49.206348],"type":"Point"}
}