{
  "type": "Feature",
  "properties": {
    "iso:country":"DE",
    "sg:address":"Westerholtsfelder Str. 5",
    "sg:city":"Bad Zwischenahn",
    "sg:phone":"+49 441/69678",
    "sg:postcode":"26160",
    "sg:province":"Niedersachsen",
    "wof:name":"E. Peter Grewe Elektroinstallation",
    "wof:placetype":"venue"
},
  "geometry": {"coordinates":[8.11346,53.184147],"type":"Point"}
}