{
  "type": "Feature",
  "properties": {
    "iso:country":"DE",
    "sg:address":"Am Fuchsbogen 16",
    "sg:city":"F\u00fcrstenfeldbruck",
    "sg:phone":"+49 8141/18557",
    "sg:postcode":"82256",
    "sg:province":"Bayern",
    "wof:name":"G. Wager",
    "wof:placetype":"venue"
},
  "geometry": {"coordinates":[11.224142,48.16349],"type":"Point"}
}