{
  "type": "Feature",
  "properties": {
    "iso:country":"DE",
    "sg:address":"Westhafen 5",
    "sg:city":"Frankfurt",
    "sg:phone":"+49 69/239454",
    "sg:postcode":"60327",
    "sg:province":"Hessen",
    "wof:name":"Koniva Hoch- Und Tiefbau Gmbh",
    "wof:placetype":"venue"
},
  "geometry": {"coordinates":[8.664396,50.101231],"type":"Point"}
}