{
  "type": "Feature",
  "properties": {
    "iso:country":"DE",
    "sg:address":"Stahlstr. 19",
    "sg:city":"R\u00fcsselsheim",
    "sg:phone":"+49 6142/64745",
    "sg:postcode":"65428",
    "sg:province":"Hessen",
    "wof:name":"Heinz Jung",
    "wof:placetype":"venue"
},
  "geometry": {"coordinates":[8.431593,49.976395],"type":"Point"}
}