{
  "type": "Feature",
  "properties": {
    "iso:country":"DE",
    "sg:address":"Osterwisch 5c",
    "sg:city":"Kiel",
    "sg:phone":"+49 431/6597965",
    "sg:postcode":"24103",
    "sg:province":"Schleswig-Holstein",
    "wof:name":"Compunow",
    "wof:placetype":"venue"
},
  "geometry": {"coordinates":[10.133549,54.323654],"type":"Point"}
}