{
  "type": "Feature",
  "properties": {
    "iso:country":"DE",
    "sg:address":"Vitalisstr. 227",
    "sg:city":"K\u00f6ln",
    "sg:phone":"+49 221/581828",
    "sg:postcode":"50827",
    "sg:province":"Nordrhein-Westfalen",
    "wof:name":"Otto M\u00fcller Steinhandel Gmbh & Co. Kg",
    "wof:placetype":"venue"
},
  "geometry": {"coordinates":[6.8977198601,50.9527587891],"type":"Point"}
}