{
  "type": "Feature",
  "properties": {
    "iso:country":"DE",
    "sg:address":"Altmarkt 11",
    "sg:city":"Aue",
    "sg:phone":"+49 3771/54657",
    "sg:postcode":"08280",
    "sg:province":"Sachsen",
    "wof:name":"Sonntag Immobilienb\u00fcro",
    "wof:placetype":"venue"
},
  "geometry": {"coordinates":[12.7031288147,50.5862617493],"type":"Point"}
}