{
  "type": "Feature",
  "properties": {
    "iso:country":"DE",
    "sg:address":"Bautzener Str. 36",
    "sg:city":"Neusalza-Spremberg",
    "sg:phone":"+49 35872/32211",
    "sg:postcode":"02742",
    "sg:province":"Sachsen",
    "wof:name":"Werner Schwarz",
    "wof:placetype":"venue"
},
  "geometry": {"coordinates":[14.5426797867,51.037651062],"type":"Point"}
}