{
  "type": "Feature",
  "properties": {
    "iso:country":"DE",
    "sg:address":"Radlkoferstr. 5",
    "sg:city":"M\u00fcnchen",
    "sg:postcode":"81373",
    "sg:province":"Bayern",
    "wof:name":"Hr Exec Edv-beratung E. K.",
    "wof:placetype":"venue"
},
  "geometry": {"coordinates":[11.54367733,48.1260948181],"type":"Point"}
}