{
  "type": "Feature",
  "properties": {
    "iso:country":"DE",
    "sg:address":"Dorfstr. 17",
    "sg:city":"Ismaning",
    "sg:phone":"+49 89/9965350",
    "sg:postcode":"85737",
    "sg:province":"Bayern",
    "wof:name":"Technoplot Cad Vertriebs-gmbh",
    "wof:placetype":"venue"
},
  "geometry": {"coordinates":[11.6738548279,48.2210769653],"type":"Point"}
}