{
  "type": "Feature",
  "properties": {
    "iso:country":"DE",
    "sg:address":"Obergasse 13",
    "sg:city":"Welgesheim",
    "sg:phone":"+49 6701/911141",
    "sg:postcode":"55576",
    "sg:province":"Rheinland-Pfalz",
    "wof:name":"Vermessungsb\u00fcro Dipl.-ing. R. Goebel \u00d6ffentl. Best. Verm.-ing., Berat. Ing.",
    "wof:placetype":"venue"
},
  "geometry": {"coordinates":[7.9624528885,49.882686615],"type":"Point"}
}