{
  "type": "Feature",
  "properties": {
    "iso:country":"DE",
    "sg:address":"Seestr. 2-4",
    "sg:city":"Rodgau",
    "sg:postcode":"63110",
    "sg:province":"Hessen",
    "wof:name":"Fecher E. Kfm.",
    "wof:placetype":"venue"
},
  "geometry": {"coordinates":[8.8639640808,50.0040817261],"type":"Point"}
}