{
  "type": "Feature",
  "properties": {
    "iso:country":"DE",
    "sg:address":"Ottobeurer Str. 30",
    "sg:city":"Sontheim",
    "sg:phone":"+49 8336/7057",
    "sg:postcode":"87776",
    "sg:province":"Bayern",
    "wof:name":"Schreinerei Boneberger E. K.",
    "wof:placetype":"venue"
},
  "geometry": {"coordinates":[10.342261,47.985188],"type":"Point"}
}