{
  "type": "Feature",
  "properties": {
    "iso:country":"DE",
    "sg:address":"Masurenallee 13",
    "sg:city":"Bad Wildungen",
    "sg:phone":"+49 5621/70980",
    "sg:postcode":"34537",
    "sg:province":"Hessen",
    "wof:name":"Hotel Mozart Und Orchidee Appart-hotel Prinz",
    "wof:placetype":"venue"
},
  "geometry": {"coordinates":[9.0763254166,51.1156463623],"type":"Point"}
}