{
  "type": "Feature",
  "properties": {
    "iso:country":"DE",
    "sg:address":"Richard-Wolff-Str. 39",
    "sg:city":"Hessisch Lichtenau",
    "sg:phone":"+49 5602/70603",
    "sg:postcode":"37235",
    "sg:province":"Hessen",
    "wof:name":"Soft And Clean Waschstra\u00dfe Inh. Guido Rohrmann",
    "wof:placetype":"venue"
},
  "geometry": {"coordinates":[9.731633,51.196018],"type":"Point"}
}