{
  "type": "Feature",
  "properties": {
    "iso:country":"DE",
    "sg:address":"Am Bahnhof 1",
    "sg:city":"Krauchenwies",
    "sg:phone":"+49 7576/525",
    "sg:postcode":"72505",
    "sg:province":"Baden-W\u00fcrttemberg",
    "wof:name":"Nestel Baumaschinen",
    "wof:placetype":"venue"
},
  "geometry": {"coordinates":[9.238624,48.019901],"type":"Point"}
}