{
  "type": "Feature",
  "properties": {
    "iso:country":"DE",
    "sg:address":"Waldschmidtstr. 28",
    "sg:city":"Cham",
    "sg:phone":"+49 9971/30202",
    "sg:postcode":"93413",
    "sg:province":"Bayern",
    "wof:name":"China-restaurant Sin Wah",
    "wof:placetype":"venue"
},
  "geometry": {"coordinates":[12.6572351456,49.2256317139],"type":"Point"}
}