{
  "type": "Feature",
  "properties": {
    "iso:country":"DE",
    "sg:address":"Luxemburger Str. 341",
    "sg:city":"H\u00fcrth",
    "sg:phone":"+49 2233/75685",
    "sg:postcode":"50354",
    "sg:province":"Nordrhein-Westfalen",
    "wof:name":"Wilfried Schmitz",
    "wof:placetype":"venue"
},
  "geometry": {"coordinates":[6.8890028,50.8786010742],"type":"Point"}
}