{
  "type": "Feature",
  "properties": {
    "iso:country":"DE",
    "sg:address":"Am H\u00fclsenbusch 43",
    "sg:city":"Hamm",
    "sg:phone":"+49 2381/50340",
    "sg:postcode":"59063",
    "sg:province":"Nordrhein-Westfalen",
    "wof:name":"Baum & Pott",
    "wof:placetype":"venue"
},
  "geometry": {"coordinates":[7.8353099823,51.6679191589],"type":"Point"}
}