{
  "type": "Feature",
  "properties": {
    "iso:country":"DE",
    "sg:address":"Im B\u00e4chel 1",
    "sg:city":"Altenglan",
    "sg:phone":"+49 6381/42000",
    "sg:postcode":"66885",
    "sg:province":"Rheinland-Pfalz",
    "wof:name":"Sft Schneider Fenstertechnik Gmbh & Co. Kg",
    "wof:placetype":"venue"
},
  "geometry": {"coordinates":[7.454957,49.559555],"type":"Point"}
}