{
  "type": "Feature",
  "properties": {
    "iso:country":"DE",
    "sg:address":"Stettiner Str. 9",
    "sg:city":"H\u00fcttlingen",
    "sg:phone":"+49 7361/970050",
    "sg:postcode":"73460",
    "sg:province":"Baden-W\u00fcrttemberg",
    "wof:name":"H. Arnold Steuerberater",
    "wof:placetype":"venue"
},
  "geometry": {"coordinates":[10.1008090973,48.8976554871],"type":"Point"}
}