{
  "type": "Feature",
  "properties": {
    "iso:country":"DE",
    "sg:address":"Sandstr. 26",
    "sg:city":"Schwandorf",
    "sg:phone":"+49 9431/1891",
    "sg:postcode":"92421",
    "sg:province":"Bayern",
    "wof:name":"Hans Gebhardt",
    "wof:placetype":"venue"
},
  "geometry": {"coordinates":[12.118192,49.321426],"type":"Point"}
}