{
  "type": "Feature",
  "properties": {
    "iso:country":"DE",
    "sg:address":"Lange Str. 42",
    "sg:city":"Mundelsheim",
    "sg:phone":"+49 7143/5543",
    "sg:postcode":"74395",
    "sg:province":"Baden-W\u00fcrttemberg",
    "wof:name":"M. Haar",
    "wof:placetype":"venue"
},
  "geometry": {"coordinates":[9.206905,48.998585],"type":"Point"}
}