{
  "type": "Feature",
  "properties": {
    "iso:country":"DE",
    "sg:address":"Goldbachstr. 11",
    "sg:city":"Haiger",
    "sg:phone":"+49 2771/31968",
    "sg:postcode":"35708",
    "sg:province":"Hessen",
    "wof:name":"Ev. Pfarramt Sechshelden",
    "wof:placetype":"venue"
},
  "geometry": {"coordinates":[8.2489700317,50.7481956482],"type":"Point"}
}