{
  "type": "Feature",
  "properties": {
    "iso:country":"DE",
    "sg:address":"Wilhelmstr. 15",
    "sg:city":"Niederstotzingen",
    "sg:phone":"+49 7325/6411",
    "sg:postcode":"89168",
    "sg:province":"Baden-W\u00fcrttemberg",
    "wof:name":"I. Hartmann",
    "wof:placetype":"venue"
},
  "geometry": {"coordinates":[10.232824,48.53569],"type":"Point"}
}