{
  "type": "Feature",
  "properties": {
    "iso:country":"DE",
    "sg:address":"Duisburger Str 22",
    "sg:city":"N\u00fcrnberg",
    "sg:phone":"+49 911/64100",
    "sg:postcode":"90451",
    "sg:province":"Bayern",
    "wof:name":"Birkart System Verkehre Gmbh",
    "wof:placetype":"venue"
},
  "geometry": {"coordinates":[11.049905,49.404278],"type":"Point"}
}