{
  "type": "Feature",
  "properties": {
    "iso:country":"DE",
    "sg:address":"G\u00f6tzstr. 8",
    "sg:city":"Berlin",
    "sg:phone":"+49 30/75602819",
    "sg:postcode":"12099",
    "sg:province":"Berlin",
    "wof:name":"Stadtbibliothek",
    "wof:placetype":"venue"
},
  "geometry": {"coordinates":[13.387501,52.464539],"type":"Point"}
}