{
  "type": "Feature",
  "properties": {
    "iso:country":"DE",
    "sg:address":"Hanauer Weg 7",
    "sg:city":"Hasselroth",
    "sg:phone":"+49 6055/6041",
    "sg:postcode":"63594",
    "sg:province":"Hessen",
    "wof:name":"Michael Wagner",
    "wof:placetype":"venue"
},
  "geometry": {"coordinates":[9.1004724503,50.153717041],"type":"Point"}
}