{
  "type": "Feature",
  "properties": {
    "iso:country":"DE",
    "sg:address":"D\u00fcsselstr. 15",
    "sg:city":"D\u00fcsseldorf",
    "sg:phone":"+49 211/391128",
    "sg:postcode":"40219",
    "sg:province":"Nordrhein-Westfalen",
    "wof:name":"Petra Breuer Hebamme",
    "wof:placetype":"venue"
},
  "geometry": {"coordinates":[6.765486,51.213867],"type":"Point"}
}