{
  "type": "Feature",
  "properties": {
    "iso:country":"DE",
    "sg:address":"Augsburger Str. 58",
    "sg:city":"Wei\u00dfenburg",
    "sg:phone":"+49 9141/73610",
    "sg:postcode":"91781",
    "sg:province":"Bayern",
    "wof:name":"H. K\u00f6bler",
    "wof:placetype":"venue"
},
  "geometry": {"coordinates":[10.964867,49.021103],"type":"Point"}
}