{
  "type": "Feature",
  "properties": {
    "iso:country":"DE",
    "sg:address":"Klostergasse 12",
    "sg:city":"Kulmbach",
    "sg:phone":"+49 9221/2627",
    "sg:postcode":"95326",
    "sg:province":"Bayern",
    "wof:name":"Pizzeria Besenstiel",
    "wof:placetype":"venue"
},
  "geometry": {"coordinates":[11.4557332993,50.1081581116],"type":"Point"}
}