{
  "type": "Feature",
  "properties": {
    "iso:country":"DE",
    "sg:address":"M\u00e4uerlesstr 11",
    "sg:city":"Magstadt",
    "sg:phone":"+49 7159/42362",
    "sg:postcode":"71106",
    "sg:province":"Baden-W\u00fcrttemberg",
    "wof:name":"Munk Gmbh & Co Kg",
    "wof:placetype":"venue"
},
  "geometry": {"coordinates":[8.959651,48.74398],"type":"Point"}
}