{
  "type": "Feature",
  "properties": {
    "iso:country":"DE",
    "sg:address":"Salzburger Str. 4",
    "sg:city":"Stephanskirchen",
    "sg:phone":"+49 8031/73971",
    "sg:postcode":"83071",
    "sg:province":"Bayern",
    "wof:name":"Josef Kerscher",
    "wof:placetype":"venue"
},
  "geometry": {"coordinates":[12.146089,47.857708],"type":"Point"}
}