{
  "type": "Feature",
  "properties": {
    "iso:country":"DE",
    "sg:address":"Parkstr.6",
    "sg:city":"Titisee",
    "sg:phone":"+49 7651/80990",
    "sg:postcode":"79815",
    "wof:name":"Wellnesshotel",
    "wof:placetype":"venue"
},
  "geometry": {"coordinates":[8.154071,47.902248],"type":"Point"}
}