{
  "type": "Feature",
  "properties": {
    "iso:country":"DE",
    "sg:address":"Engertstr. 27",
    "sg:city":"Leipzig",
    "sg:phone":"+49 341/4772668",
    "sg:postcode":"04229",
    "sg:province":"Sachsen",
    "wof:name":"Berufskleidungsprofi",
    "wof:placetype":"venue"
},
  "geometry": {"coordinates":[12.3234157562,51.3282089233],"type":"Point"}
}