{
  "type": "Feature",
  "properties": {
    "iso:country":"DE",
    "sg:address":"Uhlandstr. 32",
    "sg:city":"Hattingen",
    "sg:phone":"+49 2324/25488",
    "sg:postcode":"45525",
    "sg:province":"Nordrhein-Westfalen",
    "wof:name":"Ev. Pfarramt Kirchengemeinde Johannes",
    "wof:placetype":"venue"
},
  "geometry": {"coordinates":[7.1773080826,51.3909759521],"type":"Point"}
}