{
  "type": "Feature",
  "properties": {
    "iso:country":"DE",
    "sg:address":"Roteb\u00fchlstr. 150",
    "sg:city":"Stuttgart",
    "sg:phone":"+49 711/652038",
    "sg:postcode":"70197",
    "sg:province":"Baden-W\u00fcrttemberg",
    "wof:name":"J. Fern Ohg",
    "wof:placetype":"venue"
},
  "geometry": {"coordinates":[9.1529550552,48.7694168091],"type":"Point"}
}