{
  "type": "Feature",
  "properties": {
    "iso:country":"DE",
    "sg:address":"M\u00fchlenweg 50",
    "sg:city":"Berlin",
    "sg:phone":"+49 30/64849860",
    "sg:postcode":"12589",
    "sg:province":"Berlin",
    "wof:name":"Witt Gmbh",
    "wof:placetype":"venue"
},
  "geometry": {"coordinates":[13.690621,52.43914],"type":"Point"}
}