{
  "type": "Feature",
  "properties": {
    "iso:country":"DE",
    "sg:address":"Hauptstr. 82",
    "sg:city":"Guntersblum",
    "sg:phone":"+49 6249/7393",
    "sg:postcode":"67583",
    "sg:province":"Rheinland-Pfalz",
    "wof:name":"Dea Tankstelle",
    "wof:placetype":"venue"
},
  "geometry": {"coordinates":[8.3439903259,49.8003463745],"type":"Point"}
}