{
  "type": "Feature",
  "properties": {
    "iso:country":"DE",
    "sg:address":"Helenenstr. 9",
    "sg:city":"Aschaffenburg",
    "sg:phone":"+49 6021/23988",
    "sg:postcode":"63743",
    "sg:province":"Bayern",
    "wof:name":"Erich Junker Ingenieur",
    "wof:placetype":"venue"
},
  "geometry": {"coordinates":[9.1412687302,49.963558197],"type":"Point"}
}