{
  "type": "Feature",
  "properties": {
    "iso:country":"DE",
    "sg:address":"Mittelstr. 6",
    "sg:city":"Reichenberg",
    "sg:phone":"+49 33437/89796",
    "sg:postcode":"15377",
    "sg:province":"Brandenburg",
    "wof:name":"Relax",
    "wof:placetype":"venue"
},
  "geometry": {"coordinates":[14.1129608154,52.611366272],"type":"Point"}
}