{
  "type": "Feature",
  "properties": {
    "iso:country":"DE",
    "sg:address":"Elbestr. 1",
    "sg:city":"Traunreut",
    "sg:phone":"+49 8669/2471",
    "sg:postcode":"83301",
    "sg:province":"Bayern",
    "wof:name":"Gastager",
    "wof:placetype":"venue"
},
  "geometry": {"coordinates":[12.5914316177,47.9627685547],"type":"Point"}
}