{
  "type": "Feature",
  "properties": {
    "iso:country":"DE",
    "sg:address":"Schlattgrabenstr. 34",
    "sg:city":"Walddorfh\u00e4slach",
    "sg:postcode":"72141",
    "sg:province":"Baden-W\u00fcrttemberg",
    "wof:name":"Sani Wolf Gmbh",
    "wof:placetype":"venue"
},
  "geometry": {"coordinates":[9.1720724106,48.5883216858],"type":"Point"}
}