{
  "type": "Feature",
  "properties": {
    "iso:country":"DE",
    "sg:address":"Sachsenstr. 40",
    "sg:city":"Nordenham",
    "sg:phone":"+49 4731/923114",
    "sg:postcode":"26954",
    "sg:province":"Niedersachsen",
    "wof:name":"Clemens Strubbe & Petra Eckhoff",
    "wof:placetype":"venue"
},
  "geometry": {"coordinates":[8.4710540771,53.4766349792],"type":"Point"}
}