{
  "type": "Feature",
  "properties": {
    "iso:country":"DE",
    "sg:address":"Rathausstr. 36",
    "sg:city":"Viernheim",
    "sg:phone":"+49 6204/78607",
    "sg:postcode":"68519",
    "sg:province":"Hessen",
    "wof:name":"Rohr & Pr\u00f6ll Gmbh & Co. Kg",
    "wof:placetype":"venue"
},
  "geometry": {"coordinates":[8.5789375305,49.5372962952],"type":"Point"}
}