{
  "type": "Feature",
  "properties": {
    "iso:country":"DE",
    "sg:address":"Kapuzinerstr. 8",
    "sg:city":"Bingen",
    "sg:phone":"+49 6721/16543",
    "sg:postcode":"55411",
    "sg:province":"Rheinland-Pfalz",
    "wof:name":"Langer",
    "wof:placetype":"venue"
},
  "geometry": {"coordinates":[7.895894,49.967663],"type":"Point"}
}