{
  "type": "Feature",
  "properties": {
    "iso:country":"DE",
    "sg:address":"Meininger Str. 3",
    "sg:city":"Suhl",
    "sg:phone":"+49 3681/308260",
    "sg:postcode":"98529",
    "sg:province":"Th\u00fcringen",
    "wof:name":"Ihk-ledervertriebs Gmbh",
    "wof:placetype":"venue"
},
  "geometry": {"coordinates":[10.66169,50.599209],"type":"Point"}
}