{
  "type": "Feature",
  "properties": {
    "iso:country":"DE",
    "sg:address":"Carl-Bertelsmann-Str. 270",
    "sg:city":"G\u00fctersloh",
    "sg:phone":"+49 5241/80",
    "sg:postcode":"33335",
    "sg:province":"Nordrhein-Westfalen",
    "wof:name":"Bw Tv Und Film Verwaltungs Gmbh",
    "wof:placetype":"venue"
},
  "geometry": {"coordinates":[8.420917,51.909958],"type":"Point"}
}