{
  "type": "Feature",
  "properties": {
    "iso:country":"DE",
    "sg:address":"Teunzer Str. 19",
    "sg:city":"Niedermurach",
    "sg:phone":"+49 9671/594",
    "sg:postcode":"92545",
    "sg:province":"Bayern",
    "wof:name":"Brand Kg",
    "wof:placetype":"venue"
},
  "geometry": {"coordinates":[12.376685,49.451859],"type":"Point"}
}