{
  "type": "Feature",
  "properties": {
    "iso:country":"DE",
    "sg:address":"Auenstr. 90",
    "sg:city":"M\u00fcnchen",
    "sg:phone":"+49 89/7469299",
    "sg:postcode":"80469",
    "sg:province":"Bayern",
    "wof:name":"Wohlmann-dandl Und Kollegen Rechtsanw\u00e4lte",
    "wof:placetype":"venue"
},
  "geometry": {"coordinates":[11.5653581619,48.1228218079],"type":"Point"}
}