{
  "type": "Feature",
  "properties": {
    "iso:country":"DE",
    "sg:address":"Nordermitteldeich 34",
    "sg:city":"Pellworm",
    "sg:phone":"+49 4844/381",
    "sg:postcode":"25849",
    "sg:province":"Schleswig-Holstein",
    "wof:name":"Hans Petersen",
    "wof:placetype":"venue"
},
  "geometry": {"coordinates":[8.640171051,54.5388526917],"type":"Point"}
}