{
  "type": "Feature",
  "properties": {
    "iso:country":"DE",
    "sg:address":"Schmiedegasse 14",
    "sg:city":"Bornheim",
    "sg:phone":"+49 2227/4862",
    "sg:postcode":"53332",
    "sg:province":"Nordrhein-Westfalen",
    "wof:name":"Hans-josef Niedecker",
    "wof:placetype":"venue"
},
  "geometry": {"coordinates":[6.952001,50.764484],"type":"Point"}
}