{
  "type": "Feature",
  "properties": {
    "iso:country":"DE",
    "sg:address":"Amselstieg",
    "sg:city":"Bad Salzdetfurth",
    "sg:phone":"+49 5063",
    "sg:postcode":"31162",
    "sg:province":"Niedersachsen",
    "wof:name":"Hau Angela",
    "wof:placetype":"venue"
},
  "geometry": {"coordinates":[10.013838768,52.0602455139],"type":"Point"}
}