{
  "type": "Feature",
  "properties": {
    "iso:country":"DE",
    "sg:address":"Ditzenbrunner Str. 72",
    "sg:city":"Ditzingen",
    "sg:phone":"+49 7156/18823",
    "sg:postcode":"71254",
    "sg:province":"Baden-W\u00fcrttemberg",
    "wof:name":"Rudolf Schricker Architekt",
    "wof:placetype":"venue"
},
  "geometry": {"coordinates":[9.078368,48.829815],"type":"Point"}
}