{
  "type": "Feature",
  "properties": {
    "iso:country":"DE",
    "sg:address":"Hauptstr. 1",
    "sg:city":"Eiselfing",
    "sg:phone":"+49 8071/2048",
    "sg:postcode":"83549",
    "sg:province":"Bayern",
    "wof:name":"Alois Pauker E. K. Inh. Angelika Mittermaier",
    "wof:placetype":"venue"
},
  "geometry": {"coordinates":[12.2393817902,48.0316505432],"type":"Point"}
}