{
  "type": "Feature",
  "properties": {
    "iso:country":"DE",
    "sg:address":"N\u00fcrnberger Str. 29",
    "sg:city":"Zirndorf",
    "sg:phone":"+49 911/609676",
    "sg:postcode":"90513",
    "sg:province":"Bayern",
    "wof:name":"Baumg\u00e4rtner Und Kollegen Rechtsanw\u00e4lte",
    "wof:placetype":"venue"
},
  "geometry": {"coordinates":[10.9608983994,49.4403991699],"type":"Point"}
}