{
  "type": "Feature",
  "properties": {
    "iso:country":"DE",
    "sg:address":"Marktler Str. 23",
    "sg:city":"Burghausen",
    "sg:phone":"+49 8677/3034",
    "sg:postcode":"84489",
    "sg:province":"Bayern",
    "wof:name":"Fritzweiler Und Partner",
    "wof:placetype":"venue"
},
  "geometry": {"coordinates":[12.8304042816,48.170841217],"type":"Point"}
}