{
  "type": "Feature",
  "properties": {
    "iso:country":"DE",
    "sg:address":"Wuppertaler Str. 32",
    "sg:city":"Solingen",
    "sg:phone":"+49 212/55227",
    "sg:postcode":"42653",
    "sg:province":"Nordrhein-Westfalen",
    "wof:name":"Tsb Tankstellenbetriebe Gmbh",
    "wof:placetype":"venue"
},
  "geometry": {"coordinates":[7.0753688812,51.1935806274],"type":"Point"}
}