{
  "type": "Feature",
  "properties": {
    "iso:country":"DE",
    "sg:address":"Rostocker Str. 12",
    "sg:city":"Dormagen",
    "sg:phone":"+49 2133/478258",
    "sg:postcode":"41540",
    "sg:province":"Nordrhein-Westfalen",
    "wof:name":"Montec Falk Henninghaus Pr\u00e4zisionskomponenten Gmbh",
    "wof:placetype":"venue"
},
  "geometry": {"coordinates":[6.8188548088,51.0944290161],"type":"Point"}
}