{
  "type": "Feature",
  "properties": {
    "iso:country":"DE",
    "sg:address":"Philipp-F\u00f6rsch-Str. 22",
    "sg:city":"Budenheim",
    "sg:phone":"+49 6139/6120",
    "sg:postcode":"55257",
    "sg:province":"Rheinland-Pfalz",
    "wof:name":"Willi Kehrmann Bildhauer",
    "wof:placetype":"venue"
},
  "geometry": {"coordinates":[8.168021,50.02203],"type":"Point"}
}