{
  "type": "Feature",
  "properties": {
    "iso:country":"DE",
    "sg:address":"Hauptstr. 150",
    "sg:city":"Wiesmoor",
    "sg:phone":"+49 4944/7705",
    "sg:postcode":"26639",
    "sg:province":"Niedersachsen",
    "wof:name":"Happy Letter Fashion",
    "wof:placetype":"venue"
},
  "geometry": {"coordinates":[7.71557,53.401718],"type":"Point"}
}