{
  "type": "Feature",
  "properties": {
    "iso:country":"DE",
    "sg:address":"Dorfstr. 14",
    "sg:city":"Wa\u00dfmannsdorf",
    "sg:phone":"+49 3379/444263",
    "sg:postcode":"15831",
    "sg:province":"Brandenburg",
    "wof:name":"Dymke",
    "wof:placetype":"venue"
},
  "geometry": {"coordinates":[13.4743814468,52.3717651367],"type":"Point"}
}