{
  "type": "Feature",
  "properties": {
    "iso:country":"DE",
    "sg:address":"Kirchweg 6",
    "sg:city":"Anr\u00f6chte",
    "sg:postcode":"59609",
    "sg:province":"Nordrhein-Westfalen",
    "wof:name":"Hahne Gmbh",
    "wof:placetype":"venue"
},
  "geometry": {"coordinates":[8.2746171951,51.5547294617],"type":"Point"}
}