{
  "type": "Feature",
  "properties": {
    "iso:country":"DE",
    "sg:address":"Hauptstr. 23",
    "sg:city":"Alfdorf",
    "sg:postcode":"73553",
    "sg:province":"Baden-W\u00fcrttemberg",
    "wof:name":"Linden-apotheke P\u00e4chter F. J. Chwalek E. Kfm.",
    "wof:placetype":"venue"
},
  "geometry": {"coordinates":[9.716897,48.843208],"type":"Point"}
}