{
  "type": "Feature",
  "properties": {
    "iso:country":"DE",
    "sg:address":"Kemnather Str. 9",
    "sg:city":"Kulmain",
    "sg:phone":"+49 9642/437",
    "sg:postcode":"95508",
    "sg:province":"Bayern",
    "wof:name":"A. Kreuzer",
    "wof:placetype":"venue"
},
  "geometry": {"coordinates":[11.897672,49.890896],"type":"Point"}
}