{
  "type": "Feature",
  "properties": {
    "iso:country":"DE",
    "sg:address":"Nordstr. 20",
    "sg:city":"Hanau",
    "sg:phone":"+49 6181/14899",
    "sg:postcode":"63450",
    "sg:province":"Hessen",
    "wof:name":"Gerhard Ziegler",
    "wof:placetype":"venue"
},
  "geometry": {"coordinates":[8.9197635651,50.1359100342],"type":"Point"}
}