{
  "type": "Feature",
  "properties": {
    "iso:country":"DE",
    "sg:address":"Dettenhauser Str. 11",
    "sg:city":"Walddorfh\u00e4slach",
    "sg:phone":"+49 7127/31223",
    "sg:postcode":"72141",
    "sg:province":"Baden-W\u00fcrttemberg",
    "wof:name":"Helmut Schlecht Gmbh Elektroinstallationen",
    "wof:placetype":"venue"
},
  "geometry": {"coordinates":[9.180711,48.587429],"type":"Point"}
}