{
  "type": "Feature",
  "properties": {
    "iso:country":"DE",
    "sg:address":"Schulweg",
    "sg:city":"B\u00f6sel",
    "sg:phone":"+49 4494/313",
    "sg:postcode":"26219",
    "sg:province":"Niedersachsen",
    "wof:name":"Gemeindeb\u00fccherei",
    "wof:placetype":"venue"
},
  "geometry": {"coordinates":[7.955244,53.00713],"type":"Point"}
}