{
  "type": "Feature",
  "properties": {
    "iso:country":"DE",
    "sg:address":"Eschstr. 4",
    "sg:city":"M\u00fcnster",
    "sg:phone":"+49 2506/83090",
    "sg:postcode":"48167",
    "sg:province":"Nordrhein-Westfalen",
    "wof:name":"Vitanova Gmbh",
    "wof:placetype":"venue"
},
  "geometry": {"coordinates":[7.72491,51.921291],"type":"Point"}
}