{
  "type": "Feature",
  "properties": {
    "iso:country":"DE",
    "sg:address":"Bruchstr. 14",
    "sg:city":"Willich",
    "sg:phone":"+49 2154/5336",
    "sg:postcode":"47877",
    "sg:province":"Nordrhein-Westfalen",
    "wof:name":"Christian Troska",
    "wof:placetype":"venue"
},
  "geometry": {"coordinates":[6.466713,51.255226],"type":"Point"}
}