{
  "type": "Feature",
  "properties": {
    "iso:country":"DE",
    "sg:address":"Poststr. 1",
    "sg:city":"Elsterwerda",
    "sg:phone":"+49 3533/2646",
    "sg:postcode":"04910",
    "sg:province":"Brandenburg",
    "wof:name":"Steffen Kunitz",
    "wof:placetype":"venue"
},
  "geometry": {"coordinates":[13.5199804306,51.4586486816],"type":"Point"}
}