{
  "type": "Feature",
  "properties": {
    "iso:country":"DE",
    "sg:address":"Wittener Str. 47",
    "sg:city":"Schwelm",
    "sg:phone":"+49 2339/2261",
    "sg:postcode":"58332",
    "sg:province":"Nordrhein-Westfalen",
    "wof:name":"Paul Fisseler",
    "wof:placetype":"venue"
},
  "geometry": {"coordinates":[7.2897200584,51.312538147],"type":"Point"}
}