{
  "type": "Feature",
  "properties": {
    "iso:country":"DE",
    "sg:address":"Falkenweg 4",
    "sg:city":"Villmar",
    "sg:phone":"+49 6482/941500",
    "sg:postcode":"65606",
    "sg:province":"Hessen",
    "wof:name":"Gb Federal/mti Vertretungen Burkhardt",
    "wof:placetype":"venue"
},
  "geometry": {"coordinates":[8.1989707947,50.3964996338],"type":"Point"}
}