{
  "type": "Feature",
  "properties": {
    "iso:country":"DE",
    "sg:address":"Jagdweg 43",
    "sg:city":"Bonn",
    "sg:postcode":"53115",
    "sg:province":"Nordrhein-Westfalen",
    "wof:name":"Philipp Sch\u00f6nbucher Gmbh",
    "wof:placetype":"venue"
},
  "geometry": {"coordinates":[7.092317,50.720272],"type":"Point"}
}