{
  "type": "Feature",
  "properties": {
    "iso:country":"DE",
    "sg:address":"Fidicinstr. 38",
    "sg:city":"Berlin",
    "sg:phone":"+49 30/6919662",
    "sg:postcode":"10965",
    "sg:province":"Berlin",
    "wof:name":"Zur Sonne",
    "wof:placetype":"venue"
},
  "geometry": {"coordinates":[13.3890771866,52.4871940613],"type":"Point"}
}