{
  "type": "Feature",
  "properties": {
    "iso:country":"DE",
    "sg:address":"Holtenklinker Str. 138",
    "sg:city":"Hamburg",
    "sg:phone":"+49 40/7217534",
    "sg:postcode":"21029",
    "sg:province":"Hamburg",
    "wof:name":"Hoffmann Gmbh",
    "wof:placetype":"venue"
},
  "geometry": {"coordinates":[10.2282657623,53.4806060791],"type":"Point"}
}