{
  "type": "Feature",
  "properties": {
    "iso:country":"DE",
    "sg:address":"Eichenweg 2",
    "sg:city":"Eckartsberga",
    "sg:phone":"+49 34467/20296",
    "sg:postcode":"06648",
    "sg:province":"Sachsen-Anhalt",
    "wof:name":"Dr. Eckhard Richter Tierarzt",
    "wof:placetype":"venue"
},
  "geometry": {"coordinates":[11.549646,51.122417],"type":"Point"}
}