{
  "type": "Feature",
  "properties": {
    "iso:country":"DE",
    "sg:address":"Industriestr. 14/1",
    "sg:city":"M\u00fchlacker",
    "sg:postcode":"75417",
    "sg:province":"Baden-W\u00fcrttemberg",
    "wof:name":"Spannsysteme Vogt Gmbh",
    "wof:placetype":"venue"
},
  "geometry": {"coordinates":[8.849341,48.952461],"type":"Point"}
}