{
  "type": "Feature",
  "properties": {
    "iso:country":"DE",
    "sg:address":"Marktstr. 56",
    "sg:city":"Arnstein",
    "sg:phone":"+49 9363/270",
    "sg:postcode":"97450",
    "sg:province":"Bayern",
    "wof:name":"August Reitzenstein",
    "wof:placetype":"venue"
},
  "geometry": {"coordinates":[9.9699525833,49.9770622253],"type":"Point"}
}