{
  "type": "Feature",
  "properties": {
    "iso:country":"DE",
    "sg:address":"Faberweg 25",
    "sg:city":"Kirchheim",
    "sg:phone":"+49 7021/94300",
    "sg:postcode":"73230",
    "sg:province":"Baden-W\u00fcrttemberg",
    "wof:name":"Mvv Mosolf Versicherungs- Vermittlungs Gmbh",
    "wof:placetype":"venue"
},
  "geometry": {"coordinates":[9.4548654556,48.6349754333],"type":"Point"}
}