{
  "type": "Feature",
  "properties": {
    "iso:country":"DE",
    "sg:address":"Birkenwaldstr. 77",
    "sg:city":"Stuttgart",
    "sg:phone":"+49 711/2573335",
    "sg:postcode":"70191",
    "sg:province":"Baden-W\u00fcrttemberg",
    "wof:name":"Aic Leichtbau Architekten Und Ingenieure",
    "wof:placetype":"venue"
},
  "geometry": {"coordinates":[9.1759309769,48.7896270752],"type":"Point"}
}