{
  "type": "Feature",
  "properties": {
    "iso:country":"DE",
    "sg:address":"Albstr. 53",
    "sg:city":"Stuttgart",
    "sg:phone":"+49 711/761331",
    "sg:postcode":"70597",
    "sg:province":"Baden-W\u00fcrttemberg",
    "wof:name":"Ev. Pfarramt Hl.-geist-kirche",
    "wof:placetype":"venue"
},
  "geometry": {"coordinates":[9.1654367447,48.744140625],"type":"Point"}
}