{
  "type": "Feature",
  "properties": {
    "iso:country":"DE",
    "sg:address":"Horner Weg 222",
    "sg:city":"Hamburg",
    "sg:phone":"+49 40/6518068",
    "sg:postcode":"22111",
    "sg:province":"Hamburg",
    "wof:name":"Ertel",
    "wof:placetype":"venue"
},
  "geometry": {"coordinates":[10.07823,53.554604],"type":"Point"}
}