{
  "type": "Feature",
  "properties": {
    "iso:country":"DE",
    "sg:address":"Ob der Wanne 15",
    "sg:city":"Brigachtal",
    "sg:phone":"+49 7721/98920",
    "sg:postcode":"78086",
    "sg:province":"Baden-W\u00fcrttemberg",
    "wof:name":"Hubert Bucher Gmbh & Co. Kg",
    "wof:placetype":"venue"
},
  "geometry": {"coordinates":[8.4729976654,48.0077285767],"type":"Point"}
}