{
  "type": "Feature",
  "properties": {
    "iso:country":"DE",
    "sg:address":"Eckstr. 23",
    "sg:city":"St. Ingbert",
    "sg:phone":"+49 6894/5566",
    "sg:postcode":"66386",
    "sg:province":"Saarland",
    "wof:name":"Dieter Vogelgesang",
    "wof:placetype":"venue"
},
  "geometry": {"coordinates":[7.1588129997,49.2823600769],"type":"Point"}
}