{
  "type": "Feature",
  "properties": {
    "iso:country":"DE",
    "sg:address":"M\u00f6rfelder Landstr. 53",
    "sg:city":"Langen",
    "sg:phone":"+49 6103/97070",
    "sg:postcode":"63225",
    "sg:province":"Hessen",
    "wof:name":"Comp 4 U Edv-anlagen Gmbh",
    "wof:placetype":"venue"
},
  "geometry": {"coordinates":[8.648527,49.99337],"type":"Point"}
}