{
  "type": "Feature",
  "properties": {
    "iso:country":"DE",
    "sg:address":"Bahnhofstr. 24",
    "sg:city":"Bogen",
    "sg:phone":"+49 9422/805093",
    "sg:postcode":"94327",
    "sg:province":"Bayern",
    "wof:name":"Walhalla Betattungsunternehmen Gmbh",
    "wof:placetype":"venue"
},
  "geometry": {"coordinates":[12.687132,48.910213],"type":"Point"}
}