{
  "type": "Feature",
  "properties": {
    "iso:country":"DE",
    "sg:address":"Buchwaldstr. 102",
    "sg:city":"Hamburg",
    "sg:postcode":"22143",
    "sg:province":"Hamburg",
    "wof:name":"Trend Emw Gmbh",
    "wof:placetype":"venue"
},
  "geometry": {"coordinates":[10.1730508804,53.5964546204],"type":"Point"}
}