{
  "type": "Feature",
  "properties": {
    "iso:country":"DE",
    "sg:address":"Sendlinger Str. 28",
    "sg:city":"M\u00fcnchen",
    "sg:phone":"+49 89/267831",
    "sg:postcode":"80331",
    "sg:province":"Bayern",
    "wof:name":"Opg Online Programmierung Gmbh",
    "wof:placetype":"venue"
},
  "geometry": {"coordinates":[11.5697460175,48.1351280212],"type":"Point"}
}