{
  "type": "Feature",
  "properties": {
    "iso:country":"DE",
    "sg:address":"Ed 1",
    "sg:city":"Kirchham",
    "sg:postcode":"94148",
    "sg:province":"Bayern",
    "wof:name":"Haslinger Hof E. K.",
    "wof:placetype":"venue"
},
  "geometry": {"coordinates":[13.2882413864,48.350982666],"type":"Point"}
}