{
  "type": "Feature",
  "properties": {
    "iso:country":"DE",
    "sg:address":"Bockumer Str. 313",
    "sg:city":"D\u00fcsseldorf",
    "sg:phone":"+49 211/407252",
    "sg:postcode":"40489",
    "sg:province":"Nordrhein-Westfalen",
    "wof:name":"Walter Wittig Architekt",
    "wof:placetype":"venue"
},
  "geometry": {"coordinates":[6.726903,51.33033],"type":"Point"}
}