{
  "type": "Feature",
  "properties": {
    "iso:country":"DE",
    "sg:address":"Buchholzstr. 10",
    "sg:city":"Bad Emstal",
    "sg:phone":"+49 5624/925526",
    "sg:postcode":"34308",
    "sg:province":"Hessen",
    "wof:name":"Creativ-design",
    "wof:placetype":"venue"
},
  "geometry": {"coordinates":[9.2549161911,51.2414474487],"type":"Point"}
}