{
  "type": "Feature",
  "properties": {
    "iso:country":"DE",
    "sg:address":"Willy-Brandt-Platz 2",
    "sg:city":"Frankfurt",
    "sg:phone":"+49 69/2585033",
    "sg:postcode":"60311",
    "sg:province":"Hessen",
    "wof:name":"Wg Beteiligungs Gmbh",
    "wof:placetype":"venue"
},
  "geometry": {"coordinates":[8.674134,50.109203],"type":"Point"}
}