{
  "type": "Feature",
  "properties": {
    "iso:country":"DE",
    "sg:address":"Auf der Bitze 1",
    "sg:city":"Hamm",
    "sg:phone":"+49 2682/4015",
    "sg:postcode":"57577",
    "sg:province":"Rheinland-Pfalz",
    "wof:name":"Lukas",
    "wof:placetype":"venue"
},
  "geometry": {"coordinates":[7.6756520271,50.7654571533],"type":"Point"}
}