{
  "type": "Feature",
  "properties": {
    "iso:country":"DE",
    "sg:address":"Hohlweg 6",
    "sg:city":"Felde",
    "sg:phone":"+49 4340/8413",
    "sg:postcode":"24242",
    "sg:province":"Schleswig-Holstein",
    "wof:name":"Mercator Medienproduktion Wolfgang Smolka",
    "wof:placetype":"venue"
},
  "geometry": {"coordinates":[9.9422492981,54.2971305847],"type":"Point"}
}