{
  "type": "Feature",
  "properties": {
    "iso:country":"DE",
    "sg:address":"Hauptstr. 142",
    "sg:city":"Denkingen",
    "sg:phone":"+49 7424/86970",
    "sg:postcode":"78588",
    "sg:province":"Baden-W\u00fcrttemberg",
    "wof:name":"F. Fetzer",
    "wof:placetype":"venue"
},
  "geometry": {"coordinates":[8.735919,48.117786],"type":"Point"}
}