{
  "type": "Feature",
  "properties": {
    "iso:country":"DE",
    "sg:address":"Karl-Pfaff-Str. 6",
    "sg:city":"Stuttgart",
    "sg:phone":"+49 711/762451",
    "sg:postcode":"70597",
    "sg:province":"Baden-W\u00fcrttemberg",
    "wof:name":"F. Hunger",
    "wof:placetype":"venue"
},
  "geometry": {"coordinates":[9.1723203659,48.7461128235],"type":"Point"}
}