{
  "type": "Feature",
  "properties": {
    "iso:country":"DE",
    "sg:address":"Am Steppach 7",
    "sg:city":"Dei\u00dflingen",
    "sg:phone":"+49 7425/94010",
    "sg:postcode":"78652",
    "sg:province":"Baden-W\u00fcrttemberg",
    "wof:name":"Menath- Transporte Gmbh",
    "wof:placetype":"venue"
},
  "geometry": {"coordinates":[8.5915718079,48.0865516663],"type":"Point"}
}