{
  "type": "Feature",
  "properties": {
    "iso:country":"DE",
    "sg:address":"moltkestr.21",
    "sg:city":"eggenstein",
    "sg:postcode":"76344",
    "sg:province":"Baden-W\u00fcrttemberg",
    "wof:name":"Zico-online Bilder Gags Animationen",
    "wof:placetype":"venue"
},
  "geometry": {"coordinates":[8.393475,49.075642],"type":"Point"}
}