{
  "type": "Feature",
  "properties": {
    "iso:country":"DE",
    "sg:address":"Brautwiesenstr. 16",
    "sg:city":"G\u00f6rlitz",
    "sg:postcode":"02826",
    "sg:province":"Sachsen",
    "wof:name":"H & K Fenstersysteme Gmbh",
    "wof:placetype":"venue"
},
  "geometry": {"coordinates":[14.966891,51.151272],"type":"Point"}
}