{
  "type": "Feature",
  "properties": {
    "iso:country":"DE",
    "sg:address":"H\u00f6xterstr. 9",
    "sg:city":"Beverungen",
    "sg:phone":"+49 5273/6803",
    "sg:postcode":"37688",
    "sg:province":"Nordrhein-Westfalen",
    "wof:name":"J. Rode",
    "wof:placetype":"venue"
},
  "geometry": {"coordinates":[9.311029,51.682358],"type":"Point"}
}