{
  "type": "Feature",
  "properties": {
    "iso:country":"DE",
    "sg:address":"Industriestr. 32",
    "sg:city":"Neunkirchen",
    "sg:phone":"+49 9153/92790",
    "sg:postcode":"91233",
    "sg:province":"Bayern",
    "wof:name":"\u00dcbler Transport Gmbh",
    "wof:placetype":"venue"
},
  "geometry": {"coordinates":[11.3443536758,49.5229721069],"type":"Point"}
}