{
  "type": "Feature",
  "properties": {
    "iso:country":"DE",
    "sg:address":"Bahnhofstr. 2",
    "sg:city":"Kuchen",
    "sg:phone":"+49 4973/3181221",
    "sg:postcode":"73329",
    "sg:province":"Baden-W\u00fcrttemberg",
    "wof:name":"Kreissparkasse G\u00f6ppingen",
    "wof:placetype":"venue"
},
  "geometry": {"coordinates":[9.799648,48.636185],"type":"Point"}
}