{
  "type": "Feature",
  "properties": {
    "iso:country":"DE",
    "sg:address":"Goldsternstr.",
    "sg:city":"Leipzig",
    "sg:phone":"+49 341/2513938",
    "sg:postcode":"04329",
    "sg:province":"Sachsen",
    "wof:name":"B\u00f6se & Ruder",
    "wof:placetype":"venue"
},
  "geometry": {"coordinates":[12.4568367004,51.3546867371],"type":"Point"}
}