{
  "type": "Feature",
  "properties": {
    "iso:country":"DE",
    "sg:address":"Verb\u00e4ndehaus",
    "sg:city":"Baden-Baden",
    "sg:phone":"+49 172 7187872",
    "sg:postcode":"76530",
    "sg:province":"Baden-W\u00fcrttemberg",
    "wof:name":"Rechtsanwalt Alexander R. Zumkeller",
    "wof:placetype":"venue"
},
  "geometry": {"coordinates":[8.240915,48.762707],"type":"Point"}
}