{
  "type": "Feature",
  "properties": {
    "iso:country":"DE",
    "sg:address":"Forsthaus K\u00e4hnert",
    "sg:city":"Grabow",
    "sg:phone":"+49 3921/94157",
    "sg:postcode":"39291",
    "sg:province":"Sachsen-Anhalt",
    "wof:name":"Bratto Von Boehmer",
    "wof:placetype":"venue"
},
  "geometry": {"coordinates":[11.9717197418,52.2268486023],"type":"Point"}
}