{
  "type": "Feature",
  "properties": {
    "iso:country":"DE",
    "sg:address":"Untere Leiten 1",
    "sg:city":"Baierbrunn",
    "sg:phone":"+49 89/79360387",
    "sg:postcode":"82065",
    "sg:province":"Bayern",
    "wof:name":"Poolcap Hans-j\u00f6rg Regul",
    "wof:placetype":"venue"
},
  "geometry": {"coordinates":[11.4971199036,48.0301704407],"type":"Point"}
}