{
  "type": "Feature",
  "properties": {
    "iso:country":"DE",
    "sg:address":"Schimmelbuschstr. 4",
    "sg:city":"Erkrath",
    "sg:phone":"+49 2104/35627",
    "sg:postcode":"40699",
    "sg:province":"Nordrhein-Westfalen",
    "wof:name":"A. Rothfuss",
    "wof:placetype":"venue"
},
  "geometry": {"coordinates":[6.9451541901,51.2150192261],"type":"Point"}
}