{
  "type": "Feature",
  "properties": {
    "iso:country":"DE",
    "sg:address":"Pforzheimer Str. 27",
    "sg:city":"Karlsruhe",
    "sg:phone":"+49 721/402219",
    "sg:postcode":"76227",
    "sg:province":"Baden-W\u00fcrttemberg",
    "wof:name":"Durlacher Fitness-treff",
    "wof:placetype":"venue"
},
  "geometry": {"coordinates":[8.4702033997,49.0045814514],"type":"Point"}
}