{
  "type": "Feature",
  "properties": {
    "iso:country":"DE",
    "sg:address":"Elbestr. 10",
    "sg:city":"Marl",
    "sg:postcode":"45768",
    "sg:province":"Nordrhein-Westfalen",
    "wof:name":"Hydrosave Gmbh",
    "wof:placetype":"venue"
},
  "geometry": {"coordinates":[7.040065,51.659149],"type":"Point"}
}