{
  "type": "Feature",
  "properties": {
    "iso:country":"DE",
    "sg:address":"Bergmannstr. 13",
    "sg:city":"Steinfeld",
    "sg:phone":"+49 4443/4904",
    "sg:postcode":"49439",
    "sg:province":"Niedersachsen",
    "wof:name":"Gebr. Witte Bauschlosserei Und Bedachung Gmbh",
    "wof:placetype":"venue"
},
  "geometry": {"coordinates":[8.20873,52.596218],"type":"Point"}
}