{
  "type": "Feature",
  "properties": {
    "iso:country":"DE",
    "sg:address":"Bagelstr. 105",
    "sg:city":"D\u00fcsseldorf",
    "sg:phone":"+49 211/484307",
    "sg:postcode":"40479",
    "sg:province":"Nordrhein-Westfalen",
    "wof:name":"Hausverwaltung & Hausmeisterservice D\u00fcsseldorf",
    "wof:placetype":"venue"
},
  "geometry": {"coordinates":[6.7909722328,51.2340812683],"type":"Point"}
}