{
  "type": "Feature",
  "properties": {
    "iso:country":"DE",
    "sg:address":"Kurstr. 14 A",
    "sg:city":"Brandenburg",
    "sg:phone":"+49 3381/302216",
    "sg:postcode":"14776",
    "sg:province":"Brandenburg",
    "wof:name":"U. Krieg Architekt",
    "wof:placetype":"venue"
},
  "geometry": {"coordinates":[12.558875,52.408108],"type":"Point"}
}