{
  "type": "Feature",
  "properties": {
    "iso:country":"DE",
    "sg:address":"Regensburger Str. 81",
    "sg:city":"Weiden",
    "sg:phone":"+49 961/46939",
    "sg:postcode":"92637",
    "sg:province":"Bayern",
    "wof:name":"B & E Aktuell Polsterm\u00f6bel Gmbh",
    "wof:placetype":"venue"
},
  "geometry": {"coordinates":[12.1430778503,49.6551094055],"type":"Point"}
}