{
  "type": "Feature",
  "properties": {
    "iso:country":"DE",
    "sg:address":"Gr\u00f6nerstr. 25",
    "sg:city":"Ludwigsburg",
    "sg:phone":"+49 7141/47420",
    "sg:postcode":"71636",
    "sg:province":"Baden-W\u00fcrttemberg",
    "wof:name":"Sound Gastronomie- Gesellschaft Mbh",
    "wof:placetype":"venue"
},
  "geometry": {"coordinates":[9.16929245,48.8928604126],"type":"Point"}
}