{
  "type": "Feature",
  "properties": {
    "iso:country":"DE",
    "sg:address":"Virchowstr.20",
    "sg:city":"Potsdam",
    "sg:phone":"+49 331",
    "sg:postcode":"14482",
    "sg:province":"Brandenburg",
    "wof:name":"Blue Stonehenge",
    "wof:placetype":"venue"
},
  "geometry": {"coordinates":[13.118496,52.399067],"type":"Point"}
}