{
  "type": "Feature",
  "properties": {
    "iso:country":"DE",
    "sg:address":"Klusriede 22",
    "sg:city":"Langenhagen",
    "sg:phone":"+49 4951/1726720",
    "sg:postcode":"30851",
    "sg:province":"Niedersachsen",
    "wof:name":"Kvt Canespa Gmbh",
    "wof:placetype":"venue"
},
  "geometry": {"coordinates":[9.7391729355,52.4278793335],"type":"Point"}
}