{
  "type": "Feature",
  "properties": {
    "iso:country":"DE",
    "sg:address":"Kaiser-Wilhelm-Platz 6",
    "sg:city":"Essen",
    "sg:phone":"+49 201/8516680",
    "sg:postcode":"45276",
    "sg:province":"Nordrhein-Westfalen",
    "wof:name":"Melza Hallen Gmbh",
    "wof:placetype":"venue"
},
  "geometry": {"coordinates":[7.07714,51.448971],"type":"Point"}
}