{
  "type": "Feature",
  "properties": {
    "iso:country":"DE",
    "sg:address":"K\u00f6nigsplatz 36b",
    "sg:city":"Kassel",
    "sg:phone":"+49 561/102230",
    "sg:postcode":"34117",
    "sg:province":"Hessen",
    "wof:name":"Peter Marzinkewitsch Krankengymnast",
    "wof:placetype":"venue"
},
  "geometry": {"coordinates":[9.498596,51.31525],"type":"Point"}
}