{
  "type": "Feature",
  "properties": {
    "iso:country":"DE",
    "sg:address":"Lindenallee 36",
    "sg:city":"Bad Orb",
    "sg:phone":"+49 6052/91490",
    "sg:postcode":"63619",
    "sg:province":"Hessen",
    "wof:name":"Hotel Rheinland Fam. G\u00f6bb",
    "wof:placetype":"venue"
},
  "geometry": {"coordinates":[9.3504314423,50.2177734375],"type":"Point"}
}