{
  "type": "Feature",
  "properties": {
    "iso:country":"DE",
    "sg:address":"Am Bredberg 17",
    "sg:city":"Bissendorf",
    "sg:phone":"+49 5402/8418",
    "sg:postcode":"49143",
    "sg:province":"Niedersachsen",
    "wof:name":"Bernd R\u00f6\u00dfler",
    "wof:placetype":"venue"
},
  "geometry": {"coordinates":[8.2363004684,52.2809295654],"type":"Point"}
}