{
  "type": "Feature",
  "properties": {
    "iso:country":"DE",
    "sg:address":"Obere Str. 9a",
    "sg:city":"Gleichen",
    "sg:phone":"+49 5508/1483",
    "sg:postcode":"37130",
    "sg:province":"Niedersachsen",
    "wof:name":"J\u00f6rg Bolle Architekt",
    "wof:placetype":"venue"
},
  "geometry": {"coordinates":[10.083964,51.44746],"type":"Point"}
}