{
  "type": "Feature",
  "properties": {
    "iso:country":"DE",
    "sg:address":"Stihlstr. 5",
    "sg:city":"Tengen",
    "sg:phone":"+49 4977/3692390",
    "sg:postcode":"78250",
    "sg:province":"Baden-W\u00fcrttemberg",
    "wof:name":"Andreas Stihl Ag & Co. Kg",
    "wof:placetype":"venue"
},
  "geometry": {"coordinates":[8.63124,47.785671],"type":"Point"}
}