{
  "type": "Feature",
  "properties": {
    "iso:country":"DE",
    "sg:address":"Altenha\u00dflauer Weg 1",
    "sg:city":"Gelnhausen",
    "sg:phone":"+49 4960/5161061",
    "sg:postcode":"63571",
    "sg:province":"Hessen",
    "wof:name":"Haas Getr\u00c4nke",
    "wof:placetype":"venue"
},
  "geometry": {"coordinates":[9.174188,50.188042],"type":"Point"}
}