{
  "type": "Feature",
  "properties": {
    "iso:country":"DE",
    "sg:address":"Wandsbeker Allee 73",
    "sg:city":"Hamburg",
    "sg:phone":"+49 40/6529927",
    "sg:postcode":"22041",
    "sg:province":"Hamburg",
    "wof:name":"Elchstube",
    "wof:placetype":"venue"
},
  "geometry": {"coordinates":[10.0700826645,53.5741386414],"type":"Point"}
}