{
  "type": "Feature",
  "properties": {
    "iso:country":"DE",
    "sg:address":"Inninger Str. 100",
    "sg:city":"Augsburg",
    "sg:phone":"+49 821/82082",
    "sg:postcode":"86179",
    "sg:province":"Bayern",
    "wof:name":"Tennis-center Augsburg-s\u00fcd Max W\u00fcnschig Gmbh & Co.",
    "wof:placetype":"venue"
},
  "geometry": {"coordinates":[10.8864078522,48.3094100952],"type":"Point"}
}