{
  "type": "Feature",
  "properties": {
    "iso:country":"DE",
    "sg:address":"Falkensteiner Str. 4",
    "sg:city":"Hammerbr\u00fccke",
    "sg:phone":"+49 37465/6110",
    "sg:postcode":"08269",
    "sg:province":"Sachsen",
    "wof:name":"Wolfgang Ge\u00dfner",
    "wof:placetype":"venue"
},
  "geometry": {"coordinates":[12.413628,50.437397],"type":"Point"}
}