{
  "type": "Feature",
  "properties": {
    "iso:country":"DE",
    "sg:address":"Am Lachengraben 5",
    "sg:city":"Dreieich",
    "sg:phone":"+49 4961/0398030",
    "sg:postcode":"63303",
    "sg:province":"Hessen",
    "wof:name":"Copypoint Kopiergeraete Gmbh",
    "wof:placetype":"venue"
},
  "geometry": {"coordinates":[8.734380722,50.0001792908],"type":"Point"}
}