{
  "type": "Feature",
  "properties": {
    "iso:country":"DE",
    "sg:address":"Ohlhofbreite 38b",
    "sg:city":"Goslar",
    "sg:phone":"+49 5321/42098",
    "sg:postcode":"38642",
    "sg:province":"Niedersachsen",
    "wof:name":"Massagepraxis Ohlhof",
    "wof:placetype":"venue"
},
  "geometry": {"coordinates":[10.459888,51.924026],"type":"Point"}
}