{
  "type": "Feature",
  "properties": {
    "iso:country":"DE",
    "sg:address":"Riehlstr. 12",
    "sg:city":"Berlin",
    "sg:phone":"+49 30/3267580",
    "sg:postcode":"14057",
    "sg:province":"Berlin",
    "wof:name":"Katrin Abel Steuerberaterin",
    "wof:placetype":"venue"
},
  "geometry": {"coordinates":[13.2856254578,52.5081939697],"type":"Point"}
}