{
  "type": "Feature",
  "properties": {
    "iso:country":"DE",
    "sg:address":"D\u00fcbener Landstr.",
    "sg:city":"Leipzig",
    "sg:postcode":"04129",
    "sg:province":"Sachsen",
    "wof:name":"Beteiligungsges. Quick-mix Spezial Trockenm\u00f6rtel",
    "wof:placetype":"venue"
},
  "geometry": {"coordinates":[12.38732,51.380539],"type":"Point"}
}