{
  "type": "Feature",
  "properties": {
    "iso:country":"DE",
    "sg:address":"Fritzbruch 20",
    "sg:city":"Viersen",
    "sg:phone":"+49 2162/970434",
    "sg:postcode":"41749",
    "sg:province":"Nordrhein-Westfalen",
    "wof:name":"Hans-j\u00fcrgen Dornbusch",
    "wof:placetype":"venue"
},
  "geometry": {"coordinates":[6.372709,51.304123],"type":"Point"}
}