{
  "type": "Feature",
  "properties": {
    "iso:country":"DE",
    "sg:address":"Gerresheimer Str. 14",
    "sg:city":"D\u00fcsseldorf",
    "sg:postcode":"40211",
    "sg:province":"Nordrhein-Westfalen",
    "wof:name":"Greiserpackung High Profit And More Gmbh",
    "wof:placetype":"venue"
},
  "geometry": {"coordinates":[6.7935471535,51.2278823853],"type":"Point"}
}