{
  "type": "Feature",
  "properties": {
    "iso:country":"DE",
    "sg:address":"Glinder Str. 1",
    "sg:city":"Hamburg",
    "sg:postcode":"22117",
    "sg:province":"Hamburg",
    "wof:name":"Fegro",
    "wof:placetype":"venue"
},
  "geometry": {"coordinates":[10.128153801,53.5470314026],"type":"Point"}
}