{
  "type": "Feature",
  "properties": {
    "iso:country":"DE",
    "sg:address":"Fennastr. 23",
    "sg:city":"Nordhorn",
    "sg:phone":"+49 5921/12187",
    "sg:postcode":"48529",
    "sg:province":"Niedersachsen",
    "wof:name":"Bernd Grommel",
    "wof:placetype":"venue"
},
  "geometry": {"coordinates":[7.0633111,52.4115066528],"type":"Point"}
}