{
  "type": "Feature",
  "properties": {
    "iso:country":"DE",
    "sg:address":"Justus-von-Liebig-Str. 13",
    "sg:city":"Schwarzheide",
    "sg:phone":"+49 35752/9230",
    "sg:postcode":"01987",
    "sg:province":"Brandenburg",
    "wof:name":"Liesk Baustoffe Gmbh",
    "wof:placetype":"venue"
},
  "geometry": {"coordinates":[13.8187866211,51.4731941223],"type":"Point"}
}