{
  "type": "Feature",
  "properties": {
    "iso:country":"DE",
    "sg:address":"Fulerumer Str. 15",
    "sg:city":"Essen",
    "sg:phone":"+49 201/717801",
    "sg:postcode":"45149",
    "sg:province":"Nordrhein-Westfalen",
    "wof:name":"Helmut Kreuselberg",
    "wof:placetype":"venue"
},
  "geometry": {"coordinates":[6.965484,51.436153],"type":"Point"}
}