{
  "type": "Feature",
  "properties": {
    "iso:country":"DE",
    "sg:address":"Im Wiesengrund 4",
    "sg:city":"Lindlar",
    "sg:phone":"+49 2266/8640",
    "sg:postcode":"51789",
    "sg:province":"Nordrhein-Westfalen",
    "wof:name":"Ursula Jutz",
    "wof:placetype":"venue"
},
  "geometry": {"coordinates":[7.3897738457,51.0122566223],"type":"Point"}
}