{
  "type": "Feature",
  "properties": {
    "iso:country":"DE",
    "sg:address":"Ismaninger Str. 59",
    "sg:city":"M\u00fcnchen",
    "sg:phone":"+49 89/47084521",
    "sg:postcode":"81675",
    "sg:province":"Bayern",
    "wof:name":"Jan O. Leisner Rechtsanwalt",
    "wof:placetype":"venue"
},
  "geometry": {"coordinates":[11.6010808945,48.1424827576],"type":"Point"}
}