{
  "type": "Feature",
  "properties": {
    "iso:country":"DE",
    "sg:address":"R 7 25",
    "sg:city":"Mannheim",
    "sg:phone":"+49 621/22522",
    "sg:postcode":"68161",
    "sg:province":"Baden-W\u00fcrttemberg",
    "wof:name":"Lameygarten",
    "wof:placetype":"venue"
},
  "geometry": {"coordinates":[8.4667854309,49.4865112305],"type":"Point"}
}