{
  "type": "Feature",
  "properties": {
    "iso:country":"DE",
    "sg:address":"Nordstr. 1",
    "sg:city":"Kamen",
    "sg:phone":"+49 2307/13988",
    "sg:postcode":"59174",
    "sg:province":"Nordrhein-Westfalen",
    "wof:name":"Pizzeria Piccola",
    "wof:placetype":"venue"
},
  "geometry": {"coordinates":[7.6653151512,51.5932121277],"type":"Point"}
}