{
  "type": "Feature",
  "properties": {
    "iso:country":"DE",
    "sg:address":"Bahnhofstr. 5",
    "sg:city":"M\u00f6ckm\u00fchl",
    "sg:phone":"+49 6298/5356",
    "sg:postcode":"74219",
    "sg:province":"Baden-W\u00fcrttemberg",
    "wof:name":"Franz Hartmann Ing.-b\u00fcro",
    "wof:placetype":"venue"
},
  "geometry": {"coordinates":[9.3583650589,49.3229751587],"type":"Point"}
}