{
  "type": "Feature",
  "properties": {
    "iso:country":"DE",
    "sg:address":"Brahmsstr. 2",
    "sg:city":"Emsdetten",
    "sg:phone":"+49 2572/3962",
    "sg:postcode":"48282",
    "sg:province":"Nordrhein-Westfalen",
    "wof:name":"Heinrich Niehsing",
    "wof:placetype":"venue"
},
  "geometry": {"coordinates":[7.5252,52.1637],"type":"Point"}
}