{
  "type": "Feature",
  "properties": {
    "iso:country":"DE",
    "sg:address":"Leidenbergstr. 8",
    "sg:city":"H\u00fcnfelden",
    "sg:phone":"+49 6438/2283",
    "sg:postcode":"65597",
    "sg:province":"Hessen",
    "wof:name":"Dr. Hans-joachim Schlesies Tierarzt",
    "wof:placetype":"venue"
},
  "geometry": {"coordinates":[8.1617326736,50.3106956482],"type":"Point"}
}