{
  "type": "Feature",
  "properties": {
    "iso:country":"DE",
    "sg:address":"Staubenthaler Str. 31",
    "sg:city":"Wuppertal",
    "sg:phone":"+49 202/467208",
    "sg:postcode":"42369",
    "sg:province":"Nordrhein-Westfalen",
    "wof:name":"Heinz Prinz Bauschlosserei",
    "wof:placetype":"venue"
},
  "geometry": {"coordinates":[7.1936779022,51.2324829102],"type":"Point"}
}