{
  "type": "Feature",
  "properties": {
    "iso:country":"DE",
    "sg:address":"Reventloustr. 13",
    "sg:city":"Laboe",
    "sg:phone":"+49 4343/7472",
    "sg:postcode":"24235",
    "sg:province":"Schleswig-Holstein",
    "wof:name":"Arko Gmbh",
    "wof:placetype":"venue"
},
  "geometry": {"coordinates":[10.2201490402,54.4050941467],"type":"Point"}
}