{
  "type": "Feature",
  "properties": {
    "iso:country":"DE",
    "sg:address":"Weinstr 130",
    "sg:city":"Kallstadt",
    "sg:phone":"+49 6322/63927",
    "sg:postcode":"67169",
    "sg:province":"Rheinland-Pfalz",
    "wof:name":"Sekt- Und Weingut Stauch",
    "wof:placetype":"venue"
},
  "geometry": {"coordinates":[8.1752443314,49.4945487976],"type":"Point"}
}