{
  "type": "Feature",
  "properties": {
    "iso:country":"DE",
    "sg:address":"Messerschmittring 1",
    "sg:city":"K\u00f6nigsbrunn",
    "sg:phone":"+49 8231/34424",
    "sg:postcode":"86343",
    "sg:province":"Bayern",
    "wof:name":"Christian Kragler",
    "wof:placetype":"venue"
},
  "geometry": {"coordinates":[10.8769884109,48.2539596558],"type":"Point"}
}