{
  "type": "Feature",
  "properties": {
    "iso:country":"DE",
    "sg:address":"Triniusstr. 5",
    "sg:city":"Arnstadt",
    "sg:phone":"+49 3628/603627",
    "sg:postcode":"99310",
    "sg:province":"Th\u00fcringen",
    "wof:name":"Karl-heinz Gr\u00e4ssler",
    "wof:placetype":"venue"
},
  "geometry": {"coordinates":[10.937093,50.836628],"type":"Point"}
}