{
  "type": "Feature",
  "properties": {
    "iso:country":"DE",
    "sg:address":"Vierschillingsberg 21",
    "sg:city":"Pl\u00f6n",
    "sg:phone":"+49 4522/509337",
    "sg:postcode":"24306",
    "sg:province":"Schleswig-Holstein",
    "wof:name":"Landesverein F\u00fcr Innere Mission",
    "wof:placetype":"venue"
},
  "geometry": {"coordinates":[10.4208507538,54.1611213684],"type":"Point"}
}