{
  "type": "Feature",
  "properties": {
    "iso:country":"DE",
    "sg:address":"Pappelallee 7",
    "sg:city":"Niederp\u00f6llnitz",
    "sg:postcode":"07570",
    "sg:province":"Th\u00fcringen",
    "wof:name":"Dawatec Gmbh",
    "wof:placetype":"venue"
},
  "geometry": {"coordinates":[11.957311,50.753819],"type":"Point"}
}