{
  "type": "Feature",
  "properties": {
    "iso:country":"DE",
    "sg:address":"Oranienstr. 19",
    "sg:city":"Dillenburg",
    "sg:phone":"+49 2771/23662",
    "sg:postcode":"35683",
    "sg:province":"Hessen",
    "wof:name":"Techno-handels-gmbh",
    "wof:placetype":"venue"
},
  "geometry": {"coordinates":[8.286455,50.741745],"type":"Point"}
}