{
  "type": "Feature",
  "properties": {
    "iso:country":"DE",
    "sg:address":"Hahner Str.",
    "sg:city":"Reichshof",
    "sg:phone":"+49 2297/7475",
    "sg:postcode":"51580",
    "sg:province":"Nordrhein-Westfalen",
    "wof:name":"Gmv Gokart Motorsport Verleih- Und",
    "wof:placetype":"venue"
},
  "geometry": {"coordinates":[7.7735681534,50.9632263184],"type":"Point"}
}