{
  "type": "Feature",
  "properties": {
    "iso:country":"DE",
    "sg:address":"Wetzbach 27a",
    "sg:city":"Zwingenberg",
    "sg:phone":"+49 4962/5178188",
    "sg:postcode":"64673",
    "sg:province":"Hessen",
    "wof:name":"Thomas Kohl",
    "wof:placetype":"venue"
},
  "geometry": {"coordinates":[8.6153745651,49.7240715027],"type":"Point"}
}