{
  "type": "Feature",
  "properties": {
    "iso:country":"DE",
    "sg:address":"Egerl\u00e4nder Str. 33",
    "sg:city":"Ro\u00dfdorf",
    "sg:phone":"+49 6154/9421",
    "sg:postcode":"64380",
    "sg:province":"Hessen",
    "wof:name":"Sigrun Irmisch",
    "wof:placetype":"venue"
},
  "geometry": {"coordinates":[8.7532901764,49.865020752],"type":"Point"}
}