{
  "type": "Feature",
  "properties": {
    "iso:country":"DE",
    "sg:address":"Sodentalstr. 54",
    "sg:city":"Sulzbach",
    "sg:phone":"+49 4960/286778",
    "sg:postcode":"63834",
    "sg:province":"Bayern",
    "wof:name":"Raiffeisenbank Leidersbach Eg",
    "wof:placetype":"venue"
},
  "geometry": {"coordinates":[9.206579,49.922043],"type":"Point"}
}