{
  "type": "Feature",
  "properties": {
    "iso:country":"DE",
    "sg:address":"Lautertalstr. 4/1",
    "sg:city":"St. Johann",
    "sg:phone":"+49 7122/9255",
    "sg:postcode":"72813",
    "sg:province":"Baden-W\u00fcrttemberg",
    "wof:name":"Helmut Ostertag Gmbh",
    "wof:placetype":"venue"
},
  "geometry": {"coordinates":[9.378434,48.430492],"type":"Point"}
}