{
  "type": "Feature",
  "properties": {
    "iso:country":"DE",
    "sg:address":"Wenigenjenaer Ufer 13",
    "sg:city":"Jena",
    "sg:phone":"+49 3641/445348",
    "sg:postcode":"07749",
    "sg:province":"Th\u00fcringen",
    "wof:name":"Klotzke Und Feil",
    "wof:placetype":"venue"
},
  "geometry": {"coordinates":[11.5963582993,50.9333457947],"type":"Point"}
}