{
  "type": "Feature",
  "properties": {
    "iso:country":"DE",
    "sg:address":"Leusbergstr. 46",
    "sg:city":"Recklinghausen",
    "sg:phone":"+49 2361/63159",
    "sg:postcode":"45663",
    "sg:province":"Nordrhein-Westfalen",
    "wof:name":"Hans Look",
    "wof:placetype":"venue"
},
  "geometry": {"coordinates":[7.21421,51.564274],"type":"Point"}
}