{
  "type": "Feature",
  "properties": {
    "iso:country":"DE",
    "sg:address":"Haus am Galgenberg",
    "sg:city":"Schotten",
    "sg:phone":"+49 6044/2036",
    "sg:postcode":"63679",
    "sg:province":"Hessen",
    "wof:name":"Pr-agentur G. H. Wenzel",
    "wof:placetype":"venue"
},
  "geometry": {"coordinates":[9.1209583282,50.4993782043],"type":"Point"}
}