{
  "type": "Feature",
  "properties": {
    "iso:country":"DE",
    "sg:address":"Fr\u00f6hliche-Mann-Str. 3 b",
    "sg:city":"Suhl",
    "sg:phone":"+49 3681/44000",
    "sg:postcode":"98528",
    "sg:province":"Th\u00fcringen",
    "wof:name":"Datenverarbeitungszentrum Suhl Gmbh",
    "wof:placetype":"venue"
},
  "geometry": {"coordinates":[10.699624,50.63356],"type":"Point"}
}