{
  "type": "Feature",
  "properties": {
    "iso:country":"DE",
    "sg:address":"Niedergaul 19A",
    "sg:city":"Wipperf\u00fcrth",
    "sg:phone":"+49 2267/880851",
    "sg:postcode":"51688",
    "sg:province":"Nordrhein-Westfalen",
    "wof:name":"M. Braun Anlageberater",
    "wof:placetype":"venue"
},
  "geometry": {"coordinates":[7.4125599861,51.1065597534],"type":"Point"}
}