{
  "type": "Feature",
  "properties": {
    "iso:country":"DE",
    "sg:address":"Juliusstr. 9",
    "sg:city":"Essen",
    "sg:phone":"+49 201/234713",
    "sg:postcode":"45128",
    "sg:province":"Nordrhein-Westfalen",
    "wof:name":"Egon Echt",
    "wof:placetype":"venue"
},
  "geometry": {"coordinates":[7.012699,51.448536],"type":"Point"}
}