{
  "type": "Feature",
  "properties": {
    "iso:country":"DE",
    "sg:address":"Freiheitsallee 22",
    "sg:city":"Crivitz",
    "sg:phone":"+49 3863/502435",
    "sg:postcode":"19089",
    "sg:province":"Mecklenburg-Vorpommern",
    "wof:name":"Haus Am Crivitzer See Ggmbh",
    "wof:placetype":"venue"
},
  "geometry": {"coordinates":[11.639793,53.573681],"type":"Point"}
}