{
  "type": "Feature",
  "properties": {
    "iso:country":"DE",
    "sg:address":"Reepsholter Hauptstr.",
    "sg:city":"Friedeburg",
    "sg:phone":"+49 4468/942122",
    "sg:postcode":"26446",
    "sg:province":"Niedersachsen",
    "wof:name":"Marianne Schweppe",
    "wof:placetype":"venue"
},
  "geometry": {"coordinates":[7.8321890831,53.4930038452],"type":"Point"}
}