{
  "type": "Feature",
  "properties": {
    "iso:country":"DE",
    "sg:address":"Dorfstr. 55",
    "sg:city":"Rodewald",
    "sg:phone":"+49 5074/1650",
    "sg:postcode":"31637",
    "sg:province":"Niedersachsen",
    "wof:name":"G. Honsel Gmbh",
    "wof:placetype":"venue"
},
  "geometry": {"coordinates":[9.4786806107,52.6743125916],"type":"Point"}
}