{
  "type": "Feature",
  "properties": {
    "iso:country":"DE",
    "sg:address":"Benderstr. 103",
    "sg:city":"D\u00fcsseldorf",
    "sg:phone":"+49 211/286866",
    "sg:postcode":"40625",
    "sg:province":"Nordrhein-Westfalen",
    "wof:name":"F. R. Foerster",
    "wof:placetype":"venue"
},
  "geometry": {"coordinates":[6.849482,51.238762],"type":"Point"}
}