{
  "type": "Feature",
  "properties": {
    "iso:country":"DE",
    "sg:address":"H\u00f6rlasreuth 10",
    "sg:city":"Creu\u00dfen",
    "sg:phone":"+49 9270/1664",
    "sg:postcode":"95473",
    "sg:province":"Bayern",
    "wof:name":"Johann Kn\u00f6rrer",
    "wof:placetype":"venue"
},
  "geometry": {"coordinates":[11.5455522537,49.8466796875],"type":"Point"}
}