{
  "type": "Feature",
  "properties": {
    "iso:country":"DE",
    "sg:address":"Br\u00fchler Str. 1",
    "sg:city":"Erftstadt",
    "sg:phone":"+49 2235/2567",
    "sg:postcode":"50374",
    "sg:province":"Nordrhein-Westfalen",
    "wof:name":"Johannes Hemmersbach",
    "wof:placetype":"venue"
},
  "geometry": {"coordinates":[6.8192038536,50.81615448],"type":"Point"}
}