{
  "type": "Feature",
  "properties": {
    "iso:country":"DE",
    "sg:address":"Josefstr. 5",
    "sg:city":"Gladbeck",
    "sg:phone":"+49 2043/42304",
    "sg:postcode":"45966",
    "sg:province":"Nordrhein-Westfalen",
    "wof:name":"Ev. Pfarramt Rentfort",
    "wof:placetype":"venue"
},
  "geometry": {"coordinates":[6.9566140175,51.5753059387],"type":"Point"}
}