{
  "type": "Feature",
  "properties": {
    "iso:country":"DE",
    "sg:address":"Dorfstr.",
    "sg:city":"G\u00f6rsdorf",
    "sg:postcode":"15936",
    "sg:province":"Brandenburg",
    "wof:name":"Agrargenossenschaft Eg G\u00f6rsdorf",
    "wof:placetype":"venue"
},
  "geometry": {"coordinates":[13.42601,51.869366],"type":"Point"}
}