{
  "type": "Feature",
  "properties": {
    "iso:country":"DE",
    "sg:address":"Deufringer Str. 13",
    "sg:city":"G\u00e4rtringen",
    "sg:phone":"+49 7034/20600",
    "sg:postcode":"71116",
    "sg:province":"Baden-W\u00fcrttemberg",
    "wof:name":"Restaurant Am Weingarten",
    "wof:placetype":"venue"
},
  "geometry": {"coordinates":[8.893037796,48.642906189],"type":"Point"}
}