{
  "type": "Feature",
  "properties": {
    "iso:country":"DE",
    "sg:address":"Gr\u00fcnlingweg 3",
    "sg:city":"Wiesloch",
    "sg:phone":"+49 6222/8942",
    "sg:postcode":"69168",
    "sg:province":"Baden-W\u00fcrttemberg",
    "wof:name":"Prei\u00df & Schindler Hoch- Und Holzbau Gmbh",
    "wof:placetype":"venue"
},
  "geometry": {"coordinates":[8.6738758087,49.2830581665],"type":"Point"}
}