{
  "type": "Feature",
  "properties": {
    "iso:country":"DE",
    "sg:address":"Industriegel\u00e4nde",
    "sg:city":"Saarwellingen",
    "sg:phone":"+49 6838/6660",
    "sg:postcode":"66793",
    "sg:province":"Saarland",
    "wof:name":"Holzbau Schneider Gmbh",
    "wof:placetype":"venue"
},
  "geometry": {"coordinates":[6.8075799942,49.353515625],"type":"Point"}
}