{
  "type": "Feature",
  "properties": {
    "iso:country":"DE",
    "sg:address":"Waldstr. 67",
    "sg:city":"Reinheim",
    "sg:phone":"+49 6162/5259",
    "sg:postcode":"64354",
    "sg:province":"Hessen",
    "wof:name":"Ursula K\u00f6rner Krankengymnastin",
    "wof:placetype":"venue"
},
  "geometry": {"coordinates":[8.824758,49.82222],"type":"Point"}
}