{
  "type": "Feature",
  "properties": {
    "iso:country":"DE",
    "sg:address":"Mozartstr. 16",
    "sg:city":"Herrenberg",
    "sg:phone":"+49 7032/21423",
    "sg:postcode":"71083",
    "sg:province":"Baden-W\u00fcrttemberg",
    "wof:name":"Ev. Pfarramt Ost",
    "wof:placetype":"venue"
},
  "geometry": {"coordinates":[8.8837518692,48.5950927734],"type":"Point"}
}