{
  "type": "Feature",
  "properties": {
    "iso:country":"DE",
    "sg:address":"Surkampstr. 72a",
    "sg:city":"Gelsenkirchen",
    "sg:phone":"+49 209/798058",
    "sg:postcode":"45891",
    "sg:province":"Nordrhein-Westfalen",
    "wof:name":"Alpha-allgemeine Und Psychia- Trische Hauskrankenpflege",
    "wof:placetype":"venue"
},
  "geometry": {"coordinates":[7.079201,51.55965],"type":"Point"}
}