{
  "type": "Feature",
  "properties": {
    "iso:country":"DE",
    "sg:address":"Schlo\u00dfstr. 33",
    "sg:city":"Berlin",
    "sg:phone":"+49 30/40503300",
    "sg:postcode":"13467",
    "sg:province":"Berlin",
    "wof:name":"B\u00f6ttcher Immobilien Kg",
    "wof:placetype":"venue"
},
  "geometry": {"coordinates":[13.3095397949,52.6180610657],"type":"Point"}
}