{
  "type": "Feature",
  "properties": {
    "iso:country":"DE",
    "sg:address":"Hohenzollernstr. 11",
    "sg:city":"Velbert",
    "sg:phone":"+49 2051/319609",
    "sg:postcode":"42551",
    "sg:province":"Nordrhein-Westfalen",
    "wof:name":"Bistro Le Premier",
    "wof:placetype":"venue"
},
  "geometry": {"coordinates":[7.0463490486,51.3439331055],"type":"Point"}
}