{
  "type": "Feature",
  "properties": {
    "iso:country":"DE",
    "sg:address":"Lindenweg 6",
    "sg:city":"Witten",
    "sg:phone":"+49 2302/33029",
    "sg:postcode":"58452",
    "sg:province":"Nordrhein-Westfalen",
    "wof:name":"Dr. K\u00f6llner Oberfl\u00e4chenschutz Gmbh",
    "wof:placetype":"venue"
},
  "geometry": {"coordinates":[7.328677,51.426052],"type":"Point"}
}