{
  "type": "Feature",
  "properties": {
    "iso:country":"DE",
    "sg:address":"Linscheidstr. 46 - 48::",
    "sg:city":"Altena",
    "sg:phone":"+49 4923/5220170",
    "sg:postcode":"58762",
    "sg:province":"Nordrhein-Westfalen",
    "wof:name":"Maerkische Revision Organisations- U. Treuhandgmbh",
    "wof:placetype":"venue"
},
  "geometry": {"coordinates":[7.668904,51.303074],"type":"Point"}
}