{
  "type": "Feature",
  "properties": {
    "iso:country":"DE",
    "sg:address":"Am Dorfplatz 8",
    "sg:city":"H\u00e4nichen",
    "sg:phone":"+49 351/4015625",
    "sg:postcode":"01728",
    "sg:province":"Sachsen",
    "wof:name":"Rudi Leumer",
    "wof:placetype":"venue"
},
  "geometry": {"coordinates":[13.7217502594,50.9763259888],"type":"Point"}
}