{
  "type": "Feature",
  "properties": {
    "iso:country":"DE",
    "sg:address":"Triebweg 160",
    "sg:city":"Osterhofen",
    "sg:phone":"+49 9932/507",
    "sg:postcode":"94486",
    "sg:province":"Bayern",
    "wof:name":"Franz Dischinger",
    "wof:placetype":"venue"
},
  "geometry": {"coordinates":[13.028425,48.689812],"type":"Point"}
}