{
  "type": "Feature",
  "properties": {
    "iso:country":"DE",
    "sg:address":"M\u00f6rikeweg 7",
    "sg:city":"Neunkirchen",
    "sg:phone":"+49 2735/6836",
    "sg:postcode":"57290",
    "sg:province":"Nordrhein-Westfalen",
    "wof:name":"Cse Gmbh",
    "wof:placetype":"venue"
},
  "geometry": {"coordinates":[8.0217256546,50.7896881104],"type":"Point"}
}