{
  "type": "Feature",
  "properties": {
    "iso:country":"DE",
    "sg:address":"Bahnhofstr. 43",
    "sg:city":"Salzbergen",
    "sg:phone":"+49 5976/1221",
    "sg:postcode":"48499",
    "sg:province":"Niedersachsen",
    "wof:name":"Peter Dondrup",
    "wof:placetype":"venue"
},
  "geometry": {"coordinates":[7.3438658714,52.321144104],"type":"Point"}
}