{
  "type": "Feature",
  "properties": {
    "iso:country":"DE",
    "sg:address":"Hauptstr. 65",
    "sg:city":"Breitscheid",
    "sg:phone":"+49 2777/1331",
    "sg:postcode":"35767",
    "sg:province":"Hessen",
    "wof:name":"Klaus-dieter Sahm",
    "wof:placetype":"venue"
},
  "geometry": {"coordinates":[8.2313146591,50.7004356384],"type":"Point"}
}