{
  "type": "Feature",
  "properties": {
    "iso:country":"DE",
    "sg:address":"Falkstra\u00dfe 9",
    "sg:city":"Bielefeld",
    "sg:phone":"+49 4905/21",
    "sg:postcode":"33602",
    "sg:province":"Nordrhein-Westfalen",
    "wof:name":"Gabriele Becker-uthmann",
    "wof:placetype":"venue"
},
  "geometry": {"coordinates":[8.538452,52.022358],"type":"Point"}
}