{
  "type": "Feature",
  "properties": {
    "iso:country":"DE",
    "sg:address":"Lerchenh\u00fcgel 24",
    "sg:city":"Schwarzenbach a Wald",
    "sg:phone":"+49 9289/5240",
    "sg:postcode":"95131",
    "sg:province":"Bayern",
    "wof:name":"Sportheim",
    "wof:placetype":"venue"
},
  "geometry": {"coordinates":[11.6046772003,50.2926139832],"type":"Point"}
}