{
  "type": "Feature",
  "properties": {
    "iso:country":"DE",
    "sg:address":"Haag",
    "sg:city":"Hemau",
    "sg:phone":"+49 9491/1851",
    "sg:postcode":"93155",
    "sg:province":"Bayern",
    "wof:name":"P. Hackner",
    "wof:placetype":"venue"
},
  "geometry": {"coordinates":[11.81773,49.059391],"type":"Point"}
}