{
  "type": "Feature",
  "properties": {
    "iso:country":"DE",
    "sg:address":"Kavarinerstr. 57",
    "sg:city":"Kleve",
    "sg:phone":"+49 2821/21762",
    "sg:postcode":"47533",
    "sg:province":"Nordrhein-Westfalen",
    "wof:name":"M. Janic",
    "wof:placetype":"venue"
},
  "geometry": {"coordinates":[6.1368298531,51.7905845642],"type":"Point"}
}