{
  "type": "Feature",
  "properties": {
    "iso:country":"DE",
    "sg:address":"Uhlerbornstr. 10",
    "sg:city":"Mainz",
    "sg:phone":"+49 6131/477389",
    "sg:postcode":"55126",
    "sg:province":"Rheinland-Pfalz",
    "wof:name":"Pizzeria Etna",
    "wof:placetype":"venue"
},
  "geometry": {"coordinates":[8.1674251556,49.9881248474],"type":"Point"}
}