{
  "type": "Feature",
  "properties": {
    "iso:country":"DE",
    "sg:address":"Augustastr. 6",
    "sg:city":"Kaiserslautern",
    "sg:phone":"+49 631/41530",
    "sg:postcode":"67655",
    "sg:province":"Rheinland-Pfalz",
    "wof:name":"Wilhelm Klein Gro\u00dfk\u00fcchenbetriebs-gmbh",
    "wof:placetype":"venue"
},
  "geometry": {"coordinates":[7.7743191719,49.4390258789],"type":"Point"}
}