{
  "type": "Feature",
  "properties": {
    "iso:country":"DE",
    "sg:address":"Karl-Knauf-Str. 4",
    "sg:city":"Iphofen",
    "sg:phone":"+49 9323/3405",
    "sg:postcode":"97346",
    "sg:province":"Bayern",
    "wof:name":"Friedrich Guckenberger Weinanbau",
    "wof:placetype":"venue"
},
  "geometry": {"coordinates":[10.257235527,49.6984138489],"type":"Point"}
}