{
  "type": "Feature",
  "properties": {
    "iso:country":"DE",
    "sg:address":"Rajen 258",
    "sg:city":"Rhauderfehn",
    "sg:phone":"+49 4952/2187",
    "sg:postcode":"26817",
    "sg:province":"Niedersachsen",
    "wof:name":"E. Groeneveld",
    "wof:placetype":"venue"
},
  "geometry": {"coordinates":[7.5330858231,53.132183075],"type":"Point"}
}