{
  "type": "Feature",
  "properties": {
    "iso:country":"DE",
    "sg:address":"R\u00f6ntgenstr. 6",
    "sg:city":"Attendorn",
    "sg:phone":"+49 2722/50061",
    "sg:postcode":"57439",
    "sg:province":"Nordrhein-Westfalen",
    "wof:name":"Stinn-metallbau Gmbh",
    "wof:placetype":"venue"
},
  "geometry": {"coordinates":[7.922814,51.142387],"type":"Point"}
}