{
  "type": "Feature",
  "properties": {
    "iso:country":"DE",
    "sg:address":"Gro\u00dfe Bockenheimer Str. 10",
    "sg:city":"Frankfurt",
    "sg:phone":"+49 69/288424",
    "sg:postcode":"60313",
    "sg:province":"Hessen",
    "wof:name":"Viktoria-apotheke Apothekerin M. Sauer E. Kfr.",
    "wof:placetype":"venue"
},
  "geometry": {"coordinates":[8.675038,50.114483],"type":"Point"}
}