{
  "type": "Feature",
  "properties": {
    "iso:country":"DE",
    "sg:address":"35083",
    "sg:city":"Wetter",
    "sg:phone":"+49 6423/6908",
    "sg:postcode":"35083",
    "sg:province":"Hessen",
    "wof:name":"Deutsche Bahn Ag",
    "wof:placetype":"venue"
},
  "geometry": {"coordinates":[8.7079000473,50.917011261],"type":"Point"}
}