{
  "type": "Feature",
  "properties": {
    "iso:country":"DE",
    "sg:address":"Mauritiussteinweg 64",
    "sg:city":"K\u00f6ln",
    "sg:phone":"+49 221/249039",
    "sg:postcode":"50676",
    "sg:province":"Nordrhein-Westfalen",
    "wof:name":"Pool Pr-m Agentur",
    "wof:placetype":"venue"
},
  "geometry": {"coordinates":[6.9454388618,50.932888031],"type":"Point"}
}