{
  "type": "Feature",
  "properties": {
    "iso:country":"DE",
    "sg:address":"Corneliastr. 32",
    "sg:city":"Stolberg",
    "sg:phone":"+49 2402/30177",
    "sg:postcode":"52223",
    "sg:province":"Nordrhein-Westfalen",
    "wof:name":"Johann Schmitz",
    "wof:placetype":"venue"
},
  "geometry": {"coordinates":[6.211805,50.734032],"type":"Point"}
}