{
  "type": "Feature",
  "properties": {
    "iso:country":"DE",
    "sg:address":"Marler Str. 23a",
    "sg:city":"Haltern",
    "sg:phone":"+49 2364/4223",
    "sg:postcode":"45721",
    "sg:province":"Nordrhein-Westfalen",
    "wof:name":"Anton Korte",
    "wof:placetype":"venue"
},
  "geometry": {"coordinates":[7.182975769,51.7265586853],"type":"Point"}
}