{
  "type": "Feature",
  "properties": {
    "iso:country":"DE",
    "sg:address":"Langstr. 42-44",
    "sg:city":"Hanau",
    "sg:postcode":"63450",
    "sg:province":"Hessen",
    "wof:name":"Boieg Trading Und Specialtours Gmbh",
    "wof:placetype":"venue"
},
  "geometry": {"coordinates":[8.9187583923,50.1339530945],"type":"Point"}
}