{
  "type": "Feature",
  "properties": {
    "iso:country":"DE",
    "sg:address":"W\u00fcrzburger Str. 2",
    "sg:city":"Laatzen",
    "sg:phone":"+49 511/221180",
    "sg:postcode":"30880",
    "sg:province":"Niedersachsen",
    "wof:name":"H. J. Darges",
    "wof:placetype":"venue"
},
  "geometry": {"coordinates":[9.801796,52.305553],"type":"Point"}
}