{
  "type": "Feature",
  "properties": {
    "iso:country":"DE",
    "sg:address":"Am Scherfenbrand 129",
    "sg:city":"Leverkusen",
    "sg:phone":"+49 214/52156",
    "sg:postcode":"51375",
    "sg:province":"Nordrhein-Westfalen",
    "wof:name":"Heppekausen",
    "wof:placetype":"venue"
},
  "geometry": {"coordinates":[7.0563340187,51.0282821655],"type":"Point"}
}