{
  "type": "Feature",
  "properties": {
    "iso:country":"DE",
    "sg:address":"Bahnhofstr. 1",
    "sg:city":"Marbach",
    "sg:phone":"+49 7144/5478",
    "sg:postcode":"71672",
    "sg:province":"Baden-W\u00fcrttemberg",
    "wof:name":"F. Oehler B\u00e4ckerei-lebensmittel",
    "wof:placetype":"venue"
},
  "geometry": {"coordinates":[9.722324,50.617783],"type":"Point"}
}