{
  "type": "Feature",
  "properties": {
    "iso:country":"DE",
    "sg:address":"Dirminger Str. 2",
    "sg:city":"Tholey",
    "sg:phone":"+49 6853/922880",
    "sg:postcode":"66636",
    "sg:province":"Saarland",
    "wof:name":"Ziegler & Partner Gmbh",
    "wof:placetype":"venue"
},
  "geometry": {"coordinates":[7.040151,49.480614],"type":"Point"}
}