{
  "type": "Feature",
  "properties": {
    "iso:country":"DE",
    "sg:address":"Dahlienstr. 44",
    "sg:city":"Radevormwald",
    "sg:phone":"+49 2195/91000",
    "sg:postcode":"42477",
    "sg:province":"Nordrhein-Westfalen",
    "wof:name":"Klaus Lippelt Gmbh",
    "wof:placetype":"venue"
},
  "geometry": {"coordinates":[7.3846712112,51.2033615112],"type":"Point"}
}