{
  "type": "Feature",
  "properties": {
    "iso:country":"DE",
    "sg:address":"Steegmannstr. 5",
    "sg:city":"Fallingbostel",
    "sg:phone":"+49 5163/1212",
    "sg:postcode":"29683",
    "sg:province":"Niedersachsen",
    "wof:name":"Albert Menke Baugesch\u00e4ft Gmbh",
    "wof:placetype":"venue"
},
  "geometry": {"coordinates":[9.767916,52.90617],"type":"Point"}
}