{
  "type": "Feature",
  "properties": {
    "iso:country":"DE",
    "sg:address":"Karl-Marx-Str.",
    "sg:city":"Neuruppin",
    "sg:postcode":"16816",
    "sg:province":"Brandenburg",
    "wof:name":"Taxi",
    "wof:placetype":"venue"
},
  "geometry": {"coordinates":[12.8078203201,52.9267311096],"type":"Point"}
}