{
  "type": "Feature",
  "properties": {
    "iso:country":"DE",
    "sg:address":"Emeranstr. 47",
    "sg:city":"Feldkirchen",
    "sg:phone":"+49 89/9032206",
    "sg:postcode":"85622",
    "sg:province":"Bayern",
    "wof:name":"Branntweinbrennerei Feldkirchen B. M\u00fcnchen Eg",
    "wof:placetype":"venue"
},
  "geometry": {"coordinates":[11.7374916077,48.1506996155],"type":"Point"}
}