{
  "type": "Feature",
  "properties": {
    "iso:country":"DE",
    "sg:address":"Heissen 3",
    "sg:city":"Oberg\u00fcnzburg",
    "sg:phone":"+49 8306/263",
    "sg:postcode":"87634",
    "sg:province":"Bayern",
    "wof:name":"Gordian Ro\u00dfkopf",
    "wof:placetype":"venue"
},
  "geometry": {"coordinates":[10.45571,47.882294],"type":"Point"}
}