{
  "type": "Feature",
  "properties": {
    "iso:country":"DE",
    "sg:address":"Mainl\u00e4nde",
    "sg:city":"Veitsh\u00f6chheim",
    "sg:phone":"+49 931/98521",
    "sg:postcode":"97209",
    "sg:province":"Bayern",
    "wof:name":"Biergarten",
    "wof:placetype":"venue"
},
  "geometry": {"coordinates":[9.8697748184,49.8303794861],"type":"Point"}
}