{
  "type": "Feature",
  "properties": {
    "iso:country":"DE",
    "sg:address":"Jaudesring 16",
    "sg:city":"Bad W\u00f6rishofen",
    "sg:phone":"+49 8247/5034",
    "sg:postcode":"86825",
    "sg:province":"Bayern",
    "wof:name":"Robert Kremer Verlag Gbr",
    "wof:placetype":"venue"
},
  "geometry": {"coordinates":[10.6067056656,48.0051803589],"type":"Point"}
}