{
  "type": "Feature",
  "properties": {
    "iso:country":"DE",
    "sg:address":"Am Langen Rain 49",
    "sg:city":"Oschatz",
    "sg:postcode":"04758",
    "sg:province":"Sachsen",
    "wof:name":"Wolfgang Schramm",
    "wof:placetype":"venue"
},
  "geometry": {"coordinates":[13.0985469818,51.2965164185],"type":"Point"}
}