{
  "type": "Feature",
  "properties": {
    "iso:country":"DE",
    "sg:address":"Gebenstr. 13",
    "sg:city":"Freiburg",
    "sg:phone":"+49 7664/3813",
    "sg:postcode":"79112",
    "sg:province":"Baden-W\u00fcrttemberg",
    "wof:name":"Doris Von Lucadou Praxis F\u00fcr Krankengymnastik",
    "wof:placetype":"venue"
},
  "geometry": {"coordinates":[7.724548,48.014008],"type":"Point"}
}