{
  "type": "Feature",
  "properties": {
    "iso:country":"DE",
    "sg:address":"Wittelsbacherstr. 30a",
    "sg:city":"Wuppertal",
    "sg:postcode":"42287",
    "sg:province":"Nordrhein-Westfalen",
    "wof:name":"I & B Investitions- Und Beteiligungsgesellschaft Mbh",
    "wof:placetype":"venue"
},
  "geometry": {"coordinates":[7.199728,51.253403],"type":"Point"}
}