{
  "type": "Feature",
  "properties": {
    "iso:country":"DE",
    "sg:address":"Sauerbruchstr. 12",
    "sg:city":"Velbert",
    "sg:phone":"+49 2051/989563",
    "sg:postcode":"42549",
    "sg:province":"Nordrhein-Westfalen",
    "wof:name":"B. Koslowski",
    "wof:placetype":"venue"
},
  "geometry": {"coordinates":[7.020832,51.348881],"type":"Point"}
}