{
  "type": "Feature",
  "properties": {
    "iso:country":"DE",
    "sg:address":"Au\u00dferhalb 6",
    "sg:city":"Grasellenbach",
    "sg:postcode":"64689",
    "sg:province":"Hessen",
    "wof:name":"Walter Hartmann",
    "wof:placetype":"venue"
},
  "geometry": {"coordinates":[8.835477,49.614296],"type":"Point"}
}