{
  "type": "Feature",
  "properties": {
    "iso:country":"DE",
    "sg:address":"Bahnhofstr. 37",
    "sg:city":"Senden",
    "sg:postcode":"48308",
    "sg:province":"Nordrhein-Westfalen",
    "wof:name":"Smw Schkeuditzer M\u00f6belwerk Gesch\u00e4ftsf\u00fchrungs Gmbh",
    "wof:placetype":"venue"
},
  "geometry": {"coordinates":[7.4869418144,51.9076080322],"type":"Point"}
}