{
  "type": "Feature",
  "properties": {
    "iso:country":"DE",
    "sg:address":"Ernst-Putz-Str. 67",
    "sg:city":"Bad Br\u00fcckenau",
    "sg:postcode":"97769",
    "sg:province":"Bayern",
    "wof:name":"Park-pflegeheim Verwaltungs Gmbh",
    "wof:placetype":"venue"
},
  "geometry": {"coordinates":[9.759265,50.30537],"type":"Point"}
}