{
  "type": "Feature",
  "properties": {
    "iso:country":"DE",
    "sg:address":"Hauptstr. 19",
    "sg:city":"Immenstaad",
    "sg:phone":"+49 7545/6166",
    "sg:postcode":"88090",
    "sg:province":"Baden-W\u00fcrttemberg",
    "wof:name":"Zwirner",
    "wof:placetype":"venue"
},
  "geometry": {"coordinates":[9.36636,47.665661],"type":"Point"}
}