{
  "type": "Feature",
  "properties": {
    "iso:country":"DE",
    "sg:address":"Nesserlander Str. 109",
    "sg:city":"Emden",
    "sg:phone":"+49 4921/24136",
    "sg:postcode":"26723",
    "sg:province":"Niedersachsen",
    "wof:name":"E. & F. Urner",
    "wof:placetype":"venue"
},
  "geometry": {"coordinates":[7.1893692017,53.350189209],"type":"Point"}
}