{
  "type": "Feature",
  "properties": {
    "iso:country":"DE",
    "sg:address":"Wilhelmstr. 52",
    "sg:city":"Heilbad Heiligenstadt",
    "sg:phone":"+49 3606/553955",
    "sg:postcode":"37308",
    "sg:province":"Th\u00fcringen",
    "wof:name":"Dr. Arthur Demuth Rechtsanwalt",
    "wof:placetype":"venue"
},
  "geometry": {"coordinates":[10.137919426,51.3772926331],"type":"Point"}
}