{
  "type": "Feature",
  "properties": {
    "iso:country":"DE",
    "sg:address":"Am Stadtwald 18",
    "sg:city":"Bergneustadt",
    "sg:phone":"+49 2261/42982",
    "sg:postcode":"51702",
    "sg:province":"Nordrhein-Westfalen",
    "wof:name":"Elektro Drees E. K. Inh. M\u00f6hlendick",
    "wof:placetype":"venue"
},
  "geometry": {"coordinates":[7.658506,51.026535],"type":"Point"}
}