{
  "type": "Feature",
  "properties": {
    "iso:country":"DE",
    "sg:address":"P\u00f6ltnerstr. 20",
    "sg:city":"Weilheim",
    "sg:phone":"+49 881/2081",
    "sg:postcode":"82362",
    "sg:province":"Bayern",
    "wof:name":"Josefine Kraut",
    "wof:placetype":"venue"
},
  "geometry": {"coordinates":[11.141571,47.83794],"type":"Point"}
}