{
  "type": "Feature",
  "properties": {
    "iso:country":"DE",
    "sg:address":"Drennesweg 9",
    "sg:city":"Moers",
    "sg:phone":"+49 2841/97270",
    "sg:postcode":"47445",
    "sg:province":"Nordrhein-Westfalen",
    "wof:name":"Praxxis Gmbh",
    "wof:placetype":"venue"
},
  "geometry": {"coordinates":[6.605487,51.475719],"type":"Point"}
}