{
  "type": "Feature",
  "properties": {
    "iso:country":"DE",
    "sg:address":"Sinziger Str. 48",
    "sg:city":"Remagen",
    "sg:phone":"+49 2642/1221",
    "sg:postcode":"53424",
    "sg:province":"Rheinland-Pfalz",
    "wof:name":"Remagener Toiletten Miet- Service",
    "wof:placetype":"venue"
},
  "geometry": {"coordinates":[7.2451200485,50.5608787537],"type":"Point"}
}