{
  "type": "Feature",
  "properties": {
    "iso:country":"DE",
    "sg:address":"Aachener Str. 92",
    "sg:city":"K\u00f6ln",
    "sg:phone":"+49 221/529100",
    "sg:postcode":"50674",
    "sg:province":"Nordrhein-Westfalen",
    "wof:name":"Matratzen-markt-concord Gmbh",
    "wof:placetype":"venue"
},
  "geometry": {"coordinates":[6.929869175,50.9367828369],"type":"Point"}
}