{
  "type": "Feature",
  "properties": {
    "iso:country":"DE",
    "sg:address":"Badeweg 65",
    "sg:city":"L\u00f6hne",
    "sg:phone":"+49 5732/73411",
    "sg:postcode":"32584",
    "sg:province":"Nordrhein-Westfalen",
    "wof:name":"Helmut Buchmann Bau Gmbh",
    "wof:placetype":"venue"
},
  "geometry": {"coordinates":[8.7442455292,52.2195281982],"type":"Point"}
}