{
  "type": "Feature",
  "properties": {
    "iso:country":"DE",
    "sg:address":"Klosterstr. 20",
    "sg:city":"H\u00fcnfeld",
    "sg:phone":"+49 6652/2222",
    "sg:postcode":"36088",
    "sg:province":"Hessen",
    "wof:name":"Aha & Uth Karosseriebau Kg",
    "wof:placetype":"venue"
},
  "geometry": {"coordinates":[9.77187,50.674683],"type":"Point"}
}