{
  "type": "Feature",
  "properties": {
    "iso:country":"DE",
    "sg:address":"Oberbenrader Str 407",
    "sg:city":"Krefeld",
    "sg:phone":"+49 2151/9371811",
    "sg:postcode":"47804",
    "sg:province":"Nordrhein-Westfalen",
    "wof:name":"Lift-tek Elecar Gmbh",
    "wof:placetype":"venue"
},
  "geometry": {"coordinates":[6.51591,51.321362],"type":"Point"}
}