{
  "type": "Feature",
  "properties": {
    "iso:country":"DE",
    "sg:address":"Nederlinger Str. 70",
    "sg:city":"M\u00fcnchen",
    "sg:phone":"+49 89/155924",
    "sg:postcode":"80638",
    "sg:province":"Bayern",
    "wof:name":"E. Zika",
    "wof:placetype":"venue"
},
  "geometry": {"coordinates":[11.5180635452,48.1665153503],"type":"Point"}
}