{
  "type": "Feature",
  "properties": {
    "iso:country":"DE",
    "sg:address":"Poststr. 19",
    "sg:city":"D\u00fcsseldorf",
    "sg:phone":"+49 211/323594",
    "sg:postcode":"40213",
    "sg:province":"Nordrhein-Westfalen",
    "wof:name":"Monika Tackmann Au\u00dfenwerbung Gmbh",
    "wof:placetype":"venue"
},
  "geometry": {"coordinates":[6.7717108727,51.2206001282],"type":"Point"}
}