{
  "type": "Feature",
  "properties": {
    "iso:country":"DE",
    "sg:address":"Lindenallee 1",
    "sg:city":"Angerm\u00fcnde",
    "sg:phone":"+49 3331/33066",
    "sg:postcode":"16278",
    "sg:province":"Brandenburg",
    "wof:name":"Gut Angerm\u00fcnde Betriebsgesellschaft Mbh",
    "wof:placetype":"venue"
},
  "geometry": {"coordinates":[13.98726,52.975704],"type":"Point"}
}