{
  "type": "Feature",
  "properties": {
    "iso:country":"DE",
    "sg:address":"Jugendparkweg 58",
    "sg:city":"Hamburg",
    "sg:postcode":"22415",
    "sg:province":"Hamburg",
    "wof:name":"Kinderheim",
    "wof:placetype":"venue"
},
  "geometry": {"coordinates":[9.992562294,53.6445884705],"type":"Point"}
}