{
  "type": "Feature",
  "properties": {
    "iso:country":"DE",
    "sg:address":"Hanauer Str. 11",
    "sg:city":"Rodgau",
    "sg:phone":"+49 6106/71571",
    "sg:postcode":"63110",
    "sg:province":"Hessen",
    "wof:name":"Hvn Hausverwaltungen Gmbh",
    "wof:placetype":"venue"
},
  "geometry": {"coordinates":[8.868270874,49.9995880127],"type":"Point"}
}