{
  "type": "Feature",
  "properties": {
    "iso:country":"DE",
    "sg:address":"Hauptstr. 14",
    "sg:city":"Friedeburg",
    "sg:phone":"+49 4468/94098",
    "sg:postcode":"26446",
    "sg:province":"Niedersachsen",
    "wof:name":"Klosterschenke",
    "wof:placetype":"venue"
},
  "geometry": {"coordinates":[7.8391299248,53.4531288147],"type":"Point"}
}