{
  "type": "Feature",
  "properties": {
    "iso:country":"DE",
    "sg:address":"Bismarckstr. 43",
    "sg:city":"N\u00fcrnberg",
    "sg:phone":"+49 911/5980646",
    "sg:postcode":"90491",
    "sg:province":"Bayern",
    "wof:name":"Pilsst\u00fcberl F\u00fcrst Bismarck",
    "wof:placetype":"venue"
},
  "geometry": {"coordinates":[11.105383873,49.4647865295],"type":"Point"}
}