{
  "type": "Feature",
  "properties": {
    "iso:country":"DE",
    "sg:address":"Harburger Str. 42",
    "sg:city":"Hanstedt",
    "sg:phone":"+49 4184/7331",
    "sg:postcode":"21271",
    "sg:province":"Niedersachsen",
    "wof:name":"Hans-hermann Kr\u00f6ger Gmbh",
    "wof:placetype":"venue"
},
  "geometry": {"coordinates":[10.011393,53.262131],"type":"Point"}
}