{
  "type": "Feature",
  "properties": {
    "iso:country":"DE",
    "sg:address":"Breidenbrucher Str. 3",
    "sg:city":"Wiehl",
    "sg:phone":"+49 2261/76003",
    "sg:postcode":"51674",
    "sg:province":"Nordrhein-Westfalen",
    "wof:name":"C. H. Simon Ingenieur",
    "wof:placetype":"venue"
},
  "geometry": {"coordinates":[7.5355381966,50.9747276306],"type":"Point"}
}