{
  "type": "Feature",
  "properties": {
    "iso:country":"DE",
    "sg:address":"Gerlfanger Str. 14",
    "sg:city":"Merzig",
    "sg:phone":"+49 6831/121636",
    "sg:postcode":"66663",
    "sg:province":"Saarland",
    "wof:name":"Shirtfabrik",
    "wof:placetype":"venue"
},
  "geometry": {"coordinates":[6.627884,49.416718],"type":"Point"}
}