{
  "type": "Feature",
  "properties": {
    "iso:country":"DE",
    "sg:address":"Albiger Str. 14",
    "sg:city":"Alzey",
    "sg:phone":"+49 6731/3633",
    "sg:postcode":"55232",
    "sg:province":"Rheinland-Pfalz",
    "wof:name":"Ingenieur-biologische Bau- Gmbh",
    "wof:placetype":"venue"
},
  "geometry": {"coordinates":[8.1176538467,49.7533988953],"type":"Point"}
}