{
  "type": "Feature",
  "properties": {
    "iso:country":"DE",
    "sg:address":"Goethestr. 30",
    "sg:city":"Rathenow",
    "sg:phone":"+49 3385/516666",
    "sg:postcode":"14712",
    "sg:province":"Brandenburg",
    "wof:name":"Secom",
    "wof:placetype":"venue"
},
  "geometry": {"coordinates":[12.3458127975,52.609500885],"type":"Point"}
}