{
  "type": "Feature",
  "properties": {
    "iso:country":"DE",
    "sg:address":"Eisenstr. 34",
    "sg:city":"R\u00fcsselsheim",
    "sg:phone":"+49 6142/62659",
    "sg:postcode":"65428",
    "sg:province":"Hessen",
    "wof:name":"Metallbau Spaniol Gmbh",
    "wof:placetype":"venue"
},
  "geometry": {"coordinates":[8.428136,49.977974],"type":"Point"}
}