{
  "type": "Feature",
  "properties": {
    "iso:country":"DE",
    "sg:address":"Badstr 1",
    "sg:city":"Siegen",
    "sg:phone":"+49 271/2382510",
    "sg:postcode":"57072",
    "sg:province":"Nordrhein-Westfalen",
    "wof:name":"Conthermo Gmbh & Co Kg Produktbereich Bauger\u00e4te Corwett",
    "wof:placetype":"venue"
},
  "geometry": {"coordinates":[8.0125637054,50.8718109131],"type":"Point"}
}