{
  "type": "Feature",
  "properties": {
    "iso:country":"DE",
    "sg:address":"Potsdamer Str. 66-68",
    "sg:city":"G\u00fcterfelde",
    "sg:phone":"+49 3329/62937",
    "sg:postcode":"14532",
    "sg:province":"Brandenburg",
    "wof:name":"Prof. Dr. Macholz Umweltprojekte Gmbh",
    "wof:placetype":"venue"
},
  "geometry": {"coordinates":[13.193110466,52.3659896851],"type":"Point"}
}