{
  "type": "Feature",
  "properties": {
    "iso:country":"DE",
    "sg:address":"Lise-Meitner-Str. 16",
    "sg:city":"Itzehoe",
    "sg:phone":"+49 4821/717101",
    "sg:postcode":"25524",
    "sg:province":"Schleswig-Holstein",
    "wof:name":"J. Martens",
    "wof:placetype":"venue"
},
  "geometry": {"coordinates":[9.491549,53.954636],"type":"Point"}
}