{
  "type": "Feature",
  "properties": {
    "iso:country":"DE",
    "sg:address":"Der Breite Michelsweg 15",
    "sg:city":"Worms",
    "sg:postcode":"67547",
    "sg:province":"Rheinland-Pfalz",
    "wof:name":"Wilhelm Schon Handel Und Transport",
    "wof:placetype":"venue"
},
  "geometry": {"coordinates":[8.345809,49.6241],"type":"Point"}
}