{
  "type": "Feature",
  "properties": {
    "iso:country":"DE",
    "sg:address":"Berliner Str. 54",
    "sg:city":"Spremberg",
    "sg:phone":"+49 3563/93541",
    "sg:postcode":"03130",
    "sg:province":"Brandenburg",
    "wof:name":"Benno Huskobla",
    "wof:placetype":"venue"
},
  "geometry": {"coordinates":[14.368519783,51.5694999695],"type":"Point"}
}