{
  "type": "Feature",
  "properties": {
    "iso:country":"DE",
    "sg:address":"Schubertstr. 26",
    "sg:city":"Heusenstamm",
    "sg:phone":"+49 6104/3877",
    "sg:postcode":"63150",
    "sg:province":"Hessen",
    "wof:name":"Walter Schmidt Ingenieur",
    "wof:placetype":"venue"
},
  "geometry": {"coordinates":[8.7957267761,50.0569038391],"type":"Point"}
}