{
  "type": "Feature",
  "properties": {
    "iso:country":"DE",
    "sg:address":"Ehm-Welk-Str. 29",
    "sg:city":"L\u00fcbbenau",
    "sg:phone":"+49 3542/43361",
    "sg:postcode":"03222",
    "sg:province":"Brandenburg",
    "wof:name":"B. Domke",
    "wof:placetype":"venue"
},
  "geometry": {"coordinates":[13.983039856,51.827960968],"type":"Point"}
}