{
  "type": "Feature",
  "properties": {
    "iso:country":"DE",
    "sg:address":"Heinrich-Janssen-Str. 12",
    "sg:city":"Wuppertal",
    "sg:phone":"+49 202/596851",
    "sg:postcode":"42289",
    "sg:province":"Nordrhein-Westfalen",
    "wof:name":"Ernst Menne",
    "wof:placetype":"venue"
},
  "geometry": {"coordinates":[7.203979969,51.2686309814],"type":"Point"}
}