{
  "type": "Feature",
  "properties": {
    "iso:country":"DE",
    "sg:address":"Heidelberger Str. 48",
    "sg:city":"Hockenheim",
    "sg:phone":"+49 6205/4748",
    "sg:postcode":"68766",
    "sg:province":"Baden-W\u00fcrttemberg",
    "wof:name":"Karl Huber",
    "wof:placetype":"venue"
},
  "geometry": {"coordinates":[8.5525979996,49.3207740784],"type":"Point"}
}