{
  "type": "Feature",
  "properties": {
    "iso:country":"DE",
    "sg:address":"Liebenauer Str. 114",
    "sg:city":"Halle",
    "sg:phone":"+49 345/4820004",
    "sg:postcode":"06110",
    "sg:province":"Sachsen-Anhalt",
    "wof:name":"Tkl Halle Verwaltungsges. Mbh",
    "wof:placetype":"venue"
},
  "geometry": {"coordinates":[11.9799900055,51.4633789062],"type":"Point"}
}