{
  "type": "Feature",
  "properties": {
    "iso:country":"DE",
    "sg:address":"Sch\u00f6ninger Str. 2-3",
    "sg:city":"Helmstedt",
    "sg:phone":"+49 5351/183880",
    "sg:postcode":"38350",
    "sg:province":"Niedersachsen",
    "wof:name":"Terrakomp Gmbh",
    "wof:placetype":"venue"
},
  "geometry": {"coordinates":[11.0106191635,52.2236709595],"type":"Point"}
}