{
  "type": "Feature",
  "properties": {
    "iso:country":"DE",
    "sg:address":"An der Friedenseiche 9-11",
    "sg:city":"Kunow",
    "sg:phone":"+49 33977/80423",
    "sg:postcode":"16866",
    "sg:province":"Brandenburg",
    "wof:name":"Agrar-erzeuger-genossenschaft Kunow Eg",
    "wof:placetype":"venue"
},
  "geometry": {"coordinates":[12.134178,52.996361],"type":"Point"}
}