{
  "type": "Feature",
  "properties": {
    "iso:country":"DE",
    "sg:address":"Am Brink 6",
    "sg:city":"Hasel\u00fcnne",
    "sg:phone":"+49 5961/5613",
    "sg:postcode":"49740",
    "sg:province":"Niedersachsen",
    "wof:name":"H. K\u00f6tter",
    "wof:placetype":"venue"
},
  "geometry": {"coordinates":[7.3963527679,52.6756134033],"type":"Point"}
}