{
  "type": "Feature",
  "properties": {
    "iso:country":"DE",
    "sg:address":"Gro\u00dfe Str. 36",
    "sg:city":"Aschendorf",
    "sg:phone":"+49 4962/210",
    "sg:postcode":"26871",
    "sg:province":"Niedersachsen",
    "wof:name":"H. Tombrink",
    "wof:placetype":"venue"
},
  "geometry": {"coordinates":[7.3329,53.052593],"type":"Point"}
}