{
  "type": "Feature",
  "properties": {
    "iso:country":"DE",
    "sg:address":"Klopstockstr. 1",
    "sg:city":"Berlin",
    "sg:phone":"+49 30/3323151",
    "sg:postcode":"10557",
    "sg:province":"Berlin",
    "wof:name":"Squash-fitness-center Gmbh",
    "wof:placetype":"venue"
},
  "geometry": {"coordinates":[13.337735,52.514748],"type":"Point"}
}