{
  "type": "Feature",
  "properties": {
    "iso:country":"DE",
    "sg:address":"Dorfstr. 24",
    "sg:city":"Klinkrade",
    "sg:phone":"+49 4536/600",
    "sg:postcode":"23898",
    "sg:province":"Schleswig-Holstein",
    "wof:name":"Ernst Schinkel",
    "wof:placetype":"venue"
},
  "geometry": {"coordinates":[10.554749,53.71405],"type":"Point"}
}