{
  "type": "Feature",
  "properties": {
    "iso:country":"DE",
    "sg:address":"Industriestr. 2",
    "sg:city":"Lorsch",
    "sg:phone":"+49 4962/5159680",
    "sg:postcode":"64653",
    "sg:province":"Hessen",
    "wof:name":"Dietsch Speditionsgesellschaft Gmbh",
    "wof:placetype":"venue"
},
  "geometry": {"coordinates":[8.5716352463,49.6395797729],"type":"Point"}
}