{
  "type": "Feature",
  "properties": {
    "iso:country":"DE",
    "sg:address":"Spessartstr. 22",
    "sg:city":"Sulzbach",
    "sg:phone":"+49 6028/2640",
    "sg:postcode":"63834",
    "sg:province":"Bayern",
    "wof:name":"Wolfgang Hohl Rechtsanwalt",
    "wof:placetype":"venue"
},
  "geometry": {"coordinates":[9.1534729004,49.9089508057],"type":"Point"}
}