{
  "type": "Feature",
  "properties": {
    "iso:country":"DE",
    "sg:address":"Johannes-Bayer-Str. 3",
    "sg:city":"Rain",
    "sg:phone":"+49 9090/2098",
    "sg:postcode":"86641",
    "sg:province":"Bayern",
    "wof:name":"Norma Lebensmittelfilialbetrieb",
    "wof:placetype":"venue"
},
  "geometry": {"coordinates":[10.923830986,48.6944084167],"type":"Point"}
}