{
  "type": "Feature",
  "properties": {
    "iso:country":"DE",
    "sg:address":"Lessingstr. 100",
    "sg:city":"Dortmund",
    "sg:phone":"+49 231/822932",
    "sg:postcode":"44147",
    "sg:province":"Nordrhein-Westfalen",
    "wof:name":"Katholisches Pfarramt St. Aposteln",
    "wof:placetype":"venue"
},
  "geometry": {"coordinates":[7.4505801201,51.5227584839],"type":"Point"}
}