{
  "type": "Feature",
  "properties": {
    "iso:country":"DE",
    "sg:address":"Morgeng\u00e4rten 18",
    "sg:city":"Bremen",
    "sg:postcode":"28279",
    "sg:province":"Bremen",
    "wof:name":"\u00d6dp-landesverband Bremen",
    "wof:placetype":"venue"
},
  "geometry": {"coordinates":[8.8468227386,53.0403137207],"type":"Point"}
}