{
  "type": "Feature",
  "properties": {
    "iso:country":"DE",
    "sg:address":"Bahnhofstr. 34",
    "sg:city":"Gernrode",
    "sg:phone":"+49 39485/204",
    "sg:postcode":"06507",
    "sg:province":"Sachsen-Anhalt",
    "wof:name":"K. Bartsch Nachf. Kg",
    "wof:placetype":"venue"
},
  "geometry": {"coordinates":[11.14457,51.7262],"type":"Point"}
}