{
  "type": "Feature",
  "properties": {
    "iso:country":"DE",
    "sg:address":"Hauptstr. 12",
    "sg:city":"Biebelsheim",
    "sg:phone":"+49 6701/603",
    "sg:postcode":"55546",
    "sg:province":"Rheinland-Pfalz",
    "wof:name":"Rainer K\u00f6hler",
    "wof:placetype":"venue"
},
  "geometry": {"coordinates":[7.9383797646,49.8734016418],"type":"Point"}
}