{
  "type": "Feature",
  "properties": {
    "iso:country":"DE",
    "sg:address":"An der Stadthalle 12",
    "sg:city":"Baunatal",
    "sg:phone":"+49 561/494251",
    "sg:postcode":"34225",
    "sg:province":"Hessen",
    "wof:name":"Walter Thomas",
    "wof:placetype":"venue"
},
  "geometry": {"coordinates":[9.4117879868,51.2540054321],"type":"Point"}
}