{
  "type": "Feature",
  "properties": {
    "iso:country":"DE",
    "sg:address":"Niedertorstr. 11",
    "sg:city":"L\u00fcbbecke",
    "sg:phone":"+49 5741/7044",
    "sg:postcode":"32312",
    "sg:province":"Nordrhein-Westfalen",
    "wof:name":"Ingenieurb\u00fcro F\u00fcr Geokunst- Stoffe Und Umweltgeotechnik",
    "wof:placetype":"venue"
},
  "geometry": {"coordinates":[8.6189279556,52.3063240051],"type":"Point"}
}