{
  "type": "Feature",
  "properties": {
    "iso:country":"DE",
    "sg:address":"Robert-Bosch-Str. 16",
    "sg:city":"M\u00fcnster",
    "sg:phone":"+49 251/7636866",
    "sg:postcode":"48153",
    "sg:province":"Nordrhein-Westfalen",
    "wof:name":"Peter Beule Indoor-kart Gmbh",
    "wof:placetype":"venue"
},
  "geometry": {"coordinates":[7.6355061531,51.9357681274],"type":"Point"}
}