{
  "type": "Feature",
  "properties": {
    "iso:country":"DE",
    "sg:address":"Dorfstr. 29",
    "sg:city":"Sauldorf",
    "sg:phone":"+49 7777/1595",
    "sg:postcode":"88605",
    "sg:province":"Baden-W\u00fcrttemberg",
    "wof:name":"M. K\u00f6nig",
    "wof:placetype":"venue"
},
  "geometry": {"coordinates":[9.0319871902,47.9725036621],"type":"Point"}
}