{
  "type": "Feature",
  "properties": {
    "iso:country":"DE",
    "sg:address":"Liebknechtstr. 10",
    "sg:city":"Bernburg",
    "sg:phone":"+49 3471/626495",
    "sg:postcode":"06406",
    "sg:province":"Sachsen-Anhalt",
    "wof:name":"Ess-elektro-system- Service Gmbh",
    "wof:placetype":"venue"
},
  "geometry": {"coordinates":[11.747157,51.79388],"type":"Point"}
}