{
  "type": "Feature",
  "properties": {
    "iso:country":"DE",
    "sg:address":"Rudolf-Diesel-Str. 13",
    "sg:city":"Singen",
    "sg:phone":"+49 7731/61071",
    "sg:postcode":"78224",
    "sg:province":"Baden-W\u00fcrttemberg",
    "wof:name":"Tug Technische Unterhaltungs- Ger\u00e4te Produktions- Und",
    "wof:placetype":"venue"
},
  "geometry": {"coordinates":[8.884762764,47.754283905],"type":"Point"}
}