{
  "type": "Feature",
  "properties": {
    "iso:country":"DE",
    "sg:address":"Schlo\u00dfplatz 5",
    "sg:city":"Osterode",
    "sg:phone":"+49 5522/901930",
    "sg:postcode":"37520",
    "sg:province":"Niedersachsen",
    "wof:name":"Ev. \u00f6ffentl. Bibliothek Der St. Jacobi Schloss",
    "wof:placetype":"venue"
},
  "geometry": {"coordinates":[10.255158,51.724419],"type":"Point"}
}