{
  "type": "Feature",
  "properties": {
    "iso:country":"DE",
    "sg:address":"Alte Str. 27",
    "sg:city":"Hochstetten-Dhaun",
    "sg:phone":"+49 6752/6914",
    "sg:postcode":"55606",
    "sg:province":"Rheinland-Pfalz",
    "wof:name":"Bowling Hill Gmbh",
    "wof:placetype":"venue"
},
  "geometry": {"coordinates":[7.5115771294,49.8009605408],"type":"Point"}
}