{
  "type": "Feature",
  "properties": {
    "iso:country":"DE",
    "sg:address":"Helmpertstr. 13",
    "sg:city":"M\u00fcnchen",
    "sg:phone":"+49 89/5807036",
    "sg:postcode":"80687",
    "sg:province":"Bayern",
    "wof:name":"Johann Rauscher",
    "wof:placetype":"venue"
},
  "geometry": {"coordinates":[11.500664,48.140491],"type":"Point"}
}