{
  "type": "Feature",
  "properties": {
    "iso:country":"DE",
    "sg:address":"Eichendorffstr. 1",
    "sg:city":"Greding",
    "sg:phone":"+49 8463/400",
    "sg:postcode":"91171",
    "sg:province":"Bayern",
    "wof:name":"A. Schlee Hebamme",
    "wof:placetype":"venue"
},
  "geometry": {"coordinates":[11.366328,49.043446],"type":"Point"}
}