{
  "type": "Feature",
  "properties": {
    "iso:country":"DE",
    "sg:address":"Theaterstr. 58",
    "sg:city":"Aachen",
    "sg:phone":"+49 241/946460",
    "sg:postcode":"52062",
    "sg:province":"Nordrhein-Westfalen",
    "wof:name":"Werner Schwedt Rechtsanwalt",
    "wof:placetype":"venue"
},
  "geometry": {"coordinates":[6.0914778709,50.7707366943],"type":"Point"}
}