{
  "type": "Feature",
  "properties": {
    "iso:country":"DE",
    "sg:address":"Rungestra\u00dfe 18",
    "sg:city":"Berlin",
    "sg:phone":"+49 4930",
    "sg:postcode":"10179",
    "sg:province":"Berlin",
    "wof:name":"Zvab - Zentrales Verzeichnis Antiquarischer B\u00fccher",
    "wof:placetype":"venue"
},
  "geometry": {"coordinates":[13.4199323654,52.5121078491],"type":"Point"}
}