{
  "type": "Feature",
  "properties": {
    "iso:country":"DE",
    "sg:address":"L\u00fcbecker Str. 19",
    "sg:city":"Bargteheide",
    "sg:phone":"+49 4532/263630",
    "sg:postcode":"22941",
    "sg:province":"Schleswig-Holstein",
    "wof:name":"Helga Pem\u00f6ller Steuerberater",
    "wof:placetype":"venue"
},
  "geometry": {"coordinates":[10.2617349625,53.7333641052],"type":"Point"}
}