{
  "type": "Feature",
  "properties": {
    "iso:country":"DE",
    "sg:address":"S\u00fcdring 36",
    "sg:city":"Bochum",
    "sg:phone":"+49 234/12725",
    "sg:postcode":"44787",
    "sg:province":"Nordrhein-Westfalen",
    "wof:name":"Ruthenbeck",
    "wof:placetype":"venue"
},
  "geometry": {"coordinates":[7.21468,51.479065],"type":"Point"}
}