{
  "type": "Feature",
  "properties": {
    "iso:country":"DE",
    "sg:address":"Alte Herrenh\u00e4user Str. 48 A",
    "sg:city":"Hannover",
    "sg:phone":"+49 511/756521",
    "sg:postcode":"30419",
    "sg:province":"Niedersachsen",
    "wof:name":"Johann-ludwig Ruyter",
    "wof:placetype":"venue"
},
  "geometry": {"coordinates":[9.687903,52.391933],"type":"Point"}
}