{
  "type": "Feature",
  "properties": {
    "iso:country":"DE",
    "sg:address":"Stresemannstr. 309",
    "sg:city":"Hamburg",
    "sg:phone":"+49 40/857584",
    "sg:postcode":"22761",
    "sg:province":"Hamburg",
    "wof:name":"Heinrich Seifert",
    "wof:placetype":"venue"
},
  "geometry": {"coordinates":[9.9289951324,53.5636253357],"type":"Point"}
}