{
  "type": "Feature",
  "properties": {
    "iso:country":"DE",
    "sg:address":"Postfach 45",
    "sg:city":"Ottobeuren",
    "sg:postcode":"87720",
    "sg:province":"Bayern",
    "wof:name":"Bibliotheca Ottenburana",
    "wof:placetype":"venue"
},
  "geometry": {"coordinates":[10.299524,47.941593],"type":"Point"}
}