{
  "type": "Feature",
  "properties": {
    "iso:country":"DE",
    "sg:address":"Vechtaer Str. 2",
    "sg:city":"Goldenstedt",
    "sg:phone":"+49 4444/468",
    "sg:postcode":"49424",
    "sg:province":"Niedersachsen",
    "wof:name":"Ev. Gemeindeb\u00fccherei",
    "wof:placetype":"venue"
},
  "geometry": {"coordinates":[8.430439,52.783474],"type":"Point"}
}