{
  "type": "Feature",
  "properties": {
    "iso:country":"DE",
    "sg:address":"Br\u00fcderstr. 16",
    "sg:city":"Iserlohn",
    "sg:phone":"+49 2371/28632",
    "sg:postcode":"58636",
    "sg:province":"Nordrhein-Westfalen",
    "wof:name":"Waldsch\u00e4nke",
    "wof:placetype":"venue"
},
  "geometry": {"coordinates":[7.7021951675,51.3718910217],"type":"Point"}
}