{
  "type": "Feature",
  "properties": {
    "iso:country":"DE",
    "sg:address":"Bocksberg 56",
    "sg:city":"Mettlach",
    "sg:phone":"+49 6864/93133",
    "sg:postcode":"66693",
    "sg:province":"Saarland",
    "wof:name":"Rsg Saar",
    "wof:placetype":"venue"
},
  "geometry": {"coordinates":[6.614285,49.492393],"type":"Point"}
}