{
  "type": "Feature",
  "properties": {
    "iso:country":"DE",
    "sg:address":"Fr\u00f6lichstr. 18",
    "sg:city":"Augsburg",
    "sg:phone":"+49 821/3479960",
    "sg:postcode":"86150",
    "sg:province":"Bayern",
    "wof:name":"Mozart-apotheke Dr. Stefan Kraus E. K.",
    "wof:placetype":"venue"
},
  "geometry": {"coordinates":[10.886682,48.368519],"type":"Point"}
}