{
  "type": "Feature",
  "properties": {
    "iso:country":"DE",
    "sg:address":"Rammelsberger Str. 2",
    "sg:city":"Goslar",
    "sg:postcode":"38640",
    "sg:province":"Niedersachsen",
    "wof:name":"Sch\u00fctzenvogt-becker-stiftung",
    "wof:placetype":"venue"
},
  "geometry": {"coordinates":[10.4205207825,51.9019203186],"type":"Point"}
}