{
  "type": "Feature",
  "properties": {
    "iso:country":"DE",
    "sg:address":"Schulstr. 15",
    "sg:city":"Lengerich",
    "sg:phone":"+49 5481/2292",
    "sg:postcode":"49525",
    "sg:province":"Nordrhein-Westfalen",
    "wof:name":"T\u00dcv Hannover- Sachsen-anhalt E. V.",
    "wof:placetype":"venue"
},
  "geometry": {"coordinates":[7.8609108925,52.1868972778],"type":"Point"}
}