{
  "type": "Feature",
  "properties": {
    "iso:country":"DE",
    "sg:address":"Ixheimer Str. 169",
    "sg:city":"Zweibr\u00fccken",
    "sg:phone":"+49 6332/13865",
    "sg:postcode":"66482",
    "sg:province":"Rheinland-Pfalz",
    "wof:name":"Praxis Dr. Med. Boiselle",
    "wof:placetype":"venue"
},
  "geometry": {"coordinates":[7.3625431061,49.2378540039],"type":"Point"}
}