{
  "type": "Feature",
  "properties": {
    "iso:country":"DE",
    "sg:address":"Amselstr. 47",
    "sg:city":"M\u00fclheim",
    "sg:phone":"+49 208/490840",
    "sg:postcode":"45472",
    "sg:province":"Nordrhein-Westfalen",
    "wof:name":"Glaetzer Handelsservice F. Werbung Und",
    "wof:placetype":"venue"
},
  "geometry": {"coordinates":[6.9484758377,51.434463501],"type":"Point"}
}