{
  "type": "Feature",
  "properties": {
    "iso:country":"DE",
    "sg:address":"Marburger Str. 379",
    "sg:city":"Kreuztal",
    "sg:phone":"+49 2732/1648",
    "sg:postcode":"57223",
    "sg:province":"Nordrhein-Westfalen",
    "wof:name":"Eberhard Kr\u00e4mer",
    "wof:placetype":"venue"
},
  "geometry": {"coordinates":[8.02667,50.959682],"type":"Point"}
}