{
  "type": "Feature",
  "properties": {
    "iso:country":"DE",
    "sg:address":"Niederf\u00e4hrer Str. 31",
    "sg:city":"Mei\u00dfen",
    "sg:phone":"+49 3521/710439",
    "sg:postcode":"01662",
    "sg:province":"Sachsen",
    "wof:name":"H. Schmidt",
    "wof:placetype":"venue"
},
  "geometry": {"coordinates":[13.4813623428,51.1669692993],"type":"Point"}
}