{
  "type": "Feature",
  "properties": {
    "iso:country":"DE",
    "sg:address":"Amrigschwand 11",
    "sg:city":"H\u00f6chenschwand",
    "sg:phone":"+49 7755/757",
    "sg:postcode":"79862",
    "sg:province":"Baden-W\u00fcrttemberg",
    "wof:name":"K. Gr\u00f6ber-dupont Bildhauer",
    "wof:placetype":"venue"
},
  "geometry": {"coordinates":[8.186552,47.719482],"type":"Point"}
}