{
  "type": "Feature",
  "properties": {
    "iso:country":"DE",
    "sg:address":"Achenfeldstr. 31",
    "sg:city":"Garmisch-Partenkirchen",
    "sg:phone":"+49 8821/3363",
    "sg:postcode":"82467",
    "sg:province":"Bayern",
    "wof:name":"G\u00e4stehaus Sissi",
    "wof:placetype":"venue"
},
  "geometry": {"coordinates":[11.0938863754,47.4904289246],"type":"Point"}
}