{
  "type": "Feature",
  "properties": {
    "iso:country":"DE",
    "sg:address":"Grusonstr. 11",
    "sg:city":"M\u00fcnchen",
    "sg:phone":"+49 89/5233257",
    "sg:postcode":"80939",
    "sg:province":"Bayern",
    "wof:name":"Nordend-bau Gmbh",
    "wof:placetype":"venue"
},
  "geometry": {"coordinates":[11.5927839279,48.2025299072],"type":"Point"}
}