{
  "type": "Feature",
  "properties": {
    "iso:country":"DE",
    "sg:address":"Im Gr\u00fcn 19",
    "sg:city":"Bad Krozingen",
    "sg:phone":"+49 7633/15949",
    "sg:postcode":"79189",
    "sg:province":"Baden-W\u00fcrttemberg",
    "wof:name":"Harald Kraft Masseur",
    "wof:placetype":"venue"
},
  "geometry": {"coordinates":[7.66885,47.954227],"type":"Point"}
}