{
  "type": "Feature",
  "properties": {
    "iso:country":"DE",
    "sg:address":"Flachslandstr. 7",
    "sg:city":"L\u00f6rrach",
    "sg:phone":"+49 7621/45954",
    "sg:postcode":"79539",
    "sg:province":"Baden-W\u00fcrttemberg",
    "wof:name":"Barbara Schmid",
    "wof:placetype":"venue"
},
  "geometry": {"coordinates":[7.6606211662,47.6192436218],"type":"Point"}
}