{
  "type": "Feature",
  "properties": {
    "iso:country":"DE",
    "sg:address":"Goethestr. 1",
    "sg:city":"Offenau",
    "sg:phone":"+49 7136/6674",
    "sg:postcode":"74254",
    "sg:province":"Baden-W\u00fcrttemberg",
    "wof:name":"Willi Rudolf Seeschiffahrt-u.",
    "wof:placetype":"venue"
},
  "geometry": {"coordinates":[9.1633,49.24094],"type":"Point"}
}