{
  "type": "Feature",
  "properties": {
    "iso:country":"DE",
    "sg:address":"An der H\u00f6ssen 7",
    "sg:city":"Westerstede",
    "sg:phone":"+49 4488/2385",
    "sg:postcode":"26655",
    "sg:province":"Niedersachsen",
    "wof:name":"Roelfs & Hohm Transport Gmbh",
    "wof:placetype":"venue"
},
  "geometry": {"coordinates":[7.9168667793,53.2548294067],"type":"Point"}
}