{
  "type": "Feature",
  "properties": {
    "iso:country":"DE",
    "sg:address":"Selauer Str. 29",
    "sg:city":"Wei\u00dfenfels",
    "sg:phone":"+49 3443/303635",
    "sg:postcode":"06667",
    "sg:province":"Sachsen-Anhalt",
    "wof:name":"Schwarz-gelb",
    "wof:placetype":"venue"
},
  "geometry": {"coordinates":[11.9519453049,51.1938323975],"type":"Point"}
}