{
  "type": "Feature",
  "properties": {
    "iso:country":"DE",
    "sg:address":"Winsener Str. 26",
    "sg:city":"Hamburg",
    "sg:phone":"+49 40/7636347",
    "sg:postcode":"21077",
    "sg:province":"Hamburg",
    "wof:name":"Restaurant Taverna Regina Mare",
    "wof:placetype":"venue"
},
  "geometry": {"coordinates":[9.9873485565,53.44921875],"type":"Point"}
}