{
  "type": "Feature",
  "properties": {
    "iso:country":"DE",
    "sg:address":"Am Schlo\u00dfgarten 3",
    "sg:city":"Kirtorf",
    "sg:phone":"+49 6635/275",
    "sg:postcode":"36320",
    "sg:province":"Hessen",
    "wof:name":"Egenolf Kg",
    "wof:placetype":"venue"
},
  "geometry": {"coordinates":[9.1336631775,50.7569999695],"type":"Point"}
}