{
  "type": "Feature",
  "properties": {
    "iso:country":"DE",
    "sg:address":"Im Farneck 30",
    "sg:city":"Mandelbachtal",
    "sg:phone":"+49 6893/801174",
    "sg:postcode":"66399",
    "sg:province":"Saarland",
    "wof:name":"Secusoft Gmbh",
    "wof:placetype":"venue"
},
  "geometry": {"coordinates":[7.1407399178,49.1928977966],"type":"Point"}
}