{
  "type": "Feature",
  "properties": {
    "iso:country":"DE",
    "sg:address":"Mettener Str. 7",
    "sg:city":"Deggendorf",
    "sg:phone":"+49 991/8092",
    "sg:postcode":"94469",
    "sg:province":"Bayern",
    "wof:name":"Wagner Wohnbau Verwaltungs-gmbh",
    "wof:placetype":"venue"
},
  "geometry": {"coordinates":[12.9470348358,48.8352279663],"type":"Point"}
}