{
  "type": "Feature",
  "properties": {
    "iso:country":"DE",
    "sg:address":"Heidekamp 165 a",
    "sg:city":"Rieste",
    "sg:phone":"+49 5464/5641",
    "sg:postcode":"49597",
    "sg:province":"Niedersachsen",
    "wof:name":"Tenniscafe Am Alfsee",
    "wof:placetype":"venue"
},
  "geometry": {"coordinates":[7.992025,52.47739],"type":"Point"}
}