{
  "type": "Feature",
  "properties": {
    "iso:country":"DE",
    "sg:address":"Strahlenbergerstr. 125 a",
    "sg:city":"Offenbach",
    "sg:phone":"+49 69/82364736",
    "sg:postcode":"63067",
    "sg:province":"Hessen",
    "wof:name":"Tam Tam Musikverlags- Und -produktionsgesellschaft Mbh",
    "wof:placetype":"venue"
},
  "geometry": {"coordinates":[8.7321138382,50.1072616577],"type":"Point"}
}