{
  "type": "Feature",
  "properties": {
    "iso:country":"DE",
    "sg:address":"Sulzbachtalstr. 157",
    "sg:city":"Sulzbach",
    "sg:phone":"+49 6897/3617",
    "sg:postcode":"66280",
    "sg:province":"Saarland",
    "wof:name":"Susanne Schmitt Heilpraktikerin",
    "wof:placetype":"venue"
},
  "geometry": {"coordinates":[7.0684118271,49.3023872375],"type":"Point"}
}