{
  "type": "Feature",
  "properties": {
    "iso:country":"DE",
    "sg:address":"Fr\u00f6belring",
    "sg:city":"Eisenh\u00fcttenstadt",
    "sg:phone":"+49 3364/61433",
    "sg:postcode":"15890",
    "sg:province":"Brandenburg",
    "wof:name":"R. Wiebke",
    "wof:placetype":"venue"
},
  "geometry": {"coordinates":[14.64947,52.141144],"type":"Point"}
}