{
  "type": "Feature",
  "properties": {
    "iso:country":"DE",
    "sg:address":"Postgasse 4",
    "sg:city":"Ebersdorf",
    "sg:phone":"+49 36651/87019",
    "sg:postcode":"07368",
    "sg:province":"Th\u00fcringen",
    "wof:name":"Siegfried Richter",
    "wof:placetype":"venue"
},
  "geometry": {"coordinates":[11.602818,50.534966],"type":"Point"}
}