{
  "type": "Feature",
  "properties": {
    "iso:country":"DE",
    "sg:address":"Sondert 4",
    "sg:city":"Waltenhofen",
    "sg:phone":"+49 8379/7772",
    "sg:postcode":"87448",
    "sg:province":"Bayern",
    "wof:name":"Peter Hoerner Gmbh",
    "wof:placetype":"venue"
},
  "geometry": {"coordinates":[10.277762,47.614895],"type":"Point"}
}