{
  "type": "Feature",
  "properties": {
    "iso:country":"DE",
    "sg:address":"G\u00f6rlitzer Str. 40",
    "sg:city":"H\u00f6chstadt",
    "sg:phone":"+49 9193/1740",
    "sg:postcode":"91315",
    "sg:province":"Bayern",
    "wof:name":"Adolf Maier Ingenieur",
    "wof:placetype":"venue"
},
  "geometry": {"coordinates":[10.8067445755,49.6913604736],"type":"Point"}
}