{
  "type": "Feature",
  "properties": {
    "iso:country":"DE",
    "sg:address":"L\u00fctzowplatz 15",
    "sg:city":"Berlin",
    "sg:phone":"+49 30/2309810",
    "sg:postcode":"10785",
    "sg:province":"Berlin",
    "wof:name":"Thi Deutschland Projekt Dreilinden Gmbh",
    "wof:placetype":"venue"
},
  "geometry": {"coordinates":[13.352843,52.503925],"type":"Point"}
}