{
  "type": "Feature",
  "properties": {
    "iso:country":"DE",
    "sg:address":"R\u00f6merreuthstr. 19",
    "sg:city":"Erlangen",
    "sg:phone":"+49 9131/991166",
    "sg:postcode":"91056",
    "sg:province":"Bayern",
    "wof:name":"Gebr. Stenz Inh. Georg Rau",
    "wof:placetype":"venue"
},
  "geometry": {"coordinates":[10.950771,49.55489],"type":"Point"}
}