{
  "type": "Feature",
  "properties": {
    "iso:country":"DE",
    "sg:address":"Stedinger Landstr. 118",
    "sg:city":"Delmenhorst",
    "sg:phone":"+49 4221/41362",
    "sg:postcode":"27751",
    "sg:province":"Niedersachsen",
    "wof:name":"Adolf Osterloh Zimmerei Und Holzbau Gmbh & Co. Kg",
    "wof:placetype":"venue"
},
  "geometry": {"coordinates":[8.6468734741,53.0967483521],"type":"Point"}
}