{
  "type": "Feature",
  "properties": {
    "iso:country":"DE",
    "sg:address":"Engadiner Str.70",
    "sg:city":"Bremen",
    "sg:postcode":"28325",
    "sg:province":"Bremen",
    "wof:name":"Webscout-center",
    "wof:placetype":"venue"
},
  "geometry": {"coordinates":[8.955201,53.064777],"type":"Point"}
}