{
  "type": "Feature",
  "properties": {
    "iso:country":"DE",
    "sg:address":"Am Waltenberg 45",
    "sg:city":"Winterberg",
    "sg:phone":"+49 2981/2632",
    "sg:postcode":"59955",
    "sg:province":"Nordrhein-Westfalen",
    "wof:name":"Pizzeria Hazienda Inh. G. Djapic",
    "wof:placetype":"venue"
},
  "geometry": {"coordinates":[8.5206003189,51.1918563843],"type":"Point"}
}