{
  "type": "Feature",
  "properties": {
    "iso:country":"DE",
    "sg:address":"Frickinger Str. 1",
    "sg:city":"Salem",
    "sg:phone":"+49 7553/240",
    "sg:postcode":"88682",
    "sg:province":"Baden-W\u00fcrttemberg",
    "wof:name":"W. Dreher",
    "wof:placetype":"venue"
},
  "geometry": {"coordinates":[9.2595777512,47.7981834412],"type":"Point"}
}