{
  "type": "Feature",
  "properties": {
    "iso:country":"DE",
    "sg:address":"Schelldorfer Str. 23",
    "sg:city":"Wettstetten",
    "sg:phone":"+49 841/39668",
    "sg:postcode":"85139",
    "sg:province":"Bayern",
    "wof:name":"Salz",
    "wof:placetype":"venue"
},
  "geometry": {"coordinates":[11.4165067673,48.8260269165],"type":"Point"}
}