{
  "type": "Feature",
  "properties": {
    "iso:country":"DE",
    "sg:address":"Lippstr. 14",
    "sg:city":"Haltern",
    "sg:phone":"+49 2364/2538",
    "sg:postcode":"45721",
    "sg:province":"Nordrhein-Westfalen",
    "wof:name":"Heinz Marwitz",
    "wof:placetype":"venue"
},
  "geometry": {"coordinates":[7.1886110306,51.7430992126],"type":"Point"}
}