{
  "type": "Feature",
  "properties": {
    "iso:country":"DE",
    "sg:address":"G\u00e4nsheidestr. 2 - 4",
    "sg:city":"Stuttgart",
    "sg:phone":"+49 711/21491",
    "sg:postcode":"70184",
    "sg:province":"Baden-W\u00fcrttemberg",
    "wof:name":"Ev. Landeskirche W\u00fcrttemberg",
    "wof:placetype":"venue"
},
  "geometry": {"coordinates":[9.1964187622,48.7771492004],"type":"Point"}
}