{
  "type": "Feature",
  "properties": {
    "iso:country":"DE",
    "sg:address":"Oerlinghauser Str. 12",
    "sg:city":"Bad Salzuflen",
    "sg:phone":"+49 5222/81953",
    "sg:postcode":"32108",
    "sg:province":"Nordrhein-Westfalen",
    "wof:name":"Helmut Kordes",
    "wof:placetype":"venue"
},
  "geometry": {"coordinates":[8.748945,52.066463],"type":"Point"}
}