{
  "type": "Feature",
  "properties": {
    "iso:country":"DE",
    "sg:address":"Kesslerstr. 1",
    "sg:city":"Dettingen",
    "sg:phone":"+49 7021/58494",
    "sg:postcode":"73265",
    "sg:province":"Baden-W\u00fcrttemberg",
    "wof:name":"Wilk Heizungstechnik",
    "wof:placetype":"venue"
},
  "geometry": {"coordinates":[9.4513902664,48.6212081909],"type":"Point"}
}