{
  "type": "Feature",
  "properties": {
    "iso:country":"DE",
    "sg:address":"Brunnenstr. 1",
    "sg:city":"Kalenborn-Scheuern",
    "sg:phone":"+49 6591/7848",
    "sg:postcode":"54570",
    "sg:province":"Rheinland-Pfalz",
    "wof:name":"Franz Kuhl",
    "wof:placetype":"venue"
},
  "geometry": {"coordinates":[6.761329,50.159077],"type":"Point"}
}