{
  "type": "Feature",
  "properties": {
    "iso:country":"DE",
    "sg:address":"Vogteistr. 8",
    "sg:city":"Hessisch Oldendorf",
    "sg:phone":"+49 5158/525",
    "sg:postcode":"31840",
    "sg:province":"Niedersachsen",
    "wof:name":"Karl-heinz Rekate",
    "wof:placetype":"venue"
},
  "geometry": {"coordinates":[9.271169,52.137955],"type":"Point"}
}