{
  "type": "Feature",
  "properties": {
    "iso:country":"DE",
    "sg:address":"K\u00f6nigsteiner Str. 24",
    "sg:city":"Eschborn",
    "sg:phone":"+49 6196/41532",
    "sg:postcode":"65760",
    "sg:province":"Hessen",
    "wof:name":"Burckhardt Verwaltungs Gmbh",
    "wof:placetype":"venue"
},
  "geometry": {"coordinates":[8.5640497208,50.1441917419],"type":"Point"}
}