{
  "type": "Feature",
  "properties": {
    "iso:country":"DE",
    "sg:address":"Bredderbruchstr. 56",
    "sg:city":"Gevelsberg",
    "sg:phone":"+49 2332",
    "sg:postcode":"58285",
    "sg:province":"Nordrhein-Westfalen",
    "wof:name":"Silvia Henschke Immobilien",
    "wof:placetype":"venue"
},
  "geometry": {"coordinates":[7.3801670074,51.3319168091],"type":"Point"}
}