{
  "type": "Feature",
  "properties": {
    "iso:country":"DE",
    "sg:address":"Forststr. 31",
    "sg:city":"Radeberg",
    "sg:phone":"+49 3528/442542",
    "sg:postcode":"01454",
    "sg:province":"Sachsen",
    "wof:name":"Forsthaus",
    "wof:placetype":"venue"
},
  "geometry": {"coordinates":[13.8976421356,51.111164093],"type":"Point"}
}