{
  "type": "Feature",
  "properties": {
    "iso:country":"DE",
    "sg:address":"Engga\u00df 5",
    "sg:city":"Ottweiler",
    "sg:phone":"+49 6824/2139",
    "sg:postcode":"66564",
    "sg:province":"Saarland",
    "wof:name":"Neufang-rennwald",
    "wof:placetype":"venue"
},
  "geometry": {"coordinates":[7.1612248421,49.4031944275],"type":"Point"}
}