{
  "type": "Feature",
  "properties": {
    "iso:country":"DE",
    "sg:address":"Rosenheimer Str. 44",
    "sg:city":"Riedering",
    "sg:phone":"+49 8036/304315",
    "sg:postcode":"83083",
    "sg:province":"Bayern",
    "wof:name":"Wagschal-reisen Gmbh",
    "wof:placetype":"venue"
},
  "geometry": {"coordinates":[12.2013149261,47.8423080444],"type":"Point"}
}