{
  "type": "Feature",
  "properties": {
    "iso:country":"DE",
    "sg:address":"Hauptstr. 7",
    "sg:city":"Saarlouis",
    "sg:phone":"+49 6831/61699",
    "sg:postcode":"66740",
    "sg:province":"Saarland",
    "wof:name":"Richard Denke",
    "wof:placetype":"venue"
},
  "geometry": {"coordinates":[6.7247800827,49.3093910217],"type":"Point"}
}