{
  "type": "Feature",
  "properties": {
    "iso:country":"DE",
    "sg:address":"Querfurter Str.",
    "sg:city":"Artern",
    "sg:postcode":"06556",
    "sg:province":"Th\u00fcringen",
    "wof:name":"Tierprodukt Gmbh",
    "wof:placetype":"venue"
},
  "geometry": {"coordinates":[11.3058452606,51.3918266296],"type":"Point"}
}