{
  "type": "Feature",
  "properties": {
    "iso:country":"DE",
    "sg:address":"Hessenring 44",
    "sg:city":"Minden",
    "sg:phone":"+49 571/61969",
    "sg:postcode":"32425",
    "sg:province":"Nordrhein-Westfalen",
    "wof:name":"I. Schmidt Masseur",
    "wof:placetype":"venue"
},
  "geometry": {"coordinates":[8.900569,52.304825],"type":"Point"}
}