{
  "type": "Feature",
  "properties": {
    "iso:country":"DE",
    "sg:address":"Seestr. 21",
    "sg:city":"Reutlingen",
    "sg:phone":"+49 7121/490076",
    "sg:postcode":"72764",
    "sg:province":"Baden-W\u00fcrttemberg",
    "wof:name":"Connection Marketinggesell- Schaft Zur Entwickl. U. Umset-",
    "wof:placetype":"venue"
},
  "geometry": {"coordinates":[9.219355,48.489632],"type":"Point"}
}