{
  "type": "Feature",
  "properties": {
    "iso:country":"DE",
    "sg:address":"Ernst-Ludwig-Stra\u00dfe 43",
    "sg:city":"Egelsbach",
    "sg:phone":"+49 6103/940024",
    "sg:postcode":"63329",
    "sg:province":"Hessen",
    "wof:name":"Neubau Von 6 Doppelhaush\u00e4lften In Egelsbach",
    "wof:placetype":"venue"
},
  "geometry": {"coordinates":[8.665908,49.969151],"type":"Point"}
}