{
  "type": "Feature",
  "properties": {
    "iso:country":"DE",
    "sg:address":"Am Anger 11",
    "sg:city":"Marienm\u00fcnster",
    "sg:phone":"+49 5276/95861",
    "sg:postcode":"37696",
    "sg:province":"Nordrhein-Westfalen",
    "wof:name":"F. Matheus",
    "wof:placetype":"venue"
},
  "geometry": {"coordinates":[9.2467899323,51.7908630371],"type":"Point"}
}