{
  "type": "Feature",
  "properties": {
    "iso:country":"DE",
    "sg:address":"Alter Graben 2",
    "sg:city":"Wetter",
    "sg:phone":"+49 6423/6036",
    "sg:postcode":"35083",
    "sg:province":"Hessen",
    "wof:name":"Otto Dahm Architekt",
    "wof:placetype":"venue"
},
  "geometry": {"coordinates":[8.722411,50.903412],"type":"Point"}
}