{
  "type": "Feature",
  "properties": {
    "iso:country":"DE",
    "sg:address":"Bahnhofstr. 32",
    "sg:city":"P\u00f6sing",
    "sg:phone":"+49 9461/911030",
    "sg:postcode":"93483",
    "sg:province":"Bayern",
    "wof:name":"Beer W\u00c4rmebehandlung",
    "wof:placetype":"venue"
},
  "geometry": {"coordinates":[12.540139,49.229485],"type":"Point"}
}