{
  "type": "Feature",
  "properties": {
    "iso:country":"DE",
    "sg:address":"S\u00fcdstr. 7",
    "sg:city":"Ibbenb\u00fcren",
    "sg:phone":"+49 5451/16483",
    "sg:postcode":"49477",
    "sg:province":"Nordrhein-Westfalen",
    "wof:name":"Horst Wiesner",
    "wof:placetype":"venue"
},
  "geometry": {"coordinates":[7.7163958549,52.2708587646],"type":"Point"}
}