{
  "type": "Feature",
  "properties": {
    "iso:country":"DE",
    "sg:address":"Aschaffenburger Str. 83",
    "sg:city":"Seligenstadt",
    "sg:phone":"+49 6182/24237",
    "sg:postcode":"63500",
    "sg:province":"Hessen",
    "wof:name":"A. Torun",
    "wof:placetype":"venue"
},
  "geometry": {"coordinates":[8.9786128998,50.0413398743],"type":"Point"}
}