{
  "type": "Feature",
  "properties": {
    "iso:country":"DE",
    "sg:address":"H\u00f6henstr. 30",
    "sg:city":"Altensteig",
    "sg:phone":"+49 7453/7844",
    "sg:postcode":"72213",
    "sg:province":"Baden-W\u00fcrttemberg",
    "wof:name":"H. Seeger",
    "wof:placetype":"venue"
},
  "geometry": {"coordinates":[8.5690841675,48.621421814],"type":"Point"}
}