{
  "type": "Feature",
  "properties": {
    "iso:country":"DE",
    "sg:address":"Jechtinger Str. 7",
    "sg:city":"Sasbach",
    "sg:phone":"+49 7642/3208",
    "sg:postcode":"79361",
    "sg:province":"Baden-W\u00fcrttemberg",
    "wof:name":"Engel",
    "wof:placetype":"venue"
},
  "geometry": {"coordinates":[7.6136279106,48.1379737854],"type":"Point"}
}