{
  "type": "Feature",
  "properties": {
    "iso:country":"DE",
    "sg:address":"Neuer Platz 16",
    "sg:city":"Geretsried",
    "sg:phone":"+49 8171/8897",
    "sg:postcode":"82538",
    "sg:province":"Bayern",
    "wof:name":"Joachim Mattis",
    "wof:placetype":"venue"
},
  "geometry": {"coordinates":[11.4789619446,47.8577613831],"type":"Point"}
}