{
  "type": "Feature",
  "properties": {
    "iso:country":"DE",
    "sg:address":"Ratiborstr. 14e",
    "sg:city":"Berlin",
    "sg:phone":"+49 4930/6127055",
    "sg:postcode":"10999",
    "sg:province":"Berlin",
    "wof:name":"Max Kruppa Gmbh",
    "wof:placetype":"venue"
},
  "geometry": {"coordinates":[13.4384651184,52.4919509888],"type":"Point"}
}