{
  "type": "Feature",
  "properties": {
    "iso:country":"DE",
    "sg:address":"Schulzenstr. 17",
    "sg:city":"Stahnsdorf",
    "sg:phone":"+49 3329/62711",
    "sg:postcode":"14532",
    "sg:province":"Brandenburg",
    "wof:name":"Promontax Bau-holz Kunststoffelemente Gmbh",
    "wof:placetype":"venue"
},
  "geometry": {"coordinates":[13.2211933136,52.3884811401],"type":"Point"}
}