{
  "type": "Feature",
  "properties": {
    "iso:country":"DE",
    "sg:address":"Pflockenstr. 37",
    "sg:city":"Oelsnitz",
    "sg:postcode":"09376",
    "sg:province":"Sachsen",
    "wof:name":"Heavy & Bikertreff-anger",
    "wof:placetype":"venue"
},
  "geometry": {"coordinates":[12.7284078598,50.7235374451],"type":"Point"}
}