{
  "type": "Feature",
  "properties": {
    "iso:country":"DE",
    "sg:address":"Engerstr. 81",
    "sg:city":"B\u00fcnde",
    "sg:phone":"+49 5223/522545",
    "sg:postcode":"32257",
    "sg:province":"Nordrhein-Westfalen",
    "wof:name":"Ingrid Langhorst",
    "wof:placetype":"venue"
},
  "geometry": {"coordinates":[8.5677995682,52.172290802],"type":"Point"}
}