{
  "type": "Feature",
  "properties": {
    "iso:country":"DE",
    "sg:address":"Biberacher Str. 19-2",
    "sg:city":"Ummendorf",
    "sg:phone":"+49 7351/24030",
    "sg:postcode":"88444",
    "sg:province":"Baden-W\u00fcrttemberg",
    "wof:name":"M. Roth",
    "wof:placetype":"venue"
},
  "geometry": {"coordinates":[9.8295888901,48.0634651184],"type":"Point"}
}