{
  "type": "Feature",
  "properties": {
    "iso:country":"DE",
    "sg:address":"Pf\u00e4lzer Str. 3",
    "sg:city":"Burglengenfeld",
    "sg:phone":"+49 9471/8304",
    "sg:postcode":"93133",
    "sg:province":"Bayern",
    "wof:name":"Bauer",
    "wof:placetype":"venue"
},
  "geometry": {"coordinates":[12.053321,49.202896],"type":"Point"}
}