{
  "type": "Feature",
  "properties": {
    "iso:country":"DE",
    "sg:address":"Drosselweg 4 a",
    "sg:city":"Wathlingen",
    "sg:phone":"+49 5144/1263",
    "sg:postcode":"29339",
    "sg:province":"Niedersachsen",
    "wof:name":"Sayman Gmbh",
    "wof:placetype":"venue"
},
  "geometry": {"coordinates":[10.144844,52.534069],"type":"Point"}
}