{
  "type": "Feature",
  "properties": {
    "iso:country":"DE",
    "sg:address":"Abtsgm\u00fcnder Str. 13",
    "sg:city":"H\u00fcttlingen",
    "sg:phone":"+49 7361/71915",
    "sg:postcode":"73460",
    "sg:province":"Baden-W\u00fcrttemberg",
    "wof:name":"Otto Sch\u00e4ffner",
    "wof:placetype":"venue"
},
  "geometry": {"coordinates":[10.097711,48.892818],"type":"Point"}
}