{
  "type": "Feature",
  "properties": {
    "iso:country":"DE",
    "sg:address":"W\u00f6hrdstr. 4",
    "sg:city":"T\u00fcbingen",
    "sg:phone":"+49 7071/32300",
    "sg:postcode":"72072",
    "sg:province":"Baden-W\u00fcrttemberg",
    "wof:name":"Apotheke An Der Friedrichstra\u00dfe",
    "wof:placetype":"venue"
},
  "geometry": {"coordinates":[9.058483,48.518341],"type":"Point"}
}