{
  "type": "Feature",
  "properties": {
    "iso:country":"DE",
    "sg:address":"Hauptstr. 62",
    "sg:city":"Wattenheim",
    "sg:phone":"+49 6356/1627",
    "sg:postcode":"67319",
    "sg:province":"Rheinland-Pfalz",
    "wof:name":"Hermann Hepp",
    "wof:placetype":"venue"
},
  "geometry": {"coordinates":[8.0608119965,49.5218658447],"type":"Point"}
}