{
  "type": "Feature",
  "properties": {
    "iso:country":"DE",
    "sg:address":"Rheinstr. 74",
    "sg:city":"Wilhelmshaven",
    "sg:phone":"+49 4421/41409",
    "sg:postcode":"26382",
    "sg:province":"Niedersachsen",
    "wof:name":"Egon Neumann",
    "wof:placetype":"venue"
},
  "geometry": {"coordinates":[8.127743,53.516369],"type":"Point"}
}