{
  "type": "Feature",
  "properties": {
    "iso:country":"DE",
    "sg:address":"Waschpohler Weg 1",
    "sg:city":"K\u00f6nigswinter",
    "sg:phone":"+49 2244/7851",
    "sg:postcode":"53639",
    "sg:province":"Nordrhein-Westfalen",
    "wof:name":"Gmm Gesellschaft F\u00fcr Metallbearbeitung Und",
    "wof:placetype":"venue"
},
  "geometry": {"coordinates":[7.31001091,50.7148323059],"type":"Point"}
}