{
  "type": "Feature",
  "properties": {
    "iso:country":"DE",
    "sg:address":"Hauptstr. 95",
    "sg:city":"Weinheim",
    "sg:postcode":"69469",
    "sg:province":"Baden-W\u00fcrttemberg",
    "wof:name":"Fotoshop Rund Ums Bild Elke Wolff E. Kfr.",
    "wof:placetype":"venue"
},
  "geometry": {"coordinates":[8.6729297638,49.5476875305],"type":"Point"}
}