{
  "type": "Feature",
  "properties": {
    "iso:country":"DE",
    "sg:address":"Honings",
    "sg:city":"Hetzles",
    "sg:phone":"+49 9134/292",
    "sg:postcode":"91077",
    "sg:province":"Bayern",
    "wof:name":"Reinhard Z\u00f6llner",
    "wof:placetype":"venue"
},
  "geometry": {"coordinates":[11.1013698578,49.6384315491],"type":"Point"}
}