{
  "type": "Feature",
  "properties": {
    "iso:country":"DE",
    "sg:address":"Burgtreswitz 26",
    "sg:city":"Moosbach",
    "sg:phone":"+49 9656/577",
    "sg:postcode":"92709",
    "sg:province":"Bayern",
    "wof:name":"Ambros Held Jun. B\u00e4ckerei",
    "wof:placetype":"venue"
},
  "geometry": {"coordinates":[12.404,49.591709],"type":"Point"}
}