{
  "type": "Feature",
  "properties": {
    "iso:country":"DE",
    "sg:address":"Fasanenweg 8",
    "sg:city":"Ro\u00dfdorf",
    "sg:phone":"+49 6071/748688",
    "sg:postcode":"64380",
    "sg:province":"Hessen",
    "wof:name":"S Con Ingenieur Gmbh",
    "wof:placetype":"venue"
},
  "geometry": {"coordinates":[8.7958498001,49.8626022339],"type":"Point"}
}