{
  "type": "Feature",
  "properties": {
    "iso:country":"DE",
    "sg:address":"Neustr. 7",
    "sg:city":"Willich",
    "sg:phone":"+49 2156/5332",
    "sg:postcode":"47877",
    "sg:province":"Nordrhein-Westfalen",
    "wof:name":"Eiscafe G. Casagrande",
    "wof:placetype":"venue"
},
  "geometry": {"coordinates":[6.474658,51.251892],"type":"Point"}
}