{
  "type": "Feature",
  "properties": {
    "iso:country":"DE",
    "sg:address":"Kiefernstr. 1",
    "sg:city":"Bielefeld",
    "sg:phone":"+49 521/403549",
    "sg:postcode":"33649",
    "sg:province":"Nordrhein-Westfalen",
    "wof:name":"Helmut Preetz",
    "wof:placetype":"venue"
},
  "geometry": {"coordinates":[8.4558639526,51.9681091309],"type":"Point"}
}