{
  "type": "Feature",
  "properties": {
    "iso:country":"DE",
    "sg:address":"Berliner Platz 18-20",
    "sg:city":"Hagen",
    "sg:phone":"+49 2331/925624",
    "sg:postcode":"58089",
    "sg:province":"Nordrhein-Westfalen",
    "wof:name":"Deutsche Postbank Ag",
    "wof:placetype":"venue"
},
  "geometry": {"coordinates":[7.4621701241,51.3611793518],"type":"Point"}
}