{
  "type": "Feature",
  "properties": {
    "iso:country":"DE",
    "sg:address":"Gro\u00dfh\u00fclsen 23",
    "sg:city":"Hilden",
    "sg:phone":"+49 2103/335315",
    "sg:postcode":"40721",
    "sg:province":"Nordrhein-Westfalen",
    "wof:name":"A.m.s. Atlantic Land- Und \u00dcberseespedition Gmbh",
    "wof:placetype":"venue"
},
  "geometry": {"coordinates":[6.93707,51.169773],"type":"Point"}
}