{
  "type": "Feature",
  "properties": {
    "iso:country":"DE",
    "sg:address":"Kirchhellener Str. 44",
    "sg:city":"Bottrop",
    "sg:phone":"+49 2041/24365",
    "sg:postcode":"46236",
    "sg:province":"Nordrhein-Westfalen",
    "wof:name":"Grill Am Rathaus",
    "wof:placetype":"venue"
},
  "geometry": {"coordinates":[6.9229259491,51.5255889893],"type":"Point"}
}