{
  "type": "Feature",
  "properties": {
    "iso:country":"DE",
    "sg:address":"Grindelhof 38",
    "sg:city":"Hamburg",
    "sg:phone":"+49 40/41235706",
    "sg:postcode":"20146",
    "sg:province":"Hamburg",
    "wof:name":"Institut F\u00fcr Ausl\u00e4ndisches U. Internationales Finanz-",
    "wof:placetype":"venue"
},
  "geometry": {"coordinates":[9.9838581085,53.5690612793],"type":"Point"}
}