{
  "type": "Feature",
  "properties": {
    "iso:country":"DE",
    "sg:address":"Z\u00f6rnigaller Str. 12",
    "sg:city":"B\u00fclzig",
    "sg:phone":"+49 34924/20555",
    "sg:postcode":"06895",
    "sg:province":"Sachsen-Anhalt",
    "wof:name":"Harald Kaiser",
    "wof:placetype":"venue"
},
  "geometry": {"coordinates":[12.754752,51.891178],"type":"Point"}
}