{
  "type": "Feature",
  "properties": {
    "iso:country":"DE",
    "sg:address":"Sittigstr. 13",
    "sg:city":"Kriftel",
    "sg:phone":"+49 6192/41301",
    "sg:postcode":"65830",
    "sg:province":"Hessen",
    "wof:name":"E. Meder",
    "wof:placetype":"venue"
},
  "geometry": {"coordinates":[8.4779920578,50.0870399475],"type":"Point"}
}