{
  "type": "Feature",
  "properties": {
    "iso:country":"DE",
    "sg:address":"Auf dem Elm 2",
    "sg:city":"Perl",
    "sg:phone":"+49 700 2274 6766",
    "sg:postcode":"66706",
    "sg:province":"Saarland",
    "wof:name":"Telematik Gesellschaft F\u00fcr Logistikdienstleistungen Mbh",
    "wof:placetype":"venue"
},
  "geometry": {"coordinates":[6.4340901375,49.4959487915],"type":"Point"}
}