{
  "type": "Feature",
  "properties": {
    "iso:country":"DE",
    "sg:address":"Christaweg 5",
    "sg:city":"Freiburg",
    "sg:phone":"+49 761/43597",
    "sg:postcode":"79114",
    "sg:province":"Baden-W\u00fcrttemberg",
    "wof:name":"Farben-ullrich Inh. Johannes Ullrich",
    "wof:placetype":"venue"
},
  "geometry": {"coordinates":[7.803564,47.989258],"type":"Point"}
}