{
  "type": "Feature",
  "properties": {
    "iso:country":"DE",
    "sg:address":"Stra\u00dfe des Friedens 40",
    "sg:city":"Knapendorf",
    "sg:phone":"+49 3461/795161",
    "sg:postcode":"06246",
    "sg:province":"Sachsen-Anhalt",
    "wof:name":"Restaurierungswerkst\u00e4tten B\u00fcndorf Gmbh",
    "wof:placetype":"venue"
},
  "geometry": {"coordinates":[11.8459596634,51.38904953],"type":"Point"}
}