{
  "type": "Feature",
  "properties": {
    "iso:country":"DE",
    "sg:address":"Ring der Bauarbeiter 113",
    "sg:city":"Wolfen",
    "sg:postcode":"06766",
    "sg:province":"Sachsen-Anhalt",
    "wof:name":"Reiseb\u00fcro Franchowiak",
    "wof:placetype":"venue"
},
  "geometry": {"coordinates":[12.2554807663,51.6838722229],"type":"Point"}
}