{
  "type": "Feature",
  "properties": {
    "iso:country":"DE",
    "sg:address":"Schulstr. 1",
    "sg:city":"M\u00fcnster",
    "sg:phone":"+49 251/274930",
    "sg:postcode":"48149",
    "sg:province":"Nordrhein-Westfalen",
    "wof:name":"Ole Winkelmann Ingenieur",
    "wof:placetype":"venue"
},
  "geometry": {"coordinates":[7.6157660484,51.9679298401],"type":"Point"}
}