{
  "type": "Feature",
  "properties": {
    "iso:country":"DE",
    "sg:address":"Zum Kuhberg 6",
    "sg:city":"Gro\u00dfenkneten",
    "sg:phone":"+49 4435/96180",
    "sg:postcode":"26197",
    "sg:province":"Niedersachsen",
    "wof:name":"Hans J. Butt Gmbh",
    "wof:placetype":"venue"
},
  "geometry": {"coordinates":[8.255974,52.945694],"type":"Point"}
}