{
  "type": "Feature",
  "properties": {
    "iso:country":"DE",
    "sg:address":"Osterkamp 38",
    "sg:city":"Handewitt",
    "sg:phone":"+49 4608/437",
    "sg:postcode":"24983",
    "sg:province":"Schleswig-Holstein",
    "wof:name":"Rudolf W. Schmidt",
    "wof:placetype":"venue"
},
  "geometry": {"coordinates":[9.3330745697,54.7638053894],"type":"Point"}
}