{
  "type": "Feature",
  "properties": {
    "iso:country":"DE",
    "sg:address":"M\u00fchlhaldenstr 22",
    "sg:city":"Stuttgart",
    "sg:phone":"+49 711/2734520",
    "sg:postcode":"70567",
    "sg:province":"Baden-W\u00fcrttemberg",
    "wof:name":"Pressdvd.com",
    "wof:placetype":"venue"
},
  "geometry": {"coordinates":[9.1592,48.720684],"type":"Point"}
}