{
  "type": "Feature",
  "properties": {
    "iso:country":"DE",
    "sg:address":"Unter dem Ahorn 6a",
    "sg:city":"Wetzlar",
    "sg:phone":"+49 6441/76025",
    "sg:postcode":"35578",
    "sg:province":"Hessen",
    "wof:name":"Hubert Winter Versicherungen",
    "wof:placetype":"venue"
},
  "geometry": {"coordinates":[8.5353956223,50.5435142517],"type":"Point"}
}