{
  "type": "Feature",
  "properties": {
    "iso:country":"DE",
    "sg:address":"Jean-Paul-Str. 23",
    "sg:city":"Forchheim",
    "sg:phone":"+49 9191/65218",
    "sg:postcode":"91301",
    "sg:province":"Bayern",
    "wof:name":"Gastst\u00e4tte N. Kropp",
    "wof:placetype":"venue"
},
  "geometry": {"coordinates":[11.0642976761,49.7314186096],"type":"Point"}
}