{
  "type": "Feature",
  "properties": {
    "iso:country":"DE",
    "sg:address":"Zuschlagstr. 10",
    "sg:city":"Hannover",
    "sg:phone":"+49 511/526019",
    "sg:postcode":"30559",
    "sg:province":"Niedersachsen",
    "wof:name":"Waldfrieden",
    "wof:placetype":"venue"
},
  "geometry": {"coordinates":[9.7920036316,52.3591384888],"type":"Point"}
}