{
  "type": "Feature",
  "properties": {
    "iso:country":"DE",
    "sg:address":"Thanner Str. 32",
    "sg:city":"Nittenau",
    "sg:phone":"+49 9436/8321",
    "sg:postcode":"93149",
    "sg:province":"Bayern",
    "wof:name":"Seidemann Gmbh",
    "wof:placetype":"venue"
},
  "geometry": {"coordinates":[12.2769927979,49.2070846558],"type":"Point"}
}