{
  "type": "Feature",
  "properties": {
    "iso:country":"DE",
    "sg:address":"Wilhelmstr. 42",
    "sg:city":"Remscheid",
    "sg:phone":"+49 2191/24384",
    "sg:postcode":"42853",
    "sg:province":"Nordrhein-Westfalen",
    "wof:name":"Heinrich Debus",
    "wof:placetype":"venue"
},
  "geometry": {"coordinates":[7.179256,51.186897],"type":"Point"}
}