{
  "type": "Feature",
  "properties": {
    "iso:country":"DE",
    "sg:address":"Weselweg 8",
    "sg:city":"Angelbachtal",
    "sg:phone":"+49 7265/911135",
    "sg:postcode":"74918",
    "sg:province":"Baden-W\u00fcrttemberg",
    "wof:name":"Wiga Wohnbau- Und Immobilien- Gesellschaft F\u00fcr Das",
    "wof:placetype":"venue"
},
  "geometry": {"coordinates":[8.7827711105,49.2319297791],"type":"Point"}
}