{
  "type": "Feature",
  "properties": {
    "iso:country":"DE",
    "sg:address":"Sch\u00f6ne Gasse 3",
    "sg:city":"Wuppertal",
    "sg:phone":"+49 202/450165",
    "sg:postcode":"42103",
    "sg:province":"Nordrhein-Westfalen",
    "wof:name":"Koepchen Und Ranft Rechtsanw\u00e4lte",
    "wof:placetype":"venue"
},
  "geometry": {"coordinates":[7.1482429504,51.2575454712],"type":"Point"}
}