{
  "type": "Feature",
  "properties": {
    "iso:country":"DE",
    "sg:address":"Lienertstr. 20",
    "sg:city":"Oyten",
    "sg:phone":"+49 4207/2440",
    "sg:postcode":"28876",
    "sg:province":"Niedersachsen",
    "wof:name":"Ruth Cordes Immobilienmaklerin",
    "wof:placetype":"venue"
},
  "geometry": {"coordinates":[9.0162792206,53.0558624268],"type":"Point"}
}