{
  "type": "Feature",
  "properties": {
    "iso:country":"DE",
    "sg:address":"Waldstr. 4",
    "sg:city":"Lubmin",
    "sg:phone":"+49 38354/36252",
    "sg:postcode":"17509",
    "sg:province":"Mecklenburg-Vorpommern",
    "wof:name":"Pension Villa Am Park",
    "wof:placetype":"venue"
},
  "geometry": {"coordinates":[13.6134624481,54.1359634399],"type":"Point"}
}