{
  "type": "Feature",
  "properties": {
    "iso:country":"DE",
    "sg:address":"Voltmerstr. 56",
    "sg:city":"Hannover",
    "sg:phone":"+49 511/3500548",
    "sg:postcode":"30165",
    "sg:province":"Niedersachsen",
    "wof:name":"Hainh\u00f6lzer Bad",
    "wof:placetype":"venue"
},
  "geometry": {"coordinates":[9.7170543671,52.4025154114],"type":"Point"}
}