{
  "type": "Feature",
  "properties": {
    "iso:country":"DE",
    "sg:address":"Hamelner Str. 17",
    "sg:city":"D\u00f6rentrup",
    "sg:phone":"+49 5265/470",
    "sg:postcode":"32694",
    "sg:province":"Nordrhein-Westfalen",
    "wof:name":"Manfred Wieneke",
    "wof:placetype":"venue"
},
  "geometry": {"coordinates":[9.0258703232,52.0298919678],"type":"Point"}
}