{
  "type": "Feature",
  "properties": {
    "iso:country":"DE",
    "sg:address":"Nordstr. 21",
    "sg:city":"Seelze",
    "sg:phone":"+49 511/401760",
    "sg:postcode":"30926",
    "sg:province":"Niedersachsen",
    "wof:name":"Felix Paul Steuerberater",
    "wof:placetype":"venue"
},
  "geometry": {"coordinates":[9.6372909546,52.3992347717],"type":"Point"}
}