{
  "type": "Feature",
  "properties": {
    "iso:country":"DE",
    "sg:address":"Blatzheimer Str. 19",
    "sg:city":"Kerpen",
    "sg:phone":"+49 2275/398",
    "sg:postcode":"50170",
    "sg:province":"Nordrhein-Westfalen",
    "wof:name":"Katholisches Pfarramt St. Albanus",
    "wof:placetype":"venue"
},
  "geometry": {"coordinates":[6.6025929451,50.8804092407],"type":"Point"}
}