{
  "type": "Feature",
  "properties": {
    "iso:country":"DE",
    "sg:address":"Helenenstr. 26",
    "sg:city":"Essen",
    "sg:phone":"+49 201/620803",
    "sg:postcode":"45143",
    "sg:province":"Nordrhein-Westfalen",
    "wof:name":"Bestattungen Bernhard Holz",
    "wof:placetype":"venue"
},
  "geometry": {"coordinates":[6.981177,51.462032],"type":"Point"}
}