{
  "type": "Feature",
  "properties": {
    "iso:country":"DE",
    "sg:address":"Zuckschwerdtstr. 19",
    "sg:city":"Frankfurt",
    "sg:phone":"+49 69/318143",
    "sg:postcode":"65929",
    "sg:province":"Hessen",
    "wof:name":"Pfefferdutt",
    "wof:placetype":"venue"
},
  "geometry": {"coordinates":[8.5516414642,50.1045799255],"type":"Point"}
}