{
  "type": "Feature",
  "properties": {
    "iso:country":"DE",
    "sg:address":"M\u00fcnchener Str. 49",
    "sg:city":"Duisburg",
    "sg:phone":"+49 203/700549",
    "sg:postcode":"47249",
    "sg:province":"Nordrhein-Westfalen",
    "wof:name":"Siegbert Grunau",
    "wof:placetype":"venue"
},
  "geometry": {"coordinates":[6.7641711235,51.3840751648],"type":"Point"}
}