{
  "type": "Feature",
  "properties": {
    "iso:country":"DE",
    "sg:address":"Walpersdorfer Str. 52",
    "sg:city":"Rednitzhembach",
    "sg:postcode":"91126",
    "sg:province":"Bayern",
    "wof:name":"Wiedmann Isoliertechnik Gmbh",
    "wof:placetype":"venue"
},
  "geometry": {"coordinates":[11.05604,49.297581],"type":"Point"}
}