{
  "type": "Feature",
  "properties": {
    "iso:country":"DE",
    "sg:address":"Schweriner Str. 9-11",
    "sg:city":"Br\u00fcel",
    "sg:phone":"+49 38483/28017",
    "sg:postcode":"19412",
    "sg:province":"Mecklenburg-Vorpommern",
    "wof:name":"Hausmann Gmbh",
    "wof:placetype":"venue"
},
  "geometry": {"coordinates":[11.7148227692,53.7350769043],"type":"Point"}
}