{
  "type": "Feature",
  "properties": {
    "iso:country":"DE",
    "sg:address":"Schulstr. 12",
    "sg:city":"Lahnau",
    "sg:phone":"+49 6441/61724",
    "sg:postcode":"35633",
    "sg:province":"Hessen",
    "wof:name":"Gastst\u00e4tte Stamms Kneipe Inh. Friedhelm Stamm",
    "wof:placetype":"venue"
},
  "geometry": {"coordinates":[8.5651102066,50.5761604309],"type":"Point"}
}