{
  "type": "Feature",
  "properties": {
    "iso:country":"DE",
    "sg:address":"Wachtelweg 5",
    "sg:city":"Iserlohn",
    "sg:phone":"+49 2371/51047",
    "sg:postcode":"58638",
    "sg:province":"Nordrhein-Westfalen",
    "wof:name":"Willi Ropinski",
    "wof:placetype":"venue"
},
  "geometry": {"coordinates":[7.673894,51.373917],"type":"Point"}
}