{
  "type": "Feature",
  "properties": {
    "iso:country":"DE",
    "sg:address":"Altdorfstr. 40",
    "sg:city":"Wolfegg",
    "sg:phone":"+49 7527/96060",
    "sg:postcode":"88364",
    "sg:province":"Baden-W\u00fcrttemberg",
    "wof:name":"Guido Kattein",
    "wof:placetype":"venue"
},
  "geometry": {"coordinates":[9.7811822891,47.8198814392],"type":"Point"}
}