{
  "type": "Feature",
  "properties": {
    "iso:country":"DE",
    "sg:address":"B\u00fcrgerstr. 20",
    "sg:city":"Berlin",
    "sg:phone":"+49 30/6856941",
    "sg:postcode":"12347",
    "sg:province":"Berlin",
    "wof:name":"Kriwan Ingenieurb\u00fcro F\u00fcr Steuerungstechnik Gmbh",
    "wof:placetype":"venue"
},
  "geometry": {"coordinates":[13.4425544739,52.462272644],"type":"Point"}
}