{
  "type": "Feature",
  "properties": {
    "iso:country":"DE",
    "sg:address":"Trierer Str. 596",
    "sg:city":"Aachen",
    "sg:phone":"+49 241/523162",
    "sg:postcode":"52078",
    "sg:province":"Nordrhein-Westfalen",
    "wof:name":"Marlies Meurer",
    "wof:placetype":"venue"
},
  "geometry": {"coordinates":[6.1506710052,50.7554016113],"type":"Point"}
}