{
  "type": "Feature",
  "properties": {
    "iso:country":"DE",
    "sg:address":"Dambockstr. 40",
    "sg:city":"Berlin",
    "sg:phone":"+49 30/4319086",
    "sg:postcode":"13503",
    "sg:province":"Berlin",
    "wof:name":"Pension Am Erpelgrund",
    "wof:placetype":"venue"
},
  "geometry": {"coordinates":[13.2449169159,52.6047821045],"type":"Point"}
}