{
  "type": "Feature",
  "properties": {
    "iso:country":"DE",
    "sg:address":"Walzwerkstr. 89",
    "sg:city":"Finowfurt",
    "sg:phone":"+49 3335/44450",
    "sg:postcode":"16244",
    "sg:province":"Brandenburg",
    "wof:name":"Bbp Beton- Und Baustoff- Pr\u00fcfung Finowfurt",
    "wof:placetype":"venue"
},
  "geometry": {"coordinates":[13.689928,52.847031],"type":"Point"}
}