{
  "type": "Feature",
  "properties": {
    "iso:country":"DE",
    "sg:address":"Hermannstr. 30",
    "sg:city":"Hamburg",
    "sg:phone":"+49 40/326103",
    "sg:postcode":"20095",
    "sg:province":"Hamburg",
    "wof:name":"J. H. G. Berg Gmbh",
    "wof:placetype":"venue"
},
  "geometry": {"coordinates":[9.9968099594,53.5521697998],"type":"Point"}
}