{
  "type": "Feature",
  "properties": {
    "iso:country":"DE",
    "sg:address":"Tetz",
    "sg:city":"Linnich",
    "sg:phone":"+49 2462/8456",
    "sg:postcode":"52441",
    "sg:province":"Nordrhein-Westfalen",
    "wof:name":"Sofie Schlafen",
    "wof:placetype":"venue"
},
  "geometry": {"coordinates":[6.31878,50.96468],"type":"Point"}
}