{
  "type": "Feature",
  "properties": {
    "iso:country":"DE",
    "sg:address":"Boecke 13",
    "sg:city":"Stoetze",
    "sg:phone":"+49 5872/440",
    "sg:postcode":"29597",
    "sg:province":"Niedersachsen",
    "wof:name":"Ferkelproduktion Mehrens Gmbh",
    "wof:placetype":"venue"
},
  "geometry": {"coordinates":[10.7727298737,53.0719223022],"type":"Point"}
}