{
  "type": "Feature",
  "properties": {
    "iso:country":"DE",
    "sg:address":"Scheiderwiese 15",
    "sg:city":"Hennef",
    "sg:phone":"+49 2242/83662",
    "sg:postcode":"53773",
    "sg:province":"Nordrhein-Westfalen",
    "wof:name":"Bodeit Gmbh",
    "wof:placetype":"venue"
},
  "geometry": {"coordinates":[7.298413,50.799156],"type":"Point"}
}