{
  "type": "Feature",
  "properties": {
    "iso:country":"DE",
    "sg:address":"Im Dorf 19",
    "sg:city":"\u00d6hringen",
    "sg:phone":"+49 7941/35381",
    "sg:postcode":"74613",
    "sg:province":"Baden-W\u00fcrttemberg",
    "wof:name":"Otto Weidner",
    "wof:placetype":"venue"
},
  "geometry": {"coordinates":[9.54616,49.190891],"type":"Point"}
}