{
  "type": "Feature",
  "properties": {
    "iso:country":"DE",
    "sg:address":"Erlenweg 2",
    "sg:city":"Bad Friedrichshall",
    "sg:phone":"+49 7136/6130",
    "sg:postcode":"74177",
    "sg:province":"Baden-W\u00fcrttemberg",
    "wof:name":"Restaurant Schnitzel Charly",
    "wof:placetype":"venue"
},
  "geometry": {"coordinates":[9.2123298645,49.2361297607],"type":"Point"}
}