{
  "type": "Feature",
  "properties": {
    "iso:country":"DE",
    "sg:address":"Siegfriedstr. 49-60",
    "sg:city":"Berlin",
    "sg:phone":"+49 30/55489515",
    "sg:postcode":"10365",
    "sg:province":"Berlin",
    "wof:name":"Care Dienstleistungsges. F\u00fcr Umz\u00fcge Technology",
    "wof:placetype":"venue"
},
  "geometry": {"coordinates":[13.499798,52.523289],"type":"Point"}
}