{
  "type": "Feature",
  "properties": {
    "iso:country":"DE",
    "sg:address":"Dieskaustr. 193",
    "sg:city":"Leipzig",
    "sg:phone":"+49 341/4252621",
    "sg:postcode":"04249",
    "sg:province":"Sachsen",
    "wof:name":"Dachdeckerei Schleu\u00dfig Gmbh",
    "wof:placetype":"venue"
},
  "geometry": {"coordinates":[12.328018,51.302456],"type":"Point"}
}