{
  "type": "Feature",
  "properties": {
    "iso:country":"DE",
    "sg:address":"Hatzevennstr 27",
    "sg:city":"Monschau",
    "sg:phone":"+49 2472/7972",
    "sg:postcode":"52156",
    "sg:province":"Nordrhein-Westfalen",
    "wof:name":"Keiler Schutzhandschuh Handelsgesellschaft Mbh",
    "wof:placetype":"venue"
},
  "geometry": {"coordinates":[6.2469091415,50.5924072266],"type":"Point"}
}