{
  "type": "Feature",
  "properties": {
    "iso:country":"DE",
    "sg:address":"Weimarer Str. 11",
    "sg:city":"St. Wendel",
    "sg:phone":"+49 6851/93590",
    "sg:postcode":"66606",
    "sg:province":"Saarland",
    "wof:name":"H. D\u00f6rrenb\u00e4cher",
    "wof:placetype":"venue"
},
  "geometry": {"coordinates":[7.144657135,49.4617042542],"type":"Point"}
}