{
  "type": "Feature",
  "properties": {
    "iso:country":"DE",
    "sg:address":"Enkhausen 6",
    "sg:city":"Salzkotten",
    "sg:phone":"+49 5258/8304",
    "sg:postcode":"33154",
    "sg:province":"Nordrhein-Westfalen",
    "wof:name":"H. Wienecke",
    "wof:placetype":"venue"
},
  "geometry": {"coordinates":[8.556019,51.683273],"type":"Point"}
}