{
  "type": "Feature",
  "properties": {
    "iso:country":"DE",
    "sg:address":"Bahnhofstr. 34",
    "sg:city":"Bisingen",
    "sg:phone":"+49 7476/3505",
    "sg:postcode":"72406",
    "sg:province":"Baden-W\u00fcrttemberg",
    "wof:name":"Parkcafe",
    "wof:placetype":"venue"
},
  "geometry": {"coordinates":[8.923002,48.313274],"type":"Point"}
}