{
  "type": "Feature",
  "properties": {
    "iso:country":"DE",
    "sg:address":"Walter-Heinze-Str 11",
    "sg:city":"Leipzig",
    "sg:phone":"+49 4745/94920",
    "sg:postcode":"04229",
    "sg:province":"Sachsen",
    "wof:name":"Rudolf Kemner Fensterbau Gmbh",
    "wof:placetype":"venue"
},
  "geometry": {"coordinates":[8.815804,53.630787],"type":"Point"}
}