{
  "type": "Feature",
  "properties": {
    "iso:country":"DE",
    "sg:address":"Beethovenstr. 3",
    "sg:city":"Rastede",
    "sg:phone":"+49 4402/3232",
    "sg:postcode":"26180",
    "sg:province":"Niedersachsen",
    "wof:name":"Gerold Meyer Masseur",
    "wof:placetype":"venue"
},
  "geometry": {"coordinates":[8.202607,53.25687],"type":"Point"}
}