{
  "type": "Feature",
  "properties": {
    "iso:country":"DE",
    "sg:address":"Bahnhofstr. 16",
    "sg:city":"Geringswalde",
    "sg:phone":"+49 37382/81428",
    "sg:postcode":"09326",
    "sg:province":"Sachsen",
    "wof:name":"Johannes Brautzsch",
    "wof:placetype":"venue"
},
  "geometry": {"coordinates":[12.9067792892,51.0745697021],"type":"Point"}
}