{
  "type": "Feature",
  "properties": {
    "iso:country":"DE",
    "sg:address":"Maisachweg 5",
    "sg:city":"Bergkirchen",
    "sg:phone":"+49 180 5 482160",
    "sg:postcode":"85232",
    "sg:province":"Bayern",
    "wof:name":"G\u00fcnter Neumeier Rechtsanwalt",
    "wof:placetype":"venue"
},
  "geometry": {"coordinates":[11.397149086,48.2553634644],"type":"Point"}
}