{
  "type": "Feature",
  "properties": {
    "iso:country":"DE",
    "sg:address":"Offenbacher Landstr. 427",
    "sg:city":"Frankfurt",
    "sg:phone":"+49 69/65309545",
    "sg:postcode":"60599",
    "sg:province":"Hessen",
    "wof:name":"Mihaljevic & Sohn Gmbh",
    "wof:placetype":"venue"
},
  "geometry": {"coordinates":[8.731581,50.10054],"type":"Point"}
}