{
  "type": "Feature",
  "properties": {
    "iso:country":"DE",
    "sg:address":"Osdorfer Str. 125",
    "sg:city":"Berlin",
    "sg:postcode":"12207",
    "sg:province":"Berlin",
    "wof:name":"Ham-systemrestaurant- Gmbh",
    "wof:placetype":"venue"
},
  "geometry": {"coordinates":[13.3131341934,52.4192276001],"type":"Point"}
}