{
  "type": "Feature",
  "properties": {
    "iso:country":"DE",
    "sg:address":"Assenheimer Str. 1",
    "sg:city":"Frankfurt",
    "sg:phone":"+49 69/786856",
    "sg:postcode":"60489",
    "sg:province":"Hessen",
    "wof:name":"J.-n. Choi",
    "wof:placetype":"venue"
},
  "geometry": {"coordinates":[8.606004715,50.1243743896],"type":"Point"}
}