{
  "type": "Feature",
  "properties": {
    "iso:country":"DE",
    "sg:address":"Ulrichstr. 4",
    "sg:city":"Gelsenkirchen",
    "sg:phone":"+49 209/789095",
    "sg:postcode":"45891",
    "sg:province":"Nordrhein-Westfalen",
    "wof:name":"Maler-einkauf Rhein-ruhr Eg",
    "wof:placetype":"venue"
},
  "geometry": {"coordinates":[7.090606,51.550762],"type":"Point"}
}