{
  "type": "Feature",
  "properties": {
    "iso:country":"DE",
    "sg:address":"Hans-Werner-Str. 3",
    "sg:city":"Tyrlaching",
    "sg:phone":"+49 8623/7058",
    "sg:postcode":"84558",
    "sg:province":"Bayern",
    "wof:name":"Norbert Bergmeier",
    "wof:placetype":"venue"
},
  "geometry": {"coordinates":[12.6636991501,48.0607833862],"type":"Point"}
}