{
  "type": "Feature",
  "properties": {
    "iso:country":"DE",
    "sg:address":"Wichertstr. 14 a",
    "sg:city":"Berlin",
    "sg:postcode":"10439",
    "sg:province":"Berlin",
    "wof:name":"Bcm Bau Consult Management Gmbh",
    "wof:placetype":"venue"
},
  "geometry": {"coordinates":[13.418988,52.549099],"type":"Point"}
}