{
  "type": "Feature",
  "properties": {
    "iso:country":"DE",
    "sg:address":"Postfach 1180",
    "sg:city":"Sulzbach",
    "sg:postcode":"65837",
    "sg:province":"Hessen",
    "wof:name":"Cma Atlas Computer Leasing Gmbh",
    "wof:placetype":"venue"
},
  "geometry": {"coordinates":[8.5271196365,50.1338806152],"type":"Point"}
}