{
  "type": "Feature",
  "properties": {
    "iso:country":"DE",
    "sg:address":"Meppener Str. 9",
    "sg:city":"Geeste",
    "sg:phone":"+49 5937/7411",
    "sg:postcode":"49744",
    "sg:province":"Niedersachsen",
    "wof:name":"Coma-markt",
    "wof:placetype":"venue"
},
  "geometry": {"coordinates":[7.2342061996,52.5944137573],"type":"Point"}
}