{
  "type": "Feature",
  "properties": {
    "iso:country":"DE",
    "sg:address":"Am Treptower Park 39",
    "sg:city":"Berlin",
    "sg:phone":"+49 30/5337216",
    "sg:postcode":"12435",
    "sg:province":"Berlin",
    "wof:name":"Geographischer Verlag Gottfried R. Preuss",
    "wof:placetype":"venue"
},
  "geometry": {"coordinates":[13.465897,52.485977],"type":"Point"}
}