{
  "type": "Feature",
  "properties": {
    "iso:country":"DE",
    "sg:address":"Neustr. 25",
    "sg:city":"Kempen",
    "sg:phone":"+49 2152/3494",
    "sg:postcode":"47906",
    "sg:province":"Nordrhein-Westfalen",
    "wof:name":"Gastst\u00e4tte Altstadt",
    "wof:placetype":"venue"
},
  "geometry": {"coordinates":[6.4169478416,51.3646087646],"type":"Point"}
}