{
  "type": "Feature",
  "properties": {
    "iso:country":"DE",
    "sg:address":"Am Bienenstock 2",
    "sg:city":"Frankfurt",
    "sg:phone":"+49 6109/22915",
    "sg:postcode":"60388",
    "sg:province":"Hessen",
    "wof:name":"Transport Management Burkhard Kick Ges. Mbh",
    "wof:placetype":"venue"
},
  "geometry": {"coordinates":[8.7580604553,50.1551895142],"type":"Point"}
}