{
  "type": "Feature",
  "properties": {
    "iso:country":"DE",
    "sg:address":"Bahnhofstr. 55",
    "sg:city":"Harxheim",
    "sg:phone":"+49 6138/7887",
    "sg:postcode":"55296",
    "sg:province":"Rheinland-Pfalz",
    "wof:name":"N. Engelhardt",
    "wof:placetype":"venue"
},
  "geometry": {"coordinates":[8.2698802948,49.9035072327],"type":"Point"}
}