{
  "type": "Feature",
  "properties": {
    "iso:country":"DE",
    "sg:address":"Zum Kl\u00f6sterle 29",
    "sg:city":"N\u00fcrnberg",
    "sg:phone":"+49 911/884163",
    "sg:postcode":"90455",
    "sg:province":"Bayern",
    "wof:name":"Dieter Giffing Ingenieur",
    "wof:placetype":"venue"
},
  "geometry": {"coordinates":[11.0762577057,49.3797416687],"type":"Point"}
}