{
  "type": "Feature",
  "properties": {
    "iso:country":"DE",
    "sg:address":"M\u00fcnsterstr. 375",
    "sg:city":"D\u00fcsseldorf",
    "sg:postcode":"40470",
    "sg:province":"Nordrhein-Westfalen",
    "wof:name":"Donimic Hart Trend Fashion Gmbh",
    "wof:placetype":"venue"
},
  "geometry": {"coordinates":[6.803139,51.254326],"type":"Point"}
}