{
  "type": "Feature",
  "properties": {
    "iso:country":"DE",
    "sg:address":"Johannisallee 5",
    "sg:city":"Leipzig",
    "sg:phone":"+49 341/6883302",
    "sg:postcode":"04317",
    "sg:province":"Sachsen",
    "wof:name":"Terrawert Immobilienmanagement Gmbh",
    "wof:placetype":"venue"
},
  "geometry": {"coordinates":[12.39704,51.333508],"type":"Point"}
}