{
  "type": "Feature",
  "properties": {
    "iso:country":"DE",
    "sg:address":"Liebigstr. 6",
    "sg:city":"Lippstadt",
    "sg:phone":"+49 2941/12511",
    "sg:postcode":"59557",
    "sg:province":"Nordrhein-Westfalen",
    "wof:name":"Katholisches Pfarramt St. Pius",
    "wof:placetype":"venue"
},
  "geometry": {"coordinates":[8.3390378952,51.6560783386],"type":"Point"}
}