{
  "type": "Feature",
  "properties": {
    "iso:country":"DE",
    "sg:address":"Roteb\u00fchlstr. 104",
    "sg:city":"stuttgart",
    "sg:phone":"+49 711",
    "sg:postcode":"70197",
    "sg:province":"Baden-W\u00fcrttemberg",
    "wof:name":"Orthop\u00e4die",
    "wof:placetype":"venue"
},
  "geometry": {"coordinates":[9.15803,48.77058],"type":"Point"}
}