{
  "type": "Feature",
  "properties": {
    "iso:country":"DE",
    "sg:address":"Berliner Chaussee 66",
    "sg:city":"Magdeburg",
    "sg:phone":"+49 391/85070",
    "sg:postcode":"39114",
    "sg:province":"Sachsen-Anhalt",
    "wof:name":"\u00d6hmi Engineering Gmbh",
    "wof:placetype":"venue"
},
  "geometry": {"coordinates":[11.67463,52.12986],"type":"Point"}
}