{
  "type": "Feature",
  "properties": {
    "iso:country":"DE",
    "sg:address":"Vogesenstra\u00dfe 106",
    "sg:city":"Muggensturm",
    "sg:phone":"+49 7222/52007",
    "sg:postcode":"76461",
    "sg:province":"Baden-W\u00fcrttemberg",
    "wof:name":"Formplast Deutschland Verkaufsb\u00fcro Hersteller Tragetaschen",
    "wof:placetype":"venue"
},
  "geometry": {"coordinates":[8.287701,48.877422],"type":"Point"}
}