{
  "type": "Feature",
  "properties": {
    "iso:country":"DE",
    "sg:address":"Karl-Marx-Str. 46",
    "sg:city":"Zernsdorf",
    "sg:phone":"+49 3375/293575",
    "sg:postcode":"15758",
    "sg:province":"Brandenburg",
    "wof:name":"Harry Look",
    "wof:placetype":"venue"
},
  "geometry": {"coordinates":[13.696894,52.298717],"type":"Point"}
}