{
  "type": "Feature",
  "properties": {
    "iso:country":"DE",
    "sg:address":"Langelohstr. 119",
    "sg:city":"Hamburg",
    "sg:phone":"+49 40/801205",
    "sg:postcode":"22609",
    "sg:province":"Hamburg",
    "wof:name":"Ev. Pfarramt St. Simeon",
    "wof:placetype":"venue"
},
  "geometry": {"coordinates":[9.8447198868,53.553604126],"type":"Point"}
}