{
  "type": "Feature",
  "properties": {
    "iso:country":"DE",
    "sg:address":"Bentheimer Str. 32",
    "sg:city":"Nordhorn",
    "sg:phone":"+49 5921/4607",
    "sg:postcode":"48529",
    "sg:province":"Niedersachsen",
    "wof:name":"Hermann Aldekamp & Sohn Gemischtwarenhandlung E. K.",
    "wof:placetype":"venue"
},
  "geometry": {"coordinates":[7.070253849,52.4308509827],"type":"Point"}
}