{
  "type": "Feature",
  "properties": {
    "iso:country":"DE",
    "sg:address":"Waldweg 56",
    "sg:city":"Uhldingen-M\u00fchlhofen",
    "sg:phone":"+49 7556/6743",
    "sg:postcode":"88690",
    "sg:province":"Baden-W\u00fcrttemberg",
    "wof:name":"K. Becker Kosmetiksalon",
    "wof:placetype":"venue"
},
  "geometry": {"coordinates":[9.2379198074,47.7155799866],"type":"Point"}
}