{
  "type": "Feature",
  "properties": {
    "iso:country":"DE",
    "sg:address":"Hirtenweg 9",
    "sg:city":"L\u00fcneburg",
    "sg:phone":"+49 4131/42538",
    "sg:postcode":"21335",
    "sg:province":"Niedersachsen",
    "wof:name":"Peter Mews",
    "wof:placetype":"venue"
},
  "geometry": {"coordinates":[10.3890647888,53.2319564819],"type":"Point"}
}