{
  "type": "Feature",
  "properties": {
    "iso:country":"DE",
    "sg:address":"Schlo\u00dfplatz 16",
    "sg:city":"Saarbr\u00fccken",
    "sg:phone":"+49 681/9540511",
    "sg:postcode":"66119",
    "sg:province":"Saarland",
    "wof:name":"Landesmuseum F\u00fcr Vor- Und Fr\u00fchgeschichte",
    "wof:placetype":"venue"
},
  "geometry": {"coordinates":[6.991485,49.230129],"type":"Point"}
}