{
  "type": "Feature",
  "properties": {
    "iso:country":"DE",
    "sg:address":"Huttengasse 8",
    "sg:city":"Bad Soden-Salm\u00fcnster",
    "sg:phone":"+49 6056/1753",
    "sg:postcode":"63628",
    "sg:province":"Hessen",
    "wof:name":"Willi Dieter",
    "wof:placetype":"venue"
},
  "geometry": {"coordinates":[9.367258,50.276863],"type":"Point"}
}