{
  "type": "Feature",
  "properties": {
    "iso:country":"DE",
    "sg:address":"Am Waisenhausplatz 26",
    "sg:city":"Pforzheim",
    "sg:postcode":"75172",
    "sg:province":"Baden-W\u00fcrttemberg",
    "wof:name":"Mode Am Theater",
    "wof:placetype":"venue"
},
  "geometry": {"coordinates":[8.700237,48.890022],"type":"Point"}
}