{
  "type": "Feature",
  "properties": {
    "iso:country":"DE",
    "sg:address":"Almestr. 1",
    "sg:city":"Bielefeld",
    "sg:phone":"+49 521/48086",
    "sg:postcode":"33649",
    "sg:province":"Nordrhein-Westfalen",
    "wof:name":"Margarete Maser-ulrichsk\u00f6tter",
    "wof:placetype":"venue"
},
  "geometry": {"coordinates":[8.4395751953,51.969997406],"type":"Point"}
}