{
  "type": "Feature",
  "properties": {
    "iso:country":"DE",
    "sg:address":"Industriestr. 19 B",
    "sg:city":"Oyten",
    "sg:phone":"+49 4207/910095",
    "sg:postcode":"28876",
    "sg:province":"Niedersachsen",
    "wof:name":"Bdt Banken & Daten- Technik Uwe R\u00f6mer E. K.",
    "wof:placetype":"venue"
},
  "geometry": {"coordinates":[9.0335502625,53.0557136536],"type":"Point"}
}