{
  "type": "Feature",
  "properties": {
    "iso:country":"DE",
    "sg:address":"Jakobstr. 40",
    "sg:city":"Magdeburg",
    "sg:phone":"+49 391/5434266",
    "sg:postcode":"39104",
    "sg:province":"Sachsen-Anhalt",
    "wof:name":"Rosemarie Unbescheidt",
    "wof:placetype":"venue"
},
  "geometry": {"coordinates":[11.6445541382,52.135433197],"type":"Point"}
}