{
  "type": "Feature",
  "properties": {
    "iso:country":"DE",
    "sg:address":"Stra\u00dfe zum Reitplatz",
    "sg:city":"Wildberg",
    "sg:phone":"+49 39604/20292",
    "sg:postcode":"17091",
    "sg:province":"Mecklenburg-Vorpommern",
    "wof:name":"D. Gruschinski",
    "wof:placetype":"venue"
},
  "geometry": {"coordinates":[13.122995,53.65134],"type":"Point"}
}