{
  "type": "Feature",
  "properties": {
    "iso:country":"DE",
    "sg:address":"Gro\u00dfstr. 28",
    "sg:city":"Treuenbrietzen",
    "sg:phone":"+49 33748/76410",
    "sg:postcode":"14929",
    "sg:province":"Brandenburg",
    "wof:name":"Wwn Wasserwirtschafts- Gesellschaft Nieplitztal Mbh",
    "wof:placetype":"venue"
},
  "geometry": {"coordinates":[12.8721523285,52.0980796814],"type":"Point"}
}