{
  "type": "Feature",
  "properties": {
    "iso:country":"DE",
    "sg:address":"Unter- 37-39",
    "sg:city":"K\u00f6ln",
    "sg:postcode":"50668",
    "sg:province":"Nordrhein-Westfalen",
    "wof:name":"Stellenangebote / Stellenmarkt",
    "wof:placetype":"venue"
},
  "geometry": {"coordinates":[6.955065,50.941654],"type":"Point"}
}