{
  "type": "Feature",
  "properties": {
    "iso:country":"DE",
    "sg:address":"Meistersingerstr. 24 b",
    "sg:city":"Stuttgart",
    "sg:phone":"+49 711/762397",
    "sg:postcode":"70597",
    "sg:province":"Baden-W\u00fcrttemberg",
    "wof:name":"Eberhard Sch\u00f6nthaler Architekt",
    "wof:placetype":"venue"
},
  "geometry": {"coordinates":[9.170468,48.753277],"type":"Point"}
}