{
  "type": "Feature",
  "properties": {
    "iso:country":"DE",
    "sg:address":"Bi-Gstl-Rt-J-Zinnb-Str 8",
    "sg:city":"Dingolfing",
    "sg:phone":"+49 8731/1383",
    "sg:postcode":"84130",
    "sg:province":"Bayern",
    "wof:name":"B\u00fcrgerheim Der Oberen Spitalstiftung",
    "wof:placetype":"venue"
},
  "geometry": {"coordinates":[12.49812,48.628975],"type":"Point"}
}