{
  "type": "Feature",
  "properties": {
    "iso:country":"DE",
    "sg:address":"W\u00e4tjenstr. 22",
    "sg:city":"Bremen",
    "sg:phone":"+49 421/212496",
    "sg:postcode":"28213",
    "sg:province":"Bremen",
    "wof:name":"Wolfgang Und Brigitte Jarchow",
    "wof:placetype":"venue"
},
  "geometry": {"coordinates":[8.8485212326,53.0875053406],"type":"Point"}
}