{
  "type": "Feature",
  "properties": {
    "iso:country":"DE",
    "sg:address":"Norderstr. 26",
    "sg:city":"Elmshorn",
    "sg:phone":"+49 4121/2380",
    "sg:postcode":"25335",
    "sg:province":"Schleswig-Holstein",
    "wof:name":"Dorothea Schilling Computersysteme Gmbh",
    "wof:placetype":"venue"
},
  "geometry": {"coordinates":[9.6564235687,53.7582321167],"type":"Point"}
}