{
  "type": "Feature",
  "properties": {
    "iso:country":"DE",
    "sg:address":"Kurf\u00fcrstenstr. 39",
    "sg:city":"Ellenz-Poltersdorf",
    "sg:phone":"+49 2673/1863",
    "sg:postcode":"56821",
    "sg:province":"Rheinland-Pfalz",
    "wof:name":"Roman Weber",
    "wof:placetype":"venue"
},
  "geometry": {"coordinates":[7.2240190506,50.1077156067],"type":"Point"}
}