{
  "type": "Feature",
  "properties": {
    "iso:country":"DE",
    "sg:address":"Akazienweg 12",
    "sg:city":"Hennef",
    "sg:phone":"+49 2242/869313",
    "sg:postcode":"53773",
    "sg:province":"Nordrhein-Westfalen",
    "wof:name":"Fliesen-r\u00fchle Gmbh",
    "wof:placetype":"venue"
},
  "geometry": {"coordinates":[7.334286,50.766201],"type":"Point"}
}