{
  "type": "Feature",
  "properties": {
    "iso:country":"DE",
    "sg:address":"W\u00fcschheimer Str. 49",
    "sg:city":"Euskirchen",
    "sg:phone":"+49 2251/52539",
    "sg:postcode":"53881",
    "sg:province":"Nordrhein-Westfalen",
    "wof:name":"Wilhelm J. Schmitz",
    "wof:placetype":"venue"
},
  "geometry": {"coordinates":[6.810917,50.690014],"type":"Point"}
}