{
  "type": "Feature",
  "properties": {
    "iso:country":"DE",
    "sg:address":"Deggendorfer Str. 4",
    "sg:city":"Bernried",
    "sg:phone":"+49 9905/8732",
    "sg:postcode":"94505",
    "sg:province":"Bayern",
    "wof:name":"G. Und L. Biller E. K.",
    "wof:placetype":"venue"
},
  "geometry": {"coordinates":[12.8829755783,48.9160346985],"type":"Point"}
}