{
  "type": "Feature",
  "properties": {
    "iso:country":"DE",
    "sg:address":"L\u00fcneburger Heerstr. 69",
    "sg:city":"Celle",
    "sg:phone":"+49 5141/32411",
    "sg:postcode":"29223",
    "sg:province":"Niedersachsen",
    "wof:name":"Erich Poschmann",
    "wof:placetype":"venue"
},
  "geometry": {"coordinates":[10.0991172791,52.6346244812],"type":"Point"}
}