{
  "type": "Feature",
  "properties": {
    "iso:country":"DE",
    "sg:address":"Kanonenweg 16",
    "sg:city":"Coburg",
    "sg:phone":"+49 9561/66210",
    "sg:postcode":"96450",
    "sg:province":"Bayern",
    "wof:name":"August Hofmann & S\u00f6hne",
    "wof:placetype":"venue"
},
  "geometry": {"coordinates":[10.9631986618,50.2682151794],"type":"Point"}
}