{
  "type": "Feature",
  "properties": {
    "iso:country":"DE",
    "sg:address":"Jahnstra\u00dfe 19",
    "sg:city":"D\u00fcsseldorf",
    "sg:phone":"+49 211/386860",
    "sg:postcode":"40215",
    "sg:province":"Nordrhein-Westfalen",
    "wof:name":"Bu\u00f1ol Und Ihrer Tomatina -spanien 8/2000",
    "wof:placetype":"venue"
},
  "geometry": {"coordinates":[6.780539,51.216408],"type":"Point"}
}