{
  "type": "Feature",
  "properties": {
    "iso:country":"DE",
    "sg:address":"Friedensstr. 8",
    "sg:city":"Teltow",
    "sg:phone":"+49 3328/473784",
    "sg:postcode":"14513",
    "sg:province":"Brandenburg",
    "wof:name":"Bernd Ebert",
    "wof:placetype":"venue"
},
  "geometry": {"coordinates":[13.2530117035,52.3979301453],"type":"Point"}
}