{
  "type": "Feature",
  "properties": {
    "iso:country":"DE",
    "sg:address":"Kalver Landweg 7",
    "sg:city":"L\u00fcdenscheid",
    "sg:phone":"+49 2351/94970",
    "sg:postcode":"58511",
    "sg:province":"Nordrhein-Westfalen",
    "wof:name":"Kurt N\u00f6renberg Immobilienmakler",
    "wof:placetype":"venue"
},
  "geometry": {"coordinates":[7.6571211815,51.2165870667],"type":"Point"}
}