{
  "type": "Feature",
  "properties": {
    "iso:country":"DE",
    "sg:address":"Am Rathaus 1",
    "sg:city":"Gro\u00dfolbersdorf",
    "sg:postcode":"09432",
    "sg:province":"Sachsen",
    "wof:name":"Lpg Morgenrot Gro\u00dfolbersdorf",
    "wof:placetype":"venue"
},
  "geometry": {"coordinates":[13.0889987946,50.6940994263],"type":"Point"}
}