{
  "type": "Feature",
  "properties": {
    "iso:country":"DE",
    "sg:address":"Postfach 1320:: 85554 Ebersberg:: Germany.^^Sparkassenplatz::",
    "sg:city":"Ebersberg",
    "sg:phone":"+49 8092/2310",
    "sg:postcode":"85560",
    "sg:province":"Bayern",
    "wof:name":"Kreissparkasse Ebersberg",
    "wof:placetype":"venue"
},
  "geometry": {"coordinates":[11.96856,48.07843],"type":"Point"}
}