{
  "type": "Feature",
  "properties": {
    "iso:country":"DE",
    "sg:address":"Togostr. 24",
    "sg:city":"Duisburg",
    "sg:phone":"+49 203/666249",
    "sg:postcode":"47249",
    "sg:province":"Nordrhein-Westfalen",
    "wof:name":"Willy Striebing Mode- Und Bekleidungshaus",
    "wof:placetype":"venue"
},
  "geometry": {"coordinates":[6.764454,51.372765],"type":"Point"}
}