{
  "type": "Feature",
  "properties": {
    "iso:country":"DE",
    "sg:address":"Hohnsteinerstr. 18",
    "sg:city":"Ilfeld",
    "sg:phone":"+49 36331/46554",
    "sg:postcode":"99768",
    "sg:province":"Th\u00fcringen",
    "wof:name":"Oscar Jentsch",
    "wof:placetype":"venue"
},
  "geometry": {"coordinates":[10.792367,51.575764],"type":"Point"}
}