{
  "type": "Feature",
  "properties": {
    "iso:country":"DE",
    "sg:address":"Sonnenstr. 2a",
    "sg:city":"Sonthofen",
    "sg:phone":"+49 8321/2061",
    "sg:postcode":"87527",
    "sg:province":"Bayern",
    "wof:name":"Dipl. H. Locher Gmbh",
    "wof:placetype":"venue"
},
  "geometry": {"coordinates":[10.2783317566,47.5098457336],"type":"Point"}
}