{
  "type": "Feature",
  "properties": {
    "iso:country":"DE",
    "sg:address":"Langer Damm 4",
    "sg:city":"Wei\u00dfensee",
    "sg:phone":"+49 36374/20435",
    "sg:postcode":"99631",
    "sg:province":"Th\u00fcringen",
    "wof:name":"Gastst\u00e4tte Pfortenst\u00fcbchen",
    "wof:placetype":"venue"
},
  "geometry": {"coordinates":[11.0681228638,51.1977424622],"type":"Point"}
}