{
  "type": "Feature",
  "properties": {
    "iso:country":"DE",
    "sg:address":"Schlehenweg 1",
    "sg:city":"Haiger Offdilln",
    "sg:postcode":"35708",
    "sg:province":"Hessen",
    "wof:name":"Jugendfeuerwehr Haiger Offdilln",
    "wof:placetype":"venue"
},
  "geometry": {"coordinates":[8.199496,50.743801],"type":"Point"}
}