{
  "type": "Feature",
  "properties": {
    "iso:country":"DE",
    "sg:address":"Wilhelm-Leuschner-Str 1",
    "sg:city":"Frickenhausen",
    "sg:phone":"+49 7022/97780",
    "sg:postcode":"72636",
    "sg:province":"Baden-W\u00fcrttemberg",
    "wof:name":"Dd Kabelkonfektion Dropulic Gmbh",
    "wof:placetype":"venue"
},
  "geometry": {"coordinates":[9.356845,48.600769],"type":"Point"}
}