{
  "type": "Feature",
  "properties": {
    "iso:country":"DE",
    "sg:address":"Altenschwand",
    "sg:city":"Rickenbach",
    "sg:phone":"+49 7765/320",
    "sg:postcode":"79736",
    "sg:province":"Baden-W\u00fcrttemberg",
    "wof:name":"Franz Baumgartner",
    "wof:placetype":"venue"
},
  "geometry": {"coordinates":[7.982191,47.636497],"type":"Point"}
}