{
  "type": "Feature",
  "properties": {
    "iso:country":"DE",
    "sg:address":"Erikastr. 21",
    "sg:city":"Osnabr\u00fcck",
    "sg:phone":"+49 541/37317",
    "sg:postcode":"49086",
    "sg:province":"Niedersachsen",
    "wof:name":"Hermann Heidbrink Verwaltungs-gmbh",
    "wof:placetype":"venue"
},
  "geometry": {"coordinates":[8.096335,52.255741],"type":"Point"}
}