{
  "type": "Feature",
  "properties": {
    "iso:country":"DE",
    "sg:address":"Koellestr. 33",
    "sg:city":"Karlsruhe",
    "sg:phone":"+49 721/571049",
    "sg:postcode":"76189",
    "sg:province":"Baden-W\u00fcrttemberg",
    "wof:name":"Schmitt",
    "wof:placetype":"venue"
},
  "geometry": {"coordinates":[8.311076,49.012386],"type":"Point"}
}