{
  "type": "Feature",
  "properties": {
    "iso:country":"DE",
    "sg:address":"Bl\u00fcmgesgrundstr. 14",
    "sg:city":"Gelnhausen",
    "sg:phone":"+49 6051/68148",
    "sg:postcode":"63571",
    "sg:province":"Hessen",
    "wof:name":"Hans-joachim P\u00f6ss",
    "wof:placetype":"venue"
},
  "geometry": {"coordinates":[9.158873558,50.1827316284],"type":"Point"}
}