{
  "type": "Feature",
  "properties": {
    "iso:country":"DE",
    "sg:address":"Rauchleder 9",
    "sg:city":"M\u00fchlhausen",
    "sg:phone":"+49 6222",
    "sg:postcode":"69242",
    "sg:province":"Baden-W\u00fcrttemberg",
    "wof:name":"Jugendfeuerwehr M\u00fchlhausen",
    "wof:placetype":"venue"
},
  "geometry": {"coordinates":[8.721593,49.244961],"type":"Point"}
}