{
  "type": "Feature",
  "properties": {
    "iso:country":"DE",
    "sg:address":"Am Bahnhof 11",
    "sg:city":"Bad Iburg",
    "sg:phone":"+49 5403/5310",
    "sg:postcode":"49186",
    "sg:province":"Niedersachsen",
    "wof:name":"Martin Gerkensmeier",
    "wof:placetype":"venue"
},
  "geometry": {"coordinates":[8.0433597565,52.150478363],"type":"Point"}
}