{
  "type": "Feature",
  "properties": {
    "iso:country":"DE",
    "sg:address":"Kiefernweg 15",
    "sg:city":"Gaimersheim",
    "sg:phone":"+49 8406/1379",
    "sg:postcode":"85080",
    "sg:province":"Bayern",
    "wof:name":"Bergmann-bock-filmproduktion",
    "wof:placetype":"venue"
},
  "geometry": {"coordinates":[11.367956,48.838966],"type":"Point"}
}