{
  "type": "Feature",
  "properties": {
    "iso:country":"DE",
    "sg:address":"Schmalheck 12",
    "sg:city":"H\u00fcttenberg",
    "sg:phone":"+49 6441/75957",
    "sg:postcode":"35625",
    "sg:province":"Hessen",
    "wof:name":"Wolfgang Schick",
    "wof:placetype":"venue"
},
  "geometry": {"coordinates":[8.5733318329,50.5268516541],"type":"Point"}
}