{
  "type": "Feature",
  "properties": {
    "iso:country":"DE",
    "sg:address":"Moltkestr. 2",
    "sg:city":"L\u00fcnen",
    "sg:phone":"+49 2306/928880",
    "sg:postcode":"44536",
    "sg:province":"Nordrhein-Westfalen",
    "wof:name":"Werner Heinrichs",
    "wof:placetype":"venue"
},
  "geometry": {"coordinates":[7.5140781403,51.612197876],"type":"Point"}
}