{
  "type": "Feature",
  "properties": {
    "iso:country":"DE",
    "sg:address":"Holzengasse 25",
    "sg:city":"Ramsau",
    "sg:phone":"+49 8657/510",
    "sg:postcode":"83486",
    "sg:province":"Bayern",
    "wof:name":"G\u00e4stehaus Lichtmannegger",
    "wof:placetype":"venue"
},
  "geometry": {"coordinates":[12.8983364105,47.6081695557],"type":"Point"}
}