{
  "type": "Feature",
  "properties": {
    "iso:country":"DE",
    "sg:address":"Grunderm\u00fchle 4a",
    "sg:city":"K\u00fcrten",
    "sg:phone":"+49 2268/1470",
    "sg:postcode":"51515",
    "sg:province":"Nordrhein-Westfalen",
    "wof:name":"Klemens Bosbach",
    "wof:placetype":"venue"
},
  "geometry": {"coordinates":[7.2750449181,51.0224151611],"type":"Point"}
}