{
  "type": "Feature",
  "properties": {
    "iso:country":"DE",
    "sg:address":"Am Spielberg 5",
    "sg:city":"Isselburg",
    "sg:phone":"+49 2874/2238",
    "sg:postcode":"46419",
    "sg:province":"Nordrhein-Westfalen",
    "wof:name":"Bernhard Sackers Berufs- Und Schutzkleidung Gmbh",
    "wof:placetype":"venue"
},
  "geometry": {"coordinates":[6.442355,51.812283],"type":"Point"}
}