{
  "type": "Feature",
  "properties": {
    "iso:country":"DE",
    "sg:address":"Schirnbecker Teiche 34",
    "sg:city":"Essen",
    "sg:phone":"+49 201/531118",
    "sg:postcode":"45279",
    "sg:province":"Nordrhein-Westfalen",
    "wof:name":"C. Rau & A. Heininger",
    "wof:placetype":"venue"
},
  "geometry": {"coordinates":[7.115979,51.44582],"type":"Point"}
}