{
  "type": "Feature",
  "properties": {
    "iso:country":"DE",
    "sg:address":"Bahnhofstr. 175",
    "sg:city":"Neu-Isenburg",
    "sg:phone":"+49 6102/21969",
    "sg:postcode":"63263",
    "sg:province":"Hessen",
    "wof:name":"Spiegelchen",
    "wof:placetype":"venue"
},
  "geometry": {"coordinates":[8.6801290512,50.0532836914],"type":"Point"}
}