{
  "type": "Feature",
  "properties": {
    "iso:country":"DE",
    "sg:address":"Arthur-Hoffmann-Str. 157",
    "sg:city":"Leipzig",
    "sg:phone":"+49 341/3026883",
    "sg:postcode":"04277",
    "sg:province":"Sachsen",
    "wof:name":"Peter Senger Rechtsanwalt",
    "wof:placetype":"venue"
},
  "geometry": {"coordinates":[12.3788375854,51.3132896423],"type":"Point"}
}