{
  "type": "Feature",
  "properties": {
    "iso:country":"DE",
    "sg:address":"Schwerinstr. 27",
    "sg:city":"M\u00fclheim",
    "sg:phone":"+49 208/9926080",
    "sg:postcode":"45476",
    "sg:province":"Nordrhein-Westfalen",
    "wof:name":"Klimapartner Von Der Heidt Gmbh",
    "wof:placetype":"venue"
},
  "geometry": {"coordinates":[6.8530988693,51.4524688721],"type":"Point"}
}