{
  "type": "Feature",
  "properties": {
    "iso:country":"DE",
    "sg:address":"Bahnhofstr. 7",
    "sg:city":"Rheinfelden",
    "sg:phone":"+49 7623/4850",
    "sg:postcode":"79618",
    "sg:province":"Baden-W\u00fcrttemberg",
    "wof:name":"H. Hornsteiner",
    "wof:placetype":"venue"
},
  "geometry": {"coordinates":[7.732981,47.556107],"type":"Point"}
}