{
  "type": "Feature",
  "properties": {
    "iso:country":"DE",
    "sg:address":"Pr\u00f6hlsfeld 4",
    "sg:city":"Fallingbostel",
    "sg:phone":"+49 5162/2021",
    "sg:postcode":"29683",
    "sg:province":"Niedersachsen",
    "wof:name":"W. K\u00fcsel H\u00fcte",
    "wof:placetype":"venue"
},
  "geometry": {"coordinates":[9.6901531219,52.8595428467],"type":"Point"}
}