{
  "type": "Feature",
  "properties": {
    "iso:country":"DE",
    "sg:address":"Otto-Hahn-Str. 7",
    "sg:city":"Verden",
    "sg:phone":"+49 4231/64248",
    "sg:postcode":"27283",
    "sg:province":"Niedersachsen",
    "wof:name":"Mass Metallbau Gmbh & Co. Kg",
    "wof:placetype":"venue"
},
  "geometry": {"coordinates":[9.26092,52.912842],"type":"Point"}
}