{
  "type": "Feature",
  "properties": {
    "iso:country":"DE",
    "sg:address":"Berliner Str. 54b",
    "sg:city":"Braunschweig",
    "sg:phone":"+49 531/377077",
    "sg:postcode":"38104",
    "sg:province":"Niedersachsen",
    "wof:name":"H & C Autovermietung",
    "wof:placetype":"venue"
},
  "geometry": {"coordinates":[10.574657,52.280842],"type":"Point"}
}