{
  "type": "Feature",
  "properties": {
    "iso:country":"DE",
    "sg:address":"Sch\u00f6nbuchstr. 3",
    "sg:city":"Hildrizhausen",
    "sg:phone":"+49 7034/4215",
    "sg:postcode":"71157",
    "sg:province":"Baden-W\u00fcrttemberg",
    "wof:name":"E. Wichtermann",
    "wof:placetype":"venue"
},
  "geometry": {"coordinates":[8.9755,48.624748],"type":"Point"}
}