{
  "type": "Feature",
  "properties": {
    "iso:country":"DE",
    "sg:address":"Wiesenstr. 16",
    "sg:city":"Stockach",
    "sg:phone":"+49 7771/61876",
    "sg:postcode":"78333",
    "sg:province":"Baden-W\u00fcrttemberg",
    "wof:name":"Soziale U. Famili\u00e4re Hilfe E. V.",
    "wof:placetype":"venue"
},
  "geometry": {"coordinates":[9.107381,47.85136],"type":"Point"}
}