{
  "type": "Feature",
  "properties": {
    "iso:country":"DE",
    "sg:address":"Ermelesstr. 79",
    "sg:city":"Hechingen",
    "sg:phone":"+49 4974/715052",
    "sg:postcode":"72379",
    "sg:province":"Baden-W\u00fcrttemberg",
    "wof:name":"Hubert Zanger Gmbh",
    "wof:placetype":"venue"
},
  "geometry": {"coordinates":[8.961314,48.367611],"type":"Point"}
}