{
  "type": "Feature",
  "properties": {
    "iso:country":"DE",
    "sg:address":"Kirchstr. 25a",
    "sg:city":"Ehringshausen",
    "sg:phone":"+49 6449/432",
    "sg:postcode":"35630",
    "sg:province":"Hessen",
    "wof:name":"Maria Bangel",
    "wof:placetype":"venue"
},
  "geometry": {"coordinates":[8.35237,50.618366],"type":"Point"}
}