{
  "type": "Feature",
  "properties": {
    "iso:country":"DE",
    "sg:address":"Hauptmannstr. 2d",
    "sg:city":"Brieselang",
    "sg:phone":"+49 33232/41630",
    "sg:postcode":"14656",
    "sg:province":"Brandenburg",
    "wof:name":"Freiberg & Wende Handelsvertretungen",
    "wof:placetype":"venue"
},
  "geometry": {"coordinates":[12.990271,52.577763],"type":"Point"}
}