{
  "type": "Feature",
  "properties": {
    "iso:country":"DE",
    "sg:address":"Birkenweg 9 a",
    "sg:city":"Affing",
    "sg:phone":"+49 8207/310",
    "sg:postcode":"86444",
    "sg:province":"Bayern",
    "wof:name":"Hartl Immobilien- Verwaltungs Gmbh",
    "wof:placetype":"venue"
},
  "geometry": {"coordinates":[10.9370660782,48.4360580444],"type":"Point"}
}