{
  "type": "Feature",
  "properties": {
    "iso:country":"DE",
    "sg:address":"Steigenhohlstr. 39",
    "sg:city":"Ettlingen",
    "sg:phone":"+49 7243/12882",
    "sg:postcode":"76275",
    "sg:province":"Baden-W\u00fcrttemberg",
    "wof:name":"Ines Keydel Rechtsanw\u00e4ltin",
    "wof:placetype":"venue"
},
  "geometry": {"coordinates":[8.4171762466,48.9455604553],"type":"Point"}
}