{
  "type": "Feature",
  "properties": {
    "iso:country":"DE",
    "sg:address":"Bertuchstr. 8",
    "sg:city":"Weimar",
    "sg:phone":"+49 3643/904130",
    "sg:postcode":"99423",
    "sg:province":"Th\u00fcringen",
    "wof:name":"W. Baumgarten",
    "wof:placetype":"venue"
},
  "geometry": {"coordinates":[11.3233270645,50.9858016968],"type":"Point"}
}