{
  "type": "Feature",
  "properties": {
    "iso:country":"DE",
    "sg:address":"Bahnhofstr. 70",
    "sg:city":"Kornwestheim",
    "sg:phone":"+49 7154/26476",
    "sg:postcode":"70806",
    "sg:province":"Baden-W\u00fcrttemberg",
    "wof:name":"Gastst\u00e4tte Kupferd\u00e4chle",
    "wof:placetype":"venue"
},
  "geometry": {"coordinates":[9.1794528961,48.8637466431],"type":"Point"}
}