{
  "type": "Feature",
  "properties": {
    "iso:country":"DE",
    "sg:address":"Bautzner Landstr. 101",
    "sg:city":"Dresden",
    "sg:phone":"+49 351/2683923",
    "sg:postcode":"01324",
    "sg:province":"Sachsen",
    "wof:name":"Video-m\u00fcller",
    "wof:placetype":"venue"
},
  "geometry": {"coordinates":[13.8691034317,51.0613899231],"type":"Point"}
}