{
  "type": "Feature",
  "properties": {
    "iso:country":"DE",
    "sg:address":"Marktplatz 2",
    "sg:city":"Abenberg",
    "sg:phone":"+49 9178/711",
    "sg:postcode":"91183",
    "sg:province":"Bayern",
    "wof:name":"Kath. \u00f6ffentliche B\u00fccherei",
    "wof:placetype":"venue"
},
  "geometry": {"coordinates":[10.961591,49.24202],"type":"Point"}
}