{
  "type": "Feature",
  "properties": {
    "iso:country":"DE",
    "sg:address":"Rathausstr. 8-9",
    "sg:city":"Halle",
    "sg:phone":"+49 345/2322875",
    "sg:postcode":"06108",
    "sg:province":"Sachsen-Anhalt",
    "wof:name":"Immobilienservice",
    "wof:placetype":"venue"
},
  "geometry": {"coordinates":[11.9733657837,51.4829902649],"type":"Point"}
}