{
  "type": "Feature",
  "properties": {
    "iso:country":"DE",
    "sg:address":"Kirchhofplatz 7",
    "sg:city":"Worms",
    "sg:phone":"+49 6241/34245",
    "sg:postcode":"67551",
    "sg:province":"Rheinland-Pfalz",
    "wof:name":"Ev. Pfarramt Heppenheim",
    "wof:placetype":"venue"
},
  "geometry": {"coordinates":[8.2638349533,49.603729248],"type":"Point"}
}