{
  "type": "Feature",
  "properties": {
    "iso:country":"DE",
    "sg:address":"Amselweg 10",
    "sg:city":"Gr\u00f6ditz",
    "sg:phone":"+49 35263/67585",
    "sg:postcode":"01609",
    "sg:province":"Sachsen",
    "wof:name":"Margarete Claus",
    "wof:placetype":"venue"
},
  "geometry": {"coordinates":[13.44524,51.41785],"type":"Point"}
}