{
  "type": "Feature",
  "properties": {
    "iso:country":"DE",
    "sg:address":"Kemnather Str. 3",
    "sg:city":"Pressath",
    "sg:phone":"+49 9644/91414",
    "sg:postcode":"92690",
    "sg:province":"Bayern",
    "wof:name":"C. Zankl",
    "wof:placetype":"venue"
},
  "geometry": {"coordinates":[11.9318647385,49.7710075378],"type":"Point"}
}