{
  "type": "Feature",
  "properties": {
    "iso:country":"DE",
    "sg:address":"Eschenbacher Str. 4",
    "sg:city":"Pressath",
    "sg:phone":"+49 9644/6155",
    "sg:postcode":"92690",
    "sg:province":"Bayern",
    "wof:name":"R. Huber",
    "wof:placetype":"venue"
},
  "geometry": {"coordinates":[11.9422149658,49.7627868652],"type":"Point"}
}