{
  "type": "Feature",
  "properties": {
    "iso:country":"DE",
    "sg:address":"Seestr. 28",
    "sg:city":"Frankfurt",
    "sg:phone":"+49 335/520912",
    "sg:postcode":"15236",
    "sg:province":"Brandenburg",
    "wof:name":"Schnellreinigungsservice Lehgra Gmbh",
    "wof:placetype":"venue"
},
  "geometry": {"coordinates":[14.542059,52.313126],"type":"Point"}
}