{
  "type": "Feature",
  "properties": {
    "iso:country":"DE",
    "sg:address":"Industriestr. 4",
    "sg:city":"Hutthurm",
    "sg:phone":"+49 8505/922512",
    "sg:postcode":"94116",
    "sg:province":"Bayern",
    "wof:name":"Arop Verwaltungs- U. Beteiligungs Gmbh",
    "wof:placetype":"venue"
},
  "geometry": {"coordinates":[13.484511,48.676666],"type":"Point"}
}