{
  "type": "Feature",
  "properties": {
    "iso:country":"DE",
    "sg:address":"Fr\u00fchlingstr. 1",
    "sg:city":"Weiden",
    "sg:phone":"+49 961/29897",
    "sg:postcode":"92637",
    "sg:province":"Bayern",
    "wof:name":"Jugendzentrum",
    "wof:placetype":"venue"
},
  "geometry": {"coordinates":[12.152558,49.677303],"type":"Point"}
}