{
  "type": "Feature",
  "properties": {
    "iso:country":"DE",
    "sg:address":"Im Sonntagsgarten 9",
    "sg:city":"Br\u00fchl",
    "sg:postcode":"50321",
    "sg:province":"Nordrhein-Westfalen",
    "wof:name":"Teged Gmbh",
    "wof:placetype":"venue"
},
  "geometry": {"coordinates":[6.8910560608,50.8436737061],"type":"Point"}
}