{
  "type": "Feature",
  "properties": {
    "iso:country":"DE",
    "sg:address":"Meckinghover Weg 20",
    "sg:city":"Datteln",
    "sg:phone":"+49 2363/62351",
    "sg:postcode":"45711",
    "sg:province":"Nordrhein-Westfalen",
    "wof:name":"Ev. Pfarramt S\u00fcd",
    "wof:placetype":"venue"
},
  "geometry": {"coordinates":[7.3275718689,51.6315574646],"type":"Point"}
}