{
  "type": "Feature",
  "properties": {
    "iso:country":"DE",
    "sg:address":"Mittelfeld 5",
    "sg:city":"Seefeld",
    "sg:phone":"+49 8152/78996",
    "sg:postcode":"82229",
    "sg:province":"Bayern",
    "wof:name":"Josef Oberhauser",
    "wof:placetype":"venue"
},
  "geometry": {"coordinates":[11.1895217896,48.0402603149],"type":"Point"}
}