{
  "type": "Feature",
  "properties": {
    "iso:country":"DE",
    "sg:address":"Detmolder Str. 175 b",
    "sg:city":"Bad Oeynhausen",
    "sg:postcode":"32545",
    "sg:province":"Nordrhein-Westfalen",
    "wof:name":"Kb-edv Gmbh",
    "wof:placetype":"venue"
},
  "geometry": {"coordinates":[8.801164,52.18298],"type":"Point"}
}