{
  "type": "Feature",
  "properties": {
    "iso:country":"DE",
    "sg:address":"Daimlerstr. 5",
    "sg:city":"Frickenhausen",
    "sg:phone":"+49 7022/48444",
    "sg:postcode":"72636",
    "sg:province":"Baden-W\u00fcrttemberg",
    "wof:name":"Ruja Chemie Gmbh",
    "wof:placetype":"venue"
},
  "geometry": {"coordinates":[9.34543,48.58886],"type":"Point"}
}