{
  "type": "Feature",
  "properties": {
    "iso:country":"DE",
    "sg:address":"Wasserloser Str. 11",
    "sg:city":"Alzenau",
    "sg:phone":"+49 6023/2006",
    "sg:postcode":"63755",
    "sg:province":"Bayern",
    "wof:name":"Heinz D\u00f6rsching",
    "wof:placetype":"venue"
},
  "geometry": {"coordinates":[9.0725049973,50.084236145],"type":"Point"}
}