{
  "type": "Feature",
  "properties": {
    "iso:country":"DE",
    "sg:address":"M\u00fcnsterkamp 8",
    "sg:city":"Einbeck",
    "sg:phone":"+49 5561/3576",
    "sg:postcode":"37574",
    "sg:province":"Niedersachsen",
    "wof:name":"Gert Arkenberg",
    "wof:placetype":"venue"
},
  "geometry": {"coordinates":[9.8661899567,51.823348999],"type":"Point"}
}