{
  "type": "Feature",
  "properties": {
    "iso:country":"DE",
    "sg:address":"Sachsenh\u00e4userstr. 60",
    "sg:city":"Bad Orb",
    "sg:phone":"+49 6052/3187",
    "sg:postcode":"63619",
    "sg:province":"Hessen",
    "wof:name":"Schubert",
    "wof:placetype":"venue"
},
  "geometry": {"coordinates":[9.337105,50.226723],"type":"Point"}
}