{
  "type": "Feature",
  "properties": {
    "iso:country":"DE",
    "sg:address":"Claviusstr. 47",
    "sg:city":"Bamberg",
    "sg:phone":"+49 951/25780",
    "sg:postcode":"96047",
    "sg:province":"Bayern",
    "wof:name":"Georg Lederer Ingenieur",
    "wof:placetype":"venue"
},
  "geometry": {"coordinates":[10.9016313553,49.8844795227],"type":"Point"}
}