{
  "type": "Feature",
  "properties": {
    "iso:country":"DE",
    "sg:address":"Sterneng\u00e4ssle 17",
    "sg:city":"Gottmadingen",
    "sg:phone":"+49 7731/71919",
    "sg:postcode":"78244",
    "sg:province":"Baden-W\u00fcrttemberg",
    "wof:name":"Josef Gassner",
    "wof:placetype":"venue"
},
  "geometry": {"coordinates":[8.775587,47.736168],"type":"Point"}
}