{
  "type": "Feature",
  "properties": {
    "iso:country":"DE",
    "sg:address":"Vor Thurant 7",
    "sg:city":"Alken",
    "sg:phone":"+49 2605/633",
    "sg:postcode":"56332",
    "sg:province":"Rheinland-Pfalz",
    "wof:name":"Karl-heinz Rittel",
    "wof:placetype":"venue"
},
  "geometry": {"coordinates":[7.4488830566,50.2481422424],"type":"Point"}
}