{
  "type": "Feature",
  "properties": {
    "iso:country":"DE",
    "sg:address":"Bahnhofstr. 17",
    "sg:city":"Bad Camberg",
    "sg:phone":"+49 6434/3596",
    "sg:postcode":"65520",
    "sg:province":"Hessen",
    "wof:name":"Martins Radel Werkstatt",
    "wof:placetype":"venue"
},
  "geometry": {"coordinates":[8.264402,50.297329],"type":"Point"}
}