{
  "type": "Feature",
  "properties": {
    "iso:country":"DE",
    "sg:address":"Schlo\u00dfgasse 6",
    "sg:city":"Gie\u00dfen",
    "sg:phone":"+49 641/931160",
    "sg:postcode":"35390",
    "sg:province":"Hessen",
    "wof:name":"Eurohypo Ag",
    "wof:placetype":"venue"
},
  "geometry": {"coordinates":[8.6754302979,50.5869560242],"type":"Point"}
}