{
  "type": "Feature",
  "properties": {
    "iso:country":"DE",
    "sg:address":"Erlm\u00fchler Str. 23",
    "sg:city":"Dentlein",
    "sg:phone":"+49 9855/229",
    "sg:postcode":"91599",
    "sg:province":"Bayern",
    "wof:name":"Ludwig Gei\u00dfler Ohg",
    "wof:placetype":"venue"
},
  "geometry": {"coordinates":[10.438829,49.134533],"type":"Point"}
}