{
  "type": "Feature",
  "properties": {
    "iso:country":"DE",
    "sg:address":"Sedanstr. 47",
    "sg:city":"Essen",
    "sg:phone":"+49 201/284101",
    "sg:postcode":"45138",
    "sg:province":"Nordrhein-Westfalen",
    "wof:name":"Pickert",
    "wof:placetype":"venue"
},
  "geometry": {"coordinates":[7.0253248215,51.4479103088],"type":"Point"}
}