{
  "type": "Feature",
  "properties": {
    "iso:country":"DE",
    "sg:address":"Maybachstr. 3",
    "sg:city":"Kassel",
    "sg:phone":"+49 561/898813",
    "sg:postcode":"34127",
    "sg:province":"Hessen",
    "wof:name":"Wolfgang Jentsch",
    "wof:placetype":"venue"
},
  "geometry": {"coordinates":[9.470797,51.326385],"type":"Point"}
}