{
  "type": "Feature",
  "properties": {
    "iso:country":"DE",
    "sg:address":"Amselstr 2",
    "sg:city":"Remels",
    "sg:phone":"+49 4956/990730",
    "sg:postcode":"26670",
    "sg:province":"Niedersachsen",
    "wof:name":"Goesmann Zentralstaubsauger Gmbh",
    "wof:placetype":"venue"
},
  "geometry": {"coordinates":[7.758464,53.309448],"type":"Point"}
}