{
  "type": "Feature",
  "properties": {
    "iso:country":"DE",
    "sg:address":"Ermschwerder Str. 17",
    "sg:city":"Witzenhausen",
    "sg:postcode":"37213",
    "sg:province":"Hessen",
    "wof:name":"Stadtb\u00fccherei",
    "wof:placetype":"venue"
},
  "geometry": {"coordinates":[9.856085,51.342644],"type":"Point"}
}