{
  "type": "Feature",
  "properties": {
    "iso:country":"DE",
    "sg:address":"Bockhorst 125",
    "sg:city":"Hamburg",
    "sg:phone":"+49 40/805730",
    "sg:postcode":"22589",
    "sg:province":"Hamburg",
    "wof:name":"H. Schultze",
    "wof:placetype":"venue"
},
  "geometry": {"coordinates":[9.8397893906,53.5710105896],"type":"Point"}
}