{
  "type": "Feature",
  "properties": {
    "iso:country":"DE",
    "sg:address":"Robert-Schuman-Str. 4",
    "sg:city":"P\u00fcttlingen",
    "sg:phone":"+49 6898/61616",
    "sg:postcode":"66346",
    "sg:province":"Saarland",
    "wof:name":"Hermann Lex",
    "wof:placetype":"venue"
},
  "geometry": {"coordinates":[6.8745989799,49.2934761047],"type":"Point"}
}