{
  "type": "Feature",
  "properties": {
    "iso:country":"DE",
    "sg:address":"Gro\u00dfe Str. 19",
    "sg:city":"Schee\u00dfel",
    "sg:phone":"+49 4263/1059",
    "sg:postcode":"27383",
    "sg:province":"Niedersachsen",
    "wof:name":"Eiscafe S. Pizzol",
    "wof:placetype":"venue"
},
  "geometry": {"coordinates":[9.481948,53.168091],"type":"Point"}
}