{
  "type": "Feature",
  "properties": {
    "iso:country":"DE",
    "sg:address":"Im Hederichsfeld 16",
    "sg:city":"Leverkusen",
    "sg:phone":"+49 2171/44939",
    "sg:postcode":"51379",
    "sg:province":"Nordrhein-Westfalen",
    "wof:name":"City Sport Opladen Gmbh",
    "wof:placetype":"venue"
},
  "geometry": {"coordinates":[7.004637,51.0644],"type":"Point"}
}