{
  "type": "Feature",
  "properties": {
    "iso:country":"DE",
    "sg:address":"Ludwig-Thoma-Str. 2",
    "sg:city":"Otterfing",
    "sg:phone":"+49 8024/4260",
    "sg:postcode":"83624",
    "sg:province":"Bayern",
    "wof:name":"J. A. Steinberger",
    "wof:placetype":"venue"
},
  "geometry": {"coordinates":[11.6807556152,47.9116821289],"type":"Point"}
}