{
  "type": "Feature",
  "properties": {
    "iso:country":"DE",
    "sg:address":"Hoher Winkel 15",
    "sg:city":"Finsterbergen",
    "sg:phone":"+49 3623/306086",
    "sg:postcode":"99898",
    "sg:province":"Th\u00fcringen",
    "wof:name":"Hotel Berghaus",
    "wof:placetype":"venue"
},
  "geometry": {"coordinates":[10.591422081,50.8306846619],"type":"Point"}
}