{
  "type": "Feature",
  "properties": {
    "iso:country":"DE",
    "sg:address":"Fr\u00f6belstr. 48",
    "sg:city":"Leipzig",
    "sg:postcode":"04158",
    "sg:province":"Sachsen",
    "wof:name":"Dr. Med. Ernst Springer",
    "wof:placetype":"venue"
},
  "geometry": {"coordinates":[12.38232,51.402279],"type":"Point"}
}