{
  "type": "Feature",
  "properties": {
    "iso:country":"DE",
    "sg:address":"Annabergweg 7",
    "sg:city":"D\u00fcren",
    "sg:phone":"+49 2421/61713",
    "sg:postcode":"52355",
    "sg:province":"Nordrhein-Westfalen",
    "wof:name":"P. Str\u00f6mer",
    "wof:placetype":"venue"
},
  "geometry": {"coordinates":[6.4689531326,50.7779579163],"type":"Point"}
}