{
  "type": "Feature",
  "properties": {
    "iso:country":"DE",
    "sg:address":"Industriestr. 6- 8",
    "sg:city":"Radevormwald",
    "sg:phone":"+49 4921/952304",
    "sg:postcode":"42477",
    "sg:province":"Nordrhein-Westfalen",
    "wof:name":"Schreiber Gebr Gmbh & Co Kg",
    "wof:placetype":"venue"
},
  "geometry": {"coordinates":[7.3633790016,51.1981658936],"type":"Point"}
}