{
  "type": "Feature",
  "properties": {
    "iso:country":"DE",
    "sg:address":"St.-Florentiner-Str. 19",
    "sg:city":"Zeltingen-Rachtig",
    "sg:phone":"+49 6532/2317",
    "sg:postcode":"54492",
    "sg:province":"Rheinland-Pfalz",
    "wof:name":"Oswin Und Stefan Sch\u00e4dler",
    "wof:placetype":"venue"
},
  "geometry": {"coordinates":[7.00735,49.957642],"type":"Point"}
}