{
  "type": "Feature",
  "properties": {
    "iso:country":"DE",
    "sg:address":"Stendaler Weg 1",
    "sg:city":"Tangerh\u00fctte",
    "sg:phone":"+49 3935/28263",
    "sg:postcode":"39517",
    "sg:province":"Sachsen-Anhalt",
    "wof:name":"Damker",
    "wof:placetype":"venue"
},
  "geometry": {"coordinates":[11.807943,52.440372],"type":"Point"}
}