{
  "type": "Feature",
  "properties": {
    "iso:country":"DE",
    "sg:address":"Steinweg 9",
    "sg:city":"Frankenberg",
    "sg:phone":"+49 6452/91450",
    "sg:postcode":"35066",
    "sg:province":"Hessen",
    "wof:name":"Ibw-ingenieurb\u00fcro F\u00fcr Bau- Und Wassertechnik Gmbh",
    "wof:placetype":"venue"
},
  "geometry": {"coordinates":[8.802683,51.061554],"type":"Point"}
}