{
  "type": "Feature",
  "properties": {
    "iso:country":"DE",
    "sg:address":"Am Klosterbusch 3",
    "sg:city":"Hamminkeln",
    "sg:phone":"+49 2852/94158",
    "sg:postcode":"46499",
    "sg:province":"Nordrhein-Westfalen",
    "wof:name":"Hermann Hanzen",
    "wof:placetype":"venue"
},
  "geometry": {"coordinates":[6.578182,51.777607],"type":"Point"}
}