{
  "type": "Feature",
  "properties": {
    "iso:country":"DE",
    "sg:address":"Spessartstr. 63 a",
    "sg:city":"Langenselbold",
    "sg:phone":"+49 6184/3153",
    "sg:postcode":"63505",
    "sg:province":"Hessen",
    "wof:name":"Willi Gibbe Heiz\u00f6l-handlung Gmbh",
    "wof:placetype":"venue"
},
  "geometry": {"coordinates":[9.0469150543,50.1806030273],"type":"Point"}
}