{
  "type": "Feature",
  "properties": {
    "iso:country":"DE",
    "sg:address":"Am Eichh\u00f6lzchen 8",
    "sg:city":"Morsbach",
    "sg:phone":"+49 2294/8520",
    "sg:postcode":"51597",
    "sg:province":"Nordrhein-Westfalen",
    "wof:name":"Friedhelm Schumann",
    "wof:placetype":"venue"
},
  "geometry": {"coordinates":[7.7236437798,50.871055603],"type":"Point"}
}