{
  "type": "Feature",
  "properties": {
    "iso:country":"DE",
    "sg:address":"An den Waldh\u00f6fen 1",
    "sg:city":"Kerpen",
    "sg:phone":"+49 2275/210",
    "sg:postcode":"50170",
    "sg:province":"Nordrhein-Westfalen",
    "wof:name":"Stefan Leonards",
    "wof:placetype":"venue"
},
  "geometry": {"coordinates":[6.59255,50.893326],"type":"Point"}
}