{
  "type": "Feature",
  "properties": {
    "iso:country":"DE",
    "sg:address":"Gr\u00fcner Weg 2",
    "sg:city":"Rosbach",
    "sg:phone":"+49 6003/3264",
    "sg:postcode":"61191",
    "sg:province":"Hessen",
    "wof:name":"F. Und I. Schmidt Immobilienmakler",
    "wof:placetype":"venue"
},
  "geometry": {"coordinates":[8.6860466003,50.3082885742],"type":"Point"}
}