{
  "type": "Feature",
  "properties": {
    "iso:country":"DE",
    "sg:address":"Bessenbachstr. 13",
    "sg:city":"Bessenbach",
    "sg:phone":"+49 6095/731",
    "sg:postcode":"63856",
    "sg:province":"Bayern",
    "wof:name":"Hubertus",
    "wof:placetype":"venue"
},
  "geometry": {"coordinates":[9.2505884171,49.9535064697],"type":"Point"}
}