{
  "type": "Feature",
  "properties": {
    "iso:country":"DE",
    "sg:address":"Sylviastr. 2",
    "sg:city":"Essen",
    "sg:phone":"+49 201/233110",
    "sg:postcode":"45131",
    "sg:province":"Nordrhein-Westfalen",
    "wof:name":"J\u00fcrgen Fraczewski Heilpraktiker",
    "wof:placetype":"venue"
},
  "geometry": {"coordinates":[7.0197892189,51.4360046387],"type":"Point"}
}