{
  "type": "Feature",
  "properties": {
    "iso:country":"DE",
    "sg:address":"Schleusenstr. 21",
    "sg:city":"Michelau",
    "sg:phone":"+49 9571/8990",
    "sg:postcode":"96247",
    "sg:province":"Bayern",
    "wof:name":"Taleco-handels- Gmbh",
    "wof:placetype":"venue"
},
  "geometry": {"coordinates":[11.1169557571,50.1615638733],"type":"Point"}
}