{
  "type": "Feature",
  "properties": {
    "iso:country":"DE",
    "sg:address":"Bahnhofstra\u00dfe 46",
    "sg:city":"Treuen",
    "sg:phone":"+49 37468/600",
    "sg:postcode":"08233",
    "sg:province":"Sachsen",
    "wof:name":"Vowalon Beschichtung Gmbh Treuen",
    "wof:placetype":"venue"
},
  "geometry": {"coordinates":[12.3001699448,50.5463294983],"type":"Point"}
}