{
  "type": "Feature",
  "properties": {
    "iso:country":"DE",
    "sg:address":"Meppener Str. 82",
    "sg:city":"Lingen",
    "sg:phone":"+49 591/65913",
    "sg:postcode":"49808",
    "sg:province":"Niedersachsen",
    "wof:name":"China-restaurant Lotus",
    "wof:placetype":"venue"
},
  "geometry": {"coordinates":[7.3079152107,52.5317764282],"type":"Point"}
}