{
  "type": "Feature",
  "properties": {
    "iso:country":"DE",
    "sg:address":"Dackenheimer Str. 14",
    "sg:city":"Freinsheim",
    "sg:phone":"+49 6353/2334",
    "sg:postcode":"67251",
    "sg:province":"Rheinland-Pfalz",
    "wof:name":"B. Zinke",
    "wof:placetype":"venue"
},
  "geometry": {"coordinates":[8.208262,49.507565],"type":"Point"}
}