{
  "type": "Feature",
  "properties": {
    "iso:country":"DE",
    "sg:address":"Sieltrift 43",
    "sg:city":"Dorum",
    "sg:phone":"+49 4741/3226",
    "sg:postcode":"27632",
    "sg:province":"Niedersachsen",
    "wof:name":"Delia Metzelaar-feldhaus",
    "wof:placetype":"venue"
},
  "geometry": {"coordinates":[8.5315303802,53.7282981873],"type":"Point"}
}