{
  "type": "Feature",
  "properties": {
    "iso:country":"DE",
    "sg:address":"Maxplatz 32",
    "sg:city":"N\u00fcrnberg",
    "sg:phone":"+49 911/204239",
    "sg:postcode":"90403",
    "sg:province":"Bayern",
    "wof:name":"Egon Kunze",
    "wof:placetype":"venue"
},
  "geometry": {"coordinates":[11.0728979111,49.4545822144],"type":"Point"}
}