{
  "type": "Feature",
  "properties": {
    "iso:country":"DE",
    "sg:address":"K\u00f6nigstr. 33",
    "sg:city":"Paderborn",
    "sg:phone":"+49 5251/22018",
    "sg:postcode":"33098",
    "sg:province":"Nordrhein-Westfalen",
    "wof:name":"Meinolf Niggemeier Leder- Und Schuhmacherbedarf",
    "wof:placetype":"venue"
},
  "geometry": {"coordinates":[8.748583,51.719002],"type":"Point"}
}