{
  "type": "Feature",
  "properties": {
    "iso:country":"DE",
    "sg:address":"B\u00f6hmerstr. 24",
    "sg:city":"R\u00f6tz",
    "sg:phone":"+49 9976/1667",
    "sg:postcode":"92444",
    "sg:province":"Bayern",
    "wof:name":"Isi Pizzeria",
    "wof:placetype":"venue"
},
  "geometry": {"coordinates":[12.5316066742,49.3421707153],"type":"Point"}
}