{
  "type": "Feature",
  "properties": {
    "iso:country":"DE",
    "sg:address":"Kloster 1",
    "sg:city":"Bedburg-Hau",
    "sg:phone":"+49 2824/999891",
    "sg:postcode":"47551",
    "sg:province":"Nordrhein-Westfalen",
    "wof:name":"Icc Service Und Dienst- Leistungsgesellschaft F\u00fcr",
    "wof:placetype":"venue"
},
  "geometry": {"coordinates":[6.258947,51.760208],"type":"Point"}
}