{
  "type": "Feature",
  "properties": {
    "iso:country":"DE",
    "sg:address":"Hauptstr. 20",
    "sg:city":"Untergriesbach",
    "sg:phone":"+49 8586/2633",
    "sg:postcode":"94107",
    "sg:province":"Bayern",
    "wof:name":"Ludwig Kronawitter",
    "wof:placetype":"venue"
},
  "geometry": {"coordinates":[13.649119,48.613384],"type":"Point"}
}