{
  "type": "Feature",
  "properties": {
    "iso:country":"DE",
    "sg:address":"Scheidstr. 18",
    "sg:city":"Hatzfeld",
    "sg:phone":"+49 6467/281",
    "sg:postcode":"35116",
    "sg:province":"Hessen",
    "wof:name":"Albrecht Oesten",
    "wof:placetype":"venue"
},
  "geometry": {"coordinates":[8.542291,50.995533],"type":"Point"}
}