{
  "type": "Feature",
  "properties": {
    "iso:country":"DE",
    "sg:address":"Isenburger Str. 7",
    "sg:city":"Bendorf",
    "sg:phone":"+49 2601/3457",
    "sg:postcode":"56170",
    "sg:province":"Rheinland-Pfalz",
    "wof:name":"Theo Gottschalk",
    "wof:placetype":"venue"
},
  "geometry": {"coordinates":[7.5999011993,50.459400177],"type":"Point"}
}