{
  "type": "Feature",
  "properties": {
    "iso:country":"DE",
    "sg:address":"Spreestr. 6",
    "sg:city":"Neum\u00fcnster",
    "sg:phone":"+49 4321/99240",
    "sg:postcode":"24539",
    "sg:province":"Schleswig-Holstein",
    "wof:name":"Wilhelm Feldmann Druckluft Hydraulik Gmbh",
    "wof:placetype":"venue"
},
  "geometry": {"coordinates":[9.9747667313,54.0462608337],"type":"Point"}
}