{
  "type": "Feature",
  "properties": {
    "iso:country":"DE",
    "sg:address":"Glieshamm 9b",
    "sg:city":"Langen",
    "sg:phone":"+49 4743/4417",
    "sg:postcode":"27607",
    "sg:province":"Niedersachsen",
    "wof:name":"H. Guderian",
    "wof:placetype":"venue"
},
  "geometry": {"coordinates":[8.5912809372,53.6057624817],"type":"Point"}
}