{
  "type": "Feature",
  "properties": {
    "iso:country":"DE",
    "sg:address":"Feldbrunnenstr. 11",
    "sg:city":"Hamburg",
    "sg:phone":"+49 40/4105531",
    "sg:postcode":"20148",
    "sg:province":"Hamburg",
    "wof:name":"Wm. Meyer Sennewald",
    "wof:placetype":"venue"
},
  "geometry": {"coordinates":[9.9908561707,53.5647201538],"type":"Point"}
}