{
  "type": "Feature",
  "properties": {
    "iso:country":"DE",
    "sg:address":"Lindgesfeld 22",
    "sg:city":"Solingen",
    "sg:phone":"+49 212/590936",
    "sg:postcode":"42653",
    "sg:province":"Nordrhein-Westfalen",
    "wof:name":"Karl-heinz Evertz",
    "wof:placetype":"venue"
},
  "geometry": {"coordinates":[7.082183,51.20417],"type":"Point"}
}