{
  "type": "Feature",
  "properties": {
    "iso:country":"DE",
    "sg:address":"Am F\u00fcrstenwald 16",
    "sg:city":"Hage",
    "sg:phone":"+49 4931/974111",
    "sg:postcode":"26524",
    "sg:province":"Niedersachsen",
    "wof:name":"As Immobilien Alberta Siebelds",
    "wof:placetype":"venue"
},
  "geometry": {"coordinates":[7.2922167778,53.5943069458],"type":"Point"}
}