{
  "type": "Feature",
  "properties": {
    "iso:country":"DE",
    "sg:address":"Hartberg",
    "sg:city":"Thurmansbang",
    "sg:phone":"+49 8544/1703",
    "sg:postcode":"94169",
    "sg:province":"Bayern",
    "wof:name":"Andreas Schedlbauer",
    "wof:placetype":"venue"
},
  "geometry": {"coordinates":[13.3177042007,48.7688751221],"type":"Point"}
}