{
  "type": "Feature",
  "properties": {
    "iso:country":"DE",
    "sg:address":"Zeppelinstr. 48",
    "sg:city":"Potsdam",
    "sg:phone":"+49 331/2343230",
    "sg:postcode":"14471",
    "sg:province":"Brandenburg",
    "wof:name":"Edistherm W\u00e4rmedienstleistungen Gmbh",
    "wof:placetype":"venue"
},
  "geometry": {"coordinates":[13.032729,52.391331],"type":"Point"}
}