{
  "type": "Feature",
  "properties": {
    "iso:country":"DE",
    "sg:address":"Von-Knoeringen-Str. 110",
    "sg:city":"Leverkusen",
    "sg:phone":"+49 2171/83447",
    "sg:postcode":"51381",
    "sg:province":"Nordrhein-Westfalen",
    "wof:name":"Hans-j\u00f6rg Hamacher",
    "wof:placetype":"venue"
},
  "geometry": {"coordinates":[7.0564670563,51.0570449829],"type":"Point"}
}