{
  "type": "Feature",
  "properties": {
    "iso:country":"DE",
    "sg:address":"Gugelstr. 9",
    "sg:city":"N\u00fcrnberg",
    "sg:phone":"+49 911/262679",
    "sg:postcode":"90443",
    "sg:province":"Bayern",
    "wof:name":"Downhill",
    "wof:placetype":"venue"
},
  "geometry": {"coordinates":[11.073244,49.44165],"type":"Point"}
}