{
  "type": "Feature",
  "properties": {
    "iso:country":"DE",
    "sg:address":"Wasserburger Landstr. 268",
    "sg:city":"M\u00fcnchen",
    "sg:phone":"+49 89/4307976",
    "sg:postcode":"81827",
    "sg:province":"Bayern",
    "wof:name":"Wabula Reisen Gmbh",
    "wof:placetype":"venue"
},
  "geometry": {"coordinates":[11.7100057602,48.1111106873],"type":"Point"}
}