{
  "type": "Feature",
  "properties": {
    "iso:country":"DE",
    "sg:address":"Holzweg 129",
    "sg:city":"Bad D\u00fcrkheim",
    "sg:phone":"+49 6322/5829",
    "sg:postcode":"67098",
    "sg:province":"Rheinland-Pfalz",
    "wof:name":"H. Hammel",
    "wof:placetype":"venue"
},
  "geometry": {"coordinates":[8.1596298218,49.4522666931],"type":"Point"}
}