{
  "type": "Feature",
  "properties": {
    "iso:country":"DE",
    "sg:address":"B\u00f6ttchergasse 2",
    "sg:city":"Burgst\u00e4dt",
    "sg:phone":"+49 3724/3040",
    "sg:postcode":"09217",
    "sg:province":"Sachsen",
    "wof:name":"K. Lehmann",
    "wof:placetype":"venue"
},
  "geometry": {"coordinates":[12.806146,50.921192],"type":"Point"}
}