{
  "type": "Feature",
  "properties": {
    "iso:country":"DE",
    "sg:address":"Bahnhofstr. 14",
    "sg:city":"Eilsleben",
    "sg:phone":"+49 39409/544",
    "sg:postcode":"39365",
    "sg:province":"Sachsen-Anhalt",
    "wof:name":"Gastst\u00e4tte Zur Ahornklause Inh. Konrad Wilhelmy",
    "wof:placetype":"venue"
},
  "geometry": {"coordinates":[11.2096843719,52.1488990784],"type":"Point"}
}