{
  "type": "Feature",
  "properties": {
    "iso:country":"DE",
    "sg:address":"Ilexstra\u00dfe 18 - 20",
    "sg:city":"Wiesmoor",
    "sg:phone":"+49 4944/92210",
    "sg:postcode":"26639",
    "sg:province":"Niedersachsen",
    "wof:name":"Medizinische Ern\u00e4hrung",
    "wof:placetype":"venue"
},
  "geometry": {"coordinates":[7.750601,53.374489],"type":"Point"}
}