{
  "type": "Feature",
  "properties": {
    "iso:country":"DE",
    "sg:address":"B\u00e4ckereifeld 2",
    "sg:city":"Quellendorf",
    "sg:phone":"+49 34977/21277",
    "sg:postcode":"06386",
    "sg:province":"Sachsen-Anhalt",
    "wof:name":"U.p.r. Pl\u00f6tz Gmbh",
    "wof:placetype":"venue"
},
  "geometry": {"coordinates":[12.1253004074,51.7446746826],"type":"Point"}
}