{
  "type": "Feature",
  "properties": {
    "iso:country":"DE",
    "sg:address":"Malzstrasse 7",
    "sg:city":"Kaiserslautern",
    "sg:phone":"+49 4963/120169",
    "sg:postcode":"67663",
    "sg:province":"Rheinland-Pfalz",
    "wof:name":"Schulte's Hotel Du Vin",
    "wof:placetype":"venue"
},
  "geometry": {"coordinates":[7.7749390602,49.4360847473],"type":"Point"}
}