{
  "type": "Feature",
  "properties": {
    "iso:country":"DE",
    "sg:address":"B\u00fclowstr. 2",
    "sg:city":"K\u00f6ln",
    "sg:phone":"+49 221/766839",
    "sg:postcode":"50733",
    "sg:province":"Nordrhein-Westfalen",
    "wof:name":"Restaurant Pauls",
    "wof:placetype":"venue"
},
  "geometry": {"coordinates":[6.9562129974,50.9642715454],"type":"Point"}
}