{
  "type": "Feature",
  "properties": {
    "iso:country":"DE",
    "sg:address":"Kurf\u00fcrstenplatz 4",
    "sg:city":"M\u00fcnchen",
    "sg:phone":"+49 89/396615",
    "sg:postcode":"80796",
    "sg:province":"Bayern",
    "wof:name":"Dipl. Ing. Manfred Seif Hochbauarchitekt",
    "wof:placetype":"venue"
},
  "geometry": {"coordinates":[11.575419,48.159988],"type":"Point"}
}