{
  "type": "Feature",
  "properties": {
    "iso:country":"DE",
    "sg:address":"Seestr. 40a",
    "sg:city":"Rottach-Egern",
    "sg:phone":"+49 8022/26682",
    "sg:postcode":"83700",
    "sg:province":"Bayern",
    "wof:name":"Karl Schulz Bootsvermietungen",
    "wof:placetype":"venue"
},
  "geometry": {"coordinates":[11.7609329224,47.6957321167],"type":"Point"}
}