{
  "type": "Feature",
  "properties": {
    "iso:country":"DE",
    "sg:address":"Michael-Wenz- Str. 2-10::",
    "sg:city":"Arnstein",
    "sg:phone":"+49 9363/680",
    "sg:postcode":"97450",
    "sg:province":"Bayern",
    "wof:name":"Miwe Michael Wenz Gmbh",
    "wof:placetype":"venue"
},
  "geometry": {"coordinates":[9.98279953,49.9720573425],"type":"Point"}
}