{
  "type": "Feature",
  "properties": {
    "iso:country":"DE",
    "sg:address":"Ochsenzoller Str. 116",
    "sg:city":"Norderstedt",
    "sg:phone":"+49 40/52877581",
    "sg:postcode":"22848",
    "sg:province":"Schleswig-Holstein",
    "wof:name":"Albert E. Inh. Malihe Mohammadi",
    "wof:placetype":"venue"
},
  "geometry": {"coordinates":[9.9820137024,53.681968689],"type":"Point"}
}