{
  "type": "Feature",
  "properties": {
    "iso:country":"DE",
    "sg:address":"Haaggasse 15",
    "sg:city":"Regensburg",
    "sg:phone":"+49 941/53321",
    "sg:postcode":"93047",
    "sg:province":"Bayern",
    "wof:name":"Schwedenkugel",
    "wof:placetype":"venue"
},
  "geometry": {"coordinates":[12.0873594284,49.0205993652],"type":"Point"}
}