{
  "type": "Feature",
  "properties": {
    "iso:country":"DE",
    "sg:address":"S\u00fcdring 8",
    "sg:city":"Ermke",
    "sg:phone":"+49 4475/1485",
    "sg:postcode":"49696",
    "sg:province":"Niedersachsen",
    "wof:name":"Willi Dr\u00f6ge",
    "wof:placetype":"venue"
},
  "geometry": {"coordinates":[7.888852,52.834637],"type":"Point"}
}