{
  "type": "Feature",
  "properties": {
    "iso:country":"DE",
    "sg:address":"Kirchstr. 24",
    "sg:city":"Arnsberg",
    "sg:phone":"+49 2937/6407",
    "sg:postcode":"59823",
    "sg:province":"Nordrhein-Westfalen",
    "wof:name":"Willi Krewitt",
    "wof:placetype":"venue"
},
  "geometry": {"coordinates":[8.135827,51.393436],"type":"Point"}
}