{
  "type": "Feature",
  "properties": {
    "iso:country":"DE",
    "sg:address":"Wilhelm-Liebknecht-Str. 30",
    "sg:city":"Giessen",
    "sg:phone":"+49 641/48937",
    "sg:postcode":"35396",
    "sg:province":"Hessen",
    "wof:name":"Club-urlaub-special Riu, Robinson, Aldiana, Grecot",
    "wof:placetype":"venue"
},
  "geometry": {"coordinates":[8.703469,50.601761],"type":"Point"}
}