{
  "type": "Feature",
  "properties": {
    "iso:country":"DE",
    "sg:address":"Kirchstr. 31",
    "sg:city":"Altdorf",
    "sg:phone":"+49 7127/924266",
    "sg:postcode":"72655",
    "sg:province":"Baden-W\u00fcrttemberg",
    "wof:name":"Pizzeria Hirsch",
    "wof:placetype":"venue"
},
  "geometry": {"coordinates":[9.2722988129,48.5939407349],"type":"Point"}
}