{
  "type": "Feature",
  "properties": {
    "iso:country":"DE",
    "sg:address":"Gerbrunner Str. 34 A",
    "sg:city":"Randersacker",
    "sg:phone":"+49 931/272457",
    "sg:postcode":"97236",
    "sg:province":"Bayern",
    "wof:name":"Zum Erdinger Weissbr\u00e4u",
    "wof:placetype":"venue"
},
  "geometry": {"coordinates":[9.9919681549,49.7676239014],"type":"Point"}
}