{
  "type": "Feature",
  "properties": {
    "iso:country":"DE",
    "sg:address":"Moltkestrasse 49",
    "sg:city":"Karlsruhe",
    "sg:phone":"+49 111",
    "sg:postcode":"76133",
    "sg:province":"Baden-W\u00fcrttemberg",
    "wof:name":"Linux ? Linux By In-put Gbr",
    "wof:placetype":"venue"
},
  "geometry": {"coordinates":[8.380887,49.014793],"type":"Point"}
}