{
  "type": "Feature",
  "properties": {
    "iso:country":"DE",
    "sg:address":"Am Georgengarten 2",
    "sg:city":"Dessau",
    "sg:phone":"+49 340/610687",
    "sg:postcode":"06846",
    "sg:province":"Sachsen-Anhalt",
    "wof:name":"Planungsb\u00fcro Reinboth Gmbh",
    "wof:placetype":"venue"
},
  "geometry": {"coordinates":[12.224146843,51.8447341919],"type":"Point"}
}