{
  "type": "Feature",
  "properties": {
    "iso:country":"DE",
    "sg:address":"Am Rennplatz 18",
    "sg:city":"Cloppenburg",
    "sg:phone":"+49 4471/5940",
    "sg:postcode":"49661",
    "sg:province":"Niedersachsen",
    "wof:name":"Dr. Hans-hermann L\u00fcttich Tierarzt",
    "wof:placetype":"venue"
},
  "geometry": {"coordinates":[8.039229393,52.8541870117],"type":"Point"}
}