{
  "type": "Feature",
  "properties": {
    "iso:country":"DE",
    "sg:address":"Hauptstr. 105",
    "sg:city":"Eggenstein-Leopoldshafen",
    "sg:phone":"+49 721/704240",
    "sg:postcode":"76344",
    "sg:province":"Baden-W\u00fcrttemberg",
    "wof:name":"Ilona Stutz",
    "wof:placetype":"venue"
},
  "geometry": {"coordinates":[8.3904905319,49.0747375488],"type":"Point"}
}