{
  "type": "Feature",
  "properties": {
    "iso:country":"DE",
    "sg:address":"Elvert 14",
    "sg:city":"L\u00fcdinghausen",
    "sg:phone":"+49 2591/7510",
    "sg:postcode":"59348",
    "sg:province":"Nordrhein-Westfalen",
    "wof:name":"Reismann Bautr\u00e4ger Gmbh",
    "wof:placetype":"venue"
},
  "geometry": {"coordinates":[7.426523,51.803509],"type":"Point"}
}