{
  "type": "Feature",
  "properties": {
    "iso:country":"DE",
    "sg:address":"M\u00fchleneschweg 2/4",
    "sg:city":"Osnabr\u00fcck",
    "sg:phone":"+49 541/609490",
    "sg:postcode":"49090",
    "sg:province":"Niedersachsen",
    "wof:name":"Geisler Gesellschaft F\u00fcr Tankanlagen Und Rohrleitungsbau Elektroinstallationen Mbh",
    "wof:placetype":"venue"
},
  "geometry": {"coordinates":[8.0373849869,52.2925796509],"type":"Point"}
}