{
  "type": "Feature",
  "properties": {
    "iso:country":"DE",
    "sg:address":"Bertastr. 16a",
    "sg:city":"Issum",
    "sg:phone":"+49 2835/2504",
    "sg:postcode":"47661",
    "sg:province":"Nordrhein-Westfalen",
    "wof:name":"Frank Lange Ingenieur",
    "wof:placetype":"venue"
},
  "geometry": {"coordinates":[6.4260840416,51.540184021],"type":"Point"}
}