{
  "type": "Feature",
  "properties": {
    "iso:country":"DE",
    "sg:address":"Duisburger Str. 429",
    "sg:city":"M\u00fclheim",
    "sg:postcode":"45478",
    "sg:province":"Nordrhein-Westfalen",
    "wof:name":"Kurco-bau Gmbh",
    "wof:placetype":"venue"
},
  "geometry": {"coordinates":[6.825392,51.432423],"type":"Point"}
}