{
  "type": "Feature",
  "properties": {
    "iso:country":"DE",
    "sg:address":"Grubweg 1",
    "sg:city":"Schonach",
    "sg:phone":"+49 7722/1512",
    "sg:postcode":"78136",
    "sg:province":"Baden-W\u00fcrttemberg",
    "wof:name":"Sporthaus Hoer Inh. Sabine Hoer",
    "wof:placetype":"venue"
},
  "geometry": {"coordinates":[8.240445137,48.147644043],"type":"Point"}
}