{
  "type": "Feature",
  "properties": {
    "iso:country":"DE",
    "sg:address":"Zur Hammerbr\u00fccke 26",
    "sg:city":"Olsberg",
    "sg:phone":"+49 2962/2405",
    "sg:postcode":"59939",
    "sg:province":"Nordrhein-Westfalen",
    "wof:name":"Wilhelm Niggemann",
    "wof:placetype":"venue"
},
  "geometry": {"coordinates":[8.5292,51.32671],"type":"Point"}
}