{
  "type": "Feature",
  "properties": {
    "iso:country":"DE",
    "sg:address":"Am Klitgen 33",
    "sg:city":"Bergneustadt",
    "sg:phone":"+49 2261/41985",
    "sg:postcode":"51702",
    "sg:province":"Nordrhein-Westfalen",
    "wof:name":"I. Kuhn",
    "wof:placetype":"venue"
},
  "geometry": {"coordinates":[7.6687498093,51.0285606384],"type":"Point"}
}