{
  "type": "Feature",
  "properties": {
    "iso:country":"DE",
    "sg:address":"Stephanstr. 19",
    "sg:city":"N\u00fcrnberg",
    "sg:phone":"+49 911/465672",
    "sg:postcode":"90478",
    "sg:province":"Bayern",
    "wof:name":"R. Schmidt",
    "wof:placetype":"venue"
},
  "geometry": {"coordinates":[11.098086,49.446026],"type":"Point"}
}