{
  "type": "Feature",
  "properties": {
    "iso:country":"DE",
    "sg:address":"Leutkircher Str. 10",
    "sg:city":"Isny",
    "sg:phone":"+49 7562/55255",
    "sg:postcode":"88316",
    "sg:province":"Baden-W\u00fcrttemberg",
    "wof:name":"Disco Max",
    "wof:placetype":"venue"
},
  "geometry": {"coordinates":[10.042688,47.698147],"type":"Point"}
}