{
  "type": "Feature",
  "properties": {
    "iso:country":"DE",
    "sg:address":"Kastanienallee 11",
    "sg:city":"Braunschweig",
    "sg:phone":"+49 531/73359",
    "sg:postcode":"38102",
    "sg:province":"Niedersachsen",
    "wof:name":"Manfred Kotz",
    "wof:placetype":"venue"
},
  "geometry": {"coordinates":[10.5415382385,52.2628479004],"type":"Point"}
}