{
  "type": "Feature",
  "properties": {
    "iso:country":"DE",
    "sg:address":"Ostpreu\u00dfenweg 4",
    "sg:city":"Hessisch Oldendorf",
    "sg:phone":"+49 5152/61434",
    "sg:postcode":"31840",
    "sg:province":"Niedersachsen",
    "wof:name":"Klaus Schelske Steuerberater",
    "wof:placetype":"venue"
},
  "geometry": {"coordinates":[9.3051748276,52.1433982849],"type":"Point"}
}