{
  "type": "Feature",
  "properties": {
    "iso:country":"DE",
    "sg:address":"Hallesche Str. 53a",
    "sg:city":"Nordhausen",
    "sg:phone":"+49 3631/900034",
    "sg:postcode":"99734",
    "sg:province":"Th\u00fcringen",
    "wof:name":"Hammer Fachm\u00e4rkte F\u00fcr Heim-ausstattung",
    "wof:placetype":"venue"
},
  "geometry": {"coordinates":[10.8060722351,51.4949874878],"type":"Point"}
}