{
  "type": "Feature",
  "properties": {
    "iso:country":"DE",
    "sg:address":"Oberdorfen 4",
    "sg:city":"Dorfen",
    "sg:phone":"+49 8081/2029",
    "sg:postcode":"84405",
    "sg:province":"Bayern",
    "wof:name":"G. Hopf",
    "wof:placetype":"venue"
},
  "geometry": {"coordinates":[12.122483,48.272823],"type":"Point"}
}