{
  "type": "Feature",
  "properties": {
    "iso:country":"DE",
    "sg:address":"Einsteinstr. 7",
    "sg:city":"Paderborn",
    "sg:postcode":"33104",
    "sg:province":"Nordrhein-Westfalen",
    "wof:name":"Unirenova Generalunternehmung F\u00fcr Renovationen Und",
    "wof:placetype":"venue"
},
  "geometry": {"coordinates":[8.7080526352,51.77186203],"type":"Point"}
}