{
  "type": "Feature",
  "properties": {
    "iso:country":"DE",
    "sg:address":"Seligenthaler Str. 12",
    "sg:city":"Landshut",
    "sg:phone":"+49 871/852801",
    "sg:postcode":"84034",
    "sg:province":"Bayern",
    "wof:name":"Wasserwirtschaftsamt Landshut",
    "wof:placetype":"venue"
},
  "geometry": {"coordinates":[12.1479902267,48.5434799194],"type":"Point"}
}