{
  "type": "Feature",
  "properties": {
    "iso:country":"DE",
    "sg:address":"St.-Veit-Str. 14",
    "sg:city":"Erbendorf",
    "sg:phone":"+49 9682/2167",
    "sg:postcode":"92681",
    "sg:province":"Bayern",
    "wof:name":"Hans Reger",
    "wof:placetype":"venue"
},
  "geometry": {"coordinates":[12.044404,49.840832],"type":"Point"}
}