{
  "type": "Feature",
  "properties": {
    "iso:country":"DE",
    "sg:address":"Birkenhain 1",
    "sg:city":"Hagen",
    "sg:phone":"+49 2331/56876",
    "sg:postcode":"58093",
    "sg:province":"Nordrhein-Westfalen",
    "wof:name":"Giovanna Scrofani",
    "wof:placetype":"venue"
},
  "geometry": {"coordinates":[7.5116271973,51.3517913818],"type":"Point"}
}