{
  "type": "Feature",
  "properties": {
    "iso:country":"DE",
    "sg:address":"Gro\u00dfe-Perdekamp-Str. 5",
    "sg:city":"Recklinghausen",
    "sg:phone":"+49 2361/182364",
    "sg:postcode":"45657",
    "sg:province":"Nordrhein-Westfalen",
    "wof:name":"Ladenbau Peter Kaufhold E. K.",
    "wof:placetype":"venue"
},
  "geometry": {"coordinates":[7.20276,51.61647],"type":"Point"}
}