{
  "type": "Feature",
  "properties": {
    "iso:country":"DE",
    "sg:address":"Buchenweg 38",
    "sg:city":"Perleberg",
    "sg:phone":"+49 3876/614286",
    "sg:postcode":"19348",
    "sg:province":"Brandenburg",
    "wof:name":"Arnold M\u00fcller",
    "wof:placetype":"venue"
},
  "geometry": {"coordinates":[11.84457,53.073631],"type":"Point"}
}