{
  "type": "Feature",
  "properties": {
    "iso:country":"DE",
    "sg:address":"Im Dorfe 12",
    "sg:city":"Embsen",
    "sg:phone":"+49 4134/7291",
    "sg:postcode":"21409",
    "sg:province":"Niedersachsen",
    "wof:name":"Hans-h. Biermann",
    "wof:placetype":"venue"
},
  "geometry": {"coordinates":[10.326629,53.193508],"type":"Point"}
}