{
  "type": "Feature",
  "properties": {
    "iso:country":"DE",
    "sg:address":"Georginenstr. 15 a",
    "sg:city":"M\u00fcnchen",
    "sg:phone":"+49 89/74016918",
    "sg:postcode":"80689",
    "sg:province":"Bayern",
    "wof:name":"C. Dlusztus",
    "wof:placetype":"venue"
},
  "geometry": {"coordinates":[11.4839143753,48.1272163391],"type":"Point"}
}