{
  "type": "Feature",
  "properties": {
    "iso:country":"DE",
    "sg:address":"Laufener Str. 5",
    "sg:city":"Freilassing",
    "sg:phone":"+49 8654/63521",
    "sg:postcode":"83395",
    "sg:province":"Bayern",
    "wof:name":"M. Wallner & A. Hofherr",
    "wof:placetype":"venue"
},
  "geometry": {"coordinates":[12.9833307266,47.8417739868],"type":"Point"}
}