{
  "type": "Feature",
  "properties": {
    "iso:country":"DE",
    "sg:address":"Walter-Zeidler-Str. 19",
    "sg:city":"Osterr\u00f6nfeld",
    "sg:phone":"+49 4331/87143",
    "sg:postcode":"24783",
    "sg:province":"Schleswig-Holstein",
    "wof:name":"Reinhard Runge Gmbh",
    "wof:placetype":"venue"
},
  "geometry": {"coordinates":[9.681096077,54.2847557068],"type":"Point"}
}