{
  "type": "Feature",
  "properties": {
    "iso:country":"DE",
    "sg:address":"Am Schlachtensee 34",
    "sg:city":"Berlin",
    "sg:phone":"+49 30/8023952",
    "sg:postcode":"14129",
    "sg:province":"Berlin",
    "wof:name":"Am Golfplatz Gro\u00df-kienitz Wohnbauten Gmbh",
    "wof:placetype":"venue"
},
  "geometry": {"coordinates":[13.224887,52.440594],"type":"Point"}
}