{
  "type": "Feature",
  "properties": {
    "iso:country":"DE",
    "sg:address":"Keltergasse 1",
    "sg:city":"Cleebronn",
    "sg:phone":"+49 7135/6747",
    "sg:postcode":"74389",
    "sg:province":"Baden-W\u00fcrttemberg",
    "wof:name":"H. Walderich",
    "wof:placetype":"venue"
},
  "geometry": {"coordinates":[9.037135,49.044167],"type":"Point"}
}