{
  "type": "Feature",
  "properties": {
    "iso:country":"DE",
    "sg:address":"Brunnenstr. 4",
    "sg:city":"Bad Schwalbach",
    "sg:phone":"+49 6124/3375",
    "sg:postcode":"65307",
    "sg:province":"Hessen",
    "wof:name":"Gardinenstudio Sturm",
    "wof:placetype":"venue"
},
  "geometry": {"coordinates":[8.0693817139,50.1398735046],"type":"Point"}
}