{
  "type": "Feature",
  "properties": {
    "iso:country":"DE",
    "sg:address":"Unterm Abla\u00df 3",
    "sg:city":"Me\u00dfkirch",
    "sg:phone":"+49 7575/925410",
    "sg:postcode":"88605",
    "sg:province":"Baden-W\u00fcrttemberg",
    "wof:name":"Wgb Bau Gmbh",
    "wof:placetype":"venue"
},
  "geometry": {"coordinates":[9.128408,47.998032],"type":"Point"}
}