{
  "type": "Feature",
  "properties": {
    "iso:country":"DE",
    "sg:address":"Rheinische Str. 3",
    "sg:city":"Beckum",
    "sg:phone":"+49 2521/16700",
    "sg:postcode":"59269",
    "sg:province":"Nordrhein-Westfalen",
    "wof:name":"Ikarus Musikequipment Inh. Martin Klosterkamp",
    "wof:placetype":"venue"
},
  "geometry": {"coordinates":[8.0537652969,51.7620658875],"type":"Point"}
}