{
  "type": "Feature",
  "properties": {
    "iso:country":"DE",
    "sg:address":"Ridlerstr. 31b",
    "sg:city":"M\u00fcnchen",
    "sg:phone":"+49 89/4890670",
    "sg:postcode":"80339",
    "sg:province":"Bayern",
    "wof:name":"Tbwa Pr Gmbh",
    "wof:placetype":"venue"
},
  "geometry": {"coordinates":[11.535553,48.132164],"type":"Point"}
}