{
  "type": "Feature",
  "properties": {
    "iso:country":"DE",
    "sg:address":"Schillerstr. 30",
    "sg:city":"Magstadt",
    "sg:phone":"+49 7159/41122",
    "sg:postcode":"71106",
    "sg:province":"Baden-W\u00fcrttemberg",
    "wof:name":"Kath. Pfarramt Zur Hl. Familie",
    "wof:placetype":"venue"
},
  "geometry": {"coordinates":[8.9686126709,48.7390518188],"type":"Point"}
}