{
  "type": "Feature",
  "properties": {
    "iso:country":"DE",
    "sg:address":"Im Hasenfeld 6-8",
    "sg:city":"Vettwei\u00df",
    "sg:phone":"+49 2424/1268",
    "sg:postcode":"52391",
    "sg:province":"Nordrhein-Westfalen",
    "wof:name":"Rolith Chemicals Handels-gmbh",
    "wof:placetype":"venue"
},
  "geometry": {"coordinates":[6.607624,50.743912],"type":"Point"}
}