{
  "type": "Feature",
  "properties": {
    "iso:country":"DE",
    "sg:address":"Kaibitz 25",
    "sg:city":"Kemnath",
    "sg:postcode":"95478",
    "sg:province":"Bayern",
    "wof:name":"Bauservice Haidl-nowak Gmbh",
    "wof:placetype":"venue"
},
  "geometry": {"coordinates":[11.884218,49.844215],"type":"Point"}
}