{
  "type": "Feature",
  "properties": {
    "iso:country":"DE",
    "sg:address":"H\u00f6lderlinstr. 40",
    "sg:city":"Friedrichsthal",
    "sg:phone":"+49 6897/8276",
    "sg:postcode":"66299",
    "sg:province":"Saarland",
    "wof:name":"Gernot Scheerer Architekt",
    "wof:placetype":"venue"
},
  "geometry": {"coordinates":[7.087608,49.323784],"type":"Point"}
}