{
  "type": "Feature",
  "properties": {
    "iso:country":"DE",
    "sg:address":"Auf dem H\u00fcttenflur 8",
    "sg:city":"Kirschweiler",
    "sg:phone":"+49 6781/33370",
    "sg:postcode":"55743",
    "sg:province":"Rheinland-Pfalz",
    "wof:name":"Helmut Weis",
    "wof:placetype":"venue"
},
  "geometry": {"coordinates":[7.2480697632,49.7588691711],"type":"Point"}
}