{
  "type": "Feature",
  "properties": {
    "iso:country":"DE",
    "sg:address":"Breuna",
    "sg:city":"Breuna",
    "sg:phone":"+49 4956/93295",
    "sg:postcode":"34479",
    "sg:province":"Hessen",
    "wof:name":"Kreissparkasse Wolfhagen",
    "wof:placetype":"venue"
},
  "geometry": {"coordinates":[9.20853,51.434361],"type":"Point"}
}