{
  "type": "Feature",
  "properties": {
    "iso:country":"DE",
    "sg:address":"Bergweg 12",
    "sg:city":"Kn\u00fcllwald",
    "sg:phone":"+49 5681/2628",
    "sg:postcode":"34593",
    "sg:province":"Hessen",
    "wof:name":"August K\u00fcllmer",
    "wof:placetype":"venue"
},
  "geometry": {"coordinates":[9.4650278091,51.0007972717],"type":"Point"}
}