{
  "type": "Feature",
  "properties": {
    "iso:country":"DE",
    "sg:address":"Br\u00fcckstr. 68",
    "sg:city":"Dortmund",
    "sg:phone":"+49 231/527371",
    "sg:postcode":"44135",
    "sg:province":"Nordrhein-Westfalen",
    "wof:name":"Dr. Med. Mounir Badin",
    "wof:placetype":"venue"
},
  "geometry": {"coordinates":[7.4646701813,51.517414093],"type":"Point"}
}