{
  "type": "Feature",
  "properties": {
    "iso:country":"DE",
    "sg:address":"Oberer Steinrausch 13",
    "sg:city":"Osann-Monzel",
    "sg:phone":"+49 6535/266",
    "sg:postcode":"54518",
    "sg:province":"Rheinland-Pfalz",
    "wof:name":"G. Zimmer-schenden",
    "wof:placetype":"venue"
},
  "geometry": {"coordinates":[6.9575428963,49.9200210571],"type":"Point"}
}