{
  "type": "Feature",
  "properties": {
    "iso:country":"DE",
    "sg:address":"Weingartenstr. 2",
    "sg:city":"Dettelbach",
    "sg:postcode":"97337",
    "sg:province":"Bayern",
    "wof:name":"Drumm Sicherheit Gmbh",
    "wof:placetype":"venue"
},
  "geometry": {"coordinates":[10.165017,49.801979],"type":"Point"}
}