{
  "type": "Feature",
  "properties": {
    "iso:country":"DE",
    "sg:address":"Grootredder 15",
    "sg:city":"Kisdorf",
    "sg:phone":"+49 4193/5038",
    "sg:postcode":"24629",
    "sg:province":"Schleswig-Holstein",
    "wof:name":"M. Massmann Elektroinstallation",
    "wof:placetype":"venue"
},
  "geometry": {"coordinates":[10.010226,53.807819],"type":"Point"}
}