{
  "type": "Feature",
  "properties": {
    "iso:country":"DE",
    "sg:address":"R\u00f6merstr. 119",
    "sg:city":"Leonberg",
    "sg:phone":"+49 7152/9335100",
    "sg:postcode":"71229",
    "sg:province":"Baden-W\u00fcrttemberg",
    "wof:name":"Kemmer Baukonzept Gmbh & Co. Bautr\u00e4ger Kg",
    "wof:placetype":"venue"
},
  "geometry": {"coordinates":[9.015244,48.795921],"type":"Point"}
}