{
  "type": "Feature",
  "properties": {
    "iso:country":"DE",
    "sg:address":"Br\u00fcckenhofstr. 78",
    "sg:city":"Kassel",
    "sg:postcode":"34132",
    "sg:province":"Hessen",
    "wof:name":"Vereinsgastst\u00e4tte Behinderten- Gemeinschaft Kassel E. V.",
    "wof:placetype":"venue"
},
  "geometry": {"coordinates":[9.4450826645,51.2823028564],"type":"Point"}
}