{
  "type": "Feature",
  "properties": {
    "iso:country":"DE",
    "sg:address":"Dorfstr. 86",
    "sg:city":"Altmittweida",
    "sg:phone":"+49 3727/3290",
    "sg:postcode":"09648",
    "sg:province":"Sachsen",
    "wof:name":"Dieter Poppitz",
    "wof:placetype":"venue"
},
  "geometry": {"coordinates":[12.941771,50.962242],"type":"Point"}
}