{
  "type": "Feature",
  "properties": {
    "iso:country":"DE",
    "sg:address":"Osemundstr. 9",
    "sg:city":"Iserlohn",
    "sg:phone":"+49 2371/67894",
    "sg:postcode":"58636",
    "sg:province":"Nordrhein-Westfalen",
    "wof:name":"Eberhard Vielhaber Gmbh & Co.",
    "wof:placetype":"venue"
},
  "geometry": {"coordinates":[7.735536,51.372803],"type":"Point"}
}