{
  "type": "Feature",
  "properties": {
    "iso:country":"DE",
    "sg:address":"Industriestr 6",
    "sg:city":"Burgau",
    "sg:phone":"+49 8222/1436",
    "sg:postcode":"89331",
    "sg:province":"Bayern",
    "wof:name":"Karl Hammerschmidt & S\u00f6hne Gmbh",
    "wof:placetype":"venue"
},
  "geometry": {"coordinates":[10.419206,48.426479],"type":"Point"}
}