{
  "type": "Feature",
  "properties": {
    "iso:country":"DE",
    "sg:address":"Heinsbergplatz 12",
    "sg:city":"Soest",
    "sg:phone":"+49 2921/3560",
    "sg:postcode":"59494",
    "sg:province":"Nordrhein-Westfalen",
    "wof:name":"Adolf-clarenbach-haus",
    "wof:placetype":"venue"
},
  "geometry": {"coordinates":[8.097582,51.572998],"type":"Point"}
}