{
  "type": "Feature",
  "properties": {
    "iso:country":"DE",
    "sg:address":"Heidentalstr. 48",
    "sg:city":"Detmold",
    "sg:phone":"+49 5231/88156",
    "sg:postcode":"32760",
    "sg:province":"Nordrhein-Westfalen",
    "wof:name":"Ursula Lampe-schneider Architektin",
    "wof:placetype":"venue"
},
  "geometry": {"coordinates":[8.830808,51.921719],"type":"Point"}
}