{
  "type": "Feature",
  "properties": {
    "iso:country":"DE",
    "sg:address":"Oberheidter Str. 53",
    "sg:city":"Wuppertal",
    "sg:phone":"+49 202/470668",
    "sg:postcode":"42349",
    "sg:province":"Nordrhein-Westfalen",
    "wof:name":"Mpm Chemie-produkte Gmbh",
    "wof:placetype":"venue"
},
  "geometry": {"coordinates":[7.13596,51.186581],"type":"Point"}
}