{
  "type": "Feature",
  "properties": {
    "iso:country":"DE",
    "sg:address":"Strasse der Deutschen Einheit 20",
    "sg:city":"Bad Blankenburg",
    "sg:postcode":"07422",
    "sg:province":"Th\u00fcringen",
    "wof:name":"Unterwirbach.de",
    "wof:placetype":"venue"
},
  "geometry": {"coordinates":[11.277206,50.679787],"type":"Point"}
}