{
  "type": "Feature",
  "properties": {
    "iso:country":"DE",
    "sg:address":"Oberer Weidenpfad 28",
    "sg:city":"Laubenheim",
    "sg:phone":"+49 6704/1313",
    "sg:postcode":"55452",
    "sg:province":"Rheinland-Pfalz",
    "wof:name":"Hildegard H\u00e4ussling Inh. Johannes H\u00e4ussling",
    "wof:placetype":"venue"
},
  "geometry": {"coordinates":[7.8974018097,49.9159469604],"type":"Point"}
}