{
  "type": "Feature",
  "properties": {
    "iso:country":"DE",
    "sg:address":"Stresemannstr. 6",
    "sg:city":"Stuttgart",
    "sg:phone":"+49 711/2560636",
    "sg:postcode":"70191",
    "sg:province":"Baden-W\u00fcrttemberg",
    "wof:name":"Naturfreundehaus Vereinsheim Steinbergle",
    "wof:placetype":"venue"
},
  "geometry": {"coordinates":[9.1738681793,48.8025245667],"type":"Point"}
}