{
  "type": "Feature",
  "properties": {
    "iso:country":"DE",
    "sg:address":"Hauptstr. 68 a",
    "sg:city":"Dudeldorf",
    "sg:phone":"+49 6565/2120",
    "sg:postcode":"54647",
    "sg:province":"Rheinland-Pfalz",
    "wof:name":"A. Lonien",
    "wof:placetype":"venue"
},
  "geometry": {"coordinates":[6.640414,49.974094],"type":"Point"}
}