{
  "type": "Feature",
  "properties": {
    "iso:country":"DE",
    "sg:address":"H\u00fcttenstr. 15",
    "sg:city":"Stadthagen",
    "sg:phone":"+49 5721/3061",
    "sg:postcode":"31655",
    "sg:province":"Niedersachsen",
    "wof:name":"Schulen Dr. W. Blindow Gmbh",
    "wof:placetype":"venue"
},
  "geometry": {"coordinates":[9.185698,52.325581],"type":"Point"}
}