{
  "type": "Feature",
  "properties": {
    "iso:country":"DE",
    "sg:address":"Kasseler Str. 74",
    "sg:city":"Melsungen",
    "sg:phone":"+49 5661/1627",
    "sg:postcode":"34212",
    "sg:province":"Hessen",
    "wof:name":"Marion Viereck",
    "wof:placetype":"venue"
},
  "geometry": {"coordinates":[9.53955,51.136669],"type":"Point"}
}