{
  "type": "Feature",
  "properties": {
    "iso:country":"DE",
    "sg:address":"Industriestr. 3",
    "sg:city":"Haren",
    "sg:phone":"+49 5932/2525",
    "sg:postcode":"49733",
    "sg:province":"Niedersachsen",
    "wof:name":"Ems-jade Gmbh & Co. Kg",
    "wof:placetype":"venue"
},
  "geometry": {"coordinates":[7.2511429787,52.79895401],"type":"Point"}
}