{
  "type": "Feature",
  "properties": {
    "iso:country":"DE",
    "sg:address":"Am M\u00fchlenberg 11",
    "sg:city":"Wadern",
    "sg:phone":"+49 6871/1254",
    "sg:postcode":"66687",
    "sg:province":"Saarland",
    "wof:name":"Heinz Niesen Bootsverleih",
    "wof:placetype":"venue"
},
  "geometry": {"coordinates":[6.8748288155,49.5303535461],"type":"Point"}
}