{
  "type": "Feature",
  "properties": {
    "iso:country":"DE",
    "sg:address":"D\u00f6rnbergweg 8",
    "sg:city":"Mittelstille",
    "sg:phone":"+49 3683/608937",
    "sg:postcode":"98574",
    "sg:province":"Th\u00fcringen",
    "wof:name":"G. J\u00e4ger",
    "wof:placetype":"venue"
},
  "geometry": {"coordinates":[10.482588,50.703033],"type":"Point"}
}