{
  "type": "Feature",
  "properties": {
    "iso:country":"DE",
    "sg:address":"Im Lorsbachtal 47",
    "sg:city":"Hofheim",
    "sg:phone":"+49 6192/901530",
    "sg:postcode":"65719",
    "sg:province":"Hessen",
    "wof:name":"Gartenform Richter & Uhlenberg Gmbh",
    "wof:placetype":"venue"
},
  "geometry": {"coordinates":[8.411933,50.127861],"type":"Point"}
}