{
  "type": "Feature",
  "properties": {
    "iso:country":"DE",
    "sg:address":"Rheinstr. 7",
    "sg:city":"Ransbach-Baumbach",
    "sg:phone":"+49 2623/8944",
    "sg:postcode":"56235",
    "sg:province":"Rheinland-Pfalz",
    "wof:name":"K. G\u00fcnther Gmbh & Co. Kg",
    "wof:placetype":"venue"
},
  "geometry": {"coordinates":[7.7359390259,50.4724655151],"type":"Point"}
}