{
  "type": "Feature",
  "properties": {
    "iso:country":"DE",
    "sg:address":"Gemarkenstr. 7",
    "sg:city":"K\u00f6ln",
    "sg:phone":"+49 221/461346",
    "sg:postcode":"51069",
    "sg:province":"Nordrhein-Westfalen",
    "wof:name":"Karlheinz Klein",
    "wof:placetype":"venue"
},
  "geometry": {"coordinates":[7.078212,50.972664],"type":"Point"}
}