{
  "type": "Feature",
  "properties": {
    "iso:country":"DE",
    "sg:address":"Kirchweg 1",
    "sg:city":"Gro\u00dfefehn",
    "sg:postcode":"26629",
    "sg:province":"Niedersachsen",
    "wof:name":"Trauernicht Verwaltungsgesellschaft Mbh",
    "wof:placetype":"venue"
},
  "geometry": {"coordinates":[7.5692257881,53.3952827454],"type":"Point"}
}