{
  "type": "Feature",
  "properties": {
    "iso:country":"DE",
    "sg:address":"Ohmoor 16 a",
    "sg:city":"Hamburg",
    "sg:phone":"+49 40/55599182",
    "sg:postcode":"22455",
    "sg:province":"Hamburg",
    "wof:name":"Vibro-einsp\u00fcltechnik D\u00fcker- Und Wasserbau Gmbh",
    "wof:placetype":"venue"
},
  "geometry": {"coordinates":[9.9623680115,53.6358909607],"type":"Point"}
}