{
  "type": "Feature",
  "properties": {
    "iso:country":"DE",
    "sg:address":"Corbiestr. 33",
    "sg:city":"H\u00f6xter",
    "sg:phone":"+49 5271/8807",
    "sg:postcode":"37671",
    "sg:province":"Nordrhein-Westfalen",
    "wof:name":"Siebrecht Backstube",
    "wof:placetype":"venue"
},
  "geometry": {"coordinates":[9.382309,51.776421],"type":"Point"}
}