{
  "type": "Feature",
  "properties": {
    "iso:country":"DE",
    "sg:address":"Von-Frays-Str. 9",
    "sg:city":"M\u00fcnchen",
    "sg:phone":"+49 89/883223",
    "sg:postcode":"81245",
    "sg:province":"Bayern",
    "wof:name":"Ingeborg Faltin-battenberg",
    "wof:placetype":"venue"
},
  "geometry": {"coordinates":[11.475294,48.153378],"type":"Point"}
}