{
  "type": "Feature",
  "properties": {
    "iso:country":"DE",
    "sg:address":"Friedrichrodaer Str. 11",
    "sg:city":"Ernstroda",
    "sg:phone":"+49 3623/304896",
    "sg:postcode":"99894",
    "sg:province":"Th\u00fcringen",
    "wof:name":"H. G\u00f6rlach",
    "wof:placetype":"venue"
},
  "geometry": {"coordinates":[10.612241745,50.8631744385],"type":"Point"}
}