{
  "type": "Feature",
  "properties": {
    "iso:country":"DE",
    "sg:address":"Lange Str. 21",
    "sg:city":"Gebesee",
    "sg:postcode":"99189",
    "sg:province":"Th\u00fcringen",
    "wof:name":"Gemeindeschwesterstation Gebesee",
    "wof:placetype":"venue"
},
  "geometry": {"coordinates":[10.937237,51.11552],"type":"Point"}
}