{
  "type": "Feature",
  "properties": {
    "iso:country":"DE",
    "sg:address":"Kirchstr. 1",
    "sg:city":"Baddeckenstedt",
    "sg:phone":"+49 5345/771",
    "sg:postcode":"38271",
    "sg:province":"Niedersachsen",
    "wof:name":"Baack",
    "wof:placetype":"venue"
},
  "geometry": {"coordinates":[10.2310276031,52.0830612183],"type":"Point"}
}