{
  "type": "Feature",
  "properties": {
    "iso:country":"DE",
    "sg:address":"Adolfstr. 6",
    "sg:city":"Duisburg",
    "sg:phone":"+49 2066/99860",
    "sg:postcode":"47198",
    "sg:province":"Nordrhein-Westfalen",
    "wof:name":"J. Pentek Gmbh",
    "wof:placetype":"venue"
},
  "geometry": {"coordinates":[6.6873311996,51.444770813],"type":"Point"}
}