{
  "type": "Feature",
  "properties": {
    "iso:country":"DE",
    "sg:address":"Kutenhauser Str. 200",
    "sg:city":"Minden",
    "sg:phone":"+49 571/63123",
    "sg:postcode":"32425",
    "sg:province":"Nordrhein-Westfalen",
    "wof:name":"W. Dunken Gmbh & Co. Kg",
    "wof:placetype":"venue"
},
  "geometry": {"coordinates":[8.90406,52.331142],"type":"Point"}
}