{
  "type": "Feature",
  "properties": {
    "iso:country":"DE",
    "sg:address":"Erbsenbrink 10",
    "sg:city":"Bielefeld",
    "sg:phone":"+49 521/84795",
    "sg:postcode":"33739",
    "sg:province":"Nordrhein-Westfalen",
    "wof:name":"Albis Praxiscomputer Vertriebs-gmbh",
    "wof:placetype":"venue"
},
  "geometry": {"coordinates":[8.5640192032,52.0768585205],"type":"Point"}
}