{
  "type": "Feature",
  "properties": {
    "iso:country":"DE",
    "sg:address":"Albert-Levy-Str. 72",
    "sg:city":"Altenburg",
    "sg:postcode":"04600",
    "sg:province":"Th\u00fcringen",
    "wof:name":"Stefan Eitz",
    "wof:placetype":"venue"
},
  "geometry": {"coordinates":[12.4269733429,51.0030212402],"type":"Point"}
}