{
  "type": "Feature",
  "properties": {
    "iso:country":"DE",
    "sg:address":"Marktplatz 3",
    "sg:city":"Gladenbach",
    "sg:phone":"+49 6462/1830",
    "sg:postcode":"35075",
    "sg:province":"Hessen",
    "wof:name":"Ulrich G\u00fcnther",
    "wof:placetype":"venue"
},
  "geometry": {"coordinates":[8.580104,50.768978],"type":"Point"}
}