{
  "type": "Feature",
  "properties": {
    "iso:country":"DE",
    "sg:address":"Brauhausplatz 7",
    "sg:city":"Stadtroda",
    "sg:phone":"+49 36428/42489",
    "sg:postcode":"07646",
    "sg:province":"Th\u00fcringen",
    "wof:name":"Pension Am Brauhausplatz",
    "wof:placetype":"venue"
},
  "geometry": {"coordinates":[11.7280597687,50.8556098938],"type":"Point"}
}