{
  "type": "Feature",
  "properties": {
    "iso:country":"DE",
    "sg:address":"Augsburger Str. 410 a",
    "sg:city":"Stuttgart",
    "sg:phone":"+49 711/334923",
    "sg:postcode":"70327",
    "sg:province":"Baden-W\u00fcrttemberg",
    "wof:name":"Gerhard Kirste",
    "wof:placetype":"venue"
},
  "geometry": {"coordinates":[9.2539,48.77832],"type":"Point"}
}