{
  "type": "Feature",
  "properties": {
    "iso:country":"DE",
    "sg:address":"Ladestr 2",
    "sg:city":"Dinklage",
    "sg:phone":"+49 4443/9700",
    "sg:postcode":"49413",
    "sg:province":"Niedersachsen",
    "wof:name":"H. Br\u00f6ring Gmbh & Co Kg",
    "wof:placetype":"venue"
},
  "geometry": {"coordinates":[8.1215333939,52.6653518677],"type":"Point"}
}