{
  "type": "Feature",
  "properties": {
    "iso:country":"DE",
    "sg:address":"Mecklenburger Str. 134",
    "sg:city":"L\u00fcbeck",
    "sg:phone":"+49 451/301600",
    "sg:postcode":"23568",
    "sg:province":"Schleswig-Holstein",
    "wof:name":"H. Sch\u00fcnzel",
    "wof:placetype":"venue"
},
  "geometry": {"coordinates":[10.7904958725,53.8881149292],"type":"Point"}
}