{
  "type": "Feature",
  "properties": {
    "iso:country":"DE",
    "sg:address":"Industriestr. 11",
    "sg:city":"Bundenthal",
    "sg:phone":"+49 6394/1867",
    "sg:postcode":"76891",
    "sg:province":"Rheinland-Pfalz",
    "wof:name":"Metz Gmbh",
    "wof:placetype":"venue"
},
  "geometry": {"coordinates":[7.8019919395,49.106464386],"type":"Point"}
}