{
  "type": "Feature",
  "properties": {
    "iso:country":"DE",
    "sg:address":"L\u00fcbbecker Str. 109",
    "sg:city":"Kirchlengern",
    "sg:phone":"+49 5223/71503",
    "sg:postcode":"32278",
    "sg:province":"Nordrhein-Westfalen",
    "wof:name":"Karl Nagel",
    "wof:placetype":"venue"
},
  "geometry": {"coordinates":[8.640497,52.203388],"type":"Point"}
}