{
  "type": "Feature",
  "properties": {
    "iso:country":"DE",
    "sg:address":"Kornbach",
    "sg:city":"Gefrees",
    "sg:phone":"+49 9254/8423",
    "sg:postcode":"95482",
    "sg:province":"Bayern",
    "wof:name":"Konrad Loss & Hans Lang",
    "wof:placetype":"venue"
},
  "geometry": {"coordinates":[11.7875795364,50.0967445374],"type":"Point"}
}