{
  "type": "Feature",
  "properties": {
    "iso:country":"DE",
    "sg:address":"Deuil-La-Barre-Str. 70",
    "sg:city":"Frankfurt",
    "sg:phone":"+49 69/5074765",
    "sg:postcode":"60437",
    "sg:province":"Hessen",
    "wof:name":"Wilhelm Herzberger",
    "wof:placetype":"venue"
},
  "geometry": {"coordinates":[8.674698,50.200596],"type":"Point"}
}