{
  "type": "Feature",
  "properties": {
    "iso:country":"DE",
    "sg:address":"Wielandstr. 15",
    "sg:city":"Berlin",
    "sg:phone":"+49 30/3245066",
    "sg:postcode":"10629",
    "sg:province":"Berlin",
    "wof:name":"Feature Video Film- Und Fernsehproduktion Gmbh",
    "wof:placetype":"venue"
},
  "geometry": {"coordinates":[13.3151082993,52.5029029846],"type":"Point"}
}