{
  "type": "Feature",
  "properties": {
    "iso:country":"DE",
    "sg:address":"Friedrich-August-Str. 2 a",
    "sg:city":"Birkenfeld",
    "sg:postcode":"55765",
    "sg:province":"Rheinland-Pfalz",
    "wof:name":"Reisecenter Gaby Jener E. K.",
    "wof:placetype":"venue"
},
  "geometry": {"coordinates":[7.1654210091,49.6470718384],"type":"Point"}
}