{
  "type": "Feature",
  "properties": {
    "iso:country":"DE",
    "sg:address":"Seestr. 16",
    "sg:city":"Kressbronn",
    "sg:phone":"+49 7543/8654",
    "sg:postcode":"88079",
    "sg:province":"Baden-W\u00fcrttemberg",
    "wof:name":"Pizzeria-eiscafe San Marco",
    "wof:placetype":"venue"
},
  "geometry": {"coordinates":[9.6000833511,47.5919036865],"type":"Point"}
}