{
  "type": "Feature",
  "properties": {
    "iso:country":"DE",
    "sg:address":"Friedrichstr. 33",
    "sg:city":"M\u00fchltal",
    "sg:phone":"+49 6151/145045",
    "sg:postcode":"64367",
    "sg:province":"Hessen",
    "wof:name":"G. Vom Hoff",
    "wof:placetype":"venue"
},
  "geometry": {"coordinates":[8.7077178955,49.828212738],"type":"Point"}
}