{
  "type": "Feature",
  "properties": {
    "iso:country":"DE",
    "sg:address":"Kreuzberger Ring 21",
    "sg:city":"Wiesbaden",
    "sg:postcode":"65205",
    "sg:province":"Hessen",
    "wof:name":"Carat Espaces Deutschland Gmbh",
    "wof:placetype":"venue"
},
  "geometry": {"coordinates":[8.290123,50.054714],"type":"Point"}
}