{
  "type": "Feature",
  "properties": {
    "iso:country":"DE",
    "sg:address":"J\u00fcchsener Str. 19",
    "sg:city":"Neubrunn",
    "sg:phone":"+49 36947/54382",
    "sg:postcode":"98617",
    "sg:province":"Th\u00fcringen",
    "wof:name":"Rolf Gottwald",
    "wof:placetype":"venue"
},
  "geometry": {"coordinates":[10.4714822769,50.4997367859],"type":"Point"}
}