{
  "type": "Feature",
  "properties": {
    "iso:country":"DE",
    "sg:address":"Lange Str. 52",
    "sg:city":"Haren",
    "sg:phone":"+49 5932/2035",
    "sg:postcode":"49733",
    "sg:province":"Niedersachsen",
    "wof:name":"Asta-wohnbau Gmbh",
    "wof:placetype":"venue"
},
  "geometry": {"coordinates":[7.24493,52.790039],"type":"Point"}
}