{
  "type": "Feature",
  "properties": {
    "iso:country":"DE",
    "sg:address":"Turmgasse 18",
    "sg:city":"Leimen",
    "sg:phone":"+49 6224/75078",
    "sg:postcode":"69181",
    "sg:province":"Baden-W\u00fcrttemberg",
    "wof:name":"T. Kaschwich",
    "wof:placetype":"venue"
},
  "geometry": {"coordinates":[8.690216,49.349342],"type":"Point"}
}