{
  "type": "Feature",
  "properties": {
    "iso:country":"DE",
    "sg:address":"In der Ruraue 5",
    "sg:city":"Inden",
    "sg:phone":"+49 2428/3238",
    "sg:postcode":"52459",
    "sg:province":"Nordrhein-Westfalen",
    "wof:name":"P. Freialdenhoven",
    "wof:placetype":"venue"
},
  "geometry": {"coordinates":[6.418224,50.871326],"type":"Point"}
}