{
  "type": "Feature",
  "properties": {
    "iso:country":"DE",
    "sg:address":"Lissenstr. 53",
    "sg:city":"Kirchheim",
    "sg:phone":"+49 7143/94299",
    "sg:postcode":"74366",
    "sg:province":"Baden-W\u00fcrttemberg",
    "wof:name":"Schnuch Sb-baustoffe Gmbh",
    "wof:placetype":"venue"
},
  "geometry": {"coordinates":[9.1414232254,49.0406341553],"type":"Point"}
}