{
  "type": "Feature",
  "properties": {
    "iso:country":"DE",
    "sg:address":"Neufinning",
    "sg:city":"Finning",
    "sg:phone":"+49 8806/7402",
    "sg:postcode":"86923",
    "sg:province":"Bayern",
    "wof:name":"Rudolf Thalmayer",
    "wof:placetype":"venue"
},
  "geometry": {"coordinates":[11.031014,48.021484],"type":"Point"}
}