{
  "type": "Feature",
  "properties": {
    "iso:country":"DE",
    "sg:address":"Engerstr. 8",
    "sg:city":"Kempen",
    "sg:phone":"+49 2152/2976",
    "sg:postcode":"47906",
    "sg:province":"Nordrhein-Westfalen",
    "wof:name":"Marc Nentwig",
    "wof:placetype":"venue"
},
  "geometry": {"coordinates":[6.4210371971,51.3644638062],"type":"Point"}
}