{
  "type": "Feature",
  "properties": {
    "iso:country":"DE",
    "sg:address":"Dorfstr. 54",
    "sg:city":"Spenge",
    "sg:postcode":"32139",
    "sg:province":"Nordrhein-Westfalen",
    "wof:name":"Stief Immobilien & Handel Gmbh",
    "wof:placetype":"venue"
},
  "geometry": {"coordinates":[8.4848957062,52.1222610474],"type":"Point"}
}