{
  "type": "Feature",
  "properties": {
    "iso:country":"DE",
    "sg:address":"Paul-Nikusch-Str. 1",
    "sg:city":"Grimma",
    "sg:phone":"+49 3437/919657",
    "sg:postcode":"04668",
    "sg:province":"Sachsen",
    "wof:name":"Petra Ellmann",
    "wof:placetype":"venue"
},
  "geometry": {"coordinates":[12.733343,51.246918],"type":"Point"}
}