{
  "type": "Feature",
  "properties": {
    "iso:country":"DE",
    "sg:address":"Werner Hellweg 540",
    "sg:city":"Bochum",
    "sg:phone":"+49 234/265947",
    "sg:postcode":"44894",
    "sg:province":"Nordrhein-Westfalen",
    "wof:name":"Kosmos Grill",
    "wof:placetype":"venue"
},
  "geometry": {"coordinates":[7.3129458427,51.4929275513],"type":"Point"}
}