{
  "type": "Feature",
  "properties": {
    "iso:country":"DE",
    "sg:address":"Kelberger Str. 30",
    "sg:city":"Faid",
    "sg:phone":"+49 2671/7304",
    "sg:postcode":"56814",
    "sg:province":"Rheinland-Pfalz",
    "wof:name":"Fridolin Henrichs Schmiede",
    "wof:placetype":"venue"
},
  "geometry": {"coordinates":[7.122012,50.146832],"type":"Point"}
}