{
  "type": "Feature",
  "properties": {
    "iso:country":"DE",
    "sg:address":"Agnes-Bernauer-Str. 174",
    "sg:city":"M\u00fcnchen",
    "sg:phone":"+49 89/564744",
    "sg:postcode":"80687",
    "sg:province":"Bayern",
    "wof:name":"Annemarie Kessler Heilpraktikerin",
    "wof:placetype":"venue"
},
  "geometry": {"coordinates":[11.4856996536,48.1416168213],"type":"Point"}
}