{
  "type": "Feature",
  "properties": {
    "iso:country":"DE",
    "sg:address":"Rintheimer Str. 13",
    "sg:city":"Karlsruhe",
    "sg:phone":"+49 721/607865",
    "sg:postcode":"76131",
    "sg:province":"Baden-W\u00fcrttemberg",
    "wof:name":"Nutricon-umweltschutz- Technik Gmbh",
    "wof:placetype":"venue"
},
  "geometry": {"coordinates":[8.424773,49.011097],"type":"Point"}
}