{
  "type": "Feature",
  "properties": {
    "iso:country":"DE",
    "sg:address":"Spenerstr. 21",
    "sg:city":"Frankfurt",
    "sg:phone":"+49 69/563081",
    "sg:postcode":"60320",
    "sg:province":"Hessen",
    "wof:name":"Gertrud Funken-rudolf Koch Stiftung",
    "wof:placetype":"venue"
},
  "geometry": {"coordinates":[8.671667099,50.1380271912],"type":"Point"}
}