{
  "type": "Feature",
  "properties": {
    "iso:country":"DE",
    "sg:address":"Glash\u00fcttenweg 11-15",
    "sg:city":"L\u00fcbeck",
    "sg:phone":"+49 451/31020",
    "sg:postcode":"23568",
    "sg:province":"Schleswig-Holstein",
    "wof:name":"Kappa Wellpappe L\u00fcbeck Gmbh",
    "wof:placetype":"venue"
},
  "geometry": {"coordinates":[10.707324028,53.8921012878],"type":"Point"}
}