{
  "type": "Feature",
  "properties": {
    "iso:country":"DE",
    "sg:address":"Hocksteiner Weg 38",
    "sg:city":"M\u00f6nchengladbach",
    "sg:phone":"+49 2166/95260",
    "sg:postcode":"41189",
    "sg:province":"Nordrhein-Westfalen",
    "wof:name":"Kerbusch Gmbh",
    "wof:placetype":"venue"
},
  "geometry": {"coordinates":[6.413919,51.138649],"type":"Point"}
}