{
  "type": "Feature",
  "properties": {
    "iso:country":"DE",
    "sg:address":"Oberer Kalbacher Weg 10",
    "sg:city":"Frankfurt",
    "sg:phone":"+49 6101/48659",
    "sg:postcode":"60437",
    "sg:province":"Hessen",
    "wof:name":"M. Plaue",
    "wof:placetype":"venue"
},
  "geometry": {"coordinates":[8.663807,50.183384],"type":"Point"}
}