{
  "type": "Feature",
  "properties": {
    "iso:country":"DE",
    "sg:address":"Marienweg 3",
    "sg:city":"Stra\u00dflach-Dingharting",
    "sg:phone":"+49 8170/1377",
    "sg:postcode":"82064",
    "sg:province":"Bayern",
    "wof:name":"Riedl Gmbh",
    "wof:placetype":"venue"
},
  "geometry": {"coordinates":[11.511928,48.004807],"type":"Point"}
}