{
  "type": "Feature",
  "properties": {
    "iso:country":"DE",
    "sg:address":"Bockenheimer Landstr. 69",
    "sg:city":"Frankfurt",
    "sg:phone":"+49 69/727381",
    "sg:postcode":"60325",
    "sg:province":"Hessen",
    "wof:name":"Gotthart A. Eichhorn",
    "wof:placetype":"venue"
},
  "geometry": {"coordinates":[8.6622228622,50.118270874],"type":"Point"}
}