{
  "type": "Feature",
  "properties": {
    "iso:country":"DE",
    "sg:address":"Hauptstr. 4",
    "sg:city":"Langenbach",
    "sg:phone":"+49 2661/1558",
    "sg:postcode":"57520",
    "sg:province":"Rheinland-Pfalz",
    "wof:name":"S\u00e4gewerk Koch Gmbh",
    "wof:placetype":"venue"
},
  "geometry": {"coordinates":[-100.2087631226,44.8461112976],"type":"Point"}
}