{
  "type": "Feature",
  "properties": {
    "iso:country":"DE",
    "sg:address":"Augustaanlage 65",
    "sg:city":"Mannheim",
    "sg:phone":"+49 800 62629266",
    "sg:postcode":"68165",
    "sg:province":"Baden-W\u00fcrttemberg",
    "wof:name":"Mamax Lebensversicherung Ag",
    "wof:placetype":"venue"
},
  "geometry": {"coordinates":[8.4908189774,49.4784393311],"type":"Point"}
}