{
  "type": "Feature",
  "properties": {
    "iso:country":"DE",
    "sg:address":"Thalkirchner Str. 126",
    "sg:city":"M\u00fcnchen",
    "sg:phone":"+49 89/7250187",
    "sg:postcode":"81371",
    "sg:province":"Bayern",
    "wof:name":"Rudolf K\u00fchlmeyer",
    "wof:placetype":"venue"
},
  "geometry": {"coordinates":[11.5512170792,48.1191253662],"type":"Point"}
}