{
  "type": "Feature",
  "properties": {
    "iso:country":"DE",
    "sg:address":"Dorfstr. 59",
    "sg:city":"Heinrichswalde",
    "sg:phone":"+49 39772/20491",
    "sg:postcode":"17379",
    "sg:province":"Mecklenburg-Vorpommern",
    "wof:name":"Metallbau Rieger",
    "wof:placetype":"venue"
},
  "geometry": {"coordinates":[13.784088,53.609795],"type":"Point"}
}