{
  "type": "Feature",
  "properties": {
    "iso:country":"DE",
    "sg:address":"Berliner Ring 20",
    "sg:city":"T\u00fcbingen",
    "sg:phone":"+49 7071/62101",
    "sg:postcode":"72076",
    "sg:province":"Baden-W\u00fcrttemberg",
    "wof:name":"Pfannkuch Gmbh & Co.",
    "wof:placetype":"venue"
},
  "geometry": {"coordinates":[9.060177803,48.5424919128],"type":"Point"}
}