{
  "type": "Feature",
  "properties": {
    "iso:country":"DE",
    "sg:address":"Eilersweg 39 d",
    "sg:city":"Hamburg",
    "sg:phone":"+49 40/6771158",
    "sg:postcode":"22143",
    "sg:province":"Hamburg",
    "wof:name":"Werner Sindt Ingenieur",
    "wof:placetype":"venue"
},
  "geometry": {"coordinates":[10.1643819809,53.6002426147],"type":"Point"}
}