{
  "type": "Feature",
  "properties": {
    "iso:country":"DE",
    "sg:address":"L\u00f6nsweg 3",
    "sg:city":"Minden",
    "sg:phone":"+49 571/41803",
    "sg:postcode":"32425",
    "sg:province":"Nordrhein-Westfalen",
    "wof:name":"Pelz Atelier Forth Kg",
    "wof:placetype":"venue"
},
  "geometry": {"coordinates":[8.913012,52.338219],"type":"Point"}
}