{
  "type": "Feature",
  "properties": {
    "iso:country":"DE",
    "sg:address":"Am Ehrenmal 45a",
    "sg:city":"Essen",
    "sg:phone":"+49 201/581369",
    "sg:postcode":"45277",
    "sg:province":"Nordrhein-Westfalen",
    "wof:name":"Gartenbau-richter.de",
    "wof:placetype":"venue"
},
  "geometry": {"coordinates":[7.0772900581,51.4235992432],"type":"Point"}
}