{
  "type": "Feature",
  "properties": {
    "iso:country":"DE",
    "sg:address":"Rieberseck",
    "sg:city":"Egglkofen",
    "sg:phone":"+49 8639/5214",
    "sg:postcode":"84546",
    "sg:province":"Bayern",
    "wof:name":"Rudolf Miklautz Architekt",
    "wof:placetype":"venue"
},
  "geometry": {"coordinates":[12.458107,48.397194],"type":"Point"}
}