{
  "type": "Feature",
  "properties": {
    "iso:country":"DE",
    "sg:address":"St.-Petersburger Str. 18b",
    "sg:city":"Rostock",
    "sg:phone":"+49 381/7683314",
    "sg:postcode":"18107",
    "sg:province":"Mecklenburg-Vorpommern",
    "wof:name":"Bistro Rucki Zucki",
    "wof:placetype":"venue"
},
  "geometry": {"coordinates":[12.0569438934,54.1389465332],"type":"Point"}
}