{
  "type": "Feature",
  "properties": {
    "iso:country":"DE",
    "sg:address":"Berliner Str. 13",
    "sg:city":"Spremberg",
    "sg:phone":"+49 3563/4733",
    "sg:postcode":"03130",
    "sg:province":"Brandenburg",
    "wof:name":"Hans-j\u00fcrgen Lehnigk",
    "wof:placetype":"venue"
},
  "geometry": {"coordinates":[14.3612937927,51.581325531],"type":"Point"}
}