{
  "type": "Feature",
  "properties": {
    "iso:country":"DE",
    "sg:address":"Giesenweiler 3",
    "sg:city":"Bergatreute",
    "sg:phone":"+49 7527/1309",
    "sg:postcode":"88368",
    "sg:province":"Baden-W\u00fcrttemberg",
    "wof:name":"Biohof Albrecht Rissmann",
    "wof:placetype":"venue"
},
  "geometry": {"coordinates":[9.765261,47.860916],"type":"Point"}
}