{
  "type": "Feature",
  "properties": {
    "iso:country":"DE",
    "sg:address":"Oppeln 37",
    "sg:city":"Wingst",
    "sg:phone":"+49 4947/54662",
    "sg:postcode":"21789",
    "sg:province":"Niedersachsen",
    "wof:name":"Anuschka Blockhaus",
    "wof:placetype":"venue"
},
  "geometry": {"coordinates":[8.999652,53.733631],"type":"Point"}
}