{
  "type": "Feature",
  "properties": {
    "iso:country":"DE",
    "sg:address":"Silberburgstr. 26",
    "sg:city":"Stuttgart",
    "sg:phone":"+49 711/221400",
    "sg:postcode":"70176",
    "sg:province":"Baden-W\u00fcrttemberg",
    "wof:name":"Klaus Dudek",
    "wof:placetype":"venue"
},
  "geometry": {"coordinates":[9.159133,48.783844],"type":"Point"}
}