{
  "type": "Feature",
  "properties": {
    "iso:country":"DE",
    "sg:address":"Am Gro\u00dfen Geeren 17",
    "sg:city":"Ritterhude",
    "sg:phone":"+49 4292/81380",
    "sg:postcode":"27721",
    "sg:province":"Niedersachsen",
    "wof:name":"Fliesen R\u00f6pke Gmbh",
    "wof:placetype":"venue"
},
  "geometry": {"coordinates":[8.7535409927,53.1861953735],"type":"Point"}
}