{
  "type": "Feature",
  "properties": {
    "iso:country":"DE",
    "sg:address":"Tuchbergstr. 1",
    "sg:city":"Aidlingen",
    "sg:phone":"+49 7034/7030",
    "sg:postcode":"71134",
    "sg:province":"Baden-W\u00fcrttemberg",
    "wof:name":"Andreas Schubert",
    "wof:placetype":"venue"
},
  "geometry": {"coordinates":[8.905694,48.676945],"type":"Point"}
}