{
  "type": "Feature",
  "properties": {
    "iso:country":"DE",
    "sg:address":"Hauptstr. 1",
    "sg:city":"Bietigheim-Bissingen",
    "sg:phone":"+49 7142/940420",
    "sg:postcode":"74321",
    "sg:province":"Baden-W\u00fcrttemberg",
    "wof:name":"Geiger",
    "wof:placetype":"venue"
},
  "geometry": {"coordinates":[9.130036,48.959743],"type":"Point"}
}