{
  "type": "Feature",
  "properties": {
    "iso:country":"DE",
    "sg:address":"Hauptstr. 219",
    "sg:city":"Gorxheimertal",
    "sg:phone":"+49 6201/24251",
    "sg:postcode":"69517",
    "sg:province":"Hessen",
    "wof:name":"Udo Ga\u00dfmann",
    "wof:placetype":"venue"
},
  "geometry": {"coordinates":[8.72841,49.532337],"type":"Point"}
}