{
  "type": "Feature",
  "properties": {
    "iso:country":"DE",
    "sg:address":"Moselstr. 21",
    "sg:city":"Bruttig-Fankel",
    "sg:phone":"+49 2671/7563",
    "sg:postcode":"56814",
    "sg:province":"Rheinland-Pfalz",
    "wof:name":"Weinhaus Kolb",
    "wof:placetype":"venue"
},
  "geometry": {"coordinates":[7.2295341492,50.1251182556],"type":"Point"}
}