{
  "type": "Feature",
  "properties": {
    "iso:country":"DE",
    "sg:address":"Johann-Sebastian-Bach-Str. 3",
    "sg:city":"Hilden",
    "sg:phone":"+49 2103/334293",
    "sg:postcode":"40724",
    "sg:province":"Nordrhein-Westfalen",
    "wof:name":"Griechisches Restaurant \u00c4gina",
    "wof:placetype":"venue"
},
  "geometry": {"coordinates":[6.9334158897,51.1808052063],"type":"Point"}
}