{
  "type": "Feature",
  "properties": {
    "iso:country":"DE",
    "sg:address":"Bahnhofstr. 15",
    "sg:city":"Hallstadt",
    "sg:phone":"+49 951/71990",
    "sg:postcode":"96103",
    "sg:province":"Bayern",
    "wof:name":"Sozialstation Der Caritas",
    "wof:placetype":"venue"
},
  "geometry": {"coordinates":[10.877497,49.929188],"type":"Point"}
}