{
  "type": "Feature",
  "properties": {
    "iso:country":"DE",
    "sg:address":"Sturmbergstr. 1",
    "sg:city":"Illmensee",
    "sg:phone":"+49 7558/94221",
    "sg:postcode":"88636",
    "sg:province":"Baden-W\u00fcrttemberg",
    "wof:name":"Karl-heinz Uebele",
    "wof:placetype":"venue"
},
  "geometry": {"coordinates":[9.355999,47.880501],"type":"Point"}
}