{
  "type": "Feature",
  "properties": {
    "iso:country":"DE",
    "sg:address":"Hohe Str. 73",
    "sg:city":"K\u00f6ln",
    "sg:phone":"+49 221/2575793",
    "sg:postcode":"50667",
    "sg:province":"Nordrhein-Westfalen",
    "wof:name":"C\u00f6ln-carre",
    "wof:placetype":"venue"
},
  "geometry": {"coordinates":[6.956026,50.937267],"type":"Point"}
}