{
  "type": "Feature",
  "properties": {
    "iso:country":"DE",
    "sg:address":"Wurtestr. 7",
    "sg:city":"Nordhorn",
    "sg:phone":"+49 5921/36204",
    "sg:postcode":"48529",
    "sg:province":"Niedersachsen",
    "wof:name":"Theo Griese Ingenieur",
    "wof:placetype":"venue"
},
  "geometry": {"coordinates":[7.077270031,52.4387779236],"type":"Point"}
}