{
  "type": "Feature",
  "properties": {
    "iso:country":"DE",
    "sg:address":"Beim Amthaus 1",
    "sg:city":"Hofgeismar",
    "sg:phone":"+49 5671/2797",
    "sg:postcode":"34369",
    "sg:province":"Hessen",
    "wof:name":"Klaus-peter Jahn Steuerberater",
    "wof:placetype":"venue"
},
  "geometry": {"coordinates":[9.3820161819,51.4974822998],"type":"Point"}
}