{
  "type": "Feature",
  "properties": {
    "iso:country":"DE",
    "sg:address":"Carl-Zeiss-Str. 25",
    "sg:city":"Mainz",
    "sg:phone":"+49 6131/682244",
    "sg:postcode":"55129",
    "sg:province":"Rheinland-Pfalz",
    "wof:name":"H\u00f6hler Gmbh",
    "wof:placetype":"venue"
},
  "geometry": {"coordinates":[8.257442,49.962627],"type":"Point"}
}