{
  "type": "Feature",
  "properties": {
    "iso:country":"DE",
    "sg:address":"Bahnhofstr. 33",
    "sg:city":"Neu-Anspach",
    "sg:phone":"+49 6081/41181",
    "sg:postcode":"61267",
    "sg:province":"Hessen",
    "wof:name":"Dagmar Burgard",
    "wof:placetype":"venue"
},
  "geometry": {"coordinates":[8.5118103027,50.2935218811],"type":"Point"}
}