{
  "type": "Feature",
  "properties": {
    "iso:country":"DE",
    "sg:address":"Greifswalder Str. 9",
    "sg:city":"S\u00fcderholz",
    "sg:postcode":"18516",
    "sg:province":"Mecklenburg-Vorpommern",
    "wof:name":"Sanierungs Gmbh",
    "wof:placetype":"venue"
},
  "geometry": {"coordinates":[13.1209506989,54.053855896],"type":"Point"}
}