{
  "type": "Feature",
  "properties": {
    "iso:country":"DE",
    "sg:address":"Seestr. 82",
    "sg:city":"Seebad Bansin",
    "sg:postcode":"17429",
    "sg:province":"Mecklenburg-Vorpommern",
    "wof:name":"Kg Nord Eg",
    "wof:placetype":"venue"
},
  "geometry": {"coordinates":[14.0721549988,53.9404411316],"type":"Point"}
}