{
  "type": "Feature",
  "properties": {
    "iso:country":"DE",
    "sg:address":"Am Nordkanal 37",
    "sg:city":"Willich",
    "sg:phone":"+49 2154/600",
    "sg:postcode":"47877",
    "sg:province":"Nordrhein-Westfalen",
    "wof:name":"Norton Gmbh Objekt Schiefbahn",
    "wof:placetype":"venue"
},
  "geometry": {"coordinates":[6.5241861343,51.2335357666],"type":"Point"}
}