{
  "type": "Feature",
  "properties": {
    "iso:country":"DE",
    "sg:address":"Dieburger Str. 15",
    "sg:city":"R\u00f6dermark",
    "sg:phone":"+49 6074/97234",
    "sg:postcode":"63322",
    "sg:province":"Hessen",
    "wof:name":"Brehm Gmbh",
    "wof:placetype":"venue"
},
  "geometry": {"coordinates":[8.827949,49.977448],"type":"Point"}
}