{
  "type": "Feature",
  "properties": {
    "iso:country":"DE",
    "sg:address":"P\u00f6litzer Weg 6",
    "sg:city":"Bad Oldesloe",
    "sg:phone":"+49 4531/670307",
    "sg:postcode":"23843",
    "sg:province":"Schleswig-Holstein",
    "wof:name":"Billardcafe Players",
    "wof:placetype":"venue"
},
  "geometry": {"coordinates":[10.38226,53.802769],"type":"Point"}
}