{
  "type": "Feature",
  "properties": {
    "iso:country":"DE",
    "sg:address":"Schwarzer Weg 19",
    "sg:city":"M\u00fcncheberg",
    "sg:postcode":"15374",
    "sg:province":"Brandenburg",
    "wof:name":"Fun & Game World Gmbh",
    "wof:placetype":"venue"
},
  "geometry": {"coordinates":[14.1222219467,52.5055160522],"type":"Point"}
}