{
  "type": "Feature",
  "properties": {
    "iso:country":"DE",
    "sg:address":"Schellingstr. 2",
    "sg:city":"Seitingen-Oberflacht",
    "sg:phone":"+49 7464/37031",
    "sg:postcode":"78606",
    "sg:province":"Baden-W\u00fcrttemberg",
    "wof:name":"Carry Und Ron",
    "wof:placetype":"venue"
},
  "geometry": {"coordinates":[8.7304344177,48.0230865479],"type":"Point"}
}