{
  "type": "Feature",
  "properties": {
    "iso:country":"DE",
    "sg:address":"Sportplatzstr. 13",
    "sg:city":"Schwandorf",
    "sg:phone":"+49 9431/1051",
    "sg:postcode":"92421",
    "sg:province":"Bayern",
    "wof:name":"Fc Sportgastst\u00e4tte Tennisheim",
    "wof:placetype":"venue"
},
  "geometry": {"coordinates":[12.092420578,49.3311271667],"type":"Point"}
}