{
  "type": "Feature",
  "properties": {
    "iso:country":"DE",
    "sg:address":"Godehardstr. 22",
    "sg:city":"G\u00f6ttingen",
    "sg:phone":"+49 551/61208",
    "sg:postcode":"37081",
    "sg:province":"Niedersachsen",
    "wof:name":"Katholisches Pfarramt St. Godehard",
    "wof:placetype":"venue"
},
  "geometry": {"coordinates":[9.917798996,51.5414009094],"type":"Point"}
}