{
  "type": "Feature",
  "properties": {
    "iso:country":"DE",
    "sg:address":"Weschnitzsiedlung 6",
    "sg:city":"Laudenbach",
    "sg:phone":"+49 6201/71698",
    "sg:postcode":"69514",
    "sg:province":"Baden-W\u00fcrttemberg",
    "wof:name":"Hans Eckstein",
    "wof:placetype":"venue"
},
  "geometry": {"coordinates":[8.625598,49.607342],"type":"Point"}
}