{
  "type": "Feature",
  "properties": {
    "iso:country":"DE",
    "sg:address":"Begasstr. 10",
    "sg:city":"Berlin",
    "sg:phone":"+49 30/8554979",
    "sg:postcode":"12157",
    "sg:province":"Berlin",
    "wof:name":"Herbert Gallus Rechtsanwalt",
    "wof:placetype":"venue"
},
  "geometry": {"coordinates":[13.3435964584,52.4693183899],"type":"Point"}
}