{
  "type": "Feature",
  "properties": {
    "iso:country":"DE",
    "sg:address":"Maxburgstr. 4",
    "sg:city":"Jockgrim",
    "sg:phone":"+49 7271/51377",
    "sg:postcode":"76751",
    "sg:province":"Rheinland-Pfalz",
    "wof:name":"Hik-grundst\u00fccks-verwaltungs- Und Verwertungs- Gmbh",
    "wof:placetype":"venue"
},
  "geometry": {"coordinates":[8.2656488419,49.0868682861],"type":"Point"}
}