{
  "type": "Feature",
  "properties": {
    "iso:country":"DE",
    "sg:address":"Schneiderstr. 56",
    "sg:city":"Krefeld",
    "sg:phone":"+49 2151/610002",
    "sg:postcode":"47798",
    "sg:province":"Nordrhein-Westfalen",
    "wof:name":"F. Gr\u00fcmbel",
    "wof:placetype":"venue"
},
  "geometry": {"coordinates":[6.558411,51.335556],"type":"Point"}
}