{
  "type": "Feature",
  "properties": {
    "iso:country":"DE",
    "sg:address":"Otto-Schill-Str. 9",
    "sg:city":"Leipzig",
    "sg:phone":"+49 341/8622993",
    "sg:postcode":"04109",
    "sg:province":"Sachsen",
    "wof:name":"Verlag F\u00fcr Soziales Und Kommunales",
    "wof:placetype":"venue"
},
  "geometry": {"coordinates":[12.3711204529,51.3397903442],"type":"Point"}
}