{
  "type": "Feature",
  "properties": {
    "iso:country":"DE",
    "sg:address":"Billbrookdeich 302",
    "sg:city":"Hamburg",
    "sg:phone":"+49 40/7323110",
    "sg:postcode":"22113",
    "sg:province":"Schleswig-Holstein",
    "wof:name":"Western Communication Corp.",
    "wof:placetype":"venue"
},
  "geometry": {"coordinates":[10.1116027832,53.5276832581],"type":"Point"}
}