{
  "type": "Feature",
  "properties": {
    "iso:country":"DE",
    "sg:address":"Gem\u00fcsestr. 13",
    "sg:city":"Enger",
    "sg:phone":"+49 5224/2104",
    "sg:postcode":"32130",
    "sg:province":"Nordrhein-Westfalen",
    "wof:name":"Wilh. Schr\u00f6der",
    "wof:placetype":"venue"
},
  "geometry": {"coordinates":[8.594104,52.141422],"type":"Point"}
}