{
  "type": "Feature",
  "properties": {
    "iso:country":"DE",
    "sg:address":"Hauptstr.70",
    "sg:city":"Oldenburg",
    "sg:phone":"+49 441/9558585",
    "sg:postcode":"26122",
    "sg:province":"Niedersachsen",
    "wof:name":"Bonnke Fahrr\u00e4der",
    "wof:placetype":"venue"
},
  "geometry": {"coordinates":[8.1941814423,53.1332588196],"type":"Point"}
}