{
  "type": "Feature",
  "properties": {
    "iso:country":"DE",
    "sg:address":"Tannenweg 40",
    "sg:city":"Sankt Augustin",
    "sg:phone":"+49 2241/337417",
    "sg:postcode":"53757",
    "sg:province":"Nordrhein-Westfalen",
    "wof:name":"Ludger Und Gabriele Ueberhorst",
    "wof:placetype":"venue"
},
  "geometry": {"coordinates":[7.1945419312,50.7641716003],"type":"Point"}
}