{
  "type": "Feature",
  "properties": {
    "iso:country":"DE",
    "sg:address":"Frankfurter Str. 44",
    "sg:city":"K\u00f6ln",
    "sg:phone":"+49 221/962170",
    "sg:postcode":"51065",
    "sg:province":"Nordrhein-Westfalen",
    "wof:name":"Hapag Lloyd Reiseb\u00fcro Gmbh",
    "wof:placetype":"venue"
},
  "geometry": {"coordinates":[7.0079250336,50.9597053528],"type":"Point"}
}