{
  "type": "Feature",
  "properties": {
    "iso:country":"DE",
    "sg:address":"Hillebachstr. 6",
    "sg:city":"Eimen",
    "sg:phone":"+49 4955/65238",
    "sg:postcode":"37632",
    "sg:province":"Niedersachsen",
    "wof:name":"Lutz- Martin Buschbeck",
    "wof:placetype":"venue"
},
  "geometry": {"coordinates":[9.778762,51.878395],"type":"Point"}
}