{
  "type": "Feature",
  "properties": {
    "iso:country":"DE",
    "sg:address":"Wiesenstr. 18",
    "sg:city":"Lage",
    "sg:phone":"+49 5232/95230",
    "sg:postcode":"32791",
    "sg:province":"Nordrhein-Westfalen",
    "wof:name":"Dietrich Vennekamp Ingenieur",
    "wof:placetype":"venue"
},
  "geometry": {"coordinates":[8.8107910156,51.9914855957],"type":"Point"}
}