{
  "type": "Feature",
  "properties": {
    "iso:country":"DE",
    "sg:address":"Schulstr. 16",
    "sg:city":"Darmstadt",
    "sg:phone":"+49 6151/22136",
    "sg:postcode":"64283",
    "sg:province":"Hessen",
    "wof:name":"M. Kabel & C. Lang",
    "wof:placetype":"venue"
},
  "geometry": {"coordinates":[8.6562433243,49.8707885742],"type":"Point"}
}