{
  "type": "Feature",
  "properties": {
    "iso:country":"DE",
    "sg:address":"Dieselstr. 1-3",
    "sg:city":"Reinbek",
    "sg:postcode":"21465",
    "sg:province":"Schleswig-Holstein",
    "wof:name":"Hhg Haustechnik Handels Gmbh",
    "wof:placetype":"venue"
},
  "geometry": {"coordinates":[10.2350330353,53.5248031616],"type":"Point"}
}