{
  "type": "Feature",
  "properties": {
    "iso:country":"DE",
    "sg:address":"Lange Str. 13",
    "sg:city":"Breitenworbis",
    "sg:phone":"+49 36074/94144",
    "sg:postcode":"37339",
    "sg:province":"Th\u00fcringen",
    "wof:name":"Paul Wand",
    "wof:placetype":"venue"
},
  "geometry": {"coordinates":[10.4260034561,51.4117546082],"type":"Point"}
}