{
  "type": "Feature",
  "properties": {
    "iso:country":"DE",
    "sg:address":"Neust\u00e4dter Str. 9",
    "sg:city":"Neustadt",
    "sg:phone":"+49 5073/266",
    "sg:postcode":"31535",
    "sg:province":"Niedersachsen",
    "wof:name":"Friedrich-wilhelm Zwitters",
    "wof:placetype":"venue"
},
  "geometry": {"coordinates":[11.922644,51.480469],"type":"Point"}
}