{
  "type": "Feature",
  "properties": {
    "iso:country":"DE",
    "sg:address":"Cheruskerstr. 88",
    "sg:city":"D\u00fcsseldorf",
    "sg:phone":"+49 211/553350",
    "sg:postcode":"40545",
    "sg:province":"Nordrhein-Westfalen",
    "wof:name":"Retzko Und Topp Ingenieure",
    "wof:placetype":"venue"
},
  "geometry": {"coordinates":[6.749516964,51.2311935425],"type":"Point"}
}