{
  "type": "Feature",
  "properties": {
    "iso:country":"DE",
    "sg:address":"Marienstr. 74",
    "sg:city":"Oberhausen-Rheinhausen",
    "sg:phone":"+49 7254/2697",
    "sg:postcode":"68794",
    "sg:province":"Baden-W\u00fcrttemberg",
    "wof:name":"Madeleine",
    "wof:placetype":"venue"
},
  "geometry": {"coordinates":[8.489917,49.256847],"type":"Point"}
}