{
  "type": "Feature",
  "properties": {
    "iso:country":"DE",
    "sg:address":"Basler Str. 109",
    "sg:city":"Grenzach-Wyhlen",
    "sg:phone":"+49 7624/3050",
    "sg:postcode":"79639",
    "sg:province":"Baden-W\u00fcrttemberg",
    "wof:name":"Dr. Osypka Gmbh",
    "wof:placetype":"venue"
},
  "geometry": {"coordinates":[7.646728,47.556057],"type":"Point"}
}