{
  "type": "Feature",
  "properties": {
    "iso:country":"DE",
    "sg:address":"Moos",
    "sg:city":"Forstinning",
    "sg:phone":"+49 8121/3881",
    "sg:postcode":"85661",
    "sg:province":"Bayern",
    "wof:name":"H. F\u00f6rster",
    "wof:placetype":"venue"
},
  "geometry": {"coordinates":[11.8943996429,48.1658592224],"type":"Point"}
}