{
  "type": "Feature",
  "properties": {
    "iso:country":"DE",
    "sg:address":"Kirchlesberg 16",
    "sg:city":"Zwiefalten",
    "sg:phone":"+49 7373/316",
    "sg:postcode":"88529",
    "sg:province":"Baden-W\u00fcrttemberg",
    "wof:name":"Hans Raisle Masseur",
    "wof:placetype":"venue"
},
  "geometry": {"coordinates":[9.453385,48.243622],"type":"Point"}
}