{
  "type": "Feature",
  "properties": {
    "iso:country":"DE",
    "sg:address":"Eescher Weg 47",
    "sg:city":"Meldorf",
    "sg:phone":"+49 4832/9990",
    "sg:postcode":"25704",
    "sg:province":"Schleswig-Holstein",
    "wof:name":"Werkstatt F\u00fcr Behinderte Meldorf Ggmbh",
    "wof:placetype":"venue"
},
  "geometry": {"coordinates":[9.09253,54.091755],"type":"Point"}
}