{
  "type": "Feature",
  "properties": {
    "iso:country":"DE",
    "sg:address":"Reeperbahn 36",
    "sg:city":"Hamburg",
    "sg:phone":"+49 40/314838",
    "sg:postcode":"20359",
    "sg:province":"Hamburg",
    "wof:name":"Hotel Wellers",
    "wof:placetype":"venue"
},
  "geometry": {"coordinates":[9.9654073715,53.5499954224],"type":"Point"}
}