{
  "type": "Feature",
  "properties": {
    "iso:country":"DE",
    "sg:address":"Kaiserstr. 87",
    "sg:city":"Radevormwald",
    "sg:phone":"+49 2195/2432",
    "sg:postcode":"42477",
    "sg:province":"Nordrhein-Westfalen",
    "wof:name":"M\u00f6bel Schaub Gmbh",
    "wof:placetype":"venue"
},
  "geometry": {"coordinates":[7.359249,51.202644],"type":"Point"}
}