{
  "type": "Feature",
  "properties": {
    "iso:country":"DE",
    "sg:address":"Unterm Ohmberg 12",
    "sg:city":"Marsberg",
    "sg:phone":"+49 2992/97900",
    "sg:postcode":"34431",
    "sg:province":"Nordrhein-Westfalen",
    "wof:name":"Gebr. Tusche",
    "wof:placetype":"venue"
},
  "geometry": {"coordinates":[8.8728017807,51.4753189087],"type":"Point"}
}