{
  "type": "Feature",
  "properties": {
    "iso:country":"DE",
    "sg:address":"Reesenb\u00fcttler Redder 2",
    "sg:city":"Ahrensburg",
    "sg:phone":"+49 4102/41594",
    "sg:postcode":"22926",
    "sg:province":"Schleswig-Holstein",
    "wof:name":"Ernst Schramm",
    "wof:placetype":"venue"
},
  "geometry": {"coordinates":[10.222598,53.67942],"type":"Point"}
}