{
  "type": "Feature",
  "properties": {
    "iso:country":"DE",
    "sg:address":"Platanenstr. 2 a",
    "sg:city":"Frankenthal",
    "sg:phone":"+49 6233/53401",
    "sg:postcode":"67227",
    "sg:province":"Rheinland-Pfalz",
    "wof:name":"Oskar Strefler",
    "wof:placetype":"venue"
},
  "geometry": {"coordinates":[8.329505,49.50647],"type":"Point"}
}