{
  "type": "Feature",
  "properties": {
    "iso:country":"DE",
    "sg:address":"Minister-Karl-M\u00f6ller-Str. 9",
    "sg:city":"Quakenbr\u00fcck",
    "sg:phone":"+49 5431/94220",
    "sg:postcode":"49610",
    "sg:province":"Niedersachsen",
    "wof:name":"Nobis Und L\u00f6wenau Rechtsanw\u00e4lte Und Notare",
    "wof:placetype":"venue"
},
  "geometry": {"coordinates":[7.9513640404,52.6794242859],"type":"Point"}
}