{
  "type": "Feature",
  "properties": {
    "iso:country":"DE",
    "sg:address":"Ernst-Th\u00e4lmann-Str. 23",
    "sg:city":"Biere",
    "sg:phone":"+49 39297/21190",
    "sg:postcode":"39221",
    "sg:province":"Sachsen-Anhalt",
    "wof:name":"Peter Buchwald Bauelemente Gmbh",
    "wof:placetype":"venue"
},
  "geometry": {"coordinates":[11.649342,51.974255],"type":"Point"}
}