{
  "type": "Feature",
  "properties": {
    "iso:country":"DE",
    "sg:address":"Lindenstr. 5",
    "sg:city":"Colbitz",
    "sg:postcode":"39326",
    "sg:province":"Sachsen-Anhalt",
    "wof:name":"Eva Fehse",
    "wof:placetype":"venue"
},
  "geometry": {"coordinates":[11.5905513763,52.3031692505],"type":"Point"}
}