{
  "type": "Feature",
  "properties": {
    "iso:country":"DE",
    "sg:address":"Hauptstr. 42",
    "sg:city":"Overath",
    "sg:postcode":"51491",
    "sg:province":"Nordrhein-Westfalen",
    "wof:name":"Ingenia Informationstechnologie Gmbh",
    "wof:placetype":"venue"
},
  "geometry": {"coordinates":[7.2858948708,50.9326782227],"type":"Point"}
}