{
  "type": "Feature",
  "properties": {
    "iso:country":"DE",
    "sg:address":"Baumannsh\u00f6hlenweg 8",
    "sg:city":"R\u00fcbeland",
    "sg:phone":"+49 39454/49165",
    "sg:postcode":"38889",
    "sg:province":"Sachsen-Anhalt",
    "wof:name":"W. B\u00fcschel",
    "wof:placetype":"venue"
},
  "geometry": {"coordinates":[10.954169,51.790661],"type":"Point"}
}