{
  "type": "Feature",
  "properties": {
    "iso:country":"DE",
    "sg:address":"Am Rosenplatz 1",
    "sg:city":"R\u00fchen",
    "sg:phone":"+49 5367/714",
    "sg:postcode":"38471",
    "sg:province":"Niedersachsen",
    "wof:name":"Bernd Hoppe",
    "wof:placetype":"venue"
},
  "geometry": {"coordinates":[10.876848,52.478237],"type":"Point"}
}