{
  "type": "Feature",
  "properties": {
    "iso:country":"DE",
    "sg:address":"Dorfstr. 29",
    "sg:city":"Beggerow",
    "sg:postcode":"17111",
    "sg:province":"Mecklenburg-Vorpommern",
    "wof:name":"Evangelisch-lutherische Kirche",
    "wof:placetype":"venue"
},
  "geometry": {"coordinates":[13.0516910553,53.8273124695],"type":"Point"}
}