{
  "type": "Feature",
  "properties": {
    "iso:country":"DE",
    "sg:address":"Fl\u00f6\u00dferweg 18",
    "sg:city":"Rheinau",
    "sg:phone":"+49 7844/2134",
    "sg:postcode":"77866",
    "sg:province":"Baden-W\u00fcrttemberg",
    "wof:name":"J\u00f6rg Friedrichs Ingenieur",
    "wof:placetype":"venue"
},
  "geometry": {"coordinates":[7.9427042007,48.6697387695],"type":"Point"}
}