{
  "type": "Feature",
  "properties": {
    "iso:country":"DE",
    "sg:address":"Neustadt 18",
    "sg:city":"Zittau",
    "sg:phone":"+49 3583/77555850",
    "sg:postcode":"02763",
    "sg:province":"Sachsen",
    "wof:name":"S\u00e4chsische Zeitung",
    "wof:placetype":"venue"
},
  "geometry": {"coordinates":[14.8109750748,50.8960227966],"type":"Point"}
}