{
  "type": "Feature",
  "properties": {
    "iso:country":"DE",
    "sg:address":"Theodor-Heuss-Str. 48",
    "sg:city":"Aichach",
    "sg:phone":"+49 8251/87440",
    "sg:postcode":"86551",
    "sg:province":"Bayern",
    "wof:name":"G & S Steuerberatungsges. Mbh",
    "wof:placetype":"venue"
},
  "geometry": {"coordinates":[11.1283121109,48.4529724121],"type":"Point"}
}