{
  "type": "Feature",
  "properties": {
    "iso:country":"DE",
    "sg:address":"Bei der Neuen M\u00fcnze 18a",
    "sg:city":"Hamburg",
    "sg:phone":"+49 40/67929693",
    "sg:postcode":"22145",
    "sg:province":"Hamburg",
    "wof:name":"Alstertaler M\u00f6beltransporte Andre Raabe",
    "wof:placetype":"venue"
},
  "geometry": {"coordinates":[10.153637886,53.6235237122],"type":"Point"}
}