{
  "type": "Feature",
  "properties": {
    "iso:country":"DE",
    "sg:address":"Max-Planck-Str 15",
    "sg:city":"Wittlich",
    "sg:phone":"+49 6571/10070",
    "sg:postcode":"54516",
    "sg:province":"Rheinland-Pfalz",
    "wof:name":"Kunsmann-cordes Ag",
    "wof:placetype":"venue"
},
  "geometry": {"coordinates":[6.904788,49.986687],"type":"Point"}
}