{
  "type": "Feature",
  "properties": {
    "iso:country":"DE",
    "sg:address":"Hauptstr. 20 a",
    "sg:city":"Sulzbach-Rosenberg",
    "sg:phone":"+49 9661/6512",
    "sg:postcode":"92237",
    "sg:province":"Bayern",
    "wof:name":"E. Schinhammer",
    "wof:placetype":"venue"
},
  "geometry": {"coordinates":[11.7649316788,49.4903106689],"type":"Point"}
}