{
  "type": "Feature",
  "properties": {
    "iso:country":"DE",
    "sg:address":"Hauptstr. 36",
    "sg:city":"Patersberg",
    "sg:phone":"+49 6771/951200",
    "sg:postcode":"56348",
    "sg:province":"Rheinland-Pfalz",
    "wof:name":"Interstone Gmbh",
    "wof:placetype":"venue"
},
  "geometry": {"coordinates":[7.73491,50.156593],"type":"Point"}
}