{
  "type": "Feature",
  "properties": {
    "iso:country":"DE",
    "sg:address":"Moorstr. 38",
    "sg:city":"Wees",
    "sg:postcode":"24999",
    "sg:province":"Schleswig-Holstein",
    "wof:name":"Niels Munkholm Generalvertretung Von Dat-",
    "wof:placetype":"venue"
},
  "geometry": {"coordinates":[9.526431,54.80711],"type":"Point"}
}