{
  "type": "Feature",
  "properties": {
    "iso:country":"DE",
    "sg:address":"Garmischer Str. 4",
    "sg:city":"M\u00fcnchen",
    "sg:postcode":"80339",
    "sg:province":"Bayern",
    "wof:name":"Schweiz-deutschland-usa Dreil. Beteil. Obj, Dlf 98/29",
    "wof:placetype":"venue"
},
  "geometry": {"coordinates":[11.532854,48.133274],"type":"Point"}
}