{
  "type": "Feature",
  "properties": {
    "iso:country":"DE",
    "sg:address":"Eckernf\u00f6rder Str.",
    "sg:city":"Haby",
    "sg:phone":"+49 4356/806",
    "sg:postcode":"24361",
    "sg:province":"Schleswig-Holstein",
    "wof:name":"M\u00f6belhalle Haby Gmbh",
    "wof:placetype":"venue"
},
  "geometry": {"coordinates":[9.818903923,54.3998260498],"type":"Point"}
}