{
  "type": "Feature",
  "properties": {
    "iso:country":"DE",
    "sg:address":"Biberacher Str. 73",
    "sg:city":"Ehingen",
    "sg:phone":"+49 4973/915010",
    "sg:postcode":"89584",
    "sg:province":"Baden-W\u00fcrttemberg",
    "wof:name":"Betriebskrankenkasse Technoform",
    "wof:placetype":"venue"
},
  "geometry": {"coordinates":[9.726785,48.282387],"type":"Point"}
}