{
  "type": "Feature",
  "properties": {
    "iso:country":"DE",
    "sg:address":"Haingrabenstr. 28 a",
    "sg:city":"Frankfurt",
    "sg:phone":"+49 69/551268",
    "sg:postcode":"60488",
    "sg:province":"Hessen",
    "wof:name":"Hsh Import- Export Gmbh",
    "wof:placetype":"venue"
},
  "geometry": {"coordinates":[8.6212444305,50.152053833],"type":"Point"}
}