{
  "type": "Feature",
  "properties": {
    "iso:country":"DE",
    "sg:address":"Sagweg 14",
    "sg:city":"Furth im Wald",
    "sg:phone":"+49 9973/9514",
    "sg:postcode":"93437",
    "sg:province":"Bayern",
    "wof:name":"M.-l. Und S. Amberger",
    "wof:placetype":"venue"
},
  "geometry": {"coordinates":[12.842475,49.312798],"type":"Point"}
}