{
  "type": "Feature",
  "properties": {
    "iso:country":"DE",
    "sg:address":"M\u00fchlbach",
    "sg:city":"Selb",
    "sg:phone":"+49 9287/1373",
    "sg:postcode":"95100",
    "sg:province":"Bayern",
    "wof:name":"Wiesental",
    "wof:placetype":"venue"
},
  "geometry": {"coordinates":[12.1661310196,50.1895751953],"type":"Point"}
}