{
  "type": "Feature",
  "properties": {
    "iso:country":"DE",
    "sg:address":"Gothaer Weg 36",
    "sg:city":"Hamburg",
    "sg:phone":"+49 40/7323480",
    "sg:postcode":"22119",
    "sg:province":"Hamburg",
    "wof:name":"Dieter Pape",
    "wof:placetype":"venue"
},
  "geometry": {"coordinates":[10.105849,53.544472],"type":"Point"}
}