{
  "type": "Feature",
  "properties": {
    "iso:country":"DE",
    "sg:address":"Hohenheimer Str. 30",
    "sg:city":"Filderstadt",
    "sg:phone":"+49 711/7776108",
    "sg:postcode":"70794",
    "sg:province":"Baden-W\u00fcrttemberg",
    "wof:name":"Richard Brabandt",
    "wof:placetype":"venue"
},
  "geometry": {"coordinates":[9.2037649155,48.6642990112],"type":"Point"}
}