{
  "type": "Feature",
  "properties": {
    "iso:country":"DE",
    "sg:address":"L\u00fcbsche Str. 60",
    "sg:city":"Wismar",
    "sg:phone":"+49 3841/211469",
    "sg:postcode":"23966",
    "sg:province":"Mecklenburg-Vorpommern",
    "wof:name":"Der Neue Weipert Heimtex Gmbh",
    "wof:placetype":"venue"
},
  "geometry": {"coordinates":[11.4600543976,53.8915939331],"type":"Point"}
}