{
  "type": "Feature",
  "properties": {
    "iso:country":"DE",
    "sg:address":"Windscheidstr. 18",
    "sg:city":"Berlin",
    "sg:phone":"+49 30/7874185",
    "sg:postcode":"10627",
    "sg:province":"Berlin",
    "wof:name":"Udo Sch\u00e4fer Architekt",
    "wof:placetype":"venue"
},
  "geometry": {"coordinates":[13.299708,52.505096],"type":"Point"}
}