{
  "type": "Feature",
  "properties": {
    "iso:country":"DE",
    "sg:address":"Ahornallee 27",
    "sg:city":"Berlin",
    "sg:postcode":"14050",
    "sg:province":"Berlin",
    "wof:name":"Auftragsmalerei.gabriele Van Kempen",
    "wof:placetype":"venue"
},
  "geometry": {"coordinates":[13.2741985321,52.5098266602],"type":"Point"}
}