{
  "type": "Feature",
  "properties": {
    "iso:country":"DE",
    "sg:address":"Isestr. 74",
    "sg:city":"Hamburg",
    "sg:phone":"+49 40/46091250",
    "sg:postcode":"20149",
    "sg:province":"Hamburg",
    "wof:name":"Food Department Catering Service Gmbh",
    "wof:placetype":"venue"
},
  "geometry": {"coordinates":[9.9853935242,53.5832901001],"type":"Point"}
}