{
  "type": "Feature",
  "properties": {
    "iso:country":"DE",
    "sg:address":"Bahnhofstra\u00dfe 106c",
    "sg:city":"Altd\u00f6bern",
    "sg:phone":"+49 35434/12081",
    "sg:postcode":"03229",
    "sg:province":"Brandenburg",
    "wof:name":"Kostenlose Services Und Privates Bei Andreas Rusch",
    "wof:placetype":"venue"
},
  "geometry": {"coordinates":[14.018917,51.648335],"type":"Point"}
}