{
  "type": "Feature",
  "properties": {
    "iso:country":"DE",
    "sg:address":"Natruper Str. 11",
    "sg:city":"Hagen",
    "sg:phone":"+49 5401/9790",
    "sg:postcode":"49170",
    "sg:province":"Niedersachsen",
    "wof:name":"St. Anna-stift",
    "wof:placetype":"venue"
},
  "geometry": {"coordinates":[7.974065,52.197247],"type":"Point"}
}