{
  "type": "Feature",
  "properties": {
    "iso:country":"DE",
    "sg:address":"F\u00e4rbergasse 5",
    "sg:city":"Thum-Jahnsbach",
    "sg:phone":"+49 37297/2558",
    "sg:postcode":"09419",
    "sg:province":"Sachsen",
    "wof:name":"Reinhard Martin",
    "wof:placetype":"venue"
},
  "geometry": {"coordinates":[12.9504203796,50.6694717407],"type":"Point"}
}