{
  "type": "Feature",
  "properties": {
    "iso:country":"DE",
    "sg:address":"Fichtestr. 14",
    "sg:city":"Berlin",
    "sg:phone":"+49 30/4138798",
    "sg:postcode":"13467",
    "sg:province":"Berlin",
    "wof:name":"Manfred Baumann Ingenieur",
    "wof:placetype":"venue"
},
  "geometry": {"coordinates":[13.3059053421,52.6132392883],"type":"Point"}
}