{
  "type": "Feature",
  "properties": {
    "iso:country":"DE",
    "sg:address":"Vordere Schmiedgasse 12",
    "sg:city":"Schw\u00e4bisch Gm\u00fcnd",
    "sg:phone":"+49 7171/66374",
    "sg:postcode":"73525",
    "sg:province":"Baden-W\u00fcrttemberg",
    "wof:name":"Christian Hofielen",
    "wof:placetype":"venue"
},
  "geometry": {"coordinates":[9.799405098,48.8016967773],"type":"Point"}
}