{
  "type": "Feature",
  "properties": {
    "iso:country":"DE",
    "sg:address":"Eduard-Rhein-Str 4",
    "sg:city":"K\u00f6nigswinter",
    "sg:phone":"+49 2244/90260",
    "sg:postcode":"53639",
    "sg:province":"Nordrhein-Westfalen",
    "wof:name":"J & P Vision Gmbh",
    "wof:placetype":"venue"
},
  "geometry": {"coordinates":[7.277417,50.697887],"type":"Point"}
}