{
  "type": "Feature",
  "properties": {
    "iso:country":"DE",
    "sg:address":"Goerdtstr. 35",
    "sg:city":"Bochum",
    "sg:phone":"+49 4923/4937550",
    "sg:postcode":"44803",
    "sg:province":"Nordrhein-Westfalen",
    "wof:name":"Landschaftsbau-baumdienstfranke Gmbh",
    "wof:placetype":"venue"
},
  "geometry": {"coordinates":[7.240515,51.478714],"type":"Point"}
}