{
  "type": "Feature",
  "properties": {
    "iso:country":"DE",
    "sg:address":"Vitus-Bering-Str.34",
    "sg:city":"Rostock",
    "sg:postcode":"18106",
    "sg:province":"Mecklenburg-Vorpommern",
    "wof:name":"Www.torsten-sp.de",
    "wof:placetype":"venue"
},
  "geometry": {"coordinates":[12.071152,54.134987],"type":"Point"}
}