{
  "type": "Feature",
  "properties": {
    "iso:country":"DE",
    "sg:address":"In der Runken 10",
    "sg:city":"Bremen",
    "sg:phone":"+49 421/701911",
    "sg:postcode":"28203",
    "sg:province":"Bremen",
    "wof:name":"Martin Philips Architekt",
    "wof:placetype":"venue"
},
  "geometry": {"coordinates":[8.821876,53.071095],"type":"Point"}
}