{
  "type": "Feature",
  "properties": {
    "iso:country":"DE",
    "sg:address":"Vom-Stein-Str. 2d",
    "sg:city":"Sankt Augustin",
    "sg:phone":"+49 2241/209192",
    "sg:postcode":"53757",
    "sg:province":"Nordrhein-Westfalen",
    "wof:name":"K.-a. Eggert Architekt",
    "wof:placetype":"venue"
},
  "geometry": {"coordinates":[7.190254,50.776741],"type":"Point"}
}