{
  "type": "Feature",
  "properties": {
    "iso:country":"DE",
    "sg:address":"Rheinstr. 2",
    "sg:city":"Krefeld",
    "sg:phone":"+49 2151/29300",
    "sg:postcode":"47799",
    "sg:province":"Nordrhein-Westfalen",
    "wof:name":"Esters",
    "wof:placetype":"venue"
},
  "geometry": {"coordinates":[6.571144,51.334778],"type":"Point"}
}