{
  "type": "Feature",
  "properties": {
    "iso:country":"DE",
    "sg:address":"Feldstr 42-44",
    "sg:city":"Dierdorf",
    "sg:phone":"+49 2689/29559",
    "sg:postcode":"56269",
    "sg:province":"Rheinland-Pfalz",
    "wof:name":"Iso Protect Kunststoffverarbeitung Erik We\u00dfler",
    "wof:placetype":"venue"
},
  "geometry": {"coordinates":[7.650326,50.547665],"type":"Point"}
}