{
  "type": "Feature",
  "properties": {
    "iso:country":"DE",
    "sg:address":"Schwarzwaldstr. 13",
    "sg:city":"Bad Peterstal-Griesbach",
    "sg:phone":"+49 7806/230",
    "sg:postcode":"77740",
    "sg:province":"Baden-W\u00fcrttemberg",
    "wof:name":"Kath. Pfarramt St. Peter Und Paul",
    "wof:placetype":"venue"
},
  "geometry": {"coordinates":[8.210360527,48.4309959412],"type":"Point"}
}