{
  "type": "Feature",
  "properties": {
    "iso:country":"DE",
    "sg:address":"Oberbabing 11",
    "sg:city":"Velden",
    "sg:phone":"+49 8742/8680",
    "sg:postcode":"84149",
    "sg:province":"Bayern",
    "wof:name":"J. Strobl",
    "wof:placetype":"venue"
},
  "geometry": {"coordinates":[12.2282161713,48.3566207886],"type":"Point"}
}