{
  "type": "Feature",
  "properties": {
    "iso:country":"DE",
    "sg:address":"Ringstr. 18",
    "sg:city":"Glash\u00fctten",
    "sg:phone":"+49 6174/63261",
    "sg:postcode":"61479",
    "sg:province":"Hessen",
    "wof:name":"Dieter Paul",
    "wof:placetype":"venue"
},
  "geometry": {"coordinates":[8.3824996948,50.1959228516],"type":"Point"}
}