{
  "type": "Feature",
  "properties": {
    "iso:country":"DE",
    "sg:address":"Gleueler Str. 241",
    "sg:city":"K\u00f6ln",
    "sg:phone":"+49 221/432055",
    "sg:postcode":"50935",
    "sg:province":"Nordrhein-Westfalen",
    "wof:name":"Frank Bergheim",
    "wof:placetype":"venue"
},
  "geometry": {"coordinates":[6.907837,50.922005],"type":"Point"}
}