{
  "type": "Feature",
  "properties": {
    "iso:country":"DE",
    "sg:address":"Tannau",
    "sg:city":"Tettnang",
    "sg:phone":"+49 7542/6266",
    "sg:postcode":"88069",
    "sg:province":"Baden-W\u00fcrttemberg",
    "wof:name":"Hans-peter Vetter",
    "wof:placetype":"venue"
},
  "geometry": {"coordinates":[9.6019849777,47.6585845947],"type":"Point"}
}