{
  "type": "Feature",
  "properties": {
    "iso:country":"DE",
    "sg:address":"Platanenallee 1",
    "sg:city":"\u00d6hringen",
    "sg:phone":"+49 7941/984021",
    "sg:postcode":"74613",
    "sg:province":"Baden-W\u00fcrttemberg",
    "wof:name":"Restaurant Casa Modena",
    "wof:placetype":"venue"
},
  "geometry": {"coordinates":[9.4994182587,49.1926307678],"type":"Point"}
}