{
  "type": "Feature",
  "properties": {
    "iso:country":"DE",
    "sg:address":"Edelwei\u00dfstr. 32",
    "sg:city":"Bad T\u00f6lz",
    "sg:phone":"+49 8041/761283",
    "sg:postcode":"83646",
    "sg:province":"Bayern",
    "wof:name":"S-wohnungsbaugesellschaft Bad T\u00f6lz-wolfratshausen Mbh",
    "wof:placetype":"venue"
},
  "geometry": {"coordinates":[11.570288,47.748165],"type":"Point"}
}