{
  "type": "Feature",
  "properties": {
    "iso:country":"DE",
    "sg:address":"Astrid-Lindgren-Platz",
    "sg:city":"Borkwalde",
    "sg:phone":"+49 33845/40441",
    "sg:postcode":"14822",
    "sg:province":"Brandenburg",
    "wof:name":"Restaurant Pippi Langstrumpf",
    "wof:placetype":"venue"
},
  "geometry": {"coordinates":[12.8369674683,52.2536239624],"type":"Point"}
}