{
  "type": "Feature",
  "properties": {
    "iso:country":"DE",
    "sg:address":"Greifstr. 37 b",
    "sg:city":"Bobingen",
    "sg:phone":"+49 8234/2666",
    "sg:postcode":"86399",
    "sg:province":"Bayern",
    "wof:name":"Ing. Grad. Xaver M\u00f6slang Architekt",
    "wof:placetype":"venue"
},
  "geometry": {"coordinates":[10.83004,48.262245],"type":"Point"}
}