{
  "type": "Feature",
  "properties": {
    "iso:country":"DE",
    "sg:address":"Am Scharfen Stein 22",
    "sg:city":"Meschede",
    "sg:phone":"+49 291/3927",
    "sg:postcode":"59872",
    "sg:province":"Nordrhein-Westfalen",
    "wof:name":"Kutscheit & Co. Textilhandelsgesellschaft",
    "wof:placetype":"venue"
},
  "geometry": {"coordinates":[8.2863702774,51.343296051],"type":"Point"}
}