{
  "type": "Feature",
  "properties": {
    "iso:country":"DE",
    "sg:address":"M\u00fchlplatz 7",
    "sg:city":"Eilenburg",
    "sg:phone":"+49 3423/608455",
    "sg:postcode":"04838",
    "sg:province":"Sachsen",
    "wof:name":"Richard Wolf Inh. Manfred Wolf",
    "wof:placetype":"venue"
},
  "geometry": {"coordinates":[12.626643,51.460133],"type":"Point"}
}