{
  "type": "Feature",
  "properties": {
    "iso:country":"DE",
    "sg:address":"Vohwinkeler Str. 16",
    "sg:city":"Wuppertal",
    "sg:phone":"+49 202/730438",
    "sg:postcode":"42329",
    "sg:province":"Nordrhein-Westfalen",
    "wof:name":"Brawo",
    "wof:placetype":"venue"
},
  "geometry": {"coordinates":[7.068786,51.230686],"type":"Point"}
}