{
  "type": "Feature",
  "properties": {
    "iso:country":"DE",
    "sg:address":"Maria-Bornheim-Weg 2",
    "sg:city":"Itzehoe",
    "sg:phone":"+49 4821/71001",
    "sg:postcode":"25524",
    "sg:province":"Schleswig-Holstein",
    "wof:name":"Rancherhouse",
    "wof:placetype":"venue"
},
  "geometry": {"coordinates":[9.4995079041,53.9405899048],"type":"Point"}
}