{
  "type": "Feature",
  "properties": {
    "iso:country":"DE",
    "sg:address":"Friesenstr. 45",
    "sg:city":"Oldenburg",
    "sg:phone":"+49 441/8850288",
    "sg:postcode":"26121",
    "sg:province":"Niedersachsen",
    "wof:name":"C. W\u00e4hrer-hoffmeyer",
    "wof:placetype":"venue"
},
  "geometry": {"coordinates":[8.2157840729,53.1583404541],"type":"Point"}
}