{
  "type": "Feature",
  "properties": {
    "iso:country":"DE",
    "sg:address":"Brockh\u00e4ger Str. 25",
    "sg:city":"G\u00fctersloh",
    "sg:phone":"+49 5241/39940",
    "sg:postcode":"33330",
    "sg:province":"Nordrhein-Westfalen",
    "wof:name":"Dalke-werkstatt Industrie Leistungen Gemein.gesell-",
    "wof:placetype":"venue"
},
  "geometry": {"coordinates":[8.371761322,51.9164123535],"type":"Point"}
}