{
  "type": "Feature",
  "properties": {
    "iso:country":"DE",
    "sg:address":"Pfarrgasse 7",
    "sg:city":"Altheim",
    "sg:phone":"+49 7371/7247",
    "sg:postcode":"88499",
    "sg:province":"Baden-W\u00fcrttemberg",
    "wof:name":"Dr. Med. H.g. Blersch Arzt F\u00fcr Allgemeinmedizin",
    "wof:placetype":"venue"
},
  "geometry": {"coordinates":[9.44622612,48.1453895569],"type":"Point"}
}