{
  "type": "Feature",
  "properties": {
    "iso:country":"DE",
    "sg:address":"Thol 12",
    "sg:city":"Schleiden",
    "sg:phone":"+49 2485/1670",
    "sg:postcode":"53937",
    "sg:province":"Nordrhein-Westfalen",
    "wof:name":"M. Heinen",
    "wof:placetype":"venue"
},
  "geometry": {"coordinates":[6.3994698524,50.5407714844],"type":"Point"}
}