{
  "type": "Feature",
  "properties": {
    "iso:country":"DE",
    "sg:address":"S\u00f6renbergweg 10",
    "sg:city":"Waiblingen",
    "sg:phone":"+49 7151/83992",
    "sg:postcode":"71336",
    "sg:province":"Baden-W\u00fcrttemberg",
    "wof:name":"Albeck",
    "wof:placetype":"venue"
},
  "geometry": {"coordinates":[9.327296,48.849503],"type":"Point"}
}