{
  "type": "Feature",
  "properties": {
    "iso:country":"DE",
    "sg:address":"Geleitsstr. 39",
    "sg:city":"Offenbach",
    "sg:postcode":"63065",
    "sg:province":"Hessen",
    "wof:name":"Alen Zorca Bauservice Gmbh",
    "wof:placetype":"venue"
},
  "geometry": {"coordinates":[8.760866,50.103088],"type":"Point"}
}