{
  "type": "Feature",
  "properties": {
    "iso:country":"DE",
    "sg:address":"Heimsheimer Str 31",
    "sg:city":"Renningen",
    "sg:phone":"+49 8064/90690",
    "sg:postcode":"71272",
    "sg:province":"Baden-W\u00fcrttemberg",
    "wof:name":"Sebastian Bacher Gmbh",
    "wof:placetype":"venue"
},
  "geometry": {"coordinates":[11.9858007431,47.7989807129],"type":"Point"}
}