{
  "type": "Feature",
  "properties": {
    "iso:country":"DE",
    "sg:address":"Norbert-Steger-Str. 9",
    "sg:city":"Rotthalm\u00fcnster",
    "sg:phone":"+49 8533/1609",
    "sg:postcode":"94094",
    "sg:province":"Bayern",
    "wof:name":"Dr. Hans Lichtenstern Tierarzt",
    "wof:placetype":"venue"
},
  "geometry": {"coordinates":[13.203502655,48.3575401306],"type":"Point"}
}