{
  "type": "Feature",
  "properties": {
    "iso:country":"DE",
    "sg:address":"Glaubitzer Str. 5",
    "sg:city":"Zeithain",
    "sg:postcode":"01619",
    "sg:province":"Sachsen",
    "wof:name":"Gertig Hartmetallwerkzeuge",
    "wof:placetype":"venue"
},
  "geometry": {"coordinates":[13.33598,51.320881],"type":"Point"}
}