{
  "type": "Feature",
  "properties": {
    "iso:country":"DE",
    "sg:address":"Torkelhalden 6",
    "sg:city":"Markdorf",
    "sg:phone":"+49 7544/72738",
    "sg:postcode":"88677",
    "sg:province":"Baden-W\u00fcrttemberg",
    "wof:name":"Gabriele Rath Heilpraktikerin",
    "wof:placetype":"venue"
},
  "geometry": {"coordinates":[9.4118204117,47.7054290771],"type":"Point"}
}