{
  "type": "Feature",
  "properties": {
    "iso:country":"DE",
    "sg:address":"Jahnstr. 1",
    "sg:city":"L\u00f6bau",
    "sg:phone":"+49 3585/860520",
    "sg:postcode":"02708",
    "sg:province":"Sachsen",
    "wof:name":"Edb Commerce Und Service Hanel & Merkel Ag",
    "wof:placetype":"venue"
},
  "geometry": {"coordinates":[14.6696033478,51.0983123779],"type":"Point"}
}