{
  "type": "Feature",
  "properties": {
    "iso:country":"DE",
    "sg:address":"Bellenstr. 67",
    "sg:city":"Mannheim",
    "sg:phone":"+49 621/818432",
    "sg:postcode":"68163",
    "sg:province":"Baden-W\u00fcrttemberg",
    "wof:name":"Kath. Pfarramt St. Josef",
    "wof:placetype":"venue"
},
  "geometry": {"coordinates":[8.4704780579,49.4734382629],"type":"Point"}
}