{
  "type": "Feature",
  "properties": {
    "iso:country":"DE",
    "sg:address":"Berliner Str. 99",
    "sg:city":"G\u00fctersloh",
    "sg:phone":"+49 5241/14028",
    "sg:postcode":"33330",
    "sg:province":"Nordrhein-Westfalen",
    "wof:name":"Marianne Brune Handarbeiten",
    "wof:placetype":"venue"
},
  "geometry": {"coordinates":[8.382158,51.910362],"type":"Point"}
}