{
  "type": "Feature",
  "properties": {
    "iso:country":"DE",
    "sg:address":"Wichmannswiese 1",
    "sg:city":"Sontra",
    "sg:phone":"+49 5653/91322",
    "sg:postcode":"36205",
    "sg:province":"Hessen",
    "wof:name":"Frank Tr\u00e4bing",
    "wof:placetype":"venue"
},
  "geometry": {"coordinates":[9.9424734116,51.0669937134],"type":"Point"}
}