{
  "type": "Feature",
  "properties": {
    "iso:country":"DE",
    "sg:address":"Marktstr. 11",
    "sg:city":"Winnenden",
    "sg:phone":"+49 7195/10300",
    "sg:postcode":"71364",
    "sg:province":"Baden-W\u00fcrttemberg",
    "wof:name":"Pfl\u00fcger Reiseb\u00fcro Und Omnibusverkehr Gmbh",
    "wof:placetype":"venue"
},
  "geometry": {"coordinates":[9.3968791962,48.8770370483],"type":"Point"}
}