{
  "type": "Feature",
  "properties": {
    "iso:country":"DE",
    "sg:address":"B\u00f6rsenstr. 107",
    "sg:city":"Solingen",
    "sg:phone":"+49 212/2471290",
    "sg:postcode":"42657",
    "sg:province":"Nordrhein-Westfalen",
    "wof:name":"Susanne Sch\u00fcttler-schmidt Rechtsanw\u00e4ltin",
    "wof:placetype":"venue"
},
  "geometry": {"coordinates":[7.07062006,51.1401519775],"type":"Point"}
}