{
  "type": "Feature",
  "properties": {
    "iso:country":"DE",
    "sg:address":"Im Winkel 2",
    "sg:city":"Tetenhusen",
    "sg:phone":"+49 4624/8279",
    "sg:postcode":"24817",
    "sg:province":"Schleswig-Holstein",
    "wof:name":"Zimmereibetrieb Markus Fedde Gmbh",
    "wof:placetype":"venue"
},
  "geometry": {"coordinates":[9.4979400635,54.3481216431],"type":"Point"}
}