{
  "type": "Feature",
  "properties": {
    "iso:country":"DE",
    "sg:address":"Monrealer Str. 32",
    "sg:city":"D\u00fcngenheim",
    "sg:phone":"+49 2653/7228",
    "sg:postcode":"56761",
    "sg:province":"Rheinland-Pfalz",
    "wof:name":"Gebr. Br\u00fcck Gmbh",
    "wof:placetype":"venue"
},
  "geometry": {"coordinates":[7.1669478416,50.2613258362],"type":"Point"}
}