{
  "type": "Feature",
  "properties": {
    "iso:country":"DE",
    "sg:address":"Sellerain 8",
    "sg:city":"Kn\u00fcllwald",
    "sg:phone":"+49 5685/641",
    "sg:postcode":"34593",
    "sg:province":"Hessen",
    "wof:name":"Georg Schade",
    "wof:placetype":"venue"
},
  "geometry": {"coordinates":[9.522723,51.040371],"type":"Point"}
}