{
  "type": "Feature",
  "properties": {
    "iso:country":"DE",
    "sg:address":"Steimeler Str. 51",
    "sg:city":"Fluterschen",
    "sg:postcode":"57614",
    "sg:province":"Rheinland-Pfalz",
    "wof:name":"Gevo Baustoff-handelsges. Mbh",
    "wof:placetype":"venue"
},
  "geometry": {"coordinates":[7.629891,50.666924],"type":"Point"}
}