{
  "type": "Feature",
  "properties": {
    "iso:country":"DE",
    "sg:address":"Klagenfurter Ring 2 c",
    "sg:city":"Wiesbaden",
    "sg:phone":"+49 611/807506",
    "sg:postcode":"65187",
    "sg:province":"Hessen",
    "wof:name":"Das Haus Bautr\u00e4ger Gmbh",
    "wof:placetype":"venue"
},
  "geometry": {"coordinates":[8.226814,50.053928],"type":"Point"}
}