{
  "type": "Feature",
  "properties": {
    "iso:country":"DE",
    "sg:address":"Oberscharam 10",
    "sg:city":"Siegsdorf",
    "sg:phone":"+49 8662/9201",
    "sg:postcode":"83313",
    "sg:province":"Bayern",
    "wof:name":"Karl Gessenharter Gmbh",
    "wof:placetype":"venue"
},
  "geometry": {"coordinates":[12.6296491623,47.7974052429],"type":"Point"}
}