{
  "type": "Feature",
  "properties": {
    "iso:country":"DE",
    "sg:address":"Quellenstr. 3",
    "sg:city":"Augsburg",
    "sg:phone":"+49 821/792067",
    "sg:postcode":"86165",
    "sg:province":"Bayern",
    "wof:name":"Triple A Gesellschaft F\u00fcr Verm\u00f6gensmanagement Mbh",
    "wof:placetype":"venue"
},
  "geometry": {"coordinates":[10.9151010513,48.378742218],"type":"Point"}
}