{
  "type": "Feature",
  "properties": {
    "iso:country":"DE",
    "sg:address":"Ladberger Str. 108",
    "sg:city":"Lengerich",
    "sg:phone":"+49 5481/93830",
    "sg:postcode":"49525",
    "sg:province":"Nordrhein-Westfalen",
    "wof:name":"Eberhard Lammers",
    "wof:placetype":"venue"
},
  "geometry": {"coordinates":[7.797588,52.158554],"type":"Point"}
}