{
  "type": "Feature",
  "properties": {
    "iso:country":"DE",
    "sg:address":"Casterfeldstr. 82",
    "sg:city":"Mannheim",
    "sg:phone":"+49 621/853982",
    "sg:postcode":"68199",
    "sg:province":"Baden-W\u00fcrttemberg",
    "wof:name":"Jet-tankstelle",
    "wof:placetype":"venue"
},
  "geometry": {"coordinates":[8.5047073364,49.4479103088],"type":"Point"}
}