{
  "type": "Feature",
  "properties": {
    "iso:country":"DE",
    "sg:address":"Sandweg 38",
    "sg:city":"Frankfurt",
    "sg:phone":"+49 69/439859",
    "sg:postcode":"60316",
    "sg:province":"Hessen",
    "wof:name":"Taverna Samos",
    "wof:placetype":"venue"
},
  "geometry": {"coordinates":[8.6972017288,50.1183738708],"type":"Point"}
}