{
  "type": "Feature",
  "properties": {
    "iso:country":"DE",
    "sg:address":"Tonndeichstr. 39",
    "sg:city":"Wilhelmshaven",
    "sg:phone":"+49 4421/995570",
    "sg:postcode":"26384",
    "sg:province":"Niedersachsen",
    "wof:name":"K\u00f6hler-verlag",
    "wof:placetype":"venue"
},
  "geometry": {"coordinates":[8.1221857071,53.5276298523],"type":"Point"}
}