{
  "type": "Feature",
  "properties": {
    "iso:country":"DE",
    "sg:address":"Hauptstr. 18",
    "sg:city":"Gollenberg",
    "sg:phone":"+49 6782/981136",
    "sg:postcode":"55767",
    "sg:province":"Rheinland-Pfalz",
    "wof:name":"A. Dreyer Tierarzt",
    "wof:placetype":"venue"
},
  "geometry": {"coordinates":[7.1596078873,49.6732292175],"type":"Point"}
}