{
  "type": "Feature",
  "properties": {
    "iso:country":"DE",
    "sg:address":"Opelstr. 14",
    "sg:city":"St. Leon-Rot",
    "sg:phone":"+49 6227/55532",
    "sg:postcode":"68789",
    "sg:province":"Baden-W\u00fcrttemberg",
    "wof:name":"Milch-informationen Rolf Hinken Gmbh",
    "wof:placetype":"venue"
},
  "geometry": {"coordinates":[8.6393690109,49.246055603],"type":"Point"}
}