{
  "type": "Feature",
  "properties": {
    "iso:country":"DE",
    "sg:address":"Rottweg 19",
    "sg:city":"Langg\u00f6ns",
    "sg:phone":"+49 6403/5252",
    "sg:postcode":"35428",
    "sg:province":"Hessen",
    "wof:name":"Renate Tschersich Immobilien Ohg",
    "wof:placetype":"venue"
},
  "geometry": {"coordinates":[8.6689977646,50.4927597046],"type":"Point"}
}