{
  "type": "Feature",
  "properties": {
    "iso:country":"DE",
    "sg:address":"Siedlung Am Wald 22a",
    "sg:city":"Sellin",
    "sg:phone":"+49 4938/3038214",
    "sg:postcode":"18586",
    "sg:province":"Mecklenburg-Vorpommern",
    "wof:name":"Abacus Liegenschaften Gmbh & Co Cliff Hotel Ruegen Kg",
    "wof:placetype":"venue"
},
  "geometry": {"coordinates":[13.708313,54.365768],"type":"Point"}
}