{
  "type": "Feature",
  "properties": {
    "iso:country":"DE",
    "sg:address":"D\u00fcsterm\u00fchlenweg 15",
    "sg:city":"Heek",
    "sg:phone":"+49 2568/96104",
    "sg:postcode":"48619",
    "sg:province":"Nordrhein-Westfalen",
    "wof:name":"Helmich Gmbh",
    "wof:placetype":"venue"
},
  "geometry": {"coordinates":[7.0920348167,52.0981483459],"type":"Point"}
}