{
  "type": "Feature",
  "properties": {
    "iso:country":"DE",
    "sg:address":"Russellstr. 52",
    "sg:city":"Papenburg",
    "sg:phone":"+49 4961/1291",
    "sg:postcode":"26871",
    "sg:province":"Niedersachsen",
    "wof:name":"H. Polle",
    "wof:placetype":"venue"
},
  "geometry": {"coordinates":[7.3972911835,53.0717964172],"type":"Point"}
}