{
  "type": "Feature",
  "properties": {
    "iso:country":"DE",
    "sg:address":"Herderstr. 73",
    "sg:city":"Bremen",
    "sg:phone":"+49 421/7949627",
    "sg:postcode":"28203",
    "sg:province":"Bremen",
    "wof:name":"Pro Sano",
    "wof:placetype":"venue"
},
  "geometry": {"coordinates":[8.82782,53.078537],"type":"Point"}
}