{
  "type": "Feature",
  "properties": {
    "iso:country":"DE",
    "sg:address":"Diepholzer Str. 12",
    "sg:city":"Delmenhorst",
    "sg:phone":"+49 4221/7525",
    "sg:postcode":"27751",
    "sg:province":"Niedersachsen",
    "wof:name":"Rolf Falkenberg Sanit\u00e4r- Heizungs- Und",
    "wof:placetype":"venue"
},
  "geometry": {"coordinates":[8.6665735245,53.0394325256],"type":"Point"}
}