{
  "type": "Feature",
  "properties": {
    "iso:country":"DE",
    "sg:address":"Kemptener Str. 35",
    "sg:city":"Senden",
    "sg:phone":"+49 7307/5365",
    "sg:postcode":"89250",
    "sg:province":"Bayern",
    "wof:name":"Emmi Doms",
    "wof:placetype":"venue"
},
  "geometry": {"coordinates":[10.0465669632,48.3220977783],"type":"Point"}
}