{
  "type": "Feature",
  "properties": {
    "iso:country":"DE",
    "sg:address":"M\u00fchlenweg 16",
    "sg:city":"Handewitt",
    "sg:phone":"+49 4608/1533",
    "sg:postcode":"24983",
    "sg:province":"Schleswig-Holstein",
    "wof:name":"Wolfgang Schindler Ingenieur",
    "wof:placetype":"venue"
},
  "geometry": {"coordinates":[9.2959299088,54.7756118774],"type":"Point"}
}