{
  "type": "Feature",
  "properties": {
    "iso:country":"DE",
    "sg:address":"Silcherstr. 33",
    "sg:city":"Aldingen",
    "sg:phone":"+49 7424/1037",
    "sg:postcode":"78554",
    "sg:province":"Baden-W\u00fcrttemberg",
    "wof:name":"Malergesch\u00e4ft Hans Gehring Gmbh",
    "wof:placetype":"venue"
},
  "geometry": {"coordinates":[8.714226,48.091488],"type":"Point"}
}