{
  "type": "Feature",
  "properties": {
    "iso:country":"DE",
    "sg:address":"Alsterdorfer Str. 27",
    "sg:city":"Hamburg",
    "sg:phone":"+49 40/462438",
    "sg:postcode":"22299",
    "sg:province":"Hamburg",
    "wof:name":"Sauberland Marco Blang",
    "wof:placetype":"venue"
},
  "geometry": {"coordinates":[9.997573,53.595867],"type":"Point"}
}