{
  "type": "Feature",
  "properties": {
    "iso:country":"DE",
    "sg:address":"Hauptstr. 41",
    "sg:city":"Mulda",
    "sg:postcode":"09619",
    "sg:province":"Sachsen",
    "wof:name":"K. Mickan",
    "wof:placetype":"venue"
},
  "geometry": {"coordinates":[13.369374,50.811195],"type":"Point"}
}