{
  "type": "Feature",
  "properties": {
    "iso:country":"DE",
    "sg:address":"Wiesenstr. 72b",
    "sg:city":"D\u00fcsseldorf",
    "sg:phone":"+49 211/310010",
    "sg:postcode":"40549",
    "sg:province":"Nordrhein-Westfalen",
    "wof:name":"Architekten- Und Ingenieur- Gesellschaft Schiel",
    "wof:placetype":"venue"
},
  "geometry": {"coordinates":[6.707646,51.226658],"type":"Point"}
}