{
  "type": "Feature",
  "properties": {
    "iso:country":"DE",
    "sg:address":"Steink\u00fchlerweg 229",
    "sg:city":"Dortmund",
    "sg:phone":"+49 231/435649",
    "sg:postcode":"44263",
    "sg:province":"Nordrhein-Westfalen",
    "wof:name":"Marion Zimmermann",
    "wof:placetype":"venue"
},
  "geometry": {"coordinates":[7.508037,51.495975],"type":"Point"}
}