{
  "type": "Feature",
  "properties": {
    "iso:country":"DE",
    "sg:address":"Kieler Tor 4",
    "sg:city":"Bornh\u00f6ved",
    "sg:phone":"+49 4323/7355",
    "sg:postcode":"24619",
    "sg:province":"Schleswig-Holstein",
    "wof:name":"Manfred Peters",
    "wof:placetype":"venue"
},
  "geometry": {"coordinates":[10.2279043198,54.071521759],"type":"Point"}
}