{
  "type": "Feature",
  "properties": {
    "iso:country":"DE",
    "sg:address":"Erneeweg 64",
    "sg:city":"Dorsten",
    "sg:phone":"+49 2369/202601",
    "sg:postcode":"46286",
    "sg:province":"Nordrhein-Westfalen",
    "wof:name":"Hmp Teleconsult Ag",
    "wof:placetype":"venue"
},
  "geometry": {"coordinates":[7.037279129,51.7363166809],"type":"Point"}
}