{
  "type": "Feature",
  "properties": {
    "iso:country":"DE",
    "sg:address":"Beneckeallee 40",
    "sg:city":"Hannover",
    "sg:postcode":"30419",
    "sg:province":"Niedersachsen",
    "wof:name":"Wohlfahrts-stiftung Firma J. H. Benecke Gmbh",
    "wof:placetype":"venue"
},
  "geometry": {"coordinates":[9.7082099915,52.4234542847],"type":"Point"}
}