{
  "type": "Feature",
  "properties": {
    "iso:country":"DE",
    "sg:address":"Marschnerstieg 5",
    "sg:city":"Hamburg",
    "sg:phone":"+49 40/291554",
    "sg:postcode":"22081",
    "sg:province":"Hamburg",
    "wof:name":"Dr. Berghaus Soft-u. Hardware Entwicklungs- Und",
    "wof:placetype":"venue"
},
  "geometry": {"coordinates":[10.0373840332,53.5754013062],"type":"Point"}
}