{
  "type": "Feature",
  "properties": {
    "iso:country":"DE",
    "sg:address":"Ellwanger Str. 13",
    "sg:city":"Steinhausen",
    "sg:phone":"+49 7358/390",
    "sg:postcode":"88416",
    "sg:province":"Baden-W\u00fcrttemberg",
    "wof:name":"Fritz Birk Gmbh",
    "wof:placetype":"venue"
},
  "geometry": {"coordinates":[9.974845,48.063354],"type":"Point"}
}