{
  "type": "Feature",
  "properties": {
    "iso:country":"DE",
    "sg:address":"Humboldtstr. 12",
    "sg:city":"Beetzendorf",
    "sg:phone":"+49 39000/6161",
    "sg:postcode":"38489",
    "sg:province":"Sachsen-Anhalt",
    "wof:name":"Henning Grothe",
    "wof:placetype":"venue"
},
  "geometry": {"coordinates":[11.086225,52.700016],"type":"Point"}
}