{
  "type": "Feature",
  "properties": {
    "iso:country":"DE",
    "sg:address":"B\u00f6blinger Strasse 44",
    "sg:city":"Stuttgart",
    "sg:phone":"+49 711/6071137",
    "sg:postcode":"70199",
    "sg:province":"Baden-W\u00fcrttemberg",
    "wof:name":"Buch Media",
    "wof:placetype":"venue"
},
  "geometry": {"coordinates":[9.1379003525,48.7532081604],"type":"Point"}
}