{
  "type": "Feature",
  "properties": {
    "iso:country":"DE",
    "sg:address":"Stegelkoppel 11",
    "sg:city":"L\u00fcbeck",
    "sg:phone":"+49 451/51173",
    "sg:postcode":"23560",
    "sg:province":"Schleswig-Holstein",
    "wof:name":"Carsten Grube",
    "wof:placetype":"venue"
},
  "geometry": {"coordinates":[10.636588,53.820602],"type":"Point"}
}