{
  "type": "Feature",
  "properties": {
    "iso:country":"DE",
    "sg:address":"Gangolfstr. /Ecke Maximil",
    "sg:city":"Bonn",
    "sg:phone":"+49 228/7160",
    "sg:postcode":"53111",
    "sg:province":"Nordrhein-Westfalen",
    "wof:name":"Volksbank Bonn Eg",
    "wof:placetype":"venue"
},
  "geometry": {"coordinates":[7.09894,50.73325],"type":"Point"}
}