{
  "type": "Feature",
  "properties": {
    "iso:country":"DE",
    "sg:address":"Max-Eyth Str. 8",
    "sg:city":"Immendingen",
    "sg:phone":"+49 4974/627381",
    "sg:postcode":"78194",
    "sg:province":"Baden-W\u00fcrttemberg",
    "wof:name":"Erma-electronic Gmbh",
    "wof:placetype":"venue"
},
  "geometry": {"coordinates":[8.7269649506,47.945400238],"type":"Point"}
}