{
  "type": "Feature",
  "properties": {
    "iso:country":"DE",
    "sg:address":"Unterer Markt 2",
    "sg:city":"Weiden",
    "sg:phone":"+49 961/7814",
    "sg:postcode":"92637",
    "sg:province":"Bayern",
    "wof:name":"Technik-freizeit-hobby Spielwarenfachgesch\u00e4ft Gmbh",
    "wof:placetype":"venue"
},
  "geometry": {"coordinates":[12.1640138626,49.6754226685],"type":"Point"}
}