{
  "type": "Feature",
  "properties": {
    "iso:country":"DE",
    "sg:address":"Bahnhofstr. 46A",
    "sg:city":"Bordesholm",
    "sg:postcode":"24582",
    "sg:province":"Schleswig-Holstein",
    "wof:name":"Kleine Schritte E. V. G\u00fcnther Braun-oppert",
    "wof:placetype":"venue"
},
  "geometry": {"coordinates":[10.0415382385,54.1730194092],"type":"Point"}
}