{
  "type": "Feature",
  "properties": {
    "iso:country":"DE",
    "sg:address":"Notweg 37",
    "sg:city":"Dortmund",
    "sg:postcode":"44229",
    "sg:province":"Nordrhein-Westfalen",
    "wof:name":"G & E Technik Gesellschaft F\u00fcr Galvano- Und Elektro-",
    "wof:placetype":"venue"
},
  "geometry": {"coordinates":[7.4531989098,51.4619941711],"type":"Point"}
}