{
  "type": "Feature",
  "properties": {
    "iso:country":"DE",
    "sg:address":"Im Sande",
    "sg:city":"Celle",
    "sg:phone":"+49 5141",
    "sg:postcode":"29227",
    "sg:province":"Niedersachsen",
    "wof:name":"Baumschule Meuschel",
    "wof:placetype":"venue"
},
  "geometry": {"coordinates":[10.1302947998,52.607383728],"type":"Point"}
}