{
  "type": "Feature",
  "properties": {
    "iso:country":"DE",
    "sg:address":"Lerchenweg 3-5",
    "sg:city":"Gro\u00dfbottwar",
    "sg:phone":"+49 4971/486081",
    "sg:postcode":"71723",
    "sg:province":"Baden-W\u00fcrttemberg",
    "wof:name":"Schwarzmann Knopffabrik Kunststoffverarbeitung Gmbh",
    "wof:placetype":"venue"
},
  "geometry": {"coordinates":[9.294802,48.996056],"type":"Point"}
}