{
  "type": "Feature",
  "properties": {
    "iso:country":"DE",
    "sg:address":"Treuenbrietzener Stra\u00dfe 45",
    "sg:city":"Jueterbog",
    "sg:phone":"+49 3372/41810",
    "sg:postcode":"14913",
    "sg:province":"Brandenburg",
    "wof:name":"Rbs-elektroinstallation Gmbh",
    "wof:placetype":"venue"
},
  "geometry": {"coordinates":[13.0495433807,51.9949913025],"type":"Point"}
}