{
  "type": "Feature",
  "properties": {
    "iso:country":"DE",
    "sg:address":"Kronacher Str. 5 b",
    "sg:city":"Wei\u00dfenbrunn",
    "sg:phone":"+49 9261/91589",
    "sg:postcode":"96369",
    "sg:province":"Bayern",
    "wof:name":"Diakoniestation",
    "wof:placetype":"venue"
},
  "geometry": {"coordinates":[11.343471,50.20232],"type":"Point"}
}