{
  "type": "Feature",
  "properties": {
    "iso:country":"DE",
    "sg:address":"Ruhrorter Str. 16 f",
    "sg:city":"Duisburg",
    "sg:phone":"+49 203/311975",
    "sg:postcode":"47059",
    "sg:province":"Nordrhein-Westfalen",
    "wof:name":"Hennemann Spedition Und Brennstoffhandel Gmbh",
    "wof:placetype":"venue"
},
  "geometry": {"coordinates":[6.727775,51.432819],"type":"Point"}
}