{
  "type": "Feature",
  "properties": {
    "iso:country":"DE",
    "sg:address":"Kohlstatt 7",
    "sg:city":"St. Leonhard in Passeier",
    "sg:phone":"+49 3904/73656117",
    "sg:postcode":"39015",
    "wof:name":"Hotel Gasthof Tirolerhof St.leonhard Im Passeier",
    "wof:placetype":"venue"
},
  "geometry": {"coordinates":[11.2469520569,46.8119735718],"type":"Point"}
}