{
  "type": "Feature",
  "properties": {
    "iso:country":"DE",
    "sg:address":"Geschwister-Scholl-Str. 1",
    "sg:city":"Meerane",
    "sg:phone":"+49 3764/796428",
    "sg:postcode":"08393",
    "sg:province":"Sachsen",
    "wof:name":"Koncept Gmbh",
    "wof:placetype":"venue"
},
  "geometry": {"coordinates":[12.456174,50.852535],"type":"Point"}
}