{
  "type": "Feature",
  "properties": {
    "iso:country":"DE",
    "sg:address":"Zugspitzstr. 15",
    "sg:city":"H\u00f6llriegelskreuth",
    "sg:postcode":"82049",
    "sg:province":"Bayern",
    "wof:name":"Schoeller International Holding Gmbh",
    "wof:placetype":"venue"
},
  "geometry": {"coordinates":[11.523288,48.05637],"type":"Point"}
}