{
  "type": "Feature",
  "properties": {
    "iso:country":"DE",
    "sg:address":"Schornhofstr. 8",
    "sg:city":"Neukirchen",
    "sg:phone":"+49 6694/1623",
    "sg:postcode":"34626",
    "sg:province":"Hessen",
    "wof:name":"Heinrich Pr\u00fcssing Nachfolger Stahl- Und Metallbau- Gmbh",
    "wof:placetype":"venue"
},
  "geometry": {"coordinates":[9.393255,50.877785],"type":"Point"}
}