{
  "type": "Feature",
  "properties": {
    "iso:country":"DE",
    "sg:address":"Am D\u00f6rdelmannshof 28",
    "sg:city":"Gelsenkirchen",
    "sg:phone":"+49 209/274466",
    "sg:postcode":"45886",
    "sg:province":"Nordrhein-Westfalen",
    "wof:name":"Kfz-reparaturen, Kunststoff, Glasfaser,",
    "wof:placetype":"venue"
},
  "geometry": {"coordinates":[7.128709,51.492638],"type":"Point"}
}