{
  "type": "Feature",
  "properties": {
    "iso:country":"DE",
    "sg:address":"Schillerstr. 31",
    "sg:city":"Radeberg",
    "sg:phone":"+49 3528/443619",
    "sg:postcode":"01454",
    "sg:province":"Sachsen",
    "wof:name":"Peter Eisold",
    "wof:placetype":"venue"
},
  "geometry": {"coordinates":[13.91652,51.107212],"type":"Point"}
}