{
  "type": "Feature",
  "properties": {
    "iso:country":"DE",
    "sg:address":"Bernhard-Nocht-Str. 76",
    "sg:city":"Hamburg",
    "sg:phone":"+49 40/31908535",
    "sg:postcode":"20359",
    "sg:province":"Hamburg",
    "wof:name":"Redaktion Der Wetterlotse Deutscher Wetterdienst",
    "wof:placetype":"venue"
},
  "geometry": {"coordinates":[9.9662923813,53.5469169617],"type":"Point"}
}