{
  "type": "Feature",
  "properties": {
    "iso:country":"DE",
    "sg:address":"Oberkircher Str. 18",
    "sg:city":"Renchen",
    "sg:phone":"+49 7843/420",
    "sg:postcode":"77871",
    "sg:province":"Baden-W\u00fcrttemberg",
    "wof:name":"Restaurant Am Gem\u00fctlichen Eck",
    "wof:placetype":"venue"
},
  "geometry": {"coordinates":[8.0498886108,48.5791702271],"type":"Point"}
}