{
  "type": "Feature",
  "properties": {
    "iso:country":"DE",
    "sg:address":"Ulzburger Str. 64",
    "sg:city":"Norderstedt",
    "sg:phone":"+49 40/5253049",
    "sg:postcode":"22850",
    "sg:province":"Schleswig-Holstein",
    "wof:name":"Werner Hartmann",
    "wof:placetype":"venue"
},
  "geometry": {"coordinates":[9.9973526001,53.6885452271],"type":"Point"}
}