{
  "type": "Feature",
  "properties": {
    "iso:country":"DE",
    "sg:address":"Fischerhalde 86",
    "sg:city":"Breisach",
    "sg:phone":"+49 7667/1415",
    "sg:postcode":"79206",
    "sg:province":"Baden-W\u00fcrttemberg",
    "wof:name":"K.d. Wistup",
    "wof:placetype":"venue"
},
  "geometry": {"coordinates":[7.5753750801,48.0322532654],"type":"Point"}
}