{
  "type": "Feature",
  "properties": {
    "iso:country":"DE",
    "sg:address":"Dei\u00dflinger Str. 1",
    "sg:city":"Dauchingen",
    "sg:phone":"+49 7720/61410",
    "sg:postcode":"78083",
    "sg:province":"Baden-W\u00fcrttemberg",
    "wof:name":"Redaktion Dauchinger Anzeiger B\u00fcrgermeisteramt",
    "wof:placetype":"venue"
},
  "geometry": {"coordinates":[8.5554428101,48.0916175842],"type":"Point"}
}