{
  "type": "Feature",
  "properties": {
    "iso:country":"DE",
    "sg:address":"K\u00e4the-Kollwitz-Weg 6",
    "sg:city":"Plochingen",
    "sg:phone":"+49 7153/75360",
    "sg:postcode":"73207",
    "sg:province":"Baden-W\u00fcrttemberg",
    "wof:name":"B. Hartmann & P. Boerner Gbr",
    "wof:placetype":"venue"
},
  "geometry": {"coordinates":[9.4333457947,48.7085151672],"type":"Point"}
}