{
  "type": "Feature",
  "properties": {
    "iso:country":"DE",
    "sg:address":"Postfach 1252",
    "sg:city":"Asbach",
    "sg:postcode":"53564",
    "sg:province":"Baden-W\u00fcrttemberg",
    "wof:name":"Hans-peter Frings Gmbh",
    "wof:placetype":"venue"
},
  "geometry": {"coordinates":[7.4258451462,50.6660194397],"type":"Point"}
}