{
  "type": "Feature",
  "properties": {
    "iso:country":"DE",
    "sg:address":"H\u00fcl\u00dfestr. 15",
    "sg:city":"Dresden",
    "sg:postcode":"01237",
    "sg:province":"Sachsen",
    "wof:name":"Aer Immobilien Gmbh",
    "wof:placetype":"venue"
},
  "geometry": {"coordinates":[13.793221,51.011971],"type":"Point"}
}