{
  "type": "Feature",
  "properties": {
    "iso:country":"DE",
    "sg:address":"Dreyer Ecke 14",
    "sg:city":"Enger",
    "sg:phone":"+49 5224/2514",
    "sg:postcode":"32130",
    "sg:province":"Nordrhein-Westfalen",
    "wof:name":"Mowa",
    "wof:placetype":"venue"
},
  "geometry": {"coordinates":[8.513521,52.153515],"type":"Point"}
}