{
  "type": "Feature",
  "properties": {
    "iso:country":"DE",
    "sg:address":"Luxemburger Str. 256",
    "sg:city":"K\u00f6ln",
    "sg:phone":"+49 221/412389",
    "sg:postcode":"50937",
    "sg:province":"Nordrhein-Westfalen",
    "wof:name":"Maierhofer",
    "wof:placetype":"venue"
},
  "geometry": {"coordinates":[6.9266781807,50.9153594971],"type":"Point"}
}