{
  "type": "Feature",
  "properties": {
    "iso:country":"DE",
    "sg:address":"Kreuzgasse 11",
    "sg:city":"Regensburg",
    "sg:phone":"+49 941",
    "sg:postcode":"93047",
    "sg:province":"Bayern",
    "wof:name":"Naturlaub - M. Baldauf & R. Mankau Gbr Mbh",
    "wof:placetype":"venue"
},
  "geometry": {"coordinates":[12.0879192352,49.0194511414],"type":"Point"}
}