{
  "type": "Feature",
  "properties": {
    "iso:country":"DE",
    "sg:address":"Hillebachstr. 23",
    "sg:city":"Eimen",
    "sg:phone":"+49 4955/65272",
    "sg:postcode":"37632",
    "sg:province":"Niedersachsen",
    "wof:name":"S\u00c4gewerk Sauthof Gmbh",
    "wof:placetype":"venue"
},
  "geometry": {"coordinates":[9.7850389481,51.877204895],"type":"Point"}
}