{
  "type": "Feature",
  "properties": {
    "iso:country":"DE",
    "sg:address":"Neuer Weg 22/23",
    "sg:city":"Quedlinburg",
    "sg:phone":"+49 3946/915377",
    "sg:postcode":"06484",
    "sg:province":"Sachsen-Anhalt",
    "wof:name":"Bwc Betrieb-wirtschafts- Consults Gmbh",
    "wof:placetype":"venue"
},
  "geometry": {"coordinates":[11.1425123215,51.7844696045],"type":"Point"}
}