{
  "type": "Feature",
  "properties": {
    "iso:country":"DE",
    "sg:address":"Kleinbettlingerstr. 12",
    "sg:city":"Bempflingen",
    "sg:phone":"+49 7123",
    "sg:postcode":"72658",
    "sg:province":"Baden-W\u00fcrttemberg",
    "wof:name":"Hf-montagebetrieb",
    "wof:placetype":"venue"
},
  "geometry": {"coordinates":[9.2717552185,48.5708236694],"type":"Point"}
}