{
  "type": "Feature",
  "properties": {
    "iso:country":"DE",
    "sg:address":"Sch\u00f6ne Aussicht 1",
    "sg:city":"Zella-Mehlis",
    "sg:phone":"+49 3682/46269",
    "sg:postcode":"98544",
    "sg:province":"Th\u00fcringen",
    "wof:name":"Automarkt Gmbh & Co. Handels Kg S\u00fcdth\u00fcringen",
    "wof:placetype":"venue"
},
  "geometry": {"coordinates":[10.6753158569,50.6471481323],"type":"Point"}
}