{
  "type": "Feature",
  "properties": {
    "iso:country":"DE",
    "sg:address":"Alt-Kladow 13",
    "sg:city":"Berlin",
    "sg:phone":"+49 30/3657352",
    "sg:postcode":"14089",
    "sg:province":"Berlin",
    "wof:name":"Coiffeur Creativ Inh. Roswitha Kurzweg",
    "wof:placetype":"venue"
},
  "geometry": {"coordinates":[13.1450471878,52.4525413513],"type":"Point"}
}