{
  "type": "Feature",
  "properties": {
    "iso:country":"DE",
    "sg:address":"Kehrweeder 10",
    "sg:city":"Hamburg",
    "sg:phone":"+49 40/414410",
    "sg:postcode":"20457",
    "sg:province":"Hamburg",
    "wof:name":"Lowelintas Und Partner",
    "wof:placetype":"venue"
},
  "geometry": {"coordinates":[9.984828,53.543556],"type":"Point"}
}