{
  "type": "Feature",
  "properties": {
    "iso:country":"DE",
    "sg:address":"K\u00fcppelsteiner Str. 18-20",
    "sg:city":"Remscheid",
    "sg:phone":"+49 4921/9197040",
    "sg:postcode":"42857",
    "sg:province":"Nordrhein-Westfalen",
    "wof:name":"Schumacher Gmbh & Co. Kg",
    "wof:placetype":"venue"
},
  "geometry": {"coordinates":[7.15129,51.160786],"type":"Point"}
}