{
  "type": "Feature",
  "properties": {
    "iso:country":"DE",
    "sg:address":"Weiler Str. 7-2",
    "sg:city":"Ebersbach",
    "sg:phone":"+49 7163/909800",
    "sg:postcode":"73061",
    "sg:province":"Baden-W\u00fcrttemberg",
    "wof:name":"G-h-s Consult E. K.",
    "wof:placetype":"venue"
},
  "geometry": {"coordinates":[9.5285,48.713268],"type":"Point"}
}