{
  "type": "Feature",
  "properties": {
    "iso:country":"DE",
    "sg:address":"M\u00fcgelner Str 18",
    "sg:city":"Dresden",
    "sg:phone":"+49 351/282850",
    "sg:postcode":"01237",
    "sg:province":"Sachsen",
    "wof:name":"Formgu\u00df Dresden Gmbh",
    "wof:placetype":"venue"
},
  "geometry": {"coordinates":[13.801727,51.012054],"type":"Point"}
}