{
  "type": "Feature",
  "properties": {
    "iso:country":"DE",
    "sg:address":"Camburger Str 4",
    "sg:city":"Erfurt",
    "sg:phone":"+49 361/750570",
    "sg:postcode":"99091",
    "sg:province":"Th\u00fcringen",
    "wof:name":"Rgs Technischer Service Gmbh",
    "wof:placetype":"venue"
},
  "geometry": {"coordinates":[11.002504,51.017521],"type":"Point"}
}