{
  "type": "Feature",
  "properties": {
    "iso:country":"DE",
    "sg:address":"L\u00fchbergstr. 44",
    "sg:city":"Blankenheim",
    "sg:phone":"+49 2449/8390",
    "sg:postcode":"53945",
    "sg:province":"Nordrhein-Westfalen",
    "wof:name":"Alfred Schmuck",
    "wof:placetype":"venue"
},
  "geometry": {"coordinates":[6.648992,50.43531],"type":"Point"}
}