{
  "type": "Feature",
  "properties": {
    "iso:country":"DE",
    "sg:address":"Hengelerstr. 4",
    "sg:city":"Bernau",
    "sg:phone":"+49 8051/7025",
    "sg:postcode":"83233",
    "sg:province":"Bayern",
    "wof:name":"Dieter Harlander",
    "wof:placetype":"venue"
},
  "geometry": {"coordinates":[12.3737649918,47.8140678406],"type":"Point"}
}