{
  "type": "Feature",
  "properties": {
    "iso:country":"DE",
    "sg:address":"Wendelsteinstr. 1",
    "sg:city":"Dorfen",
    "sg:phone":"+49 8081/745",
    "sg:postcode":"84405",
    "sg:province":"Bayern",
    "wof:name":"Richard Weber",
    "wof:placetype":"venue"
},
  "geometry": {"coordinates":[12.1457233429,48.2689628601],"type":"Point"}
}