{
  "type": "Feature",
  "properties": {
    "iso:country":"DE",
    "sg:address":"D\u00f6rpeder Mark 9",
    "sg:city":"Marsberg",
    "sg:phone":"+49 4929/949222",
    "sg:postcode":"34431",
    "sg:province":"Nordrhein-Westfalen",
    "wof:name":"V\u00d6lkers Metallbearbeitung Gmbh & Co Kg",
    "wof:placetype":"venue"
},
  "geometry": {"coordinates":[8.920992,51.496906],"type":"Point"}
}