{
  "type": "Feature",
  "properties": {
    "iso:country":"DE",
    "sg:address":"Boschstr. 25",
    "sg:city":"Straubing",
    "sg:phone":"+49 9421/913392",
    "sg:postcode":"94315",
    "sg:province":"Bayern",
    "wof:name":"Ihs Industrieprodukte Handels- Und Service Gmbh",
    "wof:placetype":"venue"
},
  "geometry": {"coordinates":[12.581464,48.874828],"type":"Point"}
}