{
  "type": "Feature",
  "properties": {
    "iso:country":"DE",
    "sg:address":"Bahnhofstr. 19",
    "sg:city":"Wetzlar",
    "sg:phone":"+49 6441/94131",
    "sg:postcode":"35576",
    "sg:province":"Hessen",
    "wof:name":"Holz-kretz",
    "wof:placetype":"venue"
},
  "geometry": {"coordinates":[8.502689,50.563065],"type":"Point"}
}