{
  "type": "Feature",
  "properties": {
    "iso:country":"DE",
    "sg:address":"F\u00fcrstenbergerstr. 143",
    "sg:city":"Frankfurt",
    "sg:phone":"+49 69/9596450",
    "sg:postcode":"60322",
    "sg:province":"Hessen",
    "wof:name":"Kressin Und Heinbuch Rechtsanw\u00e4lte",
    "wof:placetype":"venue"
},
  "geometry": {"coordinates":[8.6761827469,50.1250267029],"type":"Point"}
}