{
  "type": "Feature",
  "properties": {
    "iso:country":"DE",
    "sg:address":"Adelheidstr. 32",
    "sg:city":"Friedrichshafen",
    "sg:phone":"+49 7541/71027",
    "sg:postcode":"88046",
    "sg:province":"Baden-W\u00fcrttemberg",
    "wof:name":"Blank Gmbh & Co. Kg",
    "wof:placetype":"venue"
},
  "geometry": {"coordinates":[9.50443,47.662487],"type":"Point"}
}