{
  "type": "Feature",
  "properties": {
    "iso:country":"DE",
    "sg:address":"R\u00fcdigerstr. 3",
    "sg:city":"W\u00fcrzburg",
    "sg:phone":"+49 931/3531300",
    "sg:postcode":"97070",
    "sg:province":"Bayern",
    "wof:name":"Autovermietung Hasenwinkel",
    "wof:placetype":"venue"
},
  "geometry": {"coordinates":[9.938162,49.795742],"type":"Point"}
}