{
  "type": "Feature",
  "properties": {
    "iso:country":"DE",
    "sg:address":"Bannwaldallee 40",
    "sg:city":"Karlsruhe",
    "sg:phone":"+49 721/559950",
    "sg:postcode":"76185",
    "sg:province":"Baden-W\u00fcrttemberg",
    "wof:name":"Feldmann Beteiligungs Gmbh",
    "wof:placetype":"venue"
},
  "geometry": {"coordinates":[8.369095,48.999821],"type":"Point"}
}