{
  "type": "Feature",
  "properties": {
    "iso:country":"DE",
    "sg:address":"Rosenheimer Str. 187",
    "sg:city":"M\u00fcnchen",
    "sg:phone":"+49 89/400206",
    "sg:postcode":"81671",
    "sg:province":"Bayern",
    "wof:name":"Anton Und Rosemarie Lochner",
    "wof:placetype":"venue"
},
  "geometry": {"coordinates":[11.6109828949,48.1177635193],"type":"Point"}
}