{
  "type": "Feature",
  "properties": {
    "iso:country":"DE",
    "sg:address":"Landstr. 30",
    "sg:city":"Kutenholz",
    "sg:phone":"+49 4762/1489",
    "sg:postcode":"27449",
    "sg:province":"Niedersachsen",
    "wof:name":"J. Wegner",
    "wof:placetype":"venue"
},
  "geometry": {"coordinates":[9.36266,53.464489],"type":"Point"}
}