{
  "type": "Feature",
  "properties": {
    "iso:country":"DE",
    "sg:address":"Kramerplatz 01",
    "sg:city":"Naumburg",
    "sg:phone":"+49 3445/202044",
    "sg:postcode":"06618",
    "sg:province":"Sachsen-Anhalt",
    "wof:name":"Stadtarchiv",
    "wof:placetype":"venue"
},
  "geometry": {"coordinates":[11.805413,51.151039],"type":"Point"}
}