{
  "type": "Feature",
  "properties": {
    "iso:country":"DE",
    "sg:address":"Am Unterbarmer Friedhof 53",
    "sg:city":"Wuppertal",
    "sg:phone":"+49 202/84432",
    "sg:postcode":"42285",
    "sg:province":"Nordrhein-Westfalen",
    "wof:name":"Am Schlo\u00dfeck",
    "wof:placetype":"venue"
},
  "geometry": {"coordinates":[7.1767802238,51.259513855],"type":"Point"}
}