{
  "type": "Feature",
  "properties": {
    "iso:country":"DE",
    "sg:address":"Beethovenstr. 13",
    "sg:city":"K\u00f6ln",
    "sg:phone":"+49 221/486082",
    "sg:postcode":"50858",
    "sg:province":"Nordrhein-Westfalen",
    "wof:name":"Peter Prochazka Architekt",
    "wof:placetype":"venue"
},
  "geometry": {"coordinates":[6.85015,50.930325],"type":"Point"}
}