{
  "type": "Feature",
  "properties": {
    "iso:country":"DE",
    "sg:address":"Bernsteindreherweg 7",
    "sg:city":"L\u00fcbeck",
    "sg:phone":"+49 451/873400",
    "sg:postcode":"23556",
    "sg:province":"Schleswig-Holstein",
    "wof:name":"Hbb Hanseatische Bau Gmbh Gesellschaft F\u00fcr Senioren-",
    "wof:placetype":"venue"
},
  "geometry": {"coordinates":[10.6154594421,53.8692817688],"type":"Point"}
}