{
  "type": "Feature",
  "properties": {
    "iso:country":"DE",
    "sg:address":"Stra\u00dfburger Str. 34",
    "sg:city":"Chemnitz",
    "sg:phone":"+49 371/5308662",
    "sg:postcode":"09120",
    "sg:province":"Sachsen",
    "wof:name":"City Druckerei Gmbh",
    "wof:placetype":"venue"
},
  "geometry": {"coordinates":[12.9091377258,50.816192627],"type":"Point"}
}