{
  "type": "Feature",
  "properties": {
    "iso:country":"DE",
    "sg:address":"Daimlerstr. 18",
    "sg:city":"Frittlingen",
    "sg:phone":"+49 7426/940050",
    "sg:postcode":"78665",
    "sg:province":"Baden-W\u00fcrttemberg",
    "wof:name":"Wenzler Medizintechnik Gmbh",
    "wof:placetype":"venue"
},
  "geometry": {"coordinates":[8.7004518509,48.1297531128],"type":"Point"}
}