{
  "type": "Feature",
  "properties": {
    "iso:country":"DE",
    "sg:address":"Hauptstr. 12",
    "sg:city":"Seelbach",
    "sg:phone":"+49 7823/2241",
    "sg:postcode":"77960",
    "sg:province":"Baden-W\u00fcrttemberg",
    "wof:name":"Engel",
    "wof:placetype":"venue"
},
  "geometry": {"coordinates":[7.9409098625,48.310836792],"type":"Point"}
}