{
  "type": "Feature",
  "properties": {
    "iso:country":"DE",
    "sg:address":"Allee 4",
    "sg:city":"Stolzenau",
    "sg:postcode":"31592",
    "sg:province":"Niedersachsen",
    "wof:name":"Immobilien Development Und Beteiligungsges. Nieders. Mbh",
    "wof:placetype":"venue"
},
  "geometry": {"coordinates":[9.076859,52.512852],"type":"Point"}
}