{
  "type": "Feature",
  "properties": {
    "iso:country":"DE",
    "sg:address":"Kapit\u00e4n-Dallmann-Str. 2",
    "sg:city":"Bremen",
    "sg:phone":"+49 421/602684",
    "sg:postcode":"28779",
    "sg:province":"Bremen",
    "wof:name":"Schleckerparadies",
    "wof:placetype":"venue"
},
  "geometry": {"coordinates":[8.5722560883,53.1821289062],"type":"Point"}
}