{
  "type": "Feature",
  "properties": {
    "iso:country":"DE",
    "sg:address":"Rathausstr. 1",
    "sg:city":"Oerlinghausen",
    "sg:phone":"+49 5202/6487",
    "sg:postcode":"33813",
    "sg:province":"Nordrhein-Westfalen",
    "wof:name":"Ratsst\u00fcbchen",
    "wof:placetype":"venue"
},
  "geometry": {"coordinates":[8.6648588181,51.9595603943],"type":"Point"}
}