{
  "type": "Feature",
  "properties": {
    "iso:country":"DE",
    "sg:address":"Senner Hellweg 66",
    "sg:city":"Bielefeld",
    "sg:phone":"+49 521/492751",
    "sg:postcode":"33659",
    "sg:province":"Nordrhein-Westfalen",
    "wof:name":"Walter Cordbarlag",
    "wof:placetype":"venue"
},
  "geometry": {"coordinates":[8.5560846329,51.972618103],"type":"Point"}
}