{
  "type": "Feature",
  "properties": {
    "iso:country":"DE",
    "sg:address":"Enzheimer Str. 6",
    "sg:city":"Gundersheim",
    "sg:phone":"+49 6244/284",
    "sg:postcode":"67598",
    "sg:province":"Rheinland-Pfalz",
    "wof:name":"Hansfried Hangen",
    "wof:placetype":"venue"
},
  "geometry": {"coordinates":[8.200712204,49.6950721741],"type":"Point"}
}