{
  "type": "Feature",
  "properties": {
    "iso:country":"DE",
    "sg:address":"Hohenhausgasse 7",
    "sg:city":"Konstanz",
    "sg:phone":"+49 7531/25404",
    "sg:postcode":"78462",
    "sg:province":"Baden-W\u00fcrttemberg",
    "wof:name":"Elpida Lapatopulu",
    "wof:placetype":"venue"
},
  "geometry": {"coordinates":[9.1749267578,47.6615905762],"type":"Point"}
}