{
  "type": "Feature",
  "properties": {
    "iso:country":"DE",
    "sg:address":"Hundsboden 26",
    "sg:city":"Egloffstein",
    "sg:phone":"+49 9197/1515",
    "sg:postcode":"91349",
    "sg:province":"Bayern",
    "wof:name":"Johannes Meixner Architekt",
    "wof:placetype":"venue"
},
  "geometry": {"coordinates":[11.214869,49.710011],"type":"Point"}
}