{
  "type": "Feature",
  "properties": {
    "iso:country":"DE",
    "sg:address":"Albrechtstr. 70",
    "sg:city":"Berlin",
    "sg:postcode":"12167",
    "sg:province":"Berlin",
    "wof:name":"Mode Blitz Ohg",
    "wof:placetype":"venue"
},
  "geometry": {"coordinates":[13.342269,52.447216],"type":"Point"}
}