{
  "type": "Feature",
  "properties": {
    "iso:country":"DE",
    "sg:address":"S\u00fcdstra\u00dfe 14",
    "sg:city":"Busenberg",
    "sg:phone":"+49 6391/993112",
    "sg:postcode":"76891",
    "sg:province":"Rheinland-Pfalz",
    "wof:name":"Pensionen Und Ferienwohnungen Im Dahner Felsenland.",
    "wof:placetype":"venue"
},
  "geometry": {"coordinates":[7.8225340843,49.1294593811],"type":"Point"}
}