{
  "type": "Feature",
  "properties": {
    "iso:country":"DE",
    "sg:address":"Schwanenstieg 9",
    "sg:city":"Konstanz",
    "sg:postcode":"78465",
    "sg:province":"Baden-W\u00fcrttemberg",
    "wof:name":"Glk - Grundst\u00fccksgesellschaft Liebigstr. Kiel Mbh",
    "wof:placetype":"venue"
},
  "geometry": {"coordinates":[9.179573,47.714832],"type":"Point"}
}