{
  "type": "Feature",
  "properties": {
    "iso:country":"DE",
    "sg:address":"Himmelgeister Landstr. 138",
    "sg:city":"D\u00fcsseldorf",
    "sg:phone":"+49 211/7052020",
    "sg:postcode":"40589",
    "sg:province":"Nordrhein-Westfalen",
    "wof:name":"Viba Licht-bausysteme Vinnemeier Kg",
    "wof:placetype":"venue"
},
  "geometry": {"coordinates":[6.80251,51.174],"type":"Point"}
}