{
  "type": "Feature",
  "properties": {
    "iso:country":"DE",
    "sg:address":"Philipp-Reis-Str. 7",
    "sg:city":"Heusenstamm",
    "sg:postcode":"63150",
    "sg:province":"Hessen",
    "wof:name":"Advo Plus Gmbh",
    "wof:placetype":"venue"
},
  "geometry": {"coordinates":[8.79813,50.051586],"type":"Point"}
}