{
  "type": "Feature",
  "properties": {
    "iso:country":"DE",
    "sg:address":"Amselring 31",
    "sg:city":"Flintbek",
    "sg:phone":"+49 4347/7531",
    "sg:postcode":"24220",
    "sg:province":"Schleswig-Holstein",
    "wof:name":"Praefcke Ingenieur",
    "wof:placetype":"venue"
},
  "geometry": {"coordinates":[10.075088,54.247578],"type":"Point"}
}