{
  "type": "Feature",
  "properties": {
    "iso:country":"DE",
    "sg:address":"Am Briel 68",
    "sg:city":"Konstanz",
    "sg:phone":"+49 7531/64698",
    "sg:postcode":"78467",
    "sg:province":"Baden-W\u00fcrttemberg",
    "wof:name":"Na So Was",
    "wof:placetype":"venue"
},
  "geometry": {"coordinates":[9.173791,47.677475],"type":"Point"}
}