{
  "type": "Feature",
  "properties": {
    "iso:country":"DE",
    "sg:address":"Alliger Weg 1",
    "sg:city":"Kruft",
    "sg:phone":"+49 2652/92940",
    "sg:postcode":"56642",
    "sg:province":"Rheinland-Pfalz",
    "wof:name":"Erich Lichtenstein Kg",
    "wof:placetype":"venue"
},
  "geometry": {"coordinates":[7.3318109512,50.3890190125],"type":"Point"}
}