{
  "type": "Feature",
  "properties": {
    "iso:country":"DE",
    "sg:address":"Vogesenstr. 26",
    "sg:city":"Dinkelscherben",
    "sg:phone":"+49 8292/2797",
    "sg:postcode":"86424",
    "sg:province":"Bayern",
    "wof:name":"A. Und Sylvia Zott",
    "wof:placetype":"venue"
},
  "geometry": {"coordinates":[10.5944576263,48.3449668884],"type":"Point"}
}