{
  "type": "Feature",
  "properties": {
    "iso:country":"DE",
    "sg:address":"M\u00f6nchsondheimer Str. 1 a",
    "sg:city":"Markt Einersheim",
    "sg:phone":"+49 9326/8819",
    "sg:postcode":"97348",
    "sg:province":"Bayern",
    "wof:name":"R. Milon",
    "wof:placetype":"venue"
},
  "geometry": {"coordinates":[10.29728,49.688332],"type":"Point"}
}