{
  "type": "Feature",
  "properties": {
    "iso:country":"DE",
    "sg:address":"Wiesenbornweg 8",
    "sg:city":"Heusenstamm",
    "sg:postcode":"63150",
    "sg:province":"Hessen",
    "wof:name":"Hans Sattler & Co. Gmbh",
    "wof:placetype":"venue"
},
  "geometry": {"coordinates":[8.8082828522,50.0601997375],"type":"Point"}
}