{
  "type": "Feature",
  "properties": {
    "iso:country":"DE",
    "sg:city":"Murg",
    "sg:phone":"+49 7763/5288",
    "sg:postcode":"79730",
    "sg:province":"Baden-W\u00fcrttemberg",
    "wof:name":"T. Orlando",
    "wof:placetype":"venue"
},
  "geometry": {"coordinates":[8.023525,47.553764],"type":"Point"}
}