{
  "type": "Feature",
  "properties": {
    "iso:country":"DE",
    "sg:address":"Langer Hagen 27",
    "sg:city":"Dedelstorf",
    "sg:phone":"+49 5832/1296",
    "sg:postcode":"29386",
    "sg:province":"Niedersachsen",
    "wof:name":"Gerhard Bock",
    "wof:placetype":"venue"
},
  "geometry": {"coordinates":[10.523866,52.731888],"type":"Point"}
}