{
  "type": "Feature",
  "properties": {
    "iso:country":"DE",
    "sg:address":"Brandstr. 22",
    "sg:city":"Wesel",
    "sg:phone":"+49 281/21616",
    "sg:postcode":"46483",
    "sg:province":"Nordrhein-Westfalen",
    "wof:name":"Restaurant China-peking",
    "wof:placetype":"venue"
},
  "geometry": {"coordinates":[6.6185398102,51.6565933228],"type":"Point"}
}