{
  "type": "Feature",
  "properties": {
    "iso:country":"DE",
    "sg:address":"Waldst\u00fcckerring 13",
    "sg:city":"Bellheim",
    "sg:phone":"+49 7272/2389",
    "sg:postcode":"76756",
    "sg:province":"Rheinland-Pfalz",
    "wof:name":"Schwab",
    "wof:placetype":"venue"
},
  "geometry": {"coordinates":[8.305062,49.197517],"type":"Point"}
}