{
  "type": "Feature",
  "properties": {
    "iso:country":"DE",
    "sg:address":"Im Gaisgraben 1",
    "sg:city":"Staufen",
    "sg:phone":"+49 7633/82911",
    "sg:postcode":"79219",
    "sg:province":"Baden-W\u00fcrttemberg",
    "wof:name":"Billiardstube",
    "wof:placetype":"venue"
},
  "geometry": {"coordinates":[7.7240900993,47.8880882263],"type":"Point"}
}