{
  "type": "Feature",
  "properties": {
    "iso:country":"DE",
    "sg:address":"Am Hafen 7",
    "sg:city":"Butjadingen",
    "sg:phone":"+49 4947/3392200",
    "sg:postcode":"26969",
    "sg:province":"Niedersachsen",
    "wof:name":"Heinrich Haye Gmbh Bauunternehmen",
    "wof:placetype":"venue"
},
  "geometry": {"coordinates":[8.365275,53.572826],"type":"Point"}
}