{
  "type": "Feature",
  "properties": {
    "iso:country":"DE",
    "sg:address":"Heubachgasse 9",
    "sg:city":"Eslarn",
    "sg:phone":"+49 9653/208",
    "sg:postcode":"92693",
    "sg:province":"Bayern",
    "wof:name":"Stahl Gmbh",
    "wof:placetype":"venue"
},
  "geometry": {"coordinates":[12.524436,49.583202],"type":"Point"}
}