{
  "type": "Feature",
  "properties": {
    "iso:country":"DE",
    "sg:address":"Industriestr. 21",
    "sg:city":"Leck",
    "sg:phone":"+49 4662/77373",
    "sg:postcode":"25917",
    "sg:province":"Schleswig-Holstein",
    "wof:name":"Bernd-uwe Paulsen",
    "wof:placetype":"venue"
},
  "geometry": {"coordinates":[8.9820251465,54.7776107788],"type":"Point"}
}