{
  "type": "Feature",
  "properties": {
    "iso:country":"DE",
    "sg:address":"Hauptstr. 35",
    "sg:city":"Sch\u00f6nsee",
    "sg:phone":"+49 9674/91281",
    "sg:postcode":"92539",
    "sg:province":"Bayern",
    "wof:name":"Joy",
    "wof:placetype":"venue"
},
  "geometry": {"coordinates":[12.5461301804,49.5097808838],"type":"Point"}
}