{
  "type": "Feature",
  "properties": {
    "iso:country":"DE",
    "sg:address":"Ernst-Ludwig-Str. 3",
    "sg:city":"Weiterstadt",
    "sg:phone":"+49 6150/15709",
    "sg:postcode":"64331",
    "sg:province":"Hessen",
    "wof:name":"Hess Brot Gmbh",
    "wof:placetype":"venue"
},
  "geometry": {"coordinates":[8.569285,49.914867],"type":"Point"}
}