{
  "type": "Feature",
  "properties": {
    "iso:country":"DE",
    "sg:address":"Bachstr. 24",
    "sg:city":"Bad Neuenahr-Ahrweiler",
    "sg:phone":"+49 2641/27220",
    "sg:postcode":"53474",
    "sg:province":"Rheinland-Pfalz",
    "wof:name":"Simon",
    "wof:placetype":"venue"
},
  "geometry": {"coordinates":[7.17593,50.542919],"type":"Point"}
}