{
  "type": "Feature",
  "properties": {
    "iso:country":"DE",
    "sg:address":"Wiesenstr. 15",
    "sg:city":"Wiesbaden",
    "sg:phone":"+49 611/86841",
    "sg:postcode":"65187",
    "sg:province":"Hessen",
    "wof:name":"E. Andrejew",
    "wof:placetype":"venue"
},
  "geometry": {"coordinates":[8.2273178101,50.0639533997],"type":"Point"}
}