{
  "type": "Feature",
  "properties": {
    "iso:country":"DE",
    "sg:address":"Bochumer Str. 244",
    "sg:city":"Recklinghausen",
    "sg:phone":"+49 2361/62278",
    "sg:postcode":"45661",
    "sg:province":"Nordrhein-Westfalen",
    "wof:name":"Bestattungen J\u00fcngst Havermann E. K.",
    "wof:placetype":"venue"
},
  "geometry": {"coordinates":[7.207926,51.563885],"type":"Point"}
}