{
  "type": "Feature",
  "properties": {
    "iso:country":"DE",
    "sg:address":"Mahdgasse 45",
    "sg:city":"Pfalzgrafenweiler",
    "sg:phone":"+49 7445/6226",
    "sg:postcode":"72285",
    "sg:province":"Baden-W\u00fcrttemberg",
    "wof:name":"Karl Koch",
    "wof:placetype":"venue"
},
  "geometry": {"coordinates":[8.601089,48.538521],"type":"Point"}
}