{
  "type": "Feature",
  "properties": {
    "iso:country":"DE",
    "sg:address":"Bruchstr. 4a",
    "sg:city":"Rees",
    "sg:postcode":"46459",
    "sg:province":"Nordrhein-Westfalen",
    "wof:name":"Bogaard K\u00e4se Gmbh",
    "wof:placetype":"venue"
},
  "geometry": {"coordinates":[6.3942799568,51.8144187927],"type":"Point"}
}