{
  "type": "Feature",
  "properties": {
    "iso:country":"DE",
    "sg:address":"Ludwig-Siebert-Str. 56",
    "sg:city":"Rothenburg",
    "sg:phone":"+49 9861/6222",
    "sg:postcode":"91541",
    "sg:province":"Bayern",
    "wof:name":"Andrea Gerlitz Rechtsanw\u00e4ltin",
    "wof:placetype":"venue"
},
  "geometry": {"coordinates":[10.18708992,49.3798942566],"type":"Point"}
}