{
  "type": "Feature",
  "properties": {
    "iso:country":"DE",
    "sg:address":"Bergstr. 1",
    "sg:city":"Duderstadt",
    "sg:phone":"+49 5527/2611",
    "sg:postcode":"37115",
    "sg:province":"Niedersachsen",
    "wof:name":"Katholisches Pfarramt St. Nikolaus",
    "wof:placetype":"venue"
},
  "geometry": {"coordinates":[10.2443151474,51.5016899109],"type":"Point"}
}