{
  "type": "Feature",
  "properties": {
    "iso:country":"DE",
    "sg:address":"Bantschowstr. 37",
    "sg:city":"Hamburg",
    "sg:phone":"+49 40/5362140",
    "sg:postcode":"22391",
    "sg:province":"Hamburg",
    "wof:name":"Egon Panteleit",
    "wof:placetype":"venue"
},
  "geometry": {"coordinates":[10.062497,53.637707],"type":"Point"}
}