{
  "type": "Feature",
  "properties": {
    "iso:country":"DE",
    "sg:address":"Hallerweg 284",
    "sg:city":"Becherbach/Gangloff",
    "sg:phone":"+49 6364/993165",
    "sg:postcode":"67827",
    "sg:province":"Rheinland-Pfalz",
    "wof:name":"Mo-ton Veranstaltungstechnik",
    "wof:placetype":"venue"
},
  "geometry": {"coordinates":[7.702245,49.664677],"type":"Point"}
}