{
  "type": "Feature",
  "properties": {
    "iso:country":"DE",
    "sg:address":"St\u00f6rtebekerweg 4a",
    "sg:city":"Hamburg",
    "sg:phone":"+49 40/7017818",
    "sg:postcode":"21149",
    "sg:province":"Hamburg",
    "wof:name":"Horst Bartels Schiffahrt-unternehmen",
    "wof:placetype":"venue"
},
  "geometry": {"coordinates":[9.86261,53.469124],"type":"Point"}
}