{
  "type": "Feature",
  "properties": {
    "iso:country":"DE",
    "sg:address":"Herrenstr. 9",
    "sg:city":"Cochem",
    "sg:phone":"+49 2671/97520",
    "sg:postcode":"56812",
    "sg:province":"Rheinland-Pfalz",
    "wof:name":"Sozialberatungsstelle Krs.-caritasverband",
    "wof:placetype":"venue"
},
  "geometry": {"coordinates":[7.166402,50.145061],"type":"Point"}
}