{
  "type": "Feature",
  "properties": {
    "iso:country":"DE",
    "sg:address":"Otto-Hahn-Str. 23",
    "sg:city":"Lohfelden",
    "sg:phone":"+49 4956/1581093",
    "sg:postcode":"34253",
    "sg:province":"Hessen",
    "wof:name":"Geilert & Kanstein Ohg Schrauben & Verbindungselemente",
    "wof:placetype":"venue"
},
  "geometry": {"coordinates":[9.537895,51.283409],"type":"Point"}
}