{
  "type": "Feature",
  "properties": {
    "iso:country":"DE",
    "sg:address":"Schulstr. 63",
    "sg:city":"Merenberg",
    "sg:phone":"+49 6424/964321",
    "sg:postcode":"35799",
    "sg:province":"Hessen",
    "wof:name":"M. Zabel",
    "wof:placetype":"venue"
},
  "geometry": {"coordinates":[8.20563,50.524418],"type":"Point"}
}