{
  "type": "Feature",
  "properties": {
    "iso:country":"DE",
    "sg:address":"Sandgasse 3",
    "sg:city":"Deuna",
    "sg:postcode":"37355",
    "sg:province":"Th\u00fcringen",
    "wof:name":"Katholisches Pfarramt Deuna",
    "wof:placetype":"venue"
},
  "geometry": {"coordinates":[10.4744844437,51.3543319702],"type":"Point"}
}