{
  "type": "Feature",
  "properties": {
    "iso:country":"DE",
    "sg:address":"Jakobstr. 20",
    "sg:city":"Inden",
    "sg:phone":"+49 2465/2414",
    "sg:postcode":"52459",
    "sg:province":"Nordrhein-Westfalen",
    "wof:name":"Heinrich Breuer Parkett-fu\u00dfbodentechnik Gmbh",
    "wof:placetype":"venue"
},
  "geometry": {"coordinates":[6.400698185,50.8615646362],"type":"Point"}
}