{
  "type": "Feature",
  "properties": {
    "iso:country":"DE",
    "sg:address":"Postfach 1123",
    "sg:city":"Versmold",
    "sg:phone":"+49 5423/121",
    "sg:postcode":"33759",
    "sg:province":"Nordrhein-Westfalen",
    "wof:name":"Heinrich Noelke & Co.",
    "wof:placetype":"venue"
},
  "geometry": {"coordinates":[8.1554203033,52.0429000854],"type":"Point"}
}