{
  "type": "Feature",
  "properties": {
    "iso:country":"DE",
    "sg:address":"Brahmkamp 14",
    "sg:city":"Fockbek",
    "sg:phone":"+49 4331/6626066",
    "sg:postcode":"24787",
    "sg:province":"Schleswig-Holstein",
    "wof:name":"Mamo-airbrush-design",
    "wof:placetype":"venue"
},
  "geometry": {"coordinates":[9.59499,54.310566],"type":"Point"}
}