{
  "type": "Feature",
  "properties": {
    "iso:country":"DE",
    "sg:address":"Bih\u00f6ftweg 2",
    "sg:city":"Oster-Ohrstedt",
    "sg:postcode":"25885",
    "sg:province":"Schleswig-Holstein",
    "wof:name":"Windpark Nordahl Gmbh & Co. Kg",
    "wof:placetype":"venue"
},
  "geometry": {"coordinates":[9.236226,54.517391],"type":"Point"}
}