{
  "type": "Feature",
  "properties": {
    "iso:country":"DE",
    "sg:address":"Hauptstr. 7",
    "sg:city":"Burkau",
    "sg:phone":"+49 3594/702444",
    "sg:postcode":"01906",
    "sg:province":"Sachsen",
    "wof:name":"Erbgericht",
    "wof:placetype":"venue"
},
  "geometry": {"coordinates":[14.1466398239,51.1718215942],"type":"Point"}
}