{
  "type": "Feature",
  "properties": {
    "iso:country":"DE",
    "sg:address":"Hornschuchstra\u00dfe 32-36",
    "sg:city":"Wunsiedel",
    "sg:phone":"+49 9232/2047",
    "sg:postcode":"95632",
    "sg:province":"Bayern",
    "wof:name":"Keramik Goller",
    "wof:placetype":"venue"
},
  "geometry": {"coordinates":[12.0116186142,50.0386390686],"type":"Point"}
}