{
  "type": "Feature",
  "properties": {
    "iso:country":"DE",
    "sg:address":"Mittlere Str. 14",
    "sg:city":"Holzminden",
    "sg:phone":"+49 5531/3081",
    "sg:postcode":"37603",
    "sg:province":"Niedersachsen",
    "wof:name":"Betten-becker Marga Becker",
    "wof:placetype":"venue"
},
  "geometry": {"coordinates":[9.448217392,51.8286590576],"type":"Point"}
}