{
  "type": "Feature",
  "properties": {
    "iso:country":"DE",
    "sg:address":"Hackhorststr. 32",
    "sg:city":"Gelsenkirchen",
    "sg:phone":"+49 209/43344",
    "sg:postcode":"45883",
    "sg:province":"Nordrhein-Westfalen",
    "wof:name":"F. Ibach & H. Muss Elektroinstallation",
    "wof:placetype":"venue"
},
  "geometry": {"coordinates":[7.059535,51.526268],"type":"Point"}
}