{
  "type": "Feature",
  "properties": {
    "iso:country":"DE",
    "sg:address":"Tullastr. 73",
    "sg:city":"Freiburg",
    "sg:postcode":"79108",
    "sg:province":"Baden-W\u00fcrttemberg",
    "wof:name":"S\u00fcdfleisch Holding Ag",
    "wof:placetype":"venue"
},
  "geometry": {"coordinates":[7.845307,48.031178],"type":"Point"}
}