{
  "type": "Feature",
  "properties": {
    "iso:country":"DE",
    "sg:address":"Hauptstr. 98",
    "sg:city":"Heiligenhaus",
    "sg:phone":"+49 2056/69590",
    "sg:postcode":"42579",
    "sg:province":"Nordrhein-Westfalen",
    "wof:name":"Schmitz Gmbh",
    "wof:placetype":"venue"
},
  "geometry": {"coordinates":[6.97679,51.327587],"type":"Point"}
}