{
  "type": "Feature",
  "properties": {
    "iso:country":"DE",
    "sg:address":"Schiffbr\u00fccke 39",
    "sg:city":"Flensburg",
    "sg:phone":"+49 461/852970",
    "sg:postcode":"24939",
    "sg:province":"Schleswig-Holstein",
    "wof:name":"Flensburger Schiffahrts- Museum Und Rum-museum",
    "wof:placetype":"venue"
},
  "geometry": {"coordinates":[9.43331,54.793049],"type":"Point"}
}