{
  "type": "Feature",
  "properties": {
    "iso:country":"DE",
    "sg:address":"Kasernenstr. 26",
    "sg:city":"Coburg",
    "sg:phone":"+49 9561/861100",
    "sg:postcode":"96450",
    "sg:province":"Bayern",
    "wof:name":"Tele Com",
    "wof:placetype":"venue"
},
  "geometry": {"coordinates":[10.965456,50.268467],"type":"Point"}
}