{
  "type": "Feature",
  "properties": {
    "iso:country":"DE",
    "sg:address":"S\u00fcdring 46a",
    "sg:city":"Oldenburg",
    "sg:phone":"+49 441/602204",
    "sg:postcode":"26125",
    "sg:province":"Niedersachsen",
    "wof:name":"Hans-j\u00f6rg J\u00fcchter",
    "wof:placetype":"venue"
},
  "geometry": {"coordinates":[8.211964,53.199757],"type":"Point"}
}