{
  "type": "Feature",
  "properties": {
    "iso:country":"DE",
    "sg:address":"Altenmarkter Str. 13",
    "sg:city":"Traunreut",
    "sg:phone":"+49 8669/85630",
    "sg:postcode":"83301",
    "sg:province":"Bayern",
    "wof:name":"Gabriele Liebetruth Steuerberaterin",
    "wof:placetype":"venue"
},
  "geometry": {"coordinates":[12.6076002121,47.9624481201],"type":"Point"}
}