{
  "type": "Feature",
  "properties": {
    "iso:country":"DE",
    "sg:address":"Arndtstr. 43",
    "sg:city":"Berlin",
    "sg:phone":"+49 30/6928285",
    "sg:postcode":"10965",
    "sg:province":"Berlin",
    "wof:name":"Dkv-agentur Robert Haleck - Berlin",
    "wof:placetype":"venue"
},
  "geometry": {"coordinates":[13.396231,52.487988],"type":"Point"}
}