{
  "type": "Feature",
  "properties": {
    "iso:country":"DE",
    "sg:address":"Neustr. 68 A",
    "sg:city":"Erftstadt",
    "sg:phone":"+49 2235/78653",
    "sg:postcode":"50374",
    "sg:province":"Nordrhein-Westfalen",
    "wof:name":"L\u00fcttgen-reisen Gmbh",
    "wof:placetype":"venue"
},
  "geometry": {"coordinates":[6.735804081,50.8377914429],"type":"Point"}
}