{
  "type": "Feature",
  "properties": {
    "iso:country":"DE",
    "sg:address":"Eubaer Str. 105a",
    "sg:city":"Chemnitz",
    "sg:phone":"+49 371/266520",
    "sg:postcode":"09127",
    "sg:province":"Sachsen",
    "wof:name":"J\u00fcrgen Wurdinger Ingenieur",
    "wof:placetype":"venue"
},
  "geometry": {"coordinates":[12.98489,50.832848],"type":"Point"}
}