{
  "type": "Feature",
  "properties": {
    "iso:country":"DE",
    "sg:address":"Waldweg 10 b",
    "sg:city":"M\u00fcnster",
    "sg:phone":"+49 251/717031",
    "sg:postcode":"48163",
    "sg:province":"Nordrhein-Westfalen",
    "wof:name":"Manfred Soiron",
    "wof:placetype":"venue"
},
  "geometry": {"coordinates":[7.5731730461,51.91847229],"type":"Point"}
}