{
  "type": "Feature",
  "properties": {
    "iso:country":"DE",
    "sg:address":"Wagnerfeldweg 6",
    "sg:city":"Bergen",
    "sg:phone":"+49 8662",
    "sg:postcode":"83346",
    "sg:province":"Bayern",
    "wof:name":"Webdesign Breyer",
    "wof:placetype":"venue"
},
  "geometry": {"coordinates":[12.592502594,47.8104324341],"type":"Point"}
}