{
  "type": "Feature",
  "properties": {
    "iso:country":"DE",
    "sg:address":"Woldegker Chaussee 35",
    "sg:city":"Neustrelitz",
    "sg:phone":"+49 3981/481428",
    "sg:postcode":"17235",
    "sg:province":"Mecklenburg-Vorpommern",
    "wof:name":"Kreisarchiv Au\u00dfenstelle Neustrelitz",
    "wof:placetype":"venue"
},
  "geometry": {"coordinates":[13.084864,53.344559],"type":"Point"}
}