{
  "type": "Feature",
  "properties": {
    "iso:country":"DE",
    "sg:address":"Franz-Rueff-Str. 10",
    "sg:city":"Ellwangen",
    "sg:phone":"+49 7961/91400",
    "sg:postcode":"73479",
    "sg:province":"Baden-W\u00fcrttemberg",
    "wof:name":"S & S Qualit\u00e4tsfenster",
    "wof:placetype":"venue"
},
  "geometry": {"coordinates":[10.171718,48.952686],"type":"Point"}
}