{
  "type": "Feature",
  "properties": {
    "iso:country":"DE",
    "sg:address":"Im Kirchtal 25",
    "sg:city":"Troisdorf",
    "sg:phone":"+49 2241/409797",
    "sg:postcode":"53844",
    "sg:province":"Nordrhein-Westfalen",
    "wof:name":"Klaus Kieser",
    "wof:placetype":"venue"
},
  "geometry": {"coordinates":[7.1205859184,50.7951927185],"type":"Point"}
}