{
  "type": "Feature",
  "properties": {
    "iso:country":"DE",
    "sg:address":"Amtsvennweg 78",
    "sg:city":"Gronau",
    "sg:phone":"+49 2562/6569",
    "sg:postcode":"48599",
    "sg:province":"Nordrhein-Westfalen",
    "wof:name":"Leferink",
    "wof:placetype":"venue"
},
  "geometry": {"coordinates":[6.9778051376,52.2058982849],"type":"Point"}
}