{
  "type": "Feature",
  "properties": {
    "iso:country":"DE",
    "sg:address":"Magdalenenh\u00e4user Weg",
    "sg:city":"Wetzlar",
    "sg:phone":"+49 6441/42802",
    "sg:postcode":"35578",
    "sg:province":"Hessen",
    "wof:name":"Otto Ufer Gmbh & Co. Kg",
    "wof:placetype":"venue"
},
  "geometry": {"coordinates":[8.488945961,50.5500183105],"type":"Point"}
}