{
  "type": "Feature",
  "properties": {
    "iso:country":"DE",
    "sg:address":"Stuttgarter Str. 74",
    "sg:city":"Bietigheim-Bissingen",
    "sg:phone":"+49 7142/53766",
    "sg:postcode":"74321",
    "sg:province":"Baden-W\u00fcrttemberg",
    "wof:name":"R.-m. Treiber",
    "wof:placetype":"venue"
},
  "geometry": {"coordinates":[9.13555,48.952023],"type":"Point"}
}