{
  "type": "Feature",
  "properties": {
    "iso:country":"DE",
    "sg:address":"Carl-Koenen-Str.",
    "sg:city":"Euskirchen",
    "sg:phone":"+49 2251/55034",
    "sg:postcode":"53881",
    "sg:province":"Nordrhein-Westfalen",
    "wof:name":"Rheinisches Industriemuseum Au\u00dfenstelle Euskirchen",
    "wof:placetype":"venue"
},
  "geometry": {"coordinates":[6.81998,50.648281],"type":"Point"}
}