{
  "type": "Feature",
  "properties": {
    "iso:country":"DE",
    "sg:address":"Bernsteinweg 5",
    "sg:city":"Darmstadt",
    "sg:phone":"+49 6151/56014",
    "sg:postcode":"64297",
    "sg:province":"Hessen",
    "wof:name":"W. Darmst\u00e4dter Spedition Und Transporte Gmbh",
    "wof:placetype":"venue"
},
  "geometry": {"coordinates":[8.6250705719,49.8200950623],"type":"Point"}
}