{
  "type": "Feature",
  "properties": {
    "iso:country":"DE",
    "sg:address":"Sailersh\u00e4user Str. 2",
    "sg:city":"Theres",
    "sg:phone":"+49 9521/2577",
    "sg:postcode":"97531",
    "sg:province":"Bayern",
    "wof:name":"A. Giebfried",
    "wof:placetype":"venue"
},
  "geometry": {"coordinates":[10.4485645294,50.0177154541],"type":"Point"}
}