{
  "type": "Feature",
  "properties": {
    "iso:country":"DE",
    "sg:address":"Sebastian-Kurtz-Str. 12",
    "sg:city":"St. Ingbert",
    "sg:phone":"+49 6894/36600",
    "sg:postcode":"66386",
    "sg:province":"Saarland",
    "wof:name":"Richard Kr\u00e4mer Architekt",
    "wof:placetype":"venue"
},
  "geometry": {"coordinates":[7.087384,49.262642],"type":"Point"}
}