{
  "type": "Feature",
  "properties": {
    "iso:country":"DE",
    "sg:address":"Gewerbestr. S\u00fcd 20",
    "sg:city":"Erkelenz",
    "sg:phone":"+49 2431/977440",
    "sg:postcode":"41812",
    "sg:province":"Nordrhein-Westfalen",
    "wof:name":"Peter K. Hunz Lichtpaus- Und Zeichentechnik",
    "wof:placetype":"venue"
},
  "geometry": {"coordinates":[6.3045320511,51.0687217712],"type":"Point"}
}