{
  "type": "Feature",
  "properties": {
    "iso:country":"DE",
    "sg:address":"Rennbahnstr. 33",
    "sg:city":"Hamburg",
    "sg:phone":"+49 40/6518044",
    "sg:postcode":"22111",
    "sg:province":"Hamburg",
    "wof:name":"Elektromann Dieter Maurer E. K.",
    "wof:placetype":"venue"
},
  "geometry": {"coordinates":[10.0835561752,53.5543823242],"type":"Point"}
}