{
  "type": "Feature",
  "properties": {
    "iso:country":"DE",
    "sg:address":"M\u00fchlenweg 3",
    "sg:city":"Weisendorf",
    "sg:phone":"+49 9135/981",
    "sg:postcode":"91085",
    "sg:province":"Bayern",
    "wof:name":"Elger Freiherr Von Gagern",
    "wof:placetype":"venue"
},
  "geometry": {"coordinates":[10.8714132309,49.6361465454],"type":"Point"}
}