{
  "type": "Feature",
  "properties": {
    "iso:country":"DE",
    "sg:address":"Feuerbachstr. 12",
    "sg:city":"Leipzig",
    "sg:phone":"+49 341/9808119",
    "sg:postcode":"04105",
    "sg:province":"Sachsen",
    "wof:name":"Stammk\u00f6tter Und Scharlemann Rechtsanw\u00e4lte",
    "wof:placetype":"venue"
},
  "geometry": {"coordinates":[12.3576374054,51.3464126587],"type":"Point"}
}