{
  "type": "Feature",
  "properties": {
    "iso:country":"DE",
    "sg:address":"Kalkstr. 29",
    "sg:city":"Zeitz",
    "sg:phone":"+49 3441/220415",
    "sg:postcode":"06712",
    "sg:province":"Sachsen-Anhalt",
    "wof:name":"Ramona Sch\u00fc\u00dfler Heilpraktikerin",
    "wof:placetype":"venue"
},
  "geometry": {"coordinates":[12.1372203827,51.0482139587],"type":"Point"}
}