{
  "type": "Feature",
  "properties": {
    "iso:country":"DE",
    "sg:address":"Hauptstr. 34",
    "sg:city":"Witten",
    "sg:phone":"+49 2302/56569",
    "sg:postcode":"58452",
    "sg:province":"Nordrhein-Westfalen",
    "wof:name":"Headline Werbung",
    "wof:placetype":"venue"
},
  "geometry": {"coordinates":[7.336132,51.44183],"type":"Point"}
}