{
  "type": "Feature",
  "properties": {
    "iso:country":"DE",
    "sg:address":"Quedlinburger Str. 3",
    "sg:city":"Gernrode",
    "sg:phone":"+49 39485/60784",
    "sg:postcode":"06507",
    "sg:province":"Sachsen-Anhalt",
    "wof:name":"Richard Sufin",
    "wof:placetype":"venue"
},
  "geometry": {"coordinates":[11.153676033,51.732383728],"type":"Point"}
}