{
  "type": "Feature",
  "properties": {
    "iso:country":"DE",
    "sg:address":"Mathiashof 9",
    "sg:city":"Essen",
    "sg:phone":"+49 201/296084",
    "sg:postcode":"45141",
    "sg:province":"Nordrhein-Westfalen",
    "wof:name":"Paul Wildenhues Architekt",
    "wof:placetype":"venue"
},
  "geometry": {"coordinates":[7.032969,51.471867],"type":"Point"}
}