{
  "type": "Feature",
  "properties": {
    "iso:country":"DE",
    "sg:address":"Bischmatt 7",
    "sg:city":"Tunau",
    "sg:phone":"+49 7673/7354",
    "sg:postcode":"79677",
    "sg:province":"Baden-W\u00fcrttemberg",
    "wof:name":"H. Lais",
    "wof:placetype":"venue"
},
  "geometry": {"coordinates":[7.9076929092,47.7837142944],"type":"Point"}
}