{
  "type": "Feature",
  "properties": {
    "iso:country":"DE",
    "sg:address":"Christofstr. 4-6",
    "sg:city":"Kirchheim",
    "sg:phone":"+49 7021/2812",
    "sg:postcode":"73230",
    "sg:province":"Baden-W\u00fcrttemberg",
    "wof:name":"Stempel-walter Kg",
    "wof:placetype":"venue"
},
  "geometry": {"coordinates":[9.455654,48.651497],"type":"Point"}
}