{
  "type": "Feature",
  "properties": {
    "iso:country":"DE",
    "sg:address":"Fuchsweg 68",
    "sg:city":"R\u00f6srath",
    "sg:phone":"+49 2205/6912",
    "sg:postcode":"51503",
    "sg:province":"Nordrhein-Westfalen",
    "wof:name":"K\u00f6hler & K\u00f6hler Ohg",
    "wof:placetype":"venue"
},
  "geometry": {"coordinates":[7.1779398918,50.9156188965],"type":"Point"}
}