{
  "type": "Feature",
  "properties": {
    "iso:country":"DE",
    "sg:address":"Hertelsbrunnenring 20",
    "sg:city":"Kaiserslautern",
    "sg:phone":"+49 631/34230",
    "sg:postcode":"67657",
    "sg:province":"Rheinland-Pfalz",
    "wof:name":"Wsw Bau- Und Erschlie\u00dfungstr\u00e4ger",
    "wof:placetype":"venue"
},
  "geometry": {"coordinates":[7.7886309624,49.4556312561],"type":"Point"}
}