{
  "type": "Feature",
  "properties": {
    "iso:country":"DE",
    "sg:address":"Christophstr. 56",
    "sg:city":"Leinfelden-Echterdingen",
    "sg:phone":"+49 711/7977372",
    "sg:postcode":"70771",
    "sg:province":"Baden-W\u00fcrttemberg",
    "wof:name":"Ert-einkaufsgenossenschaft Reproduktionstechnik E.g.",
    "wof:placetype":"venue"
},
  "geometry": {"coordinates":[9.167466,48.683865],"type":"Point"}
}