{
  "type": "Feature",
  "properties": {
    "iso:country":"DE",
    "sg:address":"Kirschbergweg 9",
    "sg:city":"Halle",
    "sg:postcode":"06120",
    "sg:province":"Sachsen-Anhalt",
    "wof:name":"Dr. Med. Gert.eberhard K\u00fchne",
    "wof:placetype":"venue"
},
  "geometry": {"coordinates":[11.938563,51.50872],"type":"Point"}
}