{
  "type": "Feature",
  "properties": {
    "iso:country":"DE",
    "sg:address":"Grenzweg 25",
    "sg:city":"Herne",
    "sg:phone":"+49 2323/53131",
    "sg:postcode":"44623",
    "sg:province":"Nordrhein-Westfalen",
    "wof:name":"Ks Modellbau Gmbh",
    "wof:placetype":"venue"
},
  "geometry": {"coordinates":[7.208193779,51.5402069092],"type":"Point"}
}