{
  "type": "Feature",
  "properties": {
    "iso:country":"DE",
    "sg:address":"Am Markt 6",
    "sg:city":"Springe",
    "sg:phone":"+49 5041/1497",
    "sg:postcode":"31832",
    "sg:province":"Niedersachsen",
    "wof:name":"Heinrich Iii",
    "wof:placetype":"venue"
},
  "geometry": {"coordinates":[9.5544147491,52.2088050842],"type":"Point"}
}