{
  "type": "Feature",
  "properties": {
    "iso:country":"DE",
    "sg:address":"Hohe Str. 144-146",
    "sg:city":"K\u00f6ln",
    "sg:phone":"+49 221/2581782",
    "sg:postcode":"50667",
    "sg:province":"Nordrhein-Westfalen",
    "wof:name":"A. A. Awacs Detektiv Volker Stein",
    "wof:placetype":"venue"
},
  "geometry": {"coordinates":[6.956548,50.939445],"type":"Point"}
}