{
  "type": "Feature",
  "properties": {
    "iso:country":"DE",
    "sg:address":"Klatterstr. 1",
    "sg:city":"Stolberg",
    "sg:phone":"+49 2402/24723",
    "sg:postcode":"52222",
    "sg:province":"Nordrhein-Westfalen",
    "wof:name":"Gastst\u00e4tte Elfriede Itsou",
    "wof:placetype":"venue"
},
  "geometry": {"coordinates":[6.2330598831,50.7682914734],"type":"Point"}
}