{
  "type": "Feature",
  "properties": {
    "iso:country":"DE",
    "sg:address":"Kirchstr. 25",
    "sg:city":"Leer",
    "sg:phone":"+49 491/2750",
    "sg:postcode":"26789",
    "sg:province":"Niedersachsen",
    "wof:name":"Ev. Pfarramt Lutherkirche",
    "wof:placetype":"venue"
},
  "geometry": {"coordinates":[7.4486761093,53.2279663086],"type":"Point"}
}