{
  "type": "Feature",
  "properties": {
    "iso:country":"DE",
    "sg:address":"K\u00e4the-Kollwitz-Str. 14",
    "sg:city":"Schkeuditz",
    "sg:phone":"+49 34204/64534",
    "sg:postcode":"04435",
    "sg:province":"Sachsen",
    "wof:name":"Lutz Rauhut",
    "wof:placetype":"venue"
},
  "geometry": {"coordinates":[12.2250785828,51.3983154297],"type":"Point"}
}