{
  "type": "Feature",
  "properties": {
    "iso:country":"DE",
    "sg:address":"Bochumer Landstr. 177",
    "sg:city":"Essen",
    "sg:phone":"+49 201/533294",
    "sg:postcode":"45276",
    "sg:province":"Nordrhein-Westfalen",
    "wof:name":"Hugo Bleines",
    "wof:placetype":"venue"
},
  "geometry": {"coordinates":[7.092303,51.447147],"type":"Point"}
}