{
  "type": "Feature",
  "properties": {
    "iso:country":"DE",
    "sg:address":"Vordere Bergstr. 1",
    "sg:city":"Syrgenstein",
    "sg:phone":"+49 9077/1065",
    "sg:postcode":"89428",
    "sg:province":"Bayern",
    "wof:name":"Anneliese Seeger",
    "wof:placetype":"venue"
},
  "geometry": {"coordinates":[10.3023519516,48.65650177],"type":"Point"}
}