{
  "type": "Feature",
  "properties": {
    "iso:country":"DE",
    "sg:address":"Dr.-Josef-Ammer-Str. 32",
    "sg:city":"Sch\u00f6nberg",
    "sg:postcode":"94513",
    "sg:province":"Bayern",
    "wof:name":"Michael Stefani",
    "wof:placetype":"venue"
},
  "geometry": {"coordinates":[13.3381567001,48.8443412781],"type":"Point"}
}