{
  "type": "Feature",
  "properties": {
    "iso:country":"DE",
    "sg:address":"sattelhof 3a",
    "sg:city":"Schopfheim",
    "sg:phone":"+49 7622/669933",
    "sg:postcode":"79650",
    "sg:province":"Baden-W\u00fcrttemberg",
    "wof:name":"Cafe-restaurant Reichert",
    "wof:placetype":"venue"
},
  "geometry": {"coordinates":[7.881698,47.673588],"type":"Point"}
}