{
  "type": "Feature",
  "properties": {
    "iso:country":"DE",
    "sg:address":"Bestwiger Str. 47",
    "sg:city":"Bestwig",
    "sg:phone":"+49 2904/4539",
    "sg:postcode":"59909",
    "sg:province":"Nordrhein-Westfalen",
    "wof:name":"Josef Nieder",
    "wof:placetype":"venue"
},
  "geometry": {"coordinates":[8.408012,51.333134],"type":"Point"}
}