{
  "type": "Feature",
  "properties": {
    "iso:country":"DE",
    "sg:address":"Im Bad 59",
    "sg:city":"Sankt Peter-Ording",
    "sg:phone":"+49 4863/7040",
    "sg:postcode":"25826",
    "sg:province":"Schleswig-Holstein",
    "wof:name":"Jensens Hotel Tannenhof",
    "wof:placetype":"venue"
},
  "geometry": {"coordinates":[8.6195793152,54.3078727722],"type":"Point"}
}