{
  "type": "Feature",
  "properties": {
    "iso:country":"DE",
    "sg:address":"W\u00f6lsau 28",
    "sg:city":"Marktredwitz",
    "sg:phone":"+49 9231/2962",
    "sg:postcode":"95615",
    "sg:province":"Bayern",
    "wof:name":"Hilgarth & S\u00f6hne Gmbh & Co. Kg",
    "wof:placetype":"venue"
},
  "geometry": {"coordinates":[12.11896,50.005939],"type":"Point"}
}