{
  "type": "Feature",
  "properties": {
    "iso:country":"DE",
    "sg:address":"Rosenweg 15",
    "sg:city":"Emmendingen",
    "sg:phone":"+49 7641/1269",
    "sg:postcode":"79312",
    "sg:province":"Baden-W\u00fcrttemberg",
    "wof:name":"Dr. Med. Peter-j\u00fcrgen Kuben",
    "wof:placetype":"venue"
},
  "geometry": {"coordinates":[7.8615241051,48.1041145325],"type":"Point"}
}