{
  "type": "Feature",
  "properties": {
    "iso:country":"DE",
    "sg:address":"Bahnhofstr.",
    "sg:city":"Ludwigsburg",
    "sg:phone":"+49 7141/905126",
    "sg:postcode":"71638",
    "sg:province":"Baden-W\u00fcrttemberg",
    "wof:name":"Express",
    "wof:placetype":"venue"
},
  "geometry": {"coordinates":[9.1846151352,48.8937301636],"type":"Point"}
}