{
  "type": "Feature",
  "properties": {
    "iso:country":"DE",
    "sg:address":"Peter-D\u00f6rfler-Str. 33",
    "sg:city":"Wangen",
    "sg:phone":"+49 7522/3360",
    "sg:postcode":"88239",
    "sg:province":"Baden-W\u00fcrttemberg",
    "wof:name":"Franz Messmer Elektroinstallation",
    "wof:placetype":"venue"
},
  "geometry": {"coordinates":[9.826031,47.691574],"type":"Point"}
}