{
  "type": "Feature",
  "properties": {
    "iso:country":"DE",
    "sg:address":"Niemtscher Weg 13",
    "sg:city":"Senftenberg",
    "sg:phone":"+49 3573/3150",
    "sg:postcode":"01968",
    "sg:province":"Brandenburg",
    "wof:name":"Josef Przibilla",
    "wof:placetype":"venue"
},
  "geometry": {"coordinates":[13.995808,51.516251],"type":"Point"}
}