{
  "type": "Feature",
  "properties": {
    "iso:country":"DE",
    "sg:address":"Kronenstr. 4",
    "sg:city":"Nagold",
    "sg:phone":"+49 7452/1502",
    "sg:postcode":"72202",
    "sg:province":"Baden-W\u00fcrttemberg",
    "wof:name":"S. Brenner",
    "wof:placetype":"venue"
},
  "geometry": {"coordinates":[8.720937,48.547676],"type":"Point"}
}