{
  "type": "Feature",
  "properties": {
    "iso:country":"DE",
    "sg:address":"Hannoversche Str. 91-95",
    "sg:city":"Osnabr\u00fcck",
    "sg:postcode":"49084",
    "sg:province":"Niedersachsen",
    "wof:name":"Piepenbrock Technischer Geb\u00e4udeservice",
    "wof:placetype":"venue"
},
  "geometry": {"coordinates":[8.0806188583,52.2597885132],"type":"Point"}
}