{
  "type": "Feature",
  "properties": {
    "iso:country":"DE",
    "sg:address":"Hottengrundweg 14",
    "sg:city":"Berlin",
    "sg:phone":"+49 30/36431195",
    "sg:postcode":"14089",
    "sg:province":"Berlin",
    "wof:name":"G. Luckner Gmbh",
    "wof:placetype":"venue"
},
  "geometry": {"coordinates":[13.127538681,52.450138092],"type":"Point"}
}