{
  "type": "Feature",
  "properties": {
    "iso:country":"DE",
    "sg:address":"Hechinger Str. 151",
    "sg:city":"Albstadt",
    "sg:phone":"+49 7432/3061",
    "sg:postcode":"72461",
    "sg:province":"Baden-W\u00fcrttemberg",
    "wof:name":"W. Schneider Kg",
    "wof:placetype":"venue"
},
  "geometry": {"coordinates":[9.0119199753,48.2636184692],"type":"Point"}
}