{
  "type": "Feature",
  "properties": {
    "iso:country":"DE",
    "sg:address":"Kapuzinerstr. 17",
    "sg:city":"Biberach",
    "sg:phone":"+49 7351/5060",
    "sg:postcode":"88400",
    "sg:province":"Baden-W\u00fcrttemberg",
    "wof:name":"Hotel Kapuzinerhof",
    "wof:placetype":"venue"
},
  "geometry": {"coordinates":[9.7841262817,48.0951766968],"type":"Point"}
}