{
  "type": "Feature",
  "properties": {
    "iso:country":"DE",
    "sg:address":"R\u00f6merstr. 7",
    "sg:city":"Hanau",
    "sg:phone":"+49 6181/85839",
    "sg:postcode":"63450",
    "sg:province":"Hessen",
    "wof:name":"S. Und Y. Balikci Im- Und Export Gmbh",
    "wof:placetype":"venue"
},
  "geometry": {"coordinates":[8.9146213531,50.1321868896],"type":"Point"}
}