{
  "type": "Feature",
  "properties": {
    "iso:country":"DE",
    "sg:address":"Stuttgarter Str. 9",
    "sg:city":"Knittlingen",
    "sg:phone":"+49 7043/31670",
    "sg:postcode":"75438",
    "sg:province":"Baden-W\u00fcrttemberg",
    "wof:name":"S. Kubik",
    "wof:placetype":"venue"
},
  "geometry": {"coordinates":[8.7611637115,49.0235748291],"type":"Point"}
}