{
  "type": "Feature",
  "properties": {
    "iso:country":"DE",
    "sg:address":"Neubergstr. 28",
    "sg:city":"W\u00fcrzburg",
    "sg:phone":"+49 931/72224",
    "sg:postcode":"97072",
    "sg:province":"Bayern",
    "wof:name":"Klaus M\u00fctzel",
    "wof:placetype":"venue"
},
  "geometry": {"coordinates":[9.9385118484,49.7817153931],"type":"Point"}
}