{
  "type": "Feature",
  "properties": {
    "iso:country":"DE",
    "sg:address":"Stapenhorststr. 43",
    "sg:city":"Bielefeld",
    "sg:phone":"+49 521/122137",
    "sg:postcode":"33615",
    "sg:province":"Nordrhein-Westfalen",
    "wof:name":"Nikos Schnellimbiss",
    "wof:placetype":"venue"
},
  "geometry": {"coordinates":[8.5226230621,52.0254058838],"type":"Point"}
}