{
  "type": "Feature",
  "properties": {
    "iso:country":"DE",
    "sg:address":"Altersbacher Str. 16",
    "sg:city":"Steinbach-Hallenberg",
    "sg:phone":"+49 36847/42439",
    "sg:postcode":"98587",
    "sg:province":"Th\u00fcringen",
    "wof:name":"Bau-holz Gmbh",
    "wof:placetype":"venue"
},
  "geometry": {"coordinates":[10.5580120087,50.6955718994],"type":"Point"}
}