{
  "type": "Feature",
  "properties": {
    "iso:country":"DE",
    "sg:address":"Wilhelmstr. 2 + 4",
    "sg:city":"Winnenden",
    "sg:phone":"+49 7195/3122",
    "sg:postcode":"71364",
    "sg:province":"Baden-W\u00fcrttemberg",
    "wof:name":"Sauer Raumausstattung Gmbh",
    "wof:placetype":"venue"
},
  "geometry": {"coordinates":[9.3971414566,48.8782043457],"type":"Point"}
}