{
  "type": "Feature",
  "properties": {
    "iso:country":"DE",
    "sg:address":"Werkstr. 1",
    "sg:city":"\u00dcbach-Palenberg",
    "sg:postcode":"52531",
    "sg:province":"Nordrhein-Westfalen",
    "wof:name":"Aluminium Heizk\u00f6rper Von Alulux",
    "wof:placetype":"venue"
},
  "geometry": {"coordinates":[6.138857,50.914539],"type":"Point"}
}