{
  "type": "Feature",
  "properties": {
    "iso:country":"DE",
    "sg:address":"Liebknechtstr 4",
    "sg:city":"Erfurt",
    "sg:phone":"+49 361/6461193",
    "sg:postcode":"99085",
    "sg:province":"Th\u00fcringen",
    "wof:name":"Druckerei J\u00e4cklein",
    "wof:placetype":"venue"
},
  "geometry": {"coordinates":[11.0413150787,50.9817314148],"type":"Point"}
}