{
  "type": "Feature",
  "properties": {
    "iso:country":"DE",
    "sg:address":"Maa\u00dfstr. 20",
    "sg:city":"Heidelberg",
    "sg:phone":"+49 6221/836573",
    "sg:postcode":"69123",
    "sg:province":"Baden-W\u00fcrttemberg",
    "wof:name":"Karl Stock Mech. Werkstatt",
    "wof:placetype":"venue"
},
  "geometry": {"coordinates":[8.639765,49.420856],"type":"Point"}
}