{
  "type": "Feature",
  "properties": {
    "iso:country":"DE",
    "sg:address":"Marktplatz 1",
    "sg:city":"Rosengarten",
    "sg:phone":"+49 791/51607",
    "sg:postcode":"74538",
    "sg:province":"Baden-W\u00fcrttemberg",
    "wof:name":"Gasthof R\u00f6ssle",
    "wof:placetype":"venue"
},
  "geometry": {"coordinates":[9.7389707565,49.0528144836],"type":"Point"}
}