{
  "type": "Feature",
  "properties": {
    "iso:country":"DE",
    "sg:address":"Sch\u00f6fferstr. 3",
    "sg:city":"Darmstadt",
    "sg:phone":"+49 6151/125167",
    "sg:postcode":"64295",
    "sg:province":"Hessen",
    "wof:name":"Redaktion Querschnitt Fachhochschule Darmstadt",
    "wof:placetype":"venue"
},
  "geometry": {"coordinates":[8.6390886307,49.8674507141],"type":"Point"}
}