{
  "type": "Feature",
  "properties": {
    "iso:country":"DE",
    "sg:address":"Industriestr. 25",
    "sg:city":"B\u00f6nnigheim",
    "sg:phone":"+49 7143/88420",
    "sg:postcode":"74357",
    "sg:province":"Baden-W\u00fcrttemberg",
    "wof:name":"Wachter Graphischer Betrieb Gmbh",
    "wof:placetype":"venue"
},
  "geometry": {"coordinates":[9.1048583984,49.041015625],"type":"Point"}
}