{
  "type": "Feature",
  "properties": {
    "iso:country":"DE",
    "sg:address":"Bamberger Str. 43",
    "sg:city":"Heilbronn",
    "sg:phone":"+49 7131/920472",
    "sg:postcode":"74078",
    "sg:province":"Baden-W\u00fcrttemberg",
    "wof:name":"F. Und B. Prettner",
    "wof:placetype":"venue"
},
  "geometry": {"coordinates":[9.171728,49.164906],"type":"Point"}
}