{
  "type": "Feature",
  "properties": {
    "iso:country":"DE",
    "sg:address":"Christophstr. 18",
    "sg:city":"K\u00f6ln",
    "sg:phone":"+49 221/134278",
    "sg:postcode":"50670",
    "sg:province":"Nordrhein-Westfalen",
    "wof:name":"G\u00fcnther Wehmeyer",
    "wof:placetype":"venue"
},
  "geometry": {"coordinates":[6.945194,50.943924],"type":"Point"}
}