{
  "type": "Feature",
  "properties": {
    "iso:country":"DE",
    "sg:address":"Geiststr. 3",
    "sg:city":"Ennigerloh",
    "sg:phone":"+49 2524/7241",
    "sg:postcode":"59320",
    "sg:province":"Nordrhein-Westfalen",
    "wof:name":"B. Glasing",
    "wof:placetype":"venue"
},
  "geometry": {"coordinates":[8.0246696472,51.835647583],"type":"Point"}
}