{
  "type": "Feature",
  "properties": {
    "iso:country":"DE",
    "sg:address":"Borsteler Str. 2",
    "sg:city":"Bispingen",
    "sg:phone":"+49 5194/436",
    "sg:postcode":"29646",
    "sg:province":"Niedersachsen",
    "wof:name":"Wilhelm M\u00fcller",
    "wof:placetype":"venue"
},
  "geometry": {"coordinates":[9.997965,53.084736],"type":"Point"}
}