{
  "type": "Feature",
  "properties": {
    "iso:country":"DE",
    "sg:address":"Alemannenstr. 106",
    "sg:city":"Bocholt",
    "sg:phone":"+49 2871/181393",
    "sg:postcode":"46395",
    "sg:province":"Nordrhein-Westfalen",
    "wof:name":"Agnes K\u00f6sters",
    "wof:placetype":"venue"
},
  "geometry": {"coordinates":[6.6047420502,51.8258132935],"type":"Point"}
}