{
  "type": "Feature",
  "properties": {
    "iso:country":"DE",
    "sg:address":"Hauptstr. 26",
    "sg:city":"Hausach",
    "sg:phone":"+49 7831/246",
    "sg:postcode":"77756",
    "sg:province":"Baden-W\u00fcrttemberg",
    "wof:name":"Kurt Ebner",
    "wof:placetype":"venue"
},
  "geometry": {"coordinates":[8.171728,48.284344],"type":"Point"}
}