{
  "type": "Feature",
  "properties": {
    "iso:country":"DE",
    "sg:address":"Oberdorf 66",
    "sg:city":"Dankmarshausen",
    "sg:postcode":"99837",
    "sg:province":"Th\u00fcringen",
    "wof:name":"Evangelische Kirche",
    "wof:placetype":"venue"
},
  "geometry": {"coordinates":[10.070725441,50.9400939941],"type":"Point"}
}