{
  "type": "Feature",
  "properties": {
    "iso:country":"DE",
    "sg:address":"Zur Fl\u00fcgelau 40",
    "sg:city":"Crailsheim",
    "sg:phone":"+49 4979/5129550",
    "sg:postcode":"74564",
    "sg:province":"Baden-W\u00fcrttemberg",
    "wof:name":"Aichele Werkzeuge Gmbh",
    "wof:placetype":"venue"
},
  "geometry": {"coordinates":[10.0478887558,49.1308250427],"type":"Point"}
}