{
  "type": "Feature",
  "properties": {
    "iso:country":"DE",
    "sg:address":"Auwanneweg 52",
    "sg:city":"Hanau",
    "sg:phone":"+49 6181/54115",
    "sg:postcode":"63457",
    "sg:province":"Hessen",
    "wof:name":"Club Recreativo Espanol De Gro\u00dfauheim",
    "wof:placetype":"venue"
},
  "geometry": {"coordinates":[8.9469480515,50.1060371399],"type":"Point"}
}