{
  "type": "Feature",
  "properties": {
    "iso:country":"DE",
    "sg:address":"Kirchl 82",
    "sg:city":"Hohenau",
    "sg:phone":"+49 8558/1029",
    "sg:postcode":"94545",
    "sg:province":"Bayern",
    "wof:name":"Wilhelm Gr\u00fcnzinger",
    "wof:placetype":"venue"
},
  "geometry": {"coordinates":[13.495663,48.860058],"type":"Point"}
}