{
  "type": "Feature",
  "properties": {
    "iso:country":"DE",
    "sg:address":"Hauptstr. 4",
    "sg:city":"Mehren",
    "sg:phone":"+49 6592/4685",
    "sg:postcode":"54552",
    "sg:province":"Rheinland-Pfalz",
    "wof:name":"Dietmar Schech Masseur",
    "wof:placetype":"venue"
},
  "geometry": {"coordinates":[6.88077,50.176807],"type":"Point"}
}