{
  "type": "Feature",
  "properties": {
    "iso:country":"DE",
    "sg:address":"Schulweg 3",
    "sg:city":"Lemgo",
    "sg:phone":"+49 5266/268",
    "sg:postcode":"32657",
    "sg:province":"Nordrhein-Westfalen",
    "wof:name":"Karl Wilhelm",
    "wof:placetype":"venue"
},
  "geometry": {"coordinates":[8.915488,51.989868],"type":"Point"}
}