{
  "type": "Feature",
  "properties": {
    "iso:country":"DE",
    "sg:address":"Steinstr. 16",
    "sg:city":"Witzenhausen",
    "sg:phone":"+49 5542/2496",
    "sg:postcode":"37213",
    "sg:province":"Hessen",
    "wof:name":"Elektro-velmeden Harald Velmeden",
    "wof:placetype":"venue"
},
  "geometry": {"coordinates":[9.859665,51.343224],"type":"Point"}
}