{
  "type": "Feature",
  "properties": {
    "iso:country":"DE",
    "sg:address":"Untere Torstr. 26",
    "sg:city":"\u00d6hringen",
    "sg:phone":"+49 7941/7129",
    "sg:postcode":"74613",
    "sg:province":"Baden-W\u00fcrttemberg",
    "wof:name":"Walter Kyre Kachel\u00f6fen-kamine",
    "wof:placetype":"venue"
},
  "geometry": {"coordinates":[9.4993314743,49.2016334534],"type":"Point"}
}