{
  "type": "Feature",
  "properties": {
    "iso:country":"DE",
    "sg:address":"Friedhofstr. 1",
    "sg:city":"Wahnwegen",
    "sg:phone":"+49 6384/303",
    "sg:postcode":"66909",
    "sg:province":"Rheinland-Pfalz",
    "wof:name":"G. J. Becker",
    "wof:placetype":"venue"
},
  "geometry": {"coordinates":[7.3749752045,49.4849853516],"type":"Point"}
}