{
  "type": "Feature",
  "properties": {
    "iso:country":"DE",
    "sg:address":"Blattergasse 13",
    "sg:city":"Memmingen",
    "sg:phone":"+49 8331/3362",
    "sg:postcode":"87700",
    "sg:province":"Bayern",
    "wof:name":"Kessler",
    "wof:placetype":"venue"
},
  "geometry": {"coordinates":[10.192739,47.98708],"type":"Point"}
}