{
  "type": "Feature",
  "properties": {
    "iso:country":"DE",
    "sg:address":"Coswiger Str. 15",
    "sg:city":"Zerbst",
    "sg:phone":"+49 3923/4421",
    "sg:postcode":"39261",
    "sg:province":"Sachsen-Anhalt",
    "wof:name":"G\u00fcnter Lock Sanit\u00e4rausstattung",
    "wof:placetype":"venue"
},
  "geometry": {"coordinates":[12.0990667343,51.9586524963],"type":"Point"}
}