{
  "type": "Feature",
  "properties": {
    "iso:country":"DE",
    "sg:address":"Schallbruch 34",
    "sg:city":"Haan",
    "sg:phone":"+49 212/97099",
    "sg:postcode":"42781",
    "sg:province":"Nordrhein-Westfalen",
    "wof:name":"Ralf Seilheimer Verpackungen",
    "wof:placetype":"venue"
},
  "geometry": {"coordinates":[7.020031,51.205372],"type":"Point"}
}