{
  "type": "Feature",
  "properties": {
    "iso:country":"DE",
    "sg:address":"An der B105",
    "sg:city":"J\u00f6rnstorf",
    "sg:phone":"+49 38294/12016",
    "sg:postcode":"18233",
    "sg:province":"Mecklenburg-Vorpommern",
    "wof:name":"M\u00f6belkiste Gbr",
    "wof:placetype":"venue"
},
  "geometry": {"coordinates":[11.672425,54.03154],"type":"Point"}
}