{
  "type": "Feature",
  "properties": {
    "iso:country":"DE",
    "sg:address":"Grundstr. 33",
    "sg:city":"Solingen",
    "sg:phone":"+49 4921/2813872",
    "sg:postcode":"42655",
    "sg:province":"Nordrhein-Westfalen",
    "wof:name":"Emil Schmidt Gmbh",
    "wof:placetype":"venue"
},
  "geometry": {"coordinates":[7.070435,51.166206],"type":"Point"}
}