{
  "type": "Feature",
  "properties": {
    "iso:country":"DE",
    "sg:address":"Brunnenstr. 56",
    "sg:city":"Alzey",
    "sg:phone":"+49 6731/3565",
    "sg:postcode":"55232",
    "sg:province":"Rheinland-Pfalz",
    "wof:name":"Pizza Blitz Dautenheim",
    "wof:placetype":"venue"
},
  "geometry": {"coordinates":[8.1498880386,49.7407112122],"type":"Point"}
}