{
  "type": "Feature",
  "properties": {
    "iso:country":"DE",
    "sg:address":"Frankstr. 7",
    "sg:city":"Hagen",
    "sg:phone":"+49 2331/42605",
    "sg:postcode":"58135",
    "sg:province":"Nordrhein-Westfalen",
    "wof:name":"Diakoniestation",
    "wof:placetype":"venue"
},
  "geometry": {"coordinates":[7.420557,51.348351],"type":"Point"}
}