{
  "type": "Feature",
  "properties": {
    "iso:country":"DE",
    "sg:address":"August-Bebel-Str. 15",
    "sg:city":"Atzendorf",
    "sg:phone":"+49 39266/265",
    "sg:postcode":"39443",
    "sg:province":"Sachsen-Anhalt",
    "wof:name":"Atzendorfer Schwei\u00dftechnik Und Vertriebs Gmbh",
    "wof:placetype":"venue"
},
  "geometry": {"coordinates":[11.60115242,51.9228210449],"type":"Point"}
}