{
  "type": "Feature",
  "properties": {
    "iso:country":"DE",
    "sg:address":"Erlenweg 17",
    "sg:city":"Laupheim",
    "sg:phone":"+49 7392/150127",
    "sg:postcode":"88471",
    "sg:province":"Baden-W\u00fcrttemberg",
    "wof:name":"Zehra Y\u00fcksel",
    "wof:placetype":"venue"
},
  "geometry": {"coordinates":[9.8944282532,48.2271385193],"type":"Point"}
}