{
  "type": "Feature",
  "properties": {
    "iso:country":"DE",
    "sg:address":"\u00c4u\u00dfere Windsheimer Str. 3",
    "sg:city":"Langenzenn",
    "sg:phone":"+49 9102/997985",
    "sg:postcode":"90579",
    "sg:province":"Bayern",
    "wof:name":"Andrea Heitz",
    "wof:placetype":"venue"
},
  "geometry": {"coordinates":[10.7564373016,49.4917221069],"type":"Point"}
}