{
  "type": "Feature",
  "properties": {
    "iso:country":"DE",
    "sg:address":"Waltersheide 44",
    "sg:city":"Geldern",
    "sg:phone":"+49 2831/2150",
    "sg:postcode":"47608",
    "sg:province":"Nordrhein-Westfalen",
    "wof:name":"Gartenbauprojekte Symalla Gmbh",
    "wof:placetype":"venue"
},
  "geometry": {"coordinates":[6.353376,51.548508],"type":"Point"}
}