{
  "type": "Feature",
  "properties": {
    "iso:country":"DE",
    "sg:address":"Donathstr. 6",
    "sg:city":"Quickborn",
    "sg:phone":"+49 4106/69270",
    "sg:postcode":"25451",
    "sg:province":"Schleswig-Holstein",
    "wof:name":"A. Nachtsheim",
    "wof:placetype":"venue"
},
  "geometry": {"coordinates":[9.8927774429,53.7331733704],"type":"Point"}
}