{
  "type": "Feature",
  "properties": {
    "iso:country":"DE",
    "sg:address":"Wilhelmstr. 4",
    "sg:city":"Sellin",
    "sg:phone":"+49 38303/984",
    "sg:postcode":"18586",
    "sg:province":"Mecklenburg-Vorpommern",
    "wof:name":"I. Von Schmudi",
    "wof:placetype":"venue"
},
  "geometry": {"coordinates":[13.694803,54.377735],"type":"Point"}
}