{
  "type": "Feature",
  "properties": {
    "iso:country":"DE",
    "sg:address":"am anger 5",
    "sg:city":"dresden",
    "sg:phone":"+49 351/4014167",
    "sg:postcode":"01217",
    "sg:province":"Sachsen",
    "wof:name":"Welcome Hacker",
    "wof:placetype":"venue"
},
  "geometry": {"coordinates":[13.790282,51.011272],"type":"Point"}
}