{
  "type": "Feature",
  "properties": {
    "iso:country":"DE",
    "sg:address":"Raiffeisenstr. 14",
    "sg:city":"Albstadt",
    "sg:phone":"+49 7432/7825",
    "sg:postcode":"72461",
    "sg:province":"Baden-W\u00fcrttemberg",
    "wof:name":"R. Ringwald",
    "wof:placetype":"venue"
},
  "geometry": {"coordinates":[9.0293264389,48.23695755],"type":"Point"}
}