{
  "type": "Feature",
  "properties": {
    "iso:country":"DE",
    "sg:address":"Poststr\u00e4\u00dfle 10",
    "sg:city":"Bietigheim-Bissingen",
    "sg:phone":"+49 7142/730",
    "sg:postcode":"74321",
    "sg:province":"Baden-W\u00fcrttemberg",
    "wof:name":"Valeo-autoelectric Gmbh",
    "wof:placetype":"venue"
},
  "geometry": {"coordinates":[9.1474208832,48.9575119019],"type":"Point"}
}