{
  "type": "Feature",
  "properties": {
    "iso:country":"DE",
    "sg:address":"Kiesstr. 7",
    "sg:city":"Esslingen",
    "sg:phone":"+49 711/8064586",
    "sg:postcode":"73728",
    "sg:province":"Baden-W\u00fcrttemberg",
    "wof:name":"Versicherungsb\u00fcro Montwill",
    "wof:placetype":"venue"
},
  "geometry": {"coordinates":[9.3105010986,48.7394371033],"type":"Point"}
}