{
  "type": "Feature",
  "properties": {
    "iso:country":"DE",
    "sg:address":"Kronengasse 8/1",
    "sg:city":"Reute",
    "sg:phone":"+49 7641/42957",
    "sg:postcode":"79276",
    "sg:province":"Baden-W\u00fcrttemberg",
    "wof:name":"Hans-peter Karle B\u00e4ckerei",
    "wof:placetype":"venue"
},
  "geometry": {"coordinates":[7.810415,48.080723],"type":"Point"}
}