{
  "type": "Feature",
  "properties": {
    "iso:country":"DE",
    "sg:address":"Alfen 3",
    "sg:city":"Wipperf\u00fcrth",
    "sg:phone":"+49 2267/82745",
    "sg:postcode":"51688",
    "sg:province":"Nordrhein-Westfalen",
    "wof:name":"Stefan K\u00fcrten",
    "wof:placetype":"venue"
},
  "geometry": {"coordinates":[7.353004,51.066795],"type":"Point"}
}