{
  "type": "Feature",
  "properties": {
    "iso:country":"DE",
    "sg:address":"Rathausufer 22",
    "sg:city":"D\u00fcsseldorf",
    "sg:phone":"+49 211/326648",
    "sg:postcode":"40213",
    "sg:province":"Nordrhein-Westfalen",
    "wof:name":"Ursula Salomon Innenarchitektin",
    "wof:placetype":"venue"
},
  "geometry": {"coordinates":[6.769145,51.223061],"type":"Point"}
}