{
  "type": "Feature",
  "properties": {
    "iso:country":"DE",
    "sg:address":"Nelkenweg 1",
    "sg:city":"Mainz",
    "sg:phone":"+49 6131/479142",
    "sg:postcode":"55126",
    "sg:province":"Rheinland-Pfalz",
    "wof:name":"Buwo Handels Gmbh",
    "wof:placetype":"venue"
},
  "geometry": {"coordinates":[8.1832771301,49.987323761],"type":"Point"}
}