{
  "type": "Feature",
  "properties": {
    "iso:country":"DE",
    "sg:address":"Werbelner Str. 7-9",
    "sg:city":"Wadgassen",
    "sg:phone":"+49 6834/6733",
    "sg:postcode":"66787",
    "sg:province":"Saarland",
    "wof:name":"Erwin Schirra",
    "wof:placetype":"venue"
},
  "geometry": {"coordinates":[6.7789268494,49.2419052124],"type":"Point"}
}