{
  "type": "Feature",
  "properties": {
    "iso:country":"DE",
    "sg:address":"Lindenhorster Str. 200",
    "sg:city":"Dortmund",
    "sg:phone":"+49 231/814589",
    "sg:postcode":"44339",
    "sg:province":"Nordrhein-Westfalen",
    "wof:name":"Winfried Raabe",
    "wof:placetype":"venue"
},
  "geometry": {"coordinates":[7.4480161667,51.5489807129],"type":"Point"}
}