{
  "type": "Feature",
  "properties": {
    "iso:country":"DE",
    "sg:address":"Barbarastr. 72",
    "sg:city":"K\u00f6ln",
    "sg:phone":"+49 221/762554",
    "sg:postcode":"50735",
    "sg:province":"Nordrhein-Westfalen",
    "wof:name":"Peter Chlosta",
    "wof:placetype":"venue"
},
  "geometry": {"coordinates":[6.9771437645,50.969127655],"type":"Point"}
}