{
  "type": "Feature",
  "properties": {
    "iso:country":"DE",
    "sg:address":"Am Tannenhof 28",
    "sg:city":"Siegburg",
    "sg:phone":"+49 2241/380154",
    "sg:postcode":"53721",
    "sg:province":"Nordrhein-Westfalen",
    "wof:name":"Vav Rohrleitungsbau Gmbh",
    "wof:placetype":"venue"
},
  "geometry": {"coordinates":[7.2376999855,50.8053474426],"type":"Point"}
}