{
  "type": "Feature",
  "properties": {
    "iso:country":"DE",
    "sg:address":"Alt-Marzahn 49",
    "sg:city":"Berlin",
    "sg:phone":"+49 30/5400560",
    "sg:postcode":"12685",
    "sg:province":"Berlin",
    "wof:name":"Landhaus Marzahn",
    "wof:placetype":"venue"
},
  "geometry": {"coordinates":[13.5609855652,52.5436058044],"type":"Point"}
}