{
  "type": "Feature",
  "properties": {
    "iso:country":"DE",
    "sg:address":"Drachenbergblick 9",
    "sg:city":"Braunschweig",
    "sg:phone":"+49 531/873396",
    "sg:postcode":"38122",
    "sg:province":"Niedersachsen",
    "wof:name":"Cosmeticum In Broitzem",
    "wof:placetype":"venue"
},
  "geometry": {"coordinates":[10.4875278473,52.2301597595],"type":"Point"}
}