{
  "type": "Feature",
  "properties": {
    "iso:country":"DE",
    "sg:address":"An der Schanze 3",
    "sg:city":"Sehnde",
    "sg:phone":"+49 5138/8962",
    "sg:postcode":"31319",
    "sg:province":"Niedersachsen",
    "wof:name":"Gerhard Fischer",
    "wof:placetype":"venue"
},
  "geometry": {"coordinates":[10.050015,52.305157],"type":"Point"}
}