{
  "type": "Feature",
  "properties": {
    "iso:country":"DE",
    "sg:address":"Distelecke 7",
    "sg:city":"Seesen",
    "sg:phone":"+49 5381/8794",
    "sg:postcode":"38723",
    "sg:province":"Niedersachsen",
    "wof:name":"Club Der Damen- Und Herren- Friseure Goslar 1949 E. V.",
    "wof:placetype":"venue"
},
  "geometry": {"coordinates":[10.1961679459,51.8486824036],"type":"Point"}
}