{
  "type": "Feature",
  "properties": {
    "iso:country":"DE",
    "sg:address":"Domgasse",
    "sg:city":"Freiberg",
    "sg:postcode":"09599",
    "sg:province":"Sachsen",
    "wof:name":"Christian Tempel",
    "wof:placetype":"venue"
},
  "geometry": {"coordinates":[13.34284,50.920349],"type":"Point"}
}