{
  "type": "Feature",
  "properties": {
    "iso:country":"DE",
    "sg:address":"Lindenstr. 24",
    "sg:city":"Fladungen",
    "sg:phone":"+49 9778/404",
    "sg:postcode":"97650",
    "sg:province":"Bayern",
    "wof:name":"Anton Stumpf",
    "wof:placetype":"venue"
},
  "geometry": {"coordinates":[10.1599369049,50.5377807617],"type":"Point"}
}