{
  "type": "Feature",
  "properties": {
    "iso:country":"DE",
    "sg:address":"Bahnhofstr. 40",
    "sg:city":"Burgthann",
    "sg:phone":"+49 9183/4755",
    "sg:postcode":"90559",
    "sg:province":"Bayern",
    "wof:name":"Zum Bahnhof Regina Hiltner-gaar",
    "wof:placetype":"venue"
},
  "geometry": {"coordinates":[11.3097696304,49.3460693359],"type":"Point"}
}