{
  "type": "Feature",
  "properties": {
    "iso:country":"DE",
    "sg:address":"Karolinenstr. 12",
    "sg:city":"Seeheim-Jugenheim",
    "sg:phone":"+49 6257/82936",
    "sg:postcode":"64342",
    "sg:province":"Hessen",
    "wof:name":"K. Loem Ingenieur",
    "wof:placetype":"venue"
},
  "geometry": {"coordinates":[8.6484766006,49.7612991333],"type":"Point"}
}