{
  "type": "Feature",
  "properties": {
    "iso:country":"DE",
    "sg:address":"Beerenweg 2",
    "sg:city":"Halle",
    "sg:phone":"+49 345/4449221",
    "sg:postcode":"06130",
    "sg:province":"Sachsen-Anhalt",
    "wof:name":"Wilfried Bandel",
    "wof:placetype":"venue"
},
  "geometry": {"coordinates":[11.9834480286,51.4473876953],"type":"Point"}
}