{
  "type": "Feature",
  "properties": {
    "iso:country":"DE",
    "sg:address":"Zugspitzstr. 8",
    "sg:city":"Bernried",
    "sg:phone":"+49 8151/50964",
    "sg:postcode":"82347",
    "sg:province":"Bayern",
    "wof:name":"Burghard Domsch Ingenieur",
    "wof:placetype":"venue"
},
  "geometry": {"coordinates":[11.2842216492,47.8627853394],"type":"Point"}
}