{
  "type": "Feature",
  "properties": {
    "iso:country":"DE",
    "sg:address":"Tannecker Gasse 4",
    "sg:city":"Eisenberg",
    "sg:phone":"+49 36691/42550",
    "sg:postcode":"07607",
    "sg:province":"Th\u00fcringen",
    "wof:name":"Matthias Frey",
    "wof:placetype":"venue"
},
  "geometry": {"coordinates":[11.899501,50.967815],"type":"Point"}
}