{
  "type": "Feature",
  "properties": {
    "iso:country":"DE",
    "sg:address":"Klaus-Groth-Str. 7",
    "sg:city":"Bottrop",
    "sg:phone":"+49 2045/83598",
    "sg:postcode":"46244",
    "sg:province":"Nordrhein-Westfalen",
    "wof:name":"H. Schilling",
    "wof:placetype":"venue"
},
  "geometry": {"coordinates":[6.916799,51.607483],"type":"Point"}
}