{
  "type": "Feature",
  "properties": {
    "iso:country":"DE",
    "sg:address":"R\u00f6testr. 10A",
    "sg:city":"Bietigheim-Bissingen",
    "sg:phone":"+49 7142/51991",
    "sg:postcode":"74321",
    "sg:province":"Baden-W\u00fcrttemberg",
    "wof:name":"R. Gautschi",
    "wof:placetype":"venue"
},
  "geometry": {"coordinates":[9.149999,48.952141],"type":"Point"}
}