{
  "type": "Feature",
  "properties": {
    "iso:country":"DE",
    "sg:address":"Buddestr. 18-20",
    "sg:city":"Bergisch Gladbach",
    "sg:phone":"+49 2204/54028",
    "sg:postcode":"51429",
    "sg:province":"Nordrhein-Westfalen",
    "wof:name":"Bauturm Gmbh",
    "wof:placetype":"venue"
},
  "geometry": {"coordinates":[7.151547,50.966629],"type":"Point"}
}