{
  "type": "Feature",
  "properties": {
    "iso:country":"DE",
    "sg:address":"Hein-Janssen-Str. 11",
    "sg:city":"Aachen",
    "sg:phone":"+49 241/502422",
    "sg:postcode":"52070",
    "sg:province":"Nordrhein-Westfalen",
    "wof:name":"W. Lothmann",
    "wof:placetype":"venue"
},
  "geometry": {"coordinates":[6.099233,50.778423],"type":"Point"}
}