{
  "type": "Feature",
  "properties": {
    "iso:country":"DE",
    "sg:address":"Schillerstr. 6",
    "sg:city":"Linnich",
    "sg:postcode":"52441",
    "sg:province":"Nordrhein-Westfalen",
    "wof:name":"Louisa Moden",
    "wof:placetype":"venue"
},
  "geometry": {"coordinates":[6.267888,50.973438],"type":"Point"}
}