{
  "type": "Feature",
  "properties": {
    "iso:country":"DE",
    "sg:address":"T\u00f6pferstr. 51",
    "sg:city":"Essen",
    "sg:phone":"+49 201/253377",
    "sg:postcode":"45136",
    "sg:province":"Nordrhein-Westfalen",
    "wof:name":"H.-t. Re Liwette Kunstmaler",
    "wof:placetype":"venue"
},
  "geometry": {"coordinates":[7.030703,51.439404],"type":"Point"}
}