{
  "type": "Feature",
  "properties": {
    "iso:country":"DE",
    "sg:address":"Grimmenstein",
    "sg:city":"Wolfegg",
    "sg:postcode":"88364",
    "sg:province":"Baden-W\u00fcrttemberg",
    "wof:name":"Pro Systems Gmbh",
    "wof:placetype":"venue"
},
  "geometry": {"coordinates":[9.807401,47.825233],"type":"Point"}
}