{
  "type": "Feature",
  "properties": {
    "iso:country":"DE",
    "sg:address":"Sachsentor 29",
    "sg:city":"Hamburg",
    "sg:phone":"+49 40/312755",
    "sg:postcode":"21029",
    "sg:province":"Hamburg",
    "wof:name":"Happy Nails",
    "wof:placetype":"venue"
},
  "geometry": {"coordinates":[10.2130947113,53.4880371094],"type":"Point"}
}