{
  "type": "Feature",
  "properties": {
    "iso:country":"DE",
    "sg:address":"Erler Str. 385",
    "sg:city":"Schermbeck",
    "sg:phone":"+49 2853/4246",
    "sg:postcode":"46514",
    "sg:province":"Nordrhein-Westfalen",
    "wof:name":"Johann Br\u00fcnninghoff",
    "wof:placetype":"venue"
},
  "geometry": {"coordinates":[6.863676,51.730022],"type":"Point"}
}