{
  "type": "Feature",
  "properties": {
    "iso:country":"DE",
    "sg:address":"Cimbernstr. 13",
    "sg:city":"D\u00fcsseldorf",
    "sg:phone":"+49 211/575278",
    "sg:postcode":"40545",
    "sg:province":"Nordrhein-Westfalen",
    "wof:name":"Rudolf Nachmann Steuerberater",
    "wof:placetype":"venue"
},
  "geometry": {"coordinates":[6.7570538521,51.2278022766],"type":"Point"}
}