{
  "type": "Feature",
  "properties": {
    "iso:country":"DE",
    "sg:address":"Willicher Str 12",
    "sg:city":"T\u00f6nisvorst",
    "sg:phone":"+49 2151/7079611",
    "sg:postcode":"47918",
    "sg:province":"Nordrhein-Westfalen",
    "wof:name":"Voigt",
    "wof:placetype":"venue"
},
  "geometry": {"coordinates":[6.497358799,51.319152832],"type":"Point"}
}