{
  "type": "Feature",
  "properties": {
    "iso:country":"DE",
    "sg:address":"Kalterweg 72",
    "sg:city":"Stadtlohn",
    "sg:phone":"+49 2563/7888",
    "sg:postcode":"48703",
    "sg:province":"Nordrhein-Westfalen",
    "wof:name":"Josef Heming",
    "wof:placetype":"venue"
},
  "geometry": {"coordinates":[6.930883,51.996761],"type":"Point"}
}