{
  "type": "Feature",
  "properties": {
    "iso:country":"DE",
    "sg:address":"Luppostr. 5",
    "sg:city":"Essen",
    "sg:phone":"+49 201/588143",
    "sg:postcode":"45277",
    "sg:province":"Nordrhein-Westfalen",
    "wof:name":"Otto Bovermann Mineral\u00f6l-grosshandel",
    "wof:placetype":"venue"
},
  "geometry": {"coordinates":[7.0787911415,51.4340515137],"type":"Point"}
}