{
  "type": "Feature",
  "properties": {
    "iso:country":"DE",
    "sg:address":"Alexanderstr 2::",
    "sg:city":"Hannover",
    "sg:postcode":"30159",
    "sg:province":"Niedersachsen",
    "wof:name":"Wilh Basse Kg Ik",
    "wof:placetype":"venue"
},
  "geometry": {"coordinates":[9.744685,52.373409],"type":"Point"}
}