{
  "type": "Feature",
  "properties": {
    "iso:country":"DE",
    "sg:address":"Schwarzwaldstr 40",
    "sg:city":"L\u00f6rrach",
    "sg:phone":"+49 7621/45603",
    "sg:postcode":"79539",
    "sg:province":"Baden-W\u00fcrttemberg",
    "wof:name":"M. Gro\u00dfmann Ag",
    "wof:placetype":"venue"
},
  "geometry": {"coordinates":[7.6695141792,47.6215171814],"type":"Point"}
}