{
  "type": "Feature",
  "properties": {
    "iso:country":"DE",
    "sg:address":"Rudolst\u00e4dter Str. 120",
    "sg:city":"Oberwei\u00dfbach",
    "sg:phone":"+49 36705/62169",
    "sg:postcode":"98744",
    "sg:province":"Th\u00fcringen",
    "wof:name":"J\u00fcrgen Kurras Gmbh",
    "wof:placetype":"venue"
},
  "geometry": {"coordinates":[11.150743,50.586552],"type":"Point"}
}