{
  "type": "Feature",
  "properties": {
    "iso:country":"DE",
    "sg:city":"M\u00e4hring",
    "sg:phone":"+49 9639/240",
    "sg:postcode":"95695",
    "sg:province":"Bayern",
    "wof:name":"Raiffeisenbank Tirschenreuth Eg",
    "wof:placetype":"venue"
},
  "geometry": {"coordinates":[12.528065,49.908962],"type":"Point"}
}