{
  "type": "Feature",
  "properties": {
    "iso:country":"DE",
    "sg:address":"Bahnhofstr. 50",
    "sg:city":"St. Michaelisdonn",
    "sg:phone":"+49 4853/385",
    "sg:postcode":"25693",
    "sg:province":"Schleswig-Holstein",
    "wof:name":"Hans-dieter Engel",
    "wof:placetype":"venue"
},
  "geometry": {"coordinates":[9.1145820618,53.9886322021],"type":"Point"}
}