{
  "type": "Feature",
  "properties": {
    "iso:country":"DE",
    "sg:address":"Thomas-M\u00fcntzer-Str. 8",
    "sg:city":"Berlin",
    "sg:phone":"+49 30/6773147",
    "sg:postcode":"12489",
    "sg:province":"Berlin",
    "wof:name":"D\u00f6rschel Textilpflege Gmbh & Co. Betriebs Kg",
    "wof:placetype":"venue"
},
  "geometry": {"coordinates":[13.54549,52.436161],"type":"Point"}
}