{
  "type": "Feature",
  "properties": {
    "iso:country":"DE",
    "sg:address":"Triebstr. 16",
    "sg:city":"Gutenacker",
    "sg:phone":"+49 6439/91610",
    "sg:postcode":"56370",
    "sg:province":"Rheinland-Pfalz",
    "wof:name":"Sapro Gesellschaft F\u00fcr Salzproduktion Mbh",
    "wof:placetype":"venue"
},
  "geometry": {"coordinates":[7.9187397957,50.3189239502],"type":"Point"}
}