{
  "type": "Feature",
  "properties": {
    "iso:country":"DE",
    "sg:address":"Leubener Str. 1",
    "sg:city":"Dresden",
    "sg:phone":"+49 351/2571633",
    "sg:postcode":"01279",
    "sg:province":"Sachsen",
    "wof:name":"Forsthaus Laubegast",
    "wof:placetype":"venue"
},
  "geometry": {"coordinates":[13.8372421265,51.0245513916],"type":"Point"}
}