{
  "type": "Feature",
  "properties": {
    "iso:country":"DE",
    "sg:address":"K\u00f6nigstr. 53",
    "sg:city":"Minden",
    "sg:phone":"+49 571/87279",
    "sg:postcode":"32427",
    "sg:province":"Nordrhein-Westfalen",
    "wof:name":"Chinesischer Imbi\u00df",
    "wof:placetype":"venue"
},
  "geometry": {"coordinates":[8.9083766937,52.2870140076],"type":"Point"}
}