{
  "type": "Feature",
  "properties": {
    "iso:country":"DE",
    "sg:address":"Kleine Str. 8",
    "sg:city":"Quakenbr\u00fcck",
    "sg:phone":"+49 5431/4550",
    "sg:postcode":"49610",
    "sg:province":"Niedersachsen",
    "wof:name":"Becker & Knebusch Ohg",
    "wof:placetype":"venue"
},
  "geometry": {"coordinates":[7.948631,52.681824],"type":"Point"}
}