{
  "type": "Feature",
  "properties": {
    "iso:country":"DE",
    "sg:address":"Garnsdorfer Hauptstr. 116",
    "sg:city":"Lichtenau",
    "sg:postcode":"09244",
    "sg:province":"Sachsen",
    "wof:name":"Suchy Und Kunath Gmbh",
    "wof:placetype":"venue"
},
  "geometry": {"coordinates":[12.928071022,50.9217376709],"type":"Point"}
}