{
  "type": "Feature",
  "properties": {
    "iso:country":"DE",
    "sg:address":"Obh\u00e4user Weg 4",
    "sg:city":"Querfurt",
    "sg:phone":"+49 34771/24115",
    "sg:postcode":"06268",
    "sg:province":"Sachsen-Anhalt",
    "wof:name":"Sportlerheim",
    "wof:placetype":"venue"
},
  "geometry": {"coordinates":[11.6064367294,51.3841781616],"type":"Point"}
}