{
  "type": "Feature",
  "properties": {
    "iso:country":"DE",
    "sg:address":"Breitscheidstr. 75",
    "sg:city":"Crimmitschau",
    "sg:phone":"+49 3762/945640",
    "sg:postcode":"08451",
    "sg:province":"Sachsen",
    "wof:name":"Etg Gmbh & Co. Kg",
    "wof:placetype":"venue"
},
  "geometry": {"coordinates":[12.4050912857,50.8236541748],"type":"Point"}
}