{
  "type": "Feature",
  "properties": {
    "iso:country":"DE",
    "sg:address":"Hauptstr 186",
    "sg:city":"Gro\u00dfhartmannsdorf",
    "sg:phone":"+49 7268/91240",
    "sg:postcode":"09618",
    "sg:province":"Sachsen",
    "wof:name":"E-lab Computers",
    "wof:placetype":"venue"
},
  "geometry": {"coordinates":[9.038664,49.253216],"type":"Point"}
}