{
  "type": "Feature",
  "properties": {
    "iso:country":"DE",
    "sg:address":"Halle-Kasseler-Str.",
    "sg:city":"Beuren",
    "sg:postcode":"37327",
    "sg:province":"Th\u00fcringen",
    "wof:name":"Kohlehandel Erfurt Gmbh",
    "wof:placetype":"venue"
},
  "geometry": {"coordinates":[10.28317,51.378086],"type":"Point"}
}