{
  "type": "Feature",
  "properties": {
    "iso:country":"DE",
    "sg:address":"L\u00fcbnitzer Str. 13",
    "sg:city":"Belzig",
    "sg:phone":"+49 33841/42892",
    "sg:postcode":"14806",
    "sg:province":"Brandenburg",
    "wof:name":"Gerd V\u00f6lker Ingenieur",
    "wof:placetype":"venue"
},
  "geometry": {"coordinates":[12.5813589096,52.1425933838],"type":"Point"}
}