{
  "type": "Feature",
  "properties": {
    "iso:country":"DE",
    "sg:address":"Rheinstr. 75",
    "sg:city":"Ginsheim-Gustavsburg",
    "sg:phone":"+49 6144/32929",
    "sg:postcode":"65462",
    "sg:province":"Hessen",
    "wof:name":"G. P. Arnold Heilpraktiker",
    "wof:placetype":"venue"
},
  "geometry": {"coordinates":[8.3452243805,49.9688224792],"type":"Point"}
}