{
  "type": "Feature",
  "properties": {
    "iso:country":"DE",
    "sg:address":"Marktstr. 11/1",
    "sg:city":"Schelklingen",
    "sg:phone":"+49 7394/785",
    "sg:postcode":"89601",
    "sg:province":"Baden-W\u00fcrttemberg",
    "wof:name":"Gerhard Stevanin Elektrotechnik",
    "wof:placetype":"venue"
},
  "geometry": {"coordinates":[9.733199,48.375511],"type":"Point"}
}