{
  "type": "Feature",
  "properties": {
    "iso:country":"DE",
    "sg:address":"Hasselbacher Str. 3",
    "sg:city":"Merenberg",
    "sg:phone":"+49 6471/52740",
    "sg:postcode":"35799",
    "sg:province":"Hessen",
    "wof:name":"E. Br\u00fcckel",
    "wof:placetype":"venue"
},
  "geometry": {"coordinates":[8.195616,50.493801],"type":"Point"}
}