{
  "type": "Feature",
  "properties": {
    "iso:country":"DE",
    "sg:address":"Gewerbering 13",
    "sg:city":"Wilkau-Ha\u00dflau",
    "sg:phone":"+49 375/690080",
    "sg:postcode":"08112",
    "sg:province":"Sachsen",
    "wof:name":"Wkfs-werkzeug- Komponenten-fertigung Gmbh",
    "wof:placetype":"venue"
},
  "geometry": {"coordinates":[12.5146780014,50.6850318909],"type":"Point"}
}