{
  "type": "Feature",
  "properties": {
    "iso:country":"DE",
    "sg:address":"Wielandstr. 38",
    "sg:city":"Hamburg",
    "sg:phone":"+49 40/2008661",
    "sg:postcode":"22089",
    "sg:province":"Hamburg",
    "wof:name":"Peter Lang Rechtsanwalt",
    "wof:placetype":"venue"
},
  "geometry": {"coordinates":[10.0530385971,53.5721473694],"type":"Point"}
}