{
  "type": "Feature",
  "properties": {
    "iso:country":"DE",
    "sg:address":"Schuckertstr. 22",
    "sg:city":"Rutesheim",
    "sg:phone":"+49 7152/999610",
    "sg:postcode":"71277",
    "sg:province":"Baden-W\u00fcrttemberg",
    "wof:name":"Baustoffpr\u00fcfgesellschaft Mbh",
    "wof:placetype":"venue"
},
  "geometry": {"coordinates":[8.9595403671,48.8126907349],"type":"Point"}
}