{
  "type": "Feature",
  "properties": {
    "iso:country":"DE",
    "sg:address":"Reisacher Str. 60",
    "sg:city":"L\u00f6wenstein",
    "sg:phone":"+49 7130/8172",
    "sg:postcode":"74245",
    "sg:province":"Baden-W\u00fcrttemberg",
    "wof:name":"Herbert Bihlmayer",
    "wof:placetype":"venue"
},
  "geometry": {"coordinates":[9.383020401,49.1028404236],"type":"Point"}
}