{
  "type": "Feature",
  "properties": {
    "iso:country":"DE",
    "sg:address":"Bundesstr. 58",
    "sg:city":"Bestwig",
    "sg:postcode":"59909",
    "sg:province":"Nordrhein-Westfalen",
    "wof:name":"Fleischerei Josef Hoppe Gmbh",
    "wof:placetype":"venue"
},
  "geometry": {"coordinates":[8.3812522888,51.3568725586],"type":"Point"}
}