{
  "type": "Feature",
  "properties": {
    "iso:country":"DE",
    "sg:address":"Breyeller Str. 28",
    "sg:city":"Nettetal",
    "sg:phone":"+49 2153/60583",
    "sg:postcode":"41334",
    "sg:province":"Nordrhein-Westfalen",
    "wof:name":"S. Ousoun-andreou",
    "wof:placetype":"venue"
},
  "geometry": {"coordinates":[6.273363,51.304592],"type":"Point"}
}