{
  "type": "Feature",
  "properties": {
    "iso:country":"DE",
    "sg:address":"K\u00f6nigsberger Str. 46",
    "sg:city":"Straubing",
    "sg:phone":"+49 9421/61164",
    "sg:postcode":"94315",
    "sg:province":"Bayern",
    "wof:name":"Josef Wolf",
    "wof:placetype":"venue"
},
  "geometry": {"coordinates":[12.6015481949,48.8854942322],"type":"Point"}
}