{
  "type": "Feature",
  "properties": {
    "iso:country":"DE",
    "sg:address":"Bahnhofstr. 119",
    "sg:city":"Osterholz-Scharmbeck",
    "sg:phone":"+49 4791/986398",
    "sg:postcode":"27711",
    "sg:province":"Niedersachsen",
    "wof:name":"Iris Falcke Praxis F\u00fcr Ergotherapie",
    "wof:placetype":"venue"
},
  "geometry": {"coordinates":[8.786049,53.227203],"type":"Point"}
}