{
  "type": "Feature",
  "properties": {
    "iso:country":"DE",
    "sg:address":"Binderslebener Landstr.",
    "sg:city":"Erfurt",
    "sg:phone":"+49 361/2229885",
    "sg:postcode":"99092",
    "sg:province":"Th\u00fcringen",
    "wof:name":"Gerhard Eckelmann",
    "wof:placetype":"venue"
},
  "geometry": {"coordinates":[10.965464592,50.9737892151],"type":"Point"}
}