{
  "type": "Feature",
  "properties": {
    "iso:country":"DE",
    "sg:address":"Degerndorfer Str. 10 b",
    "sg:city":"Achm\u00fchle",
    "sg:phone":"+49 8171",
    "sg:postcode":"82547",
    "sg:province":"Bayern",
    "wof:name":"Peki Fantasy Show",
    "wof:placetype":"venue"
},
  "geometry": {"coordinates":[11.4095802307,47.8841133118],"type":"Point"}
}