{
  "type": "Feature",
  "properties": {
    "iso:country":"DE",
    "sg:address":"Dornsgasse 9",
    "sg:city":"Apolda",
    "sg:phone":"+49 3644/555167",
    "sg:postcode":"99510",
    "sg:province":"Th\u00fcringen",
    "wof:name":"Ast Kr\u00fcgel & B\u00f6hme",
    "wof:placetype":"venue"
},
  "geometry": {"coordinates":[11.516864,51.025951],"type":"Point"}
}