{
  "type": "Feature",
  "properties": {
    "iso:country":"DE",
    "sg:address":"Osterfelder Str. 28",
    "sg:city":"Bottrop",
    "sg:phone":"+49 2041/21877",
    "sg:postcode":"46236",
    "sg:province":"Nordrhein-Westfalen",
    "wof:name":"China-restaurant",
    "wof:placetype":"venue"
},
  "geometry": {"coordinates":[6.9208040237,51.5210494995],"type":"Point"}
}