{
  "type": "Feature",
  "properties": {
    "iso:country":"DE",
    "sg:address":"Zschortauer Str. 14",
    "sg:city":"Leipzig",
    "sg:phone":"+49 341/9129717",
    "sg:postcode":"04129",
    "sg:province":"Sachsen",
    "wof:name":"Tabo Verges",
    "wof:placetype":"venue"
},
  "geometry": {"coordinates":[12.3966331482,51.372631073],"type":"Point"}
}