{
  "type": "Feature",
  "properties": {
    "iso:country":"DE",
    "sg:address":"Herzog Ludwig Str. 4",
    "sg:city":"Gundelfingen",
    "sg:phone":"+49 9073",
    "sg:postcode":"89423",
    "sg:province":"Bayern",
    "wof:name":"Bauplanung & Bauleitung Ludwig Schuster",
    "wof:placetype":"venue"
},
  "geometry": {"coordinates":[10.3769168854,48.5546379089],"type":"Point"}
}