{
  "type": "Feature",
  "properties": {
    "iso:country":"DE",
    "sg:address":"Am H\u00f6henblick 32",
    "sg:city":"Hirzenhain",
    "sg:phone":"+49 6045/8467",
    "sg:postcode":"63697",
    "sg:province":"Hessen",
    "wof:name":"Wolfgang Edel",
    "wof:placetype":"venue"
},
  "geometry": {"coordinates":[9.135328,50.38612],"type":"Point"}
}