{
  "type": "Feature",
  "properties": {
    "iso:country":"DE",
    "sg:address":"Rabenweg 11",
    "sg:city":"Magdeburg",
    "sg:phone":"+49 391/7329849",
    "sg:postcode":"39110",
    "sg:province":"Sachsen-Anhalt",
    "wof:name":"Jens Tetzlaff",
    "wof:placetype":"venue"
},
  "geometry": {"coordinates":[11.5949668884,52.1364631653],"type":"Point"}
}