{
  "type": "Feature",
  "properties": {
    "iso:country":"DE",
    "sg:address":"Untere Industriestr. 4",
    "sg:city":"Lichtenau",
    "sg:phone":"+49 9827/92960",
    "sg:postcode":"91586",
    "sg:province":"Bayern",
    "wof:name":"Leo Karas Gmbh & Co. Kg",
    "wof:placetype":"venue"
},
  "geometry": {"coordinates":[10.690123,49.276047],"type":"Point"}
}