{
  "type": "Feature",
  "properties": {
    "iso:country":"DE",
    "sg:address":"Stolberger Str. 351-353",
    "sg:city":"K\u00f6ln",
    "sg:postcode":"50933",
    "sg:province":"Nordrhein-Westfalen",
    "wof:name":"Fb Industrie-verm\u00f6gens-ver- Waltung Und Beteiligung Gmbh",
    "wof:placetype":"venue"
},
  "geometry": {"coordinates":[6.887898,50.942318],"type":"Point"}
}