{
  "type": "Feature",
  "properties": {
    "iso:country":"DE",
    "sg:address":"Wilmiusstr. 20",
    "sg:city":"Kempen",
    "sg:postcode":"47906",
    "sg:province":"Nordrhein-Westfalen",
    "wof:name":"Peters & Sassen Bauunternehmung Gmbh",
    "wof:placetype":"venue"
},
  "geometry": {"coordinates":[6.422914,51.358746],"type":"Point"}
}