{
  "type": "Feature",
  "properties": {
    "iso:country":"DE",
    "sg:address":"Friedensstr. 71",
    "sg:city":"Ebhausen",
    "sg:phone":"+49 7458/7628",
    "sg:postcode":"72224",
    "sg:province":"Baden-W\u00fcrttemberg",
    "wof:name":"Waldemar Wagner Architekt",
    "wof:placetype":"venue"
},
  "geometry": {"coordinates":[8.683943,48.584591],"type":"Point"}
}