{
  "type": "Feature",
  "properties": {
    "iso:country":"DE",
    "sg:address":"Daimlerstr. 10",
    "sg:city":"Wiernsheim",
    "sg:phone":"+49 7044/6977",
    "sg:postcode":"75446",
    "sg:province":"Baden-W\u00fcrttemberg",
    "wof:name":"Martin Dihlmann Masseur",
    "wof:placetype":"venue"
},
  "geometry": {"coordinates":[8.844244,48.891228],"type":"Point"}
}