{
  "type": "Feature",
  "properties": {
    "iso:country":"DE",
    "sg:address":"Zum T\u00f6fatt 4a",
    "sg:city":"Osnabr\u00fcck",
    "sg:phone":"+49 541/59095",
    "sg:postcode":"49082",
    "sg:province":"Niedersachsen",
    "wof:name":"Dietrich Und Helmut Witte Gmbh & Co. Kg",
    "wof:placetype":"venue"
},
  "geometry": {"coordinates":[8.0239953995,52.2367095947],"type":"Point"}
}