{
  "type": "Feature",
  "properties": {
    "iso:country":"DE",
    "sg:address":"Rosenthaler Str. 15",
    "sg:city":"Peine",
    "sg:phone":"+49 5171/12356",
    "sg:postcode":"31224",
    "sg:province":"Niedersachsen",
    "wof:name":"Sunset",
    "wof:placetype":"venue"
},
  "geometry": {"coordinates":[10.224756,52.323265],"type":"Point"}
}