{
  "type": "Feature",
  "properties": {
    "iso:country":"DE",
    "sg:address":"Fabrikweg 11",
    "sg:city":"Coburg",
    "sg:postcode":"96450",
    "sg:province":"Bayern",
    "wof:name":"Aldi Gmbh & Co. Kg",
    "wof:placetype":"venue"
},
  "geometry": {"coordinates":[10.9795198441,50.2288703918],"type":"Point"}
}