{
  "type": "Feature",
  "properties": {
    "iso:country":"DE",
    "sg:address":"Tannenbergstr. 7",
    "sg:city":"Gelsenkirchen",
    "sg:phone":"+49 209/42673",
    "sg:postcode":"45881",
    "sg:province":"Nordrhein-Westfalen",
    "wof:name":"Ruth Lorenz",
    "wof:placetype":"venue"
},
  "geometry": {"coordinates":[7.0778579712,51.5162582397],"type":"Point"}
}