{
  "type": "Feature",
  "properties": {
    "iso:country":"DE",
    "sg:address":"M\u00fchlenstr. 13",
    "sg:city":"Emstek",
    "sg:phone":"+49 4945/5188700",
    "sg:postcode":"49685",
    "sg:province":"Niedersachsen",
    "wof:name":"Alltech (deutschland) Gmbh",
    "wof:placetype":"venue"
},
  "geometry": {"coordinates":[10.3069,53.948708],"type":"Point"}
}