{
  "type": "Feature",
  "properties": {
    "iso:country":"DE",
    "sg:address":"Fuggerstr. 9",
    "sg:city":"Roth",
    "sg:phone":"+49 9171/2691",
    "sg:postcode":"91154",
    "sg:province":"Bayern",
    "wof:name":"Alfen Fahrzeugtechnik Gmbh",
    "wof:placetype":"venue"
},
  "geometry": {"coordinates":[11.1089801788,49.250667572],"type":"Point"}
}