{
  "type": "Feature",
  "properties": {
    "iso:country":"DE",
    "sg:address":"Wachmannstr. 9",
    "sg:city":"Bremen",
    "sg:phone":"+49 421/34030",
    "sg:postcode":"28209",
    "sg:province":"Bremen",
    "wof:name":"Beratungsstelle F\u00fcr Alkohol-drogenprobleme",
    "wof:placetype":"venue"
},
  "geometry": {"coordinates":[8.826846,53.084621],"type":"Point"}
}