{
  "type": "Feature",
  "properties": {
    "iso:country":"DE",
    "sg:address":"Siemensstr. 1-3",
    "sg:city":"F\u00fcrth",
    "sg:phone":"+49 911/9974212",
    "sg:postcode":"90766",
    "sg:province":"Bayern",
    "wof:name":"Pilkington Deutschland Ag",
    "wof:placetype":"venue"
},
  "geometry": {"coordinates":[10.9616718292,49.4829978943],"type":"Point"}
}