{
  "type": "Feature",
  "properties": {
    "iso:country":"DE",
    "sg:address":"M\u00fchlstr. 2",
    "sg:city":"Metzingen",
    "sg:phone":"+49 7123/4464",
    "sg:postcode":"72555",
    "sg:province":"Baden-W\u00fcrttemberg",
    "wof:name":"M. Lipp",
    "wof:placetype":"venue"
},
  "geometry": {"coordinates":[9.2826519012,48.5361404419],"type":"Point"}
}