{
  "type": "Feature",
  "properties": {
    "iso:country":"DE",
    "sg:address":"Rettenbacher Str. 7",
    "sg:city":"Stephansposching",
    "sg:phone":"+49 9931/2433",
    "sg:postcode":"94569",
    "sg:province":"Bayern",
    "wof:name":"Oskar Schlederer",
    "wof:placetype":"venue"
},
  "geometry": {"coordinates":[12.8570842743,48.8067131042],"type":"Point"}
}