{
  "type": "Feature",
  "properties": {
    "iso:country":"DE",
    "sg:address":"August-Bebel-Str. 28",
    "sg:city":"Vacha",
    "sg:phone":"+49 36962/24334",
    "sg:postcode":"36404",
    "sg:province":"Th\u00fcringen",
    "wof:name":"Dr. Med. Gert Kallenbach",
    "wof:placetype":"venue"
},
  "geometry": {"coordinates":[10.01848,50.8242],"type":"Point"}
}