{
  "type": "Feature",
  "properties": {
    "iso:country":"DE",
    "sg:address":"Liebigstr 94",
    "sg:city":"Hamburg",
    "sg:phone":"+49 40/7320055",
    "sg:postcode":"22113",
    "sg:province":"Schleswig-Holstein",
    "wof:name":"Schwenck Spedition Gmbh",
    "wof:placetype":"venue"
},
  "geometry": {"coordinates":[10.106653,53.530403],"type":"Point"}
}