{
  "type": "Feature",
  "properties": {
    "iso:country":"DE",
    "sg:address":"Dammstr. 21",
    "sg:city":"Uetze",
    "sg:phone":"+49 5173/2631",
    "sg:postcode":"31311",
    "sg:province":"Niedersachsen",
    "wof:name":"I. Gese",
    "wof:placetype":"venue"
},
  "geometry": {"coordinates":[10.2125062943,52.4732246399],"type":"Point"}
}