{
  "type": "Feature",
  "properties": {
    "iso:country":"DE",
    "sg:address":"Oranienstr. 70",
    "sg:city":"Bad Soden",
    "sg:phone":"+49 6196/63485",
    "sg:postcode":"65812",
    "sg:province":"Hessen",
    "wof:name":"Gebr. Schmidt Beteiligung Gmbh",
    "wof:placetype":"venue"
},
  "geometry": {"coordinates":[8.490908,50.143543],"type":"Point"}
}