{
  "type": "Feature",
  "properties": {
    "iso:country":"DE",
    "sg:address":"Merscheider Str. 23",
    "sg:city":"Solingen",
    "sg:phone":"+49 212/336282",
    "sg:postcode":"42699",
    "sg:province":"Nordrhein-Westfalen",
    "wof:name":"Dietlind Schwamberger",
    "wof:placetype":"venue"
},
  "geometry": {"coordinates":[7.011922,51.161339],"type":"Point"}
}