{
  "type": "Feature",
  "properties": {
    "iso:country":"DE",
    "sg:address":"Sankt Augustiner Str. 94 a",
    "sg:city":"Bonn",
    "sg:postcode":"53225",
    "sg:province":"Nordrhein-Westfalen",
    "wof:name":"Herwo Versicherungsmakler Gmbh",
    "wof:placetype":"venue"
},
  "geometry": {"coordinates":[7.1237740517,50.7449378967],"type":"Point"}
}