{
  "type": "Feature",
  "properties": {
    "iso:country":"DE",
    "sg:address":"Heinsberger Str. 29a",
    "sg:city":"Hilchenbach",
    "sg:phone":"+49 2733/2679",
    "sg:postcode":"57271",
    "sg:province":"Nordrhein-Westfalen",
    "wof:name":"H. -d. Schmidt Immobilienmakler",
    "wof:placetype":"venue"
},
  "geometry": {"coordinates":[8.1140184402,50.9999313354],"type":"Point"}
}