{
  "type": "Feature",
  "properties": {
    "iso:country":"DE",
    "sg:address":"Dorfstr. 1",
    "sg:city":"Emmelsb\u00fcll-Horsb\u00fcll",
    "sg:phone":"+49 4665/453",
    "sg:postcode":"25924",
    "sg:province":"Schleswig-Holstein",
    "wof:name":"Frieder Ipsen",
    "wof:placetype":"venue"
},
  "geometry": {"coordinates":[8.69899,54.810249],"type":"Point"}
}