{
  "type": "Feature",
  "properties": {
    "iso:country":"DE",
    "sg:address":"Mittelstr. 25",
    "sg:city":"D\u00fcsseldorf",
    "sg:phone":"+49 211/327053",
    "sg:postcode":"40213",
    "sg:province":"Nordrhein-Westfalen",
    "wof:name":"J. Hinkel",
    "wof:placetype":"venue"
},
  "geometry": {"coordinates":[6.774118,51.224335],"type":"Point"}
}