{
  "type": "Feature",
  "properties": {
    "iso:country":"DE",
    "sg:address":"Schrodweg 4",
    "sg:city":"Weil der Stadt",
    "sg:phone":"+49 700 2445 2633",
    "sg:postcode":"71263",
    "sg:province":"Baden-W\u00fcrttemberg",
    "wof:name":"Black Dj Meeting",
    "wof:placetype":"venue"
},
  "geometry": {"coordinates":[8.850822,48.775585],"type":"Point"}
}