{
  "type": "Feature",
  "properties": {
    "iso:country":"DE",
    "sg:address":"Benesisstr. 8-12",
    "sg:city":"K\u00f6ln",
    "sg:phone":"+49 221/9252380",
    "sg:postcode":"50672",
    "sg:province":"Nordrhein-Westfalen",
    "wof:name":"Valbert Und Vormbrock Rechtsanw\u00e4lte",
    "wof:placetype":"venue"
},
  "geometry": {"coordinates":[6.9427337646,50.9361228943],"type":"Point"}
}