{
  "type": "Feature",
  "properties": {
    "iso:country":"DE",
    "sg:address":"Meyner Str. 24",
    "sg:city":"Schafflund",
    "sg:postcode":"24980",
    "sg:province":"Schleswig-Holstein",
    "wof:name":"Svend Carstensen & Peter K\u00fchn Verwaltungs Gmbh",
    "wof:placetype":"venue"
},
  "geometry": {"coordinates":[9.191897,54.757637],"type":"Point"}
}