{
  "type": "Feature",
  "properties": {
    "iso:country":"DE",
    "sg:address":"Blumenweg 12",
    "sg:city":"Torgau",
    "sg:phone":"+49 3421/713524",
    "sg:postcode":"04860",
    "sg:province":"Sachsen",
    "wof:name":"C. H\u00f6fner",
    "wof:placetype":"venue"
},
  "geometry": {"coordinates":[12.983682,51.555367],"type":"Point"}
}