{
  "type": "Feature",
  "properties": {
    "iso:country":"DE",
    "sg:address":"Probsteistr. 11",
    "sg:city":"Teuchern",
    "sg:phone":"+49 34443/31003",
    "sg:postcode":"06682",
    "sg:province":"Sachsen-Anhalt",
    "wof:name":"Antena Bestattungen Gerhardt Gmbh",
    "wof:placetype":"venue"
},
  "geometry": {"coordinates":[12.019516,51.122498],"type":"Point"}
}