{
  "type": "Feature",
  "properties": {
    "iso:country":"DE",
    "sg:address":"An der Vogelstange 17b",
    "sg:city":"Erkelenz",
    "sg:phone":"+49 2435/549",
    "sg:postcode":"41812",
    "sg:province":"Nordrhein-Westfalen",
    "wof:name":"Norbert Schmidt Heilpraktiker",
    "wof:placetype":"venue"
},
  "geometry": {"coordinates":[6.326789856,51.0342559814],"type":"Point"}
}