{
  "type": "Feature",
  "properties": {
    "iso:country":"DE",
    "sg:address":"T\u00f6ngesstr. 40",
    "sg:city":"Mainz",
    "sg:phone":"+49 6136/45512",
    "sg:postcode":"55129",
    "sg:province":"Rheinland-Pfalz",
    "wof:name":"Eberswalde",
    "wof:placetype":"venue"
},
  "geometry": {"coordinates":[8.2582902908,49.9169006348],"type":"Point"}
}