{
  "type": "Feature",
  "properties": {
    "iso:country":"DE",
    "sg:address":"Zum Heubach 7",
    "sg:city":"Reken",
    "sg:phone":"+49 2864/1389",
    "sg:postcode":"48734",
    "sg:province":"Nordrhein-Westfalen",
    "wof:name":"A. Krampe",
    "wof:placetype":"venue"
},
  "geometry": {"coordinates":[7.099255085,51.8460197449],"type":"Point"}
}