{
  "type": "Feature",
  "properties": {
    "iso:country":"DE",
    "sg:address":"Mainburger Str. 3",
    "sg:city":"Volkenschwand",
    "sg:phone":"+49 8754/1403",
    "sg:postcode":"84106",
    "sg:province":"Bayern",
    "wof:name":"Hainz Und Schuberthan",
    "wof:placetype":"venue"
},
  "geometry": {"coordinates":[11.8719158173,48.600025177],"type":"Point"}
}