{
  "type": "Feature",
  "properties": {
    "iso:country":"DE",
    "sg:address":"Kutenhauser Dorfstr. 39",
    "sg:city":"Minden",
    "sg:phone":"+49 571/47897",
    "sg:postcode":"32425",
    "sg:province":"Nordrhein-Westfalen",
    "wof:name":"Heinrich Kanning",
    "wof:placetype":"venue"
},
  "geometry": {"coordinates":[8.911011,52.306427],"type":"Point"}
}