{
  "type": "Feature",
  "properties": {
    "iso:country":"DE",
    "sg:address":"Schlo\u00dfstra\u00dfe 70",
    "sg:city":"M\u00fchlhausen-Ehingen",
    "sg:postcode":"78259",
    "sg:province":"Baden-W\u00fcrttemberg",
    "wof:name":"Staufer L\u00d6wen - Reservistenmarschgruppe Im Vdrbw",
    "wof:placetype":"venue"
},
  "geometry": {"coordinates":[8.804884,47.811695],"type":"Point"}
}