{
  "type": "Feature",
  "properties": {
    "iso:country":"DE",
    "sg:address":"Trappenbergstr. 47",
    "sg:city":"Essen",
    "sg:postcode":"45134",
    "sg:province":"Nordrhein-Westfalen",
    "wof:name":"Forst Gesell. F\u00fcr Consulting Forst- U. Holzwirtschaftliche",
    "wof:placetype":"venue"
},
  "geometry": {"coordinates":[7.022788,51.413586],"type":"Point"}
}