{
  "type": "Feature",
  "properties": {
    "iso:country":"DE",
    "sg:address":"Schumannweg 10",
    "sg:city":"D\u00fcren",
    "sg:postcode":"52349",
    "sg:province":"Nordrhein-Westfalen",
    "wof:name":"J\u00f6rg Baumann Rechtsanwalt",
    "wof:placetype":"venue"
},
  "geometry": {"coordinates":[6.4940390587,50.791217804],"type":"Point"}
}