{
  "type": "Feature",
  "properties": {
    "iso:country":"DE",
    "sg:address":"Johanna-Senfter-Str. 13",
    "sg:city":"Oppenheim",
    "sg:phone":"+49 6133/926334",
    "sg:postcode":"55276",
    "sg:province":"Rheinland-Pfalz",
    "wof:name":"R. Petry Rechtsanwalt",
    "wof:placetype":"venue"
},
  "geometry": {"coordinates":[8.3609075546,49.8488922119],"type":"Point"}
}