{
  "type": "Feature",
  "properties": {
    "iso:country":"DE",
    "sg:address":"Schiffweilerstr. 13",
    "sg:city":"Braunschweig",
    "sg:phone":"+49 531/54445",
    "sg:postcode":"38116",
    "sg:province":"Niedersachsen",
    "wof:name":"Adolf Mahn Ingenieur",
    "wof:placetype":"venue"
},
  "geometry": {"coordinates":[10.4837188721,52.2756576538],"type":"Point"}
}