{
  "type": "Feature",
  "properties": {
    "iso:country":"DE",
    "sg:address":"Dr.-Heinrich-Jasper-Str. 27",
    "sg:city":"Wolfenb\u00fcttel",
    "sg:phone":"+49 5331/26781",
    "sg:postcode":"38304",
    "sg:province":"Niedersachsen",
    "wof:name":"Apotheke Am Waisenhaus",
    "wof:placetype":"venue"
},
  "geometry": {"coordinates":[10.525062,52.164131],"type":"Point"}
}