{
  "type": "Feature",
  "properties": {
    "iso:country":"DE",
    "sg:address":"Emerkinger Str. 14",
    "sg:city":"Munderkingen",
    "sg:phone":"+49 7393/95240",
    "sg:postcode":"89597",
    "sg:province":"Baden-W\u00fcrttemberg",
    "wof:name":"Edel-tabak-weine Gmbh",
    "wof:placetype":"venue"
},
  "geometry": {"coordinates":[9.6444702148,48.2307815552],"type":"Point"}
}