{
  "type": "Feature",
  "properties": {
    "iso:country":"DE",
    "sg:address":"Bahnhofstr. 55",
    "sg:city":"Ellern",
    "sg:phone":"+49 4967/64380",
    "sg:postcode":"55497",
    "sg:province":"Rheinland-Pfalz",
    "wof:name":"Holzindustrie Hunsr\u00dcck Gmbh Mathias Tenhaeff",
    "wof:placetype":"venue"
},
  "geometry": {"coordinates":[7.6109890938,49.9911231995],"type":"Point"}
}