{
  "type": "Feature",
  "properties": {
    "iso:country":"DE",
    "sg:address":"Luitpoldstr. 18",
    "sg:city":"Erlangen",
    "sg:phone":"+49 9131/25259",
    "sg:postcode":"91052",
    "sg:province":"Bayern",
    "wof:name":"Gertrud Dietz Papier- Und Schreibwaren",
    "wof:placetype":"venue"
},
  "geometry": {"coordinates":[11.01596,49.596951],"type":"Point"}
}