{
  "type": "Feature",
  "properties": {
    "iso:country":"DE",
    "sg:address":"Roland-Betsch-Str. 8",
    "sg:city":"Pirmasens",
    "sg:phone":"+49 6331/66185",
    "sg:postcode":"66954",
    "sg:province":"Rheinland-Pfalz",
    "wof:name":"Ev. Pfarramt Pirmasens Mitte 2",
    "wof:placetype":"venue"
},
  "geometry": {"coordinates":[7.5973858833,49.2020111084],"type":"Point"}
}