{
  "type": "Feature",
  "properties": {
    "iso:country":"DE",
    "sg:address":"Zum Blech 4",
    "sg:city":"Heroldsberg",
    "sg:phone":"+49 911/956890",
    "sg:postcode":"90562",
    "sg:province":"Bayern",
    "wof:name":"Hans Wi\u00dfmeier Ingenieur",
    "wof:placetype":"venue"
},
  "geometry": {"coordinates":[11.160700798,49.5357170105],"type":"Point"}
}