{"geometry":{"type":"Point","coordinates":[8.117176,49.197781]},"type":"Feature","id":102560649,"bbox":[8.117176,49.197781,8.117176,49.197781],"properties":{"sg:province":"Rheinland-Pfalz","geom:longitude":8.117176,"wof:breaches":[],"sg:href":"http://api.simplegeo.com/1.0/features/SG_6WTeqqJ5wa0jwEfeLZAwh9_49.197781_8.117176@1306268793.json","sg:owner":"simplegeo","sg:postcode":"76829","geom:latitude":49.197781,"sg:classifiers":[],"sg:address":"Ostbahnstr. 10::","sg:phone":"+49 4963/41180","wof:hierarchy":[{"locality_id":101760711,"venue_id":102560649,"country_id":85633111,"region_id":85682491,"county_id":102063399}],"geom:area":0.000000,"sg:city":"Landau","wof:lastmodified":1438093319,"iso:country":"DE","wof:geomhash":"cef403e563f155d4ae8a5e3613df61c5","wof:name":"Sparkasse Suedliche Weinstrasse Inlandau I D Pfalz","wof:belongsto":[101760711,85633111,85682491,102063399],"src:geom":"simplegeo","wof:placetype":"venue","wof:supersedes":[],"wof:id":102560649,"wof:superseded_by":[],"wof:concordances":{"sg:id":"SG_6WTeqqJ5wa0jwEfeLZAwh9_49.197781_8.117176@1306268793"},"wof:parent_id":101760711}}