{
  "type": "Feature",
  "properties": {
    "iso:country":"DE",
    "sg:address":"Ostbahnstr. 10::",
    "sg:city":"Landau",
    "sg:href":"http://api.simplegeo.com/1.0/features/SG_6WTeqqJ5wa0jwEfeLZAwh9_49.197781_8.117176@1306268793.json",
    "sg:phone":"+49 4963/41180",
    "sg:postcode":"76829",
    "sg:province":"Rheinland-Pfalz",
    "wof:name":"Sparkasse Suedliche Weinstrasse Inlandau I D Pfalz",
    "wof:placetype":"venue"
},
  "geometry": {"coordinates":[8.117176,49.197781],"type":"Point"}
}