{
  "type": "Feature",
  "properties": {
    "iso:country":"DE",
    "sg:address":"Raiffeisenstr. 11",
    "sg:city":"Grafenrheinfeld",
    "sg:phone":"+49 9723/3626",
    "sg:postcode":"97506",
    "sg:province":"Bayern",
    "wof:name":"Herbert Schmitt",
    "wof:placetype":"venue"
},
  "geometry": {"coordinates":[10.1923141479,50.006072998],"type":"Point"}
}