{
  "type": "Feature",
  "properties": {
    "iso:country":"DE",
    "sg:address":"Br\u00e4unleinsberg 7",
    "sg:city":"Ottensoos",
    "sg:phone":"+49 9123/81011",
    "sg:postcode":"91242",
    "sg:province":"Bayern",
    "wof:name":"Hages\u00dcd Interspice Gew\u00dcrzwerke Gmbh & Co",
    "wof:placetype":"venue"
},
  "geometry": {"coordinates":[11.3312101364,49.5175094604],"type":"Point"}
}