{
  "type": "Feature",
  "properties": {
    "iso:country":"DE",
    "sg:address":"Heiderader Weg 5",
    "sg:city":"G\u00fcby",
    "sg:postcode":"24357",
    "sg:province":"Schleswig-Holstein",
    "wof:name":"Holger Untermann Agrar-hygiene-service Gmbh",
    "wof:placetype":"venue"
},
  "geometry": {"coordinates":[9.6623830795,54.4848022461],"type":"Point"}
}