{
  "type": "Feature",
  "properties": {
    "iso:country":"DE",
    "sg:address":"Obere Breite Str. 31",
    "sg:city":"Ravensburg",
    "sg:phone":"+49 751/13268",
    "sg:postcode":"88212",
    "sg:province":"Baden-W\u00fcrttemberg",
    "wof:name":"China-restaurant Jade-garten",
    "wof:placetype":"venue"
},
  "geometry": {"coordinates":[9.6120538712,47.7838592529],"type":"Point"}
}