{
  "type": "Feature",
  "properties": {
    "iso:country":"DE",
    "sg:address":"Holter Str. 90",
    "sg:city":"Oerlinghausen",
    "sg:phone":"+49 5202/7070",
    "sg:postcode":"33813",
    "sg:province":"Nordrhein-Westfalen",
    "wof:name":"Hanning Elektro-werke Beteiligungs Gmbh",
    "wof:placetype":"venue"
},
  "geometry": {"coordinates":[8.652365,51.944862],"type":"Point"}
}