{
  "type": "Feature",
  "properties": {
    "iso:country":"DE",
    "sg:address":"Martinstr 1",
    "sg:city":"Amtzell",
    "sg:phone":"+49 7520/923600",
    "sg:postcode":"88279",
    "sg:province":"Baden-W\u00fcrttemberg",
    "wof:name":"I.m.e.s. Gesellschaft F\u00fcr Innovative Me\u00df-, Erkundungs- Und Sanierungtechnologien Mbh",
    "wof:placetype":"venue"
},
  "geometry": {"coordinates":[9.74716,47.705029],"type":"Point"}
}