{
  "type": "Feature",
  "properties": {
    "iso:country":"DE",
    "sg:address":"Sandh\u00f6he 16",
    "sg:city":"Reinbek",
    "sg:phone":"+49 40/7104340",
    "sg:postcode":"21465",
    "sg:province":"Schleswig-Holstein",
    "wof:name":"Wolf-r\u00fcdiger Mahling",
    "wof:placetype":"venue"
},
  "geometry": {"coordinates":[10.2431926727,53.556224823],"type":"Point"}
}