{
  "type": "Feature",
  "properties": {
    "iso:country":"DE",
    "sg:address":"Hohenkr\u00e4henstr. 5",
    "sg:city":"Singen",
    "sg:phone":"+49 7731/61332",
    "sg:postcode":"78224",
    "sg:province":"Baden-W\u00fcrttemberg",
    "wof:name":"Georg H\u00e4gele",
    "wof:placetype":"venue"
},
  "geometry": {"coordinates":[8.8321018219,47.7641563416],"type":"Point"}
}