{
  "type": "Feature",
  "properties": {
    "iso:country":"DE",
    "sg:address":"Zirbelstr. 64",
    "sg:city":"Augsburg",
    "sg:phone":"+49 821/411051",
    "sg:postcode":"86154",
    "sg:province":"Bayern",
    "wof:name":"Walter Deffner",
    "wof:placetype":"venue"
},
  "geometry": {"coordinates":[10.8788299561,48.3976287842],"type":"Point"}
}