{
  "type": "Feature",
  "properties": {
    "iso:country":"DE",
    "sg:address":"An der Kleibscheibe 8",
    "sg:city":"B\u00fcdingen",
    "sg:postcode":"63654",
    "sg:province":"Hessen",
    "wof:name":"Five Elements Ag",
    "wof:placetype":"venue"
},
  "geometry": {"coordinates":[9.112628,50.274933],"type":"Point"}
}