{
  "type": "Feature",
  "properties": {
    "iso:country":"DE",
    "sg:address":"Lauter 15",
    "sg:city":"Suhl",
    "sg:phone":"+49 3681/423452",
    "sg:postcode":"98528",
    "sg:province":"Th\u00fcringen",
    "wof:name":"Ehrlich Immobilienmakler",
    "wof:placetype":"venue"
},
  "geometry": {"coordinates":[10.7218999863,50.6246986389],"type":"Point"}
}