{
  "type": "Feature",
  "properties": {
    "iso:country":"DE",
    "sg:address":"An der Elbaue 20",
    "sg:city":"Pirna",
    "sg:phone":"+49 3501/521019",
    "sg:postcode":"01796",
    "sg:province":"Sachsen",
    "wof:name":"Susanne Heyden",
    "wof:placetype":"venue"
},
  "geometry": {"coordinates":[13.892971,50.96891],"type":"Point"}
}