{
  "type": "Feature",
  "properties": {
    "iso:country":"DE",
    "sg:address":"N\u00f6rdliche Ringstr. 150",
    "sg:city":"G\u00f6ppingen",
    "sg:phone":"+49 7161/23636",
    "sg:postcode":"73033",
    "sg:province":"Baden-W\u00fcrttemberg",
    "wof:name":"Rolf Witzschel",
    "wof:placetype":"venue"
},
  "geometry": {"coordinates":[9.6386861801,48.7101593018],"type":"Point"}
}