{
  "type": "Feature",
  "properties": {
    "iso:country":"DE",
    "sg:address":"Saarwellinger Str. 105",
    "sg:city":"Schwalbach",
    "sg:phone":"+49 6831/58891",
    "sg:postcode":"66773",
    "sg:province":"Saarland",
    "wof:name":"Manfred Schindler",
    "wof:placetype":"venue"
},
  "geometry": {"coordinates":[6.82145,49.313801],"type":"Point"}
}