{
  "type": "Feature",
  "properties": {
    "iso:country":"DE",
    "sg:address":"Maximilianstr 43",
    "sg:city":"M\u00fcnchen",
    "sg:phone":"+49 89/2199140",
    "sg:postcode":"80538",
    "sg:province":"Bayern",
    "wof:name":"Savecall Telecommunication Consulting Gmbh",
    "wof:placetype":"venue"
},
  "geometry": {"coordinates":[11.5872402191,48.1382026672],"type":"Point"}
}