{
  "type": "Feature",
  "properties": {
    "iso:country":"DE",
    "sg:address":"Ostseestr. 2",
    "sg:city":"Bonn",
    "sg:phone":"+49 228/373492",
    "sg:postcode":"53175",
    "sg:province":"Nordrhein-Westfalen",
    "wof:name":"Karl Schumpe Ingenieur",
    "wof:placetype":"venue"
},
  "geometry": {"coordinates":[7.1548748016,50.7007522583],"type":"Point"}
}