{
  "type": "Feature",
  "properties": {
    "iso:country":"DE",
    "sg:address":"Industriestr. 16",
    "sg:city":"Vilsbiburg",
    "sg:phone":"+49 8741/1792",
    "sg:postcode":"84137",
    "sg:province":"Bayern",
    "wof:name":"Industrieprodukte Loosberg Gmbh",
    "wof:placetype":"venue"
},
  "geometry": {"coordinates":[12.3455457687,48.4451255798],"type":"Point"}
}