{
  "type": "Feature",
  "properties": {
    "iso:country":"DE",
    "sg:address":"Rudolf-Diesel-Str 11",
    "sg:city":"Erbach",
    "sg:phone":"+49 6062/4517",
    "sg:postcode":"64711",
    "sg:province":"Hessen",
    "wof:name":"Odenwald-pool Gmbh",
    "wof:placetype":"venue"
},
  "geometry": {"coordinates":[8.9905862808,49.6704444885],"type":"Point"}
}