{
  "type": "Feature",
  "properties": {
    "iso:country":"DE",
    "sg:address":"Enzianstra\u00dfe 13 (kein Ladenverkauf%21)",
    "sg:city":"Marquartstein",
    "sg:phone":"+49 8641/63306",
    "sg:postcode":"83250",
    "sg:province":"Bayern",
    "wof:name":"Chiemseenet, Chiemsee Communication & Computer",
    "wof:placetype":"venue"
},
  "geometry": {"coordinates":[12.461819,47.762856],"type":"Point"}
}