{
  "type": "Feature",
  "properties": {
    "iso:country":"DE",
    "sg:address":"Edelwei\u00dfstr. 11",
    "sg:city":"Metten",
    "sg:phone":"+49 991/90581",
    "sg:postcode":"94526",
    "sg:province":"Bayern",
    "wof:name":"Georg Bauer",
    "wof:placetype":"venue"
},
  "geometry": {"coordinates":[12.9082717896,48.8613395691],"type":"Point"}
}