{
  "type": "Feature",
  "properties": {
    "iso:country":"DE",
    "sg:address":"Franz-Vaahsen-Weg 5a",
    "sg:city":"D\u00fcsseldorf",
    "sg:postcode":"40489",
    "sg:province":"Nordrhein-Westfalen",
    "wof:name":"Ama Video Productions Gmbh",
    "wof:placetype":"venue"
},
  "geometry": {"coordinates":[6.7424879074,51.3218307495],"type":"Point"}
}