{
  "type": "Feature",
  "properties": {
    "iso:country":"DE",
    "sg:address":"Im Hinterfeld 7 a",
    "sg:city":"B\u00fcdingen",
    "sg:phone":"+49 6041/90262",
    "sg:postcode":"63654",
    "sg:province":"Hessen",
    "wof:name":"Wolfgang Sonntag",
    "wof:placetype":"venue"
},
  "geometry": {"coordinates":[9.0326986313,50.2885665894],"type":"Point"}
}