{
  "type": "Feature",
  "properties": {
    "iso:country":"DE",
    "sg:address":"Henleinstr. 13a",
    "sg:city":"Stuhr",
    "sg:phone":"+49 4942/1871140",
    "sg:postcode":"28816",
    "sg:province":"Niedersachsen",
    "wof:name":"Dipolique Gmbh",
    "wof:placetype":"venue"
},
  "geometry": {"coordinates":[8.796586,53.025658],"type":"Point"}
}