{
  "type": "Feature",
  "properties": {
    "iso:country":"DE",
    "sg:address":"Tripweg 13",
    "sg:city":"Hannover",
    "sg:phone":"+49 511/5416850",
    "sg:postcode":"30627",
    "sg:province":"Niedersachsen",
    "wof:name":"E. Muegge Rechtsanwalt",
    "wof:placetype":"venue"
},
  "geometry": {"coordinates":[9.8127670288,52.3926544189],"type":"Point"}
}