{
  "type": "Feature",
  "properties": {
    "iso:country":"DE",
    "sg:address":"Niederhohndorfer Str. 64",
    "sg:city":"Zwickau",
    "sg:phone":"+49 375/302263",
    "sg:postcode":"08058",
    "sg:province":"Sachsen",
    "wof:name":"Caro Bautr\u00e4ger Gmbh",
    "wof:placetype":"venue"
},
  "geometry": {"coordinates":[12.4619503021,50.752243042],"type":"Point"}
}