{
  "type": "Feature",
  "properties": {
    "iso:country":"DE",
    "sg:address":"Herbert-Hellmann-Allee 12",
    "sg:city":"Bad Krozingen",
    "sg:phone":"+49 7633/40080",
    "sg:postcode":"79189",
    "sg:province":"Baden-W\u00fcrttemberg",
    "wof:name":"Kur Und B\u00e4der Gmbh",
    "wof:placetype":"venue"
},
  "geometry": {"coordinates":[7.6914300919,47.9189491272],"type":"Point"}
}