{
  "type": "Feature",
  "properties": {
    "iso:country":"DE",
    "sg:address":"Morgensternstr. 18",
    "sg:city":"Frankfurt",
    "sg:postcode":"60596",
    "sg:province":"Hessen",
    "wof:name":"Concept Consult Gmbh",
    "wof:placetype":"venue"
},
  "geometry": {"coordinates":[8.6779251099,50.101272583],"type":"Point"}
}