{
  "type": "Feature",
  "properties": {
    "iso:country":"DE",
    "sg:address":"Niendorf 3",
    "sg:city":"Insel Poel",
    "sg:phone":"+49 38425/20345",
    "sg:postcode":"23999",
    "sg:province":"Mecklenburg-Vorpommern",
    "wof:name":"W. Beyer",
    "wof:placetype":"venue"
},
  "geometry": {"coordinates":[11.4500780106,53.9910545349],"type":"Point"}
}