{
  "type": "Feature",
  "properties": {
    "iso:country":"DE",
    "sg:address":"Lohmannstr 21",
    "sg:city":"K\u00f6then",
    "sg:phone":"+49 3496/212385",
    "sg:postcode":"06366",
    "sg:province":"Sachsen-Anhalt",
    "wof:name":"Heisada Heizungs-sanit\u00e4r Dacheindeckungsgesellschaft Mbh",
    "wof:placetype":"venue"
},
  "geometry": {"coordinates":[11.9842329025,51.7462120056],"type":"Point"}
}