{
  "type": "Feature",
  "properties": {
    "iso:country":"DE",
    "sg:address":"Marktplatz 5",
    "sg:city":"Burgbernheim",
    "sg:phone":"+49 9843/1397",
    "sg:postcode":"91593",
    "sg:province":"Bayern",
    "wof:name":"Hilde Huestegge",
    "wof:placetype":"venue"
},
  "geometry": {"coordinates":[10.3227720261,49.4512023926],"type":"Point"}
}