{
  "type": "Feature",
  "properties": {
    "iso:country":"DE",
    "sg:address":"Br\u00fchlstr. 11",
    "sg:city":"H\u00fclben",
    "sg:phone":"+49 7125/5778",
    "sg:postcode":"72584",
    "sg:province":"Baden-W\u00fcrttemberg",
    "wof:name":"Rosa Scheu Hebamme",
    "wof:placetype":"venue"
},
  "geometry": {"coordinates":[9.410124,48.519951],"type":"Point"}
}