{
  "type": "Feature",
  "properties": {
    "iso:country":"DE",
    "sg:address":"Im Feuerh\u00e4gle 1",
    "sg:city":"T\u00fcbingen",
    "sg:phone":"+49 7071/72928",
    "sg:postcode":"72072",
    "sg:province":"Baden-W\u00fcrttemberg",
    "wof:name":"Markus Fendt Hebamme",
    "wof:placetype":"venue"
},
  "geometry": {"coordinates":[9.054168,48.503429],"type":"Point"}
}