{
  "type": "Feature",
  "properties": {
    "iso:country":"DE",
    "sg:address":"Hauptstr. 23",
    "sg:city":"Hollenbach",
    "sg:phone":"+49 8257/8649",
    "sg:postcode":"86568",
    "sg:province":"Bayern",
    "wof:name":"Strobl Gmbh",
    "wof:placetype":"venue"
},
  "geometry": {"coordinates":[11.0774316788,48.4883270264],"type":"Point"}
}