{
  "type": "Feature",
  "properties": {
    "iso:country":"DE",
    "sg:address":"Bahnhofstr. 14",
    "sg:city":"Lenggries",
    "sg:phone":"+49 8042/2608",
    "sg:postcode":"83661",
    "sg:province":"Bayern",
    "wof:name":"Hans Me\u00dfmer",
    "wof:placetype":"venue"
},
  "geometry": {"coordinates":[11.576042,47.680393],"type":"Point"}
}