{
  "type": "Feature",
  "properties": {
    "iso:country":"DE",
    "sg:address":"Zur Wasserm\u00fchle 2",
    "sg:city":"Magdeburg",
    "sg:phone":"+49 391/7392702",
    "sg:postcode":"39110",
    "sg:province":"Sachsen-Anhalt",
    "wof:name":"Dr. Med. E.-b. Wischeropp",
    "wof:placetype":"venue"
},
  "geometry": {"coordinates":[11.563941,52.128948],"type":"Point"}
}