{
  "type": "Feature",
  "properties": {
    "iso:country":"DE",
    "sg:address":"Bergerhof",
    "sg:city":"Brechen",
    "sg:phone":"+49 6431/45739",
    "sg:postcode":"65611",
    "sg:province":"Hessen",
    "wof:name":"Lothar Roth",
    "wof:placetype":"venue"
},
  "geometry": {"coordinates":[8.119959,50.36105],"type":"Point"}
}