{
  "type": "Feature",
  "properties": {
    "iso:country":"DE",
    "sg:address":"Passauer Str. 29",
    "sg:city":"Neuhaus",
    "sg:phone":"+49 8503/922955",
    "sg:postcode":"94152",
    "sg:province":"Bayern",
    "wof:name":"Ferdinand Obpacher",
    "wof:placetype":"venue"
},
  "geometry": {"coordinates":[13.4201002121,48.4609794617],"type":"Point"}
}