{
  "type": "Feature",
  "properties": {
    "iso:country":"DE",
    "sg:address":"Eutighofer Str. 124",
    "sg:city":"Schw\u00e4bisch Gm\u00fcnd",
    "sg:phone":"+49 7171/61351",
    "sg:postcode":"73525",
    "sg:province":"Baden-W\u00fcrttemberg",
    "wof:name":"China Restaurant Peking",
    "wof:placetype":"venue"
},
  "geometry": {"coordinates":[9.7689647675,48.7862739563],"type":"Point"}
}