{
  "type": "Feature",
  "properties": {
    "iso:country":"DE",
    "sg:address":"Teichstr. 8",
    "sg:city":"Aachen",
    "sg:phone":"+49 241/14130",
    "sg:postcode":"52074",
    "sg:province":"Nordrhein-Westfalen",
    "wof:name":"Ruscheweyh Consult Gmbh",
    "wof:placetype":"venue"
},
  "geometry": {"coordinates":[6.0601081848,50.79429245],"type":"Point"}
}