{
  "type": "Feature",
  "properties": {
    "iso:country":"DE",
    "sg:address":"Eberhardstr. 47",
    "sg:city":"Stuttgart",
    "sg:phone":"+49 711/242487",
    "sg:postcode":"70173",
    "sg:province":"Baden-W\u00fcrttemberg",
    "wof:name":"B. Giess-lory",
    "wof:placetype":"venue"
},
  "geometry": {"coordinates":[9.177582,48.773174],"type":"Point"}
}