{
  "type": "Feature",
  "properties": {
    "iso:country":"DE",
    "sg:address":"Hauptstr. 45",
    "sg:city":"Oslo\u00df",
    "sg:phone":"+49 5362/7688",
    "sg:postcode":"38557",
    "sg:province":"Niedersachsen",
    "wof:name":"Ernst G. Possiel",
    "wof:placetype":"venue"
},
  "geometry": {"coordinates":[10.682528,52.468811],"type":"Point"}
}