{
  "type": "Feature",
  "properties": {
    "iso:country":"DE",
    "sg:address":"Potsdamer Str. 88",
    "sg:city":"Berlin",
    "sg:phone":"+49 30/254350",
    "sg:postcode":"10785",
    "sg:province":"Berlin",
    "wof:name":"Aktiv Radio Berlin Gmbh",
    "wof:placetype":"venue"
},
  "geometry": {"coordinates":[13.36523,52.502857],"type":"Point"}
}