{
  "type": "Feature",
  "properties": {
    "iso:country":"DE",
    "sg:address":"B\u00fcrgermeister-Heine-Str. 11",
    "sg:city":"Celle",
    "sg:phone":"+49 5141/52305",
    "sg:postcode":"29229",
    "sg:province":"Niedersachsen",
    "wof:name":"Heinrich Gudehus",
    "wof:placetype":"venue"
},
  "geometry": {"coordinates":[10.060116,52.652618],"type":"Point"}
}