{
  "type": "Feature",
  "properties": {
    "iso:country":"DE",
    "sg:address":"Schlesienstr. 3",
    "sg:city":"Zweibr\u00fccken",
    "sg:phone":"+49 6332/44253",
    "sg:postcode":"66482",
    "sg:province":"Rheinland-Pfalz",
    "wof:name":"Walther Jung Ingenieur",
    "wof:placetype":"venue"
},
  "geometry": {"coordinates":[7.3953909874,49.2590827942],"type":"Point"}
}