{
  "type": "Feature",
  "properties": {
    "iso:country":"DE",
    "sg:address":"Bahnhofstr. 2",
    "sg:city":"G\u00f6nnheim",
    "sg:phone":"+49 6322/5003",
    "sg:postcode":"67161",
    "sg:province":"Rheinland-Pfalz",
    "wof:name":"G\u00e4stehaus M. K\u00fcnzel",
    "wof:placetype":"venue"
},
  "geometry": {"coordinates":[8.2378921509,49.4495201111],"type":"Point"}
}