{
  "type": "Feature",
  "properties": {
    "iso:country":"DE",
    "sg:address":"Blochmattenstr. 17",
    "sg:city":"Teningen",
    "sg:postcode":"79331",
    "sg:province":"Baden-W\u00fcrttemberg",
    "wof:name":"Natura Cos Gmbh",
    "wof:placetype":"venue"
},
  "geometry": {"coordinates":[7.810761,48.136051],"type":"Point"}
}