{
  "type": "Feature",
  "properties": {
    "iso:country":"DE",
    "sg:address":"Kottbusser Damm 29",
    "sg:city":"Berlin",
    "sg:phone":"+49 30/6937086",
    "sg:postcode":"10967",
    "sg:province":"Berlin",
    "wof:name":"Dr. Matthias Zieger Rechtsanwalt",
    "wof:placetype":"venue"
},
  "geometry": {"coordinates":[13.4241275787,52.4891967773],"type":"Point"}
}