{
  "type": "Feature",
  "properties": {
    "iso:country":"DE",
    "sg:address":"Rotweg 144",
    "sg:city":"Stuttgart",
    "sg:phone":"+49 711/8403138",
    "sg:postcode":"70437",
    "sg:province":"Baden-W\u00fcrttemberg",
    "wof:name":"Alfred Aman Ingenieur",
    "wof:placetype":"venue"
},
  "geometry": {"coordinates":[9.1937265396,48.8347816467],"type":"Point"}
}