{
  "type": "Feature",
  "properties": {
    "iso:country":"DE",
    "sg:address":"Stotternheimer Str. 19",
    "sg:city":"Erfurt",
    "sg:phone":"+49 4936/1779740",
    "sg:postcode":"99087",
    "sg:province":"Th\u00fcringen",
    "wof:name":"Landesverband Th\u00dcringer Rinderz\u00dcchter",
    "wof:placetype":"venue"
},
  "geometry": {"coordinates":[11.037088,51.030006],"type":"Point"}
}