{
  "type": "Feature",
  "properties": {
    "iso:country":"DE",
    "sg:address":"Sparkassenpassage 1",
    "sg:city":"Bad Kissingen",
    "sg:phone":"+49 971/64871",
    "sg:postcode":"97688",
    "sg:province":"Bayern",
    "wof:name":"A. Alberth",
    "wof:placetype":"venue"
},
  "geometry": {"coordinates":[10.0778245926,50.2024269104],"type":"Point"}
}