{
  "type": "Feature",
  "properties": {
    "iso:country":"DE",
    "sg:address":"M\u00fchlenstr. 6",
    "sg:city":"Bardowick",
    "sg:phone":"+49 4131/12243",
    "sg:postcode":"21357",
    "sg:province":"Niedersachsen",
    "wof:name":"R. Bauland",
    "wof:placetype":"venue"
},
  "geometry": {"coordinates":[10.388678,53.301659],"type":"Point"}
}