{
  "type": "Feature",
  "properties": {
    "iso:country":"DE",
    "sg:address":"Unterm Horn 17",
    "sg:city":"Immenstadt",
    "sg:phone":"+49 8323/6237",
    "sg:postcode":"87509",
    "sg:province":"Bayern",
    "wof:name":"A. Bickel Gmbh",
    "wof:placetype":"venue"
},
  "geometry": {"coordinates":[10.1894512177,47.565662384],"type":"Point"}
}