{
  "type": "Feature",
  "properties": {
    "iso:country":"DE",
    "sg:address":"Neubrandenburger Str. 90",
    "sg:city":"Berlin",
    "sg:phone":"+49 30/92799730",
    "sg:postcode":"13059",
    "sg:province":"Berlin",
    "wof:name":"Hauraton Gmbh & Co. Kg",
    "wof:placetype":"venue"
},
  "geometry": {"coordinates":[13.5196323395,52.5720748901],"type":"Point"}
}