{
  "type": "Feature",
  "properties": {
    "iso:country":"DE",
    "sg:address":"Splitting Rechts 34",
    "sg:city":"Papenburg",
    "sg:phone":"+49 4961/974171",
    "sg:postcode":"26871",
    "sg:province":"Niedersachsen",
    "wof:name":"B. H\u00f6velmann",
    "wof:placetype":"venue"
},
  "geometry": {"coordinates":[7.44186,53.073109],"type":"Point"}
}