{
  "type": "Feature",
  "properties": {
    "iso:country":"DE",
    "sg:address":"Ilmenweg 39",
    "sg:city":"Geldern",
    "sg:phone":"+49 2832/2754",
    "sg:postcode":"47608",
    "sg:province":"Nordrhein-Westfalen",
    "wof:name":"Hans Van Leuven",
    "wof:placetype":"venue"
},
  "geometry": {"coordinates":[6.255939,51.536583],"type":"Point"}
}