{
  "type": "Feature",
  "properties": {
    "iso:country":"DE",
    "sg:address":"Feldmochinger Str. 39 e",
    "sg:city":"M\u00fcnchen",
    "sg:postcode":"80993",
    "sg:province":"Bayern",
    "wof:name":"M. G. Home Couture E. K.",
    "wof:placetype":"venue"
},
  "geometry": {"coordinates":[11.5210552216,48.1839561462],"type":"Point"}
}