{
  "type": "Feature",
  "properties": {
    "iso:country":"DE",
    "sg:address":"Markt 1",
    "sg:city":"Gerstungen",
    "sg:phone":"+49 36922/20887",
    "sg:postcode":"99834",
    "sg:province":"Th\u00fcringen",
    "wof:name":"Uwe Wimmel",
    "wof:placetype":"venue"
},
  "geometry": {"coordinates":[10.0780887604,50.9692306519],"type":"Point"}
}