{
  "type": "Feature",
  "properties": {
    "iso:country":"DE",
    "sg:address":"Passauer Str. 10",
    "sg:city":"Ruderting",
    "sg:phone":"+49 8509/3336",
    "sg:postcode":"94161",
    "sg:province":"Bayern",
    "wof:name":"Pizzeria Palermo",
    "wof:placetype":"venue"
},
  "geometry": {"coordinates":[13.4074773788,48.6546058655],"type":"Point"}
}