{
  "type": "Feature",
  "properties": {
    "iso:country":"DE",
    "sg:address":"Naundorfer Str. 10",
    "sg:city":"Coswig",
    "sg:phone":"+49 3523/8730",
    "sg:postcode":"01640",
    "sg:province":"Sachsen",
    "wof:name":"Whg-ahmerkamp Gmbh & Co.",
    "wof:placetype":"venue"
},
  "geometry": {"coordinates":[13.584854,51.113686],"type":"Point"}
}