{
  "type": "Feature",
  "properties": {
    "iso:country":"DE",
    "sg:address":"Albert-Schweitzer-Str. 6",
    "sg:city":"Edingen-Neckarhausen",
    "sg:phone":"+49 6203/81886",
    "sg:postcode":"68535",
    "sg:province":"Baden-W\u00fcrttemberg",
    "wof:name":"E. Schiller",
    "wof:placetype":"venue"
},
  "geometry": {"coordinates":[8.606461525,49.4480552673],"type":"Point"}
}