{
  "type": "Feature",
  "properties": {
    "iso:country":"DE",
    "sg:address":"An der Halde 23",
    "sg:city":"Ulm",
    "sg:phone":"+49 731/382612",
    "sg:postcode":"89081",
    "sg:province":"Baden-W\u00fcrttemberg",
    "wof:name":"Heinrich Sturm",
    "wof:placetype":"venue"
},
  "geometry": {"coordinates":[9.936299324,48.373790741],"type":"Point"}
}