{
  "type": "Feature",
  "properties": {
    "iso:country":"DE",
    "sg:address":"Amorsbrunner Str 3",
    "sg:city":"Amorbach",
    "sg:phone":"+49 9373/99056",
    "sg:postcode":"63916",
    "sg:province":"Bayern",
    "wof:name":"Ec Control Gmbh",
    "wof:placetype":"venue"
},
  "geometry": {"coordinates":[9.211624,49.648228],"type":"Point"}
}