{
  "type": "Feature",
  "properties": {
    "iso:country":"DE",
    "sg:address":"Goldstr. 9",
    "sg:city":"Borken",
    "sg:phone":"+49 2861/64696",
    "sg:postcode":"46325",
    "sg:province":"Nordrhein-Westfalen",
    "wof:name":"Demes Ohg",
    "wof:placetype":"venue"
},
  "geometry": {"coordinates":[6.85844,51.842884],"type":"Point"}
}