{
  "type": "Feature",
  "properties": {
    "iso:country":"DE",
    "sg:address":"Ausbau 2",
    "sg:city":"Bergholz",
    "sg:phone":"+49 39754/20566",
    "sg:postcode":"17321",
    "sg:province":"Mecklenburg-Vorpommern",
    "wof:name":"Heidem\u00fchle Inh. Karl-heinz Sch\u00fcmann",
    "wof:placetype":"venue"
},
  "geometry": {"coordinates":[14.2159204483,53.4529838562],"type":"Point"}
}