{
  "type": "Feature",
  "properties": {
    "iso:country":"DE",
    "sg:address":"F\u00f6rdererstr. 17",
    "sg:city":"Villingen-Schwenningen",
    "sg:phone":"+49 7721/57495",
    "sg:postcode":"78050",
    "sg:province":"Baden-W\u00fcrttemberg",
    "wof:name":"G. Hettich",
    "wof:placetype":"venue"
},
  "geometry": {"coordinates":[8.4493703842,48.0599098206],"type":"Point"}
}