{
  "type": "Feature",
  "properties": {
    "iso:country":"DE",
    "sg:address":"S\u00fcntelweg 2D",
    "sg:city":"Langenhagen",
    "sg:phone":"+49 511/723323",
    "sg:postcode":"30851",
    "sg:province":"Niedersachsen",
    "wof:name":"Hartmann Werbung",
    "wof:placetype":"venue"
},
  "geometry": {"coordinates":[9.740719,52.433487],"type":"Point"}
}