{
  "type": "Feature",
  "properties": {
    "iso:country":"DE",
    "sg:address":"Auto-Union-Str.",
    "sg:city":"Ingolstadt",
    "sg:phone":"+49 841/890",
    "sg:postcode":"85057",
    "sg:province":"Bayern",
    "wof:name":"Audi Ag",
    "wof:placetype":"venue"
},
  "geometry": {"coordinates":[11.4238548279,48.7814712524],"type":"Point"}
}