{
  "type": "Feature",
  "properties": {
    "iso:country":"DE",
    "sg:address":"Hauptstr. 35",
    "sg:city":"Hof",
    "sg:phone":"+49 2661/939113",
    "sg:postcode":"56472",
    "sg:province":"Rheinland-Pfalz",
    "wof:name":"Gastst\u00e4tte Salzburger Kopf",
    "wof:placetype":"venue"
},
  "geometry": {"coordinates":[8.0153360367,50.6666717529],"type":"Point"}
}