{
  "type": "Feature",
  "properties": {
    "iso:country":"DE",
    "sg:address":"Ifflandstr. 52",
    "sg:city":"Hamburg",
    "sg:postcode":"22087",
    "sg:province":"Hamburg",
    "wof:name":"Conceptpool Verwaltungs- Gmbh",
    "wof:placetype":"venue"
},
  "geometry": {"coordinates":[10.0224761963,53.5618095398],"type":"Point"}
}