{
  "type": "Feature",
  "properties": {
    "iso:country":"DE",
    "sg:address":"Cronenberger Str. 60",
    "sg:city":"Solingen",
    "sg:phone":"+49 212/17669",
    "sg:postcode":"42651",
    "sg:province":"Nordrhein-Westfalen",
    "wof:name":"Kurt D\u00f6rner",
    "wof:placetype":"venue"
},
  "geometry": {"coordinates":[7.087186,51.177807],"type":"Point"}
}