{
  "type": "Feature",
  "properties": {
    "iso:country":"DE",
    "sg:address":"Focher Str. 129",
    "sg:city":"Solingen",
    "sg:phone":"+49 212/316004",
    "sg:postcode":"42719",
    "sg:province":"Nordrhein-Westfalen",
    "wof:name":"Haus Demmeltrath",
    "wof:placetype":"venue"
},
  "geometry": {"coordinates":[7.0595870018,51.1888237],"type":"Point"}
}