{
  "type": "Feature",
  "properties": {
    "iso:country":"DE",
    "sg:address":"Schleusenweg 5",
    "sg:city":"Limburg",
    "sg:phone":"+49 6431/26928",
    "sg:postcode":"65549",
    "sg:province":"Hessen",
    "wof:name":"Michael Schormann Rechtsanwalt",
    "wof:placetype":"venue"
},
  "geometry": {"coordinates":[8.0674858093,50.3910675049],"type":"Point"}
}