{
  "type": "Feature",
  "properties": {
    "iso:country":"DE",
    "sg:address":"H\u00f6pfertsteig 6",
    "sg:city":"Berlin",
    "sg:phone":"+49 30/4117381",
    "sg:postcode":"13469",
    "sg:province":"Berlin",
    "wof:name":"Adolf Peucker",
    "wof:placetype":"venue"
},
  "geometry": {"coordinates":[13.355396,52.615765],"type":"Point"}
}