{
  "type": "Feature",
  "properties": {
    "iso:country":"DE",
    "sg:address":"Neue Reihe 38",
    "sg:city":"Osterode",
    "sg:phone":"+49 5522/4795",
    "sg:postcode":"37520",
    "sg:province":"Niedersachsen",
    "wof:name":"Petra Schulz",
    "wof:placetype":"venue"
},
  "geometry": {"coordinates":[10.178434,51.737881],"type":"Point"}
}