{
  "type": "Feature",
  "properties": {
    "iso:country":"DE",
    "sg:address":"Am Getterbach 47 e",
    "sg:city":"M\u00fcnster",
    "sg:phone":"+49 251/714873",
    "sg:postcode":"48163",
    "sg:province":"Nordrhein-Westfalen",
    "wof:name":"Gotzen Home & Office Support Team - Homesitting",
    "wof:placetype":"venue"
},
  "geometry": {"coordinates":[7.573015,51.924686],"type":"Point"}
}