{
  "type": "Feature",
  "properties": {
    "iso:country":"DE",
    "sg:address":"Kaiserberg 20",
    "sg:city":"Erbendorf",
    "sg:phone":"+49 9682/1722",
    "sg:postcode":"92681",
    "sg:province":"Bayern",
    "wof:name":"F. Kohr",
    "wof:placetype":"venue"
},
  "geometry": {"coordinates":[12.0469636917,49.8395957947],"type":"Point"}
}