{
  "type": "Feature",
  "properties": {
    "iso:country":"DE",
    "sg:address":"Wildberg 7",
    "sg:city":"G\u00f6risried",
    "sg:phone":"+49 8302/258",
    "sg:postcode":"87657",
    "sg:province":"Bayern",
    "wof:name":"Brigitte Und Hans Wohlfahrt",
    "wof:placetype":"venue"
},
  "geometry": {"coordinates":[10.516738,47.679832],"type":"Point"}
}