{
  "type": "Feature",
  "properties": {
    "iso:country":"DE",
    "sg:address":"Ablacher Str. 3",
    "sg:city":"Sigmaringen",
    "sg:phone":"+49 7571/3113",
    "sg:postcode":"72488",
    "sg:province":"Baden-W\u00fcrttemberg",
    "wof:name":"Karl M\u00fcller Architekt",
    "wof:placetype":"venue"
},
  "geometry": {"coordinates":[9.194058,48.075455],"type":"Point"}
}