{
  "type": "Feature",
  "properties": {
    "iso:country":"DE",
    "sg:address":"Marienstr. 6",
    "sg:city":"Greiz",
    "sg:postcode":"07973",
    "sg:province":"Th\u00fcringen",
    "wof:name":"Meeraner Spirituosen- Und Weinkellerei Gmbh",
    "wof:placetype":"venue"
},
  "geometry": {"coordinates":[12.1987133026,50.6582374573],"type":"Point"}
}