{
  "type": "Feature",
  "properties": {
    "iso:country":"DE",
    "sg:address":"Karl-Liebknecht-Str. 22",
    "sg:city":"Leipzig",
    "sg:phone":"+49 341/2131850",
    "sg:postcode":"04107",
    "sg:province":"Sachsen",
    "wof:name":"Dietmar Rauch",
    "wof:placetype":"venue"
},
  "geometry": {"coordinates":[12.3732738495,51.3294181824],"type":"Point"}
}