{
  "type": "Feature",
  "properties": {
    "iso:country":"DE",
    "sg:address":"Limmerstr. 26",
    "sg:city":"Hannover",
    "sg:phone":"+49 511/445977",
    "sg:postcode":"30451",
    "sg:province":"Niedersachsen",
    "wof:name":"Pizzeria Parma",
    "wof:placetype":"venue"
},
  "geometry": {"coordinates":[9.7097930908,52.3728179932],"type":"Point"}
}