{
  "type": "Feature",
  "properties": {
    "iso:country":"DE",
    "sg:address":"Vierradener Str. 29",
    "sg:city":"Schwedt",
    "sg:phone":"+49 3332/23233",
    "sg:postcode":"16303",
    "sg:province":"Brandenburg",
    "wof:name":"Reiseb\u00fcro Zwerg Gmbh",
    "wof:placetype":"venue"
},
  "geometry": {"coordinates":[14.2869710922,53.0559005737],"type":"Point"}
}