{
  "type": "Feature",
  "properties": {
    "iso:country":"DE",
    "sg:address":"Allersberger Str. 27",
    "sg:city":"Schwanstetten",
    "sg:phone":"+49 9170/1345",
    "sg:postcode":"90596",
    "sg:province":"Bayern",
    "wof:name":"Hans Feyerlein",
    "wof:placetype":"venue"
},
  "geometry": {"coordinates":[11.1265659332,49.2974739075],"type":"Point"}
}