{
  "type": "Feature",
  "properties": {
    "iso:country":"DE",
    "sg:address":"Dechenstr. 7-11",
    "sg:city":"Bonn",
    "sg:phone":"+49 228/7240",
    "sg:postcode":"53115",
    "sg:province":"Nordrhein-Westfalen",
    "wof:name":"Redaktion Betrieb U. Personal Stollfuss Verlag",
    "wof:placetype":"venue"
},
  "geometry": {"coordinates":[7.0965747833,50.7307853699],"type":"Point"}
}