{
  "type": "Feature",
  "properties": {
    "iso:country":"DE",
    "sg:address":"H\u00fchnleinsweg 228",
    "sg:city":"Warmensteinach",
    "sg:phone":"+49 9277/1570",
    "sg:postcode":"95485",
    "sg:province":"Bayern",
    "wof:name":"Heinz Posselt Marmorwerk",
    "wof:placetype":"venue"
},
  "geometry": {"coordinates":[11.7699041367,49.985206604],"type":"Point"}
}