{
  "type": "Feature",
  "properties": {
    "iso:country":"DE",
    "sg:address":"Schulstr. 12",
    "sg:city":"Meudt",
    "sg:phone":"+49 6435/54241",
    "sg:postcode":"56414",
    "sg:province":"Rheinland-Pfalz",
    "wof:name":"Als Ingenieurb\u00fcro Und Immobilien Gmbh",
    "wof:placetype":"venue"
},
  "geometry": {"coordinates":[7.89727211,50.4971466064],"type":"Point"}
}