{
  "type": "Feature",
  "properties": {
    "iso:country":"DE",
    "sg:address":"Berliner Str. 2",
    "sg:city":"Schwedt",
    "sg:phone":"+49 3332/22696",
    "sg:postcode":"16303",
    "sg:province":"Brandenburg",
    "wof:name":"Bestattungsinstitut R. Haupt Gmbh",
    "wof:placetype":"venue"
},
  "geometry": {"coordinates":[14.28205,53.053272],"type":"Point"}
}