{
  "type": "Feature",
  "properties": {
    "iso:country":"DE",
    "sg:address":"Ottenhofstr. 22",
    "sg:city":"Lohr",
    "sg:phone":"+49 9352/2923",
    "sg:postcode":"97816",
    "sg:province":"Bayern",
    "wof:name":"Otto Kindersberger",
    "wof:placetype":"venue"
},
  "geometry": {"coordinates":[9.5752067566,49.9950790405],"type":"Point"}
}