{
  "type": "Feature",
  "properties": {
    "iso:country":"DE",
    "sg:address":"Hauptstr. 143",
    "sg:city":"Rheda-Wiedenbr\u00fcck",
    "sg:phone":"+49 5242/4090",
    "sg:postcode":"33378",
    "sg:province":"Nordrhein-Westfalen",
    "wof:name":"Garant M\u00f6bel Service Gmbh & Co.",
    "wof:placetype":"venue"
},
  "geometry": {"coordinates":[8.2936859131,51.8473091125],"type":"Point"}
}