{
  "type": "Feature",
  "properties": {
    "iso:country":"DE",
    "sg:address":"Braunschweiger Str. 33",
    "sg:city":"Magdeburg",
    "sg:phone":"+49 391/604300",
    "sg:postcode":"39116",
    "sg:province":"Sachsen-Anhalt",
    "wof:name":"J. Tr\u00e4ger",
    "wof:placetype":"venue"
},
  "geometry": {"coordinates":[11.58716,52.113522],"type":"Point"}
}