{
  "type": "Feature",
  "properties": {
    "iso:country":"DE",
    "sg:address":"Richard-Cappelle-Weg 9",
    "sg:city":"Bremerhaven",
    "sg:phone":"+49 471/62247",
    "sg:postcode":"27578",
    "sg:province":"Bremen",
    "wof:name":"A. Und B. Frischke",
    "wof:placetype":"venue"
},
  "geometry": {"coordinates":[8.606981,53.596439],"type":"Point"}
}