{
  "type": "Feature",
  "properties": {
    "iso:country":"DE",
    "sg:address":"Peter-Welter-Platz 2",
    "sg:city":"Koeln",
    "sg:phone":"+49 221/9212070",
    "sg:postcode":"50676",
    "sg:province":"Nordrhein-Westfalen",
    "wof:name":"Staatliche Zentralstelle F\u00fcr Fernunterricht (zfu)",
    "wof:placetype":"venue"
},
  "geometry": {"coordinates":[6.962258,50.934029],"type":"Point"}
}