{
  "type": "Feature",
  "properties": {
    "iso:country":"DE",
    "sg:address":"Griewenkamp 2",
    "sg:city":"Edemissen",
    "sg:phone":"+49 4951/7698910",
    "sg:postcode":"31234",
    "sg:province":"Niedersachsen",
    "wof:name":"Limagrain Nickerson Gmbh",
    "wof:placetype":"venue"
},
  "geometry": {"coordinates":[10.270485,52.386703],"type":"Point"}
}