{
  "type": "Feature",
  "properties": {
    "iso:country":"DE",
    "sg:address":"Schaumburger Str. 33",
    "sg:city":"Lohrheim",
    "sg:phone":"+49 6430/91420",
    "sg:postcode":"65558",
    "sg:province":"Rheinland-Pfalz",
    "wof:name":"Erbsl\u00f6h & Co.",
    "wof:placetype":"venue"
},
  "geometry": {"coordinates":[8.0450601578,50.3182983398],"type":"Point"}
}