{
  "type": "Feature",
  "properties": {
    "iso:country":"DE",
    "sg:address":"Am M\u00fchlenbach 24",
    "sg:city":"Bad Rothenfelde",
    "sg:phone":"+49 5424/4323",
    "sg:postcode":"49214",
    "sg:province":"Niedersachsen",
    "wof:name":"Wilfried Fahlkamp",
    "wof:placetype":"venue"
},
  "geometry": {"coordinates":[8.1763095856,52.1061210632],"type":"Point"}
}