{
  "type": "Feature",
  "properties": {
    "iso:country":"DE",
    "sg:address":"Frankfurter Allee 70",
    "sg:city":"Berlin",
    "sg:phone":"+49 30/2918105",
    "sg:postcode":"10247",
    "sg:province":"Berlin",
    "wof:name":"Helga Nachtigall Rechtsanw\u00e4ltin",
    "wof:placetype":"venue"
},
  "geometry": {"coordinates":[13.4671888351,52.514289856],"type":"Point"}
}