{
  "type": "Feature",
  "properties": {
    "iso:country":"DE",
    "sg:address":"Habacher Str. 17",
    "sg:city":"Lebach",
    "sg:phone":"+49 6881/3617",
    "sg:postcode":"66822",
    "sg:province":"Saarland",
    "wof:name":"Ernst Biesel",
    "wof:placetype":"venue"
},
  "geometry": {"coordinates":[6.929347,49.388893],"type":"Point"}
}