{
  "type": "Feature",
  "properties": {
    "iso:country":"DE",
    "sg:address":"Blumenstr. 2",
    "sg:city":"Esthal",
    "sg:phone":"+49 6325/2768",
    "sg:postcode":"67472",
    "sg:province":"Rheinland-Pfalz",
    "wof:name":"Esthaler B\u00fcrgerst\u00fcbl",
    "wof:placetype":"venue"
},
  "geometry": {"coordinates":[7.9844031334,49.3772621155],"type":"Point"}
}