{
  "type": "Feature",
  "properties": {
    "iso:country":"DE",
    "sg:address":"Richard-Wagner-Str. 20",
    "sg:city":"Fredersdorf",
    "sg:phone":"+49 33439/80915",
    "sg:postcode":"15370",
    "sg:province":"Brandenburg",
    "wof:name":"Pension Sarra",
    "wof:placetype":"venue"
},
  "geometry": {"coordinates":[13.7421884537,52.5131530762],"type":"Point"}
}