{
  "type": "Feature",
  "properties": {
    "iso:country":"DE",
    "sg:address":"Nibelungenstr. 8",
    "sg:city":"\u00d6stringen",
    "sg:phone":"+49 7259/8726",
    "sg:postcode":"76684",
    "sg:province":"Baden-W\u00fcrttemberg",
    "wof:name":"Sternen",
    "wof:placetype":"venue"
},
  "geometry": {"coordinates":[8.7513599396,49.1787605286],"type":"Point"}
}