{
  "type": "Feature",
  "properties": {
    "iso:country":"DE",
    "sg:address":"Tiefenbruchstr. 7a",
    "sg:city":"Essen",
    "sg:phone":"+49 201/8385857",
    "sg:postcode":"45326",
    "sg:province":"Nordrhein-Westfalen",
    "wof:name":"Medin Ak",
    "wof:placetype":"venue"
},
  "geometry": {"coordinates":[7.011208,51.487644],"type":"Point"}
}