{
  "type": "Feature",
  "properties": {
    "iso:country":"DE",
    "sg:address":"Langer Weg 10",
    "sg:city":"Paderborn",
    "sg:phone":"+49 5251/55852",
    "sg:postcode":"33100",
    "sg:province":"Nordrhein-Westfalen",
    "wof:name":"Dieter G\u00f6ttker",
    "wof:placetype":"venue"
},
  "geometry": {"coordinates":[8.7711200714,51.7228889465],"type":"Point"}
}