{
  "type": "Feature",
  "properties": {
    "iso:country":"DE",
    "sg:address":"Angerstr. 9",
    "sg:city":"Reddeber",
    "sg:phone":"+49 3943/22967",
    "sg:postcode":"38855",
    "sg:province":"Sachsen-Anhalt",
    "wof:name":"Klaus-dieter Hartmann",
    "wof:placetype":"venue"
},
  "geometry": {"coordinates":[10.8028469086,51.8685188293],"type":"Point"}
}