{
  "type": "Feature",
  "properties": {
    "iso:country":"DE",
    "sg:address":"Postfach 37 33",
    "sg:city":"Waldbr\u00f6l",
    "sg:phone":"+49 2291/840",
    "sg:postcode":"51537",
    "sg:province":"Nordrhein-Westfalen",
    "wof:name":"Selkirk Schornsteintechnik Gmbh",
    "wof:placetype":"venue"
},
  "geometry": {"coordinates":[7.6174201965,50.8764381409],"type":"Point"}
}