{
  "type": "Feature",
  "properties": {
    "iso:country":"DE",
    "sg:address":"Deichringstr. 27",
    "sg:city":"Neuharlingersiel",
    "sg:phone":"+49 4974/990025",
    "sg:postcode":"26427",
    "sg:province":"Niedersachsen",
    "wof:name":"Kaj\u00fcte",
    "wof:placetype":"venue"
},
  "geometry": {"coordinates":[7.6905241013,53.6983833313],"type":"Point"}
}