{
  "type": "Feature",
  "properties": {
    "iso:country":"DE",
    "sg:address":"Naundorfer Str. 9",
    "sg:city":"Neukirchen",
    "sg:postcode":"08459",
    "sg:province":"Sachsen",
    "wof:name":"Glasutex Glas- U. Textilfaser- Recycling Gmbh",
    "wof:placetype":"venue"
},
  "geometry": {"coordinates":[12.386672,50.788857],"type":"Point"}
}