{
  "type": "Feature",
  "properties": {
    "iso:country":"DE",
    "sg:address":"Dionysiusstr. 1",
    "sg:city":"Lippstadt",
    "sg:phone":"+49 2941/12588",
    "sg:postcode":"59558",
    "sg:province":"Nordrhein-Westfalen",
    "wof:name":"F. Kolkmann",
    "wof:placetype":"venue"
},
  "geometry": {"coordinates":[8.3936471939,51.6361846924],"type":"Point"}
}