{
  "type": "Feature",
  "properties": {
    "iso:country":"DE",
    "sg:address":"Kirschenweg 5",
    "sg:city":"Leingarten",
    "sg:phone":"+49 7131/45091",
    "sg:postcode":"74211",
    "sg:province":"Baden-W\u00fcrttemberg",
    "wof:name":"Ehmann Gmbh",
    "wof:placetype":"venue"
},
  "geometry": {"coordinates":[9.1063985825,49.1427841187],"type":"Point"}
}