{
  "type": "Feature",
  "properties": {
    "iso:country":"DE",
    "sg:address":"Senserstr. 2",
    "sg:city":"Olching",
    "sg:phone":"+49 8142/18686",
    "sg:postcode":"82140",
    "sg:province":"Bayern",
    "wof:name":"Monika Herrmann",
    "wof:placetype":"venue"
},
  "geometry": {"coordinates":[11.3281536102,48.2077522278],"type":"Point"}
}