{
  "type": "Feature",
  "properties": {
    "iso:country":"DE",
    "sg:address":"Arnswalder Str. 38",
    "sg:city":"Hamburg",
    "sg:phone":"+49 40/6451686",
    "sg:postcode":"22147",
    "sg:province":"Hamburg",
    "wof:name":"David Agentur F\u00fcr Medienkom- Munikation Gmbh",
    "wof:placetype":"venue"
},
  "geometry": {"coordinates":[10.1493730545,53.6171760559],"type":"Point"}
}