{
  "type": "Feature",
  "properties": {
    "iso:country":"DE",
    "sg:address":"Helmbachstr. 158",
    "sg:city":"Landau",
    "sg:phone":"+49 6341/50580",
    "sg:postcode":"76829",
    "sg:province":"Rheinland-Pfalz",
    "wof:name":"Kath. Pfarramt St. Elisabeth",
    "wof:placetype":"venue"
},
  "geometry": {"coordinates":[8.138010025,49.2061195374],"type":"Point"}
}