{
  "type": "Feature",
  "properties": {
    "iso:country":"DE",
    "sg:address":"Bahnhofstr. 21",
    "sg:city":"Bad Krozingen",
    "sg:phone":"+49 7633/1888",
    "sg:postcode":"79189",
    "sg:province":"Baden-W\u00fcrttemberg",
    "wof:name":"Sonja Weiler",
    "wof:placetype":"venue"
},
  "geometry": {"coordinates":[7.698232,47.918129],"type":"Point"}
}