{
  "type": "Feature",
  "properties": {
    "iso:country":"DE",
    "sg:address":"Wilhelmstr. 12",
    "sg:city":"Gro\u00dfbottwar",
    "sg:phone":"+49 7148/5644",
    "sg:postcode":"71723",
    "sg:province":"Baden-W\u00fcrttemberg",
    "wof:name":"Dieter Fuchs",
    "wof:placetype":"venue"
},
  "geometry": {"coordinates":[9.290682,49.00293],"type":"Point"}
}