{
  "type": "Feature",
  "properties": {
    "iso:country":"DE",
    "sg:address":"Schwarzbachstr. 23",
    "sg:city":"Schl\u00fcchtern",
    "sg:phone":"+49 6664/7208",
    "sg:postcode":"36381",
    "sg:province":"Hessen",
    "wof:name":"M. Christ",
    "wof:placetype":"venue"
},
  "geometry": {"coordinates":[9.6399402618,50.3665008545],"type":"Point"}
}