{
  "type": "Feature",
  "properties": {
    "iso:country":"DE",
    "sg:address":"Bachstr. 12b",
    "sg:city":"Iserlohn",
    "sg:phone":"+49 2374/3987",
    "sg:postcode":"58642",
    "sg:province":"Nordrhein-Westfalen",
    "wof:name":"Holzbau Humpert",
    "wof:placetype":"venue"
},
  "geometry": {"coordinates":[7.6055779457,51.3670921326],"type":"Point"}
}