{
  "type": "Feature",
  "properties": {
    "iso:country":"DE",
    "sg:address":"Dorfstr. 64 a",
    "sg:city":"Sprotta",
    "sg:phone":"+49 3423/2367",
    "sg:postcode":"04838",
    "sg:province":"Sachsen",
    "wof:name":"Agragenossenschaft Heidegl\u00fcck Sprotta Eg",
    "wof:placetype":"venue"
},
  "geometry": {"coordinates":[12.626225,51.493671],"type":"Point"}
}