{
  "type": "Feature",
  "properties": {
    "iso:country":"DE",
    "sg:address":"Meichelbeckstr. 6",
    "sg:city":"Marktoberdorf",
    "sg:phone":"+49 8342/96620",
    "sg:postcode":"87616",
    "sg:province":"Bayern",
    "wof:name":"J. Kuhn Mineral\u00f6l-vertriebs-gmbh",
    "wof:placetype":"venue"
},
  "geometry": {"coordinates":[10.6178646088,47.7786064148],"type":"Point"}
}