{
  "type": "Feature",
  "properties": {
    "iso:country":"DE",
    "sg:address":"Hasenlohe 2",
    "sg:city":"Pegnitz",
    "sg:phone":"+49 9241/8196",
    "sg:postcode":"91257",
    "sg:province":"Bayern",
    "wof:name":"Schreiner Transporte Gmbh",
    "wof:placetype":"venue"
},
  "geometry": {"coordinates":[11.5316963196,49.7374382019],"type":"Point"}
}