{
  "type": "Feature",
  "properties": {
    "iso:country":"DE",
    "sg:address":"Franz-Ehret-Str. 24",
    "sg:city":"L\u00f6rrach",
    "sg:phone":"+49 7621/51492",
    "sg:postcode":"79541",
    "sg:province":"Baden-W\u00fcrttemberg",
    "wof:name":"F. Hagin Und P. Rabus",
    "wof:placetype":"venue"
},
  "geometry": {"coordinates":[7.695126,47.638222],"type":"Point"}
}