{
  "type": "Feature",
  "properties": {
    "iso:country":"DE",
    "sg:address":"Doberkamp 17",
    "sg:city":"Raisdorf",
    "sg:phone":"+49 4307/6850",
    "sg:postcode":"24223",
    "sg:province":"Schleswig-Holstein",
    "wof:name":"Rudolf Schulze Ingenieur",
    "wof:placetype":"venue"
},
  "geometry": {"coordinates":[10.2369499207,54.2774391174],"type":"Point"}
}