{
  "type": "Feature",
  "properties": {
    "iso:country":"DE",
    "sg:address":"Im Unterdorf 6",
    "sg:city":"Idenheim",
    "sg:phone":"+49 6506/8586",
    "sg:postcode":"54636",
    "sg:province":"Rheinland-Pfalz",
    "wof:name":"Hermann Wolsfeld",
    "wof:placetype":"venue"
},
  "geometry": {"coordinates":[6.572541,49.89835],"type":"Point"}
}