{
  "type": "Feature",
  "properties": {
    "iso:country":"DE",
    "sg:address":"Eberbacher Str. 8",
    "sg:city":"Eltville",
    "sg:phone":"+49 6723/87510",
    "sg:postcode":"65347",
    "sg:province":"Hessen",
    "wof:name":"K.-u. Schuh",
    "wof:placetype":"venue"
},
  "geometry": {"coordinates":[8.061769,50.014603],"type":"Point"}
}