{
  "type": "Feature",
  "properties": {
    "iso:country":"DE",
    "sg:address":"Provinzialstr. 74",
    "sg:city":"Wadgassen",
    "sg:phone":"+49 6834/48274",
    "sg:postcode":"66787",
    "sg:province":"Saarland",
    "wof:name":"Na Sowas",
    "wof:placetype":"venue"
},
  "geometry": {"coordinates":[6.8117098808,49.2585906982],"type":"Point"}
}