{
  "type": "Feature",
  "properties": {
    "iso:country":"DE",
    "sg:address":"Hallesche Landstr. 110",
    "sg:city":"Bernburg",
    "sg:phone":"+49 3471/311149",
    "sg:postcode":"06406",
    "sg:province":"Sachsen-Anhalt",
    "wof:name":"Agip-service-station Inh. J. Rambaum",
    "wof:placetype":"venue"
},
  "geometry": {"coordinates":[11.7504434586,51.7717552185],"type":"Point"}
}