{
  "type": "Feature",
  "properties": {
    "iso:country":"DE",
    "sg:address":"Deisterstr. 5",
    "sg:city":"Lauenau",
    "sg:phone":"+49 5043/2461",
    "sg:postcode":"31867",
    "sg:province":"Niedersachsen",
    "wof:name":"Albert R\u00f6hr",
    "wof:placetype":"venue"
},
  "geometry": {"coordinates":[9.381388,52.284916],"type":"Point"}
}