{
  "type": "Feature",
  "properties": {
    "iso:country":"DE",
    "sg:address":"Limesweg 4",
    "sg:city":"Neuler",
    "sg:phone":"+49 7961/2501",
    "sg:postcode":"73491",
    "sg:province":"Baden-W\u00fcrttemberg",
    "wof:name":"Wilhelm Schlichtherle",
    "wof:placetype":"venue"
},
  "geometry": {"coordinates":[10.073956,48.925762],"type":"Point"}
}