{
  "type": "Feature",
  "properties": {
    "iso:country":"DE",
    "sg:address":"Schillerstr. 25",
    "sg:city":"Erlangen",
    "sg:phone":"+49 9131/852312",
    "sg:postcode":"91054",
    "sg:province":"Bayern",
    "wof:name":"Institut F\u00fcr Arbeits- Und Sozialmedizin",
    "wof:placetype":"venue"
},
  "geometry": {"coordinates":[11.0215616226,49.5986671448],"type":"Point"}
}