{
  "type": "Feature",
  "properties": {
    "iso:country":"DE",
    "sg:address":"Hinzistobler Str.",
    "sg:city":"Ravensburg",
    "sg:phone":"+49 751/32098",
    "sg:postcode":"88212",
    "sg:province":"Baden-W\u00fcrttemberg",
    "wof:name":"Johannes Kiderlen",
    "wof:placetype":"venue"
},
  "geometry": {"coordinates":[9.6215019226,47.7707901001],"type":"Point"}
}