{
  "type": "Feature",
  "properties": {
    "iso:country":"DE",
    "sg:address":"Wieserfeldstr. 1",
    "sg:city":"Erding",
    "sg:phone":"+49 8122/48661",
    "sg:postcode":"85435",
    "sg:province":"Bayern",
    "wof:name":"Djh Registerkassen Vertriebs Gmbh",
    "wof:placetype":"venue"
},
  "geometry": {"coordinates":[11.895391,48.279095],"type":"Point"}
}