{
  "type": "Feature",
  "properties": {
    "iso:country":"DE",
    "sg:address":"Hornkoppel 1",
    "sg:city":"Meezen",
    "sg:postcode":"24594",
    "sg:province":"Schleswig-Holstein",
    "wof:name":"B\u00fclk & Reimers Gmbh",
    "wof:placetype":"venue"
},
  "geometry": {"coordinates":[9.706388,54.056938],"type":"Point"}
}