{
  "type": "Feature",
  "properties": {
    "iso:country":"DE",
    "sg:address":"Dortmunder Str. 5",
    "sg:city":"Bremen",
    "sg:phone":"+49 4942/159510",
    "sg:postcode":"28199",
    "sg:province":"Bremen",
    "wof:name":"Hella Fahrzeug Komponenten Gmbh",
    "wof:placetype":"venue"
},
  "geometry": {"coordinates":[8.7805290222,53.0601234436],"type":"Point"}
}