{
  "type": "Feature",
  "properties": {
    "iso:country":"DE",
    "sg:address":"Pfahlweg 13",
    "sg:city":"Rainau",
    "sg:postcode":"73492",
    "sg:province":"Baden-W\u00fcrttemberg",
    "wof:name":"Beck & Meier Gmbh",
    "wof:placetype":"venue"
},
  "geometry": {"coordinates":[10.175711,48.924072],"type":"Point"}
}