{
  "type": "Feature",
  "properties": {
    "iso:country":"DE",
    "sg:address":"Ellieh\u00e4user Weg 7-11",
    "sg:city":"G\u00f6ttingen",
    "sg:postcode":"37079",
    "sg:province":"Niedersachsen",
    "wof:name":"Verpackungsmarkt Braunschweig Gmbh",
    "wof:placetype":"venue"
},
  "geometry": {"coordinates":[9.906152,51.549854],"type":"Point"}
}