{
  "type": "Feature",
  "properties": {
    "iso:country":"DE",
    "sg:address":"Habenichts 17",
    "sg:city":"Wermelskirchen",
    "sg:phone":"+49 2196/80337",
    "sg:postcode":"42929",
    "sg:province":"Nordrhein-Westfalen",
    "wof:name":"G\u00fcnter Siebel",
    "wof:placetype":"venue"
},
  "geometry": {"coordinates":[7.2486190796,51.1219978333],"type":"Point"}
}