{
  "type": "Feature",
  "properties": {
    "iso:country":"DE",
    "sg:address":"Friedensstr. 2",
    "sg:city":"Themar",
    "sg:phone":"+49 36873/20807",
    "sg:postcode":"98660",
    "sg:province":"Th\u00fcringen",
    "wof:name":"Heike Schmidt",
    "wof:placetype":"venue"
},
  "geometry": {"coordinates":[10.618932724,50.5043983459],"type":"Point"}
}