{
  "type": "Feature",
  "properties": {
    "iso:country":"DE",
    "sg:address":"Dieselstr. 1",
    "sg:city":"Unterschlei\u00dfheim",
    "sg:phone":"+49 89/3211999",
    "sg:postcode":"85716",
    "sg:province":"Bayern",
    "wof:name":"Pelocran Sarues-loch Gmbh",
    "wof:placetype":"venue"
},
  "geometry": {"coordinates":[11.5727033615,48.2812385559],"type":"Point"}
}