{
  "type": "Feature",
  "properties": {
    "iso:country":"DE",
    "sg:address":"Schrannenplatz 209",
    "sg:city":"Neuburg",
    "sg:phone":"+49 8431/5980",
    "sg:postcode":"86633",
    "sg:province":"Bayern",
    "wof:name":"Raiffeisenbank Neuburg Donau Eg",
    "wof:placetype":"venue"
},
  "geometry": {"coordinates":[11.183775,48.736771],"type":"Point"}
}