{
  "type": "Feature",
  "properties": {
    "iso:country":"DE",
    "sg:address":"Breite Str. 17",
    "sg:city":"Recklinghausen",
    "sg:phone":"+49 2361/17300",
    "sg:postcode":"45657",
    "sg:province":"Nordrhein-Westfalen",
    "wof:name":"Atlas Reisen Gmbh",
    "wof:placetype":"venue"
},
  "geometry": {"coordinates":[7.1975188255,51.6128387451],"type":"Point"}
}