{
  "type": "Feature",
  "properties": {
    "iso:country":"DE",
    "sg:address":"Ernst-Moritz-Arndt-Str. 18",
    "sg:city":"Windeck",
    "sg:phone":"+49 2292/1377",
    "sg:postcode":"51570",
    "sg:province":"Nordrhein-Westfalen",
    "wof:name":"Dr. Paul Safaric Ingenieur",
    "wof:placetype":"venue"
},
  "geometry": {"coordinates":[7.6121740341,50.803352356],"type":"Point"}
}