{
  "type": "Feature",
  "properties": {
    "iso:country":"DE",
    "sg:address":"Freytagstr. 12",
    "sg:city":"D\u00fcsseldorf",
    "sg:phone":"+49 211/662177",
    "sg:postcode":"40237",
    "sg:province":"Nordrhein-Westfalen",
    "wof:name":"Hubertus Zangen",
    "wof:placetype":"venue"
},
  "geometry": {"coordinates":[6.806353,51.238171],"type":"Point"}
}