{
  "type": "Feature",
  "properties": {
    "iso:country":"DE",
    "sg:address":"Alt\u00f6ttinger Str. 3",
    "sg:city":"Kastl",
    "sg:phone":"+49 8671/8370",
    "sg:postcode":"84556",
    "sg:province":"Bayern",
    "wof:name":"Der Schlesier Fleisch- Und Wurstwaren Gmbh",
    "wof:placetype":"venue"
},
  "geometry": {"coordinates":[12.6966819763,48.1930160522],"type":"Point"}
}