{
  "type": "Feature",
  "properties": {
    "iso:country":"DE",
    "sg:address":"Haspelstr. 25",
    "sg:city":"Kaiserslautern",
    "sg:phone":"+49 631/92294",
    "sg:postcode":"67657",
    "sg:province":"Rheinland-Pfalz",
    "wof:name":"Blindenarbeitszentrale E. V.",
    "wof:placetype":"venue"
},
  "geometry": {"coordinates":[7.774473,49.450859],"type":"Point"}
}