{
  "type": "Feature",
  "properties": {
    "iso:country":"DE",
    "sg:address":"Bitterstr. 19",
    "sg:city":"K\u00f6ln",
    "sg:phone":"+49 221/786602",
    "sg:postcode":"50769",
    "sg:province":"Nordrhein-Westfalen",
    "wof:name":"Schiefer Ingenieur",
    "wof:placetype":"venue"
},
  "geometry": {"coordinates":[6.859495163,51.0640907288],"type":"Point"}
}