{
  "type": "Feature",
  "properties": {
    "iso:country":"DE",
    "sg:address":"Graf-Spee-Str 7",
    "sg:city":"Neustadt",
    "sg:phone":"+49 6692/919260",
    "sg:postcode":"35279",
    "sg:province":"Hessen",
    "wof:name":"A.t.i.",
    "wof:placetype":"venue"
},
  "geometry": {"coordinates":[9.1076984406,50.8505172729],"type":"Point"}
}