{
  "type": "Feature",
  "properties": {
    "iso:country":"DE",
    "sg:address":"Ammerl\u00e4nder Heerstr. 333",
    "sg:city":"Oldenburg",
    "sg:phone":"+49 441/74468",
    "sg:postcode":"26129",
    "sg:province":"Niedersachsen",
    "wof:name":"Gert Von Bloh",
    "wof:placetype":"venue"
},
  "geometry": {"coordinates":[8.16556,53.162338],"type":"Point"}
}