{
  "type": "Feature",
  "properties": {
    "iso:country":"DE",
    "sg:address":"Jahnstr. 3-9",
    "sg:city":"Forst",
    "sg:phone":"+49 3562/6219",
    "sg:postcode":"03149",
    "sg:province":"Brandenburg",
    "wof:name":"St\u00e4dt. Museumssammlung",
    "wof:placetype":"venue"
},
  "geometry": {"coordinates":[8.584927,49.152821],"type":"Point"}
}