{
  "type": "Feature",
  "properties": {
    "iso:country":"DE",
    "sg:address":"Hofmannstr. 4",
    "sg:city":"Viernheim",
    "sg:phone":"+49 6204/4449",
    "sg:postcode":"68519",
    "sg:province":"Hessen",
    "wof:name":"A. Haas Heissmangel",
    "wof:placetype":"venue"
},
  "geometry": {"coordinates":[8.5816736221,49.5396270752],"type":"Point"}
}