{
  "type": "Feature",
  "properties": {
    "iso:country":"DE",
    "sg:address":"Kahlgrachtstr. 22",
    "sg:city":"Aachen",
    "sg:phone":"+49 2405/3815",
    "sg:postcode":"52080",
    "sg:province":"Nordrhein-Westfalen",
    "wof:name":"H. Storms",
    "wof:placetype":"venue"
},
  "geometry": {"coordinates":[6.1506099701,50.7947998047],"type":"Point"}
}