{
  "type": "Feature",
  "properties": {
    "iso:country":"DE",
    "sg:address":"Kaiserswerther Str. 211",
    "sg:city":"D\u00fcsseldorf",
    "sg:phone":"+49 211/432373",
    "sg:postcode":"40474",
    "sg:province":"Nordrhein-Westfalen",
    "wof:name":"Kath. Pfarramt St. Albertus Magnus",
    "wof:placetype":"venue"
},
  "geometry": {"coordinates":[6.7663788795,51.2487754822],"type":"Point"}
}