{
  "type": "Feature",
  "properties": {
    "iso:country":"DE",
    "sg:address":"Bahnhofstr 27-28",
    "sg:city":"Barleben",
    "sg:phone":"+49 39203/790",
    "sg:postcode":"39179",
    "sg:province":"Sachsen-Anhalt",
    "wof:name":"Elektromotoren Und Ger\u00e4tebau Barleben Gmbh",
    "wof:placetype":"venue"
},
  "geometry": {"coordinates":[11.622216,52.208382],"type":"Point"}
}