{
  "type": "Feature",
  "properties": {
    "iso:country":"DE",
    "sg:address":"Biehlerhof 4",
    "sg:city":"Biehlerhof",
    "sg:phone":"+49 6393/1230",
    "sg:postcode":"66996",
    "sg:province":"Rheinland-Pfalz",
    "wof:name":"Norbert Mayer",
    "wof:placetype":"venue"
},
  "geometry": {"coordinates":[7.711566925,49.0863380432],"type":"Point"}
}