{
  "type": "Feature",
  "properties": {
    "iso:country":"DE",
    "sg:address":"Meckelstr. 73",
    "sg:city":"Wuppertal",
    "sg:phone":"+49 202/599456",
    "sg:postcode":"42287",
    "sg:province":"Nordrhein-Westfalen",
    "wof:name":"Meckelstube",
    "wof:placetype":"venue"
},
  "geometry": {"coordinates":[7.1896510124,51.263217926],"type":"Point"}
}