{
  "type": "Feature",
  "properties": {
    "iso:country":"DE",
    "sg:address":"Friedrichshulder Weg 56",
    "sg:city":"Halstenbek",
    "sg:phone":"+49 4101/473647",
    "sg:postcode":"25469",
    "sg:province":"Schleswig-Holstein",
    "wof:name":"Kraeber & Co. Gmbh",
    "wof:placetype":"venue"
},
  "geometry": {"coordinates":[9.8356370926,53.6243171692],"type":"Point"}
}