{
  "type": "Feature",
  "properties": {
    "iso:country":"DE",
    "sg:address":"R\u00fcbenkamp 20",
    "sg:city":"Seevetal",
    "sg:phone":"+49 4105/68660",
    "sg:postcode":"21220",
    "sg:province":"Niedersachsen",
    "wof:name":"Transportk\u00fchlung Thermo King Gmbh",
    "wof:placetype":"venue"
},
  "geometry": {"coordinates":[10.026065,53.389751],"type":"Point"}
}