{
  "type": "Feature",
  "properties": {
    "iso:country":"DE",
    "sg:address":"Magnolienweg 14",
    "sg:city":"Aschaffenburg",
    "sg:phone":"+49 6021/84080",
    "sg:postcode":"63741",
    "sg:province":"Bayern",
    "wof:name":"Jean Hommel Gmbh",
    "wof:placetype":"venue"
},
  "geometry": {"coordinates":[9.1308736801,49.964717865],"type":"Point"}
}