{
  "type": "Feature",
  "properties": {
    "iso:country":"DE",
    "sg:address":"Bakler Berg 14",
    "sg:city":"Gro\u00dfenkneten",
    "sg:phone":"+49 4435/1515",
    "sg:postcode":"26197",
    "sg:province":"Niedersachsen",
    "wof:name":"Georg Reinke Landwirtsch. Lohnbetrieb",
    "wof:placetype":"venue"
},
  "geometry": {"coordinates":[8.2458276749,52.8771247864],"type":"Point"}
}