{
  "type": "Feature",
  "properties": {
    "iso:country":"DE",
    "sg:address":"Am Waldhaus 14 a",
    "sg:city":"Oranienbaum",
    "sg:phone":"+49 34904/4000",
    "sg:postcode":"06785",
    "sg:province":"Sachsen-Anhalt",
    "wof:name":"Hotelpension Am Waldhaus",
    "wof:placetype":"venue"
},
  "geometry": {"coordinates":[12.3949384689,51.8029327393],"type":"Point"}
}