{
  "type": "Feature",
  "properties": {
    "iso:country":"DE",
    "sg:address":"Walter-Felsenstein-Str. 5",
    "sg:city":"Berlin",
    "sg:phone":"+49 30/9311071",
    "sg:postcode":"12687",
    "sg:province":"Berlin",
    "wof:name":"Bhv Buchal Handel Und Vertrieb Gmbh",
    "wof:placetype":"venue"
},
  "geometry": {"coordinates":[13.5546035767,52.5540847778],"type":"Point"}
}