{
  "type": "Feature",
  "properties": {
    "iso:country":"DE",
    "sg:address":"Postfach 22",
    "sg:city":"Kirchen",
    "sg:postcode":"57540",
    "sg:province":"Rheinland-Pfalz",
    "wof:name":"Katholisches Pfarramt St. Petrus",
    "wof:placetype":"venue"
},
  "geometry": {"coordinates":[7.8853402138,50.8067817688],"type":"Point"}
}