{
  "type": "Feature",
  "properties": {
    "iso:country":"DE",
    "sg:address":"Neugasse 8",
    "sg:city":"Rothenburg",
    "sg:phone":"+49 9861/8425",
    "sg:postcode":"91541",
    "sg:province":"Bayern",
    "wof:name":"Karin Br\u00e4unlein-thomm Rechtsanw\u00e4ltin",
    "wof:placetype":"venue"
},
  "geometry": {"coordinates":[10.1809148788,49.3743782043],"type":"Point"}
}