{
  "type": "Feature",
  "properties": {
    "iso:country":"DE",
    "sg:address":"Vieringhausen 67",
    "sg:city":"Remscheid",
    "sg:phone":"+49 2191/462614",
    "sg:postcode":"42857",
    "sg:province":"Nordrhein-Westfalen",
    "wof:name":"P. Kaufmann",
    "wof:placetype":"venue"
},
  "geometry": {"coordinates":[7.164552,51.17643],"type":"Point"}
}