{
  "type": "Feature",
  "properties": {
    "iso:country":"DE",
    "sg:address":"Badmauer 12",
    "sg:city":"Schw\u00e4bisch Gm\u00fcnd",
    "sg:phone":"+49 7171/66003",
    "sg:postcode":"73525",
    "sg:province":"Baden-W\u00fcrttemberg",
    "wof:name":"Bistro Badmauer Inh. Hans Giedat",
    "wof:placetype":"venue"
},
  "geometry": {"coordinates":[9.7945013046,48.799369812],"type":"Point"}
}