{
  "type": "Feature",
  "properties": {
    "iso:country":"DE",
    "sg:address":"Papenreye 22",
    "sg:city":"Hamburg",
    "sg:phone":"+49 40/581742",
    "sg:postcode":"22453",
    "sg:province":"Hamburg",
    "wof:name":"F & R Verm\u00f6gensverwaltungs- Gesellschaft Mbh",
    "wof:placetype":"venue"
},
  "geometry": {"coordinates":[9.965014,53.612793],"type":"Point"}
}