{
  "type": "Feature",
  "properties": {
    "iso:country":"DE",
    "sg:address":"Schwetzinger Str. 120",
    "sg:city":"Heidelberg",
    "sg:phone":"+49 6221/785159",
    "sg:postcode":"69124",
    "sg:province":"Baden-W\u00fcrttemberg",
    "wof:name":"Pelz Immobilienmakler",
    "wof:placetype":"venue"
},
  "geometry": {"coordinates":[8.6727333069,49.3837661743],"type":"Point"}
}