{
  "type": "Feature",
  "properties": {
    "iso:country":"DE",
    "sg:address":"Am Rotweg 3",
    "sg:city":"Volkach",
    "sg:phone":"+49 9381/2076",
    "sg:postcode":"97332",
    "sg:province":"Bayern",
    "wof:name":"Ludwig Meusert",
    "wof:placetype":"venue"
},
  "geometry": {"coordinates":[10.1687135696,49.8790664673],"type":"Point"}
}