{
  "type": "Feature",
  "properties": {
    "iso:country":"DE",
    "sg:address":"Friedrichstr. 50",
    "sg:city":"Bonn",
    "sg:phone":"+49 228/5696230",
    "sg:postcode":"53111",
    "sg:province":"Nordrhein-Westfalen",
    "wof:name":"Kern & Friends Unternehmensberatung Und",
    "wof:placetype":"venue"
},
  "geometry": {"coordinates":[7.1028800011,50.7366371155],"type":"Point"}
}