{
  "type": "Feature",
  "properties": {
    "iso:country":"DE",
    "sg:address":"Am Reifenberg 31",
    "sg:city":"Ottrau",
    "sg:phone":"+49 6628/1897",
    "sg:postcode":"34633",
    "sg:province":"Hessen",
    "wof:name":"Georg Dotzel",
    "wof:placetype":"venue"
},
  "geometry": {"coordinates":[9.4122047424,50.8362350464],"type":"Point"}
}