{
  "type": "Feature",
  "properties": {
    "iso:country":"DE",
    "sg:address":"Maa\u00dfenstr. 5",
    "sg:city":"Bornheim",
    "sg:phone":"+49 2227/3259",
    "sg:postcode":"53332",
    "sg:province":"Nordrhein-Westfalen",
    "wof:name":"Jakob Schumacher",
    "wof:placetype":"venue"
},
  "geometry": {"coordinates":[6.9283080101,50.7624053955],"type":"Point"}
}