{
  "type": "Feature",
  "properties": {
    "iso:country":"DE",
    "sg:address":"Spiekersh\u00e4user Str. 9",
    "sg:city":"Niestetal",
    "sg:phone":"+49 561/526953",
    "sg:postcode":"34266",
    "sg:province":"Hessen",
    "wof:name":"H. Hahn",
    "wof:placetype":"venue"
},
  "geometry": {"coordinates":[9.555035,51.32523],"type":"Point"}
}