{
  "type": "Feature",
  "properties": {
    "iso:country":"DE",
    "sg:address":"Am Listholze 29",
    "sg:city":"Hannover",
    "sg:phone":"+49 511/699003",
    "sg:postcode":"30177",
    "sg:province":"Niedersachsen",
    "wof:name":"Drk Altenpflegeheim Am Listholze",
    "wof:placetype":"venue"
},
  "geometry": {"coordinates":[9.763591,52.398338],"type":"Point"}
}