{
  "type": "Feature",
  "properties": {
    "iso:country":"DE",
    "sg:city":"Oldenburg",
    "sg:phone":"+49 441/81018",
    "sg:postcode":"26123",
    "sg:province":"Niedersachsen",
    "wof:name":"B\u00fcro Extern Gmbh",
    "wof:placetype":"venue"
},
  "geometry": {"coordinates":[8.22239,53.149727],"type":"Point"}
}