{
  "type": "Feature",
  "properties": {
    "iso:country":"DE",
    "sg:address":"Keveraerer Str. 50",
    "sg:city":"Weeze",
    "sg:phone":"+49 2837/95662",
    "sg:postcode":"47652",
    "sg:province":"Nordrhein-Westfalen",
    "wof:name":"Kiek Doch Ma Rin - Martenson",
    "wof:placetype":"venue"
},
  "geometry": {"coordinates":[6.1984372139,51.6263237],"type":"Point"}
}