{
  "type": "Feature",
  "properties": {
    "iso:country":"DE",
    "sg:address":"Am Lindacker 38",
    "sg:city":"Freiburg",
    "sg:phone":"+49 761/491519",
    "sg:postcode":"79115",
    "sg:province":"Baden-W\u00fcrttemberg",
    "wof:name":"Prof. Dr. Klaus-dieter Pohl Ingenieur",
    "wof:placetype":"venue"
},
  "geometry": {"coordinates":[7.8139219284,47.985294342],"type":"Point"}
}