{
  "type": "Feature",
  "properties": {
    "iso:country":"DE",
    "sg:address":"Robert-Bosch-Str. 5",
    "sg:city":"Olfen",
    "sg:phone":"+49 2595/972233",
    "sg:postcode":"59399",
    "sg:province":"Nordrhein-Westfalen",
    "wof:name":"Heinrich Isselbach",
    "wof:placetype":"venue"
},
  "geometry": {"coordinates":[7.386887,51.705624],"type":"Point"}
}