{
  "type": "Feature",
  "properties": {
    "iso:country":"DE",
    "sg:address":"Alt Nowawes 116",
    "sg:city":"Potsdam",
    "sg:postcode":"14482",
    "sg:province":"Brandenburg",
    "wof:name":"Epi - Erich Pommer Institut F\u00fcr Medienpraxis",
    "wof:placetype":"venue"
},
  "geometry": {"coordinates":[13.092167,52.398506],"type":"Point"}
}