{
  "type": "Feature",
  "properties": {
    "iso:country":"DE",
    "sg:address":"Am Lindenhofe 25",
    "sg:city":"Hannover",
    "sg:postcode":"30519",
    "sg:province":"Niedersachsen",
    "wof:name":"Patrick P\u00fcnder Architekt",
    "wof:placetype":"venue"
},
  "geometry": {"coordinates":[9.762537,52.334454],"type":"Point"}
}