{
  "type": "Feature",
  "properties": {
    "iso:country":"DE",
    "sg:address":"Hartham 11",
    "sg:city":"Neuhaus",
    "sg:phone":"+49 8503/90020",
    "sg:postcode":"94152",
    "sg:province":"Bayern",
    "wof:name":"Lutz Maschinen- Und Ger\u00e4tebau Gmbh",
    "wof:placetype":"venue"
},
  "geometry": {"coordinates":[13.390485,48.441227],"type":"Point"}
}