{
  "type": "Feature",
  "properties": {
    "iso:country":"DE",
    "sg:address":"Broicher Kaul 35",
    "sg:city":"J\u00fcchen",
    "sg:phone":"+49 2181/40905",
    "sg:postcode":"41363",
    "sg:province":"Nordrhein-Westfalen",
    "wof:name":"Gierather Stuben",
    "wof:placetype":"venue"
},
  "geometry": {"coordinates":[6.5514278412,51.1131439209],"type":"Point"}
}