{
  "type": "Feature",
  "properties": {
    "iso:country":"DE",
    "sg:address":"Karwendelring 4",
    "sg:city":"Schongau",
    "sg:phone":"+49 8861/71793",
    "sg:postcode":"86956",
    "sg:province":"Bayern",
    "wof:name":"Agostino Nicoletti",
    "wof:placetype":"venue"
},
  "geometry": {"coordinates":[10.8755931854,47.8062820435],"type":"Point"}
}