{
  "type": "Feature",
  "properties": {
    "iso:country":"DE",
    "sg:address":"Breite Str. 38",
    "sg:city":"Rochau",
    "sg:phone":"+49 39328/202",
    "sg:postcode":"39579",
    "sg:province":"Sachsen-Anhalt",
    "wof:name":"H. J. Seehaus",
    "wof:placetype":"venue"
},
  "geometry": {"coordinates":[11.7489528656,52.7067108154],"type":"Point"}
}