{
  "type": "Feature",
  "properties": {
    "iso:country":"DE",
    "sg:address":"Siebenh\u00f6fen 6",
    "sg:city":"Hollern-Twielenfleth",
    "sg:postcode":"21723",
    "sg:province":"Niedersachsen",
    "wof:name":"Rinck Altl\u00e4nder Kisten Und Paletten E. K.",
    "wof:placetype":"venue"
},
  "geometry": {"coordinates":[9.573459,53.589214],"type":"Point"}
}