{
  "type": "Feature",
  "properties": {
    "iso:country":"DE",
    "sg:address":"Bei der Kammer 32",
    "sg:city":"Wildeshausen",
    "sg:phone":"+49 4431/74043",
    "sg:postcode":"27793",
    "sg:province":"Niedersachsen",
    "wof:name":"Office Ges. F\u00fcr B\u00fcroservice Mbh",
    "wof:placetype":"venue"
},
  "geometry": {"coordinates":[8.4291667938,52.8833312988],"type":"Point"}
}