{
  "type": "Feature",
  "properties": {
    "iso:country":"DE",
    "sg:address":"Schivelbeiner Stra\u00dfe 2",
    "sg:city":"Berlin",
    "sg:phone":"+49 30/50579304",
    "sg:postcode":"10439",
    "sg:province":"Berlin",
    "wof:name":"Die Serviceseiten F\u00fcr Die Kunst In Berlin",
    "wof:placetype":"venue"
},
  "geometry": {"coordinates":[13.413035,52.550938],"type":"Point"}
}