{
  "type": "Feature",
  "properties": {
    "iso:country":"DE",
    "sg:address":"Esebeckstr. 22",
    "sg:city":"M\u00fcnchen",
    "sg:phone":"+49 89",
    "sg:postcode":"80637",
    "sg:province":"Bayern",
    "wof:name":"Pewitel",
    "wof:placetype":"venue"
},
  "geometry": {"coordinates":[11.534942,48.164459],"type":"Point"}
}