{
  "type": "Feature",
  "properties": {
    "iso:country":"DE",
    "sg:address":"Kanalstr. 2",
    "sg:city":"Fellbach",
    "sg:phone":"+49 711/512293",
    "sg:postcode":"70736",
    "sg:province":"Baden-W\u00fcrttemberg",
    "wof:name":"Barbarino",
    "wof:placetype":"venue"
},
  "geometry": {"coordinates":[9.263538,48.834202],"type":"Point"}
}