{
  "type": "Feature",
  "properties": {
    "iso:country":"DE",
    "sg:address":"Egger Str. 3 a",
    "sg:city":"Itterbeck",
    "sg:postcode":"49847",
    "sg:province":"Niedersachsen",
    "wof:name":"Mollen & Braker Gmbh",
    "wof:placetype":"venue"
},
  "geometry": {"coordinates":[6.7974529266,52.505645752],"type":"Point"}
}