{
  "type": "Feature",
  "properties": {
    "iso:country":"DE",
    "sg:address":"Villiper Kreuzgasse 7",
    "sg:city":"Wachtberg",
    "sg:postcode":"53343",
    "sg:province":"Nordrhein-Westfalen",
    "wof:name":"Lamberz Exclusiv-haus Gmbh",
    "wof:placetype":"venue"
},
  "geometry": {"coordinates":[7.095846,50.636669],"type":"Point"}
}