{
  "type": "Feature",
  "properties": {
    "iso:country":"DE",
    "sg:address":"Obere Herrngasse 11",
    "sg:city":"Schw\u00e4bisch Hall",
    "sg:phone":"+49 791/6101",
    "sg:postcode":"74523",
    "sg:province":"Baden-W\u00fcrttemberg",
    "wof:name":"M\u00fcller Und Ebner Rechtsanw\u00e4lte",
    "wof:placetype":"venue"
},
  "geometry": {"coordinates":[9.7377357483,49.1115493774],"type":"Point"}
}