{
  "type": "Feature",
  "properties": {
    "iso:country":"DE",
    "sg:address":"Au\u00dferhalb 3",
    "sg:city":"B\u00fcttelborn",
    "sg:phone":"+49 6152/55072",
    "sg:postcode":"64572",
    "sg:province":"Hessen",
    "wof:name":"Karlheinz Luley",
    "wof:placetype":"venue"
},
  "geometry": {"coordinates":[8.546276,49.921284],"type":"Point"}
}