{
  "type": "Feature",
  "properties": {
    "iso:country":"DE",
    "sg:address":"Am Museum 5",
    "sg:city":"Friedrichsruh",
    "sg:phone":"+49 4104/1421",
    "sg:postcode":"21521",
    "sg:province":"Schleswig-Holstein",
    "wof:name":"F\u00fcrstlich Von Bismarcksches Archiv",
    "wof:placetype":"venue"
},
  "geometry": {"coordinates":[10.339262,53.528767],"type":"Point"}
}