{
  "type": "Feature",
  "properties": {
    "iso:country":"DE",
    "sg:address":"Gr\u00fcndlachstr. 45",
    "sg:city":"Eckental",
    "sg:postcode":"90542",
    "sg:province":"Bayern",
    "wof:name":"Pkm Beteiligungs Gmbh",
    "wof:placetype":"venue"
},
  "geometry": {"coordinates":[11.169402,49.575642],"type":"Point"}
}