{
  "type": "Feature",
  "properties": {
    "iso:country":"DE",
    "sg:address":"Kl\u00f6nnestr. 86",
    "sg:city":"Dortmund",
    "sg:phone":"+49 231/577970",
    "sg:postcode":"44143",
    "sg:province":"Nordrhein-Westfalen",
    "wof:name":"Emil Kraft Holding Gmbh",
    "wof:placetype":"venue"
},
  "geometry": {"coordinates":[7.487687,51.518818],"type":"Point"}
}