{
  "type": "Feature",
  "properties": {
    "iso:country":"DE",
    "sg:address":"Friedrich-Ludwig-Jahn-Str. 52",
    "sg:city":"Oberursel",
    "sg:phone":"+49 6171/74798",
    "sg:postcode":"61440",
    "sg:province":"Hessen",
    "wof:name":"W. Magard",
    "wof:placetype":"venue"
},
  "geometry": {"coordinates":[8.6011819839,50.1851539612],"type":"Point"}
}