{
  "type": "Feature",
  "properties": {
    "iso:country":"DE",
    "sg:address":"Bogenstr. 3",
    "sg:city":"Neunkirchen",
    "sg:phone":"+49 9123/3578",
    "sg:postcode":"91233",
    "sg:province":"Bayern",
    "wof:name":"Johann Rebler",
    "wof:placetype":"venue"
},
  "geometry": {"coordinates":[11.3157072067,49.5227165222],"type":"Point"}
}