{
  "type": "Feature",
  "properties": {
    "iso:country":"DE",
    "sg:address":"Genenderstr. 99",
    "sg:city":"Erkelenz",
    "sg:phone":"+49 2432/6325",
    "sg:postcode":"41812",
    "sg:province":"Nordrhein-Westfalen",
    "wof:name":"Leo-josef Schmitz",
    "wof:placetype":"venue"
},
  "geometry": {"coordinates":[6.219596,51.094456],"type":"Point"}
}