{
  "type": "Feature",
  "properties": {
    "iso:country":"DE",
    "sg:address":"Auf Kampen 17",
    "sg:city":"B\u00e4renbach",
    "sg:phone":"+49 6784/981900",
    "sg:postcode":"55758",
    "sg:province":"Rheinland-Pfalz",
    "wof:name":"Ingenieurb\u00fcro Faulhaber Gmbh",
    "wof:placetype":"venue"
},
  "geometry": {"coordinates":[7.444152832,49.7475547791],"type":"Point"}
}