{
  "type": "Feature",
  "properties": {
    "iso:country":"DE",
    "sg:address":"Altengammer Hauptdeich 62",
    "sg:city":"Hamburg",
    "sg:phone":"+49 40/7235441",
    "sg:postcode":"21039",
    "sg:province":"Hamburg",
    "wof:name":"Justus Habermann",
    "wof:placetype":"venue"
},
  "geometry": {"coordinates":[10.302393,53.438717],"type":"Point"}
}