{
  "type": "Feature",
  "properties": {
    "iso:country":"DE",
    "sg:address":"Panner Str. 12",
    "sg:city":"Velbert",
    "sg:phone":"+49 2052/7851",
    "sg:postcode":"42555",
    "sg:province":"Nordrhein-Westfalen",
    "wof:name":"Bender Immobilien Gmbh & Co. Kg",
    "wof:placetype":"venue"
},
  "geometry": {"coordinates":[7.125441,51.348759],"type":"Point"}
}