{
  "type": "Feature",
  "properties": {
    "iso:country":"DE",
    "sg:address":"Am Tiergarten 16",
    "sg:city":"Hannover",
    "sg:postcode":"30559",
    "sg:province":"Niedersachsen",
    "wof:name":"Patricks Networx",
    "wof:placetype":"venue"
},
  "geometry": {"coordinates":[9.853465,52.36306],"type":"Point"}
}