{
  "type": "Feature",
  "properties": {
    "iso:country":"DE",
    "sg:address":"Georg-Wimmer-Ring 21",
    "sg:city":"Zorneding",
    "sg:phone":"+49 8106/24130",
    "sg:postcode":"85604",
    "sg:province":"Bayern",
    "wof:name":"Peter Pflugbeil Gmbh",
    "wof:placetype":"venue"
},
  "geometry": {"coordinates":[11.8252401352,48.0920524597],"type":"Point"}
}