{
  "type": "Feature",
  "properties": {
    "iso:country":"DE",
    "sg:address":"F\u00fcchtenfeld 22",
    "sg:city":"Gronau-Epe",
    "sg:phone":"+49 4956/7299960",
    "sg:postcode":"48599",
    "sg:province":"Nordrhein-Westfalen",
    "wof:name":"K & S Sportbel\u00c4ge Handel & Diestleistungs Gmbh",
    "wof:placetype":"venue"
},
  "geometry": {"coordinates":[9.449055,51.645515],"type":"Point"}
}