{
  "type": "Feature",
  "properties": {
    "iso:country":"DE",
    "sg:address":"Roermonder Str. 236",
    "sg:city":"\u00dcbach-Palenberg",
    "sg:phone":"+49 2404/1704",
    "sg:postcode":"52531",
    "sg:province":"Nordrhein-Westfalen",
    "wof:name":"Gastst\u00e4tte Josef Jansen",
    "wof:placetype":"venue"
},
  "geometry": {"coordinates":[6.1355910301,50.9014549255],"type":"Point"}
}