{
  "type": "Feature",
  "properties": {
    "iso:country":"DE",
    "sg:address":"Efferter Str. 57",
    "sg:city":"Neunkirchen-Seelscheid",
    "sg:phone":"+49 2247/6400",
    "sg:postcode":"53819",
    "sg:province":"Nordrhein-Westfalen",
    "wof:name":"Werner Baumgarten",
    "wof:placetype":"venue"
},
  "geometry": {"coordinates":[7.28501,50.864876],"type":"Point"}
}