{
  "type": "Feature",
  "properties": {
    "iso:country":"DE",
    "sg:address":"Hamburger Str. 61",
    "sg:city":"Ammersbek",
    "sg:phone":"+49 40/6050956",
    "sg:postcode":"22949",
    "sg:province":"Schleswig-Holstein",
    "wof:name":"Franz Feddern & Sohn Kg",
    "wof:placetype":"venue"
},
  "geometry": {"coordinates":[10.1580190659,53.6848068237],"type":"Point"}
}