{
  "type": "Feature",
  "properties": {
    "iso:country":"DE",
    "sg:address":"Hagener Str. 325",
    "sg:city":"Gevelsberg",
    "sg:phone":"+49 2332/6690",
    "sg:postcode":"58285",
    "sg:province":"Nordrhein-Westfalen",
    "wof:name":"Intertractor Gmbh",
    "wof:placetype":"venue"
},
  "geometry": {"coordinates":[7.3777651787,51.3339920044],"type":"Point"}
}