{
  "type": "Feature",
  "properties": {
    "iso:country":"DE",
    "sg:address":"Lotzbeckstr. 25",
    "sg:city":"Lahr",
    "sg:phone":"+49 7821/271060",
    "sg:postcode":"77933",
    "sg:province":"Baden-W\u00fcrttemberg",
    "wof:name":"Andreas Estenfeld Rechtsanwalt",
    "wof:placetype":"venue"
},
  "geometry": {"coordinates":[7.8667988777,48.3393745422],"type":"Point"}
}