{
  "type": "Feature",
  "properties": {
    "iso:country":"DE",
    "sg:address":"Untergasse 25",
    "sg:city":"Gudensberg",
    "sg:phone":"+49 5603/4793",
    "sg:postcode":"34281",
    "sg:province":"Hessen",
    "wof:name":"Venezia",
    "wof:placetype":"venue"
},
  "geometry": {"coordinates":[9.369169,51.177666],"type":"Point"}
}