{
  "type": "Feature",
  "properties": {
    "iso:country":"DE",
    "sg:address":"Neustadter Str. 35",
    "sg:city":"Landau",
    "sg:phone":"+49 6341/20359",
    "sg:postcode":"76829",
    "sg:province":"Rheinland-Pfalz",
    "wof:name":"Gerd Poulsen",
    "wof:placetype":"venue"
},
  "geometry": {"coordinates":[8.115815,49.206886],"type":"Point"}
}