{
  "type": "Feature",
  "properties": {
    "iso:country":"DE",
    "sg:address":"Gewerbegebiet 14",
    "sg:city":"B\u00f6hlen",
    "sg:phone":"+49 34206/55041",
    "sg:postcode":"04564",
    "sg:province":"Sachsen",
    "wof:name":"S+m Werbe-licht-tontechnik Schiewick",
    "wof:placetype":"venue"
},
  "geometry": {"coordinates":[12.39368,51.193886],"type":"Point"}
}