{
  "type": "Feature",
  "properties": {
    "iso:country":"DE",
    "sg:address":"Setheweg",
    "sg:city":"Seebad Heringsdorf",
    "sg:postcode":"17424",
    "sg:province":"Mecklenburg-Vorpommern",
    "wof:name":"Baugesellschaft Wolgast Mbh Ig",
    "wof:placetype":"venue"
},
  "geometry": {"coordinates":[14.156909,53.95285],"type":"Point"}
}