{
  "type": "Feature",
  "properties": {
    "iso:country":"DE",
    "sg:address":"Grimselweg 89",
    "sg:city":"Berlin",
    "sg:phone":"+49 30/81886713",
    "sg:postcode":"13089",
    "sg:province":"Berlin",
    "wof:name":"Willkommen Bei Kgb-berlin, Garten-u.landschaftsbau",
    "wof:placetype":"venue"
},
  "geometry": {"coordinates":[13.455938,52.574287],"type":"Point"}
}