{
  "type": "Feature",
  "properties": {
    "iso:country":"DE",
    "sg:address":"Pfauseeallee 1",
    "sg:city":"Emleben",
    "sg:phone":"+49 3621/709076",
    "sg:postcode":"99869",
    "sg:province":"Th\u00fcringen",
    "wof:name":"Grohnert",
    "wof:placetype":"venue"
},
  "geometry": {"coordinates":[10.71052,50.892895],"type":"Point"}
}