{
  "type": "Feature",
  "properties": {
    "iso:country":"DE",
    "sg:address":"Schlo\u00dfgasse 1",
    "sg:city":"Niederwerrn",
    "sg:phone":"+49 9721/48160",
    "sg:postcode":"97464",
    "sg:province":"Bayern",
    "wof:name":"Evangelischer Kirchenbauverein Niederwerrn",
    "wof:placetype":"venue"
},
  "geometry": {"coordinates":[10.17527771,50.0626907349],"type":"Point"}
}