{
  "type": "Feature",
  "properties": {
    "iso:country":"DE",
    "sg:address":"Vogelleithe 8",
    "sg:city":"R\u00f6ttenbach",
    "sg:phone":"+49 9195/8637",
    "sg:postcode":"91341",
    "sg:province":"Bayern",
    "wof:name":"Johannes Kallweit Rechtsanwalt",
    "wof:placetype":"venue"
},
  "geometry": {"coordinates":[10.9208745956,49.6688079834],"type":"Point"}
}