{
  "type": "Feature",
  "properties": {
    "iso:country":"DE",
    "sg:address":"Sepkamp 37",
    "sg:city":"Lemgo",
    "sg:phone":"+49 5261/68394",
    "sg:postcode":"32657",
    "sg:province":"Nordrhein-Westfalen",
    "wof:name":"J\u00f6rg David",
    "wof:placetype":"venue"
},
  "geometry": {"coordinates":[8.8425445557,52.0254974365],"type":"Point"}
}