{
  "type": "Feature",
  "properties": {
    "iso:country":"DE",
    "sg:address":"Hauptstr. 42",
    "sg:city":"Recke",
    "sg:phone":"+49 5453/7799",
    "sg:postcode":"49509",
    "sg:province":"Nordrhein-Westfalen",
    "wof:name":"Wolfs Aktivm\u00e4rkte Gmbh",
    "wof:placetype":"venue"
},
  "geometry": {"coordinates":[7.7185721397,52.3663101196],"type":"Point"}
}