{
  "type": "Feature",
  "properties": {
    "iso:country":"DE",
    "sg:address":"Attendorner-Tor-Str. 9",
    "sg:city":"Wipperf\u00fcrth",
    "sg:phone":"+49 2267/9240",
    "sg:postcode":"51688",
    "sg:province":"Nordrhein-Westfalen",
    "wof:name":"Verein Der Freunde Und F\u00f6rderer Der St\u00e4dt. Kath.",
    "wof:placetype":"venue"
},
  "geometry": {"coordinates":[7.4006128311,51.1170883179],"type":"Point"}
}