{
  "type": "Feature",
  "properties": {
    "iso:country":"DE",
    "sg:address":"Bischof-Stradmann-Str. 22",
    "sg:city":"Bad H\u00f6nningen",
    "sg:phone":"+49 2635/3542",
    "sg:postcode":"53557",
    "sg:province":"Rheinland-Pfalz",
    "wof:name":"J\u00fcrgen Quatram Elektroinstallation",
    "wof:placetype":"venue"
},
  "geometry": {"coordinates":[7.309391,50.516361],"type":"Point"}
}