{
  "type": "Feature",
  "properties": {
    "iso:country":"DE",
    "sg:address":"Alte Kreisstr. 29",
    "sg:city":"Haimhausen",
    "sg:phone":"+49 8133/8436",
    "sg:postcode":"85778",
    "sg:province":"Bayern",
    "wof:name":"Fair Handelshaus Bayern Eg",
    "wof:placetype":"venue"
},
  "geometry": {"coordinates":[11.532532692,48.3260383606],"type":"Point"}
}