{
  "type": "Feature",
  "properties": {
    "iso:country":"DE",
    "sg:address":"Dorfstr. 11",
    "sg:city":"D\u00f6tlingen",
    "sg:phone":"+49 4432/357",
    "sg:postcode":"27801",
    "sg:province":"Niedersachsen",
    "wof:name":"Johann Heinefeld",
    "wof:placetype":"venue"
},
  "geometry": {"coordinates":[8.382611,52.935116],"type":"Point"}
}