{
  "type": "Feature",
  "properties": {
    "iso:country":"DE",
    "sg:address":"Hafenstr. 20",
    "sg:city":"Mei\u00dfen",
    "sg:phone":"+49 3521/734212",
    "sg:postcode":"01662",
    "sg:province":"Sachsen",
    "wof:name":"H. M\u00fcller",
    "wof:placetype":"venue"
},
  "geometry": {"coordinates":[13.4775180817,51.1674118042],"type":"Point"}
}