{
  "type": "Feature",
  "properties": {
    "iso:country":"DE",
    "sg:address":"Gasthausplatz 2",
    "sg:city":"Bocholt",
    "sg:phone":"+49 2871/12837",
    "sg:postcode":"46397",
    "sg:province":"Nordrhein-Westfalen",
    "wof:name":"Hotel-restaurant Werk Ii",
    "wof:placetype":"venue"
},
  "geometry": {"coordinates":[6.6156129837,51.8389511108],"type":"Point"}
}