{
  "type": "Feature",
  "properties": {
    "iso:country":"DE",
    "sg:address":"Helsinkier Stra\u00dfe 30",
    "sg:city":"Rostock",
    "sg:phone":"+49 381",
    "sg:postcode":"18107",
    "sg:province":"Mecklenburg-Vorpommern",
    "wof:name":"Vi-media",
    "wof:placetype":"venue"
},
  "geometry": {"coordinates":[12.054768,54.135071],"type":"Point"}
}