{
  "type": "Feature",
  "properties": {
    "iso:country":"DE",
    "sg:address":"Schwanheimer Str. 23",
    "sg:city":"Eberbach",
    "sg:phone":"+49 6271/3571",
    "sg:postcode":"69412",
    "sg:province":"Baden-W\u00fcrttemberg",
    "wof:name":"Heinrich Schmitt",
    "wof:placetype":"venue"
},
  "geometry": {"coordinates":[8.980509758,49.458480835],"type":"Point"}
}