{
  "type": "Feature",
  "properties": {
    "iso:country":"DE",
    "sg:address":"Limbacher Str. 3",
    "sg:city":"Chemnitz",
    "sg:phone":"+49 371/302608",
    "sg:postcode":"09113",
    "sg:province":"Sachsen",
    "wof:name":"Ingenieurgruppe Technik",
    "wof:placetype":"venue"
},
  "geometry": {"coordinates":[12.9059276581,50.8386077881],"type":"Point"}
}