{
  "type": "Feature",
  "properties": {
    "iso:country":"DE",
    "sg:address":"An der Beek 6",
    "sg:city":"Weeze",
    "sg:phone":"+49 2837/397",
    "sg:postcode":"47652",
    "sg:province":"Nordrhein-Westfalen",
    "wof:name":"Johann Borghorst",
    "wof:placetype":"venue"
},
  "geometry": {"coordinates":[6.18119,51.590889],"type":"Point"}
}