{
  "type": "Feature",
  "properties": {
    "iso:country":"DE",
    "sg:address":"Meschenicher Str. 451",
    "sg:city":"K\u00f6ln",
    "sg:postcode":"50997",
    "sg:province":"Nordrhein-Westfalen",
    "wof:name":"G\u00e4steh\u00e4user Exner Gmbh",
    "wof:placetype":"venue"
},
  "geometry": {"coordinates":[6.9756221771,50.847984314],"type":"Point"}
}