{
  "type": "Feature",
  "properties": {
    "iso:country":"DE",
    "sg:address":"Salzburger Str. 1",
    "sg:city":"Freilassing",
    "sg:phone":"+49 8654/66060",
    "sg:postcode":"83395",
    "sg:province":"Bayern",
    "wof:name":"Kimmel",
    "wof:placetype":"venue"
},
  "geometry": {"coordinates":[12.983288,47.841011],"type":"Point"}
}