{
  "type": "Feature",
  "properties": {
    "iso:country":"DE",
    "sg:address":"Sodentwiete 14",
    "sg:city":"Hamburg",
    "sg:phone":"+49 40/590635",
    "sg:postcode":"22337",
    "sg:province":"Hamburg",
    "wof:name":"Christine Hacker",
    "wof:placetype":"venue"
},
  "geometry": {"coordinates":[10.0574226379,53.6318893433],"type":"Point"}
}