{
  "type": "Feature",
  "properties": {
    "iso:country":"DE",
    "sg:address":"Kirchstr. 10",
    "sg:city":"Jestetten",
    "sg:phone":"+49 7745/7248",
    "sg:postcode":"79798",
    "sg:province":"Baden-W\u00fcrttemberg",
    "wof:name":"Kath. Pfarramt St. Benedikt",
    "wof:placetype":"venue"
},
  "geometry": {"coordinates":[8.5703516006,47.650177002],"type":"Point"}
}