{
  "type": "Feature",
  "properties": {
    "iso:country":"DE",
    "sg:address":"Arthur-Hoffmann-Str. 74 d",
    "sg:city":"Leipzig",
    "sg:phone":"+49 341/3027001",
    "sg:postcode":"04275",
    "sg:province":"Sachsen",
    "wof:name":"Rudolf Uhlisch",
    "wof:placetype":"venue"
},
  "geometry": {"coordinates":[12.378472,51.324425],"type":"Point"}
}