{
  "type": "Feature",
  "properties": {
    "iso:country":"DE",
    "sg:address":"Rothbachstr. 11",
    "sg:city":"Rotenburg",
    "sg:phone":"+49 4261/971294",
    "sg:postcode":"27356",
    "sg:province":"Niedersachsen",
    "wof:name":"Architekturb\u00fcro Maa\u00df",
    "wof:placetype":"venue"
},
  "geometry": {"coordinates":[9.426836,53.110718],"type":"Point"}
}