{
  "type": "Feature",
  "properties": {
    "iso:country":"DE",
    "sg:address":"Stra\u00dfburger Str. 69",
    "sg:city":"Stuttgart",
    "sg:phone":"+49 711/875226",
    "sg:postcode":"70435",
    "sg:province":"Baden-W\u00fcrttemberg",
    "wof:name":"Hirsch-apotheke",
    "wof:placetype":"venue"
},
  "geometry": {"coordinates":[9.168665,48.829796],"type":"Point"}
}