{
  "type": "Feature",
  "properties": {
    "iso:country":"DE",
    "sg:address":"Bemeroder Str. 68",
    "sg:city":"Hannover",
    "sg:postcode":"30559",
    "sg:province":"Niedersachsen",
    "wof:name":"Bemeroder Stra\u00dfe Grundst\u00fccks- Entwicklung Beteiligungs Gmbh",
    "wof:placetype":"venue"
},
  "geometry": {"coordinates":[9.813048,52.347439],"type":"Point"}
}