{
  "type": "Feature",
  "properties": {
    "iso:country":"DE",
    "sg:address":"Industriestr. 7",
    "sg:city":"Bischberg",
    "sg:phone":"+49 951/386",
    "sg:postcode":"96120",
    "sg:province":"Bayern",
    "wof:name":"E. St\u00f6ssel",
    "wof:placetype":"venue"
},
  "geometry": {"coordinates":[10.809626,49.91711],"type":"Point"}
}