{
  "type": "Feature",
  "properties": {
    "iso:country":"DE",
    "sg:address":"Triftstr. 16",
    "sg:city":"Oberau",
    "sg:phone":"+49 8824/8365",
    "sg:postcode":"82496",
    "sg:province":"Bayern",
    "wof:name":"Hans Kremer",
    "wof:placetype":"venue"
},
  "geometry": {"coordinates":[11.1343269348,47.5634651184],"type":"Point"}
}