{
  "type": "Feature",
  "properties": {
    "iso:country":"DE",
    "sg:address":"Kirchstr. 19",
    "sg:city":"Grafrath",
    "sg:postcode":"82284",
    "sg:province":"Bayern",
    "wof:name":"Remenova-peters Edv Und Unternehmensberatung Gmbh",
    "wof:placetype":"venue"
},
  "geometry": {"coordinates":[11.1654977798,48.1192855835],"type":"Point"}
}