{
  "type": "Feature",
  "properties": {
    "iso:country":"DE",
    "sg:address":"Passauer Str. 9",
    "sg:city":"Untergriesbach",
    "sg:phone":"+49 8593/1001",
    "sg:postcode":"94107",
    "sg:province":"Bayern",
    "wof:name":"Volksb\u00fccherei Kath. Pfarramt",
    "wof:placetype":"venue"
},
  "geometry": {"coordinates":[13.665336,48.573456],"type":"Point"}
}