{
  "type": "Feature",
  "properties": {
    "iso:country":"DE",
    "sg:address":"Hauptstr 42",
    "sg:city":"Oberma\u00dffeld-Grimmenthal",
    "sg:phone":"+49 36949/4060",
    "sg:postcode":"98617",
    "sg:province":"Th\u00fcringen",
    "wof:name":"Ews Umform- Und Verbindungstechnik Gmbh",
    "wof:placetype":"venue"
},
  "geometry": {"coordinates":[10.4506797791,50.5313262939],"type":"Point"}
}