{
  "type": "Feature",
  "properties": {
    "iso:country":"DE",
    "sg:address":"Gartenstr. 49",
    "sg:city":"Neuss",
    "sg:phone":"+49 2131/23970",
    "sg:postcode":"41460",
    "sg:province":"Nordrhein-Westfalen",
    "wof:name":"Trade Support S & P Gesell. F\u00fcr Handelsmarketing Und",
    "wof:placetype":"venue"
},
  "geometry": {"coordinates":[6.6842498779,51.1990699768],"type":"Point"}
}