{
  "type": "Feature",
  "properties": {
    "iso:country":"DE",
    "sg:address":"Bahnhofstr.",
    "sg:city":"Schierau",
    "sg:postcode":"06779",
    "sg:province":"Sachsen-Anhalt",
    "wof:name":"Automatendreherei Und Mechanik Gmbh",
    "wof:placetype":"venue"
},
  "geometry": {"coordinates":[12.282716,51.746735],"type":"Point"}
}