{
  "type": "Feature",
  "properties": {
    "iso:country":"DE",
    "sg:address":"Sechzigstr. 29",
    "sg:city":"K\u00f6ln",
    "sg:postcode":"50733",
    "sg:province":"Nordrhein-Westfalen",
    "wof:name":"Italbau Gmbh",
    "wof:placetype":"venue"
},
  "geometry": {"coordinates":[6.9481091499,50.9597053528],"type":"Point"}
}