{
  "type": "Feature",
  "properties": {
    "iso:country":"DE",
    "sg:city":"Reifenberg",
    "sg:phone":"+49 6334/710",
    "sg:postcode":"66507",
    "sg:province":"Rheinland-Pfalz",
    "wof:name":"Montage Gmbh F\u00fcr Baulemente Thomas Quarz",
    "wof:placetype":"venue"
},
  "geometry": {"coordinates":[7.508566,49.281925],"type":"Point"}
}