{
  "type": "Feature",
  "properties": {
    "iso:country":"DE",
    "sg:address":"Ring 20",
    "sg:city":"M\u00f6mbris",
    "sg:phone":"+49 6029/1571",
    "sg:postcode":"63776",
    "sg:province":"Bayern",
    "wof:name":"A. Pfarr",
    "wof:placetype":"venue"
},
  "geometry": {"coordinates":[9.1656370163,50.06665802],"type":"Point"}
}