{
  "type": "Feature",
  "properties": {
    "iso:country":"DE",
    "sg:address":"Rathenaustr. 55",
    "sg:city":"Neu-Isenburg",
    "sg:postcode":"63263",
    "sg:province":"Hessen",
    "wof:name":"Schneider Gmbh",
    "wof:placetype":"venue"
},
  "geometry": {"coordinates":[8.67943,50.042107],"type":"Point"}
}