{
  "type": "Feature",
  "properties": {
    "iso:country":"DE",
    "sg:address":"Riesenstr.9",
    "sg:city":"Kaiserslautern",
    "sg:phone":"+49 631/3605200",
    "sg:postcode":"67655",
    "sg:province":"Rheinland-Pfalz",
    "wof:name":"Allianz Generalvertretung",
    "wof:placetype":"venue"
},
  "geometry": {"coordinates":[7.7699651718,49.4429779053],"type":"Point"}
}