{
  "type": "Feature",
  "properties": {
    "iso:country":"DE",
    "sg:address":"Offenbacher Str. 5",
    "sg:city":"Dreieich",
    "sg:phone":"+49 6103/61706",
    "sg:postcode":"63303",
    "sg:province":"Hessen",
    "wof:name":"Pizzeria Fantastico",
    "wof:placetype":"venue"
},
  "geometry": {"coordinates":[8.6962337494,50.0192146301],"type":"Point"}
}