{
  "type": "Feature",
  "properties": {
    "iso:country":"DE",
    "sg:address":"Am Lohwasser 4",
    "sg:city":"Hessisch Lichtenau",
    "sg:phone":"+49 5602/5593",
    "sg:postcode":"37235",
    "sg:province":"Hessen",
    "wof:name":"Otto Heyner",
    "wof:placetype":"venue"
},
  "geometry": {"coordinates":[9.712322,51.206909],"type":"Point"}
}