{
  "type": "Feature",
  "properties": {
    "iso:country":"DE",
    "sg:address":"Reuterner Str. 11",
    "sg:city":"Wolframs-Eschenbach",
    "sg:phone":"+49 9875/550",
    "sg:postcode":"91639",
    "sg:province":"Bayern",
    "wof:name":"Karl Werner",
    "wof:placetype":"venue"
},
  "geometry": {"coordinates":[10.7285652161,49.2286529541],"type":"Point"}
}