{
  "type": "Feature",
  "properties": {
    "iso:country":"DE",
    "sg:address":"Bahnhofstr. 63",
    "sg:city":"Neuenhaus",
    "sg:phone":"+49 4959/411031",
    "sg:postcode":"49828",
    "sg:province":"Niedersachsen",
    "wof:name":"Raiffeisen-warengen. Veldhausen Eg",
    "wof:placetype":"venue"
},
  "geometry": {"coordinates":[6.9907698631,52.5169410706],"type":"Point"}
}