{
  "type": "Feature",
  "properties": {
    "iso:country":"DE",
    "sg:address":"Lembecker Str. 7",
    "sg:city":"Haltern",
    "sg:phone":"+49 2360/990000",
    "sg:postcode":"45721",
    "sg:province":"Nordrhein-Westfalen",
    "wof:name":"Ebi Elektro Beleuchtung Installation Gmbh",
    "wof:placetype":"venue"
},
  "geometry": {"coordinates":[7.09102,51.71838],"type":"Point"}
}