{
  "type": "Feature",
  "properties": {
    "iso:country":"DE",
    "sg:address":"Wiener Str. 6",
    "sg:city":"Spremberg",
    "sg:phone":"+49 3563/4456",
    "sg:postcode":"03130",
    "sg:province":"Brandenburg",
    "wof:name":"Manfred Mikitta",
    "wof:placetype":"venue"
},
  "geometry": {"coordinates":[14.390315,51.57486],"type":"Point"}
}