{
  "type": "Feature",
  "properties": {
    "iso:country":"DE",
    "sg:address":"Gartenstr. 13",
    "sg:city":"Auerbach",
    "sg:phone":"+49 3744/201230",
    "sg:postcode":"08209",
    "sg:province":"Sachsen",
    "wof:name":"Electric Elb Geb\u00e4ude- Technik Gmbh",
    "wof:placetype":"venue"
},
  "geometry": {"coordinates":[12.404304,50.508839],"type":"Point"}
}