{
  "type": "Feature",
  "properties": {
    "iso:country":"DE",
    "sg:address":"Lorettostr. 59",
    "sg:city":"Freiburg",
    "sg:phone":"+49 761/402641",
    "sg:postcode":"79100",
    "sg:province":"Baden-W\u00fcrttemberg",
    "wof:name":"Ev. Stadtpfarramt Petrusgem.",
    "wof:placetype":"venue"
},
  "geometry": {"coordinates":[7.837515831,47.9841651917],"type":"Point"}
}