{
  "type": "Feature",
  "properties": {
    "iso:country":"DE",
    "sg:address":"Otto-Richter-Str. 8",
    "sg:city":"Mylau",
    "sg:phone":"+49 3765/31802",
    "sg:postcode":"08499",
    "sg:province":"Sachsen",
    "wof:name":"Bianca Br\u00e4utigam",
    "wof:placetype":"venue"
},
  "geometry": {"coordinates":[12.2663021088,50.621219635],"type":"Point"}
}