{
  "type": "Feature",
  "properties": {
    "iso:country":"DE",
    "sg:address":"Amsbergstr. 24",
    "sg:city":"Bad Harzburg",
    "sg:phone":"+49 30/76803313",
    "sg:postcode":"38667",
    "sg:province":"Niedersachsen",
    "wof:name":"Irmhild Johnson",
    "wof:placetype":"venue"
},
  "geometry": {"coordinates":[10.5581893921,51.8742828369],"type":"Point"}
}