{
  "type": "Feature",
  "properties": {
    "iso:country":"DE",
    "sg:address":"Lilienthalstr. 2",
    "sg:city":"Saarlouis",
    "sg:phone":"+49 6831/1404",
    "sg:postcode":"66740",
    "sg:province":"Saarland",
    "wof:name":"Michael Huebner Transporte Gmbh",
    "wof:placetype":"venue"
},
  "geometry": {"coordinates":[6.7351431847,49.3106155396],"type":"Point"}
}