{
  "type": "Feature",
  "properties": {
    "iso:country":"DE",
    "sg:address":"Dahlienstr. 91",
    "sg:city":"Leipzig",
    "sg:phone":"+49 341/4220124",
    "sg:postcode":"04209",
    "sg:province":"Sachsen",
    "wof:name":"Lutz Kreutzmann",
    "wof:placetype":"venue"
},
  "geometry": {"coordinates":[12.3043251038,51.3250465393],"type":"Point"}
}