{
  "type": "Feature",
  "properties": {
    "iso:country":"DE",
    "sg:address":"Reichsstr. 10",
    "sg:city":"Saarbr\u00fccken",
    "sg:phone":"+49 681/374588",
    "sg:postcode":"66111",
    "sg:province":"Saarland",
    "wof:name":"China-restaurant Kwan Yee",
    "wof:placetype":"venue"
},
  "geometry": {"coordinates":[6.9908862114,49.2392196655],"type":"Point"}
}