{
  "type": "Feature",
  "properties": {
    "iso:country":"DE",
    "sg:address":"Sch\u00e4fergasse 52",
    "sg:city":"Frankfurt",
    "sg:phone":"+49 69/1310601",
    "sg:postcode":"60313",
    "sg:province":"Hessen",
    "wof:name":"Pizzeria Nr. 1",
    "wof:placetype":"venue"
},
  "geometry": {"coordinates":[8.6858129501,50.1167030334],"type":"Point"}
}