{
  "type": "Feature",
  "properties": {
    "iso:country":"DE",
    "sg:address":"Hauptstr. 7",
    "sg:city":"Niederschlettenbach",
    "sg:phone":"+49 6394/265",
    "sg:postcode":"76891",
    "sg:province":"Rheinland-Pfalz",
    "wof:name":"J\u00e4gerhof",
    "wof:placetype":"venue"
},
  "geometry": {"coordinates":[7.843474865,49.0856437683],"type":"Point"}
}