{
  "type": "Feature",
  "properties": {
    "iso:country":"DE",
    "sg:address":"Pferdemarkt 6",
    "sg:city":"Hameln",
    "sg:phone":"+49 5151/44637",
    "sg:postcode":"31785",
    "sg:province":"Niedersachsen",
    "wof:name":"Spielothek Gauselmann Gmbh & Co. Kg",
    "wof:placetype":"venue"
},
  "geometry": {"coordinates":[9.356885,52.105255],"type":"Point"}
}