{
  "type": "Feature",
  "properties": {
    "iso:country":"DE",
    "sg:address":"Beiertheimer Allee 11",
    "sg:city":"Karlsruhe",
    "sg:phone":"+49 721/937890",
    "sg:postcode":"76137",
    "sg:province":"Baden-W\u00fcrttemberg",
    "wof:name":"St\u00fctzle & Partner Spezialagentur F\u00fcr",
    "wof:placetype":"venue"
},
  "geometry": {"coordinates":[8.3993940353,49.0022583008],"type":"Point"}
}