{
  "type": "Feature",
  "properties": {
    "iso:country":"DE",
    "sg:address":"Von-Siemens-Str. 18A",
    "sg:city":"Telgte",
    "sg:phone":"+49 2504/93100",
    "sg:postcode":"48291",
    "sg:province":"Nordrhein-Westfalen",
    "wof:name":"Freitag Ingenieure Gmbh",
    "wof:placetype":"venue"
},
  "geometry": {"coordinates":[7.778647,51.97876],"type":"Point"}
}