{
  "type": "Feature",
  "properties": {
    "iso:country":"DE",
    "sg:address":"Wittenberger Str. 63",
    "sg:city":"Perleberg",
    "sg:phone":"+49 3876/612420",
    "sg:postcode":"19348",
    "sg:province":"Brandenburg",
    "wof:name":"W.-d. Necker",
    "wof:placetype":"venue"
},
  "geometry": {"coordinates":[11.856052,53.073303],"type":"Point"}
}