{
  "type": "Feature",
  "properties": {
    "iso:country":"DE",
    "sg:address":"Herstallstr. 27",
    "sg:city":"Aschaffenburg",
    "sg:phone":"+49 6021/299444",
    "sg:postcode":"63739",
    "sg:province":"Bayern",
    "wof:name":"Mannesmann Mobilfunk Gmbh",
    "wof:placetype":"venue"
},
  "geometry": {"coordinates":[9.1471309662,49.9758415222],"type":"Point"}
}