{
  "type": "Feature",
  "properties": {
    "iso:country":"DE",
    "sg:address":"Waidmannsluster Damm 173",
    "sg:city":"Berlin",
    "sg:phone":"+49 30/41472910",
    "sg:postcode":"13469",
    "sg:province":"Berlin",
    "wof:name":"Kurt Krzizanowski",
    "wof:placetype":"venue"
},
  "geometry": {"coordinates":[13.3187360764,52.6068611145],"type":"Point"}
}