{
  "type": "Feature",
  "properties": {
    "iso:country":"DE",
    "sg:address":"Hafenstr. 11",
    "sg:city":"Fl\u00f6rsheim",
    "sg:phone":"+49 6145/92610",
    "sg:postcode":"65439",
    "sg:province":"Hessen",
    "wof:name":"Jbs Vertretungen Der Elektroindustrie Gmbh",
    "wof:placetype":"venue"
},
  "geometry": {"coordinates":[8.415266,50.002457],"type":"Point"}
}