{
  "type": "Feature",
  "properties": {
    "iso:country":"DE",
    "sg:address":"Eibenstr. 6",
    "sg:city":"Schwanstetten",
    "sg:phone":"+49 9170/8660",
    "sg:postcode":"90596",
    "sg:province":"Bayern",
    "wof:name":"Reinhold Bim\u00fcller",
    "wof:placetype":"venue"
},
  "geometry": {"coordinates":[11.124453,49.317905],"type":"Point"}
}