{
  "type": "Feature",
  "properties": {
    "iso:country":"DE",
    "sg:address":"Hermannsplatz 4",
    "sg:city":"Soltendieck",
    "sg:phone":"+49 5874/477",
    "sg:postcode":"29594",
    "sg:province":"Niedersachsen",
    "wof:name":"Sis-web Internet-service",
    "wof:placetype":"venue"
},
  "geometry": {"coordinates":[10.745306015,52.8632087708],"type":"Point"}
}