{
  "type": "Feature",
  "properties": {
    "iso:country":"DE",
    "sg:address":"Meinigstr. 27c",
    "sg:city":"Bad Harzburg",
    "sg:phone":"+49 5322/81661",
    "sg:postcode":"38667",
    "sg:province":"Niedersachsen",
    "wof:name":"Krankenhauskantine Inh. Sabine Nette",
    "wof:placetype":"venue"
},
  "geometry": {"coordinates":[10.5208463669,51.9076652527],"type":"Point"}
}