{
  "type": "Feature",
  "properties": {
    "iso:country":"DE",
    "sg:address":"Marienstr. 2",
    "sg:city":"Poppenhausen",
    "sg:phone":"+49 6658/273",
    "sg:postcode":"36163",
    "sg:province":"Hessen",
    "wof:name":"St.-georg-apotheke",
    "wof:placetype":"venue"
},
  "geometry": {"coordinates":[9.869785,50.487755],"type":"Point"}
}