{
  "type": "Feature",
  "properties": {
    "iso:country":"DE",
    "sg:address":"Hessenring 82",
    "sg:city":"Bad Homburg",
    "sg:phone":"+49 6172/121435",
    "sg:postcode":"61348",
    "sg:province":"Hessen",
    "wof:name":"Hess Verwaltungs Gmbh",
    "wof:placetype":"venue"
},
  "geometry": {"coordinates":[8.617935,50.222954],"type":"Point"}
}