{
  "type": "Feature",
  "properties": {
    "iso:country":"DE",
    "sg:address":"Marsstrasse 78",
    "sg:city":"Xanten",
    "sg:phone":"+49 2801/1957",
    "sg:postcode":"46509",
    "sg:province":"Nordrhein-Westfalen",
    "wof:name":"Hotel Galerie An De Marspoort",
    "wof:placetype":"venue"
},
  "geometry": {"coordinates":[6.4576048851,51.6592178345],"type":"Point"}
}