{
  "type": "Feature",
  "properties": {
    "iso:country":"DE",
    "sg:address":"Cicerostr. 38",
    "sg:city":"Berlin",
    "sg:phone":"+49 30/890660",
    "sg:postcode":"10709",
    "sg:province":"Berlin",
    "wof:name":"Gullivers-reisen Gmbh",
    "wof:placetype":"venue"
},
  "geometry": {"coordinates":[13.3014240265,52.491985321],"type":"Point"}
}