{
  "type": "Feature",
  "properties": {
    "iso:country":"DE",
    "sg:address":"Scheda 3",
    "sg:city":"Wickede",
    "sg:phone":"+49 2377/2371",
    "sg:postcode":"58739",
    "sg:province":"Nordrhein-Westfalen",
    "wof:name":"Hubert Baum\u00fcller",
    "wof:placetype":"venue"
},
  "geometry": {"coordinates":[7.8387870789,51.4984893799],"type":"Point"}
}