{
  "type": "Feature",
  "properties": {
    "iso:country":"DE",
    "sg:address":"Hauptstr. 54",
    "sg:city":"Hohenroda",
    "sg:phone":"+49 6629/240",
    "sg:postcode":"36284",
    "sg:province":"Hessen",
    "wof:name":"Heinrich Vollmer Elektroinstallation",
    "wof:placetype":"venue"
},
  "geometry": {"coordinates":[9.915395,50.826504],"type":"Point"}
}