{
  "type": "Feature",
  "properties": {
    "iso:country":"DE",
    "sg:city":"Bad Reichenhall",
    "sg:phone":"+49 8651/67153",
    "sg:postcode":"83435",
    "sg:province":"Bayern",
    "wof:name":"Cafe Stadt Wien Inh. Eva Fritz",
    "wof:placetype":"venue"
},
  "geometry": {"coordinates":[12.873952,47.72002],"type":"Point"}
}