{
  "type": "Feature",
  "properties": {
    "iso:country":"DE",
    "sg:address":"Steinbacher Str. 21",
    "sg:city":"F\u00fcrth im Odenwald",
    "sg:phone":"+49 6253/932410",
    "sg:postcode":"64658",
    "sg:province":"Hessen",
    "wof:name":"Dr. Hansj\u00fcrgen Meyer",
    "wof:placetype":"venue"
},
  "geometry": {"coordinates":[8.786403656,49.6476821899],"type":"Point"}
}