{
  "type": "Feature",
  "properties": {
    "iso:country":"DE",
    "sg:address":"Hauptstr. 68",
    "sg:city":"Elmenhorst/Lichtenhagen",
    "sg:postcode":"18107",
    "sg:province":"Mecklenburg-Vorpommern",
    "wof:name":"Strandwind Gmbh",
    "wof:placetype":"venue"
},
  "geometry": {"coordinates":[11.9931516647,54.1595153809],"type":"Point"}
}