{
  "type": "Feature",
  "properties": {
    "iso:country":"DE",
    "sg:address":"Konterschaft 3",
    "sg:city":"Wilstedt",
    "sg:phone":"+49 4283/5948",
    "sg:postcode":"27412",
    "sg:province":"Niedersachsen",
    "wof:name":"Wilstedter Werkzeugkiste Gmbh",
    "wof:placetype":"venue"
},
  "geometry": {"coordinates":[9.091316,53.194546],"type":"Point"}
}