{
  "type": "Feature",
  "properties": {
    "iso:country":"DE",
    "sg:address":"Juelicher Landstr. 152",
    "sg:city":"Neuss",
    "sg:phone":"+49 2131/7744",
    "sg:postcode":"41464",
    "sg:province":"Nordrhein-Westfalen",
    "wof:name":"Auto Geissel Neuss - Eg-fahrzeuge Reimporte",
    "wof:placetype":"venue"
},
  "geometry": {"coordinates":[6.6805911064,51.1856880188],"type":"Point"}
}