{
  "type": "Feature",
  "properties": {
    "iso:country":"DE",
    "sg:address":"Gr\u00f6perstr. 88",
    "sg:city":"Halberstadt",
    "sg:phone":"+49 3941/586600",
    "sg:postcode":"38820",
    "sg:province":"Sachsen-Anhalt",
    "wof:name":"Freizeit- Und Tourismuscenter Zuckerfabrik Halberstadt",
    "wof:placetype":"venue"
},
  "geometry": {"coordinates":[11.0465497971,51.9030227661],"type":"Point"}
}