{
  "type": "Feature",
  "properties": {
    "iso:country":"DE",
    "sg:address":"Katenkampstr. 15",
    "sg:city":"Delmenhorst",
    "sg:phone":"+49 4221/73494",
    "sg:postcode":"27749",
    "sg:province":"Niedersachsen",
    "wof:name":"Wilfried Meyer Architekt",
    "wof:placetype":"venue"
},
  "geometry": {"coordinates":[8.649346,53.04604],"type":"Point"}
}