{
  "type": "Feature",
  "properties": {
    "iso:country":"DE",
    "sg:address":"Am Hegefeld 3 h",
    "sg:city":"Kl\u00f6tze",
    "sg:phone":"+49 3909/2050",
    "sg:postcode":"38486",
    "sg:province":"Sachsen-Anhalt",
    "wof:name":"Linden-apotheke Inh. Brigitte Liwonwski",
    "wof:placetype":"venue"
},
  "geometry": {"coordinates":[11.160882,52.62653],"type":"Point"}
}