{
  "type": "Feature",
  "properties": {
    "iso:country":"DE",
    "sg:address":"In der Au 4",
    "sg:city":"Frankfurt",
    "sg:phone":"+49 69/78910160",
    "sg:postcode":"60489",
    "sg:province":"Hessen",
    "wof:name":"Amplan - Ingenieur Gmbh",
    "wof:placetype":"venue"
},
  "geometry": {"coordinates":[8.599156,50.122059],"type":"Point"}
}