{
  "type": "Feature",
  "properties": {
    "iso:country":"DE",
    "sg:address":"Hufstr. 100",
    "sg:city":"Voerde",
    "sg:phone":"+49 281/468152",
    "sg:postcode":"46562",
    "sg:province":"Nordrhein-Westfalen",
    "wof:name":"Werner Becks Architekt",
    "wof:placetype":"venue"
},
  "geometry": {"coordinates":[6.627587,51.616718],"type":"Point"}
}