{
  "type": "Feature",
  "properties": {
    "iso:country":"DE",
    "sg:address":"obere m\u00fchlbachstr. 6/1",
    "sg:city":"Friedrichshafen",
    "sg:phone":"+49 7541",
    "sg:postcode":"88045",
    "sg:province":"Baden-W\u00fcrttemberg",
    "wof:name":"Cmmd",
    "wof:placetype":"venue"
},
  "geometry": {"coordinates":[9.440015,47.675987],"type":"Point"}
}