{
  "type": "Feature",
  "properties": {
    "iso:country":"DE",
    "sg:address":"Estermannstr. 114",
    "sg:city":"Bonn",
    "sg:phone":"+49 228/675401",
    "sg:postcode":"53117",
    "sg:province":"Nordrhein-Westfalen",
    "wof:name":"C. Bedorf",
    "wof:placetype":"venue"
},
  "geometry": {"coordinates":[7.0824408531,50.7609558105],"type":"Point"}
}