{
  "type": "Feature",
  "properties": {
    "iso:country":"DE",
    "sg:address":"Hansenweg 77",
    "sg:city":"Frankfurt",
    "sg:phone":"+49 69/651840",
    "sg:postcode":"60599",
    "sg:province":"Hessen",
    "wof:name":"Helmut Lindt Malerbetrieb Gmbh",
    "wof:placetype":"venue"
},
  "geometry": {"coordinates":[8.719351,50.095135],"type":"Point"}
}