{
  "type": "Feature",
  "properties": {
    "iso:country":"DE",
    "sg:address":"Platanenallee 19",
    "sg:city":"Aschaffenburg",
    "sg:phone":"+49 6021/24282",
    "sg:postcode":"63739",
    "sg:province":"Bayern",
    "wof:name":"Platanen-apotheke",
    "wof:placetype":"venue"
},
  "geometry": {"coordinates":[9.154458,49.976746],"type":"Point"}
}