{
  "type": "Feature",
  "properties": {
    "iso:country":"DE",
    "sg:address":"Landstr. 44-48",
    "sg:city":"Haan",
    "sg:phone":"+49 4921/295600",
    "sg:postcode":"42781",
    "sg:province":"Nordrhein-Westfalen",
    "wof:name":"Timken Germany Gmbh",
    "wof:placetype":"venue"
},
  "geometry": {"coordinates":[7.03627491,51.2028808594],"type":"Point"}
}