{
  "type": "Feature",
  "properties": {
    "iso:country":"DE",
    "sg:address":"Akazienallee 80-82",
    "sg:city":"M\u00fclheim/Ruhr",
    "sg:phone":"+49 208/570014",
    "sg:postcode":"45478",
    "sg:province":"Nordrhein-Westfalen",
    "wof:name":"M\u00fclheimer Rennverein Raffelberg E.v.",
    "wof:placetype":"venue"
},
  "geometry": {"coordinates":[6.8243560791,51.4368591309],"type":"Point"}
}