{
  "type": "Feature",
  "properties": {
    "iso:country":"DE",
    "sg:address":"Osterholzstr. 22",
    "sg:city":"Heidenheim",
    "sg:phone":"+49 7751/910552",
    "sg:postcode":"89522",
    "sg:province":"Baden-W\u00fcrttemberg",
    "wof:name":"Thomas Wasmer",
    "wof:placetype":"venue"
},
  "geometry": {"coordinates":[10.1796274185,48.6767196655],"type":"Point"}
}