{
  "type": "Feature",
  "properties": {
    "iso:country":"DE",
    "sg:address":"Hinterer Giersb\u00fchlweg 16",
    "sg:city":"Schluchsee",
    "sg:phone":"+49 7656/1445",
    "sg:postcode":"79859",
    "sg:province":"Baden-W\u00fcrttemberg",
    "wof:name":"G\u00e4stehaus Stier",
    "wof:placetype":"venue"
},
  "geometry": {"coordinates":[8.1871137619,47.8212966919],"type":"Point"}
}