{
  "type": "Feature",
  "properties": {
    "iso:country":"DE",
    "sg:address":"Grimmelshausenstr. 14-16",
    "sg:city":"Bad Soden-Salm\u00fcnster",
    "sg:phone":"+49 6056/91810",
    "sg:postcode":"63628",
    "sg:province":"Hessen",
    "wof:name":"T & R Gesellschaft F\u00fcr Dv Organisation Und",
    "wof:placetype":"venue"
},
  "geometry": {"coordinates":[9.3653020859,50.2652168274],"type":"Point"}
}