{
  "type": "Feature",
  "properties": {
    "iso:country":"DE",
    "sg:address":"Zedernweg 5",
    "sg:city":"Wesel",
    "sg:phone":"+49 281/962770",
    "sg:postcode":"46487",
    "sg:province":"Nordrhein-Westfalen",
    "wof:name":"Harry Taufenbach Steuerberater",
    "wof:placetype":"venue"
},
  "geometry": {"coordinates":[6.6077609062,51.6936149597],"type":"Point"}
}