{
  "type": "Feature",
  "properties": {
    "iso:country":"DE",
    "sg:address":"Senator-Richard-Becker-Str. 30",
    "sg:city":"Saarbr\u00fccken",
    "sg:phone":"+49 681/64579",
    "sg:postcode":"66123",
    "sg:province":"Saarland",
    "wof:name":"A. Peters",
    "wof:placetype":"venue"
},
  "geometry": {"coordinates":[7.0146379471,49.2348327637],"type":"Point"}
}