{
  "type": "Feature",
  "properties": {
    "iso:country":"DE",
    "sg:address":"Marktplatz 1",
    "sg:city":"Harburg",
    "sg:phone":"+49 9080/9990",
    "sg:postcode":"86655",
    "sg:province":"Bayern",
    "wof:name":"Hpc Harress Pickel Consult Gmbh",
    "wof:placetype":"venue"
},
  "geometry": {"coordinates":[10.6886348724,48.7873725891],"type":"Point"}
}