{
  "type": "Feature",
  "properties": {
    "iso:country":"DE",
    "sg:address":"Moorgasse 30",
    "sg:city":"Langg\u00f6ns",
    "sg:phone":"+49 6403/71406",
    "sg:postcode":"35428",
    "sg:province":"Hessen",
    "wof:name":"R\u00fchl",
    "wof:placetype":"venue"
},
  "geometry": {"coordinates":[8.6638441086,50.4979286194],"type":"Point"}
}