{
  "type": "Feature",
  "properties": {
    "iso:country":"DE",
    "sg:address":"Lenstruper Weg 5",
    "sg:city":"Detmold",
    "sg:phone":"+49 5231/570113",
    "sg:postcode":"32760",
    "sg:province":"Nordrhein-Westfalen",
    "wof:name":"Thomas Trappmann Kommunikationsagentur",
    "wof:placetype":"venue"
},
  "geometry": {"coordinates":[8.93669,51.909039],"type":"Point"}
}