{
  "type": "Feature",
  "properties": {
    "iso:country":"DE",
    "sg:address":"Georg-F\u00fc\u00dfl-Str. 10 a",
    "sg:city":"Bodenw\u00f6hr",
    "sg:phone":"+49 9434/90090",
    "sg:postcode":"92439",
    "sg:province":"Bayern",
    "wof:name":"Mdg Marks Dienstleistungs Gmbh",
    "wof:placetype":"venue"
},
  "geometry": {"coordinates":[12.298617363,49.2710113525],"type":"Point"}
}