{
  "type": "Feature",
  "properties": {
    "iso:country":"DE",
    "sg:address":"Mindermannweg 63",
    "sg:city":"Hamburg",
    "sg:phone":"+49 40/801684",
    "sg:postcode":"22609",
    "sg:province":"Hamburg",
    "wof:name":"Erwin M. Hinz Rechtsanwalt",
    "wof:placetype":"venue"
},
  "geometry": {"coordinates":[9.8497171402,53.567905426],"type":"Point"}
}