{
  "type": "Feature",
  "properties": {
    "iso:country":"DE",
    "sg:address":"Emmeransstr. 38",
    "sg:city":"Mainz",
    "sg:phone":"+49 6131/221823",
    "sg:postcode":"55116",
    "sg:province":"Rheinland-Pfalz",
    "wof:name":"Restaurant Algarve",
    "wof:placetype":"venue"
},
  "geometry": {"coordinates":[8.2701015472,50.0027961731],"type":"Point"}
}