{
  "type": "Feature",
  "properties": {
    "iso:country":"DE",
    "sg:address":"Sundh\u00e4user Str. 15",
    "sg:city":"Nordhausen",
    "sg:phone":"+49 3631/48165",
    "sg:postcode":"99734",
    "sg:province":"Th\u00fcringen",
    "wof:name":"Strauch F. M. Lebens-, Unfall- U., Sachversicherungen",
    "wof:placetype":"venue"
},
  "geometry": {"coordinates":[10.79582,51.494499],"type":"Point"}
}