{
  "type": "Feature",
  "properties": {
    "iso:country":"DE",
    "sg:address":"Weseler Str. 352",
    "sg:city":"Rees",
    "sg:phone":"+49 2857/2247",
    "sg:postcode":"46459",
    "sg:province":"Nordrhein-Westfalen",
    "wof:name":"Strandhaus",
    "wof:placetype":"venue"
},
  "geometry": {"coordinates":[6.483866,51.755039],"type":"Point"}
}