{
  "type": "Feature",
  "properties": {
    "iso:country":"DE",
    "sg:address":"Rathausstr. 60",
    "sg:city":"Elz",
    "sg:phone":"+49 6431/95090",
    "sg:postcode":"65604",
    "sg:province":"Hessen",
    "wof:name":"Peter Schneider",
    "wof:placetype":"venue"
},
  "geometry": {"coordinates":[8.0360202789,50.4136161804],"type":"Point"}
}