{
  "type": "Feature",
  "properties": {
    "iso:country":"DE",
    "sg:address":"An der Oberpforte 28",
    "sg:city":"Mainz",
    "sg:phone":"+49 6131/71391",
    "sg:postcode":"55128",
    "sg:province":"Rheinland-Pfalz",
    "wof:name":"Johann Schrohe & S\u00f6hne Inh. Willi Hans Schrohe E. K.",
    "wof:placetype":"venue"
},
  "geometry": {"coordinates":[8.2395095825,49.9787254333],"type":"Point"}
}