{
  "type": "Feature",
  "properties": {
    "iso:country":"DE",
    "sg:address":"Kolde-Ring 21",
    "sg:city":"M\u00fcnster",
    "sg:phone":"+49 251/7020",
    "sg:postcode":"48126",
    "sg:province":"Bayern",
    "wof:name":"Lvm-versicherungen",
    "wof:placetype":"venue"
},
  "geometry": {"coordinates":[7.6154961586,51.9496879578],"type":"Point"}
}