{
  "type": "Feature",
  "properties": {
    "iso:country":"DE",
    "sg:address":"Guldenbachstr. 1",
    "sg:city":"K\u00f6ln",
    "sg:phone":"+49 221/460140",
    "sg:postcode":"50935",
    "sg:province":"Nordrhein-Westfalen",
    "wof:name":"Redaktion Halbj\u00e4hrliches Verzeichnis Taschenb\u00fccher",
    "wof:placetype":"venue"
},
  "geometry": {"coordinates":[6.9076571465,50.9136047363],"type":"Point"}
}