{
  "type": "Feature",
  "properties": {
    "iso:country":"DE",
    "sg:address":"Bahnhofstr. 18",
    "sg:city":"S\u00fcderdeich",
    "sg:phone":"+49 4833/600",
    "sg:postcode":"25764",
    "sg:province":"Schleswig-Holstein",
    "wof:name":"Kruse Windkraft Gmbh & Co. Kg S\u00fcderdeich",
    "wof:placetype":"venue"
},
  "geometry": {"coordinates":[8.910788,54.198864],"type":"Point"}
}