{
  "type": "Feature",
  "properties": {
    "iso:country":"DE",
    "sg:address":"Kirchstr. 8",
    "sg:city":"Vallendar",
    "sg:phone":"+49 261/65905",
    "sg:postcode":"56179",
    "sg:province":"Rheinland-Pfalz",
    "wof:name":"Sinus-bike Gutsch & Partner",
    "wof:placetype":"venue"
},
  "geometry": {"coordinates":[7.615341,50.40181],"type":"Point"}
}