{
  "type": "Feature",
  "properties": {
    "iso:country":"DE",
    "sg:address":"Erlenweg 15a",
    "sg:city":"Emsdetten",
    "sg:phone":"+49 2572/81837",
    "sg:postcode":"48282",
    "sg:province":"Nordrhein-Westfalen",
    "wof:name":"Ludger Riddering",
    "wof:placetype":"venue"
},
  "geometry": {"coordinates":[7.5519227982,52.1586837769],"type":"Point"}
}