{
  "type": "Feature",
  "properties": {
    "iso:country":"DE",
    "sg:address":"Vo\u00dfhagen 31",
    "sg:city":"Wedel",
    "sg:phone":"+49 4103/83671",
    "sg:postcode":"22880",
    "sg:province":"Schleswig-Holstein",
    "wof:name":"Inge Dziubek Heissmangel",
    "wof:placetype":"venue"
},
  "geometry": {"coordinates":[9.7223949432,53.5791435242],"type":"Point"}
}