{
  "type": "Feature",
  "properties": {
    "iso:country":"DE",
    "sg:address":"Hauptstr. 44",
    "sg:city":"Kronburg",
    "sg:phone":"+49 8394/9260010",
    "sg:postcode":"87758",
    "sg:province":"Bayern",
    "wof:name":"Fischer Haustechnik Gmbh",
    "wof:placetype":"venue"
},
  "geometry": {"coordinates":[10.151174,47.907001],"type":"Point"}
}