{
  "type": "Feature",
  "properties": {
    "iso:country":"DE",
    "sg:address":"Haus an der Eisernen Br\u00fccke",
    "sg:city":"Regensburg",
    "sg:phone":"+49 941/5684163",
    "sg:postcode":"93059",
    "sg:province":"Bayern",
    "wof:name":"Walhalla Fachverlag",
    "wof:placetype":"venue"
},
  "geometry": {"coordinates":[12.102814,49.030167],"type":"Point"}
}