{
  "type": "Feature",
  "properties": {
    "iso:country":"DE",
    "sg:address":"Martin-Luther-Platz 11",
    "sg:city":"Selb",
    "sg:phone":"+49 9287/2575",
    "sg:postcode":"95100",
    "sg:province":"Bayern",
    "wof:name":"Eberhard Irrgang Rechtsanwalt",
    "wof:placetype":"venue"
},
  "geometry": {"coordinates":[12.1313962936,50.1694793701],"type":"Point"}
}