{
  "type": "Feature",
  "properties": {
    "iso:country":"DE",
    "sg:address":"Michaelisweg 5",
    "sg:city":"Burg",
    "sg:phone":"+49 4825/2123",
    "sg:postcode":"25712",
    "sg:province":"Schleswig-Holstein",
    "wof:name":"Alten- U. Pflegeheim Christiansen",
    "wof:placetype":"venue"
},
  "geometry": {"coordinates":[9.254765,53.999012],"type":"Point"}
}