{
  "type": "Feature",
  "properties": {
    "iso:country":"DE",
    "sg:address":"Lautertalstr. 69",
    "sg:city":"Gomadingen",
    "sg:phone":"+49 7385/685",
    "sg:postcode":"72532",
    "sg:province":"Baden-W\u00fcrttemberg",
    "wof:name":"G. Knoll Kranverleih",
    "wof:placetype":"venue"
},
  "geometry": {"coordinates":[9.4227905273,48.3717727661],"type":"Point"}
}