{
  "type": "Feature",
  "properties": {
    "iso:country":"DE",
    "sg:address":"Max-Pommer-Str. 02",
    "sg:city":"Leipzig",
    "sg:postcode":"04317",
    "sg:province":"Sachsen",
    "wof:name":"Dieter Marczynski",
    "wof:placetype":"venue"
},
  "geometry": {"coordinates":[12.411231,51.327503],"type":"Point"}
}