{
  "type": "Feature",
  "properties": {
    "iso:country":"DE",
    "sg:address":"Mathildenstr. 12/7",
    "sg:city":"L\u00fcdenscheid",
    "sg:phone":"+49 2351/23766",
    "sg:postcode":"58507",
    "sg:province":"Nordrhein-Westfalen",
    "wof:name":"California-fitness-center Inh. Heinz Isken",
    "wof:placetype":"venue"
},
  "geometry": {"coordinates":[7.6246490479,51.2218093872],"type":"Point"}
}