{
  "type": "Feature",
  "properties": {
    "iso:country":"DE",
    "sg:address":"Kaiserstr. 31",
    "sg:city":"Wadgassen",
    "sg:phone":"+49 6834/490940",
    "sg:postcode":"66787",
    "sg:province":"Saarland",
    "wof:name":"Hib Dipl.-ing. Hettinger Ingenieurb\u00fcro F\u00fcr",
    "wof:placetype":"venue"
},
  "geometry": {"coordinates":[6.824084,49.263649],"type":"Point"}
}