{
  "type": "Feature",
  "properties": {
    "iso:country":"DE",
    "sg:address":"Karl-Marx-Str. 18",
    "sg:city":"Braunschweig",
    "sg:phone":"+49 531/2702869",
    "sg:postcode":"38104",
    "sg:province":"Niedersachsen",
    "wof:name":"Bauunternehmen Profi Bau Gmbh",
    "wof:placetype":"venue"
},
  "geometry": {"coordinates":[10.54703,52.26685],"type":"Point"}
}