{
  "type": "Feature",
  "properties": {
    "iso:country":"DE",
    "sg:address":"Bahnhofstr. 28",
    "sg:city":"Betzdorf",
    "sg:phone":"+49 2741/4549",
    "sg:postcode":"57518",
    "sg:province":"Rheinland-Pfalz",
    "wof:name":"City-cafe",
    "wof:placetype":"venue"
},
  "geometry": {"coordinates":[7.872318,50.788876],"type":"Point"}
}