{
  "type": "Feature",
  "properties": {
    "iso:country":"DE",
    "sg:address":"S\u00fcdrg. 1",
    "sg:city":"Lubmin",
    "sg:phone":"+49 4938/223202",
    "sg:postcode":"17509",
    "sg:province":"Mecklenburg-Vorpommern",
    "wof:name":"Kapiten Peter Maa\u00df Bootsfahrschule",
    "wof:placetype":"venue"
},
  "geometry": {"coordinates":[12.54469,54.343266],"type":"Point"}
}