{
  "type": "Feature",
  "properties": {
    "iso:country":"DE",
    "sg:address":"Ohrdorf 69",
    "sg:city":"Wittingen",
    "sg:phone":"+49 5839/204",
    "sg:postcode":"29378",
    "sg:province":"Niedersachsen",
    "wof:name":"Karl-heinz Scholz",
    "wof:placetype":"venue"
},
  "geometry": {"coordinates":[10.7358474731,52.7284545898],"type":"Point"}
}