{
  "type": "Feature",
  "properties": {
    "iso:country":"DE",
    "sg:address":"Posthof 1",
    "sg:city":"Badenhausen",
    "sg:phone":"+49 5522/6382",
    "sg:postcode":"37534",
    "sg:province":"Niedersachsen",
    "wof:name":"Maschinenbau Geisler Gmbh",
    "wof:placetype":"venue"
},
  "geometry": {"coordinates":[10.1948347092,51.7683906555],"type":"Point"}
}