{
  "type": "Feature",
  "properties": {
    "iso:country":"DE",
    "sg:address":"Albstr. 38",
    "sg:city":"Reutlingen",
    "sg:postcode":"72764",
    "sg:province":"Baden-W\u00fcrttemberg",
    "wof:name":"Engel Gmbh - W\u00e4sche Und Bekleidung Aus Naturfasern",
    "wof:placetype":"venue"
},
  "geometry": {"coordinates":[9.2194747925,48.4880218506],"type":"Point"}
}