{
  "type": "Feature",
  "properties": {
    "iso:country":"DE",
    "sg:address":"Brahmsstr. 13",
    "sg:city":"Flensburg",
    "sg:phone":"+49 461/6705",
    "sg:postcode":"24943",
    "sg:province":"Schleswig-Holstein",
    "wof:name":"Ev. Pfarramt Engelsby",
    "wof:placetype":"venue"
},
  "geometry": {"coordinates":[9.4747638702,54.7938270569],"type":"Point"}
}