{
  "type": "Feature",
  "properties": {
    "iso:country":"DE",
    "sg:address":"Denkmalstr. 3",
    "sg:city":"Bayreuth",
    "sg:phone":"+49 921/99529",
    "sg:postcode":"95448",
    "sg:province":"Bayern",
    "wof:name":"Hans Lutz",
    "wof:placetype":"venue"
},
  "geometry": {"coordinates":[11.6236610413,49.9604873657],"type":"Point"}
}