{
  "type": "Feature",
  "properties": {
    "iso:country":"DE",
    "sg:address":"Kurf\u00fcrstendamm 153",
    "sg:city":"Berlin",
    "sg:postcode":"10709",
    "sg:province":"Berlin",
    "wof:name":"Schitthelm Beteiligungs Gmbh",
    "wof:placetype":"venue"
},
  "geometry": {"coordinates":[13.302149,52.498863],"type":"Point"}
}