{
  "type": "Feature",
  "properties": {
    "iso:country":"DE",
    "sg:address":"Sandstr. 3",
    "sg:city":"Haren",
    "sg:postcode":"49733",
    "sg:province":"Niedersachsen",
    "wof:name":"E. S. Entsorgungsservice Emsland Gmbh",
    "wof:placetype":"venue"
},
  "geometry": {"coordinates":[7.2042961121,52.760723114],"type":"Point"}
}