{
  "type": "Feature",
  "properties": {
    "iso:country":"DE",
    "sg:address":"Geschwister-Scholl-Str. 51",
    "sg:city":"Herschdorf",
    "sg:phone":"+49 36738/42765",
    "sg:postcode":"98701",
    "sg:province":"Th\u00fcringen",
    "wof:name":"Annerose Kemter",
    "wof:placetype":"venue"
},
  "geometry": {"coordinates":[11.0454788208,50.6271705627],"type":"Point"}
}