{
  "type": "Feature",
  "properties": {
    "iso:country":"DE",
    "sg:address":"Overbergstr. 8",
    "sg:city":"Twist",
    "sg:phone":"+49 5936/3010",
    "sg:postcode":"49767",
    "sg:province":"Niedersachsen",
    "wof:name":"Aktionsladen Albers Gmbh",
    "wof:placetype":"venue"
},
  "geometry": {"coordinates":[7.096855,52.647739],"type":"Point"}
}