{
  "type": "Feature",
  "properties": {
    "iso:country":"DE",
    "sg:address":"M\u00fchl\u00e4ckerstr. 11",
    "sg:city":"Ludwigsburg",
    "sg:phone":"+49 7144/7004",
    "sg:postcode":"71642",
    "sg:province":"Baden-W\u00fcrttemberg",
    "wof:name":"Datenverarbeitung- Ewl",
    "wof:placetype":"venue"
},
  "geometry": {"coordinates":[9.260202,48.902977],"type":"Point"}
}