{
  "type": "Feature",
  "properties": {
    "iso:country":"DE",
    "sg:address":"Hauptstr. 10",
    "sg:city":"Alfhausen",
    "sg:phone":"+49 5464/1239",
    "sg:postcode":"49594",
    "sg:province":"Niedersachsen",
    "wof:name":"Karl Bollmann",
    "wof:placetype":"venue"
},
  "geometry": {"coordinates":[7.9519238472,52.5005607605],"type":"Point"}
}