{
  "type": "Feature",
  "properties": {
    "iso:country":"DE",
    "sg:address":"B\u00fcrgerm.-Schmelzing-Str. 85",
    "sg:city":"Kamp-Lintfort",
    "sg:phone":"+49 2842/8483",
    "sg:postcode":"47475",
    "sg:province":"Nordrhein-Westfalen",
    "wof:name":"B\u00fcrgereck",
    "wof:placetype":"venue"
},
  "geometry": {"coordinates":[6.5475502014,51.5047149658],"type":"Point"}
}