{
  "type": "Feature",
  "properties": {
    "iso:country":"DE",
    "sg:address":"Am Ende",
    "sg:city":"Langeneichst\u00e4dt",
    "sg:postcode":"06268",
    "sg:province":"Sachsen-Anhalt",
    "wof:name":"Aldi Gmbh & Co. Kg",
    "wof:placetype":"venue"
},
  "geometry": {"coordinates":[11.7521572113,51.3445091248],"type":"Point"}
}