{
  "type": "Feature",
  "properties": {
    "iso:country":"DE",
    "sg:address":"Uhlandstr. 1",
    "sg:city":"Heroldstatt",
    "sg:postcode":"72535",
    "sg:province":"Baden-W\u00fcrttemberg",
    "wof:name":"Kulturkonzept Verlags- Und Werbeb\u00fcro E. K.",
    "wof:placetype":"venue"
},
  "geometry": {"coordinates":[9.6533155441,48.4407310486],"type":"Point"}
}