{
  "type": "Feature",
  "properties": {
    "iso:country":"DE",
    "sg:address":"Thomas-M\u00fcntzer-Str. 28",
    "sg:city":"Pratau",
    "sg:postcode":"06888",
    "sg:province":"Sachsen-Anhalt",
    "wof:name":"E. R. Immobilien Gmbh",
    "wof:placetype":"venue"
},
  "geometry": {"coordinates":[-73.358521,41.141499],"type":"Point"}
}