{
  "type": "Feature",
  "properties": {
    "iso:country":"DE",
    "sg:address":"Grenzstr. 5",
    "sg:city":"Sellessen",
    "sg:phone":"+49 3563/602680",
    "sg:postcode":"03130",
    "sg:province":"Brandenburg",
    "wof:name":"M & W Bautr\u00e4gerges. Mbh",
    "wof:placetype":"venue"
},
  "geometry": {"coordinates":[14.404915,51.597012],"type":"Point"}
}