{
  "type": "Feature",
  "properties": {
    "iso:country":"DE",
    "sg:address":"Prinzenberg 2",
    "sg:city":"Sta\u00dffurt",
    "sg:phone":"+49 3925/967720",
    "sg:postcode":"39418",
    "sg:province":"Sachsen-Anhalt",
    "wof:name":"Redaktion Sta\u00dffurter Volksstimme",
    "wof:placetype":"venue"
},
  "geometry": {"coordinates":[11.5833978653,51.8554801941],"type":"Point"}
}