{
  "type": "Feature",
  "properties": {
    "iso:country":"DE",
    "sg:address":"Albrechtstr. 48",
    "sg:city":"Dessau",
    "sg:phone":"+49 340/260460",
    "sg:postcode":"06844",
    "sg:province":"Sachsen-Anhalt",
    "wof:name":"Meier-ratio Gmbh",
    "wof:placetype":"venue"
},
  "geometry": {"coordinates":[12.240796,51.850086],"type":"Point"}
}