{
  "type": "Feature",
  "properties": {
    "iso:country":"DE",
    "sg:address":"M\u00fchlgasse 2",
    "sg:city":"Sangerhausen",
    "sg:phone":"+49 3464/573721",
    "sg:postcode":"06526",
    "sg:province":"Sachsen-Anhalt",
    "wof:name":"Billardcafe",
    "wof:placetype":"venue"
},
  "geometry": {"coordinates":[11.293663,51.472267],"type":"Point"}
}