{
  "type": "Feature",
  "properties": {
    "iso:country":"DE",
    "sg:address":"Ahornweg 12a",
    "sg:city":"Brilon",
    "sg:phone":"+49 2964/752",
    "sg:postcode":"59929",
    "sg:province":"Nordrhein-Westfalen",
    "wof:name":"Hgs Haus Und Grundst\u00fcck Handels- Und Service Gmbh",
    "wof:placetype":"venue"
},
  "geometry": {"coordinates":[8.6158542633,51.4541473389],"type":"Point"}
}