{
  "type": "Feature",
  "properties": {
    "iso:country":"DE",
    "sg:address":"Dorfstr. 20",
    "sg:city":"Stockelsdorf",
    "sg:phone":"+49 451/495287",
    "sg:postcode":"23617",
    "sg:province":"Schleswig-Holstein",
    "wof:name":"Erich Becker",
    "wof:placetype":"venue"
},
  "geometry": {"coordinates":[10.6440353394,53.8991851807],"type":"Point"}
}