{
  "type": "Feature",
  "properties": {
    "iso:country":"DE",
    "sg:address":"Hauptstr. 48",
    "sg:city":"Quolsdorf",
    "sg:phone":"+49 35894/30200",
    "sg:postcode":"02923",
    "sg:province":"Sachsen",
    "wof:name":"Bauernstube",
    "wof:placetype":"venue"
},
  "geometry": {"coordinates":[14.852063179,51.3790168762],"type":"Point"}
}