{
  "type": "Feature",
  "properties": {
    "iso:country":"DE",
    "sg:address":"Lassallestr. 12",
    "sg:city":"Kassel",
    "sg:phone":"+49 561/777579",
    "sg:postcode":"34119",
    "sg:province":"Hessen",
    "wof:name":"H.-p. Br\u00e4utigam",
    "wof:placetype":"venue"
},
  "geometry": {"coordinates":[9.4662494659,51.3154411316],"type":"Point"}
}