{
  "type": "Feature",
  "properties": {
    "iso:country":"DE",
    "sg:address":"Sch\u00fctzenhofstr. 47",
    "sg:city":"Jever",
    "sg:postcode":"26441",
    "sg:province":"Niedersachsen",
    "wof:name":"Restaurant-hotel Sch\u00fctzenhof Jever E. K.",
    "wof:placetype":"venue"
},
  "geometry": {"coordinates":[7.8859148026,53.5638008118],"type":"Point"}
}