{
  "type": "Feature",
  "properties": {
    "iso:country":"DE",
    "sg:address":"Reepmoorsweg 7",
    "sg:city":"Wildeshausen",
    "sg:phone":"+49 4431/71439",
    "sg:postcode":"27793",
    "sg:province":"Niedersachsen",
    "wof:name":"Anke Westerkamp Krankengymnastin",
    "wof:placetype":"venue"
},
  "geometry": {"coordinates":[8.427084,52.894787],"type":"Point"}
}