{
  "type": "Feature",
  "properties": {
    "iso:country":"DE",
    "sg:address":"Venloer Str. 241-245",
    "sg:city":"K\u00f6ln",
    "sg:postcode":"50823",
    "sg:province":"Nordrhein-Westfalen",
    "wof:name":"Johann Maria Farina & Cie. Zur Stadt Rom",
    "wof:placetype":"venue"
},
  "geometry": {"coordinates":[6.9235072136,50.9468536377],"type":"Point"}
}