{
  "type": "Feature",
  "properties": {
    "iso:country":"DE",
    "sg:address":"Treustr. 19",
    "sg:city":"Augsburg",
    "sg:phone":"+49 821/2291050",
    "sg:postcode":"86157",
    "sg:province":"Bayern",
    "wof:name":"Manfred H\u00f6pflinger Ingenieur",
    "wof:placetype":"venue"
},
  "geometry": {"coordinates":[10.8643016815,48.3603439331],"type":"Point"}
}