{
  "type": "Feature",
  "properties": {
    "iso:country":"DE",
    "sg:address":"Karl-Friedrich-Str. 81",
    "sg:city":"Emmendingen",
    "sg:phone":"+49 7641/8328",
    "sg:postcode":"79312",
    "sg:province":"Baden-W\u00fcrttemberg",
    "wof:name":"Insel 81",
    "wof:placetype":"venue"
},
  "geometry": {"coordinates":[7.8386678696,48.1239624023],"type":"Point"}
}