{
  "type": "Feature",
  "properties": {
    "iso:country":"DE",
    "sg:address":"Beckumer Str. 36",
    "sg:city":"Ahlen",
    "sg:phone":"+49 2382/694500",
    "sg:postcode":"59229",
    "sg:province":"Nordrhein-Westfalen",
    "wof:name":"Infa Institut F\u00fcr Abfall- Und Abwasserwirtschaft Gmbh",
    "wof:placetype":"venue"
},
  "geometry": {"coordinates":[7.9030280113,51.7631111145],"type":"Point"}
}