{
  "type": "Feature",
  "properties": {
    "iso:country":"DE",
    "sg:address":"Bahnweg 12",
    "sg:city":"Kronach / Neuses",
    "sg:phone":"+49 9261/2474",
    "sg:postcode":"96317",
    "sg:province":"Bayern",
    "wof:name":"N\u00e4hmaschinen Fugmann",
    "wof:placetype":"venue"
},
  "geometry": {"coordinates":[11.3182630539,50.2167778015],"type":"Point"}
}