{
  "type": "Feature",
  "properties": {
    "iso:country":"DE",
    "sg:city":"Kiefersfelden",
    "sg:phone":"+49 8033/7066",
    "sg:postcode":"83088",
    "sg:province":"Bayern",
    "wof:name":"Volksbank Rosenheim Eg",
    "wof:placetype":"venue"
},
  "geometry": {"coordinates":[12.18826,47.615543],"type":"Point"}
}