{
  "type": "Feature",
  "properties": {
    "iso:country":"DE",
    "sg:address":"Pilgrimstr. 27",
    "sg:city":"Bochum",
    "sg:phone":"+49 234/75246",
    "sg:postcode":"44799",
    "sg:province":"Nordrhein-Westfalen",
    "wof:name":"Elke Nehlsen",
    "wof:placetype":"venue"
},
  "geometry": {"coordinates":[7.221571,51.456528],"type":"Point"}
}