{
  "type": "Feature",
  "properties": {
    "iso:country":"DE",
    "sg:address":"Bentelerstr. 4",
    "sg:city":"Paderborn",
    "sg:phone":"+49 5254/99480",
    "sg:postcode":"33104",
    "sg:province":"Nordrhein-Westfalen",
    "wof:name":"Famila",
    "wof:placetype":"venue"
},
  "geometry": {"coordinates":[8.726234436,51.7437133789],"type":"Point"}
}