{
  "type": "Feature",
  "properties": {
    "iso:country":"DE",
    "sg:address":"Ludwigsplatz 12-14",
    "sg:city":"N\u00fcrnberg",
    "sg:phone":"+49 911/13300",
    "sg:postcode":"90403",
    "sg:province":"Bayern",
    "wof:name":"Rudolf W\u00f6hrl Das Haus Der Markenkleidung",
    "wof:placetype":"venue"
},
  "geometry": {"coordinates":[11.0713,49.450905],"type":"Point"}
}