{
  "type": "Feature",
  "properties": {
    "iso:country":"DE",
    "sg:address":"Bahnhofstr. 14",
    "sg:city":"Mertingen",
    "sg:phone":"+49 9078/1417",
    "sg:postcode":"86690",
    "sg:province":"Bayern",
    "wof:name":"Josef Und Rudolf Scherle",
    "wof:placetype":"venue"
},
  "geometry": {"coordinates":[10.816856,48.657112],"type":"Point"}
}