{
  "type": "Feature",
  "properties": {
    "iso:country":"DE",
    "sg:address":"Danziger Str. 34",
    "sg:city":"Wiesbaden",
    "sg:phone":"+49 611/54531",
    "sg:postcode":"65191",
    "sg:province":"Hessen",
    "wof:name":"Dr. Med. C. J. Stoecker",
    "wof:placetype":"venue"
},
  "geometry": {"coordinates":[8.2643470764,50.0999298096],"type":"Point"}
}