{
  "type": "Feature",
  "properties": {
    "iso:country":"DE",
    "sg:address":"Windm\u00fchlenweg 4",
    "sg:city":"M\u00f6nchengladbach",
    "sg:phone":"+49 2161/51053",
    "sg:postcode":"41068",
    "sg:province":"Nordrhein-Westfalen",
    "wof:name":"Roermonderhof",
    "wof:placetype":"venue"
},
  "geometry": {"coordinates":[6.4009962082,51.1976852417],"type":"Point"}
}