{
  "type": "Feature",
  "properties": {
    "iso:country":"DE",
    "sg:address":"S\u00fc\u00dferoder Str. 34",
    "sg:city":"Hannover",
    "sg:phone":"+49 511/9526288",
    "sg:postcode":"30559",
    "sg:province":"Niedersachsen",
    "wof:name":"Rolf Grethe Steuerberater",
    "wof:placetype":"venue"
},
  "geometry": {"coordinates":[9.845998764,52.3580970764],"type":"Point"}
}