{
  "type": "Feature",
  "properties": {
    "iso:country":"DE",
    "sg:address":"Lerchenweg 4",
    "sg:city":"Insingen",
    "sg:phone":"+49 9869/1244",
    "sg:postcode":"91610",
    "sg:province":"Bayern",
    "wof:name":"Einrichtungshaus M. Jursa Gmbh",
    "wof:placetype":"venue"
},
  "geometry": {"coordinates":[10.1675691605,49.3062591553],"type":"Point"}
}