{
  "type": "Feature",
  "properties": {
    "iso:country":"DE",
    "sg:address":"Haller Str. 15",
    "sg:city":"Sulzbach",
    "sg:phone":"+49 4971/93279",
    "sg:postcode":"71560",
    "sg:province":"Baden-W\u00fcrttemberg",
    "wof:name":"Volksbank Backnang E G",
    "wof:placetype":"venue"
},
  "geometry": {"coordinates":[9.50745,49.00832],"type":"Point"}
}