{
  "type": "Feature",
  "properties": {
    "iso:country":"DE",
    "sg:address":"Weimarstr. 32",
    "sg:city":"Kornwestheim",
    "sg:phone":"+49 7154/29900",
    "sg:postcode":"70806",
    "sg:province":"Baden-W\u00fcrttemberg",
    "wof:name":"Ulrich Bader \u00dcbersetzer",
    "wof:placetype":"venue"
},
  "geometry": {"coordinates":[9.183925,48.862358],"type":"Point"}
}