{
  "type": "Feature",
  "properties": {
    "iso:country":"DE",
    "sg:address":"Wiesenburger Str. 21",
    "sg:city":"Belzig",
    "sg:phone":"+49 33841/34880",
    "sg:postcode":"14806",
    "sg:province":"Brandenburg",
    "wof:name":"Dr. Sylvia H\u00e4nig Rechtsanw\u00e4ltin",
    "wof:placetype":"venue"
},
  "geometry": {"coordinates":[12.5849599838,52.1407699585],"type":"Point"}
}