{
  "type": "Feature",
  "properties": {
    "iso:country":"DE",
    "sg:address":"An der Kirchenrenne 12",
    "sg:city":"Rees",
    "sg:phone":"+49 2857/550",
    "sg:postcode":"46459",
    "sg:province":"Nordrhein-Westfalen",
    "wof:name":"H. Hildenhagen",
    "wof:placetype":"venue"
},
  "geometry": {"coordinates":[6.476912,51.727612],"type":"Point"}
}