{
  "type": "Feature",
  "properties": {
    "iso:country":"DE",
    "sg:address":"Gr\u00fcnberger Str. 10",
    "sg:city":"Alsfeld",
    "sg:phone":"+49 6631/3517",
    "sg:postcode":"36304",
    "sg:province":"Hessen",
    "wof:name":"Verein Der Ehemaligen Heinz P\u00f6tz",
    "wof:placetype":"venue"
},
  "geometry": {"coordinates":[9.2654399872,50.7481994629],"type":"Point"}
}