{
  "type": "Feature",
  "properties": {
    "iso:country":"DE",
    "sg:address":"Harscampstr. 75",
    "sg:city":"Aachen",
    "sg:phone":"+49 241/29208",
    "sg:postcode":"52062",
    "sg:province":"Nordrhein-Westfalen",
    "wof:name":"Hans Schmalscheidt Architekt",
    "wof:placetype":"venue"
},
  "geometry": {"coordinates":[6.092728,50.77103],"type":"Point"}
}