{
  "type": "Feature",
  "properties": {
    "iso:country":"DE",
    "sg:address":"Waldstr. 6",
    "sg:city":"Zingst",
    "sg:phone":"+49 38232/15352",
    "sg:postcode":"18374",
    "sg:province":"Mecklenburg-Vorpommern",
    "wof:name":"J. W\u00f6lfer",
    "wof:placetype":"venue"
},
  "geometry": {"coordinates":[12.6779050827,54.4303359985],"type":"Point"}
}