{
  "type": "Feature",
  "properties": {
    "iso:country":"DE",
    "sg:address":"Breite Str. 16",
    "sg:city":"Rinteln",
    "sg:phone":"+49 5751/918064",
    "sg:postcode":"31737",
    "sg:province":"Niedersachsen",
    "wof:name":"Holland Blumen Discount Glasbergen & Griffioen",
    "wof:placetype":"venue"
},
  "geometry": {"coordinates":[9.072939,52.195908],"type":"Point"}
}