{
  "type": "Feature",
  "properties": {
    "iso:country":"DE",
    "sg:address":"Untere R\u00f6merstr. 6",
    "sg:city":"Aholming",
    "sg:phone":"+49 9938/292",
    "sg:postcode":"94527",
    "sg:province":"Bayern",
    "wof:name":"Kath. Pfarramt St. Stephanus",
    "wof:placetype":"venue"
},
  "geometry": {"coordinates":[12.9128141403,48.7351112366],"type":"Point"}
}