{
  "type": "Feature",
  "properties": {
    "iso:country":"DE",
    "sg:address":"An Der Brehnaer Str. 1",
    "sg:city":"Glebitzsch",
    "sg:phone":"+49 4934/9543030",
    "sg:postcode":"06794",
    "sg:province":"Sachsen-Anhalt",
    "wof:name":"Kanal-m\u00dcller-gruppe Rohrleitungsbau Gmbh",
    "wof:placetype":"venue"
},
  "geometry": {"coordinates":[12.193355,51.591972],"type":"Point"}
}