{
  "type": "Feature",
  "properties": {
    "iso:country":"DE",
    "sg:address":"Ziegelweg 2",
    "sg:city":"Thalm\u00e4ssing",
    "sg:phone":"+49 9173/888",
    "sg:postcode":"91177",
    "sg:province":"Bayern",
    "wof:name":"Assenbaum Verwaltungs Gmbh",
    "wof:placetype":"venue"
},
  "geometry": {"coordinates":[11.21397686,49.0886497498],"type":"Point"}
}