{
  "type": "Feature",
  "properties": {
    "iso:country":"DE",
    "sg:address":"Gartenstr. 32",
    "sg:city":"Neum\u00fcnster",
    "sg:phone":"+49 4321/44550",
    "sg:postcode":"24534",
    "sg:province":"Schleswig-Holstein",
    "wof:name":"Jugendg\u00e4stehaus Haus Der Jugend Mittendrin",
    "wof:placetype":"venue"
},
  "geometry": {"coordinates":[9.9816160202,54.0662307739],"type":"Point"}
}