{
  "type": "Feature",
  "properties": {
    "iso:country":"DE",
    "sg:address":"Hagener Str. 151",
    "sg:city":"Kreuztal",
    "sg:phone":"+49 2732/8792",
    "sg:postcode":"57223",
    "sg:province":"Nordrhein-Westfalen",
    "wof:name":"Erhard Berner",
    "wof:placetype":"venue"
},
  "geometry": {"coordinates":[7.9666180611,50.9806518555],"type":"Point"}
}