{
  "type": "Feature",
  "properties": {
    "iso:country":"DE",
    "sg:address":"Wedemarkstr. 74",
    "sg:city":"Wedemark",
    "sg:phone":"+49 5130/5271",
    "sg:postcode":"30900",
    "sg:province":"Niedersachsen",
    "wof:name":"B. Schustereit",
    "wof:placetype":"venue"
},
  "geometry": {"coordinates":[9.740447,52.547169],"type":"Point"}
}