{
  "type": "Feature",
  "properties": {
    "iso:country":"DE",
    "sg:address":"Arndtstr. 55",
    "sg:city":"Dortmund",
    "sg:phone":"+49 231/525811",
    "sg:postcode":"44135",
    "sg:province":"Nordrhein-Westfalen",
    "wof:name":"Michael D\u00fcrk Ingenieur",
    "wof:placetype":"venue"
},
  "geometry": {"coordinates":[7.4803009033,51.5125312805],"type":"Point"}
}