{
  "type": "Feature",
  "properties": {
    "iso:country":"DE",
    "sg:address":"Heisenbergstr. 1",
    "sg:city":"Stuttgart",
    "sg:phone":"+49 711/6860741",
    "sg:postcode":"70569",
    "sg:province":"Baden-W\u00fcrttemberg",
    "wof:name":"Both Gmbh Kantinen Betriebe U. Feink\u00fcche",
    "wof:placetype":"venue"
},
  "geometry": {"coordinates":[9.0830936432,48.7472305298],"type":"Point"}
}