{
  "type": "Feature",
  "properties": {
    "iso:country":"DE",
    "sg:address":"Industriestr. 24",
    "sg:city":"Warendorf",
    "sg:phone":"+49 2581/4777",
    "sg:postcode":"48231",
    "sg:province":"Nordrhein-Westfalen",
    "wof:name":"Stifts-apotheke",
    "wof:placetype":"venue"
},
  "geometry": {"coordinates":[7.965769,51.924377],"type":"Point"}
}