{
  "type": "Feature",
  "properties": {
    "iso:country":"DE",
    "sg:address":"Wilhelm-Weber-Str. 1a",
    "sg:city":"Chemnitz",
    "sg:phone":"+49 371/411303",
    "sg:postcode":"09131",
    "sg:province":"Sachsen",
    "wof:name":"Gunter Voigt",
    "wof:placetype":"venue"
},
  "geometry": {"coordinates":[12.952644,50.851227],"type":"Point"}
}