{
  "type": "Feature",
  "properties": {
    "iso:country":"DE",
    "sg:address":"Steinbacher Str. 26",
    "sg:city":"Rotterode",
    "sg:phone":"+49 36847/40034",
    "sg:postcode":"98587",
    "sg:province":"Th\u00fcringen",
    "wof:name":"G. Wilhelm",
    "wof:placetype":"venue"
},
  "geometry": {"coordinates":[10.560106,50.71207],"type":"Point"}
}