{
  "type": "Feature",
  "properties": {
    "iso:country":"DE",
    "sg:address":"Hauptstr. 23",
    "sg:city":"Ziegenhain",
    "sg:phone":"+49 35246/50242",
    "sg:postcode":"01623",
    "sg:province":"Sachsen",
    "wof:name":"Lothar M\u00f6hler",
    "wof:placetype":"venue"
},
  "geometry": {"coordinates":[13.3114318848,51.1325569153],"type":"Point"}
}