{
  "type": "Feature",
  "properties": {
    "iso:country":"DE",
    "sg:address":"Dexbacher Str. 7",
    "sg:city":"Biedenkopf",
    "sg:phone":"+49 6461/5706",
    "sg:postcode":"35216",
    "sg:province":"Hessen",
    "wof:name":"R. Mayer",
    "wof:placetype":"venue"
},
  "geometry": {"coordinates":[8.5369319916,50.9127616882],"type":"Point"}
}