{
  "type": "Feature",
  "properties": {
    "iso:country":"DE",
    "sg:address":"Bleichstr. 67",
    "sg:city":"Pforzheim",
    "sg:phone":"+49 7231/26822",
    "sg:postcode":"75173",
    "sg:province":"Baden-W\u00fcrttemberg",
    "wof:name":"Restaurant Grillmaster",
    "wof:placetype":"venue"
},
  "geometry": {"coordinates":[8.695400238,48.8843994141],"type":"Point"}
}