{
  "type": "Feature",
  "properties": {
    "iso:country":"DE",
    "sg:address":"Behringstr. 16 b",
    "sg:city":"Dresden",
    "sg:phone":"+49 351/866980",
    "sg:postcode":"01067",
    "sg:province":"Sachsen",
    "wof:name":"B & K Geb\u00e4udereinigung Gmbh",
    "wof:placetype":"venue"
},
  "geometry": {"coordinates":[13.7158021927,51.0547485352],"type":"Point"}
}