{
  "type": "Feature",
  "properties": {
    "iso:country":"DE",
    "sg:address":"Von-Kalb-Ring 26",
    "sg:city":"Oberaurach",
    "sg:phone":"+49 9549/7488",
    "sg:postcode":"97514",
    "sg:province":"Bayern",
    "wof:name":"Suns Sunservice Gmbh",
    "wof:placetype":"venue"
},
  "geometry": {"coordinates":[10.674655,49.908142],"type":"Point"}
}