{
  "type": "Feature",
  "properties": {
    "iso:country":"DE",
    "sg:address":"Tiroler Str. 36",
    "sg:city":"Recklinghausen",
    "sg:phone":"+49 2361/31906",
    "sg:postcode":"45659",
    "sg:province":"Nordrhein-Westfalen",
    "wof:name":"G. Schr\u00f6ter",
    "wof:placetype":"venue"
},
  "geometry": {"coordinates":[7.203971,51.58791],"type":"Point"}
}