{
  "type": "Feature",
  "properties": {
    "iso:country":"DE",
    "sg:address":"Waldmannshofen 42",
    "sg:city":"Creglingen",
    "sg:phone":"+49 9335/518",
    "sg:postcode":"97993",
    "sg:province":"Baden-W\u00fcrttemberg",
    "wof:name":"Biohof Otto Striftler",
    "wof:placetype":"venue"
},
  "geometry": {"coordinates":[10.067536,49.532475],"type":"Point"}
}