{
  "type": "Feature",
  "properties": {
    "iso:country":"DE",
    "sg:address":"Birkenstr. 40",
    "sg:city":"Mauern",
    "sg:postcode":"85419",
    "sg:province":"Bayern",
    "wof:name":"Wollstube A. Konschak",
    "wof:placetype":"venue"
},
  "geometry": {"coordinates":[11.895948,48.521309],"type":"Point"}
}