{
  "type": "Feature",
  "properties": {
    "iso:country":"DE",
    "sg:address":"Am Bierenbonnen 19",
    "sg:city":"Bad Honnef",
    "sg:phone":"+49 2224/93210",
    "sg:postcode":"53604",
    "sg:province":"Nordrhein-Westfalen",
    "wof:name":"Hans Foppen Architekt",
    "wof:placetype":"venue"
},
  "geometry": {"coordinates":[7.243199,50.639629],"type":"Point"}
}