{
  "type": "Feature",
  "properties": {
    "iso:country":"DE",
    "sg:address":"Roitzscher Str. 40",
    "sg:city":"Dresden",
    "sg:phone":"+49 351/4226776",
    "sg:postcode":"01157",
    "sg:province":"Sachsen",
    "wof:name":"Uta F\u00fctterer",
    "wof:placetype":"venue"
},
  "geometry": {"coordinates":[13.67191,51.05991],"type":"Point"}
}