{
  "type": "Feature",
  "properties": {
    "iso:country":"DE",
    "sg:address":"Hans-B\u00f6ckler-Allee 9",
    "sg:city":"Hannover",
    "sg:phone":"+49 511/76077076",
    "sg:postcode":"30173",
    "sg:province":"Niedersachsen",
    "wof:name":"Hier.de - Hannover Internet Einkaufs Region",
    "wof:placetype":"venue"
},
  "geometry": {"coordinates":[9.765927,52.370892],"type":"Point"}
}