{
  "type": "Feature",
  "properties": {
    "iso:country":"DE",
    "sg:address":"Kernerstr. 29",
    "sg:city":"Rechberghausen",
    "sg:phone":"+49 7161/52606",
    "sg:postcode":"73098",
    "sg:province":"Baden-W\u00fcrttemberg",
    "wof:name":"E. B\u00fcttner",
    "wof:placetype":"venue"
},
  "geometry": {"coordinates":[9.6347370148,48.7283821106],"type":"Point"}
}