{
  "type": "Feature",
  "properties": {
    "iso:country":"DE",
    "sg:address":"Ahrensb\u00f6ker Str. 94 a",
    "sg:city":"Stockelsdorf",
    "sg:phone":"+49 451/496442",
    "sg:postcode":"23617",
    "sg:province":"Schleswig-Holstein",
    "wof:name":"Rainer Schlichting",
    "wof:placetype":"venue"
},
  "geometry": {"coordinates":[10.646476,53.898289],"type":"Point"}
}