{
  "type": "Feature",
  "properties": {
    "iso:country":"DE",
    "sg:address":"Neuenteich 2a",
    "sg:city":"Wuppertal",
    "sg:postcode":"42107",
    "sg:province":"Nordrhein-Westfalen",
    "wof:name":"Ft - Tauchen & Freizeit Gmbh",
    "wof:placetype":"venue"
},
  "geometry": {"coordinates":[7.1563429832,51.2641906738],"type":"Point"}
}