{
  "type": "Feature",
  "properties": {
    "iso:country":"DE",
    "sg:address":"Eisenstr. 30",
    "sg:city":"R\u00fcsselsheim",
    "sg:phone":"+49 6142/8770",
    "sg:postcode":"65428",
    "sg:province":"Hessen",
    "wof:name":"F. I. N. D. E. R. Verwaltungs Gmbh",
    "wof:placetype":"venue"
},
  "geometry": {"coordinates":[8.4276199341,49.9778785706],"type":"Point"}
}