{
  "type": "Feature",
  "properties": {
    "iso:country":"DE",
    "sg:address":"Wilhelmstr. 13",
    "sg:city":"Torgelow",
    "sg:phone":"+49 3976/202532",
    "sg:postcode":"17358",
    "sg:province":"Mecklenburg-Vorpommern",
    "wof:name":"Erhard Kriesel",
    "wof:placetype":"venue"
},
  "geometry": {"coordinates":[13.996047,53.626839],"type":"Point"}
}