{
  "type": "Feature",
  "properties": {
    "iso:country":"DE",
    "sg:address":"Wallensteiner Weg 89",
    "sg:city":"Homberg",
    "sg:phone":"+49 5686/569",
    "sg:postcode":"34576",
    "sg:province":"Hessen",
    "wof:name":"Pension Elise Arrich",
    "wof:placetype":"venue"
},
  "geometry": {"coordinates":[9.4662322998,50.9488220215],"type":"Point"}
}