{
  "type": "Feature",
  "properties": {
    "iso:country":"DE",
    "sg:address":"Rotenh\u00e4user Str. 8",
    "sg:city":"Hamburg",
    "sg:phone":"+49 40/751381",
    "sg:postcode":"21109",
    "sg:province":"Hamburg",
    "wof:name":"Behrens & Co. Bauunternehmung Gmbh",
    "wof:placetype":"venue"
},
  "geometry": {"coordinates":[10.003394,53.505844],"type":"Point"}
}