{
  "type": "Feature",
  "properties": {
    "iso:country":"DE",
    "sg:address":"Hans-B\u00f6ckler-Str. 8",
    "sg:city":"Aichach",
    "sg:phone":"+49 8251/3292",
    "sg:postcode":"86551",
    "sg:province":"Bayern",
    "wof:name":"R. Mikschl Squash-center",
    "wof:placetype":"venue"
},
  "geometry": {"coordinates":[11.1233024597,48.4430541992],"type":"Point"}
}