{
  "type": "Feature",
  "properties": {
    "iso:country":"DE",
    "sg:address":"Ottmarsfelder Weg 5",
    "sg:city":"Pleinfeld",
    "sg:phone":"+49 9144/6292",
    "sg:postcode":"91785",
    "sg:province":"Bayern",
    "wof:name":"Thomas Pich Masseur",
    "wof:placetype":"venue"
},
  "geometry": {"coordinates":[10.986947,49.101837],"type":"Point"}
}