{
  "type": "Feature",
  "properties": {
    "iso:country":"DE",
    "sg:address":"Unter den Linden 13",
    "sg:city":"Schl\u00fcchtern",
    "sg:phone":"+49 6661/1445",
    "sg:postcode":"36381",
    "sg:province":"Hessen",
    "wof:name":"Restaurant Eckeb\u00e4cker",
    "wof:placetype":"venue"
},
  "geometry": {"coordinates":[9.524438858,50.3465614319],"type":"Point"}
}