{
  "type": "Feature",
  "properties": {
    "iso:country":"DE",
    "sg:address":"Alte Schulstr. 18 a",
    "sg:city":"Langenfeld",
    "sg:phone":"+49 2173/149359",
    "sg:postcode":"40764",
    "sg:province":"Nordrhein-Westfalen",
    "wof:name":"August Schmid",
    "wof:placetype":"venue"
},
  "geometry": {"coordinates":[6.979631,51.092545],"type":"Point"}
}