{
  "type": "Feature",
  "properties": {
    "iso:country":"DE",
    "sg:address":"Neustadter Hauptstr. 58",
    "sg:city":"Waiblingen",
    "sg:phone":"+49 7151/81331",
    "sg:postcode":"71336",
    "sg:province":"Baden-W\u00fcrttemberg",
    "wof:name":"Schillerstube",
    "wof:placetype":"venue"
},
  "geometry": {"coordinates":[9.323234,48.846813],"type":"Point"}
}