{
  "type": "Feature",
  "properties": {
    "iso:country":"DE",
    "sg:address":"Arnold-Janssen-Str. 20",
    "sg:city":"Sankt Augustin",
    "sg:phone":"+49 2241/237431",
    "sg:postcode":"53757",
    "sg:province":"Nordrhein-Westfalen",
    "wof:name":"Monumenta Serica Bibliothek",
    "wof:placetype":"venue"
},
  "geometry": {"coordinates":[7.182128,50.774178],"type":"Point"}
}