{
  "type": "Feature",
  "properties": {
    "iso:country":"DE",
    "sg:address":"Kyllbergstr. 153",
    "sg:city":"P\u00fcttlingen",
    "sg:phone":"+49 6806/4302",
    "sg:postcode":"66346",
    "sg:province":"Saarland",
    "wof:name":"Kyllbergschenke",
    "wof:placetype":"venue"
},
  "geometry": {"coordinates":[6.9000220299,49.3172950745],"type":"Point"}
}