{
  "type": "Feature",
  "properties": {
    "iso:country":"DE",
    "sg:address":"Dorfstr. 21",
    "sg:city":"Hennersdorf",
    "sg:postcode":"03253",
    "sg:province":"Brandenburg",
    "wof:name":"Torner Verwaltungs- Gmbh",
    "wof:placetype":"venue"
},
  "geometry": {"coordinates":[13.6039876938,51.6357460022],"type":"Point"}
}