{
  "type": "Feature",
  "properties": {
    "iso:country":"DE",
    "sg:address":"Sandtorfer Weg. 4 b",
    "sg:city":"Lampertheim",
    "sg:postcode":"68623",
    "sg:province":"Hessen",
    "wof:name":"Erotik Er.de - Erotik- Und Sex-verzeichniss",
    "wof:placetype":"venue"
},
  "geometry": {"coordinates":[8.484449,49.587387],"type":"Point"}
}