{
  "type": "Feature",
  "properties": {
    "iso:country":"DE",
    "sg:address":"Hermeskeiler Str. 14",
    "sg:city":"K\u00f6ln",
    "sg:postcode":"50935",
    "sg:province":"Nordrhein-Westfalen",
    "wof:name":"Peter Prange",
    "wof:placetype":"venue"
},
  "geometry": {"coordinates":[6.907061,50.917439],"type":"Point"}
}