{
  "type": "Feature",
  "properties": {
    "iso:country":"DE",
    "sg:address":"Nikolaus-Otto-Str. 19",
    "sg:city":"Leinfelden-Echterdingen",
    "sg:phone":"+49 711/792498",
    "sg:postcode":"70771",
    "sg:province":"Baden-W\u00fcrttemberg",
    "wof:name":"Buchbinderei Gan\u00dfloser Kg",
    "wof:placetype":"venue"
},
  "geometry": {"coordinates":[9.162274,48.695873],"type":"Point"}
}