{
  "type": "Feature",
  "properties": {
    "iso:country":"DE",
    "sg:address":"Neuffener Str. 13",
    "sg:city":"Dettingen",
    "sg:phone":"+49 7123/972833",
    "sg:postcode":"72581",
    "sg:province":"Baden-W\u00fcrttemberg",
    "wof:name":"Cafe Peschke",
    "wof:placetype":"venue"
},
  "geometry": {"coordinates":[9.346362114,48.530544281],"type":"Point"}
}