{
  "type": "Feature",
  "properties": {
    "iso:country":"DE",
    "sg:address":"Eichelweg 6",
    "sg:city":"Wiesloch",
    "sg:phone":"+49 6222/4019",
    "sg:postcode":"69168",
    "sg:province":"Baden-W\u00fcrttemberg",
    "wof:name":"Imha Gesellschaft F\u00fcr Immo- Bilien Und Hausverwaltung Mbh",
    "wof:placetype":"venue"
},
  "geometry": {"coordinates":[8.6775979996,49.2903213501],"type":"Point"}
}