{
  "type": "Feature",
  "properties": {
    "iso:country":"DE",
    "sg:address":"Bahnhofstr. 6",
    "sg:city":"Kronberg",
    "sg:postcode":"61476",
    "sg:province":"Hessen",
    "wof:name":"Norelle Gmbh",
    "wof:placetype":"venue"
},
  "geometry": {"coordinates":[8.514408,50.179657],"type":"Point"}
}