{
  "type": "Feature",
  "properties": {
    "iso:country":"DE",
    "sg:address":"Luitpoldstr. 3",
    "sg:city":"Se\u00dflach",
    "sg:phone":"+49 9569/717",
    "sg:postcode":"96145",
    "sg:province":"Bayern",
    "wof:name":"Heimatmuseum Se\u00dfbach",
    "wof:placetype":"venue"
},
  "geometry": {"coordinates":[10.843996,50.187168],"type":"Point"}
}