{
  "type": "Feature",
  "properties": {
    "iso:country":"DE",
    "sg:address":"Hofhalde 11",
    "sg:city":"Konstanz",
    "sg:phone":"+49 7531/29352",
    "sg:postcode":"78462",
    "sg:province":"Baden-W\u00fcrttemberg",
    "wof:name":"Sedir",
    "wof:placetype":"venue"
},
  "geometry": {"coordinates":[9.1758069992,47.662437439],"type":"Point"}
}