{
  "type": "Feature",
  "properties": {
    "iso:country":"DE",
    "sg:address":"Nideggener Str. 68",
    "sg:city":"D\u00fcren",
    "sg:phone":"+49 2421/52423",
    "sg:postcode":"52349",
    "sg:province":"Nordrhein-Westfalen",
    "wof:name":"Siegmund Ptach Masseur",
    "wof:placetype":"venue"
},
  "geometry": {"coordinates":[6.489237,50.793804],"type":"Point"}
}