{
  "type": "Feature",
  "properties": {
    "iso:country":"DE",
    "sg:address":"Niedenstr. 121",
    "sg:city":"Hilden",
    "sg:phone":"+49 2103/53009",
    "sg:postcode":"40721",
    "sg:province":"Nordrhein-Westfalen",
    "wof:name":"M\u00f6bel Ric Gmbh",
    "wof:placetype":"venue"
},
  "geometry": {"coordinates":[6.90409,51.169327],"type":"Point"}
}