{
  "type": "Feature",
  "properties": {
    "iso:country":"DE",
    "sg:address":"Michelstr. 22a",
    "sg:city":"Kirkel",
    "sg:phone":"+49 6841/8208",
    "sg:postcode":"66459",
    "sg:province":"Saarland",
    "wof:name":"D. H. Knaack",
    "wof:placetype":"venue"
},
  "geometry": {"coordinates":[7.2475190163,49.3170127869],"type":"Point"}
}