{
  "type": "Feature",
  "properties": {
    "iso:country":"DE",
    "sg:address":"Martin-Treu-Str. 28",
    "sg:city":"N\u00fcrnberg",
    "sg:phone":"+49 9189/40689",
    "sg:postcode":"90403",
    "sg:province":"Bayern",
    "wof:name":"Angelikas Teppichboden- Reinigung",
    "wof:placetype":"venue"
},
  "geometry": {"coordinates":[11.0818,49.454807],"type":"Point"}
}