{
  "type": "Feature",
  "properties": {
    "iso:country":"DE",
    "sg:address":"Talstr. 70",
    "sg:city":"Freiburg",
    "sg:phone":"+49 761/71420",
    "sg:postcode":"79102",
    "sg:province":"Baden-W\u00fcrttemberg",
    "wof:name":"Braust\u00fcble",
    "wof:placetype":"venue"
},
  "geometry": {"coordinates":[7.8591179848,47.9887046814],"type":"Point"}
}