{
  "type": "Feature",
  "properties": {
    "iso:country":"DE",
    "sg:address":"Hochstr. 19 a",
    "sg:city":"Brombachtal",
    "sg:phone":"+49 6063/3810",
    "sg:postcode":"64753",
    "sg:province":"Hessen",
    "wof:name":"P. Und E. Claa\u00dfen",
    "wof:placetype":"venue"
},
  "geometry": {"coordinates":[8.969187,49.728638],"type":"Point"}
}