{
  "type": "Feature",
  "properties": {
    "iso:country":"DE",
    "sg:address":"Br\u00fcckstr. 9",
    "sg:city":"Ratingen",
    "sg:phone":"+49 2102/846934",
    "sg:postcode":"40882",
    "sg:province":"Nordrhein-Westfalen",
    "wof:name":"Margot Czerny-lamottke Hebamme",
    "wof:placetype":"venue"
},
  "geometry": {"coordinates":[6.858924,51.300999],"type":"Point"}
}