{
  "type": "Feature",
  "properties": {
    "iso:country":"DE",
    "sg:address":"Freizeitzentrum",
    "sg:city":"Sinzig",
    "sg:postcode":"53489",
    "sg:province":"Rheinland-Pfalz",
    "wof:name":"Josef Heuser",
    "wof:placetype":"venue"
},
  "geometry": {"coordinates":[7.255465,50.546227],"type":"Point"}
}