{
  "type": "Feature",
  "properties": {
    "iso:country":"DE",
    "sg:address":"Auf dem Steinacker 3",
    "sg:city":"Vielbach",
    "sg:phone":"+49 2626/8458",
    "sg:postcode":"56244",
    "sg:province":"Rheinland-Pfalz",
    "wof:name":"Irene Burckhardt Krankengymnastin",
    "wof:placetype":"venue"
},
  "geometry": {"coordinates":[7.778025,50.509281],"type":"Point"}
}