{
  "type": "Feature",
  "properties": {
    "iso:country":"DE",
    "sg:address":"Birkenweg 3-5",
    "sg:city":"Hamburg",
    "sg:postcode":"25451",
    "sg:province":"Schleswig-Holstein",
    "wof:name":"Medizintechnik Und Applikationspersonal",
    "wof:placetype":"venue"
},
  "geometry": {"coordinates":[9.895195,53.731945],"type":"Point"}
}