{
  "type": "Feature",
  "properties": {
    "iso:country":"DE",
    "sg:address":"Oberstr. 28",
    "sg:city":"Kiedrich",
    "sg:phone":"+49 6123/5181",
    "sg:postcode":"65399",
    "sg:province":"Hessen",
    "wof:name":"J\u00fcrger Pyko",
    "wof:placetype":"venue"
},
  "geometry": {"coordinates":[8.0815458298,50.0417022705],"type":"Point"}
}