{
  "type": "Feature",
  "properties": {
    "iso:country":"DE",
    "sg:address":"Uhlstr. 73",
    "sg:city":"Br\u00fchl",
    "sg:phone":"+49 2232/760254",
    "sg:postcode":"50321",
    "sg:province":"Nordrhein-Westfalen",
    "wof:name":"Kumral-hensgens",
    "wof:placetype":"venue"
},
  "geometry": {"coordinates":[6.9025478363,50.8263473511],"type":"Point"}
}