{
  "type": "Feature",
  "properties": {
    "iso:country":"DE",
    "sg:address":"Moritz-Werner-Str. 16",
    "sg:city":"Eschwege",
    "sg:phone":"+49 5651/6189",
    "sg:postcode":"37269",
    "sg:province":"Hessen",
    "wof:name":"Ambulantes Pflegeteam Edwin Heckendorf",
    "wof:placetype":"venue"
},
  "geometry": {"coordinates":[10.04673,51.187119],"type":"Point"}
}