{
  "type": "Feature",
  "properties": {
    "iso:country":"DE",
    "sg:address":"K\u00fcnkelinstr. 6",
    "sg:city":"Schorndorf",
    "sg:phone":"+49 7181/62387",
    "sg:postcode":"73614",
    "sg:province":"Baden-W\u00fcrttemberg",
    "wof:name":"Lotus-china-restaurant",
    "wof:placetype":"venue"
},
  "geometry": {"coordinates":[9.5224437714,48.8047409058],"type":"Point"}
}