{
  "type": "Feature",
  "properties": {
    "iso:country":"DE",
    "sg:address":"Schlo\u00dftorstr. 35",
    "sg:city":"Kleve",
    "sg:phone":"+49 2821/25395",
    "sg:postcode":"47533",
    "sg:province":"Nordrhein-Westfalen",
    "wof:name":"J. Van Zoggel",
    "wof:placetype":"venue"
},
  "geometry": {"coordinates":[6.138216,51.786819],"type":"Point"}
}