{
  "type": "Feature",
  "properties": {
    "iso:country":"DE",
    "sg:address":"August-Borsig-Str. 13",
    "sg:city":"Mannheim",
    "sg:phone":"+49 621/842570",
    "sg:postcode":"68199",
    "sg:province":"Baden-W\u00fcrttemberg",
    "wof:name":"Axima Refrigeration Gmbh",
    "wof:placetype":"venue"
},
  "geometry": {"coordinates":[8.505396,49.460239],"type":"Point"}
}