{
  "type": "Feature",
  "properties": {
    "iso:country":"DE",
    "sg:address":"Borsteler Chaussee 51",
    "sg:city":"Hamburg",
    "sg:phone":"+49 40/514320",
    "sg:postcode":"22453",
    "sg:province":"Hamburg",
    "wof:name":"Direct Friends Werbeagentur F\u00fcr Direct Marketing Und",
    "wof:placetype":"venue"
},
  "geometry": {"coordinates":[9.9825391769,53.6053009033],"type":"Point"}
}