{
  "type": "Feature",
  "properties": {
    "iso:country":"DE",
    "sg:address":"Richardstr. 35",
    "sg:city":"Erftstadt",
    "sg:postcode":"50374",
    "sg:province":"Nordrhein-Westfalen",
    "wof:name":"Enzymeta Gmbh",
    "wof:placetype":"venue"
},
  "geometry": {"coordinates":[6.7699689865,50.8055419922],"type":"Point"}
}