{
  "type": "Feature",
  "properties": {
    "iso:country":"DE",
    "sg:address":"Sandberg 104",
    "sg:city":"Itzehoe",
    "sg:phone":"+49 4821",
    "sg:postcode":"25524",
    "sg:province":"Schleswig-Holstein",
    "wof:name":"Predigt Archiv Der Cg Itzehoe",
    "wof:placetype":"venue"
},
  "geometry": {"coordinates":[9.526093,53.926987],"type":"Point"}
}