{
  "type": "Feature",
  "properties": {
    "iso:country":"DE",
    "sg:address":"Breite Str. 17",
    "sg:city":"Hettstedt",
    "sg:postcode":"06333",
    "sg:province":"Sachsen-Anhalt",
    "wof:name":"Quelle Agentur",
    "wof:placetype":"venue"
},
  "geometry": {"coordinates":[11.5137042999,51.6446495056],"type":"Point"}
}