{
  "type": "Feature",
  "properties": {
    "iso:country":"DE",
    "sg:address":"Klausenstr. 17",
    "sg:city":"Nordheim",
    "sg:phone":"+49 7133/960342",
    "sg:postcode":"74226",
    "sg:province":"Baden-W\u00fcrttemberg",
    "wof:name":"Dwz Wiederladetechnik Gmbh",
    "wof:placetype":"venue"
},
  "geometry": {"coordinates":[9.1233510971,49.1073570251],"type":"Point"}
}