{
  "type": "Feature",
  "properties": {
    "iso:country":"DE",
    "sg:address":"Hollerallee 14a",
    "sg:city":"Bremen",
    "sg:postcode":"28209",
    "sg:province":"Bremen",
    "wof:name":"Bening Beteiligungs Gmbh",
    "wof:placetype":"venue"
},
  "geometry": {"coordinates":[8.8293399811,53.0823707581],"type":"Point"}
}