{
  "type": "Feature",
  "properties": {
    "iso:country":"DE",
    "sg:address":"Viktor-R\u00f6per-Str. 26",
    "sg:city":"Warstein",
    "sg:phone":"+49 2925/1878",
    "sg:postcode":"59581",
    "sg:province":"Nordrhein-Westfalen",
    "wof:name":"K. Ferber",
    "wof:placetype":"venue"
},
  "geometry": {"coordinates":[8.254415,51.478607],"type":"Point"}
}