{
  "type": "Feature",
  "properties": {
    "iso:country":"DE",
    "sg:address":"Rembrandtstr. 25",
    "sg:city":"Langf\u00f6rden",
    "sg:phone":"+49 4447/1757",
    "sg:postcode":"49377",
    "sg:province":"Niedersachsen",
    "wof:name":"Die Inoffizielle Fm 2002 Seite",
    "wof:placetype":"venue"
},
  "geometry": {"coordinates":[8.249968,52.784988],"type":"Point"}
}