{
  "type": "Feature",
  "properties": {
    "iso:country":"DE",
    "sg:address":"Hirschbergstr. 22b",
    "sg:city":"M\u00fcnchen",
    "sg:phone":"+49 89/133771",
    "sg:postcode":"80634",
    "sg:province":"Bayern",
    "wof:name":"Karin Schreifeldt Heilpraktiker",
    "wof:placetype":"venue"
},
  "geometry": {"coordinates":[11.5323047638,48.1486129761],"type":"Point"}
}