{
  "type": "Feature",
  "properties": {
    "iso:country":"DE",
    "sg:address":"Rosenfelder Str. 46",
    "sg:city":"Balingen",
    "sg:phone":"+49 7433/15531",
    "sg:postcode":"72336",
    "sg:province":"Baden-W\u00fcrttemberg",
    "wof:name":"Josefine Ser",
    "wof:placetype":"venue"
},
  "geometry": {"coordinates":[8.84468,48.282173],"type":"Point"}
}