{
  "type": "Feature",
  "properties": {
    "iso:country":"DE",
    "sg:address":"Willicher Str. 39",
    "sg:city":"T\u00f6nisvorst",
    "sg:phone":"+49 2151/794439",
    "sg:postcode":"47918",
    "sg:province":"Nordrhein-Westfalen",
    "wof:name":"Leonhard Schmitz Leder- Gummi- Und Schuh-",
    "wof:placetype":"venue"
},
  "geometry": {"coordinates":[6.4975018501,51.3187446594],"type":"Point"}
}