{
  "type": "Feature",
  "properties": {
    "iso:country":"DE",
    "sg:address":"Wunsiedler Str. 14-16",
    "sg:city":"Kemnath",
    "sg:phone":"+49 9642/70990",
    "sg:postcode":"95478",
    "sg:province":"Bayern",
    "wof:name":"Edi Ganssm\u00dcller Vertriebs Gmbh",
    "wof:placetype":"venue"
},
  "geometry": {"coordinates":[11.891426,49.872234],"type":"Point"}
}