{
  "type": "Feature",
  "properties": {
    "iso:country":"DE",
    "sg:address":"Industriestra\u00dfe 27a",
    "sg:city":"Gr\u00f6benzell",
    "sg:phone":"+49 8142/50761",
    "sg:postcode":"82194",
    "sg:province":"Bayern",
    "wof:name":"Flohr Schwei\u00dftechnik Reparatur U. Ersatzteile",
    "wof:placetype":"venue"
},
  "geometry": {"coordinates":[11.3863315582,48.1872787476],"type":"Point"}
}