{
  "type": "Feature",
  "properties": {
    "iso:country":"DE",
    "sg:address":"Westerkamp 15",
    "sg:city":"Vrees",
    "sg:postcode":"49757",
    "sg:province":"Niedersachsen",
    "wof:name":"Schrandt Verwaltungs- Und Beteiligungs- Gmbh",
    "wof:placetype":"venue"
},
  "geometry": {"coordinates":[7.7612361908,52.8858985901],"type":"Point"}
}