{
  "type": "Feature",
  "properties": {
    "iso:country":"DE",
    "sg:address":"Brunnenallee 19 a",
    "sg:city":"B\u00fcnde",
    "sg:phone":"+49 5223/5042",
    "sg:postcode":"32257",
    "sg:province":"Nordrhein-Westfalen",
    "wof:name":"Karl-heinz Klingler",
    "wof:placetype":"venue"
},
  "geometry": {"coordinates":[8.594534,52.199173],"type":"Point"}
}