{
  "type": "Feature",
  "properties": {
    "iso:country":"DE",
    "sg:address":"An der Schleuse 8",
    "sg:city":"Hemer",
    "sg:phone":"+49 2372/91975",
    "sg:postcode":"58675",
    "sg:province":"Nordrhein-Westfalen",
    "wof:name":"Raufoss Metall Gmbh",
    "wof:placetype":"venue"
},
  "geometry": {"coordinates":[7.792849,51.40369],"type":"Point"}
}