{
  "type": "Feature",
  "properties": {
    "iso:country":"DE",
    "sg:address":"Industrieweg 6",
    "sg:city":"Weidenstetten",
    "sg:phone":"+49 7340/929633",
    "sg:postcode":"89197",
    "sg:province":"Baden-W\u00fcrttemberg",
    "wof:name":"Sinasi Katlan",
    "wof:placetype":"venue"
},
  "geometry": {"coordinates":[9.998686,48.554482],"type":"Point"}
}