{
  "type": "Feature",
  "properties": {
    "iso:country":"DE",
    "sg:address":"Kreuzstr. 15",
    "sg:city":"Bietigheim",
    "sg:phone":"+49 7245/5808",
    "sg:postcode":"76467",
    "sg:province":"Baden-W\u00fcrttemberg",
    "wof:name":"Volz",
    "wof:placetype":"venue"
},
  "geometry": {"coordinates":[8.247415,48.912083],"type":"Point"}
}