{
  "type": "Feature",
  "properties": {
    "iso:country":"DE",
    "sg:address":"Am Fuchsberg",
    "sg:city":"Schmerbach",
    "sg:phone":"+49 36259/58837",
    "sg:postcode":"99891",
    "sg:province":"Th\u00fcringen",
    "wof:name":"Waldgastst\u00e4tte K\u00f6hlerh\u00fctte",
    "wof:placetype":"venue"
},
  "geometry": {"coordinates":[10.4512987137,50.9031600952],"type":"Point"}
}