{
  "type": "Feature",
  "properties": {
    "iso:country":"DE",
    "sg:address":"Weender Landstr. 43",
    "sg:city":"G\u00f6ttingen",
    "sg:phone":"+49 551/383320",
    "sg:postcode":"37075",
    "sg:province":"Niedersachsen",
    "wof:name":"Berliner Hof",
    "wof:placetype":"venue"
},
  "geometry": {"coordinates":[9.9321594238,51.5433502197],"type":"Point"}
}