{
  "type": "Feature",
  "properties": {
    "iso:country":"DE",
    "sg:address":"Heienkamp 8",
    "sg:city":"Lippetal",
    "sg:phone":"+49 2923/444",
    "sg:postcode":"59510",
    "sg:province":"Nordrhein-Westfalen",
    "wof:name":"F.-w. Nienkemper",
    "wof:placetype":"venue"
},
  "geometry": {"coordinates":[8.171309,51.697685],"type":"Point"}
}