{
  "type": "Feature",
  "properties": {
    "iso:country":"DE",
    "sg:address":"Untere Fulder Gasse 55",
    "sg:city":"Alsfeld",
    "sg:phone":"+49 6631/1516",
    "sg:postcode":"36304",
    "sg:province":"Hessen",
    "wof:name":"Zur Turmstube",
    "wof:placetype":"venue"
},
  "geometry": {"coordinates":[9.2736663818,50.7497444153],"type":"Point"}
}