{
  "type": "Feature",
  "properties": {
    "iso:country":"DE",
    "sg:address":"Stadtamhof 4",
    "sg:city":"Regensburg",
    "sg:phone":"+49 941/87570",
    "sg:postcode":"93059",
    "sg:province":"Bayern",
    "wof:name":"Gardinen A. Ulrich",
    "wof:placetype":"venue"
},
  "geometry": {"coordinates":[12.0974636078,49.0248413086],"type":"Point"}
}