{
  "type": "Feature",
  "properties": {
    "iso:country":"DE",
    "sg:address":"Bremerstr. 31 a",
    "sg:city":"Wiefelstede",
    "sg:phone":"+49 4402/916774",
    "sg:postcode":"26215",
    "sg:province":"Niedersachsen",
    "wof:name":"Zietz Und Partner Architekten",
    "wof:placetype":"venue"
},
  "geometry": {"coordinates":[8.127933,53.200504],"type":"Point"}
}