{
  "type": "Feature",
  "properties": {
    "iso:country":"DE",
    "sg:address":"Dorfstr. 11 a",
    "sg:city":"Bechstedt-Wagd",
    "sg:phone":"+49 361/3459692",
    "sg:postcode":"99102",
    "sg:province":"Th\u00fcringen",
    "wof:name":"R. Schreyer",
    "wof:placetype":"venue"
},
  "geometry": {"coordinates":[11.150852,50.91317],"type":"Point"}
}