{
  "type": "Feature",
  "properties": {
    "iso:country":"DE",
    "sg:address":"Blumenstr. 5",
    "sg:city":"Ehingen",
    "sg:phone":"+49 7391/51448",
    "sg:postcode":"89584",
    "sg:province":"Baden-W\u00fcrttemberg",
    "wof:name":"Klaus Hofstetter Architekt",
    "wof:placetype":"venue"
},
  "geometry": {"coordinates":[9.720747,48.279423],"type":"Point"}
}