{
  "type": "Feature",
  "properties": {
    "iso:country":"DE",
    "sg:address":"Weitkampstr. 36",
    "sg:city":"Emsdetten",
    "sg:phone":"+49 4925/7293880",
    "sg:postcode":"48282",
    "sg:province":"Nordrhein-Westfalen",
    "wof:name":"Robert Gmbh",
    "wof:placetype":"venue"
},
  "geometry": {"coordinates":[7.5311479568,52.1797904968],"type":"Point"}
}