{
  "type": "Feature",
  "properties": {
    "iso:country":"DE",
    "sg:address":"Steinfurter Str. 72",
    "sg:city":"Ascheberg",
    "sg:phone":"+49 2593/5536",
    "sg:postcode":"59387",
    "sg:province":"Nordrhein-Westfalen",
    "wof:name":"Heinrich H\u00f6welhans",
    "wof:placetype":"venue"
},
  "geometry": {"coordinates":[7.6488661766,51.7999954224],"type":"Point"}
}