{
  "type": "Feature",
  "properties": {
    "iso:country":"DE",
    "sg:address":"Am Knill 44c",
    "sg:city":"Hamburg",
    "sg:phone":"+49 40/6458980",
    "sg:postcode":"22147",
    "sg:province":"Hamburg",
    "wof:name":"H. Hahnenberger Gmbh & Co. Kg",
    "wof:placetype":"venue"
},
  "geometry": {"coordinates":[10.1285762787,53.6088981628],"type":"Point"}
}