{
  "type": "Feature",
  "properties": {
    "iso:country":"DE",
    "sg:address":"Rheinstr 13",
    "sg:city":"Frankfurt",
    "sg:phone":"+49 69/9074770",
    "sg:postcode":"60325",
    "sg:province":"Hessen",
    "wof:name":"Ubitrade Gmbh",
    "wof:placetype":"venue"
},
  "geometry": {"coordinates":[8.6596660614,50.1124458313],"type":"Point"}
}