{
  "type": "Feature",
  "properties": {
    "iso:country":"DE",
    "sg:address":"Kappstr. 9",
    "sg:city":"Angelburg",
    "sg:phone":"+49 6464/7175",
    "sg:postcode":"35719",
    "sg:province":"Hessen",
    "wof:name":"Ernst Pimpl",
    "wof:placetype":"venue"
},
  "geometry": {"coordinates":[8.4361858368,50.8080711365],"type":"Point"}
}