{
  "type": "Feature",
  "properties": {
    "iso:country":"DE",
    "sg:address":"Asternweg 2",
    "sg:city":"Datteln",
    "sg:phone":"+49 2363/728077",
    "sg:postcode":"45711",
    "sg:province":"Nordrhein-Westfalen",
    "wof:name":"Dekorkiesboden Lux",
    "wof:placetype":"venue"
},
  "geometry": {"coordinates":[7.289233,51.628361],"type":"Point"}
}