{
  "type": "Feature",
  "properties": {
    "iso:country":"DE",
    "sg:address":"Westendstr. 273",
    "sg:city":"M\u00fcnchen",
    "sg:phone":"+49 89/575813",
    "sg:postcode":"80686",
    "sg:province":"Bayern",
    "wof:name":"Hans Hegenbarth Architekt",
    "wof:placetype":"venue"
},
  "geometry": {"coordinates":[11.510914,48.126759],"type":"Point"}
}