{
  "type": "Feature",
  "properties": {
    "iso:country":"DE",
    "sg:address":"Gr\u00fcnepleistr. 32",
    "sg:city":"Roetgen",
    "sg:phone":"+49 2471/2651",
    "sg:postcode":"52159",
    "sg:province":"Nordrhein-Westfalen",
    "wof:name":"Berthold Wolter",
    "wof:placetype":"venue"
},
  "geometry": {"coordinates":[6.212049,50.638847],"type":"Point"}
}