{
  "type": "Feature",
  "properties": {
    "iso:country":"DE",
    "sg:address":"Ernst-Iden-Ring 1",
    "sg:city":"Gol\u00dfen",
    "sg:phone":"+49 4935/4523800",
    "sg:postcode":"15938",
    "sg:province":"Brandenburg",
    "wof:name":"Iden Golssen Gmbh",
    "wof:placetype":"venue"
},
  "geometry": {"coordinates":[13.5650148392,51.9840583801],"type":"Point"}
}