{
  "type": "Feature",
  "properties": {
    "iso:country":"DE",
    "sg:address":"Ascher\u00f6der Str. 47",
    "sg:city":"Schwalmstadt",
    "sg:phone":"+49 6691/1316",
    "sg:postcode":"34613",
    "sg:province":"Hessen",
    "wof:name":"Lambrecht Gmbh",
    "wof:placetype":"venue"
},
  "geometry": {"coordinates":[9.2045307159,50.9084320068],"type":"Point"}
}