{
  "type": "Feature",
  "properties": {
    "iso:country":"DE",
    "sg:address":"Mittelrieder Str. 9",
    "sg:city":"Oberrieden",
    "sg:phone":"+49 8265/672",
    "sg:postcode":"87769",
    "sg:province":"Bayern",
    "wof:name":"Gastst\u00e4tte Konrad Huber",
    "wof:placetype":"venue"
},
  "geometry": {"coordinates":[10.4244756699,48.0914115906],"type":"Point"}
}