{
  "type": "Feature",
  "properties": {
    "iso:country":"DE",
    "sg:address":"Jasebeck 1a",
    "sg:city":"Damnatz",
    "sg:phone":"+49 5865/988778",
    "sg:postcode":"29472",
    "sg:province":"Niedersachsen",
    "wof:name":"Wolfram Belz Architekt",
    "wof:placetype":"venue"
},
  "geometry": {"coordinates":[11.141117,53.162704],"type":"Point"}
}