{
  "type": "Feature",
  "properties": {
    "iso:country":"DE",
    "sg:address":"Hauptstr. 43",
    "sg:city":"Ergoldsbach",
    "sg:phone":"+49 8771/911181",
    "sg:postcode":"84061",
    "sg:province":"Bayern",
    "wof:name":"J. K\u00f6nigbauer",
    "wof:placetype":"venue"
},
  "geometry": {"coordinates":[12.2034749985,48.6931991577],"type":"Point"}
}