{
  "type": "Feature",
  "properties": {
    "iso:country":"DE",
    "sg:address":"H\u00fclskamp 3",
    "sg:city":"Hamm",
    "sg:phone":"+49 2381/32173",
    "sg:postcode":"59073",
    "sg:province":"Nordrhein-Westfalen",
    "wof:name":"W. Moritz",
    "wof:placetype":"venue"
},
  "geometry": {"coordinates":[7.829504,51.702747],"type":"Point"}
}