{
  "type": "Feature",
  "properties": {
    "iso:country":"DE",
    "sg:address":"Industriestr. 22",
    "sg:city":"Leipzig",
    "sg:phone":"+49 341/4798776",
    "sg:postcode":"04229",
    "sg:province":"Sachsen",
    "wof:name":"Bettina Walnsch",
    "wof:placetype":"venue"
},
  "geometry": {"coordinates":[12.3422374725,51.3255271912],"type":"Point"}
}