{
  "type": "Feature",
  "properties": {
    "iso:country":"DE",
    "sg:address":"Wallstr. 18",
    "sg:city":"Winnenden",
    "sg:phone":"+49 7195/3211",
    "sg:postcode":"71364",
    "sg:province":"Baden-W\u00fcrttemberg",
    "wof:name":"Alwin Richter",
    "wof:placetype":"venue"
},
  "geometry": {"coordinates":[9.3993148804,48.8748626709],"type":"Point"}
}