{
  "type": "Feature",
  "properties": {
    "iso:country":"DE",
    "sg:address":"Bleichstr. 1",
    "sg:city":"Kronberg",
    "sg:phone":"+49 6173/805246",
    "sg:postcode":"61476",
    "sg:province":"Hessen",
    "wof:name":"Paul G. Sch\u00f6nwiese",
    "wof:placetype":"venue"
},
  "geometry": {"coordinates":[8.511311,50.179668],"type":"Point"}
}