{
  "type": "Feature",
  "properties": {
    "iso:country":"DE",
    "sg:address":"In den Wickeng\u00e4rten 10",
    "sg:city":"Mainaschaff",
    "sg:phone":"+49 6021/770777",
    "sg:postcode":"63814",
    "sg:province":"Bayern",
    "wof:name":"Kanaltechnik Kunz Gmbh",
    "wof:placetype":"venue"
},
  "geometry": {"coordinates":[9.0887155533,49.9762649536],"type":"Point"}
}