{
  "type": "Feature",
  "properties": {
    "iso:country":"DE",
    "sg:address":"Gelbinger Gasse 1",
    "sg:city":"Schw\u00e4bisch Hall",
    "sg:phone":"+49 791/6226",
    "sg:postcode":"74523",
    "sg:province":"Baden-W\u00fcrttemberg",
    "wof:name":"Otto Vatter Gmbh",
    "wof:placetype":"venue"
},
  "geometry": {"coordinates":[9.7362737656,49.1141433716],"type":"Point"}
}