{
  "type": "Feature",
  "properties": {
    "iso:country":"DE",
    "sg:address":"F\u00e4rberstr. 48",
    "sg:city":"N\u00fcrnberg",
    "sg:phone":"+49 911/225260",
    "sg:postcode":"90402",
    "sg:province":"Bayern",
    "wof:name":"L. Geyer",
    "wof:placetype":"venue"
},
  "geometry": {"coordinates":[11.071937561,49.4480361938],"type":"Point"}
}