{
  "type": "Feature",
  "properties": {
    "iso:country":"DE",
    "sg:address":"Kirchstr. 28",
    "sg:city":"Fell",
    "sg:phone":"+49 6502/6985",
    "sg:postcode":"54341",
    "sg:province":"Rheinland-Pfalz",
    "wof:name":"Gudrun Mergens",
    "wof:placetype":"venue"
},
  "geometry": {"coordinates":[6.778397,49.777794],"type":"Point"}
}