{
  "type": "Feature",
  "properties": {
    "iso:country":"DE",
    "sg:address":"St.-Georg-Str. 1",
    "sg:city":"Schwalbach",
    "sg:phone":"+49 6831/59728",
    "sg:postcode":"66773",
    "sg:province":"Saarland",
    "wof:name":"P. Noh",
    "wof:placetype":"venue"
},
  "geometry": {"coordinates":[6.8142399788,49.313949585],"type":"Point"}
}