{
  "type": "Feature",
  "properties": {
    "iso:country":"DE",
    "sg:address":"K\u00f6nigsbenden 18",
    "sg:city":"Eschweiler",
    "sg:phone":"+49 2403/22124",
    "sg:postcode":"52249",
    "sg:province":"Nordrhein-Westfalen",
    "wof:name":"Waltermann",
    "wof:placetype":"venue"
},
  "geometry": {"coordinates":[6.2878289223,50.8170623779],"type":"Point"}
}