{
  "type": "Feature",
  "properties": {
    "iso:country":"DE",
    "sg:address":"Im Werth 53",
    "sg:city":"Dorsten",
    "sg:phone":"+49 2362/200626",
    "sg:postcode":"46282",
    "sg:province":"Nordrhein-Westfalen",
    "wof:name":"Diakoniestation",
    "wof:placetype":"venue"
},
  "geometry": {"coordinates":[6.96211,51.665649],"type":"Point"}
}