{
  "type": "Feature",
  "properties": {
    "iso:country":"DE",
    "sg:address":"Bahnhofstr. 11",
    "sg:city":"Barntrup",
    "sg:phone":"+49 5263/2939",
    "sg:postcode":"32683",
    "sg:province":"Nordrhein-Westfalen",
    "wof:name":"Benze Gmbh",
    "wof:placetype":"venue"
},
  "geometry": {"coordinates":[9.1171483994,51.9918327332],"type":"Point"}
}