{
  "type": "Feature",
  "properties": {
    "iso:country":"DE",
    "sg:address":"Subbelrather Str. 299",
    "sg:city":"K\u00f6ln",
    "sg:phone":"+49 221/5505036",
    "sg:postcode":"50825",
    "sg:province":"Nordrhein-Westfalen",
    "wof:name":"Carola Rapputan",
    "wof:placetype":"venue"
},
  "geometry": {"coordinates":[6.9154601097,50.9554824829],"type":"Point"}
}