{
  "type": "Feature",
  "properties": {
    "iso:country":"DE",
    "sg:address":"Ilgenstr. 18",
    "sg:city":"Neuenb\u00fcrg",
    "sg:phone":"+49 7082/40364",
    "sg:postcode":"75305",
    "sg:province":"Baden-W\u00fcrttemberg",
    "wof:name":"Bruno Degen",
    "wof:placetype":"venue"
},
  "geometry": {"coordinates":[8.5981836319,48.8438911438],"type":"Point"}
}