{
  "type": "Feature",
  "properties": {
    "iso:country":"DE",
    "sg:address":"Rudi-W\u00fcnzer-Str 9",
    "sg:city":"Wald-Michelbach",
    "sg:phone":"+49 6207/94240",
    "sg:postcode":"69483",
    "sg:province":"Hessen",
    "wof:name":"Ocs-organisations-, Computer- Und Software-unternehmensberatung Gmbh",
    "wof:placetype":"venue"
},
  "geometry": {"coordinates":[8.820088,49.574806],"type":"Point"}
}