{
  "type": "Feature",
  "properties": {
    "iso:country":"DE",
    "sg:address":"Dolmanstr. 84",
    "sg:city":"Bergisch Gladbach",
    "sg:phone":"+49 2204/66618",
    "sg:postcode":"51427",
    "sg:province":"Nordrhein-Westfalen",
    "wof:name":"H. Sch\u00e4fer",
    "wof:placetype":"venue"
},
  "geometry": {"coordinates":[7.1142940521,50.9635734558],"type":"Point"}
}