{
  "type": "Feature",
  "properties": {
    "iso:country":"DE",
    "sg:address":"Hauptstr. 52",
    "sg:city":"Lohmar",
    "sg:phone":"+49 2246/4362",
    "sg:postcode":"53797",
    "sg:province":"Nordrhein-Westfalen",
    "wof:name":"Wimmeroth-dittscheid",
    "wof:placetype":"venue"
},
  "geometry": {"coordinates":[7.2102570534,50.8404121399],"type":"Point"}
}