{
  "type": "Feature",
  "properties": {
    "iso:country":"DE",
    "sg:address":"Schillerstr. 11",
    "sg:city":"Rostock",
    "sg:phone":"+49 381/519820",
    "sg:postcode":"18119",
    "sg:province":"Mecklenburg-Vorpommern",
    "wof:name":"Altenpflegeheim Warnem\u00fcnde",
    "wof:placetype":"venue"
},
  "geometry": {"coordinates":[12.07788,54.17728],"type":"Point"}
}