{
  "type": "Feature",
  "properties": {
    "iso:country":"DE",
    "sg:address":"Westliche Karl-Friedrich-Str.",
    "sg:city":"Pforzheim",
    "sg:phone":"+49 7231/94090",
    "sg:postcode":"75172",
    "sg:province":"Baden-W\u00fcrttemberg",
    "wof:name":"Textilhaus Klittich Gmbh",
    "wof:placetype":"venue"
},
  "geometry": {"coordinates":[8.6860704422,48.8922996521],"type":"Point"}
}