{
  "type": "Feature",
  "properties": {
    "iso:country":"DE",
    "sg:address":"Nr. 21",
    "sg:city":"Trebnitz",
    "sg:postcode":"06420",
    "sg:province":"Sachsen-Anhalt",
    "wof:name":"Martun Elze",
    "wof:placetype":"venue"
},
  "geometry": {"coordinates":[11.78269,51.671841],"type":"Point"}
}