{
  "type": "Feature",
  "properties": {
    "iso:country":"DE",
    "sg:address":"Rotenburger Str. 12",
    "sg:city":"Bebra",
    "sg:postcode":"36179",
    "sg:province":"Hessen",
    "wof:name":"Stadtb\u00fccherei Altes Rathaus",
    "wof:placetype":"venue"
},
  "geometry": {"coordinates":[9.792589,50.973274],"type":"Point"}
}