{
  "type": "Feature",
  "properties": {
    "iso:country":"DE",
    "sg:address":"Frankfurter Str. 100",
    "sg:city":"Dreieich",
    "sg:phone":"+49 6103/96130",
    "sg:postcode":"63303",
    "sg:province":"Hessen",
    "wof:name":"Franz Hofmann",
    "wof:placetype":"venue"
},
  "geometry": {"coordinates":[8.6951799393,50.0254135132],"type":"Point"}
}