{
  "type": "Feature",
  "properties": {
    "iso:country":"DE",
    "sg:address":"Werner-Von-Siemens-Str. 10-14",
    "sg:city":"W\u00fcrzburg",
    "sg:phone":"+49 931/250360",
    "sg:postcode":"97076",
    "sg:province":"Bayern",
    "wof:name":"Ingenieur Kurt Herold Gmbh & Co. Kg",
    "wof:placetype":"venue"
},
  "geometry": {"coordinates":[9.977308,49.797634],"type":"Point"}
}