{
  "type": "Feature",
  "properties": {
    "iso:country":"DE",
    "sg:address":"Br\u00fcderstr. 22",
    "sg:city":"Soest",
    "sg:phone":"+49 2921/12600",
    "sg:postcode":"59494",
    "sg:province":"Nordrhein-Westfalen",
    "wof:name":"Westfalen-apotheke",
    "wof:placetype":"venue"
},
  "geometry": {"coordinates":[8.105981,51.573956],"type":"Point"}
}