{
  "type": "Feature",
  "properties": {
    "iso:country":"DE",
    "sg:address":"Arabellastr. 6",
    "sg:city":"M\u00fcnchen",
    "sg:phone":"+49 89/92640",
    "sg:postcode":"81925",
    "sg:province":"Bayern",
    "wof:name":"Arabellasheraton Grant Hotel",
    "wof:placetype":"venue"
},
  "geometry": {"coordinates":[11.617635,48.152309],"type":"Point"}
}