{
  "type": "Feature",
  "properties": {
    "iso:country":"DE",
    "sg:address":"Haderslebener Str. 22",
    "sg:city":"Mannheim",
    "sg:phone":"+49 621/783771",
    "sg:postcode":"68307",
    "sg:province":"Baden-W\u00fcrttemberg",
    "wof:name":"Imbi\u00df Da Nico",
    "wof:placetype":"venue"
},
  "geometry": {"coordinates":[8.4780836105,49.5422706604],"type":"Point"}
}