{
  "type": "Feature",
  "properties": {
    "iso:country":"DE",
    "sg:address":"Heusteigstra\u00dfe 66",
    "sg:city":"Stuttgart",
    "sg:phone":"+49 711",
    "sg:postcode":"70180",
    "sg:province":"Baden-W\u00fcrttemberg",
    "wof:name":"Grafik Druck Gmbh",
    "wof:placetype":"venue"
},
  "geometry": {"coordinates":[9.174867,48.767971],"type":"Point"}
}