{
  "type": "Feature",
  "properties": {
    "iso:country":"DE",
    "sg:address":"Steindamm 7",
    "sg:city":"Hamburg",
    "sg:postcode":"20099",
    "sg:province":"Hamburg",
    "wof:name":"Kommanditgesellschaft Eos Holding Gmbh & Co.",
    "wof:placetype":"venue"
},
  "geometry": {"coordinates":[10.01053,53.553001],"type":"Point"}
}