{
  "type": "Feature",
  "properties": {
    "iso:country":"DE",
    "sg:address":"Alte Poststr. 90",
    "sg:city":"Porta Westfalica",
    "sg:phone":"+49 571/51553",
    "sg:postcode":"32457",
    "sg:province":"Nordrhein-Westfalen",
    "wof:name":"Friedrich Struckmeyer Gmbh & Co. Kg",
    "wof:placetype":"venue"
},
  "geometry": {"coordinates":[8.913217,52.257267],"type":"Point"}
}