{
  "type": "Feature",
  "properties": {
    "iso:country":"DE",
    "sg:address":"Lindenstr. 1",
    "sg:city":"Schondorf",
    "sg:phone":"+49 8192/999456",
    "sg:postcode":"86938",
    "sg:province":"Bayern",
    "wof:name":"Netpeer E. K.",
    "wof:placetype":"venue"
},
  "geometry": {"coordinates":[11.08348,48.050556],"type":"Point"}
}