{
  "type": "Feature",
  "properties": {
    "iso:country":"DE",
    "sg:address":"Augrabenstr. 7",
    "sg:city":"Gro\u00df-Rohrheim",
    "sg:phone":"+49 6245/3031",
    "sg:postcode":"68649",
    "sg:province":"Hessen",
    "wof:name":"Salzmann Natursteine E. K.",
    "wof:placetype":"venue"
},
  "geometry": {"coordinates":[8.468919754,49.7179107666],"type":"Point"}
}