{
  "type": "Feature",
  "properties": {
    "iso:country":"DE",
    "sg:address":"Warendorfer Str. 20",
    "sg:city":"Beelen",
    "sg:phone":"+49 2586/313",
    "sg:postcode":"48361",
    "sg:province":"Nordrhein-Westfalen",
    "wof:name":"St. Johannis-apotheke Inh. Bernhard Hauke",
    "wof:placetype":"venue"
},
  "geometry": {"coordinates":[8.118695,51.930058],"type":"Point"}
}