{
  "type": "Feature",
  "properties": {
    "iso:country":"DE",
    "sg:address":"Eppinkstr. 81",
    "sg:city":"Dinslaken",
    "sg:postcode":"46535",
    "sg:province":"Nordrhein-Westfalen",
    "wof:name":"Scanbox Gmbh",
    "wof:placetype":"venue"
},
  "geometry": {"coordinates":[6.710171,51.567623],"type":"Point"}
}