{
  "type": "Feature",
  "properties": {
    "iso:country":"DE",
    "sg:address":"Blumenstr. 19",
    "sg:city":"Neuler",
    "sg:phone":"+49 7961/4060",
    "sg:postcode":"73491",
    "sg:province":"Baden-W\u00fcrttemberg",
    "wof:name":"Karl-heinz Stegmaier",
    "wof:placetype":"venue"
},
  "geometry": {"coordinates":[10.074947,48.928772],"type":"Point"}
}