{
  "type": "Feature",
  "properties": {
    "iso:country":"DE",
    "sg:address":"Reichsapfelstr. 40",
    "sg:city":"Wiesbaden",
    "sg:phone":"+49 611/29380",
    "sg:postcode":"65201",
    "sg:province":"Hessen",
    "wof:name":"Schmidt Gmbh",
    "wof:placetype":"venue"
},
  "geometry": {"coordinates":[8.194548,50.045334],"type":"Point"}
}