{
  "type": "Feature",
  "properties": {
    "iso:country":"DE",
    "sg:address":"Hartmannstr. 72",
    "sg:city":"Maikammer",
    "sg:phone":"+49 6321/5475",
    "sg:postcode":"67487",
    "sg:province":"Rheinland-Pfalz",
    "wof:name":"Hugo M\u00fcller Weinanbau",
    "wof:placetype":"venue"
},
  "geometry": {"coordinates":[8.1244592667,49.308139801],"type":"Point"}
}