{
  "type": "Feature",
  "properties": {
    "iso:country":"DE",
    "sg:address":"Kurt-Huber-Ring 11",
    "sg:city":"F\u00fcrstenfeldbruck",
    "sg:phone":"+49 8141/23866",
    "sg:postcode":"82256",
    "sg:province":"Bayern",
    "wof:name":"Restaurant China-town",
    "wof:placetype":"venue"
},
  "geometry": {"coordinates":[11.2252454758,48.1609687805],"type":"Point"}
}