{
  "type": "Feature",
  "properties": {
    "iso:country":"DE",
    "sg:address":"Stauferstr. 1",
    "sg:city":"Mahlberg",
    "sg:postcode":"77972",
    "sg:province":"Baden-W\u00fcrttemberg",
    "wof:name":"Aldi Grundst\u00fccks-gmbh & Co. Kg",
    "wof:placetype":"venue"
},
  "geometry": {"coordinates":[7.8134999275,48.2870903015],"type":"Point"}
}