{
  "type": "Feature",
  "properties": {
    "iso:country":"DE",
    "sg:address":"Neuer Graben 8",
    "sg:city":"Melle",
    "sg:phone":"+49 5422/5595",
    "sg:postcode":"49324",
    "sg:province":"Niedersachsen",
    "wof:name":"Honerkamp Kg B\u00e4ckerei",
    "wof:placetype":"venue"
},
  "geometry": {"coordinates":[8.339398,52.202442],"type":"Point"}
}