{
  "type": "Feature",
  "properties": {
    "iso:country":"DE",
    "sg:address":"Petersh\u00fctter Allee 15",
    "sg:city":"Osterode",
    "sg:phone":"+49 5522/74242",
    "sg:postcode":"37520",
    "sg:province":"Niedersachsen",
    "wof:name":"Pizzeria San Marco",
    "wof:placetype":"venue"
},
  "geometry": {"coordinates":[10.2355136871,51.7337913513],"type":"Point"}
}