{
  "type": "Feature",
  "properties": {
    "iso:country":"DE",
    "sg:address":"Auf den Steinen 3",
    "sg:city":"Bad M\u00fcnstereifel",
    "sg:phone":"+49 2253/2058",
    "sg:postcode":"53902",
    "sg:province":"Nordrhein-Westfalen",
    "wof:name":"Extra Bau Und Hobby Handels Gmbh",
    "wof:placetype":"venue"
},
  "geometry": {"coordinates":[6.8318929672,50.4747390747],"type":"Point"}
}