{
  "type": "Feature",
  "properties": {
    "iso:country":"DE",
    "sg:address":"Admiral-Hipper-Str. 17",
    "sg:city":"Weilheim",
    "sg:phone":"+49 881/2264",
    "sg:postcode":"82362",
    "sg:province":"Bayern",
    "wof:name":"A. Luitz",
    "wof:placetype":"venue"
},
  "geometry": {"coordinates":[11.1440372467,47.8391532898],"type":"Point"}
}