{
  "type": "Feature",
  "properties": {
    "iso:country":"DE",
    "sg:address":"Kevelaerer Str. 28",
    "sg:city":"Weeze",
    "sg:phone":"+49 2837/337",
    "sg:postcode":"47652",
    "sg:province":"Nordrhein-Westfalen",
    "wof:name":"Sonnen-apotheke",
    "wof:placetype":"venue"
},
  "geometry": {"coordinates":[6.2004342079,51.6254768372],"type":"Point"}
}