{
  "type": "Feature",
  "properties": {
    "iso:country":"DE",
    "sg:address":"Fergersbergstr. 15",
    "sg:city":"Ritterhude",
    "sg:phone":"+49 4292/819167",
    "sg:postcode":"27721",
    "sg:province":"Niedersachsen",
    "wof:name":"Hans-werner Murken",
    "wof:placetype":"venue"
},
  "geometry": {"coordinates":[8.758225,53.185646],"type":"Point"}
}