{
  "type": "Feature",
  "properties": {
    "iso:country":"DE",
    "sg:address":"Hauptstr. 15",
    "sg:city":"Sankt Margarethen",
    "sg:phone":"+49 4858/881",
    "sg:postcode":"25572",
    "sg:province":"Schleswig-Holstein",
    "wof:name":"Kl\u00f6n-eck",
    "wof:placetype":"venue"
},
  "geometry": {"coordinates":[9.2539796829,53.8913269043],"type":"Point"}
}