{
  "type": "Feature",
  "properties": {
    "iso:country":"DE",
    "sg:address":"Jahnstr. 21",
    "sg:city":"A\u00dflar",
    "sg:phone":"+49 6443/3512",
    "sg:postcode":"35614",
    "sg:province":"Hessen",
    "wof:name":"Ernst Schneider",
    "wof:placetype":"venue"
},
  "geometry": {"coordinates":[8.417124,50.590244],"type":"Point"}
}