{
  "type": "Feature",
  "properties": {
    "iso:country":"DE",
    "sg:address":"Rathsberger Str. 2",
    "sg:city":"Erlangen",
    "sg:phone":"+49 9131/25025",
    "sg:postcode":"91054",
    "sg:province":"Bayern",
    "wof:name":"Restaurant B\u00e4rengarten",
    "wof:placetype":"venue"
},
  "geometry": {"coordinates":[11.0097293854,49.606502533],"type":"Point"}
}