{
  "type": "Feature",
  "properties": {
    "iso:country":"DE",
    "sg:address":"Bronnerstr. 7",
    "sg:city":"Dortmund",
    "sg:phone":"+49 231/54110",
    "sg:postcode":"44141",
    "sg:province":"Nordrhein-Westfalen",
    "wof:name":"Gwg Gesellschaft F\u00fcr Wohnungs- Und Grundst\u00fccksservice Mbh",
    "wof:placetype":"venue"
},
  "geometry": {"coordinates":[7.4922218323,51.5042037964],"type":"Point"}
}