{
  "type": "Feature",
  "properties": {
    "iso:country":"DE",
    "sg:address":"Am Neugraben 5",
    "sg:city":"Colmberg",
    "sg:postcode":"91598",
    "sg:province":"Bayern",
    "wof:name":"Polynova Gmbh",
    "wof:placetype":"venue"
},
  "geometry": {"coordinates":[10.404695,49.355915],"type":"Point"}
}