{
  "type": "Feature",
  "properties": {
    "iso:country":"DE",
    "sg:address":"Salinenstr. 4",
    "sg:city":"Bad Kreuznach",
    "sg:phone":"+49 671/28877",
    "sg:postcode":"55543",
    "sg:province":"Rheinland-Pfalz",
    "wof:name":"Salinen-apotheke E. K.",
    "wof:placetype":"venue"
},
  "geometry": {"coordinates":[7.863032,49.842892],"type":"Point"}
}