{
  "type": "Feature",
  "properties": {
    "iso:country":"DE",
    "sg:address":"Bahnhofstr. 14",
    "sg:city":"Rieschweiler-M\u00fchlbach",
    "sg:phone":"+49 6336/993030",
    "sg:postcode":"66509",
    "sg:province":"Rheinland-Pfalz",
    "wof:name":"Westrich-apotheke",
    "wof:placetype":"venue"
},
  "geometry": {"coordinates":[7.50585,49.246449],"type":"Point"}
}