{
  "type": "Feature",
  "properties": {
    "iso:country":"DE",
    "sg:address":"Friedrich-List-Str. 14",
    "sg:city":"Rottenburg",
    "sg:phone":"+49 7472/3739",
    "sg:postcode":"72108",
    "sg:province":"Baden-W\u00fcrttemberg",
    "wof:name":"Erich Thoma",
    "wof:placetype":"venue"
},
  "geometry": {"coordinates":[8.937236,48.504559],"type":"Point"}
}