{
  "type": "Feature",
  "properties": {
    "iso:country":"DE",
    "sg:address":"Wanner Str. 47",
    "sg:city":"Gelsenkirchen",
    "sg:phone":"+49 209/207245",
    "sg:postcode":"45888",
    "sg:province":"Nordrhein-Westfalen",
    "wof:name":"Voigt & Stockebrandt",
    "wof:placetype":"venue"
},
  "geometry": {"coordinates":[7.1066608429,51.5137481689],"type":"Point"}
}