{
  "type": "Feature",
  "properties": {
    "iso:country":"DE",
    "sg:address":"Bahnhofstr. 4",
    "sg:city":"Immenstadt",
    "sg:phone":"+49 8323/585",
    "sg:postcode":"87509",
    "sg:province":"Bayern",
    "wof:name":"Touristik Morent Gmbh",
    "wof:placetype":"venue"
},
  "geometry": {"coordinates":[10.2176198959,47.560092926],"type":"Point"}
}