{
  "type": "Feature",
  "properties": {
    "iso:country":"DE",
    "sg:address":"Fritz-Kotz-Str. 1",
    "sg:city":"Wiehl",
    "sg:phone":"+49 2261/73727",
    "sg:postcode":"51674",
    "sg:province":"Nordrhein-Westfalen",
    "wof:name":"Marckophon Elektrotechnik F\u00fcr M\u00f6bel Handels- Und",
    "wof:placetype":"venue"
},
  "geometry": {"coordinates":[7.530171,50.969994],"type":"Point"}
}