{
  "type": "Feature",
  "properties": {
    "iso:country":"DE",
    "sg:address":"Lennestr. 82",
    "sg:city":"Altena",
    "sg:phone":"+49 2352/22226",
    "sg:postcode":"58762",
    "sg:province":"Nordrhein-Westfalen",
    "wof:name":"Hermann Ossenberg-engels Immobilienmakler Rdm",
    "wof:placetype":"venue"
},
  "geometry": {"coordinates":[7.6734352112,51.2973060608],"type":"Point"}
}