{
  "type": "Feature",
  "properties": {
    "iso:country":"DE",
    "sg:address":"Altenaer Str. 13",
    "sg:city":"Altena",
    "sg:phone":"+49 2352/70010",
    "sg:postcode":"58762",
    "sg:province":"Nordrhein-Westfalen",
    "wof:name":"Ernst Diekgraefe Gmbh & Co.",
    "wof:placetype":"venue"
},
  "geometry": {"coordinates":[7.7486400604,51.2979469299],"type":"Point"}
}