{
  "type": "Feature",
  "properties": {
    "iso:country":"DE",
    "sg:address":"K\u00f6nigsberger Str.8",
    "sg:city":"Beckum",
    "sg:phone":"+49 162 6314254",
    "sg:postcode":"59269",
    "sg:province":"Nordrhein-Westfalen",
    "wof:name":"Talking Hands- Eric Vandenberg",
    "wof:placetype":"venue"
},
  "geometry": {"coordinates":[8.012027,51.779999],"type":"Point"}
}