{
  "type": "Feature",
  "properties": {
    "iso:country":"DE",
    "sg:address":"Schlo\u00dfberg 12",
    "sg:city":"Gotha",
    "sg:phone":"+49 3621/72400",
    "sg:postcode":"99867",
    "sg:province":"Th\u00fcringen",
    "wof:name":"Schultheis Gottlob Und Koll. Rechtsanw\u00e4lte",
    "wof:placetype":"venue"
},
  "geometry": {"coordinates":[10.702132225,50.9472732544],"type":"Point"}
}