{
  "type": "Feature",
  "properties": {
    "iso:country":"DE",
    "sg:address":"Am Kornfeld 11",
    "sg:city":"Ebstorf",
    "sg:phone":"+49 5822/3062",
    "sg:postcode":"29574",
    "sg:province":"Niedersachsen",
    "wof:name":"Debeka Versicherung Gerald Schneider",
    "wof:placetype":"venue"
},
  "geometry": {"coordinates":[10.4091005325,53.0209236145],"type":"Point"}
}