{
  "type": "Feature",
  "properties": {
    "iso:country":"DE",
    "sg:address":"Elbchaussee 530",
    "sg:city":"Hamburg",
    "sg:phone":"+49 40/860921",
    "sg:postcode":"22587",
    "sg:province":"Hamburg",
    "wof:name":"Otto Meinert",
    "wof:placetype":"venue"
},
  "geometry": {"coordinates":[9.8202114105,53.5613021851],"type":"Point"}
}