{
  "type": "Feature",
  "properties": {
    "iso:country":"DE",
    "sg:address":"Bahnhofstr. 35",
    "sg:city":"Ludwigsburg",
    "sg:phone":"+49 7141/93080",
    "sg:postcode":"71638",
    "sg:province":"Baden-W\u00fcrttemberg",
    "wof:name":"W\u00fcrttemberische Versicherung",
    "wof:placetype":"venue"
},
  "geometry": {"coordinates":[9.1875286102,48.8902854919],"type":"Point"}
}