{
  "type": "Feature",
  "properties": {
    "iso:country":"DE",
    "sg:address":"Bahnhofstr. 7",
    "sg:city":"Benediktbeuern",
    "sg:phone":"+49 8857/421",
    "sg:postcode":"83671",
    "sg:province":"Bayern",
    "wof:name":"Johannes Wurth Drogerie",
    "wof:placetype":"venue"
},
  "geometry": {"coordinates":[11.411088,47.707867],"type":"Point"}
}