{
  "type": "Feature",
  "properties": {
    "iso:country":"DE",
    "sg:address":"S\u00f6mmeringstr. 2",
    "sg:city":"K\u00f6ln",
    "sg:phone":"+49 221/523592",
    "sg:postcode":"50823",
    "sg:province":"Nordrhein-Westfalen",
    "wof:name":"Ferdinand Hoffmann Heilpraktiker",
    "wof:placetype":"venue"
},
  "geometry": {"coordinates":[6.9174399376,50.9494667053],"type":"Point"}
}