{
  "type": "Feature",
  "properties": {
    "iso:country":"DE",
    "sg:address":"Christophstr. 12",
    "sg:city":"M\u00fcnchen",
    "sg:phone":"+49 89/297310",
    "sg:postcode":"80538",
    "sg:province":"Bayern",
    "wof:name":"C. Achtel",
    "wof:placetype":"venue"
},
  "geometry": {"coordinates":[11.585555,48.141376],"type":"Point"}
}