{
  "type": "Feature",
  "properties": {
    "iso:country":"DE",
    "sg:address":"Hauptstr. 35",
    "sg:city":"Burtenbach",
    "sg:phone":"+49 8285/235",
    "sg:postcode":"89349",
    "sg:province":"Bayern",
    "wof:name":"Johann Kraus",
    "wof:placetype":"venue"
},
  "geometry": {"coordinates":[10.448392,48.33884],"type":"Point"}
}