{
  "type": "Feature",
  "properties": {
    "iso:country":"DE",
    "sg:address":"Loretostr 32",
    "sg:city":"Tettnang",
    "sg:phone":"+49 7542/7431",
    "sg:postcode":"88069",
    "sg:province":"Baden-W\u00fcrttemberg",
    "wof:name":"Auroha Gmbh",
    "wof:placetype":"venue"
},
  "geometry": {"coordinates":[9.589448,47.666386],"type":"Point"}
}