{
  "type": "Feature",
  "properties": {
    "iso:country":"DE",
    "sg:address":"Waldhofstr. 25",
    "sg:city":"Ellerbek",
    "sg:phone":"+49 4101/32904",
    "sg:postcode":"25474",
    "sg:province":"Schleswig-Holstein",
    "wof:name":"Irmgard G\u00f6bel",
    "wof:placetype":"venue"
},
  "geometry": {"coordinates":[9.8900184631,53.6446838379],"type":"Point"}
}