{
  "type": "Feature",
  "properties": {
    "iso:country":"DE",
    "sg:address":"Brachtstr. 1",
    "sg:city":"D\u00fcsseldorf",
    "sg:phone":"+49 211/332433",
    "sg:postcode":"40223",
    "sg:province":"Nordrhein-Westfalen",
    "wof:name":"City Squash Gmbh",
    "wof:placetype":"venue"
},
  "geometry": {"coordinates":[6.7786130905,51.2078971863],"type":"Point"}
}