{
  "type": "Feature",
  "properties": {
    "iso:country":"DE",
    "sg:address":"Dr. Friedrich-Uhde-Str. 14 - 16::",
    "sg:city":"Einbeck",
    "sg:phone":"+49 4955/619440",
    "sg:postcode":"37574",
    "sg:province":"Niedersachsen",
    "wof:name":"Volksbank Einbeck Eg",
    "wof:placetype":"venue"
},
  "geometry": {"coordinates":[9.872434,51.818268],"type":"Point"}
}