{
  "type": "Feature",
  "properties": {
    "iso:country":"DE",
    "sg:address":"Landrat Trimbornstr.38",
    "sg:city":"Leichlingen",
    "sg:phone":"+49 2175/890671",
    "sg:postcode":"42799",
    "sg:province":"Nordrhein-Westfalen",
    "wof:name":"Holzblockhaus Diffusionsoffen Patentiert",
    "wof:placetype":"venue"
},
  "geometry": {"coordinates":[7.027469,51.109505],"type":"Point"}
}