{
  "type": "Feature",
  "properties": {
    "iso:country":"DE",
    "sg:address":"Dessauer Str. 288 A",
    "sg:city":"Lutherstadt Wittenberg",
    "sg:postcode":"06886",
    "sg:province":"Sachsen-Anhalt",
    "wof:name":"B\u00fcro-fachmarkt",
    "wof:placetype":"venue"
},
  "geometry": {"coordinates":[12.632527,51.866673],"type":"Point"}
}