{
  "type": "Feature",
  "properties": {
    "iso:country":"DE",
    "sg:address":"Alt-Stralau 70",
    "sg:city":"Berlin",
    "sg:phone":"+49 30/2918584",
    "sg:postcode":"10245",
    "sg:province":"Berlin",
    "wof:name":"Simona G\u00fcnther",
    "wof:placetype":"venue"
},
  "geometry": {"coordinates":[13.4650707245,52.4974555969],"type":"Point"}
}