{
  "type": "Feature",
  "properties": {
    "iso:country":"DE",
    "sg:address":"Eilinger Kamp 15",
    "sg:city":"Menden",
    "sg:phone":"+49 2379/691",
    "sg:postcode":"58708",
    "sg:province":"Nordrhein-Westfalen",
    "wof:name":"Gebr. Meisterjahn Gmbh",
    "wof:placetype":"venue"
},
  "geometry": {"coordinates":[7.8624849319,51.4195022583],"type":"Point"}
}