{
  "type": "Feature",
  "properties": {
    "iso:country":"DE",
    "sg:address":"Steinbeisstr 6",
    "sg:city":"Leonberg",
    "sg:phone":"+49 7152/92590",
    "sg:postcode":"71229",
    "sg:province":"Baden-W\u00fcrttemberg",
    "wof:name":"Leomedia Gmbh",
    "wof:placetype":"venue"
},
  "geometry": {"coordinates":[9.0039806366,48.7984924316],"type":"Point"}
}