{
  "type": "Feature",
  "properties": {
    "iso:country":"DE",
    "sg:address":"Ludwigstr. 8",
    "sg:city":"Regensburg",
    "sg:phone":"+49 941/595470",
    "sg:postcode":"93047",
    "sg:province":"Bayern",
    "wof:name":"Arnulf-apotheke",
    "wof:placetype":"venue"
},
  "geometry": {"coordinates":[12.090187,49.019901],"type":"Point"}
}