{
  "type": "Feature",
  "properties": {
    "iso:country":"DE",
    "sg:address":"Altendorfer Str. 299 a",
    "sg:city":"Essen",
    "sg:phone":"+49 201/628429",
    "sg:postcode":"45143",
    "sg:province":"Nordrhein-Westfalen",
    "wof:name":"R\u00f6ntgen-apotheke",
    "wof:placetype":"venue"
},
  "geometry": {"coordinates":[6.979593,51.460613],"type":"Point"}
}