{
  "type": "Feature",
  "properties": {
    "iso:country":"DE",
    "sg:address":"Hardtweg 8",
    "sg:city":"Limbach",
    "sg:phone":"+49 2662/1301",
    "sg:postcode":"57629",
    "sg:province":"Rheinland-Pfalz",
    "wof:name":"Pension Reifenrath",
    "wof:placetype":"venue"
},
  "geometry": {"coordinates":[7.8025269508,50.7036895752],"type":"Point"}
}