{
  "type": "Feature",
  "properties": {
    "iso:country":"DE",
    "sg:address":"Wilhelm-Hauff-Str. 1",
    "sg:city":"Berlin",
    "sg:phone":"+49 30/85076313",
    "sg:postcode":"12159",
    "sg:province":"Berlin",
    "wof:name":"Hans Kurtzweg",
    "wof:placetype":"venue"
},
  "geometry": {"coordinates":[13.3357181549,52.4691581726],"type":"Point"}
}