{
  "type": "Feature",
  "properties": {
    "iso:country":"DE",
    "sg:address":"Benzinoring 25",
    "sg:city":"Kaiserslautern",
    "sg:phone":"+49 631/3608386",
    "sg:postcode":"67657",
    "sg:province":"Rheinland-Pfalz",
    "wof:name":"Werner Schr\u00f6der Ingenieurb\u00fcro Und Bauausf\u00fchrungen",
    "wof:placetype":"venue"
},
  "geometry": {"coordinates":[7.7733049393,49.4495201111],"type":"Point"}
}