{
  "type": "Feature",
  "properties": {
    "iso:country":"DE",
    "sg:address":"Am Bahnhof Westend 3",
    "sg:city":"Berlin",
    "sg:phone":"+49 30/3267000",
    "sg:postcode":"14059",
    "sg:province":"Berlin",
    "wof:name":"Hans Santner Beteiligungsges. Mbh",
    "wof:placetype":"venue"
},
  "geometry": {"coordinates":[13.285585,52.518635],"type":"Point"}
}