{
  "type": "Feature",
  "properties": {
    "iso:country":"DE",
    "sg:address":"Am Brauhaus 8",
    "sg:city":"Wetzlar",
    "sg:phone":"+49 6441/1650",
    "sg:postcode":"35584",
    "sg:province":"Hessen",
    "wof:name":"G\u00fcnter Heinrich",
    "wof:placetype":"venue"
},
  "geometry": {"coordinates":[8.522639,50.582726],"type":"Point"}
}