{
  "type": "Feature",
  "properties": {
    "iso:country":"DE",
    "sg:address":"Josef-Baumann-Stra\u00dfe 21",
    "sg:city":"Bochum",
    "sg:phone":"+49 234/893660",
    "sg:postcode":"44805",
    "sg:province":"Nordrhein-Westfalen",
    "wof:name":"Rs Verbindungstechnik Gmbh Bochum",
    "wof:placetype":"venue"
},
  "geometry": {"coordinates":[7.276012,51.508945],"type":"Point"}
}