{
  "type": "Feature",
  "properties": {
    "iso:country":"DE",
    "sg:city":"Berlin",
    "sg:postcode":"12524",
    "sg:province":"Berlin",
    "wof:name":"Amr-shop, Manns Und Ru\u00df Gbr",
    "wof:placetype":"venue"
},
  "geometry": {"coordinates":[13.539691,52.420055],"type":"Point"}
}