{
  "type": "Feature",
  "properties": {
    "iso:country":"DE",
    "sg:address":"Kasberger Str. 26",
    "sg:city":"Gr\u00e4fenberg",
    "sg:phone":"+49 9192/278",
    "sg:postcode":"91322",
    "sg:province":"Bayern",
    "wof:name":"Hans Griess",
    "wof:placetype":"venue"
},
  "geometry": {"coordinates":[11.247217,49.648121],"type":"Point"}
}