{
  "type": "Feature",
  "properties": {
    "iso:country":"DE",
    "sg:address":"Am H\u00f6henblick 10",
    "sg:city":"Nidda",
    "sg:phone":"+49 6044/1898",
    "sg:postcode":"63667",
    "sg:province":"Hessen",
    "wof:name":"Andreas Partscht Video-service",
    "wof:placetype":"venue"
},
  "geometry": {"coordinates":[9.032685,50.4865],"type":"Point"}
}