{
  "type": "Feature",
  "properties": {
    "iso:country":"DE",
    "sg:address":"Bismarckstr. 3",
    "sg:city":"Bretten",
    "sg:phone":"+49 7252/2183",
    "sg:postcode":"75015",
    "sg:province":"Baden-W\u00fcrttemberg",
    "wof:name":"H. W. Maier",
    "wof:placetype":"venue"
},
  "geometry": {"coordinates":[8.7004642487,49.0382461548],"type":"Point"}
}