{
  "type": "Feature",
  "properties": {
    "iso:country":"DE",
    "sg:address":"Sperlingstr. 4",
    "sg:city":"Schweinfurt",
    "sg:phone":"+49 9721/44457",
    "sg:postcode":"97422",
    "sg:province":"Bayern",
    "wof:name":"Klaus Kunz",
    "wof:placetype":"venue"
},
  "geometry": {"coordinates":[10.2202119827,50.0627174377],"type":"Point"}
}