{
  "type": "Feature",
  "properties": {
    "iso:country":"DE",
    "sg:address":"M\u00fcnchner Str. 36",
    "sg:city":"Dachau",
    "sg:phone":"+49 8131/71070",
    "sg:postcode":"85221",
    "sg:province":"Bayern",
    "wof:name":"Foto-video Se\u00dfner Gmbh",
    "wof:placetype":"venue"
},
  "geometry": {"coordinates":[11.4393939972,48.2544250488],"type":"Point"}
}