{
  "type": "Feature",
  "properties": {
    "iso:country":"DE",
    "sg:address":"Im Heisenrath 14",
    "sg:city":"Frankfurt",
    "sg:phone":"+49 69/6661264",
    "sg:postcode":"60529",
    "sg:province":"Hessen",
    "wof:name":"Stadtverwaltung Ffm Sozialberatungsstelle",
    "wof:placetype":"venue"
},
  "geometry": {"coordinates":[8.6024847031,50.084236145],"type":"Point"}
}