{
  "type": "Feature",
  "properties": {
    "iso:country":"DE",
    "sg:address":"Illtalstr. 58",
    "sg:city":"Eppelborn",
    "sg:phone":"+49 6881/87790",
    "sg:postcode":"66571",
    "sg:province":"Saarland",
    "wof:name":"Katja Gro\u00df Praxis F\u00fcr Krankengymnastik",
    "wof:placetype":"venue"
},
  "geometry": {"coordinates":[6.941342,49.412376],"type":"Point"}
}