{
  "type": "Feature",
  "properties": {
    "iso:country":"DE",
    "sg:address":"Industriestr. 2",
    "sg:city":"Berne",
    "sg:phone":"+49 4933/626186",
    "sg:postcode":"27804",
    "sg:province":"Niedersachsen",
    "wof:name":"Favorit Bootsbau Gmbh",
    "wof:placetype":"venue"
},
  "geometry": {"coordinates":[13.802879,52.42318],"type":"Point"}
}