{
  "type": "Feature",
  "properties": {
    "iso:country":"DE",
    "sg:address":"Gochsheim",
    "sg:city":"Gochsheim",
    "sg:phone":"+49 7258/495",
    "sg:postcode":"76703",
    "sg:province":"Baden-W\u00fcrttemberg",
    "wof:name":"Sparkasse Bruchsal-bretten",
    "wof:placetype":"venue"
},
  "geometry": {"coordinates":[8.74551,49.104069],"type":"Point"}
}