{
  "type": "Feature",
  "properties": {
    "iso:country":"DE",
    "sg:address":"Hindenburgstr. 1",
    "sg:city":"Metzingen",
    "sg:phone":"+49 7123/1342",
    "sg:postcode":"72555",
    "sg:province":"Baden-W\u00fcrttemberg",
    "wof:name":"Stadt-apotheke",
    "wof:placetype":"venue"
},
  "geometry": {"coordinates":[9.283938,48.539169],"type":"Point"}
}