{
  "type": "Feature",
  "properties": {
    "iso:country":"DE",
    "sg:address":"In den Ellern 10",
    "sg:city":"Achim",
    "sg:postcode":"28832",
    "sg:province":"Niedersachsen",
    "wof:name":"Direktbau Gmbh",
    "wof:placetype":"venue"
},
  "geometry": {"coordinates":[8.9652872086,53.0342903137],"type":"Point"}
}