{
  "type": "Feature",
  "properties": {
    "iso:country":"DE",
    "sg:address":"Detzelner Str. 15",
    "sg:city":"Waldshut-Tiengen",
    "sg:phone":"+49 7741/4691",
    "sg:postcode":"79761",
    "sg:province":"Baden-W\u00fcrttemberg",
    "wof:name":"Ursula Hoffmann Schrotthandlung Gmbh",
    "wof:placetype":"venue"
},
  "geometry": {"coordinates":[8.2144546509,47.6237068176],"type":"Point"}
}