{
  "type": "Feature",
  "properties": {
    "iso:country":"DE",
    "sg:address":"beethovenplatz 6",
    "sg:city":"bonn",
    "sg:phone":"+49 228/9694460",
    "sg:postcode":"53115",
    "sg:province":"Nordrhein-Westfalen",
    "wof:name":"Willkommen Auf Der Homepage Der Smart | Job | Card",
    "wof:placetype":"venue"
},
  "geometry": {"coordinates":[7.09023,50.730724],"type":"Point"}
}