{
  "type": "Feature",
  "properties": {
    "iso:country":"DE",
    "sg:address":"Hauptstr. 30",
    "sg:city":"Berlin",
    "sg:phone":"+49 30/9164898",
    "sg:postcode":"13158",
    "sg:province":"Berlin",
    "wof:name":"J\u00fcrgen Pawlik",
    "wof:placetype":"venue"
},
  "geometry": {"coordinates":[13.367743,52.586983],"type":"Point"}
}