{
  "type": "Feature",
  "properties": {
    "iso:country":"DE",
    "sg:address":"Am Weiberdeich 28",
    "sg:city":"Guntersblum",
    "sg:phone":"+49 6249/2514",
    "sg:postcode":"67583",
    "sg:province":"Rheinland-Pfalz",
    "wof:name":"R. Und M. De Millas",
    "wof:placetype":"venue"
},
  "geometry": {"coordinates":[8.3412446976,49.7937850952],"type":"Point"}
}