{
  "type": "Feature",
  "properties": {
    "iso:country":"DE",
    "sg:address":"Weteritzer Landstr. 14",
    "sg:city":"Gardelegen",
    "sg:phone":"+49 3907/2525",
    "sg:postcode":"39638",
    "sg:province":"Sachsen-Anhalt",
    "wof:name":"Horst Kramer",
    "wof:placetype":"venue"
},
  "geometry": {"coordinates":[11.379735,52.525337],"type":"Point"}
}