{
  "type": "Feature",
  "properties": {
    "iso:country":"DE",
    "sg:address":"Birkenstr. 1",
    "sg:city":"Eggenthal",
    "sg:phone":"+49 8347/1011",
    "sg:postcode":"87653",
    "sg:province":"Bayern",
    "wof:name":"Hk K\u00f6nigsperger Haus- Und Wohnbau Gmbh",
    "wof:placetype":"venue"
},
  "geometry": {"coordinates":[10.5153923035,47.9139785767],"type":"Point"}
}