{
  "type": "Feature",
  "properties": {
    "iso:country":"DE",
    "sg:address":"Klenauer Str. 21",
    "sg:city":"Aresing",
    "sg:phone":"+49 8445/792",
    "sg:postcode":"86561",
    "sg:province":"Bayern",
    "wof:name":"Johann Mahl",
    "wof:placetype":"venue"
},
  "geometry": {"coordinates":[11.298181,48.53236],"type":"Point"}
}