{
  "type": "Feature",
  "properties": {
    "iso:country":"DE",
    "sg:address":"Plauenscher Ring 29",
    "sg:city":"Dresden",
    "sg:phone":"+49 351/4771911",
    "sg:postcode":"01187",
    "sg:province":"Sachsen",
    "wof:name":"Intraconnect Gmbh",
    "wof:placetype":"venue"
},
  "geometry": {"coordinates":[13.7114963531,51.0260047913],"type":"Point"}
}