{
  "type": "Feature",
  "properties": {
    "iso:country":"DE",
    "sg:address":"Hummelbergstrasse 24",
    "sg:city":"Kippenheim",
    "sg:postcode":"77971",
    "sg:province":"Baden-W\u00fcrttemberg",
    "wof:name":"Remote-proof Mit Proofout!",
    "wof:placetype":"venue"
},
  "geometry": {"coordinates":[7.853146,48.282887],"type":"Point"}
}