{
  "type": "Feature",
  "properties": {
    "iso:country":"DE",
    "sg:address":"Waldpromenade 11",
    "sg:city":"Gauting",
    "sg:phone":"+49 89/8501167",
    "sg:postcode":"82131",
    "sg:province":"Bayern",
    "wof:name":"Dr. Konrad R\u00fcchardt",
    "wof:placetype":"venue"
},
  "geometry": {"coordinates":[11.3768939972,48.0763816833],"type":"Point"}
}