{
  "type": "Feature",
  "properties": {
    "iso:country":"DE",
    "sg:address":"F\u00e4rbergasse 5",
    "sg:city":"Wasserburg",
    "sg:phone":"+49 8071/2513",
    "sg:postcode":"83512",
    "sg:province":"Bayern",
    "wof:name":"Erhard M\u00fcller",
    "wof:placetype":"venue"
},
  "geometry": {"coordinates":[12.2315301895,48.0615463257],"type":"Point"}
}