{
  "type": "Feature",
  "properties": {
    "iso:country":"DE",
    "sg:address":"Fellhornstr. 13a",
    "sg:city":"Lautrach",
    "sg:phone":"+49 8394/93170",
    "sg:postcode":"87763",
    "sg:province":"Bayern",
    "wof:name":"Wabersich",
    "wof:placetype":"venue"
},
  "geometry": {"coordinates":[10.1191301346,47.8959007263],"type":"Point"}
}