{
  "type": "Feature",
  "properties": {
    "iso:country":"DE",
    "sg:address":"Schlo\u00dfgasse 1",
    "sg:city":"Beuren",
    "sg:phone":"+49 7025/5725",
    "sg:postcode":"72660",
    "sg:province":"Baden-W\u00fcrttemberg",
    "wof:name":"P. Baumann",
    "wof:placetype":"venue"
},
  "geometry": {"coordinates":[9.389705658,48.5655059814],"type":"Point"}
}