{
  "type": "Feature",
  "properties": {
    "iso:country":"DE",
    "sg:address":"Gottfried-Keller-Str. 10",
    "sg:city":"Fuldatal",
    "sg:phone":"+49 5607/531",
    "sg:postcode":"34233",
    "sg:province":"Hessen",
    "wof:name":"Klaus Neudecker Architekt",
    "wof:placetype":"venue"
},
  "geometry": {"coordinates":[9.532875,51.383007],"type":"Point"}
}