{
  "type": "Feature",
  "properties": {
    "iso:country":"DE",
    "sg:address":"Egerl\u00e4nder Str. 16",
    "sg:city":"Erding",
    "sg:phone":"+49 8122/10561",
    "sg:postcode":"85435",
    "sg:province":"Bayern",
    "wof:name":"Werner A. Ruhland Immobilienmakler",
    "wof:placetype":"venue"
},
  "geometry": {"coordinates":[11.9042778015,48.3065071106],"type":"Point"}
}