{
  "type": "Feature",
  "properties": {
    "iso:country":"DE",
    "sg:address":"Fichtestr. 46",
    "sg:city":"M\u00fchlheim",
    "sg:phone":"+49 6108/76938",
    "sg:postcode":"63165",
    "sg:province":"Hessen",
    "wof:name":"M. Deiss",
    "wof:placetype":"venue"
},
  "geometry": {"coordinates":[8.8538360596,50.1205635071],"type":"Point"}
}