{
  "type": "Feature",
  "properties": {
    "iso:country":"DE",
    "sg:address":"Celler Str. 28",
    "sg:city":"Gifhorn",
    "sg:postcode":"38518",
    "sg:province":"Niedersachsen",
    "wof:name":"Fugenbetrieb Z & T Gmbh",
    "wof:placetype":"venue"
},
  "geometry": {"coordinates":[10.5368003845,52.4862098694],"type":"Point"}
}