{
  "type": "Feature",
  "properties": {
    "iso:country":"DE",
    "sg:address":"Meiendorfer Weg 10A",
    "sg:city":"Hamburg",
    "sg:phone":"+49 40",
    "sg:postcode":"22145",
    "sg:province":"Hamburg",
    "wof:name":"Hts High-pressure Technical Systems Gmbh - Hamburg",
    "wof:placetype":"venue"
},
  "geometry": {"coordinates":[10.166313,53.630554],"type":"Point"}
}