{
  "type": "Feature",
  "properties": {
    "iso:country":"DE",
    "sg:address":"Schonnebeckh\u00f6fe 236",
    "sg:city":"Essen",
    "sg:phone":"+49 201/302430",
    "sg:postcode":"45327",
    "sg:province":"Nordrhein-Westfalen",
    "wof:name":"Wilhelm Beher Gmbh",
    "wof:placetype":"venue"
},
  "geometry": {"coordinates":[7.047805,51.495373],"type":"Point"}
}