{
  "type": "Feature",
  "properties": {
    "iso:country":"DE",
    "sg:address":"Ringstr. 40",
    "sg:city":"Neunkirchen-Seelscheid",
    "sg:phone":"+49 2247/2729",
    "sg:postcode":"53819",
    "sg:province":"Nordrhein-Westfalen",
    "wof:name":"Hans Ewens Finanzberater",
    "wof:placetype":"venue"
},
  "geometry": {"coordinates":[7.3350777626,50.842666626],"type":"Point"}
}