{
  "type": "Feature",
  "properties": {
    "iso:country":"DE",
    "sg:address":"Lattenkamp 7",
    "sg:city":"Schleswig",
    "sg:phone":"+49 4621/96570",
    "sg:postcode":"24837",
    "sg:province":"Schleswig-Holstein",
    "wof:name":"Fressnapf Gr\u00fcner Laden Und Zoo Center Gmbh",
    "wof:placetype":"venue"
},
  "geometry": {"coordinates":[9.529522,54.530315],"type":"Point"}
}