{
  "type": "Feature",
  "properties": {
    "iso:country":"DE",
    "sg:address":"Johannisstr. 7",
    "sg:city":"Dessau",
    "sg:phone":"+49 340/212682",
    "sg:postcode":"06844",
    "sg:province":"Sachsen-Anhalt",
    "wof:name":"Leder Baltrock",
    "wof:placetype":"venue"
},
  "geometry": {"coordinates":[12.24221,51.837612],"type":"Point"}
}