{
  "type": "Feature",
  "properties": {
    "iso:country":"DE",
    "sg:address":"Inninger Str. 22",
    "sg:city":"Augsburg",
    "sg:phone":"+49 821/881741",
    "sg:postcode":"86179",
    "sg:province":"Bayern",
    "wof:name":"Babalu",
    "wof:placetype":"venue"
},
  "geometry": {"coordinates":[10.8864078522,48.3094100952],"type":"Point"}
}