{
  "type": "Feature",
  "properties": {
    "iso:country":"DE",
    "sg:address":"M\u00fcnchener Str. 12",
    "sg:city":"Unterf\u00f6hring",
    "sg:postcode":"85774",
    "sg:province":"Bayern",
    "wof:name":"Ontempo Gmbh",
    "wof:placetype":"venue"
},
  "geometry": {"coordinates":[11.631371,48.179588],"type":"Point"}
}