{
  "type": "Feature",
  "properties": {
    "iso:country":"DE",
    "sg:address":"Parallelstr. I. 21",
    "sg:city":"Bochum",
    "sg:phone":"+49 234/9502110",
    "sg:postcode":"44791",
    "sg:province":"Nordrhein-Westfalen",
    "wof:name":"Gitarrengalerie Schwarz Auf Weiss",
    "wof:placetype":"venue"
},
  "geometry": {"coordinates":[7.2502698898,51.4899482727],"type":"Point"}
}