{
  "type": "Feature",
  "properties": {
    "iso:country":"DE",
    "sg:address":"Friedrichstr. 30",
    "sg:city":"M\u00fcnchen",
    "sg:phone":"+49 89/332883",
    "sg:postcode":"80801",
    "sg:province":"Bayern",
    "wof:name":"H\u00f6lzl Backstube B\u00e4ckerei",
    "wof:placetype":"venue"
},
  "geometry": {"coordinates":[11.580467,48.160152],"type":"Point"}
}