{
  "type": "Feature",
  "properties": {
    "iso:country":"DE",
    "sg:address":"Enneper Str. 128 a",
    "sg:city":"Hagen",
    "sg:phone":"+49 2331/403722",
    "sg:postcode":"58135",
    "sg:province":"Nordrhein-Westfalen",
    "wof:name":"M. Zepnik",
    "wof:placetype":"venue"
},
  "geometry": {"coordinates":[7.397704,51.339943],"type":"Point"}
}