{
  "type": "Feature",
  "properties": {
    "iso:country":"DE",
    "sg:address":"Blumenrather Str. 220a",
    "sg:city":"Alsdorf",
    "sg:phone":"+49 2404/62313",
    "sg:postcode":"52477",
    "sg:province":"Nordrhein-Westfalen",
    "wof:name":"Kath. Pfarramt St. Barbara",
    "wof:placetype":"venue"
},
  "geometry": {"coordinates":[6.183221817,50.8489112854],"type":"Point"}
}