{
  "type": "Feature",
  "properties": {
    "iso:country":"DE",
    "sg:address":"Kirchstr. 10",
    "sg:city":"Oberreichenbach",
    "sg:phone":"+49 7051/51525",
    "sg:postcode":"75394",
    "sg:province":"Baden-W\u00fcrttemberg",
    "wof:name":"Uwe Kaesebier",
    "wof:placetype":"venue"
},
  "geometry": {"coordinates":[8.6621990204,48.7358894348],"type":"Point"}
}