{
  "type": "Feature",
  "properties": {
    "iso:country":"DE",
    "sg:address":"Vor den Bergen 5",
    "sg:city":"Hanstedt",
    "sg:phone":"+49 4184/89320",
    "sg:postcode":"21271",
    "sg:province":"Niedersachsen",
    "wof:name":"Reiterzentrum Hanstedt Beteiligungsges. Mbh",
    "wof:placetype":"venue"
},
  "geometry": {"coordinates":[10.003022,53.243408],"type":"Point"}
}