{
  "type": "Feature",
  "properties": {
    "iso:country":"DE",
    "sg:address":"Sch\u00f6nenbacher Str. 9",
    "sg:city":"Reichshof",
    "sg:phone":"+49 2265/8221",
    "sg:postcode":"51580",
    "sg:province":"Nordrhein-Westfalen",
    "wof:name":"D. Waltereit",
    "wof:placetype":"venue"
},
  "geometry": {"coordinates":[7.651181,50.979771],"type":"Point"}
}