{
  "type": "Feature",
  "properties": {
    "iso:country":"DE",
    "sg:address":"Obere Remscheider Str. 7",
    "sg:city":"Wermelskirchen",
    "sg:phone":"+49 2196/81430",
    "sg:postcode":"42929",
    "sg:province":"Nordrhein-Westfalen",
    "wof:name":"M\u00fcllenmeister",
    "wof:placetype":"venue"
},
  "geometry": {"coordinates":[7.2155051231,51.1409378052],"type":"Point"}
}