{
  "type": "Feature",
  "properties": {
    "iso:country":"DE",
    "sg:address":"Ludwigstr. 97",
    "sg:city":"Offenbach",
    "sg:phone":"+49 69/883976",
    "sg:postcode":"63067",
    "sg:province":"Hessen",
    "wof:name":"Maria Hoffmann",
    "wof:placetype":"venue"
},
  "geometry": {"coordinates":[8.7529287338,50.1051521301],"type":"Point"}
}