{
  "type": "Feature",
  "properties": {
    "iso:country":"DE",
    "sg:address":"Pfarrgalle 17",
    "sg:city":"Schotten",
    "sg:phone":"+49 6044/2654",
    "sg:postcode":"63679",
    "sg:province":"Hessen",
    "wof:name":"Dr. G. Roth Arzt F\u00fcr Gyn\u00e4kologie",
    "wof:placetype":"venue"
},
  "geometry": {"coordinates":[9.1171388626,50.5012969971],"type":"Point"}
}