{
  "type": "Feature",
  "properties": {
    "iso:country":"DE",
    "sg:address":"Bahnhofstr. 25",
    "sg:city":"K\u00fcllstedt",
    "sg:phone":"+49 36075/64107",
    "sg:postcode":"37359",
    "sg:province":"Th\u00fcringen",
    "wof:name":"Annegret Oberth\u00fcr",
    "wof:placetype":"venue"
},
  "geometry": {"coordinates":[10.2856712341,51.2752685547],"type":"Point"}
}