{
  "type": "Feature",
  "properties": {
    "iso:country":"DE",
    "sg:address":"K\u00e4the-Kollwitz-Str. 8",
    "sg:city":"Pirmasens",
    "sg:phone":"+49 6331/47607",
    "sg:postcode":"66955",
    "sg:province":"Rheinland-Pfalz",
    "wof:name":"Charlotte Duscha Masseurin",
    "wof:placetype":"venue"
},
  "geometry": {"coordinates":[7.63087,49.186615],"type":"Point"}
}