{
  "type": "Feature",
  "properties": {
    "iso:country":"DE",
    "sg:address":"Am Dobben 118",
    "sg:city":"Bremen",
    "sg:phone":"+49 421/705131",
    "sg:postcode":"28203",
    "sg:province":"Bremen",
    "wof:name":"Terraforming Gesellschaft F\u00fcr Erneuerbare Energien Und",
    "wof:placetype":"venue"
},
  "geometry": {"coordinates":[8.823831,53.077126],"type":"Point"}
}