{
  "type": "Feature",
  "properties": {
    "iso:country":"DE",
    "sg:address":"Raiffeisenstr. 7",
    "sg:city":"Rottenbuch",
    "sg:phone":"+49 8867/440",
    "sg:postcode":"82401",
    "sg:province":"Bayern",
    "wof:name":"Josef Erhard Bauunternehmen Gmbh",
    "wof:placetype":"venue"
},
  "geometry": {"coordinates":[10.961736,47.733501],"type":"Point"}
}