{
  "type": "Feature",
  "properties": {
    "iso:country":"DE",
    "sg:address":"Erich-K\u00f6ckert-Str 28",
    "sg:city":"Dessau",
    "sg:phone":"+49 340/8702107",
    "sg:postcode":"06842",
    "sg:province":"Sachsen-Anhalt",
    "wof:name":"Me-le Haustechnik Ag",
    "wof:placetype":"venue"
},
  "geometry": {"coordinates":[12.2366304398,51.8106765747],"type":"Point"}
}