{
  "type": "Feature",
  "properties": {
    "iso:country":"DE",
    "sg:address":"Am Wasserturm 16",
    "sg:city":"Dorsten",
    "sg:phone":"+49 2362/913134",
    "sg:postcode":"46282",
    "sg:province":"Nordrhein-Westfalen",
    "wof:name":"Michael Neuhaus Ergotherapeutsche Praxis",
    "wof:placetype":"venue"
},
  "geometry": {"coordinates":[6.96877,51.655399],"type":"Point"}
}