{
  "type": "Feature",
  "properties": {
    "iso:country":"DE",
    "sg:address":"Bacherwinkl 5b",
    "sg:city":"Ruhpolding",
    "sg:phone":"+49 8663/39401",
    "sg:postcode":"83324",
    "sg:province":"Bayern",
    "wof:name":"Fuschlberger",
    "wof:placetype":"venue"
},
  "geometry": {"coordinates":[12.61303,47.7617],"type":"Point"}
}