{
  "type": "Feature",
  "properties": {
    "iso:country":"DE",
    "sg:address":"Adolfstr. 135",
    "sg:city":"Bad Schwalbach",
    "sg:phone":"+49 6124/1333",
    "sg:postcode":"65307",
    "sg:province":"Hessen",
    "wof:name":"Erhard S\u00e4nger",
    "wof:placetype":"venue"
},
  "geometry": {"coordinates":[8.0762586594,50.1451797485],"type":"Point"}
}