{
  "type": "Feature",
  "properties": {
    "iso:country":"DE",
    "sg:address":"Edelfinger Str. 6",
    "sg:city":"Bad Mergentheim",
    "sg:postcode":"97980",
    "sg:province":"Baden-W\u00fcrttemberg",
    "wof:name":"Mathias Uhlig",
    "wof:placetype":"venue"
},
  "geometry": {"coordinates":[9.775149,49.497215],"type":"Point"}
}