{
  "type": "Feature",
  "properties": {
    "iso:country":"DE",
    "sg:address":"Friedrichrodaer Str. 19",
    "sg:city":"Gotha",
    "sg:phone":"+49 3621/746955",
    "sg:postcode":"99867",
    "sg:province":"Th\u00fcringen",
    "wof:name":"Lasa-elektroanlagen Gmbh",
    "wof:placetype":"venue"
},
  "geometry": {"coordinates":[10.691280365,50.9387016296],"type":"Point"}
}