{
  "type": "Feature",
  "properties": {
    "iso:country":"DE",
    "sg:address":"Schmiedgasse 1",
    "sg:city":"Ursensollen",
    "sg:phone":"+49 9628/330",
    "sg:postcode":"92289",
    "sg:province":"Bayern",
    "wof:name":"C. Wenkmann",
    "wof:placetype":"venue"
},
  "geometry": {"coordinates":[11.779625,49.396763],"type":"Point"}
}