{
  "type": "Feature",
  "properties": {
    "iso:country":"DE",
    "sg:address":"Siemensstr. 5",
    "sg:city":"Wietmarschen",
    "sg:phone":"+49 5908/960803",
    "sg:postcode":"49835",
    "sg:province":"Niedersachsen",
    "wof:name":"Hackmann Hochbau Gmbh",
    "wof:placetype":"venue"
},
  "geometry": {"coordinates":[7.2224779129,52.489944458],"type":"Point"}
}