{
  "type": "Feature",
  "properties": {
    "iso:country":"DE",
    "sg:address":"Bahnstrasse 3",
    "sg:city":"Steinbach",
    "sg:phone":"+49 4961/7124227",
    "sg:postcode":"61449",
    "sg:province":"Hessen",
    "wof:name":"Nassauische Sparkasse",
    "wof:placetype":"venue"
},
  "geometry": {"coordinates":[8.572856,50.168049],"type":"Point"}
}