{
  "type": "Feature",
  "properties": {
    "iso:country":"DE",
    "sg:address":"Ahrstr. 5",
    "sg:city":"Korschenbroich",
    "sg:phone":"+49 2161/673550",
    "sg:postcode":"41352",
    "sg:province":"Nordrhein-Westfalen",
    "wof:name":"Karl-heinz Fischer Gmbh",
    "wof:placetype":"venue"
},
  "geometry": {"coordinates":[6.5648498535,51.1949577332],"type":"Point"}
}