{
  "type": "Feature",
  "properties": {
    "iso:country":"DE",
    "sg:address":"Graf-Gerold-Str. 30",
    "sg:city":"Horb",
    "sg:phone":"+49 7483/1055",
    "sg:postcode":"72160",
    "sg:province":"Baden-W\u00fcrttemberg",
    "wof:name":"Nikor Gmbh",
    "wof:placetype":"venue"
},
  "geometry": {"coordinates":[8.7583026886,48.4190177917],"type":"Point"}
}