{
  "type": "Feature",
  "properties": {
    "iso:country":"DE",
    "sg:address":"Dr.-Friedrich-Wolf-Str. 9",
    "sg:city":"Radeberg",
    "sg:phone":"+49 3528/442879",
    "sg:postcode":"01454",
    "sg:province":"Sachsen",
    "wof:name":"Dr. Wolf-dietrich Stock Wertpapiervertrieb",
    "wof:placetype":"venue"
},
  "geometry": {"coordinates":[13.9124956131,51.1015701294],"type":"Point"}
}