{
  "type": "Feature",
  "properties": {
    "iso:country":"DE",
    "sg:address":"Dudenrother Str. 8",
    "sg:city":"Holzwickede",
    "sg:phone":"+49 2301/2214",
    "sg:postcode":"59439",
    "sg:province":"Nordrhein-Westfalen",
    "wof:name":"Dieter Freund Architekt",
    "wof:placetype":"venue"
},
  "geometry": {"coordinates":[7.619346,51.494907],"type":"Point"}
}