{
  "type": "Feature",
  "properties": {
    "iso:country":"DE",
    "sg:address":"Lange Str. 17",
    "sg:city":"Baden-Baden",
    "sg:phone":"+49 7221/28567",
    "sg:postcode":"76530",
    "sg:province":"Baden-W\u00fcrttemberg",
    "wof:name":"Taake Kg",
    "wof:placetype":"venue"
},
  "geometry": {"coordinates":[8.238749,48.762066],"type":"Point"}
}