{
  "type": "Feature",
  "properties": {
    "iso:country":"DE",
    "sg:address":"Georgstr. 52",
    "sg:city":"Castrop-Rauxel",
    "sg:phone":"+49 2305/8764",
    "sg:postcode":"44579",
    "sg:province":"Nordrhein-Westfalen",
    "wof:name":"Alexi & Partner Gmbh",
    "wof:placetype":"venue"
},
  "geometry": {"coordinates":[7.31128,51.588291],"type":"Point"}
}