{
  "type": "Feature",
  "properties": {
    "iso:country":"DE",
    "sg:address":"Jahnstr. 6",
    "sg:city":"Freyung",
    "sg:phone":"+49 8551/6655",
    "sg:postcode":"94078",
    "sg:province":"Bayern",
    "wof:name":"Gerhard Kalous Steuerberater",
    "wof:placetype":"venue"
},
  "geometry": {"coordinates":[13.5528268814,48.8097610474],"type":"Point"}
}