{
  "type": "Feature",
  "properties": {
    "iso:country":"DE",
    "sg:address":"Prinz-Handjery-Str. 70 b",
    "sg:city":"Berlin",
    "sg:phone":"+49 30/8157775",
    "sg:postcode":"14167",
    "sg:province":"Berlin",
    "wof:name":"Irb Institut F\u00fcr Rechnerunter- St\u00fctzte Bau- Und Bau-ablauf-",
    "wof:placetype":"venue"
},
  "geometry": {"coordinates":[13.263584,52.429279],"type":"Point"}
}