{
  "type": "Feature",
  "properties": {
    "iso:country":"DE",
    "sg:address":"Am Kirchweg 1",
    "sg:city":"Bresegard",
    "sg:phone":"+49 38755/20208",
    "sg:postcode":"19294",
    "sg:province":"Mecklenburg-Vorpommern",
    "wof:name":"Trockenwerk Eldena Gmbh",
    "wof:placetype":"venue"
},
  "geometry": {"coordinates":[11.3007049561,53.1721191406],"type":"Point"}
}