{
  "type": "Feature",
  "properties": {
    "iso:country":"DE",
    "sg:address":"Vormarkt 5",
    "sg:city":"Trostberg",
    "sg:postcode":"83308",
    "sg:province":"Bayern",
    "wof:name":"Verlagsbuchhandlung Oskar Erdl E. K.",
    "wof:placetype":"venue"
},
  "geometry": {"coordinates":[12.5519037247,48.0277366638],"type":"Point"}
}