{
  "type": "Feature",
  "properties": {
    "iso:country":"DE",
    "sg:address":"H\u00fcgelstr. 2",
    "sg:city":"Gifhorn",
    "sg:phone":"+49 5371/52066",
    "sg:postcode":"38518",
    "sg:province":"Niedersachsen",
    "wof:name":"Marijke Van Der Sanden Masseurin",
    "wof:placetype":"venue"
},
  "geometry": {"coordinates":[10.534158,52.487431],"type":"Point"}
}