{
  "type": "Feature",
  "properties": {
    "iso:country":"DE",
    "sg:address":"Am Markt 17",
    "sg:city":"Warburg",
    "sg:phone":"+49 5641/6630",
    "sg:postcode":"34414",
    "sg:province":"Nordrhein-Westfalen",
    "wof:name":"Im Bis-s-tro",
    "wof:placetype":"venue"
},
  "geometry": {"coordinates":[9.1466531754,51.4850845337],"type":"Point"}
}