{
  "type": "Feature",
  "properties": {
    "iso:country":"DE",
    "sg:address":"Eichenhofer Weg",
    "sg:city":"Wuppertal",
    "sg:postcode":"42279",
    "sg:province":"Nordrhein-Westfalen",
    "wof:name":"Elementarbau Gmbh",
    "wof:placetype":"venue"
},
  "geometry": {"coordinates":[7.2651047707,51.3122291565],"type":"Point"}
}