{
  "type": "Feature",
  "properties": {
    "iso:country":"DE",
    "sg:address":"Kirchberg 4",
    "sg:city":"Gro\u00dfr\u00fcckerswalde",
    "sg:postcode":"09518",
    "sg:province":"Sachsen",
    "wof:name":"Ev.-luth. Kirche Gro\u00dfr\u00fcckerswalde",
    "wof:placetype":"venue"
},
  "geometry": {"coordinates":[13.1199769974,50.6307640076],"type":"Point"}
}