{
  "type": "Feature",
  "properties": {
    "iso:country":"DE",
    "sg:address":"Luitpoldstr. 1",
    "sg:city":"Gerbach",
    "sg:phone":"+49 6361/7788",
    "sg:postcode":"67813",
    "sg:province":"Rheinland-Pfalz",
    "wof:name":"A. Uhl",
    "wof:placetype":"venue"
},
  "geometry": {"coordinates":[7.8706669807,49.6727638245],"type":"Point"}
}