{
  "type": "Feature",
  "properties": {
    "iso:country":"DE",
    "sg:address":"Kieler Str. 34",
    "sg:city":"B\u00f6nningstedt",
    "sg:phone":"+49 40/5566276",
    "sg:postcode":"25474",
    "sg:province":"Schleswig-Holstein",
    "wof:name":"Fliesenhalle B\u00f6ningstedt Gmbh",
    "wof:placetype":"venue"
},
  "geometry": {"coordinates":[9.9073448181,53.6562194824],"type":"Point"}
}