{
  "type": "Feature",
  "properties": {
    "iso:country":"DE",
    "sg:address":"Edisonstr. 22",
    "sg:city":"Lampertheim",
    "sg:phone":"+49 4962/062015",
    "sg:postcode":"68623",
    "sg:province":"Hessen",
    "wof:name":"Heiselbetz Gmbh",
    "wof:placetype":"venue"
},
  "geometry": {"coordinates":[8.482626915,49.5991172791],"type":"Point"}
}