{
  "type": "Feature",
  "properties": {
    "iso:country":"DE",
    "sg:address":"R\u00fctlistr. 15",
    "sg:city":"Berlin",
    "sg:phone":"+49 30/4551171",
    "sg:postcode":"13407",
    "sg:province":"Berlin",
    "wof:name":"Joachim Braun",
    "wof:placetype":"venue"
},
  "geometry": {"coordinates":[13.357279,52.562752],"type":"Point"}
}