{
  "type": "Feature",
  "properties": {
    "iso:country":"DE",
    "sg:address":"Konstantinstr. 142",
    "sg:city":"M\u00f6nchengladbach",
    "sg:phone":"+49 2166/851010",
    "sg:postcode":"41238",
    "sg:province":"Nordrhein-Westfalen",
    "wof:name":"Herbert Hannen",
    "wof:placetype":"venue"
},
  "geometry": {"coordinates":[6.486225,51.155819],"type":"Point"}
}