{
  "type": "Feature",
  "properties": {
    "iso:country":"DE",
    "sg:address":"Im Schlenkerhof 12",
    "sg:city":"Gummersbach",
    "sg:phone":"+49 2261/21137",
    "sg:postcode":"51645",
    "sg:province":"Nordrhein-Westfalen",
    "wof:name":"Restaurant Schlenkerhof",
    "wof:placetype":"venue"
},
  "geometry": {"coordinates":[7.5743699074,51.0061607361],"type":"Point"}
}