{
  "type": "Feature",
  "properties": {
    "iso:country":"DE",
    "sg:address":"Ilkstraat 17",
    "sg:city":"Hamburg",
    "sg:phone":"+49 40/6065858",
    "sg:postcode":"22399",
    "sg:province":"Hamburg",
    "wof:name":"Hans-peter Kazmierczak",
    "wof:placetype":"venue"
},
  "geometry": {"coordinates":[10.0681781769,53.6597671509],"type":"Point"}
}