{
  "type": "Feature",
  "properties": {
    "iso:country":"DE",
    "sg:address":"Weiherwiesenweg 1",
    "sg:city":"Brachttal",
    "sg:phone":"+49 6054/2203",
    "sg:postcode":"63636",
    "sg:province":"Hessen",
    "wof:name":"Heinrich Deckenbach",
    "wof:placetype":"venue"
},
  "geometry": {"coordinates":[9.2981157303,50.3203353882],"type":"Point"}
}