{
  "type": "Feature",
  "properties": {
    "iso:country":"DE",
    "sg:address":"Hauptstr. 112",
    "sg:city":"B\u00f6hmenkirch",
    "sg:phone":"+49 7332/6517",
    "sg:postcode":"89558",
    "sg:province":"Baden-W\u00fcrttemberg",
    "wof:name":"Georg Gebhart",
    "wof:placetype":"venue"
},
  "geometry": {"coordinates":[9.9352750778,48.6850318909],"type":"Point"}
}