{
  "type": "Feature",
  "properties": {
    "iso:country":"DE",
    "sg:address":"Bergstr. 3",
    "sg:city":"Walsrode",
    "sg:phone":"+49 5161/2649",
    "sg:postcode":"29664",
    "sg:province":"Niedersachsen",
    "wof:name":"Rynas Naturkost Und Naturwaren Bestellservice",
    "wof:placetype":"venue"
},
  "geometry": {"coordinates":[9.5871038437,52.8634185791],"type":"Point"}
}