{
  "type": "Feature",
  "properties": {
    "iso:country":"DE",
    "sg:address":"Auf dem Dreieck 1-4",
    "sg:city":"Bremen",
    "sg:phone":"+49 421/5287744",
    "sg:postcode":"28197",
    "sg:province":"Bremen",
    "wof:name":"Knechtel Holding Beteiligungs Gmbh",
    "wof:placetype":"venue"
},
  "geometry": {"coordinates":[8.785115,53.079002],"type":"Point"}
}