{
  "type": "Feature",
  "properties": {
    "iso:country":"DE",
    "sg:address":"Poststr. 1",
    "sg:city":"Zweibr\u00fccken",
    "sg:phone":"+49 6332/75988",
    "sg:postcode":"66482",
    "sg:province":"Rheinland-Pfalz",
    "wof:name":"Paramount",
    "wof:placetype":"venue"
},
  "geometry": {"coordinates":[7.361828804,49.2495307922],"type":"Point"}
}