{
  "type": "Feature",
  "properties": {
    "iso:country":"DE",
    "sg:address":"R\u00f6ther Gasse 20",
    "sg:city":"Gelnhausen",
    "sg:phone":"+49 6051/17110",
    "sg:postcode":"63571",
    "sg:province":"Hessen",
    "wof:name":"Eissalon Dolomiti",
    "wof:placetype":"venue"
},
  "geometry": {"coordinates":[9.19051,50.202965],"type":"Point"}
}