{
  "type": "Feature",
  "properties": {
    "iso:country":"DE",
    "sg:address":"Herz.Joh.Alb.Str.27",
    "sg:city":"Braunlage",
    "sg:phone":"+49 5520/92270",
    "sg:postcode":"38700",
    "sg:province":"Niedersachsen",
    "wof:name":"Braunlage Hotelpension Haus Fernblick",
    "wof:placetype":"venue"
},
  "geometry": {"coordinates":[10.6105051041,51.7278556824],"type":"Point"}
}