{
  "type": "Feature",
  "properties": {
    "iso:country":"DE",
    "sg:address":"Elmenhorster Str. 35",
    "sg:city":"Bargfeld-Stegen",
    "sg:postcode":"23863",
    "sg:province":"Schleswig-Holstein",
    "wof:name":"Taxiruf Bargfeld E. K.",
    "wof:placetype":"venue"
},
  "geometry": {"coordinates":[10.1991138458,53.7655677795],"type":"Point"}
}