{
  "type": "Feature",
  "properties": {
    "iso:country":"DE",
    "sg:address":"Eberhardstr. 8",
    "sg:city":"Rottenburg",
    "sg:phone":"+49 7472/3111",
    "sg:postcode":"72108",
    "sg:province":"Baden-W\u00fcrttemberg",
    "wof:name":"A. Uttenweiler Jun.",
    "wof:placetype":"venue"
},
  "geometry": {"coordinates":[8.937577,48.478798],"type":"Point"}
}