{
  "type": "Feature",
  "properties": {
    "iso:country":"DE",
    "sg:address":"Knopfhammer",
    "sg:city":"Gefrees",
    "sg:phone":"+49 9254/336",
    "sg:postcode":"95482",
    "sg:province":"Bayern",
    "wof:name":"Forellenhof Dittmar",
    "wof:placetype":"venue"
},
  "geometry": {"coordinates":[11.7794313431,50.0980796814],"type":"Point"}
}