{
  "type": "Feature",
  "properties": {
    "iso:country":"DE",
    "sg:address":"Amselweg 4 e",
    "sg:city":"Hatten",
    "sg:phone":"+49 4481/1023",
    "sg:postcode":"26209",
    "sg:province":"Niedersachsen",
    "wof:name":"Hss Hatter Senioren- Service Gmbh",
    "wof:placetype":"venue"
},
  "geometry": {"coordinates":[8.349605,53.019501],"type":"Point"}
}