{
  "type": "Feature",
  "properties": {
    "iso:country":"DE",
    "sg:address":"Seltersweg 87",
    "sg:city":"Gie\u00dfen",
    "sg:phone":"+49 641/12046",
    "sg:postcode":"35390",
    "sg:province":"Hessen",
    "wof:name":"Gabriele H\u00fcbner Rechtsanw\u00e4ltin Und Notarin",
    "wof:placetype":"venue"
},
  "geometry": {"coordinates":[8.6705989838,50.5821304321],"type":"Point"}
}