{
  "type": "Feature",
  "properties": {
    "iso:country":"DE",
    "sg:address":"Michelstadter Weg 84",
    "sg:city":"Berlin",
    "sg:phone":"+49 30/3352151",
    "sg:postcode":"13587",
    "sg:province":"Berlin",
    "wof:name":"Horst Lehmann",
    "wof:placetype":"venue"
},
  "geometry": {"coordinates":[13.207514,52.564857],"type":"Point"}
}