{
  "type": "Feature",
  "properties": {
    "iso:country":"DE",
    "sg:address":"Staub\u00f6rnchenstr. 6-8",
    "sg:city":"Kaiserslautern",
    "sg:phone":"+49 631/3106165",
    "sg:postcode":"67655",
    "sg:province":"Rheinland-Pfalz",
    "wof:name":"A-n-d-r-e.de  Webservices And More",
    "wof:placetype":"venue"
},
  "geometry": {"coordinates":[7.764874,49.442917],"type":"Point"}
}