{
  "type": "Feature",
  "properties": {
    "iso:country":"DE",
    "sg:address":"Unteres Schlo\u00df 3",
    "sg:city":"Mitwitz",
    "sg:postcode":"96268",
    "sg:province":"Bayern",
    "wof:name":"Fritz Schmidt Verwaltungs Gmbh",
    "wof:placetype":"venue"
},
  "geometry": {"coordinates":[11.2066774368,50.2486381531],"type":"Point"}
}