{
  "type": "Feature",
  "properties": {
    "iso:country":"DE",
    "sg:address":"Pfeilstr. 15",
    "sg:city":"K\u00f6ln",
    "sg:phone":"+49 221/2573070",
    "sg:postcode":"50672",
    "sg:province":"Nordrhein-Westfalen",
    "wof:name":"Restaurant Nanas",
    "wof:placetype":"venue"
},
  "geometry": {"coordinates":[6.9410190582,50.9371299744],"type":"Point"}
}