{
  "type": "Feature",
  "properties": {
    "iso:country":"DE",
    "sg:address":"Werler Str. 2a",
    "sg:city":"Arnsberg",
    "sg:phone":"+49 2932/51105",
    "sg:postcode":"59755",
    "sg:province":"Nordrhein-Westfalen",
    "wof:name":"Fbm Fernholz System Gmbh & Co.",
    "wof:placetype":"venue"
},
  "geometry": {"coordinates":[7.9603152275,51.4548912048],"type":"Point"}
}