{
  "type": "Feature",
  "properties": {
    "iso:country":"DE",
    "sg:address":"Marktpassage 10",
    "sg:city":"Hamburg",
    "sg:phone":"+49 40/7022882",
    "sg:postcode":"21149",
    "sg:province":"Hamburg",
    "wof:name":"Lothar Leopoldt Steuerberater",
    "wof:placetype":"venue"
},
  "geometry": {"coordinates":[9.8532466888,53.4712219238],"type":"Point"}
}