{
  "type": "Feature",
  "properties": {
    "iso:country":"DE",
    "sg:address":"Raiffeisenstr. 85b",
    "sg:city":"Pulheim",
    "sg:phone":"+49 221/9483136",
    "sg:postcode":"50259",
    "sg:province":"Nordrhein-Westfalen",
    "wof:name":"Gerd Kuck Ingenieur",
    "wof:placetype":"venue"
},
  "geometry": {"coordinates":[6.7903308868,51.0038223267],"type":"Point"}
}