{
  "type": "Feature",
  "properties": {
    "iso:country":"DE",
    "sg:address":"Hauptstr. 1a",
    "sg:city":"Scheibenhardt",
    "sg:phone":"+49 7277/466",
    "sg:postcode":"76779",
    "sg:province":"Rheinland-Pfalz",
    "wof:name":"Wagner",
    "wof:placetype":"venue"
},
  "geometry": {"coordinates":[8.1364345551,48.9800720215],"type":"Point"}
}