{
  "type": "Feature",
  "properties": {
    "iso:country":"DE",
    "sg:address":"Marienburger Str. 145",
    "sg:city":"Hildesheim",
    "sg:phone":"+49 5121/85144",
    "sg:postcode":"31141",
    "sg:province":"Niedersachsen",
    "wof:name":"Lobschat Und L\u00fcdtke Rechtsanw\u00e4lte",
    "wof:placetype":"venue"
},
  "geometry": {"coordinates":[9.9622907639,52.140838623],"type":"Point"}
}