{
  "type": "Feature",
  "properties": {
    "iso:country":"DE",
    "sg:address":"Bismarckstr. 8",
    "sg:city":"Radolfzell",
    "sg:phone":"+49 7732/53336",
    "sg:postcode":"78315",
    "sg:province":"Baden-W\u00fcrttemberg",
    "wof:name":"Altbaden",
    "wof:placetype":"venue"
},
  "geometry": {"coordinates":[8.9674024582,47.7397155762],"type":"Point"}
}