{
  "type": "Feature",
  "properties": {
    "iso:country":"DE",
    "sg:address":"Friedrich-Ebert-Str 201",
    "sg:city":"Velbert",
    "sg:phone":"+49 2051/59464",
    "sg:postcode":"42549",
    "sg:province":"Nordrhein-Westfalen",
    "wof:name":"Walter Kunze & Sohn",
    "wof:placetype":"venue"
},
  "geometry": {"coordinates":[7.0398058891,51.3410453796],"type":"Point"}
}