{
  "type": "Feature",
  "properties": {
    "iso:country":"DE",
    "sg:address":"Boeckeler Str. 8",
    "sg:city":"Tutzing",
    "sg:phone":"+49 8158/6278",
    "sg:postcode":"82327",
    "sg:province":"Bayern",
    "wof:name":"Dr. Hans Radwanski",
    "wof:placetype":"venue"
},
  "geometry": {"coordinates":[11.2722129822,47.9130973816],"type":"Point"}
}