{
  "type": "Feature",
  "properties": {
    "iso:country":"DE",
    "sg:address":"Mohnstr. 30",
    "sg:city":"Dresden",
    "sg:phone":"+49 351/8489549",
    "sg:postcode":"01127",
    "sg:province":"Sachsen",
    "wof:name":"Silke H\u00fcbner",
    "wof:placetype":"venue"
},
  "geometry": {"coordinates":[13.720365,51.079006],"type":"Point"}
}