{
  "type": "Feature",
  "properties": {
    "iso:country":"DE",
    "sg:address":"Breitenbrucher Str. 12",
    "sg:city":"Arnsberg",
    "sg:phone":"+49 2931/6265",
    "sg:postcode":"59823",
    "sg:province":"Nordrhein-Westfalen",
    "wof:name":"Altes Gasthaus Spindeldreher",
    "wof:placetype":"venue"
},
  "geometry": {"coordinates":[8.1026849747,51.4361877441],"type":"Point"}
}