{
  "type": "Feature",
  "properties": {
    "iso:country":"DE",
    "sg:address":"Frankfurter Allee 45",
    "sg:city":"Berlin",
    "sg:phone":"+49 30/42010563",
    "sg:postcode":"10247",
    "sg:province":"Berlin",
    "wof:name":"Lenz-bauservice- Vermittlungs- Gmbh",
    "wof:placetype":"venue"
},
  "geometry": {"coordinates":[13.463613,52.515034],"type":"Point"}
}