{
  "type": "Feature",
  "properties": {
    "iso:country":"DE",
    "sg:address":"Max-Reger-Weg 10",
    "sg:city":"Geretsried",
    "sg:phone":"+49 8171/52192",
    "sg:postcode":"82538",
    "sg:province":"Bayern",
    "wof:name":"Kurt Schnurrer Steuerbevollm\u00e4chtigter",
    "wof:placetype":"venue"
},
  "geometry": {"coordinates":[11.4812555313,47.8532752991],"type":"Point"}
}