{
  "type": "Feature",
  "properties": {
    "iso:country":"DE",
    "sg:address":"Kantstr. 26",
    "sg:city":"Straubenhardt",
    "sg:phone":"+49 7248/932173",
    "sg:postcode":"75334",
    "sg:province":"Baden-W\u00fcrttemberg",
    "wof:name":"G\u00fcnter Eberle Architekt",
    "wof:placetype":"venue"
},
  "geometry": {"coordinates":[8.490507,48.844696],"type":"Point"}
}