{
  "type": "Feature",
  "properties": {
    "iso:country":"DE",
    "sg:address":"Hohlweg 5",
    "sg:city":"Jesberg",
    "sg:phone":"+49 6695/480",
    "sg:postcode":"34632",
    "sg:province":"Hessen",
    "wof:name":"Heinz M\u00f6ller",
    "wof:placetype":"venue"
},
  "geometry": {"coordinates":[9.164477,50.963203],"type":"Point"}
}