{
  "type": "Feature",
  "properties": {
    "iso:country":"DE",
    "sg:address":"Tulengasse 7",
    "sg:city":"Konstanz",
    "sg:phone":"+49 7531/16500",
    "sg:postcode":"78462",
    "sg:province":"Baden-W\u00fcrttemberg",
    "wof:name":"Dr. Ulrich M\u00fcller Rechtsanwalt",
    "wof:placetype":"venue"
},
  "geometry": {"coordinates":[9.1753416061,47.6653594971],"type":"Point"}
}