{
  "type": "Feature",
  "properties": {
    "iso:country":"DE",
    "sg:address":"Hauptstr. 25",
    "sg:city":"Heidelberg",
    "sg:phone":"+49 6221/25672",
    "sg:postcode":"69117",
    "sg:province":"Baden-W\u00fcrttemberg",
    "wof:name":"Konzertb\u00fcro Hohensee",
    "wof:placetype":"venue"
},
  "geometry": {"coordinates":[8.695593,49.410282],"type":"Point"}
}