{
  "type": "Feature",
  "properties": {
    "iso:country":"DE",
    "sg:address":"H\u00fcttenstr. 6",
    "sg:city":"Wiesbaden",
    "sg:phone":"+49 611/23019",
    "sg:postcode":"65201",
    "sg:province":"Hessen",
    "wof:name":"A. P. A. Autopr\u00fcfanlagen Vertrieb Und Kundendienst Gmbh",
    "wof:placetype":"venue"
},
  "geometry": {"coordinates":[8.208836,50.049202],"type":"Point"}
}