{
  "type": "Feature",
  "properties": {
    "iso:country":"DE",
    "sg:address":"Burgartenstr.24",
    "sg:city":"Bonn",
    "sg:phone":"+49 228",
    "sg:postcode":"58588",
    "sg:province":"Nordrhein-Westfalen",
    "wof:name":"Houseoferotic-4eroticgirlsfrombonnforyou",
    "wof:placetype":"venue"
},
  "geometry": {"coordinates":[7.089846,50.720821],"type":"Point"}
}