{
  "type": "Feature",
  "properties": {
    "iso:country":"DE",
    "sg:address":"Lange Str. 56",
    "sg:city":"L\u00fcbbecke",
    "sg:phone":"+49 5741/40590",
    "sg:postcode":"32312",
    "sg:province":"Nordrhein-Westfalen",
    "wof:name":"K. Dr\u00f6ge",
    "wof:placetype":"venue"
},
  "geometry": {"coordinates":[8.6190166473,52.3041114807],"type":"Point"}
}