{
  "type": "Feature",
  "properties": {
    "iso:country":"DE",
    "sg:address":"Kaiser-Wilhelm-Str. 17",
    "sg:city":"Berlin",
    "sg:phone":"+49 30/7689070",
    "sg:postcode":"12247",
    "sg:province":"Berlin",
    "wof:name":"Otto Kind Ag",
    "wof:placetype":"venue"
},
  "geometry": {"coordinates":[13.336017,52.430573],"type":"Point"}
}