{
  "type": "Feature",
  "properties": {
    "iso:country":"DE",
    "sg:address":"Bahnhofstr. 6",
    "sg:city":"Th\u00fcr",
    "sg:phone":"+49 2652/2862",
    "sg:postcode":"56743",
    "sg:province":"Rheinland-Pfalz",
    "wof:name":"Marmor Und Fliesen Franz Josef Bl\u00e4ser Gmbh",
    "wof:placetype":"venue"
},
  "geometry": {"coordinates":[7.2802410126,50.3570022583],"type":"Point"}
}