{
  "type": "Feature",
  "properties": {
    "iso:country":"DE",
    "sg:address":"Eppendorfer Landstr. 84",
    "sg:city":"Hamburg",
    "sg:phone":"+49 40/470958",
    "sg:postcode":"20249",
    "sg:province":"Hamburg",
    "wof:name":"Kids Kinderladen Inh.edelgard Wolf",
    "wof:placetype":"venue"
},
  "geometry": {"coordinates":[9.9877109528,53.5906181335],"type":"Point"}
}