{
  "type": "Feature",
  "properties": {
    "iso:country":"DE",
    "sg:address":"Germersheimer Str. 62",
    "sg:city":"Lingenfeld",
    "sg:phone":"+49 4963/445881",
    "sg:postcode":"67360",
    "sg:province":"Rheinland-Pfalz",
    "wof:name":"Sparkasse Germersheim-kandel",
    "wof:placetype":"venue"
},
  "geometry": {"coordinates":[8.342785,49.247601],"type":"Point"}
}