{
  "type": "Feature",
  "properties": {
    "iso:country":"DE",
    "sg:address":"Georg-Schumann-Str. 290",
    "sg:city":"Leipzig",
    "sg:phone":"+49 341/5906671",
    "sg:postcode":"04159",
    "sg:province":"Sachsen",
    "wof:name":"H. Knappik Gute Laune Floristik",
    "wof:placetype":"venue"
},
  "geometry": {"coordinates":[12.329549,51.372704],"type":"Point"}
}