{
  "type": "Feature",
  "properties": {
    "iso:country":"DE",
    "sg:address":"Kirchstr. 2",
    "sg:city":"Husby",
    "sg:phone":"+49 4634/328",
    "sg:postcode":"24975",
    "sg:province":"Schleswig-Holstein",
    "wof:name":"K. Nissen",
    "wof:placetype":"venue"
},
  "geometry": {"coordinates":[9.579066,54.764084],"type":"Point"}
}