{
  "type": "Feature",
  "properties": {
    "iso:country":"DE",
    "sg:address":"Homberger 5",
    "sg:city":"D\u00fcsseldorf",
    "sg:phone":"+49 4921/1494211",
    "sg:postcode":"40474",
    "sg:province":"Nordrhein-Westfalen",
    "wof:name":"M\u00d6ser-weiss Marianne Presse- U. Pr B\u00dcro",
    "wof:placetype":"venue"
},
  "geometry": {"coordinates":[6.771293,51.242214],"type":"Point"}
}