{
  "type": "Feature",
  "properties": {
    "iso:country":"DE",
    "sg:address":"Mindeltalstr. 12",
    "sg:city":"Unteregg",
    "sg:phone":"+49 8269/704",
    "sg:postcode":"87782",
    "sg:province":"Bayern",
    "wof:name":"Roman Schorer",
    "wof:placetype":"venue"
},
  "geometry": {"coordinates":[10.467533,47.963692],"type":"Point"}
}