{
  "type": "Feature",
  "properties": {
    "iso:country":"DE",
    "sg:address":"Heinz-B\u00e4cker-Str. 9",
    "sg:city":"Essen",
    "sg:phone":"+49 201/866410",
    "sg:postcode":"45356",
    "sg:province":"Nordrhein-Westfalen",
    "wof:name":"M\u00e4rz Logistic Center Gmbh",
    "wof:placetype":"venue"
},
  "geometry": {"coordinates":[6.9457859993,51.4938850403],"type":"Point"}
}