{
  "type": "Feature",
  "properties": {
    "iso:country":"DE",
    "sg:address":"Dorfstr. 78",
    "sg:city":"Borstel-Hohenraden",
    "sg:phone":"+49 4101/74647",
    "sg:postcode":"25494",
    "sg:province":"Schleswig-Holstein",
    "wof:name":"H. W\u00f6rdemann",
    "wof:placetype":"venue"
},
  "geometry": {"coordinates":[9.816123,53.695988],"type":"Point"}
}