{
  "type": "Feature",
  "properties": {
    "iso:country":"DE",
    "sg:address":"Wegerden 107",
    "sg:city":"Warmsen",
    "sg:phone":"+49 5767/1714",
    "sg:postcode":"31606",
    "sg:province":"Niedersachsen",
    "wof:name":"Rasse-gefl\u00fcgelzuchtverein Gro\u00dfenv\u00f6rde",
    "wof:placetype":"venue"
},
  "geometry": {"coordinates":[8.8493309021,52.456073761],"type":"Point"}
}