{
  "type": "Feature",
  "properties": {
    "iso:country":"DE",
    "sg:address":"Ostwall 97",
    "sg:city":"Krefeld",
    "sg:phone":"+49 2151/613314",
    "sg:postcode":"47798",
    "sg:province":"Nordrhein-Westfalen",
    "wof:name":"Dreik\u00f6nigen-apotheke",
    "wof:placetype":"venue"
},
  "geometry": {"coordinates":[6.56411,51.337318],"type":"Point"}
}