{
  "type": "Feature",
  "properties": {
    "iso:country":"DE",
    "sg:address":"Scheidter Str. 119",
    "sg:city":"Saarbr\u00fccken",
    "sg:phone":"+49 681/34298",
    "sg:postcode":"66123",
    "sg:province":"Saarland",
    "wof:name":"Horst Lorenz",
    "wof:placetype":"venue"
},
  "geometry": {"coordinates":[7.0198960304,49.241607666],"type":"Point"}
}