{
  "type": "Feature",
  "properties": {
    "iso:country":"DE",
    "sg:address":"Nu\u00dfbaumallee 10a",
    "sg:city":"Leipzig",
    "sg:phone":"+49 34297/42469",
    "sg:postcode":"04288",
    "sg:province":"Sachsen",
    "wof:name":"H. Schachtschneider",
    "wof:placetype":"venue"
},
  "geometry": {"coordinates":[12.450467,51.313591],"type":"Point"}
}