{
  "type": "Feature",
  "properties": {
    "iso:country":"DE",
    "sg:address":"Hauptstr. 33",
    "sg:city":"Winterlingen",
    "sg:phone":"+49 7577/1613",
    "sg:postcode":"72474",
    "sg:province":"Baden-W\u00fcrttemberg",
    "wof:name":"Gasthaus Hirsch",
    "wof:placetype":"venue"
},
  "geometry": {"coordinates":[9.1600179672,48.1973762512],"type":"Point"}
}