{
  "type": "Feature",
  "properties": {
    "iso:country":"DE",
    "sg:address":"Fabrikstr. 14",
    "sg:city":"Hettenleidelheim",
    "sg:postcode":"67310",
    "sg:province":"Rheinland-Pfalz",
    "wof:name":"Tri Altreifen-recycling Gmbh",
    "wof:placetype":"venue"
},
  "geometry": {"coordinates":[8.07937,49.542175],"type":"Point"}
}