{
  "type": "Feature",
  "properties": {
    "iso:country":"DE",
    "sg:address":"Vogelsang 57",
    "sg:city":"Schwetzingen",
    "sg:phone":"+49 6202/28050",
    "sg:postcode":"68723",
    "sg:province":"Baden-W\u00fcrttemberg",
    "wof:name":"Rolf Wippel Steuerberater",
    "wof:placetype":"venue"
},
  "geometry": {"coordinates":[8.5482587814,49.4115905762],"type":"Point"}
}