{
  "type": "Feature",
  "properties": {
    "iso:country":"DE",
    "sg:address":"Emminger Str. 14",
    "sg:city":"Jettingen",
    "sg:phone":"+49 7452/75266",
    "sg:postcode":"71131",
    "sg:province":"Baden-W\u00fcrttemberg",
    "wof:name":"Peter Und Ellen Scholz",
    "wof:placetype":"venue"
},
  "geometry": {"coordinates":[8.771324,48.579208],"type":"Point"}
}