{
  "type": "Feature",
  "properties": {
    "iso:country":"DE",
    "sg:address":"Dammhaststr. 3",
    "sg:city":"Zehdenick",
    "sg:phone":"+49 3307/313307",
    "sg:postcode":"16792",
    "sg:province":"Brandenburg",
    "wof:name":"Drogerie Riedinger",
    "wof:placetype":"venue"
},
  "geometry": {"coordinates":[13.334002,52.981071],"type":"Point"}
}