{
  "type": "Feature",
  "properties": {
    "iso:country":"DE",
    "sg:address":"Stefanstr. 1",
    "sg:city":"Stolberg",
    "sg:phone":"+49 2402/30545",
    "sg:postcode":"52223",
    "sg:province":"Nordrhein-Westfalen",
    "wof:name":"Tacoma Snackbar",
    "wof:placetype":"venue"
},
  "geometry": {"coordinates":[6.2105097771,50.7320747375],"type":"Point"}
}