{
  "type": "Feature",
  "properties": {
    "iso:country":"DE",
    "sg:address":"Kniprodestr. 95-97",
    "sg:city":"Wilhelmshaven",
    "sg:phone":"+49 4421/9540",
    "sg:postcode":"26388",
    "sg:province":"Niedersachsen",
    "wof:name":"Ecw Marketinggesellschaft Mbh",
    "wof:placetype":"venue"
},
  "geometry": {"coordinates":[8.09497,53.58218],"type":"Point"}
}