{
  "type": "Feature",
  "properties": {
    "iso:country":"DE",
    "sg:city":"Hausham",
    "sg:phone":"+49 8026/5071",
    "sg:postcode":"83734",
    "sg:province":"Bayern",
    "wof:name":"Raiffeisenbank Miesbach Eg",
    "wof:placetype":"venue"
},
  "geometry": {"coordinates":[11.842546,47.747509],"type":"Point"}
}