{
  "type": "Feature",
  "properties": {
    "iso:country":"DE",
    "sg:address":"Gerhart-Hauptmann-Str. 18",
    "sg:city":"Neuwied",
    "sg:phone":"+49 2631/71061",
    "sg:postcode":"56567",
    "sg:province":"Rheinland-Pfalz",
    "wof:name":"Moritz",
    "wof:placetype":"venue"
},
  "geometry": {"coordinates":[7.4712781906,50.4623641968],"type":"Point"}
}