{
  "type": "Feature",
  "properties": {
    "iso:country":"DE",
    "sg:address":"Marktstr. 22",
    "sg:city":"Schalkau",
    "sg:phone":"+49 36766/20024",
    "sg:postcode":"96528",
    "sg:province":"Th\u00fcringen",
    "wof:name":"Elektro-schramm Gmbh",
    "wof:placetype":"venue"
},
  "geometry": {"coordinates":[11.0071601868,50.3941383362],"type":"Point"}
}