{
  "type": "Feature",
  "properties": {
    "iso:country":"DE",
    "sg:address":"Eduard-Breitung-Weg 6",
    "sg:city":"Hilders",
    "sg:phone":"+49 6681/7349",
    "sg:postcode":"36115",
    "sg:province":"Hessen",
    "wof:name":"D. Kur\u00e4tzki",
    "wof:placetype":"venue"
},
  "geometry": {"coordinates":[9.999347,50.57819],"type":"Point"}
}