{
  "type": "Feature",
  "properties": {
    "iso:country":"DE",
    "sg:address":"Kirchstr. 4",
    "sg:city":"Dassel",
    "sg:phone":"+49 5562/383",
    "sg:postcode":"37586",
    "sg:province":"Niedersachsen",
    "wof:name":"Wilhelm D\u00fcker",
    "wof:placetype":"venue"
},
  "geometry": {"coordinates":[9.6895561218,51.8016967773],"type":"Point"}
}