{
  "type": "Feature",
  "properties": {
    "iso:country":"DE",
    "sg:address":"Erich-K\u00f6hn-Str. 9",
    "sg:city":"Leipzig",
    "sg:postcode":"04177",
    "sg:province":"Sachsen",
    "wof:name":"Stabag Stahl- Und Aluminium- Bau Gerlach Gmbh",
    "wof:placetype":"venue"
},
  "geometry": {"coordinates":[12.338347435,51.3417167664],"type":"Point"}
}