{
  "type": "Feature",
  "properties": {
    "iso:country":"DE",
    "sg:address":"Posthof 7",
    "sg:city":"Eitorf",
    "sg:phone":"+49 2243/5500",
    "sg:postcode":"53783",
    "sg:province":"Nordrhein-Westfalen",
    "wof:name":"Ayk Beauty Sun",
    "wof:placetype":"venue"
},
  "geometry": {"coordinates":[7.4499797821,50.7707290649],"type":"Point"}
}