{
  "type": "Feature",
  "properties": {
    "iso:country":"DE",
    "sg:address":"Bahnhofstr. 31",
    "sg:city":"Deisenhofen",
    "sg:phone":"+49 89/6132445",
    "sg:postcode":"82041",
    "sg:province":"Bayern",
    "wof:name":"Hengl",
    "wof:placetype":"venue"
},
  "geometry": {"coordinates":[11.586018,48.019455],"type":"Point"}
}