{
  "type": "Feature",
  "properties": {
    "iso:country":"DE",
    "sg:address":"Ernst-Wiss-Str. 18",
    "sg:city":"Frankfurt",
    "sg:postcode":"65933",
    "sg:province":"Hessen",
    "wof:name":"Boxheimer Und Partner Ingenieure Automation",
    "wof:placetype":"venue"
},
  "geometry": {"coordinates":[8.5908918381,50.0980796814],"type":"Point"}
}