{
  "type": "Feature",
  "properties": {
    "iso:country":"DE",
    "sg:address":"Hauptstr. 39",
    "sg:city":"Eurasburg",
    "sg:phone":"+49 8208/295",
    "sg:postcode":"86495",
    "sg:province":"Bayern",
    "wof:name":"I. Hiegl",
    "wof:placetype":"venue"
},
  "geometry": {"coordinates":[11.0797052383,48.3355445862],"type":"Point"}
}