{
  "type": "Feature",
  "properties": {
    "iso:country":"DE",
    "sg:address":"Pfl\u00fcgersrasse 16",
    "sg:city":"Bassum",
    "sg:phone":"+49 4241/970086",
    "sg:postcode":"27211",
    "sg:province":"Niedersachsen",
    "wof:name":"Bitcolor Visitenkarten Express",
    "wof:placetype":"venue"
},
  "geometry": {"coordinates":[8.731063,52.85284],"type":"Point"}
}