{
  "type": "Feature",
  "properties": {
    "iso:country":"DE",
    "sg:address":"Max-Brauer-Allee 54",
    "sg:city":"Hamburg",
    "sg:phone":"+49 40/3809969",
    "sg:postcode":"22765",
    "sg:province":"Hamburg",
    "wof:name":"G. Reichert",
    "wof:placetype":"venue"
},
  "geometry": {"coordinates":[9.9379196167,53.5527801514],"type":"Point"}
}