{
  "type": "Feature",
  "properties": {
    "iso:country":"DE",
    "sg:address":"Kasernstr. 9",
    "sg:city":"Amberg",
    "sg:phone":"+49 9621/650666",
    "sg:postcode":"92224",
    "sg:province":"Bayern",
    "wof:name":"Universa Versicherung Frank Schubert",
    "wof:placetype":"venue"
},
  "geometry": {"coordinates":[11.8584012985,49.4473114014],"type":"Point"}
}