{
  "type": "Feature",
  "properties": {
    "iso:country":"DE",
    "sg:address":"Hohlstr. 1",
    "sg:city":"Hadamar",
    "sg:phone":"+49 6433/2655",
    "sg:postcode":"65589",
    "sg:province":"Hessen",
    "wof:name":"Josef Lehnert",
    "wof:placetype":"venue"
},
  "geometry": {"coordinates":[8.036211,50.436832],"type":"Point"}
}