{
  "type": "Feature",
  "properties": {
    "iso:country":"DE",
    "sg:address":"Am M\u00fchlanger 10",
    "sg:city":"Mering",
    "sg:postcode":"86415",
    "sg:province":"Bayern",
    "wof:name":"Hvanna Gmbh",
    "wof:placetype":"venue"
},
  "geometry": {"coordinates":[10.9803876877,48.268951416],"type":"Point"}
}