{
  "type": "Feature",
  "properties": {
    "iso:country":"DE",
    "sg:address":"Allerfeldstr. 9",
    "sg:city":"Springe",
    "sg:phone":"+49 5045/7500",
    "sg:postcode":"31832",
    "sg:province":"Niedersachsen",
    "wof:name":"A. Tordai",
    "wof:placetype":"venue"
},
  "geometry": {"coordinates":[9.677403,52.235203],"type":"Point"}
}