{
  "type": "Feature",
  "properties": {
    "iso:country":"DE",
    "sg:address":"Am Friesoyther Kanal I 13",
    "sg:city":"Friesoythe",
    "sg:phone":"+49 4491/2451",
    "sg:postcode":"26169",
    "sg:province":"Niedersachsen",
    "wof:name":"Hermann Knelangen",
    "wof:placetype":"venue"
},
  "geometry": {"coordinates":[7.81698,53.029236],"type":"Point"}
}