{
  "type": "Feature",
  "properties": {
    "iso:country":"DE",
    "sg:address":"Cicerostr. 26",
    "sg:city":"Berlin",
    "sg:phone":"+49 30/8938530",
    "sg:postcode":"10709",
    "sg:province":"Berlin",
    "wof:name":"Eurawasser Betriebs- F\u00fchrungsgesellschaft Mbh",
    "wof:placetype":"venue"
},
  "geometry": {"coordinates":[13.3008813858,52.4912986755],"type":"Point"}
}