{
  "type": "Feature",
  "properties": {
    "iso:country":"DE",
    "sg:address":"Watzlikstr. 8",
    "sg:city":"K\u00f6tzting",
    "sg:phone":"+49 9941/8632",
    "sg:postcode":"93444",
    "sg:province":"Bayern",
    "wof:name":"Franz Piller Ingenieurb\u00fcro",
    "wof:placetype":"venue"
},
  "geometry": {"coordinates":[12.8692703247,49.1731185913],"type":"Point"}
}