{
  "type": "Feature",
  "properties": {
    "iso:country":"DE",
    "sg:address":"Bielefelder Str. 16",
    "sg:city":"Georgsmarienh\u00fctte",
    "sg:phone":"+49 5401/41074",
    "sg:postcode":"49124",
    "sg:province":"Niedersachsen",
    "wof:name":"Heinrich Uhlmann",
    "wof:placetype":"venue"
},
  "geometry": {"coordinates":[8.095331,52.222893],"type":"Point"}
}