{
  "type": "Feature",
  "properties": {
    "iso:country":"DE",
    "sg:address":"Breidtersteegsm\u00fchle 1",
    "sg:city":"Lohmar",
    "sg:phone":"+49 2246",
    "sg:postcode":"53797",
    "sg:province":"Nordrhein-Westfalen",
    "wof:name":"Breidtersteegsm\u00fchle - Fa. Franz Broich",
    "wof:placetype":"venue"
},
  "geometry": {"coordinates":[7.2705850601,50.8481483459],"type":"Point"}
}