{
  "type": "Feature",
  "properties": {
    "iso:country":"DE",
    "sg:address":"Schwanthalerstr. 42",
    "sg:city":"M\u00fcnchen",
    "sg:phone":"+49 89/531970",
    "sg:postcode":"80336",
    "sg:province":"Bayern",
    "wof:name":"Pension Toskana",
    "wof:placetype":"venue"
},
  "geometry": {"coordinates":[11.5579853058,48.1375427246],"type":"Point"}
}