{
  "type": "Feature",
  "properties": {
    "iso:country":"DE",
    "sg:address":"Holder\u00e4ckerstr. 13",
    "sg:city":"Stuttgart",
    "sg:phone":"+49 711/8873928",
    "sg:postcode":"70499",
    "sg:province":"Baden-W\u00fcrttemberg",
    "wof:name":"Deutscher Caravan Handelsverband E. V.",
    "wof:placetype":"venue"
},
  "geometry": {"coordinates":[9.1020936966,48.8229141235],"type":"Point"}
}