{
  "type": "Feature",
  "properties": {
    "iso:country":"DE",
    "sg:address":"Leipziger Str. 41",
    "sg:city":"M\u00fclheim",
    "sg:phone":"+49 208/490662",
    "sg:postcode":"45472",
    "sg:province":"Nordrhein-Westfalen",
    "wof:name":"H. Jost",
    "wof:placetype":"venue"
},
  "geometry": {"coordinates":[6.9549818039,51.436378479],"type":"Point"}
}