{
  "type": "Feature",
  "properties": {
    "iso:country":"DE",
    "sg:address":"Goethestr. 9",
    "sg:city":"Verl",
    "sg:phone":"+49 5246/1548",
    "sg:postcode":"33415",
    "sg:province":"Nordrhein-Westfalen",
    "wof:name":"Anne H\u00fcgelmeyer Masseurin",
    "wof:placetype":"venue"
},
  "geometry": {"coordinates":[8.510834,51.879673],"type":"Point"}
}