{
  "type": "Feature",
  "properties": {
    "iso:country":"DE",
    "sg:address":"Schmiedweg 1",
    "sg:city":"Egling",
    "sg:phone":"+49 8176/283",
    "sg:postcode":"82544",
    "sg:province":"Bayern",
    "wof:name":"K. Schie\u00dfleder Jun.",
    "wof:placetype":"venue"
},
  "geometry": {"coordinates":[11.553036,47.932812],"type":"Point"}
}