{
  "type": "Feature",
  "properties": {
    "iso:country":"DE",
    "sg:address":"Bahnhofstr. 35",
    "sg:city":"Lohne",
    "sg:postcode":"49393",
    "sg:province":"Niedersachsen",
    "wof:name":"Dewico Inh. Jutta Meistermann E. K.",
    "wof:placetype":"venue"
},
  "geometry": {"coordinates":[8.2277917862,52.664352417],"type":"Point"}
}