{
  "type": "Feature",
  "properties": {
    "iso:country":"DE",
    "sg:address":"Hedwig-Heyl-Str. 35",
    "sg:city":"Oldenburg",
    "sg:phone":"+49 441/62359",
    "sg:postcode":"26127",
    "sg:province":"Niedersachsen",
    "wof:name":"Vvs Holding Vertriebs- Verwaltungs- Und Service Gmbh",
    "wof:placetype":"venue"
},
  "geometry": {"coordinates":[8.1959018707,53.1615142822],"type":"Point"}
}