{
  "type": "Feature",
  "properties": {
    "iso:country":"DE",
    "sg:address":"Kappenberger Damm 88",
    "sg:city":"M\u00fcnster",
    "sg:postcode":"48151",
    "sg:province":"Nordrhein-Westfalen",
    "wof:name":"Blumenhaus Monika Schrieverhoff E. K.",
    "wof:placetype":"venue"
},
  "geometry": {"coordinates":[7.608518,51.935745],"type":"Point"}
}