{
  "type": "Feature",
  "properties": {
    "iso:country":"DE",
    "sg:address":"Pfingstberg 28",
    "sg:city":"Hamburg",
    "sg:phone":"+49 40/72697802",
    "sg:postcode":"21029",
    "sg:province":"Hamburg",
    "wof:name":"Somi Sales Office Maritime International Gmbh",
    "wof:placetype":"venue"
},
  "geometry": {"coordinates":[10.227963,53.488575],"type":"Point"}
}