{
  "type": "Feature",
  "properties": {
    "iso:country":"DE",
    "sg:address":"Armsener Dorfstr. 45",
    "sg:city":"Kirchlinteln",
    "sg:phone":"+49 4238/1338",
    "sg:postcode":"27308",
    "sg:province":"Niedersachsen",
    "wof:name":"J. Meyer",
    "wof:placetype":"venue"
},
  "geometry": {"coordinates":[9.34189,52.893021],"type":"Point"}
}