{
  "type": "Feature",
  "properties": {
    "iso:country":"DE",
    "sg:address":"Vogtareuth",
    "sg:city":"Vogtareuth",
    "sg:phone":"+49 7173/18090",
    "sg:postcode":"83569",
    "sg:province":"Bayern",
    "wof:name":"Raiffeisenbank Rosenstein Eg",
    "wof:placetype":"venue"
},
  "geometry": {"coordinates":[9.934625,48.791149],"type":"Point"}
}