{
  "type": "Feature",
  "properties": {
    "iso:country":"DE",
    "sg:address":"Am Vogelbusch 3",
    "sg:city":"Nottuln",
    "sg:phone":"+49 2502/9395",
    "sg:postcode":"48301",
    "sg:province":"Nordrhein-Westfalen",
    "wof:name":"J\u00e4ger Reisen",
    "wof:placetype":"venue"
},
  "geometry": {"coordinates":[7.3544192314,51.9282302856],"type":"Point"}
}