{
  "type": "Feature",
  "properties": {
    "iso:country":"DE",
    "sg:address":"Rosenstr. 4",
    "sg:city":"M\u00fcnster",
    "sg:phone":"+49 251/47622",
    "sg:postcode":"48143",
    "sg:province":"Nordrhein-Westfalen",
    "wof:name":"Gr\u00fcn & Form",
    "wof:placetype":"venue"
},
  "geometry": {"coordinates":[7.622592926,51.9651565552],"type":"Point"}
}