{
  "type": "Feature",
  "properties": {
    "iso:country":"DE",
    "sg:address":"Peyerstr. 31",
    "sg:city":"N\u00fcrnberg",
    "sg:phone":"+49 911/317761",
    "sg:postcode":"90429",
    "sg:province":"Bayern",
    "wof:name":"Wolfgang M\u00f6ckl",
    "wof:placetype":"venue"
},
  "geometry": {"coordinates":[11.0420026779,49.4582901001],"type":"Point"}
}