{
  "type": "Feature",
  "properties": {
    "iso:country":"DE",
    "sg:address":"Hasenweiler 37",
    "sg:city":"Horgenzell",
    "sg:phone":"+49 7504/7172",
    "sg:postcode":"88263",
    "sg:province":"Baden-W\u00fcrttemberg",
    "wof:name":"A. Knoll",
    "wof:placetype":"venue"
},
  "geometry": {"coordinates":[9.4654397964,47.8359107971],"type":"Point"}
}