{
  "type": "Feature",
  "properties": {
    "iso:country":"DE",
    "sg:address":"Stader Str. 12",
    "sg:city":"Wingst",
    "sg:phone":"+49 4778/811051",
    "sg:postcode":"21789",
    "sg:province":"Niedersachsen",
    "wof:name":"Rolf-dieter Stein",
    "wof:placetype":"venue"
},
  "geometry": {"coordinates":[9.1048202515,53.7253913879],"type":"Point"}
}