{
  "type": "Feature",
  "properties": {
    "iso:country":"DE",
    "sg:address":"Buchenweg 249",
    "sg:city":"Oberhausen",
    "sg:phone":"+49 208/677757",
    "sg:postcode":"46147",
    "sg:province":"Nordrhein-Westfalen",
    "wof:name":"Judith Heckmann",
    "wof:placetype":"venue"
},
  "geometry": {"coordinates":[6.842308,51.551327],"type":"Point"}
}