{
  "type": "Feature",
  "properties": {
    "iso:country":"DE",
    "sg:address":"Wartlaustr. 5",
    "sg:city":"Neubrandenburg",
    "sg:phone":"+49 395/5822907",
    "sg:postcode":"17033",
    "sg:province":"Mecklenburg-Vorpommern",
    "wof:name":"Blumen Paradies Gmbh",
    "wof:placetype":"venue"
},
  "geometry": {"coordinates":[13.263689,53.557579],"type":"Point"}
}