{
  "type": "Feature",
  "properties": {
    "iso:country":"DE",
    "sg:address":"Am Wiesenbusch 2",
    "sg:city":"Gladbeck",
    "sg:phone":"+49 2043",
    "sg:postcode":"45966",
    "sg:province":"Nordrhein-Westfalen",
    "wof:name":"Cylex Informationstechnik Gmbh",
    "wof:placetype":"venue"
},
  "geometry": {"coordinates":[6.9386701584,51.5716133118],"type":"Point"}
}