{
  "type": "Feature",
  "properties": {
    "iso:country":"DE",
    "sg:address":"Riezlerweg 9a",
    "sg:city":"M\u00fcnchen",
    "sg:phone":"+49 89/1407265",
    "sg:postcode":"80997",
    "sg:province":"Bayern",
    "wof:name":"Wilhelm H\u00f6hning",
    "wof:placetype":"venue"
},
  "geometry": {"coordinates":[11.486383,48.180462],"type":"Point"}
}