{
  "type": "Feature",
  "properties": {
    "iso:country":"DE",
    "sg:address":"R\u00f6mhilder Str. 29",
    "sg:city":"Hildburghausen",
    "sg:postcode":"98646",
    "sg:province":"Th\u00fcringen",
    "wof:name":"Eurospar",
    "wof:placetype":"venue"
},
  "geometry": {"coordinates":[10.7073278427,50.4202728271],"type":"Point"}
}