{
  "type": "Feature",
  "properties": {
    "iso:country":"DE",
    "sg:address":"Truchtlachinger Str. 2",
    "sg:city":"Chieming",
    "sg:phone":"+49 8664/1833",
    "sg:postcode":"83339",
    "sg:province":"Bayern",
    "wof:name":"Billinger Landw.lagerhaus",
    "wof:placetype":"venue"
},
  "geometry": {"coordinates":[12.538964,47.907856],"type":"Point"}
}