{
  "type": "Feature",
  "properties": {
    "iso:country":"DE",
    "sg:address":"Zum Br\u00f6hn 2",
    "sg:city":"Wathlingen",
    "sg:phone":"+49 5144/92244",
    "sg:postcode":"29339",
    "sg:province":"Niedersachsen",
    "wof:name":"G\u00fcnter Zimmer",
    "wof:placetype":"venue"
},
  "geometry": {"coordinates":[10.1413459778,52.5280380249],"type":"Point"}
}