{
  "type": "Feature",
  "properties": {
    "iso:country":"DE",
    "sg:address":"Lindenallee 23",
    "sg:city":"Meisenheim",
    "sg:phone":"+49 6753/2467",
    "sg:postcode":"55590",
    "sg:province":"Rheinland-Pfalz",
    "wof:name":"Alois Barth",
    "wof:placetype":"venue"
},
  "geometry": {"coordinates":[7.6686868668,49.7070579529],"type":"Point"}
}