{
  "type": "Feature",
  "properties": {
    "iso:country":"DE",
    "sg:address":"Dingworthstr. 10",
    "sg:city":"Hildesheim",
    "sg:phone":"+49 5121/27505",
    "sg:postcode":"31137",
    "sg:province":"Niedersachsen",
    "wof:name":"Moritz-stube",
    "wof:placetype":"venue"
},
  "geometry": {"coordinates":[9.93009758,52.1493453979],"type":"Point"}
}