{
  "type": "Feature",
  "properties": {
    "iso:country":"DE",
    "sg:address":"Abtenham 5a",
    "sg:city":"Tittmoning",
    "sg:phone":"+49 8683/1494",
    "sg:postcode":"84529",
    "sg:province":"Bayern",
    "wof:name":"Johann F\u00f6rg",
    "wof:placetype":"venue"
},
  "geometry": {"coordinates":[12.789807,48.026054],"type":"Point"}
}