{
  "type": "Feature",
  "properties": {
    "iso:country":"DE",
    "sg:address":"Loskyllerweg 12",
    "sg:city":"Preist",
    "sg:phone":"+49 6562/8585",
    "sg:postcode":"54664",
    "sg:province":"Rheinland-Pfalz",
    "wof:name":"Klaus Scheiern",
    "wof:placetype":"venue"
},
  "geometry": {"coordinates":[6.626545,49.908585],"type":"Point"}
}