{
  "type": "Feature",
  "properties": {
    "iso:country":"DE",
    "sg:address":"Zeithstr. 111",
    "sg:city":"Neunkirchen-Seelscheid",
    "sg:phone":"+49 2247/70012",
    "sg:postcode":"53819",
    "sg:province":"Nordrhein-Westfalen",
    "wof:name":"Brs Banken Reise Service Gmbh",
    "wof:placetype":"venue"
},
  "geometry": {"coordinates":[7.3220238686,50.8692321777],"type":"Point"}
}