{
  "type": "Feature",
  "properties": {
    "iso:country":"DE",
    "sg:address":"Dr.-Martin-Luther-Platz 3",
    "sg:city":"Bad Windsheim",
    "sg:phone":"+49 9841/2118",
    "sg:postcode":"91438",
    "sg:province":"Bayern",
    "wof:name":"Dekanat Bad Windsheim",
    "wof:placetype":"venue"
},
  "geometry": {"coordinates":[10.4165258408,49.5023803711],"type":"Point"}
}