{
  "type": "Feature",
  "properties": {
    "iso:country":"DE",
    "sg:address":"Am Waldfriedhof 2",
    "sg:city":"Leonberg",
    "sg:phone":"+49 7152/977390",
    "sg:postcode":"71229",
    "sg:province":"Baden-W\u00fcrttemberg",
    "wof:name":"C. Schreiner",
    "wof:placetype":"venue"
},
  "geometry": {"coordinates":[9.04154,48.790276],"type":"Point"}
}