{
  "type": "Feature",
  "properties": {
    "iso:country":"DE",
    "sg:address":"Franziskanerplatz 2",
    "sg:city":"W\u00fcrzburg",
    "sg:phone":"+49 931/35630",
    "sg:postcode":"97070",
    "sg:province":"Bayern",
    "wof:name":"Hotel Franziskaner W\u00fcrzburg E. K.",
    "wof:placetype":"venue"
},
  "geometry": {"coordinates":[9.9317073822,49.7913246155],"type":"Point"}
}