{
  "type": "Feature",
  "properties": {
    "iso:country":"DE",
    "sg:address":"Berliner Allee 88",
    "sg:city":"Hagen",
    "sg:phone":"+49 2334/54546",
    "sg:postcode":"58119",
    "sg:province":"Nordrhein-Westfalen",
    "wof:name":"Toko Institut E. V.",
    "wof:placetype":"venue"
},
  "geometry": {"coordinates":[7.5830087662,51.3684272766],"type":"Point"}
}