{
  "type": "Feature",
  "properties": {
    "iso:country":"DE",
    "sg:address":"An de Welt 45",
    "sg:city":"Krefeld",
    "sg:phone":"+49 2151/303172",
    "sg:postcode":"47807",
    "sg:province":"Nordrhein-Westfalen",
    "wof:name":"Horst Giesing",
    "wof:placetype":"venue"
},
  "geometry": {"coordinates":[6.5822691917,51.3013916016],"type":"Point"}
}