{
  "type": "Feature",
  "properties": {
    "iso:country":"DE",
    "sg:address":"Essiger Str. 7",
    "sg:city":"Swisttal",
    "sg:phone":"+49 2255/4439",
    "sg:postcode":"53913",
    "sg:province":"Nordrhein-Westfalen",
    "wof:name":"J. Schmitz Inh. M. Wallrath",
    "wof:placetype":"venue"
},
  "geometry": {"coordinates":[6.882318,50.649292],"type":"Point"}
}