{
  "type": "Feature",
  "properties": {
    "iso:country":"DE",
    "sg:address":"Industriestr. 2",
    "sg:city":"Waldems",
    "sg:phone":"+49 6087/2359",
    "sg:postcode":"65529",
    "sg:province":"Hessen",
    "wof:name":"Bernhard Krupp Steinmetzbetrieb",
    "wof:placetype":"venue"
},
  "geometry": {"coordinates":[8.3510799408,50.2757530212],"type":"Point"}
}