{
  "type": "Feature",
  "properties": {
    "iso:country":"DE",
    "sg:address":"Adlerstr. 42",
    "sg:city":"Stutensee",
    "sg:phone":"+49 7249/3439",
    "sg:postcode":"76297",
    "sg:province":"Baden-W\u00fcrttemberg",
    "wof:name":"Franz Schneider",
    "wof:placetype":"venue"
},
  "geometry": {"coordinates":[8.514182,49.113529],"type":"Point"}
}