{
  "type": "Feature",
  "properties": {
    "iso:country":"DE",
    "sg:address":"Schillerstr. 7",
    "sg:city":"Gaildorf",
    "sg:phone":"+49 7971/5753",
    "sg:postcode":"74405",
    "sg:province":"Baden-W\u00fcrttemberg",
    "wof:name":"W. Eichele",
    "wof:placetype":"venue"
},
  "geometry": {"coordinates":[9.7735214233,48.9988098145],"type":"Point"}
}