{
  "type": "Feature",
  "properties": {
    "iso:country":"DE",
    "sg:address":"Schmiedgasse 3",
    "sg:city":"Dittelbrunn",
    "sg:phone":"+49 9725/1250",
    "sg:postcode":"97456",
    "sg:province":"Bayern",
    "wof:name":"Fissneider Gmbh",
    "wof:placetype":"venue"
},
  "geometry": {"coordinates":[10.221608,50.074406],"type":"Point"}
}