{
  "type": "Feature",
  "properties": {
    "iso:country":"DE",
    "sg:address":"Alpenstr. 62",
    "sg:city":"Ulm",
    "sg:phone":"+49 731/63152",
    "sg:postcode":"89075",
    "sg:province":"Baden-W\u00fcrttemberg",
    "wof:name":"Wolfgang Schlunck Schriftsachverst\u00e4ndiger",
    "wof:placetype":"venue"
},
  "geometry": {"coordinates":[9.9906635284,48.4102134705],"type":"Point"}
}