{
  "type": "Feature",
  "properties": {
    "iso:country":"DE",
    "sg:address":"Goethestr. 3",
    "sg:city":"M\u00f6tzingen",
    "sg:phone":"+49 7452/7371",
    "sg:postcode":"71159",
    "sg:province":"Baden-W\u00fcrttemberg",
    "wof:name":"Manfred Kieschke Ingenieur",
    "wof:placetype":"venue"
},
  "geometry": {"coordinates":[8.7794971466,48.5310935974],"type":"Point"}
}