{
  "type": "Feature",
  "properties": {
    "iso:country":"DE",
    "sg:address":"Schlegldorf",
    "sg:city":"Lenggries",
    "sg:phone":"+49 8042/3754",
    "sg:postcode":"83661",
    "sg:province":"Bayern",
    "wof:name":"Anton Resenberger Malereibetrieb",
    "wof:placetype":"venue"
},
  "geometry": {"coordinates":[11.559708,47.694958],"type":"Point"}
}