{
  "type": "Feature",
  "properties": {
    "iso:country":"DE",
    "sg:address":"Sopericher Str. 70",
    "sg:city":"Waldfeucht",
    "sg:phone":"+49 2452/88917",
    "sg:postcode":"52525",
    "sg:province":"Nordrhein-Westfalen",
    "wof:name":"Johann J\u00f6rissen",
    "wof:placetype":"venue"
},
  "geometry": {"coordinates":[6.0357089043,51.0916786194],"type":"Point"}
}