{
  "type": "Feature",
  "properties": {
    "iso:country":"DE",
    "sg:address":"Hoftohorn 13",
    "sg:city":"Zeven",
    "sg:phone":"+49 4281/1362",
    "sg:postcode":"27404",
    "sg:province":"Niedersachsen",
    "wof:name":"Peter Martens",
    "wof:placetype":"venue"
},
  "geometry": {"coordinates":[9.282109,53.283966],"type":"Point"}
}