{
  "type": "Feature",
  "properties": {
    "iso:country":"DE",
    "sg:address":"Langenberg 16",
    "sg:city":"Haren",
    "sg:postcode":"49733",
    "sg:province":"Niedersachsen",
    "wof:name":"Deuling Kart-bahn Gmbh",
    "wof:placetype":"venue"
},
  "geometry": {"coordinates":[7.152504921,52.7920227051],"type":"Point"}
}