{
  "type": "Feature",
  "properties": {
    "iso:country":"DE",
    "sg:address":"Mainzer Str. 172",
    "sg:city":"Bonn",
    "sg:phone":"+49 228/342798",
    "sg:postcode":"53179",
    "sg:province":"Nordrhein-Westfalen",
    "wof:name":"Hotel Josef Becker",
    "wof:placetype":"venue"
},
  "geometry": {"coordinates":[7.1914510727,50.6613388062],"type":"Point"}
}