{
  "type": "Feature",
  "properties": {
    "iso:country":"DE",
    "sg:address":"D\u00fcstere Str. 7",
    "sg:city":"G\u00f6ttingen",
    "sg:phone":"+49 551/48069",
    "sg:postcode":"37073",
    "sg:province":"Niedersachsen",
    "wof:name":"Imbi\u00df Imparator",
    "wof:placetype":"venue"
},
  "geometry": {"coordinates":[9.9334096909,51.5311851501],"type":"Point"}
}