{
  "type": "Feature",
  "properties": {
    "iso:country":"DE",
    "sg:address":"Dr.-Muschak-Str. 10",
    "sg:city":"Kaufbeuren",
    "sg:phone":"+49 8341/65900",
    "sg:postcode":"87600",
    "sg:province":"Bayern",
    "wof:name":"Martina Trautmann Stahl- Und Normalienhandel",
    "wof:placetype":"venue"
},
  "geometry": {"coordinates":[10.631518,47.917343],"type":"Point"}
}