{
  "type": "Feature",
  "properties": {
    "iso:country":"DE",
    "sg:address":"Rudolf Diesel Str. 18",
    "sg:city":"Singen",
    "sg:phone":"+49 4977/3169424",
    "sg:postcode":"78224",
    "sg:province":"Baden-W\u00fcrttemberg",
    "wof:name":"Grau Galvanotechnik Galvanisierte Bauelemente F\u00fcr Elektronis",
    "wof:placetype":"venue"
},
  "geometry": {"coordinates":[8.8846054077,47.7557144165],"type":"Point"}
}