{
  "type": "Feature",
  "properties": {
    "iso:country":"DE",
    "sg:address":"L\u00f6wenstra\u00dfe 11",
    "sg:city":"Dresden",
    "sg:phone":"+49 351/8105355",
    "sg:postcode":"01099",
    "sg:province":"Sachsen",
    "wof:name":"Urlaubs- Und Reisevermittlungsagentur Dresden",
    "wof:placetype":"venue"
},
  "geometry": {"coordinates":[13.75741,51.063133],"type":"Point"}
}