{
  "type": "Feature",
  "properties": {
    "iso:country":"DE",
    "sg:address":"Sch\u00f6nb\u00fcchstr. 14",
    "sg:city":"Sasbachwalden",
    "sg:phone":"+49 7841/22360",
    "sg:postcode":"77887",
    "sg:province":"Baden-W\u00fcrttemberg",
    "wof:name":"Friedrich Doll",
    "wof:placetype":"venue"
},
  "geometry": {"coordinates":[8.1400146484,48.602645874],"type":"Point"}
}