{
  "type": "Feature",
  "properties": {
    "iso:country":"DE",
    "sg:address":"Westerwaldstr. 10",
    "sg:city":"R\u00fcsselsheim",
    "sg:postcode":"65428",
    "sg:province":"Hessen",
    "wof:name":"Effizienz Niedrigenergie-h\u00e4user",
    "wof:placetype":"venue"
},
  "geometry": {"coordinates":[8.456841,49.960419],"type":"Point"}
}