{
  "type": "Feature",
  "properties": {
    "iso:country":"DE",
    "sg:address":"Limmerstr. 58",
    "sg:city":"Hannover",
    "sg:phone":"+49 511/2151140",
    "sg:postcode":"30451",
    "sg:province":"Niedersachsen",
    "wof:name":"Wingert",
    "wof:placetype":"venue"
},
  "geometry": {"coordinates":[9.7062959671,52.3740234375],"type":"Point"}
}