{
  "type": "Feature",
  "properties": {
    "iso:country":"DE",
    "sg:address":"Windthorststr. 11",
    "sg:city":"Halberstadt",
    "sg:phone":"+49 3941/442675",
    "sg:postcode":"38820",
    "sg:province":"Sachsen-Anhalt",
    "wof:name":"Dr. Med. Gisela Lotz",
    "wof:placetype":"venue"
},
  "geometry": {"coordinates":[11.053737,51.885708],"type":"Point"}
}