{
  "type": "Feature",
  "properties": {
    "iso:country":"DE",
    "sg:address":"Regensburger Str. 14",
    "sg:city":"Wernberg-K\u00f6blitz",
    "sg:phone":"+49 9604/3425",
    "sg:postcode":"92533",
    "sg:province":"Bayern",
    "wof:name":"Gmk Elektronic Design Gmbh",
    "wof:placetype":"venue"
},
  "geometry": {"coordinates":[12.162899971,49.5380096436],"type":"Point"}
}