{
  "type": "Feature",
  "properties": {
    "iso:country":"DE",
    "sg:address":"Hahnengasse 2",
    "sg:city":"Mayen",
    "sg:phone":"+49 2651/902349",
    "sg:postcode":"56727",
    "sg:province":"Rheinland-Pfalz",
    "wof:name":"Bbv Mobil",
    "wof:placetype":"venue"
},
  "geometry": {"coordinates":[7.2215118408,50.329208374],"type":"Point"}
}