{
  "type": "Feature",
  "properties": {
    "iso:country":"DE",
    "sg:address":"Berliner Str. 135",
    "sg:city":"Berlin",
    "sg:phone":"+49 30/4048081",
    "sg:postcode":"13467",
    "sg:province":"Berlin",
    "wof:name":"Igo Ingenieurgemeinschaft Ohlwein Gmbh",
    "wof:placetype":"venue"
},
  "geometry": {"coordinates":[13.3167028427,52.6145591736],"type":"Point"}
}