{
  "type": "Feature",
  "properties": {
    "iso:country":"DE",
    "sg:address":"Karlstr. 1",
    "sg:city":"Tamm",
    "sg:phone":"+49 7141/207000",
    "sg:postcode":"71732",
    "sg:province":"Baden-W\u00fcrttemberg",
    "wof:name":"Peter Meyle",
    "wof:placetype":"venue"
},
  "geometry": {"coordinates":[9.120757,48.920467],"type":"Point"}
}