{
  "type": "Feature",
  "properties": {
    "iso:country":"DE",
    "sg:address":"Kirchgasse 4",
    "sg:city":"Giengen",
    "sg:phone":"+49 7322/5117",
    "sg:postcode":"89537",
    "sg:province":"Baden-W\u00fcrttemberg",
    "wof:name":"Karl Mayer",
    "wof:placetype":"venue"
},
  "geometry": {"coordinates":[10.2448215485,48.6207733154],"type":"Point"}
}