{
  "type": "Feature",
  "properties": {
    "iso:country":"DE",
    "sg:address":"Edinburger Str. 78",
    "sg:city":"Berlin",
    "sg:phone":"+49 30/4521054",
    "sg:postcode":"13349",
    "sg:province":"Berlin",
    "wof:name":"Ev. Pfarramt Kornelius-gemeinde",
    "wof:placetype":"venue"
},
  "geometry": {"coordinates":[13.343328476,52.5589485168],"type":"Point"}
}