{
  "type": "Feature",
  "properties": {
    "iso:country":"DE",
    "sg:address":"An der Sandkull 81a",
    "sg:city":"Moers",
    "sg:phone":"+49 2841/984016",
    "sg:postcode":"47445",
    "sg:province":"Nordrhein-Westfalen",
    "wof:name":"Medienpartner Erhard Thueringer",
    "wof:placetype":"venue"
},
  "geometry": {"coordinates":[6.598784,51.492336],"type":"Point"}
}