{
  "type": "Feature",
  "properties": {
    "iso:country":"DE",
    "sg:address":"Dresdner Str. 44",
    "sg:city":"Neumarkt",
    "sg:phone":"+49 9181/488350",
    "sg:postcode":"92318",
    "sg:province":"Bayern",
    "wof:name":"Egbert Schwab",
    "wof:placetype":"venue"
},
  "geometry": {"coordinates":[11.4742689133,49.2961044312],"type":"Point"}
}