{
  "type": "Feature",
  "properties": {
    "iso:country":"DE",
    "sg:address":"Dammer Str. 11",
    "sg:city":"Damme",
    "sg:phone":"+49 5491/2367",
    "sg:postcode":"49401",
    "sg:province":"Niedersachsen",
    "wof:name":"Gastst\u00e4tte Franz Broermann",
    "wof:placetype":"venue"
},
  "geometry": {"coordinates":[8.2335996628,52.5134086609],"type":"Point"}
}