{
  "type": "Feature",
  "properties": {
    "iso:country":"DE",
    "sg:address":"Bl\u00fcmgesgrundstr. 3",
    "sg:city":"Gelnhausen",
    "sg:phone":"+49 6051/69411",
    "sg:postcode":"63571",
    "sg:province":"Hessen",
    "wof:name":"F. Und W. K\u00fcster",
    "wof:placetype":"venue"
},
  "geometry": {"coordinates":[9.159917,50.183167],"type":"Point"}
}