{
  "type": "Feature",
  "properties": {
    "iso:country":"DE",
    "sg:address":"Benzstr. 5",
    "sg:city":"Schwaikheim",
    "sg:phone":"+49 7195/5031",
    "sg:postcode":"71409",
    "sg:province":"Baden-W\u00fcrttemberg",
    "wof:name":"Ett Ersatzteil-technik Gmbh",
    "wof:placetype":"venue"
},
  "geometry": {"coordinates":[9.35401,48.866329],"type":"Point"}
}