{
  "type": "Feature",
  "properties": {
    "iso:country":"DE",
    "sg:address":"Marktstr. 18",
    "sg:city":"Horb",
    "sg:phone":"+49 7451/623616",
    "sg:postcode":"72160",
    "sg:province":"Baden-W\u00fcrttemberg",
    "wof:name":"Restaurant Marktstock",
    "wof:placetype":"venue"
},
  "geometry": {"coordinates":[8.6902952194,48.4449043274],"type":"Point"}
}