{
  "type": "Feature",
  "properties": {
    "iso:country":"DE",
    "sg:address":"K\u00f6lner Str. 41",
    "sg:city":"Siegen",
    "sg:phone":"+49 271/356279",
    "sg:postcode":"57072",
    "sg:province":"Nordrhein-Westfalen",
    "wof:name":"Gastst\u00e4tte Taverne",
    "wof:placetype":"venue"
},
  "geometry": {"coordinates":[8.0219621658,50.8744621277],"type":"Point"}
}