{
  "type": "Feature",
  "properties": {
    "iso:country":"DE",
    "sg:address":"Grambker Heerstr. 137",
    "sg:city":"Bremen",
    "sg:phone":"+49 421/642986",
    "sg:postcode":"28719",
    "sg:province":"Bremen",
    "wof:name":"Am Waldrand",
    "wof:placetype":"venue"
},
  "geometry": {"coordinates":[8.7102947235,53.1509628296],"type":"Point"}
}