{
  "type": "Feature",
  "properties": {
    "iso:country":"DE",
    "sg:address":"G\u00e4rtnerstr. 28",
    "sg:city":"Elmshorn",
    "sg:phone":"+49 4121/3081",
    "sg:postcode":"25335",
    "sg:province":"Schleswig-Holstein",
    "wof:name":"G & K Meyer-heizung Gmbh",
    "wof:placetype":"venue"
},
  "geometry": {"coordinates":[9.6536359787,53.7584190369],"type":"Point"}
}