{
  "type": "Feature",
  "properties": {
    "iso:country":"DE",
    "sg:address":"Rolandstr. 6",
    "sg:city":"Wedel",
    "sg:phone":"+49 4103/81193",
    "sg:postcode":"22880",
    "sg:province":"Schleswig-Holstein",
    "wof:name":"Karin Neuhaus",
    "wof:placetype":"venue"
},
  "geometry": {"coordinates":[9.6963787079,53.5844078064],"type":"Point"}
}