{
  "type": "Feature",
  "properties": {
    "iso:country":"DE",
    "sg:address":"Friedrich Bergius Str.17",
    "sg:city":"Wiesbaden",
    "sg:phone":"+49 4961/165585",
    "sg:postcode":"65203",
    "sg:province":"Hessen",
    "wof:name":"Hansa Flex Gmbh",
    "wof:placetype":"venue"
},
  "geometry": {"coordinates":[8.220036,50.049679],"type":"Point"}
}