{
  "type": "Feature",
  "properties": {
    "iso:country":"DE",
    "sg:address":"W\u00f6rnbrunner Str. 46",
    "sg:city":"Gr\u00fcnwald",
    "sg:postcode":"82031",
    "sg:province":"Bayern",
    "wof:name":"Tdc Teledata Communication Handels Gmbh",
    "wof:placetype":"venue"
},
  "geometry": {"coordinates":[11.5360059738,48.0406417847],"type":"Point"}
}