{
  "type": "Feature",
  "properties": {
    "iso:country":"DE",
    "sg:address":"Berlepschstr. 63",
    "sg:city":"Berlin",
    "sg:postcode":"14165",
    "sg:province":"Berlin",
    "wof:name":"Flynux Gmbh",
    "wof:placetype":"venue"
},
  "geometry": {"coordinates":[13.2458877563,52.4261398315],"type":"Point"}
}