{
  "type": "Feature",
  "properties": {
    "iso:country":"DE",
    "sg:address":"Hauptstra\u00dfe 64",
    "sg:city":"Bad Bodendorf",
    "sg:phone":"+49 2642/5260",
    "sg:postcode":"53489",
    "sg:province":"Rheinland-Pfalz",
    "wof:name":"Kranzcreativ - Beschriftung, Werbetechnik & Design",
    "wof:placetype":"venue"
},
  "geometry": {"coordinates":[7.221494,50.558456],"type":"Point"}
}