{
  "type": "Feature",
  "properties": {
    "iso:country":"DE",
    "sg:address":"Am M\u00fchlbach 3",
    "sg:city":"Bischofsheim",
    "sg:phone":"+49 9772/503",
    "sg:postcode":"97653",
    "sg:province":"Bayern",
    "wof:name":"Max Popeskul",
    "wof:placetype":"venue"
},
  "geometry": {"coordinates":[10.006206,50.401711],"type":"Point"}
}