{
  "type": "Feature",
  "properties": {
    "iso:country":"DE",
    "sg:address":"Moosbauerplatz 1",
    "sg:city":"Bad Endorf",
    "sg:phone":"+49 8053/3330",
    "sg:postcode":"83093",
    "sg:province":"Bayern",
    "wof:name":"Parf\u00fcmerie Angerer",
    "wof:placetype":"venue"
},
  "geometry": {"coordinates":[12.301908,47.905746],"type":"Point"}
}