{
  "type": "Feature",
  "properties": {
    "iso:country":"DE",
    "sg:address":"Oberdorfstr. 53",
    "sg:city":"Bammental",
    "sg:phone":"+49 6223/40671",
    "sg:postcode":"69245",
    "sg:province":"Baden-W\u00fcrttemberg",
    "wof:name":"Stadt Athen",
    "wof:placetype":"venue"
},
  "geometry": {"coordinates":[8.7798862457,49.3610343933],"type":"Point"}
}