{
  "type": "Feature",
  "properties": {
    "iso:country":"DE",
    "sg:address":"Marburger Str. 200",
    "sg:city":"Gie\u00dfen",
    "sg:phone":"+49 641/51402",
    "sg:postcode":"35396",
    "sg:province":"Hessen",
    "wof:name":"Restaurante Pizzeria Karlsruh",
    "wof:placetype":"venue"
},
  "geometry": {"coordinates":[8.6930732727,50.604095459],"type":"Point"}
}