{
  "type": "Feature",
  "properties": {
    "iso:country":"DE",
    "sg:address":"Strandstr.",
    "sg:city":"Malchow",
    "sg:phone":"+49 39932/88185",
    "sg:postcode":"17213",
    "sg:province":"Mecklenburg-Vorpommern",
    "wof:name":"Strandbad Am Fleesensee",
    "wof:placetype":"venue"
},
  "geometry": {"coordinates":[12.4374818802,53.4850959778],"type":"Point"}
}