{
  "type": "Feature",
  "properties": {
    "iso:country":"DE",
    "sg:address":"Suchsdorfer Weg 120",
    "sg:city":"Kronshagen",
    "sg:phone":"+49 431/313348",
    "sg:postcode":"24119",
    "sg:province":"Schleswig-Holstein",
    "wof:name":"Werner Horn",
    "wof:placetype":"venue"
},
  "geometry": {"coordinates":[10.081147,54.340839],"type":"Point"}
}