{
  "type": "Feature",
  "properties": {
    "iso:country":"DE",
    "sg:address":"Rugbyring 87",
    "sg:city":"R\u00fcsselsheim",
    "sg:postcode":"65428",
    "sg:province":"Hessen",
    "wof:name":"Aldi Gmbh & Co. Kg",
    "wof:placetype":"venue"
},
  "geometry": {"coordinates":[8.424290657,49.9962692261],"type":"Point"}
}