{
  "type": "Feature",
  "properties": {
    "iso:country":"DE",
    "sg:address":"Im M\u00fchlfeld 32",
    "sg:city":"Crailsheim",
    "sg:phone":"+49 7951/6616",
    "sg:postcode":"74564",
    "sg:province":"Baden-W\u00fcrttemberg",
    "wof:name":"Huber Gmbh",
    "wof:placetype":"venue"
},
  "geometry": {"coordinates":[10.132204,49.139835],"type":"Point"}
}