{
  "type": "Feature",
  "properties": {
    "iso:country":"DE",
    "sg:address":"Winckelmannstr. 26",
    "sg:city":"Wuppertal",
    "sg:phone":"+49 202/556482",
    "sg:postcode":"42287",
    "sg:province":"Nordrhein-Westfalen",
    "wof:name":"Horst Saddai",
    "wof:placetype":"venue"
},
  "geometry": {"coordinates":[7.1973280907,51.2449417114],"type":"Point"}
}