{
  "type": "Feature",
  "properties": {
    "iso:country":"DE",
    "sg:address":"Berner Allee 78",
    "sg:city":"Hamburg",
    "sg:phone":"+49 40/6448921",
    "sg:postcode":"22159",
    "sg:province":"Hamburg",
    "wof:name":"Alwin Henning",
    "wof:placetype":"venue"
},
  "geometry": {"coordinates":[10.12053,53.62635],"type":"Point"}
}