{
  "type": "Feature",
  "properties": {
    "iso:country":"DE",
    "sg:address":"Markgrafstr 5",
    "sg:city":"Hannover",
    "sg:phone":"+49 511/9798690",
    "sg:postcode":"30419",
    "sg:province":"Niedersachsen",
    "wof:name":"Consoft Gmbh",
    "wof:placetype":"venue"
},
  "geometry": {"coordinates":[9.6827955246,52.3933982849],"type":"Point"}
}