{
  "type": "Feature",
  "properties": {
    "iso:country":"DE",
    "sg:address":"Karl-Liebknecht-Str. 113",
    "sg:city":"Bernsbach",
    "sg:phone":"+49 3774/61182",
    "sg:postcode":"08315",
    "sg:province":"Sachsen",
    "wof:name":"Roland Detzner",
    "wof:placetype":"venue"
},
  "geometry": {"coordinates":[12.7564668655,50.5823402405],"type":"Point"}
}