{
  "type": "Feature",
  "properties": {
    "iso:country":"DE",
    "sg:address":"H\u00fcxstr. 17",
    "sg:city":"L\u00fcbeck",
    "sg:phone":"+49 451/77770",
    "sg:postcode":"23552",
    "sg:province":"Schleswig-Holstein",
    "wof:name":"Hut-moll Gmbh",
    "wof:placetype":"venue"
},
  "geometry": {"coordinates":[10.686719,53.866566],"type":"Point"}
}