{
  "type": "Feature",
  "properties": {
    "iso:country":"DE",
    "sg:address":"Weingasse 7",
    "sg:city":"Triftern",
    "sg:phone":"+49 8562/1545",
    "sg:postcode":"84371",
    "sg:province":"Bayern",
    "wof:name":"Wilhelm Duschl",
    "wof:placetype":"venue"
},
  "geometry": {"coordinates":[13.0062141418,48.3959846497],"type":"Point"}
}