{
  "type": "Feature",
  "properties": {
    "iso:country":"DE",
    "sg:address":"Schlo\u00dfstr. 64",
    "sg:city":"Wuppertal",
    "sg:phone":"+49 202/81476",
    "sg:postcode":"42285",
    "sg:province":"Nordrhein-Westfalen",
    "wof:name":"R. Santowski",
    "wof:placetype":"venue"
},
  "geometry": {"coordinates":[7.182413,51.261578],"type":"Point"}
}