{
  "type": "Feature",
  "properties": {
    "iso:country":"DE",
    "sg:address":"Trieb",
    "sg:city":"Lichtenwald",
    "sg:phone":"+49 7153/41538",
    "sg:postcode":"73669",
    "sg:province":"Baden-W\u00fcrttemberg",
    "wof:name":"Naturfreundehaus Schurwaldhaus",
    "wof:placetype":"venue"
},
  "geometry": {"coordinates":[9.4794197083,48.7278594971],"type":"Point"}
}