{
  "type": "Feature",
  "properties": {
    "iso:country":"DE",
    "sg:address":"Vincenz-Statz-Str. 7",
    "sg:city":"K\u00f6ln",
    "sg:phone":"+49 221/495015",
    "sg:postcode":"50933",
    "sg:province":"Nordrhein-Westfalen",
    "wof:name":"Ulbtsu Und Sichla Rechtsanw\u00e4lte",
    "wof:placetype":"venue"
},
  "geometry": {"coordinates":[6.889647007,50.9358444214],"type":"Point"}
}