{
  "type": "Feature",
  "properties": {
    "iso:country":"DE",
    "sg:address":"Friedrich-Seele-Str. 30",
    "sg:city":"Braunschweig",
    "sg:phone":"+49 531/847298",
    "sg:postcode":"38122",
    "sg:province":"Niedersachsen",
    "wof:name":"Engel Maschinenbau Gmbh",
    "wof:placetype":"venue"
},
  "geometry": {"coordinates":[10.493118,52.238289],"type":"Point"}
}