{
  "type": "Feature",
  "properties": {
    "iso:country":"DE",
    "sg:address":"Fuldaer Str. 22",
    "sg:city":"Bad Br\u00fcckenau",
    "sg:phone":"+49 9741/3663",
    "sg:postcode":"97769",
    "sg:province":"Bayern",
    "wof:name":"Josef Krug",
    "wof:placetype":"venue"
},
  "geometry": {"coordinates":[9.790511,50.311878],"type":"Point"}
}