{
  "type": "Feature",
  "properties": {
    "iso:country":"DE",
    "sg:address":"Eichholzstr. 36",
    "sg:city":"Dortmund",
    "sg:phone":"+49 2304/46044",
    "sg:postcode":"44289",
    "sg:province":"Nordrhein-Westfalen",
    "wof:name":"Eichholz-apotheke",
    "wof:placetype":"venue"
},
  "geometry": {"coordinates":[7.596909,51.477615],"type":"Point"}
}