{
  "type": "Feature",
  "properties": {
    "iso:country":"DE",
    "sg:address":"In Granterath 3",
    "sg:city":"Erkelenz",
    "sg:phone":"+49 2431/3623",
    "sg:postcode":"41812",
    "sg:province":"Nordrhein-Westfalen",
    "wof:name":"Laurenz Stumm",
    "wof:placetype":"venue"
},
  "geometry": {"coordinates":[6.29471,51.056728],"type":"Point"}
}