{
  "type": "Feature",
  "properties": {
    "iso:country":"DE",
    "sg:address":"K\u00fchnertsgasse 24",
    "sg:city":"N\u00fcrnberg",
    "sg:postcode":"90402",
    "sg:province":"Bayern",
    "wof:name":"Norina-systemboden Fussboden Menkel",
    "wof:placetype":"venue"
},
  "geometry": {"coordinates":[11.0828399658,49.4503593445],"type":"Point"}
}