{
  "type": "Feature",
  "properties": {
    "iso:country":"DE",
    "sg:address":"Krumme L\u00e4ngt 6",
    "sg:city":"Saarwellingen",
    "sg:phone":"+49 6838/896300",
    "sg:postcode":"66793",
    "sg:province":"Saarland",
    "wof:name":"Hab Steuerberatungs- Gesellschaft Mbh",
    "wof:placetype":"venue"
},
  "geometry": {"coordinates":[6.8615241051,49.3296432495],"type":"Point"}
}