{
  "type": "Feature",
  "properties": {
    "iso:country":"DE",
    "sg:address":"Oststr. 58",
    "sg:city":"Bad Salzuflen",
    "sg:phone":"+49 5222/7876",
    "sg:postcode":"32107",
    "sg:province":"Nordrhein-Westfalen",
    "wof:name":"Willi Budde",
    "wof:placetype":"venue"
},
  "geometry": {"coordinates":[8.736659,52.054153],"type":"Point"}
}