{
  "type": "Feature",
  "properties": {
    "iso:country":"DE",
    "sg:address":"Berliner Platz 16",
    "sg:city":"Ratingen",
    "sg:phone":"+49 2102/473116",
    "sg:postcode":"40880",
    "sg:province":"Nordrhein-Westfalen",
    "wof:name":"Berliner Grill-imbi\u00df",
    "wof:placetype":"venue"
},
  "geometry": {"coordinates":[6.8170528412,51.2937583923],"type":"Point"}
}