{
  "type": "Feature",
  "properties": {
    "iso:country":"DE",
    "sg:address":"Hauptstr. 46",
    "sg:city":"Gelsenkirchen",
    "sg:phone":"+49 209/204479",
    "sg:postcode":"45879",
    "sg:province":"Nordrhein-Westfalen",
    "wof:name":"Norbert Kaltenkirchen Gmbh",
    "wof:placetype":"venue"
},
  "geometry": {"coordinates":[7.098052,51.512642],"type":"Point"}
}