{
  "type": "Feature",
  "properties": {
    "iso:country":"DE",
    "sg:address":"Hersfelder Str. 11",
    "sg:city":"Ludwigsau",
    "sg:phone":"+49 6621/78303",
    "sg:postcode":"36251",
    "sg:province":"Hessen",
    "wof:name":"Dorfsch\u00e4nke",
    "wof:placetype":"venue"
},
  "geometry": {"coordinates":[9.7430839539,50.8972015381],"type":"Point"}
}