{
  "type": "Feature",
  "properties": {
    "iso:country":"DE",
    "sg:address":"Lademannbogen 29",
    "sg:city":"Hamburg",
    "sg:phone":"+49 40/5385899",
    "sg:postcode":"22339",
    "sg:province":"Hamburg",
    "wof:name":"Neon Henning Gmbh",
    "wof:placetype":"venue"
},
  "geometry": {"coordinates":[10.03496,53.645294],"type":"Point"}
}