{
  "type": "Feature",
  "properties": {
    "iso:country":"DE",
    "sg:address":"Lindenstr. 6",
    "sg:city":"Leutkirch",
    "sg:phone":"+49 7561/70102",
    "sg:postcode":"88299",
    "sg:province":"Baden-W\u00fcrttemberg",
    "wof:name":"Osb-volksbank Immobilien Gmbh",
    "wof:placetype":"venue"
},
  "geometry": {"coordinates":[10.0211744308,47.826210022],"type":"Point"}
}