{
  "type": "Feature",
  "properties": {
    "iso:country":"DE",
    "sg:address":"Anna-Esche-Str. 12",
    "sg:city":"Limbach-Oberfrohna",
    "sg:postcode":"09212",
    "sg:province":"Sachsen",
    "wof:name":"Rfm-radio-fernseh- Multimedia Gmbh",
    "wof:placetype":"venue"
},
  "geometry": {"coordinates":[12.7656593323,50.860660553],"type":"Point"}
}