{
  "type": "Feature",
  "properties": {
    "iso:country":"DE",
    "sg:address":"Luegallee 130",
    "sg:city":"D\u00fcsseldorf",
    "sg:phone":"+49 211/574276",
    "sg:postcode":"40545",
    "sg:province":"Nordrhein-Westfalen",
    "wof:name":"Rene",
    "wof:placetype":"venue"
},
  "geometry": {"coordinates":[6.748115,51.231812],"type":"Point"}
}