{
  "type": "Feature",
  "properties": {
    "iso:country":"DE",
    "sg:address":"Peschmannstr. 23",
    "sg:city":"Duisburg",
    "sg:phone":"+49 2065/65179",
    "sg:postcode":"47228",
    "sg:province":"Nordrhein-Westfalen",
    "wof:name":"Rainer Peisker Ing.grad. Gmbh Fliesenfachgesch\u00e4ft",
    "wof:placetype":"venue"
},
  "geometry": {"coordinates":[6.6873459816,51.4084358215],"type":"Point"}
}