{
  "type": "Feature",
  "properties": {
    "iso:country":"DE",
    "sg:address":"Linnenstr. 24-26",
    "sg:city":"Beckum",
    "sg:phone":"+49 4925/2193490",
    "sg:postcode":"59269",
    "sg:province":"Nordrhein-Westfalen",
    "wof:name":"Awa Handelsges. Mbh",
    "wof:placetype":"venue"
},
  "geometry": {"coordinates":[8.042726,51.756565],"type":"Point"}
}