{
  "type": "Feature",
  "properties": {
    "iso:country":"DE",
    "sg:address":"Alte Landstr. 6",
    "sg:city":"Nieder-Olm",
    "sg:phone":"+49 6136/2689",
    "sg:postcode":"55268",
    "sg:province":"Rheinland-Pfalz",
    "wof:name":"G\u00fcnther Peter",
    "wof:placetype":"venue"
},
  "geometry": {"coordinates":[8.2010660172,49.9083862305],"type":"Point"}
}