{
  "type": "Feature",
  "properties": {
    "iso:country":"DE",
    "sg:address":"Werraweg 4",
    "sg:city":"Fuldatal",
    "sg:phone":"+49 561/817564",
    "sg:postcode":"34233",
    "sg:province":"Hessen",
    "wof:name":"A. M. Fromm Immobilienmakler",
    "wof:placetype":"venue"
},
  "geometry": {"coordinates":[9.5260601044,51.3503341675],"type":"Point"}
}