{
  "type": "Feature",
  "properties": {
    "iso:country":"DE",
    "sg:address":"Industriestr. 2",
    "sg:city":"L\u00f6rrach",
    "sg:phone":"+49 7621/12028",
    "sg:postcode":"79541",
    "sg:province":"Baden-W\u00fcrttemberg",
    "wof:name":"Zbb Zubeh\u00f6r F\u00fcr Biologisches Bauen Und Wohnen L\u00f6rrach Gmbh",
    "wof:placetype":"venue"
},
  "geometry": {"coordinates":[7.6795167923,47.6351737976],"type":"Point"}
}