{
  "type": "Feature",
  "properties": {
    "iso:country":"DE",
    "sg:address":"Espachstr. 21",
    "sg:city":"Balingen",
    "sg:phone":"+49 7433/9800",
    "sg:postcode":"72336",
    "sg:province":"Baden-W\u00fcrttemberg",
    "wof:name":"Hess Technology Gmbh",
    "wof:placetype":"venue"
},
  "geometry": {"coordinates":[8.8638181686,48.2345428467],"type":"Point"}
}