{
  "type": "Feature",
  "properties": {
    "iso:country":"DE",
    "sg:address":"Damaschkestr. 17",
    "sg:city":"Bad Friedrichshall",
    "sg:phone":"+49 7136/3539",
    "sg:postcode":"74177",
    "sg:province":"Baden-W\u00fcrttemberg",
    "wof:name":"E. Hofmann Gmbh",
    "wof:placetype":"venue"
},
  "geometry": {"coordinates":[9.2117023468,49.2334136963],"type":"Point"}
}