{
  "type": "Feature",
  "properties": {
    "iso:country":"DE",
    "sg:address":"W\u00f6lkauer Weg 11",
    "sg:city":"Leipzig",
    "sg:phone":"+49 341/9015716",
    "sg:postcode":"04129",
    "sg:province":"Sachsen",
    "wof:name":"D. Abitzsch",
    "wof:placetype":"venue"
},
  "geometry": {"coordinates":[12.3845281601,51.3862991333],"type":"Point"}
}