{
  "type": "Feature",
  "properties": {
    "iso:country":"DE",
    "sg:address":"Dorfstr. 17",
    "sg:city":"Axien",
    "sg:phone":"+49 35386/22346",
    "sg:postcode":"06922",
    "sg:province":"Sachsen-Anhalt",
    "wof:name":"G\u00dcwag G\u00fclle- Und Wassertech- Nischer Anlgen- Und Ger\u00e4tebau",
    "wof:placetype":"venue"
},
  "geometry": {"coordinates":[12.886801,51.700211],"type":"Point"}
}