{
  "type": "Feature",
  "properties": {
    "iso:country":"DE",
    "sg:address":"Bahnhofstr. 1",
    "sg:city":"Gifhorn",
    "sg:phone":"+49 5371/4330",
    "sg:postcode":"38518",
    "sg:province":"Niedersachsen",
    "wof:name":"Deutsche Bahn Ag",
    "wof:placetype":"venue"
},
  "geometry": {"coordinates":[10.5422172546,52.4797019958],"type":"Point"}
}