{
  "type": "Feature",
  "properties": {
    "iso:country":"DE",
    "sg:address":"Grellkampkehre 2c",
    "sg:city":"Hamburg",
    "sg:phone":"+49 40/5321970",
    "sg:postcode":"22415",
    "sg:province":"Hamburg",
    "wof:name":"Theodor V. Walsleben",
    "wof:placetype":"venue"
},
  "geometry": {"coordinates":[9.9972848892,53.6530036926],"type":"Point"}
}