{
  "type": "Feature",
  "properties": {
    "iso:country":"DE",
    "sg:address":"R\u00fcckertstr. 1",
    "sg:city":"Berlin",
    "sg:phone":"+49 30/32798090",
    "sg:postcode":"10627",
    "sg:province":"Berlin",
    "wof:name":"Alpha Research Deutschland Gmbh",
    "wof:placetype":"venue"
},
  "geometry": {"coordinates":[13.302993,52.511147],"type":"Point"}
}