{
  "type": "Feature",
  "properties": {
    "iso:country":"DE",
    "sg:address":"Sommerstr. 1 b",
    "sg:city":"M\u00fcnchen",
    "sg:postcode":"81543",
    "sg:province":"Bayern",
    "wof:name":"T Vier T Gmbh",
    "wof:placetype":"venue"
},
  "geometry": {"coordinates":[11.575364,48.122677],"type":"Point"}
}