{
  "type": "Feature",
  "properties": {
    "iso:country":"DE",
    "sg:address":"Neinstedter Feldweg 3",
    "sg:city":"Quedlinburg",
    "sg:phone":"+49 3946/51034",
    "sg:postcode":"06484",
    "sg:province":"Sachsen-Anhalt",
    "wof:name":"Diamant Haarmoden Gmbh",
    "wof:placetype":"venue"
},
  "geometry": {"coordinates":[11.1384344101,51.7778739929],"type":"Point"}
}