{
  "type": "Feature",
  "properties": {
    "iso:country":"DE",
    "sg:address":"Hugstetter Str. 55",
    "sg:city":"Freiburg",
    "sg:postcode":"79106",
    "sg:province":"Baden-W\u00fcrttemberg",
    "wof:name":"Zentrum F\u00fcr Innere Medizin",
    "wof:placetype":"venue"
},
  "geometry": {"coordinates":[7.8394188881,48.0055885315],"type":"Point"}
}