{
  "type": "Feature",
  "properties": {
    "iso:country":"DE",
    "sg:address":"Fuldaer Str. 20",
    "sg:city":"Sontra",
    "sg:phone":"+49 5653/7733",
    "sg:postcode":"36205",
    "sg:province":"Hessen",
    "wof:name":"Carl Schade",
    "wof:placetype":"venue"
},
  "geometry": {"coordinates":[9.9299917221,51.0658912659],"type":"Point"}
}