{
  "type": "Feature",
  "properties": {
    "iso:country":"DE",
    "sg:address":"Luitpoldstr. 28",
    "sg:city":"Bruchm\u00fchlbach-Miesau",
    "sg:phone":"+49 6372/2205",
    "sg:postcode":"66892",
    "sg:province":"Rheinland-Pfalz",
    "wof:name":"Transportunternehmen Peter Gro\u00df Gmbh",
    "wof:placetype":"venue"
},
  "geometry": {"coordinates":[7.4501748085,49.381652832],"type":"Point"}
}