{
  "type": "Feature",
  "properties": {
    "iso:country":"DE",
    "sg:address":"Hugo-Krone-Platz 3",
    "sg:city":"Leipzig",
    "sg:phone":"+49 341/5214355",
    "sg:postcode":"04158",
    "sg:province":"Sachsen",
    "wof:name":"J. Daum",
    "wof:placetype":"venue"
},
  "geometry": {"coordinates":[12.37391,51.393635],"type":"Point"}
}