{
  "type": "Feature",
  "properties": {
    "iso:country":"DE",
    "sg:address":"Karlstr. 29",
    "sg:city":"Karlsruhe",
    "sg:phone":"+49 721/912929",
    "sg:postcode":"76133",
    "sg:province":"Baden-W\u00fcrttemberg",
    "wof:name":"Apotheke 29",
    "wof:placetype":"venue"
},
  "geometry": {"coordinates":[8.395073,49.007553],"type":"Point"}
}