{
  "type": "Feature",
  "properties": {
    "iso:country":"DE",
    "sg:address":"Danziger Platz 8",
    "sg:city":"H\u00fcnxe",
    "sg:phone":"+49 2064/30120",
    "sg:postcode":"46569",
    "sg:province":"Nordrhein-Westfalen",
    "wof:name":"Ev. Pfarramt Ii H\u00fcnxe",
    "wof:placetype":"venue"
},
  "geometry": {"coordinates":[6.7539978027,51.5991897583],"type":"Point"}
}