{
  "type": "Feature",
  "properties": {
    "iso:country":"DE",
    "sg:address":"Putlitzer Str. 22 a",
    "sg:city":"Pritzwalk",
    "sg:phone":"+49 3395/302860",
    "sg:postcode":"16928",
    "sg:province":"Brandenburg",
    "wof:name":"Wilfried Schlinke",
    "wof:placetype":"venue"
},
  "geometry": {"coordinates":[12.1706256866,53.1507225037],"type":"Point"}
}