{
  "type": "Feature",
  "properties": {
    "iso:country":"DE",
    "sg:address":"Im Fichtental",
    "sg:city":"Kuppenheim",
    "sg:postcode":"76456",
    "sg:province":"Baden-W\u00fcrttemberg",
    "wof:name":"Kolb Gmbh",
    "wof:placetype":"venue"
},
  "geometry": {"coordinates":[8.24927,48.821674],"type":"Point"}
}