{
  "type": "Feature",
  "properties": {
    "iso:country":"DE",
    "sg:address":"Lindachstr. 15",
    "sg:city":"Reutlingen",
    "sg:phone":"+49 7121/239751",
    "sg:postcode":"72764",
    "sg:province":"Baden-W\u00fcrttemberg",
    "wof:name":"Lacroix",
    "wof:placetype":"venue"
},
  "geometry": {"coordinates":[9.216159,48.487503],"type":"Point"}
}