{
  "type": "Feature",
  "properties": {
    "iso:country":"DE",
    "sg:address":"Seidelstr. 1",
    "sg:city":"Aschaffenburg",
    "sg:phone":"+49 6021/80333",
    "sg:postcode":"63741",
    "sg:province":"Bayern",
    "wof:name":"Morhard & Kilchenstein",
    "wof:placetype":"venue"
},
  "geometry": {"coordinates":[9.1265802383,49.9743118286],"type":"Point"}
}