{
  "type": "Feature",
  "properties": {
    "iso:country":"DE",
    "sg:address":"Ro\u00dfplatz 4",
    "sg:city":"Lahr",
    "sg:phone":"+49 7821/30422",
    "sg:postcode":"77933",
    "sg:province":"Baden-W\u00fcrttemberg",
    "wof:name":"La Piccola Cantina",
    "wof:placetype":"venue"
},
  "geometry": {"coordinates":[7.8737750053,48.3392677307],"type":"Point"}
}