{
  "type": "Feature",
  "properties": {
    "iso:country":"DE",
    "sg:address":"Marktplatz 21",
    "sg:city":"Lam",
    "sg:phone":"+49 9943/642",
    "sg:postcode":"93462",
    "sg:province":"Bayern",
    "wof:name":"Volksbank Straubing Eg",
    "wof:placetype":"venue"
},
  "geometry": {"coordinates":[13.049363,49.197845],"type":"Point"}
}