{
  "type": "Feature",
  "properties": {
    "iso:country":"DE",
    "sg:address":"Sch\u00f6nebecker Str. 3",
    "sg:city":"P\u00f6mmelte",
    "sg:phone":"+49 39298/7360",
    "sg:postcode":"39249",
    "sg:province":"Sachsen-Anhalt",
    "wof:name":"J\u00f6rg Becker Tischlerei",
    "wof:placetype":"venue"
},
  "geometry": {"coordinates":[11.832108,51.994221],"type":"Point"}
}