{
  "type": "Feature",
  "properties": {
    "iso:country":"DE",
    "sg:address":"Brackweder Str. 57",
    "sg:city":"Halle",
    "sg:phone":"+49 5201/70506",
    "sg:postcode":"33790",
    "sg:province":"Nordrhein-Westfalen",
    "wof:name":"Brockmeyer",
    "wof:placetype":"venue"
},
  "geometry": {"coordinates":[8.398303,52.032753],"type":"Point"}
}