{
  "type": "Feature",
  "properties": {
    "iso:country":"DE",
    "sg:address":"Gebr\u00fcder-Grimm-Str. 5",
    "sg:city":"Gr\u00fcnstadt",
    "sg:phone":"+49 6359/2010",
    "sg:postcode":"67269",
    "sg:province":"Rheinland-Pfalz",
    "wof:name":"Grimm-immobilien E. Kfr.",
    "wof:placetype":"venue"
},
  "geometry": {"coordinates":[8.1638765335,49.5705871582],"type":"Point"}
}