{
  "type": "Feature",
  "properties": {
    "iso:country":"DE",
    "sg:address":"Frankenh\u00e4user Stra\u00dfe 28",
    "sg:city":"Sondershausen",
    "sg:phone":"+49 3632/65270",
    "sg:postcode":"99706",
    "sg:province":"Th\u00fcringen",
    "wof:name":"Hesa Ingenieurb\u00fcro Gbr Mbh",
    "wof:placetype":"venue"
},
  "geometry": {"coordinates":[10.884471,51.367668],"type":"Point"}
}