{
  "type": "Feature",
  "properties": {
    "iso:country":"DE",
    "sg:address":"Karl-Albert-Str. 32",
    "sg:city":"Duisburg",
    "sg:phone":"+49 203/460401",
    "sg:postcode":"47139",
    "sg:province":"Nordrhein-Westfalen",
    "wof:name":"Leo Pissarczyk",
    "wof:placetype":"venue"
},
  "geometry": {"coordinates":[6.7353210449,51.4795913696],"type":"Point"}
}