{
  "type": "Feature",
  "properties": {
    "iso:country":"DE",
    "sg:address":"Paul-Kornfeld-Weg 3",
    "sg:city":"Frankfurt",
    "sg:postcode":"60439",
    "sg:province":"Hessen",
    "wof:name":"Japan Risk Consulting Gmbh",
    "wof:placetype":"venue"
},
  "geometry": {"coordinates":[8.618057251,50.1595993042],"type":"Point"}
}