{
  "type": "Feature",
  "properties": {
    "iso:country":"DE",
    "sg:address":"Dorstener Str. 488",
    "sg:city":"Herne",
    "sg:phone":"+49 2325/51125",
    "sg:postcode":"44653",
    "sg:province":"Nordrhein-Westfalen",
    "wof:name":"U. Bleck",
    "wof:placetype":"venue"
},
  "geometry": {"coordinates":[7.1574978828,51.5448188782],"type":"Point"}
}