{
  "type": "Feature",
  "properties": {
    "iso:country":"DE",
    "sg:address":"Buchenlandweg 145",
    "sg:city":"Ulm",
    "sg:phone":"+49 731/262924",
    "sg:postcode":"89075",
    "sg:province":"Baden-W\u00fcrttemberg",
    "wof:name":"Midnighttrain Co Uli Hahnel",
    "wof:placetype":"venue"
},
  "geometry": {"coordinates":[10.0147094727,48.4336776733],"type":"Point"}
}