{
  "type": "Feature",
  "properties": {
    "iso:country":"DE",
    "sg:address":"Lippestr. 5",
    "sg:city":"Koblenz",
    "sg:phone":"+49 261/56122",
    "sg:postcode":"56075",
    "sg:province":"Rheinland-Pfalz",
    "wof:name":"Jackowski Gmbh",
    "wof:placetype":"venue"
},
  "geometry": {"coordinates":[7.573724,50.345974],"type":"Point"}
}