{
  "type": "Feature",
  "properties": {
    "iso:country":"DE",
    "sg:address":"Max-Planck-Str 25",
    "sg:city":"Karben",
    "sg:phone":"+49 6039/931338",
    "sg:postcode":"61184",
    "sg:province":"Hessen",
    "wof:name":"Elmeco Gmbh",
    "wof:placetype":"venue"
},
  "geometry": {"coordinates":[8.765226,50.223015],"type":"Point"}
}