{
  "type": "Feature",
  "properties": {
    "iso:country":"DE",
    "sg:address":"Dohnaer Str. 135",
    "sg:city":"Dresden",
    "sg:phone":"+49 351/2817904",
    "sg:postcode":"01239",
    "sg:province":"Sachsen",
    "wof:name":"Freibad Prohlis",
    "wof:placetype":"venue"
},
  "geometry": {"coordinates":[13.794552803,51.0015182495],"type":"Point"}
}