{
  "type": "Feature",
  "properties": {
    "iso:country":"DE",
    "sg:address":"Neumarkt 11",
    "sg:city":"Saarbr\u00fccken",
    "sg:phone":"+49 681/55110",
    "sg:postcode":"66117",
    "sg:province":"Saarland",
    "wof:name":"Gerhard Wernet",
    "wof:placetype":"venue"
},
  "geometry": {"coordinates":[6.9901461601,49.233039856],"type":"Point"}
}