{
  "type": "Feature",
  "properties": {
    "iso:country":"DE",
    "sg:address":"Allersheim 3",
    "sg:city":"Schwindegg",
    "sg:phone":"+49 8082/392",
    "sg:postcode":"84419",
    "sg:province":"Bayern",
    "wof:name":"Ludwig Wetzl",
    "wof:placetype":"venue"
},
  "geometry": {"coordinates":[12.281003,48.260662],"type":"Point"}
}