{
  "type": "Feature",
  "properties": {
    "iso:country":"DE",
    "sg:address":"Blarerplatz 8",
    "sg:city":"Esslingen",
    "sg:phone":"+49 711/359161",
    "sg:postcode":"73728",
    "sg:province":"Baden-W\u00fcrttemberg",
    "wof:name":"Bierbar Sonne",
    "wof:placetype":"venue"
},
  "geometry": {"coordinates":[9.3099355698,48.740436554],"type":"Point"}
}