{
  "type": "Feature",
  "properties": {
    "iso:country":"DE",
    "sg:address":"Herderstr. 2",
    "sg:city":"Neumarkt",
    "sg:phone":"+49 9181/48540",
    "sg:postcode":"92318",
    "sg:province":"Bayern",
    "wof:name":"Herbert Su\u00dfner",
    "wof:placetype":"venue"
},
  "geometry": {"coordinates":[11.4782085419,49.2886810303],"type":"Point"}
}