{
  "type": "Feature",
  "properties": {
    "iso:country":"DE",
    "sg:address":"Kol. Lindenbl\u00fcte 11",
    "sg:city":"Berlin",
    "sg:phone":"+49 30/3445671",
    "sg:postcode":"13627",
    "sg:province":"Berlin",
    "wof:name":"Glamsch Frachtschiffahrt Gmbh",
    "wof:placetype":"venue"
},
  "geometry": {"coordinates":[13.30054,52.538872],"type":"Point"}
}