{
  "type": "Feature",
  "properties": {
    "iso:country":"DE",
    "sg:address":"Heinsestr. 54",
    "sg:city":"Berlin",
    "sg:phone":"+49 30/4049015",
    "sg:postcode":"13467",
    "sg:province":"Berlin",
    "wof:name":"Alexander M. Rainoff Immobilienmakler",
    "wof:placetype":"venue"
},
  "geometry": {"coordinates":[13.3050289154,52.619430542],"type":"Point"}
}