{
  "type": "Feature",
  "properties": {
    "iso:country":"DE",
    "sg:address":"Hermann-W\u00fcsthof-Ring 10",
    "sg:city":"Hamburg",
    "sg:phone":"+49 40/7349941",
    "sg:postcode":"21035",
    "sg:province":"Hamburg",
    "wof:name":"J. Bez Kg",
    "wof:placetype":"venue"
},
  "geometry": {"coordinates":[10.1107988358,53.4932441711],"type":"Point"}
}