{
  "type": "Feature",
  "properties": {
    "iso:country":"DE",
    "sg:address":"Wellesweilerstr. 51b",
    "sg:city":"Bexbach",
    "sg:phone":"+49 6826/93400",
    "sg:postcode":"66450",
    "sg:province":"Saarland",
    "wof:name":"Aulenbacher Gmbh",
    "wof:placetype":"venue"
},
  "geometry": {"coordinates":[7.2459001541,49.3511123657],"type":"Point"}
}