{
  "type": "Feature",
  "properties": {
    "iso:country":"DE",
    "sg:address":"Neukirchener Str. 2",
    "sg:city":"Krefeld",
    "sg:phone":"+49 2151/49330",
    "sg:postcode":"47829",
    "sg:province":"Nordrhein-Westfalen",
    "wof:name":"Struwelpeter-apotheke Sylvia M\u00fcller",
    "wof:placetype":"venue"
},
  "geometry": {"coordinates":[6.616327,51.370747],"type":"Point"}
}