{
  "type": "Feature",
  "properties": {
    "iso:country":"DE",
    "sg:address":"Virchowstr. 19",
    "sg:city":"Hamburg",
    "sg:phone":"+49 40/3802010",
    "sg:postcode":"22767",
    "sg:province":"Hamburg",
    "wof:name":"J. F. Jens S\u00f6hne Werkzeuge-maschinen Gmbh",
    "wof:placetype":"venue"
},
  "geometry": {"coordinates":[9.9405403137,53.5512161255],"type":"Point"}
}