{
  "type": "Feature",
  "properties": {
    "iso:country":"DE",
    "sg:address":"Berliner Str. 29",
    "sg:city":"Strausberg",
    "sg:postcode":"15344",
    "sg:province":"Brandenburg",
    "wof:name":"Mtm Immobilien Management Gmbh",
    "wof:placetype":"venue"
},
  "geometry": {"coordinates":[13.8685998917,52.5647087097],"type":"Point"}
}