{
  "type": "Feature",
  "properties": {
    "iso:country":"DE",
    "sg:address":"Kalkweg 22",
    "sg:city":"Langg\u00f6ns",
    "sg:phone":"+49 6085/1560",
    "sg:postcode":"35428",
    "sg:province":"Hessen",
    "wof:name":"Hous Of Guns",
    "wof:placetype":"venue"
},
  "geometry": {"coordinates":[8.5645799637,50.4455413818],"type":"Point"}
}