{
  "type": "Feature",
  "properties": {
    "iso:country":"DE",
    "sg:address":"Rieder Str. 127",
    "sg:city":"Thedinghausen",
    "sg:phone":"+49 4204/432",
    "sg:postcode":"27321",
    "sg:province":"Niedersachsen",
    "wof:name":"Schr\u00f6der Baumschulen Und Obstplantagen",
    "wof:placetype":"venue"
},
  "geometry": {"coordinates":[8.9789028168,52.9595680237],"type":"Point"}
}