{
  "type": "Feature",
  "properties": {
    "iso:country":"DE",
    "sg:address":"Eichplatz 2",
    "sg:city":"Krottorf",
    "sg:phone":"+49 39424/5641",
    "sg:postcode":"39387",
    "sg:province":"Sachsen-Anhalt",
    "wof:name":"Kreutzer",
    "wof:placetype":"venue"
},
  "geometry": {"coordinates":[11.229539,52.028641],"type":"Point"}
}