{
  "type": "Feature",
  "properties": {
    "iso:country":"DE",
    "sg:address":"Uerdinger Str. 16",
    "sg:city":"Krefeld",
    "sg:phone":"+49 2151/22285",
    "sg:postcode":"47799",
    "sg:province":"Nordrhein-Westfalen",
    "wof:name":"Pizzeria Piccolo",
    "wof:placetype":"venue"
},
  "geometry": {"coordinates":[6.5723381042,51.3352661133],"type":"Point"}
}