{
  "type": "Feature",
  "properties": {
    "iso:country":"DE",
    "sg:address":"Leonhard-Moll-Bogen 10",
    "sg:city":"M\u00fcnchen",
    "sg:postcode":"81373",
    "sg:province":"Bayern",
    "wof:name":"Rbc R. B\u00f6ker Consulting Gmbh",
    "wof:placetype":"venue"
},
  "geometry": {"coordinates":[11.530402,48.129528],"type":"Point"}
}