{
  "type": "Feature",
  "properties": {
    "iso:country":"DE",
    "sg:address":"Bismarckstra\u00dfe 34",
    "sg:city":"Stuttgart",
    "sg:phone":"+49 711/639190",
    "sg:postcode":"70197",
    "sg:province":"Baden-W\u00fcrttemberg",
    "wof:name":"Restaurant-lilie",
    "wof:placetype":"venue"
},
  "geometry": {"coordinates":[9.155138,48.773392],"type":"Point"}
}