{
  "type": "Feature",
  "properties": {
    "iso:country":"DE",
    "sg:address":"H\u00e4ndelstr. 26",
    "sg:city":"Stuttgart",
    "sg:phone":"+49 711/6993903",
    "sg:postcode":"70195",
    "sg:province":"Baden-W\u00fcrttemberg",
    "wof:name":"B. Kuhn",
    "wof:placetype":"venue"
},
  "geometry": {"coordinates":[9.129153,48.77972],"type":"Point"}
}