{
  "type": "Feature",
  "properties": {
    "iso:country":"DE",
    "sg:address":"Ruhrfelder Str. 8",
    "sg:city":"M\u00f6nchengladbach",
    "sg:phone":"+49 2166/602477",
    "sg:postcode":"41199",
    "sg:province":"Nordrhein-Westfalen",
    "wof:name":"Otto Ehren",
    "wof:placetype":"venue"
},
  "geometry": {"coordinates":[6.4508500099,51.1342964172],"type":"Point"}
}