{
  "type": "Feature",
  "properties": {
    "iso:country":"DE",
    "sg:address":"Am Wolfsbrunnen 3",
    "sg:city":"Erfurt",
    "sg:phone":"+49 361/2219039",
    "sg:postcode":"99094",
    "sg:province":"Th\u00fcringen",
    "wof:name":"Fliesenverlegung Kamin- Und Kachelofenbau",
    "wof:placetype":"venue"
},
  "geometry": {"coordinates":[10.971316,50.953918],"type":"Point"}
}