{
  "type": "Feature",
  "properties": {
    "iso:country":"DE",
    "sg:address":"Hauptstr. 3",
    "sg:city":"K\u00f6nigsbrunn",
    "sg:postcode":"86343",
    "sg:province":"Bayern",
    "wof:name":"Mayer & S\u00f6hne Druck- Und Mediengruppe Gmbh",
    "wof:placetype":"venue"
},
  "geometry": {"coordinates":[10.890975,48.268719],"type":"Point"}
}