{
  "type": "Feature",
  "properties": {
    "iso:country":"DE",
    "sg:address":"M\u00fchlstr. 23",
    "sg:city":"Schotten",
    "sg:phone":"+49 6044/3223",
    "sg:postcode":"63679",
    "sg:province":"Hessen",
    "wof:name":"H. H. Straub",
    "wof:placetype":"venue"
},
  "geometry": {"coordinates":[9.0805778503,50.4712562561],"type":"Point"}
}