{
  "type": "Feature",
  "properties": {
    "iso:country":"DE",
    "sg:address":"M\u00fcnsterstr. 64",
    "sg:city":"Greven",
    "sg:phone":"+49 2571/2743",
    "sg:postcode":"48268",
    "sg:province":"Nordrhein-Westfalen",
    "wof:name":"Herbert Parnitzke",
    "wof:placetype":"venue"
},
  "geometry": {"coordinates":[7.613511,52.088165],"type":"Point"}
}