{
  "type": "Feature",
  "properties": {
    "iso:country":"DE",
    "sg:address":"Aalener Str. 23",
    "sg:city":"Oberkochen",
    "sg:phone":"+49 7364/6436",
    "sg:postcode":"73447",
    "sg:province":"Baden-W\u00fcrttemberg",
    "wof:name":"Emil Hug",
    "wof:placetype":"venue"
},
  "geometry": {"coordinates":[10.1073036194,48.7852745056],"type":"Point"}
}