{
  "type": "Feature",
  "properties": {
    "iso:country":"DE",
    "sg:address":"Teltower Damm 261",
    "sg:city":"Berlin",
    "sg:phone":"+49 30/8159140",
    "sg:postcode":"14167",
    "sg:province":"Berlin",
    "wof:name":"Cord-hinrich M\u00fcller Ingenieur",
    "wof:placetype":"venue"
},
  "geometry": {"coordinates":[13.2674312592,52.4106140137],"type":"Point"}
}