{
  "type": "Feature",
  "properties": {
    "iso:country":"DE",
    "sg:address":"Fahrradstr. 56",
    "sg:city":"N\u00fcrnberg",
    "sg:phone":"+49 911/320650",
    "sg:postcode":"90429",
    "sg:province":"Bayern",
    "wof:name":"Exabyte Magnetics Gmbh",
    "wof:placetype":"venue"
},
  "geometry": {"coordinates":[11.035817,49.459045],"type":"Point"}
}