{
  "type": "Feature",
  "properties": {
    "iso:country":"DE",
    "sg:address":"Dorfstr. 7",
    "sg:city":"Renthendorf",
    "sg:phone":"+49 36426/22373",
    "sg:postcode":"07646",
    "sg:province":"Th\u00fcringen",
    "wof:name":"A. Kretzschmar Makler",
    "wof:placetype":"venue"
},
  "geometry": {"coordinates":[11.8472003937,50.8020591736],"type":"Point"}
}