{
  "type": "Feature",
  "properties": {
    "iso:country":"DE",
    "sg:address":"Pieperstr. 41-47",
    "sg:city":"Lage",
    "sg:phone":"+49 5232/7010",
    "sg:postcode":"32791",
    "sg:province":"Nordrhein-Westfalen",
    "wof:name":"Landschlachterei Pieper Gmbh & Co. Kg",
    "wof:placetype":"venue"
},
  "geometry": {"coordinates":[8.7495098114,51.974697113],"type":"Point"}
}