{
  "type": "Feature",
  "properties": {
    "iso:country":"DE",
    "sg:address":"Albblickstr. 13",
    "sg:city":"M\u00f6ssingen",
    "sg:phone":"+49 7473/6347",
    "sg:postcode":"72116",
    "sg:province":"Baden-W\u00fcrttemberg",
    "wof:name":"Rosemarie Pflumm Heilpraktikerin",
    "wof:placetype":"venue"
},
  "geometry": {"coordinates":[9.0357151031,48.4025268555],"type":"Point"}
}