{
  "type": "Feature",
  "properties": {
    "iso:country":"DE",
    "sg:address":"Etzelweg 34",
    "sg:city":"Rehlingen-Siersburg",
    "sg:postcode":"66780",
    "sg:province":"Saarland",
    "wof:name":"Redaktion B\u00fcrgerbrief Der Spd Rehlingen",
    "wof:placetype":"venue"
},
  "geometry": {"coordinates":[6.6860399246,49.3738822937],"type":"Point"}
}