{
  "type": "Feature",
  "properties": {
    "iso:country":"DE",
    "sg:address":"Brehmstr. 11",
    "sg:city":"D\u00fcsseldorf",
    "sg:phone":"+49 211/632863",
    "sg:postcode":"40239",
    "sg:province":"Nordrhein-Westfalen",
    "wof:name":"Camphausen",
    "wof:placetype":"venue"
},
  "geometry": {"coordinates":[6.8019609451,51.2404174805],"type":"Point"}
}