{
  "type": "Feature",
  "properties": {
    "iso:country":"DE",
    "sg:address":"Hagener Str. 44",
    "sg:city":"Iserlohn",
    "sg:phone":"+49 2374/1879",
    "sg:postcode":"58642",
    "sg:province":"Nordrhein-Westfalen",
    "wof:name":"Textor Und Sch\u00f6nfelder Rechtsanw\u00e4lte Und Notare",
    "wof:placetype":"venue"
},
  "geometry": {"coordinates":[7.6124258041,51.365322113],"type":"Point"}
}