{
  "type": "Feature",
  "properties": {
    "iso:country":"DE",
    "sg:address":"Schillerplatz",
    "sg:city":"Schwarzheide",
    "sg:phone":"+49 35752/87310",
    "sg:postcode":"01987",
    "sg:province":"Brandenburg",
    "wof:name":"Zentrum F\u00fcr Entwicklung Innovation Und Technologie",
    "wof:placetype":"venue"
},
  "geometry": {"coordinates":[13.8617095947,51.4744491577],"type":"Point"}
}