{
  "type": "Feature",
  "properties": {
    "iso:country":"DE",
    "sg:address":"Vogelsangstr. 71",
    "sg:city":"Wuppertal",
    "sg:phone":"+49 202/754015",
    "sg:postcode":"42109",
    "sg:province":"Nordrhein-Westfalen",
    "wof:name":"Gerhard Pasenau",
    "wof:placetype":"venue"
},
  "geometry": {"coordinates":[7.1426329613,51.2730407715],"type":"Point"}
}