{
  "type": "Feature",
  "properties": {
    "iso:country":"DE",
    "sg:address":"Gemeindewiesenweg 4",
    "sg:city":"Pasewalk",
    "sg:phone":"+49 3973/4390",
    "sg:postcode":"17309",
    "sg:province":"Mecklenburg-Vorpommern",
    "wof:name":"Papyro Gmbh",
    "wof:placetype":"venue"
},
  "geometry": {"coordinates":[14.0060586929,53.5166244507],"type":"Point"}
}