{
  "type": "Feature",
  "properties": {
    "iso:country":"DE",
    "sg:address":"Delitzscher Str 77",
    "sg:city":"Halle",
    "sg:phone":"+49 345/570590",
    "sg:postcode":"06116",
    "sg:province":"Sachsen-Anhalt",
    "wof:name":"Dresdner K\u00fchlanlagenbau Gmbh",
    "wof:placetype":"venue"
},
  "geometry": {"coordinates":[12.0158596039,51.47864151],"type":"Point"}
}