{
  "type": "Feature",
  "properties": {
    "iso:country":"DE",
    "sg:address":"Hauptstr. 86",
    "sg:city":"Rehungen",
    "sg:phone":"+49 36338/60489",
    "sg:postcode":"99759",
    "sg:province":"Th\u00fcringen",
    "wof:name":"R. Kleppek",
    "wof:placetype":"venue"
},
  "geometry": {"coordinates":[10.521111,51.378967],"type":"Point"}
}