{
  "type": "Feature",
  "properties": {
    "iso:country":"DE",
    "sg:address":"Haldenhof 1",
    "sg:city":"Nagold",
    "sg:phone":"+49 7452/2386",
    "sg:postcode":"72202",
    "sg:province":"Baden-W\u00fcrttemberg",
    "wof:name":"Hans K\u00f6hler",
    "wof:placetype":"venue"
},
  "geometry": {"coordinates":[8.703102,48.589924],"type":"Point"}
}