{
  "type": "Feature",
  "properties": {
    "iso:country":"DE",
    "sg:address":"Bockwitzer Str.17",
    "sg:city":"Lauchhammer",
    "sg:phone":"+49 3574",
    "sg:postcode":"01979",
    "sg:province":"Brandenburg",
    "wof:name":"Fa.heiko Handrich",
    "wof:placetype":"venue"
},
  "geometry": {"coordinates":[13.738141,51.477215],"type":"Point"}
}