{
  "type": "Feature",
  "properties": {
    "iso:country":"DE",
    "sg:address":"Hafengasse 9",
    "sg:city":"T\u00fcbingen",
    "sg:phone":"+49 4970/7122529",
    "sg:postcode":"72070",
    "sg:province":"Baden-W\u00fcrttemberg",
    "wof:name":"Albert Grie\u00dfhaber Kg",
    "wof:placetype":"venue"
},
  "geometry": {"coordinates":[9.0568351746,48.5212440491],"type":"Point"}
}