{
  "type": "Feature",
  "properties": {
    "iso:country":"DE",
    "sg:address":"Bullmannstr. 27",
    "sg:city":"Kleve",
    "sg:phone":"+49 2821/9457",
    "sg:postcode":"47533",
    "sg:province":"Nordrhein-Westfalen",
    "wof:name":"Herbert Handel Ingenieur",
    "wof:placetype":"venue"
},
  "geometry": {"coordinates":[6.1684918404,51.7977561951],"type":"Point"}
}