{
  "type": "Feature",
  "properties": {
    "iso:country":"DE",
    "sg:address":"Markt 6",
    "sg:city":"Eltville",
    "sg:phone":"+49 6123/900633",
    "sg:postcode":"65346",
    "sg:province":"Hessen",
    "wof:name":"Andrea Uhlich Rechtsanw\u00e4ltin",
    "wof:placetype":"venue"
},
  "geometry": {"coordinates":[8.0946130753,50.0204963684],"type":"Point"}
}