{
  "type": "Feature",
  "properties": {
    "iso:country":"DE",
    "sg:address":"Margarethenstr. 8",
    "sg:city":"Kronberg",
    "sg:phone":"+49 6173/78541",
    "sg:postcode":"61476",
    "sg:province":"Hessen",
    "wof:name":"Beck Fliesen Und Kachelofenbau Gmbh",
    "wof:placetype":"venue"
},
  "geometry": {"coordinates":[8.5170450211,50.1840934753],"type":"Point"}
}