{
  "type": "Feature",
  "properties": {
    "iso:country":"DE",
    "sg:address":"Mainzer Str. 155",
    "sg:city":"Nackenheim",
    "sg:phone":"+49 6135/80374",
    "sg:postcode":"55299",
    "sg:province":"Rheinland-Pfalz",
    "wof:name":"R. N. Kerz Architekt",
    "wof:placetype":"venue"
},
  "geometry": {"coordinates":[8.328781,49.921074],"type":"Point"}
}