{
  "type": "Feature",
  "properties": {
    "iso:country":"DE",
    "sg:address":"Talstr. 2",
    "sg:city":"Wiehl",
    "sg:phone":"+49 2261/979181",
    "sg:postcode":"51674",
    "sg:province":"Nordrhein-Westfalen",
    "wof:name":"Dr. Med. Volker Br\u00fcckner",
    "wof:placetype":"venue"
},
  "geometry": {"coordinates":[7.5786128044,50.9813308716],"type":"Point"}
}