{
  "type": "Feature",
  "properties": {
    "iso:country":"DE",
    "sg:address":"Friedenstr. 16",
    "sg:city":"Crinitz",
    "sg:phone":"+49 35324/559",
    "sg:postcode":"03246",
    "sg:province":"Brandenburg",
    "wof:name":"Walter Keilholz Ingenieur",
    "wof:placetype":"venue"
},
  "geometry": {"coordinates":[13.7575750351,51.73620224],"type":"Point"}
}