{
  "type": "Feature",
  "properties": {
    "iso:country":"DE",
    "sg:address":"Kr\u00e4henb\u00fcschken 3",
    "sg:city":"M\u00fclheim",
    "sg:postcode":"45479",
    "sg:province":"Nordrhein-Westfalen",
    "wof:name":"Herglotz & Partner Steuerberatungs Gmbh",
    "wof:placetype":"venue"
},
  "geometry": {"coordinates":[6.847550869,51.4196662903],"type":"Point"}
}