{
  "type": "Feature",
  "properties": {
    "iso:country":"DE",
    "sg:address":"Friedenstr. 21",
    "sg:city":"Puchheim",
    "sg:phone":"+49 89/80078040",
    "sg:postcode":"82178",
    "sg:province":"Bayern",
    "wof:name":"Klaus Kuntze Medizin- Technik Vertriebs Gmbh",
    "wof:placetype":"venue"
},
  "geometry": {"coordinates":[11.368171,48.183037],"type":"Point"}
}