{
  "type": "Feature",
  "properties": {
    "iso:country":"DE",
    "sg:address":"Rosenstr. 51",
    "sg:city":"Schorndorf",
    "sg:phone":"+49 7181/20060",
    "sg:postcode":"73614",
    "sg:province":"Baden-W\u00fcrttemberg",
    "wof:name":"Siegle Wohnkomfort Kg",
    "wof:placetype":"venue"
},
  "geometry": {"coordinates":[9.521835,48.804893],"type":"Point"}
}