{
  "type": "Feature",
  "properties": {
    "iso:country":"DE",
    "sg:address":"Horstbohlen 159",
    "sg:city":"Hille",
    "sg:phone":"+49 5703/2346",
    "sg:postcode":"32479",
    "sg:province":"Nordrhein-Westfalen",
    "wof:name":"H. Fischer Kartoffel- Gro\u00dfhandel Gmbh, Hille",
    "wof:placetype":"venue"
},
  "geometry": {"coordinates":[8.7663822174,52.3548469543],"type":"Point"}
}