{
  "type": "Feature",
  "properties": {
    "iso:country":"DE",
    "sg:address":"Karl-Marx-Str. 9",
    "sg:city":"Zerbst",
    "sg:postcode":"39261",
    "sg:province":"Sachsen-Anhalt",
    "wof:name":"Zbe Melioration Gmbh",
    "wof:placetype":"venue"
},
  "geometry": {"coordinates":[12.087032,51.955833],"type":"Point"}
}