{
  "type": "Feature",
  "properties": {
    "iso:country":"DE",
    "sg:address":"Auenstr. 1",
    "sg:city":"Johanngeorgenstadt",
    "sg:phone":"+49 3773/505990",
    "sg:postcode":"08349",
    "sg:province":"Sachsen",
    "wof:name":"Pension Am Erzgebirgskamm",
    "wof:placetype":"venue"
},
  "geometry": {"coordinates":[12.7066650391,50.4306640625],"type":"Point"}
}