{
  "type": "Feature",
  "properties": {
    "iso:country":"DE",
    "sg:address":"M\u00fcnchener Str. 8",
    "sg:city":"Schwabhausen",
    "sg:postcode":"85247",
    "sg:province":"Bayern",
    "wof:name":"Rulim Verwaltung Gmbh",
    "wof:placetype":"venue"
},
  "geometry": {"coordinates":[11.357448,48.302837],"type":"Point"}
}