{
  "type": "Feature",
  "properties": {
    "iso:country":"DE",
    "sg:address":"Waldstr. 33",
    "sg:city":"Gaggenau",
    "sg:postcode":"76571",
    "sg:province":"Baden-W\u00fcrttemberg",
    "wof:name":"B\u00fchrer & Wehling Projekt Gmbh",
    "wof:placetype":"venue"
},
  "geometry": {"coordinates":[8.312702,48.800594],"type":"Point"}
}