{
  "type": "Feature",
  "properties": {
    "iso:country":"DE",
    "sg:address":"Frankenholzer Str. 111",
    "sg:city":"Bexbach",
    "sg:phone":"+49 6826/7516",
    "sg:postcode":"66450",
    "sg:province":"Saarland",
    "wof:name":"Pf\u00e4lzer Wald",
    "wof:placetype":"venue"
},
  "geometry": {"coordinates":[7.259953022,49.3629417419],"type":"Point"}
}