{
  "type": "Feature",
  "properties": {
    "iso:country":"DE",
    "sg:address":"Kreuzstr. 3",
    "sg:city":"Freyung",
    "sg:phone":"+49 8551/7081",
    "sg:postcode":"94078",
    "sg:province":"Bayern",
    "wof:name":"Otto Kloiber",
    "wof:placetype":"venue"
},
  "geometry": {"coordinates":[13.540877,48.825382],"type":"Point"}
}