{
  "type": "Feature",
  "properties": {
    "iso:country":"DE",
    "sg:address":"Neuenfelder Str. 19",
    "sg:city":"Jork",
    "sg:postcode":"21635",
    "sg:province":"Niedersachsen",
    "wof:name":"Ms Corsar Gebr. Winter Reedereigesellschaft",
    "wof:placetype":"venue"
},
  "geometry": {"coordinates":[9.7417230606,53.5254554749],"type":"Point"}
}