{
  "type": "Feature",
  "properties": {
    "iso:country":"DE",
    "sg:address":"Eichenstr. 40",
    "sg:city":"Duisburg",
    "sg:phone":"+49 2065/80363",
    "sg:postcode":"47228",
    "sg:province":"Nordrhein-Westfalen",
    "wof:name":"Meyer Und Josten Reiseb\u00fcro",
    "wof:placetype":"venue"
},
  "geometry": {"coordinates":[6.678437233,51.4194145203],"type":"Point"}
}