{
  "type": "Feature",
  "properties": {
    "iso:country":"DE",
    "sg:address":"Frauenschuhweg 5 a",
    "sg:city":"Berlin",
    "sg:phone":"+49 30/6615268",
    "sg:postcode":"12357",
    "sg:province":"Berlin",
    "wof:name":"Klaus Finger",
    "wof:placetype":"venue"
},
  "geometry": {"coordinates":[13.492255,52.434196],"type":"Point"}
}