{
  "type": "Feature",
  "properties": {
    "iso:country":"DE",
    "sg:address":"Rodbachstr. 7",
    "sg:city":"Pfaffenhofen",
    "sg:phone":"+49 7046/96190",
    "sg:postcode":"74397",
    "sg:province":"Baden-W\u00fcrttemberg",
    "wof:name":"Koch Gmbh",
    "wof:placetype":"venue"
},
  "geometry": {"coordinates":[8.975028038,49.0620613098],"type":"Point"}
}