{
  "type": "Feature",
  "properties": {
    "iso:country":"DE",
    "sg:address":"Vennerstr. 17",
    "sg:city":"Ostercappeln",
    "sg:phone":"+49 4954/731807",
    "sg:postcode":"49179",
    "sg:province":"Niedersachsen",
    "wof:name":"Franz Berghegger",
    "wof:placetype":"venue"
},
  "geometry": {"coordinates":[8.223226,52.3461],"type":"Point"}
}