{
  "type": "Feature",
  "properties": {
    "iso:country":"DE",
    "sg:address":"Friedensstr. 26",
    "sg:city":"Wadgassen",
    "sg:phone":"+49 6834/42290",
    "sg:postcode":"66787",
    "sg:province":"Saarland",
    "wof:name":"Helmut Scheerer Steuerberater",
    "wof:placetype":"venue"
},
  "geometry": {"coordinates":[6.7872190475,49.2634963989],"type":"Point"}
}