{
  "type": "Feature",
  "properties": {
    "iso:country":"DE",
    "sg:address":"Marktplatz 2",
    "sg:city":"Ilsenburg",
    "sg:phone":"+49 39452/9393",
    "sg:postcode":"38871",
    "sg:province":"Sachsen-Anhalt",
    "wof:name":"Landhaus Zu Den Roten Forellen R. Und H. Prause Ohg",
    "wof:placetype":"venue"
},
  "geometry": {"coordinates":[10.6766519547,51.8640632629],"type":"Point"}
}