{
  "type": "Feature",
  "properties": {
    "iso:country":"DE",
    "sg:address":"Lynarstr. 9",
    "sg:city":"Berlin",
    "sg:phone":"+49 30/8904880",
    "sg:postcode":"14193",
    "sg:province":"Berlin",
    "wof:name":"Landthaler Verm\u00f6gens- Verwaltungs Gmbh",
    "wof:placetype":"venue"
},
  "geometry": {"coordinates":[13.2833814621,52.4896430969],"type":"Point"}
}