{
  "type": "Feature",
  "properties": {
    "iso:country":"DE",
    "sg:address":"Speckacker 3",
    "sg:city":"Dortmund",
    "sg:phone":"+49 231/9893000",
    "sg:postcode":"44329",
    "sg:province":"Nordrhein-Westfalen",
    "wof:name":"Ib Deutschland Gmbh",
    "wof:placetype":"venue"
},
  "geometry": {"coordinates":[7.5037379265,51.5534706116],"type":"Point"}
}