{
  "type": "Feature",
  "properties": {
    "iso:country":"DE",
    "sg:address":"Bessunger Str. 54",
    "sg:city":"Darmstadt",
    "sg:phone":"+49 6151/63984",
    "sg:postcode":"64285",
    "sg:province":"Hessen",
    "wof:name":"Petra Kalbfuss",
    "wof:placetype":"venue"
},
  "geometry": {"coordinates":[8.651489,49.857971],"type":"Point"}
}