{
  "type": "Feature",
  "properties": {
    "iso:country":"DE",
    "sg:address":"Grafschafter Str. 28",
    "sg:city":"Duisburg",
    "sg:phone":"+49 2841/80480",
    "sg:postcode":"47199",
    "sg:province":"Nordrhein-Westfalen",
    "wof:name":"B\u00e4rler-apotheke",
    "wof:placetype":"venue"
},
  "geometry": {"coordinates":[6.681865,51.494133],"type":"Point"}
}