{
  "type": "Feature",
  "properties": {
    "iso:country":"DE",
    "sg:address":"Nei\u00dfestr. 200",
    "sg:city":"Salzgitter",
    "sg:phone":"+49 5341/44300",
    "sg:postcode":"38226",
    "sg:province":"Niedersachsen",
    "wof:name":"Vereinsgastst\u00e4tte Marienbruch Kleingartenverein E. V.",
    "wof:placetype":"venue"
},
  "geometry": {"coordinates":[10.3461608887,52.1568031311],"type":"Point"}
}