{
  "type": "Feature",
  "properties": {
    "iso:country":"DE",
    "sg:address":"Stiftstr. 1",
    "sg:city":"Sondershausen",
    "sg:postcode":"99706",
    "sg:province":"Th\u00fcringen",
    "wof:name":"Pflegeheim",
    "wof:placetype":"venue"
},
  "geometry": {"coordinates":[10.875843,51.370075],"type":"Point"}
}