{
  "type": "Feature",
  "properties": {
    "iso:country":"DE",
    "sg:address":"Trostberger Str. 12",
    "sg:city":"Kirchweidach",
    "sg:phone":"+49 8623/669",
    "sg:postcode":"84558",
    "sg:province":"Bayern",
    "wof:name":"Millihaus",
    "wof:placetype":"venue"
},
  "geometry": {"coordinates":[12.6378221512,48.0817184448],"type":"Point"}
}