{
  "type": "Feature",
  "properties": {
    "iso:country":"DE",
    "sg:address":"Bahnhofstr. 4",
    "sg:city":"Frankleben",
    "sg:phone":"+49 34637/50417",
    "sg:postcode":"06259",
    "sg:province":"Sachsen-Anhalt",
    "wof:name":"Eiscafe M\u00fcckenheim",
    "wof:placetype":"venue"
},
  "geometry": {"coordinates":[11.937631,51.310349],"type":"Point"}
}