{
  "type": "Feature",
  "properties": {
    "iso:country":"DE",
    "sg:address":"Borther Str. 215",
    "sg:city":"Rheinberg",
    "sg:phone":"+49 2802/6898",
    "sg:postcode":"47495",
    "sg:province":"Nordrhein-Westfalen",
    "wof:name":"Borther Hof",
    "wof:placetype":"venue"
},
  "geometry": {"coordinates":[6.5712199211,51.5836486816],"type":"Point"}
}