{
  "type": "Feature",
  "properties": {
    "iso:country":"DE",
    "sg:address":"Langer Kornweg 34 C",
    "sg:city":"Kelsterbach",
    "sg:phone":"+49 6107/7740",
    "sg:postcode":"65451",
    "sg:province":"Hessen",
    "wof:name":"Nippon Express Deutschland Gmbh",
    "wof:placetype":"venue"
},
  "geometry": {"coordinates":[8.521055,50.056004],"type":"Point"}
}