{
  "type": "Feature",
  "properties": {
    "iso:country":"DE",
    "sg:address":"Untere Sagestr. 7",
    "sg:city":"Altenbeken",
    "sg:phone":"+49 5255/6449",
    "sg:postcode":"33184",
    "sg:province":"Nordrhein-Westfalen",
    "wof:name":"Albert Dreps Masseur",
    "wof:placetype":"venue"
},
  "geometry": {"coordinates":[8.946357,51.763798],"type":"Point"}
}