{
  "type": "Feature",
  "properties": {
    "iso:country":"DE",
    "sg:address":"Waldstr. 9",
    "sg:city":"Pfinztal",
    "sg:phone":"+49 7240/7149",
    "sg:postcode":"76327",
    "sg:province":"Baden-W\u00fcrttemberg",
    "wof:name":"Horst Duttenhofer",
    "wof:placetype":"venue"
},
  "geometry": {"coordinates":[8.544896,48.984055],"type":"Point"}
}