{
  "type": "Feature",
  "properties": {
    "iso:country":"DE",
    "sg:address":"Mittelstr. 93",
    "sg:city":"Hilden",
    "sg:phone":"+49 2103/51194",
    "sg:postcode":"40721",
    "sg:province":"Nordrhein-Westfalen",
    "wof:name":"Wolff Inh. C. Kern",
    "wof:placetype":"venue"
},
  "geometry": {"coordinates":[6.932532,51.168049],"type":"Point"}
}