{
  "type": "Feature",
  "properties": {
    "iso:country":"DE",
    "sg:address":"Schlo\u00dfplatz 1a",
    "sg:city":"Celle",
    "sg:phone":"+49 5141/481590",
    "sg:postcode":"29221",
    "sg:province":"Niedersachsen",
    "wof:name":"Winkelmann Reiseunter- Nehmen Gmbh",
    "wof:placetype":"venue"
},
  "geometry": {"coordinates":[10.0793142319,52.6240692139],"type":"Point"}
}