{
  "type": "Feature",
  "properties": {
    "iso:country":"DE",
    "sg:address":"Osterbekstr. 90c",
    "sg:city":"Hamburg",
    "sg:phone":"+49 4970/425791",
    "sg:postcode":"22083",
    "sg:province":"Hamburg",
    "wof:name":"Astorga F. Lange Gmbh & Co",
    "wof:placetype":"venue"
},
  "geometry": {"coordinates":[8.9601926804,48.9321136475],"type":"Point"}
}