{
  "type": "Feature",
  "properties": {
    "iso:country":"DE",
    "sg:address":"Langesb\u00fchlweg 2",
    "sg:city":"Geroldsgr\u00fcn",
    "sg:phone":"+49 9288/8216",
    "sg:postcode":"95179",
    "sg:province":"Bayern",
    "wof:name":"Wirth Bedachungen Ohg",
    "wof:placetype":"venue"
},
  "geometry": {"coordinates":[11.5923519135,50.3518981934],"type":"Point"}
}