{
  "type": "Feature",
  "properties": {
    "iso:country":"DE",
    "sg:address":"Lankenweg 27b",
    "sg:city":"Brandenburg",
    "sg:phone":"+49 33839/61455",
    "sg:postcode":"14774",
    "sg:province":"Brandenburg",
    "wof:name":"Wolfgang Fried",
    "wof:placetype":"venue"
},
  "geometry": {"coordinates":[12.397848,52.363701],"type":"Point"}
}