{
  "type": "Feature",
  "properties": {
    "iso:country":"DE",
    "sg:address":"Braunser Hammerweg 12",
    "sg:city":"Bad Arolsen",
    "sg:phone":"+49 5691/5119",
    "sg:postcode":"34454",
    "sg:province":"Hessen",
    "wof:name":"Horst Gottmann",
    "wof:placetype":"venue"
},
  "geometry": {"coordinates":[9.03711,51.349239],"type":"Point"}
}