{
  "type": "Feature",
  "properties": {
    "iso:country":"DE",
    "sg:address":"Landsberger Str. 201",
    "sg:city":"M\u00fcnchen",
    "sg:phone":"+49 89/54763260",
    "sg:postcode":"80687",
    "sg:province":"Bayern",
    "wof:name":"Taxata Steuerberatungsges. Mbh",
    "wof:placetype":"venue"
},
  "geometry": {"coordinates":[11.5173835754,48.1413116455],"type":"Point"}
}