{
  "type": "Feature",
  "properties": {
    "iso:country":"DE",
    "sg:address":"Karl-Otto-Zander-Str. 10",
    "sg:city":"Naila",
    "sg:phone":"+49 9282/7593",
    "sg:postcode":"95119",
    "sg:province":"Bayern",
    "wof:name":"Gerhard Wolfrum",
    "wof:placetype":"venue"
},
  "geometry": {"coordinates":[11.709459,50.323284],"type":"Point"}
}