{
  "type": "Feature",
  "properties": {
    "iso:country":"DE",
    "sg:address":"Helgastr. 19",
    "sg:city":"Langenfeld",
    "sg:phone":"+49 2173/73167",
    "sg:postcode":"40764",
    "sg:province":"Nordrhein-Westfalen",
    "wof:name":"Uwe Petersen Ingenieur",
    "wof:placetype":"venue"
},
  "geometry": {"coordinates":[6.9484710693,51.1337738037],"type":"Point"}
}