{
  "type": "Feature",
  "properties": {
    "iso:country":"DE",
    "sg:address":"Merianstr. 1 -3",
    "sg:city":"Oppenheim",
    "sg:phone":"+49 6133/933799",
    "sg:postcode":"55276",
    "sg:province":"Rheinland-Pfalz",
    "wof:name":"Holger Bergh\u00e4user Ergotherapiepraxis",
    "wof:placetype":"venue"
},
  "geometry": {"coordinates":[8.355115,49.852711],"type":"Point"}
}