{
  "type": "Feature",
  "properties": {
    "iso:country":"DE",
    "sg:address":"Lindenhof 2",
    "sg:city":"Geislingen",
    "sg:phone":"+49 7331/42775",
    "sg:postcode":"73312",
    "sg:province":"Baden-W\u00fcrttemberg",
    "wof:name":"Hans Wittlinger",
    "wof:placetype":"venue"
},
  "geometry": {"coordinates":[8.812347,48.28688],"type":"Point"}
}