{
  "type": "Feature",
  "properties": {
    "iso:country":"DE",
    "sg:address":"P\u00f6litzstr 81",
    "sg:city":"Hohenstein-Ernstthal",
    "sg:phone":"+49 3723/411234",
    "sg:postcode":"09337",
    "sg:province":"Sachsen",
    "wof:name":"Jura-guss Gmbh",
    "wof:placetype":"venue"
},
  "geometry": {"coordinates":[12.725051,50.802525],"type":"Point"}
}