{
  "type": "Feature",
  "properties": {
    "iso:country":"DE",
    "sg:address":"Basler Str. 28",
    "sg:city":"L\u00f6rrach",
    "sg:phone":"+49 7621/3171",
    "sg:postcode":"79540",
    "sg:province":"Baden-W\u00fcrttemberg",
    "wof:name":"Franz Schmider Immobilienmakler",
    "wof:placetype":"venue"
},
  "geometry": {"coordinates":[7.6591649055,47.6029014587],"type":"Point"}
}