{
  "type": "Feature",
  "properties": {
    "iso:country":"DE",
    "sg:address":"Badangerstr. 10",
    "sg:city":"Knetzgau",
    "sg:phone":"+49 9527/382",
    "sg:postcode":"97478",
    "sg:province":"Bayern",
    "wof:name":"Leo Weinkauf",
    "wof:placetype":"venue"
},
  "geometry": {"coordinates":[10.5426549911,49.9986953735],"type":"Point"}
}