{
  "type": "Feature",
  "properties": {
    "iso:country":"DE",
    "sg:address":"Eichh\u00f6rnchenweg 4",
    "sg:city":"Lingen",
    "sg:phone":"+49 591/9150020",
    "sg:postcode":"49808",
    "sg:province":"Niedersachsen",
    "wof:name":"Christoph Dust E. K.",
    "wof:placetype":"venue"
},
  "geometry": {"coordinates":[7.3035669327,52.5408668518],"type":"Point"}
}