{
  "type": "Feature",
  "properties": {
    "iso:country":"DE",
    "sg:address":"Jahnstr. 29",
    "sg:city":"Wei\u00dfenburg",
    "sg:phone":"+49 9141/5151",
    "sg:postcode":"91781",
    "sg:province":"Bayern",
    "wof:name":"A. Gromoll",
    "wof:placetype":"venue"
},
  "geometry": {"coordinates":[10.9767246246,49.034450531],"type":"Point"}
}