{
  "type": "Feature",
  "properties": {
    "iso:country":"DE",
    "sg:address":"Pfarrhofstr. 15",
    "sg:city":"Breitnau",
    "sg:phone":"+49 7674/8420",
    "sg:postcode":"79874",
    "sg:province":"Baden-W\u00fcrttemberg",
    "wof:name":"Hotel Todtmooser Hof",
    "wof:placetype":"venue"
},
  "geometry": {"coordinates":[8.073923111,47.9408493042],"type":"Point"}
}