{
  "type": "Feature",
  "properties": {
    "iso:country":"DE",
    "sg:address":"Theodor-Heuss-Str. 2",
    "sg:city":"F\u00fcrth",
    "sg:phone":"+49 911/97685690",
    "sg:postcode":"90765",
    "sg:province":"Bayern",
    "wof:name":"Adler-apotheke",
    "wof:placetype":"venue"
},
  "geometry": {"coordinates":[10.977296,49.508038],"type":"Point"}
}