{
  "type": "Feature",
  "properties": {
    "iso:country":"DE",
    "sg:address":"Bockumer Str. 350",
    "sg:city":"D\u00fcsseldorf",
    "sg:phone":"+49 211/400042",
    "sg:postcode":"40489",
    "sg:province":"Nordrhein-Westfalen",
    "wof:name":"R. Hafermalz",
    "wof:placetype":"venue"
},
  "geometry": {"coordinates":[6.724396,51.331512],"type":"Point"}
}