{
  "type": "Feature",
  "properties": {
    "iso:country":"DE",
    "sg:address":"Steinbeisstr. 14",
    "sg:city":"Heidenheim",
    "sg:phone":"+49 7321/949960",
    "sg:postcode":"89518",
    "sg:province":"Baden-W\u00fcrttemberg",
    "wof:name":"B\u00f6y\u00fck & Coban",
    "wof:placetype":"venue"
},
  "geometry": {"coordinates":[10.1268644333,48.6813278198],"type":"Point"}
}