{
  "type": "Feature",
  "properties": {
    "iso:country":"DE",
    "sg:address":"Beckstr. 21",
    "sg:city":"Lingen",
    "sg:postcode":"49809",
    "sg:province":"Niedersachsen",
    "wof:name":"Bwl Betonwerk Lingen Verwaltungs Gmbh",
    "wof:placetype":"venue"
},
  "geometry": {"coordinates":[7.335722,52.53344],"type":"Point"}
}