{
  "type": "Feature",
  "properties": {
    "iso:country":"DE",
    "sg:address":"Beethovenstr. 51",
    "sg:city":"Helmbrechts",
    "sg:phone":"+49 9252/5298",
    "sg:postcode":"95233",
    "sg:province":"Bayern",
    "wof:name":"A. Neudert",
    "wof:placetype":"venue"
},
  "geometry": {"coordinates":[11.7090244293,50.2369384766],"type":"Point"}
}