{
  "type": "Feature",
  "properties": {
    "iso:country":"DE",
    "sg:address":"Viktoriastr 39",
    "sg:city":"Koblenz",
    "sg:phone":"+49 261/309676",
    "sg:postcode":"56068",
    "sg:province":"Rheinland-Pfalz",
    "wof:name":"L & P Ges. F\u00fcr Medizinischen Laborbedarf Mbh",
    "wof:placetype":"venue"
},
  "geometry": {"coordinates":[7.594334,50.355556],"type":"Point"}
}