{
  "type": "Feature",
  "properties": {
    "iso:country":"DE",
    "sg:address":"Kiefernweg 4",
    "sg:city":"Wickede",
    "sg:phone":"+49 2377/4175",
    "sg:postcode":"58739",
    "sg:province":"Nordrhein-Westfalen",
    "wof:name":"Klaus-dieter Siefke",
    "wof:placetype":"venue"
},
  "geometry": {"coordinates":[7.8595890999,51.4987602234],"type":"Point"}
}