{
  "type": "Feature",
  "properties": {
    "iso:country":"DE",
    "sg:address":"Badstr. 6-8",
    "sg:city":"Waldshut-Tiengen",
    "sg:phone":"+49 7741/66265",
    "sg:postcode":"79761",
    "sg:province":"Baden-W\u00fcrttemberg",
    "wof:name":"Hmt-aluminiumprofile- Vertrieb- Gmbh",
    "wof:placetype":"venue"
},
  "geometry": {"coordinates":[8.267203,47.631599],"type":"Point"}
}