{
  "type": "Feature",
  "properties": {
    "iso:country":"DE",
    "sg:address":"Nagolder Str. 1",
    "sg:city":"Ammerbuch",
    "sg:phone":"+49 7073/6259",
    "sg:postcode":"72119",
    "sg:province":"Baden-W\u00fcrttemberg",
    "wof:name":"Apotheke Am Bahnhof Inh. Dr. Peter Gundlach",
    "wof:placetype":"venue"
},
  "geometry": {"coordinates":[8.966796,48.53091],"type":"Point"}
}