{
  "type": "Feature",
  "properties": {
    "iso:country":"DE",
    "sg:address":"Grotestr 10",
    "sg:city":"Essen",
    "sg:phone":"+49 201/848030",
    "sg:postcode":"45257",
    "sg:province":"Nordrhein-Westfalen",
    "wof:name":"Espey Werbeagentur Gmbh",
    "wof:placetype":"venue"
},
  "geometry": {"coordinates":[7.089375,51.392872],"type":"Point"}
}