{
  "type": "Feature",
  "properties": {
    "iso:country":"DE",
    "sg:address":"Kurf\u00fcrst-Philipp-Str. 3",
    "sg:city":"Neumarkt",
    "sg:phone":"+49 9181/43373",
    "sg:postcode":"92318",
    "sg:province":"Bayern",
    "wof:name":"Harry Kulnig Gmbh",
    "wof:placetype":"venue"
},
  "geometry": {"coordinates":[11.4856815338,49.2824745178],"type":"Point"}
}