{
  "type": "Feature",
  "properties": {
    "iso:country":"DE",
    "sg:address":"Hermannstr. 27",
    "sg:city":"Neuwied",
    "sg:phone":"+49 2631/25700",
    "sg:postcode":"56564",
    "sg:province":"Rheinland-Pfalz",
    "wof:name":"Klaus Haubrich Ingenieur",
    "wof:placetype":"venue"
},
  "geometry": {"coordinates":[7.4637460709,50.4290275574],"type":"Point"}
}