{
  "type": "Feature",
  "properties": {
    "iso:country":"DE",
    "sg:address":"W\u00f6rthstr. 1",
    "sg:city":"M\u00fcnchen",
    "sg:phone":"+49 89/4890670",
    "sg:postcode":"81667",
    "sg:province":"Bayern",
    "wof:name":"Heigl & Meyer Gmbh",
    "wof:placetype":"venue"
},
  "geometry": {"coordinates":[11.597876,48.132271],"type":"Point"}
}