{
  "type": "Feature",
  "properties": {
    "iso:country":"DE",
    "sg:address":"Im Rank 12",
    "sg:city":"Pl\u00fcderhausen",
    "sg:phone":"+49 7181/81222",
    "sg:postcode":"73655",
    "sg:province":"Baden-W\u00fcrttemberg",
    "wof:name":"Greiner & Rube Gmbh & Co. Kg",
    "wof:placetype":"venue"
},
  "geometry": {"coordinates":[9.602371,48.794762],"type":"Point"}
}