{
  "type": "Feature",
  "properties": {
    "iso:country":"DE",
    "sg:address":"Neustr. 31",
    "sg:city":"Eschweiler",
    "sg:phone":"+49 2403/22626",
    "sg:postcode":"52249",
    "sg:province":"Nordrhein-Westfalen",
    "wof:name":"Mans & Laurs",
    "wof:placetype":"venue"
},
  "geometry": {"coordinates":[6.2675461769,50.8181419373],"type":"Point"}
}