{
  "type": "Feature",
  "properties": {
    "iso:country":"DE",
    "sg:address":"Heinrichsallee 62",
    "sg:city":"Aachen",
    "sg:phone":"+49 241/535848",
    "sg:postcode":"52062",
    "sg:province":"Nordrhein-Westfalen",
    "wof:name":"Peter Jordens Praxis F\u00fcr Krankengymnastik",
    "wof:placetype":"venue"
},
  "geometry": {"coordinates":[6.095001,50.777401],"type":"Point"}
}