{
  "type": "Feature",
  "properties": {
    "iso:country":"DE",
    "sg:address":"Dorfstr 65a",
    "sg:city":"Frankfurt",
    "sg:phone":"+49 335/387183",
    "sg:postcode":"15236",
    "sg:province":"Brandenburg",
    "wof:name":"Saz Schwei\u00dftechnik Gmbh & Co Kg",
    "wof:placetype":"venue"
},
  "geometry": {"coordinates":[14.4418449402,52.2824058533],"type":"Point"}
}