{
  "type": "Feature",
  "properties": {
    "iso:country":"DE",
    "sg:address":"Vogelstr. 1",
    "sg:city":"Forchheim",
    "sg:phone":"+49 9191/2480",
    "sg:postcode":"91301",
    "sg:province":"Bayern",
    "wof:name":"M. Vogel",
    "wof:placetype":"venue"
},
  "geometry": {"coordinates":[11.062549,49.718933],"type":"Point"}
}