{
  "type": "Feature",
  "properties": {
    "iso:country":"DE",
    "sg:address":"Michael-H\u00f6rauf-Weg 6",
    "sg:city":"Boll",
    "sg:phone":"+49 7164/3149",
    "sg:postcode":"73087",
    "sg:province":"Baden-W\u00fcrttemberg",
    "wof:name":"Rudolf-steiner-seminar F\u00fcr Heilp\u00e4dagogik",
    "wof:placetype":"venue"
},
  "geometry": {"coordinates":[9.5974960327,48.636844635],"type":"Point"}
}