{
  "type": "Feature",
  "properties": {
    "iso:country":"DE",
    "sg:address":"Am Angertor 74",
    "sg:city":"Dornheim",
    "sg:phone":"+49 3628/640479",
    "sg:postcode":"99310",
    "sg:province":"Th\u00fcringen",
    "wof:name":"Vereinslokal",
    "wof:placetype":"venue"
},
  "geometry": {"coordinates":[10.9899187088,50.8350028992],"type":"Point"}
}