{
  "type": "Feature",
  "properties": {
    "iso:country":"DE",
    "sg:address":"Merseburger Str. 110",
    "sg:city":"Halle",
    "sg:phone":"+49 345/4448104",
    "sg:postcode":"06110",
    "sg:province":"Sachsen-Anhalt",
    "wof:name":"Steffi Remmler",
    "wof:placetype":"venue"
},
  "geometry": {"coordinates":[11.983435,51.464947],"type":"Point"}
}