{
  "type": "Feature",
  "properties": {
    "iso:country":"DE",
    "sg:address":"Ringbergstr. 1",
    "sg:city":"M\u00fcnchen",
    "sg:phone":"+49 89/4316077",
    "sg:postcode":"81673",
    "sg:province":"Bayern",
    "wof:name":"Werttransporte Dipl.-kfm. H. Ehrl Gmbh",
    "wof:placetype":"venue"
},
  "geometry": {"coordinates":[11.6430892944,48.1265640259],"type":"Point"}
}