{
  "type": "Feature",
  "properties": {
    "iso:country":"DE",
    "sg:address":"Ernst-Th\u00e4lmann-Weg 20",
    "sg:city":"Freienhagen",
    "sg:phone":"+49 33051/25369",
    "sg:postcode":"16515",
    "sg:province":"Brandenburg",
    "wof:name":"Tib Technische Immobilien Betreuung Kruschinski Gmbh",
    "wof:placetype":"venue"
},
  "geometry": {"coordinates":[13.2771310806,52.8268890381],"type":"Point"}
}