{
  "type": "Feature",
  "properties": {
    "iso:country":"DE",
    "sg:address":"Dieselstr. 13",
    "sg:city":"Freigericht",
    "sg:phone":"+49 6055/912120",
    "sg:postcode":"63579",
    "sg:province":"Hessen",
    "wof:name":"Gottfried Br\u00fcckner Steuerberater",
    "wof:placetype":"venue"
},
  "geometry": {"coordinates":[9.1086511612,50.1449203491],"type":"Point"}
}