{
  "type": "Feature",
  "properties": {
    "iso:country":"DE",
    "sg:address":"S\u00fcderstr. 9",
    "sg:city":"Meldorf",
    "sg:phone":"+49 4832/1326",
    "sg:postcode":"25704",
    "sg:province":"Schleswig-Holstein",
    "wof:name":"Richard Hardekopf",
    "wof:placetype":"venue"
},
  "geometry": {"coordinates":[9.0716485977,54.0889968872],"type":"Point"}
}