{
  "type": "Feature",
  "properties": {
    "iso:country":"DE",
    "sg:city":"Frankfurt/Main",
    "sg:postcode":"60000",
    "wof:name":"Show-center",
    "wof:placetype":"venue"
},
  "geometry": {"coordinates":[8.272315,50.000561],"type":"Point"}
}