{
  "type": "Feature",
  "properties": {
    "iso:country":"DE",
    "sg:address":"Weberstr. 17",
    "sg:city":"Weinheim",
    "sg:postcode":"69469",
    "sg:province":"Baden-W\u00fcrttemberg",
    "wof:name":"Stm Medizintechnik Starnberg Gmbh",
    "wof:placetype":"venue"
},
  "geometry": {"coordinates":[8.6633911133,49.5404167175],"type":"Point"}
}