{
  "type": "Feature",
  "properties": {
    "iso:country":"DE",
    "sg:address":"Marktplatz 1",
    "sg:city":"Hohenburg",
    "sg:phone":"+49 9626/265",
    "sg:postcode":"92277",
    "sg:province":"Bayern",
    "wof:name":"G. H\u00f6llriegl",
    "wof:placetype":"venue"
},
  "geometry": {"coordinates":[11.798539,49.295216],"type":"Point"}
}