{
  "type": "Feature",
  "properties": {
    "iso:country":"DE",
    "sg:address":"Taunusstr. 23",
    "sg:city":"Wehrheim",
    "sg:phone":"+49 6081/2169",
    "sg:postcode":"61273",
    "sg:province":"Hessen",
    "wof:name":"Alexander Friedrich",
    "wof:placetype":"venue"
},
  "geometry": {"coordinates":[8.6172399521,50.3424034119],"type":"Point"}
}