{
  "type": "Feature",
  "properties": {
    "iso:country":"DE",
    "sg:address":"Stahlschmiede 3",
    "sg:city":"Iserlohn",
    "sg:phone":"+49 2371/370000",
    "sg:postcode":"58636",
    "sg:province":"Nordrhein-Westfalen",
    "wof:name":"Taxi K\u00e4mpgen Inh. Erika Br\u00fcggemeier E. K.",
    "wof:placetype":"venue"
},
  "geometry": {"coordinates":[7.7026438713,51.3745574951],"type":"Point"}
}