{
  "type": "Feature",
  "properties": {
    "iso:country":"DE",
    "sg:address":"Aronweg 33",
    "sg:city":"Essen",
    "sg:phone":"+49 4920/1851230",
    "sg:postcode":"45276",
    "sg:province":"Nordrhein-Westfalen",
    "wof:name":"Spedition L\u00dcbke Transport Gmbh",
    "wof:placetype":"venue"
},
  "geometry": {"coordinates":[7.0717811584,51.4513282776],"type":"Point"}
}