{
  "type": "Feature",
  "properties": {
    "iso:country":"DE",
    "sg:address":"Schulstra\u00dfe 31",
    "sg:city":"Nienst\u00e4dt",
    "sg:phone":"+49 5724",
    "sg:postcode":"31688",
    "sg:province":"Niedersachsen",
    "wof:name":"Feuerwehr Liekwegen",
    "wof:placetype":"venue"
},
  "geometry": {"coordinates":[9.1677484512,52.2845001221],"type":"Point"}
}