{
  "type": "Feature",
  "properties": {
    "iso:country":"DE",
    "sg:address":"B\u00f6rdestr. 29",
    "sg:city":"Welver",
    "sg:phone":"+49 2921/80490",
    "sg:postcode":"59514",
    "sg:province":"Nordrhein-Westfalen",
    "wof:name":"U. Heinermann Gmbh",
    "wof:placetype":"venue"
},
  "geometry": {"coordinates":[8.03946,51.602509],"type":"Point"}
}