{
  "type": "Feature",
  "properties": {
    "iso:country":"DE",
    "sg:address":"Kaesenstr. 21",
    "sg:city":"K\u00f6ln",
    "sg:phone":"+49 221/316347",
    "sg:postcode":"50677",
    "sg:province":"Nordrhein-Westfalen",
    "wof:name":"Karl Haake Ingenieur",
    "wof:placetype":"venue"
},
  "geometry": {"coordinates":[6.946269989,50.9239349365],"type":"Point"}
}