{
  "type": "Feature",
  "properties": {
    "iso:country":"DE",
    "sg:address":"Lindenstr. 56",
    "sg:city":"Tamm",
    "sg:phone":"+49 7141/601554",
    "sg:postcode":"71732",
    "sg:province":"Baden-W\u00fcrttemberg",
    "wof:name":"A. Raugust",
    "wof:placetype":"venue"
},
  "geometry": {"coordinates":[9.1297941208,48.923915863],"type":"Point"}
}