{
  "type": "Feature",
  "properties": {
    "iso:country":"DE",
    "sg:address":"Oschatzer Str. 1",
    "sg:city":"Dresden",
    "sg:phone":"+49 351/8489217",
    "sg:postcode":"01127",
    "sg:province":"Sachsen",
    "wof:name":"Bernd Michael",
    "wof:placetype":"venue"
},
  "geometry": {"coordinates":[13.722863,51.074905],"type":"Point"}
}