{
  "type": "Feature",
  "properties": {
    "iso:country":"DE",
    "sg:address":"Krummeck 28",
    "sg:city":"L\u00fcbeck",
    "sg:phone":"+49 451/593640",
    "sg:postcode":"23562",
    "sg:province":"Schleswig-Holstein",
    "wof:name":"Spezial-fachbetrieb Kl. Behse Selbstbauelem. F. Haus U. Gar.",
    "wof:placetype":"venue"
},
  "geometry": {"coordinates":[10.705404,53.84557],"type":"Point"}
}