{
  "type": "Feature",
  "properties": {
    "iso:country":"DE",
    "sg:address":"Zeltplatzstr. 2",
    "sg:city":"Karlshagen",
    "sg:phone":"+49 38371/20404",
    "sg:postcode":"17449",
    "sg:province":"Mecklenburg-Vorpommern",
    "wof:name":"Hotel Am Meer",
    "wof:placetype":"venue"
},
  "geometry": {"coordinates":[13.8412618637,54.1206092834],"type":"Point"}
}