{
  "type": "Feature",
  "properties": {
    "iso:country":"DE",
    "sg:address":"Tullastr. 19",
    "sg:city":"Altlu\u00dfheim",
    "sg:postcode":"68804",
    "sg:province":"Baden-W\u00fcrttemberg",
    "wof:name":"Face Music Verlag Und Tonstudio",
    "wof:placetype":"venue"
},
  "geometry": {"coordinates":[8.5017776489,49.3037376404],"type":"Point"}
}