{
  "type": "Feature",
  "properties": {
    "iso:country":"DE",
    "sg:address":"Hauptstr. 81",
    "sg:city":"Guntersblum",
    "sg:phone":"+49 6249/2234",
    "sg:postcode":"67583",
    "sg:province":"Rheinland-Pfalz",
    "wof:name":"Karl-heinz Frey",
    "wof:placetype":"venue"
},
  "geometry": {"coordinates":[8.3445186615,49.8001670837],"type":"Point"}
}