{
  "type": "Feature",
  "properties": {
    "iso:country":"DE",
    "sg:address":"Marie-Curie-Str. 6",
    "sg:city":"Gro\u00df-Umstadt",
    "sg:postcode":"64823",
    "sg:province":"Hessen",
    "wof:name":"Has Clean Industrieservice Gmbh",
    "wof:placetype":"venue"
},
  "geometry": {"coordinates":[8.9303026199,49.8650665283],"type":"Point"}
}