{
  "type": "Feature",
  "properties": {
    "iso:country":"DE",
    "sg:address":"Tangerm\u00fcnder Str. 106",
    "sg:city":"Berlin",
    "sg:phone":"+49 30/9985799",
    "sg:postcode":"12627",
    "sg:province":"Berlin",
    "wof:name":"La Galea",
    "wof:placetype":"venue"
},
  "geometry": {"coordinates":[13.607790947,52.5409851074],"type":"Point"}
}