{
  "type": "Feature",
  "properties": {
    "iso:country":"DE",
    "sg:address":"An der Stadthalle",
    "sg:city":"Bad Neustadt",
    "sg:phone":"+49 9771/92290",
    "sg:postcode":"97616",
    "sg:province":"Bayern",
    "wof:name":"Walter Preh Stiftung",
    "wof:placetype":"venue"
},
  "geometry": {"coordinates":[10.2110500336,50.3193244934],"type":"Point"}
}