{
  "type": "Feature",
  "properties": {
    "iso:country":"DE",
    "sg:address":"Obertal 9",
    "sg:city":"Stegen",
    "sg:phone":"+49 4976/616726",
    "sg:postcode":"79252",
    "sg:province":"Baden-W\u00fcrttemberg",
    "wof:name":"Zipfel Klaus Zimmerei-s\u00c4gewerk-holzbau Gmbh",
    "wof:placetype":"venue"
},
  "geometry": {"coordinates":[7.9964690208,48.004070282],"type":"Point"}
}