{
  "type": "Feature",
  "properties": {
    "iso:country":"DE",
    "sg:address":"Kleinsteinstr. 9",
    "sg:city":"Dresden",
    "sg:phone":"+49 351/4114322",
    "sg:postcode":"01219",
    "sg:province":"Sachsen",
    "wof:name":"Landesverband S\u00e4chsischer Kiebhaberorchester E. V.",
    "wof:placetype":"venue"
},
  "geometry": {"coordinates":[13.7679519653,51.0045967102],"type":"Point"}
}