{
  "type": "Feature",
  "properties": {
    "iso:country":"DE",
    "sg:address":"Kr\u00f6peliner Str. 20 a",
    "sg:city":"Rostock",
    "sg:phone":"+49 381/4904600",
    "sg:postcode":"18055",
    "sg:province":"Mecklenburg-Vorpommern",
    "wof:name":"M\u00f6llers Und Schulte Rechtsanw\u00e4lte",
    "wof:placetype":"venue"
},
  "geometry": {"coordinates":[12.1369485855,54.0883827209],"type":"Point"}
}