{
  "type": "Feature",
  "properties": {
    "iso:country":"DE",
    "sg:address":"Poststr. 17",
    "sg:city":"Weinstadt",
    "sg:postcode":"71384",
    "sg:province":"Baden-W\u00fcrttemberg",
    "wof:name":"Reichenecker Gmbh & Co. Kg",
    "wof:placetype":"venue"
},
  "geometry": {"coordinates":[9.385317,48.806534],"type":"Point"}
}