{
  "type": "Feature",
  "properties": {
    "iso:country":"DE",
    "sg:address":"Oswinsteig 25",
    "sg:city":"Berlin",
    "sg:phone":"+49 30/4046494",
    "sg:postcode":"13467",
    "sg:province":"Berlin",
    "wof:name":"Weinhaus Ziesemer",
    "wof:placetype":"venue"
},
  "geometry": {"coordinates":[13.3064880371,52.6254806519],"type":"Point"}
}