{
  "type": "Feature",
  "properties": {
    "iso:country":"DE",
    "sg:address":"Um die Halbe Stadt 7",
    "sg:city":"Peitz",
    "sg:phone":"+49 35601/22101",
    "sg:postcode":"03185",
    "sg:province":"Brandenburg",
    "wof:name":"Dr. Falk Weber",
    "wof:placetype":"venue"
},
  "geometry": {"coordinates":[14.405459,51.855911],"type":"Point"}
}