{
  "type": "Feature",
  "properties": {
    "iso:country":"DE",
    "sg:address":"Kart\u00e4userstr. 15",
    "sg:city":"Freiburg",
    "sg:phone":"+49 761/36948",
    "sg:postcode":"79102",
    "sg:province":"Baden-W\u00fcrttemberg",
    "wof:name":"Raumforum Einrichtungs-und Planungs- Gmbh",
    "wof:placetype":"venue"
},
  "geometry": {"coordinates":[7.8563117981,47.9919395447],"type":"Point"}
}