{
  "type": "Feature",
  "properties": {
    "iso:country":"DE",
    "sg:address":"Im Rosselfeld 81",
    "sg:city":"V\u00f6lklingen",
    "sg:phone":"+49 6898/7332",
    "sg:postcode":"66333",
    "sg:province":"Saarland",
    "wof:name":"Sabine Gerstner-riewer Hebamme",
    "wof:placetype":"venue"
},
  "geometry": {"coordinates":[6.832688,49.230915],"type":"Point"}
}