{
  "type": "Feature",
  "properties": {
    "iso:country":"DE",
    "sg:address":"Gutenbergstr. 5",
    "sg:city":"Aichtal",
    "sg:phone":"+49 7127/95830",
    "sg:postcode":"72631",
    "sg:province":"Baden-W\u00fcrttemberg",
    "wof:name":"Elektrotechnik Und Automation Ulrich Brodbeck Gmbh",
    "wof:placetype":"venue"
},
  "geometry": {"coordinates":[9.23125,48.630653],"type":"Point"}
}