{
  "type": "Feature",
  "properties": {
    "iso:country":"DE",
    "sg:address":"Uhland",
    "sg:city":"Graben-Neudorf",
    "sg:phone":"+49 7255/6680",
    "sg:postcode":"76676",
    "sg:province":"Baden-W\u00fcrttemberg",
    "wof:name":"Motorrad Erlbeck",
    "wof:placetype":"venue"
},
  "geometry": {"coordinates":[8.4892854691,49.1653518677],"type":"Point"}
}