{
  "type": "Feature",
  "properties": {
    "iso:country":"DE",
    "sg:address":"B\u00fcrgerm.-Weigand-Str. 2",
    "sg:city":"Gerolzhofen",
    "sg:phone":"+49 9382/7735",
    "sg:postcode":"97447",
    "sg:province":"Bayern",
    "wof:name":"Distel",
    "wof:placetype":"venue"
},
  "geometry": {"coordinates":[10.348151207,49.9010124207],"type":"Point"}
}