{
  "type": "Feature",
  "properties": {
    "iso:country":"DE",
    "sg:address":"Fahrner Str. 133",
    "sg:city":"Duisburg",
    "sg:postcode":"47169",
    "sg:province":"Nordrhein-Westfalen",
    "wof:name":"Ejk Dienstleistungs Gmbh",
    "wof:placetype":"venue"
},
  "geometry": {"coordinates":[6.767588,51.514553],"type":"Point"}
}