{
  "type": "Feature",
  "properties": {
    "iso:country":"DE",
    "sg:address":"Lindengrabenstr. 32",
    "sg:city":"Lahr",
    "sg:phone":"+49 7821/77881",
    "sg:postcode":"77933",
    "sg:province":"Baden-W\u00fcrttemberg",
    "wof:name":"Erna Fehrenbach Hebamme",
    "wof:placetype":"venue"
},
  "geometry": {"coordinates":[7.93185,48.327538],"type":"Point"}
}