{
  "type": "Feature",
  "properties": {
    "iso:country":"DE",
    "sg:address":"Poststr. 5",
    "sg:city":"Bitburg",
    "sg:phone":"+49 6561/18066",
    "sg:postcode":"54634",
    "sg:province":"Rheinland-Pfalz",
    "wof:name":"Eifel Incoming",
    "wof:placetype":"venue"
},
  "geometry": {"coordinates":[6.5251059532,49.9722442627],"type":"Point"}
}