{
  "type": "Feature",
  "properties": {
    "iso:country":"DE",
    "sg:address":"Wei\u00dfenfelser Str. 84",
    "sg:city":"Leipzig",
    "sg:classifiers":[
        {
            "category":"Professional",
            "subcategory":"Management & Consulting",
            "type":"Services"
        }
    ],
    "sg:postcode":"04229",
    "sg:tags":[
        "data-quality-management",
        "business-intelligence",
        "data-warehousing",
        "web-services"
    ],
    "sg:website":"http://www.tiq-solutions.de",
    "wof:name":"TIQ Solutions",
    "wof:placetype":"venue"
},
  "geometry": {"coordinates":[12.33384,51.330403],"type":"Point"}
}