{
  "type": "Feature",
  "properties": {
    "iso:country":"DE",
    "sg:address":"Olchinger Str. 90",
    "sg:city":"Gr\u00f6benzell",
    "sg:phone":"+49 8142/8767",
    "sg:postcode":"82194",
    "sg:province":"Bayern",
    "wof:name":"Restaurant Ming Garden",
    "wof:placetype":"venue"
},
  "geometry": {"coordinates":[11.382106781,48.1870384216],"type":"Point"}
}