{
  "type": "Feature",
  "properties": {
    "iso:country":"DE",
    "sg:address":"Gerresheimer Weg 30-32",
    "sg:city":"Dorsten",
    "sg:phone":"+49 2362/45246",
    "sg:postcode":"46282",
    "sg:province":"Nordrhein-Westfalen",
    "wof:name":"Steelenser Haus Und Grund Gmbh",
    "wof:placetype":"venue"
},
  "geometry": {"coordinates":[6.9737911224,51.6610488892],"type":"Point"}
}