{
  "type": "Feature",
  "properties": {
    "iso:country":"DE",
    "sg:address":"Eisenbahnstr. 89",
    "sg:city":"Kindsbach",
    "sg:phone":"+49 6371/17689",
    "sg:postcode":"66862",
    "sg:province":"Rheinland-Pfalz",
    "wof:name":"W. Egelhof",
    "wof:placetype":"venue"
},
  "geometry": {"coordinates":[7.611748,49.422028],"type":"Point"}
}