{
  "type": "Feature",
  "properties": {
    "iso:country":"DE",
    "sg:address":"Alsfelder Str. 4",
    "sg:city":"Wabern",
    "sg:phone":"+49 5681/2449",
    "sg:postcode":"34590",
    "sg:province":"Hessen",
    "wof:name":"Bu-ho Plast Montagebau Und Kunststoff-",
    "wof:placetype":"venue"
},
  "geometry": {"coordinates":[9.3791704178,51.065864563],"type":"Point"}
}