{
  "type": "Feature",
  "properties": {
    "iso:country":"DE",
    "sg:address":"Werner-Seelenbinder-Str. 6",
    "sg:city":"Gro\u00dfr\u00e4schen",
    "sg:phone":"+49 35753/3072",
    "sg:postcode":"01983",
    "sg:province":"Brandenburg",
    "wof:name":"Werner Burkhardt",
    "wof:placetype":"venue"
},
  "geometry": {"coordinates":[14.0052871704,51.5838851929],"type":"Point"}
}