{
  "type": "Feature",
  "properties": {
    "iso:country":"DE",
    "sg:address":"Stendaler Str. 65",
    "sg:city":"Tangerm\u00fcnde",
    "sg:phone":"+49 39322/43788",
    "sg:postcode":"39590",
    "sg:province":"Sachsen-Anhalt",
    "wof:name":"Pizzeria",
    "wof:placetype":"venue"
},
  "geometry": {"coordinates":[11.9678268433,52.5396270752],"type":"Point"}
}