{
  "type": "Feature",
  "properties": {
    "iso:country":"DE",
    "sg:address":"Weiherheide 1 c",
    "sg:city":"Hamburg",
    "sg:phone":"+49 40/7971740",
    "sg:postcode":"21079",
    "sg:province":"Hamburg",
    "wof:name":"Wi Wehnert Informations- Systeme Gmbh",
    "wof:placetype":"venue"
},
  "geometry": {"coordinates":[9.9906663895,53.4246826172],"type":"Point"}
}