{
  "type": "Feature",
  "properties": {
    "iso:country":"DE",
    "sg:address":"Marktplatz 3",
    "sg:city":"Blomberg",
    "sg:phone":"+49 5235/96980",
    "sg:postcode":"32825",
    "sg:province":"Nordrhein-Westfalen",
    "wof:name":"Lippische Landes-brand- Versicherungsanstalt",
    "wof:placetype":"venue"
},
  "geometry": {"coordinates":[9.0902204514,51.9433708191],"type":"Point"}
}