{
  "type": "Feature",
  "properties": {
    "iso:country":"DE",
    "sg:address":"Amselstr. 7",
    "sg:city":"Mannheim",
    "sg:phone":"+49 621/771291",
    "sg:postcode":"68307",
    "sg:province":"Baden-W\u00fcrttemberg",
    "wof:name":"Werner Schlosshauer Gmbh Georg Schumm Nachfolger",
    "wof:placetype":"venue"
},
  "geometry": {"coordinates":[8.4574956894,49.5504684448],"type":"Point"}
}