{
  "type": "Feature",
  "properties": {
    "iso:country":"DE",
    "sg:address":"G\u00e4rtnerstr. 103",
    "sg:city":"Neuburg",
    "sg:phone":"+49 8431/60460",
    "sg:postcode":"86633",
    "sg:province":"Bayern",
    "wof:name":"Remus Datentechnik Gmbh",
    "wof:placetype":"venue"
},
  "geometry": {"coordinates":[11.1823148727,48.7328948975],"type":"Point"}
}