{
  "type": "Feature",
  "properties": {
    "iso:country":"DE",
    "sg:address":"Unseburger Str. 20",
    "sg:city":"Borne",
    "sg:phone":"+49 39263/234",
    "sg:postcode":"39435",
    "sg:province":"Sachsen-Anhalt",
    "wof:name":"Volker Seile",
    "wof:placetype":"venue"
},
  "geometry": {"coordinates":[11.554326,51.948624],"type":"Point"}
}