{
  "type": "Feature",
  "properties": {
    "iso:country":"DE",
    "sg:address":"Am Kattenbusch 15",
    "sg:city":"Radevormwald",
    "sg:phone":"+49 2195/1388",
    "sg:postcode":"42477",
    "sg:province":"Nordrhein-Westfalen",
    "wof:name":"Edeltraud Hofmann",
    "wof:placetype":"venue"
},
  "geometry": {"coordinates":[7.3540468216,51.1952323914],"type":"Point"}
}