{
  "type": "Feature",
  "properties": {
    "iso:country":"DE",
    "sg:address":"Heignkamer Str. 2",
    "sg:city":"Holzkirchen",
    "sg:phone":"+49 8024/91925",
    "sg:postcode":"83607",
    "sg:province":"Bayern",
    "wof:name":"Mc Donalds",
    "wof:placetype":"venue"
},
  "geometry": {"coordinates":[11.6897163391,47.8866424561],"type":"Point"}
}