{
  "type": "Feature",
  "properties": {
    "iso:country":"DE",
    "sg:address":"Leitschm\u00fchle 1",
    "sg:city":"Steinwiesen",
    "sg:phone":"+49 9262/1014",
    "sg:postcode":"96349",
    "sg:province":"Bayern",
    "wof:name":"Heinrich Beitzinger S\u00e4gewerk Gmbh",
    "wof:placetype":"venue"
},
  "geometry": {"coordinates":[11.4498443604,50.3085289001],"type":"Point"}
}