{
  "type": "Feature",
  "properties": {
    "iso:country":"DE",
    "sg:address":"Jahnstr. 3",
    "sg:city":"Luckau",
    "sg:phone":"+49 3544/508647",
    "sg:postcode":"15926",
    "sg:province":"Brandenburg",
    "wof:name":"Finanztechnische Beratung Heiko Schulze E. K.",
    "wof:placetype":"venue"
},
  "geometry": {"coordinates":[13.7067098618,51.8556938171],"type":"Point"}
}