{
  "type": "Feature",
  "properties": {
    "iso:country":"DE",
    "sg:address":"Couvenstr. 6",
    "sg:city":"D\u00fcsseldorf",
    "sg:phone":"+49 211/36760",
    "sg:postcode":"40211",
    "sg:province":"Nordrhein-Westfalen",
    "wof:name":"Diskont Und Kredit Ag",
    "wof:placetype":"venue"
},
  "geometry": {"coordinates":[6.788521,51.231003],"type":"Point"}
}