{
  "type": "Feature",
  "properties": {
    "iso:country":"DE",
    "sg:address":"Hainbachstr. 5",
    "sg:city":"Sch\u00f6ffengrund",
    "sg:phone":"+49 6445/384",
    "sg:postcode":"35641",
    "sg:province":"Hessen",
    "wof:name":"Erich Karl Schmidt Transporte Baustoffe",
    "wof:placetype":"venue"
},
  "geometry": {"coordinates":[8.4594421387,50.5147323608],"type":"Point"}
}