{
  "type": "Feature",
  "properties": {
    "iso:country":"DE",
    "sg:address":"Bismarckstr. 40",
    "sg:city":"Lahr",
    "sg:phone":"+49 7821/25031",
    "sg:postcode":"77933",
    "sg:province":"Baden-W\u00fcrttemberg",
    "wof:name":"Seniorenhaus Bei Der Stiftskirche",
    "wof:placetype":"venue"
},
  "geometry": {"coordinates":[7.87757,48.340229],"type":"Point"}
}