{
  "type": "Feature",
  "properties": {
    "iso:country":"DE",
    "sg:address":"Hahnenweg 1",
    "sg:city":"Rehlingen-Siersburg",
    "sg:phone":"+49 6833/613",
    "sg:postcode":"66780",
    "sg:province":"Saarland",
    "wof:name":"Werner Spies",
    "wof:placetype":"venue"
},
  "geometry": {"coordinates":[6.6297531128,49.3563804626],"type":"Point"}
}