{
  "type": "Feature",
  "properties": {
    "iso:country":"DE",
    "sg:address":"Hohe Allee 18",
    "sg:city":"Neuenhagen",
    "sg:phone":"+49 3342/202646",
    "sg:postcode":"15366",
    "sg:province":"Brandenburg",
    "wof:name":"Dietmar Pisall Elektroinstallation",
    "wof:placetype":"venue"
},
  "geometry": {"coordinates":[13.675791,52.525681],"type":"Point"}
}