{
  "type": "Feature",
  "properties": {
    "iso:country":"DE",
    "sg:address":"Geschwister-Scholl-Str. 29",
    "sg:city":"Erftstadt",
    "sg:phone":"+49 2235/690407",
    "sg:postcode":"50374",
    "sg:province":"Nordrhein-Westfalen",
    "wof:name":"R. Ulbrich Schw\u00e4bisch Hall",
    "wof:placetype":"venue"
},
  "geometry": {"coordinates":[6.7655310631,50.7999420166],"type":"Point"}
}