{
  "type": "Feature",
  "properties": {
    "iso:country":"DE",
    "sg:address":"Ottoweg 7",
    "sg:city":"Nordhausen",
    "sg:postcode":"99734",
    "sg:province":"Th\u00fcringen",
    "wof:name":"Dr. Med. Georg Wolff",
    "wof:placetype":"venue"
},
  "geometry": {"coordinates":[10.805767,51.507824],"type":"Point"}
}