{
  "type": "Feature",
  "properties": {
    "iso:country":"DE",
    "sg:address":"Cauerstr. 7",
    "sg:city":"Erlangen",
    "sg:postcode":"91058",
    "sg:province":"Bayern",
    "wof:name":"Institut F\u00fcr Regelungstechnik",
    "wof:placetype":"venue"
},
  "geometry": {"coordinates":[11.028298378,49.5723838806],"type":"Point"}
}