{
  "type": "Feature",
  "properties": {
    "iso:country":"DE",
    "sg:address":"Goethestr. 21",
    "sg:city":"Leverkusen",
    "sg:phone":"+49 2171/41012",
    "sg:postcode":"51379",
    "sg:province":"Nordrhein-Westfalen",
    "wof:name":"Hans-peter Schramm",
    "wof:placetype":"venue"
},
  "geometry": {"coordinates":[7.0061378479,51.0660057068],"type":"Point"}
}