{
  "type": "Feature",
  "properties": {
    "iso:country":"DE",
    "sg:address":"Jenaer Str. 17",
    "sg:city":"Berlin",
    "sg:phone":"+49 30/8548984",
    "sg:postcode":"10717",
    "sg:province":"Berlin",
    "wof:name":"Ilsedore Buhmann Angelina Z\u00f6llner",
    "wof:placetype":"venue"
},
  "geometry": {"coordinates":[13.3357715607,52.4886283875],"type":"Point"}
}