{
  "type": "Feature",
  "properties": {
    "iso:country":"DE",
    "sg:address":"Dorfstr. 1",
    "sg:city":"Risum-Lindholm",
    "sg:phone":"+49 4661/8523",
    "sg:postcode":"25920",
    "sg:province":"Schleswig-Holstein",
    "wof:name":"J. Bielenberg",
    "wof:placetype":"venue"
},
  "geometry": {"coordinates":[8.862336,54.769409],"type":"Point"}
}