{
  "type": "Feature",
  "properties": {
    "iso:country":"DE",
    "sg:address":"Danziger Str. 4",
    "sg:city":"Schlitz",
    "sg:phone":"+49 6642/6474",
    "sg:postcode":"36110",
    "sg:province":"Hessen",
    "wof:name":"Hamburg-mannheimer Versicherung",
    "wof:placetype":"venue"
},
  "geometry": {"coordinates":[9.578122139,50.7159385681],"type":"Point"}
}