{
  "type": "Feature",
  "properties": {
    "iso:country":"DE",
    "sg:address":"Brandisstr. 48",
    "sg:city":"Dortmund",
    "sg:phone":"+49 231/5763333",
    "sg:postcode":"44265",
    "sg:province":"Nordrhein-Westfalen",
    "wof:name":"Siemens Ag",
    "wof:placetype":"venue"
},
  "geometry": {"coordinates":[7.484454,51.45359],"type":"Point"}
}