{
  "type": "Feature",
  "properties": {
    "iso:country":"DE",
    "sg:address":"K\u00e4the-Kollwitz-Str. 7",
    "sg:city":"Hohenstein-Ernstthal",
    "sg:phone":"+49 3723/711279",
    "sg:postcode":"09337",
    "sg:province":"Sachsen",
    "wof:name":"Fr\u00f6de",
    "wof:placetype":"venue"
},
  "geometry": {"coordinates":[12.75468,50.809608],"type":"Point"}
}