{
  "type": "Feature",
  "properties": {
    "iso:country":"DE",
    "sg:address":"Wiesestr. 118",
    "sg:city":"Herford",
    "sg:phone":"+49 5221/99150",
    "sg:postcode":"32052",
    "sg:province":"Nordrhein-Westfalen",
    "wof:name":"Telefomatic Kommunikations- Technik Herford Gmbh",
    "wof:placetype":"venue"
},
  "geometry": {"coordinates":[8.690486908,52.1064147949],"type":"Point"}
}