{
  "type": "Feature",
  "properties": {
    "iso:country":"DE",
    "sg:address":"Teichsm\u00fchlengasse 3",
    "sg:city":"Soest",
    "sg:phone":"+49 2921/392000",
    "sg:postcode":"59494",
    "sg:province":"Nordrhein-Westfalen",
    "wof:name":"Soestcom Gmbh",
    "wof:placetype":"venue"
},
  "geometry": {"coordinates":[8.1088600159,51.5738983154],"type":"Point"}
}