{
  "type": "Feature",
  "properties": {
    "iso:country":"DE",
    "sg:address":"Westf\u00e4lische Str. 9",
    "sg:city":"Bochum",
    "sg:phone":"+49 2327/55748",
    "sg:postcode":"44869",
    "sg:province":"Nordrhein-Westfalen",
    "wof:name":"Mainka",
    "wof:placetype":"venue"
},
  "geometry": {"coordinates":[7.154489994,51.4640312195],"type":"Point"}
}