{
  "type": "Feature",
  "properties": {
    "iso:country":"DE",
    "sg:address":"Borstendorfer Str. 8a",
    "sg:city":"Eppendorf",
    "sg:phone":"+49 37293/414",
    "sg:postcode":"09575",
    "sg:province":"Sachsen",
    "wof:name":"Steffen Weinhold",
    "wof:placetype":"venue"
},
  "geometry": {"coordinates":[13.237739563,50.7916984558],"type":"Point"}
}