{
  "type": "Feature",
  "properties": {
    "iso:country":"DE",
    "sg:address":"Schnellstr. 7",
    "sg:city":"Husum",
    "sg:phone":"+49 4841/75469",
    "sg:postcode":"25813",
    "sg:province":"Schleswig-Holstein",
    "wof:name":"A. Eumann",
    "wof:placetype":"venue"
},
  "geometry": {"coordinates":[9.065556,54.478901],"type":"Point"}
}