{
  "type": "Feature",
  "properties": {
    "iso:country":"DE",
    "sg:address":"Neust\u00e4dter Str. 68",
    "sg:city":"Goldenst\u00e4dt",
    "sg:phone":"+49 3868/716",
    "sg:postcode":"19079",
    "sg:province":"Mecklenburg-Vorpommern",
    "wof:name":"Norbert Jandt",
    "wof:placetype":"venue"
},
  "geometry": {"coordinates":[11.500246048,53.4588432312],"type":"Point"}
}