{
  "type": "Feature",
  "properties": {
    "iso:country":"DE",
    "sg:address":"Korekamp 8",
    "sg:city":"Krefeld",
    "sg:phone":"+49 2151/542072",
    "sg:postcode":"47809",
    "sg:province":"Nordrhein-Westfalen",
    "wof:name":"Wohnst\u00e4tte Krefeld Wohnungs- Ag",
    "wof:placetype":"venue"
},
  "geometry": {"coordinates":[6.6088428497,51.3258399963],"type":"Point"}
}