{
  "type": "Feature",
  "properties": {
    "iso:country":"DE",
    "sg:address":"Lange Str. 15",
    "sg:city":"Beverungen",
    "sg:phone":"+49 5273/369910",
    "sg:postcode":"37688",
    "sg:province":"Nordrhein-Westfalen",
    "wof:name":"Bevertor-apotheke Horst M\u00fcller E. Kfm.",
    "wof:placetype":"venue"
},
  "geometry": {"coordinates":[9.372757,51.66346],"type":"Point"}
}