{
  "type": "Feature",
  "properties": {
    "iso:country":"DE",
    "sg:address":"Talstr. 25",
    "sg:city":"St Martin",
    "sg:phone":"+49 6323/980362",
    "sg:postcode":"67487",
    "sg:province":"Rheinland-Pfalz",
    "wof:name":"Volker Heinle",
    "wof:placetype":"venue"
},
  "geometry": {"coordinates":[8.095896,49.299698],"type":"Point"}
}