{
  "type": "Feature",
  "properties": {
    "iso:country":"DE",
    "sg:address":"Am Unteren Stein 6",
    "sg:city":"Thierhaupten",
    "sg:phone":"+49 8271/80580",
    "sg:postcode":"86672",
    "sg:province":"Bayern",
    "wof:name":"Soundsector Records",
    "wof:placetype":"venue"
},
  "geometry": {"coordinates":[10.9106826782,48.5638427734],"type":"Point"}
}