{
  "type": "Feature",
  "properties": {
    "iso:country":"DE",
    "sg:address":"Haiderfeldstr. 50",
    "sg:city":"M\u00f6nchengladbach",
    "sg:phone":"+49 2161/895941",
    "sg:postcode":"41063",
    "sg:province":"Nordrhein-Westfalen",
    "wof:name":"U. Glatz",
    "wof:placetype":"venue"
},
  "geometry": {"coordinates":[6.415939,51.210487],"type":"Point"}
}