{
  "type": "Feature",
  "properties": {
    "iso:country":"DE",
    "sg:address":"Penkerstr. 6",
    "sg:city":"Nandlstadt",
    "sg:phone":"+49 8756/1244",
    "sg:postcode":"85405",
    "sg:province":"Bayern",
    "wof:name":"St. Antonius-apotheke",
    "wof:placetype":"venue"
},
  "geometry": {"coordinates":[11.804046,48.536873],"type":"Point"}
}