{
  "type": "Feature",
  "properties": {
    "iso:country":"DE",
    "sg:address":"Kornstr. 74",
    "sg:city":"Goslar",
    "sg:phone":"+49 5321/26258",
    "sg:postcode":"38640",
    "sg:province":"Niedersachsen",
    "wof:name":"Herbert Pabst",
    "wof:placetype":"venue"
},
  "geometry": {"coordinates":[10.4347753525,51.9075965881],"type":"Point"}
}