{
  "type": "Feature",
  "properties": {
    "iso:country":"DE",
    "sg:address":"Hochstr. 10",
    "sg:city":"Cadolzburg",
    "sg:phone":"+49 9103/404",
    "sg:postcode":"90556",
    "sg:province":"Bayern",
    "wof:name":"Dr. H. Schwarz Tierarzt",
    "wof:placetype":"venue"
},
  "geometry": {"coordinates":[10.8594379425,49.4581375122],"type":"Point"}
}