{
  "type": "Feature",
  "properties": {
    "iso:country":"DE",
    "sg:address":"Stei\u00dflinger Str. 20",
    "sg:city":"Allmendingen",
    "sg:phone":"+49 7384/410",
    "sg:postcode":"89604",
    "sg:province":"Baden-W\u00fcrttemberg",
    "wof:name":"E. Scherb",
    "wof:placetype":"venue"
},
  "geometry": {"coordinates":[9.6588306427,48.3406028748],"type":"Point"}
}