{
  "type": "Feature",
  "properties": {
    "iso:country":"DE",
    "sg:address":"Lichterfelder Strasse 3",
    "sg:city":"Eberswalde",
    "sg:phone":"+49 3334",
    "sg:postcode":"16227",
    "sg:province":"Brandenburg",
    "wof:name":"Per Pedes",
    "wof:placetype":"venue"
},
  "geometry": {"coordinates":[13.767105,52.840317],"type":"Point"}
}