{
  "type": "Feature",
  "properties": {
    "iso:country":"DE",
    "sg:address":"Flurstr. 4",
    "sg:city":"Dinslaken",
    "sg:postcode":"46535",
    "sg:province":"Nordrhein-Westfalen",
    "wof:name":"Behindertenwerkstatt",
    "wof:placetype":"venue"
},
  "geometry": {"coordinates":[6.723892,51.558685],"type":"Point"}
}