{
  "type": "Feature",
  "properties": {
    "iso:country":"DE",
    "sg:address":"Birkenhof 77",
    "sg:city":"Henstedt-Ulzburg",
    "sg:phone":"+49 4193/94114",
    "sg:postcode":"24558",
    "sg:province":"Schleswig-Holstein",
    "wof:name":"Wotec Automation Gmbh",
    "wof:placetype":"venue"
},
  "geometry": {"coordinates":[9.979965,53.779663],"type":"Point"}
}