{
  "type": "Feature",
  "properties": {
    "iso:country":"DE",
    "sg:address":"Augsfelder Str. 32",
    "sg:city":"Ha\u00dffurt",
    "sg:phone":"+49 9521/1330",
    "sg:postcode":"97437",
    "sg:province":"Bayern",
    "wof:name":"R. W\u00f6lfel",
    "wof:placetype":"venue"
},
  "geometry": {"coordinates":[10.53631,50.028233],"type":"Point"}
}