{
  "type": "Feature",
  "properties": {
    "iso:country":"DE",
    "sg:address":"Lindenstr. 20",
    "sg:city":"Teugn",
    "sg:phone":"+49 9405/2701",
    "sg:postcode":"93356",
    "sg:province":"Bayern",
    "wof:name":"Michael Loidl",
    "wof:placetype":"venue"
},
  "geometry": {"coordinates":[12.016324,48.894016],"type":"Point"}
}