{
  "type": "Feature",
  "properties": {
    "iso:country":"DE",
    "sg:address":"Richard-Boljahn-Allee 2",
    "sg:city":"Bremen",
    "sg:phone":"+49 421/7677040",
    "sg:postcode":"28329",
    "sg:province":"Bremen",
    "wof:name":"Deutsche Shell Ag",
    "wof:placetype":"venue"
},
  "geometry": {"coordinates":[8.8767213821,53.082660675],"type":"Point"}
}