{
  "type": "Feature",
  "properties": {
    "iso:country":"DE",
    "sg:address":"Rheinstr. 27",
    "sg:city":"Lindlar",
    "sg:phone":"+49 2266/6205",
    "sg:postcode":"51789",
    "sg:province":"Nordrhein-Westfalen",
    "wof:name":"Udo Heider Raumausstattung",
    "wof:placetype":"venue"
},
  "geometry": {"coordinates":[7.3666381836,51.0185585022],"type":"Point"}
}