{
  "type": "Feature",
  "properties": {
    "iso:country":"DE",
    "sg:address":"Am Nienhaushof 14a",
    "sg:city":"Duisburg",
    "sg:phone":"+49 203/351869",
    "sg:postcode":"47139",
    "sg:province":"Nordrhein-Westfalen",
    "wof:name":"Weien & Schwenk Gmbh",
    "wof:placetype":"venue"
},
  "geometry": {"coordinates":[6.7210988998,51.4773406982],"type":"Point"}
}