{
  "type": "Feature",
  "properties": {
    "iso:country":"DE",
    "sg:address":"Bahnhofstr. 3",
    "sg:city":"Niederzier",
    "sg:phone":"+49 2428/4780",
    "sg:postcode":"52382",
    "sg:province":"Nordrhein-Westfalen",
    "wof:name":"Gastst\u00e4tte Hans Briskot",
    "wof:placetype":"venue"
},
  "geometry": {"coordinates":[6.4590988159,50.8524742126],"type":"Point"}
}