{
  "type": "Feature",
  "properties": {
    "iso:country":"DE",
    "sg:address":"Schl\u00fcmersweg 2",
    "sg:city":"Hamminkeln",
    "sg:phone":"+49 2856/1474",
    "sg:postcode":"46499",
    "sg:province":"Nordrhein-Westfalen",
    "wof:name":"Heinrich Schlabes",
    "wof:placetype":"venue"
},
  "geometry": {"coordinates":[6.652147,51.716038],"type":"Point"}
}