{
  "type": "Feature",
  "properties": {
    "iso:country":"DE",
    "sg:address":"Wilhelmstr. 5",
    "sg:city":"Euskirchen",
    "sg:phone":"+49 2251/79000",
    "sg:postcode":"53879",
    "sg:province":"Nordrhein-Westfalen",
    "wof:name":"Heinen-verlag Gmbh",
    "wof:placetype":"venue"
},
  "geometry": {"coordinates":[6.7906498909,50.6598396301],"type":"Point"}
}