{
  "type": "Feature",
  "properties": {
    "iso:country":"DE",
    "sg:address":"Am Ganter 1",
    "sg:city":"H\u00f6henkirchen-Siegertbrn",
    "sg:phone":"+49 89/918513",
    "sg:postcode":"85635",
    "sg:province":"Bayern",
    "wof:name":"Gill R. Rockingham \u00dcbersetzungsb\u00fcro",
    "wof:placetype":"venue"
},
  "geometry": {"coordinates":[11.720247,48.02034],"type":"Point"}
}