{
  "type": "Feature",
  "properties": {
    "iso:country":"DE",
    "sg:address":"Oststr. 2",
    "sg:city":"Lugau",
    "sg:phone":"+49 37295/3287",
    "sg:postcode":"09385",
    "sg:province":"Sachsen",
    "wof:name":"M. Rei\u00dfmann",
    "wof:placetype":"venue"
},
  "geometry": {"coordinates":[12.746694,50.761078],"type":"Point"}
}