{
  "type": "Feature",
  "properties": {
    "iso:country":"DE",
    "sg:address":"Rellinghauser 266",
    "sg:city":"Essen",
    "sg:phone":"+49 201",
    "sg:postcode":"45136",
    "sg:province":"Nordrhein-Westfalen",
    "wof:name":"Zur Linde",
    "wof:placetype":"venue"
},
  "geometry": {"coordinates":[7.031726,51.436832],"type":"Point"}
}