{
  "type": "Feature",
  "properties": {
    "iso:country":"DE",
    "sg:address":"Laerstr.",
    "sg:city":"Versmold",
    "sg:phone":"+49 5423/2010",
    "sg:postcode":"33775",
    "sg:province":"Nordrhein-Westfalen",
    "wof:name":"Printpartner Gmbh",
    "wof:placetype":"venue"
},
  "geometry": {"coordinates":[8.12909,52.068481],"type":"Point"}
}