{
  "type": "Feature",
  "properties": {
    "iso:country":"DE",
    "sg:address":"Hauptstr. 15",
    "sg:city":"Neuffen",
    "sg:phone":"+49 7025/2767",
    "sg:postcode":"72639",
    "sg:province":"Baden-W\u00fcrttemberg",
    "wof:name":"Hirsch-post",
    "wof:placetype":"venue"
},
  "geometry": {"coordinates":[9.3753471375,48.55493927],"type":"Point"}
}