{
  "type": "Feature",
  "properties": {
    "iso:country":"DE",
    "sg:address":"Untere Dorfstr. 5",
    "sg:city":"Kranzberg",
    "sg:phone":"+49 8166/9720",
    "sg:postcode":"85402",
    "sg:province":"Bayern",
    "wof:name":"G. Sellmair Mech. Werkstatt",
    "wof:placetype":"venue"
},
  "geometry": {"coordinates":[11.610639,48.405537],"type":"Point"}
}