{
  "type": "Feature",
  "properties": {
    "iso:country":"DE",
    "sg:address":"Dorfstr. 2 a",
    "sg:city":"Dretzen",
    "sg:phone":"+49 33830/60909",
    "sg:postcode":"14793",
    "sg:province":"Brandenburg",
    "wof:name":"Dretzener Landprodukte Gmbh",
    "wof:placetype":"venue"
},
  "geometry": {"coordinates":[12.292835,52.266106],"type":"Point"}
}