{
  "type": "Feature",
  "properties": {
    "iso:country":"DE",
    "sg:address":"Blessemer Str. 17",
    "sg:city":"Erftstadt",
    "sg:phone":"+49 2235/71917",
    "sg:postcode":"50374",
    "sg:province":"Nordrhein-Westfalen",
    "wof:name":"Bierst\u00fcbchen",
    "wof:placetype":"venue"
},
  "geometry": {"coordinates":[6.7728419304,50.8021469116],"type":"Point"}
}