{
  "type": "Feature",
  "properties": {
    "iso:country":"DE",
    "sg:address":"M\u00fchlwiese 14",
    "sg:city":"Kelkheim",
    "sg:phone":"+49 6195/73493",
    "sg:postcode":"65779",
    "sg:province":"Hessen",
    "wof:name":"Michael Spengler Die Dachdecker Gmbh",
    "wof:placetype":"venue"
},
  "geometry": {"coordinates":[8.462911,50.127708],"type":"Point"}
}