{
  "type": "Feature",
  "properties": {
    "iso:country":"DE",
    "sg:address":"Baumerhof 1",
    "sg:city":"Fensterbach",
    "sg:phone":"+49 9438/361",
    "sg:postcode":"92269",
    "sg:province":"Bayern",
    "wof:name":"Siegfried Koch",
    "wof:placetype":"venue"
},
  "geometry": {"coordinates":[12.006475,49.42852],"type":"Point"}
}