{
  "type": "Feature",
  "properties": {
    "iso:country":"DE",
    "sg:address":"Herrenstr. 4",
    "sg:city":"Senden",
    "sg:phone":"+49 2597/96310",
    "sg:postcode":"48308",
    "sg:province":"Nordrhein-Westfalen",
    "wof:name":"Hotel G\u00fcnter Niemeyer",
    "wof:placetype":"venue"
},
  "geometry": {"coordinates":[7.4877200127,51.855342865],"type":"Point"}
}