{
  "type": "Feature",
  "properties": {
    "iso:country":"DE",
    "sg:address":"Kolpingstr. 96",
    "sg:city":"Stuttgart",
    "sg:phone":"+49 711/532643",
    "sg:postcode":"70378",
    "sg:province":"Baden-W\u00fcrttemberg",
    "wof:name":"Steinhalden-apotheke Silke Bartel E. K.",
    "wof:placetype":"venue"
},
  "geometry": {"coordinates":[9.230842,48.827805],"type":"Point"}
}