{
  "type": "Feature",
  "properties": {
    "iso:country":"DE",
    "sg:address":"Gerberstr. 6",
    "sg:city":"Wilhermsdorf",
    "sg:phone":"+49 9102/1248",
    "sg:postcode":"91452",
    "sg:province":"Bayern",
    "wof:name":"Sauerstein Gmbh",
    "wof:placetype":"venue"
},
  "geometry": {"coordinates":[10.7185668945,49.4814682007],"type":"Point"}
}