{
  "type": "Feature",
  "properties": {
    "iso:country":"DE",
    "sg:address":"Elbstorfer Str. 61",
    "sg:city":"Drage",
    "sg:phone":"+49 4177/289",
    "sg:postcode":"21423",
    "sg:province":"Niedersachsen",
    "wof:name":"W. Schuhmacher",
    "wof:placetype":"venue"
},
  "geometry": {"coordinates":[10.287817,53.420815],"type":"Point"}
}