{
  "type": "Feature",
  "properties": {
    "iso:country":"DE",
    "sg:address":"Im Riedenberg 54",
    "sg:city":"Leinfelden-Echterdingen",
    "sg:phone":"+49 711/79711",
    "sg:postcode":"70771",
    "sg:province":"Baden-W\u00fcrttemberg",
    "wof:name":"Redaktion Daniela Ehapa Verlag",
    "wof:placetype":"venue"
},
  "geometry": {"coordinates":[9.1787996292,48.6641998291],"type":"Point"}
}