{
  "type": "Feature",
  "properties": {
    "iso:country":"DE",
    "sg:address":"Homburger Str. 19",
    "sg:city":"Kirkel",
    "sg:phone":"+49 4968/418251",
    "sg:postcode":"66459",
    "sg:province":"Saarland",
    "wof:name":"Horst K\u00d6rner Gmbh & Co. Kg",
    "wof:placetype":"venue"
},
  "geometry": {"coordinates":[7.285968,49.318256],"type":"Point"}
}