{
  "type": "Feature",
  "properties": {
    "iso:country":"DE",
    "sg:address":"Jaisweg 16",
    "sg:city":"Mittenwald",
    "sg:phone":"+49 8823/8310",
    "sg:postcode":"82481",
    "sg:province":"Bayern",
    "wof:name":"Franz Sch\u00fctz",
    "wof:placetype":"venue"
},
  "geometry": {"coordinates":[11.258664,47.442768],"type":"Point"}
}