{
  "type": "Feature",
  "properties": {
    "iso:country":"DE",
    "sg:address":"Dorfstr. 34",
    "sg:city":"Sprotta",
    "sg:phone":"+49 3423/2375",
    "sg:postcode":"04838",
    "sg:province":"Sachsen",
    "wof:name":"Heidel\u00e4nder H\u00e4hnchengrill",
    "wof:placetype":"venue"
},
  "geometry": {"coordinates":[12.6262254715,51.4936714172],"type":"Point"}
}