{
  "type": "Feature",
  "properties": {
    "iso:country":"DE",
    "sg:address":"Bismarckstr. 4",
    "sg:city":"Waldshut-Tiengen",
    "sg:phone":"+49 7751/3330",
    "sg:postcode":"79761",
    "sg:province":"Baden-W\u00fcrttemberg",
    "wof:name":"E. Ebner Optiker",
    "wof:placetype":"venue"
},
  "geometry": {"coordinates":[8.2175731659,47.621421814],"type":"Point"}
}