{
  "type": "Feature",
  "properties": {
    "iso:country":"DE",
    "sg:address":"Papenhuder Str. 26",
    "sg:city":"Hamburg",
    "sg:phone":"+49 40/22756363",
    "sg:postcode":"22087",
    "sg:province":"Hamburg",
    "wof:name":"Team Music Concert Gmbh",
    "wof:placetype":"venue"
},
  "geometry": {"coordinates":[10.019411,53.566746],"type":"Point"}
}