{
  "type": "Feature",
  "properties": {
    "iso:country":"DE",
    "sg:address":"Heinrich-B\u00f6ll-Str. 113",
    "sg:city":"Hockenheim",
    "sg:postcode":"68766",
    "sg:province":"Baden-W\u00fcrttemberg",
    "wof:name":"Wohnbau Gottfried Gmbh",
    "wof:placetype":"venue"
},
  "geometry": {"coordinates":[8.5618133545,49.3134727478],"type":"Point"}
}