{
  "type": "Feature",
  "properties": {
    "iso:country":"DE",
    "sg:address":"Georg-Schwarz-Str. 107",
    "sg:city":"Leipzig",
    "sg:postcode":"04179",
    "sg:province":"Sachsen",
    "wof:name":"Kinderbibliothek West",
    "wof:placetype":"venue"
},
  "geometry": {"coordinates":[12.315395,51.346798],"type":"Point"}
}