{
  "type": "Feature",
  "properties": {
    "iso:country":"DE",
    "sg:address":"H\u00f6henweg 2",
    "sg:city":"Ellwangen",
    "sg:phone":"+49 7961/904530",
    "sg:postcode":"73479",
    "sg:province":"Baden-W\u00fcrttemberg",
    "wof:name":"K.-h. Eckart Versteigerer",
    "wof:placetype":"venue"
},
  "geometry": {"coordinates":[10.1101408005,48.951915741],"type":"Point"}
}