{
  "type": "Feature",
  "properties": {
    "iso:country":"DE",
    "sg:address":"Treptitzer Str. 1",
    "sg:city":"Cavertitz",
    "sg:phone":"+49 34363/51379",
    "sg:postcode":"04758",
    "sg:province":"Sachsen",
    "wof:name":"Landwarenhaus",
    "wof:placetype":"venue"
},
  "geometry": {"coordinates":[13.128882,51.388237],"type":"Point"}
}