{
  "type": "Feature",
  "properties": {
    "iso:country":"DE",
    "sg:address":"Talstr. 1",
    "sg:city":"L\u00fcdenscheid",
    "sg:postcode":"58511",
    "sg:province":"Nordrhein-Westfalen",
    "wof:name":"Michael Elftmann Gmbh",
    "wof:placetype":"venue"
},
  "geometry": {"coordinates":[7.643443,51.210777],"type":"Point"}
}