{
  "type": "Feature",
  "properties": {
    "iso:country":"DE",
    "sg:address":"Jahnstr. 1",
    "sg:city":"Kirchheim",
    "sg:phone":"+49 6625/5166",
    "sg:postcode":"36275",
    "sg:province":"Hessen",
    "wof:name":"Gastst\u00e4tte B\u00fcrgerhaus Inh. Gertrude Geyer",
    "wof:placetype":"venue"
},
  "geometry": {"coordinates":[9.576154,50.83757],"type":"Point"}
}