{
  "type": "Feature",
  "properties": {
    "iso:country":"DE",
    "sg:address":"P\u00e4hler Weg 22",
    "sg:city":"Gilching",
    "sg:phone":"+49 8105/24423",
    "sg:postcode":"82205",
    "sg:province":"Bayern",
    "wof:name":"Bettina Weeber",
    "wof:placetype":"venue"
},
  "geometry": {"coordinates":[11.296344,48.109657],"type":"Point"}
}