{
  "type": "Feature",
  "properties": {
    "iso:country":"DE",
    "sg:address":"Untertorstr. 6b",
    "sg:city":"Rottendorf",
    "sg:phone":"+49 9302/4234",
    "sg:postcode":"97228",
    "sg:province":"Bayern",
    "wof:name":"Frank Bleibaum Rechtsanwalt",
    "wof:placetype":"venue"
},
  "geometry": {"coordinates":[10.0242061615,49.7938919067],"type":"Point"}
}