{
  "type": "Feature",
  "properties": {
    "iso:country":"DE",
    "sg:address":"Pestalozzistr. 21",
    "sg:city":"Guben",
    "sg:phone":"+49 3561/431502",
    "sg:postcode":"03172",
    "sg:province":"Brandenburg",
    "wof:name":"G. Paechnatz",
    "wof:placetype":"venue"
},
  "geometry": {"coordinates":[14.7040290833,51.9475364685],"type":"Point"}
}