{
  "type": "Feature",
  "properties": {
    "iso:country":"DE",
    "sg:address":"Vordere Gewerbestr. 4",
    "sg:city":"Pfaffen-Schwabenheim",
    "sg:phone":"+49 6701/7877",
    "sg:postcode":"55546",
    "sg:province":"Rheinland-Pfalz",
    "wof:name":"N. Theis",
    "wof:placetype":"venue"
},
  "geometry": {"coordinates":[7.94039,49.849831],"type":"Point"}
}