{
  "type": "Feature",
  "properties": {
    "iso:country":"DE",
    "sg:address":"Hackstr. 12",
    "sg:city":"Stuttgart",
    "sg:phone":"+49 711/6367640",
    "sg:postcode":"70190",
    "sg:province":"Baden-W\u00fcrttemberg",
    "wof:name":"Abg-altenhilfe-beratungs Gmbh",
    "wof:placetype":"venue"
},
  "geometry": {"coordinates":[9.197998,48.789211],"type":"Point"}
}