{
  "type": "Feature",
  "properties": {
    "iso:country":"DE",
    "sg:address":"Am Tucherpark 7",
    "sg:city":"M\u00fcnchen",
    "sg:phone":"+49 89/335333",
    "sg:postcode":"80538",
    "sg:province":"Bayern",
    "wof:name":"Flair",
    "wof:placetype":"venue"
},
  "geometry": {"coordinates":[11.597751,48.152412],"type":"Point"}
}