{
  "type": "Feature",
  "properties": {
    "iso:country":"DE",
    "sg:address":"Ludwigsrta\u00dfe 40",
    "sg:city":"Friedberg",
    "sg:phone":"+49 821/6070503",
    "sg:postcode":"86316",
    "sg:province":"Bayern",
    "wof:name":"Marthas Glasvitrine",
    "wof:placetype":"venue"
},
  "geometry": {"coordinates":[10.9561719894,48.3593177795],"type":"Point"}
}