{
  "type": "Feature",
  "properties": {
    "iso:country":"DE",
    "sg:address":"Steinrapener Weg 3",
    "sg:city":"Oer-Erkenschwick",
    "sg:phone":"+49 2368/3349",
    "sg:postcode":"45739",
    "sg:province":"Nordrhein-Westfalen",
    "wof:name":"Heinrich Jeismann",
    "wof:placetype":"venue"
},
  "geometry": {"coordinates":[7.278319,51.64513],"type":"Point"}
}