{
  "type": "Feature",
  "properties": {
    "iso:country":"DE",
    "sg:address":"Hafnergasse 6",
    "sg:city":"Villingen-Schwenningen",
    "sg:phone":"+49 7721/51735",
    "sg:postcode":"78050",
    "sg:province":"Baden-W\u00fcrttemberg",
    "wof:name":"Schulz Contact Kg",
    "wof:placetype":"venue"
},
  "geometry": {"coordinates":[8.460204,48.061089],"type":"Point"}
}