{
  "type": "Feature",
  "properties": {
    "iso:country":"DE",
    "sg:address":"Alpenstr. 12a",
    "sg:city":"M\u00fcnchen",
    "sg:phone":"+49 89/69364680",
    "sg:postcode":"81541",
    "sg:province":"Bayern",
    "wof:name":"Mxm Digital-service F\u00fcr Werbe- Und Medienvorlagen Gmbh",
    "wof:placetype":"venue"
},
  "geometry": {"coordinates":[11.582701683,48.1168327332],"type":"Point"}
}