{
  "type": "Feature",
  "properties": {
    "iso:country":"DE",
    "sg:address":"Am Krummen Acker 18",
    "sg:city":"Ha\u00dfbergen",
    "sg:phone":"+49 5024/944050",
    "sg:postcode":"31626",
    "sg:province":"Niedersachsen",
    "wof:name":"R. Bremer",
    "wof:placetype":"venue"
},
  "geometry": {"coordinates":[9.2357263565,52.7338562012],"type":"Point"}
}