{
  "type": "Feature",
  "properties": {
    "iso:country":"DE",
    "sg:address":"Dorfstr. 131",
    "sg:city":"M\u00f6nkebude",
    "sg:phone":"+49 39774/20208",
    "sg:postcode":"17375",
    "sg:province":"Mecklenburg-Vorpommern",
    "wof:name":"Zur Sonne Inh. Egon Gaffry",
    "wof:placetype":"venue"
},
  "geometry": {"coordinates":[13.9679002762,53.7705802917],"type":"Point"}
}