{
  "type": "Feature",
  "properties": {
    "iso:country":"DE",
    "sg:address":"Alpirsbacher Str. 9",
    "sg:city":"Betzweiler",
    "sg:phone":"+49 4974/551077",
    "sg:postcode":"72291",
    "wof:name":"Genossenschaftsbank Betzweiler Eg",
    "wof:placetype":"venue"
},
  "geometry": {"coordinates":[8.485255,48.360554],"type":"Point"}
}