{
  "type": "Feature",
  "properties": {
    "iso:country":"DE",
    "sg:address":"Wollweberstr. 82",
    "sg:city":"Friedland",
    "sg:phone":"+49 39601/20242",
    "sg:postcode":"17098",
    "sg:province":"Mecklenburg-Vorpommern",
    "wof:name":"P & K Baumanagement Gmbh",
    "wof:placetype":"venue"
},
  "geometry": {"coordinates":[13.549485,53.66663],"type":"Point"}
}