{
  "type": "Feature",
  "properties": {
    "iso:country":"DE",
    "sg:address":"Lochbach 14",
    "sg:city":"Schluchsee",
    "sg:phone":"+49 7656/256",
    "sg:postcode":"79859",
    "sg:province":"Baden-W\u00fcrttemberg",
    "wof:name":"Reisecenter Reinschmidt Gmbh",
    "wof:placetype":"venue"
},
  "geometry": {"coordinates":[8.179621,47.790894],"type":"Point"}
}