{
  "type": "Feature",
  "properties": {
    "iso:country":"DE",
    "sg:address":"Rathausstr. 8",
    "sg:city":"Neustadt",
    "sg:phone":"+49 6321/7861",
    "sg:postcode":"67433",
    "sg:province":"Rheinland-Pfalz",
    "wof:name":"Rathaus Apotheke",
    "wof:placetype":"venue"
},
  "geometry": {"coordinates":[8.135354,49.354065],"type":"Point"}
}