{
  "type": "Feature",
  "properties": {
    "iso:country":"DE",
    "sg:address":"Heinrich-Heine-Ring 1",
    "sg:city":"Schleusingen",
    "sg:phone":"+49 36841/40873",
    "sg:postcode":"98553",
    "sg:province":"Th\u00fcringen",
    "wof:name":"Arno Imber",
    "wof:placetype":"venue"
},
  "geometry": {"coordinates":[10.761543,50.511055],"type":"Point"}
}