{
  "type": "Feature",
  "properties": {
    "iso:country":"DE",
    "sg:address":"Alte Poststr 24",
    "sg:city":"Lochum",
    "sg:phone":"+49 2666/95150",
    "sg:postcode":"57629",
    "sg:province":"Rheinland-Pfalz",
    "wof:name":"C-p Creativ Partner Gmbh",
    "wof:placetype":"venue"
},
  "geometry": {"coordinates":[7.858167,50.606831],"type":"Point"}
}