{
  "type": "Feature",
  "properties": {
    "iso:country":"DE",
    "sg:address":"Fabrikstr. 10",
    "sg:city":"Schee\u00dfel",
    "sg:phone":"+49 4263/8392",
    "sg:postcode":"27383",
    "sg:province":"Niedersachsen",
    "wof:name":"Joachim Behrens",
    "wof:placetype":"venue"
},
  "geometry": {"coordinates":[9.4951877594,53.1667633057],"type":"Point"}
}