{
  "type": "Feature",
  "properties": {
    "iso:country":"DE",
    "sg:address":"B\u00e4ckergasse 10",
    "sg:city":"Berg",
    "sg:phone":"+49 8151/51631",
    "sg:postcode":"82335",
    "sg:province":"Bayern",
    "wof:name":"Otto Andreae",
    "wof:placetype":"venue"
},
  "geometry": {"coordinates":[11.35521698,47.9683952332],"type":"Point"}
}