{
  "type": "Feature",
  "properties": {
    "iso:country":"DE",
    "sg:address":"Schulbergstr. 64",
    "sg:city":"Passau",
    "sg:phone":"+49 851/45151",
    "sg:postcode":"94034",
    "sg:province":"Bayern",
    "wof:name":"Manfred Endele",
    "wof:placetype":"venue"
},
  "geometry": {"coordinates":[13.490443,48.585369],"type":"Point"}
}