{
  "type": "Feature",
  "properties": {
    "iso:country":"DE",
    "sg:address":"Traunreuter Str. 28",
    "sg:city":"Waldkraiburg",
    "sg:phone":"+49 8638/2785",
    "sg:postcode":"84478",
    "sg:province":"Bayern",
    "wof:name":"Bichlmaier",
    "wof:placetype":"venue"
},
  "geometry": {"coordinates":[12.415528,48.214134],"type":"Point"}
}