{
  "type": "Feature",
  "properties": {
    "iso:country":"DE",
    "sg:address":"Niederg\u00e4rten 2",
    "sg:city":"Ranstadt",
    "sg:phone":"+49 6035/2909",
    "sg:postcode":"63691",
    "sg:province":"Hessen",
    "wof:name":"Gerhard Eberling",
    "wof:placetype":"venue"
},
  "geometry": {"coordinates":[8.9538469315,50.3606643677],"type":"Point"}
}