{
  "type": "Feature",
  "properties": {
    "iso:country":"DE",
    "sg:address":"Lappengasse 19",
    "sg:city":"Trusetal",
    "sg:phone":"+49 36840/80003",
    "sg:postcode":"98596",
    "sg:province":"Th\u00fcringen",
    "wof:name":"Giebel-bau Trusetal Gmbh",
    "wof:placetype":"venue"
},
  "geometry": {"coordinates":[10.4106550217,50.7890853882],"type":"Point"}
}