{
  "type": "Feature",
  "properties": {
    "iso:country":"DE",
    "sg:address":"J\u00e4gerbergstr. 1",
    "sg:city":"Wenzenbach",
    "sg:postcode":"93173",
    "sg:province":"Bayern",
    "wof:name":"Hugo Schall Kg",
    "wof:placetype":"venue"
},
  "geometry": {"coordinates":[12.1431589127,49.0586853027],"type":"Point"}
}