{
  "type": "Feature",
  "properties": {
    "iso:country":"DE",
    "sg:address":"Borsigstr. 32",
    "sg:city":"Velbert",
    "sg:phone":"+49 4920/5128220",
    "sg:postcode":"42551",
    "sg:province":"Nordrhein-Westfalen",
    "wof:name":"Karl Wagenaar Gmbh",
    "wof:placetype":"venue"
},
  "geometry": {"coordinates":[7.063264,51.348366],"type":"Point"}
}