{
  "type": "Feature",
  "properties": {
    "iso:country":"DE",
    "sg:address":"Friedrich-Ebert-Allee 13",
    "sg:city":"Bad M\u00fcnder",
    "sg:phone":"+49 5042/3798",
    "sg:postcode":"31848",
    "sg:province":"Niedersachsen",
    "wof:name":"R. Wegener",
    "wof:placetype":"venue"
},
  "geometry": {"coordinates":[9.464746,52.199211],"type":"Point"}
}