{
  "type": "Feature",
  "properties": {
    "iso:country":"DE",
    "sg:address":"Freudensee 25",
    "sg:city":"Hauzenberg",
    "sg:phone":"+49 8586/1364",
    "sg:postcode":"94051",
    "sg:province":"Bayern",
    "wof:name":"G. Poschinger",
    "wof:placetype":"venue"
},
  "geometry": {"coordinates":[13.6385908127,48.6606445312],"type":"Point"}
}