{
  "type": "Feature",
  "properties": {
    "iso:country":"DE",
    "sg:address":"Hendrichplatz 23",
    "sg:city":"Berlin",
    "sg:phone":"+49 30/5588337",
    "sg:postcode":"10367",
    "sg:province":"Berlin",
    "wof:name":"Jens Herfurth Otto-versandagentur",
    "wof:placetype":"venue"
},
  "geometry": {"coordinates":[13.4837245941,52.5199699402],"type":"Point"}
}