{
  "type": "Feature",
  "properties": {
    "iso:country":"DE",
    "sg:address":"Marktstr.25a",
    "sg:city":"Winningen",
    "sg:phone":"+49 2606/962551",
    "sg:postcode":"56333",
    "sg:province":"Rheinland-Pfalz",
    "wof:name":"Seiffert & Partner Gbr Mbh Handy Shop",
    "wof:placetype":"venue"
},
  "geometry": {"coordinates":[7.516326,50.312675],"type":"Point"}
}