{
  "type": "Feature",
  "properties": {
    "iso:country":"DE",
    "sg:address":"Bahnhofstr. 2",
    "sg:city":"Richtenberg",
    "sg:phone":"+49 38322/307",
    "sg:postcode":"18461",
    "sg:province":"Mecklenburg-Vorpommern",
    "wof:name":"A. Reinke Masseur",
    "wof:placetype":"venue"
},
  "geometry": {"coordinates":[12.902056,54.204243],"type":"Point"}
}