{
  "type": "Feature",
  "properties": {
    "iso:country":"DE",
    "sg:address":"Mozartweg 34",
    "sg:city":"Apolda",
    "sg:phone":"+49 3644/619994",
    "sg:postcode":"99510",
    "sg:province":"Th\u00fcringen",
    "wof:name":"Horst Immisch",
    "wof:placetype":"venue"
},
  "geometry": {"coordinates":[11.501577,51.022331],"type":"Point"}
}