{
  "type": "Feature",
  "properties": {
    "iso:country":"DE",
    "sg:address":"Junghansstr. 58",
    "sg:city":"Dresden",
    "sg:phone":"+49 351/2581613",
    "sg:postcode":"01277",
    "sg:province":"Sachsen",
    "wof:name":"J\u00fcrgen Schmidt Steuerberater",
    "wof:placetype":"venue"
},
  "geometry": {"coordinates":[13.7890758514,51.034614563],"type":"Point"}
}