{
  "type": "Feature",
  "properties": {
    "iso:country":"DE",
    "sg:address":"K\u00f6nigstr. 45",
    "sg:city":"Elmshorn",
    "sg:phone":"+49 4121/20425",
    "sg:postcode":"25335",
    "sg:province":"Schleswig-Holstein",
    "wof:name":"Rosemarie Thorm\u00e4hlen Wettannahme",
    "wof:placetype":"venue"
},
  "geometry": {"coordinates":[9.6551790237,53.7533683777],"type":"Point"}
}