{
  "type": "Feature",
  "properties": {
    "iso:country":"DE",
    "sg:address":"Danckelmannstr. 48",
    "sg:city":"Berlin",
    "sg:phone":"+49 30/3221098",
    "sg:postcode":"14059",
    "sg:province":"Berlin",
    "wof:name":"H\u00e4usliche Krankenpflege Gadow-gehrke Gbr",
    "wof:placetype":"venue"
},
  "geometry": {"coordinates":[13.291105,52.514606],"type":"Point"}
}