{
  "type": "Feature",
  "properties": {
    "iso:country":"DE",
    "sg:address":"Bachstr. 43",
    "sg:city":"H\u00fcrth",
    "sg:phone":"+49 2233/691222",
    "sg:postcode":"50354",
    "sg:province":"Nordrhein-Westfalen",
    "wof:name":"Trump Einbauk\u00fcchen Gmbh",
    "wof:placetype":"venue"
},
  "geometry": {"coordinates":[6.8955111504,50.8952064514],"type":"Point"}
}