{
  "type": "Feature",
  "properties": {
    "iso:country":"DE",
    "sg:address":"Dresdner Str. 22a",
    "sg:city":"Cossebaude",
    "sg:phone":"+49 351/4521297",
    "sg:postcode":"01462",
    "wof:name":"Eva Koch Rechtsanw\u00e4ltin",
    "wof:placetype":"venue"
},
  "geometry": {"coordinates":[13.6390695572,51.0870399475],"type":"Point"}
}