{
  "type": "Feature",
  "properties": {
    "iso:country":"DE",
    "sg:address":"Karl-Haarmann-Str. 1 b",
    "sg:city":"L\u00fcnen",
    "sg:phone":"+49 231/874937",
    "sg:postcode":"44536",
    "sg:province":"Nordrhein-Westfalen",
    "wof:name":"Podlesak",
    "wof:placetype":"venue"
},
  "geometry": {"coordinates":[7.440855,51.59375],"type":"Point"}
}