{
  "type": "Feature",
  "properties": {
    "iso:country":"DE",
    "sg:address":"Gustavstr. 41a",
    "sg:city":"Oberhausen",
    "sg:postcode":"46049",
    "sg:province":"Nordrhein-Westfalen",
    "wof:name":"G. Heisterkamp",
    "wof:placetype":"venue"
},
  "geometry": {"coordinates":[6.850425,51.47979],"type":"Point"}
}