{
  "type": "Feature",
  "properties": {
    "iso:country":"DE",
    "sg:address":"Mariannenplatz 21",
    "sg:city":"Berlin",
    "sg:phone":"+49 30/6127070",
    "sg:postcode":"10997",
    "sg:province":"Berlin",
    "wof:name":"Bewaline-vertriebs Gmbh & Co. Industrie-filter Kg",
    "wof:placetype":"venue"
},
  "geometry": {"coordinates":[13.426461,52.503914],"type":"Point"}
}