{
  "type": "Feature",
  "properties": {
    "iso:country":"DE",
    "sg:address":"Andreassteig 15",
    "sg:city":"B\u00fctzow",
    "sg:postcode":"18246",
    "sg:province":"Mecklenburg-Vorpommern",
    "wof:name":"Innova Gmbh",
    "wof:placetype":"venue"
},
  "geometry": {"coordinates":[11.9929389954,53.837146759],"type":"Point"}
}