{
  "type": "Feature",
  "properties": {
    "iso:country":"DE",
    "sg:address":"Endersbacher Str. 17",
    "sg:city":"Waiblingen",
    "sg:phone":"+49 7151/33168",
    "sg:postcode":"71334",
    "sg:province":"Baden-W\u00fcrttemberg",
    "wof:name":"Siegfried Holzwarth",
    "wof:placetype":"venue"
},
  "geometry": {"coordinates":[9.348113,48.821705],"type":"Point"}
}