{
  "type": "Feature",
  "properties": {
    "iso:country":"DE",
    "sg:address":"Am Margaretenhof 12",
    "sg:city":"Schwerin",
    "sg:postcode":"19057",
    "sg:province":"Mecklenburg-Vorpommern",
    "wof:name":"Ergo Versicherungsgruppe Ag",
    "wof:placetype":"venue"
},
  "geometry": {"coordinates":[11.3588724136,53.6598815918],"type":"Point"}
}