{
  "type": "Feature",
  "properties": {
    "iso:country":"DE",
    "sg:address":"Thiergartenstr. 72",
    "sg:city":"Herzogenrath",
    "sg:phone":"+49 2406/929530",
    "sg:postcode":"52134",
    "sg:province":"Nordrhein-Westfalen",
    "wof:name":"Eurode Projektentwicklungs- Und Bautr\u00e4ger Gmbh",
    "wof:placetype":"venue"
},
  "geometry": {"coordinates":[6.10458,50.875881],"type":"Point"}
}