{
  "type": "Feature",
  "properties": {
    "iso:country":"DE",
    "sg:address":"Bismarckstr. 6 a",
    "sg:city":"Fr\u00f6ndenberg",
    "sg:postcode":"58730",
    "sg:province":"Nordrhein-Westfalen",
    "wof:name":"Gemeinn\u00fctziger Bauverein Eg",
    "wof:placetype":"venue"
},
  "geometry": {"coordinates":[7.7708191872,51.4721488953],"type":"Point"}
}