{
  "type": "Feature",
  "properties": {
    "iso:country":"DE",
    "sg:address":"Friesoyther Str. 28 a",
    "sg:city":"Friesoythe",
    "sg:phone":"+49 4491/91055",
    "sg:postcode":"26169",
    "sg:province":"Niedersachsen",
    "wof:name":"Bernhard Backhaus",
    "wof:placetype":"venue"
},
  "geometry": {"coordinates":[7.776317,53.028862],"type":"Point"}
}