{
  "type": "Feature",
  "properties": {
    "iso:country":"DE",
    "sg:address":"K\u00f6nigstr. 44",
    "sg:city":"Landau",
    "sg:phone":"+49 6341/87523",
    "sg:postcode":"76829",
    "sg:province":"Rheinland-Pfalz",
    "wof:name":"E. J. Meyer",
    "wof:placetype":"venue"
},
  "geometry": {"coordinates":[8.1153707504,49.1972694397],"type":"Point"}
}