{
  "type": "Feature",
  "properties": {
    "iso:country":"DE",
    "sg:address":"Hornschuchallee 32",
    "sg:city":"Forchheim",
    "sg:phone":"+49 9191/15420",
    "sg:postcode":"91301",
    "sg:province":"Bayern",
    "wof:name":"F. Schneider Gmbh & Co. Grundst\u00fccksverwaltungs Kg",
    "wof:placetype":"venue"
},
  "geometry": {"coordinates":[11.0607261658,49.7195472717],"type":"Point"}
}