{
  "type": "Feature",
  "properties": {
    "iso:country":"DE",
    "sg:address":"Usedomer Weg 25",
    "sg:city":"Kiel",
    "sg:phone":"+49 431/311711",
    "sg:postcode":"24107",
    "sg:province":"Schleswig-Holstein",
    "wof:name":"Henning J\u00f6hnk",
    "wof:placetype":"venue"
},
  "geometry": {"coordinates":[10.079341,54.362408],"type":"Point"}
}