{
  "type": "Feature",
  "properties": {
    "iso:country":"DE",
    "sg:address":"Oskar-von-Miller-Str 8",
    "sg:city":"Essenbach",
    "sg:phone":"+49 8703/93980",
    "sg:postcode":"84051",
    "sg:province":"Bayern",
    "wof:name":"Wadle-ari-bau Gmbh",
    "wof:placetype":"venue"
},
  "geometry": {"coordinates":[12.198523,48.586582],"type":"Point"}
}