{
  "type": "Feature",
  "properties": {
    "iso:country":"DE",
    "sg:address":"Justinus-Kerner-Str. 11",
    "sg:city":"G\u00f6ppingen",
    "sg:phone":"+49 7161/74491",
    "sg:postcode":"73035",
    "sg:province":"Baden-W\u00fcrttemberg",
    "wof:name":"Kurt Zeller",
    "wof:placetype":"venue"
},
  "geometry": {"coordinates":[9.643283844,48.6988334656],"type":"Point"}
}