{
  "type": "Feature",
  "properties": {
    "iso:country":"DE",
    "sg:address":"Am Eichholz 10",
    "sg:city":"Morsbach",
    "sg:phone":"+49 2294/1438",
    "sg:postcode":"51597",
    "sg:province":"Nordrhein-Westfalen",
    "wof:name":"Kunibert Rolland",
    "wof:placetype":"venue"
},
  "geometry": {"coordinates":[7.6892490387,50.8366699219],"type":"Point"}
}