{
  "type": "Feature",
  "properties": {
    "iso:country":"DE",
    "sg:address":"Merkurstr. 3 a",
    "sg:city":"Kaiserslautern",
    "sg:phone":"+49 631/351830",
    "sg:postcode":"67663",
    "sg:province":"Rheinland-Pfalz",
    "wof:name":"Dyckerhoff & Widmann Ag",
    "wof:placetype":"venue"
},
  "geometry": {"coordinates":[7.73219,49.444698],"type":"Point"}
}