{
  "type": "Feature",
  "properties": {
    "iso:country":"DE",
    "sg:address":"Wilhelmsplatz 1",
    "sg:city":"Bad Urach",
    "sg:phone":"+49 7125/4801",
    "sg:postcode":"72574",
    "sg:province":"Baden-W\u00fcrttemberg",
    "wof:name":"Restaurant Rostica Inh. Salvatore Masino",
    "wof:placetype":"venue"
},
  "geometry": {"coordinates":[9.4006929398,48.491317749],"type":"Point"}
}