{
  "type": "Feature",
  "properties": {
    "iso:country":"DE",
    "sg:address":"Schwalbacher Str. 57",
    "sg:city":"Wiesbaden",
    "sg:phone":"+49 611/300934",
    "sg:postcode":"65183",
    "sg:province":"Hessen",
    "wof:name":"Del Bianchi",
    "wof:placetype":"venue"
},
  "geometry": {"coordinates":[8.2363481522,50.0825614929],"type":"Point"}
}