{
  "type": "Feature",
  "properties": {
    "iso:country":"DE",
    "sg:address":"Barbarossastr. 34-36",
    "sg:city":"Fellen",
    "sg:phone":"+49 9356/99130",
    "sg:postcode":"97778",
    "sg:province":"Bayern",
    "wof:name":"Spessarttraum Alexander Pflugbeil - Bett-",
    "wof:placetype":"venue"
},
  "geometry": {"coordinates":[9.545694,50.117249],"type":"Point"}
}