{
  "type": "Feature",
  "properties": {
    "iso:country":"DE",
    "sg:address":"Meerstr. 2",
    "sg:city":"Wunstorf",
    "sg:phone":"+49 5033/5000",
    "sg:postcode":"31515",
    "sg:province":"Niedersachsen",
    "wof:name":"Strandterrassen Steinhude Gmbh",
    "wof:placetype":"venue"
},
  "geometry": {"coordinates":[9.3495483398,52.4525260925],"type":"Point"}
}