{
  "type": "Feature",
  "properties": {
    "iso:country":"DE",
    "sg:address":"Hindenburgstr. 67",
    "sg:city":"Herzberg",
    "sg:phone":"+49 5521/2390",
    "sg:postcode":"37412",
    "sg:province":"Niedersachsen",
    "wof:name":"Hotel Goldener Hirsch Inh. Familie Scheidt",
    "wof:placetype":"venue"
},
  "geometry": {"coordinates":[10.3510437012,51.6599884033],"type":"Point"}
}