{
  "type": "Feature",
  "properties": {
    "iso:country":"DE",
    "sg:address":"Clemensstr. 1",
    "sg:city":"Koblenz",
    "sg:phone":"+49 261/10060",
    "sg:postcode":"56068",
    "sg:province":"Rheinland-Pfalz",
    "wof:name":"Hotel Trierer Hof",
    "wof:placetype":"venue"
},
  "geometry": {"coordinates":[7.5996689796,50.3583106995],"type":"Point"}
}