{
  "type": "Feature",
  "properties": {
    "iso:country":"DE",
    "sg:address":"Rothenseer Str. 66 b",
    "sg:city":"Magdeburg",
    "sg:postcode":"39124",
    "sg:province":"Sachsen-Anhalt",
    "wof:name":"Rl-vermietungs Gmbh",
    "wof:placetype":"venue"
},
  "geometry": {"coordinates":[11.6546840668,52.1602020264],"type":"Point"}
}