{
  "type": "Feature",
  "properties": {
    "iso:country":"DE",
    "sg:address":"Murgstr. 3",
    "sg:city":"Mannheim",
    "sg:phone":"+49 621/377125",
    "sg:postcode":"68167",
    "sg:province":"Baden-W\u00fcrttemberg",
    "wof:name":"Beratungsstelle F\u00fcr Jugendliche Zuwanderer",
    "wof:placetype":"venue"
},
  "geometry": {"coordinates":[8.479914,49.499722],"type":"Point"}
}