{
  "type": "Feature",
  "properties": {
    "iso:country":"DE",
    "sg:city":"Stuttgart",
    "sg:postcode":"70374",
    "sg:province":"Baden-W\u00fcrttemberg",
    "wof:name":"Partner Unternehmensgestaltung Gmbh & Immocon Bayer Gmbh",
    "wof:placetype":"venue"
},
  "geometry": {"coordinates":[9.243035,48.81535],"type":"Point"}
}