{
  "type": "Feature",
  "properties": {
    "iso:country":"DE",
    "sg:address":"Am Lemsen 13",
    "sg:city":"Gro\u00dfenkneten",
    "sg:phone":"+49 4435/1214",
    "sg:postcode":"26197",
    "sg:province":"Niedersachsen",
    "wof:name":"Heinrich Becker-br\u00fcning",
    "wof:placetype":"venue"
},
  "geometry": {"coordinates":[8.222706,52.918251],"type":"Point"}
}