{
  "type": "Feature",
  "properties": {
    "iso:country":"DE",
    "sg:address":"Friedhofstr. 10",
    "sg:city":"Breidenbach",
    "sg:phone":"+49 6465/4243",
    "sg:postcode":"35236",
    "sg:province":"Hessen",
    "wof:name":"Otto Gmbh Wohnungs- Und Siedlungsbau",
    "wof:placetype":"venue"
},
  "geometry": {"coordinates":[8.3945713043,50.8615875244],"type":"Point"}
}