{
  "type": "Feature",
  "properties": {
    "iso:country":"DE",
    "sg:address":"Karstr. 116",
    "sg:city":"M\u00f6nchengladbach",
    "sg:phone":"+49 2161/833191",
    "sg:postcode":"41068",
    "sg:province":"Nordrhein-Westfalen",
    "wof:name":"Ingenmey & Gerats Verwaltungsges. Mbh",
    "wof:placetype":"venue"
},
  "geometry": {"coordinates":[6.409953,51.190815],"type":"Point"}
}