{
  "type": "Feature",
  "properties": {
    "iso:country":"DE",
    "sg:address":"Bacchusstr. 15",
    "sg:city":"Sommerach",
    "sg:phone":"+49 9381/2885",
    "sg:postcode":"97334",
    "sg:province":"Bayern",
    "wof:name":"T. Petersen Masseur",
    "wof:placetype":"venue"
},
  "geometry": {"coordinates":[10.211035,49.831253],"type":"Point"}
}