{
  "type": "Feature",
  "properties": {
    "iso:country":"DE",
    "sg:address":"Mendener Str. 25",
    "sg:city":"Arnsberg",
    "sg:postcode":"59755",
    "sg:province":"Nordrhein-Westfalen",
    "wof:name":"Bekadis Gmbh",
    "wof:placetype":"venue"
},
  "geometry": {"coordinates":[7.957886219,51.4545478821],"type":"Point"}
}