{
  "type": "Feature",
  "properties": {
    "iso:country":"DE",
    "sg:address":"Ehlbeek 10",
    "sg:city":"Burgwedel",
    "sg:phone":"+49 5139/6318",
    "sg:postcode":"30938",
    "sg:province":"Niedersachsen",
    "wof:name":"Deutsches Rotes Kreuz",
    "wof:placetype":"venue"
},
  "geometry": {"coordinates":[9.843522,52.48946],"type":"Point"}
}