{
  "type": "Feature",
  "properties": {
    "iso:country":"DE",
    "sg:address":"Lange Str. 1",
    "sg:city":"Sulingen",
    "sg:phone":"+49 4271/5617",
    "sg:postcode":"27232",
    "sg:province":"Niedersachsen",
    "wof:name":"Reiseb\u00fcro Dr\u00e4ger Gmbh",
    "wof:placetype":"venue"
},
  "geometry": {"coordinates":[8.7846469879,52.6889801025],"type":"Point"}
}