{
  "type": "Feature",
  "properties": {
    "iso:country":"DE",
    "sg:address":"Heinrich-Krone-Str 10",
    "sg:city":"Spelle",
    "sg:phone":"+49 7524/97700",
    "sg:postcode":"48480",
    "sg:province":"Niedersachsen",
    "wof:name":"Neyer-landtechnik",
    "wof:placetype":"venue"
},
  "geometry": {"coordinates":[9.8018865585,47.8831100464],"type":"Point"}
}