{
  "type": "Feature",
  "properties": {
    "iso:country":"DE",
    "sg:address":"Steinf\u00f6rder Str. 4",
    "sg:city":"Wietze",
    "sg:phone":"+49 5146/50726",
    "sg:postcode":"29323",
    "sg:province":"Niedersachsen",
    "wof:name":"Gemeindearchiv",
    "wof:placetype":"venue"
},
  "geometry": {"coordinates":[9.840132,52.654575],"type":"Point"}
}