{
  "type": "Feature",
  "properties": {
    "iso:country":"DE",
    "sg:address":"Eckernf\u00f6rder Chaussee 3",
    "sg:city":"Gettorf",
    "sg:phone":"+49 4346/444",
    "sg:postcode":"24214",
    "sg:province":"Schleswig-Holstein",
    "wof:name":"Dillenburg Kg",
    "wof:placetype":"venue"
},
  "geometry": {"coordinates":[9.9780311584,54.4115333557],"type":"Point"}
}