{
  "type": "Feature",
  "properties": {
    "iso:country":"DE",
    "sg:address":"Bahnhofstr. 8",
    "sg:city":"Lichtenberg",
    "sg:phone":"+49 37323/264",
    "sg:postcode":"09638",
    "sg:province":"Sachsen",
    "wof:name":"Kreissparkasse Brand-erbisdorf",
    "wof:placetype":"venue"
},
  "geometry": {"coordinates":[13.404948,50.843086],"type":"Point"}
}