{
  "type": "Feature",
  "properties": {
    "iso:country":"DE",
    "sg:address":"Am Markt 5",
    "sg:city":"Templin",
    "sg:phone":"+49 3987/52325",
    "sg:postcode":"17268",
    "sg:province":"Brandenburg",
    "wof:name":"Modehaus Splinter",
    "wof:placetype":"venue"
},
  "geometry": {"coordinates":[13.50158,53.119576],"type":"Point"}
}