{
  "type": "Feature",
  "properties": {
    "iso:country":"DE",
    "sg:address":"Mittelneufnacher Str. 2",
    "sg:city":"Hiltenfingen",
    "sg:phone":"+49 8232/2403",
    "sg:postcode":"86856",
    "sg:province":"Bayern",
    "wof:name":"Traube",
    "wof:placetype":"venue"
},
  "geometry": {"coordinates":[10.7176132202,48.1617774963],"type":"Point"}
}