{
  "type": "Feature",
  "properties": {
    "iso:country":"DE",
    "sg:address":"Winzler Str. 82",
    "sg:city":"Pirmasens",
    "sg:phone":"+49 6331/63501",
    "sg:postcode":"66955",
    "sg:province":"Rheinland-Pfalz",
    "wof:name":"H. Linn",
    "wof:placetype":"venue"
},
  "geometry": {"coordinates":[7.599211216,49.1967468262],"type":"Point"}
}