{
  "type": "Feature",
  "properties": {
    "iso:country":"DE",
    "sg:address":"Starnberger Str. 24",
    "sg:city":"Gauting",
    "sg:phone":"+49 89/8502283",
    "sg:postcode":"82131",
    "sg:province":"Bayern",
    "wof:name":"Syrtaki",
    "wof:placetype":"venue"
},
  "geometry": {"coordinates":[11.3780841827,48.0642585754],"type":"Point"}
}