{
  "type": "Feature",
  "properties": {
    "iso:country":"DE",
    "sg:address":"Badergasse 10",
    "sg:city":"Colditz",
    "sg:phone":"+49 34381/42344",
    "sg:postcode":"04680",
    "sg:province":"Sachsen",
    "wof:name":"Jochen M\u00fcller",
    "wof:placetype":"venue"
},
  "geometry": {"coordinates":[12.804988,51.130623],"type":"Point"}
}