{
  "type": "Feature",
  "properties": {
    "iso:country":"DE",
    "sg:address":"Bahnhofstr. 10",
    "sg:city":"Loitsche",
    "sg:phone":"+49 4939/2082019",
    "sg:postcode":"39326",
    "sg:province":"Sachsen-Anhalt",
    "wof:name":"Manfred Ga\u00dfmann",
    "wof:placetype":"venue"
},
  "geometry": {"coordinates":[11.703474,52.304302],"type":"Point"}
}