{
  "type": "Feature",
  "properties": {
    "iso:country":"DE",
    "sg:address":"Alte Celler Heerstr. 50",
    "sg:city":"Winsen",
    "sg:phone":"+49 5143/8922",
    "sg:postcode":"29308",
    "sg:province":"Niedersachsen",
    "wof:name":"Hans-joachim K\u00fchl Garten- Und",
    "wof:placetype":"venue"
},
  "geometry": {"coordinates":[9.919269,52.679142],"type":"Point"}
}