{
  "type": "Feature",
  "properties": {
    "iso:country":"DE",
    "sg:address":"Honiggasse 15",
    "sg:city":"Heitersheim",
    "sg:phone":"+49 7634/2337",
    "sg:postcode":"79423",
    "sg:province":"Baden-W\u00fcrttemberg",
    "wof:name":"Edmund Und Heidi Wei\u00df",
    "wof:placetype":"venue"
},
  "geometry": {"coordinates":[7.6675581932,47.8684387207],"type":"Point"}
}