{
  "type": "Feature",
  "properties": {
    "iso:country":"DE",
    "sg:address":"Meisenstr. 110",
    "sg:city":"Marl",
    "sg:postcode":"45772",
    "sg:province":"Nordrhein-Westfalen",
    "wof:name":"Privatbesitz Bautr\u00e4ger Gmbh",
    "wof:placetype":"venue"
},
  "geometry": {"coordinates":[7.1342158318,51.6830329895],"type":"Point"}
}