{
  "type": "Feature",
  "properties": {
    "iso:country":"DE",
    "sg:address":"Prof.-Haindorf-Str. 28",
    "sg:city":"Hamm",
    "sg:phone":"+49 2381/953535",
    "sg:postcode":"59630",
    "sg:province":"Nordrhein-Westfalen",
    "wof:name":"Pts Psychologisches Trainingsinstitut Sch\u00fctt",
    "wof:placetype":"venue"
},
  "geometry": {"coordinates":[-99.3775253296,35.6328315735],"type":"Point"}
}