{
  "type": "Feature",
  "properties": {
    "iso:country":"DE",
    "sg:address":"Blumengasse 1",
    "sg:city":"Bad Bocklet",
    "sg:phone":"+49 9708/91990",
    "sg:postcode":"97708",
    "sg:province":"Bayern",
    "wof:name":"Ingrid Sch\u00e4fer Masseurin",
    "wof:placetype":"venue"
},
  "geometry": {"coordinates":[10.077349,50.266621],"type":"Point"}
}