{
  "type": "Feature",
  "properties": {
    "iso:country":"DE",
    "sg:address":"H\u00fcttenstra\u00dfe 15",
    "sg:city":"Isselburg",
    "sg:phone":"+49 2874/3599",
    "sg:postcode":"46419",
    "sg:province":"Nordrhein-Westfalen",
    "wof:name":"Firma Theodor Terhorst",
    "wof:placetype":"venue"
},
  "geometry": {"coordinates":[6.4613089561,51.8377113342],"type":"Point"}
}