{
  "type": "Feature",
  "properties": {
    "iso:country":"DE",
    "sg:address":"Falkenstr. 45",
    "sg:city":"Georgsmarienh\u00fctte",
    "sg:phone":"+49 5401/2546",
    "sg:postcode":"49124",
    "sg:province":"Niedersachsen",
    "wof:name":"Lachmann",
    "wof:placetype":"venue"
},
  "geometry": {"coordinates":[8.0256576538,52.2062301636],"type":"Point"}
}