{
  "type": "Feature",
  "properties": {
    "iso:country":"DE",
    "sg:address":"Mozartstr. 1",
    "sg:city":"Baunatal",
    "sg:phone":"+49 561/494054",
    "sg:postcode":"34225",
    "sg:province":"Hessen",
    "wof:name":"Anodolou Spor Asim \u00dcnalmis",
    "wof:placetype":"venue"
},
  "geometry": {"coordinates":[9.4144668579,51.2507553101],"type":"Point"}
}