{
  "type": "Feature",
  "properties": {
    "iso:country":"DE",
    "sg:address":"Falkenstr. 1",
    "sg:city":"Heilbronn",
    "sg:phone":"+49 7131/85533",
    "sg:postcode":"74072",
    "sg:province":"Baden-W\u00fcrttemberg",
    "wof:name":"Iffland H\u00f6rger\u00e4te",
    "wof:placetype":"venue"
},
  "geometry": {"coordinates":[9.2195453644,49.1425666809],"type":"Point"}
}