{
  "type": "Feature",
  "properties": {
    "iso:country":"DE",
    "sg:address":"Otto-Dix-Ring 92",
    "sg:city":"Dresden",
    "sg:phone":"+49 351/2753611",
    "sg:postcode":"01219",
    "sg:province":"Sachsen",
    "wof:name":"Dipl.-ing. W. Becker",
    "wof:placetype":"venue"
},
  "geometry": {"coordinates":[13.778971,51.017368],"type":"Point"}
}