{
  "type": "Feature",
  "properties": {
    "iso:country":"DE",
    "sg:address":"Hauptstr. 2",
    "sg:city":"Germaringen",
    "sg:phone":"+49 8341/66090",
    "sg:postcode":"87656",
    "sg:province":"Bayern",
    "wof:name":"Gebr. Nocker Verm\u00f6gensverwaltung Gmbh",
    "wof:placetype":"venue"
},
  "geometry": {"coordinates":[10.6718158722,47.9234275818],"type":"Point"}
}