{
  "type": "Feature",
  "properties": {
    "iso:country":"DE",
    "sg:address":"Steinensittenbach 16",
    "sg:city":"Kirchensittenbach",
    "sg:phone":"+49 9151/94557",
    "sg:postcode":"91241",
    "sg:province":"Bayern",
    "wof:name":"Hans Liedel",
    "wof:placetype":"venue"
},
  "geometry": {"coordinates":[11.411858,49.593742],"type":"Point"}
}