{
  "type": "Feature",
  "properties": {
    "iso:country":"DE",
    "sg:address":"Elbchaussee 330",
    "sg:city":"Hamburg",
    "sg:phone":"+49 40/82310300",
    "sg:postcode":"22609",
    "sg:province":"Hamburg",
    "wof:name":"Pensionskasse Der Lotsenbr\u00fcderschaft Elbe",
    "wof:placetype":"venue"
},
  "geometry": {"coordinates":[9.8624715805,53.5475845337],"type":"Point"}
}