{
  "type": "Feature",
  "properties": {
    "iso:country":"DE",
    "sg:address":"Wernher-V.-Braun-Str. 7",
    "sg:city":"Wallenhorst",
    "sg:phone":"+49 4954/078900",
    "sg:postcode":"49134",
    "sg:province":"Niedersachsen",
    "wof:name":"H\u00d6cker Anlagebau Gmbh",
    "wof:placetype":"venue"
},
  "geometry": {"coordinates":[8.016464,52.350082],"type":"Point"}
}