{
  "type": "Feature",
  "properties": {
    "iso:country":"DE",
    "sg:address":"Markgrafenstr 22",
    "sg:city":"Berlin",
    "sg:phone":"+49 30/284930",
    "sg:postcode":"10117",
    "sg:province":"Berlin",
    "wof:name":"Pmg Presse-monitor Deutschland Gmbh & Co Kg",
    "wof:placetype":"venue"
},
  "geometry": {"coordinates":[13.3944149017,52.5081176758],"type":"Point"}
}