{
  "type": "Feature",
  "properties": {
    "iso:country":"DE",
    "sg:address":"Blumberger Damm 164",
    "sg:city":"Berlin",
    "sg:phone":"+49 30/9370082",
    "sg:postcode":"12679",
    "sg:province":"Berlin",
    "wof:name":"Peter Jokiel",
    "wof:placetype":"venue"
},
  "geometry": {"coordinates":[13.5729780197,52.5478057861],"type":"Point"}
}