{
  "type": "Feature",
  "properties": {
    "iso:country":"DE",
    "sg:address":"Germanenstr. 56",
    "sg:city":"Bielefeld",
    "sg:phone":"+49 521/443279",
    "sg:postcode":"33647",
    "sg:province":"Nordrhein-Westfalen",
    "wof:name":"Dirk Mei\u00dfner Masseur",
    "wof:placetype":"venue"
},
  "geometry": {"coordinates":[8.504,51.988647],"type":"Point"}
}