{
  "type": "Feature",
  "properties": {
    "iso:country":"DE",
    "sg:address":"Eichendorfer Str. 15",
    "sg:city":"Eichendorf",
    "sg:phone":"+49 9956/307",
    "sg:postcode":"94428",
    "sg:province":"Bayern",
    "wof:name":"Volksbank-raiffeisenbank Landa",
    "wof:placetype":"venue"
},
  "geometry": {"coordinates":[12.761945,48.615368],"type":"Point"}
}