{
  "type": "Feature",
  "properties": {
    "iso:country":"DE",
    "sg:address":"Hochstr. 34",
    "sg:city":"Sonsbeck",
    "sg:phone":"+49 2838/2323",
    "sg:postcode":"47665",
    "sg:province":"Nordrhein-Westfalen",
    "wof:name":"Franz Jacobs",
    "wof:placetype":"venue"
},
  "geometry": {"coordinates":[6.3759050369,51.6095237732],"type":"Point"}
}