{
  "type": "Feature",
  "properties": {
    "iso:country":"DE",
    "sg:address":"Sandackerstr. 11",
    "sg:city":"Amberg",
    "sg:postcode":"92224",
    "sg:province":"Bayern",
    "wof:name":"Veritas Consult Gmbh",
    "wof:placetype":"venue"
},
  "geometry": {"coordinates":[11.8365497589,49.4319229126],"type":"Point"}
}