{
  "type": "Feature",
  "properties": {
    "iso:country":"DE",
    "sg:address":"Leipziger Str. 70",
    "sg:city":"Glauchau",
    "sg:phone":"+49 3763/15061",
    "sg:postcode":"08371",
    "sg:province":"Sachsen",
    "wof:name":"M & A Mode & Accessoires Dieter Nitschke",
    "wof:placetype":"venue"
},
  "geometry": {"coordinates":[12.542854,50.820915],"type":"Point"}
}