{
  "type": "Feature",
  "properties": {
    "iso:country":"DE",
    "sg:address":"Kladower Damm 221",
    "sg:city":"Berlin",
    "sg:phone":"+49 30/3655091",
    "sg:postcode":"14089",
    "sg:province":"Berlin",
    "wof:name":"Die Br\u00fccke E. V.",
    "wof:placetype":"venue"
},
  "geometry": {"coordinates":[13.1606893539,52.4636535645],"type":"Point"}
}