{
  "type": "Feature",
  "properties": {
    "iso:country":"DE",
    "sg:address":"Neuh\u00f6fer 6a",
    "sg:city":"Neustadt-Glewe",
    "sg:phone":"+49 38757/30247",
    "sg:postcode":"19306",
    "sg:province":"Mecklenburg-Vorpommern",
    "wof:name":"Stonedesign Eichler",
    "wof:placetype":"venue"
},
  "geometry": {"coordinates":[11.5947656631,53.3800315857],"type":"Point"}
}