{
  "type": "Feature",
  "properties": {
    "iso:country":"DE",
    "sg:address":"Allmendstr. 12",
    "sg:city":"Sandhausen",
    "sg:phone":"+49 6224/55575",
    "sg:postcode":"69207",
    "sg:province":"Baden-W\u00fcrttemberg",
    "wof:name":"Ihs",
    "wof:placetype":"venue"
},
  "geometry": {"coordinates":[8.6645679474,49.3369865417],"type":"Point"}
}