{
  "type": "Feature",
  "properties": {
    "iso:country":"DE",
    "sg:address":"Postfach 1129:: 51655 Wiehl:: Germany.^^Bahnhofstr 3::",
    "sg:city":"Wiehl",
    "sg:phone":"+49 2262/9840",
    "sg:postcode":"51674",
    "sg:province":"Nordrhein-Westfalen",
    "wof:name":"Volksbank Oberberg Eg",
    "wof:placetype":"venue"
},
  "geometry": {"coordinates":[7.499817,50.961948],"type":"Point"}
}