{
  "type": "Feature",
  "properties": {
    "iso:country":"DE",
    "sg:address":"Gr\u00fcndenseestr 7",
    "sg:city":"Frankfurt",
    "sg:phone":"+49 69/42088777",
    "sg:postcode":"60386",
    "sg:province":"Hessen",
    "wof:name":"Druckreif Gmbh & Co Kg",
    "wof:placetype":"venue"
},
  "geometry": {"coordinates":[8.7701120377,50.1215057373],"type":"Point"}
}