{
  "type": "Feature",
  "properties": {
    "iso:country":"DE",
    "sg:address":"Mendelssohnstr. 57",
    "sg:city":"Hannover",
    "sg:phone":"+49 511/806295",
    "sg:postcode":"30173",
    "sg:province":"Niedersachsen",
    "wof:name":"Klambt-verlag Gmbh & Cie.",
    "wof:placetype":"venue"
},
  "geometry": {"coordinates":[9.7564764023,52.3541297913],"type":"Point"}
}