{
  "type": "Feature",
  "properties": {
    "iso:country":"DE",
    "sg:address":"Grimmaische Str. 24",
    "sg:city":"Geithain",
    "sg:phone":"+49 34341/42628",
    "sg:postcode":"04643",
    "sg:province":"Sachsen",
    "wof:name":"Pension Juhlemann",
    "wof:placetype":"venue"
},
  "geometry": {"coordinates":[12.6908607483,51.0598144531],"type":"Point"}
}