{
  "type": "Feature",
  "properties": {
    "iso:country":"DE",
    "sg:address":"Kanalstr. 45",
    "sg:city":"Metzingen",
    "sg:phone":"+49 7123/4550",
    "sg:postcode":"72555",
    "sg:province":"Baden-W\u00fcrttemberg",
    "wof:name":"Wilhelm Wolff Masseur",
    "wof:placetype":"venue"
},
  "geometry": {"coordinates":[9.28009,48.532089],"type":"Point"}
}