{
  "type": "Feature",
  "properties": {
    "iso:country":"DE",
    "sg:address":"Diepenbrockstr. 20",
    "sg:city":"M\u00fcnster",
    "sg:phone":"+49 251/511308",
    "sg:postcode":"48145",
    "sg:province":"Nordrhein-Westfalen",
    "wof:name":"Ingenieur Gesellschaft Schmitz & Zwoll Mbh",
    "wof:placetype":"venue"
},
  "geometry": {"coordinates":[7.6409630775,51.958530426],"type":"Point"}
}