{
  "type": "Feature",
  "properties": {
    "iso:country":"DE",
    "sg:address":"Sinzingerstr. 30",
    "sg:city":"F\u00fcrstenfeldbruck",
    "sg:phone":"+49 8141/526877",
    "sg:postcode":"82256",
    "sg:province":"Bayern",
    "wof:name":"Arno H\u00e4ring",
    "wof:placetype":"venue"
},
  "geometry": {"coordinates":[11.263307,48.182743],"type":"Point"}
}