{
  "type": "Feature",
  "properties": {
    "iso:country":"DE",
    "sg:address":"Mendener Str. 106",
    "sg:city":"Iserlohn",
    "sg:phone":"+49 4923/716425",
    "sg:postcode":"58636",
    "sg:province":"Nordrhein-Westfalen",
    "wof:name":"Bruch Oberfl\u00c4chentechnik",
    "wof:placetype":"venue"
},
  "geometry": {"coordinates":[7.712988,51.377941],"type":"Point"}
}