{
  "type": "Feature",
  "properties": {
    "iso:country":"DE",
    "sg:address":"Kurt-Schumacher-Str. 44",
    "sg:city":"Eschweiler",
    "sg:phone":"+49 2403/51756",
    "sg:postcode":"52249",
    "sg:province":"Nordrhein-Westfalen",
    "wof:name":"Hb Hochbau Gmbh",
    "wof:placetype":"venue"
},
  "geometry": {"coordinates":[6.282824,50.84259],"type":"Point"}
}