{
  "type": "Feature",
  "properties": {
    "iso:country":"DE",
    "sg:address":"Benkheimer Str. 35",
    "sg:city":"Rotenburg",
    "sg:phone":"+49 4261/62841",
    "sg:postcode":"27356",
    "sg:province":"Niedersachsen",
    "wof:name":"Dr. Med. Weidel Arzt F. Allgemeinmedizin",
    "wof:placetype":"venue"
},
  "geometry": {"coordinates":[9.421669,53.109047],"type":"Point"}
}