{
  "type": "Feature",
  "properties": {
    "iso:country":"DE",
    "sg:address":"Reichlensbergweg 22",
    "sg:city":"Blaubeuren",
    "sg:phone":"+49 7344/1415",
    "sg:postcode":"89143",
    "sg:province":"Baden-W\u00fcrttemberg",
    "wof:name":"Adolf Merckle",
    "wof:placetype":"venue"
},
  "geometry": {"coordinates":[9.7889003754,48.4045982361],"type":"Point"}
}