{
  "type": "Feature",
  "properties": {
    "iso:country":"DE",
    "sg:city":"Berlin",
    "sg:phone":"+49 30/6921529",
    "sg:postcode":"10967",
    "sg:province":"Berlin",
    "wof:name":"Jachtschule Paul & Peter",
    "wof:placetype":"venue"
},
  "geometry": {"coordinates":[13.41535,52.491421],"type":"Point"}
}