{
  "type": "Feature",
  "properties": {
    "iso:country":"DE",
    "sg:address":"Andreaestr. 89",
    "sg:city":"Hannover",
    "sg:phone":"+49 511/326545",
    "sg:postcode":"30159",
    "sg:province":"Niedersachsen",
    "wof:name":"Ernst Michaelis Verwaltungen U. Beteiligungen",
    "wof:placetype":"venue"
},
  "geometry": {"coordinates":[9.7371397018,52.3759689331],"type":"Point"}
}