{
  "type": "Feature",
  "properties": {
    "iso:country":"DE",
    "sg:address":"Kurhausstr. 1",
    "sg:city":"Bad Nenndorf",
    "sg:phone":"+49 4957/2379180",
    "sg:postcode":"31542",
    "sg:province":"Niedersachsen",
    "wof:name":"Volksbank Nordschaumburg Eg",
    "wof:placetype":"venue"
},
  "geometry": {"coordinates":[9.374658,52.338005],"type":"Point"}
}