{
  "type": "Feature",
  "properties": {
    "iso:country":"DE",
    "sg:address":"Annweilerstr. 20",
    "sg:city":"Landau",
    "sg:phone":"+49 6341/30711",
    "sg:postcode":"76829",
    "sg:province":"Rheinland-Pfalz",
    "wof:name":"Tws Steuerberatungs- Gmbh",
    "wof:placetype":"venue"
},
  "geometry": {"coordinates":[8.1014947891,49.194770813],"type":"Point"}
}