{
  "type": "Feature",
  "properties": {
    "iso:country":"DE",
    "sg:address":"Dreieichstr. 3 A",
    "sg:city":"M\u00f6rfelden-Walldorf",
    "sg:phone":"+49 6105/91170",
    "sg:postcode":"64546",
    "sg:province":"Hessen",
    "wof:name":"Zaman Verlags Und Handels Gmbh",
    "wof:placetype":"venue"
},
  "geometry": {"coordinates":[8.580163002,49.9827575684],"type":"Point"}
}