{
  "type": "Feature",
  "properties": {
    "iso:country":"DE",
    "sg:address":"Industriestr. 10",
    "sg:city":"Viernheim",
    "sg:phone":"+49 6204/3351",
    "sg:postcode":"68519",
    "sg:province":"Hessen",
    "wof:name":"J. Sax & Sohn Steinmetz",
    "wof:placetype":"venue"
},
  "geometry": {"coordinates":[8.5843267441,49.5451011658],"type":"Point"}
}