{
  "type": "Feature",
  "properties": {
    "iso:country":"DE",
    "sg:address":"Zeppelinstr. 19",
    "sg:city":"M\u00f6ssingen",
    "sg:phone":"+49 7473/94450",
    "sg:postcode":"72116",
    "sg:province":"Baden-W\u00fcrttemberg",
    "wof:name":"Redaktion Amtsblatt Der Stadt M\u00f6ssingen",
    "wof:placetype":"venue"
},
  "geometry": {"coordinates":[9.0405950546,48.4044303894],"type":"Point"}
}