{
  "type": "Feature",
  "properties": {
    "iso:country":"DE",
    "sg:address":"Lindthaler Str. 6",
    "sg:city":"Massen",
    "sg:phone":"+49 3531/702235",
    "sg:postcode":"03238",
    "sg:province":"Brandenburg",
    "wof:name":"Werner Kotte",
    "wof:placetype":"venue"
},
  "geometry": {"coordinates":[13.73442,51.643932],"type":"Point"}
}