{
  "type": "Feature",
  "properties": {
    "iso:country":"DE",
    "sg:address":"Marktstr. 17",
    "sg:city":"Rudolstadt",
    "sg:phone":"+49 3672/24213",
    "sg:postcode":"07407",
    "sg:province":"Th\u00fcringen",
    "wof:name":"Reiseland Ohg",
    "wof:placetype":"venue"
},
  "geometry": {"coordinates":[11.3420057297,50.7203102112],"type":"Point"}
}