{
  "type": "Feature",
  "properties": {
    "iso:country":"DE",
    "sg:address":"Im Hof 1",
    "sg:city":"Albstadt",
    "sg:phone":"+49 7431/3444",
    "sg:postcode":"72458",
    "sg:province":"Baden-W\u00fcrttemberg",
    "wof:name":"Freitag-immobilien Ebingen Und Tailfingen",
    "wof:placetype":"venue"
},
  "geometry": {"coordinates":[9.0270700455,48.213809967],"type":"Point"}
}