{
  "type": "Feature",
  "properties": {
    "iso:country":"DE",
    "sg:address":"Hauptstr. 102",
    "sg:city":"Mannheim",
    "sg:phone":"+49 621/791572",
    "sg:postcode":"68259",
    "sg:province":"Baden-W\u00fcrttemberg",
    "wof:name":"O. Gutfleisch Architekt",
    "wof:placetype":"venue"
},
  "geometry": {"coordinates":[8.52761,49.487431],"type":"Point"}
}