{
  "type": "Feature",
  "properties": {
    "iso:country":"DE",
    "sg:address":"Braunsberg 70",
    "sg:city":"Bergisch Gladbach",
    "sg:phone":"+49 2207/3328",
    "sg:postcode":"51429",
    "sg:province":"Nordrhein-Westfalen",
    "wof:name":"Karl Wermelskirchen Gmbh",
    "wof:placetype":"venue"
},
  "geometry": {"coordinates":[7.204444,50.991703],"type":"Point"}
}