{
  "type": "Feature",
  "properties": {
    "iso:country":"DE",
    "sg:address":"Heinrich-W\u00f6hlk-Str. 4",
    "sg:city":"Sch\u00f6nkirchen",
    "sg:phone":"+49 4348/7010",
    "sg:postcode":"24232",
    "sg:province":"Schleswig-Holstein",
    "wof:name":"Carl Zeiss Sch\u00f6nkirchen Gmbh",
    "wof:placetype":"venue"
},
  "geometry": {"coordinates":[10.209776,54.335854],"type":"Point"}
}