{
  "type": "Feature",
  "properties": {
    "iso:country":"DE",
    "sg:address":"Gerresheimer Str. 8",
    "sg:city":"Hilden",
    "sg:phone":"+49 2103/45832",
    "sg:postcode":"40721",
    "sg:province":"Nordrhein-Westfalen",
    "wof:name":"Hubert Saxler",
    "wof:placetype":"venue"
},
  "geometry": {"coordinates":[6.93033,51.170563],"type":"Point"}
}