{
  "type": "Feature",
  "properties": {
    "iso:country":"DE",
    "sg:address":"Gathestr. 92",
    "sg:city":"M\u00fclheim",
    "sg:phone":"+49 208/757046",
    "sg:postcode":"45475",
    "sg:province":"Nordrhein-Westfalen",
    "wof:name":"L. Andriola",
    "wof:placetype":"venue"
},
  "geometry": {"coordinates":[6.895572,51.45446],"type":"Point"}
}