{
  "type": "Feature",
  "properties": {
    "iso:country":"DE",
    "sg:address":"Gartenkamp 28",
    "sg:city":"Westerkappeln",
    "sg:phone":"+49 5404/96140",
    "sg:postcode":"49492",
    "sg:province":"Nordrhein-Westfalen",
    "wof:name":"Isi Industrie Service E. K.",
    "wof:placetype":"venue"
},
  "geometry": {"coordinates":[7.8957939148,52.3137397766],"type":"Point"}
}