{
  "type": "Feature",
  "properties": {
    "iso:country":"DE",
    "sg:address":"Herbergsweg 1 - 5",
    "sg:city":"Bad M\u00fcnstereifel",
    "sg:phone":"+49 2253/7438",
    "sg:postcode":"53902",
    "sg:province":"Nordrhein-Westfalen",
    "wof:name":"Jugendherberge Bad M\u00fcnstereifel",
    "wof:placetype":"venue"
},
  "geometry": {"coordinates":[6.774515152,50.5535697937],"type":"Point"}
}