{
  "type": "Feature",
  "properties": {
    "iso:country":"DE",
    "sg:address":"M\u00fchlenstr. 35",
    "sg:city":"Weisweil",
    "sg:phone":"+49 7646/203",
    "sg:postcode":"79367",
    "sg:province":"Baden-W\u00fcrttemberg",
    "wof:name":"S\u00fcdgetreide Verwaltungsgesellschaft Mbh",
    "wof:placetype":"venue"
},
  "geometry": {"coordinates":[7.6753401756,48.2038993835],"type":"Point"}
}