{
  "type": "Feature",
  "properties": {
    "iso:country":"DE",
    "sg:address":"N\u00fcdelshalbach 28",
    "sg:city":"Remscheid",
    "sg:phone":"+49 2191/41607",
    "sg:postcode":"42855",
    "sg:province":"Nordrhein-Westfalen",
    "wof:name":"M. Kemper",
    "wof:placetype":"venue"
},
  "geometry": {"coordinates":[7.2001419067,51.1936683655],"type":"Point"}
}