{
  "type": "Feature",
  "properties": {
    "iso:country":"DE",
    "sg:address":"Neunmorgenstr.",
    "sg:city":"Homburg",
    "sg:phone":"+49 6848/206",
    "sg:postcode":"66424",
    "sg:province":"Saarland",
    "wof:name":"Apotheke Im Globus Ein\u00f6d Inh. Else Lehnert",
    "wof:placetype":"venue"
},
  "geometry": {"coordinates":[7.332002,49.263111],"type":"Point"}
}