{
  "type": "Feature",
  "properties": {
    "iso:country":"DE",
    "sg:address":"Appenzeller Str. 127",
    "sg:city":"M\u00fcnchen",
    "sg:phone":"+49 89/7552050",
    "sg:postcode":"81475",
    "sg:province":"Bayern",
    "wof:name":"Carl Reinhard Mosting Architekt",
    "wof:placetype":"venue"
},
  "geometry": {"coordinates":[11.475434,48.093243],"type":"Point"}
}