{
  "type": "Feature",
  "properties": {
    "iso:country":"DE",
    "sg:address":"Stobenstr. 1",
    "sg:city":"Sch\u00f6ppenstedt",
    "sg:phone":"+49 5332/4487",
    "sg:postcode":"38170",
    "sg:province":"Niedersachsen",
    "wof:name":"Grill Am Markt",
    "wof:placetype":"venue"
},
  "geometry": {"coordinates":[10.7745342255,52.144443512],"type":"Point"}
}