{
  "type": "Feature",
  "properties": {
    "iso:country":"DE",
    "sg:address":"Schillerstr. 4",
    "sg:city":"Saarlouis",
    "sg:phone":"+49 6831/2629",
    "sg:postcode":"66740",
    "sg:province":"Saarland",
    "wof:name":"Industriesch\u00e4nke",
    "wof:placetype":"venue"
},
  "geometry": {"coordinates":[6.7351579666,49.3174972534],"type":"Point"}
}