{
  "type": "Feature",
  "properties": {
    "iso:country":"DE",
    "sg:address":"Siegertstr. 2",
    "sg:city":"Hilpoltstein",
    "sg:phone":"+49 9174/492540",
    "sg:postcode":"91161",
    "sg:province":"Bayern",
    "wof:name":"China-restaurant Zuping-zhou",
    "wof:placetype":"venue"
},
  "geometry": {"coordinates":[11.1903553009,49.1882362366],"type":"Point"}
}