{
  "type": "Feature",
  "properties": {
    "iso:country":"DE",
    "sg:address":"Goethestr. 13",
    "sg:city":"Peine",
    "sg:phone":"+49 5171/72262",
    "sg:postcode":"31224",
    "sg:province":"Niedersachsen",
    "wof:name":"Thomas Bertram Rechtsanwalt",
    "wof:placetype":"venue"
},
  "geometry": {"coordinates":[10.2318792343,52.3232536316],"type":"Point"}
}