{
  "type": "Feature",
  "properties": {
    "iso:country":"DE",
    "sg:address":"Gaustr. 36",
    "sg:city":"Bad D\u00fcrkheim",
    "sg:phone":"+49 6322/1500",
    "sg:postcode":"67098",
    "sg:province":"Rheinland-Pfalz",
    "wof:name":"Ingeborg Hanke",
    "wof:placetype":"venue"
},
  "geometry": {"coordinates":[8.1679725647,49.4574623108],"type":"Point"}
}