{
  "type": "Feature",
  "properties": {
    "iso:country":"DE",
    "sg:address":"T\u00f6pferstr. 10",
    "sg:city":"Wundersleben",
    "sg:phone":"+49 36376/50655",
    "sg:postcode":"99610",
    "sg:province":"Th\u00fcringen",
    "wof:name":"Dieter Entzian",
    "wof:placetype":"venue"
},
  "geometry": {"coordinates":[11.039461,51.15218],"type":"Point"}
}