{
  "type": "Feature",
  "properties": {
    "iso:country":"DE",
    "sg:address":"Hertersplatz 7",
    "sg:city":"Alfter",
    "sg:phone":"+49 2222/934149",
    "sg:postcode":"53347",
    "sg:province":"Nordrhein-Westfalen",
    "wof:name":"D. Schneider-lange",
    "wof:placetype":"venue"
},
  "geometry": {"coordinates":[7.0076508522,50.7378196716],"type":"Point"}
}