{
  "type": "Feature",
  "properties": {
    "iso:country":"DE",
    "sg:address":"Leester.Str.86",
    "sg:city":"weyhe",
    "sg:phone":"+49 421/803860",
    "sg:postcode":"28844",
    "sg:province":"Niedersachsen",
    "wof:name":"Br\u00fcns Und Ru\u00dfmann Gbr",
    "wof:placetype":"venue"
},
  "geometry": {"coordinates":[8.8167076111,52.9938468933],"type":"Point"}
}