{
  "type": "Feature",
  "properties": {
    "iso:country":"DE",
    "sg:address":"Markt 6",
    "sg:city":"Senftenberg",
    "sg:phone":"+49 3573/2125",
    "sg:postcode":"01968",
    "sg:province":"Brandenburg",
    "wof:name":"Optik Winkler Gmbh",
    "wof:placetype":"venue"
},
  "geometry": {"coordinates":[14.0041923523,51.5192527771],"type":"Point"}
}