{
  "type": "Feature",
  "properties": {
    "iso:country":"DE",
    "sg:address":"Frankeninsel 1",
    "sg:city":"Oberma\u00dffeld-Grimmenthal",
    "sg:phone":"+49 36949/21873",
    "sg:postcode":"98617",
    "sg:province":"Th\u00fcringen",
    "wof:name":"Foto Hanf",
    "wof:placetype":"venue"
},
  "geometry": {"coordinates":[10.4386968613,50.5272293091],"type":"Point"}
}