{
  "type": "Feature",
  "properties": {
    "iso:country":"DE",
    "sg:address":"D\u00fcrerstr. 11",
    "sg:city":"Homburg",
    "sg:phone":"+49 6841/78439",
    "sg:postcode":"66424",
    "sg:province":"Saarland",
    "wof:name":"Bar Athen",
    "wof:placetype":"venue"
},
  "geometry": {"coordinates":[7.337039,49.331028],"type":"Point"}
}