{
  "type": "Feature",
  "properties": {
    "iso:country":"DE",
    "sg:address":"Grottewitzstr. 37",
    "sg:city":"Berlin",
    "sg:phone":"+49 30/6764873",
    "sg:postcode":"12526",
    "sg:province":"Berlin",
    "wof:name":"Harald Stabel Ingenieur",
    "wof:placetype":"venue"
},
  "geometry": {"coordinates":[13.566491127,52.4047889709],"type":"Point"}
}