{
  "type": "Feature",
  "properties": {
    "iso:country":"DE",
    "sg:address":"Hardenbergstr. 13",
    "sg:city":"F\u00fcrth",
    "sg:postcode":"90768",
    "sg:province":"Bayern",
    "wof:name":"Strebeg Kg",
    "wof:placetype":"venue"
},
  "geometry": {"coordinates":[10.970302,49.467815],"type":"Point"}
}