{
  "type": "Feature",
  "properties": {
    "iso:country":"DE",
    "sg:address":"Wei\u00dfer Rainpfad 8",
    "sg:city":"Bad Soden",
    "sg:phone":"+49 6196/27224",
    "sg:postcode":"65812",
    "sg:province":"Hessen",
    "wof:name":"Hannig Werpapierhandels Gmbh",
    "wof:placetype":"venue"
},
  "geometry": {"coordinates":[8.492016,50.15955],"type":"Point"}
}