{
  "type": "Feature",
  "properties": {
    "iso:country":"DE",
    "sg:address":"Hahnstr. 31-35",
    "sg:city":"Frankfurt",
    "sg:phone":"+49 69/66113278",
    "sg:postcode":"60528",
    "sg:province":"Hessen",
    "wof:name":"Db Service Store Systemf\u00fchrungs Gmbh",
    "wof:placetype":"venue"
},
  "geometry": {"coordinates":[8.6334190369,50.0834503174],"type":"Point"}
}