{
  "type": "Feature",
  "properties": {
    "iso:country":"DE",
    "sg:address":"Bergstr. 12",
    "sg:city":"Kelberg",
    "sg:phone":"+49 2692/85948",
    "sg:postcode":"53539",
    "sg:province":"Rheinland-Pfalz",
    "wof:name":"Anita Blum Architektin",
    "wof:placetype":"venue"
},
  "geometry": {"coordinates":[6.919954,50.290749],"type":"Point"}
}