{
  "type": "Feature",
  "properties": {
    "iso:country":"DE",
    "sg:address":"Rotkehlchenweg 12",
    "sg:city":"Langenfeld",
    "sg:postcode":"40764",
    "sg:province":"Nordrhein-Westfalen",
    "wof:name":"Barbara Beteiligungsges. Mbh",
    "wof:placetype":"venue"
},
  "geometry": {"coordinates":[6.961782,51.103016],"type":"Point"}
}