{
  "type": "Feature",
  "properties": {
    "iso:country":"DE",
    "sg:address":"Heinrich-Heine-Str. 37",
    "sg:city":"Wurzbach",
    "sg:phone":"+49 36652/22727",
    "sg:postcode":"07343",
    "sg:province":"Th\u00fcringen",
    "wof:name":"Mathias Hering",
    "wof:placetype":"venue"
},
  "geometry": {"coordinates":[11.5463857651,50.4663276672],"type":"Point"}
}