{
  "type": "Feature",
  "properties": {
    "iso:country":"DE",
    "sg:address":"Bahnhofsplatz 6",
    "sg:city":"Werdohl",
    "sg:phone":"+49 2392/4793",
    "sg:postcode":"58791",
    "sg:province":"Nordrhein-Westfalen",
    "wof:name":"Bremmest\u00fcbchen",
    "wof:placetype":"venue"
},
  "geometry": {"coordinates":[7.7589612007,51.2592010498],"type":"Point"}
}