{
  "type": "Feature",
  "properties": {
    "iso:country":"DE",
    "sg:address":"Tillmann-Stolz-Str. 11",
    "sg:city":"Siegen",
    "sg:phone":"+49 271/334605",
    "sg:postcode":"57074",
    "sg:province":"Nordrhein-Westfalen",
    "wof:name":"Werner Gerhards Elektroinstallations- Und",
    "wof:placetype":"venue"
},
  "geometry": {"coordinates":[8.0182743073,50.8659667969],"type":"Point"}
}