{
  "type": "Feature",
  "properties": {
    "iso:country":"DE",
    "sg:address":"Brexbachstr. 2a",
    "sg:city":"H\u00f6hr-Grenzhausen",
    "sg:phone":"+49 2624/4024",
    "sg:postcode":"56203",
    "sg:province":"Rheinland-Pfalz",
    "wof:name":"Mineral\u00f6lvertrieb Rhenania Gmbh",
    "wof:placetype":"venue"
},
  "geometry": {"coordinates":[7.6586351395,50.4512519836],"type":"Point"}
}