{
  "type": "Feature",
  "properties": {
    "iso:country":"DE",
    "sg:address":"Quellenweg 2",
    "sg:city":"Bonn",
    "sg:phone":"+49 228/284085",
    "sg:postcode":"53127",
    "sg:province":"Nordrhein-Westfalen",
    "wof:name":"H. Ulte Verm\u00f6gensverwaltung",
    "wof:placetype":"venue"
},
  "geometry": {"coordinates":[7.0901961327,50.6949386597],"type":"Point"}
}