{
  "type": "Feature",
  "properties": {
    "iso:country":"DE",
    "sg:address":"St.-Barbara-Str. 3",
    "sg:city":"Friedrichsthal",
    "sg:phone":"+49 6897/8570",
    "sg:postcode":"66299",
    "sg:province":"Saarland",
    "wof:name":"Walter Becker Elektronik Transport- Und",
    "wof:placetype":"venue"
},
  "geometry": {"coordinates":[7.07145,49.327534],"type":"Point"}
}