{
  "type": "Feature",
  "properties": {
    "iso:country":"DE",
    "sg:address":"Elisenstr. 21",
    "sg:city":"K\u00f6ln",
    "sg:phone":"+49 221/2575351",
    "sg:postcode":"50667",
    "sg:province":"Nordrhein-Westfalen",
    "wof:name":"Karl-josef Und Markus Ernst Architekten",
    "wof:placetype":"venue"
},
  "geometry": {"coordinates":[6.948331,50.940521],"type":"Point"}
}