{
  "type": "Feature",
  "properties": {
    "iso:country":"DE",
    "sg:address":"Steinweg 21/10",
    "sg:city":"M\u00f6rfelden-Walldorf",
    "sg:phone":"+49 6105/22285",
    "sg:postcode":"64546",
    "sg:province":"Hessen",
    "wof:name":"Heinrich Berz",
    "wof:placetype":"venue"
},
  "geometry": {"coordinates":[8.56507,49.975574],"type":"Point"}
}