{
  "type": "Feature",
  "properties": {
    "iso:country":"DE",
    "sg:address":"Halle-Kasseler-Str. 121 a",
    "sg:city":"Sollstedt",
    "sg:phone":"+49 36338/60004",
    "sg:postcode":"99759",
    "sg:province":"Th\u00fcringen",
    "wof:name":"Sollstedter Wohnungsbaugesellschaft Mbh",
    "wof:placetype":"venue"
},
  "geometry": {"coordinates":[10.524364,51.412735],"type":"Point"}
}