{
  "type": "Feature",
  "properties": {
    "iso:country":"DE",
    "sg:address":"Ismaninger Str. 7",
    "sg:city":"Aschheim",
    "sg:phone":"+49 89/9919090",
    "sg:postcode":"85609",
    "sg:province":"Bayern",
    "wof:name":"Abs-pumpen Ag",
    "wof:placetype":"venue"
},
  "geometry": {"coordinates":[11.715413,48.173115],"type":"Point"}
}