{
  "type": "Feature",
  "properties": {
    "iso:country":"DE",
    "sg:address":"An den G\u00fctern 11",
    "sg:city":"Mittelbach",
    "sg:phone":"+49 371/854366",
    "sg:postcode":"09224",
    "sg:province":"Sachsen",
    "wof:name":"Mittelbacher Bauernstube",
    "wof:placetype":"venue"
},
  "geometry": {"coordinates":[12.7898797989,50.7968788147],"type":"Point"}
}