{
  "type": "Feature",
  "properties": {
    "iso:country":"DE",
    "sg:address":"Rathausstr. 13",
    "sg:city":"Hamburg",
    "sg:phone":"+49 40/339700",
    "sg:postcode":"20095",
    "sg:province":"Hamburg",
    "wof:name":"Wohnungsbau- Und Kommissions-reichenstra\u00dfe",
    "wof:placetype":"venue"
},
  "geometry": {"coordinates":[9.9957847595,53.5501098633],"type":"Point"}
}