{
  "type": "Feature",
  "properties": {
    "iso:country":"DE",
    "sg:address":"Auelshag 3",
    "sg:city":"Schleiden",
    "sg:phone":"+49 2445/911102",
    "sg:postcode":"53937",
    "sg:province":"Nordrhein-Westfalen",
    "wof:name":"Anita Strawe",
    "wof:placetype":"venue"
},
  "geometry": {"coordinates":[6.4702558517,50.5227851868],"type":"Point"}
}