{
  "type": "Feature",
  "properties": {
    "iso:country":"DE",
    "sg:address":"Bischof-Blum-Str. 40",
    "sg:city":"Dernbach",
    "sg:phone":"+49 2602/7332",
    "sg:postcode":"56428",
    "sg:province":"Rheinland-Pfalz",
    "wof:name":"Josef Dillmann",
    "wof:placetype":"venue"
},
  "geometry": {"coordinates":[7.7848448753,50.4576187134],"type":"Point"}
}