{
  "type": "Feature",
  "properties": {
    "iso:country":"DE",
    "sg:address":"Siebachstr. 57",
    "sg:city":"K\u00f6ln",
    "sg:phone":"+49 221/734640",
    "sg:postcode":"50733",
    "sg:province":"Nordrhein-Westfalen",
    "wof:name":"Nippeser Radlager",
    "wof:placetype":"venue"
},
  "geometry": {"coordinates":[6.949666,50.960499],"type":"Point"}
}