{
  "type": "Feature",
  "properties": {
    "iso:country":"DE",
    "sg:address":"Alleestr 31",
    "sg:city":"Ahlen",
    "sg:phone":"+49 5691/3081",
    "sg:postcode":"59229",
    "sg:province":"Nordrhein-Westfalen",
    "wof:name":"Fahrzeugbau Friedrich Schmidt",
    "wof:placetype":"venue"
},
  "geometry": {"coordinates":[9.01308,51.380585],"type":"Point"}
}