{
  "type": "Feature",
  "properties": {
    "iso:country":"DE",
    "sg:address":"Am Pfaffenrain",
    "sg:city":"Schmalkalden",
    "sg:postcode":"98574",
    "sg:province":"Th\u00fcringen",
    "wof:name":"Bau-maschinen Service",
    "wof:placetype":"venue"
},
  "geometry": {"coordinates":[10.453624,50.720581],"type":"Point"}
}