{
  "type": "Feature",
  "properties": {
    "iso:country":"DE",
    "sg:address":"Bahnhofstr. 6",
    "sg:city":"Eichst\u00e4tt",
    "sg:phone":"+49 8421/4487",
    "sg:postcode":"85072",
    "sg:province":"Bayern",
    "wof:name":"Deutsche Bahn Ag",
    "wof:placetype":"venue"
},
  "geometry": {"coordinates":[11.1642112732,48.8699302673],"type":"Point"}
}