{
  "type": "Feature",
  "properties": {
    "iso:country":"DE",
    "sg:address":"R\u00f6thstr. 8",
    "sg:city":"Hessisch Oldendorf",
    "sg:phone":"+49 5152/3160",
    "sg:postcode":"31840",
    "sg:province":"Niedersachsen",
    "wof:name":"Friedrich Schaper",
    "wof:placetype":"venue"
},
  "geometry": {"coordinates":[9.19258,52.158089],"type":"Point"}
}