{
  "type": "Feature",
  "properties": {
    "iso:country":"DE",
    "sg:address":"Reichenberger Str. 29",
    "sg:city":"Berlin",
    "sg:postcode":"10999",
    "sg:province":"Berlin",
    "wof:name":"A & K Tradition Bauvermittlungs- Und",
    "wof:placetype":"venue"
},
  "geometry": {"coordinates":[13.42218,52.497772],"type":"Point"}
}