{
  "type": "Feature",
  "properties": {
    "iso:country":"DE",
    "sg:city":"Aidlingen",
    "sg:phone":"+49 171 3702392",
    "sg:postcode":"71134",
    "sg:province":"Baden-W\u00fcrttemberg",
    "wof:name":"1a 1ste Kostenlose Sexcam Mit Live Chat Der Spitzenklasse -",
    "wof:placetype":"venue"
},
  "geometry": {"coordinates":[8.898411,48.678917],"type":"Point"}
}