{
  "type": "Feature",
  "properties": {
    "iso:country":"DE",
    "sg:address":"Johann-Sebastian-Bach-Str. 3",
    "sg:city":"Forchheim",
    "sg:phone":"+49 9191/65542",
    "sg:postcode":"91301",
    "sg:province":"Bayern",
    "wof:name":"B\u00e4rbel Bachg",
    "wof:placetype":"venue"
},
  "geometry": {"coordinates":[11.074213,49.722527],"type":"Point"}
}