{
  "type": "Feature",
  "properties": {
    "iso:country":"DE",
    "sg:address":"Bertelestr. 32",
    "sg:city":"M\u00fcnchen",
    "sg:phone":"+49 89/795114",
    "sg:postcode":"81479",
    "sg:province":"Bayern",
    "wof:name":"Magarete Kolb",
    "wof:placetype":"venue"
},
  "geometry": {"coordinates":[11.51948,48.073898],"type":"Point"}
}