{
  "type": "Feature",
  "properties": {
    "iso:country":"DE",
    "sg:address":"Gro\u00dfe Str. 64",
    "sg:city":"Damme",
    "sg:phone":"+49 5491/5172",
    "sg:postcode":"49401",
    "sg:province":"Niedersachsen",
    "wof:name":"Billard-bistro-cafe",
    "wof:placetype":"venue"
},
  "geometry": {"coordinates":[8.194011,52.519093],"type":"Point"}
}