{
  "type": "Feature",
  "properties": {
    "iso:country":"DE",
    "sg:address":"Flensburger Str. 15 a",
    "sg:city":"Pinneberg",
    "sg:phone":"+49 4101/75252",
    "sg:postcode":"25421",
    "sg:province":"Schleswig-Holstein",
    "wof:name":"Druckhaus Fenske Klaus Fenske",
    "wof:placetype":"venue"
},
  "geometry": {"coordinates":[9.798557,53.675903],"type":"Point"}
}