{
  "type": "Feature",
  "properties": {
    "iso:country":"DE",
    "sg:address":"Carl-Benz-Str. 4",
    "sg:city":"Sinsheim",
    "sg:phone":"+49 4972/619526",
    "sg:postcode":"74889",
    "sg:province":"Baden-W\u00fcrttemberg",
    "wof:name":"Hein Industrieschilder Gmbh",
    "wof:placetype":"venue"
},
  "geometry": {"coordinates":[8.8735704422,49.253868103],"type":"Point"}
}