{
  "type": "Feature",
  "properties": {
    "iso:country":"DE",
    "sg:address":"Rathausstr. 8",
    "sg:city":"Sch\u00f6nenberg-K\u00fcbelberg",
    "sg:phone":"+49 6373/5040",
    "sg:postcode":"66901",
    "sg:province":"Rheinland-Pfalz",
    "wof:name":"Verbandsgemeindeverwaltung Gemeindeb\u00fccherei",
    "wof:placetype":"venue"
},
  "geometry": {"coordinates":[7.377893,49.408951],"type":"Point"}
}