{
  "type": "Feature",
  "properties": {
    "iso:country":"DE",
    "sg:address":"Alzenauer Str. 11",
    "sg:city":"Karlstein",
    "sg:phone":"+49 6188/5673",
    "sg:postcode":"63791",
    "sg:province":"Bayern",
    "wof:name":"R. Surmann",
    "wof:placetype":"venue"
},
  "geometry": {"coordinates":[9.019923,50.049046],"type":"Point"}
}