{
  "type": "Feature",
  "properties": {
    "iso:country":"DE",
    "sg:address":"Laichinger Str. 10",
    "sg:city":"Stuttgart",
    "sg:phone":"+49 711/422102",
    "sg:postcode":"70327",
    "sg:province":"Baden-W\u00fcrttemberg",
    "wof:name":"Erika Lindner",
    "wof:placetype":"venue"
},
  "geometry": {"coordinates":[9.242173,48.775391],"type":"Point"}
}