{
  "type": "Feature",
  "properties": {
    "iso:country":"DE",
    "sg:address":"Dorfstr. 6",
    "sg:city":"Gro\u00df Santersleben",
    "sg:postcode":"39343",
    "sg:province":"Sachsen-Anhalt",
    "wof:name":"Rostar Managementberatung Gmbh",
    "wof:placetype":"venue"
},
  "geometry": {"coordinates":[11.4571943283,52.1914100647],"type":"Point"}
}