{
  "type": "Feature",
  "properties": {
    "iso:country":"DE",
    "sg:address":"Ernst-Barlach-Str. 17",
    "sg:city":"Horst",
    "sg:phone":"+49 4126/2173",
    "sg:postcode":"25358",
    "sg:province":"Schleswig-Holstein",
    "wof:name":"Hans J\u00fcrgen Holst",
    "wof:placetype":"venue"
},
  "geometry": {"coordinates":[9.6177654266,53.8437194824],"type":"Point"}
}