{
  "type": "Feature",
  "properties": {
    "iso:country":"DE",
    "sg:address":"Hanauer Landstr. 421",
    "sg:city":"Frankfurt",
    "sg:phone":"+49 69/9421300",
    "sg:postcode":"60314",
    "sg:province":"Hessen",
    "wof:name":"Mvg Metallverkaufs- Beteiligungs Gmbh",
    "wof:placetype":"venue"
},
  "geometry": {"coordinates":[8.736635,50.121216],"type":"Point"}
}