{
  "type": "Feature",
  "properties": {
    "iso:country":"DE",
    "sg:address":"Volkshausstr. 22",
    "sg:city":"Frankfurt",
    "sg:phone":"+49 6109/31553",
    "sg:postcode":"60388",
    "sg:province":"Hessen",
    "wof:name":"H.-p. Loos",
    "wof:placetype":"venue"
},
  "geometry": {"coordinates":[8.752372,50.143391],"type":"Point"}
}