{
  "type": "Feature",
  "properties": {
    "iso:country":"DE",
    "sg:address":"Jugendherberge 30",
    "sg:city":"Lindlar",
    "sg:postcode":"51789",
    "sg:province":"Nordrhein-Westfalen",
    "wof:name":"Deutsches Jugendherbergswerk Kreisverband Oberberg",
    "wof:placetype":"venue"
},
  "geometry": {"coordinates":[7.3806738853,51.0162124634],"type":"Point"}
}