{
  "type": "Feature",
  "properties": {
    "iso:country":"DE",
    "sg:address":"Birkenweg 1",
    "sg:city":"Weilrod",
    "sg:phone":"+49 6083/788",
    "sg:postcode":"61276",
    "sg:province":"Hessen",
    "wof:name":"Weiltal-apotheke",
    "wof:placetype":"venue"
},
  "geometry": {"coordinates":[8.380711,50.337322],"type":"Point"}
}