{
  "type": "Feature",
  "properties": {
    "iso:country":"DE",
    "sg:address":"Haubachstr. 37",
    "sg:city":"Berlin",
    "sg:phone":"+49 30/3418471",
    "sg:postcode":"10585",
    "sg:province":"Berlin",
    "wof:name":"Christoph Regierer Rechtsanwalt",
    "wof:placetype":"venue"
},
  "geometry": {"coordinates":[13.3012933731,52.5152931213],"type":"Point"}
}