{
  "type": "Feature",
  "properties": {
    "iso:country":"DE",
    "sg:address":"Hubert-Prott-Str 162",
    "sg:city":"Frechen",
    "sg:phone":"+49 2234/600170",
    "sg:postcode":"50226",
    "sg:province":"Nordrhein-Westfalen",
    "wof:name":"Kreissparkasse K\u00f6ln",
    "wof:placetype":"venue"
},
  "geometry": {"coordinates":[6.816558,50.899899],"type":"Point"}
}