{
  "type": "Feature",
  "properties": {
    "iso:country":"DE",
    "sg:address":"Hauptstr. 3",
    "sg:city":"Raitenbuch",
    "sg:phone":"+49 9147/375",
    "sg:postcode":"91790",
    "sg:province":"Bayern",
    "wof:name":"Josef Hei\u00df",
    "wof:placetype":"venue"
},
  "geometry": {"coordinates":[11.120561,49.01577],"type":"Point"}
}