{
  "type": "Feature",
  "properties": {
    "iso:country":"DE",
    "sg:address":"Holzhof 10",
    "sg:city":"Pritzwalk",
    "sg:phone":"+49 3395/310213",
    "sg:postcode":"16928",
    "sg:province":"Brandenburg",
    "wof:name":"H. Lehmann",
    "wof:placetype":"venue"
},
  "geometry": {"coordinates":[12.1718492508,53.1549072266],"type":"Point"}
}