{
  "type": "Feature",
  "properties": {
    "iso:country":"DE",
    "sg:address":"Drochterser Str. 22",
    "sg:city":"Drochtersen",
    "sg:phone":"+49 4143/232",
    "sg:postcode":"21706",
    "sg:province":"Niedersachsen",
    "wof:name":"Ek-kr\u00f6hnke Gmbh",
    "wof:placetype":"venue"
},
  "geometry": {"coordinates":[9.3860292435,53.7089385986],"type":"Point"}
}