{
  "type": "Feature",
  "properties": {
    "iso:country":"DE",
    "sg:address":"Dorfaue 20",
    "sg:city":"Telz",
    "sg:phone":"+49 3377/301568",
    "sg:postcode":"15806",
    "sg:province":"Brandenburg",
    "wof:name":"V. Sieke",
    "wof:placetype":"venue"
},
  "geometry": {"coordinates":[13.4909906387,52.2458763123],"type":"Point"}
}