{
  "type": "Feature",
  "properties": {
    "iso:country":"DE",
    "sg:address":"Moltkestr. 45",
    "sg:city":"Gummersbach",
    "sg:phone":"+49 2261/27740",
    "sg:postcode":"51643",
    "sg:province":"Nordrhein-Westfalen",
    "wof:name":"St\u00e4dt. Badeanstalt",
    "wof:placetype":"venue"
},
  "geometry": {"coordinates":[7.5698580742,51.0302734375],"type":"Point"}
}