{
  "type": "Feature",
  "properties": {
    "iso:country":"DE",
    "sg:address":"B\u00fcrgerm.-Reiger-Str. 18",
    "sg:city":"N\u00f6rdlingen",
    "sg:phone":"+49 9081/6031",
    "sg:postcode":"86720",
    "sg:province":"Bayern",
    "wof:name":"Holgard Holz Im Garten Deutschland Gmbh",
    "wof:placetype":"venue"
},
  "geometry": {"coordinates":[10.496575,48.84996],"type":"Point"}
}