{
  "type": "Feature",
  "properties": {
    "iso:country":"DE",
    "sg:address":"Pirmasenser Str. 7",
    "sg:city":"Kaiserslautern",
    "sg:phone":"+49 631/362640",
    "sg:postcode":"67655",
    "sg:province":"Rheinland-Pfalz",
    "wof:name":"Winterthur Versicherung",
    "wof:placetype":"venue"
},
  "geometry": {"coordinates":[7.7674489021,49.4416389465],"type":"Point"}
}