{
  "type": "Feature",
  "properties": {
    "iso:country":"DE",
    "sg:address":"P\u00f6litzstr. 12",
    "sg:city":"Leipzig",
    "sg:phone":"+49 341/5852157",
    "sg:postcode":"04155",
    "sg:province":"Sachsen",
    "wof:name":"Thomas G\u00fcnther",
    "wof:placetype":"venue"
},
  "geometry": {"coordinates":[12.3584003448,51.3601074219],"type":"Point"}
}