{
  "type": "Feature",
  "properties": {
    "iso:country":"DE",
    "sg:address":"Bahnhofstr. 5",
    "sg:city":"Bayreuth",
    "sg:phone":"+49 921/20203",
    "sg:postcode":"95444",
    "sg:province":"Bayern",
    "wof:name":"Haus Weihenstephan Schwarz Kg",
    "wof:placetype":"venue"
},
  "geometry": {"coordinates":[11.5779876709,49.9481277466],"type":"Point"}
}