{
  "type": "Feature",
  "properties": {
    "iso:country":"DE",
    "sg:address":"Rehnaer Str. 20 a",
    "sg:city":"Grevesm\u00fchlen",
    "sg:phone":"+49 3881/712856",
    "sg:postcode":"23936",
    "sg:province":"Mecklenburg-Vorpommern",
    "wof:name":"Hans-peter Wehr",
    "wof:placetype":"venue"
},
  "geometry": {"coordinates":[11.182306,53.854351],"type":"Point"}
}