{
  "type": "Feature",
  "properties": {
    "iso:country":"DE",
    "sg:address":"Solinger Str. 42",
    "sg:city":"Langenfeld",
    "sg:phone":"+49 2173/82667",
    "sg:postcode":"40764",
    "sg:province":"Nordrhein-Westfalen",
    "wof:name":"W. Haftke",
    "wof:placetype":"venue"
},
  "geometry": {"coordinates":[6.9513049126,51.1115989685],"type":"Point"}
}