{
  "type": "Feature",
  "properties": {
    "iso:country":"DE",
    "sg:address":"Hauptstr. 29",
    "sg:city":"Pressig",
    "sg:phone":"+49 9265/9580",
    "sg:postcode":"96332",
    "sg:province":"Bayern",
    "wof:name":"Markt-apotheke Heike Kohlmann",
    "wof:placetype":"venue"
},
  "geometry": {"coordinates":[11.3118,50.347527],"type":"Point"}
}