{
  "type": "Feature",
  "properties": {
    "iso:country":"DE",
    "sg:address":"Zollbrunn 10",
    "sg:city":"Kronach",
    "sg:phone":"+49 9261/51311",
    "sg:postcode":"96317",
    "sg:province":"Bayern",
    "wof:name":"Taxi Claudia Blinzler E. Kfr.",
    "wof:placetype":"venue"
},
  "geometry": {"coordinates":[11.2828502655,50.2363090515],"type":"Point"}
}