{
  "type": "Feature",
  "properties": {
    "iso:country":"DE",
    "sg:address":"Balduinstr. 75",
    "sg:city":"Zell",
    "sg:phone":"+49 6542/960106",
    "sg:postcode":"56856",
    "sg:province":"Rheinland-Pfalz",
    "wof:name":"Friedrich Pargen",
    "wof:placetype":"venue"
},
  "geometry": {"coordinates":[7.1815671921,50.0263328552],"type":"Point"}
}