{
  "type": "Feature",
  "properties": {
    "iso:country":"DE",
    "sg:address":"Pattenser Hauptstr. 4a",
    "sg:city":"Winsen",
    "sg:phone":"+49 4173/7754",
    "sg:postcode":"21423",
    "sg:province":"Niedersachsen",
    "wof:name":"Mtv Pattensen 1909 E. V. Peter Dederke",
    "wof:placetype":"venue"
},
  "geometry": {"coordinates":[10.1492185593,53.3181037903],"type":"Point"}
}