{
  "type": "Feature",
  "properties": {
    "iso:country":"DE",
    "sg:address":"Lindenstr. 4",
    "sg:city":"P\u00e4tz",
    "sg:phone":"+49 33763/63360",
    "sg:postcode":"15741",
    "sg:province":"Brandenburg",
    "wof:name":"P\u00e4tz",
    "wof:placetype":"venue"
},
  "geometry": {"coordinates":[13.657617569,52.2265357971],"type":"Point"}
}