{
  "type": "Feature",
  "properties": {
    "iso:country":"DE",
    "sg:address":"Herrenwiese",
    "sg:city":"Eckenroth",
    "sg:phone":"+49 6724/3670",
    "sg:postcode":"55444",
    "sg:province":"Rheinland-Pfalz",
    "wof:name":"Hubert Baumg\u00e4rtner",
    "wof:placetype":"venue"
},
  "geometry": {"coordinates":[7.830825,49.928467],"type":"Point"}
}