{
  "type": "Feature",
  "properties": {
    "iso:country":"DE",
    "sg:address":"Adrian-Stoop-Str.",
    "sg:city":"Bad Wiessee",
    "sg:phone":"+49 8022/8978",
    "sg:postcode":"83707",
    "sg:province":"Bayern",
    "wof:name":"Tegernseer Segler Shop L. & S. Hornsteiner",
    "wof:placetype":"venue"
},
  "geometry": {"coordinates":[11.724715,47.718414],"type":"Point"}
}