{
  "type": "Feature",
  "properties": {
    "iso:country":"DE",
    "sg:address":"Hauptstr. 12",
    "sg:city":"Dietmannsried",
    "sg:phone":"+49 8374/5775",
    "sg:postcode":"87463",
    "sg:province":"Bayern",
    "wof:name":"Gastst\u00e4tte Max Becherer",
    "wof:placetype":"venue"
},
  "geometry": {"coordinates":[10.3313980103,47.8181533813],"type":"Point"}
}