{
  "type": "Feature",
  "properties": {
    "iso:country":"DE",
    "sg:address":"Knappenstr. 1",
    "sg:city":"Untergriesbach",
    "sg:phone":"+49 8593/8503",
    "sg:postcode":"94107",
    "sg:province":"Bayern",
    "wof:name":"Edeka Markt Ludwig Und Karin Wimmer",
    "wof:placetype":"venue"
},
  "geometry": {"coordinates":[13.6496572495,48.599609375],"type":"Point"}
}