{
  "type": "Feature",
  "properties": {
    "iso:country":"DE",
    "sg:address":"Noorderloog 13",
    "sg:city":"Spiekeroog",
    "sg:phone":"+49 4976/912010",
    "sg:postcode":"26474",
    "sg:province":"Niedersachsen",
    "wof:name":"Spiekeroog Info",
    "wof:placetype":"venue"
},
  "geometry": {"coordinates":[7.6964521408,53.7709388733],"type":"Point"}
}