{
  "type": "Feature",
  "properties": {
    "iso:country":"DE",
    "sg:address":"Nordb\u00f6gger Str. 42",
    "sg:city":"B\u00f6nen",
    "sg:phone":"+49 2383/4587",
    "sg:postcode":"59199",
    "sg:province":"Nordrhein-Westfalen",
    "wof:name":"Ralf Meier",
    "wof:placetype":"venue"
},
  "geometry": {"coordinates":[7.7596340179,51.6074485779],"type":"Point"}
}