{
  "type": "Feature",
  "properties": {
    "iso:country":"DE",
    "sg:address":"Dorfstr. 19",
    "sg:city":"W\u00fcrselen",
    "sg:phone":"+49 2405/85085",
    "sg:postcode":"52146",
    "sg:province":"Nordrhein-Westfalen",
    "wof:name":"Emunds",
    "wof:placetype":"venue"
},
  "geometry": {"coordinates":[6.1120910645,50.8422927856],"type":"Point"}
}