{
  "type": "Feature",
  "properties": {
    "iso:country":"DE",
    "sg:address":"\u00dcberlinger Str. 52",
    "sg:city":"Pfullendorf",
    "sg:phone":"+49 7552/97034",
    "sg:postcode":"88630",
    "sg:province":"Baden-W\u00fcrttemberg",
    "wof:name":"Imbi\u00df Pausen-eck",
    "wof:placetype":"venue"
},
  "geometry": {"coordinates":[9.2438640594,47.9279212952],"type":"Point"}
}