{
  "type": "Feature",
  "properties": {
    "iso:country":"DE",
    "sg:address":"Tiroler Str. 7",
    "sg:city":"Augsburg",
    "sg:phone":"+49 821/342048",
    "sg:postcode":"86179",
    "sg:province":"Bayern",
    "wof:name":"Katholisches Pfarramt St. Albert",
    "wof:placetype":"venue"
},
  "geometry": {"coordinates":[10.9068126678,48.3207359314],"type":"Point"}
}