{
  "type": "Feature",
  "properties": {
    "iso:country":"DE",
    "sg:address":"Karlstr. 15-19",
    "sg:city":"Zweibr\u00fccken",
    "sg:phone":"+49 6332/91070",
    "sg:postcode":"66482",
    "sg:province":"Rheinland-Pfalz",
    "wof:name":"S & H Sanit\u00e4r Und Heizungs- Fachhandel Gmbh",
    "wof:placetype":"venue"
},
  "geometry": {"coordinates":[7.3613700867,49.2484321594],"type":"Point"}
}