{
  "type": "Feature",
  "properties": {
    "iso:country":"DE",
    "sg:address":"Im H\u00e4usleinsb\u00fchl 9",
    "sg:city":"Satteldorf",
    "sg:phone":"+49 7951/5844",
    "sg:postcode":"74589",
    "sg:province":"Baden-W\u00fcrttemberg",
    "wof:name":"G\u00e4stehaus Edith Krau\u00df",
    "wof:placetype":"venue"
},
  "geometry": {"coordinates":[10.0866956711,49.1713256836],"type":"Point"}
}