{
  "type": "Feature",
  "properties": {
    "iso:country":"DE",
    "sg:address":"Bruderhofstr. 66",
    "sg:city":"Singen",
    "sg:postcode":"78224",
    "sg:province":"Baden-W\u00fcrttemberg",
    "wof:name":"T. Salmhofer",
    "wof:placetype":"venue"
},
  "geometry": {"coordinates":[8.843634,47.775085],"type":"Point"}
}