{
  "type": "Feature",
  "properties": {
    "iso:country":"DE",
    "sg:address":"Breslauer Str. 51 b",
    "sg:city":"Leipzig",
    "sg:phone":"+49 341/8781018",
    "sg:postcode":"04299",
    "sg:province":"Sachsen",
    "wof:name":"Prof. Dr. Annemarie Langanke Rechtsanw\u00e4ltin",
    "wof:placetype":"venue"
},
  "geometry": {"coordinates":[12.4155874252,51.3175125122],"type":"Point"}
}