{
  "type": "Feature",
  "properties": {
    "iso:country":"DE",
    "sg:address":"Madamenweg 9",
    "sg:city":"Braunschweig",
    "sg:phone":"+49 531/281060",
    "sg:postcode":"38118",
    "sg:province":"Niedersachsen",
    "wof:name":"Johanniterhaus Braunschweig St. Annen-konvent In",
    "wof:placetype":"venue"
},
  "geometry": {"coordinates":[10.505771,52.260925],"type":"Point"}
}