{
  "type": "Feature",
  "properties": {
    "iso:country":"DE",
    "sg:address":"H\u00f6lle 1",
    "sg:city":"Haverlah",
    "sg:phone":"+49 5341/33946",
    "sg:postcode":"38275",
    "sg:province":"Niedersachsen",
    "wof:name":"Hermann Wolf",
    "wof:placetype":"venue"
},
  "geometry": {"coordinates":[10.325878,52.054058],"type":"Point"}
}