{
  "type": "Feature",
  "properties": {
    "iso:country":"DE",
    "sg:address":"Gneisstr. 8",
    "sg:city":"Neubrandenburg",
    "sg:phone":"+49 395/769580",
    "sg:postcode":"17036",
    "sg:province":"Mecklenburg-Vorpommern",
    "wof:name":"Elektro-vertrieb Nord Gmbh",
    "wof:placetype":"venue"
},
  "geometry": {"coordinates":[13.3156328201,53.546131134],"type":"Point"}
}