{
  "type": "Feature",
  "properties": {
    "iso:country":"DE",
    "sg:address":"H\u00f6rvelsinger Weg 15",
    "sg:city":"Ulm",
    "sg:phone":"+49 731/14190",
    "sg:postcode":"89081",
    "sg:province":"Baden-W\u00fcrttemberg",
    "wof:name":"Klopfer & Wannenwetsch Gmbh & Co. Kg",
    "wof:placetype":"venue"
},
  "geometry": {"coordinates":[9.9880914688,48.4252471924],"type":"Point"}
}