{
  "type": "Feature",
  "properties": {
    "iso:country":"DE",
    "sg:address":"Braker Mitte 13",
    "sg:city":"Lemgo",
    "sg:phone":"+49 5261/89560",
    "sg:postcode":"32657",
    "sg:province":"Nordrhein-Westfalen",
    "wof:name":"Pl\u00f6gers Basteltreff",
    "wof:placetype":"venue"
},
  "geometry": {"coordinates":[8.9207420349,52.0165863037],"type":"Point"}
}