{
  "type": "Feature",
  "properties": {
    "iso:country":"DE",
    "sg:address":"Br\u00fcckes 56",
    "sg:city":"Bad Kreuznach",
    "sg:phone":"+49 671/4821280",
    "sg:postcode":"55545",
    "sg:province":"Rheinland-Pfalz",
    "wof:name":"Reifen- Und Autoservice W. Schmidt Gmbh",
    "wof:placetype":"venue"
},
  "geometry": {"coordinates":[7.8650698662,49.8715438843],"type":"Point"}
}