{
  "type": "Feature",
  "properties": {
    "iso:country":"DE",
    "sg:address":"Dorfstr. 15",
    "sg:city":"Sasbach",
    "sg:phone":"+49 7662/6114",
    "sg:postcode":"79361",
    "sg:province":"Baden-W\u00fcrttemberg",
    "wof:name":"F. Ehrlacher",
    "wof:placetype":"venue"
},
  "geometry": {"coordinates":[7.60796,48.118809],"type":"Point"}
}