{
  "type": "Feature",
  "properties": {
    "iso:country":"DE",
    "sg:address":"Wittelsbacherring 23",
    "sg:city":"Bonn",
    "sg:phone":"+49 228/633367",
    "sg:postcode":"53115",
    "sg:province":"Nordrhein-Westfalen",
    "wof:name":"W. Sch\u00e4fer",
    "wof:placetype":"venue"
},
  "geometry": {"coordinates":[7.0867781639,50.7335510254],"type":"Point"}
}