{
  "type": "Feature",
  "properties": {
    "iso:country":"DE",
    "sg:address":"S\u00fcdstr. 5",
    "sg:city":"Siegburg",
    "sg:phone":"+49 2241/57837",
    "sg:postcode":"53721",
    "sg:province":"Nordrhein-Westfalen",
    "wof:name":"Rs Immobilien",
    "wof:placetype":"venue"
},
  "geometry": {"coordinates":[7.2096319199,50.7916107178],"type":"Point"}
}