{
  "type": "Feature",
  "properties": {
    "iso:country":"DE",
    "sg:address":"Gewerbering 1",
    "sg:city":"Unterdie\u00dfen",
    "sg:postcode":"86944",
    "sg:province":"Bayern",
    "wof:name":"Mba Maschinen\u00fcberholung Gmbh",
    "wof:placetype":"venue"
},
  "geometry": {"coordinates":[10.848734,47.981167],"type":"Point"}
}