{
  "type": "Feature",
  "properties": {
    "iso:country":"DE",
    "sg:address":"Hauptstr. 34",
    "sg:city":"Dernbach",
    "sg:phone":"+49 2602/7588",
    "sg:postcode":"56428",
    "sg:province":"Rheinland-Pfalz",
    "wof:name":"Kath. B\u00fccherei Dernbach",
    "wof:placetype":"venue"
},
  "geometry": {"coordinates":[7.599635,50.545979],"type":"Point"}
}