{
  "type": "Feature",
  "properties": {
    "iso:country":"DE",
    "sg:address":"Kirchstr. 4",
    "sg:city":"Altensteig",
    "sg:phone":"+49 7453/8577",
    "sg:postcode":"72213",
    "sg:province":"Baden-W\u00fcrttemberg",
    "wof:name":"Engel",
    "wof:placetype":"venue"
},
  "geometry": {"coordinates":[8.6032047272,48.5867385864],"type":"Point"}
}