{
  "type": "Feature",
  "properties": {
    "iso:country":"DE",
    "sg:address":"Waltersberg",
    "sg:city":"Spatzenhausen",
    "sg:phone":"+49 8847/255",
    "sg:postcode":"82447",
    "sg:province":"Bayern",
    "wof:name":"Gerhard Schulz",
    "wof:placetype":"venue"
},
  "geometry": {"coordinates":[11.194357,47.713577],"type":"Point"}
}