{
  "type": "Feature",
  "properties": {
    "iso:country":"DE",
    "sg:address":"Martin-Luther-Str. 51",
    "sg:city":"Remscheid",
    "sg:phone":"+49 2191/74582",
    "sg:postcode":"42853",
    "sg:province":"Nordrhein-Westfalen",
    "wof:name":"Walter Schmidt & Justus Schmidt Sohn Ohg",
    "wof:placetype":"venue"
},
  "geometry": {"coordinates":[7.1755509377,51.1832504272],"type":"Point"}
}