{
  "type": "Feature",
  "properties": {
    "iso:country":"DE",
    "sg:address":"B\u00fchlertalstr. 111",
    "sg:city":"B\u00fchl",
    "sg:phone":"+49 7223/22992",
    "sg:postcode":"77815",
    "sg:province":"Baden-W\u00fcrttemberg",
    "wof:name":"Bruno Meier",
    "wof:placetype":"venue"
},
  "geometry": {"coordinates":[8.1454973221,48.694694519],"type":"Point"}
}