{
  "type": "Feature",
  "properties": {
    "iso:country":"DE",
    "sg:address":"L\u00f6hlitz 31 1/2",
    "sg:city":"Waischenfeld",
    "sg:phone":"+49 9204/1257",
    "sg:postcode":"91344",
    "sg:province":"Bayern",
    "wof:name":"Karl Poser",
    "wof:placetype":"venue"
},
  "geometry": {"coordinates":[11.3433933258,49.8474807739],"type":"Point"}
}