{
  "type": "Feature",
  "properties": {
    "iso:country":"DE",
    "sg:address":"Breitene 10",
    "sg:city":"Stockach",
    "sg:phone":"+49 7771/919365",
    "sg:postcode":"78333",
    "sg:province":"Baden-W\u00fcrttemberg",
    "wof:name":"Cygnus Giengener Immobilien Gmbh & Co. Kg",
    "wof:placetype":"venue"
},
  "geometry": {"coordinates":[9.0111551285,47.8225479126],"type":"Point"}
}