{
  "type": "Feature",
  "properties": {
    "iso:country":"DE",
    "sg:address":"Moselstr. 19",
    "sg:city":"Leverkusen",
    "sg:phone":"+49 214/8606091",
    "sg:postcode":"51371",
    "sg:province":"Nordrhein-Westfalen",
    "wof:name":"Novo Nordhoff Verwaltungs-organisation Gmbh",
    "wof:placetype":"venue"
},
  "geometry": {"coordinates":[6.9813728333,51.0442848206],"type":"Point"}
}