{
  "type": "Feature",
  "properties": {
    "iso:country":"DE",
    "sg:address":"Am Kurpark 9",
    "sg:city":"Bad Rothenfelde",
    "sg:phone":"+49 5424/4728",
    "sg:postcode":"49214",
    "sg:province":"Niedersachsen",
    "wof:name":"Johannes Dieninghoff Restaurator",
    "wof:placetype":"venue"
},
  "geometry": {"coordinates":[8.159526825,52.1096801758],"type":"Point"}
}