{
  "type": "Feature",
  "properties": {
    "iso:country":"DE",
    "sg:address":"L\u00fcneburger Str. 24",
    "sg:city":"Magdeburg",
    "sg:postcode":"39106",
    "sg:province":"Sachsen-Anhalt",
    "wof:name":"Rundum Soziales Dienstleistungszentrum Gmbh",
    "wof:placetype":"venue"
},
  "geometry": {"coordinates":[11.6394309998,52.1465988159],"type":"Point"}
}