{
  "type": "Feature",
  "properties": {
    "iso:country":"DE",
    "sg:address":"Auf den Pohl\u00e4ckern 9",
    "sg:city":"Lehrte",
    "sg:phone":"+49 5132/585858",
    "sg:postcode":"31275",
    "sg:province":"Niedersachsen",
    "wof:name":"Prosave Kommunikationstechnik M. Januschewitz",
    "wof:placetype":"venue"
},
  "geometry": {"coordinates":[9.9929409027,52.3665313721],"type":"Point"}
}