{
  "type": "Feature",
  "properties": {
    "iso:country":"DE",
    "sg:address":"K\u00f6lner Str. 113",
    "sg:city":"M\u00fclheim",
    "sg:phone":"+49 4920/8485011",
    "sg:postcode":"45481",
    "sg:province":"Nordrhein-Westfalen",
    "wof:name":"Industriereifenkontor L\u00dcdtke Gmbh",
    "wof:placetype":"venue"
},
  "geometry": {"coordinates":[6.8725738525,51.394241333],"type":"Point"}
}