{
  "type": "Feature",
  "properties": {
    "iso:country":"DE",
    "sg:address":"F\u00fcrstenaustr. 7",
    "sg:city":"Herford",
    "sg:phone":"+49 5221/57156",
    "sg:postcode":"32052",
    "sg:province":"Nordrhein-Westfalen",
    "wof:name":"Abc Automaten Spiel- Und Sportst\u00e4tten Gmbh",
    "wof:placetype":"venue"
},
  "geometry": {"coordinates":[8.6670217514,52.1194038391],"type":"Point"}
}