{
  "type": "Feature",
  "properties": {
    "iso:country":"DE",
    "sg:address":"Wachtstr. 5",
    "sg:city":"Bischoffen",
    "sg:phone":"+49 6444/92010",
    "sg:postcode":"35649",
    "sg:province":"Hessen",
    "wof:name":"Ptg Hans H. Gerbershagen",
    "wof:placetype":"venue"
},
  "geometry": {"coordinates":[8.453341,50.703926],"type":"Point"}
}