{
  "type": "Feature",
  "properties": {
    "iso:country":"DE",
    "sg:address":"Sch\u00fctzenstr. 1",
    "sg:city":"G\u00f6rlitz",
    "sg:postcode":"02826",
    "sg:province":"Sachsen",
    "wof:name":"Pr\u00e4zis Hochbau Gmbh",
    "wof:placetype":"venue"
},
  "geometry": {"coordinates":[14.988367,51.151276],"type":"Point"}
}