{
  "type": "Feature",
  "properties": {
    "iso:country":"DE",
    "sg:address":"Heckinghauser Str. 67",
    "sg:city":"Wuppertal",
    "sg:phone":"+49 202/625200",
    "sg:postcode":"42289",
    "sg:province":"Nordrhein-Westfalen",
    "wof:name":"Heinz Hast Rechtsanwalt",
    "wof:placetype":"venue"
},
  "geometry": {"coordinates":[7.2111530304,51.2715148926],"type":"Point"}
}