{
  "type": "Feature",
  "properties": {
    "iso:country":"DE",
    "sg:address":"M\u00fcnsterlandstr. 11",
    "sg:city":"Langenberg",
    "sg:phone":"+49 5248/609783",
    "sg:postcode":"33449",
    "sg:province":"Nordrhein-Westfalen",
    "wof:name":"Anton Holtk\u00f6tter",
    "wof:placetype":"venue"
},
  "geometry": {"coordinates":[8.327383,51.747639],"type":"Point"}
}