{
  "type": "Feature",
  "properties": {
    "iso:country":"DE",
    "sg:address":"Steinstr. 34",
    "sg:city":"D\u00fcsseldorf",
    "sg:phone":"+49 211/80038",
    "sg:postcode":"40210",
    "sg:province":"Nordrhein-Westfalen",
    "wof:name":"L\u00fcbecker Hypothekenbank Ag",
    "wof:placetype":"venue"
},
  "geometry": {"coordinates":[6.78634,51.223003],"type":"Point"}
}