{
  "type": "Feature",
  "properties": {
    "iso:country":"DE",
    "sg:address":"Am Tennisplatz 17",
    "sg:city":"Meckenheim",
    "sg:phone":"+49 2225/13708",
    "sg:postcode":"53340",
    "sg:province":"Nordrhein-Westfalen",
    "wof:name":"Dieter Walter Gmbh",
    "wof:placetype":"venue"
},
  "geometry": {"coordinates":[7.0477609634,50.6220054626],"type":"Point"}
}