{
  "type": "Feature",
  "properties": {
    "iso:country":"DE",
    "sg:address":"Wollmatinger Str. 70",
    "sg:city":"Konstanz",
    "sg:phone":"+49 7531",
    "sg:postcode":"78467",
    "sg:province":"Baden-W\u00fcrttemberg",
    "wof:name":"Konzepte, Design, Engineering, Entwicklung, Konstr",
    "wof:placetype":"venue"
},
  "geometry": {"coordinates":[9.171434,47.678944],"type":"Point"}
}