{
  "type": "Feature",
  "properties": {
    "iso:country":"DE",
    "sg:address":"Raistinger Str. 53",
    "sg:city":"Herrenberg",
    "sg:phone":"+49 7032/977954",
    "sg:postcode":"71083",
    "sg:province":"Baden-W\u00fcrttemberg",
    "wof:name":"Temption Gmbh",
    "wof:placetype":"venue"
},
  "geometry": {"coordinates":[8.8542118073,48.5894966125],"type":"Point"}
}