{
  "type": "Feature",
  "properties": {
    "iso:country":"DE",
    "sg:address":"Ehrengutstr. 8",
    "sg:city":"M\u00fcnchen",
    "sg:phone":"+49 89/7461570",
    "sg:postcode":"80469",
    "sg:province":"Bayern",
    "wof:name":"Ralf Stark Gmbh & Co. Hausverwaltung Kg",
    "wof:placetype":"venue"
},
  "geometry": {"coordinates":[11.5591478348,48.1211395264],"type":"Point"}
}