{
  "type": "Feature",
  "properties": {
    "iso:country":"DE",
    "sg:address":"Vordergasse 16",
    "sg:city":"Rodgau",
    "sg:phone":"+49 6106/3627",
    "sg:postcode":"63110",
    "sg:province":"Hessen",
    "wof:name":"Kath. Pfarramt St. Nikolaus",
    "wof:placetype":"venue"
},
  "geometry": {"coordinates":[8.8833589554,50.0262527466],"type":"Point"}
}