{
  "type": "Feature",
  "properties": {
    "iso:country":"DE",
    "sg:address":"Frankenh\u00e4user Str. 1",
    "sg:city":"Kelbra",
    "sg:phone":"+49 34651/6531",
    "sg:postcode":"06537",
    "sg:province":"Sachsen-Anhalt",
    "wof:name":"Hotel Kaiserhof",
    "wof:placetype":"venue"
},
  "geometry": {"coordinates":[11.0434741974,51.4352035522],"type":"Point"}
}