{
  "type": "Feature",
  "properties": {
    "iso:country":"DE",
    "sg:address":"Grumberg 9",
    "sg:city":"Wuppertal",
    "sg:phone":"+49 202/604674",
    "sg:postcode":"42389",
    "sg:province":"Nordrhein-Westfalen",
    "wof:name":"H. Rautenberg Rechtsanwalt",
    "wof:placetype":"venue"
},
  "geometry": {"coordinates":[7.2525701523,51.2734489441],"type":"Point"}
}