{
  "type": "Feature",
  "properties": {
    "iso:country":"DE",
    "sg:address":"Br\u00fcckstr. 15",
    "sg:city":"Essen",
    "sg:phone":"+49 201/493356",
    "sg:postcode":"45239",
    "sg:province":"Nordrhein-Westfalen",
    "wof:name":"C\u00fcrlis K\u00fcchenstudio",
    "wof:placetype":"venue"
},
  "geometry": {"coordinates":[7.0006999969,51.3879508972],"type":"Point"}
}