{
  "type": "Feature",
  "properties": {
    "iso:country":"DE",
    "sg:address":"Rembrandtstr. 24",
    "sg:city":"Bremen",
    "sg:phone":"+49 421/3479167",
    "sg:postcode":"28209",
    "sg:province":"Bremen",
    "wof:name":"Omnicomm.de Internet Gmbh",
    "wof:placetype":"venue"
},
  "geometry": {"coordinates":[8.8301677704,53.0843238831],"type":"Point"}
}