{
  "type": "Feature",
  "properties": {
    "iso:country":"DE",
    "sg:address":"Soestenstr. 47",
    "sg:city":"Cloppenburg",
    "sg:phone":"+49 4471/2845",
    "sg:postcode":"49661",
    "sg:province":"Niedersachsen",
    "wof:name":"G. L\u00fcsse Inh. Albert Themann",
    "wof:placetype":"venue"
},
  "geometry": {"coordinates":[8.0371303558,52.8493309021],"type":"Point"}
}