{
  "type": "Feature",
  "properties": {
    "iso:country":"DE",
    "sg:address":"Hauptstr. 21",
    "sg:city":"Brome",
    "sg:phone":"+49 5833/365",
    "sg:postcode":"38465",
    "sg:province":"Niedersachsen",
    "wof:name":"Arthur Wiebe",
    "wof:placetype":"venue"
},
  "geometry": {"coordinates":[10.943672,52.602222],"type":"Point"}
}