{
  "type": "Feature",
  "properties": {
    "iso:country":"DE",
    "sg:address":"In den Oleng\u00e4rten 14",
    "sg:city":"Dornburg",
    "sg:phone":"+49 6436/2547",
    "sg:postcode":"65599",
    "sg:province":"Hessen",
    "wof:name":"S. Und G. Lange",
    "wof:placetype":"venue"
},
  "geometry": {"coordinates":[8.0226154327,50.5039863586],"type":"Point"}
}