{
  "type": "Feature",
  "properties": {
    "iso:country":"DE",
    "sg:address":"Joseph-Gensler-Str. 8",
    "sg:city":"Donauw\u00f6rth",
    "sg:phone":"+49 906/706940",
    "sg:postcode":"86609",
    "sg:province":"Bayern",
    "wof:name":"Mts Systemtechnik Gmbh",
    "wof:placetype":"venue"
},
  "geometry": {"coordinates":[10.75458,48.710155],"type":"Point"}
}