{
  "type": "Feature",
  "properties": {
    "iso:country":"DE",
    "sg:address":"Am Meyerhof 6",
    "sg:city":"Damme",
    "sg:postcode":"49401",
    "sg:province":"Niedersachsen",
    "wof:name":"Eier Und Gefl\u00fcgel D\u00fcmmer- Lohausen Beteiligungs Gmbh",
    "wof:placetype":"venue"
},
  "geometry": {"coordinates":[8.27793,52.53093],"type":"Point"}
}