{
  "type": "Feature",
  "properties": {
    "iso:country":"DE",
    "sg:address":"Am Reischberg 9",
    "sg:city":"Andechs",
    "sg:phone":"+49 8157/1241",
    "sg:postcode":"82346",
    "sg:province":"Bayern",
    "wof:name":"Helmut Gerathwohl Architekt",
    "wof:placetype":"venue"
},
  "geometry": {"coordinates":[11.226099,47.945045],"type":"Point"}
}