{
  "type": "Feature",
  "properties": {
    "iso:country":"DE",
    "sg:address":"Wilhelmstr 28",
    "sg:city":"Euskirchen",
    "sg:phone":"+49 2251/770417",
    "sg:postcode":"53879",
    "sg:province":"Nordrhein-Westfalen",
    "wof:name":"Christine Ab\u00e9e",
    "wof:placetype":"venue"
},
  "geometry": {"coordinates":[6.789394,50.659229],"type":"Point"}
}