{
  "type": "Feature",
  "properties": {
    "iso:country":"DE",
    "sg:address":"Benzstr. 10",
    "sg:city":"Neuenstadt",
    "sg:phone":"+49 7139/8943",
    "sg:postcode":"74196",
    "sg:province":"Baden-W\u00fcrttemberg",
    "wof:name":"P. Thomanek",
    "wof:placetype":"venue"
},
  "geometry": {"coordinates":[9.339329,49.238205],"type":"Point"}
}