{
  "type": "Feature",
  "properties": {
    "iso:country":"DE",
    "sg:address":"Im Kappelfeld 23",
    "sg:city":"Stuttgart",
    "sg:phone":"+49 711/8567317",
    "sg:postcode":"70469",
    "sg:province":"Baden-W\u00fcrttemberg",
    "wof:name":"Naturstein",
    "wof:placetype":"venue"
},
  "geometry": {"coordinates":[9.151434,48.810482],"type":"Point"}
}