{
  "type": "Feature",
  "properties": {
    "iso:country":"DE",
    "sg:address":"Mittelstr. 5",
    "sg:city":"Kamen",
    "sg:phone":"+49 2307/40273",
    "sg:postcode":"59174",
    "sg:province":"Nordrhein-Westfalen",
    "wof:name":"Ernst Str\u00fcwer",
    "wof:placetype":"venue"
},
  "geometry": {"coordinates":[7.7103748322,51.5774803162],"type":"Point"}
}