{
  "type": "Feature",
  "properties": {
    "iso:country":"DE",
    "sg:address":"Grenzweg 21",
    "sg:city":"Sontheim",
    "sg:phone":"+49 7325/8250",
    "sg:postcode":"89567",
    "sg:province":"Baden-W\u00fcrttemberg",
    "wof:name":"Wrz Wertstoffr\u00fcck- Gewinnungszentrum",
    "wof:placetype":"venue"
},
  "geometry": {"coordinates":[10.3008403778,48.5451393127],"type":"Point"}
}