{
  "type": "Feature",
  "properties": {
    "iso:country":"DE",
    "sg:address":"Frauenstr. 6",
    "sg:city":"Annaberg-Buchholz",
    "sg:phone":"+49 3733/64144",
    "sg:postcode":"09456",
    "sg:province":"Sachsen",
    "wof:name":"G\u00e4stehaus Hanna Langer",
    "wof:placetype":"venue"
},
  "geometry": {"coordinates":[12.9949264526,50.5661582947],"type":"Point"}
}