{
  "type": "Feature",
  "properties": {
    "iso:country":"DE",
    "sg:address":"Im Gewerbepark 18",
    "sg:city":"Regensburg",
    "sg:phone":"+49 941/490970",
    "sg:postcode":"93059",
    "sg:province":"Bayern",
    "wof:name":"Klafs Saunabau Gmbh & Co. Kg",
    "wof:placetype":"venue"
},
  "geometry": {"coordinates":[12.125714,49.03006],"type":"Point"}
}