{
  "type": "Feature",
  "properties": {
    "iso:country":"DE",
    "sg:address":"Trumppstr. 2",
    "sg:city":"M\u00fcnchen",
    "sg:phone":"+49 89/8911380",
    "sg:postcode":"80997",
    "sg:province":"Bayern",
    "wof:name":"Wikro Verlag Wilhelm Kroth",
    "wof:placetype":"venue"
},
  "geometry": {"coordinates":[11.4757022858,48.1752548218],"type":"Point"}
}