{
  "type": "Feature",
  "properties": {
    "iso:country":"DE",
    "sg:address":"Kasseler Str. 58",
    "sg:city":"Lutherstadt Eisleben",
    "sg:phone":"+49 3475/92670",
    "sg:postcode":"06295",
    "sg:province":"Sachsen-Anhalt",
    "wof:name":"Kluge Umweltschutz Gmbh",
    "wof:placetype":"venue"
},
  "geometry": {"coordinates":[11.5350027084,51.5246124268],"type":"Point"}
}