{
  "type": "Feature",
  "properties": {
    "iso:country":"DE",
    "sg:address":"Robert-Bosch-Str. 83",
    "sg:city":"Aalen",
    "sg:phone":"+49 7361/45001",
    "sg:postcode":"73431",
    "sg:province":"Baden-W\u00fcrttemberg",
    "wof:name":"J & M Analytische Me\u00df- Und Regeltechnik Gmbh",
    "wof:placetype":"venue"
},
  "geometry": {"coordinates":[10.0620927811,48.8224105835],"type":"Point"}
}