{
  "type": "Feature",
  "properties": {
    "iso:country":"DE",
    "sg:address":"Eschstr. 24",
    "sg:city":"Friesoythe",
    "sg:postcode":"26169",
    "sg:province":"Niedersachsen",
    "wof:name":"Gustav Bruns Maschinenbau Und F\u00f6rderanlagen Gmbh & Co. Kg",
    "wof:placetype":"venue"
},
  "geometry": {"coordinates":[7.875656,53.018951],"type":"Point"}
}