{
  "type": "Feature",
  "properties": {
    "iso:country":"DE",
    "sg:address":"Asperger Str. 19",
    "sg:city":"Ludwigsburg",
    "sg:phone":"+49 7141/921618",
    "sg:postcode":"71634",
    "sg:province":"Baden-W\u00fcrttemberg",
    "wof:name":"Susanne Schullcke",
    "wof:placetype":"venue"
},
  "geometry": {"coordinates":[9.18579,48.897289],"type":"Point"}
}