{
  "type": "Feature",
  "properties": {
    "iso:country":"DE",
    "sg:address":"Breitscheidstr. 39",
    "sg:city":"Siegen",
    "sg:phone":"+49 271/85288",
    "sg:postcode":"57078",
    "sg:province":"Nordrhein-Westfalen",
    "wof:name":"Fritz Wied Inh. Dagmar Dohle",
    "wof:placetype":"venue"
},
  "geometry": {"coordinates":[8.0034980774,50.9037895203],"type":"Point"}
}