{
  "type": "Feature",
  "properties": {
    "iso:country":"DE",
    "sg:address":"In der Freiheit 4",
    "sg:city":"Vallendar",
    "sg:phone":"+49 261/61850",
    "sg:postcode":"56179",
    "sg:province":"Rheinland-Pfalz",
    "wof:name":"J. Trenspolde Heilpraktiker",
    "wof:placetype":"venue"
},
  "geometry": {"coordinates":[7.6131677628,50.4046783447],"type":"Point"}
}