{
  "type": "Feature",
  "properties": {
    "iso:country":"DE",
    "sg:address":"Marktstr. 76",
    "sg:city":"Landau",
    "sg:phone":"+49 6341/81474",
    "sg:postcode":"76829",
    "sg:province":"Rheinland-Pfalz",
    "wof:name":"Susi S\u00fc\u00dfwaren",
    "wof:placetype":"venue"
},
  "geometry": {"coordinates":[8.1118659973,49.1969070435],"type":"Point"}
}