{
  "type": "Feature",
  "properties": {
    "iso:country":"DE",
    "sg:address":"D\u00fcsseldorferstra\u00dfe 78-80",
    "sg:city":"Meerbusch",
    "sg:phone":"+49 2132/760527",
    "sg:postcode":"40667",
    "sg:province":"Nordrhein-Westfalen",
    "wof:name":"Fas Flamme Audiotex Service",
    "wof:placetype":"venue"
},
  "geometry": {"coordinates":[6.6944479942,51.2471961975],"type":"Point"}
}