{
  "type": "Feature",
  "properties": {
    "iso:country":"DE",
    "sg:address":"Eichelbergstr. 29",
    "sg:city":"Sulzbach-Laufen",
    "sg:phone":"+49 7976/98550",
    "sg:postcode":"74429",
    "sg:province":"Baden-W\u00fcrttemberg",
    "wof:name":"Bauer Verwaltungs- Und Beteiligungs-gmbh",
    "wof:placetype":"venue"
},
  "geometry": {"coordinates":[9.840488,48.965706],"type":"Point"}
}