{
  "type": "Feature",
  "properties": {
    "iso:country":"DE",
    "sg:address":"Bruchweg 5",
    "sg:city":"Salzhausen",
    "sg:phone":"+49 4172/5975",
    "sg:postcode":"21376",
    "sg:province":"Niedersachsen",
    "wof:name":"Reiterklause",
    "wof:placetype":"venue"
},
  "geometry": {"coordinates":[10.1908998489,53.2194442749],"type":"Point"}
}