{
  "type": "Feature",
  "properties": {
    "iso:country":"DE",
    "sg:address":"Oberdorf 13",
    "sg:city":"Obermaiselstein",
    "sg:phone":"+49 8326",
    "sg:postcode":"87538",
    "sg:province":"Bayern",
    "wof:name":"Tannheimer Hof",
    "wof:placetype":"venue"
},
  "geometry": {"coordinates":[10.250516,47.448517],"type":"Point"}
}