{
  "type": "Feature",
  "properties": {
    "iso:country":"DE",
    "sg:address":"Heidlohstr. 2 b",
    "sg:city":"Hamburg",
    "sg:phone":"+49 40/6890099",
    "sg:postcode":"22459",
    "sg:province":"Hamburg",
    "wof:name":"Falck Immobilien Hamburg",
    "wof:placetype":"venue"
},
  "geometry": {"coordinates":[9.9279184341,53.6293716431],"type":"Point"}
}