{
  "type": "Feature",
  "properties": {
    "iso:country":"DE",
    "sg:address":"Richard-Wagner-Str. 6",
    "sg:city":"Erlangen",
    "sg:phone":"+49 9131/28160",
    "sg:postcode":"91054",
    "sg:province":"Bayern",
    "wof:name":"Pizzeria Bella Rosa",
    "wof:placetype":"venue"
},
  "geometry": {"coordinates":[11.0031547546,49.5965499878],"type":"Point"}
}