{
  "type": "Feature",
  "properties": {
    "iso:country":"DE",
    "sg:address":"Gustav-Poensgen-Str. 2",
    "sg:city":"D\u00fcsseldorf",
    "sg:phone":"+49 211/383280",
    "sg:postcode":"40215",
    "sg:province":"Nordrhein-Westfalen",
    "wof:name":"Bar Extremadura",
    "wof:placetype":"venue"
},
  "geometry": {"coordinates":[6.790026,51.216362],"type":"Point"}
}