{
  "type": "Feature",
  "properties": {
    "iso:country":"DE",
    "sg:address":"Birkenstr. 23",
    "sg:city":"Kurtscheid",
    "sg:phone":"+49 2634/2660",
    "sg:postcode":"56581",
    "sg:province":"Rheinland-Pfalz",
    "wof:name":"Doris Und Karl-heinz Hasbach",
    "wof:placetype":"venue"
},
  "geometry": {"coordinates":[7.469087,50.53701],"type":"Point"}
}