{
  "type": "Feature",
  "properties": {
    "iso:country":"DE",
    "sg:address":"Vahrenwalder Str. 205",
    "sg:city":"Hannover",
    "sg:phone":"+49 511/678970",
    "sg:postcode":"30165",
    "sg:province":"Niedersachsen",
    "wof:name":"Fritz Dierking Lagerei U. Grundst\u00fccksverwaltung",
    "wof:placetype":"venue"
},
  "geometry": {"coordinates":[9.7343893051,52.4062271118],"type":"Point"}
}