{
  "type": "Feature",
  "properties": {
    "iso:country":"DE",
    "sg:address":"Bahnhofstr. 6",
    "sg:city":"Murnau",
    "sg:phone":"+49 8841/623327",
    "sg:postcode":"82418",
    "sg:province":"Bayern",
    "wof:name":"Fotostudio W. Wagner",
    "wof:placetype":"venue"
},
  "geometry": {"coordinates":[11.1989841461,47.6789054871],"type":"Point"}
}