{
  "type": "Feature",
  "properties": {
    "iso:country":"DE",
    "sg:address":"Lager Damm 7",
    "sg:city":"H\u00f6rstel",
    "sg:phone":"+49 5454/7232",
    "sg:postcode":"48477",
    "sg:province":"Nordrhein-Westfalen",
    "wof:name":"Alfons Engelshove",
    "wof:placetype":"venue"
},
  "geometry": {"coordinates":[7.624626,52.254196],"type":"Point"}
}