{
  "type": "Feature",
  "properties": {
    "iso:country":"DE",
    "sg:address":"Deblinghausen 22",
    "sg:city":"Steyerberg",
    "sg:phone":"+49 5764/1632",
    "sg:postcode":"31595",
    "sg:province":"Niedersachsen",
    "wof:name":"Lindenhof",
    "wof:placetype":"venue"
},
  "geometry": {"coordinates":[8.9963502884,52.6093597412],"type":"Point"}
}