{
  "type": "Feature",
  "properties": {
    "iso:country":"DE",
    "sg:address":"Georg-Fraunhofer-Str. 13",
    "sg:city":"Tiefenbach",
    "sg:postcode":"94113",
    "sg:province":"Bayern",
    "wof:name":"St Natursteinhandels Gmbh",
    "wof:placetype":"venue"
},
  "geometry": {"coordinates":[13.4126386642,48.6175308228],"type":"Point"}
}