{
  "type": "Feature",
  "properties": {
    "iso:country":"DE",
    "sg:address":"Annaberger Str. 177",
    "sg:city":"Crottendorf",
    "sg:phone":"+49 37344/8422",
    "sg:postcode":"09474",
    "sg:province":"Sachsen",
    "wof:name":"Steffen P\u00fcgner",
    "wof:placetype":"venue"
},
  "geometry": {"coordinates":[12.945605278,50.5214157104],"type":"Point"}
}