{
  "type": "Feature",
  "properties": {
    "iso:country":"DE",
    "sg:address":"Sophienstr. 48",
    "sg:city":"Frankfurt",
    "sg:phone":"+49 69/7191650",
    "sg:postcode":"60487",
    "sg:province":"Hessen",
    "wof:name":"Engelbach Und Partner",
    "wof:placetype":"venue"
},
  "geometry": {"coordinates":[8.6495475769,50.1236991882],"type":"Point"}
}