{
  "type": "Feature",
  "properties": {
    "iso:country":"DE",
    "sg:address":"Marktstr. 10",
    "sg:city":"Bad Sachsa",
    "sg:phone":"+49 5523/93176",
    "sg:postcode":"37441",
    "sg:province":"Niedersachsen",
    "wof:name":"Deutsche Woolworth Gmbh & Co. Ohg",
    "wof:placetype":"venue"
},
  "geometry": {"coordinates":[10.556752,51.594727],"type":"Point"}
}