{
  "type": "Feature",
  "properties": {
    "iso:country":"DE",
    "sg:address":"Turmstr. 68-69",
    "sg:city":"Berlin",
    "sg:postcode":"10551",
    "sg:province":"Berlin",
    "wof:name":"City-markt",
    "wof:placetype":"venue"
},
  "geometry": {"coordinates":[13.3318223953,52.526889801],"type":"Point"}
}