{
  "type": "Feature",
  "properties": {
    "iso:country":"DE",
    "sg:address":"Johann-Sebastian-Bach-Str. 23",
    "sg:city":"Gro\u00dfr\u00f6hrsdorf",
    "sg:postcode":"01900",
    "sg:province":"Sachsen",
    "wof:name":"Manfred K\u00fchne",
    "wof:placetype":"venue"
},
  "geometry": {"coordinates":[14.0206,51.146488],"type":"Point"}
}