{
  "type": "Feature",
  "properties": {
    "iso:country":"DE",
    "sg:address":"Hertenwinkelstr. 25",
    "sg:city":"Balingen",
    "sg:phone":"+49 7433/260290",
    "sg:postcode":"72336",
    "sg:province":"Baden-W\u00fcrttemberg",
    "wof:name":"Rolf Mayer",
    "wof:placetype":"venue"
},
  "geometry": {"coordinates":[8.8752803802,48.2967605591],"type":"Point"}
}