{
  "type": "Feature",
  "properties": {
    "iso:country":"DE",
    "sg:address":"Richelstr. 6",
    "sg:city":"M\u00fcnchen",
    "sg:phone":"+49 89/168065",
    "sg:postcode":"80634",
    "sg:province":"Bayern",
    "wof:name":"Fischer Malerei Kg",
    "wof:placetype":"venue"
},
  "geometry": {"coordinates":[11.534695,48.145771],"type":"Point"}
}