{
  "type": "Feature",
  "properties": {
    "iso:country":"DE",
    "sg:address":"Menterschwaige",
    "sg:city":"Muenchen",
    "sg:phone":"+49 89",
    "sg:postcode":"81545",
    "sg:province":"Bayern",
    "wof:name":"Medialab Informationsdesign Gmbh",
    "wof:placetype":"venue"
},
  "geometry": {"coordinates":[11.5498399734,48.078830719],"type":"Point"}
}