{
  "type": "Feature",
  "properties": {
    "iso:country":"DE",
    "sg:address":"Brunnenweg 40",
    "sg:city":"Ilvesheim",
    "sg:phone":"+49 621/492485",
    "sg:postcode":"68549",
    "sg:province":"Baden-W\u00fcrttemberg",
    "wof:name":"Peter Keller Architekt",
    "wof:placetype":"venue"
},
  "geometry": {"coordinates":[8.565408,49.477341],"type":"Point"}
}