{
  "type": "Feature",
  "properties": {
    "iso:country":"DE",
    "sg:address":"Karlsbader Str. 18",
    "sg:city":"Gernsheim",
    "sg:postcode":"64579",
    "sg:province":"Hessen",
    "wof:name":"Lindner Rohrleitungs- Anlage- Und Metallbau Gmbh",
    "wof:placetype":"venue"
},
  "geometry": {"coordinates":[8.5017681122,49.7554321289],"type":"Point"}
}