{
  "type": "Feature",
  "properties": {
    "iso:country":"DE",
    "sg:address":"W\u00fcllener Str. 40",
    "sg:city":"Vreden",
    "sg:postcode":"48691",
    "sg:province":"Nordrhein-Westfalen",
    "wof:name":"Ppv Lichtspielh\u00e4user",
    "wof:placetype":"venue"
},
  "geometry": {"coordinates":[6.8298668861,52.035446167],"type":"Point"}
}