{
  "type": "Feature",
  "properties": {
    "iso:country":"DE",
    "sg:address":"Schuhgasse 23",
    "sg:city":"Herrenberg",
    "sg:phone":"+49 7032/23344",
    "sg:postcode":"71083",
    "sg:province":"Baden-W\u00fcrttemberg",
    "wof:name":"Restaurant Alt Herrenberg",
    "wof:placetype":"venue"
},
  "geometry": {"coordinates":[8.8720979691,48.595451355],"type":"Point"}
}