{
  "type": "Feature",
  "properties": {
    "iso:country":"DE",
    "sg:address":"Johannisbollwerk 20",
    "sg:city":"Hamburg",
    "sg:phone":"+49 40/3191574",
    "sg:postcode":"20459",
    "sg:province":"Hamburg",
    "wof:name":"Ghg Ges. F\u00fcr Haus- Und Grundst\u00fcckspflege Mbh",
    "wof:placetype":"venue"
},
  "geometry": {"coordinates":[9.972854,53.545662],"type":"Point"}
}