{
  "type": "Feature",
  "properties": {
    "iso:country":"DE",
    "sg:address":"Beethovenstr. 9",
    "sg:city":"Tangerm\u00fcnde",
    "sg:phone":"+49 39322/41178",
    "sg:postcode":"39590",
    "sg:province":"Sachsen-Anhalt",
    "wof:name":"Reinhard Klose",
    "wof:placetype":"venue"
},
  "geometry": {"coordinates":[11.9595842361,52.5382575989],"type":"Point"}
}