{
  "type": "Feature",
  "properties": {
    "iso:country":"DE",
    "sg:address":"Spitalstr. 8",
    "sg:city":"Ingolstadt",
    "sg:phone":"+49 841/93340",
    "sg:postcode":"85049",
    "sg:province":"Bayern",
    "wof:name":"Anton Sippl Steuerberater",
    "wof:placetype":"venue"
},
  "geometry": {"coordinates":[11.4246730804,48.7617301941],"type":"Point"}
}