{
  "type": "Feature",
  "properties": {
    "iso:country":"DE",
    "sg:address":"B\u00fcltenweg 58",
    "sg:city":"Braunschweig",
    "sg:phone":"+49 531/342008",
    "sg:postcode":"38106",
    "sg:province":"Niedersachsen",
    "wof:name":"Fliesenzentrale Malik Kg",
    "wof:placetype":"venue"
},
  "geometry": {"coordinates":[10.5364265442,52.2798576355],"type":"Point"}
}