{
  "type": "Feature",
  "properties": {
    "iso:country":"DE",
    "sg:address":"In der Steinwiese 74",
    "sg:city":"Siegen",
    "sg:phone":"+49 271/660760",
    "sg:postcode":"57074",
    "sg:province":"Nordrhein-Westfalen",
    "wof:name":"Werbe Wienand Werbemittelvertriebs Gmbh",
    "wof:placetype":"venue"
},
  "geometry": {"coordinates":[8.0640554428,50.8685684204],"type":"Point"}
}