{
  "type": "Feature",
  "properties": {
    "iso:country":"DE",
    "sg:address":"Heinrich-Rieger-Str.",
    "sg:city":"Aalen",
    "sg:postcode":"73430",
    "sg:province":"Baden-W\u00fcrttemberg",
    "wof:name":"Komm",
    "wof:placetype":"venue"
},
  "geometry": {"coordinates":[10.0926113129,48.8465309143],"type":"Point"}
}