{
  "type": "Feature",
  "properties": {
    "iso:country":"DE",
    "sg:address":"Goldsteinstr. 28",
    "sg:city":"Bad Nauheim",
    "sg:phone":"+49 6032/31821",
    "sg:postcode":"61231",
    "sg:province":"Hessen",
    "wof:name":"Harry Becker",
    "wof:placetype":"venue"
},
  "geometry": {"coordinates":[8.756173,50.36549],"type":"Point"}
}