{
  "type": "Feature",
  "properties": {
    "iso:country":"DE",
    "sg:address":"Chemnitzer Str. 12",
    "sg:city":"Murrhardt",
    "sg:phone":"+49 7192/92280",
    "sg:postcode":"71540",
    "sg:province":"Baden-W\u00fcrttemberg",
    "wof:name":"Hans-gerd Szeppek Druck Gmbh",
    "wof:placetype":"venue"
},
  "geometry": {"coordinates":[9.5601415634,48.984085083],"type":"Point"}
}