{
  "type": "Feature",
  "properties": {
    "iso:country":"DE",
    "sg:address":"Plockstr. 30",
    "sg:city":"D\u00fcsseldorf",
    "sg:phone":"+49 211/30070",
    "sg:postcode":"40221",
    "sg:province":"Nordrhein-Westfalen",
    "wof:name":"Qvc Handel Gmbh",
    "wof:placetype":"venue"
},
  "geometry": {"coordinates":[6.7512049675,51.2109985352],"type":"Point"}
}