{
  "type": "Feature",
  "properties": {
    "iso:country":"DE",
    "sg:address":"Fichtenweg 7",
    "sg:city":"Leverkusen",
    "sg:phone":"+49 214/62893",
    "sg:postcode":"51373",
    "sg:province":"Nordrhein-Westfalen",
    "wof:name":"K. Vierth",
    "wof:placetype":"venue"
},
  "geometry": {"coordinates":[7.0104990005,51.0446052551],"type":"Point"}
}