{
  "type": "Feature",
  "properties": {
    "iso:country":"DE",
    "sg:address":"M\u00fchlenheide 63",
    "sg:city":"Paderborn",
    "sg:phone":"+49 5254/5556",
    "sg:postcode":"33106",
    "sg:province":"Nordrhein-Westfalen",
    "wof:name":"Heribert Sehrbrock Gmbh",
    "wof:placetype":"venue"
},
  "geometry": {"coordinates":[8.6768827438,51.7420120239],"type":"Point"}
}