{
  "type": "Feature",
  "properties": {
    "iso:country":"DE",
    "sg:city":"Abstatt",
    "sg:phone":"+49 4970/6262120",
    "sg:postcode":"74232",
    "sg:province":"Baden-W\u00fcrttemberg",
    "wof:name":"Kreissparkasse Heilbronn",
    "wof:placetype":"venue"
},
  "geometry": {"coordinates":[9.28908,49.067806],"type":"Point"}
}