{
  "type": "Feature",
  "properties": {
    "iso:country":"DE",
    "sg:address":"Weserstr. 4",
    "sg:city":"M\u00fchldorf",
    "sg:phone":"+49 8631/6120",
    "sg:postcode":"84453",
    "sg:province":"Bayern",
    "wof:name":"Stadtwerke M\u00fchldorf A. Inn- Beteiligungs- Gmbh",
    "wof:placetype":"venue"
},
  "geometry": {"coordinates":[12.542379,48.235577],"type":"Point"}
}