{
  "type": "Feature",
  "properties": {
    "iso:country":"DE",
    "sg:address":"Vogtpad 4",
    "sg:city":"Langeoog",
    "sg:phone":"+49 4972/495",
    "sg:postcode":"26465",
    "sg:province":"Niedersachsen",
    "wof:name":"G\u00e4stehaus J. Schmidt-freese",
    "wof:placetype":"venue"
},
  "geometry": {"coordinates":[7.4836440086,53.7493972778],"type":"Point"}
}