{
  "type": "Feature",
  "properties": {
    "iso:country":"DE",
    "sg:address":"Dammstr. 14",
    "sg:city":"Pattensen",
    "sg:phone":"+49 5101/12454",
    "sg:postcode":"30982",
    "sg:province":"Niedersachsen",
    "wof:name":"Werner Jausch Gro\u00dfschlachterei Notschlachtungsbetrieb",
    "wof:placetype":"venue"
},
  "geometry": {"coordinates":[9.758014679,52.2641944885],"type":"Point"}
}