{
  "type": "Feature",
  "properties": {
    "iso:country":"DE",
    "sg:address":"Kirchstr. 7",
    "sg:city":"Rivenich",
    "sg:phone":"+49 6508/7522",
    "sg:postcode":"54518",
    "sg:province":"Rheinland-Pfalz",
    "wof:name":"Krames",
    "wof:placetype":"venue"
},
  "geometry": {"coordinates":[6.8450880051,49.8760299683],"type":"Point"}
}