{
  "type": "Feature",
  "properties": {
    "iso:country":"DE",
    "sg:address":"Thierseestr. 196",
    "sg:city":"Kiefersfelden",
    "sg:phone":"+49 8033/97600",
    "sg:postcode":"83088",
    "sg:province":"Bayern",
    "wof:name":"R\u00f6sner Mautby Gmbh & Co. Holding Kg",
    "wof:placetype":"venue"
},
  "geometry": {"coordinates":[12.141806,47.60944],"type":"Point"}
}