{
  "type": "Feature",
  "properties": {
    "iso:country":"DE",
    "sg:address":"Lippst\u00e4dter Str. 70",
    "sg:city":"Lippetal",
    "sg:phone":"+49 2923/436",
    "sg:postcode":"59510",
    "sg:province":"Nordrhein-Westfalen",
    "wof:name":"Antonius Roer",
    "wof:placetype":"venue"
},
  "geometry": {"coordinates":[8.1538,51.662136],"type":"Point"}
}