{
  "type": "Feature",
  "properties": {
    "iso:country":"DE",
    "sg:address":"Hintergasse 7",
    "sg:city":"Veldenz",
    "sg:phone":"+49 6534/390",
    "sg:postcode":"54472",
    "sg:province":"Rheinland-Pfalz",
    "wof:name":"Kurt Kruft-linn",
    "wof:placetype":"venue"
},
  "geometry": {"coordinates":[7.0214619637,49.8897819519],"type":"Point"}
}