{
  "type": "Feature",
  "properties": {
    "iso:country":"DE",
    "sg:address":"Johannisthaler Chaussee 223",
    "sg:city":"Berlin",
    "sg:phone":"+49 30/6031032",
    "sg:postcode":"12351",
    "sg:province":"Berlin",
    "wof:name":"Total Fina Elf Mineral\u00f6l Und Chemie Gmbh",
    "wof:placetype":"venue"
},
  "geometry": {"coordinates":[13.467634201,52.4334869385],"type":"Point"}
}