{
  "type": "Feature",
  "properties": {
    "iso:country":"DE",
    "sg:address":"Z\u00f6llnerplatz 11",
    "sg:city":"Chemnitz",
    "sg:phone":"+49 371/449710",
    "sg:postcode":"09111",
    "sg:province":"Sachsen",
    "wof:name":"Hdl-hanseatische Steuerberatungsges. Mbh",
    "wof:placetype":"venue"
},
  "geometry": {"coordinates":[12.9300346375,50.8439865112],"type":"Point"}
}