{
  "type": "Feature",
  "properties": {
    "iso:country":"DE",
    "sg:address":"G\u00fcstower Weg 3",
    "sg:city":"Gadebusch",
    "sg:phone":"+49 3886/70110",
    "sg:postcode":"19205",
    "sg:province":"Mecklenburg-Vorpommern",
    "wof:name":"F. R. B. Dachdecker Und Zimmerer Gmbh",
    "wof:placetype":"venue"
},
  "geometry": {"coordinates":[11.116089,53.707706],"type":"Point"}
}