{
  "type": "Feature",
  "properties": {
    "iso:country":"DE",
    "sg:address":"Alter Burgwall 3",
    "sg:city":"Henstedt-Ulzburg",
    "sg:phone":"+49 700 0227 4353",
    "sg:postcode":"24558",
    "sg:province":"Schleswig-Holstein",
    "wof:name":"Kredit Net Ihre Kreditvermittlung Im Internet.",
    "wof:placetype":"venue"
},
  "geometry": {"coordinates":[9.977688,53.786228],"type":"Point"}
}