{
  "type": "Feature",
  "properties": {
    "iso:country":"DE",
    "sg:address":"Wacholderstr. 25",
    "sg:city":"Kamen",
    "sg:phone":"+49 2307/39586",
    "sg:postcode":"59174",
    "sg:province":"Nordrhein-Westfalen",
    "wof:name":"Thomas Szczepanski",
    "wof:placetype":"venue"
},
  "geometry": {"coordinates":[7.6178240776,51.5727882385],"type":"Point"}
}