{
  "type": "Feature",
  "properties": {
    "iso:country":"DE",
    "sg:address":"Dannenberger Str. 28",
    "sg:city":"L\u00fcchow",
    "sg:phone":"+49 5841/70541",
    "sg:postcode":"29439",
    "sg:province":"Niedersachsen",
    "wof:name":"Esso-tankstelle",
    "wof:placetype":"venue"
},
  "geometry": {"coordinates":[11.1477365494,52.966796875],"type":"Point"}
}