{
  "type": "Feature",
  "properties": {
    "iso:country":"DE",
    "sg:address":"Wodanstr. 9",
    "sg:city":"Berlin",
    "sg:phone":"+49 30/6485050",
    "sg:postcode":"12589",
    "sg:province":"Berlin",
    "wof:name":"Fehlhaber Gmbh & Co. Elektroinstallations-kg",
    "wof:placetype":"venue"
},
  "geometry": {"coordinates":[13.724285,52.419491],"type":"Point"}
}