{
  "type": "Feature",
  "properties": {
    "iso:country":"DE",
    "sg:address":"Morsestr. 9",
    "sg:city":"K\u00f6ln",
    "sg:phone":"+49 221/7126987",
    "sg:postcode":"50769",
    "sg:province":"Nordrhein-Westfalen",
    "wof:name":"Kurth Gmbh",
    "wof:placetype":"venue"
},
  "geometry": {"coordinates":[6.924726963,51.0381546021],"type":"Point"}
}