{
  "type": "Feature",
  "properties": {
    "iso:country":"DE",
    "sg:address":"Lange Str. 29",
    "sg:city":"Baden-Baden",
    "sg:phone":"+49 7221/392615",
    "sg:postcode":"76530",
    "sg:province":"Baden-W\u00fcrttemberg",
    "wof:name":"E-plus Shop",
    "wof:placetype":"venue"
},
  "geometry": {"coordinates":[8.2379732132,48.7627639771],"type":"Point"}
}