{
  "type": "Feature",
  "properties": {
    "iso:country":"DE",
    "sg:address":"Heessener Dorfstr. 71",
    "sg:city":"Hamm",
    "sg:phone":"+49 2381/32088",
    "sg:postcode":"59073",
    "sg:province":"Nordrhein-Westfalen",
    "wof:name":"Elektro Hugo Meyer Verwaltungs- Gmbh",
    "wof:placetype":"venue"
},
  "geometry": {"coordinates":[7.8361058235,51.7043495178],"type":"Point"}
}