{
  "type": "Feature",
  "properties": {
    "iso:country":"DE",
    "sg:address":"Im Rosengarten 25",
    "sg:city":"Bad Vilbel",
    "sg:postcode":"61118",
    "sg:province":"Hessen",
    "wof:name":"Kobel Wertpapier Handelsges. Mbh",
    "wof:placetype":"venue"
},
  "geometry": {"coordinates":[8.745216,50.196411],"type":"Point"}
}