{
  "type": "Feature",
  "properties": {
    "iso:country":"DE",
    "sg:address":"Hermelestr. 1",
    "sg:city":"Mindelheim",
    "sg:phone":"+49 8261/1486",
    "sg:postcode":"87719",
    "sg:province":"Bayern",
    "wof:name":"Hermann Freund & Co. Mittelschw\u00e4bische",
    "wof:placetype":"venue"
},
  "geometry": {"coordinates":[10.484691,48.046108],"type":"Point"}
}