{
  "type": "Feature",
  "properties": {
    "iso:country":"DE",
    "sg:address":"Auf dem Axberg 5",
    "sg:city":"Troisdorf",
    "sg:phone":"+49 228/451915",
    "sg:postcode":"53844",
    "sg:province":"Nordrhein-Westfalen",
    "wof:name":"H. Grommes",
    "wof:placetype":"venue"
},
  "geometry": {"coordinates":[7.1058287621,50.7753562927],"type":"Point"}
}