{
  "type": "Feature",
  "properties": {
    "iso:country":"DE",
    "sg:address":"Drosselweg 4",
    "sg:city":"K\u00f6ln",
    "sg:phone":"+49 221/714824",
    "sg:postcode":"50735",
    "sg:province":"Nordrhein-Westfalen",
    "wof:name":"Karl Zapletal",
    "wof:placetype":"venue"
},
  "geometry": {"coordinates":[6.957846,50.975498],"type":"Point"}
}