{
  "type": "Feature",
  "properties": {
    "iso:country":"DE",
    "sg:address":"Neuburger Str. 53",
    "sg:city":"Augsburg",
    "sg:phone":"+49 821/721052",
    "sg:postcode":"86167",
    "sg:province":"Bayern",
    "wof:name":"Jasa Reiseb\u00fcro",
    "wof:placetype":"venue"
},
  "geometry": {"coordinates":[10.9160299301,48.3814926147],"type":"Point"}
}