{
  "type": "Feature",
  "properties": {
    "iso:country":"DE",
    "sg:address":"Sotzweilerstr. 12",
    "sg:city":"Tholey",
    "sg:phone":"+49 6853/6337",
    "sg:postcode":"66636",
    "sg:province":"Saarland",
    "wof:name":"Johann Kuhn",
    "wof:placetype":"venue"
},
  "geometry": {"coordinates":[6.99893,49.47163],"type":"Point"}
}