{
  "type": "Feature",
  "properties": {
    "iso:country":"DE",
    "sg:address":"Industriestr.",
    "sg:city":"Schwarzenbek",
    "sg:phone":"+49 4151/89130",
    "sg:postcode":"21493",
    "sg:province":"Schleswig-Holstein",
    "wof:name":"Arthur Hitscher & Sohn Gmbh",
    "wof:placetype":"venue"
},
  "geometry": {"coordinates":[10.5044202805,53.5097045898],"type":"Point"}
}