{
  "type": "Feature",
  "properties": {
    "iso:country":"DE",
    "sg:address":"Plesser Str. 2",
    "sg:city":"Mainz",
    "sg:phone":"+49 6131/578271",
    "sg:postcode":"55131",
    "sg:province":"Rheinland-Pfalz",
    "wof:name":"Hans-j\u00fcrgen Boddin",
    "wof:placetype":"venue"
},
  "geometry": {"coordinates":[8.261446,49.986526],"type":"Point"}
}