{
  "type": "Feature",
  "properties": {
    "iso:country":"DE",
    "sg:address":"Liebermannstr. 5",
    "sg:city":"Solingen",
    "sg:phone":"+49 212/315089",
    "sg:postcode":"42719",
    "sg:province":"Nordrhein-Westfalen",
    "wof:name":"Paul-heinz Kimpeler",
    "wof:placetype":"venue"
},
  "geometry": {"coordinates":[7.0446228981,51.1813354492],"type":"Point"}
}