{
  "type": "Feature",
  "properties": {
    "iso:country":"DE",
    "sg:address":"Rudolf-Breitscheid-Str. 155",
    "sg:city":"Luckenwalde",
    "sg:phone":"+49 3371/400530",
    "sg:postcode":"14943",
    "sg:province":"Brandenburg",
    "wof:name":"Coupe Jeans Und Sportswear",
    "wof:placetype":"venue"
},
  "geometry": {"coordinates":[13.1693572998,52.0865211487],"type":"Point"}
}