{
  "type": "Feature",
  "properties": {
    "iso:country":"DE",
    "sg:address":"Kirschallee 5",
    "sg:city":"Halle",
    "sg:phone":"+49 345/5227030",
    "sg:postcode":"06118",
    "sg:province":"Sachsen-Anhalt",
    "wof:name":"Fruchtland- Fruchthandelsges. Mbh",
    "wof:placetype":"venue"
},
  "geometry": {"coordinates":[11.9993476868,51.5297050476],"type":"Point"}
}