{
  "type": "Feature",
  "properties": {
    "iso:country":"DE",
    "sg:address":"Gerlinger Str.",
    "sg:city":"Stuttgart",
    "sg:phone":"+49 711/8874818",
    "sg:postcode":"70499",
    "sg:province":"Baden-W\u00fcrttemberg",
    "wof:name":"Vereinsheim Der Hundefreunde Stuttgart Weilimdorf",
    "wof:placetype":"venue"
},
  "geometry": {"coordinates":[9.0937747955,48.8166236877],"type":"Point"}
}