{
  "type": "Feature",
  "properties": {
    "iso:country":"DE",
    "sg:address":"Br\u00fcckenstr. 17",
    "sg:city":"Schweich",
    "sg:phone":"+49 6502/95648",
    "sg:postcode":"54338",
    "sg:province":"Rheinland-Pfalz",
    "wof:name":"Antonio Ventura",
    "wof:placetype":"venue"
},
  "geometry": {"coordinates":[6.7525529861,49.8176231384],"type":"Point"}
}