{
  "type": "Feature",
  "properties": {
    "iso:country":"DE",
    "sg:address":"Hintersteinauer Str. 6",
    "sg:city":"Schl\u00fcchtern",
    "sg:phone":"+49 6661/4564",
    "sg:postcode":"36381",
    "sg:province":"Hessen",
    "wof:name":"K. Kl\u00fch",
    "wof:placetype":"venue"
},
  "geometry": {"coordinates":[9.4946403503,50.3947639465],"type":"Point"}
}