{
  "type": "Feature",
  "properties": {
    "iso:country":"DE",
    "sg:address":"Ledergasse 16",
    "sg:city":"Donzdorf",
    "sg:phone":"+49 7162/26172",
    "sg:postcode":"73072",
    "sg:province":"Baden-W\u00fcrttemberg",
    "wof:name":"Fredis",
    "wof:placetype":"venue"
},
  "geometry": {"coordinates":[9.810323,48.687935],"type":"Point"}
}