{
  "type": "Feature",
  "properties": {
    "iso:country":"DE",
    "sg:address":"Mainau 9",
    "sg:city":"Lichtenfels",
    "sg:phone":"+49 9571/72512",
    "sg:postcode":"96215",
    "sg:province":"Bayern",
    "wof:name":"Walter Allgaier",
    "wof:placetype":"venue"
},
  "geometry": {"coordinates":[11.065032959,50.1508522034],"type":"Point"}
}