{
  "type": "Feature",
  "properties": {
    "iso:country":"DE",
    "sg:address":"Martinstr. 1",
    "sg:city":"Eilenburg",
    "sg:phone":"+49 3423/608535",
    "sg:postcode":"04838",
    "sg:province":"Sachsen",
    "wof:name":"F. Namislo",
    "wof:placetype":"venue"
},
  "geometry": {"coordinates":[12.63819,51.462219],"type":"Point"}
}