{
  "type": "Feature",
  "properties": {
    "iso:country":"DE",
    "sg:address":"Rathausstr. 7",
    "sg:city":"Winsen",
    "sg:postcode":"21423",
    "sg:province":"Niedersachsen",
    "wof:name":"Giersch Gmbh",
    "wof:placetype":"venue"
},
  "geometry": {"coordinates":[10.2072782516,53.363243103],"type":"Point"}
}