{
  "type": "Feature",
  "properties": {
    "iso:country":"DE",
    "sg:address":"Untere R\u00f6merstr. 30",
    "sg:city":"Aholming",
    "sg:phone":"+49 9938/1528",
    "sg:postcode":"94527",
    "sg:province":"Bayern",
    "wof:name":"Josef Altmann",
    "wof:placetype":"venue"
},
  "geometry": {"coordinates":[12.91712,48.734161],"type":"Point"}
}