{
  "type": "Feature",
  "properties": {
    "iso:country":"DE",
    "sg:address":"Wurmberger Str. 4",
    "sg:city":"Wimsheim",
    "sg:phone":"+49 7044/43671",
    "sg:postcode":"71299",
    "sg:province":"Baden-W\u00fcrttemberg",
    "wof:name":"B. Benzinger",
    "wof:placetype":"venue"
},
  "geometry": {"coordinates":[8.8266096115,48.852394104],"type":"Point"}
}