{
  "type": "Feature",
  "properties": {
    "iso:country":"DE",
    "sg:address":"Schleifweg 34",
    "sg:city":"N\u00fcrnberg",
    "sg:phone":"+49 911/355354",
    "sg:postcode":"90409",
    "sg:province":"Bayern",
    "wof:name":"Dieter Heissler Architekt",
    "wof:placetype":"venue"
},
  "geometry": {"coordinates":[11.084859,49.470638],"type":"Point"}
}