{
  "type": "Feature",
  "properties": {
    "iso:country":"DE",
    "sg:address":"Gehege 10",
    "sg:city":"Pasewalk",
    "sg:postcode":"17309",
    "sg:province":"Mecklenburg-Vorpommern",
    "wof:name":"Erhard Bohnenstengel",
    "wof:placetype":"venue"
},
  "geometry": {"coordinates":[14.0412111282,53.5444793701],"type":"Point"}
}