{
  "type": "Feature",
  "properties": {
    "iso:country":"DE",
    "sg:address":"Kurhausstr. 6",
    "sg:city":"Bad M\u00fcnster-Ebernburg",
    "sg:phone":"+49 6708/1077",
    "sg:postcode":"55583",
    "sg:province":"Rheinland-Pfalz",
    "wof:name":"E. Drescher",
    "wof:placetype":"venue"
},
  "geometry": {"coordinates":[7.845375,49.809444],"type":"Point"}
}