{
  "type": "Feature",
  "properties": {
    "iso:country":"DE",
    "sg:address":"Pixm\u00fchle 6",
    "sg:city":"M\u00f6nchengladbach",
    "sg:phone":"+49 2166/604587",
    "sg:postcode":"41199",
    "sg:province":"Nordrhein-Westfalen",
    "wof:name":"Christiane Camphausen Innenarchitektin",
    "wof:placetype":"venue"
},
  "geometry": {"coordinates":[6.453071,51.138214],"type":"Point"}
}