{
  "type": "Feature",
  "properties": {
    "iso:country":"DE",
    "sg:address":"Duisburger Str. 375",
    "sg:city":"Oberhausen",
    "sg:phone":"+49 208/8330",
    "sg:postcode":"46049",
    "sg:province":"Nordrhein-Westfalen",
    "wof:name":"Babcock Kraftwerkstechnik Gmbh",
    "wof:placetype":"venue"
},
  "geometry": {"coordinates":[6.828793,51.472546],"type":"Point"}
}