{
  "type": "Feature",
  "properties": {
    "iso:country":"DE",
    "sg:address":"B\u00fcttelbronner Str. 17",
    "sg:city":"\u00d6hringen",
    "sg:phone":"+49 7941/61616",
    "sg:postcode":"74613",
    "sg:province":"Baden-W\u00fcrttemberg",
    "wof:name":"W. Und G. Wurst",
    "wof:placetype":"venue"
},
  "geometry": {"coordinates":[9.4985818863,49.2019882202],"type":"Point"}
}