{
  "type": "Feature",
  "properties": {
    "iso:country":"DE",
    "sg:address":"Illerdamm 4",
    "sg:city":"Kempten",
    "sg:phone":"+49 831/79457",
    "sg:postcode":"87437",
    "sg:province":"Bayern",
    "wof:name":"Cambodunum Gmbh Sauna & Fitness",
    "wof:placetype":"venue"
},
  "geometry": {"coordinates":[10.321335,47.727055],"type":"Point"}
}