{
  "type": "Feature",
  "properties": {
    "iso:country":"DE",
    "sg:address":"Werler Str. 19 e",
    "sg:city":"Herford",
    "sg:phone":"+49 5221/74773",
    "sg:postcode":"32052",
    "sg:province":"Nordrhein-Westfalen",
    "wof:name":"Rs Fu\u00dfbodentechnik Gmbh",
    "wof:placetype":"venue"
},
  "geometry": {"coordinates":[8.6693096161,52.116104126],"type":"Point"}
}