{
  "type": "Feature",
  "properties": {
    "iso:country":"DE",
    "sg:address":"Loogstr. 31",
    "sg:city":"Ihlow",
    "sg:phone":"+49 4941/3229",
    "sg:postcode":"26632",
    "sg:province":"Niedersachsen",
    "wof:name":"J. Ringering",
    "wof:placetype":"venue"
},
  "geometry": {"coordinates":[7.42256,53.438599],"type":"Point"}
}