{
  "type": "Feature",
  "properties": {
    "iso:country":"DE",
    "sg:address":"Bonner Str. 18",
    "sg:city":"Erftstadt",
    "sg:phone":"+49 2235/71791",
    "sg:postcode":"50374",
    "sg:province":"Nordrhein-Westfalen",
    "wof:name":"F. Zavelsberg",
    "wof:placetype":"venue"
},
  "geometry": {"coordinates":[6.767917,50.799805],"type":"Point"}
}