{
  "type": "Feature",
  "properties": {
    "iso:country":"DE",
    "sg:address":"Rathausstr. 34",
    "sg:city":"\u00d6hringen",
    "sg:phone":"+49 7941/2462",
    "sg:postcode":"74613",
    "sg:province":"Baden-W\u00fcrttemberg",
    "wof:name":"W. Nickert",
    "wof:placetype":"venue"
},
  "geometry": {"coordinates":[9.50017,49.200291],"type":"Point"}
}