{
  "type": "Feature",
  "properties": {
    "iso:country":"DE",
    "sg:address":"Rathenaustr. 17a",
    "sg:city":"Sonneberg",
    "sg:phone":"+49 3675/805000",
    "sg:postcode":"96515",
    "sg:province":"Th\u00fcringen",
    "wof:name":"Autohansa Autovermietung",
    "wof:placetype":"venue"
},
  "geometry": {"coordinates":[11.17841,50.359951],"type":"Point"}
}