{
  "type": "Feature",
  "properties": {
    "iso:country":"DE",
    "sg:address":"Rheinbr\u00fcckstr. 5-7",
    "sg:city":"Rheinfelden",
    "sg:postcode":"79618",
    "sg:province":"Baden-W\u00fcrttemberg",
    "wof:name":"Energie Dienst Gmbh",
    "wof:placetype":"venue"
},
  "geometry": {"coordinates":[7.787912,47.556614],"type":"Point"}
}