{
  "type": "Feature",
  "properties": {
    "iso:country":"DE",
    "sg:address":"Elbstr. 14 a",
    "sg:city":"Riesa",
    "sg:phone":"+49 3525/736773",
    "sg:postcode":"01589",
    "sg:province":"Sachsen",
    "wof:name":"Bootshaus",
    "wof:placetype":"venue"
},
  "geometry": {"coordinates":[13.3097400665,51.3052749634],"type":"Point"}
}