{
  "type": "Feature",
  "properties": {
    "iso:country":"DE",
    "sg:address":"Rh\u00f6nstr. 2",
    "sg:city":"Philippsthal",
    "sg:phone":"+49 6620/1775",
    "sg:postcode":"36269",
    "sg:province":"Hessen",
    "wof:name":"H. G. Media Gmbh",
    "wof:placetype":"venue"
},
  "geometry": {"coordinates":[9.9532356262,50.8515968323],"type":"Point"}
}