{
  "type": "Feature",
  "properties": {
    "iso:country":"DE",
    "sg:address":"St.-J\u00fcrgen-Str. 151",
    "sg:city":"Bremen",
    "sg:phone":"+49 421/494949",
    "sg:postcode":"28205",
    "sg:province":"Bremen",
    "wof:name":"I. Kraft",
    "wof:placetype":"venue"
},
  "geometry": {"coordinates":[8.83756,53.077068],"type":"Point"}
}