{
  "type": "Feature",
  "properties": {
    "iso:country":"DE",
    "sg:address":"Kirchstr. 22",
    "sg:city":"Berod",
    "sg:phone":"+49 6435/1572",
    "sg:postcode":"56414",
    "sg:province":"Rheinland-Pfalz",
    "wof:name":"W. Daum",
    "wof:placetype":"venue"
},
  "geometry": {"coordinates":[7.934621,50.48185],"type":"Point"}
}