{
  "type": "Feature",
  "properties": {
    "iso:country":"DE",
    "sg:address":"Dorfstr. 16",
    "sg:city":"Gro\u00dfhelfendorf",
    "sg:phone":"+49 8095/1268",
    "sg:postcode":"85655",
    "wof:name":"Karl Krommer",
    "wof:placetype":"venue"
},
  "geometry": {"coordinates":[11.791736,47.943737],"type":"Point"}
}