{
  "type": "Feature",
  "properties": {
    "iso:country":"DE",
    "sg:address":"Chopinstr. 27",
    "sg:city":"Zittau",
    "sg:phone":"+49 3583/705496",
    "sg:postcode":"02763",
    "sg:province":"Sachsen",
    "wof:name":"J. Schmidt",
    "wof:placetype":"venue"
},
  "geometry": {"coordinates":[14.822702,50.896976],"type":"Point"}
}