{
  "type": "Feature",
  "properties": {
    "iso:country":"DE",
    "sg:address":"Hauptstr. 6",
    "sg:city":"Bad Waldsee",
    "sg:phone":"+49 7524/8611",
    "sg:postcode":"88339",
    "sg:province":"Baden-W\u00fcrttemberg",
    "wof:name":"Hildegard G\u00fctler",
    "wof:placetype":"venue"
},
  "geometry": {"coordinates":[9.755933,47.919685],"type":"Point"}
}