{
  "type": "Feature",
  "properties": {
    "iso:country":"DE",
    "sg:address":"Am Findling 7",
    "sg:city":"Georgsmarienh\u00fctte",
    "sg:phone":"+49 5401/35082",
    "sg:postcode":"49124",
    "sg:province":"Niedersachsen",
    "wof:name":"Dlrg-ortsverband Georgsmarienh\u00fctte E. V.",
    "wof:placetype":"venue"
},
  "geometry": {"coordinates":[8.0258159637,52.1997795105],"type":"Point"}
}