{
  "type": "Feature",
  "properties": {
    "iso:country":"DE",
    "sg:address":"Lotterstrasse 10",
    "sg:city":"Radolfzell",
    "sg:phone":"+49 7654/86542",
    "sg:postcode":"78845",
    "wof:name":"Chemie- Und Biologienachpruefungen Fuer Eg",
    "wof:placetype":"venue"
},
  "geometry": {"coordinates":[-100.449074,23.108931],"type":"Point"}
}