{
  "type": "Feature",
  "properties": {
    "iso:country":"DE",
    "sg:address":"Unterbr\u00e4nd 12",
    "sg:city":"Br\u00e4unlingen",
    "sg:phone":"+49 7654/402",
    "sg:postcode":"78199",
    "sg:province":"Baden-W\u00fcrttemberg",
    "wof:name":"Ferienort Unterbr\u00e4nd Am Kirnbergsee",
    "wof:placetype":"venue"
},
  "geometry": {"coordinates":[8.362106,47.95657],"type":"Point"}
}