{
  "type": "Feature",
  "properties": {
    "iso:country":"DE",
    "sg:address":"Greifswalder Str. 212",
    "sg:city":"Berlin",
    "sg:postcode":"10405",
    "sg:province":"Berlin",
    "wof:name":"Panda Schuhcompany Verwaltungs Gmbh",
    "wof:placetype":"venue"
},
  "geometry": {"coordinates":[13.427633,52.531975],"type":"Point"}
}