{
  "type": "Feature",
  "properties": {
    "iso:country":"DE",
    "sg:address":"Auenstr. 25",
    "sg:city":"B\u00f6hlitz-Ehrenberg",
    "sg:postcode":"04430",
    "wof:name":"Concept Wirtschaftsingenieurges. Mbh",
    "wof:placetype":"venue"
},
  "geometry": {"coordinates":[12.297338,51.359905],"type":"Point"}
}