{
  "type": "Feature",
  "properties": {
    "iso:country":"DE",
    "sg:address":"J\u00e4gergang 6",
    "sg:city":"Stein",
    "sg:phone":"+49 4343/9297",
    "sg:postcode":"24235",
    "sg:province":"Schleswig-Holstein",
    "wof:name":"Hans Wiede Architekt",
    "wof:placetype":"venue"
},
  "geometry": {"coordinates":[10.272645,54.41489],"type":"Point"}
}