{
  "type": "Feature",
  "properties": {
    "iso:country":"DE",
    "sg:address":"Jahnstr. 26",
    "sg:city":"Bad Klosterlausnitz",
    "sg:phone":"+49 36601/43525",
    "sg:postcode":"07639",
    "sg:province":"Th\u00fcringen",
    "wof:name":"J\u00fcrgen St\u00f6rzner",
    "wof:placetype":"venue"
},
  "geometry": {"coordinates":[11.8652610779,50.9133682251],"type":"Point"}
}