{
  "type": "Feature",
  "properties": {
    "iso:country":"DE",
    "sg:address":"Hambacher Str. 12",
    "sg:city":"Neustadt",
    "sg:phone":"+49 6321/84399",
    "sg:postcode":"67434",
    "sg:province":"Rheinland-Pfalz",
    "wof:name":"W. Korb",
    "wof:placetype":"venue"
},
  "geometry": {"coordinates":[8.1387424469,49.3463020325],"type":"Point"}
}