{
  "type": "Feature",
  "properties": {
    "iso:country":"DE",
    "sg:address":"Lindenbachstr. 94",
    "sg:city":"Stuttgart",
    "sg:phone":"+49 711/8891154",
    "sg:postcode":"70499",
    "sg:province":"Baden-W\u00fcrttemberg",
    "wof:name":"Baupartner Gmbh",
    "wof:placetype":"venue"
},
  "geometry": {"coordinates":[9.125835,48.815151],"type":"Point"}
}