{
  "type": "Feature",
  "properties": {
    "iso:country":"DE",
    "sg:address":"Lohauser Esch 21",
    "sg:city":"Heiden",
    "sg:phone":"+49 2867/8845",
    "sg:postcode":"46359",
    "sg:province":"Nordrhein-Westfalen",
    "wof:name":"A & L Immobilien Gmbh",
    "wof:placetype":"venue"
},
  "geometry": {"coordinates":[6.9244570732,51.8265419006],"type":"Point"}
}