{
  "type": "Feature",
  "properties": {
    "iso:country":"DE",
    "sg:address":"An den 7 St\u00fccken",
    "sg:city":"K\u00f6nnern",
    "sg:postcode":"06420",
    "sg:province":"Sachsen-Anhalt",
    "wof:name":"Zuckerfabrik Langenbogen Gmbh",
    "wof:placetype":"venue"
},
  "geometry": {"coordinates":[11.7601099014,51.699760437],"type":"Point"}
}