{
  "type": "Feature",
  "properties": {
    "iso:country":"DE",
    "sg:address":"Mombachstr. 79",
    "sg:city":"Kassel",
    "sg:phone":"+49 561/893817",
    "sg:postcode":"34127",
    "sg:province":"Hessen",
    "wof:name":"Lothar Umbach",
    "wof:placetype":"venue"
},
  "geometry": {"coordinates":[9.4946155548,51.3249931335],"type":"Point"}
}