{
  "type": "Feature",
  "properties": {
    "iso:country":"DE",
    "sg:address":"Vogelsang 18 a",
    "sg:city":"Kusel",
    "sg:phone":"+49 6381/2004",
    "sg:postcode":"66869",
    "sg:province":"Rheinland-Pfalz",
    "wof:name":"Praxis Dr. Luft Tier\u00e4rzte",
    "wof:placetype":"venue"
},
  "geometry": {"coordinates":[7.399831,49.54216],"type":"Point"}
}