{
  "type": "Feature",
  "properties": {
    "iso:country":"DE",
    "sg:address":"Elisabethstr. 16",
    "sg:city":"Iserlohn",
    "sg:phone":"+49 2371/29175",
    "sg:postcode":"58636",
    "sg:province":"Nordrhein-Westfalen",
    "wof:name":"C. Und R. Effenberger",
    "wof:placetype":"venue"
},
  "geometry": {"coordinates":[7.7058439255,51.3771438599],"type":"Point"}
}