{
  "type": "Feature",
  "properties": {
    "iso:country":"DE",
    "sg:address":"Elbstr. 5",
    "sg:city":"Brunsb\u00fcttel",
    "sg:phone":"+49 4852/3089",
    "sg:postcode":"25541",
    "sg:province":"Schleswig-Holstein",
    "wof:name":"W. Und U. Peters Immobilienmakler",
    "wof:placetype":"venue"
},
  "geometry": {"coordinates":[9.134598732,53.8966636658],"type":"Point"}
}