{
  "type": "Feature",
  "properties": {
    "iso:country":"DE",
    "sg:address":"Friedrich-Engels-Ring 50",
    "sg:city":"Neubrandenburg",
    "sg:postcode":"17033",
    "sg:province":"Mecklenburg-Vorpommern",
    "wof:name":"Marx Assekuranzmakler Kg",
    "wof:placetype":"venue"
},
  "geometry": {"coordinates":[13.2667160034,53.5545005798],"type":"Point"}
}