{
  "type": "Feature",
  "properties": {
    "iso:country":"DE",
    "sg:address":"Langewieser Str. 12",
    "sg:city":"Winterberg",
    "sg:phone":"+49 2758/286",
    "sg:postcode":"59955",
    "sg:province":"Nordrhein-Westfalen",
    "wof:name":"Pension Alfons Dohle",
    "wof:placetype":"venue"
},
  "geometry": {"coordinates":[8.4605493546,51.1541175842],"type":"Point"}
}