{
  "type": "Feature",
  "properties": {
    "iso:country":"DE",
    "sg:address":"Frankfurter Str. 49",
    "sg:city":"K\u00f6ln",
    "sg:phone":"+49 221/623293",
    "sg:postcode":"51065",
    "sg:province":"Nordrhein-Westfalen",
    "wof:name":"Neuform Reformhaus Lesske",
    "wof:placetype":"venue"
},
  "geometry": {"coordinates":[7.0081090927,50.9598121643],"type":"Point"}
}