{
  "type": "Feature",
  "properties": {
    "iso:country":"DE",
    "sg:address":"Untermarkt 56-60",
    "sg:city":"Murnau",
    "sg:phone":"+49 8841/4710",
    "sg:postcode":"82418",
    "sg:province":"Bayern",
    "wof:name":"Hummelsheim Beteiligungs-gmbh",
    "wof:placetype":"venue"
},
  "geometry": {"coordinates":[11.201325,47.674942],"type":"Point"}
}