{
  "type": "Feature",
  "properties": {
    "iso:country":"DE",
    "sg:address":"Gemsenstr. 37",
    "sg:city":"Kaarst",
    "sg:phone":"+49 2131/666089",
    "sg:postcode":"41564",
    "sg:province":"Nordrhein-Westfalen",
    "wof:name":"E. Cornils",
    "wof:placetype":"venue"
},
  "geometry": {"coordinates":[6.594379,51.228779],"type":"Point"}
}