{
  "type": "Feature",
  "properties": {
    "iso:country":"DE",
    "sg:address":"Alte Weberei 6",
    "sg:city":"Kaufbeuren",
    "sg:phone":"+49 8341/2773",
    "sg:postcode":"87600",
    "sg:province":"Bayern",
    "wof:name":"Back Eckart Und Krapf Rechtanw\u00e4lte",
    "wof:placetype":"venue"
},
  "geometry": {"coordinates":[10.6234827042,47.8827171326],"type":"Point"}
}