{
  "type": "Feature",
  "properties": {
    "iso:country":"DE",
    "sg:address":"Klosterberg 2",
    "sg:city":"T\u00fcbingen",
    "sg:phone":"+49 7071/5610",
    "sg:postcode":"72070",
    "sg:province":"Baden-W\u00fcrttemberg",
    "wof:name":"Evangelisches Stift",
    "wof:placetype":"venue"
},
  "geometry": {"coordinates":[9.053523,48.519493],"type":"Point"}
}