{
  "type": "Feature",
  "properties": {
    "iso:country":"DE",
    "sg:address":"Sorbenstr. 3",
    "sg:city":"Hamburg",
    "sg:phone":"+49 40/2512032",
    "sg:postcode":"20537",
    "sg:province":"Hamburg",
    "wof:name":"Christel Ramsay Wilhelm Voss Nachf. Kg",
    "wof:placetype":"venue"
},
  "geometry": {"coordinates":[10.0391569138,53.5495414734],"type":"Point"}
}