{
  "type": "Feature",
  "properties": {
    "iso:country":"DE",
    "sg:address":"Greifswalder Str. 214",
    "sg:city":"Berlin",
    "sg:postcode":"10405",
    "sg:province":"Berlin",
    "wof:name":"Ingelheimer Platz Grundst\u00fccksges. Mbh",
    "wof:placetype":"venue"
},
  "geometry": {"coordinates":[13.4273843765,52.5317573547],"type":"Point"}
}