{
  "type": "Feature",
  "properties": {
    "iso:country":"DE",
    "sg:address":"Bahnhofstr. 19",
    "sg:city":"Zetel",
    "sg:phone":"+49 4453/2041",
    "sg:postcode":"26340",
    "sg:province":"Niedersachsen",
    "wof:name":"R. Meynen Gmbh Fachgesch\u00e4ft F\u00fcr Brennstoffe",
    "wof:placetype":"venue"
},
  "geometry": {"coordinates":[7.9730401039,53.416519165],"type":"Point"}
}