{
  "type": "Feature",
  "properties": {
    "iso:country":"DE",
    "sg:address":"Rebbergblick 14",
    "sg:city":"Seelbach",
    "sg:phone":"+49 7823/96555",
    "sg:postcode":"77960",
    "sg:province":"Baden-W\u00fcrttemberg",
    "wof:name":"Dr. Gerhard Baran Tierarzt",
    "wof:placetype":"venue"
},
  "geometry": {"coordinates":[7.9449329376,48.3049659729],"type":"Point"}
}