{
  "type": "Feature",
  "properties": {
    "iso:country":"DE",
    "sg:address":"Bahnhofsplatz 3",
    "sg:city":"Bruchsal",
    "sg:postcode":"76646",
    "sg:province":"Baden-W\u00fcrttemberg",
    "wof:name":"Cleopatra-online-shop E. K.",
    "wof:placetype":"venue"
},
  "geometry": {"coordinates":[8.5915031433,49.125087738],"type":"Point"}
}