{
  "type": "Feature",
  "properties": {
    "iso:country":"DE",
    "sg:address":"Gartenstr. 9",
    "sg:city":"Roth",
    "sg:postcode":"91154",
    "sg:province":"Bayern",
    "wof:name":"Mullee Gmbh & Co. Kg",
    "wof:placetype":"venue"
},
  "geometry": {"coordinates":[11.0948600769,49.2459144592],"type":"Point"}
}