{
  "type": "Feature",
  "properties": {
    "iso:country":"DE",
    "sg:address":"Fahrlachstr. 14",
    "sg:city":"Mannheim",
    "sg:phone":"+49 621/4600950",
    "sg:postcode":"68165",
    "sg:province":"Baden-W\u00fcrttemberg",
    "wof:name":"Paul Dosch Wasseraufbereitung",
    "wof:placetype":"venue"
},
  "geometry": {"coordinates":[8.492481,49.47028],"type":"Point"}
}