{
  "type": "Feature",
  "properties": {
    "iso:country":"DE",
    "sg:address":"Kirchberg 18",
    "sg:city":"Wolfegg",
    "sg:phone":"+49 7527/1567",
    "sg:postcode":"88364",
    "sg:province":"Baden-W\u00fcrttemberg",
    "wof:name":"G\u00e4stehaus U. Weinstube Oliva",
    "wof:placetype":"venue"
},
  "geometry": {"coordinates":[9.7896690369,47.837387085],"type":"Point"}
}