{
  "type": "Feature",
  "properties": {
    "iso:country":"DE",
    "sg:address":"Am Schorenweg 18",
    "sg:city":"Westendorf",
    "sg:phone":"+49 8344/1311",
    "sg:postcode":"87679",
    "sg:province":"Bayern",
    "wof:name":"A. Strobel",
    "wof:placetype":"venue"
},
  "geometry": {"coordinates":[10.71472,47.930817],"type":"Point"}
}