{
  "type": "Feature",
  "properties": {
    "iso:country":"DE",
    "sg:address":"K\u00f6nigstr. 31-33",
    "sg:city":"Paderborn",
    "sg:phone":"+49 5251/25326",
    "sg:postcode":"33098",
    "sg:province":"Nordrhein-Westfalen",
    "wof:name":"Restaurant Sala-thai",
    "wof:placetype":"venue"
},
  "geometry": {"coordinates":[8.7485427856,51.7189216614],"type":"Point"}
}