{
  "type": "Feature",
  "properties": {
    "iso:country":"DE",
    "sg:address":"Breiter Weg 69",
    "sg:city":"Aurich",
    "sg:phone":"+49 4941/3307",
    "sg:postcode":"26603",
    "sg:province":"Niedersachsen",
    "wof:name":"Sander & Sohn",
    "wof:placetype":"venue"
},
  "geometry": {"coordinates":[7.470745,53.472977],"type":"Point"}
}