{
  "type": "Feature",
  "properties": {
    "iso:country":"DE",
    "sg:address":"Hetzweger Str. 10",
    "sg:city":"Schee\u00dfel",
    "sg:phone":"+49 4263/1336",
    "sg:postcode":"27383",
    "sg:province":"Niedersachsen",
    "wof:name":"Johann Wahlers",
    "wof:placetype":"venue"
},
  "geometry": {"coordinates":[9.46537,53.17453],"type":"Point"}
}