{
  "type": "Feature",
  "properties": {
    "iso:country":"DE",
    "sg:address":"Gerberei 19",
    "sg:city":"Erlangen",
    "sg:phone":"+49 9131/28305",
    "sg:postcode":"91054",
    "sg:province":"Bayern",
    "wof:name":"Ralf Biederbick",
    "wof:placetype":"venue"
},
  "geometry": {"coordinates":[10.998457,49.598377],"type":"Point"}
}