{
  "type": "Feature",
  "properties": {
    "iso:country":"DE",
    "sg:address":"Godesberger Str. 51",
    "sg:city":"Meckenheim",
    "sg:postcode":"53340",
    "sg:province":"Nordrhein-Westfalen",
    "wof:name":"Zweigstelle D. Evangelischen \u00d6ffentl. B\u00fccherei Merl",
    "wof:placetype":"venue"
},
  "geometry": {"coordinates":[7.055903,50.632347],"type":"Point"}
}