{
  "type": "Feature",
  "properties": {
    "iso:country":"DE",
    "sg:address":"Berliner Str 13b",
    "sg:city":"Coswig",
    "sg:phone":"+49 34903/68298",
    "sg:postcode":"06869",
    "sg:province":"Sachsen-Anhalt",
    "wof:name":"T\u00f6pferei G. Dietrich",
    "wof:placetype":"venue"
},
  "geometry": {"coordinates":[12.385796,51.92762],"type":"Point"}
}