{
  "type": "Feature",
  "properties": {
    "iso:country":"DE",
    "sg:address":"Schenkendorfstr. 29",
    "sg:city":"M\u00fclheim",
    "sg:phone":"+49 208/780804",
    "sg:postcode":"45472",
    "sg:province":"Nordrhein-Westfalen",
    "wof:name":"Pools-ulpa Textil Gmbh",
    "wof:placetype":"venue"
},
  "geometry": {"coordinates":[6.9531369209,51.4442214966],"type":"Point"}
}