{
  "type": "Feature",
  "properties": {
    "iso:country":"DE",
    "sg:address":"Obere B\u00fcrgstr. 2",
    "sg:city":"\u00d6hringen",
    "sg:phone":"+49 7941/61690",
    "sg:postcode":"74613",
    "sg:province":"Baden-W\u00fcrttemberg",
    "wof:name":"Ulrich Kopp Architekt",
    "wof:placetype":"venue"
},
  "geometry": {"coordinates":[9.504223,49.206112],"type":"Point"}
}