{
  "type": "Feature",
  "properties": {
    "iso:country":"DE",
    "sg:address":"Koloniestr. 40",
    "sg:city":"Berlin",
    "sg:phone":"+49 30/4911401",
    "sg:postcode":"13359",
    "sg:province":"Berlin",
    "wof:name":"Carola Schulz",
    "wof:placetype":"venue"
},
  "geometry": {"coordinates":[13.3815279007,52.5614051819],"type":"Point"}
}