{
  "type": "Feature",
  "properties": {
    "iso:country":"DE",
    "sg:address":"Muglhofer Str. 2 a",
    "sg:city":"Vohenstrau\u00df",
    "sg:phone":"+49 9651/91119",
    "sg:postcode":"92648",
    "sg:province":"Bayern",
    "wof:name":"G\u00f6sl Metallbau Gmbh",
    "wof:placetype":"venue"
},
  "geometry": {"coordinates":[12.3417,49.623638],"type":"Point"}
}