{
  "type": "Feature",
  "properties": {
    "iso:country":"DE",
    "sg:address":"Hagenstr. 65a",
    "sg:city":"Lampertheim",
    "sg:phone":"+49 6206/56161",
    "sg:postcode":"68623",
    "sg:province":"Hessen",
    "wof:name":"Wolfgang Klemmer",
    "wof:placetype":"venue"
},
  "geometry": {"coordinates":[8.471253,49.6021],"type":"Point"}
}