{
  "type": "Feature",
  "properties": {
    "iso:country":"DE",
    "sg:address":"M\u00fchlenstr. 26",
    "sg:city":"M\u00fclsen",
    "sg:phone":"+49 37601/2745",
    "sg:postcode":"08132",
    "sg:province":"Sachsen",
    "wof:name":"Manfred Clau\u00df",
    "wof:placetype":"venue"
},
  "geometry": {"coordinates":[12.591293,50.72123],"type":"Point"}
}