{
  "type": "Feature",
  "properties": {
    "iso:country":"DE",
    "sg:address":"Nu\u00dffeldstr. 29",
    "sg:city":"Wernersberg",
    "sg:phone":"+49 6346/2522",
    "sg:postcode":"76857",
    "sg:province":"Rheinland-Pfalz",
    "wof:name":"Fritz Seiter",
    "wof:placetype":"venue"
},
  "geometry": {"coordinates":[7.931654,49.192287],"type":"Point"}
}