{
  "type": "Feature",
  "properties": {
    "iso:country":"DE",
    "sg:address":"Badergasse 3",
    "sg:city":"Colditz",
    "sg:phone":"+49 34381/43580",
    "sg:postcode":"04680",
    "sg:province":"Sachsen",
    "wof:name":"Ulrich Scheller Rechtsanwalt",
    "wof:placetype":"venue"
},
  "geometry": {"coordinates":[12.8051729202,51.130317688],"type":"Point"}
}