{
  "type": "Feature",
  "properties": {
    "iso:country":"DE",
    "sg:address":"Waldstra\u00dfe 22",
    "sg:city":"Nidderau",
    "sg:phone":"+49 6187/24660",
    "sg:postcode":"61130",
    "sg:province":"Hessen",
    "wof:name":"Aqua-terra Nidderau E.v.",
    "wof:placetype":"venue"
},
  "geometry": {"coordinates":[8.8671712875,50.2709503174],"type":"Point"}
}