{
  "type": "Feature",
  "properties": {
    "iso:country":"DE",
    "sg:address":"Silberfundstr. 44",
    "sg:city":"Hildesheim",
    "sg:phone":"+49 5121/868985",
    "sg:postcode":"31141",
    "sg:province":"Niedersachsen",
    "wof:name":"Schumacher",
    "wof:placetype":"venue"
},
  "geometry": {"coordinates":[9.965061,52.139584],"type":"Point"}
}