{
  "type": "Feature",
  "properties": {
    "iso:country":"DE",
    "sg:address":"Goethestr. 89",
    "sg:city":"Waltershausen",
    "sg:postcode":"99880",
    "sg:province":"Th\u00fcringen",
    "wof:name":"Dr. I. Kleinsteuber",
    "wof:placetype":"venue"
},
  "geometry": {"coordinates":[10.5689,50.892891],"type":"Point"}
}