{
  "type": "Feature",
  "properties": {
    "iso:country":"DE",
    "sg:address":"Kirchengasse",
    "sg:city":"Heppenheim",
    "sg:phone":"+49 6252/67560",
    "sg:postcode":"64646",
    "sg:province":"Hessen",
    "wof:name":"Auf Dem Steigkopf Gastst\u00e4tte",
    "wof:placetype":"venue"
},
  "geometry": {"coordinates":[8.6465816498,49.6417045593],"type":"Point"}
}