{
  "type": "Feature",
  "properties": {
    "iso:country":"DE",
    "sg:address":"Bornheimer Str. 30",
    "sg:city":"Bornheim",
    "sg:phone":"+49 2222/82108",
    "sg:postcode":"53332",
    "sg:province":"Nordrhein-Westfalen",
    "wof:name":"Clemens Wichmann",
    "wof:placetype":"venue"
},
  "geometry": {"coordinates":[7.0322318077,50.7801208496],"type":"Point"}
}