{
  "type": "Feature",
  "properties": {
    "iso:country":"DE",
    "sg:address":"Am Pfauenufer 6a",
    "sg:city":"Unna",
    "sg:phone":"+49 2303/50593",
    "sg:postcode":"59427",
    "sg:province":"Nordrhein-Westfalen",
    "wof:name":"Erna R\u00f6der",
    "wof:placetype":"venue"
},
  "geometry": {"coordinates":[7.640184,51.530502],"type":"Point"}
}