{
  "type": "Feature",
  "properties": {
    "iso:country":"DE",
    "sg:address":"Breite Str. 20",
    "sg:city":"Gro\u00df Ammensleben",
    "sg:phone":"+49 39202/66744",
    "sg:postcode":"39326",
    "sg:province":"Sachsen-Anhalt",
    "wof:name":"Dessau Gbr",
    "wof:placetype":"venue"
},
  "geometry": {"coordinates":[11.52232,52.234867],"type":"Point"}
}