{
  "type": "Feature",
  "properties": {
    "iso:country":"DE",
    "sg:address":"Mauergasse 4a",
    "sg:city":"Meiningen",
    "sg:postcode":"98617",
    "sg:province":"Th\u00fcringen",
    "wof:name":"Vhi Verlagses. F. Handel Und Industrie Zwlg. D. R. Krick",
    "wof:placetype":"venue"
},
  "geometry": {"coordinates":[10.4115896225,50.5680503845],"type":"Point"}
}