{
  "type": "Feature",
  "properties": {
    "iso:country":"DE",
    "sg:address":"Truderinger Str. 252",
    "sg:city":"M\u00fcnchen",
    "sg:phone":"+49 89/423841",
    "sg:postcode":"81825",
    "sg:province":"Bayern",
    "wof:name":"Gisela Volderauer",
    "wof:placetype":"venue"
},
  "geometry": {"coordinates":[11.6633453369,48.1252441406],"type":"Point"}
}