{
  "type": "Feature",
  "properties": {
    "iso:country":"DE",
    "sg:address":"Friedrich-Wilhelm-Str. 26",
    "sg:city":"Eschwege",
    "sg:phone":"+49 5651/801325",
    "sg:postcode":"37269",
    "sg:province":"Hessen",
    "wof:name":"Woelm Pahrma Gmbh & Co. Bibliothek",
    "wof:placetype":"venue"
},
  "geometry": {"coordinates":[10.047981,51.189751],"type":"Point"}
}