{
  "type": "Feature",
  "properties": {
    "iso:country":"DE",
    "sg:address":"Am Kurhaus 2",
    "sg:city":"Kurort Jonsdorf",
    "sg:phone":"+49 35844/70920",
    "sg:postcode":"02796",
    "sg:province":"Sachsen",
    "wof:name":"Jonas-apotheke E. K. Inh. Dr. Roger Stiehle",
    "wof:placetype":"venue"
},
  "geometry": {"coordinates":[14.701933,50.85397],"type":"Point"}
}