{
  "type": "Feature",
  "properties": {
    "iso:country":"DE",
    "sg:address":"Kunissastr. 2",
    "sg:city":"Die\u00dfen",
    "sg:phone":"+49 8807/9331",
    "sg:postcode":"86911",
    "sg:province":"Bayern",
    "wof:name":"Weiss Organisation Und Beratung Gmbh",
    "wof:placetype":"venue"
},
  "geometry": {"coordinates":[11.10236,47.95187],"type":"Point"}
}