{
  "type": "Feature",
  "properties": {
    "iso:country":"DE",
    "sg:address":"Kanalstr. 5",
    "sg:city":"Berg",
    "sg:phone":"+49 9189/9416",
    "sg:postcode":"92348",
    "sg:province":"Bayern",
    "wof:name":"Gb Holzbau Braun & Bayer",
    "wof:placetype":"venue"
},
  "geometry": {"coordinates":[11.4369096756,49.3308105469],"type":"Point"}
}