{
  "type": "Feature",
  "properties": {
    "iso:country":"DE",
    "sg:address":"Konrad-Duden-Weg 41",
    "sg:city":"Frankfurt",
    "sg:phone":"+49 69/95000951",
    "sg:postcode":"60437",
    "sg:province":"Hessen",
    "wof:name":"Andreas Heinzerling",
    "wof:placetype":"venue"
},
  "geometry": {"coordinates":[8.669436,50.190289],"type":"Point"}
}