{
  "type": "Feature",
  "properties": {
    "iso:country":"DE",
    "sg:address":"Hauptstr. 30",
    "sg:city":"Nufringen",
    "sg:phone":"+49 7032/958167",
    "sg:postcode":"71154",
    "sg:province":"Baden-W\u00fcrttemberg",
    "wof:name":"Bierbar In Der Passage",
    "wof:placetype":"venue"
},
  "geometry": {"coordinates":[8.891694,48.622887],"type":"Point"}
}