{
  "type": "Feature",
  "properties": {
    "iso:country":"DE",
    "sg:address":"Steinstrasse 1+3",
    "sg:city":"Sarstedt",
    "sg:phone":"+49 5066/99945",
    "sg:postcode":"31157",
    "sg:province":"Niedersachsen",
    "wof:name":"Volksbank Sarstedt Eg",
    "wof:placetype":"venue"
},
  "geometry": {"coordinates":[9.851129,52.234055],"type":"Point"}
}