{
  "type": "Feature",
  "properties": {
    "iso:country":"DE",
    "sg:address":"Georg-Sasse-Str. 16",
    "sg:city":"Ammersbek",
    "sg:phone":"+49 40/60550440",
    "sg:postcode":"22949",
    "sg:province":"Schleswig-Holstein",
    "wof:name":"Westphal Steuer- Beratungsgesellschaft Mbh",
    "wof:placetype":"venue"
},
  "geometry": {"coordinates":[10.1494007111,53.6776428223],"type":"Point"}
}