{
  "type": "Feature",
  "properties": {
    "iso:country":"DE",
    "sg:address":"Weidkamp 85",
    "sg:city":"Essen",
    "sg:phone":"+49 201/688234",
    "sg:postcode":"45355",
    "sg:province":"Nordrhein-Westfalen",
    "wof:name":"Willi Pothmann",
    "wof:placetype":"venue"
},
  "geometry": {"coordinates":[6.9463968277,51.4782943726],"type":"Point"}
}