{
  "type": "Feature",
  "properties": {
    "iso:country":"DE",
    "sg:address":"Oldenburger Str. 234",
    "sg:city":"Wardenburg",
    "sg:phone":"+49 4407/8329",
    "sg:postcode":"26203",
    "sg:province":"Niedersachsen",
    "wof:name":"Friedrich Taubert",
    "wof:placetype":"venue"
},
  "geometry": {"coordinates":[8.195883,53.063725],"type":"Point"}
}