{
  "type": "Feature",
  "properties": {
    "iso:country":"DE",
    "sg:address":"Vorster Str. 44",
    "sg:city":"M\u00f6nchengladbach",
    "sg:phone":"+49 2161/558077",
    "sg:postcode":"41169",
    "sg:province":"Nordrhein-Westfalen",
    "wof:name":"M\u00fcdder",
    "wof:placetype":"venue"
},
  "geometry": {"coordinates":[6.3449549675,51.2035751343],"type":"Point"}
}