{
  "type": "Feature",
  "properties": {
    "iso:country":"DE",
    "sg:address":"Burgstr. 35",
    "sg:city":"Lahnstein",
    "sg:postcode":"56112",
    "sg:province":"Rheinland-Pfalz",
    "wof:name":"Renate Becker",
    "wof:placetype":"venue"
},
  "geometry": {"coordinates":[7.6076722145,50.3008460999],"type":"Point"}
}