{
  "type": "Feature",
  "properties": {
    "iso:country":"DE",
    "sg:address":"Am Tannenhof 1 A",
    "sg:city":"Siegburg",
    "sg:phone":"+49 2241/382563",
    "sg:postcode":"53721",
    "sg:province":"Nordrhein-Westfalen",
    "wof:name":"E. F\u00fctterer",
    "wof:placetype":"venue"
},
  "geometry": {"coordinates":[7.2341241837,50.8058280945],"type":"Point"}
}