{
  "type": "Feature",
  "properties": {
    "iso:country":"DE",
    "sg:address":"Bundesstr. 2",
    "sg:city":"Northeim/Hammenstedt",
    "sg:phone":"+49 5551",
    "sg:postcode":"37154",
    "sg:province":"Niedersachsen",
    "wof:name":"Auto-galerie-northeim",
    "wof:placetype":"venue"
},
  "geometry": {"coordinates":[10.0067996979,51.7066497803],"type":"Point"}
}