{
  "type": "Feature",
  "properties": {
    "iso:country":"DE",
    "sg:address":"Rostocker Str. 23-29",
    "sg:city":"Berlin",
    "sg:postcode":"13059",
    "sg:province":"Berlin",
    "wof:name":"Ambulatorium Stadtbezirk Hohensch\u00f6nhaus",
    "wof:placetype":"venue"
},
  "geometry": {"coordinates":[13.5101299286,52.5736503601],"type":"Point"}
}