{
  "type": "Feature",
  "properties": {
    "iso:country":"DE",
    "sg:address":"Heinrich-Hertz-Str. 15",
    "sg:city":"Ratzeburg",
    "sg:phone":"+49 4541/82687",
    "sg:postcode":"23909",
    "sg:province":"Schleswig-Holstein",
    "wof:name":"Helmut Bark",
    "wof:placetype":"venue"
},
  "geometry": {"coordinates":[10.742169,53.703831],"type":"Point"}
}