{
  "type": "Feature",
  "properties": {
    "iso:country":"DE",
    "sg:address":"Kohlstatt 12",
    "sg:city":"Seeg",
    "sg:phone":"+49 8364/491",
    "sg:postcode":"87637",
    "sg:province":"Bayern",
    "wof:name":"J. Schm\u00f6lz",
    "wof:placetype":"venue"
},
  "geometry": {"coordinates":[10.61971,47.663399],"type":"Point"}
}