{
  "type": "Feature",
  "properties": {
    "iso:country":"DE",
    "sg:address":"Innungstr. 6",
    "sg:city":"H\u00fcrth",
    "sg:postcode":"50354",
    "sg:province":"Nordrhein-Westfalen",
    "wof:name":"Rms Research Marketing Strategy Gmbh",
    "wof:placetype":"venue"
},
  "geometry": {"coordinates":[6.8406620026,50.8924674988],"type":"Point"}
}