{
  "type": "Feature",
  "properties": {
    "iso:country":"DE",
    "sg:address":"Eschersheimer Landstr. 329",
    "sg:city":"Frankfurt",
    "sg:phone":"+49 69/568008",
    "sg:postcode":"60320",
    "sg:province":"Hessen",
    "wof:name":"Profil-immobilien- Und Wertanlagen-service Gmbh",
    "wof:placetype":"venue"
},
  "geometry": {"coordinates":[8.6689891815,50.1410293579],"type":"Point"}
}