{
  "type": "Feature",
  "properties": {
    "iso:country":"DE",
    "sg:address":"Wiesbacher Str. 22",
    "sg:city":"Heusweiler",
    "sg:phone":"+49 6806/83927",
    "sg:postcode":"66265",
    "sg:province":"Saarland",
    "wof:name":"Albert Himmes",
    "wof:placetype":"venue"
},
  "geometry": {"coordinates":[6.9970169067,49.3545837402],"type":"Point"}
}