{
  "type": "Feature",
  "properties": {
    "iso:country":"DE",
    "sg:address":"Westerwieher Str. 250",
    "sg:city":"Rietberg",
    "sg:phone":"+49 5244/2248",
    "sg:postcode":"33397",
    "sg:province":"Nordrhein-Westfalen",
    "wof:name":"Engelbert Steinberg",
    "wof:placetype":"venue"
},
  "geometry": {"coordinates":[8.49589,51.815971],"type":"Point"}
}