{
  "type": "Feature",
  "properties": {
    "iso:country":"DE",
    "sg:address":"Rauendahlstr. 30",
    "sg:city":"Hattingen",
    "sg:phone":"+49 2324/80243",
    "sg:postcode":"45529",
    "sg:province":"Nordrhein-Westfalen",
    "wof:name":"Edmund Schipiorowski",
    "wof:placetype":"venue"
},
  "geometry": {"coordinates":[7.1790041924,51.4163742065],"type":"Point"}
}