{
  "type": "Feature",
  "properties": {
    "iso:country":"DE",
    "sg:address":"Eitzer Dorfstr. 15",
    "sg:city":"Verden",
    "sg:phone":"+49 4231/63990",
    "sg:postcode":"27283",
    "sg:province":"Niedersachsen",
    "wof:name":"Gerhard G\u00f6bbert",
    "wof:placetype":"venue"
},
  "geometry": {"coordinates":[9.282614,52.90765],"type":"Point"}
}