{
  "type": "Feature",
  "properties": {
    "iso:country":"DE",
    "sg:address":"Schillerstrasse 15B",
    "sg:city":"Albstadt",
    "sg:phone":"+49 7431/54688",
    "sg:postcode":"72458",
    "sg:province":"Baden-W\u00fcrttemberg",
    "wof:name":"Photostudio Art Photography",
    "wof:placetype":"venue"
},
  "geometry": {"coordinates":[9.022055,48.211235],"type":"Point"}
}