{
  "type": "Feature",
  "properties": {
    "iso:country":"DE",
    "sg:address":"Maschener Sch\u00fctzenstr. 137",
    "sg:city":"Seevetal",
    "sg:postcode":"21220",
    "sg:province":"Niedersachsen",
    "wof:name":"Wa Wohnanlage Dorfstr. 21 Bautr\u00e4gergesellschaft Mbh",
    "wof:placetype":"venue"
},
  "geometry": {"coordinates":[10.051474,53.403175],"type":"Point"}
}