{
  "type": "Feature",
  "properties": {
    "iso:country":"DE",
    "sg:address":"Max-Planck-Str. 12",
    "sg:city":"Villingen-Schwenningen",
    "sg:phone":"+49 7721/95170",
    "sg:postcode":"78052",
    "sg:province":"Baden-W\u00fcrttemberg",
    "wof:name":"Anton Rempp Nachf. Gmbh",
    "wof:placetype":"venue"
},
  "geometry": {"coordinates":[8.448661,48.079811],"type":"Point"}
}