{
  "type": "Feature",
  "properties": {
    "iso:country":"DE",
    "sg:address":"Wohngebiet Ost 9",
    "sg:city":"Ferdinandshof",
    "sg:phone":"+49 39778/20415",
    "sg:postcode":"17379",
    "sg:province":"Mecklenburg-Vorpommern",
    "wof:name":"Krankenpflege C. Freese",
    "wof:placetype":"venue"
},
  "geometry": {"coordinates":[13.888791,53.664211],"type":"Point"}
}