{
  "type": "Feature",
  "properties": {
    "iso:country":"DE",
    "sg:address":"Moordeicher Landstr. 17",
    "sg:city":"Stuhr",
    "sg:phone":"+49 421/560486",
    "sg:postcode":"28816",
    "sg:province":"Niedersachsen",
    "wof:name":"Max Lemke",
    "wof:placetype":"venue"
},
  "geometry": {"coordinates":[8.70987,53.018993],"type":"Point"}
}