{
  "type": "Feature",
  "properties": {
    "iso:country":"DE",
    "sg:address":"Spitalfeldstr. 26",
    "sg:city":"Landsberg",
    "sg:phone":"+49 8191/922341",
    "sg:postcode":"86899",
    "sg:province":"Bayern",
    "wof:name":"Image Grafik-design Gmbh",
    "wof:placetype":"venue"
},
  "geometry": {"coordinates":[10.888026,48.051517],"type":"Point"}
}