{
  "type": "Feature",
  "properties": {
    "iso:country":"DE",
    "sg:address":"Bruchstr. 33",
    "sg:city":"Essen",
    "sg:phone":"+49 201/367268",
    "sg:postcode":"45327",
    "sg:province":"Nordrhein-Westfalen",
    "wof:name":"Haus W. Nobermann",
    "wof:placetype":"venue"
},
  "geometry": {"coordinates":[7.027780056,51.4954147339],"type":"Point"}
}