{
  "type": "Feature",
  "properties": {
    "iso:country":"DE",
    "sg:address":"Hans-Holbein-Str. 51",
    "sg:city":"Menden",
    "sg:phone":"+49 2373/4278",
    "sg:postcode":"58706",
    "sg:province":"Nordrhein-Westfalen",
    "wof:name":"R\u00fcberg-bau Gmbh",
    "wof:placetype":"venue"
},
  "geometry": {"coordinates":[7.809103,51.446655],"type":"Point"}
}