{
  "type": "Feature",
  "properties": {
    "iso:country":"DE",
    "sg:address":"Kaiserstr. 11",
    "sg:city":"Frankfurt",
    "sg:phone":"+49 69/291481",
    "sg:postcode":"60311",
    "sg:province":"Hessen",
    "wof:name":"Spinnrad Gmbh",
    "wof:placetype":"venue"
},
  "geometry": {"coordinates":[8.676167,50.111038],"type":"Point"}
}