{
  "type": "Feature",
  "properties": {
    "iso:country":"DE",
    "sg:address":"Plantagenweg 10",
    "sg:city":"Burgdorf",
    "sg:phone":"+49 5136/5235",
    "sg:postcode":"31303",
    "sg:province":"Niedersachsen",
    "wof:name":"Alfred Stadtl\u00e4nder K\u00fchlanlagenbau Gmbh",
    "wof:placetype":"venue"
},
  "geometry": {"coordinates":[10.031535,52.455044],"type":"Point"}
}