{
  "type": "Feature",
  "properties": {
    "iso:country":"DE",
    "sg:address":"Ober-Reeswinkel 35",
    "sg:city":"Schalksm\u00fchle",
    "sg:phone":"+49 30/4532437",
    "sg:postcode":"58579",
    "sg:province":"Nordrhein-Westfalen",
    "wof:name":"Gerhard Paulmann",
    "wof:placetype":"venue"
},
  "geometry": {"coordinates":[7.5129218102,51.2430763245],"type":"Point"}
}