{
  "type": "Feature",
  "properties": {
    "iso:country":"DE",
    "sg:address":"Bahnhofstr 21",
    "sg:city":"Welgesheim",
    "sg:phone":"+49 6701/93930",
    "sg:postcode":"55576",
    "sg:province":"Rheinland-Pfalz",
    "wof:name":"Eckert & Woelk Gmbh",
    "wof:placetype":"venue"
},
  "geometry": {"coordinates":[7.9601531029,49.8805236816],"type":"Point"}
}