{
  "type": "Feature",
  "properties": {
    "iso:country":"DE",
    "sg:address":"Schleizer Stra\u00dfe 100",
    "sg:city":"Hof",
    "sg:phone":"+49 9281",
    "sg:postcode":"95030",
    "sg:province":"Bayern",
    "wof:name":"Viessmann Gmbh & Co",
    "wof:placetype":"venue"
},
  "geometry": {"coordinates":[11.9079170227,50.3433647156],"type":"Point"}
}