{
  "type": "Feature",
  "properties": {
    "iso:country":"DE",
    "sg:address":"Gundelfinger Str. 25",
    "sg:city":"Freiburg",
    "sg:phone":"+49 761/552674",
    "sg:postcode":"79108",
    "sg:province":"Baden-W\u00fcrttemberg",
    "wof:name":"Johannes Hammer Nachf. Gmbh",
    "wof:placetype":"venue"
},
  "geometry": {"coordinates":[7.8623127937,48.030002594],"type":"Point"}
}