{
  "type": "Feature",
  "properties": {
    "iso:country":"DE",
    "sg:address":"M\u00fchlviertelstr. 14",
    "sg:city":"Hengersberg",
    "sg:phone":"+49 9901/7207",
    "sg:postcode":"94491",
    "sg:province":"Bayern",
    "wof:name":"Manfred Urban",
    "wof:placetype":"venue"
},
  "geometry": {"coordinates":[13.0500478745,48.7835922241],"type":"Point"}
}