{
  "type": "Feature",
  "properties": {
    "iso:country":"DE",
    "sg:address":"Unterstr. 4",
    "sg:city":"Oppertshausen",
    "sg:postcode":"55469",
    "sg:province":"Rheinland-Pfalz",
    "wof:name":"Michael Winn",
    "wof:placetype":"venue"
},
  "geometry": {"coordinates":[7.4738688469,49.9468955994],"type":"Point"}
}