{
  "type": "Feature",
  "properties": {
    "iso:country":"DE",
    "sg:address":"Wilhelmstr. 47",
    "sg:city":"Ibbenb\u00fcren",
    "sg:phone":"+49 5451/16540",
    "sg:postcode":"49477",
    "sg:province":"Nordrhein-Westfalen",
    "wof:name":"Zur Sonne",
    "wof:placetype":"venue"
},
  "geometry": {"coordinates":[7.7256698608,52.2739219666],"type":"Point"}
}