{
  "type": "Feature",
  "properties": {
    "iso:country":"DE",
    "sg:address":"Schulstr. 1",
    "sg:city":"Altenberg",
    "sg:phone":"+49 35056/35234",
    "sg:postcode":"01773",
    "sg:province":"Sachsen",
    "wof:name":"Birgit Lisk Und G\u00fcnther Walther",
    "wof:placetype":"venue"
},
  "geometry": {"coordinates":[13.758486,50.764633],"type":"Point"}
}