{
  "type": "Feature",
  "properties": {
    "iso:country":"DE",
    "sg:address":"Schlierachstr. 9 a",
    "sg:city":"Hausham",
    "sg:phone":"+49 8026/8624",
    "sg:postcode":"83734",
    "sg:province":"Bayern",
    "wof:name":"Manfred Peis Heilpraktiker",
    "wof:placetype":"venue"
},
  "geometry": {"coordinates":[11.8320903778,47.7497634888],"type":"Point"}
}