{
  "type": "Feature",
  "properties": {
    "iso:country":"DE",
    "sg:address":"Bahnhofstr. 40",
    "sg:city":"Hammelburg",
    "sg:phone":"+49 9732/2339",
    "sg:postcode":"97762",
    "sg:province":"Bayern",
    "wof:name":"Anton Schreiner",
    "wof:placetype":"venue"
},
  "geometry": {"coordinates":[9.8879289627,50.1178970337],"type":"Point"}
}