{
  "type": "Feature",
  "properties": {
    "iso:country":"DE",
    "sg:address":"Burgstr. 2",
    "sg:city":"Hildesheim",
    "sg:phone":"+49 5121/134494",
    "sg:postcode":"31134",
    "sg:province":"Niedersachsen",
    "wof:name":"Sch\u00e4rling",
    "wof:placetype":"venue"
},
  "geometry": {"coordinates":[9.944541,52.150089],"type":"Point"}
}