{
  "type": "Feature",
  "properties": {
    "iso:country":"DE",
    "sg:address":"Markt 17",
    "sg:city":"Bad Salzungen",
    "sg:phone":"+49 3695/605336",
    "sg:postcode":"36433",
    "sg:province":"Th\u00fcringen",
    "wof:name":"Helmut Eckardt",
    "wof:placetype":"venue"
},
  "geometry": {"coordinates":[10.236674,50.813129],"type":"Point"}
}