{
  "type": "Feature",
  "properties": {
    "iso:country":"DE",
    "sg:address":"Am Zollstock 2",
    "sg:city":"Karlsdorf-Neuthard",
    "sg:postcode":"76689",
    "sg:province":"Baden-W\u00fcrttemberg",
    "wof:name":"Ewald Und Josef Lackus Ohg",
    "wof:placetype":"venue"
},
  "geometry": {"coordinates":[8.5536003113,49.1411209106],"type":"Point"}
}