{
  "type": "Feature",
  "properties": {
    "iso:country":"DE",
    "sg:address":"Mozartstr. 4",
    "sg:city":"Lehrensteinsfeld",
    "sg:phone":"+49 7134/21609",
    "sg:postcode":"74251",
    "sg:province":"Baden-W\u00fcrttemberg",
    "wof:name":"Politt-immobilien",
    "wof:placetype":"venue"
},
  "geometry": {"coordinates":[9.3186330795,49.1297798157],"type":"Point"}
}