{
  "type": "Feature",
  "properties": {
    "iso:country":"DE",
    "sg:address":"M\u00f6llensdorfer Str. 13",
    "sg:city":"Lutherstadt Wittenberg",
    "sg:phone":"+49 3491/62330",
    "sg:postcode":"06886",
    "sg:province":"Sachsen-Anhalt",
    "wof:name":"Graf-bau Wittenberg Gmbh",
    "wof:placetype":"venue"
},
  "geometry": {"coordinates":[12.592132,51.879204],"type":"Point"}
}