{
  "type": "Feature",
  "properties": {
    "iso:country":"DE",
    "sg:address":"Sommerlandstr. 96",
    "sg:city":"Bedburg-Hau",
    "sg:phone":"+49 2821/9425",
    "sg:postcode":"47551",
    "sg:province":"Nordrhein-Westfalen",
    "wof:name":"E. Biermann",
    "wof:placetype":"venue"
},
  "geometry": {"coordinates":[6.2056818008,51.785823822],"type":"Point"}
}