{
  "type": "Feature",
  "properties": {
    "iso:country":"DE",
    "sg:address":"P\u00f6hlmannstr. 10",
    "sg:city":"M\u00fcnchen",
    "sg:phone":"+49 89/566931",
    "sg:postcode":"80687",
    "sg:province":"Bayern",
    "wof:name":"Klaus H. M\u00fcller Architekt",
    "wof:placetype":"venue"
},
  "geometry": {"coordinates":[11.49978,48.141418],"type":"Point"}
}