{
  "type": "Feature",
  "properties": {
    "iso:country":"DE",
    "sg:address":"Am Ballo 49",
    "sg:city":"Hemer",
    "sg:phone":"+49 2372/92980",
    "sg:postcode":"58675",
    "sg:province":"Nordrhein-Westfalen",
    "wof:name":"Oel Nolte Environmental Consulting Gmbh",
    "wof:placetype":"venue"
},
  "geometry": {"coordinates":[7.7598562241,51.3732223511],"type":"Point"}
}