{
  "type": "Feature",
  "properties": {
    "iso:country":"DE",
    "sg:address":"Zum Breen 30",
    "sg:city":"Rastede",
    "sg:postcode":"26180",
    "sg:province":"Niedersachsen",
    "wof:name":"Msb Komplett Bautr\u00e4ger Und Sanierungs Gmbh",
    "wof:placetype":"venue"
},
  "geometry": {"coordinates":[8.197834,53.233215],"type":"Point"}
}