{
  "type": "Feature",
  "properties": {
    "iso:country":"DE",
    "sg:address":"Ginsterweg 1",
    "sg:city":"Steyerberg",
    "sg:phone":"+49 5764/942883",
    "sg:postcode":"31595",
    "sg:province":"Niedersachsen",
    "wof:name":"Institut Sikor",
    "wof:placetype":"venue"
},
  "geometry": {"coordinates":[9.024052,52.585815],"type":"Point"}
}