{
  "type": "Feature",
  "properties": {
    "iso:country":"DE",
    "sg:address":"Gr\u00fcnewaldstr. 8",
    "sg:city":"Reutlingen",
    "sg:phone":"+49 7121/601213",
    "sg:postcode":"72768",
    "sg:province":"Baden-W\u00fcrttemberg",
    "wof:name":"Siegfried Pfanner",
    "wof:placetype":"venue"
},
  "geometry": {"coordinates":[9.1796302795,48.5183677673],"type":"Point"}
}