{
  "type": "Feature",
  "properties": {
    "iso:country":"DE",
    "sg:address":"Pr\u00e4sidentenstr. 33",
    "sg:city":"Bergkamen",
    "sg:phone":"+49 2307/87447",
    "sg:postcode":"59192",
    "sg:province":"Nordrhein-Westfalen",
    "wof:name":"Elli Trampnau",
    "wof:placetype":"venue"
},
  "geometry": {"coordinates":[7.639836,51.619282],"type":"Point"}
}