{
  "type": "Feature",
  "properties": {
    "iso:country":"DE",
    "sg:address":"Misburger Str. 89",
    "sg:city":"Hannover",
    "sg:phone":"+49 511/571077",
    "sg:postcode":"30625",
    "sg:province":"Niedersachsen",
    "wof:name":"Ax Air Gmbh",
    "wof:placetype":"venue"
},
  "geometry": {"coordinates":[9.8121843338,52.3801689148],"type":"Point"}
}