{
  "type": "Feature",
  "properties": {
    "iso:country":"DE",
    "sg:address":"Vermontstra\u00dfe 4",
    "sg:city":"Kornwestheim",
    "sg:phone":"+49 7141/925247",
    "sg:postcode":"70806",
    "sg:province":"Baden-W\u00fcrttemberg",
    "wof:name":"Fun-sailing - Yachtcharter, Mitsegelt\u00f6rns Und Meer",
    "wof:placetype":"venue"
},
  "geometry": {"coordinates":[9.22064,48.87254],"type":"Point"}
}