{
  "type": "Feature",
  "properties": {
    "iso:country":"DE",
    "sg:address":"Irmgardstr. 7",
    "sg:city":"Duisburg",
    "sg:phone":"+49 2065/31136",
    "sg:postcode":"47226",
    "sg:province":"Nordrhein-Westfalen",
    "wof:name":"Franz Kreuzkam Finanzberater",
    "wof:placetype":"venue"
},
  "geometry": {"coordinates":[6.7296380997,51.40675354],"type":"Point"}
}