{
  "type": "Feature",
  "properties": {
    "iso:country":"DE",
    "sg:address":"Lindenstr. 4c",
    "sg:city":"Pruchten",
    "sg:postcode":"18356",
    "sg:province":"Mecklenburg-Vorpommern",
    "wof:name":"Forst- Und Baumdienst Martens Gmbh",
    "wof:placetype":"venue"
},
  "geometry": {"coordinates":[12.6710977554,54.3752937317],"type":"Point"}
}