{
  "type": "Feature",
  "properties": {
    "iso:country":"DE",
    "sg:address":"Marktplatz 7",
    "sg:city":"Wiesau",
    "sg:phone":"+49 9634/914444",
    "sg:postcode":"95676",
    "sg:province":"Bayern",
    "wof:name":"Key-west Handytreff",
    "wof:placetype":"venue"
},
  "geometry": {"coordinates":[12.1836948395,49.9103088379],"type":"Point"}
}