{
  "type": "Feature",
  "properties": {
    "iso:country":"DE",
    "sg:address":"Hebelstr. 30",
    "sg:city":"Bad Bellingen",
    "sg:phone":"+49 7635/9472",
    "sg:postcode":"79415",
    "sg:province":"Baden-W\u00fcrttemberg",
    "wof:name":"G\u00fcnter Muser",
    "wof:placetype":"venue"
},
  "geometry": {"coordinates":[7.589347,47.724163],"type":"Point"}
}