{
  "type": "Feature",
  "properties": {
    "iso:country":"DE",
    "sg:address":"Postfach 105065:: 44128 Dortmund:: Germany.^^Betenstrasse 10::",
    "sg:city":"Dortmund",
    "sg:postcode":"44137",
    "sg:province":"Nordrhein-Westfalen",
    "wof:name":"Dr Schmitt Unternehmensberatung Gmbh",
    "wof:placetype":"venue"
},
  "geometry": {"coordinates":[9.936415,49.792793],"type":"Point"}
}