{
  "type": "Feature",
  "properties": {
    "iso:country":"DE",
    "sg:address":"Vor dem Bahnhof 5",
    "sg:city":"Monzingen",
    "sg:postcode":"55569",
    "sg:province":"Rheinland-Pfalz",
    "wof:name":"Event Light Ballon Licht Produkte U. Projekte Ohg",
    "wof:placetype":"venue"
},
  "geometry": {"coordinates":[7.593612,49.792866],"type":"Point"}
}