{
  "type": "Feature",
  "properties": {
    "iso:country":"DE",
    "sg:address":"Dotzheimer Str. 164",
    "sg:city":"Wiesbaden",
    "sg:phone":"+49 611/806536",
    "sg:postcode":"65197",
    "sg:province":"Hessen",
    "wof:name":"Aldi Gmbh & Co. Kg",
    "wof:placetype":"venue"
},
  "geometry": {"coordinates":[8.2125053406,50.0764770508],"type":"Point"}
}