{
  "type": "Feature",
  "properties": {
    "iso:country":"DE",
    "sg:address":"Behringstr. 10",
    "sg:city":"Planegg",
    "sg:phone":"+49 89/61453409",
    "sg:postcode":"82152",
    "sg:province":"Bayern",
    "wof:name":"Voigt Bbt Ingenieurges. F\u00fcr Bauwesen Mbh",
    "wof:placetype":"venue"
},
  "geometry": {"coordinates":[11.430005,48.109093],"type":"Point"}
}