{
  "type": "Feature",
  "properties": {
    "iso:country":"DE",
    "sg:address":"Leustetter Str.",
    "sg:city":"Frickingen",
    "sg:phone":"+49 7554/8547",
    "sg:postcode":"88699",
    "sg:province":"Baden-W\u00fcrttemberg",
    "wof:name":"E. Geiger",
    "wof:placetype":"venue"
},
  "geometry": {"coordinates":[9.2770624161,47.8129959106],"type":"Point"}
}