{
  "type": "Feature",
  "properties": {
    "iso:country":"DE",
    "sg:address":"Zeppelinstr. 9",
    "sg:city":"Nufringen",
    "sg:phone":"+49 7032/82379",
    "sg:postcode":"71154",
    "sg:province":"Baden-W\u00fcrttemberg",
    "wof:name":"Ewald Bogusch",
    "wof:placetype":"venue"
},
  "geometry": {"coordinates":[8.8835830688,48.6171913147],"type":"Point"}
}