{
  "type": "Feature",
  "properties": {
    "iso:country":"DE",
    "sg:address":"Fa\u00dflochsberg 17",
    "sg:city":"Magdeburg",
    "sg:phone":"+49 391/5438077",
    "sg:postcode":"39104",
    "sg:province":"Sachsen-Anhalt",
    "wof:name":"Hartmut Meyer",
    "wof:placetype":"venue"
},
  "geometry": {"coordinates":[11.647842,52.135101],"type":"Point"}
}