{
  "type": "Feature",
  "properties": {
    "iso:country":"DE",
    "sg:address":"H\u00e4uslerreihe 5",
    "sg:city":"Ziesendorf",
    "sg:phone":"+49 38207/70592",
    "sg:postcode":"18059",
    "sg:province":"Mecklenburg-Vorpommern",
    "wof:name":"Hans-joachim Ruge Rechtsanwalt",
    "wof:placetype":"venue"
},
  "geometry": {"coordinates":[12.0575304031,54.0014228821],"type":"Point"}
}