{
  "type": "Feature",
  "properties": {
    "iso:country":"DE",
    "sg:address":"Hauptstr. 75",
    "sg:city":"Stutensee",
    "sg:postcode":"76297",
    "sg:province":"Baden-W\u00fcrttemberg",
    "wof:name":"Iventra Gmbh",
    "wof:placetype":"venue"
},
  "geometry": {"coordinates":[8.4721508026,49.0658912659],"type":"Point"}
}