{
  "type": "Feature",
  "properties": {
    "iso:country":"DE",
    "sg:address":"Freidingstr. 11",
    "sg:city":"Hannover",
    "sg:phone":"+49 511/511553",
    "sg:postcode":"30559",
    "sg:province":"Niedersachsen",
    "wof:name":"B. Bauerochs",
    "wof:placetype":"venue"
},
  "geometry": {"coordinates":[9.8539323807,52.3604202271],"type":"Point"}
}