{
  "type": "Feature",
  "properties": {
    "iso:country":"DE",
    "sg:address":"Stuttgarter Str. 5",
    "sg:city":"Horb",
    "sg:phone":"+49 7451/2374",
    "sg:postcode":"72160",
    "sg:province":"Baden-W\u00fcrttemberg",
    "wof:name":"Josef Gramer",
    "wof:placetype":"venue"
},
  "geometry": {"coordinates":[8.693328,48.445988],"type":"Point"}
}