{
  "type": "Feature",
  "properties": {
    "iso:country":"DE",
    "sg:address":"Siemensstr. 7",
    "sg:city":"Steinbach",
    "sg:phone":"+49 6171/981414",
    "sg:postcode":"61449",
    "sg:province":"Hessen",
    "wof:name":"R. Klinger",
    "wof:placetype":"venue"
},
  "geometry": {"coordinates":[8.5861082077,50.171245575],"type":"Point"}
}