{
  "type": "Feature",
  "properties": {
    "iso:country":"DE",
    "sg:address":"Nr. 35",
    "sg:city":"Wettringen",
    "sg:postcode":"48493",
    "sg:province":"Nordrhein-Westfalen",
    "wof:name":"Kath. \u00f6ffentliche Bibliothek St. Michael",
    "wof:placetype":"venue"
},
  "geometry": {"coordinates":[7.319053,52.209267],"type":"Point"}
}