{
  "type": "Feature",
  "properties": {
    "iso:country":"DE",
    "sg:address":"Schillerstr. 32",
    "sg:city":"Erfurt",
    "sg:phone":"+49 361/301520",
    "sg:postcode":"99096",
    "sg:province":"Th\u00fcringen",
    "wof:name":"Wti Wohn- Tief- Und Industriebauges. Mbh",
    "wof:placetype":"venue"
},
  "geometry": {"coordinates":[11.032474,50.968651],"type":"Point"}
}