{
  "type": "Feature",
  "properties": {
    "iso:country":"DE",
    "sg:address":"Panoramastr. 27",
    "sg:city":"Winterlingen",
    "sg:phone":"+49 7434/315588",
    "sg:postcode":"72474",
    "sg:province":"Baden-W\u00fcrttemberg",
    "wof:name":"Lars Eckert",
    "wof:placetype":"venue"
},
  "geometry": {"coordinates":[9.1118,48.19099],"type":"Point"}
}