{
  "type": "Feature",
  "properties": {
    "iso:country":"DE",
    "sg:address":"Birkenstr. 51",
    "sg:city":"D\u00fcsseldorf",
    "sg:phone":"+49 211/660479",
    "sg:postcode":"40233",
    "sg:province":"Nordrhein-Westfalen",
    "wof:name":"Sporthaus Kaspar Thelen",
    "wof:placetype":"venue"
},
  "geometry": {"coordinates":[6.802877,51.226963],"type":"Point"}
}