{
  "type": "Feature",
  "properties": {
    "iso:country":"DE",
    "sg:address":"Cappelstr. 44 a",
    "sg:city":"Lippstadt",
    "sg:phone":"+49 2941/924150",
    "sg:postcode":"59555",
    "sg:province":"Nordrhein-Westfalen",
    "wof:name":"Ristorante Fellini",
    "wof:placetype":"venue"
},
  "geometry": {"coordinates":[8.3429422379,51.6738853455],"type":"Point"}
}