{
  "type": "Feature",
  "properties": {
    "iso:country":"DE",
    "sg:address":"Spremberger Str 5",
    "sg:city":"Cottbus",
    "sg:phone":"+49 355/823654",
    "sg:postcode":"03046",
    "sg:province":"Brandenburg",
    "wof:name":"Alpha Translation Service",
    "wof:placetype":"venue"
},
  "geometry": {"coordinates":[14.3336286545,51.7594451904],"type":"Point"}
}