{
  "type": "Feature",
  "properties": {
    "iso:country":"DE",
    "sg:address":"Spitzwiese 5",
    "sg:city":"Bad Kissingen",
    "sg:postcode":"97688",
    "sg:province":"Bayern",
    "wof:name":"Aldi Gmbh & Co. Kg",
    "wof:placetype":"venue"
},
  "geometry": {"coordinates":[10.0868206024,50.203212738],"type":"Point"}
}