{
  "type": "Feature",
  "properties": {
    "iso:country":"DE",
    "sg:address":"Habitzheimer Str. 2",
    "sg:city":"Otzberg",
    "sg:phone":"+49 6162/72267",
    "sg:postcode":"64853",
    "sg:province":"Hessen",
    "wof:name":"S. Jost",
    "wof:placetype":"venue"
},
  "geometry": {"coordinates":[8.9010696411,49.8385505676],"type":"Point"}
}