{
  "type": "Feature",
  "properties": {
    "iso:country":"DE",
    "sg:address":"Hauptstr. 55",
    "sg:city":"Sande",
    "sg:phone":"+49 4422/5223",
    "sg:postcode":"26452",
    "sg:province":"Niedersachsen",
    "wof:name":"Lothar Mehl Masseur",
    "wof:placetype":"venue"
},
  "geometry": {"coordinates":[8.017186,53.49963],"type":"Point"}
}