{
  "type": "Feature",
  "properties": {
    "iso:country":"DE",
    "sg:address":"Im Seesengrund 11",
    "sg:city":"Ober-Ramstadt",
    "sg:phone":"+49 6154/63530",
    "sg:postcode":"64372",
    "sg:province":"Hessen",
    "wof:name":"Erwin Weber Kg",
    "wof:placetype":"venue"
},
  "geometry": {"coordinates":[8.7428312302,49.8385658264],"type":"Point"}
}