{
  "type": "Feature",
  "properties": {
    "iso:country":"DE",
    "sg:address":"Owinger Str. 50",
    "sg:city":"\u00dcberlingen",
    "sg:phone":"+49 7551/4150",
    "sg:postcode":"88662",
    "sg:province":"Baden-W\u00fcrttemberg",
    "wof:name":"Erich Hindenberg",
    "wof:placetype":"venue"
},
  "geometry": {"coordinates":[9.171411,47.773441],"type":"Point"}
}