{
  "type": "Feature",
  "properties": {
    "iso:country":"DE",
    "sg:address":"Kalenwall 2",
    "sg:city":"Braunschweig",
    "sg:phone":"+49 531/2409999",
    "sg:postcode":"38100",
    "sg:province":"Niedersachsen",
    "wof:name":"Einschnitt Werbeagentur Gmbh",
    "wof:placetype":"venue"
},
  "geometry": {"coordinates":[10.517972,52.259663],"type":"Point"}
}