{
  "type": "Feature",
  "properties": {
    "iso:country":"DE",
    "sg:address":"Rosa-Luxemburg-Str. 4",
    "sg:city":"F\u00fcrstenwalde",
    "sg:phone":"+49 3361/50115",
    "sg:postcode":"15517",
    "sg:province":"Brandenburg",
    "wof:name":"Natis-pension",
    "wof:placetype":"venue"
},
  "geometry": {"coordinates":[14.0714435577,52.3492736816],"type":"Point"}
}