{
  "type": "Feature",
  "properties": {
    "iso:country":"DE",
    "sg:address":"Marktstr. 20",
    "sg:city":"Bochum",
    "sg:phone":"+49 234/582155",
    "sg:postcode":"44866",
    "sg:province":"Nordrhein-Westfalen",
    "wof:name":"Lystra Decor Und Licht Gmbh",
    "wof:placetype":"venue"
},
  "geometry": {"coordinates":[7.1412119865,51.4964103699],"type":"Point"}
}