{
  "type": "Feature",
  "properties": {
    "iso:country":"DE",
    "sg:address":"Stuttgarter Str. 90",
    "sg:city":"M\u00fchlacker",
    "sg:phone":"+49 7041/2402",
    "sg:postcode":"75417",
    "sg:province":"Baden-W\u00fcrttemberg",
    "wof:name":"Franz A\u00dfmus",
    "wof:placetype":"venue"
},
  "geometry": {"coordinates":[8.84598,48.946651],"type":"Point"}
}