{
  "type": "Feature",
  "properties": {
    "iso:country":"DE",
    "sg:address":"Hauptstr. 6",
    "sg:city":"Henfenfeld",
    "sg:phone":"+49 9151/95991",
    "sg:postcode":"91239",
    "sg:province":"Bayern",
    "wof:name":"Biohof Karl Singer",
    "wof:placetype":"venue"
},
  "geometry": {"coordinates":[11.391051,49.49976],"type":"Point"}
}