{
  "type": "Feature",
  "properties": {
    "iso:country":"DE",
    "sg:address":"Bahnhofstr. 6",
    "sg:city":"Rees",
    "sg:phone":"+49 2850/1468",
    "sg:postcode":"46459",
    "sg:province":"Nordrhein-Westfalen",
    "wof:name":"Clever M\u00f6bel Haldern",
    "wof:placetype":"venue"
},
  "geometry": {"coordinates":[6.456542,51.77227],"type":"Point"}
}