{
  "type": "Feature",
  "properties": {
    "iso:country":"DE",
    "sg:address":"Windm\u00fchlenstr. 12",
    "sg:city":"Uetze",
    "sg:phone":"+49 5147/8878",
    "sg:postcode":"31311",
    "sg:province":"Niedersachsen",
    "wof:name":"M. Veith",
    "wof:placetype":"venue"
},
  "geometry": {"coordinates":[10.091025,52.483326],"type":"Point"}
}