{
  "type": "Feature",
  "properties": {
    "iso:country":"DE",
    "sg:address":"Eisenbahnstr. 9",
    "sg:city":"Steinen",
    "sg:phone":"+49 7627/1346",
    "sg:postcode":"79585",
    "sg:province":"Baden-W\u00fcrttemberg",
    "wof:name":"Neukauf Markt Gmbh",
    "wof:placetype":"venue"
},
  "geometry": {"coordinates":[7.7401051521,47.6429100037],"type":"Point"}
}