{
  "type": "Feature",
  "properties": {
    "iso:country":"DE",
    "sg:address":"Regensburger Str. 38",
    "sg:city":"Amberg",
    "sg:phone":"+49 9621/85353",
    "sg:postcode":"92224",
    "sg:province":"Bayern",
    "wof:name":"Dr. Med. Christoph Ewald Arzt F\u00fcr Allgemeinmedizin",
    "wof:placetype":"venue"
},
  "geometry": {"coordinates":[11.8717622757,49.442237854],"type":"Point"}
}