{
  "type": "Feature",
  "properties": {
    "iso:country":"DE",
    "sg:address":"Sternstr. 61 a",
    "sg:city":"D\u00fcsseldorf",
    "sg:phone":"+49 211/494710",
    "sg:postcode":"40479",
    "sg:province":"Nordrhein-Westfalen",
    "wof:name":"A. Tokloth",
    "wof:placetype":"venue"
},
  "geometry": {"coordinates":[6.783082962,51.2351455688],"type":"Point"}
}