{
  "type": "Feature",
  "properties": {
    "iso:country":"DE",
    "sg:address":"Illersiedlung 43",
    "sg:city":"Sonthofen",
    "sg:phone":"+49 8321/3009",
    "sg:postcode":"87527",
    "sg:province":"Bayern",
    "wof:name":"Beate Schlicke-br\u00fcstle Heilpraktikerin",
    "wof:placetype":"venue"
},
  "geometry": {"coordinates":[10.2617425919,47.5144882202],"type":"Point"}
}