{
  "type": "Feature",
  "properties": {
    "iso:country":"DE",
    "sg:address":"Altmarkt 3",
    "sg:city":"Schmalkalden",
    "sg:phone":"+49 3683696902621",
    "sg:postcode":"98574",
    "sg:province":"Th\u00fcringen",
    "wof:name":"Th\u00fcringer Rennsteig-bahn Ag",
    "wof:placetype":"venue"
},
  "geometry": {"coordinates":[10.4511976242,50.7215156555],"type":"Point"}
}