{
  "type": "Feature",
  "properties": {
    "iso:country":"DE",
    "sg:address":"Postfach 1161",
    "sg:city":"Friolzheim",
    "sg:phone":"+49 7044/470",
    "sg:postcode":"71288",
    "sg:province":"Baden-W\u00fcrttemberg",
    "wof:name":"Dietrich Gmbh",
    "wof:placetype":"venue"
},
  "geometry": {"coordinates":[8.83521,48.835258],"type":"Point"}
}