{
  "type": "Feature",
  "properties": {
    "iso:country":"DE",
    "sg:address":"Auf dem B\u00e4nnjerr\u00fcck 62",
    "sg:city":"Kaiserslautern",
    "sg:phone":"+49 631/99619",
    "sg:postcode":"67663",
    "sg:province":"Rheinland-Pfalz",
    "wof:name":"Walter Dick Architekt",
    "wof:placetype":"venue"
},
  "geometry": {"coordinates":[7.736558,49.43235],"type":"Point"}
}