{
  "type": "Feature",
  "properties": {
    "iso:country":"DE",
    "sg:address":"Reichenbachstr. 9",
    "sg:city":"Karlsruhe",
    "sg:postcode":"76227",
    "sg:province":"Baden-W\u00fcrttemberg",
    "wof:name":"B\u00fcrgerzentrum S\u00fcdstadt Gmbh",
    "wof:placetype":"venue"
},
  "geometry": {"coordinates":[8.4617557526,48.9964027405],"type":"Point"}
}