{
  "type": "Feature",
  "properties": {
    "iso:country":"DE",
    "sg:address":"Am Schnettengraben 2",
    "sg:city":"Grub",
    "sg:phone":"+49 9560/980940",
    "sg:postcode":"96271",
    "sg:province":"Bayern",
    "wof:name":"Dr. Med. Gregor Matthe Arzt F\u00fcr Allgemeinmedizin",
    "wof:placetype":"venue"
},
  "geometry": {"coordinates":[11.0180654526,50.2318305969],"type":"Point"}
}