{
  "type": "Feature",
  "properties": {
    "iso:country":"DE",
    "sg:address":"Paul-Gruner-Str 12b",
    "sg:city":"Chemnitz",
    "sg:phone":"+49 371/53420",
    "sg:postcode":"09120",
    "sg:province":"Sachsen",
    "wof:name":"Lst Luft-sanit\u00e4r-klimatechnik Gmbh",
    "wof:placetype":"venue"
},
  "geometry": {"coordinates":[12.91053,50.814995],"type":"Point"}
}