{
  "type": "Feature",
  "properties": {
    "iso:country":"DE",
    "sg:address":"Eickener Str. 83",
    "sg:city":"M\u00f6nchengladbach",
    "sg:phone":"+49 2161/570850",
    "sg:postcode":"41061",
    "sg:province":"Nordrhein-Westfalen",
    "wof:name":"R&s Dental-labor Gmbh",
    "wof:placetype":"venue"
},
  "geometry": {"coordinates":[6.445336,51.201469],"type":"Point"}
}