{
  "type": "Feature",
  "properties": {
    "iso:country":"DE",
    "sg:address":"Seestr. 43",
    "sg:city":"Tegernsee",
    "sg:phone":"+49 8022/4296",
    "sg:postcode":"83684",
    "sg:province":"Bayern",
    "wof:name":"Thomas Rebensburg",
    "wof:placetype":"venue"
},
  "geometry": {"coordinates":[11.7592258453,47.7059822083],"type":"Point"}
}