{
  "type": "Feature",
  "properties": {
    "iso:country":"DE",
    "sg:address":"Delingsdorfer Weg 33a",
    "sg:city":"Hamburg",
    "sg:phone":"+49 40/6794337",
    "sg:postcode":"22143",
    "sg:province":"Hamburg",
    "wof:name":"Men At Work Gmbh",
    "wof:placetype":"venue"
},
  "geometry": {"coordinates":[10.1609382629,53.6129455566],"type":"Point"}
}