{
  "type": "Feature",
  "properties": {
    "iso:country":"DE",
    "sg:address":"Windm\u00fchlenstr. 10",
    "sg:city":"Lehrte",
    "sg:phone":"+49 5132/2981",
    "sg:postcode":"31275",
    "sg:province":"Niedersachsen",
    "wof:name":"Reinhard Seifert Masseur",
    "wof:placetype":"venue"
},
  "geometry": {"coordinates":[9.973595,52.371243],"type":"Point"}
}