{
  "type": "Feature",
  "properties": {
    "iso:country":"DE",
    "sg:address":"Ritzenschattenhalb 1",
    "sg:city":"Weitnau",
    "sg:phone":"+49 8375/92010",
    "sg:postcode":"87480",
    "sg:province":"Bayern",
    "wof:name":"B\u00dchler Kunststoffe, Farben Und Additive Gmbh",
    "wof:placetype":"venue"
},
  "geometry": {"coordinates":[10.105156,47.63818],"type":"Point"}
}