{
  "type": "Feature",
  "properties": {
    "iso:country":"DE",
    "sg:address":"Am Gallberg 20 a",
    "sg:city":"D\u00fcsseldorf",
    "sg:postcode":"40629",
    "sg:province":"Nordrhein-Westfalen",
    "wof:name":"Akura Gesellschaft F\u00fcr Haus- Und Grundbesitz Mbh",
    "wof:placetype":"venue"
},
  "geometry": {"coordinates":[6.860365,51.24749],"type":"Point"}
}