{
  "type": "Feature",
  "properties": {
    "iso:country":"DE",
    "sg:address":"Opladener Str. 22",
    "sg:city":"D\u00fcsseldorf",
    "sg:phone":"+49 211/762737",
    "sg:postcode":"40591",
    "sg:province":"Nordrhein-Westfalen",
    "wof:name":"Billen Immobilien Gmbh",
    "wof:placetype":"venue"
},
  "geometry": {"coordinates":[6.8206701279,51.1879005432],"type":"Point"}
}