{
  "type": "Feature",
  "properties": {
    "iso:country":"DE",
    "sg:address":"Albrecht-D\u00fcrer-Str. 5",
    "sg:city":"Niefern-\u00d6schelbronn",
    "sg:phone":"+49 7233/3908",
    "sg:postcode":"75223",
    "sg:province":"Baden-W\u00fcrttemberg",
    "wof:name":"Dieter Schneider",
    "wof:placetype":"venue"
},
  "geometry": {"coordinates":[8.793293,48.91407],"type":"Point"}
}