{
  "type": "Feature",
  "properties": {
    "iso:country":"DE",
    "sg:address":"Scharnebecker Weg 15",
    "sg:city":"Adendorf",
    "sg:phone":"+49 4131/98310",
    "sg:postcode":"21365",
    "sg:province":"Niedersachsen",
    "wof:name":"Tsv Adendorf V. 1923 E.v.",
    "wof:placetype":"venue"
},
  "geometry": {"coordinates":[10.45361,53.289127],"type":"Point"}
}