{
  "type": "Feature",
  "properties": {
    "iso:country":"DE",
    "sg:address":"Lindenallee 41",
    "sg:city":"Kleve",
    "sg:phone":"+49 2821/768781",
    "sg:postcode":"47533",
    "sg:province":"Nordrhein-Westfalen",
    "wof:name":"Kartoffelhaus Pelle",
    "wof:placetype":"venue"
},
  "geometry": {"coordinates":[6.1313920021,51.7823143005],"type":"Point"}
}