{
  "type": "Feature",
  "properties": {
    "iso:country":"DE",
    "sg:address":"Steinbecker Str. 99 b",
    "sg:city":"Buchholz",
    "sg:phone":"+49 4181/97904",
    "sg:postcode":"21244",
    "sg:province":"Niedersachsen",
    "wof:name":"Ideen Und Produkte Vertriebs Gmbh",
    "wof:placetype":"venue"
},
  "geometry": {"coordinates":[9.8650884628,53.3380126953],"type":"Point"}
}