{
  "type": "Feature",
  "properties": {
    "iso:country":"DE",
    "sg:address":"F\u00fcnfmeterweg 7",
    "sg:city":"Bremerhaven",
    "sg:phone":"+49 471/72585",
    "sg:postcode":"27572",
    "sg:province":"Bremen",
    "wof:name":"G\u00fcnter Schwellmus",
    "wof:placetype":"venue"
},
  "geometry": {"coordinates":[8.57822,53.523956],"type":"Point"}
}