{
  "type": "Feature",
  "properties": {
    "iso:country":"DE",
    "sg:address":"Gro\u00dfe Str. 62",
    "sg:city":"Wittenburg",
    "sg:phone":"+49 38852/52442",
    "sg:postcode":"19243",
    "sg:province":"Mecklenburg-Vorpommern",
    "wof:name":"Stadt-cafe Konsum",
    "wof:placetype":"venue"
},
  "geometry": {"coordinates":[11.071794,53.513172],"type":"Point"}
}