{
  "type": "Feature",
  "properties": {
    "iso:country":"DE",
    "sg:address":"Bahnhofstr. 5",
    "sg:city":"Ziltendorf",
    "sg:postcode":"15295",
    "sg:province":"Brandenburg",
    "wof:name":"G\u00fcnter Ott",
    "wof:placetype":"venue"
},
  "geometry": {"coordinates":[14.621715,52.205078],"type":"Point"}
}