{
  "type": "Feature",
  "properties": {
    "iso:country":"DE",
    "sg:address":"Stargarder Str. 11",
    "sg:city":"M\u00fcnchen",
    "sg:phone":"+49 89/9302099",
    "sg:postcode":"81927",
    "sg:province":"Bayern",
    "wof:name":"Fina Rent Gmbh",
    "wof:placetype":"venue"
},
  "geometry": {"coordinates":[11.637468,48.148388],"type":"Point"}
}