{
  "type": "Feature",
  "properties": {
    "iso:country":"DE",
    "sg:address":"Schillerstr. 17",
    "sg:city":"Germering",
    "sg:phone":"+49 89/89457777",
    "sg:postcode":"82110",
    "sg:province":"Bayern",
    "wof:name":"Schohmann & S\u00f6hne",
    "wof:placetype":"venue"
},
  "geometry": {"coordinates":[11.3608560562,48.1322898865],"type":"Point"}
}