{
  "type": "Feature",
  "properties": {
    "iso:country":"DE",
    "sg:address":"Fichtenweg 9",
    "sg:city":"Leutkirch",
    "sg:phone":"+49 7561/6633",
    "sg:postcode":"88299",
    "sg:province":"Baden-W\u00fcrttemberg",
    "wof:name":"Wolfgang Brutscher",
    "wof:placetype":"venue"
},
  "geometry": {"coordinates":[10.0340385437,47.8217201233],"type":"Point"}
}