{
  "type": "Feature",
  "properties": {
    "iso:country":"DE",
    "sg:address":"Obere Wiesen 11",
    "sg:city":"Donaueschingen",
    "sg:phone":"+49 771/8983490",
    "sg:postcode":"78166",
    "sg:province":"Baden-W\u00fcrttemberg",
    "wof:name":"Stolz Kunststoffspritzguss Formenbau Gmbh",
    "wof:placetype":"venue"
},
  "geometry": {"coordinates":[8.548703,47.976131],"type":"Point"}
}