{
  "type": "Feature",
  "properties": {
    "iso:country":"DE",
    "sg:address":"Gorkistr. 82",
    "sg:city":"Leipzig",
    "sg:phone":"+49 341/2311186",
    "sg:postcode":"04347",
    "sg:province":"Sachsen",
    "wof:name":"Winter",
    "wof:placetype":"venue"
},
  "geometry": {"coordinates":[12.4130916595,51.3549461365],"type":"Point"}
}