{
  "type": "Feature",
  "properties": {
    "iso:country":"DE",
    "sg:address":"Uttersh\u00e4user Str. 9",
    "sg:city":"Borken",
    "sg:phone":"+49 5682/1430",
    "sg:postcode":"34582",
    "sg:province":"Hessen",
    "wof:name":"Karl-heinz Reuter",
    "wof:placetype":"venue"
},
  "geometry": {"coordinates":[9.346691,51.064987],"type":"Point"}
}