{
  "type": "Feature",
  "properties": {
    "iso:country":"DE",
    "sg:address":"Strandpromenade 41",
    "sg:city":"Ostseebad Binz",
    "sg:phone":"+49 38393/2223",
    "sg:postcode":"18609",
    "sg:province":"Mecklenburg-Vorpommern",
    "wof:name":"Villa Salve",
    "wof:placetype":"venue"
},
  "geometry": {"coordinates":[13.6086549759,54.404964447],"type":"Point"}
}