{
  "type": "Feature",
  "properties": {
    "iso:country":"DE",
    "sg:address":"Zeppelinstr. 16",
    "sg:city":"Bensheim",
    "sg:postcode":"64625",
    "sg:province":"Hessen",
    "wof:name":"Sirus Development Gmbh",
    "wof:placetype":"venue"
},
  "geometry": {"coordinates":[8.592611,49.68671],"type":"Point"}
}