{
  "type": "Feature",
  "properties": {
    "iso:country":"DE",
    "sg:address":"Grenzhof 6",
    "sg:city":"Heidelberg",
    "sg:phone":"+49 6202/3603",
    "sg:postcode":"69123",
    "sg:province":"Baden-W\u00fcrttemberg",
    "wof:name":"Hermann Krauth",
    "wof:placetype":"venue"
},
  "geometry": {"coordinates":[8.596218,49.418266],"type":"Point"}
}