{
  "type": "Feature",
  "properties": {
    "iso:country":"DE",
    "sg:address":"Henry-Kruse-Str. 1",
    "sg:city":"Blumberg",
    "sg:phone":"+49 33394/510",
    "sg:postcode":"16356",
    "sg:province":"Brandenburg",
    "wof:name":"Hysa Hygiene Und Sauberkeit Vertriebsges. Mbh & Co. Kg",
    "wof:placetype":"venue"
},
  "geometry": {"coordinates":[13.5797243118,52.5762367249],"type":"Point"}
}