{
  "type": "Feature",
  "properties": {
    "iso:country":"DE",
    "sg:address":"Friedrichstr. 45",
    "sg:city":"Ettenheim",
    "sg:phone":"+49 7822/1363",
    "sg:postcode":"77955",
    "sg:province":"Baden-W\u00fcrttemberg",
    "wof:name":"Otto K\u00e4ufer",
    "wof:placetype":"venue"
},
  "geometry": {"coordinates":[7.813446,48.255623],"type":"Point"}
}