{
  "type": "Feature",
  "properties": {
    "iso:country":"DE",
    "sg:address":"Birkenweg 9",
    "sg:city":"Weilerswist",
    "sg:phone":"+49 2254/1516",
    "sg:postcode":"53919",
    "sg:province":"Nordrhein-Westfalen",
    "wof:name":"Gerhard Hauck Ingenieur",
    "wof:placetype":"venue"
},
  "geometry": {"coordinates":[6.8468260765,50.7595481873],"type":"Point"}
}