{
  "type": "Feature",
  "properties": {
    "iso:country":"DE",
    "sg:address":"Steinweg 49",
    "sg:city":"Geseke",
    "sg:phone":"+49 2942/1207",
    "sg:postcode":"59590",
    "sg:province":"Nordrhein-Westfalen",
    "wof:name":"Friedrich Hansj\u00fcrgens Gmbh",
    "wof:placetype":"venue"
},
  "geometry": {"coordinates":[8.472353,51.634045],"type":"Point"}
}