{
  "type": "Feature",
  "properties": {
    "iso:country":"DE",
    "sg:address":"Alte Bergstr. 10",
    "sg:city":"Simbach",
    "sg:phone":"+49 9954/585",
    "sg:postcode":"94436",
    "sg:province":"Bayern",
    "wof:name":"Fischbraterei Babel Gmbh",
    "wof:placetype":"venue"
},
  "geometry": {"coordinates":[12.7394104004,48.5665092468],"type":"Point"}
}