{
  "type": "Feature",
  "properties": {
    "iso:country":"DE",
    "sg:address":"Zur Wei\u00dfen Frau 21 a",
    "sg:city":"Brilon",
    "sg:postcode":"59929",
    "sg:province":"Nordrhein-Westfalen",
    "wof:name":"Bange Intermedia Ohg",
    "wof:placetype":"venue"
},
  "geometry": {"coordinates":[8.6858892441,51.4073600769],"type":"Point"}
}