{
  "type": "Feature",
  "properties": {
    "iso:country":"DE",
    "sg:address":"Otto-Hahn-Str. 40",
    "sg:city":"Borken",
    "sg:phone":"+49 4928/615019",
    "sg:postcode":"46325",
    "sg:province":"Nordrhein-Westfalen",
    "wof:name":"Bentler Gmbh",
    "wof:placetype":"venue"
},
  "geometry": {"coordinates":[6.8774728775,51.8573188782],"type":"Point"}
}