{
  "type": "Feature",
  "properties": {
    "iso:country":"DE",
    "sg:address":"Pistorstr. 2",
    "sg:city":"Giessen",
    "sg:phone":"+49 4964/170030",
    "sg:postcode":"35394",
    "sg:province":"Hessen",
    "wof:name":"Einrichtungsh\u00c4user R. Sommerlad Gmbh & Co.kg",
    "wof:placetype":"venue"
},
  "geometry": {"coordinates":[8.694981575,50.5678482056],"type":"Point"}
}