{
  "type": "Feature",
  "properties": {
    "iso:country":"DE",
    "sg:address":"Ostpreu\u00dfenstr. 1",
    "sg:city":"Northeim",
    "sg:phone":"+49 5551/1212",
    "sg:postcode":"37154",
    "sg:province":"Niedersachsen",
    "wof:name":"Erhard Schmidtke",
    "wof:placetype":"venue"
},
  "geometry": {"coordinates":[9.994905,51.711712],"type":"Point"}
}