{
  "type": "Feature",
  "properties": {
    "iso:country":"DE",
    "sg:address":"Am Damm 6",
    "sg:city":"Calberlah",
    "sg:phone":"+49 5374/1264",
    "sg:postcode":"38547",
    "sg:province":"Niedersachsen",
    "wof:name":"Hansj\u00fcrgen Goerke",
    "wof:placetype":"venue"
},
  "geometry": {"coordinates":[10.60617,52.429619],"type":"Point"}
}