{
  "type": "Feature",
  "properties": {
    "iso:country":"DE",
    "sg:address":"Kirchstr. 21",
    "sg:city":"Sugenheim",
    "sg:phone":"+49 9165/244",
    "sg:postcode":"91484",
    "sg:province":"Bayern",
    "wof:name":"Ev. Luth. Pfarramt",
    "wof:placetype":"venue"
},
  "geometry": {"coordinates":[10.434006691,49.6024894714],"type":"Point"}
}