{
  "type": "Feature",
  "properties": {
    "iso:country":"DE",
    "sg:address":"Weihbornstr. 5",
    "sg:city":"Neuenrade",
    "sg:phone":"+49 2394/328",
    "sg:postcode":"58809",
    "sg:province":"Nordrhein-Westfalen",
    "wof:name":"Heribert Kemper",
    "wof:placetype":"venue"
},
  "geometry": {"coordinates":[7.852976799,51.2757873535],"type":"Point"}
}