{
  "type": "Feature",
  "properties": {
    "iso:country":"DE",
    "sg:address":"Gladiolenweg 22",
    "sg:city":"Ravenstein",
    "sg:phone":"+49 6297/640",
    "sg:postcode":"74747",
    "sg:province":"Baden-W\u00fcrttemberg",
    "wof:name":"M\u00f6hler-wohnbau Gmbh",
    "wof:placetype":"venue"
},
  "geometry": {"coordinates":[9.553292,49.387718],"type":"Point"}
}