{
  "type": "Feature",
  "properties": {
    "iso:country":"DE",
    "sg:address":"Deller Str. 86",
    "sg:city":"Haan",
    "sg:postcode":"42781",
    "sg:province":"Nordrhein-Westfalen",
    "wof:name":"C. Drenker",
    "wof:placetype":"venue"
},
  "geometry": {"coordinates":[6.984143,51.191494],"type":"Point"}
}