{
  "type": "Feature",
  "properties": {
    "iso:country":"DE",
    "sg:address":"Im Dorf 14",
    "sg:city":"Nordrach",
    "sg:phone":"+49 7838/237",
    "sg:postcode":"77787",
    "sg:province":"Baden-W\u00fcrttemberg",
    "wof:name":"G\u00fcnther Geiges Cafe B\u00e4ckerei",
    "wof:placetype":"venue"
},
  "geometry": {"coordinates":[8.077617,48.396305],"type":"Point"}
}