{
  "type": "Feature",
  "properties": {
    "iso:country":"DE",
    "sg:address":"Sutthauser Str. 290",
    "sg:city":"Osnabr\u00fcck",
    "sg:postcode":"49080",
    "sg:province":"Niedersachsen",
    "wof:name":"Audi Zentrum Osnabr\u00fcck Verwaltungs Gmbh",
    "wof:placetype":"venue"
},
  "geometry": {"coordinates":[8.035495,52.248077],"type":"Point"}
}