{
  "type": "Feature",
  "properties": {
    "iso:country":"DE",
    "sg:address":"Hauptstr. 43",
    "sg:city":"Wuppertal",
    "sg:phone":"+49 202/474138",
    "sg:postcode":"42349",
    "sg:province":"Nordrhein-Westfalen",
    "wof:name":"Junker Einzelhandels Ohg",
    "wof:placetype":"venue"
},
  "geometry": {"coordinates":[7.1327738762,51.2069129944],"type":"Point"}
}