{
  "type": "Feature",
  "properties": {
    "iso:country":"DE",
    "sg:address":"Beuerner Str. 71",
    "sg:city":"Baden-Baden",
    "sg:phone":"+49 7221/992550",
    "sg:postcode":"76534",
    "sg:province":"Baden-W\u00fcrttemberg",
    "wof:name":"Mobile P\u00e4dagogische Dienste Christian Hoff",
    "wof:placetype":"venue"
},
  "geometry": {"coordinates":[8.270011,48.741653],"type":"Point"}
}