{
  "type": "Feature",
  "properties": {
    "iso:country":"DE",
    "sg:address":"Mehlemer Str.",
    "sg:city":"Wachtberg",
    "sg:phone":"+49 228/342051",
    "sg:postcode":"53343",
    "sg:province":"Nordrhein-Westfalen",
    "wof:name":"Pfarrb\u00fccherei In Niederbachem",
    "wof:placetype":"venue"
},
  "geometry": {"coordinates":[7.178864,50.646835],"type":"Point"}
}