{
  "type": "Feature",
  "properties": {
    "iso:country":"DE",
    "sg:address":"Mittelheimer Str. 15",
    "sg:city":"Wiesbaden",
    "sg:phone":"+49 611/48839",
    "sg:postcode":"65197",
    "sg:province":"Hessen",
    "wof:name":"Heinz Perbandt",
    "wof:placetype":"venue"
},
  "geometry": {"coordinates":[8.219531,50.07597],"type":"Point"}
}