{
  "type": "Feature",
  "properties": {
    "iso:country":"DE",
    "sg:address":"Hauptstr. 249",
    "sg:city":"Gersdorf",
    "sg:phone":"+49 37203/4637",
    "sg:postcode":"09355",
    "sg:province":"Sachsen",
    "wof:name":"Hotel Blauer Stern",
    "wof:placetype":"venue"
},
  "geometry": {"coordinates":[12.7077569962,50.7546234131],"type":"Point"}
}