{
  "type": "Feature",
  "properties": {
    "iso:country":"DE",
    "sg:address":"Bonner Str. 117 c",
    "sg:city":"Hennef",
    "sg:phone":"+49 2242/905670",
    "sg:postcode":"53773",
    "sg:province":"Nordrhein-Westfalen",
    "wof:name":"H. Werdein",
    "wof:placetype":"venue"
},
  "geometry": {"coordinates":[7.261373,50.773178],"type":"Point"}
}