{
  "type": "Feature",
  "properties": {
    "iso:country":"DE",
    "sg:address":"Gablonzer Str. 17",
    "sg:city":"Oberursel",
    "sg:phone":"+49 6171/62040",
    "sg:postcode":"61440",
    "sg:province":"Hessen",
    "wof:name":"Mabu-pressen Ag",
    "wof:placetype":"venue"
},
  "geometry": {"coordinates":[8.587024,50.194614],"type":"Point"}
}