{
  "type": "Feature",
  "properties": {
    "iso:country":"DE",
    "sg:address":"Schierker-Feuerstein-Platz 1-5",
    "sg:city":"Bad Lauterberg",
    "sg:phone":"+49 5524/92660",
    "sg:postcode":"37431",
    "sg:province":"Niedersachsen",
    "wof:name":"Schierker-feuerstein Kg",
    "wof:placetype":"venue"
},
  "geometry": {"coordinates":[10.4543466568,51.5953559875],"type":"Point"}
}