{
  "type": "Feature",
  "properties": {
    "iso:country":"DE",
    "sg:address":"Elbscheweg 18",
    "sg:city":"Wetter",
    "sg:phone":"+49 2335/7548",
    "sg:postcode":"58300",
    "sg:province":"Nordrhein-Westfalen",
    "wof:name":"Jochen Schlichtherle",
    "wof:placetype":"venue"
},
  "geometry": {"coordinates":[7.344191,51.402145],"type":"Point"}
}