{
  "type": "Feature",
  "properties": {
    "iso:country":"DE",
    "sg:address":"Rosbacher Weg 10",
    "sg:city":"W\u00f6llstadt",
    "sg:phone":"+49 6034/2917",
    "sg:postcode":"61206",
    "sg:province":"Hessen",
    "wof:name":"Josef Knorr",
    "wof:placetype":"venue"
},
  "geometry": {"coordinates":[8.747029,50.29731],"type":"Point"}
}