{
  "type": "Feature",
  "properties": {
    "iso:country":"DE",
    "sg:address":"Am Hang 1",
    "sg:city":"Achim",
    "sg:phone":"+49 4942/026838",
    "sg:postcode":"28832",
    "sg:province":"Niedersachsen",
    "wof:name":"Ansaldo Signal Gmbh",
    "wof:placetype":"venue"
},
  "geometry": {"coordinates":[9.055226326,52.9985237122],"type":"Point"}
}