{
  "type": "Feature",
  "properties": {
    "iso:country":"DE",
    "sg:address":"Overweg 24",
    "sg:city":"Soest",
    "sg:phone":"+49 2921/9700",
    "sg:postcode":"59494",
    "sg:province":"Nordrhein-Westfalen",
    "wof:name":"Alcoa Automotive Gmbh",
    "wof:placetype":"venue"
},
  "geometry": {"coordinates":[8.153027,51.553947],"type":"Point"}
}