{
  "type": "Feature",
  "properties": {
    "iso:country":"DE",
    "sg:address":"Fr\u00fchlingstr. 4",
    "sg:city":"Kraichtal",
    "sg:phone":"+49 7250/1382",
    "sg:postcode":"76703",
    "sg:province":"Baden-W\u00fcrttemberg",
    "wof:name":"California",
    "wof:placetype":"venue"
},
  "geometry": {"coordinates":[8.774720192,49.1385917664],"type":"Point"}
}