{
  "type": "Feature",
  "properties": {
    "iso:country":"DE",
    "sg:address":"M\u00f6hlenkamp 1",
    "sg:city":"Wrohm",
    "sg:phone":"+49 4802/1313",
    "sg:postcode":"25799",
    "sg:province":"Schleswig-Holstein",
    "wof:name":"Radtke Wbs - Internetdienste, Mobilfunk, Marketing",
    "wof:placetype":"venue"
},
  "geometry": {"coordinates":[9.377838,54.215084],"type":"Point"}
}