{
  "type": "Feature",
  "properties": {
    "iso:country":"DE",
    "sg:address":"Friedrich-Ebert-Str. 12",
    "sg:city":"\u00dcbach-Palenberg",
    "sg:phone":"+49 2451/48018",
    "sg:postcode":"52531",
    "sg:province":"Nordrhein-Westfalen",
    "wof:name":"Mann & Tellschow Maschinen-vertriebs-gmbh",
    "wof:placetype":"venue"
},
  "geometry": {"coordinates":[6.132753,50.920452],"type":"Point"}
}