{
  "type": "Feature",
  "properties": {
    "iso:country":"DE",
    "sg:address":"Dahlhauser Str. 44",
    "sg:city":"Radevormwald",
    "sg:phone":"+49 2195/7129",
    "sg:postcode":"42477",
    "sg:province":"Nordrhein-Westfalen",
    "wof:name":"Udo J\u00e4ger",
    "wof:placetype":"venue"
},
  "geometry": {"coordinates":[7.3180418015,51.2044448853],"type":"Point"}
}