{
  "type": "Feature",
  "properties": {
    "iso:country":"DE",
    "sg:address":"Heinrich-Sch\u00fctz-Str. 20",
    "sg:city":"Sindelfingen",
    "sg:phone":"+49 7031/814459",
    "sg:postcode":"71065",
    "sg:province":"Baden-W\u00fcrttemberg",
    "wof:name":"C. Weiss Ingenieur",
    "wof:placetype":"venue"
},
  "geometry": {"coordinates":[9.0189409256,48.7106819153],"type":"Point"}
}