{
  "type": "Feature",
  "properties": {
    "iso:country":"DE",
    "sg:address":"Wilder-Mann-Str. 25b",
    "sg:city":"Dresden",
    "sg:phone":"+49 351/5987464",
    "sg:postcode":"01129",
    "sg:province":"Sachsen",
    "wof:name":"Sabine Scheibe",
    "wof:placetype":"venue"
},
  "geometry": {"coordinates":[13.715767,51.091438],"type":"Point"}
}