{
  "type": "Feature",
  "properties": {
    "iso:country":"DE",
    "sg:address":"Breslauer Str. 4a",
    "sg:city":"Raisdorf",
    "sg:phone":"+49 4307/6296",
    "sg:postcode":"24223",
    "sg:province":"Schleswig-Holstein",
    "wof:name":"D. Noetzel Korrosionsschutz Und",
    "wof:placetype":"venue"
},
  "geometry": {"coordinates":[10.256114,54.273842],"type":"Point"}
}