{
  "type": "Feature",
  "properties": {
    "iso:country":"DE",
    "sg:address":"Martinstr. 2",
    "sg:city":"Veitsh\u00f6chheim",
    "sg:phone":"+49 931/900920",
    "sg:postcode":"97209",
    "sg:province":"Bayern",
    "wof:name":"Dreikant Bautr\u00e4gerges. Mbh",
    "wof:placetype":"venue"
},
  "geometry": {"coordinates":[9.875667,49.836029],"type":"Point"}
}