{
  "type": "Feature",
  "properties": {
    "iso:country":"DE",
    "sg:address":"Olympiastr. 8",
    "sg:city":"Augsburg",
    "sg:phone":"+49 821/888864",
    "sg:postcode":"86179",
    "sg:province":"Bayern",
    "wof:name":"Kmb Computer Und Netzwerk- Technik Vertriebs Gmbh",
    "wof:placetype":"venue"
},
  "geometry": {"coordinates":[10.9042644501,48.3194656372],"type":"Point"}
}