{
  "type": "Feature",
  "properties": {
    "iso:country":"DE",
    "sg:address":"Reichshofstr. 19",
    "sg:city":"Dortmund",
    "sg:phone":"+49 231/250286",
    "sg:postcode":"44309",
    "sg:province":"Nordrhein-Westfalen",
    "wof:name":"Olaf Dorgarthen",
    "wof:placetype":"venue"
},
  "geometry": {"coordinates":[7.5404472351,51.5237998962],"type":"Point"}
}