{
  "type": "Feature",
  "properties": {
    "iso:country":"DE",
    "sg:address":"Marienweg 1",
    "sg:city":"Kranenburg",
    "sg:postcode":"47559",
    "sg:province":"Nordrhein-Westfalen",
    "wof:name":"Van Bergen Holding Gmbh",
    "wof:placetype":"venue"
},
  "geometry": {"coordinates":[6.0207848549,51.7768783569],"type":"Point"}
}