{
  "type": "Feature",
  "properties": {
    "iso:country":"DE",
    "sg:address":"Johann-Hinrich-Wichern-Str. 5",
    "sg:city":"Norderstedt",
    "sg:phone":"+49 40/5478636",
    "sg:postcode":"22844",
    "sg:province":"Schleswig-Holstein",
    "wof:name":"Karl-heinz Wall",
    "wof:placetype":"venue"
},
  "geometry": {"coordinates":[10.004904747,53.7245864868],"type":"Point"}
}