{
  "type": "Feature",
  "properties": {
    "iso:country":"DE",
    "sg:address":"Am Bahnhof 2",
    "sg:city":"Kamen",
    "sg:phone":"+49 2307/72081",
    "sg:postcode":"59174",
    "sg:province":"Nordrhein-Westfalen",
    "wof:name":"Husemann-figger Beteiligungs- Gesellschaft Mbh",
    "wof:placetype":"venue"
},
  "geometry": {"coordinates":[7.659797,51.585732],"type":"Point"}
}