{
  "type": "Feature",
  "properties": {
    "iso:country":"DE",
    "sg:address":"Gumbertstr. 160",
    "sg:city":"D\u00fcsseldorf",
    "sg:phone":"+49 211/221126",
    "sg:postcode":"40229",
    "sg:province":"Nordrhein-Westfalen",
    "wof:name":"J\u00fcrgen B\u00f6hm",
    "wof:placetype":"venue"
},
  "geometry": {"coordinates":[6.8413701057,51.2003288269],"type":"Point"}
}