{
  "type": "Feature",
  "properties": {
    "iso:country":"DE",
    "sg:address":"Dietersheimer Str. 9",
    "sg:city":"Neufahrn",
    "sg:phone":"+49 8165/3790",
    "sg:postcode":"85375",
    "sg:province":"Bayern",
    "wof:name":"Heizungs- Und L\u00fcftungsanlagenbau",
    "wof:placetype":"venue"
},
  "geometry": {"coordinates":[11.6642370224,48.3120079041],"type":"Point"}
}