{
  "type": "Feature",
  "properties": {
    "iso:country":"DE",
    "sg:address":"Strandbad",
    "sg:city":"Gro\u00dfkrotzenburg",
    "sg:phone":"+49 6186/8752",
    "sg:postcode":"63538",
    "sg:province":"Hessen",
    "wof:name":"Konstantinos Birbilis",
    "wof:placetype":"venue"
},
  "geometry": {"coordinates":[8.9816951752,50.0823707581],"type":"Point"}
}