{
  "type": "Feature",
  "properties": {
    "iso:country":"DE",
    "sg:address":"Sternstr. 14 b",
    "sg:city":"Bielefeld",
    "sg:phone":"+49 5202/80579",
    "sg:postcode":"33699",
    "sg:province":"Nordrhein-Westfalen",
    "wof:name":"Hans Dieter Schultz",
    "wof:placetype":"venue"
},
  "geometry": {"coordinates":[8.6428775787,51.988697052],"type":"Point"}
}