{
  "type": "Feature",
  "properties": {
    "iso:country":"DE",
    "sg:address":"Martin-M\u00fcller-Str. 12",
    "sg:city":"Wedemark",
    "sg:phone":"+49 5130/2388",
    "sg:postcode":"30900",
    "sg:province":"Niedersachsen",
    "wof:name":"Alfred Bartsch",
    "wof:placetype":"venue"
},
  "geometry": {"coordinates":[9.679914,52.552418],"type":"Point"}
}