{
  "type": "Feature",
  "properties": {
    "iso:country":"DE",
    "sg:address":"Hauptstr. 1",
    "sg:city":"Vielbach",
    "sg:phone":"+49 2626/5643",
    "sg:postcode":"56244",
    "sg:province":"Rheinland-Pfalz",
    "wof:name":"Uwe Klein",
    "wof:placetype":"venue"
},
  "geometry": {"coordinates":[7.7726330757,50.5088615417],"type":"Point"}
}