{
  "type": "Feature",
  "properties": {
    "iso:country":"DE",
    "sg:address":"Gro\u00dfenv\u00f6rde 99",
    "sg:city":"Warmsen",
    "sg:phone":"+49 5767/1379",
    "sg:postcode":"31606",
    "sg:province":"Niedersachsen",
    "wof:name":"A. Brandt",
    "wof:placetype":"venue"
},
  "geometry": {"coordinates":[8.893004,52.431644],"type":"Point"}
}