{
  "type": "Feature",
  "properties": {
    "iso:country":"DE",
    "sg:address":"Weitzscher Garten 3",
    "sg:city":"Hofgeismar",
    "sg:phone":"+49 5671/925999",
    "sg:postcode":"34369",
    "sg:province":"Hessen",
    "wof:name":"M. Sembowski Anlagenberater",
    "wof:placetype":"venue"
},
  "geometry": {"coordinates":[9.4289093018,51.4904632568],"type":"Point"}
}