{
  "type": "Feature",
  "properties": {
    "iso:country":"DE",
    "sg:address":"Krebststr. 12",
    "sg:city":"Oranienburg",
    "sg:phone":"+49 3301/801222",
    "sg:postcode":"16515",
    "sg:province":"Brandenburg",
    "wof:name":"Gl\u00fccks Ei Eiergro\u00dfhandel Und Lebensmittel Gmbh",
    "wof:placetype":"venue"
},
  "geometry": {"coordinates":[13.2476654053,52.752784729],"type":"Point"}
}