{
  "type": "Feature",
  "properties": {
    "iso:country":"DE",
    "sg:address":"Trenkleweg 5",
    "sg:city":"M\u00fcnchen",
    "sg:phone":"+49 89/3164953",
    "sg:postcode":"80937",
    "sg:province":"Bayern",
    "wof:name":"Sportgastst\u00e4tte Harteck",
    "wof:placetype":"venue"
},
  "geometry": {"coordinates":[11.5720472336,48.2089157104],"type":"Point"}
}