{
  "type": "Feature",
  "properties": {
    "iso:country":"DE",
    "sg:address":"Zimmerstr. 20",
    "sg:city":"Bielefeld",
    "sg:phone":"+49 521/965560",
    "sg:postcode":"33602",
    "sg:province":"Nordrhein-Westfalen",
    "wof:name":"Steuerkanzlei Begger, Bielefeld",
    "wof:placetype":"venue"
},
  "geometry": {"coordinates":[8.532379,52.026402],"type":"Point"}
}