{
  "type": "Feature",
  "properties": {
    "iso:country":"DE",
    "sg:address":"Kornelim\u00fcnsterweg 1",
    "sg:city":"Aachen",
    "sg:phone":"+49 241/601459",
    "sg:postcode":"52066",
    "sg:province":"Nordrhein-Westfalen",
    "wof:name":"Hotel Forsthaus Sch\u00f6nthal",
    "wof:placetype":"venue"
},
  "geometry": {"coordinates":[6.1146087646,50.7479324341],"type":"Point"}
}