{
  "type": "Feature",
  "properties": {
    "iso:country":"DE",
    "sg:address":"Mollbergstr. 20",
    "sg:city":"Greiz",
    "sg:phone":"+49 3661/6140",
    "sg:postcode":"07973",
    "sg:province":"Th\u00fcringen",
    "wof:name":"Energiewerke Greiz Gmbh",
    "wof:placetype":"venue"
},
  "geometry": {"coordinates":[12.205928,50.655731],"type":"Point"}
}