{
  "type": "Feature",
  "properties": {
    "iso:country":"DE",
    "sg:address":"L\u00f6hlitz 30",
    "sg:city":"Waischenfeld",
    "sg:phone":"+49 9204/289",
    "sg:postcode":"91344",
    "sg:province":"Bayern",
    "wof:name":"G\u00fcnther Graf",
    "wof:placetype":"venue"
},
  "geometry": {"coordinates":[11.3619441986,49.8711585999],"type":"Point"}
}