{
  "type": "Feature",
  "properties": {
    "iso:country":"DE",
    "sg:address":"Industriestr. 1",
    "sg:city":"Ha\u00dfloch",
    "sg:phone":"+49 6324/92440",
    "sg:postcode":"67454",
    "sg:province":"Rheinland-Pfalz",
    "wof:name":"Raiffeisen Waren-zentrale Rhein-main Eg",
    "wof:placetype":"venue"
},
  "geometry": {"coordinates":[8.255143,49.371696],"type":"Point"}
}