{
  "type": "Feature",
  "properties": {
    "iso:country":"DE",
    "sg:address":"Vogelsang 12a",
    "sg:city":"Ahrensburg",
    "sg:phone":"+49 4102/31103",
    "sg:postcode":"22926",
    "sg:province":"Schleswig-Holstein",
    "wof:name":"Dietmar M. Carsten Pack Design & Promotion Gmbh",
    "wof:placetype":"venue"
},
  "geometry": {"coordinates":[10.2378120422,53.6562614441],"type":"Point"}
}