{
  "type": "Feature",
  "properties": {
    "iso:country":"DE",
    "sg:address":"Am Leimenst\u00fcck 4",
    "sg:city":"Frielendorf",
    "sg:phone":"+49 5684/220",
    "sg:postcode":"34621",
    "sg:province":"Hessen",
    "wof:name":"Arnold Hofmann",
    "wof:placetype":"venue"
},
  "geometry": {"coordinates":[9.3186969757,50.9762115479],"type":"Point"}
}