{
  "type": "Feature",
  "properties": {
    "iso:country":"DE",
    "sg:address":"Am Kirchberg 6",
    "sg:city":"Chemnitz",
    "sg:phone":"+49 371/2629568",
    "sg:postcode":"09123",
    "sg:province":"Sachsen",
    "wof:name":"Team Landschaftsbau Gmbh",
    "wof:placetype":"venue"
},
  "geometry": {"coordinates":[12.904315,50.766171],"type":"Point"}
}