{
  "type": "Feature",
  "properties": {
    "iso:country":"DE",
    "sg:address":"Hauptstr 63",
    "sg:city":"Liesenich",
    "sg:phone":"+49 6545/1825",
    "sg:postcode":"56858",
    "sg:province":"Rheinland-Pfalz",
    "wof:name":"Josef Friedrich Gmbh",
    "wof:placetype":"venue"
},
  "geometry": {"coordinates":[7.2666430473,50.0835723877],"type":"Point"}
}