{
  "type": "Feature",
  "properties": {
    "iso:country":"DE",
    "sg:address":"Lortzingstr. 8 a",
    "sg:city":"Berlin",
    "sg:phone":"+49 30/7446368",
    "sg:postcode":"12307",
    "sg:province":"Berlin",
    "wof:name":"Bernd Schliep Kunststoffe",
    "wof:placetype":"venue"
},
  "geometry": {"coordinates":[13.3963193893,52.3815155029],"type":"Point"}
}