{
  "type": "Feature",
  "properties": {
    "iso:country":"DE",
    "sg:address":"Ollenhauerring 3",
    "sg:city":"K\u00f6ln",
    "sg:phone":"+49 221/501150",
    "sg:postcode":"50829",
    "sg:province":"Nordrhein-Westfalen",
    "wof:name":"Aral Ag",
    "wof:placetype":"venue"
},
  "geometry": {"coordinates":[6.8690891266,50.9767494202],"type":"Point"}
}