{
  "type": "Feature",
  "properties": {
    "iso:country":"DE",
    "sg:address":"Waterstroate 25",
    "sg:city":"Warendorf",
    "sg:phone":"+49 2581/93820",
    "sg:postcode":"48231",
    "sg:province":"Nordrhein-Westfalen",
    "wof:name":"Klk Kunststofftechnik Inh. Vito Lomonte",
    "wof:placetype":"venue"
},
  "geometry": {"coordinates":[7.969799,51.950172],"type":"Point"}
}