{
  "type": "Feature",
  "properties": {
    "iso:country":"DE",
    "sg:address":"Steinstr. 28",
    "sg:city":"M\u00fcnchen",
    "sg:postcode":"81667",
    "sg:province":"Bayern",
    "wof:name":"Binnberg Gmbh",
    "wof:placetype":"venue"
},
  "geometry": {"coordinates":[11.59613,48.132454],"type":"Point"}
}