{
  "type": "Feature",
  "properties": {
    "iso:country":"DE",
    "sg:address":"Hornsteige 1",
    "sg:city":"Sindelfingen",
    "sg:phone":"+49 7031/671135",
    "sg:postcode":"71069",
    "sg:province":"Baden-W\u00fcrttemberg",
    "wof:name":"Restaurant El Dorado",
    "wof:placetype":"venue"
},
  "geometry": {"coordinates":[8.9389839172,48.6979980469],"type":"Point"}
}