{
  "type": "Feature",
  "properties": {
    "iso:country":"DE",
    "sg:address":"Paskaer Str. 1",
    "sg:city":"Ziegenr\u00fcck",
    "sg:phone":"+49 36483",
    "sg:postcode":"07924",
    "sg:province":"Th\u00fcringen",
    "wof:name":"Hotel Am Schlossberg Ziegenrueck",
    "wof:placetype":"venue"
},
  "geometry": {"coordinates":[11.6495141983,50.6118011475],"type":"Point"}
}