{
  "type": "Feature",
  "properties": {
    "iso:country":"DE",
    "sg:address":"Ostring 5e",
    "sg:city":"Grasbrunn",
    "sg:phone":"+49 89/46200637",
    "sg:postcode":"85630",
    "sg:province":"Bayern",
    "wof:name":"Friedhelm \u00d6lke Architekt",
    "wof:placetype":"venue"
},
  "geometry": {"coordinates":[11.768879,48.096252],"type":"Point"}
}