{
  "type": "Feature",
  "properties": {
    "iso:country":"DE",
    "sg:address":"Steinstiel 3",
    "sg:city":"Kreuzau",
    "sg:phone":"+49 2422/1572",
    "sg:postcode":"52372",
    "sg:province":"Nordrhein-Westfalen",
    "wof:name":"Maria Esser",
    "wof:placetype":"venue"
},
  "geometry": {"coordinates":[6.482044,50.739258],"type":"Point"}
}