{
  "type": "Feature",
  "properties": {
    "iso:country":"DE",
    "sg:address":"Am H\u00f6nig 23",
    "sg:city":"Retzstadt",
    "sg:phone":"+49 9364/89118",
    "sg:postcode":"97282",
    "sg:province":"Bayern",
    "wof:name":"Ckf Computer-kassen- Fachhandel Gmbh",
    "wof:placetype":"venue"
},
  "geometry": {"coordinates":[9.871472,49.909466],"type":"Point"}
}