{
  "type": "Feature",
  "properties": {
    "iso:country":"DE",
    "sg:address":"Stockweg 20",
    "sg:city":"Strullendorf",
    "sg:phone":"+49 9543/9506",
    "sg:postcode":"96129",
    "sg:province":"Bayern",
    "wof:name":"Elektro Amschler Gmbh",
    "wof:placetype":"venue"
},
  "geometry": {"coordinates":[10.967767,49.843395],"type":"Point"}
}