{
  "type": "Feature",
  "properties": {
    "iso:country":"DE",
    "sg:address":"Wilhelminenstr. 10",
    "sg:city":"Wiesbaden",
    "sg:phone":"+49 611/523650",
    "sg:postcode":"65193",
    "sg:province":"Hessen",
    "wof:name":"Rudi Herzog Bildberichterstatter",
    "wof:placetype":"venue"
},
  "geometry": {"coordinates":[8.2346439362,50.090259552],"type":"Point"}
}