{
  "type": "Feature",
  "properties": {
    "iso:country":"DE",
    "sg:address":"Luisenstr. 1",
    "sg:city":"Chemnitz",
    "sg:phone":"+49 371/3312503",
    "sg:postcode":"09113",
    "sg:province":"Sachsen",
    "wof:name":"H & H Projektmanagement Gmbh",
    "wof:placetype":"venue"
},
  "geometry": {"coordinates":[12.901412,50.842552],"type":"Point"}
}