{
  "type": "Feature",
  "properties": {
    "iso:country":"DE",
    "sg:address":"Kaiserstr. 5",
    "sg:city":"Waldshut-Tiengen",
    "sg:phone":"+49 7751/83170",
    "sg:postcode":"79761",
    "sg:province":"Baden-W\u00fcrttemberg",
    "wof:name":"A.b. Und E. Hilbert C. Simon Und",
    "wof:placetype":"venue"
},
  "geometry": {"coordinates":[8.2143764496,47.6225700378],"type":"Point"}
}