{
  "type": "Feature",
  "properties": {
    "iso:country":"DE",
    "sg:address":"Rosa-Luxemburg-Str. 7a",
    "sg:city":"M\u00fcgeln",
    "sg:phone":"+49 34362/33865",
    "sg:postcode":"04769",
    "sg:province":"Sachsen",
    "wof:name":"J. Wichor",
    "wof:placetype":"venue"
},
  "geometry": {"coordinates":[13.048609,51.234234],"type":"Point"}
}