{
  "type": "Feature",
  "properties": {
    "iso:country":"DE",
    "sg:address":"Altenburgstr. 31",
    "sg:city":"M\u00fcnchen",
    "sg:phone":"+49 89/878638",
    "sg:postcode":"81243",
    "sg:province":"Bayern",
    "wof:name":"Renate Insam",
    "wof:placetype":"venue"
},
  "geometry": {"coordinates":[11.422493,48.147617],"type":"Point"}
}