{
  "type": "Feature",
  "properties": {
    "iso:country":"DE",
    "sg:address":"Hofstr. 12",
    "sg:city":"Bad Salzuflen",
    "sg:phone":"+49 5222/797260",
    "sg:postcode":"32107",
    "sg:province":"Nordrhein-Westfalen",
    "wof:name":"Ernst-august Albert",
    "wof:placetype":"venue"
},
  "geometry": {"coordinates":[8.7368574142,52.0604820251],"type":"Point"}
}