{
  "type": "Feature",
  "properties": {
    "iso:country":"DE",
    "sg:address":"Marktstr. 3",
    "sg:city":"Iserlohn",
    "sg:phone":"+49 2374/3577",
    "sg:postcode":"58642",
    "sg:province":"Nordrhein-Westfalen",
    "wof:name":"Helga Reinke",
    "wof:placetype":"venue"
},
  "geometry": {"coordinates":[7.6115479469,51.3656425476],"type":"Point"}
}