{
  "type": "Feature",
  "properties": {
    "iso:country":"DE",
    "sg:address":"Dr.-Rudolf-Eberle-Str. 38",
    "sg:city":"Albbruck",
    "sg:phone":"+49 4977/535033",
    "sg:postcode":"79774",
    "sg:province":"Baden-W\u00fcrttemberg",
    "wof:name":"Holzparadies G\u00c4ng",
    "wof:placetype":"venue"
},
  "geometry": {"coordinates":[8.1540441513,47.6003990173],"type":"Point"}
}