{
  "type": "Feature",
  "properties": {
    "iso:country":"DE",
    "sg:address":"Heidelberger Ring 78",
    "sg:city":"Stutensee",
    "sg:phone":"+49 7249/1689",
    "sg:postcode":"76297",
    "sg:province":"Baden-W\u00fcrttemberg",
    "wof:name":"Max Weissglas Bw-kantine",
    "wof:placetype":"venue"
},
  "geometry": {"coordinates":[8.4723949432,49.0997924805],"type":"Point"}
}