{
  "type": "Feature",
  "properties": {
    "iso:country":"DE",
    "sg:address":"Unlander Str. 6",
    "sg:city":"Firrel",
    "sg:phone":"+49 4946/1299",
    "sg:postcode":"26835",
    "sg:province":"Niedersachsen",
    "wof:name":"Hans Aleschus",
    "wof:placetype":"venue"
},
  "geometry": {"coordinates":[7.662414,53.335789],"type":"Point"}
}