{
  "type": "Feature",
  "properties": {
    "iso:country":"DE",
    "sg:address":"Hauptstr. 8",
    "sg:city":"H\u00fcfingen",
    "sg:phone":"+49 771/61229",
    "sg:postcode":"78183",
    "sg:province":"Baden-W\u00fcrttemberg",
    "wof:name":"Stadt-apotheke H\u00fcfingen Dr. Carl Michael Ruyter",
    "wof:placetype":"venue"
},
  "geometry": {"coordinates":[8.488869,47.924553],"type":"Point"}
}