{
  "type": "Feature",
  "properties": {
    "iso:country":"DE",
    "sg:address":"Mittelstr. 2",
    "sg:city":"Netzschkau",
    "sg:phone":"+49 3765/34020",
    "sg:postcode":"08491",
    "sg:province":"Sachsen",
    "wof:name":"Anker-apotheke",
    "wof:placetype":"venue"
},
  "geometry": {"coordinates":[12.247142,50.612934],"type":"Point"}
}