{
  "type": "Feature",
  "properties": {
    "iso:country":"DE",
    "sg:address":"Oststr. 31",
    "sg:city":"L\u00fcnen",
    "sg:phone":"+49 2306/6736",
    "sg:postcode":"44534",
    "sg:province":"Nordrhein-Westfalen",
    "wof:name":"Ludwig Middendorf Gmbh",
    "wof:placetype":"venue"
},
  "geometry": {"coordinates":[7.5550842285,51.6300544739],"type":"Point"}
}