{
  "type": "Feature",
  "properties": {
    "iso:country":"DE",
    "sg:address":"Waldweg 15",
    "sg:city":"Moisburg",
    "sg:phone":"+49 4165/6659",
    "sg:postcode":"21647",
    "sg:province":"Niedersachsen",
    "wof:name":"Hans Buse",
    "wof:placetype":"venue"
},
  "geometry": {"coordinates":[9.6995458603,53.4090003967],"type":"Point"}
}