{
  "type": "Feature",
  "properties": {
    "iso:country":"DE",
    "sg:address":"Erlenstr. 7-8",
    "sg:city":"Gr\u00fcnheide",
    "sg:phone":"+49 3362/6152",
    "sg:postcode":"15537",
    "sg:province":"Brandenburg",
    "wof:name":"Bootshaus Am Werlsee Gmbh",
    "wof:placetype":"venue"
},
  "geometry": {"coordinates":[13.8028802872,52.418838501],"type":"Point"}
}