{
  "type": "Feature",
  "properties": {
    "iso:country":"DE",
    "sg:address":"Obere Kaiserstr. 29",
    "sg:city":"St. Ingbert",
    "sg:phone":"+49 6894/51450",
    "sg:postcode":"66386",
    "sg:province":"Saarland",
    "wof:name":"H. Zeiger",
    "wof:placetype":"venue"
},
  "geometry": {"coordinates":[7.133188,49.28598],"type":"Point"}
}