{
  "type": "Feature",
  "properties": {
    "iso:country":"DE",
    "sg:address":"Tiergartenstr. 38",
    "sg:city":"Dresden",
    "sg:postcode":"01219",
    "sg:province":"Sachsen",
    "wof:name":"Lenz Contracting Gmbh",
    "wof:placetype":"venue"
},
  "geometry": {"coordinates":[13.761174202,51.0331726074],"type":"Point"}
}