{
  "type": "Feature",
  "properties": {
    "iso:country":"DE",
    "sg:address":"Wiesenstr. 8",
    "sg:city":"Neunkirchen",
    "sg:postcode":"57290",
    "sg:province":"Nordrhein-Westfalen",
    "wof:name":"Dw Tec Gmbh",
    "wof:placetype":"venue"
},
  "geometry": {"coordinates":[7.996996,50.787941],"type":"Point"}
}