{
  "type": "Feature",
  "properties": {
    "iso:country":"DE",
    "sg:address":"Rosenstr. 2",
    "sg:city":"Mistelbach",
    "sg:phone":"+49 9201/7822",
    "sg:postcode":"95511",
    "sg:province":"Bayern",
    "wof:name":"Hummelgau-apotheke",
    "wof:placetype":"venue"
},
  "geometry": {"coordinates":[11.508705,49.912479],"type":"Point"}
}