{
  "type": "Feature",
  "properties": {
    "iso:country":"DE",
    "sg:address":"Sandbergstr. 95",
    "sg:city":"Rastede",
    "sg:phone":"+49 441/3990407",
    "sg:postcode":"26180",
    "sg:province":"Niedersachsen",
    "wof:name":"Tradis Informationssysteme & Produkthandelsgesellschaft Mbh",
    "wof:placetype":"venue"
},
  "geometry": {"coordinates":[8.2433977127,53.2024040222],"type":"Point"}
}