{
  "type": "Feature",
  "properties": {
    "iso:country":"DE",
    "sg:address":"Jean-Paul-Weg 4",
    "sg:city":"Niederf\u00fcllbach",
    "sg:phone":"+49 9565/921257",
    "sg:postcode":"96489",
    "sg:province":"Bayern",
    "wof:name":"Multi-fitness-center Active World",
    "wof:placetype":"venue"
},
  "geometry": {"coordinates":[10.9851799011,50.2143516541],"type":"Point"}
}