{
  "type": "Feature",
  "properties": {
    "iso:country":"DE",
    "sg:address":"Stolzestr. 39",
    "sg:city":"Hannover",
    "sg:postcode":"30171",
    "sg:province":"Niedersachsen",
    "wof:name":"Toscana Soft Gmbh",
    "wof:placetype":"venue"
},
  "geometry": {"coordinates":[9.758966,52.3661],"type":"Point"}
}