{
  "type": "Feature",
  "properties": {
    "iso:country":"DE",
    "sg:address":"Kamillenweg 9",
    "sg:city":"Dresden",
    "sg:postcode":"01169",
    "sg:province":"Sachsen",
    "wof:name":"Andreas Fritzsche",
    "wof:placetype":"venue"
},
  "geometry": {"coordinates":[13.656397,51.047123],"type":"Point"}
}