{
  "type": "Feature",
  "properties": {
    "iso:country":"DE",
    "sg:address":"Max-Planck-Str. 22",
    "sg:city":"Villingen-Schwenningen",
    "sg:phone":"+49 7721/63110",
    "sg:postcode":"78052",
    "sg:province":"Baden-W\u00fcrttemberg",
    "wof:name":"Velthuizen Autolackierungen Gmbh",
    "wof:placetype":"venue"
},
  "geometry": {"coordinates":[8.448502,48.082317],"type":"Point"}
}