{
  "type": "Feature",
  "properties": {
    "iso:country":"DE",
    "sg:address":"Daglfinger Str. 98",
    "sg:city":"M\u00fcnchen",
    "sg:phone":"+49 89/935117",
    "sg:postcode":"81929",
    "sg:province":"Bayern",
    "wof:name":"Herrero Sanchez \u00dcbersetzer",
    "wof:placetype":"venue"
},
  "geometry": {"coordinates":[11.65582,48.150139],"type":"Point"}
}