{
  "type": "Feature",
  "properties": {
    "iso:country":"DE",
    "sg:address":"Hummelbergstr. 15",
    "sg:city":"Dunningen",
    "sg:phone":"+49 7402/567",
    "sg:postcode":"78655",
    "sg:province":"Baden-W\u00fcrttemberg",
    "wof:name":"Gl\u00fcck Verwaltungs- Gmbh",
    "wof:placetype":"venue"
},
  "geometry": {"coordinates":[8.49538,48.24152],"type":"Point"}
}