{
  "type": "Feature",
  "properties": {
    "iso:country":"DE",
    "sg:address":"Hofstattstr. 15",
    "sg:city":"Wallhalben",
    "sg:phone":"+49 6375/1578",
    "sg:postcode":"66917",
    "sg:province":"Rheinland-Pfalz",
    "wof:name":"Erich Knerr Steuerberater",
    "wof:placetype":"venue"
},
  "geometry": {"coordinates":[7.5194201469,49.3177375793],"type":"Point"}
}