{
  "type": "Feature",
  "properties": {
    "iso:country":"DE",
    "sg:address":"K\u00f6nigstr. 44",
    "sg:city":"Hannover",
    "sg:postcode":"30175",
    "sg:province":"Niedersachsen",
    "wof:name":"Jc Sicht- Und Sonnen- Schutz Gmbh",
    "wof:placetype":"venue"
},
  "geometry": {"coordinates":[9.749557,52.376404],"type":"Point"}
}