{
  "type": "Feature",
  "properties": {
    "iso:country":"DE",
    "sg:address":"Am Sportplatz 6",
    "sg:city":"Iserlohn",
    "sg:phone":"+49 2371/42422",
    "sg:postcode":"58640",
    "sg:province":"Nordrhein-Westfalen",
    "wof:name":"Ute Sekulla Heilpraktikerin",
    "wof:placetype":"venue"
},
  "geometry": {"coordinates":[7.6650137901,51.4217796326],"type":"Point"}
}