{
  "type": "Feature",
  "properties": {
    "iso:country":"DE",
    "sg:address":"Lange Str. 15",
    "sg:city":"Harpstedt",
    "sg:phone":"+49 4244/1460",
    "sg:postcode":"27243",
    "sg:province":"Niedersachsen",
    "wof:name":"Le Bistro",
    "wof:placetype":"venue"
},
  "geometry": {"coordinates":[8.587269783,52.9081611633],"type":"Point"}
}