{
  "type": "Feature",
  "properties": {
    "iso:country":"DE",
    "sg:address":"Industriestr 9",
    "sg:city":"Saarbr\u00fccken",
    "sg:phone":"+49 6805/807275",
    "sg:postcode":"66129",
    "sg:province":"Saarland",
    "wof:name":"Altrans Speditions Gmbh",
    "wof:placetype":"venue"
},
  "geometry": {"coordinates":[7.0369291306,49.1827583313],"type":"Point"}
}