{
  "type": "Feature",
  "properties": {
    "iso:country":"DE",
    "sg:address":"Goethestr. 15",
    "sg:city":"Wetter",
    "sg:phone":"+49 2335/62509",
    "sg:postcode":"58300",
    "sg:province":"Nordrhein-Westfalen",
    "wof:name":"H. Herzog Rechtsanwalt",
    "wof:placetype":"venue"
},
  "geometry": {"coordinates":[7.3716220856,51.37317276],"type":"Point"}
}