{
  "type": "Feature",
  "properties": {
    "iso:country":"DE",
    "sg:address":"Seebruchstr. 41",
    "sg:city":"Vlotho",
    "sg:postcode":"32602",
    "sg:province":"Nordrhein-Westfalen",
    "wof:name":"B\u00e4dergemeinschaft Ostwest- Falen F\u00fcr Moorgewinnung Und",
    "wof:placetype":"venue"
},
  "geometry": {"coordinates":[8.85322,52.133259],"type":"Point"}
}