{
  "type": "Feature",
  "properties": {
    "iso:country":"DE",
    "sg:address":"Bahnhofstr. 25",
    "sg:city":"Krumbach",
    "sg:phone":"+49 8282/2309",
    "sg:postcode":"86381",
    "sg:province":"Bayern",
    "wof:name":"Gasthaus Barbara Sieb",
    "wof:placetype":"venue"
},
  "geometry": {"coordinates":[10.3608970642,48.2447433472],"type":"Point"}
}