{
  "type": "Feature",
  "properties": {
    "iso:country":"DE",
    "sg:address":"Ziegelh\u00fcttenweg 45",
    "sg:city":"Frankfurt",
    "sg:phone":"+49 69/6300090",
    "sg:postcode":"60598",
    "sg:province":"Hessen",
    "wof:name":"Gmt Gesellschaft F\u00fcr Medizintechnik M.b.h.",
    "wof:placetype":"venue"
},
  "geometry": {"coordinates":[8.679566,50.091007],"type":"Point"}
}