{
  "type": "Feature",
  "properties": {
    "iso:country":"DE",
    "sg:address":"Kallm\u00fcnzer Str. 23",
    "sg:city":"Burglengenfeld",
    "sg:phone":"+49 9471/6324",
    "sg:postcode":"93133",
    "sg:province":"Bayern",
    "wof:name":"Edmund Glatzl Ursula Glatzl",
    "wof:placetype":"venue"
},
  "geometry": {"coordinates":[12.0379858017,49.2024345398],"type":"Point"}
}