{
  "type": "Feature",
  "properties": {
    "iso:country":"DE",
    "sg:address":"Am Knick 39",
    "sg:city":"Sundern",
    "sg:phone":"+49 2933/2704",
    "sg:postcode":"59846",
    "sg:province":"Nordrhein-Westfalen",
    "wof:name":"Parkett Karlheinz Kahn",
    "wof:placetype":"venue"
},
  "geometry": {"coordinates":[8.0173587799,51.3203659058],"type":"Point"}
}