{
  "type": "Feature",
  "properties": {
    "iso:country":"DE",
    "sg:address":"Wielandstr. 34b",
    "sg:city":"Kirkel",
    "sg:phone":"+49 6849/91504",
    "sg:postcode":"66459",
    "sg:province":"Saarland",
    "wof:name":"D\u00f6rr & Klee",
    "wof:placetype":"venue"
},
  "geometry": {"coordinates":[7.2383828163,49.287109375],"type":"Point"}
}