{
  "type": "Feature",
  "properties": {
    "iso:country":"DE",
    "sg:address":"Hauptstr. 85",
    "sg:city":"Sontheim",
    "sg:phone":"+49 7325/5334",
    "sg:postcode":"89567",
    "sg:province":"Baden-W\u00fcrttemberg",
    "wof:name":"Gasthaus Albert H\u00f6rger",
    "wof:placetype":"venue"
},
  "geometry": {"coordinates":[10.2936182022,48.5505447388],"type":"Point"}
}