{
  "type": "Feature",
  "properties": {
    "iso:country":"DE",
    "sg:address":"Neinstedter Str.",
    "sg:city":"Thale",
    "sg:postcode":"06502",
    "sg:province":"Sachsen-Anhalt",
    "wof:name":"Aldi Gmbh & Co. Kg",
    "wof:placetype":"venue"
},
  "geometry": {"coordinates":[11.0570554733,51.7529907227],"type":"Point"}
}