{
  "type": "Feature",
  "properties": {
    "iso:country":"DE",
    "sg:address":"Bernstorffstra\u00dfe 99",
    "sg:city":"Hamburg",
    "sg:classifiers":[
        {
            "category":"Professional",
            "subcategory":"Computer Services",
            "type":"Services"
        }
    ],
    "sg:postcode":"22765",
    "sg:tags":[
        "audio-radio-live"
    ],
    "sg:website":"http://www.1000mikes.com",
    "wof:name":"1000MIKES",
    "wof:placetype":"venue"
},
  "geometry": {"coordinates":[9.9584473,53.5571845],"type":"Point"}
}