{
  "type": "Feature",
  "properties": {
    "iso:country":"DE",
    "sg:address":"Feldbergstr. 15",
    "sg:city":"Neuenb\u00fcrg",
    "sg:phone":"+49 7082/2615",
    "sg:postcode":"75305",
    "sg:province":"Baden-W\u00fcrttemberg",
    "wof:name":"Carol-ann Laux",
    "wof:placetype":"venue"
},
  "geometry": {"coordinates":[8.579364,48.848228],"type":"Point"}
}