{
  "type": "Feature",
  "properties": {
    "iso:country":"DE",
    "sg:address":"Mengendamm 18",
    "sg:city":"Hannover",
    "sg:postcode":"30177",
    "sg:province":"Niedersachsen",
    "wof:name":"Verm\u00f6gensverwaltung Kirsten Henke Gmbh & Co. Kg",
    "wof:placetype":"venue"
},
  "geometry": {"coordinates":[9.7586250305,52.3987045288],"type":"Point"}
}