{
  "type": "Feature",
  "properties": {
    "iso:country":"DE",
    "sg:address":"Nonnenbergweg 2",
    "sg:city":"Bochum",
    "sg:postcode":"44879",
    "sg:province":"Nordrhein-Westfalen",
    "wof:name":"Reinhard Pohl",
    "wof:placetype":"venue"
},
  "geometry": {"coordinates":[7.1640467644,51.4176635742],"type":"Point"}
}