{
  "type": "Feature",
  "properties": {
    "iso:country":"DE",
    "sg:address":"Naunheimer Str. 2",
    "sg:city":"Lahnau",
    "sg:phone":"+49 6441/963188",
    "sg:postcode":"35633",
    "sg:province":"Hessen",
    "wof:name":"J\u00f6rg Br\u00f6mer",
    "wof:placetype":"venue"
},
  "geometry": {"coordinates":[8.5517721176,50.5852355957],"type":"Point"}
}