{
  "type": "Feature",
  "properties": {
    "iso:country":"DE",
    "sg:address":"Sch\u00f6ninger Str. 14",
    "sg:city":"Sickte",
    "sg:phone":"+49 5305/1348",
    "sg:postcode":"38173",
    "sg:province":"Niedersachsen",
    "wof:name":"E. Bock Kg",
    "wof:placetype":"venue"
},
  "geometry": {"coordinates":[10.637348175,52.2190704346],"type":"Point"}
}