{
  "type": "Feature",
  "properties": {
    "iso:country":"DE",
    "sg:address":"Teucheler Weg 21",
    "sg:city":"Lutherstadt Wittenberg",
    "sg:postcode":"06886",
    "sg:province":"Sachsen-Anhalt",
    "wof:name":"Wohnungs- Und Selbsthilfe E. V.",
    "wof:placetype":"venue"
},
  "geometry": {"coordinates":[12.6488218307,51.8844718933],"type":"Point"}
}