{
  "type": "Feature",
  "properties": {
    "iso:country":"DE",
    "sg:address":"Konrad-Adenauer-Platz 2",
    "sg:city":"Bergisch Gladbach",
    "sg:phone":"+49 2202/32623",
    "sg:postcode":"51465",
    "sg:province":"Nordrhein-Westfalen",
    "wof:name":"Hotel Am Bock",
    "wof:placetype":"venue"
},
  "geometry": {"coordinates":[7.1300568581,50.9920578003],"type":"Point"}
}