{
  "type": "Feature",
  "properties": {
    "iso:country":"DE",
    "sg:address":"Johannes-Kepler-Str. 4",
    "sg:city":"Stuhr",
    "sg:phone":"+49 421/566120",
    "sg:postcode":"28816",
    "sg:province":"Niedersachsen",
    "wof:name":"Anita Bartsch Pumpen- Und",
    "wof:placetype":"venue"
},
  "geometry": {"coordinates":[8.772187,53.01968],"type":"Point"}
}