{
  "type": "Feature",
  "properties": {
    "iso:country":"DE",
    "sg:address":"Brackeler Hellweg 132",
    "sg:city":"Dortmund",
    "sg:phone":"+49 231/258473",
    "sg:postcode":"44309",
    "sg:province":"Nordrhein-Westfalen",
    "wof:name":"B. Zimmer",
    "wof:placetype":"venue"
},
  "geometry": {"coordinates":[7.545326,51.523632],"type":"Point"}
}