{
  "type": "Feature",
  "properties": {
    "iso:country":"DE",
    "sg:address":"Metzenweg 78",
    "sg:city":"M\u00f6nchengladbach",
    "sg:phone":"+49 2161",
    "sg:postcode":"41068",
    "sg:province":"Nordrhein-Westfalen",
    "wof:name":"Zahnlabor Walter Kurdal",
    "wof:placetype":"venue"
},
  "geometry": {"coordinates":[6.415738,51.200722],"type":"Point"}
}