{
  "type": "Feature",
  "properties": {
    "iso:country":"DE",
    "sg:address":"Bahnhofstr 14",
    "sg:city":"Wolfsburg",
    "sg:phone":"+49 4953/6251098",
    "sg:postcode":"38440",
    "sg:province":"Niedersachsen",
    "wof:name":"Deutsche Bank Ag",
    "wof:placetype":"venue"
},
  "geometry": {"coordinates":[10.78934,52.426369],"type":"Point"}
}