{
  "type": "Feature",
  "properties": {
    "iso:country":"DE",
    "sg:address":"Lindauer Str. 64",
    "sg:city":"Trebgast",
    "sg:phone":"+49 9227/384",
    "sg:postcode":"95367",
    "sg:province":"Bayern",
    "wof:name":"Zimmerei Manfred K\u00fcfner",
    "wof:placetype":"venue"
},
  "geometry": {"coordinates":[11.5491800308,50.0672302246],"type":"Point"}
}