{
  "type": "Feature",
  "properties": {
    "iso:country":"DE",
    "sg:address":"Schoenbuehlstr. 27 Pfaffenweiler",
    "sg:city":"Villingen-Schwenningen",
    "sg:phone":"+49 4926/4134286",
    "sg:postcode":"78052",
    "sg:province":"Baden-W\u00fcrttemberg",
    "wof:name":"Hansonis Gmbh",
    "wof:placetype":"venue"
},
  "geometry": {"coordinates":[7.1093997955,50.5422782898],"type":"Point"}
}