{
  "type": "Feature",
  "properties": {
    "iso:country":"DE",
    "sg:address":"M\u00fcrrigerstr. 25",
    "sg:city":"M\u00f6nchengladbach",
    "sg:phone":"+49 2166/49086",
    "sg:postcode":"41068",
    "sg:province":"Nordrhein-Westfalen",
    "wof:name":"Line Up Textilhandelsagentur Mustafa Silanoglu",
    "wof:placetype":"venue"
},
  "geometry": {"coordinates":[6.3884029388,51.2036857605],"type":"Point"}
}