{
  "type": "Feature",
  "properties": {
    "iso:country":"DE",
    "sg:address":"Ambo\u00dfstr. 23",
    "sg:city":"Wuppertal",
    "sg:phone":"+49 202/470926",
    "sg:postcode":"42349",
    "sg:province":"Nordrhein-Westfalen",
    "wof:name":"J\u00f6rg Rehse Masseur",
    "wof:placetype":"venue"
},
  "geometry": {"coordinates":[7.134398,51.207111],"type":"Point"}
}