{
  "type": "Feature",
  "properties": {
    "iso:country":"DE",
    "sg:address":"Schlo\u00dfweg 12 F",
    "sg:city":"Jessen",
    "sg:phone":"+49 3537/214835",
    "sg:postcode":"06917",
    "sg:province":"Sachsen-Anhalt",
    "wof:name":"Palm Touristik Gmbh",
    "wof:placetype":"venue"
},
  "geometry": {"coordinates":[12.8246116638,51.7881736755],"type":"Point"}
}