{
  "type": "Feature",
  "properties": {
    "iso:country":"DE",
    "sg:address":"Lange Str. 43-45::",
    "sg:city":"Halle",
    "sg:phone":"+49 4952/011810",
    "sg:postcode":"33790",
    "sg:province":"Nordrhein-Westfalen",
    "wof:name":"Volksbank Halle/westf Eg",
    "wof:placetype":"venue"
},
  "geometry": {"coordinates":[8.33043,52.044361],"type":"Point"}
}