{
  "type": "Feature",
  "properties": {
    "iso:country":"DE",
    "sg:address":"Stegemannstr. 13",
    "sg:city":"Koblenz",
    "sg:phone":"+49 261/37483",
    "sg:postcode":"56068",
    "sg:province":"Rheinland-Pfalz",
    "wof:name":"Quelle Fundgrube",
    "wof:placetype":"venue"
},
  "geometry": {"coordinates":[7.595504,50.3559],"type":"Point"}
}