{
  "type": "Feature",
  "properties": {
    "iso:country":"DE",
    "sg:address":"Bruchstr. 3",
    "sg:city":"Bad W\u00fcnnenberg",
    "sg:phone":"+49 2953/8185",
    "sg:postcode":"33181",
    "sg:province":"Nordrhein-Westfalen",
    "wof:name":"Johannes H\u00fclshoff",
    "wof:placetype":"venue"
},
  "geometry": {"coordinates":[8.6924133301,51.5190315247],"type":"Point"}
}