{
  "type": "Feature",
  "properties": {
    "iso:country":"DE",
    "sg:address":"Bischof-Josef-Str. 8",
    "sg:city":"Isen",
    "sg:phone":"+49 8083/8181",
    "sg:postcode":"84424",
    "sg:province":"Bayern",
    "wof:name":"Liebesbund-stiftung Isen",
    "wof:placetype":"venue"
},
  "geometry": {"coordinates":[12.0574588776,48.2108612061],"type":"Point"}
}