{
  "type": "Feature",
  "properties": {
    "iso:country":"DE",
    "sg:address":"Stresemannstr. 268",
    "sg:city":"Hamburg",
    "sg:phone":"+49 40/8508332",
    "sg:postcode":"22769",
    "sg:province":"Hamburg",
    "wof:name":"D. Langhals",
    "wof:placetype":"venue"
},
  "geometry": {"coordinates":[9.9335317612,53.5635643005],"type":"Point"}
}