{
  "type": "Feature",
  "properties": {
    "iso:country":"DE",
    "sg:address":"Gr\u00fcnauer Weg 2",
    "sg:city":"Rathenow",
    "sg:phone":"+49 3385/53540",
    "sg:postcode":"14712",
    "sg:province":"Brandenburg",
    "wof:name":"Havell\u00e4ndische Verkehrsgesellschaft Mbh",
    "wof:placetype":"venue"
},
  "geometry": {"coordinates":[12.341459,52.594257],"type":"Point"}
}