{
  "type": "Feature",
  "properties": {
    "iso:country":"DE",
    "sg:address":"Neuer Wall 59",
    "sg:city":"Hamburg",
    "sg:postcode":"20354",
    "sg:province":"Hamburg",
    "wof:name":"Verwaltung Grundst\u00fccksges. Mundsburger Damm 14 Mbh",
    "wof:placetype":"venue"
},
  "geometry": {"coordinates":[9.9883804321,53.5505523682],"type":"Point"}
}