{
  "type": "Feature",
  "properties": {
    "iso:country":"DE",
    "sg:address":"Hebelstr. 8",
    "sg:city":"Emmendingen",
    "sg:phone":"+49 7641/49839",
    "sg:postcode":"79312",
    "sg:province":"Baden-W\u00fcrttemberg",
    "wof:name":"Relan-reha-ladenwerkstatt Gmbh",
    "wof:placetype":"venue"
},
  "geometry": {"coordinates":[7.850681,48.121792],"type":"Point"}
}