{
  "type": "Feature",
  "properties": {
    "iso:country":"DE",
    "sg:address":"Winkel 12",
    "sg:city":"Wegeleben",
    "sg:phone":"+49 39423/6302",
    "sg:postcode":"38828",
    "sg:province":"Sachsen-Anhalt",
    "wof:name":"Fuchs",
    "wof:placetype":"venue"
},
  "geometry": {"coordinates":[11.171862,51.883774],"type":"Point"}
}