{
  "type": "Feature",
  "properties": {
    "iso:country":"DE",
    "sg:address":"S\u00fcdstr. 30",
    "sg:city":"Braunschweig",
    "sg:phone":"+49 531/124365",
    "sg:postcode":"38100",
    "sg:province":"Niedersachsen",
    "wof:name":"Helal Imbi\u00df",
    "wof:placetype":"venue"
},
  "geometry": {"coordinates":[10.5178365707,52.260761261],"type":"Point"}
}