{
  "type": "Feature",
  "properties": {
    "iso:country":"DE",
    "sg:address":"Burgunderstr. 11",
    "sg:city":"Annweiler",
    "sg:phone":"+49 6346/929769",
    "sg:postcode":"76855",
    "sg:province":"Rheinland-Pfalz",
    "wof:name":"T. Kirchhoff Ingenieur",
    "wof:placetype":"venue"
},
  "geometry": {"coordinates":[7.9716911316,49.2250289917],"type":"Point"}
}