{
  "type": "Feature",
  "properties": {
    "iso:country":"DE",
    "sg:address":"Roseggerstr. 13",
    "sg:city":"Kelkheim",
    "sg:phone":"+49 6195/62678",
    "sg:postcode":"65779",
    "sg:province":"Hessen",
    "wof:name":"Klaus Kautz Architekt",
    "wof:placetype":"venue"
},
  "geometry": {"coordinates":[8.443242,50.149151],"type":"Point"}
}