{
  "type": "Feature",
  "properties": {
    "iso:country":"DE",
    "sg:address":"Steig 4",
    "sg:city":"Erbach",
    "sg:phone":"+49 7305/6157",
    "sg:postcode":"89155",
    "sg:province":"Baden-W\u00fcrttemberg",
    "wof:name":"Anton Sp\u00e4th",
    "wof:placetype":"venue"
},
  "geometry": {"coordinates":[9.862158,48.313732],"type":"Point"}
}