{
  "type": "Feature",
  "properties": {
    "iso:country":"DE",
    "sg:address":"Beim Gerber 1",
    "sg:city":"Mittenwald",
    "sg:phone":"+49 8823/5693",
    "sg:postcode":"82481",
    "sg:province":"Bayern",
    "wof:name":"G\u00e4stehaus Karwendelschanze",
    "wof:placetype":"venue"
},
  "geometry": {"coordinates":[11.26379776,47.4304428101],"type":"Point"}
}