{
  "type": "Feature",
  "properties": {
    "iso:country":"DE",
    "sg:address":"Im Winkel 10",
    "sg:city":"Haltern",
    "sg:phone":"+49 2360/1769",
    "sg:postcode":"45721",
    "sg:province":"Nordrhein-Westfalen",
    "wof:name":"Zeltunternehmen Josef Balster E. K.",
    "wof:placetype":"venue"
},
  "geometry": {"coordinates":[7.0976810455,51.7059288025],"type":"Point"}
}