{
  "type": "Feature",
  "properties": {
    "iso:country":"DE",
    "sg:address":"Nelkenweg 32",
    "sg:city":"Kirchen",
    "sg:phone":"+49 2741/62335",
    "sg:postcode":"57548",
    "sg:province":"Rheinland-Pfalz",
    "wof:name":"Hotel-restaurant Haus Giebelwald",
    "wof:placetype":"venue"
},
  "geometry": {"coordinates":[7.9008321762,50.8175315857],"type":"Point"}
}