{
  "type": "Feature",
  "properties": {
    "iso:country":"DE",
    "sg:address":"Puricellistr. 3",
    "sg:city":"Regensburg",
    "sg:phone":"+49 941/23371",
    "sg:postcode":"93049",
    "sg:province":"Bayern",
    "wof:name":"Aral Ag",
    "wof:placetype":"venue"
},
  "geometry": {"coordinates":[12.0626249313,49.0223503113],"type":"Point"}
}