{
  "type": "Feature",
  "properties": {
    "iso:country":"DE",
    "sg:address":"Werderstr. 33",
    "sg:city":"Hamburg",
    "sg:phone":"+49 40/442418",
    "sg:postcode":"20144",
    "sg:province":"Hamburg",
    "wof:name":"Berkenhoffs Plakat Media Gmbh",
    "wof:placetype":"venue"
},
  "geometry": {"coordinates":[9.9830436707,53.5758399963],"type":"Point"}
}