{
  "type": "Feature",
  "properties": {
    "iso:country":"DE",
    "sg:address":"Osnabr\u00fccker Str. 8",
    "sg:city":"Barnstorf",
    "sg:phone":"+49 5442/2307",
    "sg:postcode":"49406",
    "sg:province":"Niedersachsen",
    "wof:name":"G\u00fcnther Meyer",
    "wof:placetype":"venue"
},
  "geometry": {"coordinates":[8.502674,52.709946],"type":"Point"}
}