{
  "type": "Feature",
  "properties": {
    "iso:country":"DE",
    "sg:address":"Am Dorfplatz 1",
    "sg:city":"Neetze",
    "sg:phone":"+49 5850/1258",
    "sg:postcode":"21398",
    "sg:province":"Niedersachsen",
    "wof:name":"Apotheke Am Dorfplatz",
    "wof:placetype":"venue"
},
  "geometry": {"coordinates":[10.624442,53.265148],"type":"Point"}
}