{
  "type": "Feature",
  "properties": {
    "iso:country":"DE",
    "sg:address":"Bischofsburger Str. 3",
    "sg:city":"Neuwied",
    "sg:phone":"+49 2631/89940",
    "sg:postcode":"56566",
    "sg:province":"Rheinland-Pfalz",
    "wof:name":"S & E Sonderabfall Gmbh",
    "wof:placetype":"venue"
},
  "geometry": {"coordinates":[7.4940190315,50.4405441284],"type":"Point"}
}