{
  "type": "Feature",
  "properties": {
    "iso:country":"DE",
    "sg:address":"Mainzer Str. 168",
    "sg:city":"Saarbr\u00fccken",
    "sg:phone":"+49 4968/181940",
    "sg:postcode":"66121",
    "sg:province":"Saarland",
    "wof:name":"Autohaus Dechent Gmbh",
    "wof:placetype":"venue"
},
  "geometry": {"coordinates":[7.0255918503,49.2260551453],"type":"Point"}
}