{
  "type": "Feature",
  "properties": {
    "iso:country":"DE",
    "sg:address":"Pestalozzistr. 6",
    "sg:city":"Pohlheim",
    "sg:phone":"+49 6403/61838",
    "sg:postcode":"35415",
    "sg:province":"Hessen",
    "wof:name":"Lang",
    "wof:placetype":"venue"
},
  "geometry": {"coordinates":[8.722528,50.538948],"type":"Point"}
}