{
  "type": "Feature",
  "properties": {
    "iso:country":"DE",
    "sg:address":"Bergstr. 18",
    "sg:city":"Surwold",
    "sg:phone":"+49 4965/698",
    "sg:postcode":"26903",
    "sg:province":"Niedersachsen",
    "wof:name":"Benno Ruhe",
    "wof:placetype":"venue"
},
  "geometry": {"coordinates":[7.537073,52.970184],"type":"Point"}
}