{
  "type": "Feature",
  "properties": {
    "iso:country":"DE",
    "sg:address":"Heldelinger Str. 6",
    "sg:city":"Weil am Rhein",
    "sg:phone":"+49 7621/63911",
    "sg:postcode":"79576",
    "sg:province":"Baden-W\u00fcrttemberg",
    "wof:name":"Heldelinger Stube",
    "wof:placetype":"venue"
},
  "geometry": {"coordinates":[7.6109552383,47.6133995056],"type":"Point"}
}