{
  "type": "Feature",
  "properties": {
    "iso:country":"DE",
    "sg:address":"Milchberg 24",
    "sg:city":"Berg",
    "sg:phone":"+49 8151/28798",
    "sg:postcode":"82335",
    "sg:province":"Bayern",
    "wof:name":"Schall\u00f6hr Verlag E. K.",
    "wof:placetype":"venue"
},
  "geometry": {"coordinates":[11.3617286682,47.9883155823],"type":"Point"}
}