{
  "type": "Feature",
  "properties": {
    "iso:country":"DE",
    "sg:address":"Falkenberger Landstr. 45a",
    "sg:city":"Lilienthal",
    "sg:postcode":"28865",
    "sg:province":"Niedersachsen",
    "wof:name":"Behrens Transporte Gmbh",
    "wof:placetype":"venue"
},
  "geometry": {"coordinates":[8.9198036194,53.1529273987],"type":"Point"}
}