{
  "type": "Feature",
  "properties": {
    "iso:country":"DE",
    "sg:address":"Steppenbergallee 201",
    "sg:city":"Aachen",
    "sg:postcode":"52074",
    "sg:province":"Nordrhein-Westfalen",
    "wof:name":"Euromat Gesellschaft F\u00fcr Werkstofftechnologie Und",
    "wof:placetype":"venue"
},
  "geometry": {"coordinates":[6.0376839638,50.7669715881],"type":"Point"}
}