{
  "type": "Feature",
  "properties": {
    "iso:country":"DE",
    "sg:address":"Hochdorfer Str. 12",
    "sg:city":"Freiburg",
    "sg:phone":"+49 7665/2484",
    "sg:postcode":"79108",
    "sg:province":"Baden-W\u00fcrttemberg",
    "wof:name":"Elsa Disch",
    "wof:placetype":"venue"
},
  "geometry": {"coordinates":[7.8015050888,48.0478286743],"type":"Point"}
}