{
  "type": "Feature",
  "properties": {
    "iso:country":"DE",
    "sg:address":"Oberpforte 11",
    "sg:city":"W\u00f6lfersheim",
    "sg:phone":"+49 6036/981715",
    "sg:postcode":"61200",
    "sg:province":"Hessen",
    "wof:name":"Alfred Streitenberger Elektroinstallation",
    "wof:placetype":"venue"
},
  "geometry": {"coordinates":[8.864127,50.427719],"type":"Point"}
}