{
  "type": "Feature",
  "properties": {
    "iso:country":"DE",
    "sg:address":"Gm\u00fcnder Str. 45",
    "sg:city":"Heubach",
    "sg:postcode":"73540",
    "sg:province":"Baden-W\u00fcrttemberg",
    "wof:name":"Hpi-zentrum Gmbh",
    "wof:placetype":"venue"
},
  "geometry": {"coordinates":[9.925422,48.794518],"type":"Point"}
}