{
  "type": "Feature",
  "properties": {
    "iso:country":"DE",
    "sg:address":"Breitewiesenstr. 12",
    "sg:city":"Sailauf",
    "sg:phone":"+49 6093/7547",
    "sg:postcode":"63877",
    "sg:province":"Bayern",
    "wof:name":"Franz-josef B\u00fcttner",
    "wof:placetype":"venue"
},
  "geometry": {"coordinates":[9.250572,50.017338],"type":"Point"}
}