{
  "type": "Feature",
  "properties": {
    "iso:country":"DE",
    "sg:address":"Meller Str. 120 a",
    "sg:city":"Melle",
    "sg:phone":"+49 5422/42894",
    "sg:postcode":"49328",
    "sg:province":"Niedersachsen",
    "wof:name":"B. Gurtzki",
    "wof:placetype":"venue"
},
  "geometry": {"coordinates":[8.416682,52.212513],"type":"Point"}
}