{
  "type": "Feature",
  "properties": {
    "iso:country":"DE",
    "sg:address":"Geroldsweiler 3",
    "sg:city":"Lo\u00dfburg",
    "sg:phone":"+49 7446/785",
    "sg:postcode":"72290",
    "sg:province":"Baden-W\u00fcrttemberg",
    "wof:name":"Gottlieb B\u00fchner",
    "wof:placetype":"venue"
},
  "geometry": {"coordinates":[8.50063,48.401371],"type":"Point"}
}