{
  "type": "Feature",
  "properties": {
    "iso:country":"DE",
    "sg:address":"Hackestr. 47",
    "sg:city":"Wuppertal",
    "sg:phone":"+49 202/4781751",
    "sg:postcode":"42349",
    "sg:province":"Nordrhein-Westfalen",
    "wof:name":"M. E. Mohr Gmbh",
    "wof:placetype":"venue"
},
  "geometry": {"coordinates":[7.131089,51.191143],"type":"Point"}
}