{
  "type": "Feature",
  "properties": {
    "iso:country":"DE",
    "sg:address":"Klosterweg 8",
    "sg:city":"Heimbach",
    "sg:phone":"+49 2425/1277",
    "sg:postcode":"52396",
    "sg:province":"Nordrhein-Westfalen",
    "wof:name":"Kath. Pfarramt Gem. St. Dionysius",
    "wof:placetype":"venue"
},
  "geometry": {"coordinates":[6.5481891632,50.6528015137],"type":"Point"}
}