{
  "type": "Feature",
  "properties": {
    "iso:country":"DE",
    "sg:address":"Liboristr. 1a",
    "sg:city":"Beverungen",
    "sg:phone":"+49 5273/1807",
    "sg:postcode":"37688",
    "sg:province":"Nordrhein-Westfalen",
    "wof:name":"Josef V\u00f6ssing & Sohn Gmbh",
    "wof:placetype":"venue"
},
  "geometry": {"coordinates":[9.370666,51.662834],"type":"Point"}
}