{
  "type": "Feature",
  "properties": {
    "iso:country":"DE",
    "sg:address":"Graf-Bentzel-Str. 2",
    "sg:city":"Rottenburg",
    "sg:phone":"+49 7472/21361",
    "sg:postcode":"72108",
    "sg:province":"Baden-W\u00fcrttemberg",
    "wof:name":"Hubert Baur",
    "wof:placetype":"venue"
},
  "geometry": {"coordinates":[8.9447650909,48.4828414917],"type":"Point"}
}