{
  "type": "Feature",
  "properties": {
    "iso:country":"DE",
    "sg:address":"An der Schule 3",
    "sg:city":"Hoyerswerda",
    "sg:phone":"+49 3571/91140",
    "sg:postcode":"02977",
    "sg:province":"Sachsen",
    "wof:name":"Wolfgang Lehmann Bau Gmbh",
    "wof:placetype":"venue"
},
  "geometry": {"coordinates":[14.238549,51.436398],"type":"Point"}
}