{
  "type": "Feature",
  "properties": {
    "iso:country":"DE",
    "sg:address":"Von-Graevemeyer-Weg 10b",
    "sg:city":"Hannover",
    "sg:phone":"+49 511/524297",
    "sg:postcode":"30539",
    "sg:province":"Niedersachsen",
    "wof:name":"Friedel Busch Ingenieur",
    "wof:placetype":"venue"
},
  "geometry": {"coordinates":[9.8304290771,52.3448257446],"type":"Point"}
}