{
  "type": "Feature",
  "properties": {
    "iso:country":"DE",
    "sg:address":"Sedanstr. 25",
    "sg:city":"Alfeld",
    "sg:phone":"+49 5181/4992",
    "sg:postcode":"31061",
    "sg:province":"Niedersachsen",
    "wof:name":"Halil G\u00fclkanat",
    "wof:placetype":"venue"
},
  "geometry": {"coordinates":[9.8228435516,51.9872436523],"type":"Point"}
}