{
  "type": "Feature",
  "properties": {
    "iso:country":"DE",
    "sg:address":"Wittenh\u00e4ger Str. 123",
    "sg:city":"Wittenhagen",
    "sg:phone":"+49 38327/40158",
    "sg:postcode":"18510",
    "sg:province":"Mecklenburg-Vorpommern",
    "wof:name":"Heiko Kumbier",
    "wof:placetype":"venue"
},
  "geometry": {"coordinates":[13.02358,54.186909],"type":"Point"}
}