{
  "type": "Feature",
  "properties": {
    "iso:country":"DE",
    "sg:address":"Pfarrstr. 3",
    "sg:city":"Neuenb\u00fcrg",
    "sg:phone":"+49 7082/2203",
    "sg:postcode":"75305",
    "sg:province":"Baden-W\u00fcrttemberg",
    "wof:name":"Ev. Pfarramt I",
    "wof:placetype":"venue"
},
  "geometry": {"coordinates":[8.5889825821,48.8465652466],"type":"Point"}
}