{
  "type": "Feature",
  "properties": {
    "iso:country":"DE",
    "sg:address":"Lehmkuhlen 12",
    "sg:city":"Kisdorf",
    "sg:phone":"+49 4193/969991",
    "sg:postcode":"24629",
    "sg:province":"Schleswig-Holstein",
    "wof:name":"Kurierdienst Thomsen",
    "wof:placetype":"venue"
},
  "geometry": {"coordinates":[10.01985,53.812008],"type":"Point"}
}