{
  "type": "Feature",
  "properties": {
    "iso:country":"DE",
    "sg:address":"St. Arnualer Markt 8",
    "sg:city":"Saarbr\u00fccken",
    "sg:phone":"+49 681/853826",
    "sg:postcode":"66119",
    "sg:province":"Saarland",
    "wof:name":"Unter Der Linde",
    "wof:placetype":"venue"
},
  "geometry": {"coordinates":[7.0167198181,49.2169837952],"type":"Point"}
}