{
  "type": "Feature",
  "properties": {
    "iso:country":"DE",
    "sg:address":"Schubystr. 91a",
    "sg:city":"Schleswig",
    "sg:phone":"+49 4621/25157",
    "sg:postcode":"24837",
    "sg:province":"Schleswig-Holstein",
    "wof:name":"Helmut Diederichsen",
    "wof:placetype":"venue"
},
  "geometry": {"coordinates":[9.5504980087,54.5220069885],"type":"Point"}
}