{
  "type": "Feature",
  "properties": {
    "iso:country":"DE",
    "sg:address":"Ludwigstr. 30",
    "sg:city":"Traunstein",
    "sg:phone":"+49 861/5396",
    "sg:postcode":"83278",
    "sg:province":"Bayern",
    "wof:name":"Friedrich Knott",
    "wof:placetype":"venue"
},
  "geometry": {"coordinates":[12.642329216,47.8705940247],"type":"Point"}
}