{
  "type": "Feature",
  "properties": {
    "iso:country":"DE",
    "sg:address":"Kleebrink 7",
    "sg:city":"Bielefeld",
    "sg:phone":"+49 521/333469",
    "sg:postcode":"33719",
    "sg:province":"Nordrhein-Westfalen",
    "wof:name":"G\u00fcnter Kassing Gmbh",
    "wof:placetype":"venue"
},
  "geometry": {"coordinates":[8.602332,52.039658],"type":"Point"}
}