{
  "type": "Feature",
  "properties": {
    "iso:country":"DE",
    "sg:address":"Petzmannsberg 2b",
    "sg:city":"Kulmbach",
    "sg:phone":"+49 9221/83706",
    "sg:postcode":"95326",
    "sg:province":"Bayern",
    "wof:name":"Drei Plan Ag",
    "wof:placetype":"venue"
},
  "geometry": {"coordinates":[11.4403371811,50.1152801514],"type":"Point"}
}