{
  "type": "Feature",
  "properties": {
    "iso:country":"DE",
    "sg:address":"Kirchhuchtinger Landstr. 122",
    "sg:city":"Bremen",
    "sg:phone":"+49 421/5961490",
    "sg:postcode":"28259",
    "sg:province":"Bremen",
    "wof:name":"Carthago Capital Beteiligungen Ag",
    "wof:placetype":"venue"
},
  "geometry": {"coordinates":[8.736463,53.044861],"type":"Point"}
}