{
  "type": "Feature",
  "properties": {
    "iso:country":"DE",
    "sg:address":"Rosenstr. 32",
    "sg:city":"Berglen",
    "sg:phone":"+49 7195/71826",
    "sg:postcode":"73663",
    "sg:province":"Baden-W\u00fcrttemberg",
    "wof:name":"Walter Benz",
    "wof:placetype":"venue"
},
  "geometry": {"coordinates":[9.465325,48.888672],"type":"Point"}
}