{
  "type": "Feature",
  "properties": {
    "iso:country":"DE",
    "sg:address":"Walkem\u00fchlenweg 29",
    "sg:city":"G\u00f6ttingen",
    "sg:postcode":"37083",
    "sg:province":"Niedersachsen",
    "wof:name":"Modellbau Gro\u00df",
    "wof:placetype":"venue"
},
  "geometry": {"coordinates":[9.935248,51.527168],"type":"Point"}
}