{
  "type": "Feature",
  "properties": {
    "iso:country":"DE",
    "sg:address":"Winkelriedweg 75",
    "sg:city":"Dortmund",
    "sg:phone":"+49 231/596189",
    "sg:postcode":"44141",
    "sg:province":"Nordrhein-Westfalen",
    "wof:name":"Klaus S\u00fcggel Kg",
    "wof:placetype":"venue"
},
  "geometry": {"coordinates":[7.5182070732,51.5085525513],"type":"Point"}
}