{
  "type": "Feature",
  "properties": {
    "iso:country":"DE",
    "sg:address":"Bahnhofstr. 1",
    "sg:city":"Straupitz",
    "sg:postcode":"15913",
    "sg:province":"Brandenburg",
    "wof:name":"Gemeindeschwesterstation Straupitz",
    "wof:placetype":"venue"
},
  "geometry": {"coordinates":[14.120556,51.912464],"type":"Point"}
}