{
  "type": "Feature",
  "properties": {
    "iso:country":"DE",
    "sg:address":"D\u00fcsseldorfer Str. 217 a",
    "sg:city":"Meerbusch",
    "sg:phone":"+49 2132/75090",
    "sg:postcode":"40667",
    "sg:province":"Nordrhein-Westfalen",
    "wof:name":"Friedrich Wassermann Hoch- Und Tiefbau Gmbh & Co.",
    "wof:placetype":"venue"
},
  "geometry": {"coordinates":[6.707527,51.238914],"type":"Point"}
}