{
  "type": "Feature",
  "properties": {
    "iso:country":"DE",
    "sg:address":"Frankenberger Str. 244",
    "sg:city":"Chemnitz",
    "sg:phone":"+49 371/414128",
    "sg:postcode":"09131",
    "sg:province":"Sachsen",
    "wof:name":"Shefd Gmbh",
    "wof:placetype":"venue"
},
  "geometry": {"coordinates":[12.9604291916,50.8670043945],"type":"Point"}
}