{
  "type": "Feature",
  "properties": {
    "iso:country":"DE",
    "sg:address":"Wupperstr. 102",
    "sg:city":"Solingen",
    "sg:phone":"+49 212/18944",
    "sg:postcode":"42651",
    "sg:province":"Nordrhein-Westfalen",
    "wof:name":"D. K\u00f6nig",
    "wof:placetype":"venue"
},
  "geometry": {"coordinates":[7.09562397,51.17445755],"type":"Point"}
}