{
  "type": "Feature",
  "properties": {
    "iso:country":"DE",
    "sg:address":"Seitenweg 2",
    "sg:city":"Netphen",
    "sg:phone":"+49 2738/2469",
    "sg:postcode":"57250",
    "sg:province":"Nordrhein-Westfalen",
    "wof:name":"Bernd K\u00fchn",
    "wof:placetype":"venue"
},
  "geometry": {"coordinates":[8.108291626,50.9115600586],"type":"Point"}
}