{
  "type": "Feature",
  "properties": {
    "iso:country":"DE",
    "sg:address":"Poststr. 33",
    "sg:city":"Hamburg",
    "sg:postcode":"20354",
    "sg:province":"Hamburg",
    "wof:name":"Stocktip Online Com Ag",
    "wof:placetype":"venue"
},
  "geometry": {"coordinates":[9.988758,53.553997],"type":"Point"}
}