{
  "type": "Feature",
  "properties": {
    "iso:country":"DE",
    "sg:address":"Br\u00fcder-Grimm-Str. 48",
    "sg:city":"Steinau",
    "sg:phone":"+49 6663/5804",
    "sg:postcode":"36396",
    "sg:province":"Hessen",
    "wof:name":"Gastst\u00e4tte Alfred Bender",
    "wof:placetype":"venue"
},
  "geometry": {"coordinates":[9.4623804092,50.3132362366],"type":"Point"}
}