{
  "type": "Feature",
  "properties": {
    "iso:country":"DE",
    "sg:address":"Kanalsteig 6",
    "sg:city":"Wischhafen",
    "sg:phone":"+49 4770/214",
    "sg:postcode":"21737",
    "sg:province":"Niedersachsen",
    "wof:name":"Wilhelm Mausbach",
    "wof:placetype":"venue"
},
  "geometry": {"coordinates":[9.3243017197,53.7521858215],"type":"Point"}
}