{
  "type": "Feature",
  "properties": {
    "iso:country":"DE",
    "sg:address":"Walter K\u00f6hn Str. 6b",
    "sg:city":"Leipzig",
    "sg:phone":"+49 4934/160740",
    "sg:postcode":"04356",
    "sg:province":"Sachsen",
    "wof:name":"Tenovis Gmbh & Co Kg",
    "wof:placetype":"venue"
},
  "geometry": {"coordinates":[12.4034633636,51.4018173218],"type":"Point"}
}