{
  "type": "Feature",
  "properties": {
    "iso:country":"DE",
    "sg:address":"Kaiser-Friedrich-Str. 4 a",
    "sg:city":"Berlin",
    "sg:phone":"+49 30/3412554",
    "sg:postcode":"10585",
    "sg:province":"Berlin",
    "wof:name":"Winfried Hartmann",
    "wof:placetype":"venue"
},
  "geometry": {"coordinates":[13.299768,52.518242],"type":"Point"}
}