{
  "type": "Feature",
  "properties": {
    "iso:country":"DE",
    "sg:address":"Lipowskystr. 12",
    "sg:city":"M\u00fcnchen",
    "sg:phone":"+49 89/7466100",
    "sg:postcode":"81373",
    "sg:province":"Bayern",
    "wof:name":"B\u00f6ck Oppler Und Hering Rechtsanw\u00e4lte",
    "wof:placetype":"venue"
},
  "geometry": {"coordinates":[11.5436153412,48.1251983643],"type":"Point"}
}