{
  "type": "Feature",
  "properties": {
    "iso:country":"DE",
    "sg:address":"Ringstr. 82",
    "sg:city":"Berlin",
    "sg:phone":"+49 30/8338602",
    "sg:postcode":"12203",
    "sg:province":"Berlin",
    "wof:name":"Wolfgang Mayr Rechtsanwalt",
    "wof:placetype":"venue"
},
  "geometry": {"coordinates":[13.3012275696,52.4400215149],"type":"Point"}
}