{
  "type": "Feature",
  "properties": {
    "iso:country":"DE",
    "sg:address":"Memminger Str. 49",
    "sg:city":"Woringen",
    "sg:phone":"+49 8331/3296",
    "sg:postcode":"87789",
    "sg:province":"Bayern",
    "wof:name":"Holprof Metallverarbeitung Gmbh",
    "wof:placetype":"venue"
},
  "geometry": {"coordinates":[10.20002,47.927784],"type":"Point"}
}