{
  "type": "Feature",
  "properties": {
    "iso:country":"DE",
    "sg:address":"Dahlienweg 2",
    "sg:city":"M\u00fcglitztal",
    "sg:phone":"+49 3529/519148",
    "sg:postcode":"01809",
    "sg:province":"Sachsen",
    "wof:name":"Lutz Pech",
    "wof:placetype":"venue"
},
  "geometry": {"coordinates":[13.8611860275,50.9219856262],"type":"Point"}
}