{
  "type": "Feature",
  "properties": {
    "iso:country":"DE",
    "sg:address":"Am Waldrand 42",
    "sg:city":"Gro\u00df Gr\u00f6nau",
    "sg:phone":"+49 4509/1655",
    "sg:postcode":"23627",
    "sg:province":"Schleswig-Holstein",
    "wof:name":"Kurt Leichnitz Ingenieur Sachverst\u00e4ndiger",
    "wof:placetype":"venue"
},
  "geometry": {"coordinates":[10.7333068848,53.8217773438],"type":"Point"}
}