{
  "type": "Feature",
  "properties": {
    "iso:country":"DE",
    "sg:address":"Ohrberg 10",
    "sg:city":"Pattensen",
    "sg:postcode":"30982",
    "sg:province":"Niedersachsen",
    "wof:name":"Rolog-services Bremeier Kg",
    "wof:placetype":"venue"
},
  "geometry": {"coordinates":[9.795559,52.214405],"type":"Point"}
}