{
  "type": "Feature",
  "properties": {
    "iso:country":"DE",
    "sg:address":"Sch\u00f6nenbucher Weg 15",
    "sg:city":"Mittelbiberach",
    "sg:phone":"+49 7351/9958",
    "sg:postcode":"88441",
    "sg:province":"Baden-W\u00fcrttemberg",
    "wof:name":"H. Schmid",
    "wof:placetype":"venue"
},
  "geometry": {"coordinates":[9.7517414093,48.0859222412],"type":"Point"}
}