{
  "type": "Feature",
  "properties": {
    "iso:country":"DE",
    "sg:address":"Friedenstr. 98",
    "sg:city":"Zeuthen",
    "sg:postcode":"15738",
    "sg:province":"Brandenburg",
    "wof:name":"Dr. Med. Ebehard K\u00fcbick",
    "wof:placetype":"venue"
},
  "geometry": {"coordinates":[13.627805,52.368145],"type":"Point"}
}