{
  "type": "Feature",
  "properties": {
    "iso:country":"DE",
    "sg:address":"Limburger Str. 12A",
    "sg:city":"Taunusstein",
    "sg:phone":"+49 6128/951546",
    "sg:postcode":"65232",
    "sg:province":"Hessen",
    "wof:name":"Ppb Planen Projektieren Bauen Gmbh",
    "wof:placetype":"venue"
},
  "geometry": {"coordinates":[8.208041,50.171772],"type":"Point"}
}