{
  "type": "Feature",
  "properties": {
    "iso:country":"DE",
    "sg:address":"Ostengasse 24",
    "sg:city":"Regensburg",
    "sg:phone":"+49 941/52531",
    "sg:postcode":"93047",
    "sg:province":"Bayern",
    "wof:name":"E. Sch\u00f6n",
    "wof:placetype":"venue"
},
  "geometry": {"coordinates":[12.105198,49.018612],"type":"Point"}
}