{
  "type": "Feature",
  "properties": {
    "iso:country":"DE",
    "sg:address":"S\u00fcdendstr. 87",
    "sg:city":"Germering",
    "sg:phone":"+49 89/89569480",
    "sg:postcode":"82110",
    "sg:province":"Bayern",
    "wof:name":"Peter Stangl",
    "wof:placetype":"venue"
},
  "geometry": {"coordinates":[11.3759021759,48.1301040649],"type":"Point"}
}