{
  "type": "Feature",
  "properties": {
    "iso:country":"DE",
    "sg:address":"Cavaillonstr. 2",
    "sg:city":"Weinheim",
    "sg:postcode":"69469",
    "sg:province":"Baden-W\u00fcrttemberg",
    "wof:name":"Deutsche Post Ag",
    "wof:placetype":"venue"
},
  "geometry": {"coordinates":[8.655412674,49.5471916199],"type":"Point"}
}