{
  "type": "Feature",
  "properties": {
    "iso:country":"DE",
    "sg:address":"Eppsteiner Str. 1",
    "sg:city":"Oberursel",
    "sg:phone":"+49 6171/54194",
    "sg:postcode":"61440",
    "sg:province":"Hessen",
    "wof:name":"Stadt Stra\u00dfburg",
    "wof:placetype":"venue"
},
  "geometry": {"coordinates":[8.5782709122,50.2039222717],"type":"Point"}
}