{
  "type": "Feature",
  "properties": {
    "iso:country":"DE",
    "sg:address":"Dr.-Warsing-Str. 28",
    "sg:city":"Moormerland",
    "sg:phone":"+49 4954/1781",
    "sg:postcode":"26802",
    "sg:province":"Niedersachsen",
    "wof:name":"Ingenieur Kurt Engel Immobilien Ges. Mbh",
    "wof:placetype":"venue"
},
  "geometry": {"coordinates":[7.4811501503,53.3241348267],"type":"Point"}
}