{
  "type": "Feature",
  "properties": {
    "iso:country":"DE",
    "sg:address":"Bahnstr. 58",
    "sg:city":"Ellerstadt",
    "sg:phone":"+49 6237/7311",
    "sg:postcode":"67158",
    "sg:province":"Rheinland-Pfalz",
    "wof:name":"Emil Merk Weinanbau",
    "wof:placetype":"venue"
},
  "geometry": {"coordinates":[8.2615356445,49.4635887146],"type":"Point"}
}