{
  "type": "Feature",
  "properties": {
    "iso:country":"DE",
    "sg:address":"Eulenweg 17",
    "sg:city":"Freising",
    "sg:phone":"+49 8161/82040",
    "sg:postcode":"85356",
    "sg:province":"Bayern",
    "wof:name":"Manfred Bl\u00fcmelsberger",
    "wof:placetype":"venue"
},
  "geometry": {"coordinates":[11.7661800385,48.3987541199],"type":"Point"}
}