{
  "type": "Feature",
  "properties": {
    "iso:country":"DE",
    "sg:address":"Meiersfelder Str. 40",
    "sg:city":"Detmold",
    "sg:phone":"+49 5231/58556",
    "sg:postcode":"32760",
    "sg:province":"Nordrhein-Westfalen",
    "wof:name":"Helmut Tietjen",
    "wof:placetype":"venue"
},
  "geometry": {"coordinates":[8.913724,51.930145],"type":"Point"}
}