{
  "type": "Feature",
  "properties": {
    "iso:country":"DE",
    "sg:address":"Turnerstr. 11",
    "sg:city":"Thum",
    "sg:phone":"+49 37297/4215",
    "sg:postcode":"09419",
    "sg:province":"Sachsen",
    "wof:name":"Frank F. B. Georgi Rechtsanwalt",
    "wof:placetype":"venue"
},
  "geometry": {"coordinates":[12.9545860291,50.6725349426],"type":"Point"}
}