{
  "type": "Feature",
  "properties": {
    "iso:country":"DE",
    "sg:address":"D\u00fcrerstr. 11",
    "sg:city":"Kornwestheim",
    "sg:postcode":"70806",
    "sg:province":"Baden-W\u00fcrttemberg",
    "wof:name":"Schmidt Consulting Gmbh",
    "wof:placetype":"venue"
},
  "geometry": {"coordinates":[9.1907844543,48.8692207336],"type":"Point"}
}