{
  "type": "Feature",
  "properties": {
    "iso:country":"DE",
    "sg:address":"Daimlerstr 10",
    "sg:city":"Geislingen",
    "sg:phone":"+49 7433/90590",
    "sg:postcode":"72351",
    "sg:province":"Baden-W\u00fcrttemberg",
    "wof:name":"Anton Amann Spezialm\u00f6bel Gmbh",
    "wof:placetype":"venue"
},
  "geometry": {"coordinates":[8.810491,48.295025],"type":"Point"}
}