{
  "type": "Feature",
  "properties": {
    "iso:country":"DE",
    "sg:address":"Rosenstr. 9",
    "sg:city":"Cappenberg",
    "sg:phone":"+49 2306/10539",
    "sg:postcode":"59379",
    "sg:province":"Nordrhein-Westfalen",
    "wof:name":"Sparkasse L\u00fcnen Zweckverbandss",
    "wof:placetype":"venue"
},
  "geometry": {"coordinates":[7.46694,51.697857],"type":"Point"}
}