{
  "type": "Feature",
  "properties": {
    "iso:country":"DE",
    "sg:address":"Konrad-Adenauer-Platz 2",
    "sg:city":"Langenfeld",
    "sg:phone":"+49 2173/76180",
    "sg:postcode":"40764",
    "sg:province":"Nordrhein-Westfalen",
    "wof:name":"Peter Manweiler",
    "wof:placetype":"venue"
},
  "geometry": {"coordinates":[6.9516429901,51.112197876],"type":"Point"}
}