{
  "type": "Feature",
  "properties": {
    "iso:country":"DE",
    "sg:address":"Buerer Str. 23",
    "sg:city":"Gelsenkirchen",
    "sg:phone":"+49 209/518055",
    "sg:postcode":"45899",
    "sg:province":"Nordrhein-Westfalen",
    "wof:name":"Schuco Verm\u00f6gensverwaltungs Gmbh",
    "wof:placetype":"venue"
},
  "geometry": {"coordinates":[7.0215439796,51.5313911438],"type":"Point"}
}