{
  "type": "Feature",
  "properties": {
    "iso:country":"DE",
    "sg:address":"Waldstr. 50",
    "sg:city":"Heusenstamm",
    "sg:phone":"+49 6106/3393",
    "sg:postcode":"63150",
    "sg:province":"Hessen",
    "wof:name":"Norbert Wanczeck Steuerberater",
    "wof:placetype":"venue"
},
  "geometry": {"coordinates":[8.8583097458,50.0500831604],"type":"Point"}
}