{
  "type": "Feature",
  "properties": {
    "iso:country":"DE",
    "sg:address":"Th\u00fcnenweg 32/33",
    "sg:city":"G\u00fcstrow",
    "sg:postcode":"18273",
    "sg:province":"Mecklenburg-Vorpommern",
    "wof:name":"Abel Bestattungen Gmbh",
    "wof:placetype":"venue"
},
  "geometry": {"coordinates":[12.167361,53.772064],"type":"Point"}
}