{
  "type": "Feature",
  "properties": {
    "iso:country":"DE",
    "sg:address":"Heidem\u00fchler Weg 36",
    "sg:city":"Berlin",
    "sg:phone":"+49 30/5325603",
    "sg:postcode":"12437",
    "sg:province":"Berlin",
    "wof:name":"Conrad Tenner",
    "wof:placetype":"venue"
},
  "geometry": {"coordinates":[13.4881792068,52.4631996155],"type":"Point"}
}