{
  "type": "Feature",
  "properties": {
    "iso:country":"DE",
    "sg:address":"Casparistr. 1",
    "sg:city":"Syke",
    "sg:phone":"+49 4242/70742",
    "sg:postcode":"28857",
    "sg:province":"Niedersachsen",
    "wof:name":"Heinz-dieter Ahrens",
    "wof:placetype":"venue"
},
  "geometry": {"coordinates":[8.825172,52.910995],"type":"Point"}
}