{
  "type": "Feature",
  "properties": {
    "iso:country":"DE",
    "sg:address":"Augsburger Str. 11",
    "sg:city":"Thierhaupten",
    "sg:phone":"+49 8271/3813",
    "sg:postcode":"86672",
    "sg:province":"Bayern",
    "wof:name":"Adolf Schreier",
    "wof:placetype":"venue"
},
  "geometry": {"coordinates":[10.9130144119,48.5633811951],"type":"Point"}
}