{
  "type": "Feature",
  "properties": {
    "iso:country":"DE",
    "sg:address":"Dorfplatz 1",
    "sg:city":"Petershagen",
    "sg:postcode":"15370",
    "sg:province":"Brandenburg",
    "wof:name":"Evangelische Kirchengemeinde Gemeindeb\u00fcro Petershagen",
    "wof:placetype":"venue"
},
  "geometry": {"coordinates":[13.7708463669,52.5262298584],"type":"Point"}
}