{
  "type": "Feature",
  "properties": {
    "iso:country":"DE",
    "sg:address":"Pfaffenpfad 12",
    "sg:city":"K\u00f6ln",
    "sg:phone":"+49 2203/25916",
    "sg:postcode":"51145",
    "sg:province":"Nordrhein-Westfalen",
    "wof:name":"Raphael Weymers Unternehmensberater",
    "wof:placetype":"venue"
},
  "geometry": {"coordinates":[7.0826678276,50.8802108765],"type":"Point"}
}