{
  "type": "Feature",
  "properties": {
    "iso:country":"DE",
    "sg:address":"Aachener Str. 451",
    "sg:city":"M\u00f6nchengladbach",
    "sg:phone":"+49 2161/54725",
    "sg:postcode":"41069",
    "sg:province":"Nordrhein-Westfalen",
    "wof:name":"Roland Lehmann",
    "wof:placetype":"venue"
},
  "geometry": {"coordinates":[6.4091920853,51.1816444397],"type":"Point"}
}