{
  "type": "Feature",
  "properties": {
    "iso:country":"DE",
    "sg:address":"Feldstr. 12",
    "sg:city":"H\u00f6hein\u00f6d",
    "sg:phone":"+49 6333/1704",
    "sg:postcode":"66989",
    "sg:province":"Rheinland-Pfalz",
    "wof:name":"Bernd Weber",
    "wof:placetype":"venue"
},
  "geometry": {"coordinates":[7.6074790955,49.2918624878],"type":"Point"}
}