{
  "type": "Feature",
  "properties": {
    "iso:country":"DE",
    "sg:address":"M\u00fcsleringen 5",
    "sg:city":"Stolzenau",
    "sg:phone":"+49 5761/3966",
    "sg:postcode":"31592",
    "sg:province":"Niedersachsen",
    "wof:name":"M. Neumann",
    "wof:placetype":"venue"
},
  "geometry": {"coordinates":[9.030507,52.498253],"type":"Point"}
}