{
  "type": "Feature",
  "properties": {
    "iso:country":"DE",
    "sg:address":"Hauptstr. 18",
    "sg:city":"Spahl",
    "sg:phone":"+49 36967/51060",
    "sg:postcode":"36419",
    "sg:province":"Th\u00fcringen",
    "wof:name":"J. Walter",
    "wof:placetype":"venue"
},
  "geometry": {"coordinates":[9.949392,50.717346],"type":"Point"}
}