{
  "type": "Feature",
  "properties": {
    "iso:country":"DE",
    "sg:address":"Grubenweg 4",
    "sg:city":"Dresden",
    "sg:phone":"+49 351/4017123",
    "sg:postcode":"01189",
    "sg:province":"Sachsen",
    "wof:name":"Rudolf Storch Rechtsanwalt",
    "wof:placetype":"venue"
},
  "geometry": {"coordinates":[13.6902770996,51.0126342773],"type":"Point"}
}