{
  "type": "Feature",
  "properties": {
    "iso:country":"DE",
    "sg:address":"Schillerstr. 20",
    "sg:city":"Osnabr\u00fcck",
    "sg:phone":"+49 541/259576",
    "sg:postcode":"49074",
    "sg:province":"Niedersachsen",
    "wof:name":"Bkv-beratende Ingenieure",
    "wof:placetype":"venue"
},
  "geometry": {"coordinates":[8.04961586,52.2755699158],"type":"Point"}
}