{
  "type": "Feature",
  "properties": {
    "iso:country":"DE",
    "sg:address":"Sachsentor 69",
    "sg:city":"Hamburg",
    "sg:phone":"+49 4562/4666",
    "sg:postcode":"21029",
    "sg:province":"Hamburg",
    "wof:name":"Internationale Pelze & Leder Moden",
    "wof:placetype":"venue"
},
  "geometry": {"coordinates":[10.2148551941,53.4868431091],"type":"Point"}
}