{
  "type": "Feature",
  "properties": {
    "iso:country":"DE",
    "sg:address":"Naunheimer Str. 36",
    "sg:city":"Wetzlar",
    "sg:phone":"+49 6441/35775",
    "sg:postcode":"35576",
    "sg:province":"Hessen",
    "wof:name":"Sb-m\u00f6bel-profi",
    "wof:placetype":"venue"
},
  "geometry": {"coordinates":[8.507805,50.576305],"type":"Point"}
}