{
  "type": "Feature",
  "properties": {
    "iso:country":"DE",
    "sg:address":"Poppenreuther Str. 2",
    "sg:city":"N\u00fcrnberg",
    "sg:postcode":"90419",
    "sg:province":"Bayern",
    "wof:name":"Artec Gmbh",
    "wof:placetype":"venue"
},
  "geometry": {"coordinates":[11.0599956512,49.4598999023],"type":"Point"}
}