{
  "type": "Feature",
  "properties": {
    "iso:country":"DE",
    "sg:address":"Hanno-G\u00fcnther-Str. 14",
    "sg:city":"Leuben-Schleinitz",
    "sg:phone":"+49 35241/58669",
    "sg:postcode":"01623",
    "sg:province":"Sachsen",
    "wof:name":"Helmut Friedrich",
    "wof:placetype":"venue"
},
  "geometry": {"coordinates":[13.302821,51.163094],"type":"Point"}
}