{
  "type": "Feature",
  "properties": {
    "iso:country":"DE",
    "sg:address":"Griesweg 2a",
    "sg:city":"Bindlach",
    "sg:phone":"+49 9208/345",
    "sg:postcode":"95463",
    "sg:province":"Bayern",
    "wof:name":"Norbert Foth",
    "wof:placetype":"venue"
},
  "geometry": {"coordinates":[11.61019,49.984276],"type":"Point"}
}