{
  "type": "Feature",
  "properties": {
    "iso:country":"DE",
    "sg:address":"Pf\u00e4lzer-Wald-Str. 31",
    "sg:city":"N\u00fcrnberg",
    "sg:phone":"+49 911/482231",
    "sg:postcode":"90469",
    "sg:province":"Bayern",
    "wof:name":"P. Kulke",
    "wof:placetype":"venue"
},
  "geometry": {"coordinates":[11.0820293427,49.4022216797],"type":"Point"}
}