{
  "type": "Feature",
  "properties": {
    "iso:country":"DE",
    "sg:address":"Hermann-Mitsch-Str. 19",
    "sg:city":"Freiburg",
    "sg:phone":"+49 761/515070",
    "sg:postcode":"79108",
    "sg:province":"Baden-W\u00fcrttemberg",
    "wof:name":"Deutsche Asphalt Gmbh",
    "wof:placetype":"venue"
},
  "geometry": {"coordinates":[7.8386797905,48.0254096985],"type":"Point"}
}