{
  "type": "Feature",
  "properties": {
    "iso:country":"DE",
    "sg:address":"Ackerstr. 63",
    "sg:city":"Bad Sooden-Allendorf",
    "sg:phone":"+49 5652/3746",
    "sg:postcode":"37242",
    "sg:province":"Hessen",
    "wof:name":"Zumwinkel Transport Gmbh",
    "wof:placetype":"venue"
},
  "geometry": {"coordinates":[9.9782218933,51.2715377808],"type":"Point"}
}