{
  "type": "Feature",
  "properties": {
    "iso:country":"DE",
    "sg:address":"Marktstr. 33",
    "sg:city":"Sonthofen",
    "sg:phone":"+49 8321/2792",
    "sg:postcode":"87527",
    "sg:province":"Bayern",
    "wof:name":"Kath. Pfarramt St. Michael",
    "wof:placetype":"venue"
},
  "geometry": {"coordinates":[10.2806797028,47.5101585388],"type":"Point"}
}