{
  "type": "Feature",
  "properties": {
    "iso:country":"DE",
    "sg:address":"W\u00fcrzburger Str. 3",
    "sg:city":"Suhl",
    "sg:phone":"+49 3681/303694",
    "sg:postcode":"98529",
    "sg:province":"Th\u00fcringen",
    "wof:name":"Brigitte Dill Rechtsanw\u00e4ltin",
    "wof:placetype":"venue"
},
  "geometry": {"coordinates":[10.6828155518,50.6078796387],"type":"Point"}
}