{
  "type": "Feature",
  "properties": {
    "iso:country":"DE",
    "sg:address":"Hans-Ammon-Str. 18",
    "sg:city":"Britz",
    "sg:phone":"+49 3334/42464",
    "sg:postcode":"16230",
    "sg:province":"Brandenburg",
    "wof:name":"Horst Bailleu Ingenieur",
    "wof:placetype":"venue"
},
  "geometry": {"coordinates":[13.826415,52.87479],"type":"Point"}
}