{
  "type": "Feature",
  "properties": {
    "iso:country":"DE",
    "sg:address":"Roseng\u00e4\u00dfchen 2",
    "sg:city":"Michelstadt",
    "sg:phone":"+49 6061/703500",
    "sg:postcode":"64720",
    "sg:province":"Hessen",
    "wof:name":"Alexander Steiger Rechtsanwalt",
    "wof:placetype":"venue"
},
  "geometry": {"coordinates":[9.0032634735,49.678943634],"type":"Point"}
}