{
  "type": "Feature",
  "properties": {
    "iso:country":"DE",
    "sg:address":"Bodestra\u00dfe 106a",
    "sg:city":"Zepernick",
    "sg:phone":"+49 30",
    "sg:postcode":"16341",
    "sg:province":"Brandenburg",
    "wof:name":"Kontextverlag",
    "wof:placetype":"venue"
},
  "geometry": {"coordinates":[13.552852,52.651272],"type":"Point"}
}