{
  "type": "Feature",
  "properties": {
    "iso:country":"DE",
    "sg:address":"Heinrich-Hertz-Str. 1b",
    "sg:city":"Kleinmachnow",
    "sg:phone":"+49 33203/290600",
    "sg:postcode":"14532",
    "sg:province":"Brandenburg",
    "wof:name":"Netfox Ag",
    "wof:placetype":"venue"
},
  "geometry": {"coordinates":[13.186839,52.404408],"type":"Point"}
}