{
  "type": "Feature",
  "properties": {
    "iso:country":"DE",
    "sg:address":"Koloniestr. 60",
    "sg:city":"Moormerland",
    "sg:phone":"+49 4954/8145",
    "sg:postcode":"26802",
    "sg:province":"Niedersachsen",
    "wof:name":"Tee-st\u00fcbchen",
    "wof:placetype":"venue"
},
  "geometry": {"coordinates":[7.4912958145,53.2976036072],"type":"Point"}
}