{
  "type": "Feature",
  "properties": {
    "iso:country":"DE",
    "sg:address":"Am Tannenkamp 1",
    "sg:city":"Steinfeld",
    "sg:postcode":"49439",
    "sg:province":"Niedersachsen",
    "wof:name":"Schwarzer Frachtenkontor Verwaltungs Gmbh",
    "wof:placetype":"venue"
},
  "geometry": {"coordinates":[8.19811,52.58009],"type":"Point"}
}