{
  "type": "Feature",
  "properties": {
    "iso:country":"DE",
    "sg:city":"Gr\u00f6mitz",
    "sg:phone":"+49 4562/7200",
    "sg:postcode":"23743",
    "sg:province":"Schleswig-Holstein",
    "wof:name":"H. Otersen",
    "wof:placetype":"venue"
},
  "geometry": {"coordinates":[10.95855,54.151218],"type":"Point"}
}