{
  "type": "Feature",
  "properties": {
    "iso:country":"DE",
    "sg:address":"Flurstr. 40",
    "sg:city":"Radevormwald",
    "sg:phone":"+49 2191/62121",
    "sg:postcode":"42477",
    "sg:province":"Nordrhein-Westfalen",
    "wof:name":"E. Nagorny Ingenieur",
    "wof:placetype":"venue"
},
  "geometry": {"coordinates":[7.3139209747,51.2162704468],"type":"Point"}
}