{
  "type": "Feature",
  "properties": {
    "iso:country":"DE",
    "sg:address":"Neue M\u00f6gglinger Str. 3",
    "sg:city":"Heuchlingen",
    "sg:phone":"+49 7174/225",
    "sg:postcode":"73572",
    "sg:province":"Baden-W\u00fcrttemberg",
    "wof:name":"Adler",
    "wof:placetype":"venue"
},
  "geometry": {"coordinates":[9.9444828033,48.8514823914],"type":"Point"}
}