{
  "type": "Feature",
  "properties": {
    "iso:country":"DE",
    "sg:address":"Eiderkamp 20",
    "sg:city":"Bordesholm",
    "sg:phone":"+49 4322/3811",
    "sg:postcode":"24582",
    "sg:province":"Schleswig-Holstein",
    "wof:name":"Friedemann & Partner Gmbh",
    "wof:placetype":"venue"
},
  "geometry": {"coordinates":[10.0450401306,54.1806678772],"type":"Point"}
}