{
  "type": "Feature",
  "properties": {
    "iso:country":"DE",
    "sg:address":"Gro\u00dfe Str. 14",
    "sg:city":"Twistringen",
    "sg:phone":"+49 4243/2604",
    "sg:postcode":"27239",
    "sg:province":"Niedersachsen",
    "wof:name":"Forum",
    "wof:placetype":"venue"
},
  "geometry": {"coordinates":[8.6391954422,52.8010139465],"type":"Point"}
}