{
  "type": "Feature",
  "properties": {
    "iso:country":"DE",
    "sg:address":"Am Petersberg",
    "sg:city":"Bad Bodenteich",
    "sg:phone":"+49 5824/96330",
    "sg:postcode":"29389",
    "sg:province":"Niedersachsen",
    "wof:name":"Cristian Schwerin Gmbh",
    "wof:placetype":"venue"
},
  "geometry": {"coordinates":[10.6831550598,52.8407287598],"type":"Point"}
}