{
  "type": "Feature",
  "properties": {
    "iso:country":"DE",
    "sg:address":"Orkotten 66",
    "sg:city":"Telgte",
    "sg:phone":"+49 4933/035260",
    "sg:postcode":"48291",
    "sg:province":"Nordrhein-Westfalen",
    "wof:name":"Tur Elektromedizin Gmbh",
    "wof:placetype":"venue"
},
  "geometry": {"coordinates":[13.2804002762,52.6702919006],"type":"Point"}
}