{
  "type": "Feature",
  "properties": {
    "iso:country":"DE",
    "sg:address":"Cleverhofer Weg 61",
    "sg:city":"Bad Schwartau",
    "sg:phone":"+49 451/280700",
    "sg:postcode":"23611",
    "sg:province":"Schleswig-Holstein",
    "wof:name":"Engel Display Gmbh & Co. Kg",
    "wof:placetype":"venue"
},
  "geometry": {"coordinates":[10.6709547043,53.9110794067],"type":"Point"}
}