{
  "type": "Feature",
  "properties": {
    "iso:country":"DE",
    "sg:address":"Bundesstr. 70",
    "sg:city":"Marienhafe",
    "sg:phone":"+49 4934/1001",
    "sg:postcode":"26529",
    "sg:province":"Niedersachsen",
    "wof:name":"Siebels Baumarkt Eisenwaren Haushalts- Und",
    "wof:placetype":"venue"
},
  "geometry": {"coordinates":[7.2761650085,53.5136947632],"type":"Point"}
}