{
  "type": "Feature",
  "properties": {
    "iso:country":"DE",
    "sg:address":"Ansdorfer Str. 9",
    "sg:city":"Hohenwarth",
    "sg:phone":"+49 9946/352",
    "sg:postcode":"93480",
    "sg:province":"Bayern",
    "wof:name":"Gastst\u00e4tte Hans M\u00fchlbauer",
    "wof:placetype":"venue"
},
  "geometry": {"coordinates":[12.9502038956,49.2108154297],"type":"Point"}
}