{
  "type": "Feature",
  "properties": {
    "iso:country":"DE",
    "sg:address":"Karl-Marx-Str. 35",
    "sg:city":"Blankenfelde",
    "sg:phone":"+49 3379/372919",
    "sg:postcode":"15827",
    "sg:province":"Brandenburg",
    "wof:name":"Manfred Stechow",
    "wof:placetype":"venue"
},
  "geometry": {"coordinates":[13.4196920395,52.3386726379],"type":"Point"}
}