{
  "type": "Feature",
  "properties": {
    "iso:country":"DE",
    "sg:address":"Karl-Marx-Allee 137",
    "sg:city":"Berlin",
    "sg:phone":"+49 30/5899441",
    "sg:postcode":"10243",
    "sg:province":"Berlin",
    "wof:name":"Stephan M. Englberger",
    "wof:placetype":"venue"
},
  "geometry": {"coordinates":[13.451945,52.516212],"type":"Point"}
}