{
  "type": "Feature",
  "properties": {
    "iso:country":"DE",
    "sg:address":"Hagenstr. 4",
    "sg:city":"Gelsenkirchen",
    "sg:phone":"+49 209/9334300",
    "sg:postcode":"45894",
    "sg:province":"Nordrhein-Westfalen",
    "wof:name":"Hotel Buerer Hof",
    "wof:placetype":"venue"
},
  "geometry": {"coordinates":[7.0520858765,51.5772819519],"type":"Point"}
}