{
  "type": "Feature",
  "properties": {
    "iso:country":"DE",
    "sg:address":"M\u00fchlenstr. 1",
    "sg:city":"Doberlug-Kirchhain",
    "sg:postcode":"03253",
    "sg:province":"Brandenburg",
    "wof:name":"M\u00fcller & Partner",
    "wof:placetype":"venue"
},
  "geometry": {"coordinates":[13.4325771332,51.6625976562],"type":"Point"}
}