{
  "type": "Feature",
  "properties": {
    "iso:country":"DE",
    "sg:address":"Gro\u00dfmaischeider Str. 63",
    "sg:city":"Kleinmaischeid",
    "sg:phone":"+49 2689",
    "sg:postcode":"56271",
    "sg:province":"Rheinland-Pfalz",
    "wof:name":"Dlc Neuwied Ggmbh",
    "wof:placetype":"venue"
},
  "geometry": {"coordinates":[7.604665,50.509407],"type":"Point"}
}