{
  "type": "Feature",
  "properties": {
    "iso:country":"DE",
    "sg:address":"Antwerpener Str. 56",
    "sg:city":"Kerpen",
    "sg:phone":"+49 2237/4598",
    "sg:postcode":"50171",
    "sg:province":"Nordrhein-Westfalen",
    "wof:name":"H. Th\u00f6rnig",
    "wof:placetype":"venue"
},
  "geometry": {"coordinates":[6.678907,50.870743],"type":"Point"}
}