{
  "type": "Feature",
  "properties": {
    "iso:country":"DE",
    "sg:address":"Alter Wixh\u00e4user Weg 8",
    "sg:city":"Darmstadt",
    "sg:phone":"+49 6151/154165",
    "sg:postcode":"64291",
    "sg:province":"Hessen",
    "wof:name":"Arztservice Wente Gmbh",
    "wof:placetype":"venue"
},
  "geometry": {"coordinates":[8.6518211365,49.9131813049],"type":"Point"}
}