{
  "type": "Feature",
  "properties": {
    "iso:country":"DE",
    "sg:address":"Damaschkestr. 66",
    "sg:city":"Bubenreuth",
    "sg:phone":"+49 9131/22645",
    "sg:postcode":"91088",
    "sg:province":"Bayern",
    "wof:name":"Helmut Neubauer",
    "wof:placetype":"venue"
},
  "geometry": {"coordinates":[11.0034952164,49.6173744202],"type":"Point"}
}