{
  "type": "Feature",
  "properties": {
    "iso:country":"DE",
    "sg:address":"Hamburger Chaussee 10",
    "sg:city":"Molfsee",
    "sg:phone":"+49 4347/3309",
    "sg:postcode":"24113",
    "sg:province":"Schleswig-Holstein",
    "wof:name":"Hotel-restaurant B\u00e4renkrug",
    "wof:placetype":"venue"
},
  "geometry": {"coordinates":[10.0631256104,54.2607879639],"type":"Point"}
}