{
  "type": "Feature",
  "properties": {
    "iso:country":"DE",
    "sg:address":"Reichenbacher Str. 65",
    "sg:city":"Greiz",
    "sg:postcode":"07973",
    "sg:province":"Th\u00fcringen",
    "wof:name":"Fr\u00f6de & R\u00fcger Gesch\u00e4ftsf\u00fchrungs-gmbh",
    "wof:placetype":"venue"
},
  "geometry": {"coordinates":[12.2130479813,50.6524429321],"type":"Point"}
}