{
  "type": "Feature",
  "properties": {
    "iso:country":"DE",
    "sg:address":"Ottmachauer Str. 3",
    "sg:city":"Beckum",
    "sg:phone":"+49 2521/7016",
    "sg:postcode":"59269",
    "sg:province":"Nordrhein-Westfalen",
    "wof:name":"Kauffel Industrieservice Gmbh",
    "wof:placetype":"venue"
},
  "geometry": {"coordinates":[8.013588,51.753685],"type":"Point"}
}