{
  "type": "Feature",
  "properties": {
    "iso:country":"DE",
    "sg:address":"Elbstr. 4",
    "sg:city":"Wittenberge",
    "sg:postcode":"19322",
    "sg:province":"Brandenburg",
    "wof:name":"Gro\u00dfhandel Versorgungskontor Papier Und Schreibwaren Gmbh",
    "wof:placetype":"venue"
},
  "geometry": {"coordinates":[11.751753,52.990097],"type":"Point"}
}