{
  "type": "Feature",
  "properties": {
    "iso:country":"DE",
    "sg:address":"Stapenhorststr. 48",
    "sg:city":"Bielefeld",
    "sg:phone":"+49 521/131823",
    "sg:postcode":"33615",
    "sg:province":"Nordrhein-Westfalen",
    "wof:name":"Wellmann",
    "wof:placetype":"venue"
},
  "geometry": {"coordinates":[8.5216770172,52.0263671875],"type":"Point"}
}