{
  "type": "Feature",
  "properties": {
    "iso:country":"DE",
    "sg:address":"Klaragasse 24",
    "sg:city":"N\u00fcrnberg",
    "sg:phone":"+49 911/226621",
    "sg:postcode":"90402",
    "sg:province":"Bayern",
    "wof:name":"China-restaurant Hong Kong",
    "wof:placetype":"venue"
},
  "geometry": {"coordinates":[11.0775356293,49.4488639832],"type":"Point"}
}