{
  "type": "Feature",
  "properties": {
    "iso:country":"DE",
    "sg:address":"Beifu\u00dfweg 29",
    "sg:city":"Berlin",
    "sg:phone":"+49 30/6611606",
    "sg:postcode":"12357",
    "sg:province":"Berlin",
    "wof:name":"Joachim K\u00fchn",
    "wof:placetype":"venue"
},
  "geometry": {"coordinates":[13.477067,52.436741],"type":"Point"}
}