{
  "type": "Feature",
  "properties": {
    "iso:country":"DE",
    "sg:address":"Fuchsrain 30",
    "sg:city":"N\u00fcrtingen",
    "sg:phone":"+49 7022/51724",
    "sg:postcode":"72622",
    "sg:province":"Baden-W\u00fcrttemberg",
    "wof:name":"Verein Der Freunde Des H\u00f6lderlin-gymnasiums",
    "wof:placetype":"venue"
},
  "geometry": {"coordinates":[9.3009595871,48.6429328918],"type":"Point"}
}