{
  "type": "Feature",
  "properties": {
    "iso:country":"DE",
    "sg:address":"Kirchenweg 6",
    "sg:city":"Altenstadt",
    "sg:phone":"+49 8861/4401",
    "sg:postcode":"86972",
    "sg:province":"Bayern",
    "wof:name":"Hans Deschler",
    "wof:placetype":"venue"
},
  "geometry": {"coordinates":[10.8729305267,47.8229522705],"type":"Point"}
}