{
  "type": "Feature",
  "properties": {
    "iso:country":"DE",
    "sg:address":"Eversbuschstr. 7 e",
    "sg:city":"M\u00fcnchen",
    "sg:phone":"+49 89/8120353",
    "sg:postcode":"80999",
    "sg:province":"Bayern",
    "wof:name":"Gert Rossmann Architekt",
    "wof:placetype":"venue"
},
  "geometry": {"coordinates":[11.460285,48.18996],"type":"Point"}
}