{
  "type": "Feature",
  "properties": {
    "iso:country":"DE",
    "sg:address":"Hauptstr. 10",
    "sg:city":"Kehl",
    "sg:phone":"+49 7851/3135",
    "sg:postcode":"77694",
    "sg:province":"Baden-W\u00fcrttemberg",
    "wof:name":"Claudia Osiander",
    "wof:placetype":"venue"
},
  "geometry": {"coordinates":[7.8076558113,48.5748977661],"type":"Point"}
}