{
  "type": "Feature",
  "properties": {
    "iso:country":"DE",
    "sg:address":"Sch\u00f6nau",
    "sg:city":"Gem\u00fcnden",
    "sg:phone":"+49 9357/1428",
    "sg:postcode":"97737",
    "sg:province":"Bayern",
    "wof:name":"J. Berthold",
    "wof:placetype":"venue"
},
  "geometry": {"coordinates":[9.7206411362,50.0760993958],"type":"Point"}
}