{
  "type": "Feature",
  "properties": {
    "iso:country":"DE",
    "sg:address":"Hauptstr. 22",
    "sg:city":"Rennersdorf",
    "sg:phone":"+49 35873/2981",
    "sg:postcode":"02747",
    "sg:province":"Sachsen",
    "wof:name":"G\u00fcnter Renger",
    "wof:placetype":"venue"
},
  "geometry": {"coordinates":[14.778536,51.022686],"type":"Point"}
}