{
  "type": "Feature",
  "properties": {
    "iso:country":"DE",
    "sg:address":"Hundiek 8",
    "sg:city":"Dannewerk",
    "sg:phone":"+49 4621/34159",
    "sg:postcode":"24867",
    "sg:province":"Schleswig-Holstein",
    "wof:name":"Ernst-heinrich Clausen",
    "wof:placetype":"venue"
},
  "geometry": {"coordinates":[9.500544,54.491943],"type":"Point"}
}