{
  "type": "Feature",
  "properties": {
    "iso:country":"DE",
    "sg:address":"Alte Poststr. 2",
    "sg:city":"Weyhe",
    "sg:phone":"+49 421/802606",
    "sg:postcode":"28844",
    "sg:province":"Niedersachsen",
    "wof:name":"Leeste Saunahaus",
    "wof:placetype":"venue"
},
  "geometry": {"coordinates":[8.815656,52.988815],"type":"Point"}
}