{
  "type": "Feature",
  "properties": {
    "iso:country":"DE",
    "sg:address":"Dieselstr 15",
    "sg:city":"Wadersloh",
    "sg:phone":"+49 2523/92260",
    "sg:postcode":"59329",
    "sg:province":"Nordrhein-Westfalen",
    "wof:name":"Oesterwiemann Gmbh",
    "wof:placetype":"venue"
},
  "geometry": {"coordinates":[8.2582168579,51.735824585],"type":"Point"}
}