{
  "type": "Feature",
  "properties": {
    "iso:country":"DE",
    "sg:address":"Ritterstr. 60B",
    "sg:city":"Berlin",
    "sg:phone":"+49 30/25291813",
    "sg:postcode":"10969",
    "sg:province":"Berlin",
    "wof:name":"Sicherheitstechnik Wolfram Wei\u00df Gmbh",
    "wof:placetype":"venue"
},
  "geometry": {"coordinates":[13.397462,52.50536],"type":"Point"}
}