{
  "type": "Feature",
  "properties": {
    "iso:country":"DE",
    "sg:address":"Ermlandstr. 95",
    "sg:city":"Bremen",
    "sg:postcode":"28777",
    "sg:province":"Bremen",
    "wof:name":"Vulkan Dieselmotoren Service Und Verwaltungs Gmbh",
    "wof:placetype":"venue"
},
  "geometry": {"coordinates":[8.5514392853,53.1964950562],"type":"Point"}
}