{
  "type": "Feature",
  "properties": {
    "iso:country":"DE",
    "sg:address":"Siegfriedstrasse 22",
    "sg:city":"Obernburg",
    "sg:phone":"+49 6022/649320",
    "sg:postcode":"63785",
    "sg:province":"Bayern",
    "wof:name":"Fach\u00fcbersetzung",
    "wof:placetype":"venue"
},
  "geometry": {"coordinates":[9.13424,49.83445],"type":"Point"}
}