{
  "type": "Feature",
  "properties": {
    "iso:country":"DE",
    "sg:address":"Maschener Kirchweg 49 a",
    "sg:city":"Seevetal",
    "sg:phone":"+49 4105/570844",
    "sg:postcode":"21218",
    "sg:province":"Niedersachsen",
    "wof:name":"Eisa G\u00fcnter Renno Gmbh",
    "wof:placetype":"venue"
},
  "geometry": {"coordinates":[9.9945631027,53.3845443726],"type":"Point"}
}