{
  "type": "Feature",
  "properties": {
    "iso:country":"DE",
    "sg:address":"An der Hansa-Linie 5",
    "sg:city":"Ascheberg",
    "sg:phone":"+49 2593/950400",
    "sg:postcode":"59387",
    "sg:province":"Nordrhein-Westfalen",
    "wof:name":"Wassmann Gmbh",
    "wof:placetype":"venue"
},
  "geometry": {"coordinates":[7.6185069084,51.7977218628],"type":"Point"}
}