{
  "type": "Feature",
  "properties": {
    "iso:country":"DE",
    "sg:address":"Pfarrkirchener Str. 40",
    "sg:city":"Eggenfelden",
    "sg:phone":"+49 8721/96340",
    "sg:postcode":"84307",
    "sg:province":"Bayern",
    "wof:name":"St. Johannisverein Eggenfelden E. V.",
    "wof:placetype":"venue"
},
  "geometry": {"coordinates":[12.7628889084,48.4023742676],"type":"Point"}
}