{
  "type": "Feature",
  "properties": {
    "iso:country":"DE",
    "sg:address":"Hauptstr. 21",
    "sg:city":"Erlenmoos",
    "sg:phone":"+49 7352/2876",
    "sg:postcode":"88416",
    "sg:province":"Baden-W\u00fcrttemberg",
    "wof:name":"Werner Pfender",
    "wof:placetype":"venue"
},
  "geometry": {"coordinates":[9.9752149582,48.0652503967],"type":"Point"}
}