{
  "type": "Feature",
  "properties": {
    "iso:country":"DE",
    "sg:address":"Oelm\u00fchlenstr. 17",
    "sg:city":"Neubrandenburg",
    "sg:phone":"+49 395/5822121",
    "sg:postcode":"17033",
    "sg:province":"Mecklenburg-Vorpommern",
    "wof:name":"Manfred Callies",
    "wof:placetype":"venue"
},
  "geometry": {"coordinates":[13.2393074036,53.5516319275],"type":"Point"}
}