{
  "type": "Feature",
  "properties": {
    "iso:country":"DE",
    "sg:address":"Scharrerstr. 28",
    "sg:city":"Grafenau",
    "sg:phone":"+49 8552/1441",
    "sg:postcode":"94481",
    "sg:province":"Bayern",
    "wof:name":"Adolf Stockinger",
    "wof:placetype":"venue"
},
  "geometry": {"coordinates":[13.39696,48.857574],"type":"Point"}
}