{
  "type": "Feature",
  "properties": {
    "iso:country":"DE",
    "sg:address":"Landwehrweg 9",
    "sg:city":"Lemf\u00f6rde",
    "sg:phone":"+49 4954/43120",
    "sg:postcode":"49448",
    "sg:province":"Niedersachsen",
    "wof:name":"Elastogran Gmbh",
    "wof:placetype":"venue"
},
  "geometry": {"coordinates":[8.3848028183,52.4605293274],"type":"Point"}
}