{
  "type": "Feature",
  "properties": {
    "iso:country":"DE",
    "sg:address":"Ludmillastr. 20a",
    "sg:city":"M\u00fcnchen",
    "sg:phone":"+49 89/663466",
    "sg:postcode":"81543",
    "sg:province":"Bayern",
    "wof:name":"Repro Ruppert Lichtpausen",
    "wof:placetype":"venue"
},
  "geometry": {"coordinates":[11.5678405762,48.1101074219],"type":"Point"}
}