{
  "type": "Feature",
  "properties": {
    "iso:country":"DE",
    "sg:address":"breitscheid-str. 33b",
    "sg:city":"gro\u00dfp\u00f6sna",
    "sg:phone":"+49 34297/86569",
    "sg:postcode":"04463",
    "sg:province":"Sachsen",
    "wof:name":"Kathrin Kiehl Bei Peregrina",
    "wof:placetype":"venue"
},
  "geometry": {"coordinates":[12.506262,51.258446],"type":"Point"}
}