{
  "type": "Feature",
  "properties": {
    "iso:country":"DE",
    "sg:address":"Raiffeisenstr. 4",
    "sg:city":"Uslar",
    "sg:phone":"+49 5573/244",
    "sg:postcode":"37170",
    "sg:province":"Niedersachsen",
    "wof:name":"Ev. Pfarramt Volpriehausen",
    "wof:placetype":"venue"
},
  "geometry": {"coordinates":[9.7383270264,51.6659202576],"type":"Point"}
}