{
  "type": "Feature",
  "properties": {
    "iso:country":"DE",
    "sg:address":"Seestr. 30",
    "sg:city":"Diemelsee",
    "sg:phone":"+49 5633/1310",
    "sg:postcode":"34519",
    "sg:province":"Hessen",
    "wof:name":"G\u00e4stehaus I. Fischer",
    "wof:placetype":"venue"
},
  "geometry": {"coordinates":[8.7327899933,51.3643608093],"type":"Point"}
}