{
  "type": "Feature",
  "properties": {
    "iso:country":"DE",
    "sg:address":"Brunnenrainstr. 14",
    "sg:city":"Lohr",
    "sg:phone":"+49 9352/3050",
    "sg:postcode":"97816",
    "sg:province":"Bayern",
    "wof:name":"H. Und Marianne Volkert",
    "wof:placetype":"venue"
},
  "geometry": {"coordinates":[9.5856971741,49.9933738708],"type":"Point"}
}