{
  "type": "Feature",
  "properties": {
    "iso:country":"DE",
    "sg:address":"Ziegenhainer Str. 179",
    "sg:city":"Frankfurt",
    "sg:phone":"+49 69/526170",
    "sg:postcode":"60433",
    "sg:province":"Hessen",
    "wof:name":"Dietrich Janke",
    "wof:placetype":"venue"
},
  "geometry": {"coordinates":[8.6703548431,50.1553077698],"type":"Point"}
}