{
  "type": "Feature",
  "properties": {
    "iso:country":"DE",
    "sg:address":"Bergstr. 1a",
    "sg:city":"Emmerich",
    "sg:phone":"+49 2828/2561",
    "sg:postcode":"46446",
    "sg:province":"Nordrhein-Westfalen",
    "wof:name":"Eiscafe San Remo",
    "wof:placetype":"venue"
},
  "geometry": {"coordinates":[6.159449,51.871552],"type":"Point"}
}