{
  "type": "Feature",
  "properties": {
    "iso:country":"DE",
    "sg:address":"Lindenstr. 37",
    "sg:city":"Bad Essen",
    "sg:phone":"+49 5472/6529",
    "sg:postcode":"49152",
    "sg:province":"Niedersachsen",
    "wof:name":"Paul Wiese",
    "wof:placetype":"venue"
},
  "geometry": {"coordinates":[8.34246,52.319843],"type":"Point"}
}