{
  "type": "Feature",
  "properties": {
    "iso:country":"DE",
    "sg:address":"Am Ochsenweg 9",
    "sg:city":"Fockbek",
    "sg:phone":"+49 4331/62326",
    "sg:postcode":"24787",
    "sg:province":"Schleswig-Holstein",
    "wof:name":"Hans-helmut Brammer",
    "wof:placetype":"venue"
},
  "geometry": {"coordinates":[9.5950069427,54.3084182739],"type":"Point"}
}