{
  "type": "Feature",
  "properties": {
    "iso:country":"DE",
    "sg:address":"Bahnhofstr. 134",
    "sg:city":"Voerde",
    "sg:phone":"+49 2855/4126",
    "sg:postcode":"46562",
    "sg:province":"Nordrhein-Westfalen",
    "wof:name":"D. Krebber",
    "wof:placetype":"venue"
},
  "geometry": {"coordinates":[6.692109,51.598682],"type":"Point"}
}