{
  "type": "Feature",
  "properties": {
    "iso:country":"DE",
    "sg:address":"Schlo\u00dfstr.",
    "sg:city":"Bergisch Gladbach",
    "sg:phone":"+49 2204/57683",
    "sg:postcode":"51429",
    "sg:province":"Nordrhein-Westfalen",
    "wof:name":"Dieter Sauerwald",
    "wof:placetype":"venue"
},
  "geometry": {"coordinates":[7.1636052132,50.9639205933],"type":"Point"}
}