{
  "type": "Feature",
  "properties": {
    "iso:country":"DE",
    "sg:address":"Busestr. 94",
    "sg:city":"Bremen",
    "sg:phone":"+49 421/2010310",
    "sg:postcode":"28213",
    "sg:province":"Bremen",
    "wof:name":"Friedensdenkmal 1995 E. V. J\u00fcrgen Engel",
    "wof:placetype":"venue"
},
  "geometry": {"coordinates":[8.8433227539,53.0952835083],"type":"Point"}
}