{
  "type": "Feature",
  "properties": {
    "iso:country":"DE",
    "sg:address":"Eisenstr. 28",
    "sg:city":"Morsbach",
    "sg:phone":"+49 2294/8061",
    "sg:postcode":"51597",
    "sg:province":"Nordrhein-Westfalen",
    "wof:name":"Optirent Mobilraum-mietservice Gmbh",
    "wof:placetype":"venue"
},
  "geometry": {"coordinates":[7.6499300003,50.8405303955],"type":"Point"}
}