{
  "type": "Feature",
  "properties": {
    "iso:country":"DE",
    "sg:address":"Fabeckstr. 20",
    "sg:city":"Berlin",
    "sg:phone":"+49 30/8314180",
    "sg:postcode":"14195",
    "sg:province":"Berlin",
    "wof:name":"J\u00f6rg-p. Anders",
    "wof:placetype":"venue"
},
  "geometry": {"coordinates":[13.2917881012,52.4549407959],"type":"Point"}
}