{
  "type": "Feature",
  "properties": {
    "iso:country":"DE",
    "sg:address":"Sophienstr. 46",
    "sg:city":"Frankfurt",
    "sg:phone":"+49 69/702590",
    "sg:postcode":"60487",
    "sg:province":"Hessen",
    "wof:name":"Anna Van Der Meulen \u00dcbersetzungsb\u00fcro",
    "wof:placetype":"venue"
},
  "geometry": {"coordinates":[8.649712,50.123604],"type":"Point"}
}