{
  "type": "Feature",
  "properties": {
    "iso:country":"DE",
    "sg:address":"M\u00fchlstr. 77",
    "sg:city":"Aschaffenburg",
    "sg:phone":"+49 6021/423312",
    "sg:postcode":"63741",
    "sg:province":"Bayern",
    "wof:name":"Elfriede Gerlach",
    "wof:placetype":"venue"
},
  "geometry": {"coordinates":[9.128517,49.986259],"type":"Point"}
}