{
  "type": "Feature",
  "properties": {
    "iso:country":"DE",
    "sg:address":"Museumstr. 14",
    "sg:city":"Neuwied",
    "sg:phone":"+49 2631/25470",
    "sg:postcode":"56564",
    "sg:province":"Rheinland-Pfalz",
    "wof:name":"Fr. Schuler",
    "wof:placetype":"venue"
},
  "geometry": {"coordinates":[7.469084,50.429169],"type":"Point"}
}