{
  "type": "Feature",
  "properties": {
    "iso:country":"DE",
    "sg:address":"Doberaner Hof 10",
    "sg:city":"Rostock",
    "sg:phone":"+49 381/4934205",
    "sg:postcode":"18057",
    "sg:province":"Mecklenburg-Vorpommern",
    "wof:name":"Seidels Brasserie",
    "wof:placetype":"venue"
},
  "geometry": {"coordinates":[12.123916626,54.087978363],"type":"Point"}
}