{
  "type": "Feature",
  "properties": {
    "iso:country":"DE",
    "sg:address":"Sch\u00e4ferstr. 2",
    "sg:city":"Dessau",
    "sg:phone":"+49 340/8828882",
    "sg:postcode":"06849",
    "sg:province":"Sachsen-Anhalt",
    "wof:name":"T\u00f6rtener Klause",
    "wof:placetype":"venue"
},
  "geometry": {"coordinates":[12.2547636032,51.7958068848],"type":"Point"}
}