{
  "type": "Feature",
  "properties": {
    "iso:country":"DE",
    "sg:address":"Hansaallee 321/20",
    "sg:city":"D\u00fcsseldorf",
    "sg:phone":"+49 211/53605100",
    "sg:postcode":"40549",
    "sg:province":"Nordrhein-Westfalen",
    "wof:name":"Hoffmann Messebau Gmbh",
    "wof:placetype":"venue"
},
  "geometry": {"coordinates":[6.716383,51.244911],"type":"Point"}
}