{
  "type": "Feature",
  "properties": {
    "iso:country":"DE",
    "sg:address":"M\u00fchlenkamp 10",
    "sg:city":"Telgte",
    "sg:phone":"+49 2504/8423",
    "sg:postcode":"48291",
    "sg:province":"Nordrhein-Westfalen",
    "wof:name":"G\u00fcnter R\u00f6bbelen",
    "wof:placetype":"venue"
},
  "geometry": {"coordinates":[7.783218,51.985588],"type":"Point"}
}