{
  "type": "Feature",
  "properties": {
    "iso:country":"DE",
    "sg:address":"Prinzregentenstr. 78",
    "sg:city":"M\u00fcnchen",
    "sg:postcode":"81675",
    "sg:province":"Bayern",
    "wof:name":"Focus Digital Ag",
    "wof:placetype":"venue"
},
  "geometry": {"coordinates":[11.602687,48.140049],"type":"Point"}
}