{
  "type": "Feature",
  "properties": {
    "iso:country":"DE",
    "sg:city":"R\u00f6dinghausen",
    "sg:phone":"+49 4957/468393",
    "sg:postcode":"32289",
    "sg:province":"Nordrhein-Westfalen",
    "wof:name":"Kreissparkasse Herford",
    "wof:placetype":"venue"
},
  "geometry": {"coordinates":[8.480574,52.251228],"type":"Point"}
}