{
  "type": "Feature",
  "properties": {
    "iso:country":"DE",
    "sg:address":"Neustr. 32a",
    "sg:city":"Moers",
    "sg:phone":"+49 2841/21169",
    "sg:postcode":"47441",
    "sg:province":"Nordrhein-Westfalen",
    "wof:name":"Henry's Sportswear Gmbh",
    "wof:placetype":"venue"
},
  "geometry": {"coordinates":[6.623395,51.451946],"type":"Point"}
}