{
  "type": "Feature",
  "properties": {
    "iso:country":"DE",
    "sg:address":"Hofstr. 4 B",
    "sg:city":"Velgast",
    "sg:postcode":"18469",
    "sg:province":"Mecklenburg-Vorpommern",
    "wof:name":"Lewa Bauservice Gmbh",
    "wof:placetype":"venue"
},
  "geometry": {"coordinates":[12.794907,54.243958],"type":"Point"}
}