{
  "type": "Feature",
  "properties": {
    "iso:country":"DE",
    "sg:address":"Am M\u00fchlentor 20",
    "sg:city":"Warin",
    "sg:postcode":"19417",
    "sg:province":"Mecklenburg-Vorpommern",
    "wof:name":"Druckservice Heiser Handel Mit Werkzeug",
    "wof:placetype":"venue"
},
  "geometry": {"coordinates":[11.70225,53.799816],"type":"Point"}
}