{
  "type": "Feature",
  "properties": {
    "iso:country":"DE",
    "sg:address":"Carsten-Dre\u00dfler-Str. 18",
    "sg:city":"Bremen",
    "sg:phone":"+49 421/4841234",
    "sg:postcode":"28279",
    "sg:province":"Bremen",
    "wof:name":"Hogema Maschinenhandel Gmbh",
    "wof:placetype":"venue"
},
  "geometry": {"coordinates":[8.849256,53.034775],"type":"Point"}
}