{
  "type": "Feature",
  "properties": {
    "iso:country":"DE",
    "sg:address":"Neumarkt 6",
    "sg:city":"Schwelm",
    "sg:phone":"+49 2336/3272",
    "sg:postcode":"58332",
    "sg:province":"Nordrhein-Westfalen",
    "wof:name":"H. Gerkau Strumpfwaren-grosshandel",
    "wof:placetype":"venue"
},
  "geometry": {"coordinates":[7.294356823,51.2852516174],"type":"Point"}
}