{
  "type": "Feature",
  "properties": {
    "iso:country":"DE",
    "sg:address":"Eichenstr. 8",
    "sg:city":"Lupburg",
    "sg:postcode":"92331",
    "sg:province":"Bayern",
    "wof:name":"Maschinenbau Silberhorn Gmbh",
    "wof:placetype":"venue"
},
  "geometry": {"coordinates":[11.760494,49.15189],"type":"Point"}
}