{
  "type": "Feature",
  "properties": {
    "iso:country":"DE",
    "sg:address":"Marienburger Str. 22",
    "sg:city":"Meerbusch",
    "sg:phone":"+49 2132/71407",
    "sg:postcode":"40667",
    "sg:province":"Nordrhein-Westfalen",
    "wof:name":"Ingeborg Werner Architektin",
    "wof:placetype":"venue"
},
  "geometry": {"coordinates":[6.700848,51.241337],"type":"Point"}
}