{
  "type": "Feature",
  "properties": {
    "iso:country":"DE",
    "sg:address":"Krefelder Str. 79",
    "sg:city":"Aachen",
    "sg:phone":"+49 241/159336",
    "sg:postcode":"52070",
    "sg:province":"Nordrhein-Westfalen",
    "wof:name":"Latzel & Havenith",
    "wof:placetype":"venue"
},
  "geometry": {"coordinates":[6.092131,50.786247],"type":"Point"}
}