{
  "type": "Feature",
  "properties": {
    "iso:country":"DE",
    "sg:address":"Frickenberg 16",
    "sg:city":"Sundern",
    "sg:phone":"+49 2933/79016",
    "sg:postcode":"59846",
    "sg:province":"Nordrhein-Westfalen",
    "wof:name":"Deutscher Amateur-radio- Club E. V.",
    "wof:placetype":"venue"
},
  "geometry": {"coordinates":[8.0092010498,51.3311805725],"type":"Point"}
}