{
  "type": "Feature",
  "properties": {
    "iso:country":"DE",
    "sg:address":"Simbeckstr. 16",
    "sg:city":"Weilheim",
    "sg:phone":"+49 881/9095346",
    "sg:postcode":"82362",
    "sg:province":"Bayern",
    "wof:name":"Case Software Gmbh",
    "wof:placetype":"venue"
},
  "geometry": {"coordinates":[11.1579647064,47.839717865],"type":"Point"}
}