{
  "type": "Feature",
  "properties": {
    "iso:country":"DE",
    "sg:address":"Max-Planck-Str. 1e",
    "sg:city":"Paderborn",
    "sg:phone":"+49 5254/7681",
    "sg:postcode":"33104",
    "sg:province":"Nordrhein-Westfalen",
    "wof:name":"Kamo Industriemontage Gmbh",
    "wof:placetype":"venue"
},
  "geometry": {"coordinates":[8.706278,51.76825],"type":"Point"}
}