{
  "type": "Feature",
  "properties": {
    "iso:country":"DE",
    "sg:address":"Hauptstr. 414",
    "sg:city":"Herne",
    "sg:phone":"+49 2325/988150",
    "sg:postcode":"44653",
    "sg:province":"Nordrhein-Westfalen",
    "wof:name":"Helvetia Versicherungen Michael Strauch",
    "wof:placetype":"venue"
},
  "geometry": {"coordinates":[7.1604380608,51.5439376831],"type":"Point"}
}