{
  "type": "Feature",
  "properties": {
    "iso:country":"DE",
    "sg:address":"Rebbergstr. 39",
    "sg:city":"Konstanz",
    "sg:phone":"+49 7531/61505",
    "sg:postcode":"78464",
    "sg:province":"Baden-W\u00fcrttemberg",
    "wof:name":"Werner Graf Architekt",
    "wof:placetype":"venue"
},
  "geometry": {"coordinates":[9.180467,47.677235],"type":"Point"}
}