{
  "type": "Feature",
  "properties": {
    "iso:country":"DE",
    "sg:address":"An der Steige 1",
    "sg:city":"Ammerndorf",
    "sg:phone":"+49 9127/578395",
    "sg:postcode":"90614",
    "sg:province":"Bayern",
    "wof:name":"Fga Malerwerkstatt Gmbh",
    "wof:placetype":"venue"
},
  "geometry": {"coordinates":[10.858477,49.421741],"type":"Point"}
}