{
  "type": "Feature",
  "properties": {
    "iso:country":"DE",
    "sg:address":"Felderbachstr. 9",
    "sg:city":"Hattingen",
    "sg:phone":"+49 2052/6415",
    "sg:postcode":"45529",
    "sg:province":"Nordrhein-Westfalen",
    "wof:name":"Landgasthaus Huxel",
    "wof:placetype":"venue"
},
  "geometry": {"coordinates":[7.1641831398,51.3579330444],"type":"Point"}
}