{
  "type": "Feature",
  "properties": {
    "iso:country":"DE",
    "sg:address":"M\u00fchlenweg 10",
    "sg:city":"Toba",
    "sg:phone":"+49 36330/65324",
    "sg:postcode":"99713",
    "sg:province":"Th\u00fcringen",
    "wof:name":"Ltm Nitschke & Sohn Gmbh",
    "wof:placetype":"venue"
},
  "geometry": {"coordinates":[10.68206,51.322021],"type":"Point"}
}