{
  "type": "Feature",
  "properties": {
    "iso:country":"DE",
    "sg:address":"August-Bebel-Str. 9",
    "sg:city":"Jena",
    "sg:phone":"+49 3641/42960",
    "sg:postcode":"07743",
    "sg:province":"Th\u00fcringen",
    "wof:name":"Bergerhoff Und Kollegen Rechtsanw\u00e4lte",
    "wof:placetype":"venue"
},
  "geometry": {"coordinates":[11.5774879456,50.9313735962],"type":"Point"}
}