{
  "type": "Feature",
  "properties": {
    "iso:country":"DE",
    "sg:address":"Saar-Pfalz-Str. 57",
    "sg:city":"Bexbach",
    "sg:phone":"+49 6826/7119",
    "sg:postcode":"66450",
    "sg:province":"Saarland",
    "wof:name":"Benno H\u00fcther",
    "wof:placetype":"venue"
},
  "geometry": {"coordinates":[7.273578,49.38924],"type":"Point"}
}