{
  "type": "Feature",
  "properties": {
    "iso:country":"DE",
    "sg:address":"Hauptstr. 30",
    "sg:city":"Pfaffenhofen",
    "sg:phone":"+49 4973/025264",
    "sg:postcode":"89284",
    "sg:province":"Bayern",
    "wof:name":"Sparkasse Neu-ulm",
    "wof:placetype":"venue"
},
  "geometry": {"coordinates":[8.972701,49.064095],"type":"Point"}
}