{
  "type": "Feature",
  "properties": {
    "iso:country":"DE",
    "sg:address":"Bahnstr. 11a",
    "sg:city":"Langenselbold",
    "sg:phone":"+49 6184/3508",
    "sg:postcode":"63505",
    "sg:province":"Hessen",
    "wof:name":"Steakhaus",
    "wof:placetype":"venue"
},
  "geometry": {"coordinates":[9.0432348251,50.1745071411],"type":"Point"}
}