{
  "type": "Feature",
  "properties": {
    "iso:country":"DE",
    "sg:address":"Am Halfenberg 11",
    "sg:city":"K\u00fcrten",
    "sg:phone":"+49 2268/1323",
    "sg:postcode":"51515",
    "sg:province":"Nordrhein-Westfalen",
    "wof:name":"Frank Clever Masseur",
    "wof:placetype":"venue"
},
  "geometry": {"coordinates":[7.259743,51.051613],"type":"Point"}
}