{
  "type": "Feature",
  "properties": {
    "iso:country":"DE",
    "sg:address":"Achterdwars 18",
    "sg:city":"Hamburg",
    "sg:phone":"+49 40/7258680",
    "sg:postcode":"21035",
    "sg:province":"Hamburg",
    "wof:name":"Elektro Eckstein Gmbh",
    "wof:placetype":"venue"
},
  "geometry": {"coordinates":[10.19994,53.486591],"type":"Point"}
}