{
  "type": "Feature",
  "properties": {
    "iso:country":"DE",
    "sg:address":"H\u00fcglerstr. 26",
    "sg:city":"Wiesbaden",
    "sg:phone":"+49 611/607385",
    "sg:postcode":"65203",
    "sg:province":"Hessen",
    "wof:name":"Helmut Habrich Ingenieur",
    "wof:placetype":"venue"
},
  "geometry": {"coordinates":[8.252212,50.05027],"type":"Point"}
}