{
  "type": "Feature",
  "properties": {
    "iso:country":"DE",
    "sg:address":"Brauhausplatz 3",
    "sg:city":"Wanfried",
    "sg:phone":"+49 5655/228",
    "sg:postcode":"37281",
    "sg:province":"Hessen",
    "wof:name":"Lieselotte Schr\u00f6der",
    "wof:placetype":"venue"
},
  "geometry": {"coordinates":[10.1703796387,51.1810417175],"type":"Point"}
}