{
  "type": "Feature",
  "properties": {
    "iso:country":"DE",
    "sg:address":"Obere Pfaffensteigstr. 30 b",
    "sg:city":"Schwabach",
    "sg:phone":"+49 911/630459",
    "sg:postcode":"91126",
    "sg:province":"Bayern",
    "wof:name":"Dr. Helmut Jeitsch Tierarzt",
    "wof:placetype":"venue"
},
  "geometry": {"coordinates":[11.0158185959,49.3593025208],"type":"Point"}
}