{
  "type": "Feature",
  "properties": {
    "iso:country":"DE",
    "sg:address":"Kronenberger Gasse 19a",
    "sg:city":"Bad Kreuznach",
    "sg:phone":"+49 671/2343",
    "sg:postcode":"55545",
    "sg:province":"Rheinland-Pfalz",
    "wof:name":"M. Straube",
    "wof:placetype":"venue"
},
  "geometry": {"coordinates":[7.8507471085,49.8498077393],"type":"Point"}
}