{
  "type": "Feature",
  "properties": {
    "iso:country":"DE",
    "sg:address":"Ginsterbg 10",
    "sg:city":"Mechernich-Obergatzerm",
    "sg:phone":"+49 4922/5694140",
    "sg:postcode":"53894",
    "sg:province":"Nordrhein-Westfalen",
    "wof:name":"H + T Trimborn Ave Verkehrseinrichtungs Gmbh",
    "wof:placetype":"venue"
},
  "geometry": {"coordinates":[6.6530900002,50.5869483948],"type":"Point"}
}