{
  "type": "Feature",
  "properties": {
    "iso:country":"DE",
    "sg:address":"Mengener Str. 5",
    "sg:city":"Krauchenwies",
    "sg:phone":"+49 7576/812",
    "sg:postcode":"72505",
    "sg:province":"Baden-W\u00fcrttemberg",
    "wof:name":"Landhotel-restaurant L\u00f6wen",
    "wof:placetype":"venue"
},
  "geometry": {"coordinates":[9.2146215439,48.0130462646],"type":"Point"}
}