{
  "type": "Feature",
  "properties": {
    "iso:country":"DE",
    "sg:address":"Herrenstr. 1",
    "sg:city":"Rastatt",
    "sg:phone":"+49 7222/39006",
    "sg:postcode":"76437",
    "sg:province":"Baden-W\u00fcrttemberg",
    "wof:name":"Otto Schmalholz Gmbh",
    "wof:placetype":"venue"
},
  "geometry": {"coordinates":[8.2056970596,48.8561401367],"type":"Point"}
}