{
  "type": "Feature",
  "properties": {
    "iso:country":"DE",
    "sg:address":"Waldracher Str. 16",
    "sg:city":"Fell",
    "sg:phone":"+49 6502/99385",
    "sg:postcode":"54341",
    "sg:province":"Rheinland-Pfalz",
    "wof:name":"D. Dewald",
    "wof:placetype":"venue"
},
  "geometry": {"coordinates":[6.7819638252,49.7687034607],"type":"Point"}
}