{
  "type": "Feature",
  "properties": {
    "iso:country":"DE",
    "sg:address":"M\u00fchlenstr. 24",
    "sg:city":"Asbach",
    "sg:postcode":"53567",
    "sg:province":"Rheinland-Pfalz",
    "wof:name":"Entec Environmental Technology Gmbh",
    "wof:placetype":"venue"
},
  "geometry": {"coordinates":[7.392216,50.653301],"type":"Point"}
}