{
  "type": "Feature",
  "properties": {
    "iso:country":"DE",
    "sg:address":"Goethestr. 1",
    "sg:city":"Dahn",
    "sg:phone":"+49 6391/4040",
    "sg:postcode":"66994",
    "sg:province":"Rheinland-Pfalz",
    "wof:name":"Hotel Pfalzblick Gmbh",
    "wof:placetype":"venue"
},
  "geometry": {"coordinates":[7.7779431343,49.1461601257],"type":"Point"}
}