{
  "type": "Feature",
  "properties": {
    "iso:country":"DE",
    "sg:address":"An der Press 5",
    "sg:city":"Altdorf",
    "sg:phone":"+49 8704/447",
    "sg:postcode":"84032",
    "sg:province":"Bayern",
    "wof:name":"Katholisches Pfarramt St. Georg",
    "wof:placetype":"venue"
},
  "geometry": {"coordinates":[12.0792093277,48.5465011597],"type":"Point"}
}