{
  "type": "Feature",
  "properties": {
    "iso:country":"DE",
    "sg:address":"Siegelsdorfer Str 9",
    "sg:city":"Veitsbronn",
    "sg:phone":"+49 911/7520109",
    "sg:postcode":"90587",
    "sg:province":"Bayern",
    "wof:name":"Vereinigte Sparkasse Im Landkreis F",
    "wof:placetype":"venue"
},
  "geometry": {"coordinates":[10.882376,49.511543],"type":"Point"}
}