{
  "type": "Feature",
  "properties": {
    "iso:country":"DE",
    "sg:address":"R\u00f6diger Str. 121",
    "sg:city":"Wuppertal",
    "sg:phone":"+49 202/250630",
    "sg:postcode":"42283",
    "sg:province":"Nordrhein-Westfalen",
    "wof:name":"Arno L\u00f6her",
    "wof:placetype":"venue"
},
  "geometry": {"coordinates":[7.1844477654,51.2757873535],"type":"Point"}
}