{
  "type": "Feature",
  "properties": {
    "iso:country":"DE",
    "sg:address":"Stormstr. 38",
    "sg:city":"Herne",
    "sg:phone":"+49 2325/61142",
    "sg:postcode":"44651",
    "sg:province":"Nordrhein-Westfalen",
    "wof:name":"N. Harstein",
    "wof:placetype":"venue"
},
  "geometry": {"coordinates":[7.1683049202,51.5172958374],"type":"Point"}
}