{
  "type": "Feature",
  "properties": {
    "iso:country":"DE",
    "sg:address":"Am Bachmannsgraben 61",
    "sg:city":"Wegberg",
    "sg:postcode":"41844",
    "sg:province":"Nordrhein-Westfalen",
    "wof:name":"Ago-tec Allgemeine Gro\u00dfk\u00fcchen- Organisations-technik Gmbh",
    "wof:placetype":"venue"
},
  "geometry": {"coordinates":[6.29078722,51.1440124512],"type":"Point"}
}