{
  "type": "Feature",
  "properties": {
    "iso:country":"DE",
    "sg:address":"Esch 19 a",
    "sg:city":"Werther",
    "sg:postcode":"33824",
    "sg:province":"Nordrhein-Westfalen",
    "wof:name":"Aldi Gmbh & Co. Kg",
    "wof:placetype":"venue"
},
  "geometry": {"coordinates":[8.4192409515,52.0797309875],"type":"Point"}
}