{
  "type": "Feature",
  "properties": {
    "iso:country":"DE",
    "sg:address":"Westerbrak 10",
    "sg:city":"Kirchbrak",
    "sg:phone":"+49 5533/2790",
    "sg:postcode":"37619",
    "sg:province":"Niedersachsen",
    "wof:name":"Verlag Deutsches Adelsblatt Gmbh",
    "wof:placetype":"venue"
},
  "geometry": {"coordinates":[9.5567016602,51.975063324],"type":"Point"}
}