{
  "type": "Feature",
  "properties": {
    "iso:country":"DE",
    "sg:address":"Straubinger Str. 14",
    "sg:city":"Landshut",
    "sg:phone":"+49 871/74533",
    "sg:postcode":"84030",
    "sg:province":"Bayern",
    "wof:name":"Franz Ostermaier",
    "wof:placetype":"venue"
},
  "geometry": {"coordinates":[12.138344,48.561356],"type":"Point"}
}