{
  "type": "Feature",
  "properties": {
    "iso:country":"DE",
    "sg:address":"In der Waage",
    "sg:city":"Westhausen",
    "sg:phone":"+49 7363/7294",
    "sg:postcode":"73463",
    "sg:province":"Baden-W\u00fcrttemberg",
    "wof:name":"Schels & Sohn Gmbh & Co. Kg",
    "wof:placetype":"venue"
},
  "geometry": {"coordinates":[10.1752939224,48.8834533691],"type":"Point"}
}