{
  "type": "Feature",
  "properties": {
    "iso:country":"DE",
    "sg:address":"Hauptstr. 10",
    "sg:city":"Mittelreidenbach",
    "sg:phone":"+49 6784/7412",
    "sg:postcode":"55758",
    "sg:province":"Rheinland-Pfalz",
    "wof:name":"Peter Ballat Architekt",
    "wof:placetype":"venue"
},
  "geometry": {"coordinates":[7.442549,49.729977],"type":"Point"}
}