{
  "type": "Feature",
  "properties": {
    "iso:country":"DE",
    "sg:address":"Am Br\u00fcckentor 16",
    "sg:city":"Mayen",
    "sg:phone":"+49 2651/1070",
    "sg:postcode":"56727",
    "sg:province":"Rheinland-Pfalz",
    "wof:name":"Herbert Klass",
    "wof:placetype":"venue"
},
  "geometry": {"coordinates":[7.2246818542,50.3301315308],"type":"Point"}
}