{
  "type": "Feature",
  "properties": {
    "iso:country":"DE",
    "sg:address":"Abendgrundweg 9",
    "sg:city":"Unterkirnach",
    "sg:postcode":"78089",
    "sg:province":"Baden-W\u00fcrttemberg",
    "wof:name":"W & Z Holzverarbeitung Gmbh",
    "wof:placetype":"venue"
},
  "geometry": {"coordinates":[8.356468,48.080173],"type":"Point"}
}