{
  "type": "Feature",
  "properties": {
    "iso:country":"DE",
    "sg:address":"Darmst\u00e4dter Landstr. 17",
    "sg:city":"Ginsheim-Gustavsburg",
    "sg:phone":"+49 6134/75930",
    "sg:postcode":"65462",
    "sg:province":"Hessen",
    "wof:name":"Hl Markt",
    "wof:placetype":"venue"
},
  "geometry": {"coordinates":[8.3154993057,49.9971504211],"type":"Point"}
}