{
  "type": "Feature",
  "properties": {
    "iso:country":"DE",
    "sg:address":"Neue Str. 2",
    "sg:city":"Wendeburg",
    "sg:phone":"+49 5303/2293",
    "sg:postcode":"38176",
    "sg:province":"Niedersachsen",
    "wof:name":"Fleischerei F. Osterloh E. K.",
    "wof:placetype":"venue"
},
  "geometry": {"coordinates":[10.3955211639,52.3208427429],"type":"Point"}
}