{
  "type": "Feature",
  "properties": {
    "iso:country":"DE",
    "sg:address":"Jagdhauser Str. 1",
    "sg:city":"Schmallenberg",
    "sg:phone":"+49 2972/4296",
    "sg:postcode":"57392",
    "sg:province":"Nordrhein-Westfalen",
    "wof:name":"Richard Hennecke Verwaltungs Gmbh",
    "wof:placetype":"venue"
},
  "geometry": {"coordinates":[8.2605800629,51.1349601746],"type":"Point"}
}