{
  "type": "Feature",
  "properties": {
    "iso:country":"DE",
    "sg:address":"Am Tr\u00e4nkwald 4",
    "sg:city":"Rodenbach",
    "sg:phone":"+49 6374/91170",
    "sg:postcode":"67688",
    "sg:province":"Rheinland-Pfalz",
    "wof:name":"Rett-gittertr\u00e4gerdecken Gmbh",
    "wof:placetype":"venue"
},
  "geometry": {"coordinates":[7.6720890999,49.4720458984],"type":"Point"}
}