{
  "type": "Feature",
  "properties": {
    "iso:country":"DE",
    "sg:address":"Markt 34",
    "sg:city":"Greu\u00dfen",
    "sg:phone":"+49 3636/703334",
    "sg:postcode":"99718",
    "sg:province":"Th\u00fcringen",
    "wof:name":"J. Witters",
    "wof:placetype":"venue"
},
  "geometry": {"coordinates":[10.9481019974,51.2293434143],"type":"Point"}
}