{
  "type": "Feature",
  "properties": {
    "iso:country":"DE",
    "sg:address":"Lange Gasse 16",
    "sg:city":"Beilngries",
    "sg:phone":"+49 8461/471",
    "sg:postcode":"92339",
    "sg:province":"Bayern",
    "wof:name":"Josef Maget \u00d6fen Und Herde",
    "wof:placetype":"venue"
},
  "geometry": {"coordinates":[11.4724740982,49.0343856812],"type":"Point"}
}