{
  "type": "Feature",
  "properties": {
    "iso:country":"DE",
    "sg:address":"Alte Ziegelei 23",
    "sg:city":"Overath",
    "sg:phone":"+49 2204/75358",
    "sg:postcode":"51491",
    "sg:province":"Nordrhein-Westfalen",
    "wof:name":"Bernd Henk",
    "wof:placetype":"venue"
},
  "geometry": {"coordinates":[7.219514,50.952953],"type":"Point"}
}