{
  "type": "Feature",
  "properties": {
    "iso:country":"DE",
    "sg:address":"Rheintalstr. 6",
    "sg:city":"M\u00fcllheim",
    "sg:phone":"+49 7631/3490",
    "sg:postcode":"79379",
    "sg:province":"Baden-W\u00fcrttemberg",
    "wof:name":"Ev. Pfarramt Gem. Feldberg",
    "wof:placetype":"venue"
},
  "geometry": {"coordinates":[7.6407361031,47.774471283],"type":"Point"}
}