{
  "type": "Feature",
  "properties": {
    "iso:country":"DE",
    "sg:address":"Rissener Landstr. 252::",
    "sg:city":"Hamburg",
    "sg:phone":"+49 40/8190080",
    "sg:postcode":"22559",
    "sg:province":"Hamburg",
    "wof:name":"Interwega International Ges Fuer Debitorenmanagement M B H",
    "wof:placetype":"venue"
},
  "geometry": {"coordinates":[9.76547,53.580032],"type":"Point"}
}