{
  "type": "Feature",
  "properties": {
    "iso:country":"DE",
    "sg:address":"J\u00e4gerallee 22",
    "sg:city":"Potsdam",
    "sg:postcode":"14469",
    "sg:province":"Brandenburg",
    "wof:name":"Wirtschafts- Und Bildungs- Gesellschaft Mbh Des Dt.",
    "wof:placetype":"venue"
},
  "geometry": {"coordinates":[13.054107,52.407608],"type":"Point"}
}