{
  "type": "Feature",
  "properties": {
    "iso:country":"DE",
    "sg:address":"Ludwigstr. 26",
    "sg:city":"Erlensee",
    "sg:phone":"+49 6183/1666",
    "sg:postcode":"63526",
    "sg:province":"Hessen",
    "wof:name":"A. Und G. H\u00e4nle",
    "wof:placetype":"venue"
},
  "geometry": {"coordinates":[8.989610672,50.1606445312],"type":"Point"}
}