{
  "type": "Feature",
  "properties": {
    "iso:country":"DE",
    "sg:address":"Karlstr. 71",
    "sg:city":"Donaueschingen",
    "sg:phone":"+49 771/2337",
    "sg:postcode":"78166",
    "sg:province":"Baden-W\u00fcrttemberg",
    "wof:name":"Kath. Pfarramt St. Johann",
    "wof:placetype":"venue"
},
  "geometry": {"coordinates":[8.5018501282,47.9523391724],"type":"Point"}
}