{
  "type": "Feature",
  "properties": {
    "iso:country":"DE",
    "sg:address":"Gerichtsstr. 2 a",
    "sg:city":"Detmold",
    "sg:phone":"+49 5231/300930",
    "sg:postcode":"32756",
    "sg:province":"Nordrhein-Westfalen",
    "wof:name":"Sermin \u00d6zel Rechtsanw\u00e4ltin",
    "wof:placetype":"venue"
},
  "geometry": {"coordinates":[8.8736877441,51.9361877441],"type":"Point"}
}