{
  "type": "Feature",
  "properties": {
    "iso:country":"DE",
    "sg:address":"Marktplatz 15",
    "sg:city":"F\u00fcrstenzell",
    "sg:phone":"+49 8502/914880",
    "sg:postcode":"94081",
    "sg:province":"Bayern",
    "wof:name":"G\u00fcnter Wachtveitl E. Kfm. Handelsv. F\u00fcr Deutscher Herold",
    "wof:placetype":"venue"
},
  "geometry": {"coordinates":[13.318655014,48.5226707458],"type":"Point"}
}