{
  "type": "Feature",
  "properties": {
    "iso:country":"DE",
    "sg:address":"Schulstr. 29",
    "sg:city":"Deuben",
    "sg:phone":"+49 3425/815023",
    "sg:postcode":"04828",
    "sg:province":"Sachsen",
    "wof:name":"G\u00fcnther Neubert Dach Und Fassade Gmbh",
    "wof:placetype":"venue"
},
  "geometry": {"coordinates":[12.6945362091,51.3658828735],"type":"Point"}
}