{
  "type": "Feature",
  "properties": {
    "iso:country":"DE",
    "sg:address":"Dorfstr. 21",
    "sg:city":"Salzhemmendorf",
    "sg:phone":"+49 5153/5259",
    "sg:postcode":"31020",
    "sg:province":"Niedersachsen",
    "wof:name":"Restaurant Zum Dorfkrug",
    "wof:placetype":"venue"
},
  "geometry": {"coordinates":[9.6355962753,52.0867424011],"type":"Point"}
}