{
  "type": "Feature",
  "properties": {
    "iso:country":"DE",
    "sg:address":"Thankirchen 1",
    "sg:city":"Dietramszell",
    "sg:postcode":"83623",
    "sg:province":"Bayern",
    "wof:name":"Ntk Technologie Gmbh",
    "wof:placetype":"venue"
},
  "geometry": {"coordinates":[11.5675916672,47.855846405],"type":"Point"}
}