{
  "type": "Feature",
  "properties": {
    "iso:country":"DE",
    "sg:address":"Neuenhauser Str. 48",
    "sg:city":"Nordhorn",
    "sg:phone":"+49 5921/723277",
    "sg:postcode":"48529",
    "sg:province":"Niedersachsen",
    "wof:name":"Schmidt",
    "wof:placetype":"venue"
},
  "geometry": {"coordinates":[7.0661959648,52.4401321411],"type":"Point"}
}