{
  "type": "Feature",
  "properties": {
    "iso:country":"DE",
    "sg:address":"In den B\u00f6cken 31",
    "sg:city":"Bochum",
    "sg:phone":"+49 234/860632",
    "sg:postcode":"44805",
    "sg:province":"Nordrhein-Westfalen",
    "wof:name":"Schl\u00fcsseldienst Degener Gmbh",
    "wof:placetype":"venue"
},
  "geometry": {"coordinates":[7.2710337639,51.5062446594],"type":"Point"}
}