{
  "type": "Feature",
  "properties": {
    "iso:country":"DE",
    "sg:address":"Geiersbergstr. 78-80",
    "sg:city":"K\u00f6ln",
    "sg:phone":"+49 221/9793155",
    "sg:postcode":"50765",
    "sg:province":"Nordrhein-Westfalen",
    "wof:name":"Edeka-markt R\u00f6tzel",
    "wof:placetype":"venue"
},
  "geometry": {"coordinates":[6.8825230598,51.0364151001],"type":"Point"}
}