{
  "type": "Feature",
  "properties": {
    "iso:country":"DE",
    "sg:address":"Altstadt 8",
    "sg:city":"Hof",
    "sg:phone":"+49 9281/16102",
    "sg:postcode":"95028",
    "sg:province":"Bayern",
    "wof:name":"La Choccolata",
    "wof:placetype":"venue"
},
  "geometry": {"coordinates":[11.915596962,50.3183937073],"type":"Point"}
}