{
  "type": "Feature",
  "properties": {
    "iso:country":"DE",
    "sg:address":"Heedfelder Str 55a",
    "sg:city":"L\u00fcdenscheid",
    "sg:phone":"+49 2351/919295",
    "sg:postcode":"58509",
    "sg:province":"Nordrhein-Westfalen",
    "wof:name":"Schr\u00f6er",
    "wof:placetype":"venue"
},
  "geometry": {"coordinates":[7.614696,51.226204],"type":"Point"}
}