{
  "type": "Feature",
  "properties": {
    "iso:country":"DE",
    "sg:address":"Zankerweg 3",
    "sg:city":"Durach",
    "sg:phone":"+49 8376/653",
    "sg:postcode":"87471",
    "sg:province":"Bayern",
    "wof:name":"Hubert Mayr",
    "wof:placetype":"venue"
},
  "geometry": {"coordinates":[10.411718,47.683929],"type":"Point"}
}