{
  "type": "Feature",
  "properties": {
    "iso:country":"DE",
    "sg:address":"Am Marktplatz 5",
    "sg:city":"Waldbr\u00f6l",
    "sg:phone":"+49 2291/2232",
    "sg:postcode":"51545",
    "sg:province":"Nordrhein-Westfalen",
    "wof:name":"Pizzeria Pina",
    "wof:placetype":"venue"
},
  "geometry": {"coordinates":[7.614177227,50.8740272522],"type":"Point"}
}