{
  "type": "Feature",
  "properties": {
    "iso:country":"DE",
    "sg:address":"Agathastrasse",
    "sg:city":"Bad Driburg",
    "sg:postcode":"33014",
    "sg:province":"Nordrhein-Westfalen",
    "wof:name":"Startseite Der Band Mittendrin",
    "wof:placetype":"venue"
},
  "geometry": {"coordinates":[9.0181,51.735134],"type":"Point"}
}