{
  "type": "Feature",
  "properties": {
    "iso:country":"DE",
    "sg:address":"Papenstr. 126",
    "sg:city":"Cuxhaven",
    "sg:postcode":"27472",
    "sg:province":"Niedersachsen",
    "wof:name":"Erste Verwaltungs- Gesellschaft Nordene Mbh",
    "wof:placetype":"venue"
},
  "geometry": {"coordinates":[8.7184534073,53.8504676819],"type":"Point"}
}