{
  "type": "Feature",
  "properties": {
    "iso:country":"DE",
    "sg:address":"Haus Uhlenkotten 34",
    "sg:city":"M\u00fcnster",
    "sg:phone":"+49 251/263390",
    "sg:postcode":"48159",
    "sg:province":"Nordrhein-Westfalen",
    "wof:name":"Studio Casa Gmbh & Co Kg",
    "wof:placetype":"venue"
},
  "geometry": {"coordinates":[7.5690231323,51.9900779724],"type":"Point"}
}