{
  "type": "Feature",
  "properties": {
    "iso:country":"DE",
    "sg:address":"Ballstr 22",
    "sg:city":"Quedlinburg",
    "sg:phone":"+49 3946/915308",
    "sg:postcode":"06484",
    "sg:province":"Sachsen-Anhalt",
    "wof:name":"Quedlinburger Edv Beratung",
    "wof:placetype":"venue"
},
  "geometry": {"coordinates":[11.1523151398,51.7896499634],"type":"Point"}
}