{
  "type": "Feature",
  "properties": {
    "iso:country":"DE",
    "sg:address":"Buchenweg 1",
    "sg:city":"Mogendorf",
    "sg:phone":"+49 2623/5967",
    "sg:postcode":"56424",
    "sg:province":"Rheinland-Pfalz",
    "wof:name":"Schlosser Gmbh",
    "wof:placetype":"venue"
},
  "geometry": {"coordinates":[7.756448,50.490746],"type":"Point"}
}