{
  "type": "Feature",
  "properties": {
    "iso:country":"DE",
    "sg:address":"Hanauer Landstr 139",
    "sg:city":"Frankfurt",
    "sg:phone":"+49 69/4050020",
    "sg:postcode":"60314",
    "sg:province":"Hessen",
    "wof:name":"B\u00fchler & Partner Gmbh & Co Kg",
    "wof:placetype":"venue"
},
  "geometry": {"coordinates":[8.71399,50.112343],"type":"Point"}
}