{
  "type": "Feature",
  "properties": {
    "iso:country":"DE",
    "sg:address":"Am Brodhagen 81",
    "sg:city":"Bielefeld",
    "sg:phone":"+49 521/882993",
    "sg:postcode":"33613",
    "sg:province":"Nordrhein-Westfalen",
    "wof:name":"Horst Iseringhausen",
    "wof:placetype":"venue"
},
  "geometry": {"coordinates":[8.511316,52.044308],"type":"Point"}
}