{
  "type": "Feature",
  "properties": {
    "iso:country":"DE",
    "sg:address":"Lotsenweg 4",
    "sg:city":"Burg",
    "sg:phone":"+49 4371/3978",
    "sg:postcode":"23769",
    "sg:province":"Schleswig-Holstein",
    "wof:name":"Heinz Pahlke Binnenfischerei",
    "wof:placetype":"venue"
},
  "geometry": {"coordinates":[11.1924409866,54.4249343872],"type":"Point"}
}