{
  "type": "Feature",
  "properties": {
    "iso:country":"DE",
    "sg:address":"Graudenzer Str. 37",
    "sg:city":"Kehl",
    "sg:phone":"+49 7851/932360",
    "sg:postcode":"77694",
    "sg:province":"Baden-W\u00fcrttemberg",
    "wof:name":"Hermann Roll Gmbh & Co. Kg",
    "wof:placetype":"venue"
},
  "geometry": {"coordinates":[7.822465,48.591022],"type":"Point"}
}