{
  "type": "Feature",
  "properties": {
    "iso:country":"DE",
    "sg:address":"Kronenstr. 13",
    "sg:city":"Wuppertal",
    "sg:phone":"+49 202/81424",
    "sg:postcode":"42285",
    "sg:province":"Nordrhein-Westfalen",
    "wof:name":"Arthur Hoffmann Architekt",
    "wof:placetype":"venue"
},
  "geometry": {"coordinates":[7.175095,51.266411],"type":"Point"}
}