{
  "type": "Feature",
  "properties": {
    "iso:country":"DE",
    "sg:address":"Bodelschwinghstr. 80",
    "sg:city":"Weimar",
    "sg:phone":"+49 3643/854467",
    "sg:postcode":"99425",
    "sg:province":"Th\u00fcringen",
    "wof:name":"Walter Bau Sanierungsges. Mbh",
    "wof:placetype":"venue"
},
  "geometry": {"coordinates":[11.343994,50.973579],"type":"Point"}
}