{
  "type": "Feature",
  "properties": {
    "iso:country":"DE",
    "sg:address":"Florastr. 11",
    "sg:city":"D\u00fcsseldorf",
    "sg:phone":"+49 211/378980",
    "sg:postcode":"40217",
    "sg:province":"Nordrhein-Westfalen",
    "wof:name":"Dieter H\u00f6hn Innenarchitekt",
    "wof:placetype":"venue"
},
  "geometry": {"coordinates":[6.772577,51.215065],"type":"Point"}
}