{
  "type": "Feature",
  "properties": {
    "iso:country":"DE",
    "sg:address":"An der D\u00f6rrwiese 3",
    "sg:city":"Saulheim",
    "sg:phone":"+49 6732/5536",
    "sg:postcode":"55291",
    "sg:province":"Rheinland-Pfalz",
    "wof:name":"Schumacher",
    "wof:placetype":"venue"
},
  "geometry": {"coordinates":[8.1572055817,49.8780021667],"type":"Point"}
}