{
  "type": "Feature",
  "properties": {
    "iso:country":"DE",
    "sg:address":"Zerbster Chaussee 6",
    "sg:city":"Burg",
    "sg:phone":"+49 3921/944734",
    "sg:postcode":"39288",
    "sg:province":"Sachsen-Anhalt",
    "wof:name":"Bischof Industrie- Und Gewerbebau Gmbh",
    "wof:placetype":"venue"
},
  "geometry": {"coordinates":[11.8613519669,52.2654533386],"type":"Point"}
}