{
  "type": "Feature",
  "properties": {
    "iso:country":"DE",
    "sg:address":"Bahnhofstr. 27",
    "sg:city":"Dinkelscherben",
    "sg:phone":"+49 8292/1335",
    "sg:postcode":"86424",
    "sg:province":"Bayern",
    "wof:name":"E. Wagner",
    "wof:placetype":"venue"
},
  "geometry": {"coordinates":[10.588276,48.344635],"type":"Point"}
}