{
  "type": "Feature",
  "properties": {
    "iso:country":"DE",
    "sg:address":"Sanderrothstr. 53",
    "sg:city":"W\u00fcrzburg",
    "sg:phone":"+49 931/887771",
    "sg:postcode":"97074",
    "sg:province":"Bayern",
    "wof:name":"Dr. Elfriede M\u00fcller Rechtsanw\u00e4ltin",
    "wof:placetype":"venue"
},
  "geometry": {"coordinates":[9.9542274475,49.7750244141],"type":"Point"}
}