{
  "type": "Feature",
  "properties": {
    "iso:country":"DE",
    "sg:address":"Ritterstr. 59",
    "sg:city":"Bad Vilbel",
    "sg:phone":"+49 6101/89362",
    "sg:postcode":"61118",
    "sg:province":"Hessen",
    "wof:name":"Klaus Mienert Architekt",
    "wof:placetype":"venue"
},
  "geometry": {"coordinates":[8.737612,50.174294],"type":"Point"}
}