{
  "type": "Feature",
  "properties": {
    "iso:country":"DE",
    "sg:address":"Mommsenstr. 62",
    "sg:city":"Berlin",
    "sg:phone":"+49 30/3212696",
    "sg:postcode":"10629",
    "sg:province":"Berlin",
    "wof:name":"Adolf Knappstein Gmbh",
    "wof:placetype":"venue"
},
  "geometry": {"coordinates":[13.316201,52.502991],"type":"Point"}
}