{
  "type": "Feature",
  "properties": {
    "iso:country":"DE",
    "sg:address":"Stiefelhagenstr. 11",
    "sg:city":"Overath",
    "sg:phone":"+49 2206/7611",
    "sg:postcode":"51491",
    "sg:province":"Nordrhein-Westfalen",
    "wof:name":"Friedrich W. Selbach",
    "wof:placetype":"venue"
},
  "geometry": {"coordinates":[7.321059227,50.9309654236],"type":"Point"}
}