{
  "type": "Feature",
  "properties": {
    "iso:country":"DE",
    "sg:address":"Im Schecken 46",
    "sg:city":"Seeheim-Jugenheim",
    "sg:phone":"+49 6257/962199",
    "sg:postcode":"64342",
    "sg:province":"Hessen",
    "wof:name":"M. M\u00fcller",
    "wof:placetype":"venue"
},
  "geometry": {"coordinates":[8.651135,49.774212],"type":"Point"}
}