{
  "type": "Feature",
  "properties": {
    "iso:country":"DE",
    "sg:address":"Helmkestr. 1",
    "sg:city":"Iserlohn",
    "sg:phone":"+49 2374/13433",
    "sg:postcode":"58642",
    "sg:province":"Nordrhein-Westfalen",
    "wof:name":"O. Giebelhausen",
    "wof:placetype":"venue"
},
  "geometry": {"coordinates":[7.6191301346,51.362159729],"type":"Point"}
}