{
  "type": "Feature",
  "properties": {
    "iso:country":"DE",
    "sg:address":"Willi-S\u00e4nger-Str. 19",
    "sg:city":"Brandenburg",
    "sg:phone":"+49 3381/302288",
    "sg:postcode":"14770",
    "sg:province":"Brandenburg",
    "wof:name":"Wolter Gmbh",
    "wof:placetype":"venue"
},
  "geometry": {"coordinates":[12.548785,52.418839],"type":"Point"}
}