{
  "type": "Feature",
  "properties": {
    "iso:country":"DE",
    "sg:address":"Rei\u00dfiger Gewerbering 15",
    "sg:city":"Plauen",
    "sg:phone":"+49 3741/54730",
    "sg:postcode":"08525",
    "sg:province":"Sachsen",
    "wof:name":"W. Schmidt",
    "wof:placetype":"venue"
},
  "geometry": {"coordinates":[12.1485824585,50.5271987915],"type":"Point"}
}