{
  "type": "Feature",
  "properties": {
    "iso:country":"DE",
    "sg:address":"Tanzw\u00e4ldlestr. 34",
    "sg:city":"K\u00f6nigsfeld",
    "sg:phone":"+49 7725/3653",
    "sg:postcode":"78126",
    "sg:province":"Baden-W\u00fcrttemberg",
    "wof:name":"J. Fichter",
    "wof:placetype":"venue"
},
  "geometry": {"coordinates":[8.3872480392,48.1562347412],"type":"Point"}
}