{
  "type": "Feature",
  "properties": {
    "iso:country":"DE",
    "sg:address":"Brambachstr. 72",
    "sg:city":"K\u00f6ln",
    "sg:phone":"+49 221/684583",
    "sg:postcode":"51069",
    "sg:province":"Nordrhein-Westfalen",
    "wof:name":"Peter Br\u00fcck Ingenieur",
    "wof:placetype":"venue"
},
  "geometry": {"coordinates":[7.0882501602,50.9745101929],"type":"Point"}
}