{
  "type": "Feature",
  "properties": {
    "iso:country":"DE",
    "sg:address":"Fahrenberg 12",
    "sg:city":"Barsb\u00fcttel",
    "sg:phone":"+49 40/6706510",
    "sg:postcode":"22885",
    "sg:province":"Schleswig-Holstein",
    "wof:name":"Norbert Wittstock Gmbh",
    "wof:placetype":"venue"
},
  "geometry": {"coordinates":[10.194637,53.573624],"type":"Point"}
}