{
  "type": "Feature",
  "properties": {
    "iso:country":"DE",
    "sg:address":"Wolfgang-Graf-Platz 3",
    "sg:city":"Fichtelberg",
    "sg:phone":"+49 9272/363",
    "sg:postcode":"95686",
    "sg:province":"Bayern",
    "wof:name":"A. Reichenberger",
    "wof:placetype":"venue"
},
  "geometry": {"coordinates":[11.8527841568,49.9989395142],"type":"Point"}
}