{
  "type": "Feature",
  "properties": {
    "iso:country":"DE",
    "sg:address":"Feldstr. 9",
    "sg:city":"Falkenstein",
    "sg:phone":"+49 3745/70050",
    "sg:postcode":"08223",
    "sg:province":"Sachsen",
    "wof:name":"F. Seifert",
    "wof:placetype":"venue"
},
  "geometry": {"coordinates":[12.3667936325,50.4762153625],"type":"Point"}
}