{
  "type": "Feature",
  "properties": {
    "iso:country":"DE",
    "sg:address":"Lindenstra\u00dfe 21",
    "sg:city":"Emmingen-Liptingen",
    "sg:phone":"+49 7465",
    "sg:postcode":"78576",
    "sg:province":"Baden-W\u00fcrttemberg",
    "wof:name":"St\u00f6rk K\u00fcfers - Biofiltersysteme",
    "wof:placetype":"venue"
},
  "geometry": {"coordinates":[8.846286,47.932621],"type":"Point"}
}