{
  "type": "Feature",
  "properties": {
    "iso:country":"DE",
    "sg:address":"Dieselstr. 19",
    "sg:city":"M\u00fcnchen",
    "sg:phone":"+49 89/1412312",
    "sg:postcode":"80993",
    "sg:province":"Bayern",
    "wof:name":"Klemt & Kamzelak Montage Gmbh",
    "wof:placetype":"venue"
},
  "geometry": {"coordinates":[11.5355882645,48.1859703064],"type":"Point"}
}