{
  "type": "Feature",
  "properties": {
    "iso:country":"DE",
    "sg:address":"Marthastr. 5",
    "sg:city":"Taucha",
    "sg:phone":"+49 34298/35662",
    "sg:postcode":"04425",
    "sg:province":"Sachsen",
    "wof:name":"H.-j. Thiele",
    "wof:placetype":"venue"
},
  "geometry": {"coordinates":[12.5066690445,51.3696708679],"type":"Point"}
}