{
  "type": "Feature",
  "properties": {
    "iso:country":"DE",
    "sg:address":"Forellenweg 17",
    "sg:city":"Bruckm\u00fchl",
    "sg:phone":"+49 8062/2695",
    "sg:postcode":"83052",
    "sg:province":"Bayern",
    "wof:name":"K. Mayer",
    "wof:placetype":"venue"
},
  "geometry": {"coordinates":[11.9008245468,47.8699913025],"type":"Point"}
}