{
  "type": "Feature",
  "properties": {
    "iso:country":"DE",
    "sg:address":"Querstr. 12",
    "sg:city":"Leipzig",
    "sg:phone":"+49 341/12920",
    "sg:postcode":"04103",
    "sg:province":"Sachsen",
    "wof:name":"Hotel Leipzig Renaissance",
    "wof:placetype":"venue"
},
  "geometry": {"coordinates":[12.3853197098,51.3404884338],"type":"Point"}
}