{
  "type": "Feature",
  "properties": {
    "iso:country":"DE",
    "sg:address":"Innere Kobergerstr. 17 a",
    "sg:city":"N\u00fcrnberg",
    "sg:postcode":"90408",
    "sg:province":"Bayern",
    "wof:name":"Tux It Ag",
    "wof:placetype":"venue"
},
  "geometry": {"coordinates":[11.0803861618,49.4641227722],"type":"Point"}
}