{
  "type": "Feature",
  "properties": {
    "iso:country":"DE",
    "sg:address":"Prielhofweg 14",
    "sg:city":"Landshut",
    "sg:phone":"+49 871/26982",
    "sg:postcode":"84036",
    "sg:province":"Bayern",
    "wof:name":"Siegfried Bezold Kameramann",
    "wof:placetype":"venue"
},
  "geometry": {"coordinates":[12.1574115753,48.5242156982],"type":"Point"}
}