{
  "type": "Feature",
  "properties": {
    "iso:country":"DE",
    "sg:address":"Lindenstr. 26",
    "sg:city":"G\u00fcglingen",
    "sg:phone":"+49 7135/6166",
    "sg:postcode":"74363",
    "sg:province":"Baden-W\u00fcrttemberg",
    "wof:name":"Tennishalle",
    "wof:placetype":"venue"
},
  "geometry": {"coordinates":[9.0022506714,49.0640792847],"type":"Point"}
}