{
  "type": "Feature",
  "properties": {
    "iso:country":"DE",
    "sg:address":"Postfach 32",
    "sg:city":"Baltrum",
    "sg:phone":"+49 4939/383",
    "sg:postcode":"26572",
    "sg:province":"Niedersachsen",
    "wof:name":"Ursula Kajetanczyk",
    "wof:placetype":"venue"
},
  "geometry": {"coordinates":[7.3705811501,53.7275314331],"type":"Point"}
}