{
  "type": "Feature",
  "properties": {
    "iso:country":"DE",
    "sg:address":"Obenpilghausen 70",
    "sg:city":"Solingen",
    "sg:phone":"+49 212/809282",
    "sg:postcode":"42657",
    "sg:province":"Nordrhein-Westfalen",
    "wof:name":"S. Weiner",
    "wof:placetype":"venue"
},
  "geometry": {"coordinates":[7.069515,51.162537],"type":"Point"}
}