{
  "type": "Feature",
  "properties": {
    "iso:country":"DE",
    "sg:address":"Gartenstr. 13",
    "sg:city":"Schwarzach",
    "sg:phone":"+49 9324/1729",
    "sg:postcode":"97359",
    "sg:province":"Bayern",
    "wof:name":"S. Und G. Wandelt",
    "wof:placetype":"venue"
},
  "geometry": {"coordinates":[10.2288,49.808537],"type":"Point"}
}