{
  "type": "Feature",
  "properties": {
    "iso:country":"DE",
    "sg:address":"Albrecht-D\u00fcrer-Str. 5",
    "sg:city":"Lennestadt",
    "sg:phone":"+49 2721/98400",
    "sg:postcode":"57368",
    "sg:province":"Nordrhein-Westfalen",
    "wof:name":"Willi Schulte Steuerberater",
    "wof:placetype":"venue"
},
  "geometry": {"coordinates":[8.0670814514,51.1230201721],"type":"Point"}
}