{
  "type": "Feature",
  "properties": {
    "iso:country":"DE",
    "sg:address":"\u00d6denhofweg 6",
    "sg:city":"Baiersbronn",
    "sg:phone":"+49 7442/2868",
    "sg:postcode":"72270",
    "sg:province":"Baden-W\u00fcrttemberg",
    "wof:name":"Martin Veith",
    "wof:placetype":"venue"
},
  "geometry": {"coordinates":[8.322759,48.521729],"type":"Point"}
}