{
  "type": "Feature",
  "properties": {
    "iso:country":"DE",
    "sg:address":"Bahnhofstr. 34",
    "sg:city":"Lorsch",
    "sg:phone":"+49 6251/57262",
    "sg:postcode":"64653",
    "sg:province":"Hessen",
    "wof:name":"Peter J. Helmling",
    "wof:placetype":"venue"
},
  "geometry": {"coordinates":[8.567707,49.657211],"type":"Point"}
}