{
  "type": "Feature",
  "properties": {
    "iso:country":"DE",
    "sg:address":"August-Bebel-Str. 5",
    "sg:city":"Weilburg",
    "sg:phone":"+49 6471/2574",
    "sg:postcode":"35781",
    "sg:province":"Hessen",
    "wof:name":"C. Wiesner",
    "wof:placetype":"venue"
},
  "geometry": {"coordinates":[8.2476091385,50.4806060791],"type":"Point"}
}