{
  "type": "Feature",
  "properties": {
    "iso:country":"DE",
    "sg:address":"Rittlerstr. 55",
    "sg:city":"M\u00fcnchen",
    "sg:phone":"+49 89/7488840",
    "sg:postcode":"80339",
    "sg:province":"Bayern",
    "wof:name":"Red Shephers Translations Gmbh",
    "wof:placetype":"venue"
},
  "geometry": {"coordinates":[11.53216,48.13409],"type":"Point"}
}