{
  "type": "Feature",
  "properties": {
    "iso:country":"DE",
    "sg:address":"G\u00e4nseriedstr. 30",
    "sg:city":"N\u00fcrnberg",
    "sg:phone":"+49 911/830978",
    "sg:postcode":"90475",
    "sg:province":"Bayern",
    "wof:name":"Dieter Bienert",
    "wof:placetype":"venue"
},
  "geometry": {"coordinates":[11.2579660416,49.4316291809],"type":"Point"}
}