{
  "type": "Feature",
  "properties": {
    "iso:country":"DE",
    "sg:address":"Eupener Str. 10",
    "sg:city":"Monschau",
    "sg:phone":"+49 2472/2367",
    "sg:postcode":"52156",
    "sg:province":"Nordrhein-Westfalen",
    "wof:name":"Plaka",
    "wof:placetype":"venue"
},
  "geometry": {"coordinates":[6.2299342155,50.5678787231],"type":"Point"}
}