{
  "type": "Feature",
  "properties": {
    "iso:country":"DE",
    "sg:city":"Duisburg",
    "sg:postcode":"47166",
    "sg:province":"Nordrhein-Westfalen",
    "wof:name":"European Tennessee Walking Horse Association E.v.",
    "wof:placetype":"venue"
},
  "geometry": {"coordinates":[6.7719,51.491386],"type":"Point"}
}