{
  "type": "Feature",
  "properties": {
    "iso:country":"DE",
    "sg:address":"Johannes-Ritter-Str 77",
    "sg:city":"Geesthacht",
    "sg:phone":"+45 63 38 21 23",
    "sg:postcode":"21502",
    "sg:province":"Schleswig-Holstein",
    "wof:name":"Ib Andresen Industri A/s",
    "wof:placetype":"venue"
},
  "geometry": {"coordinates":[10.381349,53.427204],"type":"Point"}
}