{
  "type": "Feature",
  "properties": {
    "iso:country":"DE",
    "sg:address":"Wieterstr.",
    "sg:city":"Northeim",
    "sg:phone":"+49 5551/620062",
    "sg:postcode":"37154",
    "sg:province":"Niedersachsen",
    "wof:name":"Weihrauch Uhlendorff Gmbh",
    "wof:placetype":"venue"
},
  "geometry": {"coordinates":[10.0005750656,51.7052383423],"type":"Point"}
}