{
  "type": "Feature",
  "properties": {
    "iso:country":"DE",
    "sg:address":"S\u00fcdwestpark 23",
    "sg:city":"N\u00fcrnberg",
    "sg:phone":"+49 911/68980",
    "sg:postcode":"90449",
    "sg:province":"Bayern",
    "wof:name":"Ta Triumph-adler Ag",
    "wof:placetype":"venue"
},
  "geometry": {"coordinates":[11.020499,49.428108],"type":"Point"}
}