{
  "type": "Feature",
  "properties": {
    "iso:country":"DE",
    "sg:address":"Brahmsstr. 11",
    "sg:city":"Rheinbach",
    "sg:phone":"+49 2226/17575",
    "sg:postcode":"53359",
    "sg:province":"Nordrhein-Westfalen",
    "wof:name":"P. Hesse-dubyk Rechtsanwalt",
    "wof:placetype":"venue"
},
  "geometry": {"coordinates":[6.9439201355,50.6217765808],"type":"Point"}
}