{
  "type": "Feature",
  "properties": {
    "iso:country":"DE",
    "sg:address":"Paul-Thomas-Str 47",
    "sg:city":"D\u00fcsseldorf",
    "sg:phone":"+49 211/998990",
    "sg:postcode":"40589",
    "sg:province":"Nordrhein-Westfalen",
    "wof:name":"Lenz & G\u00fcnter Gmbh",
    "wof:placetype":"venue"
},
  "geometry": {"coordinates":[6.831875,51.174755],"type":"Point"}
}