{
  "type": "Feature",
  "properties": {
    "iso:country":"DE",
    "sg:address":"B\u00e4rentaler Str. 2",
    "sg:city":"Feldberg",
    "sg:phone":"+49 7655/932060",
    "sg:postcode":"79868",
    "sg:province":"Baden-W\u00fcrttemberg",
    "wof:name":"Michael Jaschke",
    "wof:placetype":"venue"
},
  "geometry": {"coordinates":[8.036428,47.859634],"type":"Point"}
}