{
  "type": "Feature",
  "properties": {
    "iso:country":"DE",
    "sg:address":"Wung 6",
    "sg:city":"Mildstedt",
    "sg:phone":"+49 4841/73444",
    "sg:postcode":"25866",
    "sg:province":"Schleswig-Holstein",
    "wof:name":"Spedition Laffrenzen E. K. Inh. Birgit Lassen",
    "wof:placetype":"venue"
},
  "geometry": {"coordinates":[9.0956115723,54.4635238647],"type":"Point"}
}