{
  "type": "Feature",
  "properties": {
    "iso:country":"DE",
    "sg:address":"Klever Str. 23",
    "sg:city":"Moers",
    "sg:phone":"+49 2841/22288",
    "sg:postcode":"47441",
    "sg:province":"Nordrhein-Westfalen",
    "wof:name":"Deutsche Shell Ag",
    "wof:placetype":"venue"
},
  "geometry": {"coordinates":[6.6376042366,51.4532432556],"type":"Point"}
}