{
  "type": "Feature",
  "properties": {
    "iso:country":"DE",
    "sg:address":"Hauptstr. 49",
    "sg:city":"Idar-Oberstein",
    "sg:phone":"+49 6781/41533",
    "sg:postcode":"55743",
    "sg:province":"Rheinland-Pfalz",
    "wof:name":"Astrid Foos",
    "wof:placetype":"venue"
},
  "geometry": {"coordinates":[7.29951,49.72184],"type":"Point"}
}