{
  "type": "Feature",
  "properties": {
    "iso:country":"DE",
    "sg:address":"Oberntorstr. 16",
    "sg:city":"Stadthagen",
    "sg:phone":"+49 5721/1443",
    "sg:postcode":"31655",
    "sg:province":"Niedersachsen",
    "wof:name":"Georgs",
    "wof:placetype":"venue"
},
  "geometry": {"coordinates":[9.2038593292,52.3186721802],"type":"Point"}
}