{
  "type": "Feature",
  "properties": {
    "iso:country":"DE",
    "sg:address":"Kamm 19",
    "sg:city":"Ortenburg",
    "sg:phone":"+49 8542/7223",
    "sg:postcode":"94496",
    "sg:province":"Bayern",
    "wof:name":"Franz Reiter",
    "wof:placetype":"venue"
},
  "geometry": {"coordinates":[13.2145719528,48.5553894043],"type":"Point"}
}