{
  "type": "Feature",
  "properties": {
    "iso:country":"DE",
    "sg:address":"Alter Hammweg 77",
    "sg:city":"Beckum",
    "sg:phone":"+49 2521/3123",
    "sg:postcode":"59269",
    "sg:province":"Nordrhein-Westfalen",
    "wof:name":"A. Brockmann",
    "wof:placetype":"venue"
},
  "geometry": {"coordinates":[8.0264749527,51.7456359863],"type":"Point"}
}