{
  "type": "Feature",
  "properties": {
    "iso:country":"DE",
    "sg:address":"Ruhrstr. 146",
    "sg:city":"Bochum",
    "sg:phone":"+49 2327/76811",
    "sg:postcode":"44869",
    "sg:province":"Nordrhein-Westfalen",
    "wof:name":"Ingrids Backstube",
    "wof:placetype":"venue"
},
  "geometry": {"coordinates":[7.167681,51.446896],"type":"Point"}
}