{
  "type": "Feature",
  "properties": {
    "iso:country":"DE",
    "sg:address":"Bentheimer Str. 233",
    "sg:city":"Nordhorn",
    "sg:phone":"+49 5921/80450",
    "sg:postcode":"48529",
    "sg:province":"Niedersachsen",
    "wof:name":"Elf Oil Ag",
    "wof:placetype":"venue"
},
  "geometry": {"coordinates":[7.0835189819,52.4193267822],"type":"Point"}
}