{
  "type": "Feature",
  "properties": {
    "iso:country":"DE",
    "sg:address":"Waldenbucher Str. 29",
    "sg:city":"Leinfelden-Echterdingen",
    "sg:phone":"+49 711/795813",
    "sg:postcode":"70771",
    "sg:province":"Baden-W\u00fcrttemberg",
    "wof:name":"H. Holzwarth \u00dcbersetzerin",
    "wof:placetype":"venue"
},
  "geometry": {"coordinates":[9.155838,48.682007],"type":"Point"}
}