{
  "type": "Feature",
  "properties": {
    "iso:country":"DE",
    "sg:address":"Provinzialstr. 243",
    "sg:city":"Ensdorf",
    "sg:phone":"+49 6831/54528",
    "sg:postcode":"66806",
    "sg:province":"Saarland",
    "wof:name":"Big Deal Schmidt & Wei\u00dfbrodt Textilhandels Gmbh",
    "wof:placetype":"venue"
},
  "geometry": {"coordinates":[6.7780752182,49.2969474792],"type":"Point"}
}