{
  "type": "Feature",
  "properties": {
    "iso:country":"DE",
    "sg:address":"Lorscher Str. 32",
    "sg:city":"Frankfurt",
    "sg:phone":"+49 69/783367",
    "sg:postcode":"60489",
    "sg:province":"Hessen",
    "wof:name":"Trabert Spezialdruck Gmbh",
    "wof:placetype":"venue"
},
  "geometry": {"coordinates":[8.608528,50.127361],"type":"Point"}
}