{
  "type": "Feature",
  "properties": {
    "iso:country":"DE",
    "sg:address":"H\u00f6henweg 25",
    "sg:city":"Aglasterhausen",
    "sg:phone":"+49 6262/1286",
    "sg:postcode":"74858",
    "sg:province":"Baden-W\u00fcrttemberg",
    "wof:name":"Klaus Kronm\u00fcller Architekt",
    "wof:placetype":"venue"
},
  "geometry": {"coordinates":[8.983962,49.351643],"type":"Point"}
}