{
  "type": "Feature",
  "properties": {
    "iso:country":"DE",
    "sg:address":"Hegaustr. 12",
    "sg:city":"Villingen-Schwenningen",
    "sg:phone":"+49 7720/1055",
    "sg:postcode":"78054",
    "sg:province":"Baden-W\u00fcrttemberg",
    "wof:name":"Scholz-hennemann Gmbh",
    "wof:placetype":"venue"
},
  "geometry": {"coordinates":[8.5162591934,48.0633583069],"type":"Point"}
}