{
  "type": "Feature",
  "properties": {
    "iso:country":"DE",
    "sg:address":"Friedrich-Ebert-Str. 14",
    "sg:city":"Haar",
    "sg:phone":"+49 89/467256",
    "sg:postcode":"85540",
    "sg:province":"Bayern",
    "wof:name":"Hallenbad",
    "wof:placetype":"venue"
},
  "geometry": {"coordinates":[11.7310800552,48.109500885],"type":"Point"}
}