{
  "type": "Feature",
  "properties": {
    "iso:country":"DE",
    "sg:address":"Resseltstr. 9b",
    "sg:city":"Rheine",
    "sg:phone":"+49 5971/3422",
    "sg:postcode":"48431",
    "sg:province":"Nordrhein-Westfalen",
    "wof:name":"Erica Beteiligungs- Und Verwaltungsges. Mbh",
    "wof:placetype":"venue"
},
  "geometry": {"coordinates":[7.408768,52.273922],"type":"Point"}
}