{
  "type": "Feature",
  "properties": {
    "iso:country":"DE",
    "sg:address":"Gertrudisstra\u00dfe 8",
    "sg:city":"Iserlohn",
    "sg:phone":"+49 2371",
    "sg:postcode":"58640",
    "sg:province":"Nordrhein-Westfalen",
    "wof:name":"Internationale Partnervermittlung, Bernd Wittbrodt",
    "wof:placetype":"venue"
},
  "geometry": {"coordinates":[7.7118310928,51.419708252],"type":"Point"}
}