{
  "type": "Feature",
  "properties": {
    "iso:country":"DE",
    "sg:address":"Duramstr. 13",
    "sg:city":"Simbach",
    "sg:phone":"+49 9954/90232",
    "sg:postcode":"94436",
    "sg:province":"Bayern",
    "wof:name":"Karl Stinglwagner",
    "wof:placetype":"venue"
},
  "geometry": {"coordinates":[12.7375583649,48.5634155273],"type":"Point"}
}