{
  "type": "Feature",
  "properties": {
    "iso:country":"DE",
    "sg:address":"Neubauerndorf 18a",
    "sg:city":"Barnewitz",
    "sg:phone":"+49 33876/40443",
    "sg:postcode":"14715",
    "sg:province":"Brandenburg",
    "wof:name":"Renate Stichowski Heilpraktikerin",
    "wof:placetype":"venue"
},
  "geometry": {"coordinates":[12.6229810715,52.5659866333],"type":"Point"}
}