{
  "type": "Feature",
  "properties": {
    "iso:country":"DE",
    "sg:address":"Briesker Str. 46",
    "sg:city":"Brieske",
    "sg:phone":"+49 3573/66970",
    "sg:postcode":"01968",
    "sg:province":"Brandenburg",
    "wof:name":"Praktiker Bau- Und Heimwerkermarkt",
    "wof:placetype":"venue"
},
  "geometry": {"coordinates":[13.9593544006,51.4967041016],"type":"Point"}
}