{
  "type": "Feature",
  "properties": {
    "iso:country":"DE",
    "sg:address":"K\u00f6nigstr. 47",
    "sg:city":"Bad Bergzabern",
    "sg:phone":"+49 6343/1555",
    "sg:postcode":"76887",
    "sg:province":"Rheinland-Pfalz",
    "wof:name":"Alfons Sporer",
    "wof:placetype":"venue"
},
  "geometry": {"coordinates":[7.9976449013,49.1022911072],"type":"Point"}
}