{
  "type": "Feature",
  "properties": {
    "iso:country":"DE",
    "sg:address":"H\u00f6rnlis 1",
    "sg:city":"Heilbronn",
    "sg:postcode":"74074",
    "sg:province":"Baden-W\u00fcrttemberg",
    "wof:name":"Keller Gmbh",
    "wof:placetype":"venue"
},
  "geometry": {"coordinates":[9.2510919571,49.1334877014],"type":"Point"}
}