{
  "type": "Feature",
  "properties": {
    "iso:country":"DE",
    "sg:address":"Roermonder Str. 26",
    "sg:city":"Herzogenrath",
    "sg:phone":"+49 2407/96850",
    "sg:postcode":"52134",
    "sg:province":"Nordrhein-Westfalen",
    "wof:name":"Horst Und Brigitte Debus Rechtsanw\u00e4lte",
    "wof:placetype":"venue"
},
  "geometry": {"coordinates":[6.0743207932,50.843711853],"type":"Point"}
}