{
  "type": "Feature",
  "properties": {
    "iso:country":"DE",
    "sg:address":"Haydnstr. 9",
    "sg:city":"Pullach",
    "sg:phone":"+49 89/7930554",
    "sg:postcode":"82049",
    "sg:province":"Bayern",
    "wof:name":"Wilma Hennevogel Rechtsanw\u00e4ltin",
    "wof:placetype":"venue"
},
  "geometry": {"coordinates":[11.5177059174,48.0641975403],"type":"Point"}
}