{
  "type": "Feature",
  "properties": {
    "iso:country":"DE",
    "sg:address":"Dorfstr. 33",
    "sg:city":"Ahrensb\u00f6k",
    "sg:phone":"+49 4556/1067",
    "sg:postcode":"23623",
    "sg:province":"Schleswig-Holstein",
    "wof:name":"Fritz Grimm",
    "wof:placetype":"venue"
},
  "geometry": {"coordinates":[10.49021,54.000408],"type":"Point"}
}