{
  "type": "Feature",
  "properties": {
    "iso:country":"DE",
    "sg:address":"Schlo\u00dfstr. 24",
    "sg:city":"M\u00fchlacker",
    "sg:phone":"+49 7041/864264",
    "sg:postcode":"75417",
    "sg:province":"Baden-W\u00fcrttemberg",
    "wof:name":"Lothar Teifke",
    "wof:placetype":"venue"
},
  "geometry": {"coordinates":[8.8927698135,48.9407119751],"type":"Point"}
}