{
  "type": "Feature",
  "properties": {
    "iso:country":"DE",
    "sg:address":"Dresdener Str. 58",
    "sg:city":"Wurzen",
    "sg:phone":"+49 3425/88710",
    "sg:postcode":"04808",
    "sg:province":"Sachsen",
    "wof:name":"Be Ha Ge Bau Und Garten Fachhandel Eg",
    "wof:placetype":"venue"
},
  "geometry": {"coordinates":[12.749741,51.364838],"type":"Point"}
}