{
  "type": "Feature",
  "properties": {
    "iso:country":"DE",
    "sg:address":"Gro\u00dfr\u00fcckerswalder Str. 12a",
    "sg:city":"Wolkenstein",
    "sg:phone":"+49 37369/9705",
    "sg:postcode":"09429",
    "sg:province":"Sachsen",
    "wof:name":"Eckard Pohling",
    "wof:placetype":"venue"
},
  "geometry": {"coordinates":[13.082775,50.648605],"type":"Point"}
}