{
  "type": "Feature",
  "properties": {
    "iso:country":"DE",
    "sg:address":"L\u00f6wenstr. 3",
    "sg:city":"B\u00fcdelsdorf",
    "sg:phone":"+49 4331/31272",
    "sg:postcode":"24782",
    "sg:province":"Schleswig-Holstein",
    "wof:name":"Kurt Lohmeyer",
    "wof:placetype":"venue"
},
  "geometry": {"coordinates":[9.6606769562,54.3129768372],"type":"Point"}
}