{
  "type": "Feature",
  "properties": {
    "iso:country":"DE",
    "sg:address":"Schulstr. 1",
    "sg:city":"Knau",
    "sg:postcode":"07389",
    "sg:province":"Th\u00fcringen",
    "wof:name":"Ev.-luth. Kirche Knau",
    "wof:placetype":"venue"
},
  "geometry": {"coordinates":[11.7193136215,50.6519813538],"type":"Point"}
}