{
  "type": "Feature",
  "properties": {
    "iso:country":"DE",
    "sg:address":"Im Neuenheimer Feld 710",
    "sg:city":"Heidelberg",
    "sg:phone":"+49 6221/473636",
    "sg:postcode":"69120",
    "sg:province":"Baden-W\u00fcrttemberg",
    "wof:name":"Nikarklause",
    "wof:placetype":"venue"
},
  "geometry": {"coordinates":[8.6610374451,49.423160553],"type":"Point"}
}