{
  "type": "Feature",
  "properties": {
    "iso:country":"DE",
    "sg:address":"Br\u00fcckenhofstr. 13",
    "sg:city":"Kassel",
    "sg:phone":"+49 561/470056",
    "sg:postcode":"34132",
    "sg:province":"Hessen",
    "wof:name":"Cafe Pesel",
    "wof:placetype":"venue"
},
  "geometry": {"coordinates":[9.452352,51.276794],"type":"Point"}
}