{
  "type": "Feature",
  "properties": {
    "iso:country":"DE",
    "sg:address":"Sprockh\u00f6veler Str. 120",
    "sg:city":"Witten",
    "sg:phone":"+49 2302/52842",
    "sg:postcode":"58455",
    "sg:province":"Nordrhein-Westfalen",
    "wof:name":"Cornelia Vo\u00dfkuhle",
    "wof:placetype":"venue"
},
  "geometry": {"coordinates":[7.322704,51.441402],"type":"Point"}
}