{
  "type": "Feature",
  "properties": {
    "iso:country":"DE",
    "sg:address":"Luitpoldarkaden 9",
    "sg:city":"Treuchtlingen",
    "sg:phone":"+49 9142/2255",
    "sg:postcode":"91757",
    "sg:province":"Bayern",
    "wof:name":"Doris Blumenl\u00e4dchen",
    "wof:placetype":"venue"
},
  "geometry": {"coordinates":[10.908304,48.954998],"type":"Point"}
}