{
  "type": "Feature",
  "properties": {
    "iso:country":"DE",
    "sg:address":"Hammer Str. 94",
    "sg:city":"M\u00fcnster",
    "sg:phone":"+49 251/77017",
    "sg:postcode":"48153",
    "sg:province":"Nordrhein-Westfalen",
    "wof:name":"Aloys Wissing Kg",
    "wof:placetype":"venue"
},
  "geometry": {"coordinates":[7.6238150597,51.948135376],"type":"Point"}
}