{
  "type": "Feature",
  "properties": {
    "iso:country":"DE",
    "sg:address":"Waxensteinstr. 24",
    "sg:city":"Garmisch-Partenkirchen",
    "sg:phone":"+49 8821/71500",
    "sg:postcode":"82467",
    "sg:province":"Bayern",
    "wof:name":"Johann Maurer",
    "wof:placetype":"venue"
},
  "geometry": {"coordinates":[11.080256,47.485355],"type":"Point"}
}