{
  "type": "Feature",
  "properties": {
    "iso:country":"DE",
    "sg:address":"L\u00e4rchenbergweg 2",
    "sg:city":"D\u00fcrrhennersdorf",
    "sg:postcode":"02708",
    "sg:province":"Sachsen",
    "wof:name":"Evangelisches Pfarramt D\u00fcrrhennersdorf",
    "wof:placetype":"venue"
},
  "geometry": {"coordinates":[14.6049032211,51.0468063354],"type":"Point"}
}