{
  "type": "Feature",
  "properties": {
    "iso:country":"DE",
    "sg:address":"Gro\u00dfgr\u00fcndlacher Hauptstr. 33",
    "sg:city":"N\u00fcrnberg",
    "sg:phone":"+49 911/3071982",
    "sg:postcode":"90427",
    "sg:province":"Bayern",
    "wof:name":"Gerhard Berger",
    "wof:placetype":"venue"
},
  "geometry": {"coordinates":[11.0108032227,49.5288352966],"type":"Point"}
}