{
  "type": "Feature",
  "properties": {
    "iso:country":"DE",
    "sg:address":"Wellinghofer Str. 113a",
    "sg:city":"Dortmund",
    "sg:phone":"+49 231/418126",
    "sg:postcode":"44263",
    "sg:province":"Nordrhein-Westfalen",
    "wof:name":"Schumacher",
    "wof:placetype":"venue"
},
  "geometry": {"coordinates":[7.495849,51.480988],"type":"Point"}
}