{
  "type": "Feature",
  "properties": {
    "iso:country":"DE",
    "sg:address":"Hangstr. 4",
    "sg:city":"Zell",
    "sg:phone":"+49 9468/395",
    "sg:postcode":"93199",
    "sg:province":"Bayern",
    "wof:name":"Martin Schwarzfischer",
    "wof:placetype":"venue"
},
  "geometry": {"coordinates":[12.419982,49.127529],"type":"Point"}
}