{
  "type": "Feature",
  "properties": {
    "iso:country":"DE",
    "sg:address":"Zum Reisberg 21",
    "sg:city":"Merzig",
    "sg:phone":"+49 6861/88922",
    "sg:postcode":"66663",
    "sg:province":"Saarland",
    "wof:name":"Josef Donnh\u00e4user",
    "wof:placetype":"venue"
},
  "geometry": {"coordinates":[6.651261,49.46262],"type":"Point"}
}