{
  "type": "Feature",
  "properties": {
    "iso:country":"DE",
    "sg:address":"Ackerstr. 86",
    "sg:city":"D\u00fcsseldorf",
    "sg:phone":"+49 211/689293",
    "sg:postcode":"40233",
    "sg:province":"Nordrhein-Westfalen",
    "wof:name":"Birkeneck",
    "wof:placetype":"venue"
},
  "geometry": {"coordinates":[6.8010649681,51.2275352478],"type":"Point"}
}