{
  "type": "Feature",
  "properties": {
    "iso:country":"DE",
    "sg:address":"Krickmarkt 9",
    "sg:city":"Warendorf",
    "sg:phone":"+49 2581/1556",
    "sg:postcode":"48231",
    "sg:province":"Nordrhein-Westfalen",
    "wof:name":"Foto-schorcht",
    "wof:placetype":"venue"
},
  "geometry": {"coordinates":[7.9902210236,51.9519691467],"type":"Point"}
}