{
  "type": "Feature",
  "properties": {
    "iso:country":"DE",
    "sg:address":"Lortzingstra\u00dfe 1",
    "sg:city":"Hannover",
    "sg:phone":"+49 511/3587980",
    "sg:postcode":"30177",
    "sg:province":"Niedersachsen",
    "wof:name":"Cadnet",
    "wof:placetype":"venue"
},
  "geometry": {"coordinates":[9.75828,52.392605],"type":"Point"}
}