{
  "type": "Feature",
  "properties": {
    "iso:country":"DE",
    "sg:address":"Albert-Schweitzer-Str. 24",
    "sg:city":"Germering",
    "sg:phone":"+49 89/847834",
    "sg:postcode":"82110",
    "sg:province":"Bayern",
    "wof:name":"Software B\u00fcro H\u00f6ppner Gmbh",
    "wof:placetype":"venue"
},
  "geometry": {"coordinates":[11.3792448044,48.1274795532],"type":"Point"}
}