{
  "type": "Feature",
  "properties": {
    "iso:country":"DE",
    "sg:address":"Industriering 18",
    "sg:city":"Breiteng\u00fc\u00dfbach",
    "sg:phone":"+49 9544/5061",
    "sg:postcode":"96149",
    "sg:province":"Bayern",
    "wof:name":"Lechmann Bauunternehmung Gmbh & Co. Kg",
    "wof:placetype":"venue"
},
  "geometry": {"coordinates":[10.880226,49.974194],"type":"Point"}
}