{
  "type": "Feature",
  "properties": {
    "iso:country":"DE",
    "sg:address":"Hof Heidhof 14",
    "sg:city":"Remscheid",
    "sg:phone":"+49 4921/9124217",
    "sg:postcode":"42855",
    "sg:province":"Nordrhein-Westfalen",
    "wof:name":"Hans Janssen Kg",
    "wof:placetype":"venue"
},
  "geometry": {"coordinates":[7.184598,51.188931],"type":"Point"}
}