{
  "type": "Feature",
  "properties": {
    "iso:country":"DE",
    "sg:address":"Paulusstr. 5",
    "sg:city":"Stuttgart",
    "sg:phone":"+49 711/631976",
    "sg:postcode":"70197",
    "sg:province":"Baden-W\u00fcrttemberg",
    "wof:name":"Klaus Hiller Steuerberater",
    "wof:placetype":"venue"
},
  "geometry": {"coordinates":[9.1517763138,48.7727737427],"type":"Point"}
}