{
  "type": "Feature",
  "properties": {
    "iso:country":"DE",
    "sg:address":"Bahnhofstr. 9",
    "sg:city":"Frankenberg",
    "sg:phone":"+49 6455/1842",
    "sg:postcode":"35066",
    "sg:province":"Hessen",
    "wof:name":"Kath. \u00f6ffentliche Bibliothek",
    "wof:placetype":"venue"
},
  "geometry": {"coordinates":[8.792637,51.05624],"type":"Point"}
}