{
  "type": "Feature",
  "properties": {
    "iso:country":"DE",
    "sg:address":"Thalkirchner Str. 25",
    "sg:city":"M\u00fcnchen",
    "sg:postcode":"80337",
    "sg:province":"Bayern",
    "wof:name":"Helios Import Gmbh",
    "wof:placetype":"venue"
},
  "geometry": {"coordinates":[11.561459,48.124336],"type":"Point"}
}