{
  "type": "Feature",
  "properties": {
    "iso:country":"DE",
    "sg:address":"Dahlmannstr. 58",
    "sg:city":"Duisburg",
    "sg:phone":"+49 203/400731",
    "sg:postcode":"47169",
    "sg:province":"Nordrhein-Westfalen",
    "wof:name":"Hermann Kern Bauunternehmung",
    "wof:placetype":"venue"
},
  "geometry": {"coordinates":[6.7629628181,51.5031776428],"type":"Point"}
}