{
  "type": "Feature",
  "properties": {
    "iso:country":"DE",
    "sg:address":"Klosterstr. 61",
    "sg:city":"Edenkoben",
    "sg:phone":"+49 6323/5902",
    "sg:postcode":"67480",
    "sg:province":"Rheinland-Pfalz",
    "wof:name":"Klaus Schreieck Weinanbau",
    "wof:placetype":"venue"
},
  "geometry": {"coordinates":[8.1240940094,49.2829322815],"type":"Point"}
}