{
  "type": "Feature",
  "properties": {
    "iso:country":"DE",
    "sg:address":"Riedweg 2 - 4",
    "sg:city":"Br\u00e4unlingen",
    "sg:postcode":"78199",
    "sg:province":"Baden-W\u00fcrttemberg",
    "wof:name":"Fesenmeyer B\u00e4ckerm\u00fchlen Gmbh & Co. Kg",
    "wof:placetype":"venue"
},
  "geometry": {"coordinates":[8.450485,47.927288],"type":"Point"}
}