{
  "type": "Feature",
  "properties": {
    "iso:country":"DE",
    "sg:address":"Rheinstr. 15",
    "sg:city":"Schwanau",
    "sg:phone":"+49 7824/64960",
    "sg:postcode":"77963",
    "sg:province":"Baden-W\u00fcrttemberg",
    "wof:name":"Vogel-bau Gmbh",
    "wof:placetype":"venue"
},
  "geometry": {"coordinates":[7.7482051849,48.3892288208],"type":"Point"}
}