{
  "type": "Feature",
  "properties": {
    "iso:country":"DE",
    "sg:address":"Muchweg 3",
    "sg:city":"Gmund",
    "sg:phone":"+49 8022/74771",
    "sg:postcode":"83703",
    "sg:province":"Bayern",
    "wof:name":"Royo-med Hard- Und Software Gmbh",
    "wof:placetype":"venue"
},
  "geometry": {"coordinates":[11.7477416992,47.7487335205],"type":"Point"}
}