{
  "type": "Feature",
  "properties": {
    "iso:country":"DE",
    "sg:address":"Im Schluh",
    "sg:city":"Worpswede",
    "sg:phone":"+49 4792/7160",
    "sg:postcode":"27726",
    "sg:province":"Niedersachsen",
    "wof:name":"Heinrich-vogeler-sammlung Und Worsweder Archiv",
    "wof:placetype":"venue"
},
  "geometry": {"coordinates":[8.934583,53.224056],"type":"Point"}
}