{
  "type": "Feature",
  "properties": {
    "iso:country":"DE",
    "sg:address":"Alte Bahnhofstr. 16",
    "sg:city":"Schleiden",
    "sg:phone":"+49 2444/950950",
    "sg:postcode":"53937",
    "sg:province":"Nordrhein-Westfalen",
    "wof:name":"Akzent-hotel Friedrichs",
    "wof:placetype":"venue"
},
  "geometry": {"coordinates":[6.5009469986,50.57264328],"type":"Point"}
}