{
  "type": "Feature",
  "properties": {
    "iso:country":"DE",
    "sg:address":"Harburger Rathausstr. 33",
    "sg:city":"Hamburg",
    "sg:phone":"+49 40/772082",
    "sg:postcode":"21073",
    "sg:province":"Hamburg",
    "wof:name":"S & B Treuhand- Und Steuerberatungs Gmbh",
    "wof:placetype":"venue"
},
  "geometry": {"coordinates":[9.9811372757,53.4594078064],"type":"Point"}
}