{
  "type": "Feature",
  "properties": {
    "iso:country":"DE",
    "sg:address":"M\u00fcllerstr. 26",
    "sg:city":"M\u00fcnchen",
    "sg:phone":"+49 89/266712",
    "sg:postcode":"80469",
    "sg:province":"Bayern",
    "wof:name":"Wasil Jiwkow",
    "wof:placetype":"venue"
},
  "geometry": {"coordinates":[11.5717277527,48.1316146851],"type":"Point"}
}