{
  "type": "Feature",
  "properties": {
    "iso:country":"DE",
    "sg:address":"Ingenrieder Str. 1",
    "sg:city":"Schongau",
    "sg:phone":"+49 8861/8759",
    "sg:postcode":"86956",
    "sg:province":"Bayern",
    "wof:name":"W\u00f6hnl",
    "wof:placetype":"venue"
},
  "geometry": {"coordinates":[10.877338,47.809654],"type":"Point"}
}