{
  "type": "Feature",
  "properties": {
    "iso:country":"DE",
    "sg:address":"Wilhelmstr. 50",
    "sg:city":"T\u00fcbingen",
    "sg:phone":"+49 7071/294325",
    "sg:postcode":"72074",
    "sg:province":"Baden-W\u00fcrttemberg",
    "wof:name":"Neuphilologische Fakult\u00e4t Bibliothek",
    "wof:placetype":"venue"
},
  "geometry": {"coordinates":[9.063085,48.527466],"type":"Point"}
}