{
  "type": "Feature",
  "properties": {
    "iso:country":"DE",
    "sg:address":"Korbacher Str. 15",
    "sg:city":"Willingen",
    "sg:phone":"+49 5632/5363",
    "sg:postcode":"34508",
    "sg:province":"Hessen",
    "wof:name":"Pension Karl E. Saure",
    "wof:placetype":"venue"
},
  "geometry": {"coordinates":[8.6675701141,51.2821426392],"type":"Point"}
}