{
  "type": "Feature",
  "properties": {
    "iso:country":"DE",
    "sg:address":"Klobikauer Str. 78",
    "sg:city":"Merseburg",
    "sg:phone":"+49 3461/503787",
    "sg:postcode":"06217",
    "sg:province":"Sachsen-Anhalt",
    "wof:name":"W. Brockelt",
    "wof:placetype":"venue"
},
  "geometry": {"coordinates":[11.976849,51.351276],"type":"Point"}
}