{
  "type": "Feature",
  "properties": {
    "iso:country":"DE",
    "sg:address":"Vorwerk 6",
    "sg:city":"Sangerhausen",
    "sg:phone":"+49 3464/570163",
    "sg:postcode":"06526",
    "sg:province":"Sachsen-Anhalt",
    "wof:name":"Steakhouse Und Dart- Billard-pub",
    "wof:placetype":"venue"
},
  "geometry": {"coordinates":[11.298995018,51.4755897522],"type":"Point"}
}