{
  "type": "Feature",
  "properties": {
    "iso:country":"DE",
    "sg:address":"Eisenbahnweg 2",
    "sg:city":"Aachen",
    "sg:phone":"+49 241/575956",
    "sg:postcode":"52068",
    "sg:province":"Nordrhein-Westfalen",
    "wof:name":"Propan Rheingas Gmbh & Co. Kg",
    "wof:placetype":"venue"
},
  "geometry": {"coordinates":[6.118902,50.769897],"type":"Point"}
}