{
  "type": "Feature",
  "properties": {
    "iso:country":"DE",
    "sg:address":"Kurt-Tucholsky-Str. 10",
    "sg:city":"Rostock",
    "sg:phone":"+49 381/4003851",
    "sg:postcode":"18059",
    "sg:province":"Mecklenburg-Vorpommern",
    "wof:name":"Ferienhausvermietung Sonne Und Strand",
    "wof:placetype":"venue"
},
  "geometry": {"coordinates":[12.1239490509,54.0719528198],"type":"Point"}
}