{
  "type": "Feature",
  "properties": {
    "iso:country":"DE",
    "sg:address":"Schmiedestr. 20",
    "sg:city":"Markkleeberg",
    "sg:phone":"+49 341/3587415",
    "sg:postcode":"04416",
    "sg:province":"Sachsen",
    "wof:name":"Dr. Evelyne Sch\u00f6n Tier\u00e4rztin",
    "wof:placetype":"venue"
},
  "geometry": {"coordinates":[12.3565206528,51.2663040161],"type":"Point"}
}