{
  "type": "Feature",
  "properties": {
    "iso:country":"DE",
    "sg:address":"Adolfstr. 51",
    "sg:city":"Westerburg",
    "sg:phone":"+49 2663/8436",
    "sg:postcode":"56457",
    "sg:province":"Rheinland-Pfalz",
    "wof:name":"Dietmar Meudt Architekt Bdb",
    "wof:placetype":"venue"
},
  "geometry": {"coordinates":[7.977152,50.561905],"type":"Point"}
}