{
  "type": "Feature",
  "properties": {
    "iso:country":"DE",
    "sg:address":"Straubenbergstr. 38",
    "sg:city":"Bad Wildbad",
    "sg:phone":"+49 7081/8103",
    "sg:postcode":"75323",
    "sg:province":"Baden-W\u00fcrttemberg",
    "wof:name":"Restaurant Silberburg",
    "wof:placetype":"venue"
},
  "geometry": {"coordinates":[8.5483121872,48.7492523193],"type":"Point"}
}