{
  "type": "Feature",
  "properties": {
    "iso:country":"DE",
    "sg:address":"Viktoriastr. 32-36",
    "sg:city":"Koblenz",
    "sg:phone":"+49 261/24097",
    "sg:postcode":"56068",
    "sg:province":"Rheinland-Pfalz",
    "wof:name":"Bank F\u00fcr Gemeinwirtschaft",
    "wof:placetype":"venue"
},
  "geometry": {"coordinates":[7.594259,50.356346],"type":"Point"}
}