{
  "type": "Feature",
  "properties": {
    "iso:country":"DE",
    "sg:address":"Zinkstr 30",
    "sg:city":"Essen",
    "sg:phone":"+49 201/861500",
    "sg:postcode":"45356",
    "sg:province":"Nordrhein-Westfalen",
    "wof:name":"Wilhelm Damrosch Kg",
    "wof:placetype":"venue"
},
  "geometry": {"coordinates":[6.9695558548,51.4806365967],"type":"Point"}
}