{
  "type": "Feature",
  "properties": {
    "iso:country":"DE",
    "sg:address":"Max-Planck-Str. 36 b",
    "sg:city":"Friedrichsdorf",
    "sg:phone":"+49 6172/71010",
    "sg:postcode":"61381",
    "sg:province":"Hessen",
    "wof:name":"Expo Event Und Promotion Services Gmbh",
    "wof:placetype":"venue"
},
  "geometry": {"coordinates":[8.6600389481,50.2581138611],"type":"Point"}
}