{
  "type": "Feature",
  "properties": {
    "iso:country":"DE",
    "sg:address":"Weilandtshof",
    "sg:city":"Heringsdorf",
    "sg:postcode":"23777",
    "sg:province":"Schleswig-Holstein",
    "wof:name":"Windpark Kalkberg Gmbh",
    "wof:placetype":"venue"
},
  "geometry": {"coordinates":[11.004588,54.300686],"type":"Point"}
}