{
  "type": "Feature",
  "properties": {
    "iso:country":"DE",
    "sg:address":"M\u00fchlheimer Str. 5",
    "sg:city":"Empfingen",
    "sg:phone":"+49 4974/85369",
    "sg:postcode":"72186",
    "sg:province":"Baden-W\u00fcrttemberg",
    "wof:name":"Volksbank Horb Eg",
    "wof:placetype":"venue"
},
  "geometry": {"coordinates":[8.709695,48.392361],"type":"Point"}
}