{
  "type": "Feature",
  "properties": {
    "iso:country":"DE",
    "sg:address":"Stra\u00dfe der Jugend 2",
    "sg:city":"Pirna",
    "sg:phone":"+49 3501/784950",
    "sg:postcode":"01796",
    "sg:province":"Sachsen",
    "wof:name":"Lilienstein-apotheke Inh. Klaus Haufe",
    "wof:placetype":"venue"
},
  "geometry": {"coordinates":[13.955645,50.952618],"type":"Point"}
}