{
  "type": "Feature",
  "properties": {
    "iso:country":"DE",
    "sg:address":"Bedingrader Str. 135",
    "sg:city":"Essen",
    "sg:phone":"+49 201/698208",
    "sg:postcode":"45359",
    "sg:province":"Nordrhein-Westfalen",
    "wof:name":"Cafe Restaurant Talsch\u00e4nke",
    "wof:placetype":"venue"
},
  "geometry": {"coordinates":[6.9112329483,51.4686088562],"type":"Point"}
}