{
  "type": "Feature",
  "properties": {
    "iso:country":"DE",
    "sg:address":"Walder Str. 32",
    "sg:city":"Sauldorf",
    "sg:phone":"+49 7578/505",
    "sg:postcode":"88605",
    "sg:province":"Baden-W\u00fcrttemberg",
    "wof:name":"Robert Stadler",
    "wof:placetype":"venue"
},
  "geometry": {"coordinates":[9.122148,47.939129],"type":"Point"}
}