{
  "type": "Feature",
  "properties": {
    "iso:country":"DE",
    "sg:address":"Spitalplatz 5",
    "sg:city":"Landau",
    "sg:phone":"+49 9951/6547",
    "sg:postcode":"94405",
    "sg:province":"Bayern",
    "wof:name":"Hypo-bank",
    "wof:placetype":"venue"
},
  "geometry": {"coordinates":[12.69509,48.673508],"type":"Point"}
}