{
  "type": "Feature",
  "properties": {
    "iso:country":"DE",
    "sg:address":"Winkelbrunn",
    "sg:city":"Freyung",
    "sg:phone":"+49 8551/7037",
    "sg:postcode":"94078",
    "sg:province":"Bayern",
    "wof:name":"Niedermeier",
    "wof:placetype":"venue"
},
  "geometry": {"coordinates":[13.5892524719,48.7996101379],"type":"Point"}
}