{
  "type": "Feature",
  "properties": {
    "iso:country":"DE",
    "sg:address":"Am Alten Kaninsberg 10-12",
    "sg:city":"W\u00fcrselen",
    "sg:phone":"+49 4924/05610",
    "sg:postcode":"52146",
    "sg:province":"Nordrhein-Westfalen",
    "wof:name":"Trawigo Gmbh & Co Kg",
    "wof:placetype":"venue"
},
  "geometry": {"coordinates":[6.1413807869,50.8107757568],"type":"Point"}
}