{
  "type": "Feature",
  "properties": {
    "iso:country":"DE",
    "sg:address":"Rheinhessenstr. 91",
    "sg:city":"Bad Kreuznach",
    "sg:phone":"+49 671/61314",
    "sg:postcode":"55545",
    "sg:province":"Rheinland-Pfalz",
    "wof:name":"Schreinerei Huy Gmbh",
    "wof:placetype":"venue"
},
  "geometry": {"coordinates":[7.918225,49.845901],"type":"Point"}
}