{
  "type": "Feature",
  "properties": {
    "iso:country":"DE",
    "sg:address":"Nordstr. 2",
    "sg:city":"Brieske",
    "sg:phone":"+49 3573/61005",
    "sg:postcode":"01968",
    "sg:province":"Brandenburg",
    "wof:name":"Delikat Gmbh",
    "wof:placetype":"venue"
},
  "geometry": {"coordinates":[13.9737863541,51.5071563721],"type":"Point"}
}