{
  "type": "Feature",
  "properties": {
    "iso:country":"DE",
    "sg:address":"Dechbettener Str. 47b",
    "sg:city":"Regensburg",
    "sg:phone":"+49 941/26080",
    "sg:postcode":"93049",
    "sg:province":"Bayern",
    "wof:name":"Begegnung Mit B\u00f6hmen",
    "wof:placetype":"venue"
},
  "geometry": {"coordinates":[12.0765447617,49.0142593384],"type":"Point"}
}