{
  "type": "Feature",
  "properties": {
    "iso:country":"DE",
    "sg:address":"Nymphenburger Str. 2",
    "sg:city":"Berlin",
    "sg:phone":"+49 30/8546017",
    "sg:postcode":"10825",
    "sg:province":"Berlin",
    "wof:name":"Editha Seewald Rechtsanw\u00e4ltin",
    "wof:placetype":"venue"
},
  "geometry": {"coordinates":[13.3405828476,52.4814529419],"type":"Point"}
}