{
  "type": "Feature",
  "properties": {
    "iso:country":"DE",
    "sg:address":"Daimlerstr. 27",
    "sg:city":"Oberboihingen",
    "sg:phone":"+49 7022/63024",
    "sg:postcode":"72644",
    "sg:province":"Baden-W\u00fcrttemberg",
    "wof:name":"Conveyors Schwaben F\u00f6rderanlagen Gmbh",
    "wof:placetype":"venue"
},
  "geometry": {"coordinates":[9.36521,48.65564],"type":"Point"}
}