{
  "type": "Feature",
  "properties": {
    "iso:country":"DE",
    "sg:address":"Riederm\u00fchle 2 a",
    "sg:city":"Ilmm\u00fcnster",
    "sg:phone":"+49 8441/81012",
    "sg:postcode":"85304",
    "sg:province":"Bayern",
    "wof:name":"Baumann Gmbh",
    "wof:placetype":"venue"
},
  "geometry": {"coordinates":[11.501518,48.486439],"type":"Point"}
}