{
  "type": "Feature",
  "properties": {
    "iso:country":"DE",
    "sg:address":"Johann-Meier-Str. 12",
    "sg:city":"Dessau",
    "sg:phone":"+49 340/2200931",
    "sg:postcode":"06842",
    "sg:province":"Sachsen-Anhalt",
    "wof:name":"Brigitte Passek",
    "wof:placetype":"venue"
},
  "geometry": {"coordinates":[12.2332496643,51.8264541626],"type":"Point"}
}