{
  "type": "Feature",
  "properties": {
    "iso:country":"DE",
    "sg:address":"Weiskircher Str. 1",
    "sg:city":"Rodgau",
    "sg:phone":"+49 6106/3665",
    "sg:postcode":"63110",
    "sg:province":"Hessen",
    "wof:name":"Metzgerei Hiller Gmbh",
    "wof:placetype":"venue"
},
  "geometry": {"coordinates":[8.9042453766,50.0650482178],"type":"Point"}
}