{
  "type": "Feature",
  "properties": {
    "iso:country":"DE",
    "sg:address":"Neutorstr. 4",
    "sg:city":"W\u00fcrzburg",
    "sg:phone":"+49 931/17254",
    "sg:postcode":"97070",
    "sg:province":"Bayern",
    "wof:name":"Oesta Gmbh",
    "wof:placetype":"venue"
},
  "geometry": {"coordinates":[9.9394540787,49.7982635498],"type":"Point"}
}