{
  "type": "Feature",
  "properties": {
    "iso:country":"DE",
    "sg:address":"Wilhelmstr. 8",
    "sg:city":"J\u00fcchen",
    "sg:postcode":"41363",
    "sg:province":"Nordrhein-Westfalen",
    "wof:name":"Die Gr\u00fcnen In J\u00fcchen",
    "wof:placetype":"venue"
},
  "geometry": {"coordinates":[6.501989,51.0998],"type":"Point"}
}