{
  "type": "Feature",
  "properties": {
    "iso:country":"DE",
    "sg:address":"An der Obergeis 19",
    "sg:city":"Bad Hersfeld",
    "sg:phone":"+49 6621/51880",
    "sg:postcode":"36251",
    "sg:province":"Hessen",
    "wof:name":"Allkauf Foto Inh. Thomas Vaupel",
    "wof:placetype":"venue"
},
  "geometry": {"coordinates":[9.7085199356,50.8696708679],"type":"Point"}
}