{
  "type": "Feature",
  "properties": {
    "iso:country":"DE",
    "sg:address":"Glasmoorstr 24a",
    "sg:city":"Norderstedt",
    "sg:phone":"+49 40/20975173",
    "sg:postcode":"22851",
    "sg:province":"Schleswig-Holstein",
    "wof:name":"Zekal",
    "wof:placetype":"venue"
},
  "geometry": {"coordinates":[10.03375,53.697891],"type":"Point"}
}