{
  "type": "Feature",
  "properties": {
    "iso:country":"DE",
    "sg:address":"Am Schleifweg 5",
    "sg:city":"Mainz",
    "sg:phone":"+49 6131/140780",
    "sg:postcode":"55128",
    "sg:province":"Rheinland-Pfalz",
    "wof:name":"Hornbach-baumarkt- Ag",
    "wof:placetype":"venue"
},
  "geometry": {"coordinates":[8.2373161316,49.9669647217],"type":"Point"}
}