{
  "type": "Feature",
  "properties": {
    "iso:country":"DE",
    "sg:address":"Am Badezentrum 2",
    "sg:city":"Krefeld",
    "sg:phone":"+49 2151/590041",
    "sg:postcode":"47800",
    "sg:province":"Nordrhein-Westfalen",
    "wof:name":"Badezentrum Bockum",
    "wof:placetype":"venue"
},
  "geometry": {"coordinates":[6.6161599159,51.3540382385],"type":"Point"}
}