{
  "type": "Feature",
  "properties": {
    "iso:country":"DE",
    "sg:address":"Petzoltstr. 8",
    "sg:city":"Marktheidenfeld",
    "sg:phone":"+49 9391/917091",
    "sg:postcode":"97828",
    "sg:province":"Bayern",
    "wof:name":"Claus Hebeler Rechtsanwalt",
    "wof:placetype":"venue"
},
  "geometry": {"coordinates":[9.6015644073,49.846157074],"type":"Point"}
}