{
  "type": "Feature",
  "properties": {
    "iso:country":"DE",
    "sg:address":"Riedm\u00fchlestr. 2",
    "sg:city":"Sindelfingen",
    "sg:phone":"+49 7031/876081",
    "sg:postcode":"71063",
    "sg:province":"Baden-W\u00fcrttemberg",
    "wof:name":"Karl-heinz Hertel",
    "wof:placetype":"venue"
},
  "geometry": {"coordinates":[8.9977855682,48.7067947388],"type":"Point"}
}