{
  "type": "Feature",
  "properties": {
    "iso:country":"DE",
    "sg:address":"Wilhelmsdorf 9",
    "sg:city":"Brandenburg",
    "sg:phone":"+49 3381/663146",
    "sg:postcode":"14776",
    "sg:province":"Brandenburg",
    "wof:name":"G. Kluge",
    "wof:placetype":"venue"
},
  "geometry": {"coordinates":[12.502605,52.371174],"type":"Point"}
}