{
  "type": "Feature",
  "properties": {
    "iso:country":"DE",
    "sg:address":"Mittlere St\u00e4mmig 18",
    "sg:city":"Uettingen",
    "sg:phone":"+49 9369/990744",
    "sg:postcode":"97292",
    "sg:province":"Bayern",
    "wof:name":"Burkhard Weber Heizungsbau Gmbh",
    "wof:placetype":"venue"
},
  "geometry": {"coordinates":[9.7136030197,49.7947692871],"type":"Point"}
}