{
  "type": "Feature",
  "properties": {
    "iso:country":"DE",
    "sg:address":"Bergstr. 10",
    "sg:city":"Bad Schwalbach",
    "sg:postcode":"65307",
    "sg:province":"Hessen",
    "wof:name":"Gabrielle Pertoft Heilpraktikerin",
    "wof:placetype":"venue"
},
  "geometry": {"coordinates":[8.0470199585,50.1546592712],"type":"Point"}
}