{
  "type": "Feature",
  "properties": {
    "iso:country":"DE",
    "sg:address":"Sonnenstr. 43",
    "sg:city":"M\u00fcnster",
    "sg:phone":"+49 251/43013",
    "sg:postcode":"48143",
    "sg:province":"Nordrhein-Westfalen",
    "wof:name":"Na Und",
    "wof:placetype":"venue"
},
  "geometry": {"coordinates":[7.6332950592,51.9642982483],"type":"Point"}
}