{
  "type": "Feature",
  "properties": {
    "iso:country":"DE",
    "sg:address":"S\u00fcllenstr. 26",
    "sg:city":"D\u00fcsseldorf",
    "sg:phone":"+49 211/741380",
    "sg:postcode":"40599",
    "sg:province":"Nordrhein-Westfalen",
    "wof:name":"Klaus Peschel Dachdeckermeister Gmbh",
    "wof:placetype":"venue"
},
  "geometry": {"coordinates":[6.871136,51.171848],"type":"Point"}
}