{
  "type": "Feature",
  "properties": {
    "iso:country":"DE",
    "sg:address":"Coppenbr\u00fcgger Landstr. 55",
    "sg:city":"Lauenau",
    "sg:postcode":"31867",
    "sg:province":"Niedersachsen",
    "wof:name":"Hoppe Tankstellen Gmbh",
    "wof:placetype":"venue"
},
  "geometry": {"coordinates":[9.370425,52.267895],"type":"Point"}
}