{
  "type": "Feature",
  "properties": {
    "iso:country":"DE",
    "sg:address":"Quastenberger Damm 22",
    "sg:city":"Burg Stargard",
    "sg:phone":"+49 39603/20792",
    "sg:postcode":"17094",
    "sg:province":"Mecklenburg-Vorpommern",
    "wof:name":"Lutz Soback",
    "wof:placetype":"venue"
},
  "geometry": {"coordinates":[13.326965,53.495167],"type":"Point"}
}