{
  "type": "Feature",
  "properties": {
    "iso:country":"DE",
    "sg:address":"Achterweg 57",
    "sg:city":"Pr\u00fcm",
    "sg:phone":"+49 6551/6108",
    "sg:postcode":"54595",
    "sg:province":"Rheinland-Pfalz",
    "wof:name":"Norbert Klasen",
    "wof:placetype":"venue"
},
  "geometry": {"coordinates":[6.411815,50.206264],"type":"Point"}
}