{
  "type": "Feature",
  "properties": {
    "iso:country":"DE",
    "sg:address":"Waldstr.",
    "sg:city":"Bad Lausick",
    "sg:postcode":"04651",
    "sg:province":"Sachsen",
    "wof:name":"Sandra F\u00fcssel",
    "wof:placetype":"venue"
},
  "geometry": {"coordinates":[12.652094841,51.1464881897],"type":"Point"}
}