{
  "type": "Feature",
  "properties": {
    "iso:country":"DE",
    "sg:address":"Direktor-Wolf-Str. 7",
    "sg:city":"Rottenburg",
    "sg:phone":"+49 8785/244",
    "sg:postcode":"84056",
    "sg:province":"Bayern",
    "wof:name":"H. Meier",
    "wof:placetype":"venue"
},
  "geometry": {"coordinates":[12.04016,48.720341],"type":"Point"}
}