{
  "type": "Feature",
  "properties": {
    "iso:country":"DE",
    "sg:address":"Lantzallee 17",
    "sg:city":"D\u00fcsseldorf",
    "sg:phone":"+49 211/432281",
    "sg:postcode":"40474",
    "sg:province":"Nordrhein-Westfalen",
    "wof:name":"Bernhard Von Kries Architket",
    "wof:placetype":"venue"
},
  "geometry": {"coordinates":[6.739361,51.278042],"type":"Point"}
}