{
  "type": "Feature",
  "properties": {
    "iso:country":"DE",
    "sg:address":"Schulstr. 87",
    "sg:city":"Marl",
    "sg:phone":"+49 2365/84551",
    "sg:postcode":"45770",
    "sg:province":"Nordrhein-Westfalen",
    "wof:name":"Klaus Schippling",
    "wof:placetype":"venue"
},
  "geometry": {"coordinates":[7.1867599487,51.6694602966],"type":"Point"}
}