{
  "type": "Feature",
  "properties": {
    "iso:country":"DE",
    "sg:address":"Angerbrunnenstr. 10",
    "sg:city":"Freising",
    "sg:phone":"+49 8161/82861",
    "sg:postcode":"85356",
    "sg:province":"Bayern",
    "wof:name":"Meuvo \u00d6kotechnik Gmbh",
    "wof:placetype":"venue"
},
  "geometry": {"coordinates":[11.7586450577,48.3883895874],"type":"Point"}
}