{
  "type": "Feature",
  "properties": {
    "iso:country":"DE",
    "sg:address":"Am Anger 48",
    "sg:city":"Altenburg",
    "sg:phone":"+49 3447/502671",
    "sg:postcode":"04600",
    "sg:province":"Th\u00fcringen",
    "wof:name":"Holzhandel Leipzig Kl\u00f6pferholz Gmbh",
    "wof:placetype":"venue"
},
  "geometry": {"coordinates":[12.43496,50.984699],"type":"Point"}
}