{
  "type": "Feature",
  "properties": {
    "iso:country":"DE",
    "sg:address":"Berliner Str. 6",
    "sg:city":"Salzgitter",
    "sg:postcode":"38226",
    "sg:province":"Niedersachsen",
    "wof:name":"Aschmann Und Partner",
    "wof:placetype":"venue"
},
  "geometry": {"coordinates":[10.3333959579,52.153175354],"type":"Point"}
}