{
  "type": "Feature",
  "properties": {
    "iso:country":"DE",
    "sg:address":"Baroper Str. 244a",
    "sg:city":"Dortmund",
    "sg:phone":"+49 231/753513",
    "sg:postcode":"44227",
    "sg:province":"Nordrhein-Westfalen",
    "wof:name":"A. Licker Und U. Thelen Architekten",
    "wof:placetype":"venue"
},
  "geometry": {"coordinates":[7.420139,51.487629],"type":"Point"}
}