{
  "type": "Feature",
  "properties": {
    "iso:country":"DE",
    "sg:address":"Auf der Ruhr 48",
    "sg:city":"K\u00f6ln",
    "sg:phone":"+49 2236/64757",
    "sg:postcode":"50999",
    "sg:province":"Nordrhein-Westfalen",
    "wof:name":"Aloys Hannappel Gmbh",
    "wof:placetype":"venue"
},
  "geometry": {"coordinates":[7.029686,50.87252],"type":"Point"}
}