{
  "type": "Feature",
  "properties": {
    "iso:country":"DE",
    "sg:address":"Beutnerring 19",
    "sg:city":"Hamburg",
    "sg:phone":"+49 40/7604160",
    "sg:postcode":"21077",
    "sg:province":"Hamburg",
    "wof:name":"Hans Sticken",
    "wof:placetype":"venue"
},
  "geometry": {"coordinates":[9.955191,53.443832],"type":"Point"}
}