{
  "type": "Feature",
  "properties": {
    "iso:country":"DE",
    "sg:address":"Kirchstr. 17",
    "sg:city":"Achern",
    "sg:phone":"+49 7841/24757",
    "sg:postcode":"77855",
    "sg:province":"Baden-W\u00fcrttemberg",
    "wof:name":"Am Stadtgarten Inh. Thomas Kopf",
    "wof:placetype":"venue"
},
  "geometry": {"coordinates":[8.0733852386,48.6312828064],"type":"Point"}
}