{
  "type": "Feature",
  "properties": {
    "iso:country":"DE",
    "sg:address":"Gautinger Str. 38b",
    "sg:city":"Neuried",
    "sg:phone":"+49 89/74576203",
    "sg:postcode":"82061",
    "sg:province":"Bayern",
    "wof:name":"Michael Luckau Ingenieur",
    "wof:placetype":"venue"
},
  "geometry": {"coordinates":[11.4575414658,48.0888710022],"type":"Point"}
}