{
  "type": "Feature",
  "properties": {
    "iso:country":"DE",
    "sg:address":"Uhlhornsweg 99 a",
    "sg:city":"Oldenburg",
    "sg:postcode":"26129",
    "sg:province":"Niedersachsen",
    "wof:name":"Mediapolis Gmbh & Co. Kg",
    "wof:placetype":"venue"
},
  "geometry": {"coordinates":[8.1826200485,53.1483383179],"type":"Point"}
}