{
  "type": "Feature",
  "properties": {
    "iso:country":"DE",
    "sg:address":"Urentalstr. 1",
    "sg:city":"Beverungen",
    "sg:phone":"+49 5645/476",
    "sg:postcode":"37688",
    "sg:province":"Nordrhein-Westfalen",
    "wof:name":"Karl Menke",
    "wof:placetype":"venue"
},
  "geometry": {"coordinates":[9.29174,51.626999],"type":"Point"}
}