{
  "type": "Feature",
  "properties": {
    "iso:country":"DE",
    "sg:address":"Br\u00fcckenstr. 8",
    "sg:city":"Reichelsheim",
    "sg:phone":"+49 6164/4201",
    "sg:postcode":"64385",
    "sg:province":"Hessen",
    "wof:name":"P. Arras Iii",
    "wof:placetype":"venue"
},
  "geometry": {"coordinates":[8.86773,49.720039],"type":"Point"}
}