{
  "type": "Feature",
  "properties": {
    "iso:country":"DE",
    "sg:address":"Niedersachsenring 80",
    "sg:city":"M\u00fcnster",
    "sg:phone":"+49 251/2301511",
    "sg:postcode":"48147",
    "sg:province":"Nordrhein-Westfalen",
    "wof:name":"Kaspar Pr\u00fcnte Kg",
    "wof:placetype":"venue"
},
  "geometry": {"coordinates":[7.6401,51.971634],"type":"Point"}
}