{
  "type": "Feature",
  "properties": {
    "iso:country":"DE",
    "sg:address":"Beffendorfer Str. 19",
    "sg:city":"B\u00f6singen",
    "sg:phone":"+49 7404/412",
    "sg:postcode":"78662",
    "sg:province":"Baden-W\u00fcrttemberg",
    "wof:name":"Ratskeller",
    "wof:placetype":"venue"
},
  "geometry": {"coordinates":[8.5529956818,48.2398452759],"type":"Point"}
}