{
  "type": "Feature",
  "properties": {
    "iso:country":"DE",
    "sg:address":"Bahnhofstr. 5",
    "sg:city":"Schlitz",
    "sg:phone":"+49 6642/6851",
    "sg:postcode":"36110",
    "sg:province":"Hessen",
    "wof:name":"Pizzeria La Gondola",
    "wof:placetype":"venue"
},
  "geometry": {"coordinates":[9.5633888245,50.6744346619],"type":"Point"}
}