{
  "type": "Feature",
  "properties": {
    "iso:country":"DE",
    "sg:address":"Bautzener Allee 47",
    "sg:city":"Hoyerswerda",
    "sg:phone":"+49 3571/428732",
    "sg:postcode":"02977",
    "sg:province":"Sachsen",
    "wof:name":"Heinz Gr\u00f6ger",
    "wof:placetype":"venue"
},
  "geometry": {"coordinates":[14.2801609039,51.4207992554],"type":"Point"}
}