{
  "type": "Feature",
  "properties": {
    "iso:country":"DE",
    "sg:address":"Rheinstr. 10",
    "sg:city":"Pfungstadt",
    "sg:phone":"+49 6157/85225",
    "sg:postcode":"64319",
    "sg:province":"Hessen",
    "wof:name":"Restaurant Pizzeria Le Petit",
    "wof:placetype":"venue"
},
  "geometry": {"coordinates":[8.5953378677,49.8023109436],"type":"Point"}
}