{
  "type": "Feature",
  "properties": {
    "iso:country":"DE",
    "sg:address":"Neue Lustgartenstr. 1",
    "sg:city":"Erbach",
    "sg:phone":"+49 6062/3420",
    "sg:postcode":"64711",
    "sg:province":"Hessen",
    "wof:name":"Philipp Schmidt",
    "wof:placetype":"venue"
},
  "geometry": {"coordinates":[8.9936389923,49.6555709839],"type":"Point"}
}