{
  "type": "Feature",
  "properties": {
    "iso:country":"DE",
    "sg:address":"Domstr. 5",
    "sg:city":"W\u00fcrzburg",
    "sg:phone":"+49 931/30950",
    "sg:postcode":"97070",
    "sg:province":"Bayern",
    "wof:name":"Duttenhofer Verwaltungs Gmbh",
    "wof:placetype":"venue"
},
  "geometry": {"coordinates":[9.9291915894,49.7932395935],"type":"Point"}
}