{
  "type": "Feature",
  "properties": {
    "iso:country":"DE",
    "sg:address":"Am Sportplatz 3",
    "sg:city":"Vestenbergsgreuth",
    "sg:phone":"+49 9163/7170",
    "sg:postcode":"91487",
    "sg:province":"Bayern",
    "wof:name":"Greuther Stuben",
    "wof:placetype":"venue"
},
  "geometry": {"coordinates":[10.6545124054,49.6910972595],"type":"Point"}
}