{
  "type": "Feature",
  "properties": {
    "iso:country":"DE",
    "sg:address":"Krankenhausstr. 3",
    "sg:city":"Neu-Ulm",
    "sg:phone":"+49 731/88122",
    "sg:postcode":"89231",
    "sg:province":"Bayern",
    "wof:name":"Lebkuchen Weiss Gmbh",
    "wof:placetype":"venue"
},
  "geometry": {"coordinates":[9.996321,48.393997],"type":"Point"}
}