{
  "type": "Feature",
  "properties": {
    "iso:country":"DE",
    "sg:address":"Udldinger Str. 5",
    "sg:city":"Dachau",
    "sg:postcode":"85221",
    "sg:province":"Bayern",
    "wof:name":"Staufia Gmbh",
    "wof:placetype":"venue"
},
  "geometry": {"coordinates":[11.429814,48.258038],"type":"Point"}
}