{
  "type": "Feature",
  "properties": {
    "iso:country":"DE",
    "sg:address":"Ravensberger Str. 15",
    "sg:city":"Sassenberg",
    "sg:postcode":"48336",
    "sg:province":"Nordrhein-Westfalen",
    "wof:name":"R\u00fcgenwalder Wurstfabrik Fr\u00fcher Busch & Mertens",
    "wof:placetype":"venue"
},
  "geometry": {"coordinates":[8.0464305878,52.0478401184],"type":"Point"}
}