{
  "type": "Feature",
  "properties": {
    "iso:country":"DE",
    "sg:address":"Uwestr. 19",
    "sg:city":"Espelkamp",
    "sg:phone":"+49 5743/8392",
    "sg:postcode":"32339",
    "sg:province":"Nordrhein-Westfalen",
    "wof:name":"Angelika Vieker",
    "wof:placetype":"venue"
},
  "geometry": {"coordinates":[8.5753040314,52.3530693054],"type":"Point"}
}