{
  "type": "Feature",
  "properties": {
    "iso:country":"DE",
    "sg:address":"Rathausstr. 45",
    "sg:city":"Rietberg",
    "sg:phone":"+49 5244/7683",
    "sg:postcode":"33397",
    "sg:province":"Nordrhein-Westfalen",
    "wof:name":"Johannes Blomberg",
    "wof:placetype":"venue"
},
  "geometry": {"coordinates":[8.4266433716,51.8072624207],"type":"Point"}
}