{
  "type": "Feature",
  "properties": {
    "iso:country":"DE",
    "sg:address":"Lessingstr. 17",
    "sg:city":"Witten",
    "sg:phone":"+49 2302/275755",
    "sg:postcode":"58452",
    "sg:province":"Nordrhein-Westfalen",
    "wof:name":"Msc Media Support & Consulting Gmbh",
    "wof:placetype":"venue"
},
  "geometry": {"coordinates":[7.333105,51.434357],"type":"Point"}
}