{
  "type": "Feature",
  "properties": {
    "iso:country":"DE",
    "sg:address":"Bentheimer Str. 9",
    "sg:city":"Isterberg",
    "sg:phone":"+49 5926/204",
    "sg:postcode":"48465",
    "sg:province":"Niedersachsen",
    "wof:name":"Adolf Hanselle",
    "wof:placetype":"venue"
},
  "geometry": {"coordinates":[7.147983,52.341656],"type":"Point"}
}