{
  "type": "Feature",
  "properties": {
    "iso:country":"DE",
    "sg:address":"Friedhofweg 3",
    "sg:city":"Ebersbach-Musbach",
    "sg:phone":"+49 7584/3432",
    "sg:postcode":"88371",
    "sg:province":"Baden-W\u00fcrttemberg",
    "wof:name":"Ralph Greinacher",
    "wof:placetype":"venue"
},
  "geometry": {"coordinates":[9.576857,47.954624],"type":"Point"}
}