{
  "type": "Feature",
  "properties": {
    "iso:country":"DE",
    "sg:address":"Lindenstr. 35",
    "sg:city":"Meschede",
    "sg:phone":"+49 291/7646",
    "sg:postcode":"59872",
    "sg:province":"Nordrhein-Westfalen",
    "wof:name":"Elisabeth Schnier",
    "wof:placetype":"venue"
},
  "geometry": {"coordinates":[8.290845871,51.3602981567],"type":"Point"}
}