{
  "type": "Feature",
  "properties": {
    "iso:country":"DE",
    "sg:address":"Josef-Schmid-Weg 13",
    "sg:city":"Memmingen",
    "sg:phone":"+49 8331/64655",
    "sg:postcode":"87700",
    "sg:province":"Bayern",
    "wof:name":"Robin Keckeisen Handels-gmbh",
    "wof:placetype":"venue"
},
  "geometry": {"coordinates":[10.1754817963,47.9832000732],"type":"Point"}
}