{
  "type": "Feature",
  "properties": {
    "iso:country":"DE",
    "sg:address":"In der Langgewann 54",
    "sg:city":"B\u00fcdingen",
    "sg:phone":"+49 6042/2281",
    "sg:postcode":"63654",
    "sg:province":"Hessen",
    "wof:name":"R\u00fcdiger Henning Architekt",
    "wof:placetype":"venue"
},
  "geometry": {"coordinates":[9.119133,50.284679],"type":"Point"}
}