{
  "type": "Feature",
  "properties": {
    "iso:country":"DE",
    "sg:address":"Turnierstr. 9 D",
    "sg:city":"Ingelheim",
    "sg:phone":"+49 6132/41101",
    "sg:postcode":"55218",
    "sg:province":"Rheinland-Pfalz",
    "wof:name":"Beate Zimma Praxis F Ergotherapie",
    "wof:placetype":"venue"
},
  "geometry": {"coordinates":[8.067976,49.980835],"type":"Point"}
}