{
  "type": "Feature",
  "properties": {
    "iso:country":"DE",
    "sg:address":"Lange Str. 27",
    "sg:city":"Berne",
    "sg:phone":"+49 4406/6150",
    "sg:postcode":"27804",
    "sg:province":"Niedersachsen",
    "wof:name":"G. B\u00fcsing",
    "wof:placetype":"venue"
},
  "geometry": {"coordinates":[8.479041,53.184132],"type":"Point"}
}