{
  "type": "Feature",
  "properties": {
    "iso:country":"DE",
    "sg:address":"K\u00f6lner Str. 71-78",
    "sg:city":"Erkelenz",
    "sg:phone":"+49 2431/830",
    "sg:postcode":"41812",
    "sg:province":"Nordrhein-Westfalen",
    "wof:name":"Wirth Maschinen- Und Bohrger\u00e4te - Fabrik Gmbh",
    "wof:placetype":"venue"
},
  "geometry": {"coordinates":[6.3223791122,51.0741386414],"type":"Point"}
}