{
  "type": "Feature",
  "properties": {
    "iso:country":"DE",
    "sg:address":"Laurentiusstr. 4",
    "sg:city":"Porta Westfalica",
    "sg:phone":"+49 571/77633",
    "sg:postcode":"32457",
    "sg:province":"Nordrhein-Westfalen",
    "wof:name":"Wieland",
    "wof:placetype":"venue"
},
  "geometry": {"coordinates":[8.9878921509,52.2479934692],"type":"Point"}
}