{
  "type": "Feature",
  "properties": {
    "iso:country":"DE",
    "sg:address":"Gartenstr. 28",
    "sg:city":"Dresden",
    "sg:phone":"+49 351/8382086",
    "sg:postcode":"01259",
    "sg:province":"Sachsen",
    "wof:name":"Cce Systeme Gmbh",
    "wof:placetype":"venue"
},
  "geometry": {"coordinates":[13.8683099747,50.991230011],"type":"Point"}
}