{
  "type": "Feature",
  "properties": {
    "iso:country":"DE",
    "sg:address":"Bergische Str. 23",
    "sg:city":"Engelskirchen",
    "sg:phone":"+49 2263/20480",
    "sg:postcode":"51766",
    "sg:province":"Nordrhein-Westfalen",
    "wof:name":"Heinz B\u00fcscher Steuerberater",
    "wof:placetype":"venue"
},
  "geometry": {"coordinates":[7.4053621292,50.9884796143],"type":"Point"}
}