{
  "type": "Feature",
  "properties": {
    "iso:country":"DE",
    "sg:address":"Brunnenstr. 12 a",
    "sg:city":"Schkortleben",
    "sg:phone":"+49 34446/20536",
    "sg:postcode":"06688",
    "sg:province":"Sachsen-Anhalt",
    "wof:name":"Uta Piller",
    "wof:placetype":"venue"
},
  "geometry": {"coordinates":[12.01269,51.235653],"type":"Point"}
}