{
  "type": "Feature",
  "properties": {
    "iso:country":"DE",
    "sg:address":"Hauptstr. 28",
    "sg:city":"Wielenbach",
    "sg:phone":"+49 8158/7500",
    "sg:postcode":"82407",
    "sg:province":"Bayern",
    "wof:name":"Georg Schmid",
    "wof:placetype":"venue"
},
  "geometry": {"coordinates":[11.221739,47.872581],"type":"Point"}
}