{
  "type": "Feature",
  "properties": {
    "iso:country":"DE",
    "sg:address":"Gutenbergstr. 35",
    "sg:city":"Bad Langensalza",
    "sg:phone":"+49 3603/814700",
    "sg:postcode":"99947",
    "sg:province":"Th\u00fcringen",
    "wof:name":"Senioren-wohnpark Bad Langensalza Gmbh",
    "wof:placetype":"venue"
},
  "geometry": {"coordinates":[10.649873,51.101383],"type":"Point"}
}