{
  "type": "Feature",
  "properties": {
    "iso:country":"DE",
    "sg:address":"Hans-Henny-Jahnn-Weg 8",
    "sg:city":"Hamburg",
    "sg:phone":"+49 40/2207711",
    "sg:postcode":"22085",
    "sg:province":"Hamburg",
    "wof:name":"A. C. I. Inge Schmidt",
    "wof:placetype":"venue"
},
  "geometry": {"coordinates":[10.014337,53.579315],"type":"Point"}
}