{
  "type": "Feature",
  "properties": {
    "iso:country":"DE",
    "sg:address":"Am Buchrain 3 b",
    "sg:city":"R\u00f6dermark",
    "sg:postcode":"63322",
    "sg:province":"Hessen",
    "wof:name":"Ildex Handelsges. Mbh",
    "wof:placetype":"venue"
},
  "geometry": {"coordinates":[8.819856,49.998013],"type":"Point"}
}