{
  "type": "Feature",
  "properties": {
    "iso:country":"DE",
    "sg:address":"M\u00fcnsterkamp 18",
    "sg:city":"Emsdetten",
    "sg:postcode":"48282",
    "sg:province":"Nordrhein-Westfalen",
    "wof:name":"Raumplan Emsdetten Gmbh",
    "wof:placetype":"venue"
},
  "geometry": {"coordinates":[7.5358729362,52.1702766418],"type":"Point"}
}