{
  "type": "Feature",
  "properties": {
    "iso:country":"DE",
    "sg:address":"Kemnastr. 10",
    "sg:city":"Bochum",
    "sg:phone":"+49 2327/33696",
    "sg:postcode":"44866",
    "sg:province":"Nordrhein-Westfalen",
    "wof:name":"Katholisches Pfarramt St. Johannes",
    "wof:placetype":"venue"
},
  "geometry": {"coordinates":[7.1088318825,51.4787712097],"type":"Point"}
}