{
  "type": "Feature",
  "properties": {
    "iso:country":"DE",
    "sg:address":"Hauptstr. 125",
    "sg:city":"Oberursel",
    "sg:phone":"+49 6172/35953",
    "sg:postcode":"61440",
    "sg:province":"Hessen",
    "wof:name":"Hardt Media Gmbh",
    "wof:placetype":"venue"
},
  "geometry": {"coordinates":[8.5622549057,50.2265663147],"type":"Point"}
}