{
  "type": "Feature",
  "properties": {
    "iso:country":"DE",
    "sg:address":"Am Hof 1",
    "sg:city":"N\u00f6rvenich",
    "sg:phone":"+49 2421/72853",
    "sg:postcode":"52388",
    "sg:province":"Nordrhein-Westfalen",
    "wof:name":"Georg Olligs",
    "wof:placetype":"venue"
},
  "geometry": {"coordinates":[6.541082,50.795918],"type":"Point"}
}