{
  "type": "Feature",
  "properties": {
    "iso:country":"DE",
    "sg:address":"Peter-Sander-Str 13",
    "sg:city":"Mainz-Kastel",
    "sg:phone":"+49 6134/5670",
    "sg:postcode":"55252",
    "sg:province":"Hessen",
    "wof:name":"Dexxon Data Media And Storage Gmbh",
    "wof:placetype":"venue"
},
  "geometry": {"coordinates":[8.27508,50.026443],"type":"Point"}
}