{
  "type": "Feature",
  "properties": {
    "iso:country":"DE",
    "sg:address":"Postfach 1351:: 34419 Marsberg:: Germany.^^Hauptstr 28::",
    "sg:city":"Marsberg",
    "sg:phone":"+49 2992/9800",
    "sg:postcode":"34431",
    "sg:province":"Nordrhein-Westfalen",
    "wof:name":"Stadtsparkasse Marsberg",
    "wof:placetype":"venue"
},
  "geometry": {"coordinates":[8.85769,51.458408],"type":"Point"}
}