{
  "type": "Feature",
  "properties": {
    "iso:country":"DE",
    "sg:address":"Sch\u00f6nm\u00fcnzstr. 46",
    "sg:city":"Baiersbronn",
    "sg:phone":"+49 7447/692",
    "sg:postcode":"72270",
    "sg:province":"Baden-W\u00fcrttemberg",
    "wof:name":"Martin Batsch Pension",
    "wof:placetype":"venue"
},
  "geometry": {"coordinates":[8.3599510193,48.605884552],"type":"Point"}
}