{
  "type": "Feature",
  "properties": {
    "iso:country":"DE",
    "sg:address":"Erlenbachtalstr. 9",
    "sg:city":"Igersheim",
    "sg:phone":"+49 7931/45071",
    "sg:postcode":"97999",
    "sg:province":"Baden-W\u00fcrttemberg",
    "wof:name":"Mehrzweckhalle",
    "wof:placetype":"venue"
},
  "geometry": {"coordinates":[9.808002,49.495716],"type":"Point"}
}