{
  "type": "Feature",
  "properties": {
    "iso:country":"DE",
    "sg:address":"Talstr. 52",
    "sg:city":"Schriesheim",
    "sg:phone":"+49 6203/6020",
    "sg:postcode":"69198",
    "sg:province":"Baden-W\u00fcrttemberg",
    "wof:name":"Museum Theo Kerg",
    "wof:placetype":"venue"
},
  "geometry": {"coordinates":[8.665281,49.476391],"type":"Point"}
}