{
  "type": "Feature",
  "properties": {
    "iso:country":"DE",
    "sg:address":"Enzenbachstr.",
    "sg:city":"Nalbach",
    "sg:phone":"+49 6838/82149",
    "sg:postcode":"66809",
    "sg:province":"Saarland",
    "wof:name":"Sus Bilsdorf E. V. Fu\u00dfballverein",
    "wof:placetype":"venue"
},
  "geometry": {"coordinates":[6.8133649826,49.3821907043],"type":"Point"}
}