{
  "type": "Feature",
  "properties": {
    "iso:country":"DE",
    "sg:address":"Neue Reichenbacher Str 15",
    "sg:city":"Neumark",
    "sg:phone":"+49 37600/9460",
    "sg:postcode":"08496",
    "sg:province":"Sachsen",
    "wof:name":"R\u00f6ckelein Gmbh",
    "wof:placetype":"venue"
},
  "geometry": {"coordinates":[12.326372,50.666737],"type":"Point"}
}