{
  "type": "Feature",
  "properties": {
    "iso:country":"DE",
    "sg:address":"Rheinstr. 10",
    "sg:city":"Bingen",
    "sg:phone":"+49 6721/14683",
    "sg:postcode":"55411",
    "sg:province":"Rheinland-Pfalz",
    "wof:name":"Joachim Lindner",
    "wof:placetype":"venue"
},
  "geometry": {"coordinates":[7.8941469193,49.9685440063],"type":"Point"}
}