{
  "type": "Feature",
  "properties": {
    "iso:country":"DE",
    "sg:address":"Hauptstr. 26",
    "sg:city":"Rheine",
    "sg:phone":"+49 5971/3837",
    "sg:postcode":"48432",
    "sg:province":"Nordrhein-Westfalen",
    "wof:name":"Clemens Bergers",
    "wof:placetype":"venue"
},
  "geometry": {"coordinates":[7.4540901184,52.2390899658],"type":"Point"}
}