{
  "type": "Feature",
  "properties": {
    "iso:country":"DE",
    "sg:address":"Albstr. 24",
    "sg:city":"Kornwestheim",
    "sg:phone":"+49 4971/543179",
    "sg:postcode":"70806",
    "sg:province":"Baden-W\u00fcrttemberg",
    "wof:name":"G\u00dcrr-betten Gmbh",
    "wof:placetype":"venue"
},
  "geometry": {"coordinates":[9.1887979507,48.8517417908],"type":"Point"}
}