{
  "type": "Feature",
  "properties": {
    "iso:country":"DE",
    "sg:address":"Cappelstr. 25",
    "sg:city":"Lippstadt",
    "sg:phone":"+49 2941/97490",
    "sg:postcode":"59555",
    "sg:province":"Nordrhein-Westfalen",
    "wof:name":"Gerd Pickshaus-trunschke Ergotherapeutsche Praxis",
    "wof:placetype":"venue"
},
  "geometry": {"coordinates":[8.343188,51.674774],"type":"Point"}
}