{
  "type": "Feature",
  "properties": {
    "iso:country":"DE",
    "sg:address":"Radensdorfer Weg 10",
    "sg:city":"Gollmitz",
    "sg:phone":"+49 35435/223",
    "sg:postcode":"03205",
    "sg:province":"Brandenburg",
    "wof:name":"Gasthaus Krone",
    "wof:placetype":"venue"
},
  "geometry": {"coordinates":[13.9258871078,51.7286262512],"type":"Point"}
}