{
  "type": "Feature",
  "properties": {
    "iso:country":"DE",
    "sg:address":"Dannenberger Str. 12",
    "sg:city":"Dahlenburg",
    "sg:phone":"+49 5851/602095",
    "sg:postcode":"21368",
    "sg:province":"Niedersachsen",
    "wof:name":"Chinarestaurant Nam Vien",
    "wof:placetype":"venue"
},
  "geometry": {"coordinates":[10.7434778214,53.1865577698],"type":"Point"}
}