{
  "type": "Feature",
  "properties": {
    "iso:country":"DE",
    "sg:address":"R\u00f6merstr. 48",
    "sg:city":"Bad Ems",
    "sg:phone":"+49 2603/2354",
    "sg:postcode":"56130",
    "sg:province":"Rheinland-Pfalz",
    "wof:name":"Art De Fleurs Inh. Hans Stielow E. K.",
    "wof:placetype":"venue"
},
  "geometry": {"coordinates":[7.718348,50.332897],"type":"Point"}
}