{
  "type": "Feature",
  "properties": {
    "iso:country":"DE",
    "sg:address":"Greversweg 34",
    "sg:city":"Goch",
    "sg:phone":"+49 2823/97070",
    "sg:postcode":"47574",
    "sg:province":"Nordrhein-Westfalen",
    "wof:name":"Bruno V\u00f6lling Architekt",
    "wof:placetype":"venue"
},
  "geometry": {"coordinates":[6.150748,51.670498],"type":"Point"}
}