{
  "type": "Feature",
  "properties": {
    "iso:country":"DE",
    "sg:address":"Seckenheimer Str. 136-138",
    "sg:city":"Mannheim",
    "sg:phone":"+49 621/408346",
    "sg:postcode":"68165",
    "sg:province":"Baden-W\u00fcrttemberg",
    "wof:name":"Free Com Die Telekommunikat.-ges.",
    "wof:placetype":"venue"
},
  "geometry": {"coordinates":[8.487241,49.476269],"type":"Point"}
}