{
  "type": "Feature",
  "properties": {
    "iso:country":"DE",
    "sg:address":"Nicolaistr. 2",
    "sg:city":"Gera",
    "sg:postcode":"07545",
    "sg:province":"Th\u00fcringen",
    "wof:name":"Ev.-luth. Kirche Salvator I",
    "wof:placetype":"venue"
},
  "geometry": {"coordinates":[12.0866622925,50.8766479492],"type":"Point"}
}