{
  "type": "Feature",
  "properties": {
    "iso:country":"DE",
    "sg:address":"Friedrich-Ebert-Str. 98a",
    "sg:city":"Oppenheim",
    "sg:phone":"+49 6133/3144",
    "sg:postcode":"55276",
    "sg:province":"Rheinland-Pfalz",
    "wof:name":"Heinz Gutmann",
    "wof:placetype":"venue"
},
  "geometry": {"coordinates":[8.3573579788,49.850605011],"type":"Point"}
}