{
  "type": "Feature",
  "properties": {
    "iso:country":"DE",
    "sg:address":"Am Oberberg 11",
    "sg:city":"Kronberg",
    "sg:phone":"+49 6173/322194",
    "sg:postcode":"61476",
    "sg:province":"Hessen",
    "wof:name":"Von Goetz & Schwanenflie\u00df Gmbh & Co.kfz.-waschanlagen Kg",
    "wof:placetype":"venue"
},
  "geometry": {"coordinates":[8.523035,50.187595],"type":"Point"}
}