{
  "type": "Feature",
  "properties": {
    "iso:country":"DE",
    "sg:address":"Brandenburger Str. 8",
    "sg:city":"Rethem",
    "sg:phone":"+49 5165/91005",
    "sg:postcode":"27336",
    "sg:province":"Niedersachsen",
    "wof:name":"G. \u00dcltzen",
    "wof:placetype":"venue"
},
  "geometry": {"coordinates":[9.370465,52.78772],"type":"Point"}
}