{
  "type": "Feature",
  "properties": {
    "iso:country":"DE",
    "sg:address":"Am Galgenberg 5",
    "sg:city":"Harsleben",
    "sg:phone":"+49 3941/444151",
    "sg:postcode":"38829",
    "sg:province":"Sachsen-Anhalt",
    "wof:name":"Star Body Fitness Club Gmbh",
    "wof:placetype":"venue"
},
  "geometry": {"coordinates":[11.0808897018,51.8797798157],"type":"Point"}
}