{
  "type": "Feature",
  "properties": {
    "iso:country":"DE",
    "sg:address":"Sch\u00f6llstr. 2",
    "sg:city":"M\u00fcnchen",
    "sg:postcode":"80999",
    "sg:province":"Bayern",
    "wof:name":"Top Trucks Gmbh",
    "wof:placetype":"venue"
},
  "geometry": {"coordinates":[11.4612197876,48.1975593567],"type":"Point"}
}