{
  "type": "Feature",
  "properties": {
    "iso:country":"DE",
    "sg:address":"Osterholzstr. 126",
    "sg:city":"Kassel",
    "sg:phone":"+49 561/527267",
    "sg:postcode":"34123",
    "sg:province":"Hessen",
    "wof:name":"Udo Jakob",
    "wof:placetype":"venue"
},
  "geometry": {"coordinates":[9.5416269302,51.309425354],"type":"Point"}
}