{
  "type": "Feature",
  "properties": {
    "iso:country":"DE",
    "sg:address":"Gustav-Hertz-Str. 31",
    "sg:city":"Kamen",
    "sg:postcode":"59174",
    "sg:province":"Nordrhein-Westfalen",
    "wof:name":"L-e-d Gmbh",
    "wof:placetype":"venue"
},
  "geometry": {"coordinates":[7.605336,51.574158],"type":"Point"}
}