{
  "type": "Feature",
  "properties": {
    "iso:country":"DE",
    "sg:address":"Radeberger Str.",
    "sg:city":"Kleinwolmsdorf",
    "sg:phone":"+49 35200/23146",
    "sg:postcode":"01477",
    "sg:province":"Sachsen",
    "wof:name":"Sport Inn-fitness- Und Freizeitpark Arnsdorf Gmbh",
    "wof:placetype":"venue"
},
  "geometry": {"coordinates":[13.9469499588,51.0961494446],"type":"Point"}
}