{
  "type": "Feature",
  "properties": {
    "iso:country":"DE",
    "sg:address":"Am Holm",
    "sg:city":"K\u00fchlungsborn",
    "sg:phone":"+49 38293/6209",
    "sg:postcode":"18225",
    "sg:province":"Mecklenburg-Vorpommern",
    "wof:name":"Balkangrill",
    "wof:placetype":"venue"
},
  "geometry": {"coordinates":[11.744685173,54.1248588562],"type":"Point"}
}