{
  "type": "Feature",
  "properties": {
    "iso:country":"DE",
    "sg:address":"Jungenstr. 18",
    "sg:city":"M\u00fclheim-K\u00e4rlich",
    "sg:phone":"+49 261/25050",
    "sg:postcode":"56218",
    "sg:province":"Rheinland-Pfalz",
    "wof:name":"Walther Gmbh",
    "wof:placetype":"venue"
},
  "geometry": {"coordinates":[7.5378098488,50.3912315369],"type":"Point"}
}