{
  "type": "Feature",
  "properties": {
    "iso:country":"DE",
    "sg:address":"Am Kreuzplatz 2",
    "sg:city":"Ankum",
    "sg:phone":"+49 5462/477",
    "sg:postcode":"49577",
    "sg:province":"Niedersachsen",
    "wof:name":"H & M Aluminium Gmbh",
    "wof:placetype":"venue"
},
  "geometry": {"coordinates":[7.8731021881,52.5561256409],"type":"Point"}
}