{
  "type": "Feature",
  "properties": {
    "iso:country":"DE",
    "sg:address":"Schmuggelstieg 3",
    "sg:city":"Norderstedt",
    "sg:phone":"+49 40/5296951",
    "sg:postcode":"22848",
    "sg:province":"Schleswig-Holstein",
    "wof:name":"H. Rohlff",
    "wof:placetype":"venue"
},
  "geometry": {"coordinates":[9.999071,53.682259],"type":"Point"}
}