{
  "type": "Feature",
  "properties": {
    "iso:country":"DE",
    "sg:address":"Bierbrauerweg 39",
    "sg:city":"Offenbach",
    "sg:phone":"+49 69/851718",
    "sg:postcode":"63071",
    "sg:province":"Hessen",
    "wof:name":"Milenkovic & Terek Ohg Armaturenfabrikation",
    "wof:placetype":"venue"
},
  "geometry": {"coordinates":[8.793794,50.099781],"type":"Point"}
}