{
  "type": "Feature",
  "properties": {
    "iso:country":"DE",
    "sg:address":"Emil-Kemmer-Str. 21",
    "sg:city":"Hallstadt",
    "sg:postcode":"96103",
    "sg:province":"Bayern",
    "wof:name":"Dewitz Gmbh & Co. Kg",
    "wof:placetype":"venue"
},
  "geometry": {"coordinates":[10.8734998703,49.9177894592],"type":"Point"}
}