{
  "type": "Feature",
  "properties": {
    "iso:country":"DE",
    "sg:address":"Postfach",
    "sg:city":"G\u00fcstrow",
    "sg:postcode":"18261",
    "sg:province":"Mecklenburg-Vorpommern",
    "wof:name":"Miw Motorenwerke Gmbh",
    "wof:placetype":"venue"
},
  "geometry": {"coordinates":[12.1729898453,53.796749115],"type":"Point"}
}