{
  "type": "Feature",
  "properties": {
    "iso:country":"DE",
    "sg:address":"Becheltestr. 30",
    "sg:city":"Hagen",
    "sg:phone":"+49 2331/303025",
    "sg:postcode":"58089",
    "sg:province":"Nordrhein-Westfalen",
    "wof:name":"Naturana Zoohandel Gmbh",
    "wof:placetype":"venue"
},
  "geometry": {"coordinates":[7.449341,51.382687],"type":"Point"}
}