{
  "type": "Feature",
  "properties": {
    "iso:country":"DE",
    "sg:address":"Iserstr 6",
    "sg:city":"Trappenkamp",
    "sg:phone":"+49 4323/91770",
    "sg:postcode":"24610",
    "sg:province":"Schleswig-Holstein",
    "wof:name":"Me Grisard Gmbh",
    "wof:placetype":"venue"
},
  "geometry": {"coordinates":[10.2203302383,54.0372085571],"type":"Point"}
}