{
  "type": "Feature",
  "properties": {
    "iso:country":"DE",
    "sg:address":"Schlo\u00dfstr. 30",
    "sg:city":"Osnabr\u00fcck",
    "sg:phone":"+49 541/330170",
    "sg:postcode":"49074",
    "sg:province":"Niedersachsen",
    "wof:name":"Hamburg Mannheimer Versicherungs Ag",
    "wof:placetype":"venue"
},
  "geometry": {"coordinates":[8.0445785522,52.2688217163],"type":"Point"}
}