{
  "type": "Feature",
  "properties": {
    "iso:country":"DE",
    "sg:address":"Hauptstr. 11",
    "sg:city":"K\u00e4ndler",
    "sg:phone":"+49 3722/95516",
    "sg:postcode":"09247",
    "sg:province":"Sachsen",
    "wof:name":"Egon Rebentisch",
    "wof:placetype":"venue"
},
  "geometry": {"coordinates":[12.7904558182,50.8542442322],"type":"Point"}
}