{
  "type": "Feature",
  "properties": {
    "iso:country":"DE",
    "sg:address":"Staudenstr. 11",
    "sg:city":"Fischach",
    "sg:phone":"+49 8236/2055",
    "sg:postcode":"86850",
    "sg:province":"Bayern",
    "wof:name":"Ferienhaus Vermittlung Ungarn - Kuchenmeister",
    "wof:placetype":"venue"
},
  "geometry": {"coordinates":[10.6491718292,48.2680549622],"type":"Point"}
}