{
  "type": "Feature",
  "properties": {
    "iso:country":"DE",
    "sg:address":"Bramberger Weg 6",
    "sg:city":"Korbach",
    "sg:phone":"+49 5631/8833",
    "sg:postcode":"34497",
    "sg:province":"Hessen",
    "wof:name":"Heinrich Pohlmann",
    "wof:placetype":"venue"
},
  "geometry": {"coordinates":[8.873083,51.32457],"type":"Point"}
}