{
  "type": "Feature",
  "properties": {
    "iso:country":"DE",
    "sg:address":"Alpenrosenstr. 4",
    "sg:city":"Penzberg",
    "sg:phone":"+49 8856/5570",
    "sg:postcode":"82377",
    "sg:province":"Bayern",
    "wof:name":"Psf-international Marketing Und Handels Gmbh",
    "wof:placetype":"venue"
},
  "geometry": {"coordinates":[11.3555498123,47.761516571],"type":"Point"}
}