{
  "type": "Feature",
  "properties": {
    "iso:country":"DE",
    "sg:address":"Tomerdinger Str. 1",
    "sg:city":"Dornstadt",
    "sg:phone":"+49 7348/98900",
    "sg:postcode":"89160",
    "sg:province":"Baden-W\u00fcrttemberg",
    "wof:name":"Geno-immobilien Gmbh",
    "wof:placetype":"venue"
},
  "geometry": {"coordinates":[9.942068,48.466663],"type":"Point"}
}