{
  "type": "Feature",
  "properties": {
    "iso:country":"DE",
    "sg:address":"Mittermayerstr. 13",
    "sg:city":"Dachau",
    "sg:phone":"+49 8131/70000",
    "sg:postcode":"85221",
    "sg:province":"Bayern",
    "wof:name":"Amper-spedition Gmbh",
    "wof:placetype":"venue"
},
  "geometry": {"coordinates":[11.4334869385,48.2629776001],"type":"Point"}
}