{
  "type": "Feature",
  "properties": {
    "iso:country":"DE",
    "sg:address":"Peterstr. 4",
    "sg:city":"Bad Zwischenahn",
    "sg:phone":"+49 4403/4077",
    "sg:postcode":"26160",
    "sg:province":"Niedersachsen",
    "wof:name":"Ammerl\u00e4nder Puppenstube",
    "wof:placetype":"venue"
},
  "geometry": {"coordinates":[8.0048933029,53.1860961914],"type":"Point"}
}