{
  "type": "Feature",
  "properties": {
    "iso:country":"DE",
    "sg:address":"Nr. 34",
    "sg:city":"M\u00f6rsdorf",
    "sg:postcode":"07646",
    "sg:province":"Th\u00fcringen",
    "wof:name":"Ev.-luth. Kirche M\u00f6rsdorf",
    "wof:placetype":"venue"
},
  "geometry": {"coordinates":[11.7546796799,50.8473014832],"type":"Point"}
}