{
  "type": "Feature",
  "properties": {
    "iso:country":"DE",
    "sg:address":"Schiefe Str. 3",
    "sg:city":"Stade",
    "sg:phone":"+49 4141/2747",
    "sg:postcode":"21682",
    "sg:province":"Niedersachsen",
    "wof:name":"Die Br\u00fccke Stade E. V.",
    "wof:placetype":"venue"
},
  "geometry": {"coordinates":[9.4791622162,53.6001739502],"type":"Point"}
}