{
  "type": "Feature",
  "properties": {
    "iso:country":"DE",
    "sg:address":"Waldweg 12",
    "sg:city":"Viersen",
    "sg:phone":"+49 2153/3465",
    "sg:postcode":"41751",
    "sg:province":"Nordrhein-Westfalen",
    "wof:name":"Dewey Und Blohm-schr\u00f6der Architektenpartnerschaft",
    "wof:placetype":"venue"
},
  "geometry": {"coordinates":[6.267208,51.271996],"type":"Point"}
}