{
  "type": "Feature",
  "properties": {
    "iso:country":"DE",
    "sg:address":"Stadtplatz 6",
    "sg:city":"Kemnath",
    "sg:phone":"+49 9642/7556",
    "sg:postcode":"95478",
    "sg:province":"Bayern",
    "wof:name":"E. Schiener",
    "wof:placetype":"venue"
},
  "geometry": {"coordinates":[11.8874864578,49.8703193665],"type":"Point"}
}