{
  "type": "Feature",
  "properties": {
    "iso:country":"DE",
    "sg:address":"Gro\u00dfer Stellweg 18",
    "sg:city":"Viernheim",
    "sg:phone":"+49 6204/74158",
    "sg:postcode":"68519",
    "sg:province":"Hessen",
    "wof:name":"Anton Minich",
    "wof:placetype":"venue"
},
  "geometry": {"coordinates":[8.578829,49.548828],"type":"Point"}
}