{
  "type": "Feature",
  "properties": {
    "iso:country":"DE",
    "sg:address":"T\u00fcbinger Str. 28",
    "sg:city":"B\u00f6blingen",
    "sg:phone":"+49 7031/804991",
    "sg:postcode":"71032",
    "sg:province":"Baden-W\u00fcrttemberg",
    "wof:name":"Wilhelm Kopp-erben Verm\u00f6gensverwaltung Gmbh",
    "wof:placetype":"venue"
},
  "geometry": {"coordinates":[9.0103883743,48.6819458008],"type":"Point"}
}