{
  "type": "Feature",
  "properties": {
    "iso:country":"DE",
    "sg:address":"Pinnauallee 4",
    "sg:city":"Uetersen",
    "sg:postcode":"25436",
    "sg:province":"Schleswig-Holstein",
    "wof:name":"Nordmark Arzneimittel Gmbh & Co. Kg",
    "wof:placetype":"venue"
},
  "geometry": {"coordinates":[9.6770448685,53.6792411804],"type":"Point"}
}