{
  "type": "Feature",
  "properties": {
    "iso:country":"DE",
    "sg:address":"Ringstr. 127",
    "sg:city":"Koblenz",
    "sg:phone":"+49 261/6678031",
    "sg:postcode":"56077",
    "sg:province":"Rheinland-Pfalz",
    "wof:name":"Bonsai-garten",
    "wof:placetype":"venue"
},
  "geometry": {"coordinates":[7.662565,50.377068],"type":"Point"}
}