{
  "type": "Feature",
  "properties": {
    "iso:country":"DE",
    "sg:address":"Wredestr. 35",
    "sg:city":"N\u00fcrnberg",
    "sg:phone":"+49 911/613993",
    "sg:postcode":"90431",
    "sg:province":"Bayern",
    "wof:name":"Alfred Faul Steuerberater",
    "wof:placetype":"venue"
},
  "geometry": {"coordinates":[11.0294961929,49.4406929016],"type":"Point"}
}