{
  "type": "Feature",
  "properties": {
    "iso:country":"DE",
    "sg:address":"Gartenstr. 38",
    "sg:city":"Gaildorf",
    "sg:phone":"+49 7971/7799",
    "sg:postcode":"74405",
    "sg:province":"Baden-W\u00fcrttemberg",
    "wof:name":"Mini Mal Markt",
    "wof:placetype":"venue"
},
  "geometry": {"coordinates":[9.7701940536,48.9974899292],"type":"Point"}
}