{
  "type": "Feature",
  "properties": {
    "iso:country":"DE",
    "sg:address":"Jahnstr. 34",
    "sg:city":"Bielefeld",
    "sg:phone":"+49 521/40626",
    "sg:postcode":"33659",
    "sg:province":"Nordrhein-Westfalen",
    "wof:name":"Gerhard Epke",
    "wof:placetype":"venue"
},
  "geometry": {"coordinates":[8.52583,51.964207],"type":"Point"}
}