{
  "type": "Feature",
  "properties": {
    "iso:country":"DE",
    "sg:address":"Anna-Siemsen-Weg 6",
    "sg:city":"Hannover",
    "sg:phone":"+49 511/889156",
    "sg:postcode":"30173",
    "sg:province":"Niedersachsen",
    "wof:name":"G. Bohe",
    "wof:placetype":"venue"
},
  "geometry": {"coordinates":[9.766145,52.356506],"type":"Point"}
}