{
  "type": "Feature",
  "properties": {
    "iso:country":"DE",
    "sg:address":"Gartenstr. 2",
    "sg:city":"Wiesbaden",
    "sg:phone":"+49 611/540307",
    "sg:postcode":"65191",
    "sg:province":"Hessen",
    "wof:name":"Manfred Porschel",
    "wof:placetype":"venue"
},
  "geometry": {"coordinates":[8.266017,50.101028],"type":"Point"}
}