{
  "type": "Feature",
  "properties": {
    "iso:country":"DE",
    "sg:address":"Bonhoefferstr. 5",
    "sg:city":"Jena",
    "sg:phone":"+49 3641/361300",
    "sg:postcode":"07747",
    "sg:province":"Th\u00fcringen",
    "wof:name":"Beatrice Kr\u00fcger",
    "wof:placetype":"venue"
},
  "geometry": {"coordinates":[11.6119289398,50.8890686035],"type":"Point"}
}