{
  "type": "Feature",
  "properties": {
    "iso:country":"DE",
    "sg:address":"Burgstr. 21",
    "sg:city":"Siegen",
    "sg:phone":"+49 271/55315",
    "sg:postcode":"57072",
    "sg:province":"Nordrhein-Westfalen",
    "wof:name":"Kirchenkreis Siegen",
    "wof:placetype":"venue"
},
  "geometry": {"coordinates":[8.0286722183,50.8755187988],"type":"Point"}
}