{
  "type": "Feature",
  "properties": {
    "iso:country":"DE",
    "sg:address":"Hauptstr. 41",
    "sg:city":"Langenfeld",
    "sg:phone":"+49 2173/901345",
    "sg:postcode":"40764",
    "sg:province":"Nordrhein-Westfalen",
    "wof:name":"Kaisers Tengelmann Ag",
    "wof:placetype":"venue"
},
  "geometry": {"coordinates":[6.9475398064,51.1031913757],"type":"Point"}
}