{
  "type": "Feature",
  "properties": {
    "iso:country":"DE",
    "sg:address":"Siegfriedstr. 4",
    "sg:city":"Eich",
    "sg:phone":"+49 6246/6148",
    "sg:postcode":"67575",
    "sg:province":"Rheinland-Pfalz",
    "wof:name":"Burkhardt & Fischer Inh. W. Fischer",
    "wof:placetype":"venue"
},
  "geometry": {"coordinates":[8.4105386734,49.7515068054],"type":"Point"}
}