{
  "type": "Feature",
  "properties": {
    "iso:country":"DE",
    "sg:address":"Kuchenheimer Str. 115",
    "sg:city":"Euskirchen",
    "sg:postcode":"53881",
    "sg:province":"Nordrhein-Westfalen",
    "wof:name":"Hilde Grieger Verwaltungsgesellschaft Mbh",
    "wof:placetype":"venue"
},
  "geometry": {"coordinates":[6.8204498291,50.6534500122],"type":"Point"}
}