{
  "type": "Feature",
  "properties": {
    "iso:country":"DE",
    "sg:address":"Bilker Allee 209",
    "sg:city":"D\u00fcsseldorf",
    "sg:postcode":"40215",
    "sg:province":"Nordrhein-Westfalen",
    "wof:name":"Reiseb\u00fcro D\u00fcma Gmbh",
    "wof:placetype":"venue"
},
  "geometry": {"coordinates":[6.7795681953,51.2103919983],"type":"Point"}
}