{
  "type": "Feature",
  "properties": {
    "iso:country":"DE",
    "sg:address":"Zuckerbergstr. 5",
    "sg:city":"Trier",
    "sg:phone":"+49 651/41996",
    "sg:postcode":"54290",
    "sg:province":"Rheinland-Pfalz",
    "wof:name":"City Haarstudio Doris Fuchs",
    "wof:placetype":"venue"
},
  "geometry": {"coordinates":[6.6371622086,49.7564201355],"type":"Point"}
}