{
  "type": "Feature",
  "properties": {
    "iso:country":"DE",
    "sg:address":"Leiningerstr. 8",
    "sg:city":"Bad D\u00fcrkheim",
    "sg:phone":"+49 6322/65760",
    "sg:postcode":"67098",
    "sg:province":"Rheinland-Pfalz",
    "wof:name":"Metin Erciyas",
    "wof:placetype":"venue"
},
  "geometry": {"coordinates":[8.1675109863,49.4601631165],"type":"Point"}
}