{
  "type": "Feature",
  "properties": {
    "iso:country":"DE",
    "sg:address":"Zievericher M\u00fchle 6",
    "sg:city":"Bergheim",
    "sg:phone":"+49 2271/43143",
    "sg:postcode":"50126",
    "sg:province":"Nordrhein-Westfalen",
    "wof:name":"Angelpark",
    "wof:placetype":"venue"
},
  "geometry": {"coordinates":[6.6231431961,50.9562911987],"type":"Point"}
}