{
  "type": "Feature",
  "properties": {
    "iso:country":"DE",
    "sg:address":"Breite Str. 13",
    "sg:city":"Malchin",
    "sg:postcode":"17139",
    "sg:province":"Mecklenburg-Vorpommern",
    "wof:name":"Da Deutsche Allgemeine Versicherungs Ag",
    "wof:placetype":"venue"
},
  "geometry": {"coordinates":[12.7571496964,53.73985672],"type":"Point"}
}