{
  "type": "Feature",
  "properties": {
    "iso:country":"DE",
    "sg:address":"Stormstr. 15",
    "sg:city":"Herne",
    "sg:phone":"+49 2325/36792",
    "sg:postcode":"44651",
    "sg:province":"Nordrhein-Westfalen",
    "wof:name":"Frederike Bielefeld Rechtsanw\u00e4ltin",
    "wof:placetype":"venue"
},
  "geometry": {"coordinates":[7.1685290337,51.5160064697],"type":"Point"}
}