{
  "type": "Feature",
  "properties": {
    "iso:country":"DE",
    "sg:address":"Wacholderstr. 7",
    "sg:city":"D\u00fcsseldorf",
    "sg:phone":"+49 203/742407",
    "sg:postcode":"40489",
    "sg:province":"Nordrhein-Westfalen",
    "wof:name":"B. S. Gmbh",
    "wof:placetype":"venue"
},
  "geometry": {"coordinates":[6.7792768478,51.3237915039],"type":"Point"}
}