{
  "type": "Feature",
  "properties": {
    "iso:country":"DE",
    "sg:address":"Staude 4a",
    "sg:city":"Winden",
    "sg:phone":"+49 7682/7738",
    "sg:postcode":"79297",
    "sg:province":"Baden-W\u00fcrttemberg",
    "wof:name":"Wolfgang Weber",
    "wof:placetype":"venue"
},
  "geometry": {"coordinates":[8.057211,48.157677],"type":"Point"}
}