{
  "type": "Feature",
  "properties": {
    "iso:country":"DE",
    "sg:address":"Burg-Gr\u00e4fenr\u00f6der-Str. 2",
    "sg:city":"Karben",
    "sg:phone":"+49 6039/933403",
    "sg:postcode":"61184",
    "sg:province":"Hessen",
    "wof:name":"Peter Von Leonhardi",
    "wof:placetype":"venue"
},
  "geometry": {"coordinates":[8.77119,50.2379],"type":"Point"}
}