{
  "type": "Feature",
  "properties": {
    "iso:country":"DE",
    "sg:address":"Lindenstr.15",
    "sg:city":"Bernburg",
    "sg:phone":"+49 4934/7132840",
    "sg:postcode":"06406",
    "sg:province":"Sachsen-Anhalt",
    "wof:name":"Gea - Ges. F\u00dcr Elektrische Ausr\u00dcstungen Mbh",
    "wof:placetype":"venue"
},
  "geometry": {"coordinates":[11.744477,51.792522],"type":"Point"}
}