{
  "type": "Feature",
  "properties": {
    "iso:country":"DE",
    "sg:address":"Florastr. 51",
    "sg:city":"Rastatt",
    "sg:phone":"+49 7222/68140",
    "sg:postcode":"76437",
    "sg:province":"Baden-W\u00fcrttemberg",
    "wof:name":"K & T Vertrieb Baden Weine",
    "wof:placetype":"venue"
},
  "geometry": {"coordinates":[8.2016134262,48.8653297424],"type":"Point"}
}