{
  "type": "Feature",
  "properties": {
    "iso:country":"DE",
    "sg:address":"Am T\u00f6nisberg 3",
    "sg:city":"Erkrath",
    "sg:postcode":"40699",
    "sg:province":"Nordrhein-Westfalen",
    "wof:name":"Unissimo-poccino Vertriebs Gmbh",
    "wof:placetype":"venue"
},
  "geometry": {"coordinates":[6.9115757942,51.1960449219],"type":"Point"}
}