{
  "type": "Feature",
  "properties": {
    "iso:country":"DE",
    "sg:address":"Fallweg 46a",
    "sg:city":"Amberg",
    "sg:phone":"+49 9621/74544",
    "sg:postcode":"92224",
    "sg:province":"Bayern",
    "wof:name":"Paul Snajdar - Design-vertrieb",
    "wof:placetype":"venue"
},
  "geometry": {"coordinates":[11.8411302567,49.4349060059],"type":"Point"}
}