{
  "type": "Feature",
  "properties": {
    "iso:country":"DE",
    "sg:address":"Kalk-M\u00fclheimer Str. 137",
    "sg:city":"K\u00f6ln",
    "sg:postcode":"51103",
    "sg:province":"Nordrhein-Westfalen",
    "wof:name":"E Soft Gmbh",
    "wof:placetype":"venue"
},
  "geometry": {"coordinates":[7.001283,50.942169],"type":"Point"}
}