{
  "type": "Feature",
  "properties": {
    "iso:country":"DE",
    "sg:address":"Ihmerter Str. 310",
    "sg:city":"Hemer",
    "sg:phone":"+49 2372/8712",
    "sg:postcode":"58675",
    "sg:province":"Nordrhein-Westfalen",
    "wof:name":"T\u00fctebelle",
    "wof:placetype":"venue"
},
  "geometry": {"coordinates":[7.735681057,51.3245773315],"type":"Point"}
}