{
  "type": "Feature",
  "properties": {
    "iso:country":"DE",
    "sg:address":"Beim Stausee 2",
    "sg:city":"Sch\u00f6mberg",
    "sg:phone":"+49 7427/91111",
    "sg:postcode":"72355",
    "sg:province":"Baden-W\u00fcrttemberg",
    "wof:name":"Camping Am Stausee",
    "wof:placetype":"venue"
},
  "geometry": {"coordinates":[8.770512,48.211044],"type":"Point"}
}