{
  "type": "Feature",
  "properties": {
    "iso:country":"DE",
    "sg:address":"Meisenstr. 48",
    "sg:city":"Lemberg",
    "sg:phone":"+49 6331/40670",
    "sg:postcode":"66969",
    "sg:province":"Rheinland-Pfalz",
    "wof:name":"H.-w. Halasz",
    "wof:placetype":"venue"
},
  "geometry": {"coordinates":[7.6455712318,49.1715621948],"type":"Point"}
}