{
  "type": "Feature",
  "properties": {
    "iso:country":"DE",
    "sg:address":"Schonnebeckh\u00f6fe 60",
    "sg:city":"Essen",
    "sg:phone":"+49 201/211409",
    "sg:postcode":"45309",
    "sg:province":"Nordrhein-Westfalen",
    "wof:name":"Hallenbad Stadtbad Nord-ost",
    "wof:placetype":"venue"
},
  "geometry": {"coordinates":[7.0548200607,51.4854736328],"type":"Point"}
}