{
  "type": "Feature",
  "properties": {
    "iso:country":"DE",
    "sg:address":"Rosenstrasse 24",
    "sg:city":"Stuttgart",
    "sg:phone":"+49 711/25925914",
    "sg:postcode":"70119",
    "sg:province":"Baden-W\u00fcrttemberg",
    "wof:name":"B.c. Business - Communication",
    "wof:placetype":"venue"
},
  "geometry": {"coordinates":[9.183048,48.774536],"type":"Point"}
}