{
  "type": "Feature",
  "properties": {
    "iso:country":"DE",
    "sg:address":"Hausinger Str. 8",
    "sg:city":"Langenfeld",
    "sg:postcode":"40764",
    "sg:province":"Nordrhein-Westfalen",
    "wof:name":"No Limits-systems Gmbh",
    "wof:placetype":"venue"
},
  "geometry": {"coordinates":[6.9495949745,51.0941543579],"type":"Point"}
}