{
  "type": "Feature",
  "properties": {
    "iso:country":"DE",
    "sg:address":"Lange Str. 13",
    "sg:city":"Riesa",
    "sg:phone":"+49 3525/740293",
    "sg:postcode":"01587",
    "sg:province":"Sachsen",
    "wof:name":"Sachsenst\u00fcbchen",
    "wof:placetype":"venue"
},
  "geometry": {"coordinates":[13.2772502899,51.3052368164],"type":"Point"}
}