{
  "type": "Feature",
  "properties": {
    "iso:country":"DE",
    "sg:address":"Poststr. 19",
    "sg:city":"Altensteig",
    "sg:phone":"+49 7453/1258",
    "sg:postcode":"72213",
    "sg:province":"Baden-W\u00fcrttemberg",
    "wof:name":"I. Hauenstein",
    "wof:placetype":"venue"
},
  "geometry": {"coordinates":[8.602693,48.5839],"type":"Point"}
}