{
  "type": "Feature",
  "properties": {
    "iso:country":"DE",
    "sg:address":"Marktstr. 186",
    "sg:city":"Krefeld",
    "sg:phone":"+49 2151/777712",
    "sg:postcode":"47798",
    "sg:province":"Nordrhein-Westfalen",
    "wof:name":"Huk-coburg Michael Stracke",
    "wof:placetype":"venue"
},
  "geometry": {"coordinates":[6.5522170067,51.3279647827],"type":"Point"}
}