{
  "type": "Feature",
  "properties": {
    "iso:country":"DE",
    "sg:address":"Medebekskamp 6",
    "sg:city":"L\u00fcneburg",
    "sg:phone":"+49 4131/34347",
    "sg:postcode":"21339",
    "sg:province":"Niedersachsen",
    "wof:name":"Klaus Dieter M\u00fcller Ingenieur",
    "wof:placetype":"venue"
},
  "geometry": {"coordinates":[10.4097442627,53.2635917664],"type":"Point"}
}