{
  "type": "Feature",
  "properties": {
    "iso:country":"DE",
    "sg:address":"Hindenburgstr. 36",
    "sg:city":"Darmstadt",
    "sg:phone":"+49 6151/33399",
    "sg:postcode":"64295",
    "sg:province":"Hessen",
    "wof:name":"B\u00fcro Goertz",
    "wof:placetype":"venue"
},
  "geometry": {"coordinates":[8.6432256699,49.867225647],"type":"Point"}
}