{
  "type": "Feature",
  "properties": {
    "iso:country":"DE",
    "sg:address":"Johannesweg 1",
    "sg:city":"Maintal",
    "sg:phone":"+49 6181/491891",
    "sg:postcode":"63477",
    "sg:province":"Hessen",
    "wof:name":"Patrizia Gmbh",
    "wof:placetype":"venue"
},
  "geometry": {"coordinates":[8.8480081558,50.1330718994],"type":"Point"}
}