{
  "type": "Feature",
  "properties": {
    "iso:country":"DE",
    "sg:address":"Hochstra\u00dfe 11",
    "sg:city":"Altena",
    "sg:phone":"+49 4923/52",
    "sg:postcode":"58762",
    "sg:province":"Nordrhein-Westfalen",
    "wof:name":"Parfum & Kosmetikvertrieb Ingo Stute",
    "wof:placetype":"venue"
},
  "geometry": {"coordinates":[7.756313,51.301846],"type":"Point"}
}