{
  "type": "Feature",
  "properties": {
    "iso:country":"DE",
    "sg:address":"H\u00f6ferort 6",
    "sg:city":"Rahden",
    "sg:phone":"+49 5771/3607",
    "sg:postcode":"32369",
    "sg:province":"Nordrhein-Westfalen",
    "wof:name":"Wilhelm Rose",
    "wof:placetype":"venue"
},
  "geometry": {"coordinates":[8.587961,52.449036],"type":"Point"}
}