{
  "type": "Feature",
  "properties": {
    "iso:country":"DE",
    "sg:address":"Meininghausen 21",
    "sg:city":"Ennepetal",
    "sg:phone":"+49 2333/89011",
    "sg:postcode":"58256",
    "sg:province":"Nordrhein-Westfalen",
    "wof:name":"H. Piepenstock",
    "wof:placetype":"venue"
},
  "geometry": {"coordinates":[7.3565430641,51.3136253357],"type":"Point"}
}