{
  "type": "Feature",
  "properties": {
    "iso:country":"DE",
    "sg:address":"Bahnhofstr. 71",
    "sg:city":"Morsbach",
    "sg:phone":"+49 2294/8101",
    "sg:postcode":"51597",
    "sg:province":"Nordrhein-Westfalen",
    "wof:name":"Hotel Morsbacher Hof",
    "wof:placetype":"venue"
},
  "geometry": {"coordinates":[7.7185649872,50.8641967773],"type":"Point"}
}