{
  "type": "Feature",
  "properties": {
    "iso:country":"DE",
    "sg:address":"Fuchsweg 24",
    "sg:city":"Aalen",
    "sg:phone":"+49 7361/41131",
    "sg:postcode":"73434",
    "sg:province":"Baden-W\u00fcrttemberg",
    "wof:name":"Ev. Pfarramt Unterrombach",
    "wof:placetype":"venue"
},
  "geometry": {"coordinates":[10.0606517792,48.8429412842],"type":"Point"}
}