{
  "type": "Feature",
  "properties": {
    "iso:country":"DE",
    "sg:address":"Kirchstr. 18",
    "sg:city":"Seevetal",
    "sg:phone":"+49 4105/54199",
    "sg:postcode":"21218",
    "sg:province":"Niedersachsen",
    "wof:name":"Coast",
    "wof:placetype":"venue"
},
  "geometry": {"coordinates":[9.9883,53.402512],"type":"Point"}
}