{
  "type": "Feature",
  "properties": {
    "iso:country":"DE",
    "sg:address":"B\u00f6heimstr. 8",
    "sg:city":"Augsburg",
    "sg:postcode":"86153",
    "sg:province":"Bayern",
    "wof:name":"Htg-bau Gmbh",
    "wof:placetype":"venue"
},
  "geometry": {"coordinates":[10.916967,48.368484],"type":"Point"}
}