{
  "type": "Feature",
  "properties": {
    "iso:country":"DE",
    "sg:address":"M\u00fchlenstr. 43-45",
    "sg:city":"Herzogenrath",
    "sg:phone":"+49 2407/918651",
    "sg:postcode":"52134",
    "sg:province":"Nordrhein-Westfalen",
    "wof:name":"Archiplan Bauprojekt- Entwicklung Gmbh",
    "wof:placetype":"venue"
},
  "geometry": {"coordinates":[6.083754,50.836384],"type":"Point"}
}