{
  "type": "Feature",
  "properties": {
    "iso:country":"DE",
    "sg:address":"Wei\u00dfensander Str. 10",
    "sg:city":"Treuen",
    "sg:phone":"+49 37468/5552",
    "sg:postcode":"08233",
    "sg:province":"Sachsen",
    "wof:name":"Waldeslust",
    "wof:placetype":"venue"
},
  "geometry": {"coordinates":[12.3016910553,50.5471801758],"type":"Point"}
}