{
  "type": "Feature",
  "properties": {
    "iso:country":"DE",
    "sg:address":"Ro\u00dflauer Str. 51",
    "sg:city":"Zerbst",
    "sg:phone":"+49 3923/7140",
    "sg:postcode":"39261",
    "sg:province":"Sachsen-Anhalt",
    "wof:name":"Nordfrost K\u00fchl- Und Lagerhaus Gmbh",
    "wof:placetype":"venue"
},
  "geometry": {"coordinates":[12.122988,51.937572],"type":"Point"}
}