{
  "type": "Feature",
  "properties": {
    "iso:country":"DE",
    "sg:address":"Zingelstra\u00dfe 27",
    "sg:city":"Meldorf",
    "sg:phone":"+49 4832/1431",
    "sg:postcode":"25704",
    "sg:province":"Schleswig-Holstein",
    "wof:name":"Hans Heide Immobilien",
    "wof:placetype":"venue"
},
  "geometry": {"coordinates":[9.0759449005,54.0896034241],"type":"Point"}
}