{
  "type": "Feature",
  "properties": {
    "iso:country":"DE",
    "sg:address":"Heide 16",
    "sg:city":"Zerbst",
    "sg:phone":"+49 3923/782593",
    "sg:postcode":"39261",
    "sg:province":"Sachsen-Anhalt",
    "wof:name":"Ingeborg Kranz",
    "wof:placetype":"venue"
},
  "geometry": {"coordinates":[12.088596344,51.9706115723],"type":"Point"}
}