{
  "type": "Feature",
  "properties": {
    "iso:country":"DE",
    "sg:address":"Karlstr. 8",
    "sg:city":"Birkenwerder",
    "sg:postcode":"16547",
    "sg:province":"Brandenburg",
    "wof:name":"C. Rasch",
    "wof:placetype":"venue"
},
  "geometry": {"coordinates":[13.2854623795,52.6894111633],"type":"Point"}
}