{
  "type": "Feature",
  "properties": {
    "iso:country":"DE",
    "sg:address":"H\u00f6rsterplatz 5",
    "sg:city":"M\u00fcnster",
    "sg:postcode":"48147",
    "sg:province":"Nordrhein-Westfalen",
    "wof:name":"Wiss. Institut",
    "wof:placetype":"venue"
},
  "geometry": {"coordinates":[7.6301379204,51.9644584656],"type":"Point"}
}