{
  "type": "Feature",
  "properties": {
    "iso:country":"DE",
    "sg:address":"Sternstr.110",
    "sg:city":"Ludwigshaven",
    "sg:phone":"+49 621",
    "sg:postcode":"67063",
    "sg:province":"Rheinland-Pfalz",
    "wof:name":"Auto Berati",
    "wof:placetype":"venue"
},
  "geometry": {"coordinates":[8.4096212387,49.4935913086],"type":"Point"}
}