{
  "type": "Feature",
  "properties": {
    "iso:country":"DE",
    "sg:address":"Deichstr. 20",
    "sg:city":"Cuxhaven",
    "sg:phone":"+49 4721/35011",
    "sg:postcode":"27472",
    "sg:province":"Niedersachsen",
    "wof:name":"Gloria-palast",
    "wof:placetype":"venue"
},
  "geometry": {"coordinates":[8.702464,53.866734],"type":"Point"}
}