{
  "type": "Feature",
  "properties": {
    "iso:country":"DE",
    "sg:address":"M\u00fcnchener Str. 3",
    "sg:city":"Rott",
    "sg:phone":"+49 8039/1284",
    "sg:postcode":"83543",
    "sg:province":"Bayern",
    "wof:name":"Mathias Lazarus",
    "wof:placetype":"venue"
},
  "geometry": {"coordinates":[12.1275453568,47.983417511],"type":"Point"}
}