{
  "type": "Feature",
  "properties": {
    "iso:country":"DE",
    "sg:address":"Mittweidaer Str. 15",
    "sg:city":"Hainichen",
    "sg:phone":"+49 37207/2818",
    "sg:postcode":"09661",
    "sg:province":"Sachsen",
    "wof:name":"Gl\u00f6\u00df-foto",
    "wof:placetype":"venue"
},
  "geometry": {"coordinates":[13.1217346191,50.9738121033],"type":"Point"}
}