{
  "type": "Feature",
  "properties": {
    "iso:country":"DE",
    "sg:address":"Dorfstr. 15",
    "sg:city":"F\u00fcrstenau",
    "sg:phone":"+49 5901/3529",
    "sg:postcode":"49584",
    "sg:province":"Niedersachsen",
    "wof:name":"H. Beckentepe",
    "wof:placetype":"venue"
},
  "geometry": {"coordinates":[7.681703,52.500977],"type":"Point"}
}