{
  "type": "Feature",
  "properties": {
    "iso:country":"DE",
    "sg:address":"Lindenberg 1",
    "sg:city":"Euskirchen",
    "sg:phone":"+49 2255/8905",
    "sg:postcode":"53881",
    "sg:province":"Nordrhein-Westfalen",
    "wof:name":"Johann Mertens",
    "wof:placetype":"venue"
},
  "geometry": {"coordinates":[6.773118,50.651989],"type":"Point"}
}