{
  "type": "Feature",
  "properties": {
    "iso:country":"DE",
    "sg:address":"Aiblinger Str. 1",
    "sg:city":"Bad Feilnbach",
    "sg:phone":"+49 8066/8524",
    "sg:postcode":"83075",
    "sg:province":"Bayern",
    "wof:name":"Wendelstein-schafwolle H\u00f6fer Gmbh",
    "wof:placetype":"venue"
},
  "geometry": {"coordinates":[12.056265831,47.7618942261],"type":"Point"}
}