{
  "type": "Feature",
  "properties": {
    "iso:country":"DE",
    "sg:address":"Kurze Str. 17",
    "sg:city":"G\u00f6ttingen",
    "sg:phone":"+49 551/484115",
    "sg:postcode":"37073",
    "sg:province":"Niedersachsen",
    "wof:name":"Naturalia",
    "wof:placetype":"venue"
},
  "geometry": {"coordinates":[9.9360122681,51.5304641724],"type":"Point"}
}