{
  "type": "Feature",
  "properties": {
    "iso:country":"DE",
    "sg:address":"Dotzheimer Str. 74",
    "sg:city":"Wiesbaden",
    "sg:phone":"+49 611/48828",
    "sg:postcode":"65197",
    "sg:province":"Hessen",
    "wof:name":"Casinothek H Gmbh",
    "wof:placetype":"venue"
},
  "geometry": {"coordinates":[8.2260932922,50.0778083801],"type":"Point"}
}