{
  "type": "Feature",
  "properties": {
    "iso:country":"DE",
    "sg:address":"Gablonzer Str. 22",
    "sg:city":"Trappenkamp",
    "sg:phone":"+49 4323/1000",
    "sg:postcode":"24610",
    "sg:province":"Schleswig-Holstein",
    "wof:name":"S. Clausen",
    "wof:placetype":"venue"
},
  "geometry": {"coordinates":[10.216029,54.039043],"type":"Point"}
}