{
  "type": "Feature",
  "properties": {
    "iso:country":"DE",
    "sg:address":"Eberst\u00e4dter Str. 25",
    "sg:city":"M\u00fchltal",
    "sg:phone":"+49 6151/148813",
    "sg:postcode":"64367",
    "sg:province":"Hessen",
    "wof:name":"Klaus Ga\u00dfmann Rechtsanwalt",
    "wof:placetype":"venue"
},
  "geometry": {"coordinates":[8.6966848373,49.8208198547],"type":"Point"}
}