{
  "type": "Feature",
  "properties": {
    "iso:country":"DE",
    "sg:address":"Kumpfm\u00fchle 43",
    "sg:city":"F\u00fcrstenzell",
    "sg:phone":"+49 8506/1280",
    "sg:postcode":"94081",
    "sg:province":"Bayern",
    "wof:name":"Bad H\u00f6henst\u00e4dter Heilbad- Verwaltungs-gmbh",
    "wof:placetype":"venue"
},
  "geometry": {"coordinates":[13.316582,48.52243],"type":"Point"}
}