{
  "type": "Feature",
  "properties": {
    "iso:country":"DE",
    "sg:address":"Schweriner Str. 2",
    "sg:city":"Marl",
    "sg:phone":"+49 2365/14746",
    "sg:postcode":"45770",
    "sg:province":"Nordrhein-Westfalen",
    "wof:name":"Ralf Plura",
    "wof:placetype":"venue"
},
  "geometry": {"coordinates":[7.0908279419,51.6437301636],"type":"Point"}
}