{
  "type": "Feature",
  "properties": {
    "iso:country":"DE",
    "sg:address":"M\u00fcnzhofstr. 9",
    "sg:city":"Langenargen",
    "sg:phone":"+49 7543/2105",
    "sg:postcode":"88085",
    "sg:province":"Baden-W\u00fcrttemberg",
    "wof:name":"August Kittler",
    "wof:placetype":"venue"
},
  "geometry": {"coordinates":[9.540536,47.596779],"type":"Point"}
}