{
  "type": "Feature",
  "properties": {
    "iso:country":"DE",
    "sg:address":"Breite Str. 1",
    "sg:city":"Buxtehude",
    "sg:phone":"+49 4161/512341",
    "sg:postcode":"21614",
    "sg:province":"Niedersachsen",
    "wof:name":"D. Volkmer",
    "wof:placetype":"venue"
},
  "geometry": {"coordinates":[9.699945,53.476379],"type":"Point"}
}