{
  "type": "Feature",
  "properties": {
    "iso:country":"DE",
    "sg:address":"Stra\u00dfe des Friedens 116",
    "sg:city":"Parchim",
    "sg:postcode":"19370",
    "sg:province":"Mecklenburg-Vorpommern",
    "wof:name":"W. Kl\u00fcver Inh. E. Kl\u00fcver",
    "wof:placetype":"venue"
},
  "geometry": {"coordinates":[11.8542833328,53.4268493652],"type":"Point"}
}