{
  "type": "Feature",
  "properties": {
    "iso:country":"DE",
    "sg:address":"Scheuerlesstr. 33",
    "sg:city":"Eppingen",
    "sg:phone":"+49 7262/1444",
    "sg:postcode":"75031",
    "sg:province":"Baden-W\u00fcrttemberg",
    "wof:name":"Gschwandter Und Hautzinger Bauschlosserei",
    "wof:placetype":"venue"
},
  "geometry": {"coordinates":[8.9165992737,49.1402244568],"type":"Point"}
}