{
  "type": "Feature",
  "properties": {
    "iso:country":"DE",
    "sg:address":"Otto-Hahn-Str. 7",
    "sg:city":"Stockelsdorf",
    "sg:phone":"+49 451/497575",
    "sg:postcode":"23617",
    "sg:province":"Schleswig-Holstein",
    "wof:name":"Stockelsdorfer Fernmeldebauges Sfg Goll Ohg",
    "wof:placetype":"venue"
},
  "geometry": {"coordinates":[10.6431026459,53.905796051],"type":"Point"}
}