{
  "type": "Feature",
  "properties": {
    "iso:country":"DE",
    "sg:address":"Am Wildgatter 39",
    "sg:city":"Berlin",
    "sg:postcode":"14109",
    "sg:province":"Berlin",
    "wof:name":"Kreon Gmbh",
    "wof:placetype":"venue"
},
  "geometry": {"coordinates":[13.13621521,52.414680481],"type":"Point"}
}