{
  "type": "Feature",
  "properties": {
    "iso:country":"DE",
    "sg:address":"Arsterdamm 70",
    "sg:city":"Bremen",
    "sg:phone":"+49 421/87700",
    "sg:postcode":"28277",
    "sg:province":"Bremen",
    "wof:name":"Gebr. Sie Beteiligungs Gmbh",
    "wof:placetype":"venue"
},
  "geometry": {"coordinates":[8.827453,53.042767],"type":"Point"}
}