{
  "type": "Feature",
  "properties": {
    "iso:country":"DE",
    "sg:address":"Wrangelstr. 6",
    "sg:city":"Flensburg",
    "sg:phone":"+49 461/503010",
    "sg:postcode":"24937",
    "sg:province":"Schleswig-Holstein",
    "wof:name":"Revisions- Und Treuhandges. Casper-stahl & Partner",
    "wof:placetype":"venue"
},
  "geometry": {"coordinates":[9.4237451553,54.7888450623],"type":"Point"}
}