{
  "type": "Feature",
  "properties": {
    "iso:country":"DE",
    "sg:address":"Wasserburger Landstr. 225",
    "sg:city":"M\u00fcnchen",
    "sg:phone":"+49 89/4306232",
    "sg:postcode":"81827",
    "sg:province":"Bayern",
    "wof:name":"Aro-heimtextilien Gmbh & Co. Kg",
    "wof:placetype":"venue"
},
  "geometry": {"coordinates":[11.7043199539,48.1126289368],"type":"Point"}
}