{
  "type": "Feature",
  "properties": {
    "iso:country":"DE",
    "sg:address":"Am Sportplatz 15",
    "sg:city":"Sch\u00f6ffengrund",
    "sg:phone":"+49 6445/92003",
    "sg:postcode":"35641",
    "sg:province":"Hessen",
    "wof:name":"Geoconcept Gesellschaft F\u00fcr Angewandte Geotechnik Und",
    "wof:placetype":"venue"
},
  "geometry": {"coordinates":[8.4969949722,50.4921188354],"type":"Point"}
}