{
  "type": "Feature",
  "properties": {
    "iso:country":"DE",
    "sg:address":"Br\u00fchlstr. 20",
    "sg:city":"Landau",
    "sg:phone":"+49 6341/30466",
    "sg:postcode":"76829",
    "sg:province":"Rheinland-Pfalz",
    "wof:name":"W. Wambsganss Weinanbau",
    "wof:placetype":"venue"
},
  "geometry": {"coordinates":[8.0783729553,49.1681594849],"type":"Point"}
}