{
  "type": "Feature",
  "properties": {
    "iso:country":"DE",
    "sg:address":"Beuditzstr. 11",
    "sg:city":"Wei\u00dfenfels",
    "sg:phone":"+49 3443/303009",
    "sg:postcode":"06667",
    "sg:province":"Sachsen-Anhalt",
    "wof:name":"Alfred Seidel",
    "wof:placetype":"venue"
},
  "geometry": {"coordinates":[11.965274,51.199825],"type":"Point"}
}