{
  "type": "Feature",
  "properties": {
    "iso:country":"DE",
    "sg:address":"Bleichweg 11",
    "sg:city":"Ellhofen",
    "sg:phone":"+49 7134/18864",
    "sg:postcode":"74248",
    "sg:province":"Baden-W\u00fcrttemberg",
    "wof:name":"Rad Sport Gemeinschaft Heilbronn 1892 E.v.",
    "wof:placetype":"venue"
},
  "geometry": {"coordinates":[9.3226709366,49.1446037292],"type":"Point"}
}