{
  "type": "Feature",
  "properties": {
    "iso:country":"DE",
    "sg:address":"Bochumer Str. 18",
    "sg:city":"Wilnsdorf",
    "sg:phone":"+49 2739/4077",
    "sg:postcode":"57234",
    "sg:province":"Nordrhein-Westfalen",
    "wof:name":"Dieter Seifert",
    "wof:placetype":"venue"
},
  "geometry": {"coordinates":[8.1069345474,50.8180274963],"type":"Point"}
}