{
  "type": "Feature",
  "properties": {
    "iso:country":"DE",
    "sg:address":"Im Grund 1",
    "sg:city":"B\u00fcchenbeuren",
    "sg:phone":"+49 6543/980174",
    "sg:postcode":"55491",
    "sg:province":"Rheinland-Pfalz",
    "wof:name":"Bernd Nix",
    "wof:placetype":"venue"
},
  "geometry": {"coordinates":[7.2776727676,49.9191741943],"type":"Point"}
}