{
  "type": "Feature",
  "properties": {
    "iso:country":"DE",
    "sg:address":"Lassallestr. 14",
    "sg:city":"M\u00fchlhausen",
    "sg:phone":"+49 36014/49939",
    "sg:postcode":"99974",
    "sg:province":"Th\u00fcringen",
    "wof:name":"M\u00fchlh\u00e4user Fleischer- Handwerks Gmbh",
    "wof:placetype":"venue"
},
  "geometry": {"coordinates":[10.4740848541,51.2054443359],"type":"Point"}
}