{
  "type": "Feature",
  "properties": {
    "iso:country":"DE",
    "sg:address":"Alt-Buckow 34",
    "sg:city":"Berlin",
    "sg:phone":"+49 30/6041010",
    "sg:postcode":"12349",
    "sg:province":"Berlin",
    "wof:name":"Ev. Pfarramt Alt-buckow",
    "wof:placetype":"venue"
},
  "geometry": {"coordinates":[13.4310855865,52.4220619202],"type":"Point"}
}