{
  "type": "Feature",
  "properties": {
    "iso:country":"DE",
    "sg:address":"Schorndorfer Str. 9",
    "sg:city":"Uhingen",
    "sg:phone":"+49 7161/31757",
    "sg:postcode":"73066",
    "sg:province":"Baden-W\u00fcrttemberg",
    "wof:name":"Walter Wenzelburger",
    "wof:placetype":"venue"
},
  "geometry": {"coordinates":[9.58244,48.709579],"type":"Point"}
}