{
  "type": "Feature",
  "properties": {
    "iso:country":"DE",
    "sg:address":"Europastr. 63 A",
    "sg:city":"Lahr",
    "sg:phone":"+49 7821/955096",
    "sg:postcode":"77933",
    "sg:province":"Baden-W\u00fcrttemberg",
    "wof:name":"Smb Wohnungsbau Gmbh",
    "wof:placetype":"venue"
},
  "geometry": {"coordinates":[7.8259902,48.3496284485],"type":"Point"}
}