{
  "type": "Feature",
  "properties": {
    "iso:country":"DE",
    "sg:address":"Bertolt-Brecht-Allee 20",
    "sg:city":"Dresden",
    "sg:phone":"+49 351/31991900",
    "sg:postcode":"01309",
    "sg:province":"Sachsen",
    "wof:name":"Messteam Ilka Luft- Und K\u00e4ltetechnik Gmbh",
    "wof:placetype":"venue"
},
  "geometry": {"coordinates":[13.779787,51.04068],"type":"Point"}
}