{
  "type": "Feature",
  "properties": {
    "iso:country":"DE",
    "sg:address":"Beberstr.",
    "sg:city":"Heilbad Heiligenstadt",
    "sg:phone":"+49 3606/4271",
    "sg:postcode":"37308",
    "sg:province":"Th\u00fcringen",
    "wof:name":"Gastst\u00e4tte Zur Linde",
    "wof:placetype":"venue"
},
  "geometry": {"coordinates":[10.0924692154,51.3797607422],"type":"Point"}
}