{
  "type": "Feature",
  "properties": {
    "iso:country":"DE",
    "sg:address":"Vorderstr. 15",
    "sg:city":"Wiesbaden",
    "sg:phone":"+49 611/507293",
    "sg:postcode":"65207",
    "sg:province":"Hessen",
    "wof:name":"Christian Und Antje Hilbert Masseure",
    "wof:placetype":"venue"
},
  "geometry": {"coordinates":[8.306429,50.094067],"type":"Point"}
}