{
  "type": "Feature",
  "properties": {
    "iso:country":"DE",
    "sg:address":"Von-der-Tann-Str. 4",
    "sg:city":"Waldkraiburg",
    "sg:phone":"+49 8638/3677",
    "sg:postcode":"84478",
    "sg:province":"Bayern",
    "wof:name":"Wolfgang Wormuth",
    "wof:placetype":"venue"
},
  "geometry": {"coordinates":[12.38673,48.205921],"type":"Point"}
}