{
  "type": "Feature",
  "properties": {
    "iso:country":"DE",
    "sg:address":"Hermsdorfer Damm 155",
    "sg:city":"Berlin",
    "sg:phone":"+49 30/4048695",
    "sg:postcode":"13467",
    "sg:province":"Berlin",
    "wof:name":"G\u00fcnter Meinburg",
    "wof:placetype":"venue"
},
  "geometry": {"coordinates":[13.3019952774,52.6176147461],"type":"Point"}
}