{
  "type": "Feature",
  "properties": {
    "iso:country":"DE",
    "sg:address":"Raiffeisenstr. 1",
    "sg:city":"Langenfeld",
    "sg:phone":"+49 2173/78316",
    "sg:postcode":"40764",
    "sg:province":"Nordrhein-Westfalen",
    "wof:name":"Bistro Chalet",
    "wof:placetype":"venue"
},
  "geometry": {"coordinates":[6.9224658012,51.1216468811],"type":"Point"}
}