{
  "type": "Feature",
  "properties": {
    "iso:country":"DE",
    "sg:address":"Hauptstr. 41",
    "sg:city":"Burgsinn",
    "sg:phone":"+49 9356/1658",
    "sg:postcode":"97775",
    "sg:province":"Bayern",
    "wof:name":"Herbert P\u00e4tzold Eisenwaren",
    "wof:placetype":"venue"
},
  "geometry": {"coordinates":[9.6505451202,50.1487960815],"type":"Point"}
}