{
  "type": "Feature",
  "properties": {
    "iso:country":"DE",
    "sg:address":"Martin-Luther-Str. 65",
    "sg:city":"Siegen",
    "sg:phone":"+49 271/315425",
    "sg:postcode":"57080",
    "sg:province":"Nordrhein-Westfalen",
    "wof:name":"Georg U. Martin Hanke",
    "wof:placetype":"venue"
},
  "geometry": {"coordinates":[7.9938659668,50.857837677],"type":"Point"}
}