{
  "type": "Feature",
  "properties": {
    "iso:country":"DE",
    "sg:address":"In der Dreispitze 11",
    "sg:city":"R\u00f6dermark",
    "sg:postcode":"63322",
    "sg:province":"Hessen",
    "wof:name":"Stenger Consulting Gmbh",
    "wof:placetype":"venue"
},
  "geometry": {"coordinates":[8.838978,49.974297],"type":"Point"}
}