{
  "type": "Feature",
  "properties": {
    "iso:country":"DE",
    "sg:address":"Stresemannstr.",
    "sg:city":"Hamburg",
    "sg:postcode":"22761",
    "sg:province":"Hamburg",
    "wof:name":"Drewling & Borowski Tonstudios Ohg",
    "wof:placetype":"venue"
},
  "geometry": {"coordinates":[9.9206476212,53.5639266968],"type":"Point"}
}