{
  "type": "Feature",
  "properties": {
    "iso:country":"DE",
    "sg:address":"Beisengeithe 1a",
    "sg:city":"Hamm",
    "sg:phone":"+49 2381/82751",
    "sg:postcode":"59071",
    "sg:province":"Nordrhein-Westfalen",
    "wof:name":"Robert Sinn Steuerberater Und",
    "wof:placetype":"venue"
},
  "geometry": {"coordinates":[7.8630199432,51.6779289246],"type":"Point"}
}