{
  "type": "Feature",
  "properties": {
    "iso:country":"DE",
    "sg:address":"Hachestr. 34",
    "sg:city":"Essen",
    "sg:postcode":"45127",
    "sg:province":"Nordrhein-Westfalen",
    "wof:name":"Ghg Grundbesitzhandel Gmbh",
    "wof:placetype":"venue"
},
  "geometry": {"coordinates":[7.0078058243,51.4518013],"type":"Point"}
}