{
  "type": "Feature",
  "properties": {
    "iso:country":"DE",
    "sg:address":"Andersenstr. 2",
    "sg:city":"Berlin",
    "sg:phone":"+49 30/4450708",
    "sg:postcode":"10439",
    "sg:province":"Berlin",
    "wof:name":"Osteria Il Ponte",
    "wof:placetype":"venue"
},
  "geometry": {"coordinates":[13.4041204453,52.5549659729],"type":"Point"}
}