{
  "type": "Feature",
  "properties": {
    "iso:country":"DE",
    "sg:address":"Auf der Flips 1",
    "sg:city":"Oberkail",
    "sg:phone":"+49 6567/799",
    "sg:postcode":"54533",
    "sg:province":"Rheinland-Pfalz",
    "wof:name":"Alfred Densborn",
    "wof:placetype":"venue"
},
  "geometry": {"coordinates":[6.6818070412,50.0391960144],"type":"Point"}
}