{
  "type": "Feature",
  "properties": {
    "iso:country":"DE",
    "sg:address":"Alte Ramtelstr. 22",
    "sg:city":"Leonberg",
    "sg:phone":"+49 7152/94140",
    "sg:postcode":"71229",
    "sg:province":"Baden-W\u00fcrttemberg",
    "wof:name":"Endress Forst- Und Garten- Technik Vertriebs Gmbh",
    "wof:placetype":"venue"
},
  "geometry": {"coordinates":[9.016528,48.78854],"type":"Point"}
}