{
  "type": "Feature",
  "properties": {
    "iso:country":"DE",
    "sg:address":"F\u00fcrstenbergstr. 3",
    "sg:city":"Lennestadt",
    "sg:phone":"+49 2721/82544",
    "sg:postcode":"57368",
    "sg:province":"Nordrhein-Westfalen",
    "wof:name":"Karl-heinz N\u00fcschen",
    "wof:placetype":"venue"
},
  "geometry": {"coordinates":[8.0172214508,51.093536377],"type":"Point"}
}