{
  "type": "Feature",
  "properties": {
    "iso:country":"DE",
    "sg:address":"Am Sch\u00fcsselteich 9",
    "sg:city":"Lauenburg",
    "sg:phone":"+49 4153/58320",
    "sg:postcode":"21481",
    "sg:province":"Schleswig-Holstein",
    "wof:name":"Norbert Winkler Steuerberatungs Gmbh",
    "wof:placetype":"venue"
},
  "geometry": {"coordinates":[10.5506687164,53.375213623],"type":"Point"}
}