{
  "type": "Feature",
  "properties": {
    "iso:country":"DE",
    "sg:address":"Marienfelder Str. 37",
    "sg:city":"G\u00fctersloh",
    "sg:phone":"+49 5241/14734",
    "sg:postcode":"33330",
    "sg:province":"Nordrhein-Westfalen",
    "wof:name":"B\u00e4ckerei Runge",
    "wof:placetype":"venue"
},
  "geometry": {"coordinates":[8.366242,51.912228],"type":"Point"}
}