{
  "type": "Feature",
  "properties": {
    "iso:country":"DE",
    "sg:address":"Kleyerstr. 90",
    "sg:city":"Frankfurt",
    "sg:phone":"+49 69/3300880",
    "sg:postcode":"60326",
    "sg:province":"Hessen",
    "wof:name":"Hogass-hotel Und Gastronomie Service Gmbh",
    "wof:placetype":"venue"
},
  "geometry": {"coordinates":[8.6326789856,50.0985221863],"type":"Point"}
}