{
  "type": "Feature",
  "properties": {
    "iso:country":"DE",
    "sg:address":"Heidkantweg 139",
    "sg:city":"Haltern",
    "sg:phone":"+49 2360/1734",
    "sg:postcode":"45721",
    "sg:province":"Nordrhein-Westfalen",
    "wof:name":"Wilhelm B\u00f6ntert",
    "wof:placetype":"venue"
},
  "geometry": {"coordinates":[7.0754938126,51.7117919922],"type":"Point"}
}