{
  "type": "Feature",
  "properties": {
    "iso:country":"DE",
    "sg:address":"M\u00fcllerstr. 31",
    "sg:city":"Berlin",
    "sg:phone":"+49 30/45606383",
    "sg:postcode":"13353",
    "sg:province":"Berlin",
    "wof:name":"Photo Porst Inh. Dieter Meckes",
    "wof:placetype":"venue"
},
  "geometry": {"coordinates":[13.3568668365,52.5479316711],"type":"Point"}
}