{
  "type": "Feature",
  "properties": {
    "iso:country":"DE",
    "sg:address":"Maubacher Str. 9",
    "sg:city":"Herzogenrath",
    "sg:phone":"+49 2406/4808",
    "sg:postcode":"52134",
    "sg:province":"Nordrhein-Westfalen",
    "wof:name":"H. Junggeburth",
    "wof:placetype":"venue"
},
  "geometry": {"coordinates":[6.081001,50.857292],"type":"Point"}
}