{
  "type": "Feature",
  "properties": {
    "iso:country":"DE",
    "sg:address":"D\u00fcrkheimer Str. 55",
    "sg:city":"Frankenthal",
    "sg:phone":"+49 6233/54864",
    "sg:postcode":"67227",
    "sg:province":"Rheinland-Pfalz",
    "wof:name":"Rudi Schroth",
    "wof:placetype":"venue"
},
  "geometry": {"coordinates":[8.332499,49.507095],"type":"Point"}
}