{
  "type": "Feature",
  "properties": {
    "iso:country":"DE",
    "sg:address":"Fritz-Rehm-Str. 4 a",
    "sg:city":"Elze",
    "sg:phone":"+49 5068/710",
    "sg:postcode":"31008",
    "sg:province":"Niedersachsen",
    "wof:name":"K. Schneider",
    "wof:placetype":"venue"
},
  "geometry": {"coordinates":[9.7463378906,52.1304359436],"type":"Point"}
}