{
  "type": "Feature",
  "properties": {
    "iso:country":"DE",
    "sg:address":"Deichstr. 16",
    "sg:city":"H\u00f6hbeck",
    "sg:phone":"+49 5846/97980",
    "sg:postcode":"29478",
    "sg:province":"Niedersachsen",
    "wof:name":"Werner Mummelthei Steuerberater",
    "wof:placetype":"venue"
},
  "geometry": {"coordinates":[11.4420499802,53.0401878357],"type":"Point"}
}