{
  "type": "Feature",
  "properties": {
    "iso:country":"DE",
    "sg:address":"Helmut-H\u00f6rmann-Str 6-10",
    "sg:city":"Heubach",
    "sg:phone":"+49 7173/1820",
    "sg:postcode":"73540",
    "sg:province":"Baden-W\u00fcrttemberg",
    "wof:name":"Susa-vertriebs-gmbh & Co",
    "wof:placetype":"venue"
},
  "geometry": {"coordinates":[9.935838,48.790703],"type":"Point"}
}