{
  "type": "Feature",
  "properties": {
    "iso:country":"DE",
    "sg:address":"Vorgebirgstr. 360",
    "sg:city":"K\u00f6ln",
    "sg:phone":"+49 221/3603590",
    "sg:postcode":"50969",
    "sg:province":"Nordrhein-Westfalen",
    "wof:name":"R. Blissenbach",
    "wof:placetype":"venue"
},
  "geometry": {"coordinates":[6.94504,50.902378],"type":"Point"}
}