{
  "type": "Feature",
  "properties": {
    "iso:country":"DE",
    "sg:address":"Augustaanlage 25",
    "sg:city":"Mannheim",
    "sg:postcode":"68165",
    "sg:province":"Baden-W\u00fcrttemberg",
    "wof:name":"Jurcall Gmbh",
    "wof:placetype":"venue"
},
  "geometry": {"coordinates":[8.481589,49.48204],"type":"Point"}
}