{
  "type": "Feature",
  "properties": {
    "iso:country":"DE",
    "sg:address":"Aachener Str. 170",
    "sg:city":"D\u00fcsseldorf",
    "sg:phone":"+49 211/152565",
    "sg:postcode":"40223",
    "sg:province":"Nordrhein-Westfalen",
    "wof:name":"Klaus Th\u00f6mmes",
    "wof:placetype":"venue"
},
  "geometry": {"coordinates":[6.7704138756,51.1974525452],"type":"Point"}
}