{
  "type": "Feature",
  "properties": {
    "iso:country":"DE",
    "sg:address":"Marktplatz 1",
    "sg:city":"Schwandorf",
    "sg:phone":"+49 9431/71390",
    "sg:postcode":"92421",
    "sg:province":"Bayern",
    "wof:name":"Red. Mittelbayerische Zeitung",
    "wof:placetype":"venue"
},
  "geometry": {"coordinates":[12.1072101593,49.329750061],"type":"Point"}
}