{
  "type": "Feature",
  "properties": {
    "iso:country":"DE",
    "sg:address":"Im Ostfeld 4",
    "sg:city":"Schwerte",
    "sg:phone":"+49 2304/61512",
    "sg:postcode":"58239",
    "sg:province":"Nordrhein-Westfalen",
    "wof:name":"Peter Karbstein",
    "wof:placetype":"venue"
},
  "geometry": {"coordinates":[7.539926,51.424152],"type":"Point"}
}