{
  "type": "Feature",
  "properties": {
    "iso:country":"DE",
    "sg:address":"Niels-Stensen-Weg 10",
    "sg:city":"Reinbek",
    "sg:postcode":"21465",
    "sg:province":"Schleswig-Holstein",
    "wof:name":"Sozialstation Reinbek",
    "wof:placetype":"venue"
},
  "geometry": {"coordinates":[10.249038,53.511524],"type":"Point"}
}