{
  "type": "Feature",
  "properties": {
    "iso:country":"DE",
    "sg:address":"Gr\u00fcnenbergstr. 13",
    "sg:city":"G\u00f6ppingen",
    "sg:phone":"+49 7161/69826",
    "sg:postcode":"73037",
    "sg:province":"Baden-W\u00fcrttemberg",
    "wof:name":"Manfred Forderer",
    "wof:placetype":"venue"
},
  "geometry": {"coordinates":[9.6760835648,48.6964759827],"type":"Point"}
}