{
  "type": "Feature",
  "properties": {
    "iso:country":"DE",
    "sg:address":"Marktplatz 1",
    "sg:city":"Bad Windsheim",
    "sg:phone":"+49 9841/66890",
    "sg:postcode":"91438",
    "sg:province":"Bayern",
    "wof:name":"Stadtarchiv",
    "wof:placetype":"venue"
},
  "geometry": {"coordinates":[10.417484,49.502335],"type":"Point"}
}