{
  "type": "Feature",
  "properties": {
    "iso:country":"DE",
    "sg:address":"Eulenstr. 12",
    "sg:city":"Recklinghausen",
    "sg:postcode":"45665",
    "sg:province":"Nordrhein-Westfalen",
    "wof:name":"Kath. \u00f6ffentliche Bibliothek St. Barbara",
    "wof:placetype":"venue"
},
  "geometry": {"coordinates":[7.275192,51.600208],"type":"Point"}
}