{
  "type": "Feature",
  "properties": {
    "iso:country":"DE",
    "sg:address":"Bahnhofstr. 3",
    "sg:city":"Lottstetten",
    "sg:phone":"+49 7745/7552",
    "sg:postcode":"79807",
    "sg:province":"Baden-W\u00fcrttemberg",
    "wof:name":"Gastst\u00e4tte Bahnhof",
    "wof:placetype":"venue"
},
  "geometry": {"coordinates":[8.5685806274,47.626159668],"type":"Point"}
}