{
  "type": "Feature",
  "properties": {
    "iso:country":"DE",
    "sg:address":"Kaiserstr. 130",
    "sg:city":"Radevormwald",
    "sg:phone":"+49 2195/1337",
    "sg:postcode":"42477",
    "sg:province":"Nordrhein-Westfalen",
    "wof:name":"M\u00f6bel Behnke Inh. Ingrid K\u00f6rner",
    "wof:placetype":"venue"
},
  "geometry": {"coordinates":[7.361606,51.202152],"type":"Point"}
}