{
  "type": "Feature",
  "properties": {
    "iso:country":"DE",
    "sg:address":"Wattenscheider Hellweg 21",
    "sg:city":"Bochum",
    "sg:phone":"+49 2327/53444",
    "sg:postcode":"44869",
    "sg:province":"Nordrhein-Westfalen",
    "wof:name":"Ulrich Hesse",
    "wof:placetype":"venue"
},
  "geometry": {"coordinates":[7.159114,51.467472],"type":"Point"}
}