{
  "type": "Feature",
  "properties": {
    "iso:country":"DE",
    "sg:address":"Konrad-Adenauer-Str. 28",
    "sg:city":"Reutlingen",
    "sg:phone":"+49 7121/939967",
    "sg:postcode":"72762",
    "sg:province":"Baden-W\u00fcrttemberg",
    "wof:name":"Asmo K\u00fcchen Inh. Martin Rupp",
    "wof:placetype":"venue"
},
  "geometry": {"coordinates":[9.2034893036,48.4919471741],"type":"Point"}
}