{
  "type": "Feature",
  "properties": {
    "iso:country":"DE",
    "sg:address":"Eisenbahnstr. 136",
    "sg:city":"F\u00fcrstenwalde",
    "sg:phone":"+49 3361/300828",
    "sg:postcode":"15517",
    "sg:province":"Brandenburg",
    "wof:name":"M. Schmidt Immobilienmakler",
    "wof:placetype":"venue"
},
  "geometry": {"coordinates":[14.061627388,52.3631858826],"type":"Point"}
}