{
  "type": "Feature",
  "properties": {
    "iso:country":"DE",
    "sg:address":"Sigmundstr. 147",
    "sg:city":"N\u00fcrnberg",
    "sg:phone":"+49 911/616801",
    "sg:postcode":"90431",
    "sg:province":"Bayern",
    "wof:name":"Formenbau Schmid-hauer Gmbh",
    "wof:placetype":"venue"
},
  "geometry": {"coordinates":[11.0106678009,49.4472503662],"type":"Point"}
}