{
  "type": "Feature",
  "properties": {
    "iso:country":"DE",
    "sg:address":"Aussiger Str. 20",
    "sg:city":"Pohlheim",
    "sg:phone":"+49 6403/63344",
    "sg:postcode":"35415",
    "sg:province":"Hessen",
    "wof:name":"Gerhard Geisler",
    "wof:placetype":"venue"
},
  "geometry": {"coordinates":[8.7237930298,50.5450897217],"type":"Point"}
}