{
  "type": "Feature",
  "properties": {
    "iso:country":"DE",
    "sg:address":"Neubergweg 32",
    "sg:city":"Waldshut-Tiengen",
    "sg:phone":"+49 7741/65818",
    "sg:postcode":"79761",
    "sg:province":"Baden-W\u00fcrttemberg",
    "wof:name":"Lothar Weinig Architekt",
    "wof:placetype":"venue"
},
  "geometry": {"coordinates":[8.250577,47.646366],"type":"Point"}
}