{
  "type": "Feature",
  "properties": {
    "iso:country":"DE",
    "sg:address":"Gablonzer Ring 8",
    "sg:city":"Kaufbeuren",
    "sg:phone":"+49 8341/98656",
    "sg:postcode":"87600",
    "sg:province":"Bayern",
    "wof:name":"Plus Warenhandels Gmbh & Co. Ohg",
    "wof:placetype":"venue"
},
  "geometry": {"coordinates":[10.6366786957,47.9126853943],"type":"Point"}
}