{
  "type": "Feature",
  "properties": {
    "iso:country":"DE",
    "sg:address":"Josef-Haamann-Str. 6",
    "sg:city":"Kirschfurt",
    "sg:phone":"+49 9375/840",
    "sg:postcode":"97896",
    "sg:province":"Baden-W\u00fcrttemberg",
    "wof:name":"Haacon Hebetechnik Gmbh",
    "wof:placetype":"venue"
},
  "geometry": {"coordinates":[9.31933,49.744179],"type":"Point"}
}