{
  "type": "Feature",
  "properties": {
    "iso:country":"DE",
    "sg:address":"Strandstr. 14",
    "sg:city":"Ostseebad Nienhagen",
    "sg:phone":"+49 38203/81182",
    "sg:postcode":"18211",
    "sg:province":"Mecklenburg-Vorpommern",
    "wof:name":"Am Teich",
    "wof:placetype":"venue"
},
  "geometry": {"coordinates":[11.9776296616,54.1110305786],"type":"Point"}
}