{
  "type": "Feature",
  "properties": {
    "iso:country":"DE",
    "sg:address":"Friedensstr. 14",
    "sg:city":"Neustadt",
    "sg:phone":"+49 9568/5639",
    "sg:postcode":"96465",
    "sg:province":"Bayern",
    "wof:name":"Ev. Pfarramt Gem. Wildenheid-meilschnitz",
    "wof:placetype":"venue"
},
  "geometry": {"coordinates":[13.7416763306,51.0730133057],"type":"Point"}
}