{
  "type": "Feature",
  "properties": {
    "iso:country":"DE",
    "sg:address":"Hauptstr. 10",
    "sg:city":"Triberg",
    "sg:phone":"+49 7722/4493",
    "sg:postcode":"78098",
    "sg:province":"Baden-W\u00fcrttemberg",
    "wof:name":"Hotel Zum B\u00e4ren",
    "wof:placetype":"venue"
},
  "geometry": {"coordinates":[8.2350749969,48.1341972351],"type":"Point"}
}