{
  "type": "Feature",
  "properties": {
    "iso:country":"DE",
    "sg:address":"Dorotheenstr. 60",
    "sg:city":"Hamburg",
    "sg:postcode":"22301",
    "sg:province":"Hamburg",
    "wof:name":"Beteiligungsgesellschaft Frank Unverhau Mbh",
    "wof:placetype":"venue"
},
  "geometry": {"coordinates":[10.007964,53.583427],"type":"Point"}
}