{
  "type": "Feature",
  "properties": {
    "iso:country":"DE",
    "sg:address":"Zeiloch 13 Technologiedorf",
    "sg:city":"Bruchsal",
    "sg:postcode":"76646",
    "sg:province":"Baden-W\u00fcrttemberg",
    "wof:name":"Awd Einkaufs- Und Marketinggesellschaft F\u00fcr",
    "wof:placetype":"venue"
},
  "geometry": {"coordinates":[8.6010227203,49.1237716675],"type":"Point"}
}