{
  "type": "Feature",
  "properties": {
    "iso:country":"DE",
    "sg:address":"Edith-Stein-Str. 48",
    "sg:city":"Langen",
    "sg:postcode":"63225",
    "sg:province":"Hessen",
    "wof:name":"Intracom Gesellschaft F\u00fcr Edv-beratung Mbh",
    "wof:placetype":"venue"
},
  "geometry": {"coordinates":[8.6743774414,49.9938201904],"type":"Point"}
}