{
  "type": "Feature",
  "properties": {
    "iso:country":"DE",
    "sg:address":"Trippstadter Str. 125",
    "sg:city":"Kaiserslautern",
    "sg:phone":"+49 631/16669",
    "sg:postcode":"67663",
    "sg:province":"Rheinland-Pfalz",
    "wof:name":"Eulenspiegel",
    "wof:placetype":"venue"
},
  "geometry": {"coordinates":[7.752904892,49.4302558899],"type":"Point"}
}