{
  "type": "Feature",
  "properties": {
    "iso:country":"DE",
    "sg:address":"Ziolkowskistr.",
    "sg:city":"Hoyerswerda",
    "sg:postcode":"02977",
    "sg:province":"Sachsen",
    "wof:name":"Aldi Gmbh & Co. Kg",
    "wof:placetype":"venue"
},
  "geometry": {"coordinates":[14.2720098495,51.4297332764],"type":"Point"}
}