{
  "type": "Feature",
  "properties": {
    "iso:country":"DE",
    "sg:address":"Schanzstr. 9",
    "sg:city":"Sonneberg",
    "sg:phone":"+49 3675/703063",
    "sg:postcode":"96515",
    "sg:province":"Th\u00fcringen",
    "wof:name":"Ingolf Fischer",
    "wof:placetype":"venue"
},
  "geometry": {"coordinates":[11.176054,50.364471],"type":"Point"}
}