{
  "type": "Feature",
  "properties": {
    "iso:country":"DE",
    "sg:address":"Heegerm\u00fchler Str. 13",
    "sg:city":"Eberswalde",
    "sg:postcode":"16225",
    "sg:province":"Brandenburg",
    "wof:name":"Lvm-versicherungsb\u00fcro",
    "wof:placetype":"venue"
},
  "geometry": {"coordinates":[13.7921218872,52.8354454041],"type":"Point"}
}