{
  "type": "Feature",
  "properties": {
    "iso:country":"DE",
    "sg:address":"Sedanstr. 19",
    "sg:city":"Hamburg",
    "sg:phone":"+49 40/41233771",
    "sg:postcode":"20146",
    "sg:province":"Hamburg",
    "wof:name":"Universit\u00e4t Hamburg Fachbereich Evangelische",
    "wof:placetype":"venue"
},
  "geometry": {"coordinates":[9.977579,53.569366],"type":"Point"}
}