{
  "type": "Feature",
  "properties": {
    "iso:country":"DE",
    "sg:address":"Inkelthalerhof",
    "sg:city":"Rockenhausen",
    "sg:postcode":"67806",
    "sg:province":"Rheinland-Pfalz",
    "wof:name":"Ambulante Dienste Zoar Ggmbh",
    "wof:placetype":"venue"
},
  "geometry": {"coordinates":[7.802696,49.632267],"type":"Point"}
}