{
  "type": "Feature",
  "properties": {
    "iso:country":"DE",
    "sg:address":"Mittelstr. 68",
    "sg:city":"Neuwied",
    "sg:phone":"+49 2631/25425",
    "sg:postcode":"56564",
    "sg:province":"Rheinland-Pfalz",
    "wof:name":"Erika Cress",
    "wof:placetype":"venue"
},
  "geometry": {"coordinates":[7.4616231918,50.4297447205],"type":"Point"}
}