{
  "type": "Feature",
  "properties": {
    "iso:country":"DE",
    "sg:address":"Sandweg 8",
    "sg:city":"Hann. M\u00fcnden",
    "sg:phone":"+49 5544/1035",
    "sg:postcode":"34346",
    "sg:province":"Niedersachsen",
    "wof:name":"Ewald Lotze",
    "wof:placetype":"venue"
},
  "geometry": {"coordinates":[9.608707428,51.4993133545],"type":"Point"}
}