{
  "type": "Feature",
  "properties": {
    "iso:country":"DE",
    "sg:address":"Alte Teichstr. 25",
    "sg:city":"Bad Rothenfelde",
    "sg:phone":"+49 5424/4554",
    "sg:postcode":"49214",
    "sg:province":"Niedersachsen",
    "wof:name":"Dedo M\u00fcller",
    "wof:placetype":"venue"
},
  "geometry": {"coordinates":[8.139398,52.09306],"type":"Point"}
}