{
  "type": "Feature",
  "properties": {
    "iso:country":"DE",
    "sg:address":"Siemensstr. 17",
    "sg:city":"Buchen",
    "sg:phone":"+49 6281/52080",
    "sg:postcode":"74722",
    "sg:province":"Baden-W\u00fcrttemberg",
    "wof:name":"Wei\u00df Gmbh",
    "wof:placetype":"venue"
},
  "geometry": {"coordinates":[9.3409013748,49.5295143127],"type":"Point"}
}