{
  "type": "Feature",
  "properties": {
    "iso:country":"DE",
    "sg:address":"Bei der Neuen M\u00fcnze 8",
    "sg:city":"Hamburg",
    "sg:phone":"+49 40/6794570",
    "sg:postcode":"22145",
    "sg:province":"Hamburg",
    "wof:name":"Otto Jahncke Gmbh",
    "wof:placetype":"venue"
},
  "geometry": {"coordinates":[10.1513767242,53.6226348877],"type":"Point"}
}