{
  "type": "Feature",
  "properties": {
    "iso:country":"DE",
    "sg:address":"Vogteistr. 7",
    "sg:city":"Recke",
    "sg:phone":"+49 5453/3276",
    "sg:postcode":"49509",
    "sg:province":"Nordrhein-Westfalen",
    "wof:name":"Bernhard Strootmann Bauschlosserei",
    "wof:placetype":"venue"
},
  "geometry": {"coordinates":[7.718556,52.370571],"type":"Point"}
}