{
  "type": "Feature",
  "properties": {
    "iso:country":"DE",
    "sg:address":"Rilkestr. 6 a",
    "sg:city":"Weinheim",
    "sg:phone":"+49 6201/53653",
    "sg:postcode":"69469",
    "sg:province":"Baden-W\u00fcrttemberg",
    "wof:name":"Herbert Walker",
    "wof:placetype":"venue"
},
  "geometry": {"coordinates":[8.6646881104,49.5367546082],"type":"Point"}
}