{
  "type": "Feature",
  "properties": {
    "iso:country":"DE",
    "sg:address":"Atenser Allee 108",
    "sg:city":"Nordenham",
    "sg:phone":"+49 4731/24023",
    "sg:postcode":"26954",
    "sg:province":"Niedersachsen",
    "wof:name":"Ph Textilreinigungs Gmbh",
    "wof:placetype":"venue"
},
  "geometry": {"coordinates":[8.476051,53.498795],"type":"Point"}
}