{
  "type": "Feature",
  "properties": {
    "iso:country":"DE",
    "sg:address":"Els\u00e4sser Str. 35",
    "sg:city":"Stuttgart",
    "sg:phone":"+49 711/879164",
    "sg:postcode":"70435",
    "sg:province":"Baden-W\u00fcrttemberg",
    "wof:name":"Mercedes Cafe Pub",
    "wof:placetype":"venue"
},
  "geometry": {"coordinates":[9.169508934,48.830078125],"type":"Point"}
}