{
  "type": "Feature",
  "properties": {
    "iso:country":"DE",
    "sg:address":"Hauptstr. 10",
    "sg:city":"D\u00fclmen",
    "sg:phone":"+49 2548/934155",
    "sg:postcode":"48249",
    "sg:province":"Nordrhein-Westfalen",
    "wof:name":"Restaurant Dorfkrug",
    "wof:placetype":"venue"
},
  "geometry": {"coordinates":[7.2793478966,51.8287849426],"type":"Point"}
}