{
  "type": "Feature",
  "properties": {
    "iso:country":"DE",
    "sg:address":"Pforzheimer Str. 314",
    "sg:city":"Stuttgart",
    "sg:phone":"+49 711/8894665",
    "sg:postcode":"70499",
    "sg:province":"Baden-W\u00fcrttemberg",
    "wof:name":"Uhland-apotheke",
    "wof:placetype":"venue"
},
  "geometry": {"coordinates":[9.119623,48.814365],"type":"Point"}
}