{
  "type": "Feature",
  "properties": {
    "iso:country":"DE",
    "sg:address":"Flughafenstr. 52",
    "sg:city":"Hamburg",
    "sg:phone":"+49 40/38611680",
    "sg:postcode":"22335",
    "sg:province":"Hamburg",
    "wof:name":"Jose Luis De Mora",
    "wof:placetype":"venue"
},
  "geometry": {"coordinates":[10.0150022507,53.6400413513],"type":"Point"}
}