{
  "type": "Feature",
  "properties": {
    "iso:country":"DE",
    "sg:address":"Mittlerer Weinberg 10",
    "sg:city":"Freigericht",
    "sg:phone":"+49 6055/909824",
    "sg:postcode":"63579",
    "sg:province":"Hessen",
    "wof:name":"Blitz-r@@b",
    "wof:placetype":"venue"
},
  "geometry": {"coordinates":[9.145617,50.144855],"type":"Point"}
}