{
  "type": "Feature",
  "properties": {
    "iso:country":"DE",
    "sg:address":"Waldstr. 2",
    "sg:city":"Billigheim-Ingenheim",
    "sg:phone":"+49 6349/6467",
    "sg:postcode":"76831",
    "sg:province":"Rheinland-Pfalz",
    "wof:name":"Hermann Bangerth",
    "wof:placetype":"venue"
},
  "geometry": {"coordinates":[8.0931119919,49.1286811829],"type":"Point"}
}