{
  "type": "Feature",
  "properties": {
    "iso:country":"DE",
    "sg:address":"Stauffenbergstr. 2",
    "sg:city":"Ingolstadt",
    "sg:phone":"+49 841/680327",
    "sg:postcode":"85051",
    "sg:province":"Bayern",
    "wof:name":"Verlag Bayer Anzeigenbl\u00e4tter Gmbh",
    "wof:placetype":"venue"
},
  "geometry": {"coordinates":[11.4318246841,48.7580490112],"type":"Point"}
}