{
  "type": "Feature",
  "properties": {
    "iso:country":"DE",
    "sg:address":"Im Boden 10",
    "sg:city":"Hattersheim",
    "sg:phone":"+49 6190/3944",
    "sg:postcode":"65795",
    "sg:province":"Hessen",
    "wof:name":"G. Och",
    "wof:placetype":"venue"
},
  "geometry": {"coordinates":[8.48313,50.06448],"type":"Point"}
}