{
  "type": "Feature",
  "properties": {
    "iso:country":"DE",
    "sg:address":"Hiltrops Kamp 7",
    "sg:city":"Essen",
    "sg:phone":"+49 4920/1515001",
    "sg:postcode":"45276",
    "sg:province":"Nordrhein-Westfalen",
    "wof:name":"Heinz Sperling Gmbh",
    "wof:placetype":"venue"
},
  "geometry": {"coordinates":[7.067068,51.448467],"type":"Point"}
}