{
  "type": "Feature",
  "properties": {
    "iso:country":"DE",
    "sg:address":"Am M\u00fchlgraben 2",
    "sg:city":"Hungen",
    "sg:phone":"+49 6402/52270",
    "sg:postcode":"35410",
    "sg:province":"Hessen",
    "wof:name":"Romatec Rohstoffe Gmbh",
    "wof:placetype":"venue"
},
  "geometry": {"coordinates":[8.911072,50.476009],"type":"Point"}
}