{
  "type": "Feature",
  "properties": {
    "iso:country":"DE",
    "sg:address":"An der Gerberei 5",
    "sg:city":"Hellenthal",
    "sg:phone":"+49 2482/7027",
    "sg:postcode":"53940",
    "sg:province":"Nordrhein-Westfalen",
    "wof:name":"F. Axmacher",
    "wof:placetype":"venue"
},
  "geometry": {"coordinates":[6.4335708618,50.4886512756],"type":"Point"}
}