{
  "type": "Feature",
  "properties": {
    "iso:country":"DE",
    "sg:address":"Ringstr. 51",
    "sg:city":"Neumarkt",
    "sg:phone":"+49 9181/6085",
    "sg:postcode":"92318",
    "sg:province":"Bayern",
    "wof:name":"Autoverleih Maria Kohlmann",
    "wof:placetype":"venue"
},
  "geometry": {"coordinates":[11.454562,49.279018],"type":"Point"}
}