{
  "type": "Feature",
  "properties": {
    "iso:country":"DE",
    "sg:address":"Obere Moosschwaigestr. 10c",
    "sg:city":"Dachau",
    "sg:phone":"+49 8131/20909",
    "sg:postcode":"85221",
    "sg:province":"Bayern",
    "wof:name":"Dr. Klaus-j\u00fcrgen Milke Tierarzt",
    "wof:placetype":"venue"
},
  "geometry": {"coordinates":[11.446187973,48.256023407],"type":"Point"}
}