{
  "type": "Feature",
  "properties": {
    "iso:country":"DE",
    "sg:address":"Vorbachzimmerner Str. 1",
    "sg:city":"Niederstetten",
    "sg:phone":"+49 7932/7128",
    "sg:postcode":"97996",
    "sg:province":"Baden-W\u00fcrttemberg",
    "wof:name":"Herbst Gmbh",
    "wof:placetype":"venue"
},
  "geometry": {"coordinates":[9.919193,49.402042],"type":"Point"}
}