{
  "type": "Feature",
  "properties": {
    "iso:country":"DE",
    "sg:city":"Schalkau",
    "sg:phone":"+49 3681/330",
    "sg:postcode":"96528",
    "sg:province":"Th\u00fcringen",
    "wof:name":"Deutsche Telekom T-punkt",
    "wof:placetype":"venue"
},
  "geometry": {"coordinates":[11.006597,50.394005],"type":"Point"}
}