{
  "type": "Feature",
  "properties": {
    "iso:country":"DE",
    "sg:address":"St\u00f6ckener Str. 31",
    "sg:city":"Hannover",
    "sg:postcode":"30419",
    "sg:province":"Niedersachsen",
    "wof:name":"Xonox Warenhandels-gmbh",
    "wof:placetype":"venue"
},
  "geometry": {"coordinates":[9.6717557907,52.3986206055],"type":"Point"}
}