{
  "type": "Feature",
  "properties": {
    "iso:country":"DE",
    "sg:address":"Ensdorf",
    "sg:city":"Ensdorf",
    "sg:phone":"+49 8064/1378",
    "sg:postcode":"83546",
    "sg:province":"Bayern",
    "wof:name":"G\u00e4stehaus Bernhard Kobsa",
    "wof:placetype":"venue"
},
  "geometry": {"coordinates":[-115.7887268066,46.4955596924],"type":"Point"}
}