{
  "type": "Feature",
  "properties": {
    "iso:country":"DE",
    "sg:address":"Rosenheimer Str. 19",
    "sg:city":"Oberaudorf",
    "sg:phone":"+49 8033/2843",
    "sg:postcode":"83080",
    "sg:province":"Bayern",
    "wof:name":"Pizzeria Eiscafe Christina",
    "wof:placetype":"venue"
},
  "geometry": {"coordinates":[12.172478,47.649578],"type":"Point"}
}