{
  "type": "Feature",
  "properties": {
    "iso:country":"DE",
    "sg:address":"Kajetan-Koller-Weg 25",
    "sg:city":"Hechingen",
    "sg:phone":"+49 7471/5455",
    "sg:postcode":"72379",
    "sg:province":"Baden-W\u00fcrttemberg",
    "wof:name":"J\u00fcrgen Braun",
    "wof:placetype":"venue"
},
  "geometry": {"coordinates":[8.952427,48.341106],"type":"Point"}
}