{
  "type": "Feature",
  "properties": {
    "iso:country":"DE",
    "sg:address":"Ferdinand-Wagner-Str. 10",
    "sg:city":"Schwabm\u00fcnchen",
    "sg:phone":"+49 8232/4434",
    "sg:postcode":"86830",
    "sg:province":"Bayern",
    "wof:name":"Karl G. Weckmer",
    "wof:placetype":"venue"
},
  "geometry": {"coordinates":[10.7590074539,48.1783332825],"type":"Point"}
}