{
  "type": "Feature",
  "properties": {
    "iso:country":"DE",
    "sg:address":"Langendorfer Str.",
    "sg:city":"Wasserlosen",
    "sg:phone":"+49 9728/401",
    "sg:postcode":"97535",
    "sg:province":"Bayern",
    "wof:name":"Bay Wa Ag",
    "wof:placetype":"venue"
},
  "geometry": {"coordinates":[9.996798,50.056755],"type":"Point"}
}