{
  "type": "Feature",
  "properties": {
    "iso:country":"DE",
    "sg:address":"Stedinger Str. 85",
    "sg:city":"Oldenburg",
    "sg:phone":"+49 441/26599",
    "sg:postcode":"26135",
    "sg:province":"Niedersachsen",
    "wof:name":"Fre\u00dfnapf",
    "wof:placetype":"venue"
},
  "geometry": {"coordinates":[8.225715,53.129921],"type":"Point"}
}