{
  "type": "Feature",
  "properties": {
    "iso:country":"DE",
    "sg:address":"Eberbacher Str. 1",
    "sg:city":"Oestrich-Winkel",
    "sg:phone":"+49 6723/999585",
    "sg:postcode":"65375",
    "sg:province":"Hessen",
    "wof:name":"Peter J. Bug Weinanbau",
    "wof:placetype":"venue"
},
  "geometry": {"coordinates":[8.0341510773,50.025428772],"type":"Point"}
}