{
  "type": "Feature",
  "properties": {
    "iso:country":"DE",
    "sg:address":"Bewerungestr. 31",
    "sg:city":"Essen",
    "sg:phone":"+49 201/590784",
    "sg:postcode":"45276",
    "sg:province":"Nordrhein-Westfalen",
    "wof:name":"Fv-druck Fritz Volkwein",
    "wof:placetype":"venue"
},
  "geometry": {"coordinates":[7.078283,51.453094],"type":"Point"}
}