{
  "type": "Feature",
  "properties": {
    "iso:country":"DE",
    "sg:address":"Colonnaden 29",
    "sg:city":"Hamburg",
    "sg:phone":"+49 40/853910",
    "sg:postcode":"20354",
    "sg:province":"Hamburg",
    "wof:name":"Boston Piano Gmbh",
    "wof:placetype":"venue"
},
  "geometry": {"coordinates":[9.9900350571,53.5567169189],"type":"Point"}
}