{
  "type": "Feature",
  "properties": {
    "iso:country":"DE",
    "sg:address":"Uellendahler Str. 691",
    "sg:city":"Wuppertal",
    "sg:phone":"+49 202/701600",
    "sg:postcode":"42281",
    "sg:province":"Nordrhein-Westfalen",
    "wof:name":"Pfannkuchenhaus",
    "wof:placetype":"venue"
},
  "geometry": {"coordinates":[7.1746001244,51.2896614075],"type":"Point"}
}