{
  "type": "Feature",
  "properties": {
    "iso:country":"DE",
    "sg:address":"Onstmettinger Weg 5",
    "sg:city":"Stuttgart",
    "sg:phone":"+49 711/733984",
    "sg:postcode":"70567",
    "sg:province":"Baden-W\u00fcrttemberg",
    "wof:name":"Kurt Laib Architekt",
    "wof:placetype":"venue"
},
  "geometry": {"coordinates":[9.139865,48.733662],"type":"Point"}
}