{
  "type": "Feature",
  "properties": {
    "iso:country":"DE",
    "sg:address":"Georg-Leinfelder-Str. 23",
    "sg:city":"Schrobenhausen",
    "sg:phone":"+49 8252/83772",
    "sg:postcode":"86529",
    "sg:province":"Bayern",
    "wof:name":"Hermann Beyer",
    "wof:placetype":"venue"
},
  "geometry": {"coordinates":[11.272797,48.559933],"type":"Point"}
}