{
  "type": "Feature",
  "properties": {
    "iso:country":"DE",
    "sg:address":"Holstenstr. 194a",
    "sg:city":"Hamburg",
    "sg:phone":"+49 40/389704",
    "sg:postcode":"22765",
    "sg:province":"Hamburg",
    "wof:name":"Karen G\u00f6ttsche Steuerberater",
    "wof:placetype":"venue"
},
  "geometry": {"coordinates":[9.9476900101,53.5606460571],"type":"Point"}
}