{
  "type": "Feature",
  "properties": {
    "iso:country":"DE",
    "sg:address":"Breidenbacherstr. 13",
    "sg:city":"Mainz",
    "sg:phone":"+49 6131/228638",
    "sg:postcode":"55116",
    "sg:province":"Rheinland-Pfalz",
    "wof:name":"Zentrum F\u00fcr Rheuma- Pathologie Gemeinn\u00fctzige",
    "wof:placetype":"venue"
},
  "geometry": {"coordinates":[8.267080307,49.9965896606],"type":"Point"}
}