{
  "type": "Feature",
  "properties": {
    "iso:country":"DE",
    "sg:address":"Jesinger Str. 15",
    "sg:city":"Kirchheim",
    "sg:phone":"+49 7021/74460",
    "sg:postcode":"73230",
    "sg:province":"Baden-W\u00fcrttemberg",
    "wof:name":"Gerold Miller Praxis F\u00fcr Ergotherapie",
    "wof:placetype":"venue"
},
  "geometry": {"coordinates":[9.455972,48.646694],"type":"Point"}
}