{
  "type": "Feature",
  "properties": {
    "iso:country":"DE",
    "sg:city":"Oberdachstetten",
    "sg:phone":"+49 9845/96969",
    "sg:postcode":"91617",
    "sg:province":"Bayern",
    "wof:name":"Ambulante Kranken- Und Altenpflege",
    "wof:placetype":"venue"
},
  "geometry": {"coordinates":[10.42311,49.415386],"type":"Point"}
}