{
  "type": "Feature",
  "properties": {
    "iso:country":"DE",
    "sg:address":"Zinnstr. 1",
    "sg:city":"Aue",
    "sg:phone":"+49 3771/54555",
    "sg:postcode":"08280",
    "sg:province":"Sachsen",
    "wof:name":"Datapoint Gmbh & Co. Vertriebs Kg",
    "wof:placetype":"venue"
},
  "geometry": {"coordinates":[12.6940612793,50.5821800232],"type":"Point"}
}