{
  "type": "Feature",
  "properties": {
    "iso:country":"DE",
    "sg:address":"Hochdahler Str. 113",
    "sg:city":"Hilden",
    "sg:phone":"+49 2103/42300",
    "sg:postcode":"40724",
    "sg:province":"Nordrhein-Westfalen",
    "wof:name":"Meer Und Mehr",
    "wof:placetype":"venue"
},
  "geometry": {"coordinates":[6.9391608238,51.1757774353],"type":"Point"}
}