{
  "type": "Feature",
  "properties": {
    "iso:country":"DE",
    "sg:address":"Mieterkinger Str. 50",
    "sg:city":"Bad Saulgau",
    "sg:phone":"+49 7581/8425",
    "sg:postcode":"88348",
    "sg:province":"Baden-W\u00fcrttemberg",
    "wof:name":"K. Harsch",
    "wof:placetype":"venue"
},
  "geometry": {"coordinates":[9.4482049942,48.0273017883],"type":"Point"}
}