{
  "type": "Feature",
  "properties": {
    "iso:country":"DE",
    "sg:address":"Wallbergstr. 1",
    "sg:city":"Taufkirchen",
    "sg:phone":"+49 89/6144840",
    "sg:postcode":"82024",
    "sg:province":"Bayern",
    "wof:name":"Infoplan Ges F\u00dcr Informationssysteme Mbh",
    "wof:placetype":"venue"
},
  "geometry": {"coordinates":[11.614799,48.03265],"type":"Point"}
}