{
  "type": "Feature",
  "properties": {
    "iso:country":"DE",
    "sg:address":"Am Binnendamm",
    "sg:city":"Bobenheim-Roxheim",
    "sg:phone":"+49 6239/99600",
    "sg:postcode":"67240",
    "sg:province":"Rheinland-Pfalz",
    "wof:name":"Theodor Kleiner Gmbh & Co. Kg",
    "wof:placetype":"venue"
},
  "geometry": {"coordinates":[8.3722696304,49.5881309509],"type":"Point"}
}