{
  "type": "Feature",
  "properties": {
    "iso:country":"DE",
    "sg:address":"Doblerstr. 8",
    "sg:city":"T\u00fcbingen",
    "sg:phone":"+49 7071/27411",
    "sg:postcode":"72074",
    "sg:province":"Baden-W\u00fcrttemberg",
    "wof:name":"Ilse Noel Steuerbevollm\u00e4chtigte",
    "wof:placetype":"venue"
},
  "geometry": {"coordinates":[9.059217453,48.521686554],"type":"Point"}
}