{
  "type": "Feature",
  "properties": {
    "iso:country":"DE",
    "sg:address":"Moerser Str. 180",
    "sg:city":"Duisburg",
    "sg:phone":"+49 2845/4363",
    "sg:postcode":"47198",
    "sg:province":"Nordrhein-Westfalen",
    "wof:name":"Rosemarie Vierbaum",
    "wof:placetype":"venue"
},
  "geometry": {"coordinates":[6.690973,51.44976],"type":"Point"}
}