{
  "type": "Feature",
  "properties": {
    "iso:country":"DE",
    "sg:address":"Dr.-H\u00f6nlein-Str. 8",
    "sg:city":"Lohr",
    "sg:phone":"+49 9352/3122",
    "sg:postcode":"97816",
    "sg:province":"Bayern",
    "wof:name":"Heiby Fremdsprachen-dienst",
    "wof:placetype":"venue"
},
  "geometry": {"coordinates":[9.590415,50.008057],"type":"Point"}
}