{
  "type": "Feature",
  "properties": {
    "iso:country":"DE",
    "sg:address":"Saarstr. 17",
    "sg:city":"Berlin",
    "sg:phone":"+49 30/8515750",
    "sg:postcode":"12161",
    "sg:province":"Berlin",
    "wof:name":"Klaus Tomasik",
    "wof:placetype":"venue"
},
  "geometry": {"coordinates":[13.334877,52.468315],"type":"Point"}
}