{
  "type": "Feature",
  "properties": {
    "iso:country":"DE",
    "sg:address":"Hauptstr. 165",
    "sg:city":"Hemer",
    "sg:phone":"+49 2372/16644",
    "sg:postcode":"58675",
    "sg:province":"Nordrhein-Westfalen",
    "wof:name":"Ch. Ipach",
    "wof:placetype":"venue"
},
  "geometry": {"coordinates":[7.7669949532,51.3830299377],"type":"Point"}
}