{
  "type": "Feature",
  "properties": {
    "iso:country":"DE",
    "sg:address":"Oberbuchstr. 24",
    "sg:city":"Ehingen",
    "sg:phone":"+49 7391/70870",
    "sg:postcode":"89584",
    "sg:province":"Baden-W\u00fcrttemberg",
    "wof:name":"B\u00fcrgerwache Ehingen E. V. Harald Neu",
    "wof:placetype":"venue"
},
  "geometry": {"coordinates":[9.6934747696,48.2854690552],"type":"Point"}
}