{
  "type": "Feature",
  "properties": {
    "iso:country":"DE",
    "sg:address":"Sportplatzstr. 20",
    "sg:city":"Dahn",
    "sg:phone":"+49 6391/3548",
    "sg:postcode":"66994",
    "sg:province":"Rheinland-Pfalz",
    "wof:name":"Fc 1913 Dahn Fu\u00dfballverein",
    "wof:placetype":"venue"
},
  "geometry": {"coordinates":[7.7730498314,49.1478309631],"type":"Point"}
}