{
  "type": "Feature",
  "properties": {
    "iso:country":"DE",
    "sg:address":"Wilhelmstr. 62",
    "sg:city":"H\u00fcnxe",
    "sg:phone":"+49 2858/2334",
    "sg:postcode":"46569",
    "sg:province":"Nordrhein-Westfalen",
    "wof:name":"Friedrich Kaldewey",
    "wof:placetype":"venue"
},
  "geometry": {"coordinates":[6.776193,51.626247],"type":"Point"}
}