{
  "type": "Feature",
  "properties": {
    "iso:country":"DE",
    "sg:address":"Schlenkestr. 11",
    "sg:city":"Kreuztal",
    "sg:phone":"+49 2732/1691",
    "sg:postcode":"57223",
    "sg:province":"Nordrhein-Westfalen",
    "wof:name":"Werner Rother",
    "wof:placetype":"venue"
},
  "geometry": {"coordinates":[8.006497,50.964199],"type":"Point"}
}