{
  "type": "Feature",
  "properties": {
    "iso:country":"DE",
    "sg:address":"Lommatzscher Str. 18",
    "sg:city":"D\u00f6beln",
    "sg:phone":"+49 3431/701192",
    "sg:postcode":"04720",
    "sg:province":"Sachsen",
    "wof:name":"U. Ullmann",
    "wof:placetype":"venue"
},
  "geometry": {"coordinates":[13.139084816,51.1235466003],"type":"Point"}
}