{
  "type": "Feature",
  "properties": {
    "iso:country":"DE",
    "sg:address":"Landgraben 27",
    "sg:city":"Alfter",
    "sg:phone":"+49 2222/3360",
    "sg:postcode":"53347",
    "sg:province":"Nordrhein-Westfalen",
    "wof:name":"H. Frieder & Sohn Gmbh",
    "wof:placetype":"venue"
},
  "geometry": {"coordinates":[7.0133957863,50.7354125977],"type":"Point"}
}