{
  "type": "Feature",
  "properties": {
    "iso:country":"DE",
    "sg:address":"Nelkenstr. 36",
    "sg:city":"Euskirchen",
    "sg:phone":"+49 2251/6968",
    "sg:postcode":"53881",
    "sg:province":"Nordrhein-Westfalen",
    "wof:name":"Poststube",
    "wof:placetype":"venue"
},
  "geometry": {"coordinates":[6.8116559982,50.6426582336],"type":"Point"}
}