{
  "type": "Feature",
  "properties": {
    "iso:country":"DE",
    "sg:address":"Theener Oststreek 4",
    "sg:city":"Hagermarsch",
    "sg:postcode":"26524",
    "sg:province":"Niedersachsen",
    "wof:name":"Jelto Noosten",
    "wof:placetype":"venue"
},
  "geometry": {"coordinates":[7.292482,53.661087],"type":"Point"}
}