{
  "type": "Feature",
  "properties": {
    "iso:country":"DE",
    "sg:address":"\u00c4u\u00dfere Sulzbacher Str. 59",
    "sg:city":"N\u00fcrnberg",
    "sg:phone":"+49 911/959680",
    "sg:postcode":"90491",
    "sg:province":"Bayern",
    "wof:name":"Dipl.-ing. Georg Beck Ingenieur",
    "wof:placetype":"venue"
},
  "geometry": {"coordinates":[11.1108989716,49.4617729187],"type":"Point"}
}