{
  "type": "Feature",
  "properties": {
    "iso:country":"DE",
    "sg:address":"Karl-Roth-Str. 23",
    "sg:city":"Dresden",
    "sg:phone":"+49 351/3100924",
    "sg:postcode":"01309",
    "sg:province":"Sachsen",
    "wof:name":"Manfred Drescher",
    "wof:placetype":"venue"
},
  "geometry": {"coordinates":[13.7839355469,51.0389633179],"type":"Point"}
}