{
  "type": "Feature",
  "properties": {
    "iso:country":"DE",
    "sg:address":"K\u00f6nigsberger Str. 19",
    "sg:city":"Lindhorst",
    "sg:phone":"+49 5725/913700",
    "sg:postcode":"31698",
    "sg:province":"Niedersachsen",
    "wof:name":"Manthey",
    "wof:placetype":"venue"
},
  "geometry": {"coordinates":[9.2763471603,52.3625946045],"type":"Point"}
}