{
  "type": "Feature",
  "properties": {
    "iso:country":"DE",
    "sg:address":"Sonnenwall 85 POSTFACH 100852",
    "sg:city":"Duisburg",
    "sg:phone":"+49 4920/33090",
    "sg:postcode":"47008",
    "sg:province":"Nordrhein-Westfalen",
    "wof:name":"Rwe Industrie-l\u00d6sungen Gmbh",
    "wof:placetype":"venue"
},
  "geometry": {"coordinates":[6.758239,51.431034],"type":"Point"}
}