{
  "type": "Feature",
  "properties": {
    "iso:country":"DE",
    "sg:address":"Heidloh 2",
    "sg:city":"Celle",
    "sg:phone":"+49 4951/4153041",
    "sg:postcode":"29223",
    "sg:province":"Niedersachsen",
    "wof:name":"Palm, Viag Und Gprs",
    "wof:placetype":"venue"
},
  "geometry": {"coordinates":[10.030444,52.639347],"type":"Point"}
}