{
  "type": "Feature",
  "properties": {
    "iso:country":"DE",
    "sg:address":"Kirchstr. 28",
    "sg:city":"N\u00fcrtingen",
    "sg:phone":"+49 4970/2234055",
    "sg:postcode":"72622",
    "sg:province":"Baden-W\u00fcrttemberg",
    "wof:name":"Baden-w\u00fcrttembergische Bank Ag",
    "wof:placetype":"venue"
},
  "geometry": {"coordinates":[9.340543,48.626102],"type":"Point"}
}