{
  "type": "Feature",
  "properties": {
    "iso:country":"DE",
    "sg:address":"Schopenhauerstr. 2",
    "sg:city":"Potsdam",
    "sg:postcode":"14467",
    "sg:province":"Brandenburg",
    "wof:name":"Dr. Grupe Au\u00dfenwerbung Gmbh & Co.",
    "wof:placetype":"venue"
},
  "geometry": {"coordinates":[13.0483703613,52.398651123],"type":"Point"}
}