{
  "type": "Feature",
  "properties": {
    "iso:country":"DE",
    "sg:address":"Flandersbacher Str. 107",
    "sg:city":"W\u00fclfrath",
    "sg:phone":"+49 2058/4542",
    "sg:postcode":"42489",
    "sg:province":"Nordrhein-Westfalen",
    "wof:name":"Ernst-otto Kirberg",
    "wof:placetype":"venue"
},
  "geometry": {"coordinates":[7.004611,51.305298],"type":"Point"}
}