{
  "type": "Feature",
  "properties": {
    "iso:country":"DE",
    "sg:address":"Unnerweg 34",
    "sg:city":"Kirkel",
    "sg:phone":"+49 6849/375",
    "sg:postcode":"66459",
    "sg:province":"Saarland",
    "wof:name":"Herbert Sommer",
    "wof:placetype":"venue"
},
  "geometry": {"coordinates":[7.2266921997,49.2814483643],"type":"Point"}
}