{
  "type": "Feature",
  "properties": {
    "iso:country":"DE",
    "sg:address":"Peter-und-Paul-Str. 10",
    "sg:city":"Rheinfelden",
    "sg:phone":"+49 7623/5453",
    "sg:postcode":"79618",
    "sg:province":"Baden-W\u00fcrttemberg",
    "wof:name":"Gr\u00fcnkompostieranlagen Ewald L\u00fctzelschwab Gmbh",
    "wof:placetype":"venue"
},
  "geometry": {"coordinates":[7.79136,47.592136],"type":"Point"}
}