{
  "type": "Feature",
  "properties": {
    "iso:country":"DE",
    "sg:address":"Otfried-M\u00fcller-Str. 10",
    "sg:city":"T\u00fcbingen",
    "sg:postcode":"72076",
    "sg:province":"Baden-W\u00fcrttemberg",
    "wof:name":"Kks-ukt Ggmbh",
    "wof:placetype":"venue"
},
  "geometry": {"coordinates":[9.0406112671,48.5298080444],"type":"Point"}
}