{
  "type": "Feature",
  "properties": {
    "iso:country":"DE",
    "sg:address":"Auf Wies 28",
    "sg:city":"Reutlingen",
    "sg:phone":"+49 7121/45483",
    "sg:postcode":"72766",
    "sg:province":"Baden-W\u00fcrttemberg",
    "wof:name":"Klaus Tr\u00f6ster Anlageberater",
    "wof:placetype":"venue"
},
  "geometry": {"coordinates":[9.2201814651,48.5159759521],"type":"Point"}
}