{
  "type": "Feature",
  "properties": {
    "iso:country":"DE",
    "sg:address":"Ludwigstr. 8",
    "sg:city":"Darmstadt",
    "sg:phone":"+49 6151/24233",
    "sg:postcode":"64283",
    "sg:province":"Hessen",
    "wof:name":"Sexologie-heguwa",
    "wof:placetype":"venue"
},
  "geometry": {"coordinates":[8.6553525925,49.8716316223],"type":"Point"}
}