{
  "type": "Feature",
  "properties": {
    "iso:country":"DE",
    "sg:address":"Homberger Str. 2",
    "sg:city":"Moers",
    "sg:phone":"+49 2841/22525",
    "sg:postcode":"47441",
    "sg:province":"Nordrhein-Westfalen",
    "wof:name":"Vertrauens\u00e4rztlicher-dienst D. Lva Rheinprovinz",
    "wof:placetype":"venue"
},
  "geometry": {"coordinates":[6.6293778419,51.4507751465],"type":"Point"}
}