{
  "type": "Feature",
  "properties": {
    "iso:country":"DE",
    "sg:address":"Nr. 240",
    "sg:city":"Asendorf",
    "sg:postcode":"27330",
    "sg:province":"Niedersachsen",
    "wof:name":"Hoyaer Ferkelaufzucht Gmbh & Co. Kg",
    "wof:placetype":"venue"
},
  "geometry": {"coordinates":[9.0045347214,52.7725715637],"type":"Point"}
}