{
  "type": "Feature",
  "properties": {
    "iso:country":"DE",
    "sg:address":"Sonthofener Str. 5",
    "sg:city":"Immenstadt",
    "sg:phone":"+49 8323/96470",
    "sg:postcode":"87509",
    "sg:province":"Bayern",
    "wof:name":"Metzgerei M\u00fcller Gmbh",
    "wof:placetype":"venue"
},
  "geometry": {"coordinates":[10.2188453674,47.5616035461],"type":"Point"}
}