{
  "type": "Feature",
  "properties": {
    "iso:country":"DE",
    "sg:address":"Robert-Bosch-Str. 13",
    "sg:city":"Wegberg",
    "sg:phone":"+49 2434/5901",
    "sg:postcode":"41844",
    "sg:province":"Nordrhein-Westfalen",
    "wof:name":"Anna B. Hausverwaltung Gmbh",
    "wof:placetype":"venue"
},
  "geometry": {"coordinates":[6.3274149895,51.1141624451],"type":"Point"}
}