{
  "type": "Feature",
  "properties": {
    "iso:country":"DE",
    "sg:address":"Up de Bookholt 28",
    "sg:city":"Vreden",
    "sg:phone":"+49 2564/1322",
    "sg:postcode":"48691",
    "sg:province":"Nordrhein-Westfalen",
    "wof:name":"Hotelrestaurant Hamaland",
    "wof:placetype":"venue"
},
  "geometry": {"coordinates":[6.8175010681,52.0332527161],"type":"Point"}
}