{
  "type": "Feature",
  "properties": {
    "iso:country":"DE",
    "sg:address":"Hohenstaufenstr. 2",
    "sg:city":"Eberbach",
    "sg:phone":"+49 6271/2534",
    "sg:postcode":"69412",
    "sg:province":"Baden-W\u00fcrttemberg",
    "wof:name":"Friedrich M\u00fcller Holzbau Gmbh",
    "wof:placetype":"venue"
},
  "geometry": {"coordinates":[8.990606,49.465992],"type":"Point"}
}