{
  "type": "Feature",
  "properties": {
    "iso:country":"DE",
    "sg:address":"Im Unteren Angel 33",
    "sg:city":"Offenburg",
    "sg:phone":"+49 781/24980",
    "sg:postcode":"77652",
    "sg:province":"Baden-W\u00fcrttemberg",
    "wof:name":"H. Leonhardt",
    "wof:placetype":"venue"
},
  "geometry": {"coordinates":[7.9327030182,48.4791374207],"type":"Point"}
}