{
  "type": "Feature",
  "properties": {
    "iso:country":"DE",
    "sg:address":"Jahnweg 5",
    "sg:city":"Kressbronn",
    "sg:phone":"+49 7543/8563",
    "sg:postcode":"88079",
    "sg:province":"Baden-W\u00fcrttemberg",
    "wof:name":"Manfred Brugger",
    "wof:placetype":"venue"
},
  "geometry": {"coordinates":[9.5989847183,47.5925216675],"type":"Point"}
}