{
  "type": "Feature",
  "properties": {
    "iso:country":"DE",
    "sg:address":"Unterer Geisberg 24",
    "sg:city":"Saarbr\u00fccken",
    "sg:phone":"+49 681/894362",
    "sg:postcode":"66121",
    "sg:province":"Saarland",
    "wof:name":"Deko-team Kunz",
    "wof:placetype":"venue"
},
  "geometry": {"coordinates":[7.0502338409,49.2259101868],"type":"Point"}
}