{
  "type": "Feature",
  "properties": {
    "iso:country":"DE",
    "sg:address":"Weidgang 3",
    "sg:city":"Hilzingen",
    "sg:phone":"+49 7731/62721",
    "sg:postcode":"78247",
    "sg:province":"Baden-W\u00fcrttemberg",
    "wof:name":"Bistro A 81",
    "wof:placetype":"venue"
},
  "geometry": {"coordinates":[8.7996053696,47.7626647949],"type":"Point"}
}