{
  "type": "Feature",
  "properties": {
    "iso:country":"DE",
    "sg:address":"Leipziger Str 63",
    "sg:city":"Wuppertal",
    "sg:phone":"+49 202/751310",
    "sg:postcode":"42109",
    "sg:province":"Nordrhein-Westfalen",
    "wof:name":"H. Mersmann",
    "wof:placetype":"venue"
},
  "geometry": {"coordinates":[7.152373,51.27739],"type":"Point"}
}