{
  "type": "Feature",
  "properties": {
    "iso:country":"DE",
    "sg:address":"Harzweg 12",
    "sg:city":"Quedlinburg",
    "sg:phone":"+49 3946/702016",
    "sg:postcode":"06484",
    "sg:province":"Sachsen-Anhalt",
    "wof:name":"B. Pflug",
    "wof:placetype":"venue"
},
  "geometry": {"coordinates":[11.1479940414,51.783870697],"type":"Point"}
}