{
  "type": "Feature",
  "properties": {
    "iso:country":"DE",
    "sg:address":"Kornstr. 19",
    "sg:city":"Seddiner See",
    "sg:phone":"+49 33205/46909",
    "sg:postcode":"14554",
    "sg:province":"Brandenburg",
    "wof:name":"Hans-joachim Wolf Architekt",
    "wof:placetype":"venue"
},
  "geometry": {"coordinates":[13.003801,52.265385],"type":"Point"}
}