{
  "type": "Feature",
  "properties": {
    "iso:country":"DE",
    "sg:address":"Zunftstr. 4",
    "sg:city":"Buchholz",
    "sg:phone":"+49 4181/33065",
    "sg:postcode":"21244",
    "sg:province":"Niedersachsen",
    "wof:name":"Willy Beisner",
    "wof:placetype":"venue"
},
  "geometry": {"coordinates":[9.8640041351,53.3469657898],"type":"Point"}
}