{
  "type": "Feature",
  "properties": {
    "iso:country":"DE",
    "sg:address":"Oberm\u00fcnsterstr. 6",
    "sg:city":"Regensburg",
    "sg:phone":"+49 941/55573",
    "sg:postcode":"93047",
    "sg:province":"Bayern",
    "wof:name":"Dr. G. Herzogenrath-amelung Rechtsanwalt",
    "wof:placetype":"venue"
},
  "geometry": {"coordinates":[12.0949878693,49.0165939331],"type":"Point"}
}