{
  "type": "Feature",
  "properties": {
    "iso:country":"DE",
    "sg:address":"Au\u00dferhalb 45",
    "sg:city":"Gro\u00df-Gerau",
    "sg:phone":"+49 6152/39506",
    "sg:postcode":"64521",
    "sg:province":"Hessen",
    "wof:name":"Campingplatz Niederwaldsee Kurt Und J\u00fcrgen Heil",
    "wof:placetype":"venue"
},
  "geometry": {"coordinates":[8.481933,49.922211],"type":"Point"}
}