{
  "type": "Feature",
  "properties": {
    "iso:country":"DE",
    "sg:address":"Humboldtstra\u00dfe 28",
    "sg:city":"Straubenhardt",
    "sg:phone":"+49 7082/92430",
    "sg:postcode":"75334",
    "sg:province":"Baden-W\u00fcrttemberg",
    "wof:name":"B\u00e4ckereimaschinen",
    "wof:placetype":"venue"
},
  "geometry": {"coordinates":[8.517691,48.843815],"type":"Point"}
}