{
  "type": "Feature",
  "properties": {
    "iso:country":"DE",
    "sg:address":"Wonnegaustr. 59",
    "sg:city":"Worms",
    "sg:phone":"+49 6242/99772",
    "sg:postcode":"67550",
    "sg:province":"Rheinland-Pfalz",
    "wof:name":"Wilfried Cleres",
    "wof:placetype":"venue"
},
  "geometry": {"coordinates":[8.2862930298,49.6768074036],"type":"Point"}
}