{
  "type": "Feature",
  "properties": {
    "iso:country":"DE",
    "sg:address":"Wilhelm-Potenberg-Str. 2",
    "sg:city":"Zinnowitz",
    "sg:phone":"+49 38377/4500",
    "sg:postcode":"17454",
    "sg:province":"Mecklenburg-Vorpommern",
    "wof:name":"Hotel Sanddorn",
    "wof:placetype":"venue"
},
  "geometry": {"coordinates":[13.9149446487,54.0778846741],"type":"Point"}
}