{
  "type": "Feature",
  "properties": {
    "iso:country":"DE",
    "sg:address":"S\u00fcdweststr. 8",
    "sg:city":"Memmingen",
    "sg:phone":"+49 8331/12720",
    "sg:postcode":"87700",
    "sg:province":"Bayern",
    "wof:name":"Bodo Haberkorn Ingenieur",
    "wof:placetype":"venue"
},
  "geometry": {"coordinates":[10.2040472031,48.012134552],"type":"Point"}
}