{
  "type": "Feature",
  "properties": {
    "iso:country":"DE",
    "sg:address":"Zum Diekkamp 1",
    "sg:city":"Bosau",
    "sg:phone":"+49 4527/99790",
    "sg:postcode":"23715",
    "sg:province":"Schleswig-Holstein",
    "wof:name":"C. Frerichs",
    "wof:placetype":"venue"
},
  "geometry": {"coordinates":[10.4986944199,54.1100692749],"type":"Point"}
}