{
  "type": "Feature",
  "properties": {
    "iso:country":"DE",
    "sg:address":"Le\u00dfbachweg 3",
    "sg:city":"Wei\u00dfenbrunn",
    "sg:phone":"+49 9261/530232",
    "sg:postcode":"96369",
    "sg:province":"Bayern",
    "wof:name":"Friedlein Kunststoff- Technik Gmbh",
    "wof:placetype":"venue"
},
  "geometry": {"coordinates":[11.353229,50.197895],"type":"Point"}
}