{
  "type": "Feature",
  "properties": {
    "iso:country":"DE",
    "sg:address":"Waldstr. 268",
    "sg:city":"Offenbach",
    "sg:phone":"+49 69/9854320",
    "sg:postcode":"63071",
    "sg:province":"Hessen",
    "wof:name":"Reifen-diehl",
    "wof:placetype":"venue"
},
  "geometry": {"coordinates":[8.7736558914,50.0841903687],"type":"Point"}
}