{
  "type": "Feature",
  "properties": {
    "iso:country":"DE",
    "sg:address":"Culemannstr. 1",
    "sg:city":"Minden",
    "sg:phone":"+49 571/42631",
    "sg:postcode":"32425",
    "sg:province":"Nordrhein-Westfalen",
    "wof:name":"Neuer Anker",
    "wof:placetype":"venue"
},
  "geometry": {"coordinates":[8.9144239426,52.3022956848],"type":"Point"}
}