{
  "type": "Feature",
  "properties": {
    "iso:country":"DE",
    "sg:address":"Donkweg 50",
    "sg:city":"Duisburg",
    "sg:phone":"+49 2151/408887",
    "sg:postcode":"47239",
    "sg:province":"Nordrhein-Westfalen",
    "wof:name":"Gabriele-maria Klose Steuerberater",
    "wof:placetype":"venue"
},
  "geometry": {"coordinates":[6.6507339478,51.3954353333],"type":"Point"}
}