{
  "type": "Feature",
  "properties": {
    "iso:country":"DE",
    "sg:address":"Simbacher Str. 18",
    "sg:city":"Rotthalm\u00fcnster",
    "sg:phone":"+49 8533/7873",
    "sg:postcode":"94094",
    "sg:province":"Bayern",
    "wof:name":"Anton Resch",
    "wof:placetype":"venue"
},
  "geometry": {"coordinates":[13.2018547058,48.3573760986],"type":"Point"}
}