{
  "type": "Feature",
  "properties": {
    "iso:country":"DE",
    "sg:address":"Bahnhofstr. 15",
    "sg:city":"Hillesheim",
    "sg:phone":"+49 6733/6131",
    "sg:postcode":"67586",
    "sg:province":"Rheinland-Pfalz",
    "wof:name":"N & Ntt Nierstheimer & Nierstheimer Telekommuni-",
    "wof:placetype":"venue"
},
  "geometry": {"coordinates":[8.2573308945,49.7751617432],"type":"Point"}
}