{
  "type": "Feature",
  "properties": {
    "iso:country":"DE",
    "sg:address":"Agnesstr. 61 III",
    "sg:city":"M\u00fcnchen",
    "sg:phone":"+49 89/180849",
    "sg:postcode":"80797",
    "sg:province":"Bayern",
    "wof:name":"U. Gr\u00e4fin Von Der Schulenburg",
    "wof:placetype":"venue"
},
  "geometry": {"coordinates":[11.55628,48.160809],"type":"Point"}
}