{
  "type": "Feature",
  "properties": {
    "iso:country":"DE",
    "sg:address":"Georgstr. 24",
    "sg:city":"Chemnitz",
    "sg:phone":"+49 371/412642",
    "sg:postcode":"09111",
    "sg:province":"Sachsen",
    "wof:name":"Dr. Med. Dieter Freude",
    "wof:placetype":"venue"
},
  "geometry": {"coordinates":[12.923241,50.841137],"type":"Point"}
}