{
  "type": "Feature",
  "properties": {
    "iso:country":"DE",
    "sg:address":"Pfarrstr. 12",
    "sg:city":"M\u00fcnchen",
    "sg:phone":"+49 89/29160503",
    "sg:postcode":"80538",
    "sg:province":"Bayern",
    "wof:name":"Gun Lux Nimar Unterwassertechnik",
    "wof:placetype":"venue"
},
  "geometry": {"coordinates":[11.587728,48.138542],"type":"Point"}
}