{
  "type": "Feature",
  "properties": {
    "iso:country":"DE",
    "sg:address":"Welseweg 8",
    "sg:city":"Stuhr",
    "sg:phone":"+49 421/5659160",
    "sg:postcode":"28816",
    "sg:province":"Niedersachsen",
    "wof:name":"Isp-ingenieurb\u00fcro Hans-e. Spark",
    "wof:placetype":"venue"
},
  "geometry": {"coordinates":[8.716552,53.032494],"type":"Point"}
}