{
  "type": "Feature",
  "properties": {
    "iso:country":"DE",
    "sg:address":"Ladestr. 1 -3",
    "sg:city":"Eilenburg",
    "sg:phone":"+49 3423/68500",
    "sg:postcode":"04838",
    "sg:province":"Sachsen",
    "wof:name":"Agrarhandel K\u00e4mmereiforst Gmbh & Handels Kg",
    "wof:placetype":"venue"
},
  "geometry": {"coordinates":[12.555137,51.47266],"type":"Point"}
}