{
  "type": "Feature",
  "properties": {
    "iso:country":"DE",
    "sg:address":"Veltener Str. 5",
    "sg:city":"Hennigsdorf",
    "sg:phone":"+49 3302/81971",
    "sg:postcode":"16761",
    "sg:province":"Brandenburg",
    "wof:name":"L. H\u00fcller",
    "wof:placetype":"venue"
},
  "geometry": {"coordinates":[13.2053537369,52.6496086121],"type":"Point"}
}