{
  "type": "Feature",
  "properties": {
    "iso:country":"DE",
    "sg:address":"Bundesallee 117",
    "sg:city":"Berlin",
    "sg:phone":"+49 30/8593574",
    "sg:postcode":"12161",
    "sg:province":"Berlin",
    "wof:name":"Jacques Wein Depot Wein- Einzelhandel",
    "wof:placetype":"venue"
},
  "geometry": {"coordinates":[13.3287343979,52.4683036804],"type":"Point"}
}