{
  "type": "Feature",
  "properties": {
    "iso:country":"DE",
    "sg:address":"Schnackebuschstr. 8",
    "sg:city":"Roetgen",
    "sg:phone":"+49 2408/5349",
    "sg:postcode":"52159",
    "sg:province":"Nordrhein-Westfalen",
    "wof:name":"Carola Herf",
    "wof:placetype":"venue"
},
  "geometry": {"coordinates":[6.1949248314,50.645526886],"type":"Point"}
}