{
  "type": "Feature",
  "properties": {
    "iso:country":"DE",
    "sg:address":"Rathausplatz 6",
    "sg:city":"Leupoldsgr\u00fcn",
    "sg:phone":"+49 9292/451",
    "sg:postcode":"95191",
    "sg:province":"Bayern",
    "wof:name":"Stadt-und Kreissparkasse Hof",
    "wof:placetype":"venue"
},
  "geometry": {"coordinates":[11.796277,50.289692],"type":"Point"}
}