{
  "type": "Feature",
  "properties": {
    "iso:country":"DE",
    "sg:address":"Steinbach",
    "sg:city":"Steinbach",
    "sg:phone":"+49 9263/424",
    "sg:postcode":"96361",
    "sg:province":"Bayern",
    "wof:name":"Volksbank Ludwigsstadt Eg",
    "wof:placetype":"venue"
},
  "geometry": {"coordinates":[11.3733,50.44133],"type":"Point"}
}