{
  "type": "Feature",
  "properties": {
    "iso:country":"DE",
    "sg:address":"Stockst\u00e4dter Str. 31",
    "sg:city":"Gro\u00dfostheim",
    "sg:phone":"+49 6026/2666",
    "sg:postcode":"63762",
    "sg:province":"Bayern",
    "wof:name":"T. Brunn",
    "wof:placetype":"venue"
},
  "geometry": {"coordinates":[9.072180748,49.9295883179],"type":"Point"}
}