{
  "type": "Feature",
  "properties": {
    "iso:country":"DE",
    "sg:address":"Wismarer Str. 1",
    "sg:city":"Garbsen",
    "sg:phone":"+49 5137/76263",
    "sg:postcode":"30823",
    "sg:province":"Niedersachsen",
    "wof:name":"Hoffmann Heissmangel",
    "wof:placetype":"venue"
},
  "geometry": {"coordinates":[9.6164150238,52.4131965637],"type":"Point"}
}