{
  "type": "Feature",
  "properties": {
    "iso:country":"DE",
    "sg:address":"Industriestr. 6",
    "sg:city":"Maintal",
    "sg:phone":"+49 6181/4060",
    "sg:postcode":"63477",
    "sg:province":"Hessen",
    "wof:name":"Real",
    "wof:placetype":"venue"
},
  "geometry": {"coordinates":[8.8669376373,50.1310806274],"type":"Point"}
}