{
  "type": "Feature",
  "properties": {
    "iso:country":"DE",
    "sg:address":"Lorettostr. 16",
    "sg:city":"Oberstdorf",
    "sg:phone":"+49 8322/3324",
    "sg:postcode":"87561",
    "sg:province":"Bayern",
    "wof:name":"Fremdenheim Geldernhaus",
    "wof:placetype":"venue"
},
  "geometry": {"coordinates":[10.2801036835,47.4032669067],"type":"Point"}
}