{
  "type": "Feature",
  "properties": {
    "iso:country":"DE",
    "sg:address":"Calwer Str. 5",
    "sg:city":"Neubulach",
    "sg:phone":"+49 7053/96900",
    "sg:postcode":"75387",
    "sg:province":"Baden-W\u00fcrttemberg",
    "wof:name":"Hotel Am Silbertor",
    "wof:placetype":"venue"
},
  "geometry": {"coordinates":[8.6942338943,48.6616401672],"type":"Point"}
}