{
  "type": "Feature",
  "properties": {
    "iso:country":"DE",
    "sg:address":"Sch\u00f6nbergstrasse 40",
    "sg:city":"Wiesbaden",
    "sg:phone":"+49 611/9742390",
    "sg:postcode":"65199",
    "sg:province":"Hessen",
    "wof:name":"1st-marketing",
    "wof:placetype":"venue"
},
  "geometry": {"coordinates":[8.2005882263,50.0786552429],"type":"Point"}
}