{
  "type": "Feature",
  "properties": {
    "iso:country":"DE",
    "sg:address":"Gartenstr. 6a",
    "sg:city":"Edenkoben",
    "sg:phone":"+49 6323/989075",
    "sg:postcode":"67480",
    "sg:province":"Rheinland-Pfalz",
    "wof:name":"Verlag K. F. Gei\u00dfler Verwaltungs Gmbh",
    "wof:placetype":"venue"
},
  "geometry": {"coordinates":[8.1213569641,49.2802619934],"type":"Point"}
}