{
  "type": "Feature",
  "properties": {
    "iso:country":"DE",
    "sg:address":"Wittekindstr. 4",
    "sg:city":"Gelsenkirchen",
    "sg:phone":"+49 209/270454",
    "sg:postcode":"45879",
    "sg:province":"Nordrhein-Westfalen",
    "wof:name":"L. R\u00f6hricht",
    "wof:placetype":"venue"
},
  "geometry": {"coordinates":[7.092257,51.505192],"type":"Point"}
}