{
  "type": "Feature",
  "properties": {
    "iso:country":"DE",
    "sg:address":"Himmerod 10",
    "sg:city":"Gro\u00dflittgen",
    "sg:phone":"+49 6575/1616",
    "sg:postcode":"54534",
    "sg:province":"Rheinland-Pfalz",
    "wof:name":"Karl-heinz Graf",
    "wof:placetype":"venue"
},
  "geometry": {"coordinates":[6.797612,50.025272],"type":"Point"}
}