{
  "type": "Feature",
  "properties": {
    "iso:country":"DE",
    "sg:address":"Herzogenbuscher Str. 8",
    "sg:city":"Trier",
    "sg:phone":"+49 651/12876",
    "sg:postcode":"54292",
    "sg:province":"Rheinland-Pfalz",
    "wof:name":"Emmi Und Reinhard Weinem",
    "wof:placetype":"venue"
},
  "geometry": {"coordinates":[6.656011,49.767056],"type":"Point"}
}