{
  "type": "Feature",
  "properties": {
    "iso:country":"DE",
    "sg:address":"Gutenbergstr. 5 b",
    "sg:city":"Darmstadt",
    "sg:phone":"+49 6151/714173",
    "sg:postcode":"64289",
    "sg:province":"Hessen",
    "wof:name":"Jacques Wein Depot Wein- Einzelhandel",
    "wof:placetype":"venue"
},
  "geometry": {"coordinates":[8.6624288559,49.8779449463],"type":"Point"}
}