{
  "type": "Feature",
  "properties": {
    "iso:country":"DE",
    "sg:address":"Krankenhausstr. 9",
    "sg:city":"Glandorf",
    "sg:phone":"+49 5426/660",
    "sg:postcode":"49219",
    "sg:province":"Niedersachsen",
    "wof:name":"M. Freundel",
    "wof:placetype":"venue"
},
  "geometry": {"coordinates":[8.00468,52.085514],"type":"Point"}
}