{
  "type": "Feature",
  "properties": {
    "iso:country":"DE",
    "sg:address":"Bendorfer Str. 88",
    "sg:city":"Neuwied",
    "sg:phone":"+49 2622/2643",
    "sg:postcode":"56566",
    "sg:province":"Rheinland-Pfalz",
    "wof:name":"W. Kr\u00e4mer",
    "wof:placetype":"venue"
},
  "geometry": {"coordinates":[7.545759,50.424332],"type":"Point"}
}