{
  "type": "Feature",
  "properties": {
    "iso:country":"DE",
    "sg:address":"Illstra\u00dfe 14",
    "sg:city":"Berlin",
    "sg:phone":"+49 30/85965563",
    "sg:postcode":"12161",
    "sg:province":"Berlin",
    "wof:name":"Silvia Sinha, \u00dcbersetzerin Englisch-deutsch",
    "wof:placetype":"venue"
},
  "geometry": {"coordinates":[13.33305,52.468582],"type":"Point"}
}