{
  "type": "Feature",
  "properties": {
    "iso:country":"DE",
    "sg:address":"Nibelungenplatz 13",
    "sg:city":"Braunschweig",
    "sg:phone":"+49 531/321345",
    "sg:postcode":"38106",
    "sg:province":"Niedersachsen",
    "wof:name":"Doris Reimer Immobilienmaklerin",
    "wof:placetype":"venue"
},
  "geometry": {"coordinates":[10.5269260406,52.2871894836],"type":"Point"}
}