{
  "type": "Feature",
  "properties": {
    "iso:country":"DE",
    "sg:address":"Westerwaldstr. 69-71",
    "sg:city":"Hennef",
    "sg:phone":"+49 2248/912206",
    "sg:postcode":"53773",
    "sg:province":"Nordrhein-Westfalen",
    "wof:name":"Dieter L\u00f6hr",
    "wof:placetype":"venue"
},
  "geometry": {"coordinates":[7.3621268272,50.7398529053],"type":"Point"}
}