{
  "type": "Feature",
  "properties": {
    "iso:country":"DE",
    "sg:address":"Nordstr. 7",
    "sg:city":"Hilchenbach",
    "sg:phone":"+49 2733/3486",
    "sg:postcode":"57271",
    "sg:province":"Nordrhein-Westfalen",
    "wof:name":"Jutta Niederau",
    "wof:placetype":"venue"
},
  "geometry": {"coordinates":[8.104543,50.985313],"type":"Point"}
}