{
  "type": "Feature",
  "properties": {
    "iso:country":"DE",
    "sg:address":"Laufener Str. 83",
    "sg:city":"Freilassing",
    "sg:phone":"+49 8654/62322",
    "sg:postcode":"83395",
    "sg:province":"Bayern",
    "wof:name":"Helmut Fr\u00fchwirth",
    "wof:placetype":"venue"
},
  "geometry": {"coordinates":[12.9868803024,47.8493118286],"type":"Point"}
}