{
  "type": "Feature",
  "properties": {
    "iso:country":"DE",
    "sg:address":"Altharener Patt 7",
    "sg:city":"Haren",
    "sg:phone":"+49 5932/69791",
    "sg:postcode":"49733",
    "sg:province":"Niedersachsen",
    "wof:name":"M\u00f6ller Bestattungen Inh. Joh. W\u00fcbkes",
    "wof:placetype":"venue"
},
  "geometry": {"coordinates":[7.22557,52.787964],"type":"Point"}
}