{
  "type": "Feature",
  "properties": {
    "iso:country":"DE",
    "sg:address":"Waldsassener Str. 23",
    "sg:city":"M\u00fcnchen",
    "sg:phone":"+49 89/683744",
    "sg:postcode":"81549",
    "sg:province":"Bayern",
    "wof:name":"Bernd Steinhaus Gmbh",
    "wof:placetype":"venue"
},
  "geometry": {"coordinates":[11.60836,48.089478],"type":"Point"}
}