{
  "type": "Feature",
  "properties": {
    "iso:country":"DE",
    "sg:address":"Probsth\u00e4ger Str. 10",
    "sg:city":"Stadthagen",
    "sg:phone":"+49 5721/3013",
    "sg:postcode":"31655",
    "sg:province":"Niedersachsen",
    "wof:name":"Parkett-galerie Dytrt",
    "wof:placetype":"venue"
},
  "geometry": {"coordinates":[9.2110500336,52.3281211853],"type":"Point"}
}