{
  "type": "Feature",
  "properties": {
    "iso:country":"DE",
    "sg:address":"Heppinger Str. 1",
    "sg:city":"Grafschaft",
    "sg:phone":"+49 2641/26427",
    "sg:postcode":"53501",
    "sg:province":"Rheinland-Pfalz",
    "wof:name":"R. Ramershoven",
    "wof:placetype":"venue"
},
  "geometry": {"coordinates":[7.09895,50.57412],"type":"Point"}
}