{
  "type": "Feature",
  "properties": {
    "iso:country":"DE",
    "sg:address":"Lautenschlagerstr. 17",
    "sg:city":"Stuttgart",
    "sg:phone":"+49 711/20670",
    "sg:postcode":"70173",
    "sg:province":"Baden-W\u00fcrttemberg",
    "wof:name":"Post 1 Verw.",
    "wof:placetype":"venue"
},
  "geometry": {"coordinates":[9.17885,48.78162],"type":"Point"}
}