{
  "type": "Feature",
  "properties": {
    "iso:country":"DE",
    "sg:address":"Industriestr. 42",
    "sg:city":"Gundelfingen",
    "sg:postcode":"79194",
    "sg:province":"Baden-W\u00fcrttemberg",
    "wof:name":"Metro",
    "wof:placetype":"venue"
},
  "geometry": {"coordinates":[7.8596711159,48.0471992493],"type":"Point"}
}