{
  "type": "Feature",
  "properties": {
    "iso:country":"DE",
    "sg:address":"Hessenring 32",
    "sg:city":"M\u00f6rfelden-Walldorf",
    "sg:phone":"+49 6105/20060",
    "sg:postcode":"64546",
    "sg:province":"Hessen",
    "wof:name":"Woodbridge Foam Gmbh",
    "wof:placetype":"venue"
},
  "geometry": {"coordinates":[8.5840587616,49.9872894287],"type":"Point"}
}