{
  "type": "Feature",
  "properties": {
    "iso:country":"DE",
    "sg:address":"Ulbering",
    "sg:city":"Wittibreut",
    "sg:phone":"+49 8574/213",
    "sg:postcode":"84384",
    "sg:province":"Bayern",
    "wof:name":"A. Huber Lagerhaus",
    "wof:placetype":"venue"
},
  "geometry": {"coordinates":[13.01466,48.35408],"type":"Point"}
}