{
  "type": "Feature",
  "properties": {
    "iso:country":"DE",
    "sg:address":"Wirtelstr. 1",
    "sg:city":"D\u00fcren",
    "sg:phone":"+49 2421/16669",
    "sg:postcode":"52349",
    "sg:province":"Nordrhein-Westfalen",
    "wof:name":"Herbert Schagen",
    "wof:placetype":"venue"
},
  "geometry": {"coordinates":[6.484772,50.802952],"type":"Point"}
}