{
  "type": "Feature",
  "properties": {
    "iso:country":"DE",
    "sg:address":"Beundestr. 3",
    "sg:city":"W\u00f6lfersheim",
    "sg:phone":"+49 6036/980137",
    "sg:postcode":"61200",
    "sg:province":"Hessen",
    "wof:name":"T. Winter",
    "wof:placetype":"venue"
},
  "geometry": {"coordinates":[8.863634,50.423168],"type":"Point"}
}