{
  "type": "Feature",
  "properties": {
    "iso:country":"DE",
    "sg:address":"Maingasse 18",
    "sg:city":"Knetzgau",
    "sg:phone":"+49 9527/267",
    "sg:postcode":"97478",
    "sg:province":"Bayern",
    "wof:name":"Gasthaus Mainaussicht",
    "wof:placetype":"venue"
},
  "geometry": {"coordinates":[10.5471448898,49.9982376099],"type":"Point"}
}