{
  "type": "Feature",
  "properties": {
    "iso:country":"DE",
    "sg:address":"Frontenhausener Str. 1",
    "sg:city":"Vilsbiburg",
    "sg:phone":"+49 8741/7601",
    "sg:postcode":"84137",
    "sg:province":"Bayern",
    "wof:name":"Edgar F. Und Gertrud Frommeld Und Koll",
    "wof:placetype":"venue"
},
  "geometry": {"coordinates":[12.3539104462,48.4502449036],"type":"Point"}
}