{
  "type": "Feature",
  "properties": {
    "iso:country":"DE",
    "sg:address":"Thierbacher Str. 20",
    "sg:city":"Cottbus",
    "sg:phone":"+49 355/525095",
    "sg:postcode":"03048",
    "sg:province":"Brandenburg",
    "wof:name":"Bischoff-ccc & Co. Kg",
    "wof:placetype":"venue"
},
  "geometry": {"coordinates":[14.325469017,51.7285346985],"type":"Point"}
}