{
  "type": "Feature",
  "properties": {
    "iso:country":"DE",
    "sg:address":"Raiffeisenstr. 4",
    "sg:city":"Pfaffenhofen",
    "sg:phone":"+49 8441/89510",
    "sg:postcode":"85276",
    "sg:province":"Bayern",
    "wof:name":"Max Hechinger",
    "wof:placetype":"venue"
},
  "geometry": {"coordinates":[11.5154008865,48.5339584351],"type":"Point"}
}