{
  "type": "Feature",
  "properties": {
    "iso:country":"DE",
    "sg:address":"Rosenweg 13",
    "sg:city":"Ebersbach",
    "sg:phone":"+49 8372/596",
    "sg:postcode":"87634",
    "sg:province":"Bayern",
    "wof:name":"Homepage Der Zimmerei H\u00e4ring, Ebersbach (allg\u00e4u)",
    "wof:placetype":"venue"
},
  "geometry": {"coordinates":[10.475721,47.852139],"type":"Point"}
}