{
  "type": "Feature",
  "properties": {
    "iso:country":"DE",
    "sg:address":"Industriestr 10",
    "sg:city":"Greding",
    "sg:phone":"+49 8463/64020",
    "sg:postcode":"91171",
    "sg:province":"Bayern",
    "wof:name":"Spiegl Gmbh & Co Fertigteil Kg",
    "wof:placetype":"venue"
},
  "geometry": {"coordinates":[11.3432168961,49.0449829102],"type":"Point"}
}