{
  "type": "Feature",
  "properties": {
    "iso:country":"DE",
    "sg:address":"Holtener Str. 48",
    "sg:city":"Oberhausen",
    "sg:postcode":"46145",
    "sg:province":"Nordrhein-Westfalen",
    "wof:name":"Schulte-hubbert Holzbearbeitung-innenausbau",
    "wof:placetype":"venue"
},
  "geometry": {"coordinates":[6.851349,51.519337],"type":"Point"}
}