{
  "type": "Feature",
  "properties": {
    "iso:country":"DE",
    "sg:address":"Ringstr. 11",
    "sg:city":"Wallenhorst",
    "sg:phone":"+49 5407/9808",
    "sg:postcode":"49134",
    "sg:province":"Niedersachsen",
    "wof:name":"Heinz Wiechers",
    "wof:placetype":"venue"
},
  "geometry": {"coordinates":[8.0035619736,52.354839325],"type":"Point"}
}