{
  "type": "Feature",
  "properties": {
    "iso:country":"DE",
    "sg:address":"Sittardsberger Allee 115",
    "sg:city":"Duisburg",
    "sg:phone":"+49 203/701328",
    "sg:postcode":"47249",
    "sg:province":"Nordrhein-Westfalen",
    "wof:name":"Anna Grau",
    "wof:placetype":"venue"
},
  "geometry": {"coordinates":[6.7813549042,51.3872032166],"type":"Point"}
}