{
  "type": "Feature",
  "properties": {
    "iso:country":"DE",
    "sg:address":"Richard-Wagner-Str. 12",
    "sg:city":"M\u00fchldorf",
    "sg:phone":"+49 8631/140120",
    "sg:postcode":"84453",
    "sg:province":"Bayern",
    "wof:name":"Sch\u00f6n & Prambs Haustechnik Gmbh",
    "wof:placetype":"venue"
},
  "geometry": {"coordinates":[12.519435,48.243069],"type":"Point"}
}