{
  "type": "Feature",
  "properties": {
    "iso:country":"DE",
    "sg:address":"Michael-Schiffer-Weg 1",
    "sg:city":"Erftstadt",
    "sg:phone":"+49 2235/955280",
    "sg:postcode":"50374",
    "sg:province":"Nordrhein-Westfalen",
    "wof:name":"Awo-seniorenzentren Im Erftkreis Gmbh",
    "wof:placetype":"venue"
},
  "geometry": {"coordinates":[6.76352,50.797386],"type":"Point"}
}