{
  "type": "Feature",
  "properties": {
    "iso:country":"DE",
    "sg:address":"Marienh\u00fctte 6",
    "sg:city":"Siegen",
    "sg:phone":"+49 271/31890",
    "sg:postcode":"57080",
    "sg:province":"Nordrhein-Westfalen",
    "wof:name":"Benno Dr\u00f6ssler Gmbh & Co. Bauunternehmung Kg",
    "wof:placetype":"venue"
},
  "geometry": {"coordinates":[8.00253582,50.8527908325],"type":"Point"}
}