{
  "type": "Feature",
  "properties": {
    "iso:country":"DE",
    "sg:address":"Z\u00f6llnergasse 1",
    "sg:city":"Penig",
    "sg:postcode":"09322",
    "sg:province":"Sachsen",
    "wof:name":"Elektro Nitsche",
    "wof:placetype":"venue"
},
  "geometry": {"coordinates":[12.706563,50.933441],"type":"Point"}
}