{
  "type": "Feature",
  "properties": {
    "iso:country":"DE",
    "sg:address":"Untere M\u00fchlstr. 7",
    "sg:city":"Darmstadt",
    "sg:phone":"+49 6151/371779",
    "sg:postcode":"64291",
    "sg:province":"Hessen",
    "wof:name":"Katharina Elv. Diemand E. Kfr.",
    "wof:placetype":"venue"
},
  "geometry": {"coordinates":[8.658827,49.911381],"type":"Point"}
}