{
  "type": "Feature",
  "properties": {
    "iso:country":"DE",
    "sg:address":"Kirchstr. 21",
    "sg:city":"Schutterwald",
    "sg:phone":"+49 781/52519",
    "sg:postcode":"77746",
    "sg:province":"Baden-W\u00fcrttemberg",
    "wof:name":"Artur Herrmann",
    "wof:placetype":"venue"
},
  "geometry": {"coordinates":[7.8856167793,48.4518508911],"type":"Point"}
}