{
  "type": "Feature",
  "properties": {
    "iso:country":"DE",
    "sg:address":"Graf-von-Stauffenberg-Str. 28",
    "sg:city":"D\u00fcsseldorf",
    "sg:phone":"+49 211/740020",
    "sg:postcode":"40595",
    "sg:province":"Nordrhein-Westfalen",
    "wof:name":"Rohrhandel Remmele Gmbh",
    "wof:placetype":"venue"
},
  "geometry": {"coordinates":[6.903512,51.129112],"type":"Point"}
}