{
  "type": "Feature",
  "properties": {
    "iso:country":"DE",
    "sg:address":"Friedrichshafenerstr.10",
    "sg:city":"Delitzsch",
    "sg:postcode":"04509",
    "sg:province":"Sachsen",
    "wof:name":"Hm-shop",
    "wof:placetype":"venue"
},
  "geometry": {"coordinates":[12.326099,51.536343],"type":"Point"}
}