{
  "type": "Feature",
  "properties": {
    "iso:country":"DE",
    "sg:address":"Hagener Str. 71",
    "sg:city":"Gevelsberg",
    "sg:phone":"+49 2332/10717",
    "sg:postcode":"58285",
    "sg:province":"Nordrhein-Westfalen",
    "wof:name":"Zimmermann Fliesenhandel Ohg",
    "wof:placetype":"venue"
},
  "geometry": {"coordinates":[7.3490920067,51.3239326477],"type":"Point"}
}