{
  "type": "Feature",
  "properties": {
    "iso:country":"DE",
    "sg:address":"Ulzburgerstra\u00dfe 484",
    "sg:city":"Norderstedt",
    "sg:phone":"+49 40/53532622",
    "sg:postcode":"22844",
    "sg:province":"Schleswig-Holstein",
    "wof:name":"Konstruieren Von Baugruppen Und Anlagen",
    "wof:placetype":"venue"
},
  "geometry": {"coordinates":[9.996733,53.733658],"type":"Point"}
}