{
  "type": "Feature",
  "properties": {
    "iso:country":"DE",
    "sg:address":"Obere Pfaffensteigstr. 44",
    "sg:city":"Schwabach",
    "sg:phone":"+49 911/630865",
    "sg:postcode":"91126",
    "sg:province":"Bayern",
    "wof:name":"H. A. Holl",
    "wof:placetype":"venue"
},
  "geometry": {"coordinates":[11.0146160126,49.3591194153],"type":"Point"}
}