{
  "type": "Feature",
  "properties": {
    "iso:country":"DE",
    "sg:address":"Hauptstr. 46",
    "sg:city":"Pfedelbach",
    "sg:phone":"+49 4979/49482",
    "sg:postcode":"74629",
    "sg:province":"Baden-W\u00fcrttemberg",
    "wof:name":"Raiffeisenbank Pfedelbach Eg",
    "wof:placetype":"venue"
},
  "geometry": {"coordinates":[9.504684,49.175648],"type":"Point"}
}