{
  "type": "Feature",
  "properties": {
    "iso:country":"DE",
    "sg:address":"Ro\u00dfstr. 87",
    "sg:city":"D\u00fcsseldorf",
    "sg:phone":"+49 211/451734",
    "sg:postcode":"40476",
    "sg:province":"Nordrhein-Westfalen",
    "wof:name":"Luxor",
    "wof:placetype":"venue"
},
  "geometry": {"coordinates":[6.7783617973,51.2468986511],"type":"Point"}
}