{
  "type": "Feature",
  "properties": {
    "iso:country":"DE",
    "sg:address":"Bleichstr 19",
    "sg:city":"N\u00fcrnberg",
    "sg:phone":"+49 911/9291617",
    "sg:postcode":"90429",
    "sg:province":"Bayern",
    "wof:name":"Rupp + Reinhold Gbr Sprachenservice",
    "wof:placetype":"venue"
},
  "geometry": {"coordinates":[11.0631370544,49.4514312744],"type":"Point"}
}