{
  "type": "Feature",
  "properties": {
    "iso:country":"DE",
    "sg:address":"Zimmerstra\u00dfe 8-10",
    "sg:city":"D\u00fcsseldorf",
    "sg:phone":"+49 211/9348326",
    "sg:postcode":"40215",
    "sg:province":"Nordrhein-Westfalen",
    "wof:name":"Inez Publishing",
    "wof:placetype":"venue"
},
  "geometry": {"coordinates":[6.7816228867,51.2105102539],"type":"Point"}
}