{
  "type": "Feature",
  "properties": {
    "iso:country":"DE",
    "sg:address":"Aschaffenburger Str. 61",
    "sg:city":"Seligenstadt",
    "sg:phone":"+49 6182/26066",
    "sg:postcode":"63500",
    "sg:province":"Hessen",
    "wof:name":"Emp Gmbh",
    "wof:placetype":"venue"
},
  "geometry": {"coordinates":[8.976989,50.04163],"type":"Point"}
}