{
  "type": "Feature",
  "properties": {
    "iso:country":"DE",
    "sg:address":"Friedensstr. 17",
    "sg:city":"Lehnin",
    "sg:phone":"+49 3382/376",
    "sg:postcode":"14797",
    "sg:province":"Brandenburg",
    "wof:name":"Wohnungsbau Gmbh",
    "wof:placetype":"venue"
},
  "geometry": {"coordinates":[12.7443008423,52.3185882568],"type":"Point"}
}