{
  "type": "Feature",
  "properties": {
    "iso:country":"DE",
    "sg:address":"Neustadtstr. 15",
    "sg:city":"Wennigsen",
    "sg:phone":"+49 5103/1583",
    "sg:postcode":"30974",
    "sg:province":"Niedersachsen",
    "wof:name":"Dirk Hinrichs E. K. Inh. Dirk Hinrichs",
    "wof:placetype":"venue"
},
  "geometry": {"coordinates":[9.5716190338,52.2756156921],"type":"Point"}
}