{
  "type": "Feature",
  "properties": {
    "iso:country":"DE",
    "sg:address":"Friedensstr. 31",
    "sg:city":"Oschatz",
    "sg:phone":"+49 3435/926603",
    "sg:postcode":"04758",
    "sg:province":"Sachsen",
    "wof:name":"Heinz Wittig",
    "wof:placetype":"venue"
},
  "geometry": {"coordinates":[13.0994367599,51.3039970398],"type":"Point"}
}