{
  "type": "Feature",
  "properties": {
    "iso:country":"DE",
    "sg:address":"Pappelweg 2",
    "sg:city":"Mengen",
    "sg:phone":"+49 7572",
    "sg:postcode":"88512",
    "sg:province":"Baden-W\u00fcrttemberg",
    "wof:name":"Halmer Automobile Gmbh",
    "wof:placetype":"venue"
},
  "geometry": {"coordinates":[9.3242588043,48.055480957],"type":"Point"}
}