{
  "type": "Feature",
  "properties": {
    "iso:country":"DE",
    "sg:address":"Rheinstr. 85-87",
    "sg:city":"Falkensee",
    "sg:phone":"+49 3322/50090",
    "sg:postcode":"14612",
    "sg:province":"Brandenburg",
    "wof:name":"Cartec Hehn Gmbh",
    "wof:placetype":"venue"
},
  "geometry": {"coordinates":[13.062747,52.573334],"type":"Point"}
}