{
  "type": "Feature",
  "properties": {
    "iso:country":"DE",
    "sg:address":"Schellingstr. 64",
    "sg:city":"N\u00fcrtingen",
    "sg:phone":"+49 7022/38998",
    "sg:postcode":"72622",
    "sg:province":"Baden-W\u00fcrttemberg",
    "wof:name":"Alwin Wolff Kg",
    "wof:placetype":"venue"
},
  "geometry": {"coordinates":[9.3540363312,48.6255378723],"type":"Point"}
}