{
  "type": "Feature",
  "properties": {
    "iso:country":"DE",
    "sg:address":"Sebastianstr. 27",
    "sg:city":"Erlangen",
    "sg:phone":"+49 9131/77890",
    "sg:postcode":"91058",
    "sg:province":"Bayern",
    "wof:name":"Bawemo-barnickel Gmbh",
    "wof:placetype":"venue"
},
  "geometry": {"coordinates":[11.0305976868,49.5450668335],"type":"Point"}
}