{
  "type": "Feature",
  "properties": {
    "iso:country":"DE",
    "sg:address":"Dorfstr. 33",
    "sg:city":"Niedertrebra",
    "sg:postcode":"99518",
    "sg:province":"Th\u00fcringen",
    "wof:name":"Torsten Klopfleisch",
    "wof:placetype":"venue"
},
  "geometry": {"coordinates":[11.584433,51.068718],"type":"Point"}
}