{
  "type": "Feature",
  "properties": {
    "iso:country":"DE",
    "sg:address":"Bahnhofstr. 17",
    "sg:city":"Markt Schwaben",
    "sg:phone":"+49 8121/45846",
    "sg:postcode":"85570",
    "sg:province":"Bayern",
    "wof:name":"Michael Huber",
    "wof:placetype":"venue"
},
  "geometry": {"coordinates":[11.8642892838,48.1925888062],"type":"Point"}
}