{
  "type": "Feature",
  "properties": {
    "iso:country":"DE",
    "sg:address":"F\u00fcrfurter Hof",
    "sg:city":"Villmar",
    "sg:phone":"+49 6474/357",
    "sg:postcode":"65606",
    "sg:province":"Hessen",
    "wof:name":"Johann K\u00f6nig",
    "wof:placetype":"venue"
},
  "geometry": {"coordinates":[8.249614,50.430012],"type":"Point"}
}