{
  "type": "Feature",
  "properties": {
    "iso:country":"DE",
    "sg:address":"Bierweg 6",
    "sg:city":"Arnstadt",
    "sg:phone":"+49 3628/710",
    "sg:postcode":"99310",
    "sg:province":"Th\u00fcringen",
    "wof:name":"Alcatel Buisiness Systems Deutschland Gmbh",
    "wof:placetype":"venue"
},
  "geometry": {"coordinates":[10.9545640945,50.8459281921],"type":"Point"}
}