{
  "type": "Feature",
  "properties": {
    "iso:country":"DE",
    "sg:address":"Waldstr. 35 f",
    "sg:city":"Bad Salzuflen",
    "sg:phone":"+49 5222/60406",
    "sg:postcode":"32105",
    "sg:province":"Nordrhein-Westfalen",
    "wof:name":"Abs Bauplanungs- Und Vermittlungs Gmbh",
    "wof:placetype":"venue"
},
  "geometry": {"coordinates":[8.74898,52.082432],"type":"Point"}
}