{
  "type": "Feature",
  "properties": {
    "iso:country":"DE",
    "sg:address":"Mittelstr. 23",
    "sg:city":"H\u00fcckelhoven",
    "sg:phone":"+49 2433/5507",
    "sg:postcode":"41836",
    "sg:province":"Nordrhein-Westfalen",
    "wof:name":"Th. Kamp",
    "wof:placetype":"venue"
},
  "geometry": {"coordinates":[6.183933,51.066776],"type":"Point"}
}