{
  "type": "Feature",
  "properties": {
    "iso:country":"DE",
    "sg:address":"Zur Steinfirst 27",
    "sg:city":"Sinntal",
    "sg:phone":"+49 6664/348",
    "sg:postcode":"36391",
    "sg:province":"Hessen",
    "wof:name":"Kurt M\u00fcller Architekt",
    "wof:placetype":"venue"
},
  "geometry": {"coordinates":[9.624243,50.307312],"type":"Point"}
}