{
  "type": "Feature",
  "properties": {
    "iso:country":"DE",
    "sg:address":"Ludwigstr. 31",
    "sg:city":"Gie\u00dfen",
    "sg:phone":"+49 641/970666",
    "sg:postcode":"35390",
    "sg:province":"Hessen",
    "wof:name":"Compudoc Computer Support Und Vertriebsgesellschaft Mbh",
    "wof:placetype":"venue"
},
  "geometry": {"coordinates":[8.6757259369,50.5801086426],"type":"Point"}
}