{
  "type": "Feature",
  "properties": {
    "iso:country":"DE",
    "sg:address":"Am Hasenfeld 2",
    "sg:city":"Lauf",
    "sg:phone":"+49 9123/981080",
    "sg:postcode":"91207",
    "sg:province":"Bayern",
    "wof:name":"Eurothek Krauss E. K.",
    "wof:placetype":"venue"
},
  "geometry": {"coordinates":[11.265465,49.526676],"type":"Point"}
}