{
  "type": "Feature",
  "properties": {
    "iso:country":"DE",
    "sg:address":"Tronjestr. 1",
    "sg:city":"Dortmund",
    "sg:postcode":"44319",
    "sg:province":"Nordrhein-Westfalen",
    "wof:name":"Gif Verwaltungsgesellschaft F\u00fcr Innovative Fertigungs-",
    "wof:placetype":"venue"
},
  "geometry": {"coordinates":[7.6237421036,51.5289497375],"type":"Point"}
}