{
  "type": "Feature",
  "properties": {
    "iso:country":"DE",
    "sg:address":"Friedrich-List-Str. 4",
    "sg:city":"Senden",
    "sg:phone":"+49 7307/6818",
    "sg:postcode":"89250",
    "sg:province":"Bayern",
    "wof:name":"Wolfgang Junginger",
    "wof:placetype":"venue"
},
  "geometry": {"coordinates":[10.057071,48.313236],"type":"Point"}
}