{
  "type": "Feature",
  "properties": {
    "iso:country":"DE",
    "sg:address":"Schmiedberg 4",
    "sg:city":"Burgau",
    "sg:phone":"+49 8222/4944",
    "sg:postcode":"89331",
    "sg:province":"Bayern",
    "wof:name":"R. Pruckner",
    "wof:placetype":"venue"
},
  "geometry": {"coordinates":[10.4061822891,48.4323310852],"type":"Point"}
}