{
  "type": "Feature",
  "properties": {
    "iso:country":"DE",
    "sg:address":"Gutshof 1",
    "sg:city":"Heiningen",
    "sg:postcode":"38312",
    "sg:province":"Niedersachsen",
    "wof:name":"Klosterh\u00e4hnchen Handels-gmbh",
    "wof:placetype":"venue"
},
  "geometry": {"coordinates":[10.555106163,52.0727996826],"type":"Point"}
}