{
  "type": "Feature",
  "properties": {
    "iso:country":"DE",
    "sg:address":"Karl-Mayer-Str. 21",
    "sg:city":"Obertshausen",
    "sg:phone":"+49 6104/49225",
    "sg:postcode":"63179",
    "sg:province":"Hessen",
    "wof:name":"Elektro Wahl Hans Wahl Nachf. Christine Freitag",
    "wof:placetype":"venue"
},
  "geometry": {"coordinates":[8.8507928848,50.070766449],"type":"Point"}
}