{
  "type": "Feature",
  "properties": {
    "iso:country":"DE",
    "sg:address":"Oskar-Hoffmann-Str. 2",
    "sg:city":"Bochum",
    "sg:phone":"+49 234/3250419",
    "sg:postcode":"44789",
    "sg:province":"Nordrhein-Westfalen",
    "wof:name":"Heinrich Diemel Inh. Stefan Eisenmenger E. K.",
    "wof:placetype":"venue"
},
  "geometry": {"coordinates":[7.214585,51.472782],"type":"Point"}
}