{
  "type": "Feature",
  "properties": {
    "iso:country":"DE",
    "sg:address":"Lindenallee 38",
    "sg:city":"Neuruppin",
    "sg:phone":"+49 3391/397042",
    "sg:postcode":"16816",
    "sg:province":"Brandenburg",
    "wof:name":"W. Pollak",
    "wof:placetype":"venue"
},
  "geometry": {"coordinates":[12.8237924576,52.9196586609],"type":"Point"}
}