{
  "type": "Feature",
  "properties": {
    "iso:country":"DE",
    "sg:address":"Wacholderweg 18",
    "sg:city":"Br\u00fcggen",
    "sg:phone":"+49 2163/952713",
    "sg:postcode":"41379",
    "sg:province":"Nordrhein-Westfalen",
    "wof:name":"Novus Airconditioning Trade Gmbh",
    "wof:placetype":"venue"
},
  "geometry": {"coordinates":[6.20572,51.24839],"type":"Point"}
}