{
  "type": "Feature",
  "properties": {
    "iso:country":"DE",
    "sg:address":"Zollerstr. 7",
    "sg:city":"Fischach",
    "sg:postcode":"86850",
    "sg:province":"Bayern",
    "wof:name":"T.m.a. Ges. F\u00fcr Betriebswirt. U. Datenverarbeitungstech.",
    "wof:placetype":"venue"
},
  "geometry": {"coordinates":[10.653933,48.309093],"type":"Point"}
}