{
  "type": "Feature",
  "properties": {
    "iso:country":"DE",
    "sg:address":"Ulmer Str. 36",
    "sg:city":"Burgau",
    "sg:phone":"+49 8222/6860",
    "sg:postcode":"89331",
    "sg:province":"Bayern",
    "wof:name":"Betz Gmbh",
    "wof:placetype":"venue"
},
  "geometry": {"coordinates":[10.397167,48.432678],"type":"Point"}
}