{
  "type": "Feature",
  "properties": {
    "iso:country":"DE",
    "sg:address":"Lorenz-Schott-Str 4",
    "sg:city":"Mainz-Kastel",
    "sg:phone":"+49 6134/7120",
    "sg:postcode":"55252",
    "sg:province":"Hessen",
    "wof:name":"Abb Lummus Global Gmbh",
    "wof:placetype":"venue"
},
  "geometry": {"coordinates":[8.2774381638,50.0266075134],"type":"Point"}
}