{
  "type": "Feature",
  "properties": {
    "iso:country":"DE",
    "sg:address":"Petersw\u00f6rther Str. 33",
    "sg:city":"Gundelfingen",
    "sg:phone":"+49 9073/7644",
    "sg:postcode":"89423",
    "sg:province":"Bayern",
    "wof:name":"Josef M\u00fcller",
    "wof:placetype":"venue"
},
  "geometry": {"coordinates":[10.371397,48.530388],"type":"Point"}
}