{
  "type": "Feature",
  "properties": {
    "iso:country":"DE",
    "sg:address":"Firmungstr. 9",
    "sg:city":"Koblenz",
    "sg:phone":"+49 261/38107",
    "sg:postcode":"56068",
    "sg:province":"Rheinland-Pfalz",
    "wof:name":"Flugb\u00f6rse Koblenz",
    "wof:placetype":"venue"
},
  "geometry": {"coordinates":[7.600195,50.360256],"type":"Point"}
}