{
  "type": "Feature",
  "properties": {
    "iso:country":"DE",
    "sg:address":"Basilikastr. 54",
    "sg:city":"Kevelaer",
    "sg:phone":"+49 2832/70037",
    "sg:postcode":"47623",
    "sg:province":"Nordrhein-Westfalen",
    "wof:name":"E. Van Leuven",
    "wof:placetype":"venue"
},
  "geometry": {"coordinates":[6.250128,51.583645],"type":"Point"}
}