{
  "type": "Feature",
  "properties": {
    "iso:country":"DE",
    "sg:address":"Pfaffen\u00e4cker 8a",
    "sg:city":"Lohr",
    "sg:phone":"+49 9352/80476",
    "sg:postcode":"97816",
    "sg:province":"Bayern",
    "wof:name":"Susanne Waschinger",
    "wof:placetype":"venue"
},
  "geometry": {"coordinates":[9.6015434265,49.9596977234],"type":"Point"}
}