{
  "type": "Feature",
  "properties": {
    "iso:country":"DE",
    "sg:address":"Flutstr. 107",
    "sg:city":"Recklinghausen",
    "sg:phone":"+49 2361/15162",
    "sg:postcode":"45659",
    "sg:province":"Nordrhein-Westfalen",
    "wof:name":"Werner Pott Steuerberater",
    "wof:placetype":"venue"
},
  "geometry": {"coordinates":[7.1900482178,51.6423072815],"type":"Point"}
}