{
  "type": "Feature",
  "properties": {
    "iso:country":"DE",
    "sg:address":"Kreuzweg 44",
    "sg:city":"Berg",
    "sg:phone":"+49 8151/51586",
    "sg:postcode":"82335",
    "sg:province":"Bayern",
    "wof:name":"Richt-magnetton Gmbh",
    "wof:placetype":"venue"
},
  "geometry": {"coordinates":[11.3492889404,47.9557418823],"type":"Point"}
}