{
  "type": "Feature",
  "properties": {
    "iso:country":"DE",
    "sg:address":"Hans-B\u00f6ckler-Str. 18",
    "sg:city":"Wesel",
    "sg:phone":"+49 281/64251",
    "sg:postcode":"46483",
    "sg:province":"Nordrhein-Westfalen",
    "wof:name":"Ulrich Hochstrat",
    "wof:placetype":"venue"
},
  "geometry": {"coordinates":[6.6033,51.677208],"type":"Point"}
}