{
  "type": "Feature",
  "properties": {
    "iso:country":"DE",
    "sg:address":"Fuchsbachweg 6",
    "sg:city":"Hemmingen",
    "sg:phone":"+49 511/423071",
    "sg:postcode":"30966",
    "sg:province":"Niedersachsen",
    "wof:name":"A. Sievers Gmbh",
    "wof:placetype":"venue"
},
  "geometry": {"coordinates":[9.744381,52.321915],"type":"Point"}
}