{
  "type": "Feature",
  "properties": {
    "iso:country":"DE",
    "sg:address":"Maximilian-Philipp-Str. 3",
    "sg:city":"T\u00fcrkheim",
    "sg:phone":"+49 8245/1418",
    "sg:postcode":"86842",
    "sg:province":"Bayern",
    "wof:name":"Anton Vogl",
    "wof:placetype":"venue"
},
  "geometry": {"coordinates":[10.640391,48.062267],"type":"Point"}
}