{
  "type": "Feature",
  "properties": {
    "iso:country":"DE",
    "sg:address":"Schluchenhausstr. 68",
    "sg:city":"Neuss",
    "sg:phone":"+49 2137/950777",
    "sg:postcode":"41469",
    "sg:province":"Nordrhein-Westfalen",
    "wof:name":"Siegfr. F\u00f6rster Ingenieur",
    "wof:placetype":"venue"
},
  "geometry": {"coordinates":[6.6980428696,51.1480369568],"type":"Point"}
}