{
  "type": "Feature",
  "properties": {
    "iso:country":"DE",
    "sg:address":"Auf der Dannen 6 a",
    "sg:city":"Bad Salzuflen",
    "sg:phone":"+49 5222/923208",
    "sg:postcode":"32108",
    "sg:province":"Nordrhein-Westfalen",
    "wof:name":"J. Koch",
    "wof:placetype":"venue"
},
  "geometry": {"coordinates":[8.7728128433,52.0646896362],"type":"Point"}
}