{
  "type": "Feature",
  "properties": {
    "iso:country":"DE",
    "sg:address":"Osterende 3",
    "sg:city":"Ahrenvi\u00f6l",
    "sg:phone":"+49 4847/1349",
    "sg:postcode":"25885",
    "sg:province":"Schleswig-Holstein",
    "wof:name":"S\u00f6nke Johannsen",
    "wof:placetype":"venue"
},
  "geometry": {"coordinates":[9.234548,54.534168],"type":"Point"}
}