{
  "type": "Feature",
  "properties": {
    "iso:country":"DE",
    "sg:address":"Bismarckstr. 85",
    "sg:city":"Stuttgart",
    "sg:phone":"+49 711/631636",
    "sg:postcode":"70197",
    "sg:province":"Baden-W\u00fcrttemberg",
    "wof:name":"Astrid Fuchs Masseurin",
    "wof:placetype":"venue"
},
  "geometry": {"coordinates":[9.15117,48.771114],"type":"Point"}
}