{
  "type": "Feature",
  "properties": {
    "iso:country":"DE",
    "sg:address":"Fraenkelufer 38b",
    "sg:city":"Berlin",
    "sg:postcode":"10999",
    "sg:province":"Berlin",
    "wof:name":"Renocon Gmbh Dienstleistungen F\u00fcr Rechts-",
    "wof:placetype":"venue"
},
  "geometry": {"coordinates":[13.41305,52.495682],"type":"Point"}
}