{
  "type": "Feature",
  "properties": {
    "iso:country":"DE",
    "sg:address":"Kurf\u00fcrstendamm 184",
    "sg:city":"Berlin",
    "sg:phone":"+49 30/8800870",
    "sg:postcode":"10707",
    "sg:province":"Berlin",
    "wof:name":"Jochen-g. L\u00f6chel Rechtsanwalt",
    "wof:placetype":"venue"
},
  "geometry": {"coordinates":[13.3143310547,52.5005950928],"type":"Point"}
}