{
  "type": "Feature",
  "properties": {
    "iso:country":"DE",
    "sg:address":"Zum Holzplatz 16",
    "sg:city":"Moringen",
    "sg:phone":"+49 5554/2266",
    "sg:postcode":"37186",
    "sg:province":"Niedersachsen",
    "wof:name":"Jens Kiel S\u00e4gewerk Und Holzhandlung Gmbh",
    "wof:placetype":"venue"
},
  "geometry": {"coordinates":[9.8712291718,51.7022361755],"type":"Point"}
}