{
  "type": "Feature",
  "properties": {
    "iso:country":"DE",
    "sg:address":"Toyota-Allee 47",
    "sg:city":"K\u00f6ln",
    "sg:phone":"+49 2234/54014",
    "sg:postcode":"50858",
    "sg:province":"Nordrhein-Westfalen",
    "wof:name":"Intersport Deutschland Eg",
    "wof:placetype":"venue"
},
  "geometry": {"coordinates":[6.8598,50.915409],"type":"Point"}
}