{
  "type": "Feature",
  "properties": {
    "iso:country":"DE",
    "sg:address":"Alfred-Faust-Str. 11",
    "sg:city":"Bremen",
    "sg:postcode":"28277",
    "sg:province":"Bremen",
    "wof:name":"Prophy Dent E. K.",
    "wof:placetype":"venue"
},
  "geometry": {"coordinates":[8.826895,53.036228],"type":"Point"}
}