{
  "type": "Feature",
  "properties": {
    "iso:country":"DE",
    "sg:address":"Hauptstr. 5",
    "sg:city":"Hofheim",
    "sg:phone":"+49 9523/327",
    "sg:postcode":"97461",
    "sg:province":"Bayern",
    "wof:name":"G. Volk & S\u00f6hne Eisenwaren",
    "wof:placetype":"venue"
},
  "geometry": {"coordinates":[10.5228281021,50.137752533],"type":"Point"}
}