{
  "type": "Feature",
  "properties": {
    "iso:country":"DE",
    "sg:address":"Alois-T\u00fcrk-Str. 24",
    "sg:city":"Schweinfurt",
    "sg:phone":"+49 9721/782121",
    "sg:postcode":"97424",
    "sg:province":"Bayern",
    "wof:name":"Siegfried Galle",
    "wof:placetype":"venue"
},
  "geometry": {"coordinates":[10.196,50.059109],"type":"Point"}
}