{
  "type": "Feature",
  "properties": {
    "iso:country":"DE",
    "sg:address":"Dobritzer Str. 2",
    "sg:city":"Zerbst",
    "sg:phone":"+49 3923/77282",
    "sg:postcode":"39261",
    "sg:province":"Sachsen-Anhalt",
    "wof:name":"Borrmann & Partner",
    "wof:placetype":"venue"
},
  "geometry": {"coordinates":[12.0922765732,51.97240448],"type":"Point"}
}