{
  "type": "Feature",
  "properties": {
    "iso:country":"DE",
    "sg:address":"Sch\u00fctzenweg 5",
    "sg:city":"Bad Heilbrunn",
    "sg:phone":"+49 8046/8788",
    "sg:postcode":"83670",
    "sg:province":"Bayern",
    "wof:name":"Otti Sindlhauser",
    "wof:placetype":"venue"
},
  "geometry": {"coordinates":[11.4533586502,47.7406959534],"type":"Point"}
}