{
  "type": "Feature",
  "properties": {
    "iso:country":"DE",
    "sg:address":"Weberstr. 2",
    "sg:city":"Heidelberg",
    "sg:phone":"+49 6221/64380",
    "sg:postcode":"69120",
    "sg:province":"Baden-W\u00fcrttemberg",
    "wof:name":"Carl-auer-systeme Verlag Und Verlagsbuchhandlung Gmbh",
    "wof:placetype":"venue"
},
  "geometry": {"coordinates":[8.690076828,49.4186630249],"type":"Point"}
}