{
  "type": "Feature",
  "properties": {
    "iso:country":"DE",
    "sg:address":"Lohrheidestr. 59",
    "sg:city":"Bochum",
    "sg:postcode":"44866",
    "sg:province":"Nordrhein-Westfalen",
    "wof:name":"Holzapfel Zimmerei Und Bauklempnerei Gmbh",
    "wof:placetype":"venue"
},
  "geometry": {"coordinates":[7.1236281395,51.4852600098],"type":"Point"}
}