{
  "type": "Feature",
  "properties": {
    "iso:country":"DE",
    "sg:address":"Bismarckallee 33",
    "sg:city":"Ahrensburg",
    "sg:postcode":"22926",
    "sg:province":"Schleswig-Holstein",
    "wof:name":"Abag Beteiligungs Ag",
    "wof:placetype":"venue"
},
  "geometry": {"coordinates":[10.245829,53.672302],"type":"Point"}
}