{
  "type": "Feature",
  "properties": {
    "iso:country":"DE",
    "sg:address":"Heisterbacher Str. 167",
    "sg:city":"Bornheim",
    "sg:phone":"+49 2222/951953",
    "sg:postcode":"53332",
    "sg:province":"Nordrhein-Westfalen",
    "wof:name":"A. Kl\u00f6ckner",
    "wof:placetype":"venue"
},
  "geometry": {"coordinates":[7.0340871811,50.7818183899],"type":"Point"}
}