{
  "type": "Feature",
  "properties": {
    "iso:country":"DE",
    "sg:address":"Hohenecker Str. 12",
    "sg:city":"Stollberg",
    "sg:phone":"+49 37296/3003",
    "sg:postcode":"09366",
    "sg:province":"Sachsen",
    "wof:name":"H. Lindner",
    "wof:placetype":"venue"
},
  "geometry": {"coordinates":[12.7786407471,50.7034492493],"type":"Point"}
}