{
  "type": "Feature",
  "properties": {
    "iso:country":"DE",
    "sg:address":"Karl-Marx-Str.",
    "sg:city":"Leegebruch",
    "sg:postcode":"16767",
    "sg:province":"Brandenburg",
    "wof:name":"Kulturhaus",
    "wof:placetype":"venue"
},
  "geometry": {"coordinates":[13.189801,52.726643],"type":"Point"}
}