{
  "type": "Feature",
  "properties": {
    "iso:country":"DE",
    "sg:address":"Postfach 1861:: 46308 Borken:: Germany.^^Butenwall 57::",
    "sg:city":"Borken",
    "sg:phone":"+49 2861/80060",
    "sg:postcode":"46325",
    "sg:province":"Nordrhein-Westfalen",
    "wof:name":"Borkener Volksbank Eg",
    "wof:placetype":"venue"
},
  "geometry": {"coordinates":[6.856386,51.841949],"type":"Point"}
}