{
  "type": "Feature",
  "properties": {
    "iso:country":"DE",
    "sg:address":"Lippst\u00e4dter Str. 12",
    "sg:city":"Rietberg",
    "sg:phone":"+49 2944/7624",
    "sg:postcode":"33397",
    "sg:province":"Nordrhein-Westfalen",
    "wof:name":"E. Und P. B\u00f6wingloh",
    "wof:placetype":"venue"
},
  "geometry": {"coordinates":[8.38972,51.755871],"type":"Point"}
}