{
  "type": "Feature",
  "properties": {
    "iso:country":"DE",
    "sg:address":"Further Str. 63",
    "sg:city":"Bogen",
    "sg:phone":"+49 9422/85250",
    "sg:postcode":"94327",
    "sg:province":"Bayern",
    "wof:name":"Schnupp Gmbh",
    "wof:placetype":"venue"
},
  "geometry": {"coordinates":[12.670836,48.928158],"type":"Point"}
}