{
  "type": "Feature",
  "properties": {
    "iso:country":"DE",
    "sg:address":"Hofener Str. 28",
    "sg:city":"Sonthofen",
    "sg:phone":"+49 8321/88964",
    "sg:postcode":"87527",
    "sg:province":"Bayern",
    "wof:name":"Krug Anlagenbau Gmbh",
    "wof:placetype":"venue"
},
  "geometry": {"coordinates":[10.2910633087,47.502532959],"type":"Point"}
}