{
  "type": "Feature",
  "properties": {
    "iso:country":"DE",
    "sg:address":"Sommerauer Str. 7",
    "sg:city":"Feuchtwangen",
    "sg:phone":"+49 9852/67170",
    "sg:postcode":"91555",
    "sg:province":"Bayern",
    "wof:name":"Haas & Bautz Ingenieurges. Mbh",
    "wof:placetype":"venue"
},
  "geometry": {"coordinates":[10.3128833771,49.164730072],"type":"Point"}
}