{
  "type": "Feature",
  "properties": {
    "iso:country":"DE",
    "sg:address":"Katerallee 27",
    "sg:city":"Detmold",
    "sg:phone":"+49 5231/877440",
    "sg:postcode":"32760",
    "sg:province":"Nordrhein-Westfalen",
    "wof:name":"J. Niekler",
    "wof:placetype":"venue"
},
  "geometry": {"coordinates":[8.8519649506,51.9236297607],"type":"Point"}
}