{
  "type": "Feature",
  "properties": {
    "iso:country":"DE",
    "sg:address":"R\u00f6telstr. 35",
    "sg:city":"Neckarsulm",
    "sg:postcode":"74172",
    "sg:province":"Baden-W\u00fcrttemberg",
    "wof:name":"Is Warenhandel Beteiligungs Gmbh",
    "wof:placetype":"venue"
},
  "geometry": {"coordinates":[9.221685,49.171963],"type":"Point"}
}