{
  "type": "Feature",
  "properties": {
    "iso:country":"DE",
    "sg:address":"Taunusstr. 21",
    "sg:city":"Limburg",
    "sg:phone":"+49 6431/72233",
    "sg:postcode":"65553",
    "sg:province":"Hessen",
    "wof:name":"Edla Kuhl-coelho Da Cruz",
    "wof:placetype":"venue"
},
  "geometry": {"coordinates":[8.092671,50.399925],"type":"Point"}
}