{
  "type": "Feature",
  "properties": {
    "iso:country":"DE",
    "sg:address":"Windm\u00fchlenstr. 6",
    "sg:city":"Bonn",
    "sg:phone":"+49 228/655361",
    "sg:postcode":"53111",
    "sg:province":"Nordrhein-Westfalen",
    "wof:name":"W. Burg",
    "wof:placetype":"venue"
},
  "geometry": {"coordinates":[7.105208,50.739697],"type":"Point"}
}