{
  "type": "Feature",
  "properties": {
    "iso:country":"DE",
    "sg:address":"Buchfinkenweg 13",
    "sg:city":"F\u00fcrth",
    "sg:phone":"+49 911/762751",
    "sg:postcode":"90768",
    "sg:province":"Bayern",
    "wof:name":"G\u00fcnter B\u00fcschel Steuerberater",
    "wof:placetype":"venue"
},
  "geometry": {"coordinates":[10.9611997604,49.5184745789],"type":"Point"}
}