{
  "type": "Feature",
  "properties": {
    "iso:country":"DE",
    "sg:address":"Schw\u00e4rzlocher Str. 37",
    "sg:city":"T\u00fcbingen",
    "sg:phone":"+49 7071/44340",
    "sg:postcode":"72070",
    "sg:province":"Baden-W\u00fcrttemberg",
    "wof:name":"F. Geissler Immobilienmakler",
    "wof:placetype":"venue"
},
  "geometry": {"coordinates":[9.0450782776,48.519443512],"type":"Point"}
}