{
  "type": "Feature",
  "properties": {
    "iso:country":"DE",
    "sg:address":"Salacher Str. 19",
    "sg:city":"Eislingen",
    "sg:phone":"+49 7161/88661",
    "sg:postcode":"73054",
    "sg:province":"Baden-W\u00fcrttemberg",
    "wof:name":"P.a.d. Professional Application Design Gmbh",
    "wof:placetype":"venue"
},
  "geometry": {"coordinates":[9.7083358765,48.6983528137],"type":"Point"}
}