{
  "type": "Feature",
  "properties": {
    "iso:country":"DE",
    "sg:address":"Teplitzer Str. 7",
    "sg:city":"Geising",
    "sg:phone":"+49 35056/31851",
    "sg:postcode":"01778",
    "sg:province":"Sachsen",
    "wof:name":"Arndt Voigt",
    "wof:placetype":"venue"
},
  "geometry": {"coordinates":[13.793248,50.755959],"type":"Point"}
}