{
  "type": "Feature",
  "properties": {
    "iso:country":"DE",
    "sg:address":"N\u00e4gelingasse 6",
    "sg:city":"Heilbronn",
    "sg:phone":"+49 7131/82255",
    "sg:postcode":"74072",
    "sg:province":"Baden-W\u00fcrttemberg",
    "wof:name":"Joachim Klama Anwaltssoziet\u00e4t",
    "wof:placetype":"venue"
},
  "geometry": {"coordinates":[9.2180290222,49.139541626],"type":"Point"}
}