{
  "type": "Feature",
  "properties": {
    "iso:country":"DE",
    "sg:address":"Obergasse 26",
    "sg:city":"Meisenheim",
    "sg:postcode":"55590",
    "sg:province":"Rheinland-Pfalz",
    "wof:name":"Boos Von Waldeck'scher Hof Verm\u00f6gens- Und Grundst\u00fccks-",
    "wof:placetype":"venue"
},
  "geometry": {"coordinates":[7.6706438065,49.7074775696],"type":"Point"}
}