{
  "type": "Feature",
  "properties": {
    "iso:country":"DE",
    "sg:address":"Hindenburgdamm 57 C",
    "sg:city":"Berlin",
    "sg:phone":"+49 30/8343057",
    "sg:postcode":"12203",
    "sg:province":"Berlin",
    "wof:name":"Wolfgang Griese Steuerberater",
    "wof:placetype":"venue"
},
  "geometry": {"coordinates":[13.3156528473,52.4465675354],"type":"Point"}
}