{
  "type": "Feature",
  "properties": {
    "iso:country":"DE",
    "sg:address":"Raiffeisenstr. 2",
    "sg:city":"Rottenbuch",
    "sg:phone":"+49 8867/91900",
    "sg:postcode":"82401",
    "sg:province":"Bayern",
    "wof:name":"Fichtl Fleischgro\u00dfhandlung Kg",
    "wof:placetype":"venue"
},
  "geometry": {"coordinates":[10.9634847641,47.7331962585],"type":"Point"}
}