{
  "type": "Feature",
  "properties": {
    "iso:country":"DE",
    "sg:address":"Asbacher Str. 1",
    "sg:city":"Bad Hersfeld",
    "sg:phone":"+49 6621/74558",
    "sg:postcode":"36251",
    "sg:province":"Hessen",
    "wof:name":"Glebe",
    "wof:placetype":"venue"
},
  "geometry": {"coordinates":[9.6783800125,50.8319282532],"type":"Point"}
}