{
  "type": "Feature",
  "properties": {
    "iso:country":"DE",
    "sg:address":"Pappelberg 123",
    "sg:city":"Braunschweig",
    "sg:phone":"+49 531/375041",
    "sg:postcode":"38104",
    "sg:province":"Niedersachsen",
    "wof:name":"Waltraud Podlesch",
    "wof:placetype":"venue"
},
  "geometry": {"coordinates":[10.5716323853,52.284538269],"type":"Point"}
}