{
  "type": "Feature",
  "properties": {
    "iso:country":"DE",
    "sg:address":"Wilhelm-Deling-Str. 6",
    "sg:city":"M\u00f6nchengladbach",
    "sg:phone":"+49 2161/200857",
    "sg:postcode":"41065",
    "sg:province":"Nordrhein-Westfalen",
    "wof:name":"Sigma Computer E. K.",
    "wof:placetype":"venue"
},
  "geometry": {"coordinates":[6.4526958466,51.1940956116],"type":"Point"}
}