{
  "type": "Feature",
  "properties": {
    "iso:country":"DE",
    "sg:address":"Bantjed\u00fcnen 25",
    "sg:city":"Borkum",
    "sg:phone":"+49 4922/3433",
    "sg:postcode":"26757",
    "sg:province":"Niedersachsen",
    "wof:name":"Wiard Byl",
    "wof:placetype":"venue"
},
  "geometry": {"coordinates":[6.6971921921,53.5906791687],"type":"Point"}
}