{
  "type": "Feature",
  "properties": {
    "iso:country":"DE",
    "sg:address":"Ahrenshooper Str. 40",
    "sg:city":"Berlin",
    "sg:phone":"+49 30/9294688",
    "sg:postcode":"13051",
    "sg:province":"Berlin",
    "wof:name":"Ingrid Blumenthal",
    "wof:placetype":"venue"
},
  "geometry": {"coordinates":[13.5040473938,52.5694847107],"type":"Point"}
}