{
  "type": "Feature",
  "properties": {
    "iso:country":"DE",
    "sg:address":"Hauptstra\u00dfe 78",
    "sg:city":"Kehl",
    "sg:phone":"+49 7851/2094",
    "sg:postcode":"77694",
    "sg:province":"Baden-W\u00fcrttemberg",
    "wof:name":"Buchhandlung Baumg\u00e4rtner",
    "wof:placetype":"venue"
},
  "geometry": {"coordinates":[7.8135848045,48.5725593567],"type":"Point"}
}