{
  "type": "Feature",
  "properties": {
    "iso:country":"DE",
    "sg:address":"Friedrich-Engelhorn-Str. 5",
    "sg:city":"Mannheim",
    "sg:phone":"+49 621/338890",
    "sg:postcode":"68167",
    "sg:province":"Baden-W\u00fcrttemberg",
    "wof:name":"Epc Elreha Leiterplatten- Technik Gmbh",
    "wof:placetype":"venue"
},
  "geometry": {"coordinates":[8.4960002899,49.5004005432],"type":"Point"}
}