{
  "type": "Feature",
  "properties": {
    "iso:country":"DE",
    "sg:address":"Kapellenweg 10",
    "sg:city":"B\u00fcdingen",
    "sg:phone":"+49 6041/50817",
    "sg:postcode":"63654",
    "sg:province":"Hessen",
    "wof:name":"Heinz Mahr",
    "wof:placetype":"venue"
},
  "geometry": {"coordinates":[9.031723,50.296497],"type":"Point"}
}