{
  "type": "Feature",
  "properties": {
    "iso:country":"DE",
    "sg:address":"Luisenstr. 32",
    "sg:city":"Bernburg",
    "sg:phone":"+49 3471/316225",
    "sg:postcode":"06406",
    "sg:province":"Sachsen-Anhalt",
    "wof:name":"Heinz Zacher",
    "wof:placetype":"venue"
},
  "geometry": {"coordinates":[11.7439670563,51.7895812988],"type":"Point"}
}