{
  "type": "Feature",
  "properties": {
    "iso:country":"DE",
    "sg:address":"Volkardeyer Str. 23",
    "sg:city":"Ratingen",
    "sg:phone":"+49 2102/444474",
    "sg:postcode":"40878",
    "sg:province":"Nordrhein-Westfalen",
    "wof:name":"Grillpizzeria O La La",
    "wof:placetype":"venue"
},
  "geometry": {"coordinates":[6.8282551765,51.2883071899],"type":"Point"}
}