{
  "type": "Feature",
  "properties": {
    "iso:country":"DE",
    "sg:address":"Ringstr. 110",
    "sg:city":"Seevetal",
    "sg:phone":"+49 4105/2781",
    "sg:postcode":"21218",
    "sg:province":"Niedersachsen",
    "wof:name":"Hans-martin Voelsch",
    "wof:placetype":"venue"
},
  "geometry": {"coordinates":[9.9926,53.376381],"type":"Point"}
}