{
  "type": "Feature",
  "properties": {
    "iso:country":"DE",
    "sg:address":"Klapperstr. 4",
    "sg:city":"Eschweiler",
    "sg:phone":"+49 2403/25701",
    "sg:postcode":"52249",
    "sg:province":"Nordrhein-Westfalen",
    "wof:name":"W. Hunscheidt",
    "wof:placetype":"venue"
},
  "geometry": {"coordinates":[6.2427182198,50.8375511169],"type":"Point"}
}