{
  "type": "Feature",
  "properties": {
    "iso:country":"DE",
    "sg:address":"Rottstr. 31",
    "sg:city":"Dudenhofen",
    "sg:phone":"+49 6232/95939",
    "sg:postcode":"67373",
    "sg:province":"Rheinland-Pfalz",
    "wof:name":"A. Z\u00fcrker",
    "wof:placetype":"venue"
},
  "geometry": {"coordinates":[8.384806633,49.3162651062],"type":"Point"}
}