{
  "type": "Feature",
  "properties": {
    "iso:country":"DE",
    "sg:address":"Sachsenweg 102 a",
    "sg:city":"Hamburg",
    "sg:phone":"+49 40/5554116",
    "sg:postcode":"22455",
    "sg:province":"Hamburg",
    "wof:name":"Holger Becker Bau Gmbh",
    "wof:placetype":"venue"
},
  "geometry": {"coordinates":[9.9613103867,53.6447181702],"type":"Point"}
}