{
  "type": "Feature",
  "properties": {
    "iso:country":"DE",
    "sg:address":"Bunsenstr. 2",
    "sg:city":"Karlsruhe",
    "sg:phone":"+49 721/854599",
    "sg:postcode":"76135",
    "sg:province":"Baden-W\u00fcrttemberg",
    "wof:name":"R. Baitinger",
    "wof:placetype":"venue"
},
  "geometry": {"coordinates":[8.373332,49.006618],"type":"Point"}
}