{
  "type": "Feature",
  "properties": {
    "iso:country":"DE",
    "sg:address":"Eberreutestr. 8",
    "sg:city":"Pfedelbach",
    "sg:phone":"+49 7941/985247",
    "sg:postcode":"74629",
    "sg:province":"Baden-W\u00fcrttemberg",
    "wof:name":"Zeitel",
    "wof:placetype":"venue"
},
  "geometry": {"coordinates":[9.4857778549,49.1817512512],"type":"Point"}
}