{
  "type": "Feature",
  "properties": {
    "iso:country":"DE",
    "sg:address":"Vorstadt 42",
    "sg:city":"Trochtelfingen",
    "sg:phone":"+49 7124",
    "sg:postcode":"72818",
    "sg:province":"Baden-W\u00fcrttemberg",
    "wof:name":"Comfinder Projekt 2000",
    "wof:placetype":"venue"
},
  "geometry": {"coordinates":[9.247745,48.313019],"type":"Point"}
}