{
  "type": "Feature",
  "properties": {
    "iso:country":"DE",
    "sg:address":"L\u00e4mershagener Str. 280",
    "sg:city":"Bielefeld",
    "sg:phone":"+49 5202/6121",
    "sg:postcode":"33699",
    "sg:province":"Nordrhein-Westfalen",
    "wof:name":"Deppe",
    "wof:placetype":"venue"
},
  "geometry": {"coordinates":[8.6189804077,51.9719009399],"type":"Point"}
}