{
  "type": "Feature",
  "properties": {
    "iso:country":"DE",
    "sg:address":"Einkaufszentrum 36",
    "sg:city":"Bad Bibra",
    "sg:postcode":"06647",
    "sg:province":"Sachsen-Anhalt",
    "wof:name":"Mode Hensel",
    "wof:placetype":"venue"
},
  "geometry": {"coordinates":[11.54306,51.196831],"type":"Point"}
}