{
  "type": "Feature",
  "properties": {
    "iso:country":"DE",
    "sg:address":"Luisenstr. 8",
    "sg:city":"G\u00f6rlitz",
    "sg:phone":"+49 3581",
    "sg:postcode":"02826",
    "sg:province":"Sachsen",
    "wof:name":"A-qua-be Gemeinn\u00fctzige Gmbh",
    "wof:placetype":"venue"
},
  "geometry": {"coordinates":[14.983584,51.152981],"type":"Point"}
}