{
  "type": "Feature",
  "properties": {
    "iso:country":"DE",
    "sg:address":"Bahnhofstr. 39",
    "sg:city":"Regen",
    "sg:phone":"+49 9921/904431",
    "sg:postcode":"94209",
    "sg:province":"Bayern",
    "wof:name":"M. Und H. Oberl\u00e4nder",
    "wof:placetype":"venue"
},
  "geometry": {"coordinates":[13.135505,48.969746],"type":"Point"}
}