{
  "type": "Feature",
  "properties": {
    "iso:country":"DE",
    "sg:address":"Marktplatz 2",
    "sg:city":"Hessisch Oldendorf",
    "sg:postcode":"31840",
    "sg:province":"Niedersachsen",
    "wof:name":"Immobilien Development Und Beteiligungsgesellschaft",
    "wof:placetype":"venue"
},
  "geometry": {"coordinates":[9.249741,52.168427],"type":"Point"}
}