{
  "type": "Feature",
  "properties": {
    "iso:country":"DE",
    "sg:address":"Im Jesuitengarten 20",
    "sg:city":"Neustadt",
    "sg:phone":"+49 6321/66252",
    "sg:postcode":"67435",
    "sg:province":"Rheinland-Pfalz",
    "wof:name":"Wolfgang Beneke Steuerberater",
    "wof:placetype":"venue"
},
  "geometry": {"coordinates":[8.1606197357,49.3855781555],"type":"Point"}
}