{
  "type": "Feature",
  "properties": {
    "iso:country":"DE",
    "sg:address":"Haydnstr. 11",
    "sg:city":"Ottobeuren",
    "sg:phone":"+49 8332/8208",
    "sg:postcode":"87724",
    "sg:province":"Bayern",
    "wof:name":"Erwin Rauh",
    "wof:placetype":"venue"
},
  "geometry": {"coordinates":[10.2946329117,47.9352493286],"type":"Point"}
}