{
  "type": "Feature",
  "properties": {
    "iso:country":"DE",
    "sg:address":"Isergebirgsstr. 3",
    "sg:city":"Mauerstetten",
    "sg:phone":"+49 8341/62400",
    "sg:postcode":"87665",
    "sg:province":"Bayern",
    "wof:name":"Ander Galvanik Gmbh",
    "wof:placetype":"venue"
},
  "geometry": {"coordinates":[10.6603107452,47.9042282104],"type":"Point"}
}