{
  "type": "Feature",
  "properties": {
    "iso:country":"DE",
    "sg:address":"Wittbr\u00e4ucker Str. 410",
    "sg:city":"Dortmund",
    "sg:phone":"+49 231/487273",
    "sg:postcode":"44267",
    "sg:province":"Nordrhein-Westfalen",
    "wof:name":"Ingenieurb\u00fcro F\u00fcr Technische Akustik Und Bauphysik Itab",
    "wof:placetype":"venue"
},
  "geometry": {"coordinates":[7.52364,51.4608],"type":"Point"}
}