{
  "type": "Feature",
  "properties": {
    "iso:country":"DE",
    "sg:address":"Hedwig-Dransfeld-Str. 51",
    "sg:city":"Werl",
    "sg:phone":"+49 2922/6831",
    "sg:postcode":"59457",
    "sg:province":"Nordrhein-Westfalen",
    "wof:name":"L. Thiergarten",
    "wof:placetype":"venue"
},
  "geometry": {"coordinates":[7.91879,51.549934],"type":"Point"}
}