{
  "type": "Feature",
  "properties": {
    "iso:country":"DE",
    "sg:address":"Alois-J\u00e4ger-Platz 1",
    "sg:city":"Montabaur",
    "sg:postcode":"56410",
    "sg:province":"Rheinland-Pfalz",
    "wof:name":"Kath. \u00d6ffentliche Bibliothek",
    "wof:placetype":"venue"
},
  "geometry": {"coordinates":[7.829045,50.43576],"type":"Point"}
}