{
  "type": "Feature",
  "properties": {
    "iso:country":"DE",
    "sg:address":"Vo\u00dfheiderstr.2",
    "sg:city":"Doerentrup",
    "sg:phone":"+49 5265/95191",
    "sg:postcode":"32694",
    "sg:province":"Nordrhein-Westfalen",
    "wof:name":"Kostenlose Bewerbungsberatung!",
    "wof:placetype":"venue"
},
  "geometry": {"coordinates":[9.004043,52.015465],"type":"Point"}
}