{
  "type": "Feature",
  "properties": {
    "iso:country":"DE",
    "sg:address":"Oppenheimer Str. 20",
    "sg:city":"Gro\u00df-Gerau",
    "sg:phone":"+49 6152/7727",
    "sg:postcode":"64521",
    "sg:province":"Hessen",
    "wof:name":"Kleine Galerie",
    "wof:placetype":"venue"
},
  "geometry": {"coordinates":[8.473951,49.921581],"type":"Point"}
}