{
  "type": "Feature",
  "properties": {
    "iso:country":"DE",
    "sg:address":"K\u00f6lnstr. 50-52",
    "sg:city":"Z\u00fclpich",
    "sg:phone":"+49 2252/2669",
    "sg:postcode":"53909",
    "sg:province":"Nordrhein-Westfalen",
    "wof:name":"Spiel- Und Sporthaus Hans P. Gatzweiler",
    "wof:placetype":"venue"
},
  "geometry": {"coordinates":[6.6507778168,50.6927604675],"type":"Point"}
}