{
  "type": "Feature",
  "properties": {
    "iso:country":"DE",
    "sg:address":"Landgrafenstr. 56",
    "sg:city":"Bad Homburg",
    "sg:phone":"+49 6172/81047",
    "sg:postcode":"61348",
    "sg:province":"Hessen",
    "wof:name":"Technologica Gmbh",
    "wof:placetype":"venue"
},
  "geometry": {"coordinates":[8.6147890091,50.2336387634],"type":"Point"}
}