{
  "type": "Feature",
  "properties": {
    "iso:country":"DE",
    "sg:address":"Ostertagstr. 41",
    "sg:city":"Leonberg",
    "sg:phone":"+49 7152/904100",
    "sg:postcode":"71229",
    "sg:province":"Baden-W\u00fcrttemberg",
    "wof:name":"Donauer Immobilienmakler",
    "wof:placetype":"venue"
},
  "geometry": {"coordinates":[9.0124015808,48.7936286926],"type":"Point"}
}