{
  "type": "Feature",
  "properties": {
    "iso:country":"DE",
    "sg:address":"Leipziger Str. 58",
    "sg:city":"Neckarsulm",
    "sg:phone":"+49 7132/81676",
    "sg:postcode":"74172",
    "sg:province":"Baden-W\u00fcrttemberg",
    "wof:name":"Sch\u00fcrle Transport Gmbh",
    "wof:placetype":"venue"
},
  "geometry": {"coordinates":[9.2392683029,49.2021026611],"type":"Point"}
}