{
  "type": "Feature",
  "properties": {
    "iso:country":"DE",
    "sg:address":"Rodenbacher Weg 12",
    "sg:city":"Frankenberg",
    "sg:phone":"+49 6451/21794",
    "sg:postcode":"35066",
    "sg:province":"Hessen",
    "wof:name":"Hans-gerhard Arnold",
    "wof:placetype":"venue"
},
  "geometry": {"coordinates":[8.753541,51.050259],"type":"Point"}
}