{
  "type": "Feature",
  "properties": {
    "iso:country":"DE",
    "sg:address":"K\u00e4ferflugstr. 21",
    "sg:city":"Heilbronn",
    "sg:phone":"+49 7131/178818",
    "sg:postcode":"74076",
    "sg:province":"Baden-W\u00fcrttemberg",
    "wof:name":"A. Koppelmann",
    "wof:placetype":"venue"
},
  "geometry": {"coordinates":[9.2263145447,49.1549873352],"type":"Point"}
}