{
  "type": "Feature",
  "properties": {
    "iso:country":"DE",
    "sg:address":"K\u00f6nigstr. 39",
    "sg:city":"N\u00fcrnberg",
    "sg:phone":"+49 911/241235",
    "sg:postcode":"90402",
    "sg:province":"Bayern",
    "wof:name":"Doris Berg Rechtsanw\u00e4ltin",
    "wof:placetype":"venue"
},
  "geometry": {"coordinates":[11.0790014267,49.4499053955],"type":"Point"}
}