{
  "type": "Feature",
  "properties": {
    "iso:country":"DE",
    "sg:address":"Lange Str. 13-15",
    "sg:city":"Offenburg",
    "sg:phone":"+49 781/91600",
    "sg:postcode":"77652",
    "sg:province":"Baden-W\u00fcrttemberg",
    "wof:name":"Bettenhaus Leitermann Gmbh",
    "wof:placetype":"venue"
},
  "geometry": {"coordinates":[7.944062233,48.4717788696],"type":"Point"}
}