{
  "type": "Feature",
  "properties": {
    "iso:country":"DE",
    "sg:address":"Ollenhauerstr. 56",
    "sg:city":"Berlin",
    "sg:phone":"+49 30/4116272",
    "sg:postcode":"13403",
    "sg:province":"Berlin",
    "wof:name":"Peter Seewald Bastel- Und Hobby-laden 95 A",
    "wof:placetype":"venue"
},
  "geometry": {"coordinates":[13.332203,52.574623],"type":"Point"}
}