{
  "type": "Feature",
  "properties": {
    "iso:country":"DE",
    "sg:address":"Dreik\u00f6nigenstr. 36",
    "sg:city":"Krefeld",
    "sg:phone":"+49 2151/23383",
    "sg:postcode":"47799",
    "sg:province":"Nordrhein-Westfalen",
    "wof:name":"Lucien Tange",
    "wof:placetype":"venue"
},
  "geometry": {"coordinates":[6.5692019463,51.3307266235],"type":"Point"}
}