{
  "type": "Feature",
  "properties": {
    "iso:country":"DE",
    "sg:address":"Bergstr",
    "sg:city":"Niederdreisbach",
    "sg:phone":"+49 2743/921766",
    "sg:postcode":"57520",
    "sg:province":"Rheinland-Pfalz",
    "wof:name":"Meteor-siegen Maschinenfabrik Gmbh & Co Kg",
    "wof:placetype":"venue"
},
  "geometry": {"coordinates":[7.922472,50.748501],"type":"Point"}
}