{
  "type": "Feature",
  "properties": {
    "iso:country":"DE",
    "sg:address":"Salinstr. 11a",
    "sg:city":"Rosenheim",
    "sg:phone":"+49 8031/381681",
    "sg:postcode":"83022",
    "sg:province":"Bayern",
    "wof:name":"Janet Huber",
    "wof:placetype":"venue"
},
  "geometry": {"coordinates":[12.124277,47.85078],"type":"Point"}
}