{
  "type": "Feature",
  "properties": {
    "iso:country":"DE",
    "sg:address":"Otto-Hue-Str. 42a",
    "sg:city":"Marl",
    "sg:postcode":"45772",
    "sg:province":"Nordrhein-Westfalen",
    "wof:name":"Spieloase Erste Betriebs Gmbh",
    "wof:placetype":"venue"
},
  "geometry": {"coordinates":[7.136488,51.663017],"type":"Point"}
}