{
  "type": "Feature",
  "properties": {
    "iso:country":"DE",
    "sg:address":"Sautterweg 5/128",
    "sg:city":"Stuttgart",
    "sg:phone":"+49 711/7157482",
    "sg:postcode":"70565",
    "sg:province":"Baden-W\u00fcrttemberg",
    "wof:name":"Paul Frohn Architekt",
    "wof:placetype":"venue"
},
  "geometry": {"coordinates":[9.151404,48.712158],"type":"Point"}
}