{
  "type": "Feature",
  "properties": {
    "iso:country":"DE",
    "sg:address":"Am Ordensschlo\u00df 8",
    "sg:city":"Obersulm",
    "sg:phone":"+49 7130/46060",
    "sg:postcode":"74182",
    "sg:province":"Baden-W\u00fcrttemberg",
    "wof:name":"H. Fleisch",
    "wof:placetype":"venue"
},
  "geometry": {"coordinates":[9.383952,49.134541],"type":"Point"}
}