{
  "type": "Feature",
  "properties": {
    "iso:country":"DE",
    "sg:address":"Parkhofstr. 26",
    "sg:city":"H\u00fcckelhoven",
    "sg:postcode":"41836",
    "sg:province":"Nordrhein-Westfalen",
    "wof:name":"Elzet Elektrotechnik Gmbh",
    "wof:placetype":"venue"
},
  "geometry": {"coordinates":[6.2243337631,51.0511894226],"type":"Point"}
}