{
  "type": "Feature",
  "properties": {
    "iso:country":"DE",
    "sg:address":"Auweg 11b",
    "sg:city":"Regensburg",
    "sg:phone":"+49 941/794785",
    "sg:postcode":"93055",
    "sg:province":"Bayern",
    "wof:name":"Stb Block Gmbh",
    "wof:placetype":"venue"
},
  "geometry": {"coordinates":[12.1274785995,49.0164794922],"type":"Point"}
}