{
  "type": "Feature",
  "properties": {
    "iso:country":"DE",
    "sg:address":"Bad S\u00fclzer Str. 50",
    "sg:city":"L\u00f6bnitz",
    "sg:phone":"+49 38324/217",
    "sg:postcode":"18314",
    "sg:province":"Mecklenburg-Vorpommern",
    "wof:name":"L\u00f6bnitzer Wirtschafts Gmbh",
    "wof:placetype":"venue"
},
  "geometry": {"coordinates":[12.7179098129,54.2887535095],"type":"Point"}
}