{
  "type": "Feature",
  "properties": {
    "iso:country":"DE",
    "sg:address":"Seidleinweg 12",
    "sg:city":"M\u00fcnchen",
    "sg:postcode":"81929",
    "sg:province":"Bayern",
    "wof:name":"Sh-polska Sp. Zo. O. Nl Deutschland",
    "wof:placetype":"venue"
},
  "geometry": {"coordinates":[11.648666,48.157261],"type":"Point"}
}