{
  "type": "Feature",
  "properties": {
    "iso:country":"DE",
    "sg:address":"Am Wall 6",
    "sg:city":"Bingen",
    "sg:phone":"+49 6721/13224",
    "sg:postcode":"55411",
    "sg:province":"Rheinland-Pfalz",
    "wof:name":"Weinhaus Huber",
    "wof:placetype":"venue"
},
  "geometry": {"coordinates":[7.9644942284,49.9239273071],"type":"Point"}
}