{
  "type": "Feature",
  "properties": {
    "iso:country":"DE",
    "sg:address":"Mittelstr. 1",
    "sg:city":"Gieboldehausen",
    "sg:postcode":"37434",
    "sg:province":"Niedersachsen",
    "wof:name":"\u00d6ffentliche B\u00fccherei",
    "wof:placetype":"venue"
},
  "geometry": {"coordinates":[10.21471,51.611012],"type":"Point"}
}