{
  "type": "Feature",
  "properties": {
    "iso:country":"DE",
    "sg:address":"Lustnauer Zentrum",
    "sg:city":"T\u00fcbingen",
    "sg:phone":"+49 7071/82349",
    "sg:postcode":"72074",
    "sg:province":"Baden-W\u00fcrttemberg",
    "wof:name":"Femini",
    "wof:placetype":"venue"
},
  "geometry": {"coordinates":[9.094053,48.542942],"type":"Point"}
}