{
  "type": "Feature",
  "properties": {
    "iso:country":"DE",
    "sg:address":"Scheidestr. 17",
    "sg:city":"Hannover",
    "sg:phone":"+49 511/537469",
    "sg:postcode":"30625",
    "sg:province":"Niedersachsen",
    "wof:name":"Optiker-bartsch",
    "wof:placetype":"venue"
},
  "geometry": {"coordinates":[9.7846632004,52.3727149963],"type":"Point"}
}