{
  "type": "Feature",
  "properties": {
    "iso:country":"DE",
    "sg:address":"Breite Str. 51",
    "sg:city":"Lemgo",
    "sg:phone":"+49 5261/13986",
    "sg:postcode":"32657",
    "sg:province":"Nordrhein-Westfalen",
    "wof:name":"Seitensprung",
    "wof:placetype":"venue"
},
  "geometry": {"coordinates":[8.9004898071,52.0267219543],"type":"Point"}
}