{
  "type": "Feature",
  "properties": {
    "iso:country":"DE",
    "sg:address":"Schwaikheimer Str. 17",
    "sg:city":"Winnenden",
    "sg:phone":"+49 7195/60948",
    "sg:postcode":"71364",
    "sg:province":"Baden-W\u00fcrttemberg",
    "wof:name":"Heinrich Kl\u00f6pfer",
    "wof:placetype":"venue"
},
  "geometry": {"coordinates":[9.389769,48.879044],"type":"Point"}
}