{
  "type": "Feature",
  "properties": {
    "iso:country":"DE",
    "sg:address":"Grazerstr.19",
    "sg:city":"Hannover",
    "sg:phone":"+49 511/8487687",
    "sg:postcode":"30519",
    "sg:province":"Niedersachsen",
    "wof:name":"Steuerberater Norbert Heidrich",
    "wof:placetype":"venue"
},
  "geometry": {"coordinates":[9.764284,52.346771],"type":"Point"}
}