{
  "type": "Feature",
  "properties": {
    "iso:country":"DE",
    "sg:address":"Harmsweg 16",
    "sg:city":"Seevetal",
    "sg:phone":"+49 4105/660202",
    "sg:postcode":"21220",
    "sg:province":"Niedersachsen",
    "wof:name":"I.b.s. Polymers Gmbh",
    "wof:placetype":"venue"
},
  "geometry": {"coordinates":[10.0314559937,53.3828430176],"type":"Point"}
}