{
  "type": "Feature",
  "properties": {
    "iso:country":"DE",
    "sg:address":"Friesdorfer Str. 31",
    "sg:city":"Bonn",
    "sg:phone":"+49 228/315125",
    "sg:postcode":"53173",
    "sg:province":"Nordrhein-Westfalen",
    "wof:name":"J. Gr\u00fcnh\u00e4user",
    "wof:placetype":"venue"
},
  "geometry": {"coordinates":[7.1507110596,50.6868209839],"type":"Point"}
}