{
  "type": "Feature",
  "properties": {
    "iso:country":"DE",
    "sg:address":"Hauptstr. 19",
    "sg:city":"Halle",
    "sg:phone":"+49 5201/7612",
    "sg:postcode":"33790",
    "sg:province":"Nordrhein-Westfalen",
    "wof:name":"Osning Apotheke Edeltraud Schl\u00fcter E. K.",
    "wof:placetype":"venue"
},
  "geometry": {"coordinates":[8.386719,52.038685],"type":"Point"}
}