{
  "type": "Feature",
  "properties": {
    "iso:country":"DE",
    "sg:address":"Weiherplatz 18",
    "sg:city":"Wiehl",
    "sg:phone":"+49 4922/6276470",
    "sg:postcode":"51674",
    "sg:province":"Nordrhein-Westfalen",
    "wof:name":"Horst Stranzenbach",
    "wof:placetype":"venue"
},
  "geometry": {"coordinates":[7.547958,50.950939],"type":"Point"}
}