{
  "type": "Feature",
  "properties": {
    "iso:country":"DE",
    "sg:address":"Hauptstr. 26",
    "sg:city":"Frasdorf",
    "sg:phone":"+49 8052/2248",
    "sg:postcode":"83112",
    "sg:province":"Bayern",
    "wof:name":"Max Hilger",
    "wof:placetype":"venue"
},
  "geometry": {"coordinates":[12.286463,47.803158],"type":"Point"}
}