{
  "type": "Feature",
  "properties": {
    "iso:country":"DE",
    "sg:address":"H\u00fclenbergstr. 35",
    "sg:city":"N\u00fcrtingen",
    "sg:phone":"+49 7022/32170",
    "sg:postcode":"72622",
    "sg:province":"Baden-W\u00fcrttemberg",
    "wof:name":"Kr\u00e4mer Verwaltungs Gmbh",
    "wof:placetype":"venue"
},
  "geometry": {"coordinates":[9.390702,48.628033],"type":"Point"}
}