{
  "type": "Feature",
  "properties": {
    "iso:country":"DE",
    "sg:address":"Hammerstr. 21",
    "sg:city":"Waldm\u00fcnchen",
    "sg:phone":"+49 9972/3100",
    "sg:postcode":"93449",
    "sg:province":"Bayern",
    "wof:name":"Karl Krippner",
    "wof:placetype":"venue"
},
  "geometry": {"coordinates":[12.706461,49.375423],"type":"Point"}
}