{
  "type": "Feature",
  "properties": {
    "iso:country":"DE",
    "sg:address":"Eichelh\u00e4herkamp 118c",
    "sg:city":"Hamburg",
    "sg:phone":"+49 40/7679032",
    "sg:postcode":"22397",
    "sg:province":"Hamburg",
    "wof:name":"Carpe Diem",
    "wof:placetype":"venue"
},
  "geometry": {"coordinates":[10.0839109421,53.6827507019],"type":"Point"}
}