{
  "type": "Feature",
  "properties": {
    "iso:country":"DE",
    "sg:address":"Hauptstr. 27",
    "sg:city":"Altlay",
    "sg:phone":"+49 6543/4446",
    "sg:postcode":"56858",
    "sg:province":"Rheinland-Pfalz",
    "wof:name":"Hotel Zur Morschbach",
    "wof:placetype":"venue"
},
  "geometry": {"coordinates":[7.2713837624,49.9881896973],"type":"Point"}
}