{
  "type": "Feature",
  "properties": {
    "iso:country":"DE",
    "sg:address":"St.-Martin-Str. 42",
    "sg:city":"M\u00fcnchen",
    "sg:phone":"+49 89/6205330",
    "sg:postcode":"81541",
    "sg:province":"Bayern",
    "wof:name":"Josef Koch",
    "wof:placetype":"venue"
},
  "geometry": {"coordinates":[11.59133,48.117531],"type":"Point"}
}