{
  "type": "Feature",
  "properties": {
    "iso:country":"DE",
    "sg:address":"Unterstr. 26",
    "sg:city":"Aschersleben",
    "sg:postcode":"06449",
    "sg:province":"Sachsen-Anhalt",
    "wof:name":"Mtr Gmbh",
    "wof:placetype":"venue"
},
  "geometry": {"coordinates":[11.4655303955,51.7592468262],"type":"Point"}
}