{
  "type": "Feature",
  "properties": {
    "iso:country":"DE",
    "sg:address":"Berliner Str. 2",
    "sg:city":"Witzenhausen",
    "sg:phone":"+49 5542/2141",
    "sg:postcode":"37216",
    "sg:province":"Hessen",
    "wof:name":"M\u00f6belwerk Louis Steinfeld Inh. Albrecht Gr\u00e4fer E. Kfm.",
    "wof:placetype":"venue"
},
  "geometry": {"coordinates":[9.8089351654,51.3181762695],"type":"Point"}
}