{
  "type": "Feature",
  "properties": {
    "iso:country":"DE",
    "sg:address":"Bublitzer Str 32",
    "sg:city":"D\u00fcsseldorf",
    "sg:phone":"+49 211/748350",
    "sg:postcode":"40599",
    "sg:province":"Nordrhein-Westfalen",
    "wof:name":"Rockwell Automation",
    "wof:placetype":"venue"
},
  "geometry": {"coordinates":[6.8668,51.176414],"type":"Point"}
}