{
  "type": "Feature",
  "properties": {
    "iso:country":"DE",
    "sg:address":"Hauptstr. 19a",
    "sg:city":"Freiburg",
    "sg:phone":"+49 761/553975",
    "sg:postcode":"79104",
    "sg:province":"Baden-W\u00fcrttemberg",
    "wof:name":"Holzwurm",
    "wof:placetype":"venue"
},
  "geometry": {"coordinates":[7.8616762161,48.0070724487],"type":"Point"}
}