{
  "type": "Feature",
  "properties": {
    "iso:country":"DE",
    "sg:address":"Brienner Stra\u00dfe 20",
    "sg:city":"M\u00fcnchen",
    "sg:phone":"+49 89/217101",
    "sg:postcode":"80277",
    "sg:province":"Bayern",
    "wof:name":"Bayerische Landesbank Girozentrale",
    "wof:placetype":"venue"
},
  "geometry": {"coordinates":[11.572148,48.14399],"type":"Point"}
}