{
  "type": "Feature",
  "properties": {
    "iso:country":"DE",
    "sg:address":"B\u00f6blinger Str. 33",
    "sg:city":"Nagold",
    "sg:phone":"+49 7459/1303",
    "sg:postcode":"72202",
    "sg:province":"Baden-W\u00fcrttemberg",
    "wof:name":"Hopfen-stube Inh. Herbert M\u00fcller",
    "wof:placetype":"venue"
},
  "geometry": {"coordinates":[8.721200943,48.4983215332],"type":"Point"}
}