{
  "type": "Feature",
  "properties": {
    "iso:country":"DE",
    "sg:address":"Konstanzer Str. 46",
    "sg:city":"Radolfzell",
    "sg:phone":"+49 7732/10988",
    "sg:postcode":"78315",
    "sg:province":"Baden-W\u00fcrttemberg",
    "wof:name":"Eckard Huber Heilpraktiker",
    "wof:placetype":"venue"
},
  "geometry": {"coordinates":[8.9801273346,47.7434692383],"type":"Point"}
}