{
  "type": "Feature",
  "properties": {
    "iso:country":"DE",
    "sg:address":"Lange Str. 4",
    "sg:city":"G\u00f6ppingen",
    "sg:phone":"+49 7161/69860",
    "sg:postcode":"73033",
    "sg:province":"Baden-W\u00fcrttemberg",
    "wof:name":"Coiffeur Pour Monsieur Gmbh",
    "wof:placetype":"venue"
},
  "geometry": {"coordinates":[9.6542577744,48.7023544312],"type":"Point"}
}