{
  "type": "Feature",
  "properties": {
    "iso:country":"DE",
    "sg:address":"Habichtstr. 20 b",
    "sg:city":"Hattingen",
    "sg:phone":"+49 2324/201184",
    "sg:postcode":"45527",
    "sg:province":"Nordrhein-Westfalen",
    "wof:name":"Contor-handel Gesellschaft F\u00fcr B\u00fcro Accessoires Mbh",
    "wof:placetype":"venue"
},
  "geometry": {"coordinates":[7.1958241463,51.3746910095],"type":"Point"}
}