{
  "type": "Feature",
  "properties": {
    "iso:country":"DE",
    "sg:address":"Fischersiedlung 9",
    "sg:city":"Kappeln",
    "sg:phone":"+49 4642/81637",
    "sg:postcode":"24376",
    "sg:province":"Schleswig-Holstein",
    "wof:name":"Kurt Blenckner",
    "wof:placetype":"venue"
},
  "geometry": {"coordinates":[9.944145,54.661919],"type":"Point"}
}