{
  "type": "Feature",
  "properties": {
    "iso:country":"DE",
    "sg:address":"Leipziger Str. 148",
    "sg:city":"Crimmitschau",
    "sg:phone":"+49 3762/3716",
    "sg:postcode":"08451",
    "sg:province":"Sachsen",
    "wof:name":"Goldene S\u00e4ge",
    "wof:placetype":"venue"
},
  "geometry": {"coordinates":[12.3904838562,50.8288497925],"type":"Point"}
}