{
  "type": "Feature",
  "properties": {
    "iso:country":"DE",
    "sg:address":"Ziegeleistr. 19",
    "sg:city":"Metzingen",
    "sg:postcode":"72555",
    "sg:province":"Baden-W\u00fcrttemberg",
    "wof:name":"Koch & Stoo\u00df Hausm\u00fcll-entsorgung",
    "wof:placetype":"venue"
},
  "geometry": {"coordinates":[9.2731170654,48.5326538086],"type":"Point"}
}