{
  "type": "Feature",
  "properties": {
    "iso:country":"DE",
    "sg:address":"Ohmstr. 2a",
    "sg:city":"Amberg",
    "sg:phone":"+49 9621/76660",
    "sg:postcode":"92224",
    "sg:province":"Bayern",
    "wof:name":"M2 Edv-beratung Und Vertrieb Gmbh",
    "wof:placetype":"venue"
},
  "geometry": {"coordinates":[11.8663311005,49.4290390015],"type":"Point"}
}