{
  "type": "Feature",
  "properties": {
    "iso:country":"DE",
    "sg:address":"Steinweg 7",
    "sg:city":"Alpenrod",
    "sg:phone":"+49 2661/4777",
    "sg:postcode":"57642",
    "sg:province":"Rheinland-Pfalz",
    "wof:name":"Gastst\u00e4tte Isolde Wannemacher",
    "wof:placetype":"venue"
},
  "geometry": {"coordinates":[7.8660597801,50.632144928],"type":"Point"}
}