{
  "type": "Feature",
  "properties": {
    "iso:country":"DE",
    "sg:address":"Bustellistr. 10",
    "sg:city":"Aschaffenburg",
    "sg:postcode":"63739",
    "sg:province":"Bayern",
    "wof:name":"Helga Alisch E. K.",
    "wof:placetype":"venue"
},
  "geometry": {"coordinates":[9.156463,49.97517],"type":"Point"}
}