{
  "type": "Feature",
  "properties": {
    "iso:country":"DE",
    "sg:address":"Dirlewang",
    "sg:city":"Dirlewang",
    "sg:phone":"+49 8267/1380",
    "sg:postcode":"87742",
    "sg:province":"Bayern",
    "wof:name":"Raiffeisenbank Kirchheim",
    "wof:placetype":"venue"
},
  "geometry": {"coordinates":[10.506208,48.001507],"type":"Point"}
}