{
  "type": "Feature",
  "properties": {
    "iso:country":"DE",
    "sg:address":"Werther Str. 36-40",
    "sg:city":"Stolberg",
    "sg:phone":"+49 2402/98890",
    "sg:postcode":"52224",
    "sg:province":"Nordrhein-Westfalen",
    "wof:name":"Scholl-roosen Kunststoffe Gmbh",
    "wof:placetype":"venue"
},
  "geometry": {"coordinates":[6.272278,50.766907],"type":"Point"}
}