{
  "type": "Feature",
  "properties": {
    "iso:country":"DE",
    "sg:address":"Meyfartstr 14",
    "sg:city":"Erfurt",
    "sg:phone":"+49 361/6438425",
    "sg:postcode":"99084",
    "sg:province":"Th\u00fcringen",
    "wof:name":"Dg Hypothekenbank Ag",
    "wof:placetype":"venue"
},
  "geometry": {"coordinates":[11.039173,50.977764],"type":"Point"}
}