{
  "type": "Feature",
  "properties": {
    "iso:country":"DE",
    "sg:address":"Moritzstr. 22",
    "sg:city":"Bad Gandersheim",
    "sg:phone":"+49 5382/91313",
    "sg:postcode":"37581",
    "sg:province":"Niedersachsen",
    "wof:name":"Reiseland Reiseb\u00fcro Riedel Gmbh",
    "wof:placetype":"venue"
},
  "geometry": {"coordinates":[10.0245056152,51.870174408],"type":"Point"}
}