{
  "type": "Feature",
  "properties": {
    "iso:country":"DE",
    "sg:address":"Gottlieb-Daimler-Str. 21",
    "sg:city":"Wennigsen",
    "sg:postcode":"30974",
    "sg:province":"Niedersachsen",
    "wof:name":"Torab Technik Gmbh",
    "wof:placetype":"venue"
},
  "geometry": {"coordinates":[9.5812368393,52.2768859863],"type":"Point"}
}