{
  "type": "Feature",
  "properties": {
    "iso:country":"DE",
    "sg:address":"Klaus-Blank-Str. 1",
    "sg:city":"Westheim",
    "sg:phone":"+49 9082/96780",
    "sg:postcode":"91747",
    "sg:province":"Bayern",
    "wof:name":"Max Blank Gmbh",
    "wof:placetype":"venue"
},
  "geometry": {"coordinates":[10.653854,49.000511],"type":"Point"}
}