{
  "type": "Feature",
  "properties": {
    "iso:country":"DE",
    "sg:address":"Schillerstr. 39",
    "sg:city":"Burgst\u00e4dt",
    "sg:phone":"+49 3724/2435",
    "sg:postcode":"09217",
    "sg:province":"Sachsen",
    "wof:name":"E. Aumann",
    "wof:placetype":"venue"
},
  "geometry": {"coordinates":[12.803508,50.916412],"type":"Point"}
}