{
  "type": "Feature",
  "properties": {
    "iso:country":"DE",
    "sg:address":"Lange Kesselstr. 4-6",
    "sg:city":"Warendorf",
    "sg:phone":"+49 2581/541",
    "sg:postcode":"48231",
    "sg:province":"Nordrhein-Westfalen",
    "wof:name":"Wasserwerk",
    "wof:placetype":"venue"
},
  "geometry": {"coordinates":[7.987598896,51.9523620605],"type":"Point"}
}