{
  "type": "Feature",
  "properties": {
    "iso:country":"DE",
    "sg:address":"Hansengasse 2",
    "sg:city":"Geislingen",
    "sg:phone":"+49 7331/41761",
    "sg:postcode":"73312",
    "sg:province":"Baden-W\u00fcrttemberg",
    "wof:name":"Dekanat Geislingen",
    "wof:placetype":"venue"
},
  "geometry": {"coordinates":[9.8291196823,48.6244392395],"type":"Point"}
}