{
  "type": "Feature",
  "properties": {
    "iso:country":"DE",
    "sg:address":"Dr.-Salvador-Allende-Str. 172",
    "sg:city":"Chemnitz",
    "sg:phone":"+49 371/2629989",
    "sg:postcode":"09119",
    "sg:province":"Sachsen",
    "wof:name":"Gabriele Koch",
    "wof:placetype":"venue"
},
  "geometry": {"coordinates":[12.886802,50.804306],"type":"Point"}
}