{
  "type": "Feature",
  "properties": {
    "iso:country":"DE",
    "sg:address":"Sch\u00f6nbacher Str. 36",
    "sg:city":"Breitscheid",
    "sg:phone":"+49 2777/7372",
    "sg:postcode":"35767",
    "sg:province":"Hessen",
    "wof:name":"G\u00fcnter Werner Stahlbau Gmbh",
    "wof:placetype":"venue"
},
  "geometry": {"coordinates":[8.193570137,50.6817893982],"type":"Point"}
}