{
  "type": "Feature",
  "properties": {
    "iso:country":"DE",
    "sg:address":"Fahrstr. 12",
    "sg:city":"Babenhausen",
    "sg:phone":"+49 6073/62239",
    "sg:postcode":"64832",
    "sg:province":"Hessen",
    "wof:name":"Alois Buchinger",
    "wof:placetype":"venue"
},
  "geometry": {"coordinates":[8.9530477524,49.9616851807],"type":"Point"}
}