{
  "type": "Feature",
  "properties": {
    "iso:country":"DE",
    "sg:address":"Bismarckstr. 76",
    "sg:city":"Berlin",
    "sg:phone":"+49 30/7559181",
    "sg:postcode":"12157",
    "sg:province":"Berlin",
    "wof:name":"Frau Wolle",
    "wof:placetype":"venue"
},
  "geometry": {"coordinates":[13.339245,52.4641],"type":"Point"}
}