{
  "type": "Feature",
  "properties": {
    "iso:country":"DE",
    "sg:address":"Mergentheimer Str. 8",
    "sg:city":"Berlin",
    "sg:postcode":"12247",
    "sg:province":"Berlin",
    "wof:name":"Bfti Fassaden-technik Berlin Innovations- Gmbh",
    "wof:placetype":"venue"
},
  "geometry": {"coordinates":[13.3559274673,52.4439544678],"type":"Point"}
}