{
  "type": "Feature",
  "properties": {
    "iso:country":"DE",
    "sg:address":"Marienstr. 18",
    "sg:city":"Solingen",
    "sg:phone":"+49 212/816078",
    "sg:postcode":"42657",
    "sg:province":"Nordrhein-Westfalen",
    "wof:name":"Andreas Pickenhain Ingenieur",
    "wof:placetype":"venue"
},
  "geometry": {"coordinates":[7.0677871704,51.1613845825],"type":"Point"}
}