{
  "type": "Feature",
  "properties": {
    "iso:country":"DE",
    "sg:address":"Antoniusgasse 8",
    "sg:city":"Eltville",
    "sg:postcode":"65345",
    "sg:province":"Hessen",
    "wof:name":"Pfarb\u00fccherei Rauenthal",
    "wof:placetype":"venue"
},
  "geometry": {"coordinates":[8.112255,50.059528],"type":"Point"}
}