{
  "type": "Feature",
  "properties": {
    "iso:country":"DE",
    "sg:address":"Alzeyer Str. 131-133",
    "sg:city":"Bad Kreuznach",
    "sg:postcode":"55543",
    "sg:province":"Rheinland-Pfalz",
    "wof:name":"Aldi Gmbh & Co. Kg",
    "wof:placetype":"venue"
},
  "geometry": {"coordinates":[7.8820390701,49.8311424255],"type":"Point"}
}