{
  "type": "Feature",
  "properties": {
    "iso:country":"DE",
    "sg:address":"Lenzburger Str. 8",
    "sg:city":"Waldshut-Tiengen",
    "sg:phone":"+49 7751/87340",
    "sg:postcode":"79761",
    "sg:province":"Baden-W\u00fcrttemberg",
    "wof:name":"Hochtief Ag",
    "wof:placetype":"venue"
},
  "geometry": {"coordinates":[8.228302,47.608635],"type":"Point"}
}