{
  "type": "Feature",
  "properties": {
    "iso:country":"DE",
    "sg:address":"Nordendstr. 13",
    "sg:city":"Puchheim",
    "sg:postcode":"82178",
    "sg:province":"Bayern",
    "wof:name":"Herb & Ruth Ohg",
    "wof:placetype":"venue"
},
  "geometry": {"coordinates":[11.3656692505,48.1777458191],"type":"Point"}
}