{
  "type": "Feature",
  "properties": {
    "iso:country":"DE",
    "sg:address":"Hindenburgstr. 111",
    "sg:city":"M\u00fchlacker",
    "sg:phone":"+49 7041/2836",
    "sg:postcode":"75417",
    "sg:province":"Baden-W\u00fcrttemberg",
    "wof:name":"Ali Baba",
    "wof:placetype":"venue"
},
  "geometry": {"coordinates":[8.8477401733,48.952495575],"type":"Point"}
}