{
  "type": "Feature",
  "properties": {
    "iso:country":"DE",
    "sg:address":"Hauptstr. 25",
    "sg:city":"Hamb\u00fchren",
    "sg:phone":"+49 5143/1632",
    "sg:postcode":"29313",
    "sg:province":"Niedersachsen",
    "wof:name":"E. Rickmann",
    "wof:placetype":"venue"
},
  "geometry": {"coordinates":[9.9319658279,52.6571502686],"type":"Point"}
}