{
  "type": "Feature",
  "properties": {
    "iso:country":"DE",
    "sg:address":"Marienstr. 25",
    "sg:city":"N\u00fcrnberg",
    "sg:phone":"+49 911/227320",
    "sg:postcode":"90402",
    "sg:province":"Bayern",
    "wof:name":"Pilsbar Na-und",
    "wof:placetype":"venue"
},
  "geometry": {"coordinates":[11.0886039734,49.4481048584],"type":"Point"}
}