{
  "type": "Feature",
  "properties": {
    "iso:country":"DE",
    "sg:address":"Holtenauer Str. 30",
    "sg:city":"Kiel",
    "sg:phone":"+49 431/579880",
    "sg:postcode":"24105",
    "sg:province":"Schleswig-Holstein",
    "wof:name":"Hapag-lloyd Reiseb\u00fcro Gmbh",
    "wof:placetype":"venue"
},
  "geometry": {"coordinates":[10.1324672699,54.3303947449],"type":"Point"}
}