{
  "type": "Feature",
  "properties": {
    "iso:country":"DE",
    "sg:address":"Burhaver Str. 57",
    "sg:city":"Butjadingen",
    "sg:postcode":"26969",
    "sg:province":"Niedersachsen",
    "wof:name":"Hp Automaten Inh. Heinz-peter Blohm E. K.",
    "wof:placetype":"venue"
},
  "geometry": {"coordinates":[8.4407730103,53.5428886414],"type":"Point"}
}