{
  "type": "Feature",
  "properties": {
    "iso:country":"DE",
    "sg:address":"K\u00f6nigsberger Str. 16",
    "sg:city":"Landstuhl",
    "sg:phone":"+49 6371/917984",
    "sg:postcode":"66849",
    "sg:province":"Rheinland-Pfalz",
    "wof:name":"Manfred Wiehn",
    "wof:placetype":"venue"
},
  "geometry": {"coordinates":[7.5693669319,49.3997459412],"type":"Point"}
}