{
  "type": "Feature",
  "properties": {
    "iso:country":"DE",
    "sg:address":"Zinglerstr. 89",
    "sg:city":"Ulm",
    "sg:phone":"+49 731/9317455",
    "sg:postcode":"89077",
    "sg:province":"Baden-W\u00fcrttemberg",
    "wof:name":"B. Muszynska",
    "wof:placetype":"venue"
},
  "geometry": {"coordinates":[9.9790582657,48.3899841309],"type":"Point"}
}