{
  "type": "Feature",
  "properties": {
    "iso:country":"DE",
    "sg:address":"Villastr. 48",
    "sg:city":"Reutlingen",
    "sg:phone":"+49 7121/504160",
    "sg:postcode":"72770",
    "sg:province":"Baden-W\u00fcrttemberg",
    "wof:name":"Fr Unternehmensberatung Gmbh (bdu)",
    "wof:placetype":"venue"
},
  "geometry": {"coordinates":[9.184483,48.501797],"type":"Point"}
}