{
  "type": "Feature",
  "properties": {
    "iso:country":"DE",
    "sg:address":"Calwer Str. 58",
    "sg:city":"Stuttgart",
    "sg:phone":"+49 711/293410",
    "sg:postcode":"70173",
    "sg:province":"Baden-W\u00fcrttemberg",
    "wof:name":"Elisabeth Gabor",
    "wof:placetype":"venue"
},
  "geometry": {"coordinates":[9.1727399826,48.7751617432],"type":"Point"}
}