{
  "type": "Feature",
  "properties": {
    "iso:country":"DE",
    "sg:address":"Gartenstr. 8",
    "sg:city":"Radolfzell",
    "sg:phone":"+49 7732/3687",
    "sg:postcode":"78315",
    "sg:province":"Baden-W\u00fcrttemberg",
    "wof:name":"Ferdinand Ruf",
    "wof:placetype":"venue"
},
  "geometry": {"coordinates":[8.973236,47.738865],"type":"Point"}
}