{
  "type": "Feature",
  "properties": {
    "iso:country":"DE",
    "sg:address":"Am Lindenbuckel 50",
    "sg:city":"Tettnang",
    "sg:phone":"+49 7542/52243",
    "sg:postcode":"88069",
    "sg:province":"Baden-W\u00fcrttemberg",
    "wof:name":"Ariane K\u00f6ppe",
    "wof:placetype":"venue"
},
  "geometry": {"coordinates":[9.5896587372,47.6576042175],"type":"Point"}
}