{
  "type": "Feature",
  "properties": {
    "iso:country":"DE",
    "sg:address":"Bahnhofstr. 8",
    "sg:city":"Emlichheim",
    "sg:phone":"+49 5921/35556",
    "sg:postcode":"49824",
    "sg:province":"Niedersachsen",
    "wof:name":"Benno Hilberink E. K.",
    "wof:placetype":"venue"
},
  "geometry": {"coordinates":[6.8536920547,52.6077194214],"type":"Point"}
}