{
  "type": "Feature",
  "properties": {
    "iso:country":"DE",
    "sg:address":"Im M\u00e4ttel 11",
    "sg:city":"Neuried",
    "sg:phone":"+49 7807/2354",
    "sg:postcode":"77743",
    "sg:province":"Baden-W\u00fcrttemberg",
    "wof:name":"Manfred Fels",
    "wof:placetype":"venue"
},
  "geometry": {"coordinates":[7.8049740791,48.4659919739],"type":"Point"}
}