{
  "type": "Feature",
  "properties": {
    "iso:country":"DE",
    "sg:address":"Am Bahnhof Frauendorf",
    "sg:city":"Frohburg",
    "sg:postcode":"04654",
    "sg:province":"Sachsen",
    "wof:name":"A & B Spezialbau Gmbh",
    "wof:placetype":"venue"
},
  "geometry": {"coordinates":[12.61126,51.063656],"type":"Point"}
}