{
  "type": "Feature",
  "properties": {
    "iso:country":"DE",
    "sg:address":"Hombrucher Weg 21",
    "sg:city":"Iserlohn",
    "sg:phone":"+49 2371/30188",
    "sg:postcode":"58638",
    "sg:province":"Nordrhein-Westfalen",
    "wof:name":"Br\u00fcckenkamp Gmbh",
    "wof:placetype":"venue"
},
  "geometry": {"coordinates":[7.686201,51.39452],"type":"Point"}
}