{
  "type": "Feature",
  "properties": {
    "iso:country":"DE",
    "sg:address":"Wengen 24",
    "sg:city":"Die\u00dfen",
    "sg:phone":"+49 8807/7102",
    "sg:postcode":"86911",
    "sg:province":"Bayern",
    "wof:name":"A. Lotter",
    "wof:placetype":"venue"
},
  "geometry": {"coordinates":[11.0769853592,47.9406166077],"type":"Point"}
}