{
  "type": "Feature",
  "properties": {
    "iso:country":"DE",
    "sg:address":"Hauptstr. 34",
    "sg:city":"Kressbronn",
    "sg:phone":"+49 4975/435951",
    "sg:postcode":"88079",
    "sg:province":"Baden-W\u00fcrttemberg",
    "wof:name":"Kreissparkasse Friedrichshafen",
    "wof:placetype":"venue"
},
  "geometry": {"coordinates":[9.599852,47.595409],"type":"Point"}
}