{
  "type": "Feature",
  "properties": {
    "iso:country":"DE",
    "sg:address":"Oberdorf 11",
    "sg:city":"Geldersheim",
    "sg:phone":"+49 9721/802616",
    "sg:postcode":"97505",
    "sg:province":"Bayern",
    "wof:name":"Weinstube Zehnthof",
    "wof:placetype":"venue"
},
  "geometry": {"coordinates":[10.1544446945,50.0422706604],"type":"Point"}
}