{
  "type": "Feature",
  "properties": {
    "iso:country":"DE",
    "sg:address":"Waldhornweg 27",
    "sg:city":"Potsdam",
    "sg:postcode":"14480",
    "sg:province":"Brandenburg",
    "wof:name":"Imku Handel- Und Servicegesellschaft Mbh",
    "wof:placetype":"venue"
},
  "geometry": {"coordinates":[13.1451778412,52.3789825439],"type":"Point"}
}