{
  "type": "Feature",
  "properties": {
    "iso:country":"DE",
    "sg:address":"Tannenbergstr. 40",
    "sg:city":"Kirchheim",
    "sg:phone":"+49 7021/52101",
    "sg:postcode":"73230",
    "sg:province":"Baden-W\u00fcrttemberg",
    "wof:name":"Rauner Apotheke Stephan Hubert",
    "wof:placetype":"venue"
},
  "geometry": {"coordinates":[9.45769,48.639942],"type":"Point"}
}