{
  "type": "Feature",
  "properties": {
    "iso:country":"DE",
    "sg:address":"Letterhausstr. 32",
    "sg:city":"Delmenhorst",
    "sg:phone":"+49 4221/22446",
    "sg:postcode":"27755",
    "sg:province":"Niedersachsen",
    "wof:name":"Endemann",
    "wof:placetype":"venue"
},
  "geometry": {"coordinates":[8.6217775345,53.0265350342],"type":"Point"}
}