{
  "type": "Feature",
  "properties": {
    "iso:country":"DE",
    "sg:address":"Rohrbacher Str. 60",
    "sg:city":"Heidelberg",
    "sg:postcode":"69115",
    "sg:province":"Baden-W\u00fcrttemberg",
    "wof:name":"Eubler Druck Gmbh",
    "wof:placetype":"venue"
},
  "geometry": {"coordinates":[8.691402,49.402344],"type":"Point"}
}