{
  "type": "Feature",
  "properties": {
    "iso:country":"DE",
    "sg:address":"Lehmkuhl7",
    "sg:city":"Erfde",
    "sg:phone":"+49 4333",
    "sg:postcode":"24803",
    "sg:province":"Schleswig-Holstein",
    "wof:name":"Kunstmaler Helmut Knudsen",
    "wof:placetype":"venue"
},
  "geometry": {"coordinates":[9.325446,54.308956],"type":"Point"}
}