{
  "type": "Feature",
  "properties": {
    "iso:country":"DE",
    "sg:address":"Eglsee 4",
    "sg:city":"Wurmannsquick",
    "sg:phone":"+49 8725/941327",
    "sg:postcode":"84329",
    "sg:province":"Bayern",
    "wof:name":"M.i.d. Deko-design Inh. Walter Wegerer",
    "wof:placetype":"venue"
},
  "geometry": {"coordinates":[12.785655,48.352497],"type":"Point"}
}