{
  "type": "Feature",
  "properties": {
    "iso:country":"DE",
    "sg:address":"Ottostr. 25",
    "sg:city":"Marktredwitz",
    "sg:phone":"+49 9231/2252",
    "sg:postcode":"95615",
    "sg:province":"Bayern",
    "wof:name":"Hans Zeitlhofer",
    "wof:placetype":"venue"
},
  "geometry": {"coordinates":[12.086186409,49.9997901917],"type":"Point"}
}