{
  "type": "Feature",
  "properties": {
    "iso:country":"DE",
    "sg:address":"Alte Dorfstr. 4",
    "sg:city":"Lingen",
    "sg:phone":"+49 591/3374",
    "sg:postcode":"49811",
    "sg:province":"Niedersachsen",
    "wof:name":"Fehren Gmbh",
    "wof:placetype":"venue"
},
  "geometry": {"coordinates":[7.386217,52.5103],"type":"Point"}
}