{
  "type": "Feature",
  "properties": {
    "iso:country":"DE",
    "sg:address":"Laurentiusplatz 3",
    "sg:city":"M\u00f6nchengladbach",
    "sg:phone":"+49 2166/680226",
    "sg:postcode":"41199",
    "sg:province":"Nordrhein-Westfalen",
    "wof:name":"Heimatklause",
    "wof:placetype":"venue"
},
  "geometry": {"coordinates":[6.4505848885,51.1326179504],"type":"Point"}
}