{
  "type": "Feature",
  "properties": {
    "iso:country":"DE",
    "sg:address":"Kellerberg 34",
    "sg:city":"Inning",
    "sg:postcode":"82266",
    "sg:province":"Bayern",
    "wof:name":"Kep Drei Ag",
    "wof:placetype":"venue"
},
  "geometry": {"coordinates":[11.1604003906,48.0794639587],"type":"Point"}
}