{
  "type": "Feature",
  "properties": {
    "iso:country":"DE",
    "sg:address":"Stockhausen",
    "sg:city":"Schmallenberg",
    "sg:phone":"+49 2971/312109",
    "sg:postcode":"57392",
    "sg:province":"Nordrhein-Westfalen",
    "wof:name":"Golfshop Des Golfclubs Sellinghausen",
    "wof:placetype":"venue"
},
  "geometry": {"coordinates":[8.285818,51.154045],"type":"Point"}
}