{
  "type": "Feature",
  "properties": {
    "iso:country":"DE",
    "sg:address":"Am Bahndamm 31",
    "sg:city":"Emlichheim",
    "sg:phone":"+49 5943/639",
    "sg:postcode":"49824",
    "sg:province":"Niedersachsen",
    "wof:name":"Jan Germs",
    "wof:placetype":"venue"
},
  "geometry": {"coordinates":[6.847061,52.61042],"type":"Point"}
}