{
  "type": "Feature",
  "properties": {
    "iso:country":"DE",
    "sg:address":"Schilfstr. 7",
    "sg:city":"Hessisch Oldendorf",
    "sg:phone":"+49 5152/2249",
    "sg:postcode":"31840",
    "sg:province":"Niedersachsen",
    "wof:name":"U. Meier Inh. Rosemarie Schwake",
    "wof:placetype":"venue"
},
  "geometry": {"coordinates":[9.2475452423,52.171043396],"type":"Point"}
}