{
  "type": "Feature",
  "properties": {
    "iso:country":"DE",
    "sg:address":"Schulstr. 18",
    "sg:city":"Winden",
    "sg:phone":"+49 7685/364",
    "sg:postcode":"79297",
    "sg:province":"Baden-W\u00fcrttemberg",
    "wof:name":"Franz Volk",
    "wof:placetype":"venue"
},
  "geometry": {"coordinates":[7.829448,50.336662],"type":"Point"}
}