{
  "type": "Feature",
  "properties": {
    "iso:country":"DE",
    "sg:address":"48455",
    "sg:city":"Bad Bentheim",
    "sg:phone":"+49 5922/822",
    "sg:postcode":"48455",
    "sg:province":"Niedersachsen",
    "wof:name":"Deutsche Bahn Ag",
    "wof:placetype":"venue"
},
  "geometry": {"coordinates":[7.1171598434,52.3070487976],"type":"Point"}
}