{
  "type": "Feature",
  "properties": {
    "iso:country":"DE",
    "sg:address":"Poststr. 8a",
    "sg:city":"Schwarzenbruck",
    "sg:phone":"+49 9128/2673",
    "sg:postcode":"90592",
    "sg:province":"Bayern",
    "wof:name":"Richard M\u00fcller Rechtsanwalt",
    "wof:placetype":"venue"
},
  "geometry": {"coordinates":[11.2380590439,49.3564758301],"type":"Point"}
}