{
  "type": "Feature",
  "properties": {
    "iso:country":"DE",
    "sg:address":"Bo\u00dflerstr. 55",
    "sg:city":"Wendlingen",
    "sg:phone":"+49 7024/920710",
    "sg:postcode":"73240",
    "sg:province":"Baden-W\u00fcrttemberg",
    "wof:name":"Schlosserei H. Schmitt Gmbh",
    "wof:placetype":"venue"
},
  "geometry": {"coordinates":[9.396769,48.666321],"type":"Point"}
}