{
  "type": "Feature",
  "properties": {
    "iso:country":"DE",
    "sg:address":"Nymphenburger Str. 137",
    "sg:city":"M\u00fcnchen",
    "sg:phone":"+49 89/1266750",
    "sg:postcode":"80636",
    "sg:province":"Bayern",
    "wof:name":"Edgar Online Gesellschaft F\u00fcr Multimedia-",
    "wof:placetype":"venue"
},
  "geometry": {"coordinates":[11.5385837555,48.1512718201],"type":"Point"}
}