{
  "type": "Feature",
  "properties": {
    "iso:country":"DE",
    "sg:address":"Sch\u00fctzenweg 33 b",
    "sg:city":"Oldenburg",
    "sg:postcode":"26129",
    "sg:province":"Niedersachsen",
    "wof:name":"Trade Sportartikel Vertriebs Gmbh",
    "wof:placetype":"venue"
},
  "geometry": {"coordinates":[8.1899490356,53.1490974426],"type":"Point"}
}