{
  "type": "Feature",
  "properties": {
    "iso:country":"DE",
    "sg:address":"Waldweg 37",
    "sg:city":"Dessau",
    "sg:phone":"+49 340/619070",
    "sg:postcode":"06846",
    "sg:province":"Sachsen-Anhalt",
    "wof:name":"Volker Thielemann Anlageberater",
    "wof:placetype":"venue"
},
  "geometry": {"coordinates":[12.2138624191,51.8417167664],"type":"Point"}
}