{
  "type": "Feature",
  "properties": {
    "iso:country":"DE",
    "sg:address":"Krugbrink 5",
    "sg:city":"F\u00fcrstenberg",
    "sg:phone":"+49 5271/5390",
    "sg:postcode":"37699",
    "sg:province":"Niedersachsen",
    "wof:name":"Karl-august Busche",
    "wof:placetype":"venue"
},
  "geometry": {"coordinates":[9.4011440277,51.7303466797],"type":"Point"}
}