{
  "type": "Feature",
  "properties": {
    "iso:country":"DE",
    "sg:address":"Wiesenstr. 89",
    "sg:city":"St. Ingbert",
    "sg:phone":"+49 6894/99710",
    "sg:postcode":"66386",
    "sg:province":"Saarland",
    "wof:name":"Ibp Ingenieurb\u00fcro Piro Gmbh",
    "wof:placetype":"venue"
},
  "geometry": {"coordinates":[7.1180348396,49.2720985413],"type":"Point"}
}