{
  "type": "Feature",
  "properties": {
    "iso:country":"DE",
    "sg:address":"Kl\u00f6pflesberg 13",
    "sg:city":"Furth im Wald",
    "sg:phone":"+49 9973/9643",
    "sg:postcode":"93437",
    "sg:province":"Bayern",
    "wof:name":"Gasthaus Alfred Jelinek",
    "wof:placetype":"venue"
},
  "geometry": {"coordinates":[12.886598587,49.3219032288],"type":"Point"}
}