{
  "type": "Feature",
  "properties": {
    "iso:country":"DE",
    "sg:address":"Alt-Haarener Str. 40",
    "sg:city":"Aachen",
    "sg:phone":"+49 241/961124",
    "sg:postcode":"52080",
    "sg:province":"Nordrhein-Westfalen",
    "wof:name":"En Plus Mode",
    "wof:placetype":"venue"
},
  "geometry": {"coordinates":[6.1245,50.794666],"type":"Point"}
}