{
  "type": "Feature",
  "properties": {
    "iso:country":"DE",
    "sg:address":"Nassauerstr. 3",
    "sg:city":"Kleve",
    "sg:phone":"+49 2821/753190",
    "sg:postcode":"47533",
    "sg:province":"Nordrhein-Westfalen",
    "wof:name":"Knubben Spezialtiefbau Gmbh",
    "wof:placetype":"venue"
},
  "geometry": {"coordinates":[6.1375641823,51.784866333],"type":"Point"}
}