{
  "type": "Feature",
  "properties": {
    "iso:country":"DE",
    "sg:address":"S\u00fcdstr. 8",
    "sg:city":"Asperg",
    "sg:postcode":"71679",
    "sg:province":"Baden-W\u00fcrttemberg",
    "wof:name":"Espi Verkaufsf\u00f6rderung Gmbh",
    "wof:placetype":"venue"
},
  "geometry": {"coordinates":[9.1389932632,48.8999443054],"type":"Point"}
}