{
  "type": "Feature",
  "properties": {
    "iso:country":"DE",
    "sg:address":"K\u00f6rnerstr. 12",
    "sg:city":"Ludwigsburg",
    "sg:phone":"+49 7141/924219",
    "sg:postcode":"71634",
    "sg:province":"Baden-W\u00fcrttemberg",
    "wof:name":"Dr. Med. Helma Jung \u00c4rztin F\u00fcr Allgemeinmedizin",
    "wof:placetype":"venue"
},
  "geometry": {"coordinates":[9.1891746521,48.897731781],"type":"Point"}
}