{
  "type": "Feature",
  "properties": {
    "iso:country":"DE",
    "sg:address":"Colkwitzer Weg 16",
    "sg:city":"Markkleeberg",
    "sg:phone":"+49 341/3380328",
    "sg:postcode":"04416",
    "sg:province":"Sachsen",
    "wof:name":"Holger Vom Hofe",
    "wof:placetype":"venue"
},
  "geometry": {"coordinates":[12.4083452225,51.2738647461],"type":"Point"}
}