{
  "type": "Feature",
  "properties": {
    "iso:country":"DE",
    "sg:address":"Zum Kugelfang 8-12",
    "sg:city":"Naila",
    "sg:phone":"+49 9282/9370",
    "sg:postcode":"95119",
    "sg:province":"Bayern",
    "wof:name":"Serag-wiessner Kg",
    "wof:placetype":"venue"
},
  "geometry": {"coordinates":[11.6971092224,50.3250465393],"type":"Point"}
}