{
  "type": "Feature",
  "properties": {
    "iso:country":"DE",
    "sg:address":"Am Beyerteich 4",
    "sg:city":"Perleberg",
    "sg:phone":"+49 3876/785223",
    "sg:postcode":"19348",
    "sg:province":"Brandenburg",
    "wof:name":"Kommunikationstechnik Gbr",
    "wof:placetype":"venue"
},
  "geometry": {"coordinates":[11.8513841629,53.0750160217],"type":"Point"}
}