{
  "type": "Feature",
  "properties": {
    "iso:country":"DE",
    "sg:address":"Wunsiedler Str. 3",
    "sg:city":"Kirchenlamitz",
    "sg:phone":"+49 9285/388",
    "sg:postcode":"95158",
    "sg:province":"Bayern",
    "wof:name":"Roland Reinel",
    "wof:placetype":"venue"
},
  "geometry": {"coordinates":[11.950855,50.151539],"type":"Point"}
}