{
  "type": "Feature",
  "properties": {
    "iso:country":"DE",
    "sg:address":"Bergstr. 7",
    "sg:city":"L\u00fcnen",
    "sg:phone":"+49 2306/21100",
    "sg:postcode":"44532",
    "sg:province":"Nordrhein-Westfalen",
    "wof:name":"Tennis Oase Gmbh",
    "wof:placetype":"venue"
},
  "geometry": {"coordinates":[7.5142121315,51.6040039062],"type":"Point"}
}