{
  "type": "Feature",
  "properties": {
    "iso:country":"DE",
    "sg:address":"Zenettistr. 46",
    "sg:city":"M\u00fcnchen",
    "sg:phone":"+49 89/774184",
    "sg:postcode":"80337",
    "sg:province":"Bayern",
    "wof:name":"Katholisches Pfarramt St. Andreas",
    "wof:placetype":"venue"
},
  "geometry": {"coordinates":[11.5534620285,48.1263389587],"type":"Point"}
}