{
  "type": "Feature",
  "properties": {
    "iso:country":"DE",
    "sg:address":"Marktstr. 4",
    "sg:city":"G\u00fcntersberge",
    "sg:phone":"+49 39488/394",
    "sg:postcode":"06507",
    "sg:province":"Sachsen-Anhalt",
    "wof:name":"Marina M\u00fcller",
    "wof:placetype":"venue"
},
  "geometry": {"coordinates":[10.980679,51.644295],"type":"Point"}
}