{
  "type": "Feature",
  "properties": {
    "iso:country":"DE",
    "sg:address":"Langestr. 116",
    "sg:city":"K\u00e4mpfelbach",
    "sg:phone":"+49 7231/17422",
    "sg:postcode":"75236",
    "sg:province":"Baden-W\u00fcrttemberg",
    "wof:name":"Mrut Me\u00df- Regel- Und Umwelttechnik Gmbh & Co. Kg",
    "wof:placetype":"venue"
},
  "geometry": {"coordinates":[8.634928,48.933247],"type":"Point"}
}