{
  "type": "Feature",
  "properties": {
    "iso:country":"DE",
    "sg:address":"Lessingstr. 20 a",
    "sg:city":"Linkenheim-Hochstetten",
    "sg:phone":"+49 7247/6855",
    "sg:postcode":"76351",
    "sg:province":"Baden-W\u00fcrttemberg",
    "wof:name":"Mummert Verm\u00f6gens- Verwaltungs Gmbh",
    "wof:placetype":"venue"
},
  "geometry": {"coordinates":[8.4175767899,49.1338996887],"type":"Point"}
}