{
  "type": "Feature",
  "properties": {
    "iso:country":"DE",
    "sg:address":"Goldacker 46",
    "sg:city":"Steinfeld",
    "sg:phone":"+49 4641/3224",
    "sg:postcode":"24888",
    "sg:province":"Schleswig-Holstein",
    "wof:name":"Siegfried Droese",
    "wof:placetype":"venue"
},
  "geometry": {"coordinates":[9.746165,54.597115],"type":"Point"}
}