{
  "type": "Feature",
  "properties": {
    "iso:country":"DE",
    "sg:address":"Kesselgasse 29",
    "sg:city":"Alsheim",
    "sg:phone":"+49 6249/5240",
    "sg:postcode":"67577",
    "sg:province":"Rheinland-Pfalz",
    "wof:name":"Christian Und K. Kissel",
    "wof:placetype":"venue"
},
  "geometry": {"coordinates":[8.3387804031,49.7677764893],"type":"Point"}
}