{
  "type": "Feature",
  "properties": {
    "iso:country":"DE",
    "sg:address":"Bahnhofpl. 17",
    "sg:city":"Straubing",
    "sg:phone":"+49 9421/8650",
    "sg:postcode":"94315",
    "sg:province":"Bayern",
    "wof:name":"Aok Bayern Direktion Straubing",
    "wof:placetype":"venue"
},
  "geometry": {"coordinates":[12.570327,48.879601],"type":"Point"}
}