{
  "type": "Feature",
  "properties": {
    "iso:country":"DE",
    "sg:address":"Von-der-Tann-Str. 4",
    "sg:city":"Waldkraiburg",
    "sg:phone":"+49 8638/4146",
    "sg:postcode":"84478",
    "sg:province":"Bayern",
    "wof:name":"Franke Grabdenkm\u00e4ler",
    "wof:placetype":"venue"
},
  "geometry": {"coordinates":[12.3867301941,48.2059211731],"type":"Point"}
}