{
  "type": "Feature",
  "properties": {
    "iso:country":"DE",
    "sg:address":"Idsteiner Str. 69",
    "sg:city":"Niedernhausen",
    "sg:phone":"+49 6127/98910",
    "sg:postcode":"65527",
    "sg:province":"Hessen",
    "wof:name":"As Gabelstapler Alexander Schr\u00f6der",
    "wof:placetype":"venue"
},
  "geometry": {"coordinates":[8.318482399,50.1605529785],"type":"Point"}
}