{
  "type": "Feature",
  "properties": {
    "iso:country":"DE",
    "sg:address":"In der Schneithohl 3",
    "sg:city":"Kronberg",
    "sg:phone":"+49 6173/93770",
    "sg:postcode":"61476",
    "sg:province":"Hessen",
    "wof:name":"G\u00fcnther Hellriegel Gmbh",
    "wof:placetype":"venue"
},
  "geometry": {"coordinates":[8.5483093262,50.1770439148],"type":"Point"}
}