{
  "type": "Feature",
  "properties": {
    "iso:country":"DE",
    "sg:address":"Franz-Rupp-Str. 2",
    "sg:city":"Schongau",
    "sg:phone":"+49 8861/23830",
    "sg:postcode":"86956",
    "sg:province":"Bayern",
    "wof:name":"Mucheyer",
    "wof:placetype":"venue"
},
  "geometry": {"coordinates":[10.883046,47.819302],"type":"Point"}
}