{
  "type": "Feature",
  "properties": {
    "iso:country":"DE",
    "sg:address":"Johannesstr. 21 - 22",
    "sg:city":"Berlin",
    "sg:phone":"+49 30/80912054",
    "sg:postcode":"14165",
    "sg:province":"Berlin",
    "wof:name":"Seniorenwohnhaus Haus Am Park",
    "wof:placetype":"venue"
},
  "geometry": {"coordinates":[13.257652,52.423931],"type":"Point"}
}