{
  "type": "Feature",
  "properties": {
    "iso:country":"DE",
    "sg:address":"Niederhofheimer Str. 7",
    "sg:city":"Kelkheim",
    "sg:phone":"+49 6195/902893",
    "sg:postcode":"65779",
    "sg:province":"Hessen",
    "wof:name":"Werner Grimm",
    "wof:placetype":"venue"
},
  "geometry": {"coordinates":[8.466794014,50.1287612915],"type":"Point"}
}