{
  "type": "Feature",
  "properties": {
    "iso:country":"DE",
    "sg:address":"Sommerauer Str. 4",
    "sg:city":"Feuchtwangen",
    "sg:postcode":"91555",
    "sg:province":"Bayern",
    "wof:name":"Westra-druck Kg",
    "wof:placetype":"venue"
},
  "geometry": {"coordinates":[10.3154783249,49.1652069092],"type":"Point"}
}