{
  "type": "Feature",
  "properties": {
    "iso:country":"DE",
    "sg:address":"Stra\u00dfburger Str. 4",
    "sg:city":"Eschwege",
    "sg:phone":"+49 5651/20897",
    "sg:postcode":"37269",
    "sg:province":"Hessen",
    "wof:name":"Mick Beteiligungs- Verwaltung-beratung Gmbh",
    "wof:placetype":"venue"
},
  "geometry": {"coordinates":[10.0222034454,51.1963386536],"type":"Point"}
}