{
  "type": "Feature",
  "properties": {
    "iso:country":"DE",
    "sg:address":"Berthold-Dege-Weg 4",
    "sg:city":"Goslar",
    "sg:postcode":"38644",
    "sg:province":"Niedersachsen",
    "wof:name":"Betten Profi Gmbh",
    "wof:placetype":"venue"
},
  "geometry": {"coordinates":[10.4026947021,51.9503593445],"type":"Point"}
}