{
  "type": "Feature",
  "properties": {
    "iso:country":"DE",
    "sg:address":"Alter Markt 16",
    "sg:city":"Balingen",
    "sg:phone":"+49 7433/23300",
    "sg:postcode":"72336",
    "sg:province":"Baden-W\u00fcrttemberg",
    "wof:name":"Gisela Maurer",
    "wof:placetype":"venue"
},
  "geometry": {"coordinates":[8.8528881073,48.274936676],"type":"Point"}
}