{
  "type": "Feature",
  "properties": {
    "iso:country":"DE",
    "sg:address":"Osterweg 76",
    "sg:city":"Nieb\u00fcll",
    "sg:phone":"+49 4661/3656",
    "sg:postcode":"25899",
    "sg:province":"Schleswig-Holstein",
    "wof:name":"Friesisches Heimatmuseum Freilichtmuseum Hansen",
    "wof:placetype":"venue"
},
  "geometry": {"coordinates":[8.822418,54.779922],"type":"Point"}
}