{
  "type": "Feature",
  "properties": {
    "iso:country":"DE",
    "sg:address":"Deckenpfronner Str. 17",
    "sg:city":"Aidlingen",
    "sg:phone":"+49 7056/8541",
    "sg:postcode":"71134",
    "sg:province":"Baden-W\u00fcrttemberg",
    "wof:name":"Kalmbach & Partner",
    "wof:placetype":"venue"
},
  "geometry": {"coordinates":[8.8522891998,48.6769180298],"type":"Point"}
}