{
  "type": "Feature",
  "properties": {
    "iso:country":"DE",
    "sg:address":"Handwerkerstr. 71",
    "sg:city":"Voerde",
    "sg:phone":"+49 2855/8406",
    "sg:postcode":"46562",
    "sg:province":"Nordrhein-Westfalen",
    "wof:name":"Rolf Jakobs",
    "wof:placetype":"venue"
},
  "geometry": {"coordinates":[6.617733,51.60574],"type":"Point"}
}