{
  "type": "Feature",
  "properties": {
    "iso:country":"DE",
    "sg:address":"Mittelweg 5",
    "sg:city":"Felsberg",
    "sg:phone":"+49 5662/4686",
    "sg:postcode":"34587",
    "sg:province":"Hessen",
    "wof:name":"Karl Huber",
    "wof:placetype":"venue"
},
  "geometry": {"coordinates":[9.414755,51.114731],"type":"Point"}
}