{
  "type": "Feature",
  "properties": {
    "iso:country":"DE",
    "sg:address":"Gneisenaustr. 47",
    "sg:city":"Dinslaken",
    "sg:phone":"+49 2064/6070",
    "sg:postcode":"46535",
    "sg:province":"Nordrhein-Westfalen",
    "wof:name":"Seniorenzentrum Wilhelm-lantermann-haus",
    "wof:placetype":"venue"
},
  "geometry": {"coordinates":[6.723801,51.564819],"type":"Point"}
}