{
  "type": "Feature",
  "properties": {
    "iso:country":"DE",
    "sg:address":"Braunschweiger Str. 41",
    "sg:city":"Eicklingen",
    "sg:phone":"+49 5144/56372",
    "sg:postcode":"29358",
    "sg:province":"Niedersachsen",
    "wof:name":"Imbi\u00df An Der B 214",
    "wof:placetype":"venue"
},
  "geometry": {"coordinates":[10.1849756241,52.5472221375],"type":"Point"}
}