{
  "type": "Feature",
  "properties": {
    "iso:country":"DE",
    "sg:address":"In den Halben Morgen 7",
    "sg:city":"Heppenheim",
    "sg:phone":"+49 6252/7954971",
    "sg:postcode":"64646",
    "sg:province":"Hessen",
    "wof:name":"Tipto Internet Marketing Und Design",
    "wof:placetype":"venue"
},
  "geometry": {"coordinates":[8.63643,49.650768],"type":"Point"}
}