{
  "type": "Feature",
  "properties": {
    "iso:country":"DE",
    "sg:address":"Hochdahler Str. 127",
    "sg:city":"Hilden",
    "sg:phone":"+49 2103/44258",
    "sg:postcode":"40724",
    "sg:province":"Nordrhein-Westfalen",
    "wof:name":"Aral Tankstelle",
    "wof:placetype":"venue"
},
  "geometry": {"coordinates":[6.9384088516,51.1765632629],"type":"Point"}
}