{
  "type": "Feature",
  "properties": {
    "iso:country":"DE",
    "sg:address":"Modersohnstr. 66",
    "sg:city":"Berlin",
    "sg:phone":"+49 30/2911526",
    "sg:postcode":"10245",
    "sg:province":"Berlin",
    "wof:name":"Dirk A\u00dfmann",
    "wof:placetype":"venue"
},
  "geometry": {"coordinates":[13.45597,52.501553],"type":"Point"}
}