{
  "type": "Feature",
  "properties": {
    "iso:country":"DE",
    "sg:address":"Gatower Str. 197",
    "sg:city":"Berlin",
    "sg:phone":"+49 30/3626454",
    "sg:postcode":"13595",
    "sg:province":"Berlin",
    "wof:name":"L\u00fcttschwager & Partner Reha-zentrum Gmbh",
    "wof:placetype":"venue"
},
  "geometry": {"coordinates":[13.1797952652,52.5023498535],"type":"Point"}
}