{
  "type": "Feature",
  "properties": {
    "iso:country":"DE",
    "sg:address":"Wodanstr. 30",
    "sg:city":"Dortmund",
    "sg:phone":"+49 231/350328",
    "sg:postcode":"44359",
    "sg:province":"Nordrhein-Westfalen",
    "wof:name":"A. Zimmermann",
    "wof:placetype":"venue"
},
  "geometry": {"coordinates":[7.384203,51.563408],"type":"Point"}
}