{
  "type": "Feature",
  "properties": {
    "iso:country":"DE",
    "sg:address":"Im Wiesengrund 2",
    "sg:city":"Kutenholz",
    "sg:phone":"+49 4762/8226",
    "sg:postcode":"27449",
    "sg:province":"Niedersachsen",
    "wof:name":"Hartmut Wiebusch",
    "wof:placetype":"venue"
},
  "geometry": {"coordinates":[9.302848,53.506454],"type":"Point"}
}