{
  "type": "Feature",
  "properties": {
    "iso:country":"DE",
    "sg:address":"Marktstr. 8",
    "sg:city":"Ettlingen",
    "sg:phone":"+49 7243/16018",
    "sg:postcode":"76275",
    "sg:province":"Baden-W\u00fcrttemberg",
    "wof:name":"Schlo\u00df-apotheke",
    "wof:placetype":"venue"
},
  "geometry": {"coordinates":[8.407082,48.940956],"type":"Point"}
}