{
  "type": "Feature",
  "properties": {
    "iso:country":"DE",
    "sg:address":"Gro\u00dfe Rheinstr 40",
    "sg:city":"Philippsburg",
    "sg:phone":"+49 7256/944316",
    "sg:postcode":"76661",
    "sg:province":"Baden-W\u00fcrttemberg",
    "wof:name":"Ikt Kunststofftechnik Gmbh",
    "wof:placetype":"venue"
},
  "geometry": {"coordinates":[8.402093,49.237301],"type":"Point"}
}