{
  "type": "Feature",
  "properties": {
    "iso:country":"DE",
    "sg:address":"Lohbergenstr. 46",
    "sg:city":"Buchholz",
    "sg:phone":"+49 4181/6803",
    "sg:postcode":"21244",
    "sg:province":"Niedersachsen",
    "wof:name":"Haus Steinbachtal Altenheim",
    "wof:placetype":"venue"
},
  "geometry": {"coordinates":[9.865838,53.315994],"type":"Point"}
}