{
  "type": "Feature",
  "properties": {
    "iso:country":"DE",
    "sg:address":"Walkem\u00fchlenweg 26",
    "sg:city":"G\u00f6ttingen",
    "sg:phone":"+49 551/7703645",
    "sg:postcode":"37083",
    "sg:province":"Niedersachsen",
    "wof:name":"Pillenkn\u00e4ckeren Co Tobias Schr\u00f6dter",
    "wof:placetype":"venue"
},
  "geometry": {"coordinates":[9.9356956482,51.5275802612],"type":"Point"}
}