{
  "type": "Feature",
  "properties": {
    "iso:country":"DE",
    "sg:address":"Postfach 3247 (Kugel)",
    "sg:city":"Michelstadt",
    "sg:postcode":"64713",
    "sg:province":"Hessen",
    "wof:name":"Ibiza & Punta Guide Reisef\u00fchrer & Lastminute Buchuhttp://www.",
    "wof:placetype":"venue"
},
  "geometry": {"coordinates":[9.0001,49.677761],"type":"Point"}
}