{
  "type": "Feature",
  "properties": {
    "iso:country":"DE",
    "sg:address":"M\u00fchlweg 85a",
    "sg:city":"Weiden",
    "sg:phone":"+49 961/24469",
    "sg:postcode":"92637",
    "sg:province":"Bayern",
    "wof:name":"J. Krafczyk-immobilien",
    "wof:placetype":"venue"
},
  "geometry": {"coordinates":[12.1352014542,49.6714782715],"type":"Point"}
}