{
  "type": "Feature",
  "properties": {
    "iso:country":"DE",
    "sg:address":"Neue Str. 17a",
    "sg:city":"Hagen",
    "sg:phone":"+49 2331/401090",
    "sg:postcode":"58135",
    "sg:province":"Nordrhein-Westfalen",
    "wof:name":"B. Mische-topp",
    "wof:placetype":"venue"
},
  "geometry": {"coordinates":[7.399125,51.337887],"type":"Point"}
}