{
  "type": "Feature",
  "properties": {
    "iso:country":"DE",
    "sg:address":"Marbacher Gasse 12",
    "sg:city":"Erfurt",
    "sg:phone":"+49 361/5668334",
    "sg:postcode":"99084",
    "sg:province":"Th\u00fcringen",
    "wof:name":"D\u00f6rflein Und Partner Architekten",
    "wof:placetype":"venue"
},
  "geometry": {"coordinates":[11.024538,50.980469],"type":"Point"}
}