{
  "type": "Feature",
  "properties": {
    "iso:country":"DE",
    "sg:address":"Nachtigalstr. 1",
    "sg:city":"Kiel",
    "sg:phone":"+49 431/27722",
    "sg:postcode":"24149",
    "sg:province":"Schleswig-Holstein",
    "wof:name":"Restaurant Jever Deel",
    "wof:placetype":"venue"
},
  "geometry": {"coordinates":[10.189368248,54.3363952637],"type":"Point"}
}