{
  "type": "Feature",
  "properties": {
    "iso:country":"DE",
    "sg:address":"Widenmayerstr. 12",
    "sg:city":"M\u00fcnchen",
    "sg:phone":"+49 89/2199940",
    "sg:postcode":"80538",
    "sg:province":"Bayern",
    "wof:name":"Mendell Und Oberer",
    "wof:placetype":"venue"
},
  "geometry": {"coordinates":[11.593143,48.139717],"type":"Point"}
}