{
  "type": "Feature",
  "properties": {
    "iso:country":"DE",
    "sg:address":"Ochsenhof 4",
    "sg:city":"W\u00fcstenrot",
    "sg:phone":"+49 7945/534",
    "sg:postcode":"71543",
    "sg:province":"Baden-W\u00fcrttemberg",
    "wof:name":"E. Hinkel",
    "wof:placetype":"venue"
},
  "geometry": {"coordinates":[9.498484,49.119877],"type":"Point"}
}