{
  "type": "Feature",
  "properties": {
    "iso:country":"DE",
    "sg:city":"Bengel",
    "sg:postcode":"54538",
    "sg:province":"Rheinland-Pfalz",
    "wof:name":"Elektro Allmacher Gmbh",
    "wof:placetype":"venue"
},
  "geometry": {"coordinates":[7.062246,50.015373],"type":"Point"}
}