{
  "type": "Feature",
  "properties": {
    "iso:country":"DE",
    "sg:address":"Hauptstr. 21",
    "sg:city":"Selsingen",
    "sg:phone":"+49 4284/95056",
    "sg:postcode":"27446",
    "sg:province":"Niedersachsen",
    "wof:name":"L. Schaumburg",
    "wof:placetype":"venue"
},
  "geometry": {"coordinates":[9.21436,53.373554],"type":"Point"}
}