{
  "type": "Feature",
  "properties": {
    "iso:country":"DE",
    "sg:address":"Burgstr. 10",
    "sg:city":"Freudenberg",
    "sg:phone":"+49 2734/2112",
    "sg:postcode":"57258",
    "sg:province":"Nordrhein-Westfalen",
    "wof:name":"D. Gattwinkel Heissmangel",
    "wof:placetype":"venue"
},
  "geometry": {"coordinates":[7.8722929955,50.8970718384],"type":"Point"}
}