{
  "type": "Feature",
  "properties": {
    "iso:country":"DE",
    "sg:address":"Mechower Str. 67d",
    "sg:city":"Ratzeburg",
    "sg:postcode":"23909",
    "sg:province":"Schleswig-Holstein",
    "wof:name":"Bmc Bau-management-consult Gmbh & Co. Kg",
    "wof:placetype":"venue"
},
  "geometry": {"coordinates":[10.789354,53.700256],"type":"Point"}
}