{
  "type": "Feature",
  "properties": {
    "iso:country":"DE",
    "sg:address":"Liegnitzer Str. 14",
    "sg:city":"T\u00fcbingen",
    "sg:phone":"+49 7071/31989",
    "sg:postcode":"72072",
    "sg:province":"Baden-W\u00fcrttemberg",
    "wof:name":"H. Pfeiffer Ingenieur",
    "wof:placetype":"venue"
},
  "geometry": {"coordinates":[9.0700426102,48.5078392029],"type":"Point"}
}