{
  "type": "Feature",
  "properties": {
    "iso:country":"DE",
    "sg:address":"Kirchgasse 8",
    "sg:city":"Rosenthal-Bielatal",
    "sg:phone":"+49 35021/60806",
    "sg:postcode":"01824",
    "sg:province":"Sachsen",
    "wof:name":"S & B Tischler Gmbh",
    "wof:placetype":"venue"
},
  "geometry": {"coordinates":[14.059025,50.848057],"type":"Point"}
}