{
  "type": "Feature",
  "properties": {
    "iso:country":"DE",
    "sg:address":"M\u00f6sberg 2a",
    "sg:city":"Ahrensb\u00f6k",
    "sg:phone":"+49 4525/1408",
    "sg:postcode":"23623",
    "sg:province":"Schleswig-Holstein",
    "wof:name":"Kraushaar",
    "wof:placetype":"venue"
},
  "geometry": {"coordinates":[10.573965,54.012512],"type":"Point"}
}