{
  "type": "Feature",
  "properties": {
    "iso:country":"DE",
    "sg:address":"Eisvogelweg 2",
    "sg:city":"Dortmund",
    "sg:phone":"+49 231/487260",
    "sg:postcode":"44269",
    "sg:province":"Nordrhein-Westfalen",
    "wof:name":"P. Pr\u00e4zisionsdental- Technik Gmbh",
    "wof:placetype":"venue"
},
  "geometry": {"coordinates":[7.526001,51.477135],"type":"Point"}
}