{
  "type": "Feature",
  "properties": {
    "iso:country":"DE",
    "sg:address":"Hospitalstr. 21",
    "sg:city":"G\u00f6rlitz",
    "sg:postcode":"02826",
    "sg:province":"Sachsen",
    "wof:name":"Hpv Hausbau- Planungs- Und Verkaufs-gmbh",
    "wof:placetype":"venue"
},
  "geometry": {"coordinates":[14.980026,51.151409],"type":"Point"}
}