{
  "type": "Feature",
  "properties": {
    "iso:country":"DE",
    "sg:address":"Wakendorfer Str 52a",
    "sg:city":"Preetz",
    "sg:phone":"+49 4342/81010",
    "sg:postcode":"24211",
    "sg:province":"Schleswig-Holstein",
    "wof:name":"Epp & Wiebe Gmbh",
    "wof:placetype":"venue"
},
  "geometry": {"coordinates":[10.2885560989,54.2390975952],"type":"Point"}
}