{
  "type": "Feature",
  "properties": {
    "iso:country":"DE",
    "sg:address":"Zum Friedensweiler 2",
    "sg:city":"Magdeburg",
    "sg:phone":"+49 391/8115145",
    "sg:postcode":"39114",
    "sg:province":"Sachsen-Anhalt",
    "wof:name":"Bernd Bredow",
    "wof:placetype":"venue"
},
  "geometry": {"coordinates":[11.71127,52.134983],"type":"Point"}
}