{
  "type": "Feature",
  "properties": {
    "iso:country":"DE",
    "sg:address":"Seeweg 2b",
    "sg:city":"Eisendorf",
    "sg:phone":"+49 4392/3538",
    "sg:postcode":"24589",
    "sg:province":"Schleswig-Holstein",
    "wof:name":"G. Dittmann",
    "wof:placetype":"venue"
},
  "geometry": {"coordinates":[9.870403,54.1959],"type":"Point"}
}