{
  "type": "Feature",
  "properties": {
    "iso:country":"DE",
    "sg:address":"Auwer Str.",
    "sg:city":"Bleialf",
    "sg:phone":"+49 6555/222",
    "sg:postcode":"54608",
    "sg:province":"Rheinland-Pfalz",
    "wof:name":"Kath. Pfarramt Maria Himmelfahrt",
    "wof:placetype":"venue"
},
  "geometry": {"coordinates":[6.2841939926,50.2430229187],"type":"Point"}
}