{
  "type": "Feature",
  "properties": {
    "iso:country":"DE",
    "sg:address":"Werner-Von-Siemens-Str. 5a",
    "sg:city":"G\u00f6ttingen",
    "sg:phone":"+49 4955/138570",
    "sg:postcode":"37077",
    "sg:province":"Niedersachsen",
    "wof:name":"Guilbert Deutschland Gmbh",
    "wof:placetype":"venue"
},
  "geometry": {"coordinates":[9.9301338196,51.558795929],"type":"Point"}
}