{
  "type": "Feature",
  "properties": {
    "iso:country":"DE",
    "sg:address":"Dorfstr. 70 B",
    "sg:city":"Lichtenberg",
    "sg:phone":"+49 39820/30465",
    "sg:postcode":"17259",
    "sg:province":"Bayern",
    "wof:name":"P. Schmidt",
    "wof:placetype":"venue"
},
  "geometry": {"coordinates":[13.421777,50.836609],"type":"Point"}
}