{
  "type": "Feature",
  "properties": {
    "iso:country":"DE",
    "sg:address":"H\u00f6henkirchener Str. 6",
    "sg:city":"Aying",
    "sg:phone":"+49 8102/3782",
    "sg:postcode":"85653",
    "sg:province":"Bayern",
    "wof:name":"Ruhland",
    "wof:placetype":"venue"
},
  "geometry": {"coordinates":[11.7347946167,47.9936294556],"type":"Point"}
}