{
  "type": "Feature",
  "properties": {
    "iso:country":"DE",
    "sg:address":"Am Hirtenhof 2 a",
    "sg:city":"Haina",
    "sg:phone":"+49 6456/638",
    "sg:postcode":"35114",
    "sg:province":"Hessen",
    "wof:name":"Heinrich Hecker",
    "wof:placetype":"venue"
},
  "geometry": {"coordinates":[9.047852,51.011223],"type":"Point"}
}