{
  "type": "Feature",
  "properties": {
    "iso:country":"DE",
    "sg:address":"Zeppelinstr. 18",
    "sg:city":"Sersheim",
    "sg:phone":"+49 7042/32289",
    "sg:postcode":"74372",
    "sg:province":"Baden-W\u00fcrttemberg",
    "wof:name":"Gastst\u00e4tte Armins Imbi\u00df",
    "wof:placetype":"venue"
},
  "geometry": {"coordinates":[9.0030183792,48.9571037292],"type":"Point"}
}