{
  "type": "Feature",
  "properties": {
    "iso:country":"DE",
    "sg:address":"Schlo\u00dfberg 3",
    "sg:city":"K\u00f6nitz",
    "sg:phone":"+49 36732/22490",
    "sg:postcode":"07336",
    "wof:name":"Norbert K\u00e4mmer",
    "wof:placetype":"venue"
},
  "geometry": {"coordinates":[11.490253,50.649673],"type":"Point"}
}