{
  "type": "Feature",
  "properties": {
    "iso:country":"DE",
    "sg:address":"Forst 12",
    "sg:city":"Bevern",
    "sg:phone":"+49 5531/8284",
    "sg:postcode":"37639",
    "sg:province":"Niedersachsen",
    "wof:name":"Rainer Brune",
    "wof:placetype":"venue"
},
  "geometry": {"coordinates":[9.490395,51.885326],"type":"Point"}
}