{
  "type": "Feature",
  "properties": {
    "iso:country":"DE",
    "sg:address":"Leitzstr. 2",
    "sg:city":"Oberkochen",
    "sg:phone":"+49 7364/9500",
    "sg:postcode":"73447",
    "sg:province":"Baden-W\u00fcrttemberg",
    "wof:name":"Leitz Metalworking Technologies Gmbh & Co. Kg",
    "wof:placetype":"venue"
},
  "geometry": {"coordinates":[10.100342,48.779934],"type":"Point"}
}