{
  "type": "Feature",
  "properties": {
    "iso:country":"DE",
    "sg:address":"Ellgasser Str. 25a",
    "sg:city":"Lindenberg",
    "sg:phone":"+49 8381/940008",
    "sg:postcode":"88161",
    "sg:province":"Bayern",
    "wof:name":"Versicherungsb\u00fcro Wolfgang Weigl E. K.",
    "wof:placetype":"venue"
},
  "geometry": {"coordinates":[9.8971242905,47.6068534851],"type":"Point"}
}