{
  "type": "Feature",
  "properties": {
    "iso:country":"DE",
    "sg:address":"Am Mittelfeld 5",
    "sg:city":"Gifhorn",
    "sg:phone":"+49 5371/72988",
    "sg:postcode":"38518",
    "sg:province":"Niedersachsen",
    "wof:name":"H. Heise",
    "wof:placetype":"venue"
},
  "geometry": {"coordinates":[10.5250492096,52.5279197693],"type":"Point"}
}