{
  "type": "Feature",
  "properties": {
    "iso:country":"DE",
    "sg:address":"Salanderweg 5",
    "sg:city":"Berlin",
    "sg:phone":"+49 30/5415944",
    "sg:postcode":"12685",
    "sg:province":"Berlin",
    "wof:name":"Dr. Gerda Richter",
    "wof:placetype":"venue"
},
  "geometry": {"coordinates":[13.554943,52.535732],"type":"Point"}
}