{
  "type": "Feature",
  "properties": {
    "iso:country":"DE",
    "sg:address":"Birkenweg 5",
    "sg:city":"Traitsching",
    "sg:phone":"+49 9971/30382",
    "sg:postcode":"93455",
    "sg:province":"Bayern",
    "wof:name":"Granit-import Marchl E. K.",
    "wof:placetype":"venue"
},
  "geometry": {"coordinates":[12.6474266052,49.1711082458],"type":"Point"}
}