{
  "type": "Feature",
  "properties": {
    "iso:country":"DE",
    "sg:address":"Hansaring 88",
    "sg:city":"K\u00f6ln",
    "sg:phone":"+49 221/9126420",
    "sg:postcode":"50670",
    "sg:province":"Nordrhein-Westfalen",
    "wof:name":"Oetken Und Nowak Rechtsanw\u00e4lte",
    "wof:placetype":"venue"
},
  "geometry": {"coordinates":[6.9543170929,50.9495010376],"type":"Point"}
}