{
  "type": "Feature",
  "properties": {
    "iso:country":"DE",
    "sg:address":"Hauptstr. 25",
    "sg:city":"Schopfheim",
    "sg:phone":"+49 7622/3093",
    "sg:postcode":"79650",
    "sg:province":"Baden-W\u00fcrttemberg",
    "wof:name":"Hans Grether Merkur-drogerie",
    "wof:placetype":"venue"
},
  "geometry": {"coordinates":[7.820688,47.649601],"type":"Point"}
}