{
  "type": "Feature",
  "properties": {
    "iso:country":"DE",
    "sg:address":"Museumstr. 4",
    "sg:city":"Landsberg",
    "sg:phone":"+49 8191/50536",
    "sg:postcode":"86899",
    "sg:province":"Bayern",
    "wof:name":"Josef Reich",
    "wof:placetype":"venue"
},
  "geometry": {"coordinates":[10.871985,48.045792],"type":"Point"}
}