{
  "type": "Feature",
  "properties": {
    "iso:country":"DE",
    "sg:address":"Schleusenstr. 1",
    "sg:city":"Bremerhaven",
    "sg:phone":"+49 471/49027",
    "sg:postcode":"27568",
    "sg:province":"Bremen",
    "wof:name":"Parkresidenz Am B\u00fcchel 53 Wohnbau Gmbh",
    "wof:placetype":"venue"
},
  "geometry": {"coordinates":[8.569687,53.551743],"type":"Point"}
}