{
  "type": "Feature",
  "properties": {
    "iso:country":"DE",
    "sg:address":"Hubertusstr. 11 E",
    "sg:city":"Gr\u00fcnwald",
    "sg:postcode":"82031",
    "sg:province":"Bayern",
    "wof:name":"Georg Schulz Rechtsanwalt",
    "wof:placetype":"venue"
},
  "geometry": {"coordinates":[11.5227146149,48.0396347046],"type":"Point"}
}