{
  "type": "Feature",
  "properties": {
    "iso:country":"DE",
    "sg:address":"H\u00fcttenstr. 156",
    "sg:city":"D\u00fcsseldorf",
    "sg:phone":"+49 211/783877",
    "sg:postcode":"40227",
    "sg:province":"Nordrhein-Westfalen",
    "wof:name":"Falkenhorst",
    "wof:placetype":"venue"
},
  "geometry": {"coordinates":[6.7929811478,51.2114372253],"type":"Point"}
}