{
  "type": "Feature",
  "properties": {
    "iso:country":"DE",
    "sg:address":"Poststr. 22",
    "sg:city":"Sch\u00f6mberg",
    "sg:phone":"+49 7084/6099",
    "sg:postcode":"75328",
    "sg:province":"Baden-W\u00fcrttemberg",
    "wof:name":"Wlz-raiffeisen Ag",
    "wof:placetype":"venue"
},
  "geometry": {"coordinates":[8.643946,48.785107],"type":"Point"}
}