{
  "type": "Feature",
  "properties": {
    "iso:country":"DE",
    "sg:address":"Niederlehmer Chaussee 9",
    "sg:city":"Wernsdorf",
    "sg:phone":"+49 3362/82300",
    "sg:postcode":"15537",
    "sg:province":"Brandenburg",
    "wof:name":"Germania Fluggesellschaft Mbh",
    "wof:placetype":"venue"
},
  "geometry": {"coordinates":[13.697692,52.363838],"type":"Point"}
}