{
  "type": "Feature",
  "properties": {
    "iso:country":"DE",
    "sg:address":"Weidenallee 15",
    "sg:city":"Hamburg",
    "sg:phone":"+49 40/4394190",
    "sg:postcode":"20357",
    "sg:province":"Hamburg",
    "wof:name":"Busse Gmbh",
    "wof:placetype":"venue"
},
  "geometry": {"coordinates":[9.965239,53.566181],"type":"Point"}
}