{
  "type": "Feature",
  "properties": {
    "iso:country":"DE",
    "sg:address":"Pommernstr. 3",
    "sg:city":"Marktheidenfeld",
    "sg:phone":"+49 9391/3477",
    "sg:postcode":"97828",
    "sg:province":"Bayern",
    "wof:name":"Willy Schwarzkopf Und Irmgard Pfister",
    "wof:placetype":"venue"
},
  "geometry": {"coordinates":[9.604858,49.852844],"type":"Point"}
}