{
  "type": "Feature",
  "properties": {
    "iso:country":"DE",
    "sg:address":"Clemens-August-Str. 87",
    "sg:city":"Bonn",
    "sg:phone":"+49 228/241696",
    "sg:postcode":"53115",
    "sg:province":"Nordrhein-Westfalen",
    "wof:name":"Eren Bau Gmbh",
    "wof:placetype":"venue"
},
  "geometry": {"coordinates":[7.087432,50.720242],"type":"Point"}
}