{
  "type": "Feature",
  "properties": {
    "iso:country":"DE",
    "sg:address":"In der Sohl 1",
    "sg:city":"Neuwied",
    "sg:phone":"+49 2631/357972",
    "sg:postcode":"56564",
    "sg:province":"Rheinland-Pfalz",
    "wof:name":"Nkt-grund Und Boden Verwaltungs Gmbh",
    "wof:placetype":"venue"
},
  "geometry": {"coordinates":[7.4892148972,50.4312934875],"type":"Point"}
}