{
  "type": "Feature",
  "properties": {
    "iso:country":"DE",
    "sg:address":"Lahnstr. 2-6",
    "sg:city":"Berlin",
    "sg:phone":"+49 30/7579660",
    "sg:postcode":"12055",
    "sg:province":"Berlin",
    "wof:name":"Otto M\u00f6ller Tiefbau Gmbh",
    "wof:placetype":"venue"
},
  "geometry": {"coordinates":[13.4555177689,52.4692611694],"type":"Point"}
}