{
  "type": "Feature",
  "properties": {
    "iso:country":"DE",
    "sg:address":"K\u00f6penicker 9::",
    "sg:city":"Berlin",
    "sg:phone":"+49 4930/6112035",
    "sg:postcode":"10997",
    "sg:province":"Berlin",
    "wof:name":"K\u00dchnisch & Partner Betreuungs-u. Vermittlungsges.f. Verm\u00d6gensanlagen",
    "wof:placetype":"venue"
},
  "geometry": {"coordinates":[13.530562,52.488586],"type":"Point"}
}