{
  "type": "Feature",
  "properties": {
    "iso:country":"DE",
    "sg:address":"Altenburgstr. 6",
    "sg:city":"Gangelt",
    "sg:phone":"+49 2454/2498",
    "sg:postcode":"52538",
    "sg:province":"Nordrhein-Westfalen",
    "wof:name":"Kath. Pfarramt St. Maternus",
    "wof:placetype":"venue"
},
  "geometry": {"coordinates":[5.9903831482,51.0270652771],"type":"Point"}
}