{
  "type": "Feature",
  "properties": {
    "iso:country":"DE",
    "sg:address":"Sch\u00f6nhofweg 10",
    "sg:city":"Wenzenbach",
    "sg:phone":"+49 9407/1607",
    "sg:postcode":"93173",
    "sg:province":"Bayern",
    "wof:name":"G\u00fcnther Heussler Gmbh",
    "wof:placetype":"venue"
},
  "geometry": {"coordinates":[12.1653203964,49.0511322021],"type":"Point"}
}