{
  "type": "Feature",
  "properties": {
    "iso:country":"DE",
    "sg:address":"Br\u00e4uhausstr. 2",
    "sg:city":"Immenstadt",
    "sg:phone":"+49 8323/98036",
    "sg:postcode":"87509",
    "sg:province":"Bayern",
    "wof:name":"Gerhard Meier Heilpraktiker",
    "wof:placetype":"venue"
},
  "geometry": {"coordinates":[10.2180757523,47.5592727661],"type":"Point"}
}