{
  "type": "Feature",
  "properties": {
    "iso:country":"DE",
    "sg:address":"Eigelstein 74",
    "sg:city":"K\u00f6ln",
    "sg:phone":"+49 221/121601",
    "sg:postcode":"50668",
    "sg:province":"Nordrhein-Westfalen",
    "wof:name":"Weinhaus Vogel",
    "wof:placetype":"venue"
},
  "geometry": {"coordinates":[6.9569091797,50.9480438232],"type":"Point"}
}