{
  "type": "Feature",
  "properties": {
    "iso:country":"DE",
    "sg:address":"Schwarzer Weg 02",
    "sg:city":"Unterwellenborn",
    "sg:postcode":"07333",
    "sg:province":"Th\u00fcringen",
    "wof:name":"Decona Gmbh",
    "wof:placetype":"venue"
},
  "geometry": {"coordinates":[11.431068,50.656734],"type":"Point"}
}