{
  "type": "Feature",
  "properties": {
    "iso:country":"DE",
    "sg:address":"Am Brodhagen 87",
    "sg:city":"Bielefeld",
    "sg:phone":"+49 521/882444",
    "sg:postcode":"33613",
    "sg:province":"Nordrhein-Westfalen",
    "wof:name":"Mark Glaeske Finanzberater",
    "wof:placetype":"venue"
},
  "geometry": {"coordinates":[8.5107908249,52.0444717407],"type":"Point"}
}