{
  "type": "Feature",
  "properties": {
    "iso:country":"DE",
    "sg:address":"Johannes-Brahms-Platz 9",
    "sg:city":"Hamburg",
    "sg:phone":"+49 40/35105221",
    "sg:postcode":"20355",
    "sg:province":"Hamburg",
    "wof:name":"Knowledge Network Extranet",
    "wof:placetype":"venue"
},
  "geometry": {"coordinates":[9.980261,53.554974],"type":"Point"}
}