{
  "type": "Feature",
  "properties": {
    "iso:country":"DE",
    "sg:address":"Boschstr. 22",
    "sg:city":"Stadtlohn",
    "sg:phone":"+49 4925/639140",
    "sg:postcode":"48703",
    "sg:province":"Nordrhein-Westfalen",
    "wof:name":"M\u00d6llers Stahlhandel Gmbh",
    "wof:placetype":"venue"
},
  "geometry": {"coordinates":[6.897259,51.983147],"type":"Point"}
}