{
  "type": "Feature",
  "properties": {
    "iso:country":"DE",
    "sg:address":"Auf dem D\u00f6hren 1",
    "sg:city":"Dassel",
    "sg:phone":"+49 5562/269",
    "sg:postcode":"37586",
    "sg:province":"Niedersachsen",
    "wof:name":"Heinrich Herbst Kg",
    "wof:placetype":"venue"
},
  "geometry": {"coordinates":[9.7514657974,51.7667732239],"type":"Point"}
}