{
  "type": "Feature",
  "properties": {
    "iso:country":"DE",
    "sg:address":"Fliederstr. 7-8",
    "sg:city":"Vogelsdorf",
    "sg:phone":"+49 33439/51620",
    "sg:postcode":"15370",
    "sg:province":"Brandenburg",
    "wof:name":"Winfried Gronwald",
    "wof:placetype":"venue"
},
  "geometry": {"coordinates":[13.7566490173,52.5116271973],"type":"Point"}
}