{
  "type": "Feature",
  "properties": {
    "iso:country":"DE",
    "sg:address":"K.-Marx-Platz 13",
    "sg:city":"Steinach",
    "sg:phone":"+49 36762/2586",
    "sg:postcode":"96523",
    "sg:province":"Th\u00fcringen",
    "wof:name":"Kreissparkasse Sonneberg",
    "wof:placetype":"venue"
},
  "geometry": {"coordinates":[11.159245,50.431938],"type":"Point"}
}