{
  "type": "Feature",
  "properties": {
    "iso:country":"DE",
    "sg:address":"Lindenallee 7",
    "sg:city":"Gotthun",
    "sg:postcode":"17207",
    "sg:province":"Mecklenburg-Vorpommern",
    "wof:name":"Mahncke Bau Gmbh",
    "wof:placetype":"venue"
},
  "geometry": {"coordinates":[12.5845127106,53.4107704163],"type":"Point"}
}