{
  "type": "Feature",
  "properties": {
    "iso:country":"DE",
    "sg:address":"Kirchstr. 42",
    "sg:city":"Bonn",
    "sg:phone":"+49 228/442632",
    "sg:postcode":"53227",
    "sg:province":"Nordrhein-Westfalen",
    "wof:name":"Restaurant Samos",
    "wof:placetype":"venue"
},
  "geometry": {"coordinates":[7.1490311623,50.7290115356],"type":"Point"}
}