{
  "type": "Feature",
  "properties": {
    "iso:country":"DE",
    "sg:address":"Hertener Str. 42",
    "sg:city":"Recklinghausen",
    "sg:phone":"+49 2361/27640",
    "sg:postcode":"45657",
    "sg:province":"Nordrhein-Westfalen",
    "wof:name":"Kurt Wask\u00f6nig Rechtsanwalt Und Notar",
    "wof:placetype":"venue"
},
  "geometry": {"coordinates":[7.1880941391,51.6107902527],"type":"Point"}
}