{
  "type": "Feature",
  "properties": {
    "iso:country":"DE",
    "sg:address":"Kanal str 1",
    "sg:city":"Seelze",
    "sg:phone":"+49 5137930996058",
    "sg:postcode":"30926",
    "sg:province":"Niedersachsen",
    "wof:name":"Das Bettenhaus",
    "wof:placetype":"venue"
},
  "geometry": {"coordinates":[9.5900526047,52.3910331726],"type":"Point"}
}