{
  "type": "Feature",
  "properties": {
    "iso:country":"DE",
    "sg:address":"Moselstr. 68",
    "sg:city":"Hanau",
    "sg:phone":"+49 6181/15071",
    "sg:postcode":"63452",
    "sg:province":"Hessen",
    "wof:name":"Dietz Baudekoration Betriebsgesellschaft Mbh",
    "wof:placetype":"venue"
},
  "geometry": {"coordinates":[8.9232559204,50.1513442993],"type":"Point"}
}