{
  "type": "Feature",
  "properties": {
    "iso:country":"DE",
    "sg:address":"Raabestr. 35",
    "sg:city":"Wilhelmshaven",
    "sg:phone":"+49 4421/64574",
    "sg:postcode":"26386",
    "sg:province":"Niedersachsen",
    "wof:name":"Gerhard Peiler Steuerbevollm\u00e4chtigter",
    "wof:placetype":"venue"
},
  "geometry": {"coordinates":[8.1087799072,53.5481796265],"type":"Point"}
}