{
  "type": "Feature",
  "properties": {
    "iso:country":"DE",
    "sg:address":"Berliner Str. 118",
    "sg:city":"G\u00fctersloh",
    "sg:phone":"+49 5241/13787",
    "sg:postcode":"33330",
    "sg:province":"Nordrhein-Westfalen",
    "wof:name":"B\u00e4rbel Palsherm",
    "wof:placetype":"venue"
},
  "geometry": {"coordinates":[8.382553,51.910187],"type":"Point"}
}