{
  "type": "Feature",
  "properties": {
    "iso:country":"DE",
    "sg:address":"Schulstr 4-6",
    "sg:city":"Frittlingen",
    "sg:phone":"+49 7426/1336",
    "sg:postcode":"78665",
    "sg:province":"Baden-W\u00fcrttemberg",
    "wof:name":"Fred P. Langheinrich",
    "wof:placetype":"venue"
},
  "geometry": {"coordinates":[8.709276,48.127022],"type":"Point"}
}