{
  "type": "Feature",
  "properties": {
    "iso:country":"DE",
    "sg:address":"Rilkeweg 15",
    "sg:city":"Hamburg",
    "sg:phone":"+49 40/828721",
    "sg:postcode":"22607",
    "sg:province":"Hamburg",
    "wof:name":"Carsten Nibbes Ingenieur",
    "wof:placetype":"venue"
},
  "geometry": {"coordinates":[9.873732,53.561497],"type":"Point"}
}