{
  "type": "Feature",
  "properties": {
    "iso:country":"DE",
    "sg:address":"Sandstr. 1",
    "sg:city":"Werdohl",
    "sg:phone":"+49 2392/2857",
    "sg:postcode":"58791",
    "sg:province":"Nordrhein-Westfalen",
    "wof:name":"Heinz Preu\u00df",
    "wof:placetype":"venue"
},
  "geometry": {"coordinates":[7.7623019218,51.2590065002],"type":"Point"}
}