{
  "type": "Feature",
  "properties": {
    "iso:country":"DE",
    "sg:address":"Donaustr. 24",
    "sg:city":"Kelheim",
    "sg:phone":"+49 9441/2796",
    "sg:postcode":"93309",
    "sg:province":"Bayern",
    "wof:name":"Restaurant Chang Cheng",
    "wof:placetype":"venue"
},
  "geometry": {"coordinates":[11.8710012436,48.916973114],"type":"Point"}
}