{
  "type": "Feature",
  "properties": {
    "iso:country":"DE",
    "sg:address":"Montfortstr. 30",
    "sg:city":"Tettnang",
    "sg:phone":"+49 7542/7424",
    "sg:postcode":"88069",
    "sg:province":"Baden-W\u00fcrttemberg",
    "wof:name":"Lehmann",
    "wof:placetype":"venue"
},
  "geometry": {"coordinates":[9.5878582001,47.6716804504],"type":"Point"}
}