{
  "type": "Feature",
  "properties": {
    "iso:country":"DE",
    "sg:address":"Am Kreuzstein 1",
    "sg:city":"Naumburg",
    "sg:phone":"+49 3445/704600",
    "sg:postcode":"06618",
    "sg:province":"Sachsen-Anhalt",
    "wof:name":"Gefl\u00dcgelhof K\u00d6hler Gmbh",
    "wof:placetype":"venue"
},
  "geometry": {"coordinates":[11.844551,51.174965],"type":"Point"}
}