{
  "type": "Feature",
  "properties": {
    "iso:country":"DE",
    "sg:address":"Harderkamp 4",
    "sg:city":"B\u00f6neb\u00fcttel",
    "sg:phone":"+49 4321/921910",
    "sg:postcode":"24620",
    "sg:province":"Schleswig-Holstein",
    "wof:name":"Udo Spengler Stra\u00dfen- Und Tiefbau Gmbh",
    "wof:placetype":"venue"
},
  "geometry": {"coordinates":[10.0433864594,54.070930481],"type":"Point"}
}