{
  "type": "Feature",
  "properties": {
    "iso:country":"DE",
    "sg:address":"Raiffeisenstr. 1",
    "sg:city":"Donnersdorf",
    "sg:phone":"+49 9528/237",
    "sg:postcode":"97499",
    "sg:province":"Bayern",
    "wof:name":"Raiffeisenbank Gerolzhofen Und Um-, Gebung Eg",
    "wof:placetype":"venue"
},
  "geometry": {"coordinates":[10.419526,49.969612],"type":"Point"}
}