{
  "type": "Feature",
  "properties": {
    "iso:country":"DE",
    "sg:address":"Kreisstr. 86",
    "sg:city":"Selm",
    "sg:phone":"+49 2592/3771",
    "sg:postcode":"59379",
    "sg:province":"Nordrhein-Westfalen",
    "wof:name":"E. Salomon",
    "wof:placetype":"venue"
},
  "geometry": {"coordinates":[7.467475,51.686436],"type":"Point"}
}