{
  "type": "Feature",
  "properties": {
    "iso:country":"DE",
    "sg:address":"Passauer Str. 1",
    "sg:city":"Regensburg",
    "sg:postcode":"93055",
    "sg:province":"Bayern",
    "wof:name":"Bsg Bavaria See- Verkehrsgesellschaft Mbh",
    "wof:placetype":"venue"
},
  "geometry": {"coordinates":[12.1641206741,49.0107383728],"type":"Point"}
}