{
  "type": "Feature",
  "properties": {
    "iso:country":"DE",
    "sg:address":"Ludoviciweg 3",
    "sg:city":"Langenfeld",
    "sg:phone":"+49 2173/70447",
    "sg:postcode":"40764",
    "sg:province":"Nordrhein-Westfalen",
    "wof:name":"Bernd Brix",
    "wof:placetype":"venue"
},
  "geometry": {"coordinates":[6.9418668747,51.1256866455],"type":"Point"}
}