{
  "type": "Feature",
  "properties": {
    "iso:country":"DE",
    "sg:address":"Gewerbepark Am Wald 7",
    "sg:city":"Ilmenau",
    "sg:phone":"+49 3677/846690",
    "sg:postcode":"98693",
    "sg:province":"Th\u00fcringen",
    "wof:name":"Kleines Rabental Friedrichs Gmbh",
    "wof:placetype":"venue"
},
  "geometry": {"coordinates":[10.945709,50.697895],"type":"Point"}
}