{
  "type": "Feature",
  "properties": {
    "iso:country":"DE",
    "sg:address":"Am Ro\u00dfberg",
    "sg:city":"Schkeuditz",
    "sg:phone":"+49 34204/61935",
    "sg:postcode":"04435",
    "sg:province":"Sachsen",
    "wof:name":"K. Neumann Gmbh & Co.",
    "wof:placetype":"venue"
},
  "geometry": {"coordinates":[12.19374,51.396648],"type":"Point"}
}