{
  "type": "Feature",
  "properties": {
    "iso:country":"DE",
    "sg:address":"Falkenseer Str. 162",
    "sg:city":"Sch\u00f6nwalde",
    "sg:phone":"+49 3322/28410",
    "sg:postcode":"14621",
    "sg:province":"Brandenburg",
    "wof:name":"Manfred Stiller",
    "wof:placetype":"venue"
},
  "geometry": {"coordinates":[13.1209278107,52.6073455811],"type":"Point"}
}