{
  "type": "Feature",
  "properties": {
    "iso:country":"DE",
    "sg:address":"Brauckstr. 37",
    "sg:city":"Witten",
    "sg:phone":"+49 4923/0289060",
    "sg:postcode":"58454",
    "sg:province":"Nordrhein-Westfalen",
    "wof:name":"Friedrich Lohmann Gmbh",
    "wof:placetype":"venue"
},
  "geometry": {"coordinates":[7.387921,51.457844],"type":"Point"}
}