{
  "type": "Feature",
  "properties": {
    "iso:country":"DE",
    "sg:address":"B\u00f6rsenstr. 110",
    "sg:city":"Wilhelmshaven",
    "sg:phone":"+49 4421/304687",
    "sg:postcode":"26382",
    "sg:province":"Niedersachsen",
    "wof:name":"D. L\u00fcckens",
    "wof:placetype":"venue"
},
  "geometry": {"coordinates":[8.102966,53.520416],"type":"Point"}
}