{
  "type": "Feature",
  "properties": {
    "iso:country":"DE",
    "sg:address":"Brunsb\u00fctteler Damm 134",
    "sg:city":"Berlin",
    "sg:phone":"+49 30/3313858",
    "sg:postcode":"13581",
    "sg:province":"Berlin",
    "wof:name":"Holzluettge.de",
    "wof:placetype":"venue"
},
  "geometry": {"coordinates":[13.177977,52.5341],"type":"Point"}
}