{
  "type": "Feature",
  "properties": {
    "iso:country":"DE",
    "sg:address":"An Slagboom 20",
    "sg:city":"Norderstedt",
    "sg:phone":"+49 40/5230640",
    "sg:postcode":"22848",
    "sg:province":"Schleswig-Holstein",
    "wof:name":"Roman Seliger Armaturenfabrik Gmbh",
    "wof:placetype":"venue"
},
  "geometry": {"coordinates":[9.9888372421,53.6627311707],"type":"Point"}
}