{
  "type": "Feature",
  "properties": {
    "iso:country":"DE",
    "sg:address":"Im Wiesengrund 10",
    "sg:city":"Rheine",
    "sg:phone":"+49 5971/56153",
    "sg:postcode":"48432",
    "sg:province":"Nordrhein-Westfalen",
    "wof:name":"Hermann Winter",
    "wof:placetype":"venue"
},
  "geometry": {"coordinates":[7.454879,52.237465],"type":"Point"}
}