{
  "type": "Feature",
  "properties": {
    "iso:country":"DE",
    "sg:address":"Schulstr. 28",
    "sg:city":"R\u00f6hrmoos",
    "sg:phone":"+49 8139/419",
    "sg:postcode":"85244",
    "sg:province":"Bayern",
    "wof:name":"Johann Lechner",
    "wof:placetype":"venue"
},
  "geometry": {"coordinates":[11.492636,48.346989],"type":"Point"}
}