{
  "type": "Feature",
  "properties": {
    "iso:country":"DE",
    "sg:address":"Sandgewannstr. 2",
    "sg:city":"Ladenburg",
    "sg:postcode":"68526",
    "sg:province":"Baden-W\u00fcrttemberg",
    "wof:name":"Minhtec Ag",
    "wof:placetype":"venue"
},
  "geometry": {"coordinates":[8.6107931137,49.4753646851],"type":"Point"}
}