{
  "type": "Feature",
  "properties": {
    "iso:country":"DE",
    "sg:address":"Mahlastr. 21",
    "sg:city":"Frankenthal",
    "sg:phone":"+49 6233/34630",
    "sg:postcode":"67227",
    "sg:province":"Rheinland-Pfalz",
    "wof:name":"Kurpfalz Management",
    "wof:placetype":"venue"
},
  "geometry": {"coordinates":[8.3546581268,49.5290107727],"type":"Point"}
}