{
  "type": "Feature",
  "properties": {
    "iso:country":"DE",
    "sg:address":"Max-Slevogt-Str. 3",
    "sg:city":"Bad Kreuznach",
    "sg:phone":"+49 671/73080",
    "sg:postcode":"55543",
    "sg:province":"Rheinland-Pfalz",
    "wof:name":"Klaus Hill",
    "wof:placetype":"venue"
},
  "geometry": {"coordinates":[7.885837,49.844009],"type":"Point"}
}