{
  "type": "Feature",
  "properties": {
    "iso:country":"DE",
    "sg:address":"Albstr. 36",
    "sg:city":"M\u00f6nchsdeggingen",
    "sg:phone":"+49 9088/700",
    "sg:postcode":"86751",
    "sg:province":"Bayern",
    "wof:name":"Cafe-pension Am Buchberg",
    "wof:placetype":"venue"
},
  "geometry": {"coordinates":[10.5783214569,48.7738571167],"type":"Point"}
}