{
  "type": "Feature",
  "properties": {
    "iso:country":"DE",
    "sg:address":"Holm 49-51",
    "sg:city":"Flensburg",
    "sg:phone":"+49 461/13661",
    "sg:postcode":"24937",
    "sg:province":"Schleswig-Holstein",
    "wof:name":"Fielmann Optiker",
    "wof:placetype":"venue"
},
  "geometry": {"coordinates":[9.4362573624,54.7837944031],"type":"Point"}
}