{
  "type": "Feature",
  "properties": {
    "iso:country":"DE",
    "sg:address":"Oldendorfer Str. 1",
    "sg:city":"Einbeck",
    "sg:phone":"+49 5562/1605",
    "sg:postcode":"37574",
    "sg:province":"Niedersachsen",
    "wof:name":"Heinz Bruns",
    "wof:placetype":"venue"
},
  "geometry": {"coordinates":[9.799564,51.809929],"type":"Point"}
}