{
  "type": "Feature",
  "properties": {
    "iso:country":"DE",
    "sg:address":"Hasseldieksdammer Weg 10",
    "sg:city":"Kiel",
    "sg:phone":"+49 431/14480",
    "sg:postcode":"24116",
    "sg:province":"Schleswig-Holstein",
    "wof:name":"Karl-heinz Dohrmann",
    "wof:placetype":"venue"
},
  "geometry": {"coordinates":[10.1193370819,54.3223266602],"type":"Point"}
}