{
  "type": "Feature",
  "properties": {
    "iso:country":"DE",
    "sg:address":"M\u00fchlenweg 4",
    "sg:city":"Gro\u00dfharthau",
    "sg:phone":"+49 35954/53243",
    "sg:postcode":"01909",
    "sg:province":"Sachsen",
    "wof:name":"Bernhard Hoffmann",
    "wof:placetype":"venue"
},
  "geometry": {"coordinates":[14.099225,51.101711],"type":"Point"}
}