{
  "type": "Feature",
  "properties": {
    "iso:country":"DE",
    "sg:address":"Am B\u00fcrgerpark 37",
    "sg:city":"Langwedel",
    "sg:phone":"+49 4232/237",
    "sg:postcode":"27299",
    "sg:province":"Niedersachsen",
    "wof:name":"W. Brandt Heissmangelbetrieb",
    "wof:placetype":"venue"
},
  "geometry": {"coordinates":[9.1905870438,52.9794692993],"type":"Point"}
}