{
  "type": "Feature",
  "properties": {
    "iso:country":"DE",
    "sg:address":"Karolinenstr. 44-46",
    "sg:city":"Waldsassen",
    "sg:phone":"+49 9632/1374",
    "sg:postcode":"95652",
    "sg:province":"Bayern",
    "wof:name":"Hermann Lindinger",
    "wof:placetype":"venue"
},
  "geometry": {"coordinates":[12.3073768616,50.0017471313],"type":"Point"}
}