{
  "type": "Feature",
  "properties": {
    "iso:country":"DE",
    "sg:address":"Westerstr. 6",
    "sg:city":"Dellstedt",
    "sg:phone":"+49 4802/827",
    "sg:postcode":"25786",
    "sg:province":"Schleswig-Holstein",
    "wof:name":"Peter Rusch",
    "wof:placetype":"venue"
},
  "geometry": {"coordinates":[9.365794,54.23658],"type":"Point"}
}