{
  "type": "Feature",
  "properties": {
    "iso:country":"DE",
    "sg:address":"Herderstr. 6",
    "sg:city":"Eningen",
    "sg:phone":"+49 7121/82519",
    "sg:postcode":"72800",
    "sg:province":"Baden-W\u00fcrttemberg",
    "wof:name":"Friedbert Kittelberger",
    "wof:placetype":"venue"
},
  "geometry": {"coordinates":[9.2632493973,48.4930877686],"type":"Point"}
}