{
  "type": "Feature",
  "properties": {
    "iso:country":"DE",
    "sg:address":"Lessingstr. 4",
    "sg:city":"Uslar",
    "sg:phone":"+49 5571/6426",
    "sg:postcode":"37170",
    "sg:province":"Niedersachsen",
    "wof:name":"Detlef H\u00f6rold",
    "wof:placetype":"venue"
},
  "geometry": {"coordinates":[9.6365289688,51.6622962952],"type":"Point"}
}