{
  "type": "Feature",
  "properties": {
    "iso:country":"DE",
    "sg:address":"Unterzwieselau",
    "sg:city":"Lindberg",
    "sg:phone":"+49 9922/1780",
    "sg:postcode":"94227",
    "sg:province":"Bayern",
    "wof:name":"A. Harant",
    "wof:placetype":"venue"
},
  "geometry": {"coordinates":[13.2749080658,49.024230957],"type":"Point"}
}