{
  "type": "Feature",
  "properties": {
    "iso:country":"DE",
    "sg:address":"Neust\u00e4dter Str. 50",
    "sg:city":"Thale",
    "sg:phone":"+49 3947/772793",
    "sg:postcode":"06502",
    "sg:province":"Sachsen-Anhalt",
    "wof:name":"Pflegedienst Schwester Christel Sobbe",
    "wof:placetype":"venue"
},
  "geometry": {"coordinates":[11.040148,51.758316],"type":"Point"}
}