{
  "type": "Feature",
  "properties": {
    "iso:country":"DE",
    "sg:address":"Kopernikusstr. 3",
    "sg:city":"Potsdam",
    "sg:phone":"+49 331/7482008",
    "sg:postcode":"14482",
    "sg:province":"Brandenburg",
    "wof:name":"H.-u. Raschke",
    "wof:placetype":"venue"
},
  "geometry": {"coordinates":[13.0954675674,52.3908958435],"type":"Point"}
}