{
  "type": "Feature",
  "properties": {
    "iso:country":"DE",
    "sg:address":"Hans-B\u00f6ckler-Str. 77",
    "sg:city":"Bremen",
    "sg:phone":"+49 421/396090",
    "sg:postcode":"28217",
    "sg:province":"Bremen",
    "wof:name":"Spatz & Heitm\u00fcller Gmbh",
    "wof:placetype":"venue"
},
  "geometry": {"coordinates":[8.786498,53.088184],"type":"Point"}
}