{
  "type": "Feature",
  "properties": {
    "iso:country":"DE",
    "sg:address":"Malmedyer Str. 27",
    "sg:city":"Aachen",
    "sg:phone":"+49 241/68868",
    "sg:postcode":"52066",
    "sg:province":"Nordrhein-Westfalen",
    "wof:name":"Gastro Cultura Betriebs- Gesellschaft Gastronomie",
    "wof:placetype":"venue"
},
  "geometry": {"coordinates":[6.092362,50.758747],"type":"Point"}
}