{
  "type": "Feature",
  "properties": {
    "iso:country":"DE",
    "sg:address":"Sch\u00e4lzigweg 31",
    "sg:city":"Schwetzingen",
    "sg:postcode":"68723",
    "sg:province":"Baden-W\u00fcrttemberg",
    "wof:name":"Schilling Metall Gmbh",
    "wof:placetype":"venue"
},
  "geometry": {"coordinates":[8.567188,49.378124],"type":"Point"}
}