{
  "type": "Feature",
  "properties": {
    "iso:country":"DE",
    "sg:address":"Bromberger Str. 8",
    "sg:city":"Uslar",
    "sg:phone":"+49 5571/912327",
    "sg:postcode":"37170",
    "sg:province":"Niedersachsen",
    "wof:name":"R. Groffmann",
    "wof:placetype":"venue"
},
  "geometry": {"coordinates":[9.638094902,51.6533164978],"type":"Point"}
}