{
  "type": "Feature",
  "properties": {
    "iso:country":"DE",
    "sg:address":"Pestalozzistr. 25",
    "sg:city":"P\u00fcttlingen",
    "sg:phone":"+49 6898/67528",
    "sg:postcode":"66346",
    "sg:province":"Saarland",
    "wof:name":"H. Tholey",
    "wof:placetype":"venue"
},
  "geometry": {"coordinates":[6.8790750504,49.2917785645],"type":"Point"}
}