{
  "type": "Feature",
  "properties": {
    "iso:country":"DE",
    "sg:address":"Schorndorfer Str 78",
    "sg:city":"Winnenden",
    "sg:phone":"+49 7195/69080",
    "sg:postcode":"71364",
    "sg:province":"Baden-W\u00fcrttemberg",
    "wof:name":"Paul W\u00f6hrle Gmbh & Co",
    "wof:placetype":"venue"
},
  "geometry": {"coordinates":[9.4076700211,48.8722496033],"type":"Point"}
}