{
  "type": "Feature",
  "properties": {
    "iso:country":"DE",
    "sg:address":"Neustadt 20",
    "sg:city":"Ansbach",
    "sg:phone":"+49 981/96969",
    "sg:postcode":"91522",
    "sg:province":"Bayern",
    "wof:name":"Mutter Und Kind",
    "wof:placetype":"venue"
},
  "geometry": {"coordinates":[10.5731477737,49.3014259338],"type":"Point"}
}