{
  "type": "Feature",
  "properties": {
    "iso:country":"DE",
    "sg:address":"Am Anger 27",
    "sg:city":"Luckau",
    "sg:postcode":"15926",
    "sg:province":"Brandenburg",
    "wof:name":"Friedrich Schulze",
    "wof:placetype":"venue"
},
  "geometry": {"coordinates":[13.70109,51.850773],"type":"Point"}
}