{
  "type": "Feature",
  "properties": {
    "iso:country":"DE",
    "sg:address":"Am Goldenen Steig 3",
    "sg:city":"Mauth",
    "sg:phone":"+49 8557/269",
    "sg:postcode":"94151",
    "sg:province":"Bayern",
    "wof:name":"H. Und M. Schreder",
    "wof:placetype":"venue"
},
  "geometry": {"coordinates":[13.58375,48.887249],"type":"Point"}
}