{
  "type": "Feature",
  "properties": {
    "iso:country":"DE",
    "sg:address":"Normannenstr. 5",
    "sg:city":"Aachen",
    "sg:phone":"+49 241/152948",
    "sg:postcode":"52070",
    "sg:province":"Nordrhein-Westfalen",
    "wof:name":"M. Neullens Kg",
    "wof:placetype":"venue"
},
  "geometry": {"coordinates":[6.0964751244,50.7895050049],"type":"Point"}
}