{
  "type": "Feature",
  "properties": {
    "iso:country":"DE",
    "sg:address":"Lindenstr. 42",
    "sg:city":"Hohenwestedt",
    "sg:postcode":"24594",
    "sg:province":"Schleswig-Holstein",
    "wof:name":"Evangelische Kirchengemeinde",
    "wof:placetype":"venue"
},
  "geometry": {"coordinates":[9.6545190811,54.0900230408],"type":"Point"}
}