{
  "type": "Feature",
  "properties": {
    "iso:country":"DE",
    "sg:address":"Neuendorf",
    "sg:city":"Beeskow",
    "sg:postcode":"15848",
    "sg:province":"Brandenburg",
    "wof:name":"Dr. Med. Sabine G\u00f6rsdorf",
    "wof:placetype":"venue"
},
  "geometry": {"coordinates":[14.236544,52.192673],"type":"Point"}
}