{
  "type": "Feature",
  "properties": {
    "iso:country":"DE",
    "sg:address":"Oderstr. 87",
    "sg:city":"Villingen-Schwenningen",
    "sg:phone":"+49 7721/74043",
    "sg:postcode":"78052",
    "sg:province":"Baden-W\u00fcrttemberg",
    "wof:name":"B. Storz",
    "wof:placetype":"venue"
},
  "geometry": {"coordinates":[8.4630737305,48.0800514221],"type":"Point"}
}