{
  "type": "Feature",
  "properties": {
    "iso:country":"DE",
    "sg:address":"Unterkohlfurth 20",
    "sg:city":"Wuppertal",
    "sg:phone":"+49 202/471929",
    "sg:postcode":"42349",
    "sg:province":"Nordrhein-Westfalen",
    "wof:name":"Khs Computer Gmbh",
    "wof:placetype":"venue"
},
  "geometry": {"coordinates":[7.115753,51.186829],"type":"Point"}
}