{
  "type": "Feature",
  "properties": {
    "iso:country":"DE",
    "sg:address":"Am Rott 33",
    "sg:city":"Lennestadt",
    "sg:phone":"+49 2721/81251",
    "sg:postcode":"57368",
    "sg:province":"Nordrhein-Westfalen",
    "wof:name":"Peter Mertens",
    "wof:placetype":"venue"
},
  "geometry": {"coordinates":[8.051849,51.121319],"type":"Point"}
}