{
  "type": "Feature",
  "properties": {
    "iso:country":"DE",
    "sg:address":"Wilhelm-Weitling-Str. 1",
    "sg:city":"Dessau",
    "sg:phone":"+49 340/512052",
    "sg:postcode":"06847",
    "sg:province":"Sachsen-Anhalt",
    "wof:name":"U. Hartling",
    "wof:placetype":"venue"
},
  "geometry": {"coordinates":[12.1564760208,51.8112983704],"type":"Point"}
}