{
  "type": "Feature",
  "properties": {
    "iso:country":"DE",
    "sg:address":"Am Sportplatz 2",
    "sg:city":"Hausham",
    "sg:phone":"+49 8026",
    "sg:postcode":"83734",
    "sg:province":"Bayern",
    "wof:name":"Schreinerei Sterr Hausham, T\u00fcren, Fenster, S\u00fcdholz",
    "wof:placetype":"venue"
},
  "geometry": {"coordinates":[11.836,47.744614],"type":"Point"}
}