{
  "type": "Feature",
  "properties": {
    "iso:country":"DE",
    "sg:address":"Neustadt 39",
    "sg:city":"Husum",
    "sg:phone":"+49 4841/2423",
    "sg:postcode":"25813",
    "sg:province":"Schleswig-Holstein",
    "wof:name":"P. Langenbeck",
    "wof:placetype":"venue"
},
  "geometry": {"coordinates":[9.0474395752,54.4784927368],"type":"Point"}
}