{
  "type": "Feature",
  "properties": {
    "iso:country":"DE",
    "sg:address":"Willy-Brandt-Platz 5",
    "sg:city":"Bochum",
    "sg:phone":"+49 234/681898",
    "sg:postcode":"44787",
    "sg:province":"Nordrhein-Westfalen",
    "wof:name":"Oliver Jung",
    "wof:placetype":"venue"
},
  "geometry": {"coordinates":[7.2142939568,51.4816894531],"type":"Point"}
}