{
  "type": "Feature",
  "properties": {
    "iso:country":"DE",
    "sg:address":"Bismarckpassage 2",
    "sg:city":"Hilden",
    "sg:phone":"+49 2103/987994",
    "sg:postcode":"40721",
    "sg:province":"Nordrhein-Westfalen",
    "wof:name":"Biba & Pariscop Daub Gmbh",
    "wof:placetype":"venue"
},
  "geometry": {"coordinates":[6.935281,51.168861],"type":"Point"}
}