{
  "type": "Feature",
  "properties": {
    "iso:country":"DE",
    "sg:address":"Bahnhofstr. 18",
    "sg:city":"Lamerdingen",
    "sg:phone":"+49 8248/336",
    "sg:postcode":"86862",
    "sg:province":"Bayern",
    "wof:name":"Rudolf Heinzler",
    "wof:placetype":"venue"
},
  "geometry": {"coordinates":[10.735734,48.093548],"type":"Point"}
}