{
  "type": "Feature",
  "properties": {
    "iso:country":"DE",
    "sg:address":"Louis-Wackler-Str. 2",
    "sg:city":"G\u00f6ppingen",
    "sg:phone":"+49 7161/8060",
    "sg:postcode":"73037",
    "sg:province":"Baden-W\u00fcrttemberg",
    "wof:name":"Schwarz Gmbh & Co. Kg",
    "wof:placetype":"venue"
},
  "geometry": {"coordinates":[9.6894226074,48.67918396],"type":"Point"}
}