{
  "type": "Feature",
  "properties": {
    "iso:country":"DE",
    "sg:address":"Breitensteinstr. 12",
    "sg:city":"Stephanskirchen",
    "sg:postcode":"83071",
    "sg:province":"Bayern",
    "wof:name":"Overbeck Gmbh",
    "wof:placetype":"venue"
},
  "geometry": {"coordinates":[12.152015,47.854588],"type":"Point"}
}