{
  "type": "Feature",
  "properties": {
    "iso:country":"DE",
    "sg:address":"Wei\u00dfenburger Str. 15",
    "sg:city":"M\u00fcnchen",
    "sg:phone":"+49 89/4480813",
    "sg:postcode":"81667",
    "sg:province":"Bayern",
    "wof:name":"Betten-lenz",
    "wof:placetype":"venue"
},
  "geometry": {"coordinates":[11.5974683762,48.1286468506],"type":"Point"}
}