{
  "type": "Feature",
  "properties": {
    "iso:country":"DE",
    "sg:address":"Am Rosengarten 15",
    "sg:city":"Fulda",
    "sg:phone":"+49 661/21464",
    "sg:postcode":"36037",
    "sg:province":"Hessen",
    "wof:name":"Bauer",
    "wof:placetype":"venue"
},
  "geometry": {"coordinates":[9.671645,50.548264],"type":"Point"}
}