{
  "type": "Feature",
  "properties": {
    "iso:country":"DE",
    "sg:address":"Markt 8 (Enge Stra\u00dfe)",
    "sg:city":"Rinteln",
    "sg:phone":"+49 5751/993280",
    "sg:postcode":"37737",
    "sg:province":"Niedersachsen",
    "wof:name":"Sonic-clean Jalousie-reinigung Mittels Ultraschall",
    "wof:placetype":"venue"
},
  "geometry": {"coordinates":[9.081131,52.187508],"type":"Point"}
}