{
  "type": "Feature",
  "properties": {
    "iso:country":"DE",
    "sg:address":"Sch\u00f6neberger Str. 14",
    "sg:city":"G\u00f6ttingen",
    "sg:phone":"+49 551/791127",
    "sg:postcode":"37085",
    "sg:province":"Niedersachsen",
    "wof:name":"Klaus Winkelmann Architekt",
    "wof:placetype":"venue"
},
  "geometry": {"coordinates":[9.973575,51.517487],"type":"Point"}
}