{
  "type": "Feature",
  "properties": {
    "iso:country":"DE",
    "sg:address":"Dessauer Str. 14",
    "sg:city":"Aken",
    "sg:phone":"+49 8334/273",
    "sg:postcode":"06385",
    "sg:province":"Sachsen-Anhalt",
    "wof:name":"Engel-holzverarbeitung Gmbh & Co. Kg",
    "wof:placetype":"venue"
},
  "geometry": {"coordinates":[10.2078104019,47.896270752],"type":"Point"}
}