{
  "type": "Feature",
  "properties": {
    "iso:country":"DE",
    "sg:address":"Kaufunger Str. 9a",
    "sg:city":"Nieste",
    "sg:phone":"+49 5605/2420",
    "sg:postcode":"34329",
    "sg:province":"Hessen",
    "wof:name":"Harald Degenhardt",
    "wof:placetype":"venue"
},
  "geometry": {"coordinates":[9.6702537537,51.3124732971],"type":"Point"}
}