{
  "type": "Feature",
  "properties": {
    "iso:country":"DE",
    "sg:address":"Petermannstr. 33",
    "sg:city":"Hannover",
    "sg:postcode":"30455",
    "sg:province":"Niedersachsen",
    "wof:name":"A. Deichmann",
    "wof:placetype":"venue"
},
  "geometry": {"coordinates":[9.681945,52.358215],"type":"Point"}
}