{
  "type": "Feature",
  "properties": {
    "iso:country":"DE",
    "sg:address":"Rudolf-Diesel-Str. 2",
    "sg:city":"Ganderkesee",
    "sg:postcode":"27777",
    "sg:province":"Niedersachsen",
    "wof:name":"J. & H. Gehlsen Sylter Baustoffhandel Gmbh & Co. Kg",
    "wof:placetype":"venue"
},
  "geometry": {"coordinates":[8.5500669479,53.0475196838],"type":"Point"}
}