{
  "type": "Feature",
  "properties": {
    "iso:country":"DE",
    "sg:address":"Augustastr. 2",
    "sg:city":"Dortmund",
    "sg:phone":"+49 231/161395",
    "sg:postcode":"44137",
    "sg:province":"Nordrhein-Westfalen",
    "wof:name":"Gastst\u00e4tte Kraftstoff",
    "wof:placetype":"venue"
},
  "geometry": {"coordinates":[7.4521689415,51.5131797791],"type":"Point"}
}