{
  "type": "Feature",
  "properties": {
    "iso:country":"DE",
    "sg:address":"Am Bahnhof 2",
    "sg:city":"Wulfsen",
    "sg:phone":"+49 4173/8800",
    "sg:postcode":"21445",
    "sg:province":"Niedersachsen",
    "wof:name":"Joachim Vincke Ingenieur",
    "wof:placetype":"venue"
},
  "geometry": {"coordinates":[10.1418895721,53.296131134],"type":"Point"}
}