{
  "type": "Feature",
  "properties": {
    "iso:country":"DE",
    "sg:address":"Simbacher Str. 4",
    "sg:city":"Pocking",
    "sg:phone":"+49 8531/4914",
    "sg:postcode":"94060",
    "sg:province":"Bayern",
    "wof:name":"Gastst\u00e4tte Zur Alten Post",
    "wof:placetype":"venue"
},
  "geometry": {"coordinates":[13.3109474182,48.4013366699],"type":"Point"}
}