{
  "type": "Feature",
  "properties": {
    "iso:country":"DE",
    "sg:address":"Dr.-Ruer-Platz 1",
    "sg:city":"Bochum",
    "sg:phone":"+49 234/67617",
    "sg:postcode":"44787",
    "sg:province":"Nordrhein-Westfalen",
    "wof:name":"Brunnen-apotheke",
    "wof:placetype":"venue"
},
  "geometry": {"coordinates":[7.218579,51.479816],"type":"Point"}
}