{
  "type": "Feature",
  "properties": {
    "iso:country":"DE",
    "sg:address":"Von-Geissel-Str. 2",
    "sg:city":"Neustadt",
    "sg:phone":"+49 6321/68268",
    "sg:postcode":"67435",
    "sg:province":"Rheinland-Pfalz",
    "wof:name":"Werner Schwarz Architekt",
    "wof:placetype":"venue"
},
  "geometry": {"coordinates":[8.152318,49.374439],"type":"Point"}
}