{
  "type": "Feature",
  "properties": {
    "iso:country":"DE",
    "sg:address":"Lange-Feld-Str. 72",
    "sg:city":"Hannover",
    "sg:phone":"+49 511/529686",
    "sg:postcode":"30559",
    "sg:province":"Niedersachsen",
    "wof:name":"Sb Baumschulen",
    "wof:placetype":"venue"
},
  "geometry": {"coordinates":[9.804096,52.360035],"type":"Point"}
}