{
  "type": "Feature",
  "properties": {
    "iso:country":"DE",
    "sg:address":"Hospitalstr. 2",
    "sg:city":"Hanau",
    "sg:phone":"+49 6181/919738",
    "sg:postcode":"63450",
    "sg:province":"Hessen",
    "wof:name":"Aqua Point Wasserbetten",
    "wof:placetype":"venue"
},
  "geometry": {"coordinates":[8.9152669907,50.1367874146],"type":"Point"}
}