{
  "type": "Feature",
  "properties": {
    "iso:country":"DE",
    "sg:address":"Kiefernweg 48",
    "sg:city":"Ettlingen",
    "sg:phone":"+49 7243/39999",
    "sg:postcode":"76275",
    "sg:province":"Baden-W\u00fcrttemberg",
    "wof:name":"Orient Taxi-zentrale",
    "wof:placetype":"venue"
},
  "geometry": {"coordinates":[8.3788490295,48.9506072998],"type":"Point"}
}