{
  "type": "Feature",
  "properties": {
    "iso:country":"DE",
    "sg:address":"Friedensallee 3",
    "sg:city":"Hinsdorf",
    "sg:phone":"+49 34977/40111",
    "sg:postcode":"06386",
    "sg:province":"Sachsen-Anhalt",
    "wof:name":"Schwei\u00df-und D\u00fcsentechnik Norbert K\u00fchnel",
    "wof:placetype":"venue"
},
  "geometry": {"coordinates":[12.149736,51.724495],"type":"Point"}
}