{
  "type": "Feature",
  "properties": {
    "iso:country":"DE",
    "sg:address":"Meiermattstr. 28",
    "sg:city":"Neuried",
    "sg:phone":"+49 7807/955436",
    "sg:postcode":"77743",
    "sg:province":"Baden-W\u00fcrttemberg",
    "wof:name":"Monika Gro\u00df",
    "wof:placetype":"venue"
},
  "geometry": {"coordinates":[7.838783,48.468307],"type":"Point"}
}