{
  "type": "Feature",
  "properties": {
    "iso:country":"DE",
    "sg:address":"An der Spinnerei 8",
    "sg:city":"Freital",
    "sg:phone":"+49 351/4760390",
    "sg:postcode":"01705",
    "sg:province":"Sachsen",
    "wof:name":"Kaufland",
    "wof:placetype":"venue"
},
  "geometry": {"coordinates":[13.6231203079,50.9768714905],"type":"Point"}
}