{
  "type": "Feature",
  "properties": {
    "iso:country":"DE",
    "sg:address":"Bertastr. 11",
    "sg:city":"J\u00fclich",
    "sg:postcode":"52428",
    "sg:province":"Nordrhein-Westfalen",
    "wof:name":"H. Barton",
    "wof:placetype":"venue"
},
  "geometry": {"coordinates":[6.368806,50.928879],"type":"Point"}
}