{
  "type": "Feature",
  "properties": {
    "iso:country":"DE",
    "sg:address":"Gewerbegebiet Am Richterweg 8",
    "sg:city":"Gro\u00dfr\u00fcckerswalde",
    "sg:phone":"+49 3735/23809",
    "sg:postcode":"09518",
    "sg:province":"Sachsen",
    "wof:name":"Steffen Hesse",
    "wof:placetype":"venue"
},
  "geometry": {"coordinates":[13.120781,50.632313],"type":"Point"}
}