{
  "type": "Feature",
  "properties": {
    "iso:country":"DE",
    "sg:address":"W.-Mellies-Str. 88",
    "sg:city":"Detmold",
    "sg:phone":"+49 5232/8171",
    "sg:postcode":"32758",
    "sg:province":"Nordrhein-Westfalen",
    "wof:name":"Elektronikladen Mikrocomputer Gmbh",
    "wof:placetype":"venue"
},
  "geometry": {"coordinates":[8.7821998596,51.9463577271],"type":"Point"}
}