{
  "type": "Feature",
  "properties": {
    "iso:country":"DE",
    "sg:address":"L\u00fcntorfer Str. 56",
    "sg:city":"Emmerthal",
    "sg:phone":"+49 5286/467",
    "sg:postcode":"31860",
    "sg:province":"Niedersachsen",
    "wof:name":"Friedhelm Nagel",
    "wof:placetype":"venue"
},
  "geometry": {"coordinates":[9.372015,51.980972],"type":"Point"}
}