{
  "type": "Feature",
  "properties": {
    "iso:country":"DE",
    "sg:address":"Am Hagschutz 10",
    "sg:city":"Schliengen",
    "sg:phone":"+49 7635/2567",
    "sg:postcode":"79418",
    "sg:province":"Baden-W\u00fcrttemberg",
    "wof:name":"Anneliese Hurst",
    "wof:placetype":"venue"
},
  "geometry": {"coordinates":[7.6268610954,47.7530975342],"type":"Point"}
}