{
  "type": "Feature",
  "properties": {
    "iso:country":"DE",
    "sg:address":"Ostanlage 39 41",
    "sg:city":"Gie\u00dfen",
    "sg:postcode":"35390",
    "sg:province":"Hessen",
    "wof:name":"Kreisbibliothek",
    "wof:placetype":"venue"
},
  "geometry": {"coordinates":[8.680278,50.585442],"type":"Point"}
}