{
  "type": "Feature",
  "properties": {
    "iso:country":"DE",
    "sg:address":"Hohenloher Str. 31",
    "sg:city":"Langenbrettach",
    "sg:phone":"+49 7946/8786",
    "sg:postcode":"74243",
    "sg:province":"Baden-W\u00fcrttemberg",
    "wof:name":"Wilhelm Bauer",
    "wof:placetype":"venue"
},
  "geometry": {"coordinates":[9.4051,49.216991],"type":"Point"}
}