{
  "type": "Feature",
  "properties": {
    "iso:country":"DE",
    "sg:address":"Spessartstr. 18",
    "sg:city":"Niederkassel",
    "sg:phone":"+49 228/454413",
    "sg:postcode":"53859",
    "sg:province":"Nordrhein-Westfalen",
    "wof:name":"Aom Immobilien Angelika Odenthal",
    "wof:placetype":"venue"
},
  "geometry": {"coordinates":[7.0631737709,50.780002594],"type":"Point"}
}