{
  "type": "Feature",
  "properties": {
    "iso:country":"DE",
    "sg:address":"Edenkobener Str. 42",
    "sg:city":"St Martin",
    "sg:phone":"+49 6323/2909",
    "sg:postcode":"67487",
    "sg:province":"Rheinland-Pfalz",
    "wof:name":"Edgar Christmann",
    "wof:placetype":"venue"
},
  "geometry": {"coordinates":[8.1061592102,49.2977828979],"type":"Point"}
}