{
  "type": "Feature",
  "properties": {
    "iso:country":"DE",
    "sg:address":"Max-Josef-Str. 8",
    "sg:city":"Amberg",
    "sg:phone":"+49 9621/12520",
    "sg:postcode":"92224",
    "sg:province":"Bayern",
    "wof:name":"Egmont Liebl",
    "wof:placetype":"venue"
},
  "geometry": {"coordinates":[11.851086,49.448257],"type":"Point"}
}