{
  "type": "Feature",
  "properties": {
    "iso:country":"DE",
    "sg:address":"Am J\u00e4gersteig 3",
    "sg:city":"Hilden",
    "sg:phone":"+49 2103/361451",
    "sg:postcode":"40724",
    "sg:province":"Nordrhein-Westfalen",
    "wof:name":"P. Persighetti",
    "wof:placetype":"venue"
},
  "geometry": {"coordinates":[6.94315,51.177898],"type":"Point"}
}