{
  "type": "Feature",
  "properties": {
    "iso:country":"DE",
    "sg:address":"R\u00f6lkenstr. 6",
    "sg:city":"\u00dcbach-Palenberg",
    "sg:phone":"+49 2451/48889",
    "sg:postcode":"52531",
    "sg:province":"Nordrhein-Westfalen",
    "wof:name":"Norma Kuhlmey-m\u00fcller",
    "wof:placetype":"venue"
},
  "geometry": {"coordinates":[6.125814,50.915485],"type":"Point"}
}