{
  "type": "Feature",
  "properties": {
    "iso:country":"DE",
    "sg:address":"Preusweg 25",
    "sg:city":"Aachen",
    "sg:phone":"+49 241/78302",
    "sg:postcode":"52074",
    "sg:province":"Nordrhein-Westfalen",
    "wof:name":"Arwed Tomm Architekt",
    "wof:placetype":"venue"
},
  "geometry": {"coordinates":[6.062465,50.759361],"type":"Point"}
}