{
  "type": "Feature",
  "properties": {
    "iso:country":"DE",
    "sg:address":"Potsdamer Str. 18",
    "sg:city":"Brandenburg",
    "sg:phone":"+49 3381/587111",
    "sg:postcode":"14776",
    "sg:province":"Brandenburg",
    "wof:name":"Stadthafen Der Stadt Brandenburg An Der Havel",
    "wof:placetype":"venue"
},
  "geometry": {"coordinates":[12.5756464005,52.405872345],"type":"Point"}
}