{
  "type": "Feature",
  "properties": {
    "iso:country":"DE",
    "sg:address":"Anderlohrstr. 4",
    "sg:city":"Erlangen",
    "sg:phone":"+49 9131/58941",
    "sg:postcode":"91054",
    "sg:province":"Bayern",
    "wof:name":"Erlanger Chirurgie - Und Endoskopie -training Gmbh",
    "wof:placetype":"venue"
},
  "geometry": {"coordinates":[11.038522,49.601543],"type":"Point"}
}