{
  "type": "Feature",
  "properties": {
    "iso:country":"DE",
    "sg:address":"Bahnhofstr. 1 a",
    "sg:city":"Heide",
    "sg:phone":"+49 481/850510",
    "sg:postcode":"25746",
    "sg:province":"Schleswig-Holstein",
    "wof:name":"Ullrich Funk Michael Kremendahl",
    "wof:placetype":"venue"
},
  "geometry": {"coordinates":[9.0950870514,54.1959838867],"type":"Point"}
}