{
  "type": "Feature",
  "properties": {
    "iso:country":"DE",
    "sg:city":"Warendorf",
    "sg:phone":"+49 2581/634343",
    "sg:postcode":"48231",
    "sg:province":"Nordrhein-Westfalen",
    "wof:name":"Tauchteam Warendorf",
    "wof:placetype":"venue"
},
  "geometry": {"coordinates":[7.98943,51.949547],"type":"Point"}
}