{
  "type": "Feature",
  "properties": {
    "iso:country":"DE",
    "sg:address":"Zellerstr. 22",
    "sg:city":"Michelstadt",
    "sg:phone":"+49 4960/61760",
    "sg:postcode":"64720",
    "sg:province":"Hessen",
    "wof:name":"Kongskilde Howard Gmbh",
    "wof:placetype":"venue"
},
  "geometry": {"coordinates":[9.008102,49.689125],"type":"Point"}
}