{
  "type": "Feature",
  "properties": {
    "iso:country":"DE",
    "sg:address":"Am Buchenhain 1",
    "sg:city":"Vlotho",
    "sg:phone":"+49 5733/7334",
    "sg:postcode":"32602",
    "sg:province":"Nordrhein-Westfalen",
    "wof:name":"Wilhelm Meyer-kare",
    "wof:placetype":"venue"
},
  "geometry": {"coordinates":[8.817355,52.132095],"type":"Point"}
}