{
  "type": "Feature",
  "properties": {
    "iso:country":"DE",
    "sg:address":"Wiesestrasse 23",
    "sg:city":"Gera",
    "sg:phone":"+49 365",
    "sg:postcode":"07458",
    "sg:province":"Th\u00fcringen",
    "wof:name":"Klaiber Elektronik",
    "wof:placetype":"venue"
},
  "geometry": {"coordinates":[-83.73846399999999,43.38332],"type":"Point"}
}