{
  "type": "Feature",
  "properties": {
    "iso:country":"DE",
    "sg:address":"Marktstr. 94",
    "sg:city":"Oberhausen",
    "sg:phone":"+49 208/809544",
    "sg:postcode":"46045",
    "sg:province":"Nordrhein-Westfalen",
    "wof:name":"Parf\u00fcmerie Yaska",
    "wof:placetype":"venue"
},
  "geometry": {"coordinates":[6.855275,51.468987],"type":"Point"}
}