{
  "type": "Feature",
  "properties": {
    "iso:country":"DE",
    "sg:address":"Am Bahnhof 3",
    "sg:city":"Harpstedt",
    "sg:phone":"+49 4244/8045",
    "sg:postcode":"27243",
    "sg:province":"Niedersachsen",
    "wof:name":"Zur Waage",
    "wof:placetype":"venue"
},
  "geometry": {"coordinates":[8.6000432968,52.9104423523],"type":"Point"}
}