{
  "type": "Feature",
  "properties": {
    "iso:country":"DE",
    "sg:address":"Robert-Koch-Str. 74",
    "sg:city":"K\u00f6ln",
    "sg:phone":"+49 221/9591105",
    "sg:postcode":"50767",
    "sg:province":"Nordrhein-Westfalen",
    "wof:name":"Degena Natt",
    "wof:placetype":"venue"
},
  "geometry": {"coordinates":[6.880096,51.00198],"type":"Point"}
}