{
  "type": "Feature",
  "properties": {
    "iso:country":"DE",
    "sg:address":"Vincent-van-Gogh-Str. 17",
    "sg:city":"Berlin",
    "sg:phone":"+49 30/9244092",
    "sg:postcode":"13057",
    "sg:province":"Berlin",
    "wof:name":"Schneble & Partner Gmbh",
    "wof:placetype":"venue"
},
  "geometry": {"coordinates":[13.5238809586,52.5662384033],"type":"Point"}
}