{
  "type": "Feature",
  "properties": {
    "iso:country":"DE",
    "sg:address":"Badstr. 28",
    "sg:city":"F\u00fcrth",
    "sg:phone":"+49 911/7418367",
    "sg:postcode":"90762",
    "sg:province":"Bayern",
    "wof:name":"Johann Ehrhardt & S\u00f6hne Buch- Und Zeitschriften-",
    "wof:placetype":"venue"
},
  "geometry": {"coordinates":[10.982086,49.473221],"type":"Point"}
}