{
  "type": "Feature",
  "properties": {
    "iso:country":"DE",
    "sg:address":"Triftstr. 49",
    "sg:city":"Weilerswist",
    "sg:phone":"+49 2254/2599",
    "sg:postcode":"53919",
    "sg:province":"Nordrhein-Westfalen",
    "wof:name":"Manfred Becker Rechtsanwalt",
    "wof:placetype":"venue"
},
  "geometry": {"coordinates":[6.8467230797,50.7566337585],"type":"Point"}
}