{
  "type": "Feature",
  "properties": {
    "iso:country":"DE",
    "sg:address":"M\u00fcggenburg 62",
    "sg:city":"Wuppertal",
    "sg:phone":"+49 202/520168",
    "sg:postcode":"42277",
    "sg:province":"Nordrhein-Westfalen",
    "wof:name":"Asb Bootshandel Gmbh",
    "wof:placetype":"venue"
},
  "geometry": {"coordinates":[7.2121591568,51.2870063782],"type":"Point"}
}