{
  "type": "Feature",
  "properties": {
    "iso:country":"DE",
    "sg:address":"Agnes-Smedley-Str. 19",
    "sg:city":"Chemnitz",
    "sg:phone":"+49 371/517272",
    "sg:postcode":"09126",
    "sg:province":"Sachsen",
    "wof:name":"E. Biefang",
    "wof:placetype":"venue"
},
  "geometry": {"coordinates":[12.958554,50.812702],"type":"Point"}
}