{
  "type": "Feature",
  "properties": {
    "iso:country":"DE",
    "sg:address":"Knapper Str. 48",
    "sg:city":"L\u00fcdenscheid",
    "sg:phone":"+49 2351/29676",
    "sg:postcode":"58507",
    "sg:province":"Nordrhein-Westfalen",
    "wof:name":"Schwanen-apotheke",
    "wof:placetype":"venue"
},
  "geometry": {"coordinates":[7.62618,51.23053],"type":"Point"}
}