{
  "type": "Feature",
  "properties": {
    "iso:country":"DE",
    "sg:address":"Oettinger Str 2",
    "sg:city":"N\u00f6rdlingen",
    "sg:phone":"+49 9081/80110",
    "sg:postcode":"86720",
    "sg:province":"Bayern",
    "wof:name":"D\u00f6derlein Spedition Gmbh",
    "wof:placetype":"venue"
},
  "geometry": {"coordinates":[10.5029859543,48.8621253967],"type":"Point"}
}