{
  "type": "Feature",
  "properties": {
    "iso:country":"DE",
    "sg:address":"Fritz-Reuter-Str. 41",
    "sg:city":"Teltow",
    "sg:postcode":"14513",
    "sg:province":"Brandenburg",
    "wof:name":"Schmuck Und Zahn Vertriebsgesellschaft Mbh",
    "wof:placetype":"venue"
},
  "geometry": {"coordinates":[13.288977623,52.4032707214],"type":"Point"}
}