{
  "type": "Feature",
  "properties": {
    "iso:country":"DE",
    "sg:address":"Schleifbr\u00fcckenstr. 1",
    "sg:city":"Aalen",
    "sg:phone":"+49 7361/61845",
    "sg:postcode":"73430",
    "sg:province":"Baden-W\u00fcrttemberg",
    "wof:name":"Weinmarkt Grieser Gmbh",
    "wof:placetype":"venue"
},
  "geometry": {"coordinates":[10.0948677063,48.8429222107],"type":"Point"}
}