{
  "type": "Feature",
  "properties": {
    "iso:country":"DE",
    "sg:address":"Limbecker Platz 2",
    "sg:city":"Essen",
    "sg:postcode":"45127",
    "sg:province":"Nordrhein-Westfalen",
    "wof:name":"Caf\u00e9 Klatsch Gmbh",
    "wof:placetype":"venue"
},
  "geometry": {"coordinates":[7.006612,51.457825],"type":"Point"}
}