{
  "type": "Feature",
  "properties": {
    "iso:country":"DE",
    "sg:address":"Hakenbreite 23",
    "sg:city":"Dransfeld",
    "sg:phone":"+49 5502/47394",
    "sg:postcode":"37127",
    "sg:province":"Niedersachsen",
    "wof:name":"Simon Gbr",
    "wof:placetype":"venue"
},
  "geometry": {"coordinates":[9.763398,51.498379],"type":"Point"}
}