{
  "type": "Feature",
  "properties": {
    "iso:country":"DE",
    "sg:address":"Schuhmacherort 2",
    "sg:city":"Heide",
    "sg:phone":"+49 481/5666",
    "sg:postcode":"25746",
    "sg:province":"Schleswig-Holstein",
    "wof:name":"Donna Moden",
    "wof:placetype":"venue"
},
  "geometry": {"coordinates":[9.094952,54.196148],"type":"Point"}
}