{
  "type": "Feature",
  "properties": {
    "iso:country":"DE",
    "sg:address":"Oberdorfstr. 2",
    "sg:city":"Essen",
    "sg:phone":"+49 201/741014",
    "sg:postcode":"45143",
    "sg:province":"Nordrhein-Westfalen",
    "wof:name":"City Security Gmbh",
    "wof:placetype":"venue"
},
  "geometry": {"coordinates":[6.979908,51.460567],"type":"Point"}
}