{
  "type": "Feature",
  "properties": {
    "iso:country":"DE",
    "sg:address":"Lange Str. 34",
    "sg:city":"Uslar",
    "sg:phone":"+49 5571/2629",
    "sg:postcode":"37170",
    "sg:province":"Niedersachsen",
    "wof:name":"Schweizer Grill",
    "wof:placetype":"venue"
},
  "geometry": {"coordinates":[9.6364622116,51.6591835022],"type":"Point"}
}