{
  "type": "Feature",
  "properties": {
    "iso:country":"DE",
    "sg:address":"Am Gutshof 2 a",
    "sg:city":"Werder",
    "sg:phone":"+49 3327/70110",
    "sg:postcode":"14542",
    "sg:province":"Brandenburg",
    "wof:name":"Max Und Moritz Gbr",
    "wof:placetype":"venue"
},
  "geometry": {"coordinates":[12.9362678528,52.3756484985],"type":"Point"}
}