{
  "type": "Feature",
  "properties": {
    "iso:country":"DE",
    "sg:address":"Friedensstr. 4",
    "sg:city":"Dahlen",
    "sg:phone":"+49 34361/51741",
    "sg:postcode":"04774",
    "sg:province":"Sachsen",
    "wof:name":"Lakuwa Gmbh",
    "wof:placetype":"venue"
},
  "geometry": {"coordinates":[13.03754,51.33448],"type":"Point"}
}