{
  "type": "Feature",
  "properties": {
    "iso:country":"DE",
    "sg:address":"Bahnhofstr. 14",
    "sg:city":"Gundelfingen",
    "sg:phone":"+49 761/581018",
    "sg:postcode":"79194",
    "sg:province":"Baden-W\u00fcrttemberg",
    "wof:name":"V\u00f6lker Farbspritztechnik Gmbh",
    "wof:placetype":"venue"
},
  "geometry": {"coordinates":[7.872787,48.043419],"type":"Point"}
}