{
  "type": "Feature",
  "properties": {
    "iso:country":"DE",
    "sg:address":"Salzstr. 34",
    "sg:city":"Kempten",
    "sg:phone":"+49 831/520270",
    "sg:postcode":"87435",
    "sg:province":"Bayern",
    "wof:name":"Helget Und B\u00fchler Finanzberater",
    "wof:placetype":"venue"
},
  "geometry": {"coordinates":[10.3103618622,47.7277412415],"type":"Point"}
}