{
  "type": "Feature",
  "properties": {
    "iso:country":"DE",
    "sg:address":"Fuldaer Strasse 20",
    "sg:city":"Dipperz",
    "sg:phone":"+49 6657/918117",
    "sg:postcode":"36160",
    "sg:province":"Hessen",
    "wof:name":"Eilgeschenke",
    "wof:placetype":"venue"
},
  "geometry": {"coordinates":[9.794945,50.542957],"type":"Point"}
}