{
  "type": "Feature",
  "properties": {
    "iso:country":"DE",
    "sg:address":"Mozartstr. 18",
    "sg:city":"Burgst\u00e4dt",
    "sg:phone":"+49 3724/14117",
    "sg:postcode":"09217",
    "sg:province":"Sachsen",
    "wof:name":"G. Steyer",
    "wof:placetype":"venue"
},
  "geometry": {"coordinates":[12.804454,50.912762],"type":"Point"}
}