{
  "type": "Feature",
  "properties": {
    "iso:country":"DE",
    "sg:address":"Ostlandstr. 6",
    "sg:city":"Lippstadt",
    "sg:postcode":"59558",
    "sg:province":"Nordrhein-Westfalen",
    "wof:name":"Anton R\u00f6hr Gmbh",
    "wof:placetype":"venue"
},
  "geometry": {"coordinates":[8.363403,51.710426],"type":"Point"}
}