{
  "type": "Feature",
  "properties": {
    "iso:country":"DE",
    "sg:address":"Ulmer Str. 53",
    "sg:city":"Nersingen",
    "sg:phone":"+49 7308/41280",
    "sg:postcode":"89278",
    "sg:province":"Bayern",
    "wof:name":"A. Konrad",
    "wof:placetype":"venue"
},
  "geometry": {"coordinates":[10.125982,48.428684],"type":"Point"}
}