{
  "type": "Feature",
  "properties": {
    "iso:country":"DE",
    "sg:address":"Am P\u00f6nitzberg 8",
    "sg:city":"Strehla",
    "sg:phone":"+49 35264/91578",
    "sg:postcode":"01616",
    "sg:province":"Sachsen",
    "wof:name":"K. M\u00fcller",
    "wof:placetype":"venue"
},
  "geometry": {"coordinates":[13.2220592499,51.3577079773],"type":"Point"}
}