{
  "type": "Feature",
  "properties": {
    "iso:country":"DE",
    "sg:address":"Lindenstr. 12",
    "sg:city":"Bischofsheim",
    "sg:phone":"+49 9772/690",
    "sg:postcode":"97653",
    "sg:province":"Bayern",
    "wof:name":"Msb Maschinenbau Schmitt Inh. Hans-dieter Schmitt",
    "wof:placetype":"venue"
},
  "geometry": {"coordinates":[10.0108966827,50.4024047852],"type":"Point"}
}