{
  "type": "Feature",
  "properties": {
    "iso:country":"DE",
    "sg:address":"Rellinghauser Str. 273",
    "sg:city":"Essen",
    "sg:phone":"+49 201/253433",
    "sg:postcode":"45136",
    "sg:province":"Nordrhein-Westfalen",
    "wof:name":"Balzer Gmbh",
    "wof:placetype":"venue"
},
  "geometry": {"coordinates":[7.0331931114,51.4366149902],"type":"Point"}
}