{
  "type": "Feature",
  "properties": {
    "iso:country":"DE",
    "sg:address":"Piderits Bleiche 11",
    "sg:city":"Bielefeld",
    "sg:phone":"+49 5205/967636",
    "sg:postcode":"33689",
    "sg:province":"Nordrhein-Westfalen",
    "wof:name":"Senne Haus Bautr\u00e4ger Gmbh",
    "wof:placetype":"venue"
},
  "geometry": {"coordinates":[8.574543,51.936569],"type":"Point"}
}