{
  "type": "Feature",
  "properties": {
    "iso:country":"DE",
    "sg:address":"Sternstr. 12",
    "sg:city":"Lutherstadt Wittenberg",
    "sg:phone":"+49 3491/402221",
    "sg:postcode":"06886",
    "sg:province":"Sachsen-Anhalt",
    "wof:name":"Central-theater",
    "wof:placetype":"venue"
},
  "geometry": {"coordinates":[12.631833,51.878517],"type":"Point"}
}