{
  "type": "Feature",
  "properties": {
    "iso:country":"DE",
    "sg:address":"Ludwigstr. 1",
    "sg:city":"Passau",
    "sg:phone":"+49 851/34529",
    "sg:postcode":"94032",
    "sg:province":"Bayern",
    "wof:name":"Blumenwelt Breedijk Gmbh",
    "wof:placetype":"venue"
},
  "geometry": {"coordinates":[13.460546,48.574848],"type":"Point"}
}