{
  "type": "Feature",
  "properties": {
    "iso:country":"DE",
    "sg:address":"Alemannenstr. 11",
    "sg:city":"Elsdorf",
    "sg:phone":"+49 2274/905252",
    "sg:postcode":"50189",
    "sg:province":"Nordrhein-Westfalen",
    "wof:name":"Hamburg-mannheimer",
    "wof:placetype":"venue"
},
  "geometry": {"coordinates":[6.5596671104,50.9425315857],"type":"Point"}
}