{
  "type": "Feature",
  "properties": {
    "iso:country":"DE",
    "sg:address":"H\u00f6henweg 29",
    "sg:city":"Butzbach",
    "sg:postcode":"35510",
    "sg:province":"Hessen",
    "wof:name":"Ihc Inter Hospital Consult Gmbh",
    "wof:placetype":"venue"
},
  "geometry": {"coordinates":[8.6127243042,50.3813209534],"type":"Point"}
}