{
  "type": "Feature",
  "properties": {
    "iso:country":"DE",
    "sg:address":"Anreppener Str. 2",
    "sg:city":"Delbr\u00fcck",
    "sg:phone":"+49 5250/97650",
    "sg:postcode":"33129",
    "sg:province":"Nordrhein-Westfalen",
    "wof:name":"Salmen Gmbh Baumschule",
    "wof:placetype":"venue"
},
  "geometry": {"coordinates":[8.573456,51.76144],"type":"Point"}
}