{
  "type": "Feature",
  "properties": {
    "iso:country":"DE",
    "sg:address":"Victorbur",
    "sg:city":"S\u00fcdbrookmerland",
    "sg:phone":"+49 4942/1452",
    "sg:postcode":"26624",
    "sg:province":"Niedersachsen",
    "wof:name":"Constant",
    "wof:placetype":"venue"
},
  "geometry": {"coordinates":[7.395793,53.486561],"type":"Point"}
}