{
  "type": "Feature",
  "properties": {
    "iso:country":"DE",
    "sg:address":"Neuengammer Hinterdeich 34",
    "sg:city":"Hamburg",
    "sg:phone":"+49 40/7230259",
    "sg:postcode":"21037",
    "sg:province":"Hamburg",
    "wof:name":"Erich Hagen",
    "wof:placetype":"venue"
},
  "geometry": {"coordinates":[10.211455,53.427853],"type":"Point"}
}