{
  "type": "Feature",
  "properties": {
    "iso:country":"DE",
    "sg:address":"Leineweberstr. 22 b",
    "sg:city":"Viersen",
    "sg:phone":"+49 2162/13226",
    "sg:postcode":"41748",
    "sg:province":"Nordrhein-Westfalen",
    "wof:name":"Peter Steffens",
    "wof:placetype":"venue"
},
  "geometry": {"coordinates":[6.370203,51.234531],"type":"Point"}
}