{
  "type": "Feature",
  "properties": {
    "iso:country":"DE",
    "sg:address":"St.-Anna-Str. 14",
    "sg:city":"Bad W\u00f6rishofen",
    "sg:phone":"+49 8247/32916",
    "sg:postcode":"86825",
    "sg:province":"Bayern",
    "wof:name":"Alois Birk",
    "wof:placetype":"venue"
},
  "geometry": {"coordinates":[10.596935,48.002708],"type":"Point"}
}