{
  "type": "Feature",
  "properties": {
    "iso:country":"DE",
    "sg:address":"Arnshaugker Str. 15",
    "sg:city":"Neustadt",
    "sg:phone":"+49 36481/22176",
    "sg:postcode":"07806",
    "sg:province":"Th\u00fcringen",
    "wof:name":"Norbert H\u00f6fer",
    "wof:placetype":"venue"
},
  "geometry": {"coordinates":[11.736365,50.724075],"type":"Point"}
}