{
  "type": "Feature",
  "properties": {
    "iso:country":"DE",
    "sg:address":"Justus-Liebig-Str. 45",
    "sg:city":"Bayreuth",
    "sg:phone":"+49 921/58247",
    "sg:postcode":"95447",
    "sg:province":"Bayern",
    "wof:name":"Freie Tankstelle Gerhard Kraus",
    "wof:placetype":"venue"
},
  "geometry": {"coordinates":[11.5630950928,49.9336280823],"type":"Point"}
}