{
  "type": "Feature",
  "properties": {
    "iso:country":"DE",
    "sg:address":"Wismarsche Str. 3",
    "sg:city":"Grevesm\u00fchlen",
    "sg:phone":"+49 3881/2295",
    "sg:postcode":"23936",
    "sg:province":"Mecklenburg-Vorpommern",
    "wof:name":"S. Rathmann",
    "wof:placetype":"venue"
},
  "geometry": {"coordinates":[11.185844,53.864735],"type":"Point"}
}