{
  "type": "Feature",
  "properties": {
    "iso:country":"DE",
    "sg:address":"Mayerbacherstr. 54",
    "sg:city":"Ismaning",
    "sg:phone":"+49 89/968529",
    "sg:postcode":"85737",
    "sg:province":"Bayern",
    "wof:name":"Martin Soller",
    "wof:placetype":"venue"
},
  "geometry": {"coordinates":[11.694103,48.22744],"type":"Point"}
}