{
  "type": "Feature",
  "properties": {
    "iso:country":"DE",
    "sg:address":"Gartenstr. 4",
    "sg:city":"Gschwend",
    "sg:phone":"+49 7972/910492",
    "sg:postcode":"74417",
    "sg:province":"Baden-W\u00fcrttemberg",
    "wof:name":"Linares Gmbh",
    "wof:placetype":"venue"
},
  "geometry": {"coordinates":[9.7455186844,48.9355545044],"type":"Point"}
}