{
  "type": "Feature",
  "properties": {
    "iso:country":"DE",
    "sg:address":"Hartensteiner Str 5",
    "sg:city":"L\u00f6\u00dfnitz",
    "sg:phone":"+49 3771/37000",
    "sg:postcode":"08294",
    "sg:province":"Sachsen",
    "wof:name":"Telco Kommunikationstechnik Gmbh",
    "wof:placetype":"venue"
},
  "geometry": {"coordinates":[12.7719192505,50.6530303955],"type":"Point"}
}