{
  "type": "Feature",
  "properties": {
    "iso:country":"DE",
    "sg:address":"Sch\u00e4berlesg\u00e4ssle 5",
    "sg:city":"Balingen",
    "sg:phone":"+49 7433/23749",
    "sg:postcode":"72336",
    "sg:province":"Baden-W\u00fcrttemberg",
    "wof:name":"Riewe & Klumpp Fachbetr.f. W\u00e4rme-k\u00e4lte-schallschutz",
    "wof:placetype":"venue"
},
  "geometry": {"coordinates":[8.84245,48.302116],"type":"Point"}
}