{
  "type": "Feature",
  "properties": {
    "iso:country":"DE",
    "sg:address":"Parkstr. 6",
    "sg:city":"Ranstadt",
    "sg:phone":"+49 6041/50330",
    "sg:postcode":"63691",
    "sg:province":"Hessen",
    "wof:name":"Eberhard Raimund",
    "wof:placetype":"venue"
},
  "geometry": {"coordinates":[8.9626264572,50.3452262878],"type":"Point"}
}