{
  "type": "Feature",
  "properties": {
    "iso:country":"DE",
    "sg:address":"Koppel 106",
    "sg:city":"Hamburg",
    "sg:phone":"+49 40/243344",
    "sg:postcode":"20099",
    "sg:province":"Hamburg",
    "wof:name":"Heimfi Immobilien Gmbh",
    "wof:placetype":"venue"
},
  "geometry": {"coordinates":[10.0139865875,53.5601997375],"type":"Point"}
}