{
  "type": "Feature",
  "properties": {
    "iso:country":"DE",
    "sg:address":"Aegidienberger Str. 20",
    "sg:city":"K\u00f6ln",
    "sg:phone":"+49 221/428761",
    "sg:postcode":"50939",
    "sg:province":"Nordrhein-Westfalen",
    "wof:name":"Christian Gnielka",
    "wof:placetype":"venue"
},
  "geometry": {"coordinates":[6.9300570488,50.9156341553],"type":"Point"}
}