{
  "type": "Feature",
  "properties": {
    "iso:country":"DE",
    "sg:address":"Erlenstr. 10",
    "sg:city":"Meppen",
    "sg:phone":"+49 5931/12058",
    "sg:postcode":"49716",
    "sg:province":"Niedersachsen",
    "wof:name":"J\u00fcrgen Und Janna K\u00f6hler",
    "wof:placetype":"venue"
},
  "geometry": {"coordinates":[7.2236828804,52.7001266479],"type":"Point"}
}