{
  "type": "Feature",
  "properties": {
    "iso:country":"DE",
    "sg:address":"Industriestr. 94",
    "sg:city":"Bammental",
    "sg:phone":"+49 6223/48222",
    "sg:postcode":"69245",
    "sg:province":"Baden-W\u00fcrttemberg",
    "wof:name":"Seniorenresidenz",
    "wof:placetype":"venue"
},
  "geometry": {"coordinates":[8.784953,49.345356],"type":"Point"}
}