{
  "type": "Feature",
  "properties": {
    "iso:country":"DE",
    "sg:address":"Bargteheider Str. 87",
    "sg:city":"Hamburg",
    "sg:phone":"+49 40/6470026",
    "sg:postcode":"22143",
    "sg:province":"Hamburg",
    "wof:name":"L & L Lehmann & St\u00e4cker",
    "wof:placetype":"venue"
},
  "geometry": {"coordinates":[10.146313,53.603756],"type":"Point"}
}