{
  "type": "Feature",
  "properties": {
    "iso:country":"DE",
    "sg:address":"Unter dem Badertor",
    "sg:city":"B\u00fcrgel",
    "sg:phone":"+49 36692/22668",
    "sg:postcode":"07616",
    "sg:province":"Th\u00fcringen",
    "wof:name":"K. Br\u00f6cker Hebamme",
    "wof:placetype":"venue"
},
  "geometry": {"coordinates":[11.75369,50.940636],"type":"Point"}
}