{
  "type": "Feature",
  "properties": {
    "iso:country":"DE",
    "sg:address":"Wacholderstr. 12",
    "sg:city":"D\u00fcsseldorf",
    "sg:phone":"+49 203/740051",
    "sg:postcode":"40489",
    "sg:province":"Nordrhein-Westfalen",
    "wof:name":"Ferdinand Sonnen",
    "wof:placetype":"venue"
},
  "geometry": {"coordinates":[6.7796840668,51.3231620789],"type":"Point"}
}