{
  "type": "Feature",
  "properties": {
    "iso:country":"DE",
    "sg:address":"Hornisgrindestr. 75",
    "sg:city":"Rheinau",
    "sg:phone":"+49 7844/7760",
    "sg:postcode":"77866",
    "sg:province":"Baden-W\u00fcrttemberg",
    "wof:name":"Ev. Pfarramt Memprechtshofen",
    "wof:placetype":"venue"
},
  "geometry": {"coordinates":[7.9916510582,48.6794548035],"type":"Point"}
}