{
  "type": "Feature",
  "properties": {
    "iso:country":"DE",
    "sg:address":"Lindenstr. 36",
    "sg:city":"H\u00fcrth",
    "sg:phone":"+49 2233/67839",
    "sg:postcode":"50354",
    "sg:province":"Nordrhein-Westfalen",
    "wof:name":"Stadtb\u00e4ckerei Klein Gmbh",
    "wof:placetype":"venue"
},
  "geometry": {"coordinates":[6.865279,50.86961],"type":"Point"}
}