{
  "type": "Feature",
  "properties": {
    "iso:country":"DE",
    "sg:address":"Bentheimer Str. 36",
    "sg:city":"Nordhorn",
    "sg:phone":"+49 5921/75904",
    "sg:postcode":"48529",
    "sg:province":"Niedersachsen",
    "wof:name":"Cornelia Pape Praxis F\u00fcr Ergotherapie",
    "wof:placetype":"venue"
},
  "geometry": {"coordinates":[7.07103,52.430561],"type":"Point"}
}