{
  "type": "Feature",
  "properties": {
    "iso:country":"DE",
    "sg:address":"Liebigstr. 41",
    "sg:city":"Darmstadt",
    "sg:phone":"+49 6151/25204",
    "sg:postcode":"64293",
    "sg:province":"Hessen",
    "wof:name":"Alois Funk Architekt",
    "wof:placetype":"venue"
},
  "geometry": {"coordinates":[8.6479,49.880558],"type":"Point"}
}