{
  "type": "Feature",
  "properties": {
    "iso:country":"DE",
    "sg:address":"Mittelstr. 24",
    "sg:city":"N\u00fcnchritz",
    "sg:phone":"+49 35267/50271",
    "sg:postcode":"01612",
    "sg:province":"Sachsen",
    "wof:name":"Steffen Weigt",
    "wof:placetype":"venue"
},
  "geometry": {"coordinates":[13.4424266815,51.2909736633],"type":"Point"}
}