{
  "type": "Feature",
  "properties": {
    "iso:country":"DE",
    "sg:address":"Sindelfinger Str. 7",
    "sg:city":"Sindelfingen",
    "sg:phone":"+49 7031/383366",
    "sg:postcode":"71069",
    "sg:province":"Baden-W\u00fcrttemberg",
    "wof:name":"Pizzeria Alter Hirsch",
    "wof:placetype":"venue"
},
  "geometry": {"coordinates":[8.9647397995,48.7244491577],"type":"Point"}
}