{
  "type": "Feature",
  "properties": {
    "iso:country":"DE",
    "sg:address":"Barnerstr. 14",
    "sg:city":"Hamburg",
    "sg:postcode":"22765",
    "sg:province":"Hamburg",
    "wof:name":"Railconex Gmbh",
    "wof:placetype":"venue"
},
  "geometry": {"coordinates":[9.932268,53.557331],"type":"Point"}
}