{
  "type": "Feature",
  "properties": {
    "iso:country":"DE",
    "sg:address":"Bornwiese 6",
    "sg:city":"Bernkastel-Kues",
    "sg:phone":"+49 6531/570",
    "sg:postcode":"54470",
    "sg:province":"Rheinland-Pfalz",
    "wof:name":"Moselland Eg",
    "wof:placetype":"venue"
},
  "geometry": {"coordinates":[7.0612931252,49.9274635315],"type":"Point"}
}