{
  "type": "Feature",
  "properties": {
    "iso:country":"DE",
    "sg:address":"Albert-Einstein-Str. 13",
    "sg:city":"Linkenheim-Hochstetten",
    "sg:phone":"+49 7247/93840",
    "sg:postcode":"76351",
    "sg:province":"Baden-W\u00fcrttemberg",
    "wof:name":"Eurospar Wossmann",
    "wof:placetype":"venue"
},
  "geometry": {"coordinates":[8.4120254517,49.1284370422],"type":"Point"}
}