{
  "type": "Feature",
  "properties": {
    "iso:country":"DE",
    "sg:address":"Norderwieke S\u00fcd 34",
    "sg:city":"Gro\u00dfefehn",
    "sg:phone":"+49 4943/805",
    "sg:postcode":"26629",
    "sg:province":"Niedersachsen",
    "wof:name":"Gerd Beyen",
    "wof:placetype":"venue"
},
  "geometry": {"coordinates":[7.647475,53.401005],"type":"Point"}
}