{
  "type": "Feature",
  "properties": {
    "iso:country":"DE",
    "sg:address":"Weinsteinstr. 18",
    "sg:city":"Sonnenb\u00fchl",
    "sg:phone":"+49 7128/481",
    "sg:postcode":"72820",
    "sg:province":"Baden-W\u00fcrttemberg",
    "wof:name":"Walter K\u00fcbler Anlageberater",
    "wof:placetype":"venue"
},
  "geometry": {"coordinates":[9.1788396835,48.3856163025],"type":"Point"}
}