{
  "type": "Feature",
  "properties": {
    "iso:country":"DE",
    "sg:address":"Tettnanger Str. 12",
    "sg:city":"Neukirch",
    "sg:postcode":"88099",
    "sg:province":"Baden-W\u00fcrttemberg",
    "wof:name":"Modehaus Buffler Gmbh",
    "wof:placetype":"venue"
},
  "geometry": {"coordinates":[9.701921,47.658993],"type":"Point"}
}