{
  "type": "Feature",
  "properties": {
    "iso:country":"DE",
    "sg:address":"Maximiliankorso 1",
    "sg:city":"Berlin",
    "sg:phone":"+49 30/4961039",
    "sg:postcode":"13465",
    "sg:province":"Berlin",
    "wof:name":"Wolfgang Thies",
    "wof:placetype":"venue"
},
  "geometry": {"coordinates":[13.2877540588,52.6331443787],"type":"Point"}
}