{
  "type": "Feature",
  "properties": {
    "iso:country":"DE",
    "sg:address":"Gastfeldstr. 100",
    "sg:city":"Bremen",
    "sg:postcode":"28201",
    "sg:province":"Bremen",
    "wof:name":"Firat Verputz Gmbh",
    "wof:placetype":"venue"
},
  "geometry": {"coordinates":[8.7998847961,53.0626869202],"type":"Point"}
}