{
  "type": "Feature",
  "properties": {
    "iso:country":"DE",
    "sg:address":"Harenberger Meile 6",
    "sg:city":"Seelze",
    "sg:phone":"+49 5137/92906",
    "sg:postcode":"30926",
    "sg:province":"Niedersachsen",
    "wof:name":"H. H\u00f6ner",
    "wof:placetype":"venue"
},
  "geometry": {"coordinates":[9.622996,52.378387],"type":"Point"}
}