{
  "type": "Feature",
  "properties": {
    "iso:country":"DE",
    "sg:address":"Am Pionier\u00fcbungsplatz 12",
    "sg:city":"Mainz-Kastel",
    "sg:phone":"+49 6134/3193",
    "sg:postcode":"55252",
    "sg:province":"Hessen",
    "wof:name":"Josef Henke Rechtsanwalt",
    "wof:placetype":"venue"
},
  "geometry": {"coordinates":[8.2705030441,50.0202217102],"type":"Point"}
}