{
  "type": "Feature",
  "properties": {
    "iso:country":"DE",
    "sg:address":"Erftstr. 29",
    "sg:city":"Grevenbroich",
    "sg:phone":"+49 2181/28902",
    "sg:postcode":"41517",
    "sg:province":"Nordrhein-Westfalen",
    "wof:name":"E. Sch\u00f6pke",
    "wof:placetype":"venue"
},
  "geometry": {"coordinates":[6.574848175,51.0461196899],"type":"Point"}
}