{
  "type": "Feature",
  "properties": {
    "iso:country":"DE",
    "sg:address":"Schnellbachstr. 12",
    "sg:city":"L\u00fctz",
    "sg:phone":"+49 2672/2459",
    "sg:postcode":"56290",
    "sg:province":"Rheinland-Pfalz",
    "wof:name":"H. Weinem",
    "wof:placetype":"venue"
},
  "geometry": {"coordinates":[7.360183,50.1591],"type":"Point"}
}