{
  "type": "Feature",
  "properties": {
    "iso:country":"DE",
    "sg:address":"Vetschauer Weg 137",
    "sg:city":"Aachen",
    "sg:phone":"+49 241/12503",
    "sg:postcode":"52072",
    "sg:province":"Nordrhein-Westfalen",
    "wof:name":"C. Creusen",
    "wof:placetype":"venue"
},
  "geometry": {"coordinates":[6.029799,50.81617],"type":"Point"}
}