{
  "type": "Feature",
  "properties": {
    "iso:country":"DE",
    "sg:address":"Niem\u00f6llerstr. 2",
    "sg:city":"Belzig",
    "sg:phone":"+49 33841/42104",
    "sg:postcode":"14806",
    "sg:province":"Brandenburg",
    "wof:name":"Kurt Nowottnick",
    "wof:placetype":"venue"
},
  "geometry": {"coordinates":[12.585438,52.142365],"type":"Point"}
}