{
  "type": "Feature",
  "properties": {
    "iso:country":"DE",
    "sg:address":"Bahnhofstr. 2",
    "sg:city":"Ragow",
    "sg:phone":"+49 3542/2751",
    "sg:postcode":"03222",
    "sg:province":"Brandenburg",
    "wof:name":"R. Mich",
    "wof:placetype":"venue"
},
  "geometry": {"coordinates":[13.903380394,51.8886795044],"type":"Point"}
}