{
  "type": "Feature",
  "properties": {
    "iso:country":"DE",
    "sg:address":"Bellermannstr. 92",
    "sg:city":"Berlin",
    "sg:phone":"+49 30/4932539",
    "sg:postcode":"13357",
    "sg:province":"Berlin",
    "wof:name":"Karl Heinz Flemming",
    "wof:placetype":"venue"
},
  "geometry": {"coordinates":[13.385371,52.554234],"type":"Point"}
}