{
  "type": "Feature",
  "properties": {
    "iso:country":"DE",
    "sg:address":"Rupprechtstr. 7",
    "sg:city":"Berlin",
    "sg:phone":"+49 30/5296908",
    "sg:postcode":"10317",
    "sg:province":"Berlin",
    "wof:name":"Fritz Sander",
    "wof:placetype":"venue"
},
  "geometry": {"coordinates":[13.491488,52.503452],"type":"Point"}
}