{
  "type": "Feature",
  "properties": {
    "iso:country":"DE",
    "sg:address":"H\u00fclsbergstr. 99",
    "sg:city":"Bochum",
    "sg:phone":"+49 234/9791640",
    "sg:postcode":"44797",
    "sg:province":"Nordrhein-Westfalen",
    "wof:name":"Promedia Gmbh & Co. Verlag Kg",
    "wof:placetype":"venue"
},
  "geometry": {"coordinates":[7.2143740654,51.4305534363],"type":"Point"}
}