{
  "type": "Feature",
  "properties": {
    "iso:country":"DE",
    "sg:address":"Prof.-Hahn-Str. 6",
    "sg:city":"D\u00fcren",
    "sg:phone":"+49 2421/81081",
    "sg:postcode":"52353",
    "sg:province":"Nordrhein-Westfalen",
    "wof:name":"Ludwig T\u00f6ller Steuerberater",
    "wof:placetype":"venue"
},
  "geometry": {"coordinates":[6.4679541588,50.8203887939],"type":"Point"}
}