{
  "type": "Feature",
  "properties": {
    "iso:country":"DE",
    "sg:address":"Edlhardstr. 8",
    "sg:city":"G\u00fcnzburg",
    "sg:phone":"+49 8221/1040",
    "sg:postcode":"89312",
    "sg:province":"Bayern",
    "wof:name":"Helmut Fuchs",
    "wof:placetype":"venue"
},
  "geometry": {"coordinates":[10.263915062,48.4497909546],"type":"Point"}
}