{
  "type": "Feature",
  "properties": {
    "iso:country":"DE",
    "sg:address":"Neustr. 19",
    "sg:city":"Hattert",
    "sg:phone":"+49 2662/939645",
    "sg:postcode":"57644",
    "sg:province":"Rheinland-Pfalz",
    "wof:name":"Wolfram Sch\u00e4fer",
    "wof:placetype":"venue"
},
  "geometry": {"coordinates":[7.7704029083,50.6642303467],"type":"Point"}
}