{
  "type": "Feature",
  "properties": {
    "iso:country":"DE",
    "sg:address":"Huchenfelder Str. 70",
    "sg:city":"Pforzheim",
    "sg:phone":"+49 7231/74197",
    "sg:postcode":"75181",
    "sg:province":"Baden-W\u00fcrttemberg",
    "wof:name":"R. Rieber",
    "wof:placetype":"venue"
},
  "geometry": {"coordinates":[8.68294,48.873306],"type":"Point"}
}