{
  "type": "Feature",
  "properties": {
    "iso:country":"DE",
    "sg:address":"Br\u00fcckenstr 8-10",
    "sg:city":"Westerburg",
    "sg:phone":"+49 2663/1088",
    "sg:postcode":"56457",
    "sg:province":"Rheinland-Pfalz",
    "wof:name":"Sch\u00fctz Metallbau Gmbh",
    "wof:placetype":"venue"
},
  "geometry": {"coordinates":[7.963453,50.563324],"type":"Point"}
}