{
  "type": "Feature",
  "properties": {
    "iso:country":"DE",
    "sg:address":"Marienweg 19",
    "sg:city":"Heusenstamm",
    "sg:phone":"+49 6106/5931",
    "sg:postcode":"63150",
    "sg:province":"Hessen",
    "wof:name":"A. Daroub",
    "wof:placetype":"venue"
},
  "geometry": {"coordinates":[8.7966089249,50.0568008423],"type":"Point"}
}