{
  "type": "Feature",
  "properties": {
    "iso:country":"DE",
    "sg:address":"Hofmarkstr. 17",
    "sg:city":"Nittendorf",
    "sg:phone":"+49 9404/2116",
    "sg:postcode":"93152",
    "sg:province":"Bayern",
    "wof:name":"Gastst\u00e4tte Franz M\u00fcller",
    "wof:placetype":"venue"
},
  "geometry": {"coordinates":[11.9351882935,49.0268173218],"type":"Point"}
}