{
  "type": "Feature",
  "properties": {
    "iso:country":"DE",
    "sg:address":"Husumer Str. 6 a",
    "sg:city":"Tellingstedt",
    "sg:phone":"+49 4838/212",
    "sg:postcode":"25782",
    "sg:province":"Schleswig-Holstein",
    "wof:name":"Ernst-uwe Friedt Partyservice",
    "wof:placetype":"venue"
},
  "geometry": {"coordinates":[9.279917,54.220623],"type":"Point"}
}