{
  "type": "Feature",
  "properties": {
    "iso:country":"DE",
    "sg:address":"Bahnhofstr. 34",
    "sg:city":"H\u00f6henkirchen-Siegertbrn",
    "sg:phone":"+49 8102/5374",
    "sg:postcode":"85635",
    "sg:province":"Bayern",
    "wof:name":"Gerti Diester",
    "wof:placetype":"venue"
},
  "geometry": {"coordinates":[11.7250099182,48.02003479],"type":"Point"}
}