{
  "type": "Feature",
  "properties": {
    "iso:country":"DE",
    "sg:address":"Merseburger Str. 111",
    "sg:city":"Braunsbedra",
    "sg:phone":"+49 34633/32390",
    "sg:postcode":"06242",
    "sg:province":"Sachsen-Anhalt",
    "wof:name":"Erich Peuker",
    "wof:placetype":"venue"
},
  "geometry": {"coordinates":[11.896732,51.286995],"type":"Point"}
}