{
  "type": "Feature",
  "properties": {
    "iso:country":"DE",
    "sg:address":"Im Hagenbuchenacker 1",
    "sg:city":"Waldkirch",
    "sg:phone":"+49 7681/7549",
    "sg:postcode":"79183",
    "sg:province":"Baden-W\u00fcrttemberg",
    "wof:name":"Dieter Bross Architekt",
    "wof:placetype":"venue"
},
  "geometry": {"coordinates":[7.966897,48.10437],"type":"Point"}
}