{
  "type": "Feature",
  "properties": {
    "iso:country":"DE",
    "sg:address":"Talstra\u00dfe 69",
    "sg:city":"Sindelfingen",
    "sg:phone":"+49 7031",
    "sg:postcode":"71069",
    "sg:province":"Baden-W\u00fcrttemberg",
    "wof:name":"Teleconnection",
    "wof:placetype":"venue"
},
  "geometry": {"coordinates":[8.969026,48.720032],"type":"Point"}
}