{
  "type": "Feature",
  "properties": {
    "iso:country":"DE",
    "sg:address":"Waldbrunnenstr. 24",
    "sg:city":"Horb",
    "sg:phone":"+49 7486/1512",
    "sg:postcode":"72160",
    "sg:province":"Baden-W\u00fcrttemberg",
    "wof:name":"A. Kreidler",
    "wof:placetype":"venue"
},
  "geometry": {"coordinates":[8.6179523468,48.4606399536],"type":"Point"}
}