{
  "type": "Feature",
  "properties": {
    "iso:country":"DE",
    "sg:address":"Jahnweg 24",
    "sg:city":"Bad Wildbad",
    "sg:phone":"+49 7081/2014",
    "sg:postcode":"75323",
    "sg:province":"Baden-W\u00fcrttemberg",
    "wof:name":"Siegfried Bohnet Architekt",
    "wof:placetype":"venue"
},
  "geometry": {"coordinates":[8.544547,48.742233],"type":"Point"}
}