{
  "type": "Feature",
  "properties": {
    "iso:country":"DE",
    "sg:address":"Breitenstr. 27",
    "sg:city":"Bad Hersfeld",
    "sg:phone":"+49 6621/78729",
    "sg:postcode":"36251",
    "sg:province":"Hessen",
    "wof:name":"Ermano M\u00e4nnermode Inh. Peter Sturm",
    "wof:placetype":"venue"
},
  "geometry": {"coordinates":[9.7102031708,50.8675384521],"type":"Point"}
}