{
  "type": "Feature",
  "properties": {
    "iso:country":"DE",
    "sg:address":"St.-Ottilien-Str.",
    "sg:city":"Eresing",
    "sg:postcode":"86922",
    "sg:province":"Bayern",
    "wof:name":"Klosterladen Erzabtei St. Ottilien-gmbh",
    "wof:placetype":"venue"
},
  "geometry": {"coordinates":[11.0272979736,48.0905761719],"type":"Point"}
}