{
  "type": "Feature",
  "properties": {
    "iso:country":"DE",
    "sg:address":"Marlborough Road 23",
    "sg:city":"M\u00f6nchengladbach",
    "sg:phone":"+49 2161/559486",
    "sg:postcode":"41179",
    "sg:province":"Nordrhein-Westfalen",
    "wof:name":"Pizzeria Italia",
    "wof:placetype":"venue"
},
  "geometry": {"coordinates":[6.3405919075,51.1725730896],"type":"Point"}
}