{
  "type": "Feature",
  "properties": {
    "iso:country":"DE",
    "sg:address":"Gebr.-Meyer-Str. 35",
    "sg:city":"Detmold",
    "sg:postcode":"32758",
    "sg:province":"Nordrhein-Westfalen",
    "wof:name":"Wmc-service-group Gmbh",
    "wof:placetype":"venue"
},
  "geometry": {"coordinates":[8.813118,51.951134],"type":"Point"}
}