{
  "type": "Feature",
  "properties": {
    "iso:country":"DE",
    "sg:address":"Ostfeld 36",
    "sg:city":"Meschede",
    "sg:phone":"+49 2934/1475",
    "sg:postcode":"59872",
    "sg:province":"Nordrhein-Westfalen",
    "wof:name":"Hard-tech",
    "wof:placetype":"venue"
},
  "geometry": {"coordinates":[8.1374607086,51.2981872559],"type":"Point"}
}