{
  "type": "Feature",
  "properties": {
    "iso:country":"DE",
    "sg:address":"\u00d6lbergring 32 b",
    "sg:city":"Feldkirchen-Westerham",
    "sg:phone":"+49 8063/7707",
    "sg:postcode":"83620",
    "sg:province":"Bayern",
    "wof:name":"Sanipor Vertriebs Gmbh",
    "wof:placetype":"venue"
},
  "geometry": {"coordinates":[11.8500852585,47.9112319946],"type":"Point"}
}