{
  "type": "Feature",
  "properties": {
    "iso:country":"DE",
    "sg:address":"Hauptstr. 11",
    "sg:city":"Naila",
    "sg:phone":"+49 9282/3197",
    "sg:postcode":"95119",
    "sg:province":"Bayern",
    "wof:name":"Da Maurizio Pizzeria",
    "wof:placetype":"venue"
},
  "geometry": {"coordinates":[11.7074012756,50.3299674988],"type":"Point"}
}