{
  "type": "Feature",
  "properties": {
    "iso:country":"DE",
    "sg:address":"Wilfingen 9",
    "sg:city":"Dachsberg",
    "sg:phone":"+49 7755/273",
    "sg:postcode":"79875",
    "sg:province":"Baden-W\u00fcrttemberg",
    "wof:name":"Fremdenheim G. Kaiser",
    "wof:placetype":"venue"
},
  "geometry": {"coordinates":[8.1008300781,47.7284584045],"type":"Point"}
}