{
  "type": "Feature",
  "properties": {
    "iso:country":"DE",
    "sg:address":"Hauptstr. 21",
    "sg:city":"Sigmarszell",
    "sg:phone":"+49 8388/317",
    "sg:postcode":"88138",
    "sg:province":"Bayern",
    "wof:name":"Pf\u00e4nderblick Inh. Wilhelm Frey",
    "wof:placetype":"venue"
},
  "geometry": {"coordinates":[9.75184,47.590397],"type":"Point"}
}