{
  "type": "Feature",
  "properties": {
    "iso:country":"DE",
    "sg:address":"Knollstr. 104",
    "sg:city":"Osnabr\u00fcck",
    "sg:phone":"+49 541/15707",
    "sg:postcode":"49088",
    "sg:province":"Niedersachsen",
    "wof:name":"Pelikan-apotheke Andreas M. Heinze",
    "wof:placetype":"venue"
},
  "geometry": {"coordinates":[8.058339,52.290127],"type":"Point"}
}