{
  "type": "Feature",
  "properties": {
    "iso:country":"DE",
    "sg:address":"Wei\u00dfhofer Str. 73",
    "sg:city":"Bretten",
    "sg:phone":"+49 7252/78352",
    "sg:postcode":"75015",
    "sg:province":"Baden-W\u00fcrttemberg",
    "wof:name":"Pizzeria Deutsches Haus",
    "wof:placetype":"venue"
},
  "geometry": {"coordinates":[8.7149028778,49.0348243713],"type":"Point"}
}