{
  "type": "Feature",
  "properties": {
    "iso:country":"DE",
    "sg:address":"Rennekoven 18",
    "sg:city":"Nettetal",
    "sg:phone":"+49 2153/912660",
    "sg:postcode":"41334",
    "sg:province":"Nordrhein-Westfalen",
    "wof:name":"Rudolph Edv-technik",
    "wof:placetype":"venue"
},
  "geometry": {"coordinates":[6.3127508163,51.2804374695],"type":"Point"}
}