{
  "type": "Feature",
  "properties": {
    "iso:country":"DE",
    "sg:address":"B\u00e4ckerstr. 17",
    "sg:city":"T\u00fc\u00dfling",
    "sg:phone":"+49 8633/1441",
    "sg:postcode":"84577",
    "sg:province":"Bayern",
    "wof:name":"Thomas Rauch",
    "wof:placetype":"venue"
},
  "geometry": {"coordinates":[12.5896501541,48.2010154724],"type":"Point"}
}