{
  "type": "Feature",
  "properties": {
    "iso:country":"DE",
    "sg:address":"Lenbachstr. 11",
    "sg:city":"Bergholz-Rehbr\u00fccke",
    "sg:postcode":"14558",
    "sg:province":"Brandenburg",
    "wof:name":"Widynski & Roick Gmbh",
    "wof:placetype":"venue"
},
  "geometry": {"coordinates":[13.1079549789,52.3485603333],"type":"Point"}
}