{
  "type": "Feature",
  "properties": {
    "iso:country":"DE",
    "sg:address":"Vitusstr. 7",
    "sg:city":"Marsberg",
    "sg:phone":"+49 2994/595",
    "sg:postcode":"34431",
    "sg:province":"Nordrhein-Westfalen",
    "wof:name":"F.-b. Und E. Klein",
    "wof:placetype":"venue"
},
  "geometry": {"coordinates":[8.915718,51.494198],"type":"Point"}
}