{
  "type": "Feature",
  "properties": {
    "iso:country":"DE",
    "sg:address":"Lingener Str. 82",
    "sg:city":"Nordhorn",
    "sg:phone":"+49 5921/34522",
    "sg:postcode":"48531",
    "sg:province":"Niedersachsen",
    "wof:name":"Gastst\u00e4tte Barlage",
    "wof:placetype":"venue"
},
  "geometry": {"coordinates":[7.0853981972,52.4405403137],"type":"Point"}
}