{
  "type": "Feature",
  "properties": {
    "iso:country":"DE",
    "sg:address":"Kiefernstr. 10",
    "sg:city":"Germering",
    "sg:phone":"+49 89/8941490",
    "sg:postcode":"82110",
    "sg:province":"Bayern",
    "wof:name":"Service-team Rechnungswesen Gerd Sigetti Gmbh",
    "wof:placetype":"venue"
},
  "geometry": {"coordinates":[11.3590450287,48.1192893982],"type":"Point"}
}