{
  "type": "Feature",
  "properties": {
    "iso:country":"DE",
    "sg:address":"R\u00f6merstr. 4",
    "sg:city":"Weilerswist",
    "sg:phone":"+49 2254/3187",
    "sg:postcode":"53919",
    "sg:province":"Nordrhein-Westfalen",
    "wof:name":"Johann Rhiem",
    "wof:placetype":"venue"
},
  "geometry": {"coordinates":[6.888401,50.735607],"type":"Point"}
}