{
  "type": "Feature",
  "properties": {
    "iso:country":"DE",
    "sg:address":"Frankfurter Str. 10",
    "sg:city":"Guben",
    "sg:phone":"+49 3561/68840",
    "sg:postcode":"03172",
    "sg:province":"Brandenburg",
    "wof:name":"Fuhrmann Setzer Und Riedel Rechtsanw\u00e4lte",
    "wof:placetype":"venue"
},
  "geometry": {"coordinates":[14.7195444107,51.9516830444],"type":"Point"}
}