{
  "type": "Feature",
  "properties": {
    "iso:country":"DE",
    "sg:address":"Hermannstr 8",
    "sg:city":"Hamburg",
    "sg:phone":"+49 40/30383330",
    "sg:postcode":"20095",
    "sg:province":"Hamburg",
    "wof:name":"Impro Europe Gmbh",
    "wof:placetype":"venue"
},
  "geometry": {"coordinates":[9.997053,53.552456],"type":"Point"}
}