{
  "type": "Feature",
  "properties": {
    "iso:country":"DE",
    "sg:address":"M\u00fcnchner Str. 7",
    "sg:city":"Reichertshofen",
    "sg:phone":"+49 8453/330179",
    "sg:postcode":"85084",
    "sg:province":"Bayern",
    "wof:name":"Josef Keck",
    "wof:placetype":"venue"
},
  "geometry": {"coordinates":[11.4727449417,48.6570281982],"type":"Point"}
}