{
  "type": "Feature",
  "properties": {
    "iso:country":"DE",
    "sg:address":"Berliner Str. 1",
    "sg:city":"Hohenleipisch",
    "sg:phone":"+49 3533/160066",
    "sg:postcode":"04934",
    "sg:province":"Brandenburg",
    "wof:name":"Alwin Richter",
    "wof:placetype":"venue"
},
  "geometry": {"coordinates":[13.558265,51.497478],"type":"Point"}
}