{
  "type": "Feature",
  "properties": {
    "iso:country":"DE",
    "sg:address":"Bahnhofstr. 6",
    "sg:city":"Bad Lauterberg",
    "sg:postcode":"37431",
    "sg:province":"Niedersachsen",
    "wof:name":"Handy-shop Mario V\u00f6lzmann E. K.",
    "wof:placetype":"venue"
},
  "geometry": {"coordinates":[10.4645309448,51.626449585],"type":"Point"}
}