{
  "type": "Feature",
  "properties": {
    "iso:country":"DE",
    "sg:address":"Matth\u00e4us-G\u00fcnther-Str. 5 a",
    "sg:city":"Markt Indersdorf",
    "sg:phone":"+49 8136/93090",
    "sg:postcode":"85229",
    "sg:province":"Bayern",
    "wof:name":"D + P Stahlprodukte Handels Gmbh",
    "wof:placetype":"venue"
},
  "geometry": {"coordinates":[11.385538,48.359406],"type":"Point"}
}