{
  "type": "Feature",
  "properties": {
    "iso:country":"DE",
    "sg:address":"Frankfurter Str. 37",
    "sg:city":"M\u00fcllrose",
    "sg:phone":"+49 33606/332",
    "sg:postcode":"15299",
    "sg:province":"Brandenburg",
    "wof:name":"Klaus Stiller",
    "wof:placetype":"venue"
},
  "geometry": {"coordinates":[14.4180059433,52.2492332458],"type":"Point"}
}