{
  "type": "Feature",
  "properties": {
    "iso:country":"DE",
    "sg:address":"Am Kiekeberg 34",
    "sg:city":"Hamburg",
    "sg:postcode":"22587",
    "sg:province":"Hamburg",
    "wof:name":"Jwh Immobilien Gmbh",
    "wof:placetype":"venue"
},
  "geometry": {"coordinates":[9.806599617,53.5610771179],"type":"Point"}
}