{
  "type": "Feature",
  "properties": {
    "iso:country":"DE",
    "sg:address":"Brandleweg 12",
    "sg:city":"Mittenwald",
    "sg:phone":"+49 8823/8896",
    "sg:postcode":"82481",
    "sg:province":"Bayern",
    "wof:name":"Fliesen Wackerl Gmbh",
    "wof:placetype":"venue"
},
  "geometry": {"coordinates":[11.2639007568,47.4428749084],"type":"Point"}
}