{
  "type": "Feature",
  "properties": {
    "iso:country":"DE",
    "sg:address":"Arnhofen 6",
    "sg:city":"Aindling",
    "sg:phone":"+49 8237/854",
    "sg:postcode":"86447",
    "sg:province":"Bayern",
    "wof:name":"Fritz Blumh\u00f6fer",
    "wof:placetype":"venue"
},
  "geometry": {"coordinates":[10.957707,48.511147],"type":"Point"}
}