{
  "type": "Feature",
  "properties": {
    "iso:country":"DE",
    "sg:address":"Bahnhofstr 5",
    "sg:city":"Lucka",
    "sg:phone":"+49 34492/22309",
    "sg:postcode":"04613",
    "sg:province":"Th\u00fcringen",
    "wof:name":"Druckerei Reimer",
    "wof:placetype":"venue"
},
  "geometry": {"coordinates":[12.331653595,51.0975418091],"type":"Point"}
}