{
  "type": "Feature",
  "properties": {
    "iso:country":"DE",
    "sg:address":"Breite Str. 9",
    "sg:city":"Wust",
    "sg:phone":"+49 39323/61697",
    "sg:postcode":"39524",
    "sg:province":"Sachsen-Anhalt",
    "wof:name":"Bruno Gehrmann",
    "wof:placetype":"venue"
},
  "geometry": {"coordinates":[12.113751,52.546158],"type":"Point"}
}