{
  "type": "Feature",
  "properties": {
    "iso:country":"DE",
    "sg:address":"Chemnitztalstr. 60",
    "sg:city":"Chemnitz",
    "sg:postcode":"09114",
    "sg:province":"Sachsen",
    "wof:name":"Wtk Absaug- Und Filter- Technik Gmbh",
    "wof:placetype":"venue"
},
  "geometry": {"coordinates":[12.921769,50.861332],"type":"Point"}
}