{
  "type": "Feature",
  "properties": {
    "iso:country":"DE",
    "sg:address":"Iglauer Str. 3",
    "sg:city":"M\u00fcnster",
    "sg:phone":"+49 6071/31658",
    "sg:postcode":"64839",
    "sg:province":"Hessen",
    "wof:name":"Joachim Giegerich",
    "wof:placetype":"venue"
},
  "geometry": {"coordinates":[8.858736,49.917],"type":"Point"}
}