{
  "type": "Feature",
  "properties": {
    "iso:country":"DE",
    "sg:address":"Alleestr. 30",
    "sg:city":"Waldfischbach-Burgalben",
    "sg:phone":"+49 6333/955111",
    "sg:postcode":"67714",
    "sg:province":"Rheinland-Pfalz",
    "wof:name":"Herbert Bohl & S\u00f6hne Verwaltungs Gmbh",
    "wof:placetype":"venue"
},
  "geometry": {"coordinates":[7.644378,49.279922],"type":"Point"}
}