{
  "type": "Feature",
  "properties": {
    "iso:country":"DE",
    "sg:address":"Alter Postweg 3",
    "sg:city":"Petershagen",
    "sg:phone":"+49 5707/1065",
    "sg:postcode":"32469",
    "sg:province":"Nordrhein-Westfalen",
    "wof:name":"I. Strey Gmbh",
    "wof:placetype":"venue"
},
  "geometry": {"coordinates":[8.9583711624,52.399646759],"type":"Point"}
}