{
  "type": "Feature",
  "properties": {
    "iso:country":"DE",
    "sg:address":"Obotritenring 98",
    "sg:city":"Schwerin",
    "sg:phone":"+49 385/734150",
    "sg:postcode":"19053",
    "sg:province":"Mecklenburg-Vorpommern",
    "wof:name":"Paar Schneidewind Und Mevert Rechtsanw\u00e4lte",
    "wof:placetype":"venue"
},
  "geometry": {"coordinates":[11.4001598358,53.635269165],"type":"Point"}
}