{
  "type": "Feature",
  "properties": {
    "iso:country":"DE",
    "sg:address":"Wanheimer Str. 151",
    "sg:city":"Duisburg",
    "sg:phone":"+49 203/61945",
    "sg:postcode":"47053",
    "sg:province":"Nordrhein-Westfalen",
    "wof:name":"Hochfelder Hof",
    "wof:placetype":"venue"
},
  "geometry": {"coordinates":[6.7531991005,51.4148788452],"type":"Point"}
}