{
  "type": "Feature",
  "properties": {
    "iso:country":"DE",
    "sg:address":"M\u00e4ttigstr. 35",
    "sg:city":"Bautzen",
    "sg:phone":"+49 3591/501530",
    "sg:postcode":"02625",
    "sg:province":"Sachsen",
    "wof:name":"Fl\u00fcgge Und Kollegen Rechtsanw\u00e4lte",
    "wof:placetype":"venue"
},
  "geometry": {"coordinates":[14.4363012314,51.1766395569],"type":"Point"}
}