{
  "type": "Feature",
  "properties": {
    "iso:country":"DE",
    "sg:address":"Gro\u00dfb\u00fcllesheimer Str. 11",
    "sg:city":"Euskirchen",
    "sg:postcode":"53881",
    "sg:province":"Nordrhein-Westfalen",
    "wof:name":"Kath. \u00d6ffentliche Bibliothek St. Peter Und Paul",
    "wof:placetype":"venue"
},
  "geometry": {"coordinates":[6.821545,50.682129],"type":"Point"}
}