{
  "type": "Feature",
  "properties": {
    "iso:country":"DE",
    "sg:address":"Mattenbergstr. 70",
    "sg:city":"Kassel",
    "sg:phone":"+49 561/9491639",
    "sg:postcode":"34132",
    "sg:province":"Hessen",
    "wof:name":"Reinhold B\u00fclo",
    "wof:placetype":"venue"
},
  "geometry": {"coordinates":[9.4383220673,51.2741928101],"type":"Point"}
}