{
  "type": "Feature",
  "properties": {
    "iso:country":"DE",
    "sg:address":"Oesterholzstr. 27",
    "sg:city":"Dortmund",
    "sg:phone":"+49 231/8631682",
    "sg:postcode":"44145",
    "sg:province":"Nordrhein-Westfalen",
    "wof:name":"Haus Wiegand",
    "wof:placetype":"venue"
},
  "geometry": {"coordinates":[7.4813399315,51.5218887329],"type":"Point"}
}