{
  "type": "Feature",
  "properties": {
    "iso:country":"DE",
    "sg:address":"Perfstr 34",
    "sg:city":"Steffenberg",
    "sg:phone":"+49 6464/310",
    "sg:postcode":"35239",
    "sg:province":"Hessen",
    "wof:name":"Trautvetter Gmbh & Co Kg",
    "wof:placetype":"venue"
},
  "geometry": {"coordinates":[8.475256,50.817505],"type":"Point"}
}