{
  "type": "Feature",
  "properties": {
    "iso:country":"DE",
    "sg:address":"Burgwallstr. 4",
    "sg:city":"Ro\u00dflau",
    "sg:phone":"+49 34901/82339",
    "sg:postcode":"06862",
    "sg:province":"Sachsen-Anhalt",
    "wof:name":"Noble Products Germany Gmbh",
    "wof:placetype":"venue"
},
  "geometry": {"coordinates":[12.2427902222,51.8906326294],"type":"Point"}
}