{
  "type": "Feature",
  "properties": {
    "iso:country":"DE",
    "sg:address":"Wachsmuthstr. 22",
    "sg:city":"Berlin",
    "sg:phone":"+49 30/40585659",
    "sg:postcode":"13467",
    "sg:province":"Berlin",
    "wof:name":"E. Manthey Immibilienmakler",
    "wof:placetype":"venue"
},
  "geometry": {"coordinates":[13.3145446777,52.616859436],"type":"Point"}
}