{
  "type": "Feature",
  "properties": {
    "iso:country":"DE",
    "sg:address":"Unterlindau 54",
    "sg:city":"Frankfurt",
    "sg:phone":"+49 69/723167",
    "sg:postcode":"60323",
    "sg:province":"Hessen",
    "wof:name":"Burkhard Schl\u00e4ger Architekt",
    "wof:placetype":"venue"
},
  "geometry": {"coordinates":[8.667995,50.120144],"type":"Point"}
}