{
  "type": "Feature",
  "properties": {
    "iso:country":"DE",
    "sg:address":"Hahnenstr. 19",
    "sg:city":"Bremen",
    "sg:phone":"+49 421/458780",
    "sg:postcode":"28309",
    "sg:province":"Bremen",
    "wof:name":"Axel J\u00fclicher Gmbh",
    "wof:placetype":"venue"
},
  "geometry": {"coordinates":[8.887845993,53.0488777161],"type":"Point"}
}