{
  "type": "Feature",
  "properties": {
    "iso:country":"DE",
    "sg:address":"Hauptstr. 65",
    "sg:city":"Hauteroda",
    "sg:phone":"+49 34673/97179",
    "sg:postcode":"06577",
    "sg:province":"Th\u00fcringen",
    "wof:name":"Karl-heinz Scholz Ingenieur",
    "wof:placetype":"venue"
},
  "geometry": {"coordinates":[11.2797498703,51.2631912231],"type":"Point"}
}