{
  "type": "Feature",
  "properties": {
    "iso:country":"DE",
    "sg:address":"Hofbrunnstr. 9",
    "sg:city":"M\u00fcnchen",
    "sg:phone":"+49 89/796064",
    "sg:postcode":"81479",
    "sg:province":"Bayern",
    "wof:name":"Alfred Garske Architekt",
    "wof:placetype":"venue"
},
  "geometry": {"coordinates":[11.524623,48.079754],"type":"Point"}
}