{
  "type": "Feature",
  "properties": {
    "iso:country":"DE",
    "sg:address":"Hauptstr. 6",
    "sg:city":"Silberfeld",
    "sg:postcode":"07937",
    "sg:province":"Th\u00fcringen",
    "wof:name":"Pahren Agrar Vermarktungs Gmbh & Co.",
    "wof:placetype":"venue"
},
  "geometry": {"coordinates":[11.9612455368,50.6751670837],"type":"Point"}
}