{
  "type": "Feature",
  "properties": {
    "iso:country":"DE",
    "sg:address":"Sauerbreystr. 20",
    "sg:city":"Solingen",
    "sg:phone":"+49 212/14847",
    "sg:postcode":"42697",
    "sg:province":"Nordrhein-Westfalen",
    "wof:name":"Noris Datentechnik Handelsges. Mbh",
    "wof:placetype":"venue"
},
  "geometry": {"coordinates":[7.006873,51.161125],"type":"Point"}
}