{
  "type": "Feature",
  "properties": {
    "iso:country":"DE",
    "sg:address":"K\u00f6nigswiese 67",
    "sg:city":"Pocking",
    "sg:phone":"+49 8531/32768",
    "sg:postcode":"94060",
    "sg:province":"Bayern",
    "wof:name":"Alfons Karlstetter",
    "wof:placetype":"venue"
},
  "geometry": {"coordinates":[13.3484840393,48.4283599854],"type":"Point"}
}