{
  "type": "Feature",
  "properties": {
    "iso:country":"DE",
    "sg:address":"Allmendstr. 49",
    "sg:city":"Mandelbachtal",
    "sg:phone":"+49 6893/4745",
    "sg:postcode":"66399",
    "sg:province":"Saarland",
    "wof:name":"Pirrung Mensa Vitae Gmbh",
    "wof:placetype":"venue"
},
  "geometry": {"coordinates":[7.14729,49.200218],"type":"Point"}
}