{
  "type": "Feature",
  "properties": {
    "iso:country":"DE",
    "sg:address":"Herrsching",
    "sg:city":"Herrsching",
    "sg:phone":"+49 421/6600",
    "sg:postcode":"82211",
    "sg:province":"Bayern",
    "wof:name":"Volksbank Bremen-nord Eg",
    "wof:placetype":"venue"
},
  "geometry": {"coordinates":[8.6173,53.173344],"type":"Point"}
}