{
  "type": "Feature",
  "properties": {
    "iso:country":"DE",
    "sg:address":"Rudolf-Heilgers-Str. 66 a",
    "sg:city":"Worms",
    "sg:phone":"+49 6241/9785812",
    "sg:postcode":"67549",
    "sg:province":"Rheinland-Pfalz",
    "wof:name":"Ows Gmbh",
    "wof:placetype":"venue"
},
  "geometry": {"coordinates":[8.3376426697,49.6409950256],"type":"Point"}
}