{
  "type": "Feature",
  "properties": {
    "iso:country":"DE",
    "sg:address":"Unteres Schlo\u00df Wernstein",
    "sg:city":"Mainleus",
    "sg:phone":"+49 9229/974571",
    "sg:postcode":"95336",
    "sg:province":"Bayern",
    "wof:name":"Weihnachtsgeschenke",
    "wof:placetype":"venue"
},
  "geometry": {"coordinates":[11.375625,50.099903],"type":"Point"}
}