{
  "type": "Feature",
  "properties": {
    "iso:country":"DE",
    "sg:address":"Bushof 81",
    "sg:city":"Sulzbach",
    "sg:postcode":"71560",
    "sg:province":"Baden-W\u00fcrttemberg",
    "wof:name":"Weber Fleischerei Gmbh",
    "wof:placetype":"venue"
},
  "geometry": {"coordinates":[9.5354013443,49.0239830017],"type":"Point"}
}