{
  "type": "Feature",
  "properties": {
    "iso:country":"DE",
    "sg:address":"Alter Winterweg 3",
    "sg:city":"Bremen",
    "sg:phone":"+49 421/617176",
    "sg:postcode":"28237",
    "sg:province":"Bremen",
    "wof:name":"Hallenbad West",
    "wof:placetype":"venue"
},
  "geometry": {"coordinates":[8.7733230591,53.1100273132],"type":"Point"}
}