{
  "type": "Feature",
  "properties": {
    "iso:country":"DE",
    "sg:address":"Friedensstr. 9",
    "sg:city":"Wenden",
    "sg:phone":"+49 2762/979390",
    "sg:postcode":"57482",
    "sg:province":"Nordrhein-Westfalen",
    "wof:name":"Schneider Admicon Ges. F\u00fcr Strategisches",
    "wof:placetype":"venue"
},
  "geometry": {"coordinates":[7.8855171204,50.9407348633],"type":"Point"}
}