{
  "type": "Feature",
  "properties": {
    "iso:country":"DE",
    "sg:address":"Schanzenstr. 82",
    "sg:city":"D\u00fcsseldorf",
    "sg:phone":"+49 211/435320",
    "sg:postcode":"40549",
    "sg:province":"Nordrhein-Westfalen",
    "wof:name":"H. T. Import Export Gmbh",
    "wof:placetype":"venue"
},
  "geometry": {"coordinates":[6.7398648262,51.2332267761],"type":"Point"}
}