{
  "type": "Feature",
  "properties": {
    "iso:country":"DE",
    "sg:address":"Carl-Blos-Str. 17",
    "sg:city":"Offenburg",
    "sg:phone":"+49 781/30175",
    "sg:postcode":"77654",
    "sg:province":"Baden-W\u00fcrttemberg",
    "wof:name":"Georg Wei\u00dfbrodt",
    "wof:placetype":"venue"
},
  "geometry": {"coordinates":[7.9817481041,48.4740791321],"type":"Point"}
}