{
  "type": "Feature",
  "properties": {
    "iso:country":"DE",
    "sg:address":"Lyoner Str. 30",
    "sg:city":"Frankfurt",
    "sg:phone":"+49 69/63160",
    "sg:postcode":"60528",
    "sg:province":"Hessen",
    "wof:name":"Euro Lloyd Reiseb\u00fcro Gmbh",
    "wof:placetype":"venue"
},
  "geometry": {"coordinates":[8.6239614487,50.0799217224],"type":"Point"}
}