{
  "type": "Feature",
  "properties": {
    "iso:country":"DE",
    "sg:address":"Berliner Str. 907",
    "sg:city":"K\u00f6ln",
    "sg:phone":"+49 221/6002767",
    "sg:postcode":"51069",
    "sg:province":"Nordrhein-Westfalen",
    "wof:name":"Callpoint",
    "wof:placetype":"venue"
},
  "geometry": {"coordinates":[7.0382771492,50.9996910095],"type":"Point"}
}