{
  "type": "Feature",
  "properties": {
    "iso:country":"DE",
    "sg:address":"Georginenstr. 13",
    "sg:city":"M\u00fcnchen",
    "sg:postcode":"80689",
    "sg:province":"Bayern",
    "wof:name":"Blow-up Film-technik Karl Kresling Gmbh",
    "wof:placetype":"venue"
},
  "geometry": {"coordinates":[11.483653,48.127232],"type":"Point"}
}