{
  "type": "Feature",
  "properties": {
    "iso:country":"DE",
    "sg:address":"In der Grub 3",
    "sg:city":"Wirges",
    "sg:phone":"+49 2602",
    "sg:postcode":"56422",
    "sg:province":"Rheinland-Pfalz",
    "wof:name":"Jung Stahzargenmontage-feuerschutzt\u00fcren",
    "wof:placetype":"venue"
},
  "geometry": {"coordinates":[7.8054199219,50.4710006714],"type":"Point"}
}