{
  "type": "Feature",
  "properties": {
    "iso:country":"DE",
    "sg:address":"Hohenrainstr. 37",
    "sg:city":"Haiterbach",
    "sg:phone":"+49 7456/1886",
    "sg:postcode":"72221",
    "sg:province":"Baden-W\u00fcrttemberg",
    "wof:name":"Hallenbad",
    "wof:placetype":"venue"
},
  "geometry": {"coordinates":[8.6462087631,48.5244407654],"type":"Point"}
}