{
  "type": "Feature",
  "properties": {
    "iso:country":"DE",
    "sg:address":"M\u00fchlenstr. 36",
    "sg:city":"Donaueschingen",
    "sg:phone":"+49 771/2373",
    "sg:postcode":"78166",
    "sg:province":"Baden-W\u00fcrttemberg",
    "wof:name":"Alfred Goepper",
    "wof:placetype":"venue"
},
  "geometry": {"coordinates":[8.491897583,47.9547348022],"type":"Point"}
}