{
  "type": "Feature",
  "properties": {
    "iso:country":"DE",
    "sg:address":"Bahnhofstr. 18",
    "sg:city":"Eutin",
    "sg:phone":"+49 4521/71003",
    "sg:postcode":"23701",
    "sg:province":"Schleswig-Holstein",
    "wof:name":"Die Br\u00fccke Ostholstein Hilfe F\u00fcr Seelisch Kranke",
    "wof:placetype":"venue"
},
  "geometry": {"coordinates":[10.611705,54.135231],"type":"Point"}
}