{
  "type": "Feature",
  "properties": {
    "iso:country":"DE",
    "sg:address":"Ochsengasse 1",
    "sg:city":"Bad Mergentheim",
    "sg:phone":"+49 7931/562640",
    "sg:postcode":"97980",
    "sg:province":"Baden-W\u00fcrttemberg",
    "wof:name":"Dr. Karin M\u00fcller-freiberg Heilpraktikerin",
    "wof:placetype":"venue"
},
  "geometry": {"coordinates":[9.772518158,49.4901390076],"type":"Point"}
}