{
  "type": "Feature",
  "properties": {
    "iso:country":"DE",
    "sg:address":"Untere Dorfstr. 60",
    "sg:city":"Rheinfelden",
    "sg:phone":"+49 7623/8116",
    "sg:postcode":"79618",
    "sg:province":"Baden-W\u00fcrttemberg",
    "wof:name":"Peter Eberlin",
    "wof:placetype":"venue"
},
  "geometry": {"coordinates":[7.774976,47.567879],"type":"Point"}
}