{
  "type": "Feature",
  "properties": {
    "iso:country":"DE",
    "sg:address":"Holzmarktstr. 59",
    "sg:city":"Berlin",
    "sg:phone":"+49 30/2498202",
    "sg:postcode":"10179",
    "sg:province":"Berlin",
    "wof:name":"Thea Koberstein",
    "wof:placetype":"venue"
},
  "geometry": {"coordinates":[13.4217090607,52.514881134],"type":"Point"}
}