{
  "type": "Feature",
  "properties": {
    "iso:country":"DE",
    "sg:address":"Markt 10",
    "sg:city":"Coburg",
    "sg:phone":"+49 9561/99138",
    "sg:postcode":"96450",
    "sg:province":"Bayern",
    "wof:name":"Carl Martini Inh. Ingrid Muffel E. K.",
    "wof:placetype":"venue"
},
  "geometry": {"coordinates":[10.96623,50.263229],"type":"Point"}
}