{
  "type": "Feature",
  "properties": {
    "iso:country":"DE",
    "sg:address":"Tischlerstr. 3",
    "sg:city":"Sch\u00f6nebeck",
    "sg:phone":"+49 3928/400721",
    "sg:postcode":"39218",
    "sg:province":"Sachsen-Anhalt",
    "wof:name":"Pizza-haus",
    "wof:placetype":"venue"
},
  "geometry": {"coordinates":[11.7358703613,52.0203323364],"type":"Point"}
}