{
  "type": "Feature",
  "properties": {
    "iso:country":"DE",
    "sg:address":"Schlo\u00dfstr. 18",
    "sg:city":"R\u00fcdesheim am Rhein",
    "sg:phone":"+49 6722/3195",
    "sg:postcode":"65385",
    "sg:province":"Hessen",
    "wof:name":"G\u00fcnter Lauzi",
    "wof:placetype":"venue"
},
  "geometry": {"coordinates":[7.889447,49.993046],"type":"Point"}
}