{
  "type": "Feature",
  "properties": {
    "iso:country":"DE",
    "sg:address":"Flurstr. 47",
    "sg:city":"Offenbach",
    "sg:phone":"+49 69/8300660",
    "sg:postcode":"63073",
    "sg:province":"Hessen",
    "wof:name":"Evb Verm\u00f6gensberatung Gmbh",
    "wof:placetype":"venue"
},
  "geometry": {"coordinates":[8.7991285324,50.0885009766],"type":"Point"}
}