{
  "type": "Feature",
  "properties": {
    "iso:country":"DE",
    "sg:address":"Keltenring 10",
    "sg:city":"Nettersheim",
    "sg:phone":"+49 2486/282",
    "sg:postcode":"53947",
    "sg:province":"Nordrhein-Westfalen",
    "wof:name":"Richard Dietsch",
    "wof:placetype":"venue"
},
  "geometry": {"coordinates":[6.583138,50.477818],"type":"Point"}
}