{
  "type": "Feature",
  "properties": {
    "iso:country":"DE",
    "sg:address":"Wilhelmstr. 7",
    "sg:city":"W\u00f6rth",
    "sg:phone":"+49 7271/79366",
    "sg:postcode":"76744",
    "sg:province":"Rheinland-Pfalz",
    "wof:name":"Hotel Garni Anker",
    "wof:placetype":"venue"
},
  "geometry": {"coordinates":[8.0699548721,49.0640830994],"type":"Point"}
}