{
  "type": "Feature",
  "properties": {
    "iso:country":"DE",
    "sg:address":"Hainallee 64",
    "sg:city":"Dortmund",
    "sg:phone":"+49 231/526997",
    "sg:postcode":"44139",
    "sg:province":"Nordrhein-Westfalen",
    "wof:name":"Pomrenke",
    "wof:placetype":"venue"
},
  "geometry": {"coordinates":[7.4744372368,51.5015068054],"type":"Point"}
}