{
  "type": "Feature",
  "properties": {
    "iso:country":"DE",
    "sg:address":"Zum Scheider Feld 15",
    "sg:city":"Bergisch Gladbach",
    "sg:postcode":"51467",
    "sg:province":"Nordrhein-Westfalen",
    "wof:name":"Event-services-gesellschaft F\u00fcr Veranstaltungs-",
    "wof:placetype":"venue"
},
  "geometry": {"coordinates":[7.089511,51.021442],"type":"Point"}
}