{
  "type": "Feature",
  "properties": {
    "iso:country":"DE",
    "sg:address":"Kuller Str. 35",
    "sg:city":"Solingen",
    "sg:phone":"+49 212/57195",
    "sg:postcode":"42651",
    "sg:province":"Nordrhein-Westfalen",
    "wof:name":"Karibu Reisen E. K.",
    "wof:placetype":"venue"
},
  "geometry": {"coordinates":[7.0835108757,51.1820869446],"type":"Point"}
}