{
  "type": "Feature",
  "properties": {
    "iso:country":"DE",
    "sg:address":"Rudolf-Diesel-Ring 28",
    "sg:city":"Sauerlach",
    "sg:phone":"+49 8104/66400",
    "sg:postcode":"82054",
    "sg:province":"Bayern",
    "wof:name":"Pro-pack Dichtungen Und Packungen Gmbh",
    "wof:placetype":"venue"
},
  "geometry": {"coordinates":[11.662834,47.968422],"type":"Point"}
}