{
  "type": "Feature",
  "properties": {
    "iso:country":"DE",
    "sg:address":"Bad Driburger Str. 10",
    "sg:city":"Uebigau",
    "sg:postcode":"04938",
    "sg:province":"Brandenburg",
    "wof:name":"A. Hackel",
    "wof:placetype":"venue"
},
  "geometry": {"coordinates":[13.290821,51.593609],"type":"Point"}
}