{
  "type": "Feature",
  "properties": {
    "iso:country":"DE",
    "sg:address":"Wolfenb\u00fcttler Stra\u00dfe 1A",
    "sg:city":"Hannover",
    "sg:phone":"+49 511/8443535",
    "sg:postcode":"30459",
    "sg:province":"Niedersachsen",
    "wof:name":"Abhandlung Internetrecht, Rechtsanwalt M\u00f6bius, Hannover",
    "wof:placetype":"venue"
},
  "geometry": {"coordinates":[9.710075,52.341953],"type":"Point"}
}