{
  "type": "Feature",
  "properties": {
    "iso:country":"DE",
    "sg:address":"Max-Braun-Str. 4",
    "sg:city":"Marktheidenfeld",
    "sg:phone":"+49 9391/5040",
    "sg:postcode":"97828",
    "sg:province":"Bayern",
    "wof:name":"Ges. F\u00fcr Betriebssicherheit Altfeld Gmbh",
    "wof:placetype":"venue"
},
  "geometry": {"coordinates":[9.542582,49.827168],"type":"Point"}
}