{
  "type": "Feature",
  "properties": {
    "iso:country":"DE",
    "sg:address":"An der Kuhle 1",
    "sg:city":"Reichshof",
    "sg:phone":"+49 2265/594",
    "sg:postcode":"51580",
    "sg:province":"Nordrhein-Westfalen",
    "wof:name":"Josef Kentenich",
    "wof:placetype":"venue"
},
  "geometry": {"coordinates":[7.6529397964,50.9844512939],"type":"Point"}
}