{
  "type": "Feature",
  "properties": {
    "iso:country":"DE",
    "sg:address":"Friedrich-Ebert-Platz 5",
    "sg:city":"Lahr",
    "sg:phone":"+49 7821/989710",
    "sg:postcode":"77933",
    "sg:province":"Baden-W\u00fcrttemberg",
    "wof:name":"Hans-j\u00fcrgen Ziegler Rechtsanwalt",
    "wof:placetype":"venue"
},
  "geometry": {"coordinates":[7.8652501106,48.3380317688],"type":"Point"}
}