{
  "type": "Feature",
  "properties": {
    "iso:country":"DE",
    "sg:address":"Groppeler Str. 52",
    "sg:city":"Herzebrock-Clarholz",
    "sg:phone":"+49 5245/180000",
    "sg:postcode":"33442",
    "sg:province":"Nordrhein-Westfalen",
    "wof:name":"Cordes-reisen",
    "wof:placetype":"venue"
},
  "geometry": {"coordinates":[8.2690696716,51.9088973999],"type":"Point"}
}