{
  "type": "Feature",
  "properties": {
    "iso:country":"DE",
    "sg:address":"Neuer Wall 11",
    "sg:city":"Hamburg",
    "sg:phone":"+49 40/341414",
    "sg:postcode":"20354",
    "sg:province":"Hamburg",
    "wof:name":"Ladage & Oelke Bekleidungs-u. Schuh-einzelhandels Gmbh",
    "wof:placetype":"venue"
},
  "geometry": {"coordinates":[9.992438,53.552288],"type":"Point"}
}