{
  "type": "Feature",
  "properties": {
    "iso:country":"DE",
    "sg:address":"Albert-Schweitzer-Str. 9",
    "sg:city":"Mudau",
    "sg:phone":"+49 6284/419",
    "sg:postcode":"69427",
    "sg:province":"Baden-W\u00fcrttemberg",
    "wof:name":"G. Wasner",
    "wof:placetype":"venue"
},
  "geometry": {"coordinates":[9.2009897232,49.5307617188],"type":"Point"}
}