{
  "type": "Feature",
  "properties": {
    "iso:country":"DE",
    "sg:address":"Wilhelmshavener Str. 52",
    "sg:city":"N\u00fcrnberg",
    "sg:phone":"+49 911/383184",
    "sg:postcode":"90425",
    "sg:province":"Bayern",
    "wof:name":"Horst Meyer Bauplanungs Gmbh",
    "wof:placetype":"venue"
},
  "geometry": {"coordinates":[11.0685338974,49.4804000854],"type":"Point"}
}