{
  "type": "Feature",
  "properties": {
    "iso:country":"DE",
    "sg:address":"Stra\u00dfe der Nationen 22",
    "sg:city":"Oranienburg",
    "sg:phone":"+49 3301/2000",
    "sg:postcode":"16515",
    "sg:province":"Brandenburg",
    "wof:name":"Gedenkst\u00e4tte Und Museum Sachsenhausen",
    "wof:placetype":"venue"
},
  "geometry": {"coordinates":[13.261218,52.763565],"type":"Point"}
}