{
  "type": "Feature",
  "properties": {
    "iso:country":"DE",
    "sg:address":"Niedernberger Str.",
    "sg:city":"Gro\u00dfwallstadt",
    "sg:phone":"+49 9372/5488",
    "sg:postcode":"63868",
    "sg:province":"Bayern",
    "wof:name":"Alfons Orgeldinger",
    "wof:placetype":"venue"
},
  "geometry": {"coordinates":[9.1528663635,49.8852539062],"type":"Point"}
}