{
  "type": "Feature",
  "properties": {
    "iso:country":"DE",
    "sg:address":"Beethovenstr. 11",
    "sg:city":"Cappeln",
    "sg:phone":"+49 4478/1402",
    "sg:postcode":"49692",
    "sg:province":"Niedersachsen",
    "wof:name":"Karl-heinz Kleinfeld Kunststopferei",
    "wof:placetype":"venue"
},
  "geometry": {"coordinates":[8.1197385788,52.8077812195],"type":"Point"}
}