{
  "type": "Feature",
  "properties": {
    "iso:country":"DE",
    "sg:address":"Lindenstr. 2",
    "sg:city":"Altheim",
    "sg:phone":"+49 7391/53570",
    "sg:postcode":"89605",
    "sg:province":"Baden-W\u00fcrttemberg",
    "wof:name":"Fuchs Fenster Gmbh",
    "wof:placetype":"venue"
},
  "geometry": {"coordinates":[9.77272,48.327599],"type":"Point"}
}