{
  "type": "Feature",
  "properties": {
    "iso:country":"DE",
    "sg:address":"Eichenweg 2",
    "sg:city":"Lichtenfels",
    "sg:phone":"+49 9571/95810",
    "sg:postcode":"96215",
    "sg:province":"Bayern",
    "wof:name":"Adam Schmidt Kg",
    "wof:placetype":"venue"
},
  "geometry": {"coordinates":[11.0876064301,50.1494255066],"type":"Point"}
}