{
  "type": "Feature",
  "properties": {
    "iso:country":"DE",
    "sg:address":"M\u00fcnsterstr. 14",
    "sg:city":"D\u00fclmen",
    "sg:phone":"+49 2594/791557",
    "sg:postcode":"48249",
    "sg:province":"Nordrhein-Westfalen",
    "wof:name":"D2-shop D\u00fclmen R. Dombrowsky Gmbh",
    "wof:placetype":"venue"
},
  "geometry": {"coordinates":[7.2792057991,51.8295211792],"type":"Point"}
}