{
  "type": "Feature",
  "properties": {
    "iso:country":"DE",
    "sg:address":"Mahlsdorfer Str. 109",
    "sg:city":"Berlin",
    "sg:phone":"+49 30/6571320",
    "sg:postcode":"12555",
    "sg:province":"Berlin",
    "wof:name":"Lbs Ostdeutsche Landesbausparkasse Ag",
    "wof:placetype":"venue"
},
  "geometry": {"coordinates":[13.579927,52.459534],"type":"Point"}
}