{
  "type": "Feature",
  "properties": {
    "iso:country":"DE",
    "sg:address":"Hauptstr. 21",
    "sg:city":"Sehestedt",
    "sg:phone":"+49 4357/1021",
    "sg:postcode":"24814",
    "sg:province":"Schleswig-Holstein",
    "wof:name":"Baugesch\u00e4ft Sell Gmbh",
    "wof:placetype":"venue"
},
  "geometry": {"coordinates":[9.818155,54.366035],"type":"Point"}
}