{
  "type": "Feature",
  "properties": {
    "iso:country":"DE",
    "sg:address":"K\u00f6lner Str. 262",
    "sg:city":"K\u00fcrten-Neuensaal",
    "sg:phone":"+49 2207",
    "sg:postcode":"51515",
    "sg:province":"Nordrhein-Westfalen",
    "wof:name":"Accurate Systemwerbung",
    "wof:placetype":"venue"
},
  "geometry": {"coordinates":[7.263581,51.053551],"type":"Point"}
}