{
  "type": "Feature",
  "properties": {
    "iso:country":"DE",
    "sg:address":"Innerkoflerstr. 14",
    "sg:city":"M\u00fcnchen",
    "sg:phone":"+49 89/7148205",
    "sg:postcode":"81377",
    "sg:province":"Bayern",
    "wof:name":"Josef T\u00e4nzer Architekt",
    "wof:placetype":"venue"
},
  "geometry": {"coordinates":[11.509655,48.110287],"type":"Point"}
}