{
  "type": "Feature",
  "properties": {
    "iso:country":"DE",
    "sg:address":"Am Wasserwerk 6",
    "sg:city":"Plettenberg",
    "sg:phone":"+49 2391/956260",
    "sg:postcode":"58840",
    "sg:province":"Nordrhein-Westfalen",
    "wof:name":"Arnold & Rath Gmbh",
    "wof:placetype":"venue"
},
  "geometry": {"coordinates":[7.900203,51.222366],"type":"Point"}
}