{
  "type": "Feature",
  "properties": {
    "iso:country":"DE",
    "sg:address":"Pirnaer Str. 60",
    "sg:city":"Heidenau",
    "sg:phone":"+49 3529/512256",
    "sg:postcode":"01809",
    "sg:province":"Sachsen",
    "wof:name":"Pohl & Co. Gmbh",
    "wof:placetype":"venue"
},
  "geometry": {"coordinates":[13.8792676926,50.9702720642],"type":"Point"}
}