{
  "type": "Feature",
  "properties": {
    "iso:country":"DE",
    "sg:address":"Am Friedhof",
    "sg:city":"Moringen",
    "sg:phone":"+49 5554/2246",
    "sg:postcode":"37186",
    "sg:province":"Niedersachsen",
    "wof:name":"Ludwig Honig",
    "wof:placetype":"venue"
},
  "geometry": {"coordinates":[9.871285,51.701244],"type":"Point"}
}