{
  "type": "Feature",
  "properties": {
    "iso:country":"DE",
    "sg:address":"Helenenstr. 61",
    "sg:city":"Limbach-Oberfrohna",
    "sg:phone":"+49 3722/93629",
    "sg:postcode":"09212",
    "sg:province":"Sachsen",
    "wof:name":"Albin Georg Funke",
    "wof:placetype":"venue"
},
  "geometry": {"coordinates":[12.754068,50.858154],"type":"Point"}
}