{
  "type": "Feature",
  "properties": {
    "iso:country":"DE",
    "sg:address":"Danziger Str. 9",
    "sg:city":"V\u00f6lklingen",
    "sg:phone":"+49 6898/280777",
    "sg:postcode":"66333",
    "sg:province":"Saarland",
    "wof:name":"Ibb Gesellschaft F\u00fcr Innovative Bauplanung Und",
    "wof:placetype":"venue"
},
  "geometry": {"coordinates":[6.8588137627,49.2528038025],"type":"Point"}
}