{
  "type": "Feature",
  "properties": {
    "iso:country":"DE",
    "sg:address":"Plankgasse 42",
    "sg:city":"K\u00f6ln",
    "sg:phone":"+49 221/133023",
    "sg:postcode":"50668",
    "sg:province":"Nordrhein-Westfalen",
    "wof:name":"E. Kahle Gmbh",
    "wof:placetype":"venue"
},
  "geometry": {"coordinates":[6.95332,50.94735],"type":"Point"}
}