{
  "type": "Feature",
  "properties": {
    "iso:country":"DE",
    "sg:address":"Hangweg 1",
    "sg:city":"Lindenfels",
    "sg:phone":"+49 6255/737",
    "sg:postcode":"64678",
    "sg:province":"Hessen",
    "wof:name":"G. Schnellb\u00e4cher",
    "wof:placetype":"venue"
},
  "geometry": {"coordinates":[8.7827167511,49.6814804077],"type":"Point"}
}