{
  "type": "Feature",
  "properties": {
    "iso:country":"DE",
    "sg:address":"Kamener Str. 14",
    "sg:city":"Unna",
    "sg:phone":"+49 2303/69628",
    "sg:postcode":"59425",
    "sg:province":"Nordrhein-Westfalen",
    "wof:name":"Ganas",
    "wof:placetype":"venue"
},
  "geometry": {"coordinates":[7.6843781471,51.5547180176],"type":"Point"}
}