{
  "type": "Feature",
  "properties": {
    "iso:country":"DE",
    "sg:address":"Am Naturschutzpark 16",
    "sg:city":"Hanstedt",
    "sg:phone":"+49 4184/349",
    "sg:postcode":"21271",
    "sg:province":"Niedersachsen",
    "wof:name":"August Witte",
    "wof:placetype":"venue"
},
  "geometry": {"coordinates":[10.013872,53.216885],"type":"Point"}
}