{
  "type": "Feature",
  "properties": {
    "iso:country":"DE",
    "sg:address":"Hauptstr. 118",
    "sg:city":"Miltenberg",
    "sg:phone":"+49 9371/2390",
    "sg:postcode":"63897",
    "sg:province":"Bayern",
    "wof:name":"Rigobert Rufflar",
    "wof:placetype":"venue"
},
  "geometry": {"coordinates":[9.2545137405,49.6998329163],"type":"Point"}
}