{
  "type": "Feature",
  "properties": {
    "iso:country":"DE",
    "sg:address":"Suitbertusstr. 87",
    "sg:city":"D\u00fcsseldorf",
    "sg:phone":"+49 211/572355",
    "sg:postcode":"40223",
    "sg:province":"Nordrhein-Westfalen",
    "wof:name":"Fechner",
    "wof:placetype":"venue"
},
  "geometry": {"coordinates":[6.771298,51.204487],"type":"Point"}
}