{
  "type": "Feature",
  "properties": {
    "iso:country":"DE",
    "sg:address":"Weststr. 104",
    "sg:city":"Wuppertal",
    "sg:phone":"+49 202/422540",
    "sg:postcode":"42119",
    "sg:province":"Nordrhein-Westfalen",
    "wof:name":"Uwe Faulenbach Steuerberater",
    "wof:placetype":"venue"
},
  "geometry": {"coordinates":[7.1442131996,51.2505264282],"type":"Point"}
}