{
  "type": "Feature",
  "properties": {
    "iso:country":"DE",
    "sg:address":"Friedrich-Ebert-Str. 15",
    "sg:city":"Nordenham",
    "sg:phone":"+49 4731/22049",
    "sg:postcode":"26954",
    "sg:province":"Niedersachsen",
    "wof:name":"Stadt-apotheke Schulze E. K.",
    "wof:placetype":"venue"
},
  "geometry": {"coordinates":[8.484382,53.485607],"type":"Point"}
}