{
  "type": "Feature",
  "properties": {
    "iso:country":"DE",
    "sg:address":"Hintere Gemeindegasse 216",
    "sg:city":"J\u00f6hstadt",
    "sg:phone":"+49 37343/2360",
    "sg:postcode":"09477",
    "sg:province":"Sachsen",
    "wof:name":"Emil Heyn & S\u00f6hne",
    "wof:placetype":"venue"
},
  "geometry": {"coordinates":[13.088399,50.513676],"type":"Point"}
}