{
  "type": "Feature",
  "properties": {
    "iso:country":"DE",
    "sg:address":"Kapit\u00e4n-Dallmann-Str. 14",
    "sg:city":"Bremen",
    "sg:phone":"+49 421/606416",
    "sg:postcode":"28779",
    "sg:province":"Bremen",
    "wof:name":"Egon Vahlsing Rechtsanwalt",
    "wof:placetype":"venue"
},
  "geometry": {"coordinates":[8.571015358,53.1822624207],"type":"Point"}
}