{
  "type": "Feature",
  "properties": {
    "iso:country":"DE",
    "sg:address":"Graub\u00fcndener Str. 57",
    "sg:city":"Bremen",
    "sg:postcode":"28325",
    "sg:province":"Bremen",
    "wof:name":"Hobby Und Modelbau Claudia Bertram",
    "wof:placetype":"venue"
},
  "geometry": {"coordinates":[8.9478273392,53.069858551],"type":"Point"}
}