{
  "type": "Feature",
  "properties": {
    "iso:country":"DE",
    "sg:address":"Kasseler Str 37-39",
    "sg:city":"Zierenberg",
    "sg:phone":"+49 5606/51820",
    "sg:postcode":"34289",
    "sg:province":"Hessen",
    "wof:name":"Brandschutztechnik M\u00fcller Gmbh",
    "wof:placetype":"venue"
},
  "geometry": {"coordinates":[9.307829,51.367592],"type":"Point"}
}