{
  "type": "Feature",
  "properties": {
    "iso:country":"DE",
    "sg:address":"Freihofplatz 4",
    "sg:city":"Seligenstadt",
    "sg:phone":"+49 6182/26096",
    "sg:postcode":"63500",
    "sg:province":"Hessen",
    "wof:name":"Hotel-restaurant Zur Krone",
    "wof:placetype":"venue"
},
  "geometry": {"coordinates":[8.9767189026,50.0428543091],"type":"Point"}
}