{
  "type": "Feature",
  "properties": {
    "iso:country":"DE",
    "sg:address":"R\u00f6derfeld 10",
    "sg:city":"Suhl",
    "sg:phone":"+49 3681/302116",
    "sg:postcode":"98527",
    "sg:province":"Th\u00fcringen",
    "wof:name":"M. Keiner",
    "wof:placetype":"venue"
},
  "geometry": {"coordinates":[10.698195,50.611271],"type":"Point"}
}