{
  "type": "Feature",
  "properties": {
    "iso:country":"DE",
    "sg:address":"Trappenfelder Str. 10",
    "sg:city":"Mehrow",
    "sg:phone":"+49 33394/59866",
    "sg:postcode":"16356",
    "sg:province":"Brandenburg",
    "wof:name":"Buff Filmproduktion Gmbh",
    "wof:placetype":"venue"
},
  "geometry": {"coordinates":[13.5797243118,52.5762367249],"type":"Point"}
}