{
  "type": "Feature",
  "properties": {
    "iso:country":"DE",
    "sg:address":"Holtenauer Str. 338",
    "sg:city":"Kiel",
    "sg:phone":"+49 431/337382",
    "sg:postcode":"24106",
    "sg:province":"Schleswig-Holstein",
    "wof:name":"D\u00f6ner Star",
    "wof:placetype":"venue"
},
  "geometry": {"coordinates":[10.1308050156,54.356338501],"type":"Point"}
}