{
  "type": "Feature",
  "properties": {
    "iso:country":"DE",
    "sg:address":"Geisfelder Str. 6",
    "sg:city":"Strullendorf",
    "sg:phone":"+49 9505/7014",
    "sg:postcode":"96129",
    "sg:province":"Bayern",
    "wof:name":"H. Limmer",
    "wof:placetype":"venue"
},
  "geometry": {"coordinates":[10.998768,49.867199],"type":"Point"}
}