{
  "type": "Feature",
  "properties": {
    "iso:country":"DE",
    "sg:address":"K\u00f6nigstr. 1",
    "sg:city":"Elmshorn",
    "sg:phone":"+49 4121/23300",
    "sg:postcode":"25335",
    "sg:province":"Schleswig-Holstein",
    "wof:name":"Savoy-verzehrkino",
    "wof:placetype":"venue"
},
  "geometry": {"coordinates":[9.6582946777,53.7544021606],"type":"Point"}
}