{
  "type": "Feature",
  "properties": {
    "iso:country":"DE",
    "sg:address":"Scharnhorststr. 25",
    "sg:city":"L\u00fctzen",
    "sg:phone":"+49 34444/20430",
    "sg:postcode":"06686",
    "sg:province":"Sachsen-Anhalt",
    "wof:name":"Kulturhaus Gro\u00dfg\u00f6rschen",
    "wof:placetype":"venue"
},
  "geometry": {"coordinates":[12.1517181396,51.2569999695],"type":"Point"}
}