{
  "type": "Feature",
  "properties": {
    "iso:country":"DE",
    "sg:address":"Hauptstr. 180",
    "sg:city":"Bendorf",
    "sg:phone":"+49 2622/3031",
    "sg:postcode":"56170",
    "sg:province":"Rheinland-Pfalz",
    "wof:name":"Ulrich Gro\u00dfkopf Gotthard Monreal Und Partner",
    "wof:placetype":"venue"
},
  "geometry": {"coordinates":[7.5714149475,50.4276008606],"type":"Point"}
}