{
  "type": "Feature",
  "properties": {
    "iso:country":"DE",
    "sg:address":"Stra\u00dfe der Jugend 17",
    "sg:city":"Sassnitz",
    "sg:phone":"+49 38392/32091",
    "sg:postcode":"18546",
    "sg:province":"Mecklenburg-Vorpommern",
    "wof:name":"E. Drzymotta",
    "wof:placetype":"venue"
},
  "geometry": {"coordinates":[13.6273889542,54.510307312],"type":"Point"}
}