{
  "type": "Feature",
  "properties": {
    "iso:country":"DE",
    "sg:address":"Schwabstr. 48",
    "sg:city":"B\u00f6blingen",
    "sg:phone":"+49 7031/226687",
    "sg:postcode":"71032",
    "sg:province":"Baden-W\u00fcrttemberg",
    "wof:name":"Martin-luther-gemeinde",
    "wof:placetype":"venue"
},
  "geometry": {"coordinates":[9.0249967575,48.6853523254],"type":"Point"}
}