{
  "type": "Feature",
  "properties": {
    "iso:country":"DE",
    "sg:address":"Werksstr 18",
    "sg:city":"Hattingen",
    "sg:phone":"+49 2324/59850",
    "sg:postcode":"45527",
    "sg:province":"Nordrhein-Westfalen",
    "wof:name":"Martin Gmbh",
    "wof:placetype":"venue"
},
  "geometry": {"coordinates":[7.196377,51.406582],"type":"Point"}
}