{
  "type": "Feature",
  "properties": {
    "iso:country":"DE",
    "sg:address":"Am Oberen St\u00f6tchen 24",
    "sg:city":"Olpe",
    "sg:phone":"+49 2761/63071",
    "sg:postcode":"57462",
    "sg:province":"Nordrhein-Westfalen",
    "wof:name":"Rolf Middeke",
    "wof:placetype":"venue"
},
  "geometry": {"coordinates":[7.8459582329,51.0238494873],"type":"Point"}
}