{
  "type": "Feature",
  "properties": {
    "iso:country":"DE",
    "sg:address":"K\u00f6nigsberger Str. 20",
    "sg:city":"Saarbr\u00fccken",
    "sg:phone":"+49 681/814696",
    "sg:postcode":"66121",
    "sg:province":"Saarland",
    "wof:name":"Kurt Zimmer Architekt",
    "wof:placetype":"venue"
},
  "geometry": {"coordinates":[7.047691,49.234798],"type":"Point"}
}