{
  "type": "Feature",
  "properties": {
    "iso:country":"DE",
    "sg:address":"Kleine B\u00e4ckerstr. 9",
    "sg:city":"L\u00fcneburg",
    "sg:phone":"+49 4131/77910",
    "sg:postcode":"21335",
    "sg:province":"Niedersachsen",
    "wof:name":"D 2 - Shop",
    "wof:placetype":"venue"
},
  "geometry": {"coordinates":[10.409070015,53.2474784851],"type":"Point"}
}