{
  "type": "Feature",
  "properties": {
    "iso:country":"DE",
    "sg:address":"Buschungstr. 10",
    "sg:city":"Wiesbaden",
    "sg:postcode":"65205",
    "sg:province":"Hessen",
    "wof:name":"C\u00e4sar-transporte E. Kfm. Inh. Cezary Matuszkiewicz",
    "wof:placetype":"venue"
},
  "geometry": {"coordinates":[8.303342,50.055943],"type":"Point"}
}