{
  "type": "Feature",
  "properties": {
    "iso:country":"DE",
    "sg:address":"Am Harras 11",
    "sg:city":"M\u00fcnchen",
    "sg:phone":"+49 89/766417",
    "sg:postcode":"81373",
    "sg:province":"Bayern",
    "wof:name":"Eiscafe Aldo Zaia",
    "wof:placetype":"venue"
},
  "geometry": {"coordinates":[11.538913,48.117027],"type":"Point"}
}