{
  "type": "Feature",
  "properties": {
    "iso:country":"DE",
    "sg:address":"Barbarastr. 68",
    "sg:city":"Bleicherode",
    "sg:postcode":"99752",
    "sg:province":"Th\u00fcringen",
    "wof:name":"Landsiedel M\u00fcller Flagmeyer Gmbh",
    "wof:placetype":"venue"
},
  "geometry": {"coordinates":[10.5653114319,51.4430732727],"type":"Point"}
}