{
  "type": "Feature",
  "properties": {
    "iso:country":"DE",
    "sg:address":"Hauptstr. 42",
    "sg:city":"Hirschfeld",
    "sg:phone":"+49 35242/68744",
    "sg:postcode":"09634",
    "sg:province":"Sachsen",
    "wof:name":"Tischlerei Deger Gmbh",
    "wof:placetype":"venue"
},
  "geometry": {"coordinates":[13.34955,51.037441],"type":"Point"}
}