{
  "type": "Feature",
  "properties": {
    "iso:country":"DE",
    "sg:address":"Melchiorstr. 20",
    "sg:city":"M\u00fcnchen",
    "sg:phone":"+49 89/72709000",
    "sg:postcode":"81479",
    "sg:province":"Bayern",
    "wof:name":"Site Force Ag",
    "wof:placetype":"venue"
},
  "geometry": {"coordinates":[11.5206441879,48.0723953247],"type":"Point"}
}