{
  "type": "Feature",
  "properties": {
    "iso:country":"DE",
    "sg:address":"Talstr. 34",
    "sg:city":"Karlsruhe",
    "sg:postcode":"76228",
    "sg:province":"Baden-W\u00fcrttemberg",
    "wof:name":"Michael Fessler",
    "wof:placetype":"venue"
},
  "geometry": {"coordinates":[8.4834280014,48.9462242126],"type":"Point"}
}