{
  "type": "Feature",
  "properties": {
    "iso:country":"DE",
    "sg:address":"L\u00f6\u00dfnitzer Str.1",
    "sg:city":"Aue",
    "sg:phone":"+49 3771/598435",
    "sg:postcode":"08280",
    "sg:province":"Sachsen",
    "wof:name":"Interneportal F\u00fcrs Erzgebirge",
    "wof:placetype":"venue"
},
  "geometry": {"coordinates":[12.70078,50.594959],"type":"Point"}
}