{
  "type": "Feature",
  "properties": {
    "iso:country":"DE",
    "sg:address":"An den drei Kreuzen 7",
    "sg:city":"H\u00f6chstadt",
    "sg:postcode":"91315",
    "sg:province":"Bayern",
    "wof:name":"Lm Metalltechnik Gmbh",
    "wof:placetype":"venue"
},
  "geometry": {"coordinates":[10.8272457123,49.7023124695],"type":"Point"}
}