{
  "type": "Feature",
  "properties": {
    "iso:country":"DE",
    "sg:address":"Breitscheidstr. 57",
    "sg:city":"Dresden",
    "sg:phone":"+49 351/2024612",
    "sg:postcode":"01237",
    "sg:province":"Sachsen",
    "wof:name":"Wolfgang Nippgen",
    "wof:placetype":"venue"
},
  "geometry": {"coordinates":[13.8118896484,51.0125350952],"type":"Point"}
}