{
  "type": "Feature",
  "properties": {
    "iso:country":"DE",
    "sg:address":"Eichenweg 10",
    "sg:city":"Eppstein",
    "sg:phone":"+49 6198/8791",
    "sg:postcode":"65817",
    "sg:province":"Hessen",
    "wof:name":"Kurt M\u00fcller Gmbh",
    "wof:placetype":"venue"
},
  "geometry": {"coordinates":[8.3810663223,50.1491012573],"type":"Point"}
}