{
  "type": "Feature",
  "properties": {
    "iso:country":"DE",
    "sg:address":"Mainzer Str. 3",
    "sg:city":"Pirmasens",
    "sg:phone":"+49 6331/41431",
    "sg:postcode":"66953",
    "sg:province":"Rheinland-Pfalz",
    "wof:name":"Michael Diehl",
    "wof:placetype":"venue"
},
  "geometry": {"coordinates":[7.613005,49.197948],"type":"Point"}
}