{
  "type": "Feature",
  "properties": {
    "iso:country":"DE",
    "sg:address":"Volckamerstr 69",
    "sg:city":"Schwabach",
    "sg:phone":"+49 911/6327821",
    "sg:postcode":"91126",
    "sg:province":"Bayern",
    "wof:name":"Lagoudakis Gmbh",
    "wof:placetype":"venue"
},
  "geometry": {"coordinates":[11.0343446732,49.3605041504],"type":"Point"}
}