{
  "type": "Feature",
  "properties": {
    "iso:country":"DE",
    "sg:address":"Lippestr. 4",
    "sg:city":"Castrop-Rauxel",
    "sg:phone":"+49 2305/73917",
    "sg:postcode":"44579",
    "sg:province":"Nordrhein-Westfalen",
    "wof:name":"H. Wermers",
    "wof:placetype":"venue"
},
  "geometry": {"coordinates":[7.3024759293,51.5912055969],"type":"Point"}
}