{
  "type": "Feature",
  "properties": {
    "iso:country":"DE",
    "sg:address":"Wildemannstr. 13",
    "sg:city":"Seesen",
    "sg:phone":"+49 5381/8257",
    "sg:postcode":"38723",
    "sg:province":"Niedersachsen",
    "wof:name":"Zur Post",
    "wof:placetype":"venue"
},
  "geometry": {"coordinates":[10.1876840591,51.8480377197],"type":"Point"}
}