{
  "type": "Feature",
  "properties": {
    "iso:country":"DE",
    "sg:address":"Desmastr. 3-5",
    "sg:city":"Achim",
    "sg:postcode":"28832",
    "sg:province":"Niedersachsen",
    "wof:name":"Kkw Karl Oberdieck E. K.",
    "wof:placetype":"venue"
},
  "geometry": {"coordinates":[9.055645,53.009262],"type":"Point"}
}