{
  "type": "Feature",
  "properties": {
    "iso:country":"DE",
    "sg:address":"Im Fischerfeld 28",
    "sg:city":"Gengenbach",
    "sg:phone":"+49 7803/980863",
    "sg:postcode":"77723",
    "sg:province":"Baden-W\u00fcrttemberg",
    "wof:name":"Klaus Schwab",
    "wof:placetype":"venue"
},
  "geometry": {"coordinates":[8.0195350647,48.3994026184],"type":"Point"}
}