{
  "type": "Feature",
  "properties": {
    "iso:country":"DE",
    "sg:address":"Rengersh\u00e4user Str. 10",
    "sg:city":"Einbeck",
    "sg:phone":"+49 5565/843",
    "sg:postcode":"37574",
    "sg:province":"Niedersachsen",
    "wof:name":"Martin Meyer",
    "wof:placetype":"venue"
},
  "geometry": {"coordinates":[9.7796821594,51.859046936],"type":"Point"}
}