{
  "type": "Feature",
  "properties": {
    "iso:country":"DE",
    "sg:address":"Teichstr. 3",
    "sg:city":"Neutraubling",
    "sg:phone":"+49 9401/1527",
    "sg:postcode":"93073",
    "sg:province":"Bayern",
    "wof:name":"Erich Knobloch Kg",
    "wof:placetype":"venue"
},
  "geometry": {"coordinates":[12.1928510666,48.9900360107],"type":"Point"}
}