{
  "type": "Feature",
  "properties": {
    "iso:country":"DE",
    "sg:address":"Loisachauenstr. 38",
    "sg:city":"Oberau",
    "sg:phone":"+49 8824/8070",
    "sg:postcode":"82496",
    "sg:province":"Bayern",
    "wof:name":"Fuchs",
    "wof:placetype":"venue"
},
  "geometry": {"coordinates":[11.143663,47.563026],"type":"Point"}
}