{
  "type": "Feature",
  "properties": {
    "iso:country":"DE",
    "sg:address":"Kulmbacher Str. 28",
    "sg:city":"Hof",
    "sg:postcode":"95030",
    "sg:province":"Bayern",
    "wof:name":"Sch\u00e4dlich Gmbh",
    "wof:placetype":"venue"
},
  "geometry": {"coordinates":[11.9011974335,50.3180389404],"type":"Point"}
}