{
  "type": "Feature",
  "properties": {
    "iso:country":"DE",
    "sg:address":"Seebacher Str. 66",
    "sg:city":"Bad D\u00fcrkheim",
    "sg:postcode":"67098",
    "sg:province":"Rheinland-Pfalz",
    "wof:name":"Wolle-garne Marianne L\u00f6cher",
    "wof:placetype":"venue"
},
  "geometry": {"coordinates":[8.164031,49.452988],"type":"Point"}
}