{
  "type": "Feature",
  "properties": {
    "iso:country":"DE",
    "sg:address":"Industriestr. 81a",
    "sg:city":"Burscheid",
    "sg:phone":"+49 4921/7476220",
    "sg:postcode":"51399",
    "sg:province":"Nordrhein-Westfalen",
    "wof:name":"Burscheider Flanschen- Handel Gmbh",
    "wof:placetype":"venue"
},
  "geometry": {"coordinates":[7.0857567787,51.0874633789],"type":"Point"}
}