{
  "type": "Feature",
  "properties": {
    "iso:country":"DE",
    "sg:address":"Haager Str. 20",
    "sg:city":"Maitenbeth",
    "sg:phone":"+49 8076/1755",
    "sg:postcode":"83558",
    "sg:province":"Bayern",
    "wof:name":"Aral-tankstelle",
    "wof:placetype":"venue"
},
  "geometry": {"coordinates":[12.092417717,48.1533355713],"type":"Point"}
}