{
  "type": "Feature",
  "properties": {
    "iso:country":"DE",
    "sg:address":"Jakobsgasse 7-9",
    "sg:city":"Crimmitschau",
    "sg:phone":"+49 3762/5448",
    "sg:postcode":"08451",
    "sg:province":"Sachsen",
    "wof:name":"Vegas Gbr",
    "wof:placetype":"venue"
},
  "geometry": {"coordinates":[12.3844614029,50.8171272278],"type":"Point"}
}