{
  "type": "Feature",
  "properties": {
    "iso:country":"DE",
    "sg:address":"Bamberger Str. 22",
    "sg:city":"Burgkunstadt",
    "sg:phone":"+49 9572/1617",
    "sg:postcode":"96224",
    "sg:province":"Bayern",
    "wof:name":"Ursula Und Manfred Kestel",
    "wof:placetype":"venue"
},
  "geometry": {"coordinates":[11.228066,50.146099],"type":"Point"}
}