{
  "type": "Feature",
  "properties": {
    "iso:country":"DE",
    "sg:address":"Hintere H\u00f6fe 4",
    "sg:city":"Freiamt",
    "sg:phone":"+49 7645/259",
    "sg:postcode":"79348",
    "sg:province":"Baden-W\u00fcrttemberg",
    "wof:name":"Pension Hintere H\u00f6fe",
    "wof:placetype":"venue"
},
  "geometry": {"coordinates":[7.9061260223,48.1786384583],"type":"Point"}
}