{
  "type": "Feature",
  "properties": {
    "iso:country":"DE",
    "sg:address":"Chiemgaustr. 48",
    "sg:city":"M\u00fcnchen",
    "sg:phone":"+49 89/6902744",
    "sg:postcode":"81549",
    "sg:province":"Bayern",
    "wof:name":"Klaus Gre\u00dfierer",
    "wof:placetype":"venue"
},
  "geometry": {"coordinates":[11.5918998718,48.1054077148],"type":"Point"}
}