{
  "type": "Feature",
  "properties": {
    "iso:country":"DE",
    "sg:address":"Esslinger Str. 93",
    "sg:city":"Altbach",
    "sg:phone":"+49 7153/22323",
    "sg:postcode":"73776",
    "sg:province":"Baden-W\u00fcrttemberg",
    "wof:name":"Apotheke Altbach E. Kfr.",
    "wof:placetype":"venue"
},
  "geometry": {"coordinates":[9.382452,48.72197],"type":"Point"}
}