{
  "type": "Feature",
  "properties": {
    "iso:country":"DE",
    "sg:address":"R\u00f6nnestr. 14",
    "sg:city":"Berlin",
    "sg:postcode":"14057",
    "sg:province":"Berlin",
    "wof:name":"Baing Grundbesitz Und Management Gmbh",
    "wof:placetype":"venue"
},
  "geometry": {"coordinates":[13.294589,52.503433],"type":"Point"}
}