{
  "type": "Feature",
  "properties": {
    "iso:country":"DE",
    "sg:address":"Hochheimstr. 39-41",
    "sg:city":"Niederzier",
    "sg:phone":"+49 2428/6686",
    "sg:postcode":"52382",
    "sg:province":"Nordrhein-Westfalen",
    "wof:name":"Willy Steven",
    "wof:placetype":"venue"
},
  "geometry": {"coordinates":[6.4576921463,50.8551521301],"type":"Point"}
}