{
  "type": "Feature",
  "properties": {
    "iso:country":"DE",
    "sg:address":"Am Schirgiswalder Platz",
    "sg:city":"Sundern/Sauerl.",
    "sg:phone":"+49 2933/6869",
    "sg:postcode":"59846",
    "sg:province":"Nordrhein-Westfalen",
    "wof:name":"Swinging World Tanzschule J\u00fcrgen Hoffmann",
    "wof:placetype":"venue"
},
  "geometry": {"coordinates":[8.0044946671,51.3304710388],"type":"Point"}
}