{
  "type": "Feature",
  "properties": {
    "iso:country":"DE",
    "sg:address":"Kleiner Send 19",
    "sg:city":"H\u00f6rstel",
    "sg:phone":"+49 5459/7756",
    "sg:postcode":"48477",
    "sg:province":"Nordrhein-Westfalen",
    "wof:name":"Paul Paetzke Bildhauer",
    "wof:placetype":"venue"
},
  "geometry": {"coordinates":[7.57986,52.269531],"type":"Point"}
}