{
  "type": "Feature",
  "properties": {
    "iso:country":"DE",
    "sg:address":"Malvenweg 2a",
    "sg:city":"Wiesmoor",
    "sg:phone":"+49 4944/3101",
    "sg:postcode":"26639",
    "sg:province":"Niedersachsen",
    "wof:name":"Wiesmoor-haus Gmbh",
    "wof:placetype":"venue"
},
  "geometry": {"coordinates":[7.7431268692,53.4165344238],"type":"Point"}
}