{
  "type": "Feature",
  "properties": {
    "iso:country":"DE",
    "sg:address":"Molkereistr. 1",
    "sg:city":"Wingst",
    "sg:phone":"+49 4778/232",
    "sg:postcode":"21789",
    "sg:province":"Niedersachsen",
    "wof:name":"Foto Dabrock Inh. G\u00fcnter Szechleba",
    "wof:placetype":"venue"
},
  "geometry": {"coordinates":[9.0887975693,53.7444801331],"type":"Point"}
}