{
  "type": "Feature",
  "properties": {
    "iso:country":"DE",
    "sg:address":"Eggerscheidter Str. 40",
    "sg:city":"Ratingen",
    "sg:phone":"+49 2102/60676",
    "sg:postcode":"40883",
    "sg:province":"Nordrhein-Westfalen",
    "wof:name":"G\u00fcnter Undorf",
    "wof:placetype":"venue"
},
  "geometry": {"coordinates":[6.904938,51.32848],"type":"Point"}
}