{
  "type": "Feature",
  "properties": {
    "iso:country":"DE",
    "sg:address":"Rheintalstr. 42",
    "sg:city":"Mainz",
    "sg:phone":"+49 6131/883080",
    "sg:postcode":"55130",
    "sg:province":"Rheinland-Pfalz",
    "wof:name":"M. Koch",
    "wof:placetype":"venue"
},
  "geometry": {"coordinates":[8.318442,49.962898],"type":"Point"}
}