{
  "type": "Feature",
  "properties": {
    "iso:country":"DE",
    "sg:address":"Alt-Ulmer-Str. 10",
    "sg:city":"Herbrechtingen",
    "sg:postcode":"89542",
    "sg:province":"Baden-W\u00fcrttemberg",
    "wof:name":"Esband Gmbh",
    "wof:placetype":"venue"
},
  "geometry": {"coordinates":[10.180787,48.618469],"type":"Point"}
}