{
  "type": "Feature",
  "properties": {
    "iso:country":"DE",
    "sg:address":"Im Mainfeld 42",
    "sg:city":"Frankfurt",
    "sg:postcode":"60528",
    "sg:province":"Hessen",
    "wof:name":"Roms Gmbh",
    "wof:placetype":"venue"
},
  "geometry": {"coordinates":[8.6384210587,50.0891876221],"type":"Point"}
}