{
  "type": "Feature",
  "properties": {
    "iso:country":"DE",
    "sg:address":"Pucher Str. 18",
    "sg:city":"F\u00fcrstenfeldbruck",
    "sg:phone":"+49 8141/12260",
    "sg:postcode":"82256",
    "sg:province":"Bayern",
    "wof:name":"Haus Des Kindes Inh. Sofie Krau\u00df",
    "wof:placetype":"venue"
},
  "geometry": {"coordinates":[11.2522068024,48.178981781],"type":"Point"}
}