{
  "type": "Feature",
  "properties": {
    "iso:country":"DE",
    "sg:address":"Fuggerstr. 33",
    "sg:city":"Schwabm\u00fcnchen",
    "sg:phone":"+49 8232/96370",
    "sg:postcode":"86830",
    "sg:province":"Bayern",
    "wof:name":"Dr. Erhard Pauker Notar",
    "wof:placetype":"venue"
},
  "geometry": {"coordinates":[10.7576169968,48.1814117432],"type":"Point"}
}