{
  "type": "Feature",
  "properties": {
    "iso:country":"DE",
    "sg:address":"Steeg 11",
    "sg:city":"Schwalmtal",
    "sg:phone":"+49 2163/4134",
    "sg:postcode":"41366",
    "sg:province":"Nordrhein-Westfalen",
    "wof:name":"Hotel-restaurant Akropolis",
    "wof:placetype":"venue"
},
  "geometry": {"coordinates":[6.2989311218,51.2099914551],"type":"Point"}
}