{
  "type": "Feature",
  "properties": {
    "iso:country":"DE",
    "sg:address":"Bockskamp 4",
    "sg:city":"Kalkar",
    "sg:phone":"+49 2824/6889",
    "sg:postcode":"47546",
    "sg:province":"Nordrhein-Westfalen",
    "wof:name":"M. They\u00dfen",
    "wof:placetype":"venue"
},
  "geometry": {"coordinates":[6.313635,51.785011],"type":"Point"}
}