{
  "type": "Feature",
  "properties": {
    "iso:country":"DE",
    "sg:address":"Hansaring 32",
    "sg:city":"K\u00f6ln",
    "sg:phone":"+49 221/1392806",
    "sg:postcode":"50670",
    "sg:province":"Nordrhein-Westfalen",
    "wof:name":"Mc Lennon",
    "wof:placetype":"venue"
},
  "geometry": {"coordinates":[6.94581604,50.946308136],"type":"Point"}
}