{
  "type": "Feature",
  "properties": {
    "iso:country":"DE",
    "sg:address":"Nunzenrieder Str. 65",
    "sg:city":"Oberviechtach",
    "sg:phone":"+49 9671/3202",
    "sg:postcode":"92526",
    "sg:province":"Bayern",
    "wof:name":"Pils-pub Charivari",
    "wof:placetype":"venue"
},
  "geometry": {"coordinates":[12.4321460724,49.4567298889],"type":"Point"}
}