{
  "type": "Feature",
  "properties": {
    "iso:country":"DE",
    "sg:address":"Bahnhofstr. 23",
    "sg:city":"Rauschenberg",
    "sg:phone":"+49 6425/1330",
    "sg:postcode":"35282",
    "sg:province":"Hessen",
    "wof:name":"Walter Dersch",
    "wof:placetype":"venue"
},
  "geometry": {"coordinates":[8.92436,50.879391],"type":"Point"}
}