{
  "type": "Feature",
  "properties": {
    "iso:country":"DE",
    "sg:address":"Steinstr. 30",
    "sg:city":"Werne",
    "sg:phone":"+49 2389/3176",
    "sg:postcode":"59368",
    "sg:province":"Nordrhein-Westfalen",
    "wof:name":"Global",
    "wof:placetype":"venue"
},
  "geometry": {"coordinates":[7.6335721016,51.6622505188],"type":"Point"}
}