{
  "type": "Feature",
  "properties": {
    "iso:country":"DE",
    "sg:address":"W\u00e4chterhofstr. 50",
    "sg:city":"H\u00f6henkirchen-Siegertbrn",
    "sg:phone":"+49 8102/78803",
    "sg:postcode":"85635",
    "sg:province":"Bayern",
    "wof:name":"P\u00f6ttinger Zimmerei -holzbau Gmbh",
    "wof:placetype":"venue"
},
  "geometry": {"coordinates":[11.7092008591,48.025062561],"type":"Point"}
}