{
  "type": "Feature",
  "properties": {
    "iso:country":"DE",
    "sg:address":"Maria-Theresia-Str. 24",
    "sg:city":"Kirchzarten",
    "sg:phone":"+49 7661/5129",
    "sg:postcode":"79199",
    "sg:province":"Baden-W\u00fcrttemberg",
    "wof:name":"Dr. Fritz Wei\u00df Ingenieur",
    "wof:placetype":"venue"
},
  "geometry": {"coordinates":[7.9636831284,47.9647064209],"type":"Point"}
}