{
  "type": "Feature",
  "properties": {
    "iso:country":"DE",
    "sg:address":"Wolfsfurth 2",
    "sg:city":"W\u00fcrselen",
    "sg:phone":"+49 241/9108481",
    "sg:postcode":"52146",
    "sg:province":"Nordrhein-Westfalen",
    "wof:name":"Gms Gesellschaft F\u00fcr Medizinische Schulung Und",
    "wof:placetype":"venue"
},
  "geometry": {"coordinates":[6.1063752174,50.8102302551],"type":"Point"}
}