{
  "type": "Feature",
  "properties": {
    "iso:country":"DE",
    "sg:address":"Schwetzinger Str. 51",
    "sg:city":"Heidelberg",
    "sg:phone":"+49 6221/785006",
    "sg:postcode":"69124",
    "sg:province":"Baden-W\u00fcrttemberg",
    "wof:name":"Detlef Sch\u00f6pf Harald Rupp Rolf Sauer",
    "wof:placetype":"venue"
},
  "geometry": {"coordinates":[8.6683349609,49.3788032532],"type":"Point"}
}