{
  "type": "Feature",
  "properties": {
    "iso:country":"DE",
    "sg:address":"Hauptstr. 27",
    "sg:city":"Schn\u00fcrpflingen",
    "sg:phone":"+49 7346/5122",
    "sg:postcode":"89194",
    "sg:province":"Baden-W\u00fcrttemberg",
    "wof:name":"Anton Renz",
    "wof:placetype":"venue"
},
  "geometry": {"coordinates":[9.989711,48.27253],"type":"Point"}
}