{
  "type": "Feature",
  "properties": {
    "iso:country":"DE",
    "sg:address":"Bahnhofstr. 15",
    "sg:city":"Tann",
    "sg:phone":"+49 6682/377",
    "sg:postcode":"36142",
    "sg:province":"Hessen",
    "wof:name":"Gerhard Leubecher Kohlen-handlung",
    "wof:placetype":"venue"
},
  "geometry": {"coordinates":[11.8681879044,50.4933738708],"type":"Point"}
}