{
  "type": "Feature",
  "properties": {
    "iso:country":"DE",
    "sg:address":"Benrather Schlo\u00dfallee 53",
    "sg:city":"D\u00fcsseldorf",
    "sg:phone":"+49 211/711700",
    "sg:postcode":"40597",
    "sg:province":"Nordrhein-Westfalen",
    "wof:name":"Boehmert Und Boehmert Patentanw\u00e4lte",
    "wof:placetype":"venue"
},
  "geometry": {"coordinates":[6.861374855,51.1623802185],"type":"Point"}
}