{
  "type": "Feature",
  "properties": {
    "iso:country":"DE",
    "sg:address":"D\u00fcrener Str. 98",
    "sg:city":"K\u00f6ln",
    "sg:phone":"+49 221/401035",
    "sg:postcode":"50931",
    "sg:province":"Nordrhein-Westfalen",
    "wof:name":"Hans-j\u00fcrgen P\u00fctz Steuerberater",
    "wof:placetype":"venue"
},
  "geometry": {"coordinates":[6.9201622009,50.9319038391],"type":"Point"}
}