{
  "type": "Feature",
  "properties": {
    "iso:country":"DE",
    "sg:address":"Obere Marktstr. 39",
    "sg:city":"Hildburghausen",
    "sg:phone":"+49 3685/705408",
    "sg:postcode":"98646",
    "sg:province":"Th\u00fcringen",
    "wof:name":"Dart",
    "wof:placetype":"venue"
},
  "geometry": {"coordinates":[10.731388092,50.4256515503],"type":"Point"}
}