{
  "type": "Feature",
  "properties": {
    "iso:country":"DE",
    "sg:address":"Hedwigstrasse 1-3",
    "sg:city":"Leipzig",
    "sg:phone":"+49 341/69740",
    "sg:postcode":"04315",
    "sg:province":"Sachsen",
    "wof:name":"Top Galerie Hotel Leipziger Hof",
    "wof:placetype":"venue"
},
  "geometry": {"coordinates":[12.4032402039,51.3468360901],"type":"Point"}
}