{
  "type": "Feature",
  "properties": {
    "iso:country":"DE",
    "sg:address":"Planetenring",
    "sg:city":"Garbsen",
    "sg:phone":"+49 5137/89930",
    "sg:postcode":"30823",
    "sg:province":"Niedersachsen",
    "wof:name":"Otto Werner Gmbh & Co. Kg",
    "wof:placetype":"venue"
},
  "geometry": {"coordinates":[9.597471,52.419876],"type":"Point"}
}