{
  "type": "Feature",
  "properties": {
    "iso:country":"DE",
    "sg:address":"Br\u00fchlstr. 3",
    "sg:city":"Ulm",
    "sg:phone":"+49 731/65367",
    "sg:postcode":"89081",
    "sg:province":"Baden-W\u00fcrttemberg",
    "wof:name":"G\u00fcnter Schmid",
    "wof:placetype":"venue"
},
  "geometry": {"coordinates":[9.9867630005,48.4456214905],"type":"Point"}
}