{
  "type": "Feature",
  "properties": {
    "iso:country":"DE",
    "sg:address":"Bahnhofstr. 8",
    "sg:city":"Ottobrunn",
    "sg:phone":"+49 89/6097246",
    "sg:postcode":"85521",
    "sg:province":"Bayern",
    "wof:name":"Josef Danner",
    "wof:placetype":"venue"
},
  "geometry": {"coordinates":[11.657876,48.070621],"type":"Point"}
}