{
  "type": "Feature",
  "properties": {
    "iso:country":"DE",
    "sg:address":"Almoshofer Hauptstr. 85",
    "sg:city":"N\u00fcrnberg",
    "sg:phone":"+49 911/345650",
    "sg:postcode":"90427",
    "sg:province":"Bayern",
    "wof:name":"Gr\u00f6tsch Metzgerei Und Gastst\u00e4tten",
    "wof:placetype":"venue"
},
  "geometry": {"coordinates":[11.0614881516,49.4908370972],"type":"Point"}
}