{
  "type": "Feature",
  "properties": {
    "iso:country":"DE",
    "sg:address":"Atterstr. 188",
    "sg:city":"Osnabr\u00fcck",
    "sg:phone":"+49 541/29897",
    "sg:postcode":"49090",
    "sg:province":"Niedersachsen",
    "wof:name":"Walter L\u00fchrmann",
    "wof:placetype":"venue"
},
  "geometry": {"coordinates":[7.9939188957,52.3056488037],"type":"Point"}
}