{
  "type": "Feature",
  "properties": {
    "iso:country":"DE",
    "sg:address":"Berliner Str. 9",
    "sg:city":"Rinteln",
    "sg:phone":"+49 5751/6688",
    "sg:postcode":"31737",
    "sg:province":"Niedersachsen",
    "wof:name":"Wilfried Ebeling",
    "wof:placetype":"venue"
},
  "geometry": {"coordinates":[9.1015501022,52.1967315674],"type":"Point"}
}