{
  "type": "Feature",
  "properties": {
    "iso:country":"DE",
    "sg:address":"Kurt-Schumacher-Str. 32",
    "sg:city":"Schweinfurt",
    "sg:phone":"+49 9721/32478",
    "sg:postcode":"97422",
    "sg:province":"Bayern",
    "wof:name":"Horst Popp",
    "wof:placetype":"venue"
},
  "geometry": {"coordinates":[10.252966,50.066444],"type":"Point"}
}