{
  "type": "Feature",
  "properties": {
    "iso:country":"DE",
    "sg:address":"Kapellenstr.",
    "sg:city":"M\u00fclheim-K\u00e4rlich",
    "sg:phone":"+49 2630/1760",
    "sg:postcode":"56218",
    "sg:province":"Rheinland-Pfalz",
    "wof:name":"Zur Sonne",
    "wof:placetype":"venue"
},
  "geometry": {"coordinates":[7.4979410172,50.3867835999],"type":"Point"}
}