{
  "type": "Feature",
  "properties": {
    "iso:country":"DE",
    "sg:address":"Cottbuser Str. 9",
    "sg:city":"Lauchhammer",
    "sg:phone":"+49 3574/3402",
    "sg:postcode":"01979",
    "sg:province":"Brandenburg",
    "wof:name":"Thomas Kilian",
    "wof:placetype":"venue"
},
  "geometry": {"coordinates":[13.7635746002,51.4952774048],"type":"Point"}
}