{
  "type": "Feature",
  "properties": {
    "iso:country":"DE",
    "sg:address":"Friedensinsel",
    "sg:city":"Aalen/Unterkochen",
    "sg:phone":"+49 4973/615040",
    "sg:postcode":"73432",
    "sg:province":"Baden-W\u00fcrttemberg",
    "wof:name":"Rud-kettenfabrik Rieger & Dietz Gmbh & Co.",
    "wof:placetype":"venue"
},
  "geometry": {"coordinates":[10.1837711334,48.8005638123],"type":"Point"}
}