{
  "type": "Feature",
  "properties": {
    "iso:country":"DE",
    "sg:address":"Asamstrasse 12",
    "sg:city":"Deggendorf",
    "sg:phone":"+49 991",
    "sg:postcode":"94469",
    "sg:province":"Bayern",
    "wof:name":"Ferienwohnung M\u00fcnchner Kindl Bodenmais",
    "wof:placetype":"venue"
},
  "geometry": {"coordinates":[12.98926,48.838894],"type":"Point"}
}