{
  "type": "Feature",
  "properties": {
    "iso:country":"DE",
    "sg:address":"R\u00f6merstr. 3",
    "sg:city":"Kleinkahl",
    "sg:postcode":"63828",
    "sg:province":"Bayern",
    "wof:name":"Oel-maier Mineraloelvertrieb Gmbh",
    "wof:placetype":"venue"
},
  "geometry": {"coordinates":[9.2809791565,50.1079826355],"type":"Point"}
}