{
  "type": "Feature",
  "properties": {
    "iso:country":"DE",
    "sg:address":"Kopernikusstr. 45",
    "sg:city":"Hanau",
    "sg:phone":"+49 6181/258495",
    "sg:postcode":"63454",
    "sg:province":"Hessen",
    "wof:name":"Hegra Heizungsanlagen Im- Und Export Gmbh",
    "wof:placetype":"venue"
},
  "geometry": {"coordinates":[8.8782329559,50.1345558167],"type":"Point"}
}