{
  "type": "Feature",
  "properties": {
    "iso:country":"DE",
    "sg:address":"Heinrich-Ehrhardt-Str. 25",
    "sg:city":"Zella-Mehlis",
    "sg:phone":"+49 3682/40397",
    "sg:postcode":"98544",
    "sg:province":"Th\u00fcringen",
    "wof:name":"Achim Kessel",
    "wof:placetype":"venue"
},
  "geometry": {"coordinates":[10.6748008728,50.6568374634],"type":"Point"}
}