{
  "type": "Feature",
  "properties": {
    "iso:country":"DE",
    "sg:address":"Hauptstr. 25",
    "sg:city":"Donzdorf",
    "sg:phone":"+49 7162/24500",
    "sg:postcode":"73072",
    "sg:province":"Baden-W\u00fcrttemberg",
    "wof:name":"G\u00fcnter Scheiffele Ingenieur",
    "wof:placetype":"venue"
},
  "geometry": {"coordinates":[9.8045949936,48.6862297058],"type":"Point"}
}