{
  "type": "Feature",
  "properties": {
    "iso:country":"DE",
    "sg:address":"Georgsweiler Str. 27",
    "sg:city":"B\u00fcchel",
    "sg:phone":"+49 2678/411",
    "sg:postcode":"56823",
    "sg:province":"Rheinland-Pfalz",
    "wof:name":"Helmut Rein",
    "wof:placetype":"venue"
},
  "geometry": {"coordinates":[7.077,50.172089],"type":"Point"}
}