{
  "type": "Feature",
  "properties": {
    "iso:country":"DE",
    "sg:address":"Scharnhorststr. 2",
    "sg:city":"Chemnitz",
    "sg:phone":"+49 371/724069",
    "sg:postcode":"09130",
    "sg:province":"Sachsen",
    "wof:name":"Dr. Med. Christa Stahl",
    "wof:placetype":"venue"
},
  "geometry": {"coordinates":[12.9565839767,50.8319816589],"type":"Point"}
}