{
  "type": "Feature",
  "properties": {
    "iso:country":"DE",
    "sg:address":"Amselstr. 13",
    "sg:city":"R\u00f6ttenbach",
    "sg:phone":"+49 9195/1265",
    "sg:postcode":"91341",
    "sg:province":"Bayern",
    "wof:name":"Sir Schabert Instrumente Gmbh",
    "wof:placetype":"venue"
},
  "geometry": {"coordinates":[10.933147,49.666626],"type":"Point"}
}