{
  "type": "Feature",
  "properties": {
    "iso:country":"DE",
    "sg:address":"Eschstr. 30",
    "sg:city":"S\u00fcdlohn",
    "sg:phone":"+49 2862/5899836",
    "sg:postcode":"46354",
    "sg:province":"Nordrhein-Westfalen",
    "wof:name":"Sparwel & Sundrum Bau Gmbh",
    "wof:placetype":"venue"
},
  "geometry": {"coordinates":[6.8700342178,51.9470062256],"type":"Point"}
}