{
  "type": "Feature",
  "properties": {
    "iso:country":"DE",
    "sg:address":"Braungasse 3",
    "sg:city":"Reichertsheim",
    "sg:phone":"+49 8073/2060",
    "sg:postcode":"84437",
    "sg:province":"Bayern",
    "wof:name":"Hamberger Und Widauer Gmbh",
    "wof:placetype":"venue"
},
  "geometry": {"coordinates":[12.286626,48.198925],"type":"Point"}
}