{
  "type": "Feature",
  "properties": {
    "iso:country":"DE",
    "sg:address":"Markdorfer Str. 92",
    "sg:city":"Friedrichshafen",
    "sg:phone":"+49 7544/95190",
    "sg:postcode":"88048",
    "sg:province":"Baden-W\u00fcrttemberg",
    "wof:name":"H. Schmidhuber",
    "wof:placetype":"venue"
},
  "geometry": {"coordinates":[9.39933,47.694328],"type":"Point"}
}