{
  "type": "Feature",
  "properties": {
    "iso:country":"DE",
    "sg:address":"B\u00e4tznerstr. 22",
    "sg:city":"Bad Wildbad",
    "sg:phone":"+49 7081/8645",
    "sg:postcode":"75323",
    "sg:province":"Baden-W\u00fcrttemberg",
    "wof:name":"Villa Ruth",
    "wof:placetype":"venue"
},
  "geometry": {"coordinates":[8.5482664108,48.7523422241],"type":"Point"}
}