{
  "type": "Feature",
  "properties": {
    "iso:country":"DE",
    "sg:address":"Mennrath 2",
    "sg:city":"M\u00f6nchengladbach",
    "sg:phone":"+49 2161/580433",
    "sg:postcode":"41179",
    "sg:province":"Nordrhein-Westfalen",
    "wof:name":"Anton Mennen",
    "wof:placetype":"venue"
},
  "geometry": {"coordinates":[6.381835,51.137264],"type":"Point"}
}