{
  "type": "Feature",
  "properties": {
    "iso:country":"DE",
    "sg:address":"Silberburgstr. 187",
    "sg:city":"Stuttgart",
    "sg:postcode":"70178",
    "sg:province":"Baden-W\u00fcrttemberg",
    "wof:name":"Reusch International Licence Gmbh & Co. Kg",
    "wof:placetype":"venue"
},
  "geometry": {"coordinates":[9.1700525284,48.769618988],"type":"Point"}
}