{
  "type": "Feature",
  "properties": {
    "iso:country":"DE",
    "sg:address":"Neumann-Reichardt-Str. 27",
    "sg:city":"Hamburg",
    "sg:phone":"+49 40/277988",
    "sg:postcode":"22041",
    "sg:province":"Hamburg",
    "wof:name":"Maximilian Duhme Gmbh",
    "wof:placetype":"venue"
},
  "geometry": {"coordinates":[10.0660200119,53.5717086792],"type":"Point"}
}