{
  "type": "Feature",
  "properties": {
    "iso:country":"DE",
    "sg:address":"Im Stiegel 8",
    "sg:city":"Eltville",
    "sg:phone":"+49 6723/87494",
    "sg:postcode":"65347",
    "sg:province":"Hessen",
    "wof:name":"Statzner Und Lamberti Maschinen- Und Metallbau Gmbh",
    "wof:placetype":"venue"
},
  "geometry": {"coordinates":[8.053452,50.015289],"type":"Point"}
}