{
  "type": "Feature",
  "properties": {
    "iso:country":"DE",
    "sg:address":"Pflughof 16",
    "sg:city":"Schopfheim",
    "sg:phone":"+49 7622/8341",
    "sg:postcode":"79650",
    "sg:province":"Baden-W\u00fcrttemberg",
    "wof:name":"Eisdiele Cortina",
    "wof:placetype":"venue"
},
  "geometry": {"coordinates":[7.824483,47.649803],"type":"Point"}
}