{
  "type": "Feature",
  "properties": {
    "iso:country":"DE",
    "sg:address":"Schlo\u00dfbergstr. 2a",
    "sg:city":"Landsberied",
    "sg:phone":"+49 8141/21543",
    "sg:postcode":"82290",
    "sg:province":"Bayern",
    "wof:name":"Herbert Leierer",
    "wof:placetype":"venue"
},
  "geometry": {"coordinates":[11.170982,48.161121],"type":"Point"}
}