{
  "type": "Feature",
  "properties": {
    "iso:country":"DE",
    "sg:address":"Porschestr. 18",
    "sg:city":"Salzgitter",
    "sg:phone":"+49 4953/4136085",
    "sg:postcode":"38259",
    "sg:province":"Niedersachsen",
    "wof:name":"Sinter-industrie-technik Gmbh",
    "wof:placetype":"venue"
},
  "geometry": {"coordinates":[10.385753,52.056702],"type":"Point"}
}