{
  "type": "Feature",
  "properties": {
    "iso:country":"DE",
    "sg:address":"Hauptstr. 67",
    "sg:city":"Rheda-Wiedenbr\u00fcck",
    "sg:phone":"+49 4933/602214",
    "sg:postcode":"33378",
    "sg:province":"Nordrhein-Westfalen",
    "wof:name":"Pda Produktions- & Dienstleistungs Gmbh Der Agrarwirtschaft",
    "wof:placetype":"venue"
},
  "geometry": {"coordinates":[14.4454298019,52.4294090271],"type":"Point"}
}