{
  "type": "Feature",
  "properties": {
    "iso:country":"DE",
    "sg:address":"Zugspitzstr. 211a",
    "sg:city":"Augsburg",
    "sg:phone":"+49 821/729482",
    "sg:postcode":"86165",
    "sg:province":"Bayern",
    "wof:name":"R. Furmanek",
    "wof:placetype":"venue"
},
  "geometry": {"coordinates":[10.93042,48.37244],"type":"Point"}
}