{
  "type": "Feature",
  "properties": {
    "iso:country":"DE",
    "sg:address":"Bl\u00fccherstr. 95",
    "sg:city":"Schwelm",
    "sg:phone":"+49 2336/2041",
    "sg:postcode":"58332",
    "sg:province":"Nordrhein-Westfalen",
    "wof:name":"Raab Karcher Fliesen Gmbh",
    "wof:placetype":"venue"
},
  "geometry": {"coordinates":[7.2755069733,51.2889175415],"type":"Point"}
}