{
  "type": "Feature",
  "properties": {
    "iso:country":"DE",
    "sg:address":"Stuttgarter Str. 20",
    "sg:city":"Pforzheim",
    "sg:phone":"+49 7231/1540990",
    "sg:postcode":"75179",
    "sg:province":"Baden-W\u00fcrttemberg",
    "wof:name":"Joratec Gmbh",
    "wof:placetype":"venue"
},
  "geometry": {"coordinates":[8.659623,48.899647],"type":"Point"}
}