{
  "type": "Feature",
  "properties": {
    "iso:country":"DE",
    "sg:address":"Untere Metzgerstr. 15",
    "sg:city":"Siegen",
    "sg:phone":"+49 271/53226",
    "sg:postcode":"57072",
    "sg:province":"Nordrhein-Westfalen",
    "wof:name":"Katholisches Pfarramt St. Marien",
    "wof:placetype":"venue"
},
  "geometry": {"coordinates":[8.0257587433,50.8738822937],"type":"Point"}
}