{
  "type": "Feature",
  "properties": {
    "iso:country":"DE",
    "sg:address":"Sch\u00f6nbergstr. 13",
    "sg:city":"Hannover",
    "sg:phone":"+49 511/799579",
    "sg:postcode":"30419",
    "sg:province":"Niedersachsen",
    "wof:name":"Dieter Bertram",
    "wof:placetype":"venue"
},
  "geometry": {"coordinates":[9.6872644424,52.412311554],"type":"Point"}
}