{
  "type": "Feature",
  "properties": {
    "iso:country":"DE",
    "sg:address":"Dantestr 4-6",
    "sg:city":"Wiesbaden",
    "sg:phone":"+49 611/900960",
    "sg:postcode":"65189",
    "sg:province":"Hessen",
    "wof:name":"Smartloyalty Ag",
    "wof:placetype":"venue"
},
  "geometry": {"coordinates":[8.251105,50.072941],"type":"Point"}
}