{
  "type": "Feature",
  "properties": {
    "iso:country":"DE",
    "sg:address":"Uferstr. 33",
    "sg:city":"Erkner",
    "sg:phone":"+49 3362/75630",
    "sg:postcode":"15537",
    "sg:province":"Brandenburg",
    "wof:name":"F. Meineer",
    "wof:placetype":"venue"
},
  "geometry": {"coordinates":[13.7390565872,52.4165077209],"type":"Point"}
}