{
  "type": "Feature",
  "properties": {
    "iso:country":"DE",
    "sg:address":"An der Strusbek 50",
    "sg:city":"Ahrensburg",
    "sg:phone":"+49 4102/80660",
    "sg:postcode":"22926",
    "sg:province":"Schleswig-Holstein",
    "wof:name":"Badgepoint Blindow Namensschildersysteme Gmbh",
    "wof:placetype":"venue"
},
  "geometry": {"coordinates":[10.2655315399,53.6918067932],"type":"Point"}
}