{
  "type": "Feature",
  "properties": {
    "iso:country":"DE",
    "sg:address":"Rheinauer Str. 15",
    "sg:city":"Br\u00fchl",
    "sg:phone":"+49 6202/71104",
    "sg:postcode":"68782",
    "sg:province":"Baden-W\u00fcrttemberg",
    "wof:name":"Leiberich",
    "wof:placetype":"venue"
},
  "geometry": {"coordinates":[8.521775,49.410416],"type":"Point"}
}