{
  "type": "Feature",
  "properties": {
    "iso:country":"DE",
    "sg:address":"Stra\u00dfe der Einheit 23",
    "sg:city":"Bad Lausick",
    "sg:phone":"+49 34345/5060",
    "sg:postcode":"04651",
    "sg:province":"Sachsen",
    "wof:name":"Hotel Am Markt",
    "wof:placetype":"venue"
},
  "geometry": {"coordinates":[12.6436462402,51.144203186],"type":"Point"}
}