{
  "type": "Feature",
  "properties": {
    "iso:country":"DE",
    "sg:address":"Humboldtstr. 46",
    "sg:city":"Bochum",
    "sg:phone":"+49 234/961310",
    "sg:postcode":"44787",
    "sg:province":"Nordrhein-Westfalen",
    "wof:name":"Welkoborsky Und Andere Rechtsanw\u00e4lte",
    "wof:placetype":"venue"
},
  "geometry": {"coordinates":[7.2139549255,51.4777107239],"type":"Point"}
}