{
  "type": "Feature",
  "properties": {
    "iso:country":"DE",
    "sg:address":"Hauser Weg",
    "sg:city":"Waldbrunn",
    "sg:phone":"+49 6479/724",
    "sg:postcode":"65620",
    "sg:province":"Hessen",
    "wof:name":"Lidl Gmbh & Co. Kg",
    "wof:placetype":"venue"
},
  "geometry": {"coordinates":[8.1260175705,50.5103988647],"type":"Point"}
}