{
  "type": "Feature",
  "properties": {
    "iso:country":"DE",
    "sg:address":"Konrad-Adenauer-Str.23",
    "sg:city":"Neustadt",
    "sg:phone":"+49 6321",
    "sg:postcode":"67433",
    "sg:province":"Rheinland-Pfalz",
    "wof:name":"Roxy Kinos Neustadt An Der Weinstrasse",
    "wof:placetype":"venue"
},
  "geometry": {"coordinates":[8.1426200867,49.3536376953],"type":"Point"}
}