{
  "type": "Feature",
  "properties": {
    "iso:country":"DE",
    "sg:address":"Hinter der B\u00f6ck 7",
    "sg:city":"D\u00fcsseldorf",
    "sg:phone":"+49 211/306309",
    "sg:postcode":"40221",
    "sg:province":"Nordrhein-Westfalen",
    "wof:name":"Helmut Von B\u00fcren Gmbh",
    "wof:placetype":"venue"
},
  "geometry": {"coordinates":[6.739481926,51.2037086487],"type":"Point"}
}