{
  "type": "Feature",
  "properties": {
    "iso:country":"DE",
    "sg:address":"Mielenforster Str. 8",
    "sg:city":"K\u00f6ln",
    "sg:postcode":"51069",
    "sg:province":"Nordrhein-Westfalen",
    "wof:name":"Sportschiffahrtschule K\u00f6ln T\u00f6rns Gmbh",
    "wof:placetype":"venue"
},
  "geometry": {"coordinates":[7.072152,50.962517],"type":"Point"}
}