{
  "type": "Feature",
  "properties": {
    "iso:country":"DE",
    "sg:address":"Bethanienstr. 3",
    "sg:city":"Bochum",
    "sg:phone":"+49 234/850277",
    "sg:postcode":"44805",
    "sg:province":"Nordrhein-Westfalen",
    "wof:name":"Bethanien-apotheke Inh. Rita Badziong",
    "wof:placetype":"venue"
},
  "geometry": {"coordinates":[7.279921,51.519306],"type":"Point"}
}