{
  "type": "Feature",
  "properties": {
    "iso:country":"DE",
    "sg:address":"D\u00fcrerstr. 24",
    "sg:city":"Berlin",
    "sg:phone":"+49 30/8330070",
    "sg:postcode":"12203",
    "sg:province":"Berlin",
    "wof:name":"A & K Elektroinstallation Gmbh",
    "wof:placetype":"venue"
},
  "geometry": {"coordinates":[13.304412,52.436729],"type":"Point"}
}