{
  "type": "Feature",
  "properties": {
    "iso:country":"DE",
    "sg:address":"Wolfer\u00f6der Weg 15 C",
    "sg:city":"Lutherstadt Eisleben",
    "sg:postcode":"06295",
    "sg:province":"Sachsen-Anhalt",
    "wof:name":"Euro-jagd Dupp Verwaltungsgesellschaft Mbh",
    "wof:placetype":"venue"
},
  "geometry": {"coordinates":[11.5404243469,51.5187644958],"type":"Point"}
}