{
  "type": "Feature",
  "properties": {
    "iso:country":"DE",
    "sg:address":"Wiesenbornstr. 11",
    "sg:city":"Bad Homburg",
    "sg:phone":"+49 6172/82757",
    "sg:postcode":"61350",
    "sg:province":"Hessen",
    "wof:name":"Georg K\u00e4mpfer",
    "wof:placetype":"venue"
},
  "geometry": {"coordinates":[8.6120939255,50.2364997864],"type":"Point"}
}