{
  "type": "Feature",
  "properties": {
    "iso:country":"DE",
    "sg:address":"Henriettenlust 4",
    "sg:city":"Regnitzlosau",
    "sg:phone":"+49 9294/383",
    "sg:postcode":"95194",
    "sg:province":"Bayern",
    "wof:name":"Rudi Gebhardt",
    "wof:placetype":"venue"
},
  "geometry": {"coordinates":[12.056723,50.314026],"type":"Point"}
}