{
  "type": "Feature",
  "properties": {
    "iso:country":"DE",
    "sg:address":"Platanenstr. 22b",
    "sg:city":"Berlin",
    "sg:postcode":"13156",
    "sg:province":"Berlin",
    "wof:name":"Katholisches Pfarramt St. Maria Magdalena",
    "wof:placetype":"venue"
},
  "geometry": {"coordinates":[13.3944368362,52.5844192505],"type":"Point"}
}