{
  "type": "Feature",
  "properties": {
    "iso:country":"DE",
    "sg:address":"Reichsstr. 46",
    "sg:city":"Wuppertal",
    "sg:phone":"+49 202/641300",
    "sg:postcode":"42275",
    "sg:province":"Nordrhein-Westfalen",
    "wof:name":"F\u00f6rdervereine Vhs Wuppertal E. V.",
    "wof:placetype":"venue"
},
  "geometry": {"coordinates":[7.2130417824,51.2731132507],"type":"Point"}
}