{
  "type": "Feature",
  "properties": {
    "iso:country":"DE",
    "sg:address":"Gustl-Waldau-Str. 60",
    "sg:city":"Ergolding",
    "sg:phone":"+49 871/770464",
    "sg:postcode":"84030",
    "sg:province":"Bayern",
    "wof:name":"Sabine Beurer",
    "wof:placetype":"venue"
},
  "geometry": {"coordinates":[12.166612,48.552349],"type":"Point"}
}