{
  "type": "Feature",
  "properties": {
    "iso:country":"DE",
    "sg:address":"Speyerer Str. 109",
    "sg:city":"Worms",
    "sg:phone":"+49 6241/37594",
    "sg:postcode":"67547",
    "sg:province":"Rheinland-Pfalz",
    "wof:name":"Klaus Orlemann",
    "wof:placetype":"venue"
},
  "geometry": {"coordinates":[8.3537559509,49.6203231812],"type":"Point"}
}