{
  "type": "Feature",
  "properties": {
    "iso:country":"DE",
    "sg:address":"Rathausstr. 16 a",
    "sg:city":"Bexbach",
    "sg:phone":"+49 6826/5885",
    "sg:postcode":"66450",
    "sg:province":"Saarland",
    "wof:name":"It Future World Alv Gmbh",
    "wof:placetype":"venue"
},
  "geometry": {"coordinates":[7.2592377663,49.3483772278],"type":"Point"}
}