{
  "type": "Feature",
  "properties": {
    "iso:country":"DE",
    "sg:address":"Kaiserstr. 38",
    "sg:city":"Homburg",
    "sg:phone":"+49 6841/93320",
    "sg:postcode":"66424",
    "sg:province":"Saarland",
    "wof:name":"Grieser Handelsagentur Gmbh & Co. Kg",
    "wof:placetype":"venue"
},
  "geometry": {"coordinates":[7.3360757828,49.3224105835],"type":"Point"}
}