{
  "type": "Feature",
  "properties": {
    "iso:country":"DE",
    "sg:address":"Wormser Weg 3",
    "sg:city":"D\u00fcsseldorf",
    "sg:phone":"+49 211/772280",
    "sg:postcode":"40229",
    "sg:province":"Nordrhein-Westfalen",
    "wof:name":"Wolfgang Hartwig Masseur",
    "wof:placetype":"venue"
},
  "geometry": {"coordinates":[6.82063,51.20359],"type":"Point"}
}