{
  "type": "Feature",
  "properties": {
    "iso:country":"DE",
    "sg:address":"Hauptstr. 56",
    "sg:city":"Rheinau",
    "sg:phone":"+49 7844/4419",
    "sg:postcode":"77866",
    "sg:province":"Baden-W\u00fcrttemberg",
    "wof:name":"Wolfgang Rohr Ingenieur",
    "wof:placetype":"venue"
},
  "geometry": {"coordinates":[7.9424910545,48.6667404175],"type":"Point"}
}