{
  "type": "Feature",
  "properties": {
    "iso:country":"DE",
    "sg:address":"Stra\u00dfe des Friedens 84",
    "sg:city":"W\u00fcmbach",
    "sg:phone":"+49 36785/50491",
    "sg:postcode":"98704",
    "sg:province":"Th\u00fcringen",
    "wof:name":"Zelth\u00f6tz",
    "wof:placetype":"venue"
},
  "geometry": {"coordinates":[10.9883899689,50.6925506592],"type":"Point"}
}