{
  "type": "Feature",
  "properties": {
    "iso:country":"DE",
    "sg:address":"Anne-Frank-Str. 5",
    "sg:city":"N\u00fcrnberg",
    "sg:phone":"+49 911/447072",
    "sg:postcode":"90459",
    "sg:province":"Bayern",
    "wof:name":"Action-sport Nkh Gmbh",
    "wof:placetype":"venue"
},
  "geometry": {"coordinates":[11.0852918625,49.4382667542],"type":"Point"}
}