{
  "type": "Feature",
  "properties": {
    "iso:country":"DE",
    "sg:address":"Hagenstr. 28",
    "sg:city":"Berlin",
    "sg:postcode":"14193",
    "sg:province":"Berlin",
    "wof:name":"Hospitex Vertrieb Medizinischer Textilien",
    "wof:placetype":"venue"
},
  "geometry": {"coordinates":[13.272827,52.479519],"type":"Point"}
}