{
  "type": "Feature",
  "properties": {
    "iso:country":"DE",
    "sg:address":"Wiesensteiger Str. 52",
    "sg:city":"Geislingen",
    "sg:phone":"+49 7331/66677",
    "sg:postcode":"73312",
    "sg:province":"Baden-W\u00fcrttemberg",
    "wof:name":"Taxi Lello Raffaele Battaglia",
    "wof:placetype":"venue"
},
  "geometry": {"coordinates":[9.8264341354,48.6183166504],"type":"Point"}
}