{
  "type": "Feature",
  "properties": {
    "iso:country":"DE",
    "sg:address":"Am Schilde 19",
    "sg:city":"Osterode",
    "sg:postcode":"37520",
    "sg:province":"Niedersachsen",
    "wof:name":"Opticum Verwaltungsges. Mbh",
    "wof:placetype":"venue"
},
  "geometry": {"coordinates":[10.2537946701,51.7273368835],"type":"Point"}
}