{
  "type": "Feature",
  "properties": {
    "iso:country":"DE",
    "sg:address":"Sch\u00fctzenstr. 35",
    "sg:city":"Melle",
    "sg:phone":"+49 5429/1640",
    "sg:postcode":"49326",
    "sg:province":"Niedersachsen",
    "wof:name":"Alfred Raude Tischlerei",
    "wof:placetype":"venue"
},
  "geometry": {"coordinates":[8.261004,52.152905],"type":"Point"}
}