{
  "type": "Feature",
  "properties": {
    "iso:country":"DE",
    "sg:address":"Rudolst\u00e4dter Str. 60",
    "sg:city":"Jena",
    "sg:phone":"+49 3641/609831",
    "sg:postcode":"07745",
    "sg:province":"Th\u00fcringen",
    "wof:name":"Koschny Tank Und Shop Gmbh",
    "wof:placetype":"venue"
},
  "geometry": {"coordinates":[11.5822124481,50.8966789246],"type":"Point"}
}