{
  "type": "Feature",
  "properties": {
    "iso:country":"DE",
    "sg:address":"Postfach 15",
    "sg:city":"Gaienhofen",
    "sg:postcode":"78338",
    "sg:province":"Baden-W\u00fcrttemberg",
    "wof:name":"Erich Manz",
    "wof:placetype":"venue"
},
  "geometry": {"coordinates":[8.9832897186,47.6831283569],"type":"Point"}
}