{
  "type": "Feature",
  "properties": {
    "iso:country":"DE",
    "sg:address":"Poststr. 8",
    "sg:city":"Bad Freienwalde",
    "sg:phone":"+49 3344/5417",
    "sg:postcode":"16259",
    "sg:province":"Brandenburg",
    "wof:name":"Restaurant Jantra",
    "wof:placetype":"venue"
},
  "geometry": {"coordinates":[14.0868873596,52.7643966675],"type":"Point"}
}