{
  "type": "Feature",
  "properties": {
    "iso:country":"DE",
    "sg:address":"Kolpingstr. 52",
    "sg:city":"Emsdetten",
    "sg:phone":"+49 2572/1560",
    "sg:postcode":"48282",
    "sg:province":"Nordrhein-Westfalen",
    "wof:name":"Wedi Gmbh",
    "wof:placetype":"venue"
},
  "geometry": {"coordinates":[7.5233201981,52.1772155762],"type":"Point"}
}