{
  "type": "Feature",
  "properties": {
    "iso:country":"DE",
    "sg:address":"Buchheimer Str. 18",
    "sg:city":"Krefeld",
    "sg:phone":"+49 2151/595149",
    "sg:postcode":"47800",
    "sg:province":"Nordrhein-Westfalen",
    "wof:name":"Guido Kennett",
    "wof:placetype":"venue"
},
  "geometry": {"coordinates":[6.602246,51.347683],"type":"Point"}
}