{
  "type": "Feature",
  "properties": {
    "iso:country":"DE",
    "sg:address":"Dieringhauser Str. 27",
    "sg:city":"Gummersbach",
    "sg:phone":"+49 2261/75091",
    "sg:postcode":"51645",
    "sg:province":"Nordrhein-Westfalen",
    "wof:name":"L. Becker",
    "wof:placetype":"venue"
},
  "geometry": {"coordinates":[7.5388422012,50.983745575],"type":"Point"}
}