{
  "type": "Feature",
  "properties": {
    "iso:country":"DE",
    "sg:address":"Immenweg 3",
    "sg:city":"Georgsmarienh\u00fctte",
    "sg:phone":"+49 5401/46837",
    "sg:postcode":"49124",
    "sg:province":"Niedersachsen",
    "wof:name":"Out Of Space Records",
    "wof:placetype":"venue"
},
  "geometry": {"coordinates":[8.077086,52.219791],"type":"Point"}
}