{
  "type": "Feature",
  "properties": {
    "iso:country":"DE",
    "sg:address":"Herner Str. 130::",
    "sg:city":"Castrop-Rauxel",
    "sg:phone":"+49 4923/059260",
    "sg:postcode":"44575",
    "sg:province":"Nordrhein-Westfalen",
    "wof:name":"Apotheken-abrechnungen Organisation L.neumann Gmbh",
    "wof:placetype":"venue"
},
  "geometry": {"coordinates":[7.294857,51.550304],"type":"Point"}
}