{
  "type": "Feature",
  "properties": {
    "iso:country":"DE",
    "sg:address":"Bessemerstr. 76 B",
    "sg:city":"Berlin",
    "sg:phone":"+49 4930/7569070",
    "sg:postcode":"12103",
    "sg:province":"Berlin",
    "wof:name":"Gemmel & Co Gmbh",
    "wof:placetype":"venue"
},
  "geometry": {"coordinates":[13.366504,52.461929],"type":"Point"}
}