{
  "type": "Feature",
  "properties": {
    "iso:country":"DE",
    "sg:address":"Kornhausstr. 14",
    "sg:city":"Leutkirch",
    "sg:phone":"+49 7561/71473",
    "sg:postcode":"88299",
    "sg:province":"Baden-W\u00fcrttemberg",
    "wof:name":"Kornhausmetzgerei",
    "wof:placetype":"venue"
},
  "geometry": {"coordinates":[10.0226278305,47.8267021179],"type":"Point"}
}