{
  "type": "Feature",
  "properties": {
    "iso:country":"DE",
    "sg:address":"Marktplatz 29",
    "sg:city":"Sch\u00f6nberg",
    "sg:phone":"+49 8554/892",
    "sg:postcode":"94513",
    "sg:province":"Bayern",
    "wof:name":"Wald-apotheke Gerlinde Gr\u00f6ner",
    "wof:placetype":"venue"
},
  "geometry": {"coordinates":[13.33962,48.839893],"type":"Point"}
}