{
  "type": "Feature",
  "properties": {
    "iso:country":"DE",
    "sg:address":"Daimlerstr. 19",
    "sg:city":"Weinheim",
    "sg:phone":"+49 6201/12049",
    "sg:postcode":"69469",
    "sg:province":"Baden-W\u00fcrttemberg",
    "wof:name":"Intersnack Knabber-geb\u00e4ck Gmbh & Co. Kg",
    "wof:placetype":"venue"
},
  "geometry": {"coordinates":[8.6209812164,49.54662323],"type":"Point"}
}