{
  "type": "Feature",
  "properties": {
    "iso:country":"DE",
    "sg:address":"Tenter Weg 1-3",
    "sg:city":"Remscheid",
    "sg:phone":"+49 2191/6990",
    "sg:postcode":"42897",
    "sg:province":"Nordrhein-Westfalen",
    "wof:name":"Volksbank Remscheid, Solingen Eg",
    "wof:placetype":"venue"
},
  "geometry": {"coordinates":[7.24444,51.177269],"type":"Point"}
}