{
  "type": "Feature",
  "properties": {
    "iso:country":"DE",
    "sg:address":"Bahnhofstr. 2",
    "sg:city":"Nagold",
    "sg:phone":"+49 7452/3266",
    "sg:postcode":"72202",
    "sg:province":"Baden-W\u00fcrttemberg",
    "wof:name":"Bahnh\u00f6fle",
    "wof:placetype":"venue"
},
  "geometry": {"coordinates":[8.7250623703,48.5505561829],"type":"Point"}
}