{
  "type": "Feature",
  "properties": {
    "iso:country":"DE",
    "sg:address":"Bleifelder Str. 45",
    "sg:city":"R\u00f6srath",
    "sg:phone":"+49 2205/83018",
    "sg:postcode":"51503",
    "sg:province":"Nordrhein-Westfalen",
    "wof:name":"Edelbert L\u00fcck Ingenieur",
    "wof:placetype":"venue"
},
  "geometry": {"coordinates":[7.2135868073,50.9151687622],"type":"Point"}
}