{
  "type": "Feature",
  "properties": {
    "iso:country":"DE",
    "sg:address":"In der R\u00f6dersbach 25",
    "sg:city":"Neu-Anspach",
    "sg:phone":"+49 6081/8425",
    "sg:postcode":"61267",
    "sg:province":"Hessen",
    "wof:name":"Richard Halling Ingenieur",
    "wof:placetype":"venue"
},
  "geometry": {"coordinates":[8.4985704422,50.3210334778],"type":"Point"}
}