{
  "type": "Feature",
  "properties": {
    "iso:country":"DE",
    "sg:address":"B\u00fcrgerm.-Schmidt-Str. 11",
    "sg:city":"Burscheid",
    "sg:phone":"+49 2174/5235",
    "sg:postcode":"51399",
    "sg:province":"Nordrhein-Westfalen",
    "wof:name":"Treffpunkt",
    "wof:placetype":"venue"
},
  "geometry": {"coordinates":[7.1172528267,51.0814552307],"type":"Point"}
}