{
  "type": "Feature",
  "properties": {
    "iso:country":"DE",
    "sg:address":"Im Sachsenlager 16",
    "sg:city":"Frankfurt",
    "sg:phone":"+49 69/590345",
    "sg:postcode":"60322",
    "sg:province":"Hessen",
    "wof:name":"Wolfgang G. Sommer Immobilienmakler",
    "wof:placetype":"venue"
},
  "geometry": {"coordinates":[8.6751184464,50.1203041077],"type":"Point"}
}