{
  "type": "Feature",
  "properties": {
    "iso:country":"DE",
    "sg:address":"Gerstottstr. 22",
    "sg:city":"F\u00fcrstenwalde",
    "sg:postcode":"15517",
    "sg:province":"Brandenburg",
    "wof:name":"I & B Gastst\u00e4ttenbetriebs Gmbh",
    "wof:placetype":"venue"
},
  "geometry": {"coordinates":[14.0613393784,52.3574714661],"type":"Point"}
}