{
  "type": "Feature",
  "properties": {
    "iso:country":"DE",
    "sg:address":"M\u00fctzendorpsteed 32 / 32 A",
    "sg:city":"Hamburg",
    "sg:phone":"+49 40/6412022",
    "sg:postcode":"22179",
    "sg:province":"Hamburg",
    "wof:name":"Burmeister Bendel Gmbh",
    "wof:placetype":"venue"
},
  "geometry": {"coordinates":[10.082208,53.615803],"type":"Point"}
}