{
  "type": "Feature",
  "properties": {
    "iso:country":"DE",
    "sg:address":"Postfach 101307:: 30834 Langenhagen:: Germany.^^Sch\u00fctzenstr 2::",
    "sg:city":"Langenhagen",
    "sg:postcode":"30853",
    "sg:province":"Niedersachsen",
    "wof:name":"Agv Anlagen-und Grundst\u00fccksvermietungsgesellschaft Mbh & Co Kg",
    "wof:placetype":"venue"
},
  "geometry": {"coordinates":[8.242325,50.08456],"type":"Point"}
}