{
  "type": "Feature",
  "properties": {
    "iso:country":"DE",
    "sg:address":"Br\u00fcckenstr. 7",
    "sg:city":"Georgenthal",
    "sg:phone":"+49 36253/25341",
    "sg:postcode":"99887",
    "sg:province":"Th\u00fcringen",
    "wof:name":"Bruno Weber",
    "wof:placetype":"venue"
},
  "geometry": {"coordinates":[10.665432,50.831398],"type":"Point"}
}