{
  "type": "Feature",
  "properties": {
    "iso:country":"DE",
    "sg:address":"Schwarzwaldstr. 5",
    "sg:city":"Heppenheim",
    "sg:phone":"+49 6252/7020",
    "sg:postcode":"64646",
    "sg:province":"Hessen",
    "wof:name":"Jungheinrich Ag",
    "wof:placetype":"venue"
},
  "geometry": {"coordinates":[8.6120624542,49.6398849487],"type":"Point"}
}