{
  "type": "Feature",
  "properties": {
    "iso:country":"DE",
    "sg:address":"Amelogenstr. 1-3",
    "sg:city":"Diepholz",
    "sg:phone":"+49 4954/419030",
    "sg:postcode":"49356",
    "sg:province":"Niedersachsen",
    "wof:name":"Stadtwerke Evb Huntetal Gmbh",
    "wof:placetype":"venue"
},
  "geometry": {"coordinates":[8.374659,52.612038],"type":"Point"}
}