{
  "type": "Feature",
  "properties": {
    "iso:country":"DE",
    "sg:address":"Buchberg 90",
    "sg:city":"Siemerode",
    "sg:phone":"+49 3606/614447",
    "sg:postcode":"37308",
    "sg:province":"Th\u00fcringen",
    "wof:name":"Heinfried G\u00fcnther",
    "wof:placetype":"venue"
},
  "geometry": {"coordinates":[10.1175813675,51.4242744446],"type":"Point"}
}