{
  "type": "Feature",
  "properties": {
    "iso:country":"DE",
    "sg:address":"Gartenstr. 71",
    "sg:city":"Bruchweiler-B\u00e4renbach",
    "sg:phone":"+49 6394/5439",
    "sg:postcode":"76891",
    "sg:province":"Rheinland-Pfalz",
    "wof:name":"Metz Gmbh",
    "wof:placetype":"venue"
},
  "geometry": {"coordinates":[7.7998261452,49.1086502075],"type":"Point"}
}