{
  "type": "Feature",
  "properties": {
    "iso:country":"DE",
    "sg:address":"Br\u00fcckenstr. 1",
    "sg:city":"Neumagen-Dhron",
    "sg:phone":"+49 6507/5317",
    "sg:postcode":"54347",
    "sg:province":"Rheinland-Pfalz",
    "wof:name":"Stephan Kohl",
    "wof:placetype":"venue"
},
  "geometry": {"coordinates":[6.9067440033,49.8633728027],"type":"Point"}
}