{
  "type": "Feature",
  "properties": {
    "iso:country":"DE",
    "sg:address":"Am Sternanger 1",
    "sg:city":"Benediktbeuern",
    "sg:phone":"+49 8857/9027",
    "sg:postcode":"83671",
    "sg:province":"Bayern",
    "wof:name":"J\u00fcrgen Taube Steuerbevollm\u00e4chtigter",
    "wof:placetype":"venue"
},
  "geometry": {"coordinates":[11.4112052917,47.7074661255],"type":"Point"}
}