{
  "type": "Feature",
  "properties": {
    "iso:country":"DE",
    "sg:address":"Langenbergstr. 6",
    "sg:city":"Steinau",
    "sg:phone":"+49 6663/6610",
    "sg:postcode":"36396",
    "sg:province":"Hessen",
    "wof:name":"M. Beyer",
    "wof:placetype":"venue"
},
  "geometry": {"coordinates":[9.4519290924,50.3100776672],"type":"Point"}
}