{
  "type": "Feature",
  "properties": {
    "iso:country":"DE",
    "sg:address":"Deisterstr. 60",
    "sg:city":"Lauenau",
    "sg:phone":"+49 5043/1476",
    "sg:postcode":"31867",
    "sg:province":"Niedersachsen",
    "wof:name":"Rickenberg & Parno Gmbh",
    "wof:placetype":"venue"
},
  "geometry": {"coordinates":[9.3930950165,52.2848167419],"type":"Point"}
}