{
  "type": "Feature",
  "properties": {
    "iso:country":"DE",
    "sg:address":"Hauptstr. 9",
    "sg:city":"Wendelstein",
    "sg:phone":"+49 9129/6165",
    "sg:postcode":"90530",
    "sg:province":"Bayern",
    "wof:name":"T. Zwillich",
    "wof:placetype":"venue"
},
  "geometry": {"coordinates":[11.142108,49.355202],"type":"Point"}
}