{
  "type": "Feature",
  "properties": {
    "iso:country":"DE",
    "sg:address":"Wiesdorfer Platz 41",
    "sg:city":"Leverkusen",
    "sg:phone":"+49 214/45187",
    "sg:postcode":"51373",
    "sg:province":"Nordrhein-Westfalen",
    "wof:name":"H. G. Sch\u00f6nenberg",
    "wof:placetype":"venue"
},
  "geometry": {"coordinates":[6.9842920303,51.03175354],"type":"Point"}
}