{
  "type": "Feature",
  "properties": {
    "iso:country":"DE",
    "sg:address":"Schwedenweg 22",
    "sg:city":"Ebersberg",
    "sg:phone":"+49 8092/21780",
    "sg:postcode":"85560",
    "sg:province":"Bayern",
    "wof:name":"Ludwig Brunner Steuerberater",
    "wof:placetype":"venue"
},
  "geometry": {"coordinates":[11.9686346054,48.0735092163],"type":"Point"}
}