{
  "type": "Feature",
  "properties": {
    "iso:country":"DE",
    "sg:address":"Marienstr. 1",
    "sg:city":"Helmstedt",
    "sg:phone":"+49 5351/3518",
    "sg:postcode":"38350",
    "sg:province":"Niedersachsen",
    "wof:name":"Rolf Reineke",
    "wof:placetype":"venue"
},
  "geometry": {"coordinates":[11.0058498383,52.230381012],"type":"Point"}
}