{
  "type": "Feature",
  "properties": {
    "iso:country":"DE",
    "sg:address":"Jungstr. 25",
    "sg:city":"Bad Kreuznach",
    "sg:phone":"+49 671/28137",
    "sg:postcode":"55543",
    "sg:province":"Rheinland-Pfalz",
    "wof:name":"Otto Scherer Installation Sanit\u00e4re Anlagen",
    "wof:placetype":"venue"
},
  "geometry": {"coordinates":[7.8616290092,49.8397102356],"type":"Point"}
}