{
  "type": "Feature",
  "properties": {
    "iso:country":"DE",
    "sg:address":"Friedbergstr. 34",
    "sg:city":"Berlin",
    "sg:phone":"+49 30/3256784",
    "sg:postcode":"14057",
    "sg:province":"Berlin",
    "wof:name":"Werner Heinze Architekt",
    "wof:placetype":"venue"
},
  "geometry": {"coordinates":[13.293337,52.504055],"type":"Point"}
}