{
  "type": "Feature",
  "properties": {
    "iso:country":"DE",
    "sg:address":"Deutz-M\u00fclheimer Str. 216",
    "sg:city":"K\u00f6ln",
    "sg:phone":"+49 221/671160",
    "sg:postcode":"51063",
    "sg:province":"Nordrhein-Westfalen",
    "wof:name":"Khv K\u00f6lner Hausverwaltung Gmbh",
    "wof:placetype":"venue"
},
  "geometry": {"coordinates":[6.9938092232,50.956703186],"type":"Point"}
}