{
  "type": "Feature",
  "properties": {
    "iso:country":"DE",
    "sg:address":"Dorfstr. 28",
    "sg:city":"Poing",
    "sg:postcode":"85586",
    "sg:province":"Bayern",
    "wof:name":"Feuerwehrverein Angelbrechting Johann Hollerith",
    "wof:placetype":"venue"
},
  "geometry": {"coordinates":[11.8101549149,48.1579170227],"type":"Point"}
}