{
  "type": "Feature",
  "properties": {
    "iso:country":"DE",
    "sg:address":"Otterndorfer Str. 6",
    "sg:city":"Nordleda",
    "sg:phone":"+49 4758/455",
    "sg:postcode":"21765",
    "sg:province":"Niedersachsen",
    "wof:name":"Wilhelm Heinecke",
    "wof:placetype":"venue"
},
  "geometry": {"coordinates":[8.834728241,53.7631340027],"type":"Point"}
}