{
  "type": "Feature",
  "properties": {
    "iso:country":"DE",
    "sg:address":"Oskar-Messter-Str. 12",
    "sg:city":"Ismaning",
    "sg:phone":"+49 89/965722",
    "sg:postcode":"85737",
    "sg:province":"Bayern",
    "wof:name":"Reinhold Vogel Omnibusbetrieb Gmbh",
    "wof:placetype":"venue"
},
  "geometry": {"coordinates":[11.6797475815,48.2323417664],"type":"Point"}
}