{
  "type": "Feature",
  "properties": {
    "iso:country":"DE",
    "sg:address":"Am Lattenberge 4",
    "sg:city":"Denkte",
    "sg:phone":"+49 5337/1334",
    "sg:postcode":"38321",
    "sg:province":"Niedersachsen",
    "wof:name":"Friedrich Munte Gmbh",
    "wof:placetype":"venue"
},
  "geometry": {"coordinates":[10.6196746826,52.1245651245],"type":"Point"}
}