{
  "type": "Feature",
  "properties": {
    "iso:country":"DE",
    "sg:address":"Bellersheimer Str. 44",
    "sg:city":"Hungen",
    "sg:phone":"+49 6402/1297",
    "sg:postcode":"35410",
    "sg:province":"Hessen",
    "wof:name":"Helmut Erb Steuerberater",
    "wof:placetype":"venue"
},
  "geometry": {"coordinates":[8.8969573975,50.4471588135],"type":"Point"}
}