{
  "type": "Feature",
  "properties": {
    "iso:country":"DE",
    "sg:address":"Wernerstr. 61",
    "sg:city":"Stuttgart",
    "sg:phone":"+49 4971/1981760",
    "sg:postcode":"70469",
    "sg:province":"Baden-W\u00fcrttemberg",
    "wof:name":"Schneider Stuttgart Feuerverzinken Gmbh & Co. Kg",
    "wof:placetype":"venue"
},
  "geometry": {"coordinates":[9.167317,48.819096],"type":"Point"}
}