{
  "type": "Feature",
  "properties": {
    "iso:country":"DE",
    "sg:address":"Quedlinburger Str. 6",
    "sg:city":"Hoym",
    "sg:phone":"+49 34741/6340",
    "sg:postcode":"06467",
    "sg:province":"Sachsen-Anhalt",
    "wof:name":"Wilmar K\u00fchne",
    "wof:placetype":"venue"
},
  "geometry": {"coordinates":[11.3100681305,51.7822570801],"type":"Point"}
}