{
  "type": "Feature",
  "properties": {
    "iso:country":"DE",
    "sg:address":"Laubenstr. 13",
    "sg:city":"Ingolstadt",
    "sg:postcode":"85049",
    "sg:province":"Bayern",
    "wof:name":"B & G Elektrovertieb Gbr",
    "wof:placetype":"venue"
},
  "geometry": {"coordinates":[11.2774047852,48.765499115],"type":"Point"}
}