{
  "type": "Feature",
  "properties": {
    "iso:country":"DE",
    "sg:address":"Am Blaffertsberg 31+34",
    "sg:city":"Remscheid",
    "sg:phone":"+49 4921/9156250",
    "sg:postcode":"42899",
    "sg:province":"Nordrhein-Westfalen",
    "wof:name":"Picard & Birkenstock Kg",
    "wof:placetype":"venue"
},
  "geometry": {"coordinates":[7.2181901932,51.2205696106],"type":"Point"}
}