{
  "type": "Feature",
  "properties": {
    "iso:country":"DE",
    "sg:address":"G\u00e4nsheidestr. 37",
    "sg:city":"Stuttgart",
    "sg:postcode":"70184",
    "sg:province":"Baden-W\u00fcrttemberg",
    "wof:name":"W. E. R. T. Gmbh",
    "wof:placetype":"venue"
},
  "geometry": {"coordinates":[9.1949882507,48.7742004395],"type":"Point"}
}