{
  "type": "Feature",
  "properties": {
    "iso:country":"DE",
    "sg:address":"Karlstr. 4",
    "sg:city":"Donaueschingen",
    "sg:postcode":"78166",
    "sg:province":"Baden-W\u00fcrttemberg",
    "wof:name":"Studienkreis",
    "wof:placetype":"venue"
},
  "geometry": {"coordinates":[8.4960432053,47.9529418945],"type":"Point"}
}