{
  "type": "Feature",
  "properties": {
    "iso:country":"DE",
    "sg:address":"Bahnhofplatz 1",
    "sg:city":"Horb",
    "sg:phone":"+49 7451/5340",
    "sg:postcode":"72160",
    "sg:province":"Baden-W\u00fcrttemberg",
    "wof:name":"Deutsche Post Ag",
    "wof:placetype":"venue"
},
  "geometry": {"coordinates":[8.6906528473,48.442237854],"type":"Point"}
}