{
  "type": "Feature",
  "properties": {
    "iso:country":"DE",
    "sg:address":"Im Vogelsang 8",
    "sg:city":"Bad Liebenzell",
    "sg:phone":"+49 7052/1693",
    "sg:postcode":"75378",
    "sg:province":"Baden-W\u00fcrttemberg",
    "wof:name":"Gerda Haag-thierry",
    "wof:placetype":"venue"
},
  "geometry": {"coordinates":[8.8023042679,48.7589416504],"type":"Point"}
}