{
  "type": "Feature",
  "properties": {
    "iso:country":"DE",
    "sg:address":"Raestruper Str 9",
    "sg:city":"Warendorf",
    "sg:phone":"+49 2581/3130",
    "sg:postcode":"48231",
    "sg:province":"Nordrhein-Westfalen",
    "wof:name":"Hubert Buchwald",
    "wof:placetype":"venue"
},
  "geometry": {"coordinates":[7.973279,51.951477],"type":"Point"}
}