{
  "type": "Feature",
  "properties": {
    "iso:country":"DE",
    "sg:address":"Emerfeld 17",
    "sg:city":"Langenenslingen",
    "sg:postcode":"88515",
    "sg:province":"Baden-W\u00fcrttemberg",
    "wof:name":"Eckhard Biegel Heilpraktiker",
    "wof:placetype":"venue"
},
  "geometry": {"coordinates":[9.3787403107,48.1484909058],"type":"Point"}
}