{
  "type": "Feature",
  "properties": {
    "iso:country":"DE",
    "sg:address":"Hansapark 5",
    "sg:city":"Magdeburg",
    "sg:phone":"+49 391/6316218",
    "sg:postcode":"39116",
    "sg:province":"Sachsen-Anhalt",
    "wof:name":"Document Systems Magdeburg Gmbh",
    "wof:placetype":"venue"
},
  "geometry": {"coordinates":[11.5921764374,52.1027183533],"type":"Point"}
}