{
  "type": "Feature",
  "properties": {
    "iso:country":"DE",
    "sg:address":"Dorfstr. 36",
    "sg:city":"Pockau",
    "sg:phone":"+49 37360/36088",
    "sg:postcode":"09509",
    "sg:province":"Sachsen",
    "wof:name":"Volkmar K\u00f6hler",
    "wof:placetype":"venue"
},
  "geometry": {"coordinates":[13.242135,50.717892],"type":"Point"}
}