{
  "type": "Feature",
  "properties": {
    "iso:country":"DE",
    "sg:address":"Brucker Str. 27",
    "sg:city":"Emmering",
    "sg:phone":"+49 8141/92707",
    "sg:postcode":"82275",
    "sg:province":"Bayern",
    "wof:name":"Hans Kistler",
    "wof:placetype":"venue"
},
  "geometry": {"coordinates":[11.275044,48.178871],"type":"Point"}
}