{
  "type": "Feature",
  "properties": {
    "iso:country":"DE",
    "sg:address":"Osterstr. 11 A",
    "sg:city":"Barsinghausen",
    "sg:phone":"+49 5105/63815",
    "sg:postcode":"30890",
    "sg:province":"Niedersachsen",
    "wof:name":"Y. Balkis",
    "wof:placetype":"venue"
},
  "geometry": {"coordinates":[9.4674911499,52.3018341064],"type":"Point"}
}