{
  "type": "Feature",
  "properties": {
    "iso:country":"DE",
    "sg:address":"Fl\u00f6\u00dferplatz 9",
    "sg:city":"Kronach",
    "sg:phone":"+49 9261/3115",
    "sg:postcode":"96317",
    "sg:province":"Bayern",
    "wof:name":"A. Schmidt Textil Gmbh",
    "wof:placetype":"venue"
},
  "geometry": {"coordinates":[11.311518,50.213631],"type":"Point"}
}