{
  "type": "Feature",
  "properties": {
    "iso:country":"DE",
    "sg:address":"Warnower Str. 36",
    "sg:city":"Zernin",
    "sg:phone":"+49 4938/4628008",
    "sg:postcode":"18249",
    "sg:province":"Mecklenburg-Vorpommern",
    "wof:name":"Behn",
    "wof:placetype":"venue"
},
  "geometry": {"coordinates":[11.9213123322,53.7980728149],"type":"Point"}
}