{
  "type": "Feature",
  "properties": {
    "iso:country":"DE",
    "sg:address":"Kr\u00e4henbadstr. 54",
    "sg:city":"Alpirsbach",
    "sg:phone":"+49 7444/2826",
    "sg:postcode":"72275",
    "sg:province":"Baden-W\u00fcrttemberg",
    "wof:name":"Bierkeller",
    "wof:placetype":"venue"
},
  "geometry": {"coordinates":[8.3971996307,48.3436698914],"type":"Point"}
}