{
  "type": "Feature",
  "properties": {
    "iso:country":"DE",
    "sg:address":"Reichenaustr. 93",
    "sg:city":"Konstanz",
    "sg:phone":"+49 7531/284703",
    "sg:postcode":"78467",
    "sg:province":"Baden-W\u00fcrttemberg",
    "wof:name":"Entsorgungsbetriebe Der Stadt Konstanz",
    "wof:placetype":"venue"
},
  "geometry": {"coordinates":[9.1590652466,47.6730079651],"type":"Point"}
}