{
  "type": "Feature",
  "properties": {
    "iso:country":"DE",
    "sg:address":"Stanglm\u00fchle 1",
    "sg:city":"Wolnzach",
    "sg:phone":"+49 8442/3968",
    "sg:postcode":"85283",
    "sg:province":"Bayern",
    "wof:name":"Karl Maier",
    "wof:placetype":"venue"
},
  "geometry": {"coordinates":[11.627303,48.60363],"type":"Point"}
}