{
  "type": "Feature",
  "properties": {
    "iso:country":"DE",
    "sg:address":"Neuer Wandrahm 1",
    "sg:city":"Hamburg",
    "sg:phone":"+49 40/336214",
    "sg:postcode":"20457",
    "sg:province":"Hamburg",
    "wof:name":"Bartheidel & Timm Gmbh",
    "wof:placetype":"venue"
},
  "geometry": {"coordinates":[9.996875,53.545448],"type":"Point"}
}