{
  "type": "Feature",
  "properties": {
    "iso:country":"DE",
    "sg:address":"Wei\u00dfm\u00fchlenweg 17",
    "sg:city":"Ellefeld",
    "sg:phone":"+49 4975/833729",
    "sg:postcode":"08236",
    "sg:province":"Sachsen",
    "wof:name":"Albert Widmann",
    "wof:placetype":"venue"
},
  "geometry": {"coordinates":[9.663061142,48.0039672852],"type":"Point"}
}