{
  "type": "Feature",
  "properties": {
    "iso:country":"DE",
    "sg:address":"Gutenbergstr. 19",
    "sg:city":"Neus\u00e4\u00df",
    "sg:phone":"+49 821/463024",
    "sg:postcode":"86356",
    "sg:province":"Bayern",
    "wof:name":"Heizungs-schmid Gmbh",
    "wof:placetype":"venue"
},
  "geometry": {"coordinates":[10.827017,48.397472],"type":"Point"}
}