{
  "type": "Feature",
  "properties": {
    "iso:country":"DE",
    "sg:address":"Schulstr. 26",
    "sg:city":"Burgthann",
    "sg:phone":"+49 9188/905320",
    "sg:postcode":"90559",
    "sg:province":"Bayern",
    "wof:name":"Heba-tec Gmbh Polymer-engineering",
    "wof:placetype":"venue"
},
  "geometry": {"coordinates":[11.34567,49.325161],"type":"Point"}
}