{
  "type": "Feature",
  "properties": {
    "iso:country":"DE",
    "sg:address":"R\u00fcckertstr. 2",
    "sg:city":"Potsdam",
    "sg:postcode":"14469",
    "sg:province":"Brandenburg",
    "wof:name":"Meet B Gesellschaft F\u00fcr Medizintechnik Mbh",
    "wof:placetype":"venue"
},
  "geometry": {"coordinates":[13.006737709,52.4299583435],"type":"Point"}
}