{
  "type": "Feature",
  "properties": {
    "iso:country":"DE",
    "sg:address":"Elisabethstr. 17",
    "sg:city":"G\u00f6rlitz",
    "sg:phone":"+49 3581/403540",
    "sg:postcode":"02826",
    "sg:province":"Sachsen",
    "wof:name":"Frank Leiniger",
    "wof:placetype":"venue"
},
  "geometry": {"coordinates":[14.9903278351,51.1545295715],"type":"Point"}
}