{
  "type": "Feature",
  "properties": {
    "iso:country":"DE",
    "sg:address":"Stadtplatz 32",
    "sg:city":"Vilshofen",
    "sg:phone":"+49 8541/3071",
    "sg:postcode":"94474",
    "sg:province":"Bayern",
    "wof:name":"Stadt-apotheke",
    "wof:placetype":"venue"
},
  "geometry": {"coordinates":[13.194676,48.593548],"type":"Point"}
}