{
  "type": "Feature",
  "properties": {
    "iso:country":"DE",
    "sg:address":"Maxstr. 31",
    "sg:city":"F\u00fcrth",
    "sg:phone":"+49 911/7498681",
    "sg:postcode":"90762",
    "sg:province":"Bayern",
    "wof:name":"Einmaleins Software Gmbh",
    "wof:placetype":"venue"
},
  "geometry": {"coordinates":[10.9896306992,49.4713554382],"type":"Point"}
}