{
  "type": "Feature",
  "properties": {
    "iso:country":"DE",
    "sg:address":"Marienberger Str. 57",
    "sg:city":"Wolkenstein",
    "sg:phone":"+49 4937/3691370",
    "sg:postcode":"09429",
    "sg:province":"Sachsen",
    "wof:name":"Sachsenland Fruchtquell Gmbh",
    "wof:placetype":"venue"
},
  "geometry": {"coordinates":[13.075873,50.653858],"type":"Point"}
}