{
  "type": "Feature",
  "properties": {
    "iso:country":"DE",
    "sg:address":"Von-Lilien-Str. 9",
    "sg:city":"Arnsberg",
    "sg:phone":"+49 2932/33961",
    "sg:postcode":"59759",
    "sg:province":"Nordrhein-Westfalen",
    "wof:name":"W. L\u00fcbke Fruchtmarkt Sauerland Gmbh",
    "wof:placetype":"venue"
},
  "geometry": {"coordinates":[7.9772129059,51.4358825684],"type":"Point"}
}