{
  "type": "Feature",
  "properties": {
    "iso:country":"DE",
    "sg:address":"Heinrichstra\u00dfe 2",
    "sg:city":"Bad Oeynhausen",
    "sg:phone":"+49 5731/20018",
    "sg:postcode":"32545",
    "sg:province":"Nordrhein-Westfalen",
    "wof:name":"First Eroscape - Pheromone",
    "wof:placetype":"venue"
},
  "geometry": {"coordinates":[8.8037910461,52.204410553],"type":"Point"}
}