{
  "type": "Feature",
  "properties": {
    "iso:country":"DE",
    "sg:address":"Waldstr. 31",
    "sg:city":"Appenweier",
    "sg:phone":"+49 7805/795",
    "sg:postcode":"77767",
    "sg:province":"Baden-W\u00fcrttemberg",
    "wof:name":"Friedrich K\u00f6nig",
    "wof:placetype":"venue"
},
  "geometry": {"coordinates":[7.970374,48.568455],"type":"Point"}
}