{
  "type": "Feature",
  "properties": {
    "iso:country":"DE",
    "sg:address":"Mainzer Landstr. 46",
    "sg:city":"Frankfurt",
    "sg:postcode":"60325",
    "sg:province":"Hessen",
    "wof:name":"Westlaw Datenbank Gmbh",
    "wof:placetype":"venue"
},
  "geometry": {"coordinates":[8.663898468,50.1109809875],"type":"Point"}
}