{
  "type": "Feature",
  "properties": {
    "iso:country":"DE",
    "sg:address":"Im Schierholz 2",
    "sg:city":"Porta Westfalica",
    "sg:phone":"+49 5706/3761",
    "sg:postcode":"32457",
    "sg:province":"Nordrhein-Westfalen",
    "wof:name":"Ernst Steffen",
    "wof:placetype":"venue"
},
  "geometry": {"coordinates":[8.932801,52.20546],"type":"Point"}
}