{
  "type": "Feature",
  "properties": {
    "iso:country":"DE",
    "sg:address":"Roteichenring 1",
    "sg:city":"Mannheim",
    "sg:phone":"+49 621/303131",
    "sg:postcode":"68167",
    "sg:province":"Baden-W\u00fcrttemberg",
    "wof:name":"Rekord Versicherungs- Vermittlung Und Betreuungsges.",
    "wof:placetype":"venue"
},
  "geometry": {"coordinates":[8.4924449921,49.5066757202],"type":"Point"}
}