{
  "type": "Feature",
  "properties": {
    "iso:country":"DE",
    "sg:address":"Hirtenweg 19",
    "sg:city":"Seefeld",
    "sg:phone":"+49 8152/9797",
    "sg:postcode":"82229",
    "sg:province":"Bayern",
    "wof:name":"Combyte Gmbh Seite1",
    "wof:placetype":"venue"
},
  "geometry": {"coordinates":[11.190323,48.040104],"type":"Point"}
}