{
  "type": "Feature",
  "properties": {
    "iso:country":"DE",
    "sg:address":"Feauxweg 8",
    "sg:city":"Arnsberg",
    "sg:postcode":"59821",
    "sg:province":"Nordrhein-Westfalen",
    "wof:name":"Focus Gmbh",
    "wof:placetype":"venue"
},
  "geometry": {"coordinates":[8.06782,51.394058],"type":"Point"}
}