{
  "type": "Feature",
  "properties": {
    "iso:country":"DE",
    "sg:address":"Hoher Weg 2",
    "sg:city":"Hohenhameln",
    "sg:phone":"+49 5128/7159",
    "sg:postcode":"31249",
    "sg:province":"Niedersachsen",
    "wof:name":"H. Frees Jun.",
    "wof:placetype":"venue"
},
  "geometry": {"coordinates":[10.0710735321,52.2595672607],"type":"Point"}
}