{
  "type": "Feature",
  "properties": {
    "iso:country":"DE",
    "sg:address":"Ratzeburger Str. 16",
    "sg:city":"Berkenthin",
    "sg:phone":"+49 4544/329",
    "sg:postcode":"23919",
    "sg:province":"Schleswig-Holstein",
    "wof:name":"Carl Hack",
    "wof:placetype":"venue"
},
  "geometry": {"coordinates":[10.6507921219,53.7325744629],"type":"Point"}
}