{
  "type": "Feature",
  "properties": {
    "iso:country":"DE",
    "sg:address":"Im Wingert 20",
    "sg:city":"Bonn",
    "sg:phone":"+49 228/212348",
    "sg:postcode":"53115",
    "sg:province":"Nordrhein-Westfalen",
    "wof:name":"Aral Ag",
    "wof:placetype":"venue"
},
  "geometry": {"coordinates":[7.0915269852,50.7180633545],"type":"Point"}
}