{
  "type": "Feature",
  "properties": {
    "iso:country":"DE",
    "sg:address":"D\u00f6nhoffstr. 13",
    "sg:city":"Solingen",
    "sg:phone":"+49 212/208655",
    "sg:postcode":"42655",
    "sg:province":"Nordrhein-Westfalen",
    "wof:name":"Gl\u00e4tzer Gmbh",
    "wof:placetype":"venue"
},
  "geometry": {"coordinates":[7.0680661201,51.173374176],"type":"Point"}
}