{
  "type": "Feature",
  "properties": {
    "iso:country":"DE",
    "sg:address":"Rudolfstr. 26",
    "sg:city":"Stolberg",
    "sg:phone":"+49 2402/37005",
    "sg:postcode":"52223",
    "sg:province":"Nordrhein-Westfalen",
    "wof:name":"Horst Koser Finanzberater",
    "wof:placetype":"venue"
},
  "geometry": {"coordinates":[6.2161011696,50.7353286743],"type":"Point"}
}