{
  "type": "Feature",
  "properties": {
    "iso:country":"DE",
    "sg:address":"Oderlandstr. 22",
    "sg:city":"Eisenh\u00fcttenstadt",
    "sg:postcode":"15890",
    "sg:province":"Brandenburg",
    "wof:name":"Ffw Beteiligungs Gmbh",
    "wof:placetype":"venue"
},
  "geometry": {"coordinates":[14.650673,52.146103],"type":"Point"}
}