{
  "type": "Feature",
  "properties": {
    "iso:country":"DE",
    "sg:address":"Wendh\u00e4user Weg 6c",
    "sg:city":"Braunschweig",
    "sg:phone":"+49 5309/1997",
    "sg:postcode":"38108",
    "sg:province":"Niedersachsen",
    "wof:name":"Eisler Baumschule",
    "wof:placetype":"venue"
},
  "geometry": {"coordinates":[10.608201,52.306221],"type":"Point"}
}