{
  "type": "Feature",
  "properties": {
    "iso:country":"DE",
    "sg:address":"Crellestr. 48",
    "sg:city":"Berlin",
    "sg:phone":"+49 30/78702601",
    "sg:postcode":"10827",
    "sg:province":"Berlin",
    "wof:name":"Fahrrad B\u00fcro",
    "wof:placetype":"venue"
},
  "geometry": {"coordinates":[13.357954,52.486977],"type":"Point"}
}