{
  "type": "Feature",
  "properties": {
    "iso:country":"DE",
    "sg:address":"Altenhof",
    "sg:city":"Altenhof",
    "sg:postcode":"24340",
    "sg:province":"Schleswig-Holstein",
    "wof:name":"Computer-partner Infor- Mationssysteme Gmbh",
    "wof:placetype":"venue"
},
  "geometry": {"coordinates":[9.8763904572,54.4346733093],"type":"Point"}
}