{
  "type": "Feature",
  "properties": {
    "iso:country":"DE",
    "sg:address":"Gerhard-Rohlfs-Str. 62",
    "sg:city":"Bremen",
    "sg:phone":"+49 421/6588762",
    "sg:postcode":"28757",
    "sg:province":"Bremen",
    "wof:name":"M\u00f6bel-fundgrube",
    "wof:placetype":"venue"
},
  "geometry": {"coordinates":[8.616413,53.173359],"type":"Point"}
}