{
  "type": "Feature",
  "properties": {
    "iso:country":"DE",
    "sg:address":"Hindenburgstr. 16",
    "sg:city":"Wunstorf",
    "sg:phone":"+49 5031/913081",
    "sg:postcode":"31515",
    "sg:province":"Niedersachsen",
    "wof:name":"Siemer",
    "wof:placetype":"venue"
},
  "geometry": {"coordinates":[9.435318,52.423969],"type":"Point"}
}