{
  "type": "Feature",
  "properties": {
    "iso:country":"DE",
    "sg:address":"Van-Ronzelen-Str.",
    "sg:city":"Bremerhaven",
    "sg:phone":"+49 471/23277",
    "sg:postcode":"27568",
    "sg:province":"Bremen",
    "wof:name":"Volker Carstens Grundst\u00fccks- Verwaltungs-gmbh",
    "wof:placetype":"venue"
},
  "geometry": {"coordinates":[8.5799303055,53.5385551453],"type":"Point"}
}