{
  "type": "Feature",
  "properties": {
    "iso:country":"DE",
    "sg:address":"Sperberstr. 23",
    "sg:city":"Gelsenkirchen",
    "sg:phone":"+49 4920/9390446",
    "sg:postcode":"45894",
    "sg:province":"Nordrhein-Westfalen",
    "wof:name":"Madera Otto Simon Gmbh",
    "wof:placetype":"venue"
},
  "geometry": {"coordinates":[7.0365781784,51.5854492188],"type":"Point"}
}