{
  "type": "Feature",
  "properties": {
    "iso:country":"DE",
    "sg:address":"Lange Str. 89",
    "sg:city":"Delmenhorst",
    "sg:phone":"+49 4221/18659",
    "sg:postcode":"27749",
    "sg:province":"Niedersachsen",
    "wof:name":"Jean Pascale Sportswear",
    "wof:placetype":"venue"
},
  "geometry": {"coordinates":[8.631969,53.048893],"type":"Point"}
}