{
  "type": "Feature",
  "properties": {
    "iso:country":"DE",
    "sg:address":"Freiherr-vom-Stein-Str. 204 a",
    "sg:city":"Essen",
    "sg:phone":"+49 201/440702",
    "sg:postcode":"45133",
    "sg:province":"Nordrhein-Westfalen",
    "wof:name":"Skowronnek",
    "wof:placetype":"venue"
},
  "geometry": {"coordinates":[7.0067749023,51.4026947021],"type":"Point"}
}