{
  "type": "Feature",
  "properties": {
    "iso:country":"DE",
    "sg:address":"Nedderfeldstr. 6",
    "sg:city":"Hannover",
    "sg:postcode":"30451",
    "sg:province":"Niedersachsen",
    "wof:name":"Estrella Gastronomiebetriebe Gmbh",
    "wof:placetype":"venue"
},
  "geometry": {"coordinates":[9.709066391,52.3735198975],"type":"Point"}
}