{
  "type": "Feature",
  "properties": {
    "iso:country":"DE",
    "sg:address":"Markt",
    "sg:city":"Kr\u00f6pelin",
    "sg:phone":"+49 38292/229",
    "sg:postcode":"18236",
    "sg:province":"Mecklenburg-Vorpommern",
    "wof:name":"Dobra Doberaner Handelsgesellschaft",
    "wof:placetype":"venue"
},
  "geometry": {"coordinates":[11.794439,54.071102],"type":"Point"}
}