{
  "type": "Feature",
  "properties": {
    "iso:country":"DE",
    "sg:address":"Gerhart-Hauptmann-Str. 37",
    "sg:city":"Oberderdingen",
    "sg:phone":"+49 7045/3061",
    "sg:postcode":"75038",
    "sg:province":"Baden-W\u00fcrttemberg",
    "wof:name":"Walter Esslinger Architekt",
    "wof:placetype":"venue"
},
  "geometry": {"coordinates":[8.799811,49.067074],"type":"Point"}
}