{
  "type": "Feature",
  "properties": {
    "iso:country":"DE",
    "sg:address":"Gewerbestr. 4",
    "sg:city":"Elchingen",
    "sg:phone":"+49 7308/7522",
    "sg:postcode":"89275",
    "sg:province":"Bayern",
    "wof:name":"Bauspenglerei Reinhold Huber Verwaltungs Gmbh",
    "wof:placetype":"venue"
},
  "geometry": {"coordinates":[10.1024827957,48.4516563416],"type":"Point"}
}