{
  "type": "Feature",
  "properties": {
    "iso:country":"DE",
    "sg:city":"Gera",
    "sg:postcode":"07551",
    "sg:province":"Th\u00fcringen",
    "wof:name":"Sl-show-express Stefan Lehner",
    "wof:placetype":"venue"
},
  "geometry": {"coordinates":[12.09676,50.842812],"type":"Point"}
}