{
  "type": "Feature",
  "properties": {
    "iso:country":"DE",
    "sg:address":"Obere Hauptstr. 9",
    "sg:city":"Au",
    "sg:phone":"+49 8752/7263",
    "sg:postcode":"84072",
    "sg:province":"Bayern",
    "wof:name":"Carisma Damen Und Herren Friseur Margit Gantner E.k.",
    "wof:placetype":"venue"
},
  "geometry": {"coordinates":[11.7446203232,48.5573196411],"type":"Point"}
}