{
  "type": "Feature",
  "properties": {
    "iso:country":"DE",
    "sg:address":"Am Kalkofen 2",
    "sg:city":"Spangdahlem",
    "sg:phone":"+49 6565/4626",
    "sg:postcode":"54529",
    "sg:province":"Rheinland-Pfalz",
    "wof:name":"Zur Postkutsche",
    "wof:placetype":"venue"
},
  "geometry": {"coordinates":[6.6802549362,49.9863700867],"type":"Point"}
}