{
  "type": "Feature",
  "properties": {
    "iso:country":"DE",
    "sg:address":"Im Siebenswinkel 15",
    "sg:city":"Meckenheim",
    "sg:phone":"+49 2225/15808",
    "sg:postcode":"53340",
    "sg:province":"Nordrhein-Westfalen",
    "wof:name":"R. Mertens",
    "wof:placetype":"venue"
},
  "geometry": {"coordinates":[7.012141,50.625496],"type":"Point"}
}