{
  "type": "Feature",
  "properties": {
    "iso:country":"DE",
    "sg:address":"Holzkamp",
    "sg:city":"Itzehoe",
    "sg:postcode":"25524",
    "sg:province":"Schleswig-Holstein",
    "wof:name":"Max",
    "wof:placetype":"venue"
},
  "geometry": {"coordinates":[9.5229482651,53.9235801697],"type":"Point"}
}