{
  "type": "Feature",
  "properties": {
    "iso:country":"DE",
    "sg:address":"Kirchdorfer Str. 163",
    "sg:city":"Hamburg",
    "sg:phone":"+49 40/751497",
    "sg:postcode":"21109",
    "sg:province":"Hamburg",
    "wof:name":"Museum Der Elbinsel Wilhelmsburg",
    "wof:placetype":"venue"
},
  "geometry": {"coordinates":[10.017679,53.488056],"type":"Point"}
}