{
  "type": "Feature",
  "properties": {
    "iso:country":"DE",
    "sg:address":"Nienhausenstr. 43",
    "sg:city":"Gelsenkirchen",
    "sg:phone":"+49 209/44487",
    "sg:postcode":"45883",
    "sg:province":"Nordrhein-Westfalen",
    "wof:name":"Waldhaus Gastst\u00e4tten Gmbh",
    "wof:placetype":"venue"
},
  "geometry": {"coordinates":[7.0618891716,51.5030632019],"type":"Point"}
}