{
  "type": "Feature",
  "properties": {
    "iso:country":"DE",
    "sg:address":"Eurener Str 1",
    "sg:city":"Trier",
    "sg:phone":"+49 651/810050",
    "sg:postcode":"54294",
    "sg:province":"Rheinland-Pfalz",
    "wof:name":"F. J. Meyer Gmbh & Co Kg",
    "wof:placetype":"venue"
},
  "geometry": {"coordinates":[6.621414,49.751286],"type":"Point"}
}