{
  "type": "Feature",
  "properties": {
    "iso:country":"DE",
    "sg:address":"Siemensstr. 11",
    "sg:city":"Bad Friedrichshall",
    "sg:phone":"+49 7136/95500",
    "sg:postcode":"74177",
    "sg:province":"Baden-W\u00fcrttemberg",
    "wof:name":"Wagner Gmbh",
    "wof:placetype":"venue"
},
  "geometry": {"coordinates":[9.217412,49.235523],"type":"Point"}
}