{
  "type": "Feature",
  "properties": {
    "iso:country":"DE",
    "sg:address":"W\u00e4chtersbacher Str. 83",
    "sg:city":"Frankfurt",
    "sg:phone":"+49 69/40820",
    "sg:postcode":"60386",
    "sg:province":"Hessen",
    "wof:name":"Dr. Arthur Pfungst-stiftung",
    "wof:placetype":"venue"
},
  "geometry": {"coordinates":[8.7483081818,50.1321716309],"type":"Point"}
}