{
  "type": "Feature",
  "properties": {
    "iso:country":"DE",
    "sg:address":"Sleipnerstr. 15",
    "sg:city":"Berlin",
    "sg:phone":"+49 30/4714007",
    "sg:postcode":"13089",
    "sg:province":"Berlin",
    "wof:name":"Peter B\u00f6ttcher",
    "wof:placetype":"venue"
},
  "geometry": {"coordinates":[13.4364776611,52.5760154724],"type":"Point"}
}