{
  "type": "Feature",
  "properties": {
    "iso:country":"DE",
    "sg:address":"Ohlenbach",
    "sg:city":"Schmallenberg",
    "sg:phone":"+49 2977/359",
    "sg:postcode":"57392",
    "sg:province":"Nordrhein-Westfalen",
    "wof:name":"Pension Maria Albers",
    "wof:placetype":"venue"
},
  "geometry": {"coordinates":[8.4403591156,51.1639518738],"type":"Point"}
}