{
  "type": "Feature",
  "properties": {
    "iso:country":"DE",
    "sg:address":"H\u00fcttenstr. 2",
    "sg:city":"Kaufbeuren",
    "sg:phone":"+49 8341/96300",
    "sg:postcode":"87600",
    "sg:province":"Bayern",
    "wof:name":"Rosemarie Basl Steuerberaterin",
    "wof:placetype":"venue"
},
  "geometry": {"coordinates":[10.6346921921,47.9124755859],"type":"Point"}
}