{
  "type": "Feature",
  "properties": {
    "iso:country":"DE",
    "sg:address":"Georgstr. 8",
    "sg:city":"Meiningen",
    "sg:phone":"+49 3693/44210",
    "sg:postcode":"98617",
    "sg:province":"Th\u00fcringen",
    "wof:name":"Pension Pelzer",
    "wof:placetype":"venue"
},
  "geometry": {"coordinates":[10.4154062271,50.5697288513],"type":"Point"}
}