{
  "type": "Feature",
  "properties": {
    "iso:country":"DE",
    "sg:address":"Glattbacher Str. 43",
    "sg:city":"Aschaffenburg",
    "sg:phone":"+49 6021/42640",
    "sg:postcode":"63741",
    "sg:province":"Bayern",
    "wof:name":"Teleaktiv Achim Ludwig Otto",
    "wof:placetype":"venue"
},
  "geometry": {"coordinates":[9.148633,49.985638],"type":"Point"}
}