{
  "type": "Feature",
  "properties": {
    "iso:country":"DE",
    "sg:address":"Oberer Rainweg",
    "sg:city":"Heidelberg",
    "sg:phone":"+49 6221/803109",
    "sg:postcode":"69118",
    "sg:province":"Baden-W\u00fcrttemberg",
    "wof:name":"Hallenbad K\u00f6pfl",
    "wof:placetype":"venue"
},
  "geometry": {"coordinates":[8.7436742783,49.4238128662],"type":"Point"}
}