{
  "type": "Feature",
  "properties": {
    "iso:country":"DE",
    "sg:address":"Kronacher Str. 4",
    "sg:city":"Naila",
    "sg:postcode":"95119",
    "sg:province":"Bayern",
    "wof:name":"Fuchs Immobilien Gmbh & Co. Objektges. Mockritzer Str. 4-",
    "wof:placetype":"venue"
},
  "geometry": {"coordinates":[11.7076663971,50.3284111023],"type":"Point"}
}