{
  "type": "Feature",
  "properties": {
    "iso:country":"DE",
    "sg:address":"Friedenstr. 2",
    "sg:city":"M\u00fcnchen",
    "sg:phone":"+49 89/491939",
    "sg:postcode":"81671",
    "sg:province":"Bayern",
    "wof:name":"Copien & Wranka Zahntechnik Gmbh",
    "wof:placetype":"venue"
},
  "geometry": {"coordinates":[11.602606,48.123997],"type":"Point"}
}