{
  "type": "Feature",
  "properties": {
    "iso:country":"DE",
    "sg:address":"Rh\u00f6nstr. 51",
    "sg:city":"Frankfurt",
    "sg:phone":"+49 69/497179",
    "sg:postcode":"60316",
    "sg:province":"Hessen",
    "wof:name":"Gerhard Michler Verlag",
    "wof:placetype":"venue"
},
  "geometry": {"coordinates":[8.7071552277,50.1167831421],"type":"Point"}
}