{
  "type": "Feature",
  "properties": {
    "iso:country":"DE",
    "sg:address":"Stadtstr. 31",
    "sg:city":"Burgau",
    "sg:phone":"+49 8222/42560",
    "sg:postcode":"89331",
    "sg:province":"Bayern",
    "wof:name":"S. Ernst",
    "wof:placetype":"venue"
},
  "geometry": {"coordinates":[10.408466,48.431004],"type":"Point"}
}