{
  "type": "Feature",
  "properties": {
    "iso:country":"DE",
    "sg:address":"Marienkirchstr. 3",
    "sg:city":"St. Augustin",
    "sg:phone":"+49 2241/21032",
    "sg:postcode":"53757",
    "sg:province":"Nordrhein-Westfalen",
    "wof:name":"Kreissparkasse In Siegburg",
    "wof:placetype":"venue"
},
  "geometry": {"coordinates":[7.185953,50.770649],"type":"Point"}
}