{
  "type": "Feature",
  "properties": {
    "iso:country":"DE",
    "sg:address":"Wassermannstr. 52",
    "sg:city":"Berlin",
    "sg:postcode":"12489",
    "sg:province":"Berlin",
    "wof:name":"Md Info Online-dienst Verwaltungs-gmbh",
    "wof:placetype":"venue"
},
  "geometry": {"coordinates":[13.549554,52.441303],"type":"Point"}
}