{
  "type": "Feature",
  "properties": {
    "iso:country":"DE",
    "sg:address":"Waldstr 5",
    "sg:city":"Berlin",
    "sg:phone":"+49 30/6566700",
    "sg:postcode":"12555",
    "sg:province":"Berlin",
    "wof:name":"Ger\u00fcstbau Gbr",
    "wof:placetype":"venue"
},
  "geometry": {"coordinates":[13.5922212601,52.4556350708],"type":"Point"}
}