{
  "type": "Feature",
  "properties": {
    "iso:country":"DE",
    "sg:address":"Kirchenstra\u00dfe 57",
    "sg:city":"Eggenstein/Karlsruhe",
    "sg:phone":"+49 721",
    "sg:postcode":"76344",
    "sg:province":"Baden-W\u00fcrttemberg",
    "wof:name":"Grafik Digital",
    "wof:placetype":"venue"
},
  "geometry": {"coordinates":[8.394203,49.07666],"type":"Point"}
}