{
  "type": "Feature",
  "properties": {
    "iso:country":"DE",
    "sg:address":"Plinganserstr. 35",
    "sg:city":"M\u00fcnchen",
    "sg:phone":"+49 89/7256868",
    "sg:postcode":"81369",
    "sg:province":"Bayern",
    "wof:name":"Trendoptic Gmbh",
    "wof:placetype":"venue"
},
  "geometry": {"coordinates":[11.540581,48.118111],"type":"Point"}
}