{
  "type": "Feature",
  "properties": {
    "iso:country":"DE",
    "sg:address":"Limburger Stra\u00dfe 27",
    "sg:city":"R\u00fcckershausen",
    "sg:phone":"+49 6430/5031",
    "sg:postcode":"65326",
    "sg:province":"Hessen",
    "wof:name":"Terraristikshop",
    "wof:placetype":"venue"
},
  "geometry": {"coordinates":[8.0526027679,50.2637176514],"type":"Point"}
}