{
  "type": "Feature",
  "properties": {
    "iso:country":"DE",
    "sg:address":"St.-Martin-Str. 53",
    "sg:city":"M\u00fcnchen",
    "sg:postcode":"81669",
    "sg:province":"Bayern",
    "wof:name":"Infineon Ventures Co-anlagen Beteiligungs- Gmbh",
    "wof:placetype":"venue"
},
  "geometry": {"coordinates":[11.600763,48.119797],"type":"Point"}
}