{
  "type": "Feature",
  "properties": {
    "iso:country":"DE",
    "sg:address":"Schadenhofstr. 7",
    "sg:city":"Biberach",
    "sg:phone":"+49 4973/515760",
    "sg:postcode":"88400",
    "sg:province":"Baden-W\u00fcrttemberg",
    "wof:name":"Deutsche Bank Ag",
    "wof:placetype":"venue"
},
  "geometry": {"coordinates":[9.788481,48.099072],"type":"Point"}
}