{
  "type": "Feature",
  "properties": {
    "iso:country":"DE",
    "sg:address":"F\u00fcrstenwalder Str. 47",
    "sg:city":"Frankfurt",
    "sg:phone":"+49 335/558450",
    "sg:postcode":"15234",
    "sg:province":"Brandenburg",
    "wof:name":"Baer Elektronik Gbr",
    "wof:placetype":"venue"
},
  "geometry": {"coordinates":[14.537075,52.342571],"type":"Point"}
}