{
  "type": "Feature",
  "properties": {
    "iso:country":"DE",
    "sg:address":"Wilhelm-Jacoby-Str. 6",
    "sg:city":"Taunusstein",
    "sg:phone":"+49 6128/43988",
    "sg:postcode":"65232",
    "sg:province":"Hessen",
    "wof:name":"Hans-georg Kuhn",
    "wof:placetype":"venue"
},
  "geometry": {"coordinates":[8.1437311172,50.1360359192],"type":"Point"}
}