{
  "type": "Feature",
  "properties": {
    "iso:country":"DE",
    "sg:address":"Auerhammerstr. 19",
    "sg:city":"Aue",
    "sg:phone":"+49 3771/22926",
    "sg:postcode":"08280",
    "sg:province":"Sachsen",
    "wof:name":"Dettmar Architektenb\u00fcro",
    "wof:placetype":"venue"
},
  "geometry": {"coordinates":[12.696017,50.584148],"type":"Point"}
}