{
  "type": "Feature",
  "properties": {
    "iso:country":"DE",
    "sg:address":"Viktoriastr. 44",
    "sg:city":"Nordenham",
    "sg:phone":"+49 4731/21984",
    "sg:postcode":"26954",
    "sg:province":"Niedersachsen",
    "wof:name":"Rainer B\u00f6hlke",
    "wof:placetype":"venue"
},
  "geometry": {"coordinates":[8.4832878113,53.4946022034],"type":"Point"}
}