{
  "type": "Feature",
  "properties": {
    "iso:country":"DE",
    "sg:address":"Kapellenstr. 60",
    "sg:city":"Aachen",
    "sg:phone":"+49 241/68086",
    "sg:postcode":"52066",
    "sg:province":"Nordrhein-Westfalen",
    "wof:name":"Peter Olschowka",
    "wof:placetype":"venue"
},
  "geometry": {"coordinates":[6.0939202309,50.7598419189],"type":"Point"}
}