{
  "type": "Feature",
  "properties": {
    "iso:country":"DE",
    "sg:address":"Carlo-Mierendorff-Str. 11",
    "sg:city":"Neuss",
    "sg:phone":"+49 2131/471313",
    "sg:postcode":"41466",
    "sg:province":"Nordrhein-Westfalen",
    "wof:name":"Bodo Schulte Tennislehrer",
    "wof:placetype":"venue"
},
  "geometry": {"coordinates":[6.7063241005,51.1588668823],"type":"Point"}
}