{
  "type": "Feature",
  "properties": {
    "iso:country":"DE",
    "sg:address":"Am Heuberg 71",
    "sg:city":"Albstadt",
    "sg:phone":"+49 7432/900001",
    "sg:postcode":"72461",
    "sg:province":"Baden-W\u00fcrttemberg",
    "wof:name":"J\u00fcrgen Hassis Ingenieur",
    "wof:placetype":"venue"
},
  "geometry": {"coordinates":[8.9957761765,48.2773323059],"type":"Point"}
}