{
  "type": "Feature",
  "properties": {
    "iso:country":"DE",
    "sg:address":"Kerschelweg 31",
    "sg:city":"Brannenburg",
    "sg:phone":"+49 8034/90580",
    "sg:postcode":"83098",
    "sg:province":"Bayern",
    "wof:name":"Wenning Immobilienmakler",
    "wof:placetype":"venue"
},
  "geometry": {"coordinates":[12.1010742188,47.7461166382],"type":"Point"}
}