{
  "type": "Feature",
  "properties": {
    "iso:country":"DE",
    "sg:address":"Robert-Koch-Str. 14",
    "sg:city":"Fernwald",
    "sg:phone":"+49 6404/62174",
    "sg:postcode":"35463",
    "sg:province":"Hessen",
    "wof:name":"Teamwork Gmbh",
    "wof:placetype":"venue"
},
  "geometry": {"coordinates":[8.7743005753,50.5541610718],"type":"Point"}
}