{
  "type": "Feature",
  "properties": {
    "iso:country":"DE",
    "sg:address":"Krugstr. 22",
    "sg:city":"Heilbronn",
    "sg:phone":"+49 7131/177173",
    "sg:postcode":"74076",
    "sg:province":"Baden-W\u00fcrttemberg",
    "wof:name":"Fotowerbung Haarfeld & Co. Inh. M. Schneider",
    "wof:placetype":"venue"
},
  "geometry": {"coordinates":[9.2387418747,49.1480712891],"type":"Point"}
}