{
  "type": "Feature",
  "properties": {
    "iso:country":"DE",
    "sg:address":"Jahnstr. 2",
    "sg:city":"Bad T\u00f6lz",
    "sg:phone":"+49 8041/2381",
    "sg:postcode":"83646",
    "sg:province":"Bayern",
    "wof:name":"Peter Fischer Kunst- Und Bauschlosserei",
    "wof:placetype":"venue"
},
  "geometry": {"coordinates":[11.5639886856,47.7645339966],"type":"Point"}
}