{
  "type": "Feature",
  "properties": {
    "iso:country":"DE",
    "sg:address":"Auf der Engelhardt 3",
    "sg:city":"Wiehl",
    "sg:phone":"+49 2262/93508",
    "sg:postcode":"51674",
    "sg:province":"Nordrhein-Westfalen",
    "wof:name":"Volker Dellenbusch",
    "wof:placetype":"venue"
},
  "geometry": {"coordinates":[7.545537,50.945435],"type":"Point"}
}