{
  "type": "Feature",
  "properties": {
    "iso:country":"DE",
    "sg:address":"Elsterstr. 83",
    "sg:city":"Bad K\u00f6stritz",
    "sg:phone":"+49 36605/3410",
    "sg:postcode":"07586",
    "sg:province":"Th\u00fcringen",
    "wof:name":"Rittal-bad K\u00f6stritzer-zubeh\u00f6r- Komponenten Gmbh & Co. Kg",
    "wof:placetype":"venue"
},
  "geometry": {"coordinates":[12.027724,50.930882],"type":"Point"}
}