{
  "type": "Feature",
  "properties": {
    "iso:country":"DE",
    "sg:address":"Friedrichstr. 9",
    "sg:city":"Wiesbaden",
    "sg:postcode":"65185",
    "sg:province":"Hessen",
    "wof:name":"Conceptum Gmbh",
    "wof:placetype":"venue"
},
  "geometry": {"coordinates":[8.243964,50.080723],"type":"Point"}
}