{
  "type": "Feature",
  "properties": {
    "iso:country":"DE",
    "sg:address":"Am Heerdter Krankenhaus 2",
    "sg:city":"D\u00fcsseldorf",
    "sg:phone":"+49 211/5670",
    "sg:postcode":"40549",
    "sg:province":"Nordrhein-Westfalen",
    "wof:name":"Dominikus-krankenhaus D\u00fcsseldorf-heerdt Gmbh",
    "wof:placetype":"venue"
},
  "geometry": {"coordinates":[6.727645,51.232033],"type":"Point"}
}