{
  "type": "Feature",
  "properties": {
    "iso:country":"DE",
    "sg:address":"Pfarrer-Lenzel-Str. 1-5",
    "sg:city":"Berlin",
    "sg:phone":"+49 30/4774711",
    "sg:postcode":"13156",
    "sg:province":"Berlin",
    "wof:name":"Diakonie-station Pankow Niedersch\u00f6nhausen",
    "wof:placetype":"venue"
},
  "geometry": {"coordinates":[13.396311,52.588154],"type":"Point"}
}