{
  "type": "Feature",
  "properties": {
    "iso:country":"DE",
    "sg:address":"Postkamp 18",
    "sg:city":"Hannover",
    "sg:phone":"+49 511/1316019",
    "sg:postcode":"30159",
    "sg:province":"Niedersachsen",
    "wof:name":"Restaurant Himalaya",
    "wof:placetype":"venue"
},
  "geometry": {"coordinates":[9.728843689,52.3803367615],"type":"Point"}
}