{
  "type": "Feature",
  "properties": {
    "iso:country":"DE",
    "sg:address":"Feldweg 3",
    "sg:city":"Elmenhorst/Lichtenhagen",
    "sg:postcode":"18107",
    "sg:province":"Mecklenburg-Vorpommern",
    "wof:name":"Pro Nord Projektentwicklung Handel Marketing Norddeutschl.",
    "wof:placetype":"venue"
},
  "geometry": {"coordinates":[12.0136785507,54.1542320251],"type":"Point"}
}