{
  "type": "Feature",
  "properties": {
    "iso:country":"DE",
    "sg:address":"Sangm\u00fchle",
    "sg:city":"Birstein",
    "sg:phone":"+49 6668/249",
    "sg:postcode":"63633",
    "sg:province":"Hessen",
    "wof:name":"Waldemar Buchhaupt",
    "wof:placetype":"venue"
},
  "geometry": {"coordinates":[9.348912,50.423386],"type":"Point"}
}