{
  "type": "Feature",
  "properties": {
    "iso:country":"DE",
    "sg:address":"Storkower Str. 140",
    "sg:city":"Berlin",
    "sg:phone":"+49 4930/4284910",
    "sg:postcode":"10407",
    "sg:province":"Berlin",
    "wof:name":"Bsb Gmbh Best Sabel Bildungszentrum",
    "wof:placetype":"venue"
},
  "geometry": {"coordinates":[13.453777,52.53215],"type":"Point"}
}