{
  "type": "Feature",
  "properties": {
    "iso:country":"DE",
    "sg:address":"Postfach 55 12 33",
    "sg:city":"N\u00fcrnberg",
    "sg:phone":"+49 911/8129978",
    "sg:postcode":"90219",
    "sg:province":"Bayern",
    "wof:name":"Haftpflicht-direkt",
    "wof:placetype":"venue"
},
  "geometry": {"coordinates":[11.0804796219,49.4505195618],"type":"Point"}
}