{
  "type": "Feature",
  "properties": {
    "iso:country":"DE",
    "sg:address":"Rigaer Str 80",
    "sg:city":"Berlin",
    "sg:phone":"+49 30/29002608",
    "sg:postcode":"10247",
    "sg:province":"Berlin",
    "wof:name":"Fisch",
    "wof:placetype":"venue"
},
  "geometry": {"coordinates":[13.463391,52.51683],"type":"Point"}
}