{
  "type": "Feature",
  "properties": {
    "iso:country":"DE",
    "sg:address":"Dorfbauerschaft 6",
    "sg:city":"Ostbevern",
    "sg:phone":"+49 2532/7149",
    "sg:postcode":"48346",
    "sg:province":"Nordrhein-Westfalen",
    "wof:name":"Paul Eggenhaus",
    "wof:placetype":"venue"
},
  "geometry": {"coordinates":[7.810716,52.050842],"type":"Point"}
}