{
  "type": "Feature",
  "properties": {
    "iso:country":"DE",
    "sg:address":"Georgstr. 3",
    "sg:city":"Hannover",
    "sg:phone":"+49 511/15019",
    "sg:postcode":"30159",
    "sg:province":"Niedersachsen",
    "wof:name":"Tanova Modewelt Gmbh",
    "wof:placetype":"venue"
},
  "geometry": {"coordinates":[9.741368,52.369537],"type":"Point"}
}