{
  "type": "Feature",
  "properties": {
    "iso:country":"DE",
    "sg:address":"Deutsche Gasse 2",
    "sg:city":"Pliezhausen",
    "sg:phone":"+49 7127/8606",
    "sg:postcode":"72124",
    "sg:province":"Baden-W\u00fcrttemberg",
    "wof:name":"Ur Gmbh",
    "wof:placetype":"venue"
},
  "geometry": {"coordinates":[9.2068414688,48.5570678711],"type":"Point"}
}