{
  "type": "Feature",
  "properties": {
    "iso:country":"DE",
    "sg:address":"Bergheimerstr.128",
    "sg:city":"Grevenbroich",
    "sg:postcode":"41515",
    "sg:province":"Nordrhein-Westfalen",
    "wof:name":"Harald Peters Sprachendienst",
    "wof:placetype":"venue"
},
  "geometry": {"coordinates":[6.58347,51.089882],"type":"Point"}
}