{
  "type": "Feature",
  "properties": {
    "iso:country":"DE",
    "sg:address":"Karl-Theodor-Str. 7",
    "sg:city":"Tegernsee",
    "sg:phone":"+49 8022/4504",
    "sg:postcode":"83684",
    "sg:province":"Bayern",
    "wof:name":"Josef M\u00e4rkl",
    "wof:placetype":"venue"
},
  "geometry": {"coordinates":[11.757254,47.713173],"type":"Point"}
}