{
  "type": "Feature",
  "properties": {
    "iso:country":"DE",
    "sg:address":"Schulstr. 1",
    "sg:city":"Kirchberg",
    "sg:phone":"+49 4971/4436181",
    "sg:postcode":"71737",
    "sg:province":"Baden-W\u00fcrttemberg",
    "wof:name":"Kreissparkasse Waiblingen",
    "wof:placetype":"venue"
},
  "geometry": {"coordinates":[12.529669,50.621399],"type":"Point"}
}