{
  "type": "Feature",
  "properties": {
    "iso:country":"DE",
    "sg:address":"Gustav-Seebich-Str. 1",
    "sg:city":"Ebersbach",
    "sg:phone":"+49 7163/2031",
    "sg:postcode":"73061",
    "sg:province":"Baden-W\u00fcrttemberg",
    "wof:name":"Bernhard Sch\u00e4del Ingenieur",
    "wof:placetype":"venue"
},
  "geometry": {"coordinates":[9.5223913193,48.7171936035],"type":"Point"}
}