{
  "type": "Feature",
  "properties": {
    "iso:country":"DE",
    "sg:address":"Am Lachengraben 2",
    "sg:city":"Riedstadt",
    "sg:postcode":"64560",
    "sg:province":"Hessen",
    "wof:name":"Isoplex Gmbh",
    "wof:placetype":"venue"
},
  "geometry": {"coordinates":[8.500635,49.855892],"type":"Point"}
}