{
  "type": "Feature",
  "properties": {
    "iso:country":"DE",
    "sg:address":"Lammplatz 7",
    "sg:city":"Bad Krozingen",
    "sg:phone":"+49 7633/3243",
    "sg:postcode":"79189",
    "sg:province":"Baden-W\u00fcrttemberg",
    "wof:name":"Luhr & Held",
    "wof:placetype":"venue"
},
  "geometry": {"coordinates":[7.6994290352,47.9169616699],"type":"Point"}
}