{
  "type": "Feature",
  "properties": {
    "iso:country":"DE",
    "sg:address":"Brohltalstr. 40",
    "sg:city":"Burgbrohl",
    "sg:phone":"+49 2636/2212",
    "sg:postcode":"56659",
    "sg:province":"Rheinland-Pfalz",
    "wof:name":"P. M\u00fcller",
    "wof:placetype":"venue"
},
  "geometry": {"coordinates":[7.279512,50.457279],"type":"Point"}
}