{
  "type": "Feature",
  "properties": {
    "iso:country":"DE",
    "sg:address":"Hauptstr. 9",
    "sg:city":"Damsdorf",
    "sg:phone":"+49 3382/700176",
    "sg:postcode":"14797",
    "sg:province":"Brandenburg",
    "wof:name":"M. Klein",
    "wof:placetype":"venue"
},
  "geometry": {"coordinates":[12.7438249588,52.3184089661],"type":"Point"}
}