{
  "type": "Feature",
  "properties": {
    "iso:country":"DE",
    "sg:address":"Stader Landstr. 44-46",
    "sg:city":"Bremen",
    "sg:phone":"+49 421/630038",
    "sg:postcode":"28719",
    "sg:province":"Bremen",
    "wof:name":"Ernst Otto Relais-verlag",
    "wof:placetype":"venue"
},
  "geometry": {"coordinates":[8.710277,53.167919],"type":"Point"}
}