{
  "type": "Feature",
  "properties": {
    "iso:country":"DE",
    "sg:address":"Brinkstr. 3A",
    "sg:city":"Wunstorf",
    "sg:phone":"+49 5031/14777",
    "sg:postcode":"31515",
    "sg:province":"Niedersachsen",
    "wof:name":"J. Teske",
    "wof:placetype":"venue"
},
  "geometry": {"coordinates":[9.3538398743,52.4056892395],"type":"Point"}
}