{
  "type": "Feature",
  "properties": {
    "iso:country":"DE",
    "sg:address":"Reutlinger Str. 7",
    "sg:city":"T\u00fcbingen",
    "sg:phone":"+49 7071/91270",
    "sg:postcode":"72072",
    "sg:province":"Baden-W\u00fcrttemberg",
    "wof:name":"Friedrichsmeier Und Hartmann Rechtsanw\u00e4lte",
    "wof:placetype":"venue"
},
  "geometry": {"coordinates":[9.0616703033,48.5154914856],"type":"Point"}
}