{
  "type": "Feature",
  "properties": {
    "iso:country":"DE",
    "sg:address":"Florianiplatz 12",
    "sg:city":"Bad Reichenhall",
    "sg:phone":"+49 8651/65544",
    "sg:postcode":"83435",
    "sg:province":"Bayern",
    "wof:name":"Johann Ziegler",
    "wof:placetype":"venue"
},
  "geometry": {"coordinates":[12.8757762909,47.7190170288],"type":"Point"}
}