{
  "type": "Feature",
  "properties": {
    "iso:country":"DE",
    "sg:address":"Siedlungstr. 18",
    "sg:city":"Bad Saulgau",
    "sg:phone":"+49 7581/8367",
    "sg:postcode":"88348",
    "sg:province":"Baden-W\u00fcrttemberg",
    "wof:name":"Egon Leeuw Bildhauer",
    "wof:placetype":"venue"
},
  "geometry": {"coordinates":[9.499456,48.022041],"type":"Point"}
}