{
  "type": "Feature",
  "properties": {
    "iso:country":"DE",
    "sg:address":"K\u00f6nigsbr\u00fccker Str. 150",
    "sg:city":"Dresden",
    "sg:phone":"+49 351/885620",
    "sg:postcode":"01099",
    "sg:province":"Sachsen",
    "wof:name":"Centrotherm Dresden Elektrische Anlagen Gmbh & Co.",
    "wof:placetype":"venue"
},
  "geometry": {"coordinates":[13.768945694,51.0986251831],"type":"Point"}
}