{
  "type": "Feature",
  "properties": {
    "iso:country":"DE",
    "sg:address":"Memminger Str. 71",
    "sg:city":"V\u00f6hringen",
    "sg:phone":"+49 7306/950100",
    "sg:postcode":"89269",
    "sg:province":"Bayern",
    "wof:name":"M\u00f6bel Konrad Gmbh",
    "wof:placetype":"venue"
},
  "geometry": {"coordinates":[10.082956,48.271942],"type":"Point"}
}