{
  "type": "Feature",
  "properties": {
    "iso:country":"DE",
    "sg:address":"Cherisystr. 20",
    "sg:city":"Konstanz",
    "sg:phone":"+49 7531/29528",
    "sg:postcode":"78467",
    "sg:province":"Baden-W\u00fcrttemberg",
    "wof:name":"Cknupfer Internetservice, Webdesign",
    "wof:placetype":"venue"
},
  "geometry": {"coordinates":[9.1602239609,47.680519104],"type":"Point"}
}