{
  "type": "Feature",
  "properties": {
    "iso:country":"DE",
    "sg:address":"Lindenweg 13",
    "sg:city":"M\u00fchlhausen",
    "sg:postcode":"69242",
    "sg:province":"Baden-W\u00fcrttemberg",
    "wof:name":"Spektrum \u00d6kologie",
    "wof:placetype":"venue"
},
  "geometry": {"coordinates":[8.694821,49.237122],"type":"Point"}
}