{
  "type": "Feature",
  "properties": {
    "iso:country":"DE",
    "sg:address":"Karl-Marx-Str. 3",
    "sg:city":"Putlitz",
    "sg:phone":"+49 33981/80271",
    "sg:postcode":"16949",
    "sg:province":"Brandenburg",
    "wof:name":"Werner Korth",
    "wof:placetype":"venue"
},
  "geometry": {"coordinates":[12.0425,53.249821],"type":"Point"}
}