{
  "type": "Feature",
  "properties": {
    "iso:country":"DE",
    "sg:address":"Weststr 49a",
    "sg:city":"Bochum",
    "sg:phone":"+49 2327/322202",
    "sg:postcode":"44866",
    "sg:province":"Nordrhein-Westfalen",
    "wof:name":"Msw-showtechnik Musik Service Westermann",
    "wof:placetype":"venue"
},
  "geometry": {"coordinates":[7.127277,51.480972],"type":"Point"}
}