{
  "type": "Feature",
  "properties": {
    "iso:country":"DE",
    "sg:address":"Am Yachthafen 32",
    "sg:city":"Wittmund",
    "sg:phone":"+49 4464/94990",
    "sg:postcode":"26409",
    "sg:province":"Niedersachsen",
    "wof:name":"Hotel Am Yachthafen",
    "wof:placetype":"venue"
},
  "geometry": {"coordinates":[7.80809021,53.7023582458],"type":"Point"}
}