{
  "type": "Feature",
  "properties": {
    "iso:country":"DE",
    "sg:address":"In Der Neustadt 1",
    "sg:city":"Rinteln",
    "sg:phone":"+49 4957/512481",
    "sg:postcode":"31737",
    "sg:province":"Niedersachsen",
    "wof:name":"Wilhelm Reese",
    "wof:placetype":"venue"
},
  "geometry": {"coordinates":[9.029248,52.163261],"type":"Point"}
}