{
  "type": "Feature",
  "properties": {
    "iso:country":"DE",
    "sg:address":"Ernst-August-Platz 7",
    "sg:city":"Hannover",
    "sg:phone":"+49 511/329081",
    "sg:postcode":"30159",
    "sg:province":"Niedersachsen",
    "wof:name":"Rossmann Drogeriemarkt",
    "wof:placetype":"venue"
},
  "geometry": {"coordinates":[9.740768,52.375603],"type":"Point"}
}