{
  "type": "Feature",
  "properties": {
    "iso:country":"DE",
    "sg:address":"Neesendyck 504",
    "sg:city":"Kerken",
    "sg:phone":"+49 2833/3028",
    "sg:postcode":"47647",
    "sg:province":"Nordrhein-Westfalen",
    "wof:name":"Johann Sonnemanns",
    "wof:placetype":"venue"
},
  "geometry": {"coordinates":[6.346112,51.459412],"type":"Point"}
}