{
  "type": "Feature",
  "properties": {
    "iso:country":"DE",
    "sg:address":"Gutenbergstr.",
    "sg:city":"Bischofsheim",
    "sg:phone":"+49 6144/40445",
    "sg:postcode":"65474",
    "sg:province":"Hessen",
    "wof:name":"Heimatmuseum Bischofsheim",
    "wof:placetype":"venue"
},
  "geometry": {"coordinates":[8.36175,49.987541],"type":"Point"}
}