{
  "type": "Feature",
  "properties": {
    "iso:country":"DE",
    "sg:address":"Herdenweg 29",
    "sg:city":"Weiterstadt",
    "sg:phone":"+49 6150/2468",
    "sg:postcode":"64331",
    "sg:province":"Hessen",
    "wof:name":"Inpro Gew\u00fcrz Gmbh",
    "wof:placetype":"venue"
},
  "geometry": {"coordinates":[8.5776510239,49.9090309143],"type":"Point"}
}