{
  "type": "Feature",
  "properties": {
    "iso:country":"DE",
    "sg:address":"Von-Braun-Str. 52",
    "sg:city":"Ahaus",
    "sg:postcode":"48683",
    "sg:province":"Nordrhein-Westfalen",
    "wof:name":"Rudolf Kestermann Verwaltungs Gmbh",
    "wof:placetype":"venue"
},
  "geometry": {"coordinates":[7.0237770081,52.0740852356],"type":"Point"}
}