{
  "type": "Feature",
  "properties": {
    "iso:country":"DE",
    "sg:address":"Kommenderiestr. 32",
    "sg:city":"Osnabr\u00fcck",
    "sg:phone":"+49 541/2023660",
    "sg:postcode":"49074",
    "sg:province":"Niedersachsen",
    "wof:name":"Restaurant Sausalitos",
    "wof:placetype":"venue"
},
  "geometry": {"coordinates":[8.048579216,52.2692298889],"type":"Point"}
}