{
  "type": "Feature",
  "properties": {
    "iso:country":"DE",
    "sg:address":"Lise-Meitner-Strasse 5",
    "sg:city":"H\u00fcnxe",
    "sg:phone":"+49 281/9440310",
    "sg:postcode":"46569",
    "sg:province":"Nordrhein-Westfalen",
    "wof:name":"Wst-quarz Gmbh, H\u00fcnxe",
    "wof:placetype":"venue"
},
  "geometry": {"coordinates":[6.694056,51.635265],"type":"Point"}
}