{
  "type": "Feature",
  "properties": {
    "iso:country":"DE",
    "sg:address":"Ahlerhof 10",
    "sg:city":"Lahnstein",
    "sg:phone":"+49 2621/3191",
    "sg:postcode":"56112",
    "sg:province":"Rheinland-Pfalz",
    "wof:name":"Schulze",
    "wof:placetype":"venue"
},
  "geometry": {"coordinates":[7.64673,50.308651],"type":"Point"}
}