{
  "type": "Feature",
  "properties": {
    "iso:country":"DE",
    "sg:city":"Gro\u00dfbeeren",
    "sg:postcode":"14979",
    "sg:province":"Brandenburg",
    "wof:name":"Ehlert Fliesenlegerei Gmbh",
    "wof:placetype":"venue"
},
  "geometry": {"coordinates":[13.305833,52.353268],"type":"Point"}
}