{
  "type": "Feature",
  "properties": {
    "iso:country":"DE",
    "sg:address":"Geigergasse 2",
    "sg:city":"Bad T\u00f6lz",
    "sg:phone":"+49 8041/5527",
    "sg:postcode":"83646",
    "sg:province":"Bayern",
    "wof:name":"Edwin Kalitschka",
    "wof:placetype":"venue"
},
  "geometry": {"coordinates":[11.558986,47.75872],"type":"Point"}
}