{
  "type": "Feature",
  "properties": {
    "iso:country":"DE",
    "sg:address":"Birkenweg 8",
    "sg:city":"Eschborn",
    "sg:phone":"+49 6196/43579",
    "sg:postcode":"65760",
    "sg:province":"Hessen",
    "wof:name":"Elmar-ulrich Blaschke Rechtsanwalt Und Notar",
    "wof:placetype":"venue"
},
  "geometry": {"coordinates":[8.5710086823,50.1464996338],"type":"Point"}
}