{
  "type": "Feature",
  "properties": {
    "iso:country":"DE",
    "sg:address":"Schauergasse 2",
    "sg:city":"Bad Windsheim",
    "sg:phone":"+49 9841/79978",
    "sg:postcode":"91438",
    "sg:province":"Bayern",
    "wof:name":"Horn",
    "wof:placetype":"venue"
},
  "geometry": {"coordinates":[10.4182310104,49.503036499],"type":"Point"}
}