{
  "type": "Feature",
  "properties": {
    "iso:country":"DE",
    "sg:address":"Segeberger Chaussee 41",
    "sg:city":"Norderstedt",
    "sg:phone":"+49 40/5248314",
    "sg:postcode":"22850",
    "sg:province":"Schleswig-Holstein",
    "wof:name":"Jan Schnoor",
    "wof:placetype":"venue"
},
  "geometry": {"coordinates":[10.0058174133,53.6828384399],"type":"Point"}
}