{
  "type": "Feature",
  "properties": {
    "iso:country":"DE",
    "sg:address":"Elsenheimerstr. 18",
    "sg:city":"M\u00fcnchen",
    "sg:phone":"+49 89/3160690",
    "sg:postcode":"80687",
    "sg:province":"Bayern",
    "wof:name":"Rt Gmbh",
    "wof:placetype":"venue"
},
  "geometry": {"coordinates":[11.519439,48.139168],"type":"Point"}
}