{
  "type": "Feature",
  "properties": {
    "iso:country":"DE",
    "sg:address":"Oberzettlitz",
    "sg:city":"Kulmbach",
    "sg:phone":"+49 9221/64580",
    "sg:postcode":"95326",
    "sg:province":"Bayern",
    "wof:name":"G. Settekorn",
    "wof:placetype":"venue"
},
  "geometry": {"coordinates":[11.435626,50.070648],"type":"Point"}
}