{
  "type": "Feature",
  "properties": {
    "iso:country":"DE",
    "sg:address":"Josefstra\u00dfe 37",
    "sg:city":"Herten",
    "sg:phone":"+49 2366/104332",
    "sg:postcode":"45699",
    "sg:province":"Nordrhein-Westfalen",
    "wof:name":"Warner Bros. Movie World - 100% Inoffiziell",
    "wof:placetype":"venue"
},
  "geometry": {"coordinates":[7.152006,51.60371],"type":"Point"}
}