{
  "type": "Feature",
  "properties": {
    "iso:country":"DE",
    "sg:address":"Heckenweg 12",
    "sg:city":"Grafenau",
    "sg:phone":"+49 7033/43637",
    "sg:postcode":"71120",
    "sg:province":"Baden-W\u00fcrttemberg",
    "wof:name":"Wilhelm Butsch Inh. Erhard Butsch",
    "wof:placetype":"venue"
},
  "geometry": {"coordinates":[8.908876,48.715809],"type":"Point"}
}