{
  "type": "Feature",
  "properties": {
    "iso:country":"DE",
    "sg:address":"Friedrich-Ebert-Str. 181",
    "sg:city":"M\u00fcnster",
    "sg:phone":"+49 251/777720",
    "sg:postcode":"48153",
    "sg:province":"Nordrhein-Westfalen",
    "wof:name":"Haftpflichtverb. D. Dt. Industrie Va G",
    "wof:placetype":"venue"
},
  "geometry": {"coordinates":[7.6253829002,51.9421157837],"type":"Point"}
}