{
  "type": "Feature",
  "properties": {
    "iso:country":"DE",
    "sg:address":"Schweriner Str. 50",
    "sg:city":"Pampow",
    "sg:phone":"+49 3865/585",
    "sg:postcode":"19075",
    "sg:province":"Mecklenburg-Vorpommern",
    "wof:name":"Hans-juergen Matatko",
    "wof:placetype":"venue"
},
  "geometry": {"coordinates":[11.3518590927,53.5649681091],"type":"Point"}
}