{
  "type": "Feature",
  "properties": {
    "iso:country":"DE",
    "sg:address":"Am Buchrain 8",
    "sg:city":"Bad S\u00e4ckingen",
    "sg:phone":"+49 7761/6592",
    "sg:postcode":"79713",
    "sg:province":"Baden-W\u00fcrttemberg",
    "wof:name":"Fautz Gmbh",
    "wof:placetype":"venue"
},
  "geometry": {"coordinates":[7.927695,47.555119],"type":"Point"}
}