{
  "type": "Feature",
  "properties": {
    "iso:country":"DE",
    "sg:address":"Oberstra\u00dfe 27",
    "sg:city":"Korschenbroich",
    "sg:phone":"+49 2182/50040",
    "sg:postcode":"41352",
    "sg:province":"Nordrhein-Westfalen",
    "wof:name":"Handelsvertretung F\u00fcr Backwaren",
    "wof:placetype":"venue"
},
  "geometry": {"coordinates":[6.6095647812,51.1657333374],"type":"Point"}
}