{
  "type": "Feature",
  "properties": {
    "iso:country":"DE",
    "sg:address":"Pirkach 41",
    "sg:city":"Emskirchen",
    "sg:phone":"+49 9101/6928",
    "sg:postcode":"91448",
    "sg:province":"Bayern",
    "wof:name":"Reiner Prell Steuerberater",
    "wof:placetype":"venue"
},
  "geometry": {"coordinates":[10.7919397354,49.5367507935],"type":"Point"}
}