{
  "type": "Feature",
  "properties": {
    "iso:country":"DE",
    "sg:address":"Spreestr. 22",
    "sg:city":"Petershagen",
    "sg:phone":"+49 33439/80507",
    "sg:postcode":"15370",
    "sg:province":"Brandenburg",
    "wof:name":"Wolfgang Weigert",
    "wof:placetype":"venue"
},
  "geometry": {"coordinates":[13.779007,52.528404],"type":"Point"}
}