{
  "type": "Feature",
  "properties": {
    "iso:country":"DE",
    "sg:address":"Fabrikstr. 7",
    "sg:city":"Bad M\u00fcnstereifel",
    "sg:phone":"+49 2253/4216",
    "sg:postcode":"53902",
    "sg:province":"Nordrhein-Westfalen",
    "wof:name":"Josef Ludes",
    "wof:placetype":"venue"
},
  "geometry": {"coordinates":[6.793992,50.600311],"type":"Point"}
}