{
  "type": "Feature",
  "properties": {
    "iso:country":"DE",
    "sg:address":"Gezelinallee 17-19",
    "sg:city":"Leverkusen",
    "sg:phone":"+49 214/206410",
    "sg:postcode":"51375",
    "sg:province":"Nordrhein-Westfalen",
    "wof:name":"Punktgenau Gmbh",
    "wof:placetype":"venue"
},
  "geometry": {"coordinates":[7.050578,51.036217],"type":"Point"}
}