{
  "type": "Feature",
  "properties": {
    "iso:country":"DE",
    "sg:address":"Allmendstr. 6",
    "sg:city":"Engen",
    "sg:phone":"+49 7733/1501",
    "sg:postcode":"78234",
    "sg:province":"Baden-W\u00fcrttemberg",
    "wof:name":"Kiefer Immobilienmakler",
    "wof:placetype":"venue"
},
  "geometry": {"coordinates":[8.7758054733,47.8369026184],"type":"Point"}
}