{
  "type": "Feature",
  "properties": {
    "iso:country":"DE",
    "sg:address":"Am Rheinhessenblick 7",
    "sg:city":"Harxheim",
    "sg:phone":"+49 6138/7751",
    "sg:postcode":"55296",
    "sg:province":"Rheinland-Pfalz",
    "wof:name":"R. Roth",
    "wof:placetype":"venue"
},
  "geometry": {"coordinates":[8.267365,49.903503],"type":"Point"}
}