{
  "type": "Feature",
  "properties": {
    "iso:country":"DE",
    "sg:address":"S\u00e4gm\u00fchlstr. 9a",
    "sg:city":"Olching",
    "sg:phone":"+49 8142/30776",
    "sg:postcode":"82140",
    "sg:province":"Bayern",
    "wof:name":"Isabella Limbrunner Steuerberaterin",
    "wof:placetype":"venue"
},
  "geometry": {"coordinates":[11.3477602005,48.2251281738],"type":"Point"}
}