{
  "type": "Feature",
  "properties": {
    "iso:country":"DE",
    "sg:address":"Nordstr. 6",
    "sg:city":"Strausberg",
    "sg:phone":"+49 3341/22201",
    "sg:postcode":"15344",
    "sg:province":"Brandenburg",
    "wof:name":"Grollmisch",
    "wof:placetype":"venue"
},
  "geometry": {"coordinates":[13.891152,52.587688],"type":"Point"}
}