{
  "type": "Feature",
  "properties": {
    "iso:country":"DE",
    "sg:address":"Ernsdorfstr. 2",
    "sg:city":"Kreuztal",
    "sg:phone":"+49 2732/58460",
    "sg:postcode":"57223",
    "sg:province":"Nordrhein-Westfalen",
    "wof:name":"Kreuztaler Treuhand Gmbh",
    "wof:placetype":"venue"
},
  "geometry": {"coordinates":[7.9995298386,50.9618339539],"type":"Point"}
}