{
  "type": "Feature",
  "properties": {
    "iso:country":"DE",
    "sg:address":"Wendenstr. 429",
    "sg:city":"Hamburg",
    "sg:phone":"+49 40/2291797",
    "sg:postcode":"20537",
    "sg:province":"Hamburg",
    "wof:name":"Omh Ocean Marine Handelsges. Mbh",
    "wof:placetype":"venue"
},
  "geometry": {"coordinates":[10.0514116287,53.5503883362],"type":"Point"}
}