{
  "type": "Feature",
  "properties": {
    "iso:country":"DE",
    "sg:address":"Brakeler Str. 22",
    "sg:city":"Brakel",
    "sg:phone":"+49 5272/7142",
    "sg:postcode":"33034",
    "sg:province":"Nordrhein-Westfalen",
    "wof:name":"Helmut Gieffers",
    "wof:placetype":"venue"
},
  "geometry": {"coordinates":[9.119353,51.707973],"type":"Point"}
}