{
  "type": "Feature",
  "properties": {
    "iso:country":"DE",
    "sg:address":"Goethestr. 45",
    "sg:city":"Berlin",
    "sg:postcode":"12459",
    "sg:province":"Berlin",
    "wof:name":"Elf Oil Ag",
    "wof:placetype":"venue"
},
  "geometry": {"coordinates":[13.518901825,52.4624176025],"type":"Point"}
}