{
  "type": "Feature",
  "properties": {
    "iso:country":"DE",
    "sg:address":"Rabertsweg 56",
    "sg:city":"Havixbeck",
    "sg:phone":"+49 2507/2200",
    "sg:postcode":"48329",
    "sg:province":"Nordrhein-Westfalen",
    "wof:name":"Waldemar Stobbe Gmbh",
    "wof:placetype":"venue"
},
  "geometry": {"coordinates":[7.409403,51.981747],"type":"Point"}
}