{
  "type": "Feature",
  "properties": {
    "iso:country":"DE",
    "sg:address":"Alter Fischmarkt 16-18",
    "sg:city":"M\u00fcnster",
    "sg:phone":"+49 251/44770",
    "sg:postcode":"48143",
    "sg:province":"Nordrhein-Westfalen",
    "wof:name":"Margret Krukenkamp E. K.",
    "wof:placetype":"venue"
},
  "geometry": {"coordinates":[7.629026,51.963238],"type":"Point"}
}