{
  "type": "Feature",
  "properties": {
    "iso:country":"DE",
    "sg:address":"Ketzberg 18",
    "sg:city":"Wermelskirchen",
    "sg:phone":"+49 2193/4437",
    "sg:postcode":"42929",
    "sg:province":"Nordrhein-Westfalen",
    "wof:name":"G\u00fcnter N\u00f6tzel",
    "wof:placetype":"venue"
},
  "geometry": {"coordinates":[7.202443,51.086239],"type":"Point"}
}