{
  "type": "Feature",
  "properties": {
    "iso:country":"DE",
    "sg:address":"Heidmark 1",
    "sg:city":"Visselh\u00f6vede",
    "sg:phone":"+49 4262/9350",
    "sg:postcode":"27374",
    "sg:province":"Niedersachsen",
    "wof:name":"Jeddinger Hof",
    "wof:placetype":"venue"
},
  "geometry": {"coordinates":[9.5152902603,52.9812011719],"type":"Point"}
}