{
  "type": "Feature",
  "properties": {
    "iso:country":"DE",
    "sg:address":"Saarlandstr. 75",
    "sg:city":"Karlsruhe",
    "sg:phone":"+49 721/566958",
    "sg:postcode":"76187",
    "sg:province":"Baden-W\u00fcrttemberg",
    "wof:name":"W. Kiefer",
    "wof:placetype":"venue"
},
  "geometry": {"coordinates":[8.340055,49.030834],"type":"Point"}
}