{
  "type": "Feature",
  "properties": {
    "iso:country":"DE",
    "sg:address":"Rheinstr. 29",
    "sg:city":"Baden-Baden",
    "sg:phone":"+49 7221/64031",
    "sg:postcode":"76532",
    "sg:province":"Baden-W\u00fcrttemberg",
    "wof:name":"Inter Rent Gmbh Wohnmobilverleih",
    "wof:placetype":"venue"
},
  "geometry": {"coordinates":[8.2215251923,48.7750778198],"type":"Point"}
}