{
  "type": "Feature",
  "properties": {
    "iso:country":"DE",
    "sg:address":"R\u00fctscher Str. 4",
    "sg:city":"Aachen",
    "sg:phone":"+49 241/154465",
    "sg:postcode":"52072",
    "sg:province":"Nordrhein-Westfalen",
    "wof:name":"Ponttor-apotheke",
    "wof:placetype":"venue"
},
  "geometry": {"coordinates":[6.076823,50.78307],"type":"Point"}
}