{
  "type": "Feature",
  "properties": {
    "iso:country":"DE",
    "sg:address":"Schenkensteinerstr. 31",
    "sg:city":"Donauw\u00f6rth",
    "sg:phone":"+49 906/6006",
    "sg:postcode":"86609",
    "sg:province":"Bayern",
    "wof:name":"Gunter Kauffmann",
    "wof:placetype":"venue"
},
  "geometry": {"coordinates":[10.813912,48.720669],"type":"Point"}
}