{
  "type": "Feature",
  "properties": {
    "iso:country":"DE",
    "sg:address":"Im Moore 5",
    "sg:city":"Diepholz",
    "sg:postcode":"49356",
    "sg:province":"Niedersachsen",
    "wof:name":"Ge Pro Gefl\u00fcgel Protein Vertriebs Gesch\u00e4ftsf\u00fchrungs",
    "wof:placetype":"venue"
},
  "geometry": {"coordinates":[8.310531,52.617123],"type":"Point"}
}