{
  "type": "Feature",
  "properties": {
    "iso:country":"DE",
    "sg:address":"Barbarossastr. 31",
    "sg:city":"Wiesbaden",
    "sg:phone":"+49 611/702151",
    "sg:postcode":"65205",
    "sg:province":"Hessen",
    "wof:name":"B. Rutkowski",
    "wof:placetype":"venue"
},
  "geometry": {"coordinates":[8.303774,50.051739],"type":"Point"}
}