{
  "type": "Feature",
  "properties": {
    "iso:country":"DE",
    "sg:address":"Wismarsche Str. 206",
    "sg:city":"Schwerin",
    "sg:postcode":"19053",
    "sg:province":"Mecklenburg-Vorpommern",
    "wof:name":"Lvm-versicherungsb\u00fcro",
    "wof:placetype":"venue"
},
  "geometry": {"coordinates":[11.40903759,53.6374931335],"type":"Point"}
}