{
  "type": "Feature",
  "properties": {
    "iso:country":"DE",
    "sg:address":"Waldhufenstr. 76",
    "sg:city":"Doberlug-Kirchhain",
    "sg:phone":"+49 35322/2929",
    "sg:postcode":"03253",
    "sg:province":"Brandenburg",
    "wof:name":"Helmut G\u00fcnther",
    "wof:placetype":"venue"
},
  "geometry": {"coordinates":[13.547539711,51.6374206543],"type":"Point"}
}