{
  "type": "Feature",
  "properties": {
    "iso:country":"DE",
    "sg:address":"Gro\u00dfe Str. 2",
    "sg:city":"Ahrensburg",
    "sg:phone":"+49 4102/54111",
    "sg:postcode":"22926",
    "sg:province":"Schleswig-Holstein",
    "wof:name":"Schlo\u00df-apotheke",
    "wof:placetype":"venue"
},
  "geometry": {"coordinates":[10.239851,53.676861],"type":"Point"}
}