{
  "type": "Feature",
  "properties": {
    "iso:country":"DE",
    "sg:address":"Ringstr 6",
    "sg:city":"B\u00f6hmenkirch",
    "sg:phone":"+49 7332/96230",
    "sg:postcode":"89558",
    "sg:province":"Baden-W\u00fcrttemberg",
    "wof:name":"S.s.g. Schmid Spezialkabel Gmbh",
    "wof:placetype":"venue"
},
  "geometry": {"coordinates":[9.896896,48.691261],"type":"Point"}
}