{
  "type": "Feature",
  "properties": {
    "iso:country":"DE",
    "sg:address":"Judengasse 10",
    "sg:city":"Babenhausen",
    "sg:phone":"+49 8333/1328",
    "sg:postcode":"87727",
    "sg:province":"Bayern",
    "wof:name":"Gasthof Sailer-br\u00e4u",
    "wof:placetype":"venue"
},
  "geometry": {"coordinates":[10.2523937225,48.1434860229],"type":"Point"}
}