{
  "type": "Feature",
  "properties": {
    "iso:country":"DE",
    "sg:address":"Titiseestr",
    "sg:city":"Berlin",
    "sg:postcode":"13469",
    "sg:province":"Berlin",
    "wof:name":"Klimakonferenz",
    "wof:placetype":"venue"
},
  "geometry": {"coordinates":[13.334572,52.609955],"type":"Point"}
}