{
  "type": "Feature",
  "properties": {
    "iso:country":"DE",
    "sg:address":"Neuenhausener Str. 199",
    "sg:city":"Grevenbroich",
    "sg:phone":"+49 2181/3514",
    "sg:postcode":"41515",
    "sg:province":"Nordrhein-Westfalen",
    "wof:name":"D. Volkwein",
    "wof:placetype":"venue"
},
  "geometry": {"coordinates":[6.595955,51.080284],"type":"Point"}
}