{
  "type": "Feature",
  "properties": {
    "iso:country":"DE",
    "sg:address":"Wallefelder Str.",
    "sg:city":"Engelskirchen",
    "sg:postcode":"51766",
    "sg:province":"Nordrhein-Westfalen",
    "wof:name":"Fawema Maschinenfabrik Gmbh",
    "wof:placetype":"venue"
},
  "geometry": {"coordinates":[7.468369,51.008022],"type":"Point"}
}