{
  "type": "Feature",
  "properties": {
    "iso:country":"DE",
    "sg:address":"Fellbacher Str. 140",
    "sg:city":"Stuttgart",
    "sg:phone":"+49 711/333473",
    "sg:postcode":"70327",
    "sg:province":"Baden-W\u00fcrttemberg",
    "wof:name":"N. Samoladas",
    "wof:placetype":"venue"
},
  "geometry": {"coordinates":[9.2608633041,48.792011261],"type":"Point"}
}