{
  "type": "Feature",
  "properties": {
    "iso:country":"DE",
    "sg:address":"Lange Str. 66-68",
    "sg:city":"Waiblingen",
    "sg:phone":"+49 7151/53679",
    "sg:postcode":"71332",
    "sg:province":"Baden-W\u00fcrttemberg",
    "wof:name":"Minimal",
    "wof:placetype":"venue"
},
  "geometry": {"coordinates":[9.3151798248,48.8307418823],"type":"Point"}
}