{
  "type": "Feature",
  "properties": {
    "iso:country":"DE",
    "sg:address":"Rembergstr. 47a",
    "sg:city":"Hagen",
    "sg:postcode":"58095",
    "sg:province":"Nordrhein-Westfalen",
    "wof:name":"Fesenmeyer Wohnungsbau Und Immobilien Gmbh",
    "wof:placetype":"venue"
},
  "geometry": {"coordinates":[7.4849638939,51.3605766296],"type":"Point"}
}