{
  "type": "Feature",
  "properties": {
    "iso:country":"DE",
    "sg:address":"Pienzenauerstr. 48",
    "sg:city":"M\u00fcnchen",
    "sg:phone":"+49 89/9828386",
    "sg:postcode":"81679",
    "sg:province":"Bayern",
    "wof:name":"Honorarkonsulat Der Republik Ruanda",
    "wof:placetype":"venue"
},
  "geometry": {"coordinates":[11.6070241928,48.1550827026],"type":"Point"}
}