{
  "type": "Feature",
  "properties": {
    "iso:country":"DE",
    "sg:address":"Haardtstr. 2",
    "sg:city":"Ellerstadt",
    "sg:phone":"+49 6237/2303",
    "sg:postcode":"67158",
    "sg:province":"Rheinland-Pfalz",
    "wof:name":"Ev. Pfarramt Ellerstadt",
    "wof:placetype":"venue"
},
  "geometry": {"coordinates":[8.2584276199,49.4642868042],"type":"Point"}
}