{
  "type": "Feature",
  "properties": {
    "iso:country":"DE",
    "sg:address":"Obere Halde 10",
    "sg:city":"Bisingen",
    "sg:phone":"+49 7471/4422",
    "sg:postcode":"72406",
    "sg:province":"Baden-W\u00fcrttemberg",
    "wof:name":"Gerhard Sommer",
    "wof:placetype":"venue"
},
  "geometry": {"coordinates":[8.938477,48.329578],"type":"Point"}
}