{
  "type": "Feature",
  "properties": {
    "iso:country":"DE",
    "sg:address":"Berliner Str. 155",
    "sg:city":"Cottbus",
    "sg:phone":"+49 355/380330",
    "sg:postcode":"03046",
    "sg:province":"Brandenburg",
    "wof:name":"Lausitzer Reiseb\u00fcro Cottbus",
    "wof:placetype":"venue"
},
  "geometry": {"coordinates":[14.3291711807,51.7613868713],"type":"Point"}
}