{
  "type": "Feature",
  "properties": {
    "iso:country":"DE",
    "sg:address":"Strandweg 37",
    "sg:city":"Allensbach",
    "sg:phone":"+49 7533/97171",
    "sg:postcode":"78476",
    "sg:province":"Baden-W\u00fcrttemberg",
    "wof:name":"Dr. H. Voss Rechtsanwalt",
    "wof:placetype":"venue"
},
  "geometry": {"coordinates":[9.0766429901,47.7114830017],"type":"Point"}
}