{
  "type": "Feature",
  "properties": {
    "iso:country":"DE",
    "sg:address":"Gauerter Hauptdeich 91",
    "sg:city":"Hamburg",
    "sg:phone":"+49 40/7372321",
    "sg:postcode":"21037",
    "sg:province":"Hamburg",
    "wof:name":"J\u00fcrgen Speck",
    "wof:placetype":"venue"
},
  "geometry": {"coordinates":[10.072649,53.45908],"type":"Point"}
}