{
  "type": "Feature",
  "properties": {
    "iso:country":"DE",
    "sg:address":"Hymgasse 3",
    "sg:city":"Neuss",
    "sg:phone":"+49 2131/25888",
    "sg:postcode":"41460",
    "sg:province":"Nordrhein-Westfalen",
    "wof:name":"J\u00e4gerstube",
    "wof:placetype":"venue"
},
  "geometry": {"coordinates":[6.69520998,51.1970596313],"type":"Point"}
}