{
  "type": "Feature",
  "properties": {
    "iso:country":"DE",
    "sg:address":"An der Steinach 7",
    "sg:city":"Sonneberg",
    "sg:postcode":"96515",
    "sg:province":"Th\u00fcringen",
    "wof:name":"N Und N Verwaltungs Gmbh",
    "wof:placetype":"venue"
},
  "geometry": {"coordinates":[11.2108802795,50.3592529297],"type":"Point"}
}