{
  "type": "Feature",
  "properties": {
    "iso:country":"DE",
    "sg:address":"Luisenstr. 1",
    "sg:city":"Neunkirchen",
    "sg:phone":"+49 6262/2429",
    "sg:postcode":"74867",
    "sg:province":"Baden-W\u00fcrttemberg",
    "wof:name":"Gerhard Winterbauer",
    "wof:placetype":"venue"
},
  "geometry": {"coordinates":[9.007604,49.389076],"type":"Point"}
}