{
  "type": "Feature",
  "properties": {
    "iso:country":"DE",
    "sg:address":"Burgwedel 24",
    "sg:city":"Hamburg",
    "sg:phone":"+49 40/5505067",
    "sg:postcode":"22457",
    "sg:province":"Hamburg",
    "wof:name":"Blobel",
    "wof:placetype":"venue"
},
  "geometry": {"coordinates":[9.9166316986,53.6382102966],"type":"Point"}
}