{
  "type": "Feature",
  "properties": {
    "iso:country":"DE",
    "sg:address":"Lange Str. 38",
    "sg:city":"Dornstadt",
    "sg:phone":"+49 7348/989960",
    "sg:postcode":"89160",
    "sg:province":"Baden-W\u00fcrttemberg",
    "wof:name":"Sozialstation Ulmer-alb",
    "wof:placetype":"venue"
},
  "geometry": {"coordinates":[9.941628,48.466118],"type":"Point"}
}