{
  "type": "Feature",
  "properties": {
    "iso:country":"DE",
    "sg:address":"Frielick 8",
    "sg:city":"Hamm",
    "sg:postcode":"59073",
    "sg:province":"Nordrhein-Westfalen",
    "wof:name":"Kraft Verwaltungs- Und Beteiligungs Gmbh",
    "wof:placetype":"venue"
},
  "geometry": {"coordinates":[7.823389,51.73082],"type":"Point"}
}