{
  "type": "Feature",
  "properties": {
    "iso:country":"DE",
    "sg:address":"RWE-Uchtelfangen",
    "sg:city":"Illingen",
    "sg:postcode":"66557",
    "sg:province":"Saarland",
    "wof:name":"Schulbibliothek An Der Grund- Und Hauptschule",
    "wof:placetype":"venue"
},
  "geometry": {"coordinates":[6.997965,49.376701],"type":"Point"}
}