{
  "type": "Feature",
  "properties": {
    "iso:country":"DE",
    "sg:address":"Ingolst\u00e4dter Str. 8",
    "sg:city":"Wettstetten",
    "sg:phone":"+49 841/991620",
    "sg:postcode":"85139",
    "sg:province":"Bayern",
    "wof:name":"Erich Kolinsky Steuerberater",
    "wof:placetype":"venue"
},
  "geometry": {"coordinates":[11.4146127701,48.8231124878],"type":"Point"}
}