{
  "type": "Feature",
  "properties": {
    "iso:country":"DE",
    "sg:address":"Bamberger Str. 33",
    "sg:city":"Hirschaid",
    "sg:phone":"+49 9543/6230",
    "sg:postcode":"96114",
    "sg:province":"Bayern",
    "wof:name":"D. Und K. Peterh\u00e4nsel",
    "wof:placetype":"venue"
},
  "geometry": {"coordinates":[10.9873027802,49.819858551],"type":"Point"}
}