{
  "type": "Feature",
  "properties": {
    "iso:country":"DE",
    "sg:address":"Edissonstr. 1",
    "sg:city":"Bobingen",
    "sg:phone":"+49 8234/96350",
    "sg:postcode":"86399",
    "sg:province":"Bayern",
    "wof:name":"Eye Information Product",
    "wof:placetype":"venue"
},
  "geometry": {"coordinates":[10.845352,48.269375],"type":"Point"}
}