{
  "type": "Feature",
  "properties": {
    "iso:country":"DE",
    "sg:address":"Mestrenger Weg 15",
    "sg:city":"H\u00fcrtgenwald",
    "sg:phone":"+49 2429/2414",
    "sg:postcode":"52393",
    "sg:province":"Nordrhein-Westfalen",
    "wof:name":"Zion Emanuel",
    "wof:placetype":"venue"
},
  "geometry": {"coordinates":[6.374533,50.683475],"type":"Point"}
}