{
  "type": "Feature",
  "properties": {
    "iso:country":"DE",
    "sg:address":"Am Bahnhof 10 a",
    "sg:city":"Kirrweiler",
    "sg:postcode":"67489",
    "sg:province":"Rheinland-Pfalz",
    "wof:name":"H. Leydecker",
    "wof:placetype":"venue"
},
  "geometry": {"coordinates":[8.14741,49.307041],"type":"Point"}
}