{
  "type": "Feature",
  "properties": {
    "iso:country":"DE",
    "sg:address":"Industriering 11",
    "sg:city":"Edenkoben",
    "sg:phone":"+49 6323/989156",
    "sg:postcode":"67480",
    "sg:province":"Rheinland-Pfalz",
    "wof:name":"L. Von Boeltzig & Co. Gmbh",
    "wof:placetype":"venue"
},
  "geometry": {"coordinates":[8.150539,49.285645],"type":"Point"}
}