{
  "type": "Feature",
  "properties": {
    "iso:country":"DE",
    "sg:address":"Kiefernweg 20",
    "sg:city":"Mermuth",
    "sg:phone":"+49 6745/236",
    "sg:postcode":"56283",
    "sg:province":"Rheinland-Pfalz",
    "wof:name":"Jost Kohlschmidt",
    "wof:placetype":"venue"
},
  "geometry": {"coordinates":[7.4847397804,50.1715278625],"type":"Point"}
}