{
  "type": "Feature",
  "properties": {
    "iso:country":"DE",
    "sg:address":"Hauptstr. 98",
    "sg:city":"Sandhausen",
    "sg:postcode":"69207",
    "sg:province":"Baden-W\u00fcrttemberg",
    "wof:name":"Dr. Alexander Wiesinger Gmbh",
    "wof:placetype":"venue"
},
  "geometry": {"coordinates":[8.65854,49.342709],"type":"Point"}
}