{
  "type": "Feature",
  "properties": {
    "iso:country":"DE",
    "sg:address":"Zeppelinstr. 60",
    "sg:city":"M\u00fclheim",
    "sg:phone":"+49 208/375267",
    "sg:postcode":"45470",
    "sg:province":"Nordrhein-Westfalen",
    "wof:name":"Restaurant Ma Vie",
    "wof:placetype":"venue"
},
  "geometry": {"coordinates":[6.905257225,51.4165687561],"type":"Point"}
}