{
  "type": "Feature",
  "properties": {
    "iso:country":"DE",
    "sg:address":"In den Galleien 52",
    "sg:city":"Kleve",
    "sg:phone":"+49 2821/26460",
    "sg:postcode":"47533",
    "sg:province":"Nordrhein-Westfalen",
    "wof:name":"Bernd Thiele",
    "wof:placetype":"venue"
},
  "geometry": {"coordinates":[6.141867,51.780788],"type":"Point"}
}