{
  "type": "Feature",
  "properties": {
    "iso:country":"DE",
    "sg:address":"Hermann-Lamprecht-Str. 56",
    "sg:city":"Gnarrenburg",
    "sg:phone":"+49 4763/6086",
    "sg:postcode":"27442",
    "sg:province":"Niedersachsen",
    "wof:name":"Karl-heinz Osburg",
    "wof:placetype":"venue"
},
  "geometry": {"coordinates":[9.007813,53.389286],"type":"Point"}
}