{
  "type": "Feature",
  "properties": {
    "iso:country":"DE",
    "sg:address":"Alsterkrugchaussee 314",
    "sg:city":"Hamburg",
    "sg:phone":"+49 40/5141441",
    "sg:postcode":"22297",
    "sg:province":"Hamburg",
    "wof:name":"Square Music Jochen Lueg",
    "wof:placetype":"venue"
},
  "geometry": {"coordinates":[10.0033082962,53.615272522],"type":"Point"}
}