{
  "type": "Feature",
  "properties": {
    "iso:country":"DE",
    "sg:address":"L\u00fcderitz 8",
    "sg:city":"Borkum",
    "sg:phone":"+49 4922/3132",
    "sg:postcode":"26757",
    "sg:province":"Niedersachsen",
    "wof:name":"Alfred Vogt Steuerberater",
    "wof:placetype":"venue"
},
  "geometry": {"coordinates":[6.6632199287,53.5837783813],"type":"Point"}
}