{
  "type": "Feature",
  "properties": {
    "iso:country":"DE",
    "sg:address":"Hauptstr. 91",
    "sg:city":"Nordstemmen",
    "sg:phone":"+49 5069/96158",
    "sg:postcode":"31171",
    "sg:province":"Niedersachsen",
    "wof:name":"Hans-dietrich Pohl Gmbh",
    "wof:placetype":"venue"
},
  "geometry": {"coordinates":[9.7853164673,52.1644287109],"type":"Point"}
}