{
  "type": "Feature",
  "properties": {
    "iso:country":"DE",
    "sg:address":"Deichstr. 16",
    "sg:city":"Neuhaus",
    "sg:phone":"+49 4752/639",
    "sg:postcode":"21785",
    "sg:province":"Niedersachsen",
    "wof:name":"Wentzel-marim",
    "wof:placetype":"venue"
},
  "geometry": {"coordinates":[9.033901,53.803902],"type":"Point"}
}