{
  "type": "Feature",
  "properties": {
    "iso:country":"DE",
    "sg:address":"Spreequellstr. 28",
    "sg:city":"Neugersdorf",
    "sg:phone":"+49 3586/32732",
    "sg:postcode":"02727",
    "sg:province":"Sachsen",
    "wof:name":"Matthias Weber",
    "wof:placetype":"venue"
},
  "geometry": {"coordinates":[14.6194324493,50.9805984497],"type":"Point"}
}