{
  "type": "Feature",
  "properties": {
    "iso:country":"DE",
    "sg:address":"Kaiser-Karl-Str. 7",
    "sg:city":"Wei\u00dfenhorn",
    "sg:phone":"+49 7309/2429",
    "sg:postcode":"89264",
    "sg:province":"Bayern",
    "wof:name":"M. Huber",
    "wof:placetype":"venue"
},
  "geometry": {"coordinates":[10.1597614288,48.3052902222],"type":"Point"}
}