{
  "type": "Feature",
  "properties": {
    "iso:country":"DE",
    "sg:address":"Hermannstr. 4",
    "sg:city":"Werdau",
    "sg:phone":"+49 3761/3570",
    "sg:postcode":"08412",
    "sg:province":"Sachsen",
    "wof:name":"Sieghard Wittig",
    "wof:placetype":"venue"
},
  "geometry": {"coordinates":[12.376105,50.743164],"type":"Point"}
}