{
  "type": "Feature",
  "properties": {
    "iso:country":"DE",
    "sg:address":"Hauptstr. 4",
    "sg:city":"Seitingen-Oberflacht",
    "sg:phone":"+49 7464/3291",
    "sg:postcode":"78606",
    "sg:province":"Baden-W\u00fcrttemberg",
    "wof:name":"Oliver Siedler",
    "wof:placetype":"venue"
},
  "geometry": {"coordinates":[8.7200813293,48.0183105469],"type":"Point"}
}