{
  "type": "Feature",
  "properties": {
    "iso:country":"DE",
    "sg:address":"Burgstr. 13",
    "sg:city":"Stra\u00dflach-Dingharting",
    "sg:phone":"+49 8170/9969080",
    "sg:postcode":"82064",
    "sg:province":"Bayern",
    "wof:name":"Detlef Ro\u00dfbach Architekt",
    "wof:placetype":"venue"
},
  "geometry": {"coordinates":[11.510944,48.008018],"type":"Point"}
}