{
  "type": "Feature",
  "properties": {
    "iso:country":"DE",
    "sg:address":"Poststr. 2",
    "sg:city":"Lobenstein",
    "sg:phone":"+49 4936/6512428",
    "sg:postcode":"07356",
    "sg:province":"Th\u00fcringen",
    "wof:name":"Reiseb\u00dcro S\u00d6ll",
    "wof:placetype":"venue"
},
  "geometry": {"coordinates":[11.642167,50.45129],"type":"Point"}
}