{
  "type": "Feature",
  "properties": {
    "iso:country":"DE",
    "sg:address":"Altendorfer Str. 255-257",
    "sg:city":"Essen",
    "sg:phone":"+49 201/862070",
    "sg:postcode":"45143",
    "sg:province":"Nordrhein-Westfalen",
    "wof:name":"Rex-rotary Vertriebsges. Essen Mbh",
    "wof:placetype":"venue"
},
  "geometry": {"coordinates":[6.9834141731,51.4594345093],"type":"Point"}
}