{
  "type": "Feature",
  "properties": {
    "iso:country":"DE",
    "sg:address":"Gartenstr. 29",
    "sg:city":"Altensteig",
    "sg:phone":"+49 7453/2111",
    "sg:postcode":"72213",
    "sg:province":"Baden-W\u00fcrttemberg",
    "wof:name":"Wohnmobil & Caravan",
    "wof:placetype":"venue"
},
  "geometry": {"coordinates":[8.6088838577,48.586227417],"type":"Point"}
}