{
  "type": "Feature",
  "properties": {
    "iso:country":"DE",
    "sg:address":"Ludwigstr 30",
    "sg:city":"Offenbach",
    "sg:phone":"+49 69/8297570",
    "sg:postcode":"63067",
    "sg:province":"Hessen",
    "wof:name":"Offenbacher Stanzwerkzeugfabrik Gmbh & Co Kg",
    "wof:placetype":"venue"
},
  "geometry": {"coordinates":[8.755378,50.100639],"type":"Point"}
}