{
  "type": "Feature",
  "properties": {
    "iso:country":"DE",
    "sg:address":"Unterstr 1a",
    "sg:city":"Scheden",
    "sg:phone":"+49 5546/1062",
    "sg:postcode":"37127",
    "sg:province":"Niedersachsen",
    "wof:name":"E. + H. Weitemeyer Gmbh",
    "wof:placetype":"venue"
},
  "geometry": {"coordinates":[9.760391,51.445988],"type":"Point"}
}