{
  "type": "Feature",
  "properties": {
    "iso:country":"DE",
    "sg:address":"Marktplatz 21",
    "sg:city":"Ortenburg",
    "sg:phone":"+49 8542/3391",
    "sg:postcode":"94496",
    "sg:province":"Bayern",
    "wof:name":"Eiscafe Rialto",
    "wof:placetype":"venue"
},
  "geometry": {"coordinates":[13.223575,48.545876],"type":"Point"}
}