{
  "type": "Feature",
  "properties": {
    "iso:country":"DE",
    "sg:address":"Sudetenstr. 1",
    "sg:city":"Karlsruhe",
    "sg:phone":"+49 721",
    "sg:postcode":"76187",
    "sg:province":"Baden-W\u00fcrttemberg",
    "wof:name":"Doktor Autoglas",
    "wof:placetype":"venue"
},
  "geometry": {"coordinates":[8.3602104187,49.0387687683],"type":"Point"}
}