{
  "type": "Feature",
  "properties": {
    "iso:country":"DE",
    "sg:address":"Bl\u00fctenweg 17",
    "sg:city":"Lohr",
    "sg:phone":"+49 9352/9714",
    "sg:postcode":"97816",
    "sg:province":"Bayern",
    "wof:name":"Hans Roth Elektromeister",
    "wof:placetype":"venue"
},
  "geometry": {"coordinates":[9.566733,49.980286],"type":"Point"}
}