{
  "type": "Feature",
  "properties": {
    "iso:country":"DE",
    "sg:address":"Podewilsstr. 14",
    "sg:city":"Landshut",
    "sg:phone":"+49 871/28482",
    "sg:postcode":"84034",
    "sg:province":"Bayern",
    "wof:name":"R. Gietl Schl\u00fcsseldienst",
    "wof:placetype":"venue"
},
  "geometry": {"coordinates":[12.1541996002,48.5432243347],"type":"Point"}
}