{
  "type": "Feature",
  "properties": {
    "iso:country":"DE",
    "sg:address":"Am Volkspark 77",
    "sg:city":"Berlin",
    "sg:phone":"+49 4903085963110",
    "sg:postcode":"10715",
    "sg:province":"Berlin",
    "wof:name":"Sitehoppers",
    "wof:placetype":"venue"
},
  "geometry": {"coordinates":[13.3220586777,52.4827690125],"type":"Point"}
}