{
  "type": "Feature",
  "properties": {
    "iso:country":"DE",
    "sg:address":"Hunscheidtstr. 12",
    "sg:city":"Bochum",
    "sg:postcode":"44789",
    "sg:province":"Nordrhein-Westfalen",
    "wof:name":"Silikose-forschungsinstitut Der Berufsgenossenschaft",
    "wof:placetype":"venue"
},
  "geometry": {"coordinates":[7.2092909813,51.467754364],"type":"Point"}
}