{
  "type": "Feature",
  "properties": {
    "iso:country":"DE",
    "sg:address":"Winterstr. 6",
    "sg:city":"Karlsruhe",
    "sg:postcode":"76137",
    "sg:province":"Baden-W\u00fcrttemberg",
    "wof:name":"Beta - Beteiligungsges. Mbh",
    "wof:placetype":"venue"
},
  "geometry": {"coordinates":[8.404478,48.998234],"type":"Point"}
}