{
  "type": "Feature",
  "properties": {
    "iso:country":"DE",
    "sg:address":"Im M\u00fchlengrund 7",
    "sg:city":"Birkenau",
    "sg:phone":"+49 6201/31604",
    "sg:postcode":"69488",
    "sg:province":"Hessen",
    "wof:name":"Anso Gmbh",
    "wof:placetype":"venue"
},
  "geometry": {"coordinates":[8.700787,49.58287],"type":"Point"}
}