{
  "type": "Feature",
  "properties": {
    "iso:country":"DE",
    "sg:address":"Forster Str. 64-66",
    "sg:city":"D\u00f6bern",
    "sg:phone":"+49 35600/30710",
    "sg:postcode":"03159",
    "sg:province":"Brandenburg",
    "wof:name":"City-electronic B. Friederich Und D. Ladow Ohg",
    "wof:placetype":"venue"
},
  "geometry": {"coordinates":[14.5916175842,51.6203346252],"type":"Point"}
}