{
  "type": "Feature",
  "properties": {
    "iso:country":"DE",
    "sg:address":"Am Pfefferbach 12",
    "sg:city":"Oschersleben",
    "sg:phone":"+49 3949/96576",
    "sg:postcode":"39387",
    "sg:province":"Sachsen-Anhalt",
    "wof:name":"Erhard Br\u00fcckner",
    "wof:placetype":"venue"
},
  "geometry": {"coordinates":[11.258353,52.029316],"type":"Point"}
}