{
  "type": "Feature",
  "properties": {
    "iso:country":"DE",
    "sg:address":"Mundenheimer Str. 131",
    "sg:city":"Ludwigshafen",
    "sg:phone":"+49 621/5870580",
    "sg:postcode":"67061",
    "sg:province":"Rheinland-Pfalz",
    "wof:name":"Prof. Dr. Egon Stephan",
    "wof:placetype":"venue"
},
  "geometry": {"coordinates":[8.4441204071,49.4689102173],"type":"Point"}
}