{
  "type": "Feature",
  "properties": {
    "iso:country":"DE",
    "sg:address":"M\u00fcnchener Ring",
    "sg:city":"Schkeuditz",
    "sg:phone":"+49 34204/69804",
    "sg:postcode":"04435",
    "sg:province":"Sachsen",
    "wof:name":"H. I. S. Sportswear",
    "wof:placetype":"venue"
},
  "geometry": {"coordinates":[12.199126,51.400997],"type":"Point"}
}