{
  "type": "Feature",
  "properties": {
    "iso:country":"DE",
    "sg:address":"Alte R\u00fctzengr\u00fcner Str. 20",
    "sg:city":"Auerbach",
    "sg:phone":"+49 3744/212864",
    "sg:postcode":"08209",
    "sg:province":"Sachsen",
    "wof:name":"Lothar G\u00f6rler",
    "wof:placetype":"venue"
},
  "geometry": {"coordinates":[12.4168663025,50.5133666992],"type":"Point"}
}