{
  "type": "Feature",
  "properties": {
    "iso:country":"DE",
    "sg:address":"Stupbach",
    "sg:city":"L\u00fctzkampen",
    "sg:phone":"+49 6559/473",
    "sg:postcode":"54617",
    "sg:province":"Rheinland-Pfalz",
    "wof:name":"Gasthaus Waldecho",
    "wof:placetype":"venue"
},
  "geometry": {"coordinates":[6.1460199356,50.1760597229],"type":"Point"}
}