{
  "type": "Feature",
  "properties": {
    "iso:country":"DE",
    "sg:address":"M\u00fcnsterstr. 135-137",
    "sg:city":"Bocholt",
    "sg:phone":"+49 4928/71930",
    "sg:postcode":"46397",
    "sg:province":"Nordrhein-Westfalen",
    "wof:name":"Benning Elektrotechnk Und Elektronik Gmbh & Co. Kg",
    "wof:placetype":"venue"
},
  "geometry": {"coordinates":[6.639524,51.837749],"type":"Point"}
}