{
  "type": "Feature",
  "properties": {
    "iso:country":"DE",
    "sg:address":"Sommerauweg 8",
    "sg:city":"Zella-Mehlis",
    "sg:phone":"+49 3682/482171",
    "sg:postcode":"98544",
    "sg:province":"Th\u00fcringen",
    "wof:name":"G. Stock Immobilienmakler",
    "wof:placetype":"venue"
},
  "geometry": {"coordinates":[10.6697263718,50.6529884338],"type":"Point"}
}