{
  "type": "Feature",
  "properties": {
    "iso:country":"DE",
    "sg:address":"Hauptstr. 38",
    "sg:city":"Breitenbach",
    "sg:postcode":"37327",
    "sg:province":"Th\u00fcringen",
    "wof:name":"Katholisches Pfarramt Breitenholz",
    "wof:placetype":"venue"
},
  "geometry": {"coordinates":[10.3405408859,51.4050331116],"type":"Point"}
}