{
  "type": "Feature",
  "properties": {
    "iso:country":"DE",
    "sg:address":"F\u00e4hrgasse 9",
    "sg:city":"K\u00f6werich",
    "sg:phone":"+49 6507/3647",
    "sg:postcode":"54340",
    "sg:province":"Rheinland-Pfalz",
    "wof:name":"M. Basten",
    "wof:placetype":"venue"
},
  "geometry": {"coordinates":[6.8724741936,49.8411254883],"type":"Point"}
}