{
  "type": "Feature",
  "properties": {
    "iso:country":"DE",
    "sg:address":"Fritz-Reichle-Ring 11",
    "sg:city":"Radolfzell am Bodensee",
    "sg:phone":"+49 7732/996150",
    "sg:postcode":"78315",
    "sg:province":"Baden-W\u00fcrttemberg",
    "wof:name":"Stromeyer Planen Gmbh",
    "wof:placetype":"venue"
},
  "geometry": {"coordinates":[8.9576034546,47.7506332397],"type":"Point"}
}