{
  "type": "Feature",
  "properties": {
    "iso:country":"DE",
    "sg:address":"Hauptstr. 5",
    "sg:city":"Evessen",
    "sg:phone":"+49 5333/210",
    "sg:postcode":"38173",
    "sg:province":"Niedersachsen",
    "wof:name":"K. R\u00f6mmling",
    "wof:placetype":"venue"
},
  "geometry": {"coordinates":[10.7062082291,52.1895370483],"type":"Point"}
}