{
  "type": "Feature",
  "properties": {
    "iso:country":"DE",
    "sg:address":"Hochstr. 6",
    "sg:city":"Rhens",
    "sg:phone":"+49 2628/8969",
    "sg:postcode":"56321",
    "sg:province":"Rheinland-Pfalz",
    "wof:name":"R. Bindtner",
    "wof:placetype":"venue"
},
  "geometry": {"coordinates":[7.617547,50.280983],"type":"Point"}
}