{
  "type": "Feature",
  "properties": {
    "iso:country":"DE",
    "sg:address":"Marienhofweg 129-131",
    "sg:city":"Husum",
    "sg:phone":"+49 4841/72936",
    "sg:postcode":"25813",
    "sg:province":"Schleswig-Holstein",
    "wof:name":"Alu Hansen Gmbh & Co Kg",
    "wof:placetype":"venue"
},
  "geometry": {"coordinates":[9.066973,54.492867],"type":"Point"}
}