{
  "type": "Feature",
  "properties": {
    "iso:country":"DE",
    "sg:address":"F\u00fcrther Str. 5",
    "sg:city":"M\u00f6rlenbach",
    "sg:phone":"+49 6209/79279",
    "sg:postcode":"69509",
    "sg:province":"Hessen",
    "wof:name":"E. Wertz Und M. Schwabe",
    "wof:placetype":"venue"
},
  "geometry": {"coordinates":[8.7371482849,49.5983543396],"type":"Point"}
}