{
  "type": "Feature",
  "properties": {
    "iso:country":"DE",
    "sg:address":"Lindenstr. 14",
    "sg:city":"Bad Wildungen",
    "sg:phone":"+49 5621/6164",
    "sg:postcode":"34537",
    "sg:province":"Hessen",
    "wof:name":"Pizzeria Roma Da Nico",
    "wof:placetype":"venue"
},
  "geometry": {"coordinates":[9.124206543,51.1206245422],"type":"Point"}
}