{
  "type": "Feature",
  "properties": {
    "iso:country":"DE",
    "sg:address":"Schleuer",
    "sg:city":"Kollmar",
    "sg:phone":"+49 4124/3353",
    "sg:postcode":"25377",
    "sg:province":"Schleswig-Holstein",
    "wof:name":"Walter Sellnow",
    "wof:placetype":"venue"
},
  "geometry": {"coordinates":[9.451374,53.763973],"type":"Point"}
}