{
  "type": "Feature",
  "properties": {
    "iso:country":"DE",
    "sg:address":"Friedrich-Naumann-Str. 36",
    "sg:city":"Reutlingen",
    "sg:phone":"+49 7121/239131",
    "sg:postcode":"72762",
    "sg:province":"Baden-W\u00fcrttemberg",
    "wof:name":"Metzgerei Oskar Zeeb Gmbh",
    "wof:placetype":"venue"
},
  "geometry": {"coordinates":[9.1911897659,48.4874839783],"type":"Point"}
}