{
  "type": "Feature",
  "properties": {
    "iso:country":"DE",
    "sg:address":"Ha\u00dflocher Str. 126",
    "sg:city":"R\u00fcsselsheim",
    "sg:phone":"+49 6142/51569",
    "sg:postcode":"65428",
    "sg:province":"Hessen",
    "wof:name":"Robert Falbb & Sohn Bau- Und M\u00f6belschreinerei",
    "wof:placetype":"venue"
},
  "geometry": {"coordinates":[8.429706,49.98896],"type":"Point"}
}