{
  "type": "Feature",
  "properties": {
    "iso:country":"DE",
    "sg:address":"Mauerstr. 21",
    "sg:city":"Rudolstadt",
    "sg:phone":"+49 3672/422020",
    "sg:postcode":"07407",
    "sg:province":"Th\u00fcringen",
    "wof:name":"M. Rippich",
    "wof:placetype":"venue"
},
  "geometry": {"coordinates":[11.338603,50.719482],"type":"Point"}
}