{
  "type": "Feature",
  "properties": {
    "iso:country":"DE",
    "sg:address":"Albert-Hammann-Str. 9",
    "sg:city":"Biebesheim",
    "sg:phone":"+49 6258/6206",
    "sg:postcode":"64584",
    "sg:province":"Hessen",
    "wof:name":"Ernst Ludwig Sch\u00e4fer",
    "wof:placetype":"venue"
},
  "geometry": {"coordinates":[8.466489,49.781326],"type":"Point"}
}