{
  "type": "Feature",
  "properties": {
    "iso:country":"DE",
    "sg:address":"Rheydter Str. 12",
    "sg:city":"Grevenbroich",
    "sg:phone":"+49 2181/3663",
    "sg:postcode":"41515",
    "sg:province":"Nordrhein-Westfalen",
    "wof:name":"Im Str\u00e4u\u00dfchen",
    "wof:placetype":"venue"
},
  "geometry": {"coordinates":[6.582034111,51.09116745],"type":"Point"}
}