{
  "type": "Feature",
  "properties": {
    "iso:country":"DE",
    "sg:address":"Rosenstr. 5",
    "sg:city":"Herdecke",
    "sg:phone":"+49 2330/8306",
    "sg:postcode":"58313",
    "sg:province":"Nordrhein-Westfalen",
    "wof:name":"Andreas Stark",
    "wof:placetype":"venue"
},
  "geometry": {"coordinates":[7.426614,51.405315],"type":"Point"}
}