{
  "type": "Feature",
  "properties": {
    "iso:country":"DE",
    "sg:address":"Siebenmannstr. 4",
    "sg:city":"Karlsruhe",
    "sg:phone":"+49 721/47187",
    "sg:postcode":"76228",
    "sg:province":"Baden-W\u00fcrttemberg",
    "wof:name":"Michael Rieth-hoerst Ingenieur",
    "wof:placetype":"venue"
},
  "geometry": {"coordinates":[8.4581136703,48.9771232605],"type":"Point"}
}