{
  "type": "Feature",
  "properties": {
    "iso:country":"DE",
    "sg:address":"Pfahlstr. 10",
    "sg:city":"Eichst\u00e4tt",
    "sg:phone":"+49 8421/1424",
    "sg:postcode":"85072",
    "sg:province":"Bayern",
    "wof:name":"Gabriele F\u00e4hrmann",
    "wof:placetype":"venue"
},
  "geometry": {"coordinates":[11.182946,48.892651],"type":"Point"}
}