{
  "type": "Feature",
  "properties": {
    "iso:country":"DE",
    "sg:address":"Kapellenweg 36",
    "sg:city":"Immenstaad",
    "sg:phone":"+49 7545/1626",
    "sg:postcode":"88090",
    "sg:province":"Baden-W\u00fcrttemberg",
    "wof:name":"Lits & Partner Architekten",
    "wof:placetype":"venue"
},
  "geometry": {"coordinates":[9.357007,47.663315],"type":"Point"}
}