{
  "type": "Feature",
  "properties": {
    "iso:country":"DE",
    "sg:address":"K\u00f6lner Str. 21",
    "sg:city":"Kierspe",
    "sg:phone":"+49 2359/4948",
    "sg:postcode":"58566",
    "sg:province":"Nordrhein-Westfalen",
    "wof:name":"C. Harenberg",
    "wof:placetype":"venue"
},
  "geometry": {"coordinates":[7.6162409782,51.1278114319],"type":"Point"}
}