{
  "type": "Feature",
  "properties": {
    "iso:country":"DE",
    "sg:address":"Seuffertstr. 4",
    "sg:city":"W\u00fcrzburg",
    "sg:postcode":"97074",
    "sg:province":"Bayern",
    "wof:name":"Uccello Moden Gmbh",
    "wof:placetype":"venue"
},
  "geometry": {"coordinates":[9.945198,49.785595],"type":"Point"}
}