{
  "type": "Feature",
  "properties": {
    "iso:country":"DE",
    "sg:address":"Am Alten Sportplatz 23",
    "sg:city":"Wilstedt",
    "sg:phone":"+49 4283/982022",
    "sg:postcode":"27412",
    "sg:province":"Niedersachsen",
    "wof:name":"A. Schmidt",
    "wof:placetype":"venue"
},
  "geometry": {"coordinates":[9.105288,53.192776],"type":"Point"}
}