{
  "type": "Feature",
  "properties": {
    "iso:country":"DE",
    "sg:address":"Wasserstr. 2",
    "sg:city":"Steinfurt",
    "sg:phone":"+49 2551/82981",
    "sg:postcode":"48565",
    "sg:province":"Nordrhein-Westfalen",
    "wof:name":"Reisestudio Steinfurt Gmbh",
    "wof:placetype":"venue"
},
  "geometry": {"coordinates":[7.3395972252,52.1480522156],"type":"Point"}
}