{
  "type": "Feature",
  "properties": {
    "iso:country":"DE",
    "sg:address":"Kiez 25",
    "sg:city":"Neustadt-Glewe",
    "sg:postcode":"19306",
    "sg:province":"Mecklenburg-Vorpommern",
    "wof:name":"Katholisches Pfarramt Neustadt-glewe",
    "wof:placetype":"venue"
},
  "geometry": {"coordinates":[11.5823059082,53.3824157715],"type":"Point"}
}