{
  "type": "Feature",
  "properties": {
    "iso:country":"DE",
    "sg:address":"Lauberweg",
    "sg:city":"Regenstauf",
    "sg:postcode":"93128",
    "sg:province":"Bayern",
    "wof:name":"Michel & Sohn Ohg",
    "wof:placetype":"venue"
},
  "geometry": {"coordinates":[12.116235,49.10714],"type":"Point"}
}