{
  "type": "Feature",
  "properties": {
    "iso:country":"DE",
    "sg:address":"Finkenweg 26",
    "sg:city":"Ennigerloh",
    "sg:postcode":"59320",
    "sg:province":"Nordrhein-Westfalen",
    "wof:name":"Werth Beteiligungs Gmbh",
    "wof:placetype":"venue"
},
  "geometry": {"coordinates":[8.027856,51.857193],"type":"Point"}
}