{
  "type": "Feature",
  "properties": {
    "iso:country":"DE",
    "sg:address":"Hauptstra\u00dfe 63",
    "sg:city":"Kirschweiler",
    "sg:postcode":"55743",
    "sg:province":"Rheinland-Pfalz",
    "wof:name":"Kuba Erfahren",
    "wof:placetype":"venue"
},
  "geometry": {"coordinates":[7.242469,49.751942],"type":"Point"}
}