{
  "type": "Feature",
  "properties": {
    "iso:country":"DE",
    "sg:address":"Bahnhofstr. 38",
    "sg:city":"Malchin",
    "sg:phone":"+49 3994/210184",
    "sg:postcode":"17139",
    "sg:province":"Mecklenburg-Vorpommern",
    "wof:name":"H. Gabbert",
    "wof:placetype":"venue"
},
  "geometry": {"coordinates":[12.7570619583,53.7406845093],"type":"Point"}
}