{
  "type": "Feature",
  "properties": {
    "iso:country":"DE",
    "sg:address":"W\u00fclferstra\u00dfe 6",
    "sg:city":"Bad Salzuflen",
    "sg:phone":"+49 5222/369060",
    "sg:postcode":"32107",
    "sg:province":"Nordrhein-Westfalen",
    "wof:name":"Kramer & Dodt",
    "wof:placetype":"venue"
},
  "geometry": {"coordinates":[8.7235040665,52.0468788147],"type":"Point"}
}