{
  "type": "Feature",
  "properties": {
    "iso:country":"DE",
    "sg:address":"Weststr. 3",
    "sg:city":"Trebnitz",
    "sg:phone":"+49 34443/20672",
    "sg:postcode":"06682",
    "sg:province":"Sachsen-Anhalt",
    "wof:name":"D. Andreas Gmbh",
    "wof:placetype":"venue"
},
  "geometry": {"coordinates":[12.052822,51.103268],"type":"Point"}
}