{
  "type": "Feature",
  "properties": {
    "iso:country":"DE",
    "sg:address":"Kaiser-Wilhelm-Str. 11",
    "sg:city":"M\u00fclheim",
    "sg:phone":"+49 208/400127",
    "sg:postcode":"45476",
    "sg:province":"Nordrhein-Westfalen",
    "wof:name":"Irmgard Kozlowski",
    "wof:placetype":"venue"
},
  "geometry": {"coordinates":[6.8528008461,51.4509277344],"type":"Point"}
}