{
  "type": "Feature",
  "properties": {
    "iso:country":"DE",
    "sg:address":"Egon-Erwin-Kisch-Str. 10",
    "sg:city":"Schwerin",
    "sg:phone":"+49 385/3978104",
    "sg:postcode":"19061",
    "sg:province":"Mecklenburg-Vorpommern",
    "wof:name":"Gerba Hallenbau Gmbh & Co. Kg",
    "wof:placetype":"venue"
},
  "geometry": {"coordinates":[11.435105,53.604324],"type":"Point"}
}