{
  "type": "Feature",
  "properties": {
    "iso:country":"DE",
    "sg:address":"Angerstr. 1",
    "sg:city":"Brunnthal",
    "sg:postcode":"85649",
    "sg:province":"Bayern",
    "wof:name":"Sofi- Bautr\u00e4ger- Und Immobilien Beteiligungs Gmbh",
    "wof:placetype":"venue"
},
  "geometry": {"coordinates":[11.681545,48.005779],"type":"Point"}
}