{
  "type": "Feature",
  "properties": {
    "iso:country":"DE",
    "sg:address":"Vitusstr. 82",
    "sg:city":"D\u00f6rpen",
    "sg:phone":"+49 4963/1803",
    "sg:postcode":"26892",
    "sg:province":"Niedersachsen",
    "wof:name":"Bernhard Jansen",
    "wof:placetype":"venue"
},
  "geometry": {"coordinates":[7.321564,52.967499],"type":"Point"}
}