{
  "type": "Feature",
  "properties": {
    "iso:country":"DE",
    "sg:address":"B\u00f6dexer Tal 20",
    "sg:city":"H\u00f6xter",
    "sg:phone":"+49 5277/246",
    "sg:postcode":"37671",
    "sg:province":"Nordrhein-Westfalen",
    "wof:name":"Pension Agnes Ludwig",
    "wof:placetype":"venue"
},
  "geometry": {"coordinates":[9.3384532928,51.8369789124],"type":"Point"}
}