{
  "type": "Feature",
  "properties": {
    "iso:country":"DE",
    "sg:address":"Maybachstrasse 5",
    "sg:city":"Ostfildern",
    "sg:phone":"+49 711",
    "sg:postcode":"73760",
    "sg:province":"Baden-W\u00fcrttemberg",
    "wof:name":"Abbruch Weinert",
    "wof:placetype":"venue"
},
  "geometry": {"coordinates":[9.3016462326,48.7173843384],"type":"Point"}
}