{
  "type": "Feature",
  "properties": {
    "iso:country":"DE",
    "sg:address":"Pasewalker Allee 38",
    "sg:city":"Anklam",
    "sg:phone":"+49 3971/210454",
    "sg:postcode":"17389",
    "sg:province":"Mecklenburg-Vorpommern",
    "wof:name":"Reifenhaus Ralf Mauermann Gmbh",
    "wof:placetype":"venue"
},
  "geometry": {"coordinates":[13.705986,53.850269],"type":"Point"}
}