{
  "type": "Feature",
  "properties": {
    "iso:country":"DE",
    "sg:address":"Gro\u00dfer Brockhaus 5",
    "sg:city":"Leipzig",
    "sg:postcode":"04103",
    "sg:province":"Sachsen",
    "wof:name":"Fachklinikum Brandis Rehabilitationszentrum",
    "wof:placetype":"venue"
},
  "geometry": {"coordinates":[12.387364,51.340511],"type":"Point"}
}