{
  "type": "Feature",
  "properties": {
    "iso:country":"DE",
    "sg:address":"Oberkasseler Str. 37",
    "sg:city":"D\u00fcsseldorf",
    "sg:phone":"+49 211/575673",
    "sg:postcode":"40545",
    "sg:province":"Nordrhein-Westfalen",
    "wof:name":"El Gitano",
    "wof:placetype":"venue"
},
  "geometry": {"coordinates":[6.7554821968,51.2294387817],"type":"Point"}
}