{
  "type": "Feature",
  "properties": {
    "iso:country":"DE",
    "sg:address":"Voltastr. 10",
    "sg:city":"Stuttgart",
    "sg:postcode":"70376",
    "sg:province":"Baden-W\u00fcrttemberg",
    "wof:name":"Informa It-consulting Gmbh",
    "wof:placetype":"venue"
},
  "geometry": {"coordinates":[9.2176437378,48.811378479],"type":"Point"}
}