{
  "type": "Feature",
  "properties": {
    "iso:country":"DE",
    "sg:address":"Memeler Weg 1 A",
    "sg:city":"Sarstedt",
    "sg:phone":"+49 5066/1479",
    "sg:postcode":"31157",
    "sg:province":"Niedersachsen",
    "wof:name":"Goldmann Baubetreuung Gmbh",
    "wof:placetype":"venue"
},
  "geometry": {"coordinates":[9.8556318283,52.2360343933],"type":"Point"}
}