{
  "type": "Feature",
  "properties": {
    "iso:country":"DE",
    "sg:address":"Feldstr. 66",
    "sg:city":"Kiel",
    "sg:phone":"+49 431/86189",
    "sg:postcode":"24105",
    "sg:province":"Schleswig-Holstein",
    "wof:name":"Dieter H\u00fcschens",
    "wof:placetype":"venue"
},
  "geometry": {"coordinates":[10.140129,54.337814],"type":"Point"}
}