{
  "type": "Feature",
  "properties": {
    "iso:country":"DE",
    "sg:address":"M\u00fchlenkamp 11",
    "sg:city":"Korschenbroich",
    "sg:phone":"+49 2166/87979",
    "sg:postcode":"41352",
    "sg:province":"Nordrhein-Westfalen",
    "wof:name":"R. Lehnen",
    "wof:placetype":"venue"
},
  "geometry": {"coordinates":[6.5107588768,51.1902923584],"type":"Point"}
}