{
  "type": "Feature",
  "properties": {
    "iso:country":"DE",
    "sg:address":"Liebigstr. 12",
    "sg:city":"Alfeld",
    "sg:phone":"+49 5181/82077",
    "sg:postcode":"31061",
    "sg:province":"Niedersachsen",
    "wof:name":"Peter J\u00e4ckel Kommunikationssysteme Gmbh",
    "wof:placetype":"venue"
},
  "geometry": {"coordinates":[9.7939691544,51.9934425354],"type":"Point"}
}