{
  "type": "Feature",
  "properties": {
    "iso:country":"DE",
    "sg:address":"Schlo\u00df-Sch\u00f6nau-Str. 2-4",
    "sg:city":"Aachen",
    "sg:phone":"+49 241/12270",
    "sg:postcode":"52072",
    "sg:province":"Nordrhein-Westfalen",
    "wof:name":"Rheink\u00e4lte Gmbh",
    "wof:placetype":"venue"
},
  "geometry": {"coordinates":[6.0646691322,50.8131904602],"type":"Point"}
}