{
  "type": "Feature",
  "properties": {
    "iso:country":"DE",
    "sg:address":"Realschulstr 5",
    "sg:city":"Gro\u00df-Umstadt",
    "sg:phone":"+49 6078/2276",
    "sg:postcode":"64823",
    "sg:province":"Hessen",
    "wof:name":"Odenwald Druck U. Verlag Gmbh",
    "wof:placetype":"venue"
},
  "geometry": {"coordinates":[8.92628479,49.868522644],"type":"Point"}
}