{
  "type": "Feature",
  "properties": {
    "iso:country":"DE",
    "sg:address":"Heidenkampsweg 84",
    "sg:city":"Hamburg",
    "sg:postcode":"20097",
    "sg:province":"Hamburg",
    "wof:name":"Tsi Trans Software Hamburg Gmbh",
    "wof:placetype":"venue"
},
  "geometry": {"coordinates":[10.0298919678,53.5456466675],"type":"Point"}
}