{
  "type": "Feature",
  "properties": {
    "iso:country":"DE",
    "sg:address":"Treskower Ring 67",
    "sg:city":"Neuruppin",
    "sg:postcode":"16816",
    "sg:province":"Brandenburg",
    "wof:name":"Das Laufportal",
    "wof:placetype":"venue"
},
  "geometry": {"coordinates":[12.792511,52.892166],"type":"Point"}
}