{
  "type": "Feature",
  "properties": {
    "iso:country":"DE",
    "sg:address":"Am H\u00f6henstrauch 13",
    "sg:city":"Glash\u00fctten",
    "sg:postcode":"61479",
    "sg:province":"Hessen",
    "wof:name":"Fonte Fino Gmbh",
    "wof:placetype":"venue"
},
  "geometry": {"coordinates":[8.3778409958,50.2026252747],"type":"Point"}
}