{
  "type": "Feature",
  "properties": {
    "iso:country":"DE",
    "sg:address":"Ackerstr. 18",
    "sg:city":"Berlin",
    "sg:phone":"+49 30/3752077",
    "sg:postcode":"13585",
    "sg:province":"Berlin",
    "wof:name":"Holz-k\u00f6nig Ernst K\u00f6nig Ohg",
    "wof:placetype":"venue"
},
  "geometry": {"coordinates":[13.195999,52.546242],"type":"Point"}
}