{
  "type": "Feature",
  "properties": {
    "iso:country":"DE",
    "sg:address":"Am Sternbusch 3-9",
    "sg:city":"Rastede",
    "sg:postcode":"26180",
    "sg:province":"Niedersachsen",
    "wof:name":"Meiers Beteiligungsges. Mbh",
    "wof:placetype":"venue"
},
  "geometry": {"coordinates":[8.166477,53.292328],"type":"Point"}
}