{
  "type": "Feature",
  "properties": {
    "iso:country":"DE",
    "sg:address":"Engelbergerstr. 3",
    "sg:city":"Freiburg",
    "sg:postcode":"79106",
    "sg:province":"Baden-W\u00fcrttemberg",
    "wof:name":"Arbeitsgemeinschaft Jugend- Beratung Freiburg E. V.",
    "wof:placetype":"venue"
},
  "geometry": {"coordinates":[7.838125,47.995789],"type":"Point"}
}