{
  "type": "Feature",
  "properties": {
    "iso:country":"DE",
    "sg:address":"Seeweg 7",
    "sg:city":"Weinheim",
    "sg:phone":"+49 6201/599515",
    "sg:postcode":"69469",
    "sg:province":"Baden-W\u00fcrttemberg",
    "wof:name":"Modeagentur Sammet Gmbh",
    "wof:placetype":"venue"
},
  "geometry": {"coordinates":[8.6407251358,49.5305938721],"type":"Point"}
}