{
  "type": "Feature",
  "properties": {
    "iso:country":"DE",
    "sg:address":"Priesterweg 2",
    "sg:city":"Langerwisch",
    "sg:phone":"+49 33205/62087",
    "sg:postcode":"14557",
    "wof:name":"Lentz Elektrik",
    "wof:placetype":"venue"
},
  "geometry": {"coordinates":[13.072083,52.329891],"type":"Point"}
}