{
  "type": "Feature",
  "properties": {
    "iso:country":"DE",
    "sg:address":"Sendener Str. 22",
    "sg:city":"Jessen",
    "sg:phone":"+49 35388/20313",
    "sg:postcode":"06917",
    "sg:province":"Sachsen-Anhalt",
    "wof:name":"Wegebau Gmbh",
    "wof:placetype":"venue"
},
  "geometry": {"coordinates":[12.8246116638,51.7881736755],"type":"Point"}
}