{
  "type": "Feature",
  "properties": {
    "iso:country":"DE",
    "sg:address":"Fritz-Stra\u00dfmann-Str. 6",
    "sg:city":"Elmshorn",
    "sg:phone":"+49 4121/43570",
    "sg:postcode":"25337",
    "sg:province":"Schleswig-Holstein",
    "wof:name":"Channel 2000 Electronics Gmbh",
    "wof:placetype":"venue"
},
  "geometry": {"coordinates":[9.695079,53.742989],"type":"Point"}
}