{
  "type": "Feature",
  "properties": {
    "iso:country":"DE",
    "sg:address":"Zieglerberg 9",
    "sg:city":"Memmingen",
    "sg:phone":"+49 8331/923780",
    "sg:postcode":"87700",
    "sg:province":"Bayern",
    "wof:name":"Hans Rehm Architekt",
    "wof:placetype":"venue"
},
  "geometry": {"coordinates":[10.17524,48.019676],"type":"Point"}
}