{
  "type": "Feature",
  "properties": {
    "iso:country":"DE",
    "sg:city":"Ro\u00dfbach",
    "sg:phone":"+49 2638/5340",
    "sg:postcode":"53547",
    "sg:province":"Rheinland-Pfalz",
    "wof:name":"Reuschenbach & Kasakowsky",
    "wof:placetype":"venue"
},
  "geometry": {"coordinates":[7.416655,50.574944],"type":"Point"}
}