{
  "type": "Feature",
  "properties": {
    "iso:country":"DE",
    "sg:address":"Burgstr. 1",
    "sg:city":"Wernigerode",
    "sg:phone":"+49 3943/634529",
    "sg:postcode":"38855",
    "sg:province":"Sachsen-Anhalt",
    "wof:name":"Klaus Voigtlaender",
    "wof:placetype":"venue"
},
  "geometry": {"coordinates":[10.7877807617,51.8344345093],"type":"Point"}
}