{
  "type": "Feature",
  "properties": {
    "iso:country":"DE",
    "sg:address":"S\u00e4ngerstr. 2",
    "sg:city":"Lage",
    "sg:phone":"+49 5232/78107",
    "sg:postcode":"32791",
    "sg:province":"Nordrhein-Westfalen",
    "wof:name":"Harbrons Salate Gmbh",
    "wof:placetype":"venue"
},
  "geometry": {"coordinates":[8.7500352859,51.9649429321],"type":"Point"}
}