{
  "type": "Feature",
  "properties": {
    "iso:country":"DE",
    "sg:address":"Beecker Str. 64",
    "sg:city":"Wegberg",
    "sg:phone":"+49 2434/4702",
    "sg:postcode":"41844",
    "sg:province":"Nordrhein-Westfalen",
    "wof:name":"D. Lotz Ingenieur",
    "wof:placetype":"venue"
},
  "geometry": {"coordinates":[6.2830262184,51.1389732361],"type":"Point"}
}