{
  "type": "Feature",
  "properties": {
    "iso:country":"DE",
    "sg:address":"Donauw\u00f6rther Str. 138",
    "sg:city":"Augsburg",
    "sg:phone":"+49 821/217450",
    "sg:postcode":"86154",
    "sg:province":"Bayern",
    "wof:name":"Karl Moser Kraftfahrzeuge Gmbh",
    "wof:placetype":"venue"
},
  "geometry": {"coordinates":[10.88185215,48.3914833069],"type":"Point"}
}