{
  "type": "Feature",
  "properties": {
    "iso:country":"DE",
    "sg:address":"Roritzerstr. 27",
    "sg:city":"N\u00fcrnberg",
    "sg:postcode":"90419",
    "sg:province":"Bayern",
    "wof:name":"Bns Verm\u00f6gensverwaltung Gmbh",
    "wof:placetype":"venue"
},
  "geometry": {"coordinates":[11.0695953369,49.4620819092],"type":"Point"}
}