{
  "type": "Feature",
  "properties": {
    "iso:country":"DE",
    "sg:address":"Angelsburger Str. 57",
    "sg:city":"Wittmund",
    "sg:phone":"+49 4462/5689",
    "sg:postcode":"26409",
    "sg:province":"Niedersachsen",
    "wof:name":"Angelsburg",
    "wof:placetype":"venue"
},
  "geometry": {"coordinates":[7.7408819199,53.5736541748],"type":"Point"}
}