{
  "type": "Feature",
  "properties": {
    "iso:country":"DE",
    "sg:address":"Eggerscheidter Str. 131",
    "sg:city":"Ratingen",
    "sg:postcode":"40883",
    "sg:province":"Nordrhein-Westfalen",
    "wof:name":"Mertec Bautechnik Gmbh",
    "wof:placetype":"venue"
},
  "geometry": {"coordinates":[6.889394,51.320896],"type":"Point"}
}