{
  "type": "Feature",
  "properties": {
    "iso:country":"DE",
    "sg:address":"Bundesplatz 8",
    "sg:city":"Berlin",
    "sg:phone":"+49 30/8535338",
    "sg:postcode":"10715",
    "sg:province":"Berlin",
    "wof:name":"Marianne Zimmermann Masseurin",
    "wof:placetype":"venue"
},
  "geometry": {"coordinates":[13.329162,52.478966],"type":"Point"}
}