{
  "type": "Feature",
  "properties": {
    "iso:country":"DE",
    "sg:address":"Nansenpfad 25",
    "sg:city":"Kiel",
    "sg:phone":"+49 431",
    "sg:postcode":"24109",
    "sg:province":"Schleswig-Holstein",
    "wof:name":"Straehler-pohl-webdesign Internetdienstleistungen",
    "wof:placetype":"venue"
},
  "geometry": {"coordinates":[10.056286,54.333054],"type":"Point"}
}