{
  "type": "Feature",
  "properties": {
    "iso:country":"DE",
    "sg:address":"Riedstr. 46",
    "sg:city":"Ludwigsburg",
    "sg:phone":"+49 7141/32910",
    "sg:postcode":"71634",
    "sg:province":"Baden-W\u00fcrttemberg",
    "wof:name":"Pony Eil- Und Sonder- Transporte Gmbh",
    "wof:placetype":"venue"
},
  "geometry": {"coordinates":[9.1617860794,48.9066696167],"type":"Point"}
}