{
  "type": "Feature",
  "properties": {
    "iso:country":"DE",
    "sg:address":"Feldschmiede 52",
    "sg:city":"Itzehoe",
    "sg:postcode":"25524",
    "sg:province":"Schleswig-Holstein",
    "wof:name":"Prokon 5. Betriebs- Und Ver- Waltungsges Mbh & Co. New",
    "wof:placetype":"venue"
},
  "geometry": {"coordinates":[9.515692,53.925461],"type":"Point"}
}