{
  "type": "Feature",
  "properties": {
    "iso:country":"DE",
    "sg:address":"Coburger Str. 20 b",
    "sg:city":"Neustadt",
    "sg:phone":"+49 9568/5462",
    "sg:postcode":"96465",
    "sg:province":"Bayern",
    "wof:name":"A. Moeller",
    "wof:placetype":"venue"
},
  "geometry": {"coordinates":[11.1212615967,50.3282928467],"type":"Point"}
}