{
  "type": "Feature",
  "properties": {
    "iso:country":"DE",
    "sg:address":"Steinweg 22",
    "sg:city":"M\u00fchlhausen",
    "sg:phone":"+49 36014/42168",
    "sg:postcode":"99974",
    "sg:province":"Th\u00fcringen",
    "wof:name":"Western Store Gmbh",
    "wof:placetype":"venue"
},
  "geometry": {"coordinates":[10.459557,51.210056],"type":"Point"}
}