{
  "type": "Feature",
  "properties": {
    "iso:country":"DE",
    "sg:address":"Am Markt 3",
    "sg:city":"Wusterhausen",
    "sg:phone":"+49 33979/472",
    "sg:postcode":"16868",
    "sg:province":"Brandenburg",
    "wof:name":"Stadt- Und Kreismuseum",
    "wof:placetype":"venue"
},
  "geometry": {"coordinates":[12.461964,52.890724],"type":"Point"}
}