{
  "type": "Feature",
  "properties": {
    "iso:country":"DE",
    "sg:address":"Hirschstr. 4",
    "sg:city":"Scheer",
    "sg:phone":"+49 7572/8237",
    "sg:postcode":"72516",
    "sg:province":"Baden-W\u00fcrttemberg",
    "wof:name":"Ochsen",
    "wof:placetype":"venue"
},
  "geometry": {"coordinates":[9.2938508987,48.0735549927],"type":"Point"}
}