{
  "type": "Feature",
  "properties": {
    "iso:country":"DE",
    "sg:address":"Neulandstr. 25 a",
    "sg:city":"Sinsheim",
    "sg:phone":"+49 7261/95500",
    "sg:postcode":"74889",
    "sg:province":"Baden-W\u00fcrttemberg",
    "wof:name":"Fruchtpartner Gesellschaft F\u00fcr",
    "wof:placetype":"venue"
},
  "geometry": {"coordinates":[8.8849372864,49.2446289062],"type":"Point"}
}