{
  "type": "Feature",
  "properties": {
    "iso:country":"DE",
    "sg:address":"Friedrichstr. 35 B",
    "sg:city":"Eggenstein-Leopoldshafen",
    "sg:phone":"+49 4972/170890",
    "sg:postcode":"76344",
    "sg:province":"Baden-W\u00fcrttemberg",
    "wof:name":"Spar & Kreditbank Hardt Eg",
    "wof:placetype":"venue"
},
  "geometry": {"coordinates":[8.394444,49.077759],"type":"Point"}
}