{
  "type": "Feature",
  "properties": {
    "iso:country":"DE",
    "sg:address":"Felix-von-Roll-Str. 7",
    "sg:city":"Leverkusen",
    "sg:phone":"+49 214/58451",
    "sg:postcode":"51375",
    "sg:province":"Nordrhein-Westfalen",
    "wof:name":"Lindensch\u00e4nke",
    "wof:placetype":"venue"
},
  "geometry": {"coordinates":[7.0452618599,51.0343971252],"type":"Point"}
}