{
  "type": "Feature",
  "properties": {
    "iso:country":"DE",
    "sg:address":"Johann-Adam-Groh-Str. 2",
    "sg:city":"Brombachtal",
    "sg:phone":"+49 6063/2453",
    "sg:postcode":"64753",
    "sg:province":"Hessen",
    "wof:name":"Gastst\u00e4tte Sporthalle",
    "wof:placetype":"venue"
},
  "geometry": {"coordinates":[8.9531478882,49.7324867249],"type":"Point"}
}