{
  "type": "Feature",
  "properties": {
    "iso:country":"DE",
    "sg:address":"Hauptstr. 29",
    "sg:city":"Gerlingen",
    "sg:phone":"+49 7156/27336",
    "sg:postcode":"70839",
    "sg:province":"Baden-W\u00fcrttemberg",
    "wof:name":"Team S.herter",
    "wof:placetype":"venue"
},
  "geometry": {"coordinates":[9.062244,48.79911],"type":"Point"}
}