{
  "type": "Feature",
  "properties": {
    "iso:country":"DE",
    "sg:address":"Friedrich-Ebert-Str. 52",
    "sg:city":"Obertshausen",
    "sg:postcode":"63179",
    "sg:province":"Hessen",
    "wof:name":"Linea Arte Handelsges. Mbh",
    "wof:placetype":"venue"
},
  "geometry": {"coordinates":[8.8635597229,50.0844802856],"type":"Point"}
}