{
  "type": "Feature",
  "properties": {
    "iso:country":"DE",
    "sg:address":"Mainzer Str",
    "sg:city":"R\u00fcsselsheim",
    "sg:phone":"+49 6142/770",
    "sg:postcode":"65428",
    "sg:province":"Hessen",
    "wof:name":"Opel Special Vehicles Gmbh",
    "wof:placetype":"venue"
},
  "geometry": {"coordinates":[8.4113578796,49.9949455261],"type":"Point"}
}