{
  "type": "Feature",
  "properties": {
    "iso:country":"DE",
    "sg:address":"Dossestr. 15",
    "sg:city":"Berlin",
    "sg:phone":"+49 30/7063986",
    "sg:postcode":"10247",
    "sg:province":"Berlin",
    "wof:name":"Viba Licht-bausysteme Vinnemeier Gmbh & Co. Kg.",
    "wof:placetype":"venue"
},
  "geometry": {"coordinates":[13.472928,52.510082],"type":"Point"}
}