{
  "type": "Feature",
  "properties": {
    "iso:country":"DE",
    "sg:address":"Alsterbogen 34",
    "sg:city":"Flensburg",
    "sg:phone":"+49 461/39656",
    "sg:postcode":"24943",
    "sg:province":"Schleswig-Holstein",
    "wof:name":"Lothar Schmidt Inh. Meinhard Schmidt",
    "wof:placetype":"venue"
},
  "geometry": {"coordinates":[9.463286,54.797783],"type":"Point"}
}