{
  "type": "Feature",
  "properties": {
    "iso:country":"DE",
    "sg:address":"Kantstr. 3",
    "sg:city":"Saalfeld",
    "sg:phone":"+49 3671/55790",
    "sg:postcode":"07318",
    "sg:province":"Th\u00fcringen",
    "wof:name":"R. Velke",
    "wof:placetype":"venue"
},
  "geometry": {"coordinates":[11.352884,50.651459],"type":"Point"}
}