{
  "type": "Feature",
  "properties": {
    "iso:country":"DE",
    "sg:address":"Panoramastr. 14",
    "sg:city":"M\u00f6rlenbach",
    "sg:phone":"+49 6209/1717",
    "sg:postcode":"69509",
    "sg:province":"Hessen",
    "wof:name":"Manfred Schmitt Heissmangel",
    "wof:placetype":"venue"
},
  "geometry": {"coordinates":[8.7355470657,49.5956840515],"type":"Point"}
}