{
  "type": "Feature",
  "properties": {
    "iso:country":"DE",
    "sg:address":"Im Eichwald 7",
    "sg:city":"Bad Teinach-Zavelstein",
    "sg:phone":"+49 7053/1675",
    "sg:postcode":"75385",
    "sg:province":"Baden-W\u00fcrttemberg",
    "wof:name":"H. Bauer",
    "wof:placetype":"venue"
},
  "geometry": {"coordinates":[8.669762,48.706646],"type":"Point"}
}