{
  "type": "Feature",
  "properties": {
    "iso:country":"DE",
    "sg:address":"Fuggerstr. 10a",
    "sg:city":"Korschenbroich",
    "sg:phone":"+49 2161/999380",
    "sg:postcode":"41352",
    "sg:province":"Nordrhein-Westfalen",
    "wof:name":"Vev Gmbh",
    "wof:placetype":"venue"
},
  "geometry": {"coordinates":[6.5409340858,51.1987609863],"type":"Point"}
}