{
  "type": "Feature",
  "properties": {
    "iso:country":"DE",
    "sg:address":"Fulder Tor 15",
    "sg:city":"Alsfeld",
    "sg:phone":"+49 6631/4519",
    "sg:postcode":"36304",
    "sg:province":"Hessen",
    "wof:name":"Karl Ernst Koch",
    "wof:placetype":"venue"
},
  "geometry": {"coordinates":[9.275834,50.749035],"type":"Point"}
}