{
  "type": "Feature",
  "properties": {
    "iso:country":"DE",
    "sg:address":"Scheuerlenstr. 12",
    "sg:city":"Titisee-Neustadt",
    "sg:phone":"+49 7651/5163",
    "sg:postcode":"79822",
    "sg:province":"Baden-W\u00fcrttemberg",
    "wof:name":"Walter Hofmeier Steuerberater",
    "wof:placetype":"venue"
},
  "geometry": {"coordinates":[8.2146587372,47.9127960205],"type":"Point"}
}