{
  "type": "Feature",
  "properties": {
    "iso:country":"DE",
    "sg:address":"Okerring 14b",
    "sg:city":"Meinersen",
    "sg:phone":"+49 5372/9520",
    "sg:postcode":"38536",
    "sg:province":"Niedersachsen",
    "wof:name":"Altenheim Ahnsen An Der Oker Gmbh",
    "wof:placetype":"venue"
},
  "geometry": {"coordinates":[10.343848,52.484573],"type":"Point"}
}