{
  "type": "Feature",
  "properties": {
    "iso:country":"DE",
    "sg:address":"Alt-Buch 62",
    "sg:city":"Berlin",
    "sg:postcode":"13125",
    "sg:province":"Berlin",
    "wof:name":"B. Schilling",
    "wof:placetype":"venue"
},
  "geometry": {"coordinates":[13.50327,52.636505],"type":"Point"}
}