{
  "type": "Feature",
  "properties": {
    "iso:country":"DE",
    "sg:address":"Deichweg 2a",
    "sg:city":"Br\u00fcggen",
    "sg:phone":"+49 2163/952717",
    "sg:postcode":"41379",
    "sg:province":"Nordrhein-Westfalen",
    "wof:name":"Domicilio Wohnbau Gmbh & Co. Kg",
    "wof:placetype":"venue"
},
  "geometry": {"coordinates":[6.180802,51.239342],"type":"Point"}
}