{
  "type": "Feature",
  "properties": {
    "iso:country":"DE",
    "sg:address":"La\u00dfbrucher Str.",
    "sg:city":"Extertal",
    "sg:phone":"+49 5754/551",
    "sg:postcode":"32699",
    "sg:province":"Nordrhein-Westfalen",
    "wof:name":"Freibad Gemeinde Extertal",
    "wof:placetype":"venue"
},
  "geometry": {"coordinates":[9.058054924,52.1088638306],"type":"Point"}
}