{
  "type": "Feature",
  "properties": {
    "iso:country":"DE",
    "sg:address":"Schalker Str. 153",
    "sg:city":"Gelsenkirchen",
    "sg:phone":"+49 209/498757",
    "sg:postcode":"45881",
    "sg:province":"Nordrhein-Westfalen",
    "wof:name":"Spieltreff Automaten- Betriebs Gmbh",
    "wof:placetype":"venue"
},
  "geometry": {"coordinates":[7.088778,51.520668],"type":"Point"}
}