{
  "type": "Feature",
  "properties": {
    "iso:country":"DE",
    "sg:address":"Untergasse 19",
    "sg:city":"Gudensberg",
    "sg:phone":"+49 5603/6371",
    "sg:postcode":"34281",
    "sg:province":"Hessen",
    "wof:name":"Norbert Schmidt",
    "wof:placetype":"venue"
},
  "geometry": {"coordinates":[9.36787,51.177773],"type":"Point"}
}