{
  "type": "Feature",
  "properties": {
    "iso:country":"DE",
    "sg:address":"Wittekindstr. 4",
    "sg:city":"Dortmund",
    "sg:phone":"+49 231/121017",
    "sg:postcode":"44139",
    "sg:province":"Nordrhein-Westfalen",
    "wof:name":"J. Werner Gmbh",
    "wof:placetype":"venue"
},
  "geometry": {"coordinates":[7.446319,51.496399],"type":"Point"}
}