{
  "type": "Feature",
  "properties": {
    "iso:country":"DE",
    "sg:address":"M\u00f6llner Str. 6",
    "sg:city":"Ratzeburg",
    "sg:phone":"+49 4541/3494",
    "sg:postcode":"23909",
    "sg:province":"Schleswig-Holstein",
    "wof:name":"Heinrich Oldenburg B\u00e4ckerei Und Konditorei",
    "wof:placetype":"venue"
},
  "geometry": {"coordinates":[10.759787,53.698044],"type":"Point"}
}