{
  "type": "Feature",
  "properties": {
    "iso:country":"DE",
    "sg:address":"Carl-Zeiss-Str. 9",
    "sg:city":"Moers",
    "sg:phone":"+49 2841/97740",
    "sg:postcode":"47445",
    "sg:province":"Nordrhein-Westfalen",
    "wof:name":"Hti Collin & Schulten Kg",
    "wof:placetype":"venue"
},
  "geometry": {"coordinates":[6.598155,51.474125],"type":"Point"}
}