{
  "type": "Feature",
  "properties": {
    "iso:country":"DE",
    "sg:address":"Mallersrichter Str. 5",
    "sg:city":"Weiden",
    "sg:phone":"+49 961/27255",
    "sg:postcode":"92637",
    "sg:province":"Bayern",
    "wof:name":"Wilhelm Gollwitzer",
    "wof:placetype":"venue"
},
  "geometry": {"coordinates":[12.10154,49.668472],"type":"Point"}
}