{
  "type": "Feature",
  "properties": {
    "iso:country":"DE",
    "sg:address":"Bl\u00fccherstr. 36",
    "sg:city":"Kassel",
    "sg:phone":"+49 561/54161",
    "sg:postcode":"34123",
    "sg:province":"Hessen",
    "wof:name":"Christian Balcke Architekt",
    "wof:placetype":"venue"
},
  "geometry": {"coordinates":[9.505788,51.308903],"type":"Point"}
}