{
  "type": "Feature",
  "properties": {
    "iso:country":"DE",
    "sg:address":"Albert-Schweitzer-Str 18",
    "sg:city":"Kusterdingen",
    "sg:phone":"+49 7071/93290",
    "sg:postcode":"72127",
    "sg:province":"Baden-W\u00fcrttemberg",
    "wof:name":"Horst Schr\u00f6der Molkereieinrichtungen",
    "wof:placetype":"venue"
},
  "geometry": {"coordinates":[9.116965,48.525871],"type":"Point"}
}