{
  "type": "Feature",
  "properties": {
    "iso:country":"DE",
    "sg:address":"Dietrich-Bonhoeffer-Str. 26",
    "sg:city":"Zwickau",
    "sg:phone":"+49 375/452443",
    "sg:postcode":"08066",
    "sg:province":"Sachsen",
    "wof:name":"Hartmut Rummer",
    "wof:placetype":"venue"
},
  "geometry": {"coordinates":[12.5155553818,50.7300224304],"type":"Point"}
}