{
  "type": "Feature",
  "properties": {
    "iso:country":"DE",
    "sg:address":"K\u00f6nigsberger Str. 33",
    "sg:city":"Ostfildern",
    "sg:phone":"+49 711/349539",
    "sg:postcode":"73760",
    "sg:province":"Baden-W\u00fcrttemberg",
    "wof:name":"Ulrich Mundsinger Garten- Und Landschafts-",
    "wof:placetype":"venue"
},
  "geometry": {"coordinates":[9.279974,48.725845],"type":"Point"}
}