{
  "type": "Feature",
  "properties": {
    "iso:country":"DE",
    "sg:address":"Stadtbahnstr. 36",
    "sg:city":"Hamburg",
    "sg:postcode":"22393",
    "sg:province":"Hamburg",
    "wof:name":"Hausinhamburg Immobilien E. K.",
    "wof:placetype":"venue"
},
  "geometry": {"coordinates":[10.104999,53.653526],"type":"Point"}
}