{
  "type": "Feature",
  "properties": {
    "iso:country":"DE",
    "sg:address":"Karl-Marx-Str. 87",
    "sg:city":"Berlin",
    "sg:phone":"+49 30/6872080",
    "sg:postcode":"12043",
    "sg:province":"Berlin",
    "wof:name":"Lux-optik Gmbh",
    "wof:placetype":"venue"
},
  "geometry": {"coordinates":[13.435614,52.480843],"type":"Point"}
}