{
  "type": "Feature",
  "properties": {
    "iso:country":"DE",
    "sg:address":"Gymnasiumstr. 6",
    "sg:city":"Biberach",
    "sg:phone":"+49 7351/6753",
    "sg:postcode":"88400",
    "sg:province":"Baden-W\u00fcrttemberg",
    "wof:name":"C. Gro\u00dfmann",
    "wof:placetype":"venue"
},
  "geometry": {"coordinates":[9.7887582779,48.0997848511],"type":"Point"}
}