{
  "type": "Feature",
  "properties": {
    "iso:country":"DE",
    "sg:address":"Trappenweg 8c",
    "sg:city":"Falkensee",
    "sg:postcode":"14612",
    "sg:province":"Brandenburg",
    "wof:name":"Dlh Dittrich Export Gmbh",
    "wof:placetype":"venue"
},
  "geometry": {"coordinates":[13.0648555756,52.5599861145],"type":"Point"}
}