{
  "type": "Feature",
  "properties": {
    "iso:country":"DE",
    "sg:address":"Siemensallee 2",
    "sg:city":"Poing",
    "sg:phone":"+49 8121/720",
    "sg:postcode":"85586",
    "sg:province":"Bayern",
    "wof:name":"Oce Printing Systems Gmbh",
    "wof:placetype":"venue"
},
  "geometry": {"coordinates":[11.802297,48.167034],"type":"Point"}
}