{
  "type": "Feature",
  "properties": {
    "iso:country":"DE",
    "sg:address":"Wildeshauser Str. 14a",
    "sg:city":"Hatten",
    "sg:phone":"+49 4482/8194",
    "sg:postcode":"26209",
    "sg:province":"Niedersachsen",
    "wof:name":"Bistro Cappuccino",
    "wof:placetype":"venue"
},
  "geometry": {"coordinates":[8.3535261154,53.0174446106],"type":"Point"}
}