{
  "type": "Feature",
  "properties": {
    "iso:country":"DE",
    "sg:address":"Am Hopfengarten 1",
    "sg:city":"Bad Hersfeld",
    "sg:phone":"+49 6621/8096",
    "sg:postcode":"36251",
    "sg:province":"Hessen",
    "wof:name":"Saxco Saxena Engineers Consultant Gmbh",
    "wof:placetype":"venue"
},
  "geometry": {"coordinates":[9.6980323792,50.8625335693],"type":"Point"}
}