{
  "type": "Feature",
  "properties": {
    "iso:country":"DE",
    "sg:address":"Allensteiner Str.",
    "sg:city":"Einbeck",
    "sg:phone":"+49 5561/3110",
    "sg:postcode":"37574",
    "sg:province":"Niedersachsen",
    "wof:name":"Kws Saat Ag",
    "wof:placetype":"venue"
},
  "geometry": {"coordinates":[9.845625,51.817799],"type":"Point"}
}