{
  "type": "Feature",
  "properties": {
    "iso:country":"DE",
    "sg:address":"Zeilstr. 13",
    "sg:city":"Wiesbaden",
    "sg:phone":"+49 611/9200801",
    "sg:postcode":"65201",
    "sg:province":"Hessen",
    "wof:name":"Osip Gmbh",
    "wof:placetype":"venue"
},
  "geometry": {"coordinates":[8.1993398666,50.0464286804],"type":"Point"}
}