{
  "type": "Feature",
  "properties": {
    "iso:country":"DE",
    "sg:address":"Mittelweg 34",
    "sg:city":"Nordenham",
    "sg:postcode":"26954",
    "sg:province":"Niedersachsen",
    "wof:name":"Zahnarztpraxis Dr. Peter Hinrichs",
    "wof:placetype":"venue"
},
  "geometry": {"coordinates":[8.473647,53.483131],"type":"Point"}
}