{
  "type": "Feature",
  "properties": {
    "iso:country":"DE",
    "sg:address":"Rudekamp 46",
    "sg:city":"Gl\u00fccksburg",
    "sg:phone":"+49 4631/622333",
    "sg:postcode":"24960",
    "sg:province":"Schleswig-Holstein",
    "wof:name":"Klaus Und Inke Gregoreck",
    "wof:placetype":"venue"
},
  "geometry": {"coordinates":[9.5577983856,54.8345298767],"type":"Point"}
}