{
  "type": "Feature",
  "properties": {
    "iso:country":"DE",
    "sg:address":"Jasperallee 5",
    "sg:city":"Velpke",
    "sg:phone":"+49 5364",
    "sg:postcode":"38458",
    "sg:province":"Niedersachsen",
    "wof:name":"H\u00dcgel-immobilien",
    "wof:placetype":"venue"
},
  "geometry": {"coordinates":[10.9339866638,52.4068832397],"type":"Point"}
}