{
  "type": "Feature",
  "properties": {
    "iso:country":"DE",
    "sg:address":"Entenpfuhl 19",
    "sg:city":"Koblenz",
    "sg:phone":"+49 261/303470",
    "sg:postcode":"56068",
    "sg:province":"Rheinland-Pfalz",
    "wof:name":"Institut Fendel Rahmorthop\u00e4die Und Rehatechnik Gmbh",
    "wof:placetype":"venue"
},
  "geometry": {"coordinates":[7.5964379311,50.3603973389],"type":"Point"}
}