{
  "type": "Feature",
  "properties": {
    "iso:country":"DE",
    "sg:address":"Wittenberger Str. 92",
    "sg:city":"Bad Schmiedeberg",
    "sg:phone":"+49 34925/70308",
    "sg:postcode":"06905",
    "sg:province":"Sachsen-Anhalt",
    "wof:name":"Landfleischerei Horn Kg",
    "wof:placetype":"venue"
},
  "geometry": {"coordinates":[12.7375297546,51.6891136169],"type":"Point"}
}