{
  "type": "Feature",
  "properties": {
    "iso:country":"DE",
    "sg:address":"Martin-Luther-Platz 21",
    "sg:city":"Ansbach",
    "sg:phone":"+49 981/15091",
    "sg:postcode":"91522",
    "sg:province":"Bayern",
    "wof:name":"Ansbacher Reiseb\u00fcro Hans Glossner Omnibus-flug",
    "wof:placetype":"venue"
},
  "geometry": {"coordinates":[10.571064949,49.3029441833],"type":"Point"}
}