{
  "type": "Feature",
  "properties": {
    "iso:country":"DE",
    "sg:address":"Dorfstr. 38",
    "sg:city":"Wolfsberg",
    "sg:phone":"+49 34658/21061",
    "sg:postcode":"06536",
    "sg:province":"Sachsen-Anhalt",
    "wof:name":"Pvg Pflegeheimversorgungs Gmbh",
    "wof:placetype":"venue"
},
  "geometry": {"coordinates":[11.055734,51.483692],"type":"Point"}
}