{
  "type": "Feature",
  "properties": {
    "iso:country":"DE",
    "sg:address":"Marienstr. 26",
    "sg:city":"Offenbach",
    "sg:postcode":"63069",
    "sg:province":"Hessen",
    "wof:name":"Fus Beteiligungsges. Mbh",
    "wof:placetype":"venue"
},
  "geometry": {"coordinates":[8.763045,50.099007],"type":"Point"}
}