{
  "type": "Feature",
  "properties": {
    "iso:country":"DE",
    "sg:address":"Marktstr. 24",
    "sg:city":"Kobern-Gondorf",
    "sg:phone":"+49 2607/4211",
    "sg:postcode":"56330",
    "sg:province":"Rheinland-Pfalz",
    "wof:name":"Achim Matzelt",
    "wof:placetype":"venue"
},
  "geometry": {"coordinates":[7.4602470398,50.3119506836],"type":"Point"}
}