{
  "type": "Feature",
  "properties": {
    "iso:country":"DE",
    "sg:address":"Zum Sieken 1",
    "sg:city":"Suderburg",
    "sg:phone":"+49 5826/285",
    "sg:postcode":"29556",
    "sg:province":"Niedersachsen",
    "wof:name":"Alfred Scheidel Inh. Andreas Scheidel",
    "wof:placetype":"venue"
},
  "geometry": {"coordinates":[10.485124,52.912872],"type":"Point"}
}