{
  "type": "Feature",
  "properties": {
    "iso:country":"DE",
    "sg:address":"Aidenbachstr. 30",
    "sg:city":"M\u00fcnchen",
    "sg:phone":"+49 89/74879950",
    "sg:postcode":"81379",
    "sg:province":"Bayern",
    "wof:name":"Hl-markt",
    "wof:placetype":"venue"
},
  "geometry": {"coordinates":[11.5234498978,48.0990333557],"type":"Point"}
}