{
  "type": "Feature",
  "properties": {
    "iso:country":"DE",
    "sg:address":"Wiegenkamp 23",
    "sg:city":"Rhede",
    "sg:phone":"+49 2872/92760",
    "sg:postcode":"46414",
    "sg:province":"Nordrhein-Westfalen",
    "wof:name":"Herbalind Ggmbh",
    "wof:placetype":"venue"
},
  "geometry": {"coordinates":[6.709219,51.831165],"type":"Point"}
}