{
  "type": "Feature",
  "properties": {
    "iso:country":"DE",
    "sg:address":"Gr\u00fcne Trift am Walde 37",
    "sg:city":"Berlin",
    "sg:phone":"+49 30/6519097",
    "sg:postcode":"12557",
    "sg:province":"Berlin",
    "wof:name":"Manfred Schulze",
    "wof:placetype":"venue"
},
  "geometry": {"coordinates":[13.60053,52.432346],"type":"Point"}
}