{
  "type": "Feature",
  "properties": {
    "iso:country":"DE",
    "sg:address":"Altrheinstr. 39",
    "sg:city":"Eich",
    "sg:postcode":"67575",
    "sg:province":"Rheinland-Pfalz",
    "wof:name":"B\u00fcttel Verwaltung Karin Weber E. K.",
    "wof:placetype":"venue"
},
  "geometry": {"coordinates":[8.4021234512,49.7508239746],"type":"Point"}
}