{
  "type": "Feature",
  "properties": {
    "iso:country":"DE",
    "sg:address":"Von-Liebig-Str 34",
    "sg:city":"Marienfeld",
    "sg:phone":"+49 5247/98700",
    "sg:postcode":"33428",
    "sg:province":"Nordrhein-Westfalen",
    "wof:name":"Depo Werkzeugmaschinentechnik Gmbh & Co",
    "wof:placetype":"venue"
},
  "geometry": {"coordinates":[8.29402,51.952366],"type":"Point"}
}