{
  "type": "Feature",
  "properties": {
    "iso:country":"DE",
    "sg:address":"Rosengasse 1",
    "sg:city":"W\u00fcrzburg",
    "sg:phone":"+49 931",
    "sg:postcode":"97070",
    "sg:province":"Bayern",
    "wof:name":"Arge Festkultur",
    "wof:placetype":"venue"
},
  "geometry": {"coordinates":[9.928335,49.788708],"type":"Point"}
}