{
  "type": "Feature",
  "properties": {
    "iso:country":"DE",
    "sg:address":"Landsberger Str. 317",
    "sg:city":"M\u00fcnchen",
    "sg:postcode":"80687",
    "sg:province":"Bayern",
    "wof:name":"Bob Unternehmens- Betreuungs Gmbh",
    "wof:placetype":"venue"
},
  "geometry": {"coordinates":[11.497748,48.143383],"type":"Point"}
}