{
  "type": "Feature",
  "properties": {
    "iso:country":"DE",
    "sg:address":"Leffostr. 22",
    "sg:city":"L\u00f6ffingen",
    "sg:phone":"+49 7654/675",
    "sg:postcode":"79843",
    "sg:province":"Baden-W\u00fcrttemberg",
    "wof:name":"Alfons Schreiber",
    "wof:placetype":"venue"
},
  "geometry": {"coordinates":[8.3458681107,47.8766517639],"type":"Point"}
}