{
  "type": "Feature",
  "properties": {
    "iso:country":"DE",
    "sg:address":"Sieg-Lahn-Str. 41",
    "sg:city":"Bad Laasphe",
    "sg:phone":"+49 2754/260",
    "sg:postcode":"57334",
    "sg:province":"Nordrhein-Westfalen",
    "wof:name":"Klaus Hackler",
    "wof:placetype":"venue"
},
  "geometry": {"coordinates":[8.313664,50.938385],"type":"Point"}
}