{
  "type": "Feature",
  "properties": {
    "iso:country":"DE",
    "sg:address":"Breite Str. 15",
    "sg:city":"Pirna",
    "sg:phone":"+49 3501/528356",
    "sg:postcode":"01796",
    "sg:province":"Sachsen",
    "wof:name":"Graf",
    "wof:placetype":"venue"
},
  "geometry": {"coordinates":[13.9392290115,50.9589805603],"type":"Point"}
}