{
  "type": "Feature",
  "properties": {
    "iso:country":"DE",
    "sg:address":"Norbertstr. 5",
    "sg:city":"Hohensch\u00e4ftlarn",
    "sg:phone":"+49 8178/8277",
    "sg:postcode":"82069",
    "sg:province":"Bayern",
    "wof:name":"Hans-g. Lehner",
    "wof:placetype":"venue"
},
  "geometry": {"coordinates":[11.4598083496,47.9912414551],"type":"Point"}
}