{
  "type": "Feature",
  "properties": {
    "iso:country":"DE",
    "sg:address":"Kaufbeurer Str. 147",
    "sg:city":"Kempten",
    "sg:phone":"+49 831/703926",
    "sg:postcode":"87437",
    "sg:province":"Bayern",
    "wof:name":"Ld Handels Gmbh",
    "wof:placetype":"venue"
},
  "geometry": {"coordinates":[10.3230924606,47.7459602356],"type":"Point"}
}