{
  "type": "Feature",
  "properties": {
    "iso:country":"DE",
    "sg:address":"Im W\u00f6hrlet 16",
    "sg:city":"Leinburg",
    "sg:phone":"+49 9120/553",
    "sg:postcode":"91227",
    "sg:province":"Bayern",
    "wof:name":"W. Und R. Weidinger",
    "wof:placetype":"venue"
},
  "geometry": {"coordinates":[11.300881,49.457993],"type":"Point"}
}