{
  "type": "Feature",
  "properties": {
    "iso:country":"DE",
    "sg:address":"Borstelmannsweg 109 - 115",
    "sg:city":"Hamburg",
    "sg:phone":"+49 40/2190000",
    "sg:postcode":"20537",
    "sg:province":"Hamburg",
    "wof:name":"F. Carl Schr\u00f6ter",
    "wof:placetype":"venue"
},
  "geometry": {"coordinates":[10.052296,53.549366],"type":"Point"}
}