{
  "type": "Feature",
  "properties": {
    "iso:country":"DE",
    "sg:address":"Goethestr. 13",
    "sg:city":"W\u00fclfrath",
    "sg:phone":"+49 2058/2698",
    "sg:postcode":"42489",
    "sg:province":"Nordrhein-Westfalen",
    "wof:name":"Bistro Pegasus",
    "wof:placetype":"venue"
},
  "geometry": {"coordinates":[7.0361351967,51.2810096741],"type":"Point"}
}