{
  "type": "Feature",
  "properties": {
    "iso:country":"DE",
    "sg:address":"Am Knappsteig 49",
    "sg:city":"N\u00fcrnberg",
    "sg:phone":"+49 911/302545",
    "sg:postcode":"90427",
    "sg:province":"Bayern",
    "wof:name":"Kath. Pfarramt St. Thomas",
    "wof:placetype":"venue"
},
  "geometry": {"coordinates":[11.0396900177,49.5121688843],"type":"Point"}
}