{
  "type": "Feature",
  "properties": {
    "iso:country":"DE",
    "sg:address":"Velener Str. 55",
    "sg:city":"Velen",
    "sg:phone":"+49 2863/5276",
    "sg:postcode":"46342",
    "sg:province":"Nordrhein-Westfalen",
    "wof:name":"Josef Enning",
    "wof:placetype":"venue"
},
  "geometry": {"coordinates":[6.932237,51.892666],"type":"Point"}
}