{
  "type": "Feature",
  "properties": {
    "iso:country":"DE",
    "sg:address":"Am Fischteich 8",
    "sg:city":"M\u00f6hnesee",
    "sg:phone":"+49 2924/2776",
    "sg:postcode":"59519",
    "sg:province":"Nordrhein-Westfalen",
    "wof:name":"Pan Color Fotex Fotoservice Gmbh & Co. Kg",
    "wof:placetype":"venue"
},
  "geometry": {"coordinates":[8.1730184555,51.4911880493],"type":"Point"}
}