{
  "type": "Feature",
  "properties": {
    "iso:country":"DE",
    "sg:address":"Hermannstr. 7",
    "sg:city":"Darmstadt",
    "sg:phone":"+49 6151/997990",
    "sg:postcode":"64285",
    "sg:province":"Hessen",
    "wof:name":"Georg Wolf Hch.",
    "wof:placetype":"venue"
},
  "geometry": {"coordinates":[8.651957,49.861515],"type":"Point"}
}