{
  "type": "Feature",
  "properties": {
    "iso:country":"DE",
    "sg:address":"Am Schauenberg 10",
    "sg:city":"K\u00f6ln",
    "sg:phone":"+49 221/862208",
    "sg:postcode":"51107",
    "sg:province":"Nordrhein-Westfalen",
    "wof:name":"Ankerstein",
    "wof:placetype":"venue"
},
  "geometry": {"coordinates":[7.092373,50.926678],"type":"Point"}
}