{
  "type": "Feature",
  "properties": {
    "iso:country":"DE",
    "sg:address":"Hochstr. 52",
    "sg:city":"Wipperf\u00fcrth",
    "sg:phone":"+49 2267/9252",
    "sg:postcode":"51688",
    "sg:province":"Nordrhein-Westfalen",
    "wof:name":"Sanit\u00e4tshaus Massing Gmbh",
    "wof:placetype":"venue"
},
  "geometry": {"coordinates":[7.392415,51.11581],"type":"Point"}
}