{
  "type": "Feature",
  "properties": {
    "iso:country":"DE",
    "sg:address":"Gerhard-von-Are-Str. 4-6",
    "sg:city":"Bonn",
    "sg:phone":"+49 228/635022",
    "sg:postcode":"53111",
    "sg:province":"Nordrhein-Westfalen",
    "wof:name":"Rhein-apotheke",
    "wof:placetype":"venue"
},
  "geometry": {"coordinates":[7.09938,50.732838],"type":"Point"}
}