{
  "type": "Feature",
  "properties": {
    "iso:country":"DE",
    "sg:address":"Kunstseiden 10",
    "sg:city":"Pirna",
    "sg:phone":"+49 3501/46600",
    "sg:postcode":"01796",
    "sg:province":"Sachsen",
    "wof:name":"Skoda-adler",
    "wof:placetype":"venue"
},
  "geometry": {"coordinates":[13.902038,50.958324],"type":"Point"}
}