{
  "type": "Feature",
  "properties": {
    "iso:country":"DE",
    "sg:address":"Goethestr. 44",
    "sg:city":"Potsdam",
    "sg:phone":"+49 331/7480023",
    "sg:postcode":"14482",
    "sg:province":"Brandenburg",
    "wof:name":"H. Schefu\u00df",
    "wof:placetype":"venue"
},
  "geometry": {"coordinates":[13.110006,52.396309],"type":"Point"}
}