{
  "type": "Feature",
  "properties": {
    "iso:country":"DE",
    "sg:address":"Dorfstr. 6",
    "sg:city":"Hohenbucko",
    "sg:phone":"+49 35364/302",
    "sg:postcode":"04936",
    "sg:province":"Brandenburg",
    "wof:name":"Helmut Thiele",
    "wof:placetype":"venue"
},
  "geometry": {"coordinates":[13.466532,51.767403],"type":"Point"}
}