{
  "type": "Feature",
  "properties": {
    "iso:country":"DE",
    "sg:address":"Margeritenweg 16",
    "sg:city":"Northeim",
    "sg:phone":"+49 5551/1749",
    "sg:postcode":"37154",
    "sg:province":"Niedersachsen",
    "wof:name":"A. Hartmann",
    "wof:placetype":"venue"
},
  "geometry": {"coordinates":[10.0067996979,51.7066497803],"type":"Point"}
}