{
  "type": "Feature",
  "properties": {
    "iso:country":"DE",
    "sg:address":"Am Sonnfeld 12",
    "sg:city":"W\u00fcrzburg",
    "sg:phone":"+49 931/53750",
    "sg:postcode":"97076",
    "sg:province":"Bayern",
    "wof:name":"Ernst Porsch",
    "wof:placetype":"venue"
},
  "geometry": {"coordinates":[9.9767532349,49.8103637695],"type":"Point"}
}