{
  "type": "Feature",
  "properties": {
    "iso:country":"DE",
    "sg:address":"Leverner Str. 19",
    "sg:city":"Stemwede",
    "sg:phone":"+49 5745/2022",
    "sg:postcode":"32351",
    "sg:province":"Nordrhein-Westfalen",
    "wof:name":"Avo Gmbh",
    "wof:placetype":"venue"
},
  "geometry": {"coordinates":[8.4637098312,52.3741416931],"type":"Point"}
}