{
  "type": "Feature",
  "properties": {
    "iso:country":"DE",
    "sg:address":"Mainstr. 42",
    "sg:city":"Falkensee",
    "sg:phone":"+49 3322/207347",
    "sg:postcode":"14612",
    "sg:province":"Brandenburg",
    "wof:name":"Gerd Mildenberger",
    "wof:placetype":"venue"
},
  "geometry": {"coordinates":[13.0634727478,52.5762214661],"type":"Point"}
}