{
  "type": "Feature",
  "properties": {
    "iso:country":"DE",
    "sg:address":"Westwall 59",
    "sg:city":"Geldern",
    "sg:phone":"+49 2831/89402",
    "sg:postcode":"47608",
    "sg:province":"Nordrhein-Westfalen",
    "wof:name":"Klemens Krahwinkel",
    "wof:placetype":"venue"
},
  "geometry": {"coordinates":[6.319353,51.518654],"type":"Point"}
}