{
  "type": "Feature",
  "properties": {
    "iso:country":"DE",
    "sg:address":"Am Steig 10",
    "sg:city":"Marktrodach",
    "sg:phone":"+49 9261/53234",
    "sg:postcode":"96364",
    "sg:province":"Bayern",
    "wof:name":"Ralf Piwonski",
    "wof:placetype":"venue"
},
  "geometry": {"coordinates":[11.3830442429,50.249042511],"type":"Point"}
}