{
  "type": "Feature",
  "properties": {
    "iso:country":"DE",
    "sg:address":"Mondstr. 81",
    "sg:city":"M\u00fcnster",
    "sg:phone":"+49 251/381237",
    "sg:postcode":"48155",
    "sg:province":"Nordrhein-Westfalen",
    "wof:name":"Park-apotheke",
    "wof:placetype":"venue"
},
  "geometry": {"coordinates":[7.675814,51.960621],"type":"Point"}
}