{
  "type": "Feature",
  "properties": {
    "iso:country":"DE",
    "sg:address":"Friedenstr. 64",
    "sg:city":"Jena",
    "sg:phone":"+49 3641/421237",
    "sg:postcode":"07743",
    "sg:province":"Th\u00fcringen",
    "wof:name":"Antrona Gmbh",
    "wof:placetype":"venue"
},
  "geometry": {"coordinates":[11.5973539352,50.947681427],"type":"Point"}
}