{
  "type": "Feature",
  "properties": {
    "iso:country":"DE",
    "sg:address":"Nonnenwaldstr. 24",
    "sg:city":"Penzberg",
    "sg:phone":"+49 8856/2198",
    "sg:postcode":"82377",
    "sg:province":"Bayern",
    "wof:name":"Helmut Sch\u00e4fer",
    "wof:placetype":"venue"
},
  "geometry": {"coordinates":[11.380271,47.762081],"type":"Point"}
}