{
  "type": "Feature",
  "properties": {
    "iso:country":"DE",
    "sg:address":"Goethestr. 16",
    "sg:city":"Frankfurt",
    "sg:postcode":"60313",
    "sg:province":"Hessen",
    "wof:name":"Sot Grundst\u00fccksverwaltungs Gmbh & Co. Besitz Kg",
    "wof:placetype":"venue"
},
  "geometry": {"coordinates":[8.6747894287,50.1140518188],"type":"Point"}
}