{
  "type": "Feature",
  "properties": {
    "iso:country":"DE",
    "sg:address":"Wielstr. 41",
    "sg:city":"Wermelskirchen",
    "sg:postcode":"42929",
    "sg:province":"Nordrhein-Westfalen",
    "wof:name":"Eberhard D\u00fcrholt Beteiligungs Gmbh",
    "wof:placetype":"venue"
},
  "geometry": {"coordinates":[7.213118,51.132317],"type":"Point"}
}