{
  "type": "Feature",
  "properties": {
    "iso:country":"DE",
    "sg:address":"Hainsberger Str. 10",
    "sg:city":"Rabenau",
    "sg:postcode":"01734",
    "sg:province":"Sachsen",
    "wof:name":"M\u00fchlheu\u00dfer Bauelemente Gmbh",
    "wof:placetype":"venue"
},
  "geometry": {"coordinates":[13.640765,50.966537],"type":"Point"}
}