{
  "type": "Feature",
  "properties": {
    "iso:country":"DE",
    "sg:address":"Markt 10",
    "sg:city":"W\u00fcrselen",
    "sg:phone":"+49 2405/18403",
    "sg:postcode":"52146",
    "sg:province":"Nordrhein-Westfalen",
    "wof:name":"Hans-josef Th\u00f6nnissen",
    "wof:placetype":"venue"
},
  "geometry": {"coordinates":[6.1329398155,50.8182678223],"type":"Point"}
}