{
  "type": "Feature",
  "properties": {
    "iso:country":"DE",
    "sg:address":"Blumenthaler Str. 4b",
    "sg:city":"Torgelow",
    "sg:phone":"+49 3976/202428",
    "sg:postcode":"17358",
    "sg:province":"Mecklenburg-Vorpommern",
    "wof:name":"Rudi B\u00f6hm",
    "wof:placetype":"venue"
},
  "geometry": {"coordinates":[14.008382,53.63723],"type":"Point"}
}