{
  "type": "Feature",
  "properties": {
    "iso:country":"DE",
    "sg:address":"Schwabenheimer Weg 115",
    "sg:city":"Bad Kreuznach",
    "sg:phone":"+49 671/71606",
    "sg:postcode":"55543",
    "sg:province":"Rheinland-Pfalz",
    "wof:name":"Dixie Country Club",
    "wof:placetype":"venue"
},
  "geometry": {"coordinates":[7.885715,49.849007],"type":"Point"}
}