{
  "type": "Feature",
  "properties": {
    "iso:country":"DE",
    "sg:address":"In der Welle 55a",
    "sg:city":"Hagen",
    "sg:phone":"+49 2331/79091",
    "sg:postcode":"58091",
    "sg:province":"Nordrhein-Westfalen",
    "wof:name":"Kn\u00f6pfel Und Partner Architekten",
    "wof:placetype":"venue"
},
  "geometry": {"coordinates":[7.5016889572,51.3441467285],"type":"Point"}
}