{
  "type": "Feature",
  "properties": {
    "iso:country":"DE",
    "sg:address":"Krautgartenweg 10a",
    "sg:city":"Friedberg/St\u00e4tzling",
    "sg:phone":"+49 800 27982991",
    "sg:postcode":"86316",
    "sg:province":"Bayern",
    "wof:name":"Firma Mahler Telekommunikation",
    "wof:placetype":"venue"
},
  "geometry": {"coordinates":[10.978345,48.355072],"type":"Point"}
}