{
  "type": "Feature",
  "properties": {
    "iso:country":"DE",
    "sg:address":"Br\u00e4ndstr\u00f6mstr 14",
    "sg:city":"Jena",
    "sg:phone":"+49 3641/42750",
    "sg:postcode":"07749",
    "sg:province":"Th\u00fcringen",
    "wof:name":"Vacom Vakuum Komponenten & Messtechnik Gmbh",
    "wof:placetype":"venue"
},
  "geometry": {"coordinates":[11.6065330505,50.9325447083],"type":"Point"}
}