{
  "type": "Feature",
  "properties": {
    "iso:country":"DE",
    "sg:address":"Ostmarkstr. 84b",
    "sg:city":"Karlsruhe",
    "sg:phone":"+49 721/42215",
    "sg:postcode":"76227",
    "sg:province":"Baden-W\u00fcrttemberg",
    "wof:name":"Verena Layer",
    "wof:placetype":"venue"
},
  "geometry": {"coordinates":[8.4517841339,48.991985321],"type":"Point"}
}