{
  "type": "Feature",
  "properties": {
    "iso:country":"DE",
    "sg:address":"Hauptstr. 50",
    "sg:city":"Renchen",
    "sg:phone":"+49 7843/84200",
    "sg:postcode":"77871",
    "sg:province":"Baden-W\u00fcrttemberg",
    "wof:name":"G. Manna",
    "wof:placetype":"venue"
},
  "geometry": {"coordinates":[8.0119085312,48.586566925],"type":"Point"}
}