{
  "type": "Feature",
  "properties": {
    "iso:country":"DE",
    "sg:address":"Ziegelheide 27",
    "sg:city":"Kempen",
    "sg:phone":"+49 2152/52020",
    "sg:postcode":"47906",
    "sg:province":"Nordrhein-Westfalen",
    "wof:name":"A. Goldbach Kg Stahlhandel",
    "wof:placetype":"venue"
},
  "geometry": {"coordinates":[6.4032258987,51.3640670776],"type":"Point"}
}