{
  "type": "Feature",
  "properties": {
    "iso:country":"DE",
    "sg:address":"Tannenstr. 4",
    "sg:city":"K\u00fchlungsborn",
    "sg:phone":"+49 38293/14026",
    "sg:postcode":"18225",
    "sg:province":"Mecklenburg-Vorpommern",
    "wof:name":"J. Schulz",
    "wof:placetype":"venue"
},
  "geometry": {"coordinates":[11.724199,54.152412],"type":"Point"}
}