{
  "type": "Feature",
  "properties": {
    "iso:country":"DE",
    "sg:address":"Hochallee 44",
    "sg:city":"Hamburg",
    "sg:phone":"+49 40/449491",
    "sg:postcode":"20149",
    "sg:province":"Hamburg",
    "wof:name":"Hans Warnholz Ingenieur",
    "wof:placetype":"venue"
},
  "geometry": {"coordinates":[9.9863319397,53.5762138367],"type":"Point"}
}