{
  "type": "Feature",
  "properties": {
    "iso:country":"DE",
    "sg:address":"Dietrichsdorf 5",
    "sg:city":"Volkenschwand",
    "sg:phone":"+49 8754/96090",
    "sg:postcode":"84106",
    "sg:province":"Bayern",
    "wof:name":"H\u00f6gl Kompost- Und Recycling- Gmbh",
    "wof:placetype":"venue"
},
  "geometry": {"coordinates":[11.8572711945,48.6122741699],"type":"Point"}
}