{
  "type": "Feature",
  "properties": {
    "iso:country":"DE",
    "sg:address":"Schulgasse 9",
    "sg:city":"Heilbronn",
    "sg:phone":"+49 7131/84918",
    "sg:postcode":"74072",
    "sg:province":"Baden-W\u00fcrttemberg",
    "wof:name":"Top Food Im- Und Exportgesellschaft Mbh",
    "wof:placetype":"venue"
},
  "geometry": {"coordinates":[9.2209939957,49.1421356201],"type":"Point"}
}