{
  "type": "Feature",
  "properties": {
    "iso:country":"DE",
    "sg:address":"Im Bilskamp 15",
    "sg:city":"M\u00fcnster",
    "sg:phone":"+49 2506/2237",
    "sg:postcode":"48167",
    "sg:province":"Nordrhein-Westfalen",
    "wof:name":"Meinel",
    "wof:placetype":"venue"
},
  "geometry": {"coordinates":[7.740268,51.918133],"type":"Point"}
}