{
  "type": "Feature",
  "properties": {
    "iso:country":"DE",
    "sg:address":"T\u00fcrkheimer Str. 18",
    "sg:city":"Bad \u00dcberkingen",
    "sg:phone":"+49 7331/66775",
    "sg:postcode":"73337",
    "sg:province":"Baden-W\u00fcrttemberg",
    "wof:name":"U. R\u00f6cker Immobilienmakler",
    "wof:placetype":"venue"
},
  "geometry": {"coordinates":[9.7975788116,48.598274231],"type":"Point"}
}