{
  "type": "Feature",
  "properties": {
    "iso:country":"DE",
    "sg:address":"Kreuzherrenstr. 25",
    "sg:city":"D\u00fcren",
    "sg:phone":"+49 2421/62254",
    "sg:postcode":"52355",
    "sg:province":"Nordrhein-Westfalen",
    "wof:name":"Josef M\u00fcller",
    "wof:placetype":"venue"
},
  "geometry": {"coordinates":[6.431559,50.798004],"type":"Point"}
}