{
  "type": "Feature",
  "properties": {
    "iso:country":"DE",
    "sg:address":"Remscheider Str. 11a",
    "sg:city":"D\u00fcsseldorf",
    "sg:phone":"+49 211/3116520",
    "sg:postcode":"40215",
    "sg:province":"Nordrhein-Westfalen",
    "wof:name":"Werkstudio Werbung Und Design Gmbh",
    "wof:placetype":"venue"
},
  "geometry": {"coordinates":[6.7868199348,51.2117729187],"type":"Point"}
}