{
  "type": "Feature",
  "properties": {
    "iso:country":"DE",
    "sg:address":"Kantstr. 59",
    "sg:city":"Berlin",
    "sg:phone":"+49 30/3244179",
    "sg:postcode":"10627",
    "sg:province":"Berlin",
    "wof:name":"J\u00fcrgen Reinheimer Rechtsanwalt",
    "wof:placetype":"venue"
},
  "geometry": {"coordinates":[13.3051643372,52.506942749],"type":"Point"}
}