{
  "type": "Feature",
  "properties": {
    "iso:country":"DE",
    "sg:address":"Spechtweg 40",
    "sg:city":"Magdeburg",
    "sg:phone":"+49 391/7336778",
    "sg:postcode":"39110",
    "sg:province":"Sachsen-Anhalt",
    "wof:name":"Dr. Med. Roland Riedel",
    "wof:placetype":"venue"
},
  "geometry": {"coordinates":[11.589974,52.138184],"type":"Point"}
}