{
  "type": "Feature",
  "properties": {
    "iso:country":"DE",
    "sg:address":"Willinger Str. 2",
    "sg:city":"Bad Aibling",
    "sg:phone":"+49 8061/5862",
    "sg:postcode":"83043",
    "sg:province":"Bayern",
    "wof:name":"Henkenjohann & Sander Blaudruck Gmbh",
    "wof:placetype":"venue"
},
  "geometry": {"coordinates":[12.0007171631,47.8607254028],"type":"Point"}
}