{
  "type": "Feature",
  "properties": {
    "iso:country":"DE",
    "sg:address":"Schwabenstr. 56",
    "sg:city":"N\u00fcrnberg",
    "sg:postcode":"90459",
    "sg:province":"Bayern",
    "wof:name":"Sywa Systeme F\u00fcr Wasser Und Geotechnik Gmbh",
    "wof:placetype":"venue"
},
  "geometry": {"coordinates":[11.076466,49.432449],"type":"Point"}
}