{
  "type": "Feature",
  "properties": {
    "iso:country":"DE",
    "sg:address":"Finsterwalder Str. 17 a",
    "sg:city":"Hennersdorf",
    "sg:phone":"+49 35322/570",
    "sg:postcode":"03253",
    "sg:province":"Brandenburg",
    "wof:name":"Hebel Hennersdorf Gmbh & Co.kg",
    "wof:placetype":"venue"
},
  "geometry": {"coordinates":[13.619903,51.635845],"type":"Point"}
}