{
  "type": "Feature",
  "properties": {
    "iso:country":"DE",
    "sg:address":"Weidgasse 8",
    "sg:city":"Bensheim",
    "sg:phone":"+49 6251/75825",
    "sg:postcode":"64625",
    "sg:province":"Hessen",
    "wof:name":"T. G. Seitz",
    "wof:placetype":"venue"
},
  "geometry": {"coordinates":[8.6241874695,49.7038230896],"type":"Point"}
}