{
  "type": "Feature",
  "properties": {
    "iso:country":"DE",
    "sg:address":"Oststr. 17",
    "sg:city":"Limbach",
    "sg:phone":"+49 3722/2716",
    "sg:postcode":"09212",
    "sg:province":"Sachsen",
    "wof:name":"Kreissparkasse",
    "wof:placetype":"venue"
},
  "geometry": {"coordinates":[12.778842,50.857403],"type":"Point"}
}