{
  "type": "Feature",
  "properties": {
    "iso:country":"DE",
    "sg:address":"Hindenburgstr. 127",
    "sg:city":"Langenhagen",
    "sg:phone":"+49 511/739567",
    "sg:postcode":"30851",
    "sg:province":"Niedersachsen",
    "wof:name":"D. Seibert Finanzberater",
    "wof:placetype":"venue"
},
  "geometry": {"coordinates":[9.7538890839,52.4346504211],"type":"Point"}
}