{
  "type": "Feature",
  "properties": {
    "iso:country":"DE",
    "sg:address":"Schwabenweg 22",
    "sg:city":"Eschborn",
    "sg:phone":"+49 6173/93400",
    "sg:postcode":"65760",
    "sg:province":"Hessen",
    "wof:name":"Xcom Datenkommunikation Gmbh",
    "wof:placetype":"venue"
},
  "geometry": {"coordinates":[8.549991,50.153446],"type":"Point"}
}