{
  "type": "Feature",
  "properties": {
    "iso:country":"DE",
    "sg:address":"Am Rinkenpfuhl 28",
    "sg:city":"K\u00f6ln",
    "sg:phone":"+49 221/2404400",
    "sg:postcode":"50676",
    "sg:province":"Nordrhein-Westfalen",
    "wof:name":"J\u00fcrgen Busch Architekt",
    "wof:placetype":"venue"
},
  "geometry": {"coordinates":[6.94362,50.934647],"type":"Point"}
}