{
  "type": "Feature",
  "properties": {
    "iso:country":"DE",
    "sg:address":"Apostelstiege 21",
    "sg:city":"Dorsten",
    "sg:phone":"+49 2362/69577",
    "sg:postcode":"46284",
    "sg:province":"Nordrhein-Westfalen",
    "wof:name":"Opse Dorsten Karl-heinz Schr\u00f6der",
    "wof:placetype":"venue"
},
  "geometry": {"coordinates":[6.9531478882,51.6854743958],"type":"Point"}
}