{
  "type": "Feature",
  "properties": {
    "iso:country":"DE",
    "sg:address":"Essenberger Kirchweg 55",
    "sg:city":"Duisburg",
    "sg:phone":"+49 2065/60873",
    "sg:postcode":"47228",
    "sg:province":"Nordrhein-Westfalen",
    "wof:name":"G\u00fcnther Raab Schiffahrt",
    "wof:placetype":"venue"
},
  "geometry": {"coordinates":[6.712164,51.419182],"type":"Point"}
}