{
  "type": "Feature",
  "properties": {
    "iso:country":"DE",
    "sg:address":"Dresdner Str. 27",
    "sg:city":"Cossebaude",
    "sg:phone":"+49 351/4537471",
    "sg:postcode":"01462",
    "wof:name":"Industrievertretungen Sachsen Dr. Wolfgang Lis E. K.",
    "wof:placetype":"venue"
},
  "geometry": {"coordinates":[13.63907,51.08704],"type":"Point"}
}