{
  "type": "Feature",
  "properties": {
    "iso:country":"DE",
    "sg:address":"Wallstr. 5",
    "sg:city":"Dinslaken",
    "sg:phone":"+49 2064/770802",
    "sg:postcode":"46535",
    "sg:province":"Nordrhein-Westfalen",
    "wof:name":"Maggie Eastoe",
    "wof:placetype":"venue"
},
  "geometry": {"coordinates":[6.738665,51.563599],"type":"Point"}
}