{
  "type": "Feature",
  "properties": {
    "iso:country":"DE",
    "sg:address":"Auf L\u00fclingskreuz 61",
    "sg:city":"Korbach",
    "sg:phone":"+49 5631/6920",
    "sg:postcode":"34497",
    "sg:province":"Hessen",
    "wof:name":"R. M\u00fcller",
    "wof:placetype":"venue"
},
  "geometry": {"coordinates":[8.88921,51.278561],"type":"Point"}
}