{
  "type": "Feature",
  "properties": {
    "iso:country":"DE",
    "sg:address":"Gro\u00dfe Allee 32",
    "sg:city":"Dillingen",
    "sg:phone":"+49 9071/9508",
    "sg:postcode":"89407",
    "sg:province":"Bayern",
    "wof:name":"Volker Panitz",
    "wof:placetype":"venue"
},
  "geometry": {"coordinates":[10.4925670624,48.5806236267],"type":"Point"}
}