{
  "type": "Feature",
  "properties": {
    "iso:country":"DE",
    "sg:address":"Lange Gasse 32",
    "sg:city":"T\u00fcbingen",
    "sg:phone":"+49 7071/24710",
    "sg:postcode":"72070",
    "sg:province":"Baden-W\u00fcrttemberg",
    "wof:name":"Briefmarkenhaus Schrepfer",
    "wof:placetype":"venue"
},
  "geometry": {"coordinates":[9.0552902222,48.5218276978],"type":"Point"}
}