{
  "type": "Feature",
  "properties": {
    "iso:country":"DE",
    "sg:address":"Am Stadion 14",
    "sg:city":"Malente",
    "sg:phone":"+49 4523/3335",
    "sg:postcode":"23714",
    "sg:province":"Schleswig-Holstein",
    "wof:name":"Sportschule Malente",
    "wof:placetype":"venue"
},
  "geometry": {"coordinates":[10.5542879105,54.1701507568],"type":"Point"}
}