{
  "type": "Feature",
  "properties": {
    "iso:country":"DE",
    "sg:address":"Sedanstr. 10",
    "sg:city":"M\u00fcnchen",
    "sg:postcode":"81667",
    "sg:province":"Bayern",
    "wof:name":"Firstcom Gmbh & Co. Kg",
    "wof:placetype":"venue"
},
  "geometry": {"coordinates":[11.5974206924,48.1302680969],"type":"Point"}
}