{
  "type": "Feature",
  "properties": {
    "iso:country":"DE",
    "sg:address":"Auf der Heide 21",
    "sg:city":"Dingelst\u00e4dt",
    "sg:postcode":"37351",
    "sg:province":"Th\u00fcringen",
    "wof:name":"Ger\u00fcstbau Verwaltungsges. Mbh",
    "wof:placetype":"venue"
},
  "geometry": {"coordinates":[10.3262081146,51.3117141724],"type":"Point"}
}