{
  "type": "Feature",
  "properties": {
    "iso:country":"DE",
    "sg:address":"Emil-Jahn-Str. 34",
    "sg:city":"Groitzsch",
    "sg:phone":"+49 34296/42607",
    "sg:postcode":"04539",
    "sg:province":"Sachsen",
    "wof:name":"Arndt Kutzschbach",
    "wof:placetype":"venue"
},
  "geometry": {"coordinates":[12.280361,51.14875],"type":"Point"}
}