{
  "type": "Feature",
  "properties": {
    "iso:country":"DE",
    "sg:address":"Bretzinger Str. 19",
    "sg:city":"Hardheim",
    "sg:phone":"+49 6283/6241",
    "sg:postcode":"74736",
    "sg:province":"Baden-W\u00fcrttemberg",
    "wof:name":"Adelmann Gmbh",
    "wof:placetype":"venue"
},
  "geometry": {"coordinates":[9.4728012085,49.6041793823],"type":"Point"}
}