{
  "type": "Feature",
  "properties": {
    "iso:country":"DE",
    "sg:address":"Oberbachring 21",
    "sg:city":"Zellingen",
    "sg:phone":"+49 9364/800500",
    "sg:postcode":"97225",
    "sg:province":"Bayern",
    "wof:name":"Lifestyle Fitnesszentrum Gmbh",
    "wof:placetype":"venue"
},
  "geometry": {"coordinates":[9.824382782,49.8900871277],"type":"Point"}
}