{
  "type": "Feature",
  "properties": {
    "iso:country":"DE",
    "sg:address":"Fischerstr. 14",
    "sg:city":"Hanau",
    "sg:phone":"+49 6181/24608",
    "sg:postcode":"63450",
    "sg:province":"Hessen",
    "wof:name":"Matthias Seipel Rechtsanwalt",
    "wof:placetype":"venue"
},
  "geometry": {"coordinates":[8.9126358032,50.1324081421],"type":"Point"}
}