{
  "type": "Feature",
  "properties": {
    "iso:country":"DE",
    "sg:address":"Auf der Gr\u00fcn 22",
    "sg:city":"Miesbach",
    "sg:phone":"+49 8025/8209",
    "sg:postcode":"83714",
    "sg:province":"Bayern",
    "wof:name":"Harald Kreuzpointner",
    "wof:placetype":"venue"
},
  "geometry": {"coordinates":[11.824102,47.791882],"type":"Point"}
}