{
  "type": "Feature",
  "properties": {
    "iso:country":"DE",
    "sg:address":"Nogatstr. 32",
    "sg:city":"Berlin",
    "sg:phone":"+49 30/62609187",
    "sg:postcode":"12051",
    "sg:province":"Berlin",
    "wof:name":"J\u00f6rg Berndt",
    "wof:placetype":"venue"
},
  "geometry": {"coordinates":[13.4318380356,52.4691696167],"type":"Point"}
}