{
  "type": "Feature",
  "properties": {
    "iso:country":"DE",
    "sg:address":"Gutenbrunnenstr. 21",
    "sg:city":"W\u00f6rth",
    "sg:phone":"+49 7277/357",
    "sg:postcode":"76744",
    "sg:province":"Rheinland-Pfalz",
    "wof:name":"Michael Mayer Heiz\u00f6l-handlung",
    "wof:placetype":"venue"
},
  "geometry": {"coordinates":[8.0699548721,49.0640830994],"type":"Point"}
}