{
  "type": "Feature",
  "properties": {
    "iso:country":"DE",
    "sg:address":"Sch\u00fctzenstr. 52",
    "sg:city":"Meerbusch",
    "sg:phone":"+49 2150/2823",
    "sg:postcode":"40668",
    "sg:province":"Nordrhein-Westfalen",
    "wof:name":"Jakob Neuhausen",
    "wof:placetype":"venue"
},
  "geometry": {"coordinates":[6.711289,51.297829],"type":"Point"}
}