{
  "type": "Feature",
  "properties": {
    "iso:country":"DE",
    "sg:address":"Hommeswiese 94",
    "sg:city":"Freudenberg",
    "sg:phone":"+49 2734/7293",
    "sg:postcode":"57258",
    "sg:province":"Nordrhein-Westfalen",
    "wof:name":"Siebel-sp\u00e4th",
    "wof:placetype":"venue"
},
  "geometry": {"coordinates":[7.874402,50.919312],"type":"Point"}
}