{
  "type": "Feature",
  "properties": {
    "iso:country":"DE",
    "sg:address":"Markt 7",
    "sg:city":"Wesenberg",
    "sg:phone":"+49 39832/20774",
    "sg:postcode":"17255",
    "sg:province":"Mecklenburg-Vorpommern",
    "wof:name":"F. Rose",
    "wof:placetype":"venue"
},
  "geometry": {"coordinates":[12.9710197449,53.2813911438],"type":"Point"}
}