{
  "type": "Feature",
  "properties": {
    "iso:country":"DE",
    "sg:address":"Wehnserhorst 17",
    "sg:city":"Edemissen",
    "sg:phone":"+49 5176/7177",
    "sg:postcode":"31234",
    "sg:province":"Niedersachsen",
    "wof:name":"Felsmann-bau Gmbh",
    "wof:placetype":"venue"
},
  "geometry": {"coordinates":[10.268195,52.431164],"type":"Point"}
}