{
  "type": "Feature",
  "properties": {
    "iso:country":"DE",
    "sg:address":"Amtsfeldstr. 19",
    "sg:city":"Wernigerode",
    "sg:phone":"+49 3943/634925",
    "sg:postcode":"38855",
    "sg:province":"Sachsen-Anhalt",
    "wof:name":"Peter T\u00fcrk",
    "wof:placetype":"venue"
},
  "geometry": {"coordinates":[10.745535,51.819279],"type":"Point"}
}