{
  "type": "Feature",
  "properties": {
    "iso:country":"DE",
    "sg:address":"Alvesloher Str. 39",
    "sg:city":"Kaltenkirchen",
    "sg:postcode":"24568",
    "sg:province":"Schleswig-Holstein",
    "wof:name":"Hansebauherren Grund- St\u00fccksgesellschaft Mbh",
    "wof:placetype":"venue"
},
  "geometry": {"coordinates":[9.924074173,53.8159332275],"type":"Point"}
}