{
  "type": "Feature",
  "properties": {
    "iso:country":"DE",
    "sg:address":"Altewiekring 51",
    "sg:city":"Braunschweig",
    "sg:phone":"+49 531/76042",
    "sg:postcode":"38102",
    "sg:province":"Niedersachsen",
    "wof:name":"Altewiek-apotheke",
    "wof:placetype":"venue"
},
  "geometry": {"coordinates":[10.542935,52.26371],"type":"Point"}
}