{
  "type": "Feature",
  "properties": {
    "iso:country":"DE",
    "sg:address":"Alte Landstr. 98",
    "sg:city":"Hamburg",
    "sg:phone":"+49 40/5386236",
    "sg:postcode":"22339",
    "sg:province":"Hamburg",
    "wof:name":"Jens Claussen",
    "wof:placetype":"venue"
},
  "geometry": {"coordinates":[10.0499801636,53.6382408142],"type":"Point"}
}