{
  "type": "Feature",
  "properties": {
    "iso:country":"DE",
    "sg:address":"Richard-Strau\u00df-Str. 43",
    "sg:city":"H\u00f6chstadt",
    "sg:postcode":"91315",
    "sg:province":"Bayern",
    "wof:name":"Frank Gmbh",
    "wof:placetype":"venue"
},
  "geometry": {"coordinates":[10.8234262466,49.7108573914],"type":"Point"}
}