{
  "type": "Feature",
  "properties": {
    "iso:country":"DE",
    "sg:address":"Gertrud-B\u00e4umer-Str. 2",
    "sg:city":"Wiesbaden",
    "sg:phone":"+49 611/9320440",
    "sg:postcode":"65189",
    "sg:province":"Hessen",
    "wof:name":"Stramitzer Und Dei\u00dfler Architekten",
    "wof:placetype":"venue"
},
  "geometry": {"coordinates":[8.257812,50.080975],"type":"Point"}
}