{
  "type": "Feature",
  "properties": {
    "iso:country":"DE",
    "sg:address":"Hauptstr. 82",
    "sg:city":"Eningen",
    "sg:postcode":"72800",
    "sg:province":"Baden-W\u00fcrttemberg",
    "wof:name":"Immo-serv Haible Gmbh",
    "wof:placetype":"venue"
},
  "geometry": {"coordinates":[9.260844,48.487598],"type":"Point"}
}