{
  "type": "Feature",
  "properties": {
    "iso:country":"DE",
    "sg:address":"Stolper Str. 28",
    "sg:city":"Bergfelde",
    "sg:phone":"+49 3303/402309",
    "sg:postcode":"16562",
    "sg:province":"Brandenburg",
    "wof:name":"Raimund Neumann",
    "wof:placetype":"venue"
},
  "geometry": {"coordinates":[13.3104448318,52.6613044739],"type":"Point"}
}