{
  "type": "Feature",
  "properties": {
    "iso:country":"DE",
    "sg:address":"Riedstr. 2",
    "sg:city":"Oberndorf",
    "sg:phone":"+49 9090/1008",
    "sg:postcode":"86698",
    "sg:province":"Bayern",
    "wof:name":"B.braun",
    "wof:placetype":"venue"
},
  "geometry": {"coordinates":[10.8662900925,48.6668548584],"type":"Point"}
}