{
  "type": "Feature",
  "properties": {
    "iso:country":"DE",
    "sg:address":"Im Taubhaus 23",
    "sg:city":"R\u00f6dermark",
    "sg:phone":"+49 6074/629701",
    "sg:postcode":"63322",
    "sg:province":"Hessen",
    "wof:name":"Gds Internet-service Gmbh",
    "wof:placetype":"venue"
},
  "geometry": {"coordinates":[8.7887248993,49.9710502625],"type":"Point"}
}