{
  "type": "Feature",
  "properties": {
    "iso:country":"DE",
    "sg:address":"Rudolf-Breitscheid-Str. 18",
    "sg:city":"Deuben",
    "sg:phone":"+49 34443/20281",
    "sg:postcode":"06682",
    "sg:province":"Sachsen-Anhalt",
    "wof:name":"Rolf Beinroth",
    "wof:placetype":"venue"
},
  "geometry": {"coordinates":[12.075887,51.122059],"type":"Point"}
}