{
  "type": "Feature",
  "properties": {
    "iso:country":"DE",
    "sg:address":"Lindenstr. 60",
    "sg:city":"Perleberg",
    "sg:postcode":"19348",
    "sg:province":"Brandenburg",
    "wof:name":"Berg Gmbh",
    "wof:placetype":"venue"
},
  "geometry": {"coordinates":[11.860071,53.079937],"type":"Point"}
}