{
  "type": "Feature",
  "properties": {
    "iso:country":"DE",
    "sg:city":"Ko\u00dfwig",
    "sg:postcode":"03226",
    "sg:province":"Brandenburg",
    "wof:name":"Dk-bau Gmbh",
    "wof:placetype":"venue"
},
  "geometry": {"coordinates":[14.029166,51.777691],"type":"Point"}
}