{
  "type": "Feature",
  "properties": {
    "iso:country":"DE",
    "sg:address":"Dorfstr. 24",
    "sg:city":"Ennigerloh",
    "sg:phone":"+49 2524/7121",
    "sg:postcode":"59320",
    "sg:province":"Nordrhein-Westfalen",
    "wof:name":"Josef Mense",
    "wof:placetype":"venue"
},
  "geometry": {"coordinates":[8.082588,51.865463],"type":"Point"}
}