{
  "type": "Feature",
  "properties": {
    "iso:country":"DE",
    "sg:address":"N5:: 15",
    "sg:city":"Mannheim",
    "sg:phone":"+49 621/20277",
    "sg:postcode":"68161",
    "sg:province":"Baden-W\u00fcrttemberg",
    "wof:name":"Stempel Sperling",
    "wof:placetype":"venue"
},
  "geometry": {"coordinates":[8.468317,49.484791],"type":"Point"}
}