{
  "type": "Feature",
  "properties": {
    "iso:country":"DE",
    "sg:address":"Wiltrudenstr. 3",
    "sg:city":"M\u00fcnchen",
    "sg:phone":"+49 89/336610",
    "sg:postcode":"80805",
    "sg:province":"Bayern",
    "wof:name":"Bahe Assekuranzmakler Gmbh",
    "wof:placetype":"venue"
},
  "geometry": {"coordinates":[11.5920772552,48.1672401428],"type":"Point"}
}