{
  "type": "Feature",
  "properties": {
    "iso:country":"DE",
    "sg:address":"Mannheimer Str. 82",
    "sg:city":"Bad Kreuznach",
    "sg:phone":"+49 671/31178",
    "sg:postcode":"55545",
    "sg:province":"Rheinland-Pfalz",
    "wof:name":"Mohamed Khezri",
    "wof:placetype":"venue"
},
  "geometry": {"coordinates":[7.856361866,49.8453674316],"type":"Point"}
}