{
  "type": "Feature",
  "properties": {
    "iso:country":"DE",
    "sg:address":"Konrad-Kappler-Str. 5",
    "sg:city":"Rodgau",
    "sg:phone":"+49 6106/18800",
    "sg:postcode":"63110",
    "sg:province":"Hessen",
    "wof:name":"Journal-biercafe",
    "wof:placetype":"venue"
},
  "geometry": {"coordinates":[8.8811254501,50.0263824463],"type":"Point"}
}