{
  "type": "Feature",
  "properties": {
    "iso:country":"DE",
    "sg:address":"Feldschmiede 6",
    "sg:city":"Itzehoe",
    "sg:phone":"+49 4821/62226",
    "sg:postcode":"25524",
    "sg:province":"Schleswig-Holstein",
    "wof:name":"Hamburg-mannheimer Versicherungsgesellschaft",
    "wof:placetype":"venue"
},
  "geometry": {"coordinates":[9.517244339,53.9238624573],"type":"Point"}
}