{
  "type": "Feature",
  "properties": {
    "iso:country":"DE",
    "sg:address":"Am Lupinenfeld 86",
    "sg:city":"Berlin",
    "sg:phone":"+49 30/5638480",
    "sg:postcode":"12623",
    "sg:province":"Berlin",
    "wof:name":"Dirk Eichmann",
    "wof:placetype":"venue"
},
  "geometry": {"coordinates":[13.620426178,52.5220832825],"type":"Point"}
}