{
  "type": "Feature",
  "properties": {
    "iso:country":"DE",
    "sg:address":"Vorderstr. 9",
    "sg:city":"K\u00f6nigstein",
    "sg:phone":"+49 6173/940105",
    "sg:postcode":"61462",
    "sg:province":"Hessen",
    "wof:name":"R\u00fcdiger Gr\u00f6lz",
    "wof:placetype":"venue"
},
  "geometry": {"coordinates":[8.4936265945,50.1707382202],"type":"Point"}
}