{
  "type": "Feature",
  "properties": {
    "iso:country":"DE",
    "sg:address":"Herzog-Georg-Str. 39",
    "sg:city":"Lauingen",
    "sg:phone":"+49 9072/4560",
    "sg:postcode":"89415",
    "sg:province":"Bayern",
    "wof:name":"Albert Frey",
    "wof:placetype":"venue"
},
  "geometry": {"coordinates":[10.428015,48.568085],"type":"Point"}
}