{
  "type": "Feature",
  "properties": {
    "iso:country":"DE",
    "sg:address":"Stockh\u00e4user Str. 32",
    "sg:city":"Wartenberg",
    "sg:phone":"+49 6648/2428",
    "sg:postcode":"36367",
    "sg:province":"Hessen",
    "wof:name":"H. Und K. Schr\u00f6ter",
    "wof:placetype":"venue"
},
  "geometry": {"coordinates":[9.473437,50.606091],"type":"Point"}
}