{
  "type": "Feature",
  "properties": {
    "iso:country":"DE",
    "sg:address":"Rather Str. 62",
    "sg:city":"D\u00fcren",
    "sg:phone":"+49 2421/930000",
    "sg:postcode":"52353",
    "sg:province":"Nordrhein-Westfalen",
    "wof:name":"Margarete Dickas-hohr",
    "wof:placetype":"venue"
},
  "geometry": {"coordinates":[6.4979968071,50.8388061523],"type":"Point"}
}