{
  "type": "Feature",
  "properties": {
    "iso:country":"DE",
    "sg:address":"Dettenheimer Str 28",
    "sg:city":"Wei\u00dfenburg",
    "sg:phone":"+49 9141/85890",
    "sg:postcode":"91781",
    "sg:province":"Bayern",
    "wof:name":"H\u00c4rthalex H\u00c4rtetechnik Gmbh",
    "wof:placetype":"venue"
},
  "geometry": {"coordinates":[10.9531707764,49.0062637329],"type":"Point"}
}