{
  "type": "Feature",
  "properties": {
    "iso:country":"DE",
    "sg:address":"Landsberger Str. 32",
    "sg:city":"P\u00fcrgen",
    "sg:phone":"+49 8196/257",
    "sg:postcode":"86932",
    "sg:province":"Bayern",
    "wof:name":"K. H. Heilrath Bau Gmbh",
    "wof:placetype":"venue"
},
  "geometry": {"coordinates":[10.9154558182,48.0295600891],"type":"Point"}
}