{
  "type": "Feature",
  "properties": {
    "iso:country":"DE",
    "sg:address":"Rosenstr. 77",
    "sg:city":"Dresden",
    "sg:postcode":"01159",
    "sg:province":"Sachsen",
    "wof:name":"K Und R Dresdener Transportbeton",
    "wof:placetype":"venue"
},
  "geometry": {"coordinates":[13.7160196304,51.0457992554],"type":"Point"}
}