{
  "type": "Feature",
  "properties": {
    "iso:country":"DE",
    "sg:address":"Schlammersdorfer Str. 1",
    "sg:city":"Hallerndorf",
    "sg:phone":"+49 9545/306",
    "sg:postcode":"91352",
    "sg:province":"Bayern",
    "wof:name":"Johann Backof",
    "wof:placetype":"venue"
},
  "geometry": {"coordinates":[11.0041351318,49.7674980164],"type":"Point"}
}