{
  "type": "Feature",
  "properties": {
    "iso:country":"DE",
    "sg:address":"Verdener Str. 26",
    "sg:city":"Achim",
    "sg:phone":"+49 4202/2262",
    "sg:postcode":"28832",
    "sg:province":"Niedersachsen",
    "wof:name":"Max Fr\u00f6se",
    "wof:placetype":"venue"
},
  "geometry": {"coordinates":[9.0570392609,53.0026435852],"type":"Point"}
}