{
  "type": "Feature",
  "properties": {
    "iso:country":"DE",
    "sg:address":"Im blauen Garn 85",
    "sg:city":"Wesseling",
    "sg:phone":"+49 2236/840728",
    "sg:postcode":"50389",
    "sg:province":"Nordrhein-Westfalen",
    "wof:name":"Nicki & G.g.anderson",
    "wof:placetype":"venue"
},
  "geometry": {"coordinates":[6.964191,50.821941],"type":"Point"}
}