{
  "type": "Feature",
  "properties": {
    "iso:country":"DE",
    "sg:address":"Fu\u00dfst\u00e4tt",
    "sg:city":"Soyen",
    "sg:phone":"+49 8071/2759",
    "sg:postcode":"83564",
    "sg:province":"Bayern",
    "wof:name":"R. Ziegltrum",
    "wof:placetype":"venue"
},
  "geometry": {"coordinates":[12.169351,48.082588],"type":"Point"}
}