{
  "type": "Feature",
  "properties": {
    "iso:country":"DE",
    "sg:address":"Kehrbuscher Str. 23",
    "sg:city":"Erkelenz",
    "sg:phone":"+49 2431/70832",
    "sg:postcode":"41812",
    "sg:province":"Nordrhein-Westfalen",
    "wof:name":"Ratnasingam Bari",
    "wof:placetype":"venue"
},
  "geometry": {"coordinates":[6.3176951408,51.0886192322],"type":"Point"}
}