{
  "type": "Feature",
  "properties": {
    "iso:country":"DE",
    "sg:address":"Sch\u00f6nbuchener Str. 25",
    "sg:city":"Grafenwiesen",
    "sg:phone":"+49 9946/250",
    "sg:postcode":"93479",
    "sg:province":"Bayern",
    "wof:name":"Kath. \u00d6ffentliche B\u00fccherei",
    "wof:placetype":"venue"
},
  "geometry": {"coordinates":[12.882587,49.201233],"type":"Point"}
}