{
  "type": "Feature",
  "properties": {
    "iso:country":"DE",
    "sg:address":"Bahnhofstr. 37",
    "sg:city":"Nauheim",
    "sg:phone":"+49 6152/6598",
    "sg:postcode":"64569",
    "sg:province":"Hessen",
    "wof:name":"Hessischer Hof",
    "wof:placetype":"venue"
},
  "geometry": {"coordinates":[8.4505929947,49.9423408508],"type":"Point"}
}