{
  "type": "Feature",
  "properties": {
    "iso:country":"DE",
    "sg:address":"K\u00f6nigsdorfer Str. 19",
    "sg:city":"Bad T\u00f6lz",
    "sg:phone":"+49 8041/70246",
    "sg:postcode":"83646",
    "sg:province":"Bayern",
    "wof:name":"M. Sappl Garten- Und",
    "wof:placetype":"venue"
},
  "geometry": {"coordinates":[11.554281,47.760971],"type":"Point"}
}