{
  "type": "Feature",
  "properties": {
    "iso:country":"DE",
    "sg:address":"Seltersweg 55",
    "sg:city":"Gie\u00dfen",
    "sg:phone":"+49 641/74222",
    "sg:postcode":"35390",
    "sg:province":"Hessen",
    "wof:name":"Macarel",
    "wof:placetype":"venue"
},
  "geometry": {"coordinates":[8.672483,50.583401],"type":"Point"}
}