{
  "type": "Feature",
  "properties": {
    "iso:country":"DE",
    "sg:address":"Dieselstr. 5",
    "sg:city":"Helmstedt",
    "sg:phone":"+49 5351/37116",
    "sg:postcode":"38350",
    "sg:province":"Niedersachsen",
    "wof:name":"Bernhard Schulz",
    "wof:placetype":"venue"
},
  "geometry": {"coordinates":[10.987115,52.243576],"type":"Point"}
}