{
  "type": "Feature",
  "properties": {
    "iso:country":"DE",
    "sg:address":"Rheinallee 149",
    "sg:city":"D\u00fcsseldorf",
    "sg:phone":"+49 211/555455",
    "sg:postcode":"40545",
    "sg:province":"Nordrhein-Westfalen",
    "wof:name":"Werner Ruf Und Jan Sacha Architekten",
    "wof:placetype":"venue"
},
  "geometry": {"coordinates":[6.751826,51.227013],"type":"Point"}
}