{
  "type": "Feature",
  "properties": {
    "iso:country":"DE",
    "sg:address":"Schnackenburgall. 42",
    "sg:city":"Hamburg",
    "sg:phone":"+49 40/8506969",
    "sg:postcode":"22525",
    "sg:province":"Hamburg",
    "wof:name":"Kunststofftechnik Hans Rethwisch Gmbh",
    "wof:placetype":"venue"
},
  "geometry": {"coordinates":[9.9185371399,53.5787353516],"type":"Point"}
}