{
  "type": "Feature",
  "properties": {
    "iso:country":"DE",
    "sg:address":"Rilkestr. 9",
    "sg:city":"Ludwigsburg",
    "sg:phone":"+49 7141/53640",
    "sg:postcode":"71642",
    "sg:province":"Baden-W\u00fcrttemberg",
    "wof:name":"Burkhard Boegel Ingenieur",
    "wof:placetype":"venue"
},
  "geometry": {"coordinates":[9.226691246,48.9106559753],"type":"Point"}
}