{
  "type": "Feature",
  "properties": {
    "iso:country":"DE",
    "sg:address":"Katharinenstr. 15",
    "sg:city":"Oldenburg",
    "sg:phone":"+49 441/17600",
    "sg:postcode":"26121",
    "sg:province":"Niedersachsen",
    "wof:name":"Dr. Med. Rainer Adamaszek",
    "wof:placetype":"venue"
},
  "geometry": {"coordinates":[8.2040672302,53.1440391541],"type":"Point"}
}