{
  "type": "Feature",
  "properties": {
    "iso:country":"DE",
    "sg:address":"Jaminstr. 2 B",
    "sg:city":"Kronberg",
    "sg:phone":"+49 6173/79588",
    "sg:postcode":"61476",
    "sg:province":"Hessen",
    "wof:name":"Hans Blume Architekt",
    "wof:placetype":"venue"
},
  "geometry": {"coordinates":[8.507865,50.184361],"type":"Point"}
}