{
  "type": "Feature",
  "properties": {
    "iso:country":"DE",
    "sg:address":"Staufner Str. 18",
    "sg:city":"Lindenberg",
    "sg:phone":"+49 8381/926470",
    "sg:postcode":"88161",
    "sg:province":"Bayern",
    "wof:name":"Auto-keller Gmbh",
    "wof:placetype":"venue"
},
  "geometry": {"coordinates":[9.898189,47.599983],"type":"Point"}
}