{
  "type": "Feature",
  "properties": {
    "iso:country":"DE",
    "sg:address":"Brehmer Str. 2",
    "sg:city":"Heinsberg",
    "sg:phone":"+49 2452/88905",
    "sg:postcode":"52525",
    "sg:province":"Nordrhein-Westfalen",
    "wof:name":"Peter Derichs",
    "wof:placetype":"venue"
},
  "geometry": {"coordinates":[6.1209897995,51.0891609192],"type":"Point"}
}