{
  "type": "Feature",
  "properties": {
    "iso:country":"DE",
    "sg:address":"Brombergstr. 36",
    "sg:city":"Freiburg",
    "sg:phone":"+49 761/72552",
    "sg:postcode":"79102",
    "sg:province":"Baden-W\u00fcrttemberg",
    "wof:name":"Dr. Med. Karl Ramisch",
    "wof:placetype":"venue"
},
  "geometry": {"coordinates":[7.8498711586,47.9853744507],"type":"Point"}
}