{
  "type": "Feature",
  "properties": {
    "iso:country":"DE",
    "sg:address":"Penningsstr. 1",
    "sg:city":"Recklinghausen",
    "sg:phone":"+49 2361/22272",
    "sg:postcode":"45659",
    "sg:province":"Nordrhein-Westfalen",
    "wof:name":"Sozialberatungsstelle Arbeiterwohlfahrt",
    "wof:placetype":"venue"
},
  "geometry": {"coordinates":[7.19841,51.607834],"type":"Point"}
}