{
  "type": "Feature",
  "properties": {
    "iso:country":"DE",
    "sg:address":"Am Helgenhaus 15-19",
    "sg:city":"Butzbach",
    "sg:phone":"+49 6033/4161",
    "sg:postcode":"35510",
    "sg:province":"Hessen",
    "wof:name":"Medacom Gesellschaft F\u00fcr Informationssysteme Mbh",
    "wof:placetype":"venue"
},
  "geometry": {"coordinates":[8.698854,50.436069],"type":"Point"}
}