{
  "type": "Feature",
  "properties": {
    "iso:country":"DE",
    "sg:address":"Leitschsiedlung 17",
    "sg:city":"Steinwiesen",
    "sg:phone":"+49 9262/469",
    "sg:postcode":"96349",
    "sg:province":"Bayern",
    "wof:name":"Cafe Leitsch",
    "wof:placetype":"venue"
},
  "geometry": {"coordinates":[11.449431,50.29158],"type":"Point"}
}