{
  "type": "Feature",
  "properties": {
    "iso:country":"DE",
    "sg:address":"Postfach 29",
    "sg:city":"Unterwellenborn",
    "sg:postcode":"07331",
    "sg:province":"Th\u00fcringen",
    "wof:name":"Rayen Intec",
    "wof:placetype":"venue"
},
  "geometry": {"coordinates":[11.4378795624,50.6587867737],"type":"Point"}
}