{
  "type": "Feature",
  "properties": {
    "iso:country":"DE",
    "sg:address":"An der Kirche 32",
    "sg:city":"Munkbrarup",
    "sg:phone":"+49 4631/2424",
    "sg:postcode":"24960",
    "sg:province":"Schleswig-Holstein",
    "wof:name":"Schr\u00f6der Inh. Martin Henningsen",
    "wof:placetype":"venue"
},
  "geometry": {"coordinates":[9.5621290207,54.8010635376],"type":"Point"}
}