{
  "type": "Feature",
  "properties": {
    "iso:country":"DE",
    "sg:address":"Tr\u00e4nkenweg 17",
    "sg:city":"Neunkirchen",
    "sg:phone":"+49 6821/982840",
    "sg:postcode":"66540",
    "sg:province":"Saarland",
    "wof:name":"Kliebenstein Und Partner Beratende Ingenieure",
    "wof:placetype":"venue"
},
  "geometry": {"coordinates":[7.1650300026,49.3741989136],"type":"Point"}
}