{
  "type": "Feature",
  "properties": {
    "iso:country":"DE",
    "sg:address":"Stra\u00dfe 244 6",
    "sg:city":"Berlin",
    "sg:phone":"+49 30/6540084",
    "sg:postcode":"12557",
    "sg:province":"Berlin",
    "wof:name":"Klaus Sodtke",
    "wof:placetype":"venue"
},
  "geometry": {"coordinates":[13.56469,52.43858],"type":"Point"}
}