{
  "type": "Feature",
  "properties": {
    "iso:country":"DE",
    "sg:address":"Br\u00fccktor 7",
    "sg:city":"Kleve",
    "sg:phone":"+49 2821/768271",
    "sg:postcode":"47533",
    "sg:province":"Nordrhein-Westfalen",
    "wof:name":"Sport Akkermann E. K.",
    "wof:placetype":"venue"
},
  "geometry": {"coordinates":[6.142535,51.788486],"type":"Point"}
}