{
  "type": "Feature",
  "properties": {
    "iso:country":"DE",
    "sg:address":"Jean-Pierre-Jungels-Str. 32 a",
    "sg:city":"Mainz",
    "sg:postcode":"55126",
    "sg:province":"Rheinland-Pfalz",
    "wof:name":"Effect Werbeatelier E. K.",
    "wof:placetype":"venue"
},
  "geometry": {"coordinates":[8.1678256989,49.9813804626],"type":"Point"}
}