{
  "type": "Feature",
  "properties": {
    "iso:country":"DE",
    "sg:address":"Hauptstr. 4",
    "sg:city":"Eppenrod",
    "sg:phone":"+49 6485/911969",
    "sg:postcode":"65558",
    "sg:province":"Rheinland-Pfalz",
    "wof:name":"J\u00fcrgen Sukdolak",
    "wof:placetype":"venue"
},
  "geometry": {"coordinates":[7.930809021,50.403629303],"type":"Point"}
}