{
  "type": "Feature",
  "properties": {
    "iso:country":"DE",
    "sg:address":"Sch\u00f6tmarsche Str. 299",
    "sg:city":"Lage",
    "sg:phone":"+49 5232/68388",
    "sg:postcode":"32791",
    "sg:province":"Nordrhein-Westfalen",
    "wof:name":"Dorothea Bobe Masseurin",
    "wof:placetype":"venue"
},
  "geometry": {"coordinates":[8.772294,52.007381],"type":"Point"}
}