{
  "type": "Feature",
  "properties": {
    "iso:country":"DE",
    "sg:address":"Am Eichw\u00e4ldchen 14",
    "sg:city":"K\u00fcnzell",
    "sg:phone":"+49 661/43141",
    "sg:postcode":"36093",
    "sg:province":"Hessen",
    "wof:name":"Stock Grundst\u00fccks- Verwaltung Gmbh",
    "wof:placetype":"venue"
},
  "geometry": {"coordinates":[9.711148262,50.5183296204],"type":"Point"}
}