{
  "type": "Feature",
  "properties": {
    "iso:country":"DE",
    "sg:address":"Am Steinacker 1-3",
    "sg:city":"Zirndorf",
    "sg:phone":"+49 911/699049",
    "sg:postcode":"90513",
    "sg:province":"Bayern",
    "wof:name":"Mts-steffan Gmbh",
    "wof:placetype":"venue"
},
  "geometry": {"coordinates":[10.947242,49.431507],"type":"Point"}
}