{
  "type": "Feature",
  "properties": {
    "iso:country":"DE",
    "sg:address":"Gr\u00fctterstr. 8",
    "sg:city":"Hameln",
    "sg:phone":"+49 5151/94710",
    "sg:postcode":"31785",
    "sg:province":"Niedersachsen",
    "wof:name":"Nasarek Architektenteam",
    "wof:placetype":"venue"
},
  "geometry": {"coordinates":[9.362974,52.100258],"type":"Point"}
}