{
  "type": "Feature",
  "properties": {
    "iso:country":"DE",
    "sg:address":"Breitenloher Weg 6",
    "sg:city":"Georgensgm\u00fcnd",
    "sg:postcode":"91166",
    "sg:province":"Bayern",
    "wof:name":"Rkv Verwaltung Gmbh",
    "wof:placetype":"venue"
},
  "geometry": {"coordinates":[11.00712,49.172836],"type":"Point"}
}