{
  "type": "Feature",
  "properties": {
    "iso:country":"DE",
    "sg:address":"Am Gunterbach 10",
    "sg:city":"Meckenbeuren",
    "sg:phone":"+49 7542/4966",
    "sg:postcode":"88074",
    "sg:province":"Baden-W\u00fcrttemberg",
    "wof:name":"Margareta Merath",
    "wof:placetype":"venue"
},
  "geometry": {"coordinates":[9.5465478897,47.7080574036],"type":"Point"}
}