{
  "type": "Feature",
  "properties": {
    "iso:country":"DE",
    "sg:address":"Nord-West-Ring-Str. 11",
    "sg:city":"Mainhausen",
    "sg:phone":"+49 6182/9280",
    "sg:postcode":"63533",
    "sg:province":"Hessen",
    "wof:name":"Nord-west Ring Grundst\u00fccks- Gesellschaft Mbh & Co.",
    "wof:placetype":"venue"
},
  "geometry": {"coordinates":[9.0045099258,50.0117301941],"type":"Point"}
}