{
  "type": "Feature",
  "properties": {
    "iso:country":"DE",
    "sg:address":"Isardamm 115",
    "sg:city":"Geretsried",
    "sg:phone":"+49 8171/60930",
    "sg:postcode":"82538",
    "sg:province":"Bayern",
    "wof:name":"Berndt Junius Architekt",
    "wof:placetype":"venue"
},
  "geometry": {"coordinates":[11.471741,47.886856],"type":"Point"}
}