{
  "type": "Feature",
  "properties": {
    "iso:country":"DE",
    "sg:address":"Dohnaer Str 111",
    "sg:city":"Dresden",
    "sg:phone":"+49 351/289150",
    "sg:postcode":"01239",
    "sg:province":"Sachsen",
    "wof:name":"Lichttechnik Busch Ek",
    "wof:placetype":"venue"
},
  "geometry": {"coordinates":[13.7812814713,51.0115699768],"type":"Point"}
}