{
  "type": "Feature",
  "properties": {
    "iso:country":"DE",
    "sg:address":"Borsigstr. 27",
    "sg:city":"Goch",
    "sg:phone":"+49 2823/93130",
    "sg:postcode":"47574",
    "sg:province":"Nordrhein-Westfalen",
    "wof:name":"Eaf Computer Service Supplies Gmbh",
    "wof:placetype":"venue"
},
  "geometry": {"coordinates":[6.1381387711,51.6855697632],"type":"Point"}
}