{
  "type": "Feature",
  "properties": {
    "iso:country":"DE",
    "sg:address":"Ziehrerweg 12",
    "sg:city":"Hamburg",
    "sg:phone":"+49 40/6785198",
    "sg:postcode":"22145",
    "sg:province":"Hamburg",
    "wof:name":"Otto Peem\u00f6ller",
    "wof:placetype":"venue"
},
  "geometry": {"coordinates":[10.1579961777,53.6278572083],"type":"Point"}
}