{
  "type": "Feature",
  "properties": {
    "iso:country":"DE",
    "sg:address":"Habichtstr. 39",
    "sg:city":"Hattingen",
    "sg:phone":"+49 2324/24046",
    "sg:postcode":"45527",
    "sg:province":"Nordrhein-Westfalen",
    "wof:name":"Harald Vogelsang Architekt",
    "wof:placetype":"venue"
},
  "geometry": {"coordinates":[7.193751,51.37289],"type":"Point"}
}