{
  "type": "Feature",
  "properties": {
    "iso:country":"DE",
    "sg:address":"Im Gro\u00dfen Garten 1",
    "sg:city":"Ulmen",
    "sg:phone":"+49 2676/1265",
    "sg:postcode":"56766",
    "sg:province":"Rheinland-Pfalz",
    "wof:name":"Erwin Rauen Elektroinstallation",
    "wof:placetype":"venue"
},
  "geometry": {"coordinates":[6.982683,50.206512],"type":"Point"}
}