{
  "type": "Feature",
  "properties": {
    "iso:country":"DE",
    "sg:address":"Leopoldsh\u00f6her Str. 1",
    "sg:city":"Lage",
    "sg:phone":"+49 5232/6070",
    "sg:postcode":"32791",
    "sg:province":"Nordrhein-Westfalen",
    "wof:name":"Vogels\u00e4nger Studios Grossraumateliers F\u00fcr",
    "wof:placetype":"venue"
},
  "geometry": {"coordinates":[8.7311506271,52.0010490417],"type":"Point"}
}