{
  "type": "Feature",
  "properties": {
    "iso:country":"DE",
    "sg:address":"Karlsruher Str. 61 a",
    "sg:city":"Linkenheim-Hochstetten",
    "sg:phone":"+49 7247/4271",
    "sg:postcode":"76351",
    "sg:province":"Baden-W\u00fcrttemberg",
    "wof:name":"Elf Tankstelle",
    "wof:placetype":"venue"
},
  "geometry": {"coordinates":[8.4088392258,49.1251411438],"type":"Point"}
}