{
  "type": "Feature",
  "properties": {
    "iso:country":"DE",
    "sg:address":"Gl\u00fcckaufstr.",
    "sg:city":"H\u00fcrth",
    "sg:phone":"+49 2233/77097",
    "sg:postcode":"50354",
    "sg:province":"Nordrhein-Westfalen",
    "wof:name":"Qtc H\u00fcrth",
    "wof:placetype":"venue"
},
  "geometry": {"coordinates":[6.8182048798,50.867401123],"type":"Point"}
}