{
  "type": "Feature",
  "properties": {
    "iso:country":"DE",
    "sg:address":"Maibergstr. 3",
    "sg:city":"Hausen",
    "sg:phone":"+49 7622/3073",
    "sg:postcode":"79688",
    "sg:province":"Baden-W\u00fcrttemberg",
    "wof:name":"Ernst Fritz",
    "wof:placetype":"venue"
},
  "geometry": {"coordinates":[7.8393120766,47.6822013855],"type":"Point"}
}