{
  "type": "Feature",
  "properties": {
    "iso:country":"DE",
    "sg:address":"Freiherr-von-Neveu-Str. 9",
    "sg:city":"Offenburg",
    "sg:phone":"+49 781/23410",
    "sg:postcode":"77652",
    "sg:province":"Baden-W\u00fcrttemberg",
    "wof:name":"Fritz G\u00fctle",
    "wof:placetype":"venue"
},
  "geometry": {"coordinates":[7.9535708427,48.515411377],"type":"Point"}
}