{
  "type": "Feature",
  "properties": {
    "iso:country":"DE",
    "sg:address":"Am H\u00fc\u00dfelhus 7",
    "sg:city":"Hamburg",
    "sg:phone":"+49 40/7602555",
    "sg:postcode":"21077",
    "sg:province":"Hamburg",
    "wof:name":"Karl Heinz Stadtler",
    "wof:placetype":"venue"
},
  "geometry": {"coordinates":[9.9659833908,53.4342803955],"type":"Point"}
}