{
  "type": "Feature",
  "properties": {
    "iso:country":"DE",
    "sg:address":"Sch\u00fcrsdorfer Weg 2",
    "sg:city":"Scharbeutz",
    "sg:phone":"+49 4524/8889",
    "sg:postcode":"23684",
    "sg:province":"Schleswig-Holstein",
    "wof:name":"Gartenbau-wesenberg-neuanlagen",
    "wof:placetype":"venue"
},
  "geometry": {"coordinates":[10.70067,54.018288],"type":"Point"}
}