{
  "type": "Feature",
  "properties": {
    "iso:country":"DE",
    "sg:address":"E.ON-Platz 1",
    "sg:city":"D\u00fcsseldorf",
    "sg:phone":"+49 721/9431060",
    "sg:postcode":"40479",
    "sg:province":"Nordrhein-Westfalen",
    "wof:name":"Ec4u It Solutions Ag",
    "wof:placetype":"venue"
},
  "geometry": {"coordinates":[8.4491786957,49.0254554749],"type":"Point"}
}