{
  "type": "Feature",
  "properties": {
    "iso:country":"DE",
    "sg:address":"Bachstr. 9",
    "sg:city":"Geseke",
    "sg:phone":"+49 2942/4600",
    "sg:postcode":"59590",
    "sg:province":"Nordrhein-Westfalen",
    "wof:name":"M\u00fcller & Mertens Ohg",
    "wof:placetype":"venue"
},
  "geometry": {"coordinates":[8.510424614,51.6405334473],"type":"Point"}
}