{
  "type": "Feature",
  "properties": {
    "iso:country":"DE",
    "sg:address":"Schulstr. 53",
    "sg:city":"Bellheim",
    "sg:phone":"+49 7272/8160",
    "sg:postcode":"76756",
    "sg:province":"Rheinland-Pfalz",
    "wof:name":"Dr. Med. Klaus Sarnecki",
    "wof:placetype":"venue"
},
  "geometry": {"coordinates":[8.2921676636,49.1943321228],"type":"Point"}
}