{
  "type": "Feature",
  "properties": {
    "iso:country":"DE",
    "sg:address":"Riederner Str. 1",
    "sg:city":"Eichenb\u00fchl",
    "sg:phone":"+49 9378/97100",
    "sg:postcode":"63928",
    "sg:province":"Bayern",
    "wof:name":"Gebr. Konrad Verwaltungs Gmbh",
    "wof:placetype":"venue"
},
  "geometry": {"coordinates":[9.375933,49.671356],"type":"Point"}
}