{
  "type": "Feature",
  "properties": {
    "iso:country":"DE",
    "sg:address":"Paul-Robeson-Str. 6",
    "sg:city":"Berlin",
    "sg:phone":"+49 30/44690190",
    "sg:postcode":"10439",
    "sg:province":"Berlin",
    "wof:name":"Lothar Arzt & Co. Higa Projekt Gmbh Berlin",
    "wof:placetype":"venue"
},
  "geometry": {"coordinates":[13.411897,52.552433],"type":"Point"}
}