{
  "type": "Feature",
  "properties": {
    "iso:country":"DE",
    "sg:address":"Am Spitalacker 8",
    "sg:city":"Gelnhausen",
    "sg:phone":"+49 4960/5114028",
    "sg:postcode":"63571",
    "sg:province":"Hessen",
    "wof:name":"Micro- Maschinenbau Gmbh",
    "wof:placetype":"venue"
},
  "geometry": {"coordinates":[9.165851,50.205486],"type":"Point"}
}