{
  "type": "Feature",
  "properties": {
    "iso:country":"DE",
    "sg:address":"Wenigerbachstr 9",
    "sg:city":"Neunkirchen-Seelscheid",
    "sg:phone":"+49 2247/971560",
    "sg:postcode":"53819",
    "sg:province":"Nordrhein-Westfalen",
    "wof:name":"Mowa Gmbh",
    "wof:placetype":"venue"
},
  "geometry": {"coordinates":[7.3241,50.87796],"type":"Point"}
}