{
  "type": "Feature",
  "properties": {
    "iso:country":"DE",
    "sg:address":"Alte Dorfstr. 34",
    "sg:city":"Stade",
    "sg:phone":"+49 4141/81144",
    "sg:postcode":"21684",
    "sg:province":"Niedersachsen",
    "wof:name":"Eberhard Griem",
    "wof:placetype":"venue"
},
  "geometry": {"coordinates":[9.421202,53.585136],"type":"Point"}
}