{
  "type": "Feature",
  "properties": {
    "iso:country":"DE",
    "sg:address":"Karl-Marx-Str. 7",
    "sg:city":"Breuberg",
    "sg:phone":"+49 6165/912014",
    "sg:postcode":"64747",
    "sg:province":"Hessen",
    "wof:name":"Schaffer Hard- Und Software Gmbh",
    "wof:placetype":"venue"
},
  "geometry": {"coordinates":[9.0165052414,49.8183708191],"type":"Point"}
}