{
  "type": "Feature",
  "properties": {
    "iso:country":"DE",
    "sg:address":"Morgensternstr. 27",
    "sg:city":"Berlin",
    "sg:phone":"+49 30/7721401",
    "sg:postcode":"12207",
    "sg:province":"Berlin",
    "wof:name":"Annegret Lehmann",
    "wof:placetype":"venue"
},
  "geometry": {"coordinates":[13.3237218857,52.4274177551],"type":"Point"}
}