{
  "type": "Feature",
  "properties": {
    "iso:country":"DE",
    "sg:address":"Marktstr. 6",
    "sg:city":"Dillingen",
    "sg:phone":"+49 6831/71405",
    "sg:postcode":"66763",
    "sg:province":"Saarland",
    "wof:name":"Heidi Edinger",
    "wof:placetype":"venue"
},
  "geometry": {"coordinates":[6.7281031609,49.3523445129],"type":"Point"}
}