{
  "type": "Feature",
  "properties": {
    "iso:country":"DE",
    "sg:address":"Pohlandstr. 21",
    "sg:city":"Dresden",
    "sg:phone":"+49 351/337042",
    "sg:postcode":"01309",
    "sg:province":"Sachsen",
    "wof:name":"Erhard Kirsch Rechtsanwalt",
    "wof:placetype":"venue"
},
  "geometry": {"coordinates":[13.7983617783,51.0478057861],"type":"Point"}
}