{
  "type": "Feature",
  "properties": {
    "iso:country":"DE",
    "sg:address":"Siedlungsstr. 4",
    "sg:city":"Hamm",
    "sg:phone":"+49 2385/6625",
    "sg:postcode":"59069",
    "sg:province":"Nordrhein-Westfalen",
    "wof:name":"H. Sch\u00e4fer",
    "wof:placetype":"venue"
},
  "geometry": {"coordinates":[7.8556089401,51.6538658142],"type":"Point"}
}