{
  "type": "Feature",
  "properties": {
    "iso:country":"DE",
    "sg:address":"Ahlener Str 25",
    "sg:city":"Bielefeld",
    "sg:phone":"+49 521/412423",
    "sg:postcode":"33647",
    "sg:province":"Nordrhein-Westfalen",
    "wof:name":"Abonetx",
    "wof:placetype":"venue"
},
  "geometry": {"coordinates":[8.510322,51.981068],"type":"Point"}
}