{
  "type": "Feature",
  "properties": {
    "iso:country":"DE",
    "sg:address":"Veerter Str. 13",
    "sg:city":"Kevelaer",
    "sg:phone":"+49 2831/3570",
    "sg:postcode":"47625",
    "sg:province":"Nordrhein-Westfalen",
    "wof:name":"H. Gerritzen",
    "wof:placetype":"venue"
},
  "geometry": {"coordinates":[6.294866,51.542717],"type":"Point"}
}