{
  "type": "Feature",
  "properties": {
    "iso:country":"DE",
    "sg:address":"Dambachstr 7",
    "sg:city":"Herzogenaurach",
    "sg:phone":"+49 9132/7700",
    "sg:postcode":"91074",
    "sg:province":"Bayern",
    "wof:name":"Spedition Drebinger",
    "wof:placetype":"venue"
},
  "geometry": {"coordinates":[10.8741397858,49.5730400085],"type":"Point"}
}