{
  "type": "Feature",
  "properties": {
    "iso:country":"DE",
    "sg:address":"Otto-Hue-Str. 6",
    "sg:city":"Wilkau-Ha\u00dflau",
    "sg:phone":"+49 375/671650",
    "sg:postcode":"08112",
    "sg:province":"Sachsen",
    "wof:name":"Frank Wolfram",
    "wof:placetype":"venue"
},
  "geometry": {"coordinates":[12.52064991,50.6728286743],"type":"Point"}
}