{
  "type": "Feature",
  "properties": {
    "iso:country":"DE",
    "sg:address":"Widukindstr. 3",
    "sg:city":"Oldenburg",
    "sg:phone":"+49 441/8859999",
    "sg:postcode":"26121",
    "sg:province":"Niedersachsen",
    "wof:name":"Braun Und Meyer Architekten",
    "wof:placetype":"venue"
},
  "geometry": {"coordinates":[8.210112,53.157318],"type":"Point"}
}