{
  "type": "Feature",
  "properties": {
    "iso:country":"DE",
    "sg:address":"Maschstr. 27",
    "sg:city":"Stemwede",
    "sg:phone":"+49 5745/2168",
    "sg:postcode":"32351",
    "sg:province":"Nordrhein-Westfalen",
    "wof:name":"Scheer & Sohn G\u00fcter Nah Und Fernverkehr",
    "wof:placetype":"venue"
},
  "geometry": {"coordinates":[8.4751167297,52.3856773376],"type":"Point"}
}