{
  "type": "Feature",
  "properties": {
    "iso:country":"DE",
    "sg:address":"Herterichstr. 8",
    "sg:city":"M\u00fcnchen",
    "sg:phone":"+49 89/796668",
    "sg:postcode":"81479",
    "sg:province":"Bayern",
    "wof:name":"Corso Stubn",
    "wof:placetype":"venue"
},
  "geometry": {"coordinates":[11.5260858536,48.0764007568],"type":"Point"}
}