{
  "type": "Feature",
  "properties": {
    "iso:country":"DE",
    "sg:address":"Petershof",
    "sg:city":"Westfehmarn",
    "sg:phone":"+49 4372/256",
    "sg:postcode":"23769",
    "sg:province":"Schleswig-Holstein",
    "wof:name":"Bauernst\u00fcbchen",
    "wof:placetype":"venue"
},
  "geometry": {"coordinates":[11.0995397568,54.439781189],"type":"Point"}
}