{
  "type": "Feature",
  "properties": {
    "iso:country":"DE",
    "sg:address":"Hannoversche Str. 57",
    "sg:city":"Syke",
    "sg:phone":"+49 4240/952853",
    "sg:postcode":"28857",
    "sg:province":"Niedersachsen",
    "wof:name":"F. Vo\u00df",
    "wof:placetype":"venue"
},
  "geometry": {"coordinates":[8.8675765991,52.8738899231],"type":"Point"}
}