{
  "type": "Feature",
  "properties": {
    "iso:country":"DE",
    "sg:address":"Wallstr. 16",
    "sg:city":"Kleinwallstadt",
    "sg:phone":"+49 4960/222090",
    "sg:postcode":"63839",
    "sg:province":"Bayern",
    "wof:name":"Raiffeisenbank Kleinwallstadt-sulz-, Bach Eg",
    "wof:placetype":"venue"
},
  "geometry": {"coordinates":[9.166669,49.872738],"type":"Point"}
}