{
  "type": "Feature",
  "properties": {
    "iso:country":"DE",
    "sg:address":"Karl-Marx-Str. 1",
    "sg:city":"Fehrbellin",
    "sg:phone":"+49 33932/70505",
    "sg:postcode":"16833",
    "sg:province":"Brandenburg",
    "wof:name":"Gerhard Paech",
    "wof:placetype":"venue"
},
  "geometry": {"coordinates":[12.781643,52.806812],"type":"Point"}
}