{
  "type": "Feature",
  "properties": {
    "iso:country":"DE",
    "sg:address":"Martin-Luther-Str. 5 a",
    "sg:city":"W\u00fcrzburg",
    "sg:phone":"+49 931/354580",
    "sg:postcode":"97072",
    "sg:province":"Bayern",
    "wof:name":"Byte Com Ges. F\u00fcr Neue Medien Und Netzwerkkommunikation Mbh",
    "wof:placetype":"venue"
},
  "geometry": {"coordinates":[9.9443359375,49.7935180664],"type":"Point"}
}