{
  "type": "Feature",
  "properties": {
    "iso:country":"DE",
    "sg:address":"Schopflocher Str. 32",
    "sg:city":"Glatten",
    "sg:phone":"+49 7443/6257",
    "sg:postcode":"72293",
    "sg:province":"Baden-W\u00fcrttemberg",
    "wof:name":"Hansj\u00f6rg Ruthardt",
    "wof:placetype":"venue"
},
  "geometry": {"coordinates":[8.517965,48.447224],"type":"Point"}
}