{
  "type": "Feature",
  "properties": {
    "iso:country":"DE",
    "sg:address":"Fischerstr. 27",
    "sg:city":"Prenzlau",
    "sg:phone":"+49 3984/801888",
    "sg:postcode":"17291",
    "sg:province":"Brandenburg",
    "wof:name":"Pension",
    "wof:placetype":"venue"
},
  "geometry": {"coordinates":[13.8546514511,53.3112411499],"type":"Point"}
}