{
  "type": "Feature",
  "properties": {
    "iso:country":"DE",
    "sg:address":"Oststr. 37",
    "sg:city":"D\u00fcsseldorf",
    "sg:phone":"+49 211",
    "sg:postcode":"40211",
    "sg:province":"Nordrhein-Westfalen",
    "wof:name":"Italienische Schuhe",
    "wof:placetype":"venue"
},
  "geometry": {"coordinates":[6.788463,51.225754],"type":"Point"}
}