{
  "type": "Feature",
  "properties": {
    "iso:country":"DE",
    "sg:address":"J\u00fcrgen-Ponto-Platz 2",
    "sg:city":"Frankfurt",
    "sg:phone":"+49 69/250076",
    "sg:postcode":"60329",
    "sg:province":"Hessen",
    "wof:name":"Drogerie Lehr Inh. Thomas Lehr",
    "wof:placetype":"venue"
},
  "geometry": {"coordinates":[8.669446,50.108994],"type":"Point"}
}