{
  "type": "Feature",
  "properties": {
    "iso:country":"DE",
    "sg:address":"Lange Str. 52",
    "sg:city":"Karlsbad",
    "sg:phone":"+49 7248/6066",
    "sg:postcode":"76307",
    "sg:province":"Baden-W\u00fcrttemberg",
    "wof:name":"Willi Mohr",
    "wof:placetype":"venue"
},
  "geometry": {"coordinates":[8.5060863495,48.9143943787],"type":"Point"}
}