{
  "type": "Feature",
  "properties": {
    "iso:country":"DE",
    "sg:address":"Ballerstedter Str. 2",
    "sg:city":"Osterburg",
    "sg:postcode":"39606",
    "sg:province":"Sachsen-Anhalt",
    "wof:name":"Architekturb\u00fcro Zimmermann & Partner Gmbh",
    "wof:placetype":"venue"
},
  "geometry": {"coordinates":[11.7510900497,52.7877616882],"type":"Point"}
}