{
  "type": "Feature",
  "properties": {
    "iso:country":"DE",
    "sg:address":"Oldenburger Str. 80",
    "sg:city":"Bar\u00dfel",
    "sg:phone":"+49 4499/2885",
    "sg:postcode":"26676",
    "sg:province":"Niedersachsen",
    "wof:name":"J. Sch\u00f6nh\u00f6ft",
    "wof:placetype":"venue"
},
  "geometry": {"coordinates":[7.746924,53.122417],"type":"Point"}
}