{
  "type": "Feature",
  "properties": {
    "iso:country":"DE",
    "sg:address":"Balthasar-Neumann-Str. 21",
    "sg:city":"Werneck",
    "sg:phone":"+49 9722/8953",
    "sg:postcode":"97440",
    "sg:province":"Bayern",
    "wof:name":"W. K. Carl",
    "wof:placetype":"venue"
},
  "geometry": {"coordinates":[10.1041822433,49.982257843],"type":"Point"}
}