{
  "type": "Feature",
  "properties": {
    "iso:country":"DE",
    "sg:address":"Schartauer Str. 60a",
    "sg:city":"Burg",
    "sg:phone":"+49 3921/987988",
    "sg:postcode":"39288",
    "sg:province":"Sachsen-Anhalt",
    "wof:name":"Wagner",
    "wof:placetype":"venue"
},
  "geometry": {"coordinates":[11.8551149368,52.2705764771],"type":"Point"}
}