{
  "type": "Feature",
  "properties": {
    "iso:country":"DE",
    "sg:address":"St. Marienstr. 11",
    "sg:city":"R\u00f6ttenbach",
    "sg:phone":"+49 9172/695",
    "sg:postcode":"91187",
    "sg:province":"Bayern",
    "wof:name":"Katholisches Pfarramt Maria K\u00f6nigin",
    "wof:placetype":"venue"
},
  "geometry": {"coordinates":[11.0250291824,49.1525802612],"type":"Point"}
}