{
  "type": "Feature",
  "properties": {
    "iso:country":"DE",
    "sg:address":"B\u00fchlg\u00e4rten 14",
    "sg:city":"Rudersberg",
    "sg:phone":"+49 7183/939360",
    "sg:postcode":"73635",
    "sg:province":"Baden-W\u00fcrttemberg",
    "wof:name":"Ulrich Sigel Gmbh",
    "wof:placetype":"venue"
},
  "geometry": {"coordinates":[9.5444421768,48.8939094543],"type":"Point"}
}