{
  "type": "Feature",
  "properties": {
    "iso:country":"DE",
    "sg:address":"Chattenweg 10",
    "sg:city":"Bad Vilbel",
    "sg:phone":"+49 6101/6806",
    "sg:postcode":"61118",
    "sg:province":"Hessen",
    "wof:name":"W. Ament",
    "wof:placetype":"venue"
},
  "geometry": {"coordinates":[8.744318,50.186691],"type":"Point"}
}