{
  "type": "Feature",
  "properties": {
    "iso:country":"DE",
    "sg:address":"Am Markt 9",
    "sg:city":"Hillesheim",
    "sg:phone":"+49 6593/1212",
    "sg:postcode":"54576",
    "sg:province":"Rheinland-Pfalz",
    "wof:name":"Wolfgang Bauer Ingenieur",
    "wof:placetype":"venue"
},
  "geometry": {"coordinates":[6.6712532043,50.2917251587],"type":"Point"}
}