{
  "type": "Feature",
  "properties": {
    "iso:country":"DE",
    "sg:address":"Tannenweg 9",
    "sg:city":"K\u00f6nigsfeld",
    "sg:phone":"+49 7725/3925",
    "sg:postcode":"78126",
    "sg:province":"Baden-W\u00fcrttemberg",
    "wof:name":"Eigenzeit-verlag",
    "wof:placetype":"venue"
},
  "geometry": {"coordinates":[8.438923,48.152508],"type":"Point"}
}