{
  "type": "Feature",
  "properties": {
    "iso:country":"DE",
    "sg:address":"Hauptstr. 111",
    "sg:city":"\u00d6lbronn-D\u00fcrrn",
    "sg:phone":"+49 7237/5082",
    "sg:postcode":"75248",
    "sg:province":"Baden-W\u00fcrttemberg",
    "wof:name":"M. Weber",
    "wof:placetype":"venue"
},
  "geometry": {"coordinates":[8.760955,48.956627],"type":"Point"}
}