{
  "type": "Feature",
  "properties": {
    "iso:country":"DE",
    "sg:address":"Volkmarsh\u00e4user Str. 17",
    "sg:city":"Hann. M\u00fcnden",
    "sg:phone":"+49 5541/98500",
    "sg:postcode":"34346",
    "sg:province":"Niedersachsen",
    "wof:name":"Isophon Glas & Co. Betriebs Kg",
    "wof:placetype":"venue"
},
  "geometry": {"coordinates":[9.6444740295,51.4394683838],"type":"Point"}
}