{
  "type": "Feature",
  "properties": {
    "iso:country":"DE",
    "sg:address":"Seerichterstr. 4a",
    "sg:city":"Die\u00dfen",
    "sg:phone":"+49 8807/6189",
    "sg:postcode":"86911",
    "sg:province":"Bayern",
    "wof:name":"Vs-org Verkehrssysteme Gmbh",
    "wof:placetype":"venue"
},
  "geometry": {"coordinates":[11.1069402695,47.9449501038],"type":"Point"}
}