{
  "type": "Feature",
  "properties": {
    "iso:country":"DE",
    "sg:address":"Marienstr. 19",
    "sg:city":"Konz",
    "sg:phone":"+49 6501/17120",
    "sg:postcode":"54329",
    "sg:province":"Rheinland-Pfalz",
    "wof:name":"F. Und L. Burg Weinanbau",
    "wof:placetype":"venue"
},
  "geometry": {"coordinates":[6.5595440865,49.6650924683],"type":"Point"}
}