{
  "type": "Feature",
  "properties": {
    "iso:country":"DE",
    "sg:address":"Scheuergasse 5",
    "sg:city":"Bad Saulgau",
    "sg:phone":"+49 7581/8320",
    "sg:postcode":"88348",
    "sg:province":"Baden-W\u00fcrttemberg",
    "wof:name":"Karla Vollmer Masseurin",
    "wof:placetype":"venue"
},
  "geometry": {"coordinates":[9.501216,48.015335],"type":"Point"}
}