{
  "type": "Feature",
  "properties": {
    "iso:country":"DE",
    "sg:address":"Max-Planck-Str. 31",
    "sg:city":"Eningen u.A./Reutlingen-S\u00fcd",
    "sg:phone":"+49 7121/880080",
    "sg:postcode":"72800",
    "sg:province":"Baden-W\u00fcrttemberg",
    "wof:name":"K\u00fchlerbau Bleher Gmbh",
    "wof:placetype":"venue"
},
  "geometry": {"coordinates":[9.2433547974,48.4777030945],"type":"Point"}
}