{
  "type": "Feature",
  "properties": {
    "iso:country":"DE",
    "sg:address":"Br\u00fcckenstr. 3",
    "sg:city":"Idesheim",
    "sg:phone":"+49 6506/8499",
    "sg:postcode":"54636",
    "sg:province":"Rheinland-Pfalz",
    "wof:name":"Josef Burbach",
    "wof:placetype":"venue"
},
  "geometry": {"coordinates":[6.573907,49.874393],"type":"Point"}
}