{
  "type": "Feature",
  "properties": {
    "iso:country":"DE",
    "sg:address":"Oberstr. 62",
    "sg:city":"Spiesheim",
    "sg:phone":"+49 6732/7516",
    "sg:postcode":"55288",
    "sg:province":"Rheinland-Pfalz",
    "wof:name":"Adalbert Jung",
    "wof:placetype":"venue"
},
  "geometry": {"coordinates":[8.1267938614,49.8120574951],"type":"Point"}
}