{
  "type": "Feature",
  "properties": {
    "iso:country":"DE",
    "sg:address":"Heisenstr. 10",
    "sg:city":"Hannover",
    "sg:phone":"+49 511/701884",
    "sg:postcode":"30167",
    "sg:province":"Niedersachsen",
    "wof:name":"August Schreiber",
    "wof:placetype":"venue"
},
  "geometry": {"coordinates":[9.721063,52.389278],"type":"Point"}
}