{
  "type": "Feature",
  "properties": {
    "iso:country":"DE",
    "sg:address":"Dorn 2",
    "sg:city":"Bergisch Gladbach",
    "sg:phone":"+49 2207/911251",
    "sg:postcode":"51429",
    "sg:province":"Nordrhein-Westfalen",
    "wof:name":"Fliesendesign U. Meister - Verlegebetrieb Porz Gmbh",
    "wof:placetype":"venue"
},
  "geometry": {"coordinates":[7.2353820801,50.9709777832],"type":"Point"}
}