{
  "type": "Feature",
  "properties": {
    "iso:country":"DE",
    "sg:address":"Vor dem Bardowicker Tore 35",
    "sg:city":"L\u00fcneburg",
    "sg:postcode":"21339",
    "sg:province":"Niedersachsen",
    "wof:name":"Aldi Gmbh & Co. Kg",
    "wof:placetype":"venue"
},
  "geometry": {"coordinates":[10.4097137451,53.2567901611],"type":"Point"}
}