{
  "type": "Feature",
  "properties": {
    "iso:country":"DE",
    "sg:address":"Kietzer Str. 4",
    "sg:city":"Berlin",
    "sg:phone":"+49 30/6557019",
    "sg:postcode":"12555",
    "sg:province":"Berlin",
    "wof:name":"Kietzer-apotheke Inhaber: Apotheker",
    "wof:placetype":"venue"
},
  "geometry": {"coordinates":[13.577708,52.444767],"type":"Point"}
}