{
  "type": "Feature",
  "properties": {
    "iso:country":"DE",
    "sg:address":"Nr. 16",
    "sg:city":"Breddorfermoor",
    "sg:phone":"+49 4794/203",
    "sg:postcode":"27726",
    "sg:province":"Niedersachsen",
    "wof:name":"Nikolaus Tietjen",
    "wof:placetype":"venue"
},
  "geometry": {"coordinates":[8.925529,53.222748],"type":"Point"}
}