{
  "type": "Feature",
  "properties": {
    "iso:country":"DE",
    "sg:address":"Bismarckstr. 42",
    "sg:city":"Reichelsheim",
    "sg:phone":"+49 6164/5687",
    "sg:postcode":"64385",
    "sg:province":"Hessen",
    "wof:name":"Rohde Und Partner Rechtsanw\u00e4lte",
    "wof:placetype":"venue"
},
  "geometry": {"coordinates":[8.8389930725,49.7148780823],"type":"Point"}
}