{
  "type": "Feature",
  "properties": {
    "iso:country":"DE",
    "sg:address":"Sailergasse 3",
    "sg:city":"Bad Wurzach",
    "sg:phone":"+49 7564/2420",
    "sg:postcode":"88410",
    "sg:province":"Baden-W\u00fcrttemberg",
    "wof:name":"H. Erne",
    "wof:placetype":"venue"
},
  "geometry": {"coordinates":[9.8705997467,47.9498405457],"type":"Point"}
}