{
  "type": "Feature",
  "properties": {
    "iso:country":"DE",
    "sg:address":"Schullendamm 51",
    "sg:city":"Meppen",
    "sg:phone":"+49 5931/12459",
    "sg:postcode":"49716",
    "sg:province":"Niedersachsen",
    "wof:name":"M. Todt",
    "wof:placetype":"venue"
},
  "geometry": {"coordinates":[7.2755880356,52.6916542053],"type":"Point"}
}