{
  "type": "Feature",
  "properties": {
    "iso:country":"DE",
    "sg:address":"Melchior-Otto-Platz 3",
    "sg:city":"Kronach",
    "sg:phone":"+49 9261/2794",
    "sg:postcode":"96317",
    "sg:province":"Bayern",
    "wof:name":"Baptist Kramp U. Sohn Inh. Ilse Kramp",
    "wof:placetype":"venue"
},
  "geometry": {"coordinates":[11.3244066238,50.2403907776],"type":"Point"}
}