{
  "type": "Feature",
  "properties": {
    "iso:country":"DE",
    "sg:address":"K\u00f6nigsberger Str. 100",
    "sg:city":"D\u00fcsseldorf",
    "sg:postcode":"40231",
    "sg:province":"Nordrhein-Westfalen",
    "wof:name":"Freeway Traffic Systems Verwaltungs Gmbh",
    "wof:placetype":"venue"
},
  "geometry": {"coordinates":[6.8302931786,51.215927124],"type":"Point"}
}