{
  "type": "Feature",
  "properties": {
    "iso:country":"DE",
    "sg:address":"Berliner Str. 117",
    "sg:city":"Berlin",
    "sg:postcode":"10713",
    "sg:province":"Berlin",
    "wof:name":"Verm\u00f6gensverwaltungsges. H S M S Mbh",
    "wof:placetype":"venue"
},
  "geometry": {"coordinates":[13.3172082901,52.4863739014],"type":"Point"}
}