{
  "type": "Feature",
  "properties": {
    "iso:country":"DE",
    "sg:address":"Hebelstr. 7",
    "sg:city":"Ludwigshafen",
    "sg:phone":"+49 621/575160",
    "sg:postcode":"67065",
    "sg:province":"Rheinland-Pfalz",
    "wof:name":"Herbert Humm Rechtsanwalt",
    "wof:placetype":"venue"
},
  "geometry": {"coordinates":[8.4325017929,49.4684371948],"type":"Point"}
}