{
  "type": "Feature",
  "properties": {
    "iso:country":"DE",
    "sg:address":"Viceburgstr. 2",
    "sg:city":"Hof",
    "sg:phone":"+49 9281/8380",
    "sg:postcode":"95032",
    "sg:province":"Bayern",
    "wof:name":"Deutsche Telekom Ag",
    "wof:placetype":"venue"
},
  "geometry": {"coordinates":[11.9176359177,50.3062057495],"type":"Point"}
}