{
  "type": "Feature",
  "properties": {
    "iso:country":"DE",
    "sg:address":"Unterwendelsheim 54",
    "sg:city":"Wendelsheim",
    "sg:phone":"+49 6734/313",
    "sg:postcode":"55234",
    "sg:province":"Rheinland-Pfalz",
    "wof:name":"Norbert Ei\u00dffeller",
    "wof:placetype":"venue"
},
  "geometry": {"coordinates":[7.9926671982,49.76537323],"type":"Point"}
}