{
  "type": "Feature",
  "properties": {
    "iso:country":"DE",
    "sg:address":"Luitpoldstr. 22",
    "sg:city":"Krailling",
    "sg:phone":"+49 89/8597779",
    "sg:postcode":"82152",
    "sg:province":"Bayern",
    "wof:name":"Unitas Chemie Gmbh",
    "wof:placetype":"venue"
},
  "geometry": {"coordinates":[11.4145622253,48.1004180908],"type":"Point"}
}