{
  "type": "Feature",
  "properties": {
    "iso:country":"DE",
    "sg:address":"Sch\u00fctzenstr. 37",
    "sg:city":"Braunschweig",
    "sg:phone":"+49 531/17117",
    "sg:postcode":"38100",
    "sg:province":"Niedersachsen",
    "wof:name":"Harlekin-kindermoden",
    "wof:placetype":"venue"
},
  "geometry": {"coordinates":[10.5194673538,52.2629623413],"type":"Point"}
}