{
  "type": "Feature",
  "properties": {
    "iso:country":"DE",
    "sg:address":"K\u00f6penicker Str. 166",
    "sg:city":"Berlin",
    "sg:phone":"+49 30/6644409",
    "sg:postcode":"12355",
    "sg:province":"Berlin",
    "wof:name":"Cafe Am Markt",
    "wof:placetype":"venue"
},
  "geometry": {"coordinates":[13.498879,52.419411],"type":"Point"}
}