{
  "type": "Feature",
  "properties": {
    "iso:country":"DE",
    "sg:address":"Ortnitstr. 35",
    "sg:city":"M\u00fcnchen",
    "sg:phone":"+49 89/98108222",
    "sg:postcode":"81925",
    "sg:province":"Bayern",
    "wof:name":"Claus Michael Karpf Gmbh",
    "wof:placetype":"venue"
},
  "geometry": {"coordinates":[11.617509,48.157711],"type":"Point"}
}