{
  "type": "Feature",
  "properties": {
    "iso:country":"DE",
    "sg:address":"Samoastr. 21-23",
    "sg:city":"M\u00fcnchen",
    "sg:phone":"+49 89/4305578",
    "sg:postcode":"81827",
    "sg:province":"Bayern",
    "wof:name":"Porta Verlag Kg Schemm & Co.",
    "wof:placetype":"venue"
},
  "geometry": {"coordinates":[11.703097,48.110275],"type":"Point"}
}