{
  "type": "Feature",
  "properties": {
    "iso:country":"DE",
    "sg:address":"Steinstr. 12",
    "sg:city":"Holzhausen",
    "sg:phone":"+49 6772/5980",
    "sg:postcode":"56357",
    "sg:province":"Rheinland-Pfalz",
    "wof:name":"Martin Falk",
    "wof:placetype":"venue"
},
  "geometry": {"coordinates":[8.527589798,50.8137435913],"type":"Point"}
}