{
  "type": "Feature",
  "properties": {
    "iso:country":"DE",
    "sg:address":"Herwigstr. 32",
    "sg:city":"Bremerhaven",
    "sg:postcode":"27572",
    "sg:province":"Bremen",
    "wof:name":"R & M Sir Bremerhaven Gmbh",
    "wof:placetype":"venue"
},
  "geometry": {"coordinates":[8.58024,53.525589],"type":"Point"}
}