{
  "type": "Feature",
  "properties": {
    "iso:country":"DE",
    "sg:address":"Gro\u00df-Umst\u00e4dter-Str. 13",
    "sg:city":"H\u00f6chst",
    "sg:phone":"+49 6163/93010",
    "sg:postcode":"64739",
    "sg:province":"Hessen",
    "wof:name":"Orth Und Brunner Rechtsanw\u00e4lte",
    "wof:placetype":"venue"
},
  "geometry": {"coordinates":[8.9917888641,49.8002471924],"type":"Point"}
}