{
  "type": "Feature",
  "properties": {
    "iso:country":"DE",
    "sg:address":"Seelower Str. 13",
    "sg:city":"Golzow",
    "sg:postcode":"15328",
    "sg:province":"Brandenburg",
    "wof:name":"Marion Runge",
    "wof:placetype":"venue"
},
  "geometry": {"coordinates":[14.493142,52.571957],"type":"Point"}
}