{
  "type": "Feature",
  "properties": {
    "iso:country":"DE",
    "sg:address":"Hahnheimer Str. 17",
    "sg:city":"Udenheim",
    "sg:phone":"+49 6732/918385",
    "sg:postcode":"55288",
    "sg:province":"Rheinland-Pfalz",
    "wof:name":"Profi-tex Gmbh",
    "wof:placetype":"venue"
},
  "geometry": {"coordinates":[8.1738967896,49.8638191223],"type":"Point"}
}