{
  "type": "Feature",
  "properties": {
    "iso:country":"DE",
    "sg:address":"Schleestr. 2",
    "sg:city":"Hamburg",
    "sg:phone":"+49 40/384792",
    "sg:postcode":"22767",
    "sg:province":"Hamburg",
    "wof:name":"Hirsch-apotheke",
    "wof:placetype":"venue"
},
  "geometry": {"coordinates":[9.945595,53.546455],"type":"Point"}
}