{
  "type": "Feature",
  "properties": {
    "iso:country":"DE",
    "sg:address":"Schlo\u00dfberg 12",
    "sg:city":"Obertrubach",
    "sg:phone":"+49 9245/309",
    "sg:postcode":"91286",
    "sg:province":"Bayern",
    "wof:name":"Moritz Gmelch",
    "wof:placetype":"venue"
},
  "geometry": {"coordinates":[11.349292,49.695915],"type":"Point"}
}