{
  "type": "Feature",
  "properties": {
    "iso:country":"DE",
    "sg:address":"Bismarckstr. 88",
    "sg:city":"D\u00fcsseldorf",
    "sg:phone":"+49 211/358936",
    "sg:postcode":"40210",
    "sg:province":"Nordrhein-Westfalen",
    "wof:name":"N. Avdiu",
    "wof:placetype":"venue"
},
  "geometry": {"coordinates":[6.7889862061,51.2211837769],"type":"Point"}
}