{
  "type": "Feature",
  "properties": {
    "iso:country":"DE",
    "sg:address":"Weinbergerstr. 93",
    "sg:city":"M\u00fcnchen",
    "sg:phone":"+49 89/576086",
    "sg:postcode":"81241",
    "sg:province":"Bayern",
    "wof:name":"Fd Computer",
    "wof:placetype":"venue"
},
  "geometry": {"coordinates":[11.4594068527,48.1403465271],"type":"Point"}
}