{
  "type": "Feature",
  "properties": {
    "iso:country":"DE",
    "sg:address":"Gennerstr. 192",
    "sg:city":"H\u00fcrth",
    "sg:phone":"+49 2233/44464",
    "sg:postcode":"50354",
    "sg:province":"Nordrhein-Westfalen",
    "wof:name":"Walter Braunsfeld",
    "wof:placetype":"venue"
},
  "geometry": {"coordinates":[6.882171,50.855145],"type":"Point"}
}