{
  "type": "Feature",
  "properties": {
    "iso:country":"DE",
    "sg:address":"Untere Hauptstr. 8",
    "sg:city":"Freising",
    "sg:phone":"+49 8161/5867",
    "sg:postcode":"85354",
    "sg:province":"Bayern",
    "wof:name":"Bavaria-lichtspiele",
    "wof:placetype":"venue"
},
  "geometry": {"coordinates":[11.745029,48.400948],"type":"Point"}
}