{
  "type": "Feature",
  "properties": {
    "iso:country":"DE",
    "sg:address":"Neuenhainer Str. 2",
    "sg:city":"Bad Soden",
    "sg:phone":"+49 6174/7440",
    "sg:postcode":"65812",
    "sg:province":"Hessen",
    "wof:name":"J. Seefeld",
    "wof:placetype":"venue"
},
  "geometry": {"coordinates":[8.473278,50.15715],"type":"Point"}
}