{
  "type": "Feature",
  "properties": {
    "iso:country":"DE",
    "sg:address":"Am Sportplatz 26",
    "sg:city":"Thedinghausen",
    "sg:postcode":"27321",
    "sg:province":"Niedersachsen",
    "wof:name":"Willkommen Auf Der Homepage Der Sgi Thedinghausen htt",
    "wof:placetype":"venue"
},
  "geometry": {"coordinates":[9.027832,52.959042],"type":"Point"}
}