{
  "type": "Feature",
  "properties": {
    "iso:country":"DE",
    "sg:address":"Marktstr. 7",
    "sg:city":"Braunlage",
    "sg:phone":"+49 5520/1324",
    "sg:postcode":"38700",
    "sg:province":"Niedersachsen",
    "wof:name":"Cafe Nitzschke",
    "wof:placetype":"venue"
},
  "geometry": {"coordinates":[10.611981,51.726719],"type":"Point"}
}