{
  "type": "Feature",
  "properties": {
    "iso:country":"DE",
    "sg:address":"An der Hardt 21 a",
    "sg:city":"Kreuzau",
    "sg:postcode":"52372",
    "sg:province":"Nordrhein-Westfalen",
    "wof:name":"Schr\u00f6der Verwaltung Gmbh",
    "wof:placetype":"venue"
},
  "geometry": {"coordinates":[6.4380960464,50.7296638489],"type":"Point"}
}