{
  "type": "Feature",
  "properties": {
    "iso:country":"DE",
    "sg:address":"Nu\u00dfbaumallee 29",
    "sg:city":"Berlin",
    "sg:phone":"+49 30/3000940",
    "sg:postcode":"14050",
    "sg:province":"Berlin",
    "wof:name":"Gerhard Best M\u00fcnzautomaten Gmbh & Co. Kg",
    "wof:placetype":"venue"
},
  "geometry": {"coordinates":[13.2695407867,52.5185050964],"type":"Point"}
}