{
  "type": "Feature",
  "properties": {
    "iso:country":"DE",
    "sg:address":"Werner-von-Siemens-Str. 32",
    "sg:city":"Erlangen",
    "sg:phone":"+49 9131/23068",
    "sg:postcode":"91052",
    "sg:province":"Bayern",
    "wof:name":"Johann Heinlein Ohg",
    "wof:placetype":"venue"
},
  "geometry": {"coordinates":[11.014122,49.593819],"type":"Point"}
}