{
  "type": "Feature",
  "properties": {
    "iso:country":"DE",
    "sg:address":"Eichendorffweg 1",
    "sg:city":"Heidenheim",
    "sg:phone":"+49 7321/20321",
    "sg:postcode":"89522",
    "sg:province":"Baden-W\u00fcrttemberg",
    "wof:name":"Waldenmaier Verwaltungs Gmbh",
    "wof:placetype":"venue"
},
  "geometry": {"coordinates":[10.172684,48.676605],"type":"Point"}
}