{
  "type": "Feature",
  "properties": {
    "iso:country":"DE",
    "sg:address":"Gneisenaustr. 37",
    "sg:city":"D\u00fcsseldorf",
    "sg:phone":"+49 211/485772",
    "sg:postcode":"40477",
    "sg:province":"Nordrhein-Westfalen",
    "wof:name":"Credo Finanzvermittlungs- Und Verwaltungs Gmbh",
    "wof:placetype":"venue"
},
  "geometry": {"coordinates":[6.78284,51.23867],"type":"Point"}
}