{
  "type": "Feature",
  "properties": {
    "iso:country":"DE",
    "sg:address":"Neuweg 24 a",
    "sg:city":"Mengerschied",
    "sg:postcode":"55490",
    "sg:province":"Rheinland-Pfalz",
    "wof:name":"Bernd Michel Bauunternehmung Und Betreuung Gmbh",
    "wof:placetype":"venue"
},
  "geometry": {"coordinates":[7.503660202,49.9087867737],"type":"Point"}
}