{
  "type": "Feature",
  "properties": {
    "iso:country":"DE",
    "sg:address":"Bergstr. 74",
    "sg:city":"Bad Liebenzell",
    "sg:phone":"+49 7052/2217",
    "sg:postcode":"75378",
    "sg:province":"Baden-W\u00fcrttemberg",
    "wof:name":"Bayerwaldst\u00fcble",
    "wof:placetype":"venue"
},
  "geometry": {"coordinates":[8.7233953476,48.7687263489],"type":"Point"}
}