{
  "type": "Feature",
  "properties": {
    "iso:country":"DE",
    "sg:address":"Pfarrh\u00fcbel 56",
    "sg:city":"Chemnitz",
    "sg:phone":"+49 371/585426",
    "sg:postcode":"09125",
    "sg:province":"Sachsen",
    "wof:name":"Klaus Schlegel",
    "wof:placetype":"venue"
},
  "geometry": {"coordinates":[12.935922,50.788376],"type":"Point"}
}