{
  "type": "Feature",
  "properties": {
    "iso:country":"DE",
    "sg:address":"Birkenstr. 14",
    "sg:city":"Lemgo",
    "sg:phone":"+49 5261/14138",
    "sg:postcode":"32657",
    "sg:province":"Nordrhein-Westfalen",
    "wof:name":"R. Heiler",
    "wof:placetype":"venue"
},
  "geometry": {"coordinates":[8.908747673,52.0510215759],"type":"Point"}
}