{
  "type": "Feature",
  "properties": {
    "iso:country":"DE",
    "sg:address":"Handwerkstr. 14",
    "sg:city":"Waiblingen",
    "sg:phone":"+49 7151/987090",
    "sg:postcode":"71336",
    "sg:province":"Baden-W\u00fcrttemberg",
    "wof:name":"Zarb Chemo-technische Isoliersysteme Gmbh",
    "wof:placetype":"venue"
},
  "geometry": {"coordinates":[9.3253,48.864239],"type":"Point"}
}