{
  "type": "Feature",
  "properties": {
    "iso:country":"DE",
    "sg:address":"Gutenbergstr. 52",
    "sg:city":"Raisdorf",
    "sg:phone":"+49 4307/82850",
    "sg:postcode":"24223",
    "sg:province":"Schleswig-Holstein",
    "wof:name":"Wagner Ohg",
    "wof:placetype":"venue"
},
  "geometry": {"coordinates":[10.216115,54.287052],"type":"Point"}
}