{
  "type": "Feature",
  "properties": {
    "iso:country":"DE",
    "sg:address":"Frohlinder Str. 42",
    "sg:city":"Dortmund",
    "sg:phone":"+49 231/670142",
    "sg:postcode":"44379",
    "sg:province":"Nordrhein-Westfalen",
    "wof:name":"Haus Lichtenberg",
    "wof:placetype":"venue"
},
  "geometry": {"coordinates":[7.3672981262,51.5247802734],"type":"Point"}
}