{
  "type": "Feature",
  "properties": {
    "iso:country":"DE",
    "sg:address":"Am Kietz 6",
    "sg:city":"Zossen",
    "sg:phone":"+49 3377/332561",
    "sg:postcode":"15806",
    "sg:province":"Brandenburg",
    "wof:name":"Am Kietz",
    "wof:placetype":"venue"
},
  "geometry": {"coordinates":[13.4538707733,52.2136955261],"type":"Point"}
}