{
  "type": "Feature",
  "properties": {
    "iso:country":"DE",
    "sg:address":"Martinstr. 42",
    "sg:city":"Ensch",
    "sg:phone":"+49 6507/3265",
    "sg:postcode":"54340",
    "sg:province":"Rheinland-Pfalz",
    "wof:name":"Nikolaus Schu Weinanbau",
    "wof:placetype":"venue"
},
  "geometry": {"coordinates":[6.8317770958,49.8271942139],"type":"Point"}
}