{
  "type": "Feature",
  "properties": {
    "iso:country":"DE",
    "sg:address":"Industriestr.-Ost 12",
    "sg:city":"Haibach",
    "sg:phone":"+49 6021/63050",
    "sg:postcode":"63808",
    "sg:province":"Bayern",
    "wof:name":"Beyer Ingenieure Gmbh",
    "wof:placetype":"venue"
},
  "geometry": {"coordinates":[9.1921510696,49.9633636475],"type":"Point"}
}