{
  "type": "Feature",
  "properties": {
    "iso:country":"DE",
    "sg:address":"Regener Str. 1",
    "sg:city":"Kirchberg i. Wald",
    "sg:phone":"+49 9927/902020",
    "sg:postcode":"94259",
    "sg:province":"Bayern",
    "wof:name":"Friedrich Schiller",
    "wof:placetype":"venue"
},
  "geometry": {"coordinates":[13.182648,48.901016],"type":"Point"}
}