{
  "type": "Feature",
  "properties": {
    "iso:country":"DE",
    "sg:address":"Neckarstr. 28",
    "sg:city":"Viernheim",
    "sg:phone":"+49 6204/4624",
    "sg:postcode":"68519",
    "sg:province":"Hessen",
    "wof:name":"Harry Scherer",
    "wof:placetype":"venue"
},
  "geometry": {"coordinates":[8.5622196198,49.5347213745],"type":"Point"}
}