{
  "type": "Feature",
  "properties": {
    "iso:country":"DE",
    "sg:address":"Moselstr. 6",
    "sg:city":"Trittenheim",
    "sg:phone":"+49 6507/2291",
    "sg:postcode":"54349",
    "sg:province":"Rheinland-Pfalz",
    "wof:name":"Ferdinand Scholer Weinanbau",
    "wof:placetype":"venue"
},
  "geometry": {"coordinates":[6.9008321762,49.822719574],"type":"Point"}
}