{
  "type": "Feature",
  "properties": {
    "iso:country":"DE",
    "sg:address":"W\u00fcrzgartenstr. 31",
    "sg:city":"\u00dcrzig",
    "sg:phone":"+49 6532/2529",
    "sg:postcode":"54539",
    "sg:province":"Rheinland-Pfalz",
    "wof:name":"M. Junglen-inglen",
    "wof:placetype":"venue"
},
  "geometry": {"coordinates":[7.0076799393,49.9801101685],"type":"Point"}
}