{
  "type": "Feature",
  "properties": {
    "iso:country":"DE",
    "sg:address":"Am Bollwerk 1-5",
    "sg:city":"K\u00f6ln",
    "sg:phone":"+49 221/2580647",
    "sg:postcode":"50667",
    "sg:province":"Nordrhein-Westfalen",
    "wof:name":"Hotel-restaurant Kunibert Der Fiese",
    "wof:placetype":"venue"
},
  "geometry": {"coordinates":[6.9618902206,50.9392700195],"type":"Point"}
}