{
  "type": "Feature",
  "properties": {
    "iso:country":"DE",
    "sg:address":"Braunstr. 12",
    "sg:city":"Michelstadt",
    "sg:phone":"+49 6061/5065",
    "sg:postcode":"64720",
    "sg:province":"Hessen",
    "wof:name":"Eiscafe Cappuccino",
    "wof:placetype":"venue"
},
  "geometry": {"coordinates":[9.005881,49.678082],"type":"Point"}
}