{
  "type": "Feature",
  "properties": {
    "iso:country":"DE",
    "sg:address":"Ringstr. 60",
    "sg:city":"Oberschlei\u00dfheim",
    "sg:phone":"+49 89/3154233",
    "sg:postcode":"85764",
    "sg:province":"Bayern",
    "wof:name":"Df Elektronik Gmbh",
    "wof:placetype":"venue"
},
  "geometry": {"coordinates":[11.546262,48.253334],"type":"Point"}
}