{
  "type": "Feature",
  "properties": {
    "iso:country":"DE",
    "sg:address":"Amselweg 12 b",
    "sg:city":"Troisdorf",
    "sg:phone":"+49 2241/951950",
    "sg:postcode":"53844",
    "sg:province":"Nordrhein-Westfalen",
    "wof:name":"Rosen-edv E. K. Inh. Horst Rosenkranz",
    "wof:placetype":"venue"
},
  "geometry": {"coordinates":[7.1051602364,50.8019218445],"type":"Point"}
}