{
  "type": "Feature",
  "properties": {
    "iso:country":"DE",
    "sg:address":"An der Strangriede 1",
    "sg:city":"Hannover",
    "sg:phone":"+49 511/704101",
    "sg:postcode":"30167",
    "sg:province":"Niedersachsen",
    "wof:name":"Uta Limberg",
    "wof:placetype":"venue"
},
  "geometry": {"coordinates":[9.7205505371,52.3906707764],"type":"Point"}
}