{
  "type": "Feature",
  "properties": {
    "iso:country":"DE",
    "sg:address":"Elbgaustr. 248 b",
    "sg:city":"Hamburg",
    "sg:postcode":"22547",
    "sg:province":"Hamburg",
    "wof:name":"Gole Immobilien- Dienstleistungs Gmbh & Co. Kg",
    "wof:placetype":"venue"
},
  "geometry": {"coordinates":[9.8794698715,53.5911750793],"type":"Point"}
}