{
  "type": "Feature",
  "properties": {
    "iso:country":"DE",
    "sg:address":"F\u00f6ckerskamp 18",
    "sg:city":"Dorsten",
    "sg:phone":"+49 2362/25123",
    "sg:postcode":"46282",
    "sg:province":"Nordrhein-Westfalen",
    "wof:name":"Helmut Hartung",
    "wof:placetype":"venue"
},
  "geometry": {"coordinates":[7.0124101639,51.6335105896],"type":"Point"}
}