{
  "type": "Feature",
  "properties": {
    "iso:country":"DE",
    "sg:address":"Nelkenstr. 8",
    "sg:city":"Gessertshausen",
    "sg:phone":"+49 8238/7575",
    "sg:postcode":"86459",
    "sg:province":"Bayern",
    "wof:name":"Johannes Juppe Rechtsanwalt",
    "wof:placetype":"venue"
},
  "geometry": {"coordinates":[10.7309999466,48.3264961243],"type":"Point"}
}