{
  "type": "Feature",
  "properties": {
    "iso:country":"DE",
    "sg:address":"Barrien 10",
    "sg:city":"Sulingen",
    "sg:phone":"+49 4271/5294",
    "sg:postcode":"27232",
    "sg:province":"Niedersachsen",
    "wof:name":"Gasthaus Alfred Wenzel Und Friedhelm Holste",
    "wof:placetype":"venue"
},
  "geometry": {"coordinates":[8.7059020996,52.6649971008],"type":"Point"}
}