{
  "type": "Feature",
  "properties": {
    "iso:country":"DE",
    "sg:address":"Fliederweg 9",
    "sg:city":"Barsinghausen",
    "sg:phone":"+49 5105/3541",
    "sg:postcode":"30890",
    "sg:province":"Niedersachsen",
    "wof:name":"Wilfried Walther",
    "wof:placetype":"venue"
},
  "geometry": {"coordinates":[9.474012,52.307148],"type":"Point"}
}