{
  "type": "Feature",
  "properties": {
    "iso:country":"DE",
    "sg:address":"Bornaer Str 192",
    "sg:city":"Chemnitz",
    "sg:phone":"+49 8022/85194",
    "sg:postcode":"09114",
    "sg:province":"Sachsen",
    "wof:name":"Walter-f. Pristinger",
    "wof:placetype":"venue"
},
  "geometry": {"coordinates":[11.7303857803,47.7024040222],"type":"Point"}
}