{
  "type": "Feature",
  "properties": {
    "iso:country":"DE",
    "sg:address":"Judengraben 1",
    "sg:city":"Neustadt",
    "sg:phone":"+49 9602/8425",
    "sg:postcode":"92660",
    "sg:province":"Bayern",
    "wof:name":"Altbayerische Kristall- Glash\u00fctte Toni Frank",
    "wof:placetype":"venue"
},
  "geometry": {"coordinates":[12.1698713303,49.7290496826],"type":"Point"}
}