{
  "type": "Feature",
  "properties": {
    "iso:country":"DE",
    "sg:address":"Fritschestr. 47",
    "sg:city":"Berlin",
    "sg:phone":"+49 30/3654273",
    "sg:postcode":"10627",
    "sg:province":"Berlin",
    "wof:name":"Joachim Laskowsi Dipl.-ingenieur",
    "wof:placetype":"venue"
},
  "geometry": {"coordinates":[13.300365,52.507053],"type":"Point"}
}