{
  "type": "Feature",
  "properties": {
    "iso:country":"DE",
    "sg:address":"Oberdorfstr. 3a",
    "sg:city":"Eiselfing",
    "sg:phone":"+49 8071/51500",
    "sg:postcode":"83549",
    "sg:province":"Bayern",
    "wof:name":"K. Niederlechner",
    "wof:placetype":"venue"
},
  "geometry": {"coordinates":[12.241623,48.028847],"type":"Point"}
}