{
  "type": "Feature",
  "properties": {
    "iso:country":"DE",
    "sg:address":"Weiherhaus 2",
    "sg:city":"Feucht",
    "sg:phone":"+49 9128/4412",
    "sg:postcode":"90537",
    "sg:province":"Bayern",
    "wof:name":"H. Heiden",
    "wof:placetype":"venue"
},
  "geometry": {"coordinates":[11.271973,49.380955],"type":"Point"}
}