{
  "type": "Feature",
  "properties": {
    "iso:country":"DE",
    "sg:address":"Wallbergstr. 12",
    "sg:city":"Rotenburg",
    "sg:phone":"+49 4261/2247",
    "sg:postcode":"27356",
    "sg:province":"Niedersachsen",
    "wof:name":"Martha Klaproth Masseurin",
    "wof:placetype":"venue"
},
  "geometry": {"coordinates":[9.405979,53.112633],"type":"Point"}
}