{
  "type": "Feature",
  "properties": {
    "iso:country":"DE",
    "sg:address":"M\u00f6rchinger Str. 141",
    "sg:city":"Berlin",
    "sg:postcode":"14169",
    "sg:province":"Berlin",
    "wof:name":"Bytom Verwaltungs Gmbh",
    "wof:placetype":"venue"
},
  "geometry": {"coordinates":[13.2698135376,52.4352302551],"type":"Point"}
}