{
  "type": "Feature",
  "properties": {
    "iso:country":"DE",
    "sg:address":"Eitswiesenstr. 2",
    "sg:city":"Heiningen",
    "sg:phone":"+49 7161/41307",
    "sg:postcode":"73092",
    "sg:province":"Baden-W\u00fcrttemberg",
    "wof:name":"Gernhard Heim",
    "wof:placetype":"venue"
},
  "geometry": {"coordinates":[9.64483,48.654366],"type":"Point"}
}