{
  "type": "Feature",
  "properties": {
    "iso:country":"DE",
    "sg:address":"Marthabr\u00e4ustr. 37",
    "sg:city":"F\u00fcrstenfeldbruck",
    "sg:phone":"+49 8141/27869",
    "sg:postcode":"82256",
    "sg:province":"Bayern",
    "wof:name":"T. Sixt",
    "wof:placetype":"venue"
},
  "geometry": {"coordinates":[11.2463493347,48.1794662476],"type":"Point"}
}