{
  "type": "Feature",
  "properties": {
    "iso:country":"DE",
    "sg:address":"Opelstr. 46",
    "sg:city":"Isernhagen",
    "sg:phone":"+49 511/610971",
    "sg:postcode":"30916",
    "sg:province":"Niedersachsen",
    "wof:name":"Spiegel- Und Farbenglas Gmbh",
    "wof:placetype":"venue"
},
  "geometry": {"coordinates":[9.832577,52.431778],"type":"Point"}
}