{
  "type": "Feature",
  "properties": {
    "iso:country":"DE",
    "sg:address":"Heugasse 3",
    "sg:city":"Buttlar",
    "sg:phone":"+49 36967/75853",
    "sg:postcode":"36419",
    "sg:province":"Th\u00fcringen",
    "wof:name":"H. Hahn",
    "wof:placetype":"venue"
},
  "geometry": {"coordinates":[9.9522809982,50.7564506531],"type":"Point"}
}