{
  "type": "Feature",
  "properties": {
    "iso:country":"DE",
    "sg:address":"Himmelsweg 23",
    "sg:city":"Tostedt",
    "sg:phone":"+49 4182/5828",
    "sg:postcode":"21255",
    "sg:province":"Niedersachsen",
    "wof:name":"Deutsches Rotes Kreuz Ortsverein Tostedt",
    "wof:placetype":"venue"
},
  "geometry": {"coordinates":[9.7082586288,53.28307724],"type":"Point"}
}