{
  "type": "Feature",
  "properties": {
    "iso:country":"DE",
    "sg:address":"Reinstedter Str. 4",
    "sg:city":"Hoym",
    "sg:phone":"+49 34741/201",
    "sg:postcode":"06467",
    "sg:province":"Sachsen-Anhalt",
    "wof:name":"Rs Verwaltungs Gmbh",
    "wof:placetype":"venue"
},
  "geometry": {"coordinates":[11.3214063644,51.7838363647],"type":"Point"}
}