{
  "type": "Feature",
  "properties": {
    "iso:country":"DE",
    "sg:address":"Bahnhofstr. 12",
    "sg:city":"Beuren",
    "sg:phone":"+49 3605/512825",
    "sg:postcode":"37327",
    "sg:province":"Th\u00fcringen",
    "wof:name":"Michael Gorsler",
    "wof:placetype":"venue"
},
  "geometry": {"coordinates":[10.3221521378,51.3876724243],"type":"Point"}
}