{
  "type": "Feature",
  "properties": {
    "iso:country":"DE",
    "sg:address":"Johann-Sebastian-Bach-Str. 4",
    "sg:city":"Rastatt",
    "sg:phone":"+49 7222/21541",
    "sg:postcode":"76437",
    "sg:province":"Baden-W\u00fcrttemberg",
    "wof:name":"Kurt Ziegler Steuerberater",
    "wof:placetype":"venue"
},
  "geometry": {"coordinates":[8.2115488052,48.8646621704],"type":"Point"}
}