{
  "type": "Feature",
  "properties": {
    "iso:country":"DE",
    "sg:address":"Neuenweg 9-11",
    "sg:city":"Gie\u00dfen",
    "sg:postcode":"35390",
    "sg:province":"Hessen",
    "wof:name":"Ludwig Bratfisch Herrenausstatter",
    "wof:placetype":"venue"
},
  "geometry": {"coordinates":[8.675508,50.585178],"type":"Point"}
}