{
  "type": "Feature",
  "properties": {
    "iso:country":"DE",
    "sg:address":"Hardtbergweg 6",
    "sg:city":"K\u00f6nigstein",
    "sg:phone":"+49 6174/3942",
    "sg:postcode":"61462",
    "sg:province":"Hessen",
    "wof:name":"Adolf-messer-stiftung",
    "wof:placetype":"venue"
},
  "geometry": {"coordinates":[8.4780883789,50.1772346497],"type":"Point"}
}