{
  "type": "Feature",
  "properties": {
    "iso:country":"DE",
    "sg:address":"Hauptstr. 22",
    "sg:city":"Leichlingen",
    "sg:phone":"+49 2174/3151",
    "sg:postcode":"42799",
    "sg:province":"Nordrhein-Westfalen",
    "wof:name":"Otto F\u00f6rster",
    "wof:placetype":"venue"
},
  "geometry": {"coordinates":[7.114289,51.11729],"type":"Point"}
}