{
  "type": "Feature",
  "properties": {
    "iso:country":"DE",
    "sg:address":"Pforzheimer Str. 67",
    "sg:city":"Ettlingen",
    "sg:phone":"+49 7243/761720",
    "sg:postcode":"76275",
    "sg:province":"Baden-W\u00fcrttemberg",
    "wof:name":"Restaurant Engele",
    "wof:placetype":"venue"
},
  "geometry": {"coordinates":[8.4172515869,48.9392662048],"type":"Point"}
}