{
  "type": "Feature",
  "properties": {
    "iso:country":"DE",
    "sg:address":"Tagetesstr. 2",
    "sg:city":"M\u00fcnchen",
    "sg:phone":"+49 89/3575340",
    "sg:postcode":"80935",
    "sg:province":"Bayern",
    "wof:name":"Mbm Medienvertrieb Gmbh",
    "wof:placetype":"venue"
},
  "geometry": {"coordinates":[11.5442943573,48.2033195496],"type":"Point"}
}