{
  "type": "Feature",
  "properties": {
    "iso:country":"DE",
    "sg:address":"Im Druseltal 8",
    "sg:city":"Kassel",
    "sg:postcode":"34131",
    "sg:province":"Hessen",
    "wof:name":"Feg Freizeit- Und Erholungsanlagen Gmbh",
    "wof:placetype":"venue"
},
  "geometry": {"coordinates":[9.4141807556,51.3015441895],"type":"Point"}
}