{
  "type": "Feature",
  "properties": {
    "iso:country":"DE",
    "sg:address":"Ebinger Str 25",
    "sg:city":"Bitz",
    "sg:phone":"+49 7431/9800",
    "sg:postcode":"72475",
    "sg:province":"Baden-W\u00fcrttemberg",
    "wof:name":"Mey-herrenw\u00e4sche Gmbh & Co Kg",
    "wof:placetype":"venue"
},
  "geometry": {"coordinates":[9.0863142014,48.2421836853],"type":"Point"}
}