{
  "type": "Feature",
  "properties": {
    "iso:country":"DE",
    "sg:address":"Dorfstr. 106",
    "sg:city":"Neulewin",
    "sg:phone":"+49 33452/3599",
    "sg:postcode":"16259",
    "sg:province":"Brandenburg",
    "wof:name":"Pension Mittelst\u00e4dt",
    "wof:placetype":"venue"
},
  "geometry": {"coordinates":[14.2315349579,52.7707138062],"type":"Point"}
}