{
  "type": "Feature",
  "properties": {
    "iso:country":"DE",
    "sg:address":"Eichfeldstr. 13",
    "sg:city":"Chieming",
    "sg:phone":"+49 8664/98440",
    "sg:postcode":"83339",
    "sg:province":"Bayern",
    "wof:name":"Alpenholz-t\u00fcren Inh. Bodo Wagner",
    "wof:placetype":"venue"
},
  "geometry": {"coordinates":[12.535575,47.909233],"type":"Point"}
}