{
  "type": "Feature",
  "properties": {
    "iso:country":"DE",
    "sg:address":"Hauptstr. 37",
    "sg:city":"Mannheim",
    "sg:phone":"+49 621/792215",
    "sg:postcode":"68259",
    "sg:province":"Baden-W\u00fcrttemberg",
    "wof:name":"Ev. Pfarramt Johannesgemeinde",
    "wof:placetype":"venue"
},
  "geometry": {"coordinates":[8.5340061188,49.4863471985],"type":"Point"}
}