{
  "type": "Feature",
  "properties": {
    "iso:country":"DE",
    "sg:address":"Tittenkofener Str. 3",
    "sg:city":"Erding",
    "sg:phone":"+49 8122/92397",
    "sg:postcode":"85435",
    "sg:province":"Bayern",
    "wof:name":"K\u00fcchentiefpreisagentur",
    "wof:placetype":"venue"
},
  "geometry": {"coordinates":[11.924628,48.347019],"type":"Point"}
}