{
  "type": "Feature",
  "properties": {
    "iso:country":"DE",
    "sg:address":"Rudolf-Breitscheid-Str. 1",
    "sg:city":"M\u00fcgeln",
    "sg:phone":"+49 34362/32328",
    "sg:postcode":"04769",
    "sg:province":"Sachsen",
    "wof:name":"Eberhard Taube",
    "wof:placetype":"venue"
},
  "geometry": {"coordinates":[13.047709,51.236229],"type":"Point"}
}