{
  "type": "Feature",
  "properties": {
    "iso:country":"DE",
    "sg:address":"Vor der Beune 4",
    "sg:city":"Gr\u00fcndau",
    "sg:phone":"+49 6058/910600",
    "sg:postcode":"63584",
    "sg:province":"Hessen",
    "wof:name":"C. Meinhardt-kretschmann Gmbh",
    "wof:placetype":"venue"
},
  "geometry": {"coordinates":[9.1140766144,50.2327346802],"type":"Point"}
}