{
  "type": "Feature",
  "properties": {
    "iso:country":"DE",
    "sg:address":"Hauptstr. 18",
    "sg:city":"Kail",
    "sg:phone":"+49 2672/910174",
    "sg:postcode":"56829",
    "sg:province":"Rheinland-Pfalz",
    "wof:name":"Industriebedarf Schneiders Gmbh",
    "wof:placetype":"venue"
},
  "geometry": {"coordinates":[7.242164135,50.1837882996],"type":"Point"}
}