{
  "type": "Feature",
  "properties": {
    "iso:country":"DE",
    "sg:address":"Wallstr. 17",
    "sg:city":"Ruhland",
    "sg:phone":"+49 35752/2744",
    "sg:postcode":"01945",
    "sg:province":"Brandenburg",
    "wof:name":"Rudolf Schulze",
    "wof:placetype":"venue"
},
  "geometry": {"coordinates":[13.8667192459,51.4578590393],"type":"Point"}
}