{
  "type": "Feature",
  "properties": {
    "iso:country":"DE",
    "sg:address":"Nieder R\u00f6der Str 4",
    "sg:city":"Babenhausen",
    "sg:phone":"+49 6073/72920",
    "sg:postcode":"64832",
    "sg:province":"Hessen",
    "wof:name":"Devochem R\u00f6ntgenchemie",
    "wof:placetype":"venue"
},
  "geometry": {"coordinates":[8.9542150497,49.9622459412],"type":"Point"}
}