{
  "type": "Feature",
  "properties": {
    "iso:country":"DE",
    "sg:address":"Stuttgarter Str. 135",
    "sg:city":"Stuttgart",
    "sg:phone":"+49 711/853753",
    "sg:postcode":"70469",
    "sg:province":"Baden-W\u00fcrttemberg",
    "wof:name":"Sylvia Reiser-h\u00e4rlen Immobilienmaklerin",
    "wof:placetype":"venue"
},
  "geometry": {"coordinates":[9.152970314,48.8094902039],"type":"Point"}
}