{
  "type": "Feature",
  "properties": {
    "iso:country":"DE",
    "sg:address":"Usinger Str. 44",
    "sg:city":"Waldems",
    "sg:phone":"+49 6087/2332",
    "sg:postcode":"65529",
    "sg:province":"Hessen",
    "wof:name":"Udo Powalla",
    "wof:placetype":"venue"
},
  "geometry": {"coordinates":[8.3495950699,50.275592804],"type":"Point"}
}