{
  "type": "Feature",
  "properties": {
    "iso:country":"DE",
    "sg:address":"Peter-Joseph-Krahe-Str. 9",
    "sg:city":"Braunschweig",
    "sg:phone":"+49 531/73361",
    "sg:postcode":"38102",
    "sg:province":"Niedersachsen",
    "wof:name":"Gerda Gahnz Steuerbevollm\u00e4chtigte",
    "wof:placetype":"venue"
},
  "geometry": {"coordinates":[10.5247888565,52.2560386658],"type":"Point"}
}