{
  "type": "Feature",
  "properties": {
    "iso:country":"DE",
    "sg:address":"Kelsterbacher Str. 27",
    "sg:city":"Frankfurt",
    "sg:phone":"+49 69/675891",
    "sg:postcode":"60528",
    "sg:province":"Hessen",
    "wof:name":"Monika R. Royer",
    "wof:placetype":"venue"
},
  "geometry": {"coordinates":[8.645601,50.088531],"type":"Point"}
}