{
  "type": "Feature",
  "properties": {
    "iso:country":"DE",
    "sg:address":"Weichselstr. 3",
    "sg:city":"Neuhof",
    "sg:phone":"+49 6655/3250",
    "sg:postcode":"36119",
    "sg:province":"Hessen",
    "wof:name":"S. Wolf",
    "wof:placetype":"venue"
},
  "geometry": {"coordinates":[9.613368988,50.4482536316],"type":"Point"}
}