{
  "type": "Feature",
  "properties": {
    "iso:country":"DE",
    "sg:address":"Industriestr. 132",
    "sg:city":"K\u00f6ln",
    "sg:phone":"+49 221/9355230",
    "sg:postcode":"50996",
    "sg:province":"Nordrhein-Westfalen",
    "wof:name":"M. Bohm Architekt",
    "wof:placetype":"venue"
},
  "geometry": {"coordinates":[6.991387,50.882343],"type":"Point"}
}