{
  "type": "Feature",
  "properties": {
    "iso:country":"DE",
    "sg:address":"Marstallstr. 9",
    "sg:city":"Paderborn",
    "sg:postcode":"33104",
    "sg:province":"Nordrhein-Westfalen",
    "wof:name":"Historisches Museum Im Marstall",
    "wof:placetype":"venue"
},
  "geometry": {"coordinates":[8.710685,51.745445],"type":"Point"}
}