{
  "type": "Feature",
  "properties": {
    "iso:country":"DE",
    "sg:address":"Bahnhofstr. 12",
    "sg:city":"Munderkingen",
    "sg:phone":"+49 7393/2218",
    "sg:postcode":"89597",
    "sg:province":"Baden-W\u00fcrttemberg",
    "wof:name":"Deutsche Bahn Ag",
    "wof:placetype":"venue"
},
  "geometry": {"coordinates":[9.6457080841,48.2377281189],"type":"Point"}
}