{
  "type": "Feature",
  "properties": {
    "iso:country":"DE",
    "sg:address":"Heuerstr. 13",
    "sg:city":"Mainz",
    "sg:phone":"+49 6131/593154",
    "sg:postcode":"55129",
    "sg:province":"Rheinland-Pfalz",
    "wof:name":"Hans-josef Schmitt",
    "wof:placetype":"venue"
},
  "geometry": {"coordinates":[8.2778682709,49.9601173401],"type":"Point"}
}