{
  "type": "Feature",
  "properties": {
    "iso:country":"DE",
    "sg:address":"Herderstr. 6",
    "sg:city":"Ilmenau",
    "sg:phone":"+49 3677/202047",
    "sg:postcode":"98693",
    "sg:province":"Th\u00fcringen",
    "wof:name":"Dr. Klaus Wei\u00dfgerber Rechtsanwalt",
    "wof:placetype":"venue"
},
  "geometry": {"coordinates":[10.910326004,50.6803627014],"type":"Point"}
}