{
  "type": "Feature",
  "properties": {
    "iso:country":"DE",
    "sg:address":"Zeppelinstr. 42",
    "sg:city":"M\u00f6nchengladbach",
    "sg:phone":"+49 2161/603860",
    "sg:postcode":"41065",
    "sg:province":"Nordrhein-Westfalen",
    "wof:name":"Erika Und Friedrich M\u00fcller",
    "wof:placetype":"venue"
},
  "geometry": {"coordinates":[6.46314,51.208256],"type":"Point"}
}