{
  "type": "Feature",
  "properties": {
    "iso:country":"DE",
    "sg:address":"Schillerstr. 10",
    "sg:city":"N\u00fcrnberg",
    "sg:phone":"+49 911/357670",
    "sg:postcode":"90409",
    "sg:province":"Bayern",
    "wof:name":"H. Baur",
    "wof:placetype":"venue"
},
  "geometry": {"coordinates":[11.0831975937,49.4644584656],"type":"Point"}
}