{
  "type": "Feature",
  "properties": {
    "iso:country":"DE",
    "sg:address":"Neust\u00e4dter Str. 137a",
    "sg:city":"P\u00f6\u00dfneck",
    "sg:phone":"+49 3647/46880",
    "sg:postcode":"07381",
    "sg:province":"Th\u00fcringen",
    "wof:name":"Reinhard Grosch Ingenieur",
    "wof:placetype":"venue"
},
  "geometry": {"coordinates":[11.6124200821,50.7008781433],"type":"Point"}
}