{
  "type": "Feature",
  "properties": {
    "iso:country":"DE",
    "sg:address":"Unterdorfstr. 39",
    "sg:city":"D\u00fcsseldorf",
    "sg:phone":"+49 211/401075",
    "sg:postcode":"40489",
    "sg:province":"Nordrhein-Westfalen",
    "wof:name":"Karl Nawroth",
    "wof:placetype":"venue"
},
  "geometry": {"coordinates":[6.759985,51.308056],"type":"Point"}
}