{
  "type": "Feature",
  "properties": {
    "iso:country":"DE",
    "sg:address":"Marktstr. 63",
    "sg:city":"Winnenden",
    "sg:phone":"+49 7195/1698",
    "sg:postcode":"71364",
    "sg:province":"Baden-W\u00fcrttemberg",
    "wof:name":"Atlas Reisen Gmbh",
    "wof:placetype":"venue"
},
  "geometry": {"coordinates":[9.4002370834,48.8755645752],"type":"Point"}
}