{
  "type": "Feature",
  "properties": {
    "iso:country":"DE",
    "sg:address":"Bergstr. 2",
    "sg:city":"Bad Salzungen",
    "sg:phone":"+49 3695/628416",
    "sg:postcode":"36433",
    "sg:province":"Th\u00fcringen",
    "wof:name":"Cti-services",
    "wof:placetype":"venue"
},
  "geometry": {"coordinates":[10.224144,50.805458],"type":"Point"}
}