{
  "type": "Feature",
  "properties": {
    "iso:country":"DE",
    "sg:address":"Bendelstr. 15",
    "sg:city":"Aachen",
    "sg:phone":"+49 241/474240",
    "sg:postcode":"52062",
    "sg:province":"Nordrhein-Westfalen",
    "wof:name":"Medizinischer Dienst Der Krankenkasse Nordhein",
    "wof:placetype":"venue"
},
  "geometry": {"coordinates":[6.0804109573,50.7739181519],"type":"Point"}
}