{
  "type": "Feature",
  "properties": {
    "iso:country":"DE",
    "sg:address":"Balduinstr. 1",
    "sg:city":"St. Wendel",
    "sg:phone":"+49 6851/84284",
    "sg:postcode":"66606",
    "sg:province":"Saarland",
    "wof:name":"A. Sperling-breit",
    "wof:placetype":"venue"
},
  "geometry": {"coordinates":[7.1715478897,49.4679489136],"type":"Point"}
}