{
  "type": "Feature",
  "properties": {
    "iso:country":"DE",
    "sg:address":"Bei der Schleifm\u00fchle 11",
    "sg:city":"Ingolstadt",
    "sg:phone":"+49 841/910304",
    "sg:postcode":"85049",
    "sg:province":"Bayern",
    "wof:name":"Johann Kl\u00fcgl Verwaltungs- Gmbh",
    "wof:placetype":"venue"
},
  "geometry": {"coordinates":[11.422062,48.761635],"type":"Point"}
}