{
  "type": "Feature",
  "properties": {
    "iso:country":"DE",
    "sg:address":"Lauwetter 23-25",
    "sg:city":"Suhl",
    "sg:phone":"+49 3681/79690",
    "sg:postcode":"98527",
    "sg:province":"Th\u00fcringen",
    "wof:name":"Siemens Ag",
    "wof:placetype":"venue"
},
  "geometry": {"coordinates":[10.6961574554,50.6139068604],"type":"Point"}
}