{
  "type": "Feature",
  "properties": {
    "iso:country":"DE",
    "sg:address":"Industriestr. 1",
    "sg:city":"Lindhorst",
    "sg:phone":"+49 5725/94010",
    "sg:postcode":"31698",
    "sg:province":"Niedersachsen",
    "wof:name":"Otto Hattendorf Gmbh",
    "wof:placetype":"venue"
},
  "geometry": {"coordinates":[9.2909851074,52.3513832092],"type":"Point"}
}