{
  "type": "Feature",
  "properties": {
    "iso:country":"DE",
    "sg:address":"Hubertusallee 42 - 44",
    "sg:city":"Berlin",
    "sg:postcode":"14193",
    "sg:province":"Berlin",
    "wof:name":"S.t.a.r. Tankstellen Verwaltungs Gmbh",
    "wof:placetype":"venue"
},
  "geometry": {"coordinates":[13.284734726,52.4879608154],"type":"Point"}
}