{
  "type": "Feature",
  "properties": {
    "iso:country":"DE",
    "sg:address":"M\u00fcllerstr 27",
    "sg:city":"M\u00fcnchen",
    "sg:phone":"+49 355/584060",
    "sg:postcode":"80469",
    "sg:province":"Bayern",
    "wof:name":"Ahg Management & Controlling Gmbh & Co Kg",
    "wof:placetype":"venue"
},
  "geometry": {"coordinates":[14.428969,51.68594],"type":"Point"}
}