{
  "type": "Feature",
  "properties": {
    "iso:country":"DE",
    "sg:address":"Schumannstr. 4",
    "sg:city":"M\u00fcnchen",
    "sg:phone":"+49 89/54649460",
    "sg:postcode":"81679",
    "sg:province":"Bayern",
    "wof:name":"S\u00fcdvers Gmbh",
    "wof:placetype":"venue"
},
  "geometry": {"coordinates":[11.60272789,48.1407051086],"type":"Point"}
}