{
  "type": "Feature",
  "properties": {
    "iso:country":"DE",
    "sg:address":"Schweizer Str. 71",
    "sg:city":"Frankfurt",
    "sg:phone":"+49 69/616915",
    "sg:postcode":"60594",
    "sg:province":"Hessen",
    "wof:name":"S. Rudorf Gmbh & Co. Apfelweingastst\u00e4tte Kg",
    "wof:placetype":"venue"
},
  "geometry": {"coordinates":[8.6820049286,50.1004981995],"type":"Point"}
}