{
  "type": "Feature",
  "properties": {
    "iso:country":"DE",
    "sg:address":"Freeweid 25",
    "sg:city":"Flintbek",
    "sg:phone":"+49 4347/4399",
    "sg:postcode":"24220",
    "sg:province":"Schleswig-Holstein",
    "wof:name":"Kohler Und Kohler Architekten",
    "wof:placetype":"venue"
},
  "geometry": {"coordinates":[10.063597,54.246899],"type":"Point"}
}