{
  "type": "Feature",
  "properties": {
    "iso:country":"DE",
    "sg:address":"Hauptstr. 25",
    "sg:city":"Bad Nenndorf",
    "sg:phone":"+49 5723/6126",
    "sg:postcode":"31542",
    "sg:province":"Niedersachsen",
    "wof:name":"Kl\u00f6n-klause",
    "wof:placetype":"venue"
},
  "geometry": {"coordinates":[9.3803749084,52.3366775513],"type":"Point"}
}