{
  "type": "Feature",
  "properties": {
    "iso:country":"DE",
    "sg:address":"Bahnhofstr. 5",
    "sg:city":"Bad D\u00fcrrheim",
    "sg:phone":"+49 7726/248",
    "sg:postcode":"78073",
    "sg:province":"Baden-W\u00fcrttemberg",
    "wof:name":"Gasthof J\u00e4gerstuben",
    "wof:placetype":"venue"
},
  "geometry": {"coordinates":[8.5301456451,48.0193099976],"type":"Point"}
}