{
  "type": "Feature",
  "properties": {
    "iso:country":"DE",
    "sg:address":"Branchweilerhofstr. 190",
    "sg:city":"Neustadt",
    "sg:phone":"+49 6321/14097",
    "sg:postcode":"67433",
    "sg:province":"Rheinland-Pfalz",
    "wof:name":"Dat",
    "wof:placetype":"venue"
},
  "geometry": {"coordinates":[8.168728,49.350674],"type":"Point"}
}