{
  "type": "Feature",
  "properties": {
    "iso:country":"DE",
    "sg:address":"Blasiusstr. 39",
    "sg:city":"D\u00fcsseldorf",
    "sg:phone":"+49 211/305935",
    "sg:postcode":"40221",
    "sg:province":"Nordrhein-Westfalen",
    "wof:name":"Hermann Weitz",
    "wof:placetype":"venue"
},
  "geometry": {"coordinates":[6.736623,51.207359],"type":"Point"}
}