{
  "type": "Feature",
  "properties": {
    "iso:country":"DE",
    "sg:address":"Dorfstr. 32",
    "sg:city":"M\u00f6llendorf",
    "sg:phone":"+49 39388/28668",
    "sg:postcode":"39579",
    "sg:province":"Sachsen-Anhalt",
    "wof:name":"Helmut Urbschat",
    "wof:placetype":"venue"
},
  "geometry": {"coordinates":[11.846161,52.737476],"type":"Point"}
}