{
  "type": "Feature",
  "properties": {
    "iso:country":"DE",
    "sg:address":"Marienhof",
    "sg:city":"Steinau",
    "sg:phone":"+49 6667/403",
    "sg:postcode":"36396",
    "sg:province":"Hessen",
    "wof:name":"Josef Hohmann",
    "wof:placetype":"venue"
},
  "geometry": {"coordinates":[9.407944,50.374008],"type":"Point"}
}