{
  "type": "Feature",
  "properties": {
    "iso:country":"DE",
    "sg:address":"Pfarrer Walter Str. 2",
    "sg:city":"Kleinrinderfeld",
    "sg:phone":"+49 9366/1466",
    "sg:postcode":"97271",
    "sg:province":"Bayern",
    "wof:name":"Kreissparkasse W\u00fcrzburg",
    "wof:placetype":"venue"
},
  "geometry": {"coordinates":[9.84458,49.699829],"type":"Point"}
}