{
  "type": "Feature",
  "properties": {
    "iso:country":"DE",
    "sg:address":"Hanseallee 59",
    "sg:city":"Stendal",
    "sg:phone":"+49 3931/219216",
    "sg:postcode":"39576",
    "sg:province":"Sachsen-Anhalt",
    "wof:name":"Cordula Weis Praxis F\u00fcr Physiotherapie",
    "wof:placetype":"venue"
},
  "geometry": {"coordinates":[11.854362,52.587978],"type":"Point"}
}