{
  "type": "Feature",
  "properties": {
    "iso:country":"DE",
    "sg:address":"Bahnhofstr. 80",
    "sg:city":"Zeven",
    "sg:phone":"+49 4281/2227",
    "sg:postcode":"27404",
    "sg:province":"Niedersachsen",
    "wof:name":"Wilhelm Kruse",
    "wof:placetype":"venue"
},
  "geometry": {"coordinates":[9.276178,53.281406],"type":"Point"}
}