{
  "type": "Feature",
  "properties": {
    "iso:country":"DE",
    "sg:address":"Am Honberggraben",
    "sg:city":"Tuttlingen",
    "sg:phone":"+49 7461/12252",
    "sg:postcode":"78532",
    "sg:province":"Baden-W\u00fcrttemberg",
    "wof:name":"Vereinsgastst\u00e4tte Ballon- Sportgruppe Tuttlingen E. V.",
    "wof:placetype":"venue"
},
  "geometry": {"coordinates":[8.8270530701,47.9784164429],"type":"Point"}
}