{
  "type": "Feature",
  "properties": {
    "iso:country":"DE",
    "sg:address":"Wilhelm-Leuschner-Str. 5",
    "sg:city":"Ro\u00dfdorf",
    "sg:phone":"+49 6154/83792",
    "sg:postcode":"64380",
    "sg:province":"Hessen",
    "wof:name":"Restaurant Madeira",
    "wof:placetype":"venue"
},
  "geometry": {"coordinates":[8.7559480667,49.8573112488],"type":"Point"}
}