{
  "type": "Feature",
  "properties": {
    "iso:country":"DE",
    "sg:address":"Im Winkel 23",
    "sg:city":"K\u00f6nigslutter",
    "sg:phone":"+49 5353/1001",
    "sg:postcode":"38154",
    "sg:province":"Niedersachsen",
    "wof:name":"Hotel A. Richter",
    "wof:placetype":"venue"
},
  "geometry": {"coordinates":[10.7521219254,52.2599143982],"type":"Point"}
}