{
  "type": "Feature",
  "properties": {
    "iso:country":"DE",
    "sg:address":"Marienwerderstr. 15",
    "sg:city":"Grevenbroich",
    "sg:phone":"+49 2182/82070",
    "sg:postcode":"41516",
    "sg:province":"Nordrhein-Westfalen",
    "wof:name":"Weide Ingenieurteam Gmbh",
    "wof:placetype":"venue"
},
  "geometry": {"coordinates":[6.6750612259,51.1244659424],"type":"Point"}
}