{
  "type": "Feature",
  "properties": {
    "iso:country":"DE",
    "sg:address":"Vredenerstr. 230",
    "sg:city":"Stadtlohn-Wenningfeld",
    "sg:phone":"+49 2563",
    "sg:postcode":"48703",
    "sg:province":"Nordrhein-Westfalen",
    "wof:name":"Seitfeld Gmbh",
    "wof:placetype":"venue"
},
  "geometry": {"coordinates":[6.8953900337,51.9930381775],"type":"Point"}
}