{
  "type": "Feature",
  "properties": {
    "iso:country":"DE",
    "sg:address":"Wagenburgstr. 139",
    "sg:city":"Stuttgart",
    "sg:phone":"+49 711/486940",
    "sg:postcode":"70186",
    "sg:province":"Baden-W\u00fcrttemberg",
    "wof:name":"Brigitte Friedrich",
    "wof:placetype":"venue"
},
  "geometry": {"coordinates":[9.2068843842,48.7812805176],"type":"Point"}
}