{
  "type": "Feature",
  "properties": {
    "iso:country":"DE",
    "sg:address":"Balanstr. 174",
    "sg:city":"M\u00fcnchen",
    "sg:phone":"+49 89/6802183",
    "sg:postcode":"81549",
    "sg:province":"Bayern",
    "wof:name":"Der Eismacher",
    "wof:placetype":"venue"
},
  "geometry": {"coordinates":[11.603978,48.107159],"type":"Point"}
}