{
  "type": "Feature",
  "properties": {
    "iso:country":"DE",
    "sg:address":"Baumschulallee 27",
    "sg:city":"Bonn",
    "sg:phone":"+49 228/632081",
    "sg:postcode":"53115",
    "sg:province":"Nordrhein-Westfalen",
    "wof:name":"Dr. Hans Afflerbach Architekt",
    "wof:placetype":"venue"
},
  "geometry": {"coordinates":[7.093979,50.730358],"type":"Point"}
}