{
  "type": "Feature",
  "properties": {
    "iso:country":"DE",
    "sg:address":"M\u00fchlweing\u00e4rten 59",
    "sg:city":"Waiblingen",
    "sg:phone":"+49 7146/41243",
    "sg:postcode":"71336",
    "sg:province":"Baden-W\u00fcrttemberg",
    "wof:name":"Pro-oil Vertriebs Gmbh",
    "wof:placetype":"venue"
},
  "geometry": {"coordinates":[9.3081607819,48.8936271667],"type":"Point"}
}