{
  "type": "Feature",
  "properties": {
    "iso:country":"DE",
    "sg:address":"Am Hulsberg 92",
    "sg:city":"Bremen",
    "sg:phone":"+49 421/443792",
    "sg:postcode":"28205",
    "sg:province":"Bremen",
    "wof:name":"Leni Denk",
    "wof:placetype":"venue"
},
  "geometry": {"coordinates":[8.8477277756,53.0717277527],"type":"Point"}
}