{
  "type": "Feature",
  "properties": {
    "iso:country":"DE",
    "sg:address":"Stader Landstr. 1",
    "sg:city":"Bremen",
    "sg:phone":"+49 421/631705",
    "sg:postcode":"28719",
    "sg:province":"Bremen",
    "wof:name":"Peter Heinemann",
    "wof:placetype":"venue"
},
  "geometry": {"coordinates":[8.7027387619,53.1677742004],"type":"Point"}
}