{
  "type": "Feature",
  "properties": {
    "iso:country":"DE",
    "sg:address":"Nei\u00dfestr. 24-26",
    "sg:city":"Osthofen",
    "sg:phone":"+49 6242/911100",
    "sg:postcode":"67574",
    "sg:province":"Rheinland-Pfalz",
    "wof:name":"Alten Und Altenpflegeheim Haus Jacobus Ggmbh",
    "wof:placetype":"venue"
},
  "geometry": {"coordinates":[8.326478,49.710625],"type":"Point"}
}