{
  "type": "Feature",
  "properties": {
    "iso:country":"DE",
    "sg:address":"An der Trift 65",
    "sg:city":"Dreieich",
    "sg:phone":"+49 6103/98790",
    "sg:postcode":"63303",
    "sg:province":"Hessen",
    "wof:name":"Saspo Gmbh",
    "wof:placetype":"venue"
},
  "geometry": {"coordinates":[8.69102,50.004913],"type":"Point"}
}