{
  "type": "Feature",
  "properties": {
    "iso:country":"DE",
    "sg:address":"Hessestr. 3",
    "sg:city":"Frankfurt",
    "sg:phone":"+49 69/573713",
    "sg:postcode":"60439",
    "sg:province":"Hessen",
    "wof:name":"Bobbest\u00fcbchen",
    "wof:placetype":"venue"
},
  "geometry": {"coordinates":[8.6450595856,50.1612968445],"type":"Point"}
}