{
  "type": "Feature",
  "properties": {
    "iso:country":"DE",
    "sg:address":"Friedensstr. 57",
    "sg:city":"Laucha",
    "sg:phone":"+49 3622/65200",
    "sg:postcode":"99880",
    "sg:province":"Th\u00fcringen",
    "wof:name":"Th\u00fcr. Baumaschinen-center Franz Kahl Gmbh",
    "wof:placetype":"venue"
},
  "geometry": {"coordinates":[10.548089,50.917751],"type":"Point"}
}