{
  "type": "Feature",
  "properties": {
    "iso:country":"DE",
    "sg:address":"\u00c4u\u00dfere N\u00fcrnberger Str. 1",
    "sg:city":"Forchheim",
    "sg:postcode":"91301",
    "sg:province":"Bayern",
    "wof:name":"Blank Silo-estrich Verwaltungs Gmbh",
    "wof:placetype":"venue"
},
  "geometry": {"coordinates":[11.0613641739,49.7140922546],"type":"Point"}
}