{
  "type": "Feature",
  "properties": {
    "iso:country":"DE",
    "sg:address":"Kuphalstr. 69",
    "sg:city":"Rostock",
    "sg:phone":"+49 381/809200",
    "sg:postcode":"18069",
    "sg:province":"Mecklenburg-Vorpommern",
    "wof:name":"Wiro Wohnen In Rostock Wohnungsgesellschaft Mbh",
    "wof:placetype":"venue"
},
  "geometry": {"coordinates":[12.0818662643,54.0914611816],"type":"Point"}
}