{
  "type": "Feature",
  "properties": {
    "iso:country":"DE",
    "sg:address":"Industriestr. 12",
    "sg:city":"Feuchtwangen",
    "sg:phone":"+49 9852/1385",
    "sg:postcode":"91555",
    "sg:province":"Bayern",
    "wof:name":"Fr\u00fch Bauelemente Gmbh",
    "wof:placetype":"venue"
},
  "geometry": {"coordinates":[10.319224,49.16444],"type":"Point"}
}