{
  "type": "Feature",
  "properties": {
    "iso:country":"DE",
    "sg:address":"E.-Th\u00e4lmann-Str. 17",
    "sg:city":"F\u00f6rderstedt",
    "sg:phone":"+49 39266/827",
    "sg:postcode":"39443",
    "sg:province":"Sachsen-Anhalt",
    "wof:name":"Kreissparkasse Atzendorf, \u00c4tzend",
    "wof:placetype":"venue"
},
  "geometry": {"coordinates":[11.634299,51.897224],"type":"Point"}
}