{
  "type": "Feature",
  "properties": {
    "iso:country":"DE",
    "sg:address":"Weidenbornstrasse 8a",
    "sg:city":"Wiesbaden",
    "sg:phone":"+49 611/7901120",
    "sg:postcode":"65189",
    "sg:province":"Hessen",
    "wof:name":"Allka Finanzdienstleistungen",
    "wof:placetype":"venue"
},
  "geometry": {"coordinates":[8.2559080124,50.0627861023],"type":"Point"}
}