{
  "type": "Feature",
  "properties": {
    "iso:country":"DE",
    "sg:address":"Europaring 74",
    "sg:city":"Gro\u00df-Gerau",
    "sg:phone":"+49 6152/57562",
    "sg:postcode":"64521",
    "sg:province":"Hessen",
    "wof:name":"Ev. Pfarramt S\u00fcd",
    "wof:placetype":"venue"
},
  "geometry": {"coordinates":[8.4729204178,49.9081115723],"type":"Point"}
}