{
  "type": "Feature",
  "properties": {
    "iso:country":"DE",
    "sg:address":"Haffkruger Weg 33",
    "sg:city":"Hamburg",
    "sg:phone":"+49 40/2296906",
    "sg:postcode":"22143",
    "sg:province":"Hamburg",
    "wof:name":"Inter-naturales Handelsagentur Gerald Edler E. K.",
    "wof:placetype":"venue"
},
  "geometry": {"coordinates":[10.1498832703,53.6124229431],"type":"Point"}
}