{
  "type": "Feature",
  "properties": {
    "iso:country":"DE",
    "sg:address":"Darmst\u00e4dter Stra\u00dfe 23",
    "sg:city":"K\u00f6ln",
    "sg:postcode":"50678",
    "sg:province":"Nordrhein-Westfalen",
    "wof:name":"Rentenberatung Inge Richters-dokter",
    "wof:placetype":"venue"
},
  "geometry": {"coordinates":[6.9623441696,50.9191169739],"type":"Point"}
}