{
  "type": "Feature",
  "properties": {
    "iso:country":"DE",
    "sg:address":"Marktstr. 2",
    "sg:city":"Titz",
    "sg:phone":"+49 2463/7303",
    "sg:postcode":"52445",
    "sg:province":"Nordrhein-Westfalen",
    "wof:name":"Franz-peter Cla\u00dfen",
    "wof:placetype":"venue"
},
  "geometry": {"coordinates":[6.4244031906,51.0057106018],"type":"Point"}
}