{
  "type": "Feature",
  "properties": {
    "iso:country":"DE",
    "sg:address":"Nepomukweg 10",
    "sg:city":"Ravensburg",
    "sg:phone":"+49 751/62156",
    "sg:postcode":"88214",
    "sg:province":"Baden-W\u00fcrttemberg",
    "wof:name":"G. Wagner Rechtsanwalt",
    "wof:placetype":"venue"
},
  "geometry": {"coordinates":[9.6195249557,47.7232971191],"type":"Point"}
}