{
  "type": "Feature",
  "properties": {
    "iso:country":"DE",
    "sg:address":"Johannes-R.-Becher-Str. 46",
    "sg:city":"Bautzen",
    "sg:postcode":"02625",
    "sg:province":"Sachsen",
    "wof:name":"Sonnek Immobilien- Verwertungs Gmbh",
    "wof:placetype":"venue"
},
  "geometry": {"coordinates":[14.4457302094,51.1797142029],"type":"Point"}
}