{
  "type": "Feature",
  "properties": {
    "iso:country":"DE",
    "sg:address":"M\u00fcnchener Str. 135",
    "sg:city":"Ingolstadt",
    "sg:postcode":"85051",
    "sg:province":"Bayern",
    "wof:name":"Dr. Reiser Gmbh",
    "wof:placetype":"venue"
},
  "geometry": {"coordinates":[11.436392,48.739384],"type":"Point"}
}