{
  "type": "Feature",
  "properties": {
    "iso:country":"DE",
    "sg:address":"B\u00f6dekerstr. 79",
    "sg:city":"Hannover",
    "sg:phone":"+49 511/621728",
    "sg:postcode":"30161",
    "sg:province":"Niedersachsen",
    "wof:name":"Bollmann Friedemann Architektenpartnerschaft",
    "wof:placetype":"venue"
},
  "geometry": {"coordinates":[9.750651,52.387924],"type":"Point"}
}