{
  "type": "Feature",
  "properties": {
    "iso:country":"DE",
    "sg:address":"Kynastweg 18",
    "sg:city":"Mei\u00dfen",
    "sg:phone":"+49 3521/457640",
    "sg:postcode":"01662",
    "sg:province":"Sachsen",
    "wof:name":"S. Richter",
    "wof:placetype":"venue"
},
  "geometry": {"coordinates":[13.45195961,51.1599617004],"type":"Point"}
}