{
  "type": "Feature",
  "properties": {
    "iso:country":"DE",
    "sg:address":"Vierbacher Str. 3",
    "sg:city":"Mei\u00dfner",
    "sg:phone":"+49 5657/490",
    "sg:postcode":"37290",
    "sg:province":"Hessen",
    "wof:name":"Karl Hollerbach",
    "wof:placetype":"venue"
},
  "geometry": {"coordinates":[9.910337,51.191044],"type":"Point"}
}