{
  "type": "Feature",
  "properties": {
    "iso:country":"DE",
    "sg:address":"Irisweg 48",
    "sg:city":"Pl\u00fcderhausen",
    "sg:phone":"+49 7181/84721",
    "sg:postcode":"73655",
    "sg:province":"Baden-W\u00fcrttemberg",
    "wof:name":"M. Ludwig",
    "wof:placetype":"venue"
},
  "geometry": {"coordinates":[9.6001310349,48.7878837585],"type":"Point"}
}