{
  "type": "Feature",
  "properties": {
    "iso:country":"DE",
    "sg:address":"Hauptstr. 132",
    "sg:city":"Ostrhauderfehn",
    "sg:phone":"+49 4952/61782",
    "sg:postcode":"26842",
    "sg:province":"Niedersachsen",
    "wof:name":"Bistro Keita",
    "wof:placetype":"venue"
},
  "geometry": {"coordinates":[7.6233329773,53.1406402588],"type":"Point"}
}