{
  "type": "Feature",
  "properties": {
    "iso:country":"DE",
    "sg:address":"Kirchhofstr. 45",
    "sg:city":"M\u00f6nchengladbach",
    "sg:phone":"+49 2166/601329",
    "sg:postcode":"41199",
    "sg:province":"Nordrhein-Westfalen",
    "wof:name":"Manfred Kaftan",
    "wof:placetype":"venue"
},
  "geometry": {"coordinates":[6.456964,51.134117],"type":"Point"}
}