{
  "type": "Feature",
  "properties": {
    "iso:country":"DE",
    "sg:address":"Schulstr. 16-18",
    "sg:city":"D\u00fcsseldorf",
    "sg:postcode":"40213",
    "sg:province":"Nordrhein-Westfalen",
    "wof:name":"Betten-forum",
    "wof:placetype":"venue"
},
  "geometry": {"coordinates":[6.7706198692,51.2239112854],"type":"Point"}
}