{
  "type": "Feature",
  "properties": {
    "iso:country":"DE",
    "sg:address":"Segelbacher Str. 25",
    "sg:city":"Wolpertswende",
    "sg:postcode":"88284",
    "sg:province":"Baden-W\u00fcrttemberg",
    "wof:name":"Zimmerei, Holzhaus- Und Innenausbau",
    "wof:placetype":"venue"
},
  "geometry": {"coordinates":[9.6151790619,47.8965988159],"type":"Point"}
}