{
  "type": "Feature",
  "properties": {
    "iso:country":"DE",
    "sg:address":"Friedrichstr. 46",
    "sg:city":"K\u00f6then",
    "sg:phone":"+49 3496/212003",
    "sg:postcode":"06366",
    "sg:province":"Sachsen-Anhalt",
    "wof:name":"Hans-peter Tr\u00d6se",
    "wof:placetype":"venue"
},
  "geometry": {"coordinates":[11.9853391647,51.7541542053],"type":"Point"}
}