{
  "type": "Feature",
  "properties": {
    "iso:country":"DE",
    "sg:address":"Bochumer Str. 80",
    "sg:city":"Herne",
    "sg:phone":"+49 2323/44519",
    "sg:postcode":"44623",
    "sg:province":"Nordrhein-Westfalen",
    "wof:name":"K. Langner",
    "wof:placetype":"venue"
},
  "geometry": {"coordinates":[7.221763,51.530815],"type":"Point"}
}