{
  "type": "Feature",
  "properties": {
    "iso:country":"DE",
    "sg:address":"Erchanstr. 1",
    "sg:city":"Ingolstadt",
    "sg:phone":"+49 8424/1458",
    "sg:postcode":"85049",
    "sg:province":"Bayern",
    "wof:name":"Franz Zeller",
    "wof:placetype":"venue"
},
  "geometry": {"coordinates":[11.275394,48.767124],"type":"Point"}
}