{
  "type": "Feature",
  "properties": {
    "iso:country":"DE",
    "sg:address":"Turfstr. 11a",
    "sg:city":"M\u00fcnchen",
    "sg:postcode":"81929",
    "sg:province":"Bayern",
    "wof:name":"Botanischer Garten",
    "wof:placetype":"venue"
},
  "geometry": {"coordinates":[11.659055,48.141129],"type":"Point"}
}