{
  "type": "Feature",
  "properties": {
    "iso:country":"DE",
    "sg:address":"Gartenweg 10",
    "sg:city":"Kaufbeuren",
    "sg:phone":"+49 8341/2283",
    "sg:postcode":"87600",
    "sg:province":"Bayern",
    "wof:name":"Walter Lieb Masseur",
    "wof:placetype":"venue"
},
  "geometry": {"coordinates":[10.630308,47.881741],"type":"Point"}
}