{
  "type": "Feature",
  "properties": {
    "iso:country":"DE",
    "sg:address":"Traubenstr. 20",
    "sg:city":"Korb",
    "sg:phone":"+49 7151/603245",
    "sg:postcode":"71404",
    "sg:province":"Baden-W\u00fcrttemberg",
    "wof:name":"Armin Sch\u00f6n",
    "wof:placetype":"venue"
},
  "geometry": {"coordinates":[9.373392,48.827984],"type":"Point"}
}