{
  "type": "Feature",
  "properties": {
    "iso:country":"DE",
    "sg:address":"Mittelstr. 8",
    "sg:city":"Moers",
    "sg:postcode":"47441",
    "sg:province":"Nordrhein-Westfalen",
    "wof:name":"Silvia Derpmann",
    "wof:placetype":"venue"
},
  "geometry": {"coordinates":[6.6335568428,51.4496955872],"type":"Point"}
}