{
  "type": "Feature",
  "properties": {
    "iso:country":"DE",
    "sg:address":"Ringstr. 55",
    "sg:city":"Neumarkt",
    "sg:phone":"+49 9181/26670",
    "sg:postcode":"92318",
    "sg:province":"Bayern",
    "wof:name":"Caritas-altenheim",
    "wof:placetype":"venue"
},
  "geometry": {"coordinates":[11.454274,49.279442],"type":"Point"}
}