{
  "type": "Feature",
  "properties": {
    "iso:country":"DE",
    "sg:address":"Kurf\u00fcrstendamm 143",
    "sg:city":"Berlin",
    "sg:phone":"+49 30/8919096",
    "sg:postcode":"10709",
    "sg:province":"Berlin",
    "wof:name":"Adametz & R\u00f6sgen Gmbh",
    "wof:placetype":"venue"
},
  "geometry": {"coordinates":[13.298017,52.498093],"type":"Point"}
}