{
  "type": "Feature",
  "properties": {
    "iso:country":"DE",
    "sg:address":"Kastanienweg 5",
    "sg:city":"Ermlitz",
    "sg:postcode":"06184",
    "sg:province":"Sachsen-Anhalt",
    "wof:name":"Smile Und Fun Verlag Und Ideenb\u00f6rse Inh.",
    "wof:placetype":"venue"
},
  "geometry": {"coordinates":[12.1623344421,51.393371582],"type":"Point"}
}