{
  "type": "Feature",
  "properties": {
    "iso:country":"DE",
    "sg:address":"Hestert 29",
    "sg:city":"Kevelaer",
    "sg:phone":"+49 2832/8651",
    "sg:postcode":"47626",
    "sg:province":"Nordrhein-Westfalen",
    "wof:name":"Josef R\u00f6\u00f6s",
    "wof:placetype":"venue"
},
  "geometry": {"coordinates":[6.303708,51.610439],"type":"Point"}
}