{
  "type": "Feature",
  "properties": {
    "iso:country":"DE",
    "sg:address":"Heidensche Str. 105",
    "sg:city":"Lemgo",
    "sg:phone":"+49 5232/3332",
    "sg:postcode":"32657",
    "sg:province":"Nordrhein-Westfalen",
    "wof:name":"F. Krancke Holzbearbeitungsmaschinenhdl.",
    "wof:placetype":"venue"
},
  "geometry": {"coordinates":[8.8671236038,51.9966125488],"type":"Point"}
}