{
  "type": "Feature",
  "properties": {
    "iso:country":"DE",
    "sg:address":"Siedlerstr. 15 a",
    "sg:city":"B\u00fcsingen",
    "sg:phone":"+49 7734/6967",
    "sg:postcode":"78266",
    "sg:province":"Baden-W\u00fcrttemberg",
    "wof:name":"Paul G\u00fcntert",
    "wof:placetype":"venue"
},
  "geometry": {"coordinates":[8.68807,47.699982],"type":"Point"}
}