{
  "type": "Feature",
  "properties": {
    "iso:country":"DE",
    "sg:address":"Pasteurstr. 2",
    "sg:city":"M\u00fclheim",
    "sg:phone":"+49 208/374840",
    "sg:postcode":"45470",
    "sg:province":"Nordrhein-Westfalen",
    "wof:name":"Robert-koch-apotheke Dr. Frank Leimkugel E. K.",
    "wof:placetype":"venue"
},
  "geometry": {"coordinates":[6.901361,51.417538],"type":"Point"}
}