{
  "type": "Feature",
  "properties": {
    "iso:country":"DE",
    "sg:address":"Coppistr. 78",
    "sg:city":"Leipzig",
    "sg:phone":"+49 341/9111030",
    "sg:postcode":"04157",
    "sg:province":"Sachsen",
    "wof:name":"Horstmann Elementtechnik Beteiligungsges. Mbh",
    "wof:placetype":"venue"
},
  "geometry": {"coordinates":[12.36902,51.367332],"type":"Point"}
}