{
  "type": "Feature",
  "properties": {
    "iso:country":"DE",
    "sg:address":"In der Salzwiese",
    "sg:city":"Pfinztal",
    "sg:postcode":"76327",
    "sg:province":"Baden-W\u00fcrttemberg",
    "wof:name":"Minimal",
    "wof:placetype":"venue"
},
  "geometry": {"coordinates":[8.5356283188,48.9935264587],"type":"Point"}
}