{
  "type": "Feature",
  "properties": {
    "iso:country":"DE",
    "sg:address":"Drosselstr. 3",
    "sg:city":"Peiting",
    "sg:phone":"+49 8861/6008",
    "sg:postcode":"86971",
    "sg:province":"Bayern",
    "wof:name":"Asanger Verwaltungs Gmbh",
    "wof:placetype":"venue"
},
  "geometry": {"coordinates":[10.921788,47.801849],"type":"Point"}
}