{
  "type": "Feature",
  "properties": {
    "iso:country":"DE",
    "sg:address":"Lenzenerstr. 15",
    "sg:city":"Perleberg",
    "sg:phone":"+49 3876",
    "sg:postcode":"19348",
    "sg:province":"Brandenburg",
    "wof:name":"Delta Handelsgesellschaft Mbh - - - Zaunspezialist",
    "wof:placetype":"venue"
},
  "geometry": {"coordinates":[11.848634,53.071049],"type":"Point"}
}