{
  "type": "Feature",
  "properties": {
    "iso:country":"DE",
    "sg:address":"Kanzlerstr. 14",
    "sg:city":"Eimsheim",
    "sg:phone":"+49 6249/1673",
    "sg:postcode":"55278",
    "sg:province":"Rheinland-Pfalz",
    "wof:name":"Reinhard Darmstadt Steuerberater",
    "wof:placetype":"venue"
},
  "geometry": {"coordinates":[8.297246933,49.7955093384],"type":"Point"}
}