{
  "type": "Feature",
  "properties": {
    "iso:country":"DE",
    "sg:address":"Bonner Str. 35",
    "sg:city":"K\u00f6ln",
    "sg:phone":"+49 221/313448",
    "sg:postcode":"50677",
    "sg:province":"Nordrhein-Westfalen",
    "wof:name":"S. Michel",
    "wof:placetype":"venue"
},
  "geometry": {"coordinates":[6.960486,50.918839],"type":"Point"}
}