{
  "type": "Feature",
  "properties": {
    "iso:country":"DE",
    "sg:address":"Lindenstr. 40",
    "sg:city":"Parchim",
    "sg:phone":"+49 3871/264778",
    "sg:postcode":"19370",
    "sg:province":"Mecklenburg-Vorpommern",
    "wof:name":"R. Redmer",
    "wof:placetype":"venue"
},
  "geometry": {"coordinates":[11.850507,53.42804],"type":"Point"}
}