{
  "type": "Feature",
  "properties": {
    "iso:country":"DE",
    "sg:address":"Lagkamp 3",
    "sg:city":"Braunschweig",
    "sg:phone":"+49 5307/940316",
    "sg:postcode":"38110",
    "sg:province":"Niedersachsen",
    "wof:name":"Harald Und Inge Stuckenbrock",
    "wof:placetype":"venue"
},
  "geometry": {"coordinates":[10.510358,52.333878],"type":"Point"}
}