{
  "type": "Feature",
  "properties": {
    "iso:country":"DE",
    "sg:address":"Stolzestr. 29",
    "sg:city":"Hannover",
    "sg:phone":"+49 511/816446",
    "sg:postcode":"30171",
    "sg:province":"Niedersachsen",
    "wof:name":"Teha Jahnke Kunstmaler",
    "wof:placetype":"venue"
},
  "geometry": {"coordinates":[9.759126,52.366669],"type":"Point"}
}