{
  "type": "Feature",
  "properties": {
    "iso:country":"DE",
    "sg:address":"Bl\u00fccherstr. 25",
    "sg:city":"Saarbr\u00fccken",
    "sg:phone":"+49 681/586090",
    "sg:postcode":"66119",
    "sg:province":"Saarland",
    "wof:name":"Tk Thomas Koch Logistik Gesch\u00e4ftsf\u00fchrungs-gmbh",
    "wof:placetype":"venue"
},
  "geometry": {"coordinates":[7.004153,49.224983],"type":"Point"}
}