{
  "type": "Feature",
  "properties": {
    "iso:country":"DE",
    "sg:address":"Gothaer Str. 2b",
    "sg:city":"Neudietendorf",
    "sg:phone":"+49 3621/889278",
    "sg:postcode":"99192",
    "sg:province":"Th\u00fcringen",
    "wof:name":"Ihr Partner F\u00fcr Telekommunikation",
    "wof:placetype":"venue"
},
  "geometry": {"coordinates":[10.91367,50.914787],"type":"Point"}
}