{
  "type": "Feature",
  "properties": {
    "iso:country":"DE",
    "sg:address":"Konrad-Adenauer-Ufer 21::",
    "sg:city":"Koeln",
    "sg:phone":"+49 4922/114812",
    "sg:postcode":"50592",
    "wof:name":"Axa Colonia Krankenversicherung Aktiengesellschaft",
    "wof:placetype":"venue"
},
  "geometry": {"coordinates":[6.963136,50.945621],"type":"Point"}
}