{
  "type": "Feature",
  "properties": {
    "iso:country":"DE",
    "sg:address":"Eggmannstr. 7",
    "sg:city":"Tannheim",
    "sg:phone":"+49 8395/94080",
    "sg:postcode":"88459",
    "sg:province":"Baden-W\u00fcrttemberg",
    "wof:name":"K\u00fcchle Gmbh",
    "wof:placetype":"venue"
},
  "geometry": {"coordinates":[10.0815,47.999165],"type":"Point"}
}