{
  "type": "Feature",
  "properties": {
    "iso:country":"DE",
    "sg:address":"Bahnhofsplatz 6",
    "sg:city":"M\u00fcnster",
    "sg:postcode":"64839",
    "sg:province":"Hessen",
    "wof:name":"Mika Trans Gmbh",
    "wof:placetype":"venue"
},
  "geometry": {"coordinates":[8.854854,49.923775],"type":"Point"}
}