{
  "type": "Feature",
  "properties": {
    "iso:country":"DE",
    "sg:address":"Schneidm\u00fchlenweg 14",
    "sg:city":"Frankfurt",
    "sg:phone":"+49 69/30836723",
    "sg:postcode":"65929",
    "sg:province":"Hessen",
    "wof:name":"Radsportfans - Radtouristik Und Mountainbiking",
    "wof:placetype":"venue"
},
  "geometry": {"coordinates":[8.540901,50.109997],"type":"Point"}
}