{
  "type": "Feature",
  "properties": {
    "iso:country":"DE",
    "sg:address":"M\u00fchlenweg 35",
    "sg:city":"Elmlohe",
    "sg:phone":"+49 4704/524",
    "sg:postcode":"27624",
    "sg:province":"Niedersachsen",
    "wof:name":"Jugendhof Elmlohe Gmbh",
    "wof:placetype":"venue"
},
  "geometry": {"coordinates":[8.7557487488,53.5820274353],"type":"Point"}
}