{
  "type": "Feature",
  "properties": {
    "iso:country":"DE",
    "sg:address":"Erlenbachstr. 70",
    "sg:city":"Neupotz",
    "sg:postcode":"76777",
    "sg:province":"Rheinland-Pfalz",
    "wof:name":"Tbg Transportbeton- Beteiligungs-gmbh",
    "wof:placetype":"venue"
},
  "geometry": {"coordinates":[8.3262243271,49.1167755127],"type":"Point"}
}