{
  "type": "Feature",
  "properties": {
    "iso:country":"DE",
    "sg:address":"Dorfstr. 2",
    "sg:city":"Trebnitz",
    "sg:phone":"+49 3461/205512",
    "sg:postcode":"06217",
    "sg:province":"Sachsen-Anhalt",
    "wof:name":"Hiltraud Steinel",
    "wof:placetype":"venue"
},
  "geometry": {"coordinates":[12.061002,51.093281],"type":"Point"}
}