{
  "type": "Feature",
  "properties": {
    "iso:country":"DE",
    "sg:address":"Leisniger Str. 6",
    "sg:city":"Mutzschen",
    "sg:phone":"+49 34385/51364",
    "sg:postcode":"04688",
    "sg:province":"Sachsen",
    "wof:name":"J. Dietze",
    "wof:placetype":"venue"
},
  "geometry": {"coordinates":[12.8894548416,51.2551116943],"type":"Point"}
}