{
  "type": "Feature",
  "properties": {
    "iso:country":"DE",
    "sg:address":"Bahnhofstr. 33",
    "sg:city":"Oberhausen",
    "sg:phone":"+49 6755/94640",
    "sg:postcode":"55585",
    "sg:province":"Rheinland-Pfalz",
    "wof:name":"Artur Porr Fachgro\u00dfhandlung F. Kellereibedarf Kellereima.",
    "wof:placetype":"venue"
},
  "geometry": {"coordinates":[11.130911,47.776089],"type":"Point"}
}