{
  "type": "Feature",
  "properties": {
    "iso:country":"DE",
    "sg:address":"Wei\u00dfdornweg 69",
    "sg:city":"Bocholt",
    "sg:phone":"+49 2871/42215",
    "sg:postcode":"46395",
    "sg:province":"Nordrhein-Westfalen",
    "wof:name":"Schleinschock Gmbh",
    "wof:placetype":"venue"
},
  "geometry": {"coordinates":[6.58595,51.831539],"type":"Point"}
}