{
  "type": "Feature",
  "properties": {
    "iso:country":"DE",
    "sg:address":"Hauptstr. 28",
    "sg:city":"Selsingen",
    "sg:phone":"+49 4284/8420",
    "sg:postcode":"27446",
    "sg:province":"Niedersachsen",
    "wof:name":"Hans Gilbert",
    "wof:placetype":"venue"
},
  "geometry": {"coordinates":[9.214655,53.370644],"type":"Point"}
}