{
  "type": "Feature",
  "properties": {
    "iso:country":"DE",
    "sg:address":"Augsburger Str 46G/70",
    "sg:city":"Burgau",
    "sg:phone":"+49 8222/8252",
    "sg:postcode":"89331",
    "sg:province":"Bayern",
    "wof:name":"Traum-geschenke",
    "wof:placetype":"venue"
},
  "geometry": {"coordinates":[10.4169187546,48.4252738953],"type":"Point"}
}