{
  "type": "Feature",
  "properties": {
    "iso:country":"DE",
    "sg:address":"Gneisenaustr. 6",
    "sg:city":"Leverkusen",
    "sg:phone":"+49 214/75329",
    "sg:postcode":"51377",
    "sg:province":"Nordrhein-Westfalen",
    "wof:name":"W. Meurergmbh",
    "wof:placetype":"venue"
},
  "geometry": {"coordinates":[7.024494,51.033413],"type":"Point"}
}