{
  "type": "Feature",
  "properties": {
    "iso:country":"DE",
    "sg:address":"Rathausstr. 10",
    "sg:city":"Goslar",
    "sg:phone":"+49 5325/3375",
    "sg:postcode":"38644",
    "sg:province":"Niedersachsen",
    "wof:name":"A. Wagner-oels",
    "wof:placetype":"venue"
},
  "geometry": {"coordinates":[10.3407688141,51.8598747253],"type":"Point"}
}