{
  "type": "Feature",
  "properties": {
    "iso:country":"DE",
    "sg:address":"Porschestr. 56",
    "sg:city":"Wolfsburg",
    "sg:phone":"+49 5361/293257",
    "sg:postcode":"38440",
    "sg:province":"Niedersachsen",
    "wof:name":"Orsay Gmbh",
    "wof:placetype":"venue"
},
  "geometry": {"coordinates":[10.787173,52.422997],"type":"Point"}
}