{
  "type": "Feature",
  "properties": {
    "iso:country":"DE",
    "sg:address":"Ludwigseck 11",
    "sg:city":"Neunkirchen",
    "sg:phone":"+49 2735/2996",
    "sg:postcode":"57290",
    "sg:province":"Nordrhein-Westfalen",
    "wof:name":"Hotel Freiengrunder Hof",
    "wof:placetype":"venue"
},
  "geometry": {"coordinates":[8.0318050385,50.7942695618],"type":"Point"}
}