{
  "type": "Feature",
  "properties": {
    "iso:country":"DE",
    "sg:address":"Dorfstr. 2",
    "sg:city":"Sylt-Ost",
    "sg:postcode":"25980",
    "sg:province":"Schleswig-Holstein",
    "wof:name":"A. P\u00f6pping",
    "wof:placetype":"venue"
},
  "geometry": {"coordinates":[8.3935699463,54.873336792],"type":"Point"}
}