{
  "type": "Feature",
  "properties": {
    "iso:country":"DE",
    "sg:address":"Dulkweg 11",
    "sg:city":"Esslingen",
    "sg:phone":"+49 711/3702754",
    "sg:postcode":"73732",
    "sg:province":"Baden-W\u00fcrttemberg",
    "wof:name":"Ziltz Und Partner Architekten",
    "wof:placetype":"venue"
},
  "geometry": {"coordinates":[9.332423,48.755974],"type":"Point"}
}