{
  "type": "Feature",
  "properties": {
    "iso:country":"DE",
    "sg:address":"Dorfstr. 30",
    "sg:city":"Windach",
    "sg:phone":"+49 8806/636",
    "sg:postcode":"86949",
    "sg:province":"Bayern",
    "wof:name":"Alfons Graf",
    "wof:placetype":"venue"
},
  "geometry": {"coordinates":[11.061268,48.05043],"type":"Point"}
}