{
  "type": "Feature",
  "properties": {
    "iso:country":"DE",
    "sg:address":"Flurstr 14",
    "sg:city":"Oerlinghausen",
    "sg:phone":"+49 5202/158948",
    "sg:postcode":"33813",
    "sg:province":"Nordrhein-Westfalen",
    "wof:name":"Kerakisch",
    "wof:placetype":"venue"
},
  "geometry": {"coordinates":[8.715988,51.980438],"type":"Point"}
}