{
  "type": "Feature",
  "properties": {
    "iso:country":"DE",
    "sg:address":"Babenhauserstr.7",
    "sg:city":"Winterrieden",
    "sg:phone":"+49 8333",
    "sg:postcode":"87785",
    "sg:province":"Bayern",
    "wof:name":"Kaleidoskope",
    "wof:placetype":"venue"
},
  "geometry": {"coordinates":[10.225046,48.122341],"type":"Point"}
}