{
  "type": "Feature",
  "properties": {
    "iso:country":"DE",
    "sg:address":"Rathenower Str. 29",
    "sg:city":"Stendal",
    "sg:phone":"+49 3931/669380",
    "sg:postcode":"39576",
    "sg:province":"Sachsen-Anhalt",
    "wof:name":"Wilke & Seela Planende Ingenieure",
    "wof:placetype":"venue"
},
  "geometry": {"coordinates":[11.866113,52.60387],"type":"Point"}
}