{
  "type": "Feature",
  "properties": {
    "iso:country":"DE",
    "sg:address":"Am Brink 3",
    "sg:city":"Kankelau",
    "sg:phone":"+49 4156/564",
    "sg:postcode":"21514",
    "sg:province":"Schleswig-Holstein",
    "wof:name":"Hans O. H\u00fcmpel",
    "wof:placetype":"venue"
},
  "geometry": {"coordinates":[10.568314,53.549812],"type":"Point"}
}