{
  "type": "Feature",
  "properties": {
    "iso:country":"DE",
    "sg:address":"Am Birkenhain 2",
    "sg:city":"Gro\u00dfenkneten",
    "sg:phone":"+49 4487/671",
    "sg:postcode":"26197",
    "sg:province":"Niedersachsen",
    "wof:name":"Hvs Hausmann Gmbh",
    "wof:placetype":"venue"
},
  "geometry": {"coordinates":[8.224663,52.962269],"type":"Point"}
}