{
  "type": "Feature",
  "properties": {
    "iso:country":"DE",
    "sg:address":"Heinrichstr. 2",
    "sg:city":"Bamberg",
    "sg:phone":"+49 951/982600",
    "sg:postcode":"96047",
    "sg:province":"Bayern",
    "wof:name":"Babenberg-apotheke",
    "wof:placetype":"venue"
},
  "geometry": {"coordinates":[10.891805,49.894939],"type":"Point"}
}