{
  "type": "Feature",
  "properties": {
    "iso:country":"DE",
    "sg:address":"Am Obertunk 65",
    "sg:city":"Arnstadt",
    "sg:phone":"+49 3628/603114",
    "sg:postcode":"99310",
    "sg:province":"Th\u00fcringen",
    "wof:name":"Restaurant Deja-vu",
    "wof:placetype":"venue"
},
  "geometry": {"coordinates":[10.960943222,50.8423423767],"type":"Point"}
}