{
  "type": "Feature",
  "properties": {
    "iso:country":"DE",
    "sg:address":"Herrengasse 1",
    "sg:city":"Wasserburg",
    "sg:phone":"+49 8071/50291",
    "sg:postcode":"83512",
    "sg:province":"Bayern",
    "wof:name":"Restaurant Weisses R\u00f6ssl",
    "wof:placetype":"venue"
},
  "geometry": {"coordinates":[12.2315778732,48.061050415],"type":"Point"}
}