{
  "type": "Feature",
  "properties": {
    "iso:country":"DE",
    "sg:address":"Hauptstr. 2",
    "sg:city":"Kordel",
    "sg:phone":"+49 6505/777",
    "sg:postcode":"54306",
    "sg:province":"Rheinland-Pfalz",
    "wof:name":"B\u00e4ren-apotheke",
    "wof:placetype":"venue"
},
  "geometry": {"coordinates":[6.633417,49.839684],"type":"Point"}
}