{
  "type": "Feature",
  "properties": {
    "iso:country":"DE",
    "sg:address":"Goethestr. 3",
    "sg:city":"Albstadt",
    "sg:phone":"+49 7432/12483",
    "sg:postcode":"72461",
    "sg:province":"Baden-W\u00fcrttemberg",
    "wof:name":"Orient",
    "wof:placetype":"venue"
},
  "geometry": {"coordinates":[9.0181646347,48.25415802],"type":"Point"}
}