{
  "type": "Feature",
  "properties": {
    "iso:country":"DE",
    "sg:address":"Emil-Hoffmann-Str 12-16",
    "sg:city":"K\u00f6ln",
    "sg:phone":"+49 2236/39180",
    "sg:postcode":"50996",
    "sg:province":"Nordrhein-Westfalen",
    "wof:name":"Kube & Kubenz Intern. Spedition Gesellschaft Ek",
    "wof:placetype":"venue"
},
  "geometry": {"coordinates":[6.9951648712,50.8929252625],"type":"Point"}
}