{
  "type": "Feature",
  "properties": {
    "iso:country":"DE",
    "sg:address":"M\u00fchlstr. 18",
    "sg:city":"Guntersblum",
    "sg:phone":"+49 6249/7746",
    "sg:postcode":"67583",
    "sg:province":"Rheinland-Pfalz",
    "wof:name":"Rudolf M\u00f6lbert",
    "wof:placetype":"venue"
},
  "geometry": {"coordinates":[8.3468952179,49.7937316895],"type":"Point"}
}