{
  "type": "Feature",
  "properties": {
    "iso:country":"DE",
    "sg:address":"Loher Busch 54",
    "sg:city":"Bad Oeynhausen",
    "sg:phone":"+49 5731/91805",
    "sg:postcode":"32545",
    "sg:province":"Nordrhein-Westfalen",
    "wof:name":"Walter Mooshage",
    "wof:placetype":"venue"
},
  "geometry": {"coordinates":[8.8129253387,52.1795501709],"type":"Point"}
}