{
  "type": "Feature",
  "properties": {
    "iso:country":"DE",
    "sg:address":"An der Kaapd\u00fcne",
    "sg:city":"Langeoog",
    "sg:phone":"+49 4972/279",
    "sg:postcode":"26465",
    "sg:province":"Niedersachsen",
    "wof:name":"G\u00e4stehaus R. Plaisier",
    "wof:placetype":"venue"
},
  "geometry": {"coordinates":[7.4769978523,53.7468605042],"type":"Point"}
}