{
  "type": "Feature",
  "properties": {
    "iso:country":"DE",
    "sg:address":"Unterlandstr. 35",
    "sg:city":"Klingenberg",
    "sg:phone":"+49 9372/1610",
    "sg:postcode":"63911",
    "sg:province":"Bayern",
    "wof:name":"Edel",
    "wof:placetype":"venue"
},
  "geometry": {"coordinates":[9.183778,49.767673],"type":"Point"}
}