{
  "type": "Feature",
  "properties": {
    "iso:country":"DE",
    "sg:address":"Schwarzwaldstr. 9",
    "sg:city":"Stockstadt",
    "sg:phone":"+49 6027/1255",
    "sg:postcode":"63811",
    "sg:province":"Bayern",
    "wof:name":"Upic Universal Peripherals Intern. In Central Europe Gmbh",
    "wof:placetype":"venue"
},
  "geometry": {"coordinates":[9.0774774551,49.9678230286],"type":"Point"}
}