{
  "type": "Feature",
  "properties": {
    "iso:country":"DE",
    "sg:address":"Regelland 12",
    "sg:city":"Olsberg",
    "sg:phone":"+49 2985/8168",
    "sg:postcode":"59939",
    "sg:province":"Nordrhein-Westfalen",
    "wof:name":"Ulrich Lorenz",
    "wof:placetype":"venue"
},
  "geometry": {"coordinates":[8.5030708313,51.286945343],"type":"Point"}
}