{
  "type": "Feature",
  "properties": {
    "iso:country":"DE",
    "sg:address":"Martin-Luther-Str. 97",
    "sg:city":"Berlin",
    "sg:phone":"+49 30/7816333",
    "sg:postcode":"10825",
    "sg:province":"Berlin",
    "wof:name":"China-restaurant Eurasia",
    "wof:placetype":"venue"
},
  "geometry": {"coordinates":[13.3453788757,52.4857940674],"type":"Point"}
}