{
  "type": "Feature",
  "properties": {
    "iso:country":"DE",
    "sg:address":"Gorkistr. 12",
    "sg:city":"Berlin",
    "sg:postcode":"13507",
    "sg:province":"Berlin",
    "wof:name":"Aldi Gmbh & Co. Kg",
    "wof:placetype":"venue"
},
  "geometry": {"coordinates":[13.2853317261,52.5897712708],"type":"Point"}
}