{
  "type": "Feature",
  "properties": {
    "iso:country":"DE",
    "sg:address":"Goldberger Str. 700",
    "sg:city":"G\u00fcstrow",
    "sg:postcode":"18273",
    "sg:province":"Mecklenburg-Vorpommern",
    "wof:name":"Wohnpark Am Stadtgarten Verwaltungs- Gmbh",
    "wof:placetype":"venue"
},
  "geometry": {"coordinates":[12.1758308411,53.7805137634],"type":"Point"}
}