{
  "type": "Feature",
  "properties": {
    "iso:country":"DE",
    "sg:address":"Hauptstr. 85",
    "sg:city":"Heidelberg",
    "sg:phone":"+49 6221/141190",
    "sg:postcode":"69117",
    "sg:province":"Baden-W\u00fcrttemberg",
    "wof:name":"Bredl & Co. Gmbh",
    "wof:placetype":"venue"
},
  "geometry": {"coordinates":[8.7019681931,49.4112625122],"type":"Point"}
}