{
  "type": "Feature",
  "properties": {
    "iso:country":"DE",
    "sg:address":"Allersberger Str. 34",
    "sg:city":"N\u00fcrnberg",
    "sg:phone":"+49 911/94440",
    "sg:postcode":"90461",
    "sg:province":"Bayern",
    "wof:name":"Amas Hotel Gmbh",
    "wof:placetype":"venue"
},
  "geometry": {"coordinates":[11.086265564,49.4437255859],"type":"Point"}
}