{
  "type": "Feature",
  "properties": {
    "iso:country":"DE",
    "sg:address":"Heerstr. 16",
    "sg:city":"Berlin",
    "sg:phone":"+49 30/30062110",
    "sg:postcode":"14052",
    "sg:province":"Berlin",
    "wof:name":"World Trade Center Berlin Gmbh",
    "wof:placetype":"venue"
},
  "geometry": {"coordinates":[13.266826,52.509354],"type":"Point"}
}