{
  "type": "Feature",
  "properties": {
    "iso:country":"DE",
    "sg:address":"Herbst\u00e4dter Str. 23",
    "sg:city":"Bad K\u00f6nigshofen",
    "sg:phone":"+49 9761/2542",
    "sg:postcode":"97631",
    "sg:province":"Bayern",
    "wof:name":"Helga Blendinger Heilpraktikerin",
    "wof:placetype":"venue"
},
  "geometry": {"coordinates":[10.4676599503,50.2993202209],"type":"Point"}
}