{
  "type": "Feature",
  "properties": {
    "iso:country":"DE",
    "sg:address":"Hauptstr. 5",
    "sg:city":"Herborn",
    "sg:phone":"+49 2772/42635",
    "sg:postcode":"35745",
    "sg:province":"Hessen",
    "wof:name":"Burger Eck",
    "wof:placetype":"venue"
},
  "geometry": {"coordinates":[8.3028993607,50.6842880249],"type":"Point"}
}