{
  "type": "Feature",
  "properties": {
    "iso:country":"DE",
    "sg:address":"Kronenstr. 11",
    "sg:city":"T\u00fcbingen",
    "sg:phone":"+49 7071/22160",
    "sg:postcode":"72070",
    "sg:province":"Baden-W\u00fcrttemberg",
    "wof:name":"Pfuderer Cafe",
    "wof:placetype":"venue"
},
  "geometry": {"coordinates":[9.054172,48.520233],"type":"Point"}
}