{
  "type": "Feature",
  "properties": {
    "iso:country":"DE",
    "sg:address":"Koppenplatz 5",
    "sg:city":"Zirndorf",
    "sg:phone":"+49 911/604347",
    "sg:postcode":"90513",
    "sg:province":"Bayern",
    "wof:name":"Bayerische Vereinsbank Ag",
    "wof:placetype":"venue"
},
  "geometry": {"coordinates":[10.956342,49.44199],"type":"Point"}
}