{
  "type": "Feature",
  "properties": {
    "iso:country":"DE",
    "sg:address":"Raiffeisenstr. 2",
    "sg:city":"Siegsdorf",
    "sg:phone":"+49 8662/7976",
    "sg:postcode":"83313",
    "sg:province":"Bayern",
    "wof:name":"Volksbank Siegsdorf Eg",
    "wof:placetype":"venue"
},
  "geometry": {"coordinates":[12.646194,47.82235],"type":"Point"}
}