{
  "type": "Feature",
  "properties": {
    "iso:country":"DE",
    "sg:address":"Amselstr. 1",
    "sg:city":"Sch\u00f6nwald",
    "sg:phone":"+49 7722/3742",
    "sg:postcode":"78141",
    "sg:province":"Baden-W\u00fcrttemberg",
    "wof:name":"Rudolf Schwer",
    "wof:placetype":"venue"
},
  "geometry": {"coordinates":[13.1358346939,52.6005973816],"type":"Point"}
}