{
  "type": "Feature",
  "properties": {
    "iso:country":"DE",
    "sg:address":"Gschwenderstr. 11",
    "sg:city":"Marktoberdorf",
    "sg:phone":"+49 8342/5547",
    "sg:postcode":"87616",
    "sg:province":"Bayern",
    "wof:name":"Oldtimer",
    "wof:placetype":"venue"
},
  "geometry": {"coordinates":[10.616173,47.779877],"type":"Point"}
}