{
  "type": "Feature",
  "properties": {
    "iso:country":"DE",
    "sg:address":"Barthstr. 1",
    "sg:city":"Lauf",
    "sg:phone":"+49 9123/75911",
    "sg:postcode":"91207",
    "sg:province":"Bayern",
    "wof:name":"Elfi Schwartz Masseurin",
    "wof:placetype":"venue"
},
  "geometry": {"coordinates":[11.282382,49.512177],"type":"Point"}
}