{
  "type": "Feature",
  "properties": {
    "iso:country":"DE",
    "sg:address":"Hauptstr. 23",
    "sg:city":"Iphofen",
    "sg:phone":"+49 9326/99960",
    "sg:postcode":"97346",
    "sg:province":"Bayern",
    "wof:name":"Hartmut Schmieg",
    "wof:placetype":"venue"
},
  "geometry": {"coordinates":[10.3268651962,49.6682739258],"type":"Point"}
}