{
  "type": "Feature",
  "properties": {
    "iso:country":"DE",
    "sg:address":"Schillerstr. 34",
    "sg:city":"M\u00fcnchen",
    "sg:phone":"+49 89/554243",
    "sg:postcode":"80336",
    "sg:province":"Bayern",
    "wof:name":"Hartnagel Gmbh",
    "wof:placetype":"venue"
},
  "geometry": {"coordinates":[11.5606689453,48.1358261108],"type":"Point"}
}