{
  "type": "Feature",
  "properties": {
    "iso:country":"DE",
    "sg:address":"Hauptstr. 2",
    "sg:city":"Osdorf",
    "sg:phone":"+49 4346/4340",
    "sg:postcode":"24251",
    "sg:province":"Schleswig-Holstein",
    "wof:name":"Helmut Siemsen",
    "wof:placetype":"venue"
},
  "geometry": {"coordinates":[10.015332222,54.4275131226],"type":"Point"}
}