{
  "type": "Feature",
  "properties": {
    "iso:country":"DE",
    "sg:address":"Im Seifen 9",
    "sg:city":"Weilrod",
    "sg:phone":"+49 6083/2050",
    "sg:postcode":"61276",
    "sg:province":"Hessen",
    "wof:name":"Dietrich Schmidt Ingenieur",
    "wof:placetype":"venue"
},
  "geometry": {"coordinates":[8.3775930405,50.3374290466],"type":"Point"}
}