{
  "type": "Feature",
  "properties": {
    "iso:country":"DE",
    "sg:address":"Birkenstr. 17",
    "sg:city":"Kitzingen",
    "sg:phone":"+49 9321/31067",
    "sg:postcode":"97318",
    "sg:province":"Bayern",
    "wof:name":"Witt Pflegeheim",
    "wof:placetype":"venue"
},
  "geometry": {"coordinates":[10.179506,49.720001],"type":"Point"}
}