{
  "type": "Feature",
  "properties": {
    "iso:country":"DE",
    "sg:address":"Christophstr. 16-20",
    "sg:city":"Metzingen",
    "sg:phone":"+49 7123/92980",
    "sg:postcode":"72555",
    "sg:province":"Baden-W\u00fcrttemberg",
    "wof:name":"Gro\u00df Und Partner Gmbh",
    "wof:placetype":"venue"
},
  "geometry": {"coordinates":[9.2871017456,48.5405540466],"type":"Point"}
}