{
  "type": "Feature",
  "properties": {
    "iso:country":"DE",
    "sg:address":"Kaiserstr. 16",
    "sg:city":"Saarbr\u00fccken",
    "sg:phone":"+49 681/35940",
    "sg:postcode":"66111",
    "sg:province":"Saarland",
    "wof:name":"Hammer & Payr Gmbh",
    "wof:placetype":"venue"
},
  "geometry": {"coordinates":[6.9945268631,49.237071991],"type":"Point"}
}