{
  "type": "Feature",
  "properties": {
    "iso:country":"DE",
    "sg:address":"Arrild 22",
    "sg:city":"Oersberg",
    "sg:phone":"+49 4642/3594",
    "sg:postcode":"24407",
    "sg:province":"Schleswig-Holstein",
    "wof:name":"Johannes Nissen",
    "wof:placetype":"venue"
},
  "geometry": {"coordinates":[9.82761,54.682556],"type":"Point"}
}