{
  "type": "Feature",
  "properties": {
    "iso:country":"DE",
    "sg:address":"Gartenstr 6a",
    "sg:city":"G\u00fctersloh",
    "sg:phone":"+49 5241/98780",
    "sg:postcode":"33332",
    "sg:province":"Nordrhein-Westfalen",
    "wof:name":"Diestelkamp K\u00e4lte - Klima Gmbh",
    "wof:placetype":"venue"
},
  "geometry": {"coordinates":[8.390523,51.906002],"type":"Point"}
}