{
  "type": "Feature",
  "properties": {
    "iso:country":"DE",
    "sg:address":"Hanns-Eisler-Str. 10",
    "sg:city":"Berlin",
    "sg:phone":"+49 30/4236247",
    "sg:postcode":"10409",
    "sg:province":"Berlin",
    "wof:name":"Tapetenhaus Fr\u00f6hlich J\u00fcrgen Berndt E. K.",
    "wof:placetype":"venue"
},
  "geometry": {"coordinates":[13.4434070587,52.5439186096],"type":"Point"}
}