{
  "type": "Feature",
  "properties": {
    "iso:country":"DE",
    "sg:address":"Hauptstr. 34",
    "sg:city":"Efringen-Kirchen",
    "sg:phone":"+49 7628/2005",
    "sg:postcode":"79588",
    "sg:province":"Baden-W\u00fcrttemberg",
    "wof:name":"Etis-etiketten- Etikettiersysteme Gmbh",
    "wof:placetype":"venue"
},
  "geometry": {"coordinates":[7.5654439926,47.6506576538],"type":"Point"}
}