{
  "type": "Feature",
  "properties": {
    "iso:country":"DE",
    "sg:address":"Kreuzberger Str. 23",
    "sg:city":"Altenahr",
    "sg:phone":"+49 2643/8151",
    "sg:postcode":"53505",
    "sg:province":"Rheinland-Pfalz",
    "wof:name":"Seilbahn-gastst\u00e4tte",
    "wof:placetype":"venue"
},
  "geometry": {"coordinates":[6.9852170944,50.5109176636],"type":"Point"}
}