{
  "type": "Feature",
  "properties": {
    "iso:country":"DE",
    "sg:address":"Uhlenkruggarten 3",
    "sg:city":"Essen",
    "sg:phone":"+49 201/442731",
    "sg:postcode":"45133",
    "sg:province":"Nordrhein-Westfalen",
    "wof:name":"Juhr Mode Und Textil Gmbh",
    "wof:placetype":"venue"
},
  "geometry": {"coordinates":[7.0189428329,51.4257049561],"type":"Point"}
}