{
  "type": "Feature",
  "properties": {
    "iso:country":"DE",
    "sg:address":"Am Deepst\u00fcck 26 a",
    "sg:city":"Aurich",
    "sg:phone":"+49 4941/62412",
    "sg:postcode":"26605",
    "sg:province":"Niedersachsen",
    "wof:name":"Ostfriesische Jungs Musikproduktions Gmbh",
    "wof:placetype":"venue"
},
  "geometry": {"coordinates":[7.461370945,53.4598197937],"type":"Point"}
}