{
  "type": "Feature",
  "properties": {
    "iso:country":"DE",
    "sg:address":"Franz-B\u00f6res-Str. 4",
    "sg:city":"Seligenstadt",
    "sg:phone":"+49 6182/23924",
    "sg:postcode":"63500",
    "sg:province":"Hessen",
    "wof:name":"G. S\u00fc\u00dfmann",
    "wof:placetype":"venue"
},
  "geometry": {"coordinates":[8.9806175232,50.0406837463],"type":"Point"}
}