{
  "type": "Feature",
  "properties": {
    "iso:country":"DE",
    "sg:address":"Vogelsberg 21",
    "sg:city":"Hattingen",
    "sg:phone":"+49 2324/41011",
    "sg:postcode":"45529",
    "sg:province":"Nordrhein-Westfalen",
    "wof:name":"Heinz Kopot Architekt",
    "wof:placetype":"venue"
},
  "geometry": {"coordinates":[7.133338,51.388081],"type":"Point"}
}