{
  "type": "Feature",
  "properties": {
    "iso:country":"DE",
    "sg:address":"G\u00f6tzenhainer Str. 2",
    "sg:city":"Dietzenbach",
    "sg:phone":"+49 6074/3601",
    "sg:postcode":"63128",
    "sg:province":"Hessen",
    "wof:name":"H. Rettig",
    "wof:placetype":"venue"
},
  "geometry": {"coordinates":[8.774653,50.003918],"type":"Point"}
}