{
  "type": "Feature",
  "properties": {
    "iso:country":"DE",
    "sg:address":"Humboldtstr 4",
    "sg:city":"Bocholt",
    "sg:phone":"+49 2871/227147",
    "sg:postcode":"46397",
    "sg:province":"Nordrhein-Westfalen",
    "wof:name":"Blom Zahnr\u00e4der",
    "wof:placetype":"venue"
},
  "geometry": {"coordinates":[6.624406,51.847771],"type":"Point"}
}