{
  "type": "Feature",
  "properties": {
    "iso:country":"DE",
    "sg:address":"Ennemoserstr. 17",
    "sg:city":"Rottach-Egern",
    "sg:phone":"+49 8022/24272",
    "sg:postcode":"83700",
    "sg:province":"Bayern",
    "wof:name":"Kkw Steuerberatungsges. Mbh",
    "wof:placetype":"venue"
},
  "geometry": {"coordinates":[11.7776002884,47.6810646057],"type":"Point"}
}