{
  "type": "Feature",
  "properties": {
    "iso:country":"DE",
    "sg:address":"Am T\u00f6nniesberg 16-18",
    "sg:city":"Hannover",
    "sg:phone":"+49 511/432006",
    "sg:postcode":"30453",
    "sg:province":"Niedersachsen",
    "wof:name":"Morgenland Import-export Gastronomiebelieferung Gmbh",
    "wof:placetype":"venue"
},
  "geometry": {"coordinates":[9.703671,52.350983],"type":"Point"}
}