{
  "type": "Feature",
  "properties": {
    "iso:country":"DE",
    "sg:address":"Bahnhofstr. 19-21",
    "sg:city":"Sangerhausen",
    "sg:phone":"+49 3464/27280",
    "sg:postcode":"06526",
    "sg:province":"Sachsen-Anhalt",
    "wof:name":"Hanske Krebs Und Silz Rechtsanw\u00e4lte",
    "wof:placetype":"venue"
},
  "geometry": {"coordinates":[11.2966165543,51.4766464233],"type":"Point"}
}