{
  "type": "Feature",
  "properties": {
    "iso:country":"DE",
    "sg:address":"Wittekindstr. 16",
    "sg:city":"Osnabr\u00fcck",
    "sg:phone":"+49 541/21727",
    "sg:postcode":"49074",
    "sg:province":"Niedersachsen",
    "wof:name":"Wolfgang Gnirk",
    "wof:placetype":"venue"
},
  "geometry": {"coordinates":[8.0512180328,52.2753295898],"type":"Point"}
}