{
  "type": "Feature",
  "properties": {
    "iso:country":"DE",
    "sg:address":"Hinterheubach 3",
    "sg:city":"Heiligkreuzsteinach",
    "sg:phone":"+49 6220/911093",
    "sg:postcode":"69253",
    "sg:province":"Baden-W\u00fcrttemberg",
    "wof:name":"Druckerei Steinmann",
    "wof:placetype":"venue"
},
  "geometry": {"coordinates":[8.777112,49.485638],"type":"Point"}
}