{
  "type": "Feature",
  "properties": {
    "iso:country":"DE",
    "sg:address":"Zur Eiche 27",
    "sg:city":"K\u00f6ln",
    "sg:phone":"+49 2203/81587",
    "sg:postcode":"51143",
    "sg:province":"Nordrhein-Westfalen",
    "wof:name":"Oswald Werthwein Architekt",
    "wof:placetype":"venue"
},
  "geometry": {"coordinates":[7.008957,50.846127],"type":"Point"}
}