{
  "type": "Feature",
  "properties": {
    "iso:country":"DE",
    "sg:address":"Hauptstr. 39",
    "sg:city":"K\u00f6ln",
    "sg:phone":"+49 221/9502456",
    "sg:postcode":"50859",
    "sg:province":"Nordrhein-Westfalen",
    "wof:name":"Boni-dent-marketing Gmbh",
    "wof:placetype":"venue"
},
  "geometry": {"coordinates":[6.8270421028,50.9642829895],"type":"Point"}
}