{
  "type": "Feature",
  "properties": {
    "iso:country":"DE",
    "sg:address":"Krutscheider Weg 103",
    "sg:city":"Wuppertal",
    "sg:phone":"+49 202/646210",
    "sg:postcode":"42327",
    "sg:province":"Nordrhein-Westfalen",
    "wof:name":"Hans Schmitz Rechtsanwalt",
    "wof:placetype":"venue"
},
  "geometry": {"coordinates":[7.0607199669,51.2308807373],"type":"Point"}
}