{
  "type": "Feature",
  "properties": {
    "iso:country":"DE",
    "sg:address":"Saarstr. 15",
    "sg:city":"Morbach",
    "sg:phone":"+49 6533/4361",
    "sg:postcode":"54497",
    "sg:province":"Rheinland-Pfalz",
    "wof:name":"Gabriele Und Raimund Lengert",
    "wof:placetype":"venue"
},
  "geometry": {"coordinates":[7.1175870895,49.809753418],"type":"Point"}
}