{
  "type": "Feature",
  "properties": {
    "iso:country":"DE",
    "sg:address":"Am Sellhof 4",
    "sg:city":"S\u00f6hlde",
    "sg:phone":"+49 5129/1014",
    "sg:postcode":"31185",
    "sg:province":"Niedersachsen",
    "wof:name":"H. Himstedt Architekt",
    "wof:placetype":"venue"
},
  "geometry": {"coordinates":[10.227355,52.188225],"type":"Point"}
}