{
  "type": "Feature",
  "properties": {
    "iso:country":"DE",
    "sg:address":"Otto-Michael-Str.35",
    "sg:city":"Leipzig",
    "sg:phone":"+49 341",
    "sg:postcode":"04357",
    "sg:province":"Sachsen",
    "wof:name":"Internetpr\u00e4senz Mit Fa.ihm",
    "wof:placetype":"venue"
},
  "geometry": {"coordinates":[12.40456,51.37859],"type":"Point"}
}