{
  "type": "Feature",
  "properties": {
    "iso:country":"DE",
    "sg:address":"Bruckbauerstr. 24",
    "sg:city":"Pfarrkirchen",
    "sg:phone":"+49 8561/6201",
    "sg:postcode":"84347",
    "sg:province":"Bayern",
    "wof:name":"Manfred Siebrecht Ingenieurb\u00fcro",
    "wof:placetype":"venue"
},
  "geometry": {"coordinates":[12.9275960922,48.4320716858],"type":"Point"}
}