{
  "type": "Feature",
  "properties": {
    "iso:country":"DE",
    "sg:address":"Mendener Str. 10",
    "sg:city":"Arnsberg",
    "sg:phone":"+49 2932/7221",
    "sg:postcode":"59755",
    "sg:province":"Nordrhein-Westfalen",
    "wof:name":"Wvw Gmbh & Co. Kg",
    "wof:placetype":"venue"
},
  "geometry": {"coordinates":[7.9586000443,51.4543418884],"type":"Point"}
}