{
  "type": "Feature",
  "properties": {
    "iso:country":"DE",
    "sg:address":"Hufelandstr. 15",
    "sg:city":"Essen",
    "sg:phone":"+49 201/706021",
    "sg:postcode":"45147",
    "sg:province":"Nordrhein-Westfalen",
    "wof:name":"Friedrich H\u00fcbscher Ingenieur",
    "wof:placetype":"venue"
},
  "geometry": {"coordinates":[6.994207859,51.4364318848],"type":"Point"}
}