{
  "type": "Feature",
  "properties": {
    "iso:country":"DE",
    "sg:address":"M\u00fchldorfer Str. 17",
    "sg:city":"Schnaitsee",
    "sg:phone":"+49 8074/1287",
    "sg:postcode":"83530",
    "sg:province":"Bayern",
    "wof:name":"Johann Ameiser",
    "wof:placetype":"venue"
},
  "geometry": {"coordinates":[12.41357,48.109348],"type":"Point"}
}