{
  "type": "Feature",
  "properties": {
    "iso:country":"DE",
    "sg:address":"Am Westersielzug 8",
    "sg:city":"Friedrichstadt",
    "sg:phone":"+49 4881/7071",
    "sg:postcode":"25840",
    "sg:province":"Schleswig-Holstein",
    "wof:name":"G\u00e4stehaus Kleine Residenz",
    "wof:placetype":"venue"
},
  "geometry": {"coordinates":[9.0865783691,54.3779296875],"type":"Point"}
}