{
  "type": "Feature",
  "properties": {
    "iso:country":"DE",
    "sg:address":"Rembr\u00fccker Str. 15",
    "sg:city":"Heusenstamm",
    "sg:phone":"+49 4961/0469010",
    "sg:postcode":"63150",
    "sg:province":"Hessen",
    "wof:name":"Kenwood Electronics Deutschland Gmbh",
    "wof:placetype":"venue"
},
  "geometry": {"coordinates":[8.811991,50.059246],"type":"Point"}
}