{
  "type": "Feature",
  "properties": {
    "iso:country":"DE",
    "sg:address":"Schw\u00f6rstadt",
    "sg:city":"Schw\u00f6rstadt",
    "sg:phone":"+49 7762/8573",
    "sg:postcode":"79739",
    "sg:province":"Baden-W\u00fcrttemberg",
    "wof:name":"Sparkasse L\u00f6rrach-rheinfelden",
    "wof:placetype":"venue"
},
  "geometry": {"coordinates":[7.86655,47.609699],"type":"Point"}
}