{
  "type": "Feature",
  "properties": {
    "iso:country":"DE",
    "sg:address":"Heilbronner Str. 131",
    "sg:city":"Gundelsheim",
    "sg:phone":"+49 6269/8555",
    "sg:postcode":"74831",
    "sg:province":"Baden-W\u00fcrttemberg",
    "wof:name":"E. Degenhardt Steuerberater",
    "wof:placetype":"venue"
},
  "geometry": {"coordinates":[9.1601247787,49.2747802734],"type":"Point"}
}