{
  "type": "Feature",
  "properties": {
    "iso:country":"DE",
    "sg:address":"Graseggerstr. 105",
    "sg:city":"K\u00f6ln",
    "sg:phone":"+49 221/97451433",
    "sg:postcode":"50737",
    "sg:province":"Nordrhein-Westfalen",
    "wof:name":"Hotelvereinigung St. Marien Gmbh",
    "wof:placetype":"venue"
},
  "geometry": {"coordinates":[6.9239058495,50.99243927],"type":"Point"}
}