{
  "type": "Feature",
  "properties": {
    "iso:country":"DE",
    "sg:address":"Blumenstr. 8-10",
    "sg:city":"Deizisau",
    "sg:phone":"+49 7153/83460",
    "sg:postcode":"73779",
    "sg:province":"Baden-W\u00fcrttemberg",
    "wof:name":"Rmh R. M\u00fcller Holding Gmbh",
    "wof:placetype":"venue"
},
  "geometry": {"coordinates":[9.391453,48.71299],"type":"Point"}
}