{
  "type": "Feature",
  "properties": {
    "iso:country":"DE",
    "sg:address":"Walverdiek 10",
    "sg:city":"Minden",
    "sg:phone":"+49 571/9424510",
    "sg:postcode":"32425",
    "sg:province":"Nordrhein-Westfalen",
    "wof:name":"Gert Schmidt Anlageberater",
    "wof:placetype":"venue"
},
  "geometry": {"coordinates":[8.9155712128,52.3178749084],"type":"Point"}
}