{
  "type": "Feature",
  "properties": {
    "iso:country":"DE",
    "sg:address":"Stadtplatz 22",
    "sg:city":"Kemnath",
    "sg:phone":"+49 9642/406",
    "sg:postcode":"95478",
    "sg:province":"Bayern",
    "wof:name":"J. Bundscherer Elektro-install.",
    "wof:placetype":"venue"
},
  "geometry": {"coordinates":[11.888393,49.870415],"type":"Point"}
}