{
  "type": "Feature",
  "properties": {
    "iso:country":"DE",
    "sg:address":"Eupenerstra\u00dfe 161",
    "sg:city":"K\u00f6ln",
    "sg:phone":"+49 221",
    "sg:postcode":"50933",
    "sg:province":"Nordrhein-Westfalen",
    "wof:name":"Institut Prof. Dr. Kurz",
    "wof:placetype":"venue"
},
  "geometry": {"coordinates":[6.889611,50.946255],"type":"Point"}
}