{
  "type": "Feature",
  "properties": {
    "iso:country":"DE",
    "sg:address":"Bahnhofstr. 22",
    "sg:city":"Bismark",
    "sg:phone":"+49 39089/3632",
    "sg:postcode":"39629",
    "sg:province":"Sachsen-Anhalt",
    "wof:name":"Michael Reinsch",
    "wof:placetype":"venue"
},
  "geometry": {"coordinates":[11.5631465912,52.6629180908],"type":"Point"}
}