{
  "type": "Feature",
  "properties": {
    "iso:country":"DE",
    "sg:address":"Bahnhofstr. 40",
    "sg:city":"Ruhstorf",
    "sg:phone":"+49 8503/213",
    "sg:postcode":"94099",
    "sg:province":"Bayern",
    "wof:name":"Alfons Lockinger",
    "wof:placetype":"venue"
},
  "geometry": {"coordinates":[13.3810596466,48.4549407959],"type":"Point"}
}