{
  "type": "Feature",
  "properties": {
    "iso:country":"DE",
    "sg:address":"H\u00f6henweg 15",
    "sg:city":"Bergheim",
    "sg:phone":"+49 2238/41975",
    "sg:postcode":"50129",
    "sg:province":"Nordrhein-Westfalen",
    "wof:name":"Afriso Euro-index Gmbh",
    "wof:placetype":"venue"
},
  "geometry": {"coordinates":[6.750558,50.963482],"type":"Point"}
}