{
  "type": "Feature",
  "properties": {
    "iso:country":"DE",
    "sg:address":"Talbachstr. 5",
    "sg:city":"Bretten",
    "sg:phone":"+49 7252/3333",
    "sg:postcode":"75015",
    "sg:province":"Baden-W\u00fcrttemberg",
    "wof:name":"Franz R\u00f6der",
    "wof:placetype":"venue"
},
  "geometry": {"coordinates":[8.681638,49.069012],"type":"Point"}
}