{
  "type": "Feature",
  "properties": {
    "iso:country":"DE",
    "sg:address":"M\u00fchlstr. 2",
    "sg:city":"Reichenbach",
    "sg:postcode":"73262",
    "sg:province":"Baden-W\u00fcrttemberg",
    "wof:name":"J\u00fcrgen Harsch Transport- Und Reiseservice E. K.",
    "wof:placetype":"venue"
},
  "geometry": {"coordinates":[9.4636039734,48.713142395],"type":"Point"}
}