{
  "type": "Feature",
  "properties": {
    "iso:country":"DE",
    "sg:address":"Kaiserstr. 74",
    "sg:city":"Homburg",
    "sg:phone":"+49 6841/5054",
    "sg:postcode":"66424",
    "sg:province":"Saarland",
    "wof:name":"Manager Flugservice Gmbh",
    "wof:placetype":"venue"
},
  "geometry": {"coordinates":[7.332208,49.320522],"type":"Point"}
}