{
  "type": "Feature",
  "properties": {
    "iso:country":"DE",
    "sg:address":"Unterm Steinr\u00fccken",
    "sg:city":"Warstein",
    "sg:phone":"+49 2902/97530",
    "sg:postcode":"59581",
    "sg:province":"Nordrhein-Westfalen",
    "wof:name":"Wilhelm M\u00fcs Gmbh",
    "wof:placetype":"venue"
},
  "geometry": {"coordinates":[8.3702783585,51.4531288147],"type":"Point"}
}