{
  "type": "Feature",
  "properties": {
    "iso:country":"DE",
    "sg:address":"Ahornweg 11",
    "sg:city":"Beelen",
    "sg:phone":"+49 2586/8035",
    "sg:postcode":"48361",
    "sg:province":"Nordrhein-Westfalen",
    "wof:name":"Helmut Suer Steuerberater",
    "wof:placetype":"venue"
},
  "geometry": {"coordinates":[8.1246547699,51.9236793518],"type":"Point"}
}