{
  "type": "Feature",
  "properties": {
    "iso:country":"DE",
    "sg:address":"Fraaschweg 2",
    "sg:city":"Neetze",
    "sg:postcode":"21398",
    "sg:province":"Niedersachsen",
    "wof:name":"Betonwerk L\u00fcneburg Gmbh",
    "wof:placetype":"venue"
},
  "geometry": {"coordinates":[10.646332,53.296852],"type":"Point"}
}