{
  "type": "Feature",
  "properties": {
    "iso:country":"DE",
    "sg:address":"Ortelsburger Str. 36a",
    "sg:city":"Bochum",
    "sg:phone":"+49 234/294108",
    "sg:postcode":"44809",
    "sg:province":"Nordrhein-Westfalen",
    "wof:name":"Steakhaus El Gaucho",
    "wof:placetype":"venue"
},
  "geometry": {"coordinates":[7.1818699837,51.5038986206],"type":"Point"}
}