{
  "type": "Feature",
  "properties": {
    "iso:country":"DE",
    "sg:address":"Rosenbergstr. 85",
    "sg:city":"Stuttgart",
    "sg:phone":"+49 711/63570",
    "sg:postcode":"70193",
    "sg:province":"Baden-W\u00fcrttemberg",
    "wof:name":"Virotest Prof. Enders Gmbh",
    "wof:placetype":"venue"
},
  "geometry": {"coordinates":[9.1547193527,48.7779579163],"type":"Point"}
}