{
  "type": "Feature",
  "properties": {
    "iso:country":"DE",
    "sg:address":"An der Riehe 31",
    "sg:city":"Isernhagen",
    "sg:phone":"+49 511/612125",
    "sg:postcode":"30916",
    "sg:province":"Niedersachsen",
    "wof:name":"Apotheke An Der Riehe E. K.",
    "wof:placetype":"venue"
},
  "geometry": {"coordinates":[9.851433,52.434853],"type":"Point"}
}