{
  "type": "Feature",
  "properties": {
    "iso:country":"DE",
    "sg:address":"Sebaldstr. 9",
    "sg:city":"Schw\u00e4bisch Gm\u00fcnd",
    "sg:phone":"+49 7171/927800",
    "sg:postcode":"73525",
    "sg:province":"Baden-W\u00fcrttemberg",
    "wof:name":"Red. Mitt. D. Kolpingsf. Und Djk Sportgem. Schw. Gm\u00fcnd",
    "wof:placetype":"venue"
},
  "geometry": {"coordinates":[9.7985239029,48.7970314026],"type":"Point"}
}