{
  "type": "Feature",
  "properties": {
    "iso:country":"DE",
    "sg:address":"Grootestr. 88",
    "sg:city":"Bonn",
    "sg:phone":"+49 228/663845",
    "sg:postcode":"53121",
    "sg:province":"Nordrhein-Westfalen",
    "wof:name":"Reiner Wolter",
    "wof:placetype":"venue"
},
  "geometry": {"coordinates":[7.0405611992,50.7417297363],"type":"Point"}
}