{
  "type": "Feature",
  "properties": {
    "iso:country":"DE",
    "sg:address":"Im Seibig 11",
    "sg:city":"Angelburg",
    "sg:phone":"+49 6464/91710",
    "sg:postcode":"35719",
    "sg:province":"Hessen",
    "wof:name":"Schneider Maschinenservice Gmbh",
    "wof:placetype":"venue"
},
  "geometry": {"coordinates":[8.461999,50.831249],"type":"Point"}
}