{
  "type": "Feature",
  "properties": {
    "iso:country":"DE",
    "sg:address":"Bahnhofstr. 2",
    "sg:city":"Sulzberg",
    "sg:phone":"+49 8376/97320",
    "sg:postcode":"87477",
    "sg:province":"Bayern",
    "wof:name":"Schlo\u00df Apotheke Sulzberg E. K.",
    "wof:placetype":"venue"
},
  "geometry": {"coordinates":[10.349976,47.661297],"type":"Point"}
}