{
  "type": "Feature",
  "properties": {
    "iso:country":"DE",
    "sg:address":"Zollernstr. 23",
    "sg:city":"Rosenfeld",
    "sg:phone":"+49 7428/653",
    "sg:postcode":"72348",
    "sg:province":"Baden-W\u00fcrttemberg",
    "wof:name":"Georg G\u00fchring",
    "wof:placetype":"venue"
},
  "geometry": {"coordinates":[8.698905,48.294189],"type":"Point"}
}