{
  "type": "Feature",
  "properties": {
    "iso:country":"DE",
    "sg:address":"Rathausstr. 1a",
    "sg:city":"Wachtberg",
    "sg:phone":"+49 228/856084",
    "sg:postcode":"53343",
    "sg:province":"Nordrhein-Westfalen",
    "wof:name":"Hans-josef Ramershoven",
    "wof:placetype":"venue"
},
  "geometry": {"coordinates":[7.136103,50.625908],"type":"Point"}
}