{
  "type": "Feature",
  "properties": {
    "iso:country":"DE",
    "sg:address":"Feuerbachstr. 24",
    "sg:city":"Berlin",
    "sg:phone":"+49 30/7922373",
    "sg:postcode":"12163",
    "sg:province":"Berlin",
    "wof:name":"Restaurant Udagawa",
    "wof:placetype":"venue"
},
  "geometry": {"coordinates":[13.3301820755,52.4633407593],"type":"Point"}
}