{
  "type": "Feature",
  "properties": {
    "iso:country":"DE",
    "sg:address":"Breite Str. 14",
    "sg:city":"Hohenlockstedt",
    "sg:phone":"+49 4826/5447",
    "sg:postcode":"25551",
    "sg:province":"Schleswig-Holstein",
    "wof:name":"Provinzial Versicherung",
    "wof:placetype":"venue"
},
  "geometry": {"coordinates":[9.6182308197,53.9647407532],"type":"Point"}
}