{
  "type": "Feature",
  "properties": {
    "iso:country":"DE",
    "sg:address":"Lohrenkamp 30",
    "sg:city":"Bielefeld",
    "sg:phone":"+49 521/76011",
    "sg:postcode":"33729",
    "sg:province":"Nordrhein-Westfalen",
    "wof:name":"Hans-dieter Niehaus",
    "wof:placetype":"venue"
},
  "geometry": {"coordinates":[8.592979,52.074173],"type":"Point"}
}