{
  "type": "Feature",
  "properties": {
    "iso:country":"DE",
    "sg:address":"Schleptruper Strang 102",
    "sg:city":"Bramsche",
    "sg:phone":"+49 5468/334",
    "sg:postcode":"49565",
    "sg:province":"Niedersachsen",
    "wof:name":"Klaus Ri\u00dfling",
    "wof:placetype":"venue"
},
  "geometry": {"coordinates":[8.010896,52.386578],"type":"Point"}
}