{
  "type": "Feature",
  "properties": {
    "iso:country":"DE",
    "sg:address":"H\u00f6pfigheimer Str. 17",
    "sg:city":"Bietigheim-Bissingen",
    "sg:phone":"+49 7142/7050",
    "sg:postcode":"74321",
    "sg:province":"Baden-W\u00fcrttemberg",
    "wof:name":"D\u00fcrr-dental Gmbh & Co. Kg",
    "wof:placetype":"venue"
},
  "geometry": {"coordinates":[9.15831,48.953796],"type":"Point"}
}