{
  "type": "Feature",
  "properties": {
    "iso:country":"DE",
    "sg:address":"Dorfheide 8",
    "sg:city":"Bottrop",
    "sg:phone":"+49 2045/2286",
    "sg:postcode":"46244",
    "sg:province":"Nordrhein-Westfalen",
    "wof:name":"Kleine-wolters Verwaltungs Gmbh",
    "wof:placetype":"venue"
},
  "geometry": {"coordinates":[6.921994,51.59444],"type":"Point"}
}