{
  "type": "Feature",
  "properties": {
    "iso:country":"DE",
    "sg:address":"Birkengartenstr. 5",
    "sg:city":"Leverkusen",
    "sg:postcode":"51373",
    "sg:province":"Nordrhein-Westfalen",
    "wof:name":"Ganser Gmbh",
    "wof:placetype":"venue"
},
  "geometry": {"coordinates":[6.986664,51.028736],"type":"Point"}
}