{
  "type": "Feature",
  "properties": {
    "iso:country":"DE",
    "sg:address":"Hauptstr. 22",
    "sg:city":"Meinersen",
    "sg:phone":"+49 5372/1310",
    "sg:postcode":"38536",
    "sg:province":"Niedersachsen",
    "wof:name":"Quelle Dob-waren- Und Kaufhaus",
    "wof:placetype":"venue"
},
  "geometry": {"coordinates":[10.352125,52.474056],"type":"Point"}
}