{
  "type": "Feature",
  "properties": {
    "iso:country":"DE",
    "sg:address":"Mombachstr. 84",
    "sg:city":"Kassel",
    "sg:phone":"+49 561/807000",
    "sg:postcode":"34127",
    "sg:province":"Hessen",
    "wof:name":"Signet - Gesellschaft F\u00fcr Innovative Bildung Mbh",
    "wof:placetype":"venue"
},
  "geometry": {"coordinates":[9.4891119003,51.3241882324],"type":"Point"}
}