{
  "type": "Feature",
  "properties": {
    "iso:country":"DE",
    "sg:address":"Oldesloer Str. 8",
    "sg:city":"Hamburg",
    "sg:phone":"+49 40/5503180",
    "sg:postcode":"22457",
    "sg:province":"Hamburg",
    "wof:name":"H. Sichtau",
    "wof:placetype":"venue"
},
  "geometry": {"coordinates":[9.934465,53.646675],"type":"Point"}
}