{
  "type": "Feature",
  "properties": {
    "iso:country":"DE",
    "sg:address":"Rotb\u00fchlstr. 39",
    "sg:city":"Sindelfingen",
    "sg:phone":"+49 7031/806935",
    "sg:postcode":"71063",
    "sg:province":"Baden-W\u00fcrttemberg",
    "wof:name":"J. Burger Gmbh & Co. Kg",
    "wof:placetype":"venue"
},
  "geometry": {"coordinates":[9.0036039352,48.718547821],"type":"Point"}
}