{
  "type": "Feature",
  "properties": {
    "iso:country":"DE",
    "sg:address":"Fernrodder Str. 10",
    "sg:city":"Rheine",
    "sg:phone":"+49 5459/4157",
    "sg:postcode":"48432",
    "sg:province":"Nordrhein-Westfalen",
    "wof:name":"M. Gude",
    "wof:placetype":"venue"
},
  "geometry": {"coordinates":[7.5261888504,52.2805328369],"type":"Point"}
}