{
  "type": "Feature",
  "properties": {
    "iso:country":"DE",
    "sg:address":"Am Rindergraben 36 A",
    "sg:city":"Neuss",
    "sg:postcode":"41470",
    "sg:province":"Nordrhein-Westfalen",
    "wof:name":"Hit Electronics Gmbh",
    "wof:placetype":"venue"
},
  "geometry": {"coordinates":[6.7335648537,51.1230163574],"type":"Point"}
}