{
  "type": "Feature",
  "properties": {
    "iso:country":"DE",
    "sg:address":"Bremsen 6",
    "sg:city":"Leichlingen",
    "sg:phone":"+49 2175/898012",
    "sg:postcode":"42799",
    "sg:province":"Nordrhein-Westfalen",
    "wof:name":"Ohrgasmusik E. K.",
    "wof:placetype":"venue"
},
  "geometry": {"coordinates":[7.0004348755,51.1039657593],"type":"Point"}
}