{
  "type": "Feature",
  "properties": {
    "iso:country":"DE",
    "sg:address":"Eppendorfer Baum 44",
    "sg:city":"Hamburg",
    "sg:phone":"+49 40/4808794",
    "sg:postcode":"20249",
    "sg:province":"Hamburg",
    "wof:name":"R. Bl\u00f6dorn",
    "wof:placetype":"venue"
},
  "geometry": {"coordinates":[9.981847,53.585075],"type":"Point"}
}