{
  "type": "Feature",
  "properties": {
    "iso:country":"DE",
    "sg:address":"Friedrich-Lux-Str. 13",
    "sg:city":"Ruhla",
    "sg:phone":"+49 36929/88463",
    "sg:postcode":"99842",
    "sg:province":"Th\u00fcringen",
    "wof:name":"Hotel Liebergeld",
    "wof:placetype":"venue"
},
  "geometry": {"coordinates":[10.3829097748,50.8839797974],"type":"Point"}
}