{
  "type": "Feature",
  "properties": {
    "iso:country":"DE",
    "sg:address":"Oberl\u00e4nder Str. 33 1/2",
    "sg:city":"Augsburg",
    "sg:phone":"+49 821/62214",
    "sg:postcode":"86163",
    "sg:province":"Bayern",
    "wof:name":"Hermann Fiess",
    "wof:placetype":"venue"
},
  "geometry": {"coordinates":[10.94422,48.348709],"type":"Point"}
}