{
  "type": "Feature",
  "properties": {
    "iso:country":"DE",
    "sg:address":"Am M\u00fchlenwasser 5",
    "sg:city":"Geldern",
    "sg:phone":"+49 2838/2369",
    "sg:postcode":"47608",
    "sg:province":"Nordrhein-Westfalen",
    "wof:name":"Dr. Erich Stutzinger Tierarzt",
    "wof:placetype":"venue"
},
  "geometry": {"coordinates":[6.3594698906,51.5694999695],"type":"Point"}
}