{
  "type": "Feature",
  "properties": {
    "iso:country":"DE",
    "sg:address":"Lindenstr. 34",
    "sg:city":"H\u00fcfingen",
    "sg:phone":"+49 771/64406",
    "sg:postcode":"78183",
    "sg:province":"Baden-W\u00fcrttemberg",
    "wof:name":"V\u00f6gele",
    "wof:placetype":"venue"
},
  "geometry": {"coordinates":[8.49658,47.93232],"type":"Point"}
}