{
  "type": "Feature",
  "properties": {
    "iso:country":"DE",
    "sg:address":"Katternberger Str. 279",
    "sg:city":"Solingen",
    "sg:phone":"+49 5222/939830",
    "sg:postcode":"42655",
    "sg:province":"Nordrhein-Westfalen",
    "wof:name":"Procim Werkzeug & Vorrichtungsbau Gmbh",
    "wof:placetype":"venue"
},
  "geometry": {"coordinates":[8.733065,52.084934],"type":"Point"}
}