{
  "type": "Feature",
  "properties": {
    "iso:country":"DE",
    "sg:address":"Hauptstr. 143 A",
    "sg:city":"Dorfchemnitz",
    "sg:phone":"+49 4937/3208620",
    "sg:postcode":"09619",
    "sg:province":"Sachsen",
    "wof:name":"Beka Moebel Gmbh",
    "wof:placetype":"venue"
},
  "geometry": {"coordinates":[13.4465122223,50.7547531128],"type":"Point"}
}