{
  "type": "Feature",
  "properties": {
    "iso:country":"DE",
    "sg:address":"M\u00f6wenweg 2",
    "sg:city":"R\u00f6dermark",
    "sg:phone":"+49 6074/7570",
    "sg:postcode":"63322",
    "sg:province":"Hessen",
    "wof:name":"Gerlinde Krenzer Steuerberaterin",
    "wof:placetype":"venue"
},
  "geometry": {"coordinates":[8.7867927551,49.9698104858],"type":"Point"}
}