{
  "type": "Feature",
  "properties": {
    "iso:country":"DE",
    "sg:address":"Stettiner Str. 32",
    "sg:city":"Paderborn",
    "sg:phone":"+49 5251/760672",
    "sg:postcode":"33106",
    "sg:province":"Nordrhein-Westfalen",
    "wof:name":"Audentec Gesellschaft F\u00fcr Automatisierung Und",
    "wof:placetype":"venue"
},
  "geometry": {"coordinates":[8.7321405411,51.7011566162],"type":"Point"}
}