{
  "type": "Feature",
  "properties": {
    "iso:country":"DE",
    "sg:address":"Wilhelm-Busch-Weg 19",
    "sg:city":"Rohrsen",
    "sg:phone":"+49 5024/1403",
    "sg:postcode":"31627",
    "sg:province":"Niedersachsen",
    "wof:name":"Erwin Holtorf",
    "wof:placetype":"venue"
},
  "geometry": {"coordinates":[9.2463760376,52.7051925659],"type":"Point"}
}