{
  "type": "Feature",
  "properties": {
    "iso:country":"DE",
    "sg:address":"Bahnhofstr. 115",
    "sg:city":"Biesenthal",
    "sg:postcode":"16359",
    "sg:province":"Brandenburg",
    "wof:name":"Tele- Und Tiefbau Gmbh",
    "wof:placetype":"venue"
},
  "geometry": {"coordinates":[13.6633024216,52.7587089539],"type":"Point"}
}