{
  "type": "Feature",
  "properties": {
    "iso:country":"DE",
    "sg:address":"Buscher Str. 6",
    "sg:city":"H\u00fcckelhoven",
    "sg:phone":"+49 2433/51073",
    "sg:postcode":"41836",
    "sg:province":"Nordrhein-Westfalen",
    "wof:name":"Josef Tholen",
    "wof:placetype":"venue"
},
  "geometry": {"coordinates":[6.1899499893,51.0651130676],"type":"Point"}
}