{
  "type": "Feature",
  "properties": {
    "iso:country":"DE",
    "sg:address":"Gartenstr. 24",
    "sg:city":"Mittweida",
    "sg:phone":"+49 3727/94530",
    "sg:postcode":"09648",
    "sg:province":"Sachsen",
    "wof:name":"Hotel Eintracht Garni Inh. Thomas Fischer",
    "wof:placetype":"venue"
},
  "geometry": {"coordinates":[12.9847745895,50.9827232361],"type":"Point"}
}