{
  "type": "Feature",
  "properties": {
    "iso:country":"DE",
    "sg:address":"Rosenberger Str. 23",
    "sg:city":"Sulzbach-Rosenberg",
    "sg:phone":"+49 9661/52928",
    "sg:postcode":"92237",
    "sg:province":"Bayern",
    "wof:name":"K. Schwemmer",
    "wof:placetype":"venue"
},
  "geometry": {"coordinates":[11.742114,49.504311],"type":"Point"}
}