{
  "type": "Feature",
  "properties": {
    "iso:country":"DE",
    "sg:address":"Angersbacher Weg 5",
    "sg:city":"Bad Salzschlirf",
    "sg:phone":"+49 6648/5700",
    "sg:postcode":"36364",
    "sg:province":"Hessen",
    "wof:name":"Pension Sonnenblick",
    "wof:placetype":"venue"
},
  "geometry": {"coordinates":[9.4997377396,50.6284866333],"type":"Point"}
}