{
  "type": "Feature",
  "properties": {
    "iso:country":"DE",
    "sg:address":"Reuthweg 28",
    "sg:city":"Selb",
    "sg:phone":"+49 9287/890040",
    "sg:postcode":"95100",
    "sg:province":"Bayern",
    "wof:name":"Modellbahnwelt Selb Inh. Rainer Wie\u00dfner E. Kfm.",
    "wof:placetype":"venue"
},
  "geometry": {"coordinates":[12.1491479874,50.1881752014],"type":"Point"}
}