{
  "type": "Feature",
  "properties": {
    "iso:country":"DE",
    "sg:address":"Zeppelinstr. 13",
    "sg:city":"Bodelshausen",
    "sg:phone":"+49 7471/71796",
    "sg:postcode":"72411",
    "sg:province":"Baden-W\u00fcrttemberg",
    "wof:name":"Roland Nill",
    "wof:placetype":"venue"
},
  "geometry": {"coordinates":[8.9779119492,48.3868980408],"type":"Point"}
}