{
  "type": "Feature",
  "properties": {
    "iso:country":"DE",
    "sg:address":"Lange Str. 67",
    "sg:city":"Parchim",
    "sg:phone":"+49 3871/213355",
    "sg:postcode":"19370",
    "sg:province":"Mecklenburg-Vorpommern",
    "wof:name":"Matthias Koschitzki",
    "wof:placetype":"venue"
},
  "geometry": {"coordinates":[11.843001,53.427944],"type":"Point"}
}