{
  "type": "Feature",
  "properties": {
    "iso:country":"DE",
    "sg:address":"Sch\u00f6naicher Str. 5",
    "sg:city":"Holzgerlingen",
    "sg:phone":"+49 7031/604990",
    "sg:postcode":"71088",
    "sg:province":"Baden-W\u00fcrttemberg",
    "wof:name":"Video Treff R. J\u00e4hnert",
    "wof:placetype":"venue"
},
  "geometry": {"coordinates":[9.0151185989,48.6340179443],"type":"Point"}
}