{
  "type": "Feature",
  "properties": {
    "iso:country":"DE",
    "sg:address":"Riesengebirgstr. 1",
    "sg:city":"Neutraubling",
    "sg:phone":"+49 9401/2530",
    "sg:postcode":"93073",
    "sg:province":"Bayern",
    "wof:name":"Ilse Und Eckhard Klisch Massage- Und B\u00e4derpraxis",
    "wof:placetype":"venue"
},
  "geometry": {"coordinates":[12.200489,48.992702],"type":"Point"}
}