{
  "type": "Feature",
  "properties": {
    "iso:country":"DE",
    "sg:address":"Pienzenauerstr. 129",
    "sg:city":"M\u00fcnchen",
    "sg:phone":"+49 89/989012",
    "sg:postcode":"81925",
    "sg:province":"Bayern",
    "wof:name":"Iris Dahlmeier \u00dcbersetzerin U. Dolmetscherin",
    "wof:placetype":"venue"
},
  "geometry": {"coordinates":[11.616181,48.166576],"type":"Point"}
}