{
  "type": "Feature",
  "properties": {
    "iso:country":"DE",
    "sg:address":"Franz-Kleine-Str. 13",
    "sg:city":"Salzkotten",
    "sg:phone":"+49 5258/98520",
    "sg:postcode":"33154",
    "sg:province":"Nordrhein-Westfalen",
    "wof:name":"Data Techno Produktentwicklung Gmbh",
    "wof:placetype":"venue"
},
  "geometry": {"coordinates":[8.588251,51.672249],"type":"Point"}
}