{
  "type": "Feature",
  "properties": {
    "iso:country":"DE",
    "sg:address":"Ackerstr. 3",
    "sg:city":"Duisburg",
    "sg:phone":"+49 2841/80376",
    "sg:postcode":"47199",
    "sg:province":"Nordrhein-Westfalen",
    "wof:name":"G\u00fcnter Stepken",
    "wof:placetype":"venue"
},
  "geometry": {"coordinates":[6.6719088554,51.4961547852],"type":"Point"}
}