{
  "type": "Feature",
  "properties": {
    "iso:country":"DE",
    "sg:address":"Helmkestr. 14",
    "sg:city":"Hannover",
    "sg:phone":"+49 511/3521966",
    "sg:postcode":"30165",
    "sg:province":"Niedersachsen",
    "wof:name":"O. Schmitt",
    "wof:placetype":"venue"
},
  "geometry": {"coordinates":[9.7111682892,52.4003448486],"type":"Point"}
}