{
  "type": "Feature",
  "properties": {
    "iso:country":"DE",
    "sg:address":"Zeppelinstr 7",
    "sg:city":"Karlsruhe",
    "sg:phone":"+49 721/842370",
    "sg:postcode":"76185",
    "sg:province":"Baden-W\u00fcrttemberg",
    "wof:name":"Werner Wie\u00dfner Gmbh & Co Kg",
    "wof:placetype":"venue"
},
  "geometry": {"coordinates":[8.3652219772,49.0026245117],"type":"Point"}
}