{
  "type": "Feature",
  "properties": {
    "iso:country":"DE",
    "sg:address":"Taubenstr. 5",
    "sg:city":"Remscheid",
    "sg:phone":"+49 2191/8618",
    "sg:postcode":"42857",
    "sg:province":"Nordrhein-Westfalen",
    "wof:name":"Richard Vom Hoff Kg",
    "wof:placetype":"venue"
},
  "geometry": {"coordinates":[7.1640768051,51.1893882751],"type":"Point"}
}