{
  "type": "Feature",
  "properties": {
    "iso:country":"DE",
    "sg:address":"Rathausstr. 4",
    "sg:city":"W\u00f6rth",
    "sg:phone":"+49 9372/5931",
    "sg:postcode":"63939",
    "sg:province":"Bayern",
    "wof:name":"Parthenon",
    "wof:placetype":"venue"
},
  "geometry": {"coordinates":[9.15625,49.7986488342],"type":"Point"}
}