{
  "type": "Feature",
  "properties": {
    "iso:country":"DE",
    "sg:address":"M\u00fchlstr. 68",
    "sg:city":"Gladenbach",
    "sg:phone":"+49 6462/1074",
    "sg:postcode":"35075",
    "sg:province":"Hessen",
    "wof:name":"Kurt Und Joachim Haus",
    "wof:placetype":"venue"
},
  "geometry": {"coordinates":[8.5310096741,50.7520256042],"type":"Point"}
}