{
  "type": "Feature",
  "properties": {
    "iso:country":"DE",
    "sg:address":"Hauptstr. 149",
    "sg:city":"Wiesloch",
    "sg:phone":"+49 6222/2638",
    "sg:postcode":"69168",
    "sg:province":"Baden-W\u00fcrttemberg",
    "wof:name":"Allianz Gamperling & Partner Ohg",
    "wof:placetype":"venue"
},
  "geometry": {"coordinates":[8.6964941025,49.2896118164],"type":"Point"}
}