{
  "type": "Feature",
  "properties": {
    "iso:country":"DE",
    "sg:address":"Funnixer Riege 1",
    "sg:city":"Wittmund",
    "sg:phone":"+49 4467/222",
    "sg:postcode":"26409",
    "sg:province":"Niedersachsen",
    "wof:name":"Detlef Theede Landtechnisches Lohnunternehmen",
    "wof:placetype":"venue"
},
  "geometry": {"coordinates":[7.789898,53.646416],"type":"Point"}
}