{
  "type": "Feature",
  "properties": {
    "iso:country":"DE",
    "sg:address":"71083",
    "sg:city":"Herrenberg",
    "sg:phone":"+49 7032/22234",
    "sg:postcode":"71083",
    "sg:province":"Baden-W\u00fcrttemberg",
    "wof:name":"Gastst\u00e4tte Stadthalle",
    "wof:placetype":"venue"
},
  "geometry": {"coordinates":[8.884519577,48.5997810364],"type":"Point"}
}