{
  "type": "Feature",
  "properties": {
    "iso:country":"DE",
    "sg:address":"Schwedendamm 16",
    "sg:city":"Kiel",
    "sg:postcode":"24143",
    "sg:province":"Schleswig-Holstein",
    "wof:name":"Immo Fenster Und Bauelemente Gmbh",
    "wof:placetype":"venue"
},
  "geometry": {"coordinates":[10.1363506317,54.3067016602],"type":"Point"}
}