{
  "type": "Feature",
  "properties": {
    "iso:country":"DE",
    "sg:address":"Illersiedlung 34",
    "sg:city":"Sonthofen",
    "sg:phone":"+49 8321/4541",
    "sg:postcode":"87527",
    "sg:province":"Bayern",
    "wof:name":"G\u00e4stehaus Paul Stark",
    "wof:placetype":"venue"
},
  "geometry": {"coordinates":[10.2624435425,47.5147438049],"type":"Point"}
}