{
  "type": "Feature",
  "properties": {
    "iso:country":"DE",
    "sg:address":"Rheinstr. 48",
    "sg:city":"M\u00fchltal",
    "sg:phone":"+49 6151/94570",
    "sg:postcode":"64367",
    "sg:province":"Hessen",
    "wof:name":"Repro-form Druckvorlagen Und Gravur Gmbh",
    "wof:placetype":"venue"
},
  "geometry": {"coordinates":[8.670779,49.81395],"type":"Point"}
}