{
  "type": "Feature",
  "properties": {
    "iso:country":"DE",
    "sg:address":"Ruhenhof 15",
    "sg:city":"Steinfurt",
    "sg:phone":"+49 2551/2012",
    "sg:postcode":"48565",
    "sg:province":"Nordrhein-Westfalen",
    "wof:name":"Raiffeisen Steinfurter Land Eg",
    "wof:placetype":"venue"
},
  "geometry": {"coordinates":[7.319298,52.156742],"type":"Point"}
}