{
  "type": "Feature",
  "properties": {
    "iso:country":"DE",
    "sg:address":"M\u00fchlenstr. 14",
    "sg:city":"Drensteinfurt",
    "sg:phone":"+49 2508/1201",
    "sg:postcode":"48317",
    "sg:province":"Nordrhein-Westfalen",
    "wof:name":"H. Salzwedel",
    "wof:placetype":"venue"
},
  "geometry": {"coordinates":[7.7411999702,51.798122406],"type":"Point"}
}