{
  "type": "Feature",
  "properties": {
    "iso:country":"DE",
    "sg:address":"Laupheimer Str. 2",
    "sg:city":"Achstetten",
    "sg:phone":"+49 7392/4792",
    "sg:postcode":"88480",
    "sg:province":"Baden-W\u00fcrttemberg",
    "wof:name":"R\u00f6\u00dfle",
    "wof:placetype":"venue"
},
  "geometry": {"coordinates":[9.897652626,48.2587280273],"type":"Point"}
}