{
  "type": "Feature",
  "properties": {
    "iso:country":"DE",
    "sg:address":"D\u00f6rpstraat 7",
    "sg:city":"Gremersdorf",
    "sg:phone":"+49 4363/2800",
    "sg:postcode":"23758",
    "sg:province":"Schleswig-Holstein",
    "wof:name":"Uhlenhof-stickereien",
    "wof:placetype":"venue"
},
  "geometry": {"coordinates":[10.9701814651,54.3437805176],"type":"Point"}
}