{
  "type": "Feature",
  "properties": {
    "iso:country":"DE",
    "sg:address":"Vieringhausen 92",
    "sg:city":"Remscheid",
    "sg:phone":"+49 4921/9171877",
    "sg:postcode":"42857",
    "sg:province":"Nordrhein-Westfalen",
    "wof:name":"Haarmann & Co.",
    "wof:placetype":"venue"
},
  "geometry": {"coordinates":[7.162849,51.173527],"type":"Point"}
}