{
  "type": "Feature",
  "properties": {
    "iso:country":"DE",
    "sg:address":"Susannastr. 2",
    "sg:city":"Wiesbaden",
    "sg:phone":"+49 611/502100",
    "sg:postcode":"65207",
    "sg:province":"Hessen",
    "wof:name":"Georg Plaschke Architekt",
    "wof:placetype":"venue"
},
  "geometry": {"coordinates":[8.325722,50.080482],"type":"Point"}
}