{
  "type": "Feature",
  "properties": {
    "iso:country":"DE",
    "sg:address":"Kr\u00e4hbrunnenstr. 5",
    "sg:city":"Ertingen",
    "sg:phone":"+49 7371/6261",
    "sg:postcode":"88521",
    "sg:province":"Baden-W\u00fcrttemberg",
    "wof:name":"Ertinger Bau Gmbh",
    "wof:placetype":"venue"
},
  "geometry": {"coordinates":[9.4644699097,48.1011543274],"type":"Point"}
}