{
  "type": "Feature",
  "properties": {
    "iso:country":"DE",
    "sg:address":"Rethelstr. 33",
    "sg:city":"D\u00fcsseldorf",
    "sg:phone":"+49 211/914490",
    "sg:postcode":"40237",
    "sg:province":"Nordrhein-Westfalen",
    "wof:name":"Sasserath Verwaltungs-gmbh",
    "wof:placetype":"venue"
},
  "geometry": {"coordinates":[6.798468,51.232155],"type":"Point"}
}