{
  "type": "Feature",
  "properties": {
    "iso:country":"DE",
    "sg:address":"Alt Bossel 6",
    "sg:city":"Sprockh\u00f6vel",
    "sg:postcode":"45549",
    "sg:province":"Nordrhein-Westfalen",
    "wof:name":"Paul Dicke Gmbh & Co. Kg",
    "wof:placetype":"venue"
},
  "geometry": {"coordinates":[7.245349884,51.3441352844],"type":"Point"}
}