{
  "type": "Feature",
  "properties": {
    "iso:country":"DE",
    "sg:address":"Siemensstr. 21",
    "sg:city":"M\u00fchlheim",
    "sg:phone":"+49 6108/602660",
    "sg:postcode":"63165",
    "sg:province":"Hessen",
    "wof:name":"Die Kreativ Werkstatt- Gesellschaft F\u00fcr Audiovisuelle",
    "wof:placetype":"venue"
},
  "geometry": {"coordinates":[8.843734,50.112953],"type":"Point"}
}