{
  "type": "Feature",
  "properties": {
    "iso:country":"DE",
    "sg:address":"Franz-Holl-Str. 17",
    "sg:city":"Bad K\u00f6nig",
    "sg:phone":"+49 6063/93130",
    "sg:postcode":"64732",
    "sg:province":"Hessen",
    "wof:name":"Rudolf Weber Kleiderb\u00fcgel- Und Holzwarenfabrikation Kg",
    "wof:placetype":"venue"
},
  "geometry": {"coordinates":[8.9947881699,49.7573890686],"type":"Point"}
}