{
  "type": "Feature",
  "properties": {
    "iso:country":"DE",
    "sg:address":"Am Herrnsitz 2",
    "sg:city":"Tittmoning",
    "sg:phone":"+49 8683/522",
    "sg:postcode":"84529",
    "sg:province":"Bayern",
    "wof:name":"Georg Obermayer",
    "wof:placetype":"venue"
},
  "geometry": {"coordinates":[12.7246160507,48.0964202881],"type":"Point"}
}