{
  "type": "Feature",
  "properties": {
    "iso:country":"DE",
    "sg:address":"Friedrichsdorfer Str. 52",
    "sg:city":"Bremen",
    "sg:phone":"+49 421/622098",
    "sg:postcode":"28759",
    "sg:province":"Bremen",
    "wof:name":"Hastrabau-wegener Gmbh & Co. Kg",
    "wof:placetype":"venue"
},
  "geometry": {"coordinates":[8.636607,53.170128],"type":"Point"}
}