{
  "type": "Feature",
  "properties": {
    "iso:country":"DE",
    "sg:address":"S\u00fcdlenger Str. 10",
    "sg:city":"B\u00fcnde",
    "sg:phone":"+49 5223/574653",
    "sg:postcode":"32257",
    "sg:province":"Nordrhein-Westfalen",
    "wof:name":"Saffet Kaplan",
    "wof:placetype":"venue"
},
  "geometry": {"coordinates":[8.5939826965,52.2001228333],"type":"Point"}
}