{
  "type": "Feature",
  "properties": {
    "iso:country":"DE",
    "sg:address":"Am Weinberg 36",
    "sg:city":"St\u00fccken",
    "sg:phone":"+49 33204/48915",
    "sg:postcode":"14547",
    "sg:province":"Brandenburg",
    "wof:name":"Manfred R\u00f6h Bautr\u00e4ger",
    "wof:placetype":"venue"
},
  "geometry": {"coordinates":[13.0826559067,52.2463722229],"type":"Point"}
}