{
  "type": "Feature",
  "properties": {
    "iso:country":"DE",
    "sg:address":"Kybfelsenstr. 65",
    "sg:city":"Freiburg",
    "sg:phone":"+49 761/290086",
    "sg:postcode":"79100",
    "sg:province":"Baden-W\u00fcrttemberg",
    "wof:name":"Hermann Aichele",
    "wof:placetype":"venue"
},
  "geometry": {"coordinates":[7.878759,47.952957],"type":"Point"}
}