{
  "type": "Feature",
  "properties": {
    "iso:country":"DE",
    "sg:address":"Aussiger Str. 17",
    "sg:city":"Waldkraiburg",
    "sg:phone":"+49 8638/83020",
    "sg:postcode":"84478",
    "sg:province":"Bayern",
    "wof:name":"Franz K\u00f6hler",
    "wof:placetype":"venue"
},
  "geometry": {"coordinates":[12.3914031982,48.200214386],"type":"Point"}
}