{
  "type": "Feature",
  "properties": {
    "iso:country":"DE",
    "sg:address":"Marktstr. 6",
    "sg:city":"Fulda",
    "sg:phone":"+49 661/72786",
    "sg:postcode":"36037",
    "sg:province":"Hessen",
    "wof:name":"Optik Wachter Augenoptiker",
    "wof:placetype":"venue"
},
  "geometry": {"coordinates":[9.6761636734,50.5515289307],"type":"Point"}
}