{
  "type": "Feature",
  "properties": {
    "iso:country":"DE",
    "sg:address":"Hauptstr. 20",
    "sg:city":"Neuenstadt",
    "sg:phone":"+49 7139/8285",
    "sg:postcode":"74196",
    "sg:province":"Baden-W\u00fcrttemberg",
    "wof:name":"Pizzeria Senso Unico",
    "wof:placetype":"venue"
},
  "geometry": {"coordinates":[9.3287706375,49.2371826172],"type":"Point"}
}