{
  "type": "Feature",
  "properties": {
    "iso:country":"DE",
    "sg:address":"Im H\u00f6fchen 8",
    "sg:city":"Dillenburg",
    "sg:phone":"+49 2771/6103",
    "sg:postcode":"35685",
    "sg:province":"Hessen",
    "wof:name":"D. Karle",
    "wof:placetype":"venue"
},
  "geometry": {"coordinates":[8.2742948532,50.7610740662],"type":"Point"}
}