{
  "type": "Feature",
  "properties": {
    "iso:country":"DE",
    "sg:address":"Schlo\u00dfberg 30",
    "sg:city":"Villingen-Schwenningen",
    "sg:phone":"+49 7721/63850",
    "sg:postcode":"78052",
    "sg:province":"Baden-W\u00fcrttemberg",
    "wof:name":"H\u00f6r Und Bernholt Immobilienmakler",
    "wof:placetype":"venue"
},
  "geometry": {"coordinates":[8.46895504,48.1078453064],"type":"Point"}
}