{
  "type": "Feature",
  "properties": {
    "iso:country":"DE",
    "sg:address":"Helle Eichen 9",
    "sg:city":"Dessau",
    "sg:postcode":"06842",
    "sg:province":"Sachsen-Anhalt",
    "wof:name":"S. Klaus",
    "wof:placetype":"venue"
},
  "geometry": {"coordinates":[12.3145084381,51.8190803528],"type":"Point"}
}