{
  "type": "Feature",
  "properties": {
    "iso:country":"DE",
    "sg:address":"Max-Planck-Str. 8",
    "sg:city":"Neuenburg",
    "sg:phone":"+49 7631/79050",
    "sg:postcode":"79395",
    "sg:province":"Baden-W\u00fcrttemberg",
    "wof:name":"Worszeck",
    "wof:placetype":"venue"
},
  "geometry": {"coordinates":[7.5535640717,47.8118209839],"type":"Point"}
}