{
  "type": "Feature",
  "properties": {
    "iso:country":"DE",
    "sg:address":"Buschstr 372",
    "sg:city":"Krefeld",
    "sg:phone":"+49 2151/58081",
    "sg:postcode":"47800",
    "sg:province":"Nordrhein-Westfalen",
    "wof:name":"Antennenbau Goeser Gmbh",
    "wof:placetype":"venue"
},
  "geometry": {"coordinates":[6.6174411774,51.3478126526],"type":"Point"}
}