{
  "type": "Feature",
  "properties": {
    "iso:country":"DE",
    "sg:address":"Bauernstr. 1",
    "sg:city":"Hitzacker",
    "sg:phone":"+49 5862/7994",
    "sg:postcode":"29456",
    "sg:province":"Niedersachsen",
    "wof:name":"Wilhelm Schulz",
    "wof:placetype":"venue"
},
  "geometry": {"coordinates":[11.041761,53.144341],"type":"Point"}
}