{
  "type": "Feature",
  "properties": {
    "iso:country":"DE",
    "sg:address":"Im Elster 22",
    "sg:city":"Forst",
    "sg:phone":"+49 6326/1636",
    "sg:postcode":"67147",
    "sg:province":"Rheinland-Pfalz",
    "wof:name":"Horst Schneider",
    "wof:placetype":"venue"
},
  "geometry": {"coordinates":[8.188125,49.422043],"type":"Point"}
}