{
  "type": "Feature",
  "properties": {
    "iso:country":"DE",
    "sg:address":"Zum Heerenberg 3",
    "sg:city":"Westerstede",
    "sg:phone":"+49 4488/78787",
    "sg:postcode":"26655",
    "sg:province":"Niedersachsen",
    "wof:name":"Dsm Deterner Steuerungs- Und Maschinenbau Gmbh & Co.",
    "wof:placetype":"venue"
},
  "geometry": {"coordinates":[7.891472,53.286587],"type":"Point"}
}