{
  "type": "Feature",
  "properties": {
    "iso:country":"DE",
    "sg:address":"Durlacher Str. 80",
    "sg:city":"Ettlingen",
    "sg:phone":"+49 7243/14906",
    "sg:postcode":"76275",
    "sg:province":"Baden-W\u00fcrttemberg",
    "wof:name":"Udo Dingeldein Architekt",
    "wof:placetype":"venue"
},
  "geometry": {"coordinates":[8.434859,48.959785],"type":"Point"}
}