{
  "type": "Feature",
  "properties": {
    "iso:country":"DE",
    "sg:address":"Rheinbacher Str. 16",
    "sg:city":"Swisttal",
    "sg:postcode":"53913",
    "sg:province":"Nordrhein-Westfalen",
    "wof:name":"Golfbetriebsgesellschaft Schlo\u00df Miel Gmbh",
    "wof:placetype":"venue"
},
  "geometry": {"coordinates":[6.9220972061,50.6629905701],"type":"Point"}
}