{
  "type": "Feature",
  "properties": {
    "iso:country":"DE",
    "sg:address":"Schulstr. 47",
    "sg:city":"Rodgau",
    "sg:postcode":"63110",
    "sg:province":"Hessen",
    "wof:name":"Beta-beteiligungs- Und Beratungsgesellschaft Mbh",
    "wof:placetype":"venue"
},
  "geometry": {"coordinates":[8.869341,49.995876],"type":"Point"}
}