{
  "type": "Feature",
  "properties": {
    "iso:country":"DE",
    "sg:address":"Hauptstr 52",
    "sg:city":"Ottendorf-Pirna",
    "sg:phone":"+49 35025/57930",
    "sg:postcode":"01819",
    "sg:province":"Sachsen",
    "wof:name":"Tis Technischer Industrieservice F\u00fcr Verschlei\u00df- Und F\u00f6dertechnik Gmbh",
    "wof:placetype":"venue"
},
  "geometry": {"coordinates":[13.942932,50.875584],"type":"Point"}
}