{
  "type": "Feature",
  "properties": {
    "iso:country":"DE",
    "sg:address":"Sickingenstr. 9",
    "sg:city":"Berlin",
    "sg:phone":"+49 30/6139500",
    "sg:postcode":"10553",
    "sg:province":"Berlin",
    "wof:name":"Welifa Heinrich Weber",
    "wof:placetype":"venue"
},
  "geometry": {"coordinates":[13.3257036209,52.5326004028],"type":"Point"}
}