{
  "type": "Feature",
  "properties": {
    "iso:country":"DE",
    "sg:address":"Dieselstr. 23",
    "sg:city":"Raisdorf",
    "sg:phone":"+49 4307/5614",
    "sg:postcode":"24223",
    "sg:province":"Schleswig-Holstein",
    "wof:name":"Sehestedter Backstube",
    "wof:placetype":"venue"
},
  "geometry": {"coordinates":[10.242989,54.280624],"type":"Point"}
}