{
  "type": "Feature",
  "properties": {
    "iso:country":"DE",
    "sg:address":"Tippelstr. 157",
    "sg:city":"Hattingen",
    "sg:phone":"+49 2324/41139",
    "sg:postcode":"45529",
    "sg:province":"Nordrhein-Westfalen",
    "wof:name":"Heinz Degener Architekt",
    "wof:placetype":"venue"
},
  "geometry": {"coordinates":[7.123109,51.384838],"type":"Point"}
}