{
  "type": "Feature",
  "properties": {
    "iso:country":"DE",
    "sg:address":"Rappenweg 15",
    "sg:city":"Villingen-Schwenningen",
    "sg:phone":"+49 7721/62325",
    "sg:postcode":"78048",
    "sg:province":"Baden-W\u00fcrttemberg",
    "wof:name":"K. Schikowski",
    "wof:placetype":"venue"
},
  "geometry": {"coordinates":[8.4552469254,48.0736236572],"type":"Point"}
}