{
  "type": "Feature",
  "properties": {
    "iso:country":"DE",
    "sg:address":"Schie\u00dfst\u00e4tte 1 b",
    "sg:city":"Sulzbach-Rosenberg",
    "sg:phone":"+49 9661/875500",
    "sg:postcode":"92237",
    "sg:province":"Bayern",
    "wof:name":"Metallbau Vollmuth Gmbh",
    "wof:placetype":"venue"
},
  "geometry": {"coordinates":[11.73772,49.506882],"type":"Point"}
}