{
  "type": "Feature",
  "properties": {
    "iso:country":"DE",
    "sg:address":"Heisinger Str. 9",
    "sg:city":"Dietmannsried",
    "sg:phone":"+49 8374/6557",
    "sg:postcode":"87463",
    "sg:province":"Bayern",
    "wof:name":"Jochens Radlstube",
    "wof:placetype":"venue"
},
  "geometry": {"coordinates":[10.290963,47.808025],"type":"Point"}
}