{
  "type": "Feature",
  "properties": {
    "iso:country":"DE",
    "sg:address":"Justus-von-Liebig-Str. 6",
    "sg:city":"\u00d6stringen",
    "sg:phone":"+49 7253/92560",
    "sg:postcode":"76684",
    "sg:province":"Baden-W\u00fcrttemberg",
    "wof:name":"Rothermel-transport- Gmbh & Co. Kg",
    "wof:placetype":"venue"
},
  "geometry": {"coordinates":[8.6974916458,49.2158203125],"type":"Point"}
}