{
  "type": "Feature",
  "properties": {
    "iso:country":"DE",
    "sg:address":"Zum Kap 14a",
    "sg:city":"Dautphetal",
    "sg:phone":"+49 6468/383",
    "sg:postcode":"35232",
    "sg:province":"Hessen",
    "wof:name":"P. Burmann-gerlach",
    "wof:placetype":"venue"
},
  "geometry": {"coordinates":[8.5057420731,50.8451690674],"type":"Point"}
}