{
  "type": "Feature",
  "properties": {
    "iso:country":"DE",
    "sg:address":"H\u00f6b\u00e4ckerweg 1",
    "sg:city":"Schl\u00fcchtern",
    "sg:postcode":"36381",
    "sg:province":"Hessen",
    "wof:name":"Rewe-m\u00e4rkte Interkauf Handels Gmbh & Co. Kg",
    "wof:placetype":"venue"
},
  "geometry": {"coordinates":[9.5210256577,50.3436088562],"type":"Point"}
}