{
  "type": "Feature",
  "properties": {
    "iso:country":"DE",
    "sg:address":"K\u00f6lner Str. 65",
    "sg:city":"Solingen",
    "sg:phone":"+49 212/204410",
    "sg:postcode":"42651",
    "sg:province":"Nordrhein-Westfalen",
    "wof:name":"Nail Sen",
    "wof:placetype":"venue"
},
  "geometry": {"coordinates":[7.0823230743,51.1698799133],"type":"Point"}
}