{
  "type": "Feature",
  "properties": {
    "iso:country":"DE",
    "sg:address":"Rathausplatz 33",
    "sg:city":"Hemmoor",
    "sg:phone":"+49 4771/5261",
    "sg:postcode":"21745",
    "sg:province":"Niedersachsen",
    "wof:name":"Hillert",
    "wof:placetype":"venue"
},
  "geometry": {"coordinates":[9.1571,53.68779],"type":"Point"}
}