{
  "type": "Feature",
  "properties": {
    "iso:country":"DE",
    "sg:address":"Kurf\u00fcrstendamm 11",
    "sg:city":"Berlin",
    "sg:postcode":"10719",
    "sg:province":"Berlin",
    "wof:name":"Prodego E. Kfr.",
    "wof:placetype":"venue"
},
  "geometry": {"coordinates":[13.333511,52.504833],"type":"Point"}
}