{
  "type": "Feature",
  "properties": {
    "iso:country":"DE",
    "sg:address":"Klausstr. 133b",
    "sg:city":"K\u00f6nigerode",
    "sg:phone":"+49 39484/42002",
    "sg:postcode":"06493",
    "sg:province":"Sachsen-Anhalt",
    "wof:name":"B. Anskat",
    "wof:placetype":"venue"
},
  "geometry": {"coordinates":[11.2042331696,51.6024513245],"type":"Point"}
}