{
  "type": "Feature",
  "properties": {
    "iso:country":"DE",
    "sg:address":"Enge Str. 4",
    "sg:city":"G\u00fcstrow",
    "sg:phone":"+49 3843/682339",
    "sg:postcode":"18273",
    "sg:province":"Mecklenburg-Vorpommern",
    "wof:name":"Gebr. Bock",
    "wof:placetype":"venue"
},
  "geometry": {"coordinates":[12.176923,53.7943],"type":"Point"}
}