{
  "type": "Feature",
  "properties": {
    "iso:country":"DE",
    "sg:address":"Schlo\u00dfstr. 5",
    "sg:city":"Simmern",
    "sg:phone":"+49 6761/4656",
    "sg:postcode":"55469",
    "sg:province":"Rheinland-Pfalz",
    "wof:name":"For You",
    "wof:placetype":"venue"
},
  "geometry": {"coordinates":[7.673278,50.388416],"type":"Point"}
}