{
  "type": "Feature",
  "properties": {
    "iso:country":"DE",
    "sg:address":"Scherecke 12",
    "sg:city":"Blaufelden",
    "sg:phone":"+49 7953/602",
    "sg:postcode":"74572",
    "sg:province":"Baden-W\u00fcrttemberg",
    "wof:name":"E. Walther Heissmangel",
    "wof:placetype":"venue"
},
  "geometry": {"coordinates":[9.9734363556,49.2954711914],"type":"Point"}
}