{
  "type": "Feature",
  "properties": {
    "iso:country":"DE",
    "sg:address":"Hans-B\u00f6ckler-Str. 6-8",
    "sg:city":"Langenfeld",
    "sg:phone":"+49 4921/739760",
    "sg:postcode":"40764",
    "sg:province":"Nordrhein-Westfalen",
    "wof:name":"G D Automatische Verpackungs- Maschinen Gmbh",
    "wof:placetype":"venue"
},
  "geometry": {"coordinates":[6.925435,51.123104],"type":"Point"}
}