{
  "type": "Feature",
  "properties": {
    "iso:country":"DE",
    "sg:address":"Friedensthal",
    "sg:city":"Windeby",
    "sg:phone":"+49 4351/42421",
    "sg:postcode":"24340",
    "sg:province":"Schleswig-Holstein",
    "wof:name":"Christian Engel",
    "wof:placetype":"venue"
},
  "geometry": {"coordinates":[9.79737,54.440861],"type":"Point"}
}