{
  "type": "Feature",
  "properties": {
    "iso:country":"DE",
    "sg:address":"Klarastr. 76",
    "sg:city":"Freiburg",
    "sg:phone":"+49 761/289145",
    "sg:postcode":"79106",
    "sg:province":"Baden-W\u00fcrttemberg",
    "wof:name":"Ayse \u00d6zkan",
    "wof:placetype":"venue"
},
  "geometry": {"coordinates":[7.8373579979,47.9953384399],"type":"Point"}
}