{
  "type": "Feature",
  "properties": {
    "iso:country":"DE",
    "sg:address":"Postfach 60",
    "sg:city":"Partenstein",
    "sg:phone":"+49 9355/2017",
    "sg:postcode":"97846",
    "sg:province":"Bayern",
    "wof:name":"Okape Holzstoff Gmbh & Co. Kg",
    "wof:placetype":"venue"
},
  "geometry": {"coordinates":[9.517124176,50.0411148071],"type":"Point"}
}