{
  "type": "Feature",
  "properties": {
    "iso:country":"DE",
    "sg:address":"Bahnhofstr. 45",
    "sg:city":"Asperg",
    "sg:phone":"+49 7141/661600",
    "sg:postcode":"71679",
    "sg:province":"Baden-W\u00fcrttemberg",
    "wof:name":"Bistro Le Petit",
    "wof:placetype":"venue"
},
  "geometry": {"coordinates":[9.1402263641,48.9064254761],"type":"Point"}
}