{
  "type": "Feature",
  "properties": {
    "iso:country":"DE",
    "sg:address":"Katzenbruch 40",
    "sg:city":"M\u00fclheim",
    "sg:phone":"+49 208/372863",
    "sg:postcode":"45478",
    "sg:province":"Nordrhein-Westfalen",
    "wof:name":"Klaus P\u00fcttmann Modevertriebs Gmbh",
    "wof:placetype":"venue"
},
  "geometry": {"coordinates":[6.8233261108,51.4134750366],"type":"Point"}
}