{
  "type": "Feature",
  "properties": {
    "iso:country":"DE",
    "sg:address":"Schlackenm\u00fchle 1",
    "sg:city":"Alterode",
    "sg:phone":"+49 34742/9520",
    "sg:postcode":"06543",
    "sg:province":"Sachsen-Anhalt",
    "wof:name":"Hotel-restaurant Zur Schlackenm\u00fchle",
    "wof:placetype":"venue"
},
  "geometry": {"coordinates":[11.3821048737,51.6625595093],"type":"Point"}
}