{
  "type": "Feature",
  "properties": {
    "iso:country":"DE",
    "sg:address":"Dieselstr. 4",
    "sg:city":"Saarbr\u00fccken",
    "sg:phone":"+49 681/870080",
    "sg:postcode":"66130",
    "sg:province":"Saarland",
    "wof:name":"Raab Karcher Baustoffe",
    "wof:placetype":"venue"
},
  "geometry": {"coordinates":[7.0346632004,49.2046051025],"type":"Point"}
}