{
  "type": "Feature",
  "properties": {
    "iso:country":"DE",
    "sg:address":"Hauptstr. 9",
    "sg:city":"Fellbach",
    "sg:phone":"+49 711/5181858",
    "sg:postcode":"70736",
    "sg:province":"Baden-W\u00fcrttemberg",
    "wof:name":"Klaus Blazek",
    "wof:placetype":"venue"
},
  "geometry": {"coordinates":[9.265148,48.843056],"type":"Point"}
}