{
  "type": "Feature",
  "properties": {
    "iso:country":"DE",
    "sg:address":"An den G\u00e4rten 24",
    "sg:city":"L\u00fcchow",
    "sg:phone":"+49 5841/2236",
    "sg:postcode":"29439",
    "sg:province":"Niedersachsen",
    "wof:name":"Hans-dieter Zerbe Steuerberater",
    "wof:placetype":"venue"
},
  "geometry": {"coordinates":[11.1515274048,52.9620170593],"type":"Point"}
}