{
  "type": "Feature",
  "properties": {
    "iso:country":"DE",
    "sg:address":"Nikolaus-von-Weis-Str. 1",
    "sg:city":"Speyer",
    "sg:postcode":"67346",
    "sg:province":"Rheinland-Pfalz",
    "wof:name":"Chemisches Untersuchungsamt",
    "wof:placetype":"venue"
},
  "geometry": {"coordinates":[8.4161577225,49.3152008057],"type":"Point"}
}