{
  "type": "Feature",
  "properties": {
    "iso:country":"DE",
    "sg:address":"Wagenburgstr. 59",
    "sg:city":"Stuttgart",
    "sg:phone":"+49 711/464391",
    "sg:postcode":"70184",
    "sg:province":"Baden-W\u00fcrttemberg",
    "wof:name":"Bernhardt Wohnbau Gmbh",
    "wof:placetype":"venue"
},
  "geometry": {"coordinates":[9.1979503632,48.7807693481],"type":"Point"}
}