{
  "type": "Feature",
  "properties": {
    "iso:country":"DE",
    "sg:address":"Dinst\u00fchlerstr. 17",
    "sg:city":"H\u00fcckelhoven",
    "sg:phone":"+49 2433/85707",
    "sg:postcode":"41836",
    "sg:province":"Nordrhein-Westfalen",
    "wof:name":"Monika Thora",
    "wof:placetype":"venue"
},
  "geometry": {"coordinates":[6.228557,51.049229],"type":"Point"}
}