{
  "type": "Feature",
  "properties": {
    "iso:country":"DE",
    "sg:address":"Am Bahnhof",
    "sg:city":"Winterfeld",
    "sg:phone":"+49 39009/9730",
    "sg:postcode":"29416",
    "sg:province":"Sachsen-Anhalt",
    "wof:name":"R\u00fchlmann Gmbh",
    "wof:placetype":"venue"
},
  "geometry": {"coordinates":[11.24443,52.736118],"type":"Point"}
}