{
  "type": "Feature",
  "properties": {
    "iso:country":"DE",
    "sg:address":"Rosenstr. 7",
    "sg:city":"Soltau",
    "sg:phone":"+49 5191/3922",
    "sg:postcode":"29614",
    "sg:province":"Niedersachsen",
    "wof:name":"Friedhelm L\u00f6hmann",
    "wof:placetype":"venue"
},
  "geometry": {"coordinates":[9.8377304077,52.9886016846],"type":"Point"}
}