{
  "type": "Feature",
  "properties": {
    "iso:country":"DE",
    "sg:address":"Wahlenstrasse 15",
    "sg:city":"Regensburg",
    "sg:phone":"+49 941",
    "sg:postcode":"93047",
    "sg:province":"Bayern",
    "wof:name":"Wodka-martini - Shaken, Not Stirred",
    "wof:placetype":"venue"
},
  "geometry": {"coordinates":[12.095684,49.019054],"type":"Point"}
}