{
  "type": "Feature",
  "properties": {
    "iso:country":"DE",
    "sg:address":"Mitteldorf 28",
    "sg:city":"Siemerode",
    "sg:postcode":"37308",
    "sg:province":"Th\u00fcringen",
    "wof:name":"Katholisches Pfarramt Siemerode",
    "wof:placetype":"venue"
},
  "geometry": {"coordinates":[10.1214895248,51.4227638245],"type":"Point"}
}