{
  "type": "Feature",
  "properties": {
    "iso:country":"DE",
    "sg:address":"Gernsheimer Str. 8",
    "sg:city":"Gro\u00df-Gerau",
    "sg:postcode":"64521",
    "sg:province":"Hessen",
    "wof:name":"Vdk Verband Hessen E. V.",
    "wof:placetype":"venue"
},
  "geometry": {"coordinates":[8.485676,49.918083],"type":"Point"}
}