{
  "type": "Feature",
  "properties": {
    "iso:country":"DE",
    "sg:address":"Von-Weinberg-Str. 7",
    "sg:city":"M\u00f6rfelden-Walldorf",
    "sg:phone":"+49 6105/704343",
    "sg:postcode":"64546",
    "sg:province":"Hessen",
    "wof:name":"Bmc Baumaschinen- Miet-center Gmbh",
    "wof:placetype":"venue"
},
  "geometry": {"coordinates":[8.5835170746,50.0148735046],"type":"Point"}
}