{
  "type": "Feature",
  "properties": {
    "iso:country":"DE",
    "sg:address":"Von-Scheffel-Str. 6",
    "sg:city":"Prien",
    "sg:phone":"+49 8051/2016",
    "sg:postcode":"83209",
    "sg:province":"Bayern",
    "wof:name":"Inge Lischke",
    "wof:placetype":"venue"
},
  "geometry": {"coordinates":[12.3514232635,47.8546257019],"type":"Point"}
}