{
  "type": "Feature",
  "properties": {
    "iso:country":"DE",
    "sg:address":"Steinweg 5",
    "sg:city":"Breitenbrunn",
    "sg:phone":"+49 3774/23942",
    "sg:postcode":"08359",
    "sg:province":"Sachsen",
    "wof:name":"Henry Lang",
    "wof:placetype":"venue"
},
  "geometry": {"coordinates":[12.758275,50.500202],"type":"Point"}
}