{
  "type": "Feature",
  "properties": {
    "iso:country":"DE",
    "sg:address":"Neumarkt 9",
    "sg:city":"Limburg",
    "sg:phone":"+49 4964/3124109",
    "sg:postcode":"65549",
    "sg:province":"Hessen",
    "wof:name":"Nassauische Sparkasse",
    "wof:placetype":"venue"
},
  "geometry": {"coordinates":[8.06283,50.386318],"type":"Point"}
}