{
  "type": "Feature",
  "properties": {
    "iso:country":"DE",
    "sg:address":"Ilsestr. 30d",
    "sg:city":"Berlin",
    "sg:phone":"+49 30/5086113",
    "sg:postcode":"10318",
    "sg:province":"Berlin",
    "wof:name":"Thomas Schobert",
    "wof:placetype":"venue"
},
  "geometry": {"coordinates":[13.517765,52.488636],"type":"Point"}
}