{
  "type": "Feature",
  "properties": {
    "iso:country":"DE",
    "sg:address":"Dammr\u00f6der Berg 10",
    "sg:city":"Mariental",
    "sg:phone":"+49 5356/9010",
    "sg:postcode":"38368",
    "sg:province":"Niedersachsen",
    "wof:name":"Meisterb\u00e4ckerei Steinecke Verwaltungsgesellschaft Mbh",
    "wof:placetype":"venue"
},
  "geometry": {"coordinates":[11.0025596619,52.2894897461],"type":"Point"}
}