{
  "type": "Feature",
  "properties": {
    "iso:country":"DE",
    "sg:address":"Obere Hauptstr. 20",
    "sg:city":"Sulzfeld",
    "sg:phone":"+49 9761/3385",
    "sg:postcode":"97633",
    "sg:province":"Bayern",
    "wof:name":"U. Hermann",
    "wof:placetype":"venue"
},
  "geometry": {"coordinates":[10.404434,50.276577],"type":"Point"}
}