{
  "type": "Feature",
  "properties": {
    "iso:country":"DE",
    "sg:address":"Glogauer Str. 15",
    "sg:city":"Kelkheim",
    "sg:phone":"+49 6195/61444",
    "sg:postcode":"65779",
    "sg:province":"Hessen",
    "wof:name":"Steko-baumanagement Gmbh",
    "wof:placetype":"venue"
},
  "geometry": {"coordinates":[8.460572,50.130054],"type":"Point"}
}