{
  "type": "Feature",
  "properties": {
    "iso:country":"DE",
    "sg:address":"K\u00fcferstr. 26",
    "sg:city":"Wendlingen",
    "sg:phone":"+49 7024/7836",
    "sg:postcode":"73240",
    "sg:province":"Baden-W\u00fcrttemberg",
    "wof:name":"K\u00fcferst\u00fcble",
    "wof:placetype":"venue"
},
  "geometry": {"coordinates":[9.3821773529,48.672039032],"type":"Point"}
}