{
  "type": "Feature",
  "properties": {
    "iso:country":"DE",
    "sg:address":"Kegelbahn 4",
    "sg:city":"Langg\u00f6ns",
    "sg:phone":"+49 6447/1304",
    "sg:postcode":"35428",
    "sg:province":"Hessen",
    "wof:name":"E. Rosin",
    "wof:placetype":"venue"
},
  "geometry": {"coordinates":[8.5856342316,50.4636688232],"type":"Point"}
}