{
  "type": "Feature",
  "properties": {
    "iso:country":"DE",
    "sg:address":"H\u00f6henweg 10",
    "sg:city":"L\u00fctzelbach",
    "sg:phone":"+49 6066/1685",
    "sg:postcode":"64750",
    "sg:province":"Hessen",
    "wof:name":"M\u00fchling",
    "wof:placetype":"venue"
},
  "geometry": {"coordinates":[9.101378,49.766476],"type":"Point"}
}