{
  "type": "Feature",
  "properties": {
    "iso:country":"DE",
    "sg:address":"Rosengasse 31",
    "sg:city":"Gie\u00dfen",
    "sg:phone":"+49 641/494497",
    "sg:postcode":"35394",
    "sg:province":"Hessen",
    "wof:name":"K. Eichhorn Finanzberater",
    "wof:placetype":"venue"
},
  "geometry": {"coordinates":[8.750667572,50.5975151062],"type":"Point"}
}