{
  "type": "Feature",
  "properties": {
    "iso:country":"DE",
    "sg:address":"Finkenweg 19",
    "sg:city":"Lohmar",
    "sg:phone":"+49 2246/912104",
    "sg:postcode":"53797",
    "sg:province":"Nordrhein-Westfalen",
    "wof:name":"Berg-datentechnik Gmbh",
    "wof:placetype":"venue"
},
  "geometry": {"coordinates":[7.2122530937,50.8318824768],"type":"Point"}
}