{
  "type": "Feature",
  "properties": {
    "iso:country":"DE",
    "sg:address":"Gr\u00fcntenstr. 12 I",
    "sg:city":"Sonthofen",
    "sg:phone":"+49 8321/81888",
    "sg:postcode":"87527",
    "sg:province":"Bayern",
    "wof:name":"Reisle Hausverwaltungen Gmbh",
    "wof:placetype":"venue"
},
  "geometry": {"coordinates":[10.2831296921,47.5125579834],"type":"Point"}
}