{
  "type": "Feature",
  "properties": {
    "iso:country":"DE",
    "sg:address":"Kaliweg 14",
    "sg:city":"Ronnenberg",
    "sg:phone":"+49 5109/9559",
    "sg:postcode":"30952",
    "sg:province":"Niedersachsen",
    "wof:name":"U. Stein Steuerberater",
    "wof:placetype":"venue"
},
  "geometry": {"coordinates":[9.6527233124,52.3136024475],"type":"Point"}
}