{
  "type": "Feature",
  "properties": {
    "iso:country":"DE",
    "sg:address":"Altbacher Hof 17",
    "sg:city":"Altbach",
    "sg:phone":"+49 7153/29047",
    "sg:postcode":"73776",
    "sg:province":"Baden-W\u00fcrttemberg",
    "wof:name":"Hans Olbrich",
    "wof:placetype":"venue"
},
  "geometry": {"coordinates":[9.3803634644,48.7286186218],"type":"Point"}
}