{
  "type": "Feature",
  "properties": {
    "iso:country":"DE",
    "sg:address":"Amselweg 7",
    "sg:city":"Limeshain",
    "sg:phone":"+49 6048/7187",
    "sg:postcode":"63694",
    "sg:province":"Hessen",
    "wof:name":"E. Schlomm",
    "wof:placetype":"venue"
},
  "geometry": {"coordinates":[8.990089,50.260315],"type":"Point"}
}