{
  "type": "Feature",
  "properties": {
    "iso:country":"DE",
    "sg:address":"Ilsenburger Weg 18",
    "sg:city":"Hamburg",
    "sg:phone":"+49 40/5516379",
    "sg:postcode":"22455",
    "sg:province":"Hamburg",
    "wof:name":"Osbahr Gmbh",
    "wof:placetype":"venue"
},
  "geometry": {"coordinates":[9.941687,53.633167],"type":"Point"}
}