{
  "type": "Feature",
  "properties": {
    "iso:country":"DE",
    "sg:address":"Talstr. 22",
    "sg:city":"Glauchau",
    "sg:phone":"+49 3763/2018",
    "sg:postcode":"08371",
    "sg:province":"Sachsen",
    "wof:name":"R. Malecha",
    "wof:placetype":"venue"
},
  "geometry": {"coordinates":[12.5452098846,50.8235054016],"type":"Point"}
}