{
  "type": "Feature",
  "properties": {
    "iso:country":"DE",
    "sg:address":"K\u00f6hlerst\u00e4tte 4",
    "sg:city":"Hagelstadt",
    "sg:phone":"+49 9453/1368",
    "sg:postcode":"93095",
    "sg:province":"Bayern",
    "wof:name":"Rudolf Vilsmeier Steuerberater",
    "wof:placetype":"venue"
},
  "geometry": {"coordinates":[12.2207403183,48.8969802856],"type":"Point"}
}