{
  "type": "Feature",
  "properties": {
    "iso:country":"DE",
    "sg:address":"Einemstr. 16",
    "sg:city":"Berlin",
    "sg:postcode":"10785",
    "sg:province":"Berlin",
    "wof:name":"Giesensdorfer Management Gmbh",
    "wof:placetype":"venue"
},
  "geometry": {"coordinates":[13.353267,52.502659],"type":"Point"}
}