{
  "type": "Feature",
  "properties": {
    "iso:country":"DE",
    "sg:address":"Marienring 8",
    "sg:city":"Landau",
    "sg:phone":"+49 6341/13155",
    "sg:postcode":"76829",
    "sg:province":"Rheinland-Pfalz",
    "wof:name":"St\u00e4dtisches Heimatmuseum",
    "wof:placetype":"venue"
},
  "geometry": {"coordinates":[8.115414,49.193443],"type":"Point"}
}