{
  "type": "Feature",
  "properties": {
    "iso:country":"DE",
    "sg:address":"H\u00e4rterichstr. 13",
    "sg:city":"Bad Mergentheim",
    "sg:phone":"+49 7931/5950",
    "sg:postcode":"97980",
    "sg:province":"Baden-W\u00fcrttemberg",
    "wof:name":"Verwaltungsgesellschaft Der Kreissparkasse Mergentheim Mbh",
    "wof:placetype":"venue"
},
  "geometry": {"coordinates":[9.7740516663,49.4929428101],"type":"Point"}
}