{
  "type": "Feature",
  "properties": {
    "iso:country":"DE",
    "sg:address":"Am Katzenstein 9",
    "sg:city":"We\u00dfling",
    "sg:phone":"+49 8153/4426",
    "sg:postcode":"82234",
    "sg:province":"Bayern",
    "wof:name":"Contec Gmbh",
    "wof:placetype":"venue"
},
  "geometry": {"coordinates":[11.247648,48.076599],"type":"Point"}
}