{
  "type": "Feature",
  "properties": {
    "iso:country":"DE",
    "sg:address":"Melstruper Str. 14",
    "sg:city":"Lathen",
    "sg:phone":"+49 5933/4667",
    "sg:postcode":"49762",
    "sg:province":"Niedersachsen",
    "wof:name":"Bernhard Pieper",
    "wof:placetype":"venue"
},
  "geometry": {"coordinates":[7.3188939095,52.8651046753],"type":"Point"}
}