{
  "type": "Feature",
  "properties": {
    "iso:country":"DE",
    "sg:address":"Am Schimmelsk\u00e4mpchen 9",
    "sg:city":"Erkrath",
    "sg:phone":"+49 2104/48877",
    "sg:postcode":"40699",
    "sg:province":"Nordrhein-Westfalen",
    "wof:name":"Berndt Saurwein Industrievertretung",
    "wof:placetype":"venue"
},
  "geometry": {"coordinates":[6.9530878067,51.2065048218],"type":"Point"}
}