{
  "type": "Feature",
  "properties": {
    "iso:country":"DE",
    "sg:address":"Heinrich-Heine-Ring 20",
    "sg:city":"Schleusingen",
    "sg:phone":"+49 36841/41484",
    "sg:postcode":"98553",
    "sg:province":"Th\u00fcringen",
    "wof:name":"Erwin Eichler",
    "wof:placetype":"venue"
},
  "geometry": {"coordinates":[10.765473,50.51194],"type":"Point"}
}