{
  "type": "Feature",
  "properties": {
    "iso:country":"DE",
    "sg:address":"Kuhtrift 6",
    "sg:city":"Eschwege",
    "sg:phone":"+49 5651/92900",
    "sg:postcode":"37269",
    "sg:province":"Hessen",
    "wof:name":"Jost & Sohn Transport Gmbh",
    "wof:placetype":"venue"
},
  "geometry": {"coordinates":[10.0385723114,51.1949882507],"type":"Point"}
}