{
  "type": "Feature",
  "properties": {
    "iso:country":"DE",
    "sg:address":"Fuggerplatz 3",
    "sg:city":"Kaufering",
    "sg:phone":"+49 8195/208",
    "sg:postcode":"86916",
    "sg:province":"Bayern",
    "wof:name":"Fischers Reiseservice Gmbh",
    "wof:placetype":"venue"
},
  "geometry": {"coordinates":[10.850361824,48.0886802673],"type":"Point"}
}