{
  "type": "Feature",
  "properties": {
    "iso:country":"DE",
    "sg:address":"Hubertusstr. 26",
    "sg:city":"Marsberg",
    "sg:phone":"+49 2993/235",
    "sg:postcode":"34431",
    "sg:province":"Nordrhein-Westfalen",
    "wof:name":"B. Plotz",
    "wof:placetype":"venue"
},
  "geometry": {"coordinates":[8.8977098465,51.4028625488],"type":"Point"}
}