{
  "type": "Feature",
  "properties": {
    "iso:country":"DE",
    "sg:address":"Katzengasse 1",
    "sg:city":"Soest",
    "sg:phone":"+49 2921/13762",
    "sg:postcode":"59494",
    "sg:province":"Nordrhein-Westfalen",
    "wof:name":"Stadtb\u00e4ckerei",
    "wof:placetype":"venue"
},
  "geometry": {"coordinates":[8.106644,51.573715],"type":"Point"}
}