{
  "type": "Feature",
  "properties": {
    "iso:country":"DE",
    "sg:address":"Draesekestr. 7",
    "sg:city":"Dresden",
    "sg:postcode":"01277",
    "sg:province":"Sachsen",
    "wof:name":"Hans Jahn",
    "wof:placetype":"venue"
},
  "geometry": {"coordinates":[13.809926033,51.0459213257],"type":"Point"}
}