{
  "type": "Feature",
  "properties": {
    "iso:country":"DE",
    "sg:address":"Sauerlacher Str. 16",
    "sg:city":"Egling",
    "sg:phone":"+49 8176",
    "sg:postcode":"82544",
    "sg:province":"Bayern",
    "wof:name":"Extra",
    "wof:placetype":"venue"
},
  "geometry": {"coordinates":[11.5101089478,47.9246559143],"type":"Point"}
}