{
  "type": "Feature",
  "properties": {
    "iso:country":"DE",
    "sg:address":"Rosgartenstr. 23",
    "sg:city":"Konstanz",
    "sg:phone":"+49 7531/13100",
    "sg:postcode":"78462",
    "sg:province":"Baden-W\u00fcrttemberg",
    "wof:name":"Reiseb\u00fcro B\u00fchlert",
    "wof:placetype":"venue"
},
  "geometry": {"coordinates":[9.1748256683,47.6592178345],"type":"Point"}
}