{
  "type": "Feature",
  "properties": {
    "iso:country":"DE",
    "sg:address":"Julius-K\u00fcchler-Str. 46",
    "sg:city":"Kaiserslautern",
    "sg:phone":"+49 631/74515",
    "sg:postcode":"67659",
    "sg:province":"Rheinland-Pfalz",
    "wof:name":"Waltraud Wronski Krankengymnastin",
    "wof:placetype":"venue"
},
  "geometry": {"coordinates":[7.745445,49.448879],"type":"Point"}
}