{
  "type": "Feature",
  "properties": {
    "iso:country":"DE",
    "sg:address":"Scherbaumstr. 9",
    "sg:city":"Muenchen",
    "sg:phone":"+49 89",
    "sg:postcode":"81737",
    "sg:province":"Bayern",
    "wof:name":"Reiseagentur Westner",
    "wof:placetype":"venue"
},
  "geometry": {"coordinates":[11.6279497147,48.0987510681],"type":"Point"}
}