{
  "type": "Feature",
  "properties": {
    "iso:country":"DE",
    "sg:address":"Beundestr. 19",
    "sg:city":"Nidda",
    "sg:phone":"+49 6043/400781",
    "sg:postcode":"63667",
    "sg:province":"Hessen",
    "wof:name":"Optiresearch Gesellschaft F\u00fcr Information Und Unternehmens-",
    "wof:placetype":"venue"
},
  "geometry": {"coordinates":[9.0055942535,50.4143180847],"type":"Point"}
}