{
  "type": "Feature",
  "properties": {
    "iso:country":"DE",
    "sg:city":"Berlin",
    "sg:phone":"+49 30/4166060",
    "sg:postcode":"10785",
    "sg:province":"Berlin",
    "wof:name":"Fietings Internationale Doppelg\u00e4ngeragentur",
    "wof:placetype":"venue"
},
  "geometry": {"coordinates":[13.363442,52.509857],"type":"Point"}
}