{
  "type": "Feature",
  "properties": {
    "iso:country":"DE",
    "sg:address":"Ackerstr. 3",
    "sg:city":"Harmsdorf",
    "sg:phone":"+49 4363/91155",
    "sg:postcode":"23738",
    "sg:province":"Schleswig-Holstein",
    "wof:name":"Euraris Edel-naturkosmetik Helga Schmidt",
    "wof:placetype":"venue"
},
  "geometry": {"coordinates":[10.835745,54.2393],"type":"Point"}
}