{
  "type": "Feature",
  "properties": {
    "iso:country":"DE",
    "sg:address":"Schubertstr. 5",
    "sg:city":"Velbert",
    "sg:phone":"+49 2053/6600",
    "sg:postcode":"42553",
    "sg:province":"Nordrhein-Westfalen",
    "wof:name":"R. Pfaller Treuhand- Und",
    "wof:placetype":"venue"
},
  "geometry": {"coordinates":[7.0657272339,51.3153114319],"type":"Point"}
}