{
  "type": "Feature",
  "properties": {
    "iso:country":"DE",
    "sg:address":"Andersh\u00e4user Kirchweg 9",
    "sg:city":"Einbeck",
    "sg:phone":"+49 5561/73232",
    "sg:postcode":"37574",
    "sg:province":"Niedersachsen",
    "wof:name":"Richard-a. Dietrich",
    "wof:placetype":"venue"
},
  "geometry": {"coordinates":[9.8628034592,51.8332328796],"type":"Point"}
}