{
  "type": "Feature",
  "properties": {
    "iso:country":"DE",
    "sg:address":"Blumberger Damm 168",
    "sg:city":"Berlin",
    "sg:phone":"+49 30/9313101",
    "sg:postcode":"12679",
    "sg:province":"Berlin",
    "wof:name":"Erhard Zeidler Rechtsanwalt",
    "wof:placetype":"venue"
},
  "geometry": {"coordinates":[13.5729198456,52.5481185913],"type":"Point"}
}