{
  "type": "Feature",
  "properties": {
    "iso:country":"DE",
    "sg:address":"Kanonenstr. 1",
    "sg:city":"Dreieich",
    "sg:phone":"+49 6103/67307",
    "sg:postcode":"63303",
    "sg:province":"Hessen",
    "wof:name":"Horst Neubecker",
    "wof:placetype":"venue"
},
  "geometry": {"coordinates":[8.6951990128,50.0202865601],"type":"Point"}
}