{
  "type": "Feature",
  "properties": {
    "iso:country":"DE",
    "sg:address":"K\u00f6lnstr. 12",
    "sg:city":"D\u00fcren",
    "sg:phone":"+49 2421/15771",
    "sg:postcode":"52349",
    "sg:province":"Nordrhein-Westfalen",
    "wof:name":"Mode Minartz Inh. Richard Minartz",
    "wof:placetype":"venue"
},
  "geometry": {"coordinates":[6.4846229553,50.8026771545],"type":"Point"}
}