{
  "type": "Feature",
  "properties": {
    "iso:country":"DE",
    "sg:address":"Leipziger Str. 254",
    "sg:city":"Dresden",
    "sg:phone":"+49 351/8491240",
    "sg:postcode":"01139",
    "sg:province":"Sachsen",
    "wof:name":"Antennen- Und Fernsehservice Afs Gmbh",
    "wof:placetype":"venue"
},
  "geometry": {"coordinates":[13.704873,51.086105],"type":"Point"}
}