{
  "type": "Feature",
  "properties": {
    "iso:country":"DE",
    "sg:address":"Walter-Felsenstein-Str. 55",
    "sg:city":"Berlin",
    "sg:phone":"+49 30/9322393",
    "sg:postcode":"12687",
    "sg:province":"Berlin",
    "wof:name":"Ralph Webers",
    "wof:placetype":"venue"
},
  "geometry": {"coordinates":[13.5567941666,52.5552558899],"type":"Point"}
}