{
  "type": "Feature",
  "properties": {
    "iso:country":"DE",
    "sg:address":"Wiesenstr. 22",
    "sg:city":"Kirchdorf",
    "sg:phone":"+49 8571/3075",
    "sg:postcode":"84375",
    "sg:province":"Bayern",
    "wof:name":"Rudolf Duldinger Ingenieur Und Architekt",
    "wof:placetype":"venue"
},
  "geometry": {"coordinates":[12.97662,48.25956],"type":"Point"}
}