{
  "type": "Feature",
  "properties": {
    "iso:country":"DE",
    "sg:address":"Neuerwall 63::",
    "sg:city":"Hamburg",
    "sg:phone":"+49 40/3747460",
    "sg:postcode":"20354",
    "sg:province":"Hamburg",
    "wof:name":"Unibank A/s",
    "wof:placetype":"venue"
},
  "geometry": {"coordinates":[9.988,53.550396],"type":"Point"}
}