{
  "type": "Feature",
  "properties": {
    "iso:country":"DE",
    "sg:address":"Im Neuen Felde 60",
    "sg:city":"Uelzen",
    "sg:phone":"+49 581/88430",
    "sg:postcode":"29525",
    "sg:province":"Niedersachsen",
    "wof:name":"Esselte Leitz Gmbh & Co",
    "wof:placetype":"venue"
},
  "geometry": {"coordinates":[10.557675,52.985626],"type":"Point"}
}