{
  "type": "Feature",
  "properties": {
    "iso:country":"DE",
    "sg:address":"Brinkstr. 9",
    "sg:city":"Harsum",
    "sg:phone":"+49 5123/8860",
    "sg:postcode":"31177",
    "sg:province":"Niedersachsen",
    "wof:name":"Josef Bormann",
    "wof:placetype":"venue"
},
  "geometry": {"coordinates":[10.067088,52.212631],"type":"Point"}
}