{
  "type": "Feature",
  "properties": {
    "iso:country":"DE",
    "sg:address":"Adalbertsteinweg 236",
    "sg:city":"Aachen",
    "sg:phone":"+49 241/9003080",
    "sg:postcode":"52066",
    "sg:province":"Nordrhein-Westfalen",
    "wof:name":"B. Woitowitz",
    "wof:placetype":"venue"
},
  "geometry": {"coordinates":[6.1128869057,50.7721481323],"type":"Point"}
}