{
  "type": "Feature",
  "properties": {
    "iso:country":"DE",
    "sg:address":"Schmilinskystr. 20",
    "sg:city":"Hamburg",
    "sg:postcode":"20099",
    "sg:province":"Hamburg",
    "wof:name":"Nos Never Out Of Stock Handels- Gmbh",
    "wof:placetype":"venue"
},
  "geometry": {"coordinates":[10.0123558044,53.5591659546],"type":"Point"}
}