{
  "type": "Feature",
  "properties": {
    "iso:country":"DE",
    "sg:address":"Hansastr. 27f",
    "sg:city":"M\u00fcnchen",
    "sg:phone":"+49 89",
    "sg:postcode":"81373",
    "sg:province":"Bayern",
    "wof:name":"Bhw Immobilien Gmbh",
    "wof:placetype":"venue"
},
  "geometry": {"coordinates":[11.5307798386,48.1313095093],"type":"Point"}
}