{
  "type": "Feature",
  "properties": {
    "iso:country":"DE",
    "sg:address":"Rosastr. 17",
    "sg:city":"Freiburg",
    "sg:phone":"+49 761/38880",
    "sg:postcode":"79098",
    "sg:province":"Baden-W\u00fcrttemberg",
    "wof:name":"Oberrheinische Revisions- Und Treuhand Gmbh",
    "wof:placetype":"venue"
},
  "geometry": {"coordinates":[7.844689846,47.9984016418],"type":"Point"}
}