{
  "type": "Feature",
  "properties": {
    "iso:country":"DE",
    "sg:address":"Haus Riepen 1",
    "sg:city":"Warburg",
    "sg:phone":"+49 5641/740750",
    "sg:postcode":"34414",
    "sg:province":"Nordrhein-Westfalen",
    "wof:name":"Dvt Dirks Verbindungs- Technik Gmbh",
    "wof:placetype":"venue"
},
  "geometry": {"coordinates":[9.170607,51.531147],"type":"Point"}
}