{
  "type": "Feature",
  "properties": {
    "iso:country":"DE",
    "sg:address":"Alexanderstr. 6",
    "sg:city":"D\u00f6beln",
    "sg:phone":"+49 3431/66110",
    "sg:postcode":"04720",
    "sg:province":"Sachsen",
    "wof:name":"Rasoma Werkzeugmaschinen Gmbh",
    "wof:placetype":"venue"
},
  "geometry": {"coordinates":[13.0947189331,51.1323051453],"type":"Point"}
}