{
  "type": "Feature",
  "properties": {
    "iso:country":"DE",
    "sg:address":"Junghansstr. 64",
    "sg:city":"Dresden",
    "sg:phone":"+49 351/2581838",
    "sg:postcode":"01277",
    "sg:province":"Sachsen",
    "wof:name":"Inge Koegst",
    "wof:placetype":"venue"
},
  "geometry": {"coordinates":[13.7887706757,51.034034729],"type":"Point"}
}