{
  "type": "Feature",
  "properties": {
    "iso:country":"DE",
    "sg:address":"Borkumer Str. 6",
    "sg:city":"Berlin",
    "sg:phone":"+49 30/3311969",
    "sg:postcode":"13581",
    "sg:province":"Berlin",
    "wof:name":"Torsten Schmerling",
    "wof:placetype":"venue"
},
  "geometry": {"coordinates":[13.195499,52.532593],"type":"Point"}
}