{
  "type": "Feature",
  "properties": {
    "iso:country":"DE",
    "sg:address":"Traubenstr 14",
    "sg:city":"Magstadt",
    "sg:phone":"+49 7159/920855",
    "sg:postcode":"71106",
    "sg:province":"Baden-W\u00fcrttemberg",
    "wof:name":"B\u00dcrgel Gmbh Ihr Lexmark Profi",
    "wof:placetype":"venue"
},
  "geometry": {"coordinates":[8.9618692398,48.7436676025],"type":"Point"}
}