{
  "type": "Feature",
  "properties": {
    "iso:country":"DE",
    "sg:address":"Brienner Str. 40",
    "sg:city":"M\u00fcnchen",
    "sg:postcode":"80333",
    "sg:province":"Bayern",
    "wof:name":"Ilse Feldesbesitz Gmbh",
    "wof:placetype":"venue"
},
  "geometry": {"coordinates":[11.5625867844,48.1466941833],"type":"Point"}
}