{
  "type": "Feature",
  "properties": {
    "iso:country":"DE",
    "sg:address":"Hauptstr. 3",
    "sg:city":"Ochsenfurt",
    "sg:phone":"+49 9331/80620",
    "sg:postcode":"97199",
    "sg:province":"Bayern",
    "wof:name":"Jugendherberge Ochsenfurt",
    "wof:placetype":"venue"
},
  "geometry": {"coordinates":[10.0616388321,49.6647224426],"type":"Point"}
}