{
  "type": "Feature",
  "properties": {
    "iso:country":"DE",
    "sg:address":"Au\u00dferhalb 20",
    "sg:city":"Gernsheim",
    "sg:phone":"+49 6258/4643",
    "sg:postcode":"64579",
    "sg:province":"Hessen",
    "wof:name":"Gerhard Friedrich Architekt",
    "wof:placetype":"venue"
},
  "geometry": {"coordinates":[8.481428,49.754238],"type":"Point"}
}