{
  "type": "Feature",
  "properties": {
    "iso:country":"DE",
    "sg:address":"Chemnitzer Str. 4a",
    "sg:city":"Niederdorf",
    "sg:phone":"+49 37296/17159",
    "sg:postcode":"09366",
    "sg:province":"Sachsen",
    "wof:name":"C Gr\u00e4nz Gmbh & Co. Kg",
    "wof:placetype":"venue"
},
  "geometry": {"coordinates":[12.794169,50.733143],"type":"Point"}
}