{
  "type": "Feature",
  "properties": {
    "iso:country":"DE",
    "sg:address":"Eichkopfallee 45",
    "sg:city":"Liederbach",
    "sg:phone":"+49 69/302231",
    "sg:postcode":"65835",
    "sg:province":"Hessen",
    "wof:name":"American Touch Import Und Vertrieb",
    "wof:placetype":"venue"
},
  "geometry": {"coordinates":[8.491356,50.1245],"type":"Point"}
}