{
  "type": "Feature",
  "properties": {
    "iso:country":"DE",
    "sg:address":"M\u00f6hnestr. 10",
    "sg:city":"Hanau",
    "sg:phone":"+49 6181/91700",
    "sg:postcode":"63452",
    "sg:province":"Hessen",
    "wof:name":"Kvg Kunststoff-vertriebs- Gesellschaft Mbh",
    "wof:placetype":"venue"
},
  "geometry": {"coordinates":[8.9394388199,50.1451187134],"type":"Point"}
}