{
  "type": "Feature",
  "properties": {
    "iso:country":"DE",
    "sg:address":"Hauptstr. 88",
    "sg:city":"Bad Honnef",
    "sg:phone":"+49 2224/5849",
    "sg:postcode":"53604",
    "sg:province":"Nordrhein-Westfalen",
    "wof:name":"Max Linder",
    "wof:placetype":"venue"
},
  "geometry": {"coordinates":[7.2293257713,50.6437644958],"type":"Point"}
}