{
  "type": "Feature",
  "properties": {
    "iso:country":"DE",
    "sg:address":"Am Eiswurmlager 1",
    "sg:city":"Dresden",
    "sg:phone":"+49 7136/96370",
    "sg:postcode":"01189",
    "sg:province":"Sachsen",
    "wof:name":"Konkurse.com Gmbh",
    "wof:placetype":"venue"
},
  "geometry": {"coordinates":[9.216741,49.229382],"type":"Point"}
}