{
  "type": "Feature",
  "properties": {
    "iso:country":"DE",
    "sg:address":"Mainzer Str. 22",
    "sg:city":"Remagen",
    "sg:phone":"+49 2228/94240",
    "sg:postcode":"53424",
    "sg:province":"Rheinland-Pfalz",
    "wof:name":"Defudao Trading Tourist- Und Hotel-restaurant Gmbh",
    "wof:placetype":"venue"
},
  "geometry": {"coordinates":[7.2058157921,50.6370277405],"type":"Point"}
}