{
  "type": "Feature",
  "properties": {
    "iso:country":"DE",
    "sg:address":"K\u00f6nigsdorfer Str. 59",
    "sg:city":"Bad T\u00f6lz",
    "sg:postcode":"83646",
    "sg:province":"Bayern",
    "wof:name":"H.m. Verwaltungs- Gmbh & Co.",
    "wof:placetype":"venue"
},
  "geometry": {"coordinates":[11.5519342422,47.7621040344],"type":"Point"}
}