{
  "type": "Feature",
  "properties": {
    "iso:country":"DE",
    "sg:address":"Naheweinstr. 91",
    "sg:city":"Guldental",
    "sg:phone":"+49 6707/9190",
    "sg:postcode":"55452",
    "sg:province":"Rheinland-Pfalz",
    "wof:name":"Bauunternehmen Joh. Bott Gmbh",
    "wof:placetype":"venue"
},
  "geometry": {"coordinates":[7.839636,49.894268],"type":"Point"}
}