{
  "type": "Feature",
  "properties": {
    "iso:country":"DE",
    "sg:address":"Am Gr\u00fcnberg 2",
    "sg:city":"Neumarkt",
    "sg:phone":"+49 9181/46900",
    "sg:postcode":"92318",
    "sg:province":"Bayern",
    "wof:name":"Haubner Treppen Gmbh",
    "wof:placetype":"venue"
},
  "geometry": {"coordinates":[11.4065437317,49.2991142273],"type":"Point"}
}