{
  "type": "Feature",
  "properties": {
    "iso:country":"DE",
    "sg:address":"Herzog-Arenberg-Str. 59",
    "sg:city":"Meppen",
    "sg:phone":"+49 5931/5892",
    "sg:postcode":"49716",
    "sg:province":"Niedersachsen",
    "wof:name":"H. Und E. Setzer",
    "wof:placetype":"venue"
},
  "geometry": {"coordinates":[7.2956728935,52.7015419006],"type":"Point"}
}