{
  "type": "Feature",
  "properties": {
    "iso:country":"DE",
    "sg:address":"Mozartstr. 6",
    "sg:city":"Sarstedt",
    "sg:phone":"+49 5066/3237",
    "sg:postcode":"31157",
    "sg:province":"Niedersachsen",
    "wof:name":"Annemarie Wehling",
    "wof:placetype":"venue"
},
  "geometry": {"coordinates":[9.8655767441,52.2397994995],"type":"Point"}
}