{
  "type": "Feature",
  "properties": {
    "iso:country":"DE",
    "sg:address":"Dorfstr. 19",
    "sg:city":"Maasdorf",
    "sg:phone":"+49 35341/2982",
    "sg:postcode":"04924",
    "sg:province":"Brandenburg",
    "wof:name":"K. Berg",
    "wof:placetype":"venue"
},
  "geometry": {"coordinates":[13.413225174,51.5373573303],"type":"Point"}
}