{
  "type": "Feature",
  "properties": {
    "iso:country":"DE",
    "sg:address":"Lindenstr. 6",
    "sg:city":"Cainsdorf",
    "sg:phone":"+49 375/676900",
    "sg:postcode":"08124",
    "wof:name":"I. Tautenhahn",
    "wof:placetype":"venue"
},
  "geometry": {"coordinates":[12.490195,50.675625],"type":"Point"}
}