{
  "type": "Feature",
  "properties": {
    "iso:country":"DE",
    "sg:address":"Karlsruher Str. 1",
    "sg:city":"D\u00fcsseldorf",
    "sg:phone":"+49 211/2293970",
    "sg:postcode":"40229",
    "sg:province":"Nordrhein-Westfalen",
    "wof:name":"Bauunterhaltung Handwerk Und Mehr Gmbh",
    "wof:placetype":"venue"
},
  "geometry": {"coordinates":[6.835606,51.196232],"type":"Point"}
}