{
  "type": "Feature",
  "properties": {
    "iso:country":"DE",
    "sg:address":"Kupfferstr. 6",
    "sg:city":"M\u00fcnchen",
    "sg:phone":"+49 89/8123627",
    "sg:postcode":"80999",
    "sg:province":"Bayern",
    "wof:name":"Eugen Schuster Gmbh",
    "wof:placetype":"venue"
},
  "geometry": {"coordinates":[11.459332,48.198067],"type":"Point"}
}