{
  "type": "Feature",
  "properties": {
    "iso:country":"DE",
    "sg:address":"Samweg 6",
    "sg:city":"Sielenbach",
    "sg:phone":"+49 8258/214",
    "sg:postcode":"86577",
    "sg:province":"Bayern",
    "wof:name":"Josef Ankner",
    "wof:placetype":"venue"
},
  "geometry": {"coordinates":[11.1590461731,48.3994827271],"type":"Point"}
}