{
  "type": "Feature",
  "properties": {
    "iso:country":"DE",
    "sg:address":"Dalbergstr. 28",
    "sg:city":"Dittelsheim-He\u00dfloch",
    "sg:phone":"+49 6244/4921",
    "sg:postcode":"67596",
    "sg:province":"Rheinland-Pfalz",
    "wof:name":"Alfons Michel Weinanbau",
    "wof:placetype":"venue"
},
  "geometry": {"coordinates":[8.2513666153,49.7433891296],"type":"Point"}
}