{
  "type": "Feature",
  "properties": {
    "iso:country":"DE",
    "sg:address":"Vorderegglburg 20 c",
    "sg:city":"Ebersberg",
    "sg:postcode":"85560",
    "sg:province":"Bayern",
    "wof:name":"Finspeed Gmbh",
    "wof:placetype":"venue"
},
  "geometry": {"coordinates":[11.9386234283,48.075176239],"type":"Point"}
}