{
  "type": "Feature",
  "properties": {
    "iso:country":"DE",
    "sg:address":"L\u00f6rracher Str. 37 a",
    "sg:city":"Freiburg",
    "sg:phone":"+49 761/474727",
    "sg:postcode":"79115",
    "sg:province":"Baden-W\u00fcrttemberg",
    "wof:name":"Rolf Spittler",
    "wof:placetype":"venue"
},
  "geometry": {"coordinates":[7.8225951195,47.98021698],"type":"Point"}
}