{
  "type": "Feature",
  "properties": {
    "iso:country":"DE",
    "sg:address":"Kastanienweg 4",
    "sg:city":"Aerzen",
    "sg:phone":"+49 5154/4111",
    "sg:postcode":"31855",
    "sg:province":"Niedersachsen",
    "wof:name":"Zimmerei Reinhard Kietzmann Gmbh",
    "wof:placetype":"venue"
},
  "geometry": {"coordinates":[9.3024311066,52.0674705505],"type":"Point"}
}