{
  "type": "Feature",
  "properties": {
    "iso:country":"DE",
    "sg:address":"Vehrlingstr. 31",
    "sg:city":"Bad Salzuflen",
    "sg:phone":"+49 5222/83136",
    "sg:postcode":"32108",
    "sg:province":"Nordrhein-Westfalen",
    "wof:name":"G\u00fcnter Steinmann",
    "wof:placetype":"venue"
},
  "geometry": {"coordinates":[8.756047,52.069386],"type":"Point"}
}