{
  "type": "Feature",
  "properties": {
    "iso:country":"DE",
    "sg:address":"Moskauer Str. 15",
    "sg:city":"Apolda",
    "sg:phone":"+49 4936/4484490",
    "sg:postcode":"99510",
    "sg:province":"Th\u00fcringen",
    "wof:name":"Gebr Raebel & Sohn Ohg",
    "wof:placetype":"venue"
},
  "geometry": {"coordinates":[11.527756691,51.0268669128],"type":"Point"}
}