{
  "type": "Feature",
  "properties": {
    "iso:country":"DE",
    "sg:address":"Ziegeleistr. 8",
    "sg:city":"Aiglsbach",
    "sg:phone":"+49 8753/95090",
    "sg:postcode":"84089",
    "sg:province":"Bayern",
    "wof:name":"Hillerbrand Zimmerei Und Bau Gmbh",
    "wof:placetype":"venue"
},
  "geometry": {"coordinates":[11.7105674744,48.6909332275],"type":"Point"}
}