{
  "type": "Feature",
  "properties": {
    "iso:country":"DE",
    "sg:address":"Trierer Str. 5",
    "sg:city":"Gusterath",
    "sg:phone":"+49 6588/3331",
    "sg:postcode":"54317",
    "sg:province":"Rheinland-Pfalz",
    "wof:name":"Hermann Willems-theisen Anlageberater",
    "wof:placetype":"venue"
},
  "geometry": {"coordinates":[6.7182922363,49.6988792419],"type":"Point"}
}