{
  "type": "Feature",
  "properties": {
    "iso:country":"DE",
    "sg:address":"Christian-Gau-Str. 13",
    "sg:city":"K\u00f6ln",
    "sg:phone":"+49 221/493335",
    "sg:postcode":"50933",
    "sg:province":"Nordrhein-Westfalen",
    "wof:name":"Peter Stammel",
    "wof:placetype":"venue"
},
  "geometry": {"coordinates":[6.899223,50.935898],"type":"Point"}
}