{
  "type": "Feature",
  "properties": {
    "iso:country":"DE",
    "sg:address":"Kobergerstr. 34",
    "sg:city":"N\u00fcrnberg",
    "sg:phone":"+49 911/362111",
    "sg:postcode":"90408",
    "sg:province":"Bayern",
    "wof:name":"Hans Kastenhuber",
    "wof:placetype":"venue"
},
  "geometry": {"coordinates":[11.0764913559,49.4645462036],"type":"Point"}
}