{
  "type": "Feature",
  "properties": {
    "iso:country":"DE",
    "sg:address":"Luitpoldstr. 8",
    "sg:city":"Herxheim",
    "sg:phone":"+49 7276/1441",
    "sg:postcode":"76863",
    "sg:province":"Rheinland-Pfalz",
    "wof:name":"Theo Frick",
    "wof:placetype":"venue"
},
  "geometry": {"coordinates":[8.21224,49.143513],"type":"Point"}
}