{
  "type": "Feature",
  "properties": {
    "iso:country":"DE",
    "sg:address":"Nibelungenstr. 80",
    "sg:city":"H\u00fcrth",
    "sg:phone":"+49 2233/76766",
    "sg:postcode":"50354",
    "sg:province":"Nordrhein-Westfalen",
    "wof:name":"Manfred Herkenrath",
    "wof:placetype":"venue"
},
  "geometry": {"coordinates":[6.893867,50.888855],"type":"Point"}
}