{
  "type": "Feature",
  "properties": {
    "iso:country":"DE",
    "sg:address":"Smeer Ort 15",
    "sg:city":"Syke",
    "sg:phone":"+49 4242/931150",
    "sg:postcode":"28857",
    "sg:province":"Niedersachsen",
    "wof:name":"Geffken & Lippold Ingenieurges. F\u00fcr Gewerbebau",
    "wof:placetype":"venue"
},
  "geometry": {"coordinates":[8.8829631805,52.9310531616],"type":"Point"}
}