{
  "type": "Feature",
  "properties": {
    "iso:country":"DE",
    "sg:address":"Huystr. 41",
    "sg:city":"Halberstadt",
    "sg:phone":"+49 3941/604069",
    "sg:postcode":"38820",
    "sg:province":"Sachsen-Anhalt",
    "wof:name":"Kaminstudio Martin Gottschalt",
    "wof:placetype":"venue"
},
  "geometry": {"coordinates":[11.0429515839,51.9031486511],"type":"Point"}
}