{
  "type": "Feature",
  "properties": {
    "iso:country":"DE",
    "sg:address":"Im Baumgarten 12a",
    "sg:city":"Inzlingen",
    "sg:phone":"+49 7621/82341",
    "sg:postcode":"79594",
    "sg:province":"Baden-W\u00fcrttemberg",
    "wof:name":"Walter Auer",
    "wof:placetype":"venue"
},
  "geometry": {"coordinates":[7.694432,47.586895],"type":"Point"}
}