{
  "type": "Feature",
  "properties": {
    "iso:country":"DE",
    "sg:address":"Johann-Anton-Pader-Weg 2",
    "sg:city":"Dorfen",
    "sg:phone":"+49 8081/3047",
    "sg:postcode":"84405",
    "sg:province":"Bayern",
    "wof:name":"Saison Frucht- Und Feinkosthandel Gmbh",
    "wof:placetype":"venue"
},
  "geometry": {"coordinates":[12.1556053162,48.2802124023],"type":"Point"}
}