{
  "type": "Feature",
  "properties": {
    "iso:country":"DE",
    "sg:address":"Am Berg 23",
    "sg:city":"Fulda",
    "sg:phone":"+49 661/53409",
    "sg:postcode":"36041",
    "sg:province":"Hessen",
    "wof:name":"Winfried Weber",
    "wof:placetype":"venue"
},
  "geometry": {"coordinates":[9.621869,50.565609],"type":"Point"}
}