{
  "type": "Feature",
  "properties": {
    "iso:country":"DE",
    "sg:address":"Werner-Heisenberg-Str. 18",
    "sg:city":"Bretten",
    "sg:phone":"+49 7252/78521",
    "sg:postcode":"75015",
    "sg:province":"Baden-W\u00fcrttemberg",
    "wof:name":"Uwe Dahn",
    "wof:placetype":"venue"
},
  "geometry": {"coordinates":[8.7187080383,49.0266952515],"type":"Point"}
}