{
  "type": "Feature",
  "properties": {
    "iso:country":"DE",
    "sg:address":"Frankfurter Str. 38",
    "sg:city":"Linden",
    "sg:phone":"+49 6403/72192",
    "sg:postcode":"35440",
    "sg:province":"Hessen",
    "wof:name":"Franz Und S. Richter",
    "wof:placetype":"venue"
},
  "geometry": {"coordinates":[8.648565,50.524155],"type":"Point"}
}