{
  "type": "Feature",
  "properties": {
    "iso:country":"DE",
    "sg:address":"Johann-Sebastian-Bach-Str. 20",
    "sg:city":"Heddesheim",
    "sg:phone":"+49 6203/44291",
    "sg:postcode":"68542",
    "sg:province":"Baden-W\u00fcrttemberg",
    "wof:name":"Atek-elektroakustische Anlagen Gmbh",
    "wof:placetype":"venue"
},
  "geometry": {"coordinates":[8.6019411087,49.5100784302],"type":"Point"}
}