{
  "type": "Feature",
  "properties": {
    "iso:country":"DE",
    "sg:address":"Friedrich-Rech-Str. 182",
    "sg:city":"Neuwied",
    "sg:phone":"+49 2631/47100",
    "sg:postcode":"56566",
    "sg:province":"Rheinland-Pfalz",
    "wof:name":"Hans-peter Kreutz",
    "wof:placetype":"venue"
},
  "geometry": {"coordinates":[7.501943,50.474625],"type":"Point"}
}