{
  "type": "Feature",
  "properties": {
    "iso:country":"DE",
    "sg:address":"Tramplerstr. 78",
    "sg:city":"Lahr",
    "sg:phone":"+49 7821/51921",
    "sg:postcode":"77933",
    "sg:province":"Baden-W\u00fcrttemberg",
    "wof:name":"Kohrmann Baumaschinen Gmbh",
    "wof:placetype":"venue"
},
  "geometry": {"coordinates":[7.852769,48.333881],"type":"Point"}
}