{
  "type": "Feature",
  "properties": {
    "iso:country":"DE",
    "sg:address":"Bei der Nachtweide",
    "sg:city":"Altenstadt",
    "sg:postcode":"63674",
    "sg:province":"Hessen",
    "wof:name":"Stoll Gmbh",
    "wof:placetype":"venue"
},
  "geometry": {"coordinates":[8.948991,50.275497],"type":"Point"}
}