{
  "type": "Feature",
  "properties": {
    "iso:country":"DE",
    "sg:address":"D\u00f6rneweg 8",
    "sg:city":"Mudenbach",
    "sg:phone":"+49 2688/452",
    "sg:postcode":"57614",
    "sg:province":"Rheinland-Pfalz",
    "wof:name":"Hering Gmbh Herstellung Roll\u00e4den",
    "wof:placetype":"venue"
},
  "geometry": {"coordinates":[7.7315039635,50.6657218933],"type":"Point"}
}