{
  "type": "Feature",
  "properties": {
    "iso:country":"DE",
    "sg:address":"Friesenstr. 103",
    "sg:city":"Bremen",
    "sg:phone":"+49 421/73550",
    "sg:postcode":"28203",
    "sg:province":"Bremen",
    "wof:name":"Medoc",
    "wof:placetype":"venue"
},
  "geometry": {"coordinates":[8.8314304352,53.0727958679],"type":"Point"}
}