{
  "type": "Feature",
  "properties": {
    "iso:country":"DE",
    "sg:address":"Bischh\u00e4user Str. 34",
    "sg:city":"Neuental",
    "sg:phone":"+49 6693/211",
    "sg:postcode":"34599",
    "sg:province":"Hessen",
    "wof:name":"H. Parske",
    "wof:placetype":"venue"
},
  "geometry": {"coordinates":[9.207395,51.010784],"type":"Point"}
}