{
  "type": "Feature",
  "properties": {
    "iso:country":"DE",
    "sg:address":"Hauptstr. 51-53",
    "sg:city":"Hofheim",
    "sg:phone":"+49 6192/27677",
    "sg:postcode":"65719",
    "sg:province":"Hessen",
    "wof:name":"City-moden Wilma Haun Gmbh",
    "wof:placetype":"venue"
},
  "geometry": {"coordinates":[8.444617,50.087421],"type":"Point"}
}