{
  "type": "Feature",
  "properties": {
    "iso:country":"DE",
    "sg:address":"Gleichmannstr. 14",
    "sg:city":"M\u00fcnchen",
    "sg:phone":"+49 89/886585",
    "sg:postcode":"81241",
    "sg:province":"Bayern",
    "wof:name":"Reformhaus Mehl Ohg",
    "wof:placetype":"venue"
},
  "geometry": {"coordinates":[11.4602098465,48.1479301453],"type":"Point"}
}