{
  "type": "Feature",
  "properties": {
    "iso:country":"DE",
    "sg:address":"Am Pfaffenmoos 1",
    "sg:city":"Reichenau",
    "sg:phone":"+49 7531/77014",
    "sg:postcode":"78479",
    "sg:province":"Baden-W\u00fcrttemberg",
    "wof:name":"W. Runge",
    "wof:placetype":"venue"
},
  "geometry": {"coordinates":[9.1147737503,47.6985244751],"type":"Point"}
}