{
  "type": "Feature",
  "properties": {
    "iso:country":"DE",
    "sg:address":"Binge 69",
    "sg:city":"Heuthen",
    "sg:phone":"+49 36084/80313",
    "sg:postcode":"37308",
    "sg:province":"Th\u00fcringen",
    "wof:name":"Willi Apel",
    "wof:placetype":"venue"
},
  "geometry": {"coordinates":[10.222488,51.330814],"type":"Point"}
}