{
  "type": "Feature",
  "properties": {
    "iso:country":"DE",
    "sg:address":"Sandbuschweg 19",
    "sg:city":"Kassel",
    "sg:phone":"+49 561/403527",
    "sg:postcode":"34132",
    "sg:province":"Hessen",
    "wof:name":"Bernhardt Bauberatung Gmbh",
    "wof:placetype":"venue"
},
  "geometry": {"coordinates":[9.4203443527,51.286857605],"type":"Point"}
}