{
  "type": "Feature",
  "properties": {
    "iso:country":"DE",
    "sg:address":"Wurzacher Str. 61",
    "sg:city":"Bad Waldsee",
    "sg:phone":"+49 7524/2225",
    "sg:postcode":"88339",
    "sg:province":"Baden-W\u00fcrttemberg",
    "wof:name":"Karl Bauer Rechtsanwalt",
    "wof:placetype":"venue"
},
  "geometry": {"coordinates":[9.7598686218,47.9199104309],"type":"Point"}
}