{
  "type": "Feature",
  "properties": {
    "iso:country":"DE",
    "sg:address":"Bouraueler Str. 51",
    "sg:city":"Eitorf",
    "sg:phone":"+49 2243",
    "sg:postcode":"53783",
    "sg:province":"Nordrhein-Westfalen",
    "wof:name":"Ihr-geschenkeservice",
    "wof:placetype":"venue"
},
  "geometry": {"coordinates":[7.425523,50.779171],"type":"Point"}
}