{
  "type": "Feature",
  "properties": {
    "iso:country":"DE",
    "sg:address":"Cornetsstr. 12",
    "sg:city":"Melle",
    "sg:phone":"+49 5226/17536",
    "sg:postcode":"49328",
    "sg:province":"Niedersachsen",
    "wof:name":"Polster Und Leder M\u00f6bel-profi Handels- Gmbh",
    "wof:placetype":"venue"
},
  "geometry": {"coordinates":[8.4306430817,52.18126297],"type":"Point"}
}