{
  "type": "Feature",
  "properties": {
    "iso:country":"DE",
    "sg:address":"Kupferpassage",
    "sg:city":"Coesfeld",
    "sg:phone":"+49 2541/5451",
    "sg:postcode":"48653",
    "sg:province":"Nordrhein-Westfalen",
    "wof:name":"Benetton",
    "wof:placetype":"venue"
},
  "geometry": {"coordinates":[7.16567,51.944534],"type":"Point"}
}