{
  "type": "Feature",
  "properties": {
    "iso:country":"DE",
    "sg:address":"Freirodaer Weg 9-11",
    "sg:city":"Schkeuditz",
    "sg:postcode":"04435",
    "sg:province":"Sachsen",
    "wof:name":"Tlg Transport Und Logistik Gmbh",
    "wof:placetype":"venue"
},
  "geometry": {"coordinates":[12.2206296921,51.4036407471],"type":"Point"}
}