{
  "type": "Feature",
  "properties": {
    "iso:country":"DE",
    "sg:address":"August-Bebel-Str. 120",
    "sg:city":"F\u00fcrstenwalde",
    "sg:postcode":"15517",
    "sg:province":"Brandenburg",
    "wof:name":"Eberhard D\u00f6ring",
    "wof:placetype":"venue"
},
  "geometry": {"coordinates":[14.06973,52.349384],"type":"Point"}
}