{
  "type": "Feature",
  "properties": {
    "iso:country":"DE",
    "sg:address":"Kreuzberger Ring 56::",
    "sg:city":"Wiesbaden",
    "sg:postcode":"65205",
    "sg:province":"Hessen",
    "wof:name":"Commerz Netbusiness Ag",
    "wof:placetype":"venue"
},
  "geometry": {"coordinates":[8.68342,50.112041],"type":"Point"}
}