{
  "type": "Feature",
  "properties": {
    "iso:country":"DE",
    "sg:address":"Aschaffenburger Str. 85",
    "sg:city":"Aschaffenburg",
    "sg:phone":"+49 6021",
    "sg:postcode":"63743",
    "sg:province":"Bayern",
    "wof:name":"Grossteiledreherei Peter Blank",
    "wof:placetype":"venue"
},
  "geometry": {"coordinates":[9.202548027,49.9485931396],"type":"Point"}
}