{
  "type": "Feature",
  "properties": {
    "iso:country":"DE",
    "sg:address":"Am H\u00f6lzlein 18",
    "sg:city":"W\u00fcrzburg",
    "sg:phone":"+49 931/271132",
    "sg:postcode":"97076",
    "sg:province":"Bayern",
    "wof:name":"Manfred Weckert Architekt",
    "wof:placetype":"venue"
},
  "geometry": {"coordinates":[9.982067,49.803204],"type":"Point"}
}