{
  "type": "Feature",
  "properties": {
    "iso:country":"DE",
    "sg:address":"Vogelsgr\u00fcner Str. 20",
    "sg:city":"Auerbach",
    "sg:phone":"+49 3744/215041",
    "sg:postcode":"08209",
    "sg:province":"Sachsen",
    "wof:name":"Carola Sch\u00e4dlich",
    "wof:placetype":"venue"
},
  "geometry": {"coordinates":[12.4536113739,50.5050086975],"type":"Point"}
}