{
  "type": "Feature",
  "properties": {
    "iso:country":"DE",
    "sg:address":"Mittelweg 5",
    "sg:city":"Borken",
    "sg:phone":"+49 5682/2059",
    "sg:postcode":"34582",
    "sg:province":"Hessen",
    "wof:name":"Hess & B\u00fcse Verwaltung Gmbh",
    "wof:placetype":"venue"
},
  "geometry": {"coordinates":[9.277084,51.051941],"type":"Point"}
}