{
  "type": "Feature",
  "properties": {
    "iso:country":"DE",
    "sg:address":"Dantestr. 22",
    "sg:city":"Chemnitz",
    "sg:phone":"+49 371/73445",
    "sg:postcode":"09127",
    "sg:province":"Sachsen",
    "wof:name":"Knuth R\u00f6hnert",
    "wof:placetype":"venue"
},
  "geometry": {"coordinates":[12.9689159393,50.8158683777],"type":"Point"}
}