{
  "type": "Feature",
  "properties": {
    "iso:country":"DE",
    "sg:address":"Hinterstaufen",
    "sg:city":"Oberstaufen",
    "sg:phone":"+49 8386/2778",
    "sg:postcode":"87534",
    "sg:province":"Bayern",
    "wof:name":"Hubertusstuben",
    "wof:placetype":"venue"
},
  "geometry": {"coordinates":[10.0450239182,47.5513420105],"type":"Point"}
}