{
  "type": "Feature",
  "properties": {
    "iso:country":"DE",
    "sg:address":"Donauw\u00f6rther Str. 29",
    "sg:city":"Aichach",
    "sg:phone":"+49 8251/3028",
    "sg:postcode":"86551",
    "sg:province":"Bayern",
    "wof:name":"Kunstm\u00dchle Aichach Ag",
    "wof:placetype":"venue"
},
  "geometry": {"coordinates":[11.128159,48.462677],"type":"Point"}
}