{
  "type": "Feature",
  "properties": {
    "iso:country":"DE",
    "sg:address":"Menzinger Str. 44",
    "sg:city":"M\u00fcnchen",
    "sg:phone":"+49 89/1784212",
    "sg:postcode":"80638",
    "sg:province":"Bayern",
    "wof:name":"Die Ringelblume",
    "wof:placetype":"venue"
},
  "geometry": {"coordinates":[11.5046,48.164452],"type":"Point"}
}