{
  "type": "Feature",
  "properties": {
    "iso:country":"DE",
    "sg:address":"Meller Str. 226a",
    "sg:city":"Osnabr\u00fcck",
    "sg:phone":"+49 541/572254",
    "sg:postcode":"49082",
    "sg:province":"Niedersachsen",
    "wof:name":"Franz-josef Witte",
    "wof:placetype":"venue"
},
  "geometry": {"coordinates":[8.0744600296,52.2582130432],"type":"Point"}
}