{
  "type": "Feature",
  "properties": {
    "iso:country":"DE",
    "sg:address":"An Der Ihle 19",
    "sg:city":"Friedensau",
    "sg:phone":"+49 4939/219160",
    "sg:postcode":"39291",
    "sg:province":"Sachsen-Anhalt",
    "wof:name":"Theologische Hochschule Friedensau",
    "wof:placetype":"venue"
},
  "geometry": {"coordinates":[11.982329,52.211189],"type":"Point"}
}