{
  "type": "Feature",
  "properties": {
    "iso:country":"DE",
    "sg:address":"Koblenzer Str. 34",
    "sg:city":"Bad Ems",
    "sg:phone":"+49 2603/97950",
    "sg:postcode":"56130",
    "sg:province":"Rheinland-Pfalz",
    "wof:name":"Manfred Ebelh\u00e4user Steuerberater",
    "wof:placetype":"venue"
},
  "geometry": {"coordinates":[7.7106599808,50.3350791931],"type":"Point"}
}