{
  "type": "Feature",
  "properties": {
    "iso:country":"DE",
    "sg:address":"Voltmannstr. 105",
    "sg:city":"Bielefeld",
    "sg:phone":"+49 521/161415",
    "sg:postcode":"33619",
    "sg:province":"Nordrhein-Westfalen",
    "wof:name":"Wilhelm P\u00f6rtner",
    "wof:placetype":"venue"
},
  "geometry": {"coordinates":[8.5024194717,52.0418663025],"type":"Point"}
}