{
  "type": "Feature",
  "properties": {
    "iso:country":"DE",
    "sg:address":"Langer Steinweg 28",
    "sg:city":"Blomberg",
    "sg:phone":"+49 5235/2668",
    "sg:postcode":"32825",
    "sg:province":"Nordrhein-Westfalen",
    "wof:name":"Atilla",
    "wof:placetype":"venue"
},
  "geometry": {"coordinates":[9.092001,51.941765],"type":"Point"}
}