{
  "type": "Feature",
  "properties": {
    "iso:country":"DE",
    "sg:address":"Vor dem Dammtor 16",
    "sg:city":"Hornburg",
    "sg:phone":"+49 5334/94900",
    "sg:postcode":"38315",
    "sg:province":"Niedersachsen",
    "wof:name":"Drk Sozialstation",
    "wof:placetype":"venue"
},
  "geometry": {"coordinates":[10.601583,52.030598],"type":"Point"}
}