{
  "type": "Feature",
  "properties": {
    "iso:country":"DE",
    "sg:address":"Resen\u00f6dstr. 1",
    "sg:city":"Gerzen",
    "sg:phone":"+49 8744/468",
    "sg:postcode":"84175",
    "sg:province":"Bayern",
    "wof:name":"Franz K\u00f6nigbauer",
    "wof:placetype":"venue"
},
  "geometry": {"coordinates":[12.425077,48.506702],"type":"Point"}
}