{
  "type": "Feature",
  "properties": {
    "iso:country":"DE",
    "sg:address":"Am Rosenhain 3",
    "sg:city":"Gudensberg",
    "sg:postcode":"34281",
    "sg:province":"Hessen",
    "wof:name":"Tk Media Ag",
    "wof:placetype":"venue"
},
  "geometry": {"coordinates":[9.356253624,51.161567688],"type":"Point"}
}