{
  "type": "Feature",
  "properties": {
    "iso:country":"DE",
    "sg:address":"Altenberger Str. 14",
    "sg:city":"Dippoldiswalde",
    "sg:phone":"+49 3504/614253",
    "sg:postcode":"01744",
    "sg:province":"Sachsen",
    "wof:name":"Brigitte Schr\u00f6der",
    "wof:placetype":"venue"
},
  "geometry": {"coordinates":[13.6671285629,50.8927345276],"type":"Point"}
}