{
  "type": "Feature",
  "properties": {
    "iso:country":"DE",
    "sg:address":"Obergasse 2",
    "sg:city":"Worms",
    "sg:phone":"+49 6241/75651",
    "sg:postcode":"67549",
    "sg:province":"Rheinland-Pfalz",
    "wof:name":"Restaurant Zur Sch\u00f6nen Aussicht",
    "wof:placetype":"venue"
},
  "geometry": {"coordinates":[8.333407402,49.6423377991],"type":"Point"}
}