{
  "type": "Feature",
  "properties": {
    "iso:country":"DE",
    "sg:address":"Vluyner S\u00fcdring 73",
    "sg:city":"Neukirchen-Vluyn",
    "sg:phone":"+49 2845/1655",
    "sg:postcode":"47506",
    "sg:province":"Nordrhein-Westfalen",
    "wof:name":"Hotel-restaurant Vluyner Stuben",
    "wof:placetype":"venue"
},
  "geometry": {"coordinates":[6.529654026,51.4354248047],"type":"Point"}
}