{
  "type": "Feature",
  "properties": {
    "iso:country":"DE",
    "sg:address":"Schwanheimer Str. 42",
    "sg:city":"Frankfurt",
    "sg:phone":"+49 69/6708893",
    "sg:postcode":"60528",
    "sg:province":"Hessen",
    "wof:name":"Volkmar Heimann",
    "wof:placetype":"venue"
},
  "geometry": {"coordinates":[8.6427221298,50.0881843567],"type":"Point"}
}