{
  "type": "Feature",
  "properties": {
    "iso:country":"DE",
    "sg:address":"Kurf\u00fcrstenstr. 2",
    "sg:city":"Ludwigsburg",
    "sg:phone":"+49 7141/978361",
    "sg:postcode":"71636",
    "sg:province":"Baden-W\u00fcrttemberg",
    "wof:name":"Rietzke-immobilien",
    "wof:placetype":"venue"
},
  "geometry": {"coordinates":[9.1796331406,48.8974494934],"type":"Point"}
}