{
  "type": "Feature",
  "properties": {
    "iso:country":"DE",
    "sg:address":"Brahmsstr. 12",
    "sg:city":"Regensburg",
    "sg:phone":"+49 941/74260",
    "sg:postcode":"93053",
    "sg:province":"Bayern",
    "wof:name":"Druckluft Bauer Gmbh",
    "wof:placetype":"venue"
},
  "geometry": {"coordinates":[12.10726,49.005264],"type":"Point"}
}