{
  "type": "Feature",
  "properties": {
    "iso:country":"DE",
    "sg:address":"Marktstr 8::",
    "sg:city":"Cologne",
    "sg:postcode":"50968",
    "sg:province":"Nordrhein-Westfalen",
    "wof:name":"Stiftung Zur F\u00f6rderung Der Forschung F\u00fcr Die Gewerbliche Wirtschaft",
    "wof:placetype":"venue"
},
  "geometry": {"coordinates":[6.955065,50.941654],"type":"Point"}
}