{
  "type": "Feature",
  "properties": {
    "iso:country":"DE",
    "sg:address":"Wassenbergstr. 38",
    "sg:city":"Emmerich",
    "sg:phone":"+49 2822/5764",
    "sg:postcode":"46446",
    "sg:province":"Nordrhein-Westfalen",
    "wof:name":"Bernhard Ricken",
    "wof:placetype":"venue"
},
  "geometry": {"coordinates":[6.253423,51.837215],"type":"Point"}
}