{
  "type": "Feature",
  "properties": {
    "iso:country":"DE",
    "sg:address":"Heimerdinger Str. 39",
    "sg:city":"Ditzingen",
    "sg:phone":"+49 7156/39713",
    "sg:postcode":"71254",
    "sg:province":"Baden-W\u00fcrttemberg",
    "wof:name":"Kurt Deeg",
    "wof:placetype":"venue"
},
  "geometry": {"coordinates":[9.03533,48.837688],"type":"Point"}
}