{
  "type": "Feature",
  "properties": {
    "iso:country":"DE",
    "sg:address":"K\u00e4lblesrainweg 99",
    "sg:city":"Aalen",
    "sg:phone":"+49 7361/969484",
    "sg:postcode":"73430",
    "sg:province":"Baden-W\u00fcrttemberg",
    "wof:name":"Schnaeppchenjagd.de Gmbh",
    "wof:placetype":"venue"
},
  "geometry": {"coordinates":[10.0918207169,48.8511428833],"type":"Point"}
}