{
  "type": "Feature",
  "properties": {
    "iso:country":"DE",
    "sg:address":"Alexander-Puschkin-Platz 1",
    "sg:city":"Riesa",
    "sg:phone":"+49 3525/735341",
    "sg:postcode":"01587",
    "sg:province":"Sachsen",
    "wof:name":"Manfred Zacher",
    "wof:placetype":"venue"
},
  "geometry": {"coordinates":[13.3003702164,51.3041801453],"type":"Point"}
}