{
  "type": "Feature",
  "properties": {
    "iso:country":"DE",
    "sg:address":"Werler Str. 63",
    "sg:city":"Herford",
    "sg:phone":"+49 5221/70378",
    "sg:postcode":"32052",
    "sg:province":"Nordrhein-Westfalen",
    "wof:name":"A. V\u00f6geding & K. Bollhorst",
    "wof:placetype":"venue"
},
  "geometry": {"coordinates":[8.6681089401,52.08177948],"type":"Point"}
}