{
  "type": "Feature",
  "properties": {
    "iso:country":"DE",
    "sg:address":"Elisabethstr. 23",
    "sg:city":"Frechen",
    "sg:phone":"+49 2234/99660",
    "sg:postcode":"50226",
    "sg:province":"Nordrhein-Westfalen",
    "wof:name":"Terramedia Kommunikation & Werbung Gmbh",
    "wof:placetype":"venue"
},
  "geometry": {"coordinates":[6.8205919266,50.9136276245],"type":"Point"}
}