{
  "type": "Feature",
  "properties": {
    "iso:country":"DE",
    "sg:address":"B\u00e4ckerstr. 21",
    "sg:city":"Treuenbrietzen",
    "sg:phone":"+49 33748/15348",
    "sg:postcode":"14929",
    "sg:province":"Brandenburg",
    "wof:name":"Karl Ma\u00dfwig",
    "wof:placetype":"venue"
},
  "geometry": {"coordinates":[12.8712301254,52.0951766968],"type":"Point"}
}