{
  "type": "Feature",
  "properties": {
    "iso:country":"DE",
    "sg:address":"Heideweg 7",
    "sg:city":"Papenbruch",
    "sg:phone":"+49 3394/441200",
    "sg:postcode":"16909",
    "sg:province":"Brandenburg",
    "wof:name":"Witte",
    "wof:placetype":"venue"
},
  "geometry": {"coordinates":[12.427475,53.125401],"type":"Point"}
}