{
  "type": "Feature",
  "properties": {
    "iso:country":"DE",
    "sg:address":"Am Kurpark 17 a",
    "sg:city":"Garmisch-Partenkirchen",
    "sg:phone":"+49 8821/3308",
    "sg:postcode":"82467",
    "sg:province":"Bayern",
    "wof:name":"Bavaria-grill",
    "wof:placetype":"venue"
},
  "geometry": {"coordinates":[11.0898790359,47.4935951233],"type":"Point"}
}