{
  "type": "Feature",
  "properties": {
    "iso:country":"DE",
    "sg:address":"Lindwurmstr. 159",
    "sg:city":"M\u00fcnchen",
    "sg:phone":"+49 89/592337",
    "sg:postcode":"80337",
    "sg:province":"Bayern",
    "wof:name":"Pflege Pur",
    "wof:placetype":"venue"
},
  "geometry": {"coordinates":[11.550034,48.125137],"type":"Point"}
}