{
  "type": "Feature",
  "properties": {
    "iso:country":"DE",
    "sg:address":"Pleintinger Str. 10",
    "sg:city":"Vilshofen",
    "sg:phone":"+49 8549/1262",
    "sg:postcode":"94474",
    "sg:province":"Bayern",
    "wof:name":"Hermann Unertl",
    "wof:placetype":"venue"
},
  "geometry": {"coordinates":[13.194676,48.593548],"type":"Point"}
}