{
  "type": "Feature",
  "properties": {
    "iso:country":"DE",
    "sg:address":"Leckingser Str 201",
    "sg:city":"Iserlohn",
    "sg:phone":"+49 7524/5561",
    "sg:postcode":"58640",
    "sg:province":"Nordrhein-Westfalen",
    "wof:name":"Peter Oberm\u00fcller",
    "wof:placetype":"venue"
},
  "geometry": {"coordinates":[9.755546,47.933937],"type":"Point"}
}