{
  "type": "Feature",
  "properties": {
    "iso:country":"DE",
    "sg:address":"C\u00e4cilienweg 22",
    "sg:city":"Straelen",
    "sg:phone":"+49 2839/712733",
    "sg:postcode":"47638",
    "sg:province":"Nordrhein-Westfalen",
    "wof:name":"K.-h. Verheyen",
    "wof:placetype":"venue"
},
  "geometry": {"coordinates":[6.2504839897,51.3880615234],"type":"Point"}
}