{
  "type": "Feature",
  "properties": {
    "iso:country":"DE",
    "sg:address":"Friedrich-Fleischhauer-Str. 33",
    "sg:city":"Nachterstedt",
    "sg:phone":"+49 34741/6243",
    "sg:postcode":"06469",
    "sg:province":"Sachsen-Anhalt",
    "wof:name":"B. Teschke",
    "wof:placetype":"venue"
},
  "geometry": {"coordinates":[11.3321228027,51.8014068604],"type":"Point"}
}