{
  "type": "Feature",
  "properties": {
    "iso:country":"DE",
    "sg:address":"Kruppstr. 1-7",
    "sg:city":"Ditzingen",
    "sg:phone":"+49 7156/7068",
    "sg:postcode":"71254",
    "sg:province":"Baden-W\u00fcrttemberg",
    "wof:name":"F & Me Schwab Flachdach- Und Montagebau Gmbh & Co. Kg",
    "wof:placetype":"venue"
},
  "geometry": {"coordinates":[9.0777225494,48.8198471069],"type":"Point"}
}