{
  "type": "Feature",
  "properties": {
    "iso:country":"DE",
    "sg:address":"Ro\u00dfhaustr. 69",
    "sg:city":"Stuttgart",
    "sg:phone":"+49 711/765014",
    "sg:postcode":"70597",
    "sg:province":"Baden-W\u00fcrttemberg",
    "wof:name":"Santec Elektrische Ger\u00e4te F\u00fcr Gesundheitsvorsorge",
    "wof:placetype":"venue"
},
  "geometry": {"coordinates":[9.177222,48.74276],"type":"Point"}
}