{
  "type": "Feature",
  "properties": {
    "iso:country":"DE",
    "sg:address":"Hauptstr. 108",
    "sg:city":"Berlin",
    "sg:phone":"+49 30/9123670",
    "sg:postcode":"13158",
    "sg:province":"Berlin",
    "wof:name":"Ingenieurb\u00fcro Schacher",
    "wof:placetype":"venue"
},
  "geometry": {"coordinates":[13.374836,52.596794],"type":"Point"}
}