{
  "type": "Feature",
  "properties": {
    "iso:country":"DE",
    "sg:address":"Tangstedter Weg 44",
    "sg:city":"Norderstedt",
    "sg:phone":"+49 40/5243087",
    "sg:postcode":"22851",
    "sg:province":"Schleswig-Holstein",
    "wof:name":"Umwelt-technics-nord Gmbh",
    "wof:placetype":"venue"
},
  "geometry": {"coordinates":[10.0575523376,53.7045593262],"type":"Point"}
}