{
  "type": "Feature",
  "properties": {
    "iso:country":"DE",
    "sg:address":"Sportgel\u00e4nde",
    "sg:city":"Stockstadt",
    "sg:phone":"+49 6158/86320",
    "sg:postcode":"64589",
    "sg:province":"Hessen",
    "wof:name":"Tennish\u00fctte",
    "wof:placetype":"venue"
},
  "geometry": {"coordinates":[8.4670600891,49.8100395203],"type":"Point"}
}