{
  "type": "Feature",
  "properties": {
    "iso:country":"DE",
    "sg:address":"Am Markt 23",
    "sg:city":"Stadthagen",
    "sg:phone":"+49 5721/5000",
    "sg:postcode":"31655",
    "sg:province":"Niedersachsen",
    "wof:name":"Schwarzer Adler",
    "wof:placetype":"venue"
},
  "geometry": {"coordinates":[9.2053928375,52.3235778809],"type":"Point"}
}