{
  "type": "Feature",
  "properties": {
    "iso:country":"DE",
    "sg:address":"Rathausstr. 35",
    "sg:city":"Neckarsulm",
    "sg:phone":"+49 7132/2519",
    "sg:postcode":"74172",
    "sg:province":"Baden-W\u00fcrttemberg",
    "wof:name":"H. Gurr",
    "wof:placetype":"venue"
},
  "geometry": {"coordinates":[9.228545,49.190575],"type":"Point"}
}