{
  "type": "Feature",
  "properties": {
    "iso:country":"DE",
    "sg:address":"Liesegangstr. 36",
    "sg:city":"Kleve",
    "sg:phone":"+49 2821/25292",
    "sg:postcode":"47533",
    "sg:province":"Nordrhein-Westfalen",
    "wof:name":"K. Scharff",
    "wof:placetype":"venue"
},
  "geometry": {"coordinates":[6.130495,51.777039],"type":"Point"}
}