{
  "type": "Feature",
  "properties": {
    "iso:country":"DE",
    "sg:address":"Auf der H\u00f6he",
    "sg:city":"Reichshof",
    "sg:phone":"+49 2265/354",
    "sg:postcode":"51580",
    "sg:province":"Nordrhein-Westfalen",
    "wof:name":"W. K\u00f6ster",
    "wof:placetype":"venue"
},
  "geometry": {"coordinates":[7.5987148285,50.9880256653],"type":"Point"}
}