{
  "type": "Feature",
  "properties": {
    "iso:country":"DE",
    "sg:address":"Wilhelm-Raabe-Str. 2",
    "sg:city":"Braunschweig",
    "sg:phone":"+49 531/77356",
    "sg:postcode":"38104",
    "sg:province":"Niedersachsen",
    "wof:name":"Michael Muschalla Architekt",
    "wof:placetype":"venue"
},
  "geometry": {"coordinates":[10.552279,52.261269],"type":"Point"}
}