{
  "type": "Feature",
  "properties": {
    "iso:country":"DE",
    "sg:address":"Hans-Weber-Str. 9",
    "sg:city":"Marktoberdorf",
    "sg:phone":"+49 8342/2884",
    "sg:postcode":"87616",
    "sg:province":"Bayern",
    "wof:name":"Otto H. Simm Gmbh",
    "wof:placetype":"venue"
},
  "geometry": {"coordinates":[10.616793,47.78548],"type":"Point"}
}