{
  "type": "Feature",
  "properties": {
    "iso:country":"DE",
    "sg:address":"Petersweg 37",
    "sg:city":"Freilassing",
    "sg:phone":"+49 8654/67203",
    "sg:postcode":"83395",
    "sg:province":"Bayern",
    "wof:name":"J. Armstorfer",
    "wof:placetype":"venue"
},
  "geometry": {"coordinates":[12.982716,47.848831],"type":"Point"}
}