{
  "type": "Feature",
  "properties": {
    "iso:country":"DE",
    "sg:address":"H\u00f6bing 17",
    "sg:city":"Arnbruck",
    "sg:phone":"+49 9945/1625",
    "sg:postcode":"93471",
    "sg:province":"Bayern",
    "wof:name":"Pension Auguste Tremmel",
    "wof:placetype":"venue"
},
  "geometry": {"coordinates":[12.9871139526,49.1437072754],"type":"Point"}
}