{
  "type": "Feature",
  "properties": {
    "iso:country":"DE",
    "sg:address":"Meesmannstr. 43",
    "sg:city":"Bochum",
    "sg:phone":"+49 234/903920",
    "sg:postcode":"44807",
    "sg:province":"Nordrhein-Westfalen",
    "wof:name":"Befeld Pr\u00e4zisionstechnik - Qualit\u00e4tsmanagment",
    "wof:placetype":"venue"
},
  "geometry": {"coordinates":[7.2054982185,51.5142173767],"type":"Point"}
}