{
  "type": "Feature",
  "properties": {
    "iso:country":"DE",
    "sg:address":"Sienlandweg 10",
    "sg:city":"Edewecht",
    "sg:phone":"+49 4405/939476",
    "sg:postcode":"26188",
    "sg:province":"Niedersachsen",
    "wof:name":"Junker & Meves Kanalsanierungstechnik Gmbh",
    "wof:placetype":"venue"
},
  "geometry": {"coordinates":[7.9250679016,53.1208000183],"type":"Point"}
}