{
  "type": "Feature",
  "properties": {
    "iso:country":"DE",
    "sg:address":"Dorfelder Str. 18",
    "sg:city":"Karben",
    "sg:phone":"+49 6039/3608",
    "sg:postcode":"61184",
    "sg:province":"Hessen",
    "wof:name":"Walter Dewitz",
    "wof:placetype":"venue"
},
  "geometry": {"coordinates":[8.793051,50.214081],"type":"Point"}
}