{
  "type": "Feature",
  "properties": {
    "iso:country":"DE",
    "sg:address":"Meiereistr 6",
    "sg:city":"Schwarzenbek",
    "sg:phone":"+49 4151/2268",
    "sg:postcode":"21493",
    "sg:province":"Schleswig-Holstein",
    "wof:name":"F. Quaack M\u00f6belwerkst\u00e4tten Gmbh & Co Kg",
    "wof:placetype":"venue"
},
  "geometry": {"coordinates":[10.489371,53.501564],"type":"Point"}
}