{
  "type": "Feature",
  "properties": {
    "iso:country":"DE",
    "sg:address":"Hundsburgallee 12",
    "sg:city":"Rostock",
    "sg:phone":"+49 381/7697409",
    "sg:postcode":"18069",
    "sg:province":"Mecklenburg-Vorpommern",
    "wof:name":"Hanseatische Gesellschaft F\u00fcr Bildungs\u00f6konomie Mbh",
    "wof:placetype":"venue"
},
  "geometry": {"coordinates":[12.073614,54.120701],"type":"Point"}
}