{
  "type": "Feature",
  "properties": {
    "iso:country":"DE",
    "sg:address":"Rathauscenter",
    "sg:city":"Heiligenhaus",
    "sg:phone":"+49 2056/69376",
    "sg:postcode":"42579",
    "sg:province":"Nordrhein-Westfalen",
    "wof:name":"Wanners Biereck",
    "wof:placetype":"venue"
},
  "geometry": {"coordinates":[6.9715452194,51.3268280029],"type":"Point"}
}