{
  "type": "Feature",
  "properties": {
    "iso:country":"DE",
    "sg:address":"Friesenheimer Str. 31",
    "sg:city":"Ludwigshafen",
    "sg:phone":"+49 621/659060",
    "sg:postcode":"67069",
    "sg:province":"Rheinland-Pfalz",
    "wof:name":"Helmut Lips Ingenieur",
    "wof:placetype":"venue"
},
  "geometry": {"coordinates":[8.4066057205,49.517162323],"type":"Point"}
}