{
  "type": "Feature",
  "properties": {
    "iso:country":"DE",
    "sg:address":"Goethestr. 73",
    "sg:city":"Berlin",
    "sg:phone":"+49 30/3110950",
    "sg:postcode":"10625",
    "sg:province":"Berlin",
    "wof:name":"Sta Travel",
    "wof:placetype":"venue"
},
  "geometry": {"coordinates":[13.3176317215,52.5088043213],"type":"Point"}
}