{
  "type": "Feature",
  "properties": {
    "iso:country":"DE",
    "sg:address":"Rebbelstieg 67",
    "sg:city":"Wyk",
    "sg:phone":"+49 4681/2733",
    "sg:postcode":"25938",
    "sg:province":"Schleswig-Holstein",
    "wof:name":"Gerret Arfsten",
    "wof:placetype":"venue"
},
  "geometry": {"coordinates":[8.557429,54.693523],"type":"Point"}
}