{
  "type": "Feature",
  "properties": {
    "iso:country":"DE",
    "sg:address":"Rosenheimer Str. 88",
    "sg:city":"Brannenburg",
    "sg:postcode":"83098",
    "sg:province":"Bayern",
    "wof:name":"Steinbeis Gmbh & Co. Beteiligungsverwaltung Kg",
    "wof:placetype":"venue"
},
  "geometry": {"coordinates":[12.10309,47.741589],"type":"Point"}
}