{
  "type": "Feature",
  "properties": {
    "iso:country":"DE",
    "sg:address":"Gutenbergstr. 197",
    "sg:city":"Krefeld",
    "sg:phone":"+49 2151/773202",
    "sg:postcode":"47798",
    "sg:province":"Nordrhein-Westfalen",
    "wof:name":"Insel Tank",
    "wof:placetype":"venue"
},
  "geometry": {"coordinates":[6.5464658737,51.3287658691],"type":"Point"}
}