{
  "type": "Feature",
  "properties": {
    "iso:country":"DE",
    "sg:address":"Pfizerstr. 8",
    "sg:city":"Stuttgart",
    "sg:phone":"+49 711/239390",
    "sg:postcode":"70184",
    "sg:province":"Baden-W\u00fcrttemberg",
    "wof:name":"Weller Und Herz Rechtsanw\u00e4lte",
    "wof:placetype":"venue"
},
  "geometry": {"coordinates":[9.1898031235,48.7740707397],"type":"Point"}
}