{
  "type": "Feature",
  "properties": {
    "iso:country":"DE",
    "sg:address":"Gutenbergstr. 63a",
    "sg:city":"K\u00f6ln",
    "sg:postcode":"50823",
    "sg:province":"Nordrhein-Westfalen",
    "wof:name":"Norm-4 Agentur F\u00fcr Neue Medien Gmbh",
    "wof:placetype":"venue"
},
  "geometry": {"coordinates":[6.9270019531,50.9504089355],"type":"Point"}
}