{
  "type": "Feature",
  "properties": {
    "iso:country":"DE",
    "sg:address":"Kesselenstr. 1",
    "sg:city":"Ellhofen",
    "sg:phone":"+49 7134/18783",
    "sg:postcode":"74248",
    "sg:province":"Baden-W\u00fcrttemberg",
    "wof:name":"Wilhelm Spr\u00f6sser",
    "wof:placetype":"venue"
},
  "geometry": {"coordinates":[9.32384,49.145378],"type":"Point"}
}