{
  "type": "Feature",
  "properties": {
    "iso:country":"DE",
    "sg:address":"Springer Str. 21",
    "sg:city":"Altena",
    "sg:phone":"+49 2352/75674",
    "sg:postcode":"58762",
    "sg:province":"Nordrhein-Westfalen",
    "wof:name":"Reinhard Appelhaus",
    "wof:placetype":"venue"
},
  "geometry": {"coordinates":[7.7303228378,51.3024177551],"type":"Point"}
}