{
  "type": "Feature",
  "properties": {
    "iso:country":"DE",
    "sg:address":"Bahnhofstr. 30",
    "sg:city":"Gr\u00e4fenhainichen",
    "sg:phone":"+49 34953/23485",
    "sg:postcode":"06773",
    "sg:province":"Sachsen-Anhalt",
    "wof:name":"Werner M\u00fcller",
    "wof:placetype":"venue"
},
  "geometry": {"coordinates":[12.458814,51.726414],"type":"Point"}
}