{
  "type": "Feature",
  "properties": {
    "iso:country":"DE",
    "sg:address":"Hansering 110",
    "sg:city":"Hildesheim",
    "sg:phone":"+49 5121/868603",
    "sg:postcode":"31141",
    "sg:province":"Niedersachsen",
    "wof:name":"Reiseb\u00fcro Auf Der H\u00f6he Inh. Volksbank Heinde-sehlem",
    "wof:placetype":"venue"
},
  "geometry": {"coordinates":[9.9857416153,52.1243476868],"type":"Point"}
}