{
  "type": "Feature",
  "properties": {
    "iso:country":"DE",
    "sg:address":"Papenreye 11",
    "sg:city":"Hamburg",
    "sg:phone":"+49 40/580022",
    "sg:postcode":"22453",
    "sg:province":"Hamburg",
    "wof:name":"Nexum Finanzdienstleistungs- Gesellschaft Br",
    "wof:placetype":"venue"
},
  "geometry": {"coordinates":[9.959598,53.612457],"type":"Point"}
}