{
  "type": "Feature",
  "properties": {
    "iso:country":"DE",
    "sg:address":"Karolinenbr\u00fccke 1",
    "sg:city":"Eisenach",
    "sg:phone":"+49 3691/876750",
    "sg:postcode":"99817",
    "sg:province":"Th\u00fcringen",
    "wof:name":"P. Hartung",
    "wof:placetype":"venue"
},
  "geometry": {"coordinates":[10.336044,50.984619],"type":"Point"}
}