{
  "type": "Feature",
  "properties": {
    "iso:country":"DE",
    "sg:address":"Weinbergstr. 7",
    "sg:city":"Zotzenheim",
    "sg:phone":"+49 6701/7724",
    "sg:postcode":"55576",
    "sg:province":"Rheinland-Pfalz",
    "wof:name":"H.-w. Sch\u00e4fer",
    "wof:placetype":"venue"
},
  "geometry": {"coordinates":[7.9732160568,49.8730392456],"type":"Point"}
}