{
  "type": "Feature",
  "properties": {
    "iso:country":"DE",
    "sg:address":"Wismarsche Str. 30",
    "sg:city":"Grevesm\u00fchlen",
    "sg:phone":"+49 3881/79060",
    "sg:postcode":"23936",
    "sg:province":"Mecklenburg-Vorpommern",
    "wof:name":"Compeg Hard- Und Software- Vertriebs Gmbh",
    "wof:placetype":"venue"
},
  "geometry": {"coordinates":[11.1883897781,53.8645553589],"type":"Point"}
}