{
  "type": "Feature",
  "properties": {
    "iso:country":"DE",
    "sg:address":"Dammweg 20",
    "sg:city":"Rheinberg",
    "sg:phone":"+49 2843/92990",
    "sg:postcode":"47495",
    "sg:province":"Nordrhein-Westfalen",
    "wof:name":"D\u00fcmmen Holding Gmbh",
    "wof:placetype":"venue"
},
  "geometry": {"coordinates":[6.666132,51.546253],"type":"Point"}
}