{
  "type": "Feature",
  "properties": {
    "iso:country":"DE",
    "sg:address":"Langenhahner Str. 24",
    "sg:city":"Westerburg",
    "sg:phone":"+49 2663/8524",
    "sg:postcode":"56457",
    "sg:province":"Rheinland-Pfalz",
    "wof:name":"J. Bollmann",
    "wof:placetype":"venue"
},
  "geometry": {"coordinates":[7.962339,50.562893],"type":"Point"}
}