{
  "type": "Feature",
  "properties": {
    "iso:country":"DE",
    "sg:address":"Im Feld 2",
    "sg:city":"Alpen",
    "sg:phone":"+49 2802/3660",
    "sg:postcode":"46519",
    "sg:province":"Nordrhein-Westfalen",
    "wof:name":"Johannes Goossens",
    "wof:placetype":"venue"
},
  "geometry": {"coordinates":[6.465056,51.616852],"type":"Point"}
}