{
  "type": "Feature",
  "properties": {
    "iso:country":"DE",
    "sg:address":"Wegener Str. 2",
    "sg:city":"Wandlitz",
    "sg:phone":"+49 33397/21203",
    "sg:postcode":"16348",
    "sg:province":"Brandenburg",
    "wof:name":"Luise Moegelin",
    "wof:placetype":"venue"
},
  "geometry": {"coordinates":[13.4438428879,52.7483825684],"type":"Point"}
}