{
  "type": "Feature",
  "properties": {
    "iso:country":"DE",
    "sg:address":"Grundstr. 2",
    "sg:city":"Neuried",
    "sg:phone":"+49 89/7594546",
    "sg:postcode":"82061",
    "sg:province":"Bayern",
    "wof:name":"Gg Gastec E. K.",
    "wof:placetype":"venue"
},
  "geometry": {"coordinates":[11.4625902176,48.0897102356],"type":"Point"}
}