{
  "type": "Feature",
  "properties": {
    "iso:country":"DE",
    "sg:address":"Lachenhauwg 8:: Mittelstadt",
    "sg:city":"Reutlingen",
    "sg:phone":"+49 4971/2797640",
    "sg:postcode":"72766",
    "sg:province":"Baden-W\u00fcrttemberg",
    "wof:name":"Grossb\u00c4ckerei",
    "wof:placetype":"venue"
},
  "geometry": {"coordinates":[9.225667,48.518024],"type":"Point"}
}