{
  "type": "Feature",
  "properties": {
    "iso:country":"DE",
    "sg:address":"Professor-Wagner-Str. 5",
    "sg:city":"Friedrichsdorf",
    "sg:phone":"+49 6172/676100",
    "sg:postcode":"61381",
    "sg:province":"Hessen",
    "wof:name":"Altintas & K\u00fchn Gmbh",
    "wof:placetype":"venue"
},
  "geometry": {"coordinates":[8.641009,50.255787],"type":"Point"}
}