{
  "type": "Feature",
  "properties": {
    "iso:country":"DE",
    "sg:address":"Am Hasselt 5 b",
    "sg:city":"Bad Bramstedt",
    "sg:phone":"+49 4192/87940",
    "sg:postcode":"24576",
    "sg:province":"Schleswig-Holstein",
    "wof:name":"Easynet Datenver- Arbeitungs- Gmbh",
    "wof:placetype":"venue"
},
  "geometry": {"coordinates":[9.8963928223,53.9315986633],"type":"Point"}
}