{
  "type": "Feature",
  "properties": {
    "iso:country":"DE",
    "sg:address":"Hauptstr. 20",
    "sg:city":"W\u00f6rth",
    "sg:phone":"+49 9482/1725",
    "sg:postcode":"93086",
    "sg:province":"Bayern",
    "wof:name":"H. Hahn",
    "wof:placetype":"venue"
},
  "geometry": {"coordinates":[12.451731,48.989399],"type":"Point"}
}