{
  "type": "Feature",
  "properties": {
    "iso:country":"DE",
    "sg:address":"Am Kolbenstein 6",
    "sg:city":"Neustadt",
    "sg:phone":"+49 6327/5847",
    "sg:postcode":"67435",
    "sg:province":"Rheinland-Pfalz",
    "wof:name":"Doris Birli Masseurin",
    "wof:placetype":"venue"
},
  "geometry": {"coordinates":[8.25129,49.306],"type":"Point"}
}