{
  "type": "Feature",
  "properties": {
    "iso:country":"DE",
    "sg:address":"Bebericher Str. 337",
    "sg:city":"Viersen",
    "sg:phone":"+49 2162/15651",
    "sg:postcode":"41748",
    "sg:province":"Nordrhein-Westfalen",
    "wof:name":"Paul-g\u00fcnter H\u00fctter",
    "wof:placetype":"venue"
},
  "geometry": {"coordinates":[6.386586,51.22625],"type":"Point"}
}