{
  "type": "Feature",
  "properties": {
    "iso:country":"DE",
    "sg:address":"Gracht 3",
    "sg:city":"M\u00f6nchengladbach",
    "sg:phone":"+49 2166/44033",
    "sg:postcode":"41236",
    "sg:province":"Nordrhein-Westfalen",
    "wof:name":"Dieter Pauly",
    "wof:placetype":"venue"
},
  "geometry": {"coordinates":[6.4481301308,51.1668548584],"type":"Point"}
}