{
  "type": "Feature",
  "properties": {
    "iso:country":"DE",
    "sg:address":"Beethovenstr. 7",
    "sg:city":"Hannover",
    "sg:phone":"+49 511/9245563",
    "sg:postcode":"30449",
    "sg:province":"Niedersachsen",
    "wof:name":"Bfd Gmbh B\u00fcro F\u00fcr Dokumentation",
    "wof:placetype":"venue"
},
  "geometry": {"coordinates":[9.7090940475,52.3681144714],"type":"Point"}
}