{
  "type": "Feature",
  "properties": {
    "iso:country":"DE",
    "sg:address":"Bockwitzer Str. 69",
    "sg:city":"Lauchhammer",
    "sg:phone":"+49 3574/760146",
    "sg:postcode":"01979",
    "sg:province":"Brandenburg",
    "wof:name":"Erich Becker Steuerberater",
    "wof:placetype":"venue"
},
  "geometry": {"coordinates":[13.744099617,51.4812278748],"type":"Point"}
}