{
  "type": "Feature",
  "properties": {
    "iso:country":"DE",
    "sg:address":"M\u00fcllerstr. 26",
    "sg:city":"Aschaffenburg",
    "sg:phone":"+49 6021/4030",
    "sg:postcode":"63741",
    "sg:province":"Bayern",
    "wof:name":"Dre\u00dfler Bau Gmbh",
    "wof:placetype":"venue"
},
  "geometry": {"coordinates":[9.135643959,49.9826850891],"type":"Point"}
}