{
  "type": "Feature",
  "properties": {
    "iso:country":"DE",
    "sg:address":"Hauptstr. 8",
    "sg:city":"Zirndorf",
    "sg:phone":"+49 911/603006",
    "sg:postcode":"90513",
    "sg:province":"Bayern",
    "wof:name":"Joachim Kranich",
    "wof:placetype":"venue"
},
  "geometry": {"coordinates":[10.9554386139,49.4418487549],"type":"Point"}
}