{
  "type": "Feature",
  "properties": {
    "iso:country":"DE",
    "sg:address":"Wasserstr 23",
    "sg:city":"Offenburg",
    "sg:phone":"+49 781/969833",
    "sg:postcode":"77652",
    "sg:province":"Baden-W\u00fcrttemberg",
    "wof:name":"Wehrle Gmbh",
    "wof:placetype":"venue"
},
  "geometry": {"coordinates":[7.935061,48.471054],"type":"Point"}
}