{
  "type": "Feature",
  "properties": {
    "iso:country":"DE",
    "sg:address":"Panoramastr. 43",
    "sg:city":"Horb",
    "sg:phone":"+49 7451/6948",
    "sg:postcode":"72160",
    "sg:province":"Baden-W\u00fcrttemberg",
    "wof:name":"Josef Riedhammer Ingenieur",
    "wof:placetype":"venue"
},
  "geometry": {"coordinates":[8.6828098297,48.4442481995],"type":"Point"}
}