{
  "type": "Feature",
  "properties": {
    "iso:country":"DE",
    "sg:address":"Hauptstr. 84",
    "sg:city":"Bad Saulgau",
    "sg:phone":"+49 7581/1517",
    "sg:postcode":"88348",
    "sg:province":"Baden-W\u00fcrttemberg",
    "wof:name":"Oechsle Kleinpreis Gmbh",
    "wof:placetype":"venue"
},
  "geometry": {"coordinates":[9.500763,48.016247],"type":"Point"}
}