{
  "type": "Feature",
  "properties": {
    "iso:country":"DE",
    "sg:address":"Gerlindeweg 28",
    "sg:city":"Berlin",
    "sg:postcode":"13505",
    "sg:province":"Berlin",
    "wof:name":"Rum\u00e4nisch-orthodoxe Kirchengemeinde E. V.",
    "wof:placetype":"venue"
},
  "geometry": {"coordinates":[13.2296133041,52.5755157471],"type":"Point"}
}