{
  "type": "Feature",
  "properties": {
    "iso:country":"DE",
    "sg:address":"Kurf\u00fcrst-Heinrich-Str. 47",
    "sg:city":"Olpe",
    "sg:phone":"+49 2761/2567",
    "sg:postcode":"57462",
    "sg:province":"Nordrhein-Westfalen",
    "wof:name":"Hohenstein",
    "wof:placetype":"venue"
},
  "geometry": {"coordinates":[7.8473801613,51.0237159729],"type":"Point"}
}