{
  "type": "Feature",
  "properties": {
    "iso:country":"DE",
    "sg:address":"Asselner Hellweg 143",
    "sg:city":"Dortmund",
    "sg:phone":"+49 231/279582",
    "sg:postcode":"44319",
    "sg:province":"Nordrhein-Westfalen",
    "wof:name":"Heinz Brasse",
    "wof:placetype":"venue"
},
  "geometry": {"coordinates":[7.588138,51.528156],"type":"Point"}
}