{
  "type": "Feature",
  "properties": {
    "iso:country":"DE",
    "sg:address":"Allee 41",
    "sg:city":"Heilbronn",
    "sg:phone":"+49 7131/888880",
    "sg:postcode":"74072",
    "sg:province":"Baden-W\u00fcrttemberg",
    "wof:name":"Efde Verm\u00f6gens- Verwaltungs Gmbh",
    "wof:placetype":"venue"
},
  "geometry": {"coordinates":[9.2224168777,49.1435432434],"type":"Point"}
}