{
  "type": "Feature",
  "properties": {
    "iso:country":"DE",
    "sg:address":"Kranichweg 3",
    "sg:city":"Wismar",
    "sg:phone":"+49 3841/206424",
    "sg:postcode":"23970",
    "sg:province":"Mecklenburg-Vorpommern",
    "wof:name":"Tiba Eberhardt Gmbh",
    "wof:placetype":"venue"
},
  "geometry": {"coordinates":[11.5125102997,53.8905181885],"type":"Point"}
}