{
  "type": "Feature",
  "properties": {
    "iso:country":"DE",
    "sg:address":"Rostocker Str. 5",
    "sg:city":"Satow",
    "sg:phone":"+49 38295/78204",
    "sg:postcode":"18239",
    "sg:province":"Mecklenburg-Vorpommern",
    "wof:name":"Apotheke",
    "wof:placetype":"venue"
},
  "geometry": {"coordinates":[11.894488,53.988441],"type":"Point"}
}