{
  "type": "Feature",
  "properties": {
    "iso:country":"DE",
    "sg:address":"Gr\u00e4venitzstr. 25",
    "sg:city":"Flecken Zechlin",
    "sg:postcode":"16837",
    "sg:province":"Brandenburg",
    "wof:name":"Bauunternehmen B\u00f6ttcher & Heuer Gmbh",
    "wof:placetype":"venue"
},
  "geometry": {"coordinates":[12.760676,53.162422],"type":"Point"}
}