{
  "type": "Feature",
  "properties": {
    "iso:country":"DE",
    "sg:city":"Berod",
    "sg:postcode":"56414",
    "sg:province":"Rheinland-Pfalz",
    "wof:name":"Ka-projekt- Und Massivhaus Gmbh",
    "wof:placetype":"venue"
},
  "geometry": {"coordinates":[7.936599,50.483437],"type":"Point"}
}