{
  "type": "Feature",
  "properties": {
    "iso:country":"DE",
    "sg:address":"Hardtweg 3",
    "sg:city":"Remseck",
    "sg:phone":"+49 7146/89610",
    "sg:postcode":"71686",
    "sg:province":"Baden-W\u00fcrttemberg",
    "wof:name":"Rilling-sekt",
    "wof:placetype":"venue"
},
  "geometry": {"coordinates":[9.2603607178,48.8649101257],"type":"Point"}
}