{
  "type": "Feature",
  "properties": {
    "iso:country":"DE",
    "sg:address":"D\u00fcnnhofsweg 21",
    "sg:city":"Bergisch Gladbach",
    "sg:phone":"+49 2202/55827",
    "sg:postcode":"51469",
    "sg:province":"Nordrhein-Westfalen",
    "wof:name":"G\u00fcnter Krein",
    "wof:placetype":"venue"
},
  "geometry": {"coordinates":[7.1133160591,50.9825706482],"type":"Point"}
}