{
  "type": "Feature",
  "properties": {
    "iso:country":"DE",
    "sg:address":"Brautgasse 2",
    "sg:city":"Bayreuth",
    "sg:phone":"+49 921/65817",
    "sg:postcode":"95444",
    "sg:province":"Bayern",
    "wof:name":"G\u00fcnter Haberberger",
    "wof:placetype":"venue"
},
  "geometry": {"coordinates":[11.574347,49.943558],"type":"Point"}
}