{
  "type": "Feature",
  "properties": {
    "iso:country":"DE",
    "sg:address":"Bamberger Str. 17",
    "sg:city":"Hirschaid",
    "sg:phone":"+49 9543/5360",
    "sg:postcode":"96114",
    "sg:province":"Bayern",
    "wof:name":"Highway",
    "wof:placetype":"venue"
},
  "geometry": {"coordinates":[10.9879980087,49.8181686401],"type":"Point"}
}