{
  "type": "Feature",
  "properties": {
    "iso:country":"DE",
    "sg:address":"Birkenallee 17",
    "sg:city":"Neukirchen",
    "sg:phone":"+49 6694/80850",
    "sg:postcode":"34626",
    "sg:province":"Hessen",
    "wof:name":"St\u00e4dtisches Schwimmbad",
    "wof:placetype":"venue"
},
  "geometry": {"coordinates":[9.3416595459,50.8672218323],"type":"Point"}
}