{
  "type": "Feature",
  "properties": {
    "iso:country":"DE",
    "sg:address":"Zur Guldesm\u00fchle 12",
    "sg:city":"Dischingen",
    "sg:phone":"+49 7327/388",
    "sg:postcode":"89561",
    "sg:province":"Baden-W\u00fcrttemberg",
    "wof:name":"Gerhard Lehnert",
    "wof:placetype":"venue"
},
  "geometry": {"coordinates":[10.364542,48.686546],"type":"Point"}
}