{
  "type": "Feature",
  "properties": {
    "iso:country":"DE",
    "sg:address":"Sch\u00e4ferwiese 8",
    "sg:city":"Salzgitter",
    "sg:phone":"+49 5341/264181",
    "sg:postcode":"38239",
    "sg:province":"Niedersachsen",
    "wof:name":"Mende",
    "wof:placetype":"venue"
},
  "geometry": {"coordinates":[10.458661,52.194214],"type":"Point"}
}