{
  "type": "Feature",
  "properties": {
    "iso:country":"DE",
    "sg:address":"Josephinenstr. 22",
    "sg:city":"Leipzig",
    "sg:phone":"+49 341/2614140",
    "sg:postcode":"04317",
    "sg:province":"Sachsen",
    "wof:name":"Dr. Med. Martina Spreer \u00c4rztin F\u00fcr P\u00e4diatrie",
    "wof:placetype":"venue"
},
  "geometry": {"coordinates":[12.3989295959,51.3315658569],"type":"Point"}
}