{
  "type": "Feature",
  "properties": {
    "iso:country":"DE",
    "sg:address":"Industriestr. 45",
    "sg:city":"Lienen",
    "sg:phone":"+49 5483/684",
    "sg:postcode":"49536",
    "sg:province":"Nordrhein-Westfalen",
    "wof:name":"J. & H. Maler Und Vollw\u00e4rmeschutz Gmbh",
    "wof:placetype":"venue"
},
  "geometry": {"coordinates":[7.98402,52.153099],"type":"Point"}
}