{
  "type": "Feature",
  "properties": {
    "iso:country":"DE",
    "sg:address":"Meisenstr. 6",
    "sg:city":"Neu-Isenburg",
    "sg:phone":"+49 6102/51991",
    "sg:postcode":"63263",
    "sg:province":"Hessen",
    "wof:name":"Christine August & Co. Kg",
    "wof:placetype":"venue"
},
  "geometry": {"coordinates":[8.7535953522,50.0590057373],"type":"Point"}
}