{
  "type": "Feature",
  "properties": {
    "iso:country":"DE",
    "sg:address":"Hohe Str. 79",
    "sg:city":"Syke",
    "sg:phone":"+49 4242/50432",
    "sg:postcode":"28857",
    "sg:province":"Niedersachsen",
    "wof:name":"Heinrich Ruge",
    "wof:placetype":"venue"
},
  "geometry": {"coordinates":[8.8173475266,52.9050559998],"type":"Point"}
}