{
  "type": "Feature",
  "properties": {
    "iso:country":"DE",
    "sg:address":"Niederhutstr. 10",
    "sg:city":"Bad Neuenahr-Ahrweiler",
    "sg:phone":"+49 2641/4082",
    "sg:postcode":"53474",
    "sg:province":"Rheinland-Pfalz",
    "wof:name":"Restaurant Zum \u00c4nnchen G\u00fcnter Loerakker",
    "wof:placetype":"venue"
},
  "geometry": {"coordinates":[7.0981268883,50.5433197021],"type":"Point"}
}