{
  "type": "Feature",
  "properties": {
    "iso:country":"DE",
    "sg:address":"Penzberger Str. 12",
    "sg:city":"Seeshaupt",
    "sg:phone":"+49 8801/2222",
    "sg:postcode":"82402",
    "sg:province":"Bayern",
    "wof:name":"E. Wunder Immobilienmakler",
    "wof:placetype":"venue"
},
  "geometry": {"coordinates":[11.3004255295,47.8242301941],"type":"Point"}
}