{
  "type": "Feature",
  "properties": {
    "iso:country":"DE",
    "sg:address":"Schulstr. 16",
    "sg:city":"Dorstadt",
    "sg:phone":"+49 5337/330",
    "sg:postcode":"38312",
    "sg:province":"Niedersachsen",
    "wof:name":"Oskar Wischnewski",
    "wof:placetype":"venue"
},
  "geometry": {"coordinates":[10.5662212372,52.1010780334],"type":"Point"}
}