{
  "type": "Feature",
  "properties": {
    "iso:country":"DE",
    "sg:address":"Elmstr. 34",
    "sg:city":"Ennigerloh",
    "sg:phone":"+49 2524/950940",
    "sg:postcode":"59320",
    "sg:province":"Nordrhein-Westfalen",
    "wof:name":"Bi Mo-industriemontagen Gmbh",
    "wof:placetype":"venue"
},
  "geometry": {"coordinates":[8.02707,51.833294],"type":"Point"}
}