{
  "type": "Feature",
  "properties": {
    "iso:country":"DE",
    "sg:address":"Muthesiusstr. 12",
    "sg:city":"Berlin",
    "sg:phone":"+49 30/8069120",
    "sg:postcode":"12163",
    "sg:province":"Berlin",
    "wof:name":"Wig Immobilien Gmbh",
    "wof:placetype":"venue"
},
  "geometry": {"coordinates":[13.3205957413,52.4591751099],"type":"Point"}
}