{
  "type": "Feature",
  "properties": {
    "iso:country":"DE",
    "sg:address":"Gesellensteig 47",
    "sg:city":"Salzgitter",
    "sg:phone":"+49 5341/65051",
    "sg:postcode":"38229",
    "sg:province":"Niedersachsen",
    "wof:name":"Lietzautolackierei Karosseriefachbetrieb",
    "wof:placetype":"venue"
},
  "geometry": {"coordinates":[10.351804,52.165119],"type":"Point"}
}