{
  "type": "Feature",
  "properties": {
    "iso:country":"DE",
    "sg:address":"Dammallee 24",
    "sg:city":"Bayreuth",
    "sg:phone":"+49 921/65305",
    "sg:postcode":"95444",
    "sg:province":"Bayern",
    "wof:name":"Dorothea B\u00f6hner",
    "wof:placetype":"venue"
},
  "geometry": {"coordinates":[11.5712947845,49.9444160461],"type":"Point"}
}