{
  "type": "Feature",
  "properties": {
    "iso:country":"DE",
    "sg:address":"Am Fischbahnhof 2",
    "sg:city":"Bremerhaven",
    "sg:phone":"+49 471/74444",
    "sg:postcode":"27572",
    "sg:province":"Bremen",
    "wof:name":"Ankerstube",
    "wof:placetype":"venue"
},
  "geometry": {"coordinates":[8.5806045532,53.5217399597],"type":"Point"}
}