{
  "type": "Feature",
  "properties": {
    "iso:country":"DE",
    "sg:address":"Dorfstr 20",
    "sg:city":"Reichertshofen",
    "sg:phone":"+49 8453/30005",
    "sg:postcode":"85084",
    "sg:province":"Bayern",
    "wof:name":"Raiffeisenbank Langenbruck Eg",
    "wof:placetype":"venue"
},
  "geometry": {"coordinates":[11.50935,48.639217],"type":"Point"}
}