{
  "type": "Feature",
  "properties": {
    "iso:country":"DE",
    "sg:address":"Oberer Bruchweg 6",
    "sg:city":"K\u00f6ln",
    "sg:phone":"+49 221/2976856",
    "sg:postcode":"51109",
    "sg:province":"Nordrhein-Westfalen",
    "wof:name":"Multi Sports Sportvermarktungs Gmbh",
    "wof:placetype":"venue"
},
  "geometry": {"coordinates":[7.0755062103,50.9419631958],"type":"Point"}
}