{
  "type": "Feature",
  "properties": {
    "iso:country":"DE",
    "sg:address":"Grevener Damm 260",
    "sg:city":"Emsdetten",
    "sg:phone":"+49 2572",
    "sg:postcode":"48282",
    "sg:province":"Nordrhein-Westfalen",
    "wof:name":"Autohaus Tecklenborg Gmbh & Cokg",
    "wof:placetype":"venue"
},
  "geometry": {"coordinates":[7.5635080338,52.1447753906],"type":"Point"}
}