{
  "type": "Feature",
  "properties": {
    "iso:country":"DE",
    "sg:address":"Dorfstr. 14",
    "sg:city":"Witzwort",
    "sg:phone":"+49 4864/277",
    "sg:postcode":"25889",
    "sg:province":"Schleswig-Holstein",
    "wof:name":"Heinz Wichmann",
    "wof:placetype":"venue"
},
  "geometry": {"coordinates":[8.985214,54.400387],"type":"Point"}
}