{
  "type": "Feature",
  "properties": {
    "iso:country":"DE",
    "sg:address":"Am Heerberg 24",
    "sg:city":"Bad Salzdetfurth",
    "sg:phone":"+49 5064/85540",
    "sg:postcode":"31162",
    "sg:province":"Niedersachsen",
    "wof:name":"Hillebrand Immobilien",
    "wof:placetype":"venue"
},
  "geometry": {"coordinates":[10.0291624069,52.0832901001],"type":"Point"}
}