{
  "type": "Feature",
  "properties": {
    "iso:country":"DE",
    "sg:address":"Baadenberger Str. 39",
    "sg:city":"K\u00f6ln",
    "sg:phone":"+49 221/558479",
    "sg:postcode":"50825",
    "sg:province":"Nordrhein-Westfalen",
    "wof:name":"Manfred Schmitz",
    "wof:placetype":"venue"
},
  "geometry": {"coordinates":[6.922491,50.960354],"type":"Point"}
}