{
  "type": "Feature",
  "properties": {
    "iso:country":"DE",
    "sg:address":"Sandberg 13",
    "sg:city":"R\u00fcckmarsdorf",
    "sg:phone":"+49 341/9410314",
    "sg:postcode":"04430",
    "wof:name":"Aichinger Gmbh & Co. Einrichtungsbau Aluminium-",
    "wof:placetype":"venue"
},
  "geometry": {"coordinates":[12.260435,51.346558],"type":"Point"}
}