{
  "type": "Feature",
  "properties": {
    "iso:country":"DE",
    "sg:address":"St.-Gallus-Str. 11a",
    "sg:city":"Gessertshausen",
    "sg:postcode":"86459",
    "sg:province":"Bayern",
    "wof:name":"Metzgerei Singer Gmbh",
    "wof:placetype":"venue"
},
  "geometry": {"coordinates":[10.733874321,48.3416671753],"type":"Point"}
}