{
  "type": "Feature",
  "properties": {
    "iso:country":"DE",
    "sg:address":"Detmolder Str. 126",
    "sg:city":"Bielefeld",
    "sg:phone":"+49 521/22509",
    "sg:postcode":"33604",
    "sg:province":"Nordrhein-Westfalen",
    "wof:name":"Marianne Ognjan",
    "wof:placetype":"venue"
},
  "geometry": {"coordinates":[8.5445642471,52.0078811646],"type":"Point"}
}