{
  "type": "Feature",
  "properties": {
    "iso:country":"DE",
    "sg:address":"Hachenburgerstr.24",
    "sg:city":"K\u00f6ln",
    "sg:phone":"+49 221",
    "sg:postcode":"51105",
    "sg:province":"Nordrhein-Westfalen",
    "wof:name":"Tambourcorps",
    "wof:placetype":"venue"
},
  "geometry": {"coordinates":[6.992489,50.915405],"type":"Point"}
}