{
  "type": "Feature",
  "properties": {
    "iso:country":"DE",
    "sg:address":"R\u00fcttenscheider Platz 3",
    "sg:city":"Essen",
    "sg:phone":"+49 201/779017",
    "sg:postcode":"45130",
    "sg:province":"Nordrhein-Westfalen",
    "wof:name":"Kosmetikinstitut Tagessch\u00f6nheisfarm",
    "wof:placetype":"venue"
},
  "geometry": {"coordinates":[7.008753,51.43819],"type":"Point"}
}