{
  "type": "Feature",
  "properties": {
    "iso:country":"DE",
    "sg:address":"B\u00f6hmerstr. 4",
    "sg:city":"Frankfurt",
    "sg:phone":"+49 69/554218",
    "sg:postcode":"60322",
    "sg:province":"Hessen",
    "wof:name":"Klaus Hotz Rechtsanwalt Und Notar",
    "wof:placetype":"venue"
},
  "geometry": {"coordinates":[8.6732158661,50.1233062744],"type":"Point"}
}