{
  "type": "Feature",
  "properties": {
    "iso:country":"DE",
    "sg:city":"Boksee",
    "sg:postcode":"24220",
    "sg:province":"Schleswig-Holstein",
    "wof:name":"Campingplatz Ostsee-freizeitpark",
    "wof:placetype":"venue"
},
  "geometry": {"coordinates":[10.130579,54.243526],"type":"Point"}
}