{
  "type": "Feature",
  "properties": {
    "iso:country":"DE",
    "sg:address":"Schlettauer Str. 33",
    "sg:city":"Sehmatal-Sehma",
    "sg:postcode":"09465",
    "sg:province":"Sachsen",
    "wof:name":"Wohnungsgenossenschaft Einheit Sehma Eg",
    "wof:placetype":"venue"
},
  "geometry": {"coordinates":[12.9898099899,50.5379295349],"type":"Point"}
}