{
  "type": "Feature",
  "properties": {
    "iso:country":"DE",
    "sg:address":"Schlo\u00dfstr. 161",
    "sg:city":"Trier",
    "sg:phone":"+49 651/9960111",
    "sg:postcode":"54293",
    "sg:province":"Rheinland-Pfalz",
    "wof:name":"M. Und G. Faber",
    "wof:placetype":"venue"
},
  "geometry": {"coordinates":[6.707389,49.826084],"type":"Point"}
}