{
  "type": "Feature",
  "properties": {
    "iso:country":"DE",
    "sg:address":"Leonhard-Bankel-Platz 1",
    "sg:city":"Neustadt",
    "sg:phone":"+49 9161/82535",
    "sg:postcode":"91413",
    "sg:province":"Bayern",
    "wof:name":"Claudia Platz\u00f6der Rechtsanw\u00e4ltin",
    "wof:placetype":"venue"
},
  "geometry": {"coordinates":[10.6043996811,49.5777893066],"type":"Point"}
}