{
  "type": "Feature",
  "properties": {
    "iso:country":"DE",
    "sg:address":"Dorschhauser Weg 4",
    "sg:city":"Bad W\u00f6rishofen",
    "sg:phone":"+49 8247/96830",
    "sg:postcode":"86825",
    "sg:province":"Bayern",
    "wof:name":"Kurhotel Austria Ii",
    "wof:placetype":"venue"
},
  "geometry": {"coordinates":[10.5877361298,48.0067138672],"type":"Point"}
}