{
  "type": "Feature",
  "properties": {
    "iso:country":"DE",
    "sg:address":"Wilfriedstr. 30",
    "sg:city":"Bielefeld",
    "sg:phone":"+49 5204/89757",
    "sg:postcode":"33649",
    "sg:province":"Nordrhein-Westfalen",
    "wof:name":"Harald Hauser",
    "wof:placetype":"venue"
},
  "geometry": {"coordinates":[8.486596,52.000477],"type":"Point"}
}