{
  "type": "Feature",
  "properties": {
    "iso:country":"DE",
    "sg:address":"Kochsgasse 18",
    "sg:city":"Eschweiler",
    "sg:phone":"+49 2403/4183",
    "sg:postcode":"52249",
    "sg:province":"Nordrhein-Westfalen",
    "wof:name":"Konzepta Gmbh",
    "wof:placetype":"venue"
},
  "geometry": {"coordinates":[6.266262,50.821068],"type":"Point"}
}