{
  "type": "Feature",
  "properties": {
    "iso:country":"DE",
    "sg:address":"Adolphsb\u00fchlstr. 33",
    "sg:city":"Gem\u00fcnden",
    "sg:phone":"+49 9351/8959",
    "sg:postcode":"97737",
    "sg:province":"Bayern",
    "wof:name":"Ursula Joa",
    "wof:placetype":"venue"
},
  "geometry": {"coordinates":[9.7380628586,50.0318717957],"type":"Point"}
}