{
  "type": "Feature",
  "properties": {
    "iso:country":"DE",
    "sg:address":"Joseph-Haydn-Str. 7",
    "sg:city":"Hamm",
    "sg:phone":"+49 2381/74871",
    "sg:postcode":"59075",
    "sg:province":"Nordrhein-Westfalen",
    "wof:name":"W. K\u00f6nig",
    "wof:placetype":"venue"
},
  "geometry": {"coordinates":[7.7643079758,51.7012863159],"type":"Point"}
}