{
  "type": "Feature",
  "properties": {
    "iso:country":"DE",
    "sg:address":"Alicenstr. 19",
    "sg:city":"Darmstadt",
    "sg:phone":"+49 6151/21549",
    "sg:postcode":"64293",
    "sg:province":"Hessen",
    "wof:name":"Gudrun Kettmann",
    "wof:placetype":"venue"
},
  "geometry": {"coordinates":[8.6475439072,49.878944397],"type":"Point"}
}