{
  "type": "Feature",
  "properties": {
    "iso:country":"DE",
    "sg:address":"Josef-Priller-Str. 34 a",
    "sg:city":"Augsburg",
    "sg:phone":"+49 821/574130",
    "sg:postcode":"86159",
    "sg:province":"Bayern",
    "wof:name":"Gerhard Schlott",
    "wof:placetype":"venue"
},
  "geometry": {"coordinates":[10.9033689499,48.330581665],"type":"Point"}
}