{
  "type": "Feature",
  "properties": {
    "iso:country":"DE",
    "sg:address":"Burgstr. 3",
    "sg:city":"Flensburg",
    "sg:phone":"+49 461/23215",
    "sg:postcode":"24939",
    "sg:province":"Schleswig-Holstein",
    "wof:name":"Duburg-apotheke Rainer Reifenrath",
    "wof:placetype":"venue"
},
  "geometry": {"coordinates":[9.426125,54.791428],"type":"Point"}
}