{
  "type": "Feature",
  "properties": {
    "iso:country":"DE",
    "sg:address":"August-Bebel-Str. 15",
    "sg:city":"Torgau",
    "sg:phone":"+49 3421/722622",
    "sg:postcode":"04860",
    "sg:province":"Sachsen",
    "wof:name":"Uwe Hoffmann Notariat",
    "wof:placetype":"venue"
},
  "geometry": {"coordinates":[12.9957180023,51.5587234497],"type":"Point"}
}