{
  "type": "Feature",
  "properties": {
    "iso:country":"DE",
    "sg:address":"Kastanienplatz 1",
    "sg:city":"Sargstedt",
    "sg:phone":"+49 39425/6117",
    "sg:postcode":"38822",
    "sg:province":"Sachsen-Anhalt",
    "wof:name":"Hermann Heyer",
    "wof:placetype":"venue"
},
  "geometry": {"coordinates":[10.988527,51.93845],"type":"Point"}
}