{
  "type": "Feature",
  "properties": {
    "iso:country":"DE",
    "sg:address":"Fischerstr. 24a",
    "sg:city":"Elsholz",
    "sg:phone":"+49 33204/35750",
    "sg:postcode":"14547",
    "sg:province":"Brandenburg",
    "wof:name":"W. Hentschel & S\u00f6hne Gmbh",
    "wof:placetype":"venue"
},
  "geometry": {"coordinates":[12.959055,52.199272],"type":"Point"}
}