{
  "type": "Feature",
  "properties": {
    "iso:country":"DE",
    "sg:address":"Niederberndorf",
    "sg:city":"Schmallenberg",
    "sg:phone":"+49 2971/86228",
    "sg:postcode":"57392",
    "sg:province":"Nordrhein-Westfalen",
    "wof:name":"Josef J\u00fcrgens",
    "wof:placetype":"venue"
},
  "geometry": {"coordinates":[8.223266,51.193527],"type":"Point"}
}