{
  "type": "Feature",
  "properties": {
    "iso:country":"DE",
    "sg:address":"Gr\u00fcner Weg 1",
    "sg:city":"L\u00f6hnberg",
    "sg:phone":"+49 6482/91320",
    "sg:postcode":"35792",
    "sg:province":"Hessen",
    "wof:name":"Karlheinz Wendt Steuerberater",
    "wof:placetype":"venue"
},
  "geometry": {"coordinates":[8.2657327652,50.515789032],"type":"Point"}
}