{
  "type": "Feature",
  "properties": {
    "iso:country":"DE",
    "sg:address":"Bongardstr. 36",
    "sg:city":"Baesweiler",
    "sg:postcode":"52499",
    "sg:province":"Nordrhein-Westfalen",
    "wof:name":"V & S Bau Gmbh",
    "wof:placetype":"venue"
},
  "geometry": {"coordinates":[6.1639127731,50.9276351929],"type":"Point"}
}