{
  "type": "Feature",
  "properties": {
    "iso:country":"DE",
    "sg:address":"Brook 1",
    "sg:city":"Bad Laer",
    "sg:phone":"+49 5424/9263",
    "sg:postcode":"49196",
    "sg:province":"Niedersachsen",
    "wof:name":"Josef Beermann",
    "wof:placetype":"venue"
},
  "geometry": {"coordinates":[8.117328,52.077099],"type":"Point"}
}