{
  "type": "Feature",
  "properties": {
    "iso:country":"DE",
    "sg:address":"Gartenstr. 18-19",
    "sg:city":"Berlin",
    "sg:phone":"+49 30/2819238",
    "sg:postcode":"10115",
    "sg:province":"Berlin",
    "wof:name":"Dr. Med. Annelore Lange",
    "wof:placetype":"venue"
},
  "geometry": {"coordinates":[13.390327,52.531509],"type":"Point"}
}