{
  "type": "Feature",
  "properties": {
    "iso:country":"DE",
    "sg:address":"Heckendreher (Gewand)",
    "sg:city":"Reutlingen",
    "sg:phone":"+49 7121/17610",
    "sg:postcode":"72766",
    "sg:province":"Baden-W\u00fcrttemberg",
    "wof:name":"Waldschenke",
    "wof:placetype":"venue"
},
  "geometry": {"coordinates":[9.2395305634,48.5035209656],"type":"Point"}
}