{
  "type": "Feature",
  "properties": {
    "iso:country":"DE",
    "sg:address":"Hauptstr. 228",
    "sg:city":"M\u00fcnsingen",
    "sg:phone":"+49 7381/3392",
    "sg:postcode":"72525",
    "sg:province":"Baden-W\u00fcrttemberg",
    "wof:name":"Erwin Br\u00e4ndle",
    "wof:placetype":"venue"
},
  "geometry": {"coordinates":[9.5223999023,48.4125213623],"type":"Point"}
}