{
  "type": "Feature",
  "properties": {
    "iso:country":"DE",
    "sg:address":"Stettiner Str. 18",
    "sg:city":"Nagold",
    "sg:phone":"+49 7452/3485",
    "sg:postcode":"72202",
    "sg:province":"Baden-W\u00fcrttemberg",
    "wof:name":"Friedrich Roller",
    "wof:placetype":"venue"
},
  "geometry": {"coordinates":[8.7168092728,48.5440750122],"type":"Point"}
}