{
  "type": "Feature",
  "properties": {
    "iso:country":"DE",
    "sg:address":"Waldstr. 23",
    "sg:city":"Hannover",
    "sg:phone":"+49 511/663317",
    "sg:postcode":"30163",
    "sg:province":"Niedersachsen",
    "wof:name":"Georg Weber Ingenieur",
    "wof:placetype":"venue"
},
  "geometry": {"coordinates":[9.747124,52.39291],"type":"Point"}
}