{
  "type": "Feature",
  "properties": {
    "iso:country":"DE",
    "sg:address":"Inselstr. 8",
    "sg:city":"N\u00fcrtingen",
    "sg:phone":"+49 7022/932880",
    "sg:postcode":"72622",
    "sg:province":"Baden-W\u00fcrttemberg",
    "wof:name":"Amestra Gesellschaft F\u00fcr Anlagenvermittlung Durch",
    "wof:placetype":"venue"
},
  "geometry": {"coordinates":[9.3518362045,48.6386299133],"type":"Point"}
}