{
  "type": "Feature",
  "properties": {
    "iso:country":"DE",
    "sg:address":"Westlicher Stadtgraben 30",
    "sg:city":"Deggendorf",
    "sg:phone":"+49 991/5858",
    "sg:postcode":"94469",
    "sg:province":"Bayern",
    "wof:name":"Clip",
    "wof:placetype":"venue"
},
  "geometry": {"coordinates":[12.959536,48.833454],"type":"Point"}
}