{
  "type": "Feature",
  "properties": {
    "iso:country":"DE",
    "sg:address":"Hauptstr. 125",
    "sg:city":"Miltenberg",
    "sg:phone":"+49 9371/7823",
    "sg:postcode":"63897",
    "sg:province":"Bayern",
    "wof:name":"Otto Leibfried \u00d6fen Und Herde",
    "wof:placetype":"venue"
},
  "geometry": {"coordinates":[9.2545757294,49.6997756958],"type":"Point"}
}