{
  "type": "Feature",
  "properties": {
    "iso:country":"DE",
    "sg:address":"Gro\u00dfe Gsteinet Str. 24",
    "sg:city":"Denkendorf",
    "sg:postcode":"85095",
    "sg:province":"Bayern",
    "wof:name":"G. Buhtz",
    "wof:placetype":"venue"
},
  "geometry": {"coordinates":[11.4397573471,48.9528884888],"type":"Point"}
}