{
  "type": "Feature",
  "properties": {
    "iso:country":"DE",
    "sg:address":"Zierheidchen 3",
    "sg:city":"Neustadt",
    "sg:phone":"+49 2683/939700",
    "sg:postcode":"53577",
    "sg:province":"Rheinland-Pfalz",
    "wof:name":"Susanne K\u00f6nigs Masseurin",
    "wof:placetype":"venue"
},
  "geometry": {"coordinates":[7.45128,50.596581],"type":"Point"}
}