{
  "type": "Feature",
  "properties": {
    "iso:country":"DE",
    "sg:address":"L\u00fcchower Str. 1",
    "sg:city":"Dannenberg",
    "sg:phone":"+49 5861/2293",
    "sg:postcode":"29451",
    "sg:province":"Niedersachsen",
    "wof:name":"Otto Hammer",
    "wof:placetype":"venue"
},
  "geometry": {"coordinates":[11.090185,53.096073],"type":"Point"}
}