{
  "type": "Feature",
  "properties": {
    "iso:country":"DE",
    "sg:address":"Rheinallee 18a",
    "sg:city":"K\u00f6nigswinter",
    "sg:phone":"+49 2223/4311",
    "sg:postcode":"53639",
    "sg:province":"Nordrhein-Westfalen",
    "wof:name":"K. Herold Rechtsanwalt",
    "wof:placetype":"venue"
},
  "geometry": {"coordinates":[7.1894698143,50.6770477295],"type":"Point"}
}