{
  "type": "Feature",
  "properties": {
    "iso:country":"DE",
    "sg:address":"Triftstrasse 14",
    "sg:city":"Bremerhaven",
    "sg:phone":"+49 471/9812510",
    "sg:postcode":"27580",
    "sg:province":"Bremen",
    "wof:name":"Jo Drathjer Grafik Design",
    "wof:placetype":"venue"
},
  "geometry": {"coordinates":[8.592783,53.582901],"type":"Point"}
}