{
  "type": "Feature",
  "properties": {
    "iso:country":"DE",
    "sg:address":"M\u00fchlheimer Str. 384",
    "sg:city":"Offenbach",
    "sg:phone":"+49 69/816730",
    "sg:postcode":"63075",
    "sg:province":"Hessen",
    "wof:name":"Helmut Kahl",
    "wof:placetype":"venue"
},
  "geometry": {"coordinates":[8.80879,50.114941],"type":"Point"}
}