{
  "type": "Feature",
  "properties": {
    "iso:country":"DE",
    "sg:address":"Lindenallee 13",
    "sg:city":"Hamm",
    "sg:phone":"+49 2682/95110",
    "sg:postcode":"57577",
    "sg:province":"Rheinland-Pfalz",
    "wof:name":"Neue Apotheke Neue Drogerie Bernhard Pohlmann E. K.",
    "wof:placetype":"venue"
},
  "geometry": {"coordinates":[7.675204,50.766045],"type":"Point"}
}