{
  "type": "Feature",
  "properties": {
    "iso:country":"DE",
    "sg:address":"Schwaaner Chaussee 1",
    "sg:city":"Bad Doberan",
    "sg:phone":"+49 38203/7000",
    "sg:postcode":"18209",
    "sg:province":"Mecklenburg-Vorpommern",
    "wof:name":"Glash\u00e4ger Brunnen Gmbh",
    "wof:placetype":"venue"
},
  "geometry": {"coordinates":[11.9051408768,54.0988845825],"type":"Point"}
}