{
  "type": "Feature",
  "properties": {
    "iso:country":"DE",
    "sg:address":"Bei dem Neuen Krahn 2",
    "sg:city":"Hamburg",
    "sg:postcode":"20457",
    "sg:province":"Hamburg",
    "wof:name":"Unitrade Informations- Technologie Gmbh",
    "wof:placetype":"venue"
},
  "geometry": {"coordinates":[9.988923,53.544937],"type":"Point"}
}