{
  "type": "Feature",
  "properties": {
    "iso:country":"DE",
    "sg:address":"Rolfshagener Str. 6",
    "sg:city":"Auetal",
    "sg:phone":"+49 5753/228",
    "sg:postcode":"31749",
    "sg:province":"Niedersachsen",
    "wof:name":"R. Steinh\u00e4user",
    "wof:placetype":"venue"
},
  "geometry": {"coordinates":[9.1542701721,52.2326393127],"type":"Point"}
}