{
  "type": "Feature",
  "properties": {
    "iso:country":"DE",
    "sg:address":"Frankenstr. 14",
    "sg:city":"Allersberg",
    "sg:phone":"+49 9176/7186",
    "sg:postcode":"90584",
    "sg:province":"Bayern",
    "wof:name":"Karin Gr\u00e4ser",
    "wof:placetype":"venue"
},
  "geometry": {"coordinates":[11.238343,49.256889],"type":"Point"}
}