{
  "type": "Feature",
  "properties": {
    "iso:country":"DE",
    "sg:address":"Maybachstr. 3",
    "sg:city":"Holzgerlingen",
    "sg:phone":"+49 7031/75660",
    "sg:postcode":"71088",
    "sg:province":"Baden-W\u00fcrttemberg",
    "wof:name":"Brock Gmbh & Co.",
    "wof:placetype":"venue"
},
  "geometry": {"coordinates":[9.02899,48.630943],"type":"Point"}
}