{
  "type": "Feature",
  "properties": {
    "iso:country":"DE",
    "sg:address":"Burgstr. 22",
    "sg:city":"Kottenheim",
    "sg:phone":"+49 2651/42326",
    "sg:postcode":"56736",
    "sg:province":"Rheinland-Pfalz",
    "wof:name":"Bratzler Und Josten",
    "wof:placetype":"venue"
},
  "geometry": {"coordinates":[7.256388,50.34745],"type":"Point"}
}