{
  "type": "Feature",
  "properties": {
    "iso:country":"DE",
    "sg:address":"Buchenweg 48",
    "sg:city":"Emsdetten",
    "sg:phone":"+49 2572/7478",
    "sg:postcode":"48282",
    "sg:province":"Nordrhein-Westfalen",
    "wof:name":"Ernst Rengers",
    "wof:placetype":"venue"
},
  "geometry": {"coordinates":[7.557983,52.160118],"type":"Point"}
}