{
  "type": "Feature",
  "properties": {
    "iso:country":"DE",
    "sg:address":"Weiherm\u00fchl 3",
    "sg:city":"Stallwang",
    "sg:phone":"+49 9964/383",
    "sg:postcode":"94375",
    "sg:province":"Bayern",
    "wof:name":"J. Bosl",
    "wof:placetype":"venue"
},
  "geometry": {"coordinates":[12.606158,49.065903],"type":"Point"}
}