{
  "type": "Feature",
  "properties": {
    "iso:country":"DE",
    "sg:address":"Berggasse 3",
    "sg:city":"Nebra",
    "sg:phone":"+49 34461/22051",
    "sg:postcode":"06642",
    "sg:province":"Sachsen-Anhalt",
    "wof:name":"W. Und R. J\u00e4nicke",
    "wof:placetype":"venue"
},
  "geometry": {"coordinates":[11.545285,51.268059],"type":"Point"}
}