{
  "type": "Feature",
  "properties": {
    "iso:country":"DE",
    "sg:address":"Einsteinstr. 38",
    "sg:city":"Neuss",
    "sg:phone":"+49 2131/80546",
    "sg:postcode":"41464",
    "sg:province":"Nordrhein-Westfalen",
    "wof:name":"Manfred G\u00fcnther Ingenieur",
    "wof:placetype":"venue"
},
  "geometry": {"coordinates":[6.6706438065,51.1845703125],"type":"Point"}
}