{
  "type": "Feature",
  "properties": {
    "iso:country":"DE",
    "sg:address":"M\u00fcnchener Str. 22",
    "sg:city":"Roth",
    "sg:phone":"+49 9171/88479",
    "sg:postcode":"91154",
    "sg:province":"Bayern",
    "wof:name":"Gartenlaube Inh. Neumann",
    "wof:placetype":"venue"
},
  "geometry": {"coordinates":[11.0899963379,49.2434005737],"type":"Point"}
}