{
  "type": "Feature",
  "properties": {
    "iso:country":"DE",
    "sg:address":"Wehrdeich 28",
    "sg:city":"Nordenham",
    "sg:phone":"+49 4731/5339",
    "sg:postcode":"26954",
    "sg:province":"Niedersachsen",
    "wof:name":"Aenne Pollmann",
    "wof:placetype":"venue"
},
  "geometry": {"coordinates":[8.4702320099,53.4946594238],"type":"Point"}
}