{
  "type": "Feature",
  "properties": {
    "iso:country":"DE",
    "sg:address":"Hohe-Buch-Ring 23",
    "sg:city":"St. Leon-Rot",
    "sg:phone":"+49 6227/86100",
    "sg:postcode":"68789",
    "sg:province":"Baden-W\u00fcrttemberg",
    "wof:name":"Antip Transportsysteme Und Sondermaschinenbau Gmbh",
    "wof:placetype":"venue"
},
  "geometry": {"coordinates":[8.596715,49.260368],"type":"Point"}
}