{
  "type": "Feature",
  "properties": {
    "iso:country":"DE",
    "sg:address":"Nathanaelstr. 9",
    "sg:city":"Leipzig",
    "sg:postcode":"04177",
    "sg:province":"Sachsen",
    "wof:name":"Blinden- Und Seh- Schwachenverband",
    "wof:placetype":"venue"
},
  "geometry": {"coordinates":[12.331372,51.339169],"type":"Point"}
}