{
  "type": "Feature",
  "properties": {
    "iso:country":"DE",
    "sg:address":"Am Winkelzaun 33",
    "sg:city":"Chieming",
    "sg:phone":"+49 8664/207",
    "sg:postcode":"83339",
    "sg:province":"Bayern",
    "wof:name":"B. Meixner",
    "wof:placetype":"venue"
},
  "geometry": {"coordinates":[12.53895,47.897907],"type":"Point"}
}