{
  "type": "Feature",
  "properties": {
    "iso:country":"DE",
    "sg:address":"Trierer Str. 122",
    "sg:city":"N\u00fcrnberg",
    "sg:phone":"+49 911/486634",
    "sg:postcode":"90469",
    "sg:province":"Bayern",
    "wof:name":"Guy Peters Collection G\u00fcnter Peters",
    "wof:placetype":"venue"
},
  "geometry": {"coordinates":[11.105471611,49.408203125],"type":"Point"}
}