{
  "type": "Feature",
  "properties": {
    "iso:country":"DE",
    "sg:address":"Hauptstr. 134",
    "sg:city":"Schwelm",
    "sg:phone":"+49 2336/6616",
    "sg:postcode":"58332",
    "sg:province":"Nordrhein-Westfalen",
    "wof:name":"Deutsche Shell",
    "wof:placetype":"venue"
},
  "geometry": {"coordinates":[7.3021411896,51.2894058228],"type":"Point"}
}