{
  "type": "Feature",
  "properties": {
    "iso:country":"DE",
    "sg:address":"Liobastrasse",
    "sg:city":"Fulda",
    "sg:postcode":"36037",
    "sg:province":"Hessen",
    "wof:name":"Woelfle-sicherheitstechnik",
    "wof:placetype":"venue"
},
  "geometry": {"coordinates":[9.676485,50.557152],"type":"Point"}
}