{
  "type": "Feature",
  "properties": {
    "iso:country":"DE",
    "sg:address":"Bahnhofstr. 20",
    "sg:city":"Bindlach",
    "sg:phone":"+49 9208/8039",
    "sg:postcode":"95463",
    "sg:province":"Bayern",
    "wof:name":"Bahnhofsgastst\u00e4tte",
    "wof:placetype":"venue"
},
  "geometry": {"coordinates":[11.604426384,49.9803771973],"type":"Point"}
}