{
  "type": "Feature",
  "properties": {
    "iso:country":"DE",
    "sg:address":"Weinbergstr. 39",
    "sg:city":"Wutha-Farnroda",
    "sg:phone":"+49 36921/96482",
    "sg:postcode":"99848",
    "sg:province":"Th\u00fcringen",
    "wof:name":"Ernst Ebert",
    "wof:placetype":"venue"
},
  "geometry": {"coordinates":[10.398324,50.958817],"type":"Point"}
}