{
  "type": "Feature",
  "properties": {
    "iso:country":"DE",
    "sg:address":"Veldhausener Str. 32",
    "sg:city":"Neuenhaus",
    "sg:phone":"+49 5941/8186",
    "sg:postcode":"49828",
    "sg:province":"Niedersachsen",
    "wof:name":"M\u00f6lderink-zwier",
    "wof:placetype":"venue"
},
  "geometry": {"coordinates":[6.9678111076,52.5000152588],"type":"Point"}
}