{
  "type": "Feature",
  "properties": {
    "iso:country":"DE",
    "sg:address":"Rothenburger Str. 98",
    "sg:city":"Niesky",
    "sg:phone":"+49 3588/207638",
    "sg:postcode":"02906",
    "sg:province":"Sachsen",
    "wof:name":"R. Jakob",
    "wof:placetype":"venue"
},
  "geometry": {"coordinates":[14.8493976593,51.288433075],"type":"Point"}
}