{
  "type": "Feature",
  "properties": {
    "iso:country":"DE",
    "sg:address":"Thomas-Mann-Str. 1",
    "sg:city":"Ehrenfriedersdorf",
    "sg:phone":"+49 37341/2445",
    "sg:postcode":"09427",
    "sg:province":"Sachsen",
    "wof:name":"Bernd Meyer",
    "wof:placetype":"venue"
},
  "geometry": {"coordinates":[12.967004776,50.6437721252],"type":"Point"}
}