{
  "type": "Feature",
  "properties": {
    "iso:country":"DE",
    "sg:address":"Fasaneninsel 10",
    "sg:city":"Gera",
    "sg:phone":"+49 365/8303633",
    "sg:postcode":"07548",
    "sg:province":"Th\u00fcringen",
    "wof:name":"Ofs Online Fluid Sensoric Gmbh",
    "wof:placetype":"venue"
},
  "geometry": {"coordinates":[12.066546,50.895],"type":"Point"}
}