{
  "type": "Feature",
  "properties": {
    "iso:country":"DE",
    "sg:address":"Siedlung 4",
    "sg:city":"Wildenfels",
    "sg:phone":"+49 37603/8649",
    "sg:postcode":"08134",
    "sg:province":"Sachsen",
    "wof:name":"F\u00f6rster Leuchtbilder",
    "wof:placetype":"venue"
},
  "geometry": {"coordinates":[12.555065,50.64613],"type":"Point"}
}