{
  "type": "Feature",
  "properties": {
    "iso:country":"DE",
    "sg:address":"Bergstr. 29",
    "sg:city":"Seebad Bansin",
    "sg:postcode":"17429",
    "sg:province":"Mecklenburg-Vorpommern",
    "wof:name":"Vogelsberger Landhaus Baugesellschaft Gmbh",
    "wof:placetype":"venue"
},
  "geometry": {"coordinates":[14.072155,53.940441],"type":"Point"}
}