{
  "type": "Feature",
  "properties": {
    "iso:country":"DE",
    "sg:address":"Bissinger Str. 1",
    "sg:city":"Kirchheim",
    "sg:phone":"+49 7021/84883",
    "sg:postcode":"73230",
    "sg:province":"Baden-W\u00fcrttemberg",
    "wof:name":"E. M\u00f6ssner Immobilienmakler",
    "wof:placetype":"venue"
},
  "geometry": {"coordinates":[9.4875850677,48.615020752],"type":"Point"}
}