{
  "type": "Feature",
  "properties": {
    "iso:country":"DE",
    "sg:address":"Marktstr. 49-51",
    "sg:city":"Rennertshofen",
    "sg:phone":"+49 8434/94000",
    "sg:postcode":"86643",
    "sg:province":"Bayern",
    "wof:name":"W Markmiller Ohg",
    "wof:placetype":"venue"
},
  "geometry": {"coordinates":[11.050841,48.755447],"type":"Point"}
}