{
  "type": "Feature",
  "properties": {
    "iso:country":"DE",
    "sg:address":"Waldecker Str. 15",
    "sg:city":"Frankfurt",
    "sg:phone":"+49 69/525348",
    "sg:postcode":"60433",
    "sg:province":"Hessen",
    "wof:name":"A. Maric",
    "wof:placetype":"venue"
},
  "geometry": {"coordinates":[8.672942,50.152756],"type":"Point"}
}