{
  "type": "Feature",
  "properties": {
    "iso:country":"DE",
    "sg:address":"Altensteiger Str. 31",
    "sg:city":"Ebhausen",
    "sg:phone":"+49 7458/220",
    "sg:postcode":"72224",
    "sg:province":"Baden-W\u00fcrttemberg",
    "wof:name":"Forst Gartenger\u00e4te Kraftstoff Ebhausen",
    "wof:placetype":"venue"
},
  "geometry": {"coordinates":[8.6716403961,48.5891990662],"type":"Point"}
}