{
  "type": "Feature",
  "properties": {
    "iso:country":"DE",
    "sg:address":"Erasmusweg 22",
    "sg:city":"Bretten",
    "sg:phone":"+49 7252/86665",
    "sg:postcode":"75015",
    "sg:province":"Baden-W\u00fcrttemberg",
    "wof:name":"Monika Lovell \u00dcbersetzungsservice Englisch",
    "wof:placetype":"venue"
},
  "geometry": {"coordinates":[8.7174358368,49.0375328064],"type":"Point"}
}