{
  "type": "Feature",
  "properties": {
    "iso:country":"DE",
    "sg:address":"Obere Sehlhofstr. 5",
    "sg:city":"Wuppertal",
    "sg:phone":"+49 202/624534",
    "sg:postcode":"42289",
    "sg:province":"Nordrhein-Westfalen",
    "wof:name":"Paul Buchmueller Inh. Heinz Uwe Senftleben",
    "wof:placetype":"venue"
},
  "geometry": {"coordinates":[7.21026,51.271271],"type":"Point"}
}