{
  "type": "Feature",
  "properties": {
    "iso:country":"DE",
    "sg:address":"Fuchssteig 13",
    "sg:city":"Erkner",
    "sg:phone":"+49 3362/75883",
    "sg:postcode":"15537",
    "sg:province":"Brandenburg",
    "wof:name":"Rolf Weichert Patentanwalt",
    "wof:placetype":"venue"
},
  "geometry": {"coordinates":[13.7558679581,52.4363288879],"type":"Point"}
}