{
  "type": "Feature",
  "properties": {
    "iso:country":"DE",
    "sg:address":"Lammstr. 28",
    "sg:city":"Rastatt",
    "sg:phone":"+49 7222/23062",
    "sg:postcode":"76437",
    "sg:province":"Baden-W\u00fcrttemberg",
    "wof:name":"Dieter Weber",
    "wof:placetype":"venue"
},
  "geometry": {"coordinates":[8.1541252136,48.8823852539],"type":"Point"}
}