{
  "type": "Feature",
  "properties": {
    "iso:country":"DE",
    "sg:address":"Falterweg 1 a",
    "sg:city":"Gerolsheim",
    "sg:phone":"+49 6238/550",
    "sg:postcode":"67229",
    "sg:province":"Rheinland-Pfalz",
    "wof:name":"Eckhard Parchow",
    "wof:placetype":"venue"
},
  "geometry": {"coordinates":[8.2664546967,49.5494270325],"type":"Point"}
}