{
  "type": "Feature",
  "properties": {
    "iso:country":"DE",
    "sg:address":"Jagdshofer Str. 19",
    "sg:city":"Sonneberg",
    "sg:phone":"+49 3675/400800",
    "sg:postcode":"96515",
    "sg:province":"Th\u00fcringen",
    "wof:name":"Heinz Br\u00e4utigam",
    "wof:placetype":"venue"
},
  "geometry": {"coordinates":[11.221756,50.356049],"type":"Point"}
}