{
  "type": "Feature",
  "properties": {
    "iso:country":"DE",
    "sg:address":"Auf der R\u00f6tsch 2",
    "sg:city":"Essen",
    "sg:phone":"+49 2054/880",
    "sg:postcode":"45219",
    "sg:province":"Nordrhein-Westfalen",
    "wof:name":"Fachklinik Rhein Ruhr F\u00fcr Herz Kreislauf Und",
    "wof:placetype":"venue"
},
  "geometry": {"coordinates":[6.941799,51.355061],"type":"Point"}
}