{
  "type": "Feature",
  "properties": {
    "iso:country":"DE",
    "sg:address":"Auf der Grub 16",
    "sg:city":"Idar-Oberstein",
    "sg:phone":"+49 6781/44885",
    "sg:postcode":"55743",
    "sg:province":"Rheinland-Pfalz",
    "wof:name":"Karl Roland",
    "wof:placetype":"venue"
},
  "geometry": {"coordinates":[7.3092079163,49.7200737],"type":"Point"}
}