{
  "type": "Feature",
  "properties": {
    "iso:country":"DE",
    "sg:address":"Hattinger Str. 229",
    "sg:city":"Bochum",
    "sg:phone":"+49 234/34489",
    "sg:postcode":"44795",
    "sg:province":"Nordrhein-Westfalen",
    "wof:name":"Ralf Adam Rechtsanwalt",
    "wof:placetype":"venue"
},
  "geometry": {"coordinates":[7.2027630806,51.4623374939],"type":"Point"}
}