{
  "type": "Feature",
  "properties": {
    "iso:country":"DE",
    "sg:address":"Schauinsland 12",
    "sg:city":"G\u00e4ufelden",
    "sg:phone":"+49 7032/979656",
    "sg:postcode":"71126",
    "sg:province":"Baden-W\u00fcrttemberg",
    "wof:name":"Gr\u00fcnewald Gmbh",
    "wof:placetype":"venue"
},
  "geometry": {"coordinates":[8.8464260101,48.5592422485],"type":"Point"}
}