{
  "type": "Feature",
  "properties": {
    "iso:country":"DE",
    "sg:address":"Neustrelitzer Str. 3",
    "sg:city":"Wilhelmshaven",
    "sg:phone":"+49 4421/53684",
    "sg:postcode":"26388",
    "sg:province":"Niedersachsen",
    "wof:name":"Gerhard Wei\u00df Ingenieur",
    "wof:placetype":"venue"
},
  "geometry": {"coordinates":[8.0828142166,53.5667953491],"type":"Point"}
}