{
  "type": "Feature",
  "properties": {
    "iso:country":"DE",
    "sg:address":"Mittlere Str. 10",
    "sg:city":"Pfaffenweiler",
    "sg:phone":"+49 7664/6611",
    "sg:postcode":"79292",
    "sg:province":"Baden-W\u00fcrttemberg",
    "wof:name":"Karl Luhr",
    "wof:placetype":"venue"
},
  "geometry": {"coordinates":[7.755025,47.937366],"type":"Point"}
}