{
  "type": "Feature",
  "properties": {
    "iso:country":"DE",
    "sg:address":"Christian-Lassen-Str. 2",
    "sg:city":"Bonn",
    "sg:phone":"+49 228/989800",
    "sg:postcode":"53117",
    "sg:province":"Nordrhein-Westfalen",
    "wof:name":"R. Baumann Spedition Gmbh & Co. Kg",
    "wof:placetype":"venue"
},
  "geometry": {"coordinates":[7.0586681366,50.7526817322],"type":"Point"}
}