{
  "type": "Feature",
  "properties": {
    "iso:country":"DE",
    "sg:address":"Denkmalplatz 15",
    "sg:city":"Alsdorf",
    "sg:phone":"+49 2404/919533",
    "sg:postcode":"52477",
    "sg:province":"Nordrhein-Westfalen",
    "wof:name":"Lederwaren Baumanns Inh. J\u00fcrgen Baumanns E. K.",
    "wof:placetype":"venue"
},
  "geometry": {"coordinates":[6.160445,50.874329],"type":"Point"}
}