{
  "type": "Feature",
  "properties": {
    "iso:country":"DE",
    "sg:address":"Hauptstr. 38",
    "sg:city":"Kettig",
    "sg:phone":"+49 2637/4295",
    "sg:postcode":"56220",
    "sg:province":"Rheinland-Pfalz",
    "wof:name":"P. Hillesheim",
    "wof:placetype":"venue"
},
  "geometry": {"coordinates":[7.4599189758,50.3960075378],"type":"Point"}
}