{
  "type": "Feature",
  "properties": {
    "iso:country":"DE",
    "sg:address":"Am Kliepesch 8",
    "sg:city":"K\u00f6ln",
    "sg:phone":"+49 2234/497776",
    "sg:postcode":"50859",
    "sg:province":"Nordrhein-Westfalen",
    "wof:name":"Rodis Gesellschaft F\u00fcr Immobilien-beteiligungen Und",
    "wof:placetype":"venue"
},
  "geometry": {"coordinates":[6.8273320198,50.9360771179],"type":"Point"}
}