{
  "type": "Feature",
  "properties": {
    "iso:country":"DE",
    "sg:address":"Hilgenesch 26",
    "sg:city":"Billerbeck",
    "sg:phone":"+49 2543/4079",
    "sg:postcode":"48727",
    "sg:province":"Nordrhein-Westfalen",
    "wof:name":"Josef Schmitz Elektro Inst.",
    "wof:placetype":"venue"
},
  "geometry": {"coordinates":[7.283457,51.981674],"type":"Point"}
}