{
  "type": "Feature",
  "properties": {
    "iso:country":"DE",
    "sg:address":"Wallstr. 19",
    "sg:city":"Hillesheim",
    "sg:phone":"+49 6593/9209",
    "sg:postcode":"54576",
    "sg:province":"Rheinland-Pfalz",
    "wof:name":"Norma Lebensmittel- Filialbetrieb Gmbh & Co. Kg",
    "wof:placetype":"venue"
},
  "geometry": {"coordinates":[6.6706371307,50.2925682068],"type":"Point"}
}