{
  "type": "Feature",
  "properties": {
    "iso:country":"DE",
    "sg:address":"Ziolkowskistr. 63",
    "sg:city":"Schwerin",
    "sg:phone":"+49 385/2012864",
    "sg:postcode":"19063",
    "sg:province":"Mecklenburg-Vorpommern",
    "wof:name":"Gdanitz Gr\u00fcnwald & Lobenstein Ohg",
    "wof:placetype":"venue"
},
  "geometry": {"coordinates":[11.4744319916,53.58360672],"type":"Point"}
}