{
  "type": "Feature",
  "properties": {
    "iso:country":"DE",
    "sg:address":"Haydnstr. 35",
    "sg:city":"Balingen",
    "sg:phone":"+49 7433/7909",
    "sg:postcode":"72336",
    "sg:province":"Baden-W\u00fcrttemberg",
    "wof:name":"Adam Lebherz",
    "wof:placetype":"venue"
},
  "geometry": {"coordinates":[8.861484,48.272743],"type":"Point"}
}