{
  "type": "Feature",
  "properties": {
    "iso:country":"DE",
    "sg:address":"Rheinstr. 207",
    "sg:city":"Ingelheim",
    "sg:phone":"+49 6132/8157",
    "sg:postcode":"55218",
    "sg:province":"Rheinland-Pfalz",
    "wof:name":"Brigitte Fichtner",
    "wof:placetype":"venue"
},
  "geometry": {"coordinates":[8.02487,49.9897],"type":"Point"}
}