{
  "type": "Feature",
  "properties": {
    "iso:country":"DE",
    "sg:address":"Lindenplatz 9",
    "sg:city":"Sasbach",
    "sg:postcode":"77880",
    "sg:province":"Baden-W\u00fcrttemberg",
    "wof:name":"Ws Sport-studio Gmbh",
    "wof:placetype":"venue"
},
  "geometry": {"coordinates":[8.092782,48.639439],"type":"Point"}
}