{
  "type": "Feature",
  "properties": {
    "iso:country":"DE",
    "sg:address":"Hauptstr. 18",
    "sg:city":"Wiedensahl",
    "sg:phone":"+49 5726/344",
    "sg:postcode":"31719",
    "sg:province":"Niedersachsen",
    "wof:name":"Walter Prieur Inh. Siegfried Emme",
    "wof:placetype":"venue"
},
  "geometry": {"coordinates":[9.1200942993,52.3758087158],"type":"Point"}
}