{
  "type": "Feature",
  "properties": {
    "iso:country":"DE",
    "sg:address":"Ehrenbergerstr. 7",
    "sg:city":"Oberstdorf",
    "sg:phone":"+49 8322/3774",
    "sg:postcode":"87561",
    "sg:province":"Bayern",
    "wof:name":"Ulrich R\u00f6ssle Architekten",
    "wof:placetype":"venue"
},
  "geometry": {"coordinates":[10.276578,47.415237],"type":"Point"}
}