{
  "type": "Feature",
  "properties": {
    "iso:country":"DE",
    "sg:address":"Hanauer Str. 28",
    "sg:city":"Bad Vilbel",
    "sg:phone":"+49 6101/89506",
    "sg:postcode":"61118",
    "sg:province":"Hessen",
    "wof:name":"Konrad Stang",
    "wof:placetype":"venue"
},
  "geometry": {"coordinates":[8.7464208603,50.181892395],"type":"Point"}
}