{
  "type": "Feature",
  "properties": {
    "iso:country":"DE",
    "sg:address":"Stilles Tal 8",
    "sg:city":"Bad Oeynhausen",
    "sg:phone":"+49 5734/5501",
    "sg:postcode":"32549",
    "sg:province":"Nordrhein-Westfalen",
    "wof:name":"M. Bienek",
    "wof:placetype":"venue"
},
  "geometry": {"coordinates":[8.743721962,52.2536354065],"type":"Point"}
}