{
  "type": "Feature",
  "properties": {
    "iso:country":"DE",
    "sg:address":"\u00c4u\u00dfere M\u00fcnchener Str. 20",
    "sg:city":"Rosenheim",
    "sg:phone":"+49 8031/44010",
    "sg:postcode":"83026",
    "sg:province":"Bayern",
    "wof:name":"Grossmann Bau Verwaltungs Gmbh",
    "wof:placetype":"venue"
},
  "geometry": {"coordinates":[12.104566,47.852875],"type":"Point"}
}