{
  "type": "Feature",
  "properties": {
    "iso:country":"DE",
    "sg:address":"T\u00fcbinger Str. 61",
    "sg:city":"Reutlingen",
    "sg:phone":"+49 7121/387810",
    "sg:postcode":"72762",
    "sg:province":"Baden-W\u00fcrttemberg",
    "wof:name":"Universa Krankenversicherung Ag",
    "wof:placetype":"venue"
},
  "geometry": {"coordinates":[9.2005290985,48.492767334],"type":"Point"}
}