{
  "type": "Feature",
  "properties": {
    "iso:country":"DE",
    "sg:address":"Geitherstr. 43",
    "sg:city":"Neustadt",
    "sg:phone":"+49 6327/960216",
    "sg:postcode":"67435",
    "sg:province":"Rheinland-Pfalz",
    "wof:name":"Gerhard Mayer",
    "wof:placetype":"venue"
},
  "geometry": {"coordinates":[8.2522153854,49.3031425476],"type":"Point"}
}