{
  "type": "Feature",
  "properties": {
    "iso:country":"DE",
    "sg:address":"Hauptstr. 11",
    "sg:city":"Stadtbergen",
    "sg:phone":"+49 821/436703",
    "sg:postcode":"86391",
    "sg:province":"Bayern",
    "wof:name":"Hans Kammerer",
    "wof:placetype":"venue"
},
  "geometry": {"coordinates":[10.8375329971,48.3502540588],"type":"Point"}
}