{
  "type": "Feature",
  "properties": {
    "iso:country":"DE",
    "sg:address":"Bauhofstra\u00dfe 4",
    "sg:city":"Schwaig",
    "sg:phone":"+49 911",
    "sg:postcode":"90571",
    "sg:province":"Bayern",
    "wof:name":"Wittmann Hans - Fachhandel F\u00fcr Bau Und Industrie",
    "wof:placetype":"venue"
},
  "geometry": {"coordinates":[11.2031879425,49.4659194946],"type":"Point"}
}