{
  "type": "Feature",
  "properties": {
    "iso:country":"DE",
    "sg:address":"Allerfeldstr. 1",
    "sg:city":"Springe",
    "sg:phone":"+49 5045/9710",
    "sg:postcode":"31832",
    "sg:province":"Niedersachsen",
    "wof:name":"Landmaschinenvertrieb Bennigsen Gmbh",
    "wof:placetype":"venue"
},
  "geometry": {"coordinates":[9.6781387329,52.2338905334],"type":"Point"}
}