{
  "type": "Feature",
  "properties": {
    "iso:country":"DE",
    "sg:address":"Waldheimstr. 5",
    "sg:city":"Stuttgart",
    "sg:phone":"+49 711/1367330",
    "sg:postcode":"70435",
    "sg:province":"Baden-W\u00fcrttemberg",
    "wof:name":"Telenet Gmbh",
    "wof:placetype":"venue"
},
  "geometry": {"coordinates":[9.1493711472,48.8334999084],"type":"Point"}
}