{
  "type": "Feature",
  "properties": {
    "iso:country":"DE",
    "sg:address":"Hauptstr. 66",
    "sg:city":"Berlin",
    "sg:phone":"+49 30/850870",
    "sg:postcode":"12159",
    "sg:province":"Berlin",
    "wof:name":"Generali Lloyd Versicherung Ag",
    "wof:placetype":"venue"
},
  "geometry": {"coordinates":[13.3414497375,52.4768486023],"type":"Point"}
}