{
  "type": "Feature",
  "properties": {
    "iso:country":"DE",
    "sg:address":"Alfredstr. 41-43",
    "sg:city":"Essen",
    "sg:phone":"+49 201/8777666",
    "sg:postcode":"45130",
    "sg:province":"Nordrhein-Westfalen",
    "wof:name":"Musik-bar Fink",
    "wof:placetype":"venue"
},
  "geometry": {"coordinates":[7.003476,51.438072],"type":"Point"}
}