{
  "type": "Feature",
  "properties": {
    "iso:country":"DE",
    "sg:address":"An St. Adelheid 2-8",
    "sg:city":"K\u00f6ln",
    "sg:phone":"+49 221/891303",
    "sg:postcode":"51109",
    "sg:province":"Nordrhein-Westfalen",
    "wof:name":"Stadtb\u00fccherei K\u00f6ln Zweigstelle 22",
    "wof:placetype":"venue"
},
  "geometry": {"coordinates":[7.061175,50.934078],"type":"Point"}
}