{
  "type": "Feature",
  "properties": {
    "iso:country":"DE",
    "sg:address":"Liebenzeller Str. 6",
    "sg:city":"Stuttgart",
    "sg:phone":"+49 711/563260",
    "sg:postcode":"70372",
    "sg:province":"Baden-W\u00fcrttemberg",
    "wof:name":"Edelmar Krautter",
    "wof:placetype":"venue"
},
  "geometry": {"coordinates":[9.2171669006,48.8053588867],"type":"Point"}
}