{
  "type": "Feature",
  "properties": {
    "iso:country":"DE",
    "sg:address":"Bohnitzscher Str. 19 d",
    "sg:city":"Mei\u00dfen",
    "sg:phone":"+49 3521/738385",
    "sg:postcode":"01662",
    "sg:province":"Sachsen",
    "wof:name":"Zaeske Und Teske Rechtsanw\u00e4lte",
    "wof:placetype":"venue"
},
  "geometry": {"coordinates":[13.4999885559,51.1777687073],"type":"Point"}
}