{
  "type": "Feature",
  "properties": {
    "iso:country":"DE",
    "sg:address":"Wallnerstr. 6",
    "sg:city":"Tann",
    "sg:phone":"+49 8572/8825",
    "sg:postcode":"84367",
    "sg:province":"Bayern",
    "wof:name":"Dr. Oskar Kratzer Tierarzt",
    "wof:placetype":"venue"
},
  "geometry": {"coordinates":[12.888302803,48.3143730164],"type":"Point"}
}