{
  "type": "Feature",
  "properties": {
    "iso:country":"DE",
    "sg:address":"Zenettistr. 30",
    "sg:city":"M\u00fcnchen",
    "sg:phone":"+49 89/776566",
    "sg:postcode":"80337",
    "sg:province":"Bayern",
    "wof:name":"Fiakerst\u00fcberl",
    "wof:placetype":"venue"
},
  "geometry": {"coordinates":[11.5549545288,48.1251411438],"type":"Point"}
}