{
  "type": "Feature",
  "properties": {
    "iso:country":"DE",
    "sg:address":"Ortsstr 10",
    "sg:city":"W\u00f6hlsdorf",
    "sg:phone":"+49 3671/53230",
    "sg:postcode":"07318",
    "sg:province":"Th\u00fcringen",
    "wof:name":"Mws Mischwerk Saalfeld Gmbh + Co Kg",
    "wof:placetype":"venue"
},
  "geometry": {"coordinates":[11.3572,50.64835],"type":"Point"}
}