{
  "type": "Feature",
  "properties": {
    "iso:country":"DE",
    "sg:address":"Aschaffenburger Str. 41",
    "sg:city":"Seligenstadt",
    "sg:phone":"+49 6182/23360",
    "sg:postcode":"63500",
    "sg:province":"Hessen",
    "wof:name":"Capri",
    "wof:placetype":"venue"
},
  "geometry": {"coordinates":[8.975967,50.042263],"type":"Point"}
}