{
  "type": "Feature",
  "properties": {
    "iso:country":"DE",
    "sg:address":"Mittlerer Flurweg 21",
    "sg:city":"Bad Kreuznach",
    "sg:phone":"+49 671/65500",
    "sg:postcode":"55543",
    "sg:province":"Rheinland-Pfalz",
    "wof:name":"Hieronymus Senske",
    "wof:placetype":"venue"
},
  "geometry": {"coordinates":[7.869893074,49.8335762024],"type":"Point"}
}