{
  "type": "Feature",
  "properties": {
    "iso:country":"DE",
    "sg:address":"Leitenweg 4",
    "sg:city":"Tutzing",
    "sg:phone":"+49 8157/2068",
    "sg:postcode":"82327",
    "sg:province":"Bayern",
    "wof:name":"K. H. Hoppe Elektroinstallation",
    "wof:placetype":"venue"
},
  "geometry": {"coordinates":[11.252265,47.936832],"type":"Point"}
}