{
  "type": "Feature",
  "properties": {
    "iso:country":"DE",
    "sg:address":"Hans-Rasch-Weg",
    "sg:city":"Ebstorf",
    "sg:phone":"+49 5822/947529",
    "sg:postcode":"29574",
    "sg:province":"Niedersachsen",
    "wof:name":"Frei- Und Hallenbad",
    "wof:placetype":"venue"
},
  "geometry": {"coordinates":[10.4161996841,53.0328865051],"type":"Point"}
}