{
  "type": "Feature",
  "properties": {
    "iso:country":"DE",
    "sg:address":"Am Stockacker 8",
    "sg:city":"Waldsolms",
    "sg:phone":"+49 6085/9899884",
    "sg:postcode":"35647",
    "sg:province":"Hessen",
    "wof:name":"Versicherungen Deutscher Herold",
    "wof:placetype":"venue"
},
  "geometry": {"coordinates":[8.4916467667,50.405216217],"type":"Point"}
}