{
  "type": "Feature",
  "properties": {
    "iso:country":"DE",
    "sg:address":"Hauptstr. 73",
    "sg:city":"Elze",
    "sg:phone":"+49 5068/2468",
    "sg:postcode":"31008",
    "sg:province":"Niedersachsen",
    "wof:name":"Hans Schmidt Architekt",
    "wof:placetype":"venue"
},
  "geometry": {"coordinates":[9.736039,52.121258],"type":"Point"}
}