{
  "type": "Feature",
  "properties": {
    "iso:country":"DE",
    "sg:address":"Markt 26",
    "sg:city":"Burg",
    "sg:phone":"+49 3921/989032",
    "sg:postcode":"39288",
    "sg:province":"Sachsen-Anhalt",
    "wof:name":"H\u00e4rtel",
    "wof:placetype":"venue"
},
  "geometry": {"coordinates":[11.8563098907,52.2705001831],"type":"Point"}
}