{
  "type": "Feature",
  "properties": {
    "iso:country":"DE",
    "sg:address":"Wallstr. 82",
    "sg:city":"Br\u00fchl",
    "sg:phone":"+49 2232/42317",
    "sg:postcode":"50321",
    "sg:province":"Nordrhein-Westfalen",
    "wof:name":"Christian Meyer Nachfolger Ohg",
    "wof:placetype":"venue"
},
  "geometry": {"coordinates":[6.9032430649,50.8290481567],"type":"Point"}
}