{
  "type": "Feature",
  "properties": {
    "iso:country":"DE",
    "sg:address":"Br\u00fcnnsteinstr. 40",
    "sg:city":"Kiefersfelden",
    "sg:phone":"+49 8033/6655",
    "sg:postcode":"83088",
    "sg:province":"Bayern",
    "wof:name":"Baumgartenhof C. Kurz",
    "wof:placetype":"venue"
},
  "geometry": {"coordinates":[12.1572341919,47.6196403503],"type":"Point"}
}