{
  "type": "Feature",
  "properties": {
    "iso:country":"DE",
    "sg:address":"Kasinostr. 5",
    "sg:city":"Darmstadt",
    "sg:phone":"+49 6151/27030",
    "sg:postcode":"64293",
    "sg:province":"Hessen",
    "wof:name":"Gvp Treuhand Und Verm\u00f6gensverwaltung Ag",
    "wof:placetype":"venue"
},
  "geometry": {"coordinates":[8.6443119049,49.8728408813],"type":"Point"}
}