{
  "type": "Feature",
  "properties": {
    "iso:country":"DE",
    "sg:address":"Hauptstr. 4",
    "sg:city":"Mertesdorf",
    "sg:phone":"+49 651/52434",
    "sg:postcode":"54318",
    "sg:province":"Rheinland-Pfalz",
    "wof:name":"Gr\u00fcnh\u00e4user M\u00fchle",
    "wof:placetype":"venue"
},
  "geometry": {"coordinates":[6.7203941345,49.7719116211],"type":"Point"}
}