{
  "type": "Feature",
  "properties": {
    "iso:country":"DE",
    "sg:address":"Rheinblickstr. 20",
    "sg:city":"Erpel",
    "sg:phone":"+49 2644/7455",
    "sg:postcode":"53579",
    "sg:province":"Rheinland-Pfalz",
    "wof:name":"P. Von Lauvenberg Steuerberater",
    "wof:placetype":"venue"
},
  "geometry": {"coordinates":[7.2413568497,50.5907478333],"type":"Point"}
}