{
  "type": "Feature",
  "properties": {
    "iso:country":"DE",
    "sg:address":"Subbelrather Str. 195",
    "sg:city":"K\u00f6ln",
    "sg:phone":"+49 221/554359",
    "sg:postcode":"50823",
    "sg:province":"Nordrhein-Westfalen",
    "wof:name":"Cine Top Videothek",
    "wof:placetype":"venue"
},
  "geometry": {"coordinates":[6.9219260216,50.9530181885],"type":"Point"}
}