{
  "type": "Feature",
  "properties": {
    "iso:country":"DE",
    "sg:address":"Bad Cannstatt Marktstr 3",
    "sg:city":"Stuttgart",
    "sg:phone":"+49 711/1243544",
    "sg:postcode":"70173",
    "sg:province":"Baden-W\u00fcrttemberg",
    "wof:name":"Landesgirokasse \u00f6ffentliche Bank",
    "wof:placetype":"venue"
},
  "geometry": {"coordinates":[9.179908,48.776001],"type":"Point"}
}