{
  "type": "Feature",
  "properties": {
    "iso:country":"DE",
    "sg:address":"Niederauer Str.",
    "sg:city":"Mei\u00dfen",
    "sg:phone":"+49 3521/72040",
    "sg:postcode":"01662",
    "sg:province":"Sachsen",
    "wof:name":"Kaufland",
    "wof:placetype":"venue"
},
  "geometry": {"coordinates":[13.4987602234,51.1671218872],"type":"Point"}
}