{
  "type": "Feature",
  "properties": {
    "iso:country":"DE",
    "sg:address":"R\u00f6ddeliner Str. 11",
    "sg:city":"Templin",
    "sg:phone":"+49 3987/6277",
    "sg:postcode":"17268",
    "sg:province":"Brandenburg",
    "wof:name":"Dr. Med. Siegfried Hoffmann",
    "wof:placetype":"venue"
},
  "geometry": {"coordinates":[13.488227,53.121761],"type":"Point"}
}