{
  "type": "Feature",
  "properties": {
    "iso:country":"DE",
    "sg:address":"Mariaberger Str. 37",
    "sg:city":"Kempten",
    "sg:phone":"+49 831/93880",
    "sg:postcode":"87439",
    "sg:province":"Bayern",
    "wof:name":"Gruber",
    "wof:placetype":"venue"
},
  "geometry": {"coordinates":[10.2978277206,47.7337188721],"type":"Point"}
}