{
  "type": "Feature",
  "properties": {
    "iso:country":"DE",
    "sg:address":"R\u00fcsselsheimer Str. 159",
    "sg:city":"Kelsterbach",
    "sg:phone":"+49 6107/61434",
    "sg:postcode":"65451",
    "sg:province":"Hessen",
    "wof:name":"F.-u. Kunz",
    "wof:placetype":"venue"
},
  "geometry": {"coordinates":[8.520353,50.059662],"type":"Point"}
}