{
  "type": "Feature",
  "properties": {
    "iso:country":"DE",
    "sg:address":"Schulstr. 20",
    "sg:city":"Kenzingen",
    "sg:phone":"+49 7644/8431",
    "sg:postcode":"79341",
    "sg:province":"Baden-W\u00fcrttemberg",
    "wof:name":"J\u00fcrgen Pixberg Heilpraktiker",
    "wof:placetype":"venue"
},
  "geometry": {"coordinates":[7.766204834,48.1938438416],"type":"Point"}
}