{
  "type": "Feature",
  "properties": {
    "iso:country":"DE",
    "sg:address":"Kirchenstr. 4",
    "sg:city":"M\u00fcnchen",
    "sg:phone":"+49 89/4802505",
    "sg:postcode":"81675",
    "sg:province":"Bayern",
    "wof:name":"M\u00f6bel K\u00fchlfluck",
    "wof:placetype":"venue"
},
  "geometry": {"coordinates":[11.59967,48.134243],"type":"Point"}
}