{
  "type": "Feature",
  "properties": {
    "iso:country":"DE",
    "sg:address":"Schlo\u00dfstr. 3",
    "sg:city":"Gelchsheim",
    "sg:phone":"+49 9335/1516",
    "sg:postcode":"97255",
    "sg:province":"Bayern",
    "wof:name":"Gabriele Wengel-lanig Architektin",
    "wof:placetype":"venue"
},
  "geometry": {"coordinates":[10.022137,49.572456],"type":"Point"}
}