{
  "type": "Feature",
  "properties": {
    "iso:country":"DE",
    "sg:address":"Dr.-Wolfgang-Kr\u00e4mer-Str. 11",
    "sg:city":"St. Ingbert",
    "sg:phone":"+49 6894/2444",
    "sg:postcode":"66386",
    "sg:province":"Saarland",
    "wof:name":"Colbus Und Engel Rechtsanw\u00e4lte",
    "wof:placetype":"venue"
},
  "geometry": {"coordinates":[7.116350174,49.275428772],"type":"Point"}
}