{
  "type": "Feature",
  "properties": {
    "iso:country":"DE",
    "sg:address":"Auf der Hohwisch 32 a",
    "sg:city":"Bremen",
    "sg:phone":"+49 421/447678",
    "sg:postcode":"28207",
    "sg:province":"Bremen",
    "wof:name":"Helmut Schmidt Steuerberater",
    "wof:placetype":"venue"
},
  "geometry": {"coordinates":[8.8551425934,53.0668525696],"type":"Point"}
}