{
  "type": "Feature",
  "properties": {
    "iso:country":"DE",
    "sg:address":"Zur Ziese 17",
    "sg:city":"Bremen",
    "sg:phone":"+49 421/480050",
    "sg:postcode":"28307",
    "sg:province":"Bremen",
    "wof:name":"Johann Meier",
    "wof:placetype":"venue"
},
  "geometry": {"coordinates":[8.9245376587,53.0420227051],"type":"Point"}
}