{
  "type": "Feature",
  "properties": {
    "iso:country":"DE",
    "sg:address":"Hauptstr. 32",
    "sg:city":"Dassel",
    "sg:phone":"+49 5564/1633",
    "sg:postcode":"37586",
    "sg:province":"Niedersachsen",
    "wof:name":"Sollingkrug Inh. Markus Koch",
    "wof:placetype":"venue"
},
  "geometry": {"coordinates":[9.7261886597,51.7717819214],"type":"Point"}
}