{
  "type": "Feature",
  "properties": {
    "iso:country":"DE",
    "sg:address":"Schwalbenst\u00fcck 68",
    "sg:city":"Dorsten",
    "sg:phone":"+49 2369/6192",
    "sg:postcode":"46286",
    "sg:province":"Nordrhein-Westfalen",
    "wof:name":"Onwheels E.v.",
    "wof:placetype":"venue"
},
  "geometry": {"coordinates":[7.0489959717,51.7406044006],"type":"Point"}
}