{
  "type": "Feature",
  "properties": {
    "iso:country":"DE",
    "sg:address":"Bathildisstr. 3",
    "sg:city":"Bad Pyrmont",
    "sg:phone":"+49 5281/5182",
    "sg:postcode":"31812",
    "sg:province":"Niedersachsen",
    "wof:name":"Bennefeld Gmbh",
    "wof:placetype":"venue"
},
  "geometry": {"coordinates":[9.255839,51.984558],"type":"Point"}
}