{
  "type": "Feature",
  "properties": {
    "iso:country":"DE",
    "sg:address":"Rotlintstr. 60",
    "sg:city":"Frankfurt",
    "sg:phone":"+49 69/449691",
    "sg:postcode":"60316",
    "sg:province":"Hessen",
    "wof:name":"Cafe Rotlint",
    "wof:placetype":"venue"
},
  "geometry": {"coordinates":[8.694351,50.126755],"type":"Point"}
}