{
  "type": "Feature",
  "properties": {
    "iso:country":"DE",
    "sg:address":"Fl\u00e4mingstr.",
    "sg:city":"Berlin",
    "sg:phone":"+49 30",
    "sg:postcode":"12689",
    "sg:province":"Berlin",
    "wof:name":"Reiseservice Torsten Schwant",
    "wof:placetype":"venue"
},
  "geometry": {"coordinates":[13.565235,52.565811],"type":"Point"}
}