{
  "type": "Feature",
  "properties": {
    "iso:country":"DE",
    "sg:address":"Im Wennetal 20",
    "sg:city":"Eslohe",
    "sg:phone":"+49 2973/97170",
    "sg:postcode":"59889",
    "sg:province":"Nordrhein-Westfalen",
    "wof:name":"Kremer Und Brunert Gmbh",
    "wof:placetype":"venue"
},
  "geometry": {"coordinates":[8.2005987167,51.2532310486],"type":"Point"}
}