{
  "type": "Feature",
  "properties": {
    "iso:country":"DE",
    "sg:address":"Distelnblech 1",
    "sg:city":"Werdohl",
    "sg:phone":"+49 2392/7912",
    "sg:postcode":"58791",
    "sg:province":"Nordrhein-Westfalen",
    "wof:name":"Hermann Terlutter",
    "wof:placetype":"venue"
},
  "geometry": {"coordinates":[7.7397990227,51.2238845825],"type":"Point"}
}