{
  "type": "Feature",
  "properties": {
    "iso:country":"DE",
    "sg:address":"Industriestr. 6",
    "sg:city":"D\u00fclmen",
    "sg:phone":"+49 2594/91170",
    "sg:postcode":"48249",
    "sg:province":"Nordrhein-Westfalen",
    "wof:name":"Metallbau Van Der Berg Gmbh",
    "wof:placetype":"venue"
},
  "geometry": {"coordinates":[7.30169,51.820438],"type":"Point"}
}