{
  "type": "Feature",
  "properties": {
    "iso:country":"DE",
    "sg:address":"Lerchenweg 54",
    "sg:city":"Nidderau",
    "sg:phone":"+49 6187/21498",
    "sg:postcode":"61130",
    "sg:province":"Hessen",
    "wof:name":"Adec Analogdigital-ent- Wicklung Und Cad Gmbh",
    "wof:placetype":"venue"
},
  "geometry": {"coordinates":[8.9134302139,50.219959259],"type":"Point"}
}