{
  "type": "Feature",
  "properties": {
    "iso:country":"DE",
    "sg:address":"Georgstr. 1",
    "sg:city":"Poppenhausen",
    "sg:phone":"+49 6658/298",
    "sg:postcode":"36163",
    "sg:province":"Hessen",
    "wof:name":"Gustav Ebert",
    "wof:placetype":"venue"
},
  "geometry": {"coordinates":[9.865745,50.489273],"type":"Point"}
}