{
  "type": "Feature",
  "properties": {
    "iso:country":"DE",
    "sg:address":"Maxhofstr. 55",
    "sg:city":"M\u00fcnchen",
    "sg:phone":"+49 89/758828",
    "sg:postcode":"81475",
    "sg:province":"Bayern",
    "wof:name":"Anton Silberschneider",
    "wof:placetype":"venue"
},
  "geometry": {"coordinates":[11.4749298096,48.0835342407],"type":"Point"}
}