{
  "type": "Feature",
  "properties": {
    "iso:country":"DE",
    "sg:address":"Seifenwiesenweg 37",
    "sg:city":"Lautertal",
    "sg:phone":"+49 6254/2500",
    "sg:postcode":"64686",
    "sg:province":"Hessen",
    "wof:name":"H. G. Kindinger Grabdenkm\u00e4ler",
    "wof:placetype":"venue"
},
  "geometry": {"coordinates":[8.6925210953,49.7179985046],"type":"Point"}
}