{
  "type": "Feature",
  "properties": {
    "iso:country":"DE",
    "sg:address":"Am Reitweg 14",
    "sg:city":"Belgershain",
    "sg:phone":"+49 34293/33782",
    "sg:postcode":"04683",
    "sg:province":"Sachsen",
    "wof:name":"H. Bretschneider",
    "wof:placetype":"venue"
},
  "geometry": {"coordinates":[12.561752,51.24802],"type":"Point"}
}