{
  "type": "Feature",
  "properties": {
    "iso:country":"DE",
    "sg:address":"Spannstiftstr 39",
    "sg:city":"Hagen",
    "sg:phone":"+49 2334/96030",
    "sg:postcode":"58119",
    "sg:province":"Nordrhein-Westfalen",
    "wof:name":"Fudickar-metall Gmbh",
    "wof:placetype":"venue"
},
  "geometry": {"coordinates":[7.543288,51.373508],"type":"Point"}
}