{
  "type": "Feature",
  "properties": {
    "iso:country":"DE",
    "sg:address":"Saaruferstr. 11",
    "sg:city":"Saarbr\u00fccken",
    "sg:postcode":"66117",
    "sg:province":"Saarland",
    "wof:name":"Saarmobil Car Sharing Gmbh",
    "wof:placetype":"venue"
},
  "geometry": {"coordinates":[6.9904742241,49.235042572],"type":"Point"}
}