{
  "type": "Feature",
  "properties": {
    "iso:country":"DE",
    "sg:address":"Zum Scheider Feld 57",
    "sg:city":"Bergisch Gladbach",
    "sg:phone":"+49 2202/98490",
    "sg:postcode":"51467",
    "sg:province":"Nordrhein-Westfalen",
    "wof:name":"Franz Dewes Gmbh & Co.",
    "wof:placetype":"venue"
},
  "geometry": {"coordinates":[7.0894517899,51.0194168091],"type":"Point"}
}