{
  "type": "Feature",
  "properties": {
    "iso:country":"DE",
    "sg:address":"Hospitalstr. 9",
    "sg:city":"Viersen",
    "sg:phone":"+49 2162/41088",
    "sg:postcode":"41751",
    "sg:province":"Nordrhein-Westfalen",
    "wof:name":"Cafe Istanbul",
    "wof:placetype":"venue"
},
  "geometry": {"coordinates":[6.3350601196,51.2501411438],"type":"Point"}
}