{
  "type": "Feature",
  "properties": {
    "iso:country":"DE",
    "sg:address":"Igelhecke 22",
    "sg:city":"Stuttgart",
    "sg:phone":"+49 711/532291",
    "sg:postcode":"70378",
    "sg:province":"Baden-W\u00fcrttemberg",
    "wof:name":"Hans Hermet",
    "wof:placetype":"venue"
},
  "geometry": {"coordinates":[9.227756,48.827106],"type":"Point"}
}