{
  "type": "Feature",
  "properties": {
    "iso:country":"DE",
    "sg:address":"Hedem\u00fcndener Str. 43",
    "sg:city":"Hann. M\u00fcnden",
    "sg:phone":"+49 5541/7065",
    "sg:postcode":"34346",
    "sg:province":"Niedersachsen",
    "wof:name":"Storopack Hans Reichenecker Gmbh & Co.",
    "wof:placetype":"venue"
},
  "geometry": {"coordinates":[9.67187,51.417591],"type":"Point"}
}