{
  "type": "Feature",
  "properties": {
    "iso:country":"DE",
    "sg:address":"Wippenbacher Str. 53",
    "sg:city":"Ortenberg",
    "sg:phone":"+49 6046/441",
    "sg:postcode":"63683",
    "sg:province":"Hessen",
    "wof:name":"Werner Pitzius Steuerberater",
    "wof:placetype":"venue"
},
  "geometry": {"coordinates":[9.0442562103,50.3559379578],"type":"Point"}
}