{
  "type": "Feature",
  "properties": {
    "iso:country":"DE",
    "sg:address":"Hauptstr. 56",
    "sg:city":"Syke",
    "sg:phone":"+49 4242/5569",
    "sg:postcode":"28857",
    "sg:province":"Niedersachsen",
    "wof:name":"Buddelei- Mode Gmbh",
    "wof:placetype":"venue"
},
  "geometry": {"coordinates":[8.817744,52.914627],"type":"Point"}
}