{
  "type": "Feature",
  "properties": {
    "iso:country":"DE",
    "sg:address":"Hofmarkstr. 17",
    "sg:city":"Roding",
    "sg:phone":"+49 9461/1371",
    "sg:postcode":"93426",
    "sg:province":"Bayern",
    "wof:name":"Gastst\u00e4tte Willi Fleischmann",
    "wof:placetype":"venue"
},
  "geometry": {"coordinates":[12.4991912842,49.2425765991],"type":"Point"}
}