{
  "type": "Feature",
  "properties": {
    "iso:country":"DE",
    "sg:address":"Weichter Str. 8",
    "sg:city":"Buchloe",
    "sg:phone":"+49 8241/4752",
    "sg:postcode":"86807",
    "sg:province":"Bayern",
    "wof:name":"Wolfgang Sch\u00fctz",
    "wof:placetype":"venue"
},
  "geometry": {"coordinates":[10.712067,48.03336],"type":"Point"}
}