{
  "type": "Feature",
  "properties": {
    "iso:country":"DE",
    "sg:address":"Alte Vlothoer Str. 45-51",
    "sg:city":"Bad Salzuflen",
    "sg:phone":"+49 5222/16513",
    "sg:postcode":"32105",
    "sg:province":"Nordrhein-Westfalen",
    "wof:name":"Wohnstift Am Vierenberg",
    "wof:placetype":"venue"
},
  "geometry": {"coordinates":[8.763317,52.096237],"type":"Point"}
}