{
  "type": "Feature",
  "properties": {
    "iso:country":"DE",
    "sg:address":"Wittringer Str. 21",
    "sg:city":"Gladbeck",
    "sg:phone":"+49 2043/681495",
    "sg:postcode":"45964",
    "sg:province":"Nordrhein-Westfalen",
    "wof:name":"Van B\u00fcrk Datentechnik Gmbh",
    "wof:placetype":"venue"
},
  "geometry": {"coordinates":[6.981028,51.569939],"type":"Point"}
}