{
  "type": "Feature",
  "properties": {
    "iso:country":"DE",
    "sg:address":"Thomaspfad 1",
    "sg:city":"Goch",
    "sg:phone":"+49 2823/7264",
    "sg:postcode":"47574",
    "sg:province":"Nordrhein-Westfalen",
    "wof:name":"Theo Spenner Architekt",
    "wof:placetype":"venue"
},
  "geometry": {"coordinates":[6.149299,51.669537],"type":"Point"}
}