{
  "type": "Feature",
  "properties": {
    "iso:country":"DE",
    "sg:address":"Am Neuen Rheinhafen 14",
    "sg:city":"Speyer",
    "sg:postcode":"67346",
    "sg:province":"Rheinland-Pfalz",
    "wof:name":"Josef Braun Verwaltungs- Gmbh",
    "wof:placetype":"venue"
},
  "geometry": {"coordinates":[8.455056,49.308739],"type":"Point"}
}