{
  "type": "Feature",
  "properties": {
    "iso:country":"DE",
    "sg:address":"In den Erlen 16",
    "sg:city":"Edenkoben",
    "sg:phone":"+49 6323/6623",
    "sg:postcode":"67480",
    "sg:province":"Rheinland-Pfalz",
    "wof:name":"Christine Frank Hebamme",
    "wof:placetype":"venue"
},
  "geometry": {"coordinates":[8.125015,49.286598],"type":"Point"}
}