{
  "type": "Feature",
  "properties": {
    "iso:country":"DE",
    "sg:address":"Ebersbacher Str. 2",
    "sg:city":"Aschaffenburg",
    "sg:phone":"+49 6021/98850",
    "sg:postcode":"63743",
    "sg:province":"Bayern",
    "wof:name":"Wolfgang Schalwig Rechtsanwalt",
    "wof:placetype":"venue"
},
  "geometry": {"coordinates":[9.1645097733,49.955909729],"type":"Point"}
}