{
  "type": "Feature",
  "properties": {
    "iso:country":"DE",
    "sg:address":"Freckenhorster Str. 73",
    "sg:city":"Warendorf",
    "sg:phone":"+49 2581/1787",
    "sg:postcode":"48231",
    "sg:province":"Nordrhein-Westfalen",
    "wof:name":"Manfred Graupe",
    "wof:placetype":"venue"
},
  "geometry": {"coordinates":[7.984431,51.943321],"type":"Point"}
}