{
  "type": "Feature",
  "properties": {
    "iso:country":"DE",
    "sg:address":"Schmaler Stieg 2",
    "sg:city":"L\u00fcbeck",
    "sg:phone":"+49 451/301947",
    "sg:postcode":"23569",
    "sg:province":"Schleswig-Holstein",
    "wof:name":"Wilfried Sacher",
    "wof:placetype":"venue"
},
  "geometry": {"coordinates":[10.8035640717,53.9091949463],"type":"Point"}
}