{
  "type": "Feature",
  "properties": {
    "iso:country":"DE",
    "sg:address":"Motorstra\u00dfe 37",
    "sg:city":"Stuttgart",
    "sg:phone":"+49 711",
    "sg:postcode":"70499",
    "sg:province":"Baden-W\u00fcrttemberg",
    "wof:name":"Finas Gmbh",
    "wof:placetype":"venue"
},
  "geometry": {"coordinates":[9.0983972549,48.8255577087],"type":"Point"}
}