{
  "type": "Feature",
  "properties": {
    "iso:country":"DE",
    "sg:address":"Plaggestr. 32",
    "sg:city":"Schortens",
    "sg:postcode":"26419",
    "sg:province":"Niedersachsen",
    "wof:name":"Friedhofsg\u00e4rtnerei Garlichs Inh. Michael Bartels E. K.",
    "wof:placetype":"venue"
},
  "geometry": {"coordinates":[7.953109,53.530128],"type":"Point"}
}