{
  "type": "Feature",
  "properties": {
    "iso:country":"DE",
    "sg:address":"Schwanenstr. 9",
    "sg:city":"Bernkastel-Kues",
    "sg:phone":"+49 6531/3650",
    "sg:postcode":"54470",
    "sg:province":"Rheinland-Pfalz",
    "wof:name":"Reblaus Keller",
    "wof:placetype":"venue"
},
  "geometry": {"coordinates":[7.0757460594,49.916103363],"type":"Point"}
}