{
  "type": "Feature",
  "properties": {
    "iso:country":"DE",
    "sg:address":"Am Markt 24",
    "sg:city":"Bad Salzuflen",
    "sg:phone":"+49 5222/4168",
    "sg:postcode":"32105",
    "sg:province":"Nordrhein-Westfalen",
    "wof:name":"Ratsst\u00fcbl",
    "wof:placetype":"venue"
},
  "geometry": {"coordinates":[8.7472467422,52.0838165283],"type":"Point"}
}