{
  "type": "Feature",
  "properties": {
    "iso:country":"DE",
    "sg:address":"Zollenspieker Hauptdeich 92",
    "sg:city":"Hamburg",
    "sg:phone":"+49 40/7230722",
    "sg:postcode":"21037",
    "sg:province":"Hamburg",
    "wof:name":"Werner Alexander",
    "wof:placetype":"venue"
},
  "geometry": {"coordinates":[10.190697,53.402378],"type":"Point"}
}