{
  "type": "Feature",
  "properties": {
    "iso:country":"DE",
    "sg:address":"Wiesenstr. 6",
    "sg:city":"Uenglingen",
    "sg:postcode":"39579",
    "sg:province":"Sachsen-Anhalt",
    "wof:name":"Sitefashion - Internet-rundum-service",
    "wof:placetype":"venue"
},
  "geometry": {"coordinates":[11.8158,52.616165],"type":"Point"}
}