{
  "type": "Feature",
  "properties": {
    "iso:country":"DE",
    "sg:address":"Mei\u00dfner Str. 117",
    "sg:city":"Radebeul",
    "sg:phone":"+49 351/8303477",
    "sg:postcode":"01445",
    "sg:province":"Sachsen",
    "wof:name":"Gerhard Mende",
    "wof:placetype":"venue"
},
  "geometry": {"coordinates":[13.664637,51.104912],"type":"Point"}
}