{
  "type": "Feature",
  "properties": {
    "iso:country":"DE",
    "sg:address":"Am Flo\u00dfgraben 4",
    "sg:city":"Neustadt",
    "sg:phone":"+49 9568/891067",
    "sg:postcode":"96465",
    "sg:province":"Bayern",
    "wof:name":"Oscar H\u00e4fner",
    "wof:placetype":"venue"
},
  "geometry": {"coordinates":[11.1336240768,50.3352088928],"type":"Point"}
}