{
  "type": "Feature",
  "properties": {
    "iso:country":"DE",
    "sg:address":"Hauptstr. 55",
    "sg:city":"Neuenhagen",
    "sg:postcode":"15366",
    "sg:province":"Brandenburg",
    "wof:name":"Dr. Gerh. Wellmitz",
    "wof:placetype":"venue"
},
  "geometry": {"coordinates":[13.695724,52.525383],"type":"Point"}
}