{
  "type": "Feature",
  "properties": {
    "iso:country":"DE",
    "sg:address":"Quedlinburger Str. 22",
    "sg:city":"Weddersleben",
    "sg:phone":"+49 3946/3410",
    "sg:postcode":"06502",
    "sg:province":"Sachsen-Anhalt",
    "wof:name":"Dr. Med. Immo Stubbe Tierarzt",
    "wof:placetype":"venue"
},
  "geometry": {"coordinates":[11.089021,51.760979],"type":"Point"}
}