{
  "type": "Feature",
  "properties": {
    "iso:country":"DE",
    "sg:address":"Grambauerstr. 32",
    "sg:city":"Schwedt",
    "sg:phone":"+49 3332/33279",
    "sg:postcode":"16303",
    "sg:province":"Brandenburg",
    "wof:name":"Schwedter Wohnungsunternehmen Gmbh",
    "wof:placetype":"venue"
},
  "geometry": {"coordinates":[14.2548656464,53.0610046387],"type":"Point"}
}