{
  "type": "Feature",
  "properties": {
    "iso:country":"DE",
    "sg:address":"M\u00fcllergasse 5",
    "sg:city":"Algermissen",
    "sg:phone":"+49 5126/1070",
    "sg:postcode":"31191",
    "sg:province":"Niedersachsen",
    "wof:name":"Wasilus",
    "wof:placetype":"venue"
},
  "geometry": {"coordinates":[9.9230279922,52.2707824707],"type":"Point"}
}