{
  "type": "Feature",
  "properties": {
    "iso:country":"DE",
    "sg:city":"Ostfildern",
    "sg:postcode":"47376",
    "sg:province":"Baden-W\u00fcrttemberg",
    "wof:name":"Raisch Garten- Und Landschaftsbau Gmbh",
    "wof:placetype":"venue"
},
  "geometry": {"coordinates":[-102.809928894,21.163230896],"type":"Point"}
}