{
  "type": "Feature",
  "properties": {
    "iso:country":"DE",
    "sg:address":"Ernst-Ludwig-Str. 73",
    "sg:city":"W\u00f6llstein",
    "sg:phone":"+49 6703/1200",
    "sg:postcode":"55597",
    "sg:province":"Rheinland-Pfalz",
    "wof:name":"Rathgeber",
    "wof:placetype":"venue"
},
  "geometry": {"coordinates":[7.966272831,49.8172683716],"type":"Point"}
}