{
  "type": "Feature",
  "properties": {
    "iso:country":"DE",
    "sg:address":"Erbschl\u00f6er Str. 17",
    "sg:city":"Wuppertal",
    "sg:phone":"+49 202/461007",
    "sg:postcode":"42369",
    "sg:province":"Nordrhein-Westfalen",
    "wof:name":"M. Benninghoven-rodig Rechtsanw\u00e4ltin",
    "wof:placetype":"venue"
},
  "geometry": {"coordinates":[7.2128620148,51.2374267578],"type":"Point"}
}