{
  "type": "Feature",
  "properties": {
    "iso:country":"DE",
    "sg:address":"Berliner Str. 134",
    "sg:city":"Homburg",
    "sg:phone":"+49 6841/701100",
    "sg:postcode":"66424",
    "sg:province":"Saarland",
    "wof:name":"Ina Sch\u00c4ffler Kg",
    "wof:placetype":"venue"
},
  "geometry": {"coordinates":[7.346557,49.340977],"type":"Point"}
}