{
  "type": "Feature",
  "properties": {
    "iso:country":"DE",
    "sg:address":"Lange Str. 35",
    "sg:city":"S\u00fc\u00dfen",
    "sg:phone":"+49 7162/7555",
    "sg:postcode":"73079",
    "sg:province":"Baden-W\u00fcrttemberg",
    "wof:name":"D\u00f6lzersche Apotheke",
    "wof:placetype":"venue"
},
  "geometry": {"coordinates":[9.759902,48.681812],"type":"Point"}
}