{
  "type": "Feature",
  "properties": {
    "iso:country":"DE",
    "sg:address":"Bremer Str. 40",
    "sg:city":"Hamburg",
    "sg:phone":"+49 40/772033",
    "sg:postcode":"21073",
    "sg:province":"Hamburg",
    "wof:name":"Boutique Sch\u00f6ne Welt",
    "wof:placetype":"venue"
},
  "geometry": {"coordinates":[9.934877,53.436756],"type":"Point"}
}