{
  "type": "Feature",
  "properties": {
    "iso:country":"DE",
    "sg:address":"Genthiner Str. 17",
    "sg:city":"Havelberg",
    "sg:phone":"+49 39387/970",
    "sg:postcode":"39539",
    "sg:province":"Sachsen-Anhalt",
    "wof:name":"Kreisarchiv Au\u00dfenstelle Havelberg",
    "wof:placetype":"venue"
},
  "geometry": {"coordinates":[12.071868,52.820187],"type":"Point"}
}