{
  "type": "Feature",
  "properties": {
    "iso:country":"DE",
    "sg:address":"Wiesenstr. 20",
    "sg:city":"Tespe",
    "sg:phone":"+49 4176/912359",
    "sg:postcode":"21395",
    "sg:province":"Niedersachsen",
    "wof:name":"Ambulante Senioren- Betreuung Und Kranken-",
    "wof:placetype":"venue"
},
  "geometry": {"coordinates":[10.415078,53.397377],"type":"Point"}
}