{
  "type": "Feature",
  "properties": {
    "iso:country":"DE",
    "sg:address":"Niehler Kirchweg 124",
    "sg:city":"K\u00f6ln",
    "sg:phone":"+49 221/7601904",
    "sg:postcode":"50733",
    "sg:province":"Nordrhein-Westfalen",
    "wof:name":"Dragemo Ohg W. Budkammer",
    "wof:placetype":"venue"
},
  "geometry": {"coordinates":[6.95517,50.97229],"type":"Point"}
}