{
  "type": "Feature",
  "properties": {
    "iso:country":"DE",
    "sg:address":"Max-Eyth-Str. 23",
    "sg:city":"Oberboihingen",
    "sg:phone":"+49 4970/2296640",
    "sg:postcode":"72644",
    "sg:province":"Baden-W\u00fcrttemberg",
    "wof:name":"Layh Holzbau Gmbh",
    "wof:placetype":"venue"
},
  "geometry": {"coordinates":[9.3630771637,48.6527519226],"type":"Point"}
}