{
  "type": "Feature",
  "properties": {
    "iso:country":"DE",
    "sg:address":"Anne-Frank-Str. 4",
    "sg:city":"Viernheim",
    "sg:postcode":"68519",
    "sg:province":"Hessen",
    "wof:name":"Hildebrand Dokumentations- Technik Gmbh",
    "wof:placetype":"venue"
},
  "geometry": {"coordinates":[8.5682420731,49.5278320312],"type":"Point"}
}