{
  "type": "Feature",
  "properties": {
    "iso:country":"DE",
    "sg:address":"Striegauer Str. 11",
    "sg:city":"Bielefeld",
    "sg:postcode":"33719",
    "sg:province":"Nordrhein-Westfalen",
    "wof:name":"Palu-soft Verwaltungs Gmbh",
    "wof:placetype":"venue"
},
  "geometry": {"coordinates":[8.5918893814,52.0123443604],"type":"Point"}
}