{
  "type": "Feature",
  "properties": {
    "iso:country":"DE",
    "sg:address":"T\u00e4nnesberger Str. 5",
    "sg:city":"Pfreimd",
    "sg:phone":"+49 9606/91177",
    "sg:postcode":"92536",
    "sg:province":"Bayern",
    "wof:name":"Ludwig H\u00f6sl",
    "wof:placetype":"venue"
},
  "geometry": {"coordinates":[12.1882972717,49.4952468872],"type":"Point"}
}