{
  "type": "Feature",
  "properties": {
    "iso:country":"DE",
    "sg:address":"Sudbachtal 10",
    "sg:city":"L\u00f6hne",
    "sg:phone":"+49 5731/82410",
    "sg:postcode":"32584",
    "sg:province":"Nordrhein-Westfalen",
    "wof:name":"Hermann Nolting",
    "wof:placetype":"venue"
},
  "geometry": {"coordinates":[8.754251,52.188084],"type":"Point"}
}