{
  "type": "Feature",
  "properties": {
    "iso:country":"DE",
    "sg:address":"Herderstr. 5",
    "sg:city":"Hochheim",
    "sg:postcode":"65239",
    "sg:province":"Hessen",
    "wof:name":"Andres Baudet Von Gersdorf",
    "wof:placetype":"venue"
},
  "geometry": {"coordinates":[8.369608,50.008404],"type":"Point"}
}