{
  "type": "Feature",
  "properties": {
    "iso:country":"DE",
    "sg:address":"Unkairstrasse 4",
    "sg:city":"Paderborn",
    "sg:postcode":"33104",
    "sg:province":"Nordrhein-Westfalen",
    "wof:name":"B\u00fccher Bei Jnn",
    "wof:placetype":"venue"
},
  "geometry": {"coordinates":[8.7144117355,51.7511482239],"type":"Point"}
}