{
  "type": "Feature",
  "properties": {
    "iso:country":"DE",
    "sg:address":"Strundener Str. 29",
    "sg:city":"K\u00f6ln",
    "sg:phone":"+49 221/681270",
    "sg:postcode":"51069",
    "sg:province":"Nordrhein-Westfalen",
    "wof:name":"F. J. Schreckenberg Gmbh",
    "wof:placetype":"venue"
},
  "geometry": {"coordinates":[7.079174,50.972424],"type":"Point"}
}