{
  "type": "Feature",
  "properties": {
    "iso:country":"DE",
    "sg:address":"Bergheimer Str. 50a",
    "sg:city":"Niederkassel",
    "sg:phone":"+49 228/453634",
    "sg:postcode":"53859",
    "sg:province":"Nordrhein-Westfalen",
    "wof:name":"Heinz-peter Schmitz",
    "wof:placetype":"venue"
},
  "geometry": {"coordinates":[7.0797162056,50.773815155],"type":"Point"}
}