{
  "type": "Feature",
  "properties": {
    "iso:country":"DE",
    "sg:address":"Ammerl\u00e4nder Heerstr. 167-176",
    "sg:city":"Oldenburg",
    "sg:phone":"+49 441",
    "sg:postcode":"26129",
    "sg:province":"Niedersachsen",
    "wof:name":"Autohaus Rosier Gmbh & Co.kg",
    "wof:placetype":"venue"
},
  "geometry": {"coordinates":[8.1773729324,53.150718689],"type":"Point"}
}