{
  "type": "Feature",
  "properties": {
    "iso:country":"DE",
    "sg:address":"Reu\u00dfensteinstr. 4",
    "sg:city":"Uhingen",
    "sg:phone":"+49 7161/33695",
    "sg:postcode":"73066",
    "sg:province":"Baden-W\u00fcrttemberg",
    "wof:name":"Thomas Genzel",
    "wof:placetype":"venue"
},
  "geometry": {"coordinates":[9.5795583725,48.6979866028],"type":"Point"}
}