{
  "type": "Feature",
  "properties": {
    "iso:country":"DE",
    "sg:address":"Gartenstr. 12a",
    "sg:city":"Weil am Rhein",
    "sg:phone":"+49 7621/71145",
    "sg:postcode":"79576",
    "sg:province":"Baden-W\u00fcrttemberg",
    "wof:name":"Rudolf Beil",
    "wof:placetype":"venue"
},
  "geometry": {"coordinates":[7.613195,47.590778],"type":"Point"}
}