{
  "type": "Feature",
  "properties": {
    "iso:country":"DE",
    "sg:address":"Ringstr. 3",
    "sg:city":"Buchbach",
    "sg:postcode":"84428",
    "sg:province":"Bayern",
    "wof:name":"Visionary People Ag",
    "wof:placetype":"venue"
},
  "geometry": {"coordinates":[12.271471,48.31242],"type":"Point"}
}