{
  "type": "Feature",
  "properties": {
    "iso:country":"DE",
    "sg:address":"Fritz-von-dem-Berge-Str. 40",
    "sg:city":"Bleckede",
    "sg:phone":"+49 5852/3970",
    "sg:postcode":"21354",
    "sg:province":"Niedersachsen",
    "wof:name":"Kraftwerk Bleckede Ludolf Stamer Gmbh",
    "wof:placetype":"venue"
},
  "geometry": {"coordinates":[10.738756,53.28688],"type":"Point"}
}