{
  "type": "Feature",
  "properties": {
    "iso:country":"DE",
    "sg:address":"Hafenstr. 146",
    "sg:city":"Bremerhaven",
    "sg:phone":"+49 471/52767",
    "sg:postcode":"27576",
    "sg:province":"Bremen",
    "wof:name":"China Shanghai",
    "wof:placetype":"venue"
},
  "geometry": {"coordinates":[8.586268425,53.5608711243],"type":"Point"}
}