{
  "type": "Feature",
  "properties": {
    "iso:country":"DE",
    "sg:address":"Aplerbecker Str. 308",
    "sg:city":"Dortmund",
    "sg:phone":"+49 231/7225095",
    "sg:postcode":"44309",
    "sg:province":"Nordrhein-Westfalen",
    "wof:name":"Lehmann Und Herold Architekten",
    "wof:placetype":"venue"
},
  "geometry": {"coordinates":[7.561781,51.50972],"type":"Point"}
}