{
  "type": "Feature",
  "properties": {
    "iso:country":"DE",
    "sg:address":"Sebastianstr. 9",
    "sg:city":"Gersthofen",
    "sg:phone":"+49 8230/7776",
    "sg:postcode":"86368",
    "sg:province":"Bayern",
    "wof:name":"Konrad R\u00f6\u00dfle",
    "wof:placetype":"venue"
},
  "geometry": {"coordinates":[10.8155250549,48.4312477112],"type":"Point"}
}