{
  "type": "Feature",
  "properties": {
    "iso:country":"DE",
    "sg:address":"Gechinger Str. 1",
    "sg:city":"Aidlingen",
    "sg:phone":"+49 7056/3331",
    "sg:postcode":"71134",
    "sg:province":"Baden-W\u00fcrttemberg",
    "wof:name":"Rathaus-apotheke",
    "wof:placetype":"venue"
},
  "geometry": {"coordinates":[8.867443,48.680672],"type":"Point"}
}