{
  "type": "Feature",
  "properties": {
    "iso:country":"DE",
    "sg:address":"Jahnstr. 17",
    "sg:city":"Mainhausen",
    "sg:postcode":"63533",
    "sg:province":"Hessen",
    "wof:name":"Etha Anlagenbau Gmbh",
    "wof:placetype":"venue"
},
  "geometry": {"coordinates":[8.99502,50.01944],"type":"Point"}
}