{
  "type": "Feature",
  "properties": {
    "iso:country":"DE",
    "sg:address":"Ossietzkystr. 16",
    "sg:city":"Leipzig",
    "sg:phone":"+49 341/2330177",
    "sg:postcode":"04347",
    "sg:province":"Sachsen",
    "wof:name":"Monika Seidel",
    "wof:placetype":"venue"
},
  "geometry": {"coordinates":[12.416226387,51.3594398499],"type":"Point"}
}