{
  "type": "Feature",
  "properties": {
    "iso:country":"DE",
    "sg:address":"Burgallee 23d",
    "sg:city":"Hanau",
    "sg:phone":"+49 6181/21256",
    "sg:postcode":"63454",
    "sg:province":"Hessen",
    "wof:name":"Haus Der Kosmetik",
    "wof:placetype":"venue"
},
  "geometry": {"coordinates":[8.8851079941,50.141456604],"type":"Point"}
}