{
  "type": "Feature",
  "properties": {
    "iso:country":"DE",
    "sg:address":"Hildesheimer Str. 305",
    "sg:city":"Hannover",
    "sg:phone":"+49 4951/1984960",
    "sg:postcode":"30519",
    "sg:province":"Niedersachsen",
    "wof:name":"Chemische Fabrik W\u00dclfel Gmbh & Co Kg",
    "wof:placetype":"venue"
},
  "geometry": {"coordinates":[9.773049,52.333519],"type":"Point"}
}