{
  "type": "Feature",
  "properties": {
    "iso:country":"DE",
    "sg:address":"Gro\u00dfstr. 87",
    "sg:city":"Bad Sobernheim",
    "sg:phone":"+49 6751/6053",
    "sg:postcode":"55566",
    "sg:province":"Rheinland-Pfalz",
    "wof:name":"N. Sahin",
    "wof:placetype":"venue"
},
  "geometry": {"coordinates":[7.6542649269,49.7846603394],"type":"Point"}
}