{
  "type": "Feature",
  "properties": {
    "iso:country":"DE",
    "sg:address":"Heidenheimer Weg 2",
    "sg:city":"Markt Berolzheim",
    "sg:phone":"+49 9146/840",
    "sg:postcode":"91801",
    "sg:province":"Bayern",
    "wof:name":"Karl Prosiegel",
    "wof:placetype":"venue"
},
  "geometry": {"coordinates":[10.840401,49.00885],"type":"Point"}
}