{
  "type": "Feature",
  "properties": {
    "iso:country":"DE",
    "sg:address":"Bahnhofstr. 8",
    "sg:city":"Osterweddingen",
    "sg:phone":"+49 39205/23818",
    "sg:postcode":"39171",
    "sg:province":"Sachsen-Anhalt",
    "wof:name":"Frank Jasper",
    "wof:placetype":"venue"
},
  "geometry": {"coordinates":[11.5769300461,52.0474472046],"type":"Point"}
}