{
  "type": "Feature",
  "properties": {
    "iso:country":"DE",
    "sg:address":"Neuer Weg 38",
    "sg:city":"Wolfenb\u00fcttel",
    "sg:phone":"+49 5331/76597",
    "sg:postcode":"38302",
    "sg:province":"Niedersachsen",
    "wof:name":"Herbert Isensee",
    "wof:placetype":"venue"
},
  "geometry": {"coordinates":[10.538225,52.177917],"type":"Point"}
}