{
  "type": "Feature",
  "properties": {
    "iso:country":"DE",
    "sg:address":"Mierendorffplatz 12-14",
    "sg:city":"Berlin",
    "sg:phone":"+49 30/3447548",
    "sg:postcode":"10589",
    "sg:province":"Berlin",
    "wof:name":"Apotheke Am Mierendorffplatz",
    "wof:placetype":"venue"
},
  "geometry": {"coordinates":[13.304631,52.5252],"type":"Point"}
}