{
  "type": "Feature",
  "properties": {
    "iso:country":"DE",
    "sg:address":"Wilhelmstr. 8",
    "sg:city":"Vlotho",
    "sg:postcode":"32602",
    "sg:province":"Nordrhein-Westfalen",
    "wof:name":"Tagungshotel Bonneberg Gmbh",
    "wof:placetype":"venue"
},
  "geometry": {"coordinates":[8.8252239227,52.160358429],"type":"Point"}
}