{
  "type": "Feature",
  "properties": {
    "iso:country":"DE",
    "sg:address":"Schulstr. 22",
    "sg:city":"Ahorn",
    "sg:phone":"+49 6296/479",
    "sg:postcode":"74744",
    "sg:province":"Baden-W\u00fcrttemberg",
    "wof:name":"Walter D\u00f6tter",
    "wof:placetype":"venue"
},
  "geometry": {"coordinates":[9.542688,49.499294],"type":"Point"}
}