{
  "type": "Feature",
  "properties": {
    "iso:country":"DE",
    "sg:address":"Talring 110",
    "sg:city":"Krefeld",
    "sg:phone":"+49 2151/735125",
    "sg:postcode":"47802",
    "sg:province":"Nordrhein-Westfalen",
    "wof:name":"Cafe Parkschl\u00f6\u00dfchen",
    "wof:placetype":"venue"
},
  "geometry": {"coordinates":[6.533891,51.39682],"type":"Point"}
}