{
  "type": "Feature",
  "properties": {
    "iso:country":"DE",
    "sg:address":"Schmithuysenweg 3",
    "sg:city":"Willich",
    "sg:phone":"+49 2154/80707",
    "sg:postcode":"47877",
    "sg:province":"Nordrhein-Westfalen",
    "wof:name":"Cs Cadtronic Computer-systeme Gmbh",
    "wof:placetype":"venue"
},
  "geometry": {"coordinates":[6.5356431007,51.2458953857],"type":"Point"}
}