{
  "type": "Feature",
  "properties": {
    "iso:country":"DE",
    "sg:address":"Badstr. 2",
    "sg:city":"Kehl",
    "sg:phone":"+49 7851/1034",
    "sg:postcode":"77694",
    "sg:province":"Baden-W\u00fcrttemberg",
    "wof:name":"M. Wund Wettannahme",
    "wof:placetype":"venue"
},
  "geometry": {"coordinates":[7.81494,48.574188],"type":"Point"}
}