{
  "type": "Feature",
  "properties": {
    "iso:country":"DE",
    "sg:address":"Uferstr. 3",
    "sg:city":"Bremerhaven",
    "sg:phone":"+49 471/42621",
    "sg:postcode":"27568",
    "sg:province":"Bremen",
    "wof:name":"Theodor Vehmeier",
    "wof:placetype":"venue"
},
  "geometry": {"coordinates":[8.5803003311,53.5474815369],"type":"Point"}
}