{
  "type": "Feature",
  "properties": {
    "iso:country":"DE",
    "sg:address":"Theodor-Pekol-Str. 7 - 9",
    "sg:city":"Oldenburg",
    "sg:phone":"+49 441/681611",
    "sg:postcode":"26127",
    "sg:province":"Niedersachsen",
    "wof:name":"Erich Sprick",
    "wof:placetype":"venue"
},
  "geometry": {"coordinates":[8.197992,53.170013],"type":"Point"}
}