{
  "type": "Feature",
  "properties": {
    "iso:country":"DE",
    "sg:address":"Lambertimarkt 7",
    "sg:city":"Nettetal",
    "sg:phone":"+49 2153/70316",
    "sg:postcode":"41334",
    "sg:province":"Nordrhein-Westfalen",
    "wof:name":"Alt Breyeller Grill",
    "wof:placetype":"venue"
},
  "geometry": {"coordinates":[6.2472882271,51.2977180481],"type":"Point"}
}