{
  "type": "Feature",
  "properties": {
    "iso:country":"DE",
    "sg:address":"An der Waldb\u00fchne 2",
    "sg:city":"Gleichen",
    "sg:phone":"+49 5592/222",
    "sg:postcode":"37130",
    "sg:province":"Niedersachsen",
    "wof:name":"Heinrich Wedemeyer",
    "wof:placetype":"venue"
},
  "geometry": {"coordinates":[10.037946,51.449379],"type":"Point"}
}