{
  "type": "Feature",
  "properties": {
    "iso:country":"DE",
    "sg:address":"Lobeckstr. 72",
    "sg:city":"Berlin",
    "sg:phone":"+49 30/6141421",
    "sg:postcode":"10969",
    "sg:province":"Berlin",
    "wof:name":"Heinz Weber",
    "wof:placetype":"venue"
},
  "geometry": {"coordinates":[13.403655,52.499512],"type":"Point"}
}