{
  "type": "Feature",
  "properties": {
    "iso:country":"DE",
    "sg:address":"Eckweg 4 c",
    "sg:city":"Hamburg",
    "sg:phone":"+49 40/6448471",
    "sg:postcode":"22159",
    "sg:province":"Hamburg",
    "wof:name":"J\u00fcrgen Kugelberg",
    "wof:placetype":"venue"
},
  "geometry": {"coordinates":[10.119837,53.624702],"type":"Point"}
}