{
  "type": "Feature",
  "properties": {
    "iso:country":"DE",
    "sg:address":"Dessauer Str. 33",
    "sg:city":"Bitterfeld",
    "sg:postcode":"06749",
    "sg:province":"Sachsen-Anhalt",
    "wof:name":"Horus Gmbh",
    "wof:placetype":"venue"
},
  "geometry": {"coordinates":[12.3210315704,51.6306343079],"type":"Point"}
}