{
  "type": "Feature",
  "properties": {
    "iso:country":"DE",
    "sg:address":"S\u00e4bener Str. 94",
    "sg:city":"M\u00fcnchen",
    "sg:phone":"+49 89/64208845",
    "sg:postcode":"81547",
    "sg:province":"Bayern",
    "wof:name":"Erwin Hauser Architekt",
    "wof:placetype":"venue"
},
  "geometry": {"coordinates":[11.571822,48.101067],"type":"Point"}
}