{
  "type": "Feature",
  "properties": {
    "iso:country":"DE",
    "sg:address":"Hauptstr. 101",
    "sg:city":"Gaggenau",
    "sg:phone":"+49 7225/983560",
    "sg:postcode":"76571",
    "sg:province":"Baden-W\u00fcrttemberg",
    "wof:name":"Binz Hoch 3 Gmbh",
    "wof:placetype":"venue"
},
  "geometry": {"coordinates":[8.3220405579,48.8007736206],"type":"Point"}
}