{
  "type": "Feature",
  "properties": {
    "iso:country":"DE",
    "sg:address":"Bauchgasse 10",
    "sg:city":"Schornsheim",
    "sg:phone":"+49 6732/63731",
    "sg:postcode":"55288",
    "sg:province":"Rheinland-Pfalz",
    "wof:name":"R\u00fcdiger Ebling",
    "wof:placetype":"venue"
},
  "geometry": {"coordinates":[8.175485611,49.846824646],"type":"Point"}
}