{
  "type": "Feature",
  "properties": {
    "iso:country":"DE",
    "sg:address":"Steinbeisweg 14",
    "sg:city":"Winnenden",
    "sg:phone":"+49 7195/18070",
    "sg:postcode":"71364",
    "sg:province":"Baden-W\u00fcrttemberg",
    "wof:name":"H. Mayer Gmbh + Co. Metallbau Stahlbau",
    "wof:placetype":"venue"
},
  "geometry": {"coordinates":[9.391598,48.876221],"type":"Point"}
}