{
  "type": "Feature",
  "properties": {
    "iso:country":"DE",
    "sg:address":"Wettergasse 23",
    "sg:city":"Marburg",
    "sg:phone":"+49 6421/63323",
    "sg:postcode":"35037",
    "sg:province":"Hessen",
    "wof:name":"Helmut Springer Gmbh & Co. Kg",
    "wof:placetype":"venue"
},
  "geometry": {"coordinates":[8.770678,50.810154],"type":"Point"}
}