{
  "type": "Feature",
  "properties": {
    "iso:country":"DE",
    "sg:address":"Sch\u00f6fferstr. 6",
    "sg:city":"Mainz",
    "sg:phone":"+49 6131/226180",
    "sg:postcode":"55116",
    "sg:province":"Rheinland-Pfalz",
    "wof:name":"Winand Jaeger Kunsthandlung Gmbh",
    "wof:placetype":"venue"
},
  "geometry": {"coordinates":[8.2726316452,49.9990234375],"type":"Point"}
}