{
  "type": "Feature",
  "properties": {
    "iso:country":"DE",
    "sg:address":"Hauptstr. 27",
    "sg:city":"Desloch",
    "sg:phone":"+49 6753/3058",
    "sg:postcode":"55592",
    "sg:province":"Rheinland-Pfalz",
    "wof:name":"Walter Venter",
    "wof:placetype":"venue"
},
  "geometry": {"coordinates":[7.629082,49.718876],"type":"Point"}
}