{
  "type": "Feature",
  "properties": {
    "iso:country":"DE",
    "sg:address":"Hofberg 40",
    "sg:city":"Murrhardt",
    "sg:phone":"+49 7192/5363",
    "sg:postcode":"71540",
    "sg:province":"Baden-W\u00fcrttemberg",
    "wof:name":"Karl R\u00f6ssle",
    "wof:placetype":"venue"
},
  "geometry": {"coordinates":[9.5717248917,48.9924736023],"type":"Point"}
}