{
  "type": "Feature",
  "properties": {
    "iso:country":"DE",
    "sg:address":"Regerstr. 27",
    "sg:city":"M\u00fcnchen",
    "sg:postcode":"81541",
    "sg:province":"Bayern",
    "wof:name":"2 K Verwaltungsges. Mbh",
    "wof:placetype":"venue"
},
  "geometry": {"coordinates":[11.5855722427,48.1210174561],"type":"Point"}
}