{
  "type": "Feature",
  "properties": {
    "iso:country":"DE",
    "sg:address":"Ratsweg 5",
    "sg:city":"Potsdam",
    "sg:phone":"+49 331/623170",
    "sg:postcode":"14480",
    "sg:province":"Brandenburg",
    "wof:name":"Bernd Vogler",
    "wof:placetype":"venue"
},
  "geometry": {"coordinates":[13.1312294006,52.3835716248],"type":"Point"}
}