{
  "type": "Feature",
  "properties": {
    "iso:country":"DE",
    "sg:address":"Fidicinstr. 3",
    "sg:city":"Berlin",
    "sg:phone":"+49 30/3211010",
    "sg:postcode":"10965",
    "sg:province":"Berlin",
    "wof:name":"Bvb Gerti Schwenke B\u00fchnen- Veranstaltungs- Und Ball-",
    "wof:placetype":"venue"
},
  "geometry": {"coordinates":[13.387807,52.487061],"type":"Point"}
}