{
  "type": "Feature",
  "properties": {
    "iso:country":"DE",
    "sg:address":"Dammweg 15",
    "sg:city":"Dresden",
    "sg:postcode":"01097",
    "sg:province":"Sachsen",
    "wof:name":"Its Ingenieurb\u00fcro F\u00fcr Techn. Ausr\u00fcstung Schienengebundener",
    "wof:placetype":"venue"
},
  "geometry": {"coordinates":[13.74929142,51.0722160339],"type":"Point"}
}