{
  "type": "Feature",
  "properties": {
    "iso:country":"DE",
    "sg:address":"Albert-Schneider-Str. 4",
    "sg:city":"Blankenburg",
    "sg:phone":"+49 3944/900820",
    "sg:postcode":"38889",
    "sg:province":"Sachsen-Anhalt",
    "wof:name":"Pension Am Kurpark Inh. Barbara Hochmuth",
    "wof:placetype":"venue"
},
  "geometry": {"coordinates":[10.958366394,51.7936935425],"type":"Point"}
}