{
  "type": "Feature",
  "properties": {
    "iso:country":"DE",
    "sg:address":"Wallauer Str. 30",
    "sg:city":"Hofheim",
    "sg:phone":"+49 6192/8594",
    "sg:postcode":"65719",
    "sg:province":"Hessen",
    "wof:name":"Alfred Heuss",
    "wof:placetype":"venue"
},
  "geometry": {"coordinates":[8.397512,50.099949],"type":"Point"}
}