{
  "type": "Feature",
  "properties": {
    "iso:country":"DE",
    "sg:address":"Dr.-Friedrich-Wolf-Str.30",
    "sg:city":"Dresden",
    "sg:phone":"+49 351/8029487",
    "sg:postcode":"01097",
    "sg:province":"Sachsen",
    "wof:name":"Autosicherheit.de - Mobile Electronics",
    "wof:placetype":"venue"
},
  "geometry": {"coordinates":[13.745565,51.06802],"type":"Point"}
}