{
  "type": "Feature",
  "properties": {
    "iso:country":"DE",
    "sg:address":"Bergstr. 55",
    "sg:city":"Achim",
    "sg:phone":"+49 4202/62760",
    "sg:postcode":"28832",
    "sg:province":"Niedersachsen",
    "wof:name":"P. F. Jochims Gmbh",
    "wof:placetype":"venue"
},
  "geometry": {"coordinates":[9.046946,53.010368],"type":"Point"}
}