{
  "type": "Feature",
  "properties": {
    "iso:country":"DE",
    "sg:address":"Hans-Bunte-Str. 20",
    "sg:city":"Heidelberg",
    "sg:phone":"+49 6221/776238",
    "sg:postcode":"69123",
    "sg:province":"Baden-W\u00fcrttemberg",
    "wof:name":"Osg Optronik-service Gmbh",
    "wof:placetype":"venue"
},
  "geometry": {"coordinates":[8.641352,49.406845],"type":"Point"}
}