{
  "type": "Feature",
  "properties": {
    "iso:country":"DE",
    "sg:address":"Friedrichstr. 21",
    "sg:city":"Frechen",
    "sg:phone":"+49 2234/12407",
    "sg:postcode":"50226",
    "sg:province":"Nordrhein-Westfalen",
    "wof:name":"Heinrich Weiland",
    "wof:placetype":"venue"
},
  "geometry": {"coordinates":[6.8100252151,50.9152565002],"type":"Point"}
}