{
  "type": "Feature",
  "properties": {
    "iso:country":"DE",
    "sg:address":"Bleichenweg",
    "sg:city":"Zeulenroda",
    "sg:postcode":"07937",
    "sg:province":"Th\u00fcringen",
    "wof:name":"Strandbad",
    "wof:placetype":"venue"
},
  "geometry": {"coordinates":[11.9762001038,50.6517715454],"type":"Point"}
}