{
  "type": "Feature",
  "properties": {
    "iso:country":"DE",
    "sg:address":"Frankfurter Str. 605",
    "sg:city":"K\u00f6ln",
    "sg:phone":"+49 2203/34331",
    "sg:postcode":"51145",
    "sg:province":"Nordrhein-Westfalen",
    "wof:name":"Hans Lohmar Verwaltung Gmbh",
    "wof:placetype":"venue"
},
  "geometry": {"coordinates":[7.08335,50.87212],"type":"Point"}
}