{
  "type": "Feature",
  "properties": {
    "iso:country":"DE",
    "sg:address":"Hollenbek 14",
    "sg:city":"Hamburg",
    "sg:phone":"+49 40/5383069",
    "sg:postcode":"22339",
    "sg:province":"Hamburg",
    "wof:name":"A. Schmidt-mikuteit",
    "wof:placetype":"venue"
},
  "geometry": {"coordinates":[10.0594902039,53.6389503479],"type":"Point"}
}