{
  "type": "Feature",
  "properties": {
    "iso:country":"DE",
    "sg:address":"Handelsstr. 11",
    "sg:city":"Schwedt",
    "sg:phone":"+49 3332/32109",
    "sg:postcode":"16303",
    "sg:province":"Brandenburg",
    "wof:name":"Beiersdorf & Gr\u00fcschow",
    "wof:placetype":"venue"
},
  "geometry": {"coordinates":[14.2684087753,53.0674438477],"type":"Point"}
}