{
  "type": "Feature",
  "properties": {
    "iso:country":"DE",
    "sg:address":"Holtenauer Str. 62",
    "sg:city":"Kiel",
    "sg:phone":"+49 431/567506",
    "sg:postcode":"24105",
    "sg:province":"Schleswig-Holstein",
    "wof:name":"E. W\u00f6llmer & Sohn",
    "wof:placetype":"venue"
},
  "geometry": {"coordinates":[10.132395,54.331917],"type":"Point"}
}