{
  "type": "Feature",
  "properties": {
    "iso:country":"DE",
    "sg:address":"Durlacher Str. 66",
    "sg:city":"Pforzheim",
    "sg:phone":"+49 7231/312645",
    "sg:postcode":"75172",
    "sg:province":"Baden-W\u00fcrttemberg",
    "wof:name":"Josef B\u00c4r Gmbh",
    "wof:placetype":"venue"
},
  "geometry": {"coordinates":[8.6887235641,48.8942375183],"type":"Point"}
}