{
  "type": "Feature",
  "properties": {
    "iso:country":"DE",
    "sg:address":"Breidenbachstr. 51",
    "sg:city":"Leverkusen",
    "sg:phone":"+49 214/47181",
    "sg:postcode":"51373",
    "sg:province":"Nordrhein-Westfalen",
    "wof:name":"Zum Kronenkrug",
    "wof:placetype":"venue"
},
  "geometry": {"coordinates":[6.9843788147,51.0286979675],"type":"Point"}
}