{
  "type": "Feature",
  "properties": {
    "iso:country":"DE",
    "sg:address":"Rosenthaler Str. 10",
    "sg:city":"Peine",
    "sg:phone":"+49 5171/733332",
    "sg:postcode":"31224",
    "sg:province":"Niedersachsen",
    "wof:name":"Vereinte Versicherung J\u00fcrgen Winter",
    "wof:placetype":"venue"
},
  "geometry": {"coordinates":[10.2243309021,52.3230781555],"type":"Point"}
}