{
  "type": "Feature",
  "properties": {
    "iso:country":"DE",
    "sg:address":"Kylische Str. 2",
    "sg:city":"Sangerhausen",
    "sg:phone":"+49 3464/572225",
    "sg:postcode":"06526",
    "sg:province":"Sachsen-Anhalt",
    "wof:name":"Fred M\u00fcller Ohg",
    "wof:placetype":"venue"
},
  "geometry": {"coordinates":[11.298948,51.473915],"type":"Point"}
}