{
  "type": "Feature",
  "properties": {
    "iso:country":"DE",
    "sg:address":"Rosa-Luxemburg-Str. 4",
    "sg:city":"Gro\u00dfenhain",
    "sg:phone":"+49 3522/38559",
    "sg:postcode":"01558",
    "sg:province":"Sachsen",
    "wof:name":"Bert Eltzschig",
    "wof:placetype":"venue"
},
  "geometry": {"coordinates":[13.521101,51.294411],"type":"Point"}
}