{
  "type": "Feature",
  "properties": {
    "iso:country":"DE",
    "sg:address":"Edisonstr. 1",
    "sg:city":"Kempten",
    "sg:phone":"+49 831/564000",
    "sg:postcode":"87437",
    "sg:province":"Bayern",
    "wof:name":"Power Work Ag",
    "wof:placetype":"venue"
},
  "geometry": {"coordinates":[10.3385095596,47.7333106995],"type":"Point"}
}