{
  "type": "Feature",
  "properties": {
    "iso:country":"DE",
    "sg:address":"Industriestr. 30",
    "sg:city":"Rastatt",
    "sg:phone":"+49 7222/985760",
    "sg:postcode":"76437",
    "sg:province":"Baden-W\u00fcrttemberg",
    "wof:name":"Bernd D\u00fcmmig Gmbh",
    "wof:placetype":"venue"
},
  "geometry": {"coordinates":[8.222443,48.8549],"type":"Point"}
}