{
  "type": "Feature",
  "properties": {
    "iso:country":"DE",
    "sg:address":"Talstr.",
    "sg:city":"Hohenstein-Ernstthal",
    "sg:phone":"+49 3723/701021",
    "sg:postcode":"09337",
    "sg:province":"Sachsen",
    "wof:name":"K\u00fchler Grund",
    "wof:placetype":"venue"
},
  "geometry": {"coordinates":[12.6758069992,50.8061218262],"type":"Point"}
}