{
  "type": "Feature",
  "properties": {
    "iso:country":"DE",
    "sg:address":"Haunstetter Str. 28",
    "sg:city":"K\u00f6nigsbrunn",
    "sg:phone":"+49 8231/2628",
    "sg:postcode":"86343",
    "sg:province":"Bayern",
    "wof:name":"Landesbausparkasse Beratungsstelle",
    "wof:placetype":"venue"
},
  "geometry": {"coordinates":[10.89641,48.289391],"type":"Point"}
}