{
  "type": "Feature",
  "properties": {
    "iso:country":"DE",
    "sg:address":"Friedhofstr. 35",
    "sg:city":"Aalen",
    "sg:phone":"+49 7361/61444",
    "sg:postcode":"73430",
    "sg:province":"Baden-W\u00fcrttemberg",
    "wof:name":"Schubart Apotheke Karin Anderlohr E. Kfr.",
    "wof:placetype":"venue"
},
  "geometry": {"coordinates":[10.088104,48.837833],"type":"Point"}
}