{
  "type": "Feature",
  "properties": {
    "iso:country":"DE",
    "sg:address":"Spitalhofstr. 29",
    "sg:city":"Stuttgart",
    "sg:phone":"+49 711/843324",
    "sg:postcode":"70437",
    "sg:province":"Baden-W\u00fcrttemberg",
    "wof:name":"Kurt L\u00e4pple",
    "wof:placetype":"venue"
},
  "geometry": {"coordinates":[9.200056,48.839993],"type":"Point"}
}