{
  "type": "Feature",
  "properties": {
    "iso:country":"DE",
    "sg:address":"Peiner Landstr. 244",
    "sg:city":"Hildesheim",
    "sg:phone":"+49 5121/741200",
    "sg:postcode":"31135",
    "sg:province":"Niedersachsen",
    "wof:name":"Sam-tec Automotive Gmbh",
    "wof:placetype":"venue"
},
  "geometry": {"coordinates":[9.9660263062,52.1794204712],"type":"Point"}
}