{
  "type": "Feature",
  "properties": {
    "iso:country":"DE",
    "sg:address":"St. Pauli 1",
    "sg:city":"Apensen",
    "sg:phone":"+49 4167/858",
    "sg:postcode":"21641",
    "sg:province":"Niedersachsen",
    "wof:name":"Raimer Heins",
    "wof:placetype":"venue"
},
  "geometry": {"coordinates":[9.6219549179,53.4363021851],"type":"Point"}
}