{
  "type": "Feature",
  "properties": {
    "iso:country":"DE",
    "sg:address":"Teilfeld 5",
    "sg:city":"Hamburg",
    "sg:phone":"+49 40/37600222",
    "sg:postcode":"20459",
    "sg:province":"Hamburg",
    "wof:name":"Maple Leaf Rassau Gmbh",
    "wof:placetype":"venue"
},
  "geometry": {"coordinates":[9.981986,53.548351],"type":"Point"}
}