{
  "type": "Feature",
  "properties": {
    "iso:country":"DE",
    "sg:address":"L\u00f6wenbr\u00fcckener Str. 13",
    "sg:city":"Trier",
    "sg:phone":"+49 651/44058",
    "sg:postcode":"54290",
    "sg:province":"Rheinland-Pfalz",
    "wof:name":"Zweckverband Abfallbeseit. Im Raum Trier Schuttabf.",
    "wof:placetype":"venue"
},
  "geometry": {"coordinates":[6.637923,49.746109],"type":"Point"}
}