{
  "type": "Feature",
  "properties": {
    "iso:country":"DE",
    "sg:address":"Marktplatz 10",
    "sg:city":"Burglengenfeld",
    "sg:phone":"+49 9471/5594",
    "sg:postcode":"93133",
    "sg:province":"Bayern",
    "wof:name":"G\u00fcnter Richau",
    "wof:placetype":"venue"
},
  "geometry": {"coordinates":[12.0397891998,49.2069320679],"type":"Point"}
}