{
  "type": "Feature",
  "properties": {
    "iso:country":"DE",
    "sg:address":"Nordendstr. 40",
    "sg:city":"Puchheim",
    "sg:phone":"+49 89/806445",
    "sg:postcode":"82178",
    "sg:province":"Bayern",
    "wof:name":"Pension Scholl",
    "wof:placetype":"venue"
},
  "geometry": {"coordinates":[11.3664751053,48.1835517883],"type":"Point"}
}