{
  "type": "Feature",
  "properties": {
    "iso:country":"DE",
    "sg:address":"Losenburger Str. 51",
    "sg:city":"Heiligenhaus",
    "sg:phone":"+49 2056/69250",
    "sg:postcode":"42579",
    "sg:province":"Nordrhein-Westfalen",
    "wof:name":"Am Hessenbleck",
    "wof:placetype":"venue"
},
  "geometry": {"coordinates":[6.9922118187,51.3458900452],"type":"Point"}
}