{
  "type": "Feature",
  "properties": {
    "iso:country":"DE",
    "sg:address":"Heinrich-Hertz-Str 40",
    "sg:city":"Erkrath",
    "sg:phone":"+49 211/92060",
    "sg:postcode":"40699",
    "sg:province":"Nordrhein-Westfalen",
    "wof:name":"Honeywell Gmbh",
    "wof:placetype":"venue"
},
  "geometry": {"coordinates":[6.921461,51.19912],"type":"Point"}
}