{
  "type": "Feature",
  "properties": {
    "iso:country":"DE",
    "sg:address":"Lindenstr. 18b",
    "sg:city":"K\u00fchlungsborn",
    "sg:phone":"+49 38293/17245",
    "sg:postcode":"18225",
    "sg:province":"Mecklenburg-Vorpommern",
    "wof:name":"Pavillon Im Lindenpark Inh. Christa Danes",
    "wof:placetype":"venue"
},
  "geometry": {"coordinates":[11.7524900436,54.149307251],"type":"Point"}
}