{
  "type": "Feature",
  "properties": {
    "iso:country":"DE",
    "sg:address":"Halle-Kasseler-Str. 28",
    "sg:city":"Leinefelde",
    "sg:phone":"+49 3605/509837",
    "sg:postcode":"37327",
    "sg:province":"Th\u00fcringen",
    "wof:name":"Herbert Freund Architekt",
    "wof:placetype":"venue"
},
  "geometry": {"coordinates":[10.31925,51.387459],"type":"Point"}
}