{
  "type": "Feature",
  "properties": {
    "iso:country":"DE",
    "sg:address":"Bahnhofstr. 26",
    "sg:city":"Tellingstedt",
    "sg:phone":"+49 4838/78770",
    "sg:postcode":"25782",
    "sg:province":"Schleswig-Holstein",
    "wof:name":"Bernd Wartenberg Ermittlung Von Versicherungen E. K.",
    "wof:placetype":"venue"
},
  "geometry": {"coordinates":[9.2814350128,54.2165184021],"type":"Point"}
}