{
  "type": "Feature",
  "properties": {
    "iso:country":"DE",
    "sg:address":"Am Hang 14",
    "sg:city":"Rauenberg - Malschenberg",
    "sg:phone":"+49 7253",
    "sg:postcode":"69231",
    "sg:province":"Baden-W\u00fcrttemberg",
    "wof:name":"Us - Messerimport - Hbs Marketing",
    "wof:placetype":"venue"
},
  "geometry": {"coordinates":[8.7009649277,49.2703590393],"type":"Point"}
}