{
  "type": "Feature",
  "properties": {
    "iso:country":"DE",
    "sg:address":"Siefhofener Str. 35",
    "sg:city":"K\u00f6nigsmoos",
    "sg:phone":"+49 8454/597",
    "sg:postcode":"86669",
    "sg:province":"Bayern",
    "wof:name":"Alois Walter",
    "wof:placetype":"venue"
},
  "geometry": {"coordinates":[11.247498,48.656574],"type":"Point"}
}