{
  "type": "Feature",
  "properties": {
    "iso:country":"DE",
    "sg:address":"Liepmannstr. 19",
    "sg:city":"Hannover",
    "sg:phone":"+49 511/2100476",
    "sg:postcode":"30453",
    "sg:province":"Niedersachsen",
    "wof:name":"Heinz Gremmler Drogerie Im Foessefeld",
    "wof:placetype":"venue"
},
  "geometry": {"coordinates":[9.692429,52.373188],"type":"Point"}
}