{
  "type": "Feature",
  "properties": {
    "iso:country":"DE",
    "sg:address":"Visbeker Str.",
    "sg:city":"Wildeshausen",
    "sg:phone":"+49 4431/810",
    "sg:postcode":"27793",
    "sg:province":"Niedersachsen",
    "wof:name":"F. Weyhausen & Co. Beteiligungsgesellschaft Mbh",
    "wof:placetype":"venue"
},
  "geometry": {"coordinates":[8.430872,52.893551],"type":"Point"}
}