{
  "type": "Feature",
  "properties": {
    "iso:country":"DE",
    "sg:address":"Roggenkamp 11",
    "sg:city":"Bad Bevensen",
    "sg:phone":"+49 5821/1082",
    "sg:postcode":"29549",
    "sg:province":"Niedersachsen",
    "wof:name":"Das Haus Am Walde",
    "wof:placetype":"venue"
},
  "geometry": {"coordinates":[10.5900764465,53.0857925415],"type":"Point"}
}