{
  "type": "Feature",
  "properties": {
    "iso:country":"DE",
    "sg:address":"Darmst\u00e4dter Str. 28",
    "sg:city":"Bickenbach",
    "sg:phone":"+49 6257/3031",
    "sg:postcode":"64404",
    "sg:province":"Hessen",
    "wof:name":"Heimatmuseum Bickenbach",
    "wof:placetype":"venue"
},
  "geometry": {"coordinates":[8.615051,49.753899],"type":"Point"}
}