{
  "type": "Feature",
  "properties": {
    "iso:country":"DE",
    "sg:address":"Jakobstr. 2",
    "sg:city":"Trier",
    "sg:phone":"+49 651/9941237",
    "sg:postcode":"54290",
    "sg:province":"Rheinland-Pfalz",
    "wof:name":"Cafe J\u00e4nschke",
    "wof:placetype":"venue"
},
  "geometry": {"coordinates":[6.6409449577,49.7570266724],"type":"Point"}
}