{
  "type": "Feature",
  "properties": {
    "iso:country":"DE",
    "sg:address":"Erfurter Str. 20",
    "sg:city":"Rodgau",
    "sg:phone":"+49 6106/71815",
    "sg:postcode":"63110",
    "sg:province":"Hessen",
    "wof:name":"Peter Siemon",
    "wof:placetype":"venue"
},
  "geometry": {"coordinates":[8.8775415421,50.0037231445],"type":"Point"}
}