{
  "type": "Feature",
  "properties": {
    "iso:country":"DE",
    "sg:address":"Gutenbergstr. 5",
    "sg:city":"Bamberg",
    "sg:phone":"+49 951/16018",
    "sg:postcode":"96050",
    "sg:province":"Bayern",
    "wof:name":"Vms",
    "wof:placetype":"venue"
},
  "geometry": {"coordinates":[10.9239587784,49.8838195801],"type":"Point"}
}