{
  "type": "Feature",
  "properties": {
    "iso:country":"DE",
    "sg:address":"Hauptstr. 50",
    "sg:city":"Westoverledingen",
    "sg:postcode":"26810",
    "sg:province":"Niedersachsen",
    "wof:name":"B\u00fccherei V\u00f6llen",
    "wof:placetype":"venue"
},
  "geometry": {"coordinates":[7.417198,53.107571],"type":"Point"}
}