{
  "type": "Feature",
  "properties": {
    "iso:country":"DE",
    "sg:address":"Moosacher Str. 73",
    "sg:city":"M\u00fcnchen",
    "sg:phone":"+49 89/354860",
    "sg:postcode":"80809",
    "sg:province":"Bayern",
    "wof:name":"Securitas Gmbh",
    "wof:placetype":"venue"
},
  "geometry": {"coordinates":[11.5533781052,48.1859130859],"type":"Point"}
}