{
  "type": "Feature",
  "properties": {
    "iso:country":"DE",
    "sg:address":"Mosbacher Str. 9",
    "sg:city":"Wiesbaden",
    "sg:phone":"+49 611/9854850",
    "sg:postcode":"65187",
    "sg:province":"Hessen",
    "wof:name":"Haus & Wohnen Beteiligungs- Gmbh",
    "wof:placetype":"venue"
},
  "geometry": {"coordinates":[8.237859726,50.0681648254],"type":"Point"}
}