{
  "type": "Feature",
  "properties": {
    "iso:country":"DE",
    "sg:address":"Hindenburgstr. 112",
    "sg:city":"Esslingen",
    "sg:phone":"+49 711/318159",
    "sg:postcode":"73728",
    "sg:province":"Baden-W\u00fcrttemberg",
    "wof:name":"Judith Katzer \u00dcbersetzerin",
    "wof:placetype":"venue"
},
  "geometry": {"coordinates":[9.32282,48.736591],"type":"Point"}
}