{
  "type": "Feature",
  "properties": {
    "iso:country":"DE",
    "sg:address":"G-H-Dietz Str. 3",
    "sg:city":"Schneeberg",
    "sg:phone":"+49 3772/8925",
    "sg:postcode":"08289",
    "sg:province":"Sachsen",
    "wof:name":"Kreissparkasse",
    "wof:placetype":"venue"
},
  "geometry": {"coordinates":[12.63892,50.587952],"type":"Point"}
}