{
  "type": "Feature",
  "properties": {
    "iso:country":"DE",
    "sg:address":"M\u00fchlenstr. 4b",
    "sg:city":"Ismaning",
    "sg:phone":"+49 89/9613244",
    "sg:postcode":"85737",
    "sg:province":"Bayern",
    "wof:name":"Siegfried Kerschbaum Bauelemente Vertriebs Gmbh",
    "wof:placetype":"venue"
},
  "geometry": {"coordinates":[11.675628,48.223721],"type":"Point"}
}