{
  "type": "Feature",
  "properties": {
    "iso:country":"DE",
    "sg:address":"Schallenburger Str. 27",
    "sg:city":"S\u00f6mmerda",
    "sg:phone":"+49 3634/623936",
    "sg:postcode":"99610",
    "sg:province":"Th\u00fcringen",
    "wof:name":"W. Und Silvia Felgentreff",
    "wof:placetype":"venue"
},
  "geometry": {"coordinates":[11.11026,51.146023],"type":"Point"}
}