{
  "type": "Feature",
  "properties": {
    "iso:country":"DE",
    "sg:address":"Kraftwerkstr.3",
    "sg:city":"Vetschau",
    "sg:postcode":"03226",
    "sg:province":"Brandenburg",
    "wof:name":"Rund Um Den Spreewald Und Vieles Mehr",
    "wof:placetype":"venue"
},
  "geometry": {"coordinates":[14.083144,51.779209],"type":"Point"}
}