{
  "type": "Feature",
  "properties": {
    "iso:country":"DE",
    "sg:address":"Sternstr. 65",
    "sg:city":"Bonn",
    "sg:phone":"+49 228/969695",
    "sg:postcode":"53111",
    "sg:province":"Nordrhein-Westfalen",
    "wof:name":"Ludwig H\u00f6rsch",
    "wof:placetype":"venue"
},
  "geometry": {"coordinates":[7.098482132,50.7357025146],"type":"Point"}
}