{
  "type": "Feature",
  "properties": {
    "iso:country":"DE",
    "sg:address":"Waisenstr. 13",
    "sg:city":"Chemnitz",
    "sg:phone":"+49 371/641303",
    "sg:postcode":"09111",
    "sg:province":"Sachsen",
    "wof:name":"Kerstin B\u00f6rner Rechtsanw\u00e4ltin",
    "wof:placetype":"venue"
},
  "geometry": {"coordinates":[12.9270620346,50.8359184265],"type":"Point"}
}