{
  "type": "Feature",
  "properties": {
    "iso:country":"DE",
    "sg:address":"Wilhelmstr. 45",
    "sg:city":"Siegburg",
    "sg:phone":"+49 2241/55045",
    "sg:postcode":"53721",
    "sg:province":"Nordrhein-Westfalen",
    "wof:name":"Bahnhofsgastst\u00e4tte Siegburg",
    "wof:placetype":"venue"
},
  "geometry": {"coordinates":[7.2172298431,50.7915382385],"type":"Point"}
}