{
  "type": "Feature",
  "properties": {
    "iso:country":"DE",
    "sg:address":"Goldstr. 19",
    "sg:city":"Burghaun",
    "sg:phone":"+49 6652/6968",
    "sg:postcode":"36151",
    "sg:province":"Hessen",
    "wof:name":"Joachim Klamt",
    "wof:placetype":"venue"
},
  "geometry": {"coordinates":[9.7374210358,50.6906394958],"type":"Point"}
}