{
  "type": "Feature",
  "properties": {
    "iso:country":"DE",
    "sg:address":"Hauptstr. 39",
    "sg:city":"March",
    "sg:phone":"+49 7665/2252",
    "sg:postcode":"79232",
    "sg:province":"Baden-W\u00fcrttemberg",
    "wof:name":"B\u00e4ren-apotheke In Der March Inh. Klaus Dieterle",
    "wof:placetype":"venue"
},
  "geometry": {"coordinates":[7.779399,48.06332],"type":"Point"}
}