{
  "type": "Feature",
  "properties": {
    "iso:country":"DE",
    "sg:address":"In der Schanze 34",
    "sg:city":"Bottrop",
    "sg:phone":"+49 2041/20685",
    "sg:postcode":"46242",
    "sg:province":"Nordrhein-Westfalen",
    "wof:name":"Bf S\u00fcdring Herrn Horst Schiel",
    "wof:placetype":"venue"
},
  "geometry": {"coordinates":[6.9172492027,51.5118331909],"type":"Point"}
}