{
  "type": "Feature",
  "properties": {
    "iso:country":"DE",
    "sg:address":"Anklamer Str. 10",
    "sg:city":"Torgelow",
    "sg:phone":"+49 3976/432697",
    "sg:postcode":"17358",
    "sg:province":"Mecklenburg-Vorpommern",
    "wof:name":"Hotel Zum Forsthaus",
    "wof:placetype":"venue"
},
  "geometry": {"coordinates":[13.9981145859,53.630569458],"type":"Point"}
}