{
  "type": "Feature",
  "properties": {
    "iso:country":"DE",
    "sg:address":"Schelmenwaldstr. 26",
    "sg:city":"M\u00fchlacker",
    "sg:phone":"+49 7041/96540",
    "sg:postcode":"75417",
    "sg:province":"Baden-W\u00fcrttemberg",
    "wof:name":"Lepple Verwaltungs- Gmbh",
    "wof:placetype":"venue"
},
  "geometry": {"coordinates":[8.856597,48.975456],"type":"Point"}
}