{
  "type": "Feature",
  "properties": {
    "iso:country":"DE",
    "sg:address":"Freiberger Str. 38",
    "sg:city":"Olbernhau",
    "sg:phone":"+49 37360/72437",
    "sg:postcode":"09526",
    "sg:province":"Sachsen",
    "wof:name":"Electronic-land Matthe\u00df & Zenker Ohg",
    "wof:placetype":"venue"
},
  "geometry": {"coordinates":[13.33383,50.664581],"type":"Point"}
}