{
  "type": "Feature",
  "properties": {
    "iso:country":"DE",
    "sg:address":"B\u00e4ckerplatz 11",
    "sg:city":"Allstedt",
    "sg:phone":"+49 34652/783",
    "sg:postcode":"06542",
    "sg:province":"Sachsen-Anhalt",
    "wof:name":"G. M\u00fcller",
    "wof:placetype":"venue"
},
  "geometry": {"coordinates":[11.3899993896,51.4038848877],"type":"Point"}
}