{
  "type": "Feature",
  "properties": {
    "iso:country":"DE",
    "sg:address":"Am Kirchplatz 7",
    "sg:city":"Malsch",
    "sg:phone":"+49 7246/319",
    "sg:postcode":"76316",
    "sg:province":"Baden-W\u00fcrttemberg",
    "wof:name":"Kath. Pfarramt St. Cyriak",
    "wof:placetype":"venue"
},
  "geometry": {"coordinates":[8.3361263275,48.8796157837],"type":"Point"}
}