{
  "type": "Feature",
  "properties": {
    "iso:country":"DE",
    "sg:address":"Adolph-Roemer-Str. 1a",
    "sg:city":"Clausthal-Zellerfeld",
    "sg:phone":"+49 5323/721",
    "sg:postcode":"38678",
    "sg:province":"Niedersachsen",
    "wof:name":"Institut F\u00fcr Wirtschafts- Wissenschaft Der Technischen",
    "wof:placetype":"venue"
},
  "geometry": {"coordinates":[10.3334627151,51.8045501709],"type":"Point"}
}