{
  "type": "Feature",
  "properties": {
    "iso:country":"DE",
    "sg:address":"Hinter der Mauer 8",
    "sg:city":"Pressath",
    "sg:phone":"+49 9644/346",
    "sg:postcode":"92690",
    "sg:province":"Bayern",
    "wof:name":"Josef Kneidl",
    "wof:placetype":"venue"
},
  "geometry": {"coordinates":[11.935886,49.770332],"type":"Point"}
}