{
  "type": "Feature",
  "properties": {
    "iso:country":"DE",
    "sg:address":"Bulthauptstr. 29",
    "sg:city":"Bremen",
    "sg:phone":"+49 421/341907",
    "sg:postcode":"28209",
    "sg:province":"Bremen",
    "wof:name":"Hans-dieter Weiss Kunstmaler",
    "wof:placetype":"venue"
},
  "geometry": {"coordinates":[8.831498,53.088287],"type":"Point"}
}