{
  "type": "Feature",
  "properties": {
    "iso:country":"DE",
    "sg:address":"Grebbener Str. 40",
    "sg:city":"Heinsberg",
    "sg:phone":"+49 2452/967684",
    "sg:postcode":"52525",
    "sg:province":"Nordrhein-Westfalen",
    "wof:name":"M. Jahnke",
    "wof:placetype":"venue"
},
  "geometry": {"coordinates":[6.1356639862,51.0520019531],"type":"Point"}
}