{
  "type": "Feature",
  "properties": {
    "iso:country":"DE",
    "sg:address":"Rudolf-Breitscheid-Str. 72a",
    "sg:city":"R\u00fcdersdorf",
    "sg:phone":"+49 33638/4155",
    "sg:postcode":"15562",
    "sg:province":"Brandenburg",
    "wof:name":"Becker Immobilien Gmbh",
    "wof:placetype":"venue"
},
  "geometry": {"coordinates":[13.8137149811,52.4693031311],"type":"Point"}
}