{
  "type": "Feature",
  "properties": {
    "iso:country":"DE",
    "sg:address":"Gartenstr. 2",
    "sg:city":"Seligenstadt",
    "sg:phone":"+49 6182/67899",
    "sg:postcode":"63500",
    "sg:province":"Hessen",
    "wof:name":"Bierbrunnen",
    "wof:placetype":"venue"
},
  "geometry": {"coordinates":[8.9440336227,50.0534286499],"type":"Point"}
}