{
  "type": "Feature",
  "properties": {
    "iso:country":"DE",
    "sg:address":"Hans-Heinrich-Warnke-Str. 14",
    "sg:city":"Celle",
    "sg:postcode":"29227",
    "sg:province":"Niedersachsen",
    "wof:name":"Christine Wagner Musikinstrumenten-montage-",
    "wof:placetype":"venue"
},
  "geometry": {"coordinates":[10.1150503159,52.6008148193],"type":"Point"}
}