{
  "type": "Feature",
  "properties": {
    "iso:country":"DE",
    "sg:address":"Hauptstr. 42",
    "sg:city":"We\u00dfling",
    "sg:phone":"+49 8153/4080",
    "sg:postcode":"82234",
    "sg:province":"Bayern",
    "wof:name":"Raiffeisen-versicherungs- Dienst Gmbh Vierseenland",
    "wof:placetype":"venue"
},
  "geometry": {"coordinates":[11.2489023209,48.0754928589],"type":"Point"}
}