{
  "type": "Feature",
  "properties": {
    "iso:country":"DE",
    "sg:address":"Telemannstr. 22",
    "sg:city":"Frankfurt",
    "sg:postcode":"60323",
    "sg:province":"Hessen",
    "wof:name":"Mdd Modulare Informations- Systeme Ag",
    "wof:placetype":"venue"
},
  "geometry": {"coordinates":[8.669645,50.121239],"type":"Point"}
}