{
  "type": "Feature",
  "properties": {
    "iso:country":"DE",
    "sg:address":"Winkeler Str. 100",
    "sg:city":"Geisenheim",
    "sg:phone":"+49 6722/980568",
    "sg:postcode":"65366",
    "sg:province":"Hessen",
    "wof:name":"Dirlenbach & Porlein Planungs Gmbh",
    "wof:placetype":"venue"
},
  "geometry": {"coordinates":[7.973308,49.987225],"type":"Point"}
}