{
  "type": "Feature",
  "properties": {
    "iso:country":"DE",
    "sg:address":"Gro\u00dfendorf 6",
    "sg:city":"B\u00fcdingen",
    "sg:phone":"+49 6042/2870",
    "sg:postcode":"63654",
    "sg:province":"Hessen",
    "wof:name":"Aynur Feyyaz",
    "wof:placetype":"venue"
},
  "geometry": {"coordinates":[9.1062374115,50.2905044556],"type":"Point"}
}