{
  "type": "Feature",
  "properties": {
    "iso:country":"DE",
    "sg:address":"Pfingstbrunnenweg 6",
    "sg:city":"Leutkirch",
    "sg:phone":"+49 7561/1881",
    "sg:postcode":"88299",
    "sg:province":"Baden-W\u00fcrttemberg",
    "wof:name":"Vereinsgastst\u00e4tte Kleintier- Zuchtverein Leutkich",
    "wof:placetype":"venue"
},
  "geometry": {"coordinates":[10.0384349823,47.8196334839],"type":"Point"}
}