{
  "type": "Feature",
  "properties": {
    "iso:country":"DE",
    "sg:address":"Strandweg 3",
    "sg:city":"T\u00f6nning",
    "sg:postcode":"25832",
    "sg:province":"Schleswig-Holstein",
    "wof:name":"Elke Peters Nationalpark-reisen",
    "wof:placetype":"venue"
},
  "geometry": {"coordinates":[8.9356765747,54.3089675903],"type":"Point"}
}