{
  "type": "Feature",
  "properties": {
    "iso:country":"DE",
    "sg:address":"Heimchenweg 47",
    "sg:city":"Frankfurt",
    "sg:phone":"+49 69/315072",
    "sg:postcode":"65929",
    "sg:province":"Hessen",
    "wof:name":"Rhm-haustechnik Gesell. F\u00fcr Rohrleitungs-heizungs-l\u00fcftung-",
    "wof:placetype":"venue"
},
  "geometry": {"coordinates":[8.535195,50.103489],"type":"Point"}
}