{
  "type": "Feature",
  "properties": {
    "iso:country":"DE",
    "sg:address":"Welsberg 35",
    "sg:city":"Itzgrund",
    "sg:phone":"+49 9533/92370",
    "sg:postcode":"96274",
    "sg:province":"Bayern",
    "wof:name":"Finzel & Lindenlaub Gmbh",
    "wof:placetype":"venue"
},
  "geometry": {"coordinates":[10.8991346359,50.1650619507],"type":"Point"}
}