{
  "type": "Feature",
  "properties": {
    "iso:country":"DE",
    "sg:address":"Eisenbahnstr 9",
    "sg:city":"Tuttlingen",
    "sg:phone":"+49 7461/77909",
    "sg:postcode":"78532",
    "sg:province":"Baden-W\u00fcrttemberg",
    "wof:name":"Janfried Seeburger",
    "wof:placetype":"venue"
},
  "geometry": {"coordinates":[8.801821,47.982647],"type":"Point"}
}