{
  "type": "Feature",
  "properties": {
    "iso:country":"DE",
    "sg:address":"Schillerstr. 12",
    "sg:city":"Gotha",
    "sg:phone":"+49 3621/26796",
    "sg:postcode":"99867",
    "sg:province":"Th\u00fcringen",
    "wof:name":"Steffi Ziegenbalg",
    "wof:placetype":"venue"
},
  "geometry": {"coordinates":[10.7020578384,50.9548835754],"type":"Point"}
}