{
  "type": "Feature",
  "properties": {
    "iso:country":"DE",
    "sg:address":"Reiler Str. 47",
    "sg:city":"Berlin",
    "sg:phone":"+49 30/5455493",
    "sg:postcode":"12681",
    "sg:province":"Berlin",
    "wof:name":"J\u00fcrgen Paul Ingenieur",
    "wof:placetype":"venue"
},
  "geometry": {"coordinates":[13.5320396423,52.5157966614],"type":"Point"}
}