{
  "type": "Feature",
  "properties": {
    "iso:country":"DE",
    "sg:address":"Ahlbecker Str. 12",
    "sg:city":"Berlin",
    "sg:postcode":"10437",
    "sg:province":"Berlin",
    "wof:name":"Paul M\u00f6ssner & Sohn Kg",
    "wof:placetype":"venue"
},
  "geometry": {"coordinates":[13.423828125,52.5448722839],"type":"Point"}
}