{
  "type": "Feature",
  "properties": {
    "iso:country":"DE",
    "sg:address":"Raiffeisenstr. 34",
    "sg:city":"Filderstadt",
    "sg:phone":"+49 711/775198",
    "sg:postcode":"70794",
    "sg:province":"Baden-W\u00fcrttemberg",
    "wof:name":"Engitec E. K.",
    "wof:placetype":"venue"
},
  "geometry": {"coordinates":[9.228023,48.657261],"type":"Point"}
}