{
  "type": "Feature",
  "properties": {
    "iso:country":"DE",
    "sg:address":"Marienplatz 5",
    "sg:city":"Schwerin",
    "sg:phone":"+49 385/569731",
    "sg:postcode":"19053",
    "sg:province":"Mecklenburg-Vorpommern",
    "wof:name":"Sabine Koltzer",
    "wof:placetype":"venue"
},
  "geometry": {"coordinates":[11.4107046127,53.6282119751],"type":"Point"}
}