{
  "type": "Feature",
  "properties": {
    "iso:country":"DE",
    "sg:address":"Nibelungenstr. 700",
    "sg:city":"Lautertal",
    "sg:phone":"+49 6254/942226",
    "sg:postcode":"64686",
    "sg:province":"Hessen",
    "wof:name":"Ixtensa Mediadesign Ohg",
    "wof:placetype":"venue"
},
  "geometry": {"coordinates":[8.7393779755,49.7165145874],"type":"Point"}
}