{
  "type": "Feature",
  "properties": {
    "iso:country":"DE",
    "sg:address":"Dorfstr. 59",
    "sg:city":"Neukirchen",
    "sg:postcode":"39615",
    "sg:province":"Sachsen-Anhalt",
    "wof:name":"R & W Gewerbeprojekte Gmbh",
    "wof:placetype":"venue"
},
  "geometry": {"coordinates":[11.8778371811,52.8805618286],"type":"Point"}
}