{
  "type": "Feature",
  "properties": {
    "iso:country":"DE",
    "sg:address":"Humboldtstr. 24",
    "sg:city":"Jena",
    "sg:phone":"+49 3641/46000",
    "sg:postcode":"07743",
    "sg:province":"Th\u00fcringen",
    "wof:name":"Wolfgang Roth Steuerberater",
    "wof:placetype":"venue"
},
  "geometry": {"coordinates":[11.5732870102,50.9332199097],"type":"Point"}
}