{
  "type": "Feature",
  "properties": {
    "iso:country":"DE",
    "sg:address":"Th\u00e4lmannstr. 21a",
    "sg:city":"Lieberose",
    "sg:postcode":"15868",
    "sg:province":"Brandenburg",
    "wof:name":"K. Grzelachowski",
    "wof:placetype":"venue"
},
  "geometry": {"coordinates":[14.2938766479,51.9802818298],"type":"Point"}
}