{
  "type": "Feature",
  "properties": {
    "iso:country":"DE",
    "sg:address":"Ringstr. 129",
    "sg:city":"Winnenden",
    "sg:phone":"+49 7195/178339",
    "sg:postcode":"71364",
    "sg:province":"Baden-W\u00fcrttemberg",
    "wof:name":"Karl Gal",
    "wof:placetype":"venue"
},
  "geometry": {"coordinates":[9.403033,48.87315],"type":"Point"}
}