{
  "type": "Feature",
  "properties": {
    "iso:country":"DE",
    "sg:address":"In der Hommersbach 18",
    "sg:city":"Heusweiler",
    "sg:phone":"+49 6806/12478",
    "sg:postcode":"66265",
    "sg:province":"Saarland",
    "wof:name":"C. D. Maas",
    "wof:placetype":"venue"
},
  "geometry": {"coordinates":[6.9398598671,49.3451156616],"type":"Point"}
}