{
  "type": "Feature",
  "properties": {
    "iso:country":"DE",
    "sg:address":"Im Steenesch 17",
    "sg:city":"Osterholz-Scharmbeck",
    "sg:phone":"+49 4791/4517",
    "sg:postcode":"27711",
    "sg:province":"Niedersachsen",
    "wof:name":"H. Langheim",
    "wof:placetype":"venue"
},
  "geometry": {"coordinates":[8.78808,53.221004],"type":"Point"}
}