{
  "type": "Feature",
  "properties": {
    "iso:country":"DE",
    "sg:address":"Wellingsb\u00fcttler Weg 91",
    "sg:city":"Hamburg",
    "sg:phone":"+49 40/5362402",
    "sg:postcode":"22391",
    "sg:province":"Hamburg",
    "wof:name":"Country House Restaurant Wellingsb\u00fcttel Gmbh",
    "wof:placetype":"venue"
},
  "geometry": {"coordinates":[10.077132225,53.6423606873],"type":"Point"}
}