{
  "type": "Feature",
  "properties": {
    "iso:country":"DE",
    "sg:address":"Neum\u00fchler Str. 67",
    "sg:city":"Oberhausen",
    "sg:phone":"+49 208/661187",
    "sg:postcode":"46149",
    "sg:province":"Nordrhein-Westfalen",
    "wof:name":"Dr. Med. Ulrich Christ",
    "wof:placetype":"venue"
},
  "geometry": {"coordinates":[6.8356351852,51.5104484558],"type":"Point"}
}