{
  "type": "Feature",
  "properties": {
    "iso:country":"DE",
    "sg:address":"Hauptstr. 134",
    "sg:city":"Zethau",
    "sg:postcode":"09619",
    "sg:province":"Sachsen",
    "wof:name":"Hamburg-mannheimer Sachversicherungs-ag",
    "wof:placetype":"venue"
},
  "geometry": {"coordinates":[13.4148817062,50.7560653687],"type":"Point"}
}