{
  "type": "Feature",
  "properties": {
    "iso:country":"DE",
    "sg:address":"Bahnhofstr. 57",
    "sg:city":"Suderburg",
    "sg:phone":"+49 4958/268031",
    "sg:postcode":"29556",
    "sg:province":"Niedersachsen",
    "wof:name":"Sparkasse Uelzen",
    "wof:placetype":"venue"
},
  "geometry": {"coordinates":[10.43939,52.900009],"type":"Point"}
}