{
  "type": "Feature",
  "properties": {
    "iso:country":"DE",
    "sg:address":"Schwalbenweg 6",
    "sg:city":"Korntal-M\u00fcnchingen",
    "sg:phone":"+49 7150/959976",
    "sg:postcode":"70825",
    "sg:province":"Baden-W\u00fcrttemberg",
    "wof:name":"Peter Herfert",
    "wof:placetype":"venue"
},
  "geometry": {"coordinates":[9.0873250961,48.8512611389],"type":"Point"}
}