{
  "type": "Feature",
  "properties": {
    "iso:country":"DE",
    "sg:address":"Kirchplatz 8",
    "sg:city":"G\u00f6risried",
    "sg:phone":"+49 8302/1067",
    "sg:postcode":"87657",
    "sg:province":"Bayern",
    "wof:name":"Gasthaus Adler",
    "wof:placetype":"venue"
},
  "geometry": {"coordinates":[10.5093460083,47.7069702148],"type":"Point"}
}