{
  "type": "Feature",
  "properties": {
    "iso:country":"DE",
    "sg:address":"M\u00fcnchhausenstr. 9",
    "sg:city":"Bodenwerder",
    "sg:phone":"+49 5533/6466",
    "sg:postcode":"37619",
    "sg:province":"Niedersachsen",
    "wof:name":"Helmut Sporleder",
    "wof:placetype":"venue"
},
  "geometry": {"coordinates":[9.5147218704,51.9766235352],"type":"Point"}
}