{
  "type": "Feature",
  "properties": {
    "iso:country":"DE",
    "sg:address":"Wasserbank 3",
    "sg:city":"Witten",
    "sg:phone":"+49 2302/973060",
    "sg:postcode":"58456",
    "sg:province":"Nordrhein-Westfalen",
    "wof:name":"Schlee Gmbh & Co.",
    "wof:placetype":"venue"
},
  "geometry": {"coordinates":[7.2679362297,51.4076538086],"type":"Point"}
}