{
  "type": "Feature",
  "properties": {
    "iso:country":"DE",
    "sg:address":"Hauptstr. 74",
    "sg:city":"Sinsheim",
    "sg:phone":"+49 7261/17722",
    "sg:postcode":"74889",
    "sg:province":"Baden-W\u00fcrttemberg",
    "wof:name":"Dieter Schick",
    "wof:placetype":"venue"
},
  "geometry": {"coordinates":[8.875966,49.253357],"type":"Point"}
}