{
  "type": "Feature",
  "properties": {
    "iso:country":"DE",
    "sg:address":"K\u00f6nigsberger Ring 2",
    "sg:city":"Hochheim",
    "sg:phone":"+49 6146/6583",
    "sg:postcode":"65239",
    "sg:province":"Hessen",
    "wof:name":"M.-l. Drillich-naas",
    "wof:placetype":"venue"
},
  "geometry": {"coordinates":[8.34562,50.016129],"type":"Point"}
}