{
  "type": "Feature",
  "properties": {
    "iso:country":"DE",
    "sg:address":"Marktplatz 2",
    "sg:city":"Wunsiedel",
    "sg:phone":"+49 9232/996633",
    "sg:postcode":"95632",
    "sg:province":"Bayern",
    "wof:name":"Akzente Reisen Gmbh",
    "wof:placetype":"venue"
},
  "geometry": {"coordinates":[12.0026855469,50.0375747681],"type":"Point"}
}