{
  "type": "Feature",
  "properties": {
    "iso:country":"DE",
    "sg:address":"Mansfeldstr. 31",
    "sg:city":"D\u00fcsseldorf",
    "sg:phone":"+49 211/288526",
    "sg:postcode":"40625",
    "sg:province":"Nordrhein-Westfalen",
    "wof:name":"Grafiker Friedhelm Fresen",
    "wof:placetype":"venue"
},
  "geometry": {"coordinates":[6.854154,51.235641],"type":"Point"}
}