{
  "type": "Feature",
  "properties": {
    "iso:country":"DE",
    "sg:address":"Leydheckerstr. 8",
    "sg:city":"Darmstadt",
    "sg:phone":"+49 6151/87160",
    "sg:postcode":"64293",
    "sg:province":"Hessen",
    "wof:name":"Markwort Gmbh",
    "wof:placetype":"venue"
},
  "geometry": {"coordinates":[8.63731,49.885681],"type":"Point"}
}