{
  "type": "Feature",
  "properties": {
    "iso:country":"DE",
    "sg:address":"Borsigstr. 6",
    "sg:city":"Heusenstamm",
    "sg:phone":"+49 6104/924816",
    "sg:postcode":"63150",
    "sg:province":"Hessen",
    "wof:name":"Monitex Vertriebs Und Handels Gmbh",
    "wof:placetype":"venue"
},
  "geometry": {"coordinates":[8.8004713058,50.05235672],"type":"Point"}
}