{
  "type": "Feature",
  "properties": {
    "iso:country":"DE",
    "sg:address":"M\u00fclsener Str. 2",
    "sg:city":"Reinsdorf",
    "sg:phone":"+49 375/293273",
    "sg:postcode":"08141",
    "sg:province":"Sachsen",
    "wof:name":"Friedhold Otto",
    "wof:placetype":"venue"
},
  "geometry": {"coordinates":[12.573001,50.696125],"type":"Point"}
}