{
  "type": "Feature",
  "properties": {
    "iso:country":"DE",
    "sg:address":"Pfingstanger 30",
    "sg:city":"Osterode",
    "sg:phone":"+49 5522/82958",
    "sg:postcode":"37520",
    "sg:province":"Niedersachsen",
    "wof:name":"Sviklis Gmbh",
    "wof:placetype":"venue"
},
  "geometry": {"coordinates":[10.174553,51.740383],"type":"Point"}
}