{
  "type": "Feature",
  "properties": {
    "iso:country":"DE",
    "sg:address":"Adenauerallee 47",
    "sg:city":"Bocholt",
    "sg:phone":"+49 2871/38576",
    "sg:postcode":"46399",
    "sg:province":"Nordrhein-Westfalen",
    "wof:name":"Leo Heutmann",
    "wof:placetype":"venue"
},
  "geometry": {"coordinates":[6.615965,51.846497],"type":"Point"}
}