{
  "type": "Feature",
  "properties": {
    "iso:country":"DE",
    "sg:address":"Hedwig-Dransfeld-Platz 8",
    "sg:city":"Essen",
    "sg:phone":"+49 201/634020",
    "sg:postcode":"45143",
    "sg:province":"Nordrhein-Westfalen",
    "wof:name":"Wohnungsgenossenschaft Essen-nord Eg",
    "wof:placetype":"venue"
},
  "geometry": {"coordinates":[6.9621200562,51.4595489502],"type":"Point"}
}