{
  "type": "Feature",
  "properties": {
    "iso:country":"DE",
    "sg:address":"Sch\u00f6nbacher Stra\u00dfe 21",
    "sg:city":"K\u00fchbach",
    "sg:phone":"+49 8251/52465",
    "sg:postcode":"86556",
    "sg:province":"Bayern",
    "wof:name":"S. R. Brozek Vertriebsf\u00f6rderung",
    "wof:placetype":"venue"
},
  "geometry": {"coordinates":[11.1889009476,48.4898643494],"type":"Point"}
}