{
  "type": "Feature",
  "properties": {
    "iso:country":"DE",
    "sg:address":"Fuhrenkampsweg 21",
    "sg:city":"Buxtehude",
    "sg:phone":"+49 4163/3217",
    "sg:postcode":"21614",
    "sg:province":"Niedersachsen",
    "wof:name":"Siegfried Jungblut Heilpraktiker",
    "wof:placetype":"venue"
},
  "geometry": {"coordinates":[9.6121778488,53.4763717651],"type":"Point"}
}