{
  "type": "Feature",
  "properties": {
    "iso:country":"DE",
    "sg:address":"Calenberger Esplanade 2-6",
    "sg:city":"Hannover",
    "sg:postcode":"30169",
    "sg:province":"Niedersachsen",
    "wof:name":"Eqvita Gmbh",
    "wof:placetype":"venue"
},
  "geometry": {"coordinates":[9.7237863541,52.3697319031],"type":"Point"}
}