{
  "type": "Feature",
  "properties": {
    "iso:country":"DE",
    "sg:address":"Aischbachstr. 22",
    "sg:city":"T\u00fcbingen",
    "sg:phone":"+49 7071/49939",
    "sg:postcode":"72070",
    "sg:province":"Baden-W\u00fcrttemberg",
    "wof:name":"J. B\u00fchler",
    "wof:placetype":"venue"
},
  "geometry": {"coordinates":[9.0417814255,48.5242271423],"type":"Point"}
}