{
  "type": "Feature",
  "properties": {
    "iso:country":"DE",
    "sg:address":"Braker Str. 123",
    "sg:city":"Bielefeld",
    "sg:phone":"+49 521/761022",
    "sg:postcode":"33729",
    "sg:province":"Nordrhein-Westfalen",
    "wof:name":"W. Frodenau",
    "wof:placetype":"venue"
},
  "geometry": {"coordinates":[8.5929031372,52.0712127686],"type":"Point"}
}