{
  "type": "Feature",
  "properties": {
    "iso:country":"DE",
    "sg:address":"H\u00fcckeswagener Str. 68",
    "sg:city":"Gummersbach",
    "sg:phone":"+49 2261/22054",
    "sg:postcode":"51647",
    "sg:province":"Nordrhein-Westfalen",
    "wof:name":"Karl-friedrich Schneider",
    "wof:placetype":"venue"
},
  "geometry": {"coordinates":[7.548916,51.045525],"type":"Point"}
}