{
  "type": "Feature",
  "properties": {
    "iso:country":"DE",
    "sg:address":"Preziosastr. 1 a",
    "sg:city":"M\u00fcnchen",
    "sg:phone":"+49 89/771066",
    "sg:postcode":"81927",
    "sg:province":"Bayern",
    "wof:name":"Happy Diver Sport- Und Tauchreisen Gmbh",
    "wof:placetype":"venue"
},
  "geometry": {"coordinates":[11.6431779861,48.1709861755],"type":"Point"}
}