{
  "type": "Feature",
  "properties": {
    "iso:country":"DE",
    "sg:address":"Postfach 400128",
    "sg:city":"M\u00fcnchen",
    "sg:phone":"+49 89/349830",
    "sg:postcode":"80701",
    "sg:province":"Bayern",
    "wof:name":"Arts & Antiques Edition",
    "wof:placetype":"venue"
},
  "geometry": {"coordinates":[11.58027,48.139099],"type":"Point"}
}