{
  "type": "Feature",
  "properties": {
    "iso:country":"DE",
    "sg:address":"Sch\u00e4ppeleweg 2",
    "sg:city":"Freiburg",
    "sg:phone":"+49 761/82705",
    "sg:postcode":"79110",
    "sg:province":"Baden-W\u00fcrttemberg",
    "wof:name":"Hansj\u00f6rg Maier",
    "wof:placetype":"venue"
},
  "geometry": {"coordinates":[7.831086,48.01096],"type":"Point"}
}