{
  "type": "Feature",
  "properties": {
    "iso:country":"DE",
    "sg:address":"Eschholzstr. 62",
    "sg:city":"Freiburg",
    "sg:phone":"+49 761/275841",
    "sg:postcode":"79115",
    "sg:province":"Baden-W\u00fcrttemberg",
    "wof:name":"D. M\u00f6st Masseur",
    "wof:placetype":"venue"
},
  "geometry": {"coordinates":[7.83242,47.993481],"type":"Point"}
}