{
  "type": "Feature",
  "properties": {
    "iso:country":"DE",
    "sg:address":"Otto-Suhr-Allee 114",
    "sg:city":"Berlin",
    "sg:phone":"+49 30/34703685",
    "sg:postcode":"10585",
    "sg:province":"Berlin",
    "wof:name":"Interrisk Versicherungs- Ag",
    "wof:placetype":"venue"
},
  "geometry": {"coordinates":[13.3056402206,52.5179443359],"type":"Point"}
}