{
  "type": "Feature",
  "properties": {
    "iso:country":"DE",
    "sg:address":"Weidenallee 25",
    "sg:city":"Hamburg",
    "sg:phone":"+49 40/4300246",
    "sg:postcode":"20357",
    "sg:province":"Hamburg",
    "wof:name":"Snack-bar L Incontro",
    "wof:placetype":"venue"
},
  "geometry": {"coordinates":[9.9649028778,53.5667724609],"type":"Point"}
}