{
  "type": "Feature",
  "properties": {
    "iso:country":"DE",
    "sg:address":"Dahmestra\u00dfe 72",
    "sg:city":"Berlin / Gr\u00fcnau",
    "sg:phone":"+49 177 2507459",
    "sg:postcode":"12526",
    "sg:province":"Berlin",
    "wof:name":"Stahl & Partner Gbr",
    "wof:placetype":"venue"
},
  "geometry": {"coordinates":[13.5704908371,52.4012298584],"type":"Point"}
}