{
  "type": "Feature",
  "properties": {
    "iso:country":"DE",
    "sg:city":"Alexisbad",
    "sg:phone":"+49 39485",
    "sg:postcode":"06493",
    "sg:province":"Sachsen-Anhalt",
    "wof:name":"Freundeskreis Selketalbahn E.v.",
    "wof:placetype":"venue"
},
  "geometry": {"coordinates":[11.11817,51.649887],"type":"Point"}
}