{
  "type": "Feature",
  "properties": {
    "iso:country":"DE",
    "sg:address":"Wilmsstr. 22",
    "sg:city":"Berlin",
    "sg:phone":"+49 30/6936305",
    "sg:postcode":"10961",
    "sg:province":"Berlin",
    "wof:name":"Gastst\u00e4tte Zur Feuerwache",
    "wof:placetype":"venue"
},
  "geometry": {"coordinates":[13.4021282196,52.4955787659],"type":"Point"}
}