{
  "type": "Feature",
  "properties": {
    "iso:country":"DE",
    "sg:address":"Winterswijker Str. 86",
    "sg:city":"Bocholt",
    "sg:phone":"+49 2871/39375",
    "sg:postcode":"46399",
    "sg:province":"Nordrhein-Westfalen",
    "wof:name":"Hermann Thewes",
    "wof:placetype":"venue"
},
  "geometry": {"coordinates":[6.661491,51.885883],"type":"Point"}
}