{
  "type": "Feature",
  "properties": {
    "iso:country":"DE",
    "sg:address":"Mariah\u00fctter Str. 14",
    "sg:city":"Nonnweiler",
    "sg:phone":"+49 6873/64235",
    "sg:postcode":"66620",
    "sg:province":"Saarland",
    "wof:name":"Georg Nonweiler",
    "wof:placetype":"venue"
},
  "geometry": {"coordinates":[6.9933538437,49.6012535095],"type":"Point"}
}