{
  "type": "Feature",
  "properties": {
    "iso:country":"DE",
    "sg:address":"Robert-Mayer-Str. 16",
    "sg:city":"Bretzfeld",
    "sg:postcode":"74626",
    "sg:province":"Baden-W\u00fcrttemberg",
    "wof:name":"Lbw Wohnbau Gmbh",
    "wof:placetype":"venue"
},
  "geometry": {"coordinates":[9.436739,49.181145],"type":"Point"}
}