{
  "type": "Feature",
  "properties": {
    "iso:country":"DE",
    "sg:address":"N\u00e4gelestr 8",
    "sg:city":"Stuttgart",
    "sg:phone":"+49 711/8066990",
    "sg:postcode":"70597",
    "sg:province":"Baden-W\u00fcrttemberg",
    "wof:name":"Gsk Werbeagentur Gmbh",
    "wof:placetype":"venue"
},
  "geometry": {"coordinates":[9.174189,48.751862],"type":"Point"}
}