{
  "type": "Feature",
  "properties": {
    "iso:country":"DE",
    "sg:address":"Am L\u00f6schteich 8",
    "sg:city":"Neustadt",
    "sg:phone":"+49 5032/4589",
    "sg:postcode":"31535",
    "sg:province":"Niedersachsen",
    "wof:name":"Walter V\u00f6lkers",
    "wof:placetype":"venue"
},
  "geometry": {"coordinates":[9.551754,52.550243],"type":"Point"}
}