{
  "type": "Feature",
  "properties": {
    "iso:country":"DE",
    "sg:address":"Riemenschneiderstr. 29",
    "sg:city":"Straubing",
    "sg:phone":"+49 9421/41515",
    "sg:postcode":"94315",
    "sg:province":"Bayern",
    "wof:name":"Kohlmeier Dentallabor Gmbh",
    "wof:placetype":"venue"
},
  "geometry": {"coordinates":[12.557003,48.874527],"type":"Point"}
}