{
  "type": "Feature",
  "properties": {
    "iso:country":"DE",
    "sg:address":"Kickerlingsberg 2",
    "sg:city":"Leipzig",
    "sg:phone":"+49 341/5640286",
    "sg:postcode":"04105",
    "sg:province":"Sachsen",
    "wof:name":"Ferdinand Knabe",
    "wof:placetype":"venue"
},
  "geometry": {"coordinates":[12.372843,51.351757],"type":"Point"}
}