{
  "type": "Feature",
  "properties": {
    "iso:country":"DE",
    "sg:address":"Marktplatz 6",
    "sg:city":"Kirchenthumbach",
    "sg:phone":"+49 9647/260",
    "sg:postcode":"91281",
    "sg:province":"Bayern",
    "wof:name":"Gastst\u00e4tte Hans Lindner",
    "wof:placetype":"venue"
},
  "geometry": {"coordinates":[11.7242488861,49.7489700317],"type":"Point"}
}