{
  "type": "Feature",
  "properties": {
    "iso:country":"DE",
    "sg:address":"Heidgraben 4",
    "sg:city":"Schlitz",
    "sg:phone":"+49 6642/8010",
    "sg:postcode":"36110",
    "sg:province":"Hessen",
    "wof:name":"Eichhoff-werke Gmbh",
    "wof:placetype":"venue"
},
  "geometry": {"coordinates":[9.561756134,50.6795654297],"type":"Point"}
}