{
  "type": "Feature",
  "properties": {
    "iso:country":"DE",
    "sg:address":"Pferdemarkt 20",
    "sg:city":"Deggendorf",
    "sg:phone":"+49 991/22952",
    "sg:postcode":"94469",
    "sg:province":"Bayern",
    "wof:name":"Sozialberatungsstelle Kreis-caritasverband",
    "wof:placetype":"venue"
},
  "geometry": {"coordinates":[12.963153,48.829571],"type":"Point"}
}