{
  "type": "Feature",
  "properties": {
    "iso:country":"DE",
    "sg:address":"Dorfstr. 20",
    "sg:city":"Berghaupten",
    "sg:phone":"+49 7803/3107",
    "sg:postcode":"77791",
    "sg:province":"Baden-W\u00fcrttemberg",
    "wof:name":"Wilhelm R\u00f6sch",
    "wof:placetype":"venue"
},
  "geometry": {"coordinates":[7.98855,48.406277],"type":"Point"}
}