{
  "type": "Feature",
  "properties": {
    "iso:country":"DE",
    "sg:address":"Kasernenstr. 28",
    "sg:city":"Coburg",
    "sg:phone":"+49 9561/62639",
    "sg:postcode":"96450",
    "sg:province":"Bayern",
    "wof:name":"Tucher-stuben",
    "wof:placetype":"venue"
},
  "geometry": {"coordinates":[10.9654541016,50.2686233521],"type":"Point"}
}