{
  "type": "Feature",
  "properties": {
    "iso:country":"DE",
    "sg:address":"Reuteranger 14",
    "sg:city":"Sehnde",
    "sg:phone":"+49 5138/8718",
    "sg:postcode":"31319",
    "sg:province":"Niedersachsen",
    "wof:name":"G. Tubbe",
    "wof:placetype":"venue"
},
  "geometry": {"coordinates":[9.914819,52.339497],"type":"Point"}
}