{
  "type": "Feature",
  "properties": {
    "iso:country":"DE",
    "sg:address":"Karmarschstr. 30",
    "sg:city":"Hannover",
    "sg:phone":"+49 511/363311",
    "sg:postcode":"30159",
    "sg:province":"Niedersachsen",
    "wof:name":"Hettlage Gmbh & Co.",
    "wof:placetype":"venue"
},
  "geometry": {"coordinates":[9.737632,52.372494],"type":"Point"}
}