{
  "type": "Feature",
  "properties": {
    "iso:country":"DE",
    "sg:address":"Mellinghofer Str. 378",
    "sg:city":"M\u00fclheim",
    "sg:phone":"+49 208/73807",
    "sg:postcode":"45475",
    "sg:province":"Nordrhein-Westfalen",
    "wof:name":"S. Marotta",
    "wof:placetype":"venue"
},
  "geometry": {"coordinates":[6.8888378143,51.4659729004],"type":"Point"}
}