{
  "type": "Feature",
  "properties": {
    "iso:country":"DE",
    "sg:address":"Grevener Str. 418",
    "sg:city":"M\u00fcnster",
    "sg:phone":"+49 251/216088",
    "sg:postcode":"48159",
    "sg:province":"Nordrhein-Westfalen",
    "wof:name":"Gerlind Kenntoff-berkenheger Steuerberaterin",
    "wof:placetype":"venue"
},
  "geometry": {"coordinates":[7.6129322052,51.9947280884],"type":"Point"}
}