{
  "type": "Feature",
  "properties": {
    "iso:country":"DE",
    "sg:address":"Tilsiter Str. 51",
    "sg:city":"Limburgerhof",
    "sg:phone":"+49 6236/496608",
    "sg:postcode":"67117",
    "sg:province":"Rheinland-Pfalz",
    "wof:name":"Lauer-baubetreuung- Immobilien Gmbh",
    "wof:placetype":"venue"
},
  "geometry": {"coordinates":[8.377007,49.42189],"type":"Point"}
}