{
  "type": "Feature",
  "properties": {
    "iso:country":"DE",
    "sg:address":"Uerdinger Str. 292",
    "sg:city":"Krefeld",
    "sg:phone":"+49 2151/597300",
    "sg:postcode":"47800",
    "sg:province":"Nordrhein-Westfalen",
    "wof:name":"Schiller-apotheke",
    "wof:placetype":"venue"
},
  "geometry": {"coordinates":[6.592829,51.340023],"type":"Point"}
}