{
  "type": "Feature",
  "properties": {
    "iso:country":"DE",
    "sg:address":"Peter-D\u00f6rfler-Str. 11",
    "sg:city":"Lindenberg",
    "sg:phone":"+49 8381/2547",
    "sg:postcode":"88161",
    "sg:province":"Bayern",
    "wof:name":"Trachten-kolb",
    "wof:placetype":"venue"
},
  "geometry": {"coordinates":[9.877904892,47.5998725891],"type":"Point"}
}