{
  "type": "Feature",
  "properties": {
    "iso:country":"DE",
    "sg:address":"Hauptstr. 52",
    "sg:city":"Buchholz",
    "sg:phone":"+49 2683/4780",
    "sg:postcode":"53567",
    "sg:province":"Rheinland-Pfalz",
    "wof:name":"Katholisches Pfarramt St. Pantaleon",
    "wof:placetype":"venue"
},
  "geometry": {"coordinates":[9.2259550095,53.9873199463],"type":"Point"}
}