{
  "type": "Feature",
  "properties": {
    "iso:country":"DE",
    "sg:city":"Baiersdorf",
    "sg:postcode":"91083",
    "sg:province":"Bayern",
    "wof:name":"Jc-casablanca",
    "wof:placetype":"venue"
},
  "geometry": {"coordinates":[11.03207,49.656971],"type":"Point"}
}