{
  "type": "Feature",
  "properties": {
    "iso:country":"DE",
    "sg:address":"Potsdamer Str. 139",
    "sg:city":"Berlin",
    "sg:phone":"+49 30/2151022",
    "sg:postcode":"10783",
    "sg:province":"Berlin",
    "wof:name":"Frauen Unterwegs E. V. Reiseveranstaltungen",
    "wof:placetype":"venue"
},
  "geometry": {"coordinates":[13.3617429733,52.4966659546],"type":"Point"}
}