{
  "type": "Feature",
  "properties": {
    "iso:country":"DE",
    "sg:address":"Heidensche Str. 312",
    "sg:city":"Lage",
    "sg:phone":"+49 5232/2798",
    "sg:postcode":"32791",
    "sg:province":"Nordrhein-Westfalen",
    "wof:name":"Neesenhof",
    "wof:placetype":"venue"
},
  "geometry": {"coordinates":[8.8443231583,51.9800033569],"type":"Point"}
}