{
  "type": "Feature",
  "properties": {
    "iso:country":"DE",
    "sg:address":"Im Kurzst\u00fcck 5",
    "sg:city":"Gorxheimertal",
    "sg:phone":"+49 4962/0122355",
    "sg:postcode":"69517",
    "sg:province":"Hessen",
    "wof:name":"M. Fl\u00d6\u00dfer",
    "wof:placetype":"venue"
},
  "geometry": {"coordinates":[8.735796,49.53289],"type":"Point"}
}