{
  "type": "Feature",
  "properties": {
    "iso:country":"DE",
    "sg:address":"Sperberweg 2 1/2",
    "sg:city":"Augsburg",
    "sg:postcode":"86156",
    "sg:province":"Bayern",
    "wof:name":"4w\u00e4nde Verwaltungs- Gmbh",
    "wof:placetype":"venue"
},
  "geometry": {"coordinates":[10.8979949951,48.3699989319],"type":"Point"}
}