{
  "type": "Feature",
  "properties": {
    "iso:country":"DE",
    "sg:address":"Kirchstr. 9",
    "sg:city":"Blumberg",
    "sg:phone":"+49 7702/41100",
    "sg:postcode":"78176",
    "sg:province":"Baden-W\u00fcrttemberg",
    "wof:name":"Erika Lossau",
    "wof:placetype":"venue"
},
  "geometry": {"coordinates":[8.533294,47.837654],"type":"Point"}
}