{
  "type": "Feature",
  "properties": {
    "iso:country":"DE",
    "sg:address":"Bahnhofstr. 17",
    "sg:city":"Pirna",
    "sg:phone":"+49 3501/446532",
    "sg:postcode":"01796",
    "sg:province":"Sachsen",
    "wof:name":"Olaf Spiegelhauer",
    "wof:placetype":"venue"
},
  "geometry": {"coordinates":[13.933735,50.961147],"type":"Point"}
}