{
  "type": "Feature",
  "properties": {
    "iso:country":"DE",
    "sg:address":"Luigi-Pirandello-Str. 1",
    "sg:city":"Bonn",
    "sg:phone":"+49 228/299077",
    "sg:postcode":"53127",
    "sg:province":"Nordrhein-Westfalen",
    "wof:name":"Dr. Med. Irmgard Schuppert \u00c4rztin F\u00fcr Allgemeinmedizin",
    "wof:placetype":"venue"
},
  "geometry": {"coordinates":[7.0865559578,50.6998901367],"type":"Point"}
}