{
  "type": "Feature",
  "properties": {
    "iso:country":"DE",
    "sg:address":"Hammer Str. 45",
    "sg:city":"Beckum",
    "sg:phone":"+49 2521/18421",
    "sg:postcode":"59269",
    "sg:province":"Nordrhein-Westfalen",
    "wof:name":"Klaus Hengst Heilpraktiker",
    "wof:placetype":"venue"
},
  "geometry": {"coordinates":[8.0271148682,51.751373291],"type":"Point"}
}