{
  "type": "Feature",
  "properties": {
    "iso:country":"DE",
    "sg:address":"Abboweg 19",
    "sg:city":"Dortmund",
    "sg:phone":"+49 231/670529",
    "sg:postcode":"44379",
    "sg:province":"Nordrhein-Westfalen",
    "wof:name":"Data-image Vertriebsges. F\u00fcr Archivierungssysteme Mbh",
    "wof:placetype":"venue"
},
  "geometry": {"coordinates":[7.3720908165,51.5148849487],"type":"Point"}
}