{
  "type": "Feature",
  "properties": {
    "iso:country":"DE",
    "sg:address":"Hamminkelner Str. 10",
    "sg:city":"Hamminkeln",
    "sg:phone":"+49 2856/505",
    "sg:postcode":"46499",
    "sg:province":"Nordrhein-Westfalen",
    "wof:name":"Hans Heinz Elsebrock",
    "wof:placetype":"venue"
},
  "geometry": {"coordinates":[6.678194,51.726437],"type":"Point"}
}