{
  "type": "Feature",
  "properties": {
    "iso:country":"DE",
    "sg:address":"Kirchplatz 1",
    "sg:city":"Ipsheim",
    "sg:phone":"+49 9846/255",
    "sg:postcode":"91472",
    "sg:province":"Bayern",
    "wof:name":"Wilhelm Gohlke",
    "wof:placetype":"venue"
},
  "geometry": {"coordinates":[10.4810285568,49.5265274048],"type":"Point"}
}