{
  "type": "Feature",
  "properties": {
    "iso:country":"DE",
    "sg:address":"Steinm\u00fchle",
    "sg:city":"Mitterteich",
    "sg:phone":"+49 9633/92160",
    "sg:postcode":"95666",
    "sg:province":"Bayern",
    "wof:name":"Amh Asphaltmischwerke Hirschentanz Gmbh",
    "wof:placetype":"venue"
},
  "geometry": {"coordinates":[12.2699975967,49.9765930176],"type":"Point"}
}