{
  "type": "Feature",
  "properties": {
    "iso:country":"DE",
    "sg:address":"Frankenstr. 22",
    "sg:city":"Schwieberdingen",
    "sg:phone":"+49 7150/32765",
    "sg:postcode":"71701",
    "sg:province":"Baden-W\u00fcrttemberg",
    "wof:name":"Sirkka Model Architektin",
    "wof:placetype":"venue"
},
  "geometry": {"coordinates":[9.065851,48.875256],"type":"Point"}
}