{
  "type": "Feature",
  "properties": {
    "iso:country":"DE",
    "sg:address":"Exerzierplatz 34",
    "sg:city":"Kiel",
    "sg:phone":"+49 431/95154",
    "sg:postcode":"24103",
    "sg:province":"Schleswig-Holstein",
    "wof:name":"Komet",
    "wof:placetype":"venue"
},
  "geometry": {"coordinates":[10.1292276382,54.321647644],"type":"Point"}
}