{
  "type": "Feature",
  "properties": {
    "iso:country":"DE",
    "sg:address":"Richtersfeld 3",
    "sg:city":"Dorsten",
    "sg:phone":"+49 2369/8601",
    "sg:postcode":"46286",
    "sg:province":"Nordrhein-Westfalen",
    "wof:name":"Bernhard Feller",
    "wof:placetype":"venue"
},
  "geometry": {"coordinates":[7.0188012123,51.7206764221],"type":"Point"}
}