{
  "type": "Feature",
  "properties": {
    "iso:country":"DE",
    "sg:address":"Grabenstr. 22",
    "sg:city":"Wiesbaden",
    "sg:postcode":"65183",
    "sg:province":"Hessen",
    "wof:name":"Landini & Baumbach Gmbh",
    "wof:placetype":"venue"
},
  "geometry": {"coordinates":[8.240445137,50.0833015442],"type":"Point"}
}