{
  "type": "Feature",
  "properties": {
    "iso:country":"DE",
    "sg:address":"Werkstr. 17",
    "sg:city":"Baden-Baden",
    "sg:postcode":"76532",
    "sg:province":"Baden-W\u00fcrttemberg",
    "wof:name":"Herz-wegerechte E. K.",
    "wof:placetype":"venue"
},
  "geometry": {"coordinates":[8.183628,48.805496],"type":"Point"}
}