{
  "type": "Feature",
  "properties": {
    "iso:country":"DE",
    "sg:address":"Kaiserstr. 17",
    "sg:city":"Wuppertal",
    "sg:phone":"+49 202/780891",
    "sg:postcode":"42329",
    "sg:province":"Nordrhein-Westfalen",
    "wof:name":"Lilly Vom Wege",
    "wof:placetype":"venue"
},
  "geometry": {"coordinates":[7.071789,51.231953],"type":"Point"}
}