{
  "type": "Feature",
  "properties": {
    "iso:country":"DE",
    "sg:address":"Untergasse 17",
    "sg:city":"Homberg",
    "sg:phone":"+49 5681/4768",
    "sg:postcode":"34576",
    "sg:province":"Hessen",
    "wof:name":"Elektromeister Sandm\u00fcller Gmbh",
    "wof:placetype":"venue"
},
  "geometry": {"coordinates":[9.40434,51.033161],"type":"Point"}
}