{
  "type": "Feature",
  "properties": {
    "iso:country":"DE",
    "sg:address":"Gailoh",
    "sg:city":"Amberg",
    "sg:phone":"+49 9621/81091",
    "sg:postcode":"92224",
    "sg:province":"Bayern",
    "wof:name":"Restaurant-pension G\u00f6tz",
    "wof:placetype":"venue"
},
  "geometry": {"coordinates":[11.8418979645,49.439655304],"type":"Point"}
}