{
  "type": "Feature",
  "properties": {
    "iso:country":"DE",
    "sg:address":"Draht 7",
    "sg:city":"Pfaffenhofen",
    "sg:phone":"+49 8441/7500",
    "sg:postcode":"85276",
    "sg:province":"Bayern",
    "wof:name":"Eon Bayern",
    "wof:placetype":"venue"
},
  "geometry": {"coordinates":[11.506581,48.527382],"type":"Point"}
}