{
  "type": "Feature",
  "properties": {
    "iso:country":"DE",
    "sg:address":"Schwarzwaldstr. 8",
    "sg:city":"M\u00fcnchen",
    "sg:phone":"+49 89/91077635",
    "sg:postcode":"81677",
    "sg:province":"Bayern",
    "wof:name":"Varia Jet Reinigungstechnik Gmbh",
    "wof:placetype":"venue"
},
  "geometry": {"coordinates":[11.628701,48.14045],"type":"Point"}
}