{
  "type": "Feature",
  "properties": {
    "iso:country":"DE",
    "sg:address":"Herzebrocker Str. 78",
    "sg:city":"G\u00fctersloh",
    "sg:phone":"+49 5241/25001",
    "sg:postcode":"33330",
    "sg:province":"Nordrhein-Westfalen",
    "wof:name":"Heitmann Architekten",
    "wof:placetype":"venue"
},
  "geometry": {"coordinates":[8.36048,51.903732],"type":"Point"}
}