{
  "type": "Feature",
  "properties": {
    "iso:country":"DE",
    "sg:address":"Essener Str. 4",
    "sg:city":"Hamburg",
    "sg:postcode":"22419",
    "sg:province":"Hamburg",
    "wof:name":"Schroeder Und Krahne Datenverarbeitungs Gmbh",
    "wof:placetype":"venue"
},
  "geometry": {"coordinates":[9.992148,53.666653],"type":"Point"}
}