{
  "type": "Feature",
  "properties": {
    "iso:country":"DE",
    "sg:address":"Im Seefeld 18",
    "sg:city":"Antdorf",
    "sg:phone":"+49 8856/83439",
    "sg:postcode":"82387",
    "sg:province":"Bayern",
    "wof:name":"A. Andrae",
    "wof:placetype":"venue"
},
  "geometry": {"coordinates":[11.307193,47.753063],"type":"Point"}
}