{
  "type": "Feature",
  "properties": {
    "iso:country":"DE",
    "sg:address":"Siemensstr. 25",
    "sg:city":"W\u00f6rth",
    "sg:postcode":"84109",
    "sg:province":"Bayern",
    "wof:name":"Tbw Transportbeton W\u00f6rth/isar Gmbh & Co. Kg",
    "wof:placetype":"venue"
},
  "geometry": {"coordinates":[12.3263196945,48.6264648438],"type":"Point"}
}