{
  "type": "Feature",
  "properties": {
    "iso:country":"DE",
    "sg:address":"Bahnhofstr. 19",
    "sg:city":"Seligenstadt",
    "sg:phone":"+49 6182/3502",
    "sg:postcode":"63500",
    "sg:province":"Hessen",
    "wof:name":"Bahnhof-apotheke",
    "wof:placetype":"venue"
},
  "geometry": {"coordinates":[8.972741,50.042717],"type":"Point"}
}