{
  "type": "Feature",
  "properties": {
    "iso:country":"DE",
    "sg:address":"Hattenbergstr. 10",
    "sg:city":"Mainz",
    "sg:phone":"+49 6131/660",
    "sg:postcode":"55122",
    "sg:province":"Rheinland-Pfalz",
    "wof:name":"Schott Spezialglas Gmbh",
    "wof:placetype":"venue"
},
  "geometry": {"coordinates":[8.2438182831,50.0155906677],"type":"Point"}
}