{
  "type": "Feature",
  "properties": {
    "iso:country":"DE",
    "sg:address":"Wilhelmstr. 10",
    "sg:city":"L\u00fcdenscheid",
    "sg:phone":"+49 2351/919269",
    "sg:postcode":"58511",
    "sg:province":"Nordrhein-Westfalen",
    "wof:name":"Friedhelm Kurz",
    "wof:placetype":"venue"
},
  "geometry": {"coordinates":[7.6304311752,51.2157287598],"type":"Point"}
}