{
  "type": "Feature",
  "properties": {
    "iso:country":"DE",
    "sg:address":"Willibrordstr. 9",
    "sg:city":"Emmerich",
    "sg:phone":"+49 2822/2597",
    "sg:postcode":"46446",
    "sg:province":"Nordrhein-Westfalen",
    "wof:name":"B. Und D. Resse Masseur",
    "wof:placetype":"venue"
},
  "geometry": {"coordinates":[6.240098,51.832775],"type":"Point"}
}