{
  "type": "Feature",
  "properties": {
    "iso:country":"DE",
    "sg:address":"Neubr\u00fccker Weg 8",
    "sg:city":"Babenhausen",
    "sg:phone":"+49 6073/3461",
    "sg:postcode":"64832",
    "sg:province":"Hessen",
    "wof:name":"Heinrich Truber Architekt",
    "wof:placetype":"venue"
},
  "geometry": {"coordinates":[8.956665,49.960331],"type":"Point"}
}