{
  "type": "Feature",
  "properties": {
    "iso:country":"DE",
    "sg:address":"In der Hagenbeck 30",
    "sg:city":"Essen",
    "sg:phone":"+49 201/622930",
    "sg:postcode":"45143",
    "sg:province":"Nordrhein-Westfalen",
    "wof:name":"Wolfgang Schramm Jun.",
    "wof:placetype":"venue"
},
  "geometry": {"coordinates":[6.971077,51.45697],"type":"Point"}
}