{
  "type": "Feature",
  "properties": {
    "iso:country":"DE",
    "sg:address":"P\u00f6ttmeser Str. 6",
    "sg:city":"Schrobenhausen",
    "sg:postcode":"86529",
    "sg:province":"Bayern",
    "wof:name":"Matratzen Insel Gmbh",
    "wof:placetype":"venue"
},
  "geometry": {"coordinates":[11.2584638596,48.5623931885],"type":"Point"}
}