{
  "type": "Feature",
  "properties": {
    "iso:country":"DE",
    "sg:address":"Liegensberg 9",
    "sg:city":"Dippach",
    "sg:postcode":"99837",
    "sg:province":"Th\u00fcringen",
    "wof:name":"Scholl Bau Gmbh",
    "wof:placetype":"venue"
},
  "geometry": {"coordinates":[10.0465202332,50.9185829163],"type":"Point"}
}