{
  "type": "Feature",
  "properties": {
    "iso:country":"DE",
    "sg:address":"Lyckallee 6",
    "sg:city":"Berlin",
    "sg:phone":"+49 30/3042554",
    "sg:postcode":"14055",
    "sg:province":"Berlin",
    "wof:name":"Splitt-fennert Seniorenheim",
    "wof:placetype":"venue"
},
  "geometry": {"coordinates":[13.253839,52.506542],"type":"Point"}
}