{
  "type": "Feature",
  "properties": {
    "iso:country":"DE",
    "sg:address":"Schramberger Weg 16",
    "sg:city":"Aichhalden",
    "sg:phone":"+49 7422/54800",
    "sg:postcode":"78733",
    "sg:province":"Baden-W\u00fcrttemberg",
    "wof:name":"D. Broghammer",
    "wof:placetype":"venue"
},
  "geometry": {"coordinates":[8.4009571075,48.2670326233],"type":"Point"}
}