{
  "type": "Feature",
  "properties": {
    "iso:country":"DE",
    "sg:address":"Garagenweg 5",
    "sg:city":"Bubenreuth",
    "sg:phone":"+49 9131/28071",
    "sg:postcode":"91088",
    "sg:province":"Bayern",
    "wof:name":"T-shirt Quick-press Gmbh",
    "wof:placetype":"venue"
},
  "geometry": {"coordinates":[11.0073194504,49.6185493469],"type":"Point"}
}