{
  "type": "Feature",
  "properties": {
    "iso:country":"DE",
    "sg:address":"Bentheimer Str. 17",
    "sg:city":"Nordhorn",
    "sg:phone":"+49 5921/3244",
    "sg:postcode":"48529",
    "sg:province":"Niedersachsen",
    "wof:name":"H. Bardenhorst",
    "wof:placetype":"venue"
},
  "geometry": {"coordinates":[7.0695009232,52.4328613281],"type":"Point"}
}