{
  "type": "Feature",
  "properties": {
    "iso:country":"DE",
    "sg:address":"Wittelsbacherring 40",
    "sg:city":"Bayreuth",
    "sg:phone":"+49 921/52543",
    "sg:postcode":"95444",
    "sg:province":"Bayern",
    "wof:name":"Gram\u00df Gmbh",
    "wof:placetype":"venue"
},
  "geometry": {"coordinates":[11.573234,49.938931],"type":"Point"}
}