{
  "type": "Feature",
  "properties": {
    "iso:country":"DE",
    "sg:address":"Hahnenweiler 26",
    "sg:city":"Merklingen",
    "sg:phone":"+49 7337/6534",
    "sg:postcode":"89188",
    "sg:province":"Baden-W\u00fcrttemberg",
    "wof:name":"Georg Fink",
    "wof:placetype":"venue"
},
  "geometry": {"coordinates":[9.755568,48.509521],"type":"Point"}
}