{
  "type": "Feature",
  "properties": {
    "iso:country":"DE",
    "sg:address":"Storndorfer Str. 27",
    "sg:city":"Lautertal",
    "sg:phone":"+49 6630/240",
    "sg:postcode":"36369",
    "sg:province":"Hessen",
    "wof:name":"Edmund Trapp",
    "wof:placetype":"venue"
},
  "geometry": {"coordinates":[9.254386,50.625885],"type":"Point"}
}