{
  "type": "Feature",
  "properties": {
    "iso:country":"DE",
    "sg:address":"Marktplatz 15",
    "sg:city":"Gerolzhofen",
    "sg:phone":"+49 9382/1591",
    "sg:postcode":"97447",
    "sg:province":"Bayern",
    "wof:name":"Baby Fachmarkt",
    "wof:placetype":"venue"
},
  "geometry": {"coordinates":[10.3499555588,49.9009819031],"type":"Point"}
}