{
  "type": "Feature",
  "properties": {
    "iso:country":"DE",
    "sg:address":"Bahnhofstr. 49",
    "sg:city":"Eggolsheim",
    "sg:phone":"+49 9545/8750",
    "sg:postcode":"91330",
    "sg:province":"Bayern",
    "wof:name":"Alge-reisen Inh. Alfred Geisler",
    "wof:placetype":"venue"
},
  "geometry": {"coordinates":[11.0492801666,49.7711181641],"type":"Point"}
}