{
  "type": "Feature",
  "properties": {
    "iso:country":"DE",
    "sg:address":"Markt 41",
    "sg:city":"Altenburg",
    "sg:phone":"+49 3447/315111",
    "sg:postcode":"04600",
    "sg:province":"Th\u00fcringen",
    "wof:name":"Reise Welt Europ\u00e4isches Reiseb\u00fcro Gmbh",
    "wof:placetype":"venue"
},
  "geometry": {"coordinates":[12.4327316284,50.9851760864],"type":"Point"}
}