{
  "type": "Feature",
  "properties": {
    "iso:country":"DE",
    "sg:address":"Th\u00fcringer Str. 4",
    "sg:city":"Eschwege",
    "sg:phone":"+49 5651/80350",
    "sg:postcode":"37269",
    "sg:province":"Hessen",
    "wof:name":"Klatt Stahlbau Und Schlosserei Gmbh",
    "wof:placetype":"venue"
},
  "geometry": {"coordinates":[10.016997,51.200718],"type":"Point"}
}