{
  "type": "Feature",
  "properties": {
    "iso:country":"DE",
    "sg:address":"Friedrich-Spee-Str. 2",
    "sg:city":"W\u00fcrzburg",
    "sg:phone":"+49 931/7840540",
    "sg:postcode":"97072",
    "sg:province":"Bayern",
    "wof:name":"Bl\u00fctenform P. Hogenkamp E. K.",
    "wof:placetype":"venue"
},
  "geometry": {"coordinates":[9.935065,49.781467],"type":"Point"}
}