{
  "type": "Feature",
  "properties": {
    "iso:country":"DE",
    "sg:address":"Schattweg 45",
    "sg:city":"Kamen",
    "sg:phone":"+49 2307/43918",
    "sg:postcode":"59174",
    "sg:province":"Nordrhein-Westfalen",
    "wof:name":"Senioren Tagesbetreuung Born",
    "wof:placetype":"venue"
},
  "geometry": {"coordinates":[7.70436,51.576488],"type":"Point"}
}