{
  "type": "Feature",
  "properties": {
    "iso:country":"DE",
    "sg:address":"R\u00f6ntgenstr. 15",
    "sg:city":"\u00d6hringen",
    "sg:phone":"+49 7941/7312",
    "sg:postcode":"74613",
    "sg:province":"Baden-W\u00fcrttemberg",
    "wof:name":"Flexibella-bettsysteme H. Kaiser",
    "wof:placetype":"venue"
},
  "geometry": {"coordinates":[9.5090246201,49.1926269531],"type":"Point"}
}