{
  "type": "Feature",
  "properties": {
    "iso:country":"DE",
    "sg:address":"Gaertnerstr. 1",
    "sg:city":"Magdeburg",
    "sg:postcode":"39104",
    "sg:province":"Sachsen-Anhalt",
    "wof:name":"Turnerklause",
    "wof:placetype":"venue"
},
  "geometry": {"coordinates":[11.6394386292,52.1079101562],"type":"Point"}
}