{
  "type": "Feature",
  "properties": {
    "iso:country":"DE",
    "sg:address":"Enslinstr. 14",
    "sg:city":"Sulz",
    "sg:phone":"+49 7454/3507",
    "sg:postcode":"72172",
    "sg:province":"Baden-W\u00fcrttemberg",
    "wof:name":"W. Haitzmann",
    "wof:placetype":"venue"
},
  "geometry": {"coordinates":[8.579939,48.385494],"type":"Point"}
}