{
  "type": "Feature",
  "properties": {
    "iso:country":"DE",
    "sg:address":"Sattlerweg 8",
    "sg:city":"Bergisch Gladbach",
    "sg:phone":"+49 2204/917143",
    "sg:postcode":"51429",
    "sg:province":"Nordrhein-Westfalen",
    "wof:name":"Rewe Wintgens Ohg",
    "wof:placetype":"venue"
},
  "geometry": {"coordinates":[7.1628470421,50.9659156799],"type":"Point"}
}