{
  "type": "Feature",
  "properties": {
    "iso:country":"DE",
    "sg:address":"Kiefernweg 1",
    "sg:city":"Witten",
    "sg:phone":"+49 2302/31588",
    "sg:postcode":"58452",
    "sg:province":"Nordrhein-Westfalen",
    "wof:name":"Ulrich Trommel Gmbh",
    "wof:placetype":"venue"
},
  "geometry": {"coordinates":[7.33244,51.424522],"type":"Point"}
}