{
  "type": "Feature",
  "properties": {
    "iso:country":"DE",
    "sg:address":"Hermannstr. 15",
    "sg:city":"Frankfurt",
    "sg:postcode":"60318",
    "sg:province":"Hessen",
    "wof:name":"3 G Gesellschaft F\u00fcr Geb\u00e4ude- Management- Und Geb\u00e4ude-",
    "wof:placetype":"venue"
},
  "geometry": {"coordinates":[8.6847162247,50.1228523254],"type":"Point"}
}