{
  "type": "Feature",
  "properties": {
    "iso:country":"DE",
    "sg:address":"Artur-Ladebeck-Str. 115",
    "sg:city":"Bielefeld",
    "sg:phone":"+49 521/9146091",
    "sg:postcode":"33647",
    "sg:province":"Nordrhein-Westfalen",
    "wof:name":"Norbert Trosien",
    "wof:placetype":"venue"
},
  "geometry": {"coordinates":[8.511472702,52.0060272217],"type":"Point"}
}