{
  "type": "Feature",
  "properties": {
    "iso:country":"DE",
    "sg:address":"Hirschhorner Str. 21",
    "sg:city":"Neckarsteinach",
    "sg:phone":"+49 6229/7090",
    "sg:postcode":"69239",
    "sg:province":"Hessen",
    "wof:name":"Neckar-reederei Gmbh",
    "wof:placetype":"venue"
},
  "geometry": {"coordinates":[8.843951,49.400379],"type":"Point"}
}