{
  "type": "Feature",
  "properties": {
    "iso:country":"DE",
    "sg:address":"Hauptstr. 19",
    "sg:city":"Irrhausen",
    "sg:phone":"+49 6550/1512",
    "sg:postcode":"54689",
    "sg:province":"Rheinland-Pfalz",
    "wof:name":"P. Schr\u00f6der",
    "wof:placetype":"venue"
},
  "geometry": {"coordinates":[6.21175,50.080124],"type":"Point"}
}