{
  "type": "Feature",
  "properties": {
    "iso:country":"DE",
    "sg:address":"Siebengebirgsweg 16",
    "sg:city":"Remagen",
    "sg:phone":"+49 2228/7446",
    "sg:postcode":"53424",
    "sg:province":"Rheinland-Pfalz",
    "wof:name":"Dr. Med. Martha Sch\u00fctte \u00c4rztin F\u00fcr Hom\u00f6opathie",
    "wof:placetype":"venue"
},
  "geometry": {"coordinates":[7.2050170898,50.6084594727],"type":"Point"}
}