{
  "type": "Feature",
  "properties": {
    "iso:country":"DE",
    "sg:address":"Detwang 28",
    "sg:city":"Rothenburg",
    "sg:phone":"+49 9861/3177",
    "sg:postcode":"91541",
    "sg:province":"Bayern",
    "wof:name":"Campingplatz Tauber-idyll Campingplatz",
    "wof:placetype":"venue"
},
  "geometry": {"coordinates":[10.166809,49.387733],"type":"Point"}
}