{
  "type": "Feature",
  "properties": {
    "iso:country":"DE",
    "sg:address":"Frenzer Driesch 18",
    "sg:city":"Inden",
    "sg:phone":"+49 2423/2426",
    "sg:postcode":"52459",
    "sg:province":"Nordrhein-Westfalen",
    "wof:name":"E. Himpler",
    "wof:placetype":"venue"
},
  "geometry": {"coordinates":[6.345673,50.838398],"type":"Point"}
}