{
  "type": "Feature",
  "properties": {
    "iso:country":"DE",
    "sg:address":"Bahnhofstr. 39",
    "sg:city":"Oerlenbach",
    "sg:phone":"+49 9725/9044",
    "sg:postcode":"97714",
    "sg:province":"Bayern",
    "wof:name":"Pizzeria Gretsistas",
    "wof:placetype":"venue"
},
  "geometry": {"coordinates":[10.1346817017,50.1334495544],"type":"Point"}
}