{
  "type": "Feature",
  "properties": {
    "iso:country":"DE",
    "sg:address":"Bezirksstr. 23",
    "sg:city":"Alzenau",
    "sg:phone":"+49 6023/1216",
    "sg:postcode":"63755",
    "sg:province":"Bayern",
    "wof:name":"Kath. Pfarramt St. Katharina",
    "wof:placetype":"venue"
},
  "geometry": {"coordinates":[9.0739345551,50.0704498291],"type":"Point"}
}