{
  "type": "Feature",
  "properties": {
    "iso:country":"DE",
    "sg:address":"Scherenbergstr. 5",
    "sg:city":"Gem\u00fcnden",
    "sg:phone":"+49 9351/80010",
    "sg:postcode":"97737",
    "sg:province":"Bayern",
    "wof:name":"Stadtarchiv",
    "wof:placetype":"venue"
},
  "geometry": {"coordinates":[9.689326,50.056332],"type":"Point"}
}