{
  "type": "Feature",
  "properties": {
    "iso:country":"DE",
    "sg:address":"Gro\u00dfe Str. 107",
    "sg:city":"Vechta",
    "sg:phone":"+49 4441/2333",
    "sg:postcode":"49377",
    "sg:province":"Niedersachsen",
    "wof:name":"K. J. Ellendorff",
    "wof:placetype":"venue"
},
  "geometry": {"coordinates":[8.2884788513,52.7302513123],"type":"Point"}
}