{
  "type": "Feature",
  "properties": {
    "iso:country":"DE",
    "sg:address":"Klosterstr. 49",
    "sg:city":"Kiel",
    "sg:postcode":"24148",
    "sg:province":"Schleswig-Holstein",
    "wof:name":"Maricom Technische Dienste Gmbh",
    "wof:placetype":"venue"
},
  "geometry": {"coordinates":[10.1636924744,54.3152885437],"type":"Point"}
}