{
  "type": "Feature",
  "properties": {
    "iso:country":"DE",
    "sg:address":"Ausschl\u00e4ger All. 185",
    "sg:city":"Hamburg",
    "sg:phone":"+49 4935/4627420",
    "sg:postcode":"20539",
    "sg:province":"Hamburg",
    "wof:name":"Estrichbau Orbanz Undlorenz Gmbh",
    "wof:placetype":"venue"
},
  "geometry": {"coordinates":[14.009641,51.94046],"type":"Point"}
}