{
  "type": "Feature",
  "properties": {
    "iso:country":"DE",
    "sg:address":"Hauptstr. 90",
    "sg:city":"Fr\u00f6ndenberg",
    "sg:phone":"+49 2378/2510",
    "sg:postcode":"58730",
    "sg:province":"Nordrhein-Westfalen",
    "wof:name":"Volksbank Unna Eg",
    "wof:placetype":"venue"
},
  "geometry": {"coordinates":[7.691791,51.479015],"type":"Point"}
}