{
  "type": "Feature",
  "properties": {
    "iso:country":"DE",
    "sg:address":"Carl-Benz-Str 3",
    "sg:city":"Stutensee",
    "sg:phone":"+49 7249/95490",
    "sg:postcode":"76297",
    "sg:province":"Baden-W\u00fcrttemberg",
    "wof:name":"Ks Marketing Gbr",
    "wof:placetype":"venue"
},
  "geometry": {"coordinates":[8.507093,49.122353],"type":"Point"}
}