{
  "type": "Feature",
  "properties": {
    "iso:country":"DE",
    "sg:address":"Halberst\u00e4dter Str. 37",
    "sg:city":"Oschersleben",
    "sg:phone":"+49 3949/3215",
    "sg:postcode":"39387",
    "sg:province":"Sachsen-Anhalt",
    "wof:name":"Dieter Engelhardt",
    "wof:placetype":"venue"
},
  "geometry": {"coordinates":[11.2266979218,52.0247421265],"type":"Point"}
}