{
  "type": "Feature",
  "properties": {
    "iso:country":"DE",
    "sg:address":"Bahnhofstr.",
    "sg:city":"Schifferstadt",
    "sg:phone":"+49 6235/3120",
    "sg:postcode":"67105",
    "sg:province":"Rheinland-Pfalz",
    "wof:name":"Dachbau Spatz Happes Und Partner Gmbh",
    "wof:placetype":"venue"
},
  "geometry": {"coordinates":[8.373823,49.388309],"type":"Point"}
}