{
  "type": "Feature",
  "properties": {
    "iso:country":"DE",
    "sg:address":"Hauptstr. 28",
    "sg:city":"Wattendorf",
    "sg:phone":"+49 9504/207",
    "sg:postcode":"96196",
    "sg:province":"Bayern",
    "wof:name":"Johannes H\u00fcbner",
    "wof:placetype":"venue"
},
  "geometry": {"coordinates":[11.126281,50.032478],"type":"Point"}
}