{
  "type": "Feature",
  "properties": {
    "iso:country":"DE",
    "sg:address":"Uferstr. 21",
    "sg:city":"Bomlitz",
    "sg:phone":"+49 5161/4005",
    "sg:postcode":"29699",
    "sg:province":"Niedersachsen",
    "wof:name":"G. Und F. Walking",
    "wof:placetype":"venue"
},
  "geometry": {"coordinates":[9.62579,52.911129],"type":"Point"}
}