{
  "type": "Feature",
  "properties": {
    "iso:country":"DE",
    "sg:address":"Hinter den H\u00f6fen 28",
    "sg:city":"Bad Nenndorf",
    "sg:phone":"+49 5723/3633",
    "sg:postcode":"31542",
    "sg:province":"Niedersachsen",
    "wof:name":"Kappers Luft- Und Schall- D\u00e4mmtechnik Gmbh",
    "wof:placetype":"venue"
},
  "geometry": {"coordinates":[9.37113,52.327412],"type":"Point"}
}