{
  "type": "Feature",
  "properties": {
    "iso:country":"DE",
    "sg:address":"Im Simmerling 46",
    "sg:city":"Bingen",
    "sg:postcode":"55411",
    "sg:province":"Rheinland-Pfalz",
    "wof:name":"Artifex Bautr\u00e4ger Gmbh",
    "wof:placetype":"venue"
},
  "geometry": {"coordinates":[7.92481,49.919056],"type":"Point"}
}