{
  "type": "Feature",
  "properties": {
    "iso:country":"DE",
    "sg:address":"Ligsalzstr. 5",
    "sg:city":"M\u00fcnchen",
    "sg:postcode":"80339",
    "sg:province":"Bayern",
    "wof:name":"Staatliche Antikensammlung",
    "wof:placetype":"venue"
},
  "geometry": {"coordinates":[11.542426,48.137585],"type":"Point"}
}