{
  "type": "Feature",
  "properties": {
    "iso:country":"DE",
    "sg:address":"Immelmannstr. 13",
    "sg:city":"Bad Windsheim",
    "sg:phone":"+49 9841/2356",
    "sg:postcode":"91438",
    "sg:province":"Bayern",
    "wof:name":"Erika Theimer",
    "wof:placetype":"venue"
},
  "geometry": {"coordinates":[10.4072237015,49.5033454895],"type":"Point"}
}