{
  "type": "Feature",
  "properties": {
    "iso:country":"DE",
    "sg:address":"Bonfelder Str. 58",
    "sg:city":"Heilbronn",
    "sg:phone":"+49 7066/1219",
    "sg:postcode":"74078",
    "sg:province":"Baden-W\u00fcrttemberg",
    "wof:name":"G\u00fcnter R\u00fcdiger Elektromeister",
    "wof:placetype":"venue"
},
  "geometry": {"coordinates":[9.138688,49.197346],"type":"Point"}
}