{
  "type": "Feature",
  "properties": {
    "iso:country":"DE",
    "sg:address":"Hauptstr. 2",
    "sg:city":"Stadtlauringen",
    "sg:phone":"+49 9724/91220",
    "sg:postcode":"97488",
    "sg:province":"Bayern",
    "wof:name":"Karlheinz Albert Gmbh",
    "wof:placetype":"venue"
},
  "geometry": {"coordinates":[10.360534668,50.1875457764],"type":"Point"}
}