{
  "type": "Feature",
  "properties": {
    "iso:country":"DE",
    "sg:address":"Daimlerstr. 3",
    "sg:city":"Stadtbergen",
    "sg:postcode":"86391",
    "sg:province":"Bayern",
    "wof:name":"Orthop\u00e4die-technik Sanit\u00e4tshaus",
    "wof:placetype":"venue"
},
  "geometry": {"coordinates":[10.8415088654,48.3773536682],"type":"Point"}
}