{
  "type": "Feature",
  "properties": {
    "iso:country":"DE",
    "sg:address":"Miltenberg",
    "sg:city":"Miltenberg",
    "sg:phone":"+49 9371/4810",
    "sg:postcode":"63897",
    "sg:province":"Bayern",
    "wof:name":"Raiffeisenbank B\u00fcrgstadt-collenberg, Eg",
    "wof:placetype":"venue"
},
  "geometry": {"coordinates":[9.24662,49.69051],"type":"Point"}
}