{
  "type": "Feature",
  "properties": {
    "iso:country":"DE",
    "sg:address":"Turmgasse 7",
    "sg:city":"Dinkelsb\u00fchl",
    "sg:phone":"+49 9851/2636",
    "sg:postcode":"91550",
    "sg:province":"Bayern",
    "wof:name":"Ute Stirn",
    "wof:placetype":"venue"
},
  "geometry": {"coordinates":[10.319232,49.068344],"type":"Point"}
}