{
  "type": "Feature",
  "properties": {
    "iso:country":"DE",
    "sg:address":"Siemensstr 19",
    "sg:city":"Schwalmtal",
    "sg:phone":"+49 2163/10055",
    "sg:postcode":"41366",
    "sg:province":"Nordrhein-Westfalen",
    "wof:name":"Metallbau Fuchs Gmbh",
    "wof:placetype":"venue"
},
  "geometry": {"coordinates":[6.246982,51.238129],"type":"Point"}
}