{
  "type": "Feature",
  "properties": {
    "iso:country":"DE",
    "sg:address":"K\u00f6lner Str. 35",
    "sg:city":"Wesseling",
    "sg:phone":"+49 2236/943120",
    "sg:postcode":"50389",
    "sg:province":"Nordrhein-Westfalen",
    "wof:name":"Armin Hecker",
    "wof:placetype":"venue"
},
  "geometry": {"coordinates":[6.981283,50.827415],"type":"Point"}
}