{
  "type": "Feature",
  "properties": {
    "iso:country":"DE",
    "sg:address":"Heerstr. 49",
    "sg:city":"Westerkappeln",
    "sg:phone":"+49 5404/9579270",
    "sg:postcode":"49492",
    "sg:province":"Nordrhein-Westfalen",
    "wof:name":"Plant Science Services Gmbh",
    "wof:placetype":"venue"
},
  "geometry": {"coordinates":[7.8483610153,52.3251037598],"type":"Point"}
}