{
  "type": "Feature",
  "properties": {
    "iso:country":"DE",
    "sg:address":"Herrenstr. 45",
    "sg:city":"Freiburg",
    "sg:phone":"+49 761/35143",
    "sg:postcode":"79098",
    "sg:province":"Baden-W\u00fcrttemberg",
    "wof:name":"Emil Meyer Gmbh",
    "wof:placetype":"venue"
},
  "geometry": {"coordinates":[7.854038,47.994221],"type":"Point"}
}