{
  "type": "Feature",
  "properties": {
    "iso:country":"DE",
    "sg:address":"Schwaiberger Str. 2",
    "sg:city":"Tiefenbach",
    "sg:phone":"+49 8509/1253",
    "sg:postcode":"94113",
    "sg:province":"Bayern",
    "wof:name":"Gasthaus Bauer",
    "wof:placetype":"venue"
},
  "geometry": {"coordinates":[13.4149465561,48.6231040955],"type":"Point"}
}