{
  "type": "Feature",
  "properties": {
    "iso:country":"DE",
    "sg:address":"August-Hornung-Str. 17",
    "sg:city":"Heilbronn",
    "sg:phone":"+49 7131/31731",
    "sg:postcode":"74080",
    "sg:province":"Baden-W\u00fcrttemberg",
    "wof:name":"Gerhard Mogler Architekt",
    "wof:placetype":"venue"
},
  "geometry": {"coordinates":[9.188419,49.137878],"type":"Point"}
}