{
  "type": "Feature",
  "properties": {
    "iso:country":"DE",
    "sg:address":"Sperlingsberg 3",
    "sg:city":"Zepkow",
    "sg:phone":"+49 39925/2390",
    "sg:postcode":"17209",
    "sg:province":"Mecklenburg-Vorpommern",
    "wof:name":"M. Marx",
    "wof:placetype":"venue"
},
  "geometry": {"coordinates":[12.486788,53.305798],"type":"Point"}
}