{
  "type": "Feature",
  "properties": {
    "iso:country":"DE",
    "sg:address":"Hauptstr. 36",
    "sg:city":"Wietmarschen",
    "sg:phone":"+49 5908/92020",
    "sg:postcode":"49835",
    "sg:province":"Niedersachsen",
    "wof:name":"Wassermann Und Alte Rechtsanw\u00e4lte",
    "wof:placetype":"venue"
},
  "geometry": {"coordinates":[7.2278442383,52.4922180176],"type":"Point"}
}