{
  "type": "Feature",
  "properties": {
    "iso:country":"DE",
    "sg:address":"Kronenstr. 63-69",
    "sg:city":"Dortmund",
    "sg:phone":"+49 231/54830",
    "sg:postcode":"44139",
    "sg:province":"Nordrhein-Westfalen",
    "wof:name":"Aw-versorgungsges. Mbh",
    "wof:placetype":"venue"
},
  "geometry": {"coordinates":[7.477259,51.501484],"type":"Point"}
}