{
  "type": "Feature",
  "properties": {
    "iso:country":"DE",
    "sg:address":"Bistard 12",
    "sg:city":"Viersen",
    "sg:phone":"+49 2162/40956",
    "sg:postcode":"41751",
    "sg:province":"Nordrhein-Westfalen",
    "wof:name":"H. Gersdorff",
    "wof:placetype":"venue"
},
  "geometry": {"coordinates":[6.33432,51.276089],"type":"Point"}
}