{
  "type": "Feature",
  "properties": {
    "iso:country":"DE",
    "sg:address":"Mertinger Str. 2",
    "sg:city":"Oberndorf",
    "sg:phone":"+49 9022/2685",
    "sg:postcode":"86698",
    "sg:province":"Bayern",
    "wof:name":"Heimatmmuseum Oberndorf",
    "wof:placetype":"venue"
},
  "geometry": {"coordinates":[10.872908,48.669033],"type":"Point"}
}