{
  "type": "Feature",
  "properties": {
    "iso:country":"DE",
    "sg:address":"Rupprechtstr. 6",
    "sg:city":"Erding",
    "sg:phone":"+49 8122/2906",
    "sg:postcode":"85435",
    "sg:province":"Bayern",
    "wof:name":"Einbergersche-apotheke",
    "wof:placetype":"venue"
},
  "geometry": {"coordinates":[11.899152,48.307022],"type":"Point"}
}