{
  "type": "Feature",
  "properties": {
    "iso:country":"DE",
    "sg:address":"Wrangelstr. 69c",
    "sg:city":"Hamburg",
    "sg:phone":"+49 40/42936670",
    "sg:postcode":"20253",
    "sg:province":"Hamburg",
    "wof:name":"Spectris Messtechnik Gmbh",
    "wof:placetype":"venue"
},
  "geometry": {"coordinates":[9.968825,53.581394],"type":"Point"}
}