{
  "type": "Feature",
  "properties": {
    "iso:country":"DE",
    "sg:address":"Dornierstr. 17",
    "sg:city":"Stuttgart",
    "sg:phone":"+49 711/85998180",
    "sg:postcode":"70469",
    "sg:province":"Baden-W\u00fcrttemberg",
    "wof:name":"Seitenblick Interaktive Medien Gmbh",
    "wof:placetype":"venue"
},
  "geometry": {"coordinates":[9.1756391525,48.8124237061],"type":"Point"}
}