{
  "type": "Feature",
  "properties": {
    "iso:country":"DE",
    "sg:address":"Gutenbergstr. 1",
    "sg:city":"Garrel",
    "sg:phone":"+49 4474/94980",
    "sg:postcode":"49681",
    "sg:province":"Niedersachsen",
    "wof:name":"Wist & Laumann Offsetdruck Gmbh",
    "wof:placetype":"venue"
},
  "geometry": {"coordinates":[8.029685,52.948105],"type":"Point"}
}