{
  "type": "Feature",
  "properties": {
    "iso:country":"DE",
    "sg:address":"Am Markt 2",
    "sg:city":"Gl\u00fcckstadt",
    "sg:phone":"+49 4124/3636",
    "sg:postcode":"25348",
    "sg:province":"Schleswig-Holstein",
    "wof:name":"Restaurant Der Kleine Heinrich Gmbh",
    "wof:placetype":"venue"
},
  "geometry": {"coordinates":[9.423330307,53.7882652283],"type":"Point"}
}