{
  "type": "Feature",
  "properties": {
    "iso:country":"DE",
    "sg:address":"Gartenstr. 10",
    "sg:city":"Pennewitz",
    "sg:postcode":"98708",
    "sg:province":"Th\u00fcringen",
    "wof:name":"Eiscafe Ellisabetha Moeller",
    "wof:placetype":"venue"
},
  "geometry": {"coordinates":[11.054297,50.661526],"type":"Point"}
}