{
  "type": "Feature",
  "properties": {
    "iso:country":"DE",
    "sg:address":"Dr\u00f6mlingsstr. 71",
    "sg:city":"Oebisfelde",
    "sg:phone":"+49 39002/2356",
    "sg:postcode":"39646",
    "sg:province":"Sachsen-Anhalt",
    "wof:name":"Dr\u00f6mlingsklause",
    "wof:placetype":"venue"
},
  "geometry": {"coordinates":[11.0252790451,52.4419975281],"type":"Point"}
}