{
  "type": "Feature",
  "properties": {
    "iso:country":"DE",
    "sg:address":"Rothenberger Str. 31",
    "sg:city":"Hilchenbach",
    "sg:phone":"+49 2733/4841",
    "sg:postcode":"57271",
    "sg:province":"Nordrhein-Westfalen",
    "wof:name":"Karl-georg Dreisbach",
    "wof:placetype":"venue"
},
  "geometry": {"coordinates":[8.106352,50.997307],"type":"Point"}
}