{
  "type": "Feature",
  "properties": {
    "iso:country":"DE",
    "sg:address":"Barbarossastr. 51",
    "sg:city":"Esslingen",
    "sg:phone":"+49 711/378590",
    "sg:postcode":"73732",
    "sg:province":"Baden-W\u00fcrttemberg",
    "wof:name":"Kath. Pfarramt St. Joseph",
    "wof:placetype":"venue"
},
  "geometry": {"coordinates":[9.3108243942,48.7545814514],"type":"Point"}
}