{
  "type": "Feature",
  "properties": {
    "iso:country":"DE",
    "sg:address":"Sickenreuther Str. 39",
    "sg:city":"Goldkronach",
    "sg:phone":"+49 9273/8512",
    "sg:postcode":"95497",
    "sg:province":"Bayern",
    "wof:name":"Trend Line Sonnenschutztechnik Gmbh",
    "wof:placetype":"venue"
},
  "geometry": {"coordinates":[11.6954,50.007095],"type":"Point"}
}