{
  "type": "Feature",
  "properties": {
    "iso:country":"DE",
    "sg:address":"M\u00fchlbergsweg 24a",
    "sg:city":"Reinholterode",
    "sg:phone":"+49 36085/40467",
    "sg:postcode":"37308",
    "sg:province":"Th\u00fcringen",
    "wof:name":"Internetl\u00f6sungen F\u00fcr Ihren Werbeauftritt",
    "wof:placetype":"venue"
},
  "geometry": {"coordinates":[10.1944761276,51.4212608337],"type":"Point"}
}