{
  "type": "Feature",
  "properties": {
    "iso:country":"DE",
    "sg:address":"Graf-Kirchberg-Str. 66",
    "sg:city":"Illertissen",
    "sg:phone":"+49 7303/903034",
    "sg:postcode":"89257",
    "sg:province":"Bayern",
    "wof:name":"Wtp Werkstoff-technologie Und Produktion Gmbh",
    "wof:placetype":"venue"
},
  "geometry": {"coordinates":[10.1198959351,48.246509552],"type":"Point"}
}