{
  "type": "Feature",
  "properties": {
    "iso:country":"DE",
    "sg:address":"Hauptstr. 209",
    "sg:city":"Briedel",
    "sg:phone":"+49 6542/4780",
    "sg:postcode":"56867",
    "sg:province":"Rheinland-Pfalz",
    "wof:name":"Hubertus Kroth",
    "wof:placetype":"venue"
},
  "geometry": {"coordinates":[7.1465449333,50.0276298523],"type":"Point"}
}