{
  "type": "Feature",
  "properties": {
    "iso:country":"DE",
    "sg:address":"Ludwig-Schlepper-Str. 1",
    "sg:city":"Bad M\u00fcnder",
    "sg:phone":"+49 5042/81268",
    "sg:postcode":"31848",
    "sg:province":"Niedersachsen",
    "wof:name":"Medtech Medizinische Technologie Gmbh",
    "wof:placetype":"venue"
},
  "geometry": {"coordinates":[9.441399,52.259018],"type":"Point"}
}