{
  "type": "Feature",
  "properties": {
    "iso:country":"DE",
    "sg:address":"Landshuter Str. 26",
    "sg:city":"Unterschlei\u00dfheim",
    "sg:phone":"+49 89/31772656",
    "sg:postcode":"85716",
    "sg:province":"Bayern",
    "wof:name":"Euromeads Air Defence Systems Beteiligungs Gmbh",
    "wof:placetype":"venue"
},
  "geometry": {"coordinates":[11.561784,48.275414],"type":"Point"}
}