{
  "type": "Feature",
  "properties": {
    "iso:country":"DE",
    "sg:address":"Bussardweg 18 A",
    "sg:city":"Wedemark",
    "sg:phone":"+49 5130/79538",
    "sg:postcode":"30900",
    "sg:province":"Niedersachsen",
    "wof:name":"Peter Koschmieder Anlageberater",
    "wof:placetype":"venue"
},
  "geometry": {"coordinates":[9.7949371338,52.5162811279],"type":"Point"}
}