{
  "type": "Feature",
  "properties": {
    "iso:country":"DE",
    "sg:address":"Virchowstr. 21",
    "sg:city":"Gelsenkirchen",
    "sg:phone":"+49 209/140603",
    "sg:postcode":"45886",
    "sg:province":"Nordrhein-Westfalen",
    "wof:name":"Herlemann",
    "wof:placetype":"venue"
},
  "geometry": {"coordinates":[7.119316,51.498058],"type":"Point"}
}