{
  "type": "Feature",
  "properties": {
    "iso:country":"DE",
    "sg:address":"Allensteiner Str. 32",
    "sg:city":"Wuppertal",
    "sg:phone":"+49 202/521007",
    "sg:postcode":"42277",
    "sg:province":"Nordrhein-Westfalen",
    "wof:name":"Isabella Mertin",
    "wof:placetype":"venue"
},
  "geometry": {"coordinates":[7.217547,51.286373],"type":"Point"}
}