{
  "type": "Feature",
  "properties": {
    "iso:country":"DE",
    "sg:address":"Rosenweg 18",
    "sg:city":"Norden",
    "sg:phone":"+49 4931/2751",
    "sg:postcode":"26506",
    "sg:province":"Niedersachsen",
    "wof:name":"Franz Suerbier",
    "wof:placetype":"venue"
},
  "geometry": {"coordinates":[7.2063760757,53.6025543213],"type":"Point"}
}