{
  "type": "Feature",
  "properties": {
    "iso:country":"DE",
    "sg:address":"Nibelungenstr. 11",
    "sg:city":"Solingen",
    "sg:phone":"+49 212/52017",
    "sg:postcode":"42653",
    "sg:province":"Nordrhein-Westfalen",
    "wof:name":"Wolfgang Diergardt",
    "wof:placetype":"venue"
},
  "geometry": {"coordinates":[7.0777311325,51.1955680847],"type":"Point"}
}