{
  "type": "Feature",
  "properties": {
    "iso:country":"DE",
    "sg:address":"Kolpingstr. 8",
    "sg:city":"Wuppertal",
    "sg:phone":"+49 202/5632373",
    "sg:postcode":"42103",
    "sg:province":"Nordrhein-Westfalen",
    "wof:name":"Stadtbibliothek",
    "wof:placetype":"venue"
},
  "geometry": {"coordinates":[7.140599,51.257259],"type":"Point"}
}