{
  "type": "Feature",
  "properties": {
    "iso:country":"DE",
    "sg:address":"Breitenbachstr. 10",
    "sg:city":"Berlin",
    "sg:phone":"+49 30/4322003",
    "sg:postcode":"13509",
    "sg:province":"Berlin",
    "wof:name":"Ernst Hopp Fensterwerk Gmbh",
    "wof:placetype":"venue"
},
  "geometry": {"coordinates":[13.308607,52.579189],"type":"Point"}
}