{
  "type": "Feature",
  "properties": {
    "iso:country":"DE",
    "sg:address":"Lange Str. 56",
    "sg:city":"Salzkotten",
    "sg:phone":"+49 5258/931313",
    "sg:postcode":"33154",
    "sg:province":"Nordrhein-Westfalen",
    "wof:name":"H & W Telekommunikation",
    "wof:placetype":"venue"
},
  "geometry": {"coordinates":[8.6083011627,51.673122406],"type":"Point"}
}