{
  "type": "Feature",
  "properties": {
    "iso:country":"DE",
    "sg:address":"R\u00f6merstr. 18",
    "sg:city":"Boppard",
    "sg:phone":"+49 6742/6324",
    "sg:postcode":"56154",
    "sg:province":"Rheinland-Pfalz",
    "wof:name":"T. Neier Pension",
    "wof:placetype":"venue"
},
  "geometry": {"coordinates":[7.6297497749,50.2046432495],"type":"Point"}
}