{
  "type": "Feature",
  "properties": {
    "iso:country":"DE",
    "sg:address":"Friesenstr 34",
    "sg:city":"Magdeburg",
    "sg:phone":"+49 391/7447210",
    "sg:postcode":"39108",
    "sg:province":"Sachsen-Anhalt",
    "wof:name":"Rangiertechnik Magdeburg Gmbh",
    "wof:placetype":"venue"
},
  "geometry": {"coordinates":[11.6096086502,52.1390838623],"type":"Point"}
}