{
  "type": "Feature",
  "properties": {
    "iso:country":"DE",
    "sg:address":"Gro\u00dfe Schmiedestr. 36",
    "sg:city":"Stade",
    "sg:phone":"+49 4141/2474",
    "sg:postcode":"21682",
    "sg:province":"Niedersachsen",
    "wof:name":"Hans Henrizi Vorm. Ilse K\u00fcster",
    "wof:placetype":"venue"
},
  "geometry": {"coordinates":[9.47698,53.6007],"type":"Point"}
}