{
  "type": "Feature",
  "properties": {
    "iso:country":"DE",
    "sg:address":"Am Sportfeld",
    "sg:city":"Neu-Anspach",
    "sg:phone":"+49 6081/43887",
    "sg:postcode":"61267",
    "sg:province":"Hessen",
    "wof:name":"Vereinsgastst\u00e4tte Sportlertreff",
    "wof:placetype":"venue"
},
  "geometry": {"coordinates":[8.4966554642,50.3109893799],"type":"Point"}
}