{
  "type": "Feature",
  "properties": {
    "iso:country":"DE",
    "sg:address":"Teichstr. 7",
    "sg:city":"Bensheim",
    "sg:phone":"+49 6251/69890",
    "sg:postcode":"64625",
    "sg:province":"Hessen",
    "wof:name":"Restaurant Indian Palace",
    "wof:placetype":"venue"
},
  "geometry": {"coordinates":[8.6192626953,49.6827278137],"type":"Point"}
}