{
  "type": "Feature",
  "properties": {
    "iso:country":"DE",
    "sg:address":"Bruderhofstr. 5",
    "sg:city":"M\u00fcnchen",
    "sg:phone":"+49 89/7232710",
    "sg:postcode":"81371",
    "sg:province":"Bayern",
    "wof:name":"K. Goerz",
    "wof:placetype":"venue"
},
  "geometry": {"coordinates":[11.550845,48.111568],"type":"Point"}
}