{
  "type": "Feature",
  "properties": {
    "iso:country":"DE",
    "sg:address":"Friesenstr. 20",
    "sg:city":"Wittmund",
    "sg:phone":"+49 4973/661",
    "sg:postcode":"26409",
    "sg:province":"Niedersachsen",
    "wof:name":"Bruno M\u00fchle",
    "wof:placetype":"venue"
},
  "geometry": {"coordinates":[7.7090930939,53.6068305969],"type":"Point"}
}