{
  "type": "Feature",
  "properties": {
    "iso:country":"DE",
    "sg:address":"Pfarrstr. 7",
    "sg:city":"Treuen",
    "sg:postcode":"08233",
    "sg:province":"Sachsen",
    "wof:name":"Rolf Noe Augenoptiker",
    "wof:placetype":"venue"
},
  "geometry": {"coordinates":[12.3083209991,50.5396118164],"type":"Point"}
}