{
  "type": "Feature",
  "properties": {
    "iso:country":"DE",
    "sg:address":"W\u00f6rrst\u00e4dter Str. 22",
    "sg:city":"Nierstein",
    "sg:phone":"+49 6133/5482",
    "sg:postcode":"55283",
    "sg:province":"Rheinland-Pfalz",
    "wof:name":"Man Grundst\u00fccks- Gesellschaft Mbh",
    "wof:placetype":"venue"
},
  "geometry": {"coordinates":[8.3452119827,49.8683204651],"type":"Point"}
}