{
  "type": "Feature",
  "properties": {
    "iso:country":"DE",
    "sg:address":"Gotthold-Schwela-Str. 41 Merzd",
    "sg:city":"Cottbus",
    "sg:phone":"+49 355/860809",
    "sg:postcode":"03044",
    "sg:province":"Brandenburg",
    "wof:name":"Euro-transport Gmbh",
    "wof:placetype":"venue"
},
  "geometry": {"coordinates":[14.3345041275,51.7810020447],"type":"Point"}
}