{
  "type": "Feature",
  "properties": {
    "iso:country":"DE",
    "sg:address":"Schneekoppeweg 8",
    "sg:city":"Wolfenb\u00fcttel",
    "sg:phone":"+49 5331/74277",
    "sg:postcode":"38302",
    "sg:province":"Niedersachsen",
    "wof:name":"Peter Behrbohm Steuerberater",
    "wof:placetype":"venue"
},
  "geometry": {"coordinates":[10.5663814545,52.17395401],"type":"Point"}
}