{
  "type": "Feature",
  "properties": {
    "iso:country":"DE",
    "sg:address":"Glockenstr. 6-7",
    "sg:city":"Trier",
    "sg:phone":"+49 651/9780350",
    "sg:postcode":"54290",
    "sg:province":"Rheinland-Pfalz",
    "wof:name":"Rosenbaum & Partner Steuerberatungs Gmbh",
    "wof:placetype":"venue"
},
  "geometry": {"coordinates":[6.643242836,49.7578582764],"type":"Point"}
}