{
  "type": "Feature",
  "properties": {
    "iso:country":"DE",
    "sg:address":"Marktplatz 9",
    "sg:city":"Berchtesgaden",
    "sg:phone":"+49 8652/2445",
    "sg:postcode":"83471",
    "sg:province":"Bayern",
    "wof:name":"Der Huterer Kurz-gober Inh. Irmgard Schmidt",
    "wof:placetype":"venue"
},
  "geometry": {"coordinates":[13.0017766953,47.6327285767],"type":"Point"}
}