{
  "type": "Feature",
  "properties": {
    "iso:country":"DE",
    "sg:address":"Pater-Philipp-Jeningen-Platz 4",
    "sg:city":"Eichst\u00e4tt",
    "sg:phone":"+49 8421/1632",
    "sg:postcode":"85072",
    "sg:province":"Bayern",
    "wof:name":"Kath. Pfarramt St. Mari\u00e4 Himmelfahrt",
    "wof:placetype":"venue"
},
  "geometry": {"coordinates":[11.1845378876,48.8913421631],"type":"Point"}
}