{
  "type": "Feature",
  "properties": {
    "iso:country":"DE",
    "sg:address":"Appelshofer Dorfstr. 28",
    "sg:city":"Grimmen",
    "sg:phone":"+49 4938/3264461",
    "sg:postcode":"18507",
    "sg:province":"Mecklenburg-Vorpommern",
    "wof:name":"Land- Und Maschinen- Technik Gmbh",
    "wof:placetype":"venue"
},
  "geometry": {"coordinates":[13.079228,54.099037],"type":"Point"}
}