{
  "type": "Feature",
  "properties": {
    "iso:country":"DE",
    "sg:address":"Bahnhofstr. 26",
    "sg:city":"Sandersdorf",
    "sg:phone":"+49 3493/88319",
    "sg:postcode":"06792",
    "sg:province":"Sachsen-Anhalt",
    "wof:name":"Hermes",
    "wof:placetype":"venue"
},
  "geometry": {"coordinates":[12.2624616623,51.6283035278],"type":"Point"}
}