{
  "type": "Feature",
  "properties": {
    "iso:country":"DE",
    "sg:address":"Dorfstr. 9",
    "sg:city":"Bergisdorf",
    "sg:phone":"+49 3441/619719",
    "sg:postcode":"06712",
    "sg:province":"Sachsen-Anhalt",
    "wof:name":"Dieter H\u00e4selbarth",
    "wof:placetype":"venue"
},
  "geometry": {"coordinates":[12.116774559,51.0315971375],"type":"Point"}
}