{
  "type": "Feature",
  "properties": {
    "iso:country":"DE",
    "sg:address":"Rheinische Str. 2",
    "sg:city":"Dortmund",
    "sg:phone":"+49 231/18170",
    "sg:postcode":"44137",
    "sg:province":"Nordrhein-Westfalen",
    "wof:name":"Deutsche Brauerei Holding Gmbh & Co. Kg",
    "wof:placetype":"venue"
},
  "geometry": {"coordinates":[7.455362,51.51363],"type":"Point"}
}