{
  "type": "Feature",
  "properties": {
    "iso:country":"DE",
    "sg:address":"Bramfelder Chaussee 328",
    "sg:city":"Hamburg",
    "sg:phone":"+49 40/6427713",
    "sg:postcode":"22175",
    "sg:province":"Hamburg",
    "wof:name":"Der Herr",
    "wof:placetype":"venue"
},
  "geometry": {"coordinates":[10.0807847977,53.6191329956],"type":"Point"}
}