{
  "type": "Feature",
  "properties": {
    "iso:country":"DE",
    "sg:address":"Halske Str. 32",
    "sg:city":"Ratingen",
    "sg:phone":"+49 2102/770970",
    "sg:postcode":"40880",
    "sg:province":"Nordrhein-Westfalen",
    "wof:name":"Theo Geueke Gmbh",
    "wof:placetype":"venue"
},
  "geometry": {"coordinates":[6.8312010765,51.3061256409],"type":"Point"}
}