{
  "type": "Feature",
  "properties": {
    "iso:country":"DE",
    "sg:address":"Raiffeisenplatz 1",
    "sg:city":"Sulzheim",
    "sg:phone":"+49 9382/7007",
    "sg:postcode":"97529",
    "sg:province":"Bayern",
    "wof:name":"Raiffeisenbank Sulzheim",
    "wof:placetype":"venue"
},
  "geometry": {"coordinates":[10.341603,49.947968],"type":"Point"}
}