{
  "type": "Feature",
  "properties": {
    "iso:country":"DE",
    "sg:address":"Hattinger Strasse 654a",
    "sg:city":"Bochum",
    "sg:phone":"+49 234/9413720",
    "sg:postcode":"44879",
    "sg:province":"Nordrhein-Westfalen",
    "wof:name":"Mabo-color",
    "wof:placetype":"venue"
},
  "geometry": {"coordinates":[7.175813,51.434185],"type":"Point"}
}