{
  "type": "Feature",
  "properties": {
    "iso:country":"DE",
    "sg:address":"Johannes-R.-Becher-Str.",
    "sg:city":"Gera",
    "sg:postcode":"07546",
    "sg:province":"Th\u00fcringen",
    "wof:name":"Petra R\u00fchling-sippel",
    "wof:placetype":"venue"
},
  "geometry": {"coordinates":[12.087734,50.898331],"type":"Point"}
}