{
  "type": "Feature",
  "properties": {
    "iso:country":"DE",
    "sg:address":"Gro\u00dfe Bergstr. 252",
    "sg:city":"Hamburg",
    "sg:phone":"+49 40/3898021",
    "sg:postcode":"22767",
    "sg:province":"Hamburg",
    "wof:name":"Uta Pl\u00fcmer",
    "wof:placetype":"venue"
},
  "geometry": {"coordinates":[9.939312,53.551929],"type":"Point"}
}