{
  "type": "Feature",
  "properties": {
    "iso:country":"DE",
    "sg:address":"Brunshofstr. 3",
    "sg:city":"M\u00fclheim",
    "sg:phone":"+49 208/992330",
    "sg:postcode":"45470",
    "sg:province":"Nordrhein-Westfalen",
    "wof:name":"Flughafen Essen-m\u00fclheim Gmbh",
    "wof:placetype":"venue"
},
  "geometry": {"coordinates":[6.935232,51.40596],"type":"Point"}
}