{
  "type": "Feature",
  "properties": {
    "iso:country":"DE",
    "sg:address":"Goethestr. 11 a",
    "sg:city":"Frankfurt",
    "sg:postcode":"15234",
    "sg:province":"Brandenburg",
    "wof:name":"Aldi Gmbh & Co. Kg",
    "wof:placetype":"venue"
},
  "geometry": {"coordinates":[14.522936821,52.347618103],"type":"Point"}
}