{
  "type": "Feature",
  "properties": {
    "iso:country":"DE",
    "sg:address":"Streitstr. 28",
    "sg:city":"Berlin",
    "sg:phone":"+49 30/3358035",
    "sg:postcode":"13587",
    "sg:province":"Berlin",
    "wof:name":"Beauty Boutique Ulrich Gora",
    "wof:placetype":"venue"
},
  "geometry": {"coordinates":[13.208745,52.561741],"type":"Point"}
}