{
  "type": "Feature",
  "properties": {
    "iso:country":"DE",
    "sg:address":"Holzbachtalstr. 7",
    "sg:city":"Straubenhardt",
    "sg:phone":"+49 7248/1060",
    "sg:postcode":"75334",
    "sg:province":"Baden-W\u00fcrttemberg",
    "wof:name":"Heinrich J\u00e4ck E. K.",
    "wof:placetype":"venue"
},
  "geometry": {"coordinates":[8.4759950638,48.8368263245],"type":"Point"}
}