{
  "type": "Feature",
  "properties": {
    "iso:country":"DE",
    "sg:address":"Schulstr. 7",
    "sg:city":"Gro\u00dfolbersdorf",
    "sg:phone":"+49 37369/9496",
    "sg:postcode":"09432",
    "sg:province":"Sachsen",
    "wof:name":"B. Seidel",
    "wof:placetype":"venue"
},
  "geometry": {"coordinates":[13.0894670486,50.6922683716],"type":"Point"}
}