{
  "type": "Feature",
  "properties": {
    "iso:country":"DE",
    "sg:address":"Freudenst\u00e4dter Str. 4",
    "sg:city":"Dornstetten",
    "sg:postcode":"72280",
    "sg:province":"Baden-W\u00fcrttemberg",
    "wof:name":"Arztpraxis Ronald H. Muessle",
    "wof:placetype":"venue"
},
  "geometry": {"coordinates":[8.499349,48.472012],"type":"Point"}
}