{
  "type": "Feature",
  "properties": {
    "iso:country":"DE",
    "sg:address":"Prinzregentenplatz 13",
    "sg:city":"M\u00fcnchen",
    "sg:phone":"+49 89/4705064",
    "sg:postcode":"81675",
    "sg:province":"Bayern",
    "wof:name":"Treucontact Gmbh",
    "wof:placetype":"venue"
},
  "geometry": {"coordinates":[11.6063232422,48.1397743225],"type":"Point"}
}