{
  "type": "Feature",
  "properties": {
    "iso:country":"DE",
    "sg:address":"Edewechter Landstr. 44",
    "sg:city":"Oldenburg",
    "sg:phone":"+49 441/591055",
    "sg:postcode":"26131",
    "sg:province":"Niedersachsen",
    "wof:name":"Michael Neumann Masseur",
    "wof:placetype":"venue"
},
  "geometry": {"coordinates":[8.182238,53.13076],"type":"Point"}
}