{
  "type": "Feature",
  "properties": {
    "iso:country":"DE",
    "sg:address":"D\u00fcffelgaustr. 20",
    "sg:city":"Kleve",
    "sg:phone":"+49 2821/3741",
    "sg:postcode":"47533",
    "sg:province":"Nordrhein-Westfalen",
    "wof:name":"Ulrich Ahrens",
    "wof:placetype":"venue"
},
  "geometry": {"coordinates":[6.0769701004,51.8438110352],"type":"Point"}
}