{
  "type": "Feature",
  "properties": {
    "iso:country":"DE",
    "sg:address":"Rungestr. 3",
    "sg:city":"Berlin",
    "sg:phone":"+49 30/2791859",
    "sg:postcode":"10179",
    "sg:province":"Berlin",
    "wof:name":"Dr. Med. Ruth Raabe \u00c4rztin F\u00fcr Allgemeinmedizin",
    "wof:placetype":"venue"
},
  "geometry": {"coordinates":[13.4133167267,52.512550354],"type":"Point"}
}