{
  "type": "Feature",
  "properties": {
    "iso:country":"DE",
    "sg:address":"Rantzauallee 48",
    "sg:city":"Bad Schwartau",
    "sg:phone":"+49 451/22118",
    "sg:postcode":"23611",
    "sg:province":"Schleswig-Holstein",
    "wof:name":"Kurt Fester",
    "wof:placetype":"venue"
},
  "geometry": {"coordinates":[10.685741,53.921459],"type":"Point"}
}