{
  "type": "Feature",
  "properties": {
    "iso:country":"DE",
    "sg:address":"Fritz-Schubert-Ring 45",
    "sg:city":"Frankfurt",
    "sg:phone":"+49 6109/731345",
    "sg:postcode":"60388",
    "sg:province":"Hessen",
    "wof:name":"Inter-ned Ohg",
    "wof:placetype":"venue"
},
  "geometry": {"coordinates":[8.764052,50.153343],"type":"Point"}
}