{
  "type": "Feature",
  "properties": {
    "iso:country":"DE",
    "sg:address":"Ernststr. 13",
    "sg:city":"Neustadt",
    "sg:phone":"+49 9568/5625",
    "sg:postcode":"96465",
    "sg:province":"Bayern",
    "wof:name":"Pizzeria Lorso Bianco Wei\u00dfer B\u00e4r",
    "wof:placetype":"venue"
},
  "geometry": {"coordinates":[11.1231231689,50.3279380798],"type":"Point"}
}