{
  "type": "Feature",
  "properties": {
    "iso:country":"DE",
    "sg:address":"Clara-Viebig-Str. 12",
    "sg:city":"Dresden",
    "sg:postcode":"01159",
    "sg:province":"Sachsen",
    "wof:name":"Sid Marketing- Und Mediengesellschaft Mbh",
    "wof:placetype":"venue"
},
  "geometry": {"coordinates":[13.7032423019,51.0383834839],"type":"Point"}
}