{
  "type": "Feature",
  "properties": {
    "iso:country":"DE",
    "sg:address":"Gerstlestr. 19",
    "sg:city":"Memmingen",
    "sg:phone":"+49 8331/61095",
    "sg:postcode":"87700",
    "sg:province":"Bayern",
    "wof:name":"Jugl Und Ebner",
    "wof:placetype":"venue"
},
  "geometry": {"coordinates":[10.1519260406,47.9874534607],"type":"Point"}
}