{
  "type": "Feature",
  "properties": {
    "iso:country":"DE",
    "sg:address":"Bahnhofstr. 7",
    "sg:city":"Arrach",
    "sg:phone":"+49 9943/905053",
    "sg:postcode":"93474",
    "sg:province":"Bayern",
    "wof:name":"Vr Planung Von Einrichtungen Gmbh",
    "wof:placetype":"venue"
},
  "geometry": {"coordinates":[13.0034780502,49.1956558228],"type":"Point"}
}