{
  "type": "Feature",
  "properties": {
    "iso:country":"DE",
    "sg:address":"Gutenbergstr. 6",
    "sg:city":"Sinsheim",
    "sg:phone":"+49 7261/2501",
    "sg:postcode":"74889",
    "sg:province":"Baden-W\u00fcrttemberg",
    "wof:name":"Herzog-k\u00f6rber Gmbh",
    "wof:placetype":"venue"
},
  "geometry": {"coordinates":[8.880489,49.245235],"type":"Point"}
}