{
  "type": "Feature",
  "properties": {
    "iso:country":"DE",
    "sg:address":"Geckenauer Str.",
    "sg:city":"Bastheim",
    "sg:phone":"+49 9773/6333",
    "sg:postcode":"97654",
    "sg:province":"Bayern",
    "wof:name":"Haus Weissmeier",
    "wof:placetype":"venue"
},
  "geometry": {"coordinates":[10.2036972046,50.3966941833],"type":"Point"}
}