{
  "type": "Feature",
  "properties": {
    "iso:country":"DE",
    "sg:address":"Kettelerstr. 8",
    "sg:city":"Aschendorf",
    "sg:phone":"+49 4962/368",
    "sg:postcode":"26871",
    "sg:province":"Niedersachsen",
    "wof:name":"Bauunternehmung Pape Gmbh",
    "wof:placetype":"venue"
},
  "geometry": {"coordinates":[7.3391418457,53.0581092834],"type":"Point"}
}