{
  "type": "Feature",
  "properties": {
    "iso:country":"DE",
    "sg:address":"Sollner Str. 20",
    "sg:city":"M\u00fcnchen",
    "sg:phone":"+49 89/7902378",
    "sg:postcode":"81479",
    "sg:province":"Bayern",
    "wof:name":"Barbara Hinz",
    "wof:placetype":"venue"
},
  "geometry": {"coordinates":[11.5269584656,48.0831871033],"type":"Point"}
}