{
  "type": "Feature",
  "properties": {
    "iso:country":"DE",
    "sg:address":"Ohmstr. 3",
    "sg:city":"Dachau",
    "sg:phone":"+49 8131/51590",
    "sg:postcode":"85221",
    "sg:province":"Bayern",
    "wof:name":"Bth Bolzenschwei\u00df-technik Heberle Gmbh",
    "wof:placetype":"venue"
},
  "geometry": {"coordinates":[11.475972,48.26696],"type":"Point"}
}