{
  "type": "Feature",
  "properties": {
    "iso:country":"DE",
    "sg:address":"Strelitzer Str. 43",
    "sg:city":"Leipzig",
    "sg:postcode":"04157",
    "sg:province":"Sachsen",
    "wof:name":"Lutz Schindler",
    "wof:placetype":"venue"
},
  "geometry": {"coordinates":[12.3762273788,51.3742370605],"type":"Point"}
}