{
  "type": "Feature",
  "properties": {
    "iso:country":"DE",
    "sg:address":"Markt 15",
    "sg:city":"Strausberg",
    "sg:phone":"+49 3341/22733",
    "sg:postcode":"15344",
    "sg:province":"Brandenburg",
    "wof:name":"Bau- Und M\u00f6beltischlerei Haack",
    "wof:placetype":"venue"
},
  "geometry": {"coordinates":[13.880982,52.580914],"type":"Point"}
}