{
  "type": "Feature",
  "properties": {
    "iso:country":"DE",
    "sg:address":"Ludwig-Moser-Str. 12",
    "sg:city":"Haar",
    "sg:phone":"+49 89/468144",
    "sg:postcode":"85540",
    "sg:province":"Bayern",
    "wof:name":"Producta Werbemittel Und Display Gmbh",
    "wof:placetype":"venue"
},
  "geometry": {"coordinates":[11.720886,48.110291],"type":"Point"}
}