{
  "type": "Feature",
  "properties": {
    "iso:country":"DE",
    "sg:address":"Rheinstr. 14",
    "sg:city":"Stutensee",
    "sg:postcode":"76297",
    "sg:province":"Baden-W\u00fcrttemberg",
    "wof:name":"Verwaltungsstelle Friedrichstal",
    "wof:placetype":"venue"
},
  "geometry": {"coordinates":[8.4835014343,49.1072502136],"type":"Point"}
}