{
  "type": "Feature",
  "properties": {
    "iso:country":"DE",
    "sg:address":"Oberm\u00fcnsterstr. 18",
    "sg:city":"Regensburg",
    "sg:phone":"+49 941/55730",
    "sg:postcode":"93047",
    "sg:province":"Bayern",
    "wof:name":"E. Platzer",
    "wof:placetype":"venue"
},
  "geometry": {"coordinates":[12.0976228714,49.0159111023],"type":"Point"}
}