{
  "type": "Feature",
  "properties": {
    "iso:country":"DE",
    "sg:address":"Kreuzerweg 19",
    "sg:city":"Pr\u00fcm",
    "sg:phone":"+49 6551/2139",
    "sg:postcode":"54595",
    "sg:province":"Rheinland-Pfalz",
    "wof:name":"Ottmar Bechtel",
    "wof:placetype":"venue"
},
  "geometry": {"coordinates":[6.4208607674,50.2044372559],"type":"Point"}
}