{
  "type": "Feature",
  "properties": {
    "iso:country":"DE",
    "sg:address":"Hohelucht 13",
    "sg:city":"Hude",
    "sg:phone":"+49 4408/1014",
    "sg:postcode":"27798",
    "sg:province":"Niedersachsen",
    "wof:name":"Volksb\u00fccherei",
    "wof:placetype":"venue"
},
  "geometry": {"coordinates":[8.459349,53.105885],"type":"Point"}
}