{
  "type": "Feature",
  "properties": {
    "iso:country":"DE",
    "sg:address":"Twistedener Str. 38",
    "sg:city":"Geldern",
    "sg:phone":"+49 2832/4301",
    "sg:postcode":"47608",
    "sg:province":"Nordrhein-Westfalen",
    "wof:name":"Wolfgang Kaun",
    "wof:placetype":"venue"
},
  "geometry": {"coordinates":[6.234636,51.54174],"type":"Point"}
}