{
  "type": "Feature",
  "properties": {
    "iso:country":"DE",
    "sg:address":"Virmondstr. 11",
    "sg:city":"Willich",
    "sg:phone":"+49 2156/5178",
    "sg:postcode":"47877",
    "sg:province":"Nordrhein-Westfalen",
    "wof:name":"W. Neukirchen",
    "wof:placetype":"venue"
},
  "geometry": {"coordinates":[6.464589119,51.2543907166],"type":"Point"}
}