{
  "type": "Feature",
  "properties": {
    "iso:country":"DE",
    "sg:address":"Oberweyerer Str 1",
    "sg:city":"Limburg",
    "sg:phone":"+49 6433/943093",
    "sg:postcode":"65554",
    "sg:province":"Hessen",
    "wof:name":"Peter Schilling",
    "wof:placetype":"venue"
},
  "geometry": {"coordinates":[8.093269,50.439034],"type":"Point"}
}