{
  "type": "Feature",
  "properties": {
    "iso:country":"DE",
    "sg:address":"Industriestr. 31",
    "sg:city":"Dannstadt-Schauernheim",
    "sg:phone":"+49 6231/94250",
    "sg:postcode":"67125",
    "sg:province":"Rheinland-Pfalz",
    "wof:name":"Rau-touristik Gmbh",
    "wof:placetype":"venue"
},
  "geometry": {"coordinates":[8.3218603134,49.4313201904],"type":"Point"}
}