{
  "type": "Feature",
  "properties": {
    "iso:country":"DE",
    "sg:address":"Lindenstr. 02",
    "sg:city":"Neuenhagen",
    "sg:phone":"+49 3342/7993",
    "sg:postcode":"15366",
    "sg:province":"Brandenburg",
    "wof:name":"Konstantin Henke Ingenieur",
    "wof:placetype":"venue"
},
  "geometry": {"coordinates":[13.6756601334,52.5221633911],"type":"Point"}
}