{
  "type": "Feature",
  "properties": {
    "iso:country":"DE",
    "sg:address":"Heimsheim",
    "sg:city":"Heimsheim",
    "sg:phone":"+49 4970/3331225",
    "sg:postcode":"71263",
    "sg:province":"Baden-W\u00fcrttemberg",
    "wof:name":"Volksbank Heimsheim",
    "wof:placetype":"venue"
},
  "geometry": {"coordinates":[8.86126,48.809582],"type":"Point"}
}