{
  "type": "Feature",
  "properties": {
    "iso:country":"DE",
    "sg:address":"Lochau 31",
    "sg:city":"Pullenreuth",
    "sg:postcode":"95704",
    "sg:province":"Bayern",
    "wof:name":"Joseph H\u00f6rtl Architekt",
    "wof:placetype":"venue"
},
  "geometry": {"coordinates":[11.978591,49.916336],"type":"Point"}
}