{
  "type": "Feature",
  "properties": {
    "iso:country":"DE",
    "sg:address":"Hauptstr. 9",
    "sg:city":"Leinach",
    "sg:phone":"+49 9364/1343",
    "sg:postcode":"97274",
    "sg:province":"Bayern",
    "wof:name":"K. Kleinschnitz",
    "wof:placetype":"venue"
},
  "geometry": {"coordinates":[9.7990961075,49.8660964966],"type":"Point"}
}