{
  "type": "Feature",
  "properties": {
    "iso:country":"DE",
    "sg:address":"Els\u00fcsser Str. 27",
    "sg:city":"M\u00fcnchen",
    "sg:phone":"+49 89/4482652",
    "sg:postcode":"81667",
    "sg:province":"Bayern",
    "wof:name":"Marschall & Schweter Gmbh",
    "wof:placetype":"venue"
},
  "geometry": {"coordinates":[11.6052703857,48.1299819946],"type":"Point"}
}