{
  "type": "Feature",
  "properties": {
    "iso:country":"DE",
    "sg:address":"Bernhardstr. 88",
    "sg:city":"Dresden",
    "sg:postcode":"01187",
    "sg:province":"Sachsen",
    "wof:name":"E. Zuber",
    "wof:placetype":"venue"
},
  "geometry": {"coordinates":[13.713396,51.027367],"type":"Point"}
}