{
  "type": "Feature",
  "properties": {
    "iso:country":"DE",
    "sg:address":"Schwanenteichallee",
    "sg:city":"M\u00fchlhausen",
    "sg:phone":"+49 36018/74392",
    "sg:postcode":"99974",
    "sg:province":"Th\u00fcringen",
    "wof:name":"Fc Union M\u00fchlhausen",
    "wof:placetype":"venue"
},
  "geometry": {"coordinates":[10.4380331039,51.2033081055],"type":"Point"}
}