{
  "type": "Feature",
  "properties": {
    "iso:country":"DE",
    "sg:address":"Schw\u00e4rzstr. 7",
    "sg:city":"Bernau",
    "sg:phone":"+49 8051/7513",
    "sg:postcode":"83233",
    "sg:province":"Bayern",
    "wof:name":"Georg Und Erika Winkler",
    "wof:placetype":"venue"
},
  "geometry": {"coordinates":[12.3789291382,47.8152084351],"type":"Point"}
}