{
  "type": "Feature",
  "properties": {
    "iso:country":"DE",
    "sg:address":"B\u00fchlstr. 26",
    "sg:city":"G\u00f6ttingen",
    "sg:postcode":"37073",
    "sg:province":"Niedersachsen",
    "wof:name":"Detlef Vogt E. K.",
    "wof:placetype":"venue"
},
  "geometry": {"coordinates":[9.9425649643,51.5375747681],"type":"Point"}
}