{
  "type": "Feature",
  "properties": {
    "iso:country":"DE",
    "sg:address":"Eudenbachstr. 42",
    "sg:city":"Hennef",
    "sg:phone":"+49 2248/2594",
    "sg:postcode":"53773",
    "sg:province":"Nordrhein-Westfalen",
    "wof:name":"Prinsler",
    "wof:placetype":"venue"
},
  "geometry": {"coordinates":[7.335813,50.703461],"type":"Point"}
}