{
  "type": "Feature",
  "properties": {
    "iso:country":"DE",
    "sg:address":"Bleichm\u00e4rsch 37",
    "sg:city":"Dortmund",
    "sg:postcode":"44145",
    "sg:province":"Nordrhein-Westfalen",
    "wof:name":"Eac Europe Autoexport Center Gmbh",
    "wof:placetype":"venue"
},
  "geometry": {"coordinates":[7.477772,51.520691],"type":"Point"}
}