{
  "type": "Feature",
  "properties": {
    "iso:country":"DE",
    "sg:address":"Wernerusstr. 43 a",
    "sg:city":"Celle",
    "sg:phone":"+49 5141/82340",
    "sg:postcode":"29227",
    "sg:province":"Niedersachsen",
    "wof:name":"P. Str\u00f6h",
    "wof:placetype":"venue"
},
  "geometry": {"coordinates":[10.05671978,52.5926742554],"type":"Point"}
}