{
  "type": "Feature",
  "properties": {
    "iso:country":"DE",
    "sg:address":"Quellenweg 65",
    "sg:city":"Oldenburg",
    "sg:phone":"+49 441/9729928",
    "sg:postcode":"26129",
    "sg:province":"Niedersachsen",
    "wof:name":"Praxis Dr. Heckerodt-l\u00fcthe Und Dr. Med. L\u00fcthe",
    "wof:placetype":"venue"
},
  "geometry": {"coordinates":[8.1771211624,53.1444892883],"type":"Point"}
}