{
  "type": "Feature",
  "properties": {
    "iso:country":"DE",
    "sg:address":"Bleichstr. 4",
    "sg:city":"Karlsruhe",
    "sg:phone":"+49 721/496501",
    "sg:postcode":"76227",
    "sg:province":"Baden-W\u00fcrttemberg",
    "wof:name":"Eugen Richard Wied",
    "wof:placetype":"venue"
},
  "geometry": {"coordinates":[8.461178,48.998981],"type":"Point"}
}