{
  "type": "Feature",
  "properties": {
    "iso:country":"DE",
    "sg:address":"Bahnhofstrasse 15",
    "sg:city":"Bad Gr\u00f6nenbach",
    "sg:phone":"+49 8334",
    "sg:postcode":"87730",
    "sg:province":"Bayern",
    "wof:name":"Index",
    "wof:placetype":"venue"
},
  "geometry": {"coordinates":[10.22296,47.876938],"type":"Point"}
}