{
  "type": "Feature",
  "properties": {
    "iso:country":"DE",
    "sg:address":"Monningstr. 41",
    "sg:city":"M\u00fclheim",
    "sg:phone":"+49 208/52976",
    "sg:postcode":"45478",
    "sg:province":"Nordrhein-Westfalen",
    "wof:name":"Edwin Schmitt",
    "wof:placetype":"venue"
},
  "geometry": {"coordinates":[6.8182868958,51.4361228943],"type":"Point"}
}