{
  "type": "Feature",
  "properties": {
    "iso:country":"DE",
    "sg:address":"Erggertshofen 1",
    "sg:city":"Breitenbrunn",
    "sg:phone":"+49 9495/340",
    "sg:postcode":"92363",
    "sg:province":"Bayern",
    "wof:name":"Gastst\u00e4tte Josef Dietl",
    "wof:placetype":"venue"
},
  "geometry": {"coordinates":[11.6363935471,49.057308197],"type":"Point"}
}