{
  "type": "Feature",
  "properties": {
    "iso:country":"DE",
    "sg:address":"Brauhausgasse 3",
    "sg:city":"Greiz",
    "sg:phone":"+49 3661/2450",
    "sg:postcode":"07973",
    "sg:province":"Th\u00fcringen",
    "wof:name":"Paul Held",
    "wof:placetype":"venue"
},
  "geometry": {"coordinates":[12.198542,50.657066],"type":"Point"}
}