{
  "type": "Feature",
  "properties": {
    "iso:country":"DE",
    "sg:address":"Deusener Str. 91",
    "sg:city":"Dortmund",
    "sg:phone":"+49 231/391685",
    "sg:postcode":"44369",
    "sg:province":"Nordrhein-Westfalen",
    "wof:name":"L & L",
    "wof:placetype":"venue"
},
  "geometry": {"coordinates":[7.42864,51.540871],"type":"Point"}
}