{
  "type": "Feature",
  "properties": {
    "iso:country":"DE",
    "sg:address":"Harpener Heide 12",
    "sg:city":"Bochum",
    "sg:postcode":"44805",
    "sg:province":"Nordrhein-Westfalen",
    "wof:name":"Bft Bochumer Fahrzeugtechnik Gmbh",
    "wof:placetype":"venue"
},
  "geometry": {"coordinates":[7.252102,51.501308],"type":"Point"}
}