{
  "type": "Feature",
  "properties": {
    "iso:country":"DE",
    "sg:address":"M\u00f6wenburgstr. 27",
    "sg:city":"Schwerin",
    "sg:phone":"+49 385/557000",
    "sg:postcode":"19055",
    "sg:province":"Mecklenburg-Vorpommern",
    "wof:name":"Wintop Fensterwerk Gmbh",
    "wof:placetype":"venue"
},
  "geometry": {"coordinates":[11.421854,53.646202],"type":"Point"}
}