{
  "type": "Feature",
  "properties": {
    "iso:country":"DE",
    "sg:address":"SCH\u00d6NEBECKER HAGEN 13",
    "sg:city":"BREMEN",
    "sg:phone":"+49 421/658605051",
    "sg:postcode":"28757",
    "sg:province":"Bremen",
    "wof:name":"Euro Import Indo Export & Trad",
    "wof:placetype":"venue"
},
  "geometry": {"coordinates":[8.6407203674,53.1856307983],"type":"Point"}
}