{
  "type": "Feature",
  "properties": {
    "iso:country":"DE",
    "sg:address":"Hauptstr. 87",
    "sg:city":"H\u00f6chberg",
    "sg:phone":"+49 931/409086",
    "sg:postcode":"97204",
    "sg:province":"Bayern",
    "wof:name":"Uwe Und Gudrun Neu Rechtsanw\u00e4lte",
    "wof:placetype":"venue"
},
  "geometry": {"coordinates":[9.8781280518,49.7811851501],"type":"Point"}
}