{
  "type": "Feature",
  "properties": {
    "iso:country":"DE",
    "sg:address":"K\u00f6rnerstr. 20",
    "sg:city":"Braunschweig",
    "sg:phone":"+49 531/794002",
    "sg:postcode":"38102",
    "sg:province":"Niedersachsen",
    "wof:name":"J\u00f6rg Adam Architekt",
    "wof:placetype":"venue"
},
  "geometry": {"coordinates":[10.539487,52.260624],"type":"Point"}
}