{
  "type": "Feature",
  "properties": {
    "iso:country":"DE",
    "sg:address":"Untere Hauptstr. 46",
    "sg:city":"Freising",
    "sg:phone":"+49 8161/50151",
    "sg:postcode":"85354",
    "sg:province":"Bayern",
    "wof:name":"Hek Beteiligungs Gmbh",
    "wof:placetype":"venue"
},
  "geometry": {"coordinates":[11.747821,48.401394],"type":"Point"}
}