{
  "type": "Feature",
  "properties": {
    "iso:country":"DE",
    "sg:address":"Im Dol 27-29",
    "sg:city":"Berlin",
    "sg:phone":"+49 30/31471294",
    "sg:postcode":"14195",
    "sg:province":"Berlin",
    "wof:name":"Techn. Universit\u00e4t Berlin Institut Fr Agrarbetriebs- U.",
    "wof:placetype":"venue"
},
  "geometry": {"coordinates":[13.289404,52.465275],"type":"Point"}
}