{
  "type": "Feature",
  "properties": {
    "iso:country":"DE",
    "sg:address":"P\u00f6dinghauser Str. 240",
    "sg:city":"Herford",
    "sg:phone":"+49 5224/4021",
    "sg:postcode":"32051",
    "sg:province":"Nordrhein-Westfalen",
    "wof:name":"Werner Scholtz",
    "wof:placetype":"venue"
},
  "geometry": {"coordinates":[8.5789499283,52.1120910645],"type":"Point"}
}