{
  "type": "Feature",
  "properties": {
    "iso:country":"DE",
    "sg:address":"Br\u00fcninghauser Str. 95",
    "sg:city":"L\u00fcdenscheid",
    "sg:phone":"+49 2351/42400",
    "sg:postcode":"58513",
    "sg:province":"Nordrhein-Westfalen",
    "wof:name":"Schmiedemuseum Bremecker Hammer",
    "wof:placetype":"venue"
},
  "geometry": {"coordinates":[7.693862,51.206318],"type":"Point"}
}