{
  "type": "Feature",
  "properties": {
    "iso:country":"DE",
    "sg:address":"H\u00fcttenstr. 41",
    "sg:city":"Stadthagen",
    "sg:phone":"+49 5721/79128",
    "sg:postcode":"31655",
    "sg:province":"Niedersachsen",
    "wof:name":"Rippe Gmbh",
    "wof:placetype":"venue"
},
  "geometry": {"coordinates":[9.1857976913,52.3307342529],"type":"Point"}
}