{
  "type": "Feature",
  "properties": {
    "iso:country":"DE",
    "sg:address":"Marientaler Str. 24",
    "sg:city":"Berlin",
    "sg:postcode":"12437",
    "sg:province":"Berlin",
    "wof:name":"Klara Schabbel",
    "wof:placetype":"venue"
},
  "geometry": {"coordinates":[13.4893751144,52.4644393921],"type":"Point"}
}