{
  "type": "Feature",
  "properties": {
    "iso:country":"DE",
    "sg:address":"Edelwei\u00dfstr. 11",
    "sg:city":"Kr\u00fcn",
    "sg:phone":"+49 8825/1014",
    "sg:postcode":"82494",
    "sg:province":"Bayern",
    "wof:name":"Hotel-pension Alpenhof",
    "wof:placetype":"venue"
},
  "geometry": {"coordinates":[11.2804756165,47.505569458],"type":"Point"}
}