{
  "type": "Feature",
  "properties": {
    "iso:country":"DE",
    "sg:address":"Wickrather Str. 60",
    "sg:city":"M\u00f6nchengladbach",
    "sg:phone":"+49 2166/49156",
    "sg:postcode":"41236",
    "sg:province":"Nordrhein-Westfalen",
    "wof:name":"K. Hermanns",
    "wof:placetype":"venue"
},
  "geometry": {"coordinates":[6.439702,51.159958],"type":"Point"}
}