{
  "type": "Feature",
  "properties": {
    "iso:country":"DE",
    "sg:address":"Verdener Str. 8",
    "sg:city":"Schneverdingen",
    "sg:phone":"+49 5193/7600",
    "sg:postcode":"29640",
    "sg:province":"Niedersachsen",
    "wof:name":"Sanit\u00e4tshaus Klug Gmbh",
    "wof:placetype":"venue"
},
  "geometry": {"coordinates":[9.7885770798,53.1167564392],"type":"Point"}
}