{
  "type": "Feature",
  "properties": {
    "iso:country":"DE",
    "sg:address":"Kirchwerder Landweg 15",
    "sg:city":"Hamburg",
    "sg:phone":"+49 40/7237770",
    "sg:postcode":"21037",
    "sg:province":"Hamburg",
    "wof:name":"Gerd Buhk Steuerberatungsges. Mbh",
    "wof:placetype":"venue"
},
  "geometry": {"coordinates":[10.1938915253,53.4588546753],"type":"Point"}
}