{
  "type": "Feature",
  "properties": {
    "iso:country":"DE",
    "sg:address":"Hintere Str. 1",
    "sg:city":"Maselheim",
    "sg:phone":"+49 7356/95010",
    "sg:postcode":"88437",
    "sg:province":"Baden-W\u00fcrttemberg",
    "wof:name":"Martin Gerster",
    "wof:placetype":"venue"
},
  "geometry": {"coordinates":[9.857368,48.15575],"type":"Point"}
}