{
  "type": "Feature",
  "properties": {
    "iso:country":"DE",
    "sg:address":"Tiefenbacher Str. 70",
    "sg:city":"Crailsheim",
    "sg:phone":"+49 7951/3030",
    "sg:postcode":"74564",
    "sg:province":"Baden-W\u00fcrttemberg",
    "wof:name":"W\u00dcco-fleisch Gmbh",
    "wof:placetype":"venue"
},
  "geometry": {"coordinates":[10.0571403503,49.1467704773],"type":"Point"}
}