{
  "type": "Feature",
  "properties": {
    "iso:country":"DE",
    "sg:address":"Saint-Priest-Str. 1",
    "sg:city":"M\u00fchlheim",
    "sg:postcode":"63165",
    "sg:province":"Hessen",
    "wof:name":"Baukontakt Deutscher Gmbh",
    "wof:placetype":"venue"
},
  "geometry": {"coordinates":[8.836401,50.127209],"type":"Point"}
}