{
  "type": "Feature",
  "properties": {
    "iso:country":"DE",
    "sg:address":"Goethestr. 11c",
    "sg:city":"Frankfurt",
    "sg:postcode":"15234",
    "sg:province":"Brandenburg",
    "wof:name":"Stadt Bau Tischlereigesellschaft Mbh",
    "wof:placetype":"venue"
},
  "geometry": {"coordinates":[14.522937,52.347618],"type":"Point"}
}