{
  "type": "Feature",
  "properties": {
    "iso:country":"DE",
    "sg:address":"Grutholzallee 21",
    "sg:city":"Castrop-Rauxel",
    "sg:phone":"+49 2305/1021",
    "sg:postcode":"44577",
    "sg:province":"Nordrhein-Westfalen",
    "wof:name":"Krankenhausgalerie",
    "wof:placetype":"venue"
},
  "geometry": {"coordinates":[7.319143,51.567345],"type":"Point"}
}