{
  "type": "Feature",
  "properties": {
    "iso:country":"DE",
    "sg:address":"Christian-Wirth-Str 2",
    "sg:city":"Fulda",
    "sg:phone":"+49 661/94850",
    "sg:postcode":"36043",
    "sg:province":"Hessen",
    "wof:name":"Baby-direkt-gro\u00df-einzel- Und Versandhandels Gmbh",
    "wof:placetype":"venue"
},
  "geometry": {"coordinates":[9.685076,50.528561],"type":"Point"}
}