{
  "type": "Feature",
  "properties": {
    "iso:country":"DE",
    "sg:address":"Wittigstr. 8",
    "sg:city":"Stadtallendorf",
    "sg:phone":"+49 4964/287040",
    "sg:postcode":"35260",
    "sg:province":"Hessen",
    "wof:name":"Wezag Gmbh",
    "wof:placetype":"venue"
},
  "geometry": {"coordinates":[8.993811,50.810951],"type":"Point"}
}