{
  "type": "Feature",
  "properties": {
    "iso:country":"DE",
    "sg:address":"Im Alten Dorf 17",
    "sg:city":"Wallenhorst",
    "sg:phone":"+49 5407/2945",
    "sg:postcode":"49134",
    "sg:province":"Niedersachsen",
    "wof:name":"Heinrich Lahrmann",
    "wof:placetype":"venue"
},
  "geometry": {"coordinates":[8.023718,52.350422],"type":"Point"}
}