{
  "type": "Feature",
  "properties": {
    "iso:country":"DE",
    "sg:address":"Krefelder Str. 195",
    "sg:city":"Duisburg",
    "sg:phone":"+49 2065/74922",
    "sg:postcode":"47226",
    "sg:province":"Nordrhein-Westfalen",
    "wof:name":"U. Richter Drogerie",
    "wof:placetype":"venue"
},
  "geometry": {"coordinates":[6.703871,51.402779],"type":"Point"}
}