{
  "type": "Feature",
  "properties": {
    "iso:country":"DE",
    "sg:address":"Salvador-Allende-Str.",
    "sg:city":"Neubrandenburg",
    "sg:postcode":"17036",
    "sg:province":"Mecklenburg-Vorpommern",
    "wof:name":"Klinikum Neubrandenburg Bereich Technik",
    "wof:placetype":"venue"
},
  "geometry": {"coordinates":[13.29238,53.552502],"type":"Point"}
}