{
  "type": "Feature",
  "properties": {
    "iso:country":"DE",
    "sg:address":"J\u00fcterboger Str. 52",
    "sg:city":"Dahme",
    "sg:phone":"+49 35451/270",
    "sg:postcode":"15936",
    "sg:province":"Brandenburg",
    "wof:name":"Georg Vieth",
    "wof:placetype":"venue"
},
  "geometry": {"coordinates":[13.421191,51.868168],"type":"Point"}
}