{
  "type": "Feature",
  "properties": {
    "iso:country":"DE",
    "sg:address":"Am Kohlenschacht 5",
    "sg:city":"Bad Abbach",
    "sg:phone":"+49 9405/4847",
    "sg:postcode":"93077",
    "sg:province":"Bayern",
    "wof:name":"Albert Zweck Ingenieur",
    "wof:placetype":"venue"
},
  "geometry": {"coordinates":[12.0459117889,48.9397506714],"type":"Point"}
}