{
  "type": "Feature",
  "properties": {
    "iso:country":"DE",
    "sg:address":"Hospitalstr. 41",
    "sg:city":"G\u00f6rlitz",
    "sg:phone":"+49 3581/402019",
    "sg:postcode":"02826",
    "sg:province":"Sachsen",
    "wof:name":"Thomas Lange",
    "wof:placetype":"venue"
},
  "geometry": {"coordinates":[14.983874321,51.1498374939],"type":"Point"}
}