{
  "type": "Feature",
  "properties": {
    "iso:country":"DE",
    "sg:address":"Eseiterstr 5",
    "sg:city":"Illingen",
    "sg:phone":"+49 6825/942910",
    "sg:postcode":"66557",
    "sg:province":"Saarland",
    "wof:name":"Synergetik Gmbh",
    "wof:placetype":"venue"
},
  "geometry": {"coordinates":[7.010364,49.366383],"type":"Point"}
}