{
  "type": "Feature",
  "properties": {
    "iso:country":"DE",
    "sg:address":"Gewerbering 5",
    "sg:city":"Burgheim",
    "sg:phone":"+49 8432/1498",
    "sg:postcode":"86666",
    "sg:province":"Bayern",
    "wof:name":"Fritz Rucker Sachverst\u00e4ndigen Gmbh",
    "wof:placetype":"venue"
},
  "geometry": {"coordinates":[11.0080299377,48.7073898315],"type":"Point"}
}