{
  "type": "Feature",
  "properties": {
    "iso:country":"DE",
    "sg:address":"Ku\u00dfmaulstr. 66",
    "sg:city":"Freiburg",
    "sg:phone":"+49 761/83582",
    "sg:postcode":"79114",
    "sg:province":"Baden-W\u00fcrttemberg",
    "wof:name":"Klaus Maier",
    "wof:placetype":"venue"
},
  "geometry": {"coordinates":[7.8128929138,48.0065956116],"type":"Point"}
}