{
  "type": "Feature",
  "properties": {
    "iso:country":"DE",
    "sg:address":"Bozener Str. 30",
    "sg:city":"Friedberg",
    "sg:phone":"+49 821/604100",
    "sg:postcode":"86316",
    "sg:province":"Bayern",
    "wof:name":"Rita Dotterweich Krankengymnastin",
    "wof:placetype":"venue"
},
  "geometry": {"coordinates":[10.993634,48.363293],"type":"Point"}
}