{
  "type": "Feature",
  "properties": {
    "iso:country":"DE",
    "sg:address":"An der Hordelwiese 31",
    "sg:city":"Dortmund",
    "sg:phone":"+49 231/89960",
    "sg:postcode":"44329",
    "sg:province":"Nordrhein-Westfalen",
    "wof:name":"Heinz Seefeldt",
    "wof:placetype":"venue"
},
  "geometry": {"coordinates":[7.5122518539,51.5525016785],"type":"Point"}
}