{
  "type": "Feature",
  "properties": {
    "iso:country":"DE",
    "sg:address":"Ramsdorfer Str. 118",
    "sg:city":"Velen",
    "sg:phone":"+49 2863/1380",
    "sg:postcode":"46342",
    "sg:province":"Nordrhein-Westfalen",
    "wof:name":"Johannes Trepmann",
    "wof:placetype":"venue"
},
  "geometry": {"coordinates":[6.961233,51.893265],"type":"Point"}
}