{
  "type": "Feature",
  "properties": {
    "iso:country":"DE",
    "sg:address":"Schorberger Str. 48-52::",
    "sg:city":"Solingen",
    "sg:phone":"+49 4921/2652225",
    "sg:postcode":"42669",
    "sg:province":"Nordrhein-Westfalen",
    "wof:name":"Helmut Fielenbach",
    "wof:placetype":"venue"
},
  "geometry": {"coordinates":[7.027571,51.158112],"type":"Point"}
}