{
  "type": "Feature",
  "properties": {
    "iso:country":"DE",
    "sg:address":"Rorichmoorer Str. 35",
    "sg:city":"Moormerland",
    "sg:phone":"+49 4954/4606",
    "sg:postcode":"26802",
    "sg:province":"Niedersachsen",
    "wof:name":"Wilhelm Br\u00fcmmer",
    "wof:placetype":"venue"
},
  "geometry": {"coordinates":[7.467064,53.324814],"type":"Point"}
}