{
  "type": "Feature",
  "properties": {
    "iso:country":"DE",
    "sg:address":"Beusselstr. 44 N-Q",
    "sg:city":"Berlin",
    "sg:phone":"+49 4930/398900",
    "sg:postcode":"10553",
    "sg:province":"Berlin",
    "wof:name":"Peter Keuthmann Gmbh",
    "wof:placetype":"venue"
},
  "geometry": {"coordinates":[13.32015,52.528851],"type":"Point"}
}