{
  "type": "Feature",
  "properties": {
    "iso:country":"DE",
    "sg:address":"Kornstr. 7",
    "sg:city":"Tarmstedt",
    "sg:phone":"+49 4283/8613",
    "sg:postcode":"27412",
    "sg:province":"Niedersachsen",
    "wof:name":"Manfred Pilster",
    "wof:placetype":"venue"
},
  "geometry": {"coordinates":[9.086807,53.225796],"type":"Point"}
}