{
  "type": "Feature",
  "properties": {
    "iso:country":"DE",
    "sg:address":"Strehlhoferweg 41",
    "sg:city":"Volkach",
    "sg:postcode":"97332",
    "sg:province":"Bayern",
    "wof:name":"Devo Baumarkt",
    "wof:placetype":"venue"
},
  "geometry": {"coordinates":[10.2336101532,49.8611183167],"type":"Point"}
}