{
  "type": "Feature",
  "properties": {
    "iso:country":"DE",
    "sg:address":"R\u00f6merstr. 163",
    "sg:city":"Neuss",
    "sg:phone":"+49 2131/544469",
    "sg:postcode":"41462",
    "sg:province":"Nordrhein-Westfalen",
    "wof:name":"Karl-heinz Tillmann",
    "wof:placetype":"venue"
},
  "geometry": {"coordinates":[6.667145,51.223042],"type":"Point"}
}