{
  "type": "Feature",
  "properties": {
    "iso:country":"DE",
    "sg:address":"Beiertheimer Allee 19",
    "sg:city":"Karlsruhe",
    "sg:phone":"+49 721/357069",
    "sg:postcode":"76137",
    "sg:province":"Baden-W\u00fcrttemberg",
    "wof:name":"Fsw Fotosatz S\u00fcdwest Gmbh",
    "wof:placetype":"venue"
},
  "geometry": {"coordinates":[8.3982334137,49.0021591187],"type":"Point"}
}