{
  "type": "Feature",
  "properties": {
    "iso:country":"DE",
    "sg:address":"Marktstr. 5",
    "sg:city":"Bad M\u00fcnder",
    "sg:phone":"+49 5042/929343",
    "sg:postcode":"31848",
    "sg:province":"Niedersachsen",
    "wof:name":"Schuh Und Sport Fischer Gmbh",
    "wof:placetype":"venue"
},
  "geometry": {"coordinates":[9.46283,52.198071],"type":"Point"}
}