{
  "type": "Feature",
  "properties": {
    "iso:country":"DE",
    "sg:address":"Merseburger Str. 103",
    "sg:city":"Leipzig",
    "sg:phone":"+49 341/4774073",
    "sg:postcode":"04177",
    "sg:province":"Sachsen",
    "wof:name":"Dr. Andres Und Dr. Schneider Rechtsanw\u00e4lte",
    "wof:placetype":"venue"
},
  "geometry": {"coordinates":[12.3274593353,51.3371620178],"type":"Point"}
}