{
  "type": "Feature",
  "properties": {
    "iso:country":"DE",
    "sg:address":"Neckarsulmer Str. 18",
    "sg:city":"Neuenstadt",
    "sg:phone":"+49 7139/451000",
    "sg:postcode":"74196",
    "sg:province":"Baden-W\u00fcrttemberg",
    "wof:name":"Jan Lumpp",
    "wof:placetype":"venue"
},
  "geometry": {"coordinates":[9.3261203766,49.2354888916],"type":"Point"}
}