{
  "type": "Feature",
  "properties": {
    "iso:country":"DE",
    "sg:address":"M\u00fchlenstr. 59",
    "sg:city":"Bad Iburg",
    "sg:phone":"+49 5403/9665",
    "sg:postcode":"49186",
    "sg:province":"Niedersachsen",
    "wof:name":"Franz Rapp",
    "wof:placetype":"venue"
},
  "geometry": {"coordinates":[8.051839,52.151772],"type":"Point"}
}