{
  "type": "Feature",
  "properties": {
    "iso:country":"DE",
    "sg:address":"Riemenschneiderstr. 10",
    "sg:city":"Bonn",
    "sg:phone":"+49 228/810040",
    "sg:postcode":"53175",
    "sg:province":"Nordrhein-Westfalen",
    "wof:name":"Bundesverband Deutscher Zeitungsverleger",
    "wof:placetype":"venue"
},
  "geometry": {"coordinates":[7.140618,50.701389],"type":"Point"}
}