{
  "type": "Feature",
  "properties": {
    "iso:country":"DE",
    "sg:address":"Halbmondstr. 2",
    "sg:city":"Heilbronn",
    "sg:phone":"+49 7131/87273",
    "sg:postcode":"74072",
    "sg:province":"Baden-W\u00fcrttemberg",
    "wof:name":"Pip Werbeagentur",
    "wof:placetype":"venue"
},
  "geometry": {"coordinates":[9.213813,49.141151],"type":"Point"}
}