{
  "type": "Feature",
  "properties": {
    "iso:country":"DE",
    "sg:address":"Am Weiher 16",
    "sg:city":"Kreuzwertheim",
    "sg:phone":"+49 9342/59510",
    "sg:postcode":"97892",
    "sg:province":"Bayern",
    "wof:name":"Siegfried Rusnak Architekt",
    "wof:placetype":"venue"
},
  "geometry": {"coordinates":[9.524405,49.80204],"type":"Point"}
}