{
  "type": "Feature",
  "properties": {
    "iso:country":"DE",
    "sg:address":"Gro\u00dfe Schulstr. 23",
    "sg:city":"Genthin",
    "sg:phone":"+49 3933/2802",
    "sg:postcode":"39307",
    "sg:province":"Sachsen-Anhalt",
    "wof:name":"Chr. Heinzelmann",
    "wof:placetype":"venue"
},
  "geometry": {"coordinates":[12.1604547501,52.406791687],"type":"Point"}
}