{
  "type": "Feature",
  "properties": {
    "iso:country":"DE",
    "sg:address":"K\u00fcferstr. 1",
    "sg:city":"Baden-Baden",
    "sg:phone":"+49 7221/23836",
    "sg:postcode":"76530",
    "sg:province":"Baden-W\u00fcrttemberg",
    "wof:name":"K. Kneissler",
    "wof:placetype":"venue"
},
  "geometry": {"coordinates":[8.2389440536,48.7622528076],"type":"Point"}
}