{
  "type": "Feature",
  "properties": {
    "iso:country":"DE",
    "sg:address":"Berliner Str. 93",
    "sg:city":"Berlin",
    "sg:phone":"+49 30/4331221",
    "sg:postcode":"13507",
    "sg:province":"Berlin",
    "wof:name":"Thomas Pohl",
    "wof:placetype":"venue"
},
  "geometry": {"coordinates":[13.285441,52.588272],"type":"Point"}
}