{
  "type": "Feature",
  "properties": {
    "iso:country":"DE",
    "sg:address":"Wolfsgasse 13",
    "sg:city":"Schweinfurt",
    "sg:phone":"+49 9721/16871",
    "sg:postcode":"97421",
    "sg:province":"Bayern",
    "wof:name":"Margarete Volkmuth",
    "wof:placetype":"venue"
},
  "geometry": {"coordinates":[10.2293863297,50.0445709229],"type":"Point"}
}