{
  "type": "Feature",
  "properties": {
    "iso:country":"DE",
    "sg:address":"Christian-Lohse-Str. 9 b",
    "sg:city":"Itzehoe",
    "sg:phone":"+49 4821/82572",
    "sg:postcode":"25524",
    "sg:province":"Schleswig-Holstein",
    "wof:name":"Gastst\u00e4tte K.-h. Zimmer",
    "wof:placetype":"venue"
},
  "geometry": {"coordinates":[9.4950256348,53.9080047607],"type":"Point"}
}