{
  "type": "Feature",
  "properties": {
    "iso:country":"DE",
    "sg:address":"Postfach 1",
    "sg:city":"Nebra",
    "sg:phone":"+49 36377/4814",
    "sg:postcode":"06640",
    "sg:province":"Sachsen-Anhalt",
    "wof:name":"P. Gr\u00f6ning Anlageberater",
    "wof:placetype":"venue"
},
  "geometry": {"coordinates":[11.5772399902,51.2889785767],"type":"Point"}
}