{
  "type": "Feature",
  "properties": {
    "iso:country":"DE",
    "sg:address":"V\u00f6hlinstr. 5",
    "sg:city":"Illertissen",
    "sg:phone":"+49 7303/96460",
    "sg:postcode":"89257",
    "sg:province":"Bayern",
    "wof:name":"H. Fleischmann Papier- Und Schreibwaren",
    "wof:placetype":"venue"
},
  "geometry": {"coordinates":[10.108978,48.223171],"type":"Point"}
}