{
  "type": "Feature",
  "properties": {
    "iso:country":"DE",
    "sg:address":"Oldendorf 23",
    "sg:city":"Appel",
    "sg:phone":"+49 4165/80275",
    "sg:postcode":"21279",
    "sg:province":"Niedersachsen",
    "wof:name":"Mms Marine Motor Service Gmbh",
    "wof:placetype":"venue"
},
  "geometry": {"coordinates":[9.758913,53.38063],"type":"Point"}
}