{
  "type": "Feature",
  "properties": {
    "iso:country":"DE",
    "sg:address":"Ahornweg 2",
    "sg:city":"Erftstadt",
    "sg:phone":"+49 2235/42299",
    "sg:postcode":"50374",
    "sg:province":"Nordrhein-Westfalen",
    "wof:name":"R. Ennenga Textil Tradex Gmbh",
    "wof:placetype":"venue"
},
  "geometry": {"coordinates":[6.818118,50.810059],"type":"Point"}
}