{
  "type": "Feature",
  "properties": {
    "iso:country":"DE",
    "sg:address":"Neust\u00fcckweg 5",
    "sg:city":"Schifferstadt",
    "sg:phone":"+49 6235/2613",
    "sg:postcode":"67105",
    "sg:province":"Rheinland-Pfalz",
    "wof:name":"Verein Der Ruandafreunde Schifferstadt",
    "wof:placetype":"venue"
},
  "geometry": {"coordinates":[8.3731555939,49.3720932007],"type":"Point"}
}