{
  "type": "Feature",
  "properties": {
    "iso:country":"DE",
    "sg:address":"Moorhoffstr. 16",
    "sg:city":"Hannover",
    "sg:phone":"+49 511/797485",
    "sg:postcode":"30419",
    "sg:province":"Niedersachsen",
    "wof:name":"I. Baytekin",
    "wof:placetype":"venue"
},
  "geometry": {"coordinates":[9.659160614,52.4081115723],"type":"Point"}
}