{
  "type": "Feature",
  "properties": {
    "iso:country":"DE",
    "sg:address":"Hauptstr. 53",
    "sg:city":"Asbach",
    "sg:phone":"+49 2683/949000",
    "sg:postcode":"53567",
    "sg:province":"Rheinland-Pfalz",
    "wof:name":"A. Fahnenbruck Rechtsanwalt",
    "wof:placetype":"venue"
},
  "geometry": {"coordinates":[7.4261641502,50.6662940979],"type":"Point"}
}