{
  "type": "Feature",
  "properties": {
    "iso:country":"DE",
    "sg:address":"Dominikus-K\u00e4ser-Str. 27",
    "sg:city":"Allershausen",
    "sg:phone":"+49 8166/7831",
    "sg:postcode":"85391",
    "sg:province":"Bayern",
    "wof:name":"Walter U. Rita Sch\u00f6necker",
    "wof:placetype":"venue"
},
  "geometry": {"coordinates":[11.5957269669,48.435962677],"type":"Point"}
}