{
  "type": "Feature",
  "properties": {
    "iso:country":"DE",
    "sg:address":"Bargstedgasse 7",
    "sg:city":"Hamburg",
    "sg:postcode":"20539",
    "sg:province":"Hamburg",
    "wof:name":"Haak - Kooperative Hamburg Anatolisch Alevitische",
    "wof:placetype":"venue"
},
  "geometry": {"coordinates":[10.0507640839,53.5412445068],"type":"Point"}
}