{
  "type": "Feature",
  "properties": {
    "iso:country":"DE",
    "sg:address":"Gans\u00e4cker 13",
    "sg:city":"Bietigheim-Bissingen",
    "sg:phone":"+49 7142/55707",
    "sg:postcode":"74321",
    "sg:province":"Baden-W\u00fcrttemberg",
    "wof:name":"Universal Technik-service Gmbh",
    "wof:placetype":"venue"
},
  "geometry": {"coordinates":[9.1413793564,48.9393692017],"type":"Point"}
}