{
  "type": "Feature",
  "properties": {
    "iso:country":"DE",
    "sg:address":"M\u00fcnchener Str. 2",
    "sg:city":"Aying",
    "sg:phone":"+49 8095/1345",
    "sg:postcode":"85653",
    "sg:province":"Bayern",
    "wof:name":"Liebharts Br\u00e4ust\u00fcberl",
    "wof:placetype":"venue"
},
  "geometry": {"coordinates":[11.7798376083,47.9708518982],"type":"Point"}
}