{
  "type": "Feature",
  "properties": {
    "iso:country":"DE",
    "sg:address":"M\u00fcnsterstr. 85",
    "sg:city":"Dortmund",
    "sg:phone":"+49 231/811627",
    "sg:postcode":"44145",
    "sg:province":"Nordrhein-Westfalen",
    "wof:name":"S. Saikka",
    "wof:placetype":"venue"
},
  "geometry": {"coordinates":[7.45623,51.532909],"type":"Point"}
}