{
  "type": "Feature",
  "properties": {
    "iso:country":"DE",
    "sg:address":"Friedhofsallee 28",
    "sg:city":"Coesfeld",
    "sg:phone":"+49 2541/82472",
    "sg:postcode":"48653",
    "sg:province":"Nordrhein-Westfalen",
    "wof:name":"G\u00fcnter Lammers",
    "wof:placetype":"venue"
},
  "geometry": {"coordinates":[7.1577868462,51.939201355],"type":"Point"}
}