{
  "type": "Feature",
  "properties": {
    "iso:country":"DE",
    "sg:address":"Hildburgh\u00e4user Str. 22",
    "sg:city":"Eisfeld",
    "sg:phone":"+49 3686/300727",
    "sg:postcode":"98673",
    "sg:province":"Th\u00fcringen",
    "wof:name":"Wohnheim F\u00fcr Behinderte",
    "wof:placetype":"venue"
},
  "geometry": {"coordinates":[10.9006242752,50.4257583618],"type":"Point"}
}