{
  "type": "Feature",
  "properties": {
    "iso:country":"DE",
    "sg:address":"Hower Hauptdeich 7",
    "sg:city":"Hamburg",
    "sg:phone":"+49 40/7237240",
    "sg:postcode":"21037",
    "sg:province":"Hamburg",
    "wof:name":"Hotel Vierlandentor",
    "wof:placetype":"venue"
},
  "geometry": {"coordinates":[10.149310112,53.4152297974],"type":"Point"}
}