{
  "type": "Feature",
  "properties": {
    "iso:country":"DE",
    "sg:address":"Kapellenstr. 12",
    "sg:city":"Kell",
    "sg:postcode":"54427",
    "sg:province":"Rheinland-Pfalz",
    "wof:name":"Hochwald-t\u00fcrenwerk Josef Haag Kg",
    "wof:placetype":"venue"
},
  "geometry": {"coordinates":[6.8291101456,49.6341629028],"type":"Point"}
}