{
  "type": "Feature",
  "properties": {
    "iso:country":"DE",
    "sg:address":"Lindwurmstr 44",
    "sg:city":"M\u00fcnchen",
    "sg:phone":"+49 89/7673650",
    "sg:postcode":"80337",
    "sg:province":"Bayern",
    "wof:name":"Egg And Dart Design Cooperation Gmbh & Co Kg",
    "wof:placetype":"venue"
},
  "geometry": {"coordinates":[11.55477,48.127964],"type":"Point"}
}