{
  "type": "Feature",
  "properties": {
    "iso:country":"DE",
    "sg:address":"Otto-Hahn-Str. 28-30",
    "sg:city":"Ottobrunn",
    "sg:phone":"+49 89/6145200",
    "sg:postcode":"85521",
    "sg:province":"Bayern",
    "wof:name":"Concito Gesellschaft F\u00dcr Unternehmensentwicklung Mbh",
    "wof:placetype":"venue"
},
  "geometry": {"coordinates":[11.66213,48.063606],"type":"Point"}
}