{
  "type": "Feature",
  "properties": {
    "iso:country":"DE",
    "sg:address":"Entenbachstr. 3",
    "sg:city":"Riederich",
    "sg:phone":"+49 7123/932883",
    "sg:postcode":"72585",
    "sg:province":"Baden-W\u00fcrttemberg",
    "wof:name":"F. Auer Ingenieur",
    "wof:placetype":"venue"
},
  "geometry": {"coordinates":[9.2676553726,48.5586853027],"type":"Point"}
}