{
  "type": "Feature",
  "properties": {
    "iso:country":"DE",
    "sg:address":"Erbsenstr. 4",
    "sg:city":"Maintal",
    "sg:phone":"+49 6181/840027",
    "sg:postcode":"63477",
    "sg:province":"Hessen",
    "wof:name":"T. Soukop Immobilienmakler",
    "wof:placetype":"venue"
},
  "geometry": {"coordinates":[8.8585557938,50.1692276001],"type":"Point"}
}