{
  "type": "Feature",
  "properties": {
    "iso:country":"DE",
    "sg:address":"Feuerbachstr. 9",
    "sg:city":"Halle",
    "sg:phone":"+49 345/5224305",
    "sg:postcode":"06114",
    "sg:province":"Sachsen-Anhalt",
    "wof:name":"Hans Trog Gmbh",
    "wof:placetype":"venue"
},
  "geometry": {"coordinates":[11.9671201706,51.4992637634],"type":"Point"}
}