{
  "type": "Feature",
  "properties": {
    "iso:country":"DE",
    "sg:address":"Eberwurzstr. 112",
    "sg:city":"M\u00fcnchen",
    "sg:phone":"+49 89/3141755",
    "sg:postcode":"80935",
    "sg:province":"Bayern",
    "wof:name":"Georg Griesmaier",
    "wof:placetype":"venue"
},
  "geometry": {"coordinates":[11.553691,48.202942],"type":"Point"}
}