{
  "type": "Feature",
  "properties": {
    "iso:country":"DE",
    "sg:address":"Ackerwinde 20",
    "sg:city":"K\u00f6ln",
    "sg:postcode":"50858",
    "sg:province":"Nordrhein-Westfalen",
    "wof:name":"Mdt Mediatel Beteiligungs Gmbh",
    "wof:placetype":"venue"
},
  "geometry": {"coordinates":[6.85835,50.933788],"type":"Point"}
}