{
  "type": "Feature",
  "properties": {
    "iso:country":"DE",
    "sg:address":"Schie\u00dfgartenstr. 5",
    "sg:city":"Dreieich",
    "sg:phone":"+49 6103/984848",
    "sg:postcode":"63303",
    "sg:province":"Hessen",
    "wof:name":"Goc Gesellschaft F\u00fcr Optische Communication Mbh",
    "wof:placetype":"venue"
},
  "geometry": {"coordinates":[8.7375593185,49.9978141785],"type":"Point"}
}