{
  "type": "Feature",
  "properties": {
    "iso:country":"DE",
    "sg:address":"Blockhausstr. 10",
    "sg:city":"Reichshof",
    "sg:phone":"+49 2265/99250",
    "sg:postcode":"51580",
    "sg:province":"Nordrhein-Westfalen",
    "wof:name":"Hotel Aggerberg Inh. R. Und M. Dick",
    "wof:placetype":"venue"
},
  "geometry": {"coordinates":[7.696644783,50.9878463745],"type":"Point"}
}