{
  "type": "Feature",
  "properties": {
    "iso:country":"DE",
    "sg:address":"K\u00f6nigstr. 154",
    "sg:city":"Kaiserslautern",
    "sg:phone":"+49 631/2003870",
    "sg:postcode":"67655",
    "sg:province":"Rheinland-Pfalz",
    "wof:name":"Quick-rotan Elektromotoren Gmbh",
    "wof:placetype":"venue"
},
  "geometry": {"coordinates":[7.75343,49.435555],"type":"Point"}
}