{
  "type": "Feature",
  "properties": {
    "iso:country":"DE",
    "sg:address":"Kieler Str. 84",
    "sg:city":"Hohenlockstedt",
    "sg:phone":"+49 4826/2306",
    "sg:postcode":"25551",
    "sg:province":"Schleswig-Holstein",
    "wof:name":"H. Billerbeck",
    "wof:placetype":"venue"
},
  "geometry": {"coordinates":[9.6222743988,53.9649009705],"type":"Point"}
}