{
  "type": "Feature",
  "properties": {
    "iso:country":"DE",
    "sg:address":"Borgfelder Str. 36",
    "sg:city":"Hamburg",
    "sg:phone":"+49 4921/098287",
    "sg:postcode":"20537",
    "sg:province":"Hamburg",
    "wof:name":"Qcmx, Internet Provider Und Redaktions-tool",
    "wof:placetype":"venue"
},
  "geometry": {"coordinates":[10.032524,53.55452],"type":"Point"}
}