{
  "type": "Feature",
  "properties": {
    "iso:country":"DE",
    "sg:address":"Am Zeller Pfad 1",
    "sg:city":"Neuhausen",
    "sg:phone":"+49 4972/349400",
    "sg:postcode":"75242",
    "sg:province":"Baden-W\u00fcrttemberg",
    "wof:name":"Klaschka Gmbh & Co.",
    "wof:placetype":"venue"
},
  "geometry": {"coordinates":[8.766856,48.792294],"type":"Point"}
}