{
  "type": "Feature",
  "properties": {
    "iso:country":"DE",
    "sg:address":"Helmweg 6",
    "sg:city":"Sexten S\u00fcdtirol",
    "sg:postcode":"39030",
    "wof:name":"Drei Zinnen Dolomiten S\u00fcdtirol Italien",
    "wof:placetype":"venue"
},
  "geometry": {"coordinates":[12.373263,46.69363],"type":"Point"}
}