{
  "type": "Feature",
  "properties": {
    "iso:country":"DE",
    "sg:address":"Schlo\u00dfbergstr. 25",
    "sg:city":"Murnau",
    "sg:phone":"+49 8841/9471",
    "sg:postcode":"82418",
    "sg:province":"Bayern",
    "wof:name":"Franz Fischer Jun.",
    "wof:placetype":"venue"
},
  "geometry": {"coordinates":[11.204665,47.67738],"type":"Point"}
}