{
  "type": "Feature",
  "properties": {
    "iso:country":"DE",
    "sg:address":"Zum Blasius 2u 4",
    "sg:city":"Winterberg",
    "sg:phone":"+49 2983/777",
    "sg:postcode":"59955",
    "sg:province":"Nordrhein-Westfalen",
    "wof:name":"Winterberger Holzmanufaktur Gmbh",
    "wof:placetype":"venue"
},
  "geometry": {"coordinates":[8.488203,51.239082],"type":"Point"}
}