{
  "type": "Feature",
  "properties": {
    "iso:country":"DE",
    "sg:address":"Am Kreuter 1",
    "sg:city":"Bonn",
    "sg:phone":"+49 228/354045",
    "sg:postcode":"53177",
    "sg:province":"Nordrhein-Westfalen",
    "wof:name":"Botschaft Von Jamaika",
    "wof:placetype":"venue"
},
  "geometry": {"coordinates":[7.153881073,50.677734375],"type":"Point"}
}