{
  "type": "Feature",
  "properties": {
    "iso:country":"DE",
    "sg:address":"Sindorf 9 1/2",
    "sg:city":"Arnbruck",
    "sg:phone":"+49 9945/870",
    "sg:postcode":"93471",
    "sg:province":"Bayern",
    "wof:name":"G\u00e4stehaus-pension Maria Kaeser",
    "wof:placetype":"venue"
},
  "geometry": {"coordinates":[12.9971532822,49.1294250488],"type":"Point"}
}