{
  "type": "Feature",
  "properties": {
    "iso:country":"DE",
    "sg:address":"Aacher Str. 13",
    "sg:city":"Glatten",
    "sg:phone":"+49 4974/436889",
    "sg:postcode":"72293",
    "sg:province":"Baden-W\u00fcrttemberg",
    "wof:name":"Weinl\u00c4der Polsterm\u00d6bel Gmbh",
    "wof:placetype":"venue"
},
  "geometry": {"coordinates":[8.5089702606,48.4468460083],"type":"Point"}
}