{
  "type": "Feature",
  "properties": {
    "iso:country":"DE",
    "sg:address":"Hoher Heckenweg 99",
    "sg:city":"M\u00fcnster",
    "sg:phone":"+49 251/233598",
    "sg:postcode":"48147",
    "sg:province":"Nordrhein-Westfalen",
    "wof:name":"Bergmann Textilpflege",
    "wof:placetype":"venue"
},
  "geometry": {"coordinates":[7.64642,51.983639],"type":"Point"}
}