{
  "type": "Feature",
  "properties": {
    "iso:country":"DE",
    "sg:address":"Schulstr. 17",
    "sg:city":"Ostrhauderfehn",
    "sg:phone":"+49 4952/5519",
    "sg:postcode":"26842",
    "sg:province":"Niedersachsen",
    "wof:name":"Hermann D\u00fcring",
    "wof:placetype":"venue"
},
  "geometry": {"coordinates":[7.60957,53.151184],"type":"Point"}
}