{
  "type": "Feature",
  "properties": {
    "iso:country":"DE",
    "sg:address":"Mozartstr. 2",
    "sg:city":"K\u00f6ngen",
    "sg:phone":"+49 7024/80628",
    "sg:postcode":"73257",
    "sg:province":"Baden-W\u00fcrttemberg",
    "wof:name":"Helmut Flaig",
    "wof:placetype":"venue"
},
  "geometry": {"coordinates":[9.3579397202,48.6756324768],"type":"Point"}
}