{
  "type": "Feature",
  "properties": {
    "iso:country":"DE",
    "sg:address":"Graf-Wilhelm-Str. 20",
    "sg:city":"Wunstorf",
    "sg:phone":"+49 5033/911792",
    "sg:postcode":"31515",
    "sg:province":"Niedersachsen",
    "wof:name":"Hans Wach",
    "wof:placetype":"venue"
},
  "geometry": {"coordinates":[9.353403,52.454018],"type":"Point"}
}