{
  "type": "Feature",
  "properties": {
    "iso:country":"DE",
    "sg:address":"Zuckerbergweg 42",
    "sg:city":"Braunschweig",
    "sg:phone":"+49 531/693385",
    "sg:postcode":"38124",
    "sg:province":"Niedersachsen",
    "wof:name":"Nieders\u00e4chsische Bau Gmbh",
    "wof:placetype":"venue"
},
  "geometry": {"coordinates":[10.5310268402,52.241153717],"type":"Point"}
}