{
  "type": "Feature",
  "properties": {
    "iso:country":"DE",
    "sg:address":"Kiefernweg 1",
    "sg:city":"Marburg",
    "sg:phone":"+49 6424/5643",
    "sg:postcode":"35043",
    "sg:province":"Hessen",
    "wof:name":"Peter Riehl",
    "wof:placetype":"venue"
},
  "geometry": {"coordinates":[8.820911,50.771408],"type":"Point"}
}