{
  "type": "Feature",
  "properties": {
    "iso:country":"DE",
    "sg:address":"Hochh\u00e4user Str. 59",
    "sg:city":"Obrigheim",
    "sg:phone":"+49 4962/6197100",
    "sg:postcode":"74847",
    "sg:province":"Baden-W\u00fcrttemberg",
    "wof:name":"Arco Armaturenfabrik Obrigheim Gmbh & Co",
    "wof:placetype":"venue"
},
  "geometry": {"coordinates":[9.0957098007,49.34923172],"type":"Point"}
}