{
  "type": "Feature",
  "properties": {
    "iso:country":"DE",
    "sg:address":"Eckenheimer Landstr. 449",
    "sg:city":"Frankfurt",
    "sg:postcode":"60435",
    "sg:province":"Hessen",
    "wof:name":"Pmc Gmbh",
    "wof:placetype":"venue"
},
  "geometry": {"coordinates":[8.681930542,50.1475601196],"type":"Point"}
}