{
  "type": "Feature",
  "properties": {
    "iso:country":"DE",
    "sg:address":"Reschbachstr. 2",
    "sg:city":"Mauth",
    "sg:phone":"+49 8557/272",
    "sg:postcode":"94151",
    "sg:province":"Bayern",
    "wof:name":"G\u00fcnter Allesch Steinmetz",
    "wof:placetype":"venue"
},
  "geometry": {"coordinates":[13.5833625793,48.8870353699],"type":"Point"}
}