{
  "type": "Feature",
  "properties": {
    "iso:country":"DE",
    "sg:address":"Blauer Weg 76",
    "sg:city":"Weinstadt",
    "sg:phone":"+49 7151/74638",
    "sg:postcode":"71384",
    "sg:province":"Baden-W\u00fcrttemberg",
    "wof:name":"Da-capo Handelsgesellschaft",
    "wof:placetype":"venue"
},
  "geometry": {"coordinates":[9.419515,48.804672],"type":"Point"}
}