{
  "type": "Feature",
  "properties": {
    "iso:country":"DE",
    "sg:address":"Oppelner Str. 19",
    "sg:city":"M\u00f6nchengladbach",
    "sg:postcode":"41199",
    "sg:province":"Nordrhein-Westfalen",
    "wof:name":"Hans-josef Wefels Kunst- Und Bauschlosserei",
    "wof:placetype":"venue"
},
  "geometry": {"coordinates":[6.4447221756,51.1229248047],"type":"Point"}
}