{
  "type": "Feature",
  "properties": {
    "iso:country":"DE",
    "sg:address":"Parkallee 44",
    "sg:city":"Bremen",
    "sg:postcode":"28209",
    "sg:province":"Bremen",
    "wof:name":"Schalk Beteiligungs-gmbh",
    "wof:placetype":"venue"
},
  "geometry": {"coordinates":[8.823667,53.083755],"type":"Point"}
}