{
  "type": "Feature",
  "properties": {
    "iso:country":"DE",
    "sg:address":"Prager Str. 85",
    "sg:city":"Bremerhaven",
    "sg:phone":"+49 471/40206",
    "sg:postcode":"27568",
    "sg:province":"Bremen",
    "wof:name":"Prager St\u00fcbchen",
    "wof:placetype":"venue"
},
  "geometry": {"coordinates":[8.5790538788,53.5462341309],"type":"Point"}
}