{
  "type": "Feature",
  "properties": {
    "iso:country":"DE",
    "sg:address":"Hauptstr. 32",
    "sg:city":"Bergneustadt",
    "sg:phone":"+49 2261/43714",
    "sg:postcode":"51702",
    "sg:province":"Nordrhein-Westfalen",
    "wof:name":"Restaurant Zur Burg",
    "wof:placetype":"venue"
},
  "geometry": {"coordinates":[7.6495480537,51.0226135254],"type":"Point"}
}