{
  "type": "Feature",
  "properties": {
    "iso:country":"DE",
    "sg:address":"Wiesenweg 4",
    "sg:city":"Emskirchen",
    "sg:phone":"+49 9104/667",
    "sg:postcode":"91448",
    "sg:province":"Bayern",
    "wof:name":"Kurt K\u00e4\u00dfler Architekt",
    "wof:placetype":"venue"
},
  "geometry": {"coordinates":[10.715394,49.551258],"type":"Point"}
}