{
  "type": "Feature",
  "properties": {
    "iso:country":"DE",
    "sg:address":"Plattenweg 3 a",
    "sg:city":"H\u00f6xter",
    "sg:phone":"+49 5271/38751",
    "sg:postcode":"37671",
    "sg:province":"Nordrhein-Westfalen",
    "wof:name":"M. Windel",
    "wof:placetype":"venue"
},
  "geometry": {"coordinates":[9.427269,51.793034],"type":"Point"}
}