{
  "type": "Feature",
  "properties": {
    "iso:country":"DE",
    "sg:address":"Liebfrauenweg 14",
    "sg:city":"Berlin",
    "sg:phone":"+49 30/4331648",
    "sg:postcode":"13509",
    "sg:province":"Berlin",
    "wof:name":"Klaus Gr\u00e4wert",
    "wof:placetype":"venue"
},
  "geometry": {"coordinates":[13.295958,52.598991],"type":"Point"}
}