{
  "type": "Feature",
  "properties": {
    "iso:country":"DE",
    "sg:address":"Weinstr. 2",
    "sg:city":"Deidesheim",
    "sg:phone":"+49 6326/8590",
    "sg:postcode":"67146",
    "sg:province":"Rheinland-Pfalz",
    "wof:name":"Karlheinz Seiter Architekt",
    "wof:placetype":"venue"
},
  "geometry": {"coordinates":[8.189224,49.411613],"type":"Point"}
}