{
  "type": "Feature",
  "properties": {
    "iso:country":"DE",
    "sg:address":"Ke\u00dfeldorfer Rott 16",
    "sg:city":"Hamminkeln",
    "sg:phone":"+49 4928/5296300",
    "sg:postcode":"46499",
    "sg:province":"Nordrhein-Westfalen",
    "wof:name":"Leuchten & Apparatebau Gmbh Hamminkeln",
    "wof:placetype":"venue"
},
  "geometry": {"coordinates":[6.588763,51.74387],"type":"Point"}
}