{
  "type": "Feature",
  "properties": {
    "iso:country":"DE",
    "sg:address":"Am Michelskopf 4",
    "sg:city":"Edertal",
    "sg:phone":"+49 5623/4842",
    "sg:postcode":"34549",
    "sg:province":"Hessen",
    "wof:name":"Willi Stiebel",
    "wof:placetype":"venue"
},
  "geometry": {"coordinates":[9.0843143463,51.1813964844],"type":"Point"}
}