{
  "type": "Feature",
  "properties": {
    "iso:country":"DE",
    "sg:address":"Kirchplatz 12",
    "sg:city":"Steinhagen",
    "sg:phone":"+49 5204/8180",
    "sg:postcode":"33803",
    "sg:province":"Nordrhein-Westfalen",
    "wof:name":"A. Mennecke",
    "wof:placetype":"venue"
},
  "geometry": {"coordinates":[8.413781,52.006027],"type":"Point"}
}