{
  "type": "Feature",
  "properties": {
    "iso:country":"DE",
    "sg:address":"Drubbel 4",
    "sg:city":"M\u00fcnster",
    "sg:phone":"+49 251/44332",
    "sg:postcode":"48143",
    "sg:province":"Nordrhein-Westfalen",
    "wof:name":"Betten-bisping Gmbh",
    "wof:placetype":"venue"
},
  "geometry": {"coordinates":[7.6280817986,51.9631843567],"type":"Point"}
}