{
  "type": "Feature",
  "properties": {
    "iso:country":"DE",
    "sg:address":"88339",
    "sg:city":"Bad Waldsee",
    "sg:phone":"+49 7524/3404",
    "sg:postcode":"88339",
    "sg:province":"Baden-W\u00fcrttemberg",
    "wof:name":"Brunnenst\u00fcble",
    "wof:placetype":"venue"
},
  "geometry": {"coordinates":[9.7507095337,47.9180107117],"type":"Point"}
}