{
  "type": "Feature",
  "properties": {
    "iso:country":"DE",
    "sg:address":"Birkenweg 2",
    "sg:city":"Libbenichen",
    "sg:postcode":"15306",
    "sg:province":"Brandenburg",
    "wof:name":"Ergo Versicherungsgruppe Ag",
    "wof:placetype":"venue"
},
  "geometry": {"coordinates":[14.4386796951,52.476852417],"type":"Point"}
}