{
  "type": "Feature",
  "properties": {
    "iso:country":"DE",
    "sg:address":"Kampstr. 17",
    "sg:city":"L\u00f6hne",
    "sg:phone":"+49 5731/83638",
    "sg:postcode":"32584",
    "sg:province":"Nordrhein-Westfalen",
    "wof:name":"Limes Zaun- Und Sportst\u00e4ttenbau",
    "wof:placetype":"venue"
},
  "geometry": {"coordinates":[8.7636327744,52.2041549683],"type":"Point"}
}