{
  "type": "Feature",
  "properties": {
    "iso:country":"DE",
    "sg:address":"Koblenzer Str. 28",
    "sg:city":"Koblenz",
    "sg:phone":"+49 261/42333",
    "sg:postcode":"56073",
    "sg:province":"Rheinland-Pfalz",
    "wof:name":"Hermann Preusser",
    "wof:placetype":"venue"
},
  "geometry": {"coordinates":[7.559736,50.351616],"type":"Point"}
}