{
  "type": "Feature",
  "properties": {
    "iso:country":"DE",
    "sg:address":"Wachstedter Str. 7",
    "sg:city":"K\u00fcllstedt",
    "sg:phone":"+49 36075/64370",
    "sg:postcode":"37359",
    "sg:province":"Th\u00fcringen",
    "wof:name":"Matthias Hillmann",
    "wof:placetype":"venue"
},
  "geometry": {"coordinates":[10.275023,51.277847],"type":"Point"}
}