{
  "type": "Feature",
  "properties": {
    "iso:country":"DE",
    "sg:address":"Rheinuferstr.",
    "sg:city":"R\u00fcdesheim am Rhein",
    "sg:phone":"+49 6722/3808",
    "sg:postcode":"65385",
    "sg:province":"Hessen",
    "wof:name":"K\u00f6ln-d\u00fcsseldorfer Deutsche Rheinschiffahrt Ag",
    "wof:placetype":"venue"
},
  "geometry": {"coordinates":[7.865598,49.987236],"type":"Point"}
}