{
  "type": "Feature",
  "properties": {
    "iso:country":"DE",
    "sg:address":"Unterm Ettersberg 1",
    "sg:city":"Weimar",
    "sg:phone":"+49 3643/422424",
    "sg:postcode":"99427",
    "sg:province":"Th\u00fcringen",
    "wof:name":"M. Wermuth",
    "wof:placetype":"venue"
},
  "geometry": {"coordinates":[11.333654,51.015049],"type":"Point"}
}