{
  "type": "Feature",
  "properties": {
    "iso:country":"DE",
    "sg:address":"Niebuhrstr. 11 a",
    "sg:city":"Berlin",
    "sg:phone":"+49 30/3245541",
    "sg:postcode":"10629",
    "sg:province":"Berlin",
    "wof:name":"Renate Alpern",
    "wof:placetype":"venue"
},
  "geometry": {"coordinates":[13.313997,52.504524],"type":"Point"}
}