{
  "type": "Feature",
  "properties": {
    "iso:country":"DE",
    "sg:address":"Ockerweg 3",
    "sg:city":"Gie\u00dfen",
    "sg:phone":"+49 4964/15070",
    "sg:postcode":"35396",
    "sg:province":"Hessen",
    "wof:name":"Mettler-toledo Gmbh",
    "wof:placetype":"venue"
},
  "geometry": {"coordinates":[8.704392,50.612572],"type":"Point"}
}