{
  "type": "Feature",
  "properties": {
    "iso:country":"DE",
    "sg:address":"Bahnstr. 50",
    "sg:city":"D\u00fcsseldorf",
    "sg:phone":"+49 211/324663",
    "sg:postcode":"40210",
    "sg:province":"Nordrhein-Westfalen",
    "wof:name":"Francesco Pedace",
    "wof:placetype":"venue"
},
  "geometry": {"coordinates":[6.7833590508,51.2198638916],"type":"Point"}
}