{
  "type": "Feature",
  "properties": {
    "iso:country":"DE",
    "sg:address":"Hauptstr. 8 b",
    "sg:city":"Taubenheim",
    "sg:phone":"+49 35245/71377",
    "sg:postcode":"01665",
    "sg:province":"Sachsen",
    "wof:name":"Stella Verwaltungs- Und Planungs Gmbh",
    "wof:placetype":"venue"
},
  "geometry": {"coordinates":[13.4737176895,51.0976257324],"type":"Point"}
}