{
  "type": "Feature",
  "properties": {
    "iso:country":"DE",
    "sg:address":"Neuenberger Str. 57",
    "sg:city":"Fulda",
    "sg:phone":"+49 661/902650",
    "sg:postcode":"36041",
    "sg:province":"Hessen",
    "wof:name":"Martin Keller Kg",
    "wof:placetype":"venue"
},
  "geometry": {"coordinates":[9.6618041992,50.5455741882],"type":"Point"}
}