{
  "type": "Feature",
  "properties": {
    "iso:country":"DE",
    "sg:address":"Heidenheimer Str. 21",
    "sg:city":"Oberkochen",
    "sg:phone":"+49 7364/919288",
    "sg:postcode":"73447",
    "sg:province":"Baden-W\u00fcrttemberg",
    "wof:name":"Manfred Kaufmann",
    "wof:placetype":"venue"
},
  "geometry": {"coordinates":[10.1050491333,48.7827033997],"type":"Point"}
}