{
  "type": "Feature",
  "properties": {
    "iso:country":"DE",
    "sg:address":"Steinlachwasen 5",
    "sg:city":"T\u00fcbingen",
    "sg:phone":"+49 7071/73444",
    "sg:postcode":"72072",
    "sg:province":"Baden-W\u00fcrttemberg",
    "wof:name":"Gerhard Halbritter Bildhauer",
    "wof:placetype":"venue"
},
  "geometry": {"coordinates":[9.06672,48.487671],"type":"Point"}
}