{
  "type": "Feature",
  "properties": {
    "iso:country":"DE",
    "sg:address":"Hasselsstr. 62a",
    "sg:city":"D\u00fcsseldorf",
    "sg:phone":"+49 211/7480293",
    "sg:postcode":"40599",
    "sg:province":"Nordrhein-Westfalen",
    "wof:name":"Restaurant Hasseler-fass",
    "wof:placetype":"venue"
},
  "geometry": {"coordinates":[6.8709058762,51.175819397],"type":"Point"}
}