{
  "type": "Feature",
  "properties": {
    "iso:country":"DE",
    "sg:address":"Sonnenstr. 39",
    "sg:city":"Hohenstein-Ernstthal",
    "sg:postcode":"09337",
    "sg:province":"Sachsen",
    "wof:name":"Tur Transporte",
    "wof:placetype":"venue"
},
  "geometry": {"coordinates":[12.728972435,50.7976226807],"type":"Point"}
}