{
  "type": "Feature",
  "properties": {
    "iso:country":"DE",
    "sg:address":"Pettenkoferstr. 10b",
    "sg:city":"Augsburg",
    "sg:phone":"+49 821/515516",
    "sg:postcode":"86152",
    "sg:province":"Bayern",
    "wof:name":"H. Rothmayr",
    "wof:placetype":"venue"
},
  "geometry": {"coordinates":[10.8967733383,48.3778915405],"type":"Point"}
}