{
  "type": "Feature",
  "properties": {
    "iso:country":"DE",
    "sg:address":"Ablacher Str. 14",
    "sg:city":"Sigmaringen",
    "sg:phone":"+49 4975/7152099",
    "sg:postcode":"72488",
    "sg:province":"Baden-W\u00fcrttemberg",
    "wof:name":"Ekf Gnirrs Gmbh & Co. Kg",
    "wof:placetype":"venue"
},
  "geometry": {"coordinates":[9.194475,48.073639],"type":"Point"}
}