{
  "type": "Feature",
  "properties": {
    "iso:country":"DE",
    "sg:address":"Zewener Str. 21",
    "sg:city":"Trier",
    "sg:phone":"+49 651/85843",
    "sg:postcode":"54294",
    "sg:province":"Rheinland-Pfalz",
    "wof:name":"H. Scholten",
    "wof:placetype":"venue"
},
  "geometry": {"coordinates":[6.5830450058,49.7199440002],"type":"Point"}
}