{
  "type": "Feature",
  "properties": {
    "iso:country":"DE",
    "sg:address":"Am Hang 2",
    "sg:city":"Witten",
    "sg:phone":"+49 2302/60105",
    "sg:postcode":"58453",
    "sg:province":"Nordrhein-Westfalen",
    "wof:name":"H. Waning M\u00fchle",
    "wof:placetype":"venue"
},
  "geometry": {"coordinates":[7.3793878555,51.4451713562],"type":"Point"}
}