{
  "type": "Feature",
  "properties": {
    "iso:country":"DE",
    "sg:address":"Trogerstr. 48",
    "sg:city":"M\u00fcnchen",
    "sg:phone":"+49 89/4701089",
    "sg:postcode":"81675",
    "sg:province":"Bayern",
    "wof:name":"Janusz-modellboutique Inh. Janusz Szajer",
    "wof:placetype":"venue"
},
  "geometry": {"coordinates":[11.601651,48.140675],"type":"Point"}
}