{
  "type": "Feature",
  "properties": {
    "iso:country":"DE",
    "sg:address":"Am Sonnenblick 27",
    "sg:city":"Werda",
    "sg:phone":"+49 3745/71817",
    "sg:postcode":"08223",
    "sg:province":"Sachsen",
    "wof:name":"R. Neumann Architekt",
    "wof:placetype":"venue"
},
  "geometry": {"coordinates":[12.303025,50.442764],"type":"Point"}
}