{
  "type": "Feature",
  "properties": {
    "iso:country":"DE",
    "sg:address":"Paul-Singer-Str. 11d",
    "sg:city":"Bremen",
    "sg:phone":"+49 421/462184",
    "sg:postcode":"28329",
    "sg:province":"Bremen",
    "wof:name":"J\u00fcrgen Starke Drogerie",
    "wof:placetype":"venue"
},
  "geometry": {"coordinates":[8.8899,53.080204],"type":"Point"}
}