{
  "type": "Feature",
  "properties": {
    "iso:country":"DE",
    "sg:address":"Rue\u00dfstr.",
    "sg:city":"M\u00fcnchen",
    "sg:postcode":"80997",
    "sg:province":"Bayern",
    "wof:name":"Dolbau Gmbh",
    "wof:placetype":"venue"
},
  "geometry": {"coordinates":[11.4733695984,48.184753418],"type":"Point"}
}