{
  "type": "Feature",
  "properties": {
    "iso:country":"DE",
    "sg:address":"Lorscher Strasse 42",
    "sg:city":"Viernheim",
    "sg:phone":"+49 6204/76399",
    "sg:postcode":"68519",
    "sg:province":"Hessen",
    "wof:name":"Uni Mannheim",
    "wof:placetype":"venue"
},
  "geometry": {"coordinates":[8.577431,49.542431],"type":"Point"}
}