{
  "type": "Feature",
  "properties": {
    "iso:country":"DE",
    "sg:address":"Haberstr. 12",
    "sg:city":"Bremerhaven",
    "sg:postcode":"27574",
    "sg:province":"Bremen",
    "wof:name":"Cd-kritik.de",
    "wof:placetype":"venue"
},
  "geometry": {"coordinates":[8.6077699661,53.5190467834],"type":"Point"}
}