{
  "type": "Feature",
  "properties": {
    "iso:country":"DE",
    "sg:address":"Thomas-M\u00fcntzer-Str. 1",
    "sg:city":"Weimar",
    "sg:phone":"+49 3643/905157",
    "sg:postcode":"99423",
    "sg:province":"Th\u00fcringen",
    "wof:name":"Otto Paetz",
    "wof:placetype":"venue"
},
  "geometry": {"coordinates":[11.321991,50.974815],"type":"Point"}
}