{
  "type": "Feature",
  "properties": {
    "iso:country":"DE",
    "sg:address":"Verdistr. 12",
    "sg:city":"Langen",
    "sg:phone":"+49 6103/74666",
    "sg:postcode":"63225",
    "sg:province":"Hessen",
    "wof:name":"Heinz Kropf Bau Gmbh",
    "wof:placetype":"venue"
},
  "geometry": {"coordinates":[8.6523685455,49.9863090515],"type":"Point"}
}