{
  "type": "Feature",
  "properties": {
    "iso:country":"DE",
    "sg:address":"Max-Reimann-Str.",
    "sg:city":"Marolterode",
    "sg:phone":"+49 36021/483",
    "sg:postcode":"99994",
    "sg:province":"Th\u00fcringen",
    "wof:name":"Agrargenossenschaft Marolterode Eg",
    "wof:placetype":"venue"
},
  "geometry": {"coordinates":[10.680565,51.229305],"type":"Point"}
}