{
  "type": "Feature",
  "properties": {
    "iso:country":"DE",
    "sg:address":"Gartenweg 5",
    "sg:city":"Meinersen",
    "sg:phone":"+49 5372/7292",
    "sg:postcode":"38536",
    "sg:province":"Niedersachsen",
    "wof:name":"Orgelbau Amadeus Junker",
    "wof:placetype":"venue"
},
  "geometry": {"coordinates":[10.360857,52.473282],"type":"Point"}
}