{
  "type": "Feature",
  "properties": {
    "iso:country":"DE",
    "sg:address":"Oberrohr",
    "sg:city":"Ursberg",
    "sg:phone":"+49 8281/1369",
    "sg:postcode":"86513",
    "sg:province":"Bayern",
    "wof:name":"A. Goldstein",
    "wof:placetype":"venue"
},
  "geometry": {"coordinates":[10.4336900711,48.2790184021],"type":"Point"}
}