{
  "type": "Feature",
  "properties": {
    "iso:country":"DE",
    "sg:address":"Friedberger Str. 89",
    "sg:city":"Bad Vilbel",
    "sg:postcode":"61118",
    "sg:province":"Hessen",
    "wof:name":"Claus Fischer Grundst\u00fccks- Gesellschaft Mbh Immobilien",
    "wof:placetype":"venue"
},
  "geometry": {"coordinates":[8.7422819138,50.1897544861],"type":"Point"}
}