{
  "type": "Feature",
  "properties": {
    "iso:country":"DE",
    "sg:address":"K\u00f6nigstr. 87",
    "sg:city":"N\u00fcrnberg",
    "sg:postcode":"90402",
    "sg:province":"Bayern",
    "wof:name":"Dg Leasing Gmbh",
    "wof:placetype":"venue"
},
  "geometry": {"coordinates":[11.0812988281,49.4481163025],"type":"Point"}
}