{
  "type": "Feature",
  "properties": {
    "iso:country":"DE",
    "sg:address":"Lindenweg",
    "sg:city":"Templin",
    "sg:postcode":"17268",
    "sg:province":"Brandenburg",
    "wof:name":"M\u00e4rk. Brennstoffh. Handel Ost Gmbh & Co. Kg",
    "wof:placetype":"venue"
},
  "geometry": {"coordinates":[13.5037899017,53.1262817383],"type":"Point"}
}