{
  "type": "Feature",
  "properties": {
    "iso:country":"DE",
    "sg:address":"Hauptstr. 133",
    "sg:city":"Viersen",
    "sg:phone":"+49 2162/13678",
    "sg:postcode":"41747",
    "sg:province":"Nordrhein-Westfalen",
    "wof:name":"Roteringsche L\u00f6wenapotheke Inh. Karl K\u00f6nnes",
    "wof:placetype":"venue"
},
  "geometry": {"coordinates":[6.39258,51.253464],"type":"Point"}
}