{
  "type": "Feature",
  "properties": {
    "iso:country":"DE",
    "sg:address":"Schulstr. 51",
    "sg:city":"Saarlouis",
    "sg:phone":"+49 6831/81185",
    "sg:postcode":"66740",
    "sg:province":"Saarland",
    "wof:name":"M. Titeux",
    "wof:placetype":"venue"
},
  "geometry": {"coordinates":[6.7474942207,49.3335533142],"type":"Point"}
}