{
  "type": "Feature",
  "properties": {
    "iso:country":"DE",
    "sg:address":"Auwer Weg 11",
    "sg:city":"Speicher",
    "sg:phone":"+49 6562/2793",
    "sg:postcode":"54662",
    "sg:province":"Rheinland-Pfalz",
    "wof:name":"Horst Patejdl Steuerberater",
    "wof:placetype":"venue"
},
  "geometry": {"coordinates":[6.6362171173,49.9323387146],"type":"Point"}
}