{
  "type": "Feature",
  "properties": {
    "iso:country":"DE",
    "sg:address":"Cruthovener Str. 10",
    "sg:city":"D\u00fcsseldorf",
    "sg:phone":"+49 211/214643",
    "sg:postcode":"40231",
    "sg:province":"Nordrhein-Westfalen",
    "wof:name":"Theo Konrad",
    "wof:placetype":"venue"
},
  "geometry": {"coordinates":[6.839035,51.203762],"type":"Point"}
}