{
  "type": "Feature",
  "properties": {
    "iso:country":"DE",
    "sg:address":"Siebengebirgsring 4 a",
    "sg:city":"Lohmar",
    "sg:phone":"+49 2206/866590",
    "sg:postcode":"53797",
    "sg:province":"Nordrhein-Westfalen",
    "wof:name":"Markus Und Bianca Horn",
    "wof:placetype":"venue"
},
  "geometry": {"coordinates":[7.2456541061,50.907497406],"type":"Point"}
}