{
  "type": "Feature",
  "properties": {
    "iso:country":"DE",
    "sg:address":"Berliner Str. 6",
    "sg:city":"Waldkraiburg",
    "sg:phone":"+49 8638/3360",
    "sg:postcode":"84478",
    "sg:province":"Bayern",
    "wof:name":"Hubertus-apotheke",
    "wof:placetype":"venue"
},
  "geometry": {"coordinates":[12.40189,48.207405],"type":"Point"}
}