{
  "type": "Feature",
  "properties": {
    "iso:country":"DE",
    "sg:address":"Winterlingerstra\u00dfe 4",
    "sg:city":"Sigmaringen",
    "sg:phone":"+49 7571",
    "sg:postcode":"72488",
    "sg:province":"Baden-W\u00fcrttemberg",
    "wof:name":"Ing. Wolfgang Sch\u00e4fer Gmbh",
    "wof:placetype":"venue"
},
  "geometry": {"coordinates":[9.1850500107,48.0873527527],"type":"Point"}
}