{
  "type": "Feature",
  "properties": {
    "iso:country":"DE",
    "sg:address":"Blomberger Str. 4",
    "sg:city":"Schieder-Schwalenberg",
    "sg:phone":"+49 5282/288",
    "sg:postcode":"32816",
    "sg:province":"Nordrhein-Westfalen",
    "wof:name":"Landgasthof Am Park",
    "wof:placetype":"venue"
},
  "geometry": {"coordinates":[9.1461820602,51.9378623962],"type":"Point"}
}