{
  "type": "Feature",
  "properties": {
    "iso:country":"DE",
    "sg:address":"Ruhrstr. 72",
    "sg:city":"Schwelm",
    "sg:phone":"+49 2336/93950",
    "sg:postcode":"58332",
    "sg:province":"Nordrhein-Westfalen",
    "wof:name":"Hermann Isert Nachf. Gmbh & Co. Kg",
    "wof:placetype":"venue"
},
  "geometry": {"coordinates":[7.2690300941,51.2890319824],"type":"Point"}
}