{
  "type": "Feature",
  "properties": {
    "iso:country":"DE",
    "sg:address":"Huckstr. 40",
    "sg:city":"Issum",
    "sg:phone":"+49 2835/92723",
    "sg:postcode":"47661",
    "sg:province":"Nordrhein-Westfalen",
    "wof:name":"Franz-hugo Hannen",
    "wof:placetype":"venue"
},
  "geometry": {"coordinates":[6.449102,51.520882],"type":"Point"}
}