{
  "type": "Feature",
  "properties": {
    "iso:country":"DE",
    "sg:address":"Siegener Str. 4",
    "sg:city":"Erndtebr\u00fcck",
    "sg:phone":"+49 2753/2253",
    "sg:postcode":"57339",
    "sg:province":"Nordrhein-Westfalen",
    "wof:name":"Ristorante Bella Italia",
    "wof:placetype":"venue"
},
  "geometry": {"coordinates":[8.2543916702,50.9889907837],"type":"Point"}
}