{
  "type": "Feature",
  "properties": {
    "iso:country":"DE",
    "sg:address":"Daimlerstr 11",
    "sg:city":"Neumarkt",
    "sg:phone":"+49 9181/48080",
    "sg:postcode":"92318",
    "sg:province":"Bayern",
    "wof:name":"Ams-w\u00fcnsch Offsetdruck Gmbh",
    "wof:placetype":"venue"
},
  "geometry": {"coordinates":[11.4541139603,49.2711372375],"type":"Point"}
}