{
  "type": "Feature",
  "properties": {
    "iso:country":"DE",
    "sg:address":"Frank-Luck-Str 6",
    "sg:city":"Springstille",
    "sg:phone":"+49 36847/50000",
    "sg:postcode":"98587",
    "sg:province":"Th\u00fcringen",
    "wof:name":"Werkzeugbau R\u00f6tberg Gmbh & Co Kg",
    "wof:placetype":"venue"
},
  "geometry": {"coordinates":[10.510982,50.688099],"type":"Point"}
}