{
  "type": "Feature",
  "properties": {
    "iso:country":"DE",
    "sg:address":"Bahnhofstr. 1",
    "sg:city":"Hohenlockstedt",
    "sg:phone":"+49 4948/265770",
    "sg:postcode":"25551",
    "sg:province":"Schleswig-Holstein",
    "wof:name":"Maschinenbautechnik Hohenlockstedt Gmbh",
    "wof:placetype":"venue"
},
  "geometry": {"coordinates":[9.616866,53.960751],"type":"Point"}
}