{
  "type": "Feature",
  "properties": {
    "iso:country":"DE",
    "sg:address":"Teichweg 10",
    "sg:city":"Gro\u00dferlach",
    "sg:phone":"+49 7903/674",
    "sg:postcode":"71577",
    "sg:province":"Baden-W\u00fcrttemberg",
    "wof:name":"Heinz Schif",
    "wof:placetype":"venue"
},
  "geometry": {"coordinates":[9.505772,49.070885],"type":"Point"}
}