{
  "type": "Feature",
  "properties": {
    "iso:country":"DE",
    "sg:address":"Sonntagsstr. 8",
    "sg:city":"H\u00fcnfelden",
    "sg:phone":"+49 6431/42347",
    "sg:postcode":"65597",
    "sg:province":"Hessen",
    "wof:name":"K. Foike",
    "wof:placetype":"venue"
},
  "geometry": {"coordinates":[8.1053962708,50.3424606323],"type":"Point"}
}