{
  "type": "Feature",
  "properties": {
    "iso:country":"DE",
    "sg:address":"Mergentheimer Str. 5",
    "sg:city":"W\u00fcrzburg",
    "sg:phone":"+49 931/72758",
    "sg:postcode":"97082",
    "sg:province":"Bayern",
    "wof:name":"Karl Sch\u00e4ffner",
    "wof:placetype":"venue"
},
  "geometry": {"coordinates":[9.9250059128,49.7877807617],"type":"Point"}
}