{
  "type": "Feature",
  "properties": {
    "iso:country":"DE",
    "sg:address":"Waldweg 14",
    "sg:city":"Norderney",
    "sg:phone":"+49 4932/92277",
    "sg:postcode":"26548",
    "sg:province":"Niedersachsen",
    "wof:name":"G\u00e4stehaus Haus Coordes",
    "wof:placetype":"venue"
},
  "geometry": {"coordinates":[7.163880825,53.7105941772],"type":"Point"}
}