{
  "type": "Feature",
  "properties": {
    "iso:country":"DE",
    "sg:address":"Rosenstr. 3",
    "sg:city":"Isenb\u00fcttel",
    "sg:phone":"+49 5374/4855",
    "sg:postcode":"38550",
    "sg:province":"Niedersachsen",
    "wof:name":"Rainer Hanske",
    "wof:placetype":"venue"
},
  "geometry": {"coordinates":[10.582412,52.432621],"type":"Point"}
}