{
  "type": "Feature",
  "properties": {
    "iso:country":"DE",
    "sg:address":"Ganghoferstr. 88",
    "sg:city":"M\u00fcnchen",
    "sg:phone":"+49 89/536826",
    "sg:postcode":"81373",
    "sg:province":"Bayern",
    "wof:name":"Helio Gmbh",
    "wof:placetype":"venue"
},
  "geometry": {"coordinates":[11.539119,48.127064],"type":"Point"}
}