{
  "type": "Feature",
  "properties": {
    "iso:country":"DE",
    "sg:address":"Gr\u00fcnhainer Str. 33",
    "sg:city":"Zw\u00f6nitz",
    "sg:phone":"+49 37754/2888",
    "sg:postcode":"08297",
    "sg:province":"Sachsen",
    "wof:name":"Peter Clau\u00df",
    "wof:placetype":"venue"
},
  "geometry": {"coordinates":[12.8141202927,50.6253700256],"type":"Point"}
}