{
  "type": "Feature",
  "properties": {
    "iso:country":"DE",
    "sg:address":"Am Plan 2",
    "sg:city":"Meerane",
    "sg:phone":"+49 3764/4577",
    "sg:postcode":"08393",
    "sg:province":"Sachsen",
    "wof:name":"Gisela Funk",
    "wof:placetype":"venue"
},
  "geometry": {"coordinates":[12.467808,50.848129],"type":"Point"}
}