{
  "type": "Feature",
  "properties": {
    "iso:country":"DE",
    "sg:address":"Friedrichstr. 40",
    "sg:city":"Ettenheim",
    "sg:phone":"+49 7822/2280",
    "sg:postcode":"77955",
    "sg:province":"Baden-W\u00fcrttemberg",
    "wof:name":"H. Und G. Riegger",
    "wof:placetype":"venue"
},
  "geometry": {"coordinates":[7.8135228157,48.2548332214],"type":"Point"}
}