{
  "type": "Feature",
  "properties": {
    "iso:country":"DE",
    "sg:address":"Dr.-Wilhelm-K\u00fclz-Str. 36",
    "sg:city":"Burgst\u00e4dt",
    "sg:phone":"+49 3724/3446",
    "sg:postcode":"09217",
    "sg:province":"Sachsen",
    "wof:name":"Eberhard Hofmann",
    "wof:placetype":"venue"
},
  "geometry": {"coordinates":[12.81586,50.924469],"type":"Point"}
}