{
  "type": "Feature",
  "properties": {
    "iso:country":"DE",
    "sg:address":"Bonatzweg 11",
    "sg:city":"Hannover",
    "sg:phone":"+49 511/865933",
    "sg:postcode":"30559",
    "sg:province":"Niedersachsen",
    "wof:name":"Tega Wohnbedarfshandelsges.mbh",
    "wof:placetype":"venue"
},
  "geometry": {"coordinates":[9.843891,52.359276],"type":"Point"}
}