{
  "type": "Feature",
  "properties": {
    "iso:country":"DE",
    "sg:address":"Dorfstr. 20",
    "sg:city":"Dresden",
    "sg:phone":"+49 351/8901004",
    "sg:postcode":"01257",
    "sg:province":"Sachsen",
    "wof:name":"Graichen Aussenwerbung Gmbh",
    "wof:placetype":"venue"
},
  "geometry": {"coordinates":[13.8196582794,50.9984359741],"type":"Point"}
}