{
  "type": "Feature",
  "properties": {
    "iso:country":"DE",
    "sg:address":"1114 avenue de la pompignane",
    "sg:city":"Montpellier",
    "sg:postcode":"34000",
    "wof:name":"X-label Techno: Dragon",
    "wof:placetype":"venue"
},
  "geometry": {"coordinates":[3.897597,43.615944],"type":"Point"}
}