{
  "type": "Feature",
  "properties": {
    "iso:country":"DE",
    "sg:address":"Steinstr. 40",
    "sg:city":"Steinfurt",
    "sg:phone":"+49 2551/3313",
    "sg:postcode":"48565",
    "sg:province":"Nordrhein-Westfalen",
    "wof:name":"Wolfgang H\u00f6gger",
    "wof:placetype":"venue"
},
  "geometry": {"coordinates":[7.3369050026,52.1490211487],"type":"Point"}
}