{
  "type": "Feature",
  "properties": {
    "iso:country":"DE",
    "sg:address":"Kirchstr. 11",
    "sg:city":"Wittmund",
    "sg:phone":"+49 4462/6778",
    "sg:postcode":"26409",
    "sg:province":"Niedersachsen",
    "wof:name":"G. Janssen Gmbh",
    "wof:placetype":"venue"
},
  "geometry": {"coordinates":[7.781293869,53.576084137],"type":"Point"}
}