{
  "type": "Feature",
  "properties": {
    "iso:country":"DE",
    "sg:address":"Breiter Weg 18",
    "sg:city":"Meschede",
    "sg:phone":"+49 2903/6618",
    "sg:postcode":"59872",
    "sg:province":"Nordrhein-Westfalen",
    "wof:name":"T. Lempa",
    "wof:placetype":"venue"
},
  "geometry": {"coordinates":[8.174616,51.373852],"type":"Point"}
}