{
  "type": "Feature",
  "properties": {
    "iso:country":"DE",
    "sg:address":"Blumenstr. 45",
    "sg:city":"Prenzlau",
    "sg:phone":"+49 3984/6760",
    "sg:postcode":"17291",
    "sg:province":"Brandenburg",
    "wof:name":"L. St\u00f6ckel",
    "wof:placetype":"venue"
},
  "geometry": {"coordinates":[13.878587,53.329292],"type":"Point"}
}