{
  "type": "Feature",
  "properties": {
    "iso:country":"DE",
    "sg:address":"Koblenzer Str. 31",
    "sg:city":"Mayen",
    "sg:postcode":"56727",
    "sg:province":"Rheinland-Pfalz",
    "wof:name":"Vvn Verm\u00f6gensverw. Gmbh",
    "wof:placetype":"venue"
},
  "geometry": {"coordinates":[7.2277460098,50.3300094604],"type":"Point"}
}