{
  "type": "Feature",
  "properties": {
    "iso:country":"DE",
    "sg:address":"Bahnhofstr. 12",
    "sg:city":"Gerolstein",
    "sg:phone":"+49 6591/3304",
    "sg:postcode":"54568",
    "sg:province":"Rheinland-Pfalz",
    "wof:name":"Buchhandlung Raabe Inh. Ortrud Raabe",
    "wof:placetype":"venue"
},
  "geometry": {"coordinates":[6.6591601372,50.2226867676],"type":"Point"}
}