{
  "type": "Feature",
  "properties": {
    "iso:country":"DE",
    "sg:address":"Straubinger Str. 19",
    "sg:city":"Parkstetten",
    "sg:phone":"+49 9421/10402",
    "sg:postcode":"94365",
    "sg:province":"Bayern",
    "wof:name":"Josef Kammermeier",
    "wof:placetype":"venue"
},
  "geometry": {"coordinates":[12.5963048935,48.9156608582],"type":"Point"}
}