{
  "type": "Feature",
  "properties": {
    "iso:country":"DE",
    "sg:address":"Sch\u00f6nbachstr 9",
    "sg:city":"Augsburg",
    "sg:phone":"+49 821/241790",
    "sg:postcode":"86154",
    "sg:province":"Bayern",
    "wof:name":"Markus G\u00f6ppel Gmbh & Co",
    "wof:placetype":"venue"
},
  "geometry": {"coordinates":[10.882848,48.389214],"type":"Point"}
}