{
  "type": "Feature",
  "properties": {
    "iso:country":"DE",
    "sg:address":"Landhausstr. 226",
    "sg:city":"Stuttgart",
    "sg:phone":"+49 711/481766",
    "sg:postcode":"70188",
    "sg:province":"Baden-W\u00fcrttemberg",
    "wof:name":"Ulrich Burrer",
    "wof:placetype":"venue"
},
  "geometry": {"coordinates":[9.2157659531,48.783744812],"type":"Point"}
}