{
  "type": "Feature",
  "properties": {
    "iso:country":"DE",
    "sg:address":"Richard-Wagner-Str. 86",
    "sg:city":"Kaiserslautern",
    "sg:phone":"+49 631/16847",
    "sg:postcode":"67655",
    "sg:province":"Rheinland-Pfalz",
    "wof:name":"Zack-zack",
    "wof:placetype":"venue"
},
  "geometry": {"coordinates":[7.7677350044,49.4376792908],"type":"Point"}
}