{
  "type": "Feature",
  "properties": {
    "iso:country":"DE",
    "sg:address":"Ziegelstr. 2a",
    "sg:city":"Zwickau",
    "sg:phone":"+49 375/2001025",
    "sg:postcode":"08056",
    "sg:province":"Sachsen",
    "wof:name":"Engel Immobilienmakler",
    "wof:placetype":"venue"
},
  "geometry": {"coordinates":[12.467168808,50.7087669373],"type":"Point"}
}