{
  "type": "Feature",
  "properties": {
    "iso:country":"DE",
    "sg:address":"Kaulbachstr. 37",
    "sg:city":"Wuppertal",
    "sg:phone":"+49 202/5127990",
    "sg:postcode":"42113",
    "sg:province":"Nordrhein-Westfalen",
    "wof:name":"Deunil Dienstleistungen Gmbh",
    "wof:placetype":"venue"
},
  "geometry": {"coordinates":[7.12518,51.266319],"type":"Point"}
}