{
  "type": "Feature",
  "properties": {
    "iso:country":"DE",
    "sg:address":"Steinweg 4",
    "sg:city":"Gehrden",
    "sg:phone":"+49 5108/921730",
    "sg:postcode":"30989",
    "sg:province":"Niedersachsen",
    "wof:name":"Bmbf-verbund Reinigungsw\u00e4nde (reaktive W\u00e4nde)",
    "wof:placetype":"venue"
},
  "geometry": {"coordinates":[9.598936,52.314732],"type":"Point"}
}