{
  "type": "Feature",
  "properties": {
    "iso:country":"DE",
    "sg:address":"Fischergasse 9",
    "sg:city":"Glauchau",
    "sg:phone":"+49 3763/14233",
    "sg:postcode":"08371",
    "sg:province":"Sachsen",
    "wof:name":"J\u00fcrgen Sch\u00f6nfeld",
    "wof:placetype":"venue"
},
  "geometry": {"coordinates":[12.542258,50.82164],"type":"Point"}
}