{
  "type": "Feature",
  "properties": {
    "iso:country":"DE",
    "sg:address":"J\u00e4ckstr. 29",
    "sg:city":"Bamberg",
    "sg:postcode":"96052",
    "sg:province":"Bayern",
    "wof:name":"M\u00fcllers Weinparadies Dietmar M\u00fcller E. K.",
    "wof:placetype":"venue"
},
  "geometry": {"coordinates":[10.884888649,49.9029884338],"type":"Point"}
}