{
  "type": "Feature",
  "properties": {
    "iso:country":"DE",
    "sg:address":"Rosenstr. 20",
    "sg:city":"Trappenkamp",
    "sg:phone":"+49 4323/3312",
    "sg:postcode":"24610",
    "sg:province":"Schleswig-Holstein",
    "wof:name":"Rosemarie Drapatz Krankengymnastin",
    "wof:placetype":"venue"
},
  "geometry": {"coordinates":[10.214158,54.033363],"type":"Point"}
}