{
  "type": "Feature",
  "properties": {
    "iso:country":"DE",
    "sg:address":"Preinstr. 1",
    "sg:city":"Hagen",
    "sg:phone":"+49 2334/42575",
    "sg:postcode":"58119",
    "sg:province":"Nordrhein-Westfalen",
    "wof:name":"C. Stenner",
    "wof:placetype":"venue"
},
  "geometry": {"coordinates":[7.567216,51.350456],"type":"Point"}
}