{
  "type": "Feature",
  "properties": {
    "iso:country":"DE",
    "sg:address":"Radeberger Str. 25",
    "sg:city":"Dresden",
    "sg:phone":"+49 351/8037931",
    "sg:postcode":"01099",
    "sg:province":"Sachsen",
    "wof:name":"Heinz Herrgott Architekt",
    "wof:placetype":"venue"
},
  "geometry": {"coordinates":[13.767561,51.066738],"type":"Point"}
}