{
  "type": "Feature",
  "properties": {
    "iso:country":"DE",
    "sg:address":"Marktplatz 4",
    "sg:city":"Cham",
    "sg:phone":"+49 9971/7105",
    "sg:postcode":"93413",
    "sg:province":"Bayern",
    "wof:name":"Theodor Kusch",
    "wof:placetype":"venue"
},
  "geometry": {"coordinates":[12.6656332016,49.2177505493],"type":"Point"}
}