{
  "type": "Feature",
  "properties": {
    "iso:country":"DE",
    "sg:address":"Rothenkirchener Str 73",
    "sg:city":"Hartmannsdorf",
    "sg:phone":"+49 37602/66513",
    "sg:postcode":"08107",
    "sg:province":"Sachsen",
    "wof:name":"Christe Bauer Gmbh",
    "wof:placetype":"venue"
},
  "geometry": {"coordinates":[12.544470787,50.5863609314],"type":"Point"}
}