{
  "type": "Feature",
  "properties": {
    "iso:country":"DE",
    "sg:address":"Am Sonnenhang 10",
    "sg:city":"Wiesenfelden",
    "sg:phone":"+49 9428/1468",
    "sg:postcode":"94344",
    "sg:province":"Bayern",
    "wof:name":"Hans Fuchs Ingenieurb\u00fcro",
    "wof:placetype":"venue"
},
  "geometry": {"coordinates":[12.5461139679,48.9899559021],"type":"Point"}
}