{
  "type": "Feature",
  "properties": {
    "iso:country":"DE",
    "sg:address":"Wildberger Str. 6",
    "sg:city":"Reichshof",
    "sg:phone":"+49 2297/1337",
    "sg:postcode":"51580",
    "sg:province":"Nordrhein-Westfalen",
    "wof:name":"A. Hacke",
    "wof:placetype":"venue"
},
  "geometry": {"coordinates":[7.769184,50.930077],"type":"Point"}
}