{
  "type": "Feature",
  "properties": {
    "iso:country":"DE",
    "sg:address":"Sonnenwall 69",
    "sg:city":"Duisburg",
    "sg:phone":"+49 203/27805",
    "sg:postcode":"47051",
    "sg:province":"Nordrhein-Westfalen",
    "wof:name":"Ingenieurb\u00fcro Dursun & Kremer",
    "wof:placetype":"venue"
},
  "geometry": {"coordinates":[6.75989,51.431473],"type":"Point"}
}