{
  "type": "Feature",
  "properties": {
    "iso:country":"DE",
    "sg:address":"Bahnhofstr. 23",
    "sg:city":"Bredstedt",
    "sg:phone":"+49 4671/4555",
    "sg:postcode":"25821",
    "sg:province":"Schleswig-Holstein",
    "wof:name":"Naturzentrum Nordfriesland",
    "wof:placetype":"venue"
},
  "geometry": {"coordinates":[8.968744,54.620941],"type":"Point"}
}