{
  "type": "Feature",
  "properties": {
    "iso:country":"DE",
    "sg:address":"Ludwigstr. 8",
    "sg:city":"Iserlohn",
    "sg:phone":"+49 2371/22909",
    "sg:postcode":"58638",
    "sg:province":"Nordrhein-Westfalen",
    "wof:name":"Peter Friedrich",
    "wof:placetype":"venue"
},
  "geometry": {"coordinates":[7.6857042313,51.3756713867],"type":"Point"}
}