{
  "type": "Feature",
  "properties": {
    "iso:country":"DE",
    "sg:address":"Am Sand 30",
    "sg:city":"Amberg",
    "sg:phone":"+49 9621/657368",
    "sg:postcode":"92224",
    "sg:province":"Bayern",
    "wof:name":"Planungsb\u00fcro Helm & K\u00fcnzel Gmbh",
    "wof:placetype":"venue"
},
  "geometry": {"coordinates":[11.860075,49.484676],"type":"Point"}
}