{
  "type": "Feature",
  "properties": {
    "iso:country":"DE",
    "sg:address":"Tauscherstr. 14",
    "sg:city":"Dresden",
    "sg:phone":"+49 351/3103472",
    "sg:postcode":"01277",
    "sg:province":"Sachsen",
    "wof:name":"Herbert H\u00e4nel",
    "wof:placetype":"venue"
},
  "geometry": {"coordinates":[13.808568,51.041729],"type":"Point"}
}