{
  "type": "Feature",
  "properties": {
    "iso:country":"DE",
    "sg:address":"Strelitzer Str. 52",
    "sg:city":"Neustrelitz",
    "sg:postcode":"17235",
    "sg:province":"Mecklenburg-Vorpommern",
    "wof:name":"H. K\u00f6nigsmann",
    "wof:placetype":"venue"
},
  "geometry": {"coordinates":[13.0644197464,53.3615989685],"type":"Point"}
}