{
  "type": "Feature",
  "properties": {
    "iso:country":"DE",
    "sg:address":"Kurpfalz-Centrum 9",
    "sg:city":"Leimen",
    "sg:phone":"+49 6224/951829",
    "sg:postcode":"69181",
    "sg:province":"Baden-W\u00fcrttemberg",
    "wof:name":"K. Pennutis",
    "wof:placetype":"venue"
},
  "geometry": {"coordinates":[8.68977,49.347755],"type":"Point"}
}