{
  "type": "Feature",
  "properties": {
    "iso:country":"DE",
    "sg:address":"Talweg 28",
    "sg:city":"Trochtelfingen",
    "sg:phone":"+49 7124/1861",
    "sg:postcode":"72818",
    "sg:province":"Baden-W\u00fcrttemberg",
    "wof:name":"Kleintierzuchtbedarf Brezing",
    "wof:placetype":"venue"
},
  "geometry": {"coordinates":[9.250961,48.308388],"type":"Point"}
}