{
  "type": "Feature",
  "properties": {
    "iso:country":"DE",
    "sg:address":"Weihnachtssch\u00fctzenstr. 1",
    "sg:city":"Berchtesgaden",
    "sg:phone":"+49 8652/64746",
    "sg:postcode":"83471",
    "sg:province":"Bayern",
    "wof:name":"Cafe Forstner",
    "wof:placetype":"venue"
},
  "geometry": {"coordinates":[13.000992,47.632381],"type":"Point"}
}