{
  "type": "Feature",
  "properties": {
    "iso:country":"DE",
    "sg:address":"Linkertsweg 8",
    "sg:city":"Hartenfels",
    "sg:postcode":"56244",
    "sg:province":"Rheinland-Pfalz",
    "wof:name":"Sch\u00f6nberger Gmbh",
    "wof:placetype":"venue"
},
  "geometry": {"coordinates":[7.7882771492,50.5728607178],"type":"Point"}
}