{
  "type": "Feature",
  "properties": {
    "iso:country":"DE",
    "sg:address":"Am Malzbach 17",
    "sg:city":"Eisenberg",
    "sg:phone":"+49 36691/43065",
    "sg:postcode":"07607",
    "sg:province":"Th\u00fcringen",
    "wof:name":"G\u00fcnter Lamm",
    "wof:placetype":"venue"
},
  "geometry": {"coordinates":[11.912946,50.96978],"type":"Point"}
}