{
  "type": "Feature",
  "properties": {
    "iso:country":"DE",
    "sg:address":"M\u00fchlstr 3",
    "sg:city":"Reichenbach",
    "sg:phone":"+49 7429/94010",
    "sg:postcode":"78564",
    "sg:province":"Baden-W\u00fcrttemberg",
    "wof:name":"Franz Hermle & Sohn Gmbh & Co Gmbh",
    "wof:placetype":"venue"
},
  "geometry": {"coordinates":[8.791701,48.145863],"type":"Point"}
}