{
  "type": "Feature",
  "properties": {
    "iso:country":"DE",
    "sg:address":"Ballindamm 15",
    "sg:city":"Hamburg",
    "sg:phone":"+49 40/309090",
    "sg:postcode":"20095",
    "sg:province":"Hamburg",
    "wof:name":"Adca Bank Ag",
    "wof:placetype":"venue"
},
  "geometry": {"coordinates":[9.998777,53.554085],"type":"Point"}
}