{
  "type": "Feature",
  "properties": {
    "iso:country":"DE",
    "sg:address":"Stockholmer Str. 21",
    "sg:city":"Solingen",
    "sg:phone":"+49 212/800746",
    "sg:postcode":"42657",
    "sg:province":"Nordrhein-Westfalen",
    "wof:name":"Rita Bykowski Hebamme",
    "wof:placetype":"venue"
},
  "geometry": {"coordinates":[7.052236,51.146175],"type":"Point"}
}