{
  "type": "Feature",
  "properties": {
    "iso:country":"DE",
    "sg:address":"Friederikenstr. 152",
    "sg:city":"Papenburg",
    "sg:phone":"+49 4961/98990",
    "sg:postcode":"26871",
    "sg:province":"Niedersachsen",
    "wof:name":"Hermann R\u00fclander E. K.",
    "wof:placetype":"venue"
},
  "geometry": {"coordinates":[7.3804302216,53.0726699829],"type":"Point"}
}