{
  "type": "Feature",
  "properties": {
    "iso:country":"DE",
    "sg:address":"Kemnather Str. 7",
    "sg:city":"Kulmain",
    "sg:phone":"+49 9642/611",
    "sg:postcode":"95508",
    "sg:province":"Bayern",
    "wof:name":"Werner Brunner",
    "wof:placetype":"venue"
},
  "geometry": {"coordinates":[11.8981552124,49.891242981],"type":"Point"}
}