{
  "type": "Feature",
  "properties": {
    "iso:country":"DE",
    "sg:address":"Kirchstr. 42",
    "sg:city":"Bad Segeberg",
    "sg:phone":"+49 4551/2519",
    "sg:postcode":"23795",
    "sg:province":"Schleswig-Holstein",
    "wof:name":"K. Und H. Mau",
    "wof:placetype":"venue"
},
  "geometry": {"coordinates":[10.3084,53.936508],"type":"Point"}
}