{
  "type": "Feature",
  "properties": {
    "iso:country":"DE",
    "sg:address":"Hospitalstr. 3",
    "sg:city":"Frankfurt",
    "sg:phone":"+49 69/313226",
    "sg:postcode":"65929",
    "sg:province":"Hessen",
    "wof:name":"Piet\u00e4t Walter Schmidt Gmbh",
    "wof:placetype":"venue"
},
  "geometry": {"coordinates":[8.544411,50.105999],"type":"Point"}
}