{
  "type": "Feature",
  "properties": {
    "iso:country":"DE",
    "sg:address":"Dahler Str. 72",
    "sg:city":"Olpe",
    "sg:postcode":"57462",
    "sg:province":"Nordrhein-Westfalen",
    "wof:name":"Forstunternehmen Gebr. Stinn",
    "wof:placetype":"venue"
},
  "geometry": {"coordinates":[7.8546309471,51.0004501343],"type":"Point"}
}