{
  "type": "Feature",
  "properties": {
    "iso:country":"DE",
    "sg:address":"Zeitzer Str. 16",
    "sg:city":"Altenburg",
    "sg:phone":"+49 3447/313267",
    "sg:postcode":"04600",
    "sg:province":"Th\u00fcringen",
    "wof:name":"Lutz Manger Notar",
    "wof:placetype":"venue"
},
  "geometry": {"coordinates":[12.4279346466,50.9873466492],"type":"Point"}
}