{
  "type": "Feature",
  "properties": {
    "iso:country":"DE",
    "sg:address":"Blumenstr. 7",
    "sg:city":"Hannover",
    "sg:phone":"+49 511/328453",
    "sg:postcode":"30159",
    "sg:province":"Niedersachsen",
    "wof:name":"R\u00f6ger Sauna Gmbh",
    "wof:placetype":"venue"
},
  "geometry": {"coordinates":[9.748833,52.372692],"type":"Point"}
}