{
  "type": "Feature",
  "properties": {
    "iso:country":"DE",
    "sg:address":"Jacobsdorfer Str. 10",
    "sg:city":"Pillgram",
    "sg:phone":"+49 33608/3014",
    "sg:postcode":"15236",
    "sg:province":"Brandenburg",
    "wof:name":"H. Molter",
    "wof:placetype":"venue"
},
  "geometry": {"coordinates":[14.391602,52.331707],"type":"Point"}
}