{
  "type": "Feature",
  "properties": {
    "iso:country":"DE",
    "sg:address":"Auguststr. 40",
    "sg:city":"Bexbach",
    "sg:phone":"+49 6826/4487",
    "sg:postcode":"66450",
    "sg:province":"Saarland",
    "wof:name":"Oswald Rauch & S\u00f6hne Ohg",
    "wof:placetype":"venue"
},
  "geometry": {"coordinates":[7.2729167938,49.3491096497],"type":"Point"}
}