{
  "type": "Feature",
  "properties": {
    "iso:country":"DE",
    "sg:address":"M\u00f6dlitzer Str. 33",
    "sg:city":"Weidhausen",
    "sg:phone":"+49 9562/6047",
    "sg:postcode":"96279",
    "sg:province":"Bayern",
    "wof:name":"Lorenz Schreiner Kg",
    "wof:placetype":"venue"
},
  "geometry": {"coordinates":[11.1482791901,50.2041893005],"type":"Point"}
}