{
  "type": "Feature",
  "properties": {
    "iso:country":"DE",
    "sg:city":"Mudau",
    "sg:postcode":"69427",
    "sg:province":"Baden-W\u00fcrttemberg",
    "wof:name":"Art-apart",
    "wof:placetype":"venue"
},
  "geometry": {"coordinates":[9.206154,49.533363],"type":"Point"}
}