{
  "type": "Feature",
  "properties": {
    "iso:country":"DE",
    "sg:address":"J\u00fclicher Str. 371-375",
    "sg:city":"Aachen",
    "sg:phone":"+49 241/968640",
    "sg:postcode":"52070",
    "sg:province":"Nordrhein-Westfalen",
    "wof:name":"J. M. Peters Maschinenvermietung E. K.",
    "wof:placetype":"venue"
},
  "geometry": {"coordinates":[6.1164021492,50.7901229858],"type":"Point"}
}