{
  "type": "Feature",
  "properties": {
    "iso:country":"DE",
    "sg:address":"Gerhard-vom-Rath-Str. 8",
    "sg:city":"K\u00f6ln",
    "sg:phone":"+49 221/387275",
    "sg:postcode":"50968",
    "sg:province":"Nordrhein-Westfalen",
    "wof:name":"Hans Heinen",
    "wof:placetype":"venue"
},
  "geometry": {"coordinates":[6.9577188492,50.9062347412],"type":"Point"}
}