{
  "type": "Feature",
  "properties": {
    "iso:country":"DE",
    "sg:address":"Fliederweg 14",
    "sg:city":"Gera",
    "sg:phone":"+49 365/25864",
    "sg:postcode":"07546",
    "sg:province":"Th\u00fcringen",
    "wof:name":"A. Zopf Ingenieur",
    "wof:placetype":"venue"
},
  "geometry": {"coordinates":[12.1007061005,50.8721580505],"type":"Point"}
}