{
  "type": "Feature",
  "properties": {
    "iso:country":"DE",
    "sg:address":"Am Eichenquast 45",
    "sg:city":"Berlin",
    "sg:postcode":"12353",
    "sg:province":"Berlin",
    "wof:name":"Aida Autohaus Gmbh",
    "wof:placetype":"venue"
},
  "geometry": {"coordinates":[13.448943,52.419975],"type":"Point"}
}