{
  "type": "Feature",
  "properties": {
    "iso:country":"DE",
    "sg:address":"Hahnenwinkel 3",
    "sg:city":"Bodenwerder",
    "sg:phone":"+49 5533/2810",
    "sg:postcode":"37619",
    "sg:province":"Niedersachsen",
    "wof:name":"Heinrich Schreiber",
    "wof:placetype":"venue"
},
  "geometry": {"coordinates":[9.513227,51.983158],"type":"Point"}
}