{
  "type": "Feature",
  "properties": {
    "iso:country":"DE",
    "sg:address":"Castroper Str. 44",
    "sg:city":"Datteln",
    "sg:phone":"+49 2363/35333",
    "sg:postcode":"45711",
    "sg:province":"Nordrhein-Westfalen",
    "wof:name":"Reisevermittlung Nebi",
    "wof:placetype":"venue"
},
  "geometry": {"coordinates":[7.3386459351,51.6492385864],"type":"Point"}
}