{
  "type": "Feature",
  "properties": {
    "iso:country":"DE",
    "sg:address":"Backhausberg 64",
    "sg:city":"Ziegelroda",
    "sg:postcode":"06268",
    "sg:province":"Sachsen-Anhalt",
    "wof:name":"Gemeindeschwesterstation Ziegelroda",
    "wof:placetype":"venue"
},
  "geometry": {"coordinates":[11.46215,51.332539],"type":"Point"}
}