{
  "type": "Feature",
  "properties": {
    "iso:country":"DE",
    "sg:address":"Schevenstr. 23",
    "sg:city":"Dresden",
    "sg:phone":"+49 351/2683545",
    "sg:postcode":"01326",
    "sg:province":"Sachsen",
    "wof:name":"Dr. Hermann Kr\u00fcger",
    "wof:placetype":"venue"
},
  "geometry": {"coordinates":[13.8070306778,51.0612335205],"type":"Point"}
}