{
  "type": "Feature",
  "properties": {
    "iso:country":"DE",
    "sg:address":"Fischbacher Str. 17",
    "sg:city":"Ummendorf",
    "sg:phone":"+49 7351/24128",
    "sg:postcode":"88444",
    "sg:province":"Baden-W\u00fcrttemberg",
    "wof:name":"Franz H\u00f6rnle",
    "wof:placetype":"venue"
},
  "geometry": {"coordinates":[9.833589,48.059883],"type":"Point"}
}