{
  "type": "Feature",
  "properties": {
    "iso:country":"DE",
    "sg:address":"Hildebrandstr. 63",
    "sg:city":"Kassel",
    "sg:phone":"+49 561/811523",
    "sg:postcode":"34125",
    "sg:province":"Hessen",
    "wof:name":"Wolfgang Braun",
    "wof:placetype":"venue"
},
  "geometry": {"coordinates":[9.518412,51.336205],"type":"Point"}
}