{
  "type": "Feature",
  "properties": {
    "iso:country":"DE",
    "sg:address":"Am Hammerwerk 21a",
    "sg:city":"Grevenbroich",
    "sg:phone":"+49 2181",
    "sg:postcode":"41515",
    "sg:province":"Nordrhein-Westfalen",
    "wof:name":"Autocenter Grevenbroich",
    "wof:placetype":"venue"
},
  "geometry": {"coordinates":[6.5761427879,51.0894546509],"type":"Point"}
}