{
  "type": "Feature",
  "properties": {
    "iso:country":"DE",
    "sg:address":"Neuhof 7",
    "sg:city":"Pyrbaum",
    "sg:phone":"+49 9180/2686",
    "sg:postcode":"90602",
    "sg:province":"Bayern",
    "wof:name":"Heidelinde Kr\u00e4mer",
    "wof:placetype":"venue"
},
  "geometry": {"coordinates":[11.2582368851,49.2884025574],"type":"Point"}
}