{
  "type": "Feature",
  "properties": {
    "iso:country":"DE",
    "sg:address":"Allerberg 5",
    "sg:city":"Teisendorf",
    "sg:phone":"+49 8666/7432",
    "sg:postcode":"83317",
    "sg:province":"Bayern",
    "wof:name":"Herbert M\u00fchlbacher",
    "wof:placetype":"venue"
},
  "geometry": {"coordinates":[12.784746,47.834965],"type":"Point"}
}