{
  "type": "Feature",
  "properties": {
    "iso:country":"DE",
    "sg:address":"Hauptstr. 16 a",
    "sg:city":"Weitenhagen",
    "sg:phone":"+49 3834/507026",
    "sg:postcode":"17498",
    "sg:province":"Mecklenburg-Vorpommern",
    "wof:name":"T. Krumm",
    "wof:placetype":"venue"
},
  "geometry": {"coordinates":[13.411482,54.054256],"type":"Point"}
}