{
  "type": "Feature",
  "properties": {
    "iso:country":"DE",
    "sg:address":"Eichenlaubstr. 39",
    "sg:city":"Weiskirchen",
    "sg:phone":"+49 6876/349",
    "sg:postcode":"66709",
    "sg:province":"Saarland",
    "wof:name":"Schreinerei Alois Sauer Inh. Karl-heinz Mertinitz",
    "wof:placetype":"venue"
},
  "geometry": {"coordinates":[6.834336,49.558212],"type":"Point"}
}