{
  "type": "Feature",
  "properties": {
    "iso:country":"DE",
    "sg:address":"Vinckestr. 153",
    "sg:city":"Castrop-Rauxel",
    "sg:phone":"+49 2305/73812",
    "sg:postcode":"44581",
    "sg:province":"Nordrhein-Westfalen",
    "wof:name":"Paul Bartel",
    "wof:placetype":"venue"
},
  "geometry": {"coordinates":[7.341144,51.592636],"type":"Point"}
}