{
  "type": "Feature",
  "properties": {
    "iso:country":"DE",
    "sg:address":"Falkenhagener Str. 13",
    "sg:city":"Berlin",
    "sg:phone":"+49 30/3358018",
    "sg:postcode":"13585",
    "sg:province":"Berlin",
    "wof:name":"Wilhelm Fliegener",
    "wof:placetype":"venue"
},
  "geometry": {"coordinates":[13.201847,52.54565],"type":"Point"}
}