{
  "type": "Feature",
  "properties": {
    "iso:country":"DE",
    "sg:address":"aaaaaaaaaaa",
    "sg:city":"Weingarten",
    "sg:phone":"+49 123456789",
    "sg:postcode":"88250",
    "sg:province":"Baden-W\u00fcrttemberg",
    "wof:name":"Sandhaeusle",
    "wof:placetype":"venue"
},
  "geometry": {"coordinates":[9.640783,47.808258],"type":"Point"}
}