{
  "type": "Feature",
  "properties": {
    "iso:country":"DE",
    "sg:address":"Wiesenthaler Str. 35",
    "sg:city":"Kaufbeuren",
    "sg:phone":"+49 8341/64108",
    "sg:postcode":"87600",
    "sg:province":"Bayern",
    "wof:name":"Walter Bach",
    "wof:placetype":"venue"
},
  "geometry": {"coordinates":[10.6270341873,47.9142990112],"type":"Point"}
}