{
  "type": "Feature",
  "properties": {
    "iso:country":"DE",
    "sg:address":"Adlerstr. 5",
    "sg:city":"Wernau",
    "sg:phone":"+49 7153/937937",
    "sg:postcode":"73249",
    "sg:province":"Baden-W\u00fcrttemberg",
    "wof:name":"I. Zink",
    "wof:placetype":"venue"
},
  "geometry": {"coordinates":[9.4215936661,48.6899833679],"type":"Point"}
}