{
  "type": "Feature",
  "properties": {
    "iso:country":"DE",
    "sg:address":"Rittershofer Str. 1",
    "sg:city":"Neumarkt",
    "sg:phone":"+49 9181/25890",
    "sg:postcode":"92318",
    "sg:province":"Bayern",
    "wof:name":"Brk Pflegeheim Woffenbach",
    "wof:placetype":"venue"
},
  "geometry": {"coordinates":[11.430854,49.279205],"type":"Point"}
}