{
  "type": "Feature",
  "properties": {
    "iso:country":"DE",
    "sg:address":"Hinterer Anger 1",
    "sg:city":"Wurzen",
    "sg:phone":"+49 34207/72736",
    "sg:postcode":"04808",
    "sg:province":"Sachsen",
    "wof:name":"H. Kersten",
    "wof:placetype":"venue"
},
  "geometry": {"coordinates":[12.761487,51.349098],"type":"Point"}
}