{
  "type": "Feature",
  "properties": {
    "iso:country":"DE",
    "sg:address":"Hinter den H\u00f6fen 33",
    "sg:city":"Lohfelden",
    "sg:phone":"+49 5608/845",
    "sg:postcode":"34253",
    "sg:province":"Hessen",
    "wof:name":"B. Strunk",
    "wof:placetype":"venue"
},
  "geometry": {"coordinates":[9.5664663315,51.2598648071],"type":"Point"}
}