{
  "type": "Feature",
  "properties": {
    "iso:country":"DE",
    "sg:address":"Sch\u00fctzenstr. 11",
    "sg:city":"Kornwestheim",
    "sg:phone":"+49 7154/23250",
    "sg:postcode":"70806",
    "sg:province":"Baden-W\u00fcrttemberg",
    "wof:name":"Best.image",
    "wof:placetype":"venue"
},
  "geometry": {"coordinates":[9.1890077591,48.8615760803],"type":"Point"}
}