{
  "type": "Feature",
  "properties": {
    "iso:country":"DE",
    "sg:address":"Neckarstr. 14",
    "sg:city":"Nufringen",
    "sg:phone":"+49 7032/8657",
    "sg:postcode":"71154",
    "sg:province":"Baden-W\u00fcrttemberg",
    "wof:name":"J. M. Piening Soons \u00dcbersetzerin",
    "wof:placetype":"venue"
},
  "geometry": {"coordinates":[8.884705,48.621304],"type":"Point"}
}