{
  "type": "Feature",
  "properties": {
    "iso:country":"DE",
    "sg:address":"Werkstr. 4",
    "sg:city":"Bad Salzuflen",
    "sg:phone":"+49 5222/20885",
    "sg:postcode":"32107",
    "sg:province":"Nordrhein-Westfalen",
    "wof:name":"Kup Keller Verwaltungs Gmbh",
    "wof:placetype":"venue"
},
  "geometry": {"coordinates":[8.7540941238,52.04845047],"type":"Point"}
}