{
  "type": "Feature",
  "properties": {
    "iso:country":"DE",
    "sg:address":"Borngasse 9",
    "sg:city":"Ehringshausen",
    "sg:phone":"+49 6443/83880",
    "sg:postcode":"35630",
    "sg:province":"Hessen",
    "wof:name":"Kreativhaus Werbeagentur Gmbh",
    "wof:placetype":"venue"
},
  "geometry": {"coordinates":[8.3481941223,50.6050682068],"type":"Point"}
}