{
  "type": "Feature",
  "properties": {
    "iso:country":"DE",
    "sg:address":"Hochstr. 11",
    "sg:city":"Sinn",
    "sg:phone":"+49 2772/51862",
    "sg:postcode":"35764",
    "sg:province":"Hessen",
    "wof:name":"Katholisches Pfarramt St. Michael",
    "wof:placetype":"venue"
},
  "geometry": {"coordinates":[8.3300848007,50.6567726135],"type":"Point"}
}