{
  "type": "Feature",
  "properties": {
    "iso:country":"DE",
    "sg:address":"Auf den Vieren 30",
    "sg:city":"Melle",
    "sg:phone":"+49 5422/2943",
    "sg:postcode":"49324",
    "sg:province":"Niedersachsen",
    "wof:name":"Ernst Huckriede Architekt",
    "wof:placetype":"venue"
},
  "geometry": {"coordinates":[8.36688,52.221725],"type":"Point"}
}