{
  "type": "Feature",
  "properties": {
    "iso:country":"DE",
    "sg:address":"Industriestr. 7",
    "sg:city":"Wasbek",
    "sg:phone":"+49 4943/2177755",
    "sg:postcode":"24647",
    "sg:province":"Schleswig-Holstein",
    "wof:name":"Schwimmbad & Saunabau-freizeit & Fitness Gmbh",
    "wof:placetype":"venue"
},
  "geometry": {"coordinates":[9.91155,54.072319],"type":"Point"}
}