{
  "type": "Feature",
  "properties": {
    "iso:country":"DE",
    "sg:address":"Hofestr. 1",
    "sg:city":"Stolpen",
    "sg:phone":"+49 35973/28810",
    "sg:postcode":"01833",
    "sg:province":"Sachsen",
    "wof:name":"Seniorenheim Frieden",
    "wof:placetype":"venue"
},
  "geometry": {"coordinates":[14.096827,51.005478],"type":"Point"}
}