{
  "type": "Feature",
  "properties": {
    "iso:country":"DE",
    "sg:address":"Hauptstr. 11",
    "sg:city":"Flieden",
    "sg:phone":"+49 6655/2516",
    "sg:postcode":"36103",
    "sg:province":"Hessen",
    "wof:name":"M. M\u00fcller",
    "wof:placetype":"venue"
},
  "geometry": {"coordinates":[9.5685806274,50.4228172302],"type":"Point"}
}