{
  "type": "Feature",
  "properties": {
    "iso:country":"DE",
    "sg:address":"Annahofer Str. 1a",
    "sg:city":"Germendorf",
    "sg:phone":"+49 3301/58640",
    "sg:postcode":"16767",
    "sg:province":"Brandenburg",
    "wof:name":"Oberhavel Verkehrs Gmbh",
    "wof:placetype":"venue"
},
  "geometry": {"coordinates":[13.1858472824,52.7458381653],"type":"Point"}
}