{
  "type": "Feature",
  "properties": {
    "iso:country":"DE",
    "sg:address":"Sonnenstr. 28",
    "sg:city":"Birkenfeld",
    "sg:postcode":"97834",
    "sg:province":"Bayern",
    "wof:name":"Gasco Gastronomische Betriebs- Und Entwicklungs Gmbh",
    "wof:placetype":"venue"
},
  "geometry": {"coordinates":[9.7030057907,49.8608322144],"type":"Point"}
}