{
  "type": "Feature",
  "properties": {
    "iso:country":"DE",
    "sg:address":"Flurweg 14 b",
    "sg:city":"Altom\u00fcnster",
    "sg:phone":"+49 8254/2402",
    "sg:postcode":"85250",
    "sg:province":"Bayern",
    "wof:name":"Schweiger",
    "wof:placetype":"venue"
},
  "geometry": {"coordinates":[11.196764946,48.3983688354],"type":"Point"}
}