{
  "type": "Feature",
  "properties": {
    "iso:country":"DE",
    "sg:address":"Leipziger Str. 15",
    "sg:city":"Linden",
    "sg:phone":"+49 6403/61357",
    "sg:postcode":"35440",
    "sg:province":"Hessen",
    "wof:name":"Charme Dental Handels Gmbh",
    "wof:placetype":"venue"
},
  "geometry": {"coordinates":[8.6775636673,50.523399353],"type":"Point"}
}