{
  "type": "Feature",
  "properties": {
    "iso:country":"DE",
    "sg:address":"Niederstadtgraben 1",
    "sg:city":"D\u00f6beln",
    "sg:phone":"+49 3431/2275",
    "sg:postcode":"04720",
    "sg:province":"Sachsen",
    "wof:name":"Kreissparkasse",
    "wof:placetype":"venue"
},
  "geometry": {"coordinates":[13.11965,51.128841],"type":"Point"}
}