{
  "type": "Feature",
  "properties": {
    "iso:country":"DE",
    "sg:address":"R\u00f6merstra\u00dfe 2",
    "sg:city":"Ehingen",
    "sg:phone":"+49 9082",
    "sg:postcode":"86741",
    "sg:province":"Bayern",
    "wof:name":"Auto Schneller",
    "wof:placetype":"venue"
},
  "geometry": {"coordinates":[10.5512533188,48.9617614746],"type":"Point"}
}