{
  "type": "Feature",
  "properties": {
    "iso:country":"DE",
    "sg:address":"Waldstr. 15",
    "sg:city":"Nohn",
    "sg:phone":"+49 2696/497",
    "sg:postcode":"54578",
    "sg:province":"Rheinland-Pfalz",
    "wof:name":"Irmgard Leif",
    "wof:placetype":"venue"
},
  "geometry": {"coordinates":[6.7818350792,50.3272247314],"type":"Point"}
}