{
  "type": "Feature",
  "properties": {
    "iso:country":"DE",
    "sg:address":"Glash\u00fctter Str. 53",
    "sg:city":"Dresden",
    "sg:postcode":"01309",
    "sg:province":"Sachsen",
    "wof:name":"Keimed Gesellschaft F\u00fcr Handel Und Dienstleistungen",
    "wof:placetype":"venue"
},
  "geometry": {"coordinates":[13.791742,51.042404],"type":"Point"}
}