{
  "type": "Feature",
  "properties": {
    "iso:country":"DE",
    "sg:address":"Gutenbergstr. 2",
    "sg:city":"Weil der Stadt",
    "sg:phone":"+49 7033/8466",
    "sg:postcode":"71263",
    "sg:province":"Baden-W\u00fcrttemberg",
    "wof:name":"Erwin Scharpf",
    "wof:placetype":"venue"
},
  "geometry": {"coordinates":[8.877055,48.759415],"type":"Point"}
}