{
  "type": "Feature",
  "properties": {
    "iso:country":"DE",
    "sg:address":"Amberger Str. 35",
    "sg:city":"Neumarkt",
    "sg:phone":"+49 9181/44129",
    "sg:postcode":"92318",
    "sg:province":"Bayern",
    "wof:name":"Korbena Korkstudio",
    "wof:placetype":"venue"
},
  "geometry": {"coordinates":[11.4672708511,49.2864494324],"type":"Point"}
}