{
  "type": "Feature",
  "properties": {
    "iso:country":"DE",
    "sg:address":"Sebastian-Kneipp-Str. 41",
    "sg:city":"Bad Endbach",
    "sg:phone":"+49 2776/91560",
    "sg:postcode":"35080",
    "sg:province":"Hessen",
    "wof:name":"Alten- Und Pflegeheim Haus Waldesruh",
    "wof:placetype":"venue"
},
  "geometry": {"coordinates":[8.483887,50.752426],"type":"Point"}
}