{
  "type": "Feature",
  "properties": {
    "iso:country":"DE",
    "sg:address":"Duckwitzstr. 41",
    "sg:city":"Dresden",
    "sg:phone":"+49 351/8580442",
    "sg:postcode":"01129",
    "sg:province":"Sachsen",
    "wof:name":"Manfred R\u00f6thel",
    "wof:placetype":"venue"
},
  "geometry": {"coordinates":[13.7246332169,51.0953445435],"type":"Point"}
}