{
  "type": "Feature",
  "properties": {
    "iso:country":"DE",
    "sg:address":"Kienestr. 33",
    "sg:city":"Stuttgart",
    "sg:phone":"+49 711/2255360",
    "sg:postcode":"70174",
    "sg:province":"Baden-W\u00fcrttemberg",
    "wof:name":"Louis Leitz Gmbh & Co. Kg",
    "wof:placetype":"venue"
},
  "geometry": {"coordinates":[9.1734886169,48.7784729004],"type":"Point"}
}