{
  "type": "Feature",
  "properties": {
    "iso:country":"DE",
    "sg:address":"Winterberger Str. 35",
    "sg:city":"Schwelm",
    "sg:phone":"+49 2336/6515",
    "sg:postcode":"58332",
    "sg:province":"Nordrhein-Westfalen",
    "wof:name":"Erich Sattler",
    "wof:placetype":"venue"
},
  "geometry": {"coordinates":[7.3019390106,51.2791748047],"type":"Point"}
}