{
  "type": "Feature",
  "properties": {
    "iso:country":"DE",
    "sg:address":"Aubruchsweg 100",
    "sg:city":"Moers",
    "sg:phone":"+49 2841/63007",
    "sg:postcode":"47447",
    "sg:province":"Nordrhein-Westfalen",
    "wof:name":"Wilhelm Grond",
    "wof:placetype":"venue"
},
  "geometry": {"coordinates":[6.625016,51.413094],"type":"Point"}
}