{
  "type": "Feature",
  "properties": {
    "iso:country":"DE",
    "sg:address":"W\u00fcrmer Hauptstr. 9",
    "sg:city":"Pforzheim",
    "sg:phone":"+49 7231/789342",
    "sg:postcode":"75181",
    "sg:province":"Baden-W\u00fcrttemberg",
    "wof:name":"Frank Burghardt",
    "wof:placetype":"venue"
},
  "geometry": {"coordinates":[8.740408,48.859665],"type":"Point"}
}