{
  "type": "Feature",
  "properties": {
    "iso:country":"DE",
    "sg:address":"Comthurgasse 1",
    "sg:city":"Erfurt",
    "sg:postcode":"99084",
    "sg:province":"Th\u00fcringen",
    "wof:name":"Pille Wohn- Und Projektbau Gmbh",
    "wof:placetype":"venue"
},
  "geometry": {"coordinates":[11.0283746719,50.980846405],"type":"Point"}
}