{
  "type": "Feature",
  "properties": {
    "iso:country":"DE",
    "sg:address":"Teimbergstr. 12",
    "sg:city":"Velbert",
    "sg:phone":"+49 2053/4466",
    "sg:postcode":"42553",
    "sg:province":"Nordrhein-Westfalen",
    "wof:name":"Hagel\u00fcken",
    "wof:placetype":"venue"
},
  "geometry": {"coordinates":[7.1058998108,51.3111991882],"type":"Point"}
}