{
  "type": "Feature",
  "properties": {
    "iso:country":"DE",
    "sg:address":"Cuxhavener Str. 114",
    "sg:city":"Buxtehude",
    "sg:phone":"+49 4161/86355",
    "sg:postcode":"21614",
    "sg:province":"Niedersachsen",
    "wof:name":"Gastst\u00e4tte Bierkiste",
    "wof:placetype":"venue"
},
  "geometry": {"coordinates":[9.6359586716,53.4813804626],"type":"Point"}
}