{
  "type": "Feature",
  "properties": {
    "iso:country":"DE",
    "sg:address":"Mozartstr. 26",
    "sg:city":"Ilvesheim",
    "sg:phone":"+49 621/492179",
    "sg:postcode":"68549",
    "sg:province":"Baden-W\u00fcrttemberg",
    "wof:name":"Horst Brumlich",
    "wof:placetype":"venue"
},
  "geometry": {"coordinates":[8.551989,49.479492],"type":"Point"}
}