{
  "type": "Feature",
  "properties": {
    "iso:country":"DE",
    "sg:address":"Saarbr\u00fccker Str. 140",
    "sg:city":"Riegelsberg",
    "sg:phone":"+49 6806/3939",
    "sg:postcode":"66292",
    "sg:province":"Saarland",
    "wof:name":"Haus Gabriel",
    "wof:placetype":"venue"
},
  "geometry": {"coordinates":[6.9426231384,49.3084487915],"type":"Point"}
}