{
  "type": "Feature",
  "properties": {
    "iso:country":"DE",
    "sg:address":"Frankfurter Str. 2 a",
    "sg:city":"Marburg",
    "sg:phone":"+49 6421/23410",
    "sg:postcode":"35037",
    "sg:province":"Hessen",
    "wof:name":"Einsle-g\u00e4stehaus",
    "wof:placetype":"venue"
},
  "geometry": {"coordinates":[8.7708454132,50.8044776917],"type":"Point"}
}