{
  "type": "Feature",
  "properties": {
    "iso:country":"DE",
    "sg:address":"Hauptstr. 9",
    "sg:city":"Neukirchen",
    "sg:phone":"+49 9961/471",
    "sg:postcode":"94362",
    "sg:province":"Bayern",
    "wof:name":"Gasthof Josef Laschinger",
    "wof:placetype":"venue"
},
  "geometry": {"coordinates":[12.7532806396,48.9750747681],"type":"Point"}
}