{
  "type": "Feature",
  "properties": {
    "iso:country":"DE",
    "sg:address":"Am Markt 5",
    "sg:city":"Bad Arolsen",
    "sg:phone":"+49 5696/1089",
    "sg:postcode":"34454",
    "sg:province":"Hessen",
    "wof:name":"Karl-heinz Grass",
    "wof:placetype":"venue"
},
  "geometry": {"coordinates":[9.082185,51.342148],"type":"Point"}
}