{
  "type": "Feature",
  "properties": {
    "iso:country":"DE",
    "sg:address":"Marktstr 10",
    "sg:city":"Odlezhausen",
    "sg:phone":"+49 8134/2834",
    "sg:postcode":"85235",
    "sg:province":"Bayern",
    "wof:name":"Gasthaus Zur Sonne In Odelzhausen",
    "wof:placetype":"venue"
},
  "geometry": {"coordinates":[11.1638240814,48.2952690125],"type":"Point"}
}