{
  "type": "Feature",
  "properties": {
    "iso:country":"DE",
    "sg:address":"Wippenbeckhang 12",
    "sg:city":"Essen",
    "sg:phone":"+49 201/440308",
    "sg:postcode":"45134",
    "sg:province":"Nordrhein-Westfalen",
    "wof:name":"Klaus Romeiss Ingenieur",
    "wof:placetype":"venue"
},
  "geometry": {"coordinates":[7.0465698242,51.4253616333],"type":"Point"}
}