{
  "type": "Feature",
  "properties": {
    "iso:country":"DE",
    "sg:address":"Alfred-Delp-Str. 30",
    "sg:city":"Lampertheim",
    "sg:phone":"+49 6256/831248",
    "sg:postcode":"68623",
    "sg:province":"Hessen",
    "wof:name":"Horst Rhein",
    "wof:placetype":"venue"
},
  "geometry": {"coordinates":[8.5852689743,49.5965042114],"type":"Point"}
}