{
  "type": "Feature",
  "properties": {
    "iso:country":"DE",
    "sg:address":"55743",
    "sg:city":"Idar-Oberstein",
    "sg:phone":"+49 6781/1041",
    "sg:postcode":"55743",
    "sg:province":"Rheinland-Pfalz",
    "wof:name":"Eiscafe Venezia",
    "wof:placetype":"venue"
},
  "geometry": {"coordinates":[7.3293,49.724709],"type":"Point"}
}