{
  "type": "Feature",
  "properties": {
    "iso:country":"DE",
    "sg:address":"Am Unterscheid 42",
    "sg:city":"Bad Wildungen",
    "sg:phone":"+49 5621/4356",
    "sg:postcode":"34537",
    "sg:province":"Hessen",
    "wof:name":"Gert Weber",
    "wof:placetype":"venue"
},
  "geometry": {"coordinates":[9.10821,51.120522],"type":"Point"}
}