{
  "type": "Feature",
  "properties": {
    "iso:country":"DE",
    "sg:address":"Achentalstr. 30",
    "sg:city":"Rohrdorf",
    "sg:phone":"+49 8032/5204",
    "sg:postcode":"83101",
    "sg:province":"Bayern",
    "wof:name":"Josef Haimmerer",
    "wof:placetype":"venue"
},
  "geometry": {"coordinates":[12.170999527,47.798324585],"type":"Point"}
}