{
  "type": "Feature",
  "properties": {
    "iso:country":"DE",
    "sg:address":"Petersberger Str. 66",
    "sg:city":"Fulda",
    "sg:phone":"+49 661/74608",
    "sg:postcode":"36037",
    "sg:province":"Hessen",
    "wof:name":"B\u00fcrotechnik Schmitt Gmbh",
    "wof:placetype":"venue"
},
  "geometry": {"coordinates":[9.6935949326,50.5518722534],"type":"Point"}
}