{
  "type": "Feature",
  "properties": {
    "iso:country":"DE",
    "sg:address":"Greener Str. 5",
    "sg:city":"Einbeck",
    "sg:phone":"+49 5563/6945",
    "sg:postcode":"37574",
    "sg:province":"Niedersachsen",
    "wof:name":"Herbert Henze",
    "wof:placetype":"venue"
},
  "geometry": {"coordinates":[9.892882,51.87965],"type":"Point"}
}