{
  "type": "Feature",
  "properties": {
    "iso:country":"DE",
    "sg:address":"Goethestr. 30",
    "sg:city":"Gie\u00dfen",
    "sg:phone":"+49 641/77344",
    "sg:postcode":"35390",
    "sg:province":"Hessen",
    "wof:name":"Martin Obermann Rechtsanwalt",
    "wof:placetype":"venue"
},
  "geometry": {"coordinates":[8.6749534607,50.5815086365],"type":"Point"}
}