{
  "type": "Feature",
  "properties": {
    "iso:country":"DE",
    "sg:address":"Schwedensteinstr. 23",
    "sg:city":"M\u00fcnchen",
    "sg:postcode":"81827",
    "sg:province":"Bayern",
    "wof:name":"M.s.m. Marketing Gmbh",
    "wof:placetype":"venue"
},
  "geometry": {"coordinates":[11.686856,48.097908],"type":"Point"}
}