{
  "type": "Feature",
  "properties": {
    "iso:country":"DE",
    "sg:address":"Chemnitzer Str. 85",
    "sg:city":"R\u00f6hrsdorf",
    "sg:phone":"+49 3722/502714",
    "sg:postcode":"09247",
    "sg:province":"Sachsen",
    "wof:name":"J. Heydel",
    "wof:placetype":"venue"
},
  "geometry": {"coordinates":[12.840514183,50.8610115051],"type":"Point"}
}