{
  "type": "Feature",
  "properties": {
    "iso:country":"DE",
    "sg:city":"Burg",
    "sg:phone":"+49 4371/9091",
    "sg:postcode":"23769",
    "sg:province":"Schleswig-Holstein",
    "wof:name":"Cafe-gelateria Veneto",
    "wof:placetype":"venue"
},
  "geometry": {"coordinates":[11.197017,54.436218],"type":"Point"}
}