{
  "type": "Feature",
  "properties": {
    "iso:country":"DE",
    "sg:address":"Goldstr. 18",
    "sg:city":"Kaufbeuren",
    "sg:phone":"+49 8341/97950",
    "sg:postcode":"87600",
    "sg:province":"Bayern",
    "wof:name":"Rudolf Bernt & S\u00f6hne",
    "wof:placetype":"venue"
},
  "geometry": {"coordinates":[10.637955,47.917744],"type":"Point"}
}