{
  "type": "Feature",
  "properties": {
    "iso:country":"DE",
    "sg:address":"Am Ha\u00dfkamp 24",
    "sg:city":"Bremen",
    "sg:phone":"+49 421/585300",
    "sg:postcode":"28259",
    "sg:province":"Bremen",
    "wof:name":"Renate Fahrenberg",
    "wof:placetype":"venue"
},
  "geometry": {"coordinates":[8.732802,53.04483],"type":"Point"}
}