{
  "type": "Feature",
  "properties": {
    "iso:country":"DE",
    "sg:address":"Egelseestr. 28",
    "sg:city":"Bad Saulgau",
    "sg:postcode":"88348",
    "sg:province":"Baden-W\u00fcrttemberg",
    "wof:name":"B\u00e4dle Gmbh & Co. Kg",
    "wof:placetype":"venue"
},
  "geometry": {"coordinates":[9.529083252,47.9836807251],"type":"Point"}
}