{
  "type": "Feature",
  "properties": {
    "iso:country":"DE",
    "sg:address":"Grabengasse 2",
    "sg:city":"Sch\u00f6nau v d Walde",
    "sg:phone":"+49 36253/25384",
    "sg:postcode":"99894",
    "sg:province":"Th\u00fcringen",
    "wof:name":"Gessert & Knebel",
    "wof:placetype":"venue"
},
  "geometry": {"coordinates":[10.6396074295,50.8568878174],"type":"Point"}
}