{
  "type": "Feature",
  "properties": {
    "iso:country":"DE",
    "sg:address":"Steinweg 17",
    "sg:city":"Einbeck",
    "sg:phone":"+49 5561/3334",
    "sg:postcode":"37574",
    "sg:province":"Niedersachsen",
    "wof:name":"Herbert S\u00fc\u00dfenbach",
    "wof:placetype":"venue"
},
  "geometry": {"coordinates":[9.866689,51.820786],"type":"Point"}
}