{
  "type": "Feature",
  "properties": {
    "iso:country":"DE",
    "sg:address":"Grimmstr. 5",
    "sg:city":"K\u00f6ln",
    "sg:phone":"+49 221/526149",
    "sg:postcode":"50823",
    "sg:province":"Nordrhein-Westfalen",
    "wof:name":"J. Schmidt Architekt",
    "wof:placetype":"venue"
},
  "geometry": {"coordinates":[6.923526,50.950314],"type":"Point"}
}