{
  "type": "Feature",
  "properties": {
    "iso:country":"DE",
    "sg:address":"Sachsendamm 3",
    "sg:city":"Berlin",
    "sg:postcode":"10829",
    "sg:province":"Berlin",
    "wof:name":"Ipro Berlin Zwndl. Der Ipro Dresden Archi-",
    "wof:placetype":"venue"
},
  "geometry": {"coordinates":[13.3542709351,52.4785194397],"type":"Point"}
}