{
  "type": "Feature",
  "properties": {
    "iso:country":"DE",
    "sg:address":"Gr\u00f6tzinger Str. 25",
    "sg:city":"Filderstadt",
    "sg:phone":"+49 7158/61378",
    "sg:postcode":"70794",
    "sg:province":"Baden-W\u00fcrttemberg",
    "wof:name":"Euroway Logistik Und Import-handels Gmbh",
    "wof:placetype":"venue"
},
  "geometry": {"coordinates":[9.2493124008,48.6476516724],"type":"Point"}
}