{
  "type": "Feature",
  "properties": {
    "iso:country":"DE",
    "sg:address":"\u00dcrziger Str. 23",
    "sg:city":"Bonn",
    "sg:phone":"+49 228/316579",
    "sg:postcode":"53175",
    "sg:province":"Nordrhein-Westfalen",
    "wof:name":"M. Narayan Hebbar Journalist",
    "wof:placetype":"venue"
},
  "geometry": {"coordinates":[7.1318240166,50.6961212158],"type":"Point"}
}