{
  "type": "Feature",
  "properties": {
    "iso:country":"DE",
    "sg:city":"Cadolzburg",
    "sg:phone":"+49 9103/1069",
    "sg:postcode":"90556",
    "sg:province":"Bayern",
    "wof:name":"Gabsteiger Verwaltungs Gmbh",
    "wof:placetype":"venue"
},
  "geometry": {"coordinates":[10.857407,49.460304],"type":"Point"}
}