{
  "type": "Feature",
  "properties": {
    "iso:country":"DE",
    "sg:address":"Paul-Mathis-Str. 1",
    "sg:city":"Kahla",
    "sg:phone":"+49 36424/890",
    "sg:postcode":"07768",
    "sg:province":"Th\u00fcringen",
    "wof:name":"Alicant Gmbh & Co. Kg",
    "wof:placetype":"venue"
},
  "geometry": {"coordinates":[11.5786056519,50.8174133301],"type":"Point"}
}