{
  "type": "Feature",
  "properties": {
    "iso:country":"DE",
    "sg:address":"Hubertusburg",
    "sg:city":"Wermsdorf",
    "sg:phone":"+49 34364/341",
    "sg:postcode":"04779",
    "sg:province":"Sachsen",
    "wof:name":"Schlo\u00dfmuseum Hubertusburg",
    "wof:placetype":"venue"
},
  "geometry": {"coordinates":[12.942005,51.276745],"type":"Point"}
}