{
  "type": "Feature",
  "properties": {
    "iso:country":"DE",
    "sg:address":"Nelkenweg 3",
    "sg:city":"Reichertshausen",
    "sg:postcode":"85293",
    "sg:province":"Bayern",
    "wof:name":"Publishing Solutions Edv Systemintegration Gmbh",
    "wof:placetype":"venue"
},
  "geometry": {"coordinates":[11.4601020813,48.4400062561],"type":"Point"}
}