{
  "type": "Feature",
  "properties": {
    "iso:country":"DE",
    "sg:address":"Im Grund 2",
    "sg:city":"W\u00fcrzburg",
    "sg:phone":"+49 931/94612",
    "sg:postcode":"97080",
    "sg:province":"Bayern",
    "wof:name":"Konrad Schmitt",
    "wof:placetype":"venue"
},
  "geometry": {"coordinates":[9.921097,49.829491],"type":"Point"}
}