{
  "type": "Feature",
  "properties": {
    "iso:country":"DE",
    "sg:address":"Rosenh\u00f6he 9/1",
    "sg:city":"Brackenheim-Meimsheim",
    "sg:phone":"+49 7135/1750",
    "sg:postcode":"74363",
    "sg:province":"Baden-W\u00fcrttemberg",
    "wof:name":"Kurz Silosysteme",
    "wof:placetype":"venue"
},
  "geometry": {"coordinates":[9.0021781921,49.0665817261],"type":"Point"}
}