{
  "type": "Feature",
  "properties": {
    "iso:country":"DE",
    "sg:address":"Nibelungenstr. 37",
    "sg:city":"Wendelstein",
    "sg:postcode":"90530",
    "sg:province":"Bayern",
    "wof:name":"Profil Einrichtungseinkauf Verwaltungs Gmbh",
    "wof:placetype":"venue"
},
  "geometry": {"coordinates":[11.1784601212,49.3662147522],"type":"Point"}
}