{
  "type": "Feature",
  "properties": {
    "iso:country":"DE",
    "sg:address":"Wagenfelder Str.14",
    "sg:city":"Hemsloh",
    "sg:phone":"+49 5446/2134",
    "sg:postcode":"49453",
    "sg:province":"Niedersachsen",
    "wof:name":"Hundepension",
    "wof:placetype":"venue"
},
  "geometry": {"coordinates":[8.505006,52.59293],"type":"Point"}
}