{
  "type": "Feature",
  "properties": {
    "iso:country":"DE",
    "sg:address":"Wiesenweg 24",
    "sg:city":"Bleckede",
    "sg:phone":"+49 5853/297",
    "sg:postcode":"21354",
    "sg:province":"Niedersachsen",
    "wof:name":"Johann-dietrich Gerken",
    "wof:placetype":"venue"
},
  "geometry": {"coordinates":[10.853337,53.241375],"type":"Point"}
}