{
  "type": "Feature",
  "properties": {
    "iso:country":"DE",
    "sg:address":"Am Gelskamp 19",
    "sg:city":"Detmold",
    "sg:phone":"+49 5231/61820",
    "sg:postcode":"32758",
    "sg:province":"Nordrhein-Westfalen",
    "wof:name":"Votteler Lackfabrik Gmbh & Co. Kg",
    "wof:placetype":"venue"
},
  "geometry": {"coordinates":[8.857702,51.949123],"type":"Point"}
}