{
  "type": "Feature",
  "properties": {
    "iso:country":"DE",
    "sg:address":"Karower Str. 33",
    "sg:city":"Genthin",
    "sg:phone":"+49 3933/2589",
    "sg:postcode":"39307",
    "sg:province":"Sachsen-Anhalt",
    "wof:name":"Uwe Kaufmann",
    "wof:placetype":"venue"
},
  "geometry": {"coordinates":[12.178007,52.40062],"type":"Point"}
}