{
  "type": "Feature",
  "properties": {
    "iso:country":"DE",
    "sg:address":"Solitudestr. 255",
    "sg:city":"Stuttgart",
    "sg:phone":"+49 711/881745",
    "sg:postcode":"70499",
    "sg:province":"Baden-W\u00fcrttemberg",
    "wof:name":"Elektro-service Gmbh",
    "wof:placetype":"venue"
},
  "geometry": {"coordinates":[9.1135940552,48.8158035278],"type":"Point"}
}