{
  "type": "Feature",
  "properties": {
    "iso:country":"DE",
    "sg:address":"Regerstr. 19",
    "sg:city":"Hattingen",
    "sg:phone":"+49 2324/82630",
    "sg:postcode":"45529",
    "sg:province":"Nordrhein-Westfalen",
    "wof:name":"Manfred Krampe",
    "wof:placetype":"venue"
},
  "geometry": {"coordinates":[7.16728,51.409252],"type":"Point"}
}