{
  "type": "Feature",
  "properties": {
    "iso:country":"DE",
    "sg:address":"Liersbachweg 6",
    "sg:city":"Bad M\u00fcnstereifel",
    "sg:phone":"+49 2257/560",
    "sg:postcode":"53902",
    "sg:province":"Nordrhein-Westfalen",
    "wof:name":"G. Und H. Schretzmann",
    "wof:placetype":"venue"
},
  "geometry": {"coordinates":[6.8459,50.50885],"type":"Point"}
}