{
  "type": "Feature",
  "properties": {
    "iso:country":"DE",
    "sg:address":"Feringastr. 16",
    "sg:city":"Unterf\u00f6hring",
    "sg:phone":"+49 89/9296426",
    "sg:postcode":"85774",
    "sg:province":"Bayern",
    "wof:name":"Schneider",
    "wof:placetype":"venue"
},
  "geometry": {"coordinates":[11.636575,48.178043],"type":"Point"}
}