{
  "type": "Feature",
  "properties": {
    "iso:country":"DE",
    "sg:address":"Karmeliterstr. 2",
    "sg:city":"Rottenburg",
    "sg:phone":"+49 7472/98490",
    "sg:postcode":"72108",
    "sg:province":"Baden-W\u00fcrttemberg",
    "wof:name":"Di\u00f6zesanstelle Buch",
    "wof:placetype":"venue"
},
  "geometry": {"coordinates":[8.9346046448,48.4762802124],"type":"Point"}
}