{
  "type": "Feature",
  "properties": {
    "iso:country":"DE",
    "sg:address":"Ledererzeile 10",
    "sg:city":"Wasserburg",
    "sg:phone":"+49 8071/2237",
    "sg:postcode":"83512",
    "sg:province":"Bayern",
    "wof:name":"Cafe Restaurant Stocker",
    "wof:placetype":"venue"
},
  "geometry": {"coordinates":[12.231429,48.062401],"type":"Point"}
}