{
  "type": "Feature",
  "properties": {
    "iso:country":"DE",
    "sg:address":"Am Grendel 4",
    "sg:city":"Rheinbreitbach",
    "sg:phone":"+49 2224/3105",
    "sg:postcode":"53619",
    "sg:province":"Rheinland-Pfalz",
    "wof:name":"Josef Sauer",
    "wof:placetype":"venue"
},
  "geometry": {"coordinates":[7.2316532135,50.6162643433],"type":"Point"}
}