{
  "type": "Feature",
  "properties": {
    "iso:country":"DE",
    "sg:address":"Othenbergstr. 33",
    "sg:city":"Bad Wildungen",
    "sg:phone":"+49 5621/2582",
    "sg:postcode":"34537",
    "sg:province":"Hessen",
    "wof:name":"E. Kruse Immobilienmakler",
    "wof:placetype":"venue"
},
  "geometry": {"coordinates":[9.1150274277,51.1114234924],"type":"Point"}
}