{
  "type": "Feature",
  "properties": {
    "iso:country":"DE",
    "sg:address":"Ringstr 9",
    "sg:city":"Frohburg",
    "sg:phone":"+49 34348/6910",
    "sg:postcode":"04654",
    "sg:province":"Sachsen",
    "wof:name":"Graichen Bau- Und M\u00f6belwerkst\u00e4tten Gmbh",
    "wof:placetype":"venue"
},
  "geometry": {"coordinates":[12.5611782074,51.0484275818],"type":"Point"}
}