{
  "type": "Feature",
  "properties": {
    "iso:country":"DE",
    "sg:address":"Seeleite 5",
    "sg:city":"Lisberg",
    "sg:phone":"+49 9549/472",
    "sg:postcode":"96170",
    "sg:province":"Bayern",
    "wof:name":"H. Grab Obstanbau",
    "wof:placetype":"venue"
},
  "geometry": {"coordinates":[10.7246246338,49.8928642273],"type":"Point"}
}