{
  "type": "Feature",
  "properties": {
    "iso:country":"DE",
    "sg:address":"Doberaner Str 44-47",
    "sg:city":"Rostock",
    "sg:phone":"+49 381/492900",
    "sg:postcode":"18057",
    "sg:province":"Mecklenburg-Vorpommern",
    "wof:name":"Inr Informationssysteme Rostock",
    "wof:placetype":"venue"
},
  "geometry": {"coordinates":[12.114718,54.091045],"type":"Point"}
}