{
  "type": "Feature",
  "properties": {
    "iso:country":"DE",
    "sg:address":"Kasseler Str. 24",
    "sg:city":"Vellmar",
    "sg:phone":"+49 561/821571",
    "sg:postcode":"34246",
    "sg:province":"Hessen",
    "wof:name":"L\u00f6wen-apotheke",
    "wof:placetype":"venue"
},
  "geometry": {"coordinates":[9.47791,51.353687],"type":"Point"}
}