{
  "type": "Feature",
  "properties": {
    "iso:country":"DE",
    "sg:address":"Brechtestr. 30",
    "sg:city":"Rheine",
    "sg:phone":"+49 5971/66083",
    "sg:postcode":"48431",
    "sg:province":"Nordrhein-Westfalen",
    "wof:name":"R. Foullois",
    "wof:placetype":"venue"
},
  "geometry": {"coordinates":[7.418944,52.283356],"type":"Point"}
}