{
  "type": "Feature",
  "properties": {
    "iso:country":"DE",
    "sg:address":"Ehmannstr. 29",
    "sg:city":"Ulm",
    "sg:phone":"+49 4973/168046",
    "sg:postcode":"89073",
    "sg:province":"Baden-W\u00fcrttemberg",
    "wof:name":"Raiffeisenbank Jungingen Eg",
    "wof:placetype":"venue"
},
  "geometry": {"coordinates":[9.989102,48.444],"type":"Point"}
}