{
  "type": "Feature",
  "properties": {
    "iso:country":"DE",
    "sg:address":"Am Ems-Vechte-Kanal 30",
    "sg:city":"Nordhorn",
    "sg:phone":"+49 5921/330630",
    "sg:postcode":"48531",
    "sg:province":"Niedersachsen",
    "wof:name":"Ring-haus Baubetreuung- Und Handels Gmbh",
    "wof:placetype":"venue"
},
  "geometry": {"coordinates":[7.068727,52.445572],"type":"Point"}
}