{
  "type": "Feature",
  "properties": {
    "iso:country":"DE",
    "sg:address":"Th\u00e4lmannstr. 126",
    "sg:city":"H\u00f6now",
    "sg:phone":"+49 30/54800854",
    "sg:postcode":"15366",
    "sg:province":"Brandenburg",
    "wof:name":"Gaby Kiesewetter Finanzberaterin",
    "wof:placetype":"venue"
},
  "geometry": {"coordinates":[13.6535377502,52.535030365],"type":"Point"}
}