{
  "type": "Feature",
  "properties": {
    "iso:country":"DE",
    "sg:address":"Mittlerer Pfad 15",
    "sg:city":"Stuttgart",
    "sg:postcode":"70499",
    "sg:province":"Baden-W\u00fcrttemberg",
    "wof:name":"Ernst & Young It-security Gmbh",
    "wof:placetype":"venue"
},
  "geometry": {"coordinates":[9.095556,48.820175],"type":"Point"}
}