{
  "type": "Feature",
  "properties": {
    "iso:country":"DE",
    "sg:address":"Ekkehardstr. 59 b",
    "sg:city":"Singen",
    "sg:phone":"+49 7731/66322",
    "sg:postcode":"78224",
    "sg:province":"Baden-W\u00fcrttemberg",
    "wof:name":"Burkhart",
    "wof:placetype":"venue"
},
  "geometry": {"coordinates":[8.843554,47.76326],"type":"Point"}
}