{
  "type": "Feature",
  "properties": {
    "iso:country":"DE",
    "sg:address":"An der Mosel 93",
    "sg:city":"Traben-Trarbach",
    "sg:phone":"+49 6541/6004",
    "sg:postcode":"56841",
    "sg:province":"Rheinland-Pfalz",
    "wof:name":"Hotel Krone",
    "wof:placetype":"venue"
},
  "geometry": {"coordinates":[7.1305541992,49.9552612305],"type":"Point"}
}