{
  "type": "Feature",
  "properties": {
    "iso:country":"DE",
    "sg:address":"Industriering Ost 66",
    "sg:city":"Kempen",
    "sg:phone":"+49 2152/559576",
    "sg:postcode":"47906",
    "sg:province":"Nordrhein-Westfalen",
    "wof:name":"Printec Systems Ges. F\u00fcr Edv-beratung -service",
    "wof:placetype":"venue"
},
  "geometry": {"coordinates":[6.434363842,51.3720436096],"type":"Point"}
}