{
  "type": "Feature",
  "properties": {
    "iso:country":"DE",
    "sg:address":"Jahnstr. 36",
    "sg:city":"H\u00fcnfelden",
    "sg:phone":"+49 6438/4841",
    "sg:postcode":"65597",
    "sg:province":"Hessen",
    "wof:name":"Klaus Hirschmann",
    "wof:placetype":"venue"
},
  "geometry": {"coordinates":[8.1141891479,50.3148117065],"type":"Point"}
}