{
  "type": "Feature",
  "properties": {
    "iso:country":"DE",
    "sg:address":"An der Rundwies 25",
    "sg:city":"Ayl",
    "sg:phone":"+49 6581/2822",
    "sg:postcode":"54441",
    "sg:province":"Rheinland-Pfalz",
    "wof:name":"H. Kautenburger",
    "wof:placetype":"venue"
},
  "geometry": {"coordinates":[6.5540351868,49.6319923401],"type":"Point"}
}