{
  "type": "Feature",
  "properties": {
    "iso:country":"DE",
    "sg:address":"Pfeiffersgasse 12",
    "sg:city":"Erfurt",
    "sg:postcode":"99084",
    "sg:province":"Th\u00fcringen",
    "wof:name":"Mephisto Consult Gmbh",
    "wof:placetype":"venue"
},
  "geometry": {"coordinates":[11.024806,50.984528],"type":"Point"}
}