{
  "type": "Feature",
  "properties": {
    "iso:country":"DE",
    "sg:address":"Hauptstr. 69",
    "sg:city":"Zweibr\u00fccken",
    "sg:phone":"+49 6332/75351",
    "sg:postcode":"66482",
    "sg:province":"Rheinland-Pfalz",
    "wof:name":"Carl Seybold-epting Ohg Augenoptiker",
    "wof:placetype":"venue"
},
  "geometry": {"coordinates":[7.361903,49.24931],"type":"Point"}
}