{
  "type": "Feature",
  "properties": {
    "iso:country":"DE",
    "sg:address":"Bahnhofstr. 20",
    "sg:city":"Me\u00dfkirch",
    "sg:phone":"+49 7575/92300",
    "sg:postcode":"88605",
    "sg:province":"Baden-W\u00fcrttemberg",
    "wof:name":"Bs Baumaschinen-service Gmbh",
    "wof:placetype":"venue"
},
  "geometry": {"coordinates":[9.11814,47.997738],"type":"Point"}
}