{
  "type": "Feature",
  "properties": {
    "iso:country":"DE",
    "sg:address":"Bremer Str. 2",
    "sg:city":"Riede",
    "sg:phone":"+49 4294/341",
    "sg:postcode":"27339",
    "sg:province":"Niedersachsen",
    "wof:name":"Karl H\u00fclss",
    "wof:placetype":"venue"
},
  "geometry": {"coordinates":[8.938589,52.974312],"type":"Point"}
}