{
  "type": "Feature",
  "properties": {
    "iso:country":"DE",
    "sg:address":"Lange Str. 9",
    "sg:city":"Bremerhaven",
    "sg:phone":"+49 471/81411",
    "sg:postcode":"27580",
    "sg:province":"Bremen",
    "wof:name":"Hinrich Hemje Inh. Gerhard Nieb\u00fchr",
    "wof:placetype":"venue"
},
  "geometry": {"coordinates":[8.5956020355,53.5709838867],"type":"Point"}
}