{
  "type": "Feature",
  "properties": {
    "iso:country":"DE",
    "sg:address":"Rathsbergstr. 26",
    "sg:city":"N\u00fcrnberg",
    "sg:postcode":"90411",
    "sg:province":"Bayern",
    "wof:name":"M. Kaiser Gmbh",
    "wof:placetype":"venue"
},
  "geometry": {"coordinates":[11.1040792465,49.4881858826],"type":"Point"}
}