{
  "type": "Feature",
  "properties": {
    "iso:country":"DE",
    "sg:address":"Neugartenstr. 16",
    "sg:city":"Sulzbach",
    "sg:phone":"+49 6196/71669",
    "sg:postcode":"65843",
    "sg:province":"Hessen",
    "wof:name":"Herbert Arlt",
    "wof:placetype":"venue"
},
  "geometry": {"coordinates":[8.5286207199,50.1361885071],"type":"Point"}
}