{
  "type": "Feature",
  "properties": {
    "iso:country":"DE",
    "sg:address":"Amalienstr. 19",
    "sg:city":"F\u00fcrth",
    "sg:phone":"+49 911/773472",
    "sg:postcode":"90763",
    "sg:province":"Bayern",
    "wof:name":"Foto Sergio, Ihr Italienischer Fotograf",
    "wof:placetype":"venue"
},
  "geometry": {"coordinates":[10.986938,49.468586],"type":"Point"}
}