{
  "type": "Feature",
  "properties": {
    "iso:country":"DE",
    "sg:address":"Romanplatz 9",
    "sg:city":"M\u00fcnchen",
    "sg:phone":"+49 89/1781212",
    "sg:postcode":"80639",
    "sg:province":"Bayern",
    "wof:name":"B & B Trockenbau Gmbh",
    "wof:placetype":"venue"
},
  "geometry": {"coordinates":[11.511808,48.155029],"type":"Point"}
}