{
  "type": "Feature",
  "properties": {
    "iso:country":"DE",
    "sg:address":"Lindelstr. 29",
    "sg:city":"Oberstenfeld",
    "sg:phone":"+49 7062/5471",
    "sg:postcode":"71720",
    "sg:province":"Baden-W\u00fcrttemberg",
    "wof:name":"Bestattungsinstitut Bottwartal Und Murr",
    "wof:placetype":"venue"
},
  "geometry": {"coordinates":[9.315757,49.021347],"type":"Point"}
}