{
  "type": "Feature",
  "properties": {
    "iso:country":"DE",
    "sg:address":"Antonienh\u00fcttenweg 16",
    "sg:city":"Coswig",
    "sg:phone":"+49 34903/64244",
    "sg:postcode":"06869",
    "sg:province":"Sachsen-Anhalt",
    "wof:name":"Pas Pumpenservice Gmbh",
    "wof:placetype":"venue"
},
  "geometry": {"coordinates":[12.440617,51.891647],"type":"Point"}
}