{
  "type": "Feature",
  "properties": {
    "iso:country":"DE",
    "sg:address":"Beerenstr. 2",
    "sg:city":"Steinhagen",
    "sg:phone":"+49 5204/8554",
    "sg:postcode":"33803",
    "sg:province":"Nordrhein-Westfalen",
    "wof:name":"Kdo Im Handwerk Gmbh",
    "wof:placetype":"venue"
},
  "geometry": {"coordinates":[8.4287557602,52.0156478882],"type":"Point"}
}