{
  "type": "Feature",
  "properties": {
    "iso:country":"DE",
    "sg:address":"Hasselbrookstr. 15",
    "sg:city":"Hamburg",
    "sg:phone":"+49 40/2515030",
    "sg:postcode":"22089",
    "sg:province":"Hamburg",
    "wof:name":"Badenia Bausparkasse Gmbh",
    "wof:placetype":"venue"
},
  "geometry": {"coordinates":[10.038986,53.562496],"type":"Point"}
}