{
  "type": "Feature",
  "properties": {
    "iso:country":"DE",
    "sg:address":"Hinterlandstr. 3",
    "sg:city":"Eschwege",
    "sg:phone":"+49 5651/21080",
    "sg:postcode":"37269",
    "sg:province":"Hessen",
    "wof:name":"Frank Grebenstein",
    "wof:placetype":"venue"
},
  "geometry": {"coordinates":[10.00633,51.185844],"type":"Point"}
}