{
  "type": "Feature",
  "properties": {
    "iso:country":"DE",
    "sg:address":"Gro\u00dfstr. 83",
    "sg:city":"Treuenbrietzen",
    "sg:phone":"+49 33748/15458",
    "sg:postcode":"14929",
    "sg:province":"Brandenburg",
    "wof:name":"C. Edinger",
    "wof:placetype":"venue"
},
  "geometry": {"coordinates":[12.8707399368,52.0968208313],"type":"Point"}
}