{
  "type": "Feature",
  "properties": {
    "iso:country":"DE",
    "sg:address":"Germendorfer Str. 6",
    "sg:city":"Velten",
    "sg:phone":"+49 3304/33073",
    "sg:postcode":"16727",
    "sg:province":"Brandenburg",
    "wof:name":"Neumann Immobilienmakler",
    "wof:placetype":"venue"
},
  "geometry": {"coordinates":[13.1794872284,52.6959152222],"type":"Point"}
}