{
  "type": "Feature",
  "properties": {
    "iso:country":"DE",
    "sg:address":"Hagener Str. 3",
    "sg:city":"Kreuztal",
    "sg:phone":"+49 2732/21228",
    "sg:postcode":"57223",
    "sg:province":"Nordrhein-Westfalen",
    "wof:name":"Bistro Max",
    "wof:placetype":"venue"
},
  "geometry": {"coordinates":[7.9724888802,50.9763870239],"type":"Point"}
}