{
  "type": "Feature",
  "properties": {
    "iso:country":"DE",
    "sg:address":"Poststr. 6",
    "sg:city":"W\u00fcnschendorf",
    "sg:phone":"+49 36603/88212",
    "sg:postcode":"07570",
    "sg:province":"Th\u00fcringen",
    "wof:name":"Macrobius-apotheke Inh. Karl-marx Geisenheyner",
    "wof:placetype":"venue"
},
  "geometry": {"coordinates":[12.096273,50.795097],"type":"Point"}
}