{
  "type": "Feature",
  "properties": {
    "iso:country":"DE",
    "sg:address":"Im Wiesengrund 14",
    "sg:city":"Ruppertshofen",
    "sg:phone":"+49 6772/2292",
    "sg:postcode":"56357",
    "sg:province":"Rheinland-Pfalz",
    "wof:name":"Industrieschutz Walter Gmbh",
    "wof:placetype":"venue"
},
  "geometry": {"coordinates":[7.8073248863,50.1972007751],"type":"Point"}
}