{
  "type": "Feature",
  "properties": {
    "iso:country":"DE",
    "sg:address":"Hauptstr. 106",
    "sg:city":"Viersen",
    "sg:phone":"+49 2162/17195",
    "sg:postcode":"41747",
    "sg:province":"Nordrhein-Westfalen",
    "wof:name":"Monika Goertz",
    "wof:placetype":"venue"
},
  "geometry": {"coordinates":[6.391816,51.254761],"type":"Point"}
}