{
  "type": "Feature",
  "properties": {
    "iso:country":"DE",
    "sg:address":"Ludwigsluster Str. 30",
    "sg:city":"Parchim",
    "sg:phone":"+49 3871/441198",
    "sg:postcode":"19370",
    "sg:province":"Mecklenburg-Vorpommern",
    "wof:name":"Loewenzahn",
    "wof:placetype":"venue"
},
  "geometry": {"coordinates":[11.828651,53.428101],"type":"Point"}
}