{
  "type": "Feature",
  "properties": {
    "iso:country":"DE",
    "sg:address":"Lienzinger Str. 32",
    "sg:city":"M\u00fchlacker",
    "sg:phone":"+49 7041/7061",
    "sg:postcode":"75417",
    "sg:province":"Baden-W\u00fcrttemberg",
    "wof:name":"Das Der Au\u00dfergew\u00f6hnliche Service F\u00fcr Dienstleistungen",
    "wof:placetype":"venue"
},
  "geometry": {"coordinates":[8.8515233994,48.9551963806],"type":"Point"}
}