{
  "type": "Feature",
  "properties": {
    "iso:country":"DE",
    "sg:address":"Schlesierweg 3",
    "sg:city":"Herzberg",
    "sg:phone":"+49 5521/2424",
    "sg:postcode":"37412",
    "sg:province":"Niedersachsen",
    "wof:name":"Willi Aderhold",
    "wof:placetype":"venue"
},
  "geometry": {"coordinates":[10.31169,51.614849],"type":"Point"}
}