{
  "type": "Feature",
  "properties": {
    "iso:country":"DE",
    "sg:address":"Gewerbestr. 4",
    "sg:city":"Voerde",
    "sg:phone":"+49 2855/96340",
    "sg:postcode":"46562",
    "sg:province":"Nordrhein-Westfalen",
    "wof:name":"R. A. Patt Ingenieurb\u00fcro Gmbh",
    "wof:placetype":"venue"
},
  "geometry": {"coordinates":[6.675517,51.617214],"type":"Point"}
}