{
  "type": "Feature",
  "properties": {
    "iso:country":"DE",
    "sg:address":"Im Schollengarten 2",
    "sg:city":"Bruchsal",
    "sg:phone":"+49 7257/91070",
    "sg:postcode":"76646",
    "sg:province":"Baden-W\u00fcrttemberg",
    "wof:name":"Wima Maschinen- Und Ger\u00e4tebau Gmbh",
    "wof:placetype":"venue"
},
  "geometry": {"coordinates":[8.55781,49.095558],"type":"Point"}
}