{
  "type": "Feature",
  "properties": {
    "iso:country":"DE",
    "sg:address":"Humboldtstr. 8",
    "sg:city":"Halver",
    "sg:phone":"+49 2353/2507",
    "sg:postcode":"58553",
    "sg:province":"Nordrhein-Westfalen",
    "wof:name":"Ernst Pohl Immobilienmakler",
    "wof:placetype":"venue"
},
  "geometry": {"coordinates":[7.4952859879,51.1875915527],"type":"Point"}
}