{
  "type": "Feature",
  "properties": {
    "iso:country":"DE",
    "sg:address":"Ohbaumsfeld 11A",
    "sg:city":"Seevetal",
    "sg:postcode":"21220",
    "sg:province":"Niedersachsen",
    "wof:name":"Chempro Chemikalien Exportgesellschaft Mbh",
    "wof:placetype":"venue"
},
  "geometry": {"coordinates":[10.0543842316,53.3422203064],"type":"Point"}
}