{
  "type": "Feature",
  "properties": {
    "iso:country":"DE",
    "sg:address":"M\u00fcnchener Str. 15",
    "sg:city":"Herrieden",
    "sg:phone":"+49 9825/5319",
    "sg:postcode":"91567",
    "sg:province":"Bayern",
    "wof:name":"Rudolf Richter",
    "wof:placetype":"venue"
},
  "geometry": {"coordinates":[10.497367,49.235233],"type":"Point"}
}