{
  "type": "Feature",
  "properties": {
    "iso:country":"DE",
    "sg:address":"Rosenheimer Landstr. 141",
    "sg:city":"Riemerling",
    "sg:phone":"+49 89/60850266",
    "sg:postcode":"85521",
    "sg:province":"Bayern",
    "wof:name":"Jacques Weindepot Gmbh",
    "wof:placetype":"venue"
},
  "geometry": {"coordinates":[11.6698074341,48.0527153015],"type":"Point"}
}