{
  "type": "Feature",
  "properties": {
    "iso:country":"DE",
    "sg:address":"Lothringer Str. 114",
    "sg:city":"Rehlingen-Siersburg",
    "sg:phone":"+49 6833/359",
    "sg:postcode":"66780",
    "sg:province":"Saarland",
    "wof:name":"Friedbert Weitmann",
    "wof:placetype":"venue"
},
  "geometry": {"coordinates":[6.616084,49.356564],"type":"Point"}
}