{
  "type": "Feature",
  "properties": {
    "iso:country":"DE",
    "sg:address":"August-Bebel-Str. 1",
    "sg:city":"Frohburg",
    "sg:phone":"+49 34348/51376",
    "sg:postcode":"04654",
    "sg:province":"Sachsen",
    "wof:name":"Anna Hiller",
    "wof:placetype":"venue"
},
  "geometry": {"coordinates":[12.5577898026,51.0582847595],"type":"Point"}
}