{
  "type": "Feature",
  "properties": {
    "iso:country":"DE",
    "sg:address":"Bruno-Granz-Str. 60",
    "sg:city":"Chemnitz",
    "sg:phone":"+49 371/227794",
    "sg:postcode":"09122",
    "sg:province":"Sachsen",
    "wof:name":"Dieter Kandler",
    "wof:placetype":"venue"
},
  "geometry": {"coordinates":[12.888615,50.79427],"type":"Point"}
}