{
  "type": "Feature",
  "properties": {
    "iso:country":"DE",
    "sg:address":"Kaiserstr. 231-233",
    "sg:city":"Karlsruhe",
    "sg:postcode":"76133",
    "sg:province":"Baden-W\u00fcrttemberg",
    "wof:name":"Elus Media Design Gmbh",
    "wof:placetype":"venue"
},
  "geometry": {"coordinates":[8.3914966583,49.0100364685],"type":"Point"}
}