{
  "type": "Feature",
  "properties": {
    "iso:country":"DE",
    "sg:address":"H\u00f6lderlinhof 1",
    "sg:city":"Bissendorf",
    "sg:phone":"+49 171 7729477",
    "sg:postcode":"49143",
    "sg:province":"Niedersachsen",
    "wof:name":"Induction Electronic",
    "wof:placetype":"venue"
},
  "geometry": {"coordinates":[8.1655550003,52.2671012878],"type":"Point"}
}