{
  "type": "Feature",
  "properties": {
    "iso:country":"DE",
    "sg:address":"Zirrer Str. 76",
    "sg:city":"Wiehl",
    "sg:phone":"+49 2262/93938",
    "sg:postcode":"51674",
    "sg:province":"Nordrhein-Westfalen",
    "wof:name":"Ellen Biederst\u00e4dt Steuerbevollm\u00e4chtigte",
    "wof:placetype":"venue"
},
  "geometry": {"coordinates":[7.5566749573,50.9440498352],"type":"Point"}
}