{
  "type": "Feature",
  "properties": {
    "iso:country":"DE",
    "sg:address":"Martinsreuther Str. 45",
    "sg:city":"Hof",
    "sg:phone":"+49 9281/93838",
    "sg:postcode":"95032",
    "sg:province":"Bayern",
    "wof:name":"Dieter G\u00fcnther Architekt",
    "wof:placetype":"venue"
},
  "geometry": {"coordinates":[11.908871,50.296318],"type":"Point"}
}