{
  "type": "Feature",
  "properties": {
    "iso:country":"DE",
    "sg:address":"Kr\u00f6peliner Str. 3",
    "sg:city":"Altenhagen",
    "sg:phone":"+49 38292/488",
    "sg:postcode":"18236",
    "sg:province":"Mecklenburg-Vorpommern",
    "wof:name":"Walter Rach",
    "wof:placetype":"venue"
},
  "geometry": {"coordinates":[11.79075,54.028267],"type":"Point"}
}