{
  "type": "Feature",
  "properties": {
    "iso:country":"DE",
    "sg:address":"Parkstr. 5-7",
    "sg:city":"Burglengenfeld",
    "sg:phone":"+49 9471/702420",
    "sg:postcode":"93133",
    "sg:province":"Bayern",
    "wof:name":"Alpha Jeans Gmbh",
    "wof:placetype":"venue"
},
  "geometry": {"coordinates":[12.0471639633,49.2005195618],"type":"Point"}
}