{
  "type": "Feature",
  "properties": {
    "iso:country":"DE",
    "sg:address":"Tiefental 14",
    "sg:city":"Wunstorf",
    "sg:phone":"+49 5033/5350",
    "sg:postcode":"31515",
    "sg:province":"Niedersachsen",
    "wof:name":"August Behling Inh. Herbert Baumgartner",
    "wof:placetype":"venue"
},
  "geometry": {"coordinates":[9.360263,52.456268],"type":"Point"}
}