{
  "type": "Feature",
  "properties": {
    "iso:country":"DE",
    "sg:address":"Papitzer Str. 8",
    "sg:city":"Kolkwitz",
    "sg:postcode":"03099",
    "sg:province":"Brandenburg",
    "wof:name":"Euco Uhle & Co. Kg",
    "wof:placetype":"venue"
},
  "geometry": {"coordinates":[14.224591,51.767227],"type":"Point"}
}