{
  "type": "Feature",
  "properties": {
    "iso:country":"DE",
    "sg:address":"Eckersm\u00fchlener Hauptstr. 32",
    "sg:city":"Roth",
    "sg:phone":"+49 9171/2832",
    "sg:postcode":"91154",
    "sg:province":"Bayern",
    "wof:name":"Betten-karg Inh. J. Baier",
    "wof:placetype":"venue"
},
  "geometry": {"coordinates":[11.1421899796,49.2154884338],"type":"Point"}
}