{
  "type": "Feature",
  "properties": {
    "iso:country":"DE",
    "sg:address":"Im Falschen Biewertal 55",
    "sg:city":"Trier",
    "sg:phone":"+49 651/64056",
    "sg:postcode":"54293",
    "sg:province":"Rheinland-Pfalz",
    "wof:name":"Oberst",
    "wof:placetype":"venue"
},
  "geometry": {"coordinates":[6.65303,49.77602],"type":"Point"}
}