{
  "type": "Feature",
  "properties": {
    "iso:country":"DE",
    "sg:address":"Podbielskistr. 11",
    "sg:city":"Hannover",
    "sg:phone":"+49 511/9600",
    "sg:postcode":"30655",
    "sg:province":"Niedersachsen",
    "wof:name":"Bahlsen Versicherungs- Vermittlung Gmbh",
    "wof:placetype":"venue"
},
  "geometry": {"coordinates":[9.7921476364,52.4034347534],"type":"Point"}
}