{
  "type": "Feature",
  "properties": {
    "iso:country":"DE",
    "sg:address":"Hauptstr. 14",
    "sg:city":"Waldachtal",
    "sg:phone":"+49 7443/8172",
    "sg:postcode":"72178",
    "sg:province":"Baden-W\u00fcrttemberg",
    "wof:name":"Carl Hornung",
    "wof:placetype":"venue"
},
  "geometry": {"coordinates":[8.5649061203,48.4888191223],"type":"Point"}
}