{
  "type": "Feature",
  "properties": {
    "iso:country":"DE",
    "sg:address":"Rosenweg 10",
    "sg:city":"Kappelrodeck",
    "sg:phone":"+49 7842/2891",
    "sg:postcode":"77876",
    "sg:province":"Baden-W\u00fcrttemberg",
    "wof:name":"Gerd O. Falk Heilpraktiker",
    "wof:placetype":"venue"
},
  "geometry": {"coordinates":[8.1188602448,48.594959259],"type":"Point"}
}