{
  "type": "Feature",
  "properties": {
    "iso:country":"DE",
    "sg:address":"Stahlstr. 11",
    "sg:city":"Wiefelstede",
    "sg:phone":"+49 4402/6378",
    "sg:postcode":"26215",
    "sg:province":"Niedersachsen",
    "wof:name":"Johann Eiting Inh. Dieter Eiting",
    "wof:placetype":"venue"
},
  "geometry": {"coordinates":[8.1211681366,53.2472038269],"type":"Point"}
}