{
  "type": "Feature",
  "properties": {
    "iso:country":"DE",
    "sg:address":"Augsburger Str. 704",
    "sg:city":"Stuttgart",
    "sg:phone":"+49 711/9189630",
    "sg:postcode":"70329",
    "sg:province":"Baden-W\u00fcrttemberg",
    "wof:name":"Wolf & M\u00f6gle Gmbh",
    "wof:placetype":"venue"
},
  "geometry": {"coordinates":[9.2712392807,48.7608985901],"type":"Point"}
}