{
  "type": "Feature",
  "properties": {
    "iso:country":"DE",
    "sg:address":"G\u00f6rmarstr. 10",
    "sg:city":"M\u00fchlhausen",
    "sg:phone":"+49 36014/40236",
    "sg:postcode":"99974",
    "sg:province":"Th\u00fcringen",
    "wof:name":"Br\u00e4utigam Und Ottburg Rechtsanw\u00e4lte",
    "wof:placetype":"venue"
},
  "geometry": {"coordinates":[10.4634809494,51.2089385986],"type":"Point"}
}