{
  "type": "Feature",
  "properties": {
    "iso:country":"DE",
    "sg:address":"Frankfurter Landstr. 40",
    "sg:city":"Darmstadt",
    "sg:phone":"+49 6151/375930",
    "sg:postcode":"64291",
    "sg:province":"Hessen",
    "wof:name":"Karsten Bliesener Und Susanne Hehn-bliesener",
    "wof:placetype":"venue"
},
  "geometry": {"coordinates":[8.655584,49.90316],"type":"Point"}
}