{
  "type": "Feature",
  "properties": {
    "iso:country":"DE",
    "sg:address":"Kirchplatz 3",
    "sg:city":"Eichstetten",
    "sg:phone":"+49 7663/1251",
    "sg:postcode":"79356",
    "sg:province":"Baden-W\u00fcrttemberg",
    "wof:name":"Ev. Pfarramt Eichstetten",
    "wof:placetype":"venue"
},
  "geometry": {"coordinates":[7.7453269958,48.0936965942],"type":"Point"}
}