{
  "type": "Feature",
  "properties": {
    "iso:country":"DE",
    "sg:address":"Magdalenenallee 4",
    "sg:city":"Halstenbek",
    "sg:phone":"+49 4101/43062",
    "sg:postcode":"25469",
    "sg:province":"Schleswig-Holstein",
    "wof:name":"Heinr. Hartwich Sen.",
    "wof:placetype":"venue"
},
  "geometry": {"coordinates":[9.8365411758,53.6339454651],"type":"Point"}
}