{
  "type": "Feature",
  "properties": {
    "iso:country":"DE",
    "sg:address":"K\u00fcckelswerth 23",
    "sg:city":"Ratingen",
    "sg:postcode":"40883",
    "sg:province":"Nordrhein-Westfalen",
    "wof:name":"Scripta Verlagesges. Mbh",
    "wof:placetype":"venue"
},
  "geometry": {"coordinates":[6.919178009,51.3324966431],"type":"Point"}
}