{
  "type": "Feature",
  "properties": {
    "iso:country":"DE",
    "sg:address":"Henry-Ford-Ii-Str. 15",
    "sg:city":"W\u00fclfrath",
    "sg:phone":"+49 4920/589050",
    "sg:postcode":"42489",
    "sg:province":"Nordrhein-Westfalen",
    "wof:name":"Visteon Werke Deutschland Gmbh",
    "wof:placetype":"venue"
},
  "geometry": {"coordinates":[7.04138,51.285202],"type":"Point"}
}