{
  "type": "Feature",
  "properties": {
    "iso:country":"DE",
    "sg:address":"Bahnhofstr. 52 A",
    "sg:city":"Ellwangen",
    "sg:phone":"+49 7961/53744",
    "sg:postcode":"73479",
    "sg:province":"Baden-W\u00fcrttemberg",
    "wof:name":"Vereinsgastst\u00e4tte Tanzsport- Club Blau-rot Ellwangen E. V.",
    "wof:placetype":"venue"
},
  "geometry": {"coordinates":[10.1296415329,48.9686698914],"type":"Point"}
}