{
  "type": "Feature",
  "properties": {
    "iso:country":"DE",
    "sg:address":"Ringstr. 13",
    "sg:city":"Burgbrohl",
    "sg:phone":"+49 2636/929175",
    "sg:postcode":"56659",
    "sg:province":"Rheinland-Pfalz",
    "wof:name":"Pension Haus Elisabeth",
    "wof:placetype":"venue"
},
  "geometry": {"coordinates":[7.2564630508,50.4590682983],"type":"Point"}
}