{
  "type": "Feature",
  "properties": {
    "iso:country":"DE",
    "sg:address":"Weidkamp 180",
    "sg:city":"Essen",
    "sg:postcode":"45356",
    "sg:province":"Nordrhein-Westfalen",
    "wof:name":"Kaiser-keller Gmbh",
    "wof:placetype":"venue"
},
  "geometry": {"coordinates":[6.9510579109,51.4868812561],"type":"Point"}
}