{
  "type": "Feature",
  "properties": {
    "iso:country":"DE",
    "sg:address":"Besenstiel 41",
    "sg:city":"Kappelrodeck",
    "sg:phone":"+49 7842/8500",
    "sg:postcode":"77876",
    "sg:province":"Baden-W\u00fcrttemberg",
    "wof:name":"Haus Lea",
    "wof:placetype":"venue"
},
  "geometry": {"coordinates":[8.126737,48.59259],"type":"Point"}
}