{
  "type": "Feature",
  "properties": {
    "iso:country":"DE",
    "sg:address":"Julius-Leber-Str. 32",
    "sg:city":"Deisslingen",
    "sg:phone":"+49 7420",
    "sg:postcode":"78652",
    "sg:province":"Baden-W\u00fcrttemberg",
    "wof:name":"Beach Palms",
    "wof:placetype":"venue"
},
  "geometry": {"coordinates":[8.6135368347,48.1106071472],"type":"Point"}
}