{
  "type": "Feature",
  "properties": {
    "iso:country":"DE",
    "sg:address":"Gartenstr. 45",
    "sg:city":"G\u00f6ppingen",
    "sg:phone":"+49 7161/685005",
    "sg:postcode":"73033",
    "sg:province":"Baden-W\u00fcrttemberg",
    "wof:name":"J. Frankster",
    "wof:placetype":"venue"
},
  "geometry": {"coordinates":[9.6534252167,48.7007789612],"type":"Point"}
}