{
  "type": "Feature",
  "properties": {
    "iso:country":"DE",
    "sg:address":"Rosenweg 3",
    "sg:city":"Stahnsdorf",
    "sg:phone":"+49 3329/610842",
    "sg:postcode":"14532",
    "sg:province":"Brandenburg",
    "wof:name":"Behadis Meyer Gmbh",
    "wof:placetype":"venue"
},
  "geometry": {"coordinates":[13.221969,52.383781],"type":"Point"}
}