{
  "type": "Feature",
  "properties": {
    "iso:country":"DE",
    "sg:address":"Kestnerstr. 34",
    "sg:city":"Hannover",
    "sg:phone":"+49 511/855388",
    "sg:postcode":"30159",
    "sg:province":"Niedersachsen",
    "wof:name":"Pizzeria Super Lativa",
    "wof:placetype":"venue"
},
  "geometry": {"coordinates":[9.7583732605,52.3708381653],"type":"Point"}
}