{
  "type": "Feature",
  "properties": {
    "iso:country":"DE",
    "sg:address":"Torstr. 10",
    "sg:city":"Leverkusen",
    "sg:phone":"+49 2171/52203",
    "sg:postcode":"51381",
    "sg:province":"Nordrhein-Westfalen",
    "wof:name":"Imr Ms Industrie- Rohrleitungsbau Und",
    "wof:placetype":"venue"
},
  "geometry": {"coordinates":[7.0166101456,51.0621604919],"type":"Point"}
}