{
  "type": "Feature",
  "properties": {
    "iso:country":"DE",
    "sg:address":"Dudweilerstr. 71a",
    "sg:city":"Saarbr\u00fccken",
    "sg:phone":"+49 681/3906292",
    "sg:postcode":"66111",
    "sg:province":"Saarland",
    "wof:name":"La Marina",
    "wof:placetype":"venue"
},
  "geometry": {"coordinates":[6.998688221,49.2388877869],"type":"Point"}
}