{
  "type": "Feature",
  "properties": {
    "iso:country":"DE",
    "sg:address":"Heisterweg 41",
    "sg:city":"H\u00fcnxe",
    "sg:phone":"+49 2064/39471",
    "sg:postcode":"46569",
    "sg:province":"Nordrhein-Westfalen",
    "wof:name":"A. Rusterholt",
    "wof:placetype":"venue"
},
  "geometry": {"coordinates":[6.7657299042,51.641998291],"type":"Point"}
}