{
  "type": "Feature",
  "properties": {
    "iso:country":"DE",
    "sg:address":"Vaalser Str. 58",
    "sg:city":"Aachen",
    "sg:phone":"+49 241/81787",
    "sg:postcode":"52064",
    "sg:province":"Nordrhein-Westfalen",
    "wof:name":"Juliane Strang",
    "wof:placetype":"venue"
},
  "geometry": {"coordinates":[6.071358,50.77026],"type":"Point"}
}