{
  "type": "Feature",
  "properties": {
    "iso:country":"DE",
    "sg:address":"Linnerheide 24",
    "sg:city":"Bad Essen",
    "sg:phone":"+49 5472/73565",
    "sg:postcode":"49152",
    "sg:province":"Niedersachsen",
    "wof:name":"W. W\u00fcbbeler",
    "wof:placetype":"venue"
},
  "geometry": {"coordinates":[8.402164,52.287849],"type":"Point"}
}