{
  "type": "Feature",
  "properties": {
    "iso:country":"DE",
    "sg:address":"Bahnhofstr. 50",
    "sg:city":"Witten",
    "sg:phone":"+49 2302/51660",
    "sg:postcode":"58452",
    "sg:province":"Nordrhein-Westfalen",
    "wof:name":"Henry Fashion Concept Gmbh",
    "wof:placetype":"venue"
},
  "geometry": {"coordinates":[7.331165,51.43792],"type":"Point"}
}