{
  "type": "Feature",
  "properties": {
    "iso:country":"DE",
    "sg:address":"Glendalestr. 4",
    "sg:city":"Memmingen",
    "sg:phone":"+49 8331/89443",
    "sg:postcode":"87700",
    "sg:province":"Bayern",
    "wof:name":"B\u00e4ckerei Bittner Ohg",
    "wof:placetype":"venue"
},
  "geometry": {"coordinates":[10.165416,48.004086],"type":"Point"}
}