{
  "type": "Feature",
  "properties": {
    "iso:country":"DE",
    "sg:address":"Wernsbach 22",
    "sg:city":"Georgensgm\u00fcnd",
    "sg:phone":"+49 9172/410",
    "sg:postcode":"91166",
    "sg:province":"Bayern",
    "wof:name":"Schopf Gmbh",
    "wof:placetype":"venue"
},
  "geometry": {"coordinates":[11.0704202652,49.1803131104],"type":"Point"}
}