{
  "type": "Feature",
  "properties": {
    "iso:country":"DE",
    "sg:address":"Rochusstr. 170",
    "sg:city":"Bonn",
    "sg:phone":"+49 228/625578",
    "sg:postcode":"53123",
    "sg:province":"Nordrhein-Westfalen",
    "wof:name":"Peter Monschau",
    "wof:placetype":"venue"
},
  "geometry": {"coordinates":[7.050102,50.715981],"type":"Point"}
}