{
  "type": "Feature",
  "properties": {
    "iso:country":"DE",
    "sg:address":"Maxstr. 55",
    "sg:city":"Bonn",
    "sg:phone":"+49 228/636768",
    "sg:postcode":"53111",
    "sg:province":"Nordrhein-Westfalen",
    "wof:name":"Ruth Oges",
    "wof:placetype":"venue"
},
  "geometry": {"coordinates":[7.093138,50.738567],"type":"Point"}
}