{
  "type": "Feature",
  "properties": {
    "iso:country":"DE",
    "sg:address":"Otto-Devrient-Str. 7",
    "sg:city":"Jena",
    "sg:phone":"+49 3641/447795",
    "sg:postcode":"07743",
    "sg:province":"Th\u00fcringen",
    "wof:name":"Dr. Med. Ingeburg Schnabel",
    "wof:placetype":"venue"
},
  "geometry": {"coordinates":[11.56867,50.934372],"type":"Point"}
}