{
  "type": "Feature",
  "properties": {
    "iso:country":"DE",
    "sg:address":"A.-F.-vom-Endt-Str. 22",
    "sg:city":"Auerbach",
    "sg:phone":"+49 9643/795",
    "sg:postcode":"91275",
    "sg:province":"Bayern",
    "wof:name":"Hans Friedl",
    "wof:placetype":"venue"
},
  "geometry": {"coordinates":[11.629399,49.693096],"type":"Point"}
}