{
  "type": "Feature",
  "properties": {
    "iso:country":"DE",
    "sg:address":"Alte Pforzheimer Str. 63",
    "sg:city":"Wurmberg",
    "sg:postcode":"75449",
    "sg:province":"Baden-W\u00fcrttemberg",
    "wof:name":"Protrade Consumer Products Gmbh",
    "wof:placetype":"venue"
},
  "geometry": {"coordinates":[8.7997817993,48.8751220703],"type":"Point"}
}