{
  "type": "Feature",
  "properties": {
    "iso:country":"DE",
    "sg:address":"Lindenstr. 14",
    "sg:city":"M\u00f6ckern",
    "sg:phone":"+49 39221/413",
    "sg:postcode":"39291",
    "sg:province":"Sachsen-Anhalt",
    "wof:name":"T & S Objekteinrichtungen Gmbh",
    "wof:placetype":"venue"
},
  "geometry": {"coordinates":[11.95208,52.153149],"type":"Point"}
}