{
  "type": "Feature",
  "properties": {
    "iso:country":"DE",
    "sg:address":"Im Gesenk 10",
    "sg:city":"Lehrte",
    "sg:phone":"+49 5132/54276",
    "sg:postcode":"31275",
    "sg:province":"Niedersachsen",
    "wof:name":"G\u00fcnter Tobschall Gmbh & Co. Kg",
    "wof:placetype":"venue"
},
  "geometry": {"coordinates":[9.956988,52.359638],"type":"Point"}
}