{
  "type": "Feature",
  "properties": {
    "iso:country":"DE",
    "sg:address":"Hauptstr. 62",
    "sg:city":"Sprockh\u00f6vel",
    "sg:phone":"+49 2324/79867",
    "sg:postcode":"45549",
    "sg:province":"Nordrhein-Westfalen",
    "wof:name":"Connys",
    "wof:placetype":"venue"
},
  "geometry": {"coordinates":[7.2467908859,51.3656845093],"type":"Point"}
}