{
  "type": "Feature",
  "properties": {
    "iso:country":"DE",
    "sg:address":"Rathenaustr. 6",
    "sg:city":"Obernkirchen",
    "sg:phone":"+49 5724/3674",
    "sg:postcode":"31683",
    "sg:province":"Niedersachsen",
    "wof:name":"Horst Hohmeyer",
    "wof:placetype":"venue"
},
  "geometry": {"coordinates":[9.1310300827,52.2706794739],"type":"Point"}
}