{
  "type": "Feature",
  "properties": {
    "iso:country":"DE",
    "sg:address":"Ainmillerstr. 11",
    "sg:city":"M\u00fcnchen",
    "sg:phone":"+49 89/3866530",
    "sg:postcode":"80801",
    "sg:province":"Bayern",
    "wof:name":"Harald Kuhn Und Heinz Indorf",
    "wof:placetype":"venue"
},
  "geometry": {"coordinates":[11.5821762085,48.1585006714],"type":"Point"}
}