{
  "type": "Feature",
  "properties": {
    "iso:country":"DE",
    "sg:address":"Dresdener Str. 10",
    "sg:city":"Meerbusch",
    "sg:phone":"+49 2159/3449",
    "sg:postcode":"40670",
    "sg:province":"Nordrhein-Westfalen",
    "wof:name":"Dr. Manfred Zilias",
    "wof:placetype":"venue"
},
  "geometry": {"coordinates":[6.6350569725,51.2666702271],"type":"Point"}
}