{
  "type": "Feature",
  "properties": {
    "iso:country":"DE",
    "sg:address":"Heerweg 20",
    "sg:city":"Lenningen",
    "sg:phone":"+49 7026/2136",
    "sg:postcode":"73252",
    "sg:province":"Baden-W\u00fcrttemberg",
    "wof:name":"Freibad",
    "wof:placetype":"venue"
},
  "geometry": {"coordinates":[9.4904298782,48.5427246094],"type":"Point"}
}