{
  "type": "Feature",
  "properties": {
    "iso:country":"DE",
    "sg:address":"Frankfurter Str. 25",
    "sg:city":"Guben",
    "sg:phone":"+49 3561/2441",
    "sg:postcode":"03172",
    "sg:province":"Brandenburg",
    "wof:name":"Siegfried During",
    "wof:placetype":"venue"
},
  "geometry": {"coordinates":[14.7177190781,51.9510726929],"type":"Point"}
}