{
  "type": "Feature",
  "properties": {
    "iso:country":"DE",
    "sg:address":"Bielefelder Str. 108",
    "sg:city":"Halle",
    "sg:phone":"+49 5201/9641",
    "sg:postcode":"33790",
    "sg:province":"Nordrhein-Westfalen",
    "wof:name":"Aral-center Hans-j\u00fcrgen Tippe",
    "wof:placetype":"venue"
},
  "geometry": {"coordinates":[8.3772945404,52.0507240295],"type":"Point"}
}