{
  "type": "Feature",
  "properties": {
    "iso:country":"DE",
    "sg:address":"Huntestr. 14",
    "sg:city":"Cloppenburg",
    "sg:phone":"+49 4471/3002",
    "sg:postcode":"49661",
    "sg:province":"Niedersachsen",
    "wof:name":"Aloys Greten",
    "wof:placetype":"venue"
},
  "geometry": {"coordinates":[8.006476,52.834908],"type":"Point"}
}