{
  "type": "Feature",
  "properties": {
    "iso:country":"DE",
    "sg:city":"Clausthal",
    "sg:postcode":"38678",
    "sg:province":"Niedersachsen",
    "wof:name":"Dein-traumpartner",
    "wof:placetype":"venue"
},
  "geometry": {"coordinates":[10.398896,51.830971],"type":"Point"}
}