{
  "type": "Feature",
  "properties": {
    "iso:country":"DE",
    "sg:address":"Mainzer Tor 14",
    "sg:city":"Alsfeld",
    "sg:phone":"+49 6631/71788",
    "sg:postcode":"36304",
    "sg:province":"Hessen",
    "wof:name":"Horst Steinhardt",
    "wof:placetype":"venue"
},
  "geometry": {"coordinates":[9.2690572739,50.749546051],"type":"Point"}
}