{
  "type": "Feature",
  "properties": {
    "iso:country":"DE",
    "sg:address":"Siersdorfer Str. 70",
    "sg:city":"Alsdorf",
    "sg:phone":"+49 2404/24311",
    "sg:postcode":"52477",
    "sg:province":"Nordrhein-Westfalen",
    "wof:name":"H. H\u00f6ppener",
    "wof:placetype":"venue"
},
  "geometry": {"coordinates":[6.160063,50.874561],"type":"Point"}
}