{
  "type": "Feature",
  "properties": {
    "iso:country":"DE",
    "sg:address":"Seebacher Str. 55 a",
    "sg:city":"Wutha-Farnroda",
    "sg:phone":"+49 36921/90720",
    "sg:postcode":"99848",
    "sg:province":"Th\u00fcringen",
    "wof:name":"Spartenheim Bergblick",
    "wof:placetype":"venue"
},
  "geometry": {"coordinates":[10.3948898315,50.9358215332],"type":"Point"}
}