{
  "type": "Feature",
  "properties": {
    "iso:country":"DE",
    "sg:address":"Prinz-Eugen-Str 21",
    "sg:city":"Tettnang",
    "sg:phone":"+49 7542/51740",
    "sg:postcode":"88069",
    "sg:province":"Baden-W\u00fcrttemberg",
    "wof:name":"Fluolite Licht Und Leuchten Gmbh & Co Kg",
    "wof:placetype":"venue"
},
  "geometry": {"coordinates":[9.5731678009,47.6646003723],"type":"Point"}
}