{
  "type": "Feature",
  "properties": {
    "iso:country":"DE",
    "sg:address":"Sternstr. 20",
    "sg:city":"Gronau",
    "sg:phone":"+49 2562/3832",
    "sg:postcode":"48599",
    "sg:province":"Nordrhein-Westfalen",
    "wof:name":"Josef Huke Gmbh",
    "wof:placetype":"venue"
},
  "geometry": {"coordinates":[7.001099,52.212414],"type":"Point"}
}