{
  "type": "Feature",
  "properties": {
    "iso:country":"DE",
    "sg:address":"Am Anger 7",
    "sg:city":"Bad Waldsee",
    "sg:phone":"+49 7524/5455",
    "sg:postcode":"88339",
    "sg:province":"Baden-W\u00fcrttemberg",
    "wof:name":"D. Werner",
    "wof:placetype":"venue"
},
  "geometry": {"coordinates":[9.7133989334,47.8959274292],"type":"Point"}
}