{
  "type": "Feature",
  "properties": {
    "iso:country":"DE",
    "sg:address":"Lerchenring 31 a",
    "sg:city":"Steinach",
    "sg:postcode":"94377",
    "sg:province":"Bayern",
    "wof:name":"K\u00fcmpflein Maschinenbau Gmbh",
    "wof:placetype":"venue"
},
  "geometry": {"coordinates":[12.597294,48.951736],"type":"Point"}
}