{
  "type": "Feature",
  "properties": {
    "iso:country":"DE",
    "sg:address":"F\u00fcrther Str. 205",
    "sg:city":"N\u00fcrnberg",
    "sg:phone":"+49 911/316930",
    "sg:postcode":"90429",
    "sg:province":"Bayern",
    "wof:name":"Reise-quelle",
    "wof:placetype":"venue"
},
  "geometry": {"coordinates":[11.0341463089,49.4576721191],"type":"Point"}
}