{
  "type": "Feature",
  "properties": {
    "iso:country":"DE",
    "sg:address":"Anger 14",
    "sg:city":"Erfurt",
    "sg:phone":"+49 361/558240",
    "sg:postcode":"99084",
    "sg:province":"Th\u00fcringen",
    "wof:name":"Susanne Kermantschi Rechtsanw\u00e4ltin",
    "wof:placetype":"venue"
},
  "geometry": {"coordinates":[11.0347738266,50.9762458801],"type":"Point"}
}