{
  "type": "Feature",
  "properties": {
    "iso:country":"DE",
    "sg:address":"Marx",
    "sg:city":"Friedeburg",
    "sg:phone":"+49 4465/294",
    "sg:postcode":"26446",
    "sg:province":"Niedersachsen",
    "wof:name":"Gastst\u00e4tte H. Fa\u00df",
    "wof:placetype":"venue"
},
  "geometry": {"coordinates":[7.8336000443,53.425983429],"type":"Point"}
}