{
  "type": "Feature",
  "properties": {
    "iso:country":"DE",
    "sg:address":"M\u00fchlenstr. 78",
    "sg:city":"Friedland",
    "sg:phone":"+49 39601/26283",
    "sg:postcode":"17098",
    "sg:province":"Mecklenburg-Vorpommern",
    "wof:name":"Bernd Beyersdorf",
    "wof:placetype":"venue"
},
  "geometry": {"coordinates":[13.5501031876,53.6702194214],"type":"Point"}
}