{
  "type": "Feature",
  "properties": {
    "iso:country":"DE",
    "sg:address":"Edelweiler Str. 8",
    "sg:city":"Pfalzgrafenweiler",
    "sg:phone":"+49 7445/81123",
    "sg:postcode":"72285",
    "sg:province":"Baden-W\u00fcrttemberg",
    "wof:name":"Proplan Wurster Einrichtungs Gmbh",
    "wof:placetype":"venue"
},
  "geometry": {"coordinates":[8.5658874512,48.5328178406],"type":"Point"}
}