{
  "type": "Feature",
  "properties": {
    "iso:country":"DE",
    "sg:address":"Sonnbergstr 6",
    "sg:city":"Holzkirchen",
    "sg:phone":"+49 8024/999101",
    "sg:postcode":"83607",
    "sg:province":"Bayern",
    "wof:name":"Perihel Gmbh",
    "wof:placetype":"venue"
},
  "geometry": {"coordinates":[11.6747074127,47.8809242249],"type":"Point"}
}