{
  "type": "Feature",
  "properties": {
    "iso:country":"DE",
    "sg:address":"Hundemstr. 37",
    "sg:city":"Lennestadt",
    "sg:phone":"+49 2723/67077",
    "sg:postcode":"57368",
    "sg:province":"Nordrhein-Westfalen",
    "wof:name":"Projektbau Hanses Und Brieden Gmbh",
    "wof:placetype":"venue"
},
  "geometry": {"coordinates":[8.072193,51.103306],"type":"Point"}
}