{
  "type": "Feature",
  "properties": {
    "iso:country":"DE",
    "sg:address":"Am Kuchenhaus 14",
    "sg:city":"Zschorlau",
    "sg:phone":"+49 3771/43000",
    "sg:postcode":"08321",
    "sg:province":"Sachsen",
    "wof:name":"Junghans & Co Holzfenster Gmbh",
    "wof:placetype":"venue"
},
  "geometry": {"coordinates":[12.635812,50.563221],"type":"Point"}
}