{
  "type": "Feature",
  "properties": {
    "iso:country":"DE",
    "sg:address":"Welseder Str. 26A",
    "sg:city":"Hessisch Oldendorf",
    "sg:phone":"+49 5152/52276",
    "sg:postcode":"31840",
    "sg:province":"Niedersachsen",
    "wof:name":"Petra F\u00fcrll",
    "wof:placetype":"venue"
},
  "geometry": {"coordinates":[9.237045,52.171734],"type":"Point"}
}