{
  "type": "Feature",
  "properties": {
    "iso:country":"DE",
    "sg:address":"Belziger Str. 69",
    "sg:city":"Berlin",
    "sg:phone":"+49 30/7875743",
    "sg:postcode":"10823",
    "sg:province":"Berlin",
    "wof:name":"Sebo Bodenpflegesysteme Gmbh",
    "wof:placetype":"venue"
},
  "geometry": {"coordinates":[13.3467092514,52.4848594666],"type":"Point"}
}