{
  "type": "Feature",
  "properties": {
    "iso:country":"DE",
    "sg:address":"Lettengasse 7",
    "sg:city":"Weil am Rhein",
    "sg:phone":"+49 7621/62158",
    "sg:postcode":"79576",
    "sg:province":"Baden-W\u00fcrttemberg",
    "wof:name":"Dankwart J\u00fcngling Ingenieur",
    "wof:placetype":"venue"
},
  "geometry": {"coordinates":[7.6201138496,47.6154632568],"type":"Point"}
}