{
  "type": "Feature",
  "properties": {
    "iso:country":"DE",
    "sg:address":"Pforzheimer Str. 80",
    "sg:city":"Neuhausen",
    "sg:postcode":"75242",
    "sg:province":"Baden-W\u00fcrttemberg",
    "wof:name":"Joyvalley Music Gmbh",
    "wof:placetype":"venue"
},
  "geometry": {"coordinates":[8.7709817886,48.7944602966],"type":"Point"}
}