{
  "type": "Feature",
  "properties": {
    "iso:country":"DE",
    "sg:address":"Dresdner Str. 92",
    "sg:city":"Freital",
    "sg:phone":"+49 351/6491259",
    "sg:postcode":"01705",
    "sg:province":"Sachsen",
    "wof:name":"Karai Immobilienmakler",
    "wof:placetype":"venue"
},
  "geometry": {"coordinates":[13.6604204178,51.0096206665],"type":"Point"}
}