{
  "type": "Feature",
  "properties": {
    "iso:country":"DE",
    "sg:address":"Kornstr. 48",
    "sg:city":"Moers",
    "sg:phone":"+49 2841/54775",
    "sg:postcode":"47443",
    "sg:province":"Nordrhein-Westfalen",
    "wof:name":"Kurt Kiepert",
    "wof:placetype":"venue"
},
  "geometry": {"coordinates":[6.675907135,51.4554595947],"type":"Point"}
}