{
  "type": "Feature",
  "properties": {
    "iso:country":"DE",
    "sg:address":"Pappelallee 4",
    "sg:city":"Rostock",
    "sg:phone":"+49 381/694394",
    "sg:postcode":"18147",
    "sg:province":"Mecklenburg-Vorpommern",
    "wof:name":"Ewald Br\u00f6r",
    "wof:placetype":"venue"
},
  "geometry": {"coordinates":[12.13625,54.108406],"type":"Point"}
}