{
  "type": "Feature",
  "properties": {
    "iso:country":"DE",
    "sg:address":"Wessumer Str. 86",
    "sg:city":"Ahaus",
    "sg:phone":"+49 2561/2894",
    "sg:postcode":"48683",
    "sg:province":"Nordrhein-Westfalen",
    "wof:name":"Bomatex Fibres Filaments Textilhandels Gmbh",
    "wof:placetype":"venue"
},
  "geometry": {"coordinates":[7.0023331642,52.0839653015],"type":"Point"}
}