{
  "type": "Feature",
  "properties": {
    "iso:country":"DE",
    "sg:address":"August-Bebel-Str. 36::",
    "sg:city":"Bielefeld",
    "sg:phone":"+49 521/9659090",
    "sg:postcode":"33602",
    "sg:province":"Nordrhein-Westfalen",
    "wof:name":"Accura Steuerberatungsgmbh",
    "wof:placetype":"venue"
},
  "geometry": {"coordinates":[8.539556,52.028797],"type":"Point"}
}