{
  "type": "Feature",
  "properties": {
    "iso:country":"DE",
    "sg:address":"Haus Eichen 4",
    "sg:city":"Hellenthal",
    "sg:phone":"+49 2448/1448",
    "sg:postcode":"53940",
    "sg:province":"Nordrhein-Westfalen",
    "wof:name":"Jakob Bissels",
    "wof:placetype":"venue"
},
  "geometry": {"coordinates":[6.462266922,50.4579277039],"type":"Point"}
}