{
  "type": "Feature",
  "properties": {
    "iso:country":"DE",
    "sg:address":"Am Freigrafenkamp 12",
    "sg:city":"Rheda-Wiedenbr\u00fcck",
    "sg:phone":"+49 4952/423106",
    "sg:postcode":"33378",
    "sg:province":"Nordrhein-Westfalen",
    "wof:name":"J\u00d6rg Vieth",
    "wof:placetype":"venue"
},
  "geometry": {"coordinates":[8.295428,51.837425],"type":"Point"}
}