{
  "type": "Feature",
  "properties": {
    "iso:country":"DE",
    "sg:address":"Bachstr. 6",
    "sg:city":"Bad Saulgau",
    "sg:phone":"+49 7581/4108",
    "sg:postcode":"88348",
    "sg:province":"Baden-W\u00fcrttemberg",
    "wof:name":"Waltraud Manter",
    "wof:placetype":"venue"
},
  "geometry": {"coordinates":[9.499308,48.01664],"type":"Point"}
}