{
  "type": "Feature",
  "properties": {
    "iso:country":"DE",
    "sg:address":"Stadelhofer Str. 6",
    "sg:city":"Karlstadt",
    "sg:phone":"+49 9353/3742",
    "sg:postcode":"97753",
    "sg:province":"Bayern",
    "wof:name":"Martin Kraft",
    "wof:placetype":"venue"
},
  "geometry": {"coordinates":[9.758378,49.957695],"type":"Point"}
}