{
  "type": "Feature",
  "properties": {
    "iso:country":"DE",
    "sg:address":"Wei\u00dfhofer Str. 12",
    "sg:city":"Bretten",
    "sg:phone":"+49 7252/2120",
    "sg:postcode":"75015",
    "sg:province":"Baden-W\u00fcrttemberg",
    "wof:name":"Jung & Heidt",
    "wof:placetype":"venue"
},
  "geometry": {"coordinates":[8.708802,49.036427],"type":"Point"}
}