{
  "type": "Feature",
  "properties": {
    "iso:country":"DE",
    "sg:address":"Menzelstr. 39",
    "sg:city":"Hamm",
    "sg:phone":"+49 2381/57281",
    "sg:postcode":"59069",
    "sg:province":"Nordrhein-Westfalen",
    "wof:name":"Hans Pichler",
    "wof:placetype":"venue"
},
  "geometry": {"coordinates":[7.84553,51.654228],"type":"Point"}
}