{
  "type": "Feature",
  "properties": {
    "iso:country":"DE",
    "sg:address":"Weidgarten",
    "sg:city":"Soyen",
    "sg:phone":"+49 8071/50215",
    "sg:postcode":"83564",
    "sg:province":"Bayern",
    "wof:name":"J. Kainz",
    "wof:placetype":"venue"
},
  "geometry": {"coordinates":[12.193677,48.110737],"type":"Point"}
}