{
  "type": "Feature",
  "properties": {
    "iso:country":"DE",
    "sg:address":"R\u00f6merstr. 6",
    "sg:city":"Kastl",
    "sg:phone":"+49 8671/12314",
    "sg:postcode":"84556",
    "sg:province":"Bayern",
    "wof:name":"Evi Untersteger",
    "wof:placetype":"venue"
},
  "geometry": {"coordinates":[12.6999845505,48.1945953369],"type":"Point"}
}