{
  "type": "Feature",
  "properties": {
    "iso:country":"DE",
    "sg:address":"Gro\u00dfe Klostergasse 2",
    "sg:city":"Friedberg",
    "sg:phone":"+49 6031/2979",
    "sg:postcode":"61169",
    "sg:province":"Hessen",
    "wof:name":"Hotel Zum Alten M\u00fchlrad",
    "wof:placetype":"venue"
},
  "geometry": {"coordinates":[8.7555837631,50.3370666504],"type":"Point"}
}