{
  "type": "Feature",
  "properties": {
    "iso:country":"DE",
    "sg:address":"Am Tiefen Weg 8",
    "sg:city":"Hermaringen",
    "sg:phone":"+49 7322/6216",
    "sg:postcode":"89568",
    "sg:province":"Baden-W\u00fcrttemberg",
    "wof:name":"R. Grundler Und R. Prestle",
    "wof:placetype":"venue"
},
  "geometry": {"coordinates":[10.2523107529,48.5958633423],"type":"Point"}
}