{
  "type": "Feature",
  "properties": {
    "iso:country":"DE",
    "sg:address":"Herner Str. 2",
    "sg:city":"Bielefeld",
    "sg:postcode":"33649",
    "sg:province":"Nordrhein-Westfalen",
    "wof:name":"Gulf Paragon Gmbh",
    "wof:placetype":"venue"
},
  "geometry": {"coordinates":[8.485148,51.985802],"type":"Point"}
}