{
  "type": "Feature",
  "properties": {
    "iso:country":"DE",
    "sg:address":"Kirchstr. 10",
    "sg:city":"Jemgum",
    "sg:phone":"+49 4902/279",
    "sg:postcode":"26844",
    "sg:province":"Niedersachsen",
    "wof:name":"Jan Bruns & Co.",
    "wof:placetype":"venue"
},
  "geometry": {"coordinates":[7.2801327705,53.3158988953],"type":"Point"}
}