{
  "type": "Feature",
  "properties": {
    "iso:country":"DE",
    "sg:address":"Eichendorffstr. 14",
    "sg:city":"Essen",
    "sg:phone":"+49 2054/15072",
    "sg:postcode":"45219",
    "sg:province":"Nordrhein-Westfalen",
    "wof:name":"Pbs Posts Biomedicine Service Gmbh",
    "wof:placetype":"venue"
},
  "geometry": {"coordinates":[6.941133976,51.3681335449],"type":"Point"}
}