{
  "type": "Feature",
  "properties": {
    "iso:country":"DE",
    "sg:address":"In der Klewert 3",
    "sg:city":"Hemmingen",
    "sg:phone":"+49 511/2343017",
    "sg:postcode":"30966",
    "sg:province":"Niedersachsen",
    "wof:name":"Denk Art",
    "wof:placetype":"venue"
},
  "geometry": {"coordinates":[9.7290277481,52.3258132935],"type":"Point"}
}