{
  "type": "Feature",
  "properties": {
    "iso:country":"DE",
    "sg:address":"Geigelsteinstr. 1",
    "sg:city":"Bergen",
    "sg:phone":"+49 8662/8309",
    "sg:postcode":"83346",
    "sg:province":"Bayern",
    "wof:name":"Hansj\u00f6rg Hallweger",
    "wof:placetype":"venue"
},
  "geometry": {"coordinates":[12.587135,47.808384],"type":"Point"}
}