{
  "type": "Feature",
  "properties": {
    "iso:country":"DE",
    "sg:address":"Friesacker Str. 5a",
    "sg:city":"Rhinow",
    "sg:phone":"+49 33875/30010",
    "sg:postcode":"14728",
    "sg:province":"Brandenburg",
    "wof:name":"Putidoil Gesellschaft F\u00fcr \u00d6lschadensanierung Mbh",
    "wof:placetype":"venue"
},
  "geometry": {"coordinates":[12.347875,52.752289],"type":"Point"}
}