{
  "type": "Feature",
  "properties": {
    "iso:country":"DE",
    "sg:address":"Neresheimer Str. 11",
    "sg:city":"Nattheim",
    "sg:phone":"+49 7321/71897",
    "sg:postcode":"89564",
    "sg:province":"Baden-W\u00fcrttemberg",
    "wof:name":"Manfred G\u00f6sele",
    "wof:placetype":"venue"
},
  "geometry": {"coordinates":[10.242269,48.700275],"type":"Point"}
}