{
  "type": "Feature",
  "properties": {
    "iso:country":"DE",
    "sg:address":"Waltrup 7",
    "sg:city":"Altenberge",
    "sg:phone":"+49 2505/94580",
    "sg:postcode":"48341",
    "sg:province":"Nordrhein-Westfalen",
    "wof:name":"Janning Zimmerei Und Holzbau Gmbh",
    "wof:placetype":"venue"
},
  "geometry": {"coordinates":[7.4792661667,52.0228424072],"type":"Point"}
}