{
  "type": "Feature",
  "properties": {
    "iso:country":"DE",
    "sg:address":"Gartenstr. 17",
    "sg:city":"Ditzingen",
    "sg:phone":"+49 7156/951672",
    "sg:postcode":"71254",
    "sg:province":"Baden-W\u00fcrttemberg",
    "wof:name":"Cafe Flair",
    "wof:placetype":"venue"
},
  "geometry": {"coordinates":[9.069033,48.826935],"type":"Point"}
}