{
  "type": "Feature",
  "properties": {
    "iso:country":"DE",
    "sg:address":"Tratteilstr. 20",
    "sg:city":"Mering",
    "sg:phone":"+49 8233/38050",
    "sg:postcode":"86415",
    "sg:province":"Bayern",
    "wof:name":"Haco Wassertechnik Gmbh",
    "wof:placetype":"venue"
},
  "geometry": {"coordinates":[10.979675,48.26408],"type":"Point"}
}