{
  "type": "Feature",
  "properties": {
    "iso:country":"DE",
    "sg:city":"Langen",
    "sg:phone":"+49 4743/5262",
    "sg:postcode":"27607",
    "sg:province":"Niedersachsen",
    "wof:name":"Erwin Seidel",
    "wof:placetype":"venue"
},
  "geometry": {"coordinates":[8.59562,53.599091],"type":"Point"}
}