{
  "type": "Feature",
  "properties": {
    "iso:country":"DE",
    "sg:address":"Exerzierstr. 28",
    "sg:city":"Berlin",
    "sg:phone":"+49 30/4922393",
    "sg:postcode":"13357",
    "sg:province":"Berlin",
    "wof:name":"Riedel Gmbh",
    "wof:placetype":"venue"
},
  "geometry": {"coordinates":[13.373090744,52.5542144775],"type":"Point"}
}