{
  "type": "Feature",
  "properties": {
    "iso:country":"DE",
    "sg:address":"Mauerstrasse 5",
    "sg:city":"Gleichen",
    "sg:phone":"+49 5508/97790",
    "sg:postcode":"37130",
    "sg:province":"Niedersachsen",
    "wof:name":"Reicom Edv Und B\u00fcroger\u00e4te Spezial-reinigungsdienst Gmbh",
    "wof:placetype":"venue"
},
  "geometry": {"coordinates":[10.056044,51.477169],"type":"Point"}
}