{
  "type": "Feature",
  "properties": {
    "iso:country":"DE",
    "sg:address":"Wismarsche Str. 52",
    "sg:city":"Neubukow",
    "sg:phone":"+49 38294/13604",
    "sg:postcode":"18233",
    "sg:province":"Mecklenburg-Vorpommern",
    "wof:name":"R. Hirsack",
    "wof:placetype":"venue"
},
  "geometry": {"coordinates":[11.664413,54.026978],"type":"Point"}
}