{
  "type": "Feature",
  "properties": {
    "iso:country":"DE",
    "sg:address":"Kaiser-Wilhelm-Ring 32",
    "sg:city":"Mainz",
    "sg:phone":"+49 6131/677886",
    "sg:postcode":"55118",
    "sg:province":"Rheinland-Pfalz",
    "wof:name":"M. Boloban",
    "wof:placetype":"venue"
},
  "geometry": {"coordinates":[8.2573776245,50.004360199],"type":"Point"}
}