{
  "type": "Feature",
  "properties": {
    "iso:country":"DE",
    "sg:address":"Preysingstr. 11a",
    "sg:city":"Plattling",
    "sg:phone":"+49 9931/8647",
    "sg:postcode":"94447",
    "sg:province":"Bayern",
    "wof:name":"Albert K\u00f6ckeis",
    "wof:placetype":"venue"
},
  "geometry": {"coordinates":[12.868885994,48.7774391174],"type":"Point"}
}