{
  "type": "Feature",
  "properties": {
    "iso:country":"DE",
    "sg:address":"Kreisstr. 43",
    "sg:city":"Hattingen",
    "sg:phone":"+49 2324/56050",
    "sg:postcode":"45525",
    "sg:province":"Nordrhein-Westfalen",
    "wof:name":"Khl K\u00fcchenstudio Herbert Lechleuter E. K.",
    "wof:placetype":"venue"
},
  "geometry": {"coordinates":[7.1725850105,51.3988418579],"type":"Point"}
}