{
  "type": "Feature",
  "properties": {
    "iso:country":"DE",
    "sg:address":"Am Brink 24",
    "sg:city":"Visselh\u00f6vede",
    "sg:phone":"+49 4262/2330",
    "sg:postcode":"27374",
    "sg:province":"Niedersachsen",
    "wof:name":"Herbert Benien",
    "wof:placetype":"venue"
},
  "geometry": {"coordinates":[9.511247,52.972576],"type":"Point"}
}