{
  "type": "Feature",
  "properties": {
    "iso:country":"DE",
    "sg:address":"Scharfeneckstr. 2",
    "sg:city":"Annweiler",
    "sg:phone":"+49 6346/929724",
    "sg:postcode":"76855",
    "sg:province":"Rheinland-Pfalz",
    "wof:name":"Pbl Universalbautr\u00e4ger Gmbh",
    "wof:placetype":"venue"
},
  "geometry": {"coordinates":[7.979071,49.204842],"type":"Point"}
}