{
  "type": "Feature",
  "properties": {
    "iso:country":"DE",
    "sg:address":"Kiefernweg 8",
    "sg:city":"Lahr",
    "sg:phone":"+49 7821/7474",
    "sg:postcode":"77933",
    "sg:province":"Baden-W\u00fcrttemberg",
    "wof:name":"G\u00fcnter Hesemeier Steuerberater",
    "wof:placetype":"venue"
},
  "geometry": {"coordinates":[7.9057102203,48.3403549194],"type":"Point"}
}