{
  "type": "Feature",
  "properties": {
    "iso:country":"DE",
    "sg:address":"Immanuel-Kant-Str. 45",
    "sg:city":"G\u00f6ttingen",
    "sg:phone":"+49 551/77222",
    "sg:postcode":"37083",
    "sg:province":"Niedersachsen",
    "wof:name":"E. Sudmeyer",
    "wof:placetype":"venue"
},
  "geometry": {"coordinates":[9.946181,51.523979],"type":"Point"}
}