{
  "type": "Feature",
  "properties": {
    "iso:country":"DE",
    "sg:address":"Oststr. 10",
    "sg:city":"Wickede",
    "sg:phone":"+49 2377/2295",
    "sg:postcode":"58739",
    "sg:province":"Nordrhein-Westfalen",
    "wof:name":"Ev. Pfarramt Wickede",
    "wof:placetype":"venue"
},
  "geometry": {"coordinates":[7.8728070259,51.495223999],"type":"Point"}
}