{
  "type": "Feature",
  "properties": {
    "iso:country":"DE",
    "sg:address":"Richtenberger Str. 4",
    "sg:city":"Ribnitz-Damgarten",
    "sg:phone":"+49 3821/62402",
    "sg:postcode":"18311",
    "sg:province":"Mecklenburg-Vorpommern",
    "wof:name":"Bernd Dierling",
    "wof:placetype":"venue"
},
  "geometry": {"coordinates":[12.490418,54.249809],"type":"Point"}
}