{
  "type": "Feature",
  "properties": {
    "iso:country":"DE",
    "sg:address":"Schlo\u00dfhof 7",
    "sg:city":"Seefeld",
    "sg:phone":"+49 8152/981171",
    "sg:postcode":"82229",
    "sg:province":"Bayern",
    "wof:name":"Ortner Classic Interior Gmbh",
    "wof:placetype":"venue"
},
  "geometry": {"coordinates":[11.2049350739,48.031124115],"type":"Point"}
}