{
  "type": "Feature",
  "properties": {
    "iso:country":"DE",
    "sg:address":"Auf der Ahl 77",
    "sg:city":"Wiesbaden",
    "sg:phone":"+49 6122/940594",
    "sg:postcode":"65207",
    "sg:province":"Hessen",
    "wof:name":"Stefan Gerhardt Rechtsanwalt",
    "wof:placetype":"venue"
},
  "geometry": {"coordinates":[8.3739366531,50.0820617676],"type":"Point"}
}