{
  "type": "Feature",
  "properties": {
    "iso:country":"DE",
    "sg:address":"Paulinenstr. 8",
    "sg:city":"D\u00fcsseldorf",
    "sg:phone":"+49 211/9262323",
    "sg:postcode":"40627",
    "sg:province":"Nordrhein-Westfalen",
    "wof:name":"Heinz Herbert Dams Architekt",
    "wof:placetype":"venue"
},
  "geometry": {"coordinates":[6.860807,51.219734],"type":"Point"}
}