{
  "type": "Feature",
  "properties": {
    "iso:country":"DE",
    "sg:address":"M\u00fcllerstr. 54",
    "sg:city":"M\u00fcnchen",
    "sg:phone":"+49 89/2388906",
    "sg:postcode":"80469",
    "sg:province":"Bayern",
    "wof:name":"Prinas Assekuranz Service Gmbh",
    "wof:placetype":"venue"
},
  "geometry": {"coordinates":[11.5675773621,48.1320762634],"type":"Point"}
}