{
  "type": "Feature",
  "properties": {
    "iso:country":"DE",
    "sg:address":"Uhlandstr. 25",
    "sg:city":"Neckartenzlingen",
    "sg:phone":"+49 7127/35741",
    "sg:postcode":"72654",
    "sg:province":"Baden-W\u00fcrttemberg",
    "wof:name":"H.-d. H\u00f6ss",
    "wof:placetype":"venue"
},
  "geometry": {"coordinates":[9.2453384399,48.589427948],"type":"Point"}
}