{
  "type": "Feature",
  "properties": {
    "iso:country":"DE",
    "sg:address":"Mozartstr. 3",
    "sg:city":"Melle",
    "sg:phone":"+49 5422/8207",
    "sg:postcode":"49324",
    "sg:province":"Niedersachsen",
    "wof:name":"Bruno Painczyk Elektromeisetr",
    "wof:placetype":"venue"
},
  "geometry": {"coordinates":[8.28645,52.236088],"type":"Point"}
}