{
  "type": "Feature",
  "properties": {
    "iso:country":"DE",
    "sg:address":"Marktstr. 35",
    "sg:city":"Kirchheim",
    "sg:phone":"+49 7021/3591",
    "sg:postcode":"73230",
    "sg:province":"Baden-W\u00fcrttemberg",
    "wof:name":"Optik Bacher Brillen Contact- Linsen Alfred Bacher",
    "wof:placetype":"venue"
},
  "geometry": {"coordinates":[9.4513530731,48.6474075317],"type":"Point"}
}