{
  "type": "Feature",
  "properties": {
    "iso:country":"DE",
    "sg:address":"Siedlungsstr. 7",
    "sg:city":"Oy-Mittelberg",
    "sg:phone":"+49 8366/98634",
    "sg:postcode":"87466",
    "sg:province":"Bayern",
    "wof:name":"Ulrich Dombrowski Rechtsanwalt",
    "wof:placetype":"venue"
},
  "geometry": {"coordinates":[10.4580602646,47.6425933838],"type":"Point"}
}