{
  "type": "Feature",
  "properties": {
    "iso:country":"DE",
    "sg:address":"Kirchboitzen 111",
    "sg:city":"Walsrode",
    "sg:phone":"+49 5166/346",
    "sg:postcode":"29664",
    "sg:province":"Niedersachsen",
    "wof:name":"H. Fredebold",
    "wof:placetype":"venue"
},
  "geometry": {"coordinates":[9.484153,52.83136],"type":"Point"}
}