{
  "type": "Feature",
  "properties": {
    "iso:country":"DE",
    "sg:address":"St.-Martin-Str. 4",
    "sg:city":"Garmisch-Partenkirchen",
    "sg:phone":"+49 8821/76950",
    "sg:postcode":"82467",
    "sg:province":"Bayern",
    "wof:name":"K\u00f6nig-ludwig-bar",
    "wof:placetype":"venue"
},
  "geometry": {"coordinates":[11.098726,47.49255],"type":"Point"}
}