{
  "type": "Feature",
  "properties": {
    "iso:country":"DE",
    "sg:address":"\u00c4u\u00dfere Speicherstr. 6",
    "sg:city":"Riesa",
    "sg:phone":"+49 3525/50020",
    "sg:postcode":"01587",
    "sg:province":"Sachsen",
    "wof:name":"Fu\u00dfbodentechnik Gmbh",
    "wof:placetype":"venue"
},
  "geometry": {"coordinates":[13.2888717651,51.3003044128],"type":"Point"}
}