{
  "type": "Feature",
  "properties": {
    "iso:country":"DE",
    "sg:address":"98587",
    "sg:city":"Obersch\u00f6nau",
    "sg:phone":"+49 36847/33633",
    "sg:postcode":"98587",
    "sg:province":"Th\u00fcringen",
    "wof:name":"Schwimmbad",
    "wof:placetype":"venue"
},
  "geometry": {"coordinates":[10.6119384766,50.7150726318],"type":"Point"}
}