{
  "type": "Feature",
  "properties": {
    "iso:country":"DE",
    "sg:address":"Hasendorfweg 21",
    "sg:city":"H\u00f6velhof",
    "sg:phone":"+49 5257/2925",
    "sg:postcode":"33161",
    "sg:province":"Nordrhein-Westfalen",
    "wof:name":"Heinz Bredenbals Bauschlosserei",
    "wof:placetype":"venue"
},
  "geometry": {"coordinates":[8.677369,51.83181],"type":"Point"}
}