{
  "type": "Feature",
  "properties": {
    "iso:country":"DE",
    "sg:address":"Gerhard-Sch\u00fcmmer-Str. 13",
    "sg:city":"Geilenkirchen",
    "sg:phone":"+49 2451/2508",
    "sg:postcode":"52511",
    "sg:province":"Nordrhein-Westfalen",
    "wof:name":"F. W. Plum Elektroinstallation",
    "wof:placetype":"venue"
},
  "geometry": {"coordinates":[6.127363205,50.9660110474],"type":"Point"}
}