{
  "type": "Feature",
  "properties": {
    "iso:country":"DE",
    "sg:address":"Gartenstr. 21",
    "sg:city":"Z\u00fclpich",
    "sg:postcode":"53909",
    "sg:province":"Nordrhein-Westfalen",
    "wof:name":"Christian Langen Baugesellschaft Mbh",
    "wof:placetype":"venue"
},
  "geometry": {"coordinates":[6.651745,50.659214],"type":"Point"}
}