{
  "type": "Feature",
  "properties": {
    "iso:country":"DE",
    "sg:address":"Kuhlesh\u00fctte 182",
    "sg:city":"Krefeld",
    "sg:phone":"+49 2151/542721",
    "sg:postcode":"47809",
    "sg:province":"Nordrhein-Westfalen",
    "wof:name":"Peter Gruteser",
    "wof:placetype":"venue"
},
  "geometry": {"coordinates":[6.6027779579,51.3300743103],"type":"Point"}
}