{
  "type": "Feature",
  "properties": {
    "iso:country":"DE",
    "sg:address":"Mei\u00dfner Str. 228",
    "sg:city":"Radebeul",
    "sg:phone":"+49 351/8307902",
    "sg:postcode":"01445",
    "sg:province":"Sachsen",
    "wof:name":"Thomas Franz",
    "wof:placetype":"venue"
},
  "geometry": {"coordinates":[13.638367,51.107098],"type":"Point"}
}