{
  "type": "Feature",
  "properties": {
    "iso:country":"DE",
    "sg:address":"Fr\u00fchlingstr. 14a",
    "sg:city":"Obernburg",
    "sg:phone":"+49 6022/4339",
    "sg:postcode":"63785",
    "sg:province":"Bayern",
    "wof:name":"H.-w. Glock L\u00fcftungs- Klimatechnik Gmbh",
    "wof:placetype":"venue"
},
  "geometry": {"coordinates":[9.1504116058,49.844493866],"type":"Point"}
}