{
  "type": "Feature",
  "properties": {
    "iso:country":"DE",
    "sg:address":"Allee 10",
    "sg:city":"Fritzlar",
    "sg:postcode":"34560",
    "sg:province":"Hessen",
    "wof:name":"Die Braut\u00e4cker Gmbh",
    "wof:placetype":"venue"
},
  "geometry": {"coordinates":[9.271447,51.133484],"type":"Point"}
}