{
  "type": "Feature",
  "properties": {
    "iso:country":"DE",
    "sg:address":"Scharzhofstr. 291",
    "sg:city":"Wiltingen",
    "sg:phone":"+49 6501/16726",
    "sg:postcode":"54459",
    "sg:province":"Rheinland-Pfalz",
    "wof:name":"Matthias Koch",
    "wof:placetype":"venue"
},
  "geometry": {"coordinates":[6.5918078423,49.6567306519],"type":"Point"}
}