{
  "type": "Feature",
  "properties": {
    "iso:country":"DE",
    "sg:address":"Kirchenweg 4",
    "sg:city":"N\u00fcrnberg",
    "sg:phone":"+49 911/334332",
    "sg:postcode":"90419",
    "sg:province":"Bayern",
    "wof:name":"A. Askar",
    "wof:placetype":"venue"
},
  "geometry": {"coordinates":[11.0699558258,49.4625282288],"type":"Point"}
}