{
  "type": "Feature",
  "properties": {
    "iso:country":"DE",
    "sg:address":"Gro\u00dfe Str. 19",
    "sg:city":"Twistringen",
    "sg:phone":"+49 4243/1525",
    "sg:postcode":"27239",
    "sg:province":"Niedersachsen",
    "wof:name":"M. Berger",
    "wof:placetype":"venue"
},
  "geometry": {"coordinates":[8.6389188766,52.7997360229],"type":"Point"}
}