{
  "type": "Feature",
  "properties": {
    "iso:country":"DE",
    "sg:address":"Rh\u00f6ndorfer Str 14",
    "sg:city":"K\u00f6ln",
    "sg:phone":"+49 221/7325121",
    "sg:postcode":"50939",
    "sg:province":"Nordrhein-Westfalen",
    "wof:name":"Umweltzentrum K\u00f6ln-west Gesellschaft F\u00fcr Neue Arbeit Mbh",
    "wof:placetype":"venue"
},
  "geometry": {"coordinates":[6.9341378212,50.9149436951],"type":"Point"}
}