{
  "type": "Feature",
  "properties": {
    "iso:country":"DE",
    "sg:address":"Magdeburger Str. 6",
    "sg:city":"Gr\u00f6ningen",
    "sg:phone":"+49 3949/3045",
    "sg:postcode":"39397",
    "sg:province":"Sachsen-Anhalt",
    "wof:name":"W. Wesemeyer",
    "wof:placetype":"venue"
},
  "geometry": {"coordinates":[11.22271,51.940437],"type":"Point"}
}