{
  "type": "Feature",
  "properties": {
    "iso:country":"DE",
    "sg:address":"Maria-Viktoria-Str. 9",
    "sg:city":"Baden-Baden",
    "sg:phone":"+49 7221/29683",
    "sg:postcode":"76530",
    "sg:province":"Baden-W\u00fcrttemberg",
    "wof:name":"Vereinigung S\u00fcddeutscher Orthop\u00e4den E. V.",
    "wof:placetype":"venue"
},
  "geometry": {"coordinates":[8.242067337,48.7565422058],"type":"Point"}
}