{
  "type": "Feature",
  "properties": {
    "iso:country":"DE",
    "sg:address":"Hauptstr. 43",
    "sg:city":"Hinterschmiding",
    "sg:phone":"+49 8550/1662",
    "sg:postcode":"94146",
    "sg:province":"Bayern",
    "wof:name":"Gastst\u00e4tte Lydia Lenz",
    "wof:placetype":"venue"
},
  "geometry": {"coordinates":[13.6407327652,48.8375053406],"type":"Point"}
}