{
  "type": "Feature",
  "properties": {
    "iso:country":"DE",
    "sg:address":"Orchideenweg 22",
    "sg:city":"Stockach",
    "sg:phone":"+49 7771/7678",
    "sg:postcode":"78333",
    "sg:province":"Baden-W\u00fcrttemberg",
    "wof:name":"M.u.g. Bosch",
    "wof:placetype":"venue"
},
  "geometry": {"coordinates":[9.013569,47.863911],"type":"Point"}
}