{
  "type": "Feature",
  "properties": {
    "iso:country":"DE",
    "sg:address":"Im Steinernen Kreuz 11",
    "sg:city":"Wurmberg",
    "sg:phone":"+49 7044/4084",
    "sg:postcode":"75449",
    "sg:province":"Baden-W\u00fcrttemberg",
    "wof:name":"Theis Feinguss Pforzheim",
    "wof:placetype":"venue"
},
  "geometry": {"coordinates":[8.807082,48.873856],"type":"Point"}
}