{
  "type": "Feature",
  "properties": {
    "iso:country":"DE",
    "sg:address":"Kirmsees 27",
    "sg:city":"Kirchenpingarten",
    "sg:phone":"+49 9278/350",
    "sg:postcode":"95466",
    "sg:province":"Bayern",
    "wof:name":"H. Pscherer",
    "wof:placetype":"venue"
},
  "geometry": {"coordinates":[11.752324,49.916412],"type":"Point"}
}