{
  "type": "Feature",
  "properties": {
    "iso:country":"DE",
    "sg:address":"Heinrich-Barth-Str. 21",
    "sg:city":"Hamburg",
    "sg:phone":"+49 40/459856",
    "sg:postcode":"20146",
    "sg:province":"Hamburg",
    "wof:name":"J\u00fcrgen M\u00fccke Architekt",
    "wof:placetype":"venue"
},
  "geometry": {"coordinates":[9.981051,53.571613],"type":"Point"}
}