{
  "type": "Feature",
  "properties": {
    "iso:country":"DE",
    "sg:address":"Ostlandstr. 6",
    "sg:city":"Hehlen",
    "sg:phone":"+49 5533/2528",
    "sg:postcode":"37619",
    "sg:province":"Niedersachsen",
    "wof:name":"Friedel Fischer",
    "wof:placetype":"venue"
},
  "geometry": {"coordinates":[9.4750795364,51.983253479],"type":"Point"}
}