{
  "type": "Feature",
  "properties": {
    "iso:country":"DE",
    "sg:address":"Ingolst\u00e4dter Str. 1a",
    "sg:city":"Beilngries",
    "sg:phone":"+49 8461/452",
    "sg:postcode":"92339",
    "sg:province":"Bayern",
    "wof:name":"Max Rucker",
    "wof:placetype":"venue"
},
  "geometry": {"coordinates":[11.4752569199,49.0327987671],"type":"Point"}
}