{
  "type": "Feature",
  "properties": {
    "iso:country":"DE",
    "sg:address":"Kinzigstr. 43",
    "sg:city":"Fulda",
    "sg:phone":"+49 661/46900",
    "sg:postcode":"36043",
    "sg:province":"Hessen",
    "wof:name":"K\u00fchnel Bedachungen Gmbh",
    "wof:placetype":"venue"
},
  "geometry": {"coordinates":[9.677846,50.534813],"type":"Point"}
}