{
  "type": "Feature",
  "properties": {
    "iso:country":"DE",
    "sg:address":"Albanastr. 23",
    "sg:city":"Trier",
    "sg:phone":"+49 651/307545",
    "sg:postcode":"54290",
    "sg:province":"Rheinland-Pfalz",
    "wof:name":"Wilhelm Karpen",
    "wof:placetype":"venue"
},
  "geometry": {"coordinates":[6.6344017982,49.7396278381],"type":"Point"}
}