{
  "type": "Feature",
  "properties": {
    "iso:country":"DE",
    "sg:address":"Raiffeisenplatz 2",
    "sg:city":"Euskirchen",
    "sg:phone":"+49 2251/75091",
    "sg:postcode":"53881",
    "sg:province":"Nordrhein-Westfalen",
    "wof:name":"Raiffeisenbank Euskirchen Eg",
    "wof:placetype":"venue"
},
  "geometry": {"coordinates":[6.811804,50.631153],"type":"Point"}
}