{
  "type": "Feature",
  "properties": {
    "iso:country":"DE",
    "sg:address":"Landstr. 19",
    "sg:city":"Korschenbroich",
    "sg:phone":"+49 2166/87294",
    "sg:postcode":"41352",
    "sg:province":"Nordrhein-Westfalen",
    "wof:name":"Liedberger Landgasthaus",
    "wof:placetype":"venue"
},
  "geometry": {"coordinates":[6.5409498215,51.1661911011],"type":"Point"}
}