{
  "type": "Feature",
  "properties": {
    "iso:country":"DE",
    "sg:address":"Gro\u00dfe Fischgasse 18 a",
    "sg:city":"Leutesdorf",
    "sg:phone":"+49 2631/73146",
    "sg:postcode":"56599",
    "sg:province":"Rheinland-Pfalz",
    "wof:name":"Karl Schumacher",
    "wof:placetype":"venue"
},
  "geometry": {"coordinates":[7.3880338669,50.4494438171],"type":"Point"}
}