{
  "type": "Feature",
  "properties": {
    "iso:country":"DE",
    "sg:address":"Kurf\u00fcrstenstrasse 12",
    "sg:city":"Herne",
    "sg:postcode":"44623",
    "sg:province":"Nordrhein-Westfalen",
    "wof:name":"Doctor Source - Documentation Tool",
    "wof:placetype":"venue"
},
  "geometry": {"coordinates":[7.223745,51.531197],"type":"Point"}
}