{
  "type": "Feature",
  "properties": {
    "iso:country":"DE",
    "sg:address":"Grabenstr. 9",
    "sg:city":"Heidenheim",
    "sg:phone":"+49 7321/21810",
    "sg:postcode":"89522",
    "sg:province":"Baden-W\u00fcrttemberg",
    "wof:name":"Vertrauens\u00e4rztlicher-dienst Der Lva W\u00fcrttemberg",
    "wof:placetype":"venue"
},
  "geometry": {"coordinates":[10.152803421,48.6769752502],"type":"Point"}
}