{
  "type": "Feature",
  "properties": {
    "iso:country":"DE",
    "sg:address":"Kopernikusweg 17",
    "sg:city":"Solingen",
    "sg:phone":"+49 212/44220",
    "sg:postcode":"42659",
    "sg:province":"Nordrhein-Westfalen",
    "wof:name":"Paul Kratochwill",
    "wof:placetype":"venue"
},
  "geometry": {"coordinates":[7.1053471565,51.1513900757],"type":"Point"}
}