{
  "type": "Feature",
  "properties": {
    "iso:country":"DE",
    "sg:address":"Bedmor",
    "sg:city":"Norden",
    "sg:phone":"+49 4931/14300",
    "sg:postcode":"26506",
    "sg:province":"Niedersachsen",
    "wof:name":"Betreibergesell. Windpark Jennelt Mbh & Co. Kg",
    "wof:placetype":"venue"
},
  "geometry": {"coordinates":[7.175275,53.594025],"type":"Point"}
}