{
  "type": "Feature",
  "properties": {
    "iso:country":"DE",
    "sg:address":"Sandersh\u00e4user Str. 93",
    "sg:city":"Kassel",
    "sg:phone":"+49 561/53757",
    "sg:postcode":"34123",
    "sg:province":"Hessen",
    "wof:name":"Peter Nafe",
    "wof:placetype":"venue"
},
  "geometry": {"coordinates":[9.5313262939,51.3114242554],"type":"Point"}
}