{
  "type": "Feature",
  "properties": {
    "iso:country":"DE",
    "sg:address":"Westerstr. 50-54",
    "sg:city":"Elmshorn",
    "sg:phone":"+49 4941/216450",
    "sg:postcode":"25336",
    "sg:province":"Schleswig-Holstein",
    "wof:name":"Stadtwerke Elmshorn",
    "wof:placetype":"venue"
},
  "geometry": {"coordinates":[9.64982,53.747986],"type":"Point"}
}