{
  "type": "Feature",
  "properties": {
    "iso:country":"DE",
    "sg:address":"Max-Beckmann-Str. 25",
    "sg:city":"Leipzig",
    "sg:phone":"+49 341/9605753",
    "sg:postcode":"04109",
    "sg:province":"Sachsen",
    "wof:name":"Birgit U. Helmut Wie\u00dfner",
    "wof:placetype":"venue"
},
  "geometry": {"coordinates":[12.365407,51.338573],"type":"Point"}
}