{
  "type": "Feature",
  "properties": {
    "iso:country":"DE",
    "sg:address":"Hirschlander Str. 6",
    "sg:city":"Ditzingen",
    "sg:phone":"+49 7156/32054",
    "sg:postcode":"71254",
    "sg:province":"Baden-W\u00fcrttemberg",
    "wof:name":"Artur Richter",
    "wof:placetype":"venue"
},
  "geometry": {"coordinates":[9.0629997253,48.8274803162],"type":"Point"}
}