{
  "type": "Feature",
  "properties": {
    "iso:country":"DE",
    "sg:address":"Girardetstr. 109",
    "sg:city":"Wuppertal",
    "sg:phone":"+49 202/720098",
    "sg:postcode":"42109",
    "sg:province":"Nordrhein-Westfalen",
    "wof:name":"Cornelia Karstedt Rechtsanw\u00e4ltin",
    "wof:placetype":"venue"
},
  "geometry": {"coordinates":[7.1332130432,51.2772865295],"type":"Point"}
}