{
  "type": "Feature",
  "properties": {
    "iso:country":"DE",
    "sg:address":"D\u00fcrener Str. 164",
    "sg:city":"K\u00f6ln",
    "sg:phone":"+49 221/401688",
    "sg:postcode":"50931",
    "sg:province":"Nordrhein-Westfalen",
    "wof:name":"Abm Inoks & Schupp Ohg",
    "wof:placetype":"venue"
},
  "geometry": {"coordinates":[6.9156541824,50.9303588867],"type":"Point"}
}