{
  "type": "Feature",
  "properties": {
    "iso:country":"DE",
    "sg:address":"Residenzstr. 110",
    "sg:city":"Berlin",
    "sg:phone":"+49 30/49997813",
    "sg:postcode":"13409",
    "sg:province":"Berlin",
    "wof:name":"Talkum Dachdeckerei Gmbh",
    "wof:placetype":"venue"
},
  "geometry": {"coordinates":[13.364319,52.564373],"type":"Point"}
}