{
  "type": "Feature",
  "properties": {
    "iso:country":"DE",
    "sg:address":"Kurf\u00fcrstenstr. 23",
    "sg:city":"Hamburg",
    "sg:phone":"+49 40/6561488",
    "sg:postcode":"22041",
    "sg:province":"Hamburg",
    "wof:name":"Karl-erich Schwarzhaupt",
    "wof:placetype":"venue"
},
  "geometry": {"coordinates":[10.098381,53.577629],"type":"Point"}
}