{
  "type": "Feature",
  "properties": {
    "iso:country":"DE",
    "sg:address":"Bahnhofstr. 5a",
    "sg:city":"L\u00fcdersdorf",
    "sg:phone":"+49 38821/60718",
    "sg:postcode":"23923",
    "sg:province":"Mecklenburg-Vorpommern",
    "wof:name":"Landwirtschaftsbetrieb L\u00fcdersdorf Eg",
    "wof:placetype":"venue"
},
  "geometry": {"coordinates":[10.812752,53.831791],"type":"Point"}
}