{
  "type": "Feature",
  "properties": {
    "iso:country":"DE",
    "sg:address":"Detmolder Str. 271",
    "sg:city":"Vlotho",
    "sg:phone":"+49 5228/7139",
    "sg:postcode":"32602",
    "sg:province":"Nordrhein-Westfalen",
    "wof:name":"Willi Sieker Architekt",
    "wof:placetype":"venue"
},
  "geometry": {"coordinates":[8.777597,52.130497],"type":"Point"}
}