{
  "type": "Feature",
  "properties": {
    "iso:country":"DE",
    "sg:address":"Holtenauer Str. 273",
    "sg:city":"Kiel",
    "sg:phone":"+49 431/34422",
    "sg:postcode":"24106",
    "sg:province":"Schleswig-Holstein",
    "wof:name":"Lisbeth P\u00f6rksen Heilpraktikerin",
    "wof:placetype":"venue"
},
  "geometry": {"coordinates":[10.1315870285,54.3531227112],"type":"Point"}
}