{
  "type": "Feature",
  "properties": {
    "iso:country":"DE",
    "sg:address":"Dietzgenstr. 9",
    "sg:city":"Berlin",
    "sg:phone":"+49 30/4766111",
    "sg:postcode":"13156",
    "sg:province":"Berlin",
    "wof:name":"Wolfgang Krause Ingenieur",
    "wof:placetype":"venue"
},
  "geometry": {"coordinates":[13.4038696289,52.5804023743],"type":"Point"}
}