{
  "type": "Feature",
  "properties": {
    "iso:country":"DE",
    "sg:address":"Bl\u00fctenweg 18",
    "sg:city":"Niederkr\u00fcchten",
    "sg:phone":"+49 2163/81259",
    "sg:postcode":"41372",
    "sg:province":"Nordrhein-Westfalen",
    "wof:name":"Heinz Jennissen",
    "wof:placetype":"venue"
},
  "geometry": {"coordinates":[6.192059,51.204384],"type":"Point"}
}