{
  "type": "Feature",
  "properties": {
    "iso:country":"DE",
    "sg:city":"unna",
    "sg:postcode":"59425",
    "sg:province":"Nordrhein-Westfalen",
    "wof:name":"Media Contract",
    "wof:placetype":"venue"
},
  "geometry": {"coordinates":[7.723693,51.541794],"type":"Point"}
}