{
  "type": "Feature",
  "properties": {
    "iso:country":"DE",
    "sg:address":"B\u00f6ttcherstr. 9",
    "sg:city":"Hannover",
    "sg:phone":"+49 511/757674",
    "sg:postcode":"30419",
    "sg:province":"Niedersachsen",
    "wof:name":"Dr. Eggert Sass Architekt",
    "wof:placetype":"venue"
},
  "geometry": {"coordinates":[9.690321,52.393604],"type":"Point"}
}