{
  "type": "Feature",
  "properties": {
    "iso:country":"DE",
    "sg:address":"Holzmaarstr. 3",
    "sg:city":"Gillenfeld",
    "sg:phone":"+49 6573/294",
    "sg:postcode":"54558",
    "sg:province":"Rheinland-Pfalz",
    "wof:name":"M. Klas",
    "wof:placetype":"venue"
},
  "geometry": {"coordinates":[6.904298,50.127369],"type":"Point"}
}