{
  "type": "Feature",
  "properties": {
    "iso:country":"DE",
    "sg:address":"Zeppelinstr. 40",
    "sg:city":"Neu-Isenburg",
    "sg:phone":"+49 6102/25759",
    "sg:postcode":"63263",
    "sg:province":"Hessen",
    "wof:name":"Julius Marweld",
    "wof:placetype":"venue"
},
  "geometry": {"coordinates":[8.6847639084,50.0557746887],"type":"Point"}
}