{
  "type": "Feature",
  "properties": {
    "iso:country":"DE",
    "sg:address":"Haidaer Str. 14",
    "sg:city":"Hadamar",
    "sg:phone":"+49 6433/3868",
    "sg:postcode":"65589",
    "sg:province":"Hessen",
    "wof:name":"Gemeinn\u00fctzige Baugenossenschaft Eg",
    "wof:placetype":"venue"
},
  "geometry": {"coordinates":[8.054521,50.448441],"type":"Point"}
}