{
  "type": "Feature",
  "properties": {
    "iso:country":"DE",
    "sg:address":"August-Bebel-Str. 66",
    "sg:city":"Leipzig",
    "sg:phone":"+49 341/8621330",
    "sg:postcode":"04275",
    "sg:province":"Sachsen",
    "wof:name":"Volkmar Roscher Ingenieur",
    "wof:placetype":"venue"
},
  "geometry": {"coordinates":[12.3682451248,51.317111969],"type":"Point"}
}