{
  "type": "Feature",
  "properties": {
    "iso:country":"DE",
    "sg:address":"Hermann-L\u00f6ns-Str. 84",
    "sg:city":"Laatzen",
    "sg:phone":"+49 511/827063",
    "sg:postcode":"30880",
    "sg:province":"Niedersachsen",
    "wof:name":"Klaus Wilhelm Architekt",
    "wof:placetype":"venue"
},
  "geometry": {"coordinates":[9.804816,52.292404],"type":"Point"}
}