{
  "type": "Feature",
  "properties": {
    "iso:country":"DE",
    "sg:address":"Schatzgerstr. 16",
    "sg:city":"Ingolstadt",
    "sg:phone":"+49 841/480622",
    "sg:postcode":"85049",
    "sg:province":"Bayern",
    "wof:name":"Raychem Gmbh",
    "wof:placetype":"venue"
},
  "geometry": {"coordinates":[11.3926553726,48.7683296204],"type":"Point"}
}