{
  "type": "Feature",
  "properties": {
    "iso:country":"DE",
    "sg:address":"Poststr. 37",
    "sg:city":"G\u00f6ppingen",
    "sg:phone":"+49 7161/97790",
    "sg:postcode":"73033",
    "sg:province":"Baden-W\u00fcrttemberg",
    "wof:name":"Schlenger Geiger Und Seifried Rechtsanw\u00e4lte",
    "wof:placetype":"venue"
},
  "geometry": {"coordinates":[9.6562585831,48.7025032043],"type":"Point"}
}