{
  "type": "Feature",
  "properties": {
    "iso:country":"DE",
    "sg:address":"Wiemelfeldstr. 58",
    "sg:city":"Steinfurt",
    "sg:phone":"+49 2552/3362",
    "sg:postcode":"48565",
    "sg:province":"Nordrhein-Westfalen",
    "wof:name":"Alfred L\u00fcttmann",
    "wof:placetype":"venue"
},
  "geometry": {"coordinates":[7.3880839348,52.1190567017],"type":"Point"}
}