{
  "type": "Feature",
  "properties": {
    "iso:country":"DE",
    "sg:address":"Hafter Weg 62",
    "sg:city":"Bassum",
    "sg:phone":"+49 4241/4975",
    "sg:postcode":"27211",
    "sg:province":"Niedersachsen",
    "wof:name":"Wilhelm Hahn",
    "wof:placetype":"venue"
},
  "geometry": {"coordinates":[8.702434,52.842079],"type":"Point"}
}