{
  "type": "Feature",
  "properties": {
    "iso:country":"DE",
    "sg:address":"Postfach",
    "sg:city":"Mudersbach",
    "sg:phone":"+49 2745/338",
    "sg:postcode":"57549",
    "sg:province":"Rheinland-Pfalz",
    "wof:name":"Kath. \u00d6ffentl. Bibliothek",
    "wof:placetype":"venue"
},
  "geometry": {"coordinates":[7.94875,50.826542],"type":"Point"}
}