{
  "type": "Feature",
  "properties": {
    "iso:country":"DE",
    "sg:address":"Trierer Str. 653",
    "sg:city":"Aachen",
    "sg:phone":"+49 241/562026",
    "sg:postcode":"52078",
    "sg:province":"Nordrhein-Westfalen",
    "wof:name":"Dea-tankstelle",
    "wof:placetype":"venue"
},
  "geometry": {"coordinates":[6.1393899918,50.7603988647],"type":"Point"}
}