{
  "type": "Feature",
  "properties": {
    "iso:country":"DE",
    "sg:address":"Montanusstr. 54-56",
    "sg:city":"Grevenbroich",
    "sg:postcode":"41515",
    "sg:province":"Nordrhein-Westfalen",
    "wof:name":"Allianz Versicherungs Ag",
    "wof:placetype":"venue"
},
  "geometry": {"coordinates":[6.5963850021,51.0893287659],"type":"Point"}
}