{
  "type": "Feature",
  "properties": {
    "iso:country":"DE",
    "sg:address":"Hauptstr. 28",
    "sg:city":"Goldelund",
    "sg:phone":"+49 4673/473",
    "sg:postcode":"25862",
    "sg:province":"Schleswig-Holstein",
    "wof:name":"J. Und H. Becker",
    "wof:placetype":"venue"
},
  "geometry": {"coordinates":[9.102349,54.672153],"type":"Point"}
}