{
  "type": "Feature",
  "properties": {
    "iso:country":"DE",
    "sg:address":"Hauptstr. 16",
    "sg:city":"Coswig",
    "sg:phone":"+49 3523/63202",
    "sg:postcode":"01640",
    "sg:province":"Sachsen",
    "wof:name":"Kerstin Kundorf",
    "wof:placetype":"venue"
},
  "geometry": {"coordinates":[13.580685,51.126308],"type":"Point"}
}