{
  "type": "Feature",
  "properties": {
    "iso:country":"DE",
    "sg:address":"Salm\u00fcnsterer Str. 15",
    "sg:city":"Bad Orb",
    "sg:phone":"+49 6052/2238",
    "sg:postcode":"63619",
    "sg:province":"Hessen",
    "wof:name":"G\u00e4stehaus Ulrich Schuch",
    "wof:placetype":"venue"
},
  "geometry": {"coordinates":[9.3500642776,50.2346191406],"type":"Point"}
}