{
  "type": "Feature",
  "properties": {
    "iso:country":"DE",
    "sg:address":"Oelsnitzer Str. 2",
    "sg:city":"Hof",
    "sg:phone":"+49 9281/40119",
    "sg:postcode":"95028",
    "sg:province":"Bayern",
    "wof:name":"Ingeburg Baierle-gebhardt Steuerberaterin",
    "wof:placetype":"venue"
},
  "geometry": {"coordinates":[11.9237985611,50.314540863],"type":"Point"}
}