{
  "type": "Feature",
  "properties": {
    "iso:country":"DE",
    "sg:address":"Dickendorner Weg 58",
    "sg:city":"L\u00f6hne",
    "sg:phone":"+49 5732/81594",
    "sg:postcode":"32584",
    "sg:province":"Nordrhein-Westfalen",
    "wof:name":"K. Kr\u00fcger",
    "wof:placetype":"venue"
},
  "geometry": {"coordinates":[8.699194,52.187008],"type":"Point"}
}