{
  "type": "Feature",
  "properties": {
    "iso:country":"DE",
    "sg:address":"Wolthuser Str. 17",
    "sg:city":"Emden",
    "sg:phone":"+49 4921/26863",
    "sg:postcode":"26725",
    "sg:province":"Niedersachsen",
    "wof:name":"Restaurant Pir\u00e4us",
    "wof:placetype":"venue"
},
  "geometry": {"coordinates":[7.2184472084,53.3709945679],"type":"Point"}
}