{
  "type": "Feature",
  "properties": {
    "iso:country":"DE",
    "sg:address":"Neuer Weg 32",
    "sg:city":"Gr\u00fcnberg",
    "sg:phone":"+49 6401/6902",
    "sg:postcode":"35305",
    "sg:province":"Hessen",
    "wof:name":"Oskar Peter",
    "wof:placetype":"venue"
},
  "geometry": {"coordinates":[8.946264,50.634445],"type":"Point"}
}