{
  "type": "Feature",
  "properties": {
    "iso:country":"DE",
    "sg:address":"Sandstr. 29",
    "sg:city":"N\u00fcrnberg",
    "sg:phone":"+49 911/221824",
    "sg:postcode":"90443",
    "sg:province":"Bayern",
    "wof:name":"Norbert Wolff Rechtsanwalt",
    "wof:placetype":"venue"
},
  "geometry": {"coordinates":[11.0727767944,49.4457588196],"type":"Point"}
}