{
  "type": "Feature",
  "properties": {
    "iso:country":"DE",
    "sg:address":"Dorfstr 15b",
    "sg:city":"Zeischa",
    "sg:phone":"+49 35341/1520",
    "sg:postcode":"04924",
    "sg:province":"Brandenburg",
    "wof:name":"Forstbaumschulen F\u00fcrst P\u00fcckler Zeischa Gmbh",
    "wof:placetype":"venue"
},
  "geometry": {"coordinates":[13.421579,51.498837],"type":"Point"}
}