{
  "type": "Feature",
  "properties": {
    "iso:country":"DE",
    "sg:address":"Pommernstr. 5",
    "sg:city":"Memmingen",
    "sg:phone":"+49 8331/61675",
    "sg:postcode":"87700",
    "sg:province":"Bayern",
    "wof:name":"Horst Fiener Architekt",
    "wof:placetype":"venue"
},
  "geometry": {"coordinates":[10.151765,47.990929],"type":"Point"}
}