{
  "type": "Feature",
  "properties": {
    "iso:country":"DE",
    "sg:address":"Am Schwibbogen 4",
    "sg:city":"Rostock",
    "sg:phone":"+49 381/4923025",
    "sg:postcode":"18055",
    "sg:province":"Mecklenburg-Vorpommern",
    "wof:name":"Friedr.-wilh. Tarnow",
    "wof:placetype":"venue"
},
  "geometry": {"coordinates":[12.146991,54.08744],"type":"Point"}
}