{
  "type": "Feature",
  "properties": {
    "iso:country":"DE",
    "sg:address":"Lattenkamp 68",
    "sg:city":"Hamburg",
    "sg:phone":"+49 40/365096",
    "sg:postcode":"22299",
    "sg:province":"Hamburg",
    "wof:name":"M. Weck",
    "wof:placetype":"venue"
},
  "geometry": {"coordinates":[9.9954614639,53.5996055603],"type":"Point"}
}