{
  "type": "Feature",
  "properties": {
    "iso:country":"DE",
    "sg:address":"Ferdinand-Porsche-Str. 7a",
    "sg:city":"Denzlingen",
    "sg:phone":"+49 7666/7211",
    "sg:postcode":"79211",
    "sg:province":"Baden-W\u00fcrttemberg",
    "wof:name":"F. Elz",
    "wof:placetype":"venue"
},
  "geometry": {"coordinates":[7.8827161789,48.0743293762],"type":"Point"}
}