{
  "type": "Feature",
  "properties": {
    "iso:country":"DE",
    "sg:address":"Residenzplatz 12",
    "sg:city":"Passau",
    "sg:phone":"+49 851/2408",
    "sg:postcode":"94032",
    "sg:province":"Bayern",
    "wof:name":"Hofapotheke Zum Schwarzen Adler",
    "wof:placetype":"venue"
},
  "geometry": {"coordinates":[13.467241,48.57407],"type":"Point"}
}