{
  "type": "Feature",
  "properties": {
    "iso:country":"DE",
    "sg:address":"Turnhallestr. 40",
    "sg:city":"Freudenstadt",
    "sg:phone":"+49 7441/7352",
    "sg:postcode":"72250",
    "sg:province":"Baden-W\u00fcrttemberg",
    "wof:name":"Motiv",
    "wof:placetype":"venue"
},
  "geometry": {"coordinates":[8.415433,48.462261],"type":"Point"}
}