{
  "type": "Feature",
  "properties": {
    "iso:country":"DE",
    "sg:address":"Gutenbergstr. 80",
    "sg:city":"Kiel",
    "sg:phone":"+49 431/548485",
    "sg:postcode":"24118",
    "sg:province":"Schleswig-Holstein",
    "wof:name":"Deitermann Inh. H.-c. Grimm",
    "wof:placetype":"venue"
},
  "geometry": {"coordinates":[10.114756,54.332901],"type":"Point"}
}