{
  "type": "Feature",
  "properties": {
    "iso:country":"DE",
    "sg:address":"Ditzum",
    "sg:city":"Jemgum",
    "sg:phone":"+49 4902/566",
    "sg:postcode":"26844",
    "sg:province":"Niedersachsen",
    "wof:name":"U. Und G. Blank",
    "wof:placetype":"venue"
},
  "geometry": {"coordinates":[7.2619299889,53.302822113],"type":"Point"}
}