{
  "type": "Feature",
  "properties": {
    "iso:country":"DE",
    "sg:address":"Erbacher Landstr. 30",
    "sg:city":"Eltville",
    "sg:phone":"+49 6723/3774",
    "sg:postcode":"65347",
    "sg:province":"Hessen",
    "wof:name":"Karl-wilhelm Nitzling",
    "wof:placetype":"venue"
},
  "geometry": {"coordinates":[8.0660448074,50.0160903931],"type":"Point"}
}