{
  "type": "Feature",
  "properties": {
    "iso:country":"DE",
    "sg:address":"Berliner Str. 114",
    "sg:city":"Erfurt",
    "sg:phone":"+49 361/7923543",
    "sg:postcode":"99091",
    "sg:province":"Th\u00fcringen",
    "wof:name":"J\u00fcrgen Schulze",
    "wof:placetype":"venue"
},
  "geometry": {"coordinates":[11.0056695938,51.0072975159],"type":"Point"}
}