{
  "type": "Feature",
  "properties": {
    "iso:country":"DE",
    "sg:address":"Sanktjohanserstr. 80",
    "sg:city":"Bad Wiessee",
    "sg:postcode":"83707",
    "sg:province":"Bayern",
    "wof:name":"Fremdenheim Marcher",
    "wof:placetype":"venue"
},
  "geometry": {"coordinates":[11.727107048,47.702129364],"type":"Point"}
}