{
  "type": "Feature",
  "properties": {
    "iso:country":"DE",
    "sg:address":"Rothofweg 2",
    "sg:city":"Bischberg",
    "sg:phone":"+49 951/62505",
    "sg:postcode":"96120",
    "sg:province":"Bayern",
    "wof:name":"Herbert Loch",
    "wof:placetype":"venue"
},
  "geometry": {"coordinates":[10.834594,49.909382],"type":"Point"}
}