{
  "type": "Feature",
  "properties": {
    "iso:country":"DE",
    "sg:address":"Erzbi-Heinrich-Str 13",
    "sg:city":"Trier",
    "sg:phone":"+49 651/700311",
    "sg:postcode":"54295",
    "sg:province":"Rheinland-Pfalz",
    "wof:name":"Uk Projekt-baubetreuung Gmbh",
    "wof:placetype":"venue"
},
  "geometry": {"coordinates":[6.64941,49.735798],"type":"Point"}
}