{
  "type": "Feature",
  "properties": {
    "iso:country":"DE",
    "sg:address":"Auf dem Kamp 46",
    "sg:city":"L\u00fcbbecke",
    "sg:phone":"+49 5741/6440",
    "sg:postcode":"32312",
    "sg:province":"Nordrhein-Westfalen",
    "wof:name":"Anneliese Brauer",
    "wof:placetype":"venue"
},
  "geometry": {"coordinates":[8.670537,52.307182],"type":"Point"}
}