{
  "type": "Feature",
  "properties": {
    "iso:country":"DE",
    "sg:address":"Hauptstr. 43",
    "sg:city":"Wutha-Farnroda",
    "sg:phone":"+49 36921/90825",
    "sg:postcode":"99848",
    "sg:province":"Th\u00fcringen",
    "wof:name":"Matthias Otto",
    "wof:placetype":"venue"
},
  "geometry": {"coordinates":[10.3902521133,50.9355583191],"type":"Point"}
}