{
  "type": "Feature",
  "properties": {
    "iso:country":"DE",
    "sg:address":"Eisenbahnstr. 169",
    "sg:city":"Werder",
    "sg:phone":"+49 3327/42480",
    "sg:postcode":"14542",
    "sg:province":"Brandenburg",
    "wof:name":"Autoservice Kraus Gmbh",
    "wof:placetype":"venue"
},
  "geometry": {"coordinates":[12.9312047958,52.3840484619],"type":"Point"}
}