{
  "type": "Feature",
  "properties": {
    "iso:country":"DE",
    "sg:address":"Augenthal 7",
    "sg:city":"Marktl",
    "sg:postcode":"84533",
    "sg:province":"Bayern",
    "wof:name":"Alexander Schreiner Gmbh",
    "wof:placetype":"venue"
},
  "geometry": {"coordinates":[12.896334,48.261265],"type":"Point"}
}