{
  "type": "Feature",
  "properties": {
    "iso:country":"DE",
    "sg:address":"Bismarckstr. 4",
    "sg:city":"Sarstedt",
    "sg:phone":"+49 5066/3862",
    "sg:postcode":"31157",
    "sg:province":"Niedersachsen",
    "wof:name":"Friedrich Schenkemeyer",
    "wof:placetype":"venue"
},
  "geometry": {"coordinates":[9.859649,52.234924],"type":"Point"}
}