{
  "type": "Feature",
  "properties": {
    "iso:country":"DE",
    "sg:address":"Dachdeckerstr. 3 b",
    "sg:city":"Waldb\u00fcttelbrunn",
    "sg:phone":"+49 931/48511",
    "sg:postcode":"97297",
    "sg:province":"Bayern",
    "wof:name":"Schlosserei W. Hemmerich Gmbh",
    "wof:placetype":"venue"
},
  "geometry": {"coordinates":[9.842632,49.794964],"type":"Point"}
}