{
  "type": "Feature",
  "properties": {
    "iso:country":"DE",
    "sg:address":"B\u00fcrgermeister-Brantl-Str. 9",
    "sg:city":"Roding",
    "sg:phone":"+49 9461/1441",
    "sg:postcode":"93426",
    "sg:province":"Bayern",
    "wof:name":"Caritas-altenheim Eustachius-kugler-haus",
    "wof:placetype":"venue"
},
  "geometry": {"coordinates":[12.52144,49.188164],"type":"Point"}
}