{
  "type": "Feature",
  "properties": {
    "iso:country":"DE",
    "sg:address":"M\u00f6llendorffstr. 86",
    "sg:city":"Berlin",
    "sg:phone":"+49 30/5597287",
    "sg:postcode":"10367",
    "sg:province":"Berlin",
    "wof:name":"Werner Jannowsky",
    "wof:placetype":"venue"
},
  "geometry": {"coordinates":[13.4793949127,52.5209312439],"type":"Point"}
}