{
  "type": "Feature",
  "properties": {
    "iso:country":"DE",
    "sg:address":"Grubenstr. 2",
    "sg:city":"Kreuztal",
    "sg:phone":"+49 2732/80229",
    "sg:postcode":"57223",
    "sg:province":"Nordrhein-Westfalen",
    "wof:name":"Gert R\u00f6nnecke",
    "wof:placetype":"venue"
},
  "geometry": {"coordinates":[7.9779157639,51.0036125183],"type":"Point"}
}