{
  "type": "Feature",
  "properties": {
    "iso:country":"DE",
    "sg:address":"Maslingstr. 53",
    "sg:city":"Castrop-Rauxel",
    "sg:phone":"+49 2305/440383",
    "sg:postcode":"44579",
    "sg:province":"Nordrhein-Westfalen",
    "wof:name":"Expol Kunststofftechnik Gmbh",
    "wof:placetype":"venue"
},
  "geometry": {"coordinates":[7.3128991127,51.5682487488],"type":"Point"}
}