{
  "type": "Feature",
  "properties": {
    "iso:country":"DE",
    "sg:address":"Weststr. 77",
    "sg:city":"Werl",
    "sg:phone":"+49 2922/863185",
    "sg:postcode":"59457",
    "sg:province":"Nordrhein-Westfalen",
    "wof:name":"Haus Schulte Inh. Christel Schmidt",
    "wof:placetype":"venue"
},
  "geometry": {"coordinates":[7.9617438316,51.5594062805],"type":"Point"}
}