{
  "type": "Feature",
  "properties": {
    "iso:country":"DE",
    "sg:address":"Seilgraben 10",
    "sg:city":"Aachen",
    "sg:phone":"+49 241/31970",
    "sg:postcode":"52062",
    "sg:province":"Nordrhein-Westfalen",
    "wof:name":"Dieter Wei\u00dfbrod",
    "wof:placetype":"venue"
},
  "geometry": {"coordinates":[6.0871710777,50.7783851624],"type":"Point"}
}