{
  "type": "Feature",
  "properties": {
    "iso:country":"DE",
    "sg:address":"Grieshaberstr. 5",
    "sg:city":"Furtwangen",
    "sg:phone":"+49 7723/7458",
    "sg:postcode":"78120",
    "sg:province":"Baden-W\u00fcrttemberg",
    "wof:name":"G. Bareis Gravieranstalt",
    "wof:placetype":"venue"
},
  "geometry": {"coordinates":[8.2046747208,48.0530471802],"type":"Point"}
}