{
  "type": "Feature",
  "properties": {
    "iso:country":"DE",
    "sg:address":"Brandstr. 12",
    "sg:city":"Kamp-Lintfort",
    "sg:phone":"+49 2842/80527",
    "sg:postcode":"47475",
    "sg:province":"Nordrhein-Westfalen",
    "wof:name":"Siegmund Naumann Steuerberater",
    "wof:placetype":"venue"
},
  "geometry": {"coordinates":[6.5396871567,51.4952735901],"type":"Point"}
}