{
  "type": "Feature",
  "properties": {
    "iso:country":"DE",
    "sg:address":"Am Bug 19",
    "sg:city":"Wallerstein",
    "sg:phone":"+49 9081/79593",
    "sg:postcode":"86757",
    "sg:province":"Bayern",
    "wof:name":"Reiber & Feigl Gmbh",
    "wof:placetype":"venue"
},
  "geometry": {"coordinates":[10.4686632156,48.878944397],"type":"Point"}
}