{
  "type": "Feature",
  "properties": {
    "iso:country":"DE",
    "sg:address":"Nordwinkel 8",
    "sg:city":"Espelkamp",
    "sg:phone":"+49 5743/2197",
    "sg:postcode":"32339",
    "sg:province":"Nordrhein-Westfalen",
    "wof:name":"Kn\u00f6pfchen",
    "wof:placetype":"venue"
},
  "geometry": {"coordinates":[8.6125364304,52.3571205139],"type":"Point"}
}