{
  "type": "Feature",
  "properties": {
    "iso:country":"DE",
    "sg:address":"Gartenstr. 2",
    "sg:city":"Prenzlau",
    "sg:phone":"+49 3984/805912",
    "sg:postcode":"17291",
    "sg:province":"Brandenburg",
    "wof:name":"F. Bohnstengel",
    "wof:placetype":"venue"
},
  "geometry": {"coordinates":[13.86226,53.32362],"type":"Point"}
}