{
  "type": "Feature",
  "properties": {
    "iso:country":"DE",
    "sg:address":"Seestr. 75",
    "sg:city":"Seefeld",
    "sg:postcode":"82229",
    "sg:province":"Bayern",
    "wof:name":"Sch\u00fctzengesellschaft Hechendorf-g\u00fcntering E.v.",
    "wof:placetype":"venue"
},
  "geometry": {"coordinates":[11.18602,48.030048],"type":"Point"}
}