{
  "type": "Feature",
  "properties": {
    "iso:country":"DE",
    "sg:address":"Am Sportplatz 1",
    "sg:city":"Kalletal",
    "sg:phone":"+49 5264/69964",
    "sg:postcode":"32689",
    "sg:province":"Nordrhein-Westfalen",
    "wof:name":"Walter Pr\u00f6hlemeier",
    "wof:placetype":"venue"
},
  "geometry": {"coordinates":[9.008472,52.081913],"type":"Point"}
}