{
  "type": "Feature",
  "properties": {
    "iso:country":"DE",
    "sg:address":"Obere Torstr. 13a",
    "sg:city":"Dassel",
    "sg:phone":"+49 5562/8663",
    "sg:postcode":"37586",
    "sg:province":"Niedersachsen",
    "wof:name":"Dietmar K\u00f6rber Hosenkollektion Gmbh",
    "wof:placetype":"venue"
},
  "geometry": {"coordinates":[9.7636499405,51.8128814697],"type":"Point"}
}