{
  "type": "Feature",
  "properties": {
    "iso:country":"DE",
    "sg:address":"Trieschweg 4",
    "sg:city":"Neukirchen",
    "sg:phone":"+49 6694/7285",
    "sg:postcode":"34626",
    "sg:province":"Hessen",
    "wof:name":"Kurt Hahn",
    "wof:placetype":"venue"
},
  "geometry": {"coordinates":[9.383505,50.852859],"type":"Point"}
}