{
  "type": "Feature",
  "properties": {
    "iso:country":"DE",
    "sg:address":"Bl\u00fccherstr. 11",
    "sg:city":"Hof",
    "sg:phone":"+49 9281/94863",
    "sg:postcode":"95030",
    "sg:province":"Bayern",
    "wof:name":"Pizzeria Mia Bella Napoli",
    "wof:placetype":"venue"
},
  "geometry": {"coordinates":[11.9066619873,50.3103599548],"type":"Point"}
}