{
  "type": "Feature",
  "properties": {
    "iso:country":"DE",
    "sg:address":"Sulinger Str. 198",
    "sg:city":"Barver",
    "sg:phone":"+49 5448/226",
    "sg:postcode":"49453",
    "sg:province":"Niedersachsen",
    "wof:name":"Fritz B\u00fcnte",
    "wof:placetype":"venue"
},
  "geometry": {"coordinates":[8.6102428436,52.6080551147],"type":"Point"}
}