{
  "type": "Feature",
  "properties": {
    "iso:country":"DE",
    "sg:address":"Am Bahnhof 4a",
    "sg:city":"Handewitt",
    "sg:phone":"+49 4608/96216",
    "sg:postcode":"24983",
    "sg:province":"Schleswig-Holstein",
    "wof:name":"Holger Jensen",
    "wof:placetype":"venue"
},
  "geometry": {"coordinates":[9.323576,54.773224],"type":"Point"}
}