{
  "type": "Feature",
  "properties": {
    "iso:country":"DE",
    "sg:address":"Scherlebecker Str. 349",
    "sg:city":"Herten",
    "sg:phone":"+49 2366/43822",
    "sg:postcode":"45701",
    "sg:province":"Nordrhein-Westfalen",
    "wof:name":"Gastst\u00e4tte H. Berger",
    "wof:placetype":"venue"
},
  "geometry": {"coordinates":[7.1417770386,51.624584198],"type":"Point"}
}