{
  "type": "Feature",
  "properties": {
    "iso:country":"DE",
    "sg:address":"Fortunastr 24",
    "sg:city":"W\u00fclfrath",
    "sg:phone":"+49 2058/913884",
    "sg:postcode":"42489",
    "sg:province":"Nordrhein-Westfalen",
    "wof:name":"Holz-kamm W\u00fclfrather Holzhandelsgesellschaft Mbh",
    "wof:placetype":"venue"
},
  "geometry": {"coordinates":[7.01559,51.276588],"type":"Point"}
}