{
  "type": "Feature",
  "properties": {
    "iso:country":"DE",
    "sg:address":"Hauptstr. 67",
    "sg:city":"Gangelt",
    "sg:phone":"+49 2454/8919",
    "sg:postcode":"52538",
    "sg:province":"Nordrhein-Westfalen",
    "wof:name":"Sluypers Immobilienmakler",
    "wof:placetype":"venue"
},
  "geometry": {"coordinates":[6.0311999321,51.0044403076],"type":"Point"}
}