{
  "type": "Feature",
  "properties": {
    "iso:country":"DE",
    "sg:address":"Gr\u00e4pelweg 8",
    "sg:city":"Hamburg",
    "sg:phone":"+49 40/7257020",
    "sg:postcode":"21029",
    "sg:province":"Hamburg",
    "wof:name":"Haus Im Park",
    "wof:placetype":"venue"
},
  "geometry": {"coordinates":[10.218551,53.488911],"type":"Point"}
}