{
  "type": "Feature",
  "properties": {
    "iso:country":"DE",
    "sg:address":"Mozartstr. 56",
    "sg:city":"Hermersberg",
    "sg:phone":"+49 6333/64064",
    "sg:postcode":"66919",
    "sg:province":"Rheinland-Pfalz",
    "wof:name":"Hw-bauelemente",
    "wof:placetype":"venue"
},
  "geometry": {"coordinates":[7.631735,49.317291],"type":"Point"}
}