{
  "type": "Feature",
  "properties": {
    "iso:country":"DE",
    "sg:address":"Hauptstr. 47",
    "sg:city":"Leck",
    "sg:phone":"+49 4662/87160",
    "sg:postcode":"25917",
    "sg:province":"Schleswig-Holstein",
    "wof:name":"Spielzeug-paradies Hellmuth Petersen",
    "wof:placetype":"venue"
},
  "geometry": {"coordinates":[8.9692058563,54.7734947205],"type":"Point"}
}