{
  "type": "Feature",
  "properties": {
    "iso:country":"DE",
    "sg:address":"S\u00fcdring 1",
    "sg:city":"Coesfeld",
    "sg:phone":"+49 2541/3238",
    "sg:postcode":"48653",
    "sg:province":"Nordrhein-Westfalen",
    "wof:name":"Gastst\u00e4tte Monika Tebbel",
    "wof:placetype":"venue"
},
  "geometry": {"coordinates":[7.1672701836,51.942199707],"type":"Point"}
}