{
  "type": "Feature",
  "properties": {
    "iso:country":"DE",
    "sg:address":"Betzdorfer Str. 6",
    "sg:city":"Weitefeld",
    "sg:phone":"+49 2743/2442",
    "sg:postcode":"57586",
    "sg:province":"Rheinland-Pfalz",
    "wof:name":"Gasthof Gerhard",
    "wof:placetype":"venue"
},
  "geometry": {"coordinates":[7.9281430244,50.7254486084],"type":"Point"}
}