{
  "type": "Feature",
  "properties": {
    "iso:country":"DE",
    "sg:address":"Dorfstr. 11",
    "sg:city":"Atterwasch",
    "sg:postcode":"03172",
    "sg:province":"Brandenburg",
    "wof:name":"Ev. Kirche",
    "wof:placetype":"venue"
},
  "geometry": {"coordinates":[14.6419296265,51.9538383484],"type":"Point"}
}