{
  "type": "Feature",
  "properties": {
    "iso:country":"DE",
    "sg:address":"Am Steintor 18",
    "sg:city":"Halle",
    "sg:phone":"+49 345/5170248",
    "sg:postcode":"06112",
    "sg:province":"Sachsen-Anhalt",
    "wof:name":"Wilhelm",
    "wof:placetype":"venue"
},
  "geometry": {"coordinates":[11.979036,51.488266],"type":"Point"}
}