{
  "type": "Feature",
  "properties": {
    "iso:country":"DE",
    "sg:address":"Gr\u00fcnlandweg 6 A",
    "sg:city":"Neufahrn",
    "sg:phone":"+49 8165/909845",
    "sg:postcode":"85375",
    "sg:province":"Bayern",
    "wof:name":"Northgate Communications Deutschland",
    "wof:placetype":"venue"
},
  "geometry": {"coordinates":[11.658913,48.323196],"type":"Point"}
}