{
  "type": "Feature",
  "properties": {
    "iso:country":"DE",
    "sg:address":"Zum Sportplatz 1",
    "sg:city":"Bad Berleburg",
    "sg:phone":"+49 2755/558",
    "sg:postcode":"57319",
    "sg:province":"Nordrhein-Westfalen",
    "wof:name":"Gelbach Holz Gmbh",
    "wof:placetype":"venue"
},
  "geometry": {"coordinates":[8.4698581696,51.0219306946],"type":"Point"}
}