{
  "type": "Feature",
  "properties": {
    "iso:country":"DE",
    "sg:address":"Annaberger Str. 485",
    "sg:city":"Chemnitz",
    "sg:phone":"+49 371/5308730",
    "sg:postcode":"09125",
    "sg:province":"Sachsen",
    "wof:name":"K. Manegold",
    "wof:placetype":"venue"
},
  "geometry": {"coordinates":[12.927232,50.776943],"type":"Point"}
}