{
  "type": "Feature",
  "properties": {
    "iso:country":"DE",
    "sg:address":"Charlottenburger Str. 118",
    "sg:city":"Berlin",
    "sg:postcode":"13086",
    "sg:province":"Berlin",
    "wof:name":"Walter Mansfeld Bautr\u00e4ger- Und Bau-",
    "wof:placetype":"venue"
},
  "geometry": {"coordinates":[13.445586,52.552147],"type":"Point"}
}