{
  "type": "Feature",
  "properties": {
    "iso:country":"DE",
    "sg:address":"Borenweg 1a",
    "sg:city":"Rostock",
    "sg:phone":"+49 381/2520000",
    "sg:postcode":"18057",
    "sg:province":"Mecklenburg-Vorpommern",
    "wof:name":"Beteiligungsgesellschaft Wassertechnik Und Bau Gmbh",
    "wof:placetype":"venue"
},
  "geometry": {"coordinates":[12.1229391098,54.0818557739],"type":"Point"}
}