{
  "type": "Feature",
  "properties": {
    "iso:country":"DE",
    "sg:address":"Neumann-Reichardt-Str. 38",
    "sg:city":"Hamburg",
    "sg:phone":"+49 40/6560046",
    "sg:postcode":"22041",
    "sg:province":"Hamburg",
    "wof:name":"Ritter Pharma - Technik Gmbh",
    "wof:placetype":"venue"
},
  "geometry": {"coordinates":[10.083547,53.573483],"type":"Point"}
}