{
  "type": "Feature",
  "properties": {
    "iso:country":"DE",
    "sg:address":"Martin-Niem\u00f6ller-Str. 30",
    "sg:city":"Ebersbach",
    "sg:phone":"+49 3586/364648",
    "sg:postcode":"02730",
    "sg:province":"Sachsen",
    "wof:name":"Horst Pohl Gbr",
    "wof:placetype":"venue"
},
  "geometry": {"coordinates":[14.59695,51.008011],"type":"Point"}
}