{
  "type": "Feature",
  "properties": {
    "iso:country":"DE",
    "sg:address":"Ellertalstr. 34",
    "sg:city":"Litzendorf",
    "sg:phone":"+49 9505/7965",
    "sg:postcode":"96123",
    "sg:province":"Bayern",
    "wof:name":"Robert R\u00fcmpelein",
    "wof:placetype":"venue"
},
  "geometry": {"coordinates":[11.0500030518,49.9161834717],"type":"Point"}
}