{
  "type": "Feature",
  "properties": {
    "iso:country":"DE",
    "sg:address":"Sudetenring 184",
    "sg:city":"Dreieich",
    "sg:phone":"+49 6103/311481",
    "sg:postcode":"63303",
    "sg:province":"Hessen",
    "wof:name":"Volprecht Kalbfleisch Architekt",
    "wof:placetype":"venue"
},
  "geometry": {"coordinates":[8.689215,50.035023],"type":"Point"}
}