{
  "type": "Feature",
  "properties": {
    "iso:country":"DE",
    "sg:address":"Hauptstr. 138-140",
    "sg:city":"Frechen",
    "sg:phone":"+49 2234/16610",
    "sg:postcode":"50226",
    "sg:province":"Nordrhein-Westfalen",
    "wof:name":"Bernd Freutel Rechtsanwalt",
    "wof:placetype":"venue"
},
  "geometry": {"coordinates":[6.8060321808,50.909236908],"type":"Point"}
}