{
  "type": "Feature",
  "properties": {
    "iso:country":"DE",
    "sg:address":"Otto-Kaysel-Str. 3",
    "sg:city":"Ludwigslust",
    "sg:phone":"+49 3874/21448",
    "sg:postcode":"19288",
    "sg:province":"Mecklenburg-Vorpommern",
    "wof:name":"Werner Korzitze Rechtsanwalt",
    "wof:placetype":"venue"
},
  "geometry": {"coordinates":[11.4925394058,53.3290405273],"type":"Point"}
}