{
  "type": "Feature",
  "properties": {
    "iso:country":"DE",
    "sg:address":"Boltzmannstr. 15",
    "sg:city":"Garching",
    "sg:postcode":"85748",
    "sg:province":"Bayern",
    "wof:name":"Wel Chem Gmbh",
    "wof:placetype":"venue"
},
  "geometry": {"coordinates":[-110.7298736572,32.1919593811],"type":"Point"}
}