{
  "type": "Feature",
  "properties": {
    "iso:country":"DE",
    "sg:address":"Ehrenfeld 49",
    "sg:city":"Bergisch Gladbach",
    "sg:phone":"+49 2204/81464",
    "sg:postcode":"51429",
    "sg:province":"Nordrhein-Westfalen",
    "wof:name":"Kohlgr\u00fcber Orthop\u00e4die Gmbh",
    "wof:placetype":"venue"
},
  "geometry": {"coordinates":[7.2138581276,50.9636039734],"type":"Point"}
}