{
  "type": "Feature",
  "properties": {
    "iso:country":"DE",
    "sg:address":"Soltmannstr. 29",
    "sg:city":"Bad Salzdetfurth",
    "sg:postcode":"31162",
    "sg:province":"Niedersachsen",
    "wof:name":"Kath. \u00f6ffentliche B\u00fccherei Pfarrheim Detfurth",
    "wof:placetype":"venue"
},
  "geometry": {"coordinates":[10.025768,52.074844],"type":"Point"}
}