{
  "type": "Feature",
  "properties": {
    "iso:country":"DE",
    "sg:address":"M\u00fchlenweg 6 B",
    "sg:city":"Bad Honnef",
    "sg:phone":"+49 2224/5764",
    "sg:postcode":"53604",
    "sg:province":"Nordrhein-Westfalen",
    "wof:name":"Agnes Schneider Pension",
    "wof:placetype":"venue"
},
  "geometry": {"coordinates":[7.2135720253,50.6561317444],"type":"Point"}
}