{
  "type": "Feature",
  "properties": {
    "iso:country":"DE",
    "sg:address":"Heidkoppel 25",
    "sg:city":"Gro\u00dfhansdorf",
    "sg:phone":"+49 4102/691777",
    "sg:postcode":"22927",
    "sg:province":"Schleswig-Holstein",
    "wof:name":"Angelika Born Hebamme",
    "wof:placetype":"venue"
},
  "geometry": {"coordinates":[10.270079,53.648605],"type":"Point"}
}