{
  "type": "Feature",
  "properties": {
    "iso:country":"DE",
    "sg:address":"Sebald-Heyden-Str. 22",
    "sg:city":"N\u00fcrnberg",
    "sg:phone":"+49 911/483402",
    "sg:postcode":"90469",
    "sg:province":"Bayern",
    "wof:name":"Herbert Neudert",
    "wof:placetype":"venue"
},
  "geometry": {"coordinates":[11.081067,49.408161],"type":"Point"}
}