{
  "type": "Feature",
  "properties": {
    "iso:country":"DE",
    "sg:address":"Alpenstr. 1",
    "sg:city":"Woringen",
    "sg:phone":"+49 8331/95750",
    "sg:postcode":"87789",
    "sg:province":"Bayern",
    "wof:name":"Confiserie Heilemann Gmbh",
    "wof:placetype":"venue"
},
  "geometry": {"coordinates":[10.2055873871,47.9276618958],"type":"Point"}
}