{
  "type": "Feature",
  "properties": {
    "iso:country":"DE",
    "sg:address":"Lu\u00dfheimer Str. 2",
    "sg:city":"Hockenheim",
    "sg:phone":"+49 6205/14231",
    "sg:postcode":"68766",
    "sg:province":"Baden-W\u00fcrttemberg",
    "wof:name":"Minimal",
    "wof:placetype":"venue"
},
  "geometry": {"coordinates":[8.5373058319,49.3146057129],"type":"Point"}
}