{
  "type": "Feature",
  "properties": {
    "iso:country":"DE",
    "sg:address":"Schlo\u00dfstr. 48",
    "sg:city":"Saarwellingen",
    "sg:phone":"+49 6838/3886",
    "sg:postcode":"66793",
    "sg:province":"Saarland",
    "wof:name":"China-restaurant Jasmin Gmbh",
    "wof:placetype":"venue"
},
  "geometry": {"coordinates":[6.8103990555,49.3529281616],"type":"Point"}
}