{
  "type": "Feature",
  "properties": {
    "iso:country":"DE",
    "sg:address":"Schorlemerstr. 32",
    "sg:city":"Ahaus",
    "sg:phone":"+49 2561/2387",
    "sg:postcode":"48683",
    "sg:province":"Nordrhein-Westfalen",
    "wof:name":"M. Und Walter Kausler Architekten",
    "wof:placetype":"venue"
},
  "geometry": {"coordinates":[7.019227,52.075424],"type":"Point"}
}