{
  "type": "Feature",
  "properties": {
    "iso:country":"DE",
    "sg:address":"Kirchsteig 47",
    "sg:city":"K\u00f6nigs Wusterhausen",
    "sg:phone":"+49 3375/290202",
    "sg:postcode":"15711",
    "sg:province":"Brandenburg",
    "wof:name":"Marian Cybulski",
    "wof:placetype":"venue"
},
  "geometry": {"coordinates":[13.642714,52.295231],"type":"Point"}
}