{
  "type": "Feature",
  "properties": {
    "iso:country":"DE",
    "sg:address":"Bahnhofstr. 45",
    "sg:city":"Rottenburg",
    "sg:phone":"+49 7472/441333",
    "sg:postcode":"72108",
    "sg:province":"Baden-W\u00fcrttemberg",
    "wof:name":"W\u00f6llermann Und Russius Rechtsanw\u00e4lte",
    "wof:placetype":"venue"
},
  "geometry": {"coordinates":[8.9355554581,48.4729156494],"type":"Point"}
}