{
  "type": "Feature",
  "properties": {
    "iso:country":"DE",
    "sg:address":"Kreuzbergstr. 35",
    "sg:city":"Riedenberg",
    "sg:phone":"+49 9749/1271",
    "sg:postcode":"97792",
    "sg:province":"Bayern",
    "wof:name":"P. Morath",
    "wof:placetype":"venue"
},
  "geometry": {"coordinates":[9.8631048203,50.3220901489],"type":"Point"}
}