{
  "type": "Feature",
  "properties": {
    "iso:country":"DE",
    "sg:address":"Hans-B\u00f6ckler-Allee 15",
    "sg:city":"Bonn",
    "sg:postcode":"53177",
    "sg:province":"Nordrhein-Westfalen",
    "wof:name":"Buchversand Islamica",
    "wof:placetype":"venue"
},
  "geometry": {"coordinates":[7.1624031067,50.6766281128],"type":"Point"}
}