{
  "type": "Feature",
  "properties": {
    "iso:country":"DE",
    "sg:address":"Am Gehlberg 1a",
    "sg:city":"Vacha",
    "sg:phone":"+49 36962/25424",
    "sg:postcode":"36404",
    "sg:province":"Th\u00fcringen",
    "wof:name":"Joachim Heurich",
    "wof:placetype":"venue"
},
  "geometry": {"coordinates":[10.0305767059,50.8247718811],"type":"Point"}
}