{
  "type": "Feature",
  "properties": {
    "iso:country":"DE",
    "sg:address":"Im Hof 6",
    "sg:city":"Sersheim",
    "sg:phone":"+49 7042/33448",
    "sg:postcode":"74372",
    "sg:province":"Baden-W\u00fcrttemberg",
    "wof:name":"Bernhard Feile",
    "wof:placetype":"venue"
},
  "geometry": {"coordinates":[9.0136604309,48.9623603821],"type":"Point"}
}