{
  "type": "Feature",
  "properties": {
    "iso:country":"DE",
    "sg:address":"Bodelschwinghstr. 16",
    "sg:city":"Versmold",
    "sg:phone":"+49 5423/8595",
    "sg:postcode":"33775",
    "sg:province":"Nordrhein-Westfalen",
    "wof:name":"Manfred Schmidt",
    "wof:placetype":"venue"
},
  "geometry": {"coordinates":[8.1475734711,52.0339317322],"type":"Point"}
}