{
  "type": "Feature",
  "properties": {
    "iso:country":"DE",
    "sg:address":"Alte Frankfurter Str. 182",
    "sg:city":"Braunschweig",
    "sg:phone":"+49 531/871212",
    "sg:postcode":"38122",
    "sg:province":"Niedersachsen",
    "wof:name":"M\u00f6belhaus Lehmann",
    "wof:placetype":"venue"
},
  "geometry": {"coordinates":[10.5079069138,52.2370681763],"type":"Point"}
}