{
  "type": "Feature",
  "properties": {
    "iso:country":"DE",
    "sg:address":"Friedrichstr. 50",
    "sg:city":"Eltville",
    "sg:phone":"+49 4961/2392400",
    "sg:postcode":"65343",
    "sg:province":"Hessen",
    "wof:name":"F\u00d6rster Elastomer Technik Ek",
    "wof:placetype":"venue"
},
  "geometry": {"coordinates":[8.1256637573,50.0308036804],"type":"Point"}
}