{
  "type": "Feature",
  "properties": {
    "iso:country":"DE",
    "sg:address":"Frauensteiner Str. 81",
    "sg:city":"Freiberg",
    "sg:postcode":"09599",
    "sg:province":"Sachsen",
    "wof:name":"Deutsch. Brennstoffinst. Roh- Stoff- U. Anlagentech. Ges. F.",
    "wof:placetype":"venue"
},
  "geometry": {"coordinates":[13.339619,50.916958],"type":"Point"}
}