{
  "type": "Feature",
  "properties": {
    "iso:country":"DE",
    "sg:address":"Petersburgstr. 100",
    "sg:city":"Celle",
    "sg:phone":"+49 5141/53371",
    "sg:postcode":"29223",
    "sg:province":"Niedersachsen",
    "wof:name":"Eisen- Und Metallbau Pustlauk Gmbh",
    "wof:placetype":"venue"
},
  "geometry": {"coordinates":[10.065098,52.635113],"type":"Point"}
}