{
  "type": "Feature",
  "properties": {
    "iso:country":"DE",
    "sg:address":"Ebellstr. 7",
    "sg:city":"Hannover",
    "sg:phone":"+49 511/555178",
    "sg:postcode":"30625",
    "sg:province":"Niedersachsen",
    "wof:name":"K.-h. Hasselmann",
    "wof:placetype":"venue"
},
  "geometry": {"coordinates":[9.7967214584,52.3747558594],"type":"Point"}
}