{
  "type": "Feature",
  "properties": {
    "iso:country":"DE",
    "sg:address":"Eintrachtstr. 113 POSTFACH 101655",
    "sg:city":"K\u00f6ln",
    "sg:phone":"+49 221/9129097",
    "sg:postcode":"50456",
    "sg:province":"Nordrhein-Westfalen",
    "wof:name":"Gude Analog-und Digital-systeme Gmbh",
    "wof:placetype":"venue"
},
  "geometry": {"coordinates":[6.9522018433,50.9452285767],"type":"Point"}
}