{
  "type": "Feature",
  "properties": {
    "iso:country":"DE",
    "sg:address":"Frankenstr. 54",
    "sg:city":"Essen",
    "sg:postcode":"45134",
    "sg:province":"Nordrhein-Westfalen",
    "wof:name":"Kubski Einzelhandels Ohg",
    "wof:placetype":"venue"
},
  "geometry": {"coordinates":[7.050963,51.428177],"type":"Point"}
}