{
  "type": "Feature",
  "properties": {
    "iso:country":"DE",
    "sg:address":"Unterm Brink 2",
    "sg:city":"Wulften",
    "sg:phone":"+49 5556/4752",
    "sg:postcode":"37199",
    "sg:province":"Niedersachsen",
    "wof:name":"G. Ehrhardt Heissmangel",
    "wof:placetype":"venue"
},
  "geometry": {"coordinates":[10.1738166809,51.6626281738],"type":"Point"}
}