{
  "type": "Feature",
  "properties": {
    "iso:country":"DE",
    "sg:address":"Gutenbergring 23",
    "sg:city":"Fernwald",
    "sg:phone":"+49 6404/91540",
    "sg:postcode":"35463",
    "sg:province":"Hessen",
    "wof:name":"Md Schilder & Kommunalbedarf Gmbh",
    "wof:placetype":"venue"
},
  "geometry": {"coordinates":[8.775102,50.545555],"type":"Point"}
}