{
  "type": "Feature",
  "properties": {
    "iso:country":"DE",
    "sg:address":"Hultschiner Damm 47",
    "sg:city":"Berlin",
    "sg:phone":"+49 30/5677568",
    "sg:postcode":"12623",
    "sg:province":"Berlin",
    "wof:name":"Wobis Projektentwicklungs Und Beratungs Gmbh",
    "wof:placetype":"venue"
},
  "geometry": {"coordinates":[13.600652,52.478855],"type":"Point"}
}