{
  "type": "Feature",
  "properties": {
    "iso:country":"DE",
    "sg:address":"48493",
    "sg:city":"Wettringen",
    "sg:phone":"+49 2557/7866",
    "sg:postcode":"48493",
    "sg:province":"Nordrhein-Westfalen",
    "wof:name":"Schwimmhalle",
    "wof:placetype":"venue"
},
  "geometry": {"coordinates":[7.3020401001,52.2341690063],"type":"Point"}
}