{
  "type": "Feature",
  "properties": {
    "iso:country":"DE",
    "sg:address":"K\u00f6nigsau 15",
    "sg:city":"Erwitte",
    "sg:phone":"+49 2943/2464",
    "sg:postcode":"59597",
    "sg:province":"Nordrhein-Westfalen",
    "wof:name":"Sprinkmeier Bauunter- Nehmung Gmbh",
    "wof:placetype":"venue"
},
  "geometry": {"coordinates":[8.402920723,51.6205101013],"type":"Point"}
}