{
  "type": "Feature",
  "properties": {
    "iso:country":"DE",
    "sg:address":"Schlo\u00dfplatz 1",
    "sg:city":"Aschaffenburg",
    "sg:phone":"+49 6021/181710",
    "sg:postcode":"63739",
    "sg:province":"Bayern",
    "wof:name":"Glockenspiel Inh. Bernhard Counil",
    "wof:placetype":"venue"
},
  "geometry": {"coordinates":[9.1443223953,49.9762458801],"type":"Point"}
}