{
  "type": "Feature",
  "properties": {
    "iso:country":"DE",
    "sg:address":"Katzenstr. 20",
    "sg:city":"Bielefeld",
    "sg:phone":"+49 521/105408",
    "sg:postcode":"33619",
    "sg:province":"Nordrhein-Westfalen",
    "wof:name":"Vamos Grundst\u00fccks- Verwaltungs Gmbh",
    "wof:placetype":"venue"
},
  "geometry": {"coordinates":[8.4401988983,52.0448532104],"type":"Point"}
}