{
  "type": "Feature",
  "properties": {
    "iso:country":"DE",
    "sg:address":"Europa-Allee",
    "sg:city":"F\u00f6hren",
    "sg:phone":"+49 6502/92720",
    "sg:postcode":"54343",
    "sg:province":"Rheinland-Pfalz",
    "wof:name":"Hvl L\u00fcftungs- Und Geb\u00e4ude- Technische Anlagen Gmbh",
    "wof:placetype":"venue"
},
  "geometry": {"coordinates":[6.7894349098,49.8613815308],"type":"Point"}
}