{
  "type": "Feature",
  "properties": {
    "iso:country":"DE",
    "sg:address":"Asemisser Allee 44",
    "sg:city":"Leopoldsh\u00f6he",
    "sg:phone":"+49 5202/82632",
    "sg:postcode":"33818",
    "sg:province":"Nordrhein-Westfalen",
    "wof:name":"E. Schmidt-gem\u00fcnd",
    "wof:placetype":"venue"
},
  "geometry": {"coordinates":[8.66962,51.982243],"type":"Point"}
}