{
  "type": "Feature",
  "properties": {
    "iso:country":"DE",
    "sg:address":"N\u00fcrnberger Str 57",
    "sg:city":"W\u00fcrzburg",
    "sg:phone":"+49 931/705770",
    "sg:postcode":"97076",
    "sg:province":"Bayern",
    "wof:name":"Internationale Spedition Max Sch\u00fcrger Ek",
    "wof:placetype":"venue"
},
  "geometry": {"coordinates":[9.9760503769,49.7962837219],"type":"Point"}
}