{
  "type": "Feature",
  "properties": {
    "iso:country":"DE",
    "sg:address":"M\u00fchlenstr. 8",
    "sg:city":"R\u00fcschendorf",
    "sg:phone":"+49 4954/917535",
    "sg:postcode":"49401",
    "sg:province":"Niedersachsen",
    "wof:name":"Volksbank Damme Eg.",
    "wof:placetype":"venue"
},
  "geometry": {"coordinates":[8.27423,52.521839],"type":"Point"}
}