{
  "type": "Feature",
  "properties": {
    "iso:country":"DE",
    "sg:address":"Friedhofstr. 8",
    "sg:city":"Konradsreuth",
    "sg:phone":"+49 9292/1712",
    "sg:postcode":"95176",
    "sg:province":"Bayern",
    "wof:name":"H. Hoffmann",
    "wof:placetype":"venue"
},
  "geometry": {"coordinates":[11.845674,50.268452],"type":"Point"}
}