{
  "type": "Feature",
  "properties": {
    "iso:country":"DE",
    "sg:address":"Calandrellistr. 15A",
    "sg:city":"Berlin",
    "sg:phone":"+49 30/76902090",
    "sg:postcode":"12247",
    "sg:province":"Berlin",
    "wof:name":"Criee Immobilien",
    "wof:placetype":"venue"
},
  "geometry": {"coordinates":[13.3312759399,52.4398345947],"type":"Point"}
}