{
  "type": "Feature",
  "properties": {
    "iso:country":"DE",
    "sg:address":"Ostpassage 9",
    "sg:city":"Langenhagen",
    "sg:phone":"+49 511/737229",
    "sg:postcode":"30853",
    "sg:province":"Niedersachsen",
    "wof:name":"Gerti Volkmer",
    "wof:placetype":"venue"
},
  "geometry": {"coordinates":[9.741748,52.439301],"type":"Point"}
}