{
  "type": "Feature",
  "properties": {
    "iso:country":"DE",
    "sg:address":"Gleimweg 4",
    "sg:city":"Magdeburg",
    "sg:phone":"+49 391/7332461",
    "sg:postcode":"39108",
    "sg:province":"Sachsen-Anhalt",
    "wof:name":"Fliesen-ebeling",
    "wof:placetype":"venue"
},
  "geometry": {"coordinates":[11.6136770248,52.1249160767],"type":"Point"}
}