{
  "type": "Feature",
  "properties": {
    "iso:country":"DE",
    "sg:address":"K\u00f6lner Landstr. 74",
    "sg:city":"D\u00fcsseldorf",
    "sg:phone":"+49 211/720333",
    "sg:postcode":"40591",
    "sg:province":"Nordrhein-Westfalen",
    "wof:name":"D. Und L. Lemnitzer",
    "wof:placetype":"venue"
},
  "geometry": {"coordinates":[6.814219,51.19413],"type":"Point"}
}