{
  "type": "Feature",
  "properties": {
    "iso:country":"DE",
    "sg:address":"Metzinger Str. 3",
    "sg:city":"Bempflingen",
    "sg:phone":"+49 7123/36637",
    "sg:postcode":"72658",
    "sg:province":"Baden-W\u00fcrttemberg",
    "wof:name":"Jochen Lanitz Steuerberater",
    "wof:placetype":"venue"
},
  "geometry": {"coordinates":[9.2686748505,48.5715827942],"type":"Point"}
}