{
  "type": "Feature",
  "properties": {
    "iso:country":"DE",
    "sg:address":"K\u00f6nigsworther Platz 6",
    "sg:city":"Hannover",
    "sg:phone":"+49 511/76310",
    "sg:postcode":"30167",
    "sg:province":"Niedersachsen",
    "wof:name":"Verm\u00f6gensverwaltungs- U. Treu- Handges. Der Industriegewerk-",
    "wof:placetype":"venue"
},
  "geometry": {"coordinates":[9.7221012115,52.3783149719],"type":"Point"}
}