{
  "type": "Feature",
  "properties": {
    "iso:country":"DE",
    "sg:address":"Karl-Liebknecht-Str. 60 a",
    "sg:city":"Cottbus",
    "sg:phone":"+49 355/3819588",
    "sg:postcode":"03046",
    "sg:province":"Brandenburg",
    "wof:name":"Beatrix Frenkel Rechtsanw\u00e4ltin",
    "wof:placetype":"venue"
},
  "geometry": {"coordinates":[14.3035030365,51.7542800903],"type":"Point"}
}