{
  "type": "Feature",
  "properties": {
    "iso:country":"DE",
    "sg:address":"An St. Johannes 5",
    "sg:city":"Duderstadt",
    "sg:postcode":"37115",
    "sg:province":"Niedersachsen",
    "wof:name":"Dd. Leunig Gmbh",
    "wof:placetype":"venue"
},
  "geometry": {"coordinates":[10.3092412949,51.5600013733],"type":"Point"}
}