{
  "type": "Feature",
  "properties": {
    "iso:country":"DE",
    "sg:address":"Frankenring 41",
    "sg:city":"Langenhagen",
    "sg:phone":"+49 511/978650",
    "sg:postcode":"30855",
    "sg:province":"Niedersachsen",
    "wof:name":"Feuerverzinkung Hannover Gmbh & Co. Kg",
    "wof:placetype":"venue"
},
  "geometry": {"coordinates":[9.6874904633,52.4436454773],"type":"Point"}
}