{
  "type": "Feature",
  "properties": {
    "iso:country":"DE",
    "sg:address":"Gutenbergstr. 21",
    "sg:city":"Regenstauf",
    "sg:phone":"+49 9402/93170",
    "sg:postcode":"93128",
    "sg:province":"Bayern",
    "wof:name":"Knott Gmbh",
    "wof:placetype":"venue"
},
  "geometry": {"coordinates":[12.1203718185,49.110080719],"type":"Point"}
}