{
  "type": "Feature",
  "properties": {
    "iso:country":"DE",
    "sg:address":"Vogelsanger Str. 200",
    "sg:city":"K\u00f6ln",
    "sg:phone":"+49 221/542326",
    "sg:postcode":"50825",
    "sg:province":"Nordrhein-Westfalen",
    "wof:name":"Underground",
    "wof:placetype":"venue"
},
  "geometry": {"coordinates":[6.9131059647,50.9495735168],"type":"Point"}
}