{
  "type": "Feature",
  "properties": {
    "iso:country":"DE",
    "sg:address":"Katernberger Str 7",
    "sg:city":"Essen",
    "sg:phone":"+49 201/309173",
    "sg:postcode":"45355",
    "sg:province":"Nordrhein-Westfalen",
    "wof:name":"Citibank Privatkunden Ag",
    "wof:placetype":"venue"
},
  "geometry": {"coordinates":[6.950845,51.472816],"type":"Point"}
}