{
  "type": "Feature",
  "properties": {
    "iso:country":"DE",
    "sg:address":"Planstr. 8",
    "sg:city":"Neckartenzlingen",
    "sg:phone":"+49 7127/22038",
    "sg:postcode":"72654",
    "sg:province":"Baden-W\u00fcrttemberg",
    "wof:name":"Eberwein",
    "wof:placetype":"venue"
},
  "geometry": {"coordinates":[9.2362127304,48.5901184082],"type":"Point"}
}