{
  "type": "Feature",
  "properties": {
    "iso:country":"DE",
    "sg:address":"Hauptstr. 282",
    "sg:city":"Fischbach",
    "sg:postcode":"55743",
    "sg:province":"Rheinland-Pfalz",
    "wof:name":"Khb Stephan Gmbh & Co. Kg",
    "wof:placetype":"venue"
},
  "geometry": {"coordinates":[7.3903899193,49.7456817627],"type":"Point"}
}