{
  "type": "Feature",
  "properties": {
    "iso:country":"DE",
    "sg:address":"Itzenb\u00fctteler Str. 25",
    "sg:city":"Jesteburg",
    "sg:phone":"+49 4183/4020",
    "sg:postcode":"21266",
    "sg:province":"Niedersachsen",
    "wof:name":"Segufix Neuheiten Center Gmbh",
    "wof:placetype":"venue"
},
  "geometry": {"coordinates":[9.9499292374,53.311706543],"type":"Point"}
}