{
  "type": "Feature",
  "properties": {
    "iso:country":"DE",
    "sg:address":"Hamelner Str. 1a",
    "sg:city":"Barntrup",
    "sg:phone":"+49 5263/2545",
    "sg:postcode":"32683",
    "sg:province":"Nordrhein-Westfalen",
    "wof:name":"H. Ewert",
    "wof:placetype":"venue"
},
  "geometry": {"coordinates":[9.1168804169,51.9904556274],"type":"Point"}
}