{
  "type": "Feature",
  "properties": {
    "iso:country":"DE",
    "sg:address":"zur Forelle 1",
    "sg:city":"\u00dcberlingen",
    "sg:phone":"+49 7551/92630",
    "sg:postcode":"88662",
    "sg:province":"Baden-W\u00fcrttemberg",
    "wof:name":"Seepark, Kurg\u00e4stehaus",
    "wof:placetype":"venue"
},
  "geometry": {"coordinates":[9.19323,47.751411],"type":"Point"}
}