{
  "type": "Feature",
  "properties": {
    "iso:country":"DE",
    "sg:address":"Bahnhofstr. 32",
    "sg:city":"Bobingen",
    "sg:phone":"+49 8234/3612",
    "sg:postcode":"86399",
    "sg:province":"Bayern",
    "wof:name":"Pension Georg",
    "wof:placetype":"venue"
},
  "geometry": {"coordinates":[10.8347549438,48.2663154602],"type":"Point"}
}