{
  "type": "Feature",
  "properties": {
    "iso:country":"DE",
    "sg:address":"Am Lauchberg 1",
    "sg:city":"Eilenburg",
    "sg:postcode":"04838",
    "sg:province":"Sachsen",
    "wof:name":"Schwarzer Verm\u00f6gens- Und Verwaltungsgesellschaft Mbh",
    "wof:placetype":"venue"
},
  "geometry": {"coordinates":[12.6755094528,51.4491958618],"type":"Point"}
}