{
  "type": "Feature",
  "properties": {
    "iso:country":"DE",
    "sg:address":"T\u00f6nninger Str. 48",
    "sg:city":"Garding",
    "sg:phone":"+49 4862/767",
    "sg:postcode":"25836",
    "sg:province":"Schleswig-Holstein",
    "wof:name":"Dornbusch Baugesellschaft Mbh",
    "wof:placetype":"venue"
},
  "geometry": {"coordinates":[8.761235,54.361076],"type":"Point"}
}