{
  "type": "Feature",
  "properties": {
    "iso:country":"DE",
    "sg:address":"Schulstr. 1",
    "sg:city":"N\u00fctzen",
    "sg:phone":"+49 4191/2287",
    "sg:postcode":"24568",
    "sg:province":"Schleswig-Holstein",
    "wof:name":"Ernst-albert Pohlmann",
    "wof:placetype":"venue"
},
  "geometry": {"coordinates":[9.923576355,53.8634223938],"type":"Point"}
}