{
  "type": "Feature",
  "properties": {
    "iso:country":"DE",
    "sg:address":"Ro\u00dfbacher Str. 20",
    "sg:city":"Naumburg",
    "sg:phone":"+49 3445/200411",
    "sg:postcode":"06618",
    "sg:province":"Sachsen-Anhalt",
    "wof:name":"Kleine & M\u00fcller Gbr Naumburger Fruchtquell",
    "wof:placetype":"venue"
},
  "geometry": {"coordinates":[11.7981777191,51.1586265564],"type":"Point"}
}