{
  "type": "Feature",
  "properties": {
    "iso:country":"DE",
    "sg:address":"Ludwig-Guttmann-Str. 24",
    "sg:city":"Heidelberg",
    "sg:phone":"+49 6221/883163",
    "sg:postcode":"69123",
    "sg:province":"Baden-W\u00fcrttemberg",
    "wof:name":"Krankenhausvollapotheke Der Stiftung Rehabilitation",
    "wof:placetype":"venue"
},
  "geometry": {"coordinates":[8.648052,49.4254],"type":"Point"}
}