{
  "type": "Feature",
  "properties": {
    "iso:country":"DE",
    "sg:address":"Paulinenstr. 20a",
    "sg:city":"Bochum",
    "sg:phone":"+49 234/384601",
    "sg:postcode":"44799",
    "sg:province":"Nordrhein-Westfalen",
    "wof:name":"Arendt Gmbh",
    "wof:placetype":"venue"
},
  "geometry": {"coordinates":[7.241937,51.462204],"type":"Point"}
}