{
  "type": "Feature",
  "properties": {
    "iso:country":"DE",
    "sg:address":"Herzogstr. 19",
    "sg:city":"Staufenberg",
    "sg:phone":"+49 5543/1545",
    "sg:postcode":"34355",
    "sg:province":"Niedersachsen",
    "wof:name":"Bernd Petermann",
    "wof:placetype":"venue"
},
  "geometry": {"coordinates":[9.6429605484,51.3528327942],"type":"Point"}
}