{
  "type": "Feature",
  "properties": {
    "iso:country":"DE",
    "sg:address":"Am Schwabenbach 2",
    "sg:city":"Fu\u00dfg\u00f6nheim",
    "sg:phone":"+49 6237/80950",
    "sg:postcode":"67136",
    "sg:province":"Rheinland-Pfalz",
    "wof:name":"P. Harke Ingenieur",
    "wof:placetype":"venue"
},
  "geometry": {"coordinates":[8.2902879715,49.4556388855],"type":"Point"}
}