{
  "type": "Feature",
  "properties": {
    "iso:country":"DE",
    "sg:address":"Ringstr. 8",
    "sg:city":"Neuental",
    "sg:phone":"+49 6693/671",
    "sg:postcode":"34599",
    "sg:province":"Hessen",
    "wof:name":"Friedrich Albert-dingel",
    "wof:placetype":"venue"
},
  "geometry": {"coordinates":[9.269946,50.98764],"type":"Point"}
}