{
  "type": "Feature",
  "properties": {
    "iso:country":"DE",
    "sg:address":"Am K\u00f6nigshof",
    "sg:city":"Mettmann",
    "sg:phone":"+49 2104/795286",
    "sg:postcode":"40822",
    "sg:province":"Nordrhein-Westfalen",
    "wof:name":"Stadtbibliothek Stadthalle",
    "wof:placetype":"venue"
},
  "geometry": {"coordinates":[6.975779,51.2491],"type":"Point"}
}