{
  "type": "Feature",
  "properties": {
    "iso:country":"DE",
    "sg:address":"Auf dem Falkenberg 5",
    "sg:city":"Wettenberg",
    "sg:postcode":"35435",
    "sg:province":"Hessen",
    "wof:name":"Meinhard Grundst\u00fccksges. Gmbh & Co. Kg",
    "wof:placetype":"venue"
},
  "geometry": {"coordinates":[8.6477804184,50.6171226501],"type":"Point"}
}