{
  "type": "Feature",
  "properties": {
    "iso:country":"DE",
    "sg:address":"Breesener Str. 77",
    "sg:city":"Laage",
    "sg:phone":"+49 38459/506",
    "sg:postcode":"18299",
    "sg:province":"Mecklenburg-Vorpommern",
    "wof:name":"G. Przybilski",
    "wof:placetype":"venue"
},
  "geometry": {"coordinates":[12.3528718948,53.9211997986],"type":"Point"}
}