{
  "type": "Feature",
  "properties": {
    "iso:country":"DE",
    "sg:address":"Ziegenmarkt 2",
    "sg:city":"Parchim",
    "sg:postcode":"19370",
    "sg:province":"Mecklenburg-Vorpommern",
    "wof:name":"Fachgesch\u00e4ft Rundfunk Fernsehen",
    "wof:placetype":"venue"
},
  "geometry": {"coordinates":[11.8483352661,53.426109314],"type":"Point"}
}