{
  "type": "Feature",
  "properties": {
    "iso:country":"DE",
    "sg:address":"Strandweg 20",
    "sg:city":"Hamburg",
    "sg:phone":"+49 40/860385",
    "sg:postcode":"22587",
    "sg:province":"Hamburg",
    "wof:name":"Restaurant Schifferhaus Blankenese",
    "wof:placetype":"venue"
},
  "geometry": {"coordinates":[9.806848526,53.5567092896],"type":"Point"}
}