{
  "type": "Feature",
  "properties": {
    "iso:country":"DE",
    "sg:address":"Friedlandstr. 1a",
    "sg:city":"Andernach",
    "sg:phone":"+49 2632/44255",
    "sg:postcode":"56626",
    "sg:province":"Rheinland-Pfalz",
    "wof:name":"Ev. Pfarramt Pfarr. Bez. Ii",
    "wof:placetype":"venue"
},
  "geometry": {"coordinates":[7.4121198654,50.4238815308],"type":"Point"}
}