{
  "type": "Feature",
  "properties": {
    "iso:country":"DE",
    "sg:address":"Wilhelmstr. 19",
    "sg:city":"Hettstedt",
    "sg:phone":"+49 3476/200155",
    "sg:postcode":"06333",
    "sg:province":"Sachsen-Anhalt",
    "wof:name":"C. Hoppe",
    "wof:placetype":"venue"
},
  "geometry": {"coordinates":[11.510375,51.64455],"type":"Point"}
}