{
  "type": "Feature",
  "properties": {
    "iso:country":"DE",
    "sg:address":"Birkenallee 1a",
    "sg:city":"Dellfeld",
    "sg:phone":"+49 6336/6109",
    "sg:postcode":"66503",
    "sg:province":"Rheinland-Pfalz",
    "wof:name":"I. Buchmann",
    "wof:placetype":"venue"
},
  "geometry": {"coordinates":[7.4671602249,49.2269592285],"type":"Point"}
}