{
  "type": "Feature",
  "properties": {
    "iso:country":"DE",
    "sg:address":"Brunnenstr. 102",
    "sg:city":"Horn-Bad Meinberg",
    "sg:phone":"+49 5234/880988",
    "sg:postcode":"32805",
    "sg:province":"Nordrhein-Westfalen",
    "wof:name":"Christine Peter Heilpraktikerin",
    "wof:placetype":"venue"
},
  "geometry": {"coordinates":[8.985915184,51.8972892761],"type":"Point"}
}