{
  "type": "Feature",
  "properties": {
    "iso:country":"DE",
    "sg:address":"Am See 26",
    "sg:city":"Schrampe",
    "sg:phone":"+49 39384/27273",
    "sg:postcode":"39619",
    "sg:province":"Sachsen-Anhalt",
    "wof:name":"Alte Schmiede",
    "wof:placetype":"venue"
},
  "geometry": {"coordinates":[11.4912319183,52.8826560974],"type":"Point"}
}