{
  "type": "Feature",
  "properties": {
    "iso:country":"DE",
    "sg:address":"Schulstr. 32",
    "sg:city":"Oberursel",
    "sg:phone":"+49 6171/502472",
    "sg:postcode":"61440",
    "sg:province":"Hessen",
    "wof:name":"Stadtarchiv",
    "wof:placetype":"venue"
},
  "geometry": {"coordinates":[8.576657,50.201736],"type":"Point"}
}