{
  "type": "Feature",
  "properties": {
    "iso:country":"DE",
    "sg:address":"Gr\u00fctlohner Weg 27",
    "sg:city":"Borken",
    "sg:phone":"+49 2861/3358",
    "sg:postcode":"46325",
    "sg:province":"Nordrhein-Westfalen",
    "wof:name":"Johannes Feiertag Steuerberater",
    "wof:placetype":"venue"
},
  "geometry": {"coordinates":[6.8464140892,51.8362731934],"type":"Point"}
}