{
  "type": "Feature",
  "properties": {
    "iso:country":"DE",
    "sg:address":"Industrie-Park G\u00fcstrow :: R\u00f6vertannen 21",
    "sg:city":"G\u00fcstrow",
    "sg:phone":"+49 4938/4369360",
    "sg:postcode":"18273",
    "sg:province":"Mecklenburg-Vorpommern",
    "wof:name":"Mecklenburger Spirituosen Fabrik G Winkelhausen Gmbh",
    "wof:placetype":"venue"
},
  "geometry": {"coordinates":[12.172964,53.796772],"type":"Point"}
}