{
  "type": "Feature",
  "properties": {
    "iso:country":"DE",
    "sg:address":"Hauptstr 35",
    "sg:city":"Sch\u00f6ffengrund",
    "sg:phone":"+49 4964/457752",
    "sg:postcode":"35641",
    "sg:province":"Hessen",
    "wof:name":"Raiffeisenbank Eg",
    "wof:placetype":"venue"
},
  "geometry": {"coordinates":[8.470724,50.49482],"type":"Point"}
}