{
  "type": "Feature",
  "properties": {
    "iso:country":"DE",
    "sg:address":"M\u00fcnchener Str. 1",
    "sg:city":"Dillingen",
    "sg:postcode":"66763",
    "sg:province":"Saarland",
    "wof:name":"Netassist Gmbh",
    "wof:placetype":"venue"
},
  "geometry": {"coordinates":[6.7246069908,49.3724136353],"type":"Point"}
}