{
  "type": "Feature",
  "properties": {
    "iso:country":"DE",
    "sg:address":"Bahnhofstr. 39",
    "sg:city":"Gro\u00dflehna",
    "sg:phone":"+49 34205/58346",
    "sg:postcode":"04420",
    "sg:province":"Sachsen",
    "wof:name":"Horst Kober",
    "wof:placetype":"venue"
},
  "geometry": {"coordinates":[12.167845726,51.3076210022],"type":"Point"}
}