{
  "type": "Feature",
  "properties": {
    "iso:country":"DE",
    "sg:address":"Fasanenstr. 9",
    "sg:city":"Trochtelfingen",
    "sg:phone":"+49 7124/360",
    "sg:postcode":"72818",
    "sg:province":"Baden-W\u00fcrttemberg",
    "wof:name":"St\u00f6tz Gmbh",
    "wof:placetype":"venue"
},
  "geometry": {"coordinates":[9.242294,48.314213],"type":"Point"}
}