{
  "type": "Feature",
  "properties": {
    "iso:country":"DE",
    "sg:address":"Fliederstr. 9",
    "sg:city":"Malsch",
    "sg:phone":"+49 7246/5400",
    "sg:postcode":"76316",
    "sg:province":"Baden-W\u00fcrttemberg",
    "wof:name":"Anita Dobschat-oeder Architektin",
    "wof:placetype":"venue"
},
  "geometry": {"coordinates":[8.369843,48.899166],"type":"Point"}
}