{
  "type": "Feature",
  "properties": {
    "iso:country":"DE",
    "sg:address":"Gustav-Rau-Str. 3",
    "sg:city":"Bietigheim-Bissingen",
    "sg:phone":"+49 4971/426871",
    "sg:postcode":"74321",
    "sg:province":"Baden-W\u00fcrttemberg",
    "wof:name":"Eisenhandelsgmbh Sch\u00c4ffer & Mohn",
    "wof:placetype":"venue"
},
  "geometry": {"coordinates":[9.147338,48.948925],"type":"Point"}
}