{
  "type": "Feature",
  "properties": {
    "iso:country":"DE",
    "sg:address":"Schirumer Weg 4",
    "sg:city":"Aurich",
    "sg:phone":"+49 4941/4827",
    "sg:postcode":"26605",
    "sg:province":"Niedersachsen",
    "wof:name":"Harm Saathoff",
    "wof:placetype":"venue"
},
  "geometry": {"coordinates":[7.511069,53.457554],"type":"Point"}
}