{
  "type": "Feature",
  "properties": {
    "iso:country":"DE",
    "sg:address":"Justus-Liebig-Str. 6",
    "sg:city":"Walldorf",
    "sg:phone":"+49 6227/4292",
    "sg:postcode":"69190",
    "sg:province":"Baden-W\u00fcrttemberg",
    "wof:name":"Perplex M\u00f6bel Und Design Gmbh",
    "wof:placetype":"venue"
},
  "geometry": {"coordinates":[8.6495141983,49.2874526978],"type":"Point"}
}