{
  "type": "Feature",
  "properties": {
    "iso:country":"DE",
    "sg:address":"D\u00fcstergasse 5 b",
    "sg:city":"Remscheid",
    "sg:phone":"+49 2191/61730",
    "sg:postcode":"42897",
    "sg:province":"Nordrhein-Westfalen",
    "wof:name":"Helmut K\u00f6rschgen",
    "wof:placetype":"venue"
},
  "geometry": {"coordinates":[7.255543232,51.1910057068],"type":"Point"}
}