{
  "type": "Feature",
  "properties": {
    "iso:country":"DE",
    "sg:address":"Rote Str. 8",
    "sg:city":"G\u00f6ttingen",
    "sg:phone":"+49 551/41687",
    "sg:postcode":"37073",
    "sg:province":"Niedersachsen",
    "wof:name":"B\u00f6ckhoff H\u00f6rger\u00e4tehandel",
    "wof:placetype":"venue"
},
  "geometry": {"coordinates":[9.9377059937,51.5332641602],"type":"Point"}
}