{
  "type": "Feature",
  "properties": {
    "iso:country":"DE",
    "sg:address":"Osserstra\u00dfe 2",
    "sg:city":"Straubing",
    "sg:phone":"+49 9421/73070",
    "sg:postcode":"94315",
    "sg:province":"Bayern",
    "wof:name":"Hirschvogel Gmbh & Co.kg",
    "wof:placetype":"venue"
},
  "geometry": {"coordinates":[12.6072769165,48.8925628662],"type":"Point"}
}