{
  "type": "Feature",
  "properties": {
    "iso:country":"DE",
    "sg:address":"Hauptstr. 129",
    "sg:city":"Sinsheim",
    "sg:phone":"+49 7261/2481",
    "sg:postcode":"74889",
    "sg:province":"Baden-W\u00fcrttemberg",
    "wof:name":"Rudi Sitzler",
    "wof:placetype":"venue"
},
  "geometry": {"coordinates":[8.88041,49.252792],"type":"Point"}
}