{
  "type": "Feature",
  "properties": {
    "iso:country":"DE",
    "sg:address":"Am Ebertsberg 1",
    "sg:city":"Thal",
    "sg:phone":"+49 36929/88878",
    "sg:postcode":"99843",
    "sg:province":"Bayern",
    "wof:name":"B. Leibner",
    "wof:placetype":"venue"
},
  "geometry": {"coordinates":[10.3931722641,50.916305542],"type":"Point"}
}