{
  "type": "Feature",
  "properties": {
    "iso:country":"DE",
    "sg:address":"K\u00f6nigsberger Weg 6",
    "sg:city":"Saarbr\u00fccken",
    "sg:phone":"+49 681/881444",
    "sg:postcode":"66130",
    "sg:province":"Saarland",
    "wof:name":"Heinz Ries Inh. Dirk Dobronz",
    "wof:placetype":"venue"
},
  "geometry": {"coordinates":[7.0453228951,49.2120742798],"type":"Point"}
}