{
  "type": "Feature",
  "properties": {
    "iso:country":"DE",
    "sg:address":"Parkstra\u00dfe 3",
    "sg:city":"Altd\u00f6bern",
    "sg:phone":"+49 170 2174434",
    "sg:postcode":"03229",
    "sg:province":"Brandenburg",
    "wof:name":"Jan Voigt Online Altdoebern",
    "wof:placetype":"venue"
},
  "geometry": {"coordinates":[14.0309,51.651279],"type":"Point"}
}