{
  "type": "Feature",
  "properties": {
    "iso:country":"DE",
    "sg:address":"Gr\u00fcnmettstetter Str 17",
    "sg:city":"Horb",
    "sg:phone":"+49 7486/9411",
    "sg:postcode":"72160",
    "sg:province":"Baden-W\u00fcrttemberg",
    "wof:name":"Papierwarenfabrik Hermann Winkels Gmbh",
    "wof:placetype":"venue"
},
  "geometry": {"coordinates":[8.592601,48.444481],"type":"Point"}
}