{
  "type": "Feature",
  "properties": {
    "iso:country":"DE",
    "sg:address":"An der B 14",
    "sg:city":"Schnelldorf",
    "sg:phone":"+49 7950/98000",
    "sg:postcode":"91625",
    "sg:province":"Bayern",
    "wof:name":"Ruf Baustoffwerk Haundorf Gmbh",
    "wof:placetype":"venue"
},
  "geometry": {"coordinates":[10.2193813324,49.1701660156],"type":"Point"}
}