{
  "type": "Feature",
  "properties": {
    "iso:country":"DE",
    "sg:address":"Hauptstr. 57",
    "sg:city":"Wiesau",
    "sg:phone":"+49 9634/1273",
    "sg:postcode":"95676",
    "sg:province":"Bayern",
    "wof:name":"Engel-apotheke D. Gl\u00fcck P\u00e4chter Albert Haslauer E. K.",
    "wof:placetype":"venue"
},
  "geometry": {"coordinates":[12.187734,49.907963],"type":"Point"}
}