{
  "type": "Feature",
  "properties": {
    "iso:country":"DE",
    "sg:address":"Schulstr. 1",
    "sg:city":"T\u00fcrkheim",
    "sg:phone":"+49 8245/844",
    "sg:postcode":"86842",
    "sg:province":"Bayern",
    "wof:name":"L. Mayer",
    "wof:placetype":"venue"
},
  "geometry": {"coordinates":[10.643157959,48.0600166321],"type":"Point"}
}