{
  "type": "Feature",
  "properties": {
    "iso:country":"DE",
    "sg:address":"Dresdener Str. 42",
    "sg:city":"Spremberg",
    "sg:phone":"+49 3563/94962",
    "sg:postcode":"03130",
    "sg:province":"Brandenburg",
    "wof:name":"M. Kretschmer",
    "wof:placetype":"venue"
},
  "geometry": {"coordinates":[14.3717460632,51.5690116882],"type":"Point"}
}