{
  "type": "Feature",
  "properties": {
    "iso:country":"DE",
    "sg:address":"Metzer Str. 14",
    "sg:city":"Berlin",
    "sg:phone":"+49 30/4433690",
    "sg:postcode":"10405",
    "sg:province":"Berlin",
    "wof:name":"Urbanski Versorgungstechnik Und Service Gmbh",
    "wof:placetype":"venue"
},
  "geometry": {"coordinates":[13.42669,52.54052],"type":"Point"}
}