{
  "type": "Feature",
  "properties": {
    "iso:country":"DE",
    "sg:address":"Kleine Str. 12",
    "sg:city":"Wildeshausen",
    "sg:phone":"+49 4431/6836",
    "sg:postcode":"27793",
    "sg:province":"Niedersachsen",
    "wof:name":"Pizzeria Pinoccio",
    "wof:placetype":"venue"
},
  "geometry": {"coordinates":[8.4363489151,52.8957862854],"type":"Point"}
}