{
  "type": "Feature",
  "properties": {
    "iso:country":"DE",
    "sg:address":"Alexanderstr. 84",
    "sg:city":"Stuttgart",
    "sg:phone":"+49 711/245165",
    "sg:postcode":"70182",
    "sg:province":"Baden-W\u00fcrttemberg",
    "wof:name":"Prof. Antero Markelin Architekt",
    "wof:placetype":"venue"
},
  "geometry": {"coordinates":[9.183477,48.77124],"type":"Point"}
}