{
  "type": "Feature",
  "properties": {
    "iso:country":"DE",
    "sg:address":"Im Jacklbauernfeld 11",
    "sg:city":"G\u00fcnzburg",
    "sg:phone":"+49 8221/38754",
    "sg:postcode":"89312",
    "sg:province":"Bayern",
    "wof:name":"Hans Broeg",
    "wof:placetype":"venue"
},
  "geometry": {"coordinates":[10.31089,48.457684],"type":"Point"}
}