{
  "type": "Feature",
  "properties": {
    "iso:country":"DE",
    "sg:address":"Kaspersweg 47 a",
    "sg:city":"Oldenburg",
    "sg:phone":"+49 441/9519073",
    "sg:postcode":"26131",
    "sg:province":"Niedersachsen",
    "wof:name":"Paladion Immobilien Gmbh",
    "wof:placetype":"venue"
},
  "geometry": {"coordinates":[8.175302,53.130527],"type":"Point"}
}