{
  "type": "Feature",
  "properties": {
    "iso:country":"DE",
    "sg:address":"Alter Heuweg 25",
    "sg:city":"Schwarmstedt",
    "sg:phone":"+49 5071/800112",
    "sg:postcode":"29690",
    "sg:province":"Niedersachsen",
    "wof:name":"Snackmaster Tiefk\u00fchl- Produkte Gmbh & Co. Kg",
    "wof:placetype":"venue"
},
  "geometry": {"coordinates":[9.6196832657,52.6706619263],"type":"Point"}
}