{
  "type": "Feature",
  "properties": {
    "iso:country":"DE",
    "sg:address":"Kastenw\u00f6rtstr. 15a",
    "sg:city":"Karlsruhe",
    "sg:phone":"+49 721/572361",
    "sg:postcode":"76189",
    "sg:province":"Baden-W\u00fcrttemberg",
    "wof:name":"Georg L\u00f6rz",
    "wof:placetype":"venue"
},
  "geometry": {"coordinates":[8.3332452774,49.0055427551],"type":"Point"}
}