{
  "type": "Feature",
  "properties": {
    "iso:country":"DE",
    "sg:address":"Friedrich-Karl-Str 113",
    "sg:city":"Oberhausen",
    "sg:phone":"+49 208/8108950",
    "sg:postcode":"46045",
    "sg:province":"Nordrhein-Westfalen",
    "wof:name":"Essa Gmbh",
    "wof:placetype":"venue"
},
  "geometry": {"coordinates":[6.8480877876,51.4665031433],"type":"Point"}
}