{
  "type": "Feature",
  "properties": {
    "iso:country":"DE",
    "sg:address":"Mainblick 55",
    "sg:city":"Kronberg",
    "sg:phone":"+49 6173/65363",
    "sg:postcode":"61476",
    "sg:province":"Hessen",
    "wof:name":"Otmar Strobel Architekt",
    "wof:placetype":"venue"
},
  "geometry": {"coordinates":[8.525935,50.186199],"type":"Point"}
}