{
  "type": "Feature",
  "properties": {
    "iso:country":"DE",
    "sg:address":"Paradiesstr. 4",
    "sg:city":"M\u00fcnchen",
    "sg:phone":"+49 89/298478",
    "sg:postcode":"80538",
    "sg:province":"Bayern",
    "wof:name":"Roadrunners Buffet",
    "wof:placetype":"venue"
},
  "geometry": {"coordinates":[11.5937700272,48.1464004517],"type":"Point"}
}