{
  "type": "Feature",
  "properties": {
    "iso:country":"DE",
    "sg:address":"Langgasse 15",
    "sg:city":"Wetzlar",
    "sg:phone":"+49 6441/42761",
    "sg:postcode":"35576",
    "sg:province":"Hessen",
    "wof:name":"Karl Nold",
    "wof:placetype":"venue"
},
  "geometry": {"coordinates":[8.4973773956,50.5565490723],"type":"Point"}
}