{
  "type": "Feature",
  "properties": {
    "iso:country":"DE",
    "sg:address":"Alte Industriestr. 7",
    "sg:city":"Cuxhaven",
    "sg:phone":"+49 4721/74450",
    "sg:postcode":"27472",
    "sg:province":"Niedersachsen",
    "wof:name":"Techen & Steffens Kg",
    "wof:placetype":"venue"
},
  "geometry": {"coordinates":[8.711019,53.849918],"type":"Point"}
}