{
  "type": "Feature",
  "properties": {
    "iso:country":"DE",
    "sg:address":"Brunnenweg 1",
    "sg:city":"Postbauer-Heng",
    "sg:phone":"+49 9188/2300",
    "sg:postcode":"92353",
    "sg:province":"Bayern",
    "wof:name":"H\u00f6lzle Tennis-center",
    "wof:placetype":"venue"
},
  "geometry": {"coordinates":[11.3496704102,49.3036308289],"type":"Point"}
}