{
  "type": "Feature",
  "properties": {
    "iso:country":"DE",
    "sg:address":"Laurentiusstr. 35",
    "sg:city":"Sindelfingen",
    "sg:phone":"+49 7031/387236",
    "sg:postcode":"71069",
    "sg:province":"Baden-W\u00fcrttemberg",
    "wof:name":"Pudleiner Inh. Markus Pudleiner",
    "wof:placetype":"venue"
},
  "geometry": {"coordinates":[8.9633846283,48.7232246399],"type":"Point"}
}