{
  "type": "Feature",
  "properties": {
    "iso:country":"DE",
    "sg:address":"Feldstr. 3",
    "sg:city":"Uslar",
    "sg:phone":"+49 5571/1634",
    "sg:postcode":"37170",
    "sg:province":"Niedersachsen",
    "wof:name":"Karl Warnecke",
    "wof:placetype":"venue"
},
  "geometry": {"coordinates":[9.601221,51.673283],"type":"Point"}
}