{
  "type": "Feature",
  "properties": {
    "iso:country":"DE",
    "sg:address":"Johannes-Kirschbaum-Str. 2",
    "sg:city":"Meerbusch",
    "sg:phone":"+49 2132/760132",
    "sg:postcode":"40667",
    "sg:province":"Nordrhein-Westfalen",
    "wof:name":"Klaus Regnault Tennislehrer",
    "wof:placetype":"venue"
},
  "geometry": {"coordinates":[6.701031208,51.2546348572],"type":"Point"}
}