{
  "type": "Feature",
  "properties": {
    "iso:country":"DE",
    "sg:address":"Marienberger Str. 3",
    "sg:city":"Bad Marienberg",
    "sg:phone":"+49 2661/40922",
    "sg:postcode":"56470",
    "sg:province":"Rheinland-Pfalz",
    "wof:name":"S. W\u00fcst",
    "wof:placetype":"venue"
},
  "geometry": {"coordinates":[7.944199,50.636765],"type":"Point"}
}