{
  "type": "Feature",
  "properties": {
    "iso:country":"DE",
    "sg:address":"Bahnhofstr. 36",
    "sg:city":"M\u00fchlacker",
    "sg:phone":"+49 7041/940155",
    "sg:postcode":"75417",
    "sg:province":"Baden-W\u00fcrttemberg",
    "wof:name":"Computer-point Enz Gmbh",
    "wof:placetype":"venue"
},
  "geometry": {"coordinates":[8.840002,48.948936],"type":"Point"}
}