{
  "type": "Feature",
  "properties": {
    "iso:country":"DE",
    "sg:address":"In den Dillwiesen 15",
    "sg:city":"Argenthal",
    "sg:phone":"+49 6761/4022",
    "sg:postcode":"55496",
    "sg:province":"Rheinland-Pfalz",
    "wof:name":"Horst-dieter Hermani Kfz-sachverst\u00e4ndiger",
    "wof:placetype":"venue"
},
  "geometry": {"coordinates":[7.6041669846,49.9710426331],"type":"Point"}
}