{
  "type": "Feature",
  "properties": {
    "iso:country":"DE",
    "sg:address":"Kirchstr. 24",
    "sg:city":"Selfkant",
    "sg:phone":"+49 2456/1564",
    "sg:postcode":"52538",
    "sg:province":"Nordrhein-Westfalen",
    "wof:name":"Gastst\u00e4tte Dreissen",
    "wof:placetype":"venue"
},
  "geometry": {"coordinates":[5.9387388229,51.025390625],"type":"Point"}
}