{
  "type": "Feature",
  "properties": {
    "iso:country":"DE",
    "sg:address":"Wilhelmsstr. 1 u. 2",
    "sg:city":"Kassel",
    "sg:phone":"+49 561/10900",
    "sg:postcode":"34117",
    "sg:province":"Hessen",
    "wof:name":"Foto Digitallabor Heini Weber",
    "wof:placetype":"venue"
},
  "geometry": {"coordinates":[9.4912109375,51.3117866516],"type":"Point"}
}