{
  "type": "Feature",
  "properties": {
    "iso:country":"DE",
    "sg:address":"Oeseder Str. 86",
    "sg:city":"Georgsmarienh\u00fctte",
    "sg:phone":"+49 5401/6444",
    "sg:postcode":"49124",
    "sg:province":"Niedersachsen",
    "wof:name":"Stefan Siepelmeyer Rechtsanwalt",
    "wof:placetype":"venue"
},
  "geometry": {"coordinates":[8.0661802292,52.2048492432],"type":"Point"}
}