{
  "type": "Feature",
  "properties": {
    "iso:country":"DE",
    "sg:address":"Friedrichstr. 50a",
    "sg:city":"Hanau",
    "sg:phone":"+49 6181/32034",
    "sg:postcode":"63450",
    "sg:province":"Hessen",
    "wof:name":"W\u00f6lk Baubetreuungsges. Mbh",
    "wof:placetype":"venue"
},
  "geometry": {"coordinates":[8.919988,50.127632],"type":"Point"}
}