{
  "type": "Feature",
  "properties": {
    "iso:country":"DE",
    "sg:address":"Keltenring 53",
    "sg:city":"Dietzenbach",
    "sg:phone":"+49 6074/27789",
    "sg:postcode":"63128",
    "sg:province":"Hessen",
    "wof:name":"Wolfgang Fabry Rechtsanwalt",
    "wof:placetype":"venue"
},
  "geometry": {"coordinates":[8.7814207077,50.0307617188],"type":"Point"}
}