{
  "type": "Feature",
  "properties": {
    "iso:country":"DE",
    "sg:address":"Mecklenhorster Str 25",
    "sg:city":"Neustadt",
    "sg:phone":"+49 5032/2639",
    "sg:postcode":"31535",
    "sg:province":"Niedersachsen",
    "wof:name":"Saxonia Gmbh",
    "wof:placetype":"venue"
},
  "geometry": {"coordinates":[9.4794549942,52.5036277771],"type":"Point"}
}