{
  "type": "Feature",
  "properties": {
    "iso:country":"DE",
    "sg:address":"August-Macke-Str. 43",
    "sg:city":"Meckenheim",
    "sg:phone":"+49 2225/12645",
    "sg:postcode":"53340",
    "sg:province":"Nordrhein-Westfalen",
    "wof:name":"G. Maire Makler",
    "wof:placetype":"venue"
},
  "geometry": {"coordinates":[7.0412888527,50.6284065247],"type":"Point"}
}