{
  "type": "Feature",
  "properties": {
    "iso:country":"DE",
    "sg:address":"Moorstr. 25",
    "sg:city":"Steinwenden",
    "sg:postcode":"66879",
    "sg:province":"Rheinland-Pfalz",
    "wof:name":"Coplan Gmbh",
    "wof:placetype":"venue"
},
  "geometry": {"coordinates":[7.530304,49.45636],"type":"Point"}
}