{
  "type": "Feature",
  "properties": {
    "iso:country":"DE",
    "sg:address":"Kaubenheimer Str. 11",
    "sg:city":"Ipsheim",
    "sg:phone":"+49 9846/517",
    "sg:postcode":"91472",
    "sg:province":"Bayern",
    "wof:name":"H. Haag",
    "wof:placetype":"venue"
},
  "geometry": {"coordinates":[10.4811105728,49.5301322937],"type":"Point"}
}