{
  "type": "Feature",
  "properties": {
    "iso:country":"DE",
    "sg:address":"Rheinstr. 57",
    "sg:city":"Berlin",
    "sg:phone":"+49 30/8527069",
    "sg:postcode":"12159",
    "sg:province":"Berlin",
    "wof:name":"Eiscafe Michael Vietzke",
    "wof:placetype":"venue"
},
  "geometry": {"coordinates":[13.333689,52.469547],"type":"Point"}
}