{
  "type": "Feature",
  "properties": {
    "iso:country":"DE",
    "sg:address":"Flinzstr. 39",
    "sg:city":"Bautzen",
    "sg:phone":"+49 3591/45503",
    "sg:postcode":"02625",
    "sg:province":"Sachsen",
    "wof:name":"Kinderbekleidung Sachsen Kids",
    "wof:placetype":"venue"
},
  "geometry": {"coordinates":[14.4366540909,51.1903419495],"type":"Point"}
}