{
  "type": "Feature",
  "properties": {
    "iso:country":"DE",
    "sg:address":"Am Wasserturm 10",
    "sg:city":"Malschwitz",
    "sg:phone":"+49 35932/30570",
    "sg:postcode":"02694",
    "sg:province":"Sachsen",
    "wof:name":"Baugesch\u00e4ft Pursche Gmbh",
    "wof:placetype":"venue"
},
  "geometry": {"coordinates":[14.5953807831,51.2256507874],"type":"Point"}
}