{
  "type": "Feature",
  "properties": {
    "iso:country":"DE",
    "sg:address":"Heppacher Str. 16",
    "sg:city":"Korb",
    "sg:phone":"+49 7151/32977",
    "sg:postcode":"71404",
    "sg:province":"Baden-W\u00fcrttemberg",
    "wof:name":"Edith K. Metzger Heilpraktikerin",
    "wof:placetype":"venue"
},
  "geometry": {"coordinates":[9.3619565964,48.8431663513],"type":"Point"}
}