{
  "type": "Feature",
  "properties": {
    "iso:country":"DE",
    "sg:address":"Mittelfangweg 2",
    "sg:city":"Nieb\u00fcll",
    "sg:phone":"+49 4661/20358",
    "sg:postcode":"25899",
    "sg:province":"Schleswig-Holstein",
    "wof:name":"Marias Heimtierbedarf",
    "wof:placetype":"venue"
},
  "geometry": {"coordinates":[8.826905,54.784706],"type":"Point"}
}