{
  "type": "Feature",
  "properties": {
    "iso:country":"DE",
    "sg:address":"Schlo\u00dfstr. 11",
    "sg:city":"Urbach",
    "sg:phone":"+49 7181/81384",
    "sg:postcode":"73660",
    "sg:province":"Baden-W\u00fcrttemberg",
    "wof:name":"Friedrich Mehl",
    "wof:placetype":"venue"
},
  "geometry": {"coordinates":[9.575512886,48.8180847168],"type":"Point"}
}