{
  "type": "Feature",
  "properties": {
    "iso:country":"DE",
    "sg:address":"Possenhofener Str. 25",
    "sg:city":"Starnberg",
    "sg:phone":"+49 8151/16057",
    "sg:postcode":"82319",
    "sg:province":"Bayern",
    "wof:name":"Kinderspiel Gmbh",
    "wof:placetype":"venue"
},
  "geometry": {"coordinates":[11.3377504349,47.9921798706],"type":"Point"}
}