{
  "type": "Feature",
  "properties": {
    "iso:country":"DE",
    "sg:address":"Traarer Str. 57",
    "sg:city":"Krefeld",
    "sg:phone":"+49 2151/43815",
    "sg:postcode":"47829",
    "sg:province":"Nordrhein-Westfalen",
    "wof:name":"Wolfgang St\u00e4hler",
    "wof:placetype":"venue"
},
  "geometry": {"coordinates":[6.6382040977,51.3561401367],"type":"Point"}
}