{
  "type": "Feature",
  "properties": {
    "iso:country":"DE",
    "sg:address":"Marienstr. 47",
    "sg:city":"F\u00fcrth",
    "sg:phone":"+49 911/771697",
    "sg:postcode":"90762",
    "sg:province":"Bayern",
    "wof:name":"C. Stockert & Sohn",
    "wof:placetype":"venue"
},
  "geometry": {"coordinates":[10.9828453064,49.4742469788],"type":"Point"}
}