{
  "type": "Feature",
  "properties": {
    "iso:country":"DE",
    "sg:address":"Kaiserstr. 36",
    "sg:city":"Rastatt",
    "sg:phone":"+49 7222/33088",
    "sg:postcode":"76437",
    "sg:province":"Baden-W\u00fcrttemberg",
    "wof:name":"Hasso Schmidt-schmiedebach Und Michael Rauch",
    "wof:placetype":"venue"
},
  "geometry": {"coordinates":[8.2024707794,48.8581809998],"type":"Point"}
}