{
  "type": "Feature",
  "properties": {
    "iso:country":"DE",
    "sg:address":"Poppenb\u00fctteler Str. 180",
    "sg:city":"Norderstedt",
    "sg:phone":"+49 40/5246808",
    "sg:postcode":"22851",
    "sg:province":"Schleswig-Holstein",
    "wof:name":"D\u00f6rthe Hannig Heilpraktikerin",
    "wof:placetype":"venue"
},
  "geometry": {"coordinates":[10.0279550552,53.6936225891],"type":"Point"}
}