{
  "type": "Feature",
  "properties": {
    "iso:country":"DE",
    "sg:address":"Bahnhofstr. 48",
    "sg:city":"Speicher",
    "sg:phone":"+49 6562/3304",
    "sg:postcode":"54662",
    "sg:province":"Rheinland-Pfalz",
    "wof:name":"Eurospar",
    "wof:placetype":"venue"
},
  "geometry": {"coordinates":[6.6331758499,49.9345779419],"type":"Point"}
}