{
  "type": "Feature",
  "properties": {
    "iso:country":"DE",
    "sg:address":"Genfer Str. 7",
    "sg:city":"Frankfurt",
    "sg:phone":"+49 4969/5078900",
    "sg:postcode":"60437",
    "sg:province":"Hessen",
    "wof:name":"Greatlink Electronics Germany Gmbh",
    "wof:placetype":"venue"
},
  "geometry": {"coordinates":[8.659049,50.193157],"type":"Point"}
}