{
  "type": "Feature",
  "properties": {
    "iso:country":"DE",
    "sg:address":"M\u00f6rfelder Str. 97",
    "sg:city":"Kelsterbach",
    "sg:phone":"+49 6107/2051",
    "sg:postcode":"65451",
    "sg:province":"Hessen",
    "wof:name":"Hubertus Und D\u00f6nges Rechtsanw\u00e4lte Und Notare",
    "wof:placetype":"venue"
},
  "geometry": {"coordinates":[8.5382032394,50.0574226379],"type":"Point"}
}