{
  "type": "Feature",
  "properties": {
    "iso:country":"DE",
    "sg:address":"Pfarrer-Krapf-Str. 14",
    "sg:city":"Staffelstein",
    "sg:phone":"+49 9573/6442",
    "sg:postcode":"96231",
    "sg:province":"Bayern",
    "wof:name":"Josef Tremel",
    "wof:placetype":"venue"
},
  "geometry": {"coordinates":[11.063837,50.086533],"type":"Point"}
}