{
  "type": "Feature",
  "properties": {
    "iso:country":"DE",
    "sg:address":"Gartenstr. 1",
    "sg:city":"Sta\u00dffurt",
    "sg:phone":"+49 3925/302014",
    "sg:postcode":"39418",
    "sg:province":"Sachsen-Anhalt",
    "wof:name":"G. M\u00fcller",
    "wof:placetype":"venue"
},
  "geometry": {"coordinates":[11.5891475677,51.8516426086],"type":"Point"}
}