{
  "type": "Feature",
  "properties": {
    "iso:country":"DE",
    "sg:address":"Lindhorster Weg 13 B",
    "sg:city":"Wolmirstedt",
    "sg:phone":"+49 39201/29408",
    "sg:postcode":"39326",
    "sg:province":"Sachsen-Anhalt",
    "wof:name":"Bauunternehmen Rainer Gro\u00df Gmbh",
    "wof:placetype":"venue"
},
  "geometry": {"coordinates":[11.6172475815,52.2545166016],"type":"Point"}
}