{
  "type": "Feature",
  "properties": {
    "iso:country":"DE",
    "sg:address":"Zur Alten Eiche 247",
    "sg:city":"Bad Colberg-Heldburg",
    "sg:phone":"+49 36871/20650",
    "sg:postcode":"98663",
    "sg:province":"Th\u00fcringen",
    "wof:name":"I. B\u00e4hring",
    "wof:placetype":"venue"
},
  "geometry": {"coordinates":[10.7327756882,50.2860107422],"type":"Point"}
}