{
  "type": "Feature",
  "properties": {
    "iso:country":"DE",
    "sg:address":"Kirchweg 10",
    "sg:city":"Enzkl\u00f6sterle",
    "sg:phone":"+49 7085/1435",
    "sg:postcode":"75337",
    "sg:province":"Baden-W\u00fcrttemberg",
    "wof:name":"Kloster-keller",
    "wof:placetype":"venue"
},
  "geometry": {"coordinates":[8.4696960449,48.667175293],"type":"Point"}
}