{
  "type": "Feature",
  "properties": {
    "iso:country":"DE",
    "sg:address":"Ahornstr. 31",
    "sg:city":"Stuttgart",
    "sg:phone":"+49 711/766282",
    "sg:postcode":"70597",
    "sg:province":"Baden-W\u00fcrttemberg",
    "wof:name":"Antiquariat N. Wei\u00dfert Kg",
    "wof:placetype":"venue"
},
  "geometry": {"coordinates":[9.182202,48.751095],"type":"Point"}
}