{
  "type": "Feature",
  "properties": {
    "iso:country":"DE",
    "sg:address":"Oberndorfer Str.",
    "sg:city":"Hungen",
    "sg:phone":"+49 6402/7379",
    "sg:postcode":"35410",
    "sg:province":"Hessen",
    "wof:name":"Ev. Pfarramt Rodheim",
    "wof:placetype":"venue"
},
  "geometry": {"coordinates":[8.9412164688,50.4517326355],"type":"Point"}
}