{
  "type": "Feature",
  "properties": {
    "iso:country":"DE",
    "sg:address":"Falltorstr. 9",
    "sg:city":"Linden",
    "sg:phone":"+49 6403/2795",
    "sg:postcode":"35440",
    "sg:province":"Hessen",
    "wof:name":"Wilhelm Wagner",
    "wof:placetype":"venue"
},
  "geometry": {"coordinates":[8.646997,50.531326],"type":"Point"}
}