{
  "type": "Feature",
  "properties": {
    "iso:country":"DE",
    "sg:address":"Zollenspieker Hauptdeich 66",
    "sg:city":"Hamburg",
    "sg:phone":"+49 40/7230486",
    "sg:postcode":"21037",
    "sg:province":"Hamburg",
    "wof:name":"Helmut Von Hacht",
    "wof:placetype":"venue"
},
  "geometry": {"coordinates":[10.19362,53.403702],"type":"Point"}
}