{
  "type": "Feature",
  "properties": {
    "iso:country":"DE",
    "sg:address":"Nailaer Str. 6",
    "sg:city":"Selbitz",
    "sg:phone":"+49 9280/392",
    "sg:postcode":"95152",
    "sg:province":"Bayern",
    "wof:name":"Dr. Walter K\u00f6cher Gmbh & Co. Kg",
    "wof:placetype":"venue"
},
  "geometry": {"coordinates":[11.7470598221,50.3157958984],"type":"Point"}
}