{
  "type": "Feature",
  "properties": {
    "iso:country":"DE",
    "sg:address":"Sydowstr. 21",
    "sg:city":"Dortmund",
    "sg:phone":"+49 231/16944",
    "sg:postcode":"44369",
    "sg:province":"Nordrhein-Westfalen",
    "wof:name":"Stuve",
    "wof:placetype":"venue"
},
  "geometry": {"coordinates":[7.3982081413,51.5243911743],"type":"Point"}
}