{
  "type": "Feature",
  "properties": {
    "iso:country":"DE",
    "sg:address":"Bahnhofstr. 6",
    "sg:city":"Leinefelde",
    "sg:phone":"+49 3605/502123",
    "sg:postcode":"37327",
    "sg:province":"Th\u00fcringen",
    "wof:name":"S. Funke",
    "wof:placetype":"venue"
},
  "geometry": {"coordinates":[10.3222913742,51.387550354],"type":"Point"}
}