{
  "type": "Feature",
  "properties": {
    "iso:country":"DE",
    "sg:address":"Hauptstr. 13",
    "sg:city":"Gauting",
    "sg:phone":"+49 89/8505676",
    "sg:postcode":"82131",
    "sg:province":"Bayern",
    "wof:name":"Karlheinz Lederer Party Charly",
    "wof:placetype":"venue"
},
  "geometry": {"coordinates":[11.324411,48.066067],"type":"Point"}
}