{
  "type": "Feature",
  "properties": {
    "iso:country":"DE",
    "sg:address":"Mecklenburgstr. 33",
    "sg:city":"Nordenham",
    "sg:phone":"+49 4731/4781",
    "sg:postcode":"26954",
    "sg:province":"Niedersachsen",
    "wof:name":"Nara Ingenieurtechnik Und Anlagenbau Gmbh",
    "wof:placetype":"venue"
},
  "geometry": {"coordinates":[8.469149,53.471748],"type":"Point"}
}