{
  "type": "Feature",
  "properties": {
    "iso:country":"DE",
    "sg:address":"H\u00f6llstr. 14",
    "sg:city":"Stockach",
    "sg:phone":"+49 7771/61007",
    "sg:postcode":"78333",
    "sg:province":"Baden-W\u00fcrttemberg",
    "wof:name":"Bacher Edelstahl- Verarbeitung Gmbh",
    "wof:placetype":"venue"
},
  "geometry": {"coordinates":[9.005939,47.856976],"type":"Point"}
}