{
  "type": "Feature",
  "properties": {
    "iso:country":"DE",
    "sg:address":"Neue Industriestr. 15",
    "sg:city":"Cuxhaven",
    "sg:phone":"+49 4947/2140920",
    "sg:postcode":"27472",
    "sg:province":"Niedersachsen",
    "wof:name":"Noehmer Metallbau Gmbh",
    "wof:placetype":"venue"
},
  "geometry": {"coordinates":[8.706556,53.848862],"type":"Point"}
}