{
  "type": "Feature",
  "properties": {
    "iso:country":"DE",
    "sg:address":"Lohfelder Str. 20",
    "sg:city":"Bad Honnef",
    "sg:postcode":"53604",
    "sg:province":"Nordrhein-Westfalen",
    "wof:name":"Ggv Beteiligungs Gmbh",
    "wof:placetype":"venue"
},
  "geometry": {"coordinates":[7.216004,50.63245],"type":"Point"}
}