{
  "type": "Feature",
  "properties": {
    "iso:country":"DE",
    "sg:address":"Eschenrath 49",
    "sg:city":"Schwalmtal",
    "sg:phone":"+49 2163/47179",
    "sg:postcode":"41366",
    "sg:province":"Nordrhein-Westfalen",
    "wof:name":"J. Gierlings",
    "wof:placetype":"venue"
},
  "geometry": {"coordinates":[6.308311,51.212372],"type":"Point"}
}