{
  "type": "Feature",
  "properties": {
    "iso:country":"DE",
    "sg:address":"Menckesallee 13",
    "sg:city":"Hamburg",
    "sg:postcode":"22089",
    "sg:province":"Hamburg",
    "wof:name":"Avila Computer Handels- Gmbh",
    "wof:placetype":"venue"
},
  "geometry": {"coordinates":[10.059625,53.569195],"type":"Point"}
}