{
  "type": "Feature",
  "properties": {
    "iso:country":"DE",
    "sg:address":"Hauptstr. 31",
    "sg:city":"Wohratal",
    "sg:phone":"+49 6425/1081",
    "sg:postcode":"35288",
    "sg:province":"Hessen",
    "wof:name":"K. Leonh\u00e4user",
    "wof:placetype":"venue"
},
  "geometry": {"coordinates":[8.9485397339,50.9155731201],"type":"Point"}
}