{
  "type": "Feature",
  "properties": {
    "iso:country":"DE",
    "sg:address":"Heidturmweg 84",
    "sg:city":"Paderborn",
    "sg:phone":"+49 5251/1419627",
    "sg:postcode":"33100",
    "sg:province":"Nordrhein-Westfalen",
    "wof:name":"Malte Schlitzberger Rechtsanwalt",
    "wof:placetype":"venue"
},
  "geometry": {"coordinates":[8.7750740051,51.7449035645],"type":"Point"}
}