{
  "type": "Feature",
  "properties": {
    "iso:country":"DE",
    "sg:address":"Hirschberger Allee 3",
    "sg:city":"Ladenburg",
    "sg:phone":"+49 6203/12819",
    "sg:postcode":"68526",
    "sg:province":"Baden-W\u00fcrttemberg",
    "wof:name":"Ulrich Staudt Rechtsanwalt",
    "wof:placetype":"venue"
},
  "geometry": {"coordinates":[8.6218299866,49.4716682434],"type":"Point"}
}