{
  "type": "Feature",
  "properties": {
    "iso:country":"DE",
    "sg:address":"Leipziger Str. 176",
    "sg:city":"Zwickau",
    "sg:phone":"+49 375/8189880",
    "sg:postcode":"08058",
    "sg:province":"Sachsen",
    "wof:name":"Etec Industrieanlagen Gmbh",
    "wof:placetype":"venue"
},
  "geometry": {"coordinates":[12.489626,50.738625],"type":"Point"}
}