{
  "type": "Feature",
  "properties": {
    "iso:country":"DE",
    "sg:address":"Ittling 18",
    "sg:city":"Simmelsdorf",
    "sg:phone":"+49 9155/1823",
    "sg:postcode":"91245",
    "sg:province":"Bayern",
    "wof:name":"S. Hofmann Anlageberater",
    "wof:placetype":"venue"
},
  "geometry": {"coordinates":[11.3815803528,49.6353111267],"type":"Point"}
}