{
  "type": "Feature",
  "properties": {
    "iso:country":"DE",
    "sg:address":"Parkstr. 4",
    "sg:city":"Welzow",
    "sg:postcode":"03119",
    "sg:province":"Brandenburg",
    "wof:name":"Dr. Med. Rosemarie Stelzer",
    "wof:placetype":"venue"
},
  "geometry": {"coordinates":[14.170548,51.576668],"type":"Point"}
}