{
  "type": "Feature",
  "properties": {
    "iso:country":"DE",
    "sg:address":"Heidenheimer Str. 26",
    "sg:city":"Steinheim",
    "sg:phone":"+49 7323/919043",
    "sg:postcode":"89555",
    "sg:province":"Baden-W\u00fcrttemberg",
    "wof:name":"Ernst U. Martin Ziegler",
    "wof:placetype":"venue"
},
  "geometry": {"coordinates":[9.98883,48.67094],"type":"Point"}
}