{
  "type": "Feature",
  "properties": {
    "iso:country":"DE",
    "sg:address":"Gimbsheimer Str. 4-6",
    "sg:city":"Guntersblum",
    "sg:phone":"+49 6249/2444",
    "sg:postcode":"67583",
    "sg:province":"Rheinland-Pfalz",
    "wof:name":"R\u00f6sch-spies",
    "wof:placetype":"venue"
},
  "geometry": {"coordinates":[8.3499889374,49.7953453064],"type":"Point"}
}