{
  "type": "Feature",
  "properties": {
    "iso:country":"DE",
    "sg:address":"Arnst\u00e4dterstr. 28",
    "sg:city":"Erfurt",
    "sg:phone":"+49 361/669421",
    "sg:postcode":"99096",
    "sg:province":"Th\u00fcringen",
    "wof:name":"Commerzbank Ag",
    "wof:placetype":"venue"
},
  "geometry": {"coordinates":[11.032813,50.964996],"type":"Point"}
}