{
  "type": "Feature",
  "properties": {
    "iso:country":"DE",
    "sg:address":"Forstweg 1",
    "sg:city":"Rabenau",
    "sg:phone":"+49 351/649680",
    "sg:postcode":"01734",
    "sg:province":"Sachsen",
    "wof:name":"Nachtigall Bau- Und Deponietechnik Gmbh",
    "wof:placetype":"venue"
},
  "geometry": {"coordinates":[13.6490325928,50.9621696472],"type":"Point"}
}