{
  "type": "Feature",
  "properties": {
    "iso:country":"DE",
    "sg:address":"Rosenstr. 24",
    "sg:city":"Gschwend",
    "sg:phone":"+49 7972/6283",
    "sg:postcode":"74417",
    "sg:province":"Baden-W\u00fcrttemberg",
    "wof:name":"P. Henning",
    "wof:placetype":"venue"
},
  "geometry": {"coordinates":[9.73554,48.933571],"type":"Point"}
}