{
  "type": "Feature",
  "properties": {
    "iso:country":"DE",
    "sg:address":"Finkenweg 3",
    "sg:city":"Aichtal",
    "sg:phone":"+49 7127/50421",
    "sg:postcode":"72631",
    "sg:province":"Baden-W\u00fcrttemberg",
    "wof:name":"B. Roblitschka",
    "wof:placetype":"venue"
},
  "geometry": {"coordinates":[9.2057437897,48.6196784973],"type":"Point"}
}