{
  "type": "Feature",
  "properties": {
    "iso:country":"DE",
    "sg:address":"Lademannbogen 24a",
    "sg:city":"Hamburg",
    "sg:phone":"+49 40/5388191",
    "sg:postcode":"22339",
    "sg:province":"Hamburg",
    "wof:name":"Hans Steffens Graphischer Betrieb Gmbh",
    "wof:placetype":"venue"
},
  "geometry": {"coordinates":[10.0325708389,53.6443214417],"type":"Point"}
}