{
  "type": "Feature",
  "properties": {
    "iso:country":"DE",
    "sg:address":"Marienweg 44",
    "sg:city":"Steinfurt",
    "sg:phone":"+49 2552/2425",
    "sg:postcode":"48565",
    "sg:province":"Nordrhein-Westfalen",
    "wof:name":"Katholisches Pfarramt Maria Himmelfahrt",
    "wof:placetype":"venue"
},
  "geometry": {"coordinates":[7.3969740868,52.1145820618],"type":"Point"}
}