{
  "type": "Feature",
  "properties": {
    "iso:country":"DE",
    "sg:address":"Balduinstr. 6",
    "sg:city":"Zell",
    "sg:phone":"+49 6542/5447",
    "sg:postcode":"56856",
    "sg:province":"Rheinland-Pfalz",
    "wof:name":"Alte Winzerstube",
    "wof:placetype":"venue"
},
  "geometry": {"coordinates":[7.1822571754,50.0238113403],"type":"Point"}
}