{
  "type": "Feature",
  "properties": {
    "iso:country":"DE",
    "sg:address":"Leutersdorfer Str 29",
    "sg:city":"Seifhennersdorf",
    "sg:phone":"+49 3586/45080",
    "sg:postcode":"02782",
    "sg:province":"Sachsen",
    "wof:name":"Bergmann Gmbh",
    "wof:placetype":"venue"
},
  "geometry": {"coordinates":[14.622181,50.938526],"type":"Point"}
}