{
  "type": "Feature",
  "properties": {
    "iso:country":"DE",
    "sg:address":"Osternienburger Str. 1c",
    "sg:city":"Elsnigk",
    "sg:postcode":"06386",
    "sg:province":"Sachsen-Anhalt",
    "wof:name":"E. Czernik",
    "wof:placetype":"venue"
},
  "geometry": {"coordinates":[12.055354,51.791958],"type":"Point"}
}