{
  "type": "Feature",
  "properties": {
    "iso:country":"DE",
    "sg:address":"H\u00fchnerstr. 20",
    "sg:city":"Emmerich",
    "sg:phone":"+49 2822/70733",
    "sg:postcode":"46446",
    "sg:province":"Nordrhein-Westfalen",
    "wof:name":"J. Opdemom",
    "wof:placetype":"venue"
},
  "geometry": {"coordinates":[6.2478117943,51.8334503174],"type":"Point"}
}