{
  "type": "Feature",
  "properties": {
    "iso:country":"DE",
    "sg:address":"Kortumstr. 45",
    "sg:city":"Bochum",
    "sg:phone":"+49 234/961280",
    "sg:postcode":"44787",
    "sg:province":"Nordrhein-Westfalen",
    "wof:name":"Heinen-brillen Die Brillenstrasse",
    "wof:placetype":"venue"
},
  "geometry": {"coordinates":[7.2167711258,51.4789123535],"type":"Point"}
}