{
  "type": "Feature",
  "properties": {
    "iso:country":"DE",
    "sg:address":"Bahnstr. 20",
    "sg:city":"Bad Wilsnack",
    "sg:phone":"+49 38791/2676",
    "sg:postcode":"19336",
    "sg:province":"Brandenburg",
    "wof:name":"U. Littmann",
    "wof:placetype":"venue"
},
  "geometry": {"coordinates":[11.948551,52.95911],"type":"Point"}
}