{
  "type": "Feature",
  "properties": {
    "iso:country":"DE",
    "sg:address":"Am Stadtbruch 4",
    "sg:city":"Volkmarsen",
    "sg:phone":"+49 5693/7780",
    "sg:postcode":"34471",
    "sg:province":"Hessen",
    "wof:name":"Wiebusch-polymerbeton -technik-verwaltungs Gmbh",
    "wof:placetype":"venue"
},
  "geometry": {"coordinates":[9.1125020981,51.4070701599],"type":"Point"}
}