{
  "type": "Feature",
  "properties": {
    "iso:country":"DE",
    "sg:address":"Hau\u00dferstr. 124",
    "sg:city":"T\u00fcbingen",
    "sg:phone":"+49 7071/61592",
    "sg:postcode":"72076",
    "sg:province":"Baden-W\u00fcrttemberg",
    "wof:name":"Werner Breuninger Wirtschaftspr\u00fcfer",
    "wof:placetype":"venue"
},
  "geometry": {"coordinates":[9.0646572113,48.5380973816],"type":"Point"}
}