{
  "type": "Feature",
  "properties": {
    "iso:country":"DE",
    "sg:address":"Hirschstr. 8",
    "sg:city":"K\u00f6ngen",
    "sg:phone":"+49 7024/84914",
    "sg:postcode":"73257",
    "sg:province":"Baden-W\u00fcrttemberg",
    "wof:name":"Dieter Decker Drogerie",
    "wof:placetype":"venue"
},
  "geometry": {"coordinates":[9.362764,48.684734],"type":"Point"}
}