{
  "type": "Feature",
  "properties": {
    "iso:country":"DE",
    "sg:address":"Bl\u00fcthnerstr. 24",
    "sg:city":"Leipzig",
    "sg:phone":"+49 341/4411593",
    "sg:postcode":"04179",
    "sg:province":"Sachsen",
    "wof:name":"Lothar Otto",
    "wof:placetype":"venue"
},
  "geometry": {"coordinates":[12.308879,51.351398],"type":"Point"}
}