{
  "type": "Feature",
  "properties": {
    "iso:country":"DE",
    "sg:address":"Auerweg 19",
    "sg:city":"D\u00fcsseldorf",
    "sg:phone":"+49 211/753874",
    "sg:postcode":"40591",
    "sg:province":"Nordrhein-Westfalen",
    "wof:name":"G\u00fcnter Schmidt",
    "wof:placetype":"venue"
},
  "geometry": {"coordinates":[6.8073768616,51.1852798462],"type":"Point"}
}