{
  "type": "Feature",
  "properties": {
    "iso:country":"DE",
    "sg:address":"Friedhofstr. 2",
    "sg:city":"Titz",
    "sg:phone":"+49 2164/4184",
    "sg:postcode":"52445",
    "sg:province":"Nordrhein-Westfalen",
    "wof:name":"Jakob Wirtz",
    "wof:placetype":"venue"
},
  "geometry": {"coordinates":[6.451976,51.032734],"type":"Point"}
}