{
  "type": "Feature",
  "properties": {
    "iso:country":"DE",
    "sg:address":"Staufenstr. 9",
    "sg:city":"Bad Soden",
    "sg:phone":"+49 6174/4226",
    "sg:postcode":"65812",
    "sg:province":"Hessen",
    "wof:name":"J\u00fcrgen Kruck",
    "wof:placetype":"venue"
},
  "geometry": {"coordinates":[8.4723997116,50.1555747986],"type":"Point"}
}