{
  "type": "Feature",
  "properties": {
    "iso:country":"DE",
    "sg:address":"Masch 2 a",
    "sg:city":"Borgholzhausen",
    "sg:phone":"+49 5425/1633",
    "sg:postcode":"33829",
    "sg:province":"Nordrhein-Westfalen",
    "wof:name":"Freibad Borgholzhausen",
    "wof:placetype":"venue"
},
  "geometry": {"coordinates":[8.3046598434,52.1028556824],"type":"Point"}
}