{
  "type": "Feature",
  "properties": {
    "iso:country":"DE",
    "sg:address":"Auf den Porten 12",
    "sg:city":"Dortmund",
    "sg:phone":"+49 231/467840",
    "sg:postcode":"44265",
    "sg:province":"Nordrhein-Westfalen",
    "wof:name":"Andreas Neuhoff",
    "wof:placetype":"venue"
},
  "geometry": {"coordinates":[7.496102,51.466747],"type":"Point"}
}