{
  "type": "Feature",
  "properties": {
    "iso:country":"DE",
    "sg:address":"Robert-Bosch-Str 31",
    "sg:city":"Lindau",
    "sg:phone":"+49 8382/78048",
    "sg:postcode":"88131",
    "sg:province":"Bayern",
    "wof:name":"Schuster-chemie Gmbh & Co Kg",
    "wof:placetype":"venue"
},
  "geometry": {"coordinates":[9.663177,47.572323],"type":"Point"}
}