{
  "type": "Feature",
  "properties": {
    "iso:country":"DE",
    "sg:address":"Zu den Wiesen 16",
    "sg:city":"K\u00f6ln",
    "sg:phone":"+49 2203/962025",
    "sg:postcode":"51147",
    "sg:province":"Nordrhein-Westfalen",
    "wof:name":"Frederic M",
    "wof:placetype":"venue"
},
  "geometry": {"coordinates":[7.10164,50.850613],"type":"Point"}
}