{
  "type": "Feature",
  "properties": {
    "iso:country":"DE",
    "sg:address":"Fabrikstr. 13",
    "sg:city":"Brand-Erbisdorf",
    "sg:phone":"+49 37322/40107",
    "sg:postcode":"09618",
    "sg:province":"Sachsen",
    "wof:name":"Eisa - Eiprodukte Gmbh",
    "wof:placetype":"venue"
},
  "geometry": {"coordinates":[13.3269968033,50.8565979004],"type":"Point"}
}