{
  "type": "Feature",
  "properties": {
    "iso:country":"DE",
    "sg:address":"L\u00fcptitzer Str. 24 c",
    "sg:city":"Wurzen",
    "sg:postcode":"04808",
    "sg:province":"Sachsen",
    "wof:name":"Michael & Dietze Bautenschutz Schacht- Und",
    "wof:placetype":"venue"
},
  "geometry": {"coordinates":[12.749501,51.376656],"type":"Point"}
}