{
  "type": "Feature",
  "properties": {
    "iso:country":"DE",
    "sg:address":"Im Pottaschwald 29",
    "sg:city":"St. Ingbert",
    "sg:phone":"+49 6894/4781",
    "sg:postcode":"66386",
    "sg:province":"Saarland",
    "wof:name":"Willi Steffen",
    "wof:placetype":"venue"
},
  "geometry": {"coordinates":[7.12728,49.272388],"type":"Point"}
}