{
  "type": "Feature",
  "properties": {
    "iso:country":"DE",
    "sg:address":"Radgasse 31",
    "sg:city":"Ulm",
    "sg:phone":"+49 731/23388",
    "sg:postcode":"89073",
    "sg:province":"Baden-W\u00fcrttemberg",
    "wof:name":"Sabo",
    "wof:placetype":"venue"
},
  "geometry": {"coordinates":[9.998793,48.400017],"type":"Point"}
}