{
  "type": "Feature",
  "properties": {
    "iso:country":"DE",
    "sg:address":"Nonnenwaldstr. 57",
    "sg:city":"Rottenburg",
    "sg:phone":"+49 7478/357",
    "sg:postcode":"72108",
    "sg:province":"Baden-W\u00fcrttemberg",
    "wof:name":"Anton Daub",
    "wof:placetype":"venue"
},
  "geometry": {"coordinates":[8.9190387726,48.4158782959],"type":"Point"}
}