{
  "type": "Feature",
  "properties": {
    "iso:country":"DE",
    "sg:address":"Scharnweberstr. 100",
    "sg:city":"Berlin",
    "sg:phone":"+49 30/4178800",
    "sg:postcode":"13405",
    "sg:province":"Berlin",
    "wof:name":"Gfa Insurance Service Gmbh",
    "wof:placetype":"venue"
},
  "geometry": {"coordinates":[13.3170957565,52.5665016174],"type":"Point"}
}