{
  "type": "Feature",
  "properties": {
    "iso:country":"DE",
    "sg:address":"Dorfstra\u00dfe 6",
    "sg:city":"Dresden",
    "sg:postcode":"01309",
    "sg:province":"Sachsen",
    "wof:name":"Dresdner-index",
    "wof:placetype":"venue"
},
  "geometry": {"coordinates":[13.792219,51.047649],"type":"Point"}
}