{
  "type": "Feature",
  "properties": {
    "iso:country":"DE",
    "sg:address":"B\u00fcnder Str. 72",
    "sg:city":"R\u00f6dinghausen",
    "sg:phone":"+49 5746/8151",
    "sg:postcode":"32289",
    "sg:province":"Nordrhein-Westfalen",
    "wof:name":"Wilhelm Ebke",
    "wof:placetype":"venue"
},
  "geometry": {"coordinates":[8.485976,52.249866],"type":"Point"}
}