{
  "type": "Feature",
  "properties": {
    "iso:country":"DE",
    "sg:address":"Eggersten Ring 28",
    "sg:city":"Kreuztal",
    "sg:postcode":"57223",
    "sg:province":"Nordrhein-Westfalen",
    "wof:name":"\u00d6zgen Gmbh",
    "wof:placetype":"venue"
},
  "geometry": {"coordinates":[7.9875440598,50.971622467],"type":"Point"}
}