{
  "type": "Feature",
  "properties": {
    "iso:country":"DE",
    "sg:address":"Reideburger Str. 1",
    "sg:city":"Halle",
    "sg:phone":"+49 345/5601002",
    "sg:postcode":"06116",
    "sg:province":"Sachsen-Anhalt",
    "wof:name":"Holzfachm\u00e4rkte Hollywood Gmbh",
    "wof:placetype":"venue"
},
  "geometry": {"coordinates":[12.00909,51.490208],"type":"Point"}
}