{
  "type": "Feature",
  "properties": {
    "iso:country":"DE",
    "sg:address":"Borchersweg 150",
    "sg:city":"Hatten",
    "sg:phone":"+49 4481/8727",
    "sg:postcode":"26209",
    "sg:province":"Niedersachsen",
    "wof:name":"Hotel Ripken",
    "wof:placetype":"venue"
},
  "geometry": {"coordinates":[8.2809934616,53.0658416748],"type":"Point"}
}