{
  "type": "Feature",
  "properties": {
    "iso:country":"DE",
    "sg:address":"Weststr. 21",
    "sg:city":"Naila",
    "sg:phone":"+49 9282/8361",
    "sg:postcode":"95119",
    "sg:province":"Bayern",
    "wof:name":"Helmut Bodenschatz Steuerberater",
    "wof:placetype":"venue"
},
  "geometry": {"coordinates":[11.7056446075,50.3283843994],"type":"Point"}
}