{
  "type": "Feature",
  "properties": {
    "iso:country":"DE",
    "sg:address":"Ober H\u00f6vel 1",
    "sg:city":"Halver",
    "sg:phone":"+49 2353/2578",
    "sg:postcode":"58553",
    "sg:province":"Nordrhein-Westfalen",
    "wof:name":"Peter Pastoors",
    "wof:placetype":"venue"
},
  "geometry": {"coordinates":[7.472251,51.18668],"type":"Point"}
}