{
  "type": "Feature",
  "properties": {
    "iso:country":"DE",
    "sg:address":"Gelnh\u00e4user Str. 35",
    "sg:city":"Langenselbold",
    "sg:phone":"+49 6184/952278",
    "sg:postcode":"63505",
    "sg:province":"Hessen",
    "wof:name":"Schwarz Dietrich Und Hirt Rechtsanw\u00e4lte",
    "wof:placetype":"venue"
},
  "geometry": {"coordinates":[9.0501384735,50.1764602661],"type":"Point"}
}