{
  "type": "Feature",
  "properties": {
    "iso:country":"DE",
    "sg:address":"Zehntscheuergasse 1",
    "sg:city":"Fridingen",
    "sg:phone":"+49 4974/63366",
    "sg:postcode":"78567",
    "sg:province":"Baden-W\u00fcrttemberg",
    "wof:name":"Volksbank Tuttlingen Eg",
    "wof:placetype":"venue"
},
  "geometry": {"coordinates":[8.931855,48.020279],"type":"Point"}
}