{
  "type": "Feature",
  "properties": {
    "iso:country":"DE",
    "sg:address":"Waldstr. 3",
    "sg:city":"Pfeffenhausen",
    "sg:phone":"+49 8782/1400",
    "sg:postcode":"84076",
    "sg:province":"Bayern",
    "wof:name":"Oberhofer & Partner Wege- Tief- Und Kabelbau Gmbh",
    "wof:placetype":"venue"
},
  "geometry": {"coordinates":[11.9453687668,48.7066993713],"type":"Point"}
}