{
  "type": "Feature",
  "properties": {
    "iso:country":"DE",
    "sg:address":"Ginsterweg 13",
    "sg:city":"Swisttal",
    "sg:phone":"+49 2226/912427",
    "sg:postcode":"53913",
    "sg:province":"Nordrhein-Westfalen",
    "wof:name":"E. Sch\u00f6n",
    "wof:placetype":"venue"
},
  "geometry": {"coordinates":[6.9207010269,50.669216156],"type":"Point"}
}