{
  "type": "Feature",
  "properties": {
    "iso:country":"DE",
    "sg:address":"Goethestr. 1",
    "sg:city":"Wechmar",
    "sg:phone":"+49 36256/80412",
    "sg:postcode":"99869",
    "sg:province":"Th\u00fcringen",
    "wof:name":"Erich H\u00e4hner",
    "wof:placetype":"venue"
},
  "geometry": {"coordinates":[10.7793092728,50.8941879272],"type":"Point"}
}