{
  "type": "Feature",
  "properties": {
    "iso:country":"DE",
    "sg:address":"Nordstr. 45",
    "sg:city":"D\u00fcsseldorf",
    "sg:phone":"+49 211/499410",
    "sg:postcode":"40477",
    "sg:province":"Nordrhein-Westfalen",
    "wof:name":"Fielmann Derendorf Fielmann Gmbh & Co.",
    "wof:placetype":"venue"
},
  "geometry": {"coordinates":[6.779603,51.237576],"type":"Point"}
}