{
  "type": "Feature",
  "properties": {
    "iso:country":"DE",
    "sg:address":"Staufenstr. 6",
    "sg:city":"Waging",
    "sg:postcode":"83329",
    "sg:province":"Bayern",
    "wof:name":"Multi-stores E. K.",
    "wof:placetype":"venue"
},
  "geometry": {"coordinates":[12.738676,47.934334],"type":"Point"}
}