{
  "type": "Feature",
  "properties": {
    "iso:country":"DE",
    "sg:address":"Rudolf-Breitscheid-Str. 3 a",
    "sg:city":"Letschin",
    "sg:phone":"+49 33475/453",
    "sg:postcode":"15324",
    "sg:province":"Brandenburg",
    "wof:name":"Gemeinn\u00fctzige Ges. Altersge- Rechtes Und Soziales Wohnen",
    "wof:placetype":"venue"
},
  "geometry": {"coordinates":[14.3611297607,52.6450042725],"type":"Point"}
}