{
  "type": "Feature",
  "properties": {
    "iso:country":"DE",
    "sg:address":"Urlading 29",
    "sg:city":"Schaufling",
    "sg:postcode":"94571",
    "sg:province":"Bayern",
    "wof:name":"Anpfiff",
    "wof:placetype":"venue"
},
  "geometry": {"coordinates":[13.078546,48.833618],"type":"Point"}
}