{
  "type": "Feature",
  "properties": {
    "iso:country":"DE",
    "sg:address":"Rudloffstr 68",
    "sg:city":"Bremerhaven",
    "sg:phone":"+49 471/952080",
    "sg:postcode":"27568",
    "sg:province":"Bremen",
    "wof:name":"Kraeft Gmbh Systemtechnik",
    "wof:placetype":"venue"
},
  "geometry": {"coordinates":[8.5693845749,53.5529594421],"type":"Point"}
}