{
  "type": "Feature",
  "properties": {
    "iso:country":"DE",
    "sg:address":"Bahnhofstra\u00dfe 19",
    "sg:city":"Buxtehude",
    "sg:phone":"+49 4161/53862",
    "sg:postcode":"21614",
    "sg:province":"Niedersachsen",
    "wof:name":"Techno-treuhand Gmbh",
    "wof:placetype":"venue"
},
  "geometry": {"coordinates":[9.6940279007,53.4732551575],"type":"Point"}
}