{
  "type": "Feature",
  "properties": {
    "iso:country":"DE",
    "sg:address":"K\u00f6tzschenbroder Str. 1",
    "sg:city":"Dresden",
    "sg:phone":"+49 351/852920",
    "sg:postcode":"01139",
    "sg:province":"Sachsen",
    "wof:name":"Hausbr\u00e4u Im Ballhaus Watzke Gmbh",
    "wof:placetype":"venue"
},
  "geometry": {"coordinates":[13.715283,51.077393],"type":"Point"}
}