{
  "type": "Feature",
  "properties": {
    "iso:country":"DE",
    "sg:address":"Gro\u00dfe Gosenstr. 4",
    "sg:city":"Halle",
    "sg:phone":"+49 345/5224245",
    "sg:postcode":"06114",
    "sg:province":"Sachsen-Anhalt",
    "wof:name":"Kuhn Haus Gmbh",
    "wof:placetype":"venue"
},
  "geometry": {"coordinates":[11.956852,51.498089],"type":"Point"}
}