{
  "type": "Feature",
  "properties": {
    "iso:country":"DE",
    "sg:address":"Freihofstr 26",
    "sg:city":"G\u00f6ppingen",
    "sg:phone":"+49 7161/812022",
    "sg:postcode":"73033",
    "sg:province":"Baden-W\u00fcrttemberg",
    "wof:name":"Max M\u00fcnnich & Co",
    "wof:placetype":"venue"
},
  "geometry": {"coordinates":[9.6526155472,48.7031135559],"type":"Point"}
}