{
  "type": "Feature",
  "properties": {
    "iso:country":"DE",
    "sg:address":"Hembecker Talstr. 61",
    "sg:city":"Ennepetal",
    "sg:phone":"+49 2333/70381",
    "sg:postcode":"58256",
    "sg:province":"Nordrhein-Westfalen",
    "wof:name":"Karl S\u00f6hn Verwaltungs Gmbh",
    "wof:placetype":"venue"
},
  "geometry": {"coordinates":[7.3244,51.302731],"type":"Point"}
}