{
  "type": "Feature",
  "properties": {
    "iso:country":"DE",
    "sg:address":"An der Saalburg 6",
    "sg:city":"Mayen",
    "sg:phone":"+49 2651/5734",
    "sg:postcode":"56727",
    "sg:province":"Rheinland-Pfalz",
    "wof:name":"Mgv Concordia Mayen Hermann Zeus",
    "wof:placetype":"venue"
},
  "geometry": {"coordinates":[7.2184319496,50.3242874146],"type":"Point"}
}