{
  "type": "Feature",
  "properties": {
    "iso:country":"DE",
    "sg:address":"Steinendorfer Str. 27",
    "sg:city":"Solingen",
    "sg:phone":"+49 212/66041",
    "sg:postcode":"42699",
    "sg:province":"Nordrhein-Westfalen",
    "wof:name":"Omni Med Hammacher Gmbh",
    "wof:placetype":"venue"
},
  "geometry": {"coordinates":[7.019664,51.14505],"type":"Point"}
}