{
  "type": "Feature",
  "properties": {
    "iso:country":"DE",
    "sg:address":"Am Bachmann 11",
    "sg:city":"Breuna",
    "sg:phone":"+49 5693/98790",
    "sg:postcode":"34479",
    "sg:province":"Hessen",
    "wof:name":"Wvg Industrie- Und Schalttechnik Gmbh",
    "wof:placetype":"venue"
},
  "geometry": {"coordinates":[9.1740646362,51.4139938354],"type":"Point"}
}