{
  "type": "Feature",
  "properties": {
    "iso:country":"DE",
    "sg:address":"Alte Heerstr. 6",
    "sg:city":"Kevelaer",
    "sg:phone":"+49 2832/4317",
    "sg:postcode":"47623",
    "sg:province":"Nordrhein-Westfalen",
    "wof:name":"Wilfried Binn",
    "wof:placetype":"venue"
},
  "geometry": {"coordinates":[6.2524490356,51.5776405334],"type":"Point"}
}