{
  "type": "Feature",
  "properties": {
    "iso:country":"DE",
    "sg:address":"Gubitzstr. 45a",
    "sg:city":"Berlin",
    "sg:phone":"+49 30/4245676",
    "sg:postcode":"10409",
    "sg:province":"Berlin",
    "wof:name":"Joachim Wasmund Ingenieur",
    "wof:placetype":"venue"
},
  "geometry": {"coordinates":[13.4331130981,52.5450172424],"type":"Point"}
}