{
  "type": "Feature",
  "properties": {
    "iso:country":"DE",
    "sg:address":"Bahnhofstr.",
    "sg:city":"Zittau",
    "sg:phone":"+49 3583/510300",
    "sg:postcode":"02763",
    "sg:province":"Sachsen",
    "wof:name":"Christian Aust",
    "wof:placetype":"venue"
},
  "geometry": {"coordinates":[14.805476,50.900043],"type":"Point"}
}