{
  "type": "Feature",
  "properties": {
    "iso:country":"DE",
    "sg:address":"Woldsenweg 2",
    "sg:city":"Hamburg",
    "sg:phone":"+49 40/474065",
    "sg:postcode":"20249",
    "sg:province":"Hamburg",
    "wof:name":"Friedrich B\u00f6hnert Rechtsanwalt",
    "wof:placetype":"venue"
},
  "geometry": {"coordinates":[9.9860773087,53.5879936218],"type":"Point"}
}