{
  "type": "Feature",
  "properties": {
    "iso:country":"DE",
    "sg:address":"Franklinstr. 42-44",
    "sg:city":"D\u00fcsseldorf",
    "sg:phone":"+49 211/484090",
    "sg:postcode":"40479",
    "sg:province":"Nordrhein-Westfalen",
    "wof:name":"Dr. B\u00f6hm-dr. Philippiak Gmbh",
    "wof:placetype":"venue"
},
  "geometry": {"coordinates":[6.7916359901,51.236125946],"type":"Point"}
}