{
  "type": "Feature",
  "properties": {
    "iso:country":"DE",
    "sg:address":"Kramgasse 6",
    "sg:city":"Andernach",
    "sg:phone":"+49 2632/45422",
    "sg:postcode":"56626",
    "sg:province":"Rheinland-Pfalz",
    "wof:name":"Jeans Reiff Gmbh",
    "wof:placetype":"venue"
},
  "geometry": {"coordinates":[7.399960041,50.4393615723],"type":"Point"}
}