{
  "type": "Feature",
  "properties": {
    "iso:country":"DE",
    "sg:address":"Mathildenstr. 17",
    "sg:city":"F\u00fcrth",
    "sg:phone":"+49 911/7418360",
    "sg:postcode":"90762",
    "sg:province":"Bayern",
    "wof:name":"D. Schwarz",
    "wof:placetype":"venue"
},
  "geometry": {"coordinates":[10.9848642349,49.4748764038],"type":"Point"}
}