{
  "type": "Feature",
  "properties": {
    "iso:country":"DE",
    "sg:address":"Kemminghauser Str. 37",
    "sg:city":"Dortmund",
    "sg:phone":"+49 231/851007",
    "sg:postcode":"44339",
    "sg:province":"Nordrhein-Westfalen",
    "wof:name":"R. Aust",
    "wof:placetype":"venue"
},
  "geometry": {"coordinates":[7.4883599281,51.5599708557],"type":"Point"}
}