{
  "type": "Feature",
  "properties": {
    "iso:country":"DE",
    "sg:address":"Wiesenstr. 10",
    "sg:city":"Sulzbach",
    "sg:phone":"+49 6196/574107",
    "sg:postcode":"65843",
    "sg:province":"Hessen",
    "wof:name":"Manfred Weller",
    "wof:placetype":"venue"
},
  "geometry": {"coordinates":[8.532768,50.128456],"type":"Point"}
}