{
  "type": "Feature",
  "properties": {
    "iso:country":"DE",
    "sg:address":"Haidenholzstr. 62",
    "sg:city":"Stephanskirchen",
    "sg:phone":"+49 8036/9156",
    "sg:postcode":"83071",
    "sg:province":"Bayern",
    "wof:name":"Sb-gro\u00dfmarkt",
    "wof:placetype":"venue"
},
  "geometry": {"coordinates":[12.1759243011,47.8600959778],"type":"Point"}
}