{
  "type": "Feature",
  "properties": {
    "iso:country":"DE",
    "sg:address":"An der Grenzpappel 41",
    "sg:city":"Bremen",
    "sg:phone":"+49 421/435250",
    "sg:postcode":"28207",
    "sg:province":"Bremen",
    "wof:name":"Vario-service-bau Gmbh & Co. Kg",
    "wof:placetype":"venue"
},
  "geometry": {"coordinates":[8.881353,53.060017],"type":"Point"}
}