{
  "type": "Feature",
  "properties": {
    "iso:country":"DE",
    "sg:address":"Kreuzstr. 2",
    "sg:city":"Bonn",
    "sg:phone":"+49 228/4222293",
    "sg:postcode":"53225",
    "sg:province":"Nordrhein-Westfalen",
    "wof:name":"Restaurant Domklause",
    "wof:placetype":"venue"
},
  "geometry": {"coordinates":[7.123404026,50.7403030396],"type":"Point"}
}