{
  "type": "Feature",
  "properties": {
    "iso:country":"DE",
    "sg:address":"Erlenweg 14",
    "sg:city":"Karlsbad",
    "sg:phone":"+49 7202/93930",
    "sg:postcode":"76307",
    "sg:province":"Baden-W\u00fcrttemberg",
    "wof:name":"D&g-software Gmbh",
    "wof:placetype":"venue"
},
  "geometry": {"coordinates":[8.534784,48.917149],"type":"Point"}
}