{
  "type": "Feature",
  "properties": {
    "iso:country":"DE",
    "sg:address":"Altenfilsstr. 13",
    "sg:city":"Brilon",
    "sg:phone":"+49 2963/362",
    "sg:postcode":"59929",
    "sg:province":"Nordrhein-Westfalen",
    "wof:name":"Bernhard M\u00fchlenbein",
    "wof:placetype":"venue"
},
  "geometry": {"coordinates":[8.675228,51.40683],"type":"Point"}
}