{
  "type": "Feature",
  "properties": {
    "iso:country":"DE",
    "sg:address":"Dorfstr. 16",
    "sg:city":"Brandis",
    "sg:phone":"+49 35362/331",
    "sg:postcode":"04916",
    "sg:province":"Brandenburg",
    "wof:name":"Dieter Schn\u00fcrpel",
    "wof:placetype":"venue"
},
  "geometry": {"coordinates":[13.231134,51.727943],"type":"Point"}
}