{
  "type": "Feature",
  "properties": {
    "iso:country":"DE",
    "sg:address":"Hinterer Viehmarktweg 22a",
    "sg:city":"Ebersbach",
    "sg:phone":"+49 7163/6035",
    "sg:postcode":"73061",
    "sg:province":"Baden-W\u00fcrttemberg",
    "wof:name":"S. Wurmbauer",
    "wof:placetype":"venue"
},
  "geometry": {"coordinates":[9.527597,48.713867],"type":"Point"}
}