{
  "type": "Feature",
  "properties": {
    "iso:country":"DE",
    "sg:address":"Zei\u00dfelstr. 9",
    "sg:city":"Frankfurt",
    "sg:phone":"+49 69/5962899",
    "sg:postcode":"60318",
    "sg:province":"Hessen",
    "wof:name":"Dr. W. Spinner-ahnert Rechtsanwalt",
    "wof:placetype":"venue"
},
  "geometry": {"coordinates":[8.6908054352,50.1240386963],"type":"Point"}
}