{
  "type": "Feature",
  "properties": {
    "iso:country":"DE",
    "sg:address":"Hindemithstr. 11",
    "sg:city":"Kerpen",
    "sg:phone":"+49 2273/52495",
    "sg:postcode":"50170",
    "sg:province":"Nordrhein-Westfalen",
    "wof:name":"K. L\u00fcttgen Gmbh B\u00e4derbedarf-chemikalien",
    "wof:placetype":"venue"
},
  "geometry": {"coordinates":[6.665708065,50.9037017822],"type":"Point"}
}