{
  "type": "Feature",
  "properties": {
    "iso:country":"DE",
    "sg:address":"Giesenbachstr.7",
    "sg:city":"Siegen",
    "sg:phone":"+49 271",
    "sg:postcode":"57080",
    "sg:province":"Nordrhein-Westfalen",
    "wof:name":"Ihre Pr\u00e4senz Im Internet Mit Jung Webdesign",
    "wof:placetype":"venue"
},
  "geometry": {"coordinates":[8.030761,50.82766],"type":"Point"}
}