{
  "type": "Feature",
  "properties": {
    "iso:country":"DE",
    "sg:address":"Momsenstr. 8",
    "sg:city":"Langenhorn",
    "sg:phone":"+49 4672/1244",
    "sg:postcode":"25842",
    "sg:province":"Schleswig-Holstein",
    "wof:name":"Ferienhaus Wierzowiecki In Langenhorn",
    "wof:placetype":"venue"
},
  "geometry": {"coordinates":[8.96387,54.686012],"type":"Point"}
}