{
  "type": "Feature",
  "properties": {
    "iso:country":"DE",
    "sg:address":"Gr\u00fcner Weg 1",
    "sg:city":"Hennef",
    "sg:phone":"+49 2242/2643",
    "sg:postcode":"53773",
    "sg:province":"Nordrhein-Westfalen",
    "wof:name":"Hogaplan Hotel- Und Gastst\u00e4tteneinrichtungen",
    "wof:placetype":"venue"
},
  "geometry": {"coordinates":[7.265319,50.772335],"type":"Point"}
}