{
  "type": "Feature",
  "properties": {
    "iso:country":"DE",
    "sg:address":"Hauptstr. 56",
    "sg:city":"Fischerbach",
    "sg:phone":"+49 7832/67639",
    "sg:postcode":"77716",
    "sg:province":"Baden-W\u00fcrttemberg",
    "wof:name":"Wunibald Lehmann",
    "wof:placetype":"venue"
},
  "geometry": {"coordinates":[8.1177511215,48.2872657776],"type":"Point"}
}