{
  "type": "Feature",
  "properties": {
    "iso:country":"DE",
    "sg:address":"Salzufler Str. 104",
    "sg:city":"Bielefeld",
    "sg:phone":"+49 521/332860",
    "sg:postcode":"33719",
    "sg:province":"Nordrhein-Westfalen",
    "wof:name":"Karl-heinz Prante",
    "wof:placetype":"venue"
},
  "geometry": {"coordinates":[8.616798,52.028057],"type":"Point"}
}