{
  "type": "Feature",
  "properties": {
    "iso:country":"DE",
    "sg:address":"Friedrichstr. 23",
    "sg:city":"R\u00fcdesheim am Rhein",
    "sg:phone":"+49 6722/90480",
    "sg:postcode":"65385",
    "sg:province":"Hessen",
    "wof:name":"Frank-interconsulting Steuerberatungsgesellschaf Mbh",
    "wof:placetype":"venue"
},
  "geometry": {"coordinates":[7.9316248894,49.9814033508],"type":"Point"}
}