{
  "type": "Feature",
  "properties": {
    "iso:country":"DE",
    "sg:address":"Gro\u00dfsachsener Str.",
    "sg:city":"Hirschberg",
    "sg:phone":"+49 6201/54487",
    "sg:postcode":"69493",
    "sg:province":"Baden-W\u00fcrttemberg",
    "wof:name":"H. G\u00f6hrig",
    "wof:placetype":"venue"
},
  "geometry": {"coordinates":[8.6617145538,49.5031814575],"type":"Point"}
}