{
  "type": "Feature",
  "properties": {
    "iso:country":"DE",
    "sg:address":"Saarstr.",
    "sg:city":"Mainz",
    "sg:phone":"+49 6131/390",
    "sg:postcode":"55122",
    "sg:province":"Rheinland-Pfalz",
    "wof:name":"Anthropologisches Institut Bibliothek",
    "wof:placetype":"venue"
},
  "geometry": {"coordinates":[8.251911,49.997261],"type":"Point"}
}