{
  "type": "Feature",
  "properties": {
    "iso:country":"DE",
    "sg:address":"Weststr. 169",
    "sg:city":"Schkeuditz",
    "sg:postcode":"04435",
    "sg:province":"Sachsen",
    "wof:name":"Tischlerei Bittner Gmbh",
    "wof:placetype":"venue"
},
  "geometry": {"coordinates":[12.217655,51.397114],"type":"Point"}
}