{
  "type": "Feature",
  "properties": {
    "iso:country":"DE",
    "sg:address":"Spessartstr. 55",
    "sg:city":"Aschaffenburg",
    "sg:phone":"+49 6021/91684",
    "sg:postcode":"63743",
    "sg:province":"Bayern",
    "wof:name":"R. Hermann",
    "wof:placetype":"venue"
},
  "geometry": {"coordinates":[9.1536197662,49.9650192261],"type":"Point"}
}