{
  "type": "Feature",
  "properties": {
    "iso:country":"DE",
    "sg:address":"Bergstedter Kirchenstr. 2 c",
    "sg:city":"Hamburg",
    "sg:phone":"+49 40/6040223",
    "sg:postcode":"22395",
    "sg:province":"Hamburg",
    "wof:name":"Igap Ingenieurges. F\u00fcr Anlagen Und Pipelinetechnik Mbh",
    "wof:placetype":"venue"
},
  "geometry": {"coordinates":[10.1305475235,53.6719017029],"type":"Point"}
}