{
  "type": "Feature",
  "properties": {
    "iso:country":"DE",
    "sg:address":"Wilhelmstr. 4",
    "sg:city":"Ehlscheid",
    "sg:phone":"+49 2634/2309",
    "sg:postcode":"56581",
    "sg:province":"Rheinland-Pfalz",
    "wof:name":"G. Und J. Holstein Finanzberater",
    "wof:placetype":"venue"
},
  "geometry": {"coordinates":[7.4660758972,50.5143508911],"type":"Point"}
}