{
  "type": "Feature",
  "properties": {
    "iso:country":"DE",
    "sg:address":"Zwickauer Str. 116",
    "sg:city":"Chemnitz",
    "sg:phone":"+49 371/91260",
    "sg:postcode":"09112",
    "sg:province":"Sachsen",
    "wof:name":"Norman Tietze Steuerberater",
    "wof:placetype":"venue"
},
  "geometry": {"coordinates":[12.8990001678,50.8245391846],"type":"Point"}
}