{
  "type": "Feature",
  "properties": {
    "iso:country":"DE",
    "sg:address":"Obere Hauptstr. 42",
    "sg:city":"Au",
    "sg:phone":"+49 8752/9552",
    "sg:postcode":"84072",
    "sg:province":"Bayern",
    "wof:name":"Katrin Hirmer",
    "wof:placetype":"venue"
},
  "geometry": {"coordinates":[11.746933,48.55545],"type":"Point"}
}