{
  "type": "Feature",
  "properties": {
    "iso:country":"DE",
    "sg:address":"Goslarer Str. 109",
    "sg:city":"Stuttgart",
    "sg:phone":"+49 6081/67766",
    "sg:postcode":"70499",
    "sg:province":"Baden-W\u00fcrttemberg",
    "wof:name":"Dagmar G\u00fcldener Heilpraktikerin",
    "wof:placetype":"venue"
},
  "geometry": {"coordinates":[9.1264572144,48.8160667419],"type":"Point"}
}