{
  "type": "Feature",
  "properties": {
    "iso:country":"DE",
    "sg:address":"Am Tairnbacher Weg 6",
    "sg:city":"Dielheim",
    "sg:phone":"+49 6222/73400",
    "sg:postcode":"69234",
    "sg:province":"Baden-W\u00fcrttemberg",
    "wof:name":"Inform Bauen Und Wohnen Gmbh",
    "wof:placetype":"venue"
},
  "geometry": {"coordinates":[8.7425880432,49.2799797058],"type":"Point"}
}