{
  "type": "Feature",
  "properties": {
    "iso:country":"DE",
    "sg:address":"Vor dem Schulzentor 3",
    "sg:city":"Osterwieck",
    "sg:postcode":"38835",
    "sg:province":"Sachsen-Anhalt",
    "wof:name":"Rettig D. Gmbh",
    "wof:placetype":"venue"
},
  "geometry": {"coordinates":[10.703925,51.972652],"type":"Point"}
}