{
  "type": "Feature",
  "properties": {
    "iso:country":"DE",
    "sg:address":"Podbielskistr. 208",
    "sg:city":"Hannover",
    "sg:phone":"+49 511/690033",
    "sg:postcode":"30177",
    "sg:province":"Niedersachsen",
    "wof:name":"Atlanta Versicherungs- Und Wirtschaftsdienst",
    "wof:placetype":"venue"
},
  "geometry": {"coordinates":[9.7797498703,52.3995285034],"type":"Point"}
}