{
  "type": "Feature",
  "properties": {
    "iso:country":"DE",
    "sg:address":"Dornregt 6",
    "sg:city":"Minden",
    "sg:postcode":"32425",
    "sg:province":"Nordrhein-Westfalen",
    "wof:name":"Klinker-fix Fassadenbau Gmbh",
    "wof:placetype":"venue"
},
  "geometry": {"coordinates":[8.90851,52.307045],"type":"Point"}
}