{
  "type": "Feature",
  "properties": {
    "iso:country":"DE",
    "sg:address":"Ulrichsweg 1",
    "sg:city":"Langenneufnach",
    "sg:phone":"+49 8239/7146",
    "sg:postcode":"86863",
    "sg:province":"Bayern",
    "wof:name":"Elektro-kohle-k\u00f6ln Inh. H. Klever",
    "wof:placetype":"venue"
},
  "geometry": {"coordinates":[10.6082496643,48.2688217163],"type":"Point"}
}