{
  "type": "Feature",
  "properties": {
    "iso:country":"DE",
    "sg:address":"Auf dem R\u00f6mer 15",
    "sg:city":"Birkenfeld",
    "sg:phone":"+49 6782/3450",
    "sg:postcode":"55765",
    "sg:province":"Rheinland-Pfalz",
    "wof:name":"Klaus Dietz",
    "wof:placetype":"venue"
},
  "geometry": {"coordinates":[7.1669859886,49.6474380493],"type":"Point"}
}