{
  "type": "Feature",
  "properties": {
    "iso:country":"DE",
    "sg:address":"Zickzackweg 20",
    "sg:city":"Hamburg",
    "sg:phone":"+49 40/8801030",
    "sg:postcode":"22605",
    "sg:province":"Hamburg",
    "wof:name":"Traumhaus-design Jutta Tippner",
    "wof:placetype":"venue"
},
  "geometry": {"coordinates":[9.8873634338,53.5535583496],"type":"Point"}
}