{
  "type": "Feature",
  "properties": {
    "iso:country":"DE",
    "sg:address":"Schroppenstr. 8",
    "sg:city":"Dachau",
    "sg:phone":"+49 8131/21354",
    "sg:postcode":"85221",
    "sg:province":"Bayern",
    "wof:name":"Torsten Starig",
    "wof:placetype":"venue"
},
  "geometry": {"coordinates":[11.4660730362,48.2610816956],"type":"Point"}
}