{
  "type": "Feature",
  "properties": {
    "iso:country":"DE",
    "sg:address":"Liebigstr. 17c",
    "sg:city":"Geldern",
    "sg:phone":"+49 2831/89508",
    "sg:postcode":"47608",
    "sg:province":"Nordrhein-Westfalen",
    "wof:name":"Gerda Pokolm Gmbh",
    "wof:placetype":"venue"
},
  "geometry": {"coordinates":[6.3525137901,51.5267372131],"type":"Point"}
}