{
  "type": "Feature",
  "properties": {
    "iso:country":"DE",
    "sg:address":"Marienplatz 3",
    "sg:city":"Wolnzach",
    "sg:phone":"+49 8442/2926",
    "sg:postcode":"85283",
    "sg:province":"Bayern",
    "wof:name":"Optik Scheere Gmbh",
    "wof:placetype":"venue"
},
  "geometry": {"coordinates":[11.6263828278,48.6036224365],"type":"Point"}
}