{
  "type": "Feature",
  "properties": {
    "iso:country":"DE",
    "sg:address":"B\u00fcrgerm.-Kr\u00f6ger-Str. 36",
    "sg:city":"Buchholz",
    "sg:phone":"+49 4186/9710",
    "sg:postcode":"21244",
    "sg:province":"Niedersachsen",
    "wof:name":"Maschinenbau Spr\u00f6tze Gmbh",
    "wof:placetype":"venue"
},
  "geometry": {"coordinates":[9.8801221848,53.3282814026],"type":"Point"}
}