{
  "type": "Feature",
  "properties": {
    "iso:country":"DE",
    "sg:address":"Heinrich-Rorbeck-Weg 7",
    "sg:city":"Schorndorf",
    "sg:phone":"+49 7181/21701",
    "sg:postcode":"73614",
    "sg:province":"Baden-W\u00fcrttemberg",
    "wof:name":"N. Tallarek",
    "wof:placetype":"venue"
},
  "geometry": {"coordinates":[9.529676,48.795124],"type":"Point"}
}