{
  "type": "Feature",
  "properties": {
    "iso:country":"DE",
    "sg:address":"Kapuzinerstr. 38",
    "sg:city":"Passau",
    "sg:phone":"+49 851/33022",
    "sg:postcode":"94032",
    "sg:province":"Bayern",
    "wof:name":"Glasbau Josef Wetzl Gmbh",
    "wof:placetype":"venue"
},
  "geometry": {"coordinates":[13.478723526,48.5711021423],"type":"Point"}
}