{
  "type": "Feature",
  "properties": {
    "iso:country":"DE",
    "sg:address":"Bahnhofstr. 98",
    "sg:city":"Borken",
    "sg:phone":"+49 5682/2034",
    "sg:postcode":"34582",
    "sg:province":"Hessen",
    "wof:name":"Inas Bistro",
    "wof:placetype":"venue"
},
  "geometry": {"coordinates":[9.284239769,51.0458564758],"type":"Point"}
}