{
  "type": "Feature",
  "properties": {
    "iso:country":"DE",
    "sg:address":"Forststr. 4",
    "sg:city":"Linsengericht",
    "sg:phone":"+49 6051/979501",
    "sg:postcode":"63589",
    "sg:province":"Hessen",
    "wof:name":"Andre Werbung Rhein-main Gmbh",
    "wof:placetype":"venue"
},
  "geometry": {"coordinates":[9.2218379974,50.1703186035],"type":"Point"}
}