{
  "type": "Feature",
  "properties": {
    "iso:country":"DE",
    "sg:address":"Frankfurter Str. 181",
    "sg:city":"Neu-Isenburg",
    "sg:phone":"+49 6102/254749",
    "sg:postcode":"63263",
    "sg:province":"Hessen",
    "wof:name":"Steucon Immobilien Ag",
    "wof:placetype":"venue"
},
  "geometry": {"coordinates":[8.6950855255,50.0482597351],"type":"Point"}
}