{
  "type": "Feature",
  "properties": {
    "iso:country":"DE",
    "sg:address":"Am Damm 38c",
    "sg:city":"Hamburg",
    "sg:phone":"+49 40/6404400",
    "sg:postcode":"22175",
    "sg:province":"Hamburg",
    "wof:name":"U. Loeschenkohl",
    "wof:placetype":"venue"
},
  "geometry": {"coordinates":[10.095397,53.629921],"type":"Point"}
}