{
  "type": "Feature",
  "properties": {
    "iso:country":"DE",
    "sg:address":"Bopserwaldstr. 39",
    "sg:city":"Stuttgart",
    "sg:phone":"+49 711/238590",
    "sg:postcode":"70184",
    "sg:province":"Baden-W\u00fcrttemberg",
    "wof:name":"H. Haag Architekt",
    "wof:placetype":"venue"
},
  "geometry": {"coordinates":[9.186749,48.768162],"type":"Point"}
}