{
  "type": "Feature",
  "properties": {
    "iso:country":"DE",
    "sg:address":"Leckenhofstr. 2",
    "sg:city":"Dormagen",
    "sg:phone":"+49 2133/220780",
    "sg:postcode":"41542",
    "sg:province":"Nordrhein-Westfalen",
    "wof:name":"Dorfcafe Malereck",
    "wof:placetype":"venue"
},
  "geometry": {"coordinates":[6.786813,51.130527],"type":"Point"}
}