{
  "type": "Feature",
  "properties": {
    "iso:country":"DE",
    "sg:address":"Apfelweg 2",
    "sg:city":"Berlin",
    "sg:phone":"+49 30/6731365",
    "sg:postcode":"12524",
    "sg:province":"Berlin",
    "wof:name":"\u00d6kologischer Holz Und Bautenschutz -naturfarben",
    "wof:placetype":"venue"
},
  "geometry": {"coordinates":[13.535433,52.407722],"type":"Point"}
}