{
  "type": "Feature",
  "properties": {
    "iso:country":"DE",
    "sg:address":"Rheinstr. 21",
    "sg:city":"Horhausen",
    "sg:phone":"+49 2687/1076",
    "sg:postcode":"56593",
    "sg:province":"Rheinland-Pfalz",
    "wof:name":"Michael M\u00fcller",
    "wof:placetype":"venue"
},
  "geometry": {"coordinates":[7.504065,50.580383],"type":"Point"}
}