{
  "type": "Feature",
  "properties": {
    "iso:country":"DE",
    "sg:address":"Hohe Str. 8",
    "sg:city":"Steinen",
    "sg:phone":"+49 2666/8169",
    "sg:postcode":"56244",
    "sg:province":"Rheinland-Pfalz",
    "wof:name":"H. Brenner",
    "wof:placetype":"venue"
},
  "geometry": {"coordinates":[7.810107,50.574043],"type":"Point"}
}