{
  "type": "Feature",
  "properties": {
    "iso:country":"DE",
    "sg:address":"Selhofer Weg 115",
    "sg:city":"Melle",
    "sg:phone":"+49 5422/958187",
    "sg:postcode":"49324",
    "sg:province":"Niedersachsen",
    "wof:name":"As-service Inh. Mahmut Aslan",
    "wof:placetype":"venue"
},
  "geometry": {"coordinates":[8.3612947464,52.1819267273],"type":"Point"}
}