{
  "type": "Feature",
  "properties": {
    "iso:country":"DE",
    "sg:address":"Unterg\u00f6nner Str. 5",
    "sg:city":"B\u00fcnde",
    "sg:phone":"+49 5223/10607",
    "sg:postcode":"32257",
    "sg:province":"Nordrhein-Westfalen",
    "wof:name":"Helmut Schr\u00f6der Gmbh B\u00e4ckereibetrieb",
    "wof:placetype":"venue"
},
  "geometry": {"coordinates":[8.596888,52.189041],"type":"Point"}
}