{
  "type": "Feature",
  "properties": {
    "iso:country":"DE",
    "sg:address":"Gie\u00dfener Str. 12",
    "sg:city":"Gr\u00fcnberg",
    "sg:phone":"+49 6401/4767",
    "sg:postcode":"35305",
    "sg:province":"Hessen",
    "wof:name":"Arno Bartl Rechtsanwalt",
    "wof:placetype":"venue"
},
  "geometry": {"coordinates":[8.9568777084,50.5931663513],"type":"Point"}
}