{
  "type": "Feature",
  "properties": {
    "iso:country":"DE",
    "sg:address":"Gasse 5",
    "sg:city":"Neumark",
    "sg:phone":"+49 37600/3976",
    "sg:postcode":"08496",
    "sg:province":"Sachsen",
    "wof:name":"Michael Knopp Ingenieur",
    "wof:placetype":"venue"
},
  "geometry": {"coordinates":[12.3199272156,50.6738395691],"type":"Point"}
}