{
  "type": "Feature",
  "properties": {
    "iso:country":"DE",
    "sg:address":"Feldstr. 10",
    "sg:city":"Bremen",
    "sg:phone":"+49 421/706825",
    "sg:postcode":"28203",
    "sg:province":"Bremen",
    "wof:name":"U. Dechantsreiter Architekt",
    "wof:placetype":"venue"
},
  "geometry": {"coordinates":[8.82692,53.07658],"type":"Point"}
}