{
  "type": "Feature",
  "properties": {
    "iso:country":"DE",
    "sg:address":"Ludwigsthaler Str. 1",
    "sg:city":"Neunkirchen",
    "sg:phone":"+49 6821/31393",
    "sg:postcode":"66539",
    "sg:province":"Saarland",
    "wof:name":"Karl-heinz Lang",
    "wof:placetype":"venue"
},
  "geometry": {"coordinates":[7.2194719315,49.3241577148],"type":"Point"}
}