{
  "type": "Feature",
  "properties": {
    "iso:country":"DE",
    "sg:address":"Donnersbergstege 2",
    "sg:city":"H\u00fcnxe",
    "sg:phone":"+49 2858/6193",
    "sg:postcode":"46569",
    "sg:province":"Nordrhein-Westfalen",
    "wof:name":"Sport Und Freizeit Beckmann",
    "wof:placetype":"venue"
},
  "geometry": {"coordinates":[6.769178,51.643673],"type":"Point"}
}