{
  "type": "Feature",
  "properties": {
    "iso:country":"DE",
    "sg:address":"Krambuden 2",
    "sg:city":"Wolfenb\u00fcttel",
    "sg:phone":"+49 5331/5732",
    "sg:postcode":"38300",
    "sg:province":"Niedersachsen",
    "wof:name":"Natur Im Heim",
    "wof:placetype":"venue"
},
  "geometry": {"coordinates":[10.533946,52.163189],"type":"Point"}
}