{
  "type": "Feature",
  "properties": {
    "iso:country":"DE",
    "sg:address":"Hibben 5",
    "sg:city":"Stolzenau",
    "sg:phone":"+49 5761/2905",
    "sg:postcode":"31592",
    "sg:province":"Niedersachsen",
    "wof:name":"Erwin Syring",
    "wof:placetype":"venue"
},
  "geometry": {"coordinates":[9.02404,52.500549],"type":"Point"}
}