{
  "type": "Feature",
  "properties": {
    "iso:country":"DE",
    "sg:address":"Am Stillbach 12",
    "sg:city":"Vilsheim",
    "sg:phone":"+49 8706/941027",
    "sg:postcode":"84186",
    "sg:province":"Bayern",
    "wof:name":"Pscherer Druck Und Service E. K.",
    "wof:placetype":"venue"
},
  "geometry": {"coordinates":[12.100424,48.444561],"type":"Point"}
}