{
  "type": "Feature",
  "properties": {
    "iso:country":"DE",
    "sg:address":"Auf'm Berg 2",
    "sg:city":"Leutkirch",
    "sg:phone":"+49 7561/4806",
    "sg:postcode":"88299",
    "sg:province":"Baden-W\u00fcrttemberg",
    "wof:name":"\u00d6kumenische Arbeitsgruppe Eine Welt E. V.",
    "wof:placetype":"venue"
},
  "geometry": {"coordinates":[10.0289049149,47.8241729736],"type":"Point"}
}