{
  "type": "Feature",
  "properties": {
    "iso:country":"DE",
    "sg:address":"Sellerweg 20",
    "sg:city":"Warstein",
    "sg:phone":"+49 2902/51171",
    "sg:postcode":"59581",
    "sg:province":"Nordrhein-Westfalen",
    "wof:name":"J\u00f6rg Hoppe",
    "wof:placetype":"venue"
},
  "geometry": {"coordinates":[8.3305387497,51.4822311401],"type":"Point"}
}