{
  "type": "Feature",
  "properties": {
    "iso:country":"DE",
    "sg:address":"Memmelsdorfer Str. 43",
    "sg:city":"Bamberg",
    "sg:phone":"+49 951/69290",
    "sg:postcode":"96052",
    "sg:province":"Bayern",
    "wof:name":"Georg Grosskopf",
    "wof:placetype":"venue"
},
  "geometry": {"coordinates":[10.893504,49.904633],"type":"Point"}
}