{
  "type": "Feature",
  "properties": {
    "iso:country":"DE",
    "sg:address":"Kassenberger Str. 87",
    "sg:city":"Bochum",
    "sg:phone":"+49 234/413638",
    "sg:postcode":"44879",
    "sg:province":"Nordrhein-Westfalen",
    "wof:name":"U. Keller",
    "wof:placetype":"venue"
},
  "geometry": {"coordinates":[7.1496567726,51.4338722229],"type":"Point"}
}