{
  "type": "Feature",
  "properties": {
    "iso:country":"DE",
    "sg:address":"Kaiserstr. 25",
    "sg:city":"Gummersbach",
    "sg:phone":"+49 2261/23390",
    "sg:postcode":"51643",
    "sg:province":"Nordrhein-Westfalen",
    "wof:name":"Bergischer-hof-apotheke Inh. Paul G\u00fcnter Wagner",
    "wof:placetype":"venue"
},
  "geometry": {"coordinates":[7.565702,51.027031],"type":"Point"}
}