{
  "type": "Feature",
  "properties": {
    "iso:country":"DE",
    "sg:address":"Fischzucht 1",
    "sg:city":"Wiesbaden",
    "sg:phone":"+49 611/1851903",
    "sg:postcode":"65195",
    "sg:province":"Hessen",
    "wof:name":"Fischzucht",
    "wof:placetype":"venue"
},
  "geometry": {"coordinates":[8.1982688904,50.1135292053],"type":"Point"}
}