{
  "type": "Feature",
  "properties": {
    "iso:country":"DE",
    "sg:address":"K\u00f6nigsberger Str. 24",
    "sg:city":"Hemer",
    "sg:phone":"+49 2372/10427",
    "sg:postcode":"58675",
    "sg:province":"Nordrhein-Westfalen",
    "wof:name":"Johann K. A. M\u00fcller Architekt",
    "wof:placetype":"venue"
},
  "geometry": {"coordinates":[7.770934,51.37331],"type":"Point"}
}