{
  "type": "Feature",
  "properties": {
    "iso:country":"DE",
    "sg:address":"Kronwinkler Str 31",
    "sg:city":"M\u00fcnchen",
    "sg:phone":"+49 89/8630980",
    "sg:postcode":"81245",
    "sg:province":"Bayern",
    "wof:name":"Vehd Internationale Spedition Gmbh",
    "wof:placetype":"venue"
},
  "geometry": {"coordinates":[11.423806,48.160053],"type":"Point"}
}