{
  "type": "Feature",
  "properties": {
    "iso:country":"DE",
    "sg:address":"Lessingstr. 4",
    "sg:city":"Zwickau",
    "sg:phone":"+49 4937/55410",
    "sg:postcode":"08058",
    "sg:province":"Sachsen",
    "wof:name":"Bic Zwickau Gmbh",
    "wof:placetype":"venue"
},
  "geometry": {"coordinates":[12.491253,50.725929],"type":"Point"}
}