{
  "type": "Feature",
  "properties": {
    "iso:country":"DE",
    "sg:address":"Oldendorf 18",
    "sg:city":"Appel",
    "sg:phone":"+49 4165/80766",
    "sg:postcode":"21279",
    "sg:province":"Niedersachsen",
    "wof:name":"Dorothee Und Ergin Onat",
    "wof:placetype":"venue"
},
  "geometry": {"coordinates":[9.758559227,53.3805389404],"type":"Point"}
}