{
  "type": "Feature",
  "properties": {
    "iso:country":"DE",
    "sg:address":"Alte K\u00f6lner Str. 32",
    "sg:city":"Pulheim",
    "sg:postcode":"50259",
    "sg:province":"Nordrhein-Westfalen",
    "wof:name":"Rainer Begoin E. K.",
    "wof:placetype":"venue"
},
  "geometry": {"coordinates":[6.8004689217,50.9977264404],"type":"Point"}
}