{
  "type": "Feature",
  "properties": {
    "iso:country":"DE",
    "sg:address":"Frankfurter Str. 2",
    "sg:city":"Altenstadt",
    "sg:phone":"+49 6047/4428",
    "sg:postcode":"63674",
    "sg:province":"Hessen",
    "wof:name":"Willi Hensel Kohlen-handlung",
    "wof:placetype":"venue"
},
  "geometry": {"coordinates":[8.942377,50.285072],"type":"Point"}
}