{
  "type": "Feature",
  "properties": {
    "iso:country":"DE",
    "sg:address":"Owinger Str. 4",
    "sg:city":"\u00dcberlingen",
    "sg:phone":"+49 4975/515383",
    "sg:postcode":"88662",
    "sg:province":"Baden-W\u00fcrttemberg",
    "wof:name":"Fotosatz Fesser Gmbh",
    "wof:placetype":"venue"
},
  "geometry": {"coordinates":[9.1656198502,47.7707672119],"type":"Point"}
}