{
  "type": "Feature",
  "properties": {
    "iso:country":"DE",
    "sg:address":"Gautinger Str. 57",
    "sg:city":"We\u00dfling",
    "sg:phone":"+49 8153/9090",
    "sg:postcode":"82234",
    "sg:province":"Bayern",
    "wof:name":"Csd-logistik Software Gmbh",
    "wof:placetype":"venue"
},
  "geometry": {"coordinates":[11.26277,48.074631],"type":"Point"}
}