{
  "type": "Feature",
  "properties": {
    "iso:country":"DE",
    "sg:address":"Moosweg 8",
    "sg:city":"Fridolfing",
    "sg:phone":"+49 8684/585",
    "sg:postcode":"83413",
    "sg:province":"Bayern",
    "wof:name":"Restaurant Zum Bax",
    "wof:placetype":"venue"
},
  "geometry": {"coordinates":[12.8236169815,47.9970359802],"type":"Point"}
}