{
  "type": "Feature",
  "properties": {
    "iso:country":"DE",
    "sg:address":"Hauptstr. 31",
    "sg:city":"Dorn-D\u00fcrkheim",
    "sg:phone":"+49 6733/6928",
    "sg:postcode":"67585",
    "sg:province":"Rheinland-Pfalz",
    "wof:name":"Werner Schimmel",
    "wof:placetype":"venue"
},
  "geometry": {"coordinates":[8.2684621811,49.7707557678],"type":"Point"}
}