{
  "type": "Feature",
  "properties": {
    "iso:country":"DE",
    "sg:address":"Vordere Karlstr. 64",
    "sg:city":"G\u00f6ppingen",
    "sg:phone":"+49 7161/70915",
    "sg:postcode":"73033",
    "sg:province":"Baden-W\u00fcrttemberg",
    "wof:name":"M. Salci",
    "wof:placetype":"venue"
},
  "geometry": {"coordinates":[9.6584186554,48.7004966736],"type":"Point"}
}