{
  "type": "Feature",
  "properties": {
    "iso:country":"DE",
    "sg:address":"Ebbetalstr. 125",
    "sg:city":"Plettenberg",
    "sg:phone":"+49 2391/70801",
    "sg:postcode":"58840",
    "sg:province":"Nordrhein-Westfalen",
    "wof:name":"Walter Holterdorf",
    "wof:placetype":"venue"
},
  "geometry": {"coordinates":[7.8520197868,51.1714706421],"type":"Point"}
}