{
  "type": "Feature",
  "properties": {
    "iso:country":"DE",
    "sg:address":"Marktstr. 12",
    "sg:city":"Schramberg",
    "sg:phone":"+49 7422/22060",
    "sg:postcode":"78713",
    "sg:province":"Baden-W\u00fcrttemberg",
    "wof:name":"J. Mewes",
    "wof:placetype":"venue"
},
  "geometry": {"coordinates":[8.384958,48.226864],"type":"Point"}
}