{
  "type": "Feature",
  "properties": {
    "iso:country":"DE",
    "sg:address":"Wolfhager Str. 95",
    "sg:city":"Kassel",
    "sg:phone":"+49 561/85605",
    "sg:postcode":"34127",
    "sg:province":"Hessen",
    "wof:name":"Helmut Lamberty Heilpraktiker",
    "wof:placetype":"venue"
},
  "geometry": {"coordinates":[9.484856,51.324455],"type":"Point"}
}