{
  "type": "Feature",
  "properties": {
    "iso:country":"DE",
    "sg:address":"Ziegeleiweg 4",
    "sg:city":"L\u00fcbbecke",
    "sg:phone":"+49 5741/9660",
    "sg:postcode":"32312",
    "sg:province":"Nordrhein-Westfalen",
    "wof:name":"Gudrun Weymann Masseurin",
    "wof:placetype":"venue"
},
  "geometry": {"coordinates":[8.622945,52.303864],"type":"Point"}
}