{
  "type": "Feature",
  "properties": {
    "iso:country":"DE",
    "sg:address":"Sommerstr. 37",
    "sg:city":"Bielefeld",
    "sg:phone":"+49 521/444159",
    "sg:postcode":"33649",
    "sg:province":"Nordrhein-Westfalen",
    "wof:name":"Erwin Schoregge & Co. Inh. Hans-g. Kralemann",
    "wof:placetype":"venue"
},
  "geometry": {"coordinates":[8.474931,51.983349],"type":"Point"}
}