{
  "type": "Feature",
  "properties": {
    "iso:country":"DE",
    "sg:address":"Hunteburger Str. 41",
    "sg:city":"Bohmte",
    "sg:phone":"+49 4954/712293",
    "sg:postcode":"49163",
    "sg:province":"Niedersachsen",
    "wof:name":"M. Oelgeschl\u00c4ger Gmbh",
    "wof:placetype":"venue"
},
  "geometry": {"coordinates":[8.291955,52.393574],"type":"Point"}
}