{
  "type": "Feature",
  "properties": {
    "iso:country":"DE",
    "sg:address":"Nockwinkel 96",
    "sg:city":"Essen",
    "sg:phone":"+49 201/588251",
    "sg:postcode":"45277",
    "sg:province":"Nordrhein-Westfalen",
    "wof:name":"Silvia",
    "wof:placetype":"venue"
},
  "geometry": {"coordinates":[7.0777478218,51.428768158],"type":"Point"}
}