{
  "type": "Feature",
  "properties": {
    "iso:country":"DE",
    "sg:address":"Tal-Josaphat-Weg 14a",
    "sg:city":"Landshut",
    "sg:phone":"+49 871/2760288",
    "sg:postcode":"84036",
    "sg:province":"Bayern",
    "wof:name":"Thomas Berghammer",
    "wof:placetype":"venue"
},
  "geometry": {"coordinates":[12.1676912308,48.5267524719],"type":"Point"}
}