{
  "type": "Feature",
  "properties": {
    "iso:country":"DE",
    "sg:address":"Riedb\u00e4chle 36",
    "sg:city":"Bad Boll",
    "sg:phone":"+49 7164",
    "sg:postcode":"73087",
    "sg:province":"Baden-W\u00fcrttemberg",
    "wof:name":"Weincomptoir Gbr, Bad Boll",
    "wof:placetype":"venue"
},
  "geometry": {"coordinates":[9.6110296249,48.6407394409],"type":"Point"}
}