{
  "type": "Feature",
  "properties": {
    "iso:country":"DE",
    "sg:address":"Schillerstr. 15",
    "sg:city":"Elsterwerda",
    "sg:phone":"+49 3533/4201",
    "sg:postcode":"04910",
    "sg:province":"Brandenburg",
    "wof:name":"Dr. Med. Lothar Walther",
    "wof:placetype":"venue"
},
  "geometry": {"coordinates":[13.521708,51.463947],"type":"Point"}
}