{
  "type": "Feature",
  "properties": {
    "iso:country":"DE",
    "sg:address":"Bogeler Str. 1",
    "sg:city":"Lautert",
    "sg:phone":"+49 6772/3624",
    "sg:postcode":"56355",
    "sg:province":"Rheinland-Pfalz",
    "wof:name":"Thomas Klein Gmbh",
    "wof:placetype":"venue"
},
  "geometry": {"coordinates":[7.837839,50.167538],"type":"Point"}
}