{
  "type": "Feature",
  "properties": {
    "iso:country":"DE",
    "sg:address":"Hochwald 10",
    "sg:city":"Issum",
    "sg:phone":"+49 2835/3613",
    "sg:postcode":"47661",
    "sg:province":"Nordrhein-Westfalen",
    "wof:name":"Sophie Kampmann",
    "wof:placetype":"venue"
},
  "geometry": {"coordinates":[6.444645,51.543186],"type":"Point"}
}