{
  "type": "Feature",
  "properties": {
    "iso:country":"DE",
    "sg:address":"Kirchenweg 1",
    "sg:city":"Staudach-Egerndach",
    "sg:phone":"+49 8641/2293",
    "sg:postcode":"83224",
    "sg:province":"Bayern",
    "wof:name":"Georg Fritzenwenger",
    "wof:placetype":"venue"
},
  "geometry": {"coordinates":[12.4578504562,47.7785568237],"type":"Point"}
}