{
  "type": "Feature",
  "properties": {
    "iso:country":"DE",
    "sg:address":"Herderner Str.",
    "sg:city":"Hohentengen",
    "sg:phone":"+49 7742/5703",
    "sg:postcode":"79801",
    "sg:province":"Baden-W\u00fcrttemberg",
    "wof:name":"R\u00f6\u00dfle",
    "wof:placetype":"venue"
},
  "geometry": {"coordinates":[8.4428195953,47.5713195801],"type":"Point"}
}