{
  "type": "Feature",
  "properties": {
    "iso:country":"DE",
    "sg:address":"Dr.-Raber-Str. 4",
    "sg:city":"Hagenow",
    "sg:postcode":"19230",
    "sg:province":"Mecklenburg-Vorpommern",
    "wof:name":"Tfh Textile Finishing Gesellschaft Zur Aufbereitung",
    "wof:placetype":"venue"
},
  "geometry": {"coordinates":[11.1866760254,53.4178886414],"type":"Point"}
}