{
  "type": "Feature",
  "properties": {
    "iso:country":"DE",
    "sg:address":"Finkenweg 1",
    "sg:city":"Leinfelden-Echterdingen",
    "sg:phone":"+49 711/7545018",
    "sg:postcode":"70771",
    "sg:province":"Baden-W\u00fcrttemberg",
    "wof:name":"Vritex Kg",
    "wof:placetype":"venue"
},
  "geometry": {"coordinates":[9.141356,48.706367],"type":"Point"}
}