{
  "type": "Feature",
  "properties": {
    "iso:country":"DE",
    "sg:address":"Hauptstr. 47",
    "sg:city":"L\u00f6rrach",
    "sg:phone":"+49 7621/82042",
    "sg:postcode":"79540",
    "sg:province":"Baden-W\u00fcrttemberg",
    "wof:name":"Adler-fa\u00df",
    "wof:placetype":"venue"
},
  "geometry": {"coordinates":[7.663831234,47.6015777588],"type":"Point"}
}