{
  "type": "Feature",
  "properties": {
    "iso:country":"DE",
    "sg:address":"M\u00fcnzstr. 9",
    "sg:city":"Harzgerode",
    "sg:phone":"+49 39484/2719",
    "sg:postcode":"06493",
    "sg:province":"Sachsen-Anhalt",
    "wof:name":"Rainer Ahke",
    "wof:placetype":"venue"
},
  "geometry": {"coordinates":[11.145886,51.640652],"type":"Point"}
}