{
  "type": "Feature",
  "properties": {
    "iso:country":"DE",
    "sg:address":"Waidmannsruhberg 11",
    "sg:city":"Rosdorf",
    "sg:phone":"+49 4822/30000",
    "sg:postcode":"25548",
    "sg:province":"Schleswig-Holstein",
    "wof:name":"Hans Graf Zu Rantzau Holzgro\u00dfhandlung",
    "wof:placetype":"venue"
},
  "geometry": {"coordinates":[9.724086,53.974396],"type":"Point"}
}