{
  "type": "Feature",
  "properties": {
    "iso:country":"DE",
    "sg:address":"Beecker Str. 31",
    "sg:city":"M\u00f6nchengladbach",
    "sg:phone":"+49 2161/580479",
    "sg:postcode":"41179",
    "sg:province":"Nordrhein-Westfalen",
    "wof:name":"Richard R\u00f6sicke",
    "wof:placetype":"venue"
},
  "geometry": {"coordinates":[6.3606419563,51.1476325989],"type":"Point"}
}