{
  "type": "Feature",
  "properties": {
    "iso:country":"DE",
    "sg:address":"Im Aachtal 5",
    "sg:city":"Aach",
    "sg:phone":"+49 7774/6216",
    "sg:postcode":"78267",
    "sg:province":"Baden-W\u00fcrttemberg",
    "wof:name":"A.magda Kreuzfahrten",
    "wof:placetype":"venue"
},
  "geometry": {"coordinates":[8.8655366898,47.8336296082],"type":"Point"}
}