{
  "type": "Feature",
  "properties": {
    "iso:country":"DE",
    "sg:address":"Robert-Bosch-Str. 1",
    "sg:city":"Tuttlingen",
    "sg:phone":"+49 4974/6113235",
    "sg:postcode":"78532",
    "sg:province":"Baden-W\u00fcrttemberg",
    "wof:name":"Ludwig Schneider Gmbh & Co. Kg",
    "wof:placetype":"venue"
},
  "geometry": {"coordinates":[8.818975,47.985882],"type":"Point"}
}