{
  "type": "Feature",
  "properties": {
    "iso:country":"DE",
    "sg:address":"Adolf-Dambach-Str. 2-4",
    "sg:city":"Gaggenau",
    "sg:postcode":"76571",
    "sg:province":"Baden-W\u00fcrttemberg",
    "wof:name":"Poly One Deutschland Gmbh",
    "wof:placetype":"venue"
},
  "geometry": {"coordinates":[8.301543,48.817268],"type":"Point"}
}