{
  "type": "Feature",
  "properties": {
    "iso:country":"DE",
    "sg:address":"Theodor-Storm-Str 25",
    "sg:city":"Henstedt-Ulzburg",
    "sg:phone":"+49 4193/76417",
    "sg:postcode":"24558",
    "sg:province":"Schleswig-Holstein",
    "wof:name":"Tbu Thomas Brandl Umweltschutztechnik Gmbh",
    "wof:placetype":"venue"
},
  "geometry": {"coordinates":[9.993837,53.757549],"type":"Point"}
}