{
  "type": "Feature",
  "properties": {
    "iso:country":"DE",
    "sg:address":"Anhalter Str 1",
    "sg:city":"Berlin",
    "sg:phone":"+49 30/88429923",
    "sg:postcode":"10963",
    "sg:province":"Berlin",
    "wof:name":"Dfn-verein Ev",
    "wof:placetype":"venue"
},
  "geometry": {"coordinates":[13.383019,52.504524],"type":"Point"}
}