{
  "type": "Feature",
  "properties": {
    "iso:country":"DE",
    "sg:address":"Albert-Schweitzer-Str. 3",
    "sg:city":"M\u00fchlheim",
    "sg:phone":"+49 6108/91173",
    "sg:postcode":"63165",
    "sg:province":"Hessen",
    "wof:name":"H. K\u00f6nig Gmbh",
    "wof:placetype":"venue"
},
  "geometry": {"coordinates":[8.851871,50.101555],"type":"Point"}
}