{
  "type": "Feature",
  "properties": {
    "iso:country":"DE",
    "sg:address":"Maurepasstr. 113",
    "sg:city":"Henstedt-Ulzburg",
    "sg:postcode":"24558",
    "sg:province":"Schleswig-Holstein",
    "wof:name":"Trepte Immobilien Gmbh",
    "wof:placetype":"venue"
},
  "geometry": {"coordinates":[9.9901695251,53.7898902893],"type":"Point"}
}