{
  "type": "Feature",
  "properties": {
    "iso:country":"DE",
    "sg:address":"Altenwall 2",
    "sg:city":"Bremen",
    "sg:phone":"+49 421/1655290",
    "sg:postcode":"28195",
    "sg:province":"Bremen",
    "wof:name":"Sch\u00fcttrumpf Westerholt Und Partner",
    "wof:placetype":"venue"
},
  "geometry": {"coordinates":[8.8126354218,53.0732841492],"type":"Point"}
}