{
  "type": "Feature",
  "properties": {
    "iso:country":"DE",
    "sg:address":"Am R\u00f6tling 2",
    "sg:city":"Finnentrop",
    "sg:phone":"+49 2721/70729",
    "sg:postcode":"57413",
    "sg:province":"Nordrhein-Westfalen",
    "wof:name":"Hans Hentschel Ingenieur",
    "wof:placetype":"venue"
},
  "geometry": {"coordinates":[7.9862179756,51.1671943665],"type":"Point"}
}