{
  "type": "Feature",
  "properties": {
    "iso:country":"DE",
    "sg:address":"Eyendorfer Str. 6",
    "sg:city":"Salzhausen",
    "sg:phone":"+49 4172/7168",
    "sg:postcode":"21376",
    "sg:province":"Niedersachsen",
    "wof:name":"Friedrich-wilhelm Hornbostel Eisenwaren",
    "wof:placetype":"venue"
},
  "geometry": {"coordinates":[10.1659622192,53.2255783081],"type":"Point"}
}