{
  "type": "Feature",
  "properties": {
    "iso:country":"DE",
    "sg:address":"Industriestr. 16",
    "sg:city":"Garrel",
    "sg:phone":"+49 4944/7494830",
    "sg:postcode":"49681",
    "sg:province":"Niedersachsen",
    "wof:name":"Roland Werk Gmbh",
    "wof:placetype":"venue"
},
  "geometry": {"coordinates":[8.0219717026,52.9446029663],"type":"Point"}
}