{
  "type": "Feature",
  "properties": {
    "iso:country":"DE",
    "sg:address":"Windecker Str. 32",
    "sg:city":"Bad Vilbel",
    "sg:phone":"+49 6101/83943",
    "sg:postcode":"61118",
    "sg:province":"Hessen",
    "wof:name":"Bechmann Gmbh",
    "wof:placetype":"venue"
},
  "geometry": {"coordinates":[8.749802,50.17915],"type":"Point"}
}