{
  "type": "Feature",
  "properties": {
    "iso:country":"DE",
    "sg:address":"Kirchweg 32",
    "sg:city":"Leezdorf",
    "sg:phone":"+49 4934",
    "sg:postcode":"26529",
    "sg:province":"Niedersachsen",
    "wof:name":"G\u00e4stehaus Birgit, Leezdorf",
    "wof:placetype":"venue"
},
  "geometry": {"coordinates":[7.311507225,53.5395774841],"type":"Point"}
}