{
  "type": "Feature",
  "properties": {
    "iso:country":"DE",
    "sg:address":"Langer Hagen 36",
    "sg:city":"Hildesheim",
    "sg:phone":"+49 5121/37451",
    "sg:postcode":"31134",
    "sg:province":"Niedersachsen",
    "wof:name":"Magic Castle",
    "wof:placetype":"venue"
},
  "geometry": {"coordinates":[9.9440841675,52.1521186829],"type":"Point"}
}