{
  "type": "Feature",
  "properties": {
    "iso:country":"DE",
    "sg:address":"Jahnstr. 34",
    "sg:city":"Wiesbaden",
    "sg:phone":"+49 611/373957",
    "sg:postcode":"65185",
    "sg:province":"Hessen",
    "wof:name":"Schaber Und Decker Ingenieur-ges. Mbh",
    "wof:placetype":"venue"
},
  "geometry": {"coordinates":[8.232051,50.076336],"type":"Point"}
}