{
  "type": "Feature",
  "properties": {
    "iso:country":"DE",
    "sg:address":"Meller Str. 2",
    "sg:city":"R\u00f6dinghausen",
    "sg:phone":"+49 5226/591259",
    "sg:postcode":"32289",
    "sg:province":"Nordrhein-Westfalen",
    "wof:name":"Schoon Und Schumann Rechtsanwalt",
    "wof:placetype":"venue"
},
  "geometry": {"coordinates":[8.4557695389,52.200668335],"type":"Point"}
}