{
  "type": "Feature",
  "properties": {
    "iso:country":"DE",
    "sg:address":"Pfarrstr. 8",
    "sg:city":"Waibstadt",
    "sg:phone":"+49 7263/3828",
    "sg:postcode":"74915",
    "sg:province":"Baden-W\u00fcrttemberg",
    "wof:name":"Edinger",
    "wof:placetype":"venue"
},
  "geometry": {"coordinates":[8.9216,49.297501],"type":"Point"}
}