{
  "type": "Feature",
  "properties": {
    "iso:country":"DE",
    "sg:address":"Buckower Str. 8",
    "sg:city":"Hermersdorf/Obersdorf",
    "sg:postcode":"15374",
    "sg:province":"Brandenburg",
    "wof:name":"Tar Entwicklungs Gmbh & Co. Kg",
    "wof:placetype":"venue"
},
  "geometry": {"coordinates":[14.1439313889,52.5017471313],"type":"Point"}
}