{
  "type": "Feature",
  "properties": {
    "iso:country":"DE",
    "sg:address":"Rosenweg 1",
    "sg:city":"Sankt Augustin",
    "sg:phone":"+49 2241/50184",
    "sg:postcode":"53757",
    "sg:province":"Nordrhein-Westfalen",
    "wof:name":"Lothar Franke Leasing",
    "wof:placetype":"venue"
},
  "geometry": {"coordinates":[7.2320151329,50.7831687927],"type":"Point"}
}