{
  "type": "Feature",
  "properties": {
    "iso:country":"DE",
    "sg:address":"Calenberger Str. 9",
    "sg:city":"Elze",
    "sg:phone":"+49 5068/2555",
    "sg:postcode":"31008",
    "sg:province":"Niedersachsen",
    "wof:name":"Gasthaus K. Ziegenmeyer",
    "wof:placetype":"venue"
},
  "geometry": {"coordinates":[9.7387151718,52.1513214111],"type":"Point"}
}