{
  "type": "Feature",
  "properties": {
    "iso:country":"DE",
    "sg:address":"Peenestr. 12",
    "sg:city":"Loitz",
    "sg:phone":"+49 39998/10501",
    "sg:postcode":"17121",
    "sg:province":"Mecklenburg-Vorpommern",
    "wof:name":"Birgit Wickboldt",
    "wof:placetype":"venue"
},
  "geometry": {"coordinates":[13.1306257248,53.9701957703],"type":"Point"}
}