{
  "type": "Feature",
  "properties": {
    "iso:country":"DE",
    "sg:address":"Lange Str. 11",
    "sg:city":"Schafst\u00e4dt",
    "sg:phone":"+49 34636/60214",
    "sg:postcode":"06255",
    "sg:province":"Sachsen-Anhalt",
    "wof:name":"Annett Schlegel",
    "wof:placetype":"venue"
},
  "geometry": {"coordinates":[11.7832946777,51.3521881104],"type":"Point"}
}