{
  "type": "Feature",
  "properties": {
    "iso:country":"DE",
    "sg:address":"Gutenbergplatz 46-49",
    "sg:city":"Arnsberg",
    "sg:phone":"+49 2931/14747",
    "sg:postcode":"59821",
    "sg:province":"Nordrhein-Westfalen",
    "wof:name":"Winter Verwaltungs- Gmbh",
    "wof:placetype":"venue"
},
  "geometry": {"coordinates":[8.073742,51.396523],"type":"Point"}
}