{
  "type": "Feature",
  "properties": {
    "iso:country":"DE",
    "sg:address":"Frauenbergstr. 15",
    "sg:city":"Bad Waldsee",
    "sg:phone":"+49 7524/400370",
    "sg:postcode":"88339",
    "sg:province":"Baden-W\u00fcrttemberg",
    "wof:name":"Bund Der Landjugend W\u00fcrttemberg-hohenzollern",
    "wof:placetype":"venue"
},
  "geometry": {"coordinates":[9.753235817,47.9179077148],"type":"Point"}
}