{
  "type": "Feature",
  "properties": {
    "iso:country":"DE",
    "sg:address":"Herriotstr. 3",
    "sg:city":"Frankfurt",
    "sg:phone":"+49 4969/66760",
    "sg:postcode":"60528",
    "sg:province":"Hessen",
    "wof:name":"Marsh Gmbh",
    "wof:placetype":"venue"
},
  "geometry": {"coordinates":[8.628653,50.080597],"type":"Point"}
}