{
  "type": "Feature",
  "properties": {
    "iso:country":"DE",
    "sg:address":"M\u00fcnsterdeich 14",
    "sg:city":"Isselburg",
    "sg:phone":"+49 2874/3048",
    "sg:postcode":"46419",
    "sg:province":"Nordrhein-Westfalen",
    "wof:name":"Helga M\u00f6hrmann",
    "wof:placetype":"venue"
},
  "geometry": {"coordinates":[6.4665179253,51.8357582092],"type":"Point"}
}