{
  "type": "Feature",
  "properties": {
    "iso:country":"DE",
    "sg:address":"Lammstr. 1",
    "sg:city":"Kirchheim",
    "sg:phone":"+49 7021/44599",
    "sg:postcode":"73230",
    "sg:province":"Baden-W\u00fcrttemberg",
    "wof:name":"Da Gigi",
    "wof:placetype":"venue"
},
  "geometry": {"coordinates":[9.4517440796,48.6499328613],"type":"Point"}
}