{
  "type": "Feature",
  "properties": {
    "iso:country":"DE",
    "sg:address":"Albert-Viertel-Str. 1",
    "sg:city":"Burgst\u00e4dt",
    "sg:phone":"+49 3724/2720",
    "sg:postcode":"09217",
    "sg:province":"Sachsen",
    "wof:name":"Frank Beginski Gmbh",
    "wof:placetype":"venue"
},
  "geometry": {"coordinates":[12.819222,50.898739],"type":"Point"}
}