{
  "type": "Feature",
  "properties": {
    "iso:country":"DE",
    "sg:address":"Giengener Str. 60",
    "sg:city":"Heidenheim",
    "sg:phone":"+49 7321/51120",
    "sg:postcode":"89522",
    "sg:province":"Baden-W\u00fcrttemberg",
    "wof:name":"Gerhard Gravemeyer",
    "wof:placetype":"venue"
},
  "geometry": {"coordinates":[10.161294,48.667744],"type":"Point"}
}