{
  "type": "Feature",
  "properties": {
    "iso:country":"DE",
    "sg:address":"Joseph-Haydn-Weg 32",
    "sg:city":"Tuttlingen",
    "sg:phone":"+49 7461/2146",
    "sg:postcode":"78532",
    "sg:province":"Baden-W\u00fcrttemberg",
    "wof:name":"Alfons Krau\u00df Architekt",
    "wof:placetype":"venue"
},
  "geometry": {"coordinates":[8.840776,47.985229],"type":"Point"}
}