{
  "type": "Feature",
  "properties": {
    "iso:country":"DE",
    "sg:address":"Friedrich-Heinrich-Allee 64",
    "sg:city":"Kamp-Lintfort",
    "sg:phone":"+49 2842/96550",
    "sg:postcode":"47475",
    "sg:province":"Nordrhein-Westfalen",
    "wof:name":"Tennis-treff Am Zehnthof Gmbh",
    "wof:placetype":"venue"
},
  "geometry": {"coordinates":[6.5455961227,51.4960479736],"type":"Point"}
}