{
  "type": "Feature",
  "properties": {
    "iso:country":"DE",
    "sg:address":"S\u00fcdliche Hafenstr. 6 A",
    "sg:city":"W\u00fcrzburg",
    "sg:phone":"+49 931/970670",
    "sg:postcode":"97080",
    "sg:province":"Bayern",
    "wof:name":"Tbg Transportbeton W\u00fcrzburg Verwaltungs-gmbh",
    "wof:placetype":"venue"
},
  "geometry": {"coordinates":[9.893342,49.799374],"type":"Point"}
}