{
  "type": "Feature",
  "properties": {
    "iso:country":"DE",
    "sg:address":"Kurze Str. 2",
    "sg:city":"Drensteinfurt",
    "sg:phone":"+49 2508/8104",
    "sg:postcode":"48317",
    "sg:province":"Nordrhein-Westfalen",
    "wof:name":"Red. M\u00fcnstersche Zeitung",
    "wof:placetype":"venue"
},
  "geometry": {"coordinates":[7.7412939072,51.7976303101],"type":"Point"}
}