{
  "type": "Feature",
  "properties": {
    "iso:country":"DE",
    "sg:address":"Lange Wende 29",
    "sg:city":"Soest",
    "sg:phone":"+49 2921/74322",
    "sg:postcode":"59494",
    "sg:province":"Nordrhein-Westfalen",
    "wof:name":"Alfons Wiendl",
    "wof:placetype":"venue"
},
  "geometry": {"coordinates":[8.136157,51.55925],"type":"Point"}
}