{
  "type": "Feature",
  "properties": {
    "iso:country":"DE",
    "sg:address":"Tannenstr. 24",
    "sg:city":"Simbach",
    "sg:phone":"+49 8571/913130",
    "sg:postcode":"84359",
    "sg:province":"Bayern",
    "wof:name":"Trenova-treberhandel- Verwaltungs-gmbh",
    "wof:placetype":"venue"
},
  "geometry": {"coordinates":[13.043964,48.275898],"type":"Point"}
}