{
  "type": "Feature",
  "properties": {
    "iso:country":"DE",
    "sg:address":"Alexander-Puschkin-Platz 4 c",
    "sg:city":"Riesa",
    "sg:phone":"+49 3525/731716",
    "sg:postcode":"01587",
    "sg:province":"Sachsen",
    "wof:name":"Terrazzino Di Arturo",
    "wof:placetype":"venue"
},
  "geometry": {"coordinates":[13.298866272,51.3051223755],"type":"Point"}
}