{
  "type": "Feature",
  "properties": {
    "iso:country":"DE",
    "sg:address":"Welsingheide 2",
    "sg:city":"M\u00fcnster",
    "sg:phone":"+49 2534/5491",
    "sg:postcode":"48161",
    "sg:province":"Nordrhein-Westfalen",
    "wof:name":"Manfred P\u00f6hlmann Architekt",
    "wof:placetype":"venue"
},
  "geometry": {"coordinates":[7.5377,51.943901],"type":"Point"}
}