{
  "type": "Feature",
  "properties": {
    "iso:country":"DE",
    "sg:address":"Hauptstr. 36",
    "sg:city":"Dreieich",
    "sg:phone":"+49 6103/67337",
    "sg:postcode":"63303",
    "sg:province":"Hessen",
    "wof:name":"Idea Die Gr\u00fcne Drogerie Gmbh",
    "wof:placetype":"venue"
},
  "geometry": {"coordinates":[8.695161,50.017147],"type":"Point"}
}