{
  "type": "Feature",
  "properties": {
    "iso:country":"DE",
    "sg:address":"Rudolst\u00e4dter Str. 118",
    "sg:city":"Berlin",
    "sg:phone":"+49 30/8238142",
    "sg:postcode":"10713",
    "sg:province":"Berlin",
    "wof:name":"Karl Breselow Kameramann",
    "wof:placetype":"venue"
},
  "geometry": {"coordinates":[13.3033514023,52.4877166748],"type":"Point"}
}