{
  "type": "Feature",
  "properties": {
    "iso:country":"DE",
    "sg:address":"Im Steinach 14",
    "sg:city":"Oberstdorf",
    "sg:phone":"+49 8322/988002",
    "sg:postcode":"87561",
    "sg:province":"Bayern",
    "wof:name":"Susanne Schweikart Rechtsanw\u00e4ltin",
    "wof:placetype":"venue"
},
  "geometry": {"coordinates":[10.2793102264,47.4131088257],"type":"Point"}
}