{
  "type": "Feature",
  "properties": {
    "iso:country":"DE",
    "sg:address":"Wilhelm-Bechtold-Str. 10-12",
    "sg:city":"Beerfelden",
    "sg:phone":"+49 6068/930000",
    "sg:postcode":"64743",
    "sg:province":"Hessen",
    "wof:name":"Ernst Bechtold & Sohn E.k.",
    "wof:placetype":"venue"
},
  "geometry": {"coordinates":[8.9713230133,49.5652236938],"type":"Point"}
}