{
  "type": "Feature",
  "properties": {
    "iso:country":"DE",
    "sg:address":"Kohlenstr. 66",
    "sg:city":"St. Ingbert",
    "sg:phone":"+49 6894/383819",
    "sg:postcode":"66386",
    "sg:province":"Saarland",
    "wof:name":"Video Total Gmbh",
    "wof:placetype":"venue"
},
  "geometry": {"coordinates":[7.1102571487,49.2796401978],"type":"Point"}
}