{
  "type": "Feature",
  "properties": {
    "iso:country":"DE",
    "sg:address":"Meller Bogen 18",
    "sg:city":"Berlin",
    "sg:phone":"+49 30/4135830",
    "sg:postcode":"13403",
    "sg:province":"Berlin",
    "wof:name":"Martin Specht",
    "wof:placetype":"venue"
},
  "geometry": {"coordinates":[13.3226108551,52.5727005005],"type":"Point"}
}