{
  "type": "Feature",
  "properties": {
    "iso:country":"DE",
    "sg:address":"Hohenwarther Str. 17",
    "sg:city":"Magdeburg",
    "sg:phone":"+49 391/500639",
    "sg:postcode":"39126",
    "sg:province":"Sachsen-Anhalt",
    "wof:name":"Holger Prywerek",
    "wof:placetype":"venue"
},
  "geometry": {"coordinates":[11.666493,52.184395],"type":"Point"}
}