{
  "type": "Feature",
  "properties": {
    "iso:country":"DE",
    "sg:address":"Kriegsstr. 184",
    "sg:city":"Karlsruhe",
    "sg:phone":"+49 721/22556",
    "sg:postcode":"76133",
    "sg:province":"Baden-W\u00fcrttemberg",
    "wof:name":"Herbert Heil",
    "wof:placetype":"venue"
},
  "geometry": {"coordinates":[8.3886194229,49.0056228638],"type":"Point"}
}