{
  "type": "Feature",
  "properties": {
    "iso:country":"DE",
    "sg:address":"Deidesheimer Str. 26",
    "sg:city":"Stuttgart",
    "sg:phone":"+49 711/8893666",
    "sg:postcode":"70499",
    "sg:province":"Baden-W\u00fcrttemberg",
    "wof:name":"Waltraud Ziegler",
    "wof:placetype":"venue"
},
  "geometry": {"coordinates":[9.118164,48.811981],"type":"Point"}
}