{
  "type": "Feature",
  "properties": {
    "iso:country":"DE",
    "sg:address":"Im Unteren Dorfe 5",
    "sg:city":"Hohenhameln",
    "sg:phone":"+49 5128/695",
    "sg:postcode":"31249",
    "sg:province":"Niedersachsen",
    "wof:name":"Brigitte Wendel Masseurin",
    "wof:placetype":"venue"
},
  "geometry": {"coordinates":[10.064317,52.255611],"type":"Point"}
}