{
  "type": "Feature",
  "properties": {
    "iso:country":"DE",
    "sg:address":"Schlo\u00dfstr. 82",
    "sg:city":"Hamburg",
    "sg:phone":"+49 40/686601",
    "sg:postcode":"22041",
    "sg:province":"Hamburg",
    "wof:name":"Faro Import Export Gmbh & Co. Kg",
    "wof:placetype":"venue"
},
  "geometry": {"coordinates":[10.072833,53.572147],"type":"Point"}
}