{
  "type": "Feature",
  "properties": {
    "iso:country":"DE",
    "sg:address":"Im Weinfeld 2",
    "sg:city":"Kalbach",
    "sg:phone":"+49 6655/919010",
    "sg:postcode":"36148",
    "sg:province":"Hessen",
    "wof:name":"Raab Siebdruck Gmbh",
    "wof:placetype":"venue"
},
  "geometry": {"coordinates":[9.6439819336,50.4287872314],"type":"Point"}
}