{
  "type": "Feature",
  "properties": {
    "iso:country":"DE",
    "sg:address":"Rathausplatz 64",
    "sg:city":"Voerde",
    "sg:phone":"+49 2855/7269",
    "sg:postcode":"46562",
    "sg:province":"Nordrhein-Westfalen",
    "wof:name":"K\u00f6llner Und Riemer Rechtsanw\u00e4lte Und Notare",
    "wof:placetype":"venue"
},
  "geometry": {"coordinates":[6.6829380989,51.5974884033],"type":"Point"}
}