{
  "type": "Feature",
  "properties": {
    "iso:country":"DE",
    "sg:address":"Wilhelm-Spengler-Str. 5",
    "sg:city":"Sche\u00dflitz",
    "sg:postcode":"96110",
    "sg:province":"Bayern",
    "wof:name":"Kath. \u00d6ffentliche Bibliothek",
    "wof:placetype":"venue"
},
  "geometry": {"coordinates":[11.035134,49.976017],"type":"Point"}
}