{
  "type": "Feature",
  "properties": {
    "iso:country":"DE",
    "sg:address":"Am Sportplatz 13",
    "sg:city":"Neuzelle",
    "sg:phone":"+49 33652/243",
    "sg:postcode":"15898",
    "sg:province":"Brandenburg",
    "wof:name":"Sportst\u00e4ttenbetrieb",
    "wof:placetype":"venue"
},
  "geometry": {"coordinates":[14.64135,52.09148],"type":"Point"}
}