{
  "type": "Feature",
  "properties": {
    "iso:country":"DE",
    "sg:address":"Linge 7",
    "sg:city":"Wrixum",
    "sg:phone":"+49 4681/2200",
    "sg:postcode":"25938",
    "sg:province":"Schleswig-Holstein",
    "wof:name":"Otto Meister",
    "wof:placetype":"venue"
},
  "geometry": {"coordinates":[8.543143,54.690456],"type":"Point"}
}