{
  "type": "Feature",
  "properties": {
    "iso:country":"DE",
    "sg:address":"Postfach",
    "sg:city":"Dillingen",
    "sg:postcode":"89401",
    "sg:province":"Saarland",
    "wof:name":"Dillinger Montageberatungs-gmbh Saar",
    "wof:placetype":"venue"
},
  "geometry": {"coordinates":[10.4951,48.5812],"type":"Point"}
}