{
  "type": "Feature",
  "properties": {
    "iso:country":"DE",
    "sg:address":"Gangkofener Str. 30 b",
    "sg:city":"Frontenhausen",
    "sg:phone":"+49 8732/1050",
    "sg:postcode":"84160",
    "sg:province":"Bayern",
    "wof:name":"M. Und W. Getto",
    "wof:placetype":"venue"
},
  "geometry": {"coordinates":[12.528563,48.544552],"type":"Point"}
}