{
  "type": "Feature",
  "properties": {
    "iso:country":"DE",
    "sg:address":"Siegenburger Str. 13",
    "sg:city":"M\u00fcnchen",
    "sg:phone":"+49 89/7697303",
    "sg:postcode":"81373",
    "sg:province":"Bayern",
    "wof:name":"Anton L. Hottarek Fotogesch\u00e4ft",
    "wof:placetype":"venue"
},
  "geometry": {"coordinates":[11.5308704376,48.1282424927],"type":"Point"}
}