{
  "type": "Feature",
  "properties": {
    "iso:country":"DE",
    "sg:address":"Hinter der Deichstr. 5",
    "sg:city":"B\u00fcsum",
    "sg:phone":"+49 4834/2659",
    "sg:postcode":"25761",
    "sg:province":"Schleswig-Holstein",
    "wof:name":"Pension Wald",
    "wof:placetype":"venue"
},
  "geometry": {"coordinates":[8.8624248505,54.1313552856],"type":"Point"}
}