{
  "type": "Feature",
  "properties": {
    "iso:country":"DE",
    "sg:address":"Dorfstr. 43",
    "sg:city":"Golzow",
    "sg:phone":"+49 36458/32776",
    "sg:postcode":"16230",
    "sg:province":"Brandenburg",
    "wof:name":"Udo Pfotenhauer",
    "wof:placetype":"venue"
},
  "geometry": {"coordinates":[11.230634,50.898609],"type":"Point"}
}