{
  "type": "Feature",
  "properties": {
    "iso:country":"DE",
    "sg:address":"Lockh\u00fctter Str. 141a",
    "sg:city":"M\u00f6nchengladbach",
    "sg:phone":"+49 2161/963697",
    "sg:postcode":"41066",
    "sg:province":"Nordrhein-Westfalen",
    "wof:name":"Florian Maderspacher",
    "wof:placetype":"venue"
},
  "geometry": {"coordinates":[6.43941,51.230148],"type":"Point"}
}