{
  "type": "Feature",
  "properties": {
    "iso:country":"DE",
    "sg:address":"Blumenstr. 11",
    "sg:city":"M\u00f6nchsroth",
    "sg:phone":"+49 9853/386778",
    "sg:postcode":"91614",
    "sg:province":"Bayern",
    "wof:name":"Beda Dach- Und Fassadenbau Gmbh",
    "wof:placetype":"venue"
},
  "geometry": {"coordinates":[10.3505373001,49.0203704834],"type":"Point"}
}