{
  "type": "Feature",
  "properties": {
    "iso:country":"DE",
    "sg:address":"Lehmelweg 4",
    "sg:city":"Toppenstedt",
    "sg:phone":"+49 4173/6871",
    "sg:postcode":"21442",
    "sg:province":"Niedersachsen",
    "wof:name":"Gemeindearchiv",
    "wof:placetype":"venue"
},
  "geometry": {"coordinates":[10.121391,53.265392],"type":"Point"}
}