{
  "type": "Feature",
  "properties": {
    "iso:country":"DE",
    "sg:address":"Am Neuhof 25",
    "sg:city":"Schindhard",
    "sg:phone":"+49 6391/3564",
    "sg:postcode":"66996",
    "sg:province":"Rheinland-Pfalz",
    "wof:name":"Kurt Helfrich Steuerbevollm\u00e4chtigter",
    "wof:placetype":"venue"
},
  "geometry": {"coordinates":[7.8089752197,49.1402359009],"type":"Point"}
}