{
  "type": "Feature",
  "properties": {
    "iso:country":"DE",
    "sg:address":"Multring 17",
    "sg:city":"Weinheim",
    "sg:phone":"+49 6201/61492",
    "sg:postcode":"69469",
    "sg:province":"Baden-W\u00fcrttemberg",
    "wof:name":"H. Lowack Ingenieur",
    "wof:placetype":"venue"
},
  "geometry": {"coordinates":[8.65188694,49.5463752747],"type":"Point"}
}