{
  "type": "Feature",
  "properties": {
    "iso:country":"DE",
    "sg:address":"Lorscher Str. 50 a",
    "sg:city":"Viernheim",
    "sg:phone":"+49 6204/4458",
    "sg:postcode":"68519",
    "sg:province":"Hessen",
    "wof:name":"Gerd Und Christa Flessner",
    "wof:placetype":"venue"
},
  "geometry": {"coordinates":[8.5773763657,49.5428619385],"type":"Point"}
}