{
  "type": "Feature",
  "properties": {
    "iso:country":"DE",
    "sg:address":"Querstr. 25",
    "sg:city":"Ahlen",
    "sg:phone":"+49 2382/73994",
    "sg:postcode":"59229",
    "sg:province":"Nordrhein-Westfalen",
    "wof:name":"U. Driemeier Ingenieur",
    "wof:placetype":"venue"
},
  "geometry": {"coordinates":[7.8957548141,51.7589035034],"type":"Point"}
}