{
  "type": "Feature",
  "properties": {
    "iso:country":"DE",
    "sg:address":"Jonas-Elkan-Weg 8",
    "sg:city":"Hamminkeln",
    "sg:phone":"+49 2856/888",
    "sg:postcode":"46499",
    "sg:province":"Nordrhein-Westfalen",
    "wof:name":"Heinrich Zurm\u00fchlen",
    "wof:placetype":"venue"
},
  "geometry": {"coordinates":[6.679857,51.727039],"type":"Point"}
}