{
  "type": "Feature",
  "properties": {
    "iso:country":"DE",
    "sg:address":"Aystettstr. 7",
    "sg:city":"Frankfurt",
    "sg:phone":"+49 69/591025",
    "sg:postcode":"60322",
    "sg:province":"Hessen",
    "wof:name":"Comet Liegenschafts- Verwalt. Und Bau Gmbh",
    "wof:placetype":"venue"
},
  "geometry": {"coordinates":[8.677237,50.128845],"type":"Point"}
}