{
  "type": "Feature",
  "properties": {
    "iso:country":"DE",
    "sg:address":"Dorfstr. 1",
    "sg:city":"Egglham",
    "sg:phone":"+49 8543/1036",
    "sg:postcode":"84385",
    "sg:province":"Bayern",
    "wof:name":"Karl Dobler",
    "wof:placetype":"venue"
},
  "geometry": {"coordinates":[13.072013855,48.5143051147],"type":"Point"}
}