{
  "type": "Feature",
  "properties": {
    "iso:country":"DE",
    "sg:address":"Harlachener Str. 15",
    "sg:city":"W\u00f6rth",
    "sg:phone":"+49 8121/46195",
    "sg:postcode":"85457",
    "sg:province":"Bayern",
    "wof:name":"A. Steindl",
    "wof:placetype":"venue"
},
  "geometry": {"coordinates":[11.8807926178,48.2341957092],"type":"Point"}
}