{
  "type": "Feature",
  "properties": {
    "iso:country":"DE",
    "sg:address":"Bernsdorfer Str. 92",
    "sg:city":"Chemnitz",
    "sg:phone":"+49 371/55252",
    "sg:postcode":"09126",
    "sg:province":"Sachsen",
    "wof:name":"Carsten Fritsch",
    "wof:placetype":"venue"
},
  "geometry": {"coordinates":[12.9379415512,50.8183441162],"type":"Point"}
}