{
  "type": "Feature",
  "properties": {
    "iso:country":"DE",
    "sg:address":"Stiegelstr. 6",
    "sg:city":"Limburg",
    "sg:phone":"+49 6431/973853",
    "sg:postcode":"65551",
    "sg:province":"Hessen",
    "wof:name":"Heinrich Von Kleist",
    "wof:placetype":"venue"
},
  "geometry": {"coordinates":[8.1203975677,50.3752632141],"type":"Point"}
}