{
  "type": "Feature",
  "properties": {
    "iso:country":"DE",
    "sg:address":"Max-Planck-Str. 3",
    "sg:city":"Stuhr",
    "sg:postcode":"28816",
    "sg:province":"Niedersachsen",
    "wof:name":"H.-j. Herbst Beteiligungs- Gmbh",
    "wof:placetype":"venue"
},
  "geometry": {"coordinates":[8.767122,53.02166],"type":"Point"}
}