{
  "type": "Feature",
  "properties": {
    "iso:country":"DE",
    "sg:address":"Nu\u00dfallee 11 a",
    "sg:city":"Hanau",
    "sg:phone":"+49 6181/252295",
    "sg:postcode":"63450",
    "sg:province":"Hessen",
    "wof:name":"Wolfram Hildebrandt Rechtsanwalt",
    "wof:placetype":"venue"
},
  "geometry": {"coordinates":[8.9096698761,50.1345443726],"type":"Point"}
}