{
  "type": "Feature",
  "properties": {
    "iso:country":"DE",
    "sg:address":"Prozessionsweg 14",
    "sg:city":"Molbergen",
    "sg:phone":"+49 4475/236",
    "sg:postcode":"49696",
    "sg:province":"Niedersachsen",
    "wof:name":"Heinrich Koopmann",
    "wof:placetype":"venue"
},
  "geometry": {"coordinates":[7.9181637764,52.8565597534],"type":"Point"}
}