{
  "type": "Feature",
  "properties": {
    "iso:country":"DE",
    "sg:address":"Werniger\u00f6der Str. 1",
    "sg:city":"Veckenstedt",
    "sg:phone":"+49 39451/4715",
    "sg:postcode":"38871",
    "sg:province":"Sachsen-Anhalt",
    "wof:name":"F. Vogs",
    "wof:placetype":"venue"
},
  "geometry": {"coordinates":[10.73413,51.901081],"type":"Point"}
}