{
  "type": "Feature",
  "properties": {
    "iso:country":"DE",
    "sg:address":"Daniel-Sch\u00fcrmann-Str. 3",
    "sg:city":"Remscheid",
    "sg:phone":"+49 2191/21670",
    "sg:postcode":"42853",
    "sg:province":"Nordrhein-Westfalen",
    "wof:name":"Ursula Birkenbeul",
    "wof:placetype":"venue"
},
  "geometry": {"coordinates":[7.188724041,51.1797866821],"type":"Point"}
}