{
  "type": "Feature",
  "properties": {
    "iso:country":"DE",
    "sg:address":"Gothaer Str. 20",
    "sg:city":"Erfurt",
    "sg:phone":"+49 361/2250027",
    "sg:postcode":"99094",
    "sg:province":"Th\u00fcringen",
    "wof:name":"Selection-fitness-studio Gbr",
    "wof:placetype":"venue"
},
  "geometry": {"coordinates":[11.0102996826,50.9711112976],"type":"Point"}
}