{
  "type": "Feature",
  "properties": {
    "iso:country":"DE",
    "sg:address":"Alte Weinstr. 2",
    "sg:city":"Weinstadt",
    "sg:phone":"+49 7151/62262",
    "sg:postcode":"71384",
    "sg:province":"Baden-W\u00fcrttemberg",
    "wof:name":"Dieter Schmid",
    "wof:placetype":"venue"
},
  "geometry": {"coordinates":[9.369252,48.779449],"type":"Point"}
}