{
  "type": "Feature",
  "properties": {
    "iso:country":"DE",
    "sg:address":"Am Fuchsbau 9",
    "sg:city":"Niedernhausen",
    "sg:phone":"+49 6127/967720",
    "sg:postcode":"65527",
    "sg:province":"Hessen",
    "wof:name":"B\u00fcrotechnik Renner Gmbh",
    "wof:placetype":"venue"
},
  "geometry": {"coordinates":[8.3141536713,50.1703872681],"type":"Point"}
}