{
  "type": "Feature",
  "properties": {
    "iso:country":"DE",
    "sg:address":"Kurt-Bennewitz-Str. 44",
    "sg:city":"Eilenburg",
    "sg:phone":"+49 3423/603502",
    "sg:postcode":"04838",
    "sg:province":"Sachsen",
    "wof:name":"Hannelore Pr\u00fcfrock",
    "wof:placetype":"venue"
},
  "geometry": {"coordinates":[12.619685173,51.4465408325],"type":"Point"}
}