{
  "type": "Feature",
  "properties": {
    "iso:country":"DE",
    "sg:address":"Rankenstr. 70",
    "sg:city":"Zirndorf",
    "sg:phone":"+49 9127/7157",
    "sg:postcode":"90513",
    "sg:province":"Bayern",
    "wof:name":"Synergethics Ges. F\u00fcr Progessives Klinisches",
    "wof:placetype":"venue"
},
  "geometry": {"coordinates":[10.9016017914,49.426738739],"type":"Point"}
}