{
  "type": "Feature",
  "properties": {
    "iso:country":"DE",
    "sg:address":"Vinckestr. 32",
    "sg:city":"WerL",
    "sg:phone":"+49 2922/909250",
    "sg:postcode":"59457",
    "sg:province":"Nordrhein-Westfalen",
    "wof:name":"Hhimmobilien",
    "wof:placetype":"venue"
},
  "geometry": {"coordinates":[7.966878,51.554016],"type":"Point"}
}