{
  "type": "Feature",
  "properties": {
    "iso:country":"DE",
    "sg:address":"Friedrich-Wilhelm-Str. 96",
    "sg:city":"Minden",
    "sg:phone":"+49 571/31734",
    "sg:postcode":"32423",
    "sg:province":"Nordrhein-Westfalen",
    "wof:name":"Imbi\u00df R. Willharms",
    "wof:placetype":"venue"
},
  "geometry": {"coordinates":[8.9342947006,52.3028068542],"type":"Point"}
}