{
  "type": "Feature",
  "properties": {
    "iso:country":"DE",
    "sg:address":"Am Burdiek 25",
    "sg:city":"D\u00fclmen",
    "sg:phone":"+49 2594/5457",
    "sg:postcode":"48249",
    "sg:province":"Nordrhein-Westfalen",
    "wof:name":"Henschke D\u00e4mmputz Verwaltungs Gmbh",
    "wof:placetype":"venue"
},
  "geometry": {"coordinates":[7.2976660728,51.8214912415],"type":"Point"}
}