{
  "type": "Feature",
  "properties": {
    "iso:country":"DE",
    "sg:address":"Martinstr. 6",
    "sg:city":"Leipzig",
    "sg:phone":"+49 341/6880280",
    "sg:postcode":"04318",
    "sg:province":"Sachsen",
    "wof:name":"Torsten Rabe",
    "wof:placetype":"venue"
},
  "geometry": {"coordinates":[12.4124116898,51.3341255188],"type":"Point"}
}