{
  "type": "Feature",
  "properties": {
    "iso:country":"DE",
    "sg:address":"Cusanusstr. 4",
    "sg:city":"Bernkastel-Kues",
    "sg:phone":"+49 6531/8385",
    "sg:postcode":"54470",
    "sg:province":"Rheinland-Pfalz",
    "wof:name":"Annette Neuberger Krankengymnastin",
    "wof:placetype":"venue"
},
  "geometry": {"coordinates":[7.070219,49.916786],"type":"Point"}
}