{
  "type": "Feature",
  "properties": {
    "iso:country":"DE",
    "sg:address":"Am Burgblick 1",
    "sg:city":"Schw\u00e4bisch Gm\u00fcnd",
    "sg:phone":"+49 7171/4616",
    "sg:postcode":"73529",
    "sg:province":"Baden-W\u00fcrttemberg",
    "wof:name":"X. Herkommer",
    "wof:placetype":"venue"
},
  "geometry": {"coordinates":[9.792717,48.774593],"type":"Point"}
}