{
  "type": "Feature",
  "properties": {
    "iso:country":"DE",
    "sg:address":"Hauptstr. 53",
    "sg:city":"Frielendorf",
    "sg:phone":"+49 5684/317",
    "sg:postcode":"34621",
    "sg:province":"Hessen",
    "wof:name":"Apotheke Frielendorf Fritz-eckhard Avenarius",
    "wof:placetype":"venue"
},
  "geometry": {"coordinates":[9.326164,50.975254],"type":"Point"}
}