{
  "type": "Feature",
  "properties": {
    "iso:country":"DE",
    "sg:address":"Kapellenstr. 31c",
    "sg:city":"Graben-Neudorf",
    "sg:phone":"+49 7255/2892",
    "sg:postcode":"76676",
    "sg:province":"Baden-W\u00fcrttemberg",
    "wof:name":"A. Schnetzer",
    "wof:placetype":"venue"
},
  "geometry": {"coordinates":[8.4990921021,49.1750907898],"type":"Point"}
}