{
  "type": "Feature",
  "properties": {
    "iso:country":"DE",
    "sg:address":"Schoenebecker Platz 11 Barmen",
    "sg:city":"Wuppertal",
    "sg:phone":"+49 4920/25620",
    "sg:postcode":"42283",
    "sg:province":"Nordrhein-Westfalen",
    "wof:name":"Peter Holzrichter Gmbh",
    "wof:placetype":"venue"
},
  "geometry": {"coordinates":[7.19655,51.271561],"type":"Point"}
}