{
  "type": "Feature",
  "properties": {
    "iso:country":"DE",
    "sg:address":"Gallusstr. 39",
    "sg:city":"L\u00f6ffingen",
    "sg:phone":"+49 7654/7011",
    "sg:postcode":"79843",
    "sg:province":"Baden-W\u00fcrttemberg",
    "wof:name":"Bernd W. Kern Heilpraktiker",
    "wof:placetype":"venue"
},
  "geometry": {"coordinates":[8.3399333954,47.8758926392],"type":"Point"}
}