{
  "type": "Feature",
  "properties": {
    "iso:country":"DE",
    "sg:address":"Wolbecke 11",
    "sg:city":"Lennestadt",
    "sg:phone":"+49 2721/84528",
    "sg:postcode":"57368",
    "sg:province":"Nordrhein-Westfalen",
    "wof:name":"D. Wolter",
    "wof:placetype":"venue"
},
  "geometry": {"coordinates":[8.0799207687,51.1286392212],"type":"Point"}
}