{
  "type": "Feature",
  "properties": {
    "iso:country":"DE",
    "sg:address":"Heinrich-Hertz-Str. 9",
    "sg:city":"Bargteheide",
    "sg:phone":"+49 4945/322000",
    "sg:postcode":"22941",
    "sg:province":"Schleswig-Holstein",
    "wof:name":"Infoplus Gmbh & Co. Kg",
    "wof:placetype":"venue"
},
  "geometry": {"coordinates":[10.2713003159,53.7201080322],"type":"Point"}
}