{
  "type": "Feature",
  "properties": {
    "iso:country":"DE",
    "sg:address":"Siegfriedstr. 17",
    "sg:city":"D\u00fcsseldorf",
    "sg:phone":"+49 211/5581538",
    "sg:postcode":"40549",
    "sg:province":"Nordrhein-Westfalen",
    "wof:name":"Comcon Unternehmens- Beratungs Gmbh",
    "wof:placetype":"venue"
},
  "geometry": {"coordinates":[6.74376297,51.2306060791],"type":"Point"}
}