{
  "type": "Feature",
  "properties": {
    "iso:country":"DE",
    "sg:address":"Kaiserstr. 31",
    "sg:city":"Morschheim",
    "sg:phone":"+49 6352/4464",
    "sg:postcode":"67294",
    "sg:province":"Rheinland-Pfalz",
    "wof:name":"Ottmar Mandler",
    "wof:placetype":"venue"
},
  "geometry": {"coordinates":[8.024193,49.696205],"type":"Point"}
}