{
  "type": "Feature",
  "properties": {
    "iso:country":"DE",
    "sg:address":"Jacobsenweg 18",
    "sg:city":"Hamburg",
    "sg:phone":"+49 40/543954",
    "sg:postcode":"22525",
    "sg:province":"Hamburg",
    "wof:name":"Hansa Press-u. Maschinenbau Gmbh",
    "wof:placetype":"venue"
},
  "geometry": {"coordinates":[9.9153842926,53.594329834],"type":"Point"}
}