{
  "type": "Feature",
  "properties": {
    "iso:country":"DE",
    "sg:address":"Gewerbestra\u00dfe 11",
    "sg:city":"N\u00f6rdlingen",
    "sg:phone":"+49 9081",
    "sg:postcode":"86720",
    "sg:province":"Bayern",
    "wof:name":"Pfannen-valeri",
    "wof:placetype":"venue"
},
  "geometry": {"coordinates":[10.5134439468,48.8592567444],"type":"Point"}
}