{
  "type": "Feature",
  "properties": {
    "iso:country":"DE",
    "sg:address":"Bertolt-Brecht-Str. 11",
    "sg:city":"Hiddenhausen",
    "sg:phone":"+49 5221/96730",
    "sg:postcode":"32120",
    "sg:province":"Nordrhein-Westfalen",
    "wof:name":"Haus Stephanus",
    "wof:placetype":"venue"
},
  "geometry": {"coordinates":[8.640279,52.155094],"type":"Point"}
}