{
  "type": "Feature",
  "properties": {
    "iso:country":"DE",
    "sg:address":"Bahnhofstr. 224",
    "sg:city":"Karben",
    "sg:phone":"+49 6039/6290",
    "sg:postcode":"61184",
    "sg:province":"Hessen",
    "wof:name":"Pizzeria La Giara",
    "wof:placetype":"venue"
},
  "geometry": {"coordinates":[8.7521047592,50.2332191467],"type":"Point"}
}