{
  "type": "Feature",
  "properties": {
    "iso:country":"DE",
    "sg:address":"Fischtorplatz 23",
    "sg:city":"Mainz",
    "sg:phone":"+49 6131/672085",
    "sg:postcode":"55116",
    "sg:province":"Rheinland-Pfalz",
    "wof:name":"Deutsche Lesegesellschaft",
    "wof:placetype":"venue"
},
  "geometry": {"coordinates":[8.2780752182,50.0001907349],"type":"Point"}
}