{
  "type": "Feature",
  "properties": {
    "iso:country":"DE",
    "sg:address":"Sch\u00f6nfelder Str. 17",
    "sg:city":"Dresden",
    "sg:phone":"+49 351/2687530",
    "sg:postcode":"01099",
    "sg:province":"Sachsen",
    "wof:name":"R. Tsch\u00f6pe",
    "wof:placetype":"venue"
},
  "geometry": {"coordinates":[13.7594633102,51.0665397644],"type":"Point"}
}