{
  "type": "Feature",
  "properties": {
    "iso:country":"DE",
    "sg:address":"G\u00fctersloher Str. 50",
    "sg:city":"Steinhagen",
    "sg:phone":"+49 5204/3853",
    "sg:postcode":"33803",
    "sg:province":"Nordrhein-Westfalen",
    "wof:name":"Wilfried Hermbecker",
    "wof:placetype":"venue"
},
  "geometry": {"coordinates":[8.348049,51.983257],"type":"Point"}
}