{
  "type": "Feature",
  "properties": {
    "iso:country":"DE",
    "sg:address":"Bahnhofstr. 16",
    "sg:city":"Hamm",
    "sg:phone":"+49 2381/921210",
    "sg:postcode":"59065",
    "sg:province":"Nordrhein-Westfalen",
    "wof:name":"Amid Firmen-versicherungs- Makler Gmbh",
    "wof:placetype":"venue"
},
  "geometry": {"coordinates":[7.8113870621,51.6787261963],"type":"Point"}
}