{
  "type": "Feature",
  "properties": {
    "iso:country":"DE",
    "sg:address":"Marchstr. 2",
    "sg:city":"B\u00f6tzingen",
    "sg:phone":"+49 7663",
    "sg:postcode":"79268",
    "sg:province":"Baden-W\u00fcrttemberg",
    "wof:name":"Atc - Autoteile",
    "wof:placetype":"venue"
},
  "geometry": {"coordinates":[7.7265701294,48.0774803162],"type":"Point"}
}