{
  "type": "Feature",
  "properties": {
    "iso:country":"DE",
    "sg:address":"Kleinbahnring 15",
    "sg:city":"Ense",
    "sg:phone":"+49 2938/1088",
    "sg:postcode":"59469",
    "sg:province":"Nordrhein-Westfalen",
    "wof:name":"Gerhard Wetzel Tiefbau Gmbh",
    "wof:placetype":"venue"
},
  "geometry": {"coordinates":[7.990807,51.497402],"type":"Point"}
}