{
  "type": "Feature",
  "properties": {
    "iso:country":"DE",
    "sg:address":"Lemf\u00f6rder Str. 43",
    "sg:city":"Rahden",
    "sg:phone":"+49 5771/2268",
    "sg:postcode":"32369",
    "sg:province":"Nordrhein-Westfalen",
    "wof:name":"Museumshof",
    "wof:placetype":"venue"
},
  "geometry": {"coordinates":[8.599733,52.438301],"type":"Point"}
}