{
  "type": "Feature",
  "properties": {
    "iso:country":"DE",
    "sg:address":"Ravensburger Str. 5",
    "sg:city":"Bergatreute",
    "sg:phone":"+49 7527/4653",
    "sg:postcode":"88368",
    "sg:province":"Baden-W\u00fcrttemberg",
    "wof:name":"Marien-apotheke",
    "wof:placetype":"venue"
},
  "geometry": {"coordinates":[9.749079,47.848316],"type":"Point"}
}