{
  "type": "Feature",
  "properties": {
    "iso:country":"DE",
    "sg:address":"Gasstr. 32",
    "sg:city":"Preetz",
    "sg:phone":"+49 4342/4959",
    "sg:postcode":"24211",
    "sg:province":"Schleswig-Holstein",
    "wof:name":"L\u00f6schner Gmbh",
    "wof:placetype":"venue"
},
  "geometry": {"coordinates":[10.2775211334,54.2310752869],"type":"Point"}
}