{
  "type": "Feature",
  "properties": {
    "iso:country":"DE",
    "sg:address":"Bahnstr. 13",
    "sg:city":"Traben-Trarbach",
    "sg:phone":"+49 6541/6639",
    "sg:postcode":"56841",
    "sg:province":"Rheinland-Pfalz",
    "wof:name":"Helmut Malk",
    "wof:placetype":"venue"
},
  "geometry": {"coordinates":[7.1151599884,49.9516220093],"type":"Point"}
}