{
  "type": "Feature",
  "properties": {
    "iso:country":"DE",
    "sg:address":"Brennenheide 55",
    "sg:city":"Werther",
    "sg:phone":"+49 5203/7281",
    "sg:postcode":"33824",
    "sg:province":"Nordrhein-Westfalen",
    "wof:name":"Norbert Schwarze",
    "wof:placetype":"venue"
},
  "geometry": {"coordinates":[8.37149,52.109299],"type":"Point"}
}