{
  "type": "Feature",
  "properties": {
    "iso:country":"DE",
    "sg:address":"F\u00fcllerstr. 63",
    "sg:city":"Frankfurt",
    "sg:phone":"+49 69/528625",
    "sg:postcode":"60431",
    "sg:province":"Hessen",
    "wof:name":"Steppat Gmbh",
    "wof:placetype":"venue"
},
  "geometry": {"coordinates":[8.649996,50.141739],"type":"Point"}
}