{
  "type": "Feature",
  "properties": {
    "iso:country":"DE",
    "sg:address":"L\u00fcssumer Kamp 12",
    "sg:city":"Bremen",
    "sg:phone":"+49 421/605675",
    "sg:postcode":"28779",
    "sg:province":"Bremen",
    "wof:name":"J. Sonnberg",
    "wof:placetype":"venue"
},
  "geometry": {"coordinates":[8.5637578964,53.1874961853],"type":"Point"}
}