{
  "type": "Feature",
  "properties": {
    "iso:country":"DE",
    "sg:address":"Kastanienallee 3",
    "sg:city":"Severin",
    "sg:phone":"+49 38728/3060",
    "sg:postcode":"19374",
    "sg:province":"Mecklenburg-Vorpommern",
    "wof:name":"Mecklenburger Landpute Schlachterei Gmbh",
    "wof:placetype":"venue"
},
  "geometry": {"coordinates":[11.77342,53.502029],"type":"Point"}
}