{
  "type": "Feature",
  "properties": {
    "iso:country":"DE",
    "sg:address":"Keilberger Hauptstr. 4",
    "sg:city":"Regensburg",
    "sg:phone":"+49 941/47751",
    "sg:postcode":"93055",
    "sg:province":"Bayern",
    "wof:name":"Erna Christoph Hebamme",
    "wof:placetype":"venue"
},
  "geometry": {"coordinates":[12.157221,49.038914],"type":"Point"}
}