{
  "type": "Feature",
  "properties": {
    "iso:country":"DE",
    "sg:address":"Schweppenkamp 2",
    "sg:city":"Goslar",
    "sg:phone":"+49 5321/37760",
    "sg:postcode":"38644",
    "sg:province":"Niedersachsen",
    "wof:name":"Combigo Verlag Gmbh",
    "wof:placetype":"venue"
},
  "geometry": {"coordinates":[10.4206285477,51.9346656799],"type":"Point"}
}