{
  "type": "Feature",
  "properties": {
    "iso:country":"DE",
    "sg:address":"Teichstr. 5",
    "sg:city":"Ronnenberg",
    "sg:phone":"+49 5109/52970",
    "sg:postcode":"30952",
    "sg:province":"Niedersachsen",
    "wof:name":"G\u00e4stehof Schild",
    "wof:placetype":"venue"
},
  "geometry": {"coordinates":[9.6759004593,52.3051643372],"type":"Point"}
}