{
  "type": "Feature",
  "properties": {
    "iso:country":"DE",
    "sg:address":"Freiherr-vom-Stein-Str. 20",
    "sg:city":"Urmitz",
    "sg:phone":"+49 2630/7777",
    "sg:postcode":"56220",
    "sg:province":"Rheinland-Pfalz",
    "wof:name":"Helf Gmbh",
    "wof:placetype":"venue"
},
  "geometry": {"coordinates":[7.51706,50.41404],"type":"Point"}
}