{
  "type": "Feature",
  "properties": {
    "iso:country":"DE",
    "sg:address":"Oststr. 29",
    "sg:city":"Breitenworbis",
    "sg:phone":"+49 36074/94478",
    "sg:postcode":"37339",
    "sg:province":"Th\u00fcringen",
    "wof:name":"Handt & Wiegmann Gmbh",
    "wof:placetype":"venue"
},
  "geometry": {"coordinates":[10.432333,51.413666],"type":"Point"}
}