{
  "type": "Feature",
  "properties": {
    "iso:country":"DE",
    "sg:address":"Gutenbergstr. 3 a",
    "sg:city":"Hemmingen",
    "sg:phone":"+49 511/421555",
    "sg:postcode":"30966",
    "sg:province":"Niedersachsen",
    "wof:name":"Kaltwasser Ohg Elektroinstallation",
    "wof:placetype":"venue"
},
  "geometry": {"coordinates":[9.723753,52.322254],"type":"Point"}
}