{
  "type": "Feature",
  "properties": {
    "iso:country":"DE",
    "sg:address":"Marschweg 96",
    "sg:city":"Oldenburg",
    "sg:phone":"+49 441/501092",
    "sg:postcode":"26131",
    "sg:province":"Niedersachsen",
    "wof:name":"D.s.o. Datensysteme Gmbh",
    "wof:placetype":"venue"
},
  "geometry": {"coordinates":[8.2046957016,53.1262130737],"type":"Point"}
}