{
  "type": "Feature",
  "properties": {
    "iso:country":"DE",
    "sg:address":"M\u00fchlenstr. 28",
    "sg:city":"Neukirchen-Vluyn",
    "sg:phone":"+49 2845/3648",
    "sg:postcode":"47506",
    "sg:province":"Nordrhein-Westfalen",
    "wof:name":"Tillmann Nepicks & Sohn Gmbh",
    "wof:placetype":"venue"
},
  "geometry": {"coordinates":[6.521504879,51.469745636],"type":"Point"}
}