{
  "type": "Feature",
  "properties": {
    "iso:country":"DE",
    "sg:address":"Kirchstr. 11",
    "sg:city":"Lohsa",
    "sg:phone":"+49 35724/50451",
    "sg:postcode":"02999",
    "sg:province":"Sachsen",
    "wof:name":"Walter Loos",
    "wof:placetype":"venue"
},
  "geometry": {"coordinates":[14.403555,51.383495],"type":"Point"}
}