{
  "type": "Feature",
  "properties": {
    "iso:country":"DE",
    "sg:address":"Erlenstr. 8",
    "sg:city":"Dresden",
    "sg:phone":"+49 351/8046960",
    "sg:postcode":"01097",
    "sg:province":"Sachsen",
    "wof:name":"R. Broy Anlageberater",
    "wof:placetype":"venue"
},
  "geometry": {"coordinates":[13.7476816177,51.0737304688],"type":"Point"}
}