{
  "type": "Feature",
  "properties": {
    "iso:country":"DE",
    "sg:address":"Christian-Hammerschmidt-Str. 5",
    "sg:city":"Tettau",
    "sg:phone":"+49 9269/9810",
    "sg:postcode":"96355",
    "sg:province":"Bayern",
    "wof:name":"Poly Tech Kunststoff Gmbh",
    "wof:placetype":"venue"
},
  "geometry": {"coordinates":[11.259515,50.468166],"type":"Point"}
}