{
  "type": "Feature",
  "properties": {
    "iso:country":"DE",
    "sg:address":"Partnachauenstr. 22",
    "sg:city":"Garmisch-Partenkirchen",
    "sg:phone":"+49 8821/4643",
    "sg:postcode":"82467",
    "sg:province":"Bayern",
    "wof:name":"Heinrich Hellweger",
    "wof:placetype":"venue"
},
  "geometry": {"coordinates":[11.104366,47.488293],"type":"Point"}
}