{
  "type": "Feature",
  "properties": {
    "iso:country":"DE",
    "sg:address":"Kocherstr. 21",
    "sg:city":"Ludwigsburg",
    "sg:phone":"+49 7141/55902",
    "sg:postcode":"71642",
    "sg:province":"Baden-W\u00fcrttemberg",
    "wof:name":"Werner Nagel Architekt",
    "wof:placetype":"venue"
},
  "geometry": {"coordinates":[9.207498,48.912491],"type":"Point"}
}