{
  "type": "Feature",
  "properties": {
    "iso:country":"DE",
    "sg:address":"Halbergstr. 53",
    "sg:city":"Saarbr\u00fccken",
    "sg:phone":"+49 681/61788",
    "sg:postcode":"66121",
    "sg:province":"Saarland",
    "wof:name":"Karl-heinz Gutekunst",
    "wof:placetype":"venue"
},
  "geometry": {"coordinates":[7.0166931152,49.2304916382],"type":"Point"}
}