{
  "type": "Feature",
  "properties": {
    "iso:country":"DE",
    "sg:address":"Im Pfarrfeld 29",
    "sg:city":"Neunkirchen",
    "sg:phone":"+49 2735/2725",
    "sg:postcode":"57290",
    "sg:province":"Nordrhein-Westfalen",
    "wof:name":"Horst Feuring",
    "wof:placetype":"venue"
},
  "geometry": {"coordinates":[8.0091218948,50.7859611511],"type":"Point"}
}