{
  "type": "Feature",
  "properties": {
    "iso:country":"DE",
    "sg:address":"Theodor-Althoff-Str. 5",
    "sg:city":"Essen",
    "sg:phone":"+49 201/7690",
    "sg:postcode":"45133",
    "sg:province":"Nordrhein-Westfalen",
    "wof:name":"Scandic Crown Hotel Essen",
    "wof:placetype":"venue"
},
  "geometry": {"coordinates":[6.9814720154,51.4174575806],"type":"Point"}
}