{
  "type": "Feature",
  "properties": {
    "iso:country":"DE",
    "sg:address":"Elsenheimerstr. 15/II",
    "sg:city":"M\u00fcnchen",
    "sg:phone":"+49 89/5470900",
    "sg:postcode":"80687",
    "sg:province":"Bayern",
    "wof:name":"Schwarz Hempe Und Collegen Gmbh",
    "wof:placetype":"venue"
},
  "geometry": {"coordinates":[11.5082597733,48.1400184631],"type":"Point"}
}