{
  "type": "Feature",
  "properties": {
    "iso:country":"DE",
    "sg:address":"Gro\u00dfmarkthalle",
    "sg:city":"Frankfurt",
    "sg:phone":"+49 69/447804",
    "sg:postcode":"60314",
    "sg:province":"Hessen",
    "wof:name":"A. Weil Inh. Richard Fischer",
    "wof:placetype":"venue"
},
  "geometry": {"coordinates":[8.7211904526,50.1163215637],"type":"Point"}
}