{
  "type": "Feature",
  "properties": {
    "iso:country":"DE",
    "sg:address":"Celler Str. 18",
    "sg:city":"Hankensb\u00fcttel",
    "sg:phone":"+49 5832/1749",
    "sg:postcode":"29386",
    "sg:province":"Niedersachsen",
    "wof:name":"E. Bredow",
    "wof:placetype":"venue"
},
  "geometry": {"coordinates":[10.598645,52.728203],"type":"Point"}
}