{
  "type": "Feature",
  "properties": {
    "iso:country":"DE",
    "sg:address":"Pablo-Neruda-Str. 2-4",
    "sg:city":"Berlin",
    "sg:phone":"+49 30/6516684",
    "sg:postcode":"12559",
    "sg:province":"Berlin",
    "wof:name":"Bibliothek",
    "wof:placetype":"venue"
},
  "geometry": {"coordinates":[13.587324,52.441216],"type":"Point"}
}