{
  "type": "Feature",
  "properties": {
    "iso:country":"DE",
    "sg:address":"Emmernstr. 6",
    "sg:city":"Hameln",
    "sg:phone":"+49 5151/3120",
    "sg:postcode":"31785",
    "sg:province":"Niedersachsen",
    "wof:name":"Balkan Grill",
    "wof:placetype":"venue"
},
  "geometry": {"coordinates":[9.3576850891,52.1048965454],"type":"Point"}
}