{
  "type": "Feature",
  "properties": {
    "iso:country":"DE",
    "sg:address":"Schlo\u00dfstr. 23",
    "sg:city":"Ilvesheim",
    "sg:phone":"+49 4962/149690",
    "sg:postcode":"68549",
    "sg:province":"Baden-W\u00fcrttemberg",
    "wof:name":"Schlo\u00dfschule Ilvesheim Staatliche Schule F\u00dcr Blinde Und Sehbehinderte Mit Internat",
    "wof:placetype":"venue"
},
  "geometry": {"coordinates":[8.567717,49.472198],"type":"Point"}
}