{
  "type": "Feature",
  "properties": {
    "iso:country":"DE",
    "sg:address":"Leipziger Str. 7",
    "sg:city":"Sprockh\u00f6vel",
    "sg:phone":"+49 2324/73542",
    "sg:postcode":"45549",
    "sg:province":"Nordrhein-Westfalen",
    "wof:name":"Familienhilfe E. V. Sprockh\u00f6vel",
    "wof:placetype":"venue"
},
  "geometry": {"coordinates":[7.253262043,51.3635673523],"type":"Point"}
}