{
  "type": "Feature",
  "properties": {
    "iso:country":"DE",
    "sg:address":"Schulgasse 17",
    "sg:city":"Freyung",
    "sg:phone":"+49 8551/7059",
    "sg:postcode":"94078",
    "sg:province":"Bayern",
    "wof:name":"Franz Pr\u00f6bstl",
    "wof:placetype":"venue"
},
  "geometry": {"coordinates":[13.5465183258,48.8084220886],"type":"Point"}
}