{
  "type": "Feature",
  "properties": {
    "iso:country":"DE",
    "sg:address":"Bettengraben 9",
    "sg:city":"Lahnau",
    "sg:phone":"+49 6441/96074",
    "sg:postcode":"35633",
    "sg:province":"Hessen",
    "wof:name":"Eckardt & Partner",
    "wof:placetype":"venue"
},
  "geometry": {"coordinates":[8.575242,50.576965],"type":"Point"}
}