{
  "type": "Feature",
  "properties": {
    "iso:country":"DE",
    "sg:address":"Konrad-Wolf-Str. 77",
    "sg:city":"Berlin",
    "sg:phone":"+49 30/9758860",
    "sg:postcode":"13055",
    "sg:province":"Berlin",
    "wof:name":"Sport Hoppe",
    "wof:placetype":"venue"
},
  "geometry": {"coordinates":[13.481959,52.538799],"type":"Point"}
}