{
  "type": "Feature",
  "properties": {
    "iso:country":"DE",
    "sg:address":"Hauptstr. 222",
    "sg:city":"Bochum",
    "sg:phone":"+49 234/291511",
    "sg:postcode":"44892",
    "sg:province":"Nordrhein-Westfalen",
    "wof:name":"Lothar Kornfeld Grabdenkm\u00e4ler",
    "wof:placetype":"venue"
},
  "geometry": {"coordinates":[7.32336092,51.4700737],"type":"Point"}
}