{
  "type": "Feature",
  "properties": {
    "iso:country":"DE",
    "sg:address":"Johann-Strau\u00df-Str. 23b",
    "sg:city":"Kelkheim",
    "sg:phone":"+49 6195/73629",
    "sg:postcode":"65779",
    "sg:province":"Hessen",
    "wof:name":"Verotax Gmbh",
    "wof:placetype":"venue"
},
  "geometry": {"coordinates":[8.4572086334,50.1260566711],"type":"Point"}
}