{
  "type": "Feature",
  "properties": {
    "iso:country":"DE",
    "sg:address":"Hardtstr. 5",
    "sg:city":"Ansbach",
    "sg:phone":"+49 981/7677",
    "sg:postcode":"91522",
    "sg:province":"Bayern",
    "wof:name":"Union Zementlager Steinacker Gmbh",
    "wof:placetype":"venue"
},
  "geometry": {"coordinates":[10.5970420837,49.2635383606],"type":"Point"}
}