{
  "type": "Feature",
  "properties": {
    "iso:country":"DE",
    "sg:address":"Lindenstr. 26",
    "sg:city":"Altenriet",
    "sg:phone":"+49 7127/34434",
    "sg:postcode":"72657",
    "sg:province":"Baden-W\u00fcrttemberg",
    "wof:name":"G. Kehrer",
    "wof:placetype":"venue"
},
  "geometry": {"coordinates":[9.215057,48.588486],"type":"Point"}
}