{
  "type": "Feature",
  "properties": {
    "iso:country":"DE",
    "sg:address":"Am Wiesengrund 13",
    "sg:city":"Wiefelstede",
    "sg:phone":"+49 4402/6753",
    "sg:postcode":"26215",
    "sg:province":"Niedersachsen",
    "wof:name":"H. Von H\u00e4fen",
    "wof:placetype":"venue"
},
  "geometry": {"coordinates":[8.137674,53.229435],"type":"Point"}
}