{
  "type": "Feature",
  "properties": {
    "iso:country":"DE",
    "sg:address":"Goethestr. 17b",
    "sg:city":"Dippoldiswalde",
    "sg:postcode":"01744",
    "sg:province":"Sachsen",
    "wof:name":"D. Liebscher",
    "wof:placetype":"venue"
},
  "geometry": {"coordinates":[13.666448,50.902271],"type":"Point"}
}