{
  "type": "Feature",
  "properties": {
    "iso:country":"DE",
    "sg:address":"Neuh\u00e4user Str. 75",
    "sg:city":"Katzh\u00fctte",
    "sg:phone":"+49 36781/37655",
    "sg:postcode":"98746",
    "sg:province":"Th\u00fcringen",
    "wof:name":"U. Heinze",
    "wof:placetype":"venue"
},
  "geometry": {"coordinates":[11.057089,50.549652],"type":"Point"}
}