{
  "type": "Feature",
  "properties": {
    "iso:country":"DE",
    "sg:address":"Gerbereistr. 11",
    "sg:city":"Stromberg",
    "sg:phone":"+49 6724/527",
    "sg:postcode":"55442",
    "sg:province":"Rheinland-Pfalz",
    "wof:name":"Hugo Schleupen",
    "wof:placetype":"venue"
},
  "geometry": {"coordinates":[7.7715930939,49.9443778992],"type":"Point"}
}