{
  "type": "Feature",
  "properties": {
    "iso:country":"DE",
    "sg:address":"Alt Felgeleben 18",
    "sg:city":"Sch\u00f6nebeck",
    "sg:phone":"+49 3928/400191",
    "sg:postcode":"39218",
    "sg:province":"Sachsen-Anhalt",
    "wof:name":"Harald Knieling",
    "wof:placetype":"venue"
},
  "geometry": {"coordinates":[11.75347,51.999565],"type":"Point"}
}