{
  "type": "Feature",
  "properties": {
    "iso:country":"DE",
    "sg:address":"M\u00fcllers Weg 11",
    "sg:city":"Erfurt",
    "sg:postcode":"99092",
    "sg:province":"Th\u00fcringen",
    "wof:name":"Dombrink Fenster Und T\u00fcren Erfurt Vertrieb Und",
    "wof:placetype":"venue"
},
  "geometry": {"coordinates":[10.986756,50.999298],"type":"Point"}
}