{
  "type": "Feature",
  "properties": {
    "iso:country":"DE",
    "sg:address":"Mitteralmweg 31",
    "sg:city":"Rosenheim",
    "sg:phone":"+49 8031/67630",
    "sg:postcode":"83026",
    "sg:province":"Bayern",
    "wof:name":"Bernd Pusch Textilvertretung",
    "wof:placetype":"venue"
},
  "geometry": {"coordinates":[12.085565567,47.8245010376],"type":"Point"}
}