{
  "type": "Feature",
  "properties": {
    "iso:country":"DE",
    "sg:address":"Mohlstr. 1",
    "sg:city":"Stuttgart",
    "sg:phone":"+49 711/24895240",
    "sg:postcode":"70184",
    "sg:province":"Baden-W\u00fcrttemberg",
    "wof:name":"Karlheinz Stiegler",
    "wof:placetype":"venue"
},
  "geometry": {"coordinates":[9.189324,48.772377],"type":"Point"}
}