{
  "type": "Feature",
  "properties": {
    "iso:country":"DE",
    "sg:address":"Isaac-Fulda-Allee 3",
    "sg:city":"Mainz",
    "sg:phone":"+49 6131/3746022",
    "sg:postcode":"55124",
    "sg:province":"Rheinland-Pfalz",
    "wof:name":"Universit\u00e4t Koblenz-landau",
    "wof:placetype":"venue"
},
  "geometry": {"coordinates":[8.222175,49.994152],"type":"Point"}
}