{
  "type": "Feature",
  "properties": {
    "iso:country":"DE",
    "sg:address":"In der Witz 3",
    "sg:city":"Hofheim",
    "sg:phone":"+49 6192/929630",
    "sg:postcode":"65719",
    "sg:province":"Hessen",
    "wof:name":"Waffenring Hofheim Manfred Steuer",
    "wof:placetype":"venue"
},
  "geometry": {"coordinates":[8.4427614212,50.0859680176],"type":"Point"}
}