{
  "type": "Feature",
  "properties": {
    "iso:country":"DE",
    "sg:address":"Harztalstr. 19",
    "sg:city":"Miesbach",
    "sg:postcode":"83714",
    "sg:province":"Bayern",
    "wof:name":"Schlarb & Zingler Partnerschaft Steuer-",
    "wof:placetype":"venue"
},
  "geometry": {"coordinates":[11.8396987915,47.7848358154],"type":"Point"}
}