{
  "type": "Feature",
  "properties": {
    "iso:country":"DE",
    "sg:address":"Kreuzbergstr. 13/1",
    "sg:city":"Westerstetten",
    "sg:phone":"+49 4973/486076",
    "sg:postcode":"89198",
    "sg:province":"Baden-W\u00fcrttemberg",
    "wof:name":"Westerstetter Bank",
    "wof:placetype":"venue"
},
  "geometry": {"coordinates":[9.953044,48.521935],"type":"Point"}
}