{
  "type": "Feature",
  "properties": {
    "iso:country":"DE",
    "sg:address":"Blasl 1",
    "sg:city":"Schweitenkirchen",
    "sg:phone":"+49 8444/7267",
    "sg:postcode":"85301",
    "sg:province":"Bayern",
    "wof:name":"Georg Faltermeier",
    "wof:placetype":"venue"
},
  "geometry": {"coordinates":[11.613229,48.524906],"type":"Point"}
}