{
  "type": "Feature",
  "properties": {
    "iso:country":"DE",
    "sg:address":"Wallonenstr. 24",
    "sg:city":"Sch\u00f6nau",
    "sg:phone":"+49 6228/324",
    "sg:postcode":"69250",
    "sg:province":"Baden-W\u00fcrttemberg",
    "wof:name":"Karl J\u00fclg Steuerbevollm\u00e4chtigter",
    "wof:placetype":"venue"
},
  "geometry": {"coordinates":[8.8125753403,49.4387588501],"type":"Point"}
}