{
  "type": "Feature",
  "properties": {
    "iso:country":"DE",
    "sg:address":"Dellbr\u00fcck 15",
    "sg:city":"Bargenstedt",
    "sg:phone":"+49 4806/325",
    "sg:postcode":"25704",
    "sg:province":"Schleswig-Holstein",
    "wof:name":"Ernestine Dethlefsen Pflegeheim",
    "wof:placetype":"venue"
},
  "geometry": {"coordinates":[9.18208,54.099319],"type":"Point"}
}