{
  "type": "Feature",
  "properties": {
    "iso:country":"DE",
    "sg:address":"Zur Sasselbach 5",
    "sg:city":"V\u00f6hl",
    "sg:phone":"+49 5635/1044",
    "sg:postcode":"34516",
    "sg:province":"Hessen",
    "wof:name":"Paul Weyand",
    "wof:placetype":"venue"
},
  "geometry": {"coordinates":[8.873371,51.157696],"type":"Point"}
}