{
  "type": "Feature",
  "properties": {
    "iso:country":"DE",
    "sg:address":"Steinegger Str 19",
    "sg:city":"Tiefenbronn",
    "sg:phone":"+49 7234/790",
    "sg:postcode":"75233",
    "sg:province":"Baden-W\u00fcrttemberg",
    "wof:name":"Klaschka Gmbh & Co Kg",
    "wof:placetype":"venue"
},
  "geometry": {"coordinates":[8.8128099442,48.7965126038],"type":"Point"}
}