{
  "type": "Feature",
  "properties": {
    "iso:country":"DE",
    "sg:address":"Hauptstr. 28",
    "sg:city":"B\u00fcdingen",
    "sg:phone":"+49 6042/1601",
    "sg:postcode":"63654",
    "sg:province":"Hessen",
    "wof:name":"Radio Gilberg",
    "wof:placetype":"venue"
},
  "geometry": {"coordinates":[9.0291633606,50.2935638428],"type":"Point"}
}