{
  "type": "Feature",
  "properties": {
    "iso:country":"DE",
    "sg:address":"G\u00f6ttinger Str.",
    "sg:city":"Northeim",
    "sg:phone":"+49 5551/66841",
    "sg:postcode":"37154",
    "sg:province":"Niedersachsen",
    "wof:name":"Mac Donalds",
    "wof:placetype":"venue"
},
  "geometry": {"coordinates":[9.9921550751,51.7013053894],"type":"Point"}
}