{
  "type": "Feature",
  "properties": {
    "iso:country":"DE",
    "sg:address":"Schmiedestr. 35",
    "sg:city":"Wees",
    "sg:phone":"+49 4631/1219",
    "sg:postcode":"24999",
    "sg:province":"Schleswig-Holstein",
    "wof:name":"Siebdruck Oxb\u00fcll Torsten Munk",
    "wof:placetype":"venue"
},
  "geometry": {"coordinates":[9.5366401672,54.8080253601],"type":"Point"}
}