{
  "type": "Feature",
  "properties": {
    "iso:country":"DE",
    "sg:address":"Wolfgang-Wagner-Str. 15",
    "sg:city":"Glonn",
    "sg:phone":"+49 8093/4730",
    "sg:postcode":"85625",
    "sg:province":"Bayern",
    "wof:name":"Kath. \u00d6ffentliche Bibliothek Kath. Pfarramt",
    "wof:placetype":"venue"
},
  "geometry": {"coordinates":[11.867875,47.987534],"type":"Point"}
}