{
  "type": "Feature",
  "properties": {
    "iso:country":"DE",
    "sg:address":"Gruitener Weg 39",
    "sg:city":"Mettmann",
    "sg:phone":"+49 2104/15029",
    "sg:postcode":"40822",
    "sg:province":"Nordrhein-Westfalen",
    "wof:name":"Busreisen Hesselbein Gmbh",
    "wof:placetype":"venue"
},
  "geometry": {"coordinates":[6.985449791,51.2404594421],"type":"Point"}
}