{
  "type": "Feature",
  "properties": {
    "iso:country":"DE",
    "sg:address":"Hatzenturm 12",
    "sg:city":"Wolpertswende",
    "sg:phone":"+49 7502/2452",
    "sg:postcode":"88284",
    "sg:province":"Baden-W\u00fcrttemberg",
    "wof:name":"S.t.l. Seifert Gmbh",
    "wof:placetype":"venue"
},
  "geometry": {"coordinates":[9.6138849258,47.9031219482],"type":"Point"}
}