{
  "type": "Feature",
  "properties": {
    "iso:country":"DE",
    "sg:address":"Frankenstr. 99",
    "sg:city":"Essen",
    "sg:phone":"+49 201/440273",
    "sg:postcode":"45134",
    "sg:province":"Nordrhein-Westfalen",
    "wof:name":"Arno Polzer",
    "wof:placetype":"venue"
},
  "geometry": {"coordinates":[7.044156,51.426071],"type":"Point"}
}