{
  "type": "Feature",
  "properties": {
    "iso:country":"DE",
    "sg:address":"Hufelandstr. 10",
    "sg:city":"Lingen",
    "sg:phone":"+49 591/76842",
    "sg:postcode":"49811",
    "sg:province":"Niedersachsen",
    "wof:name":"Antoni Krukowski",
    "wof:placetype":"venue"
},
  "geometry": {"coordinates":[7.355745,52.539986],"type":"Point"}
}