{
  "type": "Feature",
  "properties": {
    "iso:country":"DE",
    "sg:address":"Peterstr. 12",
    "sg:city":"W\u00fcrzburg",
    "sg:phone":"+49 931/56151",
    "sg:postcode":"97070",
    "sg:province":"Bayern",
    "wof:name":"Cafe Klug",
    "wof:placetype":"venue"
},
  "geometry": {"coordinates":[9.931682,49.789391],"type":"Point"}
}