{
  "type": "Feature",
  "properties": {
    "iso:country":"DE",
    "sg:address":"Talsperrenstr. 10",
    "sg:city":"Dippoldiswalde",
    "sg:phone":"+49 3504/612170",
    "sg:postcode":"01744",
    "sg:province":"Sachsen",
    "wof:name":"Hotel-restaurant Paulsdorf Inh. G. Frenzel",
    "wof:placetype":"venue"
},
  "geometry": {"coordinates":[13.6648216248,50.900718689],"type":"Point"}
}