{
  "type": "Feature",
  "properties": {
    "iso:country":"DE",
    "sg:address":"Kirchstr. 38",
    "sg:city":"Aalen",
    "sg:phone":"+49 7366/7345",
    "sg:postcode":"73434",
    "sg:province":"Baden-W\u00fcrttemberg",
    "wof:name":"Kath. Pfarramt Zum Heiligsten Herzen Jesu",
    "wof:placetype":"venue"
},
  "geometry": {"coordinates":[10.0545082092,48.8839530945],"type":"Point"}
}