{
  "type": "Feature",
  "properties": {
    "iso:country":"DE",
    "sg:address":"Lindener Str. 34",
    "sg:city":"Oberthal",
    "sg:phone":"+49 6854/1331",
    "sg:postcode":"66649",
    "sg:province":"Saarland",
    "wof:name":"Herbert Gross Gmbh",
    "wof:placetype":"venue"
},
  "geometry": {"coordinates":[7.0972647667,49.5095367432],"type":"Point"}
}