{
  "type": "Feature",
  "properties": {
    "iso:country":"DE",
    "sg:address":"Hohe Linde 2",
    "sg:city":"Georgsmarienh\u00fctte",
    "sg:phone":"+49 5401/460188",
    "sg:postcode":"49124",
    "sg:province":"Niedersachsen",
    "wof:name":"Pizzeria I Sassi",
    "wof:placetype":"venue"
},
  "geometry": {"coordinates":[8.1087646484,52.211479187],"type":"Point"}
}