{
  "type": "Feature",
  "properties": {
    "iso:country":"DE",
    "sg:address":"Nessestr. 29",
    "sg:city":"Leer",
    "sg:postcode":"26789",
    "sg:province":"Niedersachsen",
    "wof:name":"Schleppschiffahrts-gmbh",
    "wof:placetype":"venue"
},
  "geometry": {"coordinates":[7.454939,53.225731],"type":"Point"}
}