{
  "type": "Feature",
  "properties": {
    "iso:country":"DE",
    "sg:address":"Marienberger Str. 5L",
    "sg:city":"Braunschweig",
    "sg:phone":"+49 531/873565",
    "sg:postcode":"38122",
    "sg:province":"Niedersachsen",
    "wof:name":"Fleischerei Sroka & Langkowski Gmbh",
    "wof:placetype":"venue"
},
  "geometry": {"coordinates":[10.493897438,52.2370071411],"type":"Point"}
}