{
  "type": "Feature",
  "properties": {
    "iso:country":"DE",
    "sg:address":"Zehntstr. 70",
    "sg:city":"Ladenburg",
    "sg:phone":"+49 6203/5272",
    "sg:postcode":"68526",
    "sg:province":"Baden-W\u00fcrttemberg",
    "wof:name":"Gemeinn\u00fctzige Baugenossen- Schaft Ladenburg Eg",
    "wof:placetype":"venue"
},
  "geometry": {"coordinates":[8.6094846725,49.4775695801],"type":"Point"}
}