{
  "type": "Feature",
  "properties": {
    "iso:country":"DE",
    "sg:address":"Hauptstr. 22",
    "sg:city":"Weinsberg",
    "sg:phone":"+49 7134/98910",
    "sg:postcode":"74189",
    "sg:province":"Baden-W\u00fcrttemberg",
    "wof:name":"W. Beroll Rechtsanwalt",
    "wof:placetype":"venue"
},
  "geometry": {"coordinates":[9.2865791321,49.1513557434],"type":"Point"}
}