{
  "type": "Feature",
  "properties": {
    "iso:country":"DE",
    "sg:address":"Rentpoldenreuth 8",
    "sg:city":"Perlesreut",
    "sg:phone":"+49 8555/245",
    "sg:postcode":"94157",
    "sg:province":"Bayern",
    "wof:name":"Gastst\u00e4tte Rudolf Tanzer",
    "wof:placetype":"venue"
},
  "geometry": {"coordinates":[13.4291400909,48.8120689392],"type":"Point"}
}