{
  "type": "Feature",
  "properties": {
    "iso:country":"DE",
    "sg:address":"Burgst\u00e4dter Str. 7 a",
    "sg:city":"Clau\u00dfnitz",
    "sg:phone":"+49 37202/2483",
    "sg:postcode":"09236",
    "sg:province":"Sachsen",
    "wof:name":"Steffen R\u00f6mer",
    "wof:placetype":"venue"
},
  "geometry": {"coordinates":[12.877197,50.93248],"type":"Point"}
}