{
  "type": "Feature",
  "properties": {
    "iso:country":"DE",
    "sg:address":"Ortenaustr. 10",
    "sg:city":"Offenburg",
    "sg:phone":"+49 781/54260",
    "sg:postcode":"77656",
    "sg:province":"Baden-W\u00fcrttemberg",
    "wof:name":"Adler",
    "wof:placetype":"venue"
},
  "geometry": {"coordinates":[7.9481058121,48.4405059814],"type":"Point"}
}