{
  "type": "Feature",
  "properties": {
    "iso:country":"DE",
    "sg:address":"Sedanstr. 13",
    "sg:city":"M\u00fchldorf",
    "sg:phone":"+49 8631/161329",
    "sg:postcode":"84453",
    "sg:province":"Bayern",
    "wof:name":"Ambiente Exclusiv Design Import Und Export Gmbh",
    "wof:placetype":"venue"
},
  "geometry": {"coordinates":[12.5216226578,48.2465362549],"type":"Point"}
}