{
  "type": "Feature",
  "properties": {
    "iso:country":"DE",
    "sg:address":"An der B 1 10",
    "sg:city":"Alt Tucheband",
    "sg:postcode":"15328",
    "sg:province":"Brandenburg",
    "wof:name":"Harry Markgraf",
    "wof:placetype":"venue"
},
  "geometry": {"coordinates":[14.4568758011,52.5441474915],"type":"Point"}
}