{
  "type": "Feature",
  "properties": {
    "iso:country":"DE",
    "sg:address":"Erwin-Rommel-Str. 42",
    "sg:city":"Schw\u00e4bisch Gm\u00fcnd",
    "sg:phone":"+49 7171/61142",
    "sg:postcode":"73525",
    "sg:province":"Baden-W\u00fcrttemberg",
    "wof:name":"G. Heinemann",
    "wof:placetype":"venue"
},
  "geometry": {"coordinates":[9.779264,48.78809],"type":"Point"}
}