{
  "type": "Feature",
  "properties": {
    "iso:country":"DE",
    "sg:address":"Burgstr. 1",
    "sg:city":"Sigmaringen",
    "sg:phone":"+49 7571/3262",
    "sg:postcode":"72488",
    "sg:province":"Baden-W\u00fcrttemberg",
    "wof:name":"A. Hofmann",
    "wof:placetype":"venue"
},
  "geometry": {"coordinates":[9.21434,48.08699],"type":"Point"}
}