{
  "type": "Feature",
  "properties": {
    "iso:country":"DE",
    "sg:address":"Kiebitzdeich 110",
    "sg:city":"Hamburg",
    "sg:phone":"+49 40/7235271",
    "sg:postcode":"21037",
    "sg:province":"Hamburg",
    "wof:name":"Peter Pinnau",
    "wof:placetype":"venue"
},
  "geometry": {"coordinates":[10.224662,53.416092],"type":"Point"}
}