{
  "type": "Feature",
  "properties": {
    "iso:country":"DE",
    "sg:address":"Hauptstr. 7",
    "sg:city":"Harzgerode",
    "sg:phone":"+49 39484/2673",
    "sg:postcode":"06493",
    "sg:province":"Sachsen-Anhalt",
    "wof:name":"Kutscherstube",
    "wof:placetype":"venue"
},
  "geometry": {"coordinates":[11.1307229996,51.6690177917],"type":"Point"}
}