{
  "type": "Feature",
  "properties": {
    "iso:country":"DE",
    "sg:address":"Raiffeisenstr. 29",
    "sg:city":"Rastede",
    "sg:postcode":"26180",
    "sg:province":"Niedersachsen",
    "wof:name":"Ammerland Finanz Beratung Hecht Und Pichler Ohg",
    "wof:placetype":"venue"
},
  "geometry": {"coordinates":[8.1903581619,53.248134613],"type":"Point"}
}