{
  "type": "Feature",
  "properties": {
    "iso:country":"DE",
    "sg:address":"Alfred-Delp-Str. 3",
    "sg:city":"K\u00f6ln",
    "sg:phone":"+49 2203/13291",
    "sg:postcode":"51149",
    "sg:province":"Nordrhein-Westfalen",
    "wof:name":"Otto Wilkens Steuerberater",
    "wof:placetype":"venue"
},
  "geometry": {"coordinates":[7.0400438309,50.8965148926],"type":"Point"}
}