{
  "type": "Feature",
  "properties": {
    "iso:country":"DE",
    "sg:address":"Carl-Schurz-Str. 3",
    "sg:city":"Bremen",
    "sg:postcode":"28209",
    "sg:province":"Bremen",
    "wof:name":"Website - Design Schilling Kg",
    "wof:placetype":"venue"
},
  "geometry": {"coordinates":[8.841099,53.083527],"type":"Point"}
}