{
  "type": "Feature",
  "properties": {
    "iso:country":"DE",
    "sg:address":"Herzog-Wolfgang-Str. 6",
    "sg:city":"Bad Bergzabern",
    "sg:postcode":"76887",
    "sg:province":"Rheinland-Pfalz",
    "wof:name":"Andreas Hofer Gmbh",
    "wof:placetype":"venue"
},
  "geometry": {"coordinates":[7.9997029305,49.1039581299],"type":"Point"}
}