{
  "type": "Feature",
  "properties": {
    "iso:country":"DE",
    "sg:address":"M\u00fchlenwiese 14",
    "sg:city":"Blender",
    "sg:phone":"+49 4233/417",
    "sg:postcode":"27337",
    "sg:province":"Niedersachsen",
    "wof:name":"Heinrich Bormann",
    "wof:placetype":"venue"
},
  "geometry": {"coordinates":[9.1350793839,52.9190864563],"type":"Point"}
}