{
  "type": "Feature",
  "properties": {
    "iso:country":"DE",
    "sg:address":"Daimlerstr 25",
    "sg:city":"N\u00fcrnberg",
    "sg:phone":"+49 911/621070",
    "sg:postcode":"90441",
    "sg:province":"Bayern",
    "wof:name":"Stoll Luft-und Umwelttechnik Gmbh",
    "wof:placetype":"venue"
},
  "geometry": {"coordinates":[11.052413,49.425217],"type":"Point"}
}