{
  "type": "Feature",
  "properties": {
    "iso:country":"DE",
    "sg:address":"Dr.-Walther-Str. 6",
    "sg:city":"Herzogenaurach",
    "sg:phone":"+49 9132/9448",
    "sg:postcode":"91074",
    "sg:province":"Bayern",
    "wof:name":"Klaus Burgkhardt",
    "wof:placetype":"venue"
},
  "geometry": {"coordinates":[10.8685207367,49.5752944946],"type":"Point"}
}