{
  "type": "Feature",
  "properties": {
    "iso:country":"DE",
    "sg:address":"Andreasstr. 7",
    "sg:city":"Rietberg",
    "sg:phone":"+49 5244/2409",
    "sg:postcode":"33397",
    "sg:province":"Nordrhein-Westfalen",
    "wof:name":"Herbert Diederich",
    "wof:placetype":"venue"
},
  "geometry": {"coordinates":[8.457673,51.830223],"type":"Point"}
}