{
  "type": "Feature",
  "properties": {
    "iso:country":"DE",
    "sg:address":"Hessengasse",
    "sg:city":"Greu\u00dfenheim",
    "sg:phone":"+49 931/46923",
    "sg:postcode":"97259",
    "sg:province":"Bayern",
    "wof:name":"Gut Greu\u00dfenheim Gmbh",
    "wof:placetype":"venue"
},
  "geometry": {"coordinates":[9.766044,49.814362],"type":"Point"}
}