{
  "type": "Feature",
  "properties": {
    "iso:country":"DE",
    "sg:address":"Jahnstr. 12a",
    "sg:city":"M\u00fcnster-Sarmsheim",
    "sg:phone":"+49 6721/42744",
    "sg:postcode":"55424",
    "sg:province":"Rheinland-Pfalz",
    "wof:name":"E. R. Mittelst\u00e4dt",
    "wof:placetype":"venue"
},
  "geometry": {"coordinates":[7.8932418823,49.941493988],"type":"Point"}
}