{
  "type": "Feature",
  "properties": {
    "iso:country":"DE",
    "sg:address":"Cremlingen",
    "sg:city":"Cremlingen",
    "sg:phone":"+49 4953/064081",
    "sg:postcode":"38162",
    "sg:province":"Niedersachsen",
    "wof:name":"Spar-und Darlehenskasse Eg",
    "wof:placetype":"venue"
},
  "geometry": {"coordinates":[10.67694,52.261108],"type":"Point"}
}