{
  "type": "Feature",
  "properties": {
    "iso:country":"DE",
    "sg:address":"Hauptstr. 75",
    "sg:city":"Recke",
    "sg:phone":"+49 5453/1674",
    "sg:postcode":"49509",
    "sg:province":"Nordrhein-Westfalen",
    "wof:name":"Casser Gmbh",
    "wof:placetype":"venue"
},
  "geometry": {"coordinates":[7.719287,52.362877],"type":"Point"}
}