{
  "type": "Feature",
  "properties": {
    "iso:country":"DE",
    "sg:address":"Sternenberg 68",
    "sg:city":"Wuppertal",
    "sg:phone":"+49 202/2522880",
    "sg:postcode":"42279",
    "sg:province":"Nordrhein-Westfalen",
    "wof:name":"Lothar Bruster",
    "wof:placetype":"venue"
},
  "geometry": {"coordinates":[7.216504097,51.3015098572],"type":"Point"}
}