{
  "type": "Feature",
  "properties": {
    "iso:country":"DE",
    "sg:address":"Im Altenspohl 13",
    "sg:city":"Bisingen",
    "sg:phone":"+49 7476/7770",
    "sg:postcode":"72406",
    "sg:province":"Baden-W\u00fcrttemberg",
    "wof:name":"B. Loock",
    "wof:placetype":"venue"
},
  "geometry": {"coordinates":[8.9428949356,48.2996482849],"type":"Point"}
}