{
  "type": "Feature",
  "properties": {
    "iso:country":"DE",
    "sg:address":"Weidach",
    "sg:city":"F\u00fcssen",
    "sg:postcode":"87629",
    "sg:province":"Bayern",
    "wof:name":"Ferienwohnung Maier",
    "wof:placetype":"venue"
},
  "geometry": {"coordinates":[10.706425,47.570953],"type":"Point"}
}