{
  "type": "Feature",
  "properties": {
    "iso:country":"DE",
    "sg:address":"Schwalbenweg 1",
    "sg:city":"Bretzfeld",
    "sg:phone":"+49 7946/6707",
    "sg:postcode":"74626",
    "sg:province":"Baden-W\u00fcrttemberg",
    "wof:name":"J\u00fcrgen Weinstock",
    "wof:placetype":"venue"
},
  "geometry": {"coordinates":[9.403959,49.179459],"type":"Point"}
}