{
  "type": "Feature",
  "properties": {
    "iso:country":"DE",
    "sg:address":"Marktstr. 10",
    "sg:city":"Lebach",
    "sg:phone":"+49 6881/2562",
    "sg:postcode":"66822",
    "sg:province":"Saarland",
    "wof:name":"Josef Randerath Eisenwaren",
    "wof:placetype":"venue"
},
  "geometry": {"coordinates":[6.9111680984,49.4108810425],"type":"Point"}
}