{
  "type": "Feature",
  "properties": {
    "iso:country":"DE",
    "sg:city":"Wolfratshausen",
    "sg:phone":"+49 8171/16070",
    "sg:postcode":"82515",
    "sg:province":"Bayern",
    "wof:name":"Hypo-bank Ag",
    "wof:placetype":"venue"
},
  "geometry": {"coordinates":[11.41791,47.912258],"type":"Point"}
}