{
  "type": "Feature",
  "properties": {
    "iso:country":"DE",
    "sg:address":"Am Vogelbaum 1",
    "sg:city":"Ursensollen",
    "sg:phone":"+49 9628/355",
    "sg:postcode":"92289",
    "sg:province":"Bayern",
    "wof:name":"L. Wecker",
    "wof:placetype":"venue"
},
  "geometry": {"coordinates":[11.8062477112,49.3820648193],"type":"Point"}
}