{
  "type": "Feature",
  "properties": {
    "iso:country":"DE",
    "sg:address":"Dachsweg 17",
    "sg:city":"Stolberg",
    "sg:phone":"+49 2402/28444",
    "sg:postcode":"52222",
    "sg:province":"Nordrhein-Westfalen",
    "wof:name":"Gastst\u00e4tte Barthel Odekerken",
    "wof:placetype":"venue"
},
  "geometry": {"coordinates":[6.2005529404,50.7810287476],"type":"Point"}
}