{
  "type": "Feature",
  "properties": {
    "iso:country":"DE",
    "sg:address":"Strangenh\u00e4uschen 19",
    "sg:city":"Aachen",
    "sg:phone":"+49 241/918490",
    "sg:postcode":"52070",
    "sg:province":"Nordrhein-Westfalen",
    "wof:name":"Aachener Flitzer Gmbh",
    "wof:placetype":"venue"
},
  "geometry": {"coordinates":[6.1137681007,50.8009986877],"type":"Point"}
}