{
  "type": "Feature",
  "properties": {
    "iso:country":"DE",
    "sg:address":"Schiffahrter Damm 508",
    "sg:city":"M\u00fcnster",
    "sg:phone":"+49 251/324308",
    "sg:postcode":"48157",
    "sg:province":"Nordrhein-Westfalen",
    "wof:name":"Westfalen-tankstelle Inh. Volker Happe",
    "wof:placetype":"venue"
},
  "geometry": {"coordinates":[7.679681778,52.0114555359],"type":"Point"}
}