{
  "type": "Feature",
  "properties": {
    "iso:country":"DE",
    "sg:address":"Hohenzollernstr. 69",
    "sg:city":"Ludwigshafen",
    "sg:phone":"+49 621/698808",
    "sg:postcode":"67063",
    "sg:province":"Rheinland-Pfalz",
    "wof:name":"U. Hecht",
    "wof:placetype":"venue"
},
  "geometry": {"coordinates":[8.419947,49.492153],"type":"Point"}
}