{
  "type": "Feature",
  "properties": {
    "iso:country":"DE",
    "sg:address":"Forststr. 32",
    "sg:city":"Reichelsheim",
    "sg:phone":"+49 6164/1289",
    "sg:postcode":"64385",
    "sg:province":"Hessen",
    "wof:name":"Ludwig Pfeiffer",
    "wof:placetype":"venue"
},
  "geometry": {"coordinates":[8.868527,49.671711],"type":"Point"}
}