{
  "type": "Feature",
  "properties": {
    "iso:country":"DE",
    "sg:address":"Harffer Str. 81",
    "sg:city":"Neuss",
    "sg:phone":"+49 2131/103177",
    "sg:postcode":"41469",
    "sg:province":"Nordrhein-Westfalen",
    "wof:name":"Team Datenverarb. Ohg",
    "wof:placetype":"venue"
},
  "geometry": {"coordinates":[6.7292752266,51.1663894653],"type":"Point"}
}