{
  "type": "Feature",
  "properties": {
    "iso:country":"DE",
    "sg:address":"Friedhofstr. 107",
    "sg:city":"Petershagen",
    "sg:phone":"+49 33439/82358",
    "sg:postcode":"15370",
    "sg:province":"Brandenburg",
    "wof:name":"G. Thiele",
    "wof:placetype":"venue"
},
  "geometry": {"coordinates":[13.768361,52.513885],"type":"Point"}
}