{
  "type": "Feature",
  "properties": {
    "iso:country":"DE",
    "sg:address":"Im Obereck 1",
    "sg:city":"St. Wendel",
    "sg:phone":"+49 6851/3271",
    "sg:postcode":"66606",
    "sg:province":"Saarland",
    "wof:name":"Rudolf Hell",
    "wof:placetype":"venue"
},
  "geometry": {"coordinates":[7.124919,49.441051],"type":"Point"}
}