{
  "type": "Feature",
  "properties": {
    "iso:country":"DE",
    "sg:address":"Wilhelm-Pieck-Ring 64",
    "sg:city":"K\u00f6lleda",
    "sg:phone":"+49 3635/483147",
    "sg:postcode":"99625",
    "sg:province":"Th\u00fcringen",
    "wof:name":"Restaurant Orion Inh. Marion Borchert",
    "wof:placetype":"venue"
},
  "geometry": {"coordinates":[11.2560300827,51.186882019],"type":"Point"}
}