{
  "type": "Feature",
  "properties": {
    "iso:country":"DE",
    "sg:address":"M\u00fchlentorstr. 25",
    "sg:city":"Rehburg-Loccum",
    "sg:phone":"+49 5037/3692",
    "sg:postcode":"31547",
    "sg:province":"Niedersachsen",
    "wof:name":"Waltraud Bock",
    "wof:placetype":"venue"
},
  "geometry": {"coordinates":[9.2269639969,52.4720649719],"type":"Point"}
}