{
  "type": "Feature",
  "properties": {
    "iso:country":"DE",
    "sg:address":"Am Eichberg 4",
    "sg:city":"Rosenthal-Bielatal",
    "sg:phone":"+49 35033/70557",
    "sg:postcode":"01824",
    "sg:province":"Sachsen",
    "wof:name":"Matthias Sch\u00f6nberg",
    "wof:placetype":"venue"
},
  "geometry": {"coordinates":[14.048668,50.878918],"type":"Point"}
}