{
  "type": "Feature",
  "properties": {
    "iso:country":"DE",
    "sg:address":"Finstere Gasse 7",
    "sg:city":"Markgr\u00f6ningen",
    "sg:phone":"+49 7145/26888",
    "sg:postcode":"71706",
    "sg:province":"Baden-W\u00fcrttemberg",
    "wof:name":"Chapeau Claque",
    "wof:placetype":"venue"
},
  "geometry": {"coordinates":[9.0798511505,48.9047546387],"type":"Point"}
}