{
  "type": "Feature",
  "properties": {
    "iso:country":"DE",
    "sg:address":"Dammannstr. 48-54",
    "sg:city":"Essen",
    "sg:phone":"+49 201/285555",
    "sg:postcode":"45138",
    "sg:province":"Nordrhein-Westfalen",
    "wof:name":"Haarmann & Langhoff Nachf.",
    "wof:placetype":"venue"
},
  "geometry": {"coordinates":[7.042345047,51.4475250244],"type":"Point"}
}