{
  "type": "Feature",
  "properties": {
    "iso:country":"DE",
    "sg:address":"Ortsstr. 16",
    "sg:city":"Ostrach",
    "sg:phone":"+49 7585/528",
    "sg:postcode":"88356",
    "sg:province":"Baden-W\u00fcrttemberg",
    "wof:name":"Hubert Birkhofer",
    "wof:placetype":"venue"
},
  "geometry": {"coordinates":[9.407032,47.975452],"type":"Point"}
}