{
  "type": "Feature",
  "properties": {
    "iso:country":"DE",
    "sg:address":"Frieweg 39",
    "sg:city":"L\u00f6hne",
    "sg:phone":"+49 5732",
    "sg:postcode":"32584",
    "sg:province":"Nordrhein-Westfalen",
    "wof:name":"Das Deutsche Mp3-magazin",
    "wof:placetype":"venue"
},
  "geometry": {"coordinates":[8.710096,52.2276],"type":"Point"}
}