{
  "type": "Feature",
  "properties": {
    "iso:country":"DE",
    "sg:address":"Wagnerstr. 21",
    "sg:city":"Telgte",
    "sg:postcode":"48291",
    "sg:province":"Nordrhein-Westfalen",
    "wof:name":"Kossakowski Gmbh",
    "wof:placetype":"venue"
},
  "geometry": {"coordinates":[7.7939882278,51.9754295349],"type":"Point"}
}