{
  "type": "Feature",
  "properties": {
    "iso:country":"DE",
    "sg:address":"Hauptstr. 126",
    "sg:city":"Langenwetzendorf",
    "sg:phone":"+49 36625/20341",
    "sg:postcode":"07957",
    "sg:province":"Th\u00fcringen",
    "wof:name":"Fritz Georgi",
    "wof:placetype":"venue"
},
  "geometry": {"coordinates":[12.087868,50.68388],"type":"Point"}
}