{
  "type": "Feature",
  "properties": {
    "iso:country":"DE",
    "sg:address":"Hohe Str. 88",
    "sg:city":"Herborn",
    "sg:phone":"+49 2772/62616",
    "sg:postcode":"35745",
    "sg:province":"Hessen",
    "wof:name":"Seelbacher Hof",
    "wof:placetype":"venue"
},
  "geometry": {"coordinates":[8.3534793854,50.7073020935],"type":"Point"}
}