{
  "type": "Feature",
  "properties": {
    "iso:country":"DE",
    "sg:address":"Friedrich-Engels-Str. 1",
    "sg:city":"K\u00f6nigs Wusterhausen",
    "sg:phone":"+49 3375/293027",
    "sg:postcode":"15711",
    "sg:province":"Brandenburg",
    "wof:name":"M\u00e4rkische Apotheke",
    "wof:placetype":"venue"
},
  "geometry": {"coordinates":[13.629037,52.296368],"type":"Point"}
}