{
  "type": "Feature",
  "properties": {
    "iso:country":"DE",
    "sg:address":"Obere Marktstr. 3",
    "sg:city":"Gaimersheim",
    "sg:phone":"+49 8458/744",
    "sg:postcode":"85080",
    "sg:province":"Bayern",
    "wof:name":"Mehrzweckhalle Gaimersheim",
    "wof:placetype":"venue"
},
  "geometry": {"coordinates":[11.37002,48.809345],"type":"Point"}
}