{
  "type": "Feature",
  "properties": {
    "iso:country":"DE",
    "sg:address":"Laibacher Str. 16",
    "sg:city":"Dresden",
    "sg:phone":"+49 351/2591527",
    "sg:postcode":"01279",
    "sg:province":"Sachsen",
    "wof:name":"Geldservice Dresden Inh. Achim Gottschalk",
    "wof:placetype":"venue"
},
  "geometry": {"coordinates":[13.835997,51.02026],"type":"Point"}
}