{
  "type": "Feature",
  "properties": {
    "iso:country":"DE",
    "sg:address":"Schelmenstr. 12",
    "sg:city":"Neuhausen",
    "sg:phone":"+49 7234/8574",
    "sg:postcode":"75242",
    "sg:province":"Baden-W\u00fcrttemberg",
    "wof:name":"Hans-peter Raible Architekt",
    "wof:placetype":"venue"
},
  "geometry": {"coordinates":[8.779725,48.822502],"type":"Point"}
}