{
  "type": "Feature",
  "properties": {
    "iso:country":"DE",
    "sg:address":"Gewerbepark Wispertal 20",
    "sg:city":"Lorch",
    "sg:phone":"+49 6726/533",
    "sg:postcode":"65391",
    "sg:province":"Rheinland-Pfalz",
    "wof:name":"Reinhold Pohl",
    "wof:placetype":"venue"
},
  "geometry": {"coordinates":[7.823773,50.050903],"type":"Point"}
}