{
  "type": "Feature",
  "properties": {
    "iso:country":"DE",
    "sg:address":"M\u00fchlenstr. 2 E",
    "sg:city":"Neu Wulmstorf",
    "sg:phone":"+49 4168/911648",
    "sg:postcode":"21629",
    "sg:province":"Niedersachsen",
    "wof:name":"Praxis Dorndorf Und Ohlen",
    "wof:placetype":"venue"
},
  "geometry": {"coordinates":[9.7921247482,53.4680099487],"type":"Point"}
}