{
  "type": "Feature",
  "properties": {
    "iso:country":"DE",
    "sg:address":"Broistedter Str. 30",
    "sg:city":"Lengede",
    "sg:phone":"+49 5344/7024",
    "sg:postcode":"38268",
    "sg:province":"Niedersachsen",
    "wof:name":"Karl-heinz Himstedt",
    "wof:placetype":"venue"
},
  "geometry": {"coordinates":[10.3128852844,52.2014122009],"type":"Point"}
}