{
  "type": "Feature",
  "properties": {
    "iso:country":"DE",
    "sg:address":"Waldsachsener Str. 15",
    "sg:city":"R\u00f6dental",
    "sg:phone":"+49 9563/8314",
    "sg:postcode":"96472",
    "sg:province":"Bayern",
    "wof:name":"E. K\u00f6hler",
    "wof:placetype":"venue"
},
  "geometry": {"coordinates":[11.0295572281,50.2773628235],"type":"Point"}
}