{
  "type": "Feature",
  "properties": {
    "iso:country":"DE",
    "sg:address":"Bahnhofstr. 24",
    "sg:city":"Wilhelmshaven",
    "sg:postcode":"26382",
    "sg:province":"Niedersachsen",
    "wof:name":"Neumann Verlag F\u00fcr Tele- Kommunikationsverzeichnisse",
    "wof:placetype":"venue"
},
  "geometry": {"coordinates":[8.1128206253,53.5193786621],"type":"Point"}
}