{
  "type": "Feature",
  "properties": {
    "iso:country":"DE",
    "sg:address":"Hofmarkweg 4",
    "sg:city":"Unterhaching",
    "sg:phone":"+49 89/6112253",
    "sg:postcode":"82008",
    "sg:province":"Bayern",
    "wof:name":"Woll-wichtl Erika Wichtrey",
    "wof:placetype":"venue"
},
  "geometry": {"coordinates":[11.610165,48.0672],"type":"Point"}
}