{
  "type": "Feature",
  "properties": {
    "iso:country":"DE",
    "sg:address":"Schw\u00f6rhausgasse 1-2",
    "sg:city":"Ulm",
    "sg:phone":"+49 731/66912",
    "sg:postcode":"89073",
    "sg:province":"Baden-W\u00fcrttemberg",
    "wof:name":"Christine Abele-sch\u00e4fer Gmbh",
    "wof:placetype":"venue"
},
  "geometry": {"coordinates":[9.9911699295,48.395778656],"type":"Point"}
}