{
  "type": "Feature",
  "properties": {
    "iso:country":"DE",
    "sg:address":"Rosenauer Str. 30",
    "sg:city":"Coburg",
    "sg:phone":"+49 9561/426080",
    "sg:postcode":"96450",
    "sg:province":"Bayern",
    "wof:name":"Restaurant Kr\u00e4utergarten",
    "wof:placetype":"venue"
},
  "geometry": {"coordinates":[10.9719057083,50.2678642273],"type":"Point"}
}