{
  "type": "Feature",
  "properties": {
    "iso:country":"DE",
    "sg:address":"Sievershausener Str. 10a",
    "sg:city":"Lehrte",
    "sg:phone":"+49 5175/92120",
    "sg:postcode":"31275",
    "sg:province":"Niedersachsen",
    "wof:name":"Jaeckel Verwaltungs Gmbh",
    "wof:placetype":"venue"
},
  "geometry": {"coordinates":[10.1055612564,52.3831977844],"type":"Point"}
}