{
  "type": "Feature",
  "properties": {
    "iso:country":"DE",
    "sg:address":"Hafelsstr. 200",
    "sg:city":"Krefeld",
    "sg:phone":"+49 2151/548802",
    "sg:postcode":"47809",
    "sg:province":"Nordrhein-Westfalen",
    "wof:name":"J. Kaufmann",
    "wof:placetype":"venue"
},
  "geometry": {"coordinates":[6.6014261246,51.321056366],"type":"Point"}
}