{
  "type": "Feature",
  "properties": {
    "iso:country":"DE",
    "sg:address":"Buch\u00e4ckergasse 5",
    "sg:city":"Hindelang",
    "sg:phone":"+49 8324/457",
    "sg:postcode":"87541",
    "sg:province":"Bayern",
    "wof:name":"Anton Endra\u00df",
    "wof:placetype":"venue"
},
  "geometry": {"coordinates":[10.3845701218,47.5029602051],"type":"Point"}
}