{
  "type": "Feature",
  "properties": {
    "iso:country":"DE",
    "sg:address":"Dorfaue 16",
    "sg:city":"Gro\u00dfbeeren",
    "sg:phone":"+49 33701/58502",
    "sg:postcode":"14979",
    "sg:province":"Brandenburg",
    "wof:name":"A & Z Transport Gmbh",
    "wof:placetype":"venue"
},
  "geometry": {"coordinates":[13.307094574,52.3539581299],"type":"Point"}
}