{
  "type": "Feature",
  "properties": {
    "iso:country":"DE",
    "sg:address":"Dorflache 10",
    "sg:city":"Kehl",
    "sg:phone":"+49 7853/1083",
    "sg:postcode":"77694",
    "sg:province":"Baden-W\u00fcrttemberg",
    "wof:name":"Karl Marz",
    "wof:placetype":"venue"
},
  "geometry": {"coordinates":[7.872201,48.599083],"type":"Point"}
}