{
  "type": "Feature",
  "properties": {
    "iso:country":"DE",
    "sg:address":"Husumer Str. 15 A",
    "sg:city":"Heilbad Heiligenstadt",
    "sg:phone":"+49 3606/606147",
    "sg:postcode":"37308",
    "sg:province":"Th\u00fcringen",
    "wof:name":"Liethen-apotheke Karin Arand E. Kfr.",
    "wof:placetype":"venue"
},
  "geometry": {"coordinates":[10.135267,51.384304],"type":"Point"}
}