{
  "type": "Feature",
  "properties": {
    "iso:country":"DE",
    "sg:address":"Halener Str. 107",
    "sg:city":"Duisburg",
    "sg:phone":"+49 2066/7957",
    "sg:postcode":"47198",
    "sg:province":"Nordrhein-Westfalen",
    "wof:name":"Droste Und Passlak",
    "wof:placetype":"venue"
},
  "geometry": {"coordinates":[6.6911320686,51.4641799927],"type":"Point"}
}