{
  "type": "Feature",
  "properties": {
    "iso:country":"DE",
    "sg:address":"Am Akazienschlag 3",
    "sg:city":"Georgensgm\u00fcnd",
    "sg:phone":"+49 9172/8739",
    "sg:postcode":"91166",
    "sg:province":"Bayern",
    "wof:name":"Peter Leipold",
    "wof:placetype":"venue"
},
  "geometry": {"coordinates":[11.0148677826,49.1925048828],"type":"Point"}
}