{
  "type": "Feature",
  "properties": {
    "iso:country":"DE",
    "sg:address":"Am Stellwinkel 2",
    "sg:city":"Westerheim",
    "sg:phone":"+49 8336/80440",
    "sg:postcode":"87784",
    "sg:province":"Bayern",
    "wof:name":"Georg Schalk",
    "wof:placetype":"venue"
},
  "geometry": {"coordinates":[10.2974472046,48.021774292],"type":"Point"}
}