{
  "type": "Feature",
  "properties": {
    "iso:country":"DE",
    "sg:address":"Schinkelstr. 43",
    "sg:city":"Ludwigshafen",
    "sg:phone":"+49 621/651137",
    "sg:postcode":"67069",
    "sg:province":"Rheinland-Pfalz",
    "wof:name":"Franz Friderich Kohlen-handlung",
    "wof:placetype":"venue"
},
  "geometry": {"coordinates":[8.398422,49.520592],"type":"Point"}
}