{
  "type": "Feature",
  "properties": {
    "iso:country":"DE",
    "sg:address":"Lange Str. 37",
    "sg:city":"Marbach",
    "sg:phone":"+49 7144/37039",
    "sg:postcode":"71672",
    "sg:province":"Baden-W\u00fcrttemberg",
    "wof:name":"E. Ruoff Architekt",
    "wof:placetype":"venue"
},
  "geometry": {"coordinates":[9.33604,48.969509],"type":"Point"}
}