{
  "type": "Feature",
  "properties": {
    "iso:country":"DE",
    "sg:address":"Schulstr. 2",
    "sg:city":"Walpertskirchen",
    "sg:phone":"+49 8122/15532",
    "sg:postcode":"85469",
    "sg:province":"Bayern",
    "wof:name":"Georg Glockshuber Elektro Installation",
    "wof:placetype":"venue"
},
  "geometry": {"coordinates":[11.973534,48.259232],"type":"Point"}
}