{
  "type": "Feature",
  "properties": {
    "iso:country":"DE",
    "sg:address":"Zollstr. 3-5",
    "sg:city":"Verden",
    "sg:phone":"+49 4231/5487",
    "sg:postcode":"27283",
    "sg:province":"Niedersachsen",
    "wof:name":"Druckerei Kreuzkamp",
    "wof:placetype":"venue"
},
  "geometry": {"coordinates":[9.232956,52.923061],"type":"Point"}
}