{
  "type": "Feature",
  "properties": {
    "iso:country":"DE",
    "sg:address":"Adolf-Kolping-Str. 20",
    "sg:city":"Ostercappeln",
    "sg:phone":"+49 5473/622",
    "sg:postcode":"49179",
    "sg:province":"Niedersachsen",
    "wof:name":"J\u00fcrgen Habeck Industrieelektronik",
    "wof:placetype":"venue"
},
  "geometry": {"coordinates":[8.23782,52.346169],"type":"Point"}
}