{
  "type": "Feature",
  "properties": {
    "iso:country":"DE",
    "sg:address":"Langgasse 30",
    "sg:city":"B\u00f6hl-Iggelheim",
    "sg:phone":"+49 6324/76213",
    "sg:postcode":"67459",
    "sg:province":"Rheinland-Pfalz",
    "wof:name":"Cafebar Athen",
    "wof:placetype":"venue"
},
  "geometry": {"coordinates":[8.305701,49.365417],"type":"Point"}
}