{
  "type": "Feature",
  "properties": {
    "iso:country":"DE",
    "sg:address":"Am Kr\u00e4uterberg 1",
    "sg:city":"Oberdiebach",
    "sg:phone":"+49 6743/2301",
    "sg:postcode":"55413",
    "sg:province":"Rheinland-Pfalz",
    "wof:name":"Artur Schneider",
    "wof:placetype":"venue"
},
  "geometry": {"coordinates":[7.777921,50.03289],"type":"Point"}
}