{
  "type": "Feature",
  "properties": {
    "iso:country":"DE",
    "sg:address":"Felbrigstr. 44",
    "sg:city":"Gera",
    "sg:phone":"+49 365/33963",
    "sg:postcode":"07549",
    "sg:province":"Th\u00fcringen",
    "wof:name":"K. Wagner",
    "wof:placetype":"venue"
},
  "geometry": {"coordinates":[12.057857,50.836273],"type":"Point"}
}