{
  "type": "Feature",
  "properties": {
    "iso:country":"DE",
    "sg:address":"Dammstr. 7",
    "sg:city":"Pattensen",
    "sg:phone":"+49 5101/12871",
    "sg:postcode":"30982",
    "sg:province":"Niedersachsen",
    "wof:name":"Heinrich Munke",
    "wof:placetype":"venue"
},
  "geometry": {"coordinates":[9.757881,52.26392],"type":"Point"}
}