{
  "type": "Feature",
  "properties": {
    "iso:country":"DE",
    "sg:address":"Burgstr. 18",
    "sg:city":"H\u00fcrtgenwald",
    "sg:phone":"+49 2429/901064",
    "sg:postcode":"52393",
    "sg:province":"Nordrhein-Westfalen",
    "wof:name":"R. Wirtz Rechtsanwalt",
    "wof:placetype":"venue"
},
  "geometry": {"coordinates":[6.4304380417,50.6935768127],"type":"Point"}
}