{
  "type": "Feature",
  "properties": {
    "iso:country":"DE",
    "sg:address":"F\u00f6llstr. 20",
    "sg:city":"K\u00f6nigsbrunn",
    "sg:phone":"+49 8231/96960",
    "sg:postcode":"86343",
    "sg:province":"Bayern",
    "wof:name":"Hin Und Mit",
    "wof:placetype":"venue"
},
  "geometry": {"coordinates":[10.890588,48.292866],"type":"Point"}
}