{
  "type": "Feature",
  "properties": {
    "iso:country":"DE",
    "sg:address":"Ludwigstr. 12",
    "sg:city":"Viernheim",
    "sg:phone":"+49 6204/8738",
    "sg:postcode":"68519",
    "sg:province":"Hessen",
    "wof:name":"Karl Hofmann",
    "wof:placetype":"venue"
},
  "geometry": {"coordinates":[8.576475,49.539822],"type":"Point"}
}