{
  "type": "Feature",
  "properties": {
    "iso:country":"DE",
    "sg:address":"Bietigheimer Str. 56",
    "sg:city":"Ingersheim",
    "sg:postcode":"74379",
    "sg:province":"Baden-W\u00fcrttemberg",
    "wof:name":"Metall-und Kunststoffver- Arbeitung Heinz Pohlers",
    "wof:placetype":"venue"
},
  "geometry": {"coordinates":[9.1773233414,48.9590950012],"type":"Point"}
}