{
  "type": "Feature",
  "properties": {
    "iso:country":"DE",
    "sg:address":"J\u00fclicher Str. 13",
    "sg:city":"D\u00fcsseldorf",
    "sg:phone":"+49 211/480291",
    "sg:postcode":"40477",
    "sg:province":"Nordrhein-Westfalen",
    "wof:name":"Telekopie Frank Quix",
    "wof:placetype":"venue"
},
  "geometry": {"coordinates":[6.7851881981,51.2423744202],"type":"Point"}
}