{
  "type": "Feature",
  "properties": {
    "iso:country":"DE",
    "sg:address":"Luchtenstr. 4a",
    "sg:city":"Lippstadt",
    "sg:phone":"+49 2941/5626",
    "sg:postcode":"59555",
    "sg:province":"Nordrhein-Westfalen",
    "wof:name":"Dentso Gmbh",
    "wof:placetype":"venue"
},
  "geometry": {"coordinates":[8.3479242325,51.6744842529],"type":"Point"}
}