{
  "type": "Feature",
  "properties": {
    "iso:country":"DE",
    "sg:address":"Heiligenst\u00e4dter Str. 1",
    "sg:city":"Gangkofen",
    "sg:phone":"+49 8722/1321",
    "sg:postcode":"84140",
    "sg:province":"Bayern",
    "wof:name":"Johann Schmidhuber",
    "wof:placetype":"venue"
},
  "geometry": {"coordinates":[12.564103,48.43285],"type":"Point"}
}