{
  "type": "Feature",
  "properties": {
    "iso:country":"DE",
    "sg:address":"Brunnen 9",
    "sg:city":"Ki\u00dflegg",
    "sg:postcode":"88353",
    "sg:province":"Baden-W\u00fcrttemberg",
    "wof:name":"Allpump F\u00f6rdertechnik Gmbh",
    "wof:placetype":"venue"
},
  "geometry": {"coordinates":[9.8510751724,47.8289642334],"type":"Point"}
}