{
  "type": "Feature",
  "properties": {
    "iso:country":"DE",
    "sg:address":"Richtmoorstr. 6a",
    "sg:city":"Bad Zwischenahn",
    "sg:phone":"+49 4403/3822",
    "sg:postcode":"26160",
    "sg:province":"Niedersachsen",
    "wof:name":"Wilfried M\u00fcller",
    "wof:placetype":"venue"
},
  "geometry": {"coordinates":[8.074765,53.188419],"type":"Point"}
}