{
  "type": "Feature",
  "properties": {
    "iso:country":"DE",
    "sg:address":"Stra\u00dfe der Jugend",
    "sg:city":"Velgast",
    "sg:phone":"+49 38324/7657",
    "sg:postcode":"18469",
    "sg:province":"Mecklenburg-Vorpommern",
    "wof:name":"A. Roggow",
    "wof:placetype":"venue"
},
  "geometry": {"coordinates":[12.81059,54.271503],"type":"Point"}
}