{
  "type": "Feature",
  "properties": {
    "iso:country":"DE",
    "sg:address":"Kiefernweg 28",
    "sg:city":"Arnsberg",
    "sg:phone":"+49 2932/63910",
    "sg:postcode":"59755",
    "sg:province":"Nordrhein-Westfalen",
    "wof:name":"S.a.t. Antriebstechnik Gmbh & Co Kg",
    "wof:placetype":"venue"
},
  "geometry": {"coordinates":[7.9936199188,51.4648132324],"type":"Point"}
}