{
  "type": "Feature",
  "properties": {
    "iso:country":"DE",
    "sg:address":"Ober-Ramst\u00e4dter-Weg 31",
    "sg:city":"Gro\u00df-Zimmern",
    "sg:phone":"+49 6071/41278",
    "sg:postcode":"64846",
    "sg:province":"Hessen",
    "wof:name":"Karl-heinz Ohl",
    "wof:placetype":"venue"
},
  "geometry": {"coordinates":[8.824590683,49.8674621582],"type":"Point"}
}