{
  "type": "Feature",
  "properties": {
    "iso:country":"DE",
    "sg:address":"Renninger Str. 37",
    "sg:city":"Magstadt",
    "sg:phone":"+49 7159/44864",
    "sg:postcode":"71106",
    "sg:province":"Baden-W\u00fcrttemberg",
    "wof:name":"Thomas M\u00fchlrath Architekt",
    "wof:placetype":"venue"
},
  "geometry": {"coordinates":[8.953393,48.745808],"type":"Point"}
}