{
  "type": "Feature",
  "properties": {
    "iso:country":"DE",
    "sg:address":"Wiebelsheidestr. 28a",
    "sg:city":"Arnsberg",
    "sg:phone":"+49 2932/33355",
    "sg:postcode":"59757",
    "sg:province":"Nordrhein-Westfalen",
    "wof:name":"U. Krafft",
    "wof:placetype":"venue"
},
  "geometry": {"coordinates":[7.9586439133,51.4320373535],"type":"Point"}
}