{
  "type": "Feature",
  "properties": {
    "iso:country":"DE",
    "sg:address":"Gro\u00dfhaderner Str. 30",
    "sg:city":"M\u00fcnchen",
    "sg:phone":"+49 89/7003328",
    "sg:postcode":"81375",
    "sg:province":"Bayern",
    "wof:name":"Max Neissendorfer Ohg",
    "wof:placetype":"venue"
},
  "geometry": {"coordinates":[11.4806194305,48.1189498901],"type":"Point"}
}