{
  "type": "Feature",
  "properties": {
    "iso:country":"DE",
    "sg:address":"Dammweg 4 b",
    "sg:city":"Inzell",
    "sg:postcode":"83334",
    "sg:province":"Bayern",
    "wof:name":"Af-sports Gmbh",
    "wof:placetype":"venue"
},
  "geometry": {"coordinates":[12.748005867,47.7599563599],"type":"Point"}
}