{
  "type": "Feature",
  "properties": {
    "iso:country":"DE",
    "sg:address":"Madamenweg 138",
    "sg:city":"Braunschweig",
    "sg:phone":"+49 531/894303",
    "sg:postcode":"38118",
    "sg:province":"Niedersachsen",
    "wof:name":"Hannibal-grill",
    "wof:placetype":"venue"
},
  "geometry": {"coordinates":[10.4989681244,52.2607688904],"type":"Point"}
}