{
  "type": "Feature",
  "properties": {
    "iso:country":"DE",
    "sg:address":"St.-Annen-Str. 38",
    "sg:city":"Brandenburg",
    "sg:phone":"+49 3381/500",
    "sg:postcode":"14776",
    "sg:province":"Brandenburg",
    "wof:name":"Call Und Surf Factory Dienstleistungszentrum F\u00fcr",
    "wof:placetype":"venue"
},
  "geometry": {"coordinates":[12.5633277893,52.4084358215],"type":"Point"}
}