{
  "type": "Feature",
  "properties": {
    "iso:country":"DE",
    "sg:address":"Ahornstr. 23",
    "sg:city":"Dorsten",
    "sg:phone":"+49 2362/68654",
    "sg:postcode":"46284",
    "sg:province":"Nordrhein-Westfalen",
    "wof:name":"Helmut Naroda Forellenzucht",
    "wof:placetype":"venue"
},
  "geometry": {"coordinates":[6.9543128014,51.6792144775],"type":"Point"}
}