{
  "type": "Feature",
  "properties": {
    "iso:country":"DE",
    "sg:address":"Hauptstr. 218",
    "sg:city":"Frechen",
    "sg:phone":"+49 2234/53609",
    "sg:postcode":"50226",
    "sg:province":"Nordrhein-Westfalen",
    "wof:name":"Einstein",
    "wof:placetype":"venue"
},
  "geometry": {"coordinates":[6.8015217781,50.9087791443],"type":"Point"}
}