{
  "type": "Feature",
  "properties": {
    "iso:country":"DE",
    "sg:address":"K\u00f6terbergstr. 25",
    "sg:city":"H\u00f6xter",
    "sg:phone":"+49 5531/60261",
    "sg:postcode":"37671",
    "sg:province":"Nordrhein-Westfalen",
    "wof:name":"Werner Schmidt Ingenieur",
    "wof:placetype":"venue"
},
  "geometry": {"coordinates":[9.4124298096,51.8342399597],"type":"Point"}
}