{
  "type": "Feature",
  "properties": {
    "iso:country":"DE",
    "sg:address":"Wolfhager Str. 166",
    "sg:city":"Kassel",
    "sg:phone":"+49 561/85533",
    "sg:postcode":"34127",
    "sg:province":"Hessen",
    "wof:name":"Germania-apotheke Inh. Frank H\u00f6hr",
    "wof:placetype":"venue"
},
  "geometry": {"coordinates":[9.476607,51.325825],"type":"Point"}
}