{
  "type": "Feature",
  "properties": {
    "iso:country":"DE",
    "sg:address":"M\u00f6llendorfer Chaussee 3",
    "sg:city":"Goldbeck",
    "sg:phone":"+49 39388/330",
    "sg:postcode":"39596",
    "sg:province":"Sachsen-Anhalt",
    "wof:name":"R. Schulz",
    "wof:placetype":"venue"
},
  "geometry": {"coordinates":[11.86055,52.718266],"type":"Point"}
}