{
  "type": "Feature",
  "properties": {
    "iso:country":"DE",
    "sg:address":"Gerolfinger Str. 106",
    "sg:city":"Ingolstadt",
    "sg:phone":"+49 841/85704",
    "sg:postcode":"85049",
    "sg:province":"Bayern",
    "wof:name":"J. Kijowski",
    "wof:placetype":"venue"
},
  "geometry": {"coordinates":[11.387976,48.763294],"type":"Point"}
}