{
  "type": "Feature",
  "properties": {
    "iso:country":"DE",
    "sg:address":"Ellerstr. 153",
    "sg:city":"Hilden",
    "sg:phone":"+49 2103/31165",
    "sg:postcode":"40721",
    "sg:province":"Nordrhein-Westfalen",
    "wof:name":"Siegfried Opladen",
    "wof:placetype":"venue"
},
  "geometry": {"coordinates":[6.9148259163,51.1728172302],"type":"Point"}
}