{
  "type": "Feature",
  "properties": {
    "iso:country":"DE",
    "sg:address":"Klopstockstr. 21",
    "sg:city":"Bremerhaven",
    "sg:phone":"+49 4961/9629298",
    "sg:postcode":"27570",
    "sg:province":"Bremen",
    "wof:name":"Peter St\u00dclb",
    "wof:placetype":"venue"
},
  "geometry": {"coordinates":[8.496656,50.156921],"type":"Point"}
}