{
  "type": "Feature",
  "properties": {
    "iso:country":"DE",
    "sg:address":"T\u00fcbinger Str. 21",
    "sg:city":"Herrenberg",
    "sg:phone":"+49 7032/23941",
    "sg:postcode":"71083",
    "sg:province":"Baden-W\u00fcrttemberg",
    "wof:name":"Fridolin Spielwaren Gmbh",
    "wof:placetype":"venue"
},
  "geometry": {"coordinates":[8.8713722229,48.5955543518],"type":"Point"}
}