{
  "type": "Feature",
  "properties": {
    "iso:country":"DE",
    "sg:address":"Steingasse 5",
    "sg:city":"Dinkelsb\u00fchl",
    "sg:phone":"+49 9851/6141",
    "sg:postcode":"91550",
    "sg:province":"Bayern",
    "wof:name":"Pizzeria Roma",
    "wof:placetype":"venue"
},
  "geometry": {"coordinates":[10.3181800842,49.0694580078],"type":"Point"}
}