{
  "type": "Feature",
  "properties": {
    "iso:country":"DE",
    "sg:address":"Am M\u00fchlberg 3",
    "sg:city":"Altom\u00fcnster",
    "sg:phone":"+49 8254/424",
    "sg:postcode":"85250",
    "sg:province":"Bayern",
    "wof:name":"Peter Held",
    "wof:placetype":"venue"
},
  "geometry": {"coordinates":[11.21611,48.418995],"type":"Point"}
}