{
  "type": "Feature",
  "properties": {
    "iso:country":"DE",
    "sg:address":"Regensburger Str. 2",
    "sg:city":"Berlin",
    "sg:phone":"+49 30/21478831",
    "sg:postcode":"10777",
    "sg:province":"Berlin",
    "wof:name":"Heinz-g\u00fcnther Bohne Rechtsanwalt",
    "wof:placetype":"venue"
},
  "geometry": {"coordinates":[13.3401498795,52.4959487915],"type":"Point"}
}