{
  "type": "Feature",
  "properties": {
    "iso:country":"DE",
    "sg:address":"Brucknerweg 16",
    "sg:city":"Sarstedt",
    "sg:phone":"+49 5066/5744",
    "sg:postcode":"31157",
    "sg:province":"Niedersachsen",
    "wof:name":"Ralf Paetow Architekt",
    "wof:placetype":"venue"
},
  "geometry": {"coordinates":[9.866869,52.243153],"type":"Point"}
}