{
  "type": "Feature",
  "properties": {
    "iso:country":"DE",
    "sg:address":"C\u00e4cilienstr. 16a",
    "sg:city":"Eschweiler",
    "sg:phone":"+49 2403/21121",
    "sg:postcode":"52249",
    "sg:province":"Nordrhein-Westfalen",
    "wof:name":"C. Mattausch",
    "wof:placetype":"venue"
},
  "geometry": {"coordinates":[6.289730072,50.8099441528],"type":"Point"}
}