{
  "type": "Feature",
  "properties": {
    "iso:country":"DE",
    "sg:address":"An der Steinert 7",
    "sg:city":"L\u00fcdenscheid",
    "sg:phone":"+49 2351/96880",
    "sg:postcode":"58507",
    "sg:province":"Nordrhein-Westfalen",
    "wof:name":"Wilhelm M\u00fcller Gmbh",
    "wof:placetype":"venue"
},
  "geometry": {"coordinates":[7.613821,51.22855],"type":"Point"}
}