{
  "type": "Feature",
  "properties": {
    "iso:country":"DE",
    "sg:address":"Silcherstr. 6",
    "sg:city":"Marxzell",
    "sg:phone":"+49 7248/1230",
    "sg:postcode":"76359",
    "sg:province":"Baden-W\u00fcrttemberg",
    "wof:name":"Lothar Steiner",
    "wof:placetype":"venue"
},
  "geometry": {"coordinates":[8.459668,48.864101],"type":"Point"}
}