{
  "type": "Feature",
  "properties": {
    "iso:country":"DE",
    "sg:address":"Kaiserallee 2a",
    "sg:city":"L\u00fcbeck",
    "sg:phone":"+49 4502/75057",
    "sg:postcode":"23570",
    "sg:province":"Schleswig-Holstein",
    "wof:name":"Hotel Atlantic Inh. Gabriele Ibl E. K.",
    "wof:placetype":"venue"
},
  "geometry": {"coordinates":[10.8791885376,53.9653244019],"type":"Point"}
}