{
  "type": "Feature",
  "properties": {
    "iso:country":"DE",
    "sg:address":"Wilhelmstr. 3",
    "sg:city":"Kirchdorf",
    "sg:phone":"+49 9928/1618",
    "sg:postcode":"94261",
    "sg:province":"Bayern",
    "wof:name":"Alois Perl",
    "wof:placetype":"venue"
},
  "geometry": {"coordinates":[13.2660856247,48.9103660583],"type":"Point"}
}