{
  "type": "Feature",
  "properties": {
    "iso:country":"DE",
    "sg:address":"Heyerstr. 6",
    "sg:city":"L\u00f6derburg",
    "sg:phone":"+49 39265/429",
    "sg:postcode":"39446",
    "sg:province":"Sachsen-Anhalt",
    "wof:name":"Erich Sachtleben",
    "wof:placetype":"venue"
},
  "geometry": {"coordinates":[11.543019,51.88324],"type":"Point"}
}