{
  "type": "Feature",
  "properties": {
    "iso:country":"DE",
    "sg:address":"Kaiserstr. 86",
    "sg:city":"Mandelbachtal",
    "sg:phone":"+49 6804/6248",
    "sg:postcode":"66399",
    "sg:province":"Saarland",
    "wof:name":"Belles Fleurs",
    "wof:placetype":"venue"
},
  "geometry": {"coordinates":[7.160428,49.171547],"type":"Point"}
}