{
  "type": "Feature",
  "properties": {
    "iso:country":"DE",
    "sg:address":"Rote Str. 8",
    "sg:city":"Flensburg",
    "sg:phone":"+49 461/22111",
    "sg:postcode":"24937",
    "sg:province":"Schleswig-Holstein",
    "wof:name":"Aug. Harms Gmbh & Co.",
    "wof:placetype":"venue"
},
  "geometry": {"coordinates":[9.4354753494,54.7821235657],"type":"Point"}
}