{
  "type": "Feature",
  "properties": {
    "iso:country":"DE",
    "sg:address":"Rolandstr. 2",
    "sg:city":"Berlin",
    "sg:phone":"+49 30/8038047",
    "sg:postcode":"14129",
    "sg:province":"Berlin",
    "wof:name":"Haus Matterhorn",
    "wof:placetype":"venue"
},
  "geometry": {"coordinates":[13.203717,52.43491],"type":"Point"}
}