{
  "type": "Feature",
  "properties": {
    "iso:country":"DE",
    "sg:address":"Siegener Str. 447",
    "sg:city":"Freudenberg",
    "sg:phone":"+49 2734/7192",
    "sg:postcode":"57258",
    "sg:province":"Nordrhein-Westfalen",
    "wof:name":"G. R\u00f6cher",
    "wof:placetype":"venue"
},
  "geometry": {"coordinates":[7.9396910667,50.8922958374],"type":"Point"}
}