{
  "type": "Feature",
  "properties": {
    "iso:country":"DE",
    "sg:address":"Wallfahrtsstra\u00dfe 3",
    "sg:city":"Triberg",
    "sg:phone":"+49 4907/722",
    "sg:postcode":"78098",
    "sg:province":"Baden-W\u00fcrttemberg",
    "wof:name":"Landgasthof Zur Lilie Am Wasserfall",
    "wof:placetype":"venue"
},
  "geometry": {"coordinates":[8.2300786972,48.1286773682],"type":"Point"}
}