{
  "type": "Feature",
  "properties": {
    "iso:country":"DE",
    "sg:address":"Gewerberg. 6",
    "sg:city":"Schalksm\u00fchle",
    "sg:phone":"+49 4923/552064",
    "sg:postcode":"58579",
    "sg:province":"Nordrhein-Westfalen",
    "wof:name":"Karl Ley Gmbh",
    "wof:placetype":"venue"
},
  "geometry": {"coordinates":[7.549379,51.258587],"type":"Point"}
}