{
  "type": "Feature",
  "properties": {
    "iso:country":"DE",
    "sg:address":"Gehrdener Weg 37",
    "sg:city":"Paderborn",
    "sg:phone":"+49 5251/640862",
    "sg:postcode":"33100",
    "sg:province":"Nordrhein-Westfalen",
    "wof:name":"Pabeba Verlag Klaus Ortmann",
    "wof:placetype":"venue"
},
  "geometry": {"coordinates":[8.7860221863,51.7094612122],"type":"Point"}
}