{
  "type": "Feature",
  "properties": {
    "iso:country":"DE",
    "sg:address":"Feuerbachstr. 21",
    "sg:city":"Leipzig",
    "sg:phone":"+49 341/9806610",
    "sg:postcode":"04105",
    "sg:province":"Sachsen",
    "wof:name":"K. Schultz",
    "wof:placetype":"venue"
},
  "geometry": {"coordinates":[12.355344,51.345592],"type":"Point"}
}