{
  "type": "Feature",
  "properties": {
    "iso:country":"DE",
    "sg:address":"Bengelsdorfstr. 19",
    "sg:city":"Hamburg",
    "sg:phone":"+49 40/6956400",
    "sg:postcode":"22179",
    "sg:province":"Hamburg",
    "wof:name":"K.-p. Hopp",
    "wof:placetype":"venue"
},
  "geometry": {"coordinates":[10.095419,53.598251],"type":"Point"}
}