{
  "type": "Feature",
  "properties": {
    "iso:country":"DE",
    "sg:address":"Balinger Str. 23",
    "sg:city":"Rosenfeld",
    "sg:phone":"+49 7428/8310",
    "sg:postcode":"72348",
    "sg:province":"Baden-W\u00fcrttemberg",
    "wof:name":"Eberhard Stotz",
    "wof:placetype":"venue"
},
  "geometry": {"coordinates":[8.725709,48.286694],"type":"Point"}
}