{
  "type": "Feature",
  "properties": {
    "iso:country":"DE",
    "sg:address":"Plieninger Str. 150",
    "sg:city":"Stuttgart",
    "sg:postcode":"70567",
    "sg:province":"Baden-W\u00fcrttemberg",
    "wof:name":"Radio-kombiwerbung Baden-w\u00fcrttemberg Gmbh",
    "wof:placetype":"venue"
},
  "geometry": {"coordinates":[9.16944,48.721485],"type":"Point"}
}