{
  "type": "Feature",
  "properties": {
    "iso:country":"DE",
    "sg:address":"Landwirtschaftsring 19",
    "sg:city":"Zappendorf",
    "sg:phone":"+49 34609/20309",
    "sg:postcode":"06179",
    "sg:province":"Sachsen-Anhalt",
    "wof:name":"Marquardt Verwaltungs Gmbh",
    "wof:placetype":"venue"
},
  "geometry": {"coordinates":[11.812202,51.497871],"type":"Point"}
}