{
  "type": "Feature",
  "properties": {
    "iso:country":"DE",
    "sg:address":"Badenstr. 1",
    "sg:city":"Stralsund",
    "sg:phone":"+49 3831/292544",
    "sg:postcode":"18439",
    "sg:province":"Mecklenburg-Vorpommern",
    "wof:name":"C. Stabenow Ohg",
    "wof:placetype":"venue"
},
  "geometry": {"coordinates":[13.0901184082,54.3149223328],"type":"Point"}
}