{
  "type": "Feature",
  "properties": {
    "iso:country":"DE",
    "sg:address":"Wiersbergstr. 12",
    "sg:city":"K\u00f6ln",
    "sg:phone":"+49 221/8701922",
    "sg:postcode":"51103",
    "sg:province":"Nordrhein-Westfalen",
    "wof:name":"Hotel B\u00f6hmer",
    "wof:placetype":"venue"
},
  "geometry": {"coordinates":[7.008207798,50.9381103516],"type":"Point"}
}