{
  "type": "Feature",
  "properties": {
    "iso:country":"DE",
    "sg:address":"Wedauer Str. 38",
    "sg:city":"Ratingen",
    "sg:phone":"+49 2102/35733",
    "sg:postcode":"40885",
    "sg:province":"Nordrhein-Westfalen",
    "wof:name":"Bohn & Schweiger Gmbh Kunstoff Und Alufenster T\u00fcren",
    "wof:placetype":"venue"
},
  "geometry": {"coordinates":[6.826843,51.337715],"type":"Point"}
}