{
  "type": "Feature",
  "properties": {
    "iso:country":"DE",
    "sg:address":"N\u00fcrnberger Str. 7",
    "sg:city":"Frankenthal",
    "sg:phone":"+49 6233/26996",
    "sg:postcode":"67227",
    "sg:province":"Rheinland-Pfalz",
    "wof:name":"F. Trageser",
    "wof:placetype":"venue"
},
  "geometry": {"coordinates":[8.357585,49.534172],"type":"Point"}
}