{
  "type": "Feature",
  "properties": {
    "iso:country":"DE",
    "sg:address":"Fritz-Reuter-Str. 13",
    "sg:city":"L\u00fcbeck",
    "sg:phone":"+49 451/798180",
    "sg:postcode":"23564",
    "sg:province":"Schleswig-Holstein",
    "wof:name":"M\u00fchlentor Senioren Residenz Betriebsges. Mbh & Co. Kg",
    "wof:placetype":"venue"
},
  "geometry": {"coordinates":[10.694844,53.852001],"type":"Point"}
}