{
  "type": "Feature",
  "properties": {
    "iso:country":"DE",
    "sg:address":"Landsberger Str. 398::",
    "sg:city":"Muenchen",
    "sg:phone":"+49 89/5467450",
    "sg:postcode":"81241",
    "sg:province":"Bayern",
    "wof:name":"Infodata Rechenzentrum Gmbh M\u00dcnchen",
    "wof:placetype":"venue"
},
  "geometry": {"coordinates":[11.48201,48.145229],"type":"Point"}
}