{
  "type": "Feature",
  "properties": {
    "iso:country":"DE",
    "sg:address":"Mindener Str. 1",
    "sg:city":"Eslohe",
    "sg:phone":"+49 2973/434",
    "sg:postcode":"59889",
    "sg:province":"Nordrhein-Westfalen",
    "wof:name":"J. Friedrichs Inh. W. Friedrichs",
    "wof:placetype":"venue"
},
  "geometry": {"coordinates":[8.200788,51.251377],"type":"Point"}
}