{
  "type": "Feature",
  "properties": {
    "iso:country":"DE",
    "sg:address":"Begastr. 8",
    "sg:city":"Bad Salzuflen",
    "sg:phone":"+49 5222/81249",
    "sg:postcode":"32108",
    "sg:province":"Nordrhein-Westfalen",
    "wof:name":"Eiscafe Roma",
    "wof:placetype":"venue"
},
  "geometry": {"coordinates":[8.757366,52.071087],"type":"Point"}
}