{
  "type": "Feature",
  "properties": {
    "iso:country":"DE",
    "sg:address":"Marbachweg 9",
    "sg:city":"Passau",
    "sg:postcode":"94036",
    "sg:province":"Bayern",
    "wof:name":"Varga Heizungsbau Gmbh & Co. Kg",
    "wof:placetype":"venue"
},
  "geometry": {"coordinates":[13.3820724487,48.5586204529],"type":"Point"}
}