{
  "type": "Feature",
  "properties": {
    "iso:country":"DE",
    "sg:address":"Aplerbecker Str. 456",
    "sg:city":"Dortmund",
    "sg:phone":"+49 231/945130",
    "sg:postcode":"44287",
    "sg:province":"Nordrhein-Westfalen",
    "wof:name":"Euromold Gmbh",
    "wof:placetype":"venue"
},
  "geometry": {"coordinates":[7.5606889725,51.4999389648],"type":"Point"}
}