{
  "type": "Feature",
  "properties": {
    "iso:country":"DE",
    "sg:address":"M\u00fclheimer Str. 10",
    "sg:city":"Essen",
    "sg:phone":"+49 4920/1705288",
    "sg:postcode":"45145",
    "sg:province":"Nordrhein-Westfalen",
    "wof:name":"Butzin Gmbh",
    "wof:placetype":"venue"
},
  "geometry": {"coordinates":[6.9795160294,51.4486274719],"type":"Point"}
}