{
  "type": "Feature",
  "properties": {
    "iso:country":"DE",
    "sg:address":"Pfannenstr. 11",
    "sg:city":"Grevenbroich",
    "sg:phone":"+49 2182/2538",
    "sg:postcode":"41516",
    "sg:province":"Nordrhein-Westfalen",
    "wof:name":"Rudolf Schumacher",
    "wof:placetype":"venue"
},
  "geometry": {"coordinates":[6.588196,51.122566],"type":"Point"}
}