{
  "type": "Feature",
  "properties": {
    "iso:country":"DE",
    "sg:address":"Marktstr. 10",
    "sg:city":"Warburg",
    "sg:phone":"+49 5641/4203",
    "sg:postcode":"34414",
    "sg:province":"Nordrhein-Westfalen",
    "wof:name":"Dieter Str\u00fcbig Masseur",
    "wof:placetype":"venue"
},
  "geometry": {"coordinates":[9.147414,51.488491],"type":"Point"}
}