{
  "type": "Feature",
  "properties": {
    "iso:country":"DE",
    "sg:address":"Berghoffstr. 28",
    "sg:city":"Osnabr\u00fcck",
    "sg:phone":"+49 4954/1962060",
    "sg:postcode":"49090",
    "sg:province":"Niedersachsen",
    "wof:name":"E Schr\u00d6der Getr\u00c4nke Gmbh",
    "wof:placetype":"venue"
},
  "geometry": {"coordinates":[8.027515,52.288246],"type":"Point"}
}