{
  "type": "Feature",
  "properties": {
    "iso:country":"DE",
    "sg:address":"Hofgartenstr. 87",
    "sg:city":"Schorndorf",
    "sg:phone":"+49 7181/24782",
    "sg:postcode":"73614",
    "sg:province":"Baden-W\u00fcrttemberg",
    "wof:name":"Wolfgang H\u00e4ndschke Ingenieur",
    "wof:placetype":"venue"
},
  "geometry": {"coordinates":[9.5495948792,48.8337211609],"type":"Point"}
}