{
  "type": "Feature",
  "properties": {
    "iso:country":"DE",
    "sg:address":"Lindenstr. 20",
    "sg:city":"Vehlow",
    "sg:phone":"+49 33976/50260",
    "sg:postcode":"16866",
    "sg:province":"Brandenburg",
    "wof:name":"Bernd Thiele",
    "wof:placetype":"venue"
},
  "geometry": {"coordinates":[12.32139,53.011734],"type":"Point"}
}