{
  "type": "Feature",
  "properties": {
    "iso:country":"DE",
    "sg:address":"Kobellstr. 2 a",
    "sg:city":"M\u00fcnchen",
    "sg:postcode":"80336",
    "sg:province":"Bayern",
    "wof:name":"Meatra Gmbh",
    "wof:placetype":"venue"
},
  "geometry": {"coordinates":[11.5551357269,48.1287994385],"type":"Point"}
}