{
  "type": "Feature",
  "properties": {
    "iso:country":"DE",
    "sg:address":"Rhinstr. 77",
    "sg:city":"Berlin",
    "sg:phone":"+49 30/5410200",
    "sg:postcode":"10315",
    "sg:province":"Berlin",
    "wof:name":"Sabine Symkowitz",
    "wof:placetype":"venue"
},
  "geometry": {"coordinates":[13.51918,52.52533],"type":"Point"}
}