{
  "type": "Feature",
  "properties": {
    "iso:country":"DE",
    "sg:address":"Montanstr. 17",
    "sg:city":"Berlin",
    "sg:phone":"+49 30/4088930",
    "sg:postcode":"13407",
    "sg:province":"Berlin",
    "wof:name":"Bartscherer & Co. Recycling Gmbh",
    "wof:placetype":"venue"
},
  "geometry": {"coordinates":[13.352425,52.581448],"type":"Point"}
}