{
  "type": "Feature",
  "properties": {
    "iso:country":"DE",
    "sg:address":"Sportplatzstr. 1",
    "sg:city":"Ranschbach",
    "sg:phone":"+49 6345/1407",
    "sg:postcode":"76829",
    "sg:province":"Rheinland-Pfalz",
    "wof:name":"R. Morio",
    "wof:placetype":"venue"
},
  "geometry": {"coordinates":[8.0374011993,49.1981887817],"type":"Point"}
}