{
  "type": "Feature",
  "properties": {
    "iso:country":"DE",
    "sg:address":"Kirchstr. 5",
    "sg:city":"Simonswald",
    "sg:phone":"+49 7683/859",
    "sg:postcode":"79263",
    "sg:province":"Baden-W\u00fcrttemberg",
    "wof:name":"H. Und H. Wehrle",
    "wof:placetype":"venue"
},
  "geometry": {"coordinates":[8.0570697784,48.1006202698],"type":"Point"}
}