{
  "type": "Feature",
  "properties": {
    "iso:country":"DE",
    "sg:address":"Hauptstr. 9",
    "sg:city":"Legden",
    "sg:phone":"+49 2566/4158",
    "sg:postcode":"48739",
    "sg:province":"Nordrhein-Westfalen",
    "wof:name":"Gastst\u00e4tte Franz Stegerhof",
    "wof:placetype":"venue"
},
  "geometry": {"coordinates":[7.1049418449,52.0304260254],"type":"Point"}
}