{
  "type": "Feature",
  "properties": {
    "iso:country":"DE",
    "sg:address":"Rosenweg 149",
    "sg:city":"Alfstedt",
    "sg:postcode":"27432",
    "sg:province":"Niedersachsen",
    "wof:name":"Sybra Brandschutzsysteme Und Bau-consulting Gmbh",
    "wof:placetype":"venue"
},
  "geometry": {"coordinates":[9.0697,53.549381],"type":"Point"}
}