{
  "type": "Feature",
  "properties": {
    "iso:country":"DE",
    "sg:address":"Rechterfelder Str. 36",
    "sg:city":"Visbek",
    "sg:phone":"+49 4445/961440",
    "sg:postcode":"49429",
    "sg:province":"Niedersachsen",
    "wof:name":"Kohlhoff",
    "wof:placetype":"venue"
},
  "geometry": {"coordinates":[8.3193902969,52.8364715576],"type":"Point"}
}