{
  "type": "Feature",
  "properties": {
    "iso:country":"DE",
    "sg:address":"Lindenstr. 35",
    "sg:city":"Hohenwestedt",
    "sg:phone":"+49 4871/1384",
    "sg:postcode":"24594",
    "sg:province":"Schleswig-Holstein",
    "wof:name":"Hans-dietrich T\u00f6fflinger",
    "wof:placetype":"venue"
},
  "geometry": {"coordinates":[9.655011,54.0896],"type":"Point"}
}