{
  "type": "Feature",
  "properties": {
    "iso:country":"DE",
    "sg:address":"Schmiedstr. 9",
    "sg:city":"Ellwangen",
    "sg:phone":"+49 7961/2203",
    "sg:postcode":"73479",
    "sg:province":"Baden-W\u00fcrttemberg",
    "wof:name":"Andreas Herbst",
    "wof:placetype":"venue"
},
  "geometry": {"coordinates":[10.1303777695,48.9617156982],"type":"Point"}
}