{
  "type": "Feature",
  "properties": {
    "iso:country":"DE",
    "sg:address":"Weinstr. 1",
    "sg:city":"Maikammer",
    "sg:phone":"+49 6321/5109",
    "sg:postcode":"67487",
    "sg:province":"Rheinland-Pfalz",
    "wof:name":"Liesel Mack",
    "wof:placetype":"venue"
},
  "geometry": {"coordinates":[8.1305980682,49.3050460815],"type":"Point"}
}