{
  "type": "Feature",
  "properties": {
    "iso:country":"DE",
    "sg:address":"Akazienstr. 18",
    "sg:city":"Soest",
    "sg:phone":"+49 2921/73354",
    "sg:postcode":"59494",
    "sg:province":"Nordrhein-Westfalen",
    "wof:name":"Kath. \u00f6ffentliche Bibliothek St. Bruno",
    "wof:placetype":"venue"
},
  "geometry": {"coordinates":[8.121425,51.561127],"type":"Point"}
}