{
  "type": "Feature",
  "properties": {
    "iso:country":"DE",
    "sg:address":"Hof Hoffeld 1",
    "sg:city":"K\u00f6nigheim",
    "sg:phone":"+49 9340/92010",
    "sg:postcode":"97953",
    "sg:province":"Baden-W\u00fcrttemberg",
    "wof:name":"Ahorn Wohnmobilie Verwaltungs Gmbh",
    "wof:placetype":"venue"
},
  "geometry": {"coordinates":[9.5373477936,49.5978965759],"type":"Point"}
}