{
  "type": "Feature",
  "properties": {
    "iso:country":"DE",
    "sg:address":"Steinhauerstr. 58",
    "sg:city":"Springe",
    "sg:phone":"+49 5041/8424",
    "sg:postcode":"31832",
    "sg:province":"Niedersachsen",
    "wof:name":"Busch Blumenstudio",
    "wof:placetype":"venue"
},
  "geometry": {"coordinates":[9.625089,52.217209],"type":"Point"}
}