{
  "type": "Feature",
  "properties": {
    "iso:country":"DE",
    "sg:address":"M\u00fchlenstr. 81",
    "sg:city":"Leer",
    "sg:phone":"+49 491/64544",
    "sg:postcode":"26789",
    "sg:province":"Niedersachsen",
    "wof:name":"Kaisers Kaffee-gesch\u00e4ft Ag",
    "wof:placetype":"venue"
},
  "geometry": {"coordinates":[7.4570097923,53.2301483154],"type":"Point"}
}