{
  "type": "Feature",
  "properties": {
    "iso:country":"DE",
    "sg:address":"Am Breiten Tor 5",
    "sg:city":"Lahstedt",
    "sg:phone":"+49 5172/8878",
    "sg:postcode":"31246",
    "sg:province":"Niedersachsen",
    "wof:name":"Hans-henning R\u00f6semann",
    "wof:placetype":"venue"
},
  "geometry": {"coordinates":[10.215768,52.243446],"type":"Point"}
}