{
  "type": "Feature",
  "properties": {
    "iso:country":"DE",
    "sg:address":"Kremmlerstr. 1",
    "sg:city":"Stuttgart",
    "sg:phone":"+49 711/7651806",
    "sg:postcode":"70597",
    "sg:province":"Baden-W\u00fcrttemberg",
    "wof:name":"Hallenbad Sonnenberg",
    "wof:placetype":"venue"
},
  "geometry": {"coordinates":[9.1520700455,48.7403068542],"type":"Point"}
}