{
  "type": "Feature",
  "properties": {
    "iso:country":"DE",
    "sg:address":"Ammergasse 19",
    "sg:city":"T\u00fcbingen",
    "sg:phone":"+49 7071/550662",
    "sg:postcode":"72070",
    "sg:province":"Baden-W\u00fcrttemberg",
    "wof:name":"Bmz Technisch-wissen- Schaftliche Software Gmbh",
    "wof:placetype":"venue"
},
  "geometry": {"coordinates":[9.05027771,48.5206794739],"type":"Point"}
}