{
  "type": "Feature",
  "properties": {
    "iso:country":"DE",
    "sg:address":"Nettesheimer Weg",
    "sg:city":"Rommerskirchen",
    "sg:phone":"+49 2182/9244",
    "sg:postcode":"41569",
    "sg:province":"Nordrhein-Westfalen",
    "wof:name":"Hallenbad",
    "wof:placetype":"venue"
},
  "geometry": {"coordinates":[6.6849298477,51.0356254578],"type":"Point"}
}