{
  "type": "Feature",
  "properties": {
    "iso:country":"DE",
    "sg:address":"Mackensenstr. 20",
    "sg:city":"Gronau",
    "sg:phone":"+49 2562/23010",
    "sg:postcode":"48599",
    "sg:province":"Nordrhein-Westfalen",
    "wof:name":"G\u00fcnther Mengelkamp Ohg",
    "wof:placetype":"venue"
},
  "geometry": {"coordinates":[7.001502037,52.211517334],"type":"Point"}
}