{
  "type": "Feature",
  "properties": {
    "iso:country":"DE",
    "sg:address":"Schlo\u00dfgartenweg 6",
    "sg:city":"Ermershausen",
    "sg:phone":"+49 9532/268",
    "sg:postcode":"96126",
    "sg:province":"Bayern",
    "wof:name":"Friedrich Kirchner",
    "wof:placetype":"venue"
},
  "geometry": {"coordinates":[10.621924,50.210541],"type":"Point"}
}