{
  "type": "Feature",
  "properties": {
    "iso:country":"DE",
    "sg:address":"Berliner Str. 14",
    "sg:city":"Seeheim-Jugenheim",
    "sg:phone":"+49 6257/868102",
    "sg:postcode":"64342",
    "sg:province":"Hessen",
    "wof:name":"Farbfoto Schnellservice S. K\u00fcbe Gmbh",
    "wof:placetype":"venue"
},
  "geometry": {"coordinates":[8.6327962875,49.7760887146],"type":"Point"}
}