{
  "type": "Feature",
  "properties": {
    "iso:country":"DE",
    "sg:address":"Am Winkelbusch 17",
    "sg:city":"Senden",
    "sg:phone":"+49 2597/98305",
    "sg:postcode":"48308",
    "sg:province":"Nordrhein-Westfalen",
    "wof:name":"R. Und A. Nienhaus Ingenieure",
    "wof:placetype":"venue"
},
  "geometry": {"coordinates":[7.4772911072,51.8578605652],"type":"Point"}
}