{
  "type": "Feature",
  "properties": {
    "iso:country":"DE",
    "sg:address":"Brunnenplatz 6",
    "sg:city":"Berg",
    "sg:phone":"+49 4975/141700",
    "sg:postcode":"88276",
    "sg:province":"Baden-W\u00fcrttemberg",
    "wof:name":"Kreissparkasse Berg",
    "wof:placetype":"venue"
},
  "geometry": {"coordinates":[9.602619,47.809937],"type":"Point"}
}