{
  "type": "Feature",
  "properties": {
    "iso:country":"DE",
    "sg:address":"Siemensstr. 19",
    "sg:city":"Eutin",
    "sg:phone":"+49 4521/70260",
    "sg:postcode":"23701",
    "sg:province":"Schleswig-Holstein",
    "wof:name":"Ostholsteiner Behinderten- Hilfe Ggmbh",
    "wof:placetype":"venue"
},
  "geometry": {"coordinates":[10.6222000122,54.123260498],"type":"Point"}
}