{
  "type": "Feature",
  "properties": {
    "iso:country":"DE",
    "sg:address":"asfasf",
    "sg:city":"asfasf",
    "sg:phone":"+49 6546/54654",
    "sg:postcode":"88885",
    "wof:name":"Willkommen Bei Www.swissdeejays.ch",
    "wof:placetype":"venue"
},
  "geometry": {"coordinates":[-97.941597,25.399191],"type":"Point"}
}