{
  "type": "Feature",
  "properties": {
    "iso:country":"DE",
    "sg:address":"Tannenweg 13",
    "sg:city":"Altenstadt",
    "sg:phone":"+49 6047/67128",
    "sg:postcode":"63674",
    "sg:province":"Hessen",
    "wof:name":"J. Lohse",
    "wof:placetype":"venue"
},
  "geometry": {"coordinates":[8.9753789902,50.2685317993],"type":"Point"}
}