{
  "type": "Feature",
  "properties": {
    "iso:country":"DE",
    "sg:address":"Beethovenstr. 56",
    "sg:city":"Gummersbach",
    "sg:phone":"+49 2261/26047",
    "sg:postcode":"51643",
    "sg:province":"Nordrhein-Westfalen",
    "wof:name":"Ulrich Hunscher Ingenieur",
    "wof:placetype":"venue"
},
  "geometry": {"coordinates":[7.5232610703,51.0119056702],"type":"Point"}
}