{
  "type": "Feature",
  "properties": {
    "iso:country":"DE",
    "sg:address":"In den Blumentriften 44",
    "sg:city":"Salzgitter",
    "sg:phone":"+49 5341/46951",
    "sg:postcode":"38226",
    "sg:province":"Niedersachsen",
    "wof:name":"Niedersachsen-foto",
    "wof:placetype":"venue"
},
  "geometry": {"coordinates":[10.329466,52.154541],"type":"Point"}
}