{
  "type": "Feature",
  "properties": {
    "iso:country":"DE",
    "sg:address":"Paul-Greifzu-Str. 1b",
    "sg:city":"Riesa",
    "sg:phone":"+49 3525/735254",
    "sg:postcode":"01591",
    "sg:province":"Sachsen",
    "wof:name":"Harzbecker Heizung-l\u00fcftung- Klima-sanit\u00e4rtechnik",
    "wof:placetype":"venue"
},
  "geometry": {"coordinates":[13.2782011032,51.3173179626],"type":"Point"}
}