{
  "type": "Feature",
  "properties": {
    "iso:country":"DE",
    "sg:address":"Stra\u00dfe der Freundschaft 11",
    "sg:city":"Geyer",
    "sg:phone":"+49 37346/1483",
    "sg:postcode":"09468",
    "sg:province":"Sachsen",
    "wof:name":"Edgar Schubert",
    "wof:placetype":"venue"
},
  "geometry": {"coordinates":[12.922964,50.625042],"type":"Point"}
}