{
  "type": "Feature",
  "properties": {
    "iso:country":"DE",
    "sg:address":"Taunusstr. 6",
    "sg:city":"Pohlheim",
    "sg:phone":"+49 6403/1226",
    "sg:postcode":"35415",
    "sg:province":"Hessen",
    "wof:name":"Beate H\u00f6lscher",
    "wof:placetype":"venue"
},
  "geometry": {"coordinates":[8.7294921875,50.5111083984],"type":"Point"}
}