{
  "type": "Feature",
  "properties": {
    "iso:country":"DE",
    "sg:address":"Berghausener Str. 39",
    "sg:city":"Langenfeld",
    "sg:phone":"+49 2173/989450",
    "sg:postcode":"40764",
    "sg:province":"Nordrhein-Westfalen",
    "wof:name":"Sfvv Sport + Freizeit Vertriebs- Und",
    "wof:placetype":"venue"
},
  "geometry": {"coordinates":[6.9454569817,51.1247825623],"type":"Point"}
}