{
  "type": "Feature",
  "properties": {
    "iso:country":"DE",
    "sg:address":"Fritz-Hofmann-Weg 3",
    "sg:city":"Merseburg",
    "sg:phone":"+49 3461/722444",
    "sg:postcode":"06217",
    "sg:province":"Sachsen-Anhalt",
    "wof:name":"E. Dierks",
    "wof:placetype":"venue"
},
  "geometry": {"coordinates":[11.9705810547,51.3454971313],"type":"Point"}
}