{
  "type": "Feature",
  "properties": {
    "iso:country":"DE",
    "sg:address":"Otto-Toussaint-Str. 7",
    "sg:city":"St. Ingbert",
    "sg:phone":"+49 6894/381008",
    "sg:postcode":"66386",
    "sg:province":"Saarland",
    "wof:name":"China-wintergarten",
    "wof:placetype":"venue"
},
  "geometry": {"coordinates":[7.1174249649,49.2808570862],"type":"Point"}
}