{
  "type": "Feature",
  "properties": {
    "iso:country":"DE",
    "sg:address":"Kindergartenweg 4",
    "sg:city":"Grabenstetten",
    "sg:phone":"+49 7382/284",
    "sg:postcode":"72582",
    "sg:province":"Baden-W\u00fcrttemberg",
    "wof:name":"Roland Klingler Ingenieur",
    "wof:placetype":"venue"
},
  "geometry": {"coordinates":[9.4629116058,48.5227432251],"type":"Point"}
}