{
  "type": "Feature",
  "properties": {
    "iso:country":"DE",
    "sg:address":"Otto-Lilienthal-Str. 24",
    "sg:city":"B\u00f6blingen",
    "sg:phone":"+49 7031/4402",
    "sg:postcode":"71034",
    "sg:province":"Baden-W\u00fcrttemberg",
    "wof:name":"Multi-center Warenvertriebs- Verwaltungs- Gmbh",
    "wof:placetype":"venue"
},
  "geometry": {"coordinates":[8.983036,48.684261],"type":"Point"}
}