{
  "type": "Feature",
  "properties": {
    "iso:country":"DE",
    "sg:address":"Maria-Eich-Str. 22",
    "sg:city":"M\u00fcnchen",
    "sg:phone":"+49 89/8346917",
    "sg:postcode":"81243",
    "sg:province":"Bayern",
    "wof:name":"Pap Brennicke Gmbh",
    "wof:placetype":"venue"
},
  "geometry": {"coordinates":[11.451692,48.143372],"type":"Point"}
}