{
  "type": "Feature",
  "properties": {
    "iso:country":"DE",
    "sg:address":"Weber Stra\u00dfe 3",
    "sg:city":"Arnsberg",
    "sg:phone":"+49 2932/35278",
    "sg:postcode":"59757",
    "sg:province":"Nordrhein-Westfalen",
    "wof:name":"Heinrich Walter Gmbh",
    "wof:placetype":"venue"
},
  "geometry": {"coordinates":[7.9604997635,51.4337501526],"type":"Point"}
}