{
  "type": "Feature",
  "properties": {
    "iso:country":"DE",
    "sg:address":"Winkelstr. 7",
    "sg:city":"Almstedt",
    "sg:phone":"+49 5065/8258",
    "sg:postcode":"31079",
    "sg:province":"Niedersachsen",
    "wof:name":"Gustav Rien",
    "wof:placetype":"venue"
},
  "geometry": {"coordinates":[9.9415311813,52.0347290039],"type":"Point"}
}