{
  "type": "Feature",
  "properties": {
    "iso:country":"DE",
    "sg:address":"Uhlandstr. 21",
    "sg:city":"Gladbeck",
    "sg:postcode":"45964",
    "sg:province":"Nordrhein-Westfalen",
    "wof:name":"Stern Flugreisen Gmbh",
    "wof:placetype":"venue"
},
  "geometry": {"coordinates":[6.9916958809,51.5687866211],"type":"Point"}
}