{
  "type": "Feature",
  "properties": {
    "iso:country":"DE",
    "sg:address":"Nordlichtstr. 48/ 50",
    "sg:city":"Berlin",
    "sg:phone":"+49 30/4134041",
    "sg:postcode":"13405",
    "sg:province":"Berlin",
    "wof:name":"H. J. Voigt & Sohn",
    "wof:placetype":"venue"
},
  "geometry": {"coordinates":[13.3202667236,52.5646858215],"type":"Point"}
}