{
  "type": "Feature",
  "properties": {
    "iso:country":"DE",
    "sg:address":"Gartenstr. 2",
    "sg:city":"Neuhausen",
    "sg:phone":"+49 7158/4190",
    "sg:postcode":"73765",
    "sg:province":"Baden-W\u00fcrttemberg",
    "wof:name":"Alfred B\u00e4uerle",
    "wof:placetype":"venue"
},
  "geometry": {"coordinates":[8.778208,48.789654],"type":"Point"}
}