{
  "type": "Feature",
  "properties": {
    "iso:country":"DE",
    "sg:address":"Mantelkam",
    "sg:city":"Kumhausen",
    "sg:phone":"+49 8705/326",
    "sg:postcode":"84036",
    "sg:province":"Bayern",
    "wof:name":"J. Und E. Dax",
    "wof:placetype":"venue"
},
  "geometry": {"coordinates":[12.18703,48.477219],"type":"Point"}
}