{
  "type": "Feature",
  "properties": {
    "iso:country":"DE",
    "sg:address":"Odenwaldstr. 1",
    "sg:city":"Kleinheubach",
    "sg:phone":"+49 9371/67888",
    "sg:postcode":"63924",
    "sg:province":"Bayern",
    "wof:name":"Berg Hetz Und Rauch",
    "wof:placetype":"venue"
},
  "geometry": {"coordinates":[9.2041063309,49.7169303894],"type":"Point"}
}