{
  "type": "Feature",
  "properties": {
    "iso:country":"DE",
    "sg:city":"Rethem",
    "sg:phone":"+49 5165/91119",
    "sg:postcode":"27336",
    "sg:province":"Niedersachsen",
    "wof:name":"Bauhandwerker Rethem- Aller Gmbh",
    "wof:placetype":"venue"
},
  "geometry": {"coordinates":[9.427415,52.769981],"type":"Point"}
}