{
  "type": "Feature",
  "properties": {
    "iso:country":"DE",
    "sg:address":"Elisabethenstr. 32",
    "sg:city":"Gernsheim",
    "sg:postcode":"64579",
    "sg:province":"Hessen",
    "wof:name":"W. B. Baumontage Gmbh",
    "wof:placetype":"venue"
},
  "geometry": {"coordinates":[8.486986,49.756504],"type":"Point"}
}