{
  "type": "Feature",
  "properties": {
    "iso:country":"DE",
    "sg:address":"Fuhrenkamp 56",
    "sg:city":"Buchholz",
    "sg:phone":"+49 4181/5300",
    "sg:postcode":"21244",
    "sg:province":"Niedersachsen",
    "wof:name":"Heinz Husen Gmbh",
    "wof:placetype":"venue"
},
  "geometry": {"coordinates":[9.8713979721,53.3091773987],"type":"Point"}
}