{
  "type": "Feature",
  "properties": {
    "iso:country":"DE",
    "sg:address":"Brandenburgische Str. 2",
    "sg:city":"Berlin",
    "sg:phone":"+49 30/86412384",
    "sg:postcode":"10713",
    "sg:province":"Berlin",
    "wof:name":"Stadtb\u00fccherei Wilmersdorf",
    "wof:placetype":"venue"
},
  "geometry": {"coordinates":[13.319797,52.487152],"type":"Point"}
}