{
  "type": "Feature",
  "properties": {
    "iso:country":"DE",
    "sg:address":"Hubertstr. 312a",
    "sg:city":"Essen",
    "sg:phone":"+49 201/554949",
    "sg:postcode":"45307",
    "sg:province":"Nordrhein-Westfalen",
    "wof:name":"Brinck-druck Gmbh",
    "wof:placetype":"venue"
},
  "geometry": {"coordinates":[7.078437,51.465988],"type":"Point"}
}