{
  "type": "Feature",
  "properties": {
    "iso:country":"DE",
    "sg:address":"Kolpingstr. 2",
    "sg:city":"Bad Homburg",
    "sg:phone":"+49 6172/82500",
    "sg:postcode":"61350",
    "sg:province":"Hessen",
    "wof:name":"Reinhold Sutor Architekt",
    "wof:placetype":"venue"
},
  "geometry": {"coordinates":[8.608653,50.245125],"type":"Point"}
}