{
  "type": "Feature",
  "properties": {
    "iso:country":"DE",
    "sg:address":"In der Burg 4",
    "sg:city":"Felsberg",
    "sg:phone":"+49 5665/6492",
    "sg:postcode":"34587",
    "sg:province":"Hessen",
    "wof:name":"Heinrich Pilgram",
    "wof:placetype":"venue"
},
  "geometry": {"coordinates":[9.444562,51.182457],"type":"Point"}
}