{
  "type": "Feature",
  "properties": {
    "iso:country":"DE",
    "sg:address":"Wulverliet 14",
    "sg:city":"Westerkappeln",
    "sg:phone":"+49 5404/950322",
    "sg:postcode":"49492",
    "sg:province":"Nordrhein-Westfalen",
    "wof:name":"N. Essing Kommunikation Gmbh",
    "wof:placetype":"venue"
},
  "geometry": {"coordinates":[7.8438100815,52.2927894592],"type":"Point"}
}