{
  "type": "Feature",
  "properties": {
    "iso:country":"DE",
    "sg:address":"Ringstr. 19",
    "sg:city":"Weilerswist",
    "sg:phone":"+49 2251/74719",
    "sg:postcode":"53919",
    "sg:province":"Nordrhein-Westfalen",
    "wof:name":"Erwin Fisch",
    "wof:placetype":"venue"
},
  "geometry": {"coordinates":[6.8128581047,50.7023506165],"type":"Point"}
}