{
  "type": "Feature",
  "properties": {
    "iso:country":"DE",
    "sg:address":"M\u00f6nkhofer Weg 44",
    "sg:city":"L\u00fcbeck",
    "sg:phone":"+49 451/594686",
    "sg:postcode":"23562",
    "sg:province":"Schleswig-Holstein",
    "wof:name":"Wolfgang Wloka Papier- Und Schreibwaren",
    "wof:placetype":"venue"
},
  "geometry": {"coordinates":[10.6987333298,53.8506011963],"type":"Point"}
}