{
  "type": "Feature",
  "properties": {
    "iso:country":"DE",
    "sg:address":"Steltenberg 11",
    "sg:city":"Iserlohn",
    "sg:phone":"+49 2374/4021",
    "sg:postcode":"58642",
    "sg:province":"Nordrhein-Westfalen",
    "wof:name":"Uwe B\u00f6hme Gmbh",
    "wof:placetype":"venue"
},
  "geometry": {"coordinates":[7.590801,51.362469],"type":"Point"}
}