{
  "type": "Feature",
  "properties": {
    "iso:country":"DE",
    "sg:address":"Rosenweg 26",
    "sg:city":"R\u00f6merberg",
    "sg:phone":"+49 6232/81415",
    "sg:postcode":"67354",
    "sg:province":"Rheinland-Pfalz",
    "wof:name":"Etzkorn Gmbh",
    "wof:placetype":"venue"
},
  "geometry": {"coordinates":[8.40552,49.291164],"type":"Point"}
}