{
  "type": "Feature",
  "properties": {
    "iso:country":"DE",
    "sg:address":"Im Kuckucksschlag 6",
    "sg:city":"Kaiserslautern",
    "sg:phone":"+49 631/28350",
    "sg:postcode":"67663",
    "sg:province":"Rheinland-Pfalz",
    "wof:name":"Erich Franta Steuerberater",
    "wof:placetype":"venue"
},
  "geometry": {"coordinates":[7.7615170479,49.4290313721],"type":"Point"}
}