{
  "type": "Feature",
  "properties": {
    "iso:country":"DE",
    "sg:address":"Grenzwall",
    "sg:city":"Remscheid",
    "sg:phone":"+49 2191/662285",
    "sg:postcode":"42897",
    "sg:province":"Nordrhein-Westfalen",
    "wof:name":"Siedlerheim",
    "wof:placetype":"venue"
},
  "geometry": {"coordinates":[7.241631031,51.1731719971],"type":"Point"}
}