{
  "type": "Feature",
  "properties": {
    "iso:country":"DE",
    "sg:address":"Magdeburger Str. 31",
    "sg:city":"Glienicke",
    "sg:postcode":"16548",
    "sg:province":"Brandenburg",
    "wof:name":"Ins Ingenieurb\u00fcro Antriebstechniksellin E. Kfm.",
    "wof:placetype":"venue"
},
  "geometry": {"coordinates":[13.3143148422,52.6425628662],"type":"Point"}
}