{
  "type": "Feature",
  "properties": {
    "iso:country":"DE",
    "sg:address":"Am Pappenwerk 1",
    "sg:city":"Gro\u00dfschirma",
    "sg:phone":"+49 37328/89051",
    "sg:postcode":"09603",
    "sg:province":"Sachsen",
    "wof:name":"Kurprinz Georg Keil Gmbh",
    "wof:placetype":"venue"
},
  "geometry": {"coordinates":[13.3087615967,50.9698867798],"type":"Point"}
}