{
  "type": "Feature",
  "properties": {
    "iso:country":"DE",
    "sg:address":"Sperenberger Str. 13",
    "sg:city":"Berlin",
    "sg:phone":"+49 30/720880",
    "sg:postcode":"12277",
    "sg:province":"Berlin",
    "wof:name":"Hawe Inline Hydraulik Gmbh",
    "wof:placetype":"venue"
},
  "geometry": {"coordinates":[13.376883,52.402786],"type":"Point"}
}