{
  "type": "Feature",
  "properties": {
    "iso:country":"DE",
    "sg:address":"Geschwister-Scholl-Str. 136",
    "sg:city":"Bremen",
    "sg:phone":"+49 421/471627",
    "sg:postcode":"28327",
    "sg:province":"Bremen",
    "wof:name":"Ev. Pfarramt Dreifaltigkeits-gemeinde",
    "wof:placetype":"venue"
},
  "geometry": {"coordinates":[8.90928936,53.0785140991],"type":"Point"}
}