{
  "type": "Feature",
  "properties": {
    "iso:country":"DE",
    "sg:address":"Gartenfelder Str. 37",
    "sg:city":"Berlin",
    "sg:phone":"+49 30/3549240",
    "sg:postcode":"13599",
    "sg:province":"Berlin",
    "wof:name":"M\u00fchl & Herlitz Baustoff- Logistik Beteiligungs Gmbh",
    "wof:placetype":"venue"
},
  "geometry": {"coordinates":[13.247926,52.548126],"type":"Point"}
}