{
  "type": "Feature",
  "properties": {
    "iso:country":"DE",
    "sg:address":"Lochmannstr. 2",
    "sg:city":"Leipzig",
    "sg:phone":"+49 341/8622165",
    "sg:postcode":"04299",
    "sg:province":"Sachsen",
    "wof:name":"Heinrich Richter",
    "wof:placetype":"venue"
},
  "geometry": {"coordinates":[12.423441,51.32132],"type":"Point"}
}