{
  "type": "Feature",
  "properties": {
    "iso:country":"DE",
    "sg:address":"Oldenburger Str. 211",
    "sg:city":"Wardenburg",
    "sg:phone":"+49 4407/6544",
    "sg:postcode":"26203",
    "sg:province":"Niedersachsen",
    "wof:name":"Brand Immobilien Inh. Gustav Brand",
    "wof:placetype":"venue"
},
  "geometry": {"coordinates":[8.191857338,53.0661582947],"type":"Point"}
}