{
  "type": "Feature",
  "properties": {
    "iso:country":"DE",
    "sg:address":"An der Unlandsb\u00e4ke 3",
    "sg:city":"Lohne",
    "sg:phone":"+49 4442/3681",
    "sg:postcode":"49393",
    "sg:province":"Niedersachsen",
    "wof:name":"Heinz Kuhlmann",
    "wof:placetype":"venue"
},
  "geometry": {"coordinates":[8.2083215714,52.6677207947],"type":"Point"}
}