{
  "type": "Feature",
  "properties": {
    "iso:country":"DE",
    "sg:address":"Graudenzer Str. 20",
    "sg:city":"D\u00fcsseldorf",
    "sg:phone":"+49 211/742107",
    "sg:postcode":"40599",
    "sg:province":"Nordrhein-Westfalen",
    "wof:name":"Aabk Ambulante-alten- Behinderten- Und Krankenpflege",
    "wof:placetype":"venue"
},
  "geometry": {"coordinates":[6.871733,51.180508],"type":"Point"}
}