{
  "type": "Feature",
  "properties": {
    "iso:country":"DE",
    "sg:address":"H\u00f6fles 32",
    "sg:city":"Kronach",
    "sg:phone":"+49 9261/91151",
    "sg:postcode":"96317",
    "sg:province":"Bayern",
    "wof:name":"Georg Wich",
    "wof:placetype":"venue"
},
  "geometry": {"coordinates":[11.3663463593,50.232635498],"type":"Point"}
}