{
  "type": "Feature",
  "properties": {
    "iso:country":"DE",
    "sg:address":"Hechtstr. 20",
    "sg:city":"Dresden",
    "sg:phone":"+49 351/8039263",
    "sg:postcode":"01097",
    "sg:province":"Sachsen",
    "wof:name":"Gabriele Kambach",
    "wof:placetype":"venue"
},
  "geometry": {"coordinates":[13.746985,51.073837],"type":"Point"}
}