{
  "type": "Feature",
  "properties": {
    "iso:country":"DE",
    "sg:address":"Brahmsstr. 16",
    "sg:city":"Senden",
    "sg:phone":"+49 7307/929500",
    "sg:postcode":"89250",
    "sg:province":"Bayern",
    "wof:name":"Klengel Wohnbau Und Immobilien Gmbh",
    "wof:placetype":"venue"
},
  "geometry": {"coordinates":[10.045745,48.326481],"type":"Point"}
}