{
  "type": "Feature",
  "properties": {
    "iso:country":"DE",
    "sg:address":"Kettershauser Str. 4",
    "sg:city":"Unterroth",
    "sg:phone":"+49 7343/6744",
    "sg:postcode":"89299",
    "sg:province":"Bayern",
    "wof:name":"Wallfahrtsgastst\u00e4tte Petra Dilger",
    "wof:placetype":"venue"
},
  "geometry": {"coordinates":[10.1768865585,48.1964607239],"type":"Point"}
}