{
  "type": "Feature",
  "properties": {
    "iso:country":"DE",
    "sg:address":"Kreuzstr. 2",
    "sg:city":"Kreuzwertheim",
    "sg:phone":"+49 9342/21927",
    "sg:postcode":"97892",
    "sg:province":"Bayern",
    "wof:name":"P. Lanning",
    "wof:placetype":"venue"
},
  "geometry": {"coordinates":[9.51795,49.768253],"type":"Point"}
}