{
  "type": "Feature",
  "properties": {
    "iso:country":"DE",
    "sg:address":"Eisenacher Str. 37",
    "sg:city":"Breitungen",
    "sg:phone":"+49 36848/87398",
    "sg:postcode":"98597",
    "sg:province":"Th\u00fcringen",
    "wof:name":"Pension Gei\u00dfhirt",
    "wof:placetype":"venue"
},
  "geometry": {"coordinates":[10.322842598,50.7657241821],"type":"Point"}
}