{
  "type": "Feature",
  "properties": {
    "iso:country":"DE",
    "sg:address":"Kolkwitzer Str. 11",
    "sg:city":"Cottbus",
    "sg:phone":"+49 355/795842",
    "sg:postcode":"03046",
    "sg:province":"Brandenburg",
    "wof:name":"Christian Firlle & Partner Systemfinanz Dresden Gmbh",
    "wof:placetype":"venue"
},
  "geometry": {"coordinates":[14.3277196884,51.7598495483],"type":"Point"}
}