{
  "type": "Feature",
  "properties": {
    "iso:country":"DE",
    "sg:address":"Klosterstra\u00dfe 23",
    "sg:city":"Angerm\u00fcnde",
    "sg:phone":"+49 3331/297610",
    "sg:postcode":"16278",
    "sg:province":"Brandenburg",
    "wof:name":"Internet-cappucchino",
    "wof:placetype":"venue"
},
  "geometry": {"coordinates":[14.002732,53.015759],"type":"Point"}
}