{
  "type": "Feature",
  "properties": {
    "iso:country":"DE",
    "sg:address":"Eimeldinger Weg 18",
    "sg:city":"Weil am Rhein",
    "sg:phone":"+49 7621/62267",
    "sg:postcode":"79576",
    "sg:province":"Baden-W\u00fcrttemberg",
    "wof:name":"Adam Helfmann Baugesch\u00e4ft E. K.",
    "wof:placetype":"venue"
},
  "geometry": {"coordinates":[7.609412,47.616814],"type":"Point"}
}