{
  "type": "Feature",
  "properties": {
    "iso:country":"DE",
    "sg:address":"Feldstr. 85",
    "sg:city":"Bad Homburg",
    "sg:phone":"+49 6172/41595",
    "sg:postcode":"61352",
    "sg:province":"Hessen",
    "wof:name":"Ernst Sch\u00f6sser",
    "wof:placetype":"venue"
},
  "geometry": {"coordinates":[8.627655,50.218758],"type":"Point"}
}