{
  "type": "Feature",
  "properties": {
    "iso:country":"DE",
    "sg:address":"Hauptstr. 35",
    "sg:city":"\u00dcckeritz",
    "sg:phone":"+49 38375/20600",
    "sg:postcode":"17459",
    "sg:province":"Mecklenburg-Vorpommern",
    "wof:name":"Eis Am Achterwasser Inh. Gerhard Labahn",
    "wof:placetype":"venue"
},
  "geometry": {"coordinates":[14.041327,54.011154],"type":"Point"}
}