{
  "type": "Feature",
  "properties": {
    "iso:country":"DE",
    "sg:address":"Hohensteinstr. 52",
    "sg:city":"Bochum",
    "sg:postcode":"44866",
    "sg:province":"Nordrhein-Westfalen",
    "wof:name":"Grundst\u00fccksverwaltungs- Gesellschaft F. Appelberg Mbh",
    "wof:placetype":"venue"
},
  "geometry": {"coordinates":[7.12134,51.476315],"type":"Point"}
}