{
  "type": "Feature",
  "properties": {
    "iso:country":"DE",
    "sg:address":"Marienfelder Str. 48",
    "sg:city":"Mahlow",
    "sg:phone":"+49 3379/39300",
    "sg:postcode":"15831",
    "sg:province":"Brandenburg",
    "wof:name":"E. K\u00fchnert",
    "wof:placetype":"venue"
},
  "geometry": {"coordinates":[13.3901338577,52.3718299866],"type":"Point"}
}