{
  "type": "Feature",
  "properties": {
    "iso:country":"DE",
    "sg:address":"Haldenstieg 23",
    "sg:city":"Hamburg",
    "sg:phone":"+49 40/5535031",
    "sg:postcode":"22453",
    "sg:province":"Hamburg",
    "wof:name":"J. Kr\u00f6ger & Sohn Gmbh & Co. Kg",
    "wof:placetype":"venue"
},
  "geometry": {"coordinates":[9.968651,53.614338],"type":"Point"}
}