{
  "type": "Feature",
  "properties": {
    "iso:country":"DE",
    "sg:address":"Berliner Str. 30",
    "sg:city":"Erkner",
    "sg:phone":"+49 3362/75826",
    "sg:postcode":"15537",
    "sg:province":"Brandenburg",
    "wof:name":"G\u00fcnter Reichelt",
    "wof:placetype":"venue"
},
  "geometry": {"coordinates":[13.74778,52.4272],"type":"Point"}
}