{
  "type": "Feature",
  "properties": {
    "iso:country":"DE",
    "sg:address":"Spielstr. 1",
    "sg:city":"Offenburg",
    "sg:phone":"+49 781/54429",
    "sg:postcode":"77656",
    "sg:province":"Baden-W\u00fcrttemberg",
    "wof:name":"Hodapp Frietsch & Co. Gmbh",
    "wof:placetype":"venue"
},
  "geometry": {"coordinates":[7.9160308838,48.4861602783],"type":"Point"}
}