{
  "type": "Feature",
  "properties": {
    "iso:country":"DE",
    "sg:address":"Idastr. 60",
    "sg:city":"Krefeld",
    "sg:phone":"+49 2151/5810",
    "sg:postcode":"47809",
    "sg:province":"Nordrhein-Westfalen",
    "wof:name":"Trw Fahrzeugwerksysteme Gmbh & Co. Kg",
    "wof:placetype":"venue"
},
  "geometry": {"coordinates":[6.6331992149,51.3432655334],"type":"Point"}
}