{
  "type": "Feature",
  "properties": {
    "iso:country":"DE",
    "sg:address":"Sonnenstr. 6",
    "sg:city":"Gie\u00dfen",
    "sg:phone":"+49 641/36205",
    "sg:postcode":"35390",
    "sg:province":"Hessen",
    "wof:name":"Muhsin Tatar",
    "wof:placetype":"venue"
},
  "geometry": {"coordinates":[8.6755838394,50.5861206055],"type":"Point"}
}