{
  "type": "Feature",
  "properties": {
    "iso:country":"DE",
    "sg:address":"Bernhardstr. 19",
    "sg:city":"Twistringen",
    "sg:phone":"+49 4243/779",
    "sg:postcode":"27239",
    "sg:province":"Niedersachsen",
    "wof:name":"Schmidt-hygiene Gmbh",
    "wof:placetype":"venue"
},
  "geometry": {"coordinates":[8.6398992538,52.7957611084],"type":"Point"}
}