{
  "type": "Feature",
  "properties": {
    "iso:country":"DE",
    "sg:address":"Witts Allee 8",
    "sg:city":"Hamburg",
    "sg:phone":"+49 40/865626",
    "sg:postcode":"22587",
    "sg:province":"Hamburg",
    "wof:name":"Margrit Zeller",
    "wof:placetype":"venue"
},
  "geometry": {"coordinates":[9.8159379959,53.5635681152],"type":"Point"}
}