{
  "type": "Feature",
  "properties": {
    "iso:country":"DE",
    "sg:address":"Bahnhofstr. 30",
    "sg:city":"Wolfratshausen",
    "sg:phone":"+49 8171/5456",
    "sg:postcode":"82515",
    "sg:province":"Bayern",
    "wof:name":"Bartsch Immobilien Gmbh",
    "wof:placetype":"venue"
},
  "geometry": {"coordinates":[11.426451683,47.9144477844],"type":"Point"}
}