{
  "type": "Feature",
  "properties": {
    "iso:country":"DE",
    "sg:address":"Ehrenstr. 43 B",
    "sg:city":"K\u00f6ln",
    "sg:phone":"+49 221/2583129",
    "sg:postcode":"50672",
    "sg:province":"Nordrhein-Westfalen",
    "wof:name":"Pattevugel Freizeit- Sport- Und Spiel-zeug Gmbh",
    "wof:placetype":"venue"
},
  "geometry": {"coordinates":[6.9425911903,50.9382743835],"type":"Point"}
}