{
  "type": "Feature",
  "properties": {
    "iso:country":"DE",
    "sg:address":"Bachstr. 19",
    "sg:city":"Gro\u00dfbottwar",
    "sg:phone":"+49 4971/486060",
    "sg:postcode":"71723",
    "sg:province":"Baden-W\u00fcrttemberg",
    "wof:name":"Volksbank Marbach Eg",
    "wof:placetype":"venue"
},
  "geometry": {"coordinates":[9.291562,49.000736],"type":"Point"}
}