{
  "type": "Feature",
  "properties": {
    "iso:country":"DE",
    "sg:address":"Hermann-L\u00f6ns-Str. 4",
    "sg:city":"Gr\u00f6benzell",
    "sg:phone":"+49 8142/8422",
    "sg:postcode":"82194",
    "sg:province":"Bayern",
    "wof:name":"F. Sittl",
    "wof:placetype":"venue"
},
  "geometry": {"coordinates":[11.3719110489,48.1951293945],"type":"Point"}
}