{
  "type": "Feature",
  "properties": {
    "iso:country":"DE",
    "sg:address":"Ratzelstr. 224",
    "sg:city":"Leipzig",
    "sg:phone":"+49 341/4784963",
    "sg:postcode":"04207",
    "sg:province":"Sachsen",
    "wof:name":"Buffet S\u00fcdwest Ohg",
    "wof:placetype":"venue"
},
  "geometry": {"coordinates":[12.2667636871,51.3076019287],"type":"Point"}
}