{
  "type": "Feature",
  "properties": {
    "iso:country":"DE",
    "sg:address":"Blumenstr. 24",
    "sg:city":"M\u00f6nchengladbach",
    "sg:phone":"+49 2166/40082",
    "sg:postcode":"41236",
    "sg:province":"Nordrhein-Westfalen",
    "wof:name":"Ernst-heribert Linke Architekt",
    "wof:placetype":"venue"
},
  "geometry": {"coordinates":[6.441201,51.174831],"type":"Point"}
}