{
  "type": "Feature",
  "properties": {
    "iso:country":"DE",
    "sg:address":"Heidestr. 148",
    "sg:city":"Radeberg",
    "sg:phone":"+49 3528/442947",
    "sg:postcode":"01454",
    "sg:province":"Sachsen",
    "wof:name":"J\u00fcrgen Lorenz",
    "wof:placetype":"venue"
},
  "geometry": {"coordinates":[13.899851799,51.1108474731],"type":"Point"}
}