{
  "type": "Feature",
  "properties": {
    "iso:country":"DE",
    "sg:address":"Greifswalder Str. 23",
    "sg:city":"Erfurt",
    "sg:postcode":"99085",
    "sg:province":"Th\u00fcringen",
    "wof:name":"Alfa Fleisch Gmbh & Co. Kg",
    "wof:placetype":"venue"
},
  "geometry": {"coordinates":[11.0453739166,50.9890975952],"type":"Point"}
}