{
  "type": "Feature",
  "properties": {
    "iso:country":"DE",
    "sg:address":"Kastanienweg 25",
    "sg:city":"Emmerich",
    "sg:phone":"+49 2822/689163",
    "sg:postcode":"46446",
    "sg:province":"Nordrhein-Westfalen",
    "wof:name":"\u00d6ng\u00fcd\u00fc - Bau Gmbh",
    "wof:placetype":"venue"
},
  "geometry": {"coordinates":[6.2483038902,51.8453598022],"type":"Point"}
}