{
  "type": "Feature",
  "properties": {
    "iso:country":"DE",
    "sg:address":"Freiburgstr. 7",
    "sg:city":"Tuttlingen",
    "sg:phone":"+49 7461/78764",
    "sg:postcode":"78532",
    "sg:province":"Baden-W\u00fcrttemberg",
    "wof:name":"Freiburg",
    "wof:placetype":"venue"
},
  "geometry": {"coordinates":[8.8184432983,47.979801178],"type":"Point"}
}