{
  "type": "Feature",
  "properties": {
    "iso:country":"DE",
    "sg:address":"Moorenstr. 5",
    "sg:city":"D\u00fcsseldorf",
    "sg:phone":"+49 4921/18100",
    "sg:postcode":"40225",
    "sg:province":"Nordrhein-Westfalen",
    "wof:name":"Universit\u00c4tsklinikum",
    "wof:placetype":"venue"
},
  "geometry": {"coordinates":[6.788725,51.19883],"type":"Point"}
}