{
  "type": "Feature",
  "properties": {
    "iso:country":"DE",
    "sg:address":"Kaiserstr. 27",
    "sg:city":"Hagen",
    "sg:phone":"+49 2334/3640",
    "sg:postcode":"58119",
    "sg:province":"Nordrhein-Westfalen",
    "wof:name":"Anna E. Lehmann",
    "wof:placetype":"venue"
},
  "geometry": {"coordinates":[7.5735650063,51.347442627],"type":"Point"}
}