{
  "type": "Feature",
  "properties": {
    "iso:country":"DE",
    "sg:address":"Gartenstr. 9",
    "sg:city":"Norderney",
    "sg:phone":"+49 4932/2691",
    "sg:postcode":"26548",
    "sg:province":"Niedersachsen",
    "wof:name":"Pension Wilma Gramberg-klassen",
    "wof:placetype":"venue"
},
  "geometry": {"coordinates":[7.1475219727,53.7065811157],"type":"Point"}
}