{
  "type": "Feature",
  "properties": {
    "iso:country":"DE",
    "sg:address":"Posth\u00e4user 1",
    "sg:city":"Waldb\u00fcttelbrunn",
    "sg:phone":"+49 9369/2464",
    "sg:postcode":"97297",
    "sg:province":"Bayern",
    "wof:name":"Kachelofenbau Currlin Gmbh",
    "wof:placetype":"venue"
},
  "geometry": {"coordinates":[9.7574882507,49.7986907959],"type":"Point"}
}