{
  "type": "Feature",
  "properties": {
    "iso:country":"DE",
    "sg:address":"Am Hohen Graben 2",
    "sg:city":"Hagen",
    "sg:phone":"+49 2331/183184",
    "sg:postcode":"58097",
    "sg:province":"Nordrhein-Westfalen",
    "wof:name":"Shogin Of Darkness, Sod - Technical, It Webdesign",
    "wof:placetype":"venue"
},
  "geometry": {"coordinates":[7.478535,51.357063],"type":"Point"}
}