{
  "type": "Feature",
  "properties": {
    "iso:country":"DE",
    "sg:address":"Jahnstr. 7",
    "sg:city":"Kieselbronn",
    "sg:phone":"+49 7231/51944",
    "sg:postcode":"75249",
    "sg:province":"Baden-W\u00fcrttemberg",
    "wof:name":"Bernd Coblenzer",
    "wof:placetype":"venue"
},
  "geometry": {"coordinates":[8.7544221878,48.9320106506],"type":"Point"}
}