{
  "type": "Feature",
  "properties": {
    "iso:country":"DE",
    "sg:address":"Creidlitzer Str. 119 b",
    "sg:city":"Coburg",
    "sg:phone":"+49 9561/200556",
    "sg:postcode":"96450",
    "sg:province":"Bayern",
    "wof:name":"Sch\u00fctzenverein",
    "wof:placetype":"venue"
},
  "geometry": {"coordinates":[10.980591774,50.2290878296],"type":"Point"}
}