{
  "type": "Feature",
  "properties": {
    "iso:country":"DE",
    "sg:address":"Danziger Str. 43",
    "sg:city":"Bietigheim-Bissingen",
    "sg:postcode":"74321",
    "sg:province":"Baden-W\u00fcrttemberg",
    "wof:name":"Dankudis Immobilienmakler",
    "wof:placetype":"venue"
},
  "geometry": {"coordinates":[9.1495294571,48.9430656433],"type":"Point"}
}