{
  "type": "Feature",
  "properties": {
    "iso:country":"DE",
    "sg:address":"Messerschmittstr. 11",
    "sg:city":"Gersthofen",
    "sg:phone":"+49 821/249910",
    "sg:postcode":"86368",
    "sg:province":"Bayern",
    "wof:name":"Welfo Intra Gmbh",
    "wof:placetype":"venue"
},
  "geometry": {"coordinates":[10.8625659943,48.43592453],"type":"Point"}
}