{
  "type": "Feature",
  "properties": {
    "iso:country":"DE",
    "sg:address":"Oswald-L\u00e4uterer-Str. 12",
    "sg:city":"T\u00fcrkheim",
    "sg:phone":"+49 8245/1700",
    "sg:postcode":"86842",
    "sg:province":"Bayern",
    "wof:name":"Hermann Baur",
    "wof:placetype":"venue"
},
  "geometry": {"coordinates":[10.6412315369,48.0552368164],"type":"Point"}
}