{
  "type": "Feature",
  "properties": {
    "iso:country":"DE",
    "sg:address":"Buscheyplatz 11-15",
    "sg:city":"Bochum",
    "sg:phone":"+49 234/701042",
    "sg:postcode":"44801",
    "sg:province":"Nordrhein-Westfalen",
    "wof:name":"Kr\u00e4tzig & Partner Ingenieurgesellschaft",
    "wof:placetype":"venue"
},
  "geometry": {"coordinates":[7.261768,51.44981],"type":"Point"}
}