{
  "type": "Feature",
  "properties": {
    "iso:country":"DE",
    "sg:address":"H\u00fcttenstr. 152",
    "sg:city":"D\u00fcsseldorf",
    "sg:phone":"+49 211/785502",
    "sg:postcode":"40227",
    "sg:province":"Nordrhein-Westfalen",
    "wof:name":"K. Borchardt",
    "wof:placetype":"venue"
},
  "geometry": {"coordinates":[6.7927041054,51.2115592957],"type":"Point"}
}