{
  "type": "Feature",
  "properties": {
    "iso:country":"DE",
    "sg:address":"Dorfstr. 6",
    "sg:city":"Neuendorf",
    "sg:phone":"+49 36071/506",
    "sg:postcode":"37339",
    "sg:province":"Th\u00fcringen",
    "wof:name":"M. Schwethelm",
    "wof:placetype":"venue"
},
  "geometry": {"coordinates":[10.1961936951,51.454284668],"type":"Point"}
}