{
  "type": "Feature",
  "properties": {
    "iso:country":"DE",
    "sg:address":"Sendlinger Str. 46",
    "sg:city":"M\u00fcnchen",
    "sg:phone":"+49 89/26949560",
    "sg:postcode":"80331",
    "sg:province":"Bayern",
    "wof:name":"H & Q Gastst\u00e4ttenbetriebs- Gesellschaft Mbh",
    "wof:placetype":"venue"
},
  "geometry": {"coordinates":[11.56868,48.13472],"type":"Point"}
}