{
  "type": "Feature",
  "properties": {
    "iso:country":"DE",
    "sg:address":"Dorfstr. 4",
    "sg:city":"Tittmoning",
    "sg:phone":"+49 8683/207",
    "sg:postcode":"84529",
    "sg:province":"Bayern",
    "wof:name":"Hans Wengler",
    "wof:placetype":"venue"
},
  "geometry": {"coordinates":[12.7245264053,48.0989646912],"type":"Point"}
}