{
  "type": "Feature",
  "properties": {
    "iso:country":"DE",
    "sg:address":"Am St\u00fcckenkamp 2",
    "sg:city":"Bielefeld",
    "sg:phone":"+49 521/37551",
    "sg:postcode":"33607",
    "sg:province":"Nordrhein-Westfalen",
    "wof:name":"Bernhard Kieselbach",
    "wof:placetype":"venue"
},
  "geometry": {"coordinates":[8.558927536,52.0253334045],"type":"Point"}
}