{
  "type": "Feature",
  "properties": {
    "iso:country":"DE",
    "sg:address":"Freiberger Str. 127",
    "sg:city":"Olbernhau",
    "sg:phone":"+49 37360/1790",
    "sg:postcode":"09526",
    "sg:province":"Sachsen",
    "wof:name":"Raiffeisen Bezugs- Und Handelsgenossenschaft",
    "wof:placetype":"venue"
},
  "geometry": {"coordinates":[13.321527,50.670025],"type":"Point"}
}