{
  "type": "Feature",
  "properties": {
    "iso:country":"DE",
    "sg:address":"Steinweg 21",
    "sg:city":"Emden",
    "sg:phone":"+49 4921/66482",
    "sg:postcode":"26721",
    "sg:province":"Niedersachsen",
    "wof:name":"Medicus Gmbh",
    "wof:placetype":"venue"
},
  "geometry": {"coordinates":[7.1996951103,53.3732452393],"type":"Point"}
}