{
  "type": "Feature",
  "properties": {
    "iso:country":"DE",
    "sg:address":"Untere Reithausstr. 29",
    "sg:city":"Ludwigsburg",
    "sg:phone":"+49 7141/928448",
    "sg:postcode":"71634",
    "sg:province":"Baden-W\u00fcrttemberg",
    "wof:name":"Peter List",
    "wof:placetype":"venue"
},
  "geometry": {"coordinates":[9.1865901947,48.8996047974],"type":"Point"}
}