{
  "type": "Feature",
  "properties": {
    "iso:country":"DE",
    "sg:address":"Siegtalstr. 29",
    "sg:city":"Windeck",
    "sg:phone":"+49 2243/6962",
    "sg:postcode":"51570",
    "sg:province":"Nordrhein-Westfalen",
    "wof:name":"M. Herbertz",
    "wof:placetype":"venue"
},
  "geometry": {"coordinates":[7.5051498413,50.7789115906],"type":"Point"}
}