{
  "type": "Feature",
  "properties": {
    "iso:country":"DE",
    "sg:address":"Hintere Gasse 11",
    "sg:city":"Braunsbach",
    "sg:phone":"+49 7906/8488",
    "sg:postcode":"74542",
    "sg:province":"Baden-W\u00fcrttemberg",
    "wof:name":"Kurt Schwarz",
    "wof:placetype":"venue"
},
  "geometry": {"coordinates":[9.792089,49.198441],"type":"Point"}
}