{
  "type": "Feature",
  "properties": {
    "iso:country":"DE",
    "sg:address":"Oberlaimbach 20",
    "sg:city":"Scheinfeld",
    "sg:phone":"+49 9162/7122",
    "sg:postcode":"91443",
    "sg:province":"Bayern",
    "wof:name":"Erich R\u00fcckert",
    "wof:placetype":"venue"
},
  "geometry": {"coordinates":[10.4782371521,49.6405715942],"type":"Point"}
}