{
  "type": "Feature",
  "properties": {
    "iso:country":"DE",
    "sg:address":"Wilhelm-Liebknecht-Str. 35",
    "sg:city":"Crimmitschau",
    "sg:phone":"+49 3762/3149",
    "sg:postcode":"08451",
    "sg:province":"Sachsen",
    "wof:name":"Erhard Helbig",
    "wof:placetype":"venue"
},
  "geometry": {"coordinates":[12.370944,50.813091],"type":"Point"}
}