{
  "type": "Feature",
  "properties": {
    "iso:country":"DE",
    "sg:address":"Grunewaldstr. 16",
    "sg:city":"Geldern",
    "sg:phone":"+49 2831/3228",
    "sg:postcode":"47608",
    "sg:province":"Nordrhein-Westfalen",
    "wof:name":"Norbert Latzel Steuerberater",
    "wof:placetype":"venue"
},
  "geometry": {"coordinates":[6.3002362251,51.5265693665],"type":"Point"}
}