{
  "type": "Feature",
  "properties": {
    "iso:country":"DE",
    "sg:address":"Am Fohlengarten 6",
    "sg:city":"Oberschleissheim",
    "sg:phone":"+49 89/3152090",
    "sg:postcode":"85764",
    "sg:province":"Bayern",
    "wof:name":"Kreissparkasse M\u00fcnchen",
    "wof:placetype":"venue"
},
  "geometry": {"coordinates":[11.554722,48.257107],"type":"Point"}
}