{
  "type": "Feature",
  "properties": {
    "iso:country":"DE",
    "sg:address":"Dorfstr. 27",
    "sg:city":"Wedemark",
    "sg:phone":"+49 5130/2621",
    "sg:postcode":"30900",
    "sg:province":"Niedersachsen",
    "wof:name":"Dietrich S\u00fcling Bauingenieur",
    "wof:placetype":"venue"
},
  "geometry": {"coordinates":[9.765564,52.56559],"type":"Point"}
}