{
  "type": "Feature",
  "properties": {
    "iso:country":"DE",
    "sg:address":"Gustav-Freytag-Str. 18",
    "sg:city":"Wiesbaden",
    "sg:postcode":"65189",
    "sg:province":"Hessen",
    "wof:name":"Fireworks Gmbh",
    "wof:placetype":"venue"
},
  "geometry": {"coordinates":[8.2517089844,50.0793075562],"type":"Point"}
}