{
  "type": "Feature",
  "properties": {
    "iso:country":"DE",
    "sg:address":"Wallgasse 34",
    "sg:city":"Butzbach",
    "sg:phone":"+49 6033/60322",
    "sg:postcode":"35510",
    "sg:province":"Hessen",
    "wof:name":"Landesprodukten Handels Gmbh & Co. Kg",
    "wof:placetype":"venue"
},
  "geometry": {"coordinates":[8.67452,50.436939],"type":"Point"}
}