{
  "type": "Feature",
  "properties": {
    "iso:country":"DE",
    "sg:address":"An der Mehlsee 2",
    "sg:city":"Dingelst\u00e4dt",
    "sg:phone":"+49 36075/3980",
    "sg:postcode":"37351",
    "sg:province":"Th\u00fcringen",
    "wof:name":"Alois Keppler",
    "wof:placetype":"venue"
},
  "geometry": {"coordinates":[10.309668,51.318474],"type":"Point"}
}