{
  "type": "Feature",
  "properties": {
    "iso:country":"DE",
    "sg:address":"Heimchenweg 5",
    "sg:city":"Frankfurt",
    "sg:phone":"+49 69/313015",
    "sg:postcode":"65929",
    "sg:province":"Hessen",
    "wof:name":"Manfred Elzenheimer",
    "wof:placetype":"venue"
},
  "geometry": {"coordinates":[8.5327281952,50.1086540222],"type":"Point"}
}