{
  "type": "Feature",
  "properties": {
    "iso:country":"DE",
    "sg:address":"Von-Galen-Str. 39",
    "sg:city":"Solingen",
    "sg:phone":"+49 212/590224",
    "sg:postcode":"42653",
    "sg:province":"Nordrhein-Westfalen",
    "wof:name":"Wolfgang Zeitvogel",
    "wof:placetype":"venue"
},
  "geometry": {"coordinates":[7.0775308609,51.2124099731],"type":"Point"}
}