{
  "type": "Feature",
  "properties": {
    "iso:country":"DE",
    "sg:address":"Fl\u00f6zlinger Str 37",
    "sg:city":"Zimmern",
    "sg:phone":"+49 741/928715",
    "sg:postcode":"78658",
    "sg:province":"Baden-W\u00fcrttemberg",
    "wof:name":"Bau-union Gmbh & Co Vereinigte Schotterwerke Kg",
    "wof:placetype":"venue"
},
  "geometry": {"coordinates":[8.578751,48.168724],"type":"Point"}
}