{
  "type": "Feature",
  "properties": {
    "iso:country":"DE",
    "sg:address":"Rosa-Luxemburg-Str. 8",
    "sg:city":"Oelsnitz",
    "sg:phone":"+49 37421/7050",
    "sg:postcode":"08606",
    "sg:province":"Sachsen",
    "wof:name":"Vogtland-anzeiger",
    "wof:placetype":"venue"
},
  "geometry": {"coordinates":[12.1477270126,50.4030914307],"type":"Point"}
}