{
  "type": "Feature",
  "properties": {
    "iso:country":"DE",
    "sg:address":"Theodolindenstr. 31",
    "sg:city":"M\u00fcnchen",
    "sg:phone":"+49 89/643594",
    "sg:postcode":"81545",
    "sg:province":"Bayern",
    "wof:name":"Manfred Schl\u00fcter Architekt",
    "wof:placetype":"venue"
},
  "geometry": {"coordinates":[11.558693,48.089344],"type":"Point"}
}