{
  "type": "Feature",
  "properties": {
    "iso:country":"DE",
    "sg:address":"Am Kirchberg 1",
    "sg:city":"Bad Wurzach",
    "sg:phone":"+49 7564/3349",
    "sg:postcode":"88410",
    "sg:province":"Baden-W\u00fcrttemberg",
    "wof:name":"Kanone",
    "wof:placetype":"venue"
},
  "geometry": {"coordinates":[9.8975858688,47.8558807373],"type":"Point"}
}