{
  "type": "Feature",
  "properties": {
    "iso:country":"DE",
    "sg:address":"Hermann-Bettels-Str. 1",
    "sg:city":"Algermissen",
    "sg:postcode":"31191",
    "sg:province":"Niedersachsen",
    "wof:name":"Immobiliengesellschaft Hildesheim Gesch\u00e4fts-",
    "wof:placetype":"venue"
},
  "geometry": {"coordinates":[9.9649152756,52.2470283508],"type":"Point"}
}