{
  "type": "Feature",
  "properties": {
    "iso:country":"DE",
    "sg:address":"Hortensienweg 17",
    "sg:city":"Stuttgart",
    "sg:phone":"+49 711/9539120",
    "sg:postcode":"70374",
    "sg:province":"Baden-W\u00fcrttemberg",
    "wof:name":"Ecop Deutschland Baugesellschaft Mbh",
    "wof:placetype":"venue"
},
  "geometry": {"coordinates":[9.2515125275,48.8181495667],"type":"Point"}
}