{
  "type": "Feature",
  "properties": {
    "iso:country":"DE",
    "sg:address":"Joliot-Curie-Str. 3",
    "sg:city":"Neubrandenburg",
    "sg:phone":"+49 395/4691475",
    "sg:postcode":"17036",
    "sg:province":"Mecklenburg-Vorpommern",
    "wof:name":"Christa-maria Schilling Rechtsanw\u00e4ltin",
    "wof:placetype":"venue"
},
  "geometry": {"coordinates":[13.2973670959,53.5536384583],"type":"Point"}
}