{
  "type": "Feature",
  "properties": {
    "iso:country":"DE",
    "sg:address":"Bahnhofstr. 20",
    "sg:city":"Eldena",
    "sg:phone":"+49 38755/20368",
    "sg:postcode":"19294",
    "sg:province":"Mecklenburg-Vorpommern",
    "wof:name":"Britta Senger",
    "wof:placetype":"venue"
},
  "geometry": {"coordinates":[11.4158687592,53.2330245972],"type":"Point"}
}