{
  "type": "Feature",
  "properties": {
    "iso:country":"DE",
    "sg:address":"Mittlerer Graben 18",
    "sg:city":"Weilheim",
    "sg:phone":"+49 881/8051",
    "sg:postcode":"82362",
    "sg:province":"Bayern",
    "wof:name":"Wbb Baubetreuungs Gmbh",
    "wof:placetype":"venue"
},
  "geometry": {"coordinates":[11.1436958313,47.8402481079],"type":"Point"}
}