{
  "type": "Feature",
  "properties": {
    "iso:country":"DE",
    "sg:address":"F\u00e4rberstr. 20",
    "sg:city":"Kehl",
    "sg:phone":"+49 7851/2305",
    "sg:postcode":"77694",
    "sg:province":"Baden-W\u00fcrttemberg",
    "wof:name":"Karl-heinz Schmidt B\u00e4ckerei Konditorei",
    "wof:placetype":"venue"
},
  "geometry": {"coordinates":[7.811646,48.570045],"type":"Point"}
}