{
  "type": "Feature",
  "properties": {
    "iso:country":"DE",
    "sg:address":"Steinbachstr. 13",
    "sg:city":"Besigheim",
    "sg:phone":"+49 7143/34786",
    "sg:postcode":"74354",
    "sg:province":"Baden-W\u00fcrttemberg",
    "wof:name":"Helmut Koller Steuerberater",
    "wof:placetype":"venue"
},
  "geometry": {"coordinates":[9.1376085281,48.9979095459],"type":"Point"}
}