{
  "type": "Feature",
  "properties": {
    "iso:country":"DE",
    "sg:address":"AWG-Siedlung 3",
    "sg:city":"Reichenbach",
    "sg:phone":"+49 36601/85302",
    "sg:postcode":"07629",
    "sg:province":"Th\u00fcringen",
    "wof:name":"B. Rohrer Reichenbach Awg",
    "wof:placetype":"venue"
},
  "geometry": {"coordinates":[11.873109,50.868797],"type":"Point"}
}