{
  "type": "Feature",
  "properties": {
    "iso:country":"DE",
    "sg:address":"Grenzstr. 10",
    "sg:city":"Obertshausen",
    "sg:phone":"+49 6104/409160",
    "sg:postcode":"63179",
    "sg:province":"Hessen",
    "wof:name":"Plate Bau- Und Sachsanierung Rhein Main Gmbh",
    "wof:placetype":"venue"
},
  "geometry": {"coordinates":[8.844647,50.073242],"type":"Point"}
}