{
  "type": "Feature",
  "properties": {
    "iso:country":"DE",
    "sg:address":"Berggasse 11",
    "sg:city":"Calw",
    "sg:phone":"+49 7051/3533",
    "sg:postcode":"75365",
    "sg:province":"Baden-W\u00fcrttemberg",
    "wof:name":"G. K\u00f6nig Kohlenhandlung",
    "wof:placetype":"venue"
},
  "geometry": {"coordinates":[8.709146,48.730228],"type":"Point"}
}