{
  "type": "Feature",
  "properties": {
    "iso:country":"DE",
    "sg:address":"Hofbrunnstr. 5",
    "sg:city":"M\u00fcnchen",
    "sg:phone":"+49 89/797961",
    "sg:postcode":"81479",
    "sg:province":"Bayern",
    "wof:name":"Herbert Prange Architekt",
    "wof:placetype":"venue"
},
  "geometry": {"coordinates":[11.525087,48.079494],"type":"Point"}
}