{
  "type": "Feature",
  "properties": {
    "iso:country":"DE",
    "sg:address":"Bischofsweg 2",
    "sg:city":"Wermsdorf",
    "sg:phone":"+49 34364/8020",
    "sg:postcode":"04779",
    "sg:province":"Sachsen",
    "wof:name":"Ket Energietechnik Gmbh Anlagenbau & Co Kg",
    "wof:placetype":"venue"
},
  "geometry": {"coordinates":[12.9237756729,51.281288147],"type":"Point"}
}