{
  "type": "Feature",
  "properties": {
    "iso:country":"DE",
    "sg:address":"Saarstr. 1",
    "sg:city":"Geislingen",
    "sg:phone":"+49 7331/61197",
    "sg:postcode":"73312",
    "sg:province":"Baden-W\u00fcrttemberg",
    "wof:name":"Eugen Binder Architekt",
    "wof:placetype":"venue"
},
  "geometry": {"coordinates":[9.82582,48.626404],"type":"Point"}
}