{
  "type": "Feature",
  "properties": {
    "iso:country":"DE",
    "sg:address":"Richard-Strauss-Str. 7",
    "sg:city":"Ingolstadt",
    "sg:phone":"+49 841/84414",
    "sg:postcode":"85057",
    "sg:province":"Bayern",
    "wof:name":"E. Panse",
    "wof:placetype":"venue"
},
  "geometry": {"coordinates":[11.406659,48.77227],"type":"Point"}
}