{
  "type": "Feature",
  "properties": {
    "iso:country":"DE",
    "sg:address":"Wei\u00dfenseer Str. 31 a",
    "sg:city":"S\u00f6mmerda",
    "sg:phone":"+49 3634/611928",
    "sg:postcode":"99610",
    "sg:province":"Th\u00fcringen",
    "wof:name":"Music Art",
    "wof:placetype":"venue"
},
  "geometry": {"coordinates":[11.1157608032,51.1640625],"type":"Point"}
}