{
  "type": "Feature",
  "properties": {
    "iso:country":"DE",
    "sg:address":"Hamerweg 251",
    "sg:city":"M\u00f6nchengladbach",
    "sg:postcode":"41068",
    "sg:province":"Nordrhein-Westfalen",
    "wof:name":"Norbert Wilms Et Leetera",
    "wof:placetype":"venue"
},
  "geometry": {"coordinates":[6.3966498375,51.2013015747],"type":"Point"}
}