{
  "type": "Feature",
  "properties": {
    "iso:country":"DE",
    "sg:address":"Untere Torstr. 10",
    "sg:city":"Feuchtwangen",
    "sg:phone":"+49 9852/2457",
    "sg:postcode":"91555",
    "sg:province":"Bayern",
    "wof:name":"Georg Roth Lebensmittel- Filialbetrieb Gmbh & Co. Kg",
    "wof:placetype":"venue"
},
  "geometry": {"coordinates":[10.3304224014,49.1676483154],"type":"Point"}
}