{
  "type": "Feature",
  "properties": {
    "iso:country":"DE",
    "sg:address":"Siemensstr. 32",
    "sg:city":"Ditzingen",
    "sg:phone":"+49 7156/1630",
    "sg:postcode":"71254",
    "sg:province":"Baden-W\u00fcrttemberg",
    "wof:name":"Redaktion Deutsche Literatur Reclam Verlag",
    "wof:placetype":"venue"
},
  "geometry": {"coordinates":[9.0668935776,48.822467804],"type":"Point"}
}