{
  "type": "Feature",
  "properties": {
    "iso:country":"DE",
    "sg:address":"L\u00e4ngerach 25",
    "sg:city":"Sipplingen",
    "sg:phone":"+49 4975/5167123",
    "sg:postcode":"78354",
    "sg:province":"Baden-W\u00fcrttemberg",
    "wof:name":"Matthias Widenhorn",
    "wof:placetype":"venue"
},
  "geometry": {"coordinates":[9.10331,47.797989],"type":"Point"}
}