{
  "type": "Feature",
  "properties": {
    "iso:country":"DE",
    "sg:address":"Bamberger Str 15",
    "sg:city":"Sche\u00dflitz",
    "sg:phone":"+49 9542/921200",
    "sg:postcode":"96110",
    "sg:province":"Bayern",
    "wof:name":"Rosch-buch Druckerei Gmbh",
    "wof:placetype":"venue"
},
  "geometry": {"coordinates":[11.0282297134,49.9701118469],"type":"Point"}
}