{
  "type": "Feature",
  "properties": {
    "iso:country":"DE",
    "sg:address":"Reineckstr 3",
    "sg:city":"Frankfurt",
    "sg:phone":"+49 69/21020",
    "sg:postcode":"60313",
    "sg:province":"Hessen",
    "wof:name":"Buchmesse Frankfurt",
    "wof:placetype":"venue"
},
  "geometry": {"coordinates":[8.685954,50.114079],"type":"Point"}
}