{
  "type": "Feature",
  "properties": {
    "iso:country":"DE",
    "sg:address":"Schlei\u00dfheimer Str. 12",
    "sg:city":"Dachau",
    "sg:phone":"+49 8131/371930",
    "sg:postcode":"85221",
    "sg:province":"Bayern",
    "wof:name":"Dr. Wallner Engineering & Co Gmbh",
    "wof:placetype":"venue"
},
  "geometry": {"coordinates":[11.440251,48.257702],"type":"Point"}
}