{
  "type": "Feature",
  "properties": {
    "iso:country":"DE",
    "sg:address":"Hartmannsweilerstr. 33",
    "sg:city":"Frankfurt",
    "sg:phone":"+49 69/382179",
    "sg:postcode":"65933",
    "sg:province":"Hessen",
    "wof:name":"R. Wendler",
    "wof:placetype":"venue"
},
  "geometry": {"coordinates":[8.609693,50.091599],"type":"Point"}
}