{
  "type": "Feature",
  "properties": {
    "iso:country":"DE",
    "sg:address":"Felsenstr. 6 c",
    "sg:city":"Halle",
    "sg:phone":"+49 345/5322106",
    "sg:postcode":"06114",
    "sg:province":"Sachsen-Anhalt",
    "wof:name":"R\u00fcdiger Mock Rechtsanwalt",
    "wof:placetype":"venue"
},
  "geometry": {"coordinates":[11.9543113708,51.4994735718],"type":"Point"}
}