{
  "type": "Feature",
  "properties": {
    "iso:country":"DE",
    "sg:address":"Poststr. 79",
    "sg:city":"Bad Karlshafen",
    "sg:phone":"+49 5672/627",
    "sg:postcode":"34385",
    "sg:province":"Hessen",
    "wof:name":"Erna Munsch",
    "wof:placetype":"venue"
},
  "geometry": {"coordinates":[9.4608869553,51.6308174133],"type":"Point"}
}