{
  "type": "Feature",
  "properties": {
    "iso:country":"DE",
    "sg:address":"Burdastr.",
    "sg:city":"Offenburg",
    "sg:phone":"+49 781/8401",
    "sg:postcode":"77656",
    "sg:province":"Baden-W\u00fcrttemberg",
    "wof:name":"Freizeit Revue",
    "wof:placetype":"venue"
},
  "geometry": {"coordinates":[7.9251661301,48.4670600891],"type":"Point"}
}