{
  "type": "Feature",
  "properties": {
    "iso:country":"DE",
    "sg:address":"Darmst\u00e4dter Str. 6",
    "sg:city":"Bickenbach",
    "sg:phone":"+49 6257/3560",
    "sg:postcode":"64404",
    "sg:province":"Hessen",
    "wof:name":"E. Schemel",
    "wof:placetype":"venue"
},
  "geometry": {"coordinates":[8.6121902466,49.7543907166],"type":"Point"}
}