{
  "type": "Feature",
  "properties": {
    "iso:country":"DE",
    "sg:address":"Rhein-Mosel-Str. 17",
    "sg:city":"Emmelshausen",
    "sg:phone":"+49 6747/7400",
    "sg:postcode":"56281",
    "sg:province":"Rheinland-Pfalz",
    "wof:name":"R\u00f6mer-apotheke E. K.",
    "wof:placetype":"venue"
},
  "geometry": {"coordinates":[7.54437,50.156879],"type":"Point"}
}