{
  "type": "Feature",
  "properties": {
    "iso:country":"DE",
    "sg:address":"Bartholom\u00e4usstr. 64",
    "sg:city":"N\u00fcrnberg",
    "sg:phone":"+49 911/6578954",
    "sg:postcode":"90489",
    "sg:province":"Bayern",
    "wof:name":"Howa Druck & Satz Gmbh",
    "wof:placetype":"venue"
},
  "geometry": {"coordinates":[11.1032247543,49.4593467712],"type":"Point"}
}