{
  "type": "Feature",
  "properties": {
    "iso:country":"DE",
    "sg:address":"Grunewaldstr. 71 a",
    "sg:city":"Berlin",
    "sg:phone":"+49 30/78715510",
    "sg:postcode":"10823",
    "sg:province":"Berlin",
    "wof:name":"J. P. K\u00f6ll Handelsgesellschaft Gmbh",
    "wof:placetype":"venue"
},
  "geometry": {"coordinates":[13.3483753204,52.4892044067],"type":"Point"}
}