{
  "type": "Feature",
  "properties": {
    "iso:country":"DE",
    "sg:address":"Hechinger Str. 9",
    "sg:city":"Haigerloch",
    "sg:phone":"+49 7474/6235",
    "sg:postcode":"72401",
    "sg:province":"Baden-W\u00fcrttemberg",
    "wof:name":"Gastst\u00e4tte Schl\u00f6ssle",
    "wof:placetype":"venue"
},
  "geometry": {"coordinates":[8.8066511154,48.3675842285],"type":"Point"}
}