{
  "type": "Feature",
  "properties": {
    "iso:country":"DE",
    "sg:address":"R\u00f6ntgenstr. 8",
    "sg:city":"Gro\u00df-Zimmern",
    "sg:phone":"+49 6071/42606",
    "sg:postcode":"64846",
    "sg:province":"Hessen",
    "wof:name":"Tibasch Gmbh",
    "wof:placetype":"venue"
},
  "geometry": {"coordinates":[8.81359,49.881081],"type":"Point"}
}