{
  "type": "Feature",
  "properties": {
    "iso:country":"DE",
    "sg:address":"Edgar-M\u00fcller-Str. 35a",
    "sg:city":"Neustadt",
    "sg:phone":"+49 9568/92290",
    "sg:postcode":"96465",
    "sg:province":"Bayern",
    "wof:name":"G\u00e4stehaus Monika",
    "wof:placetype":"venue"
},
  "geometry": {"coordinates":[11.0996437073,50.3578567505],"type":"Point"}
}