{
  "type": "Feature",
  "properties": {
    "iso:country":"DE",
    "sg:address":"Amsterdamer Stra\u00dfe 6",
    "sg:city":"Heilbronn",
    "sg:phone":"+49 7131/580976",
    "sg:postcode":"74081",
    "sg:province":"Baden-W\u00fcrttemberg",
    "wof:name":"Usm - Umwelt- Und Sensor Me\u00dftechnik Gmbh",
    "wof:placetype":"venue"
},
  "geometry": {"coordinates":[9.170141,49.117035],"type":"Point"}
}