{
  "type": "Feature",
  "properties": {
    "iso:country":"DE",
    "sg:address":"Schillerstr. 6",
    "sg:city":"Cuxhaven",
    "sg:phone":"+49 4721/711936",
    "sg:postcode":"27472",
    "sg:province":"Niedersachsen",
    "wof:name":"Leisure Merchandise Und Service Gmbh",
    "wof:placetype":"venue"
},
  "geometry": {"coordinates":[8.703077,53.868717],"type":"Point"}
}