{
  "type": "Feature",
  "properties": {
    "iso:country":"DE",
    "sg:address":"Reichenaustr. 55",
    "sg:city":"Konstanz",
    "sg:phone":"+49 7531/62719",
    "sg:postcode":"78467",
    "sg:province":"Baden-W\u00fcrttemberg",
    "wof:name":"Columbus-contact Gmbh",
    "wof:placetype":"venue"
},
  "geometry": {"coordinates":[9.158526,47.673035],"type":"Point"}
}