{
  "type": "Feature",
  "properties": {
    "iso:country":"DE",
    "sg:address":"Kastanienallee 2",
    "sg:city":"Kiel",
    "sg:phone":"+49 431/36457660",
    "sg:postcode":"24159",
    "sg:province":"Schleswig-Holstein",
    "wof:name":"Jan P. Fetting Rechtsanwalt",
    "wof:placetype":"venue"
},
  "geometry": {"coordinates":[10.1420526505,54.3726234436],"type":"Point"}
}