{
  "type": "Feature",
  "properties": {
    "iso:country":"DE",
    "sg:address":"Markt 22",
    "sg:city":"Mainz",
    "sg:phone":"+49 6131/227686",
    "sg:postcode":"55116",
    "sg:province":"Rheinland-Pfalz",
    "wof:name":"J. B. Schickert Drogerie",
    "wof:placetype":"venue"
},
  "geometry": {"coordinates":[8.274177,49.999317],"type":"Point"}
}