{
  "type": "Feature",
  "properties": {
    "iso:country":"DE",
    "sg:address":"D\u00fcrtenweg 1",
    "sg:city":"Rostock",
    "sg:phone":"+49 381/4922213",
    "sg:postcode":"18055",
    "sg:province":"Mecklenburg-Vorpommern",
    "wof:name":"Frank Gr\u00f6tschel Baugesellschaft Mbh",
    "wof:placetype":"venue"
},
  "geometry": {"coordinates":[12.18691,54.079865],"type":"Point"}
}