{
  "type": "Feature",
  "properties": {
    "iso:country":"DE",
    "sg:address":"M\u00f6rfelder Landstr. 17",
    "sg:city":"Frankfurt",
    "sg:phone":"+49 69/611757",
    "sg:postcode":"60598",
    "sg:province":"Hessen",
    "wof:name":"Hellmuth Frank Steinmetz",
    "wof:placetype":"venue"
},
  "geometry": {"coordinates":[8.6897964478,50.0998344421],"type":"Point"}
}