{
  "type": "Feature",
  "properties": {
    "iso:country":"DE",
    "sg:address":"Pfleggasse 31",
    "sg:city":"Deggendorf",
    "sg:phone":"+49 991/5115",
    "sg:postcode":"94469",
    "sg:province":"Bayern",
    "wof:name":"Ludwigs-apotheke",
    "wof:placetype":"venue"
},
  "geometry": {"coordinates":[12.96475,48.83345],"type":"Point"}
}