{
  "type": "Feature",
  "properties": {
    "iso:country":"DE",
    "sg:address":"Neuslinger Str. 5",
    "sg:city":"Buchhofen",
    "sg:phone":"+49 9936/95010",
    "sg:postcode":"94533",
    "sg:province":"Bayern",
    "wof:name":"Raiffeisen-versicherungs- Dienst Gmbh",
    "wof:placetype":"venue"
},
  "geometry": {"coordinates":[12.9205188751,48.6978492737],"type":"Point"}
}