{
  "type": "Feature",
  "properties": {
    "iso:country":"DE",
    "sg:address":"Staatliche Arztpraxis",
    "sg:city":"K\u00f6nigs Wusterhausen",
    "sg:postcode":"15711",
    "sg:province":"Brandenburg",
    "wof:name":"Dr. Med. J\u00fcrg. Noldenhauer",
    "wof:placetype":"venue"
},
  "geometry": {"coordinates":[13.628505,52.296581],"type":"Point"}
}