{
  "type": "Feature",
  "properties": {
    "iso:country":"DE",
    "sg:address":"Bergstr. 23",
    "sg:city":"Ransbach-Baumbach",
    "sg:phone":"+49 2623/4084",
    "sg:postcode":"56235",
    "sg:province":"Rheinland-Pfalz",
    "wof:name":"Peter Josef Gerhards",
    "wof:placetype":"venue"
},
  "geometry": {"coordinates":[7.7249331474,50.4545669556],"type":"Point"}
}