{
  "type": "Feature",
  "properties": {
    "iso:country":"DE",
    "sg:address":"H\u00f6henstr. 2",
    "sg:city":"Brombachtal",
    "sg:phone":"+49 6063/2976",
    "sg:postcode":"64753",
    "sg:province":"Hessen",
    "wof:name":"Flath Weinpressen- Technik Gmbh",
    "wof:placetype":"venue"
},
  "geometry": {"coordinates":[8.9502305984,49.7353248596],"type":"Point"}
}