{
  "type": "Feature",
  "properties": {
    "iso:country":"DE",
    "sg:address":"Moltkestr. 25",
    "sg:city":"Leichlingen",
    "sg:phone":"+49 2175/884460",
    "sg:postcode":"42799",
    "sg:province":"Nordrhein-Westfalen",
    "wof:name":"Smart Microwave And Radartechnology Gmbh",
    "wof:placetype":"venue"
},
  "geometry": {"coordinates":[7.0023999214,51.1047210693],"type":"Point"}
}