{
  "type": "Feature",
  "properties": {
    "iso:country":"DE",
    "sg:address":"Walther-Rathenau-Str.",
    "sg:city":"Ludwigsfelde",
    "sg:postcode":"14974",
    "sg:province":"Brandenburg",
    "wof:name":"Wasserversorgung Und Abwasserbehandlung Potsdam",
    "wof:placetype":"venue"
},
  "geometry": {"coordinates":[13.2556848526,52.2994804382],"type":"Point"}
}