{
  "type": "Feature",
  "properties": {
    "iso:country":"DE",
    "sg:address":"Gro\u00dfe Burgstr. 24",
    "sg:city":"Wei\u00dfenfels",
    "sg:phone":"+49 3443/302638",
    "sg:postcode":"06667",
    "sg:province":"Sachsen-Anhalt",
    "wof:name":"Drahtgitter Eduard J\u00e4nicke",
    "wof:placetype":"venue"
},
  "geometry": {"coordinates":[11.97344,51.199387],"type":"Point"}
}