{
  "type": "Feature",
  "properties": {
    "iso:country":"DE",
    "sg:address":"W\u00fcrttemberger Str. 171",
    "sg:city":"Bruchsal",
    "sg:phone":"+49 7251/2793",
    "sg:postcode":"76646",
    "sg:province":"Baden-W\u00fcrttemberg",
    "wof:name":"Schule Der Entspannung",
    "wof:placetype":"venue"
},
  "geometry": {"coordinates":[8.6157445908,49.1178779602],"type":"Point"}
}