{
  "type": "Feature",
  "properties": {
    "iso:country":"DE",
    "sg:address":"Brauerstr. 2",
    "sg:city":"Rotenburg",
    "sg:postcode":"27356",
    "sg:province":"Niedersachsen",
    "wof:name":"Scheland Gmbh & Co. Kg",
    "wof:placetype":"venue"
},
  "geometry": {"coordinates":[9.3970766068,53.1032867432],"type":"Point"}
}