{
  "type": "Feature",
  "properties": {
    "iso:country":"DE",
    "sg:address":"In der Linde 7",
    "sg:city":"Werl",
    "sg:phone":"+49 2922/2939",
    "sg:postcode":"59457",
    "sg:province":"Nordrhein-Westfalen",
    "wof:name":"Alfons Griewel",
    "wof:placetype":"venue"
},
  "geometry": {"coordinates":[7.86897,51.546947],"type":"Point"}
}