{
  "type": "Feature",
  "properties": {
    "iso:country":"DE",
    "sg:address":"Sturmburg 5b",
    "sg:city":"Papendorf",
    "sg:phone":"+49 381/21926",
    "sg:postcode":"18059",
    "sg:province":"Mecklenburg-Vorpommern",
    "wof:name":"Ulf Strasser",
    "wof:placetype":"venue"
},
  "geometry": {"coordinates":[12.1428222656,54.0391693115],"type":"Point"}
}