{
  "type": "Feature",
  "properties": {
    "iso:country":"DE",
    "sg:address":"Marktplatz 20 a",
    "sg:city":"Allersberg",
    "sg:phone":"+49 9176/5580",
    "sg:postcode":"90584",
    "sg:province":"Bayern",
    "wof:name":"Mal",
    "wof:placetype":"venue"
},
  "geometry": {"coordinates":[11.236419,49.25119],"type":"Point"}
}