{
  "type": "Feature",
  "properties": {
    "iso:country":"DE",
    "sg:address":"Glockenhofstr. 35",
    "sg:city":"N\u00fcrnberg",
    "sg:phone":"+49 911/462660",
    "sg:postcode":"90487",
    "sg:province":"Bayern",
    "wof:name":"Spitz Schaltanlagenbau Gmbh",
    "wof:placetype":"venue"
},
  "geometry": {"coordinates":[11.091407,49.444492],"type":"Point"}
}