{
  "type": "Feature",
  "properties": {
    "iso:country":"DE",
    "sg:address":"Kaistr 20",
    "sg:city":"D\u00fcsseldorf",
    "sg:phone":"+49 211/91760",
    "sg:postcode":"40221",
    "sg:province":"Nordrhein-Westfalen",
    "wof:name":"Shiseido Deutschland Gmbh",
    "wof:placetype":"venue"
},
  "geometry": {"coordinates":[6.755914,51.215752],"type":"Point"}
}