{
  "type": "Feature",
  "properties": {
    "iso:country":"DE",
    "sg:address":"Sigmundstr. 137",
    "sg:city":"N\u00fcrnberg",
    "sg:phone":"+49 911/312422",
    "sg:postcode":"90431",
    "sg:province":"Bayern",
    "wof:name":"Jos. Hesse",
    "wof:placetype":"venue"
},
  "geometry": {"coordinates":[11.0124092102,49.4489173889],"type":"Point"}
}