{
  "type": "Feature",
  "properties": {
    "iso:country":"DE",
    "sg:address":"Lange Str. 33",
    "sg:city":"Bad Zwischenahn",
    "sg:phone":"+49 4403/2201",
    "sg:postcode":"26160",
    "sg:province":"Niedersachsen",
    "wof:name":"Franz Brosig",
    "wof:placetype":"venue"
},
  "geometry": {"coordinates":[8.0075330734,53.1807899475],"type":"Point"}
}