{
  "type": "Feature",
  "properties": {
    "iso:country":"DE",
    "sg:address":"Am Junger-L\u00f6we-Schacht 4",
    "sg:city":"Freiberg",
    "sg:postcode":"09599",
    "sg:province":"Sachsen",
    "wof:name":"Elimex Ingenieur- Und Vertriebsb\u00fcro F\u00fcr Anlagen-",
    "wof:placetype":"venue"
},
  "geometry": {"coordinates":[13.356454,50.903458],"type":"Point"}
}