{
  "type": "Feature",
  "properties": {
    "iso:country":"DE",
    "sg:address":"B\u00fclowstr. 139",
    "sg:city":"Datteln",
    "sg:phone":"+49 2363/357593",
    "sg:postcode":"45711",
    "sg:province":"Nordrhein-Westfalen",
    "wof:name":"Sel Soft Ohg",
    "wof:placetype":"venue"
},
  "geometry": {"coordinates":[7.347002,51.667313],"type":"Point"}
}