{
  "type": "Feature",
  "properties": {
    "iso:country":"DE",
    "sg:address":"Im Eichholz 5",
    "sg:city":"Hannover",
    "sg:phone":"+49 511/650508",
    "sg:postcode":"30657",
    "sg:province":"Niedersachsen",
    "wof:name":"Gerhard Ewerbeck",
    "wof:placetype":"venue"
},
  "geometry": {"coordinates":[9.7972803116,52.443321228],"type":"Point"}
}