{
  "type": "Feature",
  "properties": {
    "iso:country":"DE",
    "sg:address":"Kettenstr. 4",
    "sg:city":"Trier",
    "sg:phone":"+49 651/827280",
    "sg:postcode":"54294",
    "sg:province":"Rheinland-Pfalz",
    "wof:name":"Ambiente-restaurant",
    "wof:placetype":"venue"
},
  "geometry": {"coordinates":[6.5804858208,49.7209701538],"type":"Point"}
}