{
  "type": "Feature",
  "properties": {
    "iso:country":"DE",
    "sg:address":"Albert-Schweitzer-Str. 13A",
    "sg:city":"Wolfsburg",
    "sg:phone":"+49 5361/48051",
    "sg:postcode":"38440",
    "sg:province":"Niedersachsen",
    "wof:name":"Horst Schmidt Steuerberater",
    "wof:placetype":"venue"
},
  "geometry": {"coordinates":[10.7716283798,52.4111328125],"type":"Point"}
}