{
  "type": "Feature",
  "properties": {
    "iso:country":"DE",
    "sg:address":"Espanstr. 21",
    "sg:city":"Schwaig",
    "sg:postcode":"90571",
    "sg:province":"Bayern",
    "wof:name":"Mahn & Co.",
    "wof:placetype":"venue"
},
  "geometry": {"coordinates":[11.201245,49.481724],"type":"Point"}
}