{
  "type": "Feature",
  "properties": {
    "iso:country":"DE",
    "sg:address":"Dornstr. 3",
    "sg:city":"Herne",
    "sg:postcode":"44629",
    "sg:province":"Nordrhein-Westfalen",
    "wof:name":"Eurofoon Gmbh",
    "wof:placetype":"venue"
},
  "geometry": {"coordinates":[7.217320919,51.5470314026],"type":"Point"}
}