{
  "type": "Feature",
  "properties": {
    "iso:country":"DE",
    "sg:address":"Schneeberger Str. 30",
    "sg:city":"Aue",
    "sg:phone":"+49 3771/22175",
    "sg:postcode":"08280",
    "sg:province":"Sachsen",
    "wof:name":"Stadt- Und Kreisbibliothek",
    "wof:placetype":"venue"
},
  "geometry": {"coordinates":[12.698309,50.588512],"type":"Point"}
}