{
  "type": "Feature",
  "properties": {
    "iso:country":"DE",
    "sg:address":"Hauptstr 9",
    "sg:city":"Haigerloch",
    "sg:phone":"+49 2641/2393",
    "sg:postcode":"72401",
    "sg:province":"Baden-W\u00fcrttemberg",
    "wof:name":"Wija Gmbh",
    "wof:placetype":"venue"
},
  "geometry": {"coordinates":[7.143155,50.548164],"type":"Point"}
}