{
  "type": "Feature",
  "properties": {
    "iso:country":"DE",
    "sg:address":"Sterndamm 24",
    "sg:city":"Berlin",
    "sg:phone":"+49 30/6365489",
    "sg:postcode":"12487",
    "sg:province":"Berlin",
    "wof:name":"Manfred Onischka",
    "wof:placetype":"venue"
},
  "geometry": {"coordinates":[13.5079250336,52.4517402649],"type":"Point"}
}