{
  "type": "Feature",
  "properties": {
    "iso:country":"DE",
    "sg:address":"Papestr. 47",
    "sg:city":"Brilon",
    "sg:phone":"+49 2961/8506",
    "sg:postcode":"59929",
    "sg:province":"Nordrhein-Westfalen",
    "wof:name":"Willi Wagner",
    "wof:placetype":"venue"
},
  "geometry": {"coordinates":[8.5806884766,51.3996620178],"type":"Point"}
}