{
  "type": "Feature",
  "properties": {
    "iso:country":"DE",
    "sg:address":"Obere Stadt 58",
    "sg:city":"Weilheim",
    "sg:phone":"+49 881/3152",
    "sg:postcode":"82362",
    "sg:province":"Bayern",
    "wof:name":"Werner Zippel Krawatten Herst.",
    "wof:placetype":"venue"
},
  "geometry": {"coordinates":[11.148508,47.838108],"type":"Point"}
}