{
  "type": "Feature",
  "properties": {
    "iso:country":"DE",
    "sg:address":"Ringstr. 7",
    "sg:city":"Lehrte",
    "sg:phone":"+49 5132/55858",
    "sg:postcode":"31275",
    "sg:province":"Niedersachsen",
    "wof:name":"Almuth Diedrich-willing Rechtsanw\u00e4ltin Und Notarin",
    "wof:placetype":"venue"
},
  "geometry": {"coordinates":[9.9776029587,52.3793563843],"type":"Point"}
}