{
  "type": "Feature",
  "properties": {
    "iso:country":"DE",
    "sg:address":"Wilhelmstr. 50",
    "sg:city":"Ispringen",
    "sg:phone":"+49 7231/101075",
    "sg:postcode":"75228",
    "sg:province":"Baden-W\u00fcrttemberg",
    "wof:name":"Ycos Yves Colliard Software Gmbh",
    "wof:placetype":"venue"
},
  "geometry": {"coordinates":[8.6797771454,48.9146842957],"type":"Point"}
}