{
  "type": "Feature",
  "properties": {
    "iso:country":"DE",
    "sg:address":"Ziegelh\u00fcttenweg 74",
    "sg:city":"H\u00f6chst",
    "sg:phone":"+49 6163/913213",
    "sg:postcode":"64739",
    "sg:province":"Hessen",
    "wof:name":"Lindenhof Projekt- Management Gmbh",
    "wof:placetype":"venue"
},
  "geometry": {"coordinates":[8.9703502655,49.7892990112],"type":"Point"}
}