{
  "type": "Feature",
  "properties": {
    "iso:country":"DE",
    "sg:address":"An der Lanfter 4",
    "sg:city":"Herzberg",
    "sg:phone":"+49 3535/3654",
    "sg:postcode":"04916",
    "sg:province":"Brandenburg",
    "wof:name":"Steinbacher Ingenieur",
    "wof:placetype":"venue"
},
  "geometry": {"coordinates":[13.2320079803,51.6873474121],"type":"Point"}
}