{
  "type": "Feature",
  "properties": {
    "iso:country":"DE",
    "sg:address":"Hirtenstr. 11",
    "sg:city":"Ottobrunn",
    "sg:postcode":"85521",
    "sg:province":"Bayern",
    "wof:name":"Apple Creations Gmbh",
    "wof:placetype":"venue"
},
  "geometry": {"coordinates":[11.660466,48.070889],"type":"Point"}
}