{
  "type": "Feature",
  "properties": {
    "iso:country":"DE",
    "sg:address":"Pfaffenrieder Str. 4",
    "sg:city":"Wolfratshausen",
    "sg:phone":"+49 8171/10035",
    "sg:postcode":"82515",
    "sg:province":"Bayern",
    "wof:name":"Ebner Maschinenbau Gmbh",
    "wof:placetype":"venue"
},
  "geometry": {"coordinates":[11.428558,47.905659],"type":"Point"}
}