{
  "type": "Feature",
  "properties": {
    "iso:country":"DE",
    "sg:address":"Anne-Frank-Str. 36",
    "sg:city":"Hamburg",
    "sg:postcode":"22587",
    "sg:province":"Hamburg",
    "wof:name":"Colonnaden Peter Gummlich Kg",
    "wof:placetype":"venue"
},
  "geometry": {"coordinates":[9.7981834412,53.5687294006],"type":"Point"}
}