{
  "type": "Feature",
  "properties": {
    "iso:country":"DE",
    "sg:address":"Kiebitzheide 1",
    "sg:city":"Beelen",
    "sg:phone":"+49 2586/1250",
    "sg:postcode":"48361",
    "sg:province":"Nordrhein-Westfalen",
    "wof:name":"Karin Zumbusch",
    "wof:placetype":"venue"
},
  "geometry": {"coordinates":[8.108227,51.91346],"type":"Point"}
}