{
  "type": "Feature",
  "properties": {
    "iso:country":"DE",
    "sg:address":"Schulstr. 30",
    "sg:city":"Helbra",
    "sg:phone":"+49 34772/27624",
    "sg:postcode":"06311",
    "sg:province":"Sachsen-Anhalt",
    "wof:name":"Alfred K\u00f6bbel",
    "wof:placetype":"venue"
},
  "geometry": {"coordinates":[11.491196,51.557678],"type":"Point"}
}