{
  "type": "Feature",
  "properties": {
    "iso:country":"DE",
    "sg:address":"Fuchssprung 2",
    "sg:city":"L\u00fcbeck",
    "sg:phone":"+49 451/32077",
    "sg:postcode":"23568",
    "sg:province":"Schleswig-Holstein",
    "wof:name":"Frank Meyer",
    "wof:placetype":"venue"
},
  "geometry": {"coordinates":[10.727783,53.892654],"type":"Point"}
}