{
  "type": "Feature",
  "properties": {
    "iso:country":"DE",
    "sg:address":"Kilianstr. 8",
    "sg:city":"Elfershausen",
    "sg:phone":"+49 9704/4126",
    "sg:postcode":"97725",
    "sg:province":"Bayern",
    "wof:name":"Blau Weiss Elfershausen",
    "wof:placetype":"venue"
},
  "geometry": {"coordinates":[9.973036,50.14608],"type":"Point"}
}