{
  "type": "Feature",
  "properties": {
    "iso:country":"DE",
    "sg:address":"Grabenstr 18",
    "sg:city":"Sindelfingen",
    "sg:phone":"+49 7031/8661120",
    "sg:postcode":"71063",
    "sg:province":"Baden-W\u00fcrttemberg",
    "wof:name":"Asg Rapid Prototyping Gmbh",
    "wof:placetype":"venue"
},
  "geometry": {"coordinates":[8.998503685,48.7089271545],"type":"Point"}
}