{
  "type": "Feature",
  "properties": {
    "iso:country":"DE",
    "sg:address":"Neumarkt 38",
    "sg:city":"Ibbenb\u00fcren",
    "sg:phone":"+49 5451/3650",
    "sg:postcode":"49477",
    "sg:province":"Nordrhein-Westfalen",
    "wof:name":"Dr. Med. Lothar Sommers Arzt F\u00fcr Allgemeinmedizin",
    "wof:placetype":"venue"
},
  "geometry": {"coordinates":[7.7176499367,52.2766189575],"type":"Point"}
}