{
  "type": "Feature",
  "properties": {
    "iso:country":"DE",
    "sg:address":"Stadtplatz 32",
    "sg:city":"Vilsbiburg",
    "sg:phone":"+49 8741/3040",
    "sg:postcode":"84137",
    "sg:province":"Bayern",
    "wof:name":"Sparkasse Vilsbiburg",
    "wof:placetype":"venue"
},
  "geometry": {"coordinates":[12.354449,48.449032],"type":"Point"}
}