{
  "type": "Feature",
  "properties": {
    "iso:country":"DE",
    "sg:address":"Allee der Kosmonauten 32",
    "sg:city":"Berlin",
    "sg:phone":"+49 30/54979700",
    "sg:postcode":"12681",
    "sg:province":"Berlin",
    "wof:name":"K@fo - Kaufcenter-ost",
    "wof:placetype":"venue"
},
  "geometry": {"coordinates":[13.531406,52.525284],"type":"Point"}
}