{
  "type": "Feature",
  "properties": {
    "iso:country":"DE",
    "sg:address":"Diepenauer Str. 77",
    "sg:city":"Espelkamp",
    "sg:phone":"+49 5743/1463",
    "sg:postcode":"32339",
    "sg:province":"Nordrhein-Westfalen",
    "wof:name":"Wilhelm Hegerding",
    "wof:placetype":"venue"
},
  "geometry": {"coordinates":[8.660547,52.340359],"type":"Point"}
}