{
  "type": "Feature",
  "properties": {
    "iso:country":"DE",
    "sg:address":"Gewerbepark Am Wald 6 a",
    "sg:city":"Ilmenau",
    "sg:phone":"+49 3677/844146",
    "sg:postcode":"98693",
    "sg:province":"Th\u00fcringen",
    "wof:name":"Bb-verpackungslogistik Gmbh",
    "wof:placetype":"venue"
},
  "geometry": {"coordinates":[10.94909,50.694832],"type":"Point"}
}