{
  "type": "Feature",
  "properties": {
    "iso:country":"DE",
    "sg:address":"Sch\u00f6nflie\u00dfer Str. 3a",
    "sg:city":"Berlin",
    "sg:phone":"+49 30/4015336",
    "sg:postcode":"13465",
    "sg:province":"Berlin",
    "wof:name":"Fritz D\u00fcrr",
    "wof:placetype":"venue"
},
  "geometry": {"coordinates":[13.285559,52.641399],"type":"Point"}
}