{
  "type": "Feature",
  "properties": {
    "iso:country":"DE",
    "sg:address":"Meppener Str. 70 A",
    "sg:city":"Lingen",
    "sg:phone":"+49 591/63863",
    "sg:postcode":"49808",
    "sg:province":"Niedersachsen",
    "wof:name":"Konso Gmbh",
    "wof:placetype":"venue"
},
  "geometry": {"coordinates":[7.309467,52.5312],"type":"Point"}
}