{
  "type": "Feature",
  "properties": {
    "iso:country":"DE",
    "sg:address":"Hauptstr. 26",
    "sg:city":"H\u00fcnfeld",
    "sg:phone":"+49 6652/2429",
    "sg:postcode":"36088",
    "sg:province":"Hessen",
    "wof:name":"Rudi L\u00fcbeck Stiftsm\u00fchle",
    "wof:placetype":"venue"
},
  "geometry": {"coordinates":[9.764773,50.674713],"type":"Point"}
}