{
  "type": "Feature",
  "properties": {
    "iso:country":"DE",
    "sg:address":"Lerchenweg 19",
    "sg:city":"Friedberg",
    "sg:phone":"+49 821/782123",
    "sg:postcode":"86316",
    "sg:province":"Bayern",
    "wof:name":"P.-j. Gruhn",
    "wof:placetype":"venue"
},
  "geometry": {"coordinates":[10.970414,48.389656],"type":"Point"}
}