{
  "type": "Feature",
  "properties": {
    "iso:country":"DE",
    "sg:address":"Vinkl\u00f6ther Mark 70a",
    "sg:city":"Dortmund",
    "sg:phone":"+49 231/469546",
    "sg:postcode":"44265",
    "sg:province":"Nordrhein-Westfalen",
    "wof:name":"E. Ch. Nacke Gmbh",
    "wof:placetype":"venue"
},
  "geometry": {"coordinates":[7.4909,51.44841],"type":"Point"}
}