{
  "type": "Feature",
  "properties": {
    "iso:country":"DE",
    "sg:address":"G\u00fcntherweg 3",
    "sg:city":"Regensburg",
    "sg:phone":"+49 941/91718",
    "sg:postcode":"93051",
    "sg:province":"Bayern",
    "wof:name":"Dieter Suckert",
    "wof:placetype":"venue"
},
  "geometry": {"coordinates":[12.0769195557,49.0060119629],"type":"Point"}
}