{
  "type": "Feature",
  "properties": {
    "iso:country":"DE",
    "sg:address":"Winkelstr. 18",
    "sg:city":"Bad Pyrmont",
    "sg:phone":"+49 5281/4249",
    "sg:postcode":"31812",
    "sg:province":"Niedersachsen",
    "wof:name":"Otto Jorns",
    "wof:placetype":"venue"
},
  "geometry": {"coordinates":[9.263333,51.985161],"type":"Point"}
}