{
  "type": "Feature",
  "properties": {
    "iso:country":"DE",
    "sg:address":"Birkenhof 1",
    "sg:city":"Limburg",
    "sg:phone":"+49 6482/387",
    "sg:postcode":"65551",
    "sg:province":"Hessen",
    "wof:name":"Franz Friedrich",
    "wof:placetype":"venue"
},
  "geometry": {"coordinates":[8.12683,50.378288],"type":"Point"}
}