{
  "type": "Feature",
  "properties": {
    "iso:country":"DE",
    "sg:address":"Colonia-Allee 10-20",
    "sg:city":"K\u00f6ln",
    "sg:postcode":"51067",
    "sg:province":"Nordrhein-Westfalen",
    "wof:name":"Axa Corporate Solutions Ndl. Deutschland D. Axa Cor-",
    "wof:placetype":"venue"
},
  "geometry": {"coordinates":[7.0488381386,50.9628486633],"type":"Point"}
}