{
  "type": "Feature",
  "properties": {
    "iso:country":"DE",
    "sg:address":"M\u00fchlenstr. 24",
    "sg:city":"Leiwen",
    "sg:phone":"+49 6507/3249",
    "sg:postcode":"54340",
    "sg:province":"Rheinland-Pfalz",
    "wof:name":"Nikolaus Rosch-scholtes",
    "wof:placetype":"venue"
},
  "geometry": {"coordinates":[6.8785247803,49.8224639893],"type":"Point"}
}