{
  "type": "Feature",
  "properties": {
    "iso:country":"DE",
    "sg:address":"Am Wiesenhang 4",
    "sg:city":"Remscheid",
    "sg:phone":"+49 2191/342557",
    "sg:postcode":"42859",
    "sg:province":"Nordrhein-Westfalen",
    "wof:name":"Hans Fritz",
    "wof:placetype":"venue"
},
  "geometry": {"coordinates":[7.2242188454,51.1674613953],"type":"Point"}
}