{
  "type": "Feature",
  "properties": {
    "iso:country":"DE",
    "sg:address":"Harzensweg 14",
    "sg:city":"Hamburg",
    "sg:phone":"+49 40/616754",
    "sg:postcode":"22305",
    "sg:province":"Hamburg",
    "wof:name":"Hermann Gundelach",
    "wof:placetype":"venue"
},
  "geometry": {"coordinates":[10.048504,53.592804],"type":"Point"}
}