{
  "type": "Feature",
  "properties": {
    "iso:country":"DE",
    "sg:address":"Hauptstuhler Str. 1",
    "sg:city":"H\u00fctschenhausen",
    "sg:phone":"+49 6372/7964",
    "sg:postcode":"66882",
    "sg:province":"Rheinland-Pfalz",
    "wof:name":"E. Und H. Holzhauser",
    "wof:placetype":"venue"
},
  "geometry": {"coordinates":[7.4819579124,49.4192352295],"type":"Point"}
}