{
  "type": "Feature",
  "properties": {
    "iso:country":"DE",
    "sg:address":"Flo\u00dfhafenstr. 6",
    "sg:city":"Neuss",
    "sg:phone":"+49 2131/224400",
    "sg:postcode":"41460",
    "sg:province":"Nordrhein-Westfalen",
    "wof:name":"Mega Poster Und Art Ger\u00fcstschutznetze",
    "wof:placetype":"venue"
},
  "geometry": {"coordinates":[6.7050251961,51.2028007507],"type":"Point"}
}