{
  "type": "Feature",
  "properties": {
    "iso:country":"DE",
    "sg:address":"K\u00fcrnbergstr. 30",
    "sg:city":"M\u00fcnchen",
    "sg:phone":"+49 89/7608351",
    "sg:postcode":"81369",
    "sg:province":"Bayern",
    "wof:name":"Franz Rieger",
    "wof:placetype":"venue"
},
  "geometry": {"coordinates":[11.531624,48.113689],"type":"Point"}
}