{
  "type": "Feature",
  "properties": {
    "iso:country":"DE",
    "sg:address":"Bundesstr. 1",
    "sg:city":"Sulzbach",
    "sg:phone":"+49 7193/7594",
    "sg:postcode":"71560",
    "sg:province":"Baden-W\u00fcrttemberg",
    "wof:name":"Nestlinger",
    "wof:placetype":"venue"
},
  "geometry": {"coordinates":[9.49744,49.00452],"type":"Point"}
}