{
  "type": "Feature",
  "properties": {
    "iso:country":"DE",
    "sg:address":"Bierstr. 12",
    "sg:city":"Saarlouis",
    "sg:phone":"+49 6831/121021",
    "sg:postcode":"66740",
    "sg:province":"Saarland",
    "wof:name":"Restaurant La Trattoria",
    "wof:placetype":"venue"
},
  "geometry": {"coordinates":[6.7501101494,49.3138885498],"type":"Point"}
}