{
  "type": "Feature",
  "properties": {
    "iso:country":"DE",
    "sg:address":"Ringstr. 35",
    "sg:city":"Schmallenberg",
    "sg:postcode":"57392",
    "sg:province":"Nordrhein-Westfalen",
    "wof:name":"Ev. \u00d6ffentliche Bibliothek",
    "wof:placetype":"venue"
},
  "geometry": {"coordinates":[8.28238,51.15477],"type":"Point"}
}