{
  "type": "Feature",
  "properties": {
    "iso:country":"DE",
    "sg:address":"Lange Str. 96 a",
    "sg:city":"Hagen",
    "sg:phone":"+49 2331/335456",
    "sg:postcode":"58089",
    "sg:province":"Nordrhein-Westfalen",
    "wof:name":"Stern-apotheke",
    "wof:placetype":"venue"
},
  "geometry": {"coordinates":[7.454679,51.351437],"type":"Point"}
}