{
  "type": "Feature",
  "properties": {
    "iso:country":"DE",
    "sg:address":"Hustadtring 151",
    "sg:city":"Bochum",
    "sg:postcode":"44801",
    "sg:province":"Nordrhein-Westfalen",
    "wof:name":"Sch\u00e4fer Und Stenzel Trockenbau Gmbh",
    "wof:placetype":"venue"
},
  "geometry": {"coordinates":[7.2783517838,51.4556465149],"type":"Point"}
}