{
  "type": "Feature",
  "properties": {
    "iso:country":"DE",
    "sg:address":"Pressentinstr. 3",
    "sg:city":"Rostock",
    "sg:phone":"+49 381/699936",
    "sg:postcode":"18147",
    "sg:province":"Mecklenburg-Vorpommern",
    "wof:name":"Maritim-bar",
    "wof:placetype":"venue"
},
  "geometry": {"coordinates":[12.113727,54.105003],"type":"Point"}
}