{
  "type": "Feature",
  "properties": {
    "iso:country":"DE",
    "sg:address":"Rathausplatz 1",
    "sg:city":"Lengerich",
    "sg:phone":"+49 5481/37471",
    "sg:postcode":"49525",
    "sg:province":"Nordrhein-Westfalen",
    "wof:name":"B. Peters",
    "wof:placetype":"venue"
},
  "geometry": {"coordinates":[7.8513898849,52.1884384155],"type":"Point"}
}