{
  "type": "Feature",
  "properties": {
    "iso:country":"DE",
    "sg:address":"Puschkinstr. 28",
    "sg:city":"Schwerin",
    "sg:phone":"+49 385/562419",
    "sg:postcode":"19055",
    "sg:province":"Mecklenburg-Vorpommern",
    "wof:name":"P. Struve",
    "wof:placetype":"venue"
},
  "geometry": {"coordinates":[11.416311264,53.6301307678],"type":"Point"}
}