{
  "type": "Feature",
  "properties": {
    "iso:country":"DE",
    "sg:address":"Am Orenberg 6",
    "sg:city":"Willingen",
    "sg:phone":"+49 5632/6571",
    "sg:postcode":"34508",
    "sg:province":"Hessen",
    "wof:name":"Pension Karl-heinz Engelbracht",
    "wof:placetype":"venue"
},
  "geometry": {"coordinates":[8.6170902252,51.2923583984],"type":"Point"}
}