{
  "type": "Feature",
  "properties": {
    "iso:country":"DE",
    "sg:address":"Wigandweg 91",
    "sg:city":"Hamburg",
    "sg:phone":"+49 40/55760966",
    "sg:postcode":"22453",
    "sg:province":"Hamburg",
    "wof:name":"Soup City Gmbh",
    "wof:placetype":"venue"
},
  "geometry": {"coordinates":[9.9775896072,53.6099853516],"type":"Point"}
}