{
  "type": "Feature",
  "properties": {
    "iso:country":"DE",
    "sg:address":"Goethestr. 15",
    "sg:city":"Ettlingen",
    "sg:phone":"+49 7243/765991",
    "sg:postcode":"76275",
    "sg:province":"Baden-W\u00fcrttemberg",
    "wof:name":"Assekuranz-partner Versicherungsmakler Gmbh",
    "wof:placetype":"venue"
},
  "geometry": {"coordinates":[8.4006137848,48.9411315918],"type":"Point"}
}