{
  "type": "Feature",
  "properties": {
    "iso:country":"DE",
    "sg:address":"Ebertstr. 19",
    "sg:city":"Gelsenkirchen",
    "sg:phone":"+49 209/1692825",
    "sg:postcode":"45879",
    "sg:province":"Nordrhein-Westfalen",
    "wof:name":"Institut F\u00fcr Stadtgeschichte Stadtarchiv Bildungszentrum",
    "wof:placetype":"venue"
},
  "geometry": {"coordinates":[7.09216,51.512856],"type":"Point"}
}