{
  "type": "Feature",
  "properties": {
    "iso:country":"DE",
    "sg:address":"Kallenhardter Str. 8",
    "sg:city":"R\u00fcthen",
    "sg:phone":"+49 2952/2428",
    "sg:postcode":"59602",
    "sg:province":"Nordrhein-Westfalen",
    "wof:name":"Franz Lattrich",
    "wof:placetype":"venue"
},
  "geometry": {"coordinates":[8.4473638535,51.4824943542],"type":"Point"}
}