{
  "type": "Feature",
  "properties": {
    "iso:country":"DE",
    "sg:address":"Radeberger Str. 98",
    "sg:city":"Gro\u00dfr\u00f6hrsdorf",
    "sg:phone":"+49 35952/46506",
    "sg:postcode":"01900",
    "sg:province":"Sachsen",
    "wof:name":"Ralf Thiele",
    "wof:placetype":"venue"
},
  "geometry": {"coordinates":[13.9997806549,51.1382064819],"type":"Point"}
}