{
  "type": "Feature",
  "properties": {
    "iso:country":"DE",
    "sg:address":"Obere Hauptstr. 52",
    "sg:city":"Freising",
    "sg:phone":"+49 8161/94077",
    "sg:postcode":"85354",
    "sg:province":"Bayern",
    "wof:name":"Hans Gebele Steuerberater",
    "wof:placetype":"venue"
},
  "geometry": {"coordinates":[11.7398052216,48.3989295959],"type":"Point"}
}