{
  "type": "Feature",
  "properties": {
    "iso:country":"DE",
    "sg:address":"Dorfstr. 17",
    "sg:city":"Kroppen",
    "sg:postcode":"01945",
    "sg:province":"Brandenburg",
    "wof:name":"Ev. Kirche",
    "wof:placetype":"venue"
},
  "geometry": {"coordinates":[13.8016643524,51.3854751587],"type":"Point"}
}