{
  "type": "Feature",
  "properties": {
    "iso:country":"DE",
    "sg:address":"Gerberstr. 8",
    "sg:city":"Eislingen",
    "sg:phone":"+49 7161/814836",
    "sg:postcode":"73054",
    "sg:province":"Baden-W\u00fcrttemberg",
    "wof:name":"Sportstudio Condo",
    "wof:placetype":"venue"
},
  "geometry": {"coordinates":[9.7111616135,48.6942443848],"type":"Point"}
}