{
  "type": "Feature",
  "properties": {
    "iso:country":"DE",
    "sg:address":"Fischhausweg 1",
    "sg:city":"F\u00fcssen",
    "sg:phone":"+49 8362/6380",
    "sg:postcode":"87629",
    "sg:province":"Bayern",
    "wof:name":"Haus Zanghellini",
    "wof:placetype":"venue"
},
  "geometry": {"coordinates":[10.689711,47.564934],"type":"Point"}
}