{
  "type": "Feature",
  "properties": {
    "iso:country":"DE",
    "sg:address":"Brandenburger Str. 3",
    "sg:city":"Premnitz",
    "sg:phone":"+49 3386/282232",
    "sg:postcode":"14727",
    "sg:province":"Brandenburg",
    "wof:name":"Mirko Rahn",
    "wof:placetype":"venue"
},
  "geometry": {"coordinates":[12.3657312393,52.52085495],"type":"Point"}
}