{
  "type": "Feature",
  "properties": {
    "iso:country":"DE",
    "sg:address":"Giengener Str. 19",
    "sg:city":"Herbrechtingen",
    "sg:phone":"+49 7324/3511",
    "sg:postcode":"89542",
    "sg:province":"Baden-W\u00fcrttemberg",
    "wof:name":"Alfred Scheurer",
    "wof:placetype":"venue"
},
  "geometry": {"coordinates":[10.179017,48.622402],"type":"Point"}
}