{
  "type": "Feature",
  "properties": {
    "iso:country":"DE",
    "sg:address":"Haferstr. 15",
    "sg:city":"Melle",
    "sg:phone":"+49 5422/41799",
    "sg:postcode":"49324",
    "sg:province":"Niedersachsen",
    "wof:name":"Birgit Hesprich",
    "wof:placetype":"venue"
},
  "geometry": {"coordinates":[8.338022,52.201237],"type":"Point"}
}