{
  "type": "Feature",
  "properties": {
    "iso:country":"DE",
    "sg:address":"Heidhofweg 15 a",
    "sg:city":"Osterholz-Scharmbeck",
    "sg:phone":"+49 4795/1596",
    "sg:postcode":"27711",
    "sg:province":"Niedersachsen",
    "wof:name":"J\u00fcrgen Aue",
    "wof:placetype":"venue"
},
  "geometry": {"coordinates":[8.7034683228,53.2487564087],"type":"Point"}
}