{
  "type": "Feature",
  "properties": {
    "iso:country":"DE",
    "sg:address":"Steingasse 40",
    "sg:city":"Grenzach-Wyhlen",
    "sg:phone":"+49 7624/5629",
    "sg:postcode":"79639",
    "sg:province":"Baden-W\u00fcrttemberg",
    "wof:name":"Theodor Dietrich Architekt",
    "wof:placetype":"venue"
},
  "geometry": {"coordinates":[7.668068,47.552979],"type":"Point"}
}