{
  "type": "Feature",
  "properties": {
    "iso:country":"DE",
    "sg:address":"Bachstr. 5",
    "sg:city":"Geiersthal",
    "sg:phone":"+49 9923/3232",
    "sg:postcode":"94244",
    "sg:province":"Bayern",
    "wof:name":"Dr. M. Bliersbach-bullermann Tier\u00e4rztin",
    "wof:placetype":"venue"
},
  "geometry": {"coordinates":[12.9861631393,49.0417366028],"type":"Point"}
}