{
  "type": "Feature",
  "properties": {
    "iso:country":"DE",
    "sg:address":"Am Luftschiffhafen 2",
    "sg:city":"Gotha",
    "sg:phone":"+49 3621/709747",
    "sg:postcode":"99867",
    "sg:province":"Th\u00fcringen",
    "wof:name":"Ergo Versicherungsgruppe Ag",
    "wof:placetype":"venue"
},
  "geometry": {"coordinates":[10.7286663055,50.9221496582],"type":"Point"}
}