{
  "type": "Feature",
  "properties": {
    "iso:country":"DE",
    "sg:address":"Markt 5",
    "sg:city":"Bad Honnef",
    "sg:phone":"+49 2224/2571",
    "sg:postcode":"53604",
    "sg:province":"Nordrhein-Westfalen",
    "wof:name":"Josef Ophoven",
    "wof:placetype":"venue"
},
  "geometry": {"coordinates":[7.22735,50.645432],"type":"Point"}
}