{
  "type": "Feature",
  "properties": {
    "iso:country":"DE",
    "sg:address":"Kolbstr. 26",
    "sg:city":"Kirchheim",
    "sg:phone":"+49 7021/42244",
    "sg:postcode":"73230",
    "sg:province":"Baden-W\u00fcrttemberg",
    "wof:name":"Foto-quelle Egon Koeters",
    "wof:placetype":"venue"
},
  "geometry": {"coordinates":[9.4455137253,48.6467666626],"type":"Point"}
}