{
  "type": "Feature",
  "properties": {
    "iso:country":"DE",
    "sg:address":"Friedhofstr. 2a",
    "sg:city":"Obrigheim",
    "sg:phone":"+49 6261/7359",
    "sg:postcode":"74847",
    "sg:province":"Baden-W\u00fcrttemberg",
    "wof:name":"Bruno Ripp",
    "wof:placetype":"venue"
},
  "geometry": {"coordinates":[9.096498,49.35218],"type":"Point"}
}