{
  "type": "Feature",
  "properties": {
    "iso:country":"DE",
    "sg:address":"Paradeplatz 1",
    "sg:city":"Forchheim",
    "sg:phone":"+49 9191/640600",
    "sg:postcode":"91301",
    "sg:province":"Bayern",
    "wof:name":"Bawo Wohnbau Gmbh",
    "wof:placetype":"venue"
},
  "geometry": {"coordinates":[11.060756,49.71785],"type":"Point"}
}