{
  "type": "Feature",
  "properties": {
    "iso:country":"DE",
    "sg:address":"Hauptstr. 87",
    "sg:city":"Guteborn",
    "sg:phone":"+49 35752/15992",
    "sg:postcode":"01945",
    "sg:province":"Brandenburg",
    "wof:name":"Riemer & S\u00f6hne Dachdecker Gmbh",
    "wof:placetype":"venue"
},
  "geometry": {"coordinates":[13.919699,51.424278],"type":"Point"}
}