{
  "type": "Feature",
  "properties": {
    "iso:country":"DE",
    "sg:address":"M\u00f6ttelinstr. 15",
    "sg:city":"Ravensburg",
    "sg:phone":"+49 751/23673",
    "sg:postcode":"88212",
    "sg:province":"Baden-W\u00fcrttemberg",
    "wof:name":"Misol Motorentechnik Verwaltungs Gmbh",
    "wof:placetype":"venue"
},
  "geometry": {"coordinates":[9.61489,47.786194],"type":"Point"}
}