{
  "type": "Feature",
  "properties": {
    "iso:country":"DE",
    "sg:address":"Gabelsbergerstr. 8",
    "sg:city":"Hannover",
    "sg:phone":"+49 511/628830",
    "sg:postcode":"30163",
    "sg:province":"Niedersachsen",
    "wof:name":"Suba Export-import Gmbh",
    "wof:placetype":"venue"
},
  "geometry": {"coordinates":[9.745141983,52.3914413452],"type":"Point"}
}