{
  "type": "Feature",
  "properties": {
    "iso:country":"DE",
    "sg:address":"Hermannsburg 229",
    "sg:city":"Bremen",
    "sg:phone":"+49 421/563799",
    "sg:postcode":"28259",
    "sg:province":"Bremen",
    "wof:name":"Bremer Baugesellschaft Schmidt Gmbh & Co. Kg",
    "wof:placetype":"venue"
},
  "geometry": {"coordinates":[8.730798,53.035431],"type":"Point"}
}