{
  "type": "Feature",
  "properties": {
    "iso:country":"DE",
    "sg:address":"G\u00fcbser Weg 1",
    "sg:city":"Menz",
    "sg:phone":"+49 39292/2176",
    "sg:postcode":"39175",
    "sg:province":"Sachsen-Anhalt",
    "wof:name":"Agrarunternehmen Menz Eg",
    "wof:placetype":"venue"
},
  "geometry": {"coordinates":[11.760425,52.116665],"type":"Point"}
}