{
  "type": "Feature",
  "properties": {
    "iso:country":"DE",
    "sg:address":"Schevenh\u00fctter Str. 8",
    "sg:city":"Stolberg",
    "sg:phone":"+49 2681/6283",
    "sg:postcode":"52224",
    "sg:province":"Nordrhein-Westfalen",
    "wof:name":"I. Leuchtenberg",
    "wof:placetype":"venue"
},
  "geometry": {"coordinates":[6.302312,50.773495],"type":"Point"}
}