{
  "type": "Feature",
  "properties": {
    "iso:country":"DE",
    "sg:address":"Pfinztalstr. 47",
    "sg:city":"Karlsruhe",
    "sg:phone":"+49 721/498070",
    "sg:postcode":"76227",
    "sg:province":"Baden-W\u00fcrttemberg",
    "wof:name":"Kleinpreis-mode Hans Keilbach",
    "wof:placetype":"venue"
},
  "geometry": {"coordinates":[8.4699249268,48.9991722107],"type":"Point"}
}