{
  "type": "Feature",
  "properties": {
    "iso:country":"DE",
    "sg:address":"Werster Str. 108",
    "sg:city":"Bad Oeynhausen",
    "sg:phone":"+49 5731/40395",
    "sg:postcode":"32549",
    "sg:province":"Nordrhein-Westfalen",
    "wof:name":"Friedrich Kahre",
    "wof:placetype":"venue"
},
  "geometry": {"coordinates":[8.781187,52.21553],"type":"Point"}
}