{
  "type": "Feature",
  "properties": {
    "iso:country":"DE",
    "sg:address":"Seestr. 2",
    "sg:city":"Prien",
    "sg:phone":"+49 8051/1572",
    "sg:postcode":"83209",
    "sg:province":"Bayern",
    "wof:name":"Carl Brunhuber Inh. Roswitha Rappel",
    "wof:placetype":"venue"
},
  "geometry": {"coordinates":[12.3447704315,47.8554801941],"type":"Point"}
}