{
  "type": "Feature",
  "properties": {
    "iso:country":"DE",
    "sg:address":"D\u00fcrener Str. 405",
    "sg:city":"Eschweiler",
    "sg:phone":"+49 2403/4338",
    "sg:postcode":"52249",
    "sg:province":"Nordrhein-Westfalen",
    "wof:name":"Manfred Wilhelm",
    "wof:placetype":"venue"
},
  "geometry": {"coordinates":[6.297029,50.820732],"type":"Point"}
}