{
  "type": "Feature",
  "properties": {
    "iso:country":"DE",
    "sg:address":"Blumenstr. 76",
    "sg:city":"Markgr\u00f6ningen",
    "sg:phone":"+49 7145/3957",
    "sg:postcode":"71706",
    "sg:province":"Baden-W\u00fcrttemberg",
    "wof:name":"Metallbau Diemer",
    "wof:placetype":"venue"
},
  "geometry": {"coordinates":[9.092403,48.897148],"type":"Point"}
}