{
  "type": "Feature",
  "properties": {
    "iso:country":"DE",
    "sg:address":"Zerhusenstr. 1",
    "sg:city":"Visbek",
    "sg:phone":"+49 4445/2115",
    "sg:postcode":"49429",
    "sg:province":"Niedersachsen",
    "wof:name":"Wilfried Bender",
    "wof:placetype":"venue"
},
  "geometry": {"coordinates":[8.321271,52.834202],"type":"Point"}
}