{
  "type": "Feature",
  "properties": {
    "iso:country":"DE",
    "sg:address":"Turnstr. 1",
    "sg:city":"Krickenbach",
    "sg:phone":"+49 6307/1579",
    "sg:postcode":"67706",
    "sg:province":"Rheinland-Pfalz",
    "wof:name":"Erika Wolter",
    "wof:placetype":"venue"
},
  "geometry": {"coordinates":[7.6685271263,49.362991333],"type":"Point"}
}