{
  "type": "Feature",
  "properties": {
    "iso:country":"DE",
    "sg:address":"Haldener Str. 24",
    "sg:city":"Hagen",
    "sg:phone":"+49 2331/27897",
    "sg:postcode":"58095",
    "sg:province":"Nordrhein-Westfalen",
    "wof:name":"Hans Wagener",
    "wof:placetype":"venue"
},
  "geometry": {"coordinates":[7.481427,51.360512],"type":"Point"}
}