{
  "type": "Feature",
  "properties": {
    "iso:country":"DE",
    "sg:address":"Ostring 8",
    "sg:city":"Nieb\u00fcll",
    "sg:phone":"+49 4661/766",
    "sg:postcode":"25899",
    "sg:province":"Schleswig-Holstein",
    "wof:name":"Taxi Johannsen Gmbh & Co.",
    "wof:placetype":"venue"
},
  "geometry": {"coordinates":[8.8455991745,54.7823905945],"type":"Point"}
}