{
  "type": "Feature",
  "properties": {
    "iso:country":"DE",
    "sg:address":"Rosenheimer Str. 1::",
    "sg:city":"Wasserburg",
    "sg:phone":"+49 8071/1010",
    "sg:postcode":"83512",
    "sg:province":"Bayern",
    "wof:name":"Kreis- U. Stadtsparkasse Wasserburg Am Inn",
    "wof:placetype":"venue"
},
  "geometry": {"coordinates":[12.231446,48.058113],"type":"Point"}
}