{
  "type": "Feature",
  "properties": {
    "iso:country":"DE",
    "sg:address":"Sandbergstr. 6",
    "sg:city":"N\u00fcrnberg",
    "sg:phone":"+49 911/5075591",
    "sg:postcode":"90419",
    "sg:province":"Bayern",
    "wof:name":"Hochhausen",
    "wof:placetype":"venue"
},
  "geometry": {"coordinates":[11.058966,49.458538],"type":"Point"}
}