{
  "type": "Feature",
  "properties": {
    "iso:country":"DE",
    "sg:address":"Mainstr. 39",
    "sg:city":"Schlangenbad",
    "sg:postcode":"65388",
    "sg:province":"Hessen",
    "wof:name":"Ingenieurb\u00fcro Sermond Gmbh",
    "wof:placetype":"venue"
},
  "geometry": {"coordinates":[8.122957,50.08778],"type":"Point"}
}