{
  "type": "Feature",
  "properties": {
    "iso:country":"DE",
    "sg:address":"Mittlerer Schafhofweg 6",
    "sg:city":"Frankfurt",
    "sg:phone":"+49 69/635693",
    "sg:postcode":"60598",
    "sg:province":"Hessen",
    "wof:name":"Katharina Wallenborn Architektin",
    "wof:placetype":"venue"
},
  "geometry": {"coordinates":[8.683142,50.091843],"type":"Point"}
}