{
  "type": "Feature",
  "properties": {
    "iso:country":"DE",
    "sg:address":"Ruhrstr. 100",
    "sg:city":"Heiligenhaus",
    "sg:postcode":"42579",
    "sg:province":"Nordrhein-Westfalen",
    "wof:name":"Schauenburg Stiftung Hasenberg",
    "wof:placetype":"venue"
},
  "geometry": {"coordinates":[6.9386820793,51.3396873474],"type":"Point"}
}