{
  "type": "Feature",
  "properties": {
    "iso:country":"DE",
    "sg:address":"B\u00fchlstr. 44",
    "sg:city":"G\u00f6ttingen",
    "sg:phone":"+49 551/58900",
    "sg:postcode":"37073",
    "sg:province":"Niedersachsen",
    "wof:name":"Humboldt-apotheke",
    "wof:placetype":"venue"
},
  "geometry": {"coordinates":[9.942422,51.539463],"type":"Point"}
}