{
  "type": "Feature",
  "properties": {
    "iso:country":"DE",
    "sg:address":"Reriker Str. 35a",
    "sg:city":"K\u00fchlungsborn",
    "sg:phone":"+49 38293/13053",
    "sg:postcode":"18225",
    "sg:province":"Mecklenburg-Vorpommern",
    "wof:name":"Vereinsgastst\u00e4tte K\u00fchlungsblick",
    "wof:placetype":"venue"
},
  "geometry": {"coordinates":[11.7579298019,54.1484947205],"type":"Point"}
}