{
  "type": "Feature",
  "properties": {
    "iso:country":"DE",
    "sg:address":"Unterdorfstr. 10",
    "sg:city":"Zellingen",
    "sg:phone":"+49 9396/580",
    "sg:postcode":"97225",
    "sg:province":"Bayern",
    "wof:name":"Gerhard Famulla",
    "wof:placetype":"venue"
},
  "geometry": {"coordinates":[9.717504,49.90237],"type":"Point"}
}