{
  "type": "Feature",
  "properties": {
    "iso:country":"DE",
    "sg:address":"Buchholzstr. 45",
    "sg:city":"Bergisch Gladbach",
    "sg:phone":"+49 2202/52968",
    "sg:postcode":"51469",
    "sg:province":"Nordrhein-Westfalen",
    "wof:name":"Josef B\u00fcscher Steuerberater",
    "wof:placetype":"venue"
},
  "geometry": {"coordinates":[7.1120710373,50.9871940613],"type":"Point"}
}