{
  "type": "Feature",
  "properties": {
    "iso:country":"DE",
    "sg:address":"Frohnhof 1",
    "sg:city":"Hahnbach",
    "sg:phone":"+49 9664/1766",
    "sg:postcode":"92256",
    "sg:province":"Bayern",
    "wof:name":"Werner Siewert Ingenieur",
    "wof:placetype":"venue"
},
  "geometry": {"coordinates":[11.789981842,49.5176734924],"type":"Point"}
}