{
  "type": "Feature",
  "properties": {
    "iso:country":"DE",
    "sg:address":"L\u00fctzinger Str. 19",
    "sg:city":"Brohl-L\u00fctzing",
    "sg:phone":"+49 2633/1222",
    "sg:postcode":"56656",
    "sg:province":"Rheinland-Pfalz",
    "wof:name":"Anton Mannheim Elektroinstallation",
    "wof:placetype":"venue"
},
  "geometry": {"coordinates":[7.319328,50.487049],"type":"Point"}
}