{
  "type": "Feature",
  "properties": {
    "iso:country":"DE",
    "sg:address":"Franziskanerplatz 6",
    "sg:city":"Regensburg",
    "sg:phone":"+49 941/84338",
    "sg:postcode":"93059",
    "sg:province":"Bayern",
    "wof:name":"Alfred Fahrnholz",
    "wof:placetype":"venue"
},
  "geometry": {"coordinates":[12.0948829651,49.0243606567],"type":"Point"}
}