{
  "type": "Feature",
  "properties": {
    "iso:country":"DE",
    "sg:address":"Burgstrasse 35",
    "sg:city":"Betzdorf",
    "sg:postcode":"57518",
    "sg:province":"Rheinland-Pfalz",
    "wof:name":"Allround-tech Gmbh",
    "wof:placetype":"venue"
},
  "geometry": {"coordinates":[7.8680591583,50.7879562378],"type":"Point"}
}