{
  "type": "Feature",
  "properties": {
    "iso:country":"DE",
    "sg:address":"Annenweg 2",
    "sg:city":"Verl",
    "sg:phone":"+49 5246/4281",
    "sg:postcode":"33415",
    "sg:province":"Nordrhein-Westfalen",
    "wof:name":"Anette Schlepphorst",
    "wof:placetype":"venue"
},
  "geometry": {"coordinates":[8.5681724548,51.8589286804],"type":"Point"}
}