{
  "type": "Feature",
  "properties": {
    "iso:country":"DE",
    "sg:address":"Untere Eichst\u00e4dtstr. 8",
    "sg:city":"Leipzig",
    "sg:phone":"+49 341/2116100",
    "sg:postcode":"04299",
    "sg:province":"Sachsen",
    "wof:name":"Helmut Bartsch",
    "wof:placetype":"venue"
},
  "geometry": {"coordinates":[12.416523,51.323982],"type":"Point"}
}