{
  "type": "Feature",
  "properties": {
    "iso:country":"DE",
    "sg:address":"Frenzenstr 102",
    "sg:city":"Erftstadt",
    "sg:phone":"+49 2235/95630",
    "sg:postcode":"50374",
    "sg:province":"Nordrhein-Westfalen",
    "wof:name":"Kaspers Gmbh",
    "wof:placetype":"venue"
},
  "geometry": {"coordinates":[6.7661709785,50.8107948303],"type":"Point"}
}