{
  "type": "Feature",
  "properties": {
    "iso:country":"DE",
    "sg:address":"Weiskircher Weg 18",
    "sg:city":"Heusenstamm",
    "sg:phone":"+49 6104/2440",
    "sg:postcode":"63150",
    "sg:province":"Hessen",
    "wof:name":"Bodo Meier Inh. Anna Meier",
    "wof:placetype":"venue"
},
  "geometry": {"coordinates":[8.8135404587,50.0570755005],"type":"Point"}
}