{
  "type": "Feature",
  "properties": {
    "iso:country":"DE",
    "sg:address":"Go\u00dfborngasse 3",
    "sg:city":"Gem\u00fcnden",
    "sg:phone":"+49 6634/298",
    "sg:postcode":"35329",
    "sg:province":"Hessen",
    "wof:name":"Rudolf W\u00f6ll",
    "wof:placetype":"venue"
},
  "geometry": {"coordinates":[9.059117,50.694736],"type":"Point"}
}