{
  "type": "Feature",
  "properties": {
    "iso:country":"DE",
    "sg:address":"Am Hafen 2",
    "sg:city":"Brandenburg",
    "sg:postcode":"14770",
    "sg:province":"Brandenburg",
    "wof:name":"Rhenus Verwaltungs- Ag",
    "wof:placetype":"venue"
},
  "geometry": {"coordinates":[12.5541553497,52.4240760803],"type":"Point"}
}