{
  "type": "Feature",
  "properties": {
    "iso:country":"DE",
    "sg:address":"Steinstr. 11",
    "sg:city":"Kaiserslautern",
    "sg:phone":"+49 631/67608",
    "sg:postcode":"67657",
    "sg:province":"Rheinland-Pfalz",
    "wof:name":"Pizzeria Firenze Gastst\u00e4ttenbetriebs Gmbh",
    "wof:placetype":"venue"
},
  "geometry": {"coordinates":[7.7719402313,49.4461860657],"type":"Point"}
}