{
  "type": "Feature",
  "properties": {
    "iso:country":"DE",
    "sg:address":"Charitas-Bischoff-Treppe 7",
    "sg:city":"Hamburg",
    "sg:phone":"+49 40/322388",
    "sg:postcode":"22587",
    "sg:province":"Hamburg",
    "wof:name":"Hans R\u00f6der Hausverw.",
    "wof:placetype":"venue"
},
  "geometry": {"coordinates":[9.8054714203,53.5598831177],"type":"Point"}
}