{
  "type": "Feature",
  "properties": {
    "iso:country":"DE",
    "sg:address":"Fontanestr. 1",
    "sg:city":"Frankfurt",
    "sg:phone":"+49 69/525701",
    "sg:postcode":"60431",
    "sg:province":"Hessen",
    "wof:name":"Freiherrlich Wilhelm Carl Von Rothschildsche Stiftung F\u00fcr",
    "wof:placetype":"venue"
},
  "geometry": {"coordinates":[8.6643104553,50.1478805542],"type":"Point"}
}