{
  "type": "Feature",
  "properties": {
    "iso:country":"DE",
    "sg:address":"Herzberger Landstr. 43 a",
    "sg:city":"G\u00f6ttingen",
    "sg:phone":"+49 551/47939",
    "sg:postcode":"37085",
    "sg:province":"Niedersachsen",
    "wof:name":"Dorothea Dirks Krankengymnastin",
    "wof:placetype":"venue"
},
  "geometry": {"coordinates":[9.95097,51.536137],"type":"Point"}
}