{
  "type": "Feature",
  "properties": {
    "iso:country":"DE",
    "sg:address":"Westhofener Str. 9",
    "sg:city":"Dittelsheim-He\u00dfloch",
    "sg:phone":"+49 6244/4411",
    "sg:postcode":"67596",
    "sg:province":"Rheinland-Pfalz",
    "wof:name":"Wilfried Menger",
    "wof:placetype":"venue"
},
  "geometry": {"coordinates":[8.243566,49.740154],"type":"Point"}
}