{
  "type": "Feature",
  "properties": {
    "iso:country":"DE",
    "sg:address":"Kaiserstr. 1",
    "sg:city":"Saarbr\u00fccken",
    "sg:postcode":"66111",
    "sg:province":"Saarland",
    "wof:name":"R. Sandmeyer",
    "wof:placetype":"venue"
},
  "geometry": {"coordinates":[6.996098,49.236446],"type":"Point"}
}