{
  "type": "Feature",
  "properties": {
    "iso:country":"DE",
    "sg:address":"Bahnhofstr. 5",
    "sg:city":"Reichenbach",
    "sg:phone":"+49 7153/958856",
    "sg:postcode":"73262",
    "sg:province":"Baden-W\u00fcrttemberg",
    "wof:name":"A. Mockler",
    "wof:placetype":"venue"
},
  "geometry": {"coordinates":[7.5411128998,49.5006103516],"type":"Point"}
}