{
  "type": "Feature",
  "properties": {
    "iso:country":"DE",
    "sg:address":"Mittnachtstr. 4",
    "sg:city":"Heilbronn",
    "sg:phone":"+49 7066/7278",
    "sg:postcode":"74078",
    "sg:province":"Baden-W\u00fcrttemberg",
    "wof:name":"Karl Wittmann",
    "wof:placetype":"venue"
},
  "geometry": {"coordinates":[9.1476545334,49.1919975281],"type":"Point"}
}