{
  "type": "Feature",
  "properties": {
    "iso:country":"DE",
    "sg:address":"Brunnenstr. 4",
    "sg:city":"Alf",
    "sg:phone":"+49 6542/2891",
    "sg:postcode":"56859",
    "sg:province":"Rheinland-Pfalz",
    "wof:name":"Klemens Franzen",
    "wof:placetype":"venue"
},
  "geometry": {"coordinates":[7.1253461838,50.05701828],"type":"Point"}
}