{
  "type": "Feature",
  "properties": {
    "iso:country":"DE",
    "sg:address":"Sonnenbergstr. 94",
    "sg:city":"Stuttgart",
    "sg:phone":"+49 711/241384",
    "sg:postcode":"70184",
    "sg:province":"Baden-W\u00fcrttemberg",
    "wof:name":"Michael Maier",
    "wof:placetype":"venue"
},
  "geometry": {"coordinates":[9.1949729919,48.7658233643],"type":"Point"}
}