{
  "type": "Feature",
  "properties": {
    "iso:country":"DE",
    "sg:address":"Bremkestr. 42",
    "sg:city":"Herzberg",
    "sg:phone":"+49 5521/2569",
    "sg:postcode":"37412",
    "sg:province":"Niedersachsen",
    "wof:name":"Willi Lautenbach",
    "wof:placetype":"venue"
},
  "geometry": {"coordinates":[10.3800802231,51.6307945251],"type":"Point"}
}