{
  "type": "Feature",
  "properties": {
    "iso:country":"DE",
    "sg:address":"Graf-von-L\u00f6h-Str. 6",
    "sg:city":"Drolshagen",
    "sg:phone":"+49 2763/6108",
    "sg:postcode":"57489",
    "sg:province":"Nordrhein-Westfalen",
    "wof:name":"R. Und V. B\u00fchne",
    "wof:placetype":"venue"
},
  "geometry": {"coordinates":[7.706448,51.068424],"type":"Point"}
}