{
  "type": "Feature",
  "properties": {
    "iso:country":"DE",
    "sg:address":"Allersdorf",
    "sg:city":"Kollnburg",
    "sg:phone":"+49 9929/1267",
    "sg:postcode":"94262",
    "sg:province":"Bayern",
    "wof:name":"Gasthof Bielmeier",
    "wof:placetype":"venue"
},
  "geometry": {"coordinates":[12.9107303619,49.007270813],"type":"Point"}
}