{
  "type": "Feature",
  "properties": {
    "iso:country":"DE",
    "sg:address":"Rudolf-Renner-Str. 50 a",
    "sg:city":"Pirna",
    "sg:phone":"+49 3501/525810",
    "sg:postcode":"01796",
    "sg:province":"Sachsen",
    "wof:name":"Gartenfreunde",
    "wof:placetype":"venue"
},
  "geometry": {"coordinates":[13.9313001633,50.974193573],"type":"Point"}
}