{
  "type": "Feature",
  "properties": {
    "iso:country":"DE",
    "sg:address":"Ritterstr. 17",
    "sg:city":"Aachen",
    "sg:phone":"+49 241/889840",
    "sg:postcode":"52072",
    "sg:province":"Nordrhein-Westfalen",
    "wof:name":"Hubert Schleicher Gmbh",
    "wof:placetype":"venue"
},
  "geometry": {"coordinates":[6.065293,50.790077],"type":"Point"}
}