{
  "type": "Feature",
  "properties": {
    "iso:country":"DE",
    "sg:address":"Welseder Str. 24",
    "sg:city":"Hessisch Oldendorf",
    "sg:postcode":"31840",
    "sg:province":"Niedersachsen",
    "wof:name":"Klat Bautr\u00e4ger Gmbh",
    "wof:placetype":"venue"
},
  "geometry": {"coordinates":[9.237271,52.171795],"type":"Point"}
}