{
  "type": "Feature",
  "properties": {
    "iso:country":"DE",
    "sg:address":"Hauptstr. 11",
    "sg:city":"Schopp",
    "sg:postcode":"67707",
    "sg:province":"Rheinland-Pfalz",
    "wof:name":"Mehrzweckhalle Der Ortsgemeinde Schopp",
    "wof:placetype":"venue"
},
  "geometry": {"coordinates":[7.68823,49.35276],"type":"Point"}
}