{
  "type": "Feature",
  "properties": {
    "iso:country":"DE",
    "sg:address":"Buxtehuder Str. 112 a",
    "sg:city":"Hamburg",
    "sg:phone":"+49 40/7673020",
    "sg:postcode":"21073",
    "sg:province":"Hamburg",
    "wof:name":"Net Ag",
    "wof:placetype":"venue"
},
  "geometry": {"coordinates":[9.9636726379,53.4694633484],"type":"Point"}
}