{
  "type": "Feature",
  "properties": {
    "iso:country":"DE",
    "sg:address":"Max-Welcker-Weg 16",
    "sg:city":"Krumbach",
    "sg:phone":"+49 8282/7135",
    "sg:postcode":"86381",
    "sg:province":"Bayern",
    "wof:name":"Werner Lieb Rechtsanwalt",
    "wof:placetype":"venue"
},
  "geometry": {"coordinates":[10.3687553406,48.2471237183],"type":"Point"}
}