{
  "type": "Feature",
  "properties": {
    "iso:country":"DE",
    "sg:address":"Oranienburger Str. 84",
    "sg:city":"Berlin",
    "sg:phone":"+49 30/408100",
    "sg:postcode":"13437",
    "sg:province":"Berlin",
    "wof:name":"Ecclesia - Versicherungsdienst Gmbh",
    "wof:placetype":"venue"
},
  "geometry": {"coordinates":[13.3334093094,52.5948562622],"type":"Point"}
}