{
  "type": "Feature",
  "properties": {
    "iso:country":"DE",
    "sg:address":"Zehnthofstr 2",
    "sg:city":"Sinzig",
    "sg:phone":"+49 2642/990520",
    "sg:postcode":"53489",
    "sg:province":"Rheinland-Pfalz",
    "wof:name":"Muut Me\u00df- Und Umwelttechnik Gmbh",
    "wof:placetype":"venue"
},
  "geometry": {"coordinates":[7.253106,50.545261],"type":"Point"}
}