{
  "type": "Feature",
  "properties": {
    "iso:country":"DE",
    "sg:address":"Teutoburger Str. 8",
    "sg:city":"Verl",
    "sg:postcode":"33415",
    "sg:province":"Nordrhein-Westfalen",
    "wof:name":"Komtec W\u00e4getechnik",
    "wof:placetype":"venue"
},
  "geometry": {"coordinates":[8.5036506653,51.8787307739],"type":"Point"}
}