{
  "type": "Feature",
  "properties": {
    "iso:country":"DE",
    "sg:address":"Bissinger Str. 70",
    "sg:city":"Bietigheim-Bissingen",
    "sg:phone":"+49 7147/5556",
    "sg:postcode":"74321",
    "sg:province":"Baden-W\u00fcrttemberg",
    "wof:name":"Ristorante Burgblick Bei Franco",
    "wof:placetype":"venue"
},
  "geometry": {"coordinates":[9.0877752304,48.9473991394],"type":"Point"}
}