{
  "type": "Feature",
  "properties": {
    "iso:country":"DE",
    "sg:address":"Gr\u00fcner Weg 14",
    "sg:city":"Senzig",
    "sg:phone":"+49 3375/901701",
    "sg:postcode":"15754",
    "sg:province":"Brandenburg",
    "wof:name":"Hans-rudolf Schmohl",
    "wof:placetype":"venue"
},
  "geometry": {"coordinates":[13.67174,52.287823],"type":"Point"}
}