{
  "type": "Feature",
  "properties": {
    "iso:country":"DE",
    "sg:address":"Weinstr. 9",
    "sg:city":"Tettnang",
    "sg:phone":"+49 7542/55602",
    "sg:postcode":"88069",
    "sg:province":"Baden-W\u00fcrttemberg",
    "wof:name":"Zuchtberatungsstelle",
    "wof:placetype":"venue"
},
  "geometry": {"coordinates":[9.5854101181,47.6724205017],"type":"Point"}
}