{
  "type": "Feature",
  "properties": {
    "iso:country":"DE",
    "sg:address":"Sunderplatz 1",
    "sg:city":"M\u00fclheim",
    "sg:phone":"+49 208/492387",
    "sg:postcode":"45472",
    "sg:province":"Nordrhein-Westfalen",
    "wof:name":"Kolumbus-apotheke Martin Kuenen",
    "wof:placetype":"venue"
},
  "geometry": {"coordinates":[6.945731,51.428436],"type":"Point"}
}