{
  "type": "Feature",
  "properties": {
    "iso:country":"DE",
    "sg:address":"F\u00fcnf-B\u00e4ume-Weg",
    "sg:city":"Ulm",
    "sg:phone":"+49 731/385833",
    "sg:postcode":"89081",
    "sg:province":"Baden-W\u00fcrttemberg",
    "wof:name":"G. Schlenz Immobilienmakler",
    "wof:placetype":"venue"
},
  "geometry": {"coordinates":[9.942191124,48.3967208862],"type":"Point"}
}