{
  "type": "Feature",
  "properties": {
    "iso:country":"DE",
    "sg:address":"Br\u00fchlstr. 10",
    "sg:city":"Ellwangen",
    "sg:phone":"+49 7961/6447",
    "sg:postcode":"73479",
    "sg:province":"Baden-W\u00fcrttemberg",
    "wof:name":"Eugen Und Rosalie Harsch",
    "wof:placetype":"venue"
},
  "geometry": {"coordinates":[10.164814949,48.9721717834],"type":"Point"}
}