{
  "type": "Feature",
  "properties": {
    "iso:country":"DE",
    "sg:address":"Kulmbacher Str. 21",
    "sg:city":"Kronach",
    "sg:phone":"+49 9261/53565",
    "sg:postcode":"96317",
    "sg:province":"Bayern",
    "wof:name":"Walter Preuss",
    "wof:placetype":"venue"
},
  "geometry": {"coordinates":[11.3244009018,50.235206604],"type":"Point"}
}