{
  "type": "Feature",
  "properties": {
    "iso:country":"DE",
    "sg:address":"Donautalstr. 1-1",
    "sg:city":"Sigmaringen",
    "sg:phone":"+49 7571/4676",
    "sg:postcode":"72488",
    "sg:province":"Baden-W\u00fcrttemberg",
    "wof:name":"Helmut B\u00e4r",
    "wof:placetype":"venue"
},
  "geometry": {"coordinates":[9.19524,48.077686],"type":"Point"}
}