{
  "type": "Feature",
  "properties": {
    "iso:country":"DE",
    "sg:address":"Schwieberdinger Str. 5",
    "sg:city":"Stuttgart",
    "sg:postcode":"70435",
    "sg:province":"Baden-W\u00fcrttemberg",
    "wof:name":"Jenprojekt Gmbh",
    "wof:placetype":"venue"
},
  "geometry": {"coordinates":[9.168306,48.826054],"type":"Point"}
}