{
  "type": "Feature",
  "properties": {
    "iso:country":"DE",
    "sg:address":"Sperberweg 13",
    "sg:city":"Bad Segeberg",
    "sg:phone":"+49 4551/81067",
    "sg:postcode":"23795",
    "sg:province":"Schleswig-Holstein",
    "wof:name":"Hans Von Stockhausen Steuerberater",
    "wof:placetype":"venue"
},
  "geometry": {"coordinates":[10.2994365692,53.9553375244],"type":"Point"}
}