{
  "type": "Feature",
  "properties": {
    "iso:country":"DE",
    "sg:address":"Zweigstr. 4",
    "sg:city":"Heidesheim",
    "sg:phone":"+49 6132/58432",
    "sg:postcode":"55262",
    "sg:province":"Rheinland-Pfalz",
    "wof:name":"Ulli Becker",
    "wof:placetype":"venue"
},
  "geometry": {"coordinates":[8.112421,49.995346],"type":"Point"}
}