{
  "type": "Feature",
  "properties": {
    "iso:country":"DE",
    "sg:address":"Wilhelmstr. 18",
    "sg:city":"G\u00f6ppingen",
    "sg:phone":"+49 7161/67250",
    "sg:postcode":"73033",
    "sg:province":"Baden-W\u00fcrttemberg",
    "wof:name":"Fr. Schiettinger Kg",
    "wof:placetype":"venue"
},
  "geometry": {"coordinates":[9.6582546234,48.7030105591],"type":"Point"}
}