{
  "type": "Feature",
  "properties": {
    "iso:country":"DE",
    "sg:address":"Ursulastr. 10",
    "sg:city":"M\u00fcnchen",
    "sg:phone":"+49 89/342550",
    "sg:postcode":"80802",
    "sg:province":"Bayern",
    "wof:name":"Redaktion Rind Und Schlegel Friedrich Verlag",
    "wof:placetype":"venue"
},
  "geometry": {"coordinates":[11.5911188126,48.1618728638],"type":"Point"}
}