{
  "type": "Feature",
  "properties": {
    "iso:country":"DE",
    "sg:address":"Gartenstr. 2",
    "sg:city":"Bischweier",
    "sg:phone":"+49 7222/48767",
    "sg:postcode":"76476",
    "sg:province":"Baden-W\u00fcrttemberg",
    "wof:name":"Cafe Waldeck",
    "wof:placetype":"venue"
},
  "geometry": {"coordinates":[8.278592,48.835835],"type":"Point"}
}