{
  "type": "Feature",
  "properties": {
    "iso:country":"DE",
    "sg:address":"An der Wasserm\u00fchle 2",
    "sg:city":"Schneverdingen",
    "sg:phone":"+49 5193/6199",
    "sg:postcode":"29640",
    "sg:province":"Niedersachsen",
    "wof:name":"Bierhaus L\u00fcnzen",
    "wof:placetype":"venue"
},
  "geometry": {"coordinates":[9.6901741028,53.1111755371],"type":"Point"}
}