{
  "type": "Feature",
  "properties": {
    "iso:country":"DE",
    "sg:address":"K\u00fchlhausweg 7",
    "sg:city":"Vechelde",
    "sg:phone":"+49 5300/901030",
    "sg:postcode":"38159",
    "sg:province":"Niedersachsen",
    "wof:name":"Rost Und Sehle Architekten",
    "wof:placetype":"venue"
},
  "geometry": {"coordinates":[10.381383,52.215389],"type":"Point"}
}