{
  "type": "Feature",
  "properties": {
    "iso:country":"DE",
    "sg:address":"Geusaer Str. 9C",
    "sg:city":"Bl\u00f6sien",
    "sg:phone":"+49 3461/521797",
    "sg:postcode":"06217",
    "sg:province":"Sachsen-Anhalt",
    "wof:name":"Tierauffangstation F\u00fcr Herrenlose Und Fundtiere",
    "wof:placetype":"venue"
},
  "geometry": {"coordinates":[11.925129,51.331997],"type":"Point"}
}