{
  "type": "Feature",
  "properties": {
    "iso:country":"DE",
    "sg:address":"Obermarktstr. 9",
    "sg:city":"Braubach",
    "sg:phone":"+49 2627/547",
    "sg:postcode":"56338",
    "sg:province":"Rheinland-Pfalz",
    "wof:name":"H\u00fcpper Und Breitkopf",
    "wof:placetype":"venue"
},
  "geometry": {"coordinates":[7.64576,50.272388],"type":"Point"}
}