{
  "type": "Feature",
  "properties": {
    "iso:country":"DE",
    "sg:address":"Hasseltrift 6",
    "sg:city":"Wolfenb\u00fcttel",
    "sg:phone":"+49 5341/25397",
    "sg:postcode":"38304",
    "sg:province":"Niedersachsen",
    "wof:name":"Richard Eggert",
    "wof:placetype":"venue"
},
  "geometry": {"coordinates":[10.441153,52.136299],"type":"Point"}
}