{
  "type": "Feature",
  "properties": {
    "iso:country":"DE",
    "sg:address":"Am Brink 10",
    "sg:city":"Wennigsen",
    "sg:phone":"+49 5109/6618",
    "sg:postcode":"30974",
    "sg:province":"Niedersachsen",
    "wof:name":"Wolfgang Schr\u00f6der",
    "wof:placetype":"venue"
},
  "geometry": {"coordinates":[9.616382,52.256142],"type":"Point"}
}