{
  "type": "Feature",
  "properties": {
    "iso:country":"DE",
    "sg:address":"Im Rurwinkel 3",
    "sg:city":"J\u00fclich",
    "sg:postcode":"52428",
    "sg:province":"Nordrhein-Westfalen",
    "wof:name":"Bortolussi Naturstein Gmbh",
    "wof:placetype":"venue"
},
  "geometry": {"coordinates":[6.3546218872,50.9152641296],"type":"Point"}
}