{
  "type": "Feature",
  "properties": {
    "iso:country":"DE",
    "sg:address":"Frankfurter Str. 39",
    "sg:city":"Homberg",
    "sg:phone":"+49 6633/251",
    "sg:postcode":"35315",
    "sg:province":"Hessen",
    "wof:name":"Geibel",
    "wof:placetype":"venue"
},
  "geometry": {"coordinates":[8.9973773956,50.7280502319],"type":"Point"}
}