{
  "type": "Feature",
  "properties": {
    "iso:country":"DE",
    "sg:address":"G\u00fcterstr 10",
    "sg:city":"Pforzheim",
    "sg:phone":"+49 7231/104674",
    "sg:postcode":"75177",
    "sg:province":"Baden-W\u00fcrttemberg",
    "wof:name":"F\u00fcrstenberg Design",
    "wof:placetype":"venue"
},
  "geometry": {"coordinates":[8.7089939117,48.8953933716],"type":"Point"}
}