{
  "type": "Feature",
  "properties": {
    "iso:country":"DE",
    "sg:address":"Pontinusweg 10",
    "sg:city":"K\u00f6ln",
    "sg:phone":"+49 2234/48605",
    "sg:postcode":"50859",
    "sg:province":"Nordrhein-Westfalen",
    "wof:name":"K. M\u00f6llering",
    "wof:placetype":"venue"
},
  "geometry": {"coordinates":[6.8239579201,50.9493789673],"type":"Point"}
}