{
  "type": "Feature",
  "properties": {
    "iso:country":"DE",
    "sg:address":"Obere Bahnhofstr. 11",
    "sg:city":"Germering",
    "sg:phone":"+49 89/845130",
    "sg:postcode":"82110",
    "sg:province":"Bayern",
    "wof:name":"Friedrich Kiehbacher",
    "wof:placetype":"venue"
},
  "geometry": {"coordinates":[11.356599,48.133842],"type":"Point"}
}