{
  "type": "Feature",
  "properties": {
    "iso:country":"DE",
    "sg:address":"Hauptstr.",
    "sg:city":"M\u00fchlhausen",
    "sg:phone":"+49 36014/42133",
    "sg:postcode":"99974",
    "sg:province":"Th\u00fcringen",
    "wof:name":"A. Raub",
    "wof:placetype":"venue"
},
  "geometry": {"coordinates":[10.5293445587,51.2638168335],"type":"Point"}
}