{
  "type": "Feature",
  "properties": {
    "iso:country":"DE",
    "sg:address":"Bahnhofstr. 50",
    "sg:city":"Obertshausen",
    "sg:postcode":"63179",
    "sg:province":"Hessen",
    "wof:name":"Nkd Vertriebsges. Mbh",
    "wof:placetype":"venue"
},
  "geometry": {"coordinates":[8.850681,50.072739],"type":"Point"}
}