{
  "type": "Feature",
  "properties": {
    "iso:country":"DE",
    "sg:address":"Kr\u00fcdersheide 13",
    "sg:city":"Solingen",
    "sg:phone":"+49 212/75680",
    "sg:postcode":"42697",
    "sg:province":"Nordrhein-Westfalen",
    "wof:name":"Andreas Kaufmann",
    "wof:placetype":"venue"
},
  "geometry": {"coordinates":[6.979943,51.149719],"type":"Point"}
}