{
  "type": "Feature",
  "properties": {
    "iso:country":"DE",
    "sg:address":"Freihofstr. 21",
    "sg:city":"Stuttgart",
    "sg:phone":"+49 711/803888",
    "sg:postcode":"70439",
    "sg:province":"Baden-W\u00fcrttemberg",
    "wof:name":"Balneo-design Gmbh Individuelle Badezimmer-",
    "wof:placetype":"venue"
},
  "geometry": {"coordinates":[9.156355,48.847523],"type":"Point"}
}