{
  "type": "Feature",
  "properties": {
    "iso:country":"DE",
    "sg:address":"Sch\u00f6nbacher Str. 32",
    "sg:city":"Bubenreuth",
    "sg:phone":"+49 9131/23681",
    "sg:postcode":"91088",
    "sg:province":"Bayern",
    "wof:name":"I. Lenhardt Heissmangel",
    "wof:placetype":"venue"
},
  "geometry": {"coordinates":[11.0057010651,49.6197624207],"type":"Point"}
}