{
  "type": "Feature",
  "properties": {
    "iso:country":"DE",
    "sg:address":"Gustav-Maier-Str 7",
    "sg:city":"Schramberg",
    "sg:phone":"+49 7422/96266",
    "sg:postcode":"78713",
    "sg:province":"Baden-W\u00fcrttemberg",
    "wof:name":"H\u00e4berle Laser- Und Feinwerktechnik",
    "wof:placetype":"venue"
},
  "geometry": {"coordinates":[8.417285,48.240875],"type":"Point"}
}