{
  "type": "Feature",
  "properties": {
    "iso:country":"DE",
    "sg:address":"Heerstr. 155",
    "sg:city":"Frankfurt",
    "sg:phone":"+49 69/764584",
    "sg:postcode":"60488",
    "sg:province":"Hessen",
    "wof:name":"China-restaurant Haus Chui",
    "wof:placetype":"venue"
},
  "geometry": {"coordinates":[8.6112747192,50.1462860107],"type":"Point"}
}