{
  "type": "Feature",
  "properties": {
    "iso:country":"DE",
    "sg:address":"Dachelhofer Str. 67 a",
    "sg:city":"Schwandorf",
    "sg:phone":"+49 9431/3104",
    "sg:postcode":"92421",
    "sg:province":"Bayern",
    "wof:name":"Xaver Engl Masseur",
    "wof:placetype":"venue"
},
  "geometry": {"coordinates":[12.092892,49.322155],"type":"Point"}
}