{
  "type": "Feature",
  "properties": {
    "iso:country":"DE",
    "sg:address":"Bismarckstr. 16",
    "sg:city":"Wertheim",
    "sg:phone":"+49 9342/92770",
    "sg:postcode":"97877",
    "sg:province":"Baden-W\u00fcrttemberg",
    "wof:name":"Raiffeisen-lagerhaus Eg",
    "wof:placetype":"venue"
},
  "geometry": {"coordinates":[9.510641098,49.7617111206],"type":"Point"}
}