{
  "type": "Feature",
  "properties": {
    "iso:country":"DE",
    "sg:address":"54552",
    "sg:city":"Beinhausen",
    "sg:phone":"+49 6527/235",
    "sg:postcode":"54552",
    "sg:province":"Rheinland-Pfalz",
    "wof:name":"Katholisches Pfarramt St. Hubertus",
    "wof:placetype":"venue"
},
  "geometry": {"coordinates":[6.8837227821,50.2660255432],"type":"Point"}
}