{
  "type": "Feature",
  "properties": {
    "iso:country":"DE",
    "sg:address":"L\u00e4rchenweg 5",
    "sg:city":"Dinkelscherben",
    "sg:phone":"+49 8292/803",
    "sg:postcode":"86424",
    "sg:province":"Bayern",
    "wof:name":"Dr. Med. J\u00f6rg Bartusch",
    "wof:placetype":"venue"
},
  "geometry": {"coordinates":[10.5868034363,48.3457069397],"type":"Point"}
}