{
  "type": "Feature",
  "properties": {
    "iso:country":"DE",
    "sg:address":"Schlo\u00dfstr. 6",
    "sg:city":"Heilbronn",
    "sg:phone":"+49 7066/901363",
    "sg:postcode":"74078",
    "sg:province":"Baden-W\u00fcrttemberg",
    "wof:name":"H. Gottert Anlageberater",
    "wof:placetype":"venue"
},
  "geometry": {"coordinates":[9.1141233444,49.1819076538],"type":"Point"}
}