{
  "type": "Feature",
  "properties": {
    "iso:country":"DE",
    "sg:address":"Hasselstr. 11",
    "sg:city":"Solingen",
    "sg:phone":"+49 212/51353",
    "sg:postcode":"42651",
    "sg:province":"Nordrhein-Westfalen",
    "wof:name":"Gustav Wichelhaus",
    "wof:placetype":"venue"
},
  "geometry": {"coordinates":[7.0948557854,51.1833457947],"type":"Point"}
}