{
  "type": "Feature",
  "properties": {
    "iso:country":"DE",
    "sg:city":"Kochel am See",
    "sg:phone":"+49 8851/878",
    "sg:postcode":"82431",
    "sg:province":"Bayern",
    "wof:name":"Hypo-bank Ag",
    "wof:placetype":"venue"
},
  "geometry": {"coordinates":[11.36807,47.658932],"type":"Point"}
}