{
  "type": "Feature",
  "properties": {
    "iso:country":"DE",
    "sg:address":"Dieselstr. 10",
    "sg:city":"Achern",
    "sg:postcode":"77855",
    "sg:province":"Baden-W\u00fcrttemberg",
    "wof:name":"H. Gerber Mittelbad",
    "wof:placetype":"venue"
},
  "geometry": {"coordinates":[8.06364,48.628712],"type":"Point"}
}