{
  "type": "Feature",
  "properties": {
    "iso:country":"DE",
    "sg:address":"Cicerostr. 26",
    "sg:city":"Berlin",
    "sg:phone":"+49 30/2934120",
    "sg:postcode":"10709",
    "sg:province":"Berlin",
    "wof:name":"Projekt Service Schwanke & Heilmann Gmbh",
    "wof:placetype":"venue"
},
  "geometry": {"coordinates":[13.300881,52.491299],"type":"Point"}
}