{
  "type": "Feature",
  "properties": {
    "iso:country":"DE",
    "sg:address":"K\u00f6nigsberger Str. 33",
    "sg:city":"Rottenburg",
    "sg:phone":"+49 7457/1622",
    "sg:postcode":"72108",
    "sg:province":"Baden-W\u00fcrttemberg",
    "wof:name":"R. Schiller Anlageberater",
    "wof:placetype":"venue"
},
  "geometry": {"coordinates":[8.8059587479,48.4922447205],"type":"Point"}
}