{
  "type": "Feature",
  "properties": {
    "iso:country":"DE",
    "sg:address":"Burgstr. 26a",
    "sg:city":"Ruppichteroth",
    "sg:phone":"+49 2295/6292",
    "sg:postcode":"53809",
    "sg:province":"Nordrhein-Westfalen",
    "wof:name":"Marie Luise Harth Fliesenhandel Gmbh",
    "wof:placetype":"venue"
},
  "geometry": {"coordinates":[7.481304,50.844402],"type":"Point"}
}