{
  "type": "Feature",
  "properties": {
    "iso:country":"DE",
    "sg:address":"Waldstr. 103",
    "sg:city":"Berlin",
    "sg:phone":"+49 30/41783145",
    "sg:postcode":"13403",
    "sg:province":"Berlin",
    "wof:name":"Gast\u00e4tte Felix",
    "wof:placetype":"venue"
},
  "geometry": {"coordinates":[13.3304271698,52.5753440857],"type":"Point"}
}