{
  "type": "Feature",
  "properties": {
    "iso:country":"DE",
    "sg:address":"Rehmkestr. 16",
    "sg:city":"Elmshorn",
    "sg:phone":"+49 4121/92559",
    "sg:postcode":"25336",
    "sg:province":"Schleswig-Holstein",
    "wof:name":"Atl Begr\u00fcnungsges. Mbh",
    "wof:placetype":"venue"
},
  "geometry": {"coordinates":[9.645648,53.741093],"type":"Point"}
}