{
  "type": "Feature",
  "properties": {
    "iso:country":"DE",
    "sg:address":"Sauerampferweg 11A",
    "sg:city":"Laatzen",
    "sg:postcode":"30880",
    "sg:province":"Niedersachsen",
    "wof:name":"Waat Warenhandelsges. Mbh",
    "wof:placetype":"venue"
},
  "geometry": {"coordinates":[9.8485040665,52.2692832947],"type":"Point"}
}