{
  "type": "Feature",
  "properties": {
    "iso:country":"DE",
    "sg:address":"Kajen 10",
    "sg:city":"Hamburg",
    "sg:phone":"+49 40/361580",
    "sg:postcode":"20459",
    "sg:province":"Hamburg",
    "wof:name":"Opdr - One Of The Leading European Short-sea Carriers",
    "wof:placetype":"venue"
},
  "geometry": {"coordinates":[9.9851102829,53.5454444885],"type":"Point"}
}