{
  "type": "Feature",
  "properties": {
    "iso:country":"DE",
    "sg:address":"Prinzregentenstr. 7",
    "sg:city":"Berlin",
    "sg:phone":"+49 30/21475190",
    "sg:postcode":"10717",
    "sg:province":"Berlin",
    "wof:name":"Teleservice R & S Gmbh",
    "wof:placetype":"venue"
},
  "geometry": {"coordinates":[13.332821846,52.491317749],"type":"Point"}
}