{
  "type": "Feature",
  "properties": {
    "iso:country":"DE",
    "sg:address":"Zeppelinstr. 36",
    "sg:city":"Markgr\u00f6ningen",
    "sg:phone":"+49 7145/96050",
    "sg:postcode":"71706",
    "sg:province":"Baden-W\u00fcrttemberg",
    "wof:name":"Muk Logistik Gmbh",
    "wof:placetype":"venue"
},
  "geometry": {"coordinates":[9.098728,48.901146],"type":"Point"}
}