{
  "type": "Feature",
  "properties": {
    "iso:country":"DE",
    "sg:address":"Am Galgenfeld 2",
    "sg:city":"Gelnhausen",
    "sg:phone":"+49 6051/82360",
    "sg:postcode":"63571",
    "sg:province":"Hessen",
    "wof:name":"Hubert Schacht Gmbh",
    "wof:placetype":"venue"
},
  "geometry": {"coordinates":[9.173409462,50.2025108337],"type":"Point"}
}