{
  "type": "Feature",
  "properties": {
    "iso:country":"DE",
    "sg:address":"Vogelsdorfer Str. 17",
    "sg:city":"Woltersdorf",
    "sg:postcode":"15569",
    "sg:province":"Brandenburg",
    "wof:name":"Frank Kunkel",
    "wof:placetype":"venue"
},
  "geometry": {"coordinates":[13.751704,52.456203],"type":"Point"}
}