{
  "type": "Feature",
  "properties": {
    "iso:country":"DE",
    "sg:address":"Johannesbrunnen 5",
    "sg:city":"Halbertstadt",
    "sg:phone":"+49 3941",
    "sg:postcode":"38820",
    "sg:province":"Sachsen-Anhalt",
    "wof:name":"Emo-oppermann, Einbauk\u00fcchen, Montagen Und Mehr",
    "wof:placetype":"venue"
},
  "geometry": {"coordinates":[-89.032021,34.176239],"type":"Point"}
}