{
  "type": "Feature",
  "properties": {
    "iso:country":"DE",
    "sg:address":"Bellstieg 4",
    "sg:city":"M\u00f6nchengladbach",
    "sg:phone":"+49 2161/14235",
    "sg:postcode":"41061",
    "sg:province":"Nordrhein-Westfalen",
    "wof:name":"Adolf Koch",
    "wof:placetype":"venue"
},
  "geometry": {"coordinates":[6.446445,51.199104],"type":"Point"}
}