{
  "type": "Feature",
  "properties": {
    "iso:country":"DE",
    "sg:address":"Im Kirchh\u00f6fer Grund 45",
    "sg:city":"Melsungen",
    "sg:phone":"+49 5661/50998",
    "sg:postcode":"34212",
    "sg:province":"Hessen",
    "wof:name":"Kurt Albus",
    "wof:placetype":"venue"
},
  "geometry": {"coordinates":[9.596678,51.14315],"type":"Point"}
}