{
  "type": "Feature",
  "properties": {
    "iso:country":"DE",
    "sg:address":"G\u00e4rtnerstr. 17a",
    "sg:city":"Bad Schmiedeberg",
    "sg:phone":"+49 34925/70476",
    "sg:postcode":"06905",
    "sg:province":"Sachsen-Anhalt",
    "wof:name":"Hans-dieter Mausolf",
    "wof:placetype":"venue"
},
  "geometry": {"coordinates":[12.734203,51.688046],"type":"Point"}
}