{
  "type": "Feature",
  "properties": {
    "iso:country":"DE",
    "sg:address":"Neuweststr. 10",
    "sg:city":"Uehlfeld",
    "sg:phone":"+49 9163/245",
    "sg:postcode":"91486",
    "sg:province":"Bayern",
    "wof:name":"G\u00fcnter M\u00f6hring Gmbh",
    "wof:placetype":"venue"
},
  "geometry": {"coordinates":[10.718003273,49.6706581116],"type":"Point"}
}