{
  "type": "Feature",
  "properties": {
    "iso:country":"DE",
    "sg:address":"Albert-Mayer-Str. 16",
    "sg:city":"Bruckm\u00fchl",
    "sg:phone":"+49 89/6144190",
    "sg:postcode":"83052",
    "sg:province":"Bayern",
    "wof:name":"Pro Design Electronic Und Cad-layout Gmbh",
    "wof:placetype":"venue"
},
  "geometry": {"coordinates":[11.9303045273,47.8819770813],"type":"Point"}
}