{
  "type": "Feature",
  "properties": {
    "iso:country":"DE",
    "sg:address":"Im Kanaleck 8",
    "sg:city":"Seelze",
    "sg:phone":"+49 5137/823900",
    "sg:postcode":"30926",
    "sg:province":"Niedersachsen",
    "wof:name":"Kenngott International Gmbh & Co. Kg",
    "wof:placetype":"venue"
},
  "geometry": {"coordinates":[9.5619688034,52.3969802856],"type":"Point"}
}