{
  "type": "Feature",
  "properties": {
    "iso:country":"DE",
    "sg:address":"Fischbrunnenplatz 5",
    "sg:city":"Eggenfelden",
    "sg:phone":"+49 8721/2012",
    "sg:postcode":"84307",
    "sg:province":"Bayern",
    "wof:name":"Sanit\u00e4tshaus G\u00f6ldner Gmbh",
    "wof:placetype":"venue"
},
  "geometry": {"coordinates":[12.7610359192,48.4037017822],"type":"Point"}
}