{
  "type": "Feature",
  "properties": {
    "iso:country":"DE",
    "sg:address":"Krefelder Str. 20",
    "sg:city":"Z\u00fclpich",
    "sg:phone":"+49 2252/6103",
    "sg:postcode":"53909",
    "sg:province":"Nordrhein-Westfalen",
    "wof:name":"Ilse Schumacher Masseurin",
    "wof:placetype":"venue"
},
  "geometry": {"coordinates":[6.661266,50.698429],"type":"Point"}
}