{
  "type": "Feature",
  "properties": {
    "iso:country":"DE",
    "sg:address":"Hauptstr. 72",
    "sg:city":"Kirchardt",
    "sg:phone":"+49 7266/1418",
    "sg:postcode":"74912",
    "sg:province":"Baden-W\u00fcrttemberg",
    "wof:name":"W. Retzbach Drogerie",
    "wof:placetype":"venue"
},
  "geometry": {"coordinates":[8.989375,49.203899],"type":"Point"}
}