{
  "type": "Feature",
  "properties": {
    "iso:country":"DE",
    "sg:address":"Hochschulstr. 2",
    "sg:city":"Darmstadt",
    "sg:phone":"+49 6151/163975",
    "sg:postcode":"64289",
    "sg:province":"Hessen",
    "wof:name":"Lehrstuhl I Und Institut F. Theoretische Physik",
    "wof:placetype":"venue"
},
  "geometry": {"coordinates":[8.6564426422,49.8777008057],"type":"Point"}
}