{
  "type": "Feature",
  "properties": {
    "iso:country":"DE",
    "sg:address":"Hofstr. 8",
    "sg:city":"Br\u00fchl",
    "sg:phone":"+49 6202/71576",
    "sg:postcode":"68782",
    "sg:province":"Baden-W\u00fcrttemberg",
    "wof:name":"L. Sykora",
    "wof:placetype":"venue"
},
  "geometry": {"coordinates":[8.5194559097,49.4095230103],"type":"Point"}
}