{
  "type": "Feature",
  "properties": {
    "iso:country":"DE",
    "sg:address":"Emder Str. 21",
    "sg:city":"Aurich",
    "sg:postcode":"26603",
    "sg:province":"Niedersachsen",
    "wof:name":"Systemgastronomie Heinz Straeten Ohg",
    "wof:placetype":"venue"
},
  "geometry": {"coordinates":[7.4676299095,53.4711112976],"type":"Point"}
}