{
  "type": "Feature",
  "properties": {
    "iso:country":"DE",
    "sg:address":"Rochlitzer Str. 80",
    "sg:city":"Mittweida",
    "sg:phone":"+49 3727/2605",
    "sg:postcode":"09648",
    "sg:province":"Sachsen",
    "wof:name":"G. Blochberger",
    "wof:placetype":"venue"
},
  "geometry": {"coordinates":[12.974017,50.986309],"type":"Point"}
}