{
  "type": "Feature",
  "properties": {
    "iso:country":"DE",
    "sg:address":"Obere Str. 14",
    "sg:city":"Lage",
    "sg:phone":"+49 5232/65339",
    "sg:postcode":"32791",
    "sg:province":"Nordrhein-Westfalen",
    "wof:name":"D Und W Getr\u00e4nkevertr. Gmbh",
    "wof:placetype":"venue"
},
  "geometry": {"coordinates":[8.8010168076,51.9879951477],"type":"Point"}
}