{
  "type": "Feature",
  "properties": {
    "iso:country":"DE",
    "sg:address":"Lange Str. 104",
    "sg:city":"Lage",
    "sg:phone":"+49 5232/3399",
    "sg:postcode":"32791",
    "sg:province":"Nordrhein-Westfalen",
    "wof:name":"N. Caliskan",
    "wof:placetype":"venue"
},
  "geometry": {"coordinates":[8.7958192825,51.9892272949],"type":"Point"}
}