{
  "type": "Feature",
  "properties": {
    "iso:country":"DE",
    "sg:address":"Gro\u00dfe Bruchstr. 40a",
    "sg:city":"Viersen",
    "sg:phone":"+49 2162/34445",
    "sg:postcode":"41747",
    "sg:province":"Nordrhein-Westfalen",
    "wof:name":"Essen Auf R\u00e4dern",
    "wof:placetype":"venue"
},
  "geometry": {"coordinates":[6.396679,51.254688],"type":"Point"}
}