{
  "type": "Feature",
  "properties": {
    "iso:country":"DE",
    "sg:address":"Dr.-von-Fromm-Str. 14",
    "sg:city":"Weiden",
    "sg:phone":"+49 961/28088",
    "sg:postcode":"92637",
    "sg:province":"Bayern",
    "wof:name":"Wagert Gmbh",
    "wof:placetype":"venue"
},
  "geometry": {"coordinates":[12.0959749222,49.6891555786],"type":"Point"}
}