{
  "type": "Feature",
  "properties": {
    "iso:country":"DE",
    "sg:address":"Apelstr. 1",
    "sg:city":"Haynrode",
    "sg:phone":"+49 36077/20784",
    "sg:postcode":"37339",
    "sg:province":"Th\u00fcringen",
    "wof:name":"Gastst\u00e4tte 2 Tannen",
    "wof:placetype":"venue"
},
  "geometry": {"coordinates":[10.4427614212,51.4452667236],"type":"Point"}
}