{
  "type": "Feature",
  "properties": {
    "iso:country":"DE",
    "sg:address":"Eckener Weg 3",
    "sg:city":"Langenfeld",
    "sg:postcode":"40764",
    "sg:province":"Nordrhein-Westfalen",
    "wof:name":"Fitness Und Fun Im Pohlmann Club",
    "wof:placetype":"venue"
},
  "geometry": {"coordinates":[6.938195,51.111038],"type":"Point"}
}