{
  "type": "Feature",
  "properties": {
    "iso:country":"DE",
    "sg:address":"W\u00f6hrener Str. 134",
    "sg:city":"Bad Oeynhausen",
    "sg:phone":"+49 5731/51414",
    "sg:postcode":"32549",
    "sg:province":"Nordrhein-Westfalen",
    "wof:name":"Clean-service Van Helden Gmbh",
    "wof:placetype":"venue"
},
  "geometry": {"coordinates":[8.817659,52.240303],"type":"Point"}
}