{
  "type": "Feature",
  "properties": {
    "iso:country":"DE",
    "sg:address":"Schwemeckerweg 54",
    "sg:city":"Soest",
    "sg:phone":"+49 2921/60808",
    "sg:postcode":"59494",
    "sg:province":"Nordrhein-Westfalen",
    "wof:name":"Georg Weber",
    "wof:placetype":"venue"
},
  "geometry": {"coordinates":[8.088657,51.577538],"type":"Point"}
}