{
  "type": "Feature",
  "properties": {
    "iso:country":"DE",
    "sg:address":"Br\u00fcderstr. 3",
    "sg:city":"Hannover",
    "sg:phone":"+49 511/15665",
    "sg:postcode":"30159",
    "sg:province":"Niedersachsen",
    "wof:name":"Bierpub Angies",
    "wof:placetype":"venue"
},
  "geometry": {"coordinates":[9.7333898544,52.3783378601],"type":"Point"}
}