{
  "type": "Feature",
  "properties": {
    "iso:country":"DE",
    "sg:address":"Spiegelh\u00fctte 16",
    "sg:city":"Lindberg",
    "sg:phone":"+49 9922/3053",
    "sg:postcode":"94227",
    "sg:province":"Bayern",
    "wof:name":"Pension Werner Stra\u00dfner",
    "wof:placetype":"venue"
},
  "geometry": {"coordinates":[13.3065004349,49.051990509],"type":"Point"}
}