{
  "type": "Feature",
  "properties": {
    "iso:country":"DE",
    "sg:address":"Heidenoldendorfer Str. 1",
    "sg:city":"Detmold",
    "sg:phone":"+49 5231/66755",
    "sg:postcode":"32758",
    "sg:province":"Nordrhein-Westfalen",
    "wof:name":"Autovermietung Meyer Gmbh",
    "wof:placetype":"venue"
},
  "geometry": {"coordinates":[8.861625,51.942169],"type":"Point"}
}