{
  "type": "Feature",
  "properties": {
    "iso:country":"DE",
    "sg:address":"Bahnhofstr. 3",
    "sg:city":"Steyerberg",
    "sg:phone":"+49 5764/2157",
    "sg:postcode":"31595",
    "sg:province":"Niedersachsen",
    "wof:name":"Helmut Elberding Masseur",
    "wof:placetype":"venue"
},
  "geometry": {"coordinates":[9.026473,52.566933],"type":"Point"}
}