{
  "type": "Feature",
  "properties": {
    "iso:country":"DE",
    "sg:address":"Am Stuckertsgraben 5",
    "sg:city":"Gro\u00df-Umstadt",
    "sg:phone":"+49 6078/74573",
    "sg:postcode":"64823",
    "sg:province":"Hessen",
    "wof:name":"G. H\u00fcttig",
    "wof:placetype":"venue"
},
  "geometry": {"coordinates":[8.9575195312,49.8879890442],"type":"Point"}
}