{
  "type": "Feature",
  "properties": {
    "iso:country":"DE",
    "sg:address":"Schachtstr. 28",
    "sg:city":"Sondershausen",
    "sg:phone":"+49 4936/3265160",
    "sg:postcode":"99706",
    "sg:province":"Th\u00fcringen",
    "wof:name":"Isoplus Fernw\u00c4rmetechnik Gmbh",
    "wof:placetype":"venue"
},
  "geometry": {"coordinates":[10.833438,51.391193],"type":"Point"}
}