{
  "type": "Feature",
  "properties": {
    "iso:country":"DE",
    "sg:address":"Hiberniastr. 11",
    "sg:city":"Herne",
    "sg:phone":"+49 2323/44140",
    "sg:postcode":"44623",
    "sg:province":"Nordrhein-Westfalen",
    "wof:name":"Dr. Michael Meyer",
    "wof:placetype":"venue"
},
  "geometry": {"coordinates":[7.2160801888,51.5334510803],"type":"Point"}
}