{
  "type": "Feature",
  "properties": {
    "iso:country":"DE",
    "sg:address":"Alsfeldstr. 22",
    "sg:city":"Oberhausen",
    "sg:phone":"+49 208/640360",
    "sg:postcode":"46149",
    "sg:province":"Nordrhein-Westfalen",
    "wof:name":"Heinrich Roder Architekt",
    "wof:placetype":"venue"
},
  "geometry": {"coordinates":[6.841312,51.528103],"type":"Point"}
}