{
  "type": "Feature",
  "properties": {
    "iso:country":"DE",
    "sg:address":"Hohenthanner Str 4",
    "sg:city":"Tuntenhausen",
    "sg:phone":"+49 8065/1394",
    "sg:postcode":"83104",
    "sg:province":"Bayern",
    "wof:name":"Niedermeier & Spyra Stahlbau Gmbh",
    "wof:placetype":"venue"
},
  "geometry": {"coordinates":[11.9693088531,47.9543113708],"type":"Point"}
}