{
  "type": "Feature",
  "properties": {
    "iso:country":"DE",
    "sg:address":"Hubertusstr 7",
    "sg:city":"Ehringshausen",
    "sg:phone":"+49 6449/921035",
    "sg:postcode":"35630",
    "sg:province":"Hessen",
    "wof:name":"F. Sch\u00e4fer Ohg",
    "wof:placetype":"venue"
},
  "geometry": {"coordinates":[8.34275,50.624115],"type":"Point"}
}