{
  "type": "Feature",
  "properties": {
    "iso:country":"DE",
    "sg:address":"Dr.-Carl-Goerdeler-Str. 6",
    "sg:city":"M\u00f6nchengladbach",
    "sg:phone":"+49 2166/59171",
    "sg:postcode":"41189",
    "sg:province":"Nordrhein-Westfalen",
    "wof:name":"Dea Tankstelle",
    "wof:placetype":"venue"
},
  "geometry": {"coordinates":[6.4101099968,51.1310844421],"type":"Point"}
}