{
  "type": "Feature",
  "properties": {
    "iso:country":"DE",
    "sg:address":"Bahnhofstr. 44",
    "sg:city":"Siegburg",
    "sg:phone":"+49 2241/66279",
    "sg:postcode":"53721",
    "sg:province":"Nordrhein-Westfalen",
    "wof:name":"M. Zwaka Gmbh",
    "wof:placetype":"venue"
},
  "geometry": {"coordinates":[7.2024211884,50.7956047058],"type":"Point"}
}