{
  "type": "Feature",
  "properties": {
    "iso:country":"DE",
    "sg:address":"Oberdischinger Str. 5",
    "sg:city":"Erbach",
    "sg:phone":"+49 7344/7373",
    "sg:postcode":"89155",
    "sg:province":"Baden-W\u00fcrttemberg",
    "wof:name":"Franz Braunsteffer",
    "wof:placetype":"venue"
},
  "geometry": {"coordinates":[9.814016,48.343098],"type":"Point"}
}