{
  "type": "Feature",
  "properties": {
    "iso:country":"DE",
    "sg:address":"Schnerkinger Str. 22",
    "sg:city":"Me\u00dfkirch",
    "sg:postcode":"88605",
    "sg:province":"Baden-W\u00fcrttemberg",
    "wof:name":"Torri Deutschland Gmbh",
    "wof:placetype":"venue"
},
  "geometry": {"coordinates":[9.113882,47.989937],"type":"Point"}
}