{
  "type": "Feature",
  "properties": {
    "iso:country":"DE",
    "sg:address":"Deverweg 39",
    "sg:city":"Papenburg",
    "sg:phone":"+49 4961/91940",
    "sg:postcode":"26871",
    "sg:province":"Niedersachsen",
    "wof:name":"Ruma Einkaufs- Und Verwaltungs Beteiligungs Gmbh",
    "wof:placetype":"venue"
},
  "geometry": {"coordinates":[7.382999897,53.0843315125],"type":"Point"}
}