{
  "type": "Feature",
  "properties": {
    "iso:country":"DE",
    "sg:address":"Weimarer Str. 36",
    "sg:city":"Naumburg",
    "sg:phone":"+49 3445/71240",
    "sg:postcode":"06618",
    "sg:province":"Sachsen-Anhalt",
    "wof:name":"Melzer & Esser Gmbh",
    "wof:placetype":"venue"
},
  "geometry": {"coordinates":[11.8009233475,51.150428772],"type":"Point"}
}