{
  "type": "Feature",
  "properties": {
    "iso:country":"DE",
    "sg:address":"Julius-Bamberger-Str. 6",
    "sg:city":"Bremen",
    "sg:phone":"+49 4942/1836060",
    "sg:postcode":"28279",
    "sg:province":"Bremen",
    "wof:name":"Kawasaki Motorradladen Lehne; Vertragsh\u00e4ndler In Bremen",
    "wof:placetype":"venue"
},
  "geometry": {"coordinates":[8.8353347778,53.0495872498],"type":"Point"}
}