{
  "type": "Feature",
  "properties": {
    "iso:country":"DE",
    "sg:address":"Riedstr. 16",
    "sg:city":"Stadtbergen",
    "sg:phone":"+49 821/524169",
    "sg:postcode":"86391",
    "sg:province":"Bayern",
    "wof:name":"Katholisches Pfarramt St. Oswald",
    "wof:placetype":"venue"
},
  "geometry": {"coordinates":[10.8433675766,48.3482055664],"type":"Point"}
}