{
  "type": "Feature",
  "properties": {
    "iso:country":"DE",
    "sg:address":"\u00dcckendorfer Str. 222",
    "sg:city":"Gelsenkirchen",
    "sg:phone":"+49 209/205822",
    "sg:postcode":"45886",
    "sg:province":"Nordrhein-Westfalen",
    "wof:name":"Gregor Pelka",
    "wof:placetype":"venue"
},
  "geometry": {"coordinates":[7.123002,51.491444],"type":"Point"}
}