{
  "type": "Feature",
  "properties": {
    "iso:country":"DE",
    "sg:address":"Tegeler Str. 1",
    "sg:city":"Lauterbach",
    "sg:phone":"+49 6641/3078",
    "sg:postcode":"36341",
    "sg:province":"Hessen",
    "wof:name":"Hausmann Agrarhandel Kg",
    "wof:placetype":"venue"
},
  "geometry": {"coordinates":[9.397138,50.622101],"type":"Point"}
}