{
  "type": "Feature",
  "properties": {
    "iso:country":"DE",
    "sg:address":"An den Wiesen 39",
    "sg:city":"Apen",
    "sg:phone":"+49 4489/2144",
    "sg:postcode":"26689",
    "sg:province":"Niedersachsen",
    "wof:name":"W. Br\u00fcckmann",
    "wof:placetype":"venue"
},
  "geometry": {"coordinates":[7.773616,53.230972],"type":"Point"}
}