{
  "type": "Feature",
  "properties": {
    "iso:country":"DE",
    "sg:address":"Franz-Best-Weg 25",
    "sg:city":"Darmstadt",
    "sg:phone":"+49 6151/591839",
    "sg:postcode":"64297",
    "sg:province":"Hessen",
    "wof:name":"Hartmut Delp Architekt",
    "wof:placetype":"venue"
},
  "geometry": {"coordinates":[8.653542,49.80854],"type":"Point"}
}