{
  "type": "Feature",
  "properties": {
    "iso:country":"DE",
    "sg:address":"Nymphenburger Str. 79",
    "sg:city":"M\u00fcnchen",
    "sg:phone":"+49 89/181858",
    "sg:postcode":"80636",
    "sg:province":"Bayern",
    "wof:name":"Video Connection",
    "wof:placetype":"venue"
},
  "geometry": {"coordinates":[11.5449857712,48.1500244141],"type":"Point"}
}