{
  "type": "Feature",
  "properties": {
    "iso:country":"DE",
    "sg:address":"Frauenrichter Str. 160d",
    "sg:city":"Weiden",
    "sg:phone":"+49 961/23992",
    "sg:postcode":"92637",
    "sg:province":"Bayern",
    "wof:name":"Gvs Gro\u00dfverbraucher-service",
    "wof:placetype":"venue"
},
  "geometry": {"coordinates":[12.1367473602,49.6723442078],"type":"Point"}
}