{
  "type": "Feature",
  "properties": {
    "iso:country":"DE",
    "sg:address":"Isestr. 93",
    "sg:city":"Hamburg",
    "sg:postcode":"20149",
    "sg:province":"Hamburg",
    "wof:name":"Carela Verm\u00f6gens- Verwaltungs Gmbh",
    "wof:placetype":"venue"
},
  "geometry": {"coordinates":[9.987489,53.584099],"type":"Point"}
}