{
  "type": "Feature",
  "properties": {
    "iso:country":"DE",
    "sg:address":"Stettiner Str. 10",
    "sg:city":"Berlin",
    "sg:phone":"+49 30/4934368",
    "sg:postcode":"13357",
    "sg:province":"Berlin",
    "wof:name":"Mario Und Hans Liberra",
    "wof:placetype":"venue"
},
  "geometry": {"coordinates":[13.385644,52.552666],"type":"Point"}
}