{
  "type": "Feature",
  "properties": {
    "iso:country":"DE",
    "sg:address":"Oberer Landweg 112a",
    "sg:city":"Hamburg",
    "sg:phone":"+49 40/7355577",
    "sg:postcode":"21035",
    "sg:province":"Hamburg",
    "wof:name":"U. Paul",
    "wof:placetype":"venue"
},
  "geometry": {"coordinates":[10.183225,53.48185],"type":"Point"}
}