{
  "type": "Feature",
  "properties": {
    "iso:country":"DE",
    "sg:address":"Mauritiussteinweg 84",
    "sg:city":"K\u00f6ln",
    "sg:phone":"+49 221/236843",
    "sg:postcode":"50676",
    "sg:province":"Nordrhein-Westfalen",
    "wof:name":"Coellnteam St\u00fcber & Schubert Ohg",
    "wof:placetype":"venue"
},
  "geometry": {"coordinates":[6.9452271461,50.9338798523],"type":"Point"}
}