{
  "type": "Feature",
  "properties": {
    "iso:country":"DE",
    "sg:address":"Robert-Bosch-Str. 13",
    "sg:city":"Mainz",
    "sg:phone":"+49 6131/509441",
    "sg:postcode":"55129",
    "sg:province":"Rheinland-Pfalz",
    "wof:name":"G\u00fcnters Schlemmerstube",
    "wof:placetype":"venue"
},
  "geometry": {"coordinates":[8.2606840134,49.9589653015],"type":"Point"}
}