{
  "type": "Feature",
  "properties": {
    "iso:country":"DE",
    "sg:address":"Bahnhofstr 3",
    "sg:city":"Ramstein-Miesenbach",
    "sg:phone":"+49 6371/953145",
    "sg:postcode":"66877",
    "sg:province":"Rheinland-Pfalz",
    "wof:name":"R\u00f6hricht Multimediapoint Druck & Design Gmbh",
    "wof:placetype":"venue"
},
  "geometry": {"coordinates":[7.556317,49.448463],"type":"Point"}
}