{
  "type": "Feature",
  "properties": {
    "iso:country":"DE",
    "sg:address":"Hauptstra\u00dfe 11",
    "sg:city":"Weitersburg",
    "sg:phone":"+49 2622",
    "sg:postcode":"56191",
    "sg:province":"Rheinland-Pfalz",
    "wof:name":"Redpoint Gmbh",
    "wof:placetype":"venue"
},
  "geometry": {"coordinates":[7.60088,50.409809],"type":"Point"}
}