{
  "type": "Feature",
  "properties": {
    "iso:country":"DE",
    "sg:address":"H\u00fcttruper Str. 18",
    "sg:city":"Greven",
    "sg:phone":"+49 2571/55166",
    "sg:postcode":"48268",
    "sg:province":"Nordrhein-Westfalen",
    "wof:name":"Ludger Schlautmann",
    "wof:placetype":"venue"
},
  "geometry": {"coordinates":[7.628585,52.107525],"type":"Point"}
}