{
  "type": "Feature",
  "properties": {
    "iso:country":"DE",
    "sg:address":"Lachentalstr. 3",
    "sg:city":"Weil im Sch\u00f6nbuch",
    "sg:phone":"+49 7157/62340",
    "sg:postcode":"71093",
    "sg:province":"Baden-W\u00fcrttemberg",
    "wof:name":"Wolfgang Els\u00e4sser",
    "wof:placetype":"venue"
},
  "geometry": {"coordinates":[9.043466568,48.6210174561],"type":"Point"}
}