{
  "type": "Feature",
  "properties": {
    "iso:country":"DE",
    "sg:address":"Wesselyring 20",
    "sg:city":"Hamburg",
    "sg:phone":"+49 40/517780",
    "sg:postcode":"22297",
    "sg:province":"Hamburg",
    "wof:name":"Peter Prang",
    "wof:placetype":"venue"
},
  "geometry": {"coordinates":[10.0139932632,53.6039428711],"type":"Point"}
}