{
  "type": "Feature",
  "properties": {
    "iso:country":"DE",
    "sg:address":"M\u00fchlenstr. 27",
    "sg:city":"Crailsheim",
    "sg:phone":"+49 7951/8441",
    "sg:postcode":"74564",
    "sg:province":"Baden-W\u00fcrttemberg",
    "wof:name":"Karl Glessing",
    "wof:placetype":"venue"
},
  "geometry": {"coordinates":[10.064471,49.091763],"type":"Point"}
}