{
  "type": "Feature",
  "properties": {
    "iso:country":"DE",
    "sg:address":"Lange Str. 77",
    "sg:city":"Schorndorf",
    "sg:postcode":"73614",
    "sg:province":"Baden-W\u00fcrttemberg",
    "wof:name":"Restaurant Peking City",
    "wof:placetype":"venue"
},
  "geometry": {"coordinates":[9.5160980225,48.8013191223],"type":"Point"}
}