{
  "type": "Feature",
  "properties": {
    "iso:country":"DE",
    "sg:address":"Kurf\u00fcrstenstr. 154",
    "sg:city":"Berlin",
    "sg:phone":"+49 30/2612460",
    "sg:postcode":"10785",
    "sg:province":"Berlin",
    "wof:name":"Kurmark-apotheke Inh. Michael Joachimmeyer",
    "wof:placetype":"venue"
},
  "geometry": {"coordinates":[13.36351,52.499485],"type":"Point"}
}