{
  "type": "Feature",
  "properties": {
    "iso:country":"DE",
    "sg:address":"Slevogtstr. 46",
    "sg:city":"Chemnitz",
    "sg:phone":"+49 371/8205782",
    "sg:postcode":"09114",
    "sg:province":"Sachsen",
    "wof:name":"Simone R\u00f6hl",
    "wof:placetype":"venue"
},
  "geometry": {"coordinates":[12.943206,50.883492],"type":"Point"}
}