{
  "type": "Feature",
  "properties": {
    "iso:country":"DE",
    "sg:address":"Hamburger Str. 7",
    "sg:city":"Perleberg",
    "sg:phone":"+49 3876/614039",
    "sg:postcode":"19348",
    "sg:province":"Brandenburg",
    "wof:name":"G\u00fcnter Stange",
    "wof:placetype":"venue"
},
  "geometry": {"coordinates":[11.860966,53.080875],"type":"Point"}
}