{
  "type": "Feature",
  "properties": {
    "iso:country":"DE",
    "sg:address":"Schlachthofstr. 45",
    "sg:city":"Erfurt",
    "sg:phone":"+49 361/5695135",
    "sg:postcode":"99085",
    "sg:province":"Th\u00fcringen",
    "wof:name":"Lv Th\u00fcringen-verband Der Fischweiden",
    "wof:placetype":"venue"
},
  "geometry": {"coordinates":[11.0441875458,50.9883117676],"type":"Point"}
}