{
  "type": "Feature",
  "properties": {
    "iso:country":"DE",
    "sg:address":"Schulstr. 33",
    "sg:city":"Malchin",
    "sg:phone":"+49 3994/222240",
    "sg:postcode":"17139",
    "sg:province":"Mecklenburg-Vorpommern",
    "wof:name":"Hotel-restaurant Zachow",
    "wof:placetype":"venue"
},
  "geometry": {"coordinates":[12.7593288422,53.7395744324],"type":"Point"}
}