{
  "type": "Feature",
  "properties": {
    "iso:country":"DE",
    "sg:address":"Otto-Hahn-Str. 15",
    "sg:city":"Herrenberg",
    "sg:postcode":"71083",
    "sg:province":"Baden-W\u00fcrttemberg",
    "wof:name":"Lackieung H\u00e4mmerling E. K.",
    "wof:placetype":"venue"
},
  "geometry": {"coordinates":[8.848602,48.613754],"type":"Point"}
}