{
  "type": "Feature",
  "properties": {
    "iso:country":"DE",
    "sg:address":"Huckarder Str. 91",
    "sg:city":"Dortmund",
    "sg:phone":"+49 231/9130080",
    "sg:postcode":"44147",
    "sg:province":"Nordrhein-Westfalen",
    "wof:name":"German Parcel Paket-logistik Gmbh & Co. Ohg",
    "wof:placetype":"venue"
},
  "geometry": {"coordinates":[7.431928,51.518177],"type":"Point"}
}