{
  "type": "Feature",
  "properties": {
    "iso:country":"DE",
    "sg:address":"Hauptstr. 99",
    "sg:city":"Wannweil",
    "sg:phone":"+49 7121/56770",
    "sg:postcode":"72827",
    "sg:province":"Baden-W\u00fcrttemberg",
    "wof:name":"Verwaltungs- Und Beteiligungs- Gesellschaft Screenart Gmbh",
    "wof:placetype":"venue"
},
  "geometry": {"coordinates":[9.1597175598,48.5111427307],"type":"Point"}
}