{
  "type": "Feature",
  "properties": {
    "iso:country":"DE",
    "sg:address":"Werderstr. 39",
    "sg:city":"Karlsruhe",
    "sg:phone":"+49 721/389624",
    "sg:postcode":"76137",
    "sg:province":"Baden-W\u00fcrttemberg",
    "wof:name":"Annarita Sventurato",
    "wof:placetype":"venue"
},
  "geometry": {"coordinates":[8.4071712494,49.0017204285],"type":"Point"}
}