{
  "type": "Feature",
  "properties": {
    "iso:country":"DE",
    "sg:address":"Untenende 3",
    "sg:city":"Rhauderfehn",
    "sg:postcode":"26817",
    "sg:province":"Niedersachsen",
    "wof:name":"Ev. Luth. Kirchengemeinde Westrhauderfehn",
    "wof:placetype":"venue"
},
  "geometry": {"coordinates":[7.57543993,53.1359405518],"type":"Point"}
}