{
  "type": "Feature",
  "properties": {
    "iso:country":"DE",
    "sg:address":"Hammer Deich 126",
    "sg:city":"Hamburg",
    "sg:phone":"+49 40/211371",
    "sg:postcode":"20537",
    "sg:province":"Hamburg",
    "wof:name":"Teba Gmbh",
    "wof:placetype":"venue"
},
  "geometry": {"coordinates":[10.048022,53.545551],"type":"Point"}
}