{
  "type": "Feature",
  "properties": {
    "iso:country":"DE",
    "sg:address":"Daimlerstr. 7",
    "sg:city":"Schwieberdingen",
    "sg:phone":"+49 7150/31188",
    "sg:postcode":"71701",
    "sg:province":"Baden-W\u00fcrttemberg",
    "wof:name":"E. H\u00e4ussermann -eha- Screenphot Gmbh",
    "wof:placetype":"venue"
},
  "geometry": {"coordinates":[9.076758,48.880692],"type":"Point"}
}