{
  "type": "Feature",
  "properties": {
    "iso:country":"DE",
    "sg:address":"Goethestr. 20",
    "sg:city":"D\u00fcsseldorf",
    "sg:postcode":"40237",
    "sg:province":"Nordrhein-Westfalen",
    "wof:name":"Transfer Textilvertriebs Gmbh",
    "wof:placetype":"venue"
},
  "geometry": {"coordinates":[6.8023152351,51.232421875],"type":"Point"}
}