{
  "type": "Feature",
  "properties": {
    "iso:country":"DE",
    "sg:address":"Bischof-Fleischer-Str. 3",
    "sg:city":"Dettelbach",
    "sg:phone":"+49 9324/90236",
    "sg:postcode":"97337",
    "sg:province":"Bayern",
    "wof:name":"Wohn-bauer Gmbh",
    "wof:placetype":"venue"
},
  "geometry": {"coordinates":[10.171327,49.806957],"type":"Point"}
}