{
  "type": "Feature",
  "properties": {
    "iso:country":"DE",
    "sg:address":"Zum Park 6",
    "sg:city":"Willingen",
    "sg:phone":"+49 5632/1326",
    "sg:postcode":"34508",
    "sg:province":"Hessen",
    "wof:name":"Herbert Sch\u00e4fer",
    "wof:placetype":"venue"
},
  "geometry": {"coordinates":[8.65391,51.310997],"type":"Point"}
}