{
  "type": "Feature",
  "properties": {
    "iso:country":"DE",
    "sg:address":"Blumenstr. 8",
    "sg:city":"Weeze",
    "sg:postcode":"47652",
    "sg:province":"Nordrhein-Westfalen",
    "wof:name":"Soft Pac- Software Bernardus De Jonge",
    "wof:placetype":"venue"
},
  "geometry": {"coordinates":[6.1972160339,51.6288871765],"type":"Point"}
}