{
  "type": "Feature",
  "properties": {
    "iso:country":"DE",
    "sg:address":"Linnicher Str. 16",
    "sg:city":"Alsdorf",
    "sg:phone":"+49 2404/4908",
    "sg:postcode":"52477",
    "sg:province":"Nordrhein-Westfalen",
    "wof:name":"Karl-heinz Leisten Ingenieur",
    "wof:placetype":"venue"
},
  "geometry": {"coordinates":[6.1674079895,50.8791503906],"type":"Point"}
}