{
  "type": "Feature",
  "properties": {
    "iso:country":"DE",
    "sg:address":"Jungfernstieg 4",
    "sg:city":"Rendsburg",
    "sg:phone":"+49 4331/22827",
    "sg:postcode":"24768",
    "sg:province":"Schleswig-Holstein",
    "wof:name":"Brehmer Der Rendsburger B\u00e4cker",
    "wof:placetype":"venue"
},
  "geometry": {"coordinates":[9.666245,54.303799],"type":"Point"}
}