{
  "type": "Feature",
  "properties": {
    "iso:country":"DE",
    "sg:address":"Frankfurter Str. 21",
    "sg:city":"Siegen",
    "sg:phone":"+49 271/51835",
    "sg:postcode":"57074",
    "sg:province":"Nordrhein-Westfalen",
    "wof:name":"Hermann Pamp",
    "wof:placetype":"venue"
},
  "geometry": {"coordinates":[8.0248403549,50.8711585999],"type":"Point"}
}