{
  "type": "Feature",
  "properties": {
    "iso:country":"DE",
    "sg:address":"Frankfurter Str. 16",
    "sg:city":"Halver",
    "sg:phone":"+49 2353/2330",
    "sg:postcode":"58553",
    "sg:province":"Nordrhein-Westfalen",
    "wof:name":"Michael Kortmann Augenoptiker",
    "wof:placetype":"venue"
},
  "geometry": {"coordinates":[7.4998259544,51.1865310669],"type":"Point"}
}