{
  "type": "Feature",
  "properties": {
    "iso:country":"DE",
    "sg:address":"Barbarossastr. 66",
    "sg:city":"Chemnitz",
    "sg:postcode":"09112",
    "sg:province":"Sachsen",
    "wof:name":"F. Bode",
    "wof:placetype":"venue"
},
  "geometry": {"coordinates":[12.9015951157,50.8334007263],"type":"Point"}
}