{
  "type": "Feature",
  "properties": {
    "iso:country":"DE",
    "sg:address":"Etzeler Str. 7",
    "sg:city":"Friedeburg",
    "sg:phone":"+49 4453/4339",
    "sg:postcode":"26446",
    "sg:province":"Niedersachsen",
    "wof:name":"Bernh. Korte",
    "wof:placetype":"venue"
},
  "geometry": {"coordinates":[7.939205,53.452209],"type":"Point"}
}