{
  "type": "Feature",
  "properties": {
    "iso:country":"DE",
    "sg:address":"Breitenbacher Str. 14",
    "sg:city":"Worbis",
    "sg:phone":"+49 36074/30323",
    "sg:postcode":"37339",
    "sg:province":"Th\u00fcringen",
    "wof:name":"Wilfried Leibeling",
    "wof:placetype":"venue"
},
  "geometry": {"coordinates":[10.35989,51.415009],"type":"Point"}
}