{
  "type": "Feature",
  "properties": {
    "iso:country":"DE",
    "sg:address":"Bilsteinweg 23",
    "sg:city":"Marsberg",
    "sg:phone":"+49 2992/97660",
    "sg:postcode":"34431",
    "sg:province":"Nordrhein-Westfalen",
    "wof:name":"Aqua & Fun Gmbh",
    "wof:placetype":"venue"
},
  "geometry": {"coordinates":[8.8583459854,51.4598121643],"type":"Point"}
}