{
  "type": "Feature",
  "properties": {
    "iso:country":"DE",
    "sg:city":"Wuppertal",
    "sg:phone":"+49 202/2985790",
    "sg:postcode":"42285",
    "sg:province":"Nordrhein-Westfalen",
    "wof:name":"Ako Kontierungsb\u00fcro Achim Kohl",
    "wof:placetype":"venue"
},
  "geometry": {"coordinates":[7.17464,51.256859],"type":"Point"}
}