{
  "type": "Feature",
  "properties": {
    "iso:country":"DE",
    "sg:address":"Friedensstr. 7",
    "sg:city":"H\u00f6velhof",
    "sg:postcode":"33161",
    "sg:province":"Nordrhein-Westfalen",
    "wof:name":"Mancini Gmbh",
    "wof:placetype":"venue"
},
  "geometry": {"coordinates":[8.6570291519,51.8185424805],"type":"Point"}
}