{
  "type": "Feature",
  "properties": {
    "iso:country":"DE",
    "sg:address":"Am Blauen Berg 1",
    "sg:city":"Leverkusen",
    "sg:phone":"+49 214/55085",
    "sg:postcode":"51375",
    "sg:province":"Nordrhein-Westfalen",
    "wof:name":"Mediatravel",
    "wof:placetype":"venue"
},
  "geometry": {"coordinates":[7.0464577675,51.0306625366],"type":"Point"}
}