{
  "type": "Feature",
  "properties": {
    "iso:country":"DE",
    "sg:address":"Hauptstr. 8",
    "sg:city":"Schechen",
    "sg:phone":"+49 8039/409549",
    "sg:postcode":"83135",
    "sg:province":"Bayern",
    "wof:name":"Business Concept Ges. F\u00fcr Vertriebsk. Abrechnungs- Verw.",
    "wof:placetype":"venue"
},
  "geometry": {"coordinates":[12.1265096664,47.9421234131],"type":"Point"}
}