{
  "type": "Feature",
  "properties": {
    "iso:country":"DE",
    "sg:address":"Habsburgring 86",
    "sg:city":"Mayen",
    "sg:postcode":"56727",
    "sg:province":"Rheinland-Pfalz",
    "wof:name":"Anja Grenzh\u00e4user",
    "wof:placetype":"venue"
},
  "geometry": {"coordinates":[7.2187190056,50.3294868469],"type":"Point"}
}