{
  "type": "Feature",
  "properties": {
    "iso:country":"DE",
    "sg:address":"Hans-B\u00f6ckler-Str. 5",
    "sg:city":"Bonn",
    "sg:phone":"+49 228/40010",
    "sg:postcode":"53225",
    "sg:province":"Nordrhein-Westfalen",
    "wof:name":"Archiv Der Deutschen Stiftung F\u00fcr Internationale Entwicklung",
    "wof:placetype":"venue"
},
  "geometry": {"coordinates":[7.122116,50.740173],"type":"Point"}
}