{
  "type": "Feature",
  "properties": {
    "iso:country":"DE",
    "sg:address":"Pasteurstr. 50",
    "sg:city":"Berlin",
    "sg:phone":"+49 30/4247162",
    "sg:postcode":"10407",
    "sg:province":"Berlin",
    "wof:name":"Pc-xprez E. K.",
    "wof:placetype":"venue"
},
  "geometry": {"coordinates":[13.438528,52.53104],"type":"Point"}
}