{
  "type": "Feature",
  "properties": {
    "iso:country":"DE",
    "sg:address":"Strandstr. 14",
    "sg:city":"Kr\u00f6pelin",
    "sg:phone":"+49 38292/459",
    "sg:postcode":"18236",
    "sg:province":"Mecklenburg-Vorpommern",
    "wof:name":"Zimmermann Optik Gmbh",
    "wof:placetype":"venue"
},
  "geometry": {"coordinates":[11.7913322449,54.0726928711],"type":"Point"}
}