{
  "type": "Feature",
  "properties": {
    "iso:country":"DE",
    "sg:address":"Am Reiherbusch 10",
    "sg:city":"Grevenbroich",
    "sg:phone":"+49 2181/74799",
    "sg:postcode":"41516",
    "sg:province":"Nordrhein-Westfalen",
    "wof:name":"Josef Neukirchen",
    "wof:placetype":"venue"
},
  "geometry": {"coordinates":[6.6578330994,51.1328430176],"type":"Point"}
}