{
  "type": "Feature",
  "properties": {
    "iso:country":"DE",
    "sg:address":"Wassenbergstr. 8",
    "sg:city":"Emmerich",
    "sg:phone":"+49 2822/537503",
    "sg:postcode":"46446",
    "sg:province":"Nordrhein-Westfalen",
    "wof:name":"Kranken-u. Altenpflege Die Johanniter",
    "wof:placetype":"venue"
},
  "geometry": {"coordinates":[6.249687,51.835903],"type":"Point"}
}