{
  "type": "Feature",
  "properties": {
    "iso:country":"DE",
    "sg:address":"Hochstr. 52",
    "sg:city":"Landau",
    "sg:phone":"+49 9951/98500",
    "sg:postcode":"94405",
    "sg:province":"Bayern",
    "wof:name":"G\u00fcnter Elsberger",
    "wof:placetype":"venue"
},
  "geometry": {"coordinates":[12.703783989,48.6611595154],"type":"Point"}
}