{
  "type": "Feature",
  "properties": {
    "iso:country":"DE",
    "sg:address":"Barlachstr. 46",
    "sg:city":"Altenburg",
    "sg:phone":"+49 3447/81063",
    "sg:postcode":"04600",
    "sg:province":"Th\u00fcringen",
    "wof:name":"Hans-j\u00fcrgen Herold",
    "wof:placetype":"venue"
},
  "geometry": {"coordinates":[12.4187240601,50.995929718],"type":"Point"}
}