{
  "type": "Feature",
  "properties": {
    "iso:country":"DE",
    "sg:address":"Bevenroder Str. 44",
    "sg:city":"Braunschweig",
    "sg:phone":"+49 531/375209",
    "sg:postcode":"38108",
    "sg:province":"Niedersachsen",
    "wof:name":"Restaurant Yangs Garden",
    "wof:placetype":"venue"
},
  "geometry": {"coordinates":[10.5600614548,52.2946624756],"type":"Point"}
}