{
  "type": "Feature",
  "properties": {
    "iso:country":"DE",
    "sg:address":"Hochstr. 31a",
    "sg:city":"Bottrop",
    "sg:phone":"+49 2041/24191",
    "sg:postcode":"46236",
    "sg:province":"Nordrhein-Westfalen",
    "wof:name":"Udo Feldeisen",
    "wof:placetype":"venue"
},
  "geometry": {"coordinates":[6.9249539375,51.5206260681],"type":"Point"}
}