{
  "type": "Feature",
  "properties": {
    "iso:country":"DE",
    "sg:address":"Flerrentwiete 76",
    "sg:city":"Hamburg",
    "sg:phone":"+49 40/813827",
    "sg:postcode":"22559",
    "sg:province":"Hamburg",
    "wof:name":"Riko-bauregie Helga Schultz",
    "wof:placetype":"venue"
},
  "geometry": {"coordinates":[9.7490215302,53.5776596069],"type":"Point"}
}