{
  "type": "Feature",
  "properties": {
    "iso:country":"DE",
    "sg:address":"Thomas-M\u00fcntzer-Str. 11",
    "sg:city":"Mihla",
    "sg:phone":"+49 36924/42091",
    "sg:postcode":"99826",
    "sg:province":"Th\u00fcringen",
    "wof:name":"Rosel Jauernek",
    "wof:placetype":"venue"
},
  "geometry": {"coordinates":[10.330756,51.076656],"type":"Point"}
}