{
  "type": "Feature",
  "properties": {
    "iso:country":"DE",
    "sg:address":"Liebermannstrasse 1/119",
    "sg:city":"N\u00fcrtingen",
    "sg:postcode":"72622",
    "sg:province":"Baden-W\u00fcrttemberg",
    "wof:name":"B\u00fcrgerbereinigung Ro\u00dfdorf",
    "wof:placetype":"venue"
},
  "geometry": {"coordinates":[9.342148,48.604179],"type":"Point"}
}