{
  "type": "Feature",
  "properties": {
    "iso:country":"DE",
    "sg:address":"Erich-K\u00e4stner-Str. 29",
    "sg:city":"Karben",
    "sg:phone":"+49 6039/92120",
    "sg:postcode":"61184",
    "sg:province":"Hessen",
    "wof:name":"Goerigk Informations- Technologie Gmbh",
    "wof:placetype":"venue"
},
  "geometry": {"coordinates":[8.7712497711,50.2265357971],"type":"Point"}
}