{
  "type": "Feature",
  "properties": {
    "iso:country":"DE",
    "sg:address":"Rosenweg 1a",
    "sg:city":"Herbolzheim",
    "sg:phone":"+49 7643/354",
    "sg:postcode":"79336",
    "sg:province":"Baden-W\u00fcrttemberg",
    "wof:name":"Pension Posthorn",
    "wof:placetype":"venue"
},
  "geometry": {"coordinates":[7.7684059143,48.2249565125],"type":"Point"}
}