{
  "type": "Feature",
  "properties": {
    "iso:country":"DE",
    "sg:address":"Thinggasse 8",
    "sg:city":"M\u00fcnsingen",
    "sg:phone":"+49 7381/4419",
    "sg:postcode":"72525",
    "sg:province":"Baden-W\u00fcrttemberg",
    "wof:name":"Eloquia Fach\u00fcbersetzungen Und Marketing Gmbh",
    "wof:placetype":"venue"
},
  "geometry": {"coordinates":[9.4950942993,48.4321289062],"type":"Point"}
}