{
  "type": "Feature",
  "properties": {
    "iso:country":"DE",
    "sg:address":"Zum Wiebusch 2",
    "sg:city":"Balve",
    "sg:phone":"+49 2375/4102",
    "sg:postcode":"58802",
    "sg:province":"Nordrhein-Westfalen",
    "wof:name":"Engelbert Busche",
    "wof:placetype":"venue"
},
  "geometry": {"coordinates":[7.817037,51.302139],"type":"Point"}
}