{
  "type": "Feature",
  "properties": {
    "iso:country":"DE",
    "sg:address":"Oldenburger Allee 26",
    "sg:city":"Hannover",
    "sg:phone":"+49 511/610700",
    "sg:postcode":"30659",
    "sg:province":"Niedersachsen",
    "wof:name":"Wienerberger System- Schornstein Gmbh & Co. Kg",
    "wof:placetype":"venue"
},
  "geometry": {"coordinates":[9.8255186081,52.4197273254],"type":"Point"}
}