{
  "type": "Feature",
  "properties": {
    "iso:country":"DE",
    "sg:address":"Nymphenburger Str. 184",
    "sg:city":"M\u00fcnchen",
    "sg:phone":"+49 89/163031",
    "sg:postcode":"80634",
    "sg:province":"Bayern",
    "wof:name":"Farben-klotz Stefan Klotz Gmbh",
    "wof:placetype":"venue"
},
  "geometry": {"coordinates":[11.532711,48.15546],"type":"Point"}
}