{
  "type": "Feature",
  "properties": {
    "iso:country":"DE",
    "sg:address":"Ratzeburger Str. 54",
    "sg:city":"Bad Oldesloe",
    "sg:phone":"+49 4531/81092",
    "sg:postcode":"23843",
    "sg:province":"Schleswig-Holstein",
    "wof:name":"Hanseatisches Auktionshaus F\u00fcr Historica Dr. Beer Und Partner",
    "wof:placetype":"venue"
},
  "geometry": {"coordinates":[10.394294,53.807266],"type":"Point"}
}