{
  "type": "Feature",
  "properties": {
    "iso:country":"DE",
    "sg:address":"Kapellenweg 5",
    "sg:city":"Hasel\u00fcnne",
    "sg:phone":"+49 5961/6361",
    "sg:postcode":"49740",
    "sg:province":"Niedersachsen",
    "wof:name":"Werner Robben",
    "wof:placetype":"venue"
},
  "geometry": {"coordinates":[7.421554,52.658077],"type":"Point"}
}