{
  "type": "Feature",
  "properties": {
    "iso:country":"DE",
    "sg:address":"Frontenhausener Str. 27",
    "sg:city":"Vilsbiburg",
    "sg:phone":"+49 8741/7248",
    "sg:postcode":"84137",
    "sg:province":"Bayern",
    "wof:name":"Josef Kopp Heilpraktiker",
    "wof:placetype":"venue"
},
  "geometry": {"coordinates":[12.3558225632,48.4508247375],"type":"Point"}
}