{
  "type": "Feature",
  "properties": {
    "iso:country":"DE",
    "sg:address":"Belgarder Str. 14",
    "sg:city":"N\u00fcrnberg",
    "sg:phone":"+49 911/6427323",
    "sg:postcode":"90451",
    "sg:province":"Bayern",
    "wof:name":"Elimex Bauelemente-vertrieb Gmbh",
    "wof:placetype":"venue"
},
  "geometry": {"coordinates":[11.035925,49.412605],"type":"Point"}
}