{
  "type": "Feature",
  "properties": {
    "iso:country":"DE",
    "sg:address":"Ringstr. 2",
    "sg:city":"Iphofen",
    "sg:phone":"+49 9326/561",
    "sg:postcode":"97346",
    "sg:province":"Bayern",
    "wof:name":"Karl Hassold",
    "wof:placetype":"venue"
},
  "geometry": {"coordinates":[10.285374,49.640442],"type":"Point"}
}