{
  "type": "Feature",
  "properties": {
    "iso:country":"DE",
    "sg:address":"Burgstr. 27",
    "sg:city":"Wolfhagen",
    "sg:phone":"+49 5692/5559",
    "sg:postcode":"34466",
    "sg:province":"Hessen",
    "wof:name":"Larsen Schmidt-dickel",
    "wof:placetype":"venue"
},
  "geometry": {"coordinates":[9.169332,51.324722],"type":"Point"}
}