{
  "type": "Feature",
  "properties": {
    "iso:country":"DE",
    "sg:address":"Am Teich 11",
    "sg:city":"Neum\u00fcnster",
    "sg:phone":"+49 4321/43383",
    "sg:postcode":"24534",
    "sg:province":"Schleswig-Holstein",
    "wof:name":"W.-d. Ettling",
    "wof:placetype":"venue"
},
  "geometry": {"coordinates":[9.983082,54.073105],"type":"Point"}
}