{
  "type": "Feature",
  "properties": {
    "iso:country":"DE",
    "sg:address":"Hauptstr. 28",
    "sg:city":"Menden",
    "sg:phone":"+49 2373/4048",
    "sg:postcode":"58706",
    "sg:province":"Nordrhein-Westfalen",
    "wof:name":"S. Wozny Rechtsanwalt",
    "wof:placetype":"venue"
},
  "geometry": {"coordinates":[7.7967581749,51.4370155334],"type":"Point"}
}