{
  "type": "Feature",
  "properties": {
    "iso:country":"DE",
    "sg:address":"Albert-M\u00fccke-Ring 8a",
    "sg:city":"Mei\u00dfen",
    "sg:phone":"+49 3521/732885",
    "sg:postcode":"01662",
    "sg:province":"Sachsen",
    "wof:name":"Petra Ble\u00dfmann",
    "wof:placetype":"venue"
},
  "geometry": {"coordinates":[13.512531,51.167473],"type":"Point"}
}