{
  "type": "Feature",
  "properties": {
    "iso:country":"DE",
    "sg:address":"Niederkasseler Deich 285",
    "sg:city":"D\u00fcsseldorf",
    "sg:phone":"+49 211/8212579",
    "sg:postcode":"40547",
    "sg:province":"Nordrhein-Westfalen",
    "wof:name":"Freibad L\u00f6rick",
    "wof:placetype":"venue"
},
  "geometry": {"coordinates":[6.7324681282,51.2500534058],"type":"Point"}
}