{
  "type": "Feature",
  "properties": {
    "iso:country":"DE",
    "sg:address":"Clausewitzstr. 1",
    "sg:city":"Berlin",
    "sg:phone":"+49 30/8815425",
    "sg:postcode":"10629",
    "sg:province":"Berlin",
    "wof:name":"Alaska",
    "wof:placetype":"venue"
},
  "geometry": {"coordinates":[13.309333,52.501572],"type":"Point"}
}