{
  "type": "Feature",
  "properties": {
    "iso:country":"DE",
    "sg:address":"D\u00f6rntener Str. 7",
    "sg:city":"Liebenburg",
    "sg:phone":"+49 5346/95020",
    "sg:postcode":"38704",
    "sg:province":"Niedersachsen",
    "wof:name":"Wierczeyko Kg",
    "wof:placetype":"venue"
},
  "geometry": {"coordinates":[10.399225,51.99794],"type":"Point"}
}