{
  "type": "Feature",
  "properties": {
    "iso:country":"DE",
    "sg:address":"Dr.-Karl-Gelbke-Str. 4",
    "sg:city":"Plauen",
    "sg:phone":"+49 3741/441514",
    "sg:postcode":"08529",
    "sg:province":"Sachsen",
    "wof:name":"Christian Schaufel Architekt",
    "wof:placetype":"venue"
},
  "geometry": {"coordinates":[12.164931,50.500004],"type":"Point"}
}