{
  "type": "Feature",
  "properties": {
    "iso:country":"DE",
    "sg:address":"Wiedersbacher Str. 22",
    "sg:city":"Hildburghausen",
    "sg:phone":"+49 3685/79770",
    "sg:postcode":"98646",
    "sg:province":"Th\u00fcringen",
    "wof:name":"Staffel Verwaltungs- Gmbh",
    "wof:placetype":"venue"
},
  "geometry": {"coordinates":[10.742444,50.429871],"type":"Point"}
}