{
  "type": "Feature",
  "properties": {
    "iso:country":"DE",
    "sg:address":"Daimlerstr. 6",
    "sg:city":"Aspach",
    "sg:phone":"+49 7191/919200",
    "sg:postcode":"71546",
    "sg:province":"Baden-W\u00fcrttemberg",
    "wof:name":"W. Streker Natursaft Gmbh",
    "wof:placetype":"venue"
},
  "geometry": {"coordinates":[9.38857,48.972824],"type":"Point"}
}