{
  "type": "Feature",
  "properties": {
    "iso:country":"DE",
    "sg:address":"Uhlandstr. 158",
    "sg:city":"Berlin",
    "sg:phone":"+49 30/8818048",
    "sg:postcode":"10719",
    "sg:province":"Berlin",
    "wof:name":"Fasanen-apotheke Annette Wetzel E. Kfr.",
    "wof:placetype":"venue"
},
  "geometry": {"coordinates":[13.324838,52.498772],"type":"Point"}
}