{
  "type": "Feature",
  "properties": {
    "iso:country":"DE",
    "sg:address":"Bruchstr. 4",
    "sg:city":"Bothel",
    "sg:phone":"+49 4266/660",
    "sg:postcode":"27386",
    "sg:province":"Niedersachsen",
    "wof:name":"Biohof Rainer Scheele",
    "wof:placetype":"venue"
},
  "geometry": {"coordinates":[9.503038,53.070042],"type":"Point"}
}