{
  "type": "Feature",
  "properties": {
    "iso:country":"DE",
    "sg:address":"Otto-Hahn-Str. 42",
    "sg:city":"Zwickau",
    "sg:postcode":"08066",
    "sg:province":"Sachsen",
    "wof:name":"H.-u. Walz",
    "wof:placetype":"venue"
},
  "geometry": {"coordinates":[12.525235,50.729836],"type":"Point"}
}