{
  "type": "Feature",
  "properties": {
    "iso:country":"DE",
    "sg:address":"Werner-von-Siemens-Str. 6",
    "sg:city":"Schleswig",
    "sg:phone":"+49 4621/53420",
    "sg:postcode":"24837",
    "sg:province":"Schleswig-Holstein",
    "wof:name":"Ing. Hermann Bartsch Gmbh",
    "wof:placetype":"venue"
},
  "geometry": {"coordinates":[9.57969,54.537415],"type":"Point"}
}