{
  "type": "Feature",
  "properties": {
    "iso:country":"DE",
    "sg:address":"Sch\u00f6nenbergstr.38",
    "sg:city":"M\u00fchlheim",
    "sg:postcode":"78570",
    "sg:province":"Baden-W\u00fcrttemberg",
    "wof:name":"Konstruktions- Und Zeichenb\u00fcro",
    "wof:placetype":"venue"
},
  "geometry": {"coordinates":[8.881803,48.035069],"type":"Point"}
}