{
  "type": "Feature",
  "properties": {
    "iso:country":"DE",
    "sg:address":"Amberger Str. 63",
    "sg:city":"K\u00fcmmersbruck",
    "sg:postcode":"92245",
    "sg:province":"Bayern",
    "wof:name":"Architekturb\u00fcro Roland Adler Gmbh",
    "wof:placetype":"venue"
},
  "geometry": {"coordinates":[11.874526,49.429489],"type":"Point"}
}