{
  "type": "Feature",
  "properties": {
    "iso:country":"DE",
    "sg:address":"Hellpothstr. 12",
    "sg:city":"Schwerte",
    "sg:phone":"+49 2304/244030",
    "sg:postcode":"58239",
    "sg:province":"Nordrhein-Westfalen",
    "wof:name":"M. Szerb",
    "wof:placetype":"venue"
},
  "geometry": {"coordinates":[7.572502,51.44125],"type":"Point"}
}