{
  "type": "Feature",
  "properties": {
    "iso:country":"DE",
    "sg:address":"Brunnenstr. 39",
    "sg:city":"Bodelshausen",
    "sg:phone":"+49 7471/7784",
    "sg:postcode":"72411",
    "sg:province":"Baden-W\u00fcrttemberg",
    "wof:name":"Fritz K\u00e4rcher",
    "wof:placetype":"venue"
},
  "geometry": {"coordinates":[8.970708,48.387047],"type":"Point"}
}