{
  "type": "Feature",
  "properties": {
    "iso:country":"DE",
    "sg:address":"Daimlerstr. 1-3",
    "sg:city":"Untermeitingen",
    "sg:phone":"+49 8232/96380",
    "sg:postcode":"86836",
    "sg:province":"Bayern",
    "wof:name":"Faist Systeme Gmbh",
    "wof:placetype":"venue"
},
  "geometry": {"coordinates":[10.837757,48.172153],"type":"Point"}
}