{
  "type": "Feature",
  "properties": {
    "iso:country":"DE",
    "sg:address":"Stubbenhuk 10",
    "sg:city":"Hamburg",
    "sg:phone":"+49 40/376090",
    "sg:postcode":"20459",
    "sg:province":"Hamburg",
    "wof:name":"Technolog Gmbh",
    "wof:placetype":"venue"
},
  "geometry": {"coordinates":[9.980817,53.545654],"type":"Point"}
}