{
  "type": "Feature",
  "properties": {
    "iso:country":"DE",
    "sg:address":"Odenwaldring 72",
    "sg:city":"Dreieich",
    "sg:phone":"+49 6103/85708",
    "sg:postcode":"63303",
    "sg:province":"Hessen",
    "wof:name":"K & T Bau Gmbh",
    "wof:placetype":"venue"
},
  "geometry": {"coordinates":[8.710303,50.008148],"type":"Point"}
}