{
  "type": "Feature",
  "properties": {
    "iso:country":"DE",
    "sg:address":"Wolfsgasse 10",
    "sg:city":"Satteldorf",
    "sg:phone":"+49 7951/41630",
    "sg:postcode":"74589",
    "sg:province":"Baden-W\u00fcrttemberg",
    "wof:name":"Wolfgang Dollinger",
    "wof:placetype":"venue"
},
  "geometry": {"coordinates":[10.0818309784,49.1696357727],"type":"Point"}
}