{
  "type": "Feature",
  "properties": {
    "iso:country":"DE",
    "sg:address":"Mauernstr. 32",
    "sg:city":"Celle",
    "sg:phone":"+49 5141/214777",
    "sg:postcode":"29221",
    "sg:province":"Niedersachsen",
    "wof:name":"Reiseb\u00fcro Hage",
    "wof:placetype":"venue"
},
  "geometry": {"coordinates":[10.0856742859,52.6240005493],"type":"Point"}
}