{
  "type": "Feature",
  "properties": {
    "iso:country":"DE",
    "sg:address":"Dammweg 2",
    "sg:city":"Mainz",
    "sg:phone":"+49 4961/318950",
    "sg:postcode":"55130",
    "sg:province":"Rheinland-Pfalz",
    "wof:name":"Adm Soya Mainz Gmbh & Co Kg",
    "wof:placetype":"venue"
},
  "geometry": {"coordinates":[8.32035,49.964882],"type":"Point"}
}