{
  "type": "Feature",
  "properties": {
    "iso:country":"DE",
    "sg:address":"Auf der Scholle 19",
    "sg:city":"Meerbusch",
    "sg:phone":"+49 2159/8784",
    "sg:postcode":"40668",
    "sg:province":"Nordrhein-Westfalen",
    "wof:name":"G\u00fcnter Becker Rheinwolle Inh. Dieter Lerch",
    "wof:placetype":"venue"
},
  "geometry": {"coordinates":[6.633035,51.304676],"type":"Point"}
}