{
  "type": "Feature",
  "properties": {
    "iso:country":"DE",
    "sg:address":"Langgasse 43",
    "sg:city":"Messel",
    "sg:phone":"+49 6159/5291",
    "sg:postcode":"64409",
    "sg:province":"Hessen",
    "wof:name":"Ludwig Hermann Jost Mech. Werkstatt",
    "wof:placetype":"venue"
},
  "geometry": {"coordinates":[8.744865,49.938797],"type":"Point"}
}