{
  "type": "Feature",
  "properties": {
    "iso:country":"DE",
    "sg:address":"Elisenstr. 69b",
    "sg:city":"Essen",
    "sg:phone":"+49 201/245720",
    "sg:postcode":"45139",
    "sg:province":"Nordrhein-Westfalen",
    "wof:name":"Sch\u00f6nmackers Umweltdienste Verwaltung Gmbh",
    "wof:placetype":"venue"
},
  "geometry": {"coordinates":[7.0323109627,51.4610595703],"type":"Point"}
}