{
  "type": "Feature",
  "properties": {
    "iso:country":"DE",
    "sg:address":"Bischofer Deich 35",
    "sg:city":"Wilster",
    "sg:phone":"+49 4823/432",
    "sg:postcode":"25554",
    "sg:province":"Schleswig-Holstein",
    "wof:name":"Alten- Und Pflegeheim Wilster",
    "wof:placetype":"venue"
},
  "geometry": {"coordinates":[9.383,53.918373],"type":"Point"}
}