{
  "type": "Feature",
  "properties": {
    "iso:country":"DE",
    "sg:address":"Wesendonkstr. 73",
    "sg:city":"M\u00fcnchen",
    "sg:phone":"+49 89/9574503",
    "sg:postcode":"81925",
    "sg:province":"Bayern",
    "wof:name":"Klaus Schl\u00fcpmann Rechtsanwalt",
    "wof:placetype":"venue"
},
  "geometry": {"coordinates":[11.6270341873,48.163394928],"type":"Point"}
}