{
  "type": "Feature",
  "properties": {
    "iso:country":"DE",
    "sg:address":"Hauptstr. 3",
    "sg:city":"Waldstetten",
    "sg:phone":"+49 7171/4522",
    "sg:postcode":"73550",
    "sg:province":"Baden-W\u00fcrttemberg",
    "wof:name":"Jeans L\u00e4dle",
    "wof:placetype":"venue"
},
  "geometry": {"coordinates":[9.820133,48.765491],"type":"Point"}
}