{
  "type": "Feature",
  "properties": {
    "iso:country":"DE",
    "sg:address":"Ortrudstr. 14",
    "sg:city":"M\u00fcnchen",
    "sg:phone":"+49 89/9579220",
    "sg:postcode":"81925",
    "sg:province":"Bayern",
    "wof:name":"Rolf Hak",
    "wof:placetype":"venue"
},
  "geometry": {"coordinates":[11.6283578873,48.1619606018],"type":"Point"}
}