{
  "type": "Feature",
  "properties": {
    "iso:country":"DE",
    "sg:address":"Neue Torstr. 28",
    "sg:city":"Blomberg",
    "sg:phone":"+49 5235/2929",
    "sg:postcode":"32825",
    "sg:province":"Nordrhein-Westfalen",
    "wof:name":"Pizzeria Mennecke",
    "wof:placetype":"venue"
},
  "geometry": {"coordinates":[9.0904750824,51.9451255798],"type":"Point"}
}