{
  "type": "Feature",
  "properties": {
    "iso:country":"DE",
    "sg:address":"V\u00f6lklinger Str. 1",
    "sg:city":"Mannheim",
    "sg:phone":"+49 621/720610",
    "sg:postcode":"68309",
    "sg:province":"Baden-W\u00fcrttemberg",
    "wof:name":"Secura Datensysteme Gmbh",
    "wof:placetype":"venue"
},
  "geometry": {"coordinates":[8.517365,49.507252],"type":"Point"}
}