{
  "type": "Feature",
  "properties": {
    "iso:country":"DE",
    "sg:address":"F\u00f6rsterweg 32a",
    "sg:city":"Barntrup",
    "sg:phone":"+49 5263/99090",
    "sg:postcode":"32683",
    "sg:province":"Nordrhein-Westfalen",
    "wof:name":"Kulp Gmbh & Co. Kg",
    "wof:placetype":"venue"
},
  "geometry": {"coordinates":[9.1337957382,51.9874305725],"type":"Point"}
}