{
  "type": "Feature",
  "properties": {
    "iso:country":"DE",
    "sg:address":"Okenstr. 51",
    "sg:city":"Offenburg",
    "sg:phone":"+49 781/22282",
    "sg:postcode":"77652",
    "sg:province":"Baden-W\u00fcrttemberg",
    "wof:name":"Gerd Schmid",
    "wof:placetype":"venue"
},
  "geometry": {"coordinates":[7.944774,48.479122],"type":"Point"}
}