{
  "type": "Feature",
  "properties": {
    "iso:country":"DE",
    "sg:address":"Bredenstr. 61",
    "sg:city":"Enger",
    "sg:phone":"+49 5224/6166",
    "sg:postcode":"32130",
    "sg:province":"Nordrhein-Westfalen",
    "wof:name":"R. Bollmann Immobilienmakler",
    "wof:placetype":"venue"
},
  "geometry": {"coordinates":[8.5208730698,52.1460418701],"type":"Point"}
}