{
  "type": "Feature",
  "properties": {
    "iso:country":"DE",
    "sg:address":"Gerhardstr. 9",
    "sg:city":"Recklinghausen",
    "sg:phone":"+49 2361/71271",
    "sg:postcode":"45661",
    "sg:province":"Nordrhein-Westfalen",
    "wof:name":"Max Mrohs",
    "wof:placetype":"venue"
},
  "geometry": {"coordinates":[7.1813058853,51.5688896179],"type":"Point"}
}