{
  "type": "Feature",
  "properties": {
    "iso:country":"DE",
    "sg:address":"Dorfstr. 12",
    "sg:city":"Nesse",
    "sg:phone":"+49 4933/990210",
    "sg:postcode":"26553",
    "sg:province":"Niedersachsen",
    "wof:name":"Pizzeria Gianfranco",
    "wof:placetype":"venue"
},
  "geometry": {"coordinates":[7.4299259186,53.6456756592],"type":"Point"}
}