{
  "type": "Feature",
  "properties": {
    "iso:country":"DE",
    "sg:address":"Am Pfingstgras 17",
    "sg:city":"Jerxheim",
    "sg:phone":"+49 5354/1646",
    "sg:postcode":"38381",
    "sg:province":"Niedersachsen",
    "wof:name":"Gustav Henning",
    "wof:placetype":"venue"
},
  "geometry": {"coordinates":[10.9081449509,52.0836906433],"type":"Point"}
}