{
  "type": "Feature",
  "properties": {
    "iso:country":"DE",
    "sg:address":"Glockengasse 1",
    "sg:city":"Hammersbach",
    "sg:phone":"+49 6185/80610",
    "sg:postcode":"63546",
    "sg:province":"Hessen",
    "wof:name":"Titsch-bohlender",
    "wof:placetype":"venue"
},
  "geometry": {"coordinates":[8.9984645844,50.234916687],"type":"Point"}
}