{
  "type": "Feature",
  "properties": {
    "iso:country":"DE",
    "sg:city":"Gie\u00dfen",
    "sg:phone":"+49 641/9716317",
    "sg:postcode":"35392",
    "sg:province":"Hessen",
    "wof:name":"Dirk M\u00fcller, Computer-dienstleistungen U. Handel",
    "wof:placetype":"venue"
},
  "geometry": {"coordinates":[8.676334,50.586613],"type":"Point"}
}