{
  "type": "Feature",
  "properties": {
    "iso:country":"DE",
    "sg:address":"Poppestr. 25",
    "sg:city":"Ganderkesee",
    "sg:phone":"+49 4223/3319",
    "sg:postcode":"27777",
    "sg:province":"Niedersachsen",
    "wof:name":"Fredo Kneehans",
    "wof:placetype":"venue"
},
  "geometry": {"coordinates":[8.528137207,53.0932159424],"type":"Point"}
}