{
  "type": "Feature",
  "properties": {
    "iso:country":"DE",
    "sg:address":"Eppendorfer Weg 138",
    "sg:city":"Hamburg",
    "sg:postcode":"20253",
    "sg:province":"Hamburg",
    "wof:name":"Etras Schmutzwasserentsorgung Hamburg Gmbh",
    "wof:placetype":"venue"
},
  "geometry": {"coordinates":[9.964022,53.577877],"type":"Point"}
}