{
  "type": "Feature",
  "properties": {
    "iso:country":"DE",
    "sg:address":"Am Glockenberg 1 - 3",
    "sg:city":"Hollenstedt",
    "sg:postcode":"21279",
    "sg:province":"Niedersachsen",
    "wof:name":"Arte-sano",
    "wof:placetype":"venue"
},
  "geometry": {"coordinates":[9.7162780762,53.362361908],"type":"Point"}
}