{
  "type": "Feature",
  "properties": {
    "iso:country":"DE",
    "sg:address":"Am Steinh\u00fcgel 11",
    "sg:city":"Iserlohn",
    "sg:phone":"+49 2371/60975",
    "sg:postcode":"58636",
    "sg:province":"Nordrhein-Westfalen",
    "wof:name":"Thomas Ritter",
    "wof:placetype":"venue"
},
  "geometry": {"coordinates":[7.7197270393,51.383014679],"type":"Point"}
}