{
  "type": "Feature",
  "properties": {
    "iso:country":"DE",
    "sg:address":"Kersdorfer Str. 33",
    "sg:city":"Briesen",
    "sg:phone":"+49 33607/5381",
    "sg:postcode":"15518",
    "sg:province":"Brandenburg",
    "wof:name":"I. Schindler Immobilienmakler",
    "wof:placetype":"venue"
},
  "geometry": {"coordinates":[14.2584114075,52.3393287659],"type":"Point"}
}