{
  "type": "Feature",
  "properties": {
    "iso:country":"DE",
    "sg:address":"Robert-Bosch-Str. 14",
    "sg:city":"Freiberg",
    "sg:phone":"+49 7141/941970",
    "sg:postcode":"71691",
    "sg:province":"Baden-W\u00fcrttemberg",
    "wof:name":"Karl Weis & Cie. Gmbh",
    "wof:placetype":"venue"
},
  "geometry": {"coordinates":[9.1991252899,48.929019928],"type":"Point"}
}