{
  "type": "Feature",
  "properties": {
    "iso:country":"DE",
    "sg:address":"Darmst\u00e4dter Str. 27",
    "sg:city":"Weiterstadt",
    "sg:phone":"+49 6150/189777",
    "sg:postcode":"64331",
    "sg:province":"Hessen",
    "wof:name":"Wehnert Und Taus Rechtsanw\u00e4lte Und Notare",
    "wof:placetype":"venue"
},
  "geometry": {"coordinates":[8.5830020905,49.90574646],"type":"Point"}
}