{
  "type": "Feature",
  "properties": {
    "iso:country":"DE",
    "sg:address":"Unteres Tor 21",
    "sg:city":"Northeim",
    "sg:phone":"+49 5551/912666",
    "sg:postcode":"37154",
    "sg:province":"Niedersachsen",
    "wof:name":"Gym 80 Fitnessclub",
    "wof:placetype":"venue"
},
  "geometry": {"coordinates":[9.970500946,51.6723136902],"type":"Point"}
}