{
  "type": "Feature",
  "properties": {
    "iso:country":"DE",
    "sg:address":"Siegstr 12",
    "sg:city":"Bocholt",
    "sg:phone":"+49 2871/181603",
    "sg:postcode":"46395",
    "sg:province":"Nordrhein-Westfalen",
    "wof:name":"Reyer & B\u00f6ing Gmbh & Co Kg",
    "wof:placetype":"venue"
},
  "geometry": {"coordinates":[6.625988,51.827435],"type":"Point"}
}