{
  "type": "Feature",
  "properties": {
    "iso:country":"DE",
    "sg:address":"Clara-Schumann-Weg 16",
    "sg:city":"\u00dcbach-Palenberg",
    "sg:phone":"+49 2451/900732",
    "sg:postcode":"52531",
    "sg:province":"Nordrhein-Westfalen",
    "wof:name":"T. Hackl Rechtsanwalt",
    "wof:placetype":"venue"
},
  "geometry": {"coordinates":[6.1138968468,50.9202079773],"type":"Point"}
}