{
  "type": "Feature",
  "properties": {
    "iso:country":"DE",
    "sg:address":"Adolf-Kolping-Str. 8",
    "sg:city":"Freising",
    "sg:phone":"+49 8161/83322",
    "sg:postcode":"85356",
    "sg:province":"Bayern",
    "wof:name":"W. Dambacher",
    "wof:placetype":"venue"
},
  "geometry": {"coordinates":[11.779207,48.383495],"type":"Point"}
}