{
  "type": "Feature",
  "properties": {
    "iso:country":"DE",
    "sg:address":"Konrad-Adenauer-Platz 26",
    "sg:city":"Ratingen",
    "sg:phone":"+49 2102/893189",
    "sg:postcode":"40885",
    "sg:province":"Nordrhein-Westfalen",
    "wof:name":"Kreativ B\u00e4der Civelek Gmbh",
    "wof:placetype":"venue"
},
  "geometry": {"coordinates":[6.828867,51.333176],"type":"Point"}
}