{
  "type": "Feature",
  "properties": {
    "iso:country":"DE",
    "sg:address":"Im Emerten 10",
    "sg:city":"Rinteln",
    "sg:phone":"+49 4957/5196260",
    "sg:postcode":"31737",
    "sg:province":"Niedersachsen",
    "wof:name":"Schaumburger Fleisch U Wurstwaren Werding Gmbh",
    "wof:placetype":"venue"
},
  "geometry": {"coordinates":[9.0852308273,52.1967887878],"type":"Point"}
}