{
  "type": "Feature",
  "properties": {
    "iso:country":"DE",
    "sg:address":"Freudenst\u00e4dter Str. 3",
    "sg:city":"Lo\u00dfburg",
    "sg:phone":"+49 7446/2745",
    "sg:postcode":"72290",
    "sg:province":"Baden-W\u00fcrttemberg",
    "wof:name":"Eva-maria Mewes",
    "wof:placetype":"venue"
},
  "geometry": {"coordinates":[8.447767,48.415318],"type":"Point"}
}