{
  "type": "Feature",
  "properties": {
    "iso:country":"DE",
    "sg:address":"Bahnhofstr. 32",
    "sg:city":"Neufahrn",
    "sg:phone":"+49 8165/6070",
    "sg:postcode":"85375",
    "sg:province":"Bayern",
    "wof:name":"Gemeindeb\u00fccherei Rathaus",
    "wof:placetype":"venue"
},
  "geometry": {"coordinates":[11.662455,48.316959],"type":"Point"}
}