{
  "type": "Feature",
  "properties": {
    "iso:country":"DE",
    "sg:address":"Lindenstr. 8",
    "sg:city":"Neustadt",
    "sg:phone":"+49 9568/6601",
    "sg:postcode":"96465",
    "sg:province":"Bayern",
    "wof:name":"Rosenbauer",
    "wof:placetype":"venue"
},
  "geometry": {"coordinates":[8.2013683319,47.9219474792],"type":"Point"}
}