{
  "type": "Feature",
  "properties": {
    "iso:country":"DE",
    "sg:address":"Eschborner Landstr. 130-132",
    "sg:city":"Frankfurt",
    "sg:phone":"+49 69/50918192",
    "sg:postcode":"60489",
    "sg:province":"Hessen",
    "wof:name":"Cvg Clubfahrten Verkaufs Gmbh",
    "wof:placetype":"venue"
},
  "geometry": {"coordinates":[8.5960264206,50.1290779114],"type":"Point"}
}