{
  "type": "Feature",
  "properties": {
    "iso:country":"DE",
    "sg:address":"Heiersdorfer Str 42",
    "sg:city":"Burgst\u00e4dt",
    "sg:phone":"+49 3724/2319",
    "sg:postcode":"09217",
    "sg:province":"Sachsen",
    "wof:name":"Emil Geiler Gbr",
    "wof:placetype":"venue"
},
  "geometry": {"coordinates":[12.7917108536,50.9370079041],"type":"Point"}
}