{
  "type": "Feature",
  "properties": {
    "iso:country":"DE",
    "sg:address":"Kiefernberg 6",
    "sg:city":"Hamburg",
    "sg:phone":"+49 40/7905363",
    "sg:postcode":"21075",
    "sg:province":"Hamburg",
    "wof:name":"Horst Maack Steuerberater",
    "wof:placetype":"venue"
},
  "geometry": {"coordinates":[9.9537639618,53.4621047974],"type":"Point"}
}