{
  "type": "Feature",
  "properties": {
    "iso:country":"DE",
    "sg:address":"Pannh\u00fctte 81",
    "sg:city":"Gelsenkirchen",
    "sg:postcode":"45891",
    "sg:province":"Nordrhein-Westfalen",
    "wof:name":"M\u00f6rtelberater",
    "wof:placetype":"venue"
},
  "geometry": {"coordinates":[7.0843749046,51.5564498901],"type":"Point"}
}