{
  "type": "Feature",
  "properties": {
    "iso:country":"DE",
    "sg:address":"Raiffeisenstr. 17",
    "sg:city":"Obernburg",
    "sg:phone":"+49 6022/38391",
    "sg:postcode":"63785",
    "sg:province":"Bayern",
    "wof:name":"Haertl Gmbh",
    "wof:placetype":"venue"
},
  "geometry": {"coordinates":[9.11383,49.832352],"type":"Point"}
}