{
  "type": "Feature",
  "properties": {
    "iso:country":"DE",
    "sg:address":"Theodor-Althoff-Str. 2",
    "sg:city":"Essen",
    "sg:postcode":"45133",
    "sg:province":"Nordrhein-Westfalen",
    "wof:name":"Kqn Information Services Gmbh",
    "wof:placetype":"venue"
},
  "geometry": {"coordinates":[6.979904,51.41576],"type":"Point"}
}