{
  "type": "Feature",
  "properties": {
    "iso:country":"DE",
    "sg:address":"Kleine Weingasse 6",
    "sg:city":"Weisenheim am Berg",
    "sg:phone":"+49 6353/7356",
    "sg:postcode":"67273",
    "sg:province":"Rheinland-Pfalz",
    "wof:name":"Wolfgang Kirchner",
    "wof:placetype":"venue"
},
  "geometry": {"coordinates":[8.1534824371,49.5128479004],"type":"Point"}
}