{
  "type": "Feature",
  "properties": {
    "iso:country":"DE",
    "sg:address":"Degenstr. 18",
    "sg:city":"Solingen",
    "sg:phone":"+49 212/43741",
    "sg:postcode":"42651",
    "sg:province":"Nordrhein-Westfalen",
    "wof:name":"Helmut Borgfeldt",
    "wof:placetype":"venue"
},
  "geometry": {"coordinates":[7.1027121544,51.1676521301],"type":"Point"}
}