{
  "type": "Feature",
  "properties": {
    "iso:country":"DE",
    "sg:address":"Heidestr. 14",
    "sg:city":"Eggesin",
    "sg:phone":"+49 39779/20365",
    "sg:postcode":"17367",
    "sg:province":"Mecklenburg-Vorpommern",
    "wof:name":"Barholz",
    "wof:placetype":"venue"
},
  "geometry": {"coordinates":[14.082286,53.67588],"type":"Point"}
}