{
  "type": "Feature",
  "properties": {
    "iso:country":"DE",
    "sg:address":"Alteburger Str. 16",
    "sg:city":"K\u00f6ln",
    "sg:phone":"+49 221/318930",
    "sg:postcode":"50678",
    "sg:province":"Nordrhein-Westfalen",
    "wof:name":"Weinkneipe Zur Alten Wettannahme",
    "wof:placetype":"venue"
},
  "geometry": {"coordinates":[6.9615859985,50.9211997986],"type":"Point"}
}