{
  "type": "Feature",
  "properties": {
    "iso:country":"DE",
    "sg:address":"Neu\u00f6ttinger Str. 2",
    "sg:city":"Alt\u00f6tting",
    "sg:phone":"+49 8671/6801",
    "sg:postcode":"84503",
    "sg:province":"Bayern",
    "wof:name":"Tilly-apotheke",
    "wof:placetype":"venue"
},
  "geometry": {"coordinates":[12.677576,48.22654],"type":"Point"}
}