{
  "type": "Feature",
  "properties": {
    "iso:country":"DE",
    "sg:address":"Kurstr. 1 D",
    "sg:city":"Berlin",
    "sg:phone":"+49 30/8039490",
    "sg:postcode":"14129",
    "sg:province":"Berlin",
    "wof:name":"Peter Lang",
    "wof:placetype":"venue"
},
  "geometry": {"coordinates":[13.2174911499,52.4298782349],"type":"Point"}
}