{
  "type": "Feature",
  "properties": {
    "iso:country":"DE",
    "sg:address":"Grafenberger Allee 87",
    "sg:city":"D\u00fcsseldorf",
    "sg:phone":"+49 211/669030",
    "sg:postcode":"40237",
    "sg:province":"Nordrhein-Westfalen",
    "wof:name":"Rautaruukki Holding Gmbh",
    "wof:placetype":"venue"
},
  "geometry": {"coordinates":[6.803196,51.23069],"type":"Point"}
}