{
  "type": "Feature",
  "properties": {
    "iso:country":"DE",
    "sg:address":"Bahnhofstr. 11",
    "sg:city":"Neukirchen",
    "sg:phone":"+49 6694/7027",
    "sg:postcode":"34626",
    "sg:province":"Hessen",
    "wof:name":"Molkereigenossenschaft Schwalm-aulatal Eg",
    "wof:placetype":"venue"
},
  "geometry": {"coordinates":[9.3446617126,50.8653335571],"type":"Point"}
}