{
  "type": "Feature",
  "properties": {
    "iso:country":"DE",
    "sg:address":"Dillinger Str. 1",
    "sg:city":"Dillingen",
    "sg:phone":"+49 6831/701770",
    "sg:postcode":"66763",
    "sg:province":"Saarland",
    "wof:name":"Prinzess Apotheken-bedarfshandlung",
    "wof:placetype":"venue"
},
  "geometry": {"coordinates":[6.7538142204,49.3689651489],"type":"Point"}
}