{
  "type": "Feature",
  "properties": {
    "iso:country":"DE",
    "sg:address":"Uthmannstr. 14",
    "sg:city":"Griesheim",
    "sg:phone":"+49 6155/62406",
    "sg:postcode":"64347",
    "sg:province":"Hessen",
    "wof:name":"Mohren-apotheke",
    "wof:placetype":"venue"
},
  "geometry": {"coordinates":[8.57687,49.856991],"type":"Point"}
}