{
  "type": "Feature",
  "properties": {
    "iso:country":"DE",
    "sg:address":"Oberrimbach 27",
    "sg:city":"Creglingen",
    "sg:phone":"+49 7939/363",
    "sg:postcode":"97993",
    "sg:province":"Baden-W\u00fcrttemberg",
    "wof:name":"G. Kellermann",
    "wof:placetype":"venue"
},
  "geometry": {"coordinates":[10.056785,49.409225],"type":"Point"}
}