{
  "type": "Feature",
  "properties": {
    "iso:country":"DE",
    "sg:address":"Industriestr. 34",
    "sg:city":"Bochum",
    "sg:phone":"+49 4923/492140",
    "sg:postcode":"44894",
    "sg:province":"Nordrhein-Westfalen",
    "wof:name":"Sch\u00dcrmann & Klagges Gmbh & Co Kg",
    "wof:placetype":"venue"
},
  "geometry": {"coordinates":[7.2917280197,51.4726257324],"type":"Point"}
}