{
  "type": "Feature",
  "properties": {
    "iso:country":"DE",
    "sg:address":"Mozartstr. 23",
    "sg:city":"Kempten",
    "sg:phone":"+49 831/22670",
    "sg:postcode":"87435",
    "sg:province":"Bayern",
    "wof:name":"Lohr",
    "wof:placetype":"venue"
},
  "geometry": {"coordinates":[10.311271,47.722561],"type":"Point"}
}