{
  "type": "Feature",
  "properties": {
    "iso:country":"DE",
    "sg:address":"Im Gewerbegebiet 8",
    "sg:city":"Horstmar",
    "sg:phone":"+49 2558/98936",
    "sg:postcode":"48612",
    "sg:province":"Nordrhein-Westfalen",
    "wof:name":"W & W",
    "wof:placetype":"venue"
},
  "geometry": {"coordinates":[7.306486,52.076782],"type":"Point"}
}