{
  "type": "Feature",
  "properties": {
    "iso:country":"DE",
    "sg:address":"Marienfelder Str. 45",
    "sg:city":"G\u00fctersloh",
    "sg:phone":"+49 5241/16293",
    "sg:postcode":"33330",
    "sg:province":"Nordrhein-Westfalen",
    "wof:name":"Burkhard Steuber",
    "wof:placetype":"venue"
},
  "geometry": {"coordinates":[8.3654279709,51.9131507874],"type":"Point"}
}