{
  "type": "Feature",
  "properties": {
    "iso:country":"DE",
    "sg:address":"Dessauer Str. 4",
    "sg:city":"Radegast",
    "sg:phone":"+49 34978/21469",
    "sg:postcode":"06369",
    "sg:province":"Sachsen-Anhalt",
    "wof:name":"Joachim Thormann",
    "wof:placetype":"venue"
},
  "geometry": {"coordinates":[12.094269,51.657902],"type":"Point"}
}