{
  "type": "Feature",
  "properties": {
    "iso:country":"DE",
    "sg:address":"Oscar-Wilde-Str. 5",
    "sg:city":"K\u00f6ln",
    "sg:phone":"+49 2234/76951",
    "sg:postcode":"50858",
    "sg:province":"Nordrhein-Westfalen",
    "wof:name":"F. A. Krause & Co.",
    "wof:placetype":"venue"
},
  "geometry": {"coordinates":[6.847886,50.942642],"type":"Point"}
}