{
  "type": "Feature",
  "properties": {
    "iso:country":"DE",
    "sg:address":"Fritz-Bender-Str. 3",
    "sg:city":"Edenkoben",
    "sg:phone":"+49 6323/4514",
    "sg:postcode":"67480",
    "sg:province":"Rheinland-Pfalz",
    "wof:name":"Gerhard Keller Ingenieur",
    "wof:placetype":"venue"
},
  "geometry": {"coordinates":[8.1208047867,49.2781524658],"type":"Point"}
}