{
  "type": "Feature",
  "properties": {
    "iso:country":"DE",
    "sg:address":"Zum B\u00fcrgerhaus 2c",
    "sg:city":"Mengerskirchen",
    "sg:phone":"+49 6476/8128",
    "sg:postcode":"35794",
    "sg:province":"Hessen",
    "wof:name":"Herbert Lein",
    "wof:placetype":"venue"
},
  "geometry": {"coordinates":[8.181095,50.549404],"type":"Point"}
}