{
  "type": "Feature",
  "properties": {
    "iso:country":"DE",
    "sg:address":"Lessingstrasse 12",
    "sg:city":"Halle",
    "sg:phone":"+49 345",
    "sg:postcode":"06114",
    "sg:province":"Sachsen-Anhalt",
    "wof:name":"H\u00f6ll-immobilien",
    "wof:placetype":"venue"
},
  "geometry": {"coordinates":[11.9783906937,51.4919433594],"type":"Point"}
}