{
  "type": "Feature",
  "properties": {
    "iso:country":"DE",
    "sg:address":"Markt 9",
    "sg:city":"Celle",
    "sg:phone":"+49 5141/25884",
    "sg:postcode":"29221",
    "sg:province":"Niedersachsen",
    "wof:name":"Adagio",
    "wof:placetype":"venue"
},
  "geometry": {"coordinates":[10.0817403793,52.6245002747],"type":"Point"}
}