{
  "type": "Feature",
  "properties": {
    "iso:country":"DE",
    "sg:address":"Am Ried 13",
    "sg:city":"Fulda",
    "sg:phone":"+49 661/57971",
    "sg:postcode":"36041",
    "sg:province":"Hessen",
    "wof:name":"Fuldaer Hof",
    "wof:placetype":"venue"
},
  "geometry": {"coordinates":[9.631901741,50.5637817383],"type":"Point"}
}