{
  "type": "Feature",
  "properties": {
    "iso:country":"DE",
    "sg:address":"Hauptstr. 83",
    "sg:city":"Nu\u00dfloch",
    "sg:phone":"+49 6224/12479",
    "sg:postcode":"69226",
    "sg:province":"Baden-W\u00fcrttemberg",
    "wof:name":"H. W. Zimmermann Finanzberater",
    "wof:placetype":"venue"
},
  "geometry": {"coordinates":[8.6957626343,49.3233566284],"type":"Point"}
}