{
  "type": "Feature",
  "properties": {
    "iso:country":"DE",
    "sg:address":"Glasbergweg 7",
    "sg:city":"Titisee-Neustadt",
    "sg:phone":"+49 7651/932599",
    "sg:postcode":"79822",
    "sg:province":"Baden-W\u00fcrttemberg",
    "wof:name":"Sound Magic Gmbh",
    "wof:placetype":"venue"
},
  "geometry": {"coordinates":[8.1838445663,47.9218482971],"type":"Point"}
}