{
  "type": "Feature",
  "properties": {
    "iso:country":"DE",
    "sg:address":"Wilhelmstr. 27",
    "sg:city":"T\u00fcbingen",
    "sg:phone":"+49 7071/2982365",
    "sg:postcode":"72074",
    "sg:province":"Baden-W\u00fcrttemberg",
    "wof:name":"Institut F\u00fcr Tropenmedizin",
    "wof:placetype":"venue"
},
  "geometry": {"coordinates":[9.0625247955,48.5273704529],"type":"Point"}
}