{
  "type": "Feature",
  "properties": {
    "iso:country":"DE",
    "sg:address":"Naheweinstr. 128",
    "sg:city":"Langenlonsheim",
    "sg:phone":"+49 6704/1256",
    "sg:postcode":"55450",
    "sg:province":"Rheinland-Pfalz",
    "wof:name":"Franz Reusch",
    "wof:placetype":"venue"
},
  "geometry": {"coordinates":[7.8991928101,49.8973045349],"type":"Point"}
}