{
  "type": "Feature",
  "properties": {
    "iso:country":"DE",
    "sg:address":"Hindelanger Str. 9",
    "sg:city":"Stuttgart",
    "sg:phone":"+49 711/332386",
    "sg:postcode":"70327",
    "sg:province":"Baden-W\u00fcrttemberg",
    "wof:name":"G\u00fcnter Kitzele",
    "wof:placetype":"venue"
},
  "geometry": {"coordinates":[9.2506408691,48.7826004028],"type":"Point"}
}