{
  "type": "Feature",
  "properties": {
    "iso:country":"DE",
    "sg:address":"Obere Kirchgasse 4",
    "sg:city":"Kitzingen",
    "sg:postcode":"97318",
    "sg:province":"Bayern",
    "wof:name":"High-yield-debentures: Extremely Effective Investm",
    "wof:placetype":"venue"
},
  "geometry": {"coordinates":[10.162527,49.739014],"type":"Point"}
}