{
  "type": "Feature",
  "properties": {
    "iso:country":"DE",
    "sg:address":"Wilhelmstr. 14",
    "sg:city":"T\u00fcbingen",
    "sg:phone":"+49 7071/27431",
    "sg:postcode":"72074",
    "sg:province":"Baden-W\u00fcrttemberg",
    "wof:name":"Seiden-magazin Hoch Gmbh",
    "wof:placetype":"venue"
},
  "geometry": {"coordinates":[9.05845,48.522404],"type":"Point"}
}