{
  "type": "Feature",
  "properties": {
    "iso:country":"DE",
    "sg:address":"Nicolaus-Siegen-Str. 15",
    "sg:city":"Erfurt",
    "sg:phone":"+49 361/2225311",
    "sg:postcode":"99092",
    "sg:province":"Th\u00fcringen",
    "wof:name":"Axel Metzner Rechtsanwalt",
    "wof:placetype":"venue"
},
  "geometry": {"coordinates":[11.0031070709,50.9700546265],"type":"Point"}
}