{
  "type": "Feature",
  "properties": {
    "iso:country":"DE",
    "sg:city":"Bad Bergzabern",
    "sg:phone":"+49 6343/7770",
    "sg:postcode":"76887",
    "sg:province":"Rheinland-Pfalz",
    "wof:name":"H. Attmann",
    "wof:placetype":"venue"
},
  "geometry": {"coordinates":[7.993538,49.099941],"type":"Point"}
}