{
  "type": "Feature",
  "properties": {
    "iso:country":"DE",
    "sg:address":"Scheideweg 100",
    "sg:city":"Oldenburg",
    "sg:phone":"+49 441/3046280",
    "sg:postcode":"26127",
    "sg:province":"Niedersachsen",
    "wof:name":"Martens",
    "wof:placetype":"venue"
},
  "geometry": {"coordinates":[8.2141141891,53.1675224304],"type":"Point"}
}