{
  "type": "Feature",
  "properties": {
    "iso:country":"DE",
    "sg:address":"Rosa-Luxemburg-Str. 8",
    "sg:city":"Wolmirstedt",
    "sg:phone":"+49 39201/21638",
    "sg:postcode":"39326",
    "sg:province":"Sachsen-Anhalt",
    "wof:name":"Frank K\u00fc\u00dfner",
    "wof:placetype":"venue"
},
  "geometry": {"coordinates":[11.6323051453,52.2505836487],"type":"Point"}
}