{
  "type": "Feature",
  "properties": {
    "iso:country":"DE",
    "sg:address":"Kiesweg 16",
    "sg:city":"Parsberg",
    "sg:phone":"+49 9492/5047",
    "sg:postcode":"92331",
    "sg:province":"Bayern",
    "wof:name":"Anna Baierl",
    "wof:placetype":"venue"
},
  "geometry": {"coordinates":[11.719223,49.16267],"type":"Point"}
}