{
  "type": "Feature",
  "properties": {
    "iso:country":"DE",
    "sg:address":"Heinrichstr. 2",
    "sg:city":"Bensheim",
    "sg:phone":"+49 6251/74155",
    "sg:postcode":"64625",
    "sg:province":"Hessen",
    "wof:name":"N\u00e4hmaschinen-service",
    "wof:placetype":"venue"
},
  "geometry": {"coordinates":[8.616815567,49.7027282715],"type":"Point"}
}