{
  "type": "Feature",
  "properties": {
    "iso:country":"DE",
    "sg:address":"Hauptstr. 25",
    "sg:city":"Rosengarten",
    "sg:phone":"+49 4108/6266",
    "sg:postcode":"21224",
    "sg:province":"Niedersachsen",
    "wof:name":"O. Westphal",
    "wof:placetype":"venue"
},
  "geometry": {"coordinates":[9.8868103027,53.4070167542],"type":"Point"}
}