{
  "type": "Feature",
  "properties": {
    "iso:country":"DE",
    "sg:address":"Uerdinger Str. 123-125",
    "sg:city":"Krefeld",
    "sg:phone":"+49 2151/23953",
    "sg:postcode":"47799",
    "sg:province":"Nordrhein-Westfalen",
    "wof:name":"Extra",
    "wof:placetype":"venue"
},
  "geometry": {"coordinates":[6.5789318085,51.336566925],"type":"Point"}
}