{
  "type": "Feature",
  "properties": {
    "iso:country":"DE",
    "sg:address":"Sch\u00f6nbergstr 23",
    "sg:city":"Ostfildern",
    "sg:phone":"+49 711/451280",
    "sg:postcode":"73760",
    "sg:province":"Baden-W\u00fcrttemberg",
    "wof:name":"M\u00fchlbrett Und Rapp Werbeagentur Gmbh",
    "wof:placetype":"venue"
},
  "geometry": {"coordinates":[9.227948,48.723839],"type":"Point"}
}