{
  "type": "Feature",
  "properties": {
    "iso:country":"DE",
    "sg:address":"Im Spring 24",
    "sg:city":"Velbert",
    "sg:phone":"+49 2052/961603",
    "sg:postcode":"42555",
    "sg:province":"Nordrhein-Westfalen",
    "wof:name":"R. Schenk Immobilienmakler",
    "wof:placetype":"venue"
},
  "geometry": {"coordinates":[7.1298890114,51.341758728],"type":"Point"}
}