{
  "type": "Feature",
  "properties": {
    "iso:country":"DE",
    "sg:address":"Pferdsbacher Weg",
    "sg:city":"B\u00fcdingen",
    "sg:phone":"+49 6042/96260",
    "sg:postcode":"63654",
    "sg:province":"Hessen",
    "wof:name":"Hellersche Druckerei Gmbh & Co.",
    "wof:placetype":"venue"
},
  "geometry": {"coordinates":[9.110225,50.293011],"type":"Point"}
}