{
  "type": "Feature",
  "properties": {
    "iso:country":"DE",
    "sg:address":"Mauserstr. 6",
    "sg:city":"Ludwigsburg",
    "sg:phone":"+49 7141/860520",
    "sg:postcode":"71640",
    "sg:province":"Baden-W\u00fcrttemberg",
    "wof:name":"Commdos Polsterm\u00f6bel Gmbh",
    "wof:placetype":"venue"
},
  "geometry": {"coordinates":[9.2355680466,48.8916778564],"type":"Point"}
}