{
  "type": "Feature",
  "properties": {
    "iso:country":"DE",
    "sg:address":"Golenz 29",
    "sg:city":"Gau\u00dfig",
    "sg:phone":"+49 35930/50779",
    "sg:postcode":"02633",
    "sg:province":"Sachsen",
    "wof:name":"Golenz",
    "wof:placetype":"venue"
},
  "geometry": {"coordinates":[14.308139801,51.1615905762],"type":"Point"}
}