{
  "type": "Feature",
  "properties": {
    "iso:country":"DE",
    "sg:address":"Dieselstr. 12",
    "sg:city":"Ober-M\u00f6rlen",
    "sg:phone":"+49 6002/92204",
    "sg:postcode":"61239",
    "sg:province":"Hessen",
    "wof:name":"W\u00f6ll Gmbh",
    "wof:placetype":"venue"
},
  "geometry": {"coordinates":[8.6952028275,50.3629875183],"type":"Point"}
}