{
  "type": "Feature",
  "properties": {
    "iso:country":"DE",
    "sg:address":"Katharinenstr. 4",
    "sg:city":"Kronberg",
    "sg:phone":"+49 6173/1266",
    "sg:postcode":"61476",
    "sg:province":"Hessen",
    "wof:name":"Mohamed Safainia Architekt",
    "wof:placetype":"venue"
},
  "geometry": {"coordinates":[8.510116,50.179134],"type":"Point"}
}