{
  "type": "Feature",
  "properties": {
    "iso:country":"DE",
    "sg:address":"Diedenhofener Str. 27",
    "sg:city":"Trier",
    "sg:postcode":"54294",
    "sg:province":"Rheinland-Pfalz",
    "wof:name":"Behindertenwerkstatt",
    "wof:placetype":"venue"
},
  "geometry": {"coordinates":[6.614249,49.729263],"type":"Point"}
}