{
  "type": "Feature",
  "properties": {
    "iso:country":"DE",
    "sg:address":"Park\u00e4ckerstr. 2",
    "sg:city":"Bietigheim-Bissingen",
    "sg:phone":"+49 7142/20508",
    "sg:postcode":"74321",
    "sg:province":"Baden-W\u00fcrttemberg",
    "wof:name":"Vereinsgastst\u00e4tte Bietigheimer Hockey- Und Tennis-club",
    "wof:placetype":"venue"
},
  "geometry": {"coordinates":[9.1528921127,48.9434127808],"type":"Point"}
}