{
  "type": "Feature",
  "properties": {
    "iso:country":"DE",
    "sg:address":"Bahnhofstr. 18 a",
    "sg:city":"Amberg",
    "sg:phone":"+49 9621/2912",
    "sg:postcode":"92224",
    "sg:province":"Bayern",
    "wof:name":"Gertraud Krau\u00df Masseuse",
    "wof:placetype":"venue"
},
  "geometry": {"coordinates":[11.861448,49.446609],"type":"Point"}
}