{
  "type": "Feature",
  "properties": {
    "iso:country":"DE",
    "sg:address":"Vorgebirgstr. 332",
    "sg:city":"K\u00f6ln",
    "sg:phone":"+49 221/364523",
    "sg:postcode":"50969",
    "sg:province":"Nordrhein-Westfalen",
    "wof:name":"Am Sender",
    "wof:placetype":"venue"
},
  "geometry": {"coordinates":[6.9451789856,50.9043922424],"type":"Point"}
}