{
  "type": "Feature",
  "properties": {
    "iso:country":"DE",
    "sg:address":"Am Holm 33",
    "sg:city":"Kronshagen",
    "sg:phone":"+49 431/582025",
    "sg:postcode":"24119",
    "sg:province":"Schleswig-Holstein",
    "wof:name":"G. P\u00f6tter Architekt",
    "wof:placetype":"venue"
},
  "geometry": {"coordinates":[10.078477,54.335548],"type":"Point"}
}