{
  "type": "Feature",
  "properties": {
    "iso:country":"DE",
    "sg:address":"Gamelbertstr. 18",
    "sg:city":"Stephansposching",
    "sg:phone":"+49 9931/2608",
    "sg:postcode":"94569",
    "sg:province":"Bayern",
    "wof:name":"Katholisches Pfarramt St. Michael",
    "wof:placetype":"venue"
},
  "geometry": {"coordinates":[12.8532190323,48.8042907715],"type":"Point"}
}