{
  "type": "Feature",
  "properties": {
    "iso:country":"DE",
    "sg:address":"Neud\u00f6rfler Str. 9",
    "sg:city":"Zwickau",
    "sg:postcode":"08062",
    "sg:province":"Sachsen",
    "wof:name":"St. Johanniskirche",
    "wof:placetype":"venue"
},
  "geometry": {"coordinates":[12.4781732559,50.692779541],"type":"Point"}
}