{
  "type": "Feature",
  "properties": {
    "iso:country":"DE",
    "sg:address":"Nr. 23",
    "sg:city":"Seelingst\u00e4dt/Th\u00fcringen",
    "sg:phone":"+49 4903/6608903",
    "sg:postcode":"07580",
    "sg:province":"Th\u00fcringen",
    "wof:name":"Korn-umwelttechnik Gmbh",
    "wof:placetype":"venue"
},
  "geometry": {"coordinates":[12.24437,50.772896],"type":"Point"}
}