{
  "type": "Feature",
  "properties": {
    "iso:country":"DE",
    "sg:address":"Briener Str. 46",
    "sg:city":"Kleve",
    "sg:phone":"+49 2821/980572",
    "sg:postcode":"47533",
    "sg:province":"Nordrhein-Westfalen",
    "wof:name":"Getr\u00e4nkesupermarkt Boland Kg",
    "wof:placetype":"venue"
},
  "geometry": {"coordinates":[6.146716,51.798485],"type":"Point"}
}