{
  "type": "Feature",
  "properties": {
    "iso:country":"DE",
    "sg:address":"Postfach 46",
    "sg:city":"Burg",
    "sg:postcode":"25710",
    "sg:province":"Brandenburg",
    "wof:name":"Leihb\u00fccherei",
    "wof:placetype":"venue"
},
  "geometry": {"coordinates":[9.26249,53.997429],"type":"Point"}
}