{
  "type": "Feature",
  "properties": {
    "iso:country":"DE",
    "sg:address":"Schersental 3",
    "sg:city":"Sondershausen",
    "sg:phone":"+49 3632/782866",
    "sg:postcode":"99706",
    "sg:province":"Th\u00fcringen",
    "wof:name":"R. Spie\u00df",
    "wof:placetype":"venue"
},
  "geometry": {"coordinates":[10.891086,51.374783],"type":"Point"}
}