{
  "type": "Feature",
  "properties": {
    "iso:country":"DE",
    "sg:address":"Zenettistr 43",
    "sg:city":"M\u00fcnchen",
    "sg:phone":"+49 89/7252011",
    "sg:postcode":"80337",
    "sg:province":"Bayern",
    "wof:name":"Muniger Martin Widmann Gmbh",
    "wof:placetype":"venue"
},
  "geometry": {"coordinates":[11.553495,48.125866],"type":"Point"}
}