{
  "type": "Feature",
  "properties": {
    "iso:country":"DE",
    "sg:address":"Am Gr\u00fcnland 4",
    "sg:city":"Augsburg",
    "sg:phone":"+49 821/703031",
    "sg:postcode":"86169",
    "sg:province":"Bayern",
    "wof:name":"Gruber Gmbh & Co. Kg",
    "wof:placetype":"venue"
},
  "geometry": {"coordinates":[10.902585,48.392319],"type":"Point"}
}