{
  "type": "Feature",
  "properties": {
    "iso:country":"DE",
    "sg:address":"Am Rottland 17",
    "sg:city":"Meinerzhagen",
    "sg:phone":"+49 2354/2217",
    "sg:postcode":"58540",
    "sg:province":"Nordrhein-Westfalen",
    "wof:name":"S. Heukelbach",
    "wof:placetype":"venue"
},
  "geometry": {"coordinates":[7.67945,51.093552],"type":"Point"}
}