{
  "type": "Feature",
  "properties": {
    "iso:country":"DE",
    "sg:address":"Buchenallee 7",
    "sg:city":"Anr\u00f6chte",
    "sg:postcode":"59609",
    "sg:province":"Nordrhein-Westfalen",
    "wof:name":"Walter Schencking Beteiligungsgesellschaft Mbh",
    "wof:placetype":"venue"
},
  "geometry": {"coordinates":[8.331154,51.551682],"type":"Point"}
}