{
  "type": "Feature",
  "properties": {
    "iso:country":"DE",
    "sg:address":"Frohsinnstr. 11 a",
    "sg:city":"Aschaffenburg",
    "sg:phone":"+49 6021/24523",
    "sg:postcode":"63739",
    "sg:province":"Bayern",
    "wof:name":"Vorwerk Elektrowerke Stiftung & Co. Kg",
    "wof:placetype":"venue"
},
  "geometry": {"coordinates":[9.1462631226,49.9788551331],"type":"Point"}
}