{
  "type": "Feature",
  "properties": {
    "iso:country":"DE",
    "sg:address":"Wachendorfer Str. 2 a",
    "sg:city":"Cadolzburg",
    "sg:phone":"+49 9103/7881",
    "sg:postcode":"90556",
    "sg:province":"Bayern",
    "wof:name":"Klaus Hoffmann",
    "wof:placetype":"venue"
},
  "geometry": {"coordinates":[10.859884,49.459129],"type":"Point"}
}