{
  "type": "Feature",
  "properties": {
    "iso:country":"DE",
    "sg:address":"Ernst-Ludwig-Str. 1",
    "sg:city":"Egelsbach",
    "sg:phone":"+49 6103/49683",
    "sg:postcode":"63329",
    "sg:province":"Hessen",
    "wof:name":"D. Sczesny",
    "wof:placetype":"venue"
},
  "geometry": {"coordinates":[8.661898613,49.9686698914],"type":"Point"}
}