{
  "type": "Feature",
  "properties": {
    "iso:country":"DE",
    "sg:address":"Heinkelstr 19-21",
    "sg:city":"Kirchheim",
    "sg:phone":"+49 7021/50740",
    "sg:postcode":"73230",
    "sg:province":"Baden-W\u00fcrttemberg",
    "wof:name":"Andritz Gmbh",
    "wof:placetype":"venue"
},
  "geometry": {"coordinates":[9.470132,48.640049],"type":"Point"}
}