{
  "type": "Feature",
  "properties": {
    "iso:country":"DE",
    "sg:address":"Poststr. 2",
    "sg:city":"Aue",
    "sg:postcode":"08280",
    "sg:province":"Sachsen",
    "wof:name":"Deutsche Telekom T-punkt",
    "wof:placetype":"venue"
},
  "geometry": {"coordinates":[12.7000904083,50.5879936218],"type":"Point"}
}