{
  "type": "Feature",
  "properties": {
    "iso:country":"DE",
    "sg:address":"Altestadt 13",
    "sg:city":"D\u00fcsseldorf",
    "sg:phone":"+49 211/328877",
    "sg:postcode":"40213",
    "sg:province":"Nordrhein-Westfalen",
    "wof:name":"K & M Kunst Und Material Gmbh",
    "wof:placetype":"venue"
},
  "geometry": {"coordinates":[6.7729301453,51.2288017273],"type":"Point"}
}