{
  "type": "Feature",
  "properties": {
    "iso:country":"DE",
    "sg:address":"Richard-Wagner-Str. 52",
    "sg:city":"Bobenheim-Roxheim",
    "sg:phone":"+49 6239/2675",
    "sg:postcode":"67240",
    "sg:province":"Rheinland-Pfalz",
    "wof:name":"August Vetter Steuerbevollm\u00e4chtigter",
    "wof:placetype":"venue"
},
  "geometry": {"coordinates":[8.3594360352,49.5897026062],"type":"Point"}
}