{
  "type": "Feature",
  "properties": {
    "iso:country":"DE",
    "sg:address":"Wiesenstr. 2",
    "sg:city":"Wedemark",
    "sg:phone":"+49 5131/52262",
    "sg:postcode":"30900",
    "sg:province":"Niedersachsen",
    "wof:name":"Adolf Lieke",
    "wof:placetype":"venue"
},
  "geometry": {"coordinates":[9.6236591339,52.5059661865],"type":"Point"}
}