{
  "type": "Feature",
  "properties": {
    "iso:country":"DE",
    "sg:address":"Hermann-M\u00fcller-Str. 3",
    "sg:city":"Georgsmarienh\u00fctte",
    "sg:phone":"+49 5401/1445",
    "sg:postcode":"49124",
    "sg:province":"Niedersachsen",
    "wof:name":"Thomas Haunhorst",
    "wof:placetype":"venue"
},
  "geometry": {"coordinates":[8.049672,52.20541],"type":"Point"}
}