{
  "type": "Feature",
  "properties": {
    "iso:country":"DE",
    "sg:address":"Am Leitzelbach 15",
    "sg:city":"Sinsheim",
    "sg:phone":"+49 7261/91610",
    "sg:postcode":"74889",
    "sg:province":"Baden-W\u00fcrttemberg",
    "wof:name":"Oktagon Kesselbau Gmbh",
    "wof:placetype":"venue"
},
  "geometry": {"coordinates":[8.8466444016,49.2495727539],"type":"Point"}
}