{
  "type": "Feature",
  "properties": {
    "iso:country":"DE",
    "sg:address":"Am Marktplatz 13",
    "sg:city":"Herrieden",
    "sg:phone":"+49 9825/633",
    "sg:postcode":"91567",
    "sg:province":"Bayern",
    "wof:name":"Sparkasse Feuchtwangen",
    "wof:placetype":"venue"
},
  "geometry": {"coordinates":[10.497477,49.233128],"type":"Point"}
}