{
  "type": "Feature",
  "properties": {
    "iso:country":"DE",
    "sg:address":"Baumberger Str. 48g",
    "sg:city":"Leverkusen",
    "sg:phone":"+49 214/24876",
    "sg:postcode":"51371",
    "sg:province":"Nordrhein-Westfalen",
    "wof:name":"Jugend-sprachreisen International E. V.",
    "wof:placetype":"venue"
},
  "geometry": {"coordinates":[6.9477448463,51.0593605042],"type":"Point"}
}