{
  "type": "Feature",
  "properties": {
    "iso:country":"DE",
    "sg:address":"Liebenaustr. 7",
    "sg:city":"Waldenbuch",
    "sg:phone":"+49 7157/20171",
    "sg:postcode":"71111",
    "sg:province":"Baden-W\u00fcrttemberg",
    "wof:name":"Ps Immobilien P. Schade",
    "wof:placetype":"venue"
},
  "geometry": {"coordinates":[9.1396636963,48.6430091858],"type":"Point"}
}