{
  "type": "Feature",
  "properties": {
    "iso:country":"DE",
    "sg:address":"Schiffswerft 5",
    "sg:city":"Neuderben",
    "sg:phone":"+49 4939/349280",
    "sg:postcode":"39317",
    "sg:province":"Sachsen-Anhalt",
    "wof:name":"Schiffswerft Bolle Gmbh",
    "wof:placetype":"venue"
},
  "geometry": {"coordinates":[11.984596,52.378235],"type":"Point"}
}