{
  "type": "Feature",
  "properties": {
    "iso:country":"DE",
    "sg:address":"Bierweg 13l",
    "sg:city":"Buxheim",
    "sg:phone":"+49 8458/9481",
    "sg:postcode":"85114",
    "sg:province":"Bayern",
    "wof:name":"Hildegard Und Roland Wenzel",
    "wof:placetype":"venue"
},
  "geometry": {"coordinates":[11.2954130173,48.8070716858],"type":"Point"}
}