{
  "type": "Feature",
  "properties": {
    "iso:country":"DE",
    "sg:address":"Kantstr. 14",
    "sg:city":"Trier",
    "sg:phone":"+49 651/86181",
    "sg:postcode":"54294",
    "sg:province":"Rheinland-Pfalz",
    "wof:name":"Stemper",
    "wof:placetype":"venue"
},
  "geometry": {"coordinates":[6.580472,49.720615],"type":"Point"}
}