{
  "type": "Feature",
  "properties": {
    "iso:country":"DE",
    "sg:address":"Sahlkamp 149",
    "sg:city":"Hannover",
    "sg:phone":"+49 511/908990",
    "sg:postcode":"30179",
    "sg:province":"Niedersachsen",
    "wof:name":"Gtu Ingenieurges. Mbh",
    "wof:placetype":"venue"
},
  "geometry": {"coordinates":[9.7604,52.410301],"type":"Point"}
}