{
  "type": "Feature",
  "properties": {
    "iso:country":"DE",
    "sg:address":"Bahnhofstr. -Ecke- Poststr.",
    "sg:city":"Andernach",
    "sg:phone":"+49 2632/494308",
    "sg:postcode":"56636",
    "sg:province":"Rheinland-Pfalz",
    "wof:name":"Fotostudio Elfriede M. Twardy",
    "wof:placetype":"venue"
},
  "geometry": {"coordinates":[-93.997169,47.446892],"type":"Point"}
}