{
  "type": "Feature",
  "properties": {
    "iso:country":"DE",
    "sg:address":"An der Weed",
    "sg:city":"Bad Homburg",
    "sg:phone":"+49 6172/21854",
    "sg:postcode":"61348",
    "sg:province":"Hessen",
    "wof:name":"Gerh. Gerecht Farben Und Lacke",
    "wof:placetype":"venue"
},
  "geometry": {"coordinates":[8.6101751328,50.2309989929],"type":"Point"}
}