{
  "type": "Feature",
  "properties": {
    "iso:country":"DE",
    "sg:address":"Kirchstr. 7",
    "sg:city":"Recklinghausen",
    "sg:phone":"+49 2361/81391",
    "sg:postcode":"45665",
    "sg:province":"Nordrhein-Westfalen",
    "wof:name":"Heinrich Freitag",
    "wof:placetype":"venue"
},
  "geometry": {"coordinates":[7.26212,51.611271],"type":"Point"}
}