{
  "type": "Feature",
  "properties": {
    "iso:country":"DE",
    "sg:address":"Zum Anger 4A",
    "sg:city":"Laatzen",
    "sg:postcode":"30880",
    "sg:province":"Niedersachsen",
    "wof:name":"Spangenberg Verm\u00f6gens- Verwaltung Gmbh & Co. Kg",
    "wof:placetype":"venue"
},
  "geometry": {"coordinates":[9.8388843536,52.2719268799],"type":"Point"}
}