{
  "type": "Feature",
  "properties": {
    "iso:country":"DE",
    "sg:address":"Erwitter Str. 21",
    "sg:city":"Geseke",
    "sg:phone":"+49 2942/3117",
    "sg:postcode":"59590",
    "sg:province":"Nordrhein-Westfalen",
    "wof:name":"H\u00fcttengrill",
    "wof:placetype":"venue"
},
  "geometry": {"coordinates":[8.5028600693,51.6360473633],"type":"Point"}
}