{
  "type": "Feature",
  "properties": {
    "iso:country":"DE",
    "sg:address":"R\u00f6derbergweg 118",
    "sg:city":"Frankfurt",
    "sg:phone":"+49 69/9674460",
    "sg:postcode":"60385",
    "sg:province":"Hessen",
    "wof:name":"Bolid Metallhandel Gmbh",
    "wof:placetype":"venue"
},
  "geometry": {"coordinates":[8.7110004425,50.1160011292],"type":"Point"}
}