{
  "type": "Feature",
  "properties": {
    "iso:country":"DE",
    "sg:address":"Bahnhofstr. 4",
    "sg:city":"Oberkirch",
    "sg:phone":"+49 7802/7760",
    "sg:postcode":"77704",
    "sg:province":"Baden-W\u00fcrttemberg",
    "wof:name":"Pizzeria La Fontana",
    "wof:placetype":"venue"
},
  "geometry": {"coordinates":[8.0784702301,48.530330658],"type":"Point"}
}