{
  "type": "Feature",
  "properties": {
    "iso:country":"DE",
    "sg:address":"Hauptstr.",
    "sg:city":"Geesow",
    "sg:phone":"+49 33333/484",
    "sg:postcode":"16307",
    "sg:province":"Brandenburg",
    "wof:name":"Gasthof Zur Eiche",
    "wof:placetype":"venue"
},
  "geometry": {"coordinates":[14.3789777756,53.2542037964],"type":"Point"}
}