{
  "type": "Feature",
  "properties": {
    "iso:country":"DE",
    "sg:address":"Weberstr. 13",
    "sg:city":"Radebeul",
    "sg:phone":"+49 351/8301478",
    "sg:postcode":"01445",
    "sg:province":"Sachsen",
    "wof:name":"Arno Herrmann",
    "wof:placetype":"venue"
},
  "geometry": {"coordinates":[13.668739,51.110062],"type":"Point"}
}