{
  "type": "Feature",
  "properties": {
    "iso:country":"DE",
    "sg:address":"Wittener Str. 328",
    "sg:city":"Dortmund",
    "sg:phone":"+49 231/178689",
    "sg:postcode":"44149",
    "sg:province":"Nordrhein-Westfalen",
    "wof:name":"Kreta-grill Gmbh",
    "wof:placetype":"venue"
},
  "geometry": {"coordinates":[7.4044451714,51.4968948364],"type":"Point"}
}