{
  "type": "Feature",
  "properties": {
    "iso:country":"DE",
    "sg:address":"Ringstr. 13",
    "sg:city":"Limbach",
    "sg:phone":"+49 6287/1049",
    "sg:postcode":"74838",
    "sg:province":"Baden-W\u00fcrttemberg",
    "wof:name":"Alise Und Otto Kohl Foto",
    "wof:placetype":"venue"
},
  "geometry": {"coordinates":[9.2090415955,49.4607009888],"type":"Point"}
}