{
  "type": "Feature",
  "properties": {
    "iso:country":"DE",
    "sg:address":"Drachenfelsstr. 1",
    "sg:city":"K\u00f6nigswinter",
    "sg:phone":"+49 2223/23259",
    "sg:postcode":"53639",
    "sg:province":"Nordrhein-Westfalen",
    "wof:name":"Weinhaus Lemmerz",
    "wof:placetype":"venue"
},
  "geometry": {"coordinates":[7.1925601959,50.6736412048],"type":"Point"}
}