{
  "type": "Feature",
  "properties": {
    "iso:country":"DE",
    "sg:address":"Zeppelinring 25",
    "sg:city":"M\u00fchlheim",
    "sg:phone":"+49 6108/72099",
    "sg:postcode":"63165",
    "sg:province":"Hessen",
    "wof:name":"Righetti Teigwaren Gmbh",
    "wof:placetype":"venue"
},
  "geometry": {"coordinates":[8.845705986,50.1137046814],"type":"Point"}
}