{
  "type": "Feature",
  "properties": {
    "iso:country":"DE",
    "sg:address":"Albrecht-D\u00fcrer-Weg 17",
    "sg:city":"Leipzig",
    "sg:phone":"+49 341/2512950",
    "sg:postcode":"04328",
    "sg:province":"Sachsen",
    "wof:name":"Gerd Bardehle Rechtsanwalt",
    "wof:placetype":"venue"
},
  "geometry": {"coordinates":[12.4617881775,51.3488273621],"type":"Point"}
}