{
  "type": "Feature",
  "properties": {
    "iso:country":"DE",
    "sg:address":"Am Waldhang 3",
    "sg:city":"Buch",
    "sg:phone":"+49 8709/1654",
    "sg:postcode":"84172",
    "sg:province":"Bayern",
    "wof:name":"Rainer Kriegenhofer",
    "wof:placetype":"venue"
},
  "geometry": {"coordinates":[12.0245838165,48.4546203613],"type":"Point"}
}