{
  "type": "Feature",
  "properties": {
    "iso:country":"DE",
    "sg:address":"Friedrichstr. 46",
    "sg:city":"Gro\u00df-Gerau",
    "sg:phone":"+49 6152/7028",
    "sg:postcode":"64521",
    "sg:province":"Hessen",
    "wof:name":"Wilhelm Herrmann",
    "wof:placetype":"venue"
},
  "geometry": {"coordinates":[8.487841,49.917953],"type":"Point"}
}