{
  "type": "Feature",
  "properties": {
    "iso:country":"DE",
    "sg:address":"Bahnhofstra\u00dfe 22",
    "sg:city":"Neu Wulmstorf",
    "sg:phone":"+49 40/79688414",
    "sg:postcode":"21629",
    "sg:province":"Niedersachsen",
    "wof:name":"Ihr Wasserbetten Studio",
    "wof:placetype":"venue"
},
  "geometry": {"coordinates":[9.7937068939,53.4660453796],"type":"Point"}
}