{
  "type": "Feature",
  "properties": {
    "iso:country":"DE",
    "sg:address":"Hohe Luft 7",
    "sg:city":"Sittensen",
    "sg:phone":"+49 4282/5370",
    "sg:postcode":"27419",
    "sg:province":"Niedersachsen",
    "wof:name":"Lafrenz & Sohn Gbr Heizungsservice & Wartung",
    "wof:placetype":"venue"
},
  "geometry": {"coordinates":[9.5151786804,53.2895469666],"type":"Point"}
}