{
  "type": "Feature",
  "properties": {
    "iso:country":"DE",
    "sg:address":"Augustastr. 17",
    "sg:city":"K\u00f6ln",
    "sg:phone":"+49 221/612230",
    "sg:postcode":"51065",
    "sg:province":"Nordrhein-Westfalen",
    "wof:name":"Computer Terminal Service Meermeyer Kg",
    "wof:placetype":"venue"
},
  "geometry": {"coordinates":[7.0103731155,50.9569282532],"type":"Point"}
}