{
  "type": "Feature",
  "properties": {
    "iso:country":"DE",
    "sg:address":"Galgenstieg 2 a",
    "sg:city":"H\u00f6xter",
    "sg:phone":"+49 5271/32948",
    "sg:postcode":"37671",
    "sg:province":"Nordrhein-Westfalen",
    "wof:name":"Sabine Fiege",
    "wof:placetype":"venue"
},
  "geometry": {"coordinates":[9.35742,51.773628],"type":"Point"}
}