{
  "type": "Feature",
  "properties": {
    "iso:country":"DE",
    "sg:address":"Schwarzer Weg 11",
    "sg:city":"Kaarst",
    "sg:phone":"+49 2131/668457",
    "sg:postcode":"41564",
    "sg:province":"Nordrhein-Westfalen",
    "wof:name":"K. Jensen Rechtsanwalt",
    "wof:placetype":"venue"
},
  "geometry": {"coordinates":[6.605173111,51.2215538025],"type":"Point"}
}