{
  "type": "Feature",
  "properties": {
    "iso:country":"DE",
    "sg:address":"M\u00fcnsterstr. 5",
    "sg:city":"Hamburg",
    "sg:phone":"+49 40/5533060",
    "sg:postcode":"22529",
    "sg:province":"Hamburg",
    "wof:name":"Gms Gestaltung Mit Sicherheit",
    "wof:placetype":"venue"
},
  "geometry": {"coordinates":[9.9581804276,53.5996856689],"type":"Point"}
}