{
  "type": "Feature",
  "properties": {
    "iso:country":"DE",
    "sg:address":"Am Elzdamm 44",
    "sg:city":"Emmendingen",
    "sg:phone":"+49 4976/4148530",
    "sg:postcode":"79312",
    "sg:province":"Baden-W\u00fcrttemberg",
    "wof:name":"Haltrans Transport Gmbh",
    "wof:placetype":"venue"
},
  "geometry": {"coordinates":[7.8282899857,48.1262016296],"type":"Point"}
}