{
  "type": "Feature",
  "properties": {
    "iso:country":"DE",
    "sg:address":"Olgastr. 1",
    "sg:city":"M\u00fcnchen",
    "sg:phone":"+49 89/1231784",
    "sg:postcode":"80636",
    "sg:province":"Bayern",
    "wof:name":"Monika Appel",
    "wof:placetype":"venue"
},
  "geometry": {"coordinates":[11.541317,48.151707],"type":"Point"}
}