{
  "type": "Feature",
  "properties": {
    "iso:country":"DE",
    "sg:address":"Bielefelder Str. 23",
    "sg:city":"Hilter",
    "sg:phone":"+49 5424/3458",
    "sg:postcode":"49176",
    "sg:province":"Niedersachsen",
    "wof:name":"H. Lindner Masseur",
    "wof:placetype":"venue"
},
  "geometry": {"coordinates":[8.148561,52.135822],"type":"Point"}
}