{
  "type": "Feature",
  "properties": {
    "iso:country":"DE",
    "sg:address":"Nierenhofer Str. 188 a",
    "sg:city":"Velbert",
    "sg:postcode":"42555",
    "sg:province":"Nordrhein-Westfalen",
    "wof:name":"Stuckart Gmbh",
    "wof:placetype":"venue"
},
  "geometry": {"coordinates":[7.12636,51.36792],"type":"Point"}
}