{
  "type": "Feature",
  "properties": {
    "iso:country":"DE",
    "sg:address":"Sonnenstr. 3",
    "sg:city":"Niederkirchen",
    "sg:phone":"+49 6363/5177",
    "sg:postcode":"67700",
    "sg:province":"Rheinland-Pfalz",
    "wof:name":"Kurt Mildenberger",
    "wof:placetype":"venue"
},
  "geometry": {"coordinates":[7.687645,49.577812],"type":"Point"}
}