{
  "type": "Feature",
  "properties": {
    "iso:country":"DE",
    "sg:address":"Auricher Landstr.",
    "sg:city":"Gro\u00dfefehn",
    "sg:phone":"+49 4943/1575",
    "sg:postcode":"26629",
    "sg:province":"Niedersachsen",
    "wof:name":"Aral Ag",
    "wof:placetype":"venue"
},
  "geometry": {"coordinates":[7.5855350494,53.3721694946],"type":"Point"}
}