{
  "type": "Feature",
  "properties": {
    "iso:country":"DE",
    "sg:address":"Am Kurpark 16",
    "sg:city":"Garmisch-Partenkirchen",
    "sg:phone":"+49 8821/55550",
    "sg:postcode":"82467",
    "sg:province":"Bayern",
    "wof:name":"St. Martins-apotheke Inh. Jan Weimar E. K.",
    "wof:placetype":"venue"
},
  "geometry": {"coordinates":[11.089397,47.493706],"type":"Point"}
}