{
  "type": "Feature",
  "properties": {
    "iso:country":"DE",
    "sg:address":"M\u00fchlweg 1",
    "sg:city":"Bauda",
    "sg:phone":"+49 3522/38541",
    "sg:postcode":"01561",
    "sg:province":"Sachsen",
    "wof:name":"Agrargenossenschaft Bauda Eg",
    "wof:placetype":"venue"
},
  "geometry": {"coordinates":[13.631883,51.289631],"type":"Point"}
}