{
  "type": "Feature",
  "properties": {
    "iso:country":"DE",
    "sg:address":"Robert-Koch-Str. 50",
    "sg:city":"Stuttgart",
    "sg:phone":"+49 711/7351370",
    "sg:postcode":"70563",
    "sg:province":"Baden-W\u00fcrttemberg",
    "wof:name":"Gaese Gmbh",
    "wof:placetype":"venue"
},
  "geometry": {"coordinates":[9.1073274612,48.7256317139],"type":"Point"}
}