{
  "type": "Feature",
  "properties": {
    "iso:country":"DE",
    "sg:address":"Mindener Str. 87",
    "sg:city":"Bad Oeynhausen",
    "sg:phone":"+49 5731/26187",
    "sg:postcode":"32547",
    "sg:province":"Nordrhein-Westfalen",
    "wof:name":"W. Guder",
    "wof:placetype":"venue"
},
  "geometry": {"coordinates":[8.814906,52.21254],"type":"Point"}
}