{
  "type": "Feature",
  "properties": {
    "iso:country":"DE",
    "sg:address":"Valleystr. 36",
    "sg:city":"M\u00fcnchen",
    "sg:phone":"+49 89/7256679",
    "sg:postcode":"81371",
    "sg:province":"Bayern",
    "wof:name":"Hel Und Jens Haparta Architekten",
    "wof:placetype":"venue"
},
  "geometry": {"coordinates":[11.546318,48.117363],"type":"Point"}
}