{
  "type": "Feature",
  "properties": {
    "iso:country":"DE",
    "sg:address":"Marktplatz 4",
    "sg:city":"Lam",
    "sg:phone":"+49 9943/1350",
    "sg:postcode":"93462",
    "sg:province":"Bayern",
    "wof:name":"Gasthaus Zum Dimpfelstadl Alois Lemberger",
    "wof:placetype":"venue"
},
  "geometry": {"coordinates":[13.0497093201,49.1979904175],"type":"Point"}
}