{
  "type": "Feature",
  "properties": {
    "iso:country":"DE",
    "sg:address":"Berlinerstra\u00dfe 10",
    "sg:city":"Gera",
    "sg:postcode":"07545",
    "sg:province":"Th\u00fcringen",
    "wof:name":"Christian Hennig",
    "wof:placetype":"venue"
},
  "geometry": {"coordinates":[12.0832595825,50.8836631775],"type":"Point"}
}