{
  "type": "Feature",
  "properties": {
    "iso:country":"DE",
    "sg:address":"Leininger Str. 53",
    "sg:city":"Bobenheim am Berg",
    "sg:phone":"+49 6353/8706",
    "sg:postcode":"67273",
    "sg:province":"Rheinland-Pfalz",
    "wof:name":"Alois Nahstoll Weinanbau",
    "wof:placetype":"venue"
},
  "geometry": {"coordinates":[8.1476869583,49.5227127075],"type":"Point"}
}