{
  "type": "Feature",
  "properties": {
    "iso:country":"DE",
    "sg:address":"Brecherspitzstr. 8",
    "sg:city":"M\u00fcnchen",
    "sg:phone":"+49 89/62001458",
    "sg:postcode":"81541",
    "sg:province":"Bayern",
    "wof:name":"Ingenieurb\u00fcro Karl Strasser",
    "wof:placetype":"venue"
},
  "geometry": {"coordinates":[11.589469,48.115612],"type":"Point"}
}