{
  "type": "Feature",
  "properties": {
    "iso:country":"DE",
    "sg:address":"M\u00f6rikeweg 23",
    "sg:city":"Bovenden",
    "sg:phone":"+49 551/83763",
    "sg:postcode":"37120",
    "sg:province":"Niedersachsen",
    "wof:name":"Claus-peter Siebert",
    "wof:placetype":"venue"
},
  "geometry": {"coordinates":[9.9361162186,51.5973815918],"type":"Point"}
}