{
  "type": "Feature",
  "properties": {
    "iso:country":"DE",
    "sg:address":"Moselpromenade 7",
    "sg:city":"Cochem",
    "sg:postcode":"56812",
    "sg:province":"Rheinland-Pfalz",
    "wof:name":"Pm-kommunikation E. K.",
    "wof:placetype":"venue"
},
  "geometry": {"coordinates":[7.166771,50.146431],"type":"Point"}
}