{
  "type": "Feature",
  "properties": {
    "iso:country":"DE",
    "sg:address":"Theodor-Kr\u00fcger-Stra\u00dfe 6 a",
    "sg:city":"Hannover",
    "sg:phone":"+49 30",
    "sg:postcode":"30167",
    "sg:province":"Niedersachsen",
    "wof:name":"Document Manufacturing",
    "wof:placetype":"venue"
},
  "geometry": {"coordinates":[9.718429,52.37468],"type":"Point"}
}