{
  "type": "Feature",
  "properties": {
    "iso:country":"DE",
    "sg:address":"J\u00fclicher Str. 8",
    "sg:city":"J\u00fcchen",
    "sg:phone":"+49 2165/7450",
    "sg:postcode":"41363",
    "sg:province":"Nordrhein-Westfalen",
    "wof:name":"F.-j. Bienefeld",
    "wof:placetype":"venue"
},
  "geometry": {"coordinates":[6.50045,51.098438],"type":"Point"}
}