{
  "type": "Feature",
  "properties": {
    "iso:country":"DE",
    "sg:address":"Fischerkoppel 9",
    "sg:city":"Eckernf\u00f6rde",
    "sg:phone":"+49 4351/85373",
    "sg:postcode":"24340",
    "sg:province":"Schleswig-Holstein",
    "wof:name":"Ulrike Piening Praxis F\u00fcr Krankengymnastik",
    "wof:placetype":"venue"
},
  "geometry": {"coordinates":[9.835883,54.47802],"type":"Point"}
}