{
  "type": "Feature",
  "properties": {
    "iso:country":"DE",
    "sg:address":"Heideweg 21",
    "sg:city":"Hennigsdorf",
    "sg:phone":"+49 3302/34634",
    "sg:postcode":"16761",
    "sg:province":"Brandenburg",
    "wof:name":"Goral",
    "wof:placetype":"venue"
},
  "geometry": {"coordinates":[13.197316,52.64333],"type":"Point"}
}