{
  "type": "Feature",
  "properties": {
    "iso:country":"DE",
    "sg:address":"Neue Pforte 42",
    "sg:city":"Neu-Anspach",
    "sg:phone":"+49 6081/8841",
    "sg:postcode":"61267",
    "sg:province":"Hessen",
    "wof:name":"Klaus St\u00f6rkel",
    "wof:placetype":"venue"
},
  "geometry": {"coordinates":[8.504023,50.293289],"type":"Point"}
}