{
  "type": "Feature",
  "properties": {
    "iso:country":"DE",
    "sg:address":"Berliner Allee 38-44",
    "sg:city":"Norderstedt",
    "sg:phone":"+49 40/5343600",
    "sg:postcode":"22850",
    "sg:province":"Schleswig-Holstein",
    "wof:name":"Adac Reiseb\u00fcro",
    "wof:placetype":"venue"
},
  "geometry": {"coordinates":[9.9844331741,53.6848602295],"type":"Point"}
}