{
  "type": "Feature",
  "properties": {
    "iso:country":"DE",
    "sg:address":"Rappen",
    "sg:city":"Unteregg",
    "sg:phone":"+49 8269/565",
    "sg:postcode":"87782",
    "sg:province":"Bayern",
    "wof:name":"F. Simon",
    "wof:placetype":"venue"
},
  "geometry": {"coordinates":[10.443685,47.925175],"type":"Point"}
}