{
  "type": "Feature",
  "properties": {
    "iso:country":"DE",
    "sg:address":"Engelsdorfer Str. 8",
    "sg:city":"Leipzig",
    "sg:postcode":"04316",
    "sg:province":"Sachsen",
    "wof:name":"Cegelec Sunvic Enginee- Ring Und Installation Gmbh",
    "wof:placetype":"venue"
},
  "geometry": {"coordinates":[12.4324321747,51.3308029175],"type":"Point"}
}