{
  "type": "Feature",
  "properties": {
    "iso:country":"DE",
    "sg:address":"Feldstr. 67",
    "sg:city":"Ratingen",
    "sg:phone":"+49 2102/841119",
    "sg:postcode":"40882",
    "sg:province":"Nordrhein-Westfalen",
    "wof:name":"Andreas Eichler",
    "wof:placetype":"venue"
},
  "geometry": {"coordinates":[6.872589,51.300568],"type":"Point"}
}