{
  "type": "Feature",
  "properties": {
    "iso:country":"DE",
    "sg:address":"Linzer Weg 6",
    "sg:city":"Thiendorf",
    "sg:phone":"+49 35755/50557",
    "sg:postcode":"01561",
    "sg:province":"Sachsen",
    "wof:name":"J\u00fcrgen Hansel",
    "wof:placetype":"venue"
},
  "geometry": {"coordinates":[13.7695293427,51.3425216675],"type":"Point"}
}