{
  "type": "Feature",
  "properties": {
    "iso:country":"DE",
    "sg:address":"An der Lohm\u00fchle 16",
    "sg:city":"Ober-M\u00f6rlen",
    "sg:phone":"+49 6002/6012",
    "sg:postcode":"61239",
    "sg:province":"Hessen",
    "wof:name":"J.h. Wagner",
    "wof:placetype":"venue"
},
  "geometry": {"coordinates":[8.687365,50.373352],"type":"Point"}
}