{
  "type": "Feature",
  "properties": {
    "iso:country":"DE",
    "sg:address":"Lerchenfeldstr. 21",
    "sg:city":"Willich",
    "sg:phone":"+49 2156/40055",
    "sg:postcode":"47877",
    "sg:province":"Nordrhein-Westfalen",
    "wof:name":"Johann L\u00fcpertz Steuerberater",
    "wof:placetype":"venue"
},
  "geometry": {"coordinates":[6.4617948532,51.2809257507],"type":"Point"}
}