{
  "type": "Feature",
  "properties": {
    "iso:country":"DE",
    "sg:address":"Schulstr. 39",
    "sg:city":"Oldenburg",
    "sg:phone":"+49 441/201334",
    "sg:postcode":"26135",
    "sg:province":"Niedersachsen",
    "wof:name":"Gastst\u00e4tte Henning Barkemeyer",
    "wof:placetype":"venue"
},
  "geometry": {"coordinates":[8.2362098694,53.1351509094],"type":"Point"}
}