{
  "type": "Feature",
  "properties": {
    "iso:country":"DE",
    "sg:address":"Metzer Str. 62",
    "sg:city":"Regensburg",
    "sg:phone":"+49 941/61253",
    "sg:postcode":"93057",
    "sg:province":"Bayern",
    "wof:name":"Gerda Keller",
    "wof:placetype":"venue"
},
  "geometry": {"coordinates":[12.13013,49.044182],"type":"Point"}
}