{
  "type": "Feature",
  "properties": {
    "iso:country":"DE",
    "sg:address":"Allee 65",
    "sg:city":"H\u00f6velhof",
    "sg:phone":"+49 5257/3382",
    "sg:postcode":"33161",
    "sg:province":"Nordrhein-Westfalen",
    "wof:name":"Bernhard Poll",
    "wof:placetype":"venue"
},
  "geometry": {"coordinates":[8.6554088593,51.8189697266],"type":"Point"}
}