{
  "type": "Feature",
  "properties": {
    "iso:country":"DE",
    "sg:address":"Carl-von-Linde-Str. 40",
    "sg:city":"Unterschlei\u00dfheim",
    "sg:phone":"+49 89/32147711",
    "sg:postcode":"85716",
    "sg:province":"Bayern",
    "wof:name":"Christian Kiessling Rechtsanwalt",
    "wof:placetype":"venue"
},
  "geometry": {"coordinates":[11.5673980713,48.2806663513],"type":"Point"}
}