{
  "type": "Feature",
  "properties": {
    "iso:country":"DE",
    "sg:address":"R\u00e4terstr. 17",
    "sg:city":"Kirchheim",
    "sg:phone":"+49 89/9032862",
    "sg:postcode":"85551",
    "sg:province":"Bayern",
    "wof:name":"Holiday Land Panorama Reisen Gmbh",
    "wof:placetype":"venue"
},
  "geometry": {"coordinates":[11.7577180862,48.1639442444],"type":"Point"}
}