{
  "type": "Feature",
  "properties": {
    "iso:country":"DE",
    "sg:address":"Maximilianstr. 41",
    "sg:city":"Wunsiedel",
    "sg:phone":"+49 9232/2139",
    "sg:postcode":"95632",
    "sg:province":"Bayern",
    "wof:name":"Heinz Petzold Drogerie",
    "wof:placetype":"venue"
},
  "geometry": {"coordinates":[12.003827,50.038364],"type":"Point"}
}