{
  "type": "Feature",
  "properties": {
    "iso:country":"DE",
    "sg:address":"Klecker Waldstr. 464 A",
    "sg:city":"Bendestorf",
    "sg:postcode":"21227",
    "sg:province":"Niedersachsen",
    "wof:name":"Fink Film Horst R. Fink Erben",
    "wof:placetype":"venue"
},
  "geometry": {"coordinates":[9.9582500458,53.3424491882],"type":"Point"}
}