{
  "type": "Feature",
  "properties": {
    "iso:country":"DE",
    "sg:address":"Kuttelgasse 12",
    "sg:city":"Memmingen",
    "sg:phone":"+49 8331/5243",
    "sg:postcode":"87700",
    "sg:province":"Bayern",
    "wof:name":"Ehrenfeuchter Gmbh",
    "wof:placetype":"venue"
},
  "geometry": {"coordinates":[10.1835546494,47.984462738],"type":"Point"}
}