{
  "type": "Feature",
  "properties": {
    "iso:country":"DE",
    "sg:address":"Marktplatz 2",
    "sg:city":"Blaustein",
    "sg:phone":"+49 7304/7001",
    "sg:postcode":"89134",
    "sg:province":"Baden-W\u00fcrttemberg",
    "wof:name":"Red. Blausteiner Nachrichten Av B\u00fcrgermeisteramt",
    "wof:placetype":"venue"
},
  "geometry": {"coordinates":[9.9199800491,48.415397644],"type":"Point"}
}