{
  "type": "Feature",
  "properties": {
    "iso:country":"DE",
    "sg:address":"Engelweg 5",
    "sg:city":"Waldbr\u00f6l",
    "sg:phone":"+49 2291/5934",
    "sg:postcode":"51545",
    "sg:province":"Nordrhein-Westfalen",
    "wof:name":"B. Mihalic",
    "wof:placetype":"venue"
},
  "geometry": {"coordinates":[7.6185159683,50.8729782104],"type":"Point"}
}