{
  "type": "Feature",
  "properties": {
    "iso:country":"DE",
    "sg:address":"Wendenhof 7",
    "sg:city":"Kreuztal",
    "sg:phone":"+49 2732/89630",
    "sg:postcode":"57223",
    "sg:province":"Nordrhein-Westfalen",
    "wof:name":"Spedition Gerhard Siebel Gmbh",
    "wof:placetype":"venue"
},
  "geometry": {"coordinates":[7.9730138779,50.9778213501],"type":"Point"}
}