{
  "type": "Feature",
  "properties": {
    "iso:country":"DE",
    "sg:address":"Bachstr. 4",
    "sg:city":"Bad W\u00f6rishofen",
    "sg:phone":"+49 8247/2099",
    "sg:postcode":"86825",
    "sg:province":"Bayern",
    "wof:name":"G\u00e4stehaus F\u00f6hling",
    "wof:placetype":"venue"
},
  "geometry": {"coordinates":[10.5910320282,48.0027770996],"type":"Point"}
}