{
  "type": "Feature",
  "properties": {
    "iso:country":"DE",
    "sg:address":"Wachsbleiche 30",
    "sg:city":"Osnabr\u00fcck",
    "sg:phone":"+49 541/683023",
    "sg:postcode":"49088",
    "sg:province":"Niedersachsen",
    "wof:name":"L. Pipereit",
    "wof:placetype":"venue"
},
  "geometry": {"coordinates":[8.0390701294,52.2860717773],"type":"Point"}
}