{
  "type": "Feature",
  "properties": {
    "iso:country":"DE",
    "sg:address":"Auf der G\u00fcnne 5",
    "sg:city":"Lehre",
    "sg:phone":"+49 5308/6409",
    "sg:postcode":"38165",
    "sg:province":"Niedersachsen",
    "wof:name":"Gebhard H\u00f6fer",
    "wof:placetype":"venue"
},
  "geometry": {"coordinates":[10.6740121841,52.3363075256],"type":"Point"}
}