{
  "type": "Feature",
  "properties": {
    "iso:country":"DE",
    "sg:address":"G\u00f6ttlishofen",
    "sg:city":"Argenb\u00fchl",
    "sg:phone":"+49 7566/456",
    "sg:postcode":"88260",
    "sg:province":"Baden-W\u00fcrttemberg",
    "wof:name":"Theobald Matt Schmiede",
    "wof:placetype":"venue"
},
  "geometry": {"coordinates":[9.948249,47.714001],"type":"Point"}
}