{
  "type": "Feature",
  "properties": {
    "iso:country":"DE",
    "sg:address":"J\u00e4gerstieg 11",
    "sg:city":"Bad Harzburg",
    "sg:phone":"+49 5322/6531",
    "sg:postcode":"38667",
    "sg:province":"Niedersachsen",
    "wof:name":"Junicke & Bening Gmbh & Co.",
    "wof:placetype":"venue"
},
  "geometry": {"coordinates":[10.56638,51.886627],"type":"Point"}
}