{
  "type": "Feature",
  "properties": {
    "iso:country":"DE",
    "sg:address":"Bendenstr. 34",
    "sg:city":"Stolberg",
    "sg:phone":"+49 2402/766525",
    "sg:postcode":"52223",
    "sg:province":"Nordrhein-Westfalen",
    "wof:name":"Kbm Hochbau Gmbh",
    "wof:placetype":"venue"
},
  "geometry": {"coordinates":[6.2115187645,50.7279205322],"type":"Point"}
}