{
  "type": "Feature",
  "properties": {
    "iso:country":"DE",
    "sg:address":"Bahnhofstr. 34",
    "sg:city":"Tantow",
    "sg:phone":"+49 33333/54410",
    "sg:postcode":"16307",
    "sg:province":"Brandenburg",
    "wof:name":"Freund Und Partner Gmbh",
    "wof:placetype":"venue"
},
  "geometry": {"coordinates":[14.3497829437,53.2698669434],"type":"Point"}
}