{
  "type": "Feature",
  "properties": {
    "iso:country":"DE",
    "sg:address":"Kaiserpassage 7",
    "sg:city":"Reutlingen",
    "sg:phone":"+49 7121/321518",
    "sg:postcode":"72764",
    "sg:province":"Baden-W\u00fcrttemberg",
    "wof:name":"Dr. Paul Irion Rechtsanwalt",
    "wof:placetype":"venue"
},
  "geometry": {"coordinates":[9.2113246918,48.4964790344],"type":"Point"}
}