{
  "type": "Feature",
  "properties": {
    "iso:country":"DE",
    "sg:address":"Kaspar-Kerll-Str. 47",
    "sg:city":"M\u00fcnchen",
    "sg:phone":"+49 89/887333",
    "sg:postcode":"81245",
    "sg:province":"Bayern",
    "wof:name":"Sibelius-apotheke",
    "wof:placetype":"venue"
},
  "geometry": {"coordinates":[11.470188,48.154545],"type":"Point"}
}