{
  "type": "Feature",
  "properties": {
    "iso:country":"DE",
    "sg:address":"Eschelbronner Str. 15",
    "sg:city":"Meckesheim",
    "sg:phone":"+49 6226/1205",
    "sg:postcode":"74909",
    "sg:province":"Baden-W\u00fcrttemberg",
    "wof:name":"Rudolf Wolf Steinmetzbetrieb",
    "wof:placetype":"venue"
},
  "geometry": {"coordinates":[8.8227653503,49.3193664551],"type":"Point"}
}