{
  "type": "Feature",
  "properties": {
    "iso:country":"DE",
    "sg:address":"Mannesmannufer 1 a",
    "sg:city":"D\u00fcsseldorf",
    "sg:phone":"+49 211/8371247",
    "sg:postcode":"40213",
    "sg:province":"Nordrhein-Westfalen",
    "wof:name":"Landesregierung Nordrhein-westfalen",
    "wof:placetype":"venue"
},
  "geometry": {"coordinates":[6.767838,51.220303],"type":"Point"}
}