{
  "type": "Feature",
  "properties": {
    "iso:country":"DE",
    "sg:address":"Mozartplatz 3",
    "sg:city":"Brandenburg",
    "sg:postcode":"14772",
    "sg:province":"Brandenburg",
    "wof:name":"Konsum-drogerie",
    "wof:placetype":"venue"
},
  "geometry": {"coordinates":[12.517985,52.425762],"type":"Point"}
}