{
  "type": "Feature",
  "properties": {
    "iso:country":"DE",
    "sg:address":"Bergstrasse 8",
    "sg:city":"Waldkirch-Kollnau",
    "sg:phone":"+49 7681",
    "sg:postcode":"79183",
    "sg:province":"Baden-W\u00fcrttemberg",
    "wof:name":"Www.kumlin-fahrzeugbau.de",
    "wof:placetype":"venue"
},
  "geometry": {"coordinates":[7.96622,48.100864],"type":"Point"}
}