{
  "type": "Feature",
  "properties": {
    "iso:country":"DE",
    "sg:address":"Reuthstr. 15",
    "sg:city":"Schechen",
    "sg:phone":"+49 8031/806650",
    "sg:postcode":"83135",
    "sg:province":"Bayern",
    "wof:name":"Kb-reisedienst Kontakt- Und Bildungsreisen Gmbh",
    "wof:placetype":"venue"
},
  "geometry": {"coordinates":[12.1278123856,47.8883018494],"type":"Point"}
}