{
  "type": "Feature",
  "properties": {
    "iso:country":"DE",
    "sg:address":"Krefelder Str. 10",
    "sg:city":"Berlin",
    "sg:phone":"+49 30/3934179",
    "sg:postcode":"10555",
    "sg:province":"Berlin",
    "wof:name":"T. Ang",
    "wof:placetype":"venue"
},
  "geometry": {"coordinates":[13.339552,52.523212],"type":"Point"}
}