{
  "type": "Feature",
  "properties": {
    "iso:country":"DE",
    "sg:address":"Dorfstr. 19",
    "sg:city":"Stechau",
    "sg:phone":"+49 35361/80270",
    "sg:postcode":"04936",
    "sg:province":"Brandenburg",
    "wof:name":"Bernd Kroegerrecklenfort",
    "wof:placetype":"venue"
},
  "geometry": {"coordinates":[13.462097,51.696663],"type":"Point"}
}