{
  "type": "Feature",
  "properties": {
    "iso:country":"DE",
    "sg:address":"Uml\u00e4nderwiek Links 90",
    "sg:city":"Papenburg",
    "sg:phone":"+49 4961/73489",
    "sg:postcode":"26871",
    "sg:province":"Niedersachsen",
    "wof:name":"Restaurant Schulte-lind",
    "wof:placetype":"venue"
},
  "geometry": {"coordinates":[7.4624590874,53.0695724487],"type":"Point"}
}