{
  "type": "Feature",
  "properties": {
    "iso:country":"DE",
    "sg:address":"Winzenburger Str. 24",
    "sg:city":"Freden",
    "sg:phone":"+49 5184/958888",
    "sg:postcode":"31084",
    "sg:province":"Niedersachsen",
    "wof:name":"K. M\u00e4uselein",
    "wof:placetype":"venue"
},
  "geometry": {"coordinates":[9.9034252167,51.9271583557],"type":"Point"}
}