{
  "type": "Feature",
  "properties": {
    "iso:country":"DE",
    "sg:address":"Wilhelmstr. 100",
    "sg:city":"Oberhausen",
    "sg:postcode":"46145",
    "sg:province":"Nordrhein-Westfalen",
    "wof:name":"Thyssen Krupp Stahl Bauelemente Gmbh",
    "wof:placetype":"venue"
},
  "geometry": {"coordinates":[6.841975,51.523277],"type":"Point"}
}