{
  "type": "Feature",
  "properties": {
    "iso:country":"DE",
    "sg:address":"Geretsried",
    "sg:city":"Starnberg",
    "sg:phone":"+49 8151/21435",
    "sg:postcode":"82319",
    "sg:province":"Bayern",
    "wof:name":"Lug Gmbh & Co. Kg",
    "wof:placetype":"venue"
},
  "geometry": {"coordinates":[11.342172,47.999592],"type":"Point"}
}