{
  "type": "Feature",
  "properties": {
    "iso:country":"DE",
    "sg:address":"Bergstr. 23",
    "sg:city":"Badersleben",
    "sg:phone":"+49 39422/267",
    "sg:postcode":"38836",
    "sg:province":"Sachsen-Anhalt",
    "wof:name":"Heinz Hartung",
    "wof:placetype":"venue"
},
  "geometry": {"coordinates":[10.89212,51.988884],"type":"Point"}
}