{
  "type": "Feature",
  "properties": {
    "iso:country":"DE",
    "sg:address":"Rosenstr. 22",
    "sg:city":"Bad Eilsen",
    "sg:phone":"+49 5722/8671",
    "sg:postcode":"31707",
    "sg:province":"Niedersachsen",
    "wof:name":"Wolf-dietrich Stein Architekt",
    "wof:placetype":"venue"
},
  "geometry": {"coordinates":[9.111977,52.241474],"type":"Point"}
}