{
  "type": "Feature",
  "properties": {
    "iso:country":"DE",
    "sg:address":"Els\u00e4sser Str. 5",
    "sg:city":"D\u00fcsseldorf",
    "sg:phone":"+49 211/427629",
    "sg:postcode":"40468",
    "sg:province":"Nordrhein-Westfalen",
    "wof:name":"Wilhelmine Busch",
    "wof:placetype":"venue"
},
  "geometry": {"coordinates":[6.7736911774,51.2678108215],"type":"Point"}
}