{
  "type": "Feature",
  "properties": {
    "iso:country":"DE",
    "sg:address":"M\u00fchlenstr. 18",
    "sg:city":"Geseke",
    "sg:phone":"+49 2942/7478",
    "sg:postcode":"59590",
    "sg:province":"Nordrhein-Westfalen",
    "wof:name":"Hrs Projekt Und Bauent- Wicklungs Gmbh",
    "wof:placetype":"venue"
},
  "geometry": {"coordinates":[8.510313,51.643192],"type":"Point"}
}