{
  "type": "Feature",
  "properties": {
    "iso:country":"DE",
    "sg:address":"Immermannstr. 33",
    "sg:city":"D\u00fcsseldorf",
    "sg:phone":"+49 211/359974",
    "sg:postcode":"40210",
    "sg:province":"Nordrhein-Westfalen",
    "wof:name":"Doris Coenen Architektin",
    "wof:placetype":"venue"
},
  "geometry": {"coordinates":[6.788241,51.223293],"type":"Point"}
}