{
  "type": "Feature",
  "properties": {
    "iso:country":"DE",
    "sg:address":"Eifelstra\u00dfe 19",
    "sg:city":"Saarbr\u00fccken",
    "sg:phone":"+49 6339/570",
    "sg:postcode":"66113",
    "sg:province":"Saarland",
    "wof:name":"Seeded Crown",
    "wof:placetype":"venue"
},
  "geometry": {"coordinates":[6.968087,49.250931],"type":"Point"}
}