{
  "type": "Feature",
  "properties": {
    "iso:country":"DE",
    "sg:address":"Derschlager Str. 4",
    "sg:city":"Wiehl",
    "sg:phone":"+49 2262/76290",
    "sg:postcode":"51674",
    "sg:province":"Nordrhein-Westfalen",
    "wof:name":"Caretex Medizinische Textilien Gmbh",
    "wof:placetype":"venue"
},
  "geometry": {"coordinates":[7.583281,50.945259],"type":"Point"}
}