{
  "type": "Feature",
  "properties": {
    "iso:country":"DE",
    "sg:address":"B\u00f6nninghardter Str. 139",
    "sg:city":"Alpen",
    "sg:phone":"+49 2802/4396",
    "sg:postcode":"46519",
    "sg:province":"Nordrhein-Westfalen",
    "wof:name":"Heidehof Schmitt",
    "wof:placetype":"venue"
},
  "geometry": {"coordinates":[6.4569568634,51.5785064697],"type":"Point"}
}