{
  "type": "Feature",
  "properties": {
    "iso:country":"DE",
    "sg:address":"Oberspaarer Str. 40",
    "sg:city":"Mei\u00dfen",
    "sg:phone":"+49 3521/738122",
    "sg:postcode":"01662",
    "sg:province":"Sachsen",
    "wof:name":"Pension Kleeblatt Inh. B. Herrgesell",
    "wof:placetype":"venue"
},
  "geometry": {"coordinates":[13.5027980804,51.1526832581],"type":"Point"}
}