{
  "type": "Feature",
  "properties": {
    "iso:country":"DE",
    "sg:address":"Alte Ricklinger Str. 45-47",
    "sg:city":"Garbsen",
    "sg:postcode":"30823",
    "sg:province":"Niedersachsen",
    "wof:name":"Factory Dance Gmbh",
    "wof:placetype":"venue"
},
  "geometry": {"coordinates":[9.574458,52.419212],"type":"Point"}
}