{
  "type": "Feature",
  "properties": {
    "iso:country":"DE",
    "sg:address":"An der Beeke 5",
    "sg:city":"Auetal",
    "sg:phone":"+49 5752/358",
    "sg:postcode":"31749",
    "sg:province":"Niedersachsen",
    "wof:name":"Peter Hau",
    "wof:placetype":"venue"
},
  "geometry": {"coordinates":[9.2927541733,52.2419509888],"type":"Point"}
}