{
  "type": "Feature",
  "properties": {
    "iso:country":"DE",
    "sg:address":"Br\u00fcckstr. 21",
    "sg:city":"Heiligenhafen",
    "sg:postcode":"23774",
    "sg:province":"Schleswig-Holstein",
    "wof:name":"Klabautermann",
    "wof:placetype":"venue"
},
  "geometry": {"coordinates":[10.9801750183,54.373878479],"type":"Point"}
}