{
  "type": "Feature",
  "properties": {
    "iso:country":"DE",
    "sg:address":"Lipper Hellweg 271",
    "sg:city":"Bielefeld",
    "sg:phone":"+49 521/200601",
    "sg:postcode":"33605",
    "sg:province":"Nordrhein-Westfalen",
    "wof:name":"Ev. Pfarramt Ev. Luth. Gustav Adolf",
    "wof:placetype":"venue"
},
  "geometry": {"coordinates":[8.5916824341,51.992389679],"type":"Point"}
}