{
  "type": "Feature",
  "properties": {
    "iso:country":"DE",
    "sg:address":"Tiergartenstr. 9",
    "sg:city":"Halle",
    "sg:phone":"+49 345/5231651",
    "sg:postcode":"06114",
    "sg:province":"Sachsen-Anhalt",
    "wof:name":"Helmut Schr\u00f6der Ingenieur",
    "wof:placetype":"venue"
},
  "geometry": {"coordinates":[11.9641513824,51.5075683594],"type":"Point"}
}