{
  "type": "Feature",
  "properties": {
    "iso:country":"DE",
    "sg:address":"Fraschstr. 6",
    "sg:city":"Korntal",
    "sg:postcode":"70825",
    "sg:province":"Baden-W\u00fcrttemberg",
    "wof:name":"Pro Missa Tridentina",
    "wof:placetype":"venue"
},
  "geometry": {"coordinates":[9.118894,48.827152],"type":"Point"}
}