{
  "type": "Feature",
  "properties": {
    "iso:country":"DE",
    "sg:address":"Ro\u00dfmarkt 6",
    "sg:city":"M\u00fcnchen",
    "sg:phone":"+49 89/26025330",
    "sg:postcode":"80331",
    "sg:province":"Bayern",
    "wof:name":"Peter Studt",
    "wof:placetype":"venue"
},
  "geometry": {"coordinates":[11.5689821243,48.1331825256],"type":"Point"}
}