{
  "type": "Feature",
  "properties": {
    "iso:country":"DE",
    "sg:address":"Gro\u00dfe Bauerngasse 79",
    "sg:city":"H\u00f6chstadt",
    "sg:phone":"+49 9193/4643",
    "sg:postcode":"91315",
    "sg:province":"Bayern",
    "wof:name":"Valentin Maier Ingenieur",
    "wof:placetype":"venue"
},
  "geometry": {"coordinates":[10.8210983276,49.7034683228],"type":"Point"}
}