{
  "type": "Feature",
  "properties": {
    "iso:country":"DE",
    "sg:address":"Utzstetter Str. 16",
    "sg:city":"Ruppertshofen",
    "sg:phone":"+49 7176/509",
    "sg:postcode":"73577",
    "sg:province":"Baden-W\u00fcrttemberg",
    "wof:name":"E. Beisswenger",
    "wof:placetype":"venue"
},
  "geometry": {"coordinates":[9.818286,48.882172],"type":"Point"}
}