{
  "type": "Feature",
  "properties": {
    "iso:country":"DE",
    "sg:address":"Am Sportplatz 7",
    "sg:city":"Saarbr\u00fccken",
    "sg:phone":"+49 681/87780",
    "sg:postcode":"66130",
    "sg:province":"Saarland",
    "wof:name":"Friedrich Gmbh",
    "wof:placetype":"venue"
},
  "geometry": {"coordinates":[7.0259947777,49.1925888062],"type":"Point"}
}