{
  "type": "Feature",
  "properties": {
    "iso:country":"DE",
    "sg:address":"Karl-Marx-Str. 2a",
    "sg:city":"Saubach",
    "sg:phone":"+49 34465/88297",
    "sg:postcode":"06647",
    "sg:province":"Sachsen-Anhalt",
    "wof:name":"H.-g. Thiele Ingenieur",
    "wof:placetype":"venue"
},
  "geometry": {"coordinates":[11.5279026031,51.2147407532],"type":"Point"}
}