{
  "type": "Feature",
  "properties": {
    "iso:country":"DE",
    "sg:address":"St.-Martin-Str. 12",
    "sg:city":"Ried",
    "sg:phone":"+49 8202/8341",
    "sg:postcode":"86510",
    "sg:province":"Bayern",
    "wof:name":"Georg Breitsameter",
    "wof:placetype":"venue"
},
  "geometry": {"coordinates":[11.093299,48.276653],"type":"Point"}
}