{
  "type": "Feature",
  "properties": {
    "iso:country":"DE",
    "sg:address":"R\u00fcttgergasse 21",
    "sg:city":"Gelsenkirchen",
    "sg:phone":"+49 209/55391",
    "sg:postcode":"45899",
    "sg:province":"Nordrhein-Westfalen",
    "wof:name":"Erwin Solenski",
    "wof:placetype":"venue"
},
  "geometry": {"coordinates":[7.021961,51.524559],"type":"Point"}
}