{
  "type": "Feature",
  "properties": {
    "iso:country":"DE",
    "sg:address":"Am Fahlenberg 2-8",
    "sg:city":"Bad Karlshafen",
    "sg:phone":"+49 5672/9980",
    "sg:postcode":"34385",
    "sg:province":"Hessen",
    "wof:name":"Bezirkskrankenhaus Helmarshausen Hessenklinik",
    "wof:placetype":"venue"
},
  "geometry": {"coordinates":[9.452203,51.630726],"type":"Point"}
}