{
  "type": "Feature",
  "properties": {
    "iso:country":"DE",
    "sg:address":"Raiffeisenstr. 3",
    "sg:city":"Dormettingen",
    "sg:phone":"+49 7427/94060",
    "sg:postcode":"72358",
    "sg:province":"Baden-W\u00fcrttemberg",
    "wof:name":"Getreidem\u00fchlegenossenschaft Dormettingen Eg",
    "wof:placetype":"venue"
},
  "geometry": {"coordinates":[8.7732248306,48.2365646362],"type":"Point"}
}