{
  "type": "Feature",
  "properties": {
    "iso:country":"DE",
    "sg:address":"An der Weide 3",
    "sg:city":"Bassum",
    "sg:phone":"+49 4241/2720",
    "sg:postcode":"27211",
    "sg:province":"Niedersachsen",
    "wof:name":"P. Famulok",
    "wof:placetype":"venue"
},
  "geometry": {"coordinates":[8.7343406677,52.8476409912],"type":"Point"}
}