{
  "type": "Feature",
  "properties": {
    "iso:country":"DE",
    "sg:address":"Am Gr\u00fcnen Ufer 14",
    "sg:city":"Dortmund",
    "sg:phone":"+49 231/271448",
    "sg:postcode":"44319",
    "sg:province":"Nordrhein-Westfalen",
    "wof:name":"V. Und A. Oesigmann",
    "wof:placetype":"venue"
},
  "geometry": {"coordinates":[7.5940208435,51.5270271301],"type":"Point"}
}