{
  "type": "Feature",
  "properties": {
    "iso:country":"DE",
    "sg:address":"Sch\u00fcttberg 17",
    "sg:city":"M\u00fclheim",
    "sg:phone":"+49 208/755737",
    "sg:postcode":"45475",
    "sg:province":"Nordrhein-Westfalen",
    "wof:name":"Joachim Th\u00fcrling",
    "wof:placetype":"venue"
},
  "geometry": {"coordinates":[6.8928627968,51.4560775757],"type":"Point"}
}