{
  "type": "Feature",
  "properties": {
    "iso:country":"DE",
    "sg:address":"Hackeloh 2",
    "sg:city":"M\u00f6hnesee",
    "sg:phone":"+49 2927/431",
    "sg:postcode":"59519",
    "sg:province":"Nordrhein-Westfalen",
    "wof:name":"Hellmut Wegmann",
    "wof:placetype":"venue"
},
  "geometry": {"coordinates":[8.193451,51.532654],"type":"Point"}
}