{
  "type": "Feature",
  "properties": {
    "iso:country":"DE",
    "sg:address":"Theresienthaler Str. 22",
    "sg:city":"Zwiesel",
    "sg:phone":"+49 9922/1469",
    "sg:postcode":"94227",
    "sg:province":"Bayern",
    "wof:name":"Erich Neppl Elektroinstallation",
    "wof:placetype":"venue"
},
  "geometry": {"coordinates":[13.231073,49.021603],"type":"Point"}
}