{
  "type": "Feature",
  "properties": {
    "iso:country":"DE",
    "sg:address":"Bahnstr 27",
    "sg:city":"Wipperf\u00fcrth",
    "sg:phone":"+49 2267/6810",
    "sg:postcode":"51688",
    "sg:province":"Nordrhein-Westfalen",
    "wof:name":"Genossenschaft Berg & Mark Raiffeisen-warengenossenschaft Eg",
    "wof:placetype":"venue"
},
  "geometry": {"coordinates":[7.389173,51.1185],"type":"Point"}
}