{
  "type": "Feature",
  "properties": {
    "iso:country":"DE",
    "sg:address":"Olchinger Str. 96",
    "sg:city":"Gr\u00f6benzell",
    "sg:phone":"+49 8142/60290",
    "sg:postcode":"82194",
    "sg:province":"Bayern",
    "wof:name":"Schliebitz",
    "wof:placetype":"venue"
},
  "geometry": {"coordinates":[11.381344,48.187443],"type":"Point"}
}