{
  "type": "Feature",
  "properties": {
    "iso:country":"DE",
    "sg:address":"Schie\u00dfstattweg 3",
    "sg:city":"Passau",
    "sg:phone":"+49 851/51867",
    "sg:postcode":"94032",
    "sg:province":"Bayern",
    "wof:name":"Reinhardt Immobilien- Verwaltung Gmbh",
    "wof:placetype":"venue"
},
  "geometry": {"coordinates":[13.4453792572,48.5712203979],"type":"Point"}
}