{
  "type": "Feature",
  "properties": {
    "iso:country":"DE",
    "sg:address":"Im Seegel 6",
    "sg:city":"Sontra",
    "sg:phone":"+49 5653/97950",
    "sg:postcode":"36205",
    "sg:province":"Hessen",
    "wof:name":"Laudemann Gmbh",
    "wof:placetype":"venue"
},
  "geometry": {"coordinates":[9.9331350327,51.0689582825],"type":"Point"}
}