{
  "type": "Feature",
  "properties": {
    "iso:country":"DE",
    "sg:address":"Vagtstr. 24",
    "sg:city":"Bremen",
    "sg:phone":"+49 421/74355",
    "sg:postcode":"28203",
    "sg:province":"Bremen",
    "wof:name":"Edwin Hartung Rechtsanwalt",
    "wof:placetype":"venue"
},
  "geometry": {"coordinates":[8.8328027725,53.0732498169],"type":"Point"}
}