{
  "type": "Feature",
  "properties": {
    "iso:country":"DE",
    "sg:address":"Schwabacher Str. 15",
    "sg:city":"N\u00fcrnberg",
    "sg:phone":"+49 911/6426018",
    "sg:postcode":"90439",
    "sg:province":"Bayern",
    "wof:name":"Gerd Essig Tankstellenbetrieb",
    "wof:placetype":"venue"
},
  "geometry": {"coordinates":[11.0566606522,49.4417457581],"type":"Point"}
}