{
  "type": "Feature",
  "properties": {
    "iso:country":"DE",
    "sg:address":"Landwehr 19",
    "sg:city":"Hamburg",
    "sg:phone":"+49 40/25495150",
    "sg:postcode":"22087",
    "sg:province":"Hamburg",
    "wof:name":"Night & Day Taxi Gmbh",
    "wof:placetype":"venue"
},
  "geometry": {"coordinates":[10.0360326767,53.5629692078],"type":"Point"}
}