{
  "type": "Feature",
  "properties": {
    "iso:country":"DE",
    "sg:address":"Birkenharder Str. 27",
    "sg:city":"Schemmerhofen",
    "sg:phone":"+49 7357/822",
    "sg:postcode":"88433",
    "sg:province":"Baden-W\u00fcrttemberg",
    "wof:name":"K. Bloed",
    "wof:placetype":"venue"
},
  "geometry": {"coordinates":[9.740606,48.151543],"type":"Point"}
}