{
  "type": "Feature",
  "properties": {
    "iso:country":"DE",
    "sg:address":"Goethestr. 2",
    "sg:city":"Gotha",
    "sg:phone":"+49 3621/709150",
    "sg:postcode":"99867",
    "sg:province":"Th\u00fcringen",
    "wof:name":"Itd Ing. Technik & Design Gmbh & Co. Kg",
    "wof:placetype":"venue"
},
  "geometry": {"coordinates":[10.695923,50.942375],"type":"Point"}
}