{
  "type": "Feature",
  "properties": {
    "iso:country":"DE",
    "sg:address":"Dorfstr. 31 a",
    "sg:city":"Erlangen",
    "sg:phone":"+49 9131/992226",
    "sg:postcode":"91056",
    "sg:province":"Bayern",
    "wof:name":"Georg Meyer",
    "wof:placetype":"venue"
},
  "geometry": {"coordinates":[10.9657459259,49.5903587341],"type":"Point"}
}