{
  "type": "Feature",
  "properties": {
    "iso:country":"DE",
    "sg:address":"Warth\u00e4user Str. 6",
    "sg:city":"Stuttgart",
    "sg:phone":"+49 711/422120",
    "sg:postcode":"70327",
    "sg:province":"Baden-W\u00fcrttemberg",
    "wof:name":"Traube",
    "wof:placetype":"venue"
},
  "geometry": {"coordinates":[9.2450828552,48.7709999084],"type":"Point"}
}