{
  "type": "Feature",
  "properties": {
    "iso:country":"DE",
    "sg:address":"R\u00f6hrenstr. 47",
    "sg:city":"Bitterfeld",
    "sg:phone":"+49 3493/21014",
    "sg:postcode":"06749",
    "sg:province":"Sachsen-Anhalt",
    "wof:name":"Bischoff",
    "wof:placetype":"venue"
},
  "geometry": {"coordinates":[12.321908,51.618294],"type":"Point"}
}