{
  "type": "Feature",
  "properties": {
    "iso:country":"DE",
    "sg:address":"Marienstr. 4",
    "sg:city":"Zwiefalten",
    "sg:phone":"+49 7373/807",
    "sg:postcode":"88529",
    "sg:province":"Baden-W\u00fcrttemberg",
    "wof:name":"Anton Hepp",
    "wof:placetype":"venue"
},
  "geometry": {"coordinates":[9.481516,48.22633],"type":"Point"}
}