{
  "type": "Feature",
  "properties": {
    "iso:country":"DE",
    "sg:address":"Wachmannstr. 39",
    "sg:city":"Bremen",
    "sg:phone":"+49 421/3469700",
    "sg:postcode":"28209",
    "sg:province":"Bremen",
    "wof:name":"Gert Beelmann",
    "wof:placetype":"venue"
},
  "geometry": {"coordinates":[8.829459,53.085365],"type":"Point"}
}