{
  "type": "Feature",
  "properties": {
    "iso:country":"DE",
    "sg:address":"Obergasse 15",
    "sg:city":"Leinfelden-Echterdingen",
    "sg:phone":"+49 711/795474",
    "sg:postcode":"70771",
    "sg:province":"Baden-W\u00fcrttemberg",
    "wof:name":"Hans Klingler",
    "wof:placetype":"venue"
},
  "geometry": {"coordinates":[9.1654224396,48.6889076233],"type":"Point"}
}