{
  "type": "Feature",
  "properties": {
    "iso:country":"DE",
    "sg:address":"Landungsplatz 1",
    "sg:city":"\u00dcberlingen",
    "sg:phone":"+49 7551/916325",
    "sg:postcode":"88662",
    "sg:province":"Baden-W\u00fcrttemberg",
    "wof:name":"Pizzeria Allegretto",
    "wof:placetype":"venue"
},
  "geometry": {"coordinates":[9.1591415405,47.7665023804],"type":"Point"}
}