{
  "type": "Feature",
  "properties": {
    "iso:country":"DE",
    "sg:address":"Kollostr. 36",
    "sg:city":"Bielefeld",
    "sg:phone":"+49 521/411415",
    "sg:postcode":"33647",
    "sg:province":"Nordrhein-Westfalen",
    "wof:name":"K. Kube Rechtsanwalt",
    "wof:placetype":"venue"
},
  "geometry": {"coordinates":[8.5175743103,51.9917945862],"type":"Point"}
}