{
  "type": "Feature",
  "properties": {
    "iso:country":"DE",
    "sg:address":"Hochstadenstr. 20",
    "sg:city":"Neuss",
    "sg:phone":"+49 2137/77715",
    "sg:postcode":"41469",
    "sg:province":"Nordrhein-Westfalen",
    "wof:name":"R. Helten",
    "wof:placetype":"venue"
},
  "geometry": {"coordinates":[6.702156,51.142433],"type":"Point"}
}