{
  "type": "Feature",
  "properties": {
    "iso:country":"DE",
    "sg:address":"Hauptstr. 43",
    "sg:city":"Bopfingen",
    "sg:phone":"+49 7362/4121",
    "sg:postcode":"73441",
    "sg:province":"Baden-W\u00fcrttemberg",
    "wof:name":"Pizzeria Da Felice",
    "wof:placetype":"venue"
},
  "geometry": {"coordinates":[10.3501691818,48.8582000732],"type":"Point"}
}