{
  "type": "Feature",
  "properties": {
    "iso:country":"DE",
    "sg:address":"Max-Planck-Str. 4",
    "sg:city":"Wittlich",
    "sg:phone":"+49 6571/28052",
    "sg:postcode":"54516",
    "sg:province":"Rheinland-Pfalz",
    "wof:name":"Bettwaren-fachmarkt",
    "wof:placetype":"venue"
},
  "geometry": {"coordinates":[6.904779911,49.9837188721],"type":"Point"}
}