{
  "type": "Feature",
  "properties": {
    "iso:country":"DE",
    "sg:address":"Talh\u00f6fe 1",
    "sg:city":"\u00dchlingen-Birkendorf",
    "sg:postcode":"79777",
    "sg:province":"Baden-W\u00fcrttemberg",
    "wof:name":"Josef Limberger",
    "wof:placetype":"venue"
},
  "geometry": {"coordinates":[8.33098,47.690006],"type":"Point"}
}