{
  "type": "Feature",
  "properties": {
    "iso:country":"DE",
    "sg:address":"Rochusstr. 81",
    "sg:city":"K\u00f6ln",
    "sg:phone":"+49 221/5301662",
    "sg:postcode":"50827",
    "sg:province":"Nordrhein-Westfalen",
    "wof:name":"Erich Schuth",
    "wof:placetype":"venue"
},
  "geometry": {"coordinates":[6.901676178,50.9600753784],"type":"Point"}
}