{
  "type": "Feature",
  "properties": {
    "iso:country":"DE",
    "sg:address":"Sch\u00fctzenstr. 20",
    "sg:city":"Traunstein",
    "sg:phone":"+49 861/164100",
    "sg:postcode":"83278",
    "sg:province":"Bayern",
    "wof:name":"Irlacher",
    "wof:placetype":"venue"
},
  "geometry": {"coordinates":[12.65092659,47.8705101013],"type":"Point"}
}