{
  "type": "Feature",
  "properties": {
    "iso:country":"DE",
    "sg:address":"Max-Planck-Str. 3",
    "sg:city":"Sennfeld",
    "sg:phone":"+49 9721/76520",
    "sg:postcode":"97526",
    "sg:province":"Bayern",
    "wof:name":"B\u00e4ko Franken-th\u00fcringen B\u00e4cker- Und Konditorengen. Eg",
    "wof:placetype":"venue"
},
  "geometry": {"coordinates":[10.244402,50.035522],"type":"Point"}
}