{
  "type": "Feature",
  "properties": {
    "iso:country":"DE",
    "sg:address":"Im Breitenweingarten 18",
    "sg:city":"Sipplingen",
    "sg:phone":"+49 7551/4419",
    "sg:postcode":"78354",
    "sg:province":"Baden-W\u00fcrttemberg",
    "wof:name":"Werner Widenhorn",
    "wof:placetype":"venue"
},
  "geometry": {"coordinates":[9.0951404572,47.7968482971],"type":"Point"}
}