{
  "type": "Feature",
  "properties": {
    "iso:country":"DE",
    "sg:address":"Saarschleife 1",
    "sg:city":"Wuppertal",
    "sg:phone":"+49 4920/2275440",
    "sg:postcode":"42107",
    "sg:province":"Nordrhein-Westfalen",
    "wof:name":"Portas Fachbetrieb Wiek Gmbh",
    "wof:placetype":"venue"
},
  "geometry": {"coordinates":[7.153845787,51.2697525024],"type":"Point"}
}