{
  "type": "Feature",
  "properties": {
    "iso:country":"DE",
    "sg:address":"Blumenstr. 10",
    "sg:city":"Werdohl",
    "sg:phone":"+49 2392/7974",
    "sg:postcode":"58791",
    "sg:province":"Nordrhein-Westfalen",
    "wof:name":"Sieglinde Kreikebaum Steuerberater",
    "wof:placetype":"venue"
},
  "geometry": {"coordinates":[7.7530288696,51.2345504761],"type":"Point"}
}