{
  "type": "Feature",
  "properties": {
    "iso:country":"DE",
    "sg:address":"Puschkinstr. 4",
    "sg:city":"Suhl",
    "sg:phone":"+49 3681/727277",
    "sg:postcode":"98527",
    "sg:province":"Th\u00fcringen",
    "wof:name":"Dieter Waletzko",
    "wof:placetype":"venue"
},
  "geometry": {"coordinates":[10.6853437424,50.6058197021],"type":"Point"}
}