{
  "type": "Feature",
  "properties": {
    "iso:country":"DE",
    "sg:address":"Marktstr. 27",
    "sg:city":"Stuttgart",
    "sg:phone":"+49 711/563791",
    "sg:postcode":"70372",
    "sg:province":"Baden-W\u00fcrttemberg",
    "wof:name":"Linea",
    "wof:placetype":"venue"
},
  "geometry": {"coordinates":[9.214604,48.804279],"type":"Point"}
}