{
  "type": "Feature",
  "properties": {
    "iso:country":"DE",
    "sg:address":"Beckleinsgasse 6",
    "sg:city":"Itzgrund",
    "sg:phone":"+49 9533/281",
    "sg:postcode":"96274",
    "sg:province":"Bayern",
    "wof:name":"R. K\u00f6hler",
    "wof:placetype":"venue"
},
  "geometry": {"coordinates":[10.894277,50.152805],"type":"Point"}
}