{
  "type": "Feature",
  "properties": {
    "iso:country":"DE",
    "sg:address":"Brandenburger Str. 24",
    "sg:city":"Leverkusen",
    "sg:phone":"+49 4921/4891040",
    "sg:postcode":"51377",
    "sg:province":"Nordrhein-Westfalen",
    "wof:name":"Pd-datentechnik, Edv-handel Und Service, Internet",
    "wof:placetype":"venue"
},
  "geometry": {"coordinates":[7.07534,51.047531],"type":"Point"}
}