{
  "type": "Feature",
  "properties": {
    "iso:country":"DE",
    "sg:address":"Braomweg 2",
    "sg:city":"Steinfeld",
    "sg:phone":"+49 5492/2321",
    "sg:postcode":"49439",
    "sg:province":"Niedersachsen",
    "wof:name":"Georg L\u00fcbbing",
    "wof:placetype":"venue"
},
  "geometry": {"coordinates":[8.228339,52.593403],"type":"Point"}
}