{
  "type": "Feature",
  "properties": {
    "iso:country":"DE",
    "sg:address":"Freiherr-vom-Stein-Str. 2",
    "sg:city":"Burglengenfeld",
    "sg:phone":"+49 9471/807478",
    "sg:postcode":"93133",
    "sg:province":"Bayern",
    "wof:name":"Tbs",
    "wof:placetype":"venue"
},
  "geometry": {"coordinates":[12.042625,49.20097],"type":"Point"}
}