{
  "type": "Feature",
  "properties": {
    "iso:country":"DE",
    "sg:address":"Gerberg. 4+5",
    "sg:city":"Olbernhau",
    "sg:phone":"+49 4952/0791220",
    "sg:postcode":"09526",
    "sg:province":"Sachsen",
    "wof:name":"Wilfried Strothmann Gmbh & Co Kg",
    "wof:placetype":"venue"
},
  "geometry": {"coordinates":[8.61599,51.884033],"type":"Point"}
}