{
  "type": "Feature",
  "properties": {
    "iso:country":"DE",
    "sg:address":"Sprengerstr. 13",
    "sg:city":"Hildesheim",
    "sg:phone":"+49 5121/868119",
    "sg:postcode":"31134",
    "sg:province":"Niedersachsen",
    "wof:name":"Walter Klostermaier",
    "wof:placetype":"venue"
},
  "geometry": {"coordinates":[9.9609527588,52.1401863098],"type":"Point"}
}