{
  "type": "Feature",
  "properties": {
    "iso:country":"DE",
    "sg:address":"Hauptstr. 47",
    "sg:city":"Herschbach",
    "sg:phone":"+49 2626/5257",
    "sg:postcode":"56249",
    "sg:province":"Rheinland-Pfalz",
    "wof:name":"Central-restaurant",
    "wof:placetype":"venue"
},
  "geometry": {"coordinates":[7.7382731438,50.5741004944],"type":"Point"}
}