{
  "type": "Feature",
  "properties": {
    "iso:country":"DE",
    "sg:address":"Am Zehnthof 197-203",
    "sg:city":"Essen",
    "sg:postcode":"45307",
    "sg:province":"Nordrhein-Westfalen",
    "wof:name":"Qsm Ges. F. Qualit\u00e4tssicherung Und Materialpr\u00fcfung Mbh",
    "wof:placetype":"venue"
},
  "geometry": {"coordinates":[7.073638916,51.459236145],"type":"Point"}
}