{
  "type": "Feature",
  "properties": {
    "iso:country":"DE",
    "sg:address":"Carl-Hagen-Str. 1",
    "sg:city":"Oberaudorf",
    "sg:phone":"+49 8033/2381",
    "sg:postcode":"83080",
    "sg:province":"Bayern",
    "wof:name":"G\u00e4stehaus Gruber",
    "wof:placetype":"venue"
},
  "geometry": {"coordinates":[12.1708564758,47.6479263306],"type":"Point"}
}