{
  "type": "Feature",
  "properties": {
    "iso:country":"DE",
    "sg:address":"Ellinger Str. 22",
    "sg:city":"Morsbach",
    "sg:phone":"+49 2294/8748",
    "sg:postcode":"51597",
    "sg:province":"Nordrhein-Westfalen",
    "wof:name":"J. Klein",
    "wof:placetype":"venue"
},
  "geometry": {"coordinates":[7.734609127,50.9023475647],"type":"Point"}
}