{
  "type": "Feature",
  "properties": {
    "iso:country":"DE",
    "sg:address":"Lammstr. 14",
    "sg:city":"Karlsruhe",
    "sg:phone":"+49 721/28394",
    "sg:postcode":"76133",
    "sg:province":"Baden-W\u00fcrttemberg",
    "wof:name":"Gigi",
    "wof:placetype":"venue"
},
  "geometry": {"coordinates":[8.401875,49.008324],"type":"Point"}
}