{
  "type": "Feature",
  "properties": {
    "iso:country":"DE",
    "sg:address":"Karl-Marx-Platz 24",
    "sg:city":"Berlin",
    "sg:phone":"+49 30/6817151",
    "sg:postcode":"12043",
    "sg:province":"Berlin",
    "wof:name":"Spielhallen Gmbh",
    "wof:placetype":"venue"
},
  "geometry": {"coordinates":[13.4434318542,52.4739456177],"type":"Point"}
}