{
  "type": "Feature",
  "properties": {
    "iso:country":"DE",
    "sg:address":"Merseburger Str. 105",
    "sg:city":"Querfurt",
    "sg:phone":"+49 34771/22003",
    "sg:postcode":"06268",
    "sg:province":"Sachsen-Anhalt",
    "wof:name":"Udo Jacob",
    "wof:placetype":"venue"
},
  "geometry": {"coordinates":[11.62388,51.381672],"type":"Point"}
}