{
  "type": "Feature",
  "properties": {
    "iso:country":"DE",
    "sg:address":"Melkbrink 22",
    "sg:city":"Oldenburg",
    "sg:phone":"+49 441/88135",
    "sg:postcode":"26121",
    "sg:province":"Niedersachsen",
    "wof:name":"Ratsherrenstube",
    "wof:placetype":"venue"
},
  "geometry": {"coordinates":[8.2071285248,53.1563568115],"type":"Point"}
}