{
  "type": "Feature",
  "properties": {
    "iso:country":"DE",
    "sg:address":"Schiefweger Str. 12",
    "sg:city":"Waldkirchen",
    "sg:phone":"+49 8581/2959",
    "sg:postcode":"94065",
    "sg:province":"Bayern",
    "wof:name":"Fit-aktiv",
    "wof:placetype":"venue"
},
  "geometry": {"coordinates":[13.6014928818,48.7334022522],"type":"Point"}
}