{
  "type": "Feature",
  "properties": {
    "iso:country":"DE",
    "sg:address":"Kieler Str. 657",
    "sg:city":"Hamburg",
    "sg:phone":"+49 40/5709231",
    "sg:postcode":"22527",
    "sg:province":"Hamburg",
    "wof:name":"E. Horn",
    "wof:placetype":"venue"
},
  "geometry": {"coordinates":[9.905887,53.607399],"type":"Point"}
}