{
  "type": "Feature",
  "properties": {
    "iso:country":"DE",
    "sg:address":"Radeburger Landstr. 12",
    "sg:city":"Dresden",
    "sg:phone":"+49 351",
    "sg:postcode":"01108",
    "sg:province":"Sachsen",
    "wof:name":"Dresdner Zierpflanzen Steinle",
    "wof:placetype":"venue"
},
  "geometry": {"coordinates":[13.7946691513,51.1526222229],"type":"Point"}
}