{
  "type": "Feature",
  "properties": {
    "iso:country":"DE",
    "sg:address":"Im Sonnenschein 2",
    "sg:city":"Erkrath",
    "sg:phone":"+49 2104/42598",
    "sg:postcode":"40699",
    "sg:province":"Nordrhein-Westfalen",
    "wof:name":"H. -j. Vellmann Steuerberater",
    "wof:placetype":"venue"
},
  "geometry": {"coordinates":[6.9553790092,51.2014083862],"type":"Point"}
}