{
  "type": "Feature",
  "properties": {
    "iso:country":"DE",
    "sg:address":"Mertensweg 23",
    "sg:city":"Willich",
    "sg:phone":"+49 2156/2166",
    "sg:postcode":"47877",
    "sg:province":"Nordrhein-Westfalen",
    "wof:name":"Wilhelm Werkes",
    "wof:placetype":"venue"
},
  "geometry": {"coordinates":[6.4492211342,51.2796325684],"type":"Point"}
}