{
  "type": "Feature",
  "properties": {
    "iso:country":"DE",
    "sg:address":"Strohstr. 6",
    "sg:city":"N\u00fcrtingen",
    "sg:phone":"+49 7022/31057",
    "sg:postcode":"72622",
    "sg:province":"Baden-W\u00fcrttemberg",
    "wof:name":"Gerhard M\u00fcller",
    "wof:placetype":"venue"
},
  "geometry": {"coordinates":[9.3380126953,48.626121521],"type":"Point"}
}