{
  "type": "Feature",
  "properties": {
    "iso:country":"DE",
    "sg:address":"Bergstr. 2",
    "sg:city":"Langerringen",
    "sg:phone":"+49 8248/600",
    "sg:postcode":"86853",
    "sg:province":"Bayern",
    "wof:name":"A. Und G. Weber",
    "wof:placetype":"venue"
},
  "geometry": {"coordinates":[10.771749,48.103729],"type":"Point"}
}