{
  "type": "Feature",
  "properties": {
    "iso:country":"DE",
    "sg:address":"Amselstr. 16",
    "sg:city":"Neustadt",
    "sg:phone":"+49 5032/7698",
    "sg:postcode":"31535",
    "sg:province":"Niedersachsen",
    "wof:name":"R. Peglow",
    "wof:placetype":"venue"
},
  "geometry": {"coordinates":[9.325004,48.857021],"type":"Point"}
}