{
  "type": "Feature",
  "properties": {
    "iso:country":"DE",
    "sg:address":"Dorfstr. 13",
    "sg:city":"B\u00fchren",
    "sg:phone":"+49 4447/387",
    "sg:postcode":"49685",
    "sg:province":"Niedersachsen",
    "wof:name":"Getifix",
    "wof:placetype":"venue"
},
  "geometry": {"coordinates":[8.217143,52.80946],"type":"Point"}
}