{
  "type": "Feature",
  "properties": {
    "iso:country":"DE",
    "sg:address":"Am Reitacker 29",
    "sg:city":"Schl\u00fcchtern",
    "sg:phone":"+49 6661/71812",
    "sg:postcode":"36381",
    "sg:province":"Hessen",
    "wof:name":"Jo Achim H\u00e4rter",
    "wof:placetype":"venue"
},
  "geometry": {"coordinates":[9.5342760086,50.3248710632],"type":"Point"}
}