{
  "type": "Feature",
  "properties": {
    "iso:country":"DE",
    "sg:address":"Naulitzer Str.",
    "sg:city":"Gera",
    "sg:phone":"+49 365/437360",
    "sg:postcode":"07546",
    "sg:province":"Th\u00fcringen",
    "wof:name":"Bernd Mehnert",
    "wof:placetype":"venue"
},
  "geometry": {"coordinates":[12.1101646423,50.8791275024],"type":"Point"}
}