{
  "type": "Feature",
  "properties": {
    "iso:country":"DE",
    "sg:address":"Saarbr\u00fccker Str. 89",
    "sg:city":"Schmelz",
    "sg:phone":"+49 6887/88234",
    "sg:postcode":"66839",
    "sg:province":"Saarland",
    "wof:name":"J. Ludwig",
    "wof:placetype":"venue"
},
  "geometry": {"coordinates":[6.866315,49.439697],"type":"Point"}
}