{
  "type": "Feature",
  "properties": {
    "iso:country":"DE",
    "sg:address":"Hinter der Worth 8",
    "sg:city":"Garbsen",
    "sg:phone":"+49 5131/7447",
    "sg:postcode":"30827",
    "sg:province":"Niedersachsen",
    "wof:name":"H. Dannenbrink",
    "wof:placetype":"venue"
},
  "geometry": {"coordinates":[9.6242294312,52.4435081482],"type":"Point"}
}