{
  "type": "Feature",
  "properties": {
    "iso:country":"DE",
    "sg:address":"Daimlerring 11",
    "sg:city":"Hildesheim",
    "sg:phone":"+49 5121/74760",
    "sg:postcode":"31135",
    "sg:province":"Niedersachsen",
    "wof:name":"Selatec Ger\u00e4tebau Gmbh & Co Kg",
    "wof:placetype":"venue"
},
  "geometry": {"coordinates":[9.990577,52.163437],"type":"Point"}
}