{
  "type": "Feature",
  "properties": {
    "iso:country":"DE",
    "sg:address":"Neugasse 9-11",
    "sg:city":"Zwickau",
    "sg:phone":"+49 375/275950",
    "sg:postcode":"08056",
    "sg:province":"Sachsen",
    "wof:name":"Luber & Weidlich Gmbh",
    "wof:placetype":"venue"
},
  "geometry": {"coordinates":[12.4936952591,50.7231750488],"type":"Point"}
}