{
  "type": "Feature",
  "properties": {
    "iso:country":"DE",
    "sg:address":"Emminger Str. 68",
    "sg:city":"Tuttlingen",
    "sg:phone":"+49 7461/71113",
    "sg:postcode":"78532",
    "sg:province":"Baden-W\u00fcrttemberg",
    "wof:name":"Conrad Weinhardt Architekt",
    "wof:placetype":"venue"
},
  "geometry": {"coordinates":[8.817049,47.975143],"type":"Point"}
}