{
  "type": "Feature",
  "properties": {
    "iso:country":"DE",
    "sg:address":"Am Heienberg 24",
    "sg:city":"Wiesbaden",
    "sg:phone":"+49 611/9545239",
    "sg:postcode":"65193",
    "sg:province":"Hessen",
    "wof:name":"Klaus Tresbach",
    "wof:placetype":"venue"
},
  "geometry": {"coordinates":[8.267662,50.106075],"type":"Point"}
}