{
  "type": "Feature",
  "properties": {
    "iso:country":"DE",
    "sg:address":"Stadtweg 4",
    "sg:city":"Eichst\u00e4tt",
    "sg:phone":"+49 8421/3420",
    "sg:postcode":"85072",
    "sg:province":"Bayern",
    "wof:name":"Kutschfahrten Guenthner",
    "wof:placetype":"venue"
},
  "geometry": {"coordinates":[11.225006,48.88113],"type":"Point"}
}