{
  "type": "Feature",
  "properties": {
    "iso:country":"DE",
    "sg:address":"Hauptstr. 17a",
    "sg:city":"Trulben",
    "sg:phone":"+49 4963/35269",
    "sg:postcode":"66957",
    "sg:province":"Rheinland-Pfalz",
    "wof:name":"Kreissparkasse Pirmasens",
    "wof:placetype":"venue"
},
  "geometry": {"coordinates":[7.546377,49.140598],"type":"Point"}
}