{
  "type": "Feature",
  "properties": {
    "iso:country":"DE",
    "sg:address":"Kapellenstr. 25",
    "sg:city":"Bahlingen",
    "sg:phone":"+49 7663/3337",
    "sg:postcode":"79353",
    "sg:province":"Baden-W\u00fcrttemberg",
    "wof:name":"Fritz Schmidt",
    "wof:placetype":"venue"
},
  "geometry": {"coordinates":[7.7358670235,48.1226196289],"type":"Point"}
}