{
  "type": "Feature",
  "properties": {
    "iso:country":"DE",
    "sg:address":"Ruester Siedlung 2",
    "sg:city":"Gro\u00df Niendorf",
    "sg:phone":"+49 38723/80691",
    "sg:postcode":"19374",
    "sg:province":"Mecklenburg-Vorpommern",
    "wof:name":"Idee Holz Fachmarkt Wilfried G\u00f6llner Gmbh",
    "wof:placetype":"venue"
},
  "geometry": {"coordinates":[11.8844099045,53.5985641479],"type":"Point"}
}