{
  "type": "Feature",
  "properties": {
    "iso:country":"DE",
    "sg:address":"Karl-Theodor-Str. 55",
    "sg:city":"Rottach-Egern",
    "sg:phone":"+49 8022/65721",
    "sg:postcode":"83700",
    "sg:province":"Bayern",
    "wof:name":"G\u00e4stehaus Maximilian",
    "wof:placetype":"venue"
},
  "geometry": {"coordinates":[11.7714166641,47.6813926697],"type":"Point"}
}