{
  "type": "Feature",
  "properties": {
    "iso:country":"DE",
    "sg:address":"Im Wiesental 5",
    "sg:city":"Kronberg",
    "sg:phone":"+49 6173/62561",
    "sg:postcode":"61476",
    "sg:province":"Hessen",
    "wof:name":"R. Kaufamnn Immobilienmakler",
    "wof:placetype":"venue"
},
  "geometry": {"coordinates":[8.5174779892,50.1809883118],"type":"Point"}
}