{
  "type": "Feature",
  "properties": {
    "iso:country":"DE",
    "sg:address":"Dellwiger Weg 8",
    "sg:city":"Iserlohn",
    "sg:phone":"+49 2378/2768",
    "sg:postcode":"58640",
    "sg:province":"Nordrhein-Westfalen",
    "wof:name":"Ruhrh\u00f6he Campingplatz",
    "wof:placetype":"venue"
},
  "geometry": {"coordinates":[7.679018,51.465588],"type":"Point"}
}