{
  "type": "Feature",
  "properties": {
    "iso:country":"DE",
    "sg:address":"Baumgarten 1",
    "sg:city":"Breidenbach",
    "sg:phone":"+49 6465/1797",
    "sg:postcode":"35236",
    "sg:province":"Hessen",
    "wof:name":"U. Goldmann",
    "wof:placetype":"venue"
},
  "geometry": {"coordinates":[8.4275455475,50.8995399475],"type":"Point"}
}