{
  "type": "Feature",
  "properties": {
    "iso:country":"DE",
    "sg:address":"Hangstr. 1",
    "sg:city":"Hannover",
    "sg:phone":"+49 511/461927",
    "sg:postcode":"30457",
    "sg:province":"Niedersachsen",
    "wof:name":"Fritz Und Ralf D\u00fchlmeyer Architekten",
    "wof:placetype":"venue"
},
  "geometry": {"coordinates":[9.692063,52.331486],"type":"Point"}
}