{
  "type": "Feature",
  "properties": {
    "iso:country":"DE",
    "sg:address":"Hauptstr. 10",
    "sg:city":"Draschwitz",
    "sg:postcode":"06712",
    "sg:province":"Sachsen-Anhalt",
    "wof:name":"Evangelische-luth. Kirche",
    "wof:placetype":"venue"
},
  "geometry": {"coordinates":[12.907324791,51.2179298401],"type":"Point"}
}