{
  "type": "Feature",
  "properties": {
    "iso:country":"DE",
    "sg:address":"Carl-Ulrich-Str. 33",
    "sg:city":"Neu-Isenburg",
    "sg:phone":"+49 6102/17865",
    "sg:postcode":"63263",
    "sg:province":"Hessen",
    "wof:name":"Bau-daten Gmbh",
    "wof:placetype":"venue"
},
  "geometry": {"coordinates":[8.6919603348,50.0480690002],"type":"Point"}
}