{
  "type": "Feature",
  "properties": {
    "iso:country":"DE",
    "sg:address":"Augustastr. 70",
    "sg:city":"Dinslaken",
    "sg:phone":"+49 2064/32945",
    "sg:postcode":"46537",
    "sg:province":"Nordrhein-Westfalen",
    "wof:name":"Christel Weber",
    "wof:placetype":"venue"
},
  "geometry": {"coordinates":[6.732904911,51.5812225342],"type":"Point"}
}