{
  "type": "Feature",
  "properties": {
    "iso:country":"DE",
    "sg:address":"Siegelsdorfer Str. 38",
    "sg:city":"F\u00fcrth",
    "sg:phone":"+49 911/997520",
    "sg:postcode":"90768",
    "sg:province":"Bayern",
    "wof:name":"Rudolf Haselmann Gro\u00dfschl\u00c4chterei & Fleischgro\u00dfhandel",
    "wof:placetype":"venue"
},
  "geometry": {"coordinates":[10.9191999435,49.4945793152],"type":"Point"}
}