{
  "type": "Feature",
  "properties": {
    "iso:country":"DE",
    "sg:address":"Innstr. 82a",
    "sg:city":"Passau",
    "sg:phone":"+49 851/32571",
    "sg:postcode":"94036",
    "sg:province":"Bayern",
    "wof:name":"T. Weissinger",
    "wof:placetype":"venue"
},
  "geometry": {"coordinates":[13.443521,48.562508],"type":"Point"}
}