{
  "type": "Feature",
  "properties": {
    "iso:country":"DE",
    "sg:address":"Warendorfer Str. 7",
    "sg:city":"Everswinkel",
    "sg:phone":"+49 2582/9720",
    "sg:postcode":"48351",
    "sg:province":"Nordrhein-Westfalen",
    "wof:name":"J\u00fcrgen Bellmann Masseur",
    "wof:placetype":"venue"
},
  "geometry": {"coordinates":[7.848332,51.925957],"type":"Point"}
}