{
  "type": "Feature",
  "properties": {
    "iso:country":"DE",
    "sg:address":"Bahnhofstr. 24",
    "sg:city":"Eisenberg",
    "sg:phone":"+49 6351/44759",
    "sg:postcode":"67304",
    "sg:province":"Rheinland-Pfalz",
    "wof:name":"Intercity",
    "wof:placetype":"venue"
},
  "geometry": {"coordinates":[8.0692605972,49.5542945862],"type":"Point"}
}