{
  "type": "Feature",
  "properties": {
    "iso:country":"DE",
    "sg:address":"Humboldtstr. 90",
    "sg:city":"Bremen",
    "sg:phone":"+49 421/702230",
    "sg:postcode":"28203",
    "sg:province":"Bremen",
    "wof:name":"Heiko Janssen Rechtsanwalt",
    "wof:placetype":"venue"
},
  "geometry": {"coordinates":[8.829577446,53.0746955872],"type":"Point"}
}