{
  "type": "Feature",
  "properties": {
    "iso:country":"DE",
    "sg:address":"Gro\u00dfes Meer 12",
    "sg:city":"Papenburg",
    "sg:phone":"+49 4968/355",
    "sg:postcode":"26871",
    "sg:province":"Niedersachsen",
    "wof:name":"Helmut Ambra\u00df",
    "wof:placetype":"venue"
},
  "geometry": {"coordinates":[7.4006,53.022877],"type":"Point"}
}