{
  "type": "Feature",
  "properties": {
    "iso:country":"DE",
    "sg:address":"Sommestr. 10",
    "sg:city":"Stuttgart",
    "sg:postcode":"70374",
    "sg:province":"Baden-W\u00fcrttemberg",
    "wof:name":"Gm Consult It Gmbh Gesellschaft F\u00fcr Informations-",
    "wof:placetype":"venue"
},
  "geometry": {"coordinates":[9.2426671982,48.8062896729],"type":"Point"}
}