{
  "type": "Feature",
  "properties": {
    "iso:country":"DE",
    "sg:address":"Gereonstr. 42",
    "sg:city":"Vettwei\u00df",
    "sg:phone":"+49 2424/7173",
    "sg:postcode":"52391",
    "sg:province":"Nordrhein-Westfalen",
    "wof:name":"Ernst Dortu",
    "wof:placetype":"venue"
},
  "geometry": {"coordinates":[6.596842,50.73835],"type":"Point"}
}