{
  "type": "Feature",
  "properties": {
    "iso:country":"DE",
    "sg:address":"Hellkamp 17",
    "sg:city":"Hamburg",
    "sg:phone":"+49 40/408474",
    "sg:postcode":"20255",
    "sg:province":"Hamburg",
    "wof:name":"E. D\u00f6rr",
    "wof:placetype":"venue"
},
  "geometry": {"coordinates":[9.947422,53.577595],"type":"Point"}
}