{
  "type": "Feature",
  "properties": {
    "iso:country":"DE",
    "sg:address":"Robert-Koch-Weg 16",
    "sg:city":"Unna",
    "sg:phone":"+49 2303/953023",
    "sg:postcode":"59427",
    "sg:province":"Nordrhein-Westfalen",
    "wof:name":"Ortus Gmbh",
    "wof:placetype":"venue"
},
  "geometry": {"coordinates":[7.650853157,51.5434379578],"type":"Point"}
}