{
  "type": "Feature",
  "properties": {
    "iso:country":"DE",
    "sg:address":"Poststr. 5",
    "sg:city":"Halstenbek",
    "sg:phone":"+49 4101/46075",
    "sg:postcode":"25469",
    "sg:province":"Schleswig-Holstein",
    "wof:name":"Brandt Und Kwapil Rechtsanw\u00e4lte Und Notare",
    "wof:placetype":"venue"
},
  "geometry": {"coordinates":[9.8409280777,53.6364479065],"type":"Point"}
}