{
  "type": "Feature",
  "properties": {
    "iso:country":"DE",
    "sg:city":"Steinhagen",
    "sg:postcode":"18442",
    "sg:province":"Mecklenburg-Vorpommern",
    "wof:name":"Gr\u00fcne Energien Sparen Erzeugen Verbrauchen",
    "wof:placetype":"venue"
},
  "geometry": {"coordinates":[12.979525,54.224548],"type":"Point"}
}