{
  "type": "Feature",
  "properties": {
    "iso:country":"DE",
    "sg:address":"Im Birkenborn 13",
    "sg:city":"Waldfischbach-Burgalben",
    "sg:postcode":"67714",
    "sg:province":"Rheinland-Pfalz",
    "wof:name":"Rudi Frank Mech. Werkstatt",
    "wof:placetype":"venue"
},
  "geometry": {"coordinates":[7.661396,49.284046],"type":"Point"}
}