{
  "type": "Feature",
  "properties": {
    "iso:country":"DE",
    "sg:address":"Bergknappenstr. 16",
    "sg:city":"Bochum",
    "sg:phone":"+49 2327/23581",
    "sg:postcode":"44866",
    "sg:province":"Nordrhein-Westfalen",
    "wof:name":"Dr. Anton Und Herta Binder Rechtsanwalt Und Steuerberater",
    "wof:placetype":"venue"
},
  "geometry": {"coordinates":[7.1418151855,51.4980392456],"type":"Point"}
}