{
  "type": "Feature",
  "properties": {
    "iso:country":"DE",
    "sg:address":"Adolf-Fischer-Str. 6",
    "sg:city":"J\u00fclich",
    "sg:phone":"+49 2461/939362",
    "sg:postcode":"52428",
    "sg:province":"Nordrhein-Westfalen",
    "wof:name":"Sabine Twardowski Praxis F\u00fcr Ergotherapie",
    "wof:placetype":"venue"
},
  "geometry": {"coordinates":[6.362387,50.917542],"type":"Point"}
}