{
  "type": "Feature",
  "properties": {
    "iso:country":"DE",
    "sg:address":"S\u00fcdstr. 12",
    "sg:city":"Gera",
    "sg:phone":"+49 365/7106161",
    "sg:postcode":"07548",
    "sg:province":"Th\u00fcringen",
    "wof:name":"Hotel An Der Elster",
    "wof:placetype":"venue"
},
  "geometry": {"coordinates":[12.0773611069,50.8656654358],"type":"Point"}
}