{
  "type": "Feature",
  "properties": {
    "iso:country":"DE",
    "sg:address":"Sch\u00fctzenweg 53",
    "sg:city":"Stadtlohn",
    "sg:postcode":"48703",
    "sg:province":"Nordrhein-Westfalen",
    "wof:name":"Ko-paletten Gmbh",
    "wof:placetype":"venue"
},
  "geometry": {"coordinates":[6.888807,51.988243],"type":"Point"}
}