{
  "type": "Feature",
  "properties": {
    "iso:country":"DE",
    "sg:address":"Matthias-Claudius-Str. 1",
    "sg:city":"D\u00fcren",
    "sg:phone":"+49 2421/81731",
    "sg:postcode":"52353",
    "sg:province":"Nordrhein-Westfalen",
    "wof:name":"Steinmetzbetrieb Wolfgang Olszowi Gmbh",
    "wof:placetype":"venue"
},
  "geometry": {"coordinates":[6.4603409767,50.823764801],"type":"Point"}
}