{
  "type": "Feature",
  "properties": {
    "iso:country":"DE",
    "sg:address":"Kochenholzstr. 23",
    "sg:city":"Troisdorf",
    "sg:phone":"+49 2241/946021",
    "sg:postcode":"53842",
    "sg:province":"Nordrhein-Westfalen",
    "wof:name":"Markus B\u00f6hm E. Kfm.",
    "wof:placetype":"venue"
},
  "geometry": {"coordinates":[7.1170511246,50.8279457092],"type":"Point"}
}