{
  "type": "Feature",
  "properties": {
    "iso:country":"DE",
    "sg:address":"K\u00e4the-Kollwitz-Weg 15",
    "sg:city":"Coswig",
    "sg:phone":"+49 3523/72885",
    "sg:postcode":"01640",
    "sg:province":"Sachsen",
    "wof:name":"Manfred Kneusel",
    "wof:placetype":"venue"
},
  "geometry": {"coordinates":[13.5855026245,51.1352806091],"type":"Point"}
}