{
  "type": "Feature",
  "properties": {
    "iso:country":"DE",
    "sg:address":"Hauptstr. 125",
    "sg:city":"Grevenbroich",
    "sg:phone":"+49 2181/3891",
    "sg:postcode":"41517",
    "sg:province":"Nordrhein-Westfalen",
    "wof:name":"Herbert Ross Heilpraktiker",
    "wof:placetype":"venue"
},
  "geometry": {"coordinates":[6.5950798988,51.0747413635],"type":"Point"}
}