{
  "type": "Feature",
  "properties": {
    "iso:country":"DE",
    "sg:address":"Rathausstr. 2",
    "sg:city":"Quierschied",
    "sg:phone":"+49 6897/67761",
    "sg:postcode":"66287",
    "sg:province":"Saarland",
    "wof:name":"Reiseb\u00fcro Josef Andler Inh. Petra Andler",
    "wof:placetype":"venue"
},
  "geometry": {"coordinates":[7.0521669388,49.3264083862],"type":"Point"}
}