{
  "type": "Feature",
  "properties": {
    "iso:country":"DE",
    "sg:address":"Merkurstr. 35",
    "sg:city":"Fulda",
    "sg:phone":"+49 661/402880",
    "sg:postcode":"36041",
    "sg:province":"Hessen",
    "wof:name":"Ms Messebau & Transport Gmbh",
    "wof:placetype":"venue"
},
  "geometry": {"coordinates":[9.63121,50.548489],"type":"Point"}
}