{
  "type": "Feature",
  "properties": {
    "iso:country":"DE",
    "sg:address":"Nordwestring 101",
    "sg:city":"N\u00fcrnberg",
    "sg:phone":"+49 911/3950",
    "sg:postcode":"90419",
    "sg:province":"Bayern",
    "wof:name":"Gfk Ag",
    "wof:placetype":"venue"
},
  "geometry": {"coordinates":[11.053853,49.465351],"type":"Point"}
}