{
  "type": "Feature",
  "properties": {
    "iso:country":"DE",
    "sg:address":"Dorfstr. 24",
    "sg:city":"Tangstedt",
    "sg:phone":"+49 4109/9880",
    "sg:postcode":"22889",
    "sg:province":"Schleswig-Holstein",
    "wof:name":"B\u00e4rbel D\u00f6rling",
    "wof:placetype":"venue"
},
  "geometry": {"coordinates":[10.0834522247,53.7316207886],"type":"Point"}
}