{
  "type": "Feature",
  "properties": {
    "iso:country":"DE",
    "sg:address":"Dorfstr. 59",
    "sg:city":"B\u00e4renklau",
    "sg:phone":"+49 35691/266",
    "sg:postcode":"03172",
    "sg:province":"Brandenburg",
    "wof:name":"G\u00fcnter Schulz",
    "wof:placetype":"venue"
},
  "geometry": {"coordinates":[14.64193,51.953838],"type":"Point"}
}