{
  "type": "Feature",
  "properties": {
    "iso:country":"DE",
    "sg:address":"Osterseenstr. 26a",
    "sg:city":"Iffeldorf",
    "sg:phone":"+49 8856/4225",
    "sg:postcode":"82393",
    "sg:province":"Bayern",
    "wof:name":"Wolfgang Kling Ingenieur",
    "wof:placetype":"venue"
},
  "geometry": {"coordinates":[11.321223259,47.7754211426],"type":"Point"}
}