{
  "type": "Feature",
  "properties": {
    "iso:country":"DE",
    "sg:address":"Eichendorffstr. 56",
    "sg:city":"S\u00fcdlohn",
    "sg:phone":"+49 2862/7885",
    "sg:postcode":"46354",
    "sg:province":"Nordrhein-Westfalen",
    "wof:name":"Corona",
    "wof:placetype":"venue"
},
  "geometry": {"coordinates":[6.8728318214,51.9411849976],"type":"Point"}
}