{
  "type": "Feature",
  "properties": {
    "iso:country":"DE",
    "sg:address":"Gaterweg 120",
    "sg:city":"Duisburg",
    "sg:postcode":"47229",
    "sg:province":"Nordrhein-Westfalen",
    "wof:name":"Thommessen Gmbh",
    "wof:placetype":"venue"
},
  "geometry": {"coordinates":[6.7199959755,51.3934936523],"type":"Point"}
}