{
  "type": "Feature",
  "properties": {
    "iso:country":"DE",
    "sg:address":"Hohlheide 2",
    "sg:city":"Buchholz",
    "sg:phone":"+49 4181/28760",
    "sg:postcode":"21244",
    "sg:province":"Niedersachsen",
    "wof:name":"C + L Systemboden Norden Vertriebs Gmbh & Co. Kg",
    "wof:placetype":"venue"
},
  "geometry": {"coordinates":[9.846811,53.344303],"type":"Point"}
}