{
  "type": "Feature",
  "properties": {
    "iso:country":"DE",
    "sg:address":"Schuhstr. 42",
    "sg:city":"Erlangen",
    "sg:phone":"+49 9131/26869",
    "sg:postcode":"91052",
    "sg:province":"Bayern",
    "wof:name":"Contipark International Parking Gmbh",
    "wof:placetype":"venue"
},
  "geometry": {"coordinates":[11.0085220337,49.59192276],"type":"Point"}
}