{
  "type": "Feature",
  "properties": {
    "iso:country":"DE",
    "sg:address":"Silcherstr. 2",
    "sg:city":"K\u00f6ln",
    "sg:postcode":"50827",
    "sg:province":"Nordrhein-Westfalen",
    "wof:name":"Metallbau Wendt Gmbh",
    "wof:placetype":"venue"
},
  "geometry": {"coordinates":[6.899319,50.955662],"type":"Point"}
}