{
  "type": "Feature",
  "properties": {
    "iso:country":"DE",
    "sg:address":"Ostfeld 22",
    "sg:city":"Meschede",
    "sg:phone":"+49 2934/369",
    "sg:postcode":"59872",
    "sg:province":"Nordrhein-Westfalen",
    "wof:name":"Pension Friedhelm Mertens",
    "wof:placetype":"venue"
},
  "geometry": {"coordinates":[8.1349372864,51.2989501953],"type":"Point"}
}