{
  "type": "Feature",
  "properties": {
    "iso:country":"DE",
    "sg:address":"Thermalbadstr. 20",
    "sg:city":"Bad Griesbach",
    "sg:postcode":"94086",
    "sg:province":"Bayern",
    "wof:name":"Basis Betriebswirtschaftliche Beratung Im",
    "wof:placetype":"venue"
},
  "geometry": {"coordinates":[13.1871528625,48.4274597168],"type":"Point"}
}