{
  "type": "Feature",
  "properties": {
    "iso:country":"DE",
    "sg:address":"Murmelweg 6",
    "sg:city":"Bielefeld",
    "sg:phone":"+49 521/763091",
    "sg:postcode":"33729",
    "sg:province":"Nordrhein-Westfalen",
    "wof:name":"Fischer Und Hnida Steuerberater",
    "wof:placetype":"venue"
},
  "geometry": {"coordinates":[8.6256933212,52.0620155334],"type":"Point"}
}