{
  "type": "Feature",
  "properties": {
    "iso:country":"DE",
    "sg:address":"L\u00f6ningstr. 30",
    "sg:city":"Bremen",
    "sg:phone":"+49 421/324746",
    "sg:postcode":"28195",
    "sg:province":"Bremen",
    "wof:name":"Hotel Rheinischer Hof Inh. Irmgard Mekelburg",
    "wof:placetype":"venue"
},
  "geometry": {"coordinates":[8.8160562515,53.0800666809],"type":"Point"}
}