{
  "type": "Feature",
  "properties": {
    "iso:country":"DE",
    "sg:address":"Hochgernstr. 22",
    "sg:city":"Bergen",
    "sg:phone":"+49 8662/8111",
    "sg:postcode":"83346",
    "sg:province":"Bayern",
    "wof:name":"G\u00e4stehaus Bergblick Gmbh",
    "wof:placetype":"venue"
},
  "geometry": {"coordinates":[12.5874757767,47.8040428162],"type":"Point"}
}