{
  "type": "Feature",
  "properties": {
    "iso:country":"DE",
    "sg:address":"Amselweg 22",
    "sg:city":"Brombachtal",
    "sg:phone":"+49 6063/4045",
    "sg:postcode":"64753",
    "sg:province":"Hessen",
    "wof:name":"Werner Lippert",
    "wof:placetype":"venue"
},
  "geometry": {"coordinates":[8.9608898163,49.7414627075],"type":"Point"}
}