{
  "type": "Feature",
  "properties": {
    "iso:country":"DE",
    "sg:address":"Welserstr. 5",
    "sg:city":"Babenhausen",
    "sg:phone":"+49 8333/93740",
    "sg:postcode":"87727",
    "sg:province":"Bayern",
    "wof:name":"Peter M\u00fcller Anlageberater",
    "wof:placetype":"venue"
},
  "geometry": {"coordinates":[10.2506809235,48.1399803162],"type":"Point"}
}