{
  "type": "Feature",
  "properties": {
    "iso:country":"DE",
    "sg:address":"Alicestr. 21",
    "sg:city":"Lampertheim",
    "sg:postcode":"68623",
    "sg:province":"Hessen",
    "wof:name":"Meira-maschinen Export Gmbh",
    "wof:placetype":"venue"
},
  "geometry": {"coordinates":[8.47378,49.599186],"type":"Point"}
}