{
  "type": "Feature",
  "properties": {
    "iso:country":"DE",
    "sg:address":"Tr\u00fcperweg 2/Haus V",
    "sg:city":"Jena",
    "sg:phone":"+49 3641/336512",
    "sg:postcode":"07749",
    "sg:province":"Th\u00fcringen",
    "wof:name":"Dipl.-ing. M. Hufnagl",
    "wof:placetype":"venue"
},
  "geometry": {"coordinates":[11.5982961655,50.9035491943],"type":"Point"}
}