{
  "type": "Feature",
  "properties": {
    "iso:country":"DE",
    "sg:address":"Alte Landstr. 28",
    "sg:city":"Gossersweiler-Stein",
    "sg:phone":"+49 6346/5146",
    "sg:postcode":"76857",
    "sg:province":"Rheinland-Pfalz",
    "wof:name":"Norbert Welsch Masseur",
    "wof:placetype":"venue"
},
  "geometry": {"coordinates":[7.928054,49.159973],"type":"Point"}
}