{
  "type": "Feature",
  "properties": {
    "iso:country":"DE",
    "sg:address":"Dresdener Str. 83",
    "sg:city":"Hartha",
    "sg:phone":"+49 34328/38774",
    "sg:postcode":"04746",
    "sg:province":"Sachsen",
    "wof:name":"Elfriede Petzold",
    "wof:placetype":"venue"
},
  "geometry": {"coordinates":[12.9759750366,51.0922470093],"type":"Point"}
}