{
  "type": "Feature",
  "properties": {
    "iso:country":"DE",
    "sg:address":"Brandst\u00fccken 21",
    "sg:city":"Hamburg",
    "sg:phone":"+49 40/590185",
    "sg:postcode":"22549",
    "sg:province":"Hamburg",
    "wof:name":"Hth Hyperd\u00e4mm Und Bautechnik J\u00fcrgen Weimann",
    "wof:placetype":"venue"
},
  "geometry": {"coordinates":[9.850141,53.580158],"type":"Point"}
}