{
  "type": "Feature",
  "properties": {
    "iso:country":"DE",
    "sg:address":"Fritzlarer Str. 2",
    "sg:city":"Melsungen",
    "sg:phone":"+49 5661/73880",
    "sg:postcode":"34212",
    "sg:province":"Hessen",
    "wof:name":"Hans-j\u00fcrgen Heise & Partner Steuerberatungs Gmbh",
    "wof:placetype":"venue"
},
  "geometry": {"coordinates":[9.5425701141,51.1307296753],"type":"Point"}
}