{
  "type": "Feature",
  "properties": {
    "iso:country":"DE",
    "sg:address":"Augsburger Str. 26",
    "sg:city":"Germering",
    "sg:phone":"+49 89/846051",
    "sg:postcode":"82110",
    "sg:province":"Bayern",
    "wof:name":"Schellhorn Gmbh",
    "wof:placetype":"venue"
},
  "geometry": {"coordinates":[11.3653497696,48.1378707886],"type":"Point"}
}