{
  "type": "Feature",
  "properties": {
    "iso:country":"DE",
    "sg:address":"Unter der Maate 22",
    "sg:city":"Vechelde",
    "sg:phone":"+49 5300/6261",
    "sg:postcode":"38159",
    "sg:province":"Niedersachsen",
    "wof:name":"Dr. Med. Ursula Nahde",
    "wof:placetype":"venue"
},
  "geometry": {"coordinates":[10.3599510193,52.2177009583],"type":"Point"}
}