{
  "type": "Feature",
  "properties": {
    "iso:country":"DE",
    "sg:address":"Handwerkerstr. 1",
    "sg:city":"Blumberg",
    "sg:phone":"+49 7702/871",
    "sg:postcode":"78176",
    "sg:province":"Baden-W\u00fcrttemberg",
    "wof:name":"Pizzeria Da Mauro",
    "wof:placetype":"venue"
},
  "geometry": {"coordinates":[8.5334482193,47.8389282227],"type":"Point"}
}