{
  "type": "Feature",
  "properties": {
    "iso:country":"DE",
    "sg:address":"August-Bendler-Str. 35",
    "sg:city":"Schwelm",
    "sg:phone":"+49 2336/83256",
    "sg:postcode":"58332",
    "sg:province":"Nordrhein-Westfalen",
    "wof:name":"Freie Alten- Und Nachbarschaftshilfe E. V.",
    "wof:placetype":"venue"
},
  "geometry": {"coordinates":[7.284275,51.285839],"type":"Point"}
}