{
  "type": "Feature",
  "properties": {
    "iso:country":"DE",
    "sg:address":"Kaiserswerther Str. 115",
    "sg:city":"Ratingen",
    "sg:phone":"+49 2102/74260",
    "sg:postcode":"40880",
    "sg:province":"Nordrhein-Westfalen",
    "wof:name":"Noatec Gmbh",
    "wof:placetype":"venue"
},
  "geometry": {"coordinates":[6.817335,51.299706],"type":"Point"}
}