{
  "type": "Feature",
  "properties": {
    "iso:country":"DE",
    "sg:address":"Horbacher Str. 321",
    "sg:city":"Aachen",
    "sg:postcode":"52072",
    "sg:province":"Nordrhein-Westfalen",
    "wof:name":"Jashen Handels Gmbh",
    "wof:placetype":"venue"
},
  "geometry": {"coordinates":[6.0450100899,50.8329658508],"type":"Point"}
}