{
  "type": "Feature",
  "properties": {
    "iso:country":"DE",
    "sg:address":"Sporenstr. 9",
    "sg:city":"Altenburg",
    "sg:postcode":"04600",
    "sg:province":"Th\u00fcringen",
    "wof:name":"Holiday Land Bon Voyage Reiseb\u00fcro Gmbh",
    "wof:placetype":"venue"
},
  "geometry": {"coordinates":[12.4348840714,50.9862442017],"type":"Point"}
}