{
  "type": "Feature",
  "properties": {
    "iso:country":"DE",
    "sg:address":"Luruper Hauptstr. 149",
    "sg:city":"Hamburg",
    "sg:phone":"+49 40/83210368",
    "sg:postcode":"22547",
    "sg:province":"Hamburg",
    "wof:name":"Volker Sinnig",
    "wof:placetype":"venue"
},
  "geometry": {"coordinates":[9.8722391129,53.5917434692],"type":"Point"}
}