{
  "type": "Feature",
  "properties": {
    "iso:country":"DE",
    "sg:address":"Am Rundling 10",
    "sg:city":"Priestewitz",
    "sg:postcode":"01561",
    "sg:province":"Sachsen",
    "wof:name":"Gamma Industrievertrieb Gmbh",
    "wof:placetype":"venue"
},
  "geometry": {"coordinates":[13.582067,51.248604],"type":"Point"}
}