{
  "type": "Feature",
  "properties": {
    "iso:country":"DE",
    "sg:address":"Harmoniestr. 22",
    "sg:city":"Wuppertal",
    "sg:phone":"+49 202/449394",
    "sg:postcode":"42107",
    "sg:province":"Nordrhein-Westfalen",
    "wof:name":"Optident Dentallabor Gmbh",
    "wof:placetype":"venue"
},
  "geometry": {"coordinates":[7.15151,51.259155],"type":"Point"}
}