{
  "type": "Feature",
  "properties": {
    "iso:country":"DE",
    "sg:address":"Veilchenweg 11",
    "sg:city":"Hanau",
    "sg:postcode":"63456",
    "sg:province":"Hessen",
    "wof:name":"Gemeinn\u00fctzige Bau- Und Siedlungsgenossenschaft",
    "wof:placetype":"venue"
},
  "geometry": {"coordinates":[8.924030304,50.09815979],"type":"Point"}
}