{
  "type": "Feature",
  "properties": {
    "iso:country":"DE",
    "sg:address":"Vorstadtplatz 8",
    "sg:city":"Nagold",
    "sg:phone":"+49 7452/839638",
    "sg:postcode":"72202",
    "sg:province":"Baden-W\u00fcrttemberg",
    "wof:name":"Reiseb\u00fcro R\u00fcbenacker",
    "wof:placetype":"venue"
},
  "geometry": {"coordinates":[8.7240839005,48.5501937866],"type":"Point"}
}