{
  "type": "Feature",
  "properties": {
    "iso:country":"DE",
    "sg:address":"Knorrstr. 1",
    "sg:city":"Heilbronn",
    "sg:phone":"+49 4971/315011",
    "sg:postcode":"74074",
    "sg:province":"Baden-W\u00fcrttemberg",
    "wof:name":"Unilever Bestfoods Deutschland Gmbh",
    "wof:placetype":"venue"
},
  "geometry": {"coordinates":[9.216873,49.131985],"type":"Point"}
}