{
  "type": "Feature",
  "properties": {
    "iso:country":"DE",
    "sg:address":"Werderstr. 126",
    "sg:city":"Heilbronn",
    "sg:phone":"+49 7131/629129",
    "sg:postcode":"74074",
    "sg:province":"Baden-W\u00fcrttemberg",
    "wof:name":"Hans Lughofer - Planungs- Und Koordinierungsb\u00fcro",
    "wof:placetype":"venue"
},
  "geometry": {"coordinates":[9.2213134766,49.1329803467],"type":"Point"}
}