{
  "type": "Feature",
  "properties": {
    "iso:country":"DE",
    "sg:address":"Passauer Str. 43",
    "sg:city":"R\u00f6hrnbach",
    "sg:phone":"+49 8582/321",
    "sg:postcode":"94133",
    "sg:province":"Bayern",
    "wof:name":"M\u00f6bel-k\u00f6ck E. K.",
    "wof:placetype":"venue"
},
  "geometry": {"coordinates":[13.523461,48.733295],"type":"Point"}
}