{
  "type": "Feature",
  "properties": {
    "iso:country":"DE",
    "sg:address":"\u00d6schelbronner Str. 14/1",
    "sg:city":"Wurmberg",
    "sg:phone":"+49 7044/950485",
    "sg:postcode":"75449",
    "sg:province":"Baden-W\u00fcrttemberg",
    "wof:name":"Mobil Tel",
    "wof:placetype":"venue"
},
  "geometry": {"coordinates":[8.8206911087,48.8731613159],"type":"Point"}
}