{
  "type": "Feature",
  "properties": {
    "iso:country":"DE",
    "sg:address":"Oberstr. 1",
    "sg:city":"Remscheid",
    "sg:phone":"+49 2191/963701",
    "sg:postcode":"42897",
    "sg:province":"Nordrhein-Westfalen",
    "wof:name":"Pur Gmbh",
    "wof:placetype":"venue"
},
  "geometry": {"coordinates":[7.2613592148,51.1520385742],"type":"Point"}
}