{
  "type": "Feature",
  "properties": {
    "iso:country":"DE",
    "sg:address":"Drosselweg 10",
    "sg:city":"Mendig",
    "sg:postcode":"56743",
    "sg:province":"Rheinland-Pfalz",
    "wof:name":"Service Pro Senioren Christa Dressler E. K.",
    "wof:placetype":"venue"
},
  "geometry": {"coordinates":[7.28866,50.365559],"type":"Point"}
}