{
  "type": "Feature",
  "properties": {
    "iso:country":"DE",
    "sg:address":"Josef-Biberacher-Str. 12",
    "sg:city":"Jettingen-Scheppach",
    "sg:phone":"+49 8225/3753",
    "sg:postcode":"89343",
    "sg:province":"Bayern",
    "wof:name":"Mayr Haus- Und Mieter- Verwaltungen Gmbh",
    "wof:placetype":"venue"
},
  "geometry": {"coordinates":[10.4521131516,48.4046897888],"type":"Point"}
}