{
  "type": "Feature",
  "properties": {
    "iso:country":"DE",
    "sg:address":"Schlierbergstr. 88",
    "sg:city":"Freiburg",
    "sg:phone":"+49 761/403748",
    "sg:postcode":"79100",
    "sg:province":"Baden-W\u00fcrttemberg",
    "wof:name":"Helga Jeske-knoell Rechtsanw\u00e4ltin",
    "wof:placetype":"venue"
},
  "geometry": {"coordinates":[7.8327770233,47.9774475098],"type":"Point"}
}