{
  "type": "Feature",
  "properties": {
    "iso:country":"DE",
    "sg:address":"Fritz-Gastager-Str. 2",
    "sg:city":"Inzell",
    "sg:phone":"+49 8665/6720",
    "sg:postcode":"83334",
    "sg:province":"Bayern",
    "wof:name":"Alpen-hotel Gastager",
    "wof:placetype":"venue"
},
  "geometry": {"coordinates":[12.7499103546,47.7618751526],"type":"Point"}
}