{
  "type": "Feature",
  "properties": {
    "iso:country":"DE",
    "sg:address":"Lutterothstr. 54",
    "sg:city":"Hamburg",
    "sg:phone":"+49 40/4914287",
    "sg:postcode":"20255",
    "sg:province":"Hamburg",
    "wof:name":"Bernd H\u00f6cker",
    "wof:placetype":"venue"
},
  "geometry": {"coordinates":[9.9508523941,53.5814590454],"type":"Point"}
}