{
  "type": "Feature",
  "properties": {
    "iso:country":"DE",
    "sg:address":"Am Br\u00fcnnlein 3",
    "sg:city":"Uffenheim",
    "sg:phone":"+49 9842/98300",
    "sg:postcode":"97215",
    "sg:province":"Bayern",
    "wof:name":"Hans B\u00f6hm Inh. Klaus B\u00f6hm",
    "wof:placetype":"venue"
},
  "geometry": {"coordinates":[10.2405462265,49.5547828674],"type":"Point"}
}