{
  "type": "Feature",
  "properties": {
    "iso:country":"DE",
    "sg:address":"Goebenstr. 6",
    "sg:city":"Bonn",
    "sg:phone":"+49 228/216236",
    "sg:postcode":"53113",
    "sg:province":"Nordrhein-Westfalen",
    "wof:name":"Dr. Hans-reinhard Koch Rechtsanwalt",
    "wof:placetype":"venue"
},
  "geometry": {"coordinates":[7.0996417999,50.7258911133],"type":"Point"}
}