{
  "type": "Feature",
  "properties": {
    "iso:country":"DE",
    "sg:address":"Hauptstr. 53",
    "sg:city":"Rellingen",
    "sg:phone":"+49 4101/552144",
    "sg:postcode":"25462",
    "sg:province":"Schleswig-Holstein",
    "wof:name":"Dr. Hans-joachim Winter Rechtsanwalt",
    "wof:placetype":"venue"
},
  "geometry": {"coordinates":[9.8292360306,53.652141571],"type":"Point"}
}