{
  "type": "Feature",
  "properties": {
    "iso:country":"DE",
    "sg:address":"Molkereistr 5",
    "sg:city":"Waldstetten",
    "sg:phone":"+49 8223/962353",
    "sg:postcode":"89367",
    "sg:province":"Bayern",
    "wof:name":"G\u00f6ke Glastechnik, Gebietsleitung S\u00fcd, Klaus & Back",
    "wof:placetype":"venue"
},
  "geometry": {"coordinates":[10.2913980484,48.3488693237],"type":"Point"}
}