{
  "type": "Feature",
  "properties": {
    "iso:country":"DE",
    "sg:address":"Genkeler Str. 46",
    "sg:city":"Meinerzhagen",
    "sg:phone":"+49 2354/12119",
    "sg:postcode":"58540",
    "sg:province":"Nordrhein-Westfalen",
    "wof:name":"Michael Holz",
    "wof:placetype":"venue"
},
  "geometry": {"coordinates":[7.6306891441,51.0973472595],"type":"Point"}
}