{
  "type": "Feature",
  "properties": {
    "iso:country":"DE",
    "sg:address":"Fibigerstr. 83",
    "sg:city":"Hamburg",
    "sg:phone":"+49 40/43181618",
    "sg:postcode":"22419",
    "sg:province":"Hamburg",
    "wof:name":"J\u00fcrgen Strumpf Architekt",
    "wof:placetype":"venue"
},
  "geometry": {"coordinates":[10.008832,53.676708],"type":"Point"}
}