{
  "type": "Feature",
  "properties": {
    "iso:country":"DE",
    "sg:address":"R\u00f6denhof 33",
    "sg:city":"Neuburg",
    "sg:postcode":"86633",
    "sg:province":"Bayern",
    "wof:name":"Heindl",
    "wof:placetype":"venue"
},
  "geometry": {"coordinates":[11.20463,48.745602],"type":"Point"}
}