{
  "type": "Feature",
  "properties": {
    "iso:country":"DE",
    "sg:address":"Deutschherrnstr. 21",
    "sg:city":"Saarbr\u00fccken",
    "sg:phone":"+49 681/51363",
    "sg:postcode":"66117",
    "sg:province":"Saarland",
    "wof:name":"Elkes Reinigungs-center Und \u00c4nderungs-atelier",
    "wof:placetype":"venue"
},
  "geometry": {"coordinates":[6.978553,49.231617],"type":"Point"}
}