{
  "type": "Feature",
  "properties": {
    "iso:country":"DE",
    "sg:address":"Irene-K\u00e4rcher-Str. 2-8",
    "sg:city":"Obersontheim",
    "sg:phone":"+49 7973/6920",
    "sg:postcode":"74423",
    "sg:province":"Baden-W\u00fcrttemberg",
    "wof:name":"Alfred K\u00e4rcher Gmbh & Co. Vertriebs- Und Verteil-zentrum",
    "wof:placetype":"venue"
},
  "geometry": {"coordinates":[9.8893098831,49.0540313721],"type":"Point"}
}