{
  "type": "Feature",
  "properties": {
    "iso:country":"DE",
    "sg:address":"Franz-Neumaier-Str. 11",
    "sg:city":"Durmersheim",
    "sg:phone":"+49 7245/937051",
    "sg:postcode":"76448",
    "sg:province":"Baden-W\u00fcrttemberg",
    "wof:name":"Burg-badm\u00f6bel Gmbh",
    "wof:placetype":"venue"
},
  "geometry": {"coordinates":[8.283721,48.942066],"type":"Point"}
}