{
  "type": "Feature",
  "properties": {
    "iso:country":"DE",
    "sg:address":"Bahnhofstr. 11",
    "sg:city":"Waltenhofen",
    "sg:postcode":"87448",
    "sg:province":"Bayern",
    "wof:name":"Immcona E. K.",
    "wof:placetype":"venue"
},
  "geometry": {"coordinates":[10.3052902222,47.6701431274],"type":"Point"}
}