{
  "type": "Feature",
  "properties": {
    "iso:country":"DE",
    "sg:address":"B\u00f6defelder Str. 11",
    "sg:city":"Winterberg",
    "sg:postcode":"59955",
    "sg:province":"Nordrhein-Westfalen",
    "wof:name":"P Und B Fliesen Und Naturstein Gmbh",
    "wof:placetype":"venue"
},
  "geometry": {"coordinates":[8.4431447983,51.2514152527],"type":"Point"}
}