{
  "type": "Feature",
  "properties": {
    "iso:country":"DE",
    "sg:address":"Reichenbachstr. 1",
    "sg:city":"M\u00fcnchen",
    "sg:phone":"+49 89/222620",
    "sg:postcode":"80469",
    "sg:province":"Bayern",
    "wof:name":"J\u00fcrgen K. R\u00f6der",
    "wof:placetype":"venue"
},
  "geometry": {"coordinates":[11.576567,48.134251],"type":"Point"}
}