{
  "type": "Feature",
  "properties": {
    "iso:country":"DE",
    "sg:address":"Ortsstr. 15",
    "sg:city":"M\u00fchltal",
    "sg:phone":"+49 6154/631472",
    "sg:postcode":"64367",
    "sg:province":"Hessen",
    "wof:name":"Waschenbacher Hof",
    "wof:placetype":"venue"
},
  "geometry": {"coordinates":[8.7082338333,49.8040161133],"type":"Point"}
}