{
  "type": "Feature",
  "properties": {
    "iso:country":"DE",
    "sg:address":"Dedinghauser Weg 3",
    "sg:city":"Schlangen",
    "sg:phone":"+49 5252/83252",
    "sg:postcode":"33189",
    "sg:province":"Nordrhein-Westfalen",
    "wof:name":"Annette Fischer",
    "wof:placetype":"venue"
},
  "geometry": {"coordinates":[8.8476829529,51.8075447083],"type":"Point"}
}