{
  "type": "Feature",
  "properties": {
    "iso:country":"DE",
    "sg:address":"Bahnhofstr. 32",
    "sg:city":"Bad Honnef",
    "sg:phone":"+49 2224/6165",
    "sg:postcode":"53604",
    "sg:province":"Nordrhein-Westfalen",
    "wof:name":"Herbert Fuchs",
    "wof:placetype":"venue"
},
  "geometry": {"coordinates":[7.222424,50.641865],"type":"Point"}
}