{
  "type": "Feature",
  "properties": {
    "iso:country":"DE",
    "sg:address":"M\u00fchlstr. 4",
    "sg:city":"Heidesheim",
    "sg:phone":"+49 6132/56280",
    "sg:postcode":"55262",
    "sg:province":"Rheinland-Pfalz",
    "wof:name":"Malerbetrieb Uwe Cesla Gmbh",
    "wof:placetype":"venue"
},
  "geometry": {"coordinates":[8.114642,49.995472],"type":"Point"}
}