{
  "type": "Feature",
  "properties": {
    "iso:country":"DE",
    "sg:address":"Schlo\u00dfgasse 65",
    "sg:city":"Weiterstadt",
    "sg:phone":"+49 6150/53316",
    "sg:postcode":"64331",
    "sg:province":"Hessen",
    "wof:name":"Matthias Lengfeld Architekt Und Ingenieur",
    "wof:placetype":"venue"
},
  "geometry": {"coordinates":[8.60697,49.93],"type":"Point"}
}