{
  "type": "Feature",
  "properties": {
    "iso:country":"DE",
    "sg:address":"Rabanusstr. 5",
    "sg:city":"Fulda",
    "sg:phone":"+49 661/71539",
    "sg:postcode":"36037",
    "sg:province":"Hessen",
    "wof:name":"Flip-inn",
    "wof:placetype":"venue"
},
  "geometry": {"coordinates":[9.6777801514,50.5538368225],"type":"Point"}
}