{
  "type": "Feature",
  "properties": {
    "iso:country":"DE",
    "sg:address":"Bro\u00dfhauser Str. 4",
    "sg:city":"Solingen",
    "sg:phone":"+49 4979/3194490",
    "sg:postcode":"42697",
    "sg:province":"Nordrhein-Westfalen",
    "wof:name":"Limot L\u00dcftungstechnik Gmbh & Co. Kg",
    "wof:placetype":"venue"
},
  "geometry": {"coordinates":[9.772351,49.485123],"type":"Point"}
}