{
  "type": "Feature",
  "properties": {
    "iso:country":"DE",
    "sg:address":"Flamerscheid 2",
    "sg:city":"Leichlingen",
    "sg:phone":"+49 2174/30672",
    "sg:postcode":"42799",
    "sg:province":"Nordrhein-Westfalen",
    "wof:name":"Ch. Jung",
    "wof:placetype":"venue"
},
  "geometry": {"coordinates":[7.1101298332,51.123260498],"type":"Point"}
}