{
  "type": "Feature",
  "properties": {
    "iso:country":"DE",
    "sg:address":"Alte Ortsstr. 12",
    "sg:city":"Blomberg",
    "sg:phone":"+49 5235/6359",
    "sg:postcode":"32825",
    "sg:province":"Nordrhein-Westfalen",
    "wof:name":"Rolf Fr\u00f6hlking",
    "wof:placetype":"venue"
},
  "geometry": {"coordinates":[9.024448,51.939304],"type":"Point"}
}