{
  "type": "Feature",
  "properties": {
    "iso:country":"DE",
    "sg:address":"Seegerstr. 7",
    "sg:city":"Pforzheim",
    "sg:phone":"+49 7231/97230",
    "sg:postcode":"75180",
    "sg:province":"Baden-W\u00fcrttemberg",
    "wof:name":"Jung Rudolph Webel Freie Architekten Und",
    "wof:placetype":"venue"
},
  "geometry": {"coordinates":[8.6804962158,48.8779449463],"type":"Point"}
}