{
  "type": "Feature",
  "properties": {
    "iso:country":"DE",
    "sg:address":"Am Igelsbach 9",
    "sg:city":"Rothenburg",
    "sg:phone":"+49 9861/3453",
    "sg:postcode":"91541",
    "sg:province":"Bayern",
    "wof:name":"L. Eisenmann Alt- Und Abfallstoffe",
    "wof:placetype":"venue"
},
  "geometry": {"coordinates":[10.200738,49.366879],"type":"Point"}
}