{
  "type": "Feature",
  "properties": {
    "iso:country":"DE",
    "sg:address":"Genfer Platz 19",
    "sg:city":"M\u00fcnchen",
    "sg:phone":"+49 89/7596293",
    "sg:postcode":"81476",
    "sg:province":"Bayern",
    "wof:name":"Bwb Immobilien",
    "wof:placetype":"venue"
},
  "geometry": {"coordinates":[11.489859581,48.0945930481],"type":"Point"}
}