{
  "type": "Feature",
  "properties": {
    "iso:country":"DE",
    "sg:address":"Gewerbestr. 8",
    "sg:city":"Schnaitsee",
    "sg:phone":"+49 8074/8134",
    "sg:postcode":"83530",
    "sg:province":"Bayern",
    "wof:name":"Bertram Schmitt",
    "wof:placetype":"venue"
},
  "geometry": {"coordinates":[12.4119596481,48.0812530518],"type":"Point"}
}