{
  "type": "Feature",
  "properties": {
    "iso:country":"DE",
    "sg:address":"Bebelplatz 7",
    "sg:city":"K\u00f6ln",
    "sg:phone":"+49 221/881535",
    "sg:postcode":"50679",
    "sg:province":"Nordrhein-Westfalen",
    "wof:name":"Millamusic E. K.",
    "wof:placetype":"venue"
},
  "geometry": {"coordinates":[6.9745230675,50.9298057556],"type":"Point"}
}