{
  "type": "Feature",
  "properties": {
    "iso:country":"DE",
    "sg:address":"Industriestr. 6",
    "sg:city":"Gundelfingen",
    "sg:phone":"+49 9073/95940",
    "sg:postcode":"89423",
    "sg:province":"Bayern",
    "wof:name":"Siegfried W\u00f6lz Stahl- Und Metallbau Gmbh",
    "wof:placetype":"venue"
},
  "geometry": {"coordinates":[7.862169,48.037632],"type":"Point"}
}