{
  "type": "Feature",
  "properties": {
    "iso:country":"DE",
    "sg:address":"Emil-Geis-Str. 1",
    "sg:city":"Gr\u00fcnwald",
    "sg:phone":"+49 89/6414912",
    "sg:postcode":"82031",
    "sg:province":"Bayern",
    "wof:name":"Fruchtpalette",
    "wof:placetype":"venue"
},
  "geometry": {"coordinates":[11.5216293335,48.0397872925],"type":"Point"}
}