{
  "type": "Feature",
  "properties": {
    "iso:country":"DE",
    "sg:address":"Hauptstr. 40",
    "sg:city":"Karlshagen",
    "sg:phone":"+49 38371/20158",
    "sg:postcode":"17449",
    "sg:province":"Mecklenburg-Vorpommern",
    "wof:name":"Club Karlshagen",
    "wof:placetype":"venue"
},
  "geometry": {"coordinates":[13.8340520859,54.1133918762],"type":"Point"}
}