{
  "type": "Feature",
  "properties": {
    "iso:country":"DE",
    "sg:address":"Bernardstr. 79",
    "sg:city":"Offenbach",
    "sg:phone":"+49 4950/4194610",
    "sg:postcode":"63067",
    "sg:province":"Hessen",
    "wof:name":"Pfau Kommunalger\u00c4te Gmbh",
    "wof:placetype":"venue"
},
  "geometry": {"coordinates":[9.5089559555,52.1717376709],"type":"Point"}
}