{
  "type": "Feature",
  "properties": {
    "iso:country":"DE",
    "sg:address":"Wilh\u00f6rster Teich 9",
    "sg:city":"H\u00f6velhof",
    "sg:phone":"+49 5257/6085",
    "sg:postcode":"33161",
    "sg:province":"Nordrhein-Westfalen",
    "wof:name":"Dierks Immo Gmbh",
    "wof:placetype":"venue"
},
  "geometry": {"coordinates":[8.6750679016,51.828792572],"type":"Point"}
}