{
  "type": "Feature",
  "properties": {
    "iso:country":"DE",
    "sg:address":"Kirchstr. 13",
    "sg:city":"Bous",
    "sg:phone":"+49 6834/7938",
    "sg:postcode":"66359",
    "sg:province":"Saarland",
    "wof:name":"Lidl Gmbh & Co. Kg",
    "wof:placetype":"venue"
},
  "geometry": {"coordinates":[6.7970209122,49.2756538391],"type":"Point"}
}