{
  "type": "Feature",
  "properties": {
    "iso:country":"DE",
    "sg:address":"Rhenetal 7",
    "sg:city":"Diemelsee",
    "sg:phone":"+49 5633/1092",
    "sg:postcode":"34519",
    "sg:province":"Hessen",
    "wof:name":"G\u00e4stehaus Luise Fischer",
    "wof:placetype":"venue"
},
  "geometry": {"coordinates":[8.7884483337,51.3303909302],"type":"Point"}
}