{
  "type": "Feature",
  "properties": {
    "iso:country":"DE",
    "sg:address":"Oehlertring 15",
    "sg:city":"Berlin",
    "sg:phone":"+49 30/7962124",
    "sg:postcode":"12169",
    "sg:province":"Berlin",
    "wof:name":"Gerh. Schneider Architekt",
    "wof:placetype":"venue"
},
  "geometry": {"coordinates":[13.353012,52.452946],"type":"Point"}
}