{
  "type": "Feature",
  "properties": {
    "iso:country":"DE",
    "sg:address":"Hauptstr. 31",
    "sg:city":"Silberstedt",
    "sg:phone":"+49 4626/777",
    "sg:postcode":"24887",
    "sg:province":"Schleswig-Holstein",
    "wof:name":"Provinzial Versicherung",
    "wof:placetype":"venue"
},
  "geometry": {"coordinates":[9.3723993301,54.5186424255],"type":"Point"}
}