{
  "type": "Feature",
  "properties": {
    "iso:country":"DE",
    "sg:address":"Poststr. 7",
    "sg:city":"Uetze",
    "sg:phone":"+49 172 4334006",
    "sg:postcode":"31311",
    "sg:province":"Niedersachsen",
    "wof:name":"Hans-joachim Finger",
    "wof:placetype":"venue"
},
  "geometry": {"coordinates":[10.183186,52.406349],"type":"Point"}
}