{
  "type": "Feature",
  "properties": {
    "iso:country":"DE",
    "sg:address":"Am Igelsbach 8",
    "sg:city":"Rothenburg ob der Tauber",
    "sg:phone":"+49 9861/86446",
    "sg:postcode":"91541",
    "sg:province":"Bayern",
    "wof:name":"Fachfirma D\u00fcrr Gmbh & Co. Kg - Orbitalis",
    "wof:placetype":"venue"
},
  "geometry": {"coordinates":[10.1996183395,49.3670501709],"type":"Point"}
}