{
  "type": "Feature",
  "properties": {
    "iso:country":"DE",
    "sg:address":"Austr. 36",
    "sg:city":"Elchingen",
    "sg:phone":"+49 4973/1264492",
    "sg:postcode":"89275",
    "sg:province":"Bayern",
    "wof:name":"Ulmer Volksbank Eg",
    "wof:placetype":"venue"
},
  "geometry": {"coordinates":[10.053116,48.437618],"type":"Point"}
}