{
  "type": "Feature",
  "properties": {
    "iso:country":"DE",
    "sg:address":"Kuhlenstr. 42",
    "sg:city":"M\u00fclheim",
    "sg:phone":"+49 208/472725",
    "sg:postcode":"45468",
    "sg:province":"Nordrhein-Westfalen",
    "wof:name":"Gastst\u00e4tte Haus Metz",
    "wof:placetype":"venue"
},
  "geometry": {"coordinates":[6.8934879303,51.4375038147],"type":"Point"}
}