{
  "type": "Feature",
  "properties": {
    "iso:country":"DE",
    "sg:address":"Mecklenbecker Str. 239",
    "sg:city":"M\u00fcnster",
    "sg:phone":"+49 251/71860",
    "sg:postcode":"48163",
    "sg:province":"Nordrhein-Westfalen",
    "wof:name":"Gewinnsparverein Der Volksbanken Und Spar- Und",
    "wof:placetype":"venue"
},
  "geometry": {"coordinates":[7.58898592,51.9379348755],"type":"Point"}
}