{
  "type": "Feature",
  "properties": {
    "iso:country":"DE",
    "sg:address":"Oppersh\u00e4user Str. 28",
    "sg:city":"Lachendorf",
    "sg:phone":"+49 5145/1206",
    "sg:postcode":"29331",
    "sg:province":"Niedersachsen",
    "wof:name":"Olympus Optical \u00c4rztebedarf",
    "wof:placetype":"venue"
},
  "geometry": {"coordinates":[10.239803,52.617569],"type":"Point"}
}