{
  "type": "Feature",
  "properties": {
    "iso:country":"DE",
    "sg:address":"Landsberger Str. 59",
    "sg:city":"M\u00fcnchen",
    "sg:postcode":"80339",
    "sg:province":"Bayern",
    "wof:name":"Matthies Immobilien E. K.",
    "wof:placetype":"venue"
},
  "geometry": {"coordinates":[11.539665,48.139519],"type":"Point"}
}