{
  "type": "Feature",
  "properties": {
    "iso:country":"DE",
    "sg:address":"Darwinstr. 4",
    "sg:city":"Berlin",
    "sg:phone":"+49 30/34998100",
    "sg:postcode":"10589",
    "sg:province":"Berlin",
    "wof:name":"Conus Gmbh",
    "wof:placetype":"venue"
},
  "geometry": {"coordinates":[13.3147630692,52.5214042664],"type":"Point"}
}