{
  "type": "Feature",
  "properties": {
    "iso:country":"DE",
    "sg:address":"Gutbrodstr. 6",
    "sg:city":"Stuttgart",
    "sg:phone":"+49 711/6366088",
    "sg:postcode":"70197",
    "sg:province":"Baden-W\u00fcrttemberg",
    "wof:name":"Edmund S\u00fc\u00dfbrich",
    "wof:placetype":"venue"
},
  "geometry": {"coordinates":[9.154135704,48.7742004395],"type":"Point"}
}