{
  "type": "Feature",
  "properties": {
    "iso:country":"DE",
    "sg:address":"Schwalbenweg 5",
    "sg:city":"Braunschweig",
    "sg:phone":"+49 531/577191",
    "sg:postcode":"38118",
    "sg:province":"Niedersachsen",
    "wof:name":"City-reisen Eugen M\u00fcller Kg",
    "wof:placetype":"venue"
},
  "geometry": {"coordinates":[10.4985027313,52.2646217346],"type":"Point"}
}