{
  "type": "Feature",
  "properties": {
    "iso:country":"DE",
    "sg:address":"Edisonstr. 7",
    "sg:city":"Henstedt-Ulzburg",
    "sg:phone":"+49 4193/899230",
    "sg:postcode":"24558",
    "sg:province":"Schleswig-Holstein",
    "wof:name":"Sch\u00fcler Gmbh",
    "wof:placetype":"venue"
},
  "geometry": {"coordinates":[9.9838676453,53.7641334534],"type":"Point"}
}