{
  "type": "Feature",
  "properties": {
    "iso:country":"DE",
    "sg:address":"Rixbecker Str. 61",
    "sg:city":"Lippstadt",
    "sg:phone":"+49 2941/77884",
    "sg:postcode":"59555",
    "sg:province":"Nordrhein-Westfalen",
    "wof:name":"O. Stellmacher",
    "wof:placetype":"venue"
},
  "geometry": {"coordinates":[8.3529500961,51.6716117859],"type":"Point"}
}