{
  "type": "Feature",
  "properties": {
    "iso:country":"DE",
    "sg:address":"Am Oxer 6",
    "sg:city":"Harrislee",
    "sg:phone":"+49 461/773366",
    "sg:postcode":"24955",
    "sg:province":"Schleswig-Holstein",
    "wof:name":"Dirk Jobs",
    "wof:placetype":"venue"
},
  "geometry": {"coordinates":[9.367181,54.801723],"type":"Point"}
}