{
  "type": "Feature",
  "properties": {
    "iso:country":"DE",
    "sg:address":"Hauptstr 25a",
    "sg:city":"Barsb\u00fcttel",
    "sg:phone":"+49 40/6705090",
    "sg:postcode":"22885",
    "sg:province":"Schleswig-Holstein",
    "wof:name":"Software Service Stadermann Gmbh",
    "wof:placetype":"venue"
},
  "geometry": {"coordinates":[10.1598176956,53.5687217712],"type":"Point"}
}