{
  "type": "Feature",
  "properties": {
    "iso:country":"DE",
    "sg:address":"Im Schwarzenbusch 8",
    "sg:city":"Marxzell",
    "sg:phone":"+49 4934/194503",
    "sg:postcode":"76359",
    "sg:province":"Baden-W\u00fcrttemberg",
    "wof:name":"Frank Fahrzeugbau Gmbh",
    "wof:placetype":"venue"
},
  "geometry": {"coordinates":[12.2308301926,51.281829834],"type":"Point"}
}