{
  "type": "Feature",
  "properties": {
    "iso:country":"DE",
    "sg:address":"Mainstr. 121",
    "sg:city":"Offenbach",
    "sg:phone":"+49 69/887496",
    "sg:postcode":"63065",
    "sg:province":"Hessen",
    "wof:name":"Te Gmbh Test Engineering",
    "wof:placetype":"venue"
},
  "geometry": {"coordinates":[8.7710027695,50.1069068909],"type":"Point"}
}