{
  "type": "Feature",
  "properties": {
    "iso:country":"DE",
    "sg:address":"Berliner Str. 7d",
    "sg:city":"Velten",
    "sg:phone":"+49 3304/39200",
    "sg:postcode":"16727",
    "sg:province":"Brandenburg",
    "wof:name":"Matth\u00e4i Bauunternehmen Gmbh & Co. Kg",
    "wof:placetype":"venue"
},
  "geometry": {"coordinates":[13.191782,52.675339],"type":"Point"}
}