{
  "type": "Feature",
  "properties": {
    "iso:country":"DE",
    "sg:address":"Bergham",
    "sg:city":"Bad Endorf",
    "sg:phone":"+49 8053/9715",
    "sg:postcode":"83093",
    "sg:province":"Bayern",
    "wof:name":"G\u00e4stehaus Franken",
    "wof:placetype":"venue"
},
  "geometry": {"coordinates":[12.2802095413,47.9008979797],"type":"Point"}
}