{
  "type": "Feature",
  "properties": {
    "iso:country":"DE",
    "sg:address":"Steigstr. 65",
    "sg:city":"Stuttgart",
    "sg:phone":"+49 711/747363",
    "sg:postcode":"70565",
    "sg:province":"Baden-W\u00fcrttemberg",
    "wof:name":"Kiefer Schriftreklame Gmbh",
    "wof:placetype":"venue"
},
  "geometry": {"coordinates":[9.099398,48.717304],"type":"Point"}
}