{
  "type": "Feature",
  "properties": {
    "iso:country":"DE",
    "sg:address":"Kornwestheimer Str. 228",
    "sg:city":"Korntal-M\u00fcnchingen",
    "sg:phone":"+49 7150/6068",
    "sg:postcode":"70825",
    "sg:province":"Baden-W\u00fcrttemberg",
    "wof:name":"Tr\u00f6lsch Gmbh",
    "wof:placetype":"venue"
},
  "geometry": {"coordinates":[9.121911,48.855183],"type":"Point"}
}