{
  "type": "Feature",
  "properties": {
    "iso:country":"DE",
    "sg:city":"Ottersweier",
    "sg:postcode":"77833",
    "sg:province":"Baden-W\u00fcrttemberg",
    "wof:name":"Gemeindebibliothek Schulhaus",
    "wof:placetype":"venue"
},
  "geometry": {"coordinates":[8.112795,48.669678],"type":"Point"}
}