{
  "type": "Feature",
  "properties": {
    "iso:country":"DE",
    "sg:address":"Hochvogelstr. 7",
    "sg:city":"Mindelheim",
    "sg:phone":"+49 8261/8156",
    "sg:postcode":"87719",
    "sg:province":"Bayern",
    "wof:name":"Kurt Walter",
    "wof:placetype":"venue"
},
  "geometry": {"coordinates":[10.5047044754,48.0375328064],"type":"Point"}
}