{
  "type": "Feature",
  "properties": {
    "iso:country":"DE",
    "sg:address":"Stolzestr. 24",
    "sg:city":"Hannover",
    "sg:phone":"+49 511/851337",
    "sg:postcode":"30171",
    "sg:province":"Niedersachsen",
    "wof:name":"Spd Ortsverein S\u00fcdstadt-bult (hannover)",
    "wof:placetype":"venue"
},
  "geometry": {"coordinates":[9.75885,52.367599],"type":"Point"}
}