{
  "type": "Feature",
  "properties": {
    "iso:country":"DE",
    "sg:address":"Mariendorfer Damm 165-167",
    "sg:city":"Berlin",
    "sg:postcode":"12107",
    "sg:province":"Berlin",
    "wof:name":"Bethke & Fricke",
    "wof:placetype":"venue"
},
  "geometry": {"coordinates":[13.3886919022,52.4370536804],"type":"Point"}
}