{
  "type": "Feature",
  "properties": {
    "iso:country":"DE",
    "sg:address":"Karlstr. 16",
    "sg:city":"Braunschweig",
    "sg:phone":"+49 531/332627",
    "sg:postcode":"38106",
    "sg:province":"Niedersachsen",
    "wof:name":"Hans-georg Schrader",
    "wof:placetype":"venue"
},
  "geometry": {"coordinates":[10.539157,52.273144],"type":"Point"}
}