{
  "type": "Feature",
  "properties": {
    "iso:country":"DE",
    "sg:address":"Gro\u00dfe Str. 38",
    "sg:city":"Emden",
    "sg:phone":"+49 4921/93070",
    "sg:postcode":"26721",
    "sg:province":"Niedersachsen",
    "wof:name":"G. Freymuth Und A. B\u00fcschler Notar Und Rechtsanw\u00e4lte",
    "wof:placetype":"venue"
},
  "geometry": {"coordinates":[7.2021818161,53.3668174744],"type":"Point"}
}