{
  "type": "Feature",
  "properties": {
    "iso:country":"DE",
    "sg:address":"Bahnhofstr. 9",
    "sg:city":"Nordhausen",
    "sg:phone":"+49 3631/984123",
    "sg:postcode":"99734",
    "sg:province":"Th\u00fcringen",
    "wof:name":"Eiscafe Brehm",
    "wof:placetype":"venue"
},
  "geometry": {"coordinates":[10.789856,51.494545],"type":"Point"}
}