{
  "type": "Feature",
  "properties": {
    "iso:country":"DE",
    "sg:address":"Beethovenstr. 12",
    "sg:city":"Straubenhardt",
    "sg:phone":"+49 7082/3363",
    "sg:postcode":"75334",
    "sg:province":"Baden-W\u00fcrttemberg",
    "wof:name":"Willi Bauer Gmbh",
    "wof:placetype":"venue"
},
  "geometry": {"coordinates":[8.536375,48.873882],"type":"Point"}
}