{
  "type": "Feature",
  "properties": {
    "iso:country":"DE",
    "sg:address":"Frundsbergstr. 62",
    "sg:city":"M\u00fcnchen",
    "sg:phone":"+49 89/13039049",
    "sg:postcode":"80637",
    "sg:province":"Bayern",
    "wof:name":"Infoscent - Ihre Informationssp\u00fcrnasen",
    "wof:placetype":"venue"
},
  "geometry": {"coordinates":[11.533826,48.159519],"type":"Point"}
}