{
  "type": "Feature",
  "properties": {
    "iso:country":"DE",
    "sg:address":"Schwalbacher Str. 58",
    "sg:city":"Mannheim",
    "sg:phone":"+49 621/755498",
    "sg:postcode":"68305",
    "sg:province":"Baden-W\u00fcrttemberg",
    "wof:name":"E. Stolz",
    "wof:placetype":"venue"
},
  "geometry": {"coordinates":[8.497829,49.522583],"type":"Point"}
}