{
  "type": "Feature",
  "properties": {
    "iso:country":"DE",
    "sg:address":"Orchideenstieg 12",
    "sg:city":"Hamburg",
    "sg:phone":"+49 40/5116041",
    "sg:postcode":"22297",
    "sg:province":"Hamburg",
    "wof:name":"Werner Jaerisch Immobilienmakler",
    "wof:placetype":"venue"
},
  "geometry": {"coordinates":[9.9908094406,53.6050872803],"type":"Point"}
}