{
  "type": "Feature",
  "properties": {
    "iso:country":"DE",
    "sg:address":"Weinbergstr. 9",
    "sg:city":"Mundelsheim",
    "sg:phone":"+49 4971/435771",
    "sg:postcode":"74395",
    "sg:province":"Baden-W\u00fcrttemberg",
    "wof:name":"Karl Sch\u00dctz Gmbh",
    "wof:placetype":"venue"
},
  "geometry": {"coordinates":[9.2061080933,49.002822876],"type":"Point"}
}