{
  "type": "Feature",
  "properties": {
    "iso:country":"DE",
    "sg:address":"Rinklinger Str. 7",
    "sg:city":"Bretten",
    "sg:postcode":"75015",
    "sg:province":"Baden-W\u00fcrttemberg",
    "wof:name":"Ikfs Schadstoff- Beseitigung Gmbh",
    "wof:placetype":"venue"
},
  "geometry": {"coordinates":[8.694102,49.03611],"type":"Point"}
}