{
  "type": "Feature",
  "properties": {
    "iso:country":"DE",
    "sg:address":"Hauptstr. 9",
    "sg:city":"Zeil",
    "sg:phone":"+49 9524/820800",
    "sg:postcode":"97475",
    "sg:province":"Bayern",
    "wof:name":"M\u00fcllers Reiseshop",
    "wof:placetype":"venue"
},
  "geometry": {"coordinates":[10.594909668,50.00938797],"type":"Point"}
}