{
  "type": "Feature",
  "properties": {
    "iso:country":"DE",
    "sg:address":"Chemnitzer Str. 105",
    "sg:city":"Berlin",
    "sg:phone":"+49 30/56596740",
    "sg:postcode":"12621",
    "sg:province":"Berlin",
    "wof:name":"B\u00e4renhaus Gmbh",
    "wof:placetype":"venue"
},
  "geometry": {"coordinates":[13.577557,52.496464],"type":"Point"}
}