{
  "type": "Feature",
  "properties": {
    "iso:country":"DE",
    "sg:address":"Thomas-Mann-Str. 35",
    "sg:city":"Berlin",
    "sg:phone":"+49 30",
    "sg:postcode":"10409",
    "sg:province":"Berlin",
    "wof:name":"Intercon Handels-agentur",
    "wof:placetype":"venue"
},
  "geometry": {"coordinates":[13.4464817047,52.5424919128],"type":"Point"}
}