{
  "type": "Feature",
  "properties": {
    "iso:country":"DE",
    "sg:address":"Sulminger Str.",
    "sg:city":"Maselheim",
    "sg:phone":"+49 7356/3801",
    "sg:postcode":"88437",
    "sg:province":"Baden-W\u00fcrttemberg",
    "wof:name":"J\u00e4gerhaus",
    "wof:placetype":"venue"
},
  "geometry": {"coordinates":[9.8646917343,48.1653289795],"type":"Point"}
}