{
  "type": "Feature",
  "properties": {
    "iso:country":"DE",
    "sg:address":"Colonnaden 19",
    "sg:city":"Hamburg",
    "sg:postcode":"20354",
    "sg:province":"Hamburg",
    "wof:name":"Sportkaap W.-l. Kaap Gmbh & Co. Kg",
    "wof:placetype":"venue"
},
  "geometry": {"coordinates":[9.9902744293,53.5559768677],"type":"Point"}
}