{
  "type": "Feature",
  "properties": {
    "iso:country":"DE",
    "sg:address":"Kaiserstr. 18",
    "sg:city":"Langenfeld",
    "sg:phone":"+49 2173/84019",
    "sg:postcode":"40764",
    "sg:province":"Nordrhein-Westfalen",
    "wof:name":"Roswitha Dudda Rechtsanw\u00e4ltin",
    "wof:placetype":"venue"
},
  "geometry": {"coordinates":[6.945374012,51.1291847229],"type":"Point"}
}