{
  "type": "Feature",
  "properties": {
    "iso:country":"DE",
    "sg:address":"Fehrsweg 1 A",
    "sg:city":"Hamburg",
    "sg:phone":"+49 40/504171",
    "sg:postcode":"22335",
    "sg:province":"Hamburg",
    "wof:name":"Verband F\u00fcr Haus- Und Wohneigentum Hamburg E. V.",
    "wof:placetype":"venue"
},
  "geometry": {"coordinates":[10.0174598694,53.6307182312],"type":"Point"}
}