{
  "type": "Feature",
  "properties": {
    "iso:country":"DE",
    "sg:address":"Ottendorfer Weg 47",
    "sg:city":"Sebnitz",
    "sg:phone":"+49 35971/52246",
    "sg:postcode":"01855",
    "sg:province":"Sachsen",
    "wof:name":"Dr. Med. Wolfgang K\u00f6nig",
    "wof:placetype":"venue"
},
  "geometry": {"coordinates":[14.27789,50.959888],"type":"Point"}
}