{
  "type": "Feature",
  "properties": {
    "iso:country":"DE",
    "sg:address":"Reihdamm 13",
    "sg:city":"Bad Zwischenahn",
    "sg:postcode":"26160",
    "sg:province":"Niedersachsen",
    "wof:name":"Rainer Schmidt E. K.",
    "wof:placetype":"venue"
},
  "geometry": {"coordinates":[7.9966869354,53.180721283],"type":"Point"}
}