{
  "type": "Feature",
  "properties": {
    "iso:country":"DE",
    "sg:address":"Kransberger Str. 44",
    "sg:city":"Wehrheim",
    "sg:phone":"+49 6081/916560",
    "sg:postcode":"61273",
    "sg:province":"Hessen",
    "wof:name":"Sander Massivhaus Gmbh",
    "wof:placetype":"venue"
},
  "geometry": {"coordinates":[8.604475975,50.3330383301],"type":"Point"}
}