{
  "type": "Feature",
  "properties": {
    "iso:country":"DE",
    "sg:address":"Vor dem Tore 11",
    "sg:city":"Hardegsen",
    "sg:phone":"+49 5505/2033",
    "sg:postcode":"37181",
    "sg:province":"Niedersachsen",
    "wof:name":"W. Busse",
    "wof:placetype":"venue"
},
  "geometry": {"coordinates":[9.8310680389,51.6514625549],"type":"Point"}
}