{
  "type": "Feature",
  "properties": {
    "iso:country":"DE",
    "sg:address":"Dr.-Luschberger-Str. 17",
    "sg:city":"Wirges",
    "sg:phone":"+49 2602/60137",
    "sg:postcode":"56422",
    "sg:province":"Rheinland-Pfalz",
    "wof:name":"Kleibusch Bau Gmbh",
    "wof:placetype":"venue"
},
  "geometry": {"coordinates":[7.802297,50.472454],"type":"Point"}
}