{
  "type": "Feature",
  "properties": {
    "iso:country":"DE",
    "sg:address":"Kirchstr. 3",
    "sg:city":"Bad Bellingen",
    "sg:phone":"+49 7635/527",
    "sg:postcode":"79415",
    "sg:province":"Baden-W\u00fcrttemberg",
    "wof:name":"Kath. Pfarramt St. Peter Und Paul",
    "wof:placetype":"venue"
},
  "geometry": {"coordinates":[7.5503997803,47.7163581848],"type":"Point"}
}