{
  "type": "Feature",
  "properties": {
    "iso:country":"DE",
    "sg:address":"Buxtehuder Str. 7",
    "sg:city":"Harsefeld",
    "sg:phone":"+49 4164/4520",
    "sg:postcode":"21698",
    "sg:province":"Niedersachsen",
    "wof:name":"Kurt Brunkhorst",
    "wof:placetype":"venue"
},
  "geometry": {"coordinates":[9.507565,53.454792],"type":"Point"}
}