{
  "type": "Feature",
  "properties": {
    "iso:country":"DE",
    "sg:address":"Waldweg 44",
    "sg:city":"Achim",
    "sg:phone":"+49 4202/979244",
    "sg:postcode":"28832",
    "sg:province":"Niedersachsen",
    "wof:name":"Kraft Gmbh",
    "wof:placetype":"venue"
},
  "geometry": {"coordinates":[9.0991868973,53.0225067139],"type":"Point"}
}