{
  "type": "Feature",
  "properties": {
    "iso:country":"DE",
    "sg:address":"Kerbfelder Str. 1",
    "sg:city":"Aidhausen",
    "sg:phone":"+49 9523/95250",
    "sg:postcode":"97491",
    "sg:province":"Bayern",
    "wof:name":"Gr\u00fcnewald Treppenfertigung Gmbh",
    "wof:placetype":"venue"
},
  "geometry": {"coordinates":[10.466254,50.15984],"type":"Point"}
}