{
  "type": "Feature",
  "properties": {
    "iso:country":"DE",
    "sg:address":"Weidemannweg 3",
    "sg:city":"Sylt-Ost",
    "sg:phone":"+49 4651/32150",
    "sg:postcode":"25980",
    "sg:province":"Schleswig-Holstein",
    "wof:name":"Fisch-fiete",
    "wof:placetype":"venue"
},
  "geometry": {"coordinates":[8.3728666306,54.8940734863],"type":"Point"}
}