{
  "type": "Feature",
  "properties": {
    "iso:country":"DE",
    "sg:address":"Riedwasen 3",
    "sg:city":"Frankenhardt",
    "sg:phone":"+49 7959/2618",
    "sg:postcode":"74586",
    "sg:province":"Baden-W\u00fcrttemberg",
    "wof:name":"Karl-heinz R\u00f6mmich",
    "wof:placetype":"venue"
},
  "geometry": {"coordinates":[10.0322551727,49.0730285645],"type":"Point"}
}