{
  "type": "Feature",
  "properties": {
    "iso:country":"DE",
    "sg:address":"Frankfurter Str 111b",
    "sg:city":"Offenbach",
    "sg:phone":"+49 4403/1592",
    "sg:postcode":"63067",
    "sg:province":"Hessen",
    "wof:name":"Zeit.gewinn",
    "wof:placetype":"venue"
},
  "geometry": {"coordinates":[7.9363889694,53.1597442627],"type":"Point"}
}