{
  "type": "Feature",
  "properties": {
    "iso:country":"DE",
    "sg:address":"Waldstr. 10",
    "sg:city":"Rodgau",
    "sg:phone":"+49 6106/16161",
    "sg:postcode":"63110",
    "sg:province":"Hessen",
    "wof:name":"A. Debus-weber",
    "wof:placetype":"venue"
},
  "geometry": {"coordinates":[8.8862819672,50.0533180237],"type":"Point"}
}