{
  "type": "Feature",
  "properties": {
    "iso:country":"DE",
    "sg:address":"Mittelstr. 38",
    "sg:city":"Bad Nauheim",
    "sg:phone":"+49 6032/4055",
    "sg:postcode":"61231",
    "sg:province":"Hessen",
    "wof:name":"Ts Sicherheitstechnik Gmbh",
    "wof:placetype":"venue"
},
  "geometry": {"coordinates":[8.737444,50.360497],"type":"Point"}
}