{
  "type": "Feature",
  "properties": {
    "iso:country":"DE",
    "sg:address":"Eschersheimer Landstr. 526",
    "sg:city":"Frankfurt",
    "sg:phone":"+49 69/529076",
    "sg:postcode":"60433",
    "sg:province":"Hessen",
    "wof:name":"Wolfgang Gunkel Detektei",
    "wof:placetype":"venue"
},
  "geometry": {"coordinates":[8.658666,50.155476],"type":"Point"}
}