{
  "type": "Feature",
  "properties": {
    "iso:country":"DE",
    "sg:address":"Heinrich-Seidel-Str. 3",
    "sg:city":"Berlin",
    "sg:postcode":"12167",
    "sg:province":"Berlin",
    "wof:name":"Harald Loch Programmb\u00fcro Gmbh",
    "wof:placetype":"venue"
},
  "geometry": {"coordinates":[13.3432569504,52.4486885071],"type":"Point"}
}