{
  "type": "Feature",
  "properties": {
    "iso:country":"DE",
    "sg:address":"Gartenstr. 24",
    "sg:city":"Die\u00dfen",
    "sg:phone":"+49 8807/1258",
    "sg:postcode":"86911",
    "sg:province":"Bayern",
    "wof:name":"Mathilde Dippold",
    "wof:placetype":"venue"
},
  "geometry": {"coordinates":[11.095592,47.986294],"type":"Point"}
}