{
  "type": "Feature",
  "properties": {
    "iso:country":"DE",
    "sg:address":"Chausseestra\u00dfe 6",
    "sg:city":"Berlin",
    "sg:phone":"+49 30/80682222",
    "sg:postcode":"14109",
    "sg:province":"Berlin",
    "wof:name":"Cephir Gmbh & Co. Kg",
    "wof:placetype":"venue"
},
  "geometry": {"coordinates":[13.144317,52.414497],"type":"Point"}
}