{
  "type": "Feature",
  "properties": {
    "iso:country":"DE",
    "sg:address":"Am Horseney 11",
    "sg:city":"Hagen",
    "sg:phone":"+49 2337/8181",
    "sg:postcode":"58091",
    "sg:province":"Nordrhein-Westfalen",
    "wof:name":"Nolte Gmbh & Co. Kg",
    "wof:placetype":"venue"
},
  "geometry": {"coordinates":[7.52622,51.305428],"type":"Point"}
}