{
  "type": "Feature",
  "properties": {
    "iso:country":"DE",
    "sg:address":"Wagnergasse 5-15",
    "sg:city":"Arnstadt",
    "sg:phone":"+49 3628/75317",
    "sg:postcode":"99310",
    "sg:province":"Th\u00fcringen",
    "wof:name":"Matec Material Und Technologie Gmbh",
    "wof:placetype":"venue"
},
  "geometry": {"coordinates":[10.948438,50.831715],"type":"Point"}
}