{
  "type": "Feature",
  "properties": {
    "iso:country":"DE",
    "sg:address":"Moosweiher 4",
    "sg:city":"Schwarzenbach",
    "sg:phone":"+49 9644/6912",
    "sg:postcode":"92720",
    "sg:province":"Bayern",
    "wof:name":"E. Heppner",
    "wof:placetype":"venue"
},
  "geometry": {"coordinates":[11.9995088577,49.723236084],"type":"Point"}
}