{
  "type": "Feature",
  "properties": {
    "iso:country":"DE",
    "sg:address":"Fichtenstr. 68",
    "sg:city":"M\u00f6nchweiler",
    "sg:phone":"+49 7721/7878",
    "sg:postcode":"78087",
    "sg:province":"Baden-W\u00fcrttemberg",
    "wof:name":"Gunter E. Steidinger Unternehmensberatung",
    "wof:placetype":"venue"
},
  "geometry": {"coordinates":[8.4284858704,48.0932579041],"type":"Point"}
}