{
  "type": "Feature",
  "properties": {
    "iso:country":"DE",
    "sg:address":"Wegnerstr. 1",
    "sg:city":"Wuppertal",
    "sg:phone":"+49 202/550770",
    "sg:postcode":"42275",
    "sg:province":"Nordrhein-Westfalen",
    "wof:name":"Otto Auerbach E. K.",
    "wof:placetype":"venue"
},
  "geometry": {"coordinates":[7.200126,51.272003],"type":"Point"}
}