{
  "type": "Feature",
  "properties": {
    "iso:country":"DE",
    "sg:address":"Leonrodstr. 21",
    "sg:city":"M\u00fcnchen",
    "sg:postcode":"80634",
    "sg:province":"Bayern",
    "wof:name":"Xilux Medien Manufaktur Ohg",
    "wof:placetype":"venue"
},
  "geometry": {"coordinates":[11.5356941223,48.1536521912],"type":"Point"}
}