{
  "type": "Feature",
  "properties": {
    "iso:country":"DE",
    "sg:address":"Nadlerstr. 5",
    "sg:city":"Leutkirch",
    "sg:phone":"+49 4975/612408",
    "sg:postcode":"88299",
    "sg:province":"Baden-W\u00fcrttemberg",
    "wof:name":"Andreas Waizenegger",
    "wof:placetype":"venue"
},
  "geometry": {"coordinates":[10.0153017044,47.8270454407],"type":"Point"}
}