{
  "type": "Feature",
  "properties": {
    "iso:country":"DE",
    "sg:address":"Rheingaustr. 25",
    "sg:city":"Oestrich-Winkel",
    "sg:phone":"+49 6723/2864",
    "sg:postcode":"65375",
    "sg:province":"Hessen",
    "wof:name":"Kaspar Steinmetz",
    "wof:placetype":"venue"
},
  "geometry": {"coordinates":[8.0378904343,50.009021759],"type":"Point"}
}