{
  "type": "Feature",
  "properties": {
    "iso:country":"DE",
    "sg:address":"G\u00f6nninger Str. 8",
    "sg:city":"Pfullingen",
    "sg:phone":"+49 7121/799120",
    "sg:postcode":"72793",
    "sg:province":"Baden-W\u00fcrttemberg",
    "wof:name":"Hans Abele",
    "wof:placetype":"venue"
},
  "geometry": {"coordinates":[9.224905014,48.4631156921],"type":"Point"}
}