{
  "type": "Feature",
  "properties": {
    "iso:country":"DE",
    "sg:address":"Carmerstr. 14",
    "sg:city":"Bad Kreuznach",
    "sg:phone":"+49 671/64683",
    "sg:postcode":"55543",
    "sg:province":"Rheinland-Pfalz",
    "wof:name":"J. Mann Steuerbevollm\u00e4chtigter",
    "wof:placetype":"venue"
},
  "geometry": {"coordinates":[7.8704299927,49.8392829895],"type":"Point"}
}