{
  "type": "Feature",
  "properties": {
    "iso:country":"DE",
    "sg:address":"\u00dcber der Aue 7",
    "sg:city":"B\u00f6sel",
    "sg:postcode":"26219",
    "sg:province":"Niedersachsen",
    "wof:name":"Hans Preuth",
    "wof:placetype":"venue"
},
  "geometry": {"coordinates":[7.996462,53.009933],"type":"Point"}
}