{
  "type": "Feature",
  "properties": {
    "iso:country":"DE",
    "sg:address":"Karlsbach",
    "sg:city":"Waldkirchen",
    "sg:phone":"+49 8581/8521",
    "sg:postcode":"94065",
    "sg:province":"Bayern",
    "wof:name":"Gasthaus Luise Lindlbauer",
    "wof:placetype":"venue"
},
  "geometry": {"coordinates":[13.5761299133,48.7691116333],"type":"Point"}
}