{
  "type": "Feature",
  "properties": {
    "iso:country":"DE",
    "sg:address":"Sellostr. 46",
    "sg:city":"Schortens",
    "sg:postcode":"26419",
    "sg:province":"Niedersachsen",
    "wof:name":"Musikverein \u00b4die Original Friesl\u00e4nder\u00b4 Schortens E.v.",
    "wof:placetype":"venue"
},
  "geometry": {"coordinates":[7.9460921288,53.5281143188],"type":"Point"}
}