{
  "type": "Feature",
  "properties": {
    "iso:country":"DE",
    "sg:address":"Kantstr. 4",
    "sg:city":"M\u00fcllheim",
    "sg:phone":"+49 7631/3485",
    "sg:postcode":"79379",
    "sg:province":"Baden-W\u00fcrttemberg",
    "wof:name":"Sg-bau Schildge & Gritzner Gmbh",
    "wof:placetype":"venue"
},
  "geometry": {"coordinates":[7.623508,47.811489],"type":"Point"}
}