{
  "type": "Feature",
  "properties": {
    "iso:country":"DE",
    "sg:address":"Mattenburger Str. 17",
    "sg:city":"Bad Bederkesa",
    "sg:phone":"+49 4745/1800",
    "sg:postcode":"27624",
    "sg:province":"Niedersachsen",
    "wof:name":"Sport Arena Passage",
    "wof:placetype":"venue"
},
  "geometry": {"coordinates":[8.839802,53.625675],"type":"Point"}
}