{
  "type": "Feature",
  "properties": {
    "iso:country":"DE",
    "sg:address":"Stielerstr. 19",
    "sg:city":"N\u00fcrnberg",
    "sg:phone":"+49 911/595100",
    "sg:postcode":"90491",
    "sg:province":"Bayern",
    "wof:name":"Werner Huth Ingenieur",
    "wof:placetype":"venue"
},
  "geometry": {"coordinates":[11.1316280365,49.4707756042],"type":"Point"}
}