{
  "type": "Feature",
  "properties": {
    "iso:country":"DE",
    "sg:address":"Dauelser Dorfstr. 2",
    "sg:city":"Verden",
    "sg:phone":"+49 4942/3199000",
    "sg:postcode":"27283",
    "sg:province":"Niedersachsen",
    "wof:name":"Viehverwertung Verden E.g.",
    "wof:placetype":"venue"
},
  "geometry": {"coordinates":[9.2317399979,52.954410553],"type":"Point"}
}