{
  "type": "Feature",
  "properties": {
    "iso:country":"DE",
    "sg:address":"B\u00e4ckerkamp 14",
    "sg:city":"G\u00fctersloh",
    "sg:phone":"+49 5241/37780",
    "sg:postcode":"33330",
    "sg:province":"Nordrhein-Westfalen",
    "wof:name":"Gernot Messarius",
    "wof:placetype":"venue"
},
  "geometry": {"coordinates":[8.392972,51.91811],"type":"Point"}
}