{
  "type": "Feature",
  "properties": {
    "iso:country":"DE",
    "sg:address":"Hermann-L\u00f6ns-Str. 39b",
    "sg:city":"Warendorf",
    "sg:postcode":"48231",
    "sg:province":"Nordrhein-Westfalen",
    "wof:name":"R & V Bedachungs Gmbh",
    "wof:placetype":"venue"
},
  "geometry": {"coordinates":[7.900731,51.966393],"type":"Point"}
}