{
  "type": "Feature",
  "properties": {
    "iso:country":"DE",
    "sg:address":"Efeustr. 21",
    "sg:city":"St. Johann",
    "sg:phone":"+49 7122/82400",
    "sg:postcode":"72813",
    "sg:province":"Baden-W\u00fcrttemberg",
    "wof:name":"Gebr. Berger",
    "wof:placetype":"venue"
},
  "geometry": {"coordinates":[9.382725,48.455559],"type":"Point"}
}