{
  "type": "Feature",
  "properties": {
    "iso:country":"DE",
    "sg:address":"Am Waldrand 9a",
    "sg:city":"Rastede",
    "sg:phone":"+49 4402/989920",
    "sg:postcode":"26180",
    "sg:province":"Niedersachsen",
    "wof:name":"Manfred Brunken",
    "wof:placetype":"venue"
},
  "geometry": {"coordinates":[8.1597,53.281712],"type":"Point"}
}