{
  "type": "Feature",
  "properties": {
    "iso:country":"DE",
    "sg:address":"Dorfstr. 22",
    "sg:city":"Bornholt",
    "sg:phone":"+49 4872/583",
    "sg:postcode":"25557",
    "sg:province":"Schleswig-Holstein",
    "wof:name":"Volker Timm",
    "wof:placetype":"venue"
},
  "geometry": {"coordinates":[9.327963,54.091633],"type":"Point"}
}