{
  "type": "Feature",
  "properties": {
    "iso:country":"DE",
    "sg:address":"Hauptstr. 5",
    "sg:city":"Echzell",
    "sg:postcode":"61209",
    "sg:province":"Hessen",
    "wof:name":"Demis Gmbh",
    "wof:placetype":"venue"
},
  "geometry": {"coordinates":[8.88412,50.38686],"type":"Point"}
}