{
  "type": "Feature",
  "properties": {
    "iso:country":"DE",
    "sg:address":"Kunibertistr. 35",
    "sg:city":"Recklinghausen",
    "sg:phone":"+49 2361/22501",
    "sg:postcode":"45657",
    "sg:province":"Nordrhein-Westfalen",
    "wof:name":"Sanit\u00e4tshaus Pollen Gmbh",
    "wof:placetype":"venue"
},
  "geometry": {"coordinates":[7.2014069557,51.6148834229],"type":"Point"}
}