{
  "type": "Feature",
  "properties": {
    "iso:country":"DE",
    "sg:address":"Hainer Weg 20",
    "sg:city":"Hofheim",
    "sg:phone":"+49 6192/6323",
    "sg:postcode":"65719",
    "sg:province":"Hessen",
    "wof:name":"Dr. Gustav G\u00f6ttelmann Steuerberater Und",
    "wof:placetype":"venue"
},
  "geometry": {"coordinates":[8.4137048721,50.114566803],"type":"Point"}
}