{
  "type": "Feature",
  "properties": {
    "iso:country":"DE",
    "sg:address":"Wilhelm-Pitz-Str. 1",
    "sg:city":"Stolberg",
    "sg:phone":"+49 2402/3582",
    "sg:postcode":"52223",
    "sg:province":"Nordrhein-Westfalen",
    "wof:name":"Jaka-k\u00fcchenzentrum E. K. Inh. Bernd Kather",
    "wof:placetype":"venue"
},
  "geometry": {"coordinates":[6.218123,50.731339],"type":"Point"}
}