{
  "type": "Feature",
  "properties": {
    "iso:country":"DE",
    "sg:address":"Lotzfeldchen 20a",
    "sg:city":"Eschweiler",
    "sg:phone":"+49 2403/22013",
    "sg:postcode":"52249",
    "sg:province":"Nordrhein-Westfalen",
    "wof:name":"Walter M\u00fcller Architekt",
    "wof:placetype":"venue"
},
  "geometry": {"coordinates":[6.26024,50.823376],"type":"Point"}
}