{
  "type": "Feature",
  "properties": {
    "iso:country":"DE",
    "sg:address":"Samhofer Weg 40",
    "sg:city":"Ingolstadt",
    "sg:phone":"+49 841/83086",
    "sg:postcode":"85049",
    "sg:province":"Bayern",
    "wof:name":"Andreas Brigl",
    "wof:placetype":"venue"
},
  "geometry": {"coordinates":[11.39688,48.766613],"type":"Point"}
}