{
  "type": "Feature",
  "properties": {
    "iso:country":"DE",
    "sg:address":"Hovener Str. 114",
    "sg:city":"M\u00f6nchengladbach",
    "sg:phone":"+49 2161/631891",
    "sg:postcode":"41066",
    "sg:province":"Nordrhein-Westfalen",
    "wof:name":"Robert Schmitz",
    "wof:placetype":"venue"
},
  "geometry": {"coordinates":[6.453427,51.219238],"type":"Point"}
}