{
  "type": "Feature",
  "properties": {
    "iso:country":"DE",
    "sg:address":"Spantekower Landstr. 33",
    "sg:city":"Anklam",
    "sg:phone":"+49 3971/211400",
    "sg:postcode":"17389",
    "sg:province":"Mecklenburg-Vorpommern",
    "wof:name":"Diakonie-pflegedienst Gmbh",
    "wof:placetype":"venue"
},
  "geometry": {"coordinates":[13.6683225632,53.848815918],"type":"Point"}
}