{
  "type": "Feature",
  "properties": {
    "iso:country":"DE",
    "sg:address":"M\u00fcnchner Str. 40",
    "sg:city":"Garmisch-Partenkirchen",
    "sg:phone":"+49 8821/3447",
    "sg:postcode":"82467",
    "sg:province":"Bayern",
    "wof:name":"Peter Pixis Innenarchitekt",
    "wof:placetype":"venue"
},
  "geometry": {"coordinates":[11.106466,47.498299],"type":"Point"}
}