{
  "type": "Feature",
  "properties": {
    "iso:country":"DE",
    "sg:address":"Elbstr. 77",
    "sg:city":"Wedel",
    "sg:postcode":"22880",
    "sg:province":"Schleswig-Holstein",
    "wof:name":"Galerie Nr. 77",
    "wof:placetype":"venue"
},
  "geometry": {"coordinates":[9.71384,53.570591],"type":"Point"}
}