{
  "type": "Feature",
  "properties": {
    "iso:country":"DE",
    "sg:address":"Schlo\u00dfstr. 36",
    "sg:city":"M\u00f6nchengladbach",
    "sg:postcode":"41238",
    "sg:province":"Nordrhein-Westfalen",
    "wof:name":"Aldi Gmbh & Co. Kg",
    "wof:placetype":"venue"
},
  "geometry": {"coordinates":[6.4782409668,51.1807670593],"type":"Point"}
}