{
  "type": "Feature",
  "properties": {
    "iso:country":"DE",
    "sg:address":"Thalenhorststr. 15",
    "sg:city":"Bremen",
    "sg:phone":"+49 421/482157",
    "sg:postcode":"28307",
    "sg:province":"Bremen",
    "wof:name":"Brumley Logistik Und Speditions- Gmbh",
    "wof:placetype":"venue"
},
  "geometry": {"coordinates":[8.9593868256,53.0395278931],"type":"Point"}
}