{
  "type": "Feature",
  "properties": {
    "iso:country":"DE",
    "sg:address":"Zollstr. 52-58",
    "sg:city":"Essen",
    "sg:phone":"+49 201/619021",
    "sg:postcode":"45356",
    "sg:province":"Nordrhein-Westfalen",
    "wof:name":"Mobile R\u00e4ume - Lehmann Gmbh",
    "wof:placetype":"venue"
},
  "geometry": {"coordinates":[6.9831252098,51.4695053101],"type":"Point"}
}