{
  "type": "Feature",
  "properties": {
    "iso:country":"DE",
    "sg:address":"Gebr\u00fcder-Schnack-Str. 29",
    "sg:city":"Hammelburg",
    "sg:phone":"+49 9732/4546",
    "sg:postcode":"97762",
    "sg:province":"Bayern",
    "wof:name":"Roswitha Vogler Masseurin",
    "wof:placetype":"venue"
},
  "geometry": {"coordinates":[9.889384,50.126373],"type":"Point"}
}