{
  "type": "Feature",
  "properties": {
    "iso:country":"DE",
    "sg:address":"An der Hauptwache 15",
    "sg:city":"Frankfurt",
    "sg:phone":"+49 69/283353",
    "sg:postcode":"60313",
    "sg:province":"Hessen",
    "wof:name":"Juchheims-rimbach Gmbh",
    "wof:placetype":"venue"
},
  "geometry": {"coordinates":[8.679023,50.113674],"type":"Point"}
}