{
  "type": "Feature",
  "properties": {
    "iso:country":"DE",
    "sg:address":"Obermarkt 3",
    "sg:city":"Freiberg",
    "sg:phone":"+49 3731/212345",
    "sg:postcode":"09599",
    "sg:province":"Sachsen",
    "wof:name":"Ddd Immobilien Gmbh",
    "wof:placetype":"venue"
},
  "geometry": {"coordinates":[13.343438,50.916634],"type":"Point"}
}