{
  "type": "Feature",
  "properties": {
    "iso:country":"DE",
    "sg:address":"Bussemasstr. 49",
    "sg:city":"Marienfeld",
    "sg:phone":"+49 5247/98030",
    "sg:postcode":"33428",
    "sg:province":"Nordrhein-Westfalen",
    "wof:name":"Bernhard Reiling Glas- Recycling Gmbh & Co. Kg",
    "wof:placetype":"venue"
},
  "geometry": {"coordinates":[8.2871799469,51.9592323303],"type":"Point"}
}