{
  "type": "Feature",
  "properties": {
    "iso:country":"DE",
    "sg:address":"Rheinhausenstr. 32 C",
    "sg:city":"Herbolzheim",
    "sg:phone":"+49 7643/6368",
    "sg:postcode":"79336",
    "sg:province":"Baden-W\u00fcrttemberg",
    "wof:name":"W. Neugart",
    "wof:placetype":"venue"
},
  "geometry": {"coordinates":[7.772883,48.223621],"type":"Point"}
}