{
  "type": "Feature",
  "properties": {
    "iso:country":"DE",
    "sg:address":"Schulstr. 9",
    "sg:city":"Mindelheim",
    "sg:phone":"+49 8261/1732",
    "sg:postcode":"87719",
    "sg:province":"Bayern",
    "wof:name":"Dr. Hermann Hagenmeyer Tierarzt",
    "wof:placetype":"venue"
},
  "geometry": {"coordinates":[10.4928026199,48.0488853455],"type":"Point"}
}