{
  "type": "Feature",
  "properties": {
    "iso:country":"DE",
    "sg:address":"Mittelstr. 22",
    "sg:city":"Extertal",
    "sg:phone":"+49 5262/782",
    "sg:postcode":"32699",
    "sg:province":"Nordrhein-Westfalen",
    "wof:name":"Johannsmeier Gmbh",
    "wof:placetype":"venue"
},
  "geometry": {"coordinates":[9.1258249283,52.0681610107],"type":"Point"}
}