{
  "type": "Feature",
  "properties": {
    "iso:country":"DE",
    "sg:address":"Kirchstr. 22",
    "sg:city":"G\u00fctzkow",
    "sg:phone":"+49 38353/440",
    "sg:postcode":"17506",
    "sg:province":"Mecklenburg-Vorpommern",
    "wof:name":"K. Rohr Und W. Golling",
    "wof:placetype":"venue"
},
  "geometry": {"coordinates":[13.410415,53.938019],"type":"Point"}
}