{
  "type": "Feature",
  "properties": {
    "iso:country":"DE",
    "sg:address":"Am Elbdeich 27 a",
    "sg:city":"Jork",
    "sg:phone":"+49 4162/6393",
    "sg:postcode":"21635",
    "sg:province":"Niedersachsen",
    "wof:name":"Deichgraf",
    "wof:placetype":"venue"
},
  "geometry": {"coordinates":[9.6811256409,53.5426902771],"type":"Point"}
}