{
  "type": "Feature",
  "properties": {
    "iso:country":"DE",
    "sg:address":"Koppel 66",
    "sg:city":"Hamburg",
    "sg:phone":"+49 40/247950",
    "sg:postcode":"20099",
    "sg:province":"Hamburg",
    "wof:name":"Klaus Winterscheidt",
    "wof:placetype":"venue"
},
  "geometry": {"coordinates":[10.011406,53.558578],"type":"Point"}
}