{
  "type": "Feature",
  "properties": {
    "iso:country":"DE",
    "sg:address":"Pferdetr\u00e4nke 25",
    "sg:city":"Borken",
    "sg:phone":"+49 5682/5480",
    "sg:postcode":"34582",
    "sg:province":"Hessen",
    "wof:name":"Klebeasch",
    "wof:placetype":"venue"
},
  "geometry": {"coordinates":[9.2808713913,51.0445175171],"type":"Point"}
}