{
  "type": "Feature",
  "properties": {
    "iso:country":"DE",
    "sg:address":"Kleinerlbacher Ortsstr. 16",
    "sg:city":"Neustadt",
    "sg:phone":"+49 9161/7799",
    "sg:postcode":"91413",
    "sg:province":"Bayern",
    "wof:name":"Distler",
    "wof:placetype":"venue"
},
  "geometry": {"coordinates":[10.6314268112,49.5837860107],"type":"Point"}
}