{
  "type": "Feature",
  "properties": {
    "iso:country":"DE",
    "sg:address":"Hornbergstr. 54",
    "sg:city":"Ditzingen",
    "sg:phone":"+49 7156/6131",
    "sg:postcode":"71254",
    "sg:province":"Baden-W\u00fcrttemberg",
    "wof:name":"Eugen Bauer",
    "wof:placetype":"venue"
},
  "geometry": {"coordinates":[9.078097,48.826321],"type":"Point"}
}