{
  "type": "Feature",
  "properties": {
    "iso:country":"DE",
    "sg:address":"Weidmannspfad 1",
    "sg:city":"Wuppertal",
    "sg:phone":"+49 202/721163",
    "sg:postcode":"42113",
    "sg:province":"Nordrhein-Westfalen",
    "wof:name":"Helmut Zirkenbach",
    "wof:placetype":"venue"
},
  "geometry": {"coordinates":[7.120523,51.279976],"type":"Point"}
}