{
  "type": "Feature",
  "properties": {
    "iso:country":"DE",
    "sg:address":"Schulstr. 8",
    "sg:city":"Grenderich",
    "sg:phone":"+49 2673/98660",
    "sg:postcode":"56858",
    "sg:province":"Rheinland-Pfalz",
    "wof:name":"Graf Uhrarmb\u00e4nder Gmbh",
    "wof:placetype":"venue"
},
  "geometry": {"coordinates":[7.2292199135,50.0645027161],"type":"Point"}
}