{
  "type": "Feature",
  "properties": {
    "iso:country":"DE",
    "sg:address":"Waldhausener Str. 39",
    "sg:city":"M\u00f6nchengladbach",
    "sg:phone":"+49 2161/175074",
    "sg:postcode":"41061",
    "sg:province":"Nordrhein-Westfalen",
    "wof:name":"Josef Terstappen",
    "wof:placetype":"venue"
},
  "geometry": {"coordinates":[6.4287028313,51.1949577332],"type":"Point"}
}