{
  "type": "Feature",
  "properties": {
    "iso:country":"DE",
    "sg:address":"Zur Schwarzen Br\u00fccke 4",
    "sg:city":"Wittlich",
    "sg:phone":"+49 6571/10030",
    "sg:postcode":"54516",
    "sg:province":"Rheinland-Pfalz",
    "wof:name":"Emb Wittlich Gmbh",
    "wof:placetype":"venue"
},
  "geometry": {"coordinates":[6.9504752159,49.9757652283],"type":"Point"}
}