{
  "type": "Feature",
  "properties": {
    "iso:country":"DE",
    "sg:address":"Golbergstr. 25",
    "sg:city":"\u00d6hringen",
    "sg:phone":"+49 7941/65750",
    "sg:postcode":"74613",
    "sg:province":"Baden-W\u00fcrttemberg",
    "wof:name":"R. Graulich",
    "wof:placetype":"venue"
},
  "geometry": {"coordinates":[9.4651908875,49.1866569519],"type":"Point"}
}