{
  "type": "Feature",
  "properties": {
    "iso:country":"DE",
    "sg:address":"Andreestr. 48",
    "sg:city":"Bremen",
    "sg:phone":"+49 421/354258",
    "sg:postcode":"28215",
    "sg:province":"Bremen",
    "wof:name":"Heinrich Grafenhorst Ingenieur",
    "wof:placetype":"venue"
},
  "geometry": {"coordinates":[8.8024120331,53.0913658142],"type":"Point"}
}