{
  "type": "Feature",
  "properties": {
    "iso:country":"DE",
    "sg:address":"Steeler Str. 40",
    "sg:city":"Oberhausen",
    "sg:phone":"+49 208/895738",
    "sg:postcode":"46047",
    "sg:province":"Nordrhein-Westfalen",
    "wof:name":"A. Marx",
    "wof:placetype":"venue"
},
  "geometry": {"coordinates":[6.894258,51.47884],"type":"Point"}
}