{
  "type": "Feature",
  "properties": {
    "iso:country":"DE",
    "sg:address":"Westenhellweg 60-62",
    "sg:city":"Dortmund",
    "sg:phone":"+49 231/1656129",
    "sg:postcode":"44137",
    "sg:province":"Nordrhein-Westfalen",
    "wof:name":"D2 - Shop",
    "wof:placetype":"venue"
},
  "geometry": {"coordinates":[7.4625339508,51.5141296387],"type":"Point"}
}