{
  "type": "Feature",
  "properties": {
    "iso:country":"DE",
    "sg:address":"Kleiner Eiderkamp 1",
    "sg:city":"Molfsee",
    "sg:postcode":"24113",
    "sg:province":"Schleswig-Holstein",
    "wof:name":"Immobilien Company Nord Gmbh",
    "wof:placetype":"venue"
},
  "geometry": {"coordinates":[10.089097,54.289101],"type":"Point"}
}