{
  "type": "Feature",
  "properties": {
    "iso:country":"DE",
    "sg:address":"\u00d6denburger Str. 28",
    "sg:city":"Darmstadt",
    "sg:phone":"+49 6151/61420",
    "sg:postcode":"64295",
    "sg:province":"Hessen",
    "wof:name":"A. Klein Kunstmaler",
    "wof:placetype":"venue"
},
  "geometry": {"coordinates":[8.624508,49.845524],"type":"Point"}
}