{
  "type": "Feature",
  "properties": {
    "iso:country":"DE",
    "sg:address":"An der Stiftsmauer 5",
    "sg:city":"Obernkirchen",
    "sg:phone":"+49 5724/9610",
    "sg:postcode":"31683",
    "sg:province":"Niedersachsen",
    "wof:name":"Seniorenheim Haus Sonnenhof",
    "wof:placetype":"venue"
},
  "geometry": {"coordinates":[9.12929,52.269001],"type":"Point"}
}