{
  "type": "Feature",
  "properties": {
    "iso:country":"DE",
    "sg:address":"Hindenburgstr. 36",
    "sg:city":"Korntal-M\u00fcnchingen",
    "sg:postcode":"70825",
    "sg:province":"Baden-W\u00fcrttemberg",
    "wof:name":"Pro Christ 93 E. V.",
    "wof:placetype":"venue"
},
  "geometry": {"coordinates":[9.1229352951,48.8341026306],"type":"Point"}
}