{
  "type": "Feature",
  "properties": {
    "iso:country":"DE",
    "sg:address":"Lange R\u00f6tterstr. 22",
    "sg:city":"Mannheim",
    "sg:phone":"+49 621/332522",
    "sg:postcode":"68167",
    "sg:province":"Baden-W\u00fcrttemberg",
    "wof:name":"Hans B\u00fchl",
    "wof:placetype":"venue"
},
  "geometry": {"coordinates":[8.4773674011,49.4972648621],"type":"Point"}
}