{
  "type": "Feature",
  "properties": {
    "iso:country":"DE",
    "sg:address":"Marktstr. 22",
    "sg:city":"Neckarsulm",
    "sg:phone":"+49 7132/922847",
    "sg:postcode":"74172",
    "sg:province":"Baden-W\u00fcrttemberg",
    "wof:name":"Eiscafe San Marco Inh. Camillo Colli",
    "wof:placetype":"venue"
},
  "geometry": {"coordinates":[9.224936,49.191944],"type":"Point"}
}