{
  "type": "Feature",
  "properties": {
    "iso:country":"DE",
    "sg:address":"Dellestr. 33",
    "sg:city":"D\u00fcsseldorf",
    "sg:phone":"+49 211/202018",
    "sg:postcode":"40627",
    "sg:province":"Nordrhein-Westfalen",
    "wof:name":"Marisa Manzin Dolmetscherin \u00dcbersetzerin",
    "wof:placetype":"venue"
},
  "geometry": {"coordinates":[6.896666,51.20145],"type":"Point"}
}