{
  "type": "Feature",
  "properties": {
    "iso:country":"DE",
    "sg:address":"Gli\u00dfmannweg 9",
    "sg:city":"Hamburg",
    "sg:phone":"+49 40/5594292",
    "sg:postcode":"22457",
    "sg:province":"Hamburg",
    "wof:name":"Dr. Bublitz Dentaltechnik Ohg",
    "wof:placetype":"venue"
},
  "geometry": {"coordinates":[9.9172105789,53.6351547241],"type":"Point"}
}