{
  "type": "Feature",
  "properties": {
    "iso:country":"DE",
    "sg:address":"Wertherstr. 34",
    "sg:city":"Bad M\u00fcnstereifel",
    "sg:phone":"+49 2253/8420",
    "sg:postcode":"53902",
    "sg:province":"Nordrhein-Westfalen",
    "wof:name":"Leo Forsbeck",
    "wof:placetype":"venue"
},
  "geometry": {"coordinates":[6.7652831078,50.556602478],"type":"Point"}
}