{
  "type": "Feature",
  "properties": {
    "iso:country":"DE",
    "sg:address":"Winzlarer Str. 18",
    "sg:city":"Rehburg-Loccum",
    "sg:phone":"+49 5037/795",
    "sg:postcode":"31547",
    "sg:province":"Niedersachsen",
    "wof:name":"Wilhelm Lempfer",
    "wof:placetype":"venue"
},
  "geometry": {"coordinates":[9.230483,52.461838],"type":"Point"}
}