{
  "type": "Feature",
  "properties": {
    "iso:country":"DE",
    "sg:address":"Falkenstr. 14",
    "sg:city":"Calw",
    "sg:phone":"+49 7051/40203",
    "sg:postcode":"75365",
    "sg:province":"Baden-W\u00fcrttemberg",
    "wof:name":"Josef Engl Krankengymnast",
    "wof:placetype":"venue"
},
  "geometry": {"coordinates":[8.769012,48.698524],"type":"Point"}
}