{
  "type": "Feature",
  "properties": {
    "iso:country":"DE",
    "sg:city":"Jesteburg",
    "sg:phone":"+49 4183/2871",
    "sg:postcode":"21266",
    "sg:province":"Niedersachsen",
    "wof:name":"Altenheim Stubbenhof Gmbh & Co. Betriebs Kg",
    "wof:placetype":"venue"
},
  "geometry": {"coordinates":[9.958085,53.309429],"type":"Point"}
}