{
  "type": "Feature",
  "properties": {
    "iso:country":"DE",
    "sg:address":"Kirchgang 1 a",
    "sg:city":"Gudensberg",
    "sg:phone":"+49 5603/2452",
    "sg:postcode":"34281",
    "sg:province":"Hessen",
    "wof:name":"Karl Martin",
    "wof:placetype":"venue"
},
  "geometry": {"coordinates":[9.353655,51.159611],"type":"Point"}
}