{
  "type": "Feature",
  "properties": {
    "iso:country":"DE",
    "sg:address":"Tagewerbener Str. 35",
    "sg:city":"Wei\u00dfenfels",
    "sg:phone":"+49 3443/202810",
    "sg:postcode":"06667",
    "sg:province":"Sachsen-Anhalt",
    "wof:name":"Kohlmann",
    "wof:placetype":"venue"
},
  "geometry": {"coordinates":[11.965174675,51.2131729126],"type":"Point"}
}