{
  "type": "Feature",
  "properties": {
    "iso:country":"DE",
    "sg:address":"Bertoldstr. 8",
    "sg:city":"Freiburg",
    "sg:phone":"+49 761/32999",
    "sg:postcode":"79098",
    "sg:province":"Baden-W\u00fcrttemberg",
    "wof:name":"Brunnen-apotheke",
    "wof:placetype":"venue"
},
  "geometry": {"coordinates":[7.848986,47.995049],"type":"Point"}
}