{
  "type": "Feature",
  "properties": {
    "iso:country":"DE",
    "sg:address":"Geiselgasteigstr. 55",
    "sg:city":"M\u00fcnchen",
    "sg:phone":"+49 89/644113",
    "sg:postcode":"81545",
    "sg:province":"Bayern",
    "wof:name":"Friedrich Thaler Kunstmaler",
    "wof:placetype":"venue"
},
  "geometry": {"coordinates":[11.557475,48.092106],"type":"Point"}
}