{
  "type": "Feature",
  "properties": {
    "iso:country":"DE",
    "sg:address":"Bopserwaldstr. 26 A",
    "sg:city":"Stuttgart",
    "sg:phone":"+49 711/164180",
    "sg:postcode":"70184",
    "sg:province":"Baden-W\u00fcrttemberg",
    "wof:name":"Mikropharma Pharmazeutischer Grosshandel Gmbh",
    "wof:placetype":"venue"
},
  "geometry": {"coordinates":[9.184589386,48.7662811279],"type":"Point"}
}