{
  "type": "Feature",
  "properties": {
    "iso:country":"DE",
    "sg:address":"Hardtsteige 19",
    "sg:city":"Freudenstadt",
    "sg:phone":"+49 7441/2640",
    "sg:postcode":"72250",
    "sg:province":"Baden-W\u00fcrttemberg",
    "wof:name":"Ernst Klumpp",
    "wof:placetype":"venue"
},
  "geometry": {"coordinates":[8.4325151443,48.4440231323],"type":"Point"}
}