{
  "type": "Feature",
  "properties": {
    "iso:country":"DE",
    "sg:address":"Lichtenmoorer Str. 10",
    "sg:city":"Steimbke",
    "sg:phone":"+49 5165/2011",
    "sg:postcode":"31634",
    "sg:province":"Niedersachsen",
    "wof:name":"Fahr-, Turnier- Und Ausbildungsstall Von Senden",
    "wof:placetype":"venue"
},
  "geometry": {"coordinates":[9.392689,52.717407],"type":"Point"}
}