{
  "type": "Feature",
  "properties": {
    "iso:country":"DE",
    "sg:address":"Uentroper Str. 4",
    "sg:city":"Ahlen",
    "sg:phone":"+49 2388/2157",
    "sg:postcode":"59229",
    "sg:province":"Nordrhein-Westfalen",
    "wof:name":"B. Und H. Schroer Gmbh",
    "wof:placetype":"venue"
},
  "geometry": {"coordinates":[7.9265499115,51.7075195312],"type":"Point"}
}