{
  "type": "Feature",
  "properties": {
    "iso:country":"DE",
    "sg:address":"Jakob-Welder-Weg 1",
    "sg:city":"Mainz",
    "sg:phone":"+49 6131/320888",
    "sg:postcode":"55128",
    "sg:province":"Rheinland-Pfalz",
    "wof:name":"Studentenblitz",
    "wof:placetype":"venue"
},
  "geometry": {"coordinates":[8.2433624268,49.9944152832],"type":"Point"}
}