{
  "type": "Feature",
  "properties": {
    "iso:country":"DE",
    "sg:address":"Obere Trift 20",
    "sg:city":"Barntrup",
    "sg:phone":"+49 5263/1755",
    "sg:postcode":"32683",
    "sg:province":"Nordrhein-Westfalen",
    "wof:name":"Bernhard Rigelsky Immobilienmakler",
    "wof:placetype":"venue"
},
  "geometry": {"coordinates":[9.0826196671,51.9793701172],"type":"Point"}
}