{
  "type": "Feature",
  "properties": {
    "iso:country":"DE",
    "sg:address":"Heideweg 5",
    "sg:city":"Schwarme",
    "sg:phone":"+49 4258/717",
    "sg:postcode":"27327",
    "sg:province":"Niedersachsen",
    "wof:name":"Friedrich Trumpf Grundst\u00fccks- Verwaltungsgesellschaft",
    "wof:placetype":"venue"
},
  "geometry": {"coordinates":[9.041429,52.907467],"type":"Point"}
}