{
  "type": "Feature",
  "properties": {
    "iso:country":"DE",
    "sg:address":"Nettelstr. 17",
    "sg:city":"Bremerhaven",
    "sg:postcode":"27580",
    "sg:province":"Bremen",
    "wof:name":"Hope-music",
    "wof:placetype":"venue"
},
  "geometry": {"coordinates":[8.595870018,53.5686454773],"type":"Point"}
}