{
  "type": "Feature",
  "properties": {
    "iso:country":"DE",
    "sg:address":"Waldstr. 10",
    "sg:city":"Stra\u00dflach-Dingharting",
    "sg:phone":"+49 8170/624",
    "sg:postcode":"82064",
    "sg:province":"Bayern",
    "wof:name":"Rudolf F\u00fchrmann",
    "wof:placetype":"venue"
},
  "geometry": {"coordinates":[11.5105752945,47.992275238],"type":"Point"}
}