{
  "type": "Feature",
  "properties": {
    "iso:country":"DE",
    "sg:address":"K\u00f6lner Str. 17",
    "sg:city":"Erkelenz",
    "sg:phone":"+49 2431/4960",
    "sg:postcode":"41812",
    "sg:province":"Nordrhein-Westfalen",
    "wof:name":"Moden Fr\u00f6hlich Gmbh",
    "wof:placetype":"venue"
},
  "geometry": {"coordinates":[6.317581,51.078758],"type":"Point"}
}