{
  "type": "Feature",
  "properties": {
    "iso:country":"DE",
    "sg:address":"Salinstr. 11",
    "sg:city":"Rosenheim",
    "sg:phone":"+49 8031/18980",
    "sg:postcode":"83022",
    "sg:province":"Bayern",
    "wof:name":"Aesculap-apotheke Andreas Riedrich E. Kfm.",
    "wof:placetype":"venue"
},
  "geometry": {"coordinates":[12.124277,47.85078],"type":"Point"}
}