{
  "type": "Feature",
  "properties": {
    "iso:country":"DE",
    "sg:address":"Maiselsbergerstr. 5",
    "sg:city":"Taufkirchen",
    "sg:phone":"+49 8084/9163",
    "sg:postcode":"84416",
    "sg:province":"Bayern",
    "wof:name":"Eytech Grafik Und Webdesign, Bandmanagement",
    "wof:placetype":"venue"
},
  "geometry": {"coordinates":[12.178524,48.343525],"type":"Point"}
}