{
  "type": "Feature",
  "properties": {
    "iso:country":"DE",
    "sg:address":"Tannenbergstr. 2",
    "sg:city":"Siegen",
    "sg:phone":"+49 271/331838",
    "sg:postcode":"57074",
    "sg:province":"Nordrhein-Westfalen",
    "wof:name":"Berthold Gerhards",
    "wof:placetype":"venue"
},
  "geometry": {"coordinates":[8.015624,50.864632],"type":"Point"}
}