{
  "type": "Feature",
  "properties": {
    "iso:country":"DE",
    "sg:address":"Hinter Sundheim 14",
    "sg:city":"Nierstein",
    "sg:phone":"+49 6133/5468",
    "sg:postcode":"55283",
    "sg:province":"Rheinland-Pfalz",
    "wof:name":"Heinrich D\u00e4mgen",
    "wof:placetype":"venue"
},
  "geometry": {"coordinates":[8.3395996094,49.8722801208],"type":"Point"}
}