{
  "type": "Feature",
  "properties": {
    "iso:country":"DE",
    "sg:address":"Kellerstr. 14",
    "sg:city":"Ellerbek",
    "sg:phone":"+49 4101/31368",
    "sg:postcode":"25474",
    "sg:province":"Schleswig-Holstein",
    "wof:name":"Continental Audio Electronic Gmbh",
    "wof:placetype":"venue"
},
  "geometry": {"coordinates":[9.8694992065,53.6552619934],"type":"Point"}
}