{
  "type": "Feature",
  "properties": {
    "iso:country":"DE",
    "sg:address":"Hauptstr. 73",
    "sg:city":"Deggingen",
    "sg:phone":"+49 7334/922766",
    "sg:postcode":"73326",
    "sg:province":"Baden-W\u00fcrttemberg",
    "wof:name":"Reiseb\u00fcro Alb Donau",
    "wof:placetype":"venue"
},
  "geometry": {"coordinates":[9.717149,48.595467],"type":"Point"}
}