{
  "type": "Feature",
  "properties": {
    "iso:country":"DE",
    "sg:address":"Unter Sachsenhausen 10",
    "sg:city":"K\u00f6ln",
    "sg:phone":"+49 221/1640221",
    "sg:postcode":"50667",
    "sg:province":"Nordrhein-Westfalen",
    "wof:name":"Rheinische Immobilienb\u00f6rse",
    "wof:placetype":"venue"
},
  "geometry": {"coordinates":[6.952091,50.942608],"type":"Point"}
}