{
  "type": "Feature",
  "properties": {
    "iso:country":"DE",
    "sg:address":"Gartenstr. 5",
    "sg:city":"Berlin",
    "sg:phone":"+49 30/2851840",
    "sg:postcode":"10115",
    "sg:province":"Berlin",
    "wof:name":"Zar Zentrum F\u00fcr Ambulante Rehabilitation Berlin",
    "wof:placetype":"venue"
},
  "geometry": {"coordinates":[13.3929424286,52.5294570923],"type":"Point"}
}