{
  "type": "Feature",
  "properties": {
    "iso:country":"DE",
    "sg:address":"Lillweg 44",
    "sg:city":"M\u00fcnchen",
    "sg:postcode":"80939",
    "sg:province":"Bayern",
    "wof:name":"Hasegawa Gmbh",
    "wof:placetype":"venue"
},
  "geometry": {"coordinates":[11.637955,48.21323],"type":"Point"}
}