{
  "type": "Feature",
  "properties": {
    "iso:country":"DE",
    "sg:address":"Haustadter-Tal-Str. 185",
    "sg:city":"Beckingen",
    "sg:phone":"+49 6835/93299",
    "sg:postcode":"66701",
    "sg:province":"Saarland",
    "wof:name":"N. Werhan",
    "wof:placetype":"venue"
},
  "geometry": {"coordinates":[6.723837,49.413353],"type":"Point"}
}