{
  "type": "Feature",
  "properties": {
    "iso:country":"DE",
    "sg:address":"D\u00fcbener Str. 14",
    "sg:city":"Delitzsch",
    "sg:phone":"+49 34202/61874",
    "sg:postcode":"04509",
    "sg:province":"Sachsen",
    "wof:name":"Christine Schneider",
    "wof:placetype":"venue"
},
  "geometry": {"coordinates":[12.338446,51.526344],"type":"Point"}
}