{
  "type": "Feature",
  "properties": {
    "iso:country":"DE",
    "sg:address":"Memlingstr. 5",
    "sg:city":"Berlin",
    "sg:phone":"+49 30/8343462",
    "sg:postcode":"12203",
    "sg:province":"Berlin",
    "wof:name":"Hubertus Kirner",
    "wof:placetype":"venue"
},
  "geometry": {"coordinates":[13.309373,52.441528],"type":"Point"}
}