{
  "type": "Feature",
  "properties": {
    "iso:country":"DE",
    "sg:address":"Judenhof 1",
    "sg:city":"Ulm",
    "sg:phone":"+49 731/962720",
    "sg:postcode":"89073",
    "sg:province":"Baden-W\u00fcrttemberg",
    "wof:name":"Marketeam Werbeagentur Gmbh Ulm",
    "wof:placetype":"venue"
},
  "geometry": {"coordinates":[9.994895,48.398983],"type":"Point"}
}