{
  "type": "Feature",
  "properties": {
    "iso:country":"DE",
    "sg:address":"Markneukirchner Str. 18",
    "sg:city":"Klingenthal",
    "sg:phone":"+49 37467/23330",
    "sg:postcode":"08248",
    "sg:province":"Sachsen",
    "wof:name":"Georg Tannh\u00e4user",
    "wof:placetype":"venue"
},
  "geometry": {"coordinates":[12.46421,50.355644],"type":"Point"}
}