{
  "type": "Feature",
  "properties": {
    "iso:country":"DE",
    "sg:address":"Kirchplatz 5",
    "sg:city":"Tiefenort",
    "sg:phone":"+49 3695/824011",
    "sg:postcode":"36469",
    "sg:province":"Th\u00fcringen",
    "wof:name":"Kommunale Wohnungsges. Tiefenort Mbh",
    "wof:placetype":"venue"
},
  "geometry": {"coordinates":[10.167742,50.839172],"type":"Point"}
}