{
  "type": "Feature",
  "properties": {
    "iso:country":"DE",
    "sg:address":"Polsumer Stra\u00dfe 194",
    "sg:city":"Gelsenkirchen",
    "sg:phone":"+49 209/638074",
    "sg:postcode":"45896",
    "sg:province":"Nordrhein-Westfalen",
    "wof:name":"Sv Schwarz-wei\u00df B\u00fclse",
    "wof:placetype":"venue"
},
  "geometry": {"coordinates":[7.0500779152,51.6012268066],"type":"Point"}
}