{
  "type": "Feature",
  "properties": {
    "iso:country":"DE",
    "sg:address":"Martin-Behaim-Str. 11",
    "sg:city":"Hilpoltstein",
    "sg:phone":"+49 9174/9139",
    "sg:postcode":"91161",
    "sg:province":"Bayern",
    "wof:name":"Rolf Christ",
    "wof:placetype":"venue"
},
  "geometry": {"coordinates":[11.180475235,49.1903495789],"type":"Point"}
}