{
  "type": "Feature",
  "properties": {
    "iso:country":"DE",
    "sg:address":"Oldenburger Str. 21",
    "sg:city":"Vechta",
    "sg:phone":"+49 4441/92780",
    "sg:postcode":"49377",
    "sg:province":"Niedersachsen",
    "wof:name":"Ludwig S\u00fcdbeck Nutzfahrzeuge Gmbh",
    "wof:placetype":"venue"
},
  "geometry": {"coordinates":[8.287895,52.733231],"type":"Point"}
}