{
  "type": "Feature",
  "properties": {
    "iso:country":"DE",
    "sg:address":"Alte Rothofstr. 2",
    "sg:city":"Frankfurt",
    "sg:phone":"+49 69/91000",
    "sg:postcode":"60313",
    "sg:province":"Hessen",
    "wof:name":"Interessengemeinschaft Frankfurter Kredit-",
    "wof:placetype":"venue"
},
  "geometry": {"coordinates":[8.6753101349,50.1128463745],"type":"Point"}
}