{
  "type": "Feature",
  "properties": {
    "iso:country":"DE",
    "sg:address":"Murrhardter Str. 31",
    "sg:city":"Ludwigsburg",
    "sg:phone":"+49 7141/862728",
    "sg:postcode":"71640",
    "sg:province":"Baden-W\u00fcrttemberg",
    "wof:name":"J\u00fcrgen Crai\u00df Ingenieur",
    "wof:placetype":"venue"
},
  "geometry": {"coordinates":[9.2195177078,48.8954353333],"type":"Point"}
}