{
  "type": "Feature",
  "properties": {
    "iso:country":"DE",
    "sg:address":"Hellerstr. 7",
    "sg:city":"Velbert",
    "sg:phone":"+49 2052/82725",
    "sg:postcode":"42555",
    "sg:province":"Nordrhein-Westfalen",
    "wof:name":"Gro\u00df Primmes",
    "wof:placetype":"venue"
},
  "geometry": {"coordinates":[7.1219210625,51.3523406982],"type":"Point"}
}