{
  "type": "Feature",
  "properties": {
    "iso:country":"DE",
    "sg:address":"Ardeystr. 319",
    "sg:city":"Witten",
    "sg:phone":"+49 2302/65883",
    "sg:postcode":"58453",
    "sg:province":"Nordrhein-Westfalen",
    "wof:name":"Wenig",
    "wof:placetype":"venue"
},
  "geometry": {"coordinates":[7.406009,51.434692],"type":"Point"}
}