{
  "type": "Feature",
  "properties": {
    "iso:country":"DE",
    "sg:address":"Kruppstr. 220",
    "sg:city":"Wuppertal",
    "sg:phone":"+49 214/55105",
    "sg:postcode":"42113",
    "sg:province":"Nordrhein-Westfalen",
    "wof:name":"Claudia Roder",
    "wof:placetype":"venue"
},
  "geometry": {"coordinates":[7.120791,51.276237],"type":"Point"}
}