{
  "type": "Feature",
  "properties": {
    "iso:country":"DE",
    "sg:address":"Schulstr. 7",
    "sg:city":"Hankensb\u00fcttel",
    "sg:phone":"+49 5832/6628",
    "sg:postcode":"29386",
    "sg:province":"Niedersachsen",
    "wof:name":"\u00dcbersetzungen West-ost",
    "wof:placetype":"venue"
},
  "geometry": {"coordinates":[10.606028,52.728554],"type":"Point"}
}