{
  "type": "Feature",
  "properties": {
    "iso:country":"DE",
    "sg:address":"Mittelstr. 21",
    "sg:city":"Bad Laasphe",
    "sg:phone":"+49 2752/9495",
    "sg:postcode":"57334",
    "sg:province":"Nordrhein-Westfalen",
    "wof:name":"Willi Feuring",
    "wof:placetype":"venue"
},
  "geometry": {"coordinates":[8.437997,50.929058],"type":"Point"}
}