{
  "type": "Feature",
  "properties": {
    "iso:country":"DE",
    "sg:address":"Sarresdorfer Str. 27",
    "sg:city":"Gerolstein",
    "sg:phone":"+49 6591/3552",
    "sg:postcode":"54568",
    "sg:province":"Rheinland-Pfalz",
    "wof:name":"Schmitz Immobilienmakler",
    "wof:placetype":"venue"
},
  "geometry": {"coordinates":[6.6537032127,50.2234039307],"type":"Point"}
}