{
  "type": "Feature",
  "properties": {
    "iso:country":"DE",
    "sg:address":"Blaubacher Str. 22",
    "sg:city":"Kusel",
    "sg:phone":"+49 6381/3791",
    "sg:postcode":"66869",
    "sg:province":"Rheinland-Pfalz",
    "wof:name":"Avg Agrarprodukte Vertriebs-gmbh",
    "wof:placetype":"venue"
},
  "geometry": {"coordinates":[7.394939,49.549023],"type":"Point"}
}