{
  "type": "Feature",
  "properties": {
    "iso:country":"DE",
    "sg:address":"Niedernstr. 27",
    "sg:city":"Stadthagen",
    "sg:phone":"+49 5721/2145",
    "sg:postcode":"31655",
    "sg:province":"Niedersachsen",
    "wof:name":"Th. Plawukos",
    "wof:placetype":"venue"
},
  "geometry": {"coordinates":[9.2058038712,52.3261108398],"type":"Point"}
}