{
  "type": "Feature",
  "properties": {
    "iso:country":"DE",
    "sg:address":"Neckarstr. 24",
    "sg:city":"Weinheim",
    "sg:phone":"+49 6201/962565",
    "sg:postcode":"69469",
    "sg:province":"Baden-W\u00fcrttemberg",
    "wof:name":"Sigma Ges. F\u00fcr Software- Entwicklung Und Beratung Mbh",
    "wof:placetype":"venue"
},
  "geometry": {"coordinates":[8.6667203903,49.559211731],"type":"Point"}
}