{
  "type": "Feature",
  "properties": {
    "iso:country":"DE",
    "sg:address":"Schlo\u00dfgartenstr. 4",
    "sg:city":"N\u00fcrtingen",
    "sg:postcode":"72622",
    "sg:province":"Baden-W\u00fcrttemberg",
    "wof:name":"Production Service Vertriebs- Gesellschaft F\u00fcr Medien- Und",
    "wof:placetype":"venue"
},
  "geometry": {"coordinates":[9.336350441,48.627368927],"type":"Point"}
}