{
  "type": "Feature",
  "properties": {
    "iso:country":"DE",
    "sg:address":"Beurener Str. 4",
    "sg:city":"Frickenhausen",
    "sg:phone":"+49 7025/3110",
    "sg:postcode":"72636",
    "sg:province":"Baden-W\u00fcrttemberg",
    "wof:name":"H. Wohlfahrt",
    "wof:placetype":"venue"
},
  "geometry": {"coordinates":[9.372407,48.579723],"type":"Point"}
}