{
  "type": "Feature",
  "properties": {
    "iso:country":"DE",
    "sg:address":"Thiemigstr. 5",
    "sg:city":"Elsterwerda",
    "sg:phone":"+49 3533/4615",
    "sg:postcode":"04910",
    "sg:province":"Brandenburg",
    "wof:name":"Anlagenbau Gas Elsterwerda Gmbh",
    "wof:placetype":"venue"
},
  "geometry": {"coordinates":[13.518825531,51.4560317993],"type":"Point"}
}