{
  "type": "Feature",
  "properties": {
    "iso:country":"DE",
    "sg:address":"Webergasse 12",
    "sg:city":"Wangen",
    "sg:phone":"+49 7522/20548",
    "sg:postcode":"88239",
    "sg:province":"Baden-W\u00fcrttemberg",
    "wof:name":"Pilsbar Catweazle",
    "wof:placetype":"venue"
},
  "geometry": {"coordinates":[9.8347253799,47.6845741272],"type":"Point"}
}