{
  "type": "Feature",
  "properties": {
    "iso:country":"DE",
    "sg:address":"Hohenzollernstr. 1",
    "sg:city":"Herrenberg",
    "sg:phone":"+49 7032/952209",
    "sg:postcode":"71083",
    "sg:province":"Baden-W\u00fcrttemberg",
    "wof:name":"Kurt Steinemann",
    "wof:placetype":"venue"
},
  "geometry": {"coordinates":[8.841113,48.580822],"type":"Point"}
}