{
  "type": "Feature",
  "properties": {
    "iso:country":"DE",
    "sg:address":"Landsbergstr. 3",
    "sg:city":"Papenburg",
    "sg:phone":"+49 4961/2450",
    "sg:postcode":"26871",
    "sg:province":"Niedersachsen",
    "wof:name":"Heinz Spinn",
    "wof:placetype":"venue"
},
  "geometry": {"coordinates":[7.391740799,53.0840644836],"type":"Point"}
}