{
  "type": "Feature",
  "properties": {
    "iso:country":"DE",
    "sg:address":"Dorfstr. 6",
    "sg:city":"Radewege",
    "sg:phone":"+49 33836/40226",
    "sg:postcode":"14778",
    "sg:province":"Brandenburg",
    "wof:name":"Carsten Stiehl",
    "wof:placetype":"venue"
},
  "geometry": {"coordinates":[12.575502,52.479683],"type":"Point"}
}