{
  "type": "Feature",
  "properties": {
    "iso:country":"DE",
    "sg:address":"Waisenhausstr. 56-58",
    "sg:city":"M\u00fcnchen",
    "sg:phone":"+49 89/156081",
    "sg:postcode":"80637",
    "sg:province":"Bayern",
    "wof:name":"Bayerische Vereinsbank Ag",
    "wof:placetype":"venue"
},
  "geometry": {"coordinates":[11.529231,48.163319],"type":"Point"}
}