{
  "type": "Feature",
  "properties": {
    "iso:country":"DE",
    "sg:address":"Frankfurter Str. 1",
    "sg:city":"K\u00f6nigstein",
    "sg:phone":"+49 6174/5256",
    "sg:postcode":"61462",
    "sg:province":"Hessen",
    "wof:name":"Gamma Treuhand Gmbh Steuerberatungsgesellschaft",
    "wof:placetype":"venue"
},
  "geometry": {"coordinates":[8.4682149887,50.1821098328],"type":"Point"}
}