{
  "type": "Feature",
  "properties": {
    "iso:country":"DE",
    "sg:address":"Ovelheider Weg 170",
    "sg:city":"Marl",
    "sg:phone":"+49 2365/84619",
    "sg:postcode":"45772",
    "sg:province":"Nordrhein-Westfalen",
    "wof:name":"R\u00f6ttger Gmbh",
    "wof:placetype":"venue"
},
  "geometry": {"coordinates":[7.1508188248,51.6646728516],"type":"Point"}
}