{
  "type": "Feature",
  "properties": {
    "iso:country":"DE",
    "sg:address":"Warnenweg 12",
    "sg:city":"Hamburg",
    "sg:phone":"+49 40/5513347",
    "sg:postcode":"22455",
    "sg:province":"Hamburg",
    "wof:name":"Sanyo Hartmut Liebehenz",
    "wof:placetype":"venue"
},
  "geometry": {"coordinates":[9.9549789429,53.6461601257],"type":"Point"}
}