{
  "type": "Feature",
  "properties": {
    "iso:country":"DE",
    "sg:address":"Portenl\u00e4ngerstr. 24 a",
    "sg:city":"Gr\u00fcnwald",
    "sg:phone":"+49 89/6411029",
    "sg:postcode":"82031",
    "sg:province":"Bayern",
    "wof:name":"Heko Projektmanagement Gmbh",
    "wof:placetype":"venue"
},
  "geometry": {"coordinates":[11.539385,48.043671],"type":"Point"}
}