{
  "type": "Feature",
  "properties": {
    "iso:country":"DE",
    "sg:address":"Heiligenhafener Chaussee 63",
    "sg:city":"Oldenburg",
    "sg:phone":"+49 4361/63232",
    "sg:postcode":"23758",
    "sg:province":"Schleswig-Holstein",
    "wof:name":"M. K\u00e4hler",
    "wof:placetype":"venue"
},
  "geometry": {"coordinates":[-85.206238,39.339813],"type":"Point"}
}