{
  "type": "Feature",
  "properties": {
    "iso:country":"DE",
    "sg:address":"Kuhlenstr. 55",
    "sg:city":"M\u00fclheim",
    "sg:phone":"+49 208/470761",
    "sg:postcode":"45468",
    "sg:province":"Nordrhein-Westfalen",
    "wof:name":"S. Meding Brotvertrieb",
    "wof:placetype":"venue"
},
  "geometry": {"coordinates":[6.893254,51.43774],"type":"Point"}
}