{
  "type": "Feature",
  "properties": {
    "iso:country":"DE",
    "sg:address":"Landstr. 2",
    "sg:city":"Schwendi",
    "sg:phone":"+49 7353/3270",
    "sg:postcode":"88477",
    "sg:province":"Baden-W\u00fcrttemberg",
    "wof:name":"Manfred Ruchti",
    "wof:placetype":"venue"
},
  "geometry": {"coordinates":[9.959123,48.212296],"type":"Point"}
}