{
  "type": "Feature",
  "properties": {
    "iso:country":"DE",
    "sg:address":"Beethovenstr. 8-10",
    "sg:city":"Frankfurt",
    "sg:postcode":"60325",
    "sg:province":"Hessen",
    "wof:name":"New Technologies Holding Ag",
    "wof:placetype":"venue"
},
  "geometry": {"coordinates":[8.657321,50.112373],"type":"Point"}
}