{
  "type": "Feature",
  "properties": {
    "iso:country":"DE",
    "sg:address":"Aschaffenburger Str. 49",
    "sg:city":"Goldbach",
    "sg:phone":"+49 6021/53806",
    "sg:postcode":"63773",
    "sg:province":"Bayern",
    "wof:name":"Pizzeria Pizza Pazza Bei Pietro",
    "wof:placetype":"venue"
},
  "geometry": {"coordinates":[9.1803970337,49.9974708557],"type":"Point"}
}