{
  "type": "Feature",
  "properties": {
    "iso:country":"DE",
    "sg:address":"Karlsbader Str. 11",
    "sg:city":"Baunatal",
    "sg:phone":"+49 5601/8545",
    "sg:postcode":"34225",
    "sg:province":"Hessen",
    "wof:name":"Josef Schmid",
    "wof:placetype":"venue"
},
  "geometry": {"coordinates":[9.393012,51.253799],"type":"Point"}
}