{
  "type": "Feature",
  "properties": {
    "iso:country":"DE",
    "sg:address":"Wilhelmstr. 29 a",
    "sg:city":"Wetter",
    "sg:phone":"+49 2335/1033",
    "sg:postcode":"58300",
    "sg:province":"Nordrhein-Westfalen",
    "wof:name":"Gerhard Str\u00fcmper Rechtsanwalt",
    "wof:placetype":"venue"
},
  "geometry": {"coordinates":[7.396625042,51.385684967],"type":"Point"}
}