{
  "type": "Feature",
  "properties": {
    "iso:country":"DE",
    "sg:address":"Schmale Gasse 64",
    "sg:city":"Kirchscheidungen",
    "sg:phone":"+49 34462/20543",
    "sg:postcode":"06636",
    "sg:province":"Sachsen-Anhalt",
    "wof:name":"Baustoffhandel Farys Gmbh",
    "wof:placetype":"venue"
},
  "geometry": {"coordinates":[11.65611,51.244331],"type":"Point"}
}