{
  "type": "Feature",
  "properties": {
    "iso:country":"DE",
    "sg:address":"St. H\u00fclfer Dorfstr. 34",
    "sg:city":"Diepholz",
    "sg:phone":"+49 5441/3470",
    "sg:postcode":"49356",
    "sg:province":"Niedersachsen",
    "wof:name":"Wilhelm Wiechering",
    "wof:placetype":"venue"
},
  "geometry": {"coordinates":[8.394055,52.620697],"type":"Point"}
}