{
  "type": "Feature",
  "properties": {
    "iso:country":"DE",
    "sg:address":"Kirchenstr. 29",
    "sg:city":"Ladenburg",
    "sg:phone":"+49 6203/16288",
    "sg:postcode":"68526",
    "sg:province":"Baden-W\u00fcrttemberg",
    "wof:name":"A. Wagner",
    "wof:placetype":"venue"
},
  "geometry": {"coordinates":[8.610486,49.47142],"type":"Point"}
}