{
  "type": "Feature",
  "properties": {
    "iso:country":"DE",
    "sg:address":"Zur Bauerschaft 48",
    "sg:city":"Wesel",
    "sg:phone":"+49 2803/4512",
    "sg:postcode":"46487",
    "sg:province":"Nordrhein-Westfalen",
    "wof:name":"Josef Peckel",
    "wof:placetype":"venue"
},
  "geometry": {"coordinates":[6.542579,51.651672],"type":"Point"}
}