{
  "type": "Feature",
  "properties": {
    "iso:country":"DE",
    "sg:address":"Heddernheimer Landstr. 27",
    "sg:city":"Frankfurt",
    "sg:phone":"+49 69/571433",
    "sg:postcode":"60439",
    "sg:province":"Hessen",
    "wof:name":"Merkur-apotheke Apotheker Joachim Dosch E. K.",
    "wof:placetype":"venue"
},
  "geometry": {"coordinates":[8.648091,50.159695],"type":"Point"}
}