{
  "type": "Feature",
  "properties": {
    "iso:country":"DE",
    "sg:address":"Kirchstr. 8",
    "sg:city":"Ahaus",
    "sg:phone":"+49 2567/96222",
    "sg:postcode":"48683",
    "sg:province":"Nordrhein-Westfalen",
    "wof:name":"Heinrich Sicking Foto-drogerie",
    "wof:placetype":"venue"
},
  "geometry": {"coordinates":[6.915236,52.127975],"type":"Point"}
}