{
  "type": "Feature",
  "properties": {
    "iso:country":"DE",
    "sg:address":"Heegerstr. 18",
    "sg:city":"Velbert",
    "sg:phone":"+49 2052/3035",
    "sg:postcode":"42555",
    "sg:province":"Nordrhein-Westfalen",
    "wof:name":"Holz Lumbeck Gmbh",
    "wof:placetype":"venue"
},
  "geometry": {"coordinates":[7.1245188713,51.3626251221],"type":"Point"}
}