{
  "type": "Feature",
  "properties": {
    "iso:country":"DE",
    "sg:address":"Leipziger Str. 55",
    "sg:city":"Berlin",
    "sg:postcode":"10117",
    "sg:province":"Berlin",
    "wof:name":"Jugendklub Leipziger Stra\u00dfe",
    "wof:placetype":"venue"
},
  "geometry": {"coordinates":[13.3996734619,52.5112991333],"type":"Point"}
}