{
  "type": "Feature",
  "properties": {
    "iso:country":"DE",
    "sg:address":"Eppendorfer Landstr. 161",
    "sg:city":"Hamburg",
    "sg:phone":"+49 40/482292",
    "sg:postcode":"20251",
    "sg:province":"Hamburg",
    "wof:name":"K\u00f6necke Systems Gmbh",
    "wof:placetype":"venue"
},
  "geometry": {"coordinates":[9.987699,53.595928],"type":"Point"}
}