{
  "type": "Feature",
  "properties": {
    "iso:country":"DE",
    "sg:address":"Petersbergstr 51",
    "sg:city":"Saarbr\u00fccken",
    "sg:phone":"+49 681/703042",
    "sg:postcode":"66119",
    "sg:province":"Saarland",
    "wof:name":"Fbb F\u00f6rderband Gmbh",
    "wof:placetype":"venue"
},
  "geometry": {"coordinates":[6.989675045,49.22215271],"type":"Point"}
}