{
  "type": "Feature",
  "properties": {
    "iso:country":"DE",
    "sg:address":"Rotenbergstr. 72",
    "sg:city":"Hattorf",
    "sg:phone":"+49 5584/2639",
    "sg:postcode":"37197",
    "sg:province":"Niedersachsen",
    "wof:name":"H. Albrecht",
    "wof:placetype":"venue"
},
  "geometry": {"coordinates":[10.228395,51.638348],"type":"Point"}
}