{
  "type": "Feature",
  "properties": {
    "iso:country":"DE",
    "sg:address":"Alter M\u00fchlenweg 4",
    "sg:city":"Hemsb\u00fcnde",
    "sg:phone":"+49 4266/338",
    "sg:postcode":"27386",
    "sg:province":"Niedersachsen",
    "wof:name":"Konrad Rasch",
    "wof:placetype":"venue"
},
  "geometry": {"coordinates":[9.478058,53.088367],"type":"Point"}
}