{
  "type": "Feature",
  "properties": {
    "iso:country":"DE",
    "sg:address":"Zeppelinstr.",
    "sg:city":"Frankenthal",
    "sg:phone":"+49 6233/77030",
    "sg:postcode":"67227",
    "sg:province":"Rheinland-Pfalz",
    "wof:name":"Zeppelin Baumaschinen Gmbh",
    "wof:placetype":"venue"
},
  "geometry": {"coordinates":[8.346059,49.553246],"type":"Point"}
}