{
  "type": "Feature",
  "properties": {
    "iso:country":"DE",
    "sg:address":"Hauptstr. 17",
    "sg:city":"Waibstadt",
    "sg:phone":"+49 7263/2580",
    "sg:postcode":"74915",
    "sg:province":"Baden-W\u00fcrttemberg",
    "wof:name":"B\u00e4ckerei Heike Schmid Gmbh",
    "wof:placetype":"venue"
},
  "geometry": {"coordinates":[8.92021,49.298847],"type":"Point"}
}