{
  "type": "Feature",
  "properties": {
    "iso:country":"DE",
    "sg:address":"Poststr. 15",
    "sg:city":"D\u00fcsseldorf",
    "sg:phone":"+49 211/327791",
    "sg:postcode":"40213",
    "sg:province":"Nordrhein-Westfalen",
    "wof:name":"Fotostudio Luenen",
    "wof:placetype":"venue"
},
  "geometry": {"coordinates":[6.7717161179,51.2209587097],"type":"Point"}
}