{
  "type": "Feature",
  "properties": {
    "iso:country":"DE",
    "sg:address":"Teutoburger Str. 19",
    "sg:city":"K\u00f6ln",
    "sg:phone":"+49 221/9320843",
    "sg:postcode":"50678",
    "sg:province":"Nordrhein-Westfalen",
    "wof:name":"Homepage Von Marlene Z\u00f6ller-borggreve - K\u00f6ln",
    "wof:placetype":"venue"
},
  "geometry": {"coordinates":[6.962962,50.91906],"type":"Point"}
}