{
  "type": "Feature",
  "properties": {
    "iso:country":"DE",
    "sg:address":"Zerfer Str. 43",
    "sg:city":"Irsch",
    "sg:phone":"+49 6581/6725",
    "sg:postcode":"54451",
    "sg:province":"Rheinland-Pfalz",
    "wof:name":"B. Michels",
    "wof:placetype":"venue"
},
  "geometry": {"coordinates":[6.6004118919,49.6031951904],"type":"Point"}
}