{
  "type": "Feature",
  "properties": {
    "iso:country":"DE",
    "sg:address":"Haller Str. 43",
    "sg:city":"Weinsberg",
    "sg:phone":"+49 7134/17430",
    "sg:postcode":"74189",
    "sg:province":"Baden-W\u00fcrttemberg",
    "wof:name":"Lothar Philipp",
    "wof:placetype":"venue"
},
  "geometry": {"coordinates":[9.2956800461,49.1500396729],"type":"Point"}
}