{
  "type": "Feature",
  "properties": {
    "iso:country":"DE",
    "sg:address":"Habichtstr. 24 a",
    "sg:city":"Hattingen",
    "sg:postcode":"45527",
    "sg:province":"Nordrhein-Westfalen",
    "wof:name":"Stadtb\u00fccherei Hattingen-bredenscheid",
    "wof:placetype":"venue"
},
  "geometry": {"coordinates":[7.195159,51.374367],"type":"Point"}
}