{
  "type": "Feature",
  "properties": {
    "iso:country":"DE",
    "sg:address":"Vischerstr. 1",
    "sg:city":"Aschaffenburg",
    "sg:phone":"+49 6021/960147",
    "sg:postcode":"63739",
    "sg:province":"Bayern",
    "wof:name":"W. Str\u00f6bel Anlageberater",
    "wof:placetype":"venue"
},
  "geometry": {"coordinates":[9.16776371,49.9747238159],"type":"Point"}
}