{
  "type": "Feature",
  "properties": {
    "iso:country":"DE",
    "sg:address":"Clemens-August-Str. 3",
    "sg:city":"Bonn",
    "sg:phone":"+49 228/694800",
    "sg:postcode":"53115",
    "sg:province":"Nordrhein-Westfalen",
    "wof:name":"Klim-bim",
    "wof:placetype":"venue"
},
  "geometry": {"coordinates":[7.090107,50.72401],"type":"Point"}
}