{
  "type": "Feature",
  "properties": {
    "iso:country":"DE",
    "sg:address":"Paulinenstr.45",
    "sg:city":"Detmold",
    "sg:phone":"+49 4952/317408",
    "sg:postcode":"32756",
    "sg:province":"Nordrhein-Westfalen",
    "wof:name":"Dresdner Bank",
    "wof:placetype":"venue"
},
  "geometry": {"coordinates":[8.874919,51.93766],"type":"Point"}
}