{
  "type": "Feature",
  "properties": {
    "iso:country":"DE",
    "sg:address":"Woldegker Chaussee 46",
    "sg:city":"C\u00f6lpin",
    "sg:phone":"+49 3966/210367",
    "sg:postcode":"17094",
    "sg:province":"Mecklenburg-Vorpommern",
    "wof:name":"Hubert Schulz Ingenieur",
    "wof:placetype":"venue"
},
  "geometry": {"coordinates":[13.4302759171,53.5234298706],"type":"Point"}
}