{
  "type": "Feature",
  "properties": {
    "iso:country":"DE",
    "sg:address":"Marktplatz 19",
    "sg:city":"Hauzenberg",
    "sg:phone":"+49 8586/1268",
    "sg:postcode":"94051",
    "sg:province":"Bayern",
    "wof:name":"Stadt-apotheke Inh. Sibylle Hameier",
    "wof:placetype":"venue"
},
  "geometry": {"coordinates":[13.624876,48.65089],"type":"Point"}
}