{
  "type": "Feature",
  "properties": {
    "iso:country":"DE",
    "sg:address":"Dehmelstr. 19",
    "sg:city":"Rostock",
    "sg:phone":"+49 381/492780",
    "sg:postcode":"18055",
    "sg:province":"Mecklenburg-Vorpommern",
    "wof:name":"Kremer Und Gr\u00fcnkorn Rechtsanw\u00e4lte",
    "wof:placetype":"venue"
},
  "geometry": {"coordinates":[12.140083313,54.0779380798],"type":"Point"}
}