{
  "type": "Feature",
  "properties": {
    "iso:country":"DE",
    "sg:address":"Tecklenburger Str. 38",
    "sg:city":"Steinfurt",
    "sg:phone":"+49 2551/82095",
    "sg:postcode":"48565",
    "sg:province":"Nordrhein-Westfalen",
    "wof:name":"M.-i. Helling Hebamme",
    "wof:placetype":"venue"
},
  "geometry": {"coordinates":[7.359222,52.152615],"type":"Point"}
}