{
  "type": "Feature",
  "properties": {
    "iso:country":"DE",
    "sg:address":"Eppendorfer Landstr. 33",
    "sg:city":"Hamburg",
    "sg:phone":"+49 40/473338",
    "sg:postcode":"20249",
    "sg:province":"Hamburg",
    "wof:name":"Rosemarie Dypka Heilpraktikerin",
    "wof:placetype":"venue"
},
  "geometry": {"coordinates":[9.9851341248,53.587890625],"type":"Point"}
}