{
  "type": "Feature",
  "properties": {
    "iso:country":"DE",
    "sg:address":"Kirchstr. 21",
    "sg:city":"Swisttal",
    "sg:phone":"+49 2254/7124",
    "sg:postcode":"53913",
    "sg:province":"Nordrhein-Westfalen",
    "wof:name":"Michael Lethert",
    "wof:placetype":"venue"
},
  "geometry": {"coordinates":[6.9141478539,50.7166442871],"type":"Point"}
}