{
  "type": "Feature",
  "properties": {
    "iso:country":"DE",
    "sg:address":"Dangaster Str. 13",
    "sg:city":"Sande",
    "sg:phone":"+49 4422/2281",
    "sg:postcode":"26452",
    "sg:province":"Niedersachsen",
    "wof:name":"Dietrich Theilen",
    "wof:placetype":"venue"
},
  "geometry": {"coordinates":[8.046294,53.472267],"type":"Point"}
}