{
  "type": "Feature",
  "properties": {
    "iso:country":"DE",
    "sg:address":"Hagenhofweg 35",
    "sg:city":"Michelbach/Bilz",
    "sg:phone":"+49 791/930160",
    "sg:postcode":"74544",
    "sg:province":"Baden-W\u00fcrttemberg",
    "wof:name":"Evangelisches Schulzentrum 74544 Michelbach/bilz",
    "wof:placetype":"venue"
},
  "geometry": {"coordinates":[9.763315,49.077164],"type":"Point"}
}