{
  "type": "Feature",
  "properties": {
    "iso:country":"DE",
    "sg:address":"Benzstr. 3",
    "sg:city":"Eggenstein-Leopoldshafen",
    "sg:phone":"+49 721/970420",
    "sg:postcode":"76344",
    "sg:province":"Baden-W\u00fcrttemberg",
    "wof:name":"Stober & Nees Gmbh",
    "wof:placetype":"venue"
},
  "geometry": {"coordinates":[8.3789339066,49.0771484375],"type":"Point"}
}