{
  "type": "Feature",
  "properties": {
    "iso:country":"DE",
    "sg:address":"Sperlingsweg 4",
    "sg:city":"Viersen",
    "sg:phone":"+49 2162/67246",
    "sg:postcode":"41749",
    "sg:province":"Nordrhein-Westfalen",
    "wof:name":"Schn\u00e4bler Gmbh",
    "wof:placetype":"venue"
},
  "geometry": {"coordinates":[6.368492,51.282852],"type":"Point"}
}