{
  "type": "Feature",
  "properties": {
    "iso:country":"DE",
    "sg:address":"Eulenweg 19",
    "sg:city":"Raubling",
    "sg:phone":"+49 8035/1402",
    "sg:postcode":"83064",
    "sg:province":"Bayern",
    "wof:name":"Ronald Hell",
    "wof:placetype":"venue"
},
  "geometry": {"coordinates":[12.0984382629,47.7886428833],"type":"Point"}
}