{
  "type": "Feature",
  "properties": {
    "iso:country":"DE",
    "sg:address":"Hamelner Str. 20 b",
    "sg:city":"Aerzen",
    "sg:phone":"+49 5154/96660",
    "sg:postcode":"31855",
    "sg:province":"Niedersachsen",
    "wof:name":"Baby-paradies Gmbh",
    "wof:placetype":"venue"
},
  "geometry": {"coordinates":[9.3056535721,52.0673027039],"type":"Point"}
}