{
  "type": "Feature",
  "properties": {
    "iso:country":"DE",
    "sg:address":"Koblenzer Str. 122 POSTFACH 101554",
    "sg:city":"Neuss",
    "sg:phone":"+49 4921/313820",
    "sg:postcode":"41415",
    "sg:province":"Nordrhein-Westfalen",
    "wof:name":"Hydro Aluminium Ag",
    "wof:placetype":"venue"
},
  "geometry": {"coordinates":[6.7816,51.155369],"type":"Point"}
}