{
  "type": "Feature",
  "properties": {
    "iso:country":"DE",
    "sg:address":"Kleikstr. 48",
    "sg:city":"Herzogenrath",
    "sg:phone":"+49 2406/7116",
    "sg:postcode":"52134",
    "sg:province":"Nordrhein-Westfalen",
    "wof:name":"G & L Objektbau Gmbh",
    "wof:placetype":"venue"
},
  "geometry": {"coordinates":[6.092706,50.867725],"type":"Point"}
}