{
  "type": "Feature",
  "properties": {
    "iso:country":"DE",
    "sg:address":"Wernsdorfer Str. 90",
    "sg:city":"Niederlehme",
    "sg:postcode":"15751",
    "sg:province":"Brandenburg",
    "wof:name":"Edeka Aktiv Markt",
    "wof:placetype":"venue"
},
  "geometry": {"coordinates":[13.6516857147,52.3227844238],"type":"Point"}
}