{
  "type": "Feature",
  "properties": {
    "iso:country":"DE",
    "sg:address":"Glatzer Str. 19",
    "sg:city":"H\u00f6rstel",
    "sg:phone":"+49 5978/917609",
    "sg:postcode":"48477",
    "sg:province":"Nordrhein-Westfalen",
    "wof:name":"K. -u. D\u00fcttmann",
    "wof:placetype":"venue"
},
  "geometry": {"coordinates":[7.4985542297,52.333065033],"type":"Point"}
}