{
  "type": "Feature",
  "properties": {
    "iso:country":"DE",
    "sg:address":"Im Ohl 15a",
    "sg:city":"Arnsberg",
    "sg:phone":"+49 2932/7879",
    "sg:postcode":"59757",
    "sg:province":"Nordrhein-Westfalen",
    "wof:name":"Silver Dollar Spielecke Gmbh",
    "wof:placetype":"venue"
},
  "geometry": {"coordinates":[7.9516658783,51.4568405151],"type":"Point"}
}