{
  "type": "Feature",
  "properties": {
    "iso:country":"DE",
    "sg:address":"Esslinger Str. 20",
    "sg:city":"Stuttgart",
    "sg:phone":"+49 711/244141",
    "sg:postcode":"70182",
    "sg:province":"Baden-W\u00fcrttemberg",
    "wof:name":"J\u00fcrgen Leippert Kunstmaler",
    "wof:placetype":"venue"
},
  "geometry": {"coordinates":[9.182175,48.774368],"type":"Point"}
}