{
  "type": "Feature",
  "properties": {
    "iso:country":"DE",
    "sg:address":"Widum 1",
    "sg:city":"Oberstdorf",
    "sg:phone":"+49 8326/8384",
    "sg:postcode":"87561",
    "sg:province":"Bayern",
    "wof:name":"Johannes Schmid",
    "wof:placetype":"venue"
},
  "geometry": {"coordinates":[10.286978,47.4501],"type":"Point"}
}