{
  "type": "Feature",
  "properties": {
    "iso:country":"DE",
    "sg:address":"Amselweg 2-6",
    "sg:city":"Lippstadt",
    "sg:phone":"+49 2941/94020",
    "sg:postcode":"59556",
    "sg:province":"Nordrhein-Westfalen",
    "wof:name":"Haus Amselhof Senioren- Residenz Gmbh",
    "wof:placetype":"venue"
},
  "geometry": {"coordinates":[8.345427,51.709877],"type":"Point"}
}