{
  "type": "Feature",
  "properties": {
    "iso:country":"DE",
    "sg:address":"Am Wasserturm 20",
    "sg:city":"Frechen",
    "sg:phone":"+49 2234/22402",
    "sg:postcode":"50226",
    "sg:province":"Nordrhein-Westfalen",
    "wof:name":"Dieter Fa\u00dfbender",
    "wof:placetype":"venue"
},
  "geometry": {"coordinates":[6.791425,50.909489],"type":"Point"}
}