{
  "type": "Feature",
  "properties": {
    "iso:country":"DE",
    "sg:address":"Heinrich-Mann-Allee 71",
    "sg:city":"Potsdam",
    "sg:phone":"+49 331/888230",
    "sg:postcode":"14478",
    "sg:province":"Brandenburg",
    "wof:name":"Pension Mark Brandenburg",
    "wof:placetype":"venue"
},
  "geometry": {"coordinates":[13.0837898254,52.3765716553],"type":"Point"}
}