{
  "type": "Feature",
  "properties": {
    "iso:country":"DE",
    "sg:address":"Bergstr. 12",
    "sg:city":"Kastl",
    "sg:phone":"+49 8671/12737",
    "sg:postcode":"84556",
    "sg:province":"Bayern",
    "wof:name":"Johann Voggenreiter",
    "wof:placetype":"venue"
},
  "geometry": {"coordinates":[12.6948575974,48.1936988831],"type":"Point"}
}