{
  "type": "Feature",
  "properties": {
    "iso:country":"DE",
    "sg:address":"Goethestr. 68",
    "sg:city":"M\u00fcnchen",
    "sg:phone":"+49 89/539557",
    "sg:postcode":"80336",
    "sg:province":"Bayern",
    "wof:name":"Witte Und Witte Rechtsanw\u00e4lte",
    "wof:placetype":"venue"
},
  "geometry": {"coordinates":[11.5582351685,48.1316299438],"type":"Point"}
}