{
  "type": "Feature",
  "properties": {
    "iso:country":"DE",
    "sg:address":"Nelkenweg 12",
    "sg:city":"Eitorf",
    "sg:phone":"+49 2243/5909",
    "sg:postcode":"53783",
    "sg:province":"Nordrhein-Westfalen",
    "wof:name":"Kaptein Gmbh",
    "wof:placetype":"venue"
},
  "geometry": {"coordinates":[7.438322,50.772606],"type":"Point"}
}