{
  "type": "Feature",
  "properties": {
    "iso:country":"DE",
    "sg:address":"Friedrich-Poth-Str. 2",
    "sg:city":"Wallhalben",
    "sg:phone":"+49 6375/338",
    "sg:postcode":"66917",
    "sg:province":"Rheinland-Pfalz",
    "wof:name":"Kurt Leiner",
    "wof:placetype":"venue"
},
  "geometry": {"coordinates":[7.524757,49.315762],"type":"Point"}
}