{
  "type": "Feature",
  "properties": {
    "iso:country":"DE",
    "sg:address":"Ehranger Str. 136",
    "sg:city":"Trier",
    "sg:phone":"+49 651/66178",
    "sg:postcode":"54293",
    "sg:province":"Rheinland-Pfalz",
    "wof:name":"Mosel-apotheke",
    "wof:placetype":"venue"
},
  "geometry": {"coordinates":[6.680427,49.794769],"type":"Point"}
}