{
  "type": "Feature",
  "properties": {
    "iso:country":"DE",
    "sg:address":"Halenseestr. 6",
    "sg:city":"Berlin",
    "sg:phone":"+49 30/8911396",
    "sg:postcode":"10711",
    "sg:province":"Berlin",
    "wof:name":"Wolfgang Genz",
    "wof:placetype":"venue"
},
  "geometry": {"coordinates":[13.285124,52.495476],"type":"Point"}
}