{
  "type": "Feature",
  "properties": {
    "iso:country":"DE",
    "sg:address":"Schulstr. 14 POSTFACH 1264",
    "sg:city":"Trostberg",
    "sg:phone":"+49 8621/8010",
    "sg:postcode":"83303",
    "sg:province":"Bayern",
    "wof:name":"Stadtwerketrostberg Gmbh & Co. Kg",
    "wof:placetype":"venue"
},
  "geometry": {"coordinates":[12.555179,48.028122],"type":"Point"}
}