{
  "type": "Feature",
  "properties": {
    "iso:country":"DE",
    "sg:address":"Entenfangstr. 8",
    "sg:city":"Wesseling",
    "sg:phone":"+49 2232/46979",
    "sg:postcode":"50389",
    "sg:province":"Nordrhein-Westfalen",
    "wof:name":"Astrid Bresch Rechtsanwalt",
    "wof:placetype":"venue"
},
  "geometry": {"coordinates":[6.9513812065,50.8295440674],"type":"Point"}
}