{
  "type": "Feature",
  "properties": {
    "iso:country":"DE",
    "sg:address":"Bismarckstr. 3",
    "sg:city":"Melle",
    "sg:phone":"+49 5422/2545",
    "sg:postcode":"49324",
    "sg:province":"Niedersachsen",
    "wof:name":"I. Helwich",
    "wof:placetype":"venue"
},
  "geometry": {"coordinates":[8.3415241241,52.2065963745],"type":"Point"}
}