{
  "type": "Feature",
  "properties": {
    "iso:country":"DE",
    "sg:address":"Techentiner Str. 1",
    "sg:city":"Ludwigslust",
    "sg:phone":"+49 3874/20815",
    "sg:postcode":"19288",
    "sg:province":"Mecklenburg-Vorpommern",
    "wof:name":"Kanzlei Zu Ludwigslust",
    "wof:placetype":"venue"
},
  "geometry": {"coordinates":[11.497205,53.320484],"type":"Point"}
}