{
  "type": "Feature",
  "properties": {
    "iso:country":"DE",
    "sg:address":"Siedlerhof",
    "sg:city":"H\u00fcbingen",
    "sg:phone":"+49 2602/5560",
    "sg:postcode":"56412",
    "sg:province":"Rheinland-Pfalz",
    "wof:name":"Reiterhof Montabaur Inh. Irmgard Gies",
    "wof:placetype":"venue"
},
  "geometry": {"coordinates":[7.8479299545,50.3567886353],"type":"Point"}
}