{
  "type": "Feature",
  "properties": {
    "iso:country":"DE",
    "sg:address":"Ulmenstrasse 22::",
    "sg:city":"Frankfurt",
    "sg:phone":"+49 4969/170021",
    "sg:postcode":"60325",
    "sg:province":"Hessen",
    "wof:name":"Elexis Ag",
    "wof:placetype":"venue"
},
  "geometry": {"coordinates":[8.665751,50.115627],"type":"Point"}
}