{
  "type": "Feature",
  "properties": {
    "iso:country":"DE",
    "sg:address":"\u00dcberwasserstr. 30",
    "sg:city":"M\u00fcnster",
    "sg:phone":"+49 251/43701",
    "sg:postcode":"48143",
    "sg:province":"Nordrhein-Westfalen",
    "wof:name":"Werner Reckhenrich Gmbh",
    "wof:placetype":"venue"
},
  "geometry": {"coordinates":[7.6186890602,51.9653320312],"type":"Point"}
}