{
  "type": "Feature",
  "properties": {
    "iso:country":"DE",
    "sg:address":"Am Hauptbahnhof 3",
    "sg:city":"Essen",
    "sg:postcode":"45127",
    "sg:province":"Nordrhein-Westfalen",
    "wof:name":"Db Regionalbahn Rhein-ruhr Gmbh",
    "wof:placetype":"venue"
},
  "geometry": {"coordinates":[7.0150489807,51.4520606995],"type":"Point"}
}