{
  "type": "Feature",
  "properties": {
    "iso:country":"DE",
    "sg:address":"Ostendstr. 19",
    "sg:city":"Karlsruhe",
    "sg:phone":"+49 721/31631",
    "sg:postcode":"76131",
    "sg:province":"Baden-W\u00fcrttemberg",
    "wof:name":"Kneiple",
    "wof:placetype":"venue"
},
  "geometry": {"coordinates":[8.4163150787,49.0056304932],"type":"Point"}
}