{
  "type": "Feature",
  "properties": {
    "iso:country":"DE",
    "sg:address":"St.-Josef-Siedlung 4",
    "sg:city":"Hochstadt",
    "sg:phone":"+49 9574/3080",
    "sg:postcode":"96272",
    "sg:province":"Bayern",
    "wof:name":"Adelheid Semmelroch",
    "wof:placetype":"venue"
},
  "geometry": {"coordinates":[11.176378,50.151775],"type":"Point"}
}