{
  "type": "Feature",
  "properties": {
    "iso:country":"DE",
    "sg:address":"An den Sportpl\u00e4tzen 21",
    "sg:city":"M\u00f6rfelden-Walldorf",
    "sg:phone":"+49 6105/43068",
    "sg:postcode":"64546",
    "sg:province":"Hessen",
    "wof:name":"Vereinsgastst\u00e4tte Rot-wei\u00df",
    "wof:placetype":"venue"
},
  "geometry": {"coordinates":[8.5659809113,50.0054359436],"type":"Point"}
}