{
  "type": "Feature",
  "properties": {
    "iso:country":"DE",
    "sg:address":"Christoph-Bauer-Str. 7",
    "sg:city":"Pei\u00dfenberg",
    "sg:phone":"+49 8803/9330",
    "sg:postcode":"82380",
    "sg:province":"Bayern",
    "wof:name":"Herbert Kratschmar",
    "wof:placetype":"venue"
},
  "geometry": {"coordinates":[11.050151825,47.7798500061],"type":"Point"}
}