{
  "type": "Feature",
  "properties": {
    "iso:country":"DE",
    "sg:address":"Pfarrgasse 10",
    "sg:city":"Ebersdorf",
    "sg:phone":"+49 9562/9290",
    "sg:postcode":"96237",
    "sg:province":"Bayern",
    "wof:name":"Brk Alten- Und Pflegeheim",
    "wof:placetype":"venue"
},
  "geometry": {"coordinates":[11.070376,50.220665],"type":"Point"}
}