{
  "type": "Feature",
  "properties": {
    "iso:country":"DE",
    "sg:address":"Gustav-Wick-Str. 1",
    "sg:city":"Neuenburg",
    "sg:phone":"+49 7634/35643",
    "sg:postcode":"79395",
    "sg:province":"Baden-W\u00fcrttemberg",
    "wof:name":"Elektro Lakus Gmbh",
    "wof:placetype":"venue"
},
  "geometry": {"coordinates":[7.591177,47.874111],"type":"Point"}
}