{
  "type": "Feature",
  "properties": {
    "iso:country":"DE",
    "sg:address":"Backnanger Str. 67",
    "sg:city":"Aspach",
    "sg:phone":"+49 7191/20958",
    "sg:postcode":"71546",
    "sg:province":"Baden-W\u00fcrttemberg",
    "wof:name":"Schmidt & K\u00fcbler Gmbh",
    "wof:placetype":"venue"
},
  "geometry": {"coordinates":[9.4028120041,48.962978363],"type":"Point"}
}