{
  "type": "Feature",
  "properties": {
    "iso:country":"DE",
    "sg:address":"Warnhofen 21",
    "sg:city":"Bissingen",
    "sg:phone":"+49 9089/451",
    "sg:postcode":"86657",
    "sg:province":"Bayern",
    "wof:name":"E. Hommel",
    "wof:placetype":"venue"
},
  "geometry": {"coordinates":[10.5584592819,48.716632843],"type":"Point"}
}