{
  "type": "Feature",
  "properties": {
    "iso:country":"DE",
    "sg:address":"Bahnhofstr. 75",
    "sg:city":"Eichwalde",
    "sg:phone":"+49 30/6759699",
    "sg:postcode":"15732",
    "sg:province":"Brandenburg",
    "wof:name":"Kurzel",
    "wof:placetype":"venue"
},
  "geometry": {"coordinates":[13.620059967,52.3739585876],"type":"Point"}
}