{
  "type": "Feature",
  "properties": {
    "iso:country":"DE",
    "sg:address":"Brucknerstr. 20",
    "sg:city":"D\u00fcsseldorf",
    "sg:phone":"+49 211/715039",
    "sg:postcode":"40593",
    "sg:province":"Nordrhein-Westfalen",
    "wof:name":"Dr. Ulrich Hrabal Patentanwalt",
    "wof:placetype":"venue"
},
  "geometry": {"coordinates":[6.8782320023,51.1575813293],"type":"Point"}
}