{
  "type": "Feature",
  "properties": {
    "iso:country":"DE",
    "sg:address":"Gessbachstr. 2",
    "sg:city":"Neunkirchen",
    "sg:phone":"+49 4968/2140110",
    "sg:postcode":"66538",
    "sg:province":"Saarland",
    "wof:name":"Pss Pipe Support Systems Gmbh",
    "wof:placetype":"venue"
},
  "geometry": {"coordinates":[7.181634,49.354454],"type":"Point"}
}