{
  "type": "Feature",
  "properties": {
    "iso:country":"DE",
    "sg:address":"Reinsburgstr. 13",
    "sg:city":"Stuttgart",
    "sg:phone":"+49 711/666740",
    "sg:postcode":"70178",
    "sg:province":"Baden-W\u00fcrttemberg",
    "wof:name":"Friedrich Humbeck Architekt",
    "wof:placetype":"venue"
},
  "geometry": {"coordinates":[9.169572,48.771194],"type":"Point"}
}