{
  "type": "Feature",
  "properties": {
    "iso:country":"DE",
    "sg:address":"Merseburger Str. 185",
    "sg:city":"Halle",
    "sg:phone":"+49 345/4442917",
    "sg:postcode":"06112",
    "sg:province":"Sachsen-Anhalt",
    "wof:name":"Wilfried Gie\u00dfler",
    "wof:placetype":"venue"
},
  "geometry": {"coordinates":[11.9841070175,51.4588394165],"type":"Point"}
}