{
  "type": "Feature",
  "properties": {
    "iso:country":"DE",
    "sg:address":"Vordere Warmeleite 11",
    "sg:city":"Bad Berneck",
    "sg:phone":"+49 9273/7182",
    "sg:postcode":"95460",
    "sg:province":"Bayern",
    "wof:name":"Peter Lindner Modeagentur",
    "wof:placetype":"venue"
},
  "geometry": {"coordinates":[11.6801586151,50.03881073],"type":"Point"}
}