{
  "type": "Feature",
  "properties": {
    "iso:country":"DE",
    "sg:address":"Eichholzstr. 4",
    "sg:city":"Asbach",
    "sg:phone":"+49 2683/4796",
    "sg:postcode":"53567",
    "sg:province":"Rheinland-Pfalz",
    "wof:name":"Edith Sch\u00fctzeichel",
    "wof:placetype":"venue"
},
  "geometry": {"coordinates":[7.421596,50.664173],"type":"Point"}
}