{
  "type": "Feature",
  "properties": {
    "iso:country":"DE",
    "sg:address":"Oesdorfer Str. 14",
    "sg:city":"Bad Pyrmont",
    "sg:phone":"+49 5281/2281",
    "sg:postcode":"31812",
    "sg:province":"Niedersachsen",
    "wof:name":"W. H\u00e4nning Gmbh",
    "wof:placetype":"venue"
},
  "geometry": {"coordinates":[9.262383,51.983509],"type":"Point"}
}