{
  "type": "Feature",
  "properties": {
    "iso:country":"DE",
    "sg:address":"Koelnische Str. 108-114::",
    "sg:city":"Kassel",
    "sg:phone":"+49 4956/17881",
    "sg:postcode":"34119",
    "sg:province":"Hessen",
    "wof:name":"Bruderhilfe Sachversicherung Auf Gegenseitigkeit Im Raum Der Kirchen",
    "wof:placetype":"venue"
},
  "geometry": {"coordinates":[9.477233,51.317616],"type":"Point"}
}