{
  "type": "Feature",
  "properties": {
    "iso:country":"DE",
    "sg:address":"Scheidemannstr. 22",
    "sg:city":"Haan",
    "sg:phone":"+49 212/97595",
    "sg:postcode":"42781",
    "sg:province":"Nordrhein-Westfalen",
    "wof:name":"Wilhelm Schlaus Rechtsanwalt",
    "wof:placetype":"venue"
},
  "geometry": {"coordinates":[7.0241618156,51.1941604614],"type":"Point"}
}