{
  "type": "Feature",
  "properties": {
    "iso:country":"DE",
    "sg:address":"Hauptstr. 21",
    "sg:city":"Wesseling",
    "sg:phone":"+49 2232/51433",
    "sg:postcode":"50389",
    "sg:province":"Nordrhein-Westfalen",
    "wof:name":"Kleber Wirtschafts- Und Privat-detektei Gmbh",
    "wof:placetype":"venue"
},
  "geometry": {"coordinates":[6.953416,50.829952],"type":"Point"}
}