{
  "type": "Feature",
  "properties": {
    "iso:country":"DE",
    "sg:address":"Liesborner Str. 35",
    "sg:city":"Lippstadt",
    "sg:phone":"+49 2941/8820",
    "sg:postcode":"59556",
    "sg:province":"Nordrhein-Westfalen",
    "wof:name":"Bernhard Ortkemper Ohg",
    "wof:placetype":"venue"
},
  "geometry": {"coordinates":[8.3204231262,51.712348938],"type":"Point"}
}