{
  "type": "Feature",
  "properties": {
    "iso:country":"DE",
    "sg:address":"Robert-Koch-Str. 21",
    "sg:city":"M\u00fcnster",
    "sg:phone":"+49 251/80505",
    "sg:postcode":"48149",
    "sg:province":"Nordrhein-Westfalen",
    "wof:name":"Korber Inh. P. Hagedorn",
    "wof:placetype":"venue"
},
  "geometry": {"coordinates":[7.6049990654,51.958770752],"type":"Point"}
}