{
  "type": "Feature",
  "properties": {
    "iso:country":"DE",
    "sg:address":"Kurf\u00fcrstendamm 119",
    "sg:city":"Berlin",
    "sg:phone":"+49 30/890230",
    "sg:postcode":"10711",
    "sg:province":"Berlin",
    "wof:name":"Handycap Telekommunikation Handels Gmbh",
    "wof:placetype":"venue"
},
  "geometry": {"coordinates":[13.2881,52.496578],"type":"Point"}
}