{
  "type": "Feature",
  "properties": {
    "iso:country":"DE",
    "sg:address":"Wettinerstr. 11",
    "sg:city":"Wuppertal",
    "sg:postcode":"42287",
    "sg:province":"Nordrhein-Westfalen",
    "wof:name":"Bergische Verm\u00f6gens- Verwaltungs-gmbh",
    "wof:placetype":"venue"
},
  "geometry": {"coordinates":[7.199313,51.255768],"type":"Point"}
}