{
  "type": "Feature",
  "properties": {
    "iso:country":"DE",
    "sg:address":"Ermigh\u00e4user Weg 6",
    "sg:city":"Korbach",
    "sg:phone":"+49 5631/64001",
    "sg:postcode":"34497",
    "sg:province":"Hessen",
    "wof:name":"Ernst Kahlh\u00f6fer Gmbh",
    "wof:placetype":"venue"
},
  "geometry": {"coordinates":[8.8687334061,51.2785339355],"type":"Point"}
}