{
  "type": "Feature",
  "properties": {
    "iso:country":"DE",
    "sg:address":"Friedrich-Engels-Str. 43",
    "sg:city":"Jena",
    "sg:phone":"+49 3641/396926",
    "sg:postcode":"07749",
    "sg:province":"Th\u00fcringen",
    "wof:name":"Dr. Med. Reinhard F\u00fcnfst\u00fcck",
    "wof:placetype":"venue"
},
  "geometry": {"coordinates":[11.597474,50.923386],"type":"Point"}
}