{
  "type": "Feature",
  "properties": {
    "iso:country":"DE",
    "sg:address":"Baumerstr. 5",
    "sg:city":"Erfurt",
    "sg:postcode":"99089",
    "sg:province":"Th\u00fcringen",
    "wof:name":"Elmar Nolte Stadtentwicklungsges. Mbh",
    "wof:placetype":"venue"
},
  "geometry": {"coordinates":[11.016784668,50.9880714417],"type":"Point"}
}