{
  "type": "Feature",
  "properties": {
    "iso:country":"DE",
    "sg:address":"Im Heetwinkel 1",
    "sg:city":"Schermbeck",
    "sg:phone":"+49 2853/3060",
    "sg:postcode":"46514",
    "sg:province":"Nordrhein-Westfalen",
    "wof:name":"Grosta Bau Gmbh",
    "wof:placetype":"venue"
},
  "geometry": {"coordinates":[6.8795981407,51.6832809448],"type":"Point"}
}