{
  "type": "Feature",
  "properties": {
    "iso:country":"DE",
    "sg:address":"Schnarrenbergstr. 33",
    "sg:city":"Winnenden",
    "sg:phone":"+49 7195/73362",
    "sg:postcode":"71364",
    "sg:province":"Baden-W\u00fcrttemberg",
    "wof:name":"F. Und M. Braun",
    "wof:placetype":"venue"
},
  "geometry": {"coordinates":[9.4310884476,48.8684425354],"type":"Point"}
}