{
  "type": "Feature",
  "properties": {
    "iso:country":"DE",
    "sg:address":"Schulplatz 5",
    "sg:city":"Krakow",
    "sg:postcode":"18292",
    "sg:province":"Mecklenburg-Vorpommern",
    "wof:name":"Gemeindeschwester Anni Reink",
    "wof:placetype":"venue"
},
  "geometry": {"coordinates":[12.26941,53.650021],"type":"Point"}
}