{
  "type": "Feature",
  "properties": {
    "iso:country":"DE",
    "sg:address":"H\u00fcl\u00dfestr. 1",
    "sg:city":"Dresden",
    "sg:phone":"+49 351/2845368",
    "sg:postcode":"01237",
    "sg:province":"Sachsen",
    "wof:name":"Rs Touristik Gmbh",
    "wof:placetype":"venue"
},
  "geometry": {"coordinates":[13.7910432816,51.0130004883],"type":"Point"}
}