{
  "type": "Feature",
  "properties": {
    "iso:country":"DE",
    "sg:address":"Im Eichengrund 21",
    "sg:city":"G\u00fctersloh",
    "sg:phone":"+49 5241/67532",
    "sg:postcode":"33334",
    "sg:province":"Nordrhein-Westfalen",
    "wof:name":"Syncotex Siegfried Rethage",
    "wof:placetype":"venue"
},
  "geometry": {"coordinates":[8.384173,51.959587],"type":"Point"}
}