{
  "type": "Feature",
  "properties": {
    "iso:country":"DE",
    "sg:address":"Bergstr.",
    "sg:city":"Nordenham",
    "sg:postcode":"26954",
    "sg:province":"Niedersachsen",
    "wof:name":"Mbb Messerschmid-b\u00f6lkow-blohm",
    "wof:placetype":"venue"
},
  "geometry": {"coordinates":[8.5160150528,53.5142288208],"type":"Point"}
}