{
  "type": "Feature",
  "properties": {
    "iso:country":"DE",
    "sg:address":"S\u00fcdhang 6",
    "sg:city":"Oslo\u00df",
    "sg:phone":"+49 5362/72384",
    "sg:postcode":"38557",
    "sg:province":"Niedersachsen",
    "wof:name":"W & B Haustechnik B\u00f6hlke E. K.",
    "wof:placetype":"venue"
},
  "geometry": {"coordinates":[10.6775970459,52.4703865051],"type":"Point"}
}