{
  "type": "Feature",
  "properties": {
    "iso:country":"DE",
    "sg:address":"Hegerfeldstr. 13",
    "sg:city":"Hausach",
    "sg:phone":"+49 7831/6146",
    "sg:postcode":"77756",
    "sg:province":"Baden-W\u00fcrttemberg",
    "wof:name":"K. Langenbacher Immobilienmakler",
    "wof:placetype":"venue"
},
  "geometry": {"coordinates":[8.1713409424,48.2865524292],"type":"Point"}
}