{
  "type": "Feature",
  "properties": {
    "iso:country":"DE",
    "sg:address":"Einkaufspark",
    "sg:city":"H\u00f6hn",
    "sg:postcode":"56462",
    "sg:province":"Rheinland-Pfalz",
    "wof:name":"Cinderella Cinderello E. K.",
    "wof:placetype":"venue"
},
  "geometry": {"coordinates":[7.98091,50.61797],"type":"Point"}
}