{
  "type": "Feature",
  "properties": {
    "iso:country":"DE",
    "sg:address":"Nesselrieder Str. 2",
    "sg:city":"Durbach",
    "sg:phone":"+49 781/42550",
    "sg:postcode":"77770",
    "sg:province":"Baden-W\u00fcrttemberg",
    "wof:name":"Ludwig Huber",
    "wof:placetype":"venue"
},
  "geometry": {"coordinates":[7.9870529175,48.5063285828],"type":"Point"}
}