{
  "type": "Feature",
  "properties": {
    "iso:country":"DE",
    "sg:address":"Neurott 30",
    "sg:city":"Plankstadt",
    "sg:postcode":"68723",
    "sg:province":"Baden-W\u00fcrttemberg",
    "wof:name":"Golfskulpturen",
    "wof:placetype":"venue"
},
  "geometry": {"coordinates":[8.586679,49.398903],"type":"Point"}
}