{
  "type": "Feature",
  "properties": {
    "iso:country":"DE",
    "sg:address":"Von-Coels-Str. 178",
    "sg:city":"Aachen",
    "sg:phone":"+49 241/551426",
    "sg:postcode":"52080",
    "sg:province":"Nordrhein-Westfalen",
    "wof:name":"Gertrud Laps",
    "wof:placetype":"venue"
},
  "geometry": {"coordinates":[6.1590561867,50.7775611877],"type":"Point"}
}