{
  "type": "Feature",
  "properties": {
    "iso:country":"DE",
    "sg:address":"Neinstedter Feldweg",
    "sg:city":"Quedlinburg",
    "sg:phone":"+49 3946/707549",
    "sg:postcode":"06484",
    "sg:province":"Sachsen-Anhalt",
    "wof:name":"Vomewa Vorrichtungsbau Und Metallwaren Gmbh",
    "wof:placetype":"venue"
},
  "geometry": {"coordinates":[11.1385202408,51.7777519226],"type":"Point"}
}