{
  "type": "Feature",
  "properties": {
    "iso:country":"DE",
    "sg:address":"Maria-Hilf-Str. 24",
    "sg:city":"Berching",
    "sg:phone":"+49 8462/905750",
    "sg:postcode":"92334",
    "sg:province":"Bayern",
    "wof:name":"Penny-markt Gmbh",
    "wof:placetype":"venue"
},
  "geometry": {"coordinates":[11.4440593719,49.1015357971],"type":"Point"}
}