{
  "type": "Feature",
  "properties": {
    "iso:country":"DE",
    "sg:address":"Beethovenstr. 11",
    "sg:city":"Tangerm\u00fcnde",
    "sg:phone":"+49 39322/3370",
    "sg:postcode":"39590",
    "sg:province":"Sachsen-Anhalt",
    "wof:name":"A. Beiermann Zahnarzt",
    "wof:placetype":"venue"
},
  "geometry": {"coordinates":[11.9600162506,52.5381202698],"type":"Point"}
}