{
  "type": "Feature",
  "properties": {
    "iso:country":"DE",
    "sg:address":"Auf der Windh\u00f6he 36",
    "sg:city":"Greiz",
    "sg:phone":"+49 3661/670922",
    "sg:postcode":"07973",
    "sg:province":"Th\u00fcringen",
    "wof:name":"Spedition Alekoglu",
    "wof:placetype":"venue"
},
  "geometry": {"coordinates":[12.1824016571,50.6392402649],"type":"Point"}
}