{
  "type": "Feature",
  "properties": {
    "iso:country":"DE",
    "sg:address":"Alter Markt 50",
    "sg:city":"M\u00f6nchengladbach",
    "sg:phone":"+49 2161/12171",
    "sg:postcode":"41061",
    "sg:province":"Nordrhein-Westfalen",
    "wof:name":"Marktbrunnen",
    "wof:placetype":"venue"
},
  "geometry": {"coordinates":[6.4317522049,51.1944084167],"type":"Point"}
}