{
  "type": "Feature",
  "properties": {
    "iso:country":"DE",
    "sg:address":"Hannoversche Str. 18 b",
    "sg:city":"Celle",
    "sg:phone":"+49 5141/214518",
    "sg:postcode":"29221",
    "sg:province":"Niedersachsen",
    "wof:name":"Klaus Seil",
    "wof:placetype":"venue"
},
  "geometry": {"coordinates":[10.077034,52.616802],"type":"Point"}
}