{
  "type": "Feature",
  "properties": {
    "iso:country":"DE",
    "sg:address":"Magdeburg-Leipziger-Str. 140",
    "sg:city":"F\u00f6rderstedt",
    "sg:phone":"+49 39266/337",
    "sg:postcode":"39443",
    "sg:province":"Sachsen-Anhalt",
    "wof:name":"S. Pl\u00fcmecke",
    "wof:placetype":"venue"
},
  "geometry": {"coordinates":[11.626074,51.904541],"type":"Point"}
}