{
  "type": "Feature",
  "properties": {
    "iso:country":"DE",
    "sg:address":"Hauptstr. 161-167",
    "sg:city":"Heiligenhaus",
    "sg:postcode":"42579",
    "sg:province":"Nordrhein-Westfalen",
    "wof:name":"P & S Optik Beteiligungs Gmbh",
    "wof:placetype":"venue"
},
  "geometry": {"coordinates":[6.970703,51.326481],"type":"Point"}
}