{
  "type": "Feature",
  "properties": {
    "iso:country":"DE",
    "sg:address":"Widenmayerstr. 47",
    "sg:city":"M\u00fcnchen",
    "sg:phone":"+49 89/2103760",
    "sg:postcode":"80538",
    "sg:province":"Bayern",
    "wof:name":"Generalkonsulat Der F\u00f6rderativen Republik",
    "wof:placetype":"venue"
},
  "geometry": {"coordinates":[11.5960922241,48.1485481262],"type":"Point"}
}