{
  "type": "Feature",
  "properties": {
    "iso:country":"DE",
    "sg:address":"Bankstr. 16",
    "sg:city":"D\u00fcsseldorf",
    "sg:phone":"+49 211/4920285",
    "sg:postcode":"40476",
    "sg:province":"Nordrhein-Westfalen",
    "wof:name":"H. Schneider Steuerberater",
    "wof:placetype":"venue"
},
  "geometry": {"coordinates":[6.7744870186,51.243057251],"type":"Point"}
}