{
  "type": "Feature",
  "properties": {
    "iso:country":"DE",
    "sg:address":"Kapellenstr. 35a",
    "sg:city":"Gersthofen",
    "sg:postcode":"86368",
    "sg:province":"Bayern",
    "wof:name":"Da Sofia Catering Gmbh",
    "wof:placetype":"venue"
},
  "geometry": {"coordinates":[10.880094,48.418797],"type":"Point"}
}