{
  "type": "Feature",
  "properties": {
    "iso:country":"DE",
    "sg:address":"Laberweg 2",
    "sg:city":"Oberammergau",
    "sg:phone":"+49 8822/3500",
    "sg:postcode":"82487",
    "sg:province":"Bayern",
    "wof:name":"Fremdenheim Karl Baur",
    "wof:placetype":"venue"
},
  "geometry": {"coordinates":[11.0695648193,47.5939750671],"type":"Point"}
}