{
  "type": "Feature",
  "properties": {
    "iso:country":"DE",
    "sg:address":"Marktstr. 32",
    "sg:city":"Trochtelfingen",
    "sg:phone":"+49 7124/932167",
    "sg:postcode":"72818",
    "sg:province":"Baden-W\u00fcrttemberg",
    "wof:name":"Regenbogen Imbiss 3",
    "wof:placetype":"venue"
},
  "geometry": {"coordinates":[9.2445831299,48.307964325],"type":"Point"}
}