{
  "type": "Feature",
  "properties": {
    "iso:country":"DE",
    "sg:address":"Luitpoldstr. 180",
    "sg:city":"Neuburg",
    "sg:phone":"+49 8431/7575",
    "sg:postcode":"86633",
    "sg:province":"Bayern",
    "wof:name":"Taxiring",
    "wof:placetype":"venue"
},
  "geometry": {"coordinates":[11.180472374,48.735294342],"type":"Point"}
}