{
  "type": "Feature",
  "properties": {
    "iso:country":"DE",
    "sg:address":"Barteldesplatz 2",
    "sg:city":"Dresden",
    "sg:postcode":"01309",
    "sg:province":"Sachsen",
    "wof:name":"K\u00f6rber-stiftung Dresden Winfried Ripp",
    "wof:placetype":"venue"
},
  "geometry": {"coordinates":[13.8036365509,51.0538711548],"type":"Point"}
}