{
  "type": "Feature",
  "properties": {
    "iso:country":"DE",
    "sg:address":"Obergasse 5",
    "sg:city":"Lindenfels",
    "sg:phone":"+49 6255",
    "sg:postcode":"64678",
    "sg:province":"Hessen",
    "wof:name":"B\u00fccher Flohmarkt - Internetflohmarkt.com",
    "wof:placetype":"venue"
},
  "geometry": {"coordinates":[8.740342,49.687973],"type":"Point"}
}