{
  "type": "Feature",
  "properties": {
    "iso:country":"DE",
    "sg:address":"Breitscheidstr. 51",
    "sg:city":"Magdeburg",
    "sg:postcode":"39114",
    "sg:province":"Sachsen-Anhalt",
    "wof:name":"Vivotec Biomedical Technologies Gmbh",
    "wof:placetype":"venue"
},
  "geometry": {"coordinates":[11.6864671707,52.142124176],"type":"Point"}
}