{
  "type": "Feature",
  "properties": {
    "iso:country":"DE",
    "sg:address":"Irisstr. 28",
    "sg:city":"Eriskirch",
    "sg:phone":"+49 7541/82313",
    "sg:postcode":"88097",
    "sg:province":"Baden-W\u00fcrttemberg",
    "wof:name":"Marys Bistro",
    "wof:placetype":"venue"
},
  "geometry": {"coordinates":[9.5271987915,47.6316146851],"type":"Point"}
}