{
  "type": "Feature",
  "properties": {
    "iso:country":"DE",
    "sg:address":"Leiferder Weg 8",
    "sg:city":"Wolfenb\u00fcttel",
    "sg:phone":"+49 5331/92040",
    "sg:postcode":"38304",
    "sg:province":"Niedersachsen",
    "wof:name":"Stefan Haar Architekt",
    "wof:placetype":"venue"
},
  "geometry": {"coordinates":[10.517018,52.175507],"type":"Point"}
}