{
  "type": "Feature",
  "properties": {
    "iso:country":"DE",
    "sg:address":"Herolder Str. 25",
    "sg:city":"Ehrenfriedersdorf",
    "sg:phone":"+49 37341/7356",
    "sg:postcode":"09427",
    "sg:province":"Sachsen",
    "wof:name":"Gb Greifenstein Bau Gmbh",
    "wof:placetype":"venue"
},
  "geometry": {"coordinates":[12.9691610336,50.6682510376],"type":"Point"}
}