{
  "type": "Feature",
  "properties": {
    "iso:country":"DE",
    "sg:address":"Barf\u00fc\u00dferkloster 1",
    "sg:city":"Osnabr\u00fcck",
    "sg:phone":"+49 541/29115",
    "sg:postcode":"49074",
    "sg:province":"Niedersachsen",
    "wof:name":"Boutique Dagmar",
    "wof:placetype":"venue"
},
  "geometry": {"coordinates":[8.042782,52.273361],"type":"Point"}
}