{
  "type": "Feature",
  "properties": {
    "iso:country":"DE",
    "sg:address":"Heintzmannsheide 56",
    "sg:city":"Bochum",
    "sg:phone":"+49 234/9489394",
    "sg:postcode":"44797",
    "sg:province":"Nordrhein-Westfalen",
    "wof:name":"Uwe Droste Ingenieur",
    "wof:placetype":"venue"
},
  "geometry": {"coordinates":[7.2221159935,51.4383354187],"type":"Point"}
}