{
  "type": "Feature",
  "properties": {
    "iso:country":"DE",
    "sg:address":"Dornberg 39",
    "sg:city":"Ansbach",
    "sg:postcode":"91522",
    "sg:province":"Bayern",
    "wof:name":"Db Design- Beratungs-gmbh",
    "wof:placetype":"venue"
},
  "geometry": {"coordinates":[10.4988946915,49.3084373474],"type":"Point"}
}