{
  "type": "Feature",
  "properties": {
    "iso:country":"DE",
    "sg:address":"Klosterstr. 6",
    "sg:city":"Bad K\u00f6nigshofen",
    "sg:phone":"+49 9761/6351",
    "sg:postcode":"97631",
    "sg:province":"Bayern",
    "wof:name":"Omnibus-reiseunternehmen Schroer Gmbh",
    "wof:placetype":"venue"
},
  "geometry": {"coordinates":[10.4689311981,50.2991714478],"type":"Point"}
}