{
  "type": "Feature",
  "properties": {
    "iso:country":"DE",
    "sg:address":"Glaubitzer Str. 10",
    "sg:city":"N\u00fcnchritz",
    "sg:phone":"+49 35265/54258",
    "sg:postcode":"01612",
    "sg:province":"Sachsen",
    "wof:name":"Rats-apotheke",
    "wof:placetype":"venue"
},
  "geometry": {"coordinates":[13.385006,51.303272],"type":"Point"}
}