{
  "type": "Feature",
  "properties": {
    "iso:country":"DE",
    "sg:address":"Wormser Str. 3",
    "sg:city":"Br\u00fchl",
    "sg:phone":"+49 6202/780065",
    "sg:postcode":"68782",
    "sg:province":"Baden-W\u00fcrttemberg",
    "wof:name":"Hts Hair-traders Gmbh Far-east-agents",
    "wof:placetype":"venue"
},
  "geometry": {"coordinates":[8.528321,49.406887],"type":"Point"}
}