{
  "type": "Feature",
  "properties": {
    "iso:country":"DE",
    "sg:address":"Scheffelstr. 17",
    "sg:city":"Singen",
    "sg:phone":"+49 7731/83030",
    "sg:postcode":"78224",
    "sg:province":"Baden-W\u00fcrttemberg",
    "wof:name":"Manfred Kuhn Steuerberater",
    "wof:placetype":"venue"
},
  "geometry": {"coordinates":[8.8369340897,47.7593574524],"type":"Point"}
}