{
  "type": "Feature",
  "properties": {
    "iso:country":"DE",
    "sg:address":"Werner-von-Siemens-Strasse 15",
    "sg:city":"Kaltenkirchen",
    "sg:phone":"+49 4191/50250",
    "sg:postcode":"24568",
    "sg:province":"Schleswig-Holstein",
    "wof:name":"Spirit Caraudio Speaker And Amplifier",
    "wof:placetype":"venue"
},
  "geometry": {"coordinates":[9.973509,53.822876],"type":"Point"}
}