{
  "type": "Feature",
  "properties": {
    "iso:country":"DE",
    "sg:address":"Hansastr. 34",
    "sg:city":"Oberhausen",
    "sg:phone":"+49 208/200387",
    "sg:postcode":"46049",
    "sg:province":"Nordrhein-Westfalen",
    "wof:name":"Franz An Haack Eisenwaren",
    "wof:placetype":"venue"
},
  "geometry": {"coordinates":[6.851299,51.476921],"type":"Point"}
}