{
  "type": "Feature",
  "properties": {
    "iso:country":"DE",
    "sg:address":"Feldstr. 29",
    "sg:city":"Porta Westfalica",
    "sg:phone":"+49 571/52808",
    "sg:postcode":"32457",
    "sg:province":"Nordrhein-Westfalen",
    "wof:name":"Teppich Land Gmbh",
    "wof:placetype":"venue"
},
  "geometry": {"coordinates":[8.9033813477,52.2602767944],"type":"Point"}
}