{
  "type": "Feature",
  "properties": {
    "iso:country":"DE",
    "sg:address":"Eibauer Str. 1-5",
    "sg:city":"Neugersdorf",
    "sg:phone":"+49 3586/7110",
    "sg:postcode":"02727",
    "sg:province":"Sachsen",
    "wof:name":"Oka-b\u00fcrom\u00f6bel Herstellung Und Vertrieb Gmbh",
    "wof:placetype":"venue"
},
  "geometry": {"coordinates":[14.626943,50.981411],"type":"Point"}
}