{
  "type": "Feature",
  "properties": {
    "iso:country":"DE",
    "sg:address":"Hauptstr. 30",
    "sg:city":"Neuenkirchen",
    "sg:phone":"+49 5973/3508",
    "sg:postcode":"48485",
    "sg:province":"Nordrhein-Westfalen",
    "wof:name":"Ewald Twehues",
    "wof:placetype":"venue"
},
  "geometry": {"coordinates":[7.3718490601,52.2443008423],"type":"Point"}
}