{
  "type": "Feature",
  "properties": {
    "iso:country":"DE",
    "sg:address":"Dillmannstr. 19",
    "sg:city":"Stuttgart",
    "sg:phone":"+49 711/2269066",
    "sg:postcode":"70193",
    "sg:province":"Baden-W\u00fcrttemberg",
    "wof:name":"Sanavita Gmbh",
    "wof:placetype":"venue"
},
  "geometry": {"coordinates":[9.15824,48.784519],"type":"Point"}
}