{
  "type": "Feature",
  "properties": {
    "iso:country":"DE",
    "sg:address":"Hangstr. 42",
    "sg:city":"Hofheim",
    "sg:postcode":"97461",
    "sg:province":"Bayern",
    "wof:name":"Kocher E. K.",
    "wof:placetype":"venue"
},
  "geometry": {"coordinates":[10.52237,50.137142],"type":"Point"}
}