{
  "type": "Feature",
  "properties": {
    "iso:country":"DE",
    "sg:address":"Osloweg 2",
    "sg:city":"Ellerau",
    "sg:phone":"+49 4106/773379",
    "sg:postcode":"25479",
    "sg:province":"Schleswig-Holstein",
    "wof:name":"Holger Leisner",
    "wof:placetype":"venue"
},
  "geometry": {"coordinates":[9.925078392,53.7529296875],"type":"Point"}
}