{
  "type": "Feature",
  "properties": {
    "iso:country":"DE",
    "sg:address":"Bahnhofstr. 35",
    "sg:city":"Breisach",
    "sg:phone":"+49 4976/679070",
    "sg:postcode":"79206",
    "sg:province":"Baden-W\u00fcrttemberg",
    "wof:name":"Badenova Ag & Co. Kg",
    "wof:placetype":"venue"
},
  "geometry": {"coordinates":[7.593994,48.029972],"type":"Point"}
}