{
  "type": "Feature",
  "properties": {
    "iso:country":"DE",
    "sg:address":"\u00d6sterfeldstr. 32",
    "sg:city":"Stuttgart",
    "sg:phone":"+49 711/732921",
    "sg:postcode":"70563",
    "sg:province":"Baden-W\u00fcrttemberg",
    "wof:name":"Pauline Mezger",
    "wof:placetype":"venue"
},
  "geometry": {"coordinates":[9.11176,48.73357],"type":"Point"}
}