{
  "type": "Feature",
  "properties": {
    "iso:country":"DE",
    "sg:address":"Irisstr. 45",
    "sg:city":"Eriskirch",
    "sg:phone":"+49 7541/81362",
    "sg:postcode":"88097",
    "sg:province":"Baden-W\u00fcrttemberg",
    "wof:name":"Hansmann & Becker",
    "wof:placetype":"venue"
},
  "geometry": {"coordinates":[9.526284,47.632622],"type":"Point"}
}