{
  "type": "Feature",
  "properties": {
    "iso:country":"DE",
    "sg:address":"R\u00f6vkampallee 37",
    "sg:city":"Malente",
    "sg:phone":"+49 4523/6455",
    "sg:postcode":"23714",
    "sg:province":"Schleswig-Holstein",
    "wof:name":"Bouman",
    "wof:placetype":"venue"
},
  "geometry": {"coordinates":[10.6065101624,54.184047699],"type":"Point"}
}