{
  "type": "Feature",
  "properties": {
    "iso:country":"DE",
    "sg:address":"Adelheid-Steinmann-Str. 4",
    "sg:city":"Freiburg",
    "sg:phone":"+49 761/4765450",
    "sg:postcode":"79111",
    "sg:province":"Baden-W\u00fcrttemberg",
    "wof:name":"Wohnungsgenossenschaft Stadt Und Frau Eg",
    "wof:placetype":"venue"
},
  "geometry": {"coordinates":[7.80560112,47.979347229],"type":"Point"}
}