{
  "type": "Feature",
  "properties": {
    "iso:country":"DE",
    "sg:address":"Dresdner Str. 2",
    "sg:city":"Wilsdruff",
    "sg:phone":"+49 35204/47066",
    "sg:postcode":"01723",
    "sg:province":"Sachsen",
    "wof:name":"F. Dilck",
    "wof:placetype":"venue"
},
  "geometry": {"coordinates":[13.537946,51.052013],"type":"Point"}
}