{
  "type": "Feature",
  "properties": {
    "iso:country":"DE",
    "sg:address":"Kuhstr. 25",
    "sg:city":"Braunschweig",
    "sg:phone":"+49 531/2512985",
    "sg:postcode":"38100",
    "sg:province":"Niedersachsen",
    "wof:name":"Seicon Projekt- Entwicklungs Gmbh",
    "wof:placetype":"venue"
},
  "geometry": {"coordinates":[10.5275220871,52.2602386475],"type":"Point"}
}