{
  "type": "Feature",
  "properties": {
    "iso:country":"DE",
    "sg:address":"Industriestr. 41",
    "sg:city":"Lienen",
    "sg:phone":"+49 5483/739880",
    "sg:postcode":"49536",
    "sg:province":"Nordrhein-Westfalen",
    "wof:name":"Img Modellbau Gmbh",
    "wof:placetype":"venue"
},
  "geometry": {"coordinates":[7.9837827682,52.1527862549],"type":"Point"}
}