{
  "type": "Feature",
  "properties": {
    "iso:country":"DE",
    "sg:address":"Altendorfer Str. 485",
    "sg:city":"Essen",
    "sg:phone":"+49 201/680107",
    "sg:postcode":"45355",
    "sg:province":"Nordrhein-Westfalen",
    "wof:name":"Heinz Wirtz Gmbh",
    "wof:placetype":"venue"
},
  "geometry": {"coordinates":[6.958803,51.462448],"type":"Point"}
}