{
  "type": "Feature",
  "properties": {
    "iso:country":"DE",
    "sg:address":"Lichtentaler Str. 35",
    "sg:city":"Baden-Baden",
    "sg:phone":"+49 7221/25203",
    "sg:postcode":"76530",
    "sg:province":"Baden-W\u00fcrttemberg",
    "wof:name":"Anny Schlesinger Offenbacher Lederwaren",
    "wof:placetype":"venue"
},
  "geometry": {"coordinates":[8.241333,48.758366],"type":"Point"}
}