{
  "type": "Feature",
  "properties": {
    "iso:country":"DE",
    "sg:address":"Holzm\u00fchle",
    "sg:city":"Rosenberg",
    "sg:phone":"+49 7967/1520",
    "sg:postcode":"73494",
    "sg:province":"Baden-W\u00fcrttemberg",
    "wof:name":"J. Rettenmaier & S\u00f6hne Gmbh & Co. Kg",
    "wof:placetype":"venue"
},
  "geometry": {"coordinates":[10.0615949631,49.0145378113],"type":"Point"}
}