{
  "type": "Feature",
  "properties": {
    "iso:country":"DE",
    "sg:address":"Gr\u00f6tzinger Str. 18",
    "sg:city":"Aichtal",
    "sg:phone":"+49 7127/50800",
    "sg:postcode":"72631",
    "sg:province":"Baden-W\u00fcrttemberg",
    "wof:name":"Klaus Gutbier Masseur",
    "wof:placetype":"venue"
},
  "geometry": {"coordinates":[9.241452,48.623981],"type":"Point"}
}