{
  "type": "Feature",
  "properties": {
    "iso:country":"DE",
    "sg:address":"Junkersstr. 30 - 38",
    "sg:city":"B\u00fcnde",
    "sg:phone":"+49 5223/96630",
    "sg:postcode":"32257",
    "sg:province":"Nordrhein-Westfalen",
    "wof:name":"Bkb Sportanlagen Verwaltungs Gmbh",
    "wof:placetype":"venue"
},
  "geometry": {"coordinates":[8.53457,52.197491],"type":"Point"}
}