{
  "type": "Feature",
  "properties": {
    "iso:country":"DE",
    "sg:address":"Frankenstr. 46",
    "sg:city":"Gangelt",
    "sg:phone":"+49 2454/92770",
    "sg:postcode":"52538",
    "sg:province":"Nordrhein-Westfalen",
    "wof:name":"Stahlbau Trepels Gmbh & Co. Kg",
    "wof:placetype":"venue"
},
  "geometry": {"coordinates":[6.009627,50.991352],"type":"Point"}
}