{
  "type": "Feature",
  "properties": {
    "iso:country":"DE",
    "sg:address":"Ro\u00dfmarkt 5",
    "sg:city":"Zeitz",
    "sg:phone":"+49 3441/217040",
    "sg:postcode":"06712",
    "sg:province":"Sachsen-Anhalt",
    "wof:name":"Spoon Silvana Und Steffen Peter Ohg",
    "wof:placetype":"venue"
},
  "geometry": {"coordinates":[12.1356334686,51.0501670837],"type":"Point"}
}