{
  "type": "Feature",
  "properties": {
    "iso:country":"DE",
    "sg:address":"Gr\u00fcnweg 21",
    "sg:city":"Wut\u00f6schingen",
    "sg:phone":"+49 7746/5684",
    "sg:postcode":"79793",
    "sg:province":"Baden-W\u00fcrttemberg",
    "wof:name":"Johann Landgraf Bildhauer",
    "wof:placetype":"venue"
},
  "geometry": {"coordinates":[8.35086,47.638512],"type":"Point"}
}