{
  "type": "Feature",
  "properties": {
    "iso:country":"DE",
    "sg:address":"Fabrikstrasse 26",
    "sg:city":"Sehmatal/Sehma",
    "sg:phone":"+49 3733/65186",
    "sg:postcode":"09465",
    "sg:province":"Sachsen",
    "wof:name":"Edv-pfob Computer B\u00fcrobedarf Webdesign",
    "wof:placetype":"venue"
},
  "geometry": {"coordinates":[12.996915,50.538635],"type":"Point"}
}