{
  "type": "Feature",
  "properties": {
    "iso:country":"DE",
    "sg:address":"Burgstr. 37",
    "sg:city":"Lindenfels",
    "sg:phone":"+49 6255/3139",
    "sg:postcode":"64678",
    "sg:province":"Hessen",
    "wof:name":"Siegfried H\u00f6pfner Masseur",
    "wof:placetype":"venue"
},
  "geometry": {"coordinates":[8.778023,49.683056],"type":"Point"}
}