{
  "type": "Feature",
  "properties": {
    "iso:country":"DE",
    "sg:address":"Holzgasse 24",
    "sg:city":"Bad M\u00fcnstereifel",
    "sg:phone":"+49 2253/3668",
    "sg:postcode":"53902",
    "sg:province":"Nordrhein-Westfalen",
    "wof:name":"R. Jansen",
    "wof:placetype":"venue"
},
  "geometry": {"coordinates":[6.792986,50.593601],"type":"Point"}
}