{
  "type": "Feature",
  "properties": {
    "iso:country":"DE",
    "sg:address":"Stallagsweg 180",
    "sg:city":"K\u00f6ln",
    "sg:phone":"+49 221/791570",
    "sg:postcode":"50767",
    "sg:province":"Nordrhein-Westfalen",
    "wof:name":"Felix Sch\u00f6nenborn Steuerberater",
    "wof:placetype":"venue"
},
  "geometry": {"coordinates":[6.9002537727,51.0128211975],"type":"Point"}
}