{
  "type": "Feature",
  "properties": {
    "iso:country":"DE",
    "sg:address":"Im Gro\u00dfenbruch 71",
    "sg:city":"Spiesen-Elversberg",
    "sg:phone":"+49 6821/72453",
    "sg:postcode":"66583",
    "sg:province":"Saarland",
    "wof:name":"Harald Mayer",
    "wof:placetype":"venue"
},
  "geometry": {"coordinates":[7.142848,49.320168],"type":"Point"}
}