{
  "type": "Feature",
  "properties": {
    "iso:country":"DE",
    "sg:address":"Solitudestr. 191",
    "sg:city":"Stuttgart",
    "sg:postcode":"70499",
    "sg:province":"Baden-W\u00fcrttemberg",
    "wof:name":"Wohnbau Solitude Kg",
    "wof:placetype":"venue"
},
  "geometry": {"coordinates":[9.109635,48.811939],"type":"Point"}
}