{
  "type": "Feature",
  "properties": {
    "iso:country":"DE",
    "sg:address":"Bachstr. 10 a",
    "sg:city":"Plattling",
    "sg:phone":"+49 9931/71777",
    "sg:postcode":"94447",
    "sg:province":"Bayern",
    "wof:name":"Gastst\u00e4tte Zum Dorfkurg",
    "wof:placetype":"venue"
},
  "geometry": {"coordinates":[12.8646068573,48.7663459778],"type":"Point"}
}