{
  "type": "Feature",
  "properties": {
    "iso:country":"DE",
    "sg:address":"Zeppelinstr. 1",
    "sg:city":"Waltersdorf",
    "sg:phone":"+49 33762/68420",
    "sg:postcode":"15732",
    "sg:province":"Brandenburg",
    "wof:name":"Geo-planbau-dresden Ges. F\u00fcr Planung Beratung Und",
    "wof:placetype":"venue"
},
  "geometry": {"coordinates":[13.59704,52.357361],"type":"Point"}
}