{
  "type": "Feature",
  "properties": {
    "iso:country":"DE",
    "sg:address":"Niendorfer Weg 11",
    "sg:city":"Hamburg",
    "sg:phone":"+49 40/5530010",
    "sg:postcode":"22453",
    "sg:province":"Hamburg",
    "wof:name":"Samex Gesellschaft F\u00fcr Handel Und Werbung Mbh",
    "wof:placetype":"venue"
},
  "geometry": {"coordinates":[9.9577493668,53.6249008179],"type":"Point"}
}