{
  "type": "Feature",
  "properties": {
    "iso:country":"DE",
    "sg:address":"Friedhofstr. 211",
    "sg:city":"Gro\u00df Schierstedt",
    "sg:phone":"+49 3473/813749",
    "sg:postcode":"06449",
    "sg:province":"Sachsen-Anhalt",
    "wof:name":"B-g-m Bauger\u00e4te- Mietservice Gmbh",
    "wof:placetype":"venue"
},
  "geometry": {"coordinates":[11.5199890137,51.7458877563],"type":"Point"}
}