{
  "type": "Feature",
  "properties": {
    "iso:country":"DE",
    "sg:address":"Dorfstr. 2",
    "sg:city":"Westerau",
    "sg:phone":"+49 4539/181616",
    "sg:postcode":"23847",
    "sg:province":"Schleswig-Holstein",
    "wof:name":"Check Diagnostics Gesellschaft F\u00fcr Point-of-care Testing Mbh",
    "wof:placetype":"venue"
},
  "geometry": {"coordinates":[10.4925603867,53.7791213989],"type":"Point"}
}