{
  "type": "Feature",
  "properties": {
    "iso:country":"DE",
    "sg:address":"Am Margretenberg 3",
    "sg:city":"Petersberg",
    "sg:phone":"+49 661/606080",
    "sg:postcode":"36100",
    "sg:province":"Hessen",
    "wof:name":"C. Burg Immobilienmakler",
    "wof:placetype":"venue"
},
  "geometry": {"coordinates":[9.768494606,50.5662689209],"type":"Point"}
}