{
  "type": "Feature",
  "properties": {
    "iso:country":"DE",
    "sg:address":"Sattlerstr. 5",
    "sg:city":"L\u00fcbeck",
    "sg:phone":"+49 4922/0295340",
    "sg:postcode":"23556",
    "sg:province":"Schleswig-Holstein",
    "wof:name":"Adels-contact Elektrotechnische Fabrik Gmbh & Co. Kg",
    "wof:placetype":"venue"
},
  "geometry": {"coordinates":[7.112485,50.986862],"type":"Point"}
}