{
  "type": "Feature",
  "properties": {
    "iso:country":"DE",
    "sg:address":"Sandstr. 130",
    "sg:city":"Bergheim",
    "sg:phone":"+49 2271/92974",
    "sg:postcode":"50127",
    "sg:province":"Nordrhein-Westfalen",
    "wof:name":"Elisabeth Kleinagel",
    "wof:placetype":"venue"
},
  "geometry": {"coordinates":[6.689699173,50.9323959351],"type":"Point"}
}