{
  "type": "Feature",
  "properties": {
    "iso:country":"DE",
    "sg:address":"Schubartstr. 18",
    "sg:city":"Schw\u00e4bisch Gm\u00fcnd",
    "sg:phone":"+49 7171/949116",
    "sg:postcode":"73529",
    "sg:province":"Baden-W\u00fcrttemberg",
    "wof:name":"Anton Ummenhofer Ingenieur",
    "wof:placetype":"venue"
},
  "geometry": {"coordinates":[9.7958211899,48.7481918335],"type":"Point"}
}