{
  "type": "Feature",
  "properties": {
    "iso:country":"DE",
    "sg:address":"Alter Postweg 6a",
    "sg:city":"Neu Kali\u00df",
    "sg:phone":"+49 38758/26706",
    "sg:postcode":"19294",
    "sg:province":"Mecklenburg-Vorpommern",
    "wof:name":"Bhe Bau Heiddorf Elde Gmbh",
    "wof:placetype":"venue"
},
  "geometry": {"coordinates":[11.298477,53.174175],"type":"Point"}
}