{
  "type": "Feature",
  "properties": {
    "iso:country":"DE",
    "sg:address":"Amselweg 100",
    "sg:city":"Wiesmoor",
    "sg:phone":"+49 4944/7038",
    "sg:postcode":"26639",
    "sg:province":"Niedersachsen",
    "wof:name":"Karl Bu\u00df",
    "wof:placetype":"venue"
},
  "geometry": {"coordinates":[7.760351,53.412533],"type":"Point"}
}