{
  "type": "Feature",
  "properties": {
    "iso:country":"DE",
    "sg:address":"Remsgartenstr 23",
    "sg:city":"Waiblingen",
    "sg:phone":"+49 7151/939690",
    "sg:postcode":"71334",
    "sg:province":"Baden-W\u00fcrttemberg",
    "wof:name":"Rau Kunststoff Gmbh",
    "wof:placetype":"venue"
},
  "geometry": {"coordinates":[9.3458471298,48.8220710754],"type":"Point"}
}