{
  "type": "Feature",
  "properties": {
    "iso:country":"DE",
    "sg:address":"Tulpenstieg 4",
    "sg:city":"Norderstedt",
    "sg:phone":"+49 40/5252101",
    "sg:postcode":"22850",
    "sg:province":"Schleswig-Holstein",
    "wof:name":"Natur Und Umwelt Bildarchiv- Redaktionsb\u00fcro De Cuveland",
    "wof:placetype":"venue"
},
  "geometry": {"coordinates":[9.9956979752,53.6887512207],"type":"Point"}
}