{
  "type": "Feature",
  "properties": {
    "iso:country":"DE",
    "sg:address":"Rosenheimer Str. 100",
    "sg:city":"Brannenburg",
    "sg:phone":"+49 8034/99803",
    "sg:postcode":"83098",
    "sg:province":"Bayern",
    "wof:name":"Itns Gmbh",
    "wof:placetype":"venue"
},
  "geometry": {"coordinates":[12.1030902863,47.7415885925],"type":"Point"}
}