{
  "type": "Feature",
  "properties": {
    "iso:country":"DE",
    "sg:address":"Gustav-Adolf-Str. 17",
    "sg:city":"\u00dcchtelhausen",
    "sg:phone":"+49 9720/526",
    "sg:postcode":"97532",
    "sg:province":"Bayern",
    "wof:name":"Weinstube Madenh\u00e4uschen",
    "wof:placetype":"venue"
},
  "geometry": {"coordinates":[10.2989187241,50.1353492737],"type":"Point"}
}