{
  "type": "Feature",
  "properties": {
    "iso:country":"DE",
    "sg:address":"Pachtergasse 3",
    "sg:city":"Waldenburg",
    "sg:phone":"+49 37608/22868",
    "sg:postcode":"08396",
    "sg:province":"Sachsen",
    "wof:name":"W. Brehmer",
    "wof:placetype":"venue"
},
  "geometry": {"coordinates":[12.6037197113,50.8749198914],"type":"Point"}
}