{
  "type": "Feature",
  "properties": {
    "iso:country":"DE",
    "sg:address":"Lipaer Str. 19",
    "sg:city":"Berlin",
    "sg:phone":"+49 30/84412952",
    "sg:postcode":"12203",
    "sg:province":"Berlin",
    "wof:name":"Elan Woman Pur Frauen Fitness Ag",
    "wof:placetype":"venue"
},
  "geometry": {"coordinates":[13.311988,52.446991],"type":"Point"}
}