{
  "type": "Feature",
  "properties": {
    "iso:country":"DE",
    "sg:address":"Jether Str.",
    "sg:city":"Simmersdorf",
    "sg:phone":"+49 35695/7206",
    "sg:postcode":"03149",
    "sg:province":"Brandenburg",
    "wof:name":"H & H Karosseriefachbetrieb Gmbh",
    "wof:placetype":"venue"
},
  "geometry": {"coordinates":[14.60224,51.690617],"type":"Point"}
}