{
  "type": "Feature",
  "properties": {
    "iso:country":"DE",
    "sg:address":"Budapester Str. 1::",
    "sg:city":"Berlin",
    "sg:phone":"+49 4930/259990",
    "sg:postcode":"10787",
    "sg:province":"Berlin",
    "wof:name":"Berlin Hannoverse Hypotheken Bank Ag",
    "wof:placetype":"venue"
},
  "geometry": {"coordinates":[13.347767,52.506874],"type":"Point"}
}