{
  "type": "Feature",
  "properties": {
    "iso:country":"DE",
    "sg:address":"Frankfurter Str. 71",
    "sg:city":"Weilburg",
    "sg:phone":"+49 6471/7961",
    "sg:postcode":"35781",
    "sg:province":"Hessen",
    "wof:name":"Simon",
    "wof:placetype":"venue"
},
  "geometry": {"coordinates":[8.288637,50.482662],"type":"Point"}
}