{
  "type": "Feature",
  "properties": {
    "iso:country":"DE",
    "sg:address":"Hintere Str. 22",
    "sg:city":"Ellhofen",
    "sg:phone":"+49 7134/10110",
    "sg:postcode":"74248",
    "sg:province":"Baden-W\u00fcrttemberg",
    "wof:name":"Pre\u00dfler Gmbh",
    "wof:placetype":"venue"
},
  "geometry": {"coordinates":[9.320188,49.146698],"type":"Point"}
}