{
  "type": "Feature",
  "properties": {
    "iso:country":"DE",
    "sg:address":"Waldseiter Str. 93",
    "sg:city":"Bad Bentheim",
    "sg:phone":"+49 5924/428",
    "sg:postcode":"48455",
    "sg:province":"Niedersachsen",
    "wof:name":"Friedrich Huth",
    "wof:placetype":"venue"
},
  "geometry": {"coordinates":[7.1163601875,52.3062896729],"type":"Point"}
}