{
  "type": "Feature",
  "properties": {
    "iso:country":"DE",
    "sg:address":"Daimlerstr. 3/2",
    "sg:city":"Bietigheim-Bissingen",
    "sg:phone":"+49 7142/33253",
    "sg:postcode":"74321",
    "sg:province":"Baden-W\u00fcrttemberg",
    "wof:name":"Skandal Modevertriebs- Und Marketing-gmbh",
    "wof:placetype":"venue"
},
  "geometry": {"coordinates":[9.127979,48.941803],"type":"Point"}
}