{
  "type": "Feature",
  "properties": {
    "iso:country":"DE",
    "sg:city":"Windbergen",
    "sg:phone":"+49 4859/327",
    "sg:postcode":"25729",
    "sg:province":"Schleswig-Holstein",
    "wof:name":"Post Gmbh B\u00e4ckerei",
    "wof:placetype":"venue"
},
  "geometry": {"coordinates":[9.118238,54.045189],"type":"Point"}
}