{
  "type": "Feature",
  "properties": {
    "iso:country":"DE",
    "sg:address":"Eisenbahnstr. 17",
    "sg:city":"Homburg",
    "sg:phone":"+49 4968/4163619",
    "sg:postcode":"66424",
    "sg:province":"Saarland",
    "wof:name":"Canape Kunstgewerbe+ Wohnaccessoires Gmbh",
    "wof:placetype":"venue"
},
  "geometry": {"coordinates":[7.3408198357,49.3231277466],"type":"Point"}
}