{
  "type": "Feature",
  "properties": {
    "iso:country":"DE",
    "sg:address":"Hauptstr. 3",
    "sg:city":"Rothenbuch",
    "sg:phone":"+49 4960/941397",
    "sg:postcode":"63860",
    "sg:province":"Bayern",
    "wof:name":"Sparkasse Aschaffenburg-alzenau",
    "wof:placetype":"venue"
},
  "geometry": {"coordinates":[9.397013,49.966846],"type":"Point"}
}