{
  "type": "Feature",
  "properties": {
    "iso:country":"DE",
    "sg:address":"Landwehrstr. 21",
    "sg:city":"Bergkamen",
    "sg:phone":"+49 2307/86615",
    "sg:postcode":"59192",
    "sg:province":"Nordrhein-Westfalen",
    "wof:name":"Rhodos Grill",
    "wof:placetype":"venue"
},
  "geometry": {"coordinates":[7.6353287697,51.6140632629],"type":"Point"}
}