{
  "type": "Feature",
  "properties": {
    "iso:country":"DE",
    "sg:address":"Hamm-Weg",
    "sg:city":"Weesby",
    "sg:postcode":"24994",
    "sg:province":"Schleswig-Holstein",
    "wof:name":"Video Poker Classic",
    "wof:placetype":"venue"
},
  "geometry": {"coordinates":[9.151496,54.830791],"type":"Point"}
}