{
  "type": "Feature",
  "properties": {
    "iso:country":"DE",
    "sg:address":"Lerchenstra\u00dfe 9",
    "sg:city":"Bremen",
    "sg:phone":"+49 421/9883190",
    "sg:postcode":"28755",
    "sg:province":"Bremen",
    "wof:name":"Thalcida`s",
    "wof:placetype":"venue"
},
  "geometry": {"coordinates":[8.63152,53.19199],"type":"Point"}
}