{
  "type": "Feature",
  "properties": {
    "iso:country":"DE",
    "sg:address":"Heinrichstr. 55",
    "sg:city":"M\u00fclheim",
    "sg:phone":"+49 208/438950",
    "sg:postcode":"45470",
    "sg:province":"Nordrhein-Westfalen",
    "wof:name":"Bannik Moden",
    "wof:placetype":"venue"
},
  "geometry": {"coordinates":[6.909458,51.437073],"type":"Point"}
}