{
  "type": "Feature",
  "properties": {
    "iso:country":"DE",
    "sg:address":"Murrhardter Str. 2",
    "sg:city":"Sulzbach",
    "sg:phone":"+49 7193/6967",
    "sg:postcode":"71560",
    "sg:province":"Baden-W\u00fcrttemberg",
    "wof:name":"L\u00f6wen-apotheke Inh. Dr. Klaus Weyrich E. K.",
    "wof:placetype":"venue"
},
  "geometry": {"coordinates":[9.502295,49.002777],"type":"Point"}
}