{
  "type": "Feature",
  "properties": {
    "iso:country":"DE",
    "sg:address":"Lutherstr. 4",
    "sg:city":"Merseburg",
    "sg:postcode":"06217",
    "sg:province":"Sachsen-Anhalt",
    "wof:name":"Ingeborg Kentsch",
    "wof:placetype":"venue"
},
  "geometry": {"coordinates":[11.989961,51.362877],"type":"Point"}
}