{
  "type": "Feature",
  "properties": {
    "iso:country":"DE",
    "sg:address":"Sch\u00fctzenstr. 3",
    "sg:city":"Gundelsheim",
    "sg:phone":"+49 6269/385",
    "sg:postcode":"74831",
    "sg:province":"Baden-W\u00fcrttemberg",
    "wof:name":"Gebhard Schad",
    "wof:placetype":"venue"
},
  "geometry": {"coordinates":[9.1674489975,49.2809753418],"type":"Point"}
}