{
  "type": "Feature",
  "properties": {
    "iso:country":"DE",
    "sg:address":"Mittenwalder Str. 17",
    "sg:city":"Kochel am See",
    "sg:phone":"+49 8851/614614",
    "sg:postcode":"82431",
    "sg:province":"Bayern",
    "wof:name":"Gleitschirmschule Aerogen Klaus Brandl",
    "wof:placetype":"venue"
},
  "geometry": {"coordinates":[11.3654432297,47.6563072205],"type":"Point"}
}