{
  "type": "Feature",
  "properties": {
    "iso:country":"DE",
    "sg:address":"Tietmecker Weg 1",
    "sg:city":"L\u00fcdenscheid",
    "sg:phone":"+49 2351/9950",
    "sg:postcode":"58513",
    "sg:province":"Nordrhein-Westfalen",
    "wof:name":"Adolf Seuster Gmbh & Co. Kg",
    "wof:placetype":"venue"
},
  "geometry": {"coordinates":[7.618364,51.245106],"type":"Point"}
}