{
  "type": "Feature",
  "properties": {
    "iso:country":"DE",
    "sg:address":"Elisabethstr. 6",
    "sg:city":"Neuwied",
    "sg:phone":"+49 4963/227980",
    "sg:postcode":"56564",
    "sg:province":"Rheinland-Pfalz",
    "wof:name":"Rhein-plast Gmbh",
    "wof:placetype":"venue"
},
  "geometry": {"coordinates":[8.1719913483,49.4621086121],"type":"Point"}
}