{
  "type": "Feature",
  "properties": {
    "iso:country":"DE",
    "sg:address":"Memminger Str. 64",
    "sg:city":"Leutkirch",
    "sg:phone":"+49 7561/3666",
    "sg:postcode":"88299",
    "sg:province":"Baden-W\u00fcrttemberg",
    "wof:name":"Aral",
    "wof:placetype":"venue"
},
  "geometry": {"coordinates":[10.0196380615,47.8331947327],"type":"Point"}
}