{
  "type": "Feature",
  "properties": {
    "iso:country":"DE",
    "sg:address":"Hauptstr. 43",
    "sg:city":"Eich",
    "sg:postcode":"67575",
    "sg:province":"Rheinland-Pfalz",
    "wof:name":"Evangelisches Dekanat Osthofen",
    "wof:placetype":"venue"
},
  "geometry": {"coordinates":[8.4042901993,49.74974823],"type":"Point"}
}