{
  "type": "Feature",
  "properties": {
    "iso:country":"DE",
    "sg:address":"Eichendorffstr. 19",
    "sg:city":"Gernsheim",
    "sg:phone":"+49 6258/3714",
    "sg:postcode":"64579",
    "sg:province":"Hessen",
    "wof:name":"W. Massholder",
    "wof:placetype":"venue"
},
  "geometry": {"coordinates":[8.4880256653,49.745716095],"type":"Point"}
}