{
  "type": "Feature",
  "properties": {
    "iso:country":"DE",
    "sg:address":"Alte Augsburger Str. 9",
    "sg:city":"Donauw\u00f6rth",
    "sg:phone":"+49 906/706780",
    "sg:postcode":"86609",
    "sg:province":"Bayern",
    "wof:name":"K\u00e4the Kruse-puppen Gmbh",
    "wof:placetype":"venue"
},
  "geometry": {"coordinates":[10.7862911224,48.7097511292],"type":"Point"}
}