{
  "type": "Feature",
  "properties": {
    "iso:country":"DE",
    "sg:address":"Fischerinsel 4-03/6",
    "sg:city":"Berlin",
    "sg:postcode":"10179",
    "sg:province":"Berlin",
    "wof:name":"Medicare-produkte Michael Baade E. K.",
    "wof:placetype":"venue"
},
  "geometry": {"coordinates":[13.407083,52.513283],"type":"Point"}
}