{
  "type": "Feature",
  "properties": {
    "iso:country":"DE",
    "sg:address":"Leininger Ring 39",
    "sg:city":"Bockenheim",
    "sg:phone":"+49 6359/4139",
    "sg:postcode":"67278",
    "sg:province":"Rheinland-Pfalz",
    "wof:name":"Edgar Brehm Weinanbau",
    "wof:placetype":"venue"
},
  "geometry": {"coordinates":[8.1859741211,49.6047782898],"type":"Point"}
}