{
  "type": "Feature",
  "properties": {
    "iso:country":"DE",
    "sg:address":"Westring 23",
    "sg:city":"Bochum",
    "sg:phone":"+49 234/961370",
    "sg:postcode":"44787",
    "sg:province":"Nordrhein-Westfalen",
    "wof:name":"Jersch Und Kollegen Rechtsanw\u00e4lte",
    "wof:placetype":"venue"
},
  "geometry": {"coordinates":[7.2127690315,51.4810218811],"type":"Point"}
}