{
  "type": "Feature",
  "properties": {
    "iso:country":"DE",
    "sg:address":"Lindenstr. 26",
    "sg:city":"Ennepetal",
    "sg:phone":"+49 2333/3161",
    "sg:postcode":"58256",
    "sg:province":"Nordrhein-Westfalen",
    "wof:name":"Frank Weber",
    "wof:placetype":"venue"
},
  "geometry": {"coordinates":[7.3867659569,51.3072738647],"type":"Point"}
}