{
  "type": "Feature",
  "properties": {
    "iso:country":"DE",
    "sg:address":"Zevener Str. 7",
    "sg:city":"Schee\u00dfel",
    "sg:postcode":"27383",
    "sg:province":"Niedersachsen",
    "wof:name":"Extra",
    "wof:placetype":"venue"
},
  "geometry": {"coordinates":[9.4802389145,53.1691207886],"type":"Point"}
}