{
  "type": "Feature",
  "properties": {
    "iso:country":"DE",
    "sg:address":"Friedrichshafener Str. 16",
    "sg:city":"Brandenburg",
    "sg:phone":"+49 3381/717807",
    "sg:postcode":"14772",
    "sg:province":"Brandenburg",
    "wof:name":"Steinmetz Gmbh",
    "wof:placetype":"venue"
},
  "geometry": {"coordinates":[12.5061702728,52.438331604],"type":"Point"}
}