{
  "type": "Feature",
  "properties": {
    "iso:country":"DE",
    "sg:address":"Luxemburger Str. 269",
    "sg:city":"K\u00f6ln",
    "sg:phone":"+49 221/416963",
    "sg:postcode":"50939",
    "sg:province":"Nordrhein-Westfalen",
    "wof:name":"L. Wilden",
    "wof:placetype":"venue"
},
  "geometry": {"coordinates":[6.9279580116,50.9157714844],"type":"Point"}
}