{
  "type": "Feature",
  "properties": {
    "iso:country":"DE",
    "sg:address":"Felderhoferbr\u00fccke 15",
    "sg:city":"Ruppichteroth",
    "sg:phone":"+49 4922/9592090",
    "sg:postcode":"53809",
    "sg:province":"Nordrhein-Westfalen",
    "wof:name":"Willms Fleisch Gmbh",
    "wof:placetype":"venue"
},
  "geometry": {"coordinates":[7.4854660034,50.8443641663],"type":"Point"}
}