{
  "type": "Feature",
  "properties": {
    "iso:country":"DE",
    "sg:address":"Lehmder Damm 3",
    "sg:city":"Diepholz",
    "sg:phone":"+49 5441/927400",
    "sg:postcode":"49356",
    "sg:province":"Niedersachsen",
    "wof:name":"Flugplatz Diepholz-d\u00fcmmerland Verwaltungsgesellschaft Mbh",
    "wof:placetype":"venue"
},
  "geometry": {"coordinates":[8.348843,52.581596],"type":"Point"}
}