{
  "type": "Feature",
  "properties": {
    "iso:country":"DE",
    "sg:address":"In den Ellern 32",
    "sg:city":"L\u00f6hne",
    "sg:phone":"+49 5732/2296",
    "sg:postcode":"32584",
    "sg:province":"Nordrhein-Westfalen",
    "wof:name":"H. Saggel Versicherungen",
    "wof:placetype":"venue"
},
  "geometry": {"coordinates":[8.6883401871,52.2062301636],"type":"Point"}
}