{
  "type": "Feature",
  "properties": {
    "iso:country":"DE",
    "sg:address":"Uferstr. 11",
    "sg:city":"Solingen",
    "sg:phone":"+49 212/66142",
    "sg:postcode":"42699",
    "sg:province":"Nordrhein-Westfalen",
    "wof:name":"J. Himmerlich",
    "wof:placetype":"venue"
},
  "geometry": {"coordinates":[7.013124,51.155849],"type":"Point"}
}