{
  "type": "Feature",
  "properties": {
    "iso:country":"DE",
    "sg:address":"Hauptstr. 88",
    "sg:city":"Durmersheim",
    "sg:phone":"+49 7245/2367",
    "sg:postcode":"76448",
    "sg:province":"Baden-W\u00fcrttemberg",
    "wof:name":"Anton Wenzel",
    "wof:placetype":"venue"
},
  "geometry": {"coordinates":[8.268456,48.931011],"type":"Point"}
}