{
  "type": "Feature",
  "properties": {
    "iso:country":"DE",
    "sg:address":"Daimlerstr. 7",
    "sg:city":"Aschaffenburg",
    "sg:phone":"+49 6021/4910",
    "sg:postcode":"63741",
    "sg:province":"Bayern",
    "wof:name":"Schmitt & Orschler",
    "wof:placetype":"venue"
},
  "geometry": {"coordinates":[9.110515,49.985249],"type":"Point"}
}