{
  "type": "Feature",
  "properties": {
    "iso:country":"DE",
    "sg:address":"Johannesstr. 28",
    "sg:city":"Bottrop",
    "sg:phone":"+49 2041/45488",
    "sg:postcode":"46240",
    "sg:province":"Nordrhein-Westfalen",
    "wof:name":"Irmgard Und Wilh. Kuhlmann Haus- Und K\u00fcchenger\u00e4te",
    "wof:placetype":"venue"
},
  "geometry": {"coordinates":[6.9729027748,51.5348358154],"type":"Point"}
}