{
  "type": "Feature",
  "properties": {
    "iso:country":"DE",
    "sg:address":"Harter Str. 3",
    "sg:city":"Nu\u00dfdorf",
    "sg:phone":"+49 8669/6340",
    "sg:postcode":"83365",
    "sg:province":"Bayern",
    "wof:name":"H. Mittermaier",
    "wof:placetype":"venue"
},
  "geometry": {"coordinates":[12.595146,47.905758],"type":"Point"}
}