{
  "type": "Feature",
  "properties": {
    "iso:country":"DE",
    "sg:address":"D\u00fcnblick 9",
    "sg:city":"Beuren",
    "sg:phone":"+49 3605/510176",
    "sg:postcode":"37327",
    "sg:province":"Th\u00fcringen",
    "wof:name":"U. Und S. Barthel Gmbh",
    "wof:placetype":"venue"
},
  "geometry": {"coordinates":[10.322152,51.387672],"type":"Point"}
}