{
  "type": "Feature",
  "properties": {
    "iso:country":"DE",
    "sg:address":"Bracknellstr. 23",
    "sg:city":"Leverkusen",
    "sg:phone":"+49 2171/45712",
    "sg:postcode":"51379",
    "sg:province":"Nordrhein-Westfalen",
    "wof:name":"H. G\u00f6rgen Immobilienmakler",
    "wof:placetype":"venue"
},
  "geometry": {"coordinates":[6.9967107773,51.0639228821],"type":"Point"}
}