{
  "type": "Feature",
  "properties": {
    "iso:country":"DE",
    "sg:address":"Trift 13",
    "sg:city":"Marsberg",
    "sg:phone":"+49 2992/2031",
    "sg:postcode":"34431",
    "sg:province":"Nordrhein-Westfalen",
    "wof:name":"Engemann Ohg Udo Und Brigitte Engemann",
    "wof:placetype":"venue"
},
  "geometry": {"coordinates":[8.849571,51.461044],"type":"Point"}
}