{
  "type": "Feature",
  "properties": {
    "iso:country":"DE",
    "sg:address":"Sthamerstr. 36",
    "sg:city":"Hamburg",
    "sg:phone":"+49 40/6054024",
    "sg:postcode":"22397",
    "sg:province":"Hamburg",
    "wof:name":"Dr. Michael Sohnke Rechtsanwalt",
    "wof:placetype":"venue"
},
  "geometry": {"coordinates":[10.139248848,53.6919403076],"type":"Point"}
}