{
  "type": "Feature",
  "properties": {
    "iso:country":"DE",
    "sg:address":"Grimmaische Str. 23 b",
    "sg:city":"Borsdorf",
    "sg:phone":"+49 34291/86344",
    "sg:postcode":"04451",
    "sg:province":"Sachsen",
    "wof:name":"Roland Bartsch Architekt",
    "wof:placetype":"venue"
},
  "geometry": {"coordinates":[12.536637,51.342617],"type":"Point"}
}