{
  "type": "Feature",
  "properties": {
    "iso:country":"DE",
    "sg:address":"Gewerbestr. 6",
    "sg:city":"Moos",
    "sg:phone":"+49 7732/56526",
    "sg:postcode":"78345",
    "sg:province":"Baden-W\u00fcrttemberg",
    "wof:name":"Fred Fessel Architekt",
    "wof:placetype":"venue"
},
  "geometry": {"coordinates":[8.935142,47.722412],"type":"Point"}
}