{
  "type": "Feature",
  "properties": {
    "iso:country":"DE",
    "sg:address":"Rathsweg 11",
    "sg:city":"Bad Grund",
    "sg:phone":"+49 5327/2228",
    "sg:postcode":"37539",
    "sg:province":"Niedersachsen",
    "wof:name":"Reiseagentur Stein",
    "wof:placetype":"venue"
},
  "geometry": {"coordinates":[10.2382335663,51.8113899231],"type":"Point"}
}