{
  "type": "Feature",
  "properties": {
    "iso:country":"DE",
    "sg:address":"Schwabacher Str. 262",
    "sg:city":"F\u00fcrth",
    "sg:phone":"+49 911/713461",
    "sg:postcode":"90763",
    "sg:province":"Bayern",
    "wof:name":"Villa Verde",
    "wof:placetype":"venue"
},
  "geometry": {"coordinates":[10.988407135,49.4556503296],"type":"Point"}
}