{
  "type": "Feature",
  "properties": {
    "iso:country":"DE",
    "sg:address":"Lederergasse 13",
    "sg:city":"Dingolfing",
    "sg:phone":"+49 8731/8086",
    "sg:postcode":"84130",
    "sg:province":"Bayern",
    "wof:name":"Dr. Bernd Pachtner Und Dr. Friedrich Brenner",
    "wof:placetype":"venue"
},
  "geometry": {"coordinates":[12.4974365234,48.6301345825],"type":"Point"}
}