{
  "type": "Feature",
  "properties": {
    "iso:country":"DE",
    "sg:address":"Wilhelmstr. 84",
    "sg:city":"W\u00fclfrath",
    "sg:phone":"+49 2058/3159",
    "sg:postcode":"42489",
    "sg:province":"Nordrhein-Westfalen",
    "wof:name":"Karl-w. Euer",
    "wof:placetype":"venue"
},
  "geometry": {"coordinates":[7.0369901657,51.2822952271],"type":"Point"}
}