{
  "type": "Feature",
  "properties": {
    "iso:country":"DE",
    "sg:address":"Eckenerstr. 37",
    "sg:city":"Heilbronn",
    "sg:phone":"+49 7131/572642",
    "sg:postcode":"74081",
    "sg:province":"Baden-W\u00fcrttemberg",
    "wof:name":"Hermann Volk Gmbh & Co.",
    "wof:placetype":"venue"
},
  "geometry": {"coordinates":[9.2059440613,49.1175765991],"type":"Point"}
}