{
  "type": "Feature",
  "properties": {
    "iso:country":"DE",
    "sg:address":"Zisterzienserstr. 16",
    "sg:city":"Borken",
    "sg:phone":"+49 2862/42110",
    "sg:postcode":"46325",
    "sg:province":"Nordrhein-Westfalen",
    "wof:name":"Paul Terbeck Steuerberater",
    "wof:placetype":"venue"
},
  "geometry": {"coordinates":[6.7842321396,51.9045333862],"type":"Point"}
}