{
  "type": "Feature",
  "properties": {
    "iso:country":"DE",
    "sg:address":"Telemannstr. 1",
    "sg:city":"Leipzig",
    "sg:phone":"+49 341/9612757",
    "sg:postcode":"04107",
    "sg:province":"Sachsen",
    "wof:name":"Jan Goslar",
    "wof:placetype":"venue"
},
  "geometry": {"coordinates":[12.3687858582,51.3274497986],"type":"Point"}
}