{
  "type": "Feature",
  "properties": {
    "iso:country":"DE",
    "sg:address":"Wasserstr. 9",
    "sg:city":"Offenburg",
    "sg:phone":"+49 781/76253",
    "sg:postcode":"77652",
    "sg:province":"Baden-W\u00fcrttemberg",
    "wof:name":"Parkhaus Stadthalle",
    "wof:placetype":"venue"
},
  "geometry": {"coordinates":[7.9395442009,48.4718132019],"type":"Point"}
}