{
  "type": "Feature",
  "properties": {
    "iso:country":"DE",
    "sg:address":"Haimhauser Str. 26",
    "sg:city":"Unterschlei\u00dfheim",
    "sg:phone":"+49 89/3104453",
    "sg:postcode":"85716",
    "sg:province":"Bayern",
    "wof:name":"Ludwig Gmbh",
    "wof:placetype":"venue"
},
  "geometry": {"coordinates":[11.587584,48.264221],"type":"Point"}
}