{
  "type": "Feature",
  "properties": {
    "iso:country":"DE",
    "sg:address":"K\u00f6sliner Weg 13",
    "sg:city":"Norderstedt",
    "sg:phone":"+49 40/5232209",
    "sg:postcode":"22850",
    "sg:province":"Schleswig-Holstein",
    "wof:name":"Schultz & Tiede",
    "wof:placetype":"venue"
},
  "geometry": {"coordinates":[9.980094,53.689106],"type":"Point"}
}