{
  "type": "Feature",
  "properties": {
    "iso:country":"DE",
    "sg:address":"Schwanthalerstr. 86",
    "sg:city":"M\u00fcnchen",
    "sg:phone":"+49 89/532533",
    "sg:postcode":"80336",
    "sg:province":"Bayern",
    "wof:name":"Requisitenhaus Alfons Hoch",
    "wof:placetype":"venue"
},
  "geometry": {"coordinates":[11.5522146225,48.137676239],"type":"Point"}
}