{
  "type": "Feature",
  "properties": {
    "iso:country":"DE",
    "sg:address":"Frankfurter Str. 74",
    "sg:city":"Gro\u00df-Gerau",
    "sg:phone":"+49 6152/81091",
    "sg:postcode":"64521",
    "sg:province":"Hessen",
    "wof:name":"Winkler Truck Parts Gmbh",
    "wof:placetype":"venue"
},
  "geometry": {"coordinates":[8.485588,49.927723],"type":"Point"}
}