{
  "type": "Feature",
  "properties": {
    "iso:country":"DE",
    "sg:address":"Friedhofstr. 2",
    "sg:city":"R\u00f6thenbach",
    "sg:phone":"+49 911/5755769",
    "sg:postcode":"90552",
    "sg:province":"Bayern",
    "wof:name":"Gerhard Schmidt",
    "wof:placetype":"venue"
},
  "geometry": {"coordinates":[11.238992691,49.4830856323],"type":"Point"}
}