{
  "type": "Feature",
  "properties": {
    "iso:country":"DE",
    "sg:address":"Holzhauserstr. 1",
    "sg:city":"Landsberg",
    "sg:phone":"+49 8191/59833",
    "sg:postcode":"86899",
    "sg:province":"Bayern",
    "wof:name":"Top3d - Www Design & Beratung",
    "wof:placetype":"venue"
},
  "geometry": {"coordinates":[10.876584053,48.0495414734],"type":"Point"}
}