{
  "type": "Feature",
  "properties": {
    "iso:country":"DE",
    "sg:address":"Von-Galen-Str. 8",
    "sg:city":"Neuss",
    "sg:phone":"+49 2131/470967",
    "sg:postcode":"41466",
    "sg:province":"Nordrhein-Westfalen",
    "wof:name":"Kivelitz Gmbh",
    "wof:placetype":"venue"
},
  "geometry": {"coordinates":[6.702091,51.156189],"type":"Point"}
}