{
  "type": "Feature",
  "properties": {
    "iso:country":"DE",
    "sg:address":"H\u00f6xterstr. 27",
    "sg:city":"Marienm\u00fcnster",
    "sg:phone":"+49 5276/536",
    "sg:postcode":"37696",
    "sg:province":"Nordrhein-Westfalen",
    "wof:name":"Kr\u00f6ger Baustoffhandel Beteiligungsgesellschaft Mbh",
    "wof:placetype":"venue"
},
  "geometry": {"coordinates":[9.199141,51.80835],"type":"Point"}
}