{
  "type": "Feature",
  "properties": {
    "iso:country":"DE",
    "sg:address":"Hutbergstr. 20",
    "sg:city":"Ullersdorf",
    "sg:phone":"+49 3528/447822",
    "sg:postcode":"01454",
    "sg:province":"Sachsen",
    "wof:name":"A. G\u00e4bler",
    "wof:placetype":"venue"
},
  "geometry": {"coordinates":[13.898956,51.078308],"type":"Point"}
}