{
  "type": "Feature",
  "properties": {
    "iso:country":"DE",
    "sg:address":"Mahlsdorfer Str. 61E",
    "sg:city":"H\u00f6now",
    "sg:phone":"+49 30/9913030",
    "sg:postcode":"15366",
    "sg:province":"Brandenburg",
    "wof:name":"Thomas Scherz Gmbh",
    "wof:placetype":"venue"
},
  "geometry": {"coordinates":[13.6337547302,52.5371665955],"type":"Point"}
}