{
  "type": "Feature",
  "properties": {
    "iso:country":"DE",
    "sg:address":"Karmarschstr. 30",
    "sg:city":"Hannover",
    "sg:phone":"+49 511/326181",
    "sg:postcode":"30159",
    "sg:province":"Niedersachsen",
    "wof:name":"Karl-heinz Schirmer Immobilien Rdm",
    "wof:placetype":"venue"
},
  "geometry": {"coordinates":[9.7376317978,52.3724937439],"type":"Point"}
}