{
  "type": "Feature",
  "properties": {
    "iso:country":"DE",
    "sg:address":"Waldstr. 32",
    "sg:city":"Moosinning",
    "sg:phone":"+49 8123/4544",
    "sg:postcode":"85452",
    "sg:province":"Bayern",
    "wof:name":"W. Und H. Pratter",
    "wof:placetype":"venue"
},
  "geometry": {"coordinates":[11.7662267685,48.2789764404],"type":"Point"}
}