{
  "type": "Feature",
  "properties": {
    "iso:country":"DE",
    "sg:address":"Schwarzwaldstr. 7",
    "sg:city":"Wiesbaden",
    "sg:phone":"+49 611/22277",
    "sg:postcode":"65201",
    "sg:province":"Hessen",
    "wof:name":"Hans Eger",
    "wof:placetype":"venue"
},
  "geometry": {"coordinates":[8.189929,50.050503],"type":"Point"}
}