{
  "type": "Feature",
  "properties": {
    "iso:country":"DE",
    "sg:address":"Holzhofstr. 39",
    "sg:city":"Herzebrock-Clarholz",
    "sg:phone":"+49 5245/5891",
    "sg:postcode":"33442",
    "sg:province":"Nordrhein-Westfalen",
    "wof:name":"Vitus Gertheinrich",
    "wof:placetype":"venue"
},
  "geometry": {"coordinates":[8.212705,51.910164],"type":"Point"}
}