{
  "type": "Feature",
  "properties": {
    "iso:country":"DE",
    "sg:address":"Ottostr 9",
    "sg:city":"Goslar",
    "sg:phone":"+49 5321/37330",
    "sg:postcode":"38644",
    "sg:province":"Niedersachsen",
    "wof:name":"Concept Gmp Engineering Gmbh & Co Kg",
    "wof:placetype":"venue"
},
  "geometry": {"coordinates":[10.423242,51.926647],"type":"Point"}
}