{
  "type": "Feature",
  "properties": {
    "iso:country":"DE",
    "sg:address":"Sommerweg 4",
    "sg:city":"Hausen",
    "sg:phone":"+49 3605/513505",
    "sg:postcode":"37327",
    "sg:province":"Th\u00fcringen",
    "wof:name":"Karl-josef Keppler",
    "wof:placetype":"venue"
},
  "geometry": {"coordinates":[10.375587,51.378296],"type":"Point"}
}