{
  "type": "Feature",
  "properties": {
    "iso:country":"DE",
    "sg:address":"Seeadlerstr. 2",
    "sg:city":"Senftenberg",
    "sg:phone":"+49 3573/63037",
    "sg:postcode":"01968",
    "sg:province":"Brandenburg",
    "wof:name":"Steakhaus Am See",
    "wof:placetype":"venue"
},
  "geometry": {"coordinates":[13.989982605,51.5112037659],"type":"Point"}
}