{
  "type": "Feature",
  "properties": {
    "iso:country":"DE",
    "sg:address":"Steinstr. 2",
    "sg:city":"G\u00fcstrow",
    "sg:phone":"+49 3843/687654",
    "sg:postcode":"18273",
    "sg:province":"Mecklenburg-Vorpommern",
    "wof:name":"R. Jeske",
    "wof:placetype":"venue"
},
  "geometry": {"coordinates":[12.170873,53.796726],"type":"Point"}
}