{
  "type": "Feature",
  "properties": {
    "iso:country":"DE",
    "sg:address":"Dorfstr. 1",
    "sg:city":"Semmenstedt",
    "sg:phone":"+49 5336/328",
    "sg:postcode":"38327",
    "sg:province":"Niedersachsen",
    "wof:name":"Dr. Dietrich Wegner Tierarzt",
    "wof:placetype":"venue"
},
  "geometry": {"coordinates":[10.6964130402,52.0963821411],"type":"Point"}
}