{
  "type": "Feature",
  "properties": {
    "iso:country":"DE",
    "sg:address":"Zedernweg 35",
    "sg:city":"Wuppertal",
    "sg:phone":"+49 202/771753",
    "sg:postcode":"42111",
    "sg:province":"Nordrhein-Westfalen",
    "wof:name":"D.-r. Jacob Architekt",
    "wof:placetype":"venue"
},
  "geometry": {"coordinates":[7.15709,51.296658],"type":"Point"}
}