{
  "type": "Feature",
  "properties": {
    "iso:country":"DE",
    "sg:address":"Greifstr. 28",
    "sg:city":"Heidelberg",
    "sg:phone":"+49 6221/839494",
    "sg:postcode":"69123",
    "sg:province":"Baden-W\u00fcrttemberg",
    "wof:name":"Dr. Med. Ortrun Ritschl-jakob",
    "wof:placetype":"venue"
},
  "geometry": {"coordinates":[8.6454439163,49.4207382202],"type":"Point"}
}