{
  "type": "Feature",
  "properties": {
    "iso:country":"DE",
    "sg:address":"Kirchstr. 80",
    "sg:city":"Bad Sooden-Allendorf",
    "sg:phone":"+49 5652/1626",
    "sg:postcode":"37242",
    "sg:province":"Hessen",
    "wof:name":"Rolf Erich Barie Rechtsanwalt",
    "wof:placetype":"venue"
},
  "geometry": {"coordinates":[9.9731798172,51.2740974426],"type":"Point"}
}