{
  "type": "Feature",
  "properties": {
    "iso:country":"DE",
    "sg:address":"Garbsener Landstr. 10",
    "sg:city":"Hannover",
    "sg:postcode":"30419",
    "sg:province":"Niedersachsen",
    "wof:name":"Mikroelektronik Akademie Gmbh",
    "wof:placetype":"venue"
},
  "geometry": {"coordinates":[9.635682106,52.41223526],"type":"Point"}
}