{
  "type": "Feature",
  "properties": {
    "iso:country":"DE",
    "sg:address":"Textorstr. 3",
    "sg:city":"W\u00fcrzburg",
    "sg:phone":"+49 931/15563",
    "sg:postcode":"97070",
    "sg:province":"Bayern",
    "wof:name":"Topuzoglu Und \u00dclk\u00fc Rechtsanw\u00e4lte",
    "wof:placetype":"venue"
},
  "geometry": {"coordinates":[9.9345312119,49.7964096069],"type":"Point"}
}