{
  "type": "Feature",
  "properties": {
    "iso:country":"DE",
    "sg:address":"Lossaustr. 3",
    "sg:city":"Coburg",
    "sg:phone":"+49 9561/55213",
    "sg:postcode":"96450",
    "sg:province":"Bayern",
    "wof:name":"Max Fiedler",
    "wof:placetype":"venue"
},
  "geometry": {"coordinates":[10.959208,50.260921],"type":"Point"}
}