{
  "type": "Feature",
  "properties": {
    "iso:country":"DE",
    "sg:address":"B\u00f6hmergasse 6",
    "sg:city":"Limburg",
    "sg:phone":"+49 6431/22252",
    "sg:postcode":"65549",
    "sg:province":"Hessen",
    "wof:name":"F. Schwedt",
    "wof:placetype":"venue"
},
  "geometry": {"coordinates":[8.064537,50.387882],"type":"Point"}
}