{
  "type": "Feature",
  "properties": {
    "iso:country":"DE",
    "sg:address":"Moerser Str. 311",
    "sg:city":"Duisburg",
    "sg:phone":"+49 2066/30622",
    "sg:postcode":"47198",
    "sg:province":"Nordrhein-Westfalen",
    "wof:name":"K.-h. Voss",
    "wof:placetype":"venue"
},
  "geometry": {"coordinates":[6.6812801361,51.4495811462],"type":"Point"}
}