{
  "type": "Feature",
  "properties": {
    "iso:country":"DE",
    "sg:address":"Niederwaldstr. 21",
    "sg:city":"Rastatt",
    "sg:phone":"+49 7222/155478",
    "sg:postcode":"76437",
    "sg:province":"Baden-W\u00fcrttemberg",
    "wof:name":"Octomedia Hifi Video Tv Heinz Schmidt",
    "wof:placetype":"venue"
},
  "geometry": {"coordinates":[8.2211675644,48.8649978638],"type":"Point"}
}