{
  "type": "Feature",
  "properties": {
    "iso:country":"DE",
    "sg:address":"Sch\u00fctzeberger Str. 74",
    "sg:city":"Wolfhagen",
    "sg:postcode":"34466",
    "sg:province":"Hessen",
    "wof:name":"Verein Landwirtschaftlicher Fachschulabsolventen",
    "wof:placetype":"venue"
},
  "geometry": {"coordinates":[9.1762809753,51.3309822083],"type":"Point"}
}