{
  "type": "Feature",
  "properties": {
    "iso:country":"DE",
    "sg:address":"Arndtstr. 6",
    "sg:city":"Iserlohn",
    "sg:phone":"+49 2374/2329",
    "sg:postcode":"58642",
    "sg:province":"Nordrhein-Westfalen",
    "wof:name":"R. Lock Heissmangel",
    "wof:placetype":"venue"
},
  "geometry": {"coordinates":[7.6094360352,51.3697052002],"type":"Point"}
}