{
  "type": "Feature",
  "properties": {
    "iso:country":"DE",
    "sg:address":"Oeschberg 7a",
    "sg:city":"Ratingen",
    "sg:phone":"+49 2054/4270",
    "sg:postcode":"40885",
    "sg:province":"Nordrhein-Westfalen",
    "wof:name":"Anne Jacob Heilpraktikerin",
    "wof:placetype":"venue"
},
  "geometry": {"coordinates":[6.8890600204,51.3664398193],"type":"Point"}
}