{
  "type": "Feature",
  "properties": {
    "iso:country":"DE",
    "sg:address":"Madamenweg 55",
    "sg:city":"Braunschweig",
    "sg:phone":"+49 531/281180",
    "sg:postcode":"38118",
    "sg:province":"Niedersachsen",
    "wof:name":"Heinz Schmidt Gmbh",
    "wof:placetype":"venue"
},
  "geometry": {"coordinates":[10.492612,52.260345],"type":"Point"}
}