{
  "type": "Feature",
  "properties": {
    "iso:country":"DE",
    "sg:address":"An der Apostelkirche 1",
    "sg:city":"Hannover",
    "sg:phone":"+49 511/314836",
    "sg:postcode":"30161",
    "sg:province":"Niedersachsen",
    "wof:name":"Ev. Pfarramt Apostelkirche",
    "wof:placetype":"venue"
},
  "geometry": {"coordinates":[9.745516777,52.3847351074],"type":"Point"}
}