{
  "type": "Feature",
  "properties": {
    "iso:country":"DE",
    "sg:address":"Siemensstr 14",
    "sg:city":"Altenstadt",
    "sg:phone":"+49 6047/988880",
    "sg:postcode":"63674",
    "sg:province":"Hessen",
    "wof:name":"Dovebid Germany Gmbh",
    "wof:placetype":"venue"
},
  "geometry": {"coordinates":[8.966682,50.270935],"type":"Point"}
}