{
  "type": "Feature",
  "properties": {
    "iso:country":"DE",
    "sg:address":"Nederlinger Str. 77",
    "sg:city":"M\u00fcnchen",
    "sg:phone":"+49 89/152251",
    "sg:postcode":"80638",
    "sg:province":"Bayern",
    "wof:name":"Gernot Steinbacher Rechtsanwalt",
    "wof:placetype":"venue"
},
  "geometry": {"coordinates":[11.5187273026,48.1652565002],"type":"Point"}
}