{
  "type": "Feature",
  "properties": {
    "iso:country":"DE",
    "sg:address":"Kiefenholz 29",
    "sg:city":"W\u00f6rth",
    "sg:phone":"+49 9482/2270",
    "sg:postcode":"93086",
    "sg:province":"Bayern",
    "wof:name":"Donausch\u00e4nke",
    "wof:placetype":"venue"
},
  "geometry": {"coordinates":[12.3491859436,48.9916381836],"type":"Point"}
}