{
  "type": "Feature",
  "properties": {
    "iso:country":"DE",
    "sg:address":"Hauptstr. 4",
    "sg:city":"Kaufbeuren",
    "sg:phone":"+49 8341/2950",
    "sg:postcode":"87600",
    "sg:province":"Bayern",
    "wof:name":"Kath. Pfarramt St. Dionysius",
    "wof:placetype":"venue"
},
  "geometry": {"coordinates":[10.6034574509,47.8723526001],"type":"Point"}
}