{
  "type": "Feature",
  "properties": {
    "iso:country":"DE",
    "sg:address":"Frans-Hals-Str. 3",
    "sg:city":"M\u00fcnchen",
    "sg:phone":"+49 89/799885",
    "sg:postcode":"81479",
    "sg:province":"Bayern",
    "wof:name":"Al Pino Restaurant Gmbh",
    "wof:placetype":"venue"
},
  "geometry": {"coordinates":[11.5248537064,48.0772972107],"type":"Point"}
}