{
  "type": "Feature",
  "properties": {
    "iso:country":"DE",
    "sg:address":"Anzengruberstr. 3",
    "sg:city":"Ottobrunn",
    "sg:phone":"+49 89/6061155",
    "sg:postcode":"85521",
    "sg:province":"Bayern",
    "wof:name":"Christian Klug Masseur",
    "wof:placetype":"venue"
},
  "geometry": {"coordinates":[11.689664,48.072796],"type":"Point"}
}