{
  "type": "Feature",
  "properties": {
    "iso:country":"DE",
    "sg:address":"Im Schlung 5",
    "sg:city":"H\u00fcckelhoven",
    "sg:phone":"+49 2433/7027",
    "sg:postcode":"41836",
    "sg:province":"Nordrhein-Westfalen",
    "wof:name":"Jakob Venedey",
    "wof:placetype":"venue"
},
  "geometry": {"coordinates":[6.259988,51.049168],"type":"Point"}
}