{
  "type": "Feature",
  "properties": {
    "iso:country":"DE",
    "sg:address":"Panoramastr. 61",
    "sg:city":"Pforzheim",
    "sg:phone":"+49 7231/74968",
    "sg:postcode":"75180",
    "sg:province":"Baden-W\u00fcrttemberg",
    "wof:name":"B. Sch\u00f6ffler Leibersberger Krankengymnast",
    "wof:placetype":"venue"
},
  "geometry": {"coordinates":[8.666967,48.859291],"type":"Point"}
}