{
  "type": "Feature",
  "properties": {
    "iso:country":"DE",
    "sg:address":"Schie\u00dfstr. 1",
    "sg:city":"Steinheim",
    "sg:phone":"+49 7323/6193",
    "sg:postcode":"89555",
    "sg:province":"Baden-W\u00fcrttemberg",
    "wof:name":"A. Weidenbacher",
    "wof:placetype":"venue"
},
  "geometry": {"coordinates":[9.98942,48.672779],"type":"Point"}
}