{
  "type": "Feature",
  "properties": {
    "iso:country":"DE",
    "sg:address":"Dissenchener Schulstr. 5",
    "sg:city":"Cottbus",
    "sg:phone":"+49 355/720461",
    "sg:postcode":"03052",
    "sg:province":"Brandenburg",
    "wof:name":"Franks Blumenwelt",
    "wof:placetype":"venue"
},
  "geometry": {"coordinates":[14.392916,51.764248],"type":"Point"}
}