{
  "type": "Feature",
  "properties": {
    "iso:country":"DE",
    "sg:address":"Passauer Str. 4",
    "sg:city":"Bad Griesbach",
    "sg:phone":"+49 8532/920641",
    "sg:postcode":"94086",
    "sg:province":"Bayern",
    "wof:name":"Neue Presse Verlags-gmbh",
    "wof:placetype":"venue"
},
  "geometry": {"coordinates":[13.1931762695,48.4525299072],"type":"Point"}
}