{
  "type": "Feature",
  "properties": {
    "iso:country":"DE",
    "sg:address":"Maarstr. 2",
    "sg:city":"Aldenhoven",
    "sg:phone":"+49 2464/5336",
    "sg:postcode":"52457",
    "sg:province":"Nordrhein-Westfalen",
    "wof:name":"Gastst\u00e4tte Arnold Sevenich",
    "wof:placetype":"venue"
},
  "geometry": {"coordinates":[6.2555217743,50.9062423706],"type":"Point"}
}