{
  "type": "Feature",
  "properties": {
    "iso:country":"DE",
    "sg:address":"Bahnhofstr. 2",
    "sg:city":"Altdorf",
    "sg:phone":"+49 9187/902828",
    "sg:postcode":"90518",
    "sg:province":"Bayern",
    "wof:name":"Apotheke Am Bahnhof",
    "wof:placetype":"venue"
},
  "geometry": {"coordinates":[12.106384,48.557438],"type":"Point"}
}