{
  "type": "Feature",
  "properties": {
    "iso:country":"DE",
    "sg:address":"Schwabstr. 30",
    "sg:city":"Stuttgart",
    "sg:phone":"+49 711/616347",
    "sg:postcode":"70197",
    "sg:province":"Baden-W\u00fcrttemberg",
    "wof:name":"Gabriele Ziegenhagen Steuerberaterin",
    "wof:placetype":"venue"
},
  "geometry": {"coordinates":[9.1578502655,48.7711639404],"type":"Point"}
}