{
  "type": "Feature",
  "properties": {
    "iso:country":"DE",
    "sg:address":"Am Anger 1 a",
    "sg:city":"Bergisch Gladbach",
    "sg:phone":"+49 2204/61908",
    "sg:postcode":"51427",
    "sg:province":"Nordrhein-Westfalen",
    "wof:name":"G\u00fcnter Pfeiffer Rechtsanwalt",
    "wof:placetype":"venue"
},
  "geometry": {"coordinates":[7.1046051979,50.95104599],"type":"Point"}
}