{
  "type": "Feature",
  "properties": {
    "iso:country":"DE",
    "sg:address":"Niedernstr. 21",
    "sg:city":"Bielefeld",
    "sg:phone":"+49 521/61075",
    "sg:postcode":"33602",
    "sg:province":"Nordrhein-Westfalen",
    "wof:name":"Reiseb\u00fcro Kahn Gmbh",
    "wof:placetype":"venue"
},
  "geometry": {"coordinates":[8.531586647,52.0218009949],"type":"Point"}
}