{
  "type": "Feature",
  "properties": {
    "iso:country":"DE",
    "sg:address":"Juliuspromenade 24",
    "sg:city":"W\u00fcrzburg",
    "sg:phone":"+49 931/54704",
    "sg:postcode":"97070",
    "sg:province":"Bayern",
    "wof:name":"Schlemmer-eck Ersay Gmbh",
    "wof:placetype":"venue"
},
  "geometry": {"coordinates":[9.928716,49.796455],"type":"Point"}
}