{
  "type": "Feature",
  "properties": {
    "iso:country":"DE",
    "sg:address":"Breslauer Str. 2",
    "sg:city":"Melle",
    "sg:phone":"+49 5422/3748",
    "sg:postcode":"49324",
    "sg:province":"Niedersachsen",
    "wof:name":"Elf-station",
    "wof:placetype":"venue"
},
  "geometry": {"coordinates":[8.3425827026,52.2014694214],"type":"Point"}
}