{
  "type": "Feature",
  "properties": {
    "iso:country":"DE",
    "sg:address":"Ortsstr. 10",
    "sg:city":"E\u00dfbach",
    "sg:phone":"+49 36483/22390",
    "sg:postcode":"07924",
    "sg:province":"Th\u00fcringen",
    "wof:name":"Hotel Fuchsbau",
    "wof:placetype":"venue"
},
  "geometry": {"coordinates":[11.6845340729,50.5905838013],"type":"Point"}
}