{
  "type": "Feature",
  "properties": {
    "iso:country":"DE",
    "sg:address":"Pfarrkirchener Str. 29",
    "sg:city":"Ruhstorf",
    "sg:phone":"+49 8531/31646",
    "sg:postcode":"94099",
    "sg:province":"Bayern",
    "wof:name":"A. Baumgartner",
    "wof:placetype":"venue"
},
  "geometry": {"coordinates":[13.327569,48.42802],"type":"Point"}
}