{
  "type": "Feature",
  "properties": {
    "iso:country":"DE",
    "sg:address":"Herrgottswinkel",
    "sg:city":"Wallenfels",
    "sg:phone":"+49 9262/1224",
    "sg:postcode":"96346",
    "sg:province":"Bayern",
    "wof:name":"Wanderh\u00fctte",
    "wof:placetype":"venue"
},
  "geometry": {"coordinates":[11.4731616974,50.2675933838],"type":"Point"}
}