{
  "type": "Feature",
  "properties": {
    "iso:country":"DE",
    "sg:address":"Adolph-Menzel-Str. 9",
    "sg:city":"Leipzig",
    "sg:phone":"+49 341/9115081",
    "sg:postcode":"04157",
    "sg:province":"Sachsen",
    "wof:name":"G\u00f6tz & Urban",
    "wof:placetype":"venue"
},
  "geometry": {"coordinates":[12.3724393845,51.3685531616],"type":"Point"}
}