{
  "type": "Feature",
  "properties": {
    "iso:country":"DE",
    "sg:address":"Breslauer Str. 6",
    "sg:city":"Ottersweier",
    "sg:phone":"+49 7223/22168",
    "sg:postcode":"77833",
    "sg:province":"Baden-W\u00fcrttemberg",
    "wof:name":"Huck & Fritz Elektro Und Oelfeuerungsanl.",
    "wof:placetype":"venue"
},
  "geometry": {"coordinates":[8.122242,48.664574],"type":"Point"}
}