{
  "type": "Feature",
  "properties": {
    "iso:country":"DE",
    "sg:address":"Otto-Lilienthal-Str. 56",
    "sg:city":"Dinslaken",
    "sg:phone":"+49 2064/41210",
    "sg:postcode":"46539",
    "sg:province":"Nordrhein-Westfalen",
    "wof:name":"Heddenhausen Gmbh",
    "wof:placetype":"venue"
},
  "geometry": {"coordinates":[6.7523422241,51.5687065125],"type":"Point"}
}