{
  "type": "Feature",
  "properties": {
    "iso:country":"DE",
    "sg:address":"Bahnhofstr. 12",
    "sg:city":"Castrop-Rauxel",
    "sg:phone":"+49 2305/356570",
    "sg:postcode":"44575",
    "sg:province":"Nordrhein-Westfalen",
    "wof:name":"Gesellschaft F\u00fcr Wohnungs- Und St\u00e4dtebau Castrop-rauxel Mbh",
    "wof:placetype":"venue"
},
  "geometry": {"coordinates":[7.3110890388,51.5549201965],"type":"Point"}
}