{
  "type": "Feature",
  "properties": {
    "iso:country":"DE",
    "sg:address":"Heinrich-von-Tettingen-Str 16",
    "sg:city":"Konstanz",
    "sg:phone":"+49 7533/99470",
    "sg:postcode":"78465",
    "sg:province":"Baden-W\u00fcrttemberg",
    "wof:name":"A.s.k. Gmbh",
    "wof:placetype":"venue"
},
  "geometry": {"coordinates":[9.1337299347,47.7460975647],"type":"Point"}
}