{
  "type": "Feature",
  "properties": {
    "iso:country":"DE",
    "sg:address":"Steinstr. 17",
    "sg:city":"Witten",
    "sg:phone":"+49 2302/23264",
    "sg:postcode":"58452",
    "sg:province":"Nordrhein-Westfalen",
    "wof:name":"Renate Kowal",
    "wof:placetype":"venue"
},
  "geometry": {"coordinates":[7.3338217735,51.4368743896],"type":"Point"}
}