{
  "type": "Feature",
  "properties": {
    "iso:country":"DE",
    "sg:address":"Rehhagweg 31",
    "sg:city":"Freiburg",
    "sg:phone":"+49 761/290050",
    "sg:postcode":"79100",
    "sg:province":"Baden-W\u00fcrttemberg",
    "wof:name":"Frowein Gmbh",
    "wof:placetype":"venue"
},
  "geometry": {"coordinates":[7.864477,47.964821],"type":"Point"}
}