{
  "type": "Feature",
  "properties": {
    "iso:country":"DE",
    "sg:address":"August-Ullrich-Str. 25",
    "sg:city":"Elfershausen",
    "sg:phone":"+49 9704/6070",
    "sg:postcode":"97725",
    "sg:province":"Bayern",
    "wof:name":"Ullrich Gmbh",
    "wof:placetype":"venue"
},
  "geometry": {"coordinates":[9.964802742,50.1451187134],"type":"Point"}
}