{
  "type": "Feature",
  "properties": {
    "iso:country":"DE",
    "sg:address":"Hauptstr. 54",
    "sg:city":"Kirchheim",
    "sg:phone":"+49 6625/265",
    "sg:postcode":"36275",
    "sg:province":"Hessen",
    "wof:name":"Gastst\u00e4tte H. F\u00e4lber",
    "wof:placetype":"venue"
},
  "geometry": {"coordinates":[9.5741834641,50.8411521912],"type":"Point"}
}