{
  "type": "Feature",
  "properties": {
    "iso:country":"DE",
    "sg:address":"Hintergasse 1",
    "sg:city":"Gelnhausen",
    "sg:phone":"+49 4960/5169414",
    "sg:postcode":"63571",
    "sg:province":"Hessen",
    "wof:name":"Christian Liesen Gmbh",
    "wof:placetype":"venue"
},
  "geometry": {"coordinates":[9.137819,50.184807],"type":"Point"}
}