{
  "type": "Feature",
  "properties": {
    "iso:country":"DE",
    "sg:address":"Neuenloher Weg 34",
    "sg:city":"Ennepetal",
    "sg:phone":"+49 2333/88309",
    "sg:postcode":"58256",
    "sg:province":"Nordrhein-Westfalen",
    "wof:name":"Ingrid Refflinghaus Steuerberaterin",
    "wof:placetype":"venue"
},
  "geometry": {"coordinates":[7.3866300583,51.3027305603],"type":"Point"}
}