{
  "type": "Feature",
  "properties": {
    "iso:country":"DE",
    "sg:address":"Habsburger Allee 36",
    "sg:city":"Hagenbach",
    "sg:phone":"+49 7273/3663",
    "sg:postcode":"76767",
    "sg:province":"Rheinland-Pfalz",
    "wof:name":"H. Seeland",
    "wof:placetype":"venue"
},
  "geometry": {"coordinates":[8.249721,49.024727],"type":"Point"}
}