{
  "type": "Feature",
  "properties": {
    "iso:country":"DE",
    "sg:address":"Sulzbachtalstr. 127",
    "sg:city":"Sulzbach",
    "sg:phone":"+49 6897/764030",
    "sg:postcode":"66280",
    "sg:province":"Saarland",
    "wof:name":"Ludwig Ziehmer Gmbh",
    "wof:placetype":"venue"
},
  "geometry": {"coordinates":[7.066094,49.30109],"type":"Point"}
}