{
  "type": "Feature",
  "properties": {
    "iso:country":"DE",
    "sg:address":"102 rue des dames",
    "sg:city":"paris",
    "sg:phone":"+49 142949556",
    "sg:postcode":"75017",
    "wof:name":"Relax-oeil",
    "wof:placetype":"venue"
},
  "geometry": {"coordinates":[2.317058,48.882786],"type":"Point"}
}