{
  "type": "Feature",
  "properties": {
    "iso:country":"DE",
    "sg:address":"Neugasse 9",
    "sg:city":"Ensheim",
    "sg:phone":"+49 6732/8714",
    "sg:postcode":"55232",
    "sg:province":"Rheinland-Pfalz",
    "wof:name":"Siegfried Baumg\u00e4rtner",
    "wof:placetype":"venue"
},
  "geometry": {"coordinates":[8.1137037277,49.8048362732],"type":"Point"}
}