{
  "type": "Feature",
  "properties": {
    "iso:country":"DE",
    "sg:address":"Bahnhofstr. 147",
    "sg:city":"Grassau",
    "sg:postcode":"83224",
    "sg:province":"Bayern",
    "wof:name":"Coil Trans Tec Gmbh",
    "wof:placetype":"venue"
},
  "geometry": {"coordinates":[12.4605703354,47.7782707214],"type":"Point"}
}