{
  "type": "Feature",
  "properties": {
    "iso:country":"DE",
    "sg:address":"Am Hasenhe\u00df 1 PF 400143",
    "sg:city":"M\u00f6nchengladbach",
    "sg:phone":"+49 4921/665540",
    "sg:postcode":"41189",
    "sg:province":"Nordrhein-Westfalen",
    "wof:name":"Krings Fruchtsaft Gmbh",
    "wof:placetype":"venue"
},
  "geometry": {"coordinates":[6.41295,51.129421],"type":"Point"}
}