{
  "type": "Feature",
  "properties": {
    "iso:country":"DE",
    "sg:address":"Stockwiese 8",
    "sg:city":"Wetzlar",
    "sg:phone":"+49 6441/72887",
    "sg:postcode":"35581",
    "sg:province":"Hessen",
    "wof:name":"Schnorr Schleiftechnik Gmbh",
    "wof:placetype":"venue"
},
  "geometry": {"coordinates":[8.5842409134,50.5517311096],"type":"Point"}
}