{
  "type": "Feature",
  "properties": {
    "iso:country":"DE",
    "sg:address":"Ebertstr. 30a",
    "sg:city":"Herzogenrath",
    "sg:phone":"+49 2204/844100",
    "sg:postcode":"52134",
    "sg:province":"Nordrhein-Westfalen",
    "wof:name":"Heim Systems Gmbh",
    "wof:placetype":"venue"
},
  "geometry": {"coordinates":[7.162847,50.965916],"type":"Point"}
}