{
  "type": "Feature",
  "properties": {
    "iso:country":"DE",
    "sg:address":"Marktplatz 7",
    "sg:city":"M\u00fchlacker",
    "sg:phone":"+49 7041/937470",
    "sg:postcode":"75417",
    "sg:province":"Baden-W\u00fcrttemberg",
    "wof:name":"Maler Metzger Gmbh",
    "wof:placetype":"venue"
},
  "geometry": {"coordinates":[8.841991,48.9408],"type":"Point"}
}