{
  "type": "Feature",
  "properties": {
    "iso:country":"DE",
    "sg:address":"Sonnenstrasse 21",
    "sg:city":"Naila",
    "sg:phone":"+49 9282/5868",
    "sg:postcode":"95119",
    "sg:province":"Bayern",
    "wof:name":"Urlaub Guenstig Wie Noch Nie !!!!",
    "wof:placetype":"venue"
},
  "geometry": {"coordinates":[11.711648,50.33844],"type":"Point"}
}