{
  "type": "Feature",
  "properties": {
    "iso:country":"DE",
    "sg:address":"Industriestr. 12",
    "sg:city":"Schlangen",
    "sg:phone":"+49 5252/8480",
    "sg:postcode":"33189",
    "sg:province":"Nordrhein-Westfalen",
    "wof:name":"Pelipal Badm\u00f6bel",
    "wof:placetype":"venue"
},
  "geometry": {"coordinates":[8.83032,51.80048],"type":"Point"}
}