{
  "type": "Feature",
  "properties": {
    "iso:country":"DE",
    "sg:address":"Breite Str. 47",
    "sg:city":"Mainz",
    "sg:phone":"+49 6131/45165",
    "sg:postcode":"55124",
    "sg:province":"Rheinland-Pfalz",
    "wof:name":"Pizzeria Da Otello",
    "wof:placetype":"venue"
},
  "geometry": {"coordinates":[8.2120704651,50.0034255981],"type":"Point"}
}