{
  "type": "Feature",
  "properties": {
    "iso:country":"DE",
    "sg:address":"Leopoldstr. 20",
    "sg:city":"M\u00fcnchen",
    "sg:postcode":"80802",
    "sg:province":"Bayern",
    "wof:name":"Ramaj Gmbh",
    "wof:placetype":"venue"
},
  "geometry": {"coordinates":[11.583167,48.154148],"type":"Point"}
}