{
  "type": "Feature",
  "properties": {
    "iso:country":"DE",
    "sg:address":"Gereonstr 5-11",
    "sg:city":"K\u00f6ln",
    "sg:phone":"+49 221/9126310",
    "sg:postcode":"50670",
    "sg:province":"Nordrhein-Westfalen",
    "wof:name":"Db Services West Gmbh",
    "wof:placetype":"venue"
},
  "geometry": {"coordinates":[6.94885,50.94297],"type":"Point"}
}