{
  "type": "Feature",
  "properties": {
    "iso:country":"DE",
    "sg:address":"Decizer Str. 17",
    "sg:city":"Betzdorf",
    "sg:phone":"+49 2741/3249",
    "sg:postcode":"57518",
    "sg:province":"Rheinland-Pfalz",
    "wof:name":"F. K. Schmidt",
    "wof:placetype":"venue"
},
  "geometry": {"coordinates":[7.8735108376,50.7890777588],"type":"Point"}
}