{
  "type": "Feature",
  "properties": {
    "iso:country":"DE",
    "sg:address":"Vogelsbergstr 4",
    "sg:city":"Heppenheim",
    "sg:phone":"+49 6252/790030",
    "sg:postcode":"64646",
    "sg:province":"Hessen",
    "wof:name":"Tk Industrielackierungs Gmbh",
    "wof:placetype":"venue"
},
  "geometry": {"coordinates":[8.6131792068,49.6435852051],"type":"Point"}
}