{
  "type": "Feature",
  "properties": {
    "iso:country":"DE",
    "sg:address":"Spitzgrundstr. 11",
    "sg:city":"Coswig",
    "sg:phone":"+49 3523/75058",
    "sg:postcode":"01640",
    "sg:province":"Sachsen",
    "wof:name":"Speisegastst\u00e4tte Erholung",
    "wof:placetype":"venue"
},
  "geometry": {"coordinates":[13.5982055664,51.1327857971],"type":"Point"}
}