{
  "type": "Feature",
  "properties": {
    "iso:country":"DE",
    "sg:address":"Andreas-Seufert-Ring 19",
    "sg:city":"Kolitzheim",
    "sg:postcode":"97509",
    "sg:province":"Bayern",
    "wof:name":"Innotec Gmbh",
    "wof:placetype":"venue"
},
  "geometry": {"coordinates":[10.258003,49.950623],"type":"Point"}
}