{
  "type": "Feature",
  "properties": {
    "iso:country":"DE",
    "sg:address":"Frankfurter Str. 2",
    "sg:city":"Weilburg",
    "sg:phone":"+49 6471/2703",
    "sg:postcode":"35781",
    "sg:province":"Hessen",
    "wof:name":"Apotheke Am Landtor",
    "wof:placetype":"venue"
},
  "geometry": {"coordinates":[8.26673,50.482609],"type":"Point"}
}