{
  "type": "Feature",
  "properties": {
    "iso:country":"DE",
    "sg:address":"Puschkinstr. 51",
    "sg:city":"Eilenburg",
    "sg:phone":"+49 3423/750814",
    "sg:postcode":"04838",
    "sg:province":"Sachsen",
    "wof:name":"Pension Schubert Inh. Manuela Schubert",
    "wof:placetype":"venue"
},
  "geometry": {"coordinates":[12.6654167175,51.4715766907],"type":"Point"}
}