{
  "type": "Feature",
  "properties": {
    "iso:country":"DE",
    "sg:address":"Boschstr. 3 POSTFACH 2425",
    "sg:city":"Beckum",
    "sg:phone":"+49 4925/252267",
    "sg:postcode":"59257",
    "sg:province":"Nordrhein-Westfalen",
    "wof:name":"Windh\u00d6vel",
    "wof:placetype":"venue"
},
  "geometry": {"coordinates":[7.997556,51.798191],"type":"Point"}
}