{
  "type": "Feature",
  "properties": {
    "iso:country":"DE",
    "sg:address":"Georg-August-Str. 6",
    "sg:city":"Wiesbaden",
    "sg:phone":"+49 611/409670",
    "sg:postcode":"65195",
    "sg:province":"Hessen",
    "wof:name":"Dietmar Koelzer Kameramann",
    "wof:placetype":"venue"
},
  "geometry": {"coordinates":[8.2232866287,50.0834465027],"type":"Point"}
}