{
  "type": "Feature",
  "properties": {
    "iso:country":"DE",
    "sg:address":"Helmutstr. 18b",
    "sg:city":"Gladbeck",
    "sg:phone":"+49 2043/72370",
    "sg:postcode":"45968",
    "sg:province":"Nordrhein-Westfalen",
    "wof:name":"R\u00f6hl Gmbh",
    "wof:placetype":"venue"
},
  "geometry": {"coordinates":[6.999084,51.556118],"type":"Point"}
}