{
  "type": "Feature",
  "properties": {
    "iso:country":"DE",
    "sg:address":"Eixer Str. 6",
    "sg:city":"Edemissen",
    "sg:phone":"+49 5177/369",
    "sg:postcode":"31234",
    "sg:province":"Niedersachsen",
    "wof:name":"Gerhard Schrader",
    "wof:placetype":"venue"
},
  "geometry": {"coordinates":[10.181659,52.362122],"type":"Point"}
}