{
  "type": "Feature",
  "properties": {
    "iso:country":"DE",
    "sg:address":"M\u00fchlenweg 1",
    "sg:city":"Northeim",
    "sg:phone":"+49 5551/54344",
    "sg:postcode":"37154",
    "sg:province":"Niedersachsen",
    "wof:name":"Werner Boldt Architekt",
    "wof:placetype":"venue"
},
  "geometry": {"coordinates":[10.000497,51.706745],"type":"Point"}
}