{
  "type": "Feature",
  "properties": {
    "iso:country":"DE",
    "sg:address":"Am Alten Hafen 71",
    "sg:city":"Bremerhaven",
    "sg:postcode":"27568",
    "sg:province":"Bremen",
    "wof:name":"Deutsche Volksunion Landesverband",
    "wof:placetype":"venue"
},
  "geometry": {"coordinates":[8.5785865784,53.5428543091],"type":"Point"}
}