{
  "type": "Feature",
  "properties": {
    "iso:country":"DE",
    "sg:address":"Hauptstr 80",
    "sg:city":"Waldshut-Tiengen",
    "sg:phone":"+49 7741/2798",
    "sg:postcode":"79761",
    "sg:province":"Baden-W\u00fcrttemberg",
    "wof:name":"Steffen Gmbh",
    "wof:placetype":"venue"
},
  "geometry": {"coordinates":[8.278705,47.63512],"type":"Point"}
}