{
  "type": "Feature",
  "properties": {
    "iso:country":"DE",
    "sg:address":"Brunnenstr. 4",
    "sg:city":"Grevenbroich",
    "sg:phone":"+49 2182/7137",
    "sg:postcode":"41516",
    "sg:province":"Nordrhein-Westfalen",
    "wof:name":"E. R\u00fctten Inh. C. Schneider",
    "wof:placetype":"venue"
},
  "geometry": {"coordinates":[6.6832680702,51.1225471497],"type":"Point"}
}