{
  "type": "Feature",
  "properties": {
    "iso:country":"DE",
    "sg:address":"Berchemstr. 4",
    "sg:city":"Krailling",
    "sg:phone":"+49 89/8572568",
    "sg:postcode":"82152",
    "sg:province":"Bayern",
    "wof:name":"Uwe Thiel",
    "wof:placetype":"venue"
},
  "geometry": {"coordinates":[11.4147577286,48.0922050476],"type":"Point"}
}