{
  "type": "Feature",
  "properties": {
    "iso:country":"DE",
    "sg:address":"Ickstattstr. 19",
    "sg:city":"M\u00fcnchen",
    "sg:phone":"+49 89/2010826",
    "sg:postcode":"80469",
    "sg:province":"Bayern",
    "wof:name":"Klaus Baronetzky Patentanwalt",
    "wof:placetype":"venue"
},
  "geometry": {"coordinates":[11.5735902786,48.1277770996],"type":"Point"}
}