{
  "type": "Feature",
  "properties": {
    "iso:country":"DE",
    "sg:address":"Kalverkamp 9",
    "sg:city":"N\u00fcmbrecht",
    "sg:phone":"+49 2293/6979",
    "sg:postcode":"51588",
    "sg:province":"Nordrhein-Westfalen",
    "wof:name":"Fritz Kaminski",
    "wof:placetype":"venue"
},
  "geometry": {"coordinates":[7.52119,50.928261],"type":"Point"}
}