{
  "type": "Feature",
  "properties": {
    "iso:country":"DE",
    "sg:address":"Saxdorfer Str. 9",
    "sg:city":"Ko\u00dfdorf",
    "sg:phone":"+49 35342/71354",
    "sg:postcode":"04895",
    "sg:province":"Brandenburg",
    "wof:name":"Joachim Kriegisch",
    "wof:placetype":"venue"
},
  "geometry": {"coordinates":[13.23320961,51.4985694885],"type":"Point"}
}