{
  "type": "Feature",
  "properties": {
    "iso:country":"DE",
    "sg:address":"Behrend-Behrends-Weg 4",
    "sg:city":"Nieb\u00fcll",
    "sg:phone":"+49 4661/5212",
    "sg:postcode":"25899",
    "sg:province":"Schleswig-Holstein",
    "wof:name":"Bruno Lemke",
    "wof:placetype":"venue"
},
  "geometry": {"coordinates":[8.776158,54.83382],"type":"Point"}
}