{
  "type": "Feature",
  "properties": {
    "iso:country":"DE",
    "sg:address":"Birnbaumstr. 1",
    "sg:city":"Mannheim",
    "sg:phone":"+49 621/7887514",
    "sg:postcode":"68307",
    "sg:province":"Baden-W\u00fcrttemberg",
    "wof:name":"Bernd Und Doris Knopp",
    "wof:placetype":"venue"
},
  "geometry": {"coordinates":[8.4506378174,49.5434379578],"type":"Point"}
}