{
  "type": "Feature",
  "properties": {
    "iso:country":"DE",
    "sg:address":"Syker Str. 6",
    "sg:city":"Bassum",
    "sg:phone":"+49 4241/93370",
    "sg:postcode":"27211",
    "sg:province":"Niedersachsen",
    "wof:name":"Eichen-apotheke",
    "wof:placetype":"venue"
},
  "geometry": {"coordinates":[8.72811,52.84985],"type":"Point"}
}