{
  "type": "Feature",
  "properties": {
    "iso:country":"DE",
    "sg:address":"M\u00f6rfelder Landstr.2",
    "sg:city":"Frankfurt",
    "sg:phone":"+49 4969/612080",
    "sg:postcode":"60598",
    "sg:province":"Hessen",
    "wof:name":"Dresdner Bank",
    "wof:placetype":"venue"
},
  "geometry": {"coordinates":[8.691346,50.100712],"type":"Point"}
}