{
  "type": "Feature",
  "properties": {
    "iso:country":"DE",
    "sg:address":"Sindelfinger Str 21",
    "sg:city":"Leinfelden-Echterdingen",
    "sg:phone":"+49 711/97510",
    "sg:postcode":"70771",
    "sg:province":"Baden-W\u00fcrttemberg",
    "wof:name":"Mhz Hachtel Gmbh & Co",
    "wof:placetype":"venue"
},
  "geometry": {"coordinates":[9.169013,48.688347],"type":"Point"}
}