{
  "type": "Feature",
  "properties": {
    "iso:country":"DE",
    "sg:address":"Klingenbergstr. 28",
    "sg:city":"Detmold",
    "sg:phone":"+49 5231/96740",
    "sg:postcode":"32758",
    "sg:province":"Nordrhein-Westfalen",
    "wof:name":"Satzky Wohnwagen Und Reisemobile Gmbh",
    "wof:placetype":"venue"
},
  "geometry": {"coordinates":[8.853634,51.950672],"type":"Point"}
}