{
  "type": "Feature",
  "properties": {
    "iso:country":"DE",
    "sg:address":"Rh\u00f6nstr. 10",
    "sg:city":"Reinheim",
    "sg:phone":"+49 6162/85452",
    "sg:postcode":"64354",
    "sg:province":"Hessen",
    "wof:name":"C. Wolf",
    "wof:placetype":"venue"
},
  "geometry": {"coordinates":[8.7965993881,49.8455657959],"type":"Point"}
}