{
  "type": "Feature",
  "properties": {
    "iso:country":"DE",
    "sg:address":"Bussardweg 5",
    "sg:city":"Hemer",
    "sg:phone":"+49 2372/10245",
    "sg:postcode":"58675",
    "sg:province":"Nordrhein-Westfalen",
    "wof:name":"O & M Kabelkonfektion Gmbh",
    "wof:placetype":"venue"
},
  "geometry": {"coordinates":[7.7766242027,51.3821678162],"type":"Point"}
}