{
  "type": "Feature",
  "properties": {
    "iso:country":"DE",
    "sg:address":"Westerholtsfelder Str. 6",
    "sg:city":"Bad Zwischenahn",
    "sg:phone":"+49 4486/1787",
    "sg:postcode":"26160",
    "sg:province":"Niedersachsen",
    "wof:name":"Johann Wienken",
    "wof:placetype":"venue"
},
  "geometry": {"coordinates":[8.10826,53.179974],"type":"Point"}
}