{
  "type": "Feature",
  "properties": {
    "iso:country":"DE",
    "sg:address":"Kulmbacher Str. 3",
    "sg:city":"Neudrossenfeld",
    "sg:phone":"+49 9203/300",
    "sg:postcode":"95512",
    "sg:province":"Bayern",
    "wof:name":"Sparkasse Kulmbach",
    "wof:placetype":"venue"
},
  "geometry": {"coordinates":[11.501903,50.016541],"type":"Point"}
}