{
  "type": "Feature",
  "properties": {
    "iso:country":"DE",
    "sg:address":"Simrockstr. 190",
    "sg:city":"Hamburg",
    "sg:phone":"+49 40/8703370",
    "sg:postcode":"22589",
    "sg:province":"Hamburg",
    "wof:name":"Christina Spengler-sadkowski Rechtsanw\u00e4ltin",
    "wof:placetype":"venue"
},
  "geometry": {"coordinates":[9.8214864731,53.576259613],"type":"Point"}
}