{
  "type": "Feature",
  "properties": {
    "iso:country":"DE",
    "sg:address":"Sallstr. 76",
    "sg:city":"Hannover",
    "sg:phone":"+49 511/8091999",
    "sg:postcode":"30171",
    "sg:province":"Niedersachsen",
    "wof:name":"Der Kleine Teeladen",
    "wof:placetype":"venue"
},
  "geometry": {"coordinates":[9.7590513229,52.3616600037],"type":"Point"}
}