{
  "type": "Feature",
  "properties": {
    "iso:country":"DE",
    "sg:address":"Van-Acken-Str. 11",
    "sg:city":"Lingen",
    "sg:phone":"+49 591/3133",
    "sg:postcode":"49809",
    "sg:province":"Niedersachsen",
    "wof:name":"Frank Timmer Ingenieur",
    "wof:placetype":"venue"
},
  "geometry": {"coordinates":[7.334581852,52.525844574],"type":"Point"}
}