{
  "type": "Feature",
  "properties": {
    "iso:country":"DE",
    "sg:address":"Brieskower Str. 13 b",
    "sg:city":"Wiesenau",
    "sg:phone":"+49 33609/35320",
    "sg:postcode":"15295",
    "sg:province":"Brandenburg",
    "wof:name":"E. Schaar",
    "wof:placetype":"venue"
},
  "geometry": {"coordinates":[14.5891866684,52.2347221375],"type":"Point"}
}