{
  "type": "Feature",
  "properties": {
    "iso:country":"DE",
    "sg:address":"Hertastr. 5",
    "sg:city":"Idstein",
    "sg:phone":"+49 6126/6669",
    "sg:postcode":"65510",
    "sg:province":"Hessen",
    "wof:name":"A. Adam",
    "wof:placetype":"venue"
},
  "geometry": {"coordinates":[8.2557611465,50.2155647278],"type":"Point"}
}