{
  "type": "Feature",
  "properties": {
    "iso:country":"DE",
    "sg:address":"Hauptstrasse",
    "sg:city":"N\u00fcrburgring",
    "sg:phone":"+49 180 5 352530",
    "sg:postcode":"53520",
    "sg:province":"Rheinland-Pfalz",
    "wof:name":"Rock Am Ring Board",
    "wof:placetype":"venue"
},
  "geometry": {"coordinates":[6.953006,50.343231],"type":"Point"}
}