{
  "type": "Feature",
  "properties": {
    "iso:country":"DE",
    "sg:address":"Lindenstr. 31",
    "sg:city":"Sch\u00f6llkrippen",
    "sg:phone":"+49 6024/9405",
    "sg:postcode":"63825",
    "sg:province":"Bayern",
    "wof:name":"G. Gr\u00fcnewald",
    "wof:placetype":"venue"
},
  "geometry": {"coordinates":[9.2469434738,50.0841522217],"type":"Point"}
}