{
  "type": "Feature",
  "properties": {
    "iso:country":"DE",
    "sg:address":"Gartenstr. 28",
    "sg:city":"Fritzlar",
    "sg:phone":"+49 5622/1435",
    "sg:postcode":"34560",
    "sg:province":"Hessen",
    "wof:name":"R. Ewald Fuhr-bagger-stra\u00dfen- Baubetrieb Containerdienst",
    "wof:placetype":"venue"
},
  "geometry": {"coordinates":[9.264749527,51.1344642639],"type":"Point"}
}