{
  "type": "Feature",
  "properties": {
    "iso:country":"DE",
    "sg:address":"Herner Str. 76",
    "sg:city":"Bochum",
    "sg:phone":"+49 234/512958",
    "sg:postcode":"44791",
    "sg:province":"Nordrhein-Westfalen",
    "wof:name":"Gudrun Schmelz",
    "wof:placetype":"venue"
},
  "geometry": {"coordinates":[7.213781,51.490288],"type":"Point"}
}