{
  "type": "Feature",
  "properties": {
    "iso:country":"DE",
    "sg:address":"Weinstr. 16",
    "sg:city":"Bad Hersfeld",
    "sg:phone":"+49 6621/15744",
    "sg:postcode":"36251",
    "sg:province":"Hessen",
    "wof:name":"Ratskeller",
    "wof:placetype":"venue"
},
  "geometry": {"coordinates":[9.6948108673,50.8587875366],"type":"Point"}
}