{
  "type": "Feature",
  "properties": {
    "iso:country":"DE",
    "sg:address":"Leo-Center",
    "sg:city":"Leonberg",
    "sg:phone":"+49 7152/97961",
    "sg:postcode":"71229",
    "sg:province":"Baden-W\u00fcrttemberg",
    "wof:name":"Flachsmann",
    "wof:placetype":"venue"
},
  "geometry": {"coordinates":[9.0143098831,48.8017234802],"type":"Point"}
}