{
  "type": "Feature",
  "properties": {
    "iso:country":"DE",
    "sg:address":"Sommerhalde 52",
    "sg:city":"Altensteig",
    "sg:postcode":"72213",
    "sg:province":"Baden-W\u00fcrttemberg",
    "wof:name":"Ingenieurb\u00fcro Nesselberger Gmbh",
    "wof:placetype":"venue"
},
  "geometry": {"coordinates":[8.6640090942,48.5746879578],"type":"Point"}
}