{
  "type": "Feature",
  "properties": {
    "iso:country":"DE",
    "sg:address":"Rienharzer Str 34",
    "sg:city":"Welzheim",
    "sg:phone":"+49 7182/524",
    "sg:postcode":"73642",
    "sg:province":"Baden-W\u00fcrttemberg",
    "wof:name":"Joh. Oertel & Co, Kristallglas Inhaberin Petra Sch\u00fctte",
    "wof:placetype":"venue"
},
  "geometry": {"coordinates":[9.638508,48.873062],"type":"Point"}
}