{
  "type": "Feature",
  "properties": {
    "iso:country":"DE",
    "sg:address":"K\u00e4ferstr. 8",
    "sg:city":"Schwabenheim",
    "sg:phone":"+49 6130/1303",
    "sg:postcode":"55270",
    "sg:province":"Rheinland-Pfalz",
    "wof:name":"Lothar Huff",
    "wof:placetype":"venue"
},
  "geometry": {"coordinates":[8.0993490219,49.9330024719],"type":"Point"}
}