{
  "type": "Feature",
  "properties": {
    "iso:country":"DE",
    "sg:address":"Georg-Krau\u00df-Str. 18",
    "sg:city":"Erlangen",
    "sg:phone":"+49 9131/42081",
    "sg:postcode":"91056",
    "sg:province":"Bayern",
    "wof:name":"Paul Becker Architekt",
    "wof:placetype":"venue"
},
  "geometry": {"coordinates":[10.973752,49.592339],"type":"Point"}
}