{
  "type": "Feature",
  "properties": {
    "iso:country":"DE",
    "sg:address":"Ludwig-D\u00fcrr-Str. 28",
    "sg:city":"Icking",
    "sg:phone":"+49 8178/5377",
    "sg:postcode":"82057",
    "sg:province":"Bayern",
    "wof:name":"Fritz Noppes Architekt",
    "wof:placetype":"venue"
},
  "geometry": {"coordinates":[11.4311,47.952507],"type":"Point"}
}