{
  "type": "Feature",
  "properties": {
    "iso:country":"DE",
    "sg:address":"Heinrich-Heine-Str. 8",
    "sg:city":"Metzingen",
    "sg:phone":"+49 7123/4340",
    "sg:postcode":"72555",
    "sg:province":"Baden-W\u00fcrttemberg",
    "wof:name":"Hans-peter Bazlen",
    "wof:placetype":"venue"
},
  "geometry": {"coordinates":[9.285033,48.543434],"type":"Point"}
}