{
  "type": "Feature",
  "properties": {
    "iso:country":"DE",
    "sg:address":"Marktoberdorfer Str. 11",
    "sg:city":"Biessenhofen",
    "sg:phone":"+49 8342/95050",
    "sg:postcode":"87640",
    "sg:province":"Bayern",
    "wof:name":"S. Und R. Lober",
    "wof:placetype":"venue"
},
  "geometry": {"coordinates":[10.6385803223,47.8129348755],"type":"Point"}
}