{
  "type": "Feature",
  "properties": {
    "iso:country":"DE",
    "sg:address":"Eppendorfer Landstr. 31",
    "sg:city":"Hamburg",
    "sg:phone":"+49 40/4807381",
    "sg:postcode":"20249",
    "sg:province":"Hamburg",
    "wof:name":"Adriane Beck Und Partner Gmbh",
    "wof:placetype":"venue"
},
  "geometry": {"coordinates":[9.985007,53.587791],"type":"Point"}
}