{
  "type": "Feature",
  "properties": {
    "iso:country":"DE",
    "sg:address":"Bachstr. 4",
    "sg:city":"Longuich",
    "sg:phone":"+49 6502/6525",
    "sg:postcode":"54340",
    "sg:province":"Rheinland-Pfalz",
    "wof:name":"Horst J\u00e4gen",
    "wof:placetype":"venue"
},
  "geometry": {"coordinates":[6.760765,49.810547],"type":"Point"}
}