{
  "type": "Feature",
  "properties": {
    "iso:country":"DE",
    "sg:address":"Lange Herzogstr. 52",
    "sg:city":"Wolfenb\u00fcttel",
    "sg:phone":"+49 5331/92090",
    "sg:postcode":"38300",
    "sg:province":"Niedersachsen",
    "wof:name":"Herzog-apotheke",
    "wof:placetype":"venue"
},
  "geometry": {"coordinates":[10.53494,52.163448],"type":"Point"}
}