{
  "type": "Feature",
  "properties": {
    "iso:country":"DE",
    "sg:address":"Eulerstr. 9",
    "sg:city":"M\u00fcnster",
    "sg:phone":"+49 251/662101",
    "sg:postcode":"48155",
    "sg:province":"Nordrhein-Westfalen",
    "wof:name":"Transportbetonwerk Knoche Gmbh & Co.",
    "wof:placetype":"venue"
},
  "geometry": {"coordinates":[7.6391859055,51.938079834],"type":"Point"}
}