{
  "type": "Feature",
  "properties": {
    "iso:country":"DE",
    "sg:address":"Winkelstr. 35",
    "sg:city":"M\u00fchlhausen-Ehingen",
    "sg:phone":"+49 7733/8147",
    "sg:postcode":"78259",
    "sg:province":"Baden-W\u00fcrttemberg",
    "wof:name":"Agritrans Gmbh",
    "wof:placetype":"venue"
},
  "geometry": {"coordinates":[8.807566,47.823608],"type":"Point"}
}