{
  "type": "Feature",
  "properties": {
    "iso:country":"DE",
    "sg:address":"Neidensteiner Str. 31",
    "sg:city":"Epfenbach",
    "sg:phone":"+49 7263/2212",
    "sg:postcode":"74925",
    "sg:province":"Baden-W\u00fcrttemberg",
    "wof:name":"Reinhard Mozzi",
    "wof:placetype":"venue"
},
  "geometry": {"coordinates":[8.9066476822,49.3332138062],"type":"Point"}
}