{
  "type": "Feature",
  "properties": {
    "iso:country":"DE",
    "sg:address":"Planstr. 9",
    "sg:city":"Neckartenzlingen",
    "sg:phone":"+49 7127/31443",
    "sg:postcode":"72654",
    "sg:province":"Baden-W\u00fcrttemberg",
    "wof:name":"F. Alt",
    "wof:placetype":"venue"
},
  "geometry": {"coordinates":[9.2369966507,48.5901908875],"type":"Point"}
}