{
  "type": "Feature",
  "properties": {
    "iso:country":"DE",
    "sg:address":"Hospitalstr. 13",
    "sg:city":"Tirschenreuth",
    "sg:phone":"+49 9631/2252",
    "sg:postcode":"95643",
    "sg:province":"Bayern",
    "wof:name":"A. Reber",
    "wof:placetype":"venue"
},
  "geometry": {"coordinates":[12.3376941681,49.8798217773],"type":"Point"}
}