{
  "type": "Feature",
  "properties": {
    "iso:country":"DE",
    "sg:address":"Schlei\u00dfheimer Str. 442",
    "sg:city":"M\u00fcnchen",
    "sg:phone":"+49 89/31215430",
    "sg:postcode":"80935",
    "sg:province":"Bayern",
    "wof:name":"K & R -computersysteme Gmbh",
    "wof:placetype":"venue"
},
  "geometry": {"coordinates":[11.5643577576,48.2024765015],"type":"Point"}
}