{
  "type": "Feature",
  "properties": {
    "iso:country":"DE",
    "sg:address":"Straupitzstr. 3",
    "sg:city":"Guben",
    "sg:phone":"+49 3561/431530",
    "sg:postcode":"03172",
    "sg:province":"Brandenburg",
    "wof:name":"Modernisierung-sanierung- Ausbau Gmbh",
    "wof:placetype":"venue"
},
  "geometry": {"coordinates":[14.7147140503,51.9515266418],"type":"Point"}
}