{
  "type": "Feature",
  "properties": {
    "iso:country":"DE",
    "sg:address":"Theodor-Neubauer-Str. 11",
    "sg:city":"Altenburg",
    "sg:phone":"+49 3447/505075",
    "sg:postcode":"04600",
    "sg:province":"Th\u00fcringen",
    "wof:name":"Pension Am Standesamt",
    "wof:placetype":"venue"
},
  "geometry": {"coordinates":[12.4264907837,50.9844169617],"type":"Point"}
}