{
  "type": "Feature",
  "properties": {
    "iso:country":"DE",
    "sg:address":"Sudetenstr. 7",
    "sg:city":"Kaufbeuren",
    "sg:phone":"+49 8341/8030",
    "sg:postcode":"87600",
    "sg:province":"Bayern",
    "wof:name":"Kontron Modular Computers Gmbh",
    "wof:placetype":"venue"
},
  "geometry": {"coordinates":[10.6442241669,47.8983535767],"type":"Point"}
}