{
  "type": "Feature",
  "properties": {
    "iso:country":"DE",
    "sg:address":"Norderweg 9",
    "sg:city":"Garding",
    "sg:phone":"+49 4862/106010",
    "sg:postcode":"25836",
    "sg:province":"Schleswig-Holstein",
    "wof:name":"T\u00f6dten Gmbh",
    "wof:placetype":"venue"
},
  "geometry": {"coordinates":[8.7680654526,54.3307723999],"type":"Point"}
}