{
  "type": "Feature",
  "properties": {
    "iso:country":"DE",
    "sg:address":"Am M\u00fchlenberg 26",
    "sg:city":"Lilienthal",
    "sg:phone":"+49 4298/3832",
    "sg:postcode":"28865",
    "sg:province":"Niedersachsen",
    "wof:name":"Erich Haltermann",
    "wof:placetype":"venue"
},
  "geometry": {"coordinates":[8.985333,53.139294],"type":"Point"}
}