{
  "type": "Feature",
  "properties": {
    "iso:country":"DE",
    "sg:address":"Buchenweg 5",
    "sg:city":"Rottenburg",
    "sg:phone":"+49 7457/2030",
    "sg:postcode":"72108",
    "sg:province":"Baden-W\u00fcrttemberg",
    "wof:name":"G\u00fcnther Teufel",
    "wof:placetype":"venue"
},
  "geometry": {"coordinates":[8.8693714142,48.5070457458],"type":"Point"}
}