{
  "type": "Feature",
  "properties": {
    "iso:country":"DE",
    "sg:address":"Breitenfelder Str. 32",
    "sg:city":"Gevelsberg",
    "sg:phone":"+49 2332/914484",
    "sg:postcode":"58285",
    "sg:province":"Nordrhein-Westfalen",
    "wof:name":"Dimetec Gmbh",
    "wof:placetype":"venue"
},
  "geometry": {"coordinates":[7.319876194,51.3172607422],"type":"Point"}
}