{
  "type": "Feature",
  "properties": {
    "iso:country":"DE",
    "sg:address":"Marburger Str. 3",
    "sg:city":"Korbach",
    "sg:phone":"+49 5631/2008",
    "sg:postcode":"34497",
    "sg:province":"Hessen",
    "wof:name":"Grass Gmbh",
    "wof:placetype":"venue"
},
  "geometry": {"coordinates":[8.8958797455,51.2718696594],"type":"Point"}
}