{
  "type": "Feature",
  "properties": {
    "iso:country":"DE",
    "sg:address":"Hofstr. 56",
    "sg:city":"Gescher",
    "sg:phone":"+49 2542/7679",
    "sg:postcode":"48712",
    "sg:province":"Nordrhein-Westfalen",
    "wof:name":"Maria Blenker Verwaltungs Gmbh",
    "wof:placetype":"venue"
},
  "geometry": {"coordinates":[7.0019230843,51.9546356201],"type":"Point"}
}