{
  "type": "Feature",
  "properties": {
    "iso:country":"DE",
    "sg:address":"Carl-Benz-Str. 1",
    "sg:city":"Germaringen",
    "sg:phone":"+49 8341/62977",
    "sg:postcode":"87656",
    "sg:province":"Bayern",
    "wof:name":"Marmor Peter Gmbh",
    "wof:placetype":"venue"
},
  "geometry": {"coordinates":[10.6524372101,47.9210128784],"type":"Point"}
}