{
  "type": "Feature",
  "properties": {
    "iso:country":"DE",
    "sg:address":"Schwalbengasse 42-44",
    "sg:city":"K\u00f6ln",
    "sg:phone":"+49 221/2727250",
    "sg:postcode":"50667",
    "sg:province":"Nordrhein-Westfalen",
    "wof:name":"D\u00f6ding Verm\u00f6gens- Verwaltung Gmbh",
    "wof:placetype":"venue"
},
  "geometry": {"coordinates":[6.9483008385,50.9402503967],"type":"Point"}
}