{
  "type": "Feature",
  "properties": {
    "iso:country":"DE",
    "sg:address":"Mettinger Str. 3",
    "sg:city":"Ibbenb\u00fcren",
    "sg:phone":"+49 5451/8161",
    "sg:postcode":"49479",
    "sg:province":"Nordrhein-Westfalen",
    "wof:name":"Theodor Neyer Blumen",
    "wof:placetype":"venue"
},
  "geometry": {"coordinates":[7.788769,52.27079],"type":"Point"}
}