{
  "type": "Feature",
  "properties": {
    "iso:country":"DE",
    "sg:address":"Duringstr. 17 a",
    "sg:city":"T\u00fcrkenfeld",
    "sg:phone":"+49 8193/269",
    "sg:postcode":"82299",
    "sg:province":"Bayern",
    "wof:name":"Walter Reger",
    "wof:placetype":"venue"
},
  "geometry": {"coordinates":[11.084736824,48.1064376831],"type":"Point"}
}