{
  "type": "Feature",
  "properties": {
    "iso:country":"DE",
    "sg:address":"Arendahls Wiese 44",
    "sg:city":"Essen",
    "sg:phone":"+49 201/322478",
    "sg:postcode":"45141",
    "sg:province":"Nordrhein-Westfalen",
    "wof:name":"Baumgarten & Schmidt",
    "wof:placetype":"venue"
},
  "geometry": {"coordinates":[7.028924942,51.48072052],"type":"Point"}
}