{
  "type": "Feature",
  "properties": {
    "iso:country":"DE",
    "sg:address":"Schlo\u00dfstr. 9",
    "sg:city":"Osnabr\u00fcck",
    "sg:postcode":"49074",
    "sg:province":"Niedersachsen",
    "wof:name":"Schr\u00f6der Verm\u00f6gens- Verwaltung Gmbh & Co. Kg",
    "wof:placetype":"venue"
},
  "geometry": {"coordinates":[8.047088623,52.2697944641],"type":"Point"}
}