{
  "type": "Feature",
  "properties": {
    "iso:country":"DE",
    "sg:address":"Flintbeker Str. 1",
    "sg:city":"Kiel",
    "sg:phone":"+49 431/642033",
    "sg:postcode":"24113",
    "sg:province":"Schleswig-Holstein",
    "wof:name":"Klee Garten-fachmarkt Gmbh",
    "wof:placetype":"venue"
},
  "geometry": {"coordinates":[10.128538,54.302021],"type":"Point"}
}