{
  "type": "Feature",
  "properties": {
    "iso:country":"DE",
    "sg:address":"Br\u00fcckenstr. 15",
    "sg:city":"Vilsbiburg",
    "sg:phone":"+49 8741/6360",
    "sg:postcode":"84137",
    "sg:province":"Bayern",
    "wof:name":"Sportparkrestaurant",
    "wof:placetype":"venue"
},
  "geometry": {"coordinates":[12.3483142853,48.4526634216],"type":"Point"}
}