{
  "type": "Feature",
  "properties": {
    "iso:country":"DE",
    "sg:address":"Stresemannallee 5",
    "sg:city":"Hamburg",
    "sg:phone":"+49 40/567985",
    "sg:postcode":"22529",
    "sg:province":"Hamburg",
    "wof:name":"Helmut Holzwei\u00dfig",
    "wof:placetype":"venue"
},
  "geometry": {"coordinates":[9.959989,53.591278],"type":"Point"}
}