{
  "type": "Feature",
  "properties": {
    "iso:country":"DE",
    "sg:address":"Himmelgeister Str. 113",
    "sg:city":"D\u00fcsseldorf",
    "sg:phone":"+49 211/341802",
    "sg:postcode":"40225",
    "sg:province":"Nordrhein-Westfalen",
    "wof:name":"M. Gottsmann",
    "wof:placetype":"venue"
},
  "geometry": {"coordinates":[6.781955,51.198689],"type":"Point"}
}