{
  "type": "Feature",
  "properties": {
    "iso:country":"DE",
    "sg:address":"Lindenstr. 7",
    "sg:city":"Ibbenb\u00fcren",
    "sg:phone":"+49 5451/88958",
    "sg:postcode":"49479",
    "sg:province":"Nordrhein-Westfalen",
    "wof:name":"Badziong-automaten-gmbh",
    "wof:placetype":"venue"
},
  "geometry": {"coordinates":[7.7875847816,52.2606430054],"type":"Point"}
}