{
  "type": "Feature",
  "properties": {
    "iso:country":"DE",
    "sg:address":"Hauptstr. 40",
    "sg:city":"Laar",
    "sg:phone":"+49 5947/297",
    "sg:postcode":"49824",
    "sg:province":"Niedersachsen",
    "wof:name":"Karl Heinz Ossege",
    "wof:placetype":"venue"
},
  "geometry": {"coordinates":[6.744574,52.614799],"type":"Point"}
}