{
  "type": "Feature",
  "properties": {
    "iso:country":"DE",
    "sg:address":"Weberstr. 39",
    "sg:city":"Gro\u00df-Zimmern",
    "sg:postcode":"64846",
    "sg:province":"Hessen",
    "wof:name":"I. Jung Gmbh",
    "wof:placetype":"venue"
},
  "geometry": {"coordinates":[8.8228626251,49.8794898987],"type":"Point"}
}