{
  "type": "Feature",
  "properties": {
    "iso:country":"DE",
    "sg:address":"Bahnhofstr. 23",
    "sg:city":"Wesseling",
    "sg:phone":"+49 2236/1347",
    "sg:postcode":"50389",
    "sg:province":"Nordrhein-Westfalen",
    "wof:name":"Ballon Bistro",
    "wof:placetype":"venue"
},
  "geometry": {"coordinates":[6.9807710648,50.8245544434],"type":"Point"}
}