{
  "type": "Feature",
  "properties": {
    "iso:country":"DE",
    "sg:address":"Schelmenhag 4",
    "sg:city":"Burladingen",
    "sg:phone":"+49 7475/7734",
    "sg:postcode":"72393",
    "sg:province":"Baden-W\u00fcrttemberg",
    "wof:name":"Isabella Kemmler",
    "wof:placetype":"venue"
},
  "geometry": {"coordinates":[9.164918,48.273594],"type":"Point"}
}