{
  "type": "Feature",
  "properties": {
    "iso:country":"DE",
    "sg:address":"Kanalstr 5-7",
    "sg:city":"Heilbronn",
    "sg:phone":"+49 7131/46010",
    "sg:postcode":"74080",
    "sg:province":"Baden-W\u00fcrttemberg",
    "wof:name":"Metallgu\u00df Franz",
    "wof:placetype":"venue"
},
  "geometry": {"coordinates":[9.19855,49.14204],"type":"Point"}
}