{
  "type": "Feature",
  "properties": {
    "iso:country":"DE",
    "sg:address":"Postfach 2186:: 35432 Wettenberg:: Germany.^^Schulstr 38::",
    "sg:city":"Wettenberg",
    "sg:phone":"+49 6406/91050",
    "sg:postcode":"35435",
    "sg:province":"Hessen",
    "wof:name":"Volksbank Wissmar Eg",
    "wof:placetype":"venue"
},
  "geometry": {"coordinates":[8.63572,50.623566],"type":"Point"}
}