{
  "type": "Feature",
  "properties": {
    "iso:country":"DE",
    "sg:address":"Auguststr. 108",
    "sg:city":"Recklinghausen",
    "sg:phone":"+49 2361/61846",
    "sg:postcode":"45661",
    "sg:province":"Nordrhein-Westfalen",
    "wof:name":"Estate Enterprise Gmbh",
    "wof:placetype":"venue"
},
  "geometry": {"coordinates":[7.173157,51.576054],"type":"Point"}
}