{
  "type": "Feature",
  "properties": {
    "iso:country":"DE",
    "sg:address":"Puschkinstr. 33",
    "sg:city":"Eilenburg",
    "sg:phone":"+49 3423/759528",
    "sg:postcode":"04838",
    "sg:province":"Sachsen",
    "wof:name":"Hotel Il-burg",
    "wof:placetype":"venue"
},
  "geometry": {"coordinates":[12.6611280441,51.4697570801],"type":"Point"}
}