{
  "type": "Feature",
  "properties": {
    "iso:country":"DE",
    "sg:address":"Franz-Joseph-Str. 35",
    "sg:city":"M\u00fcnchen",
    "sg:phone":"+49 89/335761",
    "sg:postcode":"80801",
    "sg:province":"Bayern",
    "wof:name":"Exatmo",
    "wof:placetype":"venue"
},
  "geometry": {"coordinates":[11.578132,48.157684],"type":"Point"}
}