{
  "type": "Feature",
  "properties": {
    "iso:country":"DE",
    "sg:address":"Heganger 12",
    "sg:city":"Hallstadt",
    "sg:phone":"+49 951/965090",
    "sg:postcode":"96103",
    "sg:province":"Bayern",
    "wof:name":"Amon Holzbau Gmbh",
    "wof:placetype":"venue"
},
  "geometry": {"coordinates":[10.8753108978,49.9290390015],"type":"Point"}
}