{
  "type": "Feature",
  "properties": {
    "iso:country":"DE",
    "sg:address":"Titotstr. 8",
    "sg:city":"Heilbronn",
    "sg:phone":"+49 7131/9390",
    "sg:postcode":"74072",
    "sg:province":"Baden-W\u00fcrttemberg",
    "wof:name":"Heilbronner Treuhand- Gmbh",
    "wof:placetype":"venue"
},
  "geometry": {"coordinates":[9.222902298,49.1403083801],"type":"Point"}
}