{
  "type": "Feature",
  "properties": {
    "iso:country":"DE",
    "sg:address":"Berliner Str. 90 e",
    "sg:city":"Kolkwitz",
    "sg:phone":"+49 355/28361",
    "sg:postcode":"03099",
    "sg:province":"Brandenburg",
    "wof:name":"Rudolf Wurm",
    "wof:placetype":"venue"
},
  "geometry": {"coordinates":[14.21155,51.750889],"type":"Point"}
}