{
  "type": "Feature",
  "properties": {
    "iso:country":"DE",
    "sg:address":"An der Raa 7",
    "sg:city":"Pinneberg",
    "sg:phone":"+49 4101/63206",
    "sg:postcode":"25421",
    "sg:province":"Schleswig-Holstein",
    "wof:name":"Kegelstuben",
    "wof:placetype":"venue"
},
  "geometry": {"coordinates":[9.7932453156,53.6436843872],"type":"Point"}
}