{
  "type": "Feature",
  "properties": {
    "iso:country":"DE",
    "sg:address":"J\u00fcdenstr. 42",
    "sg:city":"M\u00fchlhausen",
    "sg:phone":"+49 36018/12573",
    "sg:postcode":"99974",
    "sg:province":"Th\u00fcringen",
    "wof:name":"K.-heinz Luhn Rechtsanwalt",
    "wof:placetype":"venue"
},
  "geometry": {"coordinates":[10.456530571,51.2092437744],"type":"Point"}
}