{
  "type": "Feature",
  "properties": {
    "iso:country":"DE",
    "sg:address":"St.-Cosmas-Str. 2a",
    "sg:city":"Kaufbeuren",
    "sg:phone":"+49 8341/8756",
    "sg:postcode":"87600",
    "sg:province":"Bayern",
    "wof:name":"Josef Faber Ingenieur",
    "wof:placetype":"venue"
},
  "geometry": {"coordinates":[10.604804039,47.8704605103],"type":"Point"}
}