{
  "type": "Feature",
  "properties": {
    "iso:country":"DE",
    "sg:address":"Br\u00fcsseler Str. 28",
    "sg:city":"Bad Bentheim",
    "sg:phone":"+49 5924/8323",
    "sg:postcode":"48455",
    "sg:province":"Niedersachsen",
    "wof:name":"Gack Spiel- Und Freizeitger\u00e4te Gmbh",
    "wof:placetype":"venue"
},
  "geometry": {"coordinates":[7.0651960373,52.3201675415],"type":"Point"}
}