{
  "type": "Feature",
  "properties": {
    "iso:country":"DE",
    "sg:address":"Oberstr. 4",
    "sg:city":"Arnsberg",
    "sg:phone":"+49 2932/24529",
    "sg:postcode":"59755",
    "sg:province":"Nordrhein-Westfalen",
    "wof:name":"K.g. Klasmeyer Augenoptiker",
    "wof:placetype":"venue"
},
  "geometry": {"coordinates":[7.9664030075,51.4505844116],"type":"Point"}
}