{
  "type": "Feature",
  "properties": {
    "iso:country":"DE",
    "sg:address":"Pontinusweg 36",
    "sg:city":"K\u00f6ln",
    "sg:phone":"+49 2234/49407",
    "sg:postcode":"50859",
    "sg:province":"Nordrhein-Westfalen",
    "wof:name":"Carl Berger Consulting",
    "wof:placetype":"venue"
},
  "geometry": {"coordinates":[6.8250141144,50.9494132996],"type":"Point"}
}