{
  "type": "Feature",
  "properties": {
    "iso:country":"DE",
    "sg:address":"Wiehenstr. 167",
    "sg:city":"B\u00fcnde",
    "sg:phone":"+49 4952/2349710",
    "sg:postcode":"32257",
    "sg:province":"Nordrhein-Westfalen",
    "wof:name":"Ludewig Gmbh",
    "wof:placetype":"venue"
},
  "geometry": {"coordinates":[8.5745792389,52.2403068542],"type":"Point"}
}