{
  "type": "Feature",
  "properties": {
    "iso:country":"DE",
    "sg:address":"Gentilstr. 33",
    "sg:city":"Aschaffenburg",
    "sg:phone":"+49 6021/97910",
    "sg:postcode":"63739",
    "sg:province":"Bayern",
    "wof:name":"Detlev Buller Handelsvertretungen Gmbh",
    "wof:placetype":"venue"
},
  "geometry": {"coordinates":[9.1713190079,49.9689254761],"type":"Point"}
}