{
  "type": "Feature",
  "properties": {
    "iso:country":"DE",
    "sg:address":"Steubenstr. 4 b",
    "sg:city":"D\u00fcsseldorf",
    "sg:phone":"+49 211/7489769",
    "sg:postcode":"40599",
    "sg:province":"Nordrhein-Westfalen",
    "wof:name":"J. Loepke Ingenieur",
    "wof:placetype":"venue"
},
  "geometry": {"coordinates":[6.8559679985,51.1773490906],"type":"Point"}
}