{
  "type": "Feature",
  "properties": {
    "iso:country":"DE",
    "sg:address":"Hauptstr. 140",
    "sg:city":"Wiesloch",
    "sg:phone":"+49 6222/2289",
    "sg:postcode":"69168",
    "sg:province":"Baden-W\u00fcrttemberg",
    "wof:name":"Erbprinzen",
    "wof:placetype":"venue"
},
  "geometry": {"coordinates":[8.6972923279,49.2919044495],"type":"Point"}
}