{
  "type": "Feature",
  "properties": {
    "iso:country":"DE",
    "sg:address":"Alte Frankfurter Str. 17 a",
    "sg:city":"Bad Vilbel",
    "sg:phone":"+49 6101/58480",
    "sg:postcode":"61118",
    "sg:province":"Hessen",
    "wof:name":"Heinrich Maeusel Gmbh",
    "wof:placetype":"venue"
},
  "geometry": {"coordinates":[8.7271509171,50.1675872803],"type":"Point"}
}