{
  "type": "Feature",
  "properties": {
    "iso:country":"DE",
    "sg:address":"Brandrain 14",
    "sg:city":"Kappelrodeck",
    "sg:phone":"+49 7842/575",
    "sg:postcode":"77876",
    "sg:province":"Baden-W\u00fcrttemberg",
    "wof:name":"Fuchs Grabdenkm\u00e4ler",
    "wof:placetype":"venue"
},
  "geometry": {"coordinates":[8.1069030762,48.588596344],"type":"Point"}
}