{
  "type": "Feature",
  "properties": {
    "iso:country":"DE",
    "sg:address":"Kleine M\u00fchlenstr. 9",
    "sg:city":"Quakenbr\u00fcck",
    "sg:phone":"+49 5431/94060",
    "sg:postcode":"49610",
    "sg:province":"Niedersachsen",
    "wof:name":"Neue Osnabr\u00fccker Zeitung Gmbh & Co. Kg",
    "wof:placetype":"venue"
},
  "geometry": {"coordinates":[7.9545259476,52.6757125854],"type":"Point"}
}