{
  "type": "Feature",
  "properties": {
    "iso:country":"DE",
    "sg:address":"Semmelweisstr. 7",
    "sg:city":"Havelberg",
    "sg:phone":"+49 39387/88750",
    "sg:postcode":"39539",
    "sg:province":"Sachsen-Anhalt",
    "wof:name":"Havel-apotheke Inh. Gerald Friedl",
    "wof:placetype":"venue"
},
  "geometry": {"coordinates":[12.079957,52.831963],"type":"Point"}
}