{
  "type": "Feature",
  "properties": {
    "iso:country":"DE",
    "sg:address":"Nachtigallenweg 10",
    "sg:city":"M\u00f6nchengladbach",
    "sg:phone":"+49 2161/651561",
    "sg:postcode":"41065",
    "sg:province":"Nordrhein-Westfalen",
    "wof:name":"Bauunternehmung Portz Gmbh",
    "wof:placetype":"venue"
},
  "geometry": {"coordinates":[6.4846129417,51.1995315552],"type":"Point"}
}