{
  "type": "Feature",
  "properties": {
    "iso:country":"DE",
    "sg:address":"Ludwigstr. 11",
    "sg:city":"Krailling",
    "sg:phone":"+49 89/8574442",
    "sg:postcode":"82152",
    "sg:province":"Bayern",
    "wof:name":"Rudolf Paternoster",
    "wof:placetype":"venue"
},
  "geometry": {"coordinates":[11.4105587006,48.0985412598],"type":"Point"}
}