{
  "type": "Feature",
  "properties": {
    "iso:country":"DE",
    "sg:address":"Werdenstr. 47a",
    "sg:city":"Eschweiler",
    "sg:phone":"+49 2403/87870",
    "sg:postcode":"52249",
    "sg:province":"Nordrhein-Westfalen",
    "wof:name":"Heinz Nie\u00dfen Gmbh",
    "wof:placetype":"venue"
},
  "geometry": {"coordinates":[6.235406,50.823273],"type":"Point"}
}