{
  "type": "Feature",
  "properties": {
    "iso:country":"DE",
    "sg:address":"Meerbrauckweg 21",
    "sg:city":"Iserlohn",
    "sg:phone":"+49 2371/60425",
    "sg:postcode":"58644",
    "sg:province":"Nordrhein-Westfalen",
    "wof:name":"Friedr.-wilh. Jochheim",
    "wof:placetype":"venue"
},
  "geometry": {"coordinates":[7.714105,51.335449],"type":"Point"}
}