{
  "type": "Feature",
  "properties": {
    "iso:country":"DE",
    "sg:address":"Lange Str. 26",
    "sg:city":"Sebnitz",
    "sg:phone":"+49 35971/52662",
    "sg:postcode":"01855",
    "sg:province":"Sachsen",
    "wof:name":"Gerhard Lange",
    "wof:placetype":"venue"
},
  "geometry": {"coordinates":[14.2757501602,50.9723014832],"type":"Point"}
}