{
  "type": "Feature",
  "properties": {
    "iso:country":"DE",
    "sg:address":"An der Eiskaut 56",
    "sg:city":"Usingen",
    "sg:phone":"+49 6081/66530",
    "sg:postcode":"61250",
    "sg:province":"Hessen",
    "wof:name":"Karl-heinz Karell Finanzberater",
    "wof:placetype":"venue"
},
  "geometry": {"coordinates":[8.53221035,50.3292007446],"type":"Point"}
}