{
  "type": "Feature",
  "properties": {
    "iso:country":"DE",
    "sg:address":"Forbachstr. 1",
    "sg:city":"Baiersbronn",
    "sg:phone":"+49 7442/180050",
    "sg:postcode":"72270",
    "sg:province":"Baden-W\u00fcrttemberg",
    "wof:name":"J\u00fcrgen Morlok",
    "wof:placetype":"venue"
},
  "geometry": {"coordinates":[8.3704395294,48.5064888],"type":"Point"}
}