{
  "type": "Feature",
  "properties": {
    "iso:country":"DE",
    "sg:address":"Tungeler Damm 193",
    "sg:city":"Wardenburg/Oberlethe",
    "sg:postcode":"26203",
    "sg:province":"Niedersachsen",
    "wof:name":"Letheschule",
    "wof:placetype":"venue"
},
  "geometry": {"coordinates":[8.163816,53.066952],"type":"Point"}
}