{
  "type": "Feature",
  "properties": {
    "iso:country":"DE",
    "sg:address":"Ferdinandstr. 15",
    "sg:city":"Dinkelscherben",
    "sg:phone":"+49 8292/2205",
    "sg:postcode":"86424",
    "sg:province":"Bayern",
    "wof:name":"E. Mayer",
    "wof:placetype":"venue"
},
  "geometry": {"coordinates":[10.5810756683,48.3521156311],"type":"Point"}
}