{
  "type": "Feature",
  "properties": {
    "iso:country":"DE",
    "sg:address":"Am Kamp 12",
    "sg:city":"Preu\u00dfisch Oldendorf",
    "sg:phone":"+49 5742/2282",
    "sg:postcode":"32361",
    "sg:province":"Nordrhein-Westfalen",
    "wof:name":"Heinz M\u00f6ller",
    "wof:placetype":"venue"
},
  "geometry": {"coordinates":[8.490091,52.312592],"type":"Point"}
}