{
  "type": "Feature",
  "properties": {
    "iso:country":"DE",
    "sg:address":"Maximilianstr. 24",
    "sg:city":"Mindelheim",
    "sg:phone":"+49 8261/21261",
    "sg:postcode":"87719",
    "sg:province":"Bayern",
    "wof:name":"Christoph Schindele",
    "wof:placetype":"venue"
},
  "geometry": {"coordinates":[10.4889,48.046535],"type":"Point"}
}