{
  "type": "Feature",
  "properties": {
    "iso:country":"DE",
    "sg:address":"Gewerbegebiet Laugkfeld 21",
    "sg:city":"Senftenberg",
    "sg:phone":"+49 3573/73144",
    "sg:postcode":"01968",
    "sg:province":"Brandenburg",
    "wof:name":"Vogel Und Partner Gmbh",
    "wof:placetype":"venue"
},
  "geometry": {"coordinates":[14.0159597397,51.5265007019],"type":"Point"}
}