{
  "type": "Feature",
  "properties": {
    "iso:country":"DE",
    "sg:address":"Schillerstr. 20",
    "sg:city":"Bad Bramstedt",
    "sg:phone":"+49 4192/9636",
    "sg:postcode":"24576",
    "sg:province":"Schleswig-Holstein",
    "wof:name":"Babyparadies Ute Langner",
    "wof:placetype":"venue"
},
  "geometry": {"coordinates":[9.8700885773,53.9159812927],"type":"Point"}
}