{
  "type": "Feature",
  "properties": {
    "iso:country":"DE",
    "sg:address":"Aumaer Str. 3",
    "sg:city":"Triebes",
    "sg:phone":"+49 36622/72746",
    "sg:postcode":"07950",
    "sg:province":"Th\u00fcringen",
    "wof:name":"Claus Kaufmann",
    "wof:placetype":"venue"
},
  "geometry": {"coordinates":[12.0179662704,50.6837654114],"type":"Point"}
}