{
  "type": "Feature",
  "properties": {
    "iso:country":"DE",
    "sg:address":"Industriestr. 26",
    "sg:city":"M\u00f6rlenbach",
    "sg:phone":"+49 6209/712330",
    "sg:postcode":"69509",
    "sg:province":"Hessen",
    "wof:name":"Weber-produktions- Und Vertriebsgesellschaft Mbh",
    "wof:placetype":"venue"
},
  "geometry": {"coordinates":[8.7443094254,49.6030769348],"type":"Point"}
}