{
  "type": "Feature",
  "properties": {
    "iso:country":"DE",
    "sg:address":"Dieskaustr 155",
    "sg:city":"Leipzig",
    "sg:phone":"+49 341/4250658",
    "sg:postcode":"04249",
    "sg:province":"Sachsen",
    "wof:name":"Mtl Mikrofontechnik Leipzig Gmbh",
    "wof:placetype":"venue"
},
  "geometry": {"coordinates":[12.326899,51.307648],"type":"Point"}
}