{
  "type": "Feature",
  "properties": {
    "iso:country":"DE",
    "sg:address":"Im Eichholz 26",
    "sg:city":"Schalksm\u00fchle",
    "sg:phone":"+49 2351/952941",
    "sg:postcode":"58579",
    "sg:province":"Nordrhein-Westfalen",
    "wof:name":"Axel Bremer",
    "wof:placetype":"venue"
},
  "geometry": {"coordinates":[7.5885429382,51.257648468],"type":"Point"}
}