{
  "type": "Feature",
  "properties": {
    "iso:country":"DE",
    "sg:address":"Ludwigstr. 2",
    "sg:city":"Gaildorf",
    "sg:postcode":"74405",
    "sg:province":"Baden-W\u00fcrttemberg",
    "wof:name":"Fgw Gaildorf Gmbh",
    "wof:placetype":"venue"
},
  "geometry": {"coordinates":[9.768535614,48.9834327698],"type":"Point"}
}