{
  "type": "Feature",
  "properties": {
    "iso:country":"DE",
    "sg:address":"Francoisstr. 58",
    "sg:city":"Saarbr\u00fccken",
    "sg:phone":"+49 681/51277",
    "sg:postcode":"66117",
    "sg:province":"Saarland",
    "wof:name":"Egon Wagner",
    "wof:placetype":"venue"
},
  "geometry": {"coordinates":[6.975898,49.232494],"type":"Point"}
}