{
  "type": "Feature",
  "properties": {
    "iso:country":"DE",
    "sg:address":"W\u00fcrttembergstr. 3",
    "sg:city":"Rangendingen",
    "sg:phone":"+49 7471/98255",
    "sg:postcode":"72414",
    "sg:province":"Baden-W\u00fcrttemberg",
    "wof:name":"Heinz Dahlhoff",
    "wof:placetype":"venue"
},
  "geometry": {"coordinates":[8.8781929016,48.3771286011],"type":"Point"}
}