{
  "type": "Feature",
  "properties": {
    "iso:country":"DE",
    "sg:address":"Unterer Kirchweg 17",
    "sg:city":"Badenweiler",
    "sg:phone":"+49 7632/338",
    "sg:postcode":"79410",
    "sg:province":"Baden-W\u00fcrttemberg",
    "wof:name":"G\u00e4stehaus I. Fichtlscherer",
    "wof:placetype":"venue"
},
  "geometry": {"coordinates":[7.670771122,47.8057975769],"type":"Point"}
}