{
  "type": "Feature",
  "properties": {
    "iso:country":"DE",
    "sg:address":"Talstr. 21",
    "sg:city":"Murr",
    "sg:phone":"+49 7144/25490",
    "sg:postcode":"71711",
    "sg:province":"Baden-W\u00fcrttemberg",
    "wof:name":"Becker Gmbh & Co.",
    "wof:placetype":"venue"
},
  "geometry": {"coordinates":[9.260018,48.966209],"type":"Point"}
}