{
  "type": "Feature",
  "properties": {
    "iso:country":"DE",
    "sg:address":"Urbanweg 3",
    "sg:city":"Stra\u00dflach-Dingharting",
    "sg:phone":"+49 8170/8072",
    "sg:postcode":"82064",
    "sg:province":"Bayern",
    "wof:name":"Albert Patzak",
    "wof:placetype":"venue"
},
  "geometry": {"coordinates":[11.5213422775,47.9802207947],"type":"Point"}
}