{
  "type": "Feature",
  "properties": {
    "iso:country":"DE",
    "sg:address":"Paulinenstr. 50",
    "sg:city":"Detmold",
    "sg:phone":"+49 5231/34911",
    "sg:postcode":"32756",
    "sg:province":"Nordrhein-Westfalen",
    "wof:name":"Reiseladen Albatros Inh. Christiane Laue",
    "wof:placetype":"venue"
},
  "geometry": {"coordinates":[8.8745241165,51.9378089905],"type":"Point"}
}