{
  "type": "Feature",
  "properties": {
    "iso:country":"DE",
    "sg:address":"Am Markt 12",
    "sg:city":"Hanau",
    "sg:phone":"+49 6181/23033",
    "sg:postcode":"63450",
    "sg:province":"Hessen",
    "wof:name":"Clemens Glas- Und Porzellanwaren",
    "wof:placetype":"venue"
},
  "geometry": {"coordinates":[8.9174098969,50.1332893372],"type":"Point"}
}