{
  "type": "Feature",
  "properties": {
    "iso:country":"DE",
    "sg:address":"Spanberg 17",
    "sg:city":"Hebertsfelden",
    "sg:phone":"+49 8721/95960",
    "sg:postcode":"84332",
    "sg:province":"Bayern",
    "wof:name":"Schmidbauer Blechbearbeitung Gmbh",
    "wof:placetype":"venue"
},
  "geometry": {"coordinates":[12.7940177917,48.4130783081],"type":"Point"}
}