{
  "type": "Feature",
  "properties": {
    "iso:country":"DE",
    "sg:address":"Alte Bahnhofstr. 12",
    "sg:city":"Puchheim",
    "sg:phone":"+49 89/806300",
    "sg:postcode":"82178",
    "sg:province":"Bayern",
    "wof:name":"Biohof Josef Unglert",
    "wof:placetype":"venue"
},
  "geometry": {"coordinates":[11.349451,48.160004],"type":"Point"}
}