{
  "type": "Feature",
  "properties": {
    "iso:country":"DE",
    "sg:address":"Barkhausstr. 64",
    "sg:city":"Darmstadt",
    "sg:phone":"+49 6151/781848",
    "sg:postcode":"64289",
    "sg:province":"Hessen",
    "wof:name":"Hermann Schratz Architekt",
    "wof:placetype":"venue"
},
  "geometry": {"coordinates":[8.654376,49.882767],"type":"Point"}
}