{
  "type": "Feature",
  "properties": {
    "iso:country":"DE",
    "sg:address":"Antoinettenstr.",
    "sg:city":"Dessau",
    "sg:phone":"+49 340/214908",
    "sg:postcode":"06844",
    "sg:province":"Sachsen-Anhalt",
    "wof:name":"Peking Ente",
    "wof:placetype":"venue"
},
  "geometry": {"coordinates":[12.238360405,51.8386459351],"type":"Point"}
}