{
  "type": "Feature",
  "properties": {
    "iso:country":"DE",
    "sg:address":"Lindenstr. 30",
    "sg:city":"Frankfurt",
    "sg:phone":"+49 69/727244",
    "sg:postcode":"60325",
    "sg:province":"Hessen",
    "wof:name":"Archiv Des Verbandes Der Deutschen Bahnindustrie E. V.",
    "wof:placetype":"venue"
},
  "geometry": {"coordinates":[8.661531,50.117176],"type":"Point"}
}