{
  "type": "Feature",
  "properties": {
    "iso:country":"DE",
    "sg:address":"Hattorfer Str. 33",
    "sg:city":"Wolfsburg",
    "sg:phone":"+49 5361/72066",
    "sg:postcode":"38442",
    "sg:province":"Niedersachsen",
    "wof:name":"Heinrich Bartels",
    "wof:placetype":"venue"
},
  "geometry": {"coordinates":[10.733336,52.391438],"type":"Point"}
}