{
  "type": "Feature",
  "properties": {
    "iso:country":"DE",
    "sg:address":"Offheimer Weg 11a",
    "sg:city":"Limburg",
    "sg:phone":"+49 6431/26077",
    "sg:postcode":"65549",
    "sg:province":"Hessen",
    "wof:name":"Tegrol-industriebedarfs- Gesellschaft Mbh",
    "wof:placetype":"venue"
},
  "geometry": {"coordinates":[8.063017,50.395729],"type":"Point"}
}