{
  "type": "Feature",
  "properties": {
    "iso:country":"DE",
    "sg:address":"Am R\u00f6merkastell 16",
    "sg:city":"Florstadt",
    "sg:phone":"+49 6035/8807",
    "sg:postcode":"61197",
    "sg:province":"Hessen",
    "wof:name":"Wenisch Rechtsanwalt",
    "wof:placetype":"venue"
},
  "geometry": {"coordinates":[8.91492939,50.327129364],"type":"Point"}
}