{
  "type": "Feature",
  "properties": {
    "iso:country":"DE",
    "sg:address":"Hohe Str. 58",
    "sg:city":"Leipzig",
    "sg:phone":"+49 341/9612989",
    "sg:postcode":"04107",
    "sg:province":"Sachsen",
    "wof:name":"H\u00e4rtwig",
    "wof:placetype":"venue"
},
  "geometry": {"coordinates":[12.370815,51.330181],"type":"Point"}
}