{
  "type": "Feature",
  "properties": {
    "iso:country":"DE",
    "sg:address":"M\u00f6hnestr. 11",
    "sg:city":"Brilon",
    "sg:phone":"+49 2961/51056",
    "sg:postcode":"59929",
    "sg:province":"Nordrhein-Westfalen",
    "wof:name":"Tuschen",
    "wof:placetype":"venue"
},
  "geometry": {"coordinates":[8.5702314377,51.4021072388],"type":"Point"}
}