{
  "type": "Feature",
  "properties": {
    "iso:country":"DE",
    "sg:address":"Hauptstr. 24",
    "sg:city":"Altusried",
    "sg:phone":"+49 8373/92260",
    "sg:postcode":"87452",
    "sg:province":"Bayern",
    "wof:name":"Josef Morent",
    "wof:placetype":"venue"
},
  "geometry": {"coordinates":[10.2146072388,47.8044166565],"type":"Point"}
}