{
  "type": "Feature",
  "properties": {
    "iso:country":"DE",
    "sg:address":"Richard-Wagner-Str 24",
    "sg:city":"Idar-Oberstein",
    "sg:phone":"+49 6781/43536",
    "sg:postcode":"55743",
    "sg:province":"Rheinland-Pfalz",
    "wof:name":"Rudolf K\u00f6hler",
    "wof:placetype":"venue"
},
  "geometry": {"coordinates":[7.3001151085,49.7189445496],"type":"Point"}
}