{
  "type": "Feature",
  "properties": {
    "iso:country":"DE",
    "sg:address":"Brodberg 5",
    "sg:city":"Sontra",
    "sg:phone":"+49 5653/91363",
    "sg:postcode":"36205",
    "sg:province":"Hessen",
    "wof:name":"H. Hahn",
    "wof:placetype":"venue"
},
  "geometry": {"coordinates":[9.930751,51.061516],"type":"Point"}
}