{
  "type": "Feature",
  "properties": {
    "iso:country":"DE",
    "sg:address":"Treptitzer Str. 9",
    "sg:city":"Cavertitz",
    "sg:phone":"+49 34363/51026",
    "sg:postcode":"04758",
    "sg:province":"Sachsen",
    "wof:name":"Rudolf Stavenow Arzt F\u00fcr Allgemeinmedizin",
    "wof:placetype":"venue"
},
  "geometry": {"coordinates":[13.1288967133,51.3892784119],"type":"Point"}
}