{
  "type": "Feature",
  "properties": {
    "iso:country":"DE",
    "sg:address":"Schiefersteinstr. 73 a",
    "sg:city":"Kellenbach",
    "sg:phone":"+49 6765/1743",
    "sg:postcode":"55606",
    "sg:province":"Rheinland-Pfalz",
    "wof:name":"Fenro Fenstertechnik Gmbh",
    "wof:placetype":"venue"
},
  "geometry": {"coordinates":[7.489888,49.847118],"type":"Point"}
}