{
  "type": "Feature",
  "properties": {
    "iso:country":"DE",
    "sg:address":"Sonnenstr. 54",
    "sg:city":"Gilching",
    "sg:phone":"+49 8105/778060",
    "sg:postcode":"82205",
    "sg:province":"Bayern",
    "wof:name":"Eduard Segerer",
    "wof:placetype":"venue"
},
  "geometry": {"coordinates":[11.286884,48.098804],"type":"Point"}
}