{
  "type": "Feature",
  "properties": {
    "iso:country":"DE",
    "sg:address":"Cloppenburger Str. 9",
    "sg:city":"Molbergen",
    "sg:phone":"+49 4475/947777",
    "sg:postcode":"49696",
    "sg:province":"Niedersachsen",
    "wof:name":"Molberger Reiseb\u00fcro",
    "wof:placetype":"venue"
},
  "geometry": {"coordinates":[7.9236211777,52.858543396],"type":"Point"}
}