{
  "type": "Feature",
  "properties": {
    "iso:country":"DE",
    "sg:address":"Kaje 1",
    "sg:city":"Elsfleth",
    "sg:postcode":"26931",
    "sg:province":"Niedersachsen",
    "wof:name":"Verwaltung Talada Schiffahrtsges. Mbh",
    "wof:placetype":"venue"
},
  "geometry": {"coordinates":[8.4647817612,53.2359962463],"type":"Point"}
}