{
  "type": "Feature",
  "properties": {
    "iso:country":"DE",
    "sg:city":"P\u00e4wesin",
    "sg:postcode":"14778",
    "sg:province":"Brandenburg",
    "wof:name":"Trail Club Brandenburg E.v.",
    "wof:placetype":"venue"
},
  "geometry": {"coordinates":[12.715908,52.511482],"type":"Point"}
}