{
  "type": "Feature",
  "properties": {
    "iso:country":"DE",
    "sg:address":"Ludwigstr. 76",
    "sg:city":"Speyer",
    "sg:postcode":"67346",
    "sg:province":"Rheinland-Pfalz",
    "wof:name":"Bsct Business Software Consulting Und Trading Gmbh",
    "wof:placetype":"venue"
},
  "geometry": {"coordinates":[8.4295053482,49.3128318787],"type":"Point"}
}