{
  "type": "Feature",
  "properties": {
    "iso:country":"DE",
    "sg:address":"Dahlienstr. 13",
    "sg:city":"Bad Kissingen",
    "sg:phone":"+49 971/78050",
    "sg:postcode":"97688",
    "sg:province":"Bayern",
    "wof:name":"Kurt Kleinhenz Gmbh & Co. Kg",
    "wof:placetype":"venue"
},
  "geometry": {"coordinates":[10.100076,50.20573],"type":"Point"}
}