{
  "type": "Feature",
  "properties": {
    "iso:country":"DE",
    "sg:address":"Neusser Str. 59",
    "sg:city":"Bergheim",
    "sg:phone":"+49 2271/41790",
    "sg:postcode":"50126",
    "sg:province":"Nordrhein-Westfalen",
    "wof:name":"D. Hoffmann Masseur",
    "wof:placetype":"venue"
},
  "geometry": {"coordinates":[6.640139,50.962353],"type":"Point"}
}