{
  "type": "Feature",
  "properties": {
    "iso:country":"DE",
    "sg:address":"Boschstr. 4",
    "sg:city":"Kehl",
    "sg:phone":"+49 7851/7034",
    "sg:postcode":"77694",
    "sg:province":"Baden-W\u00fcrttemberg",
    "wof:name":"Falk Gmbh & Co.",
    "wof:placetype":"venue"
},
  "geometry": {"coordinates":[7.838157177,48.5508003235],"type":"Point"}
}