{
  "type": "Feature",
  "properties": {
    "iso:country":"DE",
    "sg:address":"Neue Str. 19",
    "sg:city":"Olbernhau",
    "sg:phone":"+49 37360/75024",
    "sg:postcode":"09526",
    "sg:province":"Sachsen",
    "wof:name":"Beleduc Lernspielwaren Gmbh",
    "wof:placetype":"venue"
},
  "geometry": {"coordinates":[13.3241214752,50.6692390442],"type":"Point"}
}