{
  "type": "Feature",
  "properties": {
    "iso:country":"DE",
    "sg:address":"Kleesbergstr. 4",
    "sg:city":"Borstendorf",
    "sg:phone":"+49 37294/96769",
    "sg:postcode":"09579",
    "sg:province":"Sachsen",
    "wof:name":"R. Schubert",
    "wof:placetype":"venue"
},
  "geometry": {"coordinates":[13.1786336899,50.7746086121],"type":"Point"}
}