{
  "type": "Feature",
  "properties": {
    "iso:country":"DE",
    "sg:address":"Haus Uhlenkotten 8",
    "sg:city":"M\u00fcnster",
    "sg:postcode":"48159",
    "sg:province":"Nordrhein-Westfalen",
    "wof:name":"Dobermann Gmbh & Co.",
    "wof:placetype":"venue"
},
  "geometry": {"coordinates":[7.568293,51.99379],"type":"Point"}
}