{
  "type": "Feature",
  "properties": {
    "iso:country":"DE",
    "sg:address":"Panoramaweg 2",
    "sg:city":"Langenbrettach",
    "sg:phone":"+49 7946/585",
    "sg:postcode":"74243",
    "sg:province":"Baden-W\u00fcrttemberg",
    "wof:name":"Hilmar Rothkegel Architekt",
    "wof:placetype":"venue"
},
  "geometry": {"coordinates":[9.41596,49.215069],"type":"Point"}
}