{
  "type": "Feature",
  "properties": {
    "iso:country":"DE",
    "sg:address":"Erbacher Str. 58",
    "sg:city":"Michelstadt",
    "sg:phone":"+49 6061/3812",
    "sg:postcode":"64720",
    "sg:province":"Hessen",
    "wof:name":"Hallenbad Odenwald",
    "wof:placetype":"venue"
},
  "geometry": {"coordinates":[9.0033845901,49.6705474854],"type":"Point"}
}