{
  "type": "Feature",
  "properties": {
    "iso:country":"DE",
    "sg:address":"K\u00f6lner Str. 113",
    "sg:city":"Solingen",
    "sg:phone":"+49 212/203245",
    "sg:postcode":"42651",
    "sg:province":"Nordrhein-Westfalen",
    "wof:name":"C. R. Heyderhoff Kg Eisenwaren",
    "wof:placetype":"venue"
},
  "geometry": {"coordinates":[7.08288908,51.172000885],"type":"Point"}
}