{
  "type": "Feature",
  "properties": {
    "iso:country":"DE",
    "sg:address":"Alte Schefflenzer Steige 13",
    "sg:city":"Mosbach",
    "sg:phone":"+49 6261/2437",
    "sg:postcode":"74821",
    "sg:province":"Baden-W\u00fcrttemberg",
    "wof:name":"Gerhard Luft",
    "wof:placetype":"venue"
},
  "geometry": {"coordinates":[9.15497,49.356941],"type":"Point"}
}