{
  "type": "Feature",
  "properties": {
    "iso:country":"DE",
    "sg:address":"Bergedorfer Str. 34",
    "sg:city":"Geesthacht",
    "sg:phone":"+49 4152/79536",
    "sg:postcode":"21502",
    "sg:province":"Schleswig-Holstein",
    "wof:name":"Gertrud Weidenbach-oldenburg Krankengymnastin",
    "wof:placetype":"venue"
},
  "geometry": {"coordinates":[10.371389,53.433872],"type":"Point"}
}