{
  "type": "Feature",
  "properties": {
    "iso:country":"DE",
    "sg:address":"Sedanstr. 18",
    "sg:city":"M\u00fcnchen",
    "sg:phone":"+49 89/4480158",
    "sg:postcode":"81667",
    "sg:province":"Bayern",
    "wof:name":"Cafe Fortuna Cafe Und Konditorei",
    "wof:placetype":"venue"
},
  "geometry": {"coordinates":[11.5983324051,48.1296615601],"type":"Point"}
}