{
  "type": "Feature",
  "properties": {
    "iso:country":"DE",
    "sg:address":"Holzweger Str. 54",
    "sg:city":"Attendorn",
    "sg:phone":"+49 2722/51952",
    "sg:postcode":"57439",
    "sg:province":"Nordrhein-Westfalen",
    "wof:name":"Berthold Wacker Inh. Heribert Pulte",
    "wof:placetype":"venue"
},
  "geometry": {"coordinates":[7.9052371979,51.1473731995],"type":"Point"}
}