{
  "type": "Feature",
  "properties": {
    "iso:country":"DE",
    "sg:address":"M\u00fchlhauser Str. 7",
    "sg:city":"Volkertshausen",
    "sg:phone":"+49 7774/382",
    "sg:postcode":"78269",
    "sg:province":"Baden-W\u00fcrttemberg",
    "wof:name":"H. Sapper",
    "wof:placetype":"venue"
},
  "geometry": {"coordinates":[8.859995,47.822887],"type":"Point"}
}