{
  "type": "Feature",
  "properties": {
    "iso:country":"DE",
    "sg:address":"Rote Reihe 2",
    "sg:city":"Garbsen",
    "sg:phone":"+49 5131/477074",
    "sg:postcode":"30827",
    "sg:province":"Niedersachsen",
    "wof:name":"Dirk Rossmann Gmbh",
    "wof:placetype":"venue"
},
  "geometry": {"coordinates":[9.611453,52.436676],"type":"Point"}
}