{
  "type": "Feature",
  "properties": {
    "iso:country":"DE",
    "sg:address":"Zum Wengenwald 26",
    "sg:city":"Heusweiler",
    "sg:phone":"+49 6806/5693",
    "sg:postcode":"66265",
    "sg:province":"Saarland",
    "wof:name":"Rassegefl\u00fcgel-zuchtverein Heusweiler",
    "wof:placetype":"venue"
},
  "geometry": {"coordinates":[6.9255261421,49.3594665527],"type":"Point"}
}