{
  "type": "Feature",
  "properties": {
    "iso:country":"DE",
    "sg:address":"Bahnweg 7",
    "sg:city":"Taufkirchen",
    "sg:phone":"+49 8084/1263",
    "sg:postcode":"84416",
    "sg:province":"Bayern",
    "wof:name":"Josef Huber Planungsb\u00fcro Bauleitungbauunternehmung",
    "wof:placetype":"venue"
},
  "geometry": {"coordinates":[12.131542,48.342373],"type":"Point"}
}