{
  "type": "Feature",
  "properties": {
    "iso:country":"DE",
    "sg:address":"Hasenpfad 29",
    "sg:city":"Damme",
    "sg:phone":"+49 5491/2956",
    "sg:postcode":"49401",
    "sg:province":"Niedersachsen",
    "wof:name":"Friedrich Klausing Baugesch\u00e4fte Gmbh",
    "wof:placetype":"venue"
},
  "geometry": {"coordinates":[8.194081,52.532505],"type":"Point"}
}