{
  "type": "Feature",
  "properties": {
    "iso:country":"DE",
    "sg:address":"Vo\u00dfwinkeler Str.",
    "sg:city":"Arnsberg",
    "sg:postcode":"59757",
    "sg:province":"Nordrhein-Westfalen",
    "wof:name":"Hotel-restaurant Flugplatz",
    "wof:placetype":"venue"
},
  "geometry": {"coordinates":[7.8921060562,51.4684028625],"type":"Point"}
}