{
  "type": "Feature",
  "properties": {
    "iso:country":"DE",
    "sg:address":"Industriestr. 29",
    "sg:city":"Gosheim",
    "sg:phone":"+49 7426/8655",
    "sg:postcode":"78559",
    "sg:province":"Baden-W\u00fcrttemberg",
    "wof:name":"Sigrid Hitzer Krankengymnastin",
    "wof:placetype":"venue"
},
  "geometry": {"coordinates":[8.76942,48.139008],"type":"Point"}
}