{
  "type": "Feature",
  "properties": {
    "iso:country":"DE",
    "sg:address":"Christophstrasse 49",
    "sg:city":"Ueberlingen",
    "sg:phone":"+49 40/3603515713",
    "sg:postcode":"88662",
    "sg:province":"Baden-W\u00fcrttemberg",
    "wof:name":"Astrocohors Science Fiction Made In Europe",
    "wof:placetype":"venue"
},
  "geometry": {"coordinates":[9.158991,47.766972],"type":"Point"}
}