{
  "type": "Feature",
  "properties": {
    "iso:country":"DE",
    "sg:address":"Nr. 46 b",
    "sg:city":"Beiersdorf",
    "sg:postcode":"08435",
    "sg:province":"Brandenburg",
    "wof:name":"Gotthard Andr\u00e4",
    "wof:placetype":"venue"
},
  "geometry": {"coordinates":[-99.11669921879999,19.3833007812],"type":"Point"}
}