{
  "type": "Feature",
  "properties": {
    "iso:country":"DE",
    "sg:address":"Kirchstr. 6",
    "sg:city":"Sieversh\u00fctten",
    "sg:phone":"+49 4194/98340",
    "sg:postcode":"24641",
    "sg:province":"Schleswig-Holstein",
    "wof:name":"Hellmann Und Hellmann-sieg Rechtsanw\u00e4lte",
    "wof:placetype":"venue"
},
  "geometry": {"coordinates":[10.107011795,53.8404350281],"type":"Point"}
}