{
  "type": "Feature",
  "properties": {
    "iso:country":"DE",
    "sg:address":"Messingweg 13",
    "sg:city":"Senden",
    "sg:phone":"+49 2597/96020",
    "sg:postcode":"48308",
    "sg:province":"Nordrhein-Westfalen",
    "wof:name":"Bergmann Engineering Gmbh",
    "wof:placetype":"venue"
},
  "geometry": {"coordinates":[7.4831762314,51.8438644409],"type":"Point"}
}