{
  "type": "Feature",
  "properties": {
    "iso:country":"DE",
    "sg:address":"Rohrstorf",
    "sg:city":"Himbergen",
    "sg:phone":"+49 5828/880",
    "sg:postcode":"29584",
    "sg:province":"Niedersachsen",
    "wof:name":"Hotel-pension Eichenhof Inh. Antje Braesel-behn",
    "wof:placetype":"venue"
},
  "geometry": {"coordinates":[10.7138595581,53.1063308716],"type":"Point"}
}