{
  "type": "Feature",
  "properties": {
    "iso:country":"DE",
    "sg:address":"Kirchstrasse 57",
    "sg:city":"Herne",
    "sg:phone":"+49 2323",
    "sg:postcode":"44627",
    "sg:province":"Nordrhein-Westfalen",
    "wof:name":"Ristorante Da Fernando",
    "wof:placetype":"venue"
},
  "geometry": {"coordinates":[7.259384,51.543331],"type":"Point"}
}