{
  "type": "Feature",
  "properties": {
    "iso:country":"DE",
    "sg:address":"Sonnenweg 1",
    "sg:city":"Bad Hersfeld",
    "sg:phone":"+49 6621/72573",
    "sg:postcode":"36251",
    "sg:province":"Hessen",
    "wof:name":"Fritz K\u00e4berich",
    "wof:placetype":"venue"
},
  "geometry": {"coordinates":[9.7100028992,50.8739089966],"type":"Point"}
}