{
  "type": "Feature",
  "properties": {
    "iso:country":"DE",
    "sg:address":"Bivangweg 14",
    "sg:city":"Jestetten",
    "sg:phone":"+49 7745/96872",
    "sg:postcode":"79798",
    "sg:province":"Baden-W\u00fcrttemberg",
    "wof:name":"G. Kornmaier",
    "wof:placetype":"venue"
},
  "geometry": {"coordinates":[8.5642385483,47.6504936218],"type":"Point"}
}