{
  "type": "Feature",
  "properties": {
    "iso:country":"DE",
    "sg:address":"Karlstr. 19",
    "sg:city":"Ansbach",
    "sg:phone":"+49 981/3949",
    "sg:postcode":"91522",
    "sg:province":"Bayern",
    "wof:name":"M. B\u00fcy\u00fckcetin",
    "wof:placetype":"venue"
},
  "geometry": {"coordinates":[10.5757255554,49.2992706299],"type":"Point"}
}