{
  "type": "Feature",
  "properties": {
    "iso:country":"DE",
    "sg:address":"Industriestr 8-10",
    "sg:city":"Leopoldsh\u00f6he",
    "sg:phone":"+49 5202/2169",
    "sg:postcode":"33818",
    "sg:province":"Nordrhein-Westfalen",
    "wof:name":"Walter Tilleke Gmbh & Co Kg",
    "wof:placetype":"venue"
},
  "geometry": {"coordinates":[8.7091302872,51.9825019836],"type":"Point"}
}