{
  "type": "Feature",
  "properties": {
    "iso:country":"DE",
    "sg:address":"Strahlenberger Str. 1",
    "sg:city":"Schriesheim",
    "sg:phone":"+49 6203/69430",
    "sg:postcode":"69198",
    "sg:province":"Baden-W\u00fcrttemberg",
    "wof:name":"Kreisaltenheim",
    "wof:placetype":"venue"
},
  "geometry": {"coordinates":[8.683327,49.47525],"type":"Point"}
}