{
  "type": "Feature",
  "properties": {
    "iso:country":"DE",
    "sg:address":"Bochumer Str. 155a",
    "sg:city":"Recklinghausen",
    "sg:phone":"+49 2361/71449",
    "sg:postcode":"45661",
    "sg:province":"Nordrhein-Westfalen",
    "wof:name":"Aixtra-sport",
    "wof:placetype":"venue"
},
  "geometry": {"coordinates":[7.212153,51.569874],"type":"Point"}
}