{
  "type": "Feature",
  "properties": {
    "iso:country":"DE",
    "sg:address":"Nienburger Str. 5",
    "sg:city":"Wietze",
    "sg:phone":"+49 5146/2890",
    "sg:postcode":"29323",
    "sg:province":"Niedersachsen",
    "wof:name":"Hl-markt",
    "wof:placetype":"venue"
},
  "geometry": {"coordinates":[9.8388786316,52.6553077698],"type":"Point"}
}