{
  "type": "Feature",
  "properties": {
    "iso:country":"DE",
    "sg:address":"Bahnhofstr. 28 a",
    "sg:city":"Eutin",
    "sg:phone":"+49 4521/706990",
    "sg:postcode":"23701",
    "sg:province":"Schleswig-Holstein",
    "wof:name":"Fabio Fachdienst F\u00fcr Berufliche Integration Ggmbh",
    "wof:placetype":"venue"
},
  "geometry": {"coordinates":[10.6102399826,54.1360054016],"type":"Point"}
}