{
  "type": "Feature",
  "properties": {
    "iso:country":"DE",
    "sg:address":"Ringelhorst 27",
    "sg:city":"Celle",
    "sg:phone":"+49 5141/882770",
    "sg:postcode":"29227",
    "sg:province":"Niedersachsen",
    "wof:name":"Klaus Kruskop",
    "wof:placetype":"venue"
},
  "geometry": {"coordinates":[10.07629,52.597271],"type":"Point"}
}