{
  "type": "Feature",
  "properties": {
    "iso:country":"DE",
    "sg:address":"Am Fischteich 4",
    "sg:city":"Barenburg",
    "sg:phone":"+49 4273/96014",
    "sg:postcode":"27245",
    "sg:province":"Niedersachsen",
    "wof:name":"Die Agentur Werbekonzepte Gmbh",
    "wof:placetype":"venue"
},
  "geometry": {"coordinates":[8.8030099869,52.6180992126],"type":"Point"}
}