{
  "type": "Feature",
  "properties": {
    "iso:country":"DE",
    "sg:address":"B\u00f6gnerweg 1",
    "sg:city":"Offenburg",
    "sg:phone":"+49 781/67202",
    "sg:postcode":"77656",
    "sg:province":"Baden-W\u00fcrttemberg",
    "wof:name":"Herbert Wahl",
    "wof:placetype":"venue"
},
  "geometry": {"coordinates":[7.925620079,48.4651222229],"type":"Point"}
}