{
  "type": "Feature",
  "properties": {
    "iso:country":"DE",
    "sg:address":"Str\u00fcvensiek 1",
    "sg:city":"Rinteln",
    "sg:phone":"+49 5751/2506",
    "sg:postcode":"31737",
    "sg:province":"Niedersachsen",
    "wof:name":"Heinrich Str\u00fcve",
    "wof:placetype":"venue"
},
  "geometry": {"coordinates":[9.087717,52.163403],"type":"Point"}
}