{
  "type": "Feature",
  "properties": {
    "iso:country":"DE",
    "sg:address":"Marktplatz 34",
    "sg:city":"Gunzenhausen",
    "sg:phone":"+49 9831/7484",
    "sg:postcode":"91710",
    "sg:province":"Bayern",
    "wof:name":"Cafe Rohrbach",
    "wof:placetype":"venue"
},
  "geometry": {"coordinates":[10.75438,49.114044],"type":"Point"}
}