{
  "type": "Feature",
  "properties": {
    "iso:country":"DE",
    "sg:address":"Ostpreu\u00dfendamm 151",
    "sg:city":"Berlin",
    "sg:postcode":"12207",
    "sg:province":"Berlin",
    "wof:name":"Stil-haus Das Andere Haus Gmbh",
    "wof:placetype":"venue"
},
  "geometry": {"coordinates":[13.3175506592,52.4267463684],"type":"Point"}
}