{
  "type": "Feature",
  "properties": {
    "iso:country":"DE",
    "sg:address":"Falkenried 84",
    "sg:city":"Hamburg",
    "sg:phone":"+49 40/46777230",
    "sg:postcode":"20251",
    "sg:province":"Hamburg",
    "wof:name":"Musik F\u00fcr Feste Und Festlich- Keiten Heinz Polster E. K.",
    "wof:placetype":"venue"
},
  "geometry": {"coordinates":[9.9724664688,53.5850410461],"type":"Point"}
}