{
  "type": "Feature",
  "properties": {
    "iso:country":"DE",
    "sg:address":"Ortlerstr. 77",
    "sg:city":"Augsburg",
    "sg:phone":"+49 821/64084",
    "sg:postcode":"86163",
    "sg:province":"Bayern",
    "wof:name":"Richter Technik Gmbh",
    "wof:placetype":"venue"
},
  "geometry": {"coordinates":[10.9485378265,48.3495903015],"type":"Point"}
}