{
  "type": "Feature",
  "properties": {
    "iso:country":"DE",
    "sg:address":"Hagener Stra\u00dfe",
    "sg:city":"Gevelsberg",
    "sg:phone":"+49 2332/4054",
    "sg:postcode":"58285",
    "sg:province":"Nordrhein-Westfalen",
    "wof:name":"Classic Line Warenhandels Gmbh",
    "wof:placetype":"venue"
},
  "geometry": {"coordinates":[7.3695597649,51.3298416138],"type":"Point"}
}