{
  "type": "Feature",
  "properties": {
    "iso:country":"DE",
    "sg:address":"Bei Neukreuz 2",
    "sg:city":"Kr\u00f6v",
    "sg:phone":"+49 6541/9513",
    "sg:postcode":"54536",
    "sg:province":"Rheinland-Pfalz",
    "wof:name":"Norbert Diewald",
    "wof:placetype":"venue"
},
  "geometry": {"coordinates":[7.0738229752,49.9756507874],"type":"Point"}
}