{
  "type": "Feature",
  "properties": {
    "iso:country":"DE",
    "sg:address":"Lange Str. 28",
    "sg:city":"Bad Zwischenahn",
    "sg:phone":"+49 4403/2544",
    "sg:postcode":"26160",
    "sg:province":"Niedersachsen",
    "wof:name":"J. Witte Kg",
    "wof:placetype":"venue"
},
  "geometry": {"coordinates":[7.998092,53.184494],"type":"Point"}
}