{
  "type": "Feature",
  "properties": {
    "iso:country":"DE",
    "sg:address":"Hauptstr. 62a",
    "sg:city":"Tennenbronn",
    "sg:phone":"+49 7729/1846",
    "sg:postcode":"78144",
    "sg:province":"Baden-W\u00fcrttemberg",
    "wof:name":"Udo Kuhlmey",
    "wof:placetype":"venue"
},
  "geometry": {"coordinates":[8.3545160294,48.1912002563],"type":"Point"}
}