{
  "type": "Feature",
  "properties": {
    "iso:country":"DE",
    "sg:address":"Kirchplatz 4",
    "sg:city":"Nabburg",
    "sg:phone":"+49 9433/24160",
    "sg:postcode":"92507",
    "sg:province":"Bayern",
    "wof:name":"Arges Gesellschaft F\u00fcr Industrieplanung Und",
    "wof:placetype":"venue"
},
  "geometry": {"coordinates":[12.1798171997,49.4555015564],"type":"Point"}
}