{
  "type": "Feature",
  "properties": {
    "iso:country":"DE",
    "sg:address":"Unnenheimer Weg 4",
    "sg:city":"Rastatt",
    "sg:phone":"+49 7222/17828",
    "sg:postcode":"76437",
    "sg:province":"Baden-W\u00fcrttemberg",
    "wof:name":"Unser",
    "wof:placetype":"venue"
},
  "geometry": {"coordinates":[8.1608076096,48.8836174011],"type":"Point"}
}