{
  "type": "Feature",
  "properties": {
    "iso:country":"DE",
    "sg:address":"Hofackerweg 14",
    "sg:city":"Goldbach",
    "sg:phone":"+49 6021/51568",
    "sg:postcode":"63773",
    "sg:province":"Bayern",
    "wof:name":"Gottfried Beck Elektroinstallation",
    "wof:placetype":"venue"
},
  "geometry": {"coordinates":[9.175098,50.017666],"type":"Point"}
}