{
  "type": "Feature",
  "properties": {
    "iso:country":"DE",
    "sg:address":"August-Schanz-Str. 18",
    "sg:city":"Frankfurt",
    "sg:phone":"+49 69/5480900",
    "sg:postcode":"60433",
    "sg:province":"Hessen",
    "wof:name":"Geb\u00e4udereinigung Gonder Kg",
    "wof:placetype":"venue"
},
  "geometry": {"coordinates":[8.6886234283,50.1625976562],"type":"Point"}
}