{
  "type": "Feature",
  "properties": {
    "iso:country":"DE",
    "sg:address":"Altl\u00e4nder Str. 9",
    "sg:city":"Hamburg",
    "sg:phone":"+49 40/321511",
    "sg:postcode":"20095",
    "sg:province":"Hamburg",
    "wof:name":"Roxx",
    "wof:placetype":"venue"
},
  "geometry": {"coordinates":[10.0071582794,53.5463294983],"type":"Point"}
}