{
  "type": "Feature",
  "properties": {
    "iso:country":"DE",
    "sg:address":"Taunusstr. 14",
    "sg:city":"Ro\u00dfdorf",
    "sg:postcode":"64380",
    "sg:province":"Hessen",
    "wof:name":"Franken Brunnen Stiftung",
    "wof:placetype":"venue"
},
  "geometry": {"coordinates":[8.7498903275,49.8605384827],"type":"Point"}
}