{
  "type": "Feature",
  "properties": {
    "iso:country":"DE",
    "sg:address":"Am Kampbusch 5",
    "sg:city":"Hattingen",
    "sg:phone":"+49 2324/74728",
    "sg:postcode":"45527",
    "sg:province":"Nordrhein-Westfalen",
    "wof:name":"Heinrich Eckey",
    "wof:placetype":"venue"
},
  "geometry": {"coordinates":[7.248715,51.379269],"type":"Point"}
}