{
  "type": "Feature",
  "properties": {
    "iso:country":"DE",
    "sg:address":"Holljestr. 1 c",
    "sg:city":"Edewecht",
    "sg:phone":"+49 4405/8939",
    "sg:postcode":"26188",
    "sg:province":"Niedersachsen",
    "wof:name":"Aktiv-fitness Club Inh E. Schmiemann",
    "wof:placetype":"venue"
},
  "geometry": {"coordinates":[7.9823179245,53.1247024536],"type":"Point"}
}