{
  "type": "Feature",
  "properties": {
    "iso:country":"DE",
    "sg:address":"Ravensburger Str. 3",
    "sg:city":"Bergatreute",
    "sg:phone":"+49 7527/1425",
    "sg:postcode":"88368",
    "sg:province":"Baden-W\u00fcrttemberg",
    "wof:name":"Edmund H\u00e4mmerle",
    "wof:placetype":"venue"
},
  "geometry": {"coordinates":[9.749244,47.848183],"type":"Point"}
}