{
  "type": "Feature",
  "properties": {
    "iso:country":"DE",
    "sg:address":"Bahnhofstr. 30",
    "sg:city":"Delmenhorst",
    "sg:phone":"+49 4221/18135",
    "sg:postcode":"27749",
    "sg:province":"Niedersachsen",
    "wof:name":"Mehmet Baz",
    "wof:placetype":"venue"
},
  "geometry": {"coordinates":[8.630238533,53.0511207581],"type":"Point"}
}