{
  "type": "Feature",
  "properties": {
    "iso:country":"DE",
    "sg:address":"Goethestr. 4",
    "sg:city":"Dahn",
    "sg:phone":"+49 6391/2427",
    "sg:postcode":"66994",
    "sg:province":"Rheinland-Pfalz",
    "wof:name":"Heinz Maurer Steuerberater",
    "wof:placetype":"venue"
},
  "geometry": {"coordinates":[7.7769999504,49.1486282349],"type":"Point"}
}