{
  "type": "Feature",
  "properties": {
    "iso:country":"DE",
    "sg:address":"Plenzer 26",
    "sg:city":"Fl\u00f6rsheim-Dalsheim",
    "sg:phone":"+49 6243/7196",
    "sg:postcode":"67592",
    "sg:province":"Rheinland-Pfalz",
    "wof:name":"Herbert Pfannebecker",
    "wof:placetype":"venue"
},
  "geometry": {"coordinates":[8.2104616165,49.6544265747],"type":"Point"}
}