{
  "type": "Feature",
  "properties": {
    "iso:country":"DE",
    "sg:address":"Westerburger Str. 30",
    "sg:city":"Bad Marienberg",
    "sg:phone":"+49 2661/8840",
    "sg:postcode":"56470",
    "sg:province":"Rheinland-Pfalz",
    "wof:name":"Erwin Giebeler",
    "wof:placetype":"venue"
},
  "geometry": {"coordinates":[7.950273037,50.6346473694],"type":"Point"}
}