{
  "type": "Feature",
  "properties": {
    "iso:country":"DE",
    "sg:address":"Auf dem B\u00fclt 16::",
    "sg:city":"Twist",
    "sg:postcode":"49767",
    "sg:province":"Niedersachsen",
    "wof:name":"Raiffeisenkasse Twist Eg",
    "wof:placetype":"venue"
},
  "geometry": {"coordinates":[7.060876,52.641171],"type":"Point"}
}