{
  "type": "Feature",
  "properties": {
    "iso:country":"DE",
    "sg:address":"Meckenstocker H\u00f6fe 9",
    "sg:city":"Essen",
    "sg:postcode":"45133",
    "sg:province":"Nordrhein-Westfalen",
    "wof:name":"Birken & Birken Verwaltungs- Und Beteiligungs Mbh",
    "wof:placetype":"venue"
},
  "geometry": {"coordinates":[6.979831,51.402626],"type":"Point"}
}