{
  "type": "Feature",
  "properties": {
    "iso:country":"DE",
    "sg:address":"Morezstr. 4",
    "sg:city":"Achern",
    "sg:phone":"+49 7841/9283",
    "sg:postcode":"77855",
    "sg:province":"Baden-W\u00fcrttemberg",
    "wof:name":"Tennishalle",
    "wof:placetype":"venue"
},
  "geometry": {"coordinates":[8.0762844086,48.6351623535],"type":"Point"}
}