{
  "type": "Feature",
  "properties": {
    "iso:country":"DE",
    "sg:address":"Fladderlohausen 135",
    "sg:city":"Holdorf",
    "sg:phone":"+49 5494/510",
    "sg:postcode":"49451",
    "sg:province":"Niedersachsen",
    "wof:name":"Gastst\u00e4tte Hermann Niemann",
    "wof:placetype":"venue"
},
  "geometry": {"coordinates":[8.0879163742,52.5642051697],"type":"Point"}
}