{
  "type": "Feature",
  "properties": {
    "iso:country":"DE",
    "sg:address":"Marktstr. 1",
    "sg:city":"J\u00fclich",
    "sg:phone":"+49 2461/58225",
    "sg:postcode":"52428",
    "sg:province":"Nordrhein-Westfalen",
    "wof:name":"City-spieltreff",
    "wof:placetype":"venue"
},
  "geometry": {"coordinates":[6.3581771851,50.9215621948],"type":"Point"}
}