{
  "type": "Feature",
  "properties": {
    "iso:country":"DE",
    "sg:address":"Hugenottenallee 152",
    "sg:city":"Neu-Isenburg",
    "sg:phone":"+49 6102/25533",
    "sg:postcode":"63263",
    "sg:province":"Hessen",
    "wof:name":"Josef G\u00f6ppner",
    "wof:placetype":"venue"
},
  "geometry": {"coordinates":[8.6891145706,50.0470275879],"type":"Point"}
}