{
  "type": "Feature",
  "properties": {
    "iso:country":"DE",
    "sg:address":"Alter Postweg 10::",
    "sg:city":"Suderburg",
    "sg:phone":"+49 5826/967312",
    "sg:postcode":"29556",
    "sg:province":"Niedersachsen",
    "wof:name":"Gerep Gmbh",
    "wof:placetype":"venue"
},
  "geometry": {"coordinates":[10.4377250671,52.9041213989],"type":"Point"}
}