{
  "type": "Feature",
  "properties": {
    "iso:country":"DE",
    "sg:address":"Friedrich-Engels-Str. 10",
    "sg:city":"Bremen",
    "sg:phone":"+49 421/833090",
    "sg:postcode":"28279",
    "sg:province":"Bremen",
    "wof:name":"Heinrich H\u00fclsemeyer",
    "wof:placetype":"venue"
},
  "geometry": {"coordinates":[8.851924,53.047001],"type":"Point"}
}