{
  "type": "Feature",
  "properties": {
    "iso:country":"DE",
    "sg:address":"R\u00fclzheimer Str. 4",
    "sg:city":"Bellheim",
    "sg:phone":"+49 7272/5339",
    "sg:postcode":"76756",
    "sg:province":"Rheinland-Pfalz",
    "wof:name":"M\u00fcller",
    "wof:placetype":"venue"
},
  "geometry": {"coordinates":[8.2839717865,49.1904602051],"type":"Point"}
}