{
  "type": "Feature",
  "properties": {
    "iso:country":"DE",
    "sg:address":"Hauptstr. 55",
    "sg:city":"Bad Saulgau",
    "sg:phone":"+49 7581/8738",
    "sg:postcode":"88348",
    "sg:province":"Baden-W\u00fcrttemberg",
    "wof:name":"Drei K\u00f6nig",
    "wof:placetype":"venue"
},
  "geometry": {"coordinates":[9.5002994537,48.0169487],"type":"Point"}
}