{
  "type": "Feature",
  "properties": {
    "iso:country":"DE",
    "sg:address":"Frankfurter Str. 58",
    "sg:city":"Bad Rothenfelde",
    "sg:phone":"+49 5424/1394",
    "sg:postcode":"49214",
    "sg:province":"Niedersachsen",
    "wof:name":"Siegwart Clau\u00df Architekt",
    "wof:placetype":"venue"
},
  "geometry": {"coordinates":[8.164347,52.10284],"type":"Point"}
}