{
  "type": "Feature",
  "properties": {
    "iso:country":"DE",
    "sg:address":"Siegburger Str. 104",
    "sg:city":"K\u00f6ln",
    "sg:phone":"+49 221/884409",
    "sg:postcode":"50679",
    "sg:province":"Nordrhein-Westfalen",
    "wof:name":"Ruland Transport Und Lagerung Brigitte Ruland",
    "wof:placetype":"venue"
},
  "geometry": {"coordinates":[6.9766988754,50.9265823364],"type":"Point"}
}