{
  "type": "Feature",
  "properties": {
    "iso:country":"DE",
    "sg:address":"S\u00fcdwall 12 a",
    "sg:city":"Celle",
    "sg:phone":"+49 5141/905026",
    "sg:postcode":"29221",
    "sg:province":"Niedersachsen",
    "wof:name":"Hotel Atlantik",
    "wof:placetype":"venue"
},
  "geometry": {"coordinates":[10.0853214264,52.6229553223],"type":"Point"}
}