{
  "type": "Feature",
  "properties": {
    "iso:country":"DE",
    "sg:address":"Karl-Marx-Str. 19",
    "sg:city":"Baasdorf",
    "sg:phone":"+49 3496/558389",
    "sg:postcode":"06388",
    "sg:province":"Sachsen-Anhalt",
    "wof:name":"B. Ermisch",
    "wof:placetype":"venue"
},
  "geometry": {"coordinates":[11.982211,51.708324],"type":"Point"}
}