{
  "type": "Feature",
  "properties": {
    "iso:country":"DE",
    "sg:address":"Zemmerer Str. 17",
    "sg:city":"Orenhofen",
    "sg:phone":"+49 6580/274",
    "sg:postcode":"54298",
    "sg:province":"Rheinland-Pfalz",
    "wof:name":"Albert Berg",
    "wof:placetype":"venue"
},
  "geometry": {"coordinates":[6.653189,49.896332],"type":"Point"}
}