{
  "type": "Feature",
  "properties": {
    "iso:country":"DE",
    "sg:address":"Auguststr. 33",
    "sg:city":"Bonn",
    "sg:phone":"+49 228/4298700",
    "sg:postcode":"53229",
    "sg:province":"Nordrhein-Westfalen",
    "wof:name":"Scharrenbach & Thelen Gmbh",
    "wof:placetype":"venue"
},
  "geometry": {"coordinates":[7.128833,50.742752],"type":"Point"}
}