{
  "type": "Feature",
  "properties": {
    "iso:country":"DE",
    "sg:address":"Am B\u00fcchl 2",
    "sg:city":"Oberhaching",
    "sg:phone":"+49 89/6132236",
    "sg:postcode":"82041",
    "sg:province":"Bayern",
    "wof:name":"Franzika Schwarz",
    "wof:placetype":"venue"
},
  "geometry": {"coordinates":[11.6028671265,48.0239562988],"type":"Point"}
}