{
  "type": "Feature",
  "properties": {
    "iso:country":"DE",
    "sg:address":"Im Eichensiek 2",
    "sg:city":"L\u00fcbbecke",
    "sg:phone":"+49 5741/370169",
    "sg:postcode":"32312",
    "sg:province":"Nordrhein-Westfalen",
    "wof:name":"Pries Rolladenbau- Verwaltungs- Gmbh",
    "wof:placetype":"venue"
},
  "geometry": {"coordinates":[8.693828,52.300381],"type":"Point"}
}