{
  "type": "Feature",
  "properties": {
    "iso:country":"DE",
    "sg:address":"Landsberger Allee 131c",
    "sg:city":"Berlin",
    "sg:phone":"+49 30/4253759",
    "sg:postcode":"10369",
    "sg:province":"Berlin",
    "wof:name":"Awg Industrieanlagen Und Wassertechnik Gmbh",
    "wof:placetype":"venue"
},
  "geometry": {"coordinates":[13.4622449875,52.530166626],"type":"Point"}
}