{
  "type": "Feature",
  "properties": {
    "iso:country":"DE",
    "sg:address":"Weingartenstr. 40",
    "sg:city":"Lahr",
    "sg:phone":"+49 7821/30779",
    "sg:postcode":"77933",
    "sg:province":"Baden-W\u00fcrttemberg",
    "wof:name":"Kupferkessel",
    "wof:placetype":"venue"
},
  "geometry": {"coordinates":[7.8595581055,48.3136062622],"type":"Point"}
}