{
  "type": "Feature",
  "properties": {
    "iso:country":"DE",
    "sg:address":"Industriestr. 12",
    "sg:city":"Lienen",
    "sg:phone":"+49 4954/83315",
    "sg:postcode":"49536",
    "sg:province":"Nordrhein-Westfalen",
    "wof:name":"Metallgiesserei Peters Gmbh",
    "wof:placetype":"venue"
},
  "geometry": {"coordinates":[7.981865,52.148933],"type":"Point"}
}