{
  "type": "Feature",
  "properties": {
    "iso:country":"DE",
    "sg:address":"Raiffeisenstr. 1",
    "sg:city":"Langenfeld",
    "sg:phone":"+49 2173/97440",
    "sg:postcode":"40764",
    "sg:province":"Nordrhein-Westfalen",
    "wof:name":"K\u00fcrten M\u00f6belcenter Gmbh",
    "wof:placetype":"venue"
},
  "geometry": {"coordinates":[6.922466,51.121647],"type":"Point"}
}