{
  "type": "Feature",
  "properties": {
    "iso:country":"DE",
    "sg:address":"Klausenerplatz 4",
    "sg:city":"Berlin",
    "sg:phone":"+49 30",
    "sg:postcode":"14059",
    "sg:province":"Berlin",
    "wof:name":"Arabische Kultur, Reisen, Grafik, Naturheilkunde",
    "wof:placetype":"venue"
},
  "geometry": {"coordinates":[13.292767,52.518456],"type":"Point"}
}