{
  "type": "Feature",
  "properties": {
    "iso:country":"DE",
    "sg:address":"Gerberstr. 6",
    "sg:city":"Weimar",
    "sg:phone":"+49 3643/903739",
    "sg:postcode":"99423",
    "sg:province":"Th\u00fcringen",
    "wof:name":"Liane Dathe",
    "wof:placetype":"venue"
},
  "geometry": {"coordinates":[11.3324165344,50.9819755554],"type":"Point"}
}