{
  "type": "Feature",
  "properties": {
    "iso:country":"DE",
    "sg:address":"Neuendamm 1-3",
    "sg:city":"Cloppenburg",
    "sg:postcode":"49661",
    "sg:province":"Niedersachsen",
    "wof:name":"Willi Wewer",
    "wof:placetype":"venue"
},
  "geometry": {"coordinates":[7.9990282059,52.8283309937],"type":"Point"}
}