{
  "type": "Feature",
  "properties": {
    "iso:country":"DE",
    "sg:address":"Am M\u00fchlberg 1",
    "sg:city":"Tann",
    "sg:phone":"+49 4966/8296180",
    "sg:postcode":"36142",
    "sg:province":"Hessen",
    "wof:name":"Johann Ulrich Gmbh & Co. Kg Metallbe- U. Verarbeitung",
    "wof:placetype":"venue"
},
  "geometry": {"coordinates":[10.025143,50.648354],"type":"Point"}
}