{
  "type": "Feature",
  "properties": {
    "iso:country":"DE",
    "sg:address":"Heideweg 2",
    "sg:city":"Lichtenau",
    "sg:phone":"+49 5259/637",
    "sg:postcode":"33165",
    "sg:province":"Nordrhein-Westfalen",
    "wof:name":"Erhard R\u00fccker",
    "wof:placetype":"venue"
},
  "geometry": {"coordinates":[8.941395,51.675022],"type":"Point"}
}