{
  "type": "Feature",
  "properties": {
    "iso:country":"DE",
    "sg:address":"Hauptstr. 39",
    "sg:city":"Meerbusch",
    "sg:phone":"+49 2150/3942",
    "sg:postcode":"40668",
    "sg:province":"Nordrhein-Westfalen",
    "wof:name":"M. Dammer",
    "wof:placetype":"venue"
},
  "geometry": {"coordinates":[6.6806731224,51.3034439087],"type":"Point"}
}