{
  "type": "Feature",
  "properties": {
    "iso:country":"DE",
    "sg:address":"L\u00e4rchenhain 5",
    "sg:city":"Wegberg",
    "sg:phone":"+49 2434/4766",
    "sg:postcode":"41844",
    "sg:province":"Nordrhein-Westfalen",
    "wof:name":"Heka Industriebedarf Und Verpackungen E. K.",
    "wof:placetype":"venue"
},
  "geometry": {"coordinates":[6.29014,51.140156],"type":"Point"}
}