{
  "type": "Feature",
  "properties": {
    "iso:country":"DE",
    "sg:address":"Seminargasse 11",
    "sg:city":"Straubing",
    "sg:phone":"+49 9421/80101",
    "sg:postcode":"94315",
    "sg:province":"Bayern",
    "wof:name":"Georg G\u00f6ttlinger",
    "wof:placetype":"venue"
},
  "geometry": {"coordinates":[12.568944,48.881889],"type":"Point"}
}