{
  "type": "Feature",
  "properties": {
    "iso:country":"DE",
    "sg:address":"Deutsch-Ritter-Allee 10",
    "sg:city":"Grevenbroich",
    "sg:phone":"+49 2181/499344",
    "sg:postcode":"41515",
    "sg:province":"Nordrhein-Westfalen",
    "wof:name":"Braust\u00fcbl",
    "wof:placetype":"venue"
},
  "geometry": {"coordinates":[6.5661149025,51.0918769836],"type":"Point"}
}