{
  "type": "Feature",
  "properties": {
    "iso:country":"DE",
    "sg:address":"Allg\u00e4uer Str. 36",
    "sg:city":"Memmingen",
    "sg:phone":"+49 8331/5060",
    "sg:postcode":"87700",
    "sg:province":"Bayern",
    "wof:name":"Andrea Kutter Gmbh",
    "wof:placetype":"venue"
},
  "geometry": {"coordinates":[10.1821689606,47.9710197449],"type":"Point"}
}