{
  "type": "Feature",
  "properties": {
    "iso:country":"DE",
    "sg:address":"Eulbacher Str. 34",
    "sg:city":"L\u00fctzelbach",
    "sg:phone":"+49 6165/3363",
    "sg:postcode":"64750",
    "sg:province":"Hessen",
    "wof:name":"Bernd Olt",
    "wof:placetype":"venue"
},
  "geometry": {"coordinates":[9.074364,49.765095],"type":"Point"}
}