{
  "type": "Feature",
  "properties": {
    "iso:country":"DE",
    "sg:address":"Unterri\u00dfdorfer Str.",
    "sg:city":"Lutherstadt Eisleben",
    "sg:phone":"+49 3475/65090",
    "sg:postcode":"06295",
    "sg:province":"Sachsen-Anhalt",
    "wof:name":"Landesgut Pflanzenproduktion Obstbau Eisleben",
    "wof:placetype":"venue"
},
  "geometry": {"coordinates":[11.583902,51.508099],"type":"Point"}
}