{
  "type": "Feature",
  "properties": {
    "iso:country":"DE",
    "sg:address":"\u00c4u\u00dfere Uferstr. 175",
    "sg:city":"Augsburg",
    "sg:phone":"+49 821/416608",
    "sg:postcode":"86154",
    "sg:province":"Bayern",
    "wof:name":"Erwin B\u00f6ld Flaschengrosshandel",
    "wof:placetype":"venue"
},
  "geometry": {"coordinates":[10.8868541718,48.4022903442],"type":"Point"}
}