{
  "type": "Feature",
  "properties": {
    "iso:country":"DE",
    "sg:address":"Strandstr. 18",
    "sg:city":"Norderney",
    "sg:phone":"+49 4932/1494",
    "sg:postcode":"26548",
    "sg:province":"Niedersachsen",
    "wof:name":"G\u00e4stehaus Ferienhaus Irina",
    "wof:placetype":"venue"
},
  "geometry": {"coordinates":[7.1416869164,53.705368042],"type":"Point"}
}