{
  "type": "Feature",
  "properties": {
    "iso:country":"DE",
    "sg:address":"Giebelstr. 11c",
    "sg:city":"Stuttgart",
    "sg:phone":"+49 711/865436",
    "sg:postcode":"70499",
    "sg:province":"Baden-W\u00fcrttemberg",
    "wof:name":"R. Brahmann Augenoptiker",
    "wof:placetype":"venue"
},
  "geometry": {"coordinates":[9.0918445587,48.8036499023],"type":"Point"}
}