{
  "type": "Feature",
  "properties": {
    "iso:country":"DE",
    "sg:address":"Vilbeler Landstr. 144",
    "sg:city":"Frankfurt",
    "sg:phone":"+49 69/479185",
    "sg:postcode":"60388",
    "sg:province":"Hessen",
    "wof:name":"Pax Instruments",
    "wof:placetype":"venue"
},
  "geometry": {"coordinates":[8.7425899506,50.149471283],"type":"Point"}
}