{
  "type": "Feature",
  "properties": {
    "iso:country":"DE",
    "sg:address":"Am Gro\u00dfen Tief 17",
    "sg:city":"Moormerland",
    "sg:phone":"+49 4924/1825",
    "sg:postcode":"26802",
    "sg:province":"Niedersachsen",
    "wof:name":"Carsten M\u00fcller",
    "wof:placetype":"venue"
},
  "geometry": {"coordinates":[7.338080883,53.3284568787],"type":"Point"}
}