{
  "type": "Feature",
  "properties": {
    "iso:country":"DE",
    "sg:address":"Wildtaubenweg 4",
    "sg:city":"M\u00f6lln",
    "sg:phone":"+49 4542/2073",
    "sg:postcode":"23879",
    "sg:province":"Schleswig-Holstein",
    "wof:name":"Veronika Werner Heilpraktikerin",
    "wof:placetype":"venue"
},
  "geometry": {"coordinates":[10.6906995773,53.5939712524],"type":"Point"}
}