{
  "type": "Feature",
  "properties": {
    "iso:country":"DE",
    "sg:address":"Hauptstr. 26",
    "sg:city":"Apen",
    "sg:phone":"+49 4499/476",
    "sg:postcode":"26689",
    "sg:province":"Niedersachsen",
    "wof:name":"Wilfried Borchers",
    "wof:placetype":"venue"
},
  "geometry": {"coordinates":[7.837526,53.227585],"type":"Point"}
}