{
  "type": "Feature",
  "properties": {
    "iso:country":"DE",
    "sg:address":"Sch\u00f6nberger Str. 11",
    "sg:city":"Kiel",
    "sg:phone":"+49 431/7206300",
    "sg:postcode":"24148",
    "sg:province":"Schleswig-Holstein",
    "wof:name":"Praxisklinik Kiel Verwaltungsgesellschaft Mbh",
    "wof:placetype":"venue"
},
  "geometry": {"coordinates":[10.186028,54.325951],"type":"Point"}
}