{
  "type": "Feature",
  "properties": {
    "iso:country":"DE",
    "sg:address":"M\u00f6lmerhagen",
    "sg:city":"Alfeld",
    "sg:phone":"+49 5181/25306",
    "sg:postcode":"31061",
    "sg:province":"Niedersachsen",
    "wof:name":"K. Schewior",
    "wof:placetype":"venue"
},
  "geometry": {"coordinates":[9.8718547821,51.9589538574],"type":"Point"}
}