{
  "type": "Feature",
  "properties": {
    "iso:country":"DE",
    "sg:address":"Hohenzollernstr. 2",
    "sg:city":"Dortmund",
    "sg:phone":"+49 4923/154040",
    "sg:postcode":"44135",
    "sg:province":"Nordrhein-Westfalen",
    "wof:name":"Leue & Nill Gmbh & Co",
    "wof:placetype":"venue"
},
  "geometry": {"coordinates":[7.477505,51.513332],"type":"Point"}
}