{
  "type": "Feature",
  "properties": {
    "iso:country":"DE",
    "sg:address":"Buchenauer Weg 2",
    "sg:city":"Haunetal",
    "sg:phone":"+49 6673/382",
    "sg:postcode":"36166",
    "sg:province":"Hessen",
    "wof:name":"H. Ruppel",
    "wof:placetype":"venue"
},
  "geometry": {"coordinates":[9.69849,50.772125],"type":"Point"}
}