{
  "type": "Feature",
  "properties": {
    "iso:country":"DE",
    "sg:address":"Quirinstr. 9",
    "sg:city":"D\u00fcsseldorf",
    "sg:phone":"+49 211/576570",
    "sg:postcode":"40545",
    "sg:province":"Nordrhein-Westfalen",
    "wof:name":"Janne Pawig",
    "wof:placetype":"venue"
},
  "geometry": {"coordinates":[6.748699,51.23238],"type":"Point"}
}