{
  "type": "Feature",
  "properties": {
    "iso:country":"DE",
    "sg:address":"Waldstr. 170",
    "sg:city":"Neu-Isenburg",
    "sg:phone":"+49 6102/23575",
    "sg:postcode":"63263",
    "sg:province":"Hessen",
    "wof:name":"La Bustique Nicole Praun",
    "wof:placetype":"venue"
},
  "geometry": {"coordinates":[8.692097,50.048794],"type":"Point"}
}