{
  "type": "Feature",
  "properties": {
    "iso:country":"DE",
    "sg:address":"Adalbertstr. 11",
    "sg:city":"Frankfurt",
    "sg:phone":"+49 69/778795",
    "sg:postcode":"60486",
    "sg:province":"Hessen",
    "wof:name":"C. Topp",
    "wof:placetype":"venue"
},
  "geometry": {"coordinates":[8.647895813,50.1197776794],"type":"Point"}
}