{
  "type": "Feature",
  "properties": {
    "iso:country":"DE",
    "sg:address":"Bungsbergstr. 30",
    "sg:city":"Wangels",
    "sg:phone":"+49 4382/380",
    "sg:postcode":"23758",
    "sg:province":"Schleswig-Holstein",
    "wof:name":"H. Pitzschel",
    "wof:placetype":"venue"
},
  "geometry": {"coordinates":[10.749546,54.252289],"type":"Point"}
}