{
  "type": "Feature",
  "properties": {
    "iso:country":"DE",
    "sg:address":"Carolus-Magnus-Str. 87",
    "sg:city":"Essen",
    "sg:phone":"+49 201/634010",
    "sg:postcode":"45356",
    "sg:province":"Nordrhein-Westfalen",
    "wof:name":"A. Sommer Immobilien Und Beteiligungs Gmbh",
    "wof:placetype":"venue"
},
  "geometry": {"coordinates":[6.9679708481,51.4843063354],"type":"Point"}
}