{
  "type": "Feature",
  "properties": {
    "iso:country":"DE",
    "sg:address":"Leutkirchstr. 16",
    "sg:city":"Gengenbach",
    "sg:phone":"+49 7803/4387",
    "sg:postcode":"77723",
    "sg:province":"Baden-W\u00fcrttemberg",
    "wof:name":"Brauerei Willmann",
    "wof:placetype":"venue"
},
  "geometry": {"coordinates":[8.0122756958,48.4046783447],"type":"Point"}
}