{
  "type": "Feature",
  "properties": {
    "iso:country":"DE",
    "sg:address":"Sandberg 102",
    "sg:city":"Elmshorn",
    "sg:phone":"+49 4121/2940",
    "sg:postcode":"25335",
    "sg:province":"Schleswig-Holstein",
    "wof:name":"Alten- Und Pflegeheim Haus Elbmarsch",
    "wof:placetype":"venue"
},
  "geometry": {"coordinates":[9.639241,53.754143],"type":"Point"}
}