{
  "type": "Feature",
  "properties": {
    "iso:country":"DE",
    "sg:address":"Sch\u00f6nbergstr. 64",
    "sg:city":"Sonneberg",
    "sg:phone":"+49 3675/46400",
    "sg:postcode":"96515",
    "sg:province":"Th\u00fcringen",
    "wof:name":"G. Und K.-j. Gelbricht Architekten",
    "wof:placetype":"venue"
},
  "geometry": {"coordinates":[11.186153,50.359959],"type":"Point"}
}