{
  "type": "Feature",
  "properties": {
    "iso:country":"DE",
    "sg:address":"Bl\u00fccherstr. 49",
    "sg:city":"D\u00fcsseldorf",
    "sg:phone":"+49 211/444729",
    "sg:postcode":"40477",
    "sg:province":"Nordrhein-Westfalen",
    "wof:name":"B\u00e4rbel Spallek",
    "wof:placetype":"venue"
},
  "geometry": {"coordinates":[6.7835588455,51.2383575439],"type":"Point"}
}