{
  "type": "Feature",
  "properties": {
    "iso:country":"DE",
    "sg:address":"Wesselinger Str. 12",
    "sg:city":"Pulheim",
    "sg:phone":"+49 2238/7576",
    "sg:postcode":"50259",
    "sg:province":"Nordrhein-Westfalen",
    "wof:name":"Dr. U. Janus Ingenieur",
    "wof:placetype":"venue"
},
  "geometry": {"coordinates":[6.770316124,50.9867210388],"type":"Point"}
}