{
  "type": "Feature",
  "properties": {
    "iso:country":"DE",
    "sg:address":"St.-Emmeran-Str. 2",
    "sg:city":"Aichach",
    "sg:phone":"+49 8251/3752",
    "sg:postcode":"86551",
    "sg:province":"Bayern",
    "wof:name":"Josef Winter",
    "wof:placetype":"venue"
},
  "geometry": {"coordinates":[11.109077,48.446682],"type":"Point"}
}