{
  "type": "Feature",
  "properties": {
    "iso:country":"DE",
    "sg:address":"Brackeler Hellweg 111",
    "sg:city":"Dortmund",
    "sg:phone":"+49 231/255481",
    "sg:postcode":"44309",
    "sg:province":"Nordrhein-Westfalen",
    "wof:name":"Augenoptik Reinecke Gmbh",
    "wof:placetype":"venue"
},
  "geometry": {"coordinates":[7.5436091423,51.5230674744],"type":"Point"}
}