{
  "type": "Feature",
  "properties": {
    "iso:country":"DE",
    "sg:address":"Glauchauer Str. 49",
    "sg:city":"St. Egidien",
    "sg:phone":"+49 37204/2462",
    "sg:postcode":"09356",
    "sg:province":"Sachsen",
    "wof:name":"Gerhard Maryska",
    "wof:placetype":"venue"
},
  "geometry": {"coordinates":[12.608203,50.789413],"type":"Point"}
}