{
  "type": "Feature",
  "properties": {
    "iso:country":"DE",
    "sg:address":"Zwickauer Str. 31",
    "sg:city":"Lengenfeld",
    "sg:phone":"+49 37606/3136",
    "sg:postcode":"08485",
    "sg:province":"Sachsen",
    "wof:name":"R. Lang",
    "wof:placetype":"venue"
},
  "geometry": {"coordinates":[12.373929,50.574482],"type":"Point"}
}