{
  "type": "Feature",
  "properties": {
    "iso:country":"DE",
    "sg:address":"Anrather Str. 21",
    "sg:city":"Krefeld",
    "sg:phone":"+49 2151/30920",
    "sg:postcode":"47807",
    "sg:province":"Nordrhein-Westfalen",
    "wof:name":"Wilfried Oelschl\u00e4gel Steuerberater",
    "wof:placetype":"venue"
},
  "geometry": {"coordinates":[6.5870370865,51.3041229248],"type":"Point"}
}