{
  "type": "Feature",
  "properties": {
    "iso:country":"DE",
    "sg:address":"Mondstr. 2-4",
    "sg:city":"Feldkirchen",
    "sg:phone":"+49 89/9004750",
    "sg:postcode":"85622",
    "sg:province":"Bayern",
    "wof:name":"Mondstra\u00dfe Verlag-holding Gmbh & Co. Kg",
    "wof:placetype":"venue"
},
  "geometry": {"coordinates":[11.7335805893,48.15026474],"type":"Point"}
}