{
  "type": "Feature",
  "properties": {
    "iso:country":"DE",
    "sg:address":"Ringstr. 2",
    "sg:city":"Weingarten",
    "sg:phone":"+49 7244/2459",
    "sg:postcode":"76356",
    "sg:province":"Baden-W\u00fcrttemberg",
    "wof:name":"Freibad",
    "wof:placetype":"venue"
},
  "geometry": {"coordinates":[8.5311384201,49.0533065796],"type":"Point"}
}