{
  "type": "Feature",
  "properties": {
    "iso:country":"DE",
    "sg:address":"Horststr. 17",
    "sg:city":"Steinhagen",
    "sg:phone":"+49 5204/1040",
    "sg:postcode":"33803",
    "sg:province":"Nordrhein-Westfalen",
    "wof:name":"H\u00f6rmann Kg",
    "wof:placetype":"venue"
},
  "geometry": {"coordinates":[8.340724,51.986359],"type":"Point"}
}