{
  "type": "Feature",
  "properties": {
    "iso:country":"DE",
    "sg:address":"Marienstr. 10A",
    "sg:city":"Traunstein",
    "sg:phone":"+49 861/7456",
    "sg:postcode":"83278",
    "sg:province":"Bayern",
    "wof:name":"Optello Optik Ohg",
    "wof:placetype":"venue"
},
  "geometry": {"coordinates":[12.6445503235,47.8687171936],"type":"Point"}
}