{
  "type": "Feature",
  "properties": {
    "iso:country":"DE",
    "sg:address":"Markt 15",
    "sg:city":"Schlotheim",
    "sg:phone":"+49 36021/81030",
    "sg:postcode":"99994",
    "sg:province":"Th\u00fcringen",
    "wof:name":"Michael Hense Rechtsanwalt",
    "wof:placetype":"venue"
},
  "geometry": {"coordinates":[10.6565189362,51.2469100952],"type":"Point"}
}