{
  "type": "Feature",
  "properties": {
    "iso:country":"DE",
    "sg:address":"Berkaer Str. 39",
    "sg:city":"Berlin",
    "sg:postcode":"14199",
    "sg:province":"Berlin",
    "wof:name":"Sarplan Bauplanung Gmbh",
    "wof:placetype":"venue"
},
  "geometry": {"coordinates":[13.2878236771,52.4772453308],"type":"Point"}
}