{
  "type": "Feature",
  "properties": {
    "iso:country":"DE",
    "sg:address":"Horner Weg 17",
    "sg:city":"Hamburg",
    "sg:phone":"+49 40/484983",
    "sg:postcode":"20535",
    "sg:province":"Hamburg",
    "wof:name":"Schachfreunde Hamburg Von 1934 E. V.",
    "wof:placetype":"venue"
},
  "geometry": {"coordinates":[10.0584583282,53.5561790466],"type":"Point"}
}