{
  "type": "Feature",
  "properties": {
    "iso:country":"DE",
    "sg:address":"Rathausstr. 20",
    "sg:city":"Mainz",
    "sg:phone":"+49 6131/34834",
    "sg:postcode":"55128",
    "sg:province":"Rheinland-Pfalz",
    "wof:name":"Dieter Miesem Drogerie",
    "wof:placetype":"venue"
},
  "geometry": {"coordinates":[8.244575,49.981506],"type":"Point"}
}