{
  "type": "Feature",
  "properties": {
    "iso:country":"DE",
    "sg:address":"Am M\u00fchlenbach 12",
    "sg:city":"Greven",
    "sg:phone":"+49 2571/4257",
    "sg:postcode":"48268",
    "sg:province":"Nordrhein-Westfalen",
    "wof:name":"Engelbert Parnitzke",
    "wof:placetype":"venue"
},
  "geometry": {"coordinates":[7.571731,52.097588],"type":"Point"}
}