{
  "type": "Feature",
  "properties": {
    "iso:country":"DE",
    "sg:address":"Am Hasselt 7",
    "sg:city":"Hoppst\u00e4dten-Weiersbach",
    "sg:phone":"+49 6782/2263",
    "sg:postcode":"55768",
    "sg:province":"Rheinland-Pfalz",
    "wof:name":"Hotel Waldesruh",
    "wof:placetype":"venue"
},
  "geometry": {"coordinates":[7.1661829948,49.6052055359],"type":"Point"}
}