{
  "type": "Feature",
  "properties": {
    "iso:country":"DE",
    "sg:address":"Neuer Weg 7",
    "sg:city":"Neschwitz",
    "sg:phone":"+49 35933/30663",
    "sg:postcode":"02699",
    "sg:province":"Sachsen",
    "wof:name":"Druckerei Delany Ciscernja Gmbh",
    "wof:placetype":"venue"
},
  "geometry": {"coordinates":[14.3272304535,51.2694892883],"type":"Point"}
}