{
  "type": "Feature",
  "properties": {
    "iso:country":"DE",
    "sg:address":"Werderstr. 84",
    "sg:city":"Sinsheim",
    "sg:phone":"+49 4972/616950",
    "sg:postcode":"74889",
    "sg:province":"Baden-W\u00fcrttemberg",
    "wof:name":"Werkzeugmaschinenbau Sinsheim Gmbh",
    "wof:placetype":"venue"
},
  "geometry": {"coordinates":[8.866914,49.25811],"type":"Point"}
}