{
  "type": "Feature",
  "properties": {
    "iso:country":"DE",
    "sg:address":"Teltower Damm 25",
    "sg:city":"Berlin",
    "sg:phone":"+49 30/8118866",
    "sg:postcode":"14169",
    "sg:province":"Berlin",
    "wof:name":"Ingrid Demski",
    "wof:placetype":"venue"
},
  "geometry": {"coordinates":[13.259475708,52.4325904846],"type":"Point"}
}