{
  "type": "Feature",
  "properties": {
    "iso:country":"DE",
    "sg:address":"Hauptstr. 161",
    "sg:city":"Hemer",
    "sg:phone":"+49 2372/12192",
    "sg:postcode":"58675",
    "sg:province":"Nordrhein-Westfalen",
    "wof:name":"G. Webers",
    "wof:placetype":"venue"
},
  "geometry": {"coordinates":[7.767343998,51.3828315735],"type":"Point"}
}