{
  "type": "Feature",
  "properties": {
    "iso:country":"DE",
    "sg:address":"Goldammerweg 3",
    "sg:city":"Leipzig",
    "sg:phone":"+49 341/4614249",
    "sg:postcode":"04159",
    "sg:province":"Sachsen",
    "wof:name":"Dr. Med. Sigrid Gl\u00fcck",
    "wof:placetype":"venue"
},
  "geometry": {"coordinates":[12.326139,51.382236],"type":"Point"}
}