{
  "type": "Feature",
  "properties": {
    "iso:country":"DE",
    "sg:address":"Berxer Marschbruch 16",
    "sg:city":"Bruchhausen-Vilsen",
    "sg:phone":"+49 4252/2635",
    "sg:postcode":"27305",
    "sg:province":"Niedersachsen",
    "wof:name":"Regina Wendt Gmbh",
    "wof:placetype":"venue"
},
  "geometry": {"coordinates":[8.960474,52.831661],"type":"Point"}
}