{
  "type": "Feature",
  "properties": {
    "iso:country":"DE",
    "sg:address":"Werner-von-Siemens-Str 22",
    "sg:city":"Georgsmarienh\u00fctte",
    "sg:phone":"+49 5401/83550",
    "sg:postcode":"49124",
    "sg:province":"Niedersachsen",
    "wof:name":"Pur-systems Gmbh & Co Kg",
    "wof:placetype":"venue"
},
  "geometry": {"coordinates":[8.0467233658,52.2055664062],"type":"Point"}
}