{
  "type": "Feature",
  "properties": {
    "iso:country":"DE",
    "sg:address":"Meisenweg 2",
    "sg:city":"Saarbr\u00fccken",
    "sg:phone":"+49 681/703389",
    "sg:postcode":"66128",
    "sg:province":"Saarland",
    "wof:name":"W. Seel",
    "wof:placetype":"venue"
},
  "geometry": {"coordinates":[6.9078397751,49.2320175171],"type":"Point"}
}