{
  "type": "Feature",
  "properties": {
    "iso:country":"DE",
    "sg:address":"Dohmeyers Weg 1",
    "sg:city":"Hannover",
    "sg:phone":"+49 511/557711",
    "sg:postcode":"30625",
    "sg:province":"Niedersachsen",
    "wof:name":"Gattermann",
    "wof:placetype":"venue"
},
  "geometry": {"coordinates":[9.78691,52.373688],"type":"Point"}
}