{
  "type": "Feature",
  "properties": {
    "iso:country":"DE",
    "sg:address":"Sonnenredder 2c",
    "sg:city":"Hamburg",
    "sg:postcode":"22045",
    "sg:province":"Hamburg",
    "wof:name":"Schreiber Kg",
    "wof:placetype":"venue"
},
  "geometry": {"coordinates":[10.1150617599,53.5857276917],"type":"Point"}
}