{
  "type": "Feature",
  "properties": {
    "iso:country":"DE",
    "sg:address":"Ernetstr. 41",
    "sg:city":"Lahr",
    "sg:phone":"+49 7821/37116",
    "sg:postcode":"77933",
    "sg:province":"Baden-W\u00fcrttemberg",
    "wof:name":"Claudia Gr\u00f6sser",
    "wof:placetype":"venue"
},
  "geometry": {"coordinates":[7.8746080399,48.3322906494],"type":"Point"}
}