{
  "type": "Feature",
  "properties": {
    "iso:country":"DE",
    "sg:address":"Saarstr. 21",
    "sg:city":"Mainz",
    "sg:phone":"+49 6131/381702",
    "sg:postcode":"55122",
    "sg:province":"Rheinland-Pfalz",
    "wof:name":"Physiologisches Institut Bibliothek",
    "wof:placetype":"venue"
},
  "geometry": {"coordinates":[8.240185,49.995106],"type":"Point"}
}