{
  "type": "Feature",
  "properties": {
    "iso:country":"DE",
    "sg:address":"Zum Industriepark",
    "sg:city":"Ludwigsfelde",
    "sg:phone":"+49 3378/86180",
    "sg:postcode":"14974",
    "sg:province":"Brandenburg",
    "wof:name":"Dmv-medizintechnik Gmbh",
    "wof:placetype":"venue"
},
  "geometry": {"coordinates":[13.264923,52.317142],"type":"Point"}
}