{
  "type": "Feature",
  "properties": {
    "iso:country":"DE",
    "sg:address":"Wiesenstr.",
    "sg:city":"K\u00f6nnern",
    "sg:phone":"+49 34691/20284",
    "sg:postcode":"06420",
    "sg:province":"Sachsen-Anhalt",
    "wof:name":"P. Toepel",
    "wof:placetype":"venue"
},
  "geometry": {"coordinates":[11.7714796066,51.6741027832],"type":"Point"}
}