{
  "type": "Feature",
  "properties": {
    "iso:country":"DE",
    "sg:address":"Eichendorffstr. 21",
    "sg:city":"Hamburg",
    "sg:phone":"+49 40/869662",
    "sg:postcode":"22587",
    "sg:province":"Hamburg",
    "wof:name":"Ralph Kessler",
    "wof:placetype":"venue"
},
  "geometry": {"coordinates":[9.834417,53.558216],"type":"Point"}
}