{
  "type": "Feature",
  "properties": {
    "iso:country":"DE",
    "sg:address":"L\u00fctzowallee 7",
    "sg:city":"Aurich",
    "sg:phone":"+49 4941/62662",
    "sg:postcode":"26603",
    "sg:province":"Niedersachsen",
    "wof:name":"Orgaplan",
    "wof:placetype":"venue"
},
  "geometry": {"coordinates":[7.482199192,53.4760971069],"type":"Point"}
}