{
  "type": "Feature",
  "properties": {
    "iso:country":"DE",
    "sg:address":"Bebraer Str. 10",
    "sg:city":"Bebra",
    "sg:phone":"+49 6627/213",
    "sg:postcode":"36179",
    "sg:province":"Hessen",
    "wof:name":"Karl Knoth",
    "wof:placetype":"venue"
},
  "geometry": {"coordinates":[9.888432,51.006241],"type":"Point"}
}