{
  "type": "Feature",
  "properties": {
    "iso:country":"DE",
    "sg:address":"Mescheder Str. 2",
    "sg:city":"Meschede",
    "sg:phone":"+49 291/9082395",
    "sg:postcode":"59872",
    "sg:province":"Nordrhein-Westfalen",
    "wof:name":"Taverne",
    "wof:placetype":"venue"
},
  "geometry": {"coordinates":[8.2227706909,51.3359947205],"type":"Point"}
}