{
  "type": "Feature",
  "properties": {
    "iso:country":"DE",
    "sg:address":"Jahnstr. 2a",
    "sg:city":"Ergoldsbach",
    "sg:phone":"+49 8771/1551",
    "sg:postcode":"84061",
    "sg:province":"Bayern",
    "wof:name":"Max Eder Ingenieur",
    "wof:placetype":"venue"
},
  "geometry": {"coordinates":[12.2061891556,48.6944198608],"type":"Point"}
}