{
  "type": "Feature",
  "properties": {
    "iso:country":"DE",
    "sg:address":"Lungstra\u00dfe 8",
    "sg:city":"Burscheid",
    "sg:phone":"+49 2174/41536",
    "sg:postcode":"51399",
    "sg:province":"Nordrhein-Westfalen",
    "wof:name":"J\u00fcrgen Sch\u00fcttler",
    "wof:placetype":"venue"
},
  "geometry": {"coordinates":[7.1192188263,51.0682983398],"type":"Point"}
}