{
  "type": "Feature",
  "properties": {
    "iso:country":"DE",
    "sg:address":"Dotzheimer Str. 57",
    "sg:city":"Wiesbaden",
    "sg:phone":"+49 611/8410340",
    "sg:postcode":"65197",
    "sg:province":"Hessen",
    "wof:name":"Visitas Von Mensch Zu Mensch Liliane Franz E. Kfr.",
    "wof:placetype":"venue"
},
  "geometry": {"coordinates":[8.227961,50.078194],"type":"Point"}
}