{
  "type": "Feature",
  "properties": {
    "iso:country":"DE",
    "sg:address":"Robert-Koch-Str. 24",
    "sg:city":"Husum",
    "sg:phone":"+49 4948/419000",
    "sg:postcode":"25813",
    "sg:province":"Schleswig-Holstein",
    "wof:name":"Steuer Ag",
    "wof:placetype":"venue"
},
  "geometry": {"coordinates":[9.083938,54.49287],"type":"Point"}
}