{
  "type": "Feature",
  "properties": {
    "iso:country":"DE",
    "sg:address":"Meininger Str. 9",
    "sg:city":"M\u00fcnnerstadt",
    "sg:phone":"+49 9733/818050",
    "sg:postcode":"97702",
    "sg:province":"Bayern",
    "wof:name":"Bernhard Seger & S\u00f6hne",
    "wof:placetype":"venue"
},
  "geometry": {"coordinates":[10.1975870132,50.25573349],"type":"Point"}
}