{
  "type": "Feature",
  "properties": {
    "iso:country":"DE",
    "sg:address":"Alban-Stolz-Str. 20",
    "sg:city":"Freiburg",
    "sg:phone":"+49 761/54344",
    "sg:postcode":"79108",
    "sg:province":"Baden-W\u00fcrttemberg",
    "wof:name":"H. Schmidt Pilger Bildhauer",
    "wof:placetype":"venue"
},
  "geometry": {"coordinates":[7.857993,48.024395],"type":"Point"}
}