{
  "type": "Feature",
  "properties": {
    "iso:country":"DE",
    "sg:address":"Hauptstr. 113",
    "sg:city":"H\u00fctschenhausen",
    "sg:phone":"+49 6372/1443",
    "sg:postcode":"66882",
    "sg:province":"Rheinland-Pfalz",
    "wof:name":"Karl Ziegle",
    "wof:placetype":"venue"
},
  "geometry": {"coordinates":[7.4767160416,49.4192123413],"type":"Point"}
}