{
  "type": "Feature",
  "properties": {
    "iso:country":"DE",
    "sg:address":"Lanver 36",
    "sg:city":"Heiden",
    "sg:postcode":"46359",
    "sg:province":"Nordrhein-Westfalen",
    "wof:name":"Keul & Partner Gmbh",
    "wof:placetype":"venue"
},
  "geometry": {"coordinates":[6.958626,51.80117],"type":"Point"}
}