{
  "type": "Feature",
  "properties": {
    "iso:country":"DE",
    "sg:address":"Birkensteinstr.",
    "sg:city":"Fischbachau",
    "sg:phone":"+49 8028/764",
    "sg:postcode":"83730",
    "sg:province":"Bayern",
    "wof:name":"Friedrich F. Haindl Architekt",
    "wof:placetype":"venue"
},
  "geometry": {"coordinates":[11.95456,47.71909],"type":"Point"}
}