{
  "type": "Feature",
  "properties": {
    "iso:country":"DE",
    "sg:address":"Herrnschrot",
    "sg:city":"Stammbach",
    "sg:phone":"+49 9256/460",
    "sg:postcode":"95236",
    "sg:province":"Bayern",
    "wof:name":"Verlag Beyerlein Steinschulte Literatur Buddhismus",
    "wof:placetype":"venue"
},
  "geometry": {"coordinates":[11.64815,50.128281],"type":"Point"}
}