{
  "type": "Feature",
  "properties": {
    "iso:country":"DE",
    "sg:address":"Schillerstr. 7",
    "sg:city":"Bad Nenndorf",
    "sg:phone":"+49 5723/7120",
    "sg:postcode":"31542",
    "sg:province":"Niedersachsen",
    "wof:name":"China Restaurant Goldene Pekingente",
    "wof:placetype":"venue"
},
  "geometry": {"coordinates":[9.3796129227,52.3410377502],"type":"Point"}
}