{
  "type": "Feature",
  "properties": {
    "iso:country":"DE",
    "sg:address":"Hauptstr. 10",
    "sg:city":"Abtswind",
    "sg:phone":"+49 9383/6051",
    "sg:postcode":"97355",
    "sg:province":"Bayern",
    "wof:name":"Hotel-restaurant Zur Schwane",
    "wof:placetype":"venue"
},
  "geometry": {"coordinates":[10.3750085831,49.7708511353],"type":"Point"}
}