{
  "type": "Feature",
  "properties": {
    "iso:country":"DE",
    "sg:address":"Altdorfer Str. 21",
    "sg:city":"Schlier",
    "sg:phone":"+49 4975/299760",
    "sg:postcode":"88281",
    "sg:province":"Baden-W\u00fcrttemberg",
    "wof:name":"Raiffeisenbank Ankenreute-schlier",
    "wof:placetype":"venue"
},
  "geometry": {"coordinates":[9.694725,47.800152],"type":"Point"}
}