{
  "type": "Feature",
  "properties": {
    "iso:country":"DE",
    "sg:address":"L\u00e4ndenstr. 7",
    "sg:city":"Riedenburg",
    "sg:phone":"+49 9442/91930",
    "sg:postcode":"93339",
    "sg:province":"Bayern",
    "wof:name":"Rieduklin-chemie Egon Beck Gmbh",
    "wof:placetype":"venue"
},
  "geometry": {"coordinates":[11.6910295486,48.9825897217],"type":"Point"}
}