{
  "type": "Feature",
  "properties": {
    "iso:country":"DE",
    "sg:address":"Burgunderstr. 2",
    "sg:city":"Neu-Ulm",
    "sg:phone":"+49 7307/4815",
    "sg:postcode":"89233",
    "sg:province":"Bayern",
    "wof:name":"Germanen Apotheke E. K. Apotheker Dagobert Weber",
    "wof:placetype":"venue"
},
  "geometry": {"coordinates":[10.036978,48.347843],"type":"Point"}
}