{
  "type": "Feature",
  "properties": {
    "iso:country":"DE",
    "sg:address":"Hauptstr. 53",
    "sg:city":"Nieb\u00fcll",
    "sg:phone":"+49 4661/2114",
    "sg:postcode":"25899",
    "sg:province":"Schleswig-Holstein",
    "wof:name":"Romeo Und Julia Inh. Carl S\u00f6nnichsen",
    "wof:placetype":"venue"
},
  "geometry": {"coordinates":[8.826938,54.785587],"type":"Point"}
}