{
  "type": "Feature",
  "properties": {
    "iso:country":"DE",
    "sg:address":"Kiefernweg 10",
    "sg:city":"Alsbach-H\u00e4hnlein",
    "sg:phone":"+49 6257/68138",
    "sg:postcode":"64665",
    "sg:province":"Hessen",
    "wof:name":"Mac Bauplanung Gmbh",
    "wof:placetype":"venue"
},
  "geometry": {"coordinates":[8.6047506332,49.7420654297],"type":"Point"}
}