{
  "type": "Feature",
  "properties": {
    "iso:country":"DE",
    "sg:address":"Erdbr\u00fcggenkamp 12",
    "sg:city":"Hille",
    "sg:phone":"+49 5734/93370",
    "sg:postcode":"32479",
    "sg:province":"Nordrhein-Westfalen",
    "wof:name":"Werner Jungmann",
    "wof:placetype":"venue"
},
  "geometry": {"coordinates":[8.771738,52.29295],"type":"Point"}
}