{
  "type": "Feature",
  "properties": {
    "iso:country":"DE",
    "sg:address":"Bleikaule 16",
    "sg:city":"Brilon",
    "sg:phone":"+49 2961/2232",
    "sg:postcode":"59929",
    "sg:province":"Nordrhein-Westfalen",
    "wof:name":"Kanand M\u00f6belschreinerei Gmbh",
    "wof:placetype":"venue"
},
  "geometry": {"coordinates":[8.581557,51.405338],"type":"Point"}
}