{
  "type": "Feature",
  "properties": {
    "iso:country":"DE",
    "sg:address":"Remscheider Str. 43",
    "sg:city":"Wuppertal",
    "sg:phone":"+49 202/463222",
    "sg:postcode":"42369",
    "sg:province":"Nordrhein-Westfalen",
    "wof:name":"Rosemarie Mehler Sportmoden",
    "wof:placetype":"venue"
},
  "geometry": {"coordinates":[7.20577,51.216381],"type":"Point"}
}