{
  "type": "Feature",
  "properties": {
    "iso:country":"DE",
    "sg:address":"Osterberg 1",
    "sg:city":"Wolfsburg",
    "sg:phone":"+49 5308/4343",
    "sg:postcode":"38444",
    "sg:province":"Niedersachsen",
    "wof:name":"Treffpunkt Mtv",
    "wof:placetype":"venue"
},
  "geometry": {"coordinates":[10.7521352768,52.3597946167],"type":"Point"}
}