{
  "type": "Feature",
  "properties": {
    "iso:country":"DE",
    "sg:address":"Steinweg 11",
    "sg:city":"Suhl",
    "sg:phone":"+49 3681/305629",
    "sg:postcode":"98527",
    "sg:province":"Th\u00fcringen",
    "wof:name":"H. Beulich",
    "wof:placetype":"venue"
},
  "geometry": {"coordinates":[10.6926803589,50.6099014282],"type":"Point"}
}