{
  "type": "Feature",
  "properties": {
    "iso:country":"DE",
    "sg:address":"Zeunerstr. 67",
    "sg:city":"Dresden",
    "sg:phone":"+49 351/4724249",
    "sg:postcode":"01069",
    "sg:province":"Sachsen",
    "wof:name":"E. Andrich",
    "wof:placetype":"venue"
},
  "geometry": {"coordinates":[13.7318887711,51.0263938904],"type":"Point"}
}