{
  "type": "Feature",
  "properties": {
    "iso:country":"DE",
    "sg:address":"Hohenstaufenstr. 14",
    "sg:city":"Wiesbaden",
    "sg:phone":"+49 611/973700",
    "sg:postcode":"65189",
    "sg:province":"Hessen",
    "wof:name":"J\u00f6rg Gaalfrank Elektroinstallation",
    "wof:placetype":"venue"
},
  "geometry": {"coordinates":[8.255262,50.065327],"type":"Point"}
}