{
  "type": "Feature",
  "properties": {
    "iso:country":"DE",
    "sg:address":"Weilheimer Str. 5",
    "sg:city":"Landsberg",
    "sg:phone":"+49 8191/32020",
    "sg:postcode":"86899",
    "sg:province":"Bayern",
    "wof:name":"Hotel Landsberger Hof",
    "wof:placetype":"venue"
},
  "geometry": {"coordinates":[10.8841142654,48.046546936],"type":"Point"}
}