{
  "type": "Feature",
  "properties": {
    "iso:country":"DE",
    "sg:address":"Jenaer Str. 17",
    "sg:city":"Thalb\u00fcrgel",
    "sg:phone":"+49 36692/20664",
    "sg:postcode":"07616",
    "sg:province":"Th\u00fcringen",
    "wof:name":"Walter P\u00f6hnlein",
    "wof:placetype":"venue"
},
  "geometry": {"coordinates":[11.7205553055,50.9570846558],"type":"Point"}
}