{
  "type": "Feature",
  "properties": {
    "iso:country":"DE",
    "sg:address":"Ortsstra\u00dfe",
    "sg:city":"Gladenbach",
    "sg:phone":"+49 6462/926658",
    "sg:postcode":"35075",
    "sg:province":"Hessen",
    "wof:name":"Showlighting",
    "wof:placetype":"venue"
},
  "geometry": {"coordinates":[8.608544,50.822266],"type":"Point"}
}