{
  "type": "Feature",
  "properties": {
    "iso:country":"DE",
    "sg:address":"In der Schlage 6",
    "sg:city":"Gevelsberg",
    "sg:phone":"+49 2332/50773",
    "sg:postcode":"58285",
    "sg:province":"Nordrhein-Westfalen",
    "wof:name":"Kunstschmiede Und Schlosserei Janorschke Gmbh & Co. Kg",
    "wof:placetype":"venue"
},
  "geometry": {"coordinates":[7.33628,51.349541],"type":"Point"}
}