{
  "type": "Feature",
  "properties": {
    "iso:country":"DE",
    "sg:address":"Veilchenstr. 13",
    "sg:city":"Langenhagen",
    "sg:phone":"+49 511/733613",
    "sg:postcode":"30853",
    "sg:province":"Niedersachsen",
    "wof:name":"G\u00fcnter Bielecki Blitzschutzbauunternehmen",
    "wof:placetype":"venue"
},
  "geometry": {"coordinates":[9.731031,52.443943],"type":"Point"}
}