{
  "type": "Feature",
  "properties": {
    "iso:country":"DE",
    "sg:address":"Lutherstr. 26",
    "sg:city":"Lauchhammer",
    "sg:phone":"+49 3574/3542",
    "sg:postcode":"01979",
    "sg:province":"Brandenburg",
    "wof:name":"B. Weist",
    "wof:placetype":"venue"
},
  "geometry": {"coordinates":[13.77235,51.49432],"type":"Point"}
}