{
  "type": "Feature",
  "properties": {
    "iso:country":"DE",
    "sg:address":"Schu\u00dfbachstr. 87",
    "sg:city":"Baden-Baden",
    "sg:phone":"+49 7221/61972",
    "sg:postcode":"76532",
    "sg:province":"Baden-W\u00fcrttemberg",
    "wof:name":"Harald Himer",
    "wof:placetype":"venue"
},
  "geometry": {"coordinates":[8.2082748413,48.7868041992],"type":"Point"}
}