{
  "type": "Feature",
  "properties": {
    "iso:country":"DE",
    "sg:address":"Riedweg 3",
    "sg:city":"Mainz",
    "sg:phone":"+49 6131/881828",
    "sg:postcode":"55130",
    "sg:province":"Rheinland-Pfalz",
    "wof:name":"Peter Pferdekemper Rechtsanwalt",
    "wof:placetype":"venue"
},
  "geometry": {"coordinates":[8.3146533966,49.9596748352],"type":"Point"}
}