{
  "type": "Feature",
  "properties": {
    "iso:country":"DE",
    "sg:address":"Hauptstr. 10",
    "sg:city":"Niederwerrn",
    "sg:phone":"+49 9726/8622",
    "sg:postcode":"97464",
    "sg:province":"Bayern",
    "wof:name":"Georg Poschinger",
    "wof:placetype":"venue"
},
  "geometry": {"coordinates":[10.156071,50.071335],"type":"Point"}
}