{
  "type": "Feature",
  "properties": {
    "iso:country":"DE",
    "sg:address":"Bahnhofstr. 25",
    "sg:city":"Donauw\u00f6rth",
    "sg:phone":"+49 906/706170",
    "sg:postcode":"86609",
    "sg:province":"Bayern",
    "wof:name":"Hotel Drei Kronen",
    "wof:placetype":"venue"
},
  "geometry": {"coordinates":[10.773018837,48.7158889771],"type":"Point"}
}