{
  "type": "Feature",
  "properties": {
    "iso:country":"DE",
    "sg:address":"Pezolddamm 109",
    "sg:city":"Hamburg",
    "sg:phone":"+49 40/6438968",
    "sg:postcode":"22175",
    "sg:province":"Hamburg",
    "wof:name":"Elektro - K\u00f6tzsche Ferdinand K\u00f6tzsche",
    "wof:placetype":"venue"
},
  "geometry": {"coordinates":[10.108384,53.622356],"type":"Point"}
}