{
  "type": "Feature",
  "properties": {
    "iso:country":"DE",
    "sg:address":"Gartenstr. 35",
    "sg:city":"Eckernf\u00f6rde",
    "sg:phone":"+49 4351/5608",
    "sg:postcode":"24340",
    "sg:province":"Schleswig-Holstein",
    "wof:name":"Dieter Gilewski Ingenieur",
    "wof:placetype":"venue"
},
  "geometry": {"coordinates":[9.8357591629,54.4707984924],"type":"Point"}
}