{
  "type": "Feature",
  "properties": {
    "iso:country":"DE",
    "sg:address":"Brunirode 74",
    "sg:city":"Laatzen",
    "sg:phone":"+49 4967/2247200",
    "sg:postcode":"30880",
    "sg:province":"Niedersachsen",
    "wof:name":"M. & E. Christ Kg",
    "wof:placetype":"venue"
},
  "geometry": {"coordinates":[7.920299,49.979065],"type":"Point"}
}