{
  "type": "Feature",
  "properties": {
    "iso:country":"DE",
    "sg:address":"Eickener Str. 140",
    "sg:city":"M\u00f6nchengladbach",
    "sg:phone":"+49 2161/22363",
    "sg:postcode":"41063",
    "sg:province":"Nordrhein-Westfalen",
    "wof:name":"Bei Milan",
    "wof:placetype":"venue"
},
  "geometry": {"coordinates":[6.4456858635,51.2041778564],"type":"Point"}
}