{
  "type": "Feature",
  "properties": {
    "iso:country":"DE",
    "sg:address":"Ostseeallee 13",
    "sg:city":"Timmendorfer Strand",
    "sg:postcode":"23669",
    "sg:province":"Schleswig-Holstein",
    "wof:name":"Monika Kronenberg Krankengymnastin",
    "wof:placetype":"venue"
},
  "geometry": {"coordinates":[10.838004,53.990112],"type":"Point"}
}