{
  "type": "Feature",
  "properties": {
    "iso:country":"DE",
    "sg:address":"Kirchstr. 7",
    "sg:city":"Zeulenroda",
    "sg:postcode":"07937",
    "sg:province":"Th\u00fcringen",
    "wof:name":"Evangelisch-lutherische Kirchgemeinde",
    "wof:placetype":"venue"
},
  "geometry": {"coordinates":[11.9804239273,50.6484375],"type":"Point"}
}