{
  "type": "Feature",
  "properties": {
    "iso:country":"DE",
    "sg:address":"Fr\u00f6ndenberger Str. 32",
    "sg:city":"Menden",
    "sg:postcode":"58706",
    "sg:province":"Nordrhein-Westfalen",
    "wof:name":"Dipl.-ing. K. Kr\u00fcger Ingenieurb\u00fcro F\u00fcr",
    "wof:placetype":"venue"
},
  "geometry": {"coordinates":[7.783850193,51.4459953308],"type":"Point"}
}