{
  "type": "Feature",
  "properties": {
    "iso:country":"DE",
    "sg:address":"Ritterspornweg 15",
    "sg:city":"Berlin",
    "sg:phone":"+49 30/6633191",
    "sg:postcode":"12357",
    "sg:province":"Berlin",
    "wof:name":"Harry Schmiedeberg",
    "wof:placetype":"venue"
},
  "geometry": {"coordinates":[13.50576,52.423679],"type":"Point"}
}