{
  "type": "Feature",
  "properties": {
    "iso:country":"DE",
    "sg:address":"Arnst\u00e4dter Chaussee 14",
    "sg:city":"Erfurt",
    "sg:postcode":"99096",
    "sg:province":"Th\u00fcringen",
    "wof:name":"Versicherungs- Und Reiseb\u00fcro Erfordia",
    "wof:placetype":"venue"
},
  "geometry": {"coordinates":[11.0316257477,50.9670982361],"type":"Point"}
}