{
  "type": "Feature",
  "properties": {
    "iso:country":"DE",
    "sg:address":"Wasserkurler Str. 45",
    "sg:city":"Kamen",
    "sg:phone":"+49 2307/931300",
    "sg:postcode":"59174",
    "sg:province":"Nordrhein-Westfalen",
    "wof:name":"Alte Wasserkurler Schmiede",
    "wof:placetype":"venue"
},
  "geometry": {"coordinates":[7.6247210503,51.5601425171],"type":"Point"}
}