{
  "type": "Feature",
  "properties": {
    "iso:country":"DE",
    "sg:address":"Am Tidehafen 5",
    "sg:city":"Elsfleth",
    "sg:phone":"+49 4404/9250",
    "sg:postcode":"26931",
    "sg:province":"Niedersachsen",
    "wof:name":"Omni-pac Verpackungsmittel Verwaltungsges. Mbh",
    "wof:placetype":"venue"
},
  "geometry": {"coordinates":[8.458404541,53.227596283],"type":"Point"}
}