{
  "type": "Feature",
  "properties": {
    "iso:country":"DE",
    "sg:address":"Seifendamm 16",
    "sg:city":"Neuenhaus",
    "sg:phone":"+49 5941/920537",
    "sg:postcode":"49828",
    "sg:province":"Niedersachsen",
    "wof:name":"Ir-service",
    "wof:placetype":"venue"
},
  "geometry": {"coordinates":[6.9638881683,52.5020751953],"type":"Point"}
}