{
  "type": "Feature",
  "properties": {
    "iso:country":"DE",
    "sg:address":"Seenheimer Str. 8",
    "sg:city":"Ergersheim",
    "sg:phone":"+49 9847/321",
    "sg:postcode":"91465",
    "sg:province":"Bayern",
    "wof:name":"Ludwig Steinkrug",
    "wof:placetype":"venue"
},
  "geometry": {"coordinates":[10.3281612396,49.512386322],"type":"Point"}
}