{
  "type": "Feature",
  "properties": {
    "iso:country":"DE",
    "sg:address":"Talstr. 25",
    "sg:city":"Kreischa",
    "sg:phone":"+49 35206/21764",
    "sg:postcode":"01731",
    "sg:province":"Sachsen",
    "wof:name":"Udo Sakalowski",
    "wof:placetype":"venue"
},
  "geometry": {"coordinates":[13.726497,50.946472],"type":"Point"}
}