{
  "type": "Feature",
  "properties": {
    "iso:country":"DE",
    "sg:address":"W\u00fcnsdorfer Str. 119",
    "sg:city":"Berlin",
    "sg:phone":"+49 30/7445319",
    "sg:postcode":"12307",
    "sg:province":"Berlin",
    "wof:name":"Trans-inter Dienstleistungs- Und Handelsges. Mbh",
    "wof:placetype":"venue"
},
  "geometry": {"coordinates":[13.3952646255,52.3873672485],"type":"Point"}
}