{
  "type": "Feature",
  "properties": {
    "iso:country":"DE",
    "sg:address":"Stefan-Meier-Str. 131",
    "sg:city":"Freiburg",
    "sg:phone":"+49 761/36547",
    "sg:postcode":"79104",
    "sg:province":"Baden-W\u00fcrttemberg",
    "wof:name":"Erla Zentrale",
    "wof:placetype":"venue"
},
  "geometry": {"coordinates":[7.8495349884,48.0056152344],"type":"Point"}
}