{
  "type": "Feature",
  "properties": {
    "iso:country":"DE",
    "sg:address":"Wilhelmstr. 27",
    "sg:city":"Marburg",
    "sg:phone":"+49 6421/17110",
    "sg:postcode":"35037",
    "sg:province":"Hessen",
    "wof:name":"Geilhof Schlaeger Und Faecks Rechtsanw\u00e4lte Und Notare",
    "wof:placetype":"venue"
},
  "geometry": {"coordinates":[8.764043808,50.8050575256],"type":"Point"}
}