{
  "type": "Feature",
  "properties": {
    "iso:country":"DE",
    "sg:address":"Anselm-Feuerbach-Str. 26",
    "sg:city":"Gaggenau",
    "sg:phone":"+49 7225/77133",
    "sg:postcode":"76571",
    "sg:province":"Baden-W\u00fcrttemberg",
    "wof:name":"Klaus Merkel Kino",
    "wof:placetype":"venue"
},
  "geometry": {"coordinates":[8.33239,48.790199],"type":"Point"}
}