{
  "type": "Feature",
  "properties": {
    "iso:country":"DE",
    "sg:address":"Am Hausplatz 7",
    "sg:city":"Freudenberg",
    "sg:phone":"+49 2734/7071",
    "sg:postcode":"57258",
    "sg:province":"Nordrhein-Westfalen",
    "wof:name":"Schr\u00f6der Kg",
    "wof:placetype":"venue"
},
  "geometry": {"coordinates":[7.8762359619,50.8897132874],"type":"Point"}
}