{
  "type": "Feature",
  "properties": {
    "iso:country":"DE",
    "sg:address":"Sternbuschweg 128",
    "sg:city":"Duisburg",
    "sg:phone":"+49 203/376599",
    "sg:postcode":"47057",
    "sg:province":"Nordrhein-Westfalen",
    "wof:name":"Gastst\u00e4tte Hannen Sudhaus",
    "wof:placetype":"venue"
},
  "geometry": {"coordinates":[6.7899470329,51.4259185791],"type":"Point"}
}