{
  "type": "Feature",
  "properties": {
    "iso:country":"DE",
    "sg:address":"Hahler Str. 203",
    "sg:city":"Minden",
    "sg:phone":"+49 571/648863",
    "sg:postcode":"32427",
    "sg:province":"Nordrhein-Westfalen",
    "wof:name":"Hans-dieter Seckelmann Steuerberater",
    "wof:placetype":"venue"
},
  "geometry": {"coordinates":[8.8738965988,52.2987785339],"type":"Point"}
}