{
  "type": "Feature",
  "properties": {
    "iso:country":"DE",
    "sg:address":"Am Bielstein 3",
    "sg:city":"Meiningen",
    "sg:phone":"+49 4936/934530",
    "sg:postcode":"98617",
    "sg:province":"Th\u00fcringen",
    "wof:name":"Meininger Privatbrauerei Gmbh",
    "wof:placetype":"venue"
},
  "geometry": {"coordinates":[10.411241,50.573265],"type":"Point"}
}