{
  "type": "Feature",
  "properties": {
    "iso:country":"DE",
    "sg:address":"Neuensteiner Str. 6",
    "sg:city":"Oppenau",
    "sg:phone":"+49 7804/97840",
    "sg:postcode":"77728",
    "sg:province":"Baden-W\u00fcrttemberg",
    "wof:name":"Armbruster Bau-einrichtungssysteme Gmbh",
    "wof:placetype":"venue"
},
  "geometry": {"coordinates":[8.137434,48.497475],"type":"Point"}
}