{
  "type": "Feature",
  "properties": {
    "iso:country":"DE",
    "sg:address":"Lange Str. 4-6",
    "sg:city":"Steinhagen",
    "sg:phone":"+49 5204/2245",
    "sg:postcode":"33803",
    "sg:province":"Nordrhein-Westfalen",
    "wof:name":"H. Dieckmann",
    "wof:placetype":"venue"
},
  "geometry": {"coordinates":[8.445201,52.016705],"type":"Point"}
}