{
  "type": "Feature",
  "properties": {
    "iso:country":"DE",
    "sg:address":"Hofackerstr. 19",
    "sg:city":"Augsburg",
    "sg:phone":"+49 821/808800",
    "sg:postcode":"86179",
    "sg:province":"Bayern",
    "wof:name":"Deutsche Woolworth Gmbh & Co. Ohg",
    "wof:placetype":"venue"
},
  "geometry": {"coordinates":[10.904236,48.312099],"type":"Point"}
}