{
  "type": "Feature",
  "properties": {
    "iso:country":"DE",
    "sg:address":"Am Steigweg 4",
    "sg:city":"Itzgrund",
    "sg:postcode":"96274",
    "sg:province":"Bayern",
    "wof:name":"Deutscher Verkehrswacht Kreis- Verkehrswacht Lichtenf. E. V.",
    "wof:placetype":"venue"
},
  "geometry": {"coordinates":[10.9339580536,50.1264953613],"type":"Point"}
}