{
  "type": "Feature",
  "properties": {
    "iso:country":"DE",
    "sg:address":"Weidenweg 13b",
    "sg:city":"Unna",
    "sg:phone":"+49 2303/89277",
    "sg:postcode":"59423",
    "sg:province":"Nordrhein-Westfalen",
    "wof:name":"Horst Kramer Bauunternehmung Gmbh",
    "wof:placetype":"venue"
},
  "geometry": {"coordinates":[7.667572,51.524944],"type":"Point"}
}