{
  "type": "Feature",
  "properties": {
    "iso:country":"DE",
    "sg:address":"Delmenhorster Str. 186",
    "sg:city":"Stuhr",
    "sg:phone":"+49 4206/330",
    "sg:postcode":"28816",
    "sg:province":"Niedersachsen",
    "wof:name":"Alfred Meyer Gmbh",
    "wof:placetype":"venue"
},
  "geometry": {"coordinates":[8.71069,52.99604],"type":"Point"}
}