{
  "type": "Feature",
  "properties": {
    "iso:country":"DE",
    "sg:address":"An der Klosterruine 8 a",
    "sg:city":"Greifswald",
    "sg:phone":"+49 3834/839636",
    "sg:postcode":"17493",
    "sg:province":"Mecklenburg-Vorpommern",
    "wof:name":"Helga Hethke Finanzberater",
    "wof:placetype":"venue"
},
  "geometry": {"coordinates":[13.4538698196,54.08934021],"type":"Point"}
}