{
  "type": "Feature",
  "properties": {
    "iso:country":"DE",
    "sg:address":"Lindenallee 60",
    "sg:city":"Oldenburg",
    "sg:classifiers":[
        {
            "category":"Professional",
            "subcategory":"Computer Services",
            "type":"Services"
        }
    ],
    "sg:postcode":"26122",
    "sg:tags":[
        "germany",
        "oldenburg",
        "wiki"
    ],
    "sg:website":"http://www.youserbase.org",
    "wof:name":"youserbase",
    "wof:placetype":"venue"
},
  "geometry": {"coordinates":[8.200653,53.14967],"type":"Point"}
}