{
  "type": "Feature",
  "properties": {
    "iso:country":"DE",
    "sg:address":"Ludwig-K\u00fchn-Str. 11",
    "sg:city":"Chemnitz",
    "sg:phone":"+49 371/241499",
    "sg:postcode":"09123",
    "sg:province":"Sachsen",
    "wof:name":"Wilfried Landgraf",
    "wof:placetype":"venue"
},
  "geometry": {"coordinates":[12.8967647552,50.7850036621],"type":"Point"}
}