{
  "type": "Feature",
  "properties": {
    "iso:country":"DE",
    "sg:address":"Alter Postweg 5",
    "sg:city":"Neu Kali\u00df",
    "sg:phone":"+49 38758/3070",
    "sg:postcode":"19294",
    "sg:province":"Mecklenburg-Vorpommern",
    "wof:name":"Mbs Mauritz - Bau - Service Dipl.-ing. Rolf Mauritz",
    "wof:placetype":"venue"
},
  "geometry": {"coordinates":[11.29986,53.172821],"type":"Point"}
}