{
  "type": "Feature",
  "properties": {
    "iso:country":"DE",
    "sg:address":"Maria-Sophia-Str. 6",
    "sg:city":"Emmerich",
    "sg:phone":"+49 2822/2413",
    "sg:postcode":"46446",
    "sg:province":"Nordrhein-Westfalen",
    "wof:name":"Hans Van Der Laan",
    "wof:placetype":"venue"
},
  "geometry": {"coordinates":[6.1654210091,51.8695068359],"type":"Point"}
}