{
  "type": "Feature",
  "properties": {
    "iso:country":"DE",
    "sg:address":"Langgr\u00fcn 5",
    "sg:city":"Gefell",
    "sg:postcode":"07926",
    "sg:province":"Th\u00fcringen",
    "wof:name":"Schneller & M\u00fcller Transport- Und Baustoff Gmbh",
    "wof:placetype":"venue"
},
  "geometry": {"coordinates":[11.768699646,50.4600715637],"type":"Point"}
}