{
  "type": "Feature",
  "properties": {
    "iso:country":"DE",
    "sg:address":"Hindenburgstr. 14",
    "sg:city":"Calw",
    "sg:phone":"+49 7051/12195",
    "sg:postcode":"75365",
    "sg:province":"Baden-W\u00fcrttemberg",
    "wof:name":"Ev. Pfarramt Stadtkirche Ii",
    "wof:placetype":"venue"
},
  "geometry": {"coordinates":[8.7427167892,48.717540741],"type":"Point"}
}