{
  "type": "Feature",
  "properties": {
    "iso:country":"DE",
    "sg:address":"Querstr. 14",
    "sg:city":"Delligsen",
    "sg:phone":"+49 5187/3315",
    "sg:postcode":"31073",
    "sg:province":"Niedersachsen",
    "wof:name":"Gerald Siemers",
    "wof:placetype":"venue"
},
  "geometry": {"coordinates":[9.804387,51.939606],"type":"Point"}
}