{
  "type": "Feature",
  "properties": {
    "iso:country":"DE",
    "sg:address":"Kamper Str 26",
    "sg:city":"N\u00fctzen",
    "sg:phone":"+49 4191/958882",
    "sg:postcode":"24568",
    "sg:province":"Schleswig-Holstein",
    "wof:name":"Werkstatt-service Nord",
    "wof:placetype":"venue"
},
  "geometry": {"coordinates":[9.93711,53.862621],"type":"Point"}
}