{
  "type": "Feature",
  "properties": {
    "iso:country":"DE",
    "sg:address":"In der Sohl 122",
    "sg:city":"Neuwied",
    "sg:postcode":"56564",
    "sg:province":"Rheinland-Pfalz",
    "wof:name":"Imerys Deutschland Gmbh",
    "wof:placetype":"venue"
},
  "geometry": {"coordinates":[7.489215,50.431293],"type":"Point"}
}