{
  "type": "Feature",
  "properties": {
    "iso:country":"DE",
    "sg:address":"Waldhornstr. 41a",
    "sg:city":"Germering",
    "sg:phone":"+49 89/842646",
    "sg:postcode":"82110",
    "sg:province":"Bayern",
    "wof:name":"Lh Spielhallen Gmbh",
    "wof:placetype":"venue"
},
  "geometry": {"coordinates":[11.3835058212,48.1323356628],"type":"Point"}
}