{
  "type": "Feature",
  "properties": {
    "iso:country":"DE",
    "sg:address":"Markt 9",
    "sg:city":"Bad Schmiedeberg",
    "sg:phone":"+49 34925/50000",
    "sg:postcode":"06905",
    "sg:province":"Sachsen-Anhalt",
    "wof:name":"L\u00f6wen-apotheke",
    "wof:placetype":"venue"
},
  "geometry": {"coordinates":[12.738394,51.687473],"type":"Point"}
}