{
  "type": "Feature",
  "properties": {
    "iso:country":"DE",
    "sg:address":"Bei der Neuen M\u00fcnze 1",
    "sg:city":"Hamburg",
    "sg:phone":"+49 40/679465",
    "sg:postcode":"22145",
    "sg:province":"Hamburg",
    "wof:name":"Portofino Versand",
    "wof:placetype":"venue"
},
  "geometry": {"coordinates":[10.150929451,53.6215438843],"type":"Point"}
}