{
  "type": "Feature",
  "properties": {
    "iso:country":"DE",
    "sg:address":"Rohrer Str. 5",
    "sg:city":"Ro\u00dftal",
    "sg:phone":"+49 9127/6577",
    "sg:postcode":"90574",
    "sg:province":"Bayern",
    "wof:name":"J. Bierlein",
    "wof:placetype":"venue"
},
  "geometry": {"coordinates":[10.8841123581,49.3628959656],"type":"Point"}
}