{
  "type": "Feature",
  "properties": {
    "iso:country":"DE",
    "sg:address":"Salzstr. 15",
    "sg:city":"Bad Sassendorf",
    "sg:phone":"+49 2921/52963",
    "sg:postcode":"59505",
    "sg:province":"Nordrhein-Westfalen",
    "wof:name":"Werner Bu\u00dfmann",
    "wof:placetype":"venue"
},
  "geometry": {"coordinates":[8.171747,51.588497],"type":"Point"}
}