{
  "type": "Feature",
  "properties": {
    "iso:country":"DE",
    "sg:address":"Zimmerplatzstr. 16",
    "sg:city":"Bad Waldsee",
    "sg:phone":"+49 7524/2842",
    "sg:postcode":"88339",
    "sg:province":"Baden-W\u00fcrttemberg",
    "wof:name":"C. Daiber",
    "wof:placetype":"venue"
},
  "geometry": {"coordinates":[9.812144,47.930393],"type":"Point"}
}