{
  "type": "Feature",
  "properties": {
    "iso:country":"DE",
    "sg:address":"Zeitzer Str. 97",
    "sg:city":"Altenburg",
    "sg:phone":"+49 3447/836201",
    "sg:postcode":"04600",
    "sg:province":"Th\u00fcringen",
    "wof:name":"Conoco Mineral\u00f6l Gmbh",
    "wof:placetype":"venue"
},
  "geometry": {"coordinates":[12.4101018906,50.9987640381],"type":"Point"}
}