{
  "type": "Feature",
  "properties": {
    "iso:country":"DE",
    "sg:address":"K\u00f6sener Str. 36",
    "sg:city":"Naumburg",
    "sg:phone":"+49 3445/772551",
    "sg:postcode":"06618",
    "sg:province":"Sachsen-Anhalt",
    "wof:name":"A. Kurth",
    "wof:placetype":"venue"
},
  "geometry": {"coordinates":[11.793136,51.152157],"type":"Point"}
}