{
  "type": "Feature",
  "properties": {
    "iso:country":"DE",
    "sg:address":"Enzianweg 4",
    "sg:city":"Gmund",
    "sg:phone":"+49 8022/75319",
    "sg:postcode":"83703",
    "sg:province":"Bayern",
    "wof:name":"H.-g. Schneider",
    "wof:placetype":"venue"
},
  "geometry": {"coordinates":[11.7417545319,47.7606315613],"type":"Point"}
}