{
  "type": "Feature",
  "properties": {
    "iso:country":"DE",
    "sg:address":"Winkelstr 8",
    "sg:city":"Guben",
    "sg:phone":"+49 3561/2618",
    "sg:postcode":"03172",
    "sg:province":"Brandenburg",
    "wof:name":"B\u00e4rmann & Partner Gbr",
    "wof:placetype":"venue"
},
  "geometry": {"coordinates":[14.718452,51.951111],"type":"Point"}
}