{
  "type": "Feature",
  "properties": {
    "iso:country":"DE",
    "sg:address":"Lindenstr. 2",
    "sg:city":"Eichenzell",
    "sg:phone":"+49 6659/2848",
    "sg:postcode":"36124",
    "sg:province":"Hessen",
    "wof:name":"Stuckgesch\u00e4ft Schulz Verwaltungs Gmbh",
    "wof:placetype":"venue"
},
  "geometry": {"coordinates":[9.6974887848,50.4975738525],"type":"Point"}
}