{
  "type": "Feature",
  "properties": {
    "iso:country":"DE",
    "sg:address":"Meierhafe 37",
    "sg:city":"Ganderkesee",
    "sg:phone":"+49 4222/6988",
    "sg:postcode":"27777",
    "sg:province":"Niedersachsen",
    "wof:name":"G\u00fcnter Westermann",
    "wof:placetype":"venue"
},
  "geometry": {"coordinates":[8.543574,52.979858],"type":"Point"}
}