{
  "type": "Feature",
  "properties": {
    "iso:country":"DE",
    "sg:address":"Lange Str. 13",
    "sg:city":"Wittingen",
    "sg:phone":"+49 5831/1522",
    "sg:postcode":"29378",
    "sg:province":"Niedersachsen",
    "wof:name":"Cafe Classic",
    "wof:placetype":"venue"
},
  "geometry": {"coordinates":[10.73728,52.728195],"type":"Point"}
}