{
  "type": "Feature",
  "properties": {
    "iso:country":"DE",
    "sg:address":"Sch\u00f6nholzer Stra\u00dfe 18",
    "sg:city":"Eberswalde",
    "sg:phone":"+49 3334/30980",
    "sg:postcode":"16227",
    "sg:province":"Brandenburg",
    "wof:name":"Rose Geh\u00e4usetechnik Gmbh Aus Eberswalde",
    "wof:placetype":"venue"
},
  "geometry": {"coordinates":[13.73765,52.832279],"type":"Point"}
}