{
  "type": "Feature",
  "properties": {
    "iso:country":"DE",
    "sg:address":"Gau\u00dfstr. 103",
    "sg:city":"Bochum",
    "sg:phone":"+49 234/494006",
    "sg:postcode":"44879",
    "sg:province":"Nordrhein-Westfalen",
    "wof:name":"Helmut Quinting",
    "wof:placetype":"venue"
},
  "geometry": {"coordinates":[7.1557569504,51.4344329834],"type":"Point"}
}