{
  "type": "Feature",
  "properties": {
    "iso:country":"DE",
    "sg:address":"Leimersberg 7",
    "sg:city":"G\u00f6\u00dfweinstein",
    "sg:phone":"+49 9242/92466",
    "sg:postcode":"91327",
    "sg:province":"Bayern",
    "wof:name":"J. Dressel Gmbh",
    "wof:placetype":"venue"
},
  "geometry": {"coordinates":[11.319126,49.723557],"type":"Point"}
}