{
  "type": "Feature",
  "properties": {
    "iso:country":"DE",
    "sg:address":"D\u00fclferstr. 3",
    "sg:city":"Dresden",
    "sg:phone":"+49 351/4726024",
    "sg:postcode":"01069",
    "sg:province":"Sachsen",
    "wof:name":"Dr. Med. Heike Pansegrau",
    "wof:placetype":"venue"
},
  "geometry": {"coordinates":[13.727198,51.026398],"type":"Point"}
}