{
  "type": "Feature",
  "properties": {
    "iso:country":"DE",
    "sg:address":"Senftenberger Str. 55",
    "sg:city":"Dresden",
    "sg:phone":"+49 351/285980",
    "sg:postcode":"01239",
    "sg:province":"Sachsen",
    "wof:name":"August Holder Gmbh",
    "wof:placetype":"venue"
},
  "geometry": {"coordinates":[13.8020906448,51.002243042],"type":"Point"}
}