{
  "type": "Feature",
  "properties": {
    "iso:country":"DE",
    "sg:address":"Hagenring 20",
    "sg:city":"Ammerbuch",
    "sg:phone":"+49 7032/97900",
    "sg:postcode":"72119",
    "sg:province":"Baden-W\u00fcrttemberg",
    "wof:name":"Rmp Chemisch-technische Spezialprodukte Verwaltungs-",
    "wof:placetype":"venue"
},
  "geometry": {"coordinates":[8.9058876038,48.5665855408],"type":"Point"}
}