{
  "type": "Feature",
  "properties": {
    "iso:country":"DE",
    "sg:address":"Strandstr. 21",
    "sg:city":"Trassenheide",
    "sg:phone":"+49 38371/21987",
    "sg:postcode":"17449",
    "sg:province":"Mecklenburg-Vorpommern",
    "wof:name":"Restaurant Wassermann",
    "wof:placetype":"venue"
},
  "geometry": {"coordinates":[13.8638296127,54.0876998901],"type":"Point"}
}