{
  "type": "Feature",
  "properties": {
    "iso:country":"DE",
    "sg:address":"Webereistr. 6",
    "sg:city":"Oerlinghausen",
    "sg:phone":"+49 5202/91440",
    "sg:postcode":"33813",
    "sg:province":"Nordrhein-Westfalen",
    "wof:name":"Dr. August Oetker Nahrungsmittel Kg",
    "wof:placetype":"venue"
},
  "geometry": {"coordinates":[8.6666498184,51.9626617432],"type":"Point"}
}