{
  "type": "Feature",
  "properties": {
    "iso:country":"DE",
    "sg:address":"Kirchgasse 9",
    "sg:city":"Wiesbaden",
    "sg:phone":"+49 611/309903",
    "sg:postcode":"65185",
    "sg:province":"Hessen",
    "wof:name":"Dr. Med. Manoucheher Radmehr",
    "wof:placetype":"venue"
},
  "geometry": {"coordinates":[8.2384347916,50.0784683228],"type":"Point"}
}