{
  "type": "Feature",
  "properties": {
    "iso:country":"DE",
    "sg:address":"Hirtenackerstr. 5",
    "sg:city":"Gundelsheim",
    "sg:phone":"+49 951/43249",
    "sg:postcode":"96163",
    "sg:province":"Bayern",
    "wof:name":"Hauffbr\u00e4u-stuben",
    "wof:placetype":"venue"
},
  "geometry": {"coordinates":[10.9175357819,49.9386558533],"type":"Point"}
}