{
  "type": "Feature",
  "properties": {
    "iso:country":"DE",
    "sg:address":"Am Hafenkopf 8",
    "sg:city":"Krefeld",
    "sg:phone":"+49 2151/579940",
    "sg:postcode":"47809",
    "sg:province":"Nordrhein-Westfalen",
    "wof:name":"Kit Krefeld Intermodal Terminal Gmbh",
    "wof:placetype":"venue"
},
  "geometry": {"coordinates":[6.663818,51.345783],"type":"Point"}
}