{
  "type": "Feature",
  "properties": {
    "iso:country":"DE",
    "sg:address":"Breitenbergstr. 4",
    "sg:city":"Mindelheim",
    "sg:phone":"+49 8261/8014",
    "sg:postcode":"87719",
    "sg:province":"Bayern",
    "wof:name":"Mindeltaler Recyclinggesellschaft Mbh",
    "wof:placetype":"venue"
},
  "geometry": {"coordinates":[10.507815361,48.0350990295],"type":"Point"}
}