{
  "type": "Feature",
  "properties": {
    "iso:country":"DE",
    "sg:address":"Diestedder Str. 13",
    "sg:city":"Wadersloh",
    "sg:phone":"+49 2523/7477",
    "sg:postcode":"59329",
    "sg:province":"Nordrhein-Westfalen",
    "wof:name":"Bertelt Treppenbau Gmbh",
    "wof:placetype":"venue"
},
  "geometry": {"coordinates":[8.241288,51.734715],"type":"Point"}
}