{
  "type": "Feature",
  "properties": {
    "iso:country":"DE",
    "sg:address":"B\u00f6tzinger Str. 31",
    "sg:city":"Freiburg",
    "sg:phone":"+49 761/452420",
    "sg:postcode":"79111",
    "sg:province":"Baden-W\u00fcrttemberg",
    "wof:name":"Spectral Gesellschaft F\u00fcr Lichttechnik Mbh",
    "wof:placetype":"venue"
},
  "geometry": {"coordinates":[7.787322,47.98592],"type":"Point"}
}