{
  "type": "Feature",
  "properties": {
    "iso:country":"DE",
    "sg:address":"Scillawaldstr. 72",
    "sg:city":"Stuttgart",
    "sg:phone":"+49 711/531313",
    "sg:postcode":"70378",
    "sg:province":"Baden-W\u00fcrttemberg",
    "wof:name":"Josef Lambert",
    "wof:placetype":"venue"
},
  "geometry": {"coordinates":[9.2251996994,48.8367843628],"type":"Point"}
}