{
  "type": "Feature",
  "properties": {
    "iso:country":"DE",
    "sg:address":"Maximilianstr. 27",
    "sg:city":"Traunstein",
    "sg:phone":"+49 861/4551",
    "sg:postcode":"83278",
    "sg:province":"Bayern",
    "wof:name":"Dagmar G\u00f6rschel",
    "wof:placetype":"venue"
},
  "geometry": {"coordinates":[12.64501,47.867455],"type":"Point"}
}