{
  "type": "Feature",
  "properties": {
    "iso:country":"DE",
    "sg:address":"Hohenlieth",
    "sg:city":"Holtsee",
    "sg:postcode":"24363",
    "sg:province":"Schleswig-Holstein",
    "wof:name":"Dr. Dietrich Brauer- Erben Beteiligung Kg",
    "wof:placetype":"venue"
},
  "geometry": {"coordinates":[9.88682,54.417511],"type":"Point"}
}