{
  "type": "Feature",
  "properties": {
    "iso:country":"DE",
    "sg:address":"Bahnhofstr. 51",
    "sg:city":"Owschlag",
    "sg:phone":"+49 4336/3210",
    "sg:postcode":"24811",
    "sg:province":"Schleswig-Holstein",
    "wof:name":"Dierk Haas",
    "wof:placetype":"venue"
},
  "geometry": {"coordinates":[9.5988378525,54.3915901184],"type":"Point"}
}