{
  "type": "Feature",
  "properties": {
    "iso:country":"DE",
    "sg:address":"Wiesenweg 44",
    "sg:city":"Hamb\u00fchren",
    "sg:phone":"+49 5084/6436",
    "sg:postcode":"29313",
    "sg:province":"Niedersachsen",
    "wof:name":"Restaurant Akropolis",
    "wof:placetype":"venue"
},
  "geometry": {"coordinates":[9.939991951,52.6366844177],"type":"Point"}
}