{
  "type": "Feature",
  "properties": {
    "iso:country":"DE",
    "sg:address":"Urbanstr. 31",
    "sg:city":"Plochingen",
    "sg:phone":"+49 7153/83560",
    "sg:postcode":"73207",
    "sg:province":"Baden-W\u00fcrttemberg",
    "wof:name":"Heinz Springmann Architekt",
    "wof:placetype":"venue"
},
  "geometry": {"coordinates":[9.416898,48.713318],"type":"Point"}
}