{
  "type": "Feature",
  "properties": {
    "iso:country":"DE",
    "sg:address":"Heideweg 2",
    "sg:city":"Kossa",
    "sg:phone":"+49 34243/26245",
    "sg:postcode":"04849",
    "sg:province":"Sachsen",
    "wof:name":"Walter M\u00fccke",
    "wof:placetype":"venue"
},
  "geometry": {"coordinates":[12.688395,51.616814],"type":"Point"}
}