{
  "type": "Feature",
  "properties": {
    "iso:country":"DE",
    "sg:address":"Doyenweg",
    "sg:city":"Soest",
    "sg:postcode":"59494",
    "sg:province":"Nordrhein-Westfalen",
    "wof:name":"Meister-markt Verwaltungsgesellschaft Mbh",
    "wof:placetype":"venue"
},
  "geometry": {"coordinates":[8.1303749084,51.5583267212],"type":"Point"}
}