{
  "type": "Feature",
  "properties": {
    "iso:country":"DE",
    "sg:address":"Klus 7",
    "sg:city":"Negenborn",
    "sg:phone":"+49 5532/8268",
    "sg:postcode":"37643",
    "sg:province":"Niedersachsen",
    "wof:name":"Wilfried Albrecht",
    "wof:placetype":"venue"
},
  "geometry": {"coordinates":[9.575085,51.892384],"type":"Point"}
}