{
  "type": "Feature",
  "properties": {
    "iso:country":"DE",
    "sg:address":"Oebisfelder Str. 3",
    "sg:city":"Kl\u00f6tze",
    "sg:postcode":"38486",
    "sg:province":"Sachsen-Anhalt",
    "wof:name":"Herbert Fuchs",
    "wof:placetype":"venue"
},
  "geometry": {"coordinates":[11.1599464417,52.6254234314],"type":"Point"}
}