{
  "type": "Feature",
  "properties": {
    "iso:country":"DE",
    "sg:address":"Hofangerstr. 49",
    "sg:city":"M\u00fcnchen",
    "sg:phone":"+49 89/408645",
    "sg:postcode":"81735",
    "sg:province":"Bayern",
    "wof:name":"Gerhard Wenzl Architekt",
    "wof:placetype":"venue"
},
  "geometry": {"coordinates":[11.629665,48.114162],"type":"Point"}
}