{
  "type": "Feature",
  "properties": {
    "iso:country":"DE",
    "sg:address":"S\u00e4ntisstr. 26",
    "sg:city":"\u00dcberlingen",
    "sg:phone":"+49 7551/65704",
    "sg:postcode":"88662",
    "sg:province":"Baden-W\u00fcrttemberg",
    "wof:name":"T. Pross Architekt",
    "wof:placetype":"venue"
},
  "geometry": {"coordinates":[9.140143,47.772442],"type":"Point"}
}