{
  "type": "Feature",
  "properties": {
    "iso:country":"DE",
    "sg:address":"Im Gettelhagen 98",
    "sg:city":"Braunschweig",
    "sg:postcode":"38108",
    "sg:province":"Niedersachsen",
    "wof:name":"K-bau Tiefbaugesellschaft Verwaltungs Gmbh",
    "wof:placetype":"venue"
},
  "geometry": {"coordinates":[10.5736761093,52.3024597168],"type":"Point"}
}