{
  "type": "Feature",
  "properties": {
    "iso:country":"DE",
    "sg:address":"Olandwinkel 3",
    "sg:city":"Kiel",
    "sg:phone":"+49 431/311583",
    "sg:postcode":"24107",
    "sg:province":"Schleswig-Holstein",
    "wof:name":"Hans Angermann Ingenieur",
    "wof:placetype":"venue"
},
  "geometry": {"coordinates":[10.0740270615,54.3596687317],"type":"Point"}
}