{
  "type": "Feature",
  "properties": {
    "iso:country":"DE",
    "sg:address":"Alt-K\u00f6penick 34",
    "sg:city":"Berlin",
    "sg:phone":"+49 30/6557525",
    "sg:postcode":"12555",
    "sg:province":"Berlin",
    "wof:name":"Norbert Stark & Co. - Porzel- Lan - Handels - Gmbh",
    "wof:placetype":"venue"
},
  "geometry": {"coordinates":[13.5739631653,52.4451293945],"type":"Point"}
}