{
  "type": "Feature",
  "properties": {
    "iso:country":"DE",
    "sg:address":"Marienstr. 14",
    "sg:city":"Friedrichshafen",
    "sg:phone":"+49 7541/21744",
    "sg:postcode":"88045",
    "sg:province":"Baden-W\u00fcrttemberg",
    "wof:name":"Eugen Molitor Inh. Jarko Bowitz E. K.",
    "wof:placetype":"venue"
},
  "geometry": {"coordinates":[9.4795455933,47.6550254822],"type":"Point"}
}