{
  "type": "Feature",
  "properties": {
    "iso:country":"DE",
    "sg:address":"Eichhorst",
    "sg:city":"Wittmoldt",
    "sg:postcode":"24306",
    "sg:province":"Schleswig-Holstein",
    "wof:name":"Peter Und Thie\u00df Luther Ohg",
    "wof:placetype":"venue"
},
  "geometry": {"coordinates":[10.3686304092,54.1891059875],"type":"Point"}
}