{
  "type": "Feature",
  "properties": {
    "iso:country":"DE",
    "sg:address":"Hauptstr. 16",
    "sg:city":"Dietfurt",
    "sg:phone":"+49 8464/229",
    "sg:postcode":"92345",
    "sg:province":"Bayern",
    "wof:name":"Benedikt Spitzer",
    "wof:placetype":"venue"
},
  "geometry": {"coordinates":[11.586858,49.035137],"type":"Point"}
}