{
  "type": "Feature",
  "properties": {
    "iso:country":"DE",
    "sg:address":"Schieringstr. 2",
    "sg:city":"Menslage",
    "sg:phone":"+49 5437/752",
    "sg:postcode":"49637",
    "sg:province":"Niedersachsen",
    "wof:name":"Hermann Wolke",
    "wof:placetype":"venue"
},
  "geometry": {"coordinates":[7.84609,52.653381],"type":"Point"}
}