{
  "type": "Feature",
  "properties": {
    "iso:country":"DE",
    "sg:address":"Weststr. 39-41",
    "sg:city":"Lemgo",
    "sg:phone":"+49 4952/6168068",
    "sg:postcode":"32657",
    "sg:province":"Nordrhein-Westfalen",
    "wof:name":"Readymix Beton Westfalen Gmbh",
    "wof:placetype":"venue"
},
  "geometry": {"coordinates":[8.8286657333,52.0343437195],"type":"Point"}
}