{
  "type": "Feature",
  "properties": {
    "iso:country":"DE",
    "sg:address":"Friedrichstr. 153",
    "sg:city":"Berlin",
    "sg:phone":"+49 30/2787902",
    "sg:postcode":"10117",
    "sg:province":"Berlin",
    "wof:name":"Gro\u00df & Partner Bautr\u00e4ger- Und Baubetreuungsges. Mbh & Co.",
    "wof:placetype":"venue"
},
  "geometry": {"coordinates":[13.388459,52.517845],"type":"Point"}
}