{
  "type": "Feature",
  "properties": {
    "iso:country":"DE",
    "sg:address":"Roggenkamp 1",
    "sg:city":"Bad Iburg",
    "sg:phone":"+49 5403/757",
    "sg:postcode":"49186",
    "sg:province":"Niedersachsen",
    "wof:name":"W. Picker",
    "wof:placetype":"venue"
},
  "geometry": {"coordinates":[8.020975,52.142784],"type":"Point"}
}