{
  "type": "Feature",
  "properties": {
    "iso:country":"DE",
    "sg:address":"Bergstr. 14",
    "sg:city":"Hunding",
    "sg:phone":"+49 9904/528",
    "sg:postcode":"94551",
    "sg:province":"Bayern",
    "wof:name":"Franz Wei\u00df",
    "wof:placetype":"venue"
},
  "geometry": {"coordinates":[13.159078598,48.8443145752],"type":"Point"}
}