{
  "type": "Feature",
  "properties": {
    "iso:country":"DE",
    "sg:address":"Calauer Chaussee 2",
    "sg:city":"Boblitz",
    "sg:phone":"+49 3542/43341",
    "sg:postcode":"03222",
    "sg:province":"Brandenburg",
    "wof:name":"Terra Baumaschinenvertriebs- Gesellschaft Mbh",
    "wof:placetype":"venue"
},
  "geometry": {"coordinates":[13.975232,51.840839],"type":"Point"}
}