{
  "type": "Feature",
  "properties": {
    "iso:country":"DE",
    "sg:address":"Dorfstr. 17",
    "sg:city":"Heikendorf",
    "sg:phone":"+49 431/241944",
    "sg:postcode":"24226",
    "sg:province":"Schleswig-Holstein",
    "wof:name":"Provinzial Versicherungen",
    "wof:placetype":"venue"
},
  "geometry": {"coordinates":[10.2048768997,54.3704605103],"type":"Point"}
}