{
  "type": "Feature",
  "properties": {
    "iso:country":"DE",
    "sg:address":"Lackerbauerstr. 9",
    "sg:city":"M\u00fcnchen",
    "sg:phone":"+49 89/888644",
    "sg:postcode":"81241",
    "sg:province":"Bayern",
    "wof:name":"Publimed Verlag Gmbh",
    "wof:placetype":"venue"
},
  "geometry": {"coordinates":[11.4653186798,48.1393814087],"type":"Point"}
}