{
  "type": "Feature",
  "properties": {
    "iso:country":"DE",
    "sg:city":"Frankfurt/Main",
    "sg:phone":"+49 69/21770",
    "sg:postcode":"60311",
    "sg:province":"Hessen",
    "wof:name":"Bethmann Bank",
    "wof:placetype":"venue"
},
  "geometry": {"coordinates":[8.68342,50.112041],"type":"Point"}
}