{
  "type": "Feature",
  "properties": {
    "iso:country":"DE",
    "sg:address":"Frankstr. 9",
    "sg:city":"Hagen",
    "sg:phone":"+49 2331/43438",
    "sg:postcode":"58135",
    "sg:province":"Nordrhein-Westfalen",
    "wof:name":"Ev. Pfarramt Hagen-haspe",
    "wof:placetype":"venue"
},
  "geometry": {"coordinates":[7.4202799797,51.348575592],"type":"Point"}
}