{
  "type": "Feature",
  "properties": {
    "iso:country":"DE",
    "sg:address":"Winterbacher Str. 1 u.3",
    "sg:city":"Remshalden",
    "sg:phone":"+49 7181/45061",
    "sg:postcode":"73630",
    "sg:province":"Baden-W\u00fcrttemberg",
    "wof:name":"Restaurant Lamm",
    "wof:placetype":"venue"
},
  "geometry": {"coordinates":[9.4428787231,48.8098907471],"type":"Point"}
}