{
  "type": "Feature",
  "properties": {
    "iso:country":"DE",
    "sg:address":"Mannheimer Str. 52",
    "sg:city":"Kaiserslautern",
    "sg:phone":"+49 631/67270",
    "sg:postcode":"67655",
    "sg:province":"Rheinland-Pfalz",
    "wof:name":"E. Frank",
    "wof:placetype":"venue"
},
  "geometry": {"coordinates":[7.7808089256,49.4458274841],"type":"Point"}
}