{
  "type": "Feature",
  "properties": {
    "iso:country":"DE",
    "sg:address":"21745",
    "sg:city":"Hemmoor",
    "sg:phone":"+49 4771/3343",
    "sg:postcode":"21745",
    "sg:province":"Niedersachsen",
    "wof:name":"Schwimmhalle",
    "wof:placetype":"venue"
},
  "geometry": {"coordinates":[9.14083004,53.6832389832],"type":"Point"}
}