{
  "type": "Feature",
  "properties": {
    "iso:country":"DE",
    "sg:address":"Mannhardtstr. 6",
    "sg:city":"M\u00fcnchen",
    "sg:postcode":"80538",
    "sg:province":"Bayern",
    "wof:name":"Margo Beteiligungs Gmbh & Co. Vermietungs-kg",
    "wof:placetype":"venue"
},
  "geometry": {"coordinates":[11.585308,48.135189],"type":"Point"}
}