{
  "type": "Feature",
  "properties": {
    "iso:country":"DE",
    "sg:address":"Haager Str. 40",
    "sg:city":"Erding",
    "sg:phone":"+49 8122/92571",
    "sg:postcode":"85435",
    "sg:province":"Bayern",
    "wof:name":"Elke Steinh\u00e4user",
    "wof:placetype":"venue"
},
  "geometry": {"coordinates":[11.9083709717,48.3011169434],"type":"Point"}
}