{
  "type": "Feature",
  "properties": {
    "iso:country":"DE",
    "sg:address":"Holthorster Weg 19",
    "sg:city":"Schwanewede",
    "sg:phone":"+49 421/621172",
    "sg:postcode":"28790",
    "sg:province":"Niedersachsen",
    "wof:name":"Arbeitsgruppe Stoffwechsel- Forschung Bremen E. V.",
    "wof:placetype":"venue"
},
  "geometry": {"coordinates":[8.6630916595,53.1862564087],"type":"Point"}
}