{
  "type": "Feature",
  "properties": {
    "iso:country":"DE",
    "sg:address":"L\u00fcnener Str. 120",
    "sg:city":"Hamm",
    "sg:postcode":"59077",
    "sg:province":"Nordrhein-Westfalen",
    "wof:name":"Nwc Beteiligungen Gmbh",
    "wof:placetype":"venue"
},
  "geometry": {"coordinates":[7.736969,51.671738],"type":"Point"}
}