{
  "type": "Feature",
  "properties": {
    "iso:country":"DE",
    "sg:address":"Abteistr. 47",
    "sg:city":"Hamburg",
    "sg:phone":"+49 40/418343",
    "sg:postcode":"20149",
    "sg:province":"Hamburg",
    "wof:name":"Grundst\u00fccksverwaltungs- Gesellschaft Hohenufer Mbh",
    "wof:placetype":"venue"
},
  "geometry": {"coordinates":[9.9900503159,53.579875946],"type":"Point"}
}