{
  "type": "Feature",
  "properties": {
    "iso:country":"DE",
    "sg:address":"Twistetalstr. 36",
    "sg:city":"Warburg",
    "sg:phone":"+49 5641/5851",
    "sg:postcode":"34414",
    "sg:province":"Nordrhein-Westfalen",
    "wof:name":"Heinrich Floren",
    "wof:placetype":"venue"
},
  "geometry": {"coordinates":[9.137064,51.474682],"type":"Point"}
}