{
  "type": "Feature",
  "properties": {
    "iso:country":"DE",
    "sg:address":"Hafenm\u00fchlweg 22",
    "sg:city":"Augsburg",
    "sg:phone":"+49 821/701509",
    "sg:postcode":"86169",
    "sg:province":"Bayern",
    "wof:name":"Hermann M\u00fcller",
    "wof:placetype":"venue"
},
  "geometry": {"coordinates":[10.912422,48.404018],"type":"Point"}
}