{
  "type": "Feature",
  "properties": {
    "iso:country":"DE",
    "sg:address":"Im Uhlenbusch 4",
    "sg:city":"Rosengarten",
    "sg:phone":"+49 40/79717811",
    "sg:postcode":"21224",
    "sg:province":"Niedersachsen",
    "wof:name":"Handelsverpackungen Erik Bintz",
    "wof:placetype":"venue"
},
  "geometry": {"coordinates":[9.893348,53.453346],"type":"Point"}
}