{
  "type": "Feature",
  "properties": {
    "iso:country":"DE",
    "sg:address":"Lengenlocher Str. 27",
    "sg:city":"Altensteig",
    "sg:postcode":"72213",
    "sg:province":"Baden-W\u00fcrttemberg",
    "wof:name":"H. I. S. Vertriebsges. F. Gesundheitsger\u00e4te Mbh",
    "wof:placetype":"venue"
},
  "geometry": {"coordinates":[8.5742893219,48.597946167],"type":"Point"}
}