{
  "type": "Feature",
  "properties": {
    "iso:country":"DE",
    "sg:address":"Enoch-Widman-Str. 1",
    "sg:city":"Hof",
    "sg:phone":"+49 9281/41716",
    "sg:postcode":"95028",
    "sg:province":"Bayern",
    "wof:name":"Pizzeria La Romantica",
    "wof:placetype":"venue"
},
  "geometry": {"coordinates":[11.9238319397,50.3220252991],"type":"Point"}
}