{
  "type": "Feature",
  "properties": {
    "iso:country":"DE",
    "sg:address":"Br\u00e4uhausstr. 15",
    "sg:city":"Berchtesgaden",
    "sg:phone":"+49 8652/1423",
    "sg:postcode":"83471",
    "sg:province":"Bayern",
    "wof:name":"Br\u00e4ust\u00fcberl",
    "wof:placetype":"venue"
},
  "geometry": {"coordinates":[13.0070419312,47.6343536377],"type":"Point"}
}