{
  "type": "Feature",
  "properties": {
    "iso:country":"DE",
    "sg:address":"Am Pferdeteich 4",
    "sg:city":"K\u00f6lleda",
    "sg:phone":"+49 3635/463900",
    "sg:postcode":"99625",
    "sg:province":"Th\u00fcringen",
    "wof:name":"Wacker Werbung",
    "wof:placetype":"venue"
},
  "geometry": {"coordinates":[11.243505,51.188587],"type":"Point"}
}