{
  "type": "Feature",
  "properties": {
    "iso:country":"DE",
    "sg:address":"Annastr. 2",
    "sg:city":"Augsburg",
    "sg:phone":"+49 821/30227",
    "sg:postcode":"86150",
    "sg:province":"Bayern",
    "wof:name":"Falk",
    "wof:placetype":"venue"
},
  "geometry": {"coordinates":[10.895778,48.369755],"type":"Point"}
}