{
  "type": "Feature",
  "properties": {
    "iso:country":"DE",
    "sg:address":"Goethestr. 5",
    "sg:city":"Lauter",
    "sg:phone":"+49 3771/256345",
    "sg:postcode":"08312",
    "sg:province":"Sachsen",
    "wof:name":"Hanskarl Morgenstern",
    "wof:placetype":"venue"
},
  "geometry": {"coordinates":[12.735752,50.559299],"type":"Point"}
}