{
  "type": "Feature",
  "properties": {
    "iso:country":"DE",
    "sg:address":"Kandelstr.2",
    "sg:city":"Gundelfingen",
    "sg:phone":"+49 4976/1584593",
    "sg:postcode":"89423",
    "sg:province":"Bayern",
    "wof:name":"Dresdner Bank",
    "wof:placetype":"venue"
},
  "geometry": {"coordinates":[7.869057,48.043201],"type":"Point"}
}