{
  "type": "Feature",
  "properties": {
    "iso:country":"DE",
    "sg:address":"Erhard-Dressel-Bogen 12 b",
    "sg:city":"Hamburg",
    "sg:phone":"+49 40/7131674",
    "sg:postcode":"22115",
    "sg:province":"Hamburg",
    "wof:name":"Peter Gerke",
    "wof:placetype":"venue"
},
  "geometry": {"coordinates":[10.137056,53.535412],"type":"Point"}
}