{
  "type": "Feature",
  "properties": {
    "iso:country":"DE",
    "sg:address":"Eich 20",
    "sg:city":"Wermelskirchen",
    "sg:phone":"+49 2196/4639",
    "sg:postcode":"42929",
    "sg:province":"Nordrhein-Westfalen",
    "wof:name":"Heinz Becher",
    "wof:placetype":"venue"
},
  "geometry": {"coordinates":[7.21137,51.13776],"type":"Point"}
}