{
  "type": "Feature",
  "properties": {
    "iso:country":"DE",
    "sg:address":"Dalheimer Str. 9",
    "sg:city":"Bad W\u00fcnnenberg",
    "sg:phone":"+49 2957/494",
    "sg:postcode":"33181",
    "sg:province":"Nordrhein-Westfalen",
    "wof:name":"Hubert Niggemeyer",
    "wof:placetype":"venue"
},
  "geometry": {"coordinates":[8.771332,51.571114],"type":"Point"}
}