{
  "type": "Feature",
  "properties": {
    "iso:country":"DE",
    "sg:address":"M\u00fchlheimer Str. 47",
    "sg:city":"Empfingen",
    "sg:phone":"+49 7485/228",
    "sg:postcode":"72186",
    "sg:province":"Baden-W\u00fcrttemberg",
    "wof:name":"K. Baiker",
    "wof:placetype":"venue"
},
  "geometry": {"coordinates":[8.7071428299,48.3911209106],"type":"Point"}
}