{
  "type": "Feature",
  "properties": {
    "iso:country":"DE",
    "sg:address":"Triftstr. 34",
    "sg:city":"Prenzlau",
    "sg:phone":"+49 3984/2413",
    "sg:postcode":"17291",
    "sg:province":"Brandenburg",
    "wof:name":"Eiscafe Oase",
    "wof:placetype":"venue"
},
  "geometry": {"coordinates":[13.862132,53.324471],"type":"Point"}
}