{
  "type": "Feature",
  "properties": {
    "iso:country":"DE",
    "sg:address":"Ludwig-Thoma-Str. 21",
    "sg:city":"Rottach-Egern",
    "sg:phone":"+49 8022/95566",
    "sg:postcode":"83700",
    "sg:province":"Bayern",
    "wof:name":"Susanne Neumaier",
    "wof:placetype":"venue"
},
  "geometry": {"coordinates":[11.773294,47.691124],"type":"Point"}
}