{
  "type": "Feature",
  "properties": {
    "iso:country":"DE",
    "sg:address":"L\u00fctgendortmunder Hellweg 166",
    "sg:city":"Dortmund",
    "sg:phone":"+49 231/697010",
    "sg:postcode":"44388",
    "sg:province":"Nordrhein-Westfalen",
    "wof:name":"W. L\u00f6bbert",
    "wof:placetype":"venue"
},
  "geometry": {"coordinates":[7.35966,51.49781],"type":"Point"}
}