{
  "type": "Feature",
  "properties": {
    "iso:country":"DE",
    "sg:address":"Laustr. 3",
    "sg:city":"Stuttgart",
    "sg:phone":"+49 711/7654440",
    "sg:postcode":"70597",
    "sg:province":"Baden-W\u00fcrttemberg",
    "wof:name":"Apotheke Am Sonnenberg",
    "wof:placetype":"venue"
},
  "geometry": {"coordinates":[9.153223,48.741634],"type":"Point"}
}