{
  "type": "Feature",
  "properties": {
    "iso:country":"DE",
    "sg:address":"Klosterhof 12",
    "sg:city":"Meldorf",
    "sg:phone":"+49 4832/9272",
    "sg:postcode":"25704",
    "sg:province":"Schleswig-Holstein",
    "wof:name":"Michael Strate",
    "wof:placetype":"venue"
},
  "geometry": {"coordinates":[9.0742177963,54.0911140442],"type":"Point"}
}