{
  "type": "Feature",
  "properties": {
    "iso:country":"DE",
    "sg:address":"Hauptstr. 17-19",
    "sg:city":"Nordhorn",
    "sg:phone":"+49 5921/89385",
    "sg:postcode":"48529",
    "sg:province":"Niedersachsen",
    "wof:name":"Yaska",
    "wof:placetype":"venue"
},
  "geometry": {"coordinates":[7.070433,52.435287],"type":"Point"}
}