{
  "type": "Feature",
  "properties": {
    "iso:country":"DE",
    "sg:address":"Wallbergstr. 19 a",
    "sg:city":"Poing",
    "sg:phone":"+49 8121/7499",
    "sg:postcode":"85586",
    "sg:province":"Bayern",
    "wof:name":"Sr-bau Gmbh",
    "wof:placetype":"venue"
},
  "geometry": {"coordinates":[11.8262,48.167564],"type":"Point"}
}