{
  "type": "Feature",
  "properties": {
    "iso:country":"DE",
    "sg:address":"Am Beiberg 10",
    "sg:city":"Bopfingen",
    "sg:phone":"+49 7362/7140",
    "sg:postcode":"73441",
    "sg:province":"Baden-W\u00fcrttemberg",
    "wof:name":"Hermann Heindel",
    "wof:placetype":"venue"
},
  "geometry": {"coordinates":[10.3600082397,48.8486404419],"type":"Point"}
}