{
  "type": "Feature",
  "properties": {
    "iso:country":"DE",
    "sg:address":"Dorfstr. 9",
    "sg:city":"Pretzsch",
    "sg:phone":"+49 34445/20381",
    "sg:postcode":"06667",
    "sg:province":"Sachsen-Anhalt",
    "wof:name":"Werner Hofmann",
    "wof:placetype":"venue"
},
  "geometry": {"coordinates":[11.94517,51.092728],"type":"Point"}
}