{
  "type": "Feature",
  "properties": {
    "iso:country":"DE",
    "sg:address":"Hauptstr. 49",
    "sg:city":"Hausach",
    "sg:phone":"+49 7831/239",
    "sg:postcode":"77756",
    "sg:province":"Baden-W\u00fcrttemberg",
    "wof:name":"Hermann Winterer",
    "wof:placetype":"venue"
},
  "geometry": {"coordinates":[8.168223381,48.2837486267],"type":"Point"}
}