{
  "type": "Feature",
  "properties": {
    "iso:country":"DE",
    "sg:address":"Hauptstr. 49",
    "sg:city":"Nordhorn",
    "sg:phone":"+49 5921/77206",
    "sg:postcode":"48529",
    "sg:province":"Niedersachsen",
    "wof:name":"Kochl\u00f6ffel Gmbh",
    "wof:placetype":"venue"
},
  "geometry": {"coordinates":[7.0701088905,52.4368400574],"type":"Point"}
}