{
  "type": "Feature",
  "properties": {
    "iso:country":"DE",
    "sg:address":"K\u00f6nigsberger Str. 24",
    "sg:city":"Bodenfelde",
    "sg:phone":"+49 5572/7538",
    "sg:postcode":"37194",
    "sg:province":"Hessen",
    "wof:name":"Hannelore Knipping",
    "wof:placetype":"venue"
},
  "geometry": {"coordinates":[9.54526,51.642551],"type":"Point"}
}