{
  "type": "Feature",
  "properties": {
    "iso:country":"DE",
    "sg:address":"Georg-Leinfelder-Str. 19",
    "sg:city":"Schrobenhausen",
    "sg:phone":"+49 8252/1430",
    "sg:postcode":"86529",
    "sg:province":"Bayern",
    "wof:name":"Hallenbad",
    "wof:placetype":"venue"
},
  "geometry": {"coordinates":[11.2696504593,48.5568351746],"type":"Point"}
}