{
  "type": "Feature",
  "properties": {
    "iso:country":"DE",
    "sg:address":"Roderbruchstr. 9",
    "sg:city":"Hannover",
    "sg:phone":"+49 511/5490865",
    "sg:postcode":"30655",
    "sg:province":"Niedersachsen",
    "wof:name":"Herbert Schwarzer",
    "wof:placetype":"venue"
},
  "geometry": {"coordinates":[9.803024292,52.3961219788],"type":"Point"}
}