{
  "type": "Feature",
  "properties": {
    "iso:country":"DE",
    "sg:address":"Untergasse",
    "sg:city":"Grolsheim",
    "sg:phone":"+49 6727/8513",
    "sg:postcode":"55459",
    "sg:province":"Rheinland-Pfalz",
    "wof:name":"Hiltrud Fogt",
    "wof:placetype":"venue"
},
  "geometry": {"coordinates":[7.91254282,49.9094200134],"type":"Point"}
}