{
  "type": "Feature",
  "properties": {
    "iso:country":"DE",
    "sg:address":"Stephanstr. 33",
    "sg:city":"Stuttgart",
    "sg:phone":"+49 711/292506",
    "sg:postcode":"70173",
    "sg:province":"Baden-W\u00fcrttemberg",
    "wof:name":"Marquardt-garagen",
    "wof:placetype":"venue"
},
  "geometry": {"coordinates":[9.1786270142,48.7802619934],"type":"Point"}
}