{
  "type": "Feature",
  "properties": {
    "iso:country":"DE",
    "sg:address":"Badhausweg 12",
    "sg:city":"Karlsbad",
    "sg:phone":"+49 7084/5100",
    "sg:postcode":"76307",
    "sg:province":"Baden-W\u00fcrttemberg",
    "wof:name":"Achim L\u00f6tterle",
    "wof:placetype":"venue"
},
  "geometry": {"coordinates":[8.507353,48.882408],"type":"Point"}
}