{
  "type": "Feature",
  "properties": {
    "iso:country":"DE",
    "sg:address":"Blankeneser Bahnhofstr. 38",
    "sg:city":"Hamburg",
    "sg:phone":"+49 40/8662071",
    "sg:postcode":"22587",
    "sg:province":"Hamburg",
    "wof:name":"Anja Mordhorst Rechtsanw\u00e4ltin",
    "wof:placetype":"venue"
},
  "geometry": {"coordinates":[9.8113718033,53.5612640381],"type":"Point"}
}