{
  "type": "Feature",
  "properties": {
    "iso:country":"DE",
    "sg:address":"Feuerbacher-Tal-Str. 22 A",
    "sg:city":"Stuttgart",
    "sg:postcode":"70469",
    "sg:province":"Baden-W\u00fcrttemberg",
    "wof:name":"Nachbar In Not In Baden-w\u00fcrtt. E. V.",
    "wof:placetype":"venue"
},
  "geometry": {"coordinates":[9.1562328339,48.8070602417],"type":"Point"}
}