{
  "type": "Feature",
  "properties": {
    "iso:country":"DE",
    "sg:address":"R\u00f6pkestra\u00dfe",
    "sg:city":"Hannover",
    "sg:phone":"+49 511/49998877",
    "sg:postcode":"30173",
    "sg:province":"Niedersachsen",
    "wof:name":"Springbok Sportwagen",
    "wof:placetype":"venue"
},
  "geometry": {"coordinates":[9.7779006958,52.3689651489],"type":"Point"}
}