{
  "type": "Feature",
  "properties": {
    "iso:country":"DE",
    "sg:address":"Palmstr. 14",
    "sg:city":"Chemnitz",
    "sg:phone":"+49 371/413671",
    "sg:postcode":"09130",
    "sg:province":"Sachsen",
    "wof:name":"Wolfgang Schlenkrich",
    "wof:placetype":"venue"
},
  "geometry": {"coordinates":[12.9393959045,50.8431358337],"type":"Point"}
}