{
  "type": "Feature",
  "properties": {
    "iso:country":"DE",
    "sg:address":"Im Hagenacker 11",
    "sg:city":"Waldshut-Tiengen",
    "sg:phone":"+49 7751/2405",
    "sg:postcode":"79761",
    "sg:province":"Baden-W\u00fcrttemberg",
    "wof:name":"Ralf Sibold Gmbh & Co. Kg",
    "wof:placetype":"venue"
},
  "geometry": {"coordinates":[8.1881723404,47.6141357422],"type":"Point"}
}