{
  "type": "Feature",
  "properties": {
    "iso:country":"DE",
    "sg:address":"Berliner Str. 41",
    "sg:city":"Bad Freienwalde",
    "sg:phone":"+49 3344/3432",
    "sg:postcode":"16259",
    "sg:province":"Brandenburg",
    "wof:name":"M. Gro\u00dfmann",
    "wof:placetype":"venue"
},
  "geometry": {"coordinates":[14.0229682922,52.7808151245],"type":"Point"}
}