{
  "type": "Feature",
  "properties": {
    "iso:country":"DE",
    "sg:address":"Industriestr 33",
    "sg:city":"Heinsberg",
    "sg:phone":"+49 2452/91330",
    "sg:postcode":"52525",
    "sg:province":"Nordrhein-Westfalen",
    "wof:name":"Randerath Elektrotechnik Gmbh",
    "wof:placetype":"venue"
},
  "geometry": {"coordinates":[6.13678,51.064709],"type":"Point"}
}