{
  "type": "Feature",
  "properties": {
    "iso:country":"DE",
    "sg:address":"Frankfurter Str. 35",
    "sg:city":"M\u00f6rfelden-Walldorf",
    "sg:phone":"+49 6105/277654",
    "sg:postcode":"64546",
    "sg:province":"Hessen",
    "wof:name":"Alfred Otto",
    "wof:placetype":"venue"
},
  "geometry": {"coordinates":[8.56943,49.978535],"type":"Point"}
}