{
  "type": "Feature",
  "properties": {
    "iso:country":"DE",
    "sg:address":"Obergasse 18",
    "sg:city":"Uelversheim",
    "sg:phone":"+49 6249/8387",
    "sg:postcode":"55278",
    "sg:province":"Rheinland-Pfalz",
    "wof:name":"B. Duttenh\u00f6fer",
    "wof:placetype":"venue"
},
  "geometry": {"coordinates":[8.2897987366,49.810295105],"type":"Point"}
}