{
  "type": "Feature",
  "properties": {
    "iso:country":"DE",
    "sg:address":"Robert-Bosch-Str. 4 Rath-Anhoven",
    "sg:city":"Wegberg",
    "sg:phone":"+49 2431/943480",
    "sg:postcode":"41844",
    "sg:province":"Nordrhein-Westfalen",
    "wof:name":"Pechtheiden Landtechnik Inh.johannes Peter Clev Ek.",
    "wof:placetype":"venue"
},
  "geometry": {"coordinates":[6.278691,51.14156],"type":"Point"}
}