{
  "type": "Feature",
  "properties": {
    "iso:country":"DE",
    "sg:address":"Vor dem Hannoverschen Tor 1",
    "sg:city":"Burgdorf",
    "sg:postcode":"31303",
    "sg:province":"Niedersachsen",
    "wof:name":"Stadtwerke Burgdorf Gmbh",
    "wof:placetype":"venue"
},
  "geometry": {"coordinates":[10.0039,52.445332],"type":"Point"}
}