{
  "type": "Feature",
  "properties": {
    "iso:country":"DE",
    "sg:address":"Herzogin-Elisabeth-Str. 16",
    "sg:city":"Braunschweig",
    "sg:phone":"+49 531/75896",
    "sg:postcode":"38104",
    "sg:province":"Niedersachsen",
    "wof:name":"Die Hanse Herbert Brandes Ohg",
    "wof:placetype":"venue"
},
  "geometry": {"coordinates":[10.550444,52.265354],"type":"Point"}
}