{
  "type": "Feature",
  "properties": {
    "iso:country":"DE",
    "sg:address":"Herknerstr 4",
    "sg:city":"Weingarten",
    "sg:phone":"+49 7564/3475",
    "sg:postcode":"88250",
    "sg:province":"Baden-W\u00fcrttemberg",
    "wof:name":"Scheck Gmbh & Co Kg",
    "wof:placetype":"venue"
},
  "geometry": {"coordinates":[9.8861913681,47.9108695984],"type":"Point"}
}