{
  "type": "Feature",
  "properties": {
    "iso:country":"DE",
    "sg:address":"Clemens-August-Str. 56-58",
    "sg:city":"Arnsberg",
    "sg:phone":"+49 2931/16966",
    "sg:postcode":"59821",
    "sg:province":"Nordrhein-Westfalen",
    "wof:name":"Rats-apotheke",
    "wof:placetype":"venue"
},
  "geometry": {"coordinates":[8.069355,51.399536],"type":"Point"}
}