{
  "type": "Feature",
  "properties": {
    "iso:country":"DE",
    "sg:address":"Willst\u00e4tterstr. 9",
    "sg:city":"D\u00fcsseldorf",
    "sg:phone":"+49 211/5374150",
    "sg:postcode":"40549",
    "sg:province":"Nordrhein-Westfalen",
    "wof:name":"X-map Ag",
    "wof:placetype":"venue"
},
  "geometry": {"coordinates":[6.7138929367,51.2399940491],"type":"Point"}
}