{
  "type": "Feature",
  "properties": {
    "iso:country":"DE",
    "sg:address":"Wilhelm-Kraft-Str. 18",
    "sg:city":"Sprockh\u00f6vel",
    "sg:phone":"+49 2339/910791",
    "sg:postcode":"45549",
    "sg:province":"Nordrhein-Westfalen",
    "wof:name":"M. Strah",
    "wof:placetype":"venue"
},
  "geometry": {"coordinates":[7.2747540474,51.3319511414],"type":"Point"}
}