{
  "type": "Feature",
  "properties": {
    "iso:country":"DE",
    "sg:address":"Am Rech 4",
    "sg:city":"R\u00fcdesheim am Rhein",
    "sg:phone":"+49 6722/2954",
    "sg:postcode":"65385",
    "sg:province":"Hessen",
    "wof:name":"Reuter Mineral\u00f6le Und Kraftfahrzeughandel Ohg",
    "wof:placetype":"venue"
},
  "geometry": {"coordinates":[7.933125,49.994999],"type":"Point"}
}