{
  "type": "Feature",
  "properties": {
    "iso:country":"DE",
    "sg:address":"Timmendorfer Platz 3",
    "sg:city":"Timmendorfer Strand",
    "sg:phone":"+49 4503/2315",
    "sg:postcode":"23669",
    "sg:province":"Schleswig-Holstein",
    "wof:name":"Bernd Und Ellen Schumann",
    "wof:placetype":"venue"
},
  "geometry": {"coordinates":[10.7815551758,53.9981117249],"type":"Point"}
}