{
  "type": "Feature",
  "properties": {
    "iso:country":"DE",
    "sg:address":"Benzstr. 2",
    "sg:city":"Ketsch",
    "sg:phone":"+49 6202/69990",
    "sg:postcode":"68775",
    "sg:province":"Baden-W\u00fcrttemberg",
    "wof:name":"Fischer Kindermann Schlesinger",
    "wof:placetype":"venue"
},
  "geometry": {"coordinates":[8.5384674072,49.3638648987],"type":"Point"}
}