{
  "type": "Feature",
  "properties": {
    "iso:country":"DE",
    "sg:address":"Hohlgasse 22a",
    "sg:city":"Kirchzarten",
    "sg:phone":"+49 7661/5339",
    "sg:postcode":"79199",
    "sg:province":"Baden-W\u00fcrttemberg",
    "wof:name":"Konrad Goldschmidt",
    "wof:placetype":"venue"
},
  "geometry": {"coordinates":[7.9755821228,47.9580802917],"type":"Point"}
}