{
  "type": "Feature",
  "properties": {
    "iso:country":"DE",
    "sg:address":"Parkstr. 45 b",
    "sg:city":"Nidda",
    "sg:phone":"+49 171 2295174",
    "sg:postcode":"63667",
    "sg:province":"Hessen",
    "wof:name":"G\u00fcnther Gremlica",
    "wof:placetype":"venue"
},
  "geometry": {"coordinates":[8.97214,50.407158],"type":"Point"}
}