{
  "type": "Feature",
  "properties": {
    "iso:country":"DE",
    "sg:address":"Niederes Feld",
    "sg:city":"Hameln",
    "sg:phone":"+49 5151",
    "sg:postcode":"31789",
    "sg:province":"Niedersachsen",
    "wof:name":"Tv-store",
    "wof:placetype":"venue"
},
  "geometry": {"coordinates":[9.4060850143,52.1013793945],"type":"Point"}
}