{
  "type": "Feature",
  "properties": {
    "iso:country":"DE",
    "sg:address":"Ollenhauerstr. 113",
    "sg:city":"Berlin",
    "sg:phone":"+49 30/396400",
    "sg:postcode":"13403",
    "sg:province":"Berlin",
    "wof:name":"Cts-contrast Steuerberatungs- Gmbh",
    "wof:placetype":"venue"
},
  "geometry": {"coordinates":[13.329451561,52.5689239502],"type":"Point"}
}