{
  "type": "Feature",
  "properties": {
    "iso:country":"DE",
    "sg:address":"Corbiestr. 38",
    "sg:city":"H\u00f6xter",
    "sg:phone":"+49 5271/2429",
    "sg:postcode":"37671",
    "sg:province":"Nordrhein-Westfalen",
    "wof:name":"H. Wemmels-apotheke",
    "wof:placetype":"venue"
},
  "geometry": {"coordinates":[9.381978,51.776718],"type":"Point"}
}