{
  "type": "Feature",
  "properties": {
    "iso:country":"DE",
    "sg:address":"Hamburger Str. 152",
    "sg:city":"Hamburg",
    "sg:postcode":"22083",
    "sg:province":"Hamburg",
    "wof:name":"Weischer Medien-service Kg",
    "wof:placetype":"venue"
},
  "geometry": {"coordinates":[10.0380001068,53.5764312744],"type":"Point"}
}