{
  "type": "Feature",
  "properties": {
    "iso:country":"DE",
    "sg:address":"Klinikumallee 41 c",
    "sg:city":"Bayreuth",
    "sg:phone":"+49 921/42721",
    "sg:postcode":"95445",
    "sg:province":"Bayern",
    "wof:name":"Horn-international-gbr",
    "wof:placetype":"venue"
},
  "geometry": {"coordinates":[11.538679,49.943684],"type":"Point"}
}