{
  "type": "Feature",
  "properties": {
    "iso:country":"DE",
    "sg:address":"Ebenhausen 6",
    "sg:city":"Pfeffenhausen",
    "sg:phone":"+49 8782/941001",
    "sg:postcode":"84076",
    "sg:province":"Bayern",
    "wof:name":"Program Betriebswirt- Schaftliche Beratung Und",
    "wof:placetype":"venue"
},
  "geometry": {"coordinates":[11.9518594742,48.680847168],"type":"Point"}
}