{
  "type": "Feature",
  "properties": {
    "iso:country":"DE",
    "sg:address":"Stresemannstr. 18",
    "sg:city":"Hagen",
    "sg:phone":"+49 2331/32787",
    "sg:postcode":"58095",
    "sg:province":"Nordrhein-Westfalen",
    "wof:name":"D. Heyer",
    "wof:placetype":"venue"
},
  "geometry": {"coordinates":[7.4627799988,51.360710144],"type":"Point"}
}