{
  "type": "Feature",
  "properties": {
    "iso:country":"DE",
    "sg:address":"Horstweg 31",
    "sg:city":"Berlin",
    "sg:phone":"+49 30/3228024",
    "sg:postcode":"14059",
    "sg:province":"Berlin",
    "wof:name":"Varu Bau Gmbh",
    "wof:placetype":"venue"
},
  "geometry": {"coordinates":[13.291597,52.51231],"type":"Point"}
}