{
  "type": "Feature",
  "properties": {
    "iso:country":"DE",
    "sg:address":"Am Altenhof 21",
    "sg:city":"Ratingen",
    "sg:phone":"+49 2102/67425",
    "sg:postcode":"40883",
    "sg:province":"Nordrhein-Westfalen",
    "wof:name":"Edgar Gutsmann Steuerberater",
    "wof:placetype":"venue"
},
  "geometry": {"coordinates":[6.9087128639,51.3323631287],"type":"Point"}
}