{
  "type": "Feature",
  "properties": {
    "iso:country":"DE",
    "sg:address":"Rathausstr. 1",
    "sg:city":"Bad Driburg",
    "sg:phone":"+49 5253/2391",
    "sg:postcode":"33014",
    "sg:province":"Nordrhein-Westfalen",
    "wof:name":"Kur-lichtspiele",
    "wof:placetype":"venue"
},
  "geometry": {"coordinates":[9.024408,51.73439],"type":"Point"}
}