{
  "type": "Feature",
  "properties": {
    "iso:country":"DE",
    "sg:address":"Im T\u00e4lchen 18",
    "sg:city":"K\u00f6nigswinter",
    "sg:phone":"+49 2223/24833",
    "sg:postcode":"53639",
    "sg:province":"Nordrhein-Westfalen",
    "wof:name":"Ingeborg Chrysant-plitz Steuerberaterin",
    "wof:placetype":"venue"
},
  "geometry": {"coordinates":[7.1908397675,50.6775550842],"type":"Point"}
}