{
  "type": "Feature",
  "properties": {
    "iso:country":"DE",
    "sg:address":"Eicherm\u00fchle 3",
    "sg:city":"Linsengericht",
    "sg:phone":"+49 6051/72311",
    "sg:postcode":"63589",
    "sg:province":"Hessen",
    "wof:name":"Gebr. Hummel",
    "wof:placetype":"venue"
},
  "geometry": {"coordinates":[9.2036657333,50.1743888855],"type":"Point"}
}