{
  "type": "Feature",
  "properties": {
    "iso:country":"DE",
    "sg:address":"Otto-Schmerbach-Str. 19",
    "sg:city":"Chemnitz",
    "sg:phone":"+49 371/8663206",
    "sg:postcode":"09117",
    "sg:province":"Sachsen",
    "wof:name":"Unitech-maschinen Gmbh",
    "wof:placetype":"venue"
},
  "geometry": {"coordinates":[12.8537,50.81041],"type":"Point"}
}