{
  "type": "Feature",
  "properties": {
    "iso:country":"DE",
    "sg:address":"Am Klosterfelde 9",
    "sg:city":"Leipzig",
    "sg:phone":"+49 341/692279",
    "sg:postcode":"04316",
    "sg:province":"Sachsen",
    "wof:name":"H.-j. Weingart Ingenieur",
    "wof:placetype":"venue"
},
  "geometry": {"coordinates":[12.4557199478,51.3222198486],"type":"Point"}
}