{
  "type": "Feature",
  "properties": {
    "iso:country":"DE",
    "sg:address":"Orffstr. 16",
    "sg:city":"Mauer",
    "sg:phone":"+49 6226/3104",
    "sg:postcode":"69256",
    "sg:province":"Baden-W\u00fcrttemberg",
    "wof:name":"Walter Heid",
    "wof:placetype":"venue"
},
  "geometry": {"coordinates":[8.801714,49.344048],"type":"Point"}
}