{
  "type": "Feature",
  "properties": {
    "iso:country":"DE",
    "sg:address":"Weinbergstr. 17",
    "sg:city":"Schwerin",
    "sg:postcode":"19061",
    "sg:province":"Mecklenburg-Vorpommern",
    "wof:name":"Profil Gesellschaft F\u00fcr Struktur- Unternehmens- Und",
    "wof:placetype":"venue"
},
  "geometry": {"coordinates":[11.422929,53.617203],"type":"Point"}
}