{
  "type": "Feature",
  "properties": {
    "iso:country":"DE",
    "sg:address":"Sinaburger Str. 34",
    "sg:city":"Brake",
    "sg:phone":"+49 4401/81774",
    "sg:postcode":"26919",
    "sg:province":"Niedersachsen",
    "wof:name":"Helmuth Zur Horst Postagentur",
    "wof:placetype":"venue"
},
  "geometry": {"coordinates":[8.46653,53.350712],"type":"Point"}
}