{
  "type": "Feature",
  "properties": {
    "iso:country":"DE",
    "sg:address":"Tecklenburger Str. 30",
    "sg:city":"Hasbergen",
    "sg:phone":"+49 5405/69996",
    "sg:postcode":"49205",
    "sg:province":"Niedersachsen",
    "wof:name":"Peters Zweiradshop",
    "wof:placetype":"venue"
},
  "geometry": {"coordinates":[7.960728,52.243252],"type":"Point"}
}