{
  "type": "Feature",
  "properties": {
    "iso:country":"DE",
    "sg:address":"Hauptstr. 63",
    "sg:city":"Hausach",
    "sg:phone":"+49 7831/6262",
    "sg:postcode":"77756",
    "sg:province":"Baden-W\u00fcrttemberg",
    "wof:name":"Burg-sch\u00e4nke",
    "wof:placetype":"venue"
},
  "geometry": {"coordinates":[8.1672153473,48.283870697],"type":"Point"}
}