{
  "type": "Feature",
  "properties": {
    "iso:country":"DE",
    "sg:address":"Zum Gro\u00dfen Stein 28",
    "sg:city":"Burbach",
    "sg:phone":"+49 2736/290000",
    "sg:postcode":"57299",
    "sg:province":"Nordrhein-Westfalen",
    "wof:name":"Ristorante Pizzeria Luisa",
    "wof:placetype":"venue"
},
  "geometry": {"coordinates":[8.1295251846,50.7367744446],"type":"Point"}
}