{
  "type": "Feature",
  "properties": {
    "iso:country":"DE",
    "sg:address":"In der Bredenau 26",
    "sg:city":"Ottersberg",
    "sg:phone":"+49 4293/625",
    "sg:postcode":"28870",
    "sg:province":"Niedersachsen",
    "wof:name":"Hoyer Verwaltungs Gmbh & Co. Kg",
    "wof:placetype":"venue"
},
  "geometry": {"coordinates":[9.068998,53.115128],"type":"Point"}
}