{
  "type": "Feature",
  "properties": {
    "iso:country":"DE",
    "sg:address":"Otto-Wallach-Str. 4",
    "sg:city":"Wiesbaden",
    "sg:phone":"+49 611/24770",
    "sg:postcode":"65203",
    "sg:province":"Hessen",
    "wof:name":"Atm Arbeitsger\u00e4te- Transportmittel Merker Gmbh",
    "wof:placetype":"venue"
},
  "geometry": {"coordinates":[8.2211885452,50.0438613892],"type":"Point"}
}