{
  "type": "Feature",
  "properties": {
    "iso:country":"DE",
    "sg:address":"Hohe Str. 62",
    "sg:city":"Wesel",
    "sg:phone":"+49 281/15942",
    "sg:postcode":"46483",
    "sg:province":"Nordrhein-Westfalen",
    "wof:name":"Parf\u00fcmerie Douglas West Gmbh & Co.",
    "wof:placetype":"venue"
},
  "geometry": {"coordinates":[6.618547,51.657589],"type":"Point"}
}