{
  "type": "Feature",
  "properties": {
    "iso:country":"DE",
    "sg:address":"Friedhofstr. 1",
    "sg:city":"Saarlouis",
    "sg:phone":"+49 6831/82050",
    "sg:postcode":"66740",
    "sg:province":"Saarland",
    "wof:name":"Gebr. Zech Gesch\u00e4fts- F\u00fchrungsgesellschaft Mbh",
    "wof:placetype":"venue"
},
  "geometry": {"coordinates":[6.7673,49.328262],"type":"Point"}
}