{
  "type": "Feature",
  "properties": {
    "iso:country":"DE",
    "sg:address":"Brandst\u00e4tt 16",
    "sg:city":"Grassau",
    "sg:postcode":"83224",
    "sg:province":"Bayern",
    "wof:name":"Gtc Fax Eins Ag",
    "wof:placetype":"venue"
},
  "geometry": {"coordinates":[12.469476,47.786533],"type":"Point"}
}