{
  "type": "Feature",
  "properties": {
    "iso:country":"DE",
    "sg:address":"Relenbergstr. 6",
    "sg:city":"Stuttgart",
    "sg:phone":"+49 711/2245103",
    "sg:postcode":"70174",
    "sg:province":"Baden-W\u00fcrttemberg",
    "wof:name":"L2m3 Kommunikations- Design Gmbh",
    "wof:placetype":"venue"
},
  "geometry": {"coordinates":[9.171905,48.785664],"type":"Point"}
}