{
  "type": "Feature",
  "properties": {
    "iso:country":"DE",
    "sg:address":"Breitenau 8",
    "sg:city":"Kiefersfelden",
    "sg:phone":"+49 8033/609570",
    "sg:postcode":"83088",
    "sg:province":"Bayern",
    "wof:name":"Ledererhof",
    "wof:placetype":"venue"
},
  "geometry": {"coordinates":[12.1464452744,47.6174087524],"type":"Point"}
}