{
  "type": "Feature",
  "properties": {
    "iso:country":"DE",
    "sg:address":"Rubensstr. 2",
    "sg:city":"Augsburg",
    "sg:phone":"+49 821/705604",
    "sg:postcode":"86169",
    "sg:province":"Bayern",
    "wof:name":"Rudolf B. Vlasak",
    "wof:placetype":"venue"
},
  "geometry": {"coordinates":[10.9043521881,48.3899536133],"type":"Point"}
}