{
  "type": "Feature",
  "properties": {
    "iso:country":"DE",
    "sg:address":"M\u00fcnchwiesenstr. 20",
    "sg:city":"Blieskastel",
    "sg:postcode":"66440",
    "sg:province":"Saarland",
    "wof:name":"Comline Sicherheitssysteme",
    "wof:placetype":"venue"
},
  "geometry": {"coordinates":[7.210323,49.223614],"type":"Point"}
}