{
  "type": "Feature",
  "properties": {
    "iso:country":"DE",
    "sg:address":"Alte Landstr. 20",
    "sg:city":"Gro\u00dfhansdorf",
    "sg:phone":"+49 4102/62434",
    "sg:postcode":"22927",
    "sg:province":"Schleswig-Holstein",
    "wof:name":"Ev. Pfarramt Grosshansdorf-schmallenbeck",
    "wof:placetype":"venue"
},
  "geometry": {"coordinates":[10.2673978806,53.6536216736],"type":"Point"}
}