{
  "type": "Feature",
  "properties": {
    "iso:country":"DE",
    "sg:address":"Riedlinger Str. 53",
    "sg:city":"Ehingen",
    "sg:phone":"+49 7391/1483",
    "sg:postcode":"89584",
    "sg:province":"Baden-W\u00fcrttemberg",
    "wof:name":"O Sole Mio",
    "wof:placetype":"venue"
},
  "geometry": {"coordinates":[9.7267847061,48.2823867798],"type":"Point"}
}