{
  "type": "Feature",
  "properties": {
    "iso:country":"DE",
    "sg:address":"R\u00fcdesheimer Platz 3",
    "sg:city":"Berlin",
    "sg:phone":"+49 30/8270070",
    "sg:postcode":"14197",
    "sg:province":"Berlin",
    "wof:name":"Sipar Gmbh",
    "wof:placetype":"venue"
},
  "geometry": {"coordinates":[13.3160667419,52.473449707],"type":"Point"}
}