{
  "type": "Feature",
  "properties": {
    "iso:country":"DE",
    "sg:address":"Rosa-Luxemburg-Str. 30",
    "sg:city":"Oderwitz",
    "sg:phone":"+49 35842/25307",
    "sg:postcode":"02791",
    "sg:province":"Sachsen",
    "wof:name":"Pension Zur Hasenschenke",
    "wof:placetype":"venue"
},
  "geometry": {"coordinates":[14.7367420197,50.9485588074],"type":"Point"}
}