{
  "type": "Feature",
  "properties": {
    "iso:country":"DE",
    "sg:address":"Eupenerstrasse 139",
    "sg:city":"K\u00f6ln",
    "sg:phone":"+49 221/9472460",
    "sg:postcode":"50933",
    "sg:province":"Nordrhein-Westfalen",
    "wof:name":"Cityinfothek",
    "wof:placetype":"venue"
},
  "geometry": {"coordinates":[6.8894729614,50.9447822571],"type":"Point"}
}