{
  "type": "Feature",
  "properties": {
    "iso:country":"DE",
    "sg:address":"An der Schanz 21",
    "sg:city":"Pfedelbach",
    "sg:phone":"+49 7941/959555",
    "sg:postcode":"74629",
    "sg:province":"Baden-W\u00fcrttemberg",
    "wof:name":"Ergotherapiepraxis Staab",
    "wof:placetype":"venue"
},
  "geometry": {"coordinates":[9.498488,49.180344],"type":"Point"}
}