{
  "type": "Feature",
  "properties": {
    "iso:country":"DE",
    "sg:address":"Grimmstr. 9",
    "sg:city":"Lilienthal",
    "sg:phone":"+49 4298/8720",
    "sg:postcode":"28865",
    "sg:province":"Niedersachsen",
    "wof:name":"Paul Uschinski Inh. Wilfried M\u00fcller",
    "wof:placetype":"venue"
},
  "geometry": {"coordinates":[8.9158306122,53.152305603],"type":"Point"}
}