{
  "type": "Feature",
  "properties": {
    "iso:country":"DE",
    "sg:address":"Rathenower Str. 1",
    "sg:city":"Gr\u00e4ningen",
    "sg:postcode":"14715",
    "sg:province":"Brandenburg",
    "wof:name":"Historic-art - Der Museumsshop",
    "wof:placetype":"venue"
},
  "geometry": {"coordinates":[12.474509,52.577633],"type":"Point"}
}