{
  "type": "Feature",
  "properties": {
    "iso:country":"DE",
    "sg:address":"Bostalstr. 17",
    "sg:city":"Duderstadt",
    "sg:postcode":"37115",
    "sg:province":"Niedersachsen",
    "wof:name":"Rybau Gmbh",
    "wof:placetype":"venue"
},
  "geometry": {"coordinates":[10.233817,51.508335],"type":"Point"}
}