{
  "type": "Feature",
  "properties": {
    "iso:country":"DE",
    "sg:address":"Gewerbeparkring 1",
    "sg:city":"F\u00fcrstenwalde",
    "sg:postcode":"15517",
    "sg:province":"Brandenburg",
    "wof:name":"Horti Plast Kunststoffe Gmbh",
    "wof:placetype":"venue"
},
  "geometry": {"coordinates":[14.095054,52.354301],"type":"Point"}
}