{
  "type": "Feature",
  "properties": {
    "iso:country":"DE",
    "sg:address":"Rathausgasse 9",
    "sg:city":"Schwabach",
    "sg:phone":"+49 9122/15020",
    "sg:postcode":"91126",
    "sg:province":"Bayern",
    "wof:name":"Bayerische Vereinsbank Ag",
    "wof:placetype":"venue"
},
  "geometry": {"coordinates":[11.021986,49.327667],"type":"Point"}
}