{
  "type": "Feature",
  "properties": {
    "iso:country":"DE",
    "sg:address":"Bahnhofplatz 8",
    "sg:city":"Starnberg",
    "sg:phone":"+49 8151/360850",
    "sg:postcode":"82319",
    "sg:province":"Bayern",
    "wof:name":"Grundst\u00fccksverwaltungs Gmbh Der Bayla Steuerberatungs Gmbh",
    "wof:placetype":"venue"
},
  "geometry": {"coordinates":[11.3428812027,47.9965057373],"type":"Point"}
}