{
  "type": "Feature",
  "properties": {
    "iso:country":"DE",
    "sg:address":"Mainzer Landstr. 90",
    "sg:city":"Frankfurt",
    "sg:phone":"+49 69/746154",
    "sg:postcode":"60327",
    "sg:province":"Hessen",
    "wof:name":"Europ\u00e4ischer Austauschdienst",
    "wof:placetype":"venue"
},
  "geometry": {"coordinates":[8.658989,50.109005],"type":"Point"}
}