{
  "type": "Feature",
  "properties": {
    "iso:country":"DE",
    "sg:address":"Kamper Weg 317",
    "sg:city":"D\u00fcsseldorf",
    "sg:phone":"+49 211/278884",
    "sg:postcode":"40627",
    "sg:province":"Nordrhein-Westfalen",
    "wof:name":"Helmut Fingerle Architekt",
    "wof:placetype":"venue"
},
  "geometry": {"coordinates":[6.864567,51.215881],"type":"Point"}
}