{
  "type": "Feature",
  "properties": {
    "iso:country":"DE",
    "sg:address":"Eberswalder Str. 84a",
    "sg:city":"M\u00fcncheberg",
    "sg:phone":"+49 33432/89575",
    "sg:postcode":"15374",
    "sg:province":"Brandenburg",
    "wof:name":"Umwelt-ger\u00e4te-technik",
    "wof:placetype":"venue"
},
  "geometry": {"coordinates":[14.114473,52.5149],"type":"Point"}
}