{
  "type": "Feature",
  "properties": {
    "iso:country":"DE",
    "sg:address":"Fronhofstr. 21",
    "sg:city":"Tuttlingen",
    "sg:phone":"+49 7461/74120",
    "sg:postcode":"78532",
    "sg:province":"Baden-W\u00fcrttemberg",
    "wof:name":"H. Geng Chirug. Instrumente",
    "wof:placetype":"venue"
},
  "geometry": {"coordinates":[8.857337,48.003532],"type":"Point"}
}