{
  "type": "Feature",
  "properties": {
    "iso:country":"DE",
    "sg:address":"Am Golfplatz",
    "sg:city":"Bad Nauheim",
    "sg:phone":"+49 6032/33797",
    "sg:postcode":"61231",
    "sg:province":"Hessen",
    "wof:name":"Bernd Raschke",
    "wof:placetype":"venue"
},
  "geometry": {"coordinates":[8.733748,50.374706],"type":"Point"}
}