{
  "type": "Feature",
  "properties": {
    "iso:country":"DE",
    "sg:address":"K\u00f6thenwaldstr 64c",
    "sg:city":"Lehrte",
    "sg:phone":"+49 5132/50930",
    "sg:postcode":"31275",
    "sg:province":"Niedersachsen",
    "wof:name":"Albaum Dental-gipspr\u00e4parate Gmbh & Co Kg",
    "wof:placetype":"venue"
},
  "geometry": {"coordinates":[9.964392,52.374195],"type":"Point"}
}