{
  "type": "Feature",
  "properties": {
    "iso:country":"DE",
    "sg:address":"Kuhnbergstr. 1:: Gewerbepark Voralb",
    "sg:city":"Goeppingen",
    "sg:phone":"+49 4971/6185090",
    "sg:postcode":"73037",
    "sg:province":"Baden-W\u00fcrttemberg",
    "wof:name":"Saxonia-franke Gmbh & Co.",
    "wof:placetype":"venue"
},
  "geometry": {"coordinates":[9.686141,48.687576],"type":"Point"}
}