{
  "type": "Feature",
  "properties": {
    "iso:country":"DE",
    "sg:address":"Koblenzer Str. 73",
    "sg:city":"Limburg",
    "sg:phone":"+49 6431/3774",
    "sg:postcode":"65556",
    "sg:province":"Hessen",
    "wof:name":"Dieter Fischer Antiquit\u00e4ten",
    "wof:placetype":"venue"
},
  "geometry": {"coordinates":[8.06246,50.371651],"type":"Point"}
}