{
  "type": "Feature",
  "properties": {
    "iso:country":"DE",
    "sg:address":"Peterstr. 38",
    "sg:city":"N\u00fcrnberg",
    "sg:phone":"+49 911/498451",
    "sg:postcode":"90478",
    "sg:province":"Bayern",
    "wof:name":"Harrys Zweiradladen",
    "wof:placetype":"venue"
},
  "geometry": {"coordinates":[11.102895,49.44521],"type":"Point"}
}