{
  "type": "Feature",
  "properties": {
    "iso:country":"DE",
    "sg:address":"Bereiteranger 15",
    "sg:city":"M\u00fcnchen",
    "sg:phone":"+49 89/654919",
    "sg:postcode":"81541",
    "sg:province":"Bayern",
    "wof:name":"Raumkontor",
    "wof:placetype":"venue"
},
  "geometry": {"coordinates":[11.580665,48.126026],"type":"Point"}
}