{
  "type": "Feature",
  "properties": {
    "iso:country":"DE",
    "sg:address":"K\u00fcllenhahner Str. 186",
    "sg:city":"Wuppertal",
    "sg:phone":"+49 202/401707",
    "sg:postcode":"42349",
    "sg:province":"Nordrhein-Westfalen",
    "wof:name":"Harald Gerlich Architekt",
    "wof:placetype":"venue"
},
  "geometry": {"coordinates":[7.13881,51.228798],"type":"Point"}
}