{
  "type": "Feature",
  "properties": {
    "iso:country":"DE",
    "sg:address":"M\u00fcnsterknapp 25",
    "sg:city":"Haltern",
    "sg:phone":"+49 2364/4036",
    "sg:postcode":"45721",
    "sg:province":"Nordrhein-Westfalen",
    "wof:name":"Bernhard Mast Gmbh & Co. Kg",
    "wof:placetype":"venue"
},
  "geometry": {"coordinates":[7.197664,51.7533],"type":"Point"}
}