{
  "type": "Feature",
  "properties": {
    "iso:country":"DE",
    "sg:address":"Weststr. 44",
    "sg:city":"Schmallenberg",
    "sg:phone":"+49 2972/47008",
    "sg:postcode":"57392",
    "sg:province":"Nordrhein-Westfalen",
    "wof:name":"Reise-center Dolle",
    "wof:placetype":"venue"
},
  "geometry": {"coordinates":[8.2838144302,51.1486816406],"type":"Point"}
}