{
  "type": "Feature",
  "properties": {
    "iso:country":"DE",
    "sg:address":"Am Adler 24",
    "sg:city":"Hoyerswerda",
    "sg:postcode":"02977",
    "sg:province":"Sachsen",
    "wof:name":"Wohnkonzept Schmidt Schreiber Gmbh",
    "wof:placetype":"venue"
},
  "geometry": {"coordinates":[14.218102,51.420853],"type":"Point"}
}