{
  "type": "Feature",
  "properties": {
    "iso:country":"DE",
    "sg:address":"Strousbergstr. 8",
    "sg:city":"Liebenburg",
    "sg:phone":"+49 5346/4028",
    "sg:postcode":"38704",
    "sg:province":"Niedersachsen",
    "wof:name":"Thomas Guder",
    "wof:placetype":"venue"
},
  "geometry": {"coordinates":[10.379814,52.003597],"type":"Point"}
}