{
  "type": "Feature",
  "properties": {
    "iso:country":"DE",
    "sg:address":"B\u00fchlstr. 15",
    "sg:city":"Korb",
    "sg:phone":"+49 7151/32889",
    "sg:postcode":"71404",
    "sg:province":"Baden-W\u00fcrttemberg",
    "wof:name":"Herbert Haug",
    "wof:placetype":"venue"
},
  "geometry": {"coordinates":[9.368973,48.838924],"type":"Point"}
}