{
  "type": "Feature",
  "properties": {
    "iso:country":"DE",
    "sg:address":"Graf-Recke-Str. 209",
    "sg:city":"D\u00fcsseldorf",
    "sg:postcode":"40237",
    "sg:province":"Nordrhein-Westfalen",
    "wof:name":"Rheinischer Verband F\u00fcr Kindergottesdienst",
    "wof:placetype":"venue"
},
  "geometry": {"coordinates":[6.8188557625,51.2444572449],"type":"Point"}
}