{
  "type": "Feature",
  "properties": {
    "iso:country":"DE",
    "sg:address":"Lange Str. 1",
    "sg:city":"Adorf",
    "sg:phone":"+49 37423/2355",
    "sg:postcode":"08626",
    "sg:province":"Sachsen",
    "wof:name":"V. Braun & Partner",
    "wof:placetype":"venue"
},
  "geometry": {"coordinates":[12.219499588,50.3222084045],"type":"Point"}
}