{
  "type": "Feature",
  "properties": {
    "iso:country":"DE",
    "sg:address":"Paul-Gerhardt-Str. 6",
    "sg:city":"Merseburg",
    "sg:phone":"+49 3461/210372",
    "sg:postcode":"06217",
    "sg:province":"Sachsen-Anhalt",
    "wof:name":"Klaus-joachim Bock",
    "wof:placetype":"venue"
},
  "geometry": {"coordinates":[11.987505,51.363239],"type":"Point"}
}