{
  "type": "Feature",
  "properties": {
    "iso:country":"DE",
    "sg:address":"Bahnhofstr. 17",
    "sg:city":"Nemsdorf-G\u00f6hrendorf",
    "sg:phone":"+49 34771/23139",
    "sg:postcode":"06268",
    "sg:province":"Sachsen-Anhalt",
    "wof:name":"Metallbau Kramer Gmbh",
    "wof:placetype":"venue"
},
  "geometry": {"coordinates":[11.6602840424,51.3572540283],"type":"Point"}
}