{
  "type": "Feature",
  "properties": {
    "iso:country":"DE",
    "sg:address":"Planstr. 6",
    "sg:city":"Gittelde",
    "sg:phone":"+49 5327/5298",
    "sg:postcode":"37534",
    "sg:province":"Niedersachsen",
    "wof:name":"Wilhelm Dr\u00fccker",
    "wof:placetype":"venue"
},
  "geometry": {"coordinates":[10.186913,51.798538],"type":"Point"}
}