{
  "type": "Feature",
  "properties": {
    "iso:country":"DE",
    "sg:address":"Sebastistr. 12",
    "sg:city":"Kipfenberg",
    "sg:phone":"+49 8465/446",
    "sg:postcode":"85110",
    "sg:province":"Bayern",
    "wof:name":"J. Bemsel",
    "wof:placetype":"venue"
},
  "geometry": {"coordinates":[11.432354,48.964855],"type":"Point"}
}