{
  "type": "Feature",
  "properties": {
    "iso:country":"DE",
    "sg:address":"Senkingstr. 25",
    "sg:city":"Hildesheim",
    "sg:phone":"+49 5121/52014",
    "sg:postcode":"31137",
    "sg:province":"Niedersachsen",
    "wof:name":"W. Dr\u00e4ger",
    "wof:placetype":"venue"
},
  "geometry": {"coordinates":[9.9431400299,52.1584587097],"type":"Point"}
}