{
  "type": "Feature",
  "properties": {
    "iso:country":"DE",
    "sg:address":"Bahnhofstr. 32-33",
    "sg:city":"Kirchentellinsfurt",
    "sg:phone":"+49 7121/9080",
    "sg:postcode":"72138",
    "sg:province":"Baden-W\u00fcrttemberg",
    "wof:name":"Leitenberger Mess- Und Regeltechnik Gmbh",
    "wof:placetype":"venue"
},
  "geometry": {"coordinates":[9.1383142471,48.5304832458],"type":"Point"}
}