{
  "type": "Feature",
  "properties": {
    "iso:country":"DE",
    "sg:address":"Grabenstr. 4",
    "sg:city":"Bielefeld",
    "sg:phone":"+49 4952/1417250",
    "sg:postcode":"33647",
    "sg:province":"Nordrhein-Westfalen",
    "wof:name":"Gustav Brinkjost Kg",
    "wof:placetype":"venue"
},
  "geometry": {"coordinates":[8.5143470764,51.9796142578],"type":"Point"}
}