{
  "type": "Feature",
  "properties": {
    "iso:country":"DE",
    "sg:address":"Hans-Mielich-Str. 14",
    "sg:city":"M\u00fcnchen",
    "sg:phone":"+49 89/650897",
    "sg:postcode":"81543",
    "sg:province":"Bayern",
    "wof:name":"Katholisches Pfarramt St. Franziskus",
    "wof:placetype":"venue"
},
  "geometry": {"coordinates":[11.5699520111,48.1146430969],"type":"Point"}
}