{
  "type": "Feature",
  "properties": {
    "iso:country":"DE",
    "sg:address":"Vogelsbergstr. 54",
    "sg:city":"Darmstadt",
    "sg:phone":"+49 6151/718169",
    "sg:postcode":"64289",
    "sg:province":"Hessen",
    "wof:name":"Heinz Oehme",
    "wof:placetype":"venue"
},
  "geometry": {"coordinates":[8.665219,49.882397],"type":"Point"}
}