{
  "type": "Feature",
  "properties": {
    "iso:country":"DE",
    "sg:address":"Finkenweg 18",
    "sg:city":"Moormerland",
    "sg:phone":"+49 4954/942944",
    "sg:postcode":"26802",
    "sg:province":"Niedersachsen",
    "wof:name":"Wulf",
    "wof:placetype":"venue"
},
  "geometry": {"coordinates":[7.4823122025,53.3154067993],"type":"Point"}
}