{
  "type": "Feature",
  "properties": {
    "iso:country":"DE",
    "sg:address":"Schorba 6",
    "sg:city":"Bucha",
    "sg:phone":"+49 3641/606383",
    "sg:postcode":"07751",
    "sg:province":"Th\u00fcringen",
    "wof:name":"Hepolan Heeren Gmbh",
    "wof:placetype":"venue"
},
  "geometry": {"coordinates":[11.477421,50.875477],"type":"Point"}
}