{
  "type": "Feature",
  "properties": {
    "iso:country":"DE",
    "sg:address":"Industriestr. 2b",
    "sg:city":"Luckenwalde",
    "sg:phone":"+49 3371/632548",
    "sg:postcode":"14943",
    "sg:province":"Brandenburg",
    "wof:name":"Dr. Schiller Walz-u. Werkzeugtechnik Gmbh",
    "wof:placetype":"venue"
},
  "geometry": {"coordinates":[13.156206,52.079857],"type":"Point"}
}