{
  "type": "Feature",
  "properties": {
    "iso:country":"DE",
    "sg:address":"Draiser Str. 85",
    "sg:city":"Mainz",
    "sg:phone":"+49 6131/364401",
    "sg:postcode":"55128",
    "sg:province":"Rheinland-Pfalz",
    "wof:name":"Manfred Schneider",
    "wof:placetype":"venue"
},
  "geometry": {"coordinates":[8.242459,49.985847],"type":"Point"}
}