{
  "type": "Feature",
  "properties": {
    "iso:country":"DE",
    "sg:address":"Kurf\u00fcrstenstr. 28",
    "sg:city":"K\u00f6nigswinter",
    "sg:phone":"+49 2223/22423",
    "sg:postcode":"53639",
    "sg:province":"Nordrhein-Westfalen",
    "wof:name":"Restaurant Felgenklause",
    "wof:placetype":"venue"
},
  "geometry": {"coordinates":[7.1894731522,50.6812820435],"type":"Point"}
}