{
  "type": "Feature",
  "properties": {
    "iso:country":"DE",
    "sg:address":"Gr\u00fcnberger Str. 49-53",
    "sg:city":"Gie\u00dfen",
    "sg:postcode":"35394",
    "sg:province":"Hessen",
    "wof:name":"Michel Gmbh",
    "wof:placetype":"venue"
},
  "geometry": {"coordinates":[8.688375,50.58456],"type":"Point"}
}