{
  "type": "Feature",
  "properties": {
    "iso:country":"DE",
    "sg:address":"Krampnitzer Weg 38",
    "sg:city":"Berlin",
    "sg:phone":"+49 30/3654343",
    "sg:postcode":"14089",
    "sg:province":"Berlin",
    "wof:name":"Lothar Lambeck",
    "wof:placetype":"venue"
},
  "geometry": {"coordinates":[13.129279,52.453033],"type":"Point"}
}