{
  "type": "Feature",
  "properties": {
    "iso:country":"DE",
    "sg:address":"Steinstr. 21",
    "sg:city":"Sch\u00fcttorf",
    "sg:phone":"+49 5923/7765",
    "sg:postcode":"48465",
    "sg:province":"Niedersachsen",
    "wof:name":"Steinstra\u00dfengrill",
    "wof:placetype":"venue"
},
  "geometry": {"coordinates":[7.2243690491,52.3202972412],"type":"Point"}
}