{
  "type": "Feature",
  "properties": {
    "iso:country":"DE",
    "sg:address":"Waldemar-Bonsels-Weg 151",
    "sg:city":"Ahrensburg",
    "sg:phone":"+49 4102/53814",
    "sg:postcode":"22926",
    "sg:province":"Schleswig-Holstein",
    "wof:name":"H. Willemeit",
    "wof:placetype":"venue"
},
  "geometry": {"coordinates":[10.2230072021,53.6661949158],"type":"Point"}
}