{
  "type": "Feature",
  "properties": {
    "iso:country":"DE",
    "sg:address":"Steigerstr. 5 d",
    "sg:city":"Papenburg",
    "sg:phone":"+49 4961/75442",
    "sg:postcode":"26871",
    "sg:province":"Niedersachsen",
    "wof:name":"J. Bruns",
    "wof:placetype":"venue"
},
  "geometry": {"coordinates":[7.4310288429,53.0792427063],"type":"Point"}
}