{
  "type": "Feature",
  "properties": {
    "iso:country":"DE",
    "sg:address":"Graf-Moltke-Str. 60",
    "sg:city":"Bremen",
    "sg:phone":"+49 4942/1340610",
    "sg:postcode":"28211",
    "sg:province":"Bremen",
    "wof:name":"Papp Werbeagentur Gmbh",
    "wof:placetype":"venue"
},
  "geometry": {"coordinates":[8.833029,53.080647],"type":"Point"}
}