{
  "type": "Feature",
  "properties": {
    "iso:country":"DE",
    "sg:address":"Leibstr. 29",
    "sg:city":"Haar",
    "sg:phone":"+49 89/466950",
    "sg:postcode":"85540",
    "sg:province":"Bayern",
    "wof:name":"R. Und C. Von Rettberg",
    "wof:placetype":"venue"
},
  "geometry": {"coordinates":[11.7327442169,48.1101493835],"type":"Point"}
}