{
  "type": "Feature",
  "properties": {
    "iso:country":"DE",
    "sg:address":"Sindelfinger Str. 4",
    "sg:city":"B\u00f6blingen",
    "sg:phone":"+49 7031/20070",
    "sg:postcode":"71032",
    "sg:province":"Baden-W\u00fcrttemberg",
    "wof:name":"K. Schmid",
    "wof:placetype":"venue"
},
  "geometry": {"coordinates":[9.0147771835,48.6859741211],"type":"Point"}
}