{
  "type": "Feature",
  "properties": {
    "iso:country":"DE",
    "sg:address":"Dietrich-Bonhoeffer-Str. 6",
    "sg:city":"Neuss",
    "sg:phone":"+49 2131/476131",
    "sg:postcode":"41466",
    "sg:province":"Nordrhein-Westfalen",
    "wof:name":"Holger Schellhas Masseur",
    "wof:placetype":"venue"
},
  "geometry": {"coordinates":[6.704641,51.159683],"type":"Point"}
}