{
  "type": "Feature",
  "properties": {
    "iso:country":"DE",
    "sg:address":"Osterstr. 136",
    "sg:city":"Norden",
    "sg:phone":"+49 4931/3455",
    "sg:postcode":"26506",
    "sg:province":"Niedersachsen",
    "wof:name":"Remmer",
    "wof:placetype":"venue"
},
  "geometry": {"coordinates":[7.2105050087,53.597076416],"type":"Point"}
}