{
  "type": "Feature",
  "properties": {
    "iso:country":"DE",
    "sg:address":"Peter-Auzinger-Str. 7",
    "sg:city":"M\u00fcnchen",
    "sg:phone":"+49 89/6903953",
    "sg:postcode":"81547",
    "sg:province":"Bayern",
    "wof:name":"Mangfallst\u00fcberl",
    "wof:placetype":"venue"
},
  "geometry": {"coordinates":[11.5835447311,48.0987968445],"type":"Point"}
}