{
  "type": "Feature",
  "properties": {
    "iso:country":"DE",
    "sg:address":"Bergstr. 23",
    "sg:city":"Rosenthal-Bielatal",
    "sg:phone":"+49 35033/71246",
    "sg:postcode":"01824",
    "sg:province":"Sachsen",
    "wof:name":"Guenter Wylegalla",
    "wof:placetype":"venue"
},
  "geometry": {"coordinates":[14.036731,50.872784],"type":"Point"}
}