{
  "type": "Feature",
  "properties": {
    "iso:country":"DE",
    "sg:address":"Spenglerallee 23",
    "sg:city":"Zwenkau",
    "sg:phone":"+49 34203/53637",
    "sg:postcode":"04442",
    "sg:province":"Sachsen",
    "wof:name":"Hip Isoliertechnik Gmbh",
    "wof:placetype":"venue"
},
  "geometry": {"coordinates":[12.337932,51.210274],"type":"Point"}
}