{
  "type": "Feature",
  "properties": {
    "iso:country":"DE",
    "sg:address":"Neudorf 44",
    "sg:city":"Amorbach",
    "sg:phone":"+49 9373/630",
    "sg:postcode":"63916",
    "sg:province":"Bayern",
    "wof:name":"Odenwaldblick",
    "wof:placetype":"venue"
},
  "geometry": {"coordinates":[9.2641496658,49.6561508179],"type":"Point"}
}