{
  "type": "Feature",
  "properties": {
    "iso:country":"DE",
    "sg:address":"Wittenkamp 1",
    "sg:city":"Hamburg",
    "sg:phone":"+49 40/6929844",
    "sg:postcode":"22307",
    "sg:province":"Hamburg",
    "wof:name":"Wittmann Service Gesellschaft Mbh",
    "wof:placetype":"venue"
},
  "geometry": {"coordinates":[10.0470809937,53.5968933105],"type":"Point"}
}