{
  "type": "Feature",
  "properties": {
    "iso:country":"DE",
    "sg:address":"Zu den Deichen 10",
    "sg:city":"Stadland",
    "sg:phone":"+49 4732/1696",
    "sg:postcode":"26935",
    "sg:province":"Niedersachsen",
    "wof:name":"Erwin Reinen",
    "wof:placetype":"venue"
},
  "geometry": {"coordinates":[8.4628705978,53.4069862366],"type":"Point"}
}