{
  "type": "Feature",
  "properties": {
    "iso:country":"DE",
    "sg:address":"Herschelstr. 10",
    "sg:city":"Zwickau",
    "sg:phone":"+49 375/390050",
    "sg:postcode":"08060",
    "sg:province":"Sachsen",
    "wof:name":"Kr\u00e4mer & Partner Planungs Gmbh",
    "wof:placetype":"venue"
},
  "geometry": {"coordinates":[12.4708299637,50.7244186401],"type":"Point"}
}