{
  "type": "Feature",
  "properties": {
    "iso:country":"DE",
    "sg:address":"Siemensring 98",
    "sg:city":"Willich",
    "sg:phone":"+49 2154/60540",
    "sg:postcode":"47877",
    "sg:province":"Nordrhein-Westfalen",
    "wof:name":"K-h-t Professional Label Solutions",
    "wof:placetype":"venue"
},
  "geometry": {"coordinates":[6.512345,51.265621],"type":"Point"}
}