{
  "type": "Feature",
  "properties": {
    "iso:country":"DE",
    "sg:address":"Hauptstr. 61Am Hasentobel 12",
    "sg:city":"Lindenberg",
    "sg:phone":"+49 8381/1452",
    "sg:postcode":"88161",
    "sg:province":"Bayern",
    "wof:name":"St. Ulrich-apotheke E. K.",
    "wof:placetype":"venue"
},
  "geometry": {"coordinates":[9.8872699738,47.6016235352],"type":"Point"}
}