{
  "type": "Feature",
  "properties": {
    "iso:country":"DE",
    "sg:address":"Wilhelmsh\u00f6her Weg 106",
    "sg:city":"Kassel",
    "sg:phone":"+49 561/62143",
    "sg:postcode":"34130",
    "sg:province":"Hessen",
    "wof:name":"Hessenschanze",
    "wof:placetype":"venue"
},
  "geometry": {"coordinates":[9.4299535751,51.3254203796],"type":"Point"}
}