{
  "type": "Feature",
  "properties": {
    "iso:country":"DE",
    "sg:address":"Am Kietz 14",
    "sg:city":"Liebenwalde",
    "sg:phone":"+49 33054/61660",
    "sg:postcode":"16559",
    "sg:province":"Brandenburg",
    "wof:name":"Detec Oberfl\u00e4chen Liebenwalde Gmbh",
    "wof:placetype":"venue"
},
  "geometry": {"coordinates":[13.404287,52.864784],"type":"Point"}
}