{
  "type": "Feature",
  "properties": {
    "iso:country":"DE",
    "sg:address":"Roonstr. 24",
    "sg:city":"Karlsruhe",
    "sg:phone":"+49 721/816996",
    "sg:postcode":"76137",
    "sg:province":"Baden-W\u00fcrttemberg",
    "wof:name":"Peter Wolf",
    "wof:placetype":"venue"
},
  "geometry": {"coordinates":[8.388048172,49.0022468567],"type":"Point"}
}