{
  "type": "Feature",
  "properties": {
    "iso:country":"DE",
    "sg:address":"Bendenweg 18",
    "sg:city":"Linnich",
    "sg:phone":"+49 2462/8598",
    "sg:postcode":"52441",
    "sg:province":"Nordrhein-Westfalen",
    "wof:name":"Hallen- Und Freibad",
    "wof:placetype":"venue"
},
  "geometry": {"coordinates":[6.2707858086,50.9832611084],"type":"Point"}
}