{
  "type": "Feature",
  "properties": {
    "iso:country":"DE",
    "sg:address":"Winterleite 10",
    "sg:city":"Steinbach",
    "sg:phone":"+49 9268/7583",
    "sg:postcode":"96361",
    "sg:province":"Bayern",
    "wof:name":"Aha Werbemittelproduktion Und Vertrieb",
    "wof:placetype":"venue"
},
  "geometry": {"coordinates":[11.3395032883,50.4251785278],"type":"Point"}
}