{
  "type": "Feature",
  "properties": {
    "iso:country":"DE",
    "sg:address":"Karlsbader Str. 2",
    "sg:city":"Schwarzenberg",
    "sg:phone":"+49 3774/178860",
    "sg:postcode":"08340",
    "sg:province":"Sachsen",
    "wof:name":"Richartz Und B\u00f6hme Ergotherapeutische Praxis",
    "wof:placetype":"venue"
},
  "geometry": {"coordinates":[12.786017,50.539925],"type":"Point"}
}