{
  "type": "Feature",
  "properties": {
    "iso:country":"DE",
    "sg:address":"Hochallee 126",
    "sg:city":"Hamburg",
    "sg:phone":"+49 40/464046",
    "sg:postcode":"20149",
    "sg:province":"Hamburg",
    "wof:name":"Planquadrat Reise- Beratung Gmbh",
    "wof:placetype":"venue"
},
  "geometry": {"coordinates":[9.9854784012,53.5826683044],"type":"Point"}
}