{
  "type": "Feature",
  "properties": {
    "iso:country":"DE",
    "sg:address":"Herforder Str. 163",
    "sg:city":"Lemgo",
    "sg:phone":"+49 5261/68193",
    "sg:postcode":"32657",
    "sg:province":"Nordrhein-Westfalen",
    "wof:name":"Walter Kluckhuhn",
    "wof:placetype":"venue"
},
  "geometry": {"coordinates":[8.860595,52.028633],"type":"Point"}
}