{
  "type": "Feature",
  "properties": {
    "iso:country":"DE",
    "sg:address":"Kirchstr. 17",
    "sg:city":"Uhingen",
    "sg:phone":"+49 7161/37373",
    "sg:postcode":"73066",
    "sg:province":"Baden-W\u00fcrttemberg",
    "wof:name":"Eugen Blessing Eisenwaren",
    "wof:placetype":"venue"
},
  "geometry": {"coordinates":[9.587238,48.704704],"type":"Point"}
}