{
  "type": "Feature",
  "properties": {
    "iso:country":"DE",
    "sg:address":"G\u00fctzkower Landstr.",
    "sg:city":"Greifswald",
    "sg:phone":"+49 3834/502356",
    "sg:postcode":"17489",
    "sg:province":"Mecklenburg-Vorpommern",
    "wof:name":"China-haus",
    "wof:placetype":"venue"
},
  "geometry": {"coordinates":[13.3810853958,54.0745544434],"type":"Point"}
}