{
  "type": "Feature",
  "properties": {
    "iso:country":"DE",
    "sg:address":"Bahnhofstr. 3",
    "sg:city":"Gol\u00dfen",
    "sg:postcode":"15938",
    "sg:province":"Brandenburg",
    "wof:name":"Katholisches Pfarramt",
    "wof:placetype":"venue"
},
  "geometry": {"coordinates":[13.5932531357,51.9731826782],"type":"Point"}
}