{
  "type": "Feature",
  "properties": {
    "iso:country":"DE",
    "sg:address":"Theodor-Storm-Str. 19",
    "sg:city":"Westerland",
    "sg:phone":"+49 4651/22334",
    "sg:postcode":"25980",
    "sg:province":"Schleswig-Holstein",
    "wof:name":"Christel Jensen",
    "wof:placetype":"venue"
},
  "geometry": {"coordinates":[8.3135499954,54.9160118103],"type":"Point"}
}