{
  "type": "Feature",
  "properties": {
    "iso:country":"DE",
    "sg:address":"Postfach 1580",
    "sg:city":"Selb",
    "sg:postcode":"95089",
    "sg:province":"Bayern",
    "wof:name":"Stadtverwaltung",
    "wof:placetype":"venue"
},
  "geometry": {"coordinates":[12.1307601929,50.169708252],"type":"Point"}
}