{
  "type": "Feature",
  "properties": {
    "iso:country":"DE",
    "sg:address":"Vorsumer Weg 3a",
    "sg:city":"Geldern",
    "sg:phone":"+49 4928/382324",
    "sg:postcode":"47608",
    "sg:province":"Nordrhein-Westfalen",
    "wof:name":"Aengenheyster H\u00c4utegrosshandlung E.k.",
    "wof:placetype":"venue"
},
  "geometry": {"coordinates":[6.361813,51.566067],"type":"Point"}
}