{
  "type": "Feature",
  "properties": {
    "iso:country":"DE",
    "sg:address":"Florastr. 10",
    "sg:city":"Bielefeld",
    "sg:phone":"+49 521/3930039",
    "sg:postcode":"33729",
    "sg:province":"Nordrhein-Westfalen",
    "wof:name":"U. Kaiser",
    "wof:placetype":"venue"
},
  "geometry": {"coordinates":[8.646933,52.044979],"type":"Point"}
}