{
  "type": "Feature",
  "properties": {
    "iso:country":"DE",
    "sg:address":"Maria-G\u00f6ppert-Weg 9",
    "sg:city":"G\u00f6ttingen",
    "sg:phone":"+49 551/83383",
    "sg:postcode":"37077",
    "sg:province":"Niedersachsen",
    "wof:name":"Andreas H\u00f6fert",
    "wof:placetype":"venue"
},
  "geometry": {"coordinates":[9.9320745468,51.572052002],"type":"Point"}
}