{
  "type": "Feature",
  "properties": {
    "iso:country":"DE",
    "sg:address":"Herforder Str. 10",
    "sg:city":"Melle",
    "sg:phone":"+49 5226/5135",
    "sg:postcode":"49328",
    "sg:province":"Niedersachsen",
    "wof:name":"Ev. Pfarramt Ev. Luth. Kirchengemeinde",
    "wof:placetype":"venue"
},
  "geometry": {"coordinates":[8.4347000122,52.1810035706],"type":"Point"}
}