{
  "type": "Feature",
  "properties": {
    "iso:country":"DE",
    "sg:address":"Baumschulenstr. 67",
    "sg:city":"Berlin",
    "sg:phone":"+49 30/5253123",
    "sg:postcode":"12437",
    "sg:province":"Berlin",
    "wof:name":"Euen Bestattungen",
    "wof:placetype":"venue"
},
  "geometry": {"coordinates":[13.482623,52.462147],"type":"Point"}
}