{
  "type": "Feature",
  "properties": {
    "iso:country":"DE",
    "sg:address":"Hauptstr. 43",
    "sg:city":"Offenburg",
    "sg:phone":"+49 781/9266309",
    "sg:postcode":"77652",
    "sg:province":"Baden-W\u00fcrttemberg",
    "wof:name":"Andreas Hund",
    "wof:placetype":"venue"
},
  "geometry": {"coordinates":[7.9430499077,48.4712944031],"type":"Point"}
}