{
  "type": "Feature",
  "properties": {
    "iso:country":"DE",
    "sg:address":"Wandsbeker Stieg 13",
    "sg:city":"Hamburg",
    "sg:phone":"+49 40/2513682",
    "sg:postcode":"22087",
    "sg:province":"Hamburg",
    "wof:name":"Henrichs & Federwitz Gascontrol Gbr",
    "wof:placetype":"venue"
},
  "geometry": {"coordinates":[10.0258998871,53.5602378845],"type":"Point"}
}