{
  "type": "Feature",
  "properties": {
    "iso:country":"DE",
    "sg:address":"Nauklerstr. 58",
    "sg:city":"T\u00fcbingen",
    "sg:postcode":"72074",
    "sg:province":"Baden-W\u00fcrttemberg",
    "wof:name":"Dr. S\u00fcleymann B\u00f6hringer Heilpraktiker",
    "wof:placetype":"venue"
},
  "geometry": {"coordinates":[9.0641431808,48.5299606323],"type":"Point"}
}