{
  "type": "Feature",
  "properties": {
    "iso:country":"DE",
    "sg:address":"Heddorf 21",
    "sg:city":"D\u00f6rverden",
    "sg:phone":"+49 4234/2976",
    "sg:postcode":"27313",
    "sg:province":"Niedersachsen",
    "wof:name":"Detlef Kurz Elektro- Und Haustechnik Gmbh",
    "wof:placetype":"venue"
},
  "geometry": {"coordinates":[9.235748,52.849995],"type":"Point"}
}