{
  "type": "Feature",
  "properties": {
    "iso:country":"DE",
    "sg:address":"Neuengammer Hausdeich 88",
    "sg:city":"Hamburg",
    "sg:phone":"+49 40/7231955",
    "sg:postcode":"21039",
    "sg:province":"Hamburg",
    "wof:name":"Ewald Wulff",
    "wof:placetype":"venue"
},
  "geometry": {"coordinates":[10.241428,53.432175],"type":"Point"}
}