{
  "type": "Feature",
  "properties": {
    "iso:country":"DE",
    "sg:address":"Kap-herr-Weg 4",
    "sg:city":"Dresden",
    "sg:phone":"+49 351/2846097",
    "sg:postcode":"01257",
    "sg:province":"Sachsen",
    "wof:name":"Olaf Zebisch Transport",
    "wof:placetype":"venue"
},
  "geometry": {"coordinates":[13.8100099564,50.9862098694],"type":"Point"}
}