{
  "type": "Feature",
  "properties": {
    "iso:country":"DE",
    "sg:address":"Am Hirtenschild 18",
    "sg:city":"Offenbach - Bieber",
    "sg:phone":"+49 69",
    "sg:postcode":"63073",
    "sg:province":"Hessen",
    "wof:name":"Schlander Versicherungen",
    "wof:placetype":"venue"
},
  "geometry": {"coordinates":[8.7985200882,50.0838851929],"type":"Point"}
}