{
  "type": "Feature",
  "properties": {
    "iso:country":"DE",
    "sg:address":"Ottweilerstr. 16",
    "sg:city":"Duisburg",
    "sg:phone":"+49 203/472386",
    "sg:postcode":"47178",
    "sg:province":"Nordrhein-Westfalen",
    "wof:name":"Lions-hilfswerk Dinslaken E. V.",
    "wof:placetype":"venue"
},
  "geometry": {"coordinates":[6.728621006,51.5449485779],"type":"Point"}
}