{
  "type": "Feature",
  "properties": {
    "iso:country":"DE",
    "sg:address":"Erdorfer Str. 1",
    "sg:city":"Bitburg",
    "sg:phone":"+49 6561/7311",
    "sg:postcode":"54634",
    "sg:province":"Rheinland-Pfalz",
    "wof:name":"Alt Bitburg",
    "wof:placetype":"venue"
},
  "geometry": {"coordinates":[6.5266470909,49.9743804932],"type":"Point"}
}