{
  "type": "Feature",
  "properties": {
    "iso:country":"DE",
    "sg:address":"Didierstr.",
    "sg:city":"K\u00f6nigswinter",
    "sg:postcode":"53639",
    "sg:province":"Nordrhein-Westfalen",
    "wof:name":"Rheinischer Vulkan Chamotte- Und Dinaswerke Gmbh",
    "wof:placetype":"venue"
},
  "geometry": {"coordinates":[7.1827001572,50.6979942322],"type":"Point"}
}