{
  "type": "Feature",
  "properties": {
    "iso:country":"DE",
    "sg:address":"Alte Bonnstr. 56",
    "sg:city":"Br\u00fchl",
    "sg:phone":"+49 2232/32529",
    "sg:postcode":"50321",
    "sg:province":"Nordrhein-Westfalen",
    "wof:name":"Ulrich Teraske Fliesen Gmbh",
    "wof:placetype":"venue"
},
  "geometry": {"coordinates":[6.895113945,50.8138923645],"type":"Point"}
}