{
  "type": "Feature",
  "properties": {
    "iso:country":"DE",
    "sg:address":"Kegelbahnstr. 10",
    "sg:city":"Freigericht",
    "sg:phone":"+49 6055/7189",
    "sg:postcode":"63579",
    "sg:province":"Hessen",
    "wof:name":"K. Und G. Reus",
    "wof:placetype":"venue"
},
  "geometry": {"coordinates":[9.140335,50.146572],"type":"Point"}
}