{
  "type": "Feature",
  "properties": {
    "iso:country":"DE",
    "sg:address":"Ernststr. 26",
    "sg:city":"Berlin",
    "sg:phone":"+49 30/4324151",
    "sg:postcode":"13509",
    "sg:province":"Berlin",
    "wof:name":"Thomas Nerlich",
    "wof:placetype":"venue"
},
  "geometry": {"coordinates":[13.2965860367,52.5828170776],"type":"Point"}
}