{
  "type": "Feature",
  "properties": {
    "iso:country":"DE",
    "sg:address":"Karlsbader Str. 41",
    "sg:city":"Rittersgr\u00fcn",
    "sg:phone":"+49 4937/7577000",
    "sg:postcode":"08355",
    "wof:name":"Ps Elektro-telekommunikations-anlagen Gmbh",
    "wof:placetype":"venue"
},
  "geometry": {"coordinates":[12.7986326218,50.4746322632],"type":"Point"}
}