{
  "type": "Feature",
  "properties": {
    "iso:country":"DE",
    "sg:address":"Haydnstr. 45",
    "sg:city":"Dortmund",
    "sg:postcode":"44145",
    "sg:province":"Nordrhein-Westfalen",
    "wof:name":"Becker + Lange Gmbh",
    "wof:placetype":"venue"
},
  "geometry": {"coordinates":[7.461443,51.526157],"type":"Point"}
}