{
  "type": "Feature",
  "properties": {
    "iso:country":"DE",
    "sg:address":"Lindenallee 15",
    "sg:city":"Bonn",
    "sg:phone":"+49 228/364658",
    "sg:postcode":"53173",
    "sg:province":"Nordrhein-Westfalen",
    "wof:name":"Flm Gesellschaft F\u00fcr Kommunikationsberatung Mbh",
    "wof:placetype":"venue"
},
  "geometry": {"coordinates":[7.16363,50.683853],"type":"Point"}
}