{
  "type": "Feature",
  "properties": {
    "iso:country":"DE",
    "sg:address":"Rossertweg 30",
    "sg:city":"Besigheim",
    "sg:phone":"+49 7143/60856",
    "sg:postcode":"74354",
    "sg:province":"Baden-W\u00fcrttemberg",
    "wof:name":"Hans Berndl",
    "wof:placetype":"venue"
},
  "geometry": {"coordinates":[9.133469,48.99192],"type":"Point"}
}