{
  "type": "Feature",
  "properties": {
    "iso:country":"DE",
    "sg:address":"Schuhstr. 16",
    "sg:city":"Celle",
    "sg:phone":"+49 5141/23544",
    "sg:postcode":"29221",
    "sg:province":"Niedersachsen",
    "wof:name":"Junior Chic",
    "wof:placetype":"venue"
},
  "geometry": {"coordinates":[10.083521843,52.625629425],"type":"Point"}
}