{
  "type": "Feature",
  "properties": {
    "iso:country":"DE",
    "sg:address":"Otto-Brenner-Str. 7",
    "sg:city":"Trier",
    "sg:phone":"+49 651/33033",
    "sg:postcode":"54294",
    "sg:province":"Rheinland-Pfalz",
    "wof:name":"Neu & Co.",
    "wof:placetype":"venue"
},
  "geometry": {"coordinates":[6.613671,49.728382],"type":"Point"}
}