{
  "type": "Feature",
  "properties": {
    "iso:country":"DE",
    "sg:address":"M\u00fchlenstr. 1",
    "sg:city":"Ganderkesee",
    "sg:phone":"+49 4222/70289",
    "sg:postcode":"27777",
    "sg:province":"Niedersachsen",
    "wof:name":"China-restaurant Tschung-lin",
    "wof:placetype":"venue"
},
  "geometry": {"coordinates":[8.5458192825,53.0319099426],"type":"Point"}
}