{
  "type": "Feature",
  "properties": {
    "iso:country":"DE",
    "sg:address":"Zum Walkm\u00fcller 39",
    "sg:city":"Duisburg",
    "sg:phone":"+49 203/760567",
    "sg:postcode":"47269",
    "sg:province":"Nordrhein-Westfalen",
    "wof:name":"Willibald R\u00f6sch",
    "wof:placetype":"venue"
},
  "geometry": {"coordinates":[6.773027,51.366688],"type":"Point"}
}