{
  "type": "Feature",
  "properties": {
    "iso:country":"DE",
    "sg:address":"Alois-T\u00fcrk-Str. 14",
    "sg:city":"Schweinfurt",
    "sg:phone":"+49 9721/78900",
    "sg:postcode":"97424",
    "sg:province":"Bayern",
    "wof:name":"Ing.-b\u00fcro Bopp Gmbh",
    "wof:placetype":"venue"
},
  "geometry": {"coordinates":[10.1944971085,50.0570869446],"type":"Point"}
}