{
  "type": "Feature",
  "properties": {
    "iso:country":"DE",
    "sg:address":"Am Buschfeld 18",
    "sg:city":"Bergheim",
    "sg:phone":"+49 2238/450077",
    "sg:postcode":"50129",
    "sg:province":"Nordrhein-Westfalen",
    "wof:name":"Prof. Blendl Me\u00dflabor Gmbh",
    "wof:placetype":"venue"
},
  "geometry": {"coordinates":[6.742634,50.994411],"type":"Point"}
}