{
  "type": "Feature",
  "properties": {
    "iso:country":"DE",
    "sg:address":"Sasbacher Str. 8a",
    "sg:city":"Achern",
    "sg:phone":"+49 7841/26233",
    "sg:postcode":"77855",
    "sg:province":"Baden-W\u00fcrttemberg",
    "wof:name":"Walter Lorenz",
    "wof:placetype":"venue"
},
  "geometry": {"coordinates":[8.080667,48.630741],"type":"Point"}
}