{
  "type": "Feature",
  "properties": {
    "iso:country":"DE",
    "sg:address":"Mittelstr. 15",
    "sg:city":"G\u00fcnthersleben",
    "sg:phone":"+49 36256/21603",
    "sg:postcode":"99869",
    "sg:province":"Th\u00fcringen",
    "wof:name":"Dietze & Tepper Gbr",
    "wof:placetype":"venue"
},
  "geometry": {"coordinates":[10.7634181976,50.9006958008],"type":"Point"}
}