{
  "type": "Feature",
  "properties": {
    "iso:country":"DE",
    "sg:address":"Ledergasse 2",
    "sg:city":"Unterw\u00f6ssen",
    "sg:postcode":"83246",
    "sg:province":"Bayern",
    "wof:name":"Manfred Aberger Gmbh",
    "wof:placetype":"venue"
},
  "geometry": {"coordinates":[12.459107,47.73555],"type":"Point"}
}