{
  "type": "Feature",
  "properties": {
    "iso:country":"DE",
    "sg:address":"Zollstock 9 a",
    "sg:city":"G\u00f6ttingen",
    "sg:phone":"+49 551/9000812",
    "sg:postcode":"37081",
    "sg:province":"Niedersachsen",
    "wof:name":"Parit\u00e4tischer Wohlfahrts Verband Sozialstation",
    "wof:placetype":"venue"
},
  "geometry": {"coordinates":[9.897674,51.532085],"type":"Point"}
}