{
  "type": "Feature",
  "properties": {
    "iso:country":"DE",
    "sg:address":"Werburger Str. 4",
    "sg:city":"Spenge",
    "sg:postcode":"32139",
    "sg:province":"Nordrhein-Westfalen",
    "wof:name":"Bhd Handels- Ferien- Und Freizeit Dienstleistungs Gmbh",
    "wof:placetype":"venue"
},
  "geometry": {"coordinates":[8.48258,52.142399],"type":"Point"}
}