{
  "type": "Feature",
  "properties": {
    "iso:country":"DE",
    "sg:address":"M\u00fchlenstr. 4",
    "sg:city":"Ergolding",
    "sg:phone":"+49 871/973800",
    "sg:postcode":"84030",
    "sg:province":"Bayern",
    "wof:name":"Ludwig Siegl Gmbh",
    "wof:placetype":"venue"
},
  "geometry": {"coordinates":[12.1592798233,48.5634346008],"type":"Point"}
}