{
  "type": "Feature",
  "properties": {
    "iso:country":"DE",
    "sg:address":"Lemkerberg 2",
    "sg:city":"Wadersloh",
    "sg:phone":"+49 2523/98800",
    "sg:postcode":"59329",
    "sg:province":"Nordrhein-Westfalen",
    "wof:name":"Bernhard B\u00f6cker-riese Mastschweine Kg",
    "wof:placetype":"venue"
},
  "geometry": {"coordinates":[8.1869945526,51.7022895813],"type":"Point"}
}