{
  "type": "Feature",
  "properties": {
    "iso:country":"DE",
    "sg:address":"Westpreu\u00dfenring 124",
    "sg:city":"L\u00fcbeck",
    "sg:phone":"+49 451/301687",
    "sg:postcode":"23569",
    "sg:province":"Schleswig-Holstein",
    "wof:name":"Peter Wenski",
    "wof:placetype":"venue"
},
  "geometry": {"coordinates":[10.8239860535,53.9201469421],"type":"Point"}
}