{
  "type": "Feature",
  "properties": {
    "iso:country":"DE",
    "sg:address":"Clara-Zetkin-Str. 1",
    "sg:city":"Bad Muskau",
    "sg:postcode":"02953",
    "sg:province":"Sachsen",
    "wof:name":"H. Wenzel",
    "wof:placetype":"venue"
},
  "geometry": {"coordinates":[14.7231063843,51.5437965393],"type":"Point"}
}