{
  "type": "Feature",
  "properties": {
    "iso:country":"DE",
    "sg:address":"Erlbachstr. 3",
    "sg:city":"Buchbach",
    "sg:phone":"+49 8086/1861",
    "sg:postcode":"84428",
    "sg:province":"Bayern",
    "wof:name":"Georg Krieger",
    "wof:placetype":"venue"
},
  "geometry": {"coordinates":[12.266408,48.30603],"type":"Point"}
}