{
  "type": "Feature",
  "properties": {
    "iso:country":"DE",
    "sg:address":"Lohstr. 72 a",
    "sg:city":"Stockelsdorf",
    "sg:phone":"+49 451/493850",
    "sg:postcode":"23617",
    "sg:province":"Schleswig-Holstein",
    "wof:name":"Koch Bau Gmbh",
    "wof:placetype":"venue"
},
  "geometry": {"coordinates":[10.6521606445,53.8950500488],"type":"Point"}
}