{
  "type": "Feature",
  "properties": {
    "iso:country":"DE",
    "sg:address":"Stauffenbergstr. 1",
    "sg:city":"Bochum",
    "sg:phone":"+49 2327/88201",
    "sg:postcode":"44866",
    "sg:province":"Nordrhein-Westfalen",
    "wof:name":"S. Katscher Steuerberater",
    "wof:placetype":"venue"
},
  "geometry": {"coordinates":[7.1581091881,51.4864234924],"type":"Point"}
}