{
  "type": "Feature",
  "properties": {
    "iso:country":"DE",
    "sg:address":"Ludwig-Thoma-Str 13",
    "sg:city":"Seebruck",
    "sg:phone":"+49 8667/888311",
    "sg:postcode":"83358",
    "sg:province":"Bayern",
    "wof:name":"Prolib Software Gmbh",
    "wof:placetype":"venue"
},
  "geometry": {"coordinates":[12.4775953293,47.9355010986],"type":"Point"}
}