{
  "type": "Feature",
  "properties": {
    "iso:country":"DE",
    "sg:address":"Bahnhofstr. 69",
    "sg:city":"Magdeburg",
    "sg:phone":"+49 391/344762",
    "sg:postcode":"39104",
    "sg:province":"Sachsen-Anhalt",
    "wof:name":"Sparda-bank Magdeburg",
    "wof:placetype":"venue"
},
  "geometry": {"coordinates":[11.628163,52.129543],"type":"Point"}
}