{
  "type": "Feature",
  "properties": {
    "iso:country":"DE",
    "sg:address":"Galgenkamp 31",
    "sg:city":"Vlotho",
    "sg:phone":"+49 5733/969424",
    "sg:postcode":"32602",
    "sg:province":"Nordrhein-Westfalen",
    "wof:name":"Gerd Bass Architekt",
    "wof:placetype":"venue"
},
  "geometry": {"coordinates":[8.84902,52.157021],"type":"Point"}
}