{
  "type": "Feature",
  "properties": {
    "iso:country":"DE",
    "sg:address":"Auf der Juh\u00f6he 2",
    "sg:city":"M\u00f6rlenbach",
    "sg:phone":"+49 6252/3916",
    "sg:postcode":"69509",
    "sg:province":"Hessen",
    "wof:name":"Gastst\u00e4tte A Bis Z",
    "wof:placetype":"venue"
},
  "geometry": {"coordinates":[8.6961927414,49.6234283447],"type":"Point"}
}