{
  "type": "Feature",
  "properties": {
    "iso:country":"DE",
    "sg:address":"Mittelweg 176",
    "sg:city":"Hamburg",
    "sg:phone":"+49 40/451012",
    "sg:postcode":"20148",
    "sg:province":"Hamburg",
    "wof:name":"Dianova Gesellschaft F\u00fcr Biochemiche Immunolog. U. Mi-",
    "wof:placetype":"venue"
},
  "geometry": {"coordinates":[9.994678,53.564327],"type":"Point"}
}