{
  "type": "Feature",
  "properties": {
    "iso:country":"DE",
    "sg:address":"Hinter der M\u00fchle",
    "sg:city":"Stendal",
    "sg:postcode":"39576",
    "sg:province":"Sachsen-Anhalt",
    "wof:name":"Gws Gas- Und Wasserversorgungs Gmbh",
    "wof:placetype":"venue"
},
  "geometry": {"coordinates":[11.8689289093,52.6054725647],"type":"Point"}
}