{
  "type": "Feature",
  "properties": {
    "iso:country":"DE",
    "sg:address":"Parkstr. 14",
    "sg:city":"Tarmstedt",
    "sg:phone":"+49 4283/1544",
    "sg:postcode":"27412",
    "sg:province":"Niedersachsen",
    "wof:name":"Egbert Bilke Masseur",
    "wof:placetype":"venue"
},
  "geometry": {"coordinates":[9.083456,53.22546],"type":"Point"}
}