{
  "type": "Feature",
  "properties": {
    "iso:country":"DE",
    "sg:address":"Lunaustr. 1",
    "sg:city":"Uslar",
    "sg:phone":"+49 5571/2617",
    "sg:postcode":"37170",
    "sg:province":"Niedersachsen",
    "wof:name":"Konsumgen. Gmbh",
    "wof:placetype":"venue"
},
  "geometry": {"coordinates":[9.5616073608,51.6893959045],"type":"Point"}
}