{
  "type": "Feature",
  "properties": {
    "iso:country":"DE",
    "sg:address":"L\u00f6hrstr. 70",
    "sg:city":"Koblenz",
    "sg:phone":"+49 261/37487",
    "sg:postcode":"56068",
    "sg:province":"Rheinland-Pfalz",
    "wof:name":"Zoom Gmbh",
    "wof:placetype":"venue"
},
  "geometry": {"coordinates":[7.5920581818,50.3576622009],"type":"Point"}
}