{
  "type": "Feature",
  "properties": {
    "iso:country":"DE",
    "sg:address":"Frankenwaldstr. 8",
    "sg:city":"Teuschnitz",
    "sg:phone":"+49 9268/1584",
    "sg:postcode":"96358",
    "sg:province":"Bayern",
    "wof:name":"P. Hader",
    "wof:placetype":"venue"
},
  "geometry": {"coordinates":[11.3850669861,50.3987579346],"type":"Point"}
}