{
  "type": "Feature",
  "properties": {
    "iso:country":"DE",
    "sg:address":"Marienburger Str. 56 B",
    "sg:city":"M\u00fcnchen",
    "sg:phone":"+49 89/937253",
    "sg:postcode":"81929",
    "sg:province":"Bayern",
    "wof:name":"Dr. Marion Weindl E. K.",
    "wof:placetype":"venue"
},
  "geometry": {"coordinates":[11.6463289261,48.1525611877],"type":"Point"}
}