{
  "type": "Feature",
  "properties": {
    "iso:country":"DE",
    "sg:address":"M\u00fchlwiesenstr. 28",
    "sg:city":"St. Georgen",
    "sg:phone":"+49 7724/5418",
    "sg:postcode":"78112",
    "sg:province":"Baden-W\u00fcrttemberg",
    "wof:name":"Optotest Gesellschaft F\u00fcr Ber\u00fchrungslose Me\u00dftechnik Mbh",
    "wof:placetype":"venue"
},
  "geometry": {"coordinates":[8.3706407547,48.1364479065],"type":"Point"}
}