{
  "type": "Feature",
  "properties": {
    "iso:country":"DE",
    "sg:address":"Friedhofstr 8",
    "sg:city":"L\u00fcdenscheid",
    "sg:phone":"+49 2351/380673",
    "sg:postcode":"58507",
    "sg:province":"Nordrhein-Westfalen",
    "wof:name":"B. Morawski",
    "wof:placetype":"venue"
},
  "geometry": {"coordinates":[7.6278247833,51.2209701538],"type":"Point"}
}