{
  "type": "Feature",
  "properties": {
    "iso:country":"DE",
    "sg:address":"Karneidplatz 18 A",
    "sg:city":"M\u00fcnchen",
    "sg:phone":"+49 89/644038",
    "sg:postcode":"81547",
    "sg:province":"Bayern",
    "wof:name":"Sollner Grundbesitzverw. Gmbh",
    "wof:placetype":"venue"
},
  "geometry": {"coordinates":[11.5680942535,48.0995483398],"type":"Point"}
}