{
  "type": "Feature",
  "properties": {
    "iso:country":"DE",
    "sg:address":"Brunecker Str. 1",
    "sg:city":"Gro\u00df-Gerau",
    "sg:phone":"+49 6152/54803",
    "sg:postcode":"64521",
    "sg:province":"Hessen",
    "wof:name":"Exquisit",
    "wof:placetype":"venue"
},
  "geometry": {"coordinates":[8.479072,49.911434],"type":"Point"}
}