{
  "type": "Feature",
  "properties": {
    "iso:country":"DE",
    "sg:address":"Braunschweiger Str 43",
    "sg:city":"Thedinghausen",
    "sg:phone":"+49 4204/91640",
    "sg:postcode":"27321",
    "sg:province":"Niedersachsen",
    "wof:name":"Automatisierungs-team Tote Gmbh",
    "wof:placetype":"venue"
},
  "geometry": {"coordinates":[9.0233354568,52.9619064331],"type":"Point"}
}