{
  "type": "Feature",
  "properties": {
    "iso:country":"DE",
    "sg:address":"Akademiestr. 7",
    "sg:city":"Karlsruhe",
    "sg:phone":"+49 721/25066",
    "sg:postcode":"76133",
    "sg:province":"Baden-W\u00fcrttemberg",
    "wof:name":"Oberl\u00e4nder Weinstube",
    "wof:placetype":"venue"
},
  "geometry": {"coordinates":[8.39802742,49.011631012],"type":"Point"}
}