{
  "type": "Feature",
  "properties": {
    "iso:country":"DE",
    "sg:address":"Fabrikstr. 8",
    "sg:city":"Kronau",
    "sg:phone":"+49 7253/7124",
    "sg:postcode":"76709",
    "sg:province":"Baden-W\u00fcrttemberg",
    "wof:name":"Alexander Hillenbrand",
    "wof:placetype":"venue"
},
  "geometry": {"coordinates":[8.6335058212,49.216960907],"type":"Point"}
}