{
  "type": "Feature",
  "properties": {
    "iso:country":"DE",
    "sg:address":"Gartenstr. 4",
    "sg:city":"Bergheim",
    "sg:phone":"+49 2271/62813",
    "sg:postcode":"50126",
    "sg:province":"Nordrhein-Westfalen",
    "wof:name":"Heinz Junggeburth",
    "wof:placetype":"venue"
},
  "geometry": {"coordinates":[6.652367,50.949013],"type":"Point"}
}