{
  "type": "Feature",
  "properties": {
    "iso:country":"DE",
    "sg:address":"Emster Str. 84",
    "sg:city":"Hagen",
    "sg:phone":"+49 2331/26060",
    "sg:postcode":"58093",
    "sg:province":"Nordrhein-Westfalen",
    "wof:name":"Lothar Br\u00fcninghaus",
    "wof:placetype":"venue"
},
  "geometry": {"coordinates":[7.5032877922,51.3533439636],"type":"Point"}
}