{
  "type": "Feature",
  "properties": {
    "iso:country":"DE",
    "sg:address":"Ludemert 7",
    "sg:city":"Werdohl",
    "sg:phone":"+49 2392/72000",
    "sg:postcode":"58791",
    "sg:province":"Nordrhein-Westfalen",
    "wof:name":"F. Und Dr. A. Hermes Steuerberater",
    "wof:placetype":"venue"
},
  "geometry": {"coordinates":[7.7398319244,51.2299957275],"type":"Point"}
}