{
  "type": "Feature",
  "properties": {
    "iso:country":"DE",
    "sg:address":"Oranienstr 183",
    "sg:city":"Berlin",
    "sg:phone":"+49 30/6147076",
    "sg:postcode":"10999",
    "sg:province":"Berlin",
    "wof:name":"Druckerei Wilhelm Schwarz Kg",
    "wof:placetype":"venue"
},
  "geometry": {"coordinates":[13.4207305908,52.5007324219],"type":"Point"}
}