{
  "type": "Feature",
  "properties": {
    "iso:country":"DE",
    "sg:address":"D\u00fcrerplatz 8",
    "sg:city":"N\u00fcrtingen",
    "sg:phone":"+49 7022/43333",
    "sg:postcode":"72622",
    "sg:province":"Baden-W\u00fcrttemberg",
    "wof:name":"Apotheke Ro\u00dfdorf",
    "wof:placetype":"venue"
},
  "geometry": {"coordinates":[9.34084,48.6068],"type":"Point"}
}