{
  "type": "Feature",
  "properties": {
    "iso:country":"DE",
    "sg:address":"Fliegenmoor 9",
    "sg:city":"Neu Wulmstorf",
    "sg:phone":"+49 4168/449",
    "sg:postcode":"21629",
    "sg:province":"Niedersachsen",
    "wof:name":"Werner Facklam",
    "wof:placetype":"venue"
},
  "geometry": {"coordinates":[9.7772598267,53.4276809692],"type":"Point"}
}