{
  "type": "Feature",
  "properties": {
    "iso:country":"DE",
    "sg:address":"Zahn-Nopper-Str. 3",
    "sg:city":"Stuttgart",
    "sg:postcode":"70435",
    "sg:province":"Baden-W\u00fcrttemberg",
    "wof:name":"Csw Eyyup Zabun E. K.",
    "wof:placetype":"venue"
},
  "geometry": {"coordinates":[9.1642227173,48.8322906494],"type":"Point"}
}