{
  "type": "Feature",
  "properties": {
    "iso:country":"DE",
    "sg:address":"Hochstr. 14",
    "sg:city":"Schmitten",
    "sg:phone":"+49 6082/2206",
    "sg:postcode":"61389",
    "sg:province":"Hessen",
    "wof:name":"Wilhelm Schmitt",
    "wof:placetype":"venue"
},
  "geometry": {"coordinates":[8.4323759079,50.2452583313],"type":"Point"}
}