{
  "type": "Feature",
  "properties": {
    "iso:country":"DE",
    "sg:address":"Edisonstr. 15",
    "sg:city":"Lampertheim",
    "sg:phone":"+49 6206/503700",
    "sg:postcode":"68623",
    "sg:province":"Hessen",
    "wof:name":"Microfluidics Corporationeuropean Office",
    "wof:placetype":"venue"
},
  "geometry": {"coordinates":[8.4818954468,49.6004714966],"type":"Point"}
}