{
  "type": "Feature",
  "properties": {
    "iso:country":"DE",
    "sg:address":"Behringstr. 5",
    "sg:city":"Reutlingen",
    "sg:phone":"+49 7121/491523",
    "sg:postcode":"72766",
    "sg:province":"Baden-W\u00fcrttemberg",
    "wof:name":"Hotel Garni Kohler Inh. Rosemarie Venus",
    "wof:placetype":"venue"
},
  "geometry": {"coordinates":[9.21941185,48.5006523132],"type":"Point"}
}