{
  "type": "Feature",
  "properties": {
    "iso:country":"DE",
    "sg:address":"Glockenberg 6",
    "sg:city":"Neustadt",
    "sg:phone":"+49 9568/5973",
    "sg:postcode":"96465",
    "sg:province":"Bayern",
    "wof:name":"As-dekor Albert Schindhelm",
    "wof:placetype":"venue"
},
  "geometry": {"coordinates":[11.12565,50.326172],"type":"Point"}
}