{
  "type": "Feature",
  "properties": {
    "iso:country":"DE",
    "sg:address":"Augustin-Wibbelt-Str. 49",
    "sg:city":"Gelsenkirchen",
    "sg:phone":"+49 209/33753",
    "sg:postcode":"45894",
    "sg:province":"Nordrhein-Westfalen",
    "wof:name":"G\u00fcnter Bednarz",
    "wof:placetype":"venue"
},
  "geometry": {"coordinates":[7.0733861923,51.5775375366],"type":"Point"}
}