{
  "type": "Feature",
  "properties": {
    "iso:country":"DE",
    "sg:address":"Markt 4",
    "sg:city":"R\u00f6tha",
    "sg:phone":"+49 34206/72189",
    "sg:postcode":"04571",
    "sg:province":"Sachsen",
    "wof:name":"R. K\u00e4stner",
    "wof:placetype":"venue"
},
  "geometry": {"coordinates":[12.41044,51.197495],"type":"Point"}
}