{
  "type": "Feature",
  "properties": {
    "iso:country":"DE",
    "sg:address":"Sartoriusstr. 22",
    "sg:city":"Hamburg",
    "sg:postcode":"20257",
    "sg:province":"Hamburg",
    "wof:name":"W.e. Heinold Beratungsges. Mbh",
    "wof:placetype":"venue"
},
  "geometry": {"coordinates":[9.9427928925,53.5801391602],"type":"Point"}
}