{
  "type": "Feature",
  "properties": {
    "iso:country":"DE",
    "sg:address":"Marktplatz 2",
    "sg:city":"M\u00fcllheim",
    "sg:phone":"+49 7631/14494",
    "sg:postcode":"79379",
    "sg:province":"Baden-W\u00fcrttemberg",
    "wof:name":"Michael Greger Garten- Und",
    "wof:placetype":"venue"
},
  "geometry": {"coordinates":[7.629914,47.806053],"type":"Point"}
}