{
  "type": "Feature",
  "properties": {
    "iso:country":"DE",
    "sg:address":"P\u00f6tzschker Weg 2-4",
    "sg:city":"Leipzig",
    "sg:phone":"+49 341/9404097",
    "sg:postcode":"04179",
    "sg:province":"Sachsen",
    "wof:name":"Montageservice Roman Linhart K\u00fcchen & Mehr",
    "wof:placetype":"venue"
},
  "geometry": {"coordinates":[12.308994,51.327469],"type":"Point"}
}