{
  "type": "Feature",
  "properties": {
    "iso:country":"DE",
    "sg:address":"Astweg 43",
    "sg:city":"Hamburg",
    "sg:phone":"+49 40/578271",
    "sg:postcode":"22523",
    "sg:province":"Hamburg",
    "wof:name":"Grundst\u00fccksverwaltung Friedrichskoog",
    "wof:placetype":"venue"
},
  "geometry": {"coordinates":[9.88530159,53.6149520874],"type":"Point"}
}