{
  "type": "Feature",
  "properties": {
    "iso:country":"DE",
    "sg:address":"Blumentrave 10",
    "sg:city":"Gr\u00f6mitz",
    "sg:phone":"+49 4562/9860",
    "sg:postcode":"23743",
    "sg:province":"Schleswig-Holstein",
    "wof:name":"Faust Gmbh",
    "wof:placetype":"venue"
},
  "geometry": {"coordinates":[10.947863,54.140873],"type":"Point"}
}