{
  "type": "Feature",
  "properties": {
    "iso:country":"DE",
    "sg:address":"Mariendorfer Damm 197 -199",
    "sg:city":"Berlin",
    "sg:phone":"+49 30/76108111",
    "sg:postcode":"12107",
    "sg:province":"Berlin",
    "wof:name":"Avis Autovermietung Gmbh",
    "wof:placetype":"venue"
},
  "geometry": {"coordinates":[13.390739,52.43359],"type":"Point"}
}