{
  "type": "Feature",
  "properties": {
    "iso:country":"DE",
    "sg:address":"Wismarsche Str. 19",
    "sg:city":"Warin",
    "sg:phone":"+49 38482/60504",
    "sg:postcode":"19417",
    "sg:province":"Mecklenburg-Vorpommern",
    "wof:name":"Egon Giersdorf",
    "wof:placetype":"venue"
},
  "geometry": {"coordinates":[11.6998567581,53.7996177673],"type":"Point"}
}