{
  "type": "Feature",
  "properties": {
    "iso:country":"DE",
    "sg:address":"Georg-Fischer-Str. 42",
    "sg:city":"Singen",
    "sg:phone":"+49 7731/924790",
    "sg:postcode":"78224",
    "sg:province":"Baden-W\u00fcrttemberg",
    "wof:name":"Hans Kowalski",
    "wof:placetype":"venue"
},
  "geometry": {"coordinates":[8.850623,47.752895],"type":"Point"}
}