{
  "type": "Feature",
  "properties": {
    "iso:country":"DE",
    "sg:address":"Wormser Landstr. 194",
    "sg:city":"Speyer",
    "sg:phone":"+49 6232/40420",
    "sg:postcode":"67346",
    "sg:province":"Rheinland-Pfalz",
    "wof:name":"Deutsche Shell Ag",
    "wof:placetype":"venue"
},
  "geometry": {"coordinates":[8.4291954041,49.3381729126],"type":"Point"}
}