{
  "type": "Feature",
  "properties": {
    "iso:country":"DE",
    "sg:address":"Einsiedlerstr. 11-13",
    "sg:city":"Gernsheim",
    "sg:phone":"+49 6258/93450",
    "sg:postcode":"64579",
    "sg:province":"Hessen",
    "wof:name":"Kaufhaus Schuker Gmbh & Co. Kg",
    "wof:placetype":"venue"
},
  "geometry": {"coordinates":[8.485782,49.750385],"type":"Point"}
}