{
  "type": "Feature",
  "properties": {
    "iso:country":"DE",
    "sg:address":"Postfach 1204",
    "sg:city":"Kolbermoor",
    "sg:phone":"+49 8031/29450",
    "sg:postcode":"08031",
    "sg:province":"Bayern",
    "wof:name":"Mail Point",
    "wof:placetype":"venue"
},
  "geometry": {"coordinates":[-75.092339,39.865829],"type":"Point"}
}