{
  "type": "Feature",
  "properties": {
    "iso:country":"DE",
    "sg:address":"Bismarckstr. 56",
    "sg:city":"M\u00f6nchengladbach",
    "sg:phone":"+49 2161/12466",
    "sg:postcode":"41061",
    "sg:province":"Nordrhein-Westfalen",
    "wof:name":"Brigitte Reichartz",
    "wof:placetype":"venue"
},
  "geometry": {"coordinates":[6.44084,51.197166],"type":"Point"}
}