{
  "type": "Feature",
  "properties": {
    "iso:country":"DE",
    "sg:address":"Duisburger Str. 92",
    "sg:city":"D\u00fcsseldorf",
    "sg:phone":"+49 211/4911547",
    "sg:postcode":"40479",
    "sg:province":"Nordrhein-Westfalen",
    "wof:name":"Fisch Und Meer Ulrich Und Steinicke Gbr",
    "wof:placetype":"venue"
},
  "geometry": {"coordinates":[6.784632206,51.2337493896],"type":"Point"}
}