{
  "type": "Feature",
  "properties": {
    "iso:country":"DE",
    "sg:address":"Dorfstr. 31",
    "sg:city":"Wittmannsdorf-B\u00fcckchen",
    "sg:phone":"+49 35476/287",
    "sg:postcode":"15910",
    "sg:province":"Brandenburg",
    "wof:name":"Herbert Nimtz",
    "wof:placetype":"venue"
},
  "geometry": {"coordinates":[13.765821,51.979591],"type":"Point"}
}