{
  "type": "Feature",
  "properties": {
    "iso:country":"DE",
    "sg:address":"Oppacher Str. 14 a",
    "sg:city":"Lawalde",
    "sg:phone":"+49 3585/404032",
    "sg:postcode":"02708",
    "sg:province":"Sachsen",
    "wof:name":"Frank Streiter",
    "wof:placetype":"venue"
},
  "geometry": {"coordinates":[14.6013479233,51.0810585022],"type":"Point"}
}