{
  "type": "Feature",
  "properties": {
    "iso:country":"DE",
    "sg:address":"Gebr\u00fcder-Wright-Str. 14",
    "sg:city":"Bonn",
    "sg:phone":"+49 228/363676",
    "sg:postcode":"53125",
    "sg:province":"Nordrhein-Westfalen",
    "wof:name":"Rattan-trends Gmbh",
    "wof:placetype":"venue"
},
  "geometry": {"coordinates":[7.0534338951,50.6933822632],"type":"Point"}
}