{
  "type": "Feature",
  "properties": {
    "iso:country":"DE",
    "sg:address":"Heinkelstr. 9",
    "sg:city":"B\u00f6blingen",
    "sg:postcode":"71034",
    "sg:province":"Baden-W\u00fcrttemberg",
    "wof:name":"R. Tv Medien Ag",
    "wof:placetype":"venue"
},
  "geometry": {"coordinates":[8.9876928329,48.6840553284],"type":"Point"}
}