{
  "type": "Feature",
  "properties": {
    "iso:country":"DE",
    "sg:address":"Rabenweg 38",
    "sg:city":"Willich",
    "sg:phone":"+49 2154/8456",
    "sg:postcode":"47877",
    "sg:province":"Nordrhein-Westfalen",
    "wof:name":"Walter Nardelli",
    "wof:placetype":"venue"
},
  "geometry": {"coordinates":[6.5512399673,51.2626991272],"type":"Point"}
}