{
  "type": "Feature",
  "properties": {
    "iso:country":"DE",
    "sg:address":"Bahnhofstr. 11",
    "sg:city":"Hude",
    "sg:phone":"+49 4484/422",
    "sg:postcode":"27798",
    "sg:province":"Niedersachsen",
    "wof:name":"Ludwig Triphaus",
    "wof:placetype":"venue"
},
  "geometry": {"coordinates":[8.334404,53.11924],"type":"Point"}
}