{
  "type": "Feature",
  "properties": {
    "iso:country":"DE",
    "sg:address":"Drontheimer Str. 32a",
    "sg:city":"Berlin",
    "sg:phone":"+49 30/4900010",
    "sg:postcode":"13359",
    "sg:province":"Berlin",
    "wof:name":"Quadriga Gmbh",
    "wof:placetype":"venue"
},
  "geometry": {"coordinates":[13.376742,52.558609],"type":"Point"}
}