{
  "type": "Feature",
  "properties": {
    "iso:country":"DE",
    "sg:address":"Ennepestr. 5",
    "sg:city":"Gevelsberg",
    "sg:phone":"+49 2332/83319",
    "sg:postcode":"58285",
    "sg:province":"Nordrhein-Westfalen",
    "wof:name":"M. Und S. Agricola",
    "wof:placetype":"venue"
},
  "geometry": {"coordinates":[7.3406767845,51.3162307739],"type":"Point"}
}