{
  "type": "Feature",
  "properties": {
    "iso:country":"DE",
    "sg:address":"Metzstr. 14",
    "sg:city":"M\u00fcnchen",
    "sg:postcode":"81667",
    "sg:province":"Bayern",
    "wof:name":"Moba Verwaltungsgesellschaft Gmbh & Co. Objekt Zarrentin",
    "wof:placetype":"venue"
},
  "geometry": {"coordinates":[11.5972833633,48.1291656494],"type":"Point"}
}