{
  "type": "Feature",
  "properties": {
    "iso:country":"DE",
    "sg:address":"Bismarckstr. 35",
    "sg:city":"Berlin",
    "sg:phone":"+49 30/21967628",
    "sg:postcode":"10627",
    "sg:province":"Berlin",
    "wof:name":"Tickets-worldwide",
    "wof:placetype":"venue"
},
  "geometry": {"coordinates":[13.308506,52.511932],"type":"Point"}
}