{
  "type": "Feature",
  "properties": {
    "iso:country":"DE",
    "sg:address":"Geleitsstr. 50",
    "sg:city":"Offenbach",
    "sg:phone":"+49 69/880847",
    "sg:postcode":"63067",
    "sg:province":"Hessen",
    "wof:name":"Peter Und Miriam Kasten",
    "wof:placetype":"venue"
},
  "geometry": {"coordinates":[8.759305954,50.1024398804],"type":"Point"}
}