{
  "type": "Feature",
  "properties": {
    "iso:country":"DE",
    "sg:address":"Sch\u00fctzenstr. 3",
    "sg:city":"W\u00f6rnitz",
    "sg:phone":"+49 9868/379",
    "sg:postcode":"91637",
    "sg:province":"Bayern",
    "wof:name":"Karl N\u00fctzel",
    "wof:placetype":"venue"
},
  "geometry": {"coordinates":[10.242373,49.25452],"type":"Point"}
}