{
  "type": "Feature",
  "properties": {
    "iso:country":"DE",
    "sg:address":"Hauptstr. 93",
    "sg:city":"Schopfheim",
    "sg:phone":"+49 7622/9990",
    "sg:postcode":"79650",
    "sg:province":"Baden-W\u00fcrttemberg",
    "wof:name":"Anita Seger",
    "wof:placetype":"venue"
},
  "geometry": {"coordinates":[7.8238339424,47.6515426636],"type":"Point"}
}