{
  "type": "Feature",
  "properties": {
    "iso:country":"DE",
    "sg:address":"Rathenaustr. 4",
    "sg:city":"Mannheim",
    "sg:phone":"+49 621/411020",
    "sg:postcode":"68165",
    "sg:province":"Baden-W\u00fcrttemberg",
    "wof:name":"M\u00f6hrle Und Gruler Rechtsanw\u00e4lte",
    "wof:placetype":"venue"
},
  "geometry": {"coordinates":[8.4793777466,49.4872779846],"type":"Point"}
}