{
  "type": "Feature",
  "properties": {
    "iso:country":"DE",
    "sg:address":"Schierker Str. 33-34",
    "sg:city":"Berlin",
    "sg:postcode":"12051",
    "sg:province":"Berlin",
    "wof:name":"Aldi Gmbh & Co. Kg",
    "wof:placetype":"venue"
},
  "geometry": {"coordinates":[13.4378585815,52.4704322815],"type":"Point"}
}