{
  "type": "Feature",
  "properties": {
    "iso:country":"DE",
    "sg:address":"Hauptstr. 77",
    "sg:city":"Sch\u00f6nborn",
    "sg:phone":"+49 35326/643",
    "sg:postcode":"03253",
    "sg:province":"Brandenburg",
    "wof:name":"Drei Linden",
    "wof:placetype":"venue"
},
  "geometry": {"coordinates":[13.5000228882,51.5960273743],"type":"Point"}
}