{
  "type": "Feature",
  "properties": {
    "iso:country":"DE",
    "sg:address":"M\u00fchlenweg 67",
    "sg:city":"Norderstedt",
    "sg:phone":"+49 40/5267540",
    "sg:postcode":"22844",
    "sg:province":"Schleswig-Holstein",
    "wof:name":"Heinz Ahrens",
    "wof:placetype":"venue"
},
  "geometry": {"coordinates":[10.006139,53.728973],"type":"Point"}
}