{
  "type": "Feature",
  "properties": {
    "iso:country":"DE",
    "sg:address":"Jetzendorfer Str. 6",
    "sg:city":"Petershausen",
    "sg:postcode":"85238",
    "sg:province":"Bayern",
    "wof:name":"Camline Holding Ag",
    "wof:placetype":"venue"
},
  "geometry": {"coordinates":[11.4672994614,48.4095573425],"type":"Point"}
}