{
  "type": "Feature",
  "properties": {
    "iso:country":"DE",
    "sg:address":"Geschwister-Scholl-Platz 1",
    "sg:city":"Gotha",
    "sg:phone":"+49 3621/743886",
    "sg:postcode":"99867",
    "sg:province":"Th\u00fcringen",
    "wof:name":"Malerbetrieb Willi M\u00f6ller Gmbh",
    "wof:placetype":"venue"
},
  "geometry": {"coordinates":[10.693276,50.934643],"type":"Point"}
}