{
  "type": "Feature",
  "properties": {
    "iso:country":"DE",
    "sg:address":"T\u00f6lzer Str. 13",
    "sg:city":"Gmund",
    "sg:phone":"+49 8022/76296",
    "sg:postcode":"83703",
    "sg:province":"Bayern",
    "wof:name":"R. Vogelhuber",
    "wof:placetype":"venue"
},
  "geometry": {"coordinates":[11.7347984314,47.7508773804],"type":"Point"}
}