{
  "type": "Feature",
  "properties": {
    "iso:country":"DE",
    "sg:address":"Schillerstr. 9",
    "sg:city":"Frickenhausen",
    "sg:phone":"+49 7022/44090",
    "sg:postcode":"72636",
    "sg:province":"Baden-W\u00fcrttemberg",
    "wof:name":"E. Rothweiler Mech. Werkstatt",
    "wof:placetype":"venue"
},
  "geometry": {"coordinates":[9.35513,48.594021],"type":"Point"}
}