{
  "type": "Feature",
  "properties": {
    "iso:country":"DE",
    "sg:address":"Haslerstr. 27",
    "sg:city":"N\u00fcrnberg",
    "sg:phone":"+49 911/429272",
    "sg:postcode":"90443",
    "sg:province":"Bayern",
    "wof:name":"Walter Heiss Heilpraktiker",
    "wof:placetype":"venue"
},
  "geometry": {"coordinates":[11.0706539154,49.4401092529],"type":"Point"}
}