{
  "type": "Feature",
  "properties": {
    "iso:country":"DE",
    "sg:address":"Gutenbergstr. 20",
    "sg:city":"Stutensee",
    "sg:phone":"+49 7249/3479",
    "sg:postcode":"76297",
    "sg:province":"Baden-W\u00fcrttemberg",
    "wof:name":"Rolf Roller",
    "wof:placetype":"venue"
},
  "geometry": {"coordinates":[8.512556,49.113564],"type":"Point"}
}