{
  "type": "Feature",
  "properties": {
    "iso:country":"DE",
    "sg:address":"Stra\u00dfe des Friedens 5",
    "sg:city":"Ilmenau",
    "sg:phone":"+49 3677/202160",
    "sg:postcode":"98693",
    "sg:province":"Th\u00fcringen",
    "wof:name":"Karl H\u00fclfenhaus",
    "wof:placetype":"venue"
},
  "geometry": {"coordinates":[10.9143028259,50.6848754883],"type":"Point"}
}