{
  "type": "Feature",
  "properties": {
    "iso:country":"DE",
    "sg:address":"Inkofener Str 34",
    "sg:city":"Wang",
    "sg:phone":"+49 791/5063000",
    "sg:postcode":"85368",
    "sg:province":"Bayern",
    "wof:name":"Kugler - Division Of Optima Packaging Group Gmbh",
    "wof:placetype":"venue"
},
  "geometry": {"coordinates":[9.705641,49.1049],"type":"Point"}
}