{
  "type": "Feature",
  "properties": {
    "iso:country":"DE",
    "sg:address":"Am Siegenbittel 7",
    "sg:city":"Arnsberg",
    "sg:phone":"+49 2932/32318",
    "sg:postcode":"59759",
    "sg:province":"Nordrhein-Westfalen",
    "wof:name":"Wilhelm Gutland",
    "wof:placetype":"venue"
},
  "geometry": {"coordinates":[7.9924058914,51.420173645],"type":"Point"}
}