{
  "type": "Feature",
  "properties": {
    "iso:country":"DE",
    "sg:address":"Alersborn 10",
    "sg:city":"Haiger",
    "sg:phone":"+49 2773/4438",
    "sg:postcode":"35708",
    "sg:province":"Hessen",
    "wof:name":"Stovatec Oberfl\u00e4chenveredelungs Gmbh",
    "wof:placetype":"venue"
},
  "geometry": {"coordinates":[8.175747,50.707394],"type":"Point"}
}