{
  "type": "Feature",
  "properties": {
    "iso:country":"DE",
    "sg:address":"Hohe Eiche 15",
    "sg:city":"Bochum",
    "sg:phone":"+49 234/288822",
    "sg:postcode":"44892",
    "sg:province":"Nordrhein-Westfalen",
    "wof:name":"Eiscafe Cesare Darmann",
    "wof:placetype":"venue"
},
  "geometry": {"coordinates":[7.305221,51.475456],"type":"Point"}
}