{
  "type": "Feature",
  "properties": {
    "iso:country":"DE",
    "sg:address":"Schwanenstr. 13",
    "sg:city":"Velbert",
    "sg:phone":"+49 2051/55595",
    "sg:postcode":"42551",
    "sg:province":"Nordrhein-Westfalen",
    "wof:name":"Studitalia Reisen",
    "wof:placetype":"venue"
},
  "geometry": {"coordinates":[7.0453300476,51.343585968],"type":"Point"}
}