{
  "type": "Feature",
  "properties": {
    "iso:country":"DE",
    "sg:address":"Ankerstr. 37",
    "sg:city":"K\u00f6nigsbach-Stein",
    "sg:phone":"+49 7232/30040",
    "sg:postcode":"75203",
    "sg:province":"Baden-W\u00fcrttemberg",
    "wof:name":"Nkc Schuler Gmbh",
    "wof:placetype":"venue"
},
  "geometry": {"coordinates":[8.608666,48.965923],"type":"Point"}
}