{
  "type": "Feature",
  "properties": {
    "iso:country":"DE",
    "sg:address":"Carl-Goerdeler-Weg 8",
    "sg:city":"Stade",
    "sg:postcode":"21684",
    "sg:province":"Niedersachsen",
    "wof:name":"Interessen-gemeinschaft Modellbau Niederelbe E.v.",
    "wof:placetype":"venue"
},
  "geometry": {"coordinates":[9.499538,53.572147],"type":"Point"}
}