{
  "type": "Feature",
  "properties": {
    "iso:country":"DE",
    "sg:address":"K\u00e4the-Kollwitz-Str.16",
    "sg:city":"Heidenau",
    "sg:postcode":"01809",
    "sg:province":"Sachsen",
    "wof:name":"Hobby - Und Sammlerhomepage Lothar Hoppenz Privat",
    "wof:placetype":"venue"
},
  "geometry": {"coordinates":[13.863175,50.982998],"type":"Point"}
}