{
  "type": "Feature",
  "properties": {
    "iso:country":"DE",
    "sg:address":"Michaelisstr. 74",
    "sg:city":"Darmstadt",
    "sg:postcode":"64293",
    "sg:province":"Hessen",
    "wof:name":"Buchbinderei Schaumann E. K.",
    "wof:placetype":"venue"
},
  "geometry": {"coordinates":[8.621092,49.884174],"type":"Point"}
}