{
  "type": "Feature",
  "properties": {
    "iso:country":"DE",
    "sg:address":"Am Querkamp 2",
    "sg:city":"Bremen",
    "sg:phone":"+49 421/250806",
    "sg:postcode":"28355",
    "sg:province":"Bremen",
    "wof:name":"Niels Rodewald",
    "wof:placetype":"venue"
},
  "geometry": {"coordinates":[8.9299726486,53.0949668884],"type":"Point"}
}