{
  "type": "Feature",
  "properties": {
    "iso:country":"DE",
    "sg:address":"Am Patentbusch 14",
    "sg:city":"Oldenburg",
    "sg:phone":"+49 441/930250",
    "sg:postcode":"26125",
    "sg:province":"Niedersachsen",
    "wof:name":"Terra Bauindustrie Gmbh",
    "wof:placetype":"venue"
},
  "geometry": {"coordinates":[8.2298326492,53.1947631836],"type":"Point"}
}