{
  "type": "Feature",
  "properties": {
    "iso:country":"DE",
    "sg:address":"Alexanderstr. 28",
    "sg:city":"Viernheim",
    "sg:phone":"+49 6204/3237",
    "sg:postcode":"68519",
    "sg:province":"Hessen",
    "wof:name":"Alexanderklause",
    "wof:placetype":"venue"
},
  "geometry": {"coordinates":[8.5741539001,49.5408744812],"type":"Point"}
}