{
  "type": "Feature",
  "properties": {
    "iso:country":"DE",
    "sg:address":"Rundweg 7",
    "sg:city":"Neuss",
    "sg:phone":"+49 2131/467614",
    "sg:postcode":"41472",
    "sg:province":"Nordrhein-Westfalen",
    "wof:name":"Schraubenvertrieb H. Doppel",
    "wof:placetype":"venue"
},
  "geometry": {"coordinates":[6.663171,51.159103],"type":"Point"}
}