{
  "type": "Feature",
  "properties": {
    "iso:country":"DE",
    "sg:address":"Ratsstr. 2",
    "sg:city":"Bad Salzungen",
    "sg:phone":"+49 3695/671116",
    "sg:postcode":"36433",
    "sg:province":"Th\u00fcringen",
    "wof:name":"Stadtarchiv",
    "wof:placetype":"venue"
},
  "geometry": {"coordinates":[10.235326,50.813057],"type":"Point"}
}