{
  "type": "Feature",
  "properties": {
    "iso:country":"DE",
    "sg:address":"Im Hesselbruch 25",
    "sg:city":"Essen",
    "sg:phone":"+49 201/611779",
    "sg:postcode":"45356",
    "sg:province":"Nordrhein-Westfalen",
    "wof:name":"Fischer & Adams Gmbh & Co. Kg",
    "wof:placetype":"venue"
},
  "geometry": {"coordinates":[6.956251,51.488541],"type":"Point"}
}