{
  "type": "Feature",
  "properties": {
    "iso:country":"DE",
    "sg:address":"Tannenh\u00f6he 2",
    "sg:city":"Schulenberg",
    "sg:phone":"+49 5329/806",
    "sg:postcode":"38707",
    "sg:province":"Niedersachsen",
    "wof:name":"Hotel Pension Lug Ins Land",
    "wof:placetype":"venue"
},
  "geometry": {"coordinates":[-96.90380096440001,29.6820907593],"type":"Point"}
}