{
  "type": "Feature",
  "properties": {
    "iso:country":"DE",
    "sg:city":"Marienthal /Ww.",
    "sg:phone":"+49 2682",
    "sg:postcode":"57612",
    "sg:province":"Rheinland-Pfalz",
    "wof:name":"Waldhotel Imh\u00e4user",
    "wof:placetype":"venue"
},
  "geometry": {"coordinates":[7.619361,50.696148],"type":"Point"}
}