{
  "type": "Feature",
  "properties": {
    "iso:country":"DE",
    "sg:address":"Stolzingstr. 4",
    "sg:city":"M\u00fcnchen",
    "sg:phone":"+49 89/914979",
    "sg:postcode":"81927",
    "sg:province":"Bayern",
    "wof:name":"Alexander Kasper Architekt",
    "wof:placetype":"venue"
},
  "geometry": {"coordinates":[11.632034,48.155201],"type":"Point"}
}