{
  "type": "Feature",
  "properties": {
    "iso:country":"DE",
    "sg:address":"Bertleinstr. 12",
    "sg:city":"Lauf",
    "sg:phone":"+49 9123/81594",
    "sg:postcode":"91207",
    "sg:province":"Bayern",
    "wof:name":"Mon. Scanzoni Von Lichtenfels Krankengymnastin",
    "wof:placetype":"venue"
},
  "geometry": {"coordinates":[11.284551,49.50386],"type":"Point"}
}