{
  "type": "Feature",
  "properties": {
    "iso:country":"DE",
    "sg:address":"Orleansstr. 10 - 12",
    "sg:city":"M\u00fcnchen",
    "sg:phone":"+49 89/4484354",
    "sg:postcode":"81669",
    "sg:province":"Bayern",
    "wof:name":"Bayerisches Zentrum F\u00fcr Ost-west-management-",
    "wof:placetype":"venue"
},
  "geometry": {"coordinates":[11.5988368988,48.1247291565],"type":"Point"}
}