{
  "type": "Feature",
  "properties": {
    "iso:country":"DE",
    "sg:address":"Poststr. 11",
    "sg:city":"Xanten",
    "sg:phone":"+49 2801/4434",
    "sg:postcode":"46509",
    "sg:province":"Nordrhein-Westfalen",
    "wof:name":"J. Bousardt Masseur",
    "wof:placetype":"venue"
},
  "geometry": {"coordinates":[6.452183,51.659298],"type":"Point"}
}