{
  "type": "Feature",
  "properties": {
    "iso:country":"DE",
    "sg:address":"Am Alten Born 32",
    "sg:city":"Weyerbusch",
    "sg:phone":"+49 2686/1418",
    "sg:postcode":"57635",
    "sg:province":"Rheinland-Pfalz",
    "wof:name":"H\u00f6hner Kg",
    "wof:placetype":"venue"
},
  "geometry": {"coordinates":[7.5527749062,50.7170677185],"type":"Point"}
}