{
  "type": "Feature",
  "properties": {
    "iso:country":"DE",
    "sg:address":"Untere Str. 18",
    "sg:city":"Wildberg",
    "sg:postcode":"72218",
    "sg:province":"Baden-W\u00fcrttemberg",
    "wof:name":"Schwarzwald-quelle Wildberg Gesch\u00e4ftsf\u00fchrungs- Und",
    "wof:placetype":"venue"
},
  "geometry": {"coordinates":[8.775844,48.61956],"type":"Point"}
}