{
  "type": "Feature",
  "properties": {
    "iso:country":"DE",
    "sg:address":"G\u00fctzkower Str. 30",
    "sg:city":"Greifswald",
    "sg:phone":"+49 3834/57900",
    "sg:postcode":"17489",
    "sg:province":"Mecklenburg-Vorpommern",
    "wof:name":"Generalvertretung Matthias Ch. Ruchholz E. Kfm.",
    "wof:placetype":"venue"
},
  "geometry": {"coordinates":[13.3790597916,54.0889625549],"type":"Point"}
}