{
  "type": "Feature",
  "properties": {
    "iso:country":"DE",
    "sg:address":"Parkstr. 1",
    "sg:city":"Weidenbach",
    "sg:phone":"+49 9826/271",
    "sg:postcode":"91746",
    "sg:province":"Bayern",
    "wof:name":"Rudolf Albert",
    "wof:placetype":"venue"
},
  "geometry": {"coordinates":[10.6483068466,49.2012863159],"type":"Point"}
}