{
  "type": "Feature",
  "properties": {
    "iso:country":"DE",
    "sg:address":"Kurt-A.-K\u00f6rber-Chaussee 102",
    "sg:city":"Hamburg",
    "sg:phone":"+49 40/7241590",
    "sg:postcode":"21033",
    "sg:province":"Hamburg",
    "wof:name":"Wolfgang H. J\u00e4ger Steuerberater",
    "wof:placetype":"venue"
},
  "geometry": {"coordinates":[10.1895170212,53.4901847839],"type":"Point"}
}