{
  "type": "Feature",
  "properties": {
    "iso:country":"DE",
    "sg:address":"Am Bahndamm 2a",
    "sg:city":"Hannover",
    "sg:phone":"+49 511/482012",
    "sg:postcode":"30453",
    "sg:province":"Niedersachsen",
    "wof:name":"Klaas Messtechnik Gmbh",
    "wof:placetype":"venue"
},
  "geometry": {"coordinates":[9.671261,52.382927],"type":"Point"}
}