{
  "type": "Feature",
  "properties": {
    "iso:country":"DE",
    "sg:address":"Waldemeinestr. 26",
    "sg:city":"Bad Salzuflen",
    "sg:phone":"+49 5222/6964",
    "sg:postcode":"32108",
    "sg:province":"Nordrhein-Westfalen",
    "wof:name":"Intera Training Und Personalentwicklung Gmbh",
    "wof:placetype":"venue"
},
  "geometry": {"coordinates":[8.7718353271,52.1049041748],"type":"Point"}
}