{
  "type": "Feature",
  "properties": {
    "iso:country":"DE",
    "sg:address":"Quickborner Str. 76",
    "sg:city":"Berlin",
    "sg:phone":"+49 30/4151001",
    "sg:postcode":"13439",
    "sg:province":"Berlin",
    "wof:name":"M\u00f6bel Tip",
    "wof:placetype":"venue"
},
  "geometry": {"coordinates":[13.36638,52.604362],"type":"Point"}
}