{
  "type": "Feature",
  "properties": {
    "iso:country":"DE",
    "sg:address":"Immengartenstr. 60 a",
    "sg:city":"Maikammer",
    "sg:phone":"+49 6321/57285",
    "sg:postcode":"67487",
    "sg:province":"Rheinland-Pfalz",
    "wof:name":"Werner Wei\u00dfbrod Architekt",
    "wof:placetype":"venue"
},
  "geometry": {"coordinates":[8.135564,49.303211],"type":"Point"}
}