{
  "type": "Feature",
  "properties": {
    "iso:country":"DE",
    "sg:address":"Agnesstr. 22",
    "sg:city":"Frammersbach",
    "sg:phone":"+49 9355/1016",
    "sg:postcode":"97833",
    "sg:province":"Bayern",
    "wof:name":"Wiesner",
    "wof:placetype":"venue"
},
  "geometry": {"coordinates":[9.480111,50.06377],"type":"Point"}
}