{
  "type": "Feature",
  "properties": {
    "iso:country":"DE",
    "sg:address":"Weinstr. 20",
    "sg:city":"Offenburg",
    "sg:phone":"+49 781/34540",
    "sg:postcode":"77654",
    "sg:province":"Baden-W\u00fcrttemberg",
    "wof:name":"Ratskeller",
    "wof:placetype":"venue"
},
  "geometry": {"coordinates":[7.9861330986,48.4756546021],"type":"Point"}
}