{
  "type": "Feature",
  "properties": {
    "iso:country":"DE",
    "sg:address":"Br\u00fcckenstr. 6",
    "sg:city":"Marktoberdorf",
    "sg:phone":"+49 8342/5352",
    "sg:postcode":"87616",
    "sg:province":"Bayern",
    "wof:name":"Werner Beggel",
    "wof:placetype":"venue"
},
  "geometry": {"coordinates":[10.6034202576,47.7734947205],"type":"Point"}
}