{
  "type": "Feature",
  "properties": {
    "iso:country":"DE",
    "sg:address":"Hauptstr. 88",
    "sg:city":"Langenburg",
    "sg:phone":"+49 7905/208",
    "sg:postcode":"74595",
    "sg:province":"Baden-W\u00fcrttemberg",
    "wof:name":"Hof-apotheke",
    "wof:placetype":"venue"
},
  "geometry": {"coordinates":[9.852358,49.253563],"type":"Point"}
}