{
  "type": "Feature",
  "properties": {
    "iso:country":"DE",
    "sg:address":"Falderbaumstr. 24",
    "sg:city":"Sankt Augustin",
    "sg:phone":"+49 2241/202583",
    "sg:postcode":"53757",
    "sg:province":"Nordrhein-Westfalen",
    "wof:name":"J\u00fcrgen Tartz Rechtsanwalt",
    "wof:placetype":"venue"
},
  "geometry": {"coordinates":[7.1692900658,50.762550354],"type":"Point"}
}