{
  "type": "Feature",
  "properties": {
    "iso:country":"DE",
    "sg:address":"Raiffeisenstr. 1",
    "sg:city":"Eching",
    "sg:phone":"+49 89/31971828",
    "sg:postcode":"85386",
    "sg:province":"Bayern",
    "wof:name":"A. Zrenner",
    "wof:placetype":"venue"
},
  "geometry": {"coordinates":[11.620786,48.294014],"type":"Point"}
}