{
  "type": "Feature",
  "properties": {
    "iso:country":"DE",
    "sg:address":"Am Busbahnhof 7",
    "sg:city":"Westerr\u00f6nfeld",
    "sg:phone":"+49 4331/8160",
    "sg:postcode":"24784",
    "sg:province":"Schleswig-Holstein",
    "wof:name":"Helmut Wandmaker Gmbh",
    "wof:placetype":"venue"
},
  "geometry": {"coordinates":[9.654665947,54.2770614624],"type":"Point"}
}