{
  "type": "Feature",
  "properties": {
    "iso:country":"DE",
    "sg:address":"Thymianweg 10",
    "sg:city":"Bad Zwischenahn",
    "sg:phone":"+49 4403/4596",
    "sg:postcode":"26160",
    "sg:province":"Niedersachsen",
    "wof:name":"M. Und Veronika Setje-eilers",
    "wof:placetype":"venue"
},
  "geometry": {"coordinates":[8.018181,53.176445],"type":"Point"}
}