{
  "type": "Feature",
  "properties": {
    "iso:country":"DE",
    "sg:address":"Friedenstr. 18",
    "sg:city":"Triefenstein",
    "sg:phone":"+49 9395/97090",
    "sg:postcode":"97855",
    "sg:province":"Bayern",
    "wof:name":"Georg Sch\u00e4fer Transport-beton Gmbh",
    "wof:placetype":"venue"
},
  "geometry": {"coordinates":[9.6159381866,49.7984313965],"type":"Point"}
}