{
  "type": "Feature",
  "properties": {
    "iso:country":"DE",
    "sg:address":"Beethovenstr. 1 a",
    "sg:city":"W\u00fcrzburg",
    "sg:phone":"+49 931/322180",
    "sg:postcode":"97080",
    "sg:province":"Bayern",
    "wof:name":"Capitol Entertainment Gmbh",
    "wof:placetype":"venue"
},
  "geometry": {"coordinates":[9.944577,49.797619],"type":"Point"}
}