{
  "type": "Feature",
  "properties": {
    "iso:country":"DE",
    "sg:address":"Pillauer Str. 9",
    "sg:city":"Bremerhaven",
    "sg:postcode":"27580",
    "sg:province":"Bremen",
    "wof:name":"Gesellschaft F\u00fcr European Hearings E.v.",
    "wof:placetype":"venue"
},
  "geometry": {"coordinates":[8.5744495392,53.5856018066],"type":"Point"}
}