{
  "type": "Feature",
  "properties": {
    "iso:country":"DE",
    "sg:address":"L\u00fcnener Str. 239",
    "sg:city":"Kamen",
    "sg:phone":"+49 2307/17803",
    "sg:postcode":"59174",
    "sg:province":"Nordrhein-Westfalen",
    "wof:name":"Frank Schmidt E. K.",
    "wof:placetype":"venue"
},
  "geometry": {"coordinates":[7.6548490524,51.5919723511],"type":"Point"}
}