{
  "type": "Feature",
  "properties": {
    "iso:country":"DE",
    "sg:address":"Weiherstr. 25",
    "sg:city":"Pforzheim",
    "sg:phone":"+49 7231/24665",
    "sg:postcode":"75173",
    "sg:province":"Baden-W\u00fcrttemberg",
    "wof:name":"Klaus Peiter",
    "wof:placetype":"venue"
},
  "geometry": {"coordinates":[8.695839,48.888767],"type":"Point"}
}