{
  "type": "Feature",
  "properties": {
    "iso:country":"DE",
    "sg:address":"Angerstr. 5",
    "sg:city":"Gutenberg",
    "sg:phone":"+49 34606/20459",
    "sg:postcode":"06193",
    "sg:province":"Sachsen-Anhalt",
    "wof:name":"Kindertagesst\u00e4tte Gutenberg",
    "wof:placetype":"venue"
},
  "geometry": {"coordinates":[11.9753875732,51.5453109741],"type":"Point"}
}