{
  "type": "Feature",
  "properties": {
    "iso:country":"DE",
    "sg:address":"Zollhausstr. 2",
    "sg:city":"Heppenheim",
    "sg:phone":"+49 6252/2527",
    "sg:postcode":"64646",
    "sg:province":"Hessen",
    "wof:name":"Anton Held",
    "wof:placetype":"venue"
},
  "geometry": {"coordinates":[8.643907547,49.6381835938],"type":"Point"}
}