{
  "type": "Feature",
  "properties": {
    "iso:country":"DE",
    "sg:address":"Flamweg 54",
    "sg:city":"Elmshorn",
    "sg:phone":"+49 4121/25524",
    "sg:postcode":"25335",
    "sg:province":"Schleswig-Holstein",
    "wof:name":"Restaurant Hellas",
    "wof:placetype":"venue"
},
  "geometry": {"coordinates":[9.6482944489,53.7555656433],"type":"Point"}
}