{
  "type": "Feature",
  "properties": {
    "iso:country":"DE",
    "sg:address":"Werastr. 27",
    "sg:city":"Geislingen",
    "sg:phone":"+49 7331/60863",
    "sg:postcode":"73312",
    "sg:province":"Baden-W\u00fcrttemberg",
    "wof:name":"Adolf Hibbing",
    "wof:placetype":"venue"
},
  "geometry": {"coordinates":[9.8229837418,48.6225700378],"type":"Point"}
}