{
  "type": "Feature",
  "properties": {
    "iso:country":"DE",
    "sg:address":"Hauptstr. 36",
    "sg:city":"Osterberg",
    "sg:phone":"+49 8333/93676",
    "sg:postcode":"89296",
    "sg:province":"Bayern",
    "wof:name":"Josef Weh",
    "wof:placetype":"venue"
},
  "geometry": {"coordinates":[10.169042,48.144554],"type":"Point"}
}