{
  "type": "Feature",
  "properties": {
    "iso:country":"DE",
    "sg:address":"Bahnhofstr. 11",
    "sg:city":"Scheibenberg",
    "sg:phone":"+49 37349/76602",
    "sg:postcode":"09481",
    "sg:province":"Sachsen",
    "wof:name":"Diamant Natur Gmbh",
    "wof:placetype":"venue"
},
  "geometry": {"coordinates":[12.9112882614,50.5432014465],"type":"Point"}
}