{
  "type": "Feature",
  "properties": {
    "iso:country":"DE",
    "sg:address":"Hardtweg 2",
    "sg:city":"Babenhausen",
    "sg:postcode":"64832",
    "sg:province":"Hessen",
    "wof:name":"Kalksandsteinwerke Baustoffwerke Durmersbach",
    "wof:placetype":"venue"
},
  "geometry": {"coordinates":[8.9446201324,49.9479064941],"type":"Point"}
}