{
  "type": "Feature",
  "properties": {
    "iso:country":"DE",
    "sg:address":"Bornsieksweg 20",
    "sg:city":"Isenb\u00fcttel",
    "sg:phone":"+49 5374/2855",
    "sg:postcode":"38550",
    "sg:province":"Niedersachsen",
    "wof:name":"Bodo M\u00fcller Bau Gmbh",
    "wof:placetype":"venue"
},
  "geometry": {"coordinates":[10.55152,52.442093],"type":"Point"}
}