{
  "type": "Feature",
  "properties": {
    "iso:country":"DE",
    "sg:address":"Meersburgerstr. 4/3",
    "sg:city":"Hagnau",
    "sg:phone":"+49 7532/43130",
    "sg:postcode":"88709",
    "sg:province":"Baden-W\u00fcrttemberg",
    "wof:name":"Villa Am See",
    "wof:placetype":"venue"
},
  "geometry": {"coordinates":[9.272444725,47.6946640015],"type":"Point"}
}