{
  "type": "Feature",
  "properties": {
    "iso:country":"DE",
    "sg:address":"Werner-von-Siemens-Str. 10",
    "sg:city":"G\u00f6ttingen",
    "sg:phone":"+49 551/3898720",
    "sg:postcode":"37077",
    "sg:province":"Niedersachsen",
    "wof:name":"\u00c4hg Handelsgesellschaft F\u00fcr Medizinische Produkte Mbh",
    "wof:placetype":"venue"
},
  "geometry": {"coordinates":[9.9296951294,51.5587310791],"type":"Point"}
}