{
  "type": "Feature",
  "properties": {
    "iso:country":"DE",
    "sg:address":"Enzlesm\u00fchler Weg 10",
    "sg:city":"Leutkirch",
    "sg:phone":"+49 7563/1444",
    "sg:postcode":"88299",
    "sg:province":"Baden-W\u00fcrttemberg",
    "wof:name":"Bernhart Sicherheitstechnik",
    "wof:placetype":"venue"
},
  "geometry": {"coordinates":[9.946409,47.784233],"type":"Point"}
}