{
  "type": "Feature",
  "properties": {
    "iso:country":"DE",
    "sg:address":"Babenh\u00e4user Landstr. 11",
    "sg:city":"Frankfurt",
    "sg:phone":"+49 69/682256",
    "sg:postcode":"60599",
    "sg:province":"Hessen",
    "wof:name":"Friedrich Giersch",
    "wof:placetype":"venue"
},
  "geometry": {"coordinates":[8.69298,50.086578],"type":"Point"}
}