{
  "type": "Feature",
  "properties": {
    "iso:country":"DE",
    "sg:address":"Am Steinacker 20",
    "sg:city":"Grevenbroich",
    "sg:phone":"+49 2181/63600",
    "sg:postcode":"41517",
    "sg:province":"Nordrhein-Westfalen",
    "wof:name":"Helga Bettray Yachenvermittlung",
    "wof:placetype":"venue"
},
  "geometry": {"coordinates":[6.587432,51.067726],"type":"Point"}
}