{
  "type": "Feature",
  "properties": {
    "iso:country":"DE",
    "sg:address":"J\u00fcrgensallee 68 d",
    "sg:city":"Hamburg",
    "sg:phone":"+49 40/828702",
    "sg:postcode":"22609",
    "sg:province":"Hamburg",
    "wof:name":"Albion Handelsgesellschaft Mbh",
    "wof:placetype":"venue"
},
  "geometry": {"coordinates":[9.8606758118,53.557384491],"type":"Point"}
}