{
  "type": "Feature",
  "properties": {
    "iso:country":"DE",
    "sg:address":"Zum Bahnhof 9",
    "sg:city":"Uetze",
    "sg:phone":"+49 5173/1294",
    "sg:postcode":"31311",
    "sg:province":"Niedersachsen",
    "wof:name":"Reinhard Brandes",
    "wof:placetype":"venue"
},
  "geometry": {"coordinates":[10.2301626205,52.4329948425],"type":"Point"}
}