{
  "type": "Feature",
  "properties": {
    "iso:country":"DE",
    "sg:address":"Lipschitzallee 74-76",
    "sg:city":"Berlin",
    "sg:phone":"+49 30/6043178",
    "sg:postcode":"12353",
    "sg:province":"Berlin",
    "wof:name":"Katholisches Pfarramt St. Dominicus",
    "wof:placetype":"venue"
},
  "geometry": {"coordinates":[13.462638855,52.4239730835],"type":"Point"}
}