{
  "type": "Feature",
  "properties": {
    "iso:country":"DE",
    "sg:address":"Soltauer Str. 17",
    "sg:city":"Hanstedt",
    "sg:phone":"+49 4184/385",
    "sg:postcode":"21271",
    "sg:province":"Niedersachsen",
    "wof:name":"Bp Tankstelle",
    "wof:placetype":"venue"
},
  "geometry": {"coordinates":[10.0227489471,53.2558021545],"type":"Point"}
}