{
  "type": "Feature",
  "properties": {
    "iso:country":"DE",
    "sg:address":"Hasenfelder Str. 25",
    "sg:city":"Heimbach",
    "sg:phone":"+49 2446/430",
    "sg:postcode":"52396",
    "sg:province":"Nordrhein-Westfalen",
    "wof:name":"Bertram-flohr",
    "wof:placetype":"venue"
},
  "geometry": {"coordinates":[6.4666771889,50.6361732483],"type":"Point"}
}