{
  "type": "Feature",
  "properties": {
    "iso:country":"DE",
    "sg:address":"Gautschweg 2",
    "sg:city":"Dresden",
    "sg:postcode":"01309",
    "sg:province":"Sachsen",
    "wof:name":"H & H Treuhand Gmbh",
    "wof:placetype":"venue"
},
  "geometry": {"coordinates":[13.8057117462,51.0543556213],"type":"Point"}
}