{
  "type": "Feature",
  "properties": {
    "iso:country":"DE",
    "sg:address":"Gorch-Fock-Str. 28",
    "sg:city":"Timmendorfer Strand",
    "sg:phone":"+49 4503/2546",
    "sg:postcode":"23669",
    "sg:province":"Schleswig-Holstein",
    "wof:name":"Heinrich Nau Verleihbetrieb",
    "wof:placetype":"venue"
},
  "geometry": {"coordinates":[10.7933759689,53.9919586182],"type":"Point"}
}