{
  "type": "Feature",
  "properties": {
    "iso:country":"DE",
    "sg:address":"H\u00f6chstadter Str.",
    "sg:city":"Lonnerstadt",
    "sg:postcode":"91475",
    "sg:province":"Bayern",
    "wof:name":"Saha-sack-handels- Gmbh",
    "wof:placetype":"venue"
},
  "geometry": {"coordinates":[10.76992,49.698067],"type":"Point"}
}