{
  "type": "Feature",
  "properties": {
    "iso:country":"DE",
    "sg:address":"Vidumestr. 21",
    "sg:city":"Hattingen",
    "sg:phone":"+49 2324/33861",
    "sg:postcode":"45527",
    "sg:province":"Nordrhein-Westfalen",
    "wof:name":"Spornhauer",
    "wof:placetype":"venue"
},
  "geometry": {"coordinates":[7.2236480713,51.4062271118],"type":"Point"}
}