{
  "type": "Feature",
  "properties": {
    "iso:country":"DE",
    "sg:address":"St\u00fcmpelstal 10",
    "sg:city":"Marburg",
    "sg:phone":"+49 6420/1010",
    "sg:postcode":"35041",
    "sg:province":"Hessen",
    "wof:name":"H. Hinzmann Architekt",
    "wof:placetype":"venue"
},
  "geometry": {"coordinates":[8.717199,50.843956],"type":"Point"}
}