{
  "type": "Feature",
  "properties": {
    "iso:country":"DE",
    "sg:address":"Spitzweidenweg 28",
    "sg:city":"Jena",
    "sg:phone":"+49 3641/88520",
    "sg:postcode":"07743",
    "sg:province":"Th\u00fcringen",
    "wof:name":"Europcar Autovermietung Gmbh",
    "wof:placetype":"venue"
},
  "geometry": {"coordinates":[11.592357,50.936077],"type":"Point"}
}