{
  "type": "Feature",
  "properties": {
    "iso:country":"DE",
    "sg:address":"Heinrichsweg 8",
    "sg:city":"Nordhausen",
    "sg:phone":"+49 3631/990422",
    "sg:postcode":"99734",
    "sg:province":"Th\u00fcringen",
    "wof:name":"Vermessungsb\u00fcro Manfred Gropp",
    "wof:placetype":"venue"
},
  "geometry": {"coordinates":[10.8056049347,51.5064888],"type":"Point"}
}