{
  "type": "Feature",
  "properties": {
    "iso:country":"DE",
    "sg:address":"W\u00fclfrather Str. 6",
    "sg:city":"Heiligenhaus",
    "sg:phone":"+49 2056/9730",
    "sg:postcode":"42579",
    "sg:province":"Nordrhein-Westfalen",
    "wof:name":"Kini Beteiligungsges. Mbh",
    "wof:placetype":"venue"
},
  "geometry": {"coordinates":[6.975391,51.325729],"type":"Point"}
}