{
  "type": "Feature",
  "properties": {
    "iso:country":"DE",
    "sg:address":"Segelfliegerweg 17",
    "sg:city":"Melle",
    "sg:phone":"+49 5422/3668",
    "sg:postcode":"49324",
    "sg:province":"Niedersachsen",
    "wof:name":"Frank Horst",
    "wof:placetype":"venue"
},
  "geometry": {"coordinates":[8.374130249,52.2114181519],"type":"Point"}
}