{
  "type": "Feature",
  "properties": {
    "iso:country":"DE",
    "sg:address":"Kriegersiedlung 18",
    "sg:city":"Ebersberg",
    "sg:phone":"+49 8092/20429",
    "sg:postcode":"85560",
    "sg:province":"Bayern",
    "wof:name":"Erich Zmarsly Kunstmaler",
    "wof:placetype":"venue"
},
  "geometry": {"coordinates":[11.970149,48.071869],"type":"Point"}
}