{
  "type": "Feature",
  "properties": {
    "iso:country":"DE",
    "sg:address":"Harvestehuder Weg 92",
    "sg:city":"Hamburg",
    "sg:phone":"+49 40/418201",
    "sg:postcode":"20149",
    "sg:province":"Hamburg",
    "wof:name":"G. Ploog Steuerberater",
    "wof:placetype":"venue"
},
  "geometry": {"coordinates":[9.9934530258,53.5799064636],"type":"Point"}
}