{
  "type": "Feature",
  "properties": {
    "iso:country":"DE",
    "sg:address":"Ascherbachweg 24",
    "sg:city":"Dachau",
    "sg:phone":"+49 8131/87256",
    "sg:postcode":"85221",
    "sg:province":"Bayern",
    "wof:name":"B\u00f6ck Verwaltungs Gmbh",
    "wof:placetype":"venue"
},
  "geometry": {"coordinates":[11.425488,48.251595],"type":"Point"}
}