{
  "type": "Feature",
  "properties": {
    "iso:country":"DE",
    "sg:address":"Ennester Weg 9",
    "sg:city":"Attendorn",
    "sg:phone":"+49 2722/610",
    "sg:postcode":"57439",
    "sg:province":"Nordrhein-Westfalen",
    "wof:name":"Viega Beteiligungs Gmbh",
    "wof:placetype":"venue"
},
  "geometry": {"coordinates":[7.902969,51.129021],"type":"Point"}
}