{
  "type": "Feature",
  "properties": {
    "iso:country":"DE",
    "sg:address":"Aachener Str. 370",
    "sg:city":"K\u00f6ln",
    "sg:phone":"+49 221/9541111",
    "sg:postcode":"50933",
    "sg:province":"Nordrhein-Westfalen",
    "wof:name":"Werner B\u00fcscher Und Kollegen Rechtsanw\u00e4lte",
    "wof:placetype":"venue"
},
  "geometry": {"coordinates":[6.9017939568,50.9373435974],"type":"Point"}
}