{
  "type": "Feature",
  "properties": {
    "iso:country":"DE",
    "sg:address":"Hengem\u00fchlweg 205",
    "sg:city":"Rheine",
    "sg:phone":"+49 5971/65136",
    "sg:postcode":"48432",
    "sg:province":"Nordrhein-Westfalen",
    "wof:name":"K & K Feriendorf Hengem\u00fchlen Beteilig. Gmbh",
    "wof:placetype":"venue"
},
  "geometry": {"coordinates":[7.433411,52.308144],"type":"Point"}
}