{
  "type": "Feature",
  "properties": {
    "iso:country":"DE",
    "sg:address":"H\u00fcgelstr. 2",
    "sg:city":"Frankfurt",
    "sg:phone":"+49 69/545495",
    "sg:postcode":"60435",
    "sg:province":"Hessen",
    "wof:name":"Pizzeria La Favola",
    "wof:placetype":"venue"
},
  "geometry": {"coordinates":[8.6758098602,50.1497535706],"type":"Point"}
}