{
  "type": "Feature",
  "properties": {
    "iso:country":"DE",
    "sg:address":"Betonstr. 8",
    "sg:city":"Milmersdorf",
    "sg:phone":"+49 39886/270",
    "sg:postcode":"17268",
    "sg:province":"Brandenburg",
    "wof:name":"Arzneimittel-ausgabestelle",
    "wof:placetype":"venue"
},
  "geometry": {"coordinates":[13.640068,53.109013],"type":"Point"}
}