{
  "type": "Feature",
  "properties": {
    "iso:country":"DE",
    "sg:address":"Buchenstr. 1",
    "sg:city":"Speichersdorf",
    "sg:phone":"+49 9275/6174",
    "sg:postcode":"95469",
    "sg:province":"Bayern",
    "wof:name":"Thomas G\u00fcttler",
    "wof:placetype":"venue"
},
  "geometry": {"coordinates":[11.759256,49.867481],"type":"Point"}
}