{
  "type": "Feature",
  "properties": {
    "iso:country":"DE",
    "sg:address":"Bachstr. 4",
    "sg:city":"Bockenem",
    "sg:phone":"+49 5067/6476",
    "sg:postcode":"31167",
    "sg:province":"Niedersachsen",
    "wof:name":"Martin Wecken",
    "wof:placetype":"venue"
},
  "geometry": {"coordinates":[10.141319,51.977814],"type":"Point"}
}