{
  "type": "Feature",
  "properties": {
    "iso:country":"DE",
    "sg:address":"Stiller Weg 52",
    "sg:city":"Mannheim",
    "sg:phone":"+49 621/762560",
    "sg:postcode":"68305",
    "sg:province":"Baden-W\u00fcrttemberg",
    "wof:name":"G\u00fcnter Butter Anlageberater",
    "wof:placetype":"venue"
},
  "geometry": {"coordinates":[8.5098695755,49.5292816162],"type":"Point"}
}