{
  "type": "Feature",
  "properties": {
    "iso:country":"DE",
    "sg:address":"Birkenweg",
    "sg:city":"Calden",
    "sg:phone":"+49 5609/83880",
    "sg:postcode":"34379",
    "sg:province":"Hessen",
    "wof:name":"F\u00fcrstenwalder Betonsteinwerk",
    "wof:placetype":"venue"
},
  "geometry": {"coordinates":[9.3578300476,51.4044113159],"type":"Point"}
}