{
  "type": "Feature",
  "properties": {
    "iso:country":"DE",
    "sg:address":"Christinestr. 2 a",
    "sg:city":"Oberhausen",
    "sg:phone":"+49 208/663883",
    "sg:postcode":"46145",
    "sg:province":"Nordrhein-Westfalen",
    "wof:name":"S. Basaran",
    "wof:placetype":"venue"
},
  "geometry": {"coordinates":[6.8460049629,51.5144500732],"type":"Point"}
}