{
  "type": "Feature",
  "properties": {
    "iso:country":"DE",
    "sg:address":"An der Christ-K\u00f6nig-Kirche 4",
    "sg:city":"Saarbr\u00fccken",
    "sg:phone":"+49 681/57098",
    "sg:postcode":"66119",
    "sg:province":"Saarland",
    "wof:name":"Hermann Luckas Notar",
    "wof:placetype":"venue"
},
  "geometry": {"coordinates":[7.0012440681,49.2248802185],"type":"Point"}
}