{
  "type": "Feature",
  "properties": {
    "iso:country":"DE",
    "sg:address":"Trauttmansdorffstr. 65",
    "sg:city":"M\u00fcnster",
    "sg:phone":"+49 251/785009",
    "sg:postcode":"48153",
    "sg:province":"Nordrhein-Westfalen",
    "wof:name":"Newels Garten-center Kg",
    "wof:placetype":"venue"
},
  "geometry": {"coordinates":[7.637469,51.925636],"type":"Point"}
}