{
  "type": "Feature",
  "properties": {
    "iso:country":"DE",
    "sg:address":"Bahnhofplatz 7",
    "sg:city":"Konstanz",
    "sg:phone":"+49 7531/24662",
    "sg:postcode":"78462",
    "sg:province":"Baden-W\u00fcrttemberg",
    "wof:name":"B\u00fcrgerstuben",
    "wof:placetype":"venue"
},
  "geometry": {"coordinates":[9.1772155762,47.6596107483],"type":"Point"}
}