{
  "type": "Feature",
  "properties": {
    "iso:country":"DE",
    "sg:address":"Dorfstr. 25",
    "sg:city":"Michelfeld",
    "sg:phone":"+49 791/72572",
    "sg:postcode":"74545",
    "sg:province":"Baden-W\u00fcrttemberg",
    "wof:name":"Wilfried Lenz",
    "wof:placetype":"venue"
},
  "geometry": {"coordinates":[9.654703,49.128082],"type":"Point"}
}