{
  "type": "Feature",
  "properties": {
    "iso:country":"DE",
    "sg:address":"Albert-Ro\u00dfhaupter-Str. 37",
    "sg:city":"M\u00fcnchen",
    "sg:phone":"+49 89/74379966",
    "sg:postcode":"81369",
    "sg:province":"Bayern",
    "wof:name":"Boarders Sportsproducts Gmbh",
    "wof:placetype":"venue"
},
  "geometry": {"coordinates":[11.5322618484,48.1166496277],"type":"Point"}
}