{
  "type": "Feature",
  "properties": {
    "iso:country":"DE",
    "sg:address":"Oststr. 2",
    "sg:city":"Finnentrop",
    "sg:phone":"+49 2724/8584",
    "sg:postcode":"57413",
    "sg:province":"Nordrhein-Westfalen",
    "wof:name":"Gastst\u00e4tte Ruiener Dorftreff",
    "wof:placetype":"venue"
},
  "geometry": {"coordinates":[7.9655079842,51.1738243103],"type":"Point"}
}