{
  "type": "Feature",
  "properties": {
    "iso:country":"DE",
    "sg:address":"Steinbergstr. 4",
    "sg:city":"Fuldatal",
    "sg:phone":"+49 561/8150937",
    "sg:postcode":"34233",
    "sg:province":"Hessen",
    "wof:name":"H. J. Und K. Strippel",
    "wof:placetype":"venue"
},
  "geometry": {"coordinates":[9.5165929794,51.3668899536],"type":"Point"}
}