{
  "type": "Feature",
  "properties": {
    "iso:country":"DE",
    "sg:address":"Auf dem Brook 13-16",
    "sg:city":"Parchim",
    "sg:postcode":"19370",
    "sg:province":"Mecklenburg-Vorpommern",
    "wof:name":"Wobau Wohnungsbau G.m.b.h. Parchim",
    "wof:placetype":"venue"
},
  "geometry": {"coordinates":[11.8406391144,53.4297561646],"type":"Point"}
}