{
  "type": "Feature",
  "properties": {
    "iso:country":"DE",
    "sg:address":"Hohenzollernstr. 83",
    "sg:city":"Weil der Stadt",
    "sg:phone":"+49 7033/44855",
    "sg:postcode":"71263",
    "sg:province":"Baden-W\u00fcrttemberg",
    "wof:name":"Thomas Farnung",
    "wof:placetype":"venue"
},
  "geometry": {"coordinates":[8.898652,48.727669],"type":"Point"}
}