{
  "type": "Feature",
  "properties": {
    "iso:country":"DE",
    "sg:address":"Zwolle-Allee 5",
    "sg:city":"L\u00fcnen",
    "sg:phone":"+49 2306/71971",
    "sg:postcode":"44534",
    "sg:province":"Nordrhein-Westfalen",
    "wof:name":"Tennishalle Center Court",
    "wof:placetype":"venue"
},
  "geometry": {"coordinates":[7.5435199738,51.6205825806],"type":"Point"}
}