{
  "type": "Feature",
  "properties": {
    "iso:country":"DE",
    "sg:address":"Bergstr. 14",
    "sg:city":"Jameln",
    "sg:phone":"+49 5864/655",
    "sg:postcode":"29479",
    "sg:province":"Niedersachsen",
    "wof:name":"Helmut Behning Apothekeninventuren E. Kfm.",
    "wof:placetype":"venue"
},
  "geometry": {"coordinates":[11.076118,53.041813],"type":"Point"}
}