{
  "type": "Feature",
  "properties": {
    "iso:country":"DE",
    "sg:address":"Feldm\u00fchlenweg 17",
    "sg:city":"Soest",
    "sg:phone":"+49 2921/371250",
    "sg:postcode":"59494",
    "sg:province":"Nordrhein-Westfalen",
    "wof:name":"Altenheim Lina Oberb\u00e4umer Haus",
    "wof:placetype":"venue"
},
  "geometry": {"coordinates":[8.09627,51.57555],"type":"Point"}
}