{
  "type": "Feature",
  "properties": {
    "iso:country":"DE",
    "sg:address":"Redder 50",
    "sg:city":"Mustin",
    "sg:postcode":"23911",
    "sg:province":"Schleswig-Holstein",
    "wof:name":"Pieske-vertriebs Gmbh & Co.",
    "wof:placetype":"venue"
},
  "geometry": {"coordinates":[10.8820962906,53.6823196411],"type":"Point"}
}