{
  "type": "Feature",
  "properties": {
    "iso:country":"DE",
    "sg:address":"Fischbacher Str. 10",
    "sg:city":"Feucht",
    "sg:phone":"+49 9128/4113",
    "sg:postcode":"90537",
    "sg:province":"Bayern",
    "wof:name":"Verein Dritte-welt Gruppe E. V.",
    "wof:placetype":"venue"
},
  "geometry": {"coordinates":[11.2128267288,49.3779182434],"type":"Point"}
}