{
  "type": "Feature",
  "properties": {
    "iso:country":"DE",
    "sg:address":"Oberer Zollweg 7",
    "sg:city":"Bad Kissingen",
    "sg:phone":"+49 971/4158",
    "sg:postcode":"97688",
    "sg:province":"Bayern",
    "wof:name":"Martin Borst",
    "wof:placetype":"venue"
},
  "geometry": {"coordinates":[10.085805,50.172653],"type":"Point"}
}