{
  "type": "Feature",
  "properties": {
    "iso:country":"DE",
    "sg:address":"Finkenstr. 64",
    "sg:city":"Buxtehude",
    "sg:phone":"+49 4161/86466",
    "sg:postcode":"21614",
    "sg:province":"Niedersachsen",
    "wof:name":"Eigenheimbau Gmbh & Co. Kg",
    "wof:placetype":"venue"
},
  "geometry": {"coordinates":[9.6684484482,53.4637794495],"type":"Point"}
}