{
  "type": "Feature",
  "properties": {
    "iso:country":"DE",
    "sg:address":"Zur Burg 9",
    "sg:city":"Hofheim",
    "sg:phone":"+49 6122/16669",
    "sg:postcode":"65719",
    "sg:province":"Hessen",
    "wof:name":"Gerry U. Mario Leonardic",
    "wof:placetype":"venue"
},
  "geometry": {"coordinates":[8.3737630844,50.0622711182],"type":"Point"}
}