{
  "type": "Feature",
  "properties": {
    "iso:country":"DE",
    "sg:address":"Adenauerallee 266-268",
    "sg:city":"Bonn",
    "sg:postcode":"53113",
    "sg:province":"Nordrhein-Westfalen",
    "wof:name":"Pr-berlin Public Relations- Ges. F\u00fcr Kommunikations- Und",
    "wof:placetype":"venue"
},
  "geometry": {"coordinates":[7.11657,50.71941],"type":"Point"}
}