{
  "type": "Feature",
  "properties": {
    "iso:country":"DE",
    "sg:address":"Herrnstr. 5",
    "sg:city":"Hanau",
    "sg:phone":"+49 6181/23359",
    "sg:postcode":"63450",
    "sg:province":"Hessen",
    "wof:name":"Domino Electronic-spiele Gmbh",
    "wof:placetype":"venue"
},
  "geometry": {"coordinates":[8.9121551514,50.1331062317],"type":"Point"}
}