{
  "type": "Feature",
  "properties": {
    "iso:country":"DE",
    "sg:address":"Neefestr. 2a",
    "sg:city":"Bonn",
    "sg:phone":"+49 228/725990",
    "sg:postcode":"53115",
    "sg:province":"Nordrhein-Westfalen",
    "wof:name":"Verlag Deutsches Volksheimst\u00e4ttenwerk Gmbh",
    "wof:placetype":"venue"
},
  "geometry": {"coordinates":[7.0938520432,50.7285957336],"type":"Point"}
}