{
  "type": "Feature",
  "properties": {
    "iso:country":"DE",
    "sg:address":"Herrenstr. 33",
    "sg:city":"Kraichtal",
    "sg:phone":"+49 7251/6536",
    "sg:postcode":"76703",
    "sg:province":"Baden-W\u00fcrttemberg",
    "wof:name":"R. Kratz",
    "wof:placetype":"venue"
},
  "geometry": {"coordinates":[8.6693716049,49.1439819336],"type":"Point"}
}