{
  "type": "Feature",
  "properties": {
    "iso:country":"DE",
    "sg:address":"Hollager Str. 121",
    "sg:city":"Wallenhorst",
    "sg:phone":"+49 5407/5576",
    "sg:postcode":"49134",
    "sg:province":"Niedersachsen",
    "wof:name":"Gasthaus Barlag",
    "wof:placetype":"venue"
},
  "geometry": {"coordinates":[7.9914431572,52.3480148315],"type":"Point"}
}