{
  "type": "Feature",
  "properties": {
    "iso:country":"DE",
    "sg:address":"Burgstr. 23",
    "sg:city":"Zorneding",
    "sg:phone":"+49 8106/22985",
    "sg:postcode":"85604",
    "sg:province":"Bayern",
    "wof:name":"Josef Mairsamer",
    "wof:placetype":"venue"
},
  "geometry": {"coordinates":[11.8333415985,48.0951271057],"type":"Point"}
}