{
  "type": "Feature",
  "properties": {
    "iso:country":"DE",
    "sg:address":"Sauerstaden 6 a",
    "sg:city":"Bollendorf",
    "sg:phone":"+49 6526/1368",
    "sg:postcode":"54669",
    "sg:province":"Rheinland-Pfalz",
    "wof:name":"Peter Helbach",
    "wof:placetype":"venue"
},
  "geometry": {"coordinates":[6.362610817,49.851524353],"type":"Point"}
}