{
  "type": "Feature",
  "properties": {
    "iso:country":"DE",
    "sg:address":"Clayallee 355",
    "sg:city":"Berlin",
    "sg:phone":"+49 30/8022441",
    "sg:postcode":"14169",
    "sg:province":"Berlin",
    "wof:name":"Heimatmuseum Zehlendorf",
    "wof:placetype":"venue"
},
  "geometry": {"coordinates":[13.2602987289,52.4353866577],"type":"Point"}
}