{
  "type": "Feature",
  "properties": {
    "iso:country":"DE",
    "sg:address":"Nieder-Ramst\u00e4dter Str. 63",
    "sg:city":"Darmstadt",
    "sg:phone":"+49 6151/47363",
    "sg:postcode":"64287",
    "sg:province":"Hessen",
    "wof:name":"M\u00f6ser-lederwaren",
    "wof:placetype":"venue"
},
  "geometry": {"coordinates":[8.662948,49.868145],"type":"Point"}
}