{
  "type": "Feature",
  "properties": {
    "iso:country":"DE",
    "sg:address":"Berner Heerweg 188",
    "sg:city":"Hamburg",
    "sg:postcode":"22159",
    "sg:province":"Hamburg",
    "wof:name":"B\u00fcrgerverein Oldenfelde Hamburg-rahlstedt E. V.",
    "wof:placetype":"venue"
},
  "geometry": {"coordinates":[10.1209259033,53.6075363159],"type":"Point"}
}