{
  "type": "Feature",
  "properties": {
    "iso:country":"DE",
    "sg:address":"Billstr. 30 a",
    "sg:city":"Hamburg",
    "sg:phone":"+49 40/78070024",
    "sg:postcode":"20539",
    "sg:province":"Hamburg",
    "wof:name":"Schiewers Automaten- Handelsgesellschaft Mbh",
    "wof:placetype":"venue"
},
  "geometry": {"coordinates":[10.034578,53.541336],"type":"Point"}
}