{
  "type": "Feature",
  "properties": {
    "iso:country":"DE",
    "sg:address":"Jahnstr. 3",
    "sg:city":"Edesheim",
    "sg:phone":"+49 6323/2350",
    "sg:postcode":"67483",
    "sg:province":"Rheinland-Pfalz",
    "wof:name":"Agria Und As-motor",
    "wof:placetype":"venue"
},
  "geometry": {"coordinates":[8.139335,49.263863],"type":"Point"}
}