{
  "type": "Feature",
  "properties": {
    "iso:country":"DE",
    "sg:address":"Amtsseite-Dorfstr. 109",
    "sg:city":"Pobershau",
    "sg:postcode":"09496",
    "sg:province":"Sachsen",
    "wof:name":"Steffen Krau\u00df Ingenieurb\u00fcro F\u00fcr Mess- Und Regeltechnik",
    "wof:placetype":"venue"
},
  "geometry": {"coordinates":[13.208711,50.629471],"type":"Point"}
}