{
  "type": "Feature",
  "properties": {
    "iso:country":"DE",
    "sg:address":"Eschenstrasse 14",
    "sg:city":"Duisburg",
    "sg:postcode":"47055",
    "sg:province":"Nordrhein-Westfalen",
    "wof:name":"Freie Evangelische Gemeinde Duisburg Wanheimerort",
    "wof:placetype":"venue"
},
  "geometry": {"coordinates":[6.754575,51.405846],"type":"Point"}
}