{
  "type": "Feature",
  "properties": {
    "iso:country":"DE",
    "sg:address":"Mariah\u00fctte",
    "sg:city":"Nonnweiler",
    "sg:phone":"+49 6873/701",
    "sg:postcode":"66620",
    "sg:province":"Saarland",
    "wof:name":"Goma Gmbh",
    "wof:placetype":"venue"
},
  "geometry": {"coordinates":[6.9789228439,49.5902786255],"type":"Point"}
}