{
  "type": "Feature",
  "properties": {
    "iso:country":"DE",
    "sg:address":"Benstaben 20",
    "sg:city":"Barnitz",
    "sg:phone":"+49 4533/1489",
    "sg:postcode":"23858",
    "sg:province":"Schleswig-Holstein",
    "wof:name":"Karl-heinz Maack",
    "wof:placetype":"venue"
},
  "geometry": {"coordinates":[10.459836,53.813427],"type":"Point"}
}