{
  "type": "Feature",
  "properties": {
    "iso:country":"DE",
    "sg:address":"Ihringsh\u00e4userstr. 11",
    "sg:city":"Kassel",
    "sg:phone":"+49 561/875276",
    "sg:postcode":"34125",
    "sg:province":"Hessen",
    "wof:name":"Kleintransporte, Eil- Und Kuriedienste Albert Gbr",
    "wof:placetype":"venue"
},
  "geometry": {"coordinates":[9.512912,51.326382],"type":"Point"}
}