{
  "type": "Feature",
  "properties": {
    "iso:country":"DE",
    "sg:address":"Unterdorf 1",
    "sg:city":"M\u00f6ttingen",
    "sg:phone":"+49 9083/211",
    "sg:postcode":"86753",
    "sg:province":"Bayern",
    "wof:name":"Friedrich En\u00dflin",
    "wof:placetype":"venue"
},
  "geometry": {"coordinates":[10.60672,48.787209],"type":"Point"}
}