{
  "type": "Feature",
  "properties": {
    "iso:country":"DE",
    "sg:address":"Bahnhofstr. 5",
    "sg:city":"Eschenbach",
    "sg:phone":"+49 9645/92070",
    "sg:postcode":"92676",
    "sg:province":"Bayern",
    "wof:name":"Engelbert Meier",
    "wof:placetype":"venue"
},
  "geometry": {"coordinates":[10.6700963974,49.4839553833],"type":"Point"}
}