{
  "type": "Feature",
  "properties": {
    "iso:country":"DE",
    "sg:address":"Plinganserstr. 20",
    "sg:city":"Simbach",
    "sg:phone":"+49 8571/1335",
    "sg:postcode":"84359",
    "sg:province":"Bayern",
    "wof:name":"B. H\u00f6ller",
    "wof:placetype":"venue"
},
  "geometry": {"coordinates":[13.0191612244,48.2672348022],"type":"Point"}
}