{
  "type": "Feature",
  "properties": {
    "iso:country":"DE",
    "sg:address":"Am Bahnhof 7",
    "sg:city":"Gleichen",
    "sg:postcode":"37130",
    "sg:province":"Niedersachsen",
    "wof:name":"Erzeugergemeinschaft F\u00fcr Qualit\u00e4tsgetreide Garnetal Eg",
    "wof:placetype":"venue"
},
  "geometry": {"coordinates":[10.094667,51.482647],"type":"Point"}
}