{
  "type": "Feature",
  "properties": {
    "iso:country":"DE",
    "sg:address":"Christoph-Allee 23-25",
    "sg:city":"Pforzheim",
    "sg:phone":"+49 7231/358424",
    "sg:postcode":"75180",
    "sg:province":"Baden-W\u00fcrttemberg",
    "wof:name":"Dresdner Bank",
    "wof:placetype":"venue"
},
  "geometry": {"coordinates":[8.706479,48.896782],"type":"Point"}
}