{
  "type": "Feature",
  "properties": {
    "iso:country":"DE",
    "sg:address":"Lerchenneststr. 1",
    "sg:city":"Sinsheim",
    "sg:phone":"+49 7261/5448",
    "sg:postcode":"74889",
    "sg:province":"Baden-W\u00fcrttemberg",
    "wof:name":"Krone",
    "wof:placetype":"venue"
},
  "geometry": {"coordinates":[8.9122400284,49.2385482788],"type":"Point"}
}