{
  "type": "Feature",
  "properties": {
    "iso:country":"DE",
    "sg:address":"Hauptstr. 24",
    "sg:city":"Pferdsdorf",
    "sg:postcode":"36414",
    "sg:province":"Th\u00fcringen",
    "wof:name":"E. Sch\u00f6\u00dfler",
    "wof:placetype":"venue"
},
  "geometry": {"coordinates":[10.2191295624,51.0224914551],"type":"Point"}
}