{
  "type": "Feature",
  "properties": {
    "iso:country":"DE",
    "sg:address":"Ammerseestr. 6",
    "sg:city":"Neuried",
    "sg:phone":"+49 89/7459001",
    "sg:postcode":"82061",
    "sg:province":"Bayern",
    "wof:name":"Rent Wash Wienholt Und Steer Gmbh",
    "wof:placetype":"venue"
},
  "geometry": {"coordinates":[11.471516,48.091679],"type":"Point"}
}