{
  "type": "Feature",
  "properties": {
    "iso:country":"DE",
    "sg:address":"Hauptstr. 7",
    "sg:city":"Bad Wildungen",
    "sg:phone":"+49 5621/94732",
    "sg:postcode":"34537",
    "sg:province":"Hessen",
    "wof:name":"Cafe Pinoccio",
    "wof:placetype":"venue"
},
  "geometry": {"coordinates":[9.07687,51.11203],"type":"Point"}
}