{
  "type": "Feature",
  "properties": {
    "iso:country":"DE",
    "sg:address":"Im Troppel 92",
    "sg:city":"Weil im Sch\u00f6nbuch",
    "sg:phone":"+49 7157/66387",
    "sg:postcode":"71093",
    "sg:province":"Baden-W\u00fcrttemberg",
    "wof:name":"Gasthaus Troppelstube",
    "wof:placetype":"venue"
},
  "geometry": {"coordinates":[9.0314025879,48.6171226501],"type":"Point"}
}