{
  "type": "Feature",
  "properties": {
    "iso:country":"DE",
    "sg:address":"Vornholzstr. 19",
    "sg:city":"Passau",
    "sg:phone":"+49 851/6417",
    "sg:postcode":"94036",
    "sg:province":"Bayern",
    "wof:name":"Hans Hatz",
    "wof:placetype":"venue"
},
  "geometry": {"coordinates":[13.4164266586,48.5696640015],"type":"Point"}
}