{
  "type": "Feature",
  "properties": {
    "iso:country":"DE",
    "sg:address":"Hermann-Blenk-Str. 18",
    "sg:city":"Braunschweig",
    "sg:phone":"+49 531/354466",
    "sg:postcode":"38108",
    "sg:province":"Niedersachsen",
    "wof:name":"Ingenieurb\u00fcro Kuhn Und Partner Diplom-ingenieure",
    "wof:placetype":"venue"
},
  "geometry": {"coordinates":[10.5523147583,52.3139724731],"type":"Point"}
}