{
  "type": "Feature",
  "properties": {
    "iso:country":"DE",
    "sg:address":"Hahnenstr. 45",
    "sg:city":"K\u00f6ln",
    "sg:phone":"+49 221/2190320",
    "sg:postcode":"50667",
    "sg:province":"Nordrhein-Westfalen",
    "wof:name":"Innocasa M\u00f6bel Und Accessoires Gmbh",
    "wof:placetype":"venue"
},
  "geometry": {"coordinates":[6.9461197853,50.9356651306],"type":"Point"}
}