{
  "type": "Feature",
  "properties": {
    "iso:country":"DE",
    "sg:address":"Adalmundstr. 2",
    "sg:city":"Dortmund",
    "sg:phone":"+49 231/333773",
    "sg:postcode":"44359",
    "sg:province":"Nordrhein-Westfalen",
    "wof:name":"Maria Mevenkamp",
    "wof:placetype":"venue"
},
  "geometry": {"coordinates":[7.3820791245,51.5723075867],"type":"Point"}
}