{
  "type": "Feature",
  "properties": {
    "iso:country":"DE",
    "sg:address":"Rosenbergstr. 87",
    "sg:city":"Stuttgart",
    "sg:postcode":"70193",
    "sg:province":"Baden-W\u00fcrttemberg",
    "wof:name":"Airship Technologies Gmbh",
    "wof:placetype":"venue"
},
  "geometry": {"coordinates":[9.1545553207,48.7779121399],"type":"Point"}
}