{
  "type": "Feature",
  "properties": {
    "iso:country":"DE",
    "sg:address":"Nachtigallenstr. 38",
    "sg:city":"Neu-Isenburg",
    "sg:phone":"+49 6102/51191",
    "sg:postcode":"63263",
    "sg:province":"Hessen",
    "wof:name":"Topolino Media Agentur E. K.",
    "wof:placetype":"venue"
},
  "geometry": {"coordinates":[8.7531633377,50.0557594299],"type":"Point"}
}