{
  "type": "Feature",
  "properties": {
    "iso:country":"DE",
    "sg:address":"Dahlener Str. 3",
    "sg:city":"Torgau",
    "sg:phone":"+49 3421/712851",
    "sg:postcode":"04860",
    "sg:province":"Sachsen",
    "wof:name":"Aral Tankstelle",
    "wof:placetype":"venue"
},
  "geometry": {"coordinates":[13.0010023117,51.5551643372],"type":"Point"}
}