{
  "type": "Feature",
  "properties": {
    "iso:country":"DE",
    "sg:address":"Neuenlander Str. 111",
    "sg:city":"Bremen",
    "sg:phone":"+49 421/55940",
    "sg:postcode":"28201",
    "sg:province":"Bremen",
    "wof:name":"Metro",
    "wof:placetype":"venue"
},
  "geometry": {"coordinates":[8.8067502975,53.0518836975],"type":"Point"}
}