{
  "type": "Feature",
  "properties": {
    "iso:country":"DE",
    "sg:address":"Kamperbach 40",
    "sg:city":"Witten",
    "sg:phone":"+49 2302/277400",
    "sg:postcode":"58456",
    "sg:province":"Nordrhein-Westfalen",
    "wof:name":"R. Bruse",
    "wof:placetype":"venue"
},
  "geometry": {"coordinates":[7.2780528069,51.4062957764],"type":"Point"}
}