{
  "type": "Feature",
  "properties": {
    "iso:country":"DE",
    "sg:address":"Weher K\u00f6ppel 7",
    "sg:city":"Wiesbaden",
    "sg:phone":"+49 611/461003",
    "sg:postcode":"65199",
    "sg:province":"Hessen",
    "wof:name":"Dieter Elsenbast Rechtsanwalt",
    "wof:placetype":"venue"
},
  "geometry": {"coordinates":[8.1893901825,50.0891494751],"type":"Point"}
}