{
  "type": "Feature",
  "properties": {
    "iso:country":"DE",
    "sg:address":"Joliot-Curie-Allee 48",
    "sg:city":"Rostock",
    "sg:phone":"+49 381/690278",
    "sg:postcode":"18147",
    "sg:province":"Mecklenburg-Vorpommern",
    "wof:name":"Charly S Bowling-bar",
    "wof:placetype":"venue"
},
  "geometry": {"coordinates":[12.137291,54.112278],"type":"Point"}
}