{
  "type": "Feature",
  "properties": {
    "iso:country":"DE",
    "sg:address":"Gernotstr. 19",
    "sg:city":"Dortmund",
    "sg:phone":"+49 4923/192410",
    "sg:postcode":"44319",
    "sg:province":"Nordrhein-Westfalen",
    "wof:name":"Winter Gmbh",
    "wof:placetype":"venue"
},
  "geometry": {"coordinates":[7.6235132217,51.5308876038],"type":"Point"}
}