{
  "type": "Feature",
  "properties": {
    "iso:country":"DE",
    "sg:address":"Ansgaristr. 17",
    "sg:city":"Hage",
    "sg:phone":"+49 4931/74919",
    "sg:postcode":"26524",
    "sg:province":"Niedersachsen",
    "wof:name":"W. Freese Immobilienmakler",
    "wof:placetype":"venue"
},
  "geometry": {"coordinates":[7.2876701355,53.596118927],"type":"Point"}
}