{
  "type": "Feature",
  "properties": {
    "iso:country":"DE",
    "sg:address":"Alt-Vynscher-Weg 40",
    "sg:city":"Xanten",
    "sg:phone":"+49 2804/593",
    "sg:postcode":"46509",
    "sg:province":"Nordrhein-Westfalen",
    "wof:name":"Heinrich H\u00f6rsting",
    "wof:placetype":"venue"
},
  "geometry": {"coordinates":[6.41693,51.69939],"type":"Point"}
}