{
  "type": "Feature",
  "properties": {
    "iso:country":"DE",
    "sg:address":"Berliner Str. 1",
    "sg:city":"Zossen",
    "sg:postcode":"15806",
    "sg:province":"Brandenburg",
    "wof:name":"Kinderbibliothek",
    "wof:placetype":"venue"
},
  "geometry": {"coordinates":[13.474238,52.163502],"type":"Point"}
}