{
  "type": "Feature",
  "properties": {
    "iso:country":"DE",
    "sg:address":"Fasanenstr 68",
    "sg:city":"Unterhaching",
    "sg:phone":"+49 89/6655940",
    "sg:postcode":"82008",
    "sg:province":"Bayern",
    "wof:name":"Cosinus Computermesstechnik Gmbh",
    "wof:placetype":"venue"
},
  "geometry": {"coordinates":[11.609246,48.075043],"type":"Point"}
}