{
  "type": "Feature",
  "properties": {
    "iso:country":"DE",
    "sg:address":"Vorberg 46",
    "sg:city":"Schwanewede",
    "sg:phone":"+49 4209/5758",
    "sg:postcode":"28790",
    "sg:province":"Niedersachsen",
    "wof:name":"Bbv-immobilien B\u00e4rbel Behling",
    "wof:placetype":"venue"
},
  "geometry": {"coordinates":[8.5938997269,53.2500610352],"type":"Point"}
}