{
  "type": "Feature",
  "properties": {
    "iso:country":"DE",
    "sg:address":"Douglasstr. 18",
    "sg:city":"Berlin",
    "sg:postcode":"14193",
    "sg:province":"Berlin",
    "wof:name":"R-con Zehnte Verm\u00f6gensverwaltungs Ag",
    "wof:placetype":"venue"
},
  "geometry": {"coordinates":[13.26122,52.484612],"type":"Point"}
}