{
  "type": "Feature",
  "properties": {
    "iso:country":"DE",
    "sg:address":"Kirchweg 11",
    "sg:city":"Vienenburg",
    "sg:phone":"+49 5324/2277",
    "sg:postcode":"38690",
    "sg:province":"Niedersachsen",
    "wof:name":"W. Brodhage Ohg",
    "wof:placetype":"venue"
},
  "geometry": {"coordinates":[10.5564050674,51.9517440796],"type":"Point"}
}