{
  "type": "Feature",
  "properties": {
    "iso:country":"DE",
    "sg:address":"Bahnhofstr. 1 a",
    "sg:city":"K\u00f6nigswinter",
    "sg:phone":"+49 2223/26687",
    "sg:postcode":"53639",
    "sg:province":"Nordrhein-Westfalen",
    "wof:name":"Bistro-imbiss",
    "wof:placetype":"venue"
},
  "geometry": {"coordinates":[7.1916871071,50.6771011353],"type":"Point"}
}