{
  "type": "Feature",
  "properties": {
    "iso:country":"DE",
    "sg:address":"Oberstr. 9",
    "sg:city":"Sch\u00f6neberg",
    "sg:postcode":"55444",
    "sg:province":"Rheinland-Pfalz",
    "wof:name":"Wema Elektro- Und Automati- Sationsanlagen Gmbh",
    "wof:placetype":"venue"
},
  "geometry": {"coordinates":[7.7506661415,49.9222145081],"type":"Point"}
}