{
  "type": "Feature",
  "properties": {
    "iso:country":"DE",
    "sg:address":"Dr.-Ehlen-Str. 54 a",
    "sg:city":"Schwabach",
    "sg:phone":"+49 9122/75050",
    "sg:postcode":"91126",
    "sg:province":"Bayern",
    "wof:name":"P. Sommer Sachverst\u00e4ndiger",
    "wof:placetype":"venue"
},
  "geometry": {"coordinates":[11.0624237061,49.325378418],"type":"Point"}
}