{
  "type": "Feature",
  "properties": {
    "iso:country":"DE",
    "sg:address":"Gl\u00fcckaufstr. 1",
    "sg:city":"Sarstedt",
    "sg:phone":"+49 4950/6670090",
    "sg:postcode":"31157",
    "sg:province":"Niedersachsen",
    "wof:name":"Selecta Deutschland Gmbh",
    "wof:placetype":"venue"
},
  "geometry": {"coordinates":[9.847261,52.229713],"type":"Point"}
}