{
  "type": "Feature",
  "properties": {
    "iso:country":"DE",
    "sg:address":"R\u00f6merstr. 47",
    "sg:city":"Obernburg",
    "sg:phone":"+49 6022/509490",
    "sg:postcode":"63785",
    "sg:province":"Bayern",
    "wof:name":"Petra M\u00e4rl\u00e4nder Rechtsanw\u00e4ltin",
    "wof:placetype":"venue"
},
  "geometry": {"coordinates":[9.1443548203,49.839641571],"type":"Point"}
}