{
  "type": "Feature",
  "properties": {
    "iso:country":"DE",
    "sg:address":"Paul-Junius-Str. 53",
    "sg:city":"Berlin",
    "sg:phone":"+49 30/9755750",
    "sg:postcode":"10369",
    "sg:province":"Berlin",
    "wof:name":"Horst Riepert Rechtsanwalt",
    "wof:placetype":"venue"
},
  "geometry": {"coordinates":[13.4748182297,52.5268058777],"type":"Point"}
}