{
  "type": "Feature",
  "properties": {
    "iso:country":"DE",
    "sg:address":"Neust\u00e4dter Str. 3",
    "sg:city":"L\u00fctzelbach",
    "sg:phone":"+49 6165/801",
    "sg:postcode":"64750",
    "sg:province":"Hessen",
    "wof:name":"Altenpflegeheim L\u00fctzelbach Betriebsgesellschaft Mbh",
    "wof:placetype":"venue"
},
  "geometry": {"coordinates":[9.071356,49.784317],"type":"Point"}
}