{
  "type": "Feature",
  "properties": {
    "iso:country":"DE",
    "sg:address":"Bertha-von-Suttner-Weg 10",
    "sg:city":"Kaltenkirchen",
    "sg:postcode":"24568",
    "sg:province":"Schleswig-Holstein",
    "wof:name":"G\u00fcnter Wunner Immobilienmakler",
    "wof:placetype":"venue"
},
  "geometry": {"coordinates":[9.961894989,53.842010498],"type":"Point"}
}