{
  "type": "Feature",
  "properties": {
    "iso:country":"DE",
    "sg:address":"Heidelberger Str. 26",
    "sg:city":"Mosbach",
    "sg:phone":"+49 6261/64740",
    "sg:postcode":"74821",
    "sg:province":"Baden-W\u00fcrttemberg",
    "wof:name":"Sinner Optik Gmbh",
    "wof:placetype":"venue"
},
  "geometry": {"coordinates":[9.105594,49.34306],"type":"Point"}
}