{
  "type": "Feature",
  "properties": {
    "iso:country":"DE",
    "sg:address":"Karlsbach 19",
    "sg:city":"Waldkirchen",
    "sg:postcode":"94065",
    "sg:province":"Bayern",
    "wof:name":"Johann G\u00f6ttl Gmbh",
    "wof:placetype":"venue"
},
  "geometry": {"coordinates":[13.5759954453,48.7691116333],"type":"Point"}
}