{
  "type": "Feature",
  "properties": {
    "iso:country":"DE",
    "sg:address":"Hurststr. 33",
    "sg:city":"Rheinm\u00fcnster",
    "sg:phone":"+49 7227/2490",
    "sg:postcode":"77836",
    "sg:province":"Baden-W\u00fcrttemberg",
    "wof:name":"Bruno G\u00f6tz",
    "wof:placetype":"venue"
},
  "geometry": {"coordinates":[8.0515651703,48.7468452454],"type":"Point"}
}