{
  "type": "Feature",
  "properties": {
    "iso:country":"DE",
    "sg:address":"Wehlingweg 14",
    "sg:city":"Weinheim",
    "sg:phone":"+49 6201/22906",
    "sg:postcode":"69469",
    "sg:province":"Baden-W\u00fcrttemberg",
    "wof:name":"Gerald Heckmann Architekt",
    "wof:placetype":"venue"
},
  "geometry": {"coordinates":[8.726705,49.507843],"type":"Point"}
}