{
  "type": "Feature",
  "properties": {
    "iso:country":"DE",
    "sg:address":"Kirner Str. 82",
    "sg:city":"Kirn",
    "sg:phone":"+49 6752/4426",
    "sg:postcode":"55606",
    "sg:province":"Rheinland-Pfalz",
    "wof:name":"Michael Willrich",
    "wof:placetype":"venue"
},
  "geometry": {"coordinates":[7.461105,49.78516],"type":"Point"}
}