{
  "type": "Feature",
  "properties": {
    "iso:country":"DE",
    "sg:address":"Dohnaer Str 168",
    "sg:city":"Dresden",
    "sg:phone":"+49 7907/8720",
    "sg:postcode":"01239",
    "sg:province":"Sachsen",
    "wof:name":"Scheib Baugruppe Hoch- Und Komplettbau Gmbh & Co",
    "wof:placetype":"venue"
},
  "geometry": {"coordinates":[9.839474678,49.0943374634],"type":"Point"}
}