{
  "type": "Feature",
  "properties": {
    "iso:country":"DE",
    "sg:address":"Otto-Keck-Str. 24",
    "sg:city":"Oberstaufen",
    "sg:phone":"+49 8386/2124",
    "sg:postcode":"87534",
    "sg:province":"Bayern",
    "wof:name":"H.a. Schaumann",
    "wof:placetype":"venue"
},
  "geometry": {"coordinates":[10.0214748383,47.5606193542],"type":"Point"}
}