{
  "type": "Feature",
  "properties": {
    "iso:country":"DE",
    "sg:address":"Hauptstr. 53",
    "sg:city":"Langenberg",
    "sg:phone":"+49 5248/943",
    "sg:postcode":"33449",
    "sg:province":"Nordrhein-Westfalen",
    "wof:name":"Stefan Pagenkemper",
    "wof:placetype":"venue"
},
  "geometry": {"coordinates":[8.3152770996,51.7754631042],"type":"Point"}
}