{
  "type": "Feature",
  "properties": {
    "iso:country":"DE",
    "sg:address":"Wildsteig 5",
    "sg:city":"Wuppertal",
    "sg:phone":"+49 202/722805",
    "sg:postcode":"42113",
    "sg:province":"Nordrhein-Westfalen",
    "wof:name":"Gerhard P\u00e4tsch Inh. Rainer P\u00e4tsch",
    "wof:placetype":"venue"
},
  "geometry": {"coordinates":[7.1058139801,51.2811737061],"type":"Point"}
}