{
  "type": "Feature",
  "properties": {
    "iso:country":"DE",
    "sg:address":"Richard-Wagner-Str. 55",
    "sg:city":"Halberstadt",
    "sg:phone":"+49 3941/691750",
    "sg:postcode":"38820",
    "sg:province":"Sachsen-Anhalt",
    "wof:name":"Christian Wolff Rechtsanwalt",
    "wof:placetype":"venue"
},
  "geometry": {"coordinates":[11.0632762909,51.8949241638],"type":"Point"}
}