{
  "type": "Feature",
  "properties": {
    "iso:country":"DE",
    "sg:address":"Hallstedt 29",
    "sg:city":"Bassum",
    "sg:phone":"+49 4248/249",
    "sg:postcode":"27211",
    "sg:province":"Niedersachsen",
    "wof:name":"Alfred Siemers",
    "wof:placetype":"venue"
},
  "geometry": {"coordinates":[8.810455,52.828648],"type":"Point"}
}