{
  "type": "Feature",
  "properties": {
    "iso:country":"DE",
    "sg:address":"Nienburger Str. 28",
    "sg:city":"Borstel",
    "sg:phone":"+49 4276/1244",
    "sg:postcode":"27246",
    "sg:province":"Niedersachsen",
    "wof:name":"Karl Meyer",
    "wof:placetype":"venue"
},
  "geometry": {"coordinates":[8.9964199066,52.6667098999],"type":"Point"}
}