{
  "type": "Feature",
  "properties": {
    "iso:country":"DE",
    "sg:address":"Ulzburger Str. 107",
    "sg:city":"Norderstedt",
    "sg:phone":"+49 40/5217159",
    "sg:postcode":"22850",
    "sg:province":"Schleswig-Holstein",
    "wof:name":"B. Kampe Hebamme",
    "wof:placetype":"venue"
},
  "geometry": {"coordinates":[9.995369,53.6917],"type":"Point"}
}