{
  "type": "Feature",
  "properties": {
    "iso:country":"DE",
    "sg:address":"Schmittensteinstr. 34",
    "sg:city":"Freilassing",
    "sg:postcode":"83395",
    "sg:province":"Bayern",
    "wof:name":"Sonalo E. K.",
    "wof:placetype":"venue"
},
  "geometry": {"coordinates":[12.9703683853,47.8314437866],"type":"Point"}
}