{
  "type": "Feature",
  "properties": {
    "iso:country":"DE",
    "sg:address":"Nossener Str. 31",
    "sg:city":"Siebenlehn",
    "sg:phone":"+49 35242/64219",
    "sg:postcode":"09634",
    "sg:province":"Sachsen",
    "wof:name":"Klaus Voigtl\u00e4nder",
    "wof:placetype":"venue"
},
  "geometry": {"coordinates":[13.304349,51.03273],"type":"Point"}
}