{
  "type": "Feature",
  "properties": {
    "iso:country":"DE",
    "sg:address":"Hauptstr. 37",
    "sg:city":"Sohren",
    "sg:phone":"+49 6543/1691",
    "sg:postcode":"55487",
    "sg:province":"Rheinland-Pfalz",
    "wof:name":"Thomas Roth",
    "wof:placetype":"venue"
},
  "geometry": {"coordinates":[7.306497097,49.9306907654],"type":"Point"}
}