{
  "type": "Feature",
  "properties": {
    "iso:country":"DE",
    "sg:address":"Karolinenplatz 5 A",
    "sg:city":"M\u00fcnchen",
    "sg:phone":"+49 89/288369",
    "sg:postcode":"80333",
    "sg:province":"Bayern",
    "wof:name":"Gabriele D\u00fcrichen Rechtsanw\u00e4ltin",
    "wof:placetype":"venue"
},
  "geometry": {"coordinates":[11.5698671341,48.1448898315],"type":"Point"}
}