{
  "type": "Feature",
  "properties": {
    "iso:country":"DE",
    "sg:address":"Sch\u00f6ne Aussicht 50",
    "sg:city":"Eschborn",
    "sg:phone":"+49 6173/63686",
    "sg:postcode":"65760",
    "sg:province":"Hessen",
    "wof:name":"Gerd Gutmann",
    "wof:placetype":"venue"
},
  "geometry": {"coordinates":[8.5523290634,50.1535682678],"type":"Point"}
}