{
  "type": "Feature",
  "properties": {
    "iso:country":"DE",
    "sg:address":"Sch\u00fctzenstr. 21",
    "sg:city":"M\u00fcnster",
    "sg:phone":"+49 251/43523",
    "sg:postcode":"48143",
    "sg:province":"Nordrhein-Westfalen",
    "wof:name":"St\u00fcer Und Ehebrecht-st\u00fcer Rechtsanw\u00e4lte",
    "wof:placetype":"venue"
},
  "geometry": {"coordinates":[7.6229758263,51.9575767517],"type":"Point"}
}