{
  "type": "Feature",
  "properties": {
    "iso:country":"DE",
    "sg:address":"Stapelberg",
    "sg:city":"Bramsche",
    "sg:phone":"+49 5461/6998",
    "sg:postcode":"49565",
    "sg:province":"Niedersachsen",
    "wof:name":"Fernleitungs-betriebsges. Mbh",
    "wof:placetype":"venue"
},
  "geometry": {"coordinates":[7.9464402199,52.433391571],"type":"Point"}
}