{
  "type": "Feature",
  "properties": {
    "iso:country":"DE",
    "sg:address":"Schneckenburgerstr.19",
    "sg:city":"Muenchen",
    "sg:phone":"+49 89/41988041",
    "sg:postcode":"81675",
    "sg:province":"Bayern",
    "wof:name":"Kascada",
    "wof:placetype":"venue"
},
  "geometry": {"coordinates":[11.6061868668,48.1374168396],"type":"Point"}
}