{
  "type": "Feature",
  "properties": {
    "iso:country":"DE",
    "sg:address":"Hauptstr. 52",
    "sg:city":"Heinsdorfergrund",
    "sg:phone":"+49 37600/3642",
    "sg:postcode":"08468",
    "sg:province":"Sachsen",
    "wof:name":"U. Zucher",
    "wof:placetype":"venue"
},
  "geometry": {"coordinates":[12.3936576843,50.6305809021],"type":"Point"}
}