{
  "type": "Feature",
  "properties": {
    "iso:country":"DE",
    "sg:address":"Erkelenzer Str. 11",
    "sg:city":"Heinsberg",
    "sg:phone":"+49 2452/61688",
    "sg:postcode":"52525",
    "sg:province":"Nordrhein-Westfalen",
    "wof:name":"S\u00e4ngerheim",
    "wof:placetype":"venue"
},
  "geometry": {"coordinates":[6.1486959457,51.0423927307],"type":"Point"}
}