{
  "type": "Feature",
  "properties": {
    "iso:country":"DE",
    "sg:address":"Brunnenstr. 8",
    "sg:city":"Niddatal",
    "sg:phone":"+49 6187/22786",
    "sg:postcode":"61194",
    "sg:province":"Hessen",
    "wof:name":"Heinrich Kopp",
    "wof:placetype":"venue"
},
  "geometry": {"coordinates":[8.835642,50.253269],"type":"Point"}
}