{
  "type": "Feature",
  "properties": {
    "iso:country":"DE",
    "sg:address":"Reichenauplatz 23",
    "sg:city":"Berching",
    "sg:phone":"+49 8462/94030",
    "sg:postcode":"92334",
    "sg:province":"Bayern",
    "wof:name":"Karlheinz Sandtner Steuerberater",
    "wof:placetype":"venue"
},
  "geometry": {"coordinates":[11.4397592545,49.106590271],"type":"Point"}
}