{
  "type": "Feature",
  "properties": {
    "iso:country":"DE",
    "sg:address":"Hagenau 4",
    "sg:city":"Falkenstein",
    "sg:phone":"+49 9462/373",
    "sg:postcode":"93167",
    "sg:province":"Bayern",
    "wof:name":"Alfons Senft",
    "wof:placetype":"venue"
},
  "geometry": {"coordinates":[12.486365,49.097439],"type":"Point"}
}