{
  "type": "Feature",
  "properties": {
    "iso:country":"DE",
    "sg:address":"Crivitzer Str. 36",
    "sg:city":"Wessin",
    "sg:phone":"+49 3863/222830",
    "sg:postcode":"19089",
    "sg:province":"Mecklenburg-Vorpommern",
    "wof:name":"Zur Schnitterkaserne",
    "wof:placetype":"venue"
},
  "geometry": {"coordinates":[11.7272882462,53.5729141235],"type":"Point"}
}