{
  "type": "Feature",
  "properties": {
    "iso:country":"DE",
    "sg:address":"Insterburger Str. 8",
    "sg:city":"Bonn",
    "sg:phone":"+49 228/687856",
    "sg:postcode":"53117",
    "sg:province":"Nordrhein-Westfalen",
    "wof:name":"Bo\u00c4 Dr. Dr. Vogelsang & Co. B\u00fcroorga. F. \u00c4rzte Ohg",
    "wof:placetype":"venue"
},
  "geometry": {"coordinates":[7.069037,50.756557],"type":"Point"}
}