{
  "type": "Feature",
  "properties": {
    "iso:country":"DE",
    "sg:address":"Auf dem Berg 6",
    "sg:city":"Pforzheim",
    "sg:phone":"+49 7231/70590",
    "sg:postcode":"75181",
    "sg:province":"Baden-W\u00fcrttemberg",
    "wof:name":"Alpengarten W\u00fcrm",
    "wof:placetype":"venue"
},
  "geometry": {"coordinates":[8.732306,48.86195],"type":"Point"}
}