{
  "type": "Feature",
  "properties": {
    "iso:country":"DE",
    "sg:address":"Feldstr. 6",
    "sg:city":"M\u00f6rfelden-Walldorf",
    "sg:phone":"+49 6105/25641",
    "sg:postcode":"64546",
    "sg:province":"Hessen",
    "wof:name":"Theobald Meffert Steinmetz",
    "wof:placetype":"venue"
},
  "geometry": {"coordinates":[8.5723514557,49.9773750305],"type":"Point"}
}