{
  "type": "Feature",
  "properties": {
    "iso:country":"DE",
    "sg:address":"Helmer 91",
    "sg:city":"Bremen",
    "sg:phone":"+49 421/235077",
    "sg:postcode":"28359",
    "sg:province":"Bremen",
    "wof:name":"Bauer & Ropers Ohg",
    "wof:placetype":"venue"
},
  "geometry": {"coordinates":[8.8630867004,53.1005096436],"type":"Point"}
}