{
  "type": "Feature",
  "properties": {
    "iso:country":"DE",
    "sg:address":"Im Ellerbrock 14",
    "sg:city":"Bocholt",
    "sg:phone":"+49 2871/38299",
    "sg:postcode":"46397",
    "sg:province":"Nordrhein-Westfalen",
    "wof:name":"Johannes H\u00fcmmelink Transport Gmbh",
    "wof:placetype":"venue"
},
  "geometry": {"coordinates":[6.6244931221,51.8584976196],"type":"Point"}
}