{
  "type": "Feature",
  "properties": {
    "iso:country":"DE",
    "sg:address":"Auf Schalen / Im Industriegebiet",
    "sg:city":"Blieskastel",
    "sg:phone":"+49 4968/4252098",
    "sg:postcode":"66440",
    "sg:province":"Saarland",
    "wof:name":"Dieter Kitto Werkzeug- Undmaschinenbau Gmbh",
    "wof:placetype":"venue"
},
  "geometry": {"coordinates":[7.258194,49.23745],"type":"Point"}
}