{
  "type": "Feature",
  "properties": {
    "iso:country":"DE",
    "sg:address":"Gerberstr. 15",
    "sg:city":"Bochum",
    "sg:phone":"+49 234/964850",
    "sg:postcode":"44787",
    "sg:province":"Nordrhein-Westfalen",
    "wof:name":"Fairsicherungsladen Bochum Gmbh",
    "wof:placetype":"venue"
},
  "geometry": {"coordinates":[7.2195000648,51.4837188721],"type":"Point"}
}