{
  "type": "Feature",
  "properties": {
    "iso:country":"DE",
    "sg:address":"Spielsee 4",
    "sg:city":"Gerolzhofen",
    "sg:phone":"+49 9382/97220",
    "sg:postcode":"97447",
    "sg:province":"Bayern",
    "wof:name":"Peter Vetter Speditions Gmbh",
    "wof:placetype":"venue"
},
  "geometry": {"coordinates":[10.3534860611,49.9078559875],"type":"Point"}
}