{
  "type": "Feature",
  "properties": {
    "iso:country":"DE",
    "sg:address":"Neukircher M\u00fchle 26",
    "sg:city":"Essen",
    "sg:phone":"+49 201/408670",
    "sg:postcode":"45239",
    "sg:province":"Nordrhein-Westfalen",
    "wof:name":"Creative Company Studio F\u00fcr Visuelle Kommunikation Gmbh",
    "wof:placetype":"venue"
},
  "geometry": {"coordinates":[7.0027570724,51.3954467773],"type":"Point"}
}