{
  "type": "Feature",
  "properties": {
    "iso:country":"DE",
    "sg:address":"Hebelstr",
    "sg:city":"HEIDELBERG",
    "sg:phone":"+49 4962/2127026",
    "sg:postcode":"69115",
    "sg:province":"Baden-W\u00fcrttemberg",
    "wof:name":"Jobsgurus",
    "wof:placetype":"venue"
},
  "geometry": {"coordinates":[8.677846,49.396172],"type":"Point"}
}