{
  "type": "Feature",
  "properties": {
    "iso:country":"DE",
    "sg:address":"Kornhausstr. 23",
    "sg:city":"Dessau",
    "sg:phone":"+49 340/610108",
    "sg:postcode":"06846",
    "sg:province":"Sachsen-Anhalt",
    "wof:name":"Margot Draxel",
    "wof:placetype":"venue"
},
  "geometry": {"coordinates":[12.2225990295,51.8465957642],"type":"Point"}
}