{
  "type": "Feature",
  "properties": {
    "iso:country":"DE",
    "sg:address":"H\u00fcttenstr. 102",
    "sg:city":"Aachen",
    "sg:phone":"+49 241/551937",
    "sg:postcode":"52068",
    "sg:province":"Nordrhein-Westfalen",
    "wof:name":"Gerhard Jakubeit Architekt",
    "wof:placetype":"venue"
},
  "geometry": {"coordinates":[6.136071,50.77681],"type":"Point"}
}