{
  "type": "Feature",
  "properties": {
    "iso:country":"DE",
    "sg:address":"Brahmsstr. 79",
    "sg:city":"Krefeld",
    "sg:phone":"+49 2151/596109",
    "sg:postcode":"47799",
    "sg:province":"Nordrhein-Westfalen",
    "wof:name":"Peter Becker Werkzeuge",
    "wof:placetype":"venue"
},
  "geometry": {"coordinates":[6.5782661438,51.3419265747],"type":"Point"}
}