{
  "type": "Feature",
  "properties": {
    "iso:country":"DE",
    "sg:address":"B\u00fcrgermeister-Haupt-Str. 31 a",
    "sg:city":"Wismar",
    "sg:postcode":"23966",
    "sg:province":"Mecklenburg-Vorpommern",
    "wof:name":"Komet-nr. 1 - Unterhaltungs- Betriebsgesellschaft Mbh",
    "wof:placetype":"venue"
},
  "geometry": {"coordinates":[11.4487142563,53.8854751587],"type":"Point"}
}