{
  "type": "Feature",
  "properties": {
    "iso:country":"DE",
    "sg:address":"Bahnhofstr. 1",
    "sg:city":"Wegscheid",
    "sg:phone":"+49 8592/237",
    "sg:postcode":"94110",
    "sg:province":"Bayern",
    "wof:name":"W. Hoffmann",
    "wof:placetype":"venue"
},
  "geometry": {"coordinates":[13.7854118347,48.5976791382],"type":"Point"}
}