{
  "type": "Feature",
  "properties": {
    "iso:country":"DE",
    "sg:address":"Industriestr. 3",
    "sg:city":"B\u00fchl",
    "sg:phone":"+49 4972/2326570",
    "sg:postcode":"77815",
    "sg:province":"Baden-W\u00fcrttemberg",
    "wof:name":"Schneider Gmbh",
    "wof:placetype":"venue"
},
  "geometry": {"coordinates":[8.1249752045,48.7050971985],"type":"Point"}
}