{
  "type": "Feature",
  "properties": {
    "iso:country":"DE",
    "sg:address":"An den Lindenb\u00e4umen 19-25",
    "sg:city":"Fuldabr\u00fcck",
    "sg:phone":"+49 561/998880",
    "sg:postcode":"34277",
    "sg:province":"Hessen",
    "wof:name":"Netcomdata Gesellschaft F\u00fcr Kommunikation Und",
    "wof:placetype":"venue"
},
  "geometry": {"coordinates":[9.5065059662,51.2675437927],"type":"Point"}
}