{
  "type": "Feature",
  "properties": {
    "iso:country":"DE",
    "sg:address":"Sartoriusstr. 27",
    "sg:city":"Essen",
    "sg:phone":"+49 201/471602",
    "sg:postcode":"45134",
    "sg:province":"Nordrhein-Westfalen",
    "wof:name":"Westkauf Tochtermann & Co. Inh. Heinrich Tillmann",
    "wof:placetype":"venue"
},
  "geometry": {"coordinates":[7.0477309227,51.4257698059],"type":"Point"}
}