{
  "type": "Feature",
  "properties": {
    "iso:country":"DE",
    "sg:address":"Am Reuterplatz 17",
    "sg:city":"Ritterhude",
    "sg:postcode":"27721",
    "sg:province":"Niedersachsen",
    "wof:name":"Rio Software-service Gmbh",
    "wof:placetype":"venue"
},
  "geometry": {"coordinates":[8.7265844345,53.1810112],"type":"Point"}
}