{
  "type": "Feature",
  "properties": {
    "iso:country":"DE",
    "sg:address":"Industriestr. 5",
    "sg:city":"Sulzbach",
    "sg:phone":"+49 6028/4285",
    "sg:postcode":"63834",
    "sg:province":"Bayern",
    "wof:name":"K. Kress",
    "wof:placetype":"venue"
},
  "geometry": {"coordinates":[9.1481466293,49.9204673767],"type":"Point"}
}