{
  "type": "Feature",
  "properties": {
    "iso:country":"DE",
    "sg:address":"Reiherweg 12",
    "sg:city":"Oldenburg",
    "sg:phone":"+49 441/201191",
    "sg:postcode":"26135",
    "sg:province":"Niedersachsen",
    "wof:name":"Georg Sander Gmbh",
    "wof:placetype":"venue"
},
  "geometry": {"coordinates":[8.2570991516,53.1273956299],"type":"Point"}
}