{
  "type": "Feature",
  "properties": {
    "iso:country":"DE",
    "sg:address":"Kirchstr. 12",
    "sg:city":"Dotternhausen",
    "sg:phone":"+49 7427/914362",
    "sg:postcode":"72359",
    "sg:province":"Baden-W\u00fcrttemberg",
    "wof:name":"Outlaw Trendwear Mode-vertriebsges. Mbh",
    "wof:placetype":"venue"
},
  "geometry": {"coordinates":[8.791368,48.229458],"type":"Point"}
}