{
  "type": "Feature",
  "properties": {
    "iso:country":"DE",
    "sg:address":"Nikolausstr. 4",
    "sg:city":"Herrsching",
    "sg:phone":"+49 8152/96373",
    "sg:postcode":"82211",
    "sg:province":"Bayern",
    "wof:name":"Martina Wurst",
    "wof:placetype":"venue"
},
  "geometry": {"coordinates":[11.173779,47.993664],"type":"Point"}
}