{
  "type": "Feature",
  "properties": {
    "iso:country":"DE",
    "sg:address":"Alpener Str. 312",
    "sg:city":"Rheinberg",
    "sg:phone":"+49 2843/50174",
    "sg:postcode":"47495",
    "sg:province":"Nordrhein-Westfalen",
    "wof:name":"A. Ricking Heissmangel",
    "wof:placetype":"venue"
},
  "geometry": {"coordinates":[6.5509772301,51.555770874],"type":"Point"}
}