{
  "type": "Feature",
  "properties": {
    "iso:country":"DE",
    "sg:address":"Seligenst\u00e4dter Str. 5",
    "sg:city":"Offenbach",
    "sg:phone":"+49 69/893707",
    "sg:postcode":"63073",
    "sg:province":"Hessen",
    "wof:name":"Hans Reissner Augenoptiker",
    "wof:placetype":"venue"
},
  "geometry": {"coordinates":[8.807600975,50.0882835388],"type":"Point"}
}