{
  "type": "Feature",
  "properties": {
    "iso:country":"DE",
    "sg:address":"Hauptstr. 54",
    "sg:city":"Ottersweier",
    "sg:phone":"+49 7223/21127",
    "sg:postcode":"77833",
    "sg:province":"Baden-W\u00fcrttemberg",
    "wof:name":"Bruno Bohn",
    "wof:placetype":"venue"
},
  "geometry": {"coordinates":[8.1115159988,48.6688766479],"type":"Point"}
}