{
  "type": "Feature",
  "properties": {
    "iso:country":"DE",
    "sg:address":"Am Dobben 147",
    "sg:city":"Bremen",
    "sg:phone":"+49 421/338680",
    "sg:postcode":"28203",
    "sg:province":"Bremen",
    "wof:name":"Gfg Gruppe F\u00fcr Gestaltung Gmbh",
    "wof:placetype":"venue"
},
  "geometry": {"coordinates":[8.8201189041,53.0798988342],"type":"Point"}
}