{
  "type": "Feature",
  "properties": {
    "iso:country":"DE",
    "sg:address":"Nu\u00dfbaumstr. 12",
    "sg:city":"M\u00fcnchen",
    "sg:phone":"+49 89/53870",
    "sg:postcode":"80336",
    "sg:province":"Bayern",
    "wof:name":"M\u00fcnchener Hypothekenbank Eg",
    "wof:placetype":"venue"
},
  "geometry": {"coordinates":[11.563377,48.133511],"type":"Point"}
}