{
  "type": "Feature",
  "properties": {
    "iso:country":"DE",
    "sg:address":"Arkadenstr. 1",
    "sg:city":"Bad Iburg",
    "sg:phone":"+49 5403/9354",
    "sg:postcode":"49186",
    "sg:province":"Niedersachsen",
    "wof:name":"Chr. Menzefricke",
    "wof:placetype":"venue"
},
  "geometry": {"coordinates":[8.046128273,52.1584091187],"type":"Point"}
}