{
  "type": "Feature",
  "properties": {
    "iso:country":"DE",
    "sg:address":"Bahnhofstr. 13",
    "sg:city":"Eislingen",
    "sg:phone":"+49 7161/83954",
    "sg:postcode":"73054",
    "sg:province":"Baden-W\u00fcrttemberg",
    "wof:name":"Black Jack",
    "wof:placetype":"venue"
},
  "geometry": {"coordinates":[9.7058210373,48.6956825256],"type":"Point"}
}