{
  "type": "Feature",
  "properties": {
    "iso:country":"DE",
    "sg:address":"Schillerstr. 35",
    "sg:city":"Berlin",
    "sg:phone":"+49 30/31505924",
    "sg:postcode":"10627",
    "sg:province":"Berlin",
    "wof:name":"Ths Technik Handels Und Service Gmbh",
    "wof:placetype":"venue"
},
  "geometry": {"coordinates":[13.3075027466,52.5102272034],"type":"Point"}
}