{
  "type": "Feature",
  "properties": {
    "iso:country":"DE",
    "sg:address":"Markt 6",
    "sg:city":"Hann. M\u00fcnden",
    "sg:phone":"+49 5541/4043",
    "sg:postcode":"34346",
    "sg:province":"Niedersachsen",
    "wof:name":"Endig Und Langkau Rechtsanw\u00e4lte Und Notare",
    "wof:placetype":"venue"
},
  "geometry": {"coordinates":[9.6513757706,51.4179267883],"type":"Point"}
}