{
  "type": "Feature",
  "properties": {
    "iso:country":"DE",
    "sg:address":"Kaiserstr. 123",
    "sg:city":"Siegburg",
    "sg:phone":"+49 2241/69505",
    "sg:postcode":"53721",
    "sg:province":"Nordrhein-Westfalen",
    "wof:name":"China-restaurant Jasmin",
    "wof:placetype":"venue"
},
  "geometry": {"coordinates":[7.2048401833,50.8031539917],"type":"Point"}
}