{
  "type": "Feature",
  "properties": {
    "iso:country":"DE",
    "sg:address":"Weinolsheimer Str. 14",
    "sg:city":"Bechtolsheim",
    "sg:phone":"+49 6733/243",
    "sg:postcode":"55234",
    "sg:province":"Rheinland-Pfalz",
    "wof:name":"H. Bretz",
    "wof:placetype":"venue"
},
  "geometry": {"coordinates":[8.1976490021,49.8066101074],"type":"Point"}
}