{
  "type": "Feature",
  "properties": {
    "iso:country":"DE",
    "sg:address":"Wengertstr. 32",
    "sg:city":"Reutlingen",
    "sg:phone":"+49 7121/490608",
    "sg:postcode":"72766",
    "sg:province":"Baden-W\u00fcrttemberg",
    "wof:name":"Wengertst\u00fcble",
    "wof:placetype":"venue"
},
  "geometry": {"coordinates":[9.2274703979,48.5392532349],"type":"Point"}
}