{
  "type": "Feature",
  "properties": {
    "iso:country":"DE",
    "sg:address":"M\u00fchlenstr. 5",
    "sg:city":"Sprockh\u00f6vel",
    "sg:phone":"+49 2324/77680",
    "sg:postcode":"45549",
    "sg:province":"Nordrhein-Westfalen",
    "wof:name":"Pizzeria Scalini",
    "wof:placetype":"venue"
},
  "geometry": {"coordinates":[7.25045681,51.3683929443],"type":"Point"}
}