{
  "type": "Feature",
  "properties": {
    "iso:country":"DE",
    "sg:address":"Kornbergstr. 10",
    "sg:city":"B\u00f6blingen",
    "sg:phone":"+49 7031",
    "sg:postcode":"71032",
    "sg:province":"Baden-W\u00fcrttemberg",
    "wof:name":"Forster Kugelstrahlen Und Fr\u00e4sen",
    "wof:placetype":"venue"
},
  "geometry": {"coordinates":[9.0224189758,48.6807556152],"type":"Point"}
}