{
  "type": "Feature",
  "properties": {
    "iso:country":"DE",
    "sg:address":"Turnerstr. 22",
    "sg:city":"Solingen",
    "sg:phone":"+49 212/330021",
    "sg:postcode":"42699",
    "sg:province":"Nordrhein-Westfalen",
    "wof:name":"Erwin Kolfertz",
    "wof:placetype":"venue"
},
  "geometry": {"coordinates":[7.0245251656,51.1663360596],"type":"Point"}
}