{
  "type": "Feature",
  "properties": {
    "iso:country":"DE",
    "sg:address":"Ernst-Th\u00e4lmann-Str. 27",
    "sg:city":"Kitzen",
    "sg:phone":"+49 34203/54842",
    "sg:postcode":"04460",
    "sg:province":"Sachsen",
    "wof:name":"Konsum Haushaltwaren Textilien",
    "wof:placetype":"venue"
},
  "geometry": {"coordinates":[12.225069046,51.2259979248],"type":"Point"}
}