{
  "type": "Feature",
  "properties": {
    "iso:country":"DE",
    "sg:address":"Beim Strohhause 32",
    "sg:city":"Hamburg",
    "sg:phone":"+49 40/2801011",
    "sg:postcode":"20097",
    "sg:province":"Hamburg",
    "wof:name":"Aktiv Arbeit Gmbh",
    "wof:placetype":"venue"
},
  "geometry": {"coordinates":[10.0231189728,53.5531692505],"type":"Point"}
}