{
  "type": "Feature",
  "properties": {
    "iso:country":"DE",
    "sg:address":"Peter-Michels-Str. 13",
    "sg:city":"K\u00f6ln",
    "sg:phone":"+49 221/597040",
    "sg:postcode":"50827",
    "sg:province":"Nordrhein-Westfalen",
    "wof:name":"Cerberus Agentur F\u00fcr Werbung Gmbh",
    "wof:placetype":"venue"
},
  "geometry": {"coordinates":[6.9143610001,50.9708442688],"type":"Point"}
}