{
  "type": "Feature",
  "properties": {
    "iso:country":"DE",
    "sg:address":"Kurzes Gel\u00e4nd 14",
    "sg:city":"Augsburg",
    "sg:phone":"+49 821/407062",
    "sg:postcode":"86156",
    "sg:province":"Bayern",
    "wof:name":"Biberacher Dentaltechnik Gmbh",
    "wof:placetype":"venue"
},
  "geometry": {"coordinates":[10.847351,48.387161],"type":"Point"}
}