{
  "type": "Feature",
  "properties": {
    "iso:country":"DE",
    "sg:address":"Breisacher Str. 86",
    "sg:city":"Freiburg",
    "sg:postcode":"79110",
    "sg:province":"Baden-W\u00fcrttemberg",
    "wof:name":"Kw Beteiligungsges. Mbh",
    "wof:placetype":"venue"
},
  "geometry": {"coordinates":[7.829442,48.007622],"type":"Point"}
}