{
  "type": "Feature",
  "properties": {
    "iso:country":"DE",
    "sg:address":"Hartmannskoppel 4",
    "sg:city":"Pl\u00f6n",
    "sg:phone":"+49 4522/8120",
    "sg:postcode":"24306",
    "sg:province":"Schleswig-Holstein",
    "wof:name":"Klaus Thiele",
    "wof:placetype":"venue"
},
  "geometry": {"coordinates":[10.407874,54.158703],"type":"Point"}
}