{
  "type": "Feature",
  "properties": {
    "iso:country":"DE",
    "sg:address":"Am Wochenmarkt 22",
    "sg:city":"G\u00f6ttingen",
    "sg:phone":"+49 551/487770",
    "sg:postcode":"37073",
    "sg:province":"Niedersachsen",
    "wof:name":"Gastst\u00e4tte Z. A. K.",
    "wof:placetype":"venue"
},
  "geometry": {"coordinates":[9.9375553131,51.5311546326],"type":"Point"}
}