{
  "type": "Feature",
  "properties": {
    "iso:country":"DE",
    "sg:address":"Lindwurmstr. 57",
    "sg:city":"M\u00fcnchen",
    "sg:phone":"+49 89/7470203",
    "sg:postcode":"80337",
    "sg:province":"Bayern",
    "wof:name":"Thomas M\u00fchlmann",
    "wof:placetype":"venue"
},
  "geometry": {"coordinates":[11.5604476929,48.1302833557],"type":"Point"}
}