{
  "type": "Feature",
  "properties": {
    "iso:country":"DE",
    "sg:address":"Podbielskistr. 197-199",
    "sg:city":"Hannover",
    "sg:phone":"+49 511/691727",
    "sg:postcode":"30177",
    "sg:province":"Niedersachsen",
    "wof:name":"Werner Ansorge Porzellan-kunstgewerbe",
    "wof:placetype":"venue"
},
  "geometry": {"coordinates":[9.7789239883,52.3997688293],"type":"Point"}
}