{
  "type": "Feature",
  "properties": {
    "iso:country":"DE",
    "sg:address":"Worthdamm 13-27",
    "sg:city":"Hamburg",
    "sg:phone":"+49 40/78115720",
    "sg:postcode":"20457",
    "sg:province":"Hamburg",
    "wof:name":"Rubitherm Gmbh",
    "wof:placetype":"venue"
},
  "geometry": {"coordinates":[9.9832630157,53.5362739563],"type":"Point"}
}