{
  "type": "Feature",
  "properties": {
    "iso:country":"DE",
    "sg:address":"Ulmenstr. 8",
    "sg:city":"Reitmehring",
    "sg:postcode":"83512",
    "sg:province":"Bayern",
    "wof:name":"Transportvermittlung Sts Gmbh",
    "wof:placetype":"venue"
},
  "geometry": {"coordinates":[12.1813716888,48.0517921448],"type":"Point"}
}