{
  "type": "Feature",
  "properties": {
    "iso:country":"DE",
    "sg:address":"Halfmannstr. 10",
    "sg:city":"Dortmund",
    "sg:phone":"+49 231/800139",
    "sg:postcode":"44143",
    "sg:province":"Nordrhein-Westfalen",
    "wof:name":"Menne Kg Rohrleitungsbau",
    "wof:placetype":"venue"
},
  "geometry": {"coordinates":[7.5205211639,51.5245857239],"type":"Point"}
}