{
  "type": "Feature",
  "properties": {
    "iso:country":"DE",
    "sg:address":"Kaiserstr 23",
    "sg:city":"Wipperf\u00fcrth",
    "sg:phone":"+49 2267/7633",
    "sg:postcode":"51688",
    "sg:province":"Nordrhein-Westfalen",
    "wof:name":"Glas-eschbach Gmbh",
    "wof:placetype":"venue"
},
  "geometry": {"coordinates":[7.3872199059,51.1178016663],"type":"Point"}
}