{
  "type": "Feature",
  "properties": {
    "iso:country":"DE",
    "sg:address":"Ringstr. 5",
    "sg:city":"Dresden",
    "sg:postcode":"01067",
    "sg:province":"Sachsen",
    "wof:name":"Flug & Fern Reiseb\u00fcro Gmbh",
    "wof:placetype":"venue"
},
  "geometry": {"coordinates":[13.7429704666,51.0485954285],"type":"Point"}
}