{
  "type": "Feature",
  "properties": {
    "iso:country":"DE",
    "sg:address":"Schregenhof 8",
    "sg:city":"Hamburg",
    "sg:phone":"+49 40/5385678",
    "sg:postcode":"22339",
    "sg:province":"Hamburg",
    "wof:name":"Pauk Schulz Inh. Heinz Schulz",
    "wof:placetype":"venue"
},
  "geometry": {"coordinates":[10.0465021133,53.6483268738],"type":"Point"}
}