{
  "type": "Feature",
  "properties": {
    "iso:country":"DE",
    "sg:address":"Bahnhofstr. 44",
    "sg:city":"Vetschau",
    "sg:phone":"+49 35433/3145",
    "sg:postcode":"03226",
    "sg:province":"Brandenburg",
    "wof:name":"Pension Bugner",
    "wof:placetype":"venue"
},
  "geometry": {"coordinates":[14.0786333084,51.7867393494],"type":"Point"}
}