{
  "type": "Feature",
  "properties": {
    "iso:country":"DE",
    "sg:address":"An der Aussicht 1",
    "sg:city":"Gummersbach",
    "sg:phone":"+49 2261/66144",
    "sg:postcode":"51647",
    "sg:province":"Nordrhein-Westfalen",
    "wof:name":"Manfred Pieper Architekt",
    "wof:placetype":"venue"
},
  "geometry": {"coordinates":[7.500882,51.041752],"type":"Point"}
}