{
  "type": "Feature",
  "properties": {
    "iso:country":"DE",
    "sg:address":"Markt 2",
    "sg:city":"Telgte",
    "sg:phone":"+49 2504/77399",
    "sg:postcode":"48291",
    "sg:province":"Nordrhein-Westfalen",
    "wof:name":"Hansen Am Markt Verwaltungs- Gmbh",
    "wof:placetype":"venue"
},
  "geometry": {"coordinates":[7.78576,51.984295],"type":"Point"}
}