{
  "type": "Feature",
  "properties": {
    "iso:country":"DE",
    "sg:address":"Stromberger Str. 168",
    "sg:city":"Beckum",
    "sg:phone":"+49 2521/4123",
    "sg:postcode":"59269",
    "sg:province":"Nordrhein-Westfalen",
    "wof:name":"Theodor Sasse",
    "wof:placetype":"venue"
},
  "geometry": {"coordinates":[8.0423145294,51.7579612732],"type":"Point"}
}