{
  "type": "Feature",
  "properties": {
    "iso:country":"DE",
    "sg:address":"Gro\u00dfbeerenstr. 97",
    "sg:city":"Potsdam",
    "sg:phone":"+49 331/2708168",
    "sg:postcode":"14482",
    "sg:province":"Brandenburg",
    "wof:name":"Bb Counter Reisen Gmbh",
    "wof:placetype":"venue"
},
  "geometry": {"coordinates":[13.1029586792,52.3870506287],"type":"Point"}
}