{
  "type": "Feature",
  "properties": {
    "iso:country":"DE",
    "sg:address":"Neustr. 2",
    "sg:city":"M\u00fcnster",
    "sg:phone":"+49 2506/2088",
    "sg:postcode":"48167",
    "sg:province":"Nordrhein-Westfalen",
    "wof:name":"P. Schmidt",
    "wof:placetype":"venue"
},
  "geometry": {"coordinates":[7.7285580635,51.9175949097],"type":"Point"}
}