{
  "type": "Feature",
  "properties": {
    "iso:country":"DE",
    "sg:address":"Camburger Str. 5",
    "sg:city":"Droy\u00dfig",
    "sg:phone":"+49 34425/21204",
    "sg:postcode":"06722",
    "sg:province":"Sachsen-Anhalt",
    "wof:name":"L\u00f6wen-apotheke",
    "wof:placetype":"venue"
},
  "geometry": {"coordinates":[12.025945,51.041676],"type":"Point"}
}