{
  "type": "Feature",
  "properties": {
    "iso:country":"DE",
    "sg:address":"Ostertorsteinweg 30 a",
    "sg:city":"Bremen",
    "sg:phone":"+49 421/700421",
    "sg:postcode":"28203",
    "sg:province":"Bremen",
    "wof:name":"Manfred Komoll Schl\u00fcsseldienst",
    "wof:placetype":"venue"
},
  "geometry": {"coordinates":[8.8213834763,53.0728187561],"type":"Point"}
}