{
  "type": "Feature",
  "properties": {
    "iso:country":"DE",
    "sg:address":"Neersbroicher Str. 54",
    "sg:city":"M\u00f6nchengladbach",
    "sg:phone":"+49 2161/966095",
    "sg:postcode":"41066",
    "sg:province":"Nordrhein-Westfalen",
    "wof:name":"Gebr. Schmitz Bauwerks-abbdichtungen Gmbh",
    "wof:placetype":"venue"
},
  "geometry": {"coordinates":[6.4772,51.224243],"type":"Point"}
}