{
  "type": "Feature",
  "properties": {
    "iso:country":"DE",
    "sg:address":"Wolframstrasse 8",
    "sg:city":"Vilshofen",
    "sg:phone":"+49 8541",
    "sg:postcode":"94474",
    "sg:province":"Bayern",
    "wof:name":"Lastminute Reisen Fl\u00fcge Reiseversicherung",
    "wof:placetype":"venue"
},
  "geometry": {"coordinates":[13.194676,48.593548],"type":"Point"}
}