{
  "type": "Feature",
  "properties": {
    "iso:country":"DE",
    "sg:address":"Hauert 15",
    "sg:city":"Dortmund",
    "sg:phone":"+49 231/5578780",
    "sg:postcode":"44227",
    "sg:province":"Nordrhein-Westfalen",
    "wof:name":"Leonhardt Zeit- Und Datenerfassungssysteme Gmbh",
    "wof:placetype":"venue"
},
  "geometry": {"coordinates":[7.40148592,51.4884986877],"type":"Point"}
}