{
  "type": "Feature",
  "properties": {
    "iso:country":"DE",
    "sg:address":"Hohes St\u00fcck 1",
    "sg:city":"Wetter",
    "sg:phone":"+49 2335/62441",
    "sg:postcode":"58300",
    "sg:province":"Nordrhein-Westfalen",
    "wof:name":"Hans-georg Kubatzsch",
    "wof:placetype":"venue"
},
  "geometry": {"coordinates":[7.371213,51.363956],"type":"Point"}
}