{
  "type": "Feature",
  "properties": {
    "iso:country":"DE",
    "sg:address":"Simon-Bolivar-Str. 12",
    "sg:city":"Bremen",
    "sg:phone":"+49 421/543821",
    "sg:postcode":"28197",
    "sg:province":"Bremen",
    "wof:name":"Kreis Gmbh",
    "wof:placetype":"venue"
},
  "geometry": {"coordinates":[8.782677,53.075413],"type":"Point"}
}