{
  "type": "Feature",
  "properties": {
    "iso:country":"DE",
    "sg:address":"Hofgasse 5",
    "sg:city":"Traunstein",
    "sg:phone":"+49 861/164542",
    "sg:postcode":"83278",
    "sg:province":"Bayern",
    "wof:name":"August Koch Gmbh",
    "wof:placetype":"venue"
},
  "geometry": {"coordinates":[12.650551796,47.8691673279],"type":"Point"}
}