{
  "type": "Feature",
  "properties": {
    "iso:country":"DE",
    "sg:address":"Lenzener Str. 9",
    "sg:city":"D\u00f6mitz",
    "sg:phone":"+49 38758/22287",
    "sg:postcode":"19303",
    "sg:province":"Mecklenburg-Vorpommern",
    "wof:name":"Karsten Linke",
    "wof:placetype":"venue"
},
  "geometry": {"coordinates":[11.293618,53.130894],"type":"Point"}
}