{
  "type": "Feature",
  "properties": {
    "iso:country":"DE",
    "sg:address":"Schubartstr. 20a",
    "sg:city":"Heilbronn",
    "sg:phone":"+49 7131/95290",
    "sg:postcode":"74076",
    "sg:province":"Baden-W\u00fcrttemberg",
    "wof:name":"Bachler Und Krummlauf Architekten",
    "wof:placetype":"venue"
},
  "geometry": {"coordinates":[9.235164,49.142738],"type":"Point"}
}