{
  "type": "Feature",
  "properties": {
    "iso:country":"DE",
    "sg:address":"Maigl\u00f6ckchenweg 14",
    "sg:city":"J\u00fclich",
    "sg:phone":"+49 2461/910303",
    "sg:postcode":"52428",
    "sg:province":"Nordrhein-Westfalen",
    "wof:name":"Michael Steegmann Architekt",
    "wof:placetype":"venue"
},
  "geometry": {"coordinates":[6.37541,50.927849],"type":"Point"}
}