{
  "type": "Feature",
  "properties": {
    "iso:country":"DE",
    "sg:address":"B\u00fcrgerweide 10-12",
    "sg:city":"Hamburg",
    "sg:phone":"+49 40/2542131",
    "sg:postcode":"20535",
    "sg:province":"Hamburg",
    "wof:name":"Matthiessen & Noesselt",
    "wof:placetype":"venue"
},
  "geometry": {"coordinates":[10.0288085938,53.5563812256],"type":"Point"}
}