{
  "type": "Feature",
  "properties": {
    "iso:country":"DE",
    "sg:address":"Hauptstr. 47",
    "sg:city":"Echzell",
    "sg:postcode":"61209",
    "sg:province":"Hessen",
    "wof:name":"Mobilplan-engineering Gmbh",
    "wof:placetype":"venue"
},
  "geometry": {"coordinates":[8.8841199875,50.3868598938],"type":"Point"}
}