{
  "type": "Feature",
  "properties": {
    "iso:country":"DE",
    "sg:address":"Silcherstr. 33",
    "sg:city":"Ostrach",
    "sg:phone":"+49 7585/444",
    "sg:postcode":"88356",
    "sg:province":"Baden-W\u00fcrttemberg",
    "wof:name":"Hans Strobel",
    "wof:placetype":"venue"
},
  "geometry": {"coordinates":[9.379345,47.948406],"type":"Point"}
}