{
  "type": "Feature",
  "properties": {
    "iso:country":"DE",
    "sg:address":"Dr.-Schott-Str. 26",
    "sg:city":"Zwiesel",
    "sg:phone":"+49 9922/2192",
    "sg:postcode":"94227",
    "sg:province":"Bayern",
    "wof:name":"M. Und B. Reichmann Holzbildhauer",
    "wof:placetype":"venue"
},
  "geometry": {"coordinates":[13.228126,49.015873],"type":"Point"}
}