{
  "type": "Feature",
  "properties": {
    "iso:country":"DE",
    "sg:address":"Georgsh\u00fcttenstr. 9",
    "sg:city":"Solms",
    "sg:phone":"+49 6442/8904",
    "sg:postcode":"35606",
    "sg:province":"Hessen",
    "wof:name":"Leberecht",
    "wof:placetype":"venue"
},
  "geometry": {"coordinates":[8.4069976807,50.5408058167],"type":"Point"}
}