{
  "type": "Feature",
  "properties": {
    "iso:country":"DE",
    "sg:address":"Liliencronstrasse 53",
    "sg:city":"Neu Wulmstorf (Hamburg)",
    "sg:postcode":"21629",
    "sg:province":"Niedersachsen",
    "wof:name":"H S Alubau",
    "wof:placetype":"venue"
},
  "geometry": {"coordinates":[9.782951355,53.4663352966],"type":"Point"}
}