{
  "type": "Feature",
  "properties": {
    "iso:country":"DE",
    "sg:address":"Uhlenhof 12",
    "sg:city":"Vietmannsdorf",
    "sg:phone":"+49 39882/258",
    "sg:postcode":"17268",
    "sg:province":"Brandenburg",
    "wof:name":"Wolf Lobedan",
    "wof:placetype":"venue"
},
  "geometry": {"coordinates":[13.5313749313,53.0501556396],"type":"Point"}
}