{
  "type": "Feature",
  "properties": {
    "iso:country":"DE",
    "sg:address":"Heilbronner Str. 19",
    "sg:city":"Schw\u00e4bisch Hall",
    "sg:phone":"+49 791/970150",
    "sg:postcode":"74523",
    "sg:province":"Baden-W\u00fcrttemberg",
    "wof:name":"Bestattungsunternehmen Stadt Schw\u00e4bisch Hall",
    "wof:placetype":"venue"
},
  "geometry": {"coordinates":[9.737032,49.120594],"type":"Point"}
}