{
  "type": "Feature",
  "properties": {
    "iso:country":"DE",
    "sg:address":"Schl\u00fcterstr. 70",
    "sg:city":"Berlin",
    "sg:phone":"+49 30/3133656",
    "sg:postcode":"10625",
    "sg:province":"Berlin",
    "wof:name":"Das Verborgene Museum",
    "wof:placetype":"venue"
},
  "geometry": {"coordinates":[13.3180503845,52.5079994202],"type":"Point"}
}