{
  "type": "Feature",
  "properties": {
    "iso:country":"DE",
    "sg:address":"An der Koppel 11",
    "sg:city":"Gardelegen",
    "sg:postcode":"39638",
    "sg:province":"Sachsen-Anhalt",
    "wof:name":"Kerstin Fr\u00f6se",
    "wof:placetype":"venue"
},
  "geometry": {"coordinates":[11.375442,52.523411],"type":"Point"}
}