{
  "type": "Feature",
  "properties": {
    "iso:country":"DE",
    "sg:address":"Deininghauser Str. 66",
    "sg:city":"Dortmund",
    "sg:phone":"+49 231/375887",
    "sg:postcode":"44357",
    "sg:province":"Nordrhein-Westfalen",
    "wof:name":"A. Benedikt",
    "wof:placetype":"venue"
},
  "geometry": {"coordinates":[7.3635878563,51.557220459],"type":"Point"}
}