{
  "type": "Feature",
  "properties": {
    "iso:country":"DE",
    "sg:address":"Klopstockstr. 23",
    "sg:city":"Unna",
    "sg:postcode":"59423",
    "sg:province":"Nordrhein-Westfalen",
    "wof:name":"Projektentwicklungs- Gesellschaft Wohnanlage",
    "wof:placetype":"venue"
},
  "geometry": {"coordinates":[7.70392,51.533588],"type":"Point"}
}