{
  "type": "Feature",
  "properties": {
    "iso:country":"DE",
    "sg:address":"Matthias-Bauer-Str. 48",
    "sg:city":"Neuburg",
    "sg:phone":"+49 8431/67550",
    "sg:postcode":"86633",
    "sg:province":"Bayern",
    "wof:name":"Johann R\u00f6sener Heizungs- U. L\u00fcftungsbau Gmbh",
    "wof:placetype":"venue"
},
  "geometry": {"coordinates":[11.2212724686,48.7258644104],"type":"Point"}
}