{
  "type": "Feature",
  "properties": {
    "iso:country":"DE",
    "sg:address":"In der Laubach 20",
    "sg:city":"Rosbach",
    "sg:phone":"+49 6003/930034",
    "sg:postcode":"61191",
    "sg:province":"Hessen",
    "wof:name":"F. Wurzrainer Anlagenberater",
    "wof:placetype":"venue"
},
  "geometry": {"coordinates":[8.7062616348,50.297454834],"type":"Point"}
}