{
  "type": "Feature",
  "properties": {
    "iso:country":"DE",
    "sg:address":"Hinter dem Zoll 26",
    "sg:city":"Aschersleben",
    "sg:postcode":"06449",
    "sg:province":"Sachsen-Anhalt",
    "wof:name":"Vs Catering Und Service Gmbh",
    "wof:placetype":"venue"
},
  "geometry": {"coordinates":[11.45497,51.754322],"type":"Point"}
}