{
  "type": "Feature",
  "properties": {
    "iso:country":"DE",
    "sg:address":"Wetzh\u00e4user Str. 17",
    "sg:city":"Stadtlauringen",
    "sg:phone":"+49 9724/656",
    "sg:postcode":"97488",
    "sg:province":"Bayern",
    "wof:name":"Gerhard Unger",
    "wof:placetype":"venue"
},
  "geometry": {"coordinates":[10.4110641479,50.1946525574],"type":"Point"}
}