{
  "type": "Feature",
  "properties": {
    "iso:country":"DE",
    "sg:address":"Methestr. 18",
    "sg:city":"Moringen",
    "sg:phone":"+49 5554/8093",
    "sg:postcode":"37186",
    "sg:province":"Niedersachsen",
    "wof:name":"Heinzbert Hartmann",
    "wof:placetype":"venue"
},
  "geometry": {"coordinates":[9.864352,51.700241],"type":"Point"}
}