{
  "type": "Feature",
  "properties": {
    "iso:country":"DE",
    "sg:address":"Platanenstr. 59",
    "sg:city":"Taufkirchen",
    "sg:phone":"+49 89/6123206",
    "sg:postcode":"82024",
    "sg:province":"Bayern",
    "wof:name":"K-a Planungs- Und Baubetreuungsges. Mbh",
    "wof:placetype":"venue"
},
  "geometry": {"coordinates":[11.6012878418,48.0507164001],"type":"Point"}
}