{
  "type": "Feature",
  "properties": {
    "iso:country":"DE",
    "sg:address":"Bismarckstr. 22",
    "sg:city":"Leonberg",
    "sg:phone":"+49 7152/71600",
    "sg:postcode":"71229",
    "sg:province":"Baden-W\u00fcrttemberg",
    "wof:name":"Walter Schmidt",
    "wof:placetype":"venue"
},
  "geometry": {"coordinates":[9.007276,48.792133],"type":"Point"}
}