{
  "type": "Feature",
  "properties": {
    "iso:country":"DE",
    "sg:address":"Teutoburger Str. 8",
    "sg:city":"N\u00fcrnberg",
    "sg:phone":"+49 911/592333",
    "sg:postcode":"90491",
    "sg:province":"Bayern",
    "wof:name":"See-adler-optik",
    "wof:placetype":"venue"
},
  "geometry": {"coordinates":[11.112683,49.46682],"type":"Point"}
}