{
  "type": "Feature",
  "properties": {
    "iso:country":"DE",
    "sg:address":"Dorfstr. 36",
    "sg:city":"Balingen",
    "sg:phone":"+49 7433/6257",
    "sg:postcode":"72336",
    "sg:province":"Baden-W\u00fcrttemberg",
    "wof:name":"Helmut Hofmann",
    "wof:placetype":"venue"
},
  "geometry": {"coordinates":[8.8400201797,48.3037223816],"type":"Point"}
}