{
  "type": "Feature",
  "properties": {
    "iso:country":"DE",
    "sg:address":"R\u00e4tikonstr. 8",
    "sg:city":"Friedrichshafen",
    "sg:phone":"+49 7541/22750",
    "sg:postcode":"88045",
    "sg:province":"Baden-W\u00fcrttemberg",
    "wof:name":"Dr. Hans-gerhd Braun",
    "wof:placetype":"venue"
},
  "geometry": {"coordinates":[9.4573421478,47.658454895],"type":"Point"}
}