{
  "type": "Feature",
  "properties": {
    "iso:country":"DE",
    "sg:address":"Konradin-Kreutzer-Str. 1",
    "sg:city":"Ettlingen",
    "sg:phone":"+49 7243/29453",
    "sg:postcode":"76275",
    "sg:province":"Baden-W\u00fcrttemberg",
    "wof:name":"Walter Hirzler Architekt",
    "wof:placetype":"venue"
},
  "geometry": {"coordinates":[8.417928,48.893841],"type":"Point"}
}