{
  "type": "Feature",
  "properties": {
    "iso:country":"DE",
    "sg:address":"Weidekampstr. 12",
    "sg:city":"Hamm",
    "sg:postcode":"59063",
    "sg:province":"Nordrhein-Westfalen",
    "wof:name":"Fas Luftfahrtdienst- Leistungen Gmbh",
    "wof:placetype":"venue"
},
  "geometry": {"coordinates":[7.836837,51.683941],"type":"Point"}
}