{
  "type": "Feature",
  "properties": {
    "iso:country":"DE",
    "sg:address":"Landsberger Str. 353",
    "sg:city":"M\u00fcnchen",
    "sg:postcode":"80687",
    "sg:province":"Bayern",
    "wof:name":"Farbdesign Gmbh",
    "wof:placetype":"venue"
},
  "geometry": {"coordinates":[11.49123,48.14402],"type":"Point"}
}