{
  "type": "Feature",
  "properties": {
    "iso:country":"DE",
    "sg:address":"Ferdinand-Reich-Stra\u00dfe 1",
    "sg:city":"Freiberg",
    "sg:phone":"+49 3731/67660",
    "sg:postcode":"09599",
    "sg:province":"Sachsen",
    "wof:name":"Wie\u00dfner Metallbau Gmbh Stahl- Und Leichtmetallbau",
    "wof:placetype":"venue"
},
  "geometry": {"coordinates":[13.353244,50.90205],"type":"Point"}
}