{
  "type": "Feature",
  "properties": {
    "iso:country":"DE",
    "sg:address":"Sch\u00fctzenstr. 21 a",
    "sg:city":"Speyer",
    "sg:phone":"+49 6232/24605",
    "sg:postcode":"67346",
    "sg:province":"Rheinland-Pfalz",
    "wof:name":"Alte Zisterne",
    "wof:placetype":"venue"
},
  "geometry": {"coordinates":[8.4265193939,49.3163146973],"type":"Point"}
}