{
  "type": "Feature",
  "properties": {
    "iso:country":"DE",
    "sg:address":"Pappelallee 2",
    "sg:city":"Zeven",
    "sg:phone":"+49 4281/1622",
    "sg:postcode":"27404",
    "sg:province":"Niedersachsen",
    "wof:name":"Johann Otten E. K.",
    "wof:placetype":"venue"
},
  "geometry": {"coordinates":[9.2752447128,53.3003120422],"type":"Point"}
}