{
  "type": "Feature",
  "properties": {
    "iso:country":"DE",
    "sg:address":"Marienwall 29",
    "sg:city":"Minden",
    "sg:phone":"+49 571/84344",
    "sg:postcode":"32423",
    "sg:province":"Nordrhein-Westfalen",
    "wof:name":"Sozialberatungsstelle F\u00fcr T\u00fcrken",
    "wof:placetype":"venue"
},
  "geometry": {"coordinates":[8.918715,52.291336],"type":"Point"}
}