{
  "type": "Feature",
  "properties": {
    "iso:country":"DE",
    "sg:address":"Fleischhauerstr. 48",
    "sg:city":"L\u00fcbeck",
    "sg:phone":"+49 451/7063612",
    "sg:postcode":"23552",
    "sg:province":"Schleswig-Holstein",
    "wof:name":"Carsten Heise",
    "wof:placetype":"venue"
},
  "geometry": {"coordinates":[10.6892728806,53.8664398193],"type":"Point"}
}