{
  "type": "Feature",
  "properties": {
    "iso:country":"DE",
    "sg:address":"Steinweg 73/74",
    "sg:city":"M\u00fchlhausen",
    "sg:phone":"+49 36013/095",
    "sg:postcode":"99974",
    "sg:province":"Th\u00fcringen",
    "wof:name":"B\u00f6rner Und Schm\u00fccking Steuerberater",
    "wof:placetype":"venue"
},
  "geometry": {"coordinates":[10.4566164017,51.2364654541],"type":"Point"}
}