{
  "type": "Feature",
  "properties": {
    "iso:country":"DE",
    "sg:address":"Rambacher Str. 2",
    "sg:city":"Heideck",
    "sg:phone":"+49 9177/980",
    "sg:postcode":"91180",
    "sg:province":"Bayern",
    "wof:name":"Opitz & Flierl Hospitaltechnik Ag",
    "wof:placetype":"venue"
},
  "geometry": {"coordinates":[11.118781,49.129719],"type":"Point"}
}