{
  "type": "Feature",
  "properties": {
    "iso:country":"DE",
    "sg:address":"Gutenbergstr. 4",
    "sg:city":"Benningen",
    "sg:phone":"+49 7144/12189",
    "sg:postcode":"71726",
    "sg:province":"Baden-W\u00fcrttemberg",
    "wof:name":"Rolf Holzwarth",
    "wof:placetype":"venue"
},
  "geometry": {"coordinates":[9.2377376556,48.945022583],"type":"Point"}
}