{
  "type": "Feature",
  "properties": {
    "iso:country":"DE",
    "sg:address":"Hundeshagener Str.",
    "sg:city":"Leinefelde",
    "sg:phone":"+49 3605/509086",
    "sg:postcode":"37327",
    "sg:province":"Th\u00fcringen",
    "wof:name":"Gastst\u00e4tte M\u00fchlenkrug",
    "wof:placetype":"venue"
},
  "geometry": {"coordinates":[10.3175058365,51.3896026611],"type":"Point"}
}