{
  "type": "Feature",
  "properties": {
    "iso:country":"DE",
    "sg:address":"Ziegelkamp 8",
    "sg:city":"Buxtehude",
    "sg:phone":"+49 4941/617270",
    "sg:postcode":"21614",
    "sg:province":"Niedersachsen",
    "wof:name":"Stadtwerke Buxtehude Gmbh",
    "wof:placetype":"venue"
},
  "geometry": {"coordinates":[9.690743,53.468891],"type":"Point"}
}