{
  "type": "Feature",
  "properties": {
    "iso:country":"DE",
    "sg:address":"Mozartstr. 24",
    "sg:city":"Meppen",
    "sg:phone":"+49 5931/13032",
    "sg:postcode":"49716",
    "sg:province":"Niedersachsen",
    "wof:name":"Johann Anneken",
    "wof:placetype":"venue"
},
  "geometry": {"coordinates":[7.265261,52.696415],"type":"Point"}
}