{
  "type": "Feature",
  "properties": {
    "iso:country":"DE",
    "sg:address":"Brunnenstr. 21",
    "sg:city":"Borstorf",
    "sg:phone":"+49 4543/7146",
    "sg:postcode":"23881",
    "sg:province":"Schleswig-Holstein",
    "wof:name":"Rudolf D\u00e4hn",
    "wof:placetype":"venue"
},
  "geometry": {"coordinates":[10.564961,53.615883],"type":"Point"}
}