{
  "type": "Feature",
  "properties": {
    "iso:country":"DE",
    "sg:address":"Herzbergstr. 51-54",
    "sg:city":"Berlin",
    "sg:phone":"+49 30/5597916",
    "sg:postcode":"10365",
    "sg:province":"Berlin",
    "wof:name":"M. G\u00e4rtner",
    "wof:placetype":"venue"
},
  "geometry": {"coordinates":[13.498083,52.526237],"type":"Point"}
}