{
  "type": "Feature",
  "properties": {
    "iso:country":"DE",
    "sg:address":"Birrbachstr. 7",
    "sg:city":"Schmelz",
    "sg:phone":"+49 6887/1534",
    "sg:postcode":"66839",
    "sg:province":"Saarland",
    "wof:name":"Johannes Dittgen B\u00e4ckerei Und Konditorei Gmbh",
    "wof:placetype":"venue"
},
  "geometry": {"coordinates":[6.856608,49.442024],"type":"Point"}
}