{
  "type": "Feature",
  "properties": {
    "iso:country":"DE",
    "sg:address":"Feldstr. 20",
    "sg:city":"Hasel\u00fcnne",
    "sg:phone":"+49 5961/6911",
    "sg:postcode":"49740",
    "sg:province":"Niedersachsen",
    "wof:name":"Dr. Helmut Melbaum Tierarzt",
    "wof:placetype":"venue"
},
  "geometry": {"coordinates":[7.518032074,52.6825561523],"type":"Point"}
}