{
  "type": "Feature",
  "properties": {
    "iso:country":"DE",
    "sg:address":"S\u00fcdstr. 14",
    "sg:city":"Friedberg",
    "sg:phone":"+49 6031/18667",
    "sg:postcode":"61169",
    "sg:province":"Hessen",
    "wof:name":"S. Klein",
    "wof:placetype":"venue"
},
  "geometry": {"coordinates":[8.720843,50.328938],"type":"Point"}
}