{
  "type": "Feature",
  "properties": {
    "iso:country":"DE",
    "sg:address":"Roggenbachweg 3",
    "sg:city":"Unterkirnach",
    "sg:phone":"+49 7721/84530",
    "sg:postcode":"78089",
    "sg:province":"Baden-W\u00fcrttemberg",
    "wof:name":"Otto B\u00e4chle Gmbh",
    "wof:placetype":"venue"
},
  "geometry": {"coordinates":[8.3674793243,48.0764884949],"type":"Point"}
}