{
  "type": "Feature",
  "properties": {
    "iso:country":"DE",
    "sg:address":"Rathausstr. 10",
    "sg:city":"Velten",
    "sg:phone":"+49 3304/502402",
    "sg:postcode":"16727",
    "sg:province":"Brandenburg",
    "wof:name":"Ratskeller",
    "wof:placetype":"venue"
},
  "geometry": {"coordinates":[13.1755695343,52.6895637512],"type":"Point"}
}