{
  "type": "Feature",
  "properties": {
    "iso:country":"DE",
    "sg:address":"Dransfelder Str. 7",
    "sg:city":"G\u00f6ttingen",
    "sg:postcode":"37079",
    "sg:province":"Niedersachsen",
    "wof:name":"Tfb Treuhandgesellschaft F\u00fcr Beteiligungen Mbh",
    "wof:placetype":"venue"
},
  "geometry": {"coordinates":[9.870728,51.522457],"type":"Point"}
}