{
  "type": "Feature",
  "properties": {
    "iso:country":"DE",
    "sg:address":"Bernsweg 2",
    "sg:city":"Moers",
    "sg:phone":"+49 2841/73024",
    "sg:postcode":"47445",
    "sg:province":"Nordrhein-Westfalen",
    "wof:name":"Holtmann Fahrzeug- Und Maschinenbau Gmbh",
    "wof:placetype":"venue"
},
  "geometry": {"coordinates":[6.607282,51.474396],"type":"Point"}
}