{
  "type": "Feature",
  "properties": {
    "iso:country":"DE",
    "sg:address":"Hasengasse 5 -7",
    "sg:city":"Frankfurt",
    "sg:phone":"+49 69/294390",
    "sg:postcode":"60311",
    "sg:province":"Hessen",
    "wof:name":"Casa Italiana Gmbh",
    "wof:placetype":"venue"
},
  "geometry": {"coordinates":[8.6838750839,50.1127624512],"type":"Point"}
}