{
  "type": "Feature",
  "properties": {
    "iso:country":"DE",
    "sg:address":"Dr.-Wilhelm-K\u00fclz-Str. 2",
    "sg:city":"Suhl",
    "sg:phone":"+49 3681/31438",
    "sg:postcode":"98527",
    "sg:province":"Th\u00fcringen",
    "wof:name":"Norbert Grass",
    "wof:placetype":"venue"
},
  "geometry": {"coordinates":[10.687037468,50.6040763855],"type":"Point"}
}