{
  "type": "Feature",
  "properties": {
    "iso:country":"DE",
    "sg:address":"Konrad-Zuse-Bogen 9",
    "sg:city":"Krailling",
    "sg:phone":"+49 89/8980250",
    "sg:postcode":"82152",
    "sg:province":"Bayern",
    "wof:name":"Kazana",
    "wof:placetype":"venue"
},
  "geometry": {"coordinates":[11.362521,48.095078],"type":"Point"}
}