{
  "type": "Feature",
  "properties": {
    "iso:country":"DE",
    "sg:address":"Augsburger Str. 72",
    "sg:city":"Schwabm\u00fcnchen",
    "sg:phone":"+49 8232/78686",
    "sg:postcode":"86830",
    "sg:province":"Bayern",
    "wof:name":"R + S Regel-undschaltanlagen Gmbh",
    "wof:placetype":"venue"
},
  "geometry": {"coordinates":[10.755646,48.194859],"type":"Point"}
}