{
  "type": "Feature",
  "properties": {
    "iso:country":"DE",
    "sg:address":"Johann-von-Korb-Str. 25",
    "sg:city":"Karlstadt",
    "sg:phone":"+49 9353/99737",
    "sg:postcode":"97753",
    "sg:province":"Bayern",
    "wof:name":"Alban Winheim Ingenieur",
    "wof:placetype":"venue"
},
  "geometry": {"coordinates":[9.7756214142,49.9616966248],"type":"Point"}
}