{
  "type": "Feature",
  "properties": {
    "iso:country":"DE",
    "sg:address":"Werner-Hilpert-Str. 3",
    "sg:city":"Neu-Isenburg",
    "sg:phone":"+49 6102/4218",
    "sg:postcode":"63263",
    "sg:province":"Hessen",
    "wof:name":"Gerhard R\u00fcb",
    "wof:placetype":"venue"
},
  "geometry": {"coordinates":[8.6729574203,50.0546569824],"type":"Point"}
}