{
  "type": "Feature",
  "properties": {
    "iso:country":"DE",
    "sg:address":"Bahnhofsallee 23",
    "sg:city":"Solms",
    "sg:phone":"+49 6442/23913",
    "sg:postcode":"35606",
    "sg:province":"Hessen",
    "wof:name":"Rockn Ride",
    "wof:placetype":"venue"
},
  "geometry": {"coordinates":[8.4064683914,50.5437316895],"type":"Point"}
}