{
  "type": "Feature",
  "properties": {
    "iso:country":"DE",
    "sg:address":"Nelkenstr. 2",
    "sg:city":"Walluf",
    "sg:phone":"+49 6123",
    "sg:postcode":"65396",
    "sg:province":"Hessen",
    "wof:name":"Rosenberg & Guttmann Gmbh",
    "wof:placetype":"venue"
},
  "geometry": {"coordinates":[8.160904,50.039898],"type":"Point"}
}