{
  "type": "Feature",
  "properties": {
    "iso:country":"DE",
    "sg:address":"Weinbrennerstr. 56",
    "sg:city":"Leipzig",
    "sg:postcode":"04328",
    "sg:province":"Sachsen",
    "wof:name":"Sun Bau Bock Inh. Wieland Bock",
    "wof:placetype":"venue"
},
  "geometry": {"coordinates":[12.4454908371,51.3503608704],"type":"Point"}
}