{
  "type": "Feature",
  "properties": {
    "iso:country":"DE",
    "sg:address":"Holstenstr. 27",
    "sg:city":"Stendal",
    "sg:phone":"+49 3931/217250",
    "sg:postcode":"39576",
    "sg:province":"Sachsen-Anhalt",
    "wof:name":"Wolfgang D\u00e4hre",
    "wof:placetype":"venue"
},
  "geometry": {"coordinates":[11.8549375534,52.618560791],"type":"Point"}
}