{
  "type": "Feature",
  "properties": {
    "iso:country":"DE",
    "sg:address":"L\u00fcssumer Str. 99d",
    "sg:city":"Bremen",
    "sg:phone":"+49 421/600101",
    "sg:postcode":"28779",
    "sg:province":"Bremen",
    "wof:name":"Holger H\u00fcner",
    "wof:placetype":"venue"
},
  "geometry": {"coordinates":[8.575463295,53.1913261414],"type":"Point"}
}