{
  "type": "Feature",
  "properties": {
    "iso:country":"DE",
    "sg:address":"Herlen 1",
    "sg:city":"Bergisch Gladbach",
    "sg:phone":"+49 2207/1529",
    "sg:postcode":"51429",
    "sg:province":"Nordrhein-Westfalen",
    "wof:name":"Joachim Br\u00fcggelmann Gmbh",
    "wof:placetype":"venue"
},
  "geometry": {"coordinates":[7.221414,50.988441],"type":"Point"}
}