{
  "type": "Feature",
  "properties": {
    "iso:country":"DE",
    "sg:address":"Steinbergerhof 6",
    "sg:city":"Wehr",
    "sg:phone":"+49 2655/1523",
    "sg:postcode":"56653",
    "sg:province":"Rheinland-Pfalz",
    "wof:name":"Christian Schomisch",
    "wof:placetype":"venue"
},
  "geometry": {"coordinates":[7.184683,50.425343],"type":"Point"}
}