{
  "type": "Feature",
  "properties": {
    "iso:country":"DE",
    "sg:address":"Wilhelm-Drapp-Str. 14",
    "sg:city":"Baden-Baden",
    "sg:phone":"+49 7221/5046690",
    "sg:postcode":"76532",
    "sg:province":"Baden-W\u00fcrttemberg",
    "wof:name":"Heinrich Kauffeld",
    "wof:placetype":"venue"
},
  "geometry": {"coordinates":[8.1970758438,48.7943763733],"type":"Point"}
}