{
  "type": "Feature",
  "properties": {
    "iso:country":"DE",
    "sg:address":"Heiglhofstr. 21",
    "sg:city":"M\u00fcnchen",
    "sg:phone":"+49 89/7144276",
    "sg:postcode":"81377",
    "sg:province":"Bayern",
    "wof:name":"Mechthilde Wagner Immobilien Verwaltungs-gmbh & Co. Kg",
    "wof:placetype":"venue"
},
  "geometry": {"coordinates":[11.4781398773,48.1121292114],"type":"Point"}
}