{
  "type": "Feature",
  "properties": {
    "iso:country":"DE",
    "sg:address":"M\u00f6llsiepen 2",
    "sg:city":"Meinerzhagen",
    "sg:phone":"+49 2358/90900",
    "sg:postcode":"58540",
    "sg:province":"Nordrhein-Westfalen",
    "wof:name":"Haus Eckern",
    "wof:placetype":"venue"
},
  "geometry": {"coordinates":[7.7237820625,51.1016769409],"type":"Point"}
}