{
  "type": "Feature",
  "properties": {
    "iso:country":"DE",
    "sg:address":"Schleswiger Str. 13",
    "sg:city":"Eckernf\u00f6rde",
    "sg:phone":"+49 4351/3131",
    "sg:postcode":"24340",
    "sg:province":"Schleswig-Holstein",
    "wof:name":"Eva Detlefsen",
    "wof:placetype":"venue"
},
  "geometry": {"coordinates":[9.8284606934,54.4783287048],"type":"Point"}
}