{
  "type": "Feature",
  "properties": {
    "iso:country":"DE",
    "sg:address":"Ankerstr. 6",
    "sg:city":"Magdeburg",
    "sg:phone":"+49 391/5614514",
    "sg:postcode":"39124",
    "sg:province":"Sachsen-Anhalt",
    "wof:name":"Holm Schreiber",
    "wof:placetype":"venue"
},
  "geometry": {"coordinates":[11.6343431473,52.1537971497],"type":"Point"}
}