{
  "type": "Feature",
  "properties": {
    "iso:country":"DE",
    "sg:address":"Saarbr\u00fccker Str. 66",
    "sg:city":"Friedrichsthal",
    "sg:phone":"+49 6897/89153",
    "sg:postcode":"66299",
    "sg:province":"Saarland",
    "wof:name":"Erich Hey",
    "wof:placetype":"venue"
},
  "geometry": {"coordinates":[7.089145,49.32082],"type":"Point"}
}