{
  "type": "Feature",
  "properties": {
    "iso:country":"DE",
    "sg:address":"Buchbergblick 24",
    "sg:city":"Langenselbold",
    "sg:phone":"+49 6184/900525",
    "sg:postcode":"63505",
    "sg:province":"Hessen",
    "wof:name":"Vfi Immobilien Gmbh",
    "wof:placetype":"venue"
},
  "geometry": {"coordinates":[9.0552949905,50.1808547974],"type":"Point"}
}