{
  "type": "Feature",
  "properties": {
    "iso:country":"DE",
    "sg:address":"Saturnweg 7",
    "sg:city":"Minden",
    "sg:phone":"+49 571/5084934",
    "sg:postcode":"32427",
    "sg:province":"Nordrhein-Westfalen",
    "wof:name":"Domo Sano Ambulanter Pflegedienst",
    "wof:placetype":"venue"
},
  "geometry": {"coordinates":[8.864479,52.293903],"type":"Point"}
}