{
  "type": "Feature",
  "properties": {
    "iso:country":"DE",
    "sg:address":"Emschestr. 38",
    "sg:city":"Hattingen",
    "sg:phone":"+49 2324/22977",
    "sg:postcode":"45525",
    "sg:province":"Nordrhein-Westfalen",
    "wof:name":"Wilh. Backhaus",
    "wof:placetype":"venue"
},
  "geometry": {"coordinates":[7.185845,51.398468],"type":"Point"}
}