{
  "type": "Feature",
  "properties": {
    "iso:country":"DE",
    "sg:address":"Bokelstr. 10",
    "sg:city":"Bielefeld",
    "sg:postcode":"33649",
    "sg:province":"Nordrhein-Westfalen",
    "wof:name":"Gewerbepark Langenfeld West Kg",
    "wof:placetype":"venue"
},
  "geometry": {"coordinates":[8.4559793472,51.9626312256],"type":"Point"}
}