{
  "type": "Feature",
  "properties": {
    "iso:country":"DE",
    "sg:address":"Heckelbeckstr. 18",
    "sg:city":"Dortmund",
    "sg:phone":"+49 231/673267",
    "sg:postcode":"44379",
    "sg:province":"Nordrhein-Westfalen",
    "wof:name":"Rudolf Sprengepiel",
    "wof:placetype":"venue"
},
  "geometry": {"coordinates":[7.36515,51.52673],"type":"Point"}
}