{
  "type": "Feature",
  "properties": {
    "iso:country":"DE",
    "sg:address":"Pionierstr. 135",
    "sg:city":"Emmerich",
    "sg:phone":"+49 2822/6940347",
    "sg:postcode":"46446",
    "sg:province":"Nordrhein-Westfalen",
    "wof:name":"Rolf Vedder",
    "wof:placetype":"venue"
},
  "geometry": {"coordinates":[6.316915,51.814171],"type":"Point"}
}