{
  "type": "Feature",
  "properties": {
    "iso:country":"DE",
    "sg:address":"Lessingstr. 2B",
    "sg:city":"L\u00f6\u00dfnitz",
    "sg:postcode":"08294",
    "sg:province":"Sachsen",
    "wof:name":"Kress Gmbh & Co. Kg",
    "wof:placetype":"venue"
},
  "geometry": {"coordinates":[12.7169866562,50.610244751],"type":"Point"}
}