{
  "type": "Feature",
  "properties": {
    "iso:country":"DE",
    "sg:address":"Hoher Weg 7",
    "sg:city":"Stendal",
    "sg:phone":"+49 3931/715544",
    "sg:postcode":"39576",
    "sg:province":"Sachsen-Anhalt",
    "wof:name":"Toilettenvermietung Kerkow",
    "wof:placetype":"venue"
},
  "geometry": {"coordinates":[11.8797969818,52.5911178589],"type":"Point"}
}