{
  "type": "Feature",
  "properties": {
    "iso:country":"DE",
    "sg:address":"Jahnstr. 32",
    "sg:city":"Kaarst",
    "sg:phone":"+49 2131/666139",
    "sg:postcode":"41564",
    "sg:province":"Nordrhein-Westfalen",
    "wof:name":"Klaus Koloska",
    "wof:placetype":"venue"
},
  "geometry": {"coordinates":[6.6087379456,51.2312431335],"type":"Point"}
}