{
  "type": "Feature",
  "properties": {
    "iso:country":"DE",
    "sg:address":"R\u00f6thgener Str. 12",
    "sg:city":"Eschweiler",
    "sg:phone":"+49 2403/4488",
    "sg:postcode":"52249",
    "sg:province":"Nordrhein-Westfalen",
    "wof:name":"Verba Gmbh",
    "wof:placetype":"venue"
},
  "geometry": {"coordinates":[6.2584118843,50.8152542114],"type":"Point"}
}