{
  "type": "Feature",
  "properties": {
    "iso:country":"DE",
    "sg:address":"Sachsenhausener Str. 28",
    "sg:city":"Oranienburg",
    "sg:phone":"+49 3301/809855",
    "sg:postcode":"16515",
    "sg:province":"Brandenburg",
    "wof:name":"Mediengesellschaft Mbh",
    "wof:placetype":"venue"
},
  "geometry": {"coordinates":[13.2431840897,52.7606658936],"type":"Point"}
}