{
  "type": "Feature",
  "properties": {
    "iso:country":"DE",
    "sg:address":"Am Stempel 6",
    "sg:city":"Gro\u00dfenl\u00fcder",
    "sg:phone":"+49 6648/8800",
    "sg:postcode":"36137",
    "sg:province":"Hessen",
    "wof:name":"K. Und A. Dietz",
    "wof:placetype":"venue"
},
  "geometry": {"coordinates":[9.5043296814,50.5890426636],"type":"Point"}
}