{
  "type": "Feature",
  "properties": {
    "iso:country":"DE",
    "sg:address":"Dorfstr. 70",
    "sg:city":"Kummerfeld",
    "sg:phone":"+49 4101/75081",
    "sg:postcode":"25495",
    "sg:province":"Schleswig-Holstein",
    "wof:name":"E. Hachmann",
    "wof:placetype":"venue"
},
  "geometry": {"coordinates":[9.7926368713,53.6992988586],"type":"Point"}
}