{
  "type": "Feature",
  "properties": {
    "iso:country":"DE",
    "sg:address":"Hans-Sachs-Str. 23",
    "sg:city":"Duisburg",
    "sg:phone":"+49 203/551611",
    "sg:postcode":"47166",
    "sg:province":"Nordrhein-Westfalen",
    "wof:name":"Big Nothing Gmbh",
    "wof:placetype":"venue"
},
  "geometry": {"coordinates":[6.7725691795,51.4990005493],"type":"Point"}
}