{
  "type": "Feature",
  "properties": {
    "iso:country":"DE",
    "sg:address":"Neustadt 73",
    "sg:city":"Greu\u00dfen",
    "sg:postcode":"99718",
    "sg:province":"Th\u00fcringen",
    "wof:name":"Mtk Systemhaus F\u00fcr Kommunikationstechnik Gmbh",
    "wof:placetype":"venue"
},
  "geometry": {"coordinates":[10.946813,51.231369],"type":"Point"}
}