{
  "type": "Feature",
  "properties": {
    "iso:country":"DE",
    "sg:address":"Grasm\u00fcckenweg 3",
    "sg:city":"Augsburg",
    "sg:phone":"+49 821/92771",
    "sg:postcode":"86199",
    "sg:province":"Bayern",
    "wof:name":"Gottlieb Adolf",
    "wof:placetype":"venue"
},
  "geometry": {"coordinates":[10.820645,48.324001],"type":"Point"}
}