{
  "type": "Feature",
  "properties": {
    "iso:country":"DE",
    "sg:address":"Hauptstr. 59",
    "sg:city":"Wiedersbach",
    "sg:phone":"+49 36878/60255",
    "sg:postcode":"98667",
    "sg:province":"Th\u00fcringen",
    "wof:name":"Tannenst\u00fcbchen",
    "wof:placetype":"venue"
},
  "geometry": {"coordinates":[10.8002920151,50.4763793945],"type":"Point"}
}