{
  "type": "Feature",
  "properties": {
    "iso:country":"DE",
    "sg:address":"Carl-Bertelsmann-Str. 105",
    "sg:city":"G\u00fctersloh",
    "sg:phone":"+49 5241/863838",
    "sg:postcode":"33332",
    "sg:province":"Nordrhein-Westfalen",
    "wof:name":"Redaktion Wir Bertelsmann Lexikothek",
    "wof:placetype":"venue"
},
  "geometry": {"coordinates":[8.3997125626,51.9051971436],"type":"Point"}
}