{
  "type": "Feature",
  "properties": {
    "iso:country":"DE",
    "sg:address":"Julius-Leber-Str. 19",
    "sg:city":"Bergkamen",
    "sg:postcode":"59192",
    "sg:province":"Nordrhein-Westfalen",
    "wof:name":"Dino-tec Gmbh",
    "wof:placetype":"venue"
},
  "geometry": {"coordinates":[7.6450271606,51.6149482727],"type":"Point"}
}