{
  "type": "Feature",
  "properties": {
    "iso:country":"DE",
    "sg:address":"Wilhelm-B\u00f6ttiger-Str. 5",
    "sg:city":"Biebesheim",
    "sg:phone":"+49 6258/6263",
    "sg:postcode":"64584",
    "sg:province":"Hessen",
    "wof:name":"Gebr. B\u00f6ttiger",
    "wof:placetype":"venue"
},
  "geometry": {"coordinates":[8.46497,49.779655],"type":"Point"}
}