{
  "type": "Feature",
  "properties": {
    "iso:country":"DE",
    "sg:address":"August-Bebel-Str. 135",
    "sg:city":"Bielefeld",
    "sg:postcode":"33602",
    "sg:province":"Nordrhein-Westfalen",
    "wof:name":"Jugendg\u00e4stehaus Und Bildungs- Zentrum Bielefeld Ggmbh",
    "wof:placetype":"venue"
},
  "geometry": {"coordinates":[8.5399255753,52.0196266174],"type":"Point"}
}