{
  "type": "Feature",
  "properties": {
    "iso:country":"DE",
    "sg:address":"Hamburger Str. 148",
    "sg:city":"Hamburg",
    "sg:phone":"+49 40/240747",
    "sg:postcode":"22083",
    "sg:province":"Hamburg",
    "wof:name":"Tri Uni Trading Corporation Gmbh",
    "wof:placetype":"venue"
},
  "geometry": {"coordinates":[10.037530899,53.5761108398],"type":"Point"}
}