{
  "type": "Feature",
  "properties": {
    "iso:country":"DE",
    "sg:address":"Kirchenstr. 10",
    "sg:city":"Elmshorn",
    "sg:phone":"+49 4121/20926",
    "sg:postcode":"25335",
    "sg:province":"Schleswig-Holstein",
    "wof:name":"Bettina Wichelmann",
    "wof:placetype":"venue"
},
  "geometry": {"coordinates":[9.6527843475,53.7541847229],"type":"Point"}
}