{
  "type": "Feature",
  "properties": {
    "iso:country":"DE",
    "sg:address":"Ringstr. 56 a",
    "sg:city":"Remscheid",
    "sg:phone":"+49 2191/62519",
    "sg:postcode":"42897",
    "sg:province":"Nordrhein-Westfalen",
    "wof:name":"Aral Ag",
    "wof:placetype":"venue"
},
  "geometry": {"coordinates":[7.2604470253,51.1855239868],"type":"Point"}
}