{
  "type": "Feature",
  "properties": {
    "iso:country":"DE",
    "sg:address":"Widenmayerstr. 32",
    "sg:city":"M\u00fcnchen",
    "sg:postcode":"80538",
    "sg:province":"Bayern",
    "wof:name":"Greco E.v. Groupment European Pour",
    "wof:placetype":"venue"
},
  "geometry": {"coordinates":[11.5950651169,48.1442222595],"type":"Point"}
}