{
  "type": "Feature",
  "properties": {
    "iso:country":"DE",
    "sg:address":"Wilhelm-Maybachstra\u00dfe 7",
    "sg:city":"Krauchenwies",
    "sg:phone":"+49 7576/92174",
    "sg:postcode":"72505",
    "sg:province":"Baden-W\u00fcrttemberg",
    "wof:name":"Weizenegger Werkzeugbau",
    "wof:placetype":"venue"
},
  "geometry": {"coordinates":[9.236751,48.016006],"type":"Point"}
}