{
  "type": "Feature",
  "properties": {
    "iso:country":"DE",
    "sg:address":"Industriestr. 7",
    "sg:city":"Herzogenrath",
    "sg:phone":"+49 2407/2064",
    "sg:postcode":"52134",
    "sg:province":"Nordrhein-Westfalen",
    "wof:name":"Friedrich Debus Maschinenbau",
    "wof:placetype":"venue"
},
  "geometry": {"coordinates":[6.0788378716,50.8338394165],"type":"Point"}
}