{
  "type": "Feature",
  "properties": {
    "iso:country":"DE",
    "sg:address":"Br\u00fcckenstr. 28",
    "sg:city":"Modautal",
    "sg:postcode":"64397",
    "sg:province":"Hessen",
    "wof:name":"In Mind Innovative Medien Gmbh",
    "wof:placetype":"venue"
},
  "geometry": {"coordinates":[8.772202,49.77739],"type":"Point"}
}