{
  "type": "Feature",
  "properties": {
    "iso:country":"DE",
    "sg:address":"Wilhelm-Blos-Str. 59",
    "sg:city":"Stuttgart",
    "sg:phone":"+49 711/250010",
    "sg:postcode":"70191",
    "sg:province":"Baden-W\u00fcrttemberg",
    "wof:name":"Bau- Und Heimst\u00e4ttenverein Stuttgart Eg",
    "wof:placetype":"venue"
},
  "geometry": {"coordinates":[9.1817932129,48.802280426],"type":"Point"}
}