{
  "type": "Feature",
  "properties": {
    "iso:country":"DE",
    "sg:address":"Pariciusstr. 17",
    "sg:city":"Regensburg",
    "sg:phone":"+49 941/21171",
    "sg:postcode":"93049",
    "sg:province":"Bayern",
    "wof:name":"Isabella Joachimsthaler-ruf Architektin",
    "wof:placetype":"venue"
},
  "geometry": {"coordinates":[12.072305,49.022476],"type":"Point"}
}