{
  "type": "Feature",
  "properties": {
    "iso:country":"DE",
    "sg:address":"Grafenberger Allee 358a",
    "sg:city":"D\u00fcsseldorf",
    "sg:phone":"+49 211/665343",
    "sg:postcode":"40235",
    "sg:province":"Nordrhein-Westfalen",
    "wof:name":"Rosengarten",
    "wof:placetype":"venue"
},
  "geometry": {"coordinates":[6.823622,51.239635],"type":"Point"}
}