{
  "type": "Feature",
  "properties": {
    "iso:country":"DE",
    "sg:address":"Hornschuchallee 19",
    "sg:city":"Forchheim",
    "sg:phone":"+49 9191/729272",
    "sg:postcode":"91301",
    "sg:province":"Bayern",
    "wof:name":"Helena Schwarzmann Melitta Schwarzmann",
    "wof:placetype":"venue"
},
  "geometry": {"coordinates":[11.0603504181,49.7200965881],"type":"Point"}
}