{
  "type": "Feature",
  "properties": {
    "iso:country":"DE",
    "sg:address":"Bahnhofstr. 54",
    "sg:city":"Neuhausen",
    "sg:phone":"+49 7158/8210",
    "sg:postcode":"73765",
    "sg:province":"Baden-W\u00fcrttemberg",
    "wof:name":"Pf\u00e4ffle Grundst\u00fccks- Verwertungs Gmbh & Co. Kg",
    "wof:placetype":"venue"
},
  "geometry": {"coordinates":[9.2727127075,48.6841812134],"type":"Point"}
}