{
  "type": "Feature",
  "properties": {
    "iso:country":"DE",
    "sg:address":"Untere Halde 10",
    "sg:city":"Untereisesheim",
    "sg:postcode":"74257",
    "sg:province":"Baden-W\u00fcrttemberg",
    "wof:name":"Carife Verwaltungs Gmbh",
    "wof:placetype":"venue"
},
  "geometry": {"coordinates":[9.2028064728,49.2141456604],"type":"Point"}
}