{
  "type": "Feature",
  "properties": {
    "iso:country":"DE",
    "sg:address":"Von-Einem-Str. 11",
    "sg:city":"Essen",
    "sg:postcode":"45130",
    "sg:province":"Nordrhein-Westfalen",
    "wof:name":"Calpam Mineral\u00f6lhandel Verwaltungsges. Mbh",
    "wof:placetype":"venue"
},
  "geometry": {"coordinates":[7.0198140144,51.4405403137],"type":"Point"}
}