{
  "type": "Feature",
  "properties": {
    "iso:country":"DE",
    "sg:address":"Rastenburger Str. 7",
    "sg:city":"Peine",
    "sg:phone":"+49 5171/81088",
    "sg:postcode":"31226",
    "sg:province":"Niedersachsen",
    "wof:name":"Sansteel Trading Gmbh",
    "wof:placetype":"venue"
},
  "geometry": {"coordinates":[10.2631702423,52.2953529358],"type":"Point"}
}