{
  "type": "Feature",
  "properties": {
    "iso:country":"DE",
    "sg:address":"Saarstra\u00dfe 2",
    "sg:city":"Wallerfangen",
    "sg:phone":"+49 6831/62163",
    "sg:postcode":"66798",
    "sg:province":"Saarland",
    "wof:name":"Dres. Med. Dick Und Dutt",
    "wof:placetype":"venue"
},
  "geometry": {"coordinates":[6.716379,49.330666],"type":"Point"}
}