{
  "type": "Feature",
  "properties": {
    "iso:country":"DE",
    "sg:address":"Kufsteiner Str. 94",
    "sg:city":"Rosenheim",
    "sg:postcode":"83026",
    "sg:province":"Bayern",
    "wof:name":"M\u00f6bel-fabrikverkauf Gerwald B\u00e4r",
    "wof:placetype":"venue"
},
  "geometry": {"coordinates":[12.1235599518,47.8432579041],"type":"Point"}
}