{
  "type": "Feature",
  "properties": {
    "iso:country":"DE",
    "sg:address":"Weimarische Str. 10",
    "sg:city":"Eisenach",
    "sg:phone":"+49 3691/75025",
    "sg:postcode":"99817",
    "sg:province":"Th\u00fcringen",
    "wof:name":"Helmut Kieselbach",
    "wof:placetype":"venue"
},
  "geometry": {"coordinates":[10.343369,50.973331],"type":"Point"}
}