{
  "type": "Feature",
  "properties": {
    "iso:country":"DE",
    "sg:address":"Am Friedeholz 5",
    "sg:city":"Syke",
    "sg:phone":"+49 4242/2784",
    "sg:postcode":"28857",
    "sg:province":"Niedersachsen",
    "wof:name":"Inge Butzlaff",
    "wof:placetype":"venue"
},
  "geometry": {"coordinates":[8.8357067108,52.9153938293],"type":"Point"}
}