{
  "type": "Feature",
  "properties": {
    "iso:country":"DE",
    "sg:address":"Hinterm Rhaden 6",
    "sg:city":"Edewecht",
    "sg:phone":"+49 4405/99880",
    "sg:postcode":"26188",
    "sg:province":"Niedersachsen",
    "wof:name":"Wiechmann Ketten- Und Kettenr\u00e4derbau Gmbh",
    "wof:placetype":"venue"
},
  "geometry": {"coordinates":[8.036765,53.124256],"type":"Point"}
}