{
  "type": "Feature",
  "properties": {
    "iso:country":"DE",
    "sg:address":"St\u00f6hrer Str. 6",
    "sg:city":"Leipzig",
    "sg:phone":"+49 4934/1244080",
    "sg:postcode":"04347",
    "sg:province":"Sachsen",
    "wof:name":"Achilles Papierveredlung Gmbh",
    "wof:placetype":"venue"
},
  "geometry": {"coordinates":[12.425786972,51.3657035828],"type":"Point"}
}