{
  "type": "Feature",
  "properties": {
    "iso:country":"DE",
    "sg:address":"Waldenburger Str. 42",
    "sg:city":"Hamburg",
    "sg:phone":"+49 40/6546429",
    "sg:postcode":"22045",
    "sg:province":"Hamburg",
    "wof:name":"J. Hlozek",
    "wof:placetype":"venue"
},
  "geometry": {"coordinates":[10.142251,53.577179],"type":"Point"}
}