{
  "type": "Feature",
  "properties": {
    "iso:country":"DE",
    "sg:address":"W\u00fcstemser Weg 33",
    "sg:city":"Waldems",
    "sg:phone":"+49 6087/2313",
    "sg:postcode":"65529",
    "sg:province":"Hessen",
    "wof:name":"Helmut Kopp",
    "wof:placetype":"venue"
},
  "geometry": {"coordinates":[8.3790102005,50.2714538574],"type":"Point"}
}