{
  "type": "Feature",
  "properties": {
    "iso:country":"DE",
    "sg:address":"Jahnstr. 12",
    "sg:city":"M\u00fcnster-Sarmsheim",
    "sg:phone":"+49 6721/43537",
    "sg:postcode":"55424",
    "sg:province":"Rheinland-Pfalz",
    "wof:name":"M. Benje",
    "wof:placetype":"venue"
},
  "geometry": {"coordinates":[7.893242,49.941494],"type":"Point"}
}