{
  "type": "Feature",
  "properties": {
    "iso:country":"DE",
    "sg:address":"Schl\u00fcterstr. 29",
    "sg:city":"Dresden",
    "sg:phone":"+49 351/31920",
    "sg:postcode":"01277",
    "sg:province":"Sachsen",
    "wof:name":"Heine Fenster Und T\u00fcren Gmbh",
    "wof:placetype":"venue"
},
  "geometry": {"coordinates":[13.792131,51.039402],"type":"Point"}
}