{
  "type": "Feature",
  "properties": {
    "iso:country":"DE",
    "sg:address":"Markt 10",
    "sg:city":"Oestrich-Winkel",
    "sg:postcode":"65375",
    "sg:province":"Hessen",
    "wof:name":"Aiticon Gmbh",
    "wof:placetype":"venue"
},
  "geometry": {"coordinates":[8.030213,50.004871],"type":"Point"}
}