{
  "type": "Feature",
  "properties": {
    "iso:country":"DE",
    "sg:address":"Bismarckallee 26",
    "sg:city":"Berlin",
    "sg:phone":"+49 30/89500250",
    "sg:postcode":"14193",
    "sg:province":"Berlin",
    "wof:name":"H & E Elektro- Installations Gmbh",
    "wof:placetype":"venue"
},
  "geometry": {"coordinates":[13.275204,52.485931],"type":"Point"}
}