{
  "type": "Feature",
  "properties": {
    "iso:country":"DE",
    "sg:address":"H\u00f6herweg 282h",
    "sg:city":"D\u00fcsseldorf",
    "sg:phone":"+49 211/7338772",
    "sg:postcode":"40231",
    "sg:province":"Nordrhein-Westfalen",
    "wof:name":"A. Hetterle",
    "wof:placetype":"venue"
},
  "geometry": {"coordinates":[6.8301649094,51.2216033936],"type":"Point"}
}