{
  "type": "Feature",
  "properties": {
    "iso:country":"DE",
    "sg:address":"Gundersreuth 13",
    "sg:city":"Mainleus",
    "sg:phone":"+49 9229/326",
    "sg:postcode":"95336",
    "sg:province":"Bayern",
    "wof:name":"Gasthaus Schr\u00f6der",
    "wof:placetype":"venue"
},
  "geometry": {"coordinates":[11.3642044067,50.0760612488],"type":"Point"}
}