{
  "type": "Feature",
  "properties": {
    "iso:country":"DE",
    "sg:address":"Hauptstr. 54",
    "sg:city":"Ladenburg",
    "sg:phone":"+49 6203/13520",
    "sg:postcode":"68526",
    "sg:province":"Baden-W\u00fcrttemberg",
    "wof:name":"Albert Friedrich Elektroinstallation",
    "wof:placetype":"venue"
},
  "geometry": {"coordinates":[8.612189,49.472591],"type":"Point"}
}