{
  "type": "Feature",
  "properties": {
    "iso:country":"DE",
    "sg:address":"Talstr. 23",
    "sg:city":"D\u00fcsseldorf",
    "sg:phone":"+49 4921/1376657",
    "sg:postcode":"40217",
    "sg:province":"Nordrhein-Westfalen",
    "wof:name":"Heinz Remong Orthopaedie-technik Gmbh",
    "wof:placetype":"venue"
},
  "geometry": {"coordinates":[6.7785401344,51.2160453796],"type":"Point"}
}