{
  "type": "Feature",
  "properties": {
    "iso:country":"DE",
    "sg:address":"Hauptstr. 80",
    "sg:city":"Rattelsdorf",
    "sg:phone":"+49 9547/1712",
    "sg:postcode":"96179",
    "sg:province":"Bayern",
    "wof:name":"Andreas F\u00f6rster",
    "wof:placetype":"venue"
},
  "geometry": {"coordinates":[10.8844537735,50.0142555237],"type":"Point"}
}