{
  "type": "Feature",
  "properties": {
    "iso:country":"DE",
    "sg:address":"Seeburger Str. 8",
    "sg:city":"Berlin",
    "sg:phone":"+49 30/3632230",
    "sg:postcode":"13581",
    "sg:province":"Berlin",
    "wof:name":"Digenta Liegenschaften Gmbh",
    "wof:placetype":"venue"
},
  "geometry": {"coordinates":[13.1919031143,52.528678894],"type":"Point"}
}