{
  "type": "Feature",
  "properties": {
    "iso:country":"DE",
    "sg:address":"Am Klafelder Markt 11",
    "sg:city":"Siegen",
    "sg:phone":"+49 271/81260",
    "sg:postcode":"57078",
    "sg:province":"Nordrhein-Westfalen",
    "wof:name":"Friedhelm Hillenbach Obst- Gem\u00fcse- Und S\u00fcd-",
    "wof:placetype":"venue"
},
  "geometry": {"coordinates":[8.0098152161,50.9144554138],"type":"Point"}
}