{
  "type": "Feature",
  "properties": {
    "iso:country":"DE",
    "sg:address":"Max-Planck-Str. 4",
    "sg:city":"Villingen-Schwenningen",
    "sg:phone":"+49 7721/20276",
    "sg:postcode":"78052",
    "sg:province":"Baden-W\u00fcrttemberg",
    "wof:name":"Eas Elektrische Anlagen Sicherheitstechnik Gmbh",
    "wof:placetype":"venue"
},
  "geometry": {"coordinates":[8.4498167038,48.0786552429],"type":"Point"}
}