{
  "type": "Feature",
  "properties": {
    "iso:country":"DE",
    "sg:address":"Am Sonnenhang 40",
    "sg:city":"Siegburg",
    "sg:phone":"+49 2246/6161",
    "sg:postcode":"53721",
    "sg:province":"Nordrhein-Westfalen",
    "wof:name":"Sowka Ingenieur",
    "wof:placetype":"venue"
},
  "geometry": {"coordinates":[7.2562642097,50.8075828552],"type":"Point"}
}