{
  "type": "Feature",
  "properties": {
    "iso:country":"DE",
    "sg:address":"Trauchbergstr. 6",
    "sg:city":"M\u00fcnchen",
    "sg:phone":"+49 89/696069",
    "sg:postcode":"81539",
    "sg:province":"Bayern",
    "wof:name":"Alfred Riedel",
    "wof:placetype":"venue"
},
  "geometry": {"coordinates":[11.59123,48.10902],"type":"Point"}
}