{
  "type": "Feature",
  "properties": {
    "iso:country":"DE",
    "sg:address":"Haidrath 5",
    "sg:city":"Wohltorf",
    "sg:phone":"+49 4104/97160",
    "sg:postcode":"21521",
    "sg:province":"Schleswig-Holstein",
    "wof:name":"W Und W Versicherungsmarkler Walter Frerichs",
    "wof:placetype":"venue"
},
  "geometry": {"coordinates":[10.2957248688,53.5194206238],"type":"Point"}
}