{
  "type": "Feature",
  "properties": {
    "iso:country":"DE",
    "sg:address":"Schillerstr. 1",
    "sg:city":"K\u00f6nigstein",
    "sg:phone":"+49 6174/932830",
    "sg:postcode":"61462",
    "sg:province":"Hessen",
    "wof:name":"Intact Bad-service Gmbh",
    "wof:placetype":"venue"
},
  "geometry": {"coordinates":[8.464183,50.174335],"type":"Point"}
}