{
  "type": "Feature",
  "properties": {
    "iso:country":"DE",
    "sg:address":"Am Parkplatz 8",
    "sg:city":"Ostseebad Rerik",
    "sg:phone":"+49 38296/78452",
    "sg:postcode":"18230",
    "sg:province":"Mecklenburg-Vorpommern",
    "wof:name":"A. Lippelt",
    "wof:placetype":"venue"
},
  "geometry": {"coordinates":[11.6140651703,54.1058616638],"type":"Point"}
}