{
  "type": "Feature",
  "properties": {
    "iso:country":"DE",
    "sg:address":"Lebacher Str. 102",
    "sg:city":"Saarlouis",
    "sg:phone":"+49 6831/80239",
    "sg:postcode":"66740",
    "sg:province":"Saarland",
    "wof:name":"P. Mayer",
    "wof:placetype":"venue"
},
  "geometry": {"coordinates":[6.770138,49.327881],"type":"Point"}
}