{
  "type": "Feature",
  "properties": {
    "iso:country":"DE",
    "sg:address":"Baustr. 21",
    "sg:city":"Hameln",
    "sg:phone":"+49 5151/29402",
    "sg:postcode":"31785",
    "sg:province":"Niedersachsen",
    "wof:name":"Imbi\u00df Santorin",
    "wof:placetype":"venue"
},
  "geometry": {"coordinates":[9.3592185974,52.1059989929],"type":"Point"}
}