{
  "type": "Feature",
  "properties": {
    "iso:country":"DE",
    "sg:address":"Im Nordfeld 43",
    "sg:city":"Iserlohn",
    "sg:phone":"+49 2374",
    "sg:postcode":"58642",
    "sg:province":"Nordrhein-Westfalen",
    "wof:name":"B\u00fcroeinrichtungen Dembski - B\u00fcro, B\u00fcrom\u00f6bel, Schra",
    "wof:placetype":"venue"
},
  "geometry": {"coordinates":[7.601586,51.368893],"type":"Point"}
}