{
  "type": "Feature",
  "properties": {
    "iso:country":"DE",
    "sg:address":"Meybeswall 20",
    "sg:city":"Gehrde",
    "sg:phone":"+49 5439/2917",
    "sg:postcode":"49596",
    "sg:province":"Niedersachsen",
    "wof:name":"Reinhard Wyduba",
    "wof:placetype":"venue"
},
  "geometry": {"coordinates":[7.997837,52.558449],"type":"Point"}
}