{
  "type": "Feature",
  "properties": {
    "iso:country":"DE",
    "sg:address":"Pfauengasse 11",
    "sg:city":"Ulm",
    "sg:phone":"+49 731/64740",
    "sg:postcode":"89073",
    "sg:province":"Baden-W\u00fcrttemberg",
    "wof:name":"Brillen Wilhelm Gmbh",
    "wof:placetype":"venue"
},
  "geometry": {"coordinates":[9.9896268845,48.3990592957],"type":"Point"}
}