{
  "type": "Feature",
  "properties": {
    "iso:country":"DE",
    "sg:address":"Friesenstr. 1",
    "sg:city":"Euskirchen",
    "sg:phone":"+49 2251/780790",
    "sg:postcode":"53881",
    "sg:province":"Nordrhein-Westfalen",
    "wof:name":"Pritzl & Scholz Maler Gmbh",
    "wof:placetype":"venue"
},
  "geometry": {"coordinates":[6.840115,50.658249],"type":"Point"}
}