{
  "type": "Feature",
  "properties": {
    "iso:country":"DE",
    "sg:address":"Am Konradsheimer Weg 1",
    "sg:city":"Erftstadt",
    "sg:phone":"+49 2235/74565",
    "sg:postcode":"50374",
    "sg:province":"Nordrhein-Westfalen",
    "wof:name":"Richartz & Schiffer Gmbh",
    "wof:placetype":"venue"
},
  "geometry": {"coordinates":[6.798739,50.793842],"type":"Point"}
}