{
  "type": "Feature",
  "properties": {
    "iso:country":"DE",
    "sg:address":"Kupferstr. 14",
    "sg:city":"Wildeck",
    "sg:phone":"+49 6626/582",
    "sg:postcode":"36208",
    "sg:province":"Hessen",
    "wof:name":"Hotel Th\u00fcringer Hof",
    "wof:placetype":"venue"
},
  "geometry": {"coordinates":[10.007818222,50.9769668579],"type":"Point"}
}