{
  "type": "Feature",
  "properties": {
    "iso:country":"DE",
    "sg:address":"Schubertweg 1",
    "sg:city":"Aldingen",
    "sg:phone":"+49 7424/8238",
    "sg:postcode":"78554",
    "sg:province":"Baden-W\u00fcrttemberg",
    "wof:name":"K. Bitsch",
    "wof:placetype":"venue"
},
  "geometry": {"coordinates":[8.709294,48.091759],"type":"Point"}
}