{
  "type": "Feature",
  "properties": {
    "iso:country":"DE",
    "sg:address":"Reichenberger Str. 32",
    "sg:city":"Stuttgart",
    "sg:phone":"+49 711/7227732",
    "sg:postcode":"70567",
    "sg:province":"Baden-W\u00fcrttemberg",
    "wof:name":"Werner Vielhauer",
    "wof:placetype":"venue"
},
  "geometry": {"coordinates":[9.1578416824,48.7294006348],"type":"Point"}
}