{
  "type": "Feature",
  "properties": {
    "iso:country":"DE",
    "sg:address":"Baumarktstr. 8 A",
    "sg:city":"Garbsen",
    "sg:phone":"+49 5137/77940",
    "sg:postcode":"30823",
    "sg:province":"Niedersachsen",
    "wof:name":"Dr. Dirk Gerisch Tierarzt",
    "wof:placetype":"venue"
},
  "geometry": {"coordinates":[9.5862178802,52.4228591919],"type":"Point"}
}