{
  "type": "Feature",
  "properties": {
    "iso:country":"DE",
    "sg:address":"Otto-Weltzin-Str.7",
    "sg:city":"Schwerin",
    "sg:phone":"+49 4938/5646110",
    "sg:postcode":"19061",
    "sg:province":"Mecklenburg-Vorpommern",
    "wof:name":"Wibau-haustechnik Gmbh & Co. Kg",
    "wof:placetype":"venue"
},
  "geometry": {"coordinates":[11.43275,53.6035],"type":"Point"}
}