{
  "type": "Feature",
  "properties": {
    "iso:country":"DE",
    "sg:address":"Eggenstein",
    "sg:city":"Eggenstein Leopoldshafen",
    "sg:phone":"+49 4972/1782269",
    "sg:postcode":"76344",
    "sg:province":"Baden-W\u00fcrttemberg",
    "wof:name":"Bezirkssparkasse Graben-neudorf",
    "wof:placetype":"venue"
},
  "geometry": {"coordinates":[8.4045,49.09655],"type":"Point"}
}