{
  "type": "Feature",
  "properties": {
    "iso:country":"DE",
    "sg:address":"Am Bildstock 12",
    "sg:city":"B\u00fcrstadt",
    "sg:phone":"+49 6206/8475",
    "sg:postcode":"68642",
    "sg:province":"Hessen",
    "wof:name":"Ernst Zerhau",
    "wof:placetype":"venue"
},
  "geometry": {"coordinates":[8.462967,49.640438],"type":"Point"}
}