{
  "type": "Feature",
  "properties": {
    "iso:country":"DE",
    "sg:address":"Ritscher Deichstr. 1",
    "sg:city":"Drochtersen",
    "sg:phone":"+49 4148/5060",
    "sg:postcode":"21706",
    "sg:province":"Niedersachsen",
    "wof:name":"A. Tietz Und M. Brudermann",
    "wof:placetype":"venue"
},
  "geometry": {"coordinates":[9.422786,53.696815],"type":"Point"}
}