{
  "type": "Feature",
  "properties": {
    "iso:country":"DE",
    "sg:address":"Alte-Uslarer-Str. 19d",
    "sg:city":"Hardegsen",
    "sg:phone":"+49 5505/5467",
    "sg:postcode":"37181",
    "sg:province":"Niedersachsen",
    "wof:name":"Horst Frische Ingenieur",
    "wof:placetype":"venue"
},
  "geometry": {"coordinates":[9.8219766617,51.6504707336],"type":"Point"}
}