{
  "type": "Feature",
  "properties": {
    "iso:country":"DE",
    "sg:address":"Oerweg 8",
    "sg:city":"Recklinghausen",
    "sg:phone":"+49 2361/24833",
    "sg:postcode":"45657",
    "sg:province":"Nordrhein-Westfalen",
    "wof:name":"Elektro Blumberg Inh. Thomas Kluwe",
    "wof:placetype":"venue"
},
  "geometry": {"coordinates":[7.201856,51.618313],"type":"Point"}
}