{
  "type": "Feature",
  "properties": {
    "iso:country":"DE",
    "sg:address":"Die Reihe 26",
    "sg:city":"Rinteln",
    "sg:phone":"+49 5751/3922",
    "sg:postcode":"31737",
    "sg:province":"Niedersachsen",
    "wof:name":"Kaiser-repro Gmbh",
    "wof:placetype":"venue"
},
  "geometry": {"coordinates":[9.0355272293,52.1645393372],"type":"Point"}
}