{
  "type": "Feature",
  "properties": {
    "iso:country":"DE",
    "sg:address":"Schulerhofstr. 16",
    "sg:city":"Winnenden",
    "sg:phone":"+49 7195/72633",
    "sg:postcode":"71364",
    "sg:province":"Baden-W\u00fcrttemberg",
    "wof:name":"Schulerhof-st\u00fcble",
    "wof:placetype":"venue"
},
  "geometry": {"coordinates":[9.443821907,48.8790512085],"type":"Point"}
}