{
  "type": "Feature",
  "properties": {
    "iso:country":"DE",
    "sg:address":"Dortustra\u00dfe 68a",
    "sg:city":"Potsdam",
    "sg:phone":"+49 331/2800464",
    "sg:postcode":"14467",
    "sg:province":"Brandenburg",
    "wof:name":"Dg Bank Deutsche Genossenschaftsban",
    "wof:placetype":"venue"
},
  "geometry": {"coordinates":[13.053944,52.401691],"type":"Point"}
}