{
  "type": "Feature",
  "properties": {
    "iso:country":"DE",
    "sg:address":"Hebelstr. 2",
    "sg:city":"M\u00fcllheim",
    "sg:phone":"+49 7631/8254",
    "sg:postcode":"79379",
    "sg:province":"Baden-W\u00fcrttemberg",
    "wof:name":"Psycho-soz. Beratungsstelle Des. Badischen Landesv. Frbg.",
    "wof:placetype":"venue"
},
  "geometry": {"coordinates":[7.628884,47.805222],"type":"Point"}
}