{
  "type": "Feature",
  "properties": {
    "iso:country":"DE",
    "sg:address":"Rosenstr. 49b",
    "sg:city":"Riemerling",
    "sg:postcode":"85521",
    "sg:province":"Bayern",
    "wof:name":"Ing- Grad. Klaus Hildebrand Architekt",
    "wof:placetype":"venue"
},
  "geometry": {"coordinates":[11.6884,48.060135],"type":"Point"}
}