{
  "type": "Feature",
  "properties": {
    "iso:country":"DE",
    "sg:address":"Dorfstr. 13",
    "sg:city":"M\u00fcnchehofe",
    "sg:phone":"+49 33760/56060",
    "sg:postcode":"15748",
    "sg:province":"Brandenburg",
    "wof:name":"Agrargenossenschaft M\u00fcnchehofe E. G.",
    "wof:placetype":"venue"
},
  "geometry": {"coordinates":[13.83087,52.145657],"type":"Point"}
}