{
  "type": "Feature",
  "properties": {
    "iso:country":"DE",
    "sg:address":"Julius-Lippold-Str. 23",
    "sg:city":"Eisenach",
    "sg:phone":"+49 3691/71568",
    "sg:postcode":"99817",
    "sg:province":"Th\u00fcringen",
    "wof:name":"Heiner Topfst\u00e4dt",
    "wof:placetype":"venue"
},
  "geometry": {"coordinates":[10.309683,50.98584],"type":"Point"}
}