{
  "type": "Feature",
  "properties": {
    "iso:country":"DE",
    "sg:address":"\u00d6stliche Alpenstr. 26",
    "sg:city":"Sonthofen",
    "sg:postcode":"87527",
    "sg:province":"Bayern",
    "wof:name":"Aldi Gmbh & Co. Kg",
    "wof:placetype":"venue"
},
  "geometry": {"coordinates":[10.2862901688,47.5185966492],"type":"Point"}
}