{
  "type": "Feature",
  "properties": {
    "iso:country":"DE",
    "sg:address":"De niege Wech 1 a",
    "sg:city":"Thiessow",
    "sg:phone":"+49 38308/8378",
    "sg:postcode":"18586",
    "sg:province":"Mecklenburg-Vorpommern",
    "wof:name":"Brigitta Scheibel",
    "wof:placetype":"venue"
},
  "geometry": {"coordinates":[13.7156915665,54.2754669189],"type":"Point"}
}