{
  "type": "Feature",
  "properties": {
    "iso:country":"DE",
    "sg:address":"Hof Meinefeld",
    "sg:city":"Nienst\u00e4dt",
    "sg:phone":"+49 5721/4053",
    "sg:postcode":"31688",
    "sg:province":"Niedersachsen",
    "wof:name":"Gisela Hagen Architektin",
    "wof:placetype":"venue"
},
  "geometry": {"coordinates":[9.161846,52.30864],"type":"Point"}
}