{
  "type": "Feature",
  "properties": {
    "iso:country":"DE",
    "sg:address":"Richardstr. 139",
    "sg:city":"D\u00fcsseldorf",
    "sg:phone":"+49 211/221250",
    "sg:postcode":"40231",
    "sg:province":"Nordrhein-Westfalen",
    "wof:name":"Anneliese Frohnhofer",
    "wof:placetype":"venue"
},
  "geometry": {"coordinates":[6.837045,51.211594],"type":"Point"}
}