{
  "type": "Feature",
  "properties": {
    "iso:country":"DE",
    "sg:address":"Rheinstr. 19",
    "sg:city":"Wiesbaden",
    "sg:phone":"+49 611/17220",
    "sg:postcode":"65185",
    "sg:province":"Hessen",
    "wof:name":"Possehl Spezialbau Gmbh",
    "wof:placetype":"venue"
},
  "geometry": {"coordinates":[8.244223,50.078259],"type":"Point"}
}