{
  "type": "Feature",
  "properties": {
    "iso:country":"DE",
    "sg:address":"Johannesstr. 42",
    "sg:city":"R\u00f6slau",
    "sg:phone":"+49 9238/502",
    "sg:postcode":"95195",
    "sg:province":"Bayern",
    "wof:name":"Rudolf Grimm",
    "wof:placetype":"venue"
},
  "geometry": {"coordinates":[11.962934,50.086216],"type":"Point"}
}