{
  "type": "Feature",
  "properties": {
    "iso:country":"DE",
    "sg:address":"Alsterstieg 6",
    "sg:city":"Kayhude",
    "sg:phone":"+49 4535/6525",
    "sg:postcode":"23863",
    "sg:province":"Schleswig-Holstein",
    "wof:name":"E. Bahlinger",
    "wof:placetype":"venue"
},
  "geometry": {"coordinates":[10.1398010254,53.7572097778],"type":"Point"}
}