{
  "type": "Feature",
  "properties": {
    "iso:country":"DE",
    "sg:address":"Im Karweg 10",
    "sg:city":"Sundern",
    "sg:phone":"+49 2933/2698",
    "sg:postcode":"59846",
    "sg:province":"Nordrhein-Westfalen",
    "wof:name":"N & W Baugesellschaft Gesch\u00e4ftsf\u00fchrung-gmbh",
    "wof:placetype":"venue"
},
  "geometry": {"coordinates":[7.9816470146,51.2978973389],"type":"Point"}
}