{
  "type": "Feature",
  "properties": {
    "iso:country":"DE",
    "sg:address":"Hunwesstr. 1",
    "sg:city":"L\u00f6hnberg",
    "sg:phone":"+49 6471/8962",
    "sg:postcode":"35792",
    "sg:province":"Hessen",
    "wof:name":"Walter Keller",
    "wof:placetype":"venue"
},
  "geometry": {"coordinates":[8.2698574066,50.5100326538],"type":"Point"}
}