{
  "type": "Feature",
  "properties": {
    "iso:country":"DE",
    "sg:address":"Siegburger Str. 355",
    "sg:city":"K\u00f6ln",
    "sg:phone":"+49 221/8302404",
    "sg:postcode":"51105",
    "sg:province":"Nordrhein-Westfalen",
    "wof:name":"Hans-j\u00fcrgen Koch Masseur",
    "wof:placetype":"venue"
},
  "geometry": {"coordinates":[6.990522,50.916756],"type":"Point"}
}