{
  "type": "Feature",
  "properties": {
    "iso:country":"DE",
    "sg:address":"Sigmarshofen 16",
    "sg:city":"Gr\u00fcnkraut",
    "sg:phone":"+49 7520/2187",
    "sg:postcode":"88287",
    "sg:province":"Baden-W\u00fcrttemberg",
    "wof:name":"R. Spie\u00df",
    "wof:placetype":"venue"
},
  "geometry": {"coordinates":[9.6661739349,47.7263412476],"type":"Point"}
}