{
  "type": "Feature",
  "properties": {
    "iso:country":"DE",
    "sg:address":"Gr\u00f6benbachweg 4b",
    "sg:city":"Bergkirchen",
    "sg:postcode":"85232",
    "sg:province":"Bayern",
    "wof:name":"R. Bognar Gmbh",
    "wof:placetype":"venue"
},
  "geometry": {"coordinates":[11.4270677567,48.2221336365],"type":"Point"}
}