{
  "type": "Feature",
  "properties": {
    "iso:country":"DE",
    "sg:address":"Breite Str. 1",
    "sg:city":"Saathain",
    "sg:phone":"+49 3533/4119",
    "sg:postcode":"04932",
    "sg:province":"Brandenburg",
    "wof:name":"Z\u00f6ller Und Z\u00f6ller Wirtschaftsberater",
    "wof:placetype":"venue"
},
  "geometry": {"coordinates":[13.5463972092,51.4182777405],"type":"Point"}
}