{
  "type": "Feature",
  "properties": {
    "iso:country":"DE",
    "sg:address":"Alte Poststr.",
    "sg:city":"Kenn",
    "sg:phone":"+49 6502/8928",
    "sg:postcode":"54344",
    "sg:province":"Rheinland-Pfalz",
    "wof:name":"P. Herrig",
    "wof:placetype":"venue"
},
  "geometry": {"coordinates":[6.7169208527,49.7947921753],"type":"Point"}
}