{
  "type": "Feature",
  "properties": {
    "iso:country":"DE",
    "sg:address":"Weselerstr. 63",
    "sg:city":"D\u00fcsseldorf",
    "sg:phone":"+49 211/6003895",
    "sg:postcode":"40239",
    "sg:province":"Nordrhein-Westfalen",
    "wof:name":"Willkommen Bei Nippon-food-company",
    "wof:placetype":"venue"
},
  "geometry": {"coordinates":[6.801613,51.238911],"type":"Point"}
}