{
  "type": "Feature",
  "properties": {
    "iso:country":"DE",
    "sg:address":"Lambacher Str. 10",
    "sg:city":"Lam",
    "sg:phone":"+49 9943/8851",
    "sg:postcode":"93462",
    "sg:province":"Bayern",
    "wof:name":"Pension Bergesblick",
    "wof:placetype":"venue"
},
  "geometry": {"coordinates":[13.0507173538,49.2008972168],"type":"Point"}
}