{
  "type": "Feature",
  "properties": {
    "iso:country":"DE",
    "sg:address":"Georgstr. 4",
    "sg:city":"Euskirchen",
    "sg:phone":"+49 2251/77170",
    "sg:postcode":"53879",
    "sg:province":"Nordrhein-Westfalen",
    "wof:name":"Christian Bruske Rechtsanwalt",
    "wof:placetype":"venue"
},
  "geometry": {"coordinates":[6.7717962265,50.6570281982],"type":"Point"}
}