{
  "type": "Feature",
  "properties": {
    "iso:country":"DE",
    "sg:address":"An der Landwehr 22",
    "sg:city":"G\u00fctersloh",
    "sg:phone":"+49 5241/701701",
    "sg:postcode":"33335",
    "sg:province":"Nordrhein-Westfalen",
    "wof:name":"G\u00fctersloher Lift & Krane Gmbh",
    "wof:placetype":"venue"
},
  "geometry": {"coordinates":[8.4201517105,51.9147644043],"type":"Point"}
}