{
  "type": "Feature",
  "properties": {
    "iso:country":"DE",
    "sg:address":"Burgstr. 3",
    "sg:city":"Ludwigsstadt",
    "sg:phone":"+49 9263/400",
    "sg:postcode":"96337",
    "sg:province":"Bayern",
    "wof:name":"Burgverwaltung Lauenstein",
    "wof:placetype":"venue"
},
  "geometry": {"coordinates":[11.387791,50.485054],"type":"Point"}
}