{
  "type": "Feature",
  "properties": {
    "iso:country":"DE",
    "sg:address":"Oberer Stehling 2",
    "sg:city":"Monschau",
    "sg:phone":"+49 2472/3320",
    "sg:postcode":"52156",
    "sg:province":"Nordrhein-Westfalen",
    "wof:name":"Ulrich Hermanns",
    "wof:placetype":"venue"
},
  "geometry": {"coordinates":[6.219183,50.56945],"type":"Point"}
}