{
  "type": "Feature",
  "properties": {
    "iso:country":"DE",
    "sg:address":"Im Gemmingtal 55",
    "sg:city":"Heilbronn",
    "sg:phone":"+49 7131/161263",
    "sg:postcode":"74074",
    "sg:province":"Baden-W\u00fcrttemberg",
    "wof:name":"D. Habler Folien + Industrieverpackungen",
    "wof:placetype":"venue"
},
  "geometry": {"coordinates":[9.2382040024,49.1322402954],"type":"Point"}
}