{
  "type": "Feature",
  "properties": {
    "iso:country":"DE",
    "sg:address":"Bahnhofstr 33",
    "sg:city":"Pappenheim",
    "sg:phone":"+49 9143/85562",
    "sg:postcode":"91788",
    "sg:province":"Bayern",
    "wof:name":"Spedition Michel Gmbh",
    "wof:placetype":"venue"
},
  "geometry": {"coordinates":[10.9679927826,48.9299278259],"type":"Point"}
}