{
  "type": "Feature",
  "properties": {
    "iso:country":"DE",
    "sg:address":"Stra\u00dfe der DSF 24",
    "sg:city":"Bl\u00f6nsdorf",
    "sg:phone":"+49 33743/50396",
    "sg:postcode":"14913",
    "sg:province":"Brandenburg",
    "wof:name":"Angelika G\u00e4rtner",
    "wof:placetype":"venue"
},
  "geometry": {"coordinates":[12.8950538635,51.9589157104],"type":"Point"}
}