{
  "type": "Feature",
  "properties": {
    "iso:country":"DE",
    "sg:address":"Adolf-Vogt-Str. 20",
    "sg:city":"Frechen",
    "sg:phone":"+49 2234/360316",
    "sg:postcode":"50226",
    "sg:province":"Nordrhein-Westfalen",
    "wof:name":"A & O Michels Spielautomaten Gmbh",
    "wof:placetype":"venue"
},
  "geometry": {"coordinates":[6.7618188858,50.9045906067],"type":"Point"}
}