{
  "type": "Feature",
  "properties": {
    "iso:country":"DE",
    "sg:address":"Haustadter-Tal-Str. 175",
    "sg:city":"Beckingen",
    "sg:phone":"+49 6835/1718",
    "sg:postcode":"66701",
    "sg:province":"Saarland",
    "wof:name":"Pizzeria Italia",
    "wof:placetype":"venue"
},
  "geometry": {"coordinates":[6.7233800888,49.413105011],"type":"Point"}
}