{
  "type": "Feature",
  "properties": {
    "iso:country":"DE",
    "sg:address":"K\u00f6lner Str. 52",
    "sg:city":"Troisdorf",
    "sg:phone":"+49 2241/78500",
    "sg:postcode":"53840",
    "sg:province":"Nordrhein-Westfalen",
    "wof:name":"Kodi Diskontl\u00e4den Gmbh",
    "wof:placetype":"venue"
},
  "geometry": {"coordinates":[7.158010006,50.8147392273],"type":"Point"}
}