{
  "type": "Feature",
  "properties": {
    "iso:country":"DE",
    "sg:address":"Rektoratsweg 117",
    "sg:city":"M\u00fcnster",
    "sg:phone":"+49 251/263816",
    "sg:postcode":"48159",
    "sg:province":"Nordrhein-Westfalen",
    "wof:name":"Schneberger Beteiligungs Gmbh",
    "wof:placetype":"venue"
},
  "geometry": {"coordinates":[7.607096,51.994637],"type":"Point"}
}