{
  "type": "Feature",
  "properties": {
    "iso:country":"DE",
    "sg:address":"Durlach",
    "sg:city":"Karlsruhe",
    "sg:phone":"+49 721/496168",
    "sg:postcode":"76135",
    "sg:province":"Baden-W\u00fcrttemberg",
    "wof:name":"Seniorenheim Markgrafenstift",
    "wof:placetype":"venue"
},
  "geometry": {"coordinates":[8.3727,48.991119],"type":"Point"}
}