{
  "type": "Feature",
  "properties": {
    "iso:country":"DE",
    "sg:address":"M\u00fchlenfeldstr. 1",
    "sg:city":"Holzminden",
    "sg:phone":"+49 5531/900",
    "sg:postcode":"37603",
    "sg:province":"Niedersachsen",
    "wof:name":"Schimmel & Co. Gmbh",
    "wof:placetype":"venue"
},
  "geometry": {"coordinates":[9.4566230774,51.82472229],"type":"Point"}
}