{
  "type": "Feature",
  "properties": {
    "iso:country":"DE",
    "sg:address":"Bahnhofstr. 23",
    "sg:city":"Ostbevern",
    "sg:phone":"+49 2532/5140",
    "sg:postcode":"48346",
    "sg:province":"Nordrhein-Westfalen",
    "wof:name":"Harro Keuper",
    "wof:placetype":"venue"
},
  "geometry": {"coordinates":[7.8380870819,52.0383987427],"type":"Point"}
}