{
  "type": "Feature",
  "properties": {
    "iso:country":"DE",
    "sg:address":"Woogstr. 1a",
    "sg:city":"Frankfurt",
    "sg:phone":"+49 69/511716",
    "sg:postcode":"60431",
    "sg:province":"Hessen",
    "wof:name":"R. K. Becker",
    "wof:placetype":"venue"
},
  "geometry": {"coordinates":[8.6486740112,50.1447181702],"type":"Point"}
}