{
  "type": "Feature",
  "properties": {
    "iso:country":"DE",
    "sg:address":"Rosengasse 26",
    "sg:city":"Ulm",
    "sg:phone":"+49 731/67093",
    "sg:postcode":"89073",
    "sg:province":"Baden-W\u00fcrttemberg",
    "wof:name":"Dr. Ulli Heinz Waiblinger Rechtsanwalt",
    "wof:placetype":"venue"
},
  "geometry": {"coordinates":[9.9963998795,48.4008255005],"type":"Point"}
}