{
  "type": "Feature",
  "properties": {
    "iso:country":"DE",
    "sg:address":"Hambergstr. 5 a",
    "sg:city":"Rosdorf",
    "sg:phone":"+49 551/782227",
    "sg:postcode":"37124",
    "sg:province":"Niedersachsen",
    "wof:name":"Soko Warenvertriebs Gmbh",
    "wof:placetype":"venue"
},
  "geometry": {"coordinates":[9.906652,51.510948],"type":"Point"}
}