{
  "type": "Feature",
  "properties": {
    "iso:country":"DE",
    "sg:address":"Landwehr 188",
    "sg:city":"Oberhausen",
    "sg:phone":"+49 208/807822",
    "sg:postcode":"46045",
    "sg:province":"Nordrhein-Westfalen",
    "wof:name":"Jost Drenger Architekt",
    "wof:placetype":"venue"
},
  "geometry": {"coordinates":[6.848335,51.459244],"type":"Point"}
}