{
  "type": "Feature",
  "properties": {
    "iso:country":"DE",
    "sg:address":"Zum Scheidberg 85",
    "sg:city":"Wallerfangen",
    "sg:phone":"+49 6837/887",
    "sg:postcode":"66798",
    "sg:province":"Saarland",
    "wof:name":"J. Gerard",
    "wof:placetype":"venue"
},
  "geometry": {"coordinates":[6.6554889679,49.3271713257],"type":"Point"}
}