{
  "type": "Feature",
  "properties": {
    "iso:country":"DE",
    "sg:address":"Bahnhofstr. 2-4",
    "sg:city":"K\u00f6ln",
    "sg:phone":"+49 2236/31015",
    "sg:postcode":"50999",
    "sg:province":"Nordrhein-Westfalen",
    "wof:name":"Eheleute Dr. Karl Emil Und Lilli Br\u00fcgmann Stiftung",
    "wof:placetype":"venue"
},
  "geometry": {"coordinates":[7.0066299438,50.8626937866],"type":"Point"}
}