{
  "type": "Feature",
  "properties": {
    "iso:country":"DE",
    "sg:address":"Gasstr. 18",
    "sg:city":"Hamburg",
    "sg:phone":"+49 40/8908330",
    "sg:postcode":"22761",
    "sg:province":"Hamburg",
    "wof:name":"Infas-media-metric Gmbh",
    "wof:placetype":"venue"
},
  "geometry": {"coordinates":[9.914165,53.561165],"type":"Point"}
}