{
  "type": "Feature",
  "properties": {
    "iso:country":"DE",
    "sg:address":"Schwarzwaldstr. 61",
    "sg:city":"Rheinstetten",
    "sg:phone":"+49 721/51141",
    "sg:postcode":"76287",
    "sg:province":"Baden-W\u00fcrttemberg",
    "wof:name":"Pferrer Hausbau Gmbh",
    "wof:placetype":"venue"
},
  "geometry": {"coordinates":[8.318878,48.977074],"type":"Point"}
}