{
  "type": "Feature",
  "properties": {
    "iso:country":"DE",
    "sg:address":"Vierenstr.16",
    "sg:city":"Oberwiesenthal",
    "sg:postcode":"09484",
    "sg:province":"Sachsen",
    "wof:name":"Alpiner Skiclub Oberwiesenthal E.v. - Asc",
    "wof:placetype":"venue"
},
  "geometry": {"coordinates":[12.967634201,50.42370224],"type":"Point"}
}