{
  "type": "Feature",
  "properties": {
    "iso:country":"DE",
    "sg:address":"G\u00e4rtnerstr.",
    "sg:city":"Spremberg",
    "sg:postcode":"03130",
    "sg:province":"Brandenburg",
    "wof:name":"Handycamp Bildung Und Freizeit Gmbh",
    "wof:placetype":"venue"
},
  "geometry": {"coordinates":[14.3782129288,51.5653800964],"type":"Point"}
}