{
  "type": "Feature",
  "properties": {
    "iso:country":"DE",
    "sg:address":"Karlstr. 68",
    "sg:city":"Leinfelden-Echterdingen",
    "sg:phone":"+49 711/7541145",
    "sg:postcode":"70771",
    "sg:province":"Baden-W\u00fcrttemberg",
    "wof:name":"Krieg Gmbh",
    "wof:placetype":"venue"
},
  "geometry": {"coordinates":[9.125626,48.692028],"type":"Point"}
}