{
  "type": "Feature",
  "properties": {
    "iso:country":"DE",
    "sg:address":"Mariazeller Str. 6",
    "sg:city":"Schramberg",
    "sg:phone":"+49 7422/8263",
    "sg:postcode":"78713",
    "sg:province":"Baden-W\u00fcrttemberg",
    "wof:name":"Kath. Pfarramt St. Laurentius",
    "wof:placetype":"venue"
},
  "geometry": {"coordinates":[8.4184856415,48.2216453552],"type":"Point"}
}