{
  "type": "Feature",
  "properties": {
    "iso:country":"DE",
    "sg:address":"Rudolf-Diesel-Str. 6",
    "sg:city":"Visselh\u00f6vede",
    "sg:phone":"+49 4262/93140",
    "sg:postcode":"27374",
    "sg:province":"Niedersachsen",
    "wof:name":"Juwel Ladenbau Gmbh & Co. Kg",
    "wof:placetype":"venue"
},
  "geometry": {"coordinates":[9.59867,52.980289],"type":"Point"}
}