{
  "type": "Feature",
  "properties": {
    "iso:country":"DE",
    "sg:address":"Angerstr. 7",
    "sg:city":"Goldkronach",
    "sg:phone":"+49 9208/8156",
    "sg:postcode":"95497",
    "sg:province":"Bayern",
    "wof:name":"Georg P\u00f6hlmann",
    "wof:placetype":"venue"
},
  "geometry": {"coordinates":[11.661387,49.99321],"type":"Point"}
}