{
  "type": "Feature",
  "properties": {
    "iso:country":"DE",
    "sg:address":"Dorfstr. 12",
    "sg:city":"Drelsdorf",
    "sg:phone":"+49 4671/2994",
    "sg:postcode":"25853",
    "sg:province":"Schleswig-Holstein",
    "wof:name":"J. Und R. Carstens Heissmangel",
    "wof:placetype":"venue"
},
  "geometry": {"coordinates":[9.0423078537,54.6059341431],"type":"Point"}
}