{
  "type": "Feature",
  "properties": {
    "iso:country":"DE",
    "sg:address":"Metzer Str. 52",
    "sg:city":"Saarbr\u00fccken",
    "sg:phone":"+49 681/52691",
    "sg:postcode":"66117",
    "sg:province":"Saarland",
    "wof:name":"G\u00fcnther Walch Buchdruckerei Gmbh",
    "wof:placetype":"venue"
},
  "geometry": {"coordinates":[6.970624,49.220215],"type":"Point"}
}