{
  "type": "Feature",
  "properties": {
    "iso:country":"DE",
    "sg:address":"Rosa-Luxemburg-Str. 23",
    "sg:city":"Grockst\u00e4dt",
    "sg:phone":"+49 34461/23593",
    "sg:postcode":"06268",
    "sg:province":"Sachsen-Anhalt",
    "wof:name":"Ralf Zwirner",
    "wof:placetype":"venue"
},
  "geometry": {"coordinates":[11.6096601486,51.3361701965],"type":"Point"}
}