{
  "type": "Feature",
  "properties": {
    "iso:country":"DE",
    "sg:address":"Brandenburger Str. 4",
    "sg:city":"Werder",
    "sg:phone":"+49 3327/44208",
    "sg:postcode":"14542",
    "sg:province":"Brandenburg",
    "wof:name":"Heike K\u00f6pge Masseurin",
    "wof:placetype":"venue"
},
  "geometry": {"coordinates":[12.92599,52.374039],"type":"Point"}
}