{
  "type": "Feature",
  "properties": {
    "iso:country":"DE",
    "sg:address":"Gutsstrasse 7",
    "sg:city":"Porta Westfalica",
    "sg:phone":"+49 5731",
    "sg:postcode":"32457",
    "sg:province":"Nordrhein-Westfalen",
    "wof:name":"Hornrabe - Tours",
    "wof:placetype":"venue"
},
  "geometry": {"coordinates":[8.8683691025,52.2278518677],"type":"Point"}
}