{
  "type": "Feature",
  "properties": {
    "iso:country":"DE",
    "sg:address":"Frieslandring 13",
    "sg:city":"Troisdorf",
    "sg:phone":"+49 2241/47989",
    "sg:postcode":"53844",
    "sg:province":"Nordrhein-Westfalen",
    "wof:name":"Angela Emons",
    "wof:placetype":"venue"
},
  "geometry": {"coordinates":[7.1176390648,50.8098144531],"type":"Point"}
}