{
  "type": "Feature",
  "properties": {
    "iso:country":"DE",
    "sg:address":"Feldbergweg 6",
    "sg:city":"Ettlingen",
    "sg:phone":"+49 7243/30705",
    "sg:postcode":"76275",
    "sg:province":"Baden-W\u00fcrttemberg",
    "wof:name":"Immo-verwaltung Donecker Gmbh",
    "wof:placetype":"venue"
},
  "geometry": {"coordinates":[8.4139719009,48.9349517822],"type":"Point"}
}