{
  "type": "Feature",
  "properties": {
    "iso:country":"DE",
    "sg:address":"G\u00fcstrower Str. 25",
    "sg:city":"Malchow",
    "sg:phone":"+49 39932/19373",
    "sg:postcode":"17213",
    "sg:province":"Mecklenburg-Vorpommern",
    "wof:name":"Apotheke Inh. B. K\u00f6hn",
    "wof:placetype":"venue"
},
  "geometry": {"coordinates":[12.425618,53.476089],"type":"Point"}
}