{
  "type": "Feature",
  "properties": {
    "iso:country":"DE",
    "sg:address":"Dreik\u00f6niggasse 1",
    "sg:city":"Ulm",
    "sg:phone":"+49 731/65342",
    "sg:postcode":"89073",
    "sg:province":"Baden-W\u00fcrttemberg",
    "wof:name":"Reichhart",
    "wof:placetype":"venue"
},
  "geometry": {"coordinates":[9.9908103943,48.40001297],"type":"Point"}
}