{
  "type": "Feature",
  "properties": {
    "iso:country":"DE",
    "sg:address":"Zum Sportplatz 1",
    "sg:city":"Wenden",
    "sg:phone":"+49 2762/8095",
    "sg:postcode":"57482",
    "sg:province":"Nordrhein-Westfalen",
    "wof:name":"Christoph Greiten",
    "wof:placetype":"venue"
},
  "geometry": {"coordinates":[7.8262300491,50.9472503662],"type":"Point"}
}