{
  "type": "Feature",
  "properties": {
    "iso:country":"DE",
    "sg:address":"Marktplatz 12",
    "sg:city":"Kraiburg",
    "sg:phone":"+49 8638/72543",
    "sg:postcode":"84559",
    "sg:province":"Bayern",
    "wof:name":"Elfriede Hutterer",
    "wof:placetype":"venue"
},
  "geometry": {"coordinates":[12.429226,48.181301],"type":"Point"}
}