{
  "type": "Feature",
  "properties": {
    "iso:country":"DE",
    "sg:address":"Vorderschlo\u00df 9",
    "sg:city":"Ortenburg",
    "sg:postcode":"94496",
    "sg:province":"Bayern",
    "wof:name":"Seeblick Cafe",
    "wof:placetype":"venue"
},
  "geometry": {"coordinates":[13.229609,48.551884],"type":"Point"}
}