{
  "type": "Feature",
  "properties": {
    "iso:country":"DE",
    "sg:address":"Elisenstr. 18",
    "sg:city":"Chemnitz",
    "sg:postcode":"09111",
    "sg:province":"Sachsen",
    "wof:name":"Mp Marketing Gmbh",
    "wof:placetype":"venue"
},
  "geometry": {"coordinates":[12.9266338348,50.8440093994],"type":"Point"}
}