{
  "type": "Feature",
  "properties": {
    "iso:country":"DE",
    "sg:address":"Georgenstr. 117",
    "sg:city":"M\u00fcnchen",
    "sg:phone":"+49 89/12392963",
    "sg:postcode":"80797",
    "sg:province":"Bayern",
    "wof:name":"Dipl.-ing. Erich Jenewein Architekt",
    "wof:placetype":"venue"
},
  "geometry": {"coordinates":[11.56187,48.157127],"type":"Point"}
}