{
  "type": "Feature",
  "properties": {
    "iso:country":"DE",
    "sg:address":"Tullastr. 26",
    "sg:city":"Kenzingen",
    "sg:phone":"+49 7644/91190",
    "sg:postcode":"79341",
    "sg:province":"Baden-W\u00fcrttemberg",
    "wof:name":"L. Zipse",
    "wof:placetype":"venue"
},
  "geometry": {"coordinates":[7.7623729706,48.1967201233],"type":"Point"}
}