{
  "type": "Feature",
  "properties": {
    "iso:country":"DE",
    "sg:address":"Karlstr. 28",
    "sg:city":"Reutlingen",
    "sg:phone":"+49 7121/470242",
    "sg:postcode":"72764",
    "sg:province":"Baden-W\u00fcrttemberg",
    "wof:name":"Hans-j. Schneider Rechtsanwalt",
    "wof:placetype":"venue"
},
  "geometry": {"coordinates":[9.2128295898,48.4964599609],"type":"Point"}
}