{
  "type": "Feature",
  "properties": {
    "iso:country":"DE",
    "sg:address":"Goethestr. 10",
    "sg:city":"Bad Lauchst\u00e4dt",
    "sg:postcode":"06246",
    "sg:province":"Sachsen-Anhalt",
    "wof:name":"B. Bornschein",
    "wof:placetype":"venue"
},
  "geometry": {"coordinates":[11.8664093018,51.3881072998],"type":"Point"}
}