{
  "type": "Feature",
  "properties": {
    "iso:country":"DE",
    "sg:address":"Poststr. 16",
    "sg:city":"Altensteig",
    "sg:phone":"+49 7453/6661",
    "sg:postcode":"72213",
    "sg:province":"Baden-W\u00fcrttemberg",
    "wof:name":"Rolf Katz",
    "wof:placetype":"venue"
},
  "geometry": {"coordinates":[8.603418,48.584003],"type":"Point"}
}