{
  "type": "Feature",
  "properties": {
    "iso:country":"DE",
    "sg:address":"Schulstr. 21-25",
    "sg:city":"Wiesbach",
    "sg:phone":"+49 6337/92130",
    "sg:postcode":"66894",
    "sg:province":"Rheinland-Pfalz",
    "wof:name":"Fhe-design Werbeagentur Frederic Egger",
    "wof:placetype":"venue"
},
  "geometry": {"coordinates":[7.4560642242,49.3350563049],"type":"Point"}
}