{
  "type": "Feature",
  "properties": {
    "iso:country":"DE",
    "sg:address":"Bachackerweg 31",
    "sg:city":"Marl",
    "sg:phone":"+49 2365/22663",
    "sg:postcode":"45772",
    "sg:province":"Nordrhein-Westfalen",
    "wof:name":"Hammer Stuben",
    "wof:placetype":"venue"
},
  "geometry": {"coordinates":[7.1199021339,51.6900215149],"type":"Point"}
}