{
  "type": "Feature",
  "properties": {
    "iso:country":"DE",
    "sg:address":"Am Sonnenberg 30",
    "sg:city":"Breitnau",
    "sg:phone":"+49 7652/791",
    "sg:postcode":"79874",
    "sg:province":"Baden-W\u00fcrttemberg",
    "wof:name":"M. Eschenlohr Ingenieur",
    "wof:placetype":"venue"
},
  "geometry": {"coordinates":[8.0751886368,47.940372467],"type":"Point"}
}