{
  "type": "Feature",
  "properties": {
    "iso:country":"DE",
    "sg:address":"Friedrichstr. 3",
    "sg:city":"Norderney",
    "sg:phone":"+49 4932/82876",
    "sg:postcode":"26548",
    "sg:province":"Niedersachsen",
    "wof:name":"Pension Haus Nordsee",
    "wof:placetype":"venue"
},
  "geometry": {"coordinates":[7.1404662132,53.707901001],"type":"Point"}
}