{
  "type": "Feature",
  "properties": {
    "iso:country":"DE",
    "sg:address":"Bamberger Str. 1",
    "sg:city":"Dresden",
    "sg:phone":"+49 351/4724060",
    "sg:postcode":"01187",
    "sg:province":"Sachsen",
    "wof:name":"A-z Druck Dresden E. K.",
    "wof:placetype":"venue"
},
  "geometry": {"coordinates":[13.710293,51.035183],"type":"Point"}
}