{
  "type": "Feature",
  "properties": {
    "iso:country":"DE",
    "sg:address":"Friedenstr. 13",
    "sg:city":"Unterreichenbach",
    "sg:phone":"+49 7235/7356",
    "sg:postcode":"75399",
    "sg:province":"Baden-W\u00fcrttemberg",
    "wof:name":"Leni Schmid Lebensmittel",
    "wof:placetype":"venue"
},
  "geometry": {"coordinates":[8.70865345,48.8254013062],"type":"Point"}
}