{
  "type": "Feature",
  "properties": {
    "iso:country":"DE",
    "sg:address":"Wehlachstr. 15",
    "sg:city":"B\u00f6hl-Iggelheim",
    "sg:phone":"+49 6324/64326",
    "sg:postcode":"67459",
    "sg:province":"Rheinland-Pfalz",
    "wof:name":"Rudi Reil",
    "wof:placetype":"venue"
},
  "geometry": {"coordinates":[8.3021631241,49.3587150574],"type":"Point"}
}