{
  "type": "Feature",
  "properties": {
    "iso:country":"DE",
    "sg:address":"Friedrich-Wilhelm-Str. 2",
    "sg:city":"Minden",
    "sg:phone":"+49 571/3889880",
    "sg:postcode":"32423",
    "sg:province":"Nordrhein-Westfalen",
    "wof:name":"Spedition Ackmann & Sohn Gmbh",
    "wof:placetype":"venue"
},
  "geometry": {"coordinates":[8.9328050613,52.2914428711],"type":"Point"}
}