{
  "type": "Feature",
  "properties": {
    "iso:country":"DE",
    "sg:address":"Br\u00fchl 100",
    "sg:city":"Heubach",
    "sg:phone":"+49 7173/929170",
    "sg:postcode":"73540",
    "sg:province":"Baden-W\u00fcrttemberg",
    "wof:name":"Werner Koch",
    "wof:placetype":"venue"
},
  "geometry": {"coordinates":[9.967569,48.806507],"type":"Point"}
}