{
  "type": "Feature",
  "properties": {
    "iso:country":"DE",
    "sg:address":"Alte Schulstr. 25",
    "sg:city":"Loxstedt",
    "sg:phone":"+49 4703/5118",
    "sg:postcode":"27612",
    "sg:province":"Niedersachsen",
    "wof:name":"Horst K\u00f6lling Masseur",
    "wof:placetype":"venue"
},
  "geometry": {"coordinates":[8.70907,53.475391],"type":"Point"}
}