{
  "type": "Feature",
  "properties": {
    "iso:country":"DE",
    "sg:address":"Untere Ein\u00f6de 14",
    "sg:city":"Woringen",
    "sg:phone":"+49 8331/82253",
    "sg:postcode":"87789",
    "sg:province":"Bayern",
    "wof:name":"Erwin Klotz",
    "wof:placetype":"venue"
},
  "geometry": {"coordinates":[10.197991,47.946083],"type":"Point"}
}