{
  "type": "Feature",
  "properties": {
    "iso:country":"DE",
    "sg:address":"Edgar-Bennert-Str. 61",
    "sg:city":"Schwerin",
    "sg:postcode":"19057",
    "sg:province":"Mecklenburg-Vorpommern",
    "wof:name":"Hotel-mv - Das Unterkunfts-webverzeichnis",
    "wof:placetype":"venue"
},
  "geometry": {"coordinates":[11.370717,53.651398],"type":"Point"}
}