{
  "type": "Feature",
  "properties": {
    "iso:country":"DE",
    "sg:address":"Dreherstr 36",
    "sg:city":"Remscheid",
    "sg:phone":"+49 2191/94510",
    "sg:postcode":"42899",
    "sg:province":"Nordrhein-Westfalen",
    "wof:name":"Carlfriedrich Br\u00fccher Kg",
    "wof:placetype":"venue"
},
  "geometry": {"coordinates":[7.221864,51.219822],"type":"Point"}
}