{
  "type": "Feature",
  "properties": {
    "iso:country":"DE",
    "sg:address":"Lohbachstrasse",
    "sg:city":"Schwarzenbach",
    "sg:phone":"+49 9284/95010",
    "sg:postcode":"95126",
    "sg:province":"Bayern",
    "wof:name":"Sch\u00fcrr Schuhvertrieb Gmbh",
    "wof:placetype":"venue"
},
  "geometry": {"coordinates":[11.9412326813,50.2228660583],"type":"Point"}
}