{
  "type": "Feature",
  "properties": {
    "iso:country":"DE",
    "sg:address":"Halskestr. 27",
    "sg:city":"Willich",
    "sg:phone":"+49 2154/428605",
    "sg:postcode":"47877",
    "sg:province":"Nordrhein-Westfalen",
    "wof:name":"Nippon Carbide Industries Europe Gmbh",
    "wof:placetype":"venue"
},
  "geometry": {"coordinates":[6.5172009468,51.2716941833],"type":"Point"}
}