{
  "type": "Feature",
  "properties": {
    "iso:country":"DE",
    "sg:address":"Markt 9",
    "sg:city":"Neustrelitz",
    "sg:phone":"+49 3981/206522",
    "sg:postcode":"17235",
    "sg:province":"Mecklenburg-Vorpommern",
    "wof:name":"Apotheke Am Markt",
    "wof:placetype":"venue"
},
  "geometry": {"coordinates":[13.062961,53.362976],"type":"Point"}
}