{
  "type": "Feature",
  "properties": {
    "iso:country":"DE",
    "sg:address":"Blumenstr. 37",
    "sg:city":"M\u00fcnchen",
    "sg:phone":"+49 89/264224",
    "sg:postcode":"80331",
    "sg:province":"Bayern",
    "wof:name":"Sauter Trading Inh. Harald Sauter",
    "wof:placetype":"venue"
},
  "geometry": {"coordinates":[11.569376,48.131931],"type":"Point"}
}