{
  "type": "Feature",
  "properties": {
    "iso:country":"DE",
    "sg:address":"Schulweg 48",
    "sg:city":"Hamburg",
    "sg:phone":"+49 40/4017600",
    "sg:postcode":"20259",
    "sg:province":"Hamburg",
    "wof:name":"Detlef Pielenz Steuerberater",
    "wof:placetype":"venue"
},
  "geometry": {"coordinates":[9.9599132538,53.574924469],"type":"Point"}
}