{
  "type": "Feature",
  "properties": {
    "iso:country":"DE",
    "sg:address":"Am Heumahdenweg 15",
    "sg:city":"Bad Rappenau",
    "sg:phone":"+49 7264/206263",
    "sg:postcode":"74906",
    "sg:province":"Baden-W\u00fcrttemberg",
    "wof:name":"F. Krenn Gmbh",
    "wof:placetype":"venue"
},
  "geometry": {"coordinates":[9.128192,49.252346],"type":"Point"}
}