{
  "type": "Feature",
  "properties": {
    "iso:country":"DE",
    "sg:address":"Kelterstr. 3",
    "sg:city":"Erligheim",
    "sg:phone":"+49 7143/870510",
    "sg:postcode":"74391",
    "sg:province":"Baden-W\u00fcrttemberg",
    "wof:name":"Ulrich Sebald Architekt",
    "wof:placetype":"venue"
},
  "geometry": {"coordinates":[9.099826,49.020344],"type":"Point"}
}