{
  "type": "Feature",
  "properties": {
    "iso:country":"DE",
    "sg:address":"Heinrich-Heine-Str. 5 a",
    "sg:city":"M\u00f6hlau",
    "sg:postcode":"06791",
    "sg:province":"Sachsen-Anhalt",
    "wof:name":"Landk\u00fcche Essenservice M\u00f6hlau Gmbh",
    "wof:placetype":"venue"
},
  "geometry": {"coordinates":[12.353594,51.722019],"type":"Point"}
}