{
  "type": "Feature",
  "properties": {
    "iso:country":"DE",
    "sg:address":"Unterlaichling 117",
    "sg:city":"Schierling",
    "sg:phone":"+49 9451/2982",
    "sg:postcode":"84069",
    "sg:province":"Bayern",
    "wof:name":"Michael Aumeier",
    "wof:placetype":"venue"
},
  "geometry": {"coordinates":[12.14847,48.855907],"type":"Point"}
}