{
  "type": "Feature",
  "properties": {
    "iso:country":"DE",
    "sg:address":"Mudauer Ring 221",
    "sg:city":"Mannheim",
    "sg:phone":"+49 621/752378",
    "sg:postcode":"68259",
    "sg:province":"Baden-W\u00fcrttemberg",
    "wof:name":"F. Lossmann",
    "wof:placetype":"venue"
},
  "geometry": {"coordinates":[8.5445537567,49.4933357239],"type":"Point"}
}