{
  "type": "Feature",
  "properties": {
    "iso:country":"DE",
    "sg:address":"Hauptstr. 21",
    "sg:city":"Bad Endorf",
    "sg:phone":"+49 8053/2270",
    "sg:postcode":"83093",
    "sg:province":"Bayern",
    "wof:name":"E. Und P. Ziegler Antiquit\u00e4ten",
    "wof:placetype":"venue"
},
  "geometry": {"coordinates":[12.335767,47.911259],"type":"Point"}
}