{
  "type": "Feature",
  "properties": {
    "iso:country":"DE",
    "sg:address":"L\u00f6wengasse 18",
    "sg:city":"Radolfzell",
    "sg:phone":"+49 7732/99110",
    "sg:postcode":"78315",
    "sg:province":"Baden-W\u00fcrttemberg",
    "wof:name":"Kuhn Und Klausmann Steuerberatungs Gmbh",
    "wof:placetype":"venue"
},
  "geometry": {"coordinates":[8.9687690735,47.738445282],"type":"Point"}
}