{
  "type": "Feature",
  "properties": {
    "iso:country":"DE",
    "sg:address":"Untere Dorfstr. 19",
    "sg:city":"Emmerting",
    "sg:phone":"+49 8679/911988",
    "sg:postcode":"84547",
    "sg:province":"Bayern",
    "wof:name":"Pils-pub Domino",
    "wof:placetype":"venue"
},
  "geometry": {"coordinates":[12.7705278397,48.2037124634],"type":"Point"}
}