{
  "type": "Feature",
  "properties": {
    "iso:country":"DE",
    "sg:address":"Mozartstr. 35",
    "sg:city":"Donzdorf",
    "sg:phone":"+49 7162/23466",
    "sg:postcode":"73072",
    "sg:province":"Baden-W\u00fcrttemberg",
    "wof:name":"G. Frey B\u00e4ckerei",
    "wof:placetype":"venue"
},
  "geometry": {"coordinates":[9.796541,48.685699],"type":"Point"}
}