{
  "type": "Feature",
  "properties": {
    "iso:country":"DE",
    "sg:address":"Bahnhofstr. 57",
    "sg:city":"M\u00fchlheim",
    "sg:phone":"+49 6108/794636",
    "sg:postcode":"63165",
    "sg:province":"Hessen",
    "wof:name":"Git Reiseb\u00fcro Gmbh",
    "wof:placetype":"venue"
},
  "geometry": {"coordinates":[8.8353061676,50.12109375],"type":"Point"}
}