{
  "type": "Feature",
  "properties": {
    "iso:country":"DE",
    "sg:address":"Inzlinger Str. 40",
    "sg:city":"L\u00f6rrach",
    "sg:postcode":"79540",
    "sg:province":"Baden-W\u00fcrttemberg",
    "wof:name":"Kaltenbach Stiftung Zentrum F\u00fcr Spielen Und",
    "wof:placetype":"venue"
},
  "geometry": {"coordinates":[7.6798501015,47.6049041748],"type":"Point"}
}