{
  "type": "Feature",
  "properties": {
    "iso:country":"DE",
    "sg:address":"Im Weiherfeld",
    "sg:city":"G\u00f6rwihl",
    "sg:phone":"+49 7754/1561",
    "sg:postcode":"79733",
    "sg:province":"Baden-W\u00fcrttemberg",
    "wof:name":"Wolfgang Fr\u00f6se",
    "wof:placetype":"venue"
},
  "geometry": {"coordinates":[8.074296,47.639732],"type":"Point"}
}