{
  "type": "Feature",
  "properties": {
    "iso:country":"DE",
    "sg:address":"Raiffeisenstr. 4",
    "sg:city":"Bad Nauheim",
    "sg:phone":"+49 6032/82621",
    "sg:postcode":"61231",
    "sg:province":"Hessen",
    "wof:name":"G.e. Witzel",
    "wof:placetype":"venue"
},
  "geometry": {"coordinates":[8.718225,50.381474],"type":"Point"}
}