{
  "type": "Feature",
  "properties": {
    "iso:country":"DE",
    "sg:address":"K\u00f6lnische Str. 20",
    "sg:city":"Kassel",
    "sg:phone":"+49 561/710671",
    "sg:postcode":"34117",
    "sg:province":"Hessen",
    "wof:name":"Hanse-merkur Und Braun- Schweigische Ag",
    "wof:placetype":"venue"
},
  "geometry": {"coordinates":[9.4938993454,51.3164291382],"type":"Point"}
}