{
  "type": "Feature",
  "properties": {
    "iso:country":"DE",
    "sg:address":"Wachtelschlag 29",
    "sg:city":"Bocholt",
    "sg:phone":"+49 2871/261763",
    "sg:postcode":"46395",
    "sg:province":"Nordrhein-Westfalen",
    "wof:name":"Maa\u00df-software- Gmbh",
    "wof:placetype":"venue"
},
  "geometry": {"coordinates":[6.5967121124,51.8219337463],"type":"Point"}
}