{
  "type": "Feature",
  "properties": {
    "iso:country":"DE",
    "sg:address":"Schacht Neu-C\u00f6ln 16",
    "sg:city":"Essen",
    "sg:postcode":"45355",
    "sg:province":"Nordrhein-Westfalen",
    "wof:name":"Laube Helming Und Partner",
    "wof:placetype":"venue"
},
  "geometry": {"coordinates":[6.9577159882,51.4827957153],"type":"Point"}
}