{
  "type": "Feature",
  "properties": {
    "iso:country":"DE",
    "sg:address":"Na\u00df\u00e4ckerstr. 23",
    "sg:city":"P\u00f6\u00dfneck",
    "sg:phone":"+49 4936/4746100",
    "sg:postcode":"07381",
    "sg:province":"Th\u00fcringen",
    "wof:name":"Th\u00dcringer Zucho Maschinenfabrik Gmbh",
    "wof:placetype":"venue"
},
  "geometry": {"coordinates":[11.6263542175,50.6985626221],"type":"Point"}
}