{
  "type": "Feature",
  "properties": {
    "iso:country":"DE",
    "sg:address":"Bamberger Str. 1",
    "sg:city":"Forchheim",
    "sg:phone":"+49 9191/14656",
    "sg:postcode":"91301",
    "sg:province":"Bayern",
    "wof:name":"Sozialstation Der Caritas",
    "wof:placetype":"venue"
},
  "geometry": {"coordinates":[11.05915,49.721439],"type":"Point"}
}