{
  "type": "Feature",
  "properties": {
    "iso:country":"DE",
    "sg:address":"Hammesberger Str. 11",
    "sg:city":"Remscheid",
    "sg:phone":"+49 2191/80359",
    "sg:postcode":"42855",
    "sg:province":"Nordrhein-Westfalen",
    "wof:name":"Carl R\u00f6ntgen Gmbh",
    "wof:placetype":"venue"
},
  "geometry": {"coordinates":[7.1719808578,51.1918983459],"type":"Point"}
}