{
  "type": "Feature",
  "properties": {
    "iso:country":"DE",
    "sg:address":"Karl-Birzer-Str. 11",
    "sg:city":"Ottobrunn",
    "sg:phone":"+49 89/62987224",
    "sg:postcode":"85521",
    "sg:province":"Bayern",
    "wof:name":"Walter Berndt",
    "wof:placetype":"venue"
},
  "geometry": {"coordinates":[11.667205,48.061764],"type":"Point"}
}