{
  "type": "Feature",
  "properties": {
    "iso:country":"DE",
    "sg:address":"Marienfelder Str. 18",
    "sg:city":"G\u00fctersloh",
    "sg:phone":"+49 5241/15177",
    "sg:postcode":"33330",
    "sg:province":"Nordrhein-Westfalen",
    "wof:name":"Treffpunkt Zum Ilias",
    "wof:placetype":"venue"
},
  "geometry": {"coordinates":[8.3689136505,51.9111480713],"type":"Point"}
}