{
  "type": "Feature",
  "properties": {
    "iso:country":"DE",
    "sg:address":"Raiffeisenstr. 8",
    "sg:city":"Uetze",
    "sg:postcode":"31311",
    "sg:province":"Niedersachsen",
    "wof:name":"Speisekartoffelerzeugergem. Dollbergen Und Umgebung Egmbh",
    "wof:placetype":"venue"
},
  "geometry": {"coordinates":[10.2141857147,52.4689941406],"type":"Point"}
}