{
  "type": "Feature",
  "properties": {
    "iso:country":"DE",
    "sg:address":"Theaterstr. 17",
    "sg:city":"F\u00fcrth",
    "sg:phone":"+49 911/7499583",
    "sg:postcode":"90762",
    "sg:province":"Bayern",
    "wof:name":"Helmut Wagner",
    "wof:placetype":"venue"
},
  "geometry": {"coordinates":[10.9848470688,49.4757919312],"type":"Point"}
}