{
  "type": "Feature",
  "properties": {
    "iso:country":"DE",
    "sg:address":"Tiergartenstr.",
    "sg:city":"Westerburg",
    "sg:phone":"+49 2663/8800",
    "sg:postcode":"56457",
    "sg:province":"Rheinland-Pfalz",
    "wof:name":"Penny-markt Gmbh",
    "wof:placetype":"venue"
},
  "geometry": {"coordinates":[7.9807882309,50.5620880127],"type":"Point"}
}