{
  "type": "Feature",
  "properties": {
    "iso:country":"DE",
    "sg:address":"S\u00fcdstr. 23",
    "sg:city":"S\u00f6gel",
    "sg:phone":"+49 5952/98151",
    "sg:postcode":"49751",
    "sg:province":"Niedersachsen",
    "wof:name":"Bernhard Thyen",
    "wof:placetype":"venue"
},
  "geometry": {"coordinates":[7.524089,52.836399],"type":"Point"}
}