{
  "type": "Feature",
  "properties": {
    "iso:country":"DE",
    "sg:address":"Waldstr. 29",
    "sg:city":"Bonn",
    "sg:postcode":"53177",
    "sg:province":"Nordrhein-Westfalen",
    "wof:name":"Gom Gesellschaft F\u00fcr Online- Und",
    "wof:placetype":"venue"
},
  "geometry": {"coordinates":[7.1269698143,50.6830215454],"type":"Point"}
}