{
  "type": "Feature",
  "properties": {
    "iso:country":"DE",
    "sg:address":"Burg Zievel 1",
    "sg:city":"Mechernich",
    "sg:phone":"+49 2256/7134",
    "sg:postcode":"53894",
    "sg:province":"Nordrhein-Westfalen",
    "wof:name":"Karl Josef Krewel",
    "wof:placetype":"venue"
},
  "geometry": {"coordinates":[6.7243571281,50.6176757812],"type":"Point"}
}