{
  "type": "Feature",
  "properties": {
    "iso:country":"DE",
    "sg:address":"Im Hostert",
    "sg:city":"Holzheim",
    "sg:phone":"+49 6432/1413",
    "sg:postcode":"65558",
    "sg:province":"Rheinland-Pfalz",
    "wof:name":"L. Jeuck",
    "wof:placetype":"venue"
},
  "geometry": {"coordinates":[8.0500955582,50.3554801941],"type":"Point"}
}