{
  "type": "Feature",
  "properties": {
    "iso:country":"DE",
    "sg:address":"Hoherainstr. 31",
    "sg:city":"Gladenbach",
    "sg:phone":"+49 6462/1431",
    "sg:postcode":"35075",
    "sg:province":"Hessen",
    "wof:name":"P. Will",
    "wof:placetype":"venue"
},
  "geometry": {"coordinates":[8.5803508759,50.7728767395],"type":"Point"}
}