{
  "type": "Feature",
  "properties": {
    "iso:country":"DE",
    "sg:address":"Wilhelm-Servas-Str. 21",
    "sg:city":"Rodalben",
    "sg:postcode":"66976",
    "sg:province":"Rheinland-Pfalz",
    "wof:name":"Fab Materialflu\u00df Und Automatisierung Gmbh",
    "wof:placetype":"venue"
},
  "geometry": {"coordinates":[7.626187,49.2416],"type":"Point"}
}