{
  "type": "Feature",
  "properties": {
    "iso:country":"DE",
    "sg:address":"Gravenbruchweg 84",
    "sg:city":"Offenbach",
    "sg:phone":"+49 69/837615",
    "sg:postcode":"63069",
    "sg:province":"Hessen",
    "wof:name":"Offenbacher Wollstube Elisabeth De Vivo",
    "wof:placetype":"venue"
},
  "geometry": {"coordinates":[8.759852,50.078335],"type":"Point"}
}