{
  "type": "Feature",
  "properties": {
    "iso:country":"DE",
    "sg:address":"Jakob-Stadler-Platz 3",
    "sg:city":"Konstanz",
    "sg:phone":"+49 7531/892920",
    "sg:postcode":"78467",
    "sg:province":"Baden-W\u00fcrttemberg",
    "wof:name":"Untersee Gmbh",
    "wof:placetype":"venue"
},
  "geometry": {"coordinates":[9.15466,47.670963],"type":"Point"}
}