{
  "type": "Feature",
  "properties": {
    "iso:country":"DE",
    "sg:address":"M\u00fchlau",
    "sg:city":"Kiefersfelden",
    "sg:phone":"+49 8033/1446",
    "sg:postcode":"83088",
    "sg:province":"Bayern",
    "wof:name":"Niederauer",
    "wof:placetype":"venue"
},
  "geometry": {"coordinates":[12.1521949768,47.6329193115],"type":"Point"}
}