{
  "type": "Feature",
  "properties": {
    "iso:country":"DE",
    "sg:address":"Kornstr 297-301",
    "sg:city":"Bremen",
    "sg:phone":"+49 421/53636",
    "sg:postcode":"28201",
    "sg:province":"Bremen",
    "wof:name":"Tandler Zahnrad- Und Getriebefabrik Gmbh & Co. Kg",
    "wof:placetype":"venue"
},
  "geometry": {"coordinates":[8.813851,53.055302],"type":"Point"}
}