{
  "type": "Feature",
  "properties": {
    "iso:country":"DE",
    "sg:address":"M\u00fchlgasse 12-15",
    "sg:city":"Erfurt",
    "sg:phone":"+49 361/5623534",
    "sg:postcode":"99084",
    "sg:province":"Th\u00fcringen",
    "wof:name":"Str\u00fcber & W\u00f6lke Gmbh & Co. Kg",
    "wof:placetype":"venue"
},
  "geometry": {"coordinates":[11.0342,50.975021],"type":"Point"}
}