{
  "type": "Feature",
  "properties": {
    "iso:country":"DE",
    "sg:address":"L\u00fcbecker Str. 30",
    "sg:city":"Schwerin",
    "sg:phone":"+49 385/5811691",
    "sg:postcode":"19053",
    "sg:province":"Mecklenburg-Vorpommern",
    "wof:name":"Schmidt & Partner Gmbh",
    "wof:placetype":"venue"
},
  "geometry": {"coordinates":[11.408156395,53.6294021606],"type":"Point"}
}