{
  "type": "Feature",
  "properties": {
    "iso:country":"DE",
    "sg:address":"Merziger Stra\u00dfe 3",
    "sg:city":"Beckingen",
    "sg:phone":"+49 6835",
    "sg:postcode":"66701",
    "sg:province":"Saarland",
    "wof:name":"Gartec Edelstahlm\u00f6bel F\u00fcr Gro\u00dfk\u00fcchen",
    "wof:placetype":"venue"
},
  "geometry": {"coordinates":[6.6711769104,49.3916664124],"type":"Point"}
}