{
  "type": "Feature",
  "properties": {
    "iso:country":"DE",
    "sg:address":"Zeppelinstr. 52",
    "sg:city":"Bremen",
    "sg:phone":"+49 421/456933",
    "sg:postcode":"28309",
    "sg:province":"Bremen",
    "wof:name":"Ulf M\u00fcller Steuerberater",
    "wof:placetype":"venue"
},
  "geometry": {"coordinates":[8.885974884,53.0654792786],"type":"Point"}
}