{
  "type": "Feature",
  "properties": {
    "iso:country":"DE",
    "sg:address":"Meschwitzstr. 5",
    "sg:city":"Dresden",
    "sg:phone":"+49 351/8043457",
    "sg:postcode":"01099",
    "sg:province":"Sachsen",
    "wof:name":"Dieter Otto Verlag",
    "wof:placetype":"venue"
},
  "geometry": {"coordinates":[13.7648963928,51.0843276978],"type":"Point"}
}