{
  "type": "Feature",
  "properties": {
    "iso:country":"DE",
    "sg:city":"Kolbermoor",
    "sg:phone":"+49 8031/98199",
    "sg:postcode":"83059",
    "sg:province":"Bayern",
    "wof:name":"Schlarb Wohnbau Gmbh",
    "wof:placetype":"venue"
},
  "geometry": {"coordinates":[12.065445,47.850155],"type":"Point"}
}