{
  "type": "Feature",
  "properties": {
    "iso:country":"DE",
    "sg:address":"Hindenburgstr. 8",
    "sg:city":"Weil der Stadt",
    "sg:phone":"+49 7033/80886",
    "sg:postcode":"71263",
    "sg:province":"Baden-W\u00fcrttemberg",
    "wof:name":"Manufaktur E.v. Weil Der Stadt",
    "wof:placetype":"venue"
},
  "geometry": {"coordinates":[8.865952,48.751945],"type":"Point"}
}