{
  "type": "Feature",
  "properties": {
    "iso:country":"DE",
    "sg:address":"G\u00f6\u00dfweinsteiner Gang 5",
    "sg:city":"Berlin",
    "sg:phone":"+49 30/3653158",
    "sg:postcode":"14089",
    "sg:province":"Berlin",
    "wof:name":"Ibevau Gesellschaft F\u00fcr Die Betreuung Von Immobilien Mbh",
    "wof:placetype":"venue"
},
  "geometry": {"coordinates":[13.136579,52.447411],"type":"Point"}
}