{
  "type": "Feature",
  "properties": {
    "iso:country":"DE",
    "sg:city":"Kalenborn",
    "sg:phone":"+49 2643/900075",
    "sg:postcode":"53505",
    "sg:province":"Rheinland-Pfalz",
    "wof:name":"Anita Br\u00f6cher",
    "wof:placetype":"venue"
},
  "geometry": {"coordinates":[6.9972,50.547916],"type":"Point"}
}