{
  "type": "Feature",
  "properties": {
    "iso:country":"DE",
    "sg:address":"Am R\u00f6merberg 11",
    "sg:city":"Kisselbach",
    "sg:phone":"+49 6766/1258",
    "sg:postcode":"56291",
    "sg:province":"Rheinland-Pfalz",
    "wof:name":"Horst Glitza Ingenieur",
    "wof:placetype":"venue"
},
  "geometry": {"coordinates":[7.6120858192,50.0521850586],"type":"Point"}
}