{
  "type": "Feature",
  "properties": {
    "iso:country":"DE",
    "sg:address":"Lust 26",
    "sg:city":"L\u00f6derburg",
    "sg:phone":"+49 39265/232",
    "sg:postcode":"39446",
    "sg:province":"Sachsen-Anhalt",
    "wof:name":"Klaus Dieckmann",
    "wof:placetype":"venue"
},
  "geometry": {"coordinates":[11.539727,51.878269],"type":"Point"}
}