{
  "type": "Feature",
  "properties": {
    "iso:country":"DE",
    "sg:address":"Raiffeisenstr. 27",
    "sg:city":"Wiesbaden",
    "sg:phone":"+49 611/507409",
    "sg:postcode":"65191",
    "sg:province":"Hessen",
    "wof:name":"A. Schneider & Sohn",
    "wof:placetype":"venue"
},
  "geometry": {"coordinates":[8.2831,50.084141],"type":"Point"}
}