{
  "type": "Feature",
  "properties": {
    "iso:country":"DE",
    "sg:address":"Wolfgangstr. 1",
    "sg:city":"Ellwangen",
    "sg:phone":"+49 7961/54370",
    "sg:postcode":"73479",
    "sg:province":"Baden-W\u00fcrttemberg",
    "wof:name":"Burkhard G\u00fcthlen",
    "wof:placetype":"venue"
},
  "geometry": {"coordinates":[10.129016,48.958523],"type":"Point"}
}