{
  "type": "Feature",
  "properties": {
    "iso:country":"DE",
    "sg:address":"Am Gries 3",
    "sg:city":"Rosenheim",
    "sg:postcode":"83026",
    "sg:province":"Bayern",
    "wof:name":"Rosenheimer Handy-b\u00f6rse E. K.",
    "wof:placetype":"venue"
},
  "geometry": {"coordinates":[12.1001243591,47.852394104],"type":"Point"}
}