{
  "type": "Feature",
  "properties": {
    "iso:country":"DE",
    "sg:address":"Feldbergstr. 11",
    "sg:city":"Wagh\u00e4usel",
    "sg:postcode":"68753",
    "sg:province":"Baden-W\u00fcrttemberg",
    "wof:name":"N. Schermesser",
    "wof:placetype":"venue"
},
  "geometry": {"coordinates":[8.518695,49.248852],"type":"Point"}
}