{
  "type": "Feature",
  "properties": {
    "iso:country":"DE",
    "sg:address":"Dittrichstr. 45",
    "sg:city":"Kamenz",
    "sg:phone":"+49 35783/04489",
    "sg:postcode":"01917",
    "sg:province":"Sachsen",
    "wof:name":"Gottfried Zawadzki",
    "wof:placetype":"venue"
},
  "geometry": {"coordinates":[14.10245,51.284534],"type":"Point"}
}