{
  "type": "Feature",
  "properties": {
    "iso:country":"DE",
    "sg:address":"Werkstr. 6",
    "sg:city":"Aachen",
    "sg:phone":"+49 241/1822250",
    "sg:postcode":"52076",
    "sg:province":"Nordrhein-Westfalen",
    "wof:name":"Fvt Faserverbundtechnik Gmbh",
    "wof:placetype":"venue"
},
  "geometry": {"coordinates":[6.137628,50.71246],"type":"Point"}
}