{
  "type": "Feature",
  "properties": {
    "iso:country":"DE",
    "sg:address":"Blasberg 17",
    "sg:city":"Burscheid",
    "sg:phone":"+49 2174/8538",
    "sg:postcode":"51399",
    "sg:province":"Nordrhein-Westfalen",
    "wof:name":"Restaurant Dorfkrug",
    "wof:placetype":"venue"
},
  "geometry": {"coordinates":[7.0997099876,51.0957946777],"type":"Point"}
}