{
  "type": "Feature",
  "properties": {
    "iso:country":"DE",
    "sg:address":"Herzogenring 6",
    "sg:city":"Wesel",
    "sg:phone":"+49 281/338130",
    "sg:postcode":"46483",
    "sg:province":"Nordrhein-Westfalen",
    "wof:name":"Beratungsstelle D. Caritas- Verbandes",
    "wof:placetype":"venue"
},
  "geometry": {"coordinates":[6.614735,51.661564],"type":"Point"}
}