{
  "type": "Feature",
  "properties": {
    "iso:country":"DE",
    "sg:address":"Teutoburger-Wald-Weg 17",
    "sg:city":"Werther",
    "sg:phone":"+49 5203/5999",
    "sg:postcode":"33824",
    "sg:province":"Nordrhein-Westfalen",
    "wof:name":"Robot Kanalinstandsetzung Verwaltungsgesellschaft Mbh",
    "wof:placetype":"venue"
},
  "geometry": {"coordinates":[8.4091501236,52.0655708313],"type":"Point"}
}