{
  "type": "Feature",
  "properties": {
    "iso:country":"DE",
    "sg:address":"Am Hummelbach 36",
    "sg:city":"Neuss",
    "sg:phone":"+49 2137/60712",
    "sg:postcode":"41469",
    "sg:province":"Nordrhein-Westfalen",
    "wof:name":"Montagebau G\u00fcnter Rasche Gmbh",
    "wof:placetype":"venue"
},
  "geometry": {"coordinates":[6.704813,51.147011],"type":"Point"}
}