{
  "type": "Feature",
  "properties": {
    "iso:country":"DE",
    "sg:address":"Am Steinkreuz",
    "sg:city":"Lohne",
    "sg:phone":"+49 4442/3336",
    "sg:postcode":"49393",
    "sg:province":"Niedersachsen",
    "wof:name":"Gastst\u00e4tte August B\u00fcnnemeyer",
    "wof:placetype":"venue"
},
  "geometry": {"coordinates":[8.2542724609,52.6599655151],"type":"Point"}
}