{
  "type": "Feature",
  "properties": {
    "iso:country":"DE",
    "sg:address":"Etschberger Str. 38",
    "sg:city":"Schellweiler",
    "sg:phone":"+49 6381/1608",
    "sg:postcode":"66869",
    "sg:province":"Rheinland-Pfalz",
    "wof:name":"Wolfgang Becker",
    "wof:placetype":"venue"
},
  "geometry": {"coordinates":[7.39389,49.514206],"type":"Point"}
}