{
  "type": "Feature",
  "properties": {
    "iso:country":"DE",
    "sg:address":"Wehdeler Str. 3",
    "sg:city":"Gehrde",
    "sg:phone":"+49 5439/2285",
    "sg:postcode":"49596",
    "sg:province":"Niedersachsen",
    "wof:name":"Walter Reinermann",
    "wof:placetype":"venue"
},
  "geometry": {"coordinates":[8.00932,52.593487],"type":"Point"}
}