{
  "type": "Feature",
  "properties": {
    "iso:country":"DE",
    "sg:address":"Hettstedter Str. 4",
    "sg:city":"Sandersleben",
    "sg:phone":"+49 34785/20223",
    "sg:postcode":"06456",
    "sg:province":"Sachsen-Anhalt",
    "wof:name":"Brs Bauschutt Und Recycling Gmbh",
    "wof:placetype":"venue"
},
  "geometry": {"coordinates":[11.559573,51.67588],"type":"Point"}
}