{
  "type": "Feature",
  "properties": {
    "iso:country":"DE",
    "sg:address":"Wittbr\u00e4ucker Str. 24",
    "sg:city":"Dortmund",
    "sg:phone":"+49 231/441833",
    "sg:postcode":"44287",
    "sg:province":"Nordrhein-Westfalen",
    "wof:name":"Otto Ussat Inh. Ulrich Beyer",
    "wof:placetype":"venue"
},
  "geometry": {"coordinates":[7.555018,51.48885],"type":"Point"}
}