{
  "type": "Feature",
  "properties": {
    "iso:country":"DE",
    "sg:address":"Karl-Theodor-Str. 2",
    "sg:city":"Bergisch Gladbach",
    "sg:phone":"+49 2204/53479",
    "sg:postcode":"51429",
    "sg:province":"Nordrhein-Westfalen",
    "wof:name":"Paul Schulte Architekt",
    "wof:placetype":"venue"
},
  "geometry": {"coordinates":[7.148612,50.96603],"type":"Point"}
}