{
  "type": "Feature",
  "properties": {
    "iso:country":"DE",
    "sg:address":"M\u00fchlenbergh\u00f6he 5",
    "sg:city":"Springe",
    "sg:phone":"+49 5045/1419",
    "sg:postcode":"31832",
    "sg:province":"Niedersachsen",
    "wof:name":"Reika Transport Gmbh",
    "wof:placetype":"venue"
},
  "geometry": {"coordinates":[9.7096881866,52.2125205994],"type":"Point"}
}