{
  "type": "Feature",
  "properties": {
    "iso:country":"DE",
    "sg:address":"S\u00fcdstr. 10",
    "sg:city":"Ottendorf-Okrilla",
    "sg:phone":"+49 35205/73835",
    "sg:postcode":"01458",
    "sg:province":"Sachsen",
    "wof:name":"C. Sch\u00fctze",
    "wof:placetype":"venue"
},
  "geometry": {"coordinates":[13.8323154449,51.1858444214],"type":"Point"}
}