{
  "type": "Feature",
  "properties": {
    "iso:country":"DE",
    "sg:address":"Dauborner Str. 6",
    "sg:city":"Brechen",
    "sg:phone":"+49 6438/4526",
    "sg:postcode":"65611",
    "sg:province":"Hessen",
    "wof:name":"Jung",
    "wof:placetype":"venue"
},
  "geometry": {"coordinates":[8.1589660645,50.3481254578],"type":"Point"}
}