{
  "type": "Feature",
  "properties": {
    "iso:country":"DE",
    "sg:address":"Gaehtjestr. 18",
    "sg:city":"Eckernf\u00f6rde",
    "sg:phone":"+49 4351/2526",
    "sg:postcode":"24340",
    "sg:province":"Schleswig-Holstein",
    "wof:name":"Couscherung Inh. F. Gey",
    "wof:placetype":"venue"
},
  "geometry": {"coordinates":[9.832597,54.474045],"type":"Point"}
}