{
  "type": "Feature",
  "properties": {
    "iso:country":"DE",
    "sg:address":"Hinterb\u00fcchelberg 17",
    "sg:city":"Abtsgm\u00fcnd",
    "sg:phone":"+49 7963/242",
    "sg:postcode":"73453",
    "sg:province":"Baden-W\u00fcrttemberg",
    "wof:name":"W. Sperle",
    "wof:placetype":"venue"
},
  "geometry": {"coordinates":[9.94624,48.941566],"type":"Point"}
}