{
  "type": "Feature",
  "properties": {
    "iso:country":"DE",
    "sg:address":"Westeroder Str. 14c",
    "sg:city":"Bad Harzburg",
    "sg:phone":"+49 5322/8591",
    "sg:postcode":"38667",
    "sg:province":"Niedersachsen",
    "wof:name":"Br\u00fcser-kranverleih Gmbh",
    "wof:placetype":"venue"
},
  "geometry": {"coordinates":[10.5490093231,51.8979606628],"type":"Point"}
}