{
  "type": "Feature",
  "properties": {
    "iso:country":"DE",
    "sg:address":"Sandbergweg 1",
    "sg:city":"Freden",
    "sg:phone":"+49 5184/206",
    "sg:postcode":"31084",
    "sg:province":"Niedersachsen",
    "wof:name":"Metallgie\u00dferei Freitag",
    "wof:placetype":"venue"
},
  "geometry": {"coordinates":[9.873082,51.932018],"type":"Point"}
}