{
  "type": "Feature",
  "properties": {
    "iso:country":"DE",
    "sg:address":"Marktplatz 27",
    "sg:city":"Grafenw\u00f6hr",
    "sg:phone":"+49 9641/3764",
    "sg:postcode":"92655",
    "sg:province":"Bayern",
    "wof:name":"Claudia Krause",
    "wof:placetype":"venue"
},
  "geometry": {"coordinates":[11.905457,49.721165],"type":"Point"}
}