{
  "type": "Feature",
  "properties": {
    "iso:country":"DE",
    "sg:address":"Neureutherstr. 28",
    "sg:city":"M\u00fcnchen",
    "sg:postcode":"80799",
    "sg:province":"Bayern",
    "wof:name":"Integrate Partners Unternehmensberatung Gmbh",
    "wof:placetype":"venue"
},
  "geometry": {"coordinates":[11.5705480576,48.1554794312],"type":"Point"}
}