{
  "type": "Feature",
  "properties": {
    "iso:country":"DE",
    "sg:city":"Zschornewitz",
    "sg:phone":"+49 34953/89500",
    "sg:postcode":"06791",
    "sg:province":"Sachsen-Anhalt",
    "wof:name":"A. Willmann",
    "wof:placetype":"venue"
},
  "geometry": {"coordinates":[12.399395,51.714287],"type":"Point"}
}