{
  "type": "Feature",
  "properties": {
    "iso:country":"DE",
    "sg:address":"Brechtener Str. 34",
    "sg:city":"Dortmund",
    "sg:phone":"+49 231/852720",
    "sg:postcode":"44339",
    "sg:province":"Nordrhein-Westfalen",
    "wof:name":"Hobach-eitel",
    "wof:placetype":"venue"
},
  "geometry": {"coordinates":[7.4822502136,51.5623092651],"type":"Point"}
}