{
  "type": "Feature",
  "properties": {
    "iso:country":"DE",
    "sg:address":"Wasgaustr. 30",
    "sg:city":"Frankfurt",
    "sg:phone":"+49 69/302735",
    "sg:postcode":"65929",
    "sg:province":"Hessen",
    "wof:name":"Josef Ehry Elektroinstallation",
    "wof:placetype":"venue"
},
  "geometry": {"coordinates":[8.535036,50.109722],"type":"Point"}
}