{
  "type": "Feature",
  "properties": {
    "iso:country":"DE",
    "sg:address":"Truderinger Str. 208",
    "sg:city":"M\u00fcnchen",
    "sg:phone":"+49 89/426451",
    "sg:postcode":"81825",
    "sg:province":"Bayern",
    "wof:name":"Coldweld Molecular Welding System R. Schinabeck & Co. Kg",
    "wof:placetype":"venue"
},
  "geometry": {"coordinates":[11.657612,48.126888],"type":"Point"}
}