{
  "type": "Feature",
  "properties": {
    "iso:country":"DE",
    "sg:address":"Reichenberger Str. 63",
    "sg:city":"Berlin",
    "sg:phone":"+49 30/6118102",
    "sg:postcode":"10999",
    "sg:province":"Berlin",
    "wof:name":"Monokel Optik Gmbh",
    "wof:placetype":"venue"
},
  "geometry": {"coordinates":[13.4305906296,52.4953079224],"type":"Point"}
}