{
  "type": "Feature",
  "properties": {
    "iso:country":"DE",
    "sg:address":"Westliche Ringstr 30",
    "sg:city":"Frankenthal",
    "sg:phone":"+49 6233/359300",
    "sg:postcode":"67227",
    "sg:province":"Rheinland-Pfalz",
    "wof:name":"9 Net Avenue Deutschland Gmbh",
    "wof:placetype":"venue"
},
  "geometry": {"coordinates":[8.352273941,49.5377883911],"type":"Point"}
}