{
  "type": "Feature",
  "properties": {
    "iso:country":"DE",
    "sg:address":"Stillerzeile 92",
    "sg:city":"Berlin",
    "sg:phone":"+49 30/6457602",
    "sg:postcode":"12587",
    "sg:province":"Berlin",
    "wof:name":"Lothar Pachale",
    "wof:placetype":"venue"
},
  "geometry": {"coordinates":[13.605055809,52.4539108276],"type":"Point"}
}