{
  "type": "Feature",
  "properties": {
    "iso:country":"DE",
    "sg:address":"Zwickauer Str. 235",
    "sg:city":"Chemnitz",
    "sg:phone":"+49 371/850410",
    "sg:postcode":"09116",
    "sg:province":"Sachsen",
    "wof:name":"Ambrosia Bestattungen Inh. Frank Blumstein",
    "wof:placetype":"venue"
},
  "geometry": {"coordinates":[12.87847,50.820107],"type":"Point"}
}