{
  "type": "Feature",
  "properties": {
    "iso:country":"DE",
    "sg:address":"Deichkamp 13",
    "sg:city":"Herford",
    "sg:postcode":"32051",
    "sg:province":"Nordrhein-Westfalen",
    "wof:name":"Apotheke Am Marktkauf Siamak Davoudi E. K.",
    "wof:placetype":"venue"
},
  "geometry": {"coordinates":[8.65774,52.11396],"type":"Point"}
}