{
  "type": "Feature",
  "properties": {
    "iso:country":"DE",
    "sg:address":"Gutenbergplatz 35",
    "sg:city":"Arnsberg",
    "sg:phone":"+49 2931/2028",
    "sg:postcode":"59821",
    "sg:province":"Nordrhein-Westfalen",
    "wof:name":"Sittler Sanit\u00e4tshaus Gmbh",
    "wof:placetype":"venue"
},
  "geometry": {"coordinates":[8.073358,51.397503],"type":"Point"}
}