{
  "type": "Feature",
  "properties": {
    "iso:country":"DE",
    "sg:address":"Horbellerstr. 33",
    "sg:city":"K\u00f6ln",
    "sg:phone":"+49 2234/955600",
    "sg:postcode":"50858",
    "sg:province":"Nordrhein-Westfalen",
    "wof:name":"L. Hopmann Maschinenfabrik Gmbh",
    "wof:placetype":"venue"
},
  "geometry": {"coordinates":[6.859414,50.914516],"type":"Point"}
}