{
  "type": "Feature",
  "properties": {
    "iso:country":"DE",
    "sg:address":"Gewerbepark 18",
    "sg:city":"Bissendorf",
    "sg:phone":"+49 4954/0298440",
    "sg:postcode":"49143",
    "sg:province":"Niedersachsen",
    "wof:name":"Cce Systemhaus Gmbh & Co. Kg",
    "wof:placetype":"venue"
},
  "geometry": {"coordinates":[8.1398820877,52.2410926819],"type":"Point"}
}