{
  "type": "Feature",
  "properties": {
    "iso:country":"DE",
    "sg:address":"Kaspar-Grove-Str. 32",
    "sg:city":"Marl",
    "sg:phone":"+49 2365/91250",
    "sg:postcode":"45768",
    "sg:province":"Nordrhein-Westfalen",
    "wof:name":"Hans-eberhard Severin Steuerberater",
    "wof:placetype":"venue"
},
  "geometry": {"coordinates":[7.0771350861,51.6489601135],"type":"Point"}
}