{
  "type": "Feature",
  "properties": {
    "iso:country":"DE",
    "sg:address":"T\u00f6lzer Str. 16",
    "sg:city":"Gr\u00fcnwald",
    "sg:postcode":"82031",
    "sg:province":"Bayern",
    "wof:name":"Bavaria Bautr\u00e4ger Und Bau- Betreuungs Gmbh",
    "wof:placetype":"venue"
},
  "geometry": {"coordinates":[11.521265,48.036842],"type":"Point"}
}