{
  "type": "Feature",
  "properties": {
    "iso:country":"DE",
    "sg:address":"Spreetaler-Stra\u00dfe-4",
    "sg:city":"Elsterheide",
    "sg:postcode":"02979",
    "sg:province":"Sachsen",
    "wof:name":"Bul Sachsen Gmbh",
    "wof:placetype":"venue"
},
  "geometry": {"coordinates":[14.184595108,51.5176124573],"type":"Point"}
}