{
  "type": "Feature",
  "properties": {
    "iso:country":"DE",
    "sg:address":"Obere Hauptstr. 73",
    "sg:city":"Oelsnitz",
    "sg:phone":"+49 37298/2123",
    "sg:postcode":"09376",
    "sg:province":"Sachsen",
    "wof:name":"R. Bauer",
    "wof:placetype":"venue"
},
  "geometry": {"coordinates":[12.682298,50.714222],"type":"Point"}
}