{
  "type": "Feature",
  "properties": {
    "iso:country":"DE",
    "sg:address":"M\u00fchlenlohne 5",
    "sg:city":"Norden",
    "sg:phone":"+49 4931/992827",
    "sg:postcode":"26506",
    "sg:province":"Niedersachsen",
    "wof:name":"D. Peters",
    "wof:placetype":"venue"
},
  "geometry": {"coordinates":[7.197572,53.593353],"type":"Point"}
}