{
  "type": "Feature",
  "properties": {
    "iso:country":"DE",
    "sg:address":"Vordere Str. 3",
    "sg:city":"Beimerstetten",
    "sg:phone":"+49 7348/5587",
    "sg:postcode":"89179",
    "sg:province":"Baden-W\u00fcrttemberg",
    "wof:name":"Post",
    "wof:placetype":"venue"
},
  "geometry": {"coordinates":[9.986948967,48.4826202393],"type":"Point"}
}