{
  "type": "Feature",
  "properties": {
    "iso:country":"DE",
    "sg:address":"Siedlung 7",
    "sg:city":"Steina",
    "sg:phone":"+49 35955/43256",
    "sg:postcode":"01920",
    "sg:province":"Sachsen",
    "wof:name":"Manfred Werner & Sohn",
    "wof:placetype":"venue"
},
  "geometry": {"coordinates":[14.0643911362,51.2008743286],"type":"Point"}
}