{
  "type": "Feature",
  "properties": {
    "iso:country":"DE",
    "sg:address":"Schleusinger Str. 21",
    "sg:city":"Hildburghausen",
    "sg:phone":"+49 3685/700491",
    "sg:postcode":"98646",
    "sg:province":"Th\u00fcringen",
    "wof:name":"Zahntechnik Hildburghausen Gbr",
    "wof:placetype":"venue"
},
  "geometry": {"coordinates":[10.7289266586,50.4296836853],"type":"Point"}
}