{
  "type": "Feature",
  "properties": {
    "iso:country":"DE",
    "sg:address":"Johannes-Prassel-Str. 3",
    "sg:city":"K\u00f6ln",
    "sg:phone":"+49 221/5901328",
    "sg:postcode":"50765",
    "sg:province":"Nordrhein-Westfalen",
    "wof:name":"Josef Schumacher",
    "wof:placetype":"venue"
},
  "geometry": {"coordinates":[6.8516559601,51.0146903992],"type":"Point"}
}