{
  "type": "Feature",
  "properties": {
    "iso:country":"DE",
    "sg:address":"Dorfstr. 33",
    "sg:city":"Gaildorf",
    "sg:phone":"+49 7971/6653",
    "sg:postcode":"74405",
    "sg:province":"Baden-W\u00fcrttemberg",
    "wof:name":"Emil Bei\u00dfwenger",
    "wof:placetype":"venue"
},
  "geometry": {"coordinates":[9.784812,48.996803],"type":"Point"}
}