{
  "type": "Feature",
  "properties": {
    "iso:country":"DE",
    "sg:address":"Atzelbergstr. 9",
    "sg:city":"Frankfurt",
    "sg:phone":"+49 69/471699",
    "sg:postcode":"60389",
    "sg:province":"Hessen",
    "wof:name":"Francisc Und Ute Moskovits",
    "wof:placetype":"venue"
},
  "geometry": {"coordinates":[8.718959,50.140728],"type":"Point"}
}