{
  "type": "Feature",
  "properties": {
    "iso:country":"DE",
    "sg:address":"Str\u00e4hlerweg 6b",
    "sg:city":"Karlsruhe",
    "sg:phone":"+49 721/407844",
    "sg:postcode":"76227",
    "sg:province":"Baden-W\u00fcrttemberg",
    "wof:name":"Marianne Schulz Krankengymnastin",
    "wof:placetype":"venue"
},
  "geometry": {"coordinates":[8.479886,48.994663],"type":"Point"}
}