{
  "type": "Feature",
  "properties": {
    "iso:country":"DE",
    "sg:address":"Gold-Zack-Str. 7",
    "sg:city":"Mettmann",
    "sg:phone":"+49 2104/9876",
    "sg:postcode":"40822",
    "sg:province":"Nordrhein-Westfalen",
    "wof:name":"Hts Haustechnik Service Gmbh & Co. Grundbesitz Kg",
    "wof:placetype":"venue"
},
  "geometry": {"coordinates":[7.0041279793,51.2513809204],"type":"Point"}
}