{
  "type": "Feature",
  "properties": {
    "iso:country":"DE",
    "sg:address":"Marktstr. 52",
    "sg:city":"Kirchheim",
    "sg:phone":"+49 7021/2536",
    "sg:postcode":"73230",
    "sg:province":"Baden-W\u00fcrttemberg",
    "wof:name":"H. Locher",
    "wof:placetype":"venue"
},
  "geometry": {"coordinates":[9.451171875,48.6466140747],"type":"Point"}
}