{
  "type": "Feature",
  "properties": {
    "iso:country":"DE",
    "sg:address":"M\u00f6serstr. 52-54",
    "sg:city":"Osnabr\u00fcck",
    "sg:postcode":"49074",
    "sg:province":"Niedersachsen",
    "wof:name":"Ims-verwaltungs- Gmbh",
    "wof:placetype":"venue"
},
  "geometry": {"coordinates":[8.0554971695,52.2731666565],"type":"Point"}
}