{
  "type": "Feature",
  "properties": {
    "iso:country":"DE",
    "sg:address":"Ahornweg 5",
    "sg:city":"Gusterath",
    "sg:phone":"+49 6588/7556",
    "sg:postcode":"54317",
    "sg:province":"Rheinland-Pfalz",
    "wof:name":"Gerd-dieter Gesink",
    "wof:placetype":"venue"
},
  "geometry": {"coordinates":[6.716917038,49.7018890381],"type":"Point"}
}