{
  "type": "Feature",
  "properties": {
    "iso:country":"DE",
    "sg:address":"Kanalstr. 30",
    "sg:city":"Heidenheim",
    "sg:phone":"+49 7321/21544",
    "sg:postcode":"89522",
    "sg:province":"Baden-W\u00fcrttemberg",
    "wof:name":"Club 30",
    "wof:placetype":"venue"
},
  "geometry": {"coordinates":[10.1575498581,48.6805915833],"type":"Point"}
}