{
  "type": "Feature",
  "properties": {
    "iso:country":"DE",
    "sg:address":"Gasland 3",
    "sg:city":"Wardenburg",
    "sg:phone":"+49 4407/1497",
    "sg:postcode":"26203",
    "sg:province":"Niedersachsen",
    "wof:name":"Heinz Meyer",
    "wof:placetype":"venue"
},
  "geometry": {"coordinates":[8.163361,53.03471],"type":"Point"}
}