{
  "type": "Feature",
  "properties": {
    "iso:country":"DE",
    "sg:address":"Am Stein 23",
    "sg:city":"Niestetal",
    "sg:phone":"+49 561/526812",
    "sg:postcode":"34266",
    "sg:province":"Hessen",
    "wof:name":"Ulrich M\u00fcller Steuerberater Und",
    "wof:placetype":"venue"
},
  "geometry": {"coordinates":[9.5675573349,51.3039588928],"type":"Point"}
}