{
  "type": "Feature",
  "properties": {
    "iso:country":"DE",
    "sg:address":"Gartenstr. 2a",
    "sg:city":"Neubrandenburg",
    "sg:phone":"+49 395/5668819",
    "sg:postcode":"17033",
    "sg:province":"Mecklenburg-Vorpommern",
    "wof:name":"Dieter Hacker",
    "wof:placetype":"venue"
},
  "geometry": {"coordinates":[13.266058,53.553726],"type":"Point"}
}