{
  "type": "Feature",
  "properties": {
    "iso:country":"DE",
    "sg:address":"Beckengasse 16",
    "sg:city":"Urbach",
    "sg:phone":"+49 7181/81258",
    "sg:postcode":"73660",
    "sg:province":"Baden-W\u00fcrttemberg",
    "wof:name":"Gerhard Walz",
    "wof:placetype":"venue"
},
  "geometry": {"coordinates":[9.5758609772,48.8169593811],"type":"Point"}
}