{
  "type": "Feature",
  "properties": {
    "iso:country":"DE",
    "sg:address":"Habichtweg 2",
    "sg:city":"Wiesloch",
    "sg:phone":"+49 6222/92430",
    "sg:postcode":"69168",
    "sg:province":"Baden-W\u00fcrttemberg",
    "wof:name":"Seew\u00f6rster",
    "wof:placetype":"venue"
},
  "geometry": {"coordinates":[8.701789856,49.2950439453],"type":"Point"}
}