{
  "type": "Feature",
  "properties": {
    "iso:country":"DE",
    "sg:address":"B\u00fcrgerm.-Steenbock-Str. 5",
    "sg:city":"Eutin",
    "sg:phone":"+49 4521/1000",
    "sg:postcode":"23701",
    "sg:province":"Schleswig-Holstein",
    "wof:name":"Dennis Smith Gmbh",
    "wof:placetype":"venue"
},
  "geometry": {"coordinates":[10.6180143356,54.130443573],"type":"Point"}
}