{
  "type": "Feature",
  "properties": {
    "iso:country":"DE",
    "sg:address":"Hauensteinstr. 8",
    "sg:city":"Senftenberg",
    "sg:phone":"+49 3573/64054",
    "sg:postcode":"01968",
    "sg:province":"Brandenburg",
    "wof:name":"Martin Dudacy",
    "wof:placetype":"venue"
},
  "geometry": {"coordinates":[13.989610672,51.5121879578],"type":"Point"}
}