{
  "type": "Feature",
  "properties": {
    "iso:country":"DE",
    "sg:address":"D\u00fcrener Str. 236",
    "sg:city":"K\u00f6ln",
    "sg:phone":"+49 221/403631",
    "sg:postcode":"50931",
    "sg:province":"Nordrhein-Westfalen",
    "wof:name":"Rainer Berr",
    "wof:placetype":"venue"
},
  "geometry": {"coordinates":[6.91067,50.928425],"type":"Point"}
}