{
  "type": "Feature",
  "properties": {
    "iso:country":"DE",
    "sg:address":"G\u00f6tzstr.6",
    "sg:city":"Worms",
    "sg:postcode":"67547",
    "sg:province":"Rheinland-Pfalz",
    "wof:name":"Rockband Superpowerplant",
    "wof:placetype":"venue"
},
  "geometry": {"coordinates":[8.365398,49.637569],"type":"Point"}
}