{
  "type": "Feature",
  "properties": {
    "iso:country":"DE",
    "sg:address":"K\u00fccknitzer Weg 1",
    "sg:city":"L\u00fcbeck",
    "sg:phone":"+49 451/394501",
    "sg:postcode":"23569",
    "sg:province":"Schleswig-Holstein",
    "wof:name":"Osma-aufz\u00fcge Albert Schenk Gmbh & Co. Kg",
    "wof:placetype":"venue"
},
  "geometry": {"coordinates":[10.7978630066,53.9142074585],"type":"Point"}
}