{
  "type": "Feature",
  "properties": {
    "iso:country":"DE",
    "sg:address":"Neustr. 4",
    "sg:city":"Nistertal",
    "sg:phone":"+49 2661/8335",
    "sg:postcode":"57647",
    "sg:province":"Rheinland-Pfalz",
    "wof:name":"Gro\u00df Verwaltungsges. Mbh",
    "wof:placetype":"venue"
},
  "geometry": {"coordinates":[7.905259,50.631653],"type":"Point"}
}