{
  "type": "Feature",
  "properties": {
    "iso:country":"DE",
    "sg:address":"Dorfstr. 54",
    "sg:city":"Much",
    "sg:phone":"+49 2245/3679",
    "sg:postcode":"53804",
    "sg:province":"Nordrhein-Westfalen",
    "wof:name":"Hermann B\u00fcth",
    "wof:placetype":"venue"
},
  "geometry": {"coordinates":[7.4433507919,50.8886604309],"type":"Point"}
}