{
  "type": "Feature",
  "properties": {
    "iso:country":"DE",
    "sg:address":"\u00d6tisheimer Str. 10",
    "sg:city":"M\u00fchlacker",
    "sg:phone":"+49 7041/6180",
    "sg:postcode":"75417",
    "sg:province":"Baden-W\u00fcrttemberg",
    "wof:name":"Erwin Mayer Grabdenkm\u00e4ler",
    "wof:placetype":"venue"
},
  "geometry": {"coordinates":[8.8364057541,48.948387146],"type":"Point"}
}