{
  "type": "Feature",
  "properties": {
    "iso:country":"DE",
    "sg:address":"Olkstr. 2",
    "sg:city":"Trittenheim",
    "sg:phone":"+49 6507/2815",
    "sg:postcode":"54349",
    "sg:province":"Rheinland-Pfalz",
    "wof:name":"Bernhard Kohr",
    "wof:placetype":"venue"
},
  "geometry": {"coordinates":[6.9018068314,49.8205528259],"type":"Point"}
}