{
  "type": "Feature",
  "properties": {
    "iso:country":"DE",
    "sg:address":"Hinter der Zehntscheuer 2",
    "sg:city":"Hilzingen",
    "sg:phone":"+49 7739/92930",
    "sg:postcode":"78247",
    "sg:province":"Baden-W\u00fcrttemberg",
    "wof:name":"R. Kreuzer Gmbh",
    "wof:placetype":"venue"
},
  "geometry": {"coordinates":[8.7288169861,47.7939186096],"type":"Point"}
}