{
  "type": "Feature",
  "properties": {
    "iso:country":"DE",
    "sg:address":"Friedensstr. 1",
    "sg:city":"Zittau",
    "sg:phone":"+49 3583/702503",
    "sg:postcode":"02763",
    "sg:province":"Sachsen",
    "wof:name":"Ursula Gei\u00dfler",
    "wof:placetype":"venue"
},
  "geometry": {"coordinates":[14.810351,50.892899],"type":"Point"}
}