{
  "type": "Feature",
  "properties": {
    "iso:country":"DE",
    "sg:address":"Lange Gasse 3",
    "sg:city":"Habichtswald",
    "sg:phone":"+49 5606/9795",
    "sg:postcode":"34317",
    "sg:province":"Hessen",
    "wof:name":"Horst G\u00f6rlitz Architekt",
    "wof:placetype":"venue"
},
  "geometry": {"coordinates":[9.341863,51.343079],"type":"Point"}
}