{
  "type": "Feature",
  "properties": {
    "iso:country":"DE",
    "sg:address":"K\u00f6lner Str. 76",
    "sg:city":"Dahlem",
    "sg:postcode":"53949",
    "sg:province":"Nordrhein-Westfalen",
    "wof:name":"Claraffa It-dienstleistungen Inh. Philipp R\u00fctz E. Kfm.",
    "wof:placetype":"venue"
},
  "geometry": {"coordinates":[6.545549,50.38998],"type":"Point"}
}