{
  "type": "Feature",
  "properties": {
    "iso:country":"DE",
    "sg:address":"Rosa-Luxemburg-Str. 11/12",
    "sg:city":"Altenburg",
    "sg:phone":"+49 3447/2517",
    "sg:postcode":"04600",
    "sg:province":"Th\u00fcringen",
    "wof:name":"Pbs Gmbh",
    "wof:placetype":"venue"
},
  "geometry": {"coordinates":[12.439367,50.990314],"type":"Point"}
}