{
  "type": "Feature",
  "properties": {
    "iso:country":"DE",
    "sg:address":"Bahnhofstr. 72",
    "sg:city":"Mudersbach",
    "sg:phone":"+49 2745/92030",
    "sg:postcode":"57555",
    "sg:province":"Rheinland-Pfalz",
    "wof:name":"Gebr. Becher Rohrleitungsbau Gmbh",
    "wof:placetype":"venue"
},
  "geometry": {"coordinates":[7.9407701492,50.8223075867],"type":"Point"}
}