{
  "type": "Feature",
  "properties": {
    "iso:country":"DE",
    "sg:address":"Kirchplatz 7",
    "sg:city":"Kitzingen",
    "sg:phone":"+49 9321/37752",
    "sg:postcode":"97318",
    "sg:province":"Bayern",
    "wof:name":"Beer Gmbh",
    "wof:placetype":"venue"
},
  "geometry": {"coordinates":[10.184643,49.721813],"type":"Point"}
}