{
  "type": "Feature",
  "properties": {
    "iso:country":"DE",
    "sg:address":"L\u00f6nsstr. 2",
    "sg:city":"Castrop-Rauxel",
    "sg:phone":"+49 2305/23630",
    "sg:postcode":"44575",
    "sg:province":"Nordrhein-Westfalen",
    "wof:name":"K. H. Klapputh",
    "wof:placetype":"venue"
},
  "geometry": {"coordinates":[7.3093361855,51.5479774475],"type":"Point"}
}