{
  "type": "Feature",
  "properties": {
    "iso:country":"DE",
    "sg:address":"Aueweg 1",
    "sg:city":"Sch\u00f6pstal",
    "sg:phone":"+49 3581/314769",
    "sg:postcode":"02829",
    "sg:province":"Sachsen",
    "wof:name":"Gr\u00fcne Aue",
    "wof:placetype":"venue"
},
  "geometry": {"coordinates":[14.9363698959,51.170501709],"type":"Point"}
}