{
  "type": "Feature",
  "properties": {
    "iso:country":"DE",
    "sg:address":"Wittekindweg 10",
    "sg:city":"Iserlohn",
    "sg:phone":"+49 2374/16270",
    "sg:postcode":"58642",
    "sg:province":"Nordrhein-Westfalen",
    "wof:name":"H. Und H. Wawrzyniak",
    "wof:placetype":"venue"
},
  "geometry": {"coordinates":[7.6315121651,51.374130249],"type":"Point"}
}