{
  "type": "Feature",
  "properties": {
    "iso:country":"DE",
    "sg:address":"Silberger Str. 5",
    "sg:city":"Kirchhundem",
    "sg:phone":"+49 2764/219",
    "sg:postcode":"57399",
    "sg:province":"Nordrhein-Westfalen",
    "wof:name":"E. Schmidt",
    "wof:placetype":"venue"
},
  "geometry": {"coordinates":[8.042797,51.033306],"type":"Point"}
}