{
  "type": "Feature",
  "properties": {
    "iso:country":"DE",
    "sg:address":"Ernst-Toller-Str. 15",
    "sg:city":"Halle",
    "sg:phone":"+49 345/2023578",
    "sg:postcode":"06110",
    "sg:province":"Sachsen-Anhalt",
    "wof:name":"Ulrich Spanka",
    "wof:placetype":"venue"
},
  "geometry": {"coordinates":[11.9793682098,51.4758262634],"type":"Point"}
}