{
  "type": "Feature",
  "properties": {
    "iso:country":"DE",
    "sg:address":"K\u00f6nigstr. 9",
    "sg:city":"Telgte",
    "sg:phone":"+49 2504/77592",
    "sg:postcode":"48291",
    "sg:province":"Nordrhein-Westfalen",
    "wof:name":"Simsek",
    "wof:placetype":"venue"
},
  "geometry": {"coordinates":[7.7832989693,51.9844894409],"type":"Point"}
}