{
  "type": "Feature",
  "properties": {
    "iso:country":"DE",
    "sg:address":"Spitalstr. 31",
    "sg:city":"Kuppenheim",
    "sg:phone":"+49 7222/4557",
    "sg:postcode":"76456",
    "sg:province":"Baden-W\u00fcrttemberg",
    "wof:name":"H. Semling Heissmangel",
    "wof:placetype":"venue"
},
  "geometry": {"coordinates":[8.2584886551,48.8250160217],"type":"Point"}
}