{
  "type": "Feature",
  "properties": {
    "iso:country":"DE",
    "sg:address":"Am Heerweg 6",
    "sg:city":"Rippach",
    "sg:phone":"+49 39978/51233",
    "sg:postcode":"06686",
    "sg:province":"Sachsen-Anhalt",
    "wof:name":"Hannah Gmbh",
    "wof:placetype":"venue"
},
  "geometry": {"coordinates":[12.4984102249,53.7799415588],"type":"Point"}
}