{
  "type": "Feature",
  "properties": {
    "iso:country":"DE",
    "sg:address":"Zeppelinstr. 17",
    "sg:city":"Haan",
    "sg:phone":"+49 212/958206",
    "sg:postcode":"42781",
    "sg:province":"Nordrhein-Westfalen",
    "wof:name":"Factory Projekt Gmbh",
    "wof:placetype":"venue"
},
  "geometry": {"coordinates":[7.000028,51.191162],"type":"Point"}
}