{
  "type": "Feature",
  "properties": {
    "iso:country":"DE",
    "sg:address":"Haltestelle R\u00f6ttingen",
    "sg:city":"Lauchheim",
    "sg:phone":"+49 7363/5164",
    "sg:postcode":"73466",
    "sg:province":"Baden-W\u00fcrttemberg",
    "wof:name":"Anton Feil",
    "wof:placetype":"venue"
},
  "geometry": {"coordinates":[10.2460699081,48.871761322],"type":"Point"}
}