{
  "type": "Feature",
  "properties": {
    "iso:country":"DE",
    "sg:address":"Sch\u00fctzenstr. 14 a",
    "sg:city":"Heinsberg",
    "sg:phone":"+49 2452/23504",
    "sg:postcode":"52525",
    "sg:province":"Nordrhein-Westfalen",
    "wof:name":"Heinz Speis",
    "wof:placetype":"venue"
},
  "geometry": {"coordinates":[6.097006,51.06702],"type":"Point"}
}