{
  "type": "Feature",
  "properties": {
    "iso:country":"DE",
    "sg:address":"Eschenweg 5",
    "sg:city":"T\u00fcbingen",
    "sg:phone":"+49 7071/61877",
    "sg:postcode":"72076",
    "sg:province":"Baden-W\u00fcrttemberg",
    "wof:name":"Elmar Maier Architekt",
    "wof:placetype":"venue"
},
  "geometry": {"coordinates":[9.062869,48.544609],"type":"Point"}
}