{
  "type": "Feature",
  "properties": {
    "iso:country":"DE",
    "sg:address":"Am Efing 27",
    "sg:city":"Bocholt",
    "sg:postcode":"46399",
    "sg:province":"Nordrhein-Westfalen",
    "wof:name":"Warnath Gmbh",
    "wof:placetype":"venue"
},
  "geometry": {"coordinates":[6.602903,51.848923],"type":"Point"}
}