{
  "type": "Feature",
  "properties": {
    "iso:country":"DE",
    "sg:address":"Stotternheimer Str. 45",
    "sg:city":"Erfurt",
    "sg:phone":"+49 361/73953",
    "sg:postcode":"99086",
    "sg:province":"Th\u00fcringen",
    "wof:name":"Metall Rohstoffe Th\u00fcringen Gmbh",
    "wof:placetype":"venue"
},
  "geometry": {"coordinates":[11.033655,51.009563],"type":"Point"}
}