{
  "type": "Feature",
  "properties": {
    "iso:country":"DE",
    "sg:address":"Hauptstr. 57",
    "sg:city":"Dernbach",
    "sg:phone":"+49 2602/69842",
    "sg:postcode":"56428",
    "sg:province":"Rheinland-Pfalz",
    "wof:name":"C. Schneider",
    "wof:placetype":"venue"
},
  "geometry": {"coordinates":[7.598324,50.54845],"type":"Point"}
}