{
  "type": "Feature",
  "properties": {
    "iso:country":"DE",
    "sg:address":"Amselweg 7",
    "sg:city":"Beilstein",
    "sg:phone":"+49 7062/5568",
    "sg:postcode":"71717",
    "sg:province":"Baden-W\u00fcrttemberg",
    "wof:name":"Albrecht Werner",
    "wof:placetype":"venue"
},
  "geometry": {"coordinates":[9.31588,49.043465],"type":"Point"}
}