{
  "type": "Feature",
  "properties": {
    "iso:country":"DE",
    "sg:address":"Lindenfelder Weg 19",
    "sg:city":"Bad Laasphe",
    "sg:phone":"+49 2752/9354",
    "sg:postcode":"57334",
    "sg:province":"Nordrhein-Westfalen",
    "wof:name":"Wilhelm M\u00fcsse",
    "wof:placetype":"venue"
},
  "geometry": {"coordinates":[8.348173,50.91539],"type":"Point"}
}