{
  "type": "Feature",
  "properties": {
    "iso:country":"DE",
    "sg:address":"Pastor-Wolff-Str. 65",
    "sg:city":"K\u00f6ln",
    "sg:phone":"+49 221/9711647",
    "sg:postcode":"50735",
    "sg:province":"Nordrhein-Westfalen",
    "wof:name":"Christian Scholl Architekt",
    "wof:placetype":"venue"
},
  "geometry": {"coordinates":[6.955618,50.99332],"type":"Point"}
}