{
  "type": "Feature",
  "properties": {
    "iso:country":"DE",
    "sg:address":"Lange Str. 4",
    "sg:city":"Schw\u00e4bisch Hall",
    "sg:phone":"+49 791/7741",
    "sg:postcode":"74523",
    "sg:province":"Baden-W\u00fcrttemberg",
    "wof:name":"Helmut Mohr",
    "wof:placetype":"venue"
},
  "geometry": {"coordinates":[9.7381229401,49.1139526367],"type":"Point"}
}