{
  "type": "Feature",
  "properties": {
    "iso:country":"DE",
    "sg:address":"Rheinstr. 53-55",
    "sg:city":"Neu-Isenburg",
    "sg:phone":"+49 6102/78850",
    "sg:postcode":"63263",
    "sg:province":"Hessen",
    "wof:name":"Gerhard W\u00fcst Architekt Und Bausachverst\u00e4nd.",
    "wof:placetype":"venue"
},
  "geometry": {"coordinates":[8.68527,50.054619],"type":"Point"}
}