{
  "type": "Feature",
  "properties": {
    "iso:country":"DE",
    "sg:address":"Hans-B\u00f6ckler-Str. 46",
    "sg:city":"Remscheid",
    "sg:phone":"+49 2191/953146",
    "sg:postcode":"42899",
    "sg:province":"Nordrhein-Westfalen",
    "wof:name":"G. Rathert",
    "wof:placetype":"venue"
},
  "geometry": {"coordinates":[7.23008,51.217602],"type":"Point"}
}