{
  "type": "Feature",
  "properties": {
    "iso:country":"DE",
    "sg:address":"Humboldtstr. 3",
    "sg:city":"Meckenbeuren",
    "sg:phone":"+49 7542/1613",
    "sg:postcode":"88074",
    "sg:province":"Baden-W\u00fcrttemberg",
    "wof:name":"G. Amann",
    "wof:placetype":"venue"
},
  "geometry": {"coordinates":[9.5604400635,47.6938591003],"type":"Point"}
}