{
  "type": "Feature",
  "properties": {
    "iso:country":"DE",
    "sg:address":"Edisonstr. 11",
    "sg:city":"Henstedt-Ulzburg",
    "sg:phone":"+49 4193/79047",
    "sg:postcode":"24558",
    "sg:province":"Schleswig-Holstein",
    "wof:name":"Akropolis Grill",
    "wof:placetype":"venue"
},
  "geometry": {"coordinates":[9.9821176529,53.7637290955],"type":"Point"}
}