{
  "type": "Feature",
  "properties": {
    "iso:country":"DE",
    "sg:address":"Burger Str. 100",
    "sg:city":"Remscheid",
    "sg:phone":"+49 2191/387723",
    "sg:postcode":"42859",
    "sg:province":"Nordrhein-Westfalen",
    "wof:name":"Bestattungen Limke Gmbh",
    "wof:placetype":"venue"
},
  "geometry": {"coordinates":[7.2011,51.167076],"type":"Point"}
}