{
  "type": "Feature",
  "properties": {
    "iso:country":"DE",
    "sg:address":"Bahnhofplatz 6",
    "sg:city":"Erlangen",
    "sg:phone":"+49 9131/129400",
    "sg:postcode":"91054",
    "sg:province":"Bayern",
    "wof:name":"Beko Markteting Und Vermittlungsges. Mbh",
    "wof:placetype":"venue"
},
  "geometry": {"coordinates":[11.0024776459,49.5957565308],"type":"Point"}
}