{
  "type": "Feature",
  "properties": {
    "iso:country":"DE",
    "sg:address":"Donauschwabenstr. 2",
    "sg:city":"Karlsruhe",
    "sg:phone":"+49 721/788346",
    "sg:postcode":"76149",
    "sg:province":"Baden-W\u00fcrttemberg",
    "wof:name":"K. F\u00fctterer",
    "wof:placetype":"venue"
},
  "geometry": {"coordinates":[8.3962745667,49.049861908],"type":"Point"}
}