{
  "type": "Feature",
  "properties": {
    "iso:country":"DE",
    "sg:address":"Otzinger Str. 20",
    "sg:city":"Otzing",
    "sg:phone":"+49 9931/8526",
    "sg:postcode":"94563",
    "sg:province":"Bayern",
    "wof:name":"Georg Arbinger",
    "wof:placetype":"venue"
},
  "geometry": {"coordinates":[12.820475,48.745461],"type":"Point"}
}