{
  "type": "Feature",
  "properties": {
    "iso:country":"DE",
    "sg:address":"Schlierseer Str. 26",
    "sg:city":"Bayrischzell",
    "sg:phone":"+49 8023/445",
    "sg:postcode":"83735",
    "sg:province":"Bayern",
    "wof:name":"Pritzl Gmbh",
    "wof:placetype":"venue"
},
  "geometry": {"coordinates":[12.009341,47.675976],"type":"Point"}
}