{
  "type": "Feature",
  "properties": {
    "iso:country":"DE",
    "sg:address":"Fellbacher Str. 52",
    "sg:city":"Fellbach",
    "sg:phone":"+49 711/511755",
    "sg:postcode":"70736",
    "sg:province":"Baden-W\u00fcrttemberg",
    "wof:name":"A. K\u00f6nigsdorfer",
    "wof:placetype":"venue"
},
  "geometry": {"coordinates":[9.2649106979,48.8296890259],"type":"Point"}
}