{
  "type": "Feature",
  "properties": {
    "iso:country":"DE",
    "sg:address":"Friedrichsschleuse 17",
    "sg:city":"Wittmund",
    "sg:phone":"+49 4464/384",
    "sg:postcode":"26409",
    "sg:province":"Niedersachsen",
    "wof:name":"K\u00fcsten-r\u00e4ucherei Johann Albrecht Gmbh",
    "wof:placetype":"venue"
},
  "geometry": {"coordinates":[7.8085727692,53.7014884949],"type":"Point"}
}