{
  "type": "Feature",
  "properties": {
    "iso:country":"DE",
    "sg:address":"Jahnstr. 6",
    "sg:city":"Geretsried",
    "sg:phone":"+49 8171/51216",
    "sg:postcode":"82538",
    "sg:province":"Bayern",
    "wof:name":"St\u00e4dt. Hallenbad",
    "wof:placetype":"venue"
},
  "geometry": {"coordinates":[11.476456,47.869556],"type":"Point"}
}