{
  "type": "Feature",
  "properties": {
    "iso:country":"DE",
    "sg:address":"Hindenburgstr. 255",
    "sg:city":"M\u00f6nchengladbach",
    "sg:phone":"+49 2161/52019",
    "sg:postcode":"41061",
    "sg:province":"Nordrhein-Westfalen",
    "wof:name":"W. Zanders",
    "wof:placetype":"venue"
},
  "geometry": {"coordinates":[6.44695,51.198952],"type":"Point"}
}