{
  "type": "Feature",
  "properties": {
    "iso:country":"DE",
    "sg:address":"Lindenweg",
    "sg:city":"Vollrathsruhe",
    "sg:postcode":"17194",
    "sg:province":"Mecklenburg-Vorpommern",
    "wof:name":"Kreisbetrieb F\u00fcr Land- Technik Waren",
    "wof:placetype":"venue"
},
  "geometry": {"coordinates":[12.48905,53.643444],"type":"Point"}
}