{
  "type": "Feature",
  "properties": {
    "iso:country":"DE",
    "sg:address":"Am K\u00f6nigsholz 14",
    "sg:city":"Bad Oeynhausen",
    "sg:phone":"+49 5731/940251",
    "sg:postcode":"32547",
    "sg:province":"Nordrhein-Westfalen",
    "wof:name":"Rolf Kottmeier Beteiligungsgesellschaft Mbh",
    "wof:placetype":"venue"
},
  "geometry": {"coordinates":[8.8424625397,52.1848297119],"type":"Point"}
}