{
  "type": "Feature",
  "properties": {
    "iso:country":"DE",
    "sg:address":"Untere Gasse 5",
    "sg:city":"M\u00f6ckm\u00fchl",
    "sg:phone":"+49 6298/1282",
    "sg:postcode":"74219",
    "sg:province":"Baden-W\u00fcrttemberg",
    "wof:name":"Spielwaren Hess",
    "wof:placetype":"venue"
},
  "geometry": {"coordinates":[9.3600730896,49.3229064941],"type":"Point"}
}