{
  "type": "Feature",
  "properties": {
    "iso:country":"DE",
    "sg:address":"Mark\u00f6beler Str. 2",
    "sg:city":"Neuberg",
    "sg:phone":"+49 6185/2499",
    "sg:postcode":"63543",
    "sg:province":"Hessen",
    "wof:name":"Weinhaus Gassenhauer",
    "wof:placetype":"venue"
},
  "geometry": {"coordinates":[8.9771308899,50.2034072876],"type":"Point"}
}