{
  "type": "Feature",
  "properties": {
    "iso:country":"DE",
    "sg:address":"Schweffelstr. 6",
    "sg:city":"Kiel",
    "sg:phone":"+49 4943/1565848",
    "sg:postcode":"24118",
    "sg:province":"Schleswig-Holstein",
    "wof:name":"Einblatt-druck",
    "wof:placetype":"venue"
},
  "geometry": {"coordinates":[10.1210365295,54.3324584961],"type":"Point"}
}