{
  "type": "Feature",
  "properties": {
    "iso:country":"DE",
    "sg:address":"Hauptstr. 16",
    "sg:city":"Stuttgart",
    "sg:phone":"+49 711/733035",
    "sg:postcode":"70563",
    "sg:province":"Baden-W\u00fcrttemberg",
    "wof:name":"Wolfgang Stikel Rechtsanwalt",
    "wof:placetype":"venue"
},
  "geometry": {"coordinates":[9.1100263596,48.7300071716],"type":"Point"}
}