{
  "type": "Feature",
  "properties": {
    "iso:country":"DE",
    "sg:address":"Borkener Str. 7",
    "sg:city":"Coesfeld",
    "sg:phone":"+49 2541/71042",
    "sg:postcode":"48653",
    "sg:province":"Nordrhein-Westfalen",
    "wof:name":"Buckting Gmbh",
    "wof:placetype":"venue"
},
  "geometry": {"coordinates":[7.160384,51.943985],"type":"Point"}
}