{
  "type": "Feature",
  "properties": {
    "iso:country":"DE",
    "sg:address":"Ostheimer Str. 16",
    "sg:city":"Hanau",
    "sg:phone":"+49 6181/840896",
    "sg:postcode":"63452",
    "sg:province":"Hessen",
    "wof:name":"Hanauer Heinzelm\u00e4nnchen E. K.",
    "wof:placetype":"venue"
},
  "geometry": {"coordinates":[8.911015,50.14883],"type":"Point"}
}