{
  "type": "Feature",
  "properties": {
    "iso:country":"DE",
    "sg:address":"Rudolf-Virchow-Str. 5",
    "sg:city":"Koblenz",
    "sg:phone":"+49 261/405314",
    "sg:postcode":"56073",
    "sg:province":"Rheinland-Pfalz",
    "wof:name":"Fachvermittlung F\u00fcr Binnenschiffer",
    "wof:placetype":"venue"
},
  "geometry": {"coordinates":[7.569992,50.358704],"type":"Point"}
}