{
  "type": "Feature",
  "properties": {
    "iso:country":"DE",
    "sg:address":"Gehlenbergstr. 4",
    "sg:city":"Saarbr\u00fccken",
    "sg:phone":"+49 6897/75320",
    "sg:postcode":"66125",
    "sg:province":"Saarland",
    "wof:name":"Bierquelle",
    "wof:placetype":"venue"
},
  "geometry": {"coordinates":[7.0505452156,49.2681236267],"type":"Point"}
}