{
  "type": "Feature",
  "properties": {
    "iso:country":"DE",
    "sg:address":"Canterstr. 19",
    "sg:city":"Ebersdorf",
    "sg:phone":"+49 9562/1283",
    "sg:postcode":"96237",
    "sg:province":"Bayern",
    "wof:name":"Rudolf Knorr",
    "wof:placetype":"venue"
},
  "geometry": {"coordinates":[11.067904,50.22097],"type":"Point"}
}