{
  "type": "Feature",
  "properties": {
    "iso:country":"DE",
    "sg:address":"Kirchstr. 51",
    "sg:city":"Besigheim",
    "sg:phone":"+49 7143/34917",
    "sg:postcode":"74354",
    "sg:province":"Baden-W\u00fcrttemberg",
    "wof:name":"Armin Schmid",
    "wof:placetype":"venue"
},
  "geometry": {"coordinates":[9.1424617767,48.9994125366],"type":"Point"}
}