{
  "type": "Feature",
  "properties": {
    "iso:country":"DE",
    "sg:address":"K\u00f6kelsumer Str. 64",
    "sg:city":"Olfen",
    "sg:phone":"+49 2595/961310",
    "sg:postcode":"59399",
    "sg:province":"Nordrhein-Westfalen",
    "wof:name":"Cornelia Linnert Rechtsanw\u00e4ltin",
    "wof:placetype":"venue"
},
  "geometry": {"coordinates":[7.3544588089,51.7221755981],"type":"Point"}
}