{
  "type": "Feature",
  "properties": {
    "iso:country":"DE",
    "sg:address":"Gingster Str. 16",
    "sg:city":"Samtens",
    "sg:postcode":"18573",
    "sg:province":"Mecklenburg-Vorpommern",
    "wof:name":"Dr. Stefan Krajci-lazari",
    "wof:placetype":"venue"
},
  "geometry": {"coordinates":[13.292236,54.357903],"type":"Point"}
}