{
  "type": "Feature",
  "properties": {
    "iso:country":"DE",
    "sg:address":"Waldstr. 2",
    "sg:city":"Starnberg",
    "sg:phone":"+49 8151/3279",
    "sg:postcode":"82319",
    "sg:province":"Bayern",
    "wof:name":"Bildarchiv Des Anthony-verlags",
    "wof:placetype":"venue"
},
  "geometry": {"coordinates":[11.332735,47.991158],"type":"Point"}
}