{
  "type": "Feature",
  "properties": {
    "iso:country":"DE",
    "sg:address":"Gartenstr. 15",
    "sg:city":"Bietigheim",
    "sg:phone":"+49 7245/81672",
    "sg:postcode":"76467",
    "sg:province":"Baden-W\u00fcrttemberg",
    "wof:name":"Ambiente Bautr\u00e4ger- Gesellschaft Mbh",
    "wof:placetype":"venue"
},
  "geometry": {"coordinates":[8.255024,48.910961],"type":"Point"}
}