{
  "type": "Feature",
  "properties": {
    "iso:country":"DE",
    "sg:address":"Bahnhofstr. 15",
    "sg:city":"Garmisch-Partenkirchen",
    "sg:phone":"+49 8821/943870",
    "sg:postcode":"82467",
    "sg:province":"Bayern",
    "wof:name":"Hotel Patenkirchener Hof",
    "wof:placetype":"venue"
},
  "geometry": {"coordinates":[11.1010465622,47.4921607971],"type":"Point"}
}