{
  "type": "Feature",
  "properties": {
    "iso:country":"DE",
    "sg:address":"Bebelstr. 18",
    "sg:city":"Herne",
    "sg:phone":"+49 2323/51266",
    "sg:postcode":"44623",
    "sg:province":"Nordrhein-Westfalen",
    "wof:name":"Heinrich Wiedeler Dachdeckerbetrieb Gmbh",
    "wof:placetype":"venue"
},
  "geometry": {"coordinates":[7.220155,51.539745],"type":"Point"}
}