{
  "type": "Feature",
  "properties": {
    "iso:country":"DE",
    "sg:address":"Neuplanitzer Str. 31",
    "sg:city":"Zwickau",
    "sg:postcode":"08062",
    "sg:province":"Sachsen",
    "wof:name":"Elkon Ges. F\u00fcr Elektro- Technische Steuerungen Und",
    "wof:placetype":"venue"
},
  "geometry": {"coordinates":[12.4642858505,50.6940917969],"type":"Point"}
}