{
  "type": "Feature",
  "properties": {
    "iso:country":"DE",
    "sg:address":"Carl-Zeiss-Str. 42",
    "sg:city":"G\u00fctersloh",
    "sg:phone":"+49 5241/6004810",
    "sg:postcode":"33334",
    "sg:province":"Nordrhein-Westfalen",
    "wof:name":"Heinz Stoltefu\u00df Gmbh & Co.",
    "wof:placetype":"venue"
},
  "geometry": {"coordinates":[8.4156923294,51.9290390015],"type":"Point"}
}