{
  "type": "Feature",
  "properties": {
    "iso:country":"DE",
    "sg:address":"Empelder Str. 10",
    "sg:city":"Ronnenberg",
    "sg:phone":"+49 5109/1539",
    "sg:postcode":"30952",
    "sg:province":"Niedersachsen",
    "wof:name":"Ehrhardt Objektbetreuungs Gmbh",
    "wof:placetype":"venue"
},
  "geometry": {"coordinates":[9.662508,52.320881],"type":"Point"}
}