{
  "type": "Feature",
  "properties": {
    "iso:country":"DE",
    "sg:address":"Weinbergsweg 20",
    "sg:city":"Berlin",
    "sg:phone":"+49 30/4496389",
    "sg:postcode":"10119",
    "sg:province":"Berlin",
    "wof:name":"Mountain Bike Center Berlin Inh. S. K\u00f6nig",
    "wof:placetype":"venue"
},
  "geometry": {"coordinates":[13.402535,52.531467],"type":"Point"}
}