{
  "type": "Feature",
  "properties": {
    "iso:country":"DE",
    "sg:address":"Kirchsteig 2",
    "sg:city":"Trossingen",
    "sg:phone":"+49 7425/4751",
    "sg:postcode":"78647",
    "sg:province":"Baden-W\u00fcrttemberg",
    "wof:name":"Brigitte Heizmann",
    "wof:placetype":"venue"
},
  "geometry": {"coordinates":[8.6501913071,48.0803337097],"type":"Point"}
}