{
  "type": "Feature",
  "properties": {
    "iso:country":"DE",
    "sg:address":"Warendorfer Str. 82",
    "sg:city":"Oelde",
    "sg:phone":"+49 2522/5402",
    "sg:postcode":"59302",
    "sg:province":"Nordrhein-Westfalen",
    "wof:name":"Albert Krampe",
    "wof:placetype":"venue"
},
  "geometry": {"coordinates":[8.1423168182,51.8228912354],"type":"Point"}
}