{
  "type": "Feature",
  "properties": {
    "iso:country":"DE",
    "sg:address":"Stiftsgeh\u00f6lz 20",
    "sg:city":"Dortmund",
    "sg:phone":"+49 231/47115",
    "sg:postcode":"44265",
    "sg:province":"Nordrhein-Westfalen",
    "wof:name":"Inge Raschke Spielsalon Gmbh",
    "wof:placetype":"venue"
},
  "geometry": {"coordinates":[7.4933409691,51.4563980103],"type":"Point"}
}