{
  "type": "Feature",
  "properties": {
    "iso:country":"DE",
    "sg:address":"Auf der H\u00f6he 14",
    "sg:city":"Finning",
    "sg:phone":"+49 8806/9360",
    "sg:postcode":"86923",
    "sg:province":"Bayern",
    "wof:name":"Kriebel Verlag Gmbh",
    "wof:placetype":"venue"
},
  "geometry": {"coordinates":[11.0167255402,48.0247001648],"type":"Point"}
}