{
  "type": "Feature",
  "properties": {
    "iso:country":"DE",
    "sg:address":"Farmstr. 14",
    "sg:city":"M\u00f6rfelden Walldorf",
    "sg:phone":"+49 4961/0571033",
    "sg:postcode":"64546",
    "sg:province":"Hessen",
    "wof:name":"Gro\u00df-gerauer Volksbank Eg",
    "wof:placetype":"venue"
},
  "geometry": {"coordinates":[8.580107,50.001793],"type":"Point"}
}