{
  "type": "Feature",
  "properties": {
    "iso:country":"DE",
    "sg:address":"Am Butterh\u00fcgel 6",
    "sg:city":"Bexbach",
    "sg:postcode":"66450",
    "sg:province":"Saarland",
    "wof:name":"Sushi - San Gmbh",
    "wof:placetype":"venue"
},
  "geometry": {"coordinates":[7.2826180458,49.3449859619],"type":"Point"}
}