{
  "type": "Feature",
  "properties": {
    "iso:country":"DE",
    "sg:address":"Rechbergstr. 12",
    "sg:city":"Heubach",
    "sg:phone":"+49 7173/2773",
    "sg:postcode":"73540",
    "sg:province":"Baden-W\u00fcrttemberg",
    "wof:name":"W. Marquardt",
    "wof:placetype":"venue"
},
  "geometry": {"coordinates":[9.928817749,48.7977561951],"type":"Point"}
}