{
  "type": "Feature",
  "properties": {
    "iso:country":"DE",
    "sg:address":"Reinickendorfer Str. 70",
    "sg:city":"Berlin",
    "sg:phone":"+49 30/4564696",
    "sg:postcode":"13347",
    "sg:province":"Berlin",
    "wof:name":"Ali Koc",
    "wof:placetype":"venue"
},
  "geometry": {"coordinates":[13.3665571213,52.5523490906],"type":"Point"}
}