{
  "type": "Feature",
  "properties": {
    "iso:country":"DE",
    "sg:address":"Adolf-Murthum-Str. 20",
    "sg:city":"Leinfelden-Echterdingen",
    "sg:phone":"+49 711/793460",
    "sg:postcode":"70771",
    "sg:province":"Baden-W\u00fcrttemberg",
    "wof:name":"Eberhard Vollmer",
    "wof:placetype":"venue"
},
  "geometry": {"coordinates":[9.1617660522,48.6879386902],"type":"Point"}
}