{
  "type": "Feature",
  "properties": {
    "iso:country":"DE",
    "sg:address":"Hermann-L\u00f6ns-Str. 16",
    "sg:city":"S\u00f6hrewald",
    "sg:phone":"+49 5608/860",
    "sg:postcode":"34320",
    "sg:province":"Hessen",
    "wof:name":"J\u00fcrgen Vesper Gmbh",
    "wof:placetype":"venue"
},
  "geometry": {"coordinates":[9.588138,51.193497],"type":"Point"}
}