{
  "type": "Feature",
  "properties": {
    "iso:country":"DE",
    "sg:address":"Gr\u00e4sseweg 6",
    "sg:city":"Berlin",
    "sg:phone":"+49 30/35103006",
    "sg:postcode":"13581",
    "sg:province":"Berlin",
    "wof:name":"Marco Seel",
    "wof:placetype":"venue"
},
  "geometry": {"coordinates":[13.1727285385,52.5288848877],"type":"Point"}
}