{
  "type": "Feature",
  "properties": {
    "iso:country":"DE",
    "sg:address":"Gro\u00dfstr. 115",
    "sg:city":"Treuenbrietzen",
    "sg:phone":"+49 33748/207",
    "sg:postcode":"14929",
    "sg:province":"Brandenburg",
    "wof:name":"Kreissparkasse",
    "wof:placetype":"venue"
},
  "geometry": {"coordinates":[12.87257,52.098045],"type":"Point"}
}