{
  "type": "Feature",
  "properties": {
    "iso:country":"DE",
    "sg:address":"Wildh\u00fcterweg 45",
    "sg:city":"Berlin",
    "sg:phone":"+49 30/6052958",
    "sg:postcode":"12353",
    "sg:province":"Berlin",
    "wof:name":"Werner Gappa",
    "wof:placetype":"venue"
},
  "geometry": {"coordinates":[13.448982,52.421162],"type":"Point"}
}