{
  "type": "Feature",
  "properties": {
    "iso:country":"DE",
    "sg:address":"Am Eutsch\u00fctzgrund 4",
    "sg:city":"Bannewitz",
    "sg:phone":"+49 351/4034016",
    "sg:postcode":"01728",
    "sg:province":"Sachsen",
    "wof:name":"Tgb Schwei\u00dftechnischer Fachhandel Gmbh",
    "wof:placetype":"venue"
},
  "geometry": {"coordinates":[13.724557,50.995396],"type":"Point"}
}