{
  "type": "Feature",
  "properties": {
    "iso:country":"DE",
    "sg:address":"Bahnhofstr. 20",
    "sg:city":"Schwandorf",
    "sg:phone":"+49 9431/2329",
    "sg:postcode":"92421",
    "sg:province":"Bayern",
    "wof:name":"Josef Braun",
    "wof:placetype":"venue"
},
  "geometry": {"coordinates":[12.1074056625,49.3280410767],"type":"Point"}
}