{
  "type": "Feature",
  "properties": {
    "iso:country":"DE",
    "sg:address":"Dorfstr. 6",
    "sg:city":"Eichwerder",
    "sg:phone":"+49 33456/543",
    "sg:postcode":"16269",
    "sg:province":"Brandenburg",
    "wof:name":"Getr\u00e4nke-strache- Gmbh",
    "wof:placetype":"venue"
},
  "geometry": {"coordinates":[14.1325063705,52.7218971252],"type":"Point"}
}