{
  "type": "Feature",
  "properties": {
    "iso:country":"DE",
    "sg:address":"Bahnhofstr. 5",
    "sg:city":"W\u00fcrzburg",
    "sg:phone":"+49 931/15031",
    "sg:postcode":"97070",
    "sg:province":"Bayern",
    "wof:name":"Sonja Imhof Rechtsanw\u00e4ltin",
    "wof:placetype":"venue"
},
  "geometry": {"coordinates":[9.9351100922,49.798500061],"type":"Point"}
}