{
  "type": "Feature",
  "properties": {
    "iso:country":"DE",
    "sg:address":"Postfach 11 80",
    "sg:city":"Wilhelmsfeld",
    "sg:postcode":"69259",
    "sg:province":"Baden-W\u00fcrttemberg",
    "wof:name":"Gottfried Egert Verlag",
    "wof:placetype":"venue"
},
  "geometry": {"coordinates":[8.754409,49.470188],"type":"Point"}
}