{
  "type": "Feature",
  "properties": {
    "iso:country":"DE",
    "sg:address":"Rauentaler Str. 12",
    "sg:city":"Rastatt",
    "sg:phone":"+49 7222/51008",
    "sg:postcode":"76437",
    "sg:province":"Baden-W\u00fcrttemberg",
    "wof:name":"Fritz & Saumer",
    "wof:placetype":"venue"
},
  "geometry": {"coordinates":[8.2158966064,48.8591308594],"type":"Point"}
}