{
  "type": "Feature",
  "properties": {
    "iso:country":"DE",
    "sg:address":"Industriestr. 14",
    "sg:city":"Traunstein",
    "sg:phone":"+49 861/2052",
    "sg:postcode":"83278",
    "sg:province":"Bayern",
    "wof:name":"Willy Raschke & S\u00f6hne Autolackiererei Gmbh",
    "wof:placetype":"venue"
},
  "geometry": {"coordinates":[12.62751,47.88736],"type":"Point"}
}