{
  "type": "Feature",
  "properties": {
    "iso:country":"DE",
    "sg:address":"Bissingzeile 11",
    "sg:city":"Berlin",
    "sg:phone":"+49 30/26101691",
    "sg:postcode":"10785",
    "sg:province":"Berlin",
    "wof:name":"Skygames",
    "wof:placetype":"venue"
},
  "geometry": {"coordinates":[13.369833,52.503574],"type":"Point"}
}