{
  "type": "Feature",
  "properties": {
    "iso:country":"DE",
    "sg:address":"Erftstr. 38",
    "sg:city":"M\u00f6nchengladbach",
    "sg:phone":"+49 4921/6698640",
    "sg:postcode":"41238",
    "sg:province":"Nordrhein-Westfalen",
    "wof:name":"Hitachi Seiki Deutschland Werkzeugmaschinen Gmbh",
    "wof:placetype":"venue"
},
  "geometry": {"coordinates":[6.502065,51.159546],"type":"Point"}
}