{
  "type": "Feature",
  "properties": {
    "iso:country":"DE",
    "sg:address":"B\u00fcrgerm.-Bodmeier-Str. 13",
    "sg:city":"Pfaffing",
    "sg:phone":"+49 8076/1093",
    "sg:postcode":"83539",
    "sg:province":"Bayern",
    "wof:name":"Wilhelm Vosteen",
    "wof:placetype":"venue"
},
  "geometry": {"coordinates":[12.10916996,48.0552711487],"type":"Point"}
}