{
  "type": "Feature",
  "properties": {
    "iso:country":"DE",
    "sg:address":"Gehrenweg 9a",
    "sg:city":"Gleichen",
    "sg:phone":"+49 551/792764",
    "sg:postcode":"37130",
    "sg:province":"Niedersachsen",
    "wof:name":"Windkraft Diemarden Verwaltungsgesellschaft Mbh",
    "wof:placetype":"venue"
},
  "geometry": {"coordinates":[9.971804,51.485992],"type":"Point"}
}