{
  "type": "Feature",
  "properties": {
    "iso:country":"DE",
    "sg:address":"Neubrunnstr. 4",
    "sg:city":"Sennfeld",
    "sg:phone":"+49 9721/68031",
    "sg:postcode":"97526",
    "sg:province":"Bayern",
    "wof:name":"Helmut Rudloff",
    "wof:placetype":"venue"
},
  "geometry": {"coordinates":[10.260279,50.04258],"type":"Point"}
}