{
  "type": "Feature",
  "properties": {
    "iso:country":"DE",
    "sg:address":"Am Trieb 15",
    "sg:city":"K\u00fcrnach",
    "sg:phone":"+49 9367/7700",
    "sg:postcode":"97273",
    "sg:province":"Bayern",
    "wof:name":"Restaurant H\u00f6llberg",
    "wof:placetype":"venue"
},
  "geometry": {"coordinates":[10.0471200943,49.8417205811],"type":"Point"}
}