{
  "type": "Feature",
  "properties": {
    "iso:country":"DE",
    "sg:address":"G\u00fcrtelstr. 41",
    "sg:city":"Berlin",
    "sg:phone":"+49 30/293830",
    "sg:postcode":"10247",
    "sg:province":"Berlin",
    "wof:name":"Picco Hotel",
    "wof:placetype":"venue"
},
  "geometry": {"coordinates":[13.4753656387,52.5115356445],"type":"Point"}
}