{
  "type": "Feature",
  "properties": {
    "iso:country":"DE",
    "sg:address":"Gewerbering 4",
    "sg:city":"Richtenberg",
    "sg:phone":"+49 4938/3225380",
    "sg:postcode":"18461",
    "sg:province":"Mecklenburg-Vorpommern",
    "wof:name":"Rohstoff Recycling Rostock Gmbh & Co. Kg Filiale Preuhs U. K\u00dcnstler",
    "wof:placetype":"venue"
},
  "geometry": {"coordinates":[12.90558815,54.2032432556],"type":"Point"}
}