{
  "type": "Feature",
  "properties": {
    "iso:country":"DE",
    "sg:address":"Karlstr. 17",
    "sg:city":"Hermaringen",
    "sg:postcode":"89568",
    "sg:province":"Baden-W\u00fcrttemberg",
    "wof:name":"Hermia Gmbh",
    "wof:placetype":"venue"
},
  "geometry": {"coordinates":[9.992445,53.553345],"type":"Point"}
}