{
  "type": "Feature",
  "properties": {
    "iso:country":"DE",
    "sg:address":"Lutterstr.",
    "sg:city":"Bielefeld",
    "sg:phone":"+49 521/520601",
    "sg:postcode":"33617",
    "sg:province":"Nordrhein-Westfalen",
    "wof:name":"Omnia Media Service Gmbh",
    "wof:placetype":"venue"
},
  "geometry": {"coordinates":[8.519989,52.014748],"type":"Point"}
}