{
  "type": "Feature",
  "properties": {
    "iso:country":"DE",
    "sg:address":"Sophienstr. 19/21",
    "sg:city":"L\u00fcbeck",
    "sg:postcode":"23560",
    "sg:province":"Schleswig-Holstein",
    "wof:name":"Mirodata Services Gmbh",
    "wof:placetype":"venue"
},
  "geometry": {"coordinates":[10.68639,53.856079],"type":"Point"}
}