{
  "type": "Feature",
  "properties": {
    "iso:country":"DE",
    "sg:address":"Scherzachstr. 4",
    "sg:city":"Schlier",
    "sg:phone":"+49 7529/3770",
    "sg:postcode":"88281",
    "sg:province":"Baden-W\u00fcrttemberg",
    "wof:name":"H\u00f6rger & Partner Beteiligungs-gmbh",
    "wof:placetype":"venue"
},
  "geometry": {"coordinates":[9.670383,47.772274],"type":"Point"}
}