{
  "type": "Feature",
  "properties": {
    "iso:country":"DE",
    "sg:address":"Karl-Marx-Str. 32",
    "sg:city":"Dortmund",
    "sg:phone":"+49 231/573027",
    "sg:postcode":"44141",
    "sg:province":"Nordrhein-Westfalen",
    "wof:name":"Heinrich Hopmeier Und H. Tiemann",
    "wof:placetype":"venue"
},
  "geometry": {"coordinates":[7.4814291,51.5045127869],"type":"Point"}
}