{
  "type": "Feature",
  "properties": {
    "iso:country":"DE",
    "sg:address":"Im Hasseldamm 23",
    "sg:city":"Korschenbroich",
    "sg:phone":"+49 2161/67448",
    "sg:postcode":"41352",
    "sg:province":"Nordrhein-Westfalen",
    "wof:name":"Helmut Schelesniak",
    "wof:placetype":"venue"
},
  "geometry": {"coordinates":[6.545476,51.215485],"type":"Point"}
}