{
  "type": "Feature",
  "properties": {
    "iso:country":"DE",
    "sg:address":"Wachtelweg 17",
    "sg:city":"Langen",
    "sg:phone":"+49 4743/4185",
    "sg:postcode":"27607",
    "sg:province":"Niedersachsen",
    "wof:name":"Isabell Schneithorst",
    "wof:placetype":"venue"
},
  "geometry": {"coordinates":[8.582226,53.598297],"type":"Point"}
}