{
  "type": "Feature",
  "properties": {
    "iso:country":"DE",
    "sg:address":"Karlstr. 8",
    "sg:city":"Deizisau",
    "sg:phone":"+49 7153/28261",
    "sg:postcode":"73779",
    "sg:province":"Baden-W\u00fcrttemberg",
    "wof:name":"A. Paul",
    "wof:placetype":"venue"
},
  "geometry": {"coordinates":[9.3823270798,48.713180542],"type":"Point"}
}