{
  "type": "Feature",
  "properties": {
    "iso:country":"DE",
    "sg:address":"Delitzscher Str. 72",
    "sg:city":"Halle",
    "sg:phone":"+49 345/5600214",
    "sg:postcode":"06112",
    "sg:province":"Sachsen-Anhalt",
    "wof:name":"Ilka Chemie Handelsgesellschaft Mbh",
    "wof:placetype":"venue"
},
  "geometry": {"coordinates":[12.0038700104,51.4785690308],"type":"Point"}
}