{
  "type": "Feature",
  "properties": {
    "iso:country":"DE",
    "sg:address":"Frohmarkt 6",
    "sg:city":"Oberstdorf",
    "sg:phone":"+49 8322/3464",
    "sg:postcode":"87561",
    "sg:province":"Bayern",
    "wof:name":"Fremdenheim Luise Feurstein",
    "wof:placetype":"venue"
},
  "geometry": {"coordinates":[10.2810163498,47.4063529968],"type":"Point"}
}