{
  "type": "Feature",
  "properties": {
    "iso:country":"DE",
    "sg:address":"Schertlinstr. 25",
    "sg:city":"Augsburg",
    "sg:phone":"+49 821/259670",
    "sg:postcode":"86159",
    "sg:province":"Bayern",
    "wof:name":"Manage It Gmbh & Co. Kg",
    "wof:placetype":"venue"
},
  "geometry": {"coordinates":[10.8965959549,48.3529891968],"type":"Point"}
}