{
  "type": "Feature",
  "properties": {
    "iso:country":"DE",
    "sg:address":"M\u00fchlenstr. 4",
    "sg:city":"Hamwarde",
    "sg:phone":"+49 4152/3998",
    "sg:postcode":"21502",
    "sg:province":"Schleswig-Holstein",
    "wof:name":"G\u00fcnter Lemke Gmbh",
    "wof:placetype":"venue"
},
  "geometry": {"coordinates":[10.421265,53.451462],"type":"Point"}
}