{
  "type": "Feature",
  "properties": {
    "iso:country":"DE",
    "sg:address":"Gustav-Heinemann-Ufer 86-88",
    "sg:city":"K\u00f6ln",
    "sg:phone":"+49 221",
    "sg:postcode":"50968",
    "sg:province":"Nordrhein-Westfalen",
    "wof:name":"Ecl@ss",
    "wof:placetype":"venue"
},
  "geometry": {"coordinates":[6.972901,50.911991],"type":"Point"}
}