{
  "type": "Feature",
  "properties": {
    "iso:country":"DE",
    "sg:address":"Kupferberg",
    "sg:city":"Wipperf\u00fcrth",
    "sg:phone":"+49 2267/5028",
    "sg:postcode":"51688",
    "sg:province":"Nordrhein-Westfalen",
    "wof:name":"Kupferberg-kabel",
    "wof:placetype":"venue"
},
  "geometry": {"coordinates":[7.4405679703,51.1118507385],"type":"Point"}
}