{
  "type": "Feature",
  "properties": {
    "iso:country":"DE",
    "sg:address":"Hauptstr. 59 a",
    "sg:city":"Gro\u00df Gr\u00f6nau",
    "sg:postcode":"23627",
    "sg:province":"Schleswig-Holstein",
    "wof:name":"Gemeindeb\u00fccherei",
    "wof:placetype":"venue"
},
  "geometry": {"coordinates":[10.748934,53.806694],"type":"Point"}
}