{
  "type": "Feature",
  "properties": {
    "iso:country":"DE",
    "sg:address":"Internatstr. 22",
    "sg:city":"Freren",
    "sg:phone":"+49 5902/940040",
    "sg:postcode":"49832",
    "sg:province":"Niedersachsen",
    "wof:name":"Varelmann Gmbh",
    "wof:placetype":"venue"
},
  "geometry": {"coordinates":[7.539624,52.484818],"type":"Point"}
}