{
  "type": "Feature",
  "properties": {
    "iso:country":"DE",
    "sg:address":"Lange Str. 41",
    "sg:city":"Diepholz",
    "sg:phone":"+49 5441/6513",
    "sg:postcode":"49356",
    "sg:province":"Niedersachsen",
    "wof:name":"Cafe Restaurant Zum Burggrafen",
    "wof:placetype":"venue"
},
  "geometry": {"coordinates":[8.3705596924,52.6056785583],"type":"Point"}
}