{
  "type": "Feature",
  "properties": {
    "iso:country":"DE",
    "sg:address":"Hebelstr. 2",
    "sg:city":"N\u00fcrnberg",
    "sg:postcode":"90491",
    "sg:province":"Bayern",
    "wof:name":"Philipp Plein Gmbh",
    "wof:placetype":"venue"
},
  "geometry": {"coordinates":[11.1306123734,49.4740867615],"type":"Point"}
}