{
  "type": "Feature",
  "properties": {
    "iso:country":"DE",
    "sg:address":"Heisfelder Str. 133",
    "sg:city":"Leer",
    "sg:phone":"+49 491/9293910",
    "sg:postcode":"26789",
    "sg:province":"Niedersachsen",
    "wof:name":"Adler-apotheke",
    "wof:placetype":"venue"
},
  "geometry": {"coordinates":[7.455318,53.238262],"type":"Point"}
}