{
  "type": "Feature",
  "properties": {
    "iso:country":"DE",
    "sg:address":"Goldbrink 173",
    "sg:city":"M\u00fcnster",
    "sg:phone":"+49 2506/2048",
    "sg:postcode":"48167",
    "sg:province":"Nordrhein-Westfalen",
    "wof:name":"Johanne Horn",
    "wof:placetype":"venue"
},
  "geometry": {"coordinates":[7.7237300873,51.9213485718],"type":"Point"}
}