{
  "type": "Feature",
  "properties": {
    "iso:country":"DE",
    "sg:address":"Falkensteiner Str. 25",
    "sg:city":"Roding",
    "sg:phone":"+49 9461/1615",
    "sg:postcode":"93426",
    "sg:province":"Bayern",
    "wof:name":"Ev. Luth. Pfarramt",
    "wof:placetype":"venue"
},
  "geometry": {"coordinates":[12.5184001923,49.1928291321],"type":"Point"}
}