{
  "type": "Feature",
  "properties": {
    "iso:country":"DE",
    "sg:address":"Borgesch 30",
    "sg:city":"Telgte",
    "sg:phone":"+49 2504/98060",
    "sg:postcode":"48291",
    "sg:province":"Nordrhein-Westfalen",
    "wof:name":"Lbh On Tour Veranstaltungs-management Gmbh",
    "wof:placetype":"venue"
},
  "geometry": {"coordinates":[7.738622,52.028477],"type":"Point"}
}