{
  "type": "Feature",
  "properties": {
    "iso:country":"DE",
    "sg:address":"Westermoorstr. 4",
    "sg:city":"Saterland",
    "sg:phone":"+49 4492/240",
    "sg:postcode":"26683",
    "sg:province":"Niedersachsen",
    "wof:name":"Joh. Thoben",
    "wof:placetype":"venue"
},
  "geometry": {"coordinates":[7.712121,53.05698],"type":"Point"}
}