{
  "type": "Feature",
  "properties": {
    "iso:country":"DE",
    "sg:address":"Hauptstr. 112",
    "sg:city":"Wallhausen",
    "sg:phone":"+49 7955/520",
    "sg:postcode":"74599",
    "sg:province":"Baden-W\u00fcrttemberg",
    "wof:name":"Hewobau Gesellschaft F\u00fcr Wohn- Bau Und Baubetreuung Mbh",
    "wof:placetype":"venue"
},
  "geometry": {"coordinates":[10.0972127914,49.217880249],"type":"Point"}
}