{
  "type": "Feature",
  "properties": {
    "iso:country":"DE",
    "sg:address":"Helenenstr. 44",
    "sg:city":"Meiningen",
    "sg:phone":"+49 3693/503701",
    "sg:postcode":"98617",
    "sg:province":"Th\u00fcringen",
    "wof:name":"Thomas G\u00f6hring",
    "wof:placetype":"venue"
},
  "geometry": {"coordinates":[10.4080791473,50.5627212524],"type":"Point"}
}