{
  "type": "Feature",
  "properties": {
    "iso:country":"DE",
    "sg:address":"Am Markt 2",
    "sg:city":"Hanau",
    "sg:phone":"+49 6181/22292",
    "sg:postcode":"63450",
    "sg:province":"Hessen",
    "wof:name":"Atlasreisen Gmbh",
    "wof:placetype":"venue"
},
  "geometry": {"coordinates":[8.9181451797,50.1327705383],"type":"Point"}
}