{
  "type": "Feature",
  "properties": {
    "iso:country":"DE",
    "sg:address":"Dechenstr. 29",
    "sg:city":"Dortmund",
    "sg:phone":"+49 231/9820280",
    "sg:postcode":"44147",
    "sg:province":"Nordrhein-Westfalen",
    "wof:name":"Arnold B\u00f6hm Ceramicbedarf Gmbh",
    "wof:placetype":"venue"
},
  "geometry": {"coordinates":[7.439973,51.518261],"type":"Point"}
}