{
  "type": "Feature",
  "properties": {
    "iso:country":"DE",
    "sg:address":"Marktstr. 37",
    "sg:city":"Friedrichroda",
    "sg:phone":"+49 3623/304308",
    "sg:postcode":"99894",
    "sg:province":"Th\u00fcringen",
    "wof:name":"Wilfried Jahn",
    "wof:placetype":"venue"
},
  "geometry": {"coordinates":[10.564731,50.857777],"type":"Point"}
}