{
  "type": "Feature",
  "properties": {
    "iso:country":"DE",
    "sg:address":"Tecklenburger Str. 10",
    "sg:city":"Steinfurt",
    "sg:postcode":"48565",
    "sg:province":"Nordrhein-Westfalen",
    "wof:name":"Krav Ag Versicherungsverband D. Dt.",
    "wof:placetype":"venue"
},
  "geometry": {"coordinates":[7.3592219353,52.1526145935],"type":"Point"}
}