{
  "type": "Feature",
  "properties": {
    "iso:country":"DE",
    "sg:address":"Hindenburgstr. 14",
    "sg:city":"Meerbusch",
    "sg:phone":"+49 2132/960081",
    "sg:postcode":"40667",
    "sg:province":"Nordrhein-Westfalen",
    "wof:name":"Werner Leu Architekt",
    "wof:placetype":"venue"
},
  "geometry": {"coordinates":[6.66511,51.25919],"type":"Point"}
}