{
  "type": "Feature",
  "properties": {
    "iso:country":"DE",
    "sg:address":"Mittelstr. 49",
    "sg:city":"Gevelsberg",
    "sg:phone":"+49 2332/3836",
    "sg:postcode":"58285",
    "sg:province":"Nordrhein-Westfalen",
    "wof:name":"Alfred Nowotsch",
    "wof:placetype":"venue"
},
  "geometry": {"coordinates":[7.336687088,51.318687439],"type":"Point"}
}