{
  "type": "Feature",
  "properties": {
    "iso:country":"DE",
    "sg:address":"Wellinghofer Str. 117",
    "sg:city":"Dortmund",
    "sg:postcode":"44263",
    "sg:province":"Nordrhein-Westfalen",
    "wof:name":"G Und E Baugesellschaft Mbh",
    "wof:placetype":"venue"
},
  "geometry": {"coordinates":[7.49578,51.480801],"type":"Point"}
}