{
  "type": "Feature",
  "properties": {
    "iso:country":"DE",
    "sg:address":"Schafsteg 13",
    "sg:city":"R\u00f6dental",
    "sg:phone":"+49 9563/6487",
    "sg:postcode":"96472",
    "sg:province":"Bayern",
    "wof:name":"Roland Hofmann",
    "wof:placetype":"venue"
},
  "geometry": {"coordinates":[11.0539512634,50.2970809937],"type":"Point"}
}