{
  "type": "Feature",
  "properties": {
    "iso:country":"DE",
    "sg:address":"Wasserstr. 25",
    "sg:city":"Rheda-Wiedenbr\u00fcck",
    "sg:phone":"+49 5242/5359",
    "sg:postcode":"33378",
    "sg:province":"Nordrhein-Westfalen",
    "wof:name":"Franz Schmalhorst",
    "wof:placetype":"venue"
},
  "geometry": {"coordinates":[8.3117399216,51.833530426],"type":"Point"}
}