{
  "type": "Feature",
  "properties": {
    "iso:country":"DE",
    "sg:address":"K\u00f6pfchen 3",
    "sg:city":"Zella-Mehlis",
    "sg:phone":"+49 3682/43117",
    "sg:postcode":"98544",
    "sg:province":"Th\u00fcringen",
    "wof:name":"C. Waizenh\u00f6fer",
    "wof:placetype":"venue"
},
  "geometry": {"coordinates":[10.676912,50.65543],"type":"Point"}
}