{
  "type": "Feature",
  "properties": {
    "iso:country":"DE",
    "sg:address":"Detmolder Str. 201",
    "sg:city":"Bad Lippspringe",
    "sg:phone":"+49 5252/3560",
    "sg:postcode":"33175",
    "sg:province":"Nordrhein-Westfalen",
    "wof:name":"Massagepraxis Meyer",
    "wof:placetype":"venue"
},
  "geometry": {"coordinates":[8.823651,51.78653],"type":"Point"}
}