{
  "type": "Feature",
  "properties": {
    "iso:country":"DE",
    "sg:address":"Hauptstr. 44",
    "sg:city":"Dernbach",
    "sg:phone":"+49 2689/3522",
    "sg:postcode":"56307",
    "sg:province":"Rheinland-Pfalz",
    "wof:name":"H.-p. Waller Und A. Debus",
    "wof:placetype":"venue"
},
  "geometry": {"coordinates":[7.5996022224,50.5471420288],"type":"Point"}
}