{
  "type": "Feature",
  "properties": {
    "iso:country":"DE",
    "sg:address":"Ringstr. 18",
    "sg:city":"Rengsdorf",
    "sg:phone":"+49 2634/8501",
    "sg:postcode":"56579",
    "sg:province":"Rheinland-Pfalz",
    "wof:name":"Walter Reinhard Schreinerei",
    "wof:placetype":"venue"
},
  "geometry": {"coordinates":[7.487858,50.512142],"type":"Point"}
}