{
  "type": "Feature",
  "properties": {
    "iso:country":"DE",
    "sg:address":"Fahltskamp 64b",
    "sg:city":"Pinneberg",
    "sg:postcode":"25421",
    "sg:province":"Schleswig-Holstein",
    "wof:name":"Digitopics Gmbh",
    "wof:placetype":"venue"
},
  "geometry": {"coordinates":[9.8091316223,53.6563453674],"type":"Point"}
}