{
  "type": "Feature",
  "properties": {
    "iso:country":"DE",
    "sg:address":"Heemstr. 51-55",
    "sg:city":"Wildeshausen",
    "sg:phone":"+49 4944/3189070",
    "sg:postcode":"27793",
    "sg:province":"Niedersachsen",
    "wof:name":"Heinrich Schr\u00d6der Landmaschinen Gmbh",
    "wof:placetype":"venue"
},
  "geometry": {"coordinates":[8.434237,52.899979],"type":"Point"}
}