{
  "type": "Feature",
  "properties": {
    "iso:country":"DE",
    "sg:address":"L\u00f6nsweg 6",
    "sg:city":"Nienburg",
    "sg:phone":"+49 5021/2937",
    "sg:postcode":"31582",
    "sg:province":"Niedersachsen",
    "wof:name":"Prof. Siegfried Stahl Architekt",
    "wof:placetype":"venue"
},
  "geometry": {"coordinates":[9.25432,52.621395],"type":"Point"}
}