{
  "type": "Feature",
  "properties": {
    "iso:country":"DE",
    "sg:address":"Salzstr 185::",
    "sg:city":"Heilbronn",
    "sg:postcode":"74076",
    "sg:province":"Baden-W\u00fcrttemberg",
    "wof:name":"Transterra Gesellschaft F\u00fcr Immobilienverwaltung Mbh",
    "wof:placetype":"venue"
},
  "geometry": {"coordinates":[11.640545,48.192394],"type":"Point"}
}