{
  "type": "Feature",
  "properties": {
    "iso:country":"DE",
    "sg:address":"Hauptstr. 165",
    "sg:city":"Eichenb\u00fchl",
    "sg:phone":"+49 9371/7533",
    "sg:postcode":"63928",
    "sg:province":"Bayern",
    "wof:name":"A. Bergmann Gmbh",
    "wof:placetype":"venue"
},
  "geometry": {"coordinates":[9.3283395767,49.7051391602],"type":"Point"}
}