{
  "type": "Feature",
  "properties": {
    "iso:country":"DE",
    "sg:address":"St.-Martin-Weg",
    "sg:city":"Bad Waldsee",
    "sg:phone":"+49 7524/5384",
    "sg:postcode":"88339",
    "sg:province":"Baden-W\u00fcrttemberg",
    "wof:name":"Herbert Wei\u00df",
    "wof:placetype":"venue"
},
  "geometry": {"coordinates":[9.7139158249,47.8970794678],"type":"Point"}
}