{
  "type": "Feature",
  "properties": {
    "iso:country":"DE",
    "sg:address":"Alte Seer Str. 2",
    "sg:city":"Parsberg",
    "sg:phone":"+49 9492/5056",
    "sg:postcode":"92331",
    "sg:province":"Bayern",
    "wof:name":"Stadtb\u00fccherei Parsberg",
    "wof:placetype":"venue"
},
  "geometry": {"coordinates":[11.720089,49.158295],"type":"Point"}
}