{
  "type": "Feature",
  "properties": {
    "iso:country":"DE",
    "sg:address":"M\u00fchlenstr. 7",
    "sg:city":"Bunde",
    "sg:phone":"+49 4953/761",
    "sg:postcode":"26831",
    "sg:province":"Niedersachsen",
    "wof:name":"Ev. Pfarramt Bunde",
    "wof:placetype":"venue"
},
  "geometry": {"coordinates":[7.2700529099,53.1874313354],"type":"Point"}
}