{
  "type": "Feature",
  "properties": {
    "iso:country":"DE",
    "sg:address":"Ulmenweg 5a",
    "sg:city":"Dillingen",
    "sg:phone":"+49 9071/3732",
    "sg:postcode":"89407",
    "sg:province":"Bayern",
    "wof:name":"Hartmut Gebauer",
    "wof:placetype":"venue"
},
  "geometry": {"coordinates":[10.501945,48.587055],"type":"Point"}
}