{
  "type": "Feature",
  "properties": {
    "iso:country":"DE",
    "sg:address":"Richard-Wagner-Str. 29",
    "sg:city":"Bayreuth",
    "sg:phone":"+49 921/64459",
    "sg:postcode":"95444",
    "sg:province":"Bayern",
    "wof:name":"Grimm Musikstudio",
    "wof:placetype":"venue"
},
  "geometry": {"coordinates":[11.5814723969,49.9423599243],"type":"Point"}
}