{
  "type": "Feature",
  "properties": {
    "iso:country":"DE",
    "sg:address":"M\u00fcnchner Str 20",
    "sg:city":"Unterf\u00f6hring",
    "sg:phone":"+49 89/95078600",
    "sg:postcode":"85774",
    "sg:province":"Bayern",
    "wof:name":"Mm Merchandising M\u00fcnchen Gmbh",
    "wof:placetype":"venue"
},
  "geometry": {"coordinates":[11.632649,48.18235],"type":"Point"}
}