{
  "type": "Feature",
  "properties": {
    "iso:country":"DE",
    "sg:address":"M\u00fchlstr. 7",
    "sg:city":"H\u00f6sbach",
    "sg:phone":"+49 6021/560042",
    "sg:postcode":"63768",
    "sg:province":"Bayern",
    "wof:name":"Ewald Sch\u00fcssler Gmbh",
    "wof:placetype":"venue"
},
  "geometry": {"coordinates":[9.2011766434,50.0023193359],"type":"Point"}
}