{
  "type": "Feature",
  "properties": {
    "iso:country":"DE",
    "sg:address":"Waltersh\u00e4user Str.",
    "sg:city":"Tabarz",
    "sg:phone":"+49 36259/50954",
    "sg:postcode":"99891",
    "sg:province":"Th\u00fcringen",
    "wof:name":"W. Ortlepp",
    "wof:placetype":"venue"
},
  "geometry": {"coordinates":[10.4800243378,50.8848228455],"type":"Point"}
}