{
  "type": "Feature",
  "properties": {
    "iso:country":"DE",
    "sg:address":"Cezanneweg 17",
    "sg:city":"Leipzig",
    "sg:phone":"+49 341/8772898",
    "sg:postcode":"04289",
    "sg:province":"Sachsen",
    "wof:name":"Gerhard Guse",
    "wof:placetype":"venue"
},
  "geometry": {"coordinates":[12.4381,51.287956],"type":"Point"}
}