{
  "type": "Feature",
  "properties": {
    "iso:country":"DE",
    "sg:address":"Hauptstr. 35",
    "sg:city":"Geroldsgr\u00fcn",
    "sg:phone":"+49 9288/7509",
    "sg:postcode":"95179",
    "sg:province":"Bayern",
    "wof:name":"Busunternehmen Oelsnitz- Talreisen",
    "wof:placetype":"venue"
},
  "geometry": {"coordinates":[11.5959672928,50.3737182617],"type":"Point"}
}