{
  "type": "Feature",
  "properties": {
    "iso:country":"DE",
    "sg:address":"Walter-Freitag-Str. 10",
    "sg:city":"Remscheid",
    "sg:phone":"+49 2191",
    "sg:postcode":"42899",
    "sg:province":"Nordrhein-Westfalen",
    "wof:name":"Wrs - Werkzeugshop, Ernst Winterhoff Gmbh & Co. Kg",
    "wof:placetype":"venue"
},
  "geometry": {"coordinates":[7.23816,51.218365],"type":"Point"}
}