{
  "type": "Feature",
  "properties": {
    "iso:country":"DE",
    "sg:address":"J\u00e4gerstr. 16",
    "sg:city":"Weiden",
    "sg:phone":"+49 961/43789",
    "sg:postcode":"92637",
    "sg:province":"Bayern",
    "wof:name":"Amalie Kr\u00e4mer Gmbh",
    "wof:placetype":"venue"
},
  "geometry": {"coordinates":[12.139840126,49.6565856934],"type":"Point"}
}