{
  "type": "Feature",
  "properties": {
    "iso:country":"DE",
    "sg:address":"Rinchnacher Str. 3",
    "sg:city":"Regen",
    "sg:phone":"+49 9921/2853",
    "sg:postcode":"94209",
    "sg:province":"Bayern",
    "wof:name":"La Palma",
    "wof:placetype":"venue"
},
  "geometry": {"coordinates":[13.1382608414,48.9694976807],"type":"Point"}
}