{
  "type": "Feature",
  "properties": {
    "iso:country":"DE",
    "sg:address":"Schmiedebergstr. 8",
    "sg:city":"Kn\u00fcllwald",
    "sg:phone":"+49 5686/265",
    "sg:postcode":"34593",
    "sg:province":"Hessen",
    "wof:name":"Gastst\u00e4tte Reinhold Preis",
    "wof:placetype":"venue"
},
  "geometry": {"coordinates":[9.4829273224,50.9397964478],"type":"Point"}
}