{
  "type": "Feature",
  "properties": {
    "iso:country":"DE",
    "sg:address":"Stoltzestr. 80",
    "sg:city":"Neu-Isenburg",
    "sg:phone":"+49 6102/89191",
    "sg:postcode":"63263",
    "sg:province":"Hessen",
    "wof:name":"Harald Vogel Filmtheater- Betriebsgesellschaft Mbh",
    "wof:placetype":"venue"
},
  "geometry": {"coordinates":[8.6820898056,50.0559806824],"type":"Point"}
}