{
  "type": "Feature",
  "properties": {
    "iso:country":"DE",
    "sg:address":"Fontanestr. 31",
    "sg:city":"Kleinmachnow",
    "sg:postcode":"14532",
    "sg:province":"Brandenburg",
    "wof:name":"Sportforum Kleinmachnow Gmbh",
    "wof:placetype":"venue"
},
  "geometry": {"coordinates":[13.2361078262,52.4015846252],"type":"Point"}
}