{
  "type": "Feature",
  "properties": {
    "iso:country":"DE",
    "sg:address":"Leonhardistr. 2",
    "sg:city":"Pf\u00f6rring",
    "sg:phone":"+49 8403/328",
    "sg:postcode":"85104",
    "sg:province":"Bayern",
    "wof:name":"Gastst\u00e4tte Ignaz P\u00f6ppel",
    "wof:placetype":"venue"
},
  "geometry": {"coordinates":[11.6883659363,48.8091316223],"type":"Point"}
}