{
  "type": "Feature",
  "properties": {
    "iso:country":"DE",
    "sg:address":"Babenh\u00e4user Str. 19",
    "sg:city":"Seligenstadt",
    "sg:phone":"+49 6182/898100",
    "sg:postcode":"63500",
    "sg:province":"Hessen",
    "wof:name":"Wei\u00df Und Graul-sattler Rechtsanw\u00e4lte",
    "wof:placetype":"venue"
},
  "geometry": {"coordinates":[8.9717721939,50.0418319702],"type":"Point"}
}