{
  "type": "Feature",
  "properties": {
    "iso:country":"DE",
    "sg:address":"Annastr. 33",
    "sg:city":"Ichenhausen",
    "sg:phone":"+49 8223/3442",
    "sg:postcode":"89335",
    "sg:province":"Bayern",
    "wof:name":"Anton Ley",
    "wof:placetype":"venue"
},
  "geometry": {"coordinates":[10.308395,48.369476],"type":"Point"}
}