{
  "type": "Feature",
  "properties": {
    "iso:country":"DE",
    "sg:address":"Fuldaer Str. 38",
    "sg:city":"H\u00fcnfeld",
    "sg:phone":"+49 6652/2759",
    "sg:postcode":"36088",
    "sg:province":"Hessen",
    "wof:name":"Autoservice Krieger Inh. Karlheinz Krieger",
    "wof:placetype":"venue"
},
  "geometry": {"coordinates":[9.7614402771,50.6667060852],"type":"Point"}
}