{
  "type": "Feature",
  "properties": {
    "iso:country":"DE",
    "sg:address":"Treuenbrietzener Str. 3",
    "sg:city":"Beelitz",
    "sg:phone":"+49 33204/4920",
    "sg:postcode":"14547",
    "sg:province":"Brandenburg",
    "wof:name":"A. Kamphenkel Getr\u00e4nke- Fachgro\u00dfhandel West Gmbh",
    "wof:placetype":"venue"
},
  "geometry": {"coordinates":[12.972657,52.226154],"type":"Point"}
}