{
  "type": "Feature",
  "properties": {
    "iso:country":"DE",
    "sg:address":"Kleine Masch 7",
    "sg:city":"Rahden",
    "sg:phone":"+49 5771/94705",
    "sg:postcode":"32369",
    "sg:province":"Nordrhein-Westfalen",
    "wof:name":"Knost Kommunikations-technik",
    "wof:placetype":"venue"
},
  "geometry": {"coordinates":[8.6386709213,52.4612236023],"type":"Point"}
}