{
  "type": "Feature",
  "properties": {
    "iso:country":"DE",
    "sg:address":"L\u00fclsdorfer Str. 224a",
    "sg:city":"K\u00f6ln",
    "sg:phone":"+49 2203/84297",
    "sg:postcode":"51143",
    "sg:province":"Nordrhein-Westfalen",
    "wof:name":"Kopp Gmbh",
    "wof:placetype":"venue"
},
  "geometry": {"coordinates":[7.013047,50.850624],"type":"Point"}
}