{
  "type": "Feature",
  "properties": {
    "iso:country":"DE",
    "sg:address":"B\u00e4ckerplatz 13",
    "sg:city":"Allstedt",
    "sg:phone":"+49 34652/475",
    "sg:postcode":"06542",
    "sg:province":"Sachsen-Anhalt",
    "wof:name":"Sylvana Opitz",
    "wof:placetype":"venue"
},
  "geometry": {"coordinates":[11.38983,51.40387],"type":"Point"}
}