{
  "type": "Feature",
  "properties": {
    "iso:country":"DE",
    "sg:address":"Sandwelle 13",
    "sg:city":"Soest",
    "sg:phone":"+49 2921/31001",
    "sg:postcode":"59494",
    "sg:province":"Nordrhein-Westfalen",
    "wof:name":"Reform- U. Di\u00e4thaus Sonnenau",
    "wof:placetype":"venue"
},
  "geometry": {"coordinates":[8.1049394608,51.5739135742],"type":"Point"}
}