{
  "type": "Feature",
  "properties": {
    "iso:country":"DE",
    "sg:address":"Neuer Markt 17",
    "sg:city":"Emden",
    "sg:phone":"+49 4921/26025",
    "sg:postcode":"26721",
    "sg:province":"Niedersachsen",
    "wof:name":"Pizzeria Restaurante Riccolo Inh. Mariano Dettori",
    "wof:placetype":"venue"
},
  "geometry": {"coordinates":[7.2029881477,53.3676147461],"type":"Point"}
}