{
  "type": "Feature",
  "properties": {
    "iso:country":"DE",
    "sg:address":"Happurger Str. 35",
    "sg:city":"Hersbruck",
    "sg:phone":"+49 9151/7492",
    "sg:postcode":"91217",
    "sg:province":"Bayern",
    "wof:name":"Sef-pack Handels Gmbh",
    "wof:placetype":"venue"
},
  "geometry": {"coordinates":[11.4408969879,49.5032615662],"type":"Point"}
}