{
  "type": "Feature",
  "properties": {
    "iso:country":"DE",
    "sg:address":"Friedrich-Paffrath-Str. 116",
    "sg:city":"Wilhelmshaven",
    "sg:phone":"+49 4421/87708",
    "sg:postcode":"26389",
    "sg:province":"Niedersachsen",
    "wof:name":"F. A. Meyer Beteiligungs Gmbh",
    "wof:placetype":"venue"
},
  "geometry": {"coordinates":[8.084182,53.545555],"type":"Point"}
}