{
  "type": "Feature",
  "properties": {
    "iso:country":"DE",
    "sg:address":"Br\u00fcsseler Ring 27",
    "sg:city":"Aachen",
    "sg:phone":"+49 241/71325",
    "sg:postcode":"52074",
    "sg:province":"Nordrhein-Westfalen",
    "wof:name":"Alfred Schmitz Beteiligungs Gmbh",
    "wof:placetype":"venue"
},
  "geometry": {"coordinates":[6.069141,50.751694],"type":"Point"}
}