{
  "type": "Feature",
  "properties": {
    "iso:country":"DE",
    "sg:address":"Am Bullhamm 20",
    "sg:city":"Jever",
    "sg:phone":"+49 4461/984198",
    "sg:postcode":"26441",
    "sg:province":"Niedersachsen",
    "wof:name":"Kreativ Metallbau Gmbh",
    "wof:placetype":"venue"
},
  "geometry": {"coordinates":[7.9059247971,53.5856246948],"type":"Point"}
}