{
  "type": "Feature",
  "properties": {
    "iso:country":"DE",
    "sg:address":"Ringbahnstr. 32-34",
    "sg:city":"Berlin",
    "sg:phone":"+49 30/7550080",
    "sg:postcode":"12099",
    "sg:province":"Berlin",
    "wof:name":"Zibell Willner & Partner Ingenieurgesellschaft F\u00fcr",
    "wof:placetype":"venue"
},
  "geometry": {"coordinates":[13.3908367157,52.4679107666],"type":"Point"}
}