{
  "type": "Feature",
  "properties": {
    "iso:country":"DE",
    "sg:address":"Hauptstr. 66",
    "sg:city":"Bad Orb",
    "sg:phone":"+49 6052/2232",
    "sg:postcode":"63619",
    "sg:province":"Hessen",
    "wof:name":"Hotel Berliner Hof",
    "wof:placetype":"venue"
},
  "geometry": {"coordinates":[9.3485469818,50.2248077393],"type":"Point"}
}