{
  "type": "Feature",
  "properties": {
    "iso:country":"DE",
    "sg:address":"Osterkamp 100",
    "sg:city":"Melle",
    "sg:phone":"+49 5422/5465",
    "sg:postcode":"49324",
    "sg:province":"Niedersachsen",
    "wof:name":"Matthias Schom\u00f6ller",
    "wof:placetype":"venue"
},
  "geometry": {"coordinates":[8.3576812744,52.1955337524],"type":"Point"}
}