{
  "type": "Feature",
  "properties": {
    "iso:country":"DE",
    "sg:address":"Von-der-Mark-Str. 52",
    "sg:city":"Duisburg",
    "sg:postcode":"47137",
    "sg:province":"Nordrhein-Westfalen",
    "wof:name":"Edeka-markt Dr\u00f6schel",
    "wof:placetype":"venue"
},
  "geometry": {"coordinates":[6.7757740021,51.4675674438],"type":"Point"}
}