{
  "type": "Feature",
  "properties": {
    "iso:country":"DE",
    "sg:address":"Frenkstr. 22",
    "sg:city":"H\u00fcrtgenwald",
    "sg:phone":"+49 2429/2793",
    "sg:postcode":"52393",
    "sg:province":"Nordrhein-Westfalen",
    "wof:name":"Randerath",
    "wof:placetype":"venue"
},
  "geometry": {"coordinates":[6.3930678368,50.7349281311],"type":"Point"}
}