{
  "type": "Feature",
  "properties": {
    "iso:country":"DE",
    "sg:address":"Ladestr 52",
    "sg:city":"B\u00fcnde",
    "sg:phone":"+49 5223/69000",
    "sg:postcode":"32257",
    "sg:province":"Nordrhein-Westfalen",
    "wof:name":"Rabe & Meyer K\u00fcchen Gmbh & Co Kg",
    "wof:placetype":"venue"
},
  "geometry": {"coordinates":[8.5796699524,52.1968193054],"type":"Point"}
}