{
  "type": "Feature",
  "properties": {
    "iso:country":"DE",
    "sg:address":"Oberndorfer Str. 26",
    "sg:city":"Rottweil",
    "sg:phone":"+49 741/8347",
    "sg:postcode":"78628",
    "sg:province":"Baden-W\u00fcrttemberg",
    "wof:name":"Josef Peter",
    "wof:placetype":"venue"
},
  "geometry": {"coordinates":[8.619337,48.1688],"type":"Point"}
}