{
  "type": "Feature",
  "properties": {
    "iso:country":"DE",
    "sg:address":"Am Berg 3",
    "sg:city":"Langg\u00f6ns",
    "sg:phone":"+49 6085/842",
    "sg:postcode":"35428",
    "sg:province":"Hessen",
    "wof:name":"Willi Kuhl",
    "wof:placetype":"venue"
},
  "geometry": {"coordinates":[8.560917,50.445736],"type":"Point"}
}