{
  "type": "Feature",
  "properties": {
    "iso:country":"DE",
    "sg:address":"Salzstr. 23",
    "sg:city":"Marktoberdorf",
    "sg:phone":"+49 8342/5629",
    "sg:postcode":"87616",
    "sg:province":"Bayern",
    "wof:name":"Egbert Felber",
    "wof:placetype":"venue"
},
  "geometry": {"coordinates":[10.6183319092,47.7773399353],"type":"Point"}
}