{
  "type": "Feature",
  "properties": {
    "iso:country":"DE",
    "sg:address":"Bruno-Taut-Ring 9 d",
    "sg:city":"Berlin",
    "sg:phone":"+49 30/6012072",
    "sg:postcode":"12359",
    "sg:province":"Berlin",
    "wof:name":"Kath. \u00d6ffentliche Bibliothek Bruder Klaus",
    "wof:placetype":"venue"
},
  "geometry": {"coordinates":[13.448575,52.440361],"type":"Point"}
}