{
  "type": "Feature",
  "properties": {
    "iso:country":"DE",
    "sg:address":"Duvenstr. 91",
    "sg:city":"M\u00f6nchengladbach",
    "sg:phone":"+49 2166/963880",
    "sg:postcode":"41199",
    "sg:province":"Nordrhein-Westfalen",
    "wof:name":"Microdesk Cad Cae Systemhaus Gmbh",
    "wof:placetype":"venue"
},
  "geometry": {"coordinates":[6.450282,51.139744],"type":"Point"}
}