{
  "type": "Feature",
  "properties": {
    "iso:country":"DE",
    "sg:address":"Mercartorstr.10",
    "sg:city":"Geesthacht",
    "sg:phone":"+49 4941/5287750",
    "sg:postcode":"21502",
    "sg:province":"Schleswig-Holstein",
    "wof:name":"Aw Schultze Gmbh",
    "wof:placetype":"venue"
},
  "geometry": {"coordinates":[10.365763,53.455742],"type":"Point"}
}