{
  "type": "Feature",
  "properties": {
    "iso:country":"DE",
    "sg:address":"Im Feldle 1-3",
    "sg:city":"Markt Wald",
    "sg:postcode":"86865",
    "sg:province":"Bayern",
    "wof:name":"Ews Beleuchtungstechnik Vertriebs-verwaltungs Gmbh",
    "wof:placetype":"venue"
},
  "geometry": {"coordinates":[10.592267,48.151737],"type":"Point"}
}