{
  "type": "Feature",
  "properties": {
    "iso:country":"DE",
    "sg:address":"Weizenacker 9",
    "sg:city":"Ahaus",
    "sg:phone":"+49 2561/420260",
    "sg:postcode":"48683",
    "sg:province":"Nordrhein-Westfalen",
    "wof:name":"Weba System-bau Gmbh & Co. Kg",
    "wof:placetype":"venue"
},
  "geometry": {"coordinates":[6.9737591743,52.0951194763],"type":"Point"}
}