{
  "type": "Feature",
  "properties": {
    "iso:country":"DE",
    "sg:address":"Kutterstr. 6",
    "sg:city":"Wilhelmshaven",
    "sg:phone":"+49 4421/9138800",
    "sg:postcode":"26386",
    "sg:province":"Niedersachsen",
    "wof:name":"Elutec Ohg",
    "wof:placetype":"venue"
},
  "geometry": {"coordinates":[8.11664,53.57111],"type":"Point"}
}