{
  "type": "Feature",
  "properties": {
    "iso:country":"DE",
    "sg:address":"K\u00f6nigsberger Str. 79",
    "sg:city":"Wolfsburg",
    "sg:postcode":"38440",
    "sg:province":"Niedersachsen",
    "wof:name":"Whiskyservice.de Fleischer & Trzaska Ohg",
    "wof:placetype":"venue"
},
  "geometry": {"coordinates":[10.7578239441,52.4238090515],"type":"Point"}
}