{
  "type": "Feature",
  "properties": {
    "iso:country":"DE",
    "sg:address":"R\u00f6mergasse 6a",
    "sg:city":"M\u00fchldorf",
    "sg:phone":"+49 8631/7453",
    "sg:postcode":"84453",
    "sg:province":"Bayern",
    "wof:name":"Silzl Ohg Eisenwaren",
    "wof:placetype":"venue"
},
  "geometry": {"coordinates":[12.532674,48.260105],"type":"Point"}
}