{
  "type": "Feature",
  "properties": {
    "iso:country":"DE",
    "sg:address":"Jacobstr. 14",
    "sg:city":"Leipzig",
    "sg:postcode":"04105",
    "sg:province":"Sachsen",
    "wof:name":"Dr. Med. Gerhard Herrmann",
    "wof:placetype":"venue"
},
  "geometry": {"coordinates":[12.36755,51.345867],"type":"Point"}
}