{
  "type": "Feature",
  "properties": {
    "iso:country":"DE",
    "sg:address":"Hauptstr. 3",
    "sg:city":"Leubnitz",
    "sg:phone":"+49 36645/35342",
    "sg:postcode":"08539",
    "sg:province":"Sachsen",
    "wof:name":"H & F Holz-undmontagebau Gmbh",
    "wof:placetype":"venue"
},
  "geometry": {"coordinates":[12.0192928314,50.514213562],"type":"Point"}
}