{
  "type": "Feature",
  "properties": {
    "iso:country":"DE",
    "sg:address":"Veltener Str. 21",
    "sg:city":"B\u00f6tzow",
    "sg:phone":"+49 3304/33760",
    "sg:postcode":"16727",
    "sg:province":"Brandenburg",
    "wof:name":"M. Pfeiffer",
    "wof:placetype":"venue"
},
  "geometry": {"coordinates":[13.145687,52.656445],"type":"Point"}
}