{
  "type": "Feature",
  "properties": {
    "iso:country":"DE",
    "sg:address":"Eichendorffstr. 104",
    "sg:city":"Vaihingen",
    "sg:phone":"+49 7042/98641",
    "sg:postcode":"71665",
    "sg:province":"Baden-W\u00fcrttemberg",
    "wof:name":"Erhard Hamel Ingenieur Und Architekt",
    "wof:placetype":"venue"
},
  "geometry": {"coordinates":[8.970408,48.931622],"type":"Point"}
}