{
  "type": "Feature",
  "properties": {
    "iso:country":"DE",
    "sg:address":"Gro\u00dfherzog-Friedrich-Str. 81",
    "sg:city":"Saarbr\u00fccken",
    "sg:phone":"+49 681/684848",
    "sg:postcode":"66121",
    "sg:province":"Saarland",
    "wof:name":"J\u00fcrgen Kohlbecher Immobilienmakler",
    "wof:placetype":"venue"
},
  "geometry": {"coordinates":[7.0042800903,49.2316665649],"type":"Point"}
}