{
  "type": "Feature",
  "properties": {
    "iso:country":"DE",
    "sg:address":"Am Obertor",
    "sg:city":"Gengenbach",
    "sg:phone":"+49 7803/3425",
    "sg:postcode":"77723",
    "sg:province":"Baden-W\u00fcrttemberg",
    "wof:name":"Elisabeth Jehle",
    "wof:placetype":"venue"
},
  "geometry": {"coordinates":[8.016513,48.406296],"type":"Point"}
}