{
  "type": "Feature",
  "properties": {
    "iso:country":"DE",
    "sg:address":"Auwer Str. 56",
    "sg:city":"Bleialf",
    "sg:phone":"+49 6555/92510",
    "sg:postcode":"54608",
    "sg:province":"Rheinland-Pfalz",
    "wof:name":"Reho Gmbh",
    "wof:placetype":"venue"
},
  "geometry": {"coordinates":[6.2831177711,50.243976593],"type":"Point"}
}