{
  "type": "Feature",
  "properties": {
    "iso:country":"DE",
    "sg:address":"Clemens-August-Str. 69",
    "sg:city":"Bonn",
    "sg:phone":"+49 228/215100",
    "sg:postcode":"53115",
    "sg:province":"Nordrhein-Westfalen",
    "wof:name":"Famagusta Gmbh Lebensmittel-importe",
    "wof:placetype":"venue"
},
  "geometry": {"coordinates":[7.0882749557,50.7213783264],"type":"Point"}
}