{
  "type": "Feature",
  "properties": {
    "iso:country":"DE",
    "sg:address":"Westendstr. 76",
    "sg:city":"Maintal",
    "sg:phone":"+49 6181/495729",
    "sg:postcode":"63477",
    "sg:province":"Hessen",
    "wof:name":"T. Moog Immobilienmakler",
    "wof:placetype":"venue"
},
  "geometry": {"coordinates":[8.8276090622,50.1360702515],"type":"Point"}
}