{
  "type": "Feature",
  "properties": {
    "iso:country":"DE",
    "sg:address":"Eppendorfer Landstr. 113",
    "sg:city":"Hamburg",
    "sg:phone":"+49 40/461817",
    "sg:postcode":"20251",
    "sg:province":"Hamburg",
    "wof:name":"Peter Busch Schl\u00fcsseldienst",
    "wof:placetype":"venue"
},
  "geometry": {"coordinates":[9.9881696701,53.5945091248],"type":"Point"}
}