{
  "type": "Feature",
  "properties": {
    "iso:country":"DE",
    "sg:address":"Riedstr. 67A",
    "sg:city":"Fl\u00f6rsheim",
    "sg:phone":"+49 6145/502121",
    "sg:postcode":"65439",
    "sg:province":"Hessen",
    "wof:name":"S. B\u00f6hm",
    "wof:placetype":"venue"
},
  "geometry": {"coordinates":[8.4390058517,50.0203323364],"type":"Point"}
}