{
  "type": "Feature",
  "properties": {
    "iso:country":"DE",
    "sg:address":"Bahnhofstr. 71",
    "sg:city":"Haiger",
    "sg:phone":"+49 2773/4637",
    "sg:postcode":"35708",
    "sg:province":"Hessen",
    "wof:name":"Hans Lehr",
    "wof:placetype":"venue"
},
  "geometry": {"coordinates":[8.2080688477,50.740524292],"type":"Point"}
}