{
  "type": "Feature",
  "properties": {
    "iso:country":"DE",
    "sg:address":"Schlo\u00dfbergstr. 4",
    "sg:city":"Anzing",
    "sg:phone":"+49 8121/3484",
    "sg:postcode":"85646",
    "sg:province":"Bayern",
    "wof:name":"Sebastian Germeier",
    "wof:placetype":"venue"
},
  "geometry": {"coordinates":[11.8441801071,48.1356086731],"type":"Point"}
}