{
  "type": "Feature",
  "properties": {
    "iso:country":"DE",
    "sg:address":"Korallenring 3",
    "sg:city":"Wilhelmshaven",
    "sg:phone":"+49 4421/501638",
    "sg:postcode":"26388",
    "sg:province":"Niedersachsen",
    "wof:name":"Prof. Dr. Adolf Hobbacher",
    "wof:placetype":"venue"
},
  "geometry": {"coordinates":[8.1074390411,53.5796966553],"type":"Point"}
}