{
  "type": "Feature",
  "properties": {
    "iso:country":"DE",
    "sg:address":"Schlesierstr. 1",
    "sg:city":"Sulzbach",
    "sg:phone":"+49 6028/6305",
    "sg:postcode":"63834",
    "sg:province":"Bayern",
    "wof:name":"Hock Gmbh Fliesen",
    "wof:placetype":"venue"
},
  "geometry": {"coordinates":[9.1642904282,49.9129295349],"type":"Point"}
}