{
  "type": "Feature",
  "properties": {
    "iso:country":"DE",
    "sg:address":"An den Platanen 2a",
    "sg:city":"Duisburg",
    "sg:phone":"+49 203/720746",
    "sg:postcode":"47279",
    "sg:province":"Nordrhein-Westfalen",
    "wof:name":"Top Velo Gmbh",
    "wof:placetype":"venue"
},
  "geometry": {"coordinates":[6.7980132103,51.3923912048],"type":"Point"}
}