{
  "type": "Feature",
  "properties": {
    "iso:country":"DE",
    "sg:address":"Bernried 18",
    "sg:city":"Neukirch",
    "sg:phone":"+49 7528/92030",
    "sg:postcode":"88099",
    "sg:province":"Baden-W\u00fcrttemberg",
    "wof:name":"Wolfgang S\u00f6rgel Metall- Beh\u00e4lter- Und",
    "wof:placetype":"venue"
},
  "geometry": {"coordinates":[9.6933517456,47.6577262878],"type":"Point"}
}