{
  "type": "Feature",
  "properties": {
    "iso:country":"DE",
    "sg:address":"Theodor-Heuss-Str. 55",
    "sg:city":"Taunusstein",
    "sg:phone":"+49 6128/86651",
    "sg:postcode":"65232",
    "sg:province":"Hessen",
    "wof:name":"S & G Servicleistungen E. Kfm.",
    "wof:placetype":"venue"
},
  "geometry": {"coordinates":[8.147262,50.134155],"type":"Point"}
}