{
  "type": "Feature",
  "properties": {
    "iso:country":"DE",
    "sg:address":"Ob der Wette 7",
    "sg:city":"Ostfildern",
    "sg:phone":"+49 711/454708",
    "sg:postcode":"73760",
    "sg:province":"Baden-W\u00fcrttemberg",
    "wof:name":"B. Gehrung",
    "wof:placetype":"venue"
},
  "geometry": {"coordinates":[9.232908,48.718403],"type":"Point"}
}