{
  "type": "Feature",
  "properties": {
    "iso:country":"DE",
    "sg:address":"Grundscheidsweg 11",
    "sg:city":"Velbert",
    "sg:phone":"+49 2051/81708",
    "sg:postcode":"42549",
    "sg:province":"Nordrhein-Westfalen",
    "wof:name":"F. J. Diers",
    "wof:placetype":"venue"
},
  "geometry": {"coordinates":[7.01207,51.358421],"type":"Point"}
}