{
  "type": "Feature",
  "properties": {
    "iso:country":"DE",
    "sg:address":"Fabrikstrasse 11",
    "sg:city":"Hassloch",
    "sg:phone":"+49 6324/982020",
    "sg:postcode":"67454",
    "sg:province":"Rheinland-Pfalz",
    "wof:name":"Eugen Hartmann Gmbh",
    "wof:placetype":"venue"
},
  "geometry": {"coordinates":[8.239932,49.3461],"type":"Point"}
}