{
  "type": "Feature",
  "properties": {
    "iso:country":"DE",
    "sg:address":"Schlagfeld 6",
    "sg:city":"Bodenw\u00f6hr",
    "sg:phone":"+49 9434/763",
    "sg:postcode":"92439",
    "sg:province":"Bayern",
    "wof:name":"Wildenauer Gmbh",
    "wof:placetype":"venue"
},
  "geometry": {"coordinates":[12.2476596832,49.297252655],"type":"Point"}
}