{
  "type": "Feature",
  "properties": {
    "iso:country":"DE",
    "sg:address":"Kaiserstr. 24",
    "sg:city":"Rendsburg",
    "sg:phone":"+49 4331/5057",
    "sg:postcode":"24768",
    "sg:province":"Schleswig-Holstein",
    "wof:name":"Radtke Heigener Und Brugger Rechtsanw\u00e4lte Und Notare",
    "wof:placetype":"venue"
},
  "geometry": {"coordinates":[9.6713228226,54.2968254089],"type":"Point"}
}