{
  "type": "Feature",
  "properties": {
    "iso:country":"DE",
    "sg:address":"H\u00fcgelstr. 24",
    "sg:city":"R\u00fcsselsheim",
    "sg:phone":"+49 6142/62560",
    "sg:postcode":"65428",
    "sg:province":"Hessen",
    "wof:name":"Beuerle Leder Gmbh",
    "wof:placetype":"venue"
},
  "geometry": {"coordinates":[8.4160394669,49.9930610657],"type":"Point"}
}