{
  "type": "Feature",
  "properties": {
    "iso:country":"DE",
    "sg:address":"Breite Gasse 7",
    "sg:city":"Hummeltal",
    "sg:phone":"+49 9201/95270",
    "sg:postcode":"95503",
    "sg:province":"Bayern",
    "wof:name":"Amk Gmbh",
    "wof:placetype":"venue"
},
  "geometry": {"coordinates":[11.500446,49.896088],"type":"Point"}
}