{
  "type": "Feature",
  "properties": {
    "iso:country":"DE",
    "sg:address":"Mauerkircherstr. 197",
    "sg:city":"M\u00fcnchen",
    "sg:phone":"+49 89/9989980",
    "sg:postcode":"81925",
    "sg:province":"Bayern",
    "wof:name":"Dr. Gies Verm\u00f6gens- Verwaltungs- Gmbh",
    "wof:placetype":"venue"
},
  "geometry": {"coordinates":[11.6197395325,48.1683921814],"type":"Point"}
}