{
  "type": "Feature",
  "properties": {
    "iso:country":"DE",
    "sg:address":"Zum Eichwald",
    "sg:city":"Seibersbach",
    "sg:phone":"+49 6736/792",
    "sg:postcode":"55444",
    "sg:province":"Rheinland-Pfalz",
    "wof:name":"Linke Kleintransporte",
    "wof:placetype":"venue"
},
  "geometry": {"coordinates":[7.714665,49.96294],"type":"Point"}
}