{
  "type": "Feature",
  "properties": {
    "iso:country":"DE",
    "sg:address":"Am L\u00f6schling7",
    "sg:city":"Tholey-Bergweiler",
    "sg:phone":"+49 6853/7185",
    "sg:postcode":"66636",
    "sg:province":"Saarland",
    "wof:name":"Inormationsplattform F\u00fcr Die Schaumbergregion Im S Http:/",
    "wof:placetype":"venue"
},
  "geometry": {"coordinates":[7.038075,49.483597],"type":"Point"}
}