{
  "type": "Feature",
  "properties": {
    "iso:country":"DE",
    "sg:address":"Ulmenweg 46",
    "sg:city":"Aschaffenburg",
    "sg:phone":"+49 6021/89185",
    "sg:postcode":"63741",
    "sg:province":"Bayern",
    "wof:name":"Gro\u00dfmann Gmbh",
    "wof:placetype":"venue"
},
  "geometry": {"coordinates":[9.117046,49.959351],"type":"Point"}
}