{
  "type": "Feature",
  "properties": {
    "iso:country":"DE",
    "sg:address":"Mariahilfbergweg",
    "sg:city":"Amberg",
    "sg:phone":"+49 9621/15081",
    "sg:postcode":"92224",
    "sg:province":"Bayern",
    "wof:name":"Kath. \u00d6ffentliche B\u00fccherei Des St\u00e4dtischen Marienkrankh.",
    "wof:placetype":"venue"
},
  "geometry": {"coordinates":[11.876412,49.451633],"type":"Point"}
}