{
  "type": "Feature",
  "properties": {
    "iso:country":"DE",
    "sg:address":"Sedanstr. 43",
    "sg:city":"Hildesheim",
    "sg:phone":"+49 5121/33615",
    "sg:postcode":"31134",
    "sg:province":"Niedersachsen",
    "wof:name":"Albert M\u00f6hle Steuerberater",
    "wof:placetype":"venue"
},
  "geometry": {"coordinates":[9.9589853287,52.1472663879],"type":"Point"}
}