{
  "type": "Feature",
  "properties": {
    "iso:country":"DE",
    "sg:address":"Teckstr. 40",
    "sg:city":"Deizisau",
    "sg:postcode":"73779",
    "sg:province":"Baden-W\u00fcrttemberg",
    "wof:name":"Kleintierz\u00fcchterverein Heini Jahn",
    "wof:placetype":"venue"
},
  "geometry": {"coordinates":[9.3774089813,48.7089500427],"type":"Point"}
}