{
  "type": "Feature",
  "properties": {
    "iso:country":"DE",
    "sg:address":"Seifgrundstr. 2",
    "sg:city":"Bad Homburg",
    "sg:phone":"+49 6172/301091",
    "sg:postcode":"61348",
    "sg:province":"Hessen",
    "wof:name":"Mercury Publicity Deutschland Gmbh",
    "wof:placetype":"venue"
},
  "geometry": {"coordinates":[8.6064844131,50.2239456177],"type":"Point"}
}