{
  "type": "Feature",
  "properties": {
    "iso:country":"DE",
    "sg:address":"Dachsweg 25",
    "sg:city":"Ahaus",
    "sg:phone":"+49 2561/3918",
    "sg:postcode":"48683",
    "sg:province":"Nordrhein-Westfalen",
    "wof:name":"Schulze-herringen Architekt",
    "wof:placetype":"venue"
},
  "geometry": {"coordinates":[7.011486,52.09119],"type":"Point"}
}