{
  "type": "Feature",
  "properties": {
    "iso:country":"DE",
    "sg:address":"Gut Neuhof",
    "sg:city":"Bad Kreuznach",
    "sg:phone":"+49 671/41119",
    "sg:postcode":"55545",
    "sg:province":"Rheinland-Pfalz",
    "wof:name":"Wigbert Wolfarth",
    "wof:placetype":"venue"
},
  "geometry": {"coordinates":[7.859459877,49.8692817688],"type":"Point"}
}