{
  "type": "Feature",
  "properties": {
    "iso:country":"DE",
    "sg:address":"Moltkestr. 38",
    "sg:city":"D\u00fcsseldorf",
    "sg:postcode":"40477",
    "sg:province":"Nordrhein-Westfalen",
    "wof:name":"Amd Einkaufsgenossenschaft Der Medizin- Heil- Und",
    "wof:placetype":"venue"
},
  "geometry": {"coordinates":[6.78571,51.240547],"type":"Point"}
}