{
  "type": "Feature",
  "properties": {
    "iso:country":"DE",
    "sg:address":"Segeberger Landstr. 183",
    "sg:city":"Kiel",
    "sg:phone":"+49 431/713718",
    "sg:postcode":"24145",
    "sg:province":"Schleswig-Holstein",
    "wof:name":"Wolfgang Michel",
    "wof:placetype":"venue"
},
  "geometry": {"coordinates":[10.169885,54.282047],"type":"Point"}
}