{
  "type": "Feature",
  "properties": {
    "iso:country":"DE",
    "sg:address":"Egglkofenstr. 9-11",
    "sg:city":"M\u00fchldorf",
    "sg:phone":"+49 8631/166261",
    "sg:postcode":"84453",
    "sg:province":"Bayern",
    "wof:name":"Bauinvestor Baubetreuungs- Und",
    "wof:placetype":"venue"
},
  "geometry": {"coordinates":[12.533038,48.255596],"type":"Point"}
}