{
  "type": "Feature",
  "properties": {
    "iso:country":"DE",
    "sg:address":"Auf dem Dreische 3",
    "sg:city":"Hagen",
    "sg:phone":"+49 2334/2550",
    "sg:postcode":"58119",
    "sg:province":"Nordrhein-Westfalen",
    "wof:name":"Gl\u00e4ser Bau Gmbh",
    "wof:placetype":"venue"
},
  "geometry": {"coordinates":[7.5742230415,51.3585128784],"type":"Point"}
}