{
  "type": "Feature",
  "properties": {
    "iso:country":"DE",
    "sg:address":"Opladener Str. 143",
    "sg:city":"Langenfeld",
    "sg:phone":"+49 2173/17733",
    "sg:postcode":"40764",
    "sg:province":"Nordrhein-Westfalen",
    "wof:name":"Reusrather Apotheke Grit Hartmann-crahs E. K.",
    "wof:placetype":"venue"
},
  "geometry": {"coordinates":[6.973387,51.083824],"type":"Point"}
}