{
  "type": "Feature",
  "properties": {
    "iso:country":"DE",
    "sg:address":"Frischwassertal 17 b",
    "sg:city":"List",
    "sg:postcode":"25992",
    "sg:province":"Schleswig-Holstein",
    "wof:name":"H\u00fcs Bi See",
    "wof:placetype":"venue"
},
  "geometry": {"coordinates":[8.421336174,55.0103302002],"type":"Point"}
}