{
  "type": "Feature",
  "properties": {
    "iso:country":"DE",
    "sg:address":"Kleinwolmsdorfer Str. 33",
    "sg:city":"Arnsdorf",
    "sg:phone":"+49 35200/23193",
    "sg:postcode":"01477",
    "sg:province":"Sachsen",
    "wof:name":"Julius Schramm",
    "wof:placetype":"venue"
},
  "geometry": {"coordinates":[13.975557,51.090279],"type":"Point"}
}