{
  "type": "Feature",
  "properties": {
    "iso:country":"DE",
    "sg:address":"Lindenstr. 2",
    "sg:city":"St\u00f6dtlen",
    "sg:phone":"+49 7964/2255",
    "sg:postcode":"73495",
    "sg:province":"Baden-W\u00fcrttemberg",
    "wof:name":"G\u00fcnter Stark",
    "wof:placetype":"venue"
},
  "geometry": {"coordinates":[10.3453931808,49.0221290588],"type":"Point"}
}