{
  "type": "Feature",
  "properties": {
    "iso:country":"DE",
    "sg:address":"Wellingshof 1",
    "sg:city":"Wellingshof",
    "sg:phone":"+49 7181/65976",
    "sg:postcode":"73614",
    "sg:province":"Baden-W\u00fcrttemberg",
    "wof:name":"Heinrich Rube",
    "wof:placetype":"venue"
},
  "geometry": {"coordinates":[9.562034,48.832863],"type":"Point"}
}