{
  "type": "Feature",
  "properties": {
    "iso:country":"DE",
    "sg:address":"Weilerswister Str. 2",
    "sg:city":"Erftstadt",
    "sg:phone":"+49 2235/77261",
    "sg:postcode":"50374",
    "sg:province":"Nordrhein-Westfalen",
    "wof:name":"Gastst\u00e4tte Ludwig M\u00fchrer",
    "wof:placetype":"venue"
},
  "geometry": {"coordinates":[6.7655310631,50.7999420166],"type":"Point"}
}