{
  "type": "Feature",
  "properties": {
    "iso:country":"DE",
    "sg:address":"Marktplatz 2",
    "sg:city":"Deidesheim",
    "sg:phone":"+49 4963/2670942",
    "sg:postcode":"67146",
    "sg:province":"Rheinland-Pfalz",
    "wof:name":"Raiffeisenbank Mittelhaardt Eg",
    "wof:placetype":"venue"
},
  "geometry": {"coordinates":[8.187483,49.407761],"type":"Point"}
}