{
  "type": "Feature",
  "properties": {
    "iso:country":"DE",
    "sg:address":"Freiburger Str. 6",
    "sg:city":"V\u00f6rstetten",
    "sg:phone":"+49 4976/666033",
    "sg:postcode":"79279",
    "sg:province":"Baden-W\u00fcrttemberg",
    "wof:name":"Raiffeisenbank Gundelfingen Eg",
    "wof:placetype":"venue"
},
  "geometry": {"coordinates":[7.850834,48.063965],"type":"Point"}
}