{
  "type": "Feature",
  "properties": {
    "iso:country":"DE",
    "sg:address":"Neugrabener Bahnhofstr. 24",
    "sg:city":"Hamburg",
    "sg:postcode":"21149",
    "sg:province":"Hamburg",
    "wof:name":"Mtu Multi-transport- Union Gmbh",
    "wof:placetype":"venue"
},
  "geometry": {"coordinates":[9.854224205,53.4692306519],"type":"Point"}
}