{
  "type": "Feature",
  "properties": {
    "iso:country":"DE",
    "sg:address":"Lindenstr. 19",
    "sg:city":"Pritzwalk",
    "sg:phone":"+49 3395/306180",
    "sg:postcode":"16928",
    "sg:province":"Brandenburg",
    "wof:name":"Charles Rouvel",
    "wof:placetype":"venue"
},
  "geometry": {"coordinates":[12.184043,53.148281],"type":"Point"}
}