{
  "type": "Feature",
  "properties": {
    "iso:country":"DE",
    "sg:address":"Spindeltal 32",
    "sg:city":"Eichst\u00e4tt",
    "sg:phone":"+49 8421/901263",
    "sg:postcode":"85072",
    "sg:province":"Bayern",
    "wof:name":"Prof. Karl-josef Schattner Architekt",
    "wof:placetype":"venue"
},
  "geometry": {"coordinates":[11.20406,48.887611],"type":"Point"}
}