{
  "type": "Feature",
  "properties": {
    "iso:country":"DE",
    "sg:address":"Moosbachstr. 8",
    "sg:city":"Rotterode",
    "sg:phone":"+49 36847/33800",
    "sg:postcode":"98587",
    "sg:province":"Th\u00fcringen",
    "wof:name":"H. Recknagel",
    "wof:placetype":"venue"
},
  "geometry": {"coordinates":[10.5609102249,50.7128791809],"type":"Point"}
}