{
  "type": "Feature",
  "properties": {
    "iso:country":"DE",
    "sg:address":"Hauptstr. 103",
    "sg:city":"Seth",
    "sg:phone":"+49 4194/7195",
    "sg:postcode":"23845",
    "sg:province":"Schleswig-Holstein",
    "wof:name":"Bruno Studt",
    "wof:placetype":"venue"
},
  "geometry": {"coordinates":[10.171242,53.851086],"type":"Point"}
}