{
  "type": "Feature",
  "properties": {
    "iso:country":"DE",
    "sg:address":"Karlstr. 70",
    "sg:city":"Lauterbach",
    "sg:phone":"+49 6641/3374",
    "sg:postcode":"36341",
    "sg:province":"Hessen",
    "wof:name":"Edeka-markt",
    "wof:placetype":"venue"
},
  "geometry": {"coordinates":[9.3962240219,50.6271324158],"type":"Point"}
}