{
  "type": "Feature",
  "properties": {
    "iso:country":"DE",
    "sg:address":"Mundinger Str. 16",
    "sg:city":"Emmendingen",
    "sg:phone":"+49 4976/418035",
    "sg:postcode":"79312",
    "sg:province":"Baden-W\u00fcrttemberg",
    "wof:name":"Metzgerei Mertz Gmbh",
    "wof:placetype":"venue"
},
  "geometry": {"coordinates":[7.8438138962,48.1242675781],"type":"Point"}
}