{
  "type": "Feature",
  "properties": {
    "iso:country":"DE",
    "sg:address":"Gelderner Str. 2",
    "sg:city":"Issum",
    "sg:phone":"+49 2835/444160",
    "sg:postcode":"47661",
    "sg:province":"Nordrhein-Westfalen",
    "wof:name":"Thomas Sengerling Rechtsanwalt",
    "wof:placetype":"venue"
},
  "geometry": {"coordinates":[6.4256010056,51.5346832275],"type":"Point"}
}