{
  "type": "Feature",
  "properties": {
    "iso:country":"DE",
    "sg:address":"Am Moosrangen 45",
    "sg:city":"Ammerndorf",
    "sg:phone":"+49 9127/8077",
    "sg:postcode":"90614",
    "sg:province":"Bayern",
    "wof:name":"Grassinger Gmbh & Co, F Dipling(fh)",
    "wof:placetype":"venue"
},
  "geometry": {"coordinates":[10.84645,49.422592],"type":"Point"}
}