{
  "type": "Feature",
  "properties": {
    "iso:country":"DE",
    "sg:address":"Hauptstr. 53",
    "sg:city":"Sippersfeld",
    "sg:phone":"+49 6357/96002",
    "sg:postcode":"67729",
    "sg:province":"Rheinland-Pfalz",
    "wof:name":"Ulrich Scheiba Ingenieurb\u00fcro Gmbh",
    "wof:placetype":"venue"
},
  "geometry": {"coordinates":[7.9361639023,49.552482605],"type":"Point"}
}