{
  "type": "Feature",
  "properties": {
    "iso:country":"DE",
    "sg:address":"Unterbornstr. 3",
    "sg:city":"Wiesbaden",
    "sg:phone":"+49 611/507116",
    "sg:postcode":"65207",
    "sg:province":"Hessen",
    "wof:name":"Karl-heinz Brauer",
    "wof:placetype":"venue"
},
  "geometry": {"coordinates":[8.327696,50.081703],"type":"Point"}
}