{
  "type": "Feature",
  "properties": {
    "iso:country":"DE",
    "sg:address":"Windthorststr. 7",
    "sg:city":"Erfurt",
    "sg:phone":"+49 361/3465966",
    "sg:postcode":"99096",
    "sg:province":"Th\u00fcringen",
    "wof:name":"Edmund Gaubitz",
    "wof:placetype":"venue"
},
  "geometry": {"coordinates":[11.040981,50.969997],"type":"Point"}
}