{
  "type": "Feature",
  "properties": {
    "iso:country":"DE",
    "sg:address":"Zum Achimer Bahnhof 15",
    "sg:city":"Achim",
    "sg:phone":"+49 4202/4163",
    "sg:postcode":"28832",
    "sg:province":"Niedersachsen",
    "wof:name":"Heinrich Wendt",
    "wof:placetype":"venue"
},
  "geometry": {"coordinates":[9.032011,53.014587],"type":"Point"}
}