{
  "type": "Feature",
  "properties": {
    "iso:country":"DE",
    "sg:address":"Ankergasse 30",
    "sg:city":"Miltenberg",
    "sg:phone":"+49 9371/65940",
    "sg:postcode":"63897",
    "sg:province":"Bayern",
    "wof:name":"Sparkassenneubau",
    "wof:placetype":"venue"
},
  "geometry": {"coordinates":[9.257902,49.703072],"type":"Point"}
}