{
  "type": "Feature",
  "properties": {
    "iso:country":"DE",
    "sg:address":"Am Strehl 132 a",
    "sg:city":"Oldenburg",
    "sg:phone":"+49 441/9608013",
    "sg:postcode":"26125",
    "sg:province":"Niedersachsen",
    "wof:name":"E. W\u00fcppenhorst Gmbh",
    "wof:placetype":"venue"
},
  "geometry": {"coordinates":[8.2063970566,53.1982917786],"type":"Point"}
}