{
  "type": "Feature",
  "properties": {
    "iso:country":"DE",
    "sg:address":"Magdeburger Str. 15",
    "sg:city":"Brandenburg",
    "sg:postcode":"14770",
    "sg:province":"Brandenburg",
    "wof:name":"Tonstudio Track4",
    "wof:placetype":"venue"
},
  "geometry": {"coordinates":[12.5389280319,52.4124107361],"type":"Point"}
}