{
  "type": "Feature",
  "properties": {
    "iso:country":"DE",
    "sg:address":"Berliner Damm 10",
    "sg:city":"Ellerau",
    "sg:phone":"+49 4106/74321",
    "sg:postcode":"25479",
    "sg:province":"Schleswig-Holstein",
    "wof:name":"E. Habekost",
    "wof:placetype":"venue"
},
  "geometry": {"coordinates":[9.919635,53.75061],"type":"Point"}
}