{
  "type": "Feature",
  "properties": {
    "iso:country":"DE",
    "sg:address":"Georgstr. 10",
    "sg:city":"N\u00fcrnberg",
    "sg:phone":"+49 911/657770",
    "sg:postcode":"90439",
    "sg:province":"Bayern",
    "wof:name":"Praxis Dr. Med. Itzel Jung Und Dr. Med. Zink",
    "wof:placetype":"venue"
},
  "geometry": {"coordinates":[11.0508871078,49.4399108887],"type":"Point"}
}