{
  "type": "Feature",
  "properties": {
    "iso:country":"DE",
    "sg:address":"Waldstra\u00dfe 44",
    "sg:city":"Gro\u00df-Zimmern / Darmstadt",
    "sg:phone":"+49 6071/748853",
    "sg:postcode":"64846",
    "sg:province":"Hessen",
    "wof:name":"Orgaplan",
    "wof:placetype":"venue"
},
  "geometry": {"coordinates":[8.821993,49.878464],"type":"Point"}
}