{
  "type": "Feature",
  "properties": {
    "iso:country":"DE",
    "sg:address":"Erlenweg 14",
    "sg:city":"Nienst\u00e4dt",
    "sg:phone":"+49 5724/7809",
    "sg:postcode":"31688",
    "sg:province":"Niedersachsen",
    "wof:name":"W & O West-ost-handel Gmbh Nienst\u00e4dt",
    "wof:placetype":"venue"
},
  "geometry": {"coordinates":[9.1554870605,52.2813682556],"type":"Point"}
}