{
  "type": "Feature",
  "properties": {
    "iso:country":"DE",
    "sg:address":"Fritz-Lehmhaus-Weg 4",
    "sg:city":"Sprockh\u00f6vel",
    "sg:phone":"+49 2324/90760",
    "sg:postcode":"45549",
    "sg:province":"Nordrhein-Westfalen",
    "wof:name":"Paul Pleiger Handelsgesellschaft Mbh",
    "wof:placetype":"venue"
},
  "geometry": {"coordinates":[7.2506809235,51.3689613342],"type":"Point"}
}