{
  "type": "Feature",
  "properties": {
    "iso:country":"DE",
    "sg:address":"Schulstr. 13",
    "sg:city":"Wittlich",
    "sg:phone":"+49 6571/5053",
    "sg:postcode":"54516",
    "sg:province":"Rheinland-Pfalz",
    "wof:name":"Joh. Birresborn Gmbh",
    "wof:placetype":"venue"
},
  "geometry": {"coordinates":[6.9360218048,49.9729270935],"type":"Point"}
}