{
  "type": "Feature",
  "properties": {
    "iso:country":"DE",
    "sg:address":"Hanauer Str. 9-13",
    "sg:city":"Friedberg",
    "sg:phone":"+49 6031/820",
    "sg:postcode":"61169",
    "sg:province":"Hessen",
    "wof:name":"Oberhessische Versorgungsbetriebe Ag",
    "wof:placetype":"venue"
},
  "geometry": {"coordinates":[8.757265,50.3367],"type":"Point"}
}