{
  "type": "Feature",
  "properties": {
    "iso:country":"DE",
    "sg:address":"Jahnstr. 87",
    "sg:city":"Bergkamen",
    "sg:phone":"+49 2306/84230",
    "sg:postcode":"59192",
    "sg:province":"Nordrhein-Westfalen",
    "wof:name":"Haus Nielinger",
    "wof:placetype":"venue"
},
  "geometry": {"coordinates":[7.5911870003,51.6283416748],"type":"Point"}
}