{
  "type": "Feature",
  "properties": {
    "iso:country":"DE",
    "sg:address":"Hohenberger Str. 27",
    "sg:city":"Seeshaupt",
    "sg:postcode":"82402",
    "sg:province":"Bayern",
    "wof:name":"Wohnbau Beteiligungs Gmbh",
    "wof:placetype":"venue"
},
  "geometry": {"coordinates":[11.287205,47.820911],"type":"Point"}
}