{
  "type": "Feature",
  "properties": {
    "iso:country":"DE",
    "sg:address":"In der Unteren Rombach 6",
    "sg:city":"Heidelberg",
    "sg:postcode":"69118",
    "sg:province":"Baden-W\u00fcrttemberg",
    "wof:name":"Sibylle W\u00fcst Krankengymnastin",
    "wof:placetype":"venue"
},
  "geometry": {"coordinates":[8.743771,49.414238],"type":"Point"}
}