{
  "type": "Feature",
  "properties": {
    "iso:country":"DE",
    "sg:address":"Marktplatz 16",
    "sg:city":"Bad Urach",
    "sg:phone":"+49 7125/8253",
    "sg:postcode":"72574",
    "sg:province":"Baden-W\u00fcrttemberg",
    "wof:name":"Betz Strick- Und Wirkwaren",
    "wof:placetype":"venue"
},
  "geometry": {"coordinates":[9.3995809555,48.4926605225],"type":"Point"}
}