{
  "type": "Feature",
  "properties": {
    "iso:country":"DE",
    "sg:address":"Obere Talstr 7",
    "sg:city":"Osterburken-Schlierstadt",
    "sg:phone":"+49 6292/92810",
    "sg:postcode":"74706",
    "sg:province":"Baden-W\u00fcrttemberg",
    "wof:name":"Bkw Baul\u00e4nder Kunststoffwerk Gmbh",
    "wof:placetype":"venue"
},
  "geometry": {"coordinates":[9.3688783646,49.4581871033],"type":"Point"}
}