{
  "type": "Feature",
  "properties": {
    "iso:country":"DE",
    "sg:address":"Gro\u00dfe Str. 19",
    "sg:city":"Ibbenb\u00fcren",
    "sg:phone":"+49 5451/745665",
    "sg:postcode":"49477",
    "sg:province":"Nordrhein-Westfalen",
    "wof:name":"Bistro-biercafe Magic",
    "wof:placetype":"venue"
},
  "geometry": {"coordinates":[7.7156481743,52.2774581909],"type":"Point"}
}