{
  "type": "Feature",
  "properties": {
    "iso:country":"DE",
    "sg:address":"Langer Weg 24",
    "sg:city":"Esslingen",
    "sg:phone":"+49 711/9372933",
    "sg:postcode":"73732",
    "sg:province":"Baden-W\u00fcrttemberg",
    "wof:name":"Martina Baier",
    "wof:placetype":"venue"
},
  "geometry": {"coordinates":[9.316551,48.754986],"type":"Point"}
}