{
  "type": "Feature",
  "properties": {
    "iso:country":"DE",
    "sg:address":"H\u00fclsemannshof 5b",
    "sg:city":"Duisburg",
    "sg:phone":"+49 4920/3485500",
    "sg:postcode":"47179",
    "sg:province":"Nordrhein-Westfalen",
    "wof:name":"Baugesellschaft Richter Gmbh & Co Kg",
    "wof:placetype":"venue"
},
  "geometry": {"coordinates":[6.747662,51.534439],"type":"Point"}
}