{
  "type": "Feature",
  "properties": {
    "iso:country":"DE",
    "sg:address":"T\u00f6lzer Str. 26 a",
    "sg:city":"Gr\u00fcnwald",
    "sg:phone":"+49 89/6417326",
    "sg:postcode":"82031",
    "sg:province":"Bayern",
    "wof:name":"Wolfram Stutz Rechtsanwalt",
    "wof:placetype":"venue"
},
  "geometry": {"coordinates":[11.5211725235,48.0355186462],"type":"Point"}
}