{
  "type": "Feature",
  "properties": {
    "iso:country":"DE",
    "sg:address":"Bahnhofstr. 9",
    "sg:city":"Mainz",
    "sg:phone":"+49 6131/288080",
    "sg:postcode":"55116",
    "sg:province":"Rheinland-Pfalz",
    "wof:name":"Gebr. Alexander Rheinische Musikinstrumentenfabrik Gmbh",
    "wof:placetype":"venue"
},
  "geometry": {"coordinates":[8.2618837357,50.0008850098],"type":"Point"}
}