{
  "type": "Feature",
  "properties": {
    "iso:country":"DE",
    "sg:address":"Bahnhofstr. 7",
    "sg:city":"Glaubitz",
    "sg:phone":"+49 35265/56881",
    "sg:postcode":"01612",
    "sg:province":"Sachsen",
    "wof:name":"Birgit F\u00f6rster",
    "wof:placetype":"venue"
},
  "geometry": {"coordinates":[13.376412,51.323807],"type":"Point"}
}