{
  "type": "Feature",
  "properties": {
    "iso:country":"DE",
    "sg:address":"B\u00e4renhofweg 31",
    "sg:city":"Titisee-Neustadt",
    "sg:phone":"+49 7651/8165",
    "sg:postcode":"79822",
    "sg:province":"Baden-W\u00fcrttemberg",
    "wof:name":"J\u00fcrgen Kremh\u00fcller",
    "wof:placetype":"venue"
},
  "geometry": {"coordinates":[8.1431131363,47.9044113159],"type":"Point"}
}