{
  "type": "Feature",
  "properties": {
    "iso:country":"DE",
    "sg:address":"\u00d6serstr. 180",
    "sg:city":"Frankfurt",
    "sg:phone":"+49 4969/39050",
    "sg:postcode":"65933",
    "sg:province":"Hessen",
    "wof:name":"Courtyard By Marriott Frankfurt Messe",
    "wof:placetype":"venue"
},
  "geometry": {"coordinates":[8.59509,50.110275],"type":"Point"}
}