{
  "type": "Feature",
  "properties": {
    "iso:country":"DE",
    "sg:address":"Hecklinger Str. 12a",
    "sg:city":"Aschersleben",
    "sg:phone":"+49 3473/816039",
    "sg:postcode":"06449",
    "sg:province":"Sachsen-Anhalt",
    "wof:name":"W. Brandt",
    "wof:placetype":"venue"
},
  "geometry": {"coordinates":[11.46549,51.765209],"type":"Point"}
}