{
  "type": "Feature",
  "properties": {
    "iso:country":"DE",
    "sg:address":"Alemannenstr. 5",
    "sg:city":"Veringenstadt",
    "sg:phone":"+49 7577/3811",
    "sg:postcode":"72519",
    "sg:province":"Baden-W\u00fcrttemberg",
    "wof:name":"Rosemarie P\u00f6tzold",
    "wof:placetype":"venue"
},
  "geometry": {"coordinates":[9.211389,48.184189],"type":"Point"}
}