{
  "type": "Feature",
  "properties": {
    "iso:country":"DE",
    "sg:address":"Bahnhofstr. 92",
    "sg:city":"Lauterbach",
    "sg:postcode":"36341",
    "sg:province":"Hessen",
    "wof:name":"Minimal",
    "wof:placetype":"venue"
},
  "geometry": {"coordinates":[9.4062166214,50.6424789429],"type":"Point"}
}