{
  "type": "Feature",
  "properties": {
    "iso:country":"DE",
    "sg:address":"Spalter Str. 62",
    "sg:city":"Abenberg",
    "sg:phone":"+49 9178/98110",
    "sg:postcode":"91183",
    "sg:province":"Bayern",
    "wof:name":"Bs Bauger\u00e4te-service Gmbh",
    "wof:placetype":"venue"
},
  "geometry": {"coordinates":[10.954839,49.234272],"type":"Point"}
}