{
  "type": "Feature",
  "properties": {
    "iso:country":"DE",
    "sg:address":"Bahnhofstr. 43",
    "sg:city":"Redwitz",
    "sg:phone":"+49 9574/810",
    "sg:postcode":"96257",
    "sg:province":"Bayern",
    "wof:name":"Siemens Ag",
    "wof:placetype":"venue"
},
  "geometry": {"coordinates":[11.204926,50.174805],"type":"Point"}
}