{
  "type": "Feature",
  "properties": {
    "iso:country":"DE",
    "sg:address":"Wohldorfer Str. 9",
    "sg:city":"Hamburg",
    "sg:phone":"+49 40/293870",
    "sg:postcode":"22081",
    "sg:province":"Hamburg",
    "wof:name":"Schnabel & Sa\u00df Gmbh",
    "wof:placetype":"venue"
},
  "geometry": {"coordinates":[10.039884,53.577236],"type":"Point"}
}