{
  "type": "Feature",
  "properties": {
    "iso:country":"DE",
    "sg:address":"An der Christ-K\u00f6nig-Kirche 10",
    "sg:city":"Saarbr\u00fccken",
    "sg:phone":"+49 681/926920",
    "sg:postcode":"66119",
    "sg:province":"Saarland",
    "wof:name":"Medic Gesellschaft F\u00fcr Medizinische Leistungs-",
    "wof:placetype":"venue"
},
  "geometry": {"coordinates":[7.002240181,49.2252464294],"type":"Point"}
}