{
  "type": "Feature",
  "properties": {
    "iso:country":"DE",
    "sg:address":"Kirchstr. 7",
    "sg:city":"Rottweil",
    "sg:phone":"+49 741/21910",
    "sg:postcode":"78628",
    "sg:province":"Baden-W\u00fcrttemberg",
    "wof:name":"Ralf Boegel",
    "wof:placetype":"venue"
},
  "geometry": {"coordinates":[8.6732788086,48.1288414001],"type":"Point"}
}