{
  "type": "Feature",
  "properties": {
    "iso:country":"DE",
    "sg:address":"Anton-Kayser-Str. 20",
    "sg:city":"Dortmund",
    "sg:postcode":"44263",
    "sg:province":"Nordrhein-Westfalen",
    "wof:name":"Reinders Immobilien Gmbh",
    "wof:placetype":"venue"
},
  "geometry": {"coordinates":[7.49578619,51.4878768921],"type":"Point"}
}