{
  "type": "Feature",
  "properties": {
    "iso:country":"DE",
    "sg:address":"M\u00fchlenstr. 13",
    "sg:city":"Liebenburg",
    "sg:postcode":"38704",
    "sg:province":"Niedersachsen",
    "wof:name":"Sl-werkzeugmaschinen Gmbh",
    "wof:placetype":"venue"
},
  "geometry": {"coordinates":[10.4410476685,51.9971466064],"type":"Point"}
}