{
  "type": "Feature",
  "properties": {
    "iso:country":"DE",
    "sg:address":"Obere Regenstr. 32",
    "sg:city":"Regensburg",
    "sg:phone":"+49 941/41710",
    "sg:postcode":"93059",
    "sg:province":"Bayern",
    "wof:name":"Hahn",
    "wof:placetype":"venue"
},
  "geometry": {"coordinates":[12.1029596329,49.0333251953],"type":"Point"}
}