{
  "type": "Feature",
  "properties": {
    "iso:country":"DE",
    "sg:address":"Bahnhofstr.13",
    "sg:city":"Schenklengsfeld",
    "sg:phone":"+49 6629/6031",
    "sg:postcode":"36277",
    "sg:province":"Hessen",
    "wof:name":"Walin",
    "wof:placetype":"venue"
},
  "geometry": {"coordinates":[9.846462,50.816547],"type":"Point"}
}