{
  "type": "Feature",
  "properties": {
    "iso:country":"DE",
    "sg:address":"Tegernseer Str. 95",
    "sg:city":"Reitrain",
    "sg:phone":"+49 8022/26713",
    "sg:postcode":"83700",
    "sg:province":"Bayern",
    "wof:name":"Anton Schaflitzel",
    "wof:placetype":"venue"
},
  "geometry": {"coordinates":[11.757709,47.684967],"type":"Point"}
}