{
  "type": "Feature",
  "properties": {
    "iso:country":"DE",
    "sg:address":"Holstenstr. 110",
    "sg:city":"Hamburg",
    "sg:phone":"+49 40/3806492",
    "sg:postcode":"22767",
    "sg:province":"Hamburg",
    "wof:name":"Klaus Peters Architekt",
    "wof:placetype":"venue"
},
  "geometry": {"coordinates":[9.949374,53.557976],"type":"Point"}
}