{
  "type": "Feature",
  "properties": {
    "iso:country":"DE",
    "sg:address":"Bergstr. 7",
    "sg:city":"Allendorf",
    "sg:phone":"+49 6452/6816",
    "sg:postcode":"35108",
    "sg:province":"Hessen",
    "wof:name":"Helmut Friedrich",
    "wof:placetype":"venue"
},
  "geometry": {"coordinates":[8.6677036285,51.0337867737],"type":"Point"}
}