{
  "type": "Feature",
  "properties": {
    "iso:country":"DE",
    "sg:address":"Bruchhauser Str. 10",
    "sg:city":"Martfeld",
    "sg:phone":"+49 4255/276",
    "sg:postcode":"27327",
    "sg:province":"Niedersachsen",
    "wof:name":"Windpark Neue Weide Verwaltungsgesellschaft Mbh",
    "wof:placetype":"venue"
},
  "geometry": {"coordinates":[9.0557718277,52.8729743958],"type":"Point"}
}