{
  "type": "Feature",
  "properties": {
    "iso:country":"DE",
    "sg:address":"Koblenzer Str. 16",
    "sg:city":"Falkensee",
    "sg:phone":"+49 3322/201288",
    "sg:postcode":"14612",
    "sg:province":"Brandenburg",
    "wof:name":"Thomas Jung",
    "wof:placetype":"venue"
},
  "geometry": {"coordinates":[13.1153717041,52.5621871948],"type":"Point"}
}