{
  "type": "Feature",
  "properties": {
    "iso:country":"DE",
    "sg:address":"Neusalzaer Str. 27a",
    "sg:city":"L\u00f6bau",
    "sg:phone":"+49 3585/862070",
    "sg:postcode":"02708",
    "sg:province":"Sachsen",
    "wof:name":"Dr. Ernst Schlegel Tierarzt",
    "wof:placetype":"venue"
},
  "geometry": {"coordinates":[14.659236908,51.0936546326],"type":"Point"}
}