{
  "type": "Feature",
  "properties": {
    "iso:country":"DE",
    "sg:address":"Breite Str. 6",
    "sg:city":"Hannover",
    "sg:phone":"+49 511/321826",
    "sg:postcode":"30159",
    "sg:province":"Niedersachsen",
    "wof:name":"Rbi Regionale Beteiligungs- Ges. F\u00fcr Inovationsanwendung",
    "wof:placetype":"venue"
},
  "geometry": {"coordinates":[9.738157,52.372276],"type":"Point"}
}