{
  "type": "Feature",
  "properties": {
    "iso:country":"DE",
    "sg:address":"Herrenstein 46",
    "sg:city":"Drensteinfurt",
    "sg:postcode":"48317",
    "sg:province":"Nordrhein-Westfalen",
    "wof:name":"Herrensteiner Agrargro\u00dfhandels-",
    "wof:placetype":"venue"
},
  "geometry": {"coordinates":[7.803826,51.737335],"type":"Point"}
}