{
  "type": "Feature",
  "properties": {
    "iso:country":"DE",
    "sg:address":"Auf der Ader 3",
    "sg:city":"Horbruch",
    "sg:phone":"+49 6543/2562",
    "sg:postcode":"55483",
    "sg:province":"Rheinland-Pfalz",
    "wof:name":"Robert Trarbach",
    "wof:placetype":"venue"
},
  "geometry": {"coordinates":[7.240812,49.888077],"type":"Point"}
}