{
  "type": "Feature",
  "properties": {
    "iso:country":"DE",
    "sg:address":"Am Seerhein 6",
    "sg:city":"Konstanz",
    "sg:phone":"+49 7531/53097",
    "sg:postcode":"78467",
    "sg:province":"Baden-W\u00fcrttemberg",
    "wof:name":"Corona Consulting Ges. F\u00fcr Strategische Unternehmens-",
    "wof:placetype":"venue"
},
  "geometry": {"coordinates":[9.1580572128,47.6715316772],"type":"Point"}
}