{
  "type": "Feature",
  "properties": {
    "iso:country":"DE",
    "sg:address":"Kampstr. 20",
    "sg:city":"Bottrop",
    "sg:phone":"+49 2041/61851",
    "sg:postcode":"46238",
    "sg:province":"Nordrhein-Westfalen",
    "wof:name":"Karl Lindemann",
    "wof:placetype":"venue"
},
  "geometry": {"coordinates":[6.9487051964,51.5227165222],"type":"Point"}
}