{
  "type": "Feature",
  "properties": {
    "iso:country":"DE",
    "sg:address":"L\u00f6rickstr. 12",
    "sg:city":"Neuss",
    "sg:phone":"+49 2131/44552",
    "sg:postcode":"41464",
    "sg:province":"Nordrhein-Westfalen",
    "wof:name":"Maler Dworak Gmbh",
    "wof:placetype":"venue"
},
  "geometry": {"coordinates":[6.687794,51.191971],"type":"Point"}
}