{
  "type": "Feature",
  "properties": {
    "iso:country":"DE",
    "sg:address":"Hamalandstr. 75",
    "sg:city":"Ahaus",
    "sg:phone":"+49 2561/2804",
    "sg:postcode":"48683",
    "sg:province":"Nordrhein-Westfalen",
    "wof:name":"Johann Gorkotte",
    "wof:placetype":"venue"
},
  "geometry": {"coordinates":[6.968999,52.094173],"type":"Point"}
}