{
  "type": "Feature",
  "properties": {
    "iso:country":"DE",
    "sg:address":"Untergasse 17",
    "sg:city":"Guxhagen",
    "sg:phone":"+49 5665/2234",
    "sg:postcode":"34302",
    "sg:province":"Hessen",
    "wof:name":"Walter Most",
    "wof:placetype":"venue"
},
  "geometry": {"coordinates":[9.48063,51.200909],"type":"Point"}
}