{
  "type": "Feature",
  "properties": {
    "iso:country":"DE",
    "sg:address":"Lappenbrink 20",
    "sg:city":"Sassenberg",
    "sg:phone":"+49 2583/1557",
    "sg:postcode":"48336",
    "sg:province":"Nordrhein-Westfalen",
    "wof:name":"Josef Berkemeier",
    "wof:placetype":"venue"
},
  "geometry": {"coordinates":[8.0377187729,51.9885101318],"type":"Point"}
}