{
  "type": "Feature",
  "properties": {
    "iso:country":"DE",
    "sg:address":"Lorscher Str. 1",
    "sg:city":"Viernheim",
    "sg:phone":"+49 6204/77436",
    "sg:postcode":"68519",
    "sg:province":"Hessen",
    "wof:name":"Bistro Journal",
    "wof:placetype":"venue"
},
  "geometry": {"coordinates":[8.5800542831,49.5393447876],"type":"Point"}
}