{
  "type": "Feature",
  "properties": {
    "iso:country":"DE",
    "sg:address":"Landsberger Str. 478",
    "sg:city":"M\u00fcnchen",
    "sg:phone":"+49 89/8206062",
    "sg:postcode":"81241",
    "sg:province":"Bayern",
    "wof:name":"Kurt Brummer Steuerberater",
    "wof:placetype":"venue"
},
  "geometry": {"coordinates":[11.4645338058,48.1465072632],"type":"Point"}
}