{
  "type": "Feature",
  "properties": {
    "iso:country":"DE",
    "sg:address":"Gleviner Str. 3",
    "sg:city":"G\u00fcstrow",
    "sg:phone":"+49 3843/69690",
    "sg:postcode":"18273",
    "sg:province":"Mecklenburg-Vorpommern",
    "wof:name":"Connys Reiseb\u00fcro Gmbh",
    "wof:placetype":"venue"
},
  "geometry": {"coordinates":[12.1775093079,53.7929496765],"type":"Point"}
}