{
  "type": "Feature",
  "properties": {
    "iso:country":"DE",
    "sg:address":"Maybachstr. 43",
    "sg:city":"L\u00f6wenstein",
    "sg:phone":"+49 7130/542",
    "sg:postcode":"74245",
    "sg:province":"Baden-W\u00fcrttemberg",
    "wof:name":"Lamm",
    "wof:placetype":"venue"
},
  "geometry": {"coordinates":[9.3804988861,49.0944824219],"type":"Point"}
}