{
  "type": "Feature",
  "properties": {
    "iso:country":"DE",
    "sg:address":"Schillerstr. 10",
    "sg:city":"Bremen",
    "sg:phone":"+49 421/3680233",
    "sg:postcode":"28195",
    "sg:province":"Bremen",
    "wof:name":"Betriebsarztzentrum Bremen E. V.",
    "wof:placetype":"venue"
},
  "geometry": {"coordinates":[8.81431,53.079411],"type":"Point"}
}