{
  "type": "Feature",
  "properties": {
    "iso:country":"DE",
    "sg:address":"rajen 203",
    "sg:city":"rhauderfehn",
    "sg:phone":"+49 4952/92260",
    "sg:postcode":"26817",
    "sg:province":"Niedersachsen",
    "wof:name":"Solarien Solarienhandel Solarien Albers Gmbh",
    "wof:placetype":"venue"
},
  "geometry": {"coordinates":[7.537249,53.132122],"type":"Point"}
}