{
  "type": "Feature",
  "properties": {
    "iso:country":"DE",
    "sg:address":"Heinrich-Kanzler-Str. 2a",
    "sg:city":"Naila",
    "sg:phone":"+49 9282/412",
    "sg:postcode":"95119",
    "sg:province":"Bayern",
    "wof:name":"Reinhard Sp\u00f6rl Ingenieur",
    "wof:placetype":"venue"
},
  "geometry": {"coordinates":[11.7130527496,50.3257865906],"type":"Point"}
}