{
  "type": "Feature",
  "properties": {
    "iso:country":"DE",
    "sg:address":"Kaiserstr. 1 a",
    "sg:city":"K\u00f6ln",
    "sg:phone":"+49 2203/24530",
    "sg:postcode":"51145",
    "sg:province":"Nordrhein-Westfalen",
    "wof:name":"T. Lissy",
    "wof:placetype":"venue"
},
  "geometry": {"coordinates":[7.0814218521,50.8811683655],"type":"Point"}
}