{
  "type": "Feature",
  "properties": {
    "iso:country":"DE",
    "sg:address":"Schulstr. 1",
    "sg:city":"Gro\u00dfkmehlen",
    "sg:postcode":"01990",
    "sg:province":"Brandenburg",
    "wof:name":"Evangelische Kirche",
    "wof:placetype":"venue"
},
  "geometry": {"coordinates":[13.7236328125,51.3788490295],"type":"Point"}
}