{
  "type": "Feature",
  "properties": {
    "iso:country":"DE",
    "sg:address":"Hauptstr. 47",
    "sg:city":"Staufen",
    "sg:phone":"+49 7633/7078",
    "sg:postcode":"79219",
    "sg:province":"Baden-W\u00fcrttemberg",
    "wof:name":"Hotel-restaurant Zum L\u00f6wen",
    "wof:placetype":"venue"
},
  "geometry": {"coordinates":[9.5638008118,51.3455276489],"type":"Point"}
}