{
  "type": "Feature",
  "properties": {
    "iso:country":"DE",
    "sg:address":"Heinrich-K\u00fcmmel-Str. 8",
    "sg:city":"Hannover",
    "sg:phone":"+49 511/8007970",
    "sg:postcode":"30169",
    "sg:province":"Niedersachsen",
    "wof:name":"Central Immobilien Michael Weise E. Kfm.",
    "wof:placetype":"venue"
},
  "geometry": {"coordinates":[9.7414636612,52.3667831421],"type":"Point"}
}