{
  "type": "Feature",
  "properties": {
    "iso:country":"DE",
    "sg:address":"Langes Feld 20",
    "sg:city":"Hameln",
    "sg:phone":"+49 5151/12009",
    "sg:postcode":"31789",
    "sg:province":"Niedersachsen",
    "wof:name":"C. W. Henke Gmbh Eisen-u. R\u00f6hrengrosshandlung",
    "wof:placetype":"venue"
},
  "geometry": {"coordinates":[9.397152,52.099052],"type":"Point"}
}