{
  "type": "Feature",
  "properties": {
    "iso:country":"DE",
    "sg:address":"Friedensweg 4",
    "sg:city":"Beuren",
    "sg:phone":"+49 7025/7965",
    "sg:postcode":"72660",
    "sg:province":"Baden-W\u00fcrttemberg",
    "wof:name":"Gerhard Maier",
    "wof:placetype":"venue"
},
  "geometry": {"coordinates":[9.395896,48.56702],"type":"Point"}
}