{
  "type": "Feature",
  "properties": {
    "iso:country":"DE",
    "sg:address":"Tisinstr. 2",
    "sg:city":"Oberhaching",
    "sg:phone":"+49 89/6252198",
    "sg:postcode":"82041",
    "sg:province":"Bayern",
    "wof:name":"Eis Cafe Calimero",
    "wof:placetype":"venue"
},
  "geometry": {"coordinates":[11.593162,48.025307],"type":"Point"}
}