{
  "type": "Feature",
  "properties": {
    "iso:country":"DE",
    "sg:address":"Talstr. 10",
    "sg:city":"Hof",
    "sg:phone":"+49 2661/5495",
    "sg:postcode":"56472",
    "sg:province":"Rheinland-Pfalz",
    "wof:name":"Marga Uhr Hebamme",
    "wof:placetype":"venue"
},
  "geometry": {"coordinates":[8.015921,50.664818],"type":"Point"}
}