{
  "type": "Feature",
  "properties": {
    "iso:country":"DE",
    "sg:address":"Selber Str. 26",
    "sg:city":"Hohenberg",
    "sg:phone":"+49 9233/9495",
    "sg:postcode":"95691",
    "sg:province":"Bayern",
    "wof:name":"C. Ru\u00dfwurm",
    "wof:placetype":"venue"
},
  "geometry": {"coordinates":[12.2198801041,50.0978546143],"type":"Point"}
}