{
  "type": "Feature",
  "properties": {
    "iso:country":"DE",
    "sg:address":"Bahnhofstr. 33",
    "sg:city":"Isny",
    "sg:phone":"+49 7562/4004",
    "sg:postcode":"88316",
    "sg:province":"Baden-W\u00fcrttemberg",
    "wof:name":"Carolas Reisetreff",
    "wof:placetype":"venue"
},
  "geometry": {"coordinates":[10.0425109863,47.6963233948],"type":"Point"}
}