{
  "type": "Feature",
  "properties": {
    "iso:country":"DE",
    "sg:address":"Untere Bliesstr. 1",
    "sg:city":"Neunkirchen",
    "sg:phone":"+49 6821/26310",
    "sg:postcode":"66538",
    "sg:province":"Saarland",
    "wof:name":"Knut Mettendorf",
    "wof:placetype":"venue"
},
  "geometry": {"coordinates":[7.208909,49.350739],"type":"Point"}
}