{
  "type": "Feature",
  "properties": {
    "iso:country":"DE",
    "sg:address":"Zeppelinstra\u00dfe 68",
    "sg:city":"Berlin",
    "sg:phone":"+49 30",
    "sg:postcode":"13583",
    "sg:province":"Berlin",
    "wof:name":"Verlag Bernd Neddermeyer - Eisenbahnliteratur",
    "wof:placetype":"venue"
},
  "geometry": {"coordinates":[13.1838636398,52.5422782898],"type":"Point"}
}