{
  "type": "Feature",
  "properties": {
    "iso:country":"DE",
    "sg:address":"Gregor-Mendel-Str. 24 a",
    "sg:city":"Potsdam",
    "sg:postcode":"14469",
    "sg:province":"Brandenburg",
    "wof:name":"Cosmetic Sports Gmbh",
    "wof:placetype":"venue"
},
  "geometry": {"coordinates":[13.043017,52.404533],"type":"Point"}
}