{
  "type": "Feature",
  "properties": {
    "iso:country":"DE",
    "sg:address":"Marktstr. 8",
    "sg:city":"Ochtrup",
    "sg:phone":"+49 2553/2455",
    "sg:postcode":"48607",
    "sg:province":"Nordrhein-Westfalen",
    "wof:name":"T. Hamacher Rechtsanwalt",
    "wof:placetype":"venue"
},
  "geometry": {"coordinates":[7.1869721413,52.2077255249],"type":"Point"}
}