{
  "type": "Feature",
  "properties": {
    "iso:country":"DE",
    "sg:address":"Segelfliegerdamm 94-98",
    "sg:city":"Berlin",
    "sg:phone":"+49 30/6390900",
    "sg:postcode":"12487",
    "sg:province":"Berlin",
    "wof:name":"Inabau Tischlerei Gmbh",
    "wof:placetype":"venue"
},
  "geometry": {"coordinates":[13.5070409775,52.4389915466],"type":"Point"}
}