{
  "type": "Feature",
  "properties": {
    "iso:country":"DE",
    "sg:address":"Theodorenstr. 2",
    "sg:city":"Wiesbaden",
    "sg:phone":"+49 611/3083768",
    "sg:postcode":"65189",
    "sg:province":"Hessen",
    "wof:name":"Itb Industrietechnik Beratung Gmbh",
    "wof:placetype":"venue"
},
  "geometry": {"coordinates":[8.250910759,50.0804710388],"type":"Point"}
}