{
  "type": "Feature",
  "properties": {
    "iso:country":"DE",
    "sg:address":"Biberacher Str. 54",
    "sg:city":"Mittelbiberach",
    "sg:phone":"+49 7351/8823",
    "sg:postcode":"88441",
    "sg:province":"Baden-W\u00fcrttemberg",
    "wof:name":"Erwin Schmid",
    "wof:placetype":"venue"
},
  "geometry": {"coordinates":[9.7473363876,48.0871276855],"type":"Point"}
}