{
  "type": "Feature",
  "properties": {
    "iso:country":"DE",
    "sg:address":"Loisachauen 15",
    "sg:city":"Garmisch-Partenkirchen",
    "sg:phone":"+49 8821/78485",
    "sg:postcode":"82467",
    "sg:province":"Bayern",
    "wof:name":"Hans-j\u00f6rg Neuner Container-betrieb Gmbh",
    "wof:placetype":"venue"
},
  "geometry": {"coordinates":[11.1039905548,47.5131607056],"type":"Point"}
}