{
  "type": "Feature",
  "properties": {
    "iso:country":"DE",
    "sg:address":"K\u00f6nigsallee 24",
    "sg:city":"D\u00fcsseldorf",
    "sg:phone":"+49 211/320548",
    "sg:postcode":"40212",
    "sg:province":"Nordrhein-Westfalen",
    "wof:name":"Berkenheier & Hoerhager Gmbh",
    "wof:placetype":"venue"
},
  "geometry": {"coordinates":[6.779569,51.224979],"type":"Point"}
}