{
  "type": "Feature",
  "properties": {
    "iso:country":"DE",
    "sg:address":"Am Bleichewall 3",
    "sg:city":"Northeim",
    "sg:phone":"+49 5551/98180",
    "sg:postcode":"37154",
    "sg:province":"Niedersachsen",
    "wof:name":"Northeimer Wohnungsbau Gmbh",
    "wof:placetype":"venue"
},
  "geometry": {"coordinates":[10.0040407181,51.707069397],"type":"Point"}
}