{
  "type": "Feature",
  "properties": {
    "iso:country":"DE",
    "sg:address":"J\u00fclicher Str 191",
    "sg:city":"Aachen",
    "sg:phone":"+49 241/82525",
    "sg:postcode":"52070",
    "sg:province":"Nordrhein-Westfalen",
    "wof:name":"Minetti",
    "wof:placetype":"venue"
},
  "geometry": {"coordinates":[6.1088571548,50.7846374512],"type":"Point"}
}