{
  "type": "Feature",
  "properties": {
    "iso:country":"DE",
    "sg:address":"Hohe Str. 85-87",
    "sg:city":"K\u00f6ln",
    "sg:phone":"+49 221/920440",
    "sg:postcode":"50667",
    "sg:province":"Nordrhein-Westfalen",
    "wof:name":"Pro Sky Airbroker Gmbh",
    "wof:placetype":"venue"
},
  "geometry": {"coordinates":[6.9560141563,50.9376296997],"type":"Point"}
}