{
  "type": "Feature",
  "properties": {
    "iso:country":"DE",
    "sg:address":"Peter-Nonnenm\u00fchlen-Allee 80 F",
    "sg:city":"M\u00f6nchengladbach",
    "sg:phone":"+49 2161/88526",
    "sg:postcode":"41063",
    "sg:province":"Nordrhein-Westfalen",
    "wof:name":"Fritz Offermann Architekt",
    "wof:placetype":"venue"
},
  "geometry": {"coordinates":[6.430345,51.205036],"type":"Point"}
}