{
  "type": "Feature",
  "properties": {
    "iso:country":"DE",
    "sg:address":"An der Kreuzkirche 2",
    "sg:city":"Wassenberg",
    "sg:phone":"+49 2432/2142",
    "sg:postcode":"41849",
    "sg:province":"Nordrhein-Westfalen",
    "wof:name":"Ev. Pfarramt",
    "wof:placetype":"venue"
},
  "geometry": {"coordinates":[6.169066906,51.1051216125],"type":"Point"}
}