{
  "type": "Feature",
  "properties": {
    "iso:country":"DE",
    "sg:address":"Wasserweg 9",
    "sg:city":"Winkelhaid",
    "sg:phone":"+49 9187/41255",
    "sg:postcode":"90610",
    "sg:province":"Bayern",
    "wof:name":"Hans Zantner",
    "wof:placetype":"venue"
},
  "geometry": {"coordinates":[11.295914,49.390816],"type":"Point"}
}