{
  "type": "Feature",
  "properties": {
    "iso:country":"DE",
    "sg:address":"Obertorstr. 23",
    "sg:city":"\u00dcberlingen",
    "sg:phone":"+49 7551/2885",
    "sg:postcode":"88662",
    "sg:province":"Baden-W\u00fcrttemberg",
    "wof:name":"Gei\u00dfele",
    "wof:placetype":"venue"
},
  "geometry": {"coordinates":[9.168867,47.769184],"type":"Point"}
}