{
  "type": "Feature",
  "properties": {
    "iso:country":"DE",
    "sg:address":"Georgstr. 2",
    "sg:city":"Wiesbaden",
    "sg:phone":"+49 611/421961",
    "sg:postcode":"65201",
    "sg:province":"Hessen",
    "wof:name":"Katholisches Pfarramt St. Georg Und Kathar.",
    "wof:placetype":"venue"
},
  "geometry": {"coordinates":[8.153263092,50.0651283264],"type":"Point"}
}