{
  "type": "Feature",
  "properties": {
    "iso:country":"DE",
    "sg:address":"Hauptstr. 99",
    "sg:city":"Ehingen",
    "sg:phone":"+49 7391/70410",
    "sg:postcode":"89584",
    "sg:province":"Baden-W\u00fcrttemberg",
    "wof:name":"Paul G\u00f6tz",
    "wof:placetype":"venue"
},
  "geometry": {"coordinates":[9.7240476608,48.2831344604],"type":"Point"}
}