{
  "type": "Feature",
  "properties": {
    "iso:country":"DE",
    "sg:address":"Rheinstr. 470",
    "sg:city":"Kalkar",
    "sg:phone":"+49 2824/2215",
    "sg:postcode":"47546",
    "sg:province":"Nordrhein-Westfalen",
    "wof:name":"Angenendt",
    "wof:placetype":"venue"
},
  "geometry": {"coordinates":[6.3642549515,51.74792099],"type":"Point"}
}