{
  "type": "Feature",
  "properties": {
    "iso:country":"DE",
    "sg:address":"Friesenstr. 46",
    "sg:city":"Delmenhorst",
    "sg:phone":"+49 4221/54078",
    "sg:postcode":"27751",
    "sg:province":"Niedersachsen",
    "wof:name":"Visurgis Gmbh",
    "wof:placetype":"venue"
},
  "geometry": {"coordinates":[8.6390714645,53.0607833862],"type":"Point"}
}