{
  "type": "Feature",
  "properties": {
    "iso:country":"DE",
    "sg:address":"Flurstr. 10",
    "sg:city":"Schwabach",
    "sg:phone":"+49 9122/77464",
    "sg:postcode":"91126",
    "sg:province":"Bayern",
    "wof:name":"Bernhard Schmeiss",
    "wof:placetype":"venue"
},
  "geometry": {"coordinates":[11.04522,49.33762],"type":"Point"}
}