{
  "type": "Feature",
  "properties": {
    "iso:country":"DE",
    "sg:address":"K\u00e4seicher Weg",
    "sg:city":"Idar-Oberstein",
    "sg:postcode":"55743",
    "sg:province":"Rheinland-Pfalz",
    "wof:name":"Autohaus Nahetal Immobilien-verwaltungs-",
    "wof:placetype":"venue"
},
  "geometry": {"coordinates":[7.4079780579,49.7334365845],"type":"Point"}
}