{
  "type": "Feature",
  "properties": {
    "iso:country":"DE",
    "sg:address":"Fontaneweg 1",
    "sg:city":"Alt Ruppin",
    "sg:phone":"+49 3391/7376",
    "sg:postcode":"16827",
    "sg:province":"Brandenburg",
    "wof:name":"Peter Heyse",
    "wof:placetype":"venue"
},
  "geometry": {"coordinates":[12.845973,52.952339],"type":"Point"}
}