{
  "type": "Feature",
  "properties": {
    "iso:country":"DE",
    "sg:address":"Neumarkter Str. 87",
    "sg:city":"M\u00fcnchen",
    "sg:phone":"+49 89/4319810",
    "sg:postcode":"81673",
    "sg:province":"Bayern",
    "wof:name":"Visual Analysis Ag",
    "wof:placetype":"venue"
},
  "geometry": {"coordinates":[11.628792,48.131226],"type":"Point"}
}