{
  "type": "Feature",
  "properties": {
    "iso:country":"DE",
    "sg:address":"Hauptstr. 31",
    "sg:city":"H\u00f6chberg",
    "sg:postcode":"97204",
    "sg:province":"Bayern",
    "wof:name":"M. Riess & H. Karl",
    "wof:placetype":"venue"
},
  "geometry": {"coordinates":[9.880607605,49.7838935852],"type":"Point"}
}