{
  "type": "Feature",
  "properties": {
    "iso:country":"DE",
    "sg:address":"Am J\u00e4gerpark 8",
    "sg:city":"Dresden",
    "sg:phone":"+49 351/8041856",
    "sg:postcode":"01099",
    "sg:province":"Sachsen",
    "wof:name":"Kinderladen Sandm\u00e4nnchen E. V.",
    "wof:placetype":"venue"
},
  "geometry": {"coordinates":[13.7843017578,51.0715408325],"type":"Point"}
}