{
  "type": "Feature",
  "properties": {
    "iso:country":"DE",
    "sg:address":"Rh\u00f6nstr. 23",
    "sg:city":"Ebersburg",
    "sg:postcode":"36157",
    "sg:province":"Hessen",
    "wof:name":"Anneliese Sch\u00e4fer Verwaltungsgesellschaft Mbh",
    "wof:placetype":"venue"
},
  "geometry": {"coordinates":[9.8123083115,50.4846992493],"type":"Point"}
}