{
  "type": "Feature",
  "properties": {
    "iso:country":"DE",
    "sg:address":"Alstertalweg 1",
    "sg:city":"Wakendorf",
    "sg:phone":"+49 4945/356860",
    "sg:postcode":"24558",
    "sg:province":"Schleswig-Holstein",
    "wof:name":"Mfr-produkte Manfred F. R\u00d6ttger Gmbh",
    "wof:placetype":"venue"
},
  "geometry": {"coordinates":[10.0828962326,53.7821502686],"type":"Point"}
}