{
  "type": "Feature",
  "properties": {
    "iso:country":"DE",
    "sg:address":"Jemgumkloster 5",
    "sg:city":"Jemgum",
    "sg:phone":"+49 4958/1332",
    "sg:postcode":"26844",
    "sg:province":"Niedersachsen",
    "wof:name":"Peter Janssen Gmbh",
    "wof:placetype":"venue"
},
  "geometry": {"coordinates":[7.389513,53.248043],"type":"Point"}
}