{
  "type": "Feature",
  "properties": {
    "iso:country":"DE",
    "sg:address":"Peronner Str. 35",
    "sg:city":"Altena",
    "sg:phone":"+49 2352/73300",
    "sg:postcode":"58762",
    "sg:province":"Nordrhein-Westfalen",
    "wof:name":"M. Brinkmann",
    "wof:placetype":"venue"
},
  "geometry": {"coordinates":[7.716485,51.296162],"type":"Point"}
}