{
  "type": "Feature",
  "properties": {
    "iso:country":"DE",
    "sg:address":"Hohenloher Weg 16",
    "sg:city":"Paderborn",
    "sg:phone":"+49 5251/141910",
    "sg:postcode":"33102",
    "sg:province":"Nordrhein-Westfalen",
    "wof:name":"Becker Systembau Gmbh",
    "wof:placetype":"venue"
},
  "geometry": {"coordinates":[8.759938,51.747574],"type":"Point"}
}