{
  "type": "Feature",
  "properties": {
    "iso:country":"DE",
    "sg:address":"Flutweg 125",
    "sg:city":"Duisburg",
    "sg:phone":"+49 2065/77936",
    "sg:postcode":"47228",
    "sg:province":"Nordrhein-Westfalen",
    "wof:name":"Lebensmitteleinzelhandel Hans Czaikowski Gmbh",
    "wof:placetype":"venue"
},
  "geometry": {"coordinates":[6.6927680969,51.4115142822],"type":"Point"}
}