{
  "type": "Feature",
  "properties": {
    "iso:country":"DE",
    "sg:address":"Wolbecker Str. 20",
    "sg:city":"M\u00fcnster",
    "sg:phone":"+49 251/64936",
    "sg:postcode":"48155",
    "sg:province":"Nordrhein-Westfalen",
    "wof:name":"Walter Rogee Inh. Sabine Schulte",
    "wof:placetype":"venue"
},
  "geometry": {"coordinates":[7.65712,51.954151],"type":"Point"}
}