{
  "type": "Feature",
  "properties": {
    "iso:country":"DE",
    "sg:address":"K\u00f6lnstr. 79",
    "sg:city":"D\u00fcren",
    "sg:phone":"+49 2421/292652",
    "sg:postcode":"52351",
    "sg:province":"Nordrhein-Westfalen",
    "wof:name":"F.-j. Haas - Haas Verwaltungs- Gesellschaft Mbh & Co. Kg",
    "wof:placetype":"venue"
},
  "geometry": {"coordinates":[6.4896998405,50.8042411804],"type":"Point"}
}