{
  "type": "Feature",
  "properties": {
    "iso:country":"DE",
    "sg:address":"Lerchenweg 7",
    "sg:city":"Rheinbach",
    "sg:phone":"+49 2226/912976",
    "sg:postcode":"53359",
    "sg:province":"Nordrhein-Westfalen",
    "wof:name":"Bnc Network Consulting Gmbh",
    "wof:placetype":"venue"
},
  "geometry": {"coordinates":[6.9162321091,50.6488113403],"type":"Point"}
}