{
  "type": "Feature",
  "properties": {
    "iso:country":"DE",
    "sg:address":"73087",
    "sg:city":"Boll",
    "sg:phone":"+49 7164/5294",
    "sg:postcode":"73087",
    "sg:province":"Baden-W\u00fcrttemberg",
    "wof:name":"Freibad",
    "wof:placetype":"venue"
},
  "geometry": {"coordinates":[9.605509758,48.6392784119],"type":"Point"}
}