{
  "type": "Feature",
  "properties": {
    "iso:country":"DE",
    "sg:address":"Industriestr. 85",
    "sg:city":"Horb",
    "sg:phone":"+49 7451/55100",
    "sg:postcode":"72160",
    "sg:province":"Baden-W\u00fcrttemberg",
    "wof:name":"Vbc Datentechnik Gmbh",
    "wof:placetype":"venue"
},
  "geometry": {"coordinates":[8.6626968384,48.4652557373],"type":"Point"}
}