{
  "type": "Feature",
  "properties": {
    "iso:country":"DE",
    "sg:address":"Hauptstr. 50",
    "sg:city":"\u00dcberherrn",
    "sg:phone":"+49 6836/4086",
    "sg:postcode":"66802",
    "sg:province":"Saarland",
    "wof:name":"Eiscafe Europa",
    "wof:placetype":"venue"
},
  "geometry": {"coordinates":[6.697851181,49.2453575134],"type":"Point"}
}