{
  "type": "Feature",
  "properties": {
    "iso:country":"DE",
    "sg:address":"Hainsbachweg 2",
    "sg:city":"Heidelberg",
    "sg:phone":"+49 6221/413322",
    "sg:postcode":"69120",
    "sg:province":"Baden-W\u00fcrttemberg",
    "wof:name":"Alfons Nowak Immobilienmakler",
    "wof:placetype":"venue"
},
  "geometry": {"coordinates":[8.6900119781,49.4224700928],"type":"Point"}
}