{
  "type": "Feature",
  "properties": {
    "iso:country":"DE",
    "sg:address":"Humperdinckstr.",
    "sg:city":"Boppard",
    "sg:postcode":"56154",
    "sg:province":"Rheinland-Pfalz",
    "wof:name":"Sachverst\u00e4ndigenb\u00fcro Henzler Gmbh",
    "wof:placetype":"venue"
},
  "geometry": {"coordinates":[7.5863008499,50.2302093506],"type":"Point"}
}