{
  "type": "Feature",
  "properties": {
    "iso:country":"DE",
    "sg:address":"Am Steinberg 17",
    "sg:city":"Coburg",
    "sg:phone":"+49 9561/31143",
    "sg:postcode":"96450",
    "sg:province":"Bayern",
    "wof:name":"Norbert Misar",
    "wof:placetype":"venue"
},
  "geometry": {"coordinates":[10.934423,50.255161],"type":"Point"}
}