{
  "type": "Feature",
  "properties": {
    "iso:country":"DE",
    "sg:address":"Hoffmannallee 41-51",
    "sg:city":"Kleve",
    "sg:phone":"+49 2821/860",
    "sg:postcode":"47533",
    "sg:province":"Nordrhein-Westfalen",
    "wof:name":"Elefanten Gmbh",
    "wof:placetype":"venue"
},
  "geometry": {"coordinates":[6.127829,51.780197],"type":"Point"}
}