{
  "type": "Feature",
  "properties": {
    "iso:country":"DE",
    "sg:address":"Wilder-Mann-Str. 15",
    "sg:city":"Dresden",
    "sg:phone":"+49 351/8496415",
    "sg:postcode":"01129",
    "sg:province":"Sachsen",
    "wof:name":"Dresden-vermietung",
    "wof:placetype":"venue"
},
  "geometry": {"coordinates":[13.715407,51.088985],"type":"Point"}
}