{
  "type": "Feature",
  "properties": {
    "iso:country":"DE",
    "sg:address":"Bahnhofstra\u00dfe 35 b",
    "sg:city":"Sankt Augustin",
    "sg:phone":"+49 2241/314525",
    "sg:postcode":"53757",
    "sg:province":"Nordrhein-Westfalen",
    "wof:name":"Faf Ton & Lichtanlagen Verleih",
    "wof:placetype":"venue"
},
  "geometry": {"coordinates":[7.142578,50.778057],"type":"Point"}
}