{
  "type": "Feature",
  "properties": {
    "iso:country":"DE",
    "sg:address":"Raiffeisenstr. 41",
    "sg:city":"Olpe",
    "sg:postcode":"57462",
    "sg:province":"Nordrhein-Westfalen",
    "wof:name":"Kettner Rohstoff Handels Gmbh",
    "wof:placetype":"venue"
},
  "geometry": {"coordinates":[7.8389601707,50.9979133606],"type":"Point"}
}