{
  "type": "Feature",
  "properties": {
    "iso:country":"DE",
    "sg:address":"Rathausplatz 22",
    "sg:city":"Adendorf",
    "sg:phone":"+49 4131/180099",
    "sg:postcode":"21365",
    "sg:province":"Niedersachsen",
    "wof:name":"B. Rech",
    "wof:placetype":"venue"
},
  "geometry": {"coordinates":[10.4392681122,53.2823143005],"type":"Point"}
}