{
  "type": "Feature",
  "properties": {
    "iso:country":"DE",
    "sg:address":"Angelh\u00e4user Str. 11",
    "sg:city":"Arnstadt",
    "sg:phone":"+49 3628/46753",
    "sg:postcode":"99310",
    "sg:province":"Th\u00fcringen",
    "wof:name":"Michael Mei\u00dfner",
    "wof:placetype":"venue"
},
  "geometry": {"coordinates":[10.9630098343,50.8292922974],"type":"Point"}
}