{
  "type": "Feature",
  "properties": {
    "iso:country":"DE",
    "sg:address":"Hauptstr. 83",
    "sg:city":"Witten",
    "sg:phone":"+49 2302/52286",
    "sg:postcode":"58452",
    "sg:province":"Nordrhein-Westfalen",
    "wof:name":"Katholisches Pfarramt St. Marien",
    "wof:placetype":"venue"
},
  "geometry": {"coordinates":[7.336204052,51.4447059631],"type":"Point"}
}