{
  "type": "Feature",
  "properties": {
    "iso:country":"DE",
    "sg:address":"Haubachweg 6",
    "sg:city":"Darmstadt",
    "sg:postcode":"64285",
    "sg:province":"Hessen",
    "wof:name":"Immosolar Deutschland Gmbh",
    "wof:placetype":"venue"
},
  "geometry": {"coordinates":[8.6629734039,49.8588256836],"type":"Point"}
}