{
  "type": "Feature",
  "properties": {
    "iso:country":"DE",
    "sg:address":"Tiefe Str. 8",
    "sg:city":"Halle",
    "sg:phone":"+49 345/7798320",
    "sg:postcode":"06132",
    "sg:province":"Sachsen-Anhalt",
    "wof:name":"Mr. Drink Gastronomie- Und Personalversorgung Gmbh",
    "wof:placetype":"venue"
},
  "geometry": {"coordinates":[11.98719,51.424751],"type":"Point"}
}