{
  "type": "Feature",
  "properties": {
    "iso:country":"DE",
    "sg:address":"Untereickener Str 26",
    "sg:city":"M\u00f6nchengladbach",
    "sg:phone":"+49 2161/241720",
    "sg:postcode":"41063",
    "sg:province":"Nordrhein-Westfalen",
    "wof:name":"Textilveredlung Simons & Gier Gmbh & Co Kg",
    "wof:placetype":"venue"
},
  "geometry": {"coordinates":[6.4506759644,51.2129249573],"type":"Point"}
}