{
  "type": "Feature",
  "properties": {
    "iso:country":"DE",
    "sg:address":"Mindener Str. 60",
    "sg:city":"Herford",
    "sg:phone":"+49 5221/75517",
    "sg:postcode":"32049",
    "sg:province":"Nordrhein-Westfalen",
    "wof:name":"Margret Br\u00fcnger",
    "wof:placetype":"venue"
},
  "geometry": {"coordinates":[8.682442,52.123363],"type":"Point"}
}