{
  "type": "Feature",
  "properties": {
    "iso:country":"DE",
    "sg:address":"Pfalzstr. 2",
    "sg:city":"Marxheim",
    "sg:phone":"+49 821/7488847",
    "sg:postcode":"86688",
    "sg:province":"Bayern",
    "wof:name":"Ahorn Gmbh Wirtschaftsberatung",
    "wof:placetype":"venue"
},
  "geometry": {"coordinates":[10.945682,48.742638],"type":"Point"}
}