{
  "type": "Feature",
  "properties": {
    "iso:country":"DE",
    "sg:address":"Nagolder Str. 15",
    "sg:city":"Herrenberg",
    "sg:phone":"+49 7032/180",
    "sg:postcode":"71083",
    "sg:province":"Baden-W\u00fcrttemberg",
    "wof:name":"Wlz-raiffeisen Ag",
    "wof:placetype":"venue"
},
  "geometry": {"coordinates":[8.8640804291,48.5954933167],"type":"Point"}
}