{
  "type": "Feature",
  "properties": {
    "iso:country":"DE",
    "sg:address":"Hammer Str. 14",
    "sg:city":"M\u00fcnster",
    "sg:phone":"+49 251/524240",
    "sg:postcode":"48153",
    "sg:province":"Nordrhein-Westfalen",
    "wof:name":"Blumenhaus Rech Inh. Annette Und Ulrich Herder",
    "wof:placetype":"venue"
},
  "geometry": {"coordinates":[7.625796,51.954144],"type":"Point"}
}