{
  "type": "Feature",
  "properties": {
    "iso:country":"DE",
    "sg:address":"Oberstr. 4",
    "sg:city":"Witten",
    "sg:phone":"+49 2302/12083",
    "sg:postcode":"58452",
    "sg:province":"Nordrhein-Westfalen",
    "wof:name":"Pfalz Ohg",
    "wof:placetype":"venue"
},
  "geometry": {"coordinates":[7.3379068375,51.4384841919],"type":"Point"}
}