{
  "type": "Feature",
  "properties": {
    "iso:country":"DE",
    "sg:address":"Lilienthalstr. 51",
    "sg:city":"Stade",
    "sg:phone":"+49 4141/68114",
    "sg:postcode":"21680",
    "sg:province":"Niedersachsen",
    "wof:name":"Hans-j\u00fcrgen Quell Architekt",
    "wof:placetype":"venue"
},
  "geometry": {"coordinates":[9.487211,53.583336],"type":"Point"}
}