{
  "type": "Feature",
  "properties": {
    "iso:country":"DE",
    "sg:address":"Augsburger Str. 21",
    "sg:city":"Berlin",
    "sg:postcode":"10789",
    "sg:province":"Berlin",
    "wof:name":"Embassy Real Estate Consultancy And Services Gmbh",
    "wof:placetype":"venue"
},
  "geometry": {"coordinates":[13.3360366821,52.5010566711],"type":"Point"}
}