{
  "type": "Feature",
  "properties": {
    "iso:country":"DE",
    "sg:address":"Berliner Str. 4",
    "sg:city":"Bad K\u00f6nig",
    "sg:phone":"+49 6063/50060",
    "sg:postcode":"64732",
    "sg:province":"Hessen",
    "wof:name":"Wilhelm A. Klinger",
    "wof:placetype":"venue"
},
  "geometry": {"coordinates":[9.0036420822,49.7494850159],"type":"Point"}
}