{
  "type": "Feature",
  "properties": {
    "iso:country":"DE",
    "sg:address":"Schorndorfer Str. 47",
    "sg:city":"Esslingen",
    "sg:phone":"+49 711/312516",
    "sg:postcode":"73730",
    "sg:province":"Baden-W\u00fcrttemberg",
    "wof:name":"Heinz Mangold",
    "wof:placetype":"venue"
},
  "geometry": {"coordinates":[9.3353071213,48.7316398621],"type":"Point"}
}