{
  "type": "Feature",
  "properties": {
    "iso:country":"DE",
    "sg:address":"Hochstr. 21",
    "sg:city":"Wipperf\u00fcrth",
    "sg:phone":"+49 2267/1212",
    "sg:postcode":"51688",
    "sg:province":"Nordrhein-Westfalen",
    "wof:name":"Verein Zur F\u00f6rderung Der Wirtschaftlichen Entwicklung",
    "wof:placetype":"venue"
},
  "geometry": {"coordinates":[7.3956971169,51.116268158],"type":"Point"}
}