{
  "type": "Feature",
  "properties": {
    "iso:country":"DE",
    "sg:address":"Zerbster Str. 14",
    "sg:city":"Burg",
    "sg:phone":"+49 3921/2331",
    "sg:postcode":"39288",
    "sg:province":"Sachsen-Anhalt",
    "wof:name":"Stadt- Und Kreisbibliothek",
    "wof:placetype":"venue"
},
  "geometry": {"coordinates":[11.862261,52.264889],"type":"Point"}
}