{
  "type": "Feature",
  "properties": {
    "iso:country":"DE",
    "sg:address":"Sch\u00f6nlinder Weg 35",
    "sg:city":"Wei\u00dfenstadt",
    "sg:phone":"+49 9253/347",
    "sg:postcode":"95163",
    "sg:province":"Bayern",
    "wof:name":"Schmidt Stra\u00dfenbau Gmbh",
    "wof:placetype":"venue"
},
  "geometry": {"coordinates":[11.8772802353,50.0942192078],"type":"Point"}
}