{
  "type": "Feature",
  "properties": {
    "iso:country":"DE",
    "sg:address":"Berliner Freiheit 3 b",
    "sg:city":"Bremen",
    "sg:phone":"+49 421/436320",
    "sg:postcode":"28327",
    "sg:province":"Bremen",
    "wof:name":"Dr. Med. Stefan Gregori Arzt F\u00fcr Allgemeinmedizin",
    "wof:placetype":"venue"
},
  "geometry": {"coordinates":[8.8926773071,53.0810928345],"type":"Point"}
}