{
  "type": "Feature",
  "properties": {
    "iso:country":"DE",
    "sg:address":"Wallenstr. 57",
    "sg:city":"Schw\u00e4bisch Gm\u00fcnd",
    "sg:phone":"+49 7171/44591",
    "sg:postcode":"73529",
    "sg:province":"Baden-W\u00fcrttemberg",
    "wof:name":"Hubert Herkommer Architekt",
    "wof:placetype":"venue"
},
  "geometry": {"coordinates":[9.798732,48.777199],"type":"Point"}
}