{
  "type": "Feature",
  "properties": {
    "iso:country":"DE",
    "sg:address":"Parkstr. 1",
    "sg:city":"Netzschkau",
    "sg:phone":"+49 3765/34818",
    "sg:postcode":"08491",
    "sg:province":"Sachsen",
    "wof:name":"Agathe Alfarth",
    "wof:placetype":"venue"
},
  "geometry": {"coordinates":[12.2496957779,50.613483429],"type":"Point"}
}