{
  "type": "Feature",
  "properties": {
    "iso:country":"DE",
    "sg:address":"Hauptstr 123::",
    "sg:city":"Herxheim",
    "sg:phone":"+49 7276/929290",
    "sg:postcode":"76863",
    "sg:province":"Rheinland-Pfalz",
    "wof:name":"Raiffeisenbank Hayna Eg",
    "wof:placetype":"venue"
},
  "geometry": {"coordinates":[8.24835,49.15123],"type":"Point"}
}