{
  "type": "Feature",
  "properties": {
    "iso:country":"DE",
    "sg:address":"Burbacher Str. 229",
    "sg:city":"Bonn",
    "sg:phone":"+49 228/232659",
    "sg:postcode":"53129",
    "sg:province":"Nordrhein-Westfalen",
    "wof:name":"Michael Sch\u00fcller Inh. Heiner Sch\u00fcller",
    "wof:placetype":"venue"
},
  "geometry": {"coordinates":[7.110427,50.711475],"type":"Point"}
}