{
  "type": "Feature",
  "properties": {
    "iso:country":"DE",
    "sg:address":"D\u00fcrener Str. 44",
    "sg:city":"Geilenkirchen",
    "sg:phone":"+49 2451/2920",
    "sg:postcode":"52511",
    "sg:province":"Nordrhein-Westfalen",
    "wof:name":"R. Mutsaers",
    "wof:placetype":"venue"
},
  "geometry": {"coordinates":[6.1689882278,50.9517707825],"type":"Point"}
}