{
  "type": "Feature",
  "properties": {
    "iso:country":"DE",
    "sg:address":"Friedrich-Naumann-Str. 23",
    "sg:city":"Marburg",
    "sg:phone":"+49 6421/22798",
    "sg:postcode":"35037",
    "sg:province":"Hessen",
    "wof:name":"Dr. Ingo Texdorf Tierarzt",
    "wof:placetype":"venue"
},
  "geometry": {"coordinates":[8.7606248856,50.8012237549],"type":"Point"}
}