{
  "type": "Feature",
  "properties": {
    "iso:country":"DE",
    "sg:address":"Forster Str. 44",
    "sg:city":"Guben",
    "sg:phone":"+49 3561/66404",
    "sg:postcode":"03172",
    "sg:province":"Brandenburg",
    "wof:name":"Sb-f\u00f6rdertechnik Gmbh",
    "wof:placetype":"venue"
},
  "geometry": {"coordinates":[14.700776,51.932751],"type":"Point"}
}