{
  "type": "Feature",
  "properties": {
    "iso:country":"DE",
    "sg:address":"Gro\u00dfe Diesdorfer Str. 5",
    "sg:city":"Magdeburg",
    "sg:phone":"+49 391/7331507",
    "sg:postcode":"39108",
    "sg:province":"Sachsen-Anhalt",
    "wof:name":"A. Stiele Anlageberater",
    "wof:placetype":"venue"
},
  "geometry": {"coordinates":[11.6190252304,52.1306190491],"type":"Point"}
}