{
  "type": "Feature",
  "properties": {
    "iso:country":"DE",
    "sg:address":"Schlehenweg 3",
    "sg:city":"Kaarst",
    "sg:postcode":"41564",
    "sg:province":"Nordrhein-Westfalen",
    "wof:name":"Galina Handelsagentur Gmbh",
    "wof:placetype":"venue"
},
  "geometry": {"coordinates":[6.623281002,51.2150497437],"type":"Point"}
}