{
  "type": "Feature",
  "properties": {
    "iso:country":"DE",
    "sg:address":"Kitzinger Str. 57",
    "sg:city":"Schwarzach",
    "sg:phone":"+49 9324/2229",
    "sg:postcode":"97359",
    "sg:province":"Bayern",
    "wof:name":"C. Stafflinger",
    "wof:placetype":"venue"
},
  "geometry": {"coordinates":[10.2171611786,49.7901573181],"type":"Point"}
}