{
  "type": "Feature",
  "properties": {
    "iso:country":"DE",
    "sg:address":"Boulognestr. 49",
    "sg:city":"Zweibr\u00fccken",
    "sg:phone":"+49 6332/76287",
    "sg:postcode":"66482",
    "sg:province":"Rheinland-Pfalz",
    "wof:name":"Elisabeth Kalsch",
    "wof:placetype":"venue"
},
  "geometry": {"coordinates":[7.3502750397,49.2599487305],"type":"Point"}
}