{
  "type": "Feature",
  "properties": {
    "iso:country":"DE",
    "sg:address":"Berolinastr. 7",
    "sg:city":"Berlin",
    "sg:phone":"+49 30/2424776",
    "sg:postcode":"10178",
    "sg:province":"Berlin",
    "wof:name":"City-apotheke",
    "wof:placetype":"venue"
},
  "geometry": {"coordinates":[13.424005,52.521717],"type":"Point"}
}