{
  "type": "Feature",
  "properties": {
    "iso:country":"DE",
    "sg:address":"Steeler Str. 56",
    "sg:city":"Oberhausen",
    "sg:phone":"+49 208/860292",
    "sg:postcode":"46047",
    "sg:province":"Nordrhein-Westfalen",
    "wof:name":"Hans G. Grunauer Und Hans Saxe Architekten",
    "wof:placetype":"venue"
},
  "geometry": {"coordinates":[6.893653,51.477951],"type":"Point"}
}