{
  "type": "Feature",
  "properties": {
    "iso:country":"DE",
    "sg:address":"Gro\u00df Borsteler Str. 33",
    "sg:city":"Hamburg",
    "sg:phone":"+49 40/5894473",
    "sg:postcode":"22453",
    "sg:province":"Hamburg",
    "wof:name":"Christian Matthiessen Rechtsanwalt",
    "wof:placetype":"venue"
},
  "geometry": {"coordinates":[9.9632368088,53.6101913452],"type":"Point"}
}