{
  "type": "Feature",
  "properties": {
    "iso:country":"DE",
    "sg:address":"Selliner Str. 11",
    "sg:city":"Leipzig",
    "sg:phone":"+49 341/4225028",
    "sg:postcode":"04207",
    "sg:province":"Sachsen",
    "wof:name":"K. P\u00f6tzsch",
    "wof:placetype":"venue"
},
  "geometry": {"coordinates":[12.2640190125,51.3140602112],"type":"Point"}
}