{
  "type": "Feature",
  "properties": {
    "iso:country":"DE",
    "sg:address":"Kottberg 10",
    "sg:city":"Bodenfelde",
    "sg:phone":"+49 5572/845",
    "sg:postcode":"37194",
    "sg:province":"Hessen",
    "wof:name":"Additan-touristik Gmbh Kfz Garantie",
    "wof:placetype":"venue"
},
  "geometry": {"coordinates":[9.558049202,51.6381072998],"type":"Point"}
}