{
  "type": "Feature",
  "properties": {
    "iso:country":"DE",
    "sg:address":"Humperdinckstr. 37",
    "sg:city":"Leverkusen",
    "sg:phone":"+49 214/502081",
    "sg:postcode":"51375",
    "sg:province":"Nordrhein-Westfalen",
    "wof:name":"D. Foest Ingenieur",
    "wof:placetype":"venue"
},
  "geometry": {"coordinates":[7.0492558479,51.0262985229],"type":"Point"}
}