{
  "type": "Feature",
  "properties": {
    "iso:country":"DE",
    "sg:address":"Zur Tannenburg 31",
    "sg:city":"Sulzbach",
    "sg:phone":"+49 6897/98120",
    "sg:postcode":"66280",
    "sg:province":"Saarland",
    "wof:name":"Wolfgang Preinfalk Gmbh",
    "wof:placetype":"venue"
},
  "geometry": {"coordinates":[7.0835351944,49.309387207],"type":"Point"}
}