{
  "type": "Feature",
  "properties": {
    "iso:country":"DE",
    "sg:address":"Am Scheibchen 16",
    "sg:city":"Nonnweiler",
    "sg:phone":"+49 6873/6156",
    "sg:postcode":"66620",
    "sg:province":"Saarland",
    "wof:name":"Armin Junker",
    "wof:placetype":"venue"
},
  "geometry": {"coordinates":[6.97,49.606369],"type":"Point"}
}