{
  "type": "Feature",
  "properties": {
    "iso:country":"DE",
    "sg:address":"Leerer Landstr. 57",
    "sg:city":"Gro\u00dfefehn",
    "sg:phone":"+49 4945/9909017",
    "sg:postcode":"26629",
    "sg:province":"Niedersachsen",
    "wof:name":"H. G. Onken",
    "wof:placetype":"venue"
},
  "geometry": {"coordinates":[7.52832,53.379501],"type":"Point"}
}