{
  "type": "Feature",
  "properties": {
    "iso:country":"DE",
    "sg:address":"Kr\u00e4henberg 47",
    "sg:city":"Celle",
    "sg:phone":"+49 5141/481014",
    "sg:postcode":"29225",
    "sg:province":"Niedersachsen",
    "wof:name":"Herbert Berger",
    "wof:placetype":"venue"
},
  "geometry": {"coordinates":[10.045688,52.603626],"type":"Point"}
}