{
  "type": "Feature",
  "properties": {
    "iso:country":"DE",
    "sg:address":"Schwieberdinger Str 44",
    "sg:city":"Ludwigsburg",
    "sg:phone":"+49 7141/44540",
    "sg:postcode":"71636",
    "sg:province":"Baden-W\u00fcrttemberg",
    "wof:name":"Gesellschaft F\u00fcr Elektrische Anlagen Leitungsbau S\u00fcd Gmbh",
    "wof:placetype":"venue"
},
  "geometry": {"coordinates":[9.177432,48.89056],"type":"Point"}
}