{
  "type": "Feature",
  "properties": {
    "iso:country":"DE",
    "sg:address":"M\u00fchlstr 58",
    "sg:city":"Sch\u00f6mberg",
    "sg:phone":"+49 7235/97090",
    "sg:postcode":"75328",
    "sg:province":"Baden-W\u00fcrttemberg",
    "wof:name":"Haessler Information Gmbh",
    "wof:placetype":"venue"
},
  "geometry": {"coordinates":[8.709162,48.80537],"type":"Point"}
}