{
  "type": "Feature",
  "properties": {
    "iso:country":"DE",
    "sg:address":"Siemensstr. 43",
    "sg:city":"Velbert",
    "sg:phone":"+49 2051/289490",
    "sg:postcode":"42551",
    "sg:province":"Nordrhein-Westfalen",
    "wof:name":"Sk Metallguss Gmbh",
    "wof:placetype":"venue"
},
  "geometry": {"coordinates":[7.079756,51.351067],"type":"Point"}
}