{
  "type": "Feature",
  "properties": {
    "iso:country":"DE",
    "sg:address":"Lilienstr. 32",
    "sg:city":"Weil der Stadt",
    "sg:phone":"+49 7033/32141",
    "sg:postcode":"71263",
    "sg:province":"Baden-W\u00fcrttemberg",
    "wof:name":"Gebhard Lindm\u00fcller",
    "wof:placetype":"venue"
},
  "geometry": {"coordinates":[8.851898,48.763466],"type":"Point"}
}