{
  "type": "Feature",
  "properties": {
    "iso:country":"DE",
    "sg:address":"Berliner Str. 76",
    "sg:city":"M\u00fcnchen",
    "sg:phone":"+49 89/36108707",
    "sg:postcode":"80805",
    "sg:province":"Bayern",
    "wof:name":"Stephan Schneller Rechtsanwalt",
    "wof:placetype":"venue"
},
  "geometry": {"coordinates":[11.5907850266,48.1740951538],"type":"Point"}
}