{
  "type": "Feature",
  "properties": {
    "iso:country":"DE",
    "sg:address":"Zur Schule 1",
    "sg:city":"Minden",
    "sg:phone":"+49 571/43272",
    "sg:postcode":"32425",
    "sg:province":"Nordrhein-Westfalen",
    "wof:name":"Ewald Netzeband",
    "wof:placetype":"venue"
},
  "geometry": {"coordinates":[8.881149292,52.317237854],"type":"Point"}
}