{
  "type": "Feature",
  "properties": {
    "iso:country":"DE",
    "sg:address":"Eisenbahnstr. 17",
    "sg:city":"M\u00fcnster",
    "sg:phone":"+49 251/51722",
    "sg:postcode":"48143",
    "sg:province":"Nordrhein-Westfalen",
    "wof:name":"Restaurant Trattoria Salvatore",
    "wof:placetype":"venue"
},
  "geometry": {"coordinates":[7.6352329254,51.9618759155],"type":"Point"}
}