{
  "type": "Feature",
  "properties": {
    "iso:country":"DE",
    "sg:address":"Platzgasse 19",
    "sg:city":"Ulm",
    "sg:phone":"+49 731/63533",
    "sg:postcode":"89073",
    "sg:province":"Baden-W\u00fcrttemberg",
    "wof:name":"V. Freitag",
    "wof:placetype":"venue"
},
  "geometry": {"coordinates":[9.9909105301,48.400390625],"type":"Point"}
}