{
  "type": "Feature",
  "properties": {
    "iso:country":"DE",
    "sg:address":"Nordstr. 14",
    "sg:city":"D\u00fcren",
    "sg:phone":"+49 2421/86283",
    "sg:postcode":"52353",
    "sg:province":"Nordrhein-Westfalen",
    "wof:name":"Helga Starkens",
    "wof:placetype":"venue"
},
  "geometry": {"coordinates":[6.45697,50.830441],"type":"Point"}
}