{
  "type": "Feature",
  "properties": {
    "iso:country":"DE",
    "sg:address":"Brunnenstr. 10",
    "sg:city":"Retterath",
    "sg:phone":"+49 2657/1533",
    "sg:postcode":"56769",
    "sg:province":"Rheinland-Pfalz",
    "wof:name":"Paul Simon",
    "wof:placetype":"venue"
},
  "geometry": {"coordinates":[7.012284,50.273205],"type":"Point"}
}