{
  "type": "Feature",
  "properties": {
    "iso:country":"DE",
    "sg:address":"Papenmoorweg 7 a",
    "sg:city":"Halstenbek",
    "sg:phone":"+49 4101/48564",
    "sg:postcode":"25469",
    "sg:province":"Schleswig-Holstein",
    "wof:name":"F. Und H. Schumacher Ingenieure",
    "wof:placetype":"venue"
},
  "geometry": {"coordinates":[9.8704004288,53.6206321716],"type":"Point"}
}