{
  "type": "Feature",
  "properties": {
    "iso:country":"DE",
    "sg:address":"Marktstr. 2",
    "sg:city":"Tann",
    "sg:phone":"+49 6682/272",
    "sg:postcode":"36142",
    "sg:province":"Hessen",
    "wof:name":"G. T\u00f6lle",
    "wof:placetype":"venue"
},
  "geometry": {"coordinates":[12.8917617798,48.3160972595],"type":"Point"}
}