{
  "type": "Feature",
  "properties": {
    "iso:country":"DE",
    "sg:address":"Klaf 18",
    "sg:city":"Utersum",
    "sg:postcode":"25938",
    "sg:province":"Schleswig-Holstein",
    "wof:name":"Pme Projekt Management Eschbach Gmbh",
    "wof:placetype":"venue"
},
  "geometry": {"coordinates":[8.398007,54.711056],"type":"Point"}
}