{
  "type": "Feature",
  "properties": {
    "iso:country":"DE",
    "sg:address":"Greiters",
    "sg:city":"Wiggensbach",
    "sg:phone":"+49 8370/331",
    "sg:postcode":"87487",
    "sg:province":"Bayern",
    "wof:name":"Alfa-laval Agrar Gmbh",
    "wof:placetype":"venue"
},
  "geometry": {"coordinates":[10.204168,47.757973],"type":"Point"}
}