{
  "type": "Feature",
  "properties": {
    "iso:country":"DE",
    "sg:address":"Christoph-L\u00fcders-Str. 24",
    "sg:city":"G\u00f6rlitz",
    "sg:postcode":"02826",
    "sg:province":"Sachsen",
    "wof:name":"Bombardier Transportation Dwa Deutsche Waggonbau Gmbh",
    "wof:placetype":"venue"
},
  "geometry": {"coordinates":[14.9690313339,51.1555023193],"type":"Point"}
}