{
  "type": "Feature",
  "properties": {
    "iso:country":"DE",
    "sg:address":"Buntzelstr. 15",
    "sg:city":"Berlin",
    "sg:postcode":"12526",
    "sg:province":"Berlin",
    "wof:name":"Dr. Med. Ilse Sperling",
    "wof:placetype":"venue"
},
  "geometry": {"coordinates":[13.573541,52.409245],"type":"Point"}
}