{
  "type": "Feature",
  "properties": {
    "iso:country":"DE",
    "sg:address":"K\u00e4rntener Str. 4",
    "sg:city":"Berlin",
    "sg:phone":"+49 30/2168215",
    "sg:postcode":"10827",
    "sg:province":"Berlin",
    "wof:name":"Didier Dupuis \u00dcbersetzer",
    "wof:placetype":"venue"
},
  "geometry": {"coordinates":[13.347192,52.479939],"type":"Point"}
}