{
  "type": "Feature",
  "properties": {
    "iso:country":"DE",
    "sg:address":"Marienplatz 2",
    "sg:city":"Wolnzach",
    "sg:phone":"+49 8442/3672",
    "sg:postcode":"85283",
    "sg:province":"Bayern",
    "wof:name":"J. Tietze",
    "wof:placetype":"venue"
},
  "geometry": {"coordinates":[11.6265449524,48.6035766602],"type":"Point"}
}