{
  "type": "Feature",
  "properties": {
    "iso:country":"DE",
    "sg:address":"Boller Str. 21",
    "sg:city":"G\u00f6ppingen",
    "sg:phone":"+49 7161/41558",
    "sg:postcode":"73035",
    "sg:province":"Baden-W\u00fcrttemberg",
    "wof:name":"Waldhorn",
    "wof:placetype":"venue"
},
  "geometry": {"coordinates":[9.6284866333,48.6866874695],"type":"Point"}
}