{
  "type": "Feature",
  "properties": {
    "iso:country":"DE",
    "sg:address":"Am Sandberg 4",
    "sg:city":"Langerwehe",
    "sg:phone":"+49 4977/417075",
    "sg:postcode":"52379",
    "sg:province":"Nordrhein-Westfalen",
    "wof:name":"Karl Ernesti Gmbh",
    "wof:placetype":"venue"
},
  "geometry": {"coordinates":[8.214455,47.623707],"type":"Point"}
}