{
  "type": "Feature",
  "properties": {
    "iso:country":"DE",
    "sg:address":"Adam-Krafft-Str. 8",
    "sg:city":"Weiden",
    "sg:phone":"+49 961/33861",
    "sg:postcode":"92637",
    "sg:province":"Bayern",
    "wof:name":"Gottfried Haupt",
    "wof:placetype":"venue"
},
  "geometry": {"coordinates":[12.1804895401,49.6716804504],"type":"Point"}
}