{
  "type": "Feature",
  "properties": {
    "iso:country":"DE",
    "sg:address":"Lindenstr. 35",
    "sg:city":"Kade",
    "sg:phone":"+49 39347/50003",
    "sg:postcode":"39307",
    "sg:province":"Sachsen-Anhalt",
    "wof:name":"Lothar Beck",
    "wof:placetype":"venue"
},
  "geometry": {"coordinates":[12.263093,52.380196],"type":"Point"}
}