{
  "type": "Feature",
  "properties": {
    "iso:country":"DE",
    "sg:address":"Am Steig 7",
    "sg:city":"Schondorf",
    "sg:phone":"+49 8192/447",
    "sg:postcode":"86938",
    "sg:province":"Bayern",
    "wof:name":"Hartmut Riechers Anlageberater",
    "wof:placetype":"venue"
},
  "geometry": {"coordinates":[11.0975389481,48.052406311],"type":"Point"}
}