{
  "type": "Feature",
  "properties": {
    "iso:country":"DE",
    "sg:address":"M\u00f6hringer Str. 18",
    "sg:city":"Stuttgart",
    "sg:phone":"+49 711/6406174",
    "sg:postcode":"70178",
    "sg:province":"Baden-W\u00fcrttemberg",
    "wof:name":"Petra Ziegler-neuner Dolmetscherin Und \u00dcbersetz.",
    "wof:placetype":"venue"
},
  "geometry": {"coordinates":[9.16396,48.763165],"type":"Point"}
}