{
  "type": "Feature",
  "properties": {
    "iso:country":"DE",
    "sg:address":"Birkenhof",
    "sg:city":"Biebertal",
    "sg:phone":"+49 6409/6588",
    "sg:postcode":"35444",
    "sg:province":"Hessen",
    "wof:name":"Karl Willersh\u00e4user",
    "wof:placetype":"venue"
},
  "geometry": {"coordinates":[8.610288,50.609936],"type":"Point"}
}