{
  "type": "Feature",
  "properties": {
    "iso:country":"DE",
    "sg:address":"Carl-Benz-Str. 4",
    "sg:city":"Schwetzingen",
    "sg:phone":"+49 6202/25902",
    "sg:postcode":"68723",
    "sg:province":"Baden-W\u00fcrttemberg",
    "wof:name":"Klaus Martin",
    "wof:placetype":"venue"
},
  "geometry": {"coordinates":[8.584127,49.377151],"type":"Point"}
}