{
  "type": "Feature",
  "properties": {
    "iso:country":"DE",
    "sg:address":"Winzerstr. 15",
    "sg:city":"Niederhausen",
    "sg:phone":"+49 6758/6701",
    "sg:postcode":"55585",
    "sg:province":"Rheinland-Pfalz",
    "wof:name":"Jakob Schneider",
    "wof:placetype":"venue"
},
  "geometry": {"coordinates":[7.7822189331,49.8028411865],"type":"Point"}
}