{
  "type": "Feature",
  "properties": {
    "iso:country":"DE",
    "sg:address":"Friedrich-Engels-Str 1",
    "sg:city":"Premnitz",
    "sg:phone":"+49 3386/243522",
    "sg:postcode":"14727",
    "sg:province":"Brandenburg",
    "wof:name":"Rhenus Ag & Co Kg",
    "wof:placetype":"venue"
},
  "geometry": {"coordinates":[12.345700264,52.5318908691],"type":"Point"}
}