{
  "type": "Feature",
  "properties": {
    "iso:country":"DE",
    "sg:address":"Lange Str. 77",
    "sg:city":"Bad Driburg",
    "sg:phone":"+49 5253/97670",
    "sg:postcode":"33014",
    "sg:province":"Nordrhein-Westfalen",
    "wof:name":"M\u00fcller Und Rohe Rechtsanw\u00e4lte Und Notare",
    "wof:placetype":"venue"
},
  "geometry": {"coordinates":[9.0181283951,51.7358512878],"type":"Point"}
}