{
  "type": "Feature",
  "properties": {
    "iso:country":"DE",
    "sg:address":"Wieckesweg 18",
    "sg:city":"Dortmund",
    "sg:phone":"+49 4923/120800",
    "sg:postcode":"44309",
    "sg:province":"Nordrhein-Westfalen",
    "wof:name":"Siebdruck Gmbh Bernd Koch",
    "wof:placetype":"venue"
},
  "geometry": {"coordinates":[7.5354938507,51.5213623047],"type":"Point"}
}