{
  "type": "Feature",
  "properties": {
    "iso:country":"DE",
    "sg:address":"Kleiner Spiegelberg 3",
    "sg:city":"Neustrelitz",
    "sg:phone":"+49 3981/444078",
    "sg:postcode":"17235",
    "sg:province":"Mecklenburg-Vorpommern",
    "wof:name":"Dr. Med. G\u00fcnter Ode",
    "wof:placetype":"venue"
},
  "geometry": {"coordinates":[13.08687,53.332008],"type":"Point"}
}