{
  "type": "Feature",
  "properties": {
    "iso:country":"DE",
    "sg:address":"Humboldtstr. 111",
    "sg:city":"N\u00fcrnberg",
    "sg:phone":"+49 911/5197273",
    "sg:postcode":"90459",
    "sg:province":"Bayern",
    "wof:name":"Rainer Edelmann",
    "wof:placetype":"venue"
},
  "geometry": {"coordinates":[11.084509,49.439732],"type":"Point"}
}