{
  "type": "Feature",
  "properties": {
    "iso:country":"DE",
    "sg:address":"Steglitzer Damm 68",
    "sg:city":"Berlin",
    "sg:phone":"+49 30/7962814",
    "sg:postcode":"12169",
    "sg:province":"Berlin",
    "wof:name":"Karl-heinz Koschitzki Optiker",
    "wof:placetype":"venue"
},
  "geometry": {"coordinates":[13.3479156494,52.4497299194],"type":"Point"}
}