{
  "type": "Feature",
  "properties": {
    "iso:country":"DE",
    "sg:address":"Ludwigsthaler Str. 9",
    "sg:city":"Neunkirchen",
    "sg:phone":"+49 6821/31859",
    "sg:postcode":"66539",
    "sg:province":"Saarland",
    "wof:name":"Furbach-apotheke",
    "wof:placetype":"venue"
},
  "geometry": {"coordinates":[7.218476,49.323505],"type":"Point"}
}