{
  "type": "Feature",
  "properties": {
    "iso:country":"DE",
    "sg:address":"Frauenstr. 3",
    "sg:city":"Zittau",
    "sg:phone":"+49 3583/512500",
    "sg:postcode":"02763",
    "sg:province":"Sachsen",
    "wof:name":"Taxi-genossenschaft Gmbh",
    "wof:placetype":"venue"
},
  "geometry": {"coordinates":[14.8087539673,50.8965072632],"type":"Point"}
}