{
  "type": "Feature",
  "properties": {
    "iso:country":"DE",
    "sg:address":"Rehwinkel 5",
    "sg:city":"Boppard",
    "sg:phone":"+49 6742/4538",
    "sg:postcode":"56154",
    "sg:province":"Rheinland-Pfalz",
    "wof:name":"Karamat Nassiri Masseur",
    "wof:placetype":"venue"
},
  "geometry": {"coordinates":[7.545402,50.212254],"type":"Point"}
}