{
  "type": "Feature",
  "properties": {
    "iso:country":"DE",
    "sg:address":"Zensweg 12",
    "sg:city":"K\u00f6nigswinter",
    "sg:phone":"+49 2244/5934",
    "sg:postcode":"53639",
    "sg:province":"Nordrhein-Westfalen",
    "wof:name":"Henseler Gmbh",
    "wof:placetype":"venue"
},
  "geometry": {"coordinates":[7.234893,50.698769],"type":"Point"}
}