{
  "type": "Feature",
  "properties": {
    "iso:country":"DE",
    "sg:address":"Waldsiedlung 3",
    "sg:city":"Halbe",
    "sg:phone":"+49 33765/80861",
    "sg:postcode":"15757",
    "sg:province":"Brandenburg",
    "wof:name":"K. Dra\u00dfdo",
    "wof:placetype":"venue"
},
  "geometry": {"coordinates":[13.691168,52.107922],"type":"Point"}
}