{
  "type": "Feature",
  "properties": {
    "iso:country":"DE",
    "sg:address":"H\u00f6kerkamp 3",
    "sg:city":"Hemdingen",
    "sg:postcode":"25485",
    "sg:province":"Schleswig-Holstein",
    "wof:name":"Holzstein Haus Gmbh",
    "wof:placetype":"venue"
},
  "geometry": {"coordinates":[9.8388347626,53.7617378235],"type":"Point"}
}