{
  "type": "Feature",
  "properties": {
    "iso:country":"DE",
    "sg:address":"Steinackersweg 11",
    "sg:city":"Syke",
    "sg:postcode":"28857",
    "sg:province":"Niedersachsen",
    "wof:name":"Gilde-wohnbau Und Beteiligungs Gmbh",
    "wof:placetype":"venue"
},
  "geometry": {"coordinates":[8.807642,52.912254],"type":"Point"}
}