{
  "type": "Feature",
  "properties": {
    "iso:country":"DE",
    "sg:address":"Promenadenweg 3",
    "sg:city":"Nesselwang",
    "sg:phone":"+49 8361/3117",
    "sg:postcode":"87484",
    "sg:province":"Bayern",
    "wof:name":"R. H\u00e4gele Heissmangel",
    "wof:placetype":"venue"
},
  "geometry": {"coordinates":[10.5022716522,47.6228294373],"type":"Point"}
}