{
  "type": "Feature",
  "properties": {
    "iso:country":"DE",
    "sg:address":"Badweg 6-2",
    "sg:city":"Weinstadt",
    "sg:phone":"+49 7151/64774",
    "sg:postcode":"71384",
    "sg:province":"Baden-W\u00fcrttemberg",
    "wof:name":"Karl Seeger",
    "wof:placetype":"venue"
},
  "geometry": {"coordinates":[9.3832349777,48.8197441101],"type":"Point"}
}