{
  "type": "Feature",
  "properties": {
    "iso:country":"DE",
    "sg:address":"Hohe Str. 53",
    "sg:city":"D\u00fclmen",
    "sg:phone":"+49 2594/2385",
    "sg:postcode":"48249",
    "sg:province":"Nordrhein-Westfalen",
    "wof:name":"Wilhelm Pr\u00f6be",
    "wof:placetype":"venue"
},
  "geometry": {"coordinates":[7.2879271507,51.8289756775],"type":"Point"}
}