{
  "type": "Feature",
  "properties": {
    "iso:country":"DE",
    "sg:address":"Gildehauser Str. 28",
    "sg:city":"Gronau",
    "sg:phone":"+49 2562/5349",
    "sg:postcode":"48599",
    "sg:province":"Nordrhein-Westfalen",
    "wof:name":"Jan Van Koetsveld",
    "wof:placetype":"venue"
},
  "geometry": {"coordinates":[7.030456,52.212296],"type":"Point"}
}