{
  "type": "Feature",
  "properties": {
    "iso:country":"DE",
    "sg:address":"9",
    "sg:city":"574",
    "sg:postcode":"9",
    "wof:name":"03ng",
    "wof:placetype":"venue"
},
  "geometry": {"coordinates":[-99.0110626221,19.3892002106],"type":"Point"}
}