{
  "type": "Feature",
  "properties": {
    "iso:country":"DE",
    "sg:address":"Oswald-Kahnt-Ring 17",
    "sg:city":"Leipzig",
    "sg:phone":"+49 341/4614863",
    "sg:postcode":"04158",
    "sg:province":"Sachsen",
    "wof:name":"Texxon Holding Gmbh",
    "wof:placetype":"venue"
},
  "geometry": {"coordinates":[12.333864,51.388672],"type":"Point"}
}