{
  "type": "Feature",
  "properties": {
    "iso:country":"DE",
    "sg:address":"Schevenstr. 13",
    "sg:city":"Gelsenkirchen",
    "sg:phone":"+49 209/201866",
    "sg:postcode":"45879",
    "sg:province":"Nordrhein-Westfalen",
    "wof:name":"H.-g. Schmitt Transporte Gmbh",
    "wof:placetype":"venue"
},
  "geometry": {"coordinates":[7.0922951698,51.5005950928],"type":"Point"}
}