{
  "type": "Feature",
  "properties": {
    "iso:country":"DE",
    "sg:address":"Heuweg 5",
    "sg:city":"Eschede",
    "sg:postcode":"29348",
    "sg:province":"Niedersachsen",
    "wof:name":"Mfh Gmbh M\u00fcdener Forst Und Holz",
    "wof:placetype":"venue"
},
  "geometry": {"coordinates":[10.1704063416,52.7384605408],"type":"Point"}
}