{
  "type": "Feature",
  "properties": {
    "iso:country":"DE",
    "sg:address":"Bachstr. 45",
    "sg:city":"Korschenbroich",
    "sg:postcode":"41352",
    "sg:province":"Nordrhein-Westfalen",
    "wof:name":"Sjb Investment-beratung Ohg",
    "wof:placetype":"venue"
},
  "geometry": {"coordinates":[6.5793161392,51.1644821167],"type":"Point"}
}