{
  "type": "Feature",
  "properties": {
    "iso:country":"DE",
    "sg:address":"Kaltehardtstr. 64",
    "sg:city":"Bochum",
    "sg:phone":"+49 234/28216",
    "sg:postcode":"44892",
    "sg:province":"Nordrhein-Westfalen",
    "wof:name":"Klaus-dieter Schmidt",
    "wof:placetype":"venue"
},
  "geometry": {"coordinates":[7.309117,51.467419],"type":"Point"}
}