{
  "type": "Feature",
  "properties": {
    "iso:country":"DE",
    "sg:address":"Schlenkenweg 50",
    "sg:city":"Werlte",
    "sg:phone":"+49 5956/1264",
    "sg:postcode":"49757",
    "sg:province":"Niedersachsen",
    "wof:name":"Werner St\u00fcrmeyer",
    "wof:placetype":"venue"
},
  "geometry": {"coordinates":[7.703989,52.886753],"type":"Point"}
}