{
  "type": "Feature",
  "properties": {
    "iso:country":"DE",
    "sg:address":"Eichenstr. 8",
    "sg:city":"Kaisersesch",
    "sg:phone":"+49 2653/3524",
    "sg:postcode":"56759",
    "sg:province":"Rheinland-Pfalz",
    "wof:name":"Annemarie Stein",
    "wof:placetype":"venue"
},
  "geometry": {"coordinates":[7.1336860657,50.2318611145],"type":"Point"}
}