{
  "type": "Feature",
  "properties": {
    "iso:country":"DE",
    "sg:address":"Hoherodskopfstr. 31",
    "sg:city":"Ulrichstein",
    "sg:phone":"+49 6645/318",
    "sg:postcode":"35327",
    "sg:province":"Hessen",
    "wof:name":"Georg Tamm Kg",
    "wof:placetype":"venue"
},
  "geometry": {"coordinates":[9.1344213486,50.580619812],"type":"Point"}
}