{
  "type": "Feature",
  "properties": {
    "iso:country":"DE",
    "sg:address":"Senkelteichstr. 1",
    "sg:city":"Vlotho",
    "sg:phone":"+49 5733/6166",
    "sg:postcode":"32602",
    "sg:province":"Nordrhein-Westfalen",
    "wof:name":"Cafe Meisenhaus",
    "wof:placetype":"venue"
},
  "geometry": {"coordinates":[8.863185,52.135681],"type":"Point"}
}