{
  "type": "Feature",
  "properties": {
    "iso:country":"DE",
    "sg:address":"Benzstr. 11",
    "sg:city":"\u00d6hringen",
    "sg:phone":"+49 7941/8265",
    "sg:postcode":"74613",
    "sg:province":"Baden-W\u00fcrttemberg",
    "wof:name":"Ev. Pfarramt Iv",
    "wof:placetype":"venue"
},
  "geometry": {"coordinates":[9.5097208023,49.1992454529],"type":"Point"}
}