{
  "type": "Feature",
  "properties": {
    "iso:country":"DE",
    "sg:address":"Aachener Str. 2",
    "sg:city":"K\u00f6ln",
    "sg:phone":"+49 221/251969",
    "sg:postcode":"50674",
    "sg:province":"Nordrhein-Westfalen",
    "wof:name":"Roxy",
    "wof:placetype":"venue"
},
  "geometry": {"coordinates":[6.9388651848,50.936466217],"type":"Point"}
}