{
  "type": "Feature",
  "properties": {
    "iso:country":"DE",
    "sg:address":"Hans-B\u00f6ckler-Str. 17",
    "sg:city":"Kirchheim",
    "sg:phone":"+49 7021/980600",
    "sg:postcode":"73230",
    "sg:province":"Baden-W\u00fcrttemberg",
    "wof:name":"Office-products Zeitler & Schneck Gmbh",
    "wof:placetype":"venue"
},
  "geometry": {"coordinates":[9.4752912521,48.6398544312],"type":"Point"}
}