{
  "type": "Feature",
  "properties": {
    "iso:country":"DE",
    "sg:address":"Kuckumer Str. 23",
    "sg:city":"Erkelenz",
    "sg:phone":"+49 2431/3640",
    "sg:postcode":"41812",
    "sg:province":"Nordrhein-Westfalen",
    "wof:name":"Gastst\u00e4tte H. U. U. Lanfermann",
    "wof:placetype":"venue"
},
  "geometry": {"coordinates":[6.3739519119,51.0895996094],"type":"Point"}
}