{
  "type": "Feature",
  "properties": {
    "iso:country":"DE",
    "sg:address":"Schwanenwall 46",
    "sg:city":"Dortmund",
    "sg:phone":"+49 231/572392",
    "sg:postcode":"44135",
    "sg:province":"Nordrhein-Westfalen",
    "wof:name":"Wolfgang K\u00f6hler",
    "wof:placetype":"venue"
},
  "geometry": {"coordinates":[7.4700708389,51.5163955688],"type":"Point"}
}