{
  "type": "Feature",
  "properties": {
    "iso:country":"DE",
    "sg:address":"Ingolst\u00e4dter Str. 31",
    "sg:city":"Manching",
    "sg:phone":"+49 8459/32910",
    "sg:postcode":"85077",
    "sg:province":"Bayern",
    "wof:name":"Hotel-restaurant Sandner",
    "wof:placetype":"venue"
},
  "geometry": {"coordinates":[11.4894685745,48.7168998718],"type":"Point"}
}