{
  "type": "Feature",
  "properties": {
    "iso:country":"DE",
    "sg:address":"Kegelbahnstr. 13",
    "sg:city":"Reipoltskirchen",
    "sg:postcode":"67753",
    "sg:province":"Rheinland-Pfalz",
    "wof:name":"Vkt Verpackung Und Kunststofftechnik Eisenberg",
    "wof:placetype":"venue"
},
  "geometry": {"coordinates":[7.6626448631,49.6347351074],"type":"Point"}
}