{
  "type": "Feature",
  "properties": {
    "iso:country":"DE",
    "sg:address":"Bachstr. 18",
    "sg:city":"Breitscheid",
    "sg:phone":"+49 2777/7239",
    "sg:postcode":"35767",
    "sg:province":"Hessen",
    "wof:name":"Bezirkssparkasse Dillenburg",
    "wof:placetype":"venue"
},
  "geometry": {"coordinates":[8.233747,50.699837],"type":"Point"}
}