{
  "type": "Feature",
  "properties": {
    "iso:country":"DE",
    "sg:address":"Bocholder Str. 276",
    "sg:city":"Essen",
    "sg:phone":"+49 201/668036",
    "sg:postcode":"45356",
    "sg:province":"Nordrhein-Westfalen",
    "wof:name":"Novelle Bautr\u00e4ger Gmbh",
    "wof:placetype":"venue"
},
  "geometry": {"coordinates":[6.972306,51.475044],"type":"Point"}
}