{
  "type": "Feature",
  "properties": {
    "iso:country":"DE",
    "sg:address":"Ritterweg 75",
    "sg:city":"Bendorf",
    "sg:phone":"+49 2622/4245",
    "sg:postcode":"56170",
    "sg:province":"Rheinland-Pfalz",
    "wof:name":"Hotel Zum Friedrichsberg",
    "wof:placetype":"venue"
},
  "geometry": {"coordinates":[7.5672187805,50.4423446655],"type":"Point"}
}