{
  "type": "Feature",
  "properties": {
    "iso:country":"DE",
    "sg:address":"Friedrich-Humbert-Str. 122",
    "sg:city":"Bremen",
    "sg:phone":"+49 421/623040",
    "sg:postcode":"28759",
    "sg:province":"Bremen",
    "wof:name":"K. Sonnenberg",
    "wof:placetype":"venue"
},
  "geometry": {"coordinates":[8.6367940903,53.1667327881],"type":"Point"}
}