{
  "type": "Feature",
  "properties": {
    "iso:country":"DE",
    "sg:address":"Schlo\u00df Zeil",
    "sg:city":"Leutkirch",
    "sg:phone":"+49 7561/2071",
    "sg:postcode":"88299",
    "sg:province":"Baden-W\u00fcrttemberg",
    "wof:name":"Archiv Des F\u00fcrsten Von Waldburg Zu Zeil",
    "wof:placetype":"venue"
},
  "geometry": {"coordinates":[9.995955,47.869495],"type":"Point"}
}