{
  "type": "Feature",
  "properties": {
    "iso:country":"DE",
    "sg:address":"Hauptstr. 18",
    "sg:city":"Baiersdorf",
    "sg:phone":"+49 9133/2330",
    "sg:postcode":"91083",
    "sg:province":"Bayern",
    "wof:name":"Drogerie Hammerl Gmbh & Co. Kg",
    "wof:placetype":"venue"
},
  "geometry": {"coordinates":[11.032016,49.6576],"type":"Point"}
}