{
  "type": "Feature",
  "properties": {
    "iso:country":"DE",
    "sg:address":"Entenpfuhl 10",
    "sg:city":"Mayen",
    "sg:phone":"+49 2651/73783",
    "sg:postcode":"56727",
    "sg:province":"Rheinland-Pfalz",
    "wof:name":"Verein Ehemaliger Sch\u00fcler Des Gymnasiums Mayen E. V.",
    "wof:placetype":"venue"
},
  "geometry": {"coordinates":[7.2236580849,50.3287658691],"type":"Point"}
}