{
  "type": "Feature",
  "properties": {
    "iso:country":"DE",
    "sg:address":"Jederitzer Str. 17",
    "sg:city":"Sandau",
    "sg:phone":"+49 4939/383317",
    "sg:postcode":"39524",
    "sg:province":"Sachsen-Anhalt",
    "wof:name":"Agrargen. Fortschritt",
    "wof:placetype":"venue"
},
  "geometry": {"coordinates":[12.050898,52.790058],"type":"Point"}
}