{
  "type": "Feature",
  "properties": {
    "iso:country":"DE",
    "sg:address":"Dorfstr. 11",
    "sg:city":"Appenweier",
    "sg:phone":"+49 7805/5303",
    "sg:postcode":"77767",
    "sg:province":"Baden-W\u00fcrttemberg",
    "wof:name":"Bernd Dreier",
    "wof:placetype":"venue"
},
  "geometry": {"coordinates":[8.001337,48.521248],"type":"Point"}
}