{
  "type": "Feature",
  "properties": {
    "iso:country":"DE",
    "sg:address":"Hauptstr. 42",
    "sg:city":"Kirchberg",
    "sg:phone":"+49 7144/36964",
    "sg:postcode":"71737",
    "sg:province":"Baden-W\u00fcrttemberg",
    "wof:name":"Berthold Gleich",
    "wof:placetype":"venue"
},
  "geometry": {"coordinates":[12.520827,50.61137],"type":"Point"}
}