{
  "type": "Feature",
  "properties": {
    "iso:country":"DE",
    "sg:address":"Schindkautweg 5",
    "sg:city":"Mannheim",
    "sg:phone":"+49 621/852473",
    "sg:postcode":"68199",
    "sg:province":"Baden-W\u00fcrttemberg",
    "wof:name":"W. H. Ecker",
    "wof:placetype":"venue"
},
  "geometry": {"coordinates":[8.4775161743,49.4483032227],"type":"Point"}
}