{
  "type": "Feature",
  "properties": {
    "iso:country":"DE",
    "sg:address":"Birkenstr. 1 a",
    "sg:city":"Ronsberg",
    "sg:phone":"+49 8306/544",
    "sg:postcode":"87671",
    "sg:province":"Bayern",
    "wof:name":"Wankmiller Holding Gmbh & Co. Kg",
    "wof:placetype":"venue"
},
  "geometry": {"coordinates":[10.414542,47.896347],"type":"Point"}
}