{
  "type": "Feature",
  "properties": {
    "iso:country":"DE",
    "sg:address":"Dr.-Thyroff-Str. 2",
    "sg:city":"Alt\u00f6tting",
    "sg:phone":"+49 8671/881999",
    "sg:postcode":"84503",
    "sg:province":"Bayern",
    "wof:name":"Peter Schwinghammer",
    "wof:placetype":"venue"
},
  "geometry": {"coordinates":[12.674118042,48.2200241089],"type":"Point"}
}