{
  "type": "Feature",
  "properties": {
    "iso:country":"DE",
    "sg:address":"Neuer Wall 30",
    "sg:city":"Moers",
    "sg:phone":"+49 2841/178720",
    "sg:postcode":"47441",
    "sg:province":"Nordrhein-Westfalen",
    "wof:name":"Hudeydan Erk",
    "wof:placetype":"venue"
},
  "geometry": {"coordinates":[6.6288781166,51.4514389038],"type":"Point"}
}