{
  "type": "Feature",
  "properties": {
    "iso:country":"DE",
    "sg:address":"Wiehengebirgsstr. 35 POSTFACH 140",
    "sg:city":"Melle",
    "sg:phone":"+49 4954/27452",
    "sg:postcode":"49328",
    "sg:province":"Niedersachsen",
    "wof:name":"Korfhage Ed & S\u00d6hne Gmbh & Co",
    "wof:placetype":"venue"
},
  "geometry": {"coordinates":[8.3964681625,52.250957489],"type":"Point"}
}