{
  "type": "Feature",
  "properties": {
    "iso:country":"DE",
    "sg:address":"B\u00e4derstr.",
    "sg:city":"Singhofen",
    "sg:phone":"+49 2604/953914",
    "sg:postcode":"56379",
    "sg:province":"Rheinland-Pfalz",
    "wof:name":"Gemmer Transporte Gmbh",
    "wof:placetype":"venue"
},
  "geometry": {"coordinates":[7.8209748268,50.2924804688],"type":"Point"}
}