{
  "type": "Feature",
  "properties": {
    "iso:country":"DE",
    "sg:address":"R\u00f6ntgenstr. 43",
    "sg:city":"Essen",
    "sg:phone":"+49 201/7502334",
    "sg:postcode":"45143",
    "sg:province":"Nordrhein-Westfalen",
    "wof:name":"Esoterik Siron",
    "wof:placetype":"venue"
},
  "geometry": {"coordinates":[6.974225,51.458576],"type":"Point"}
}