{
  "type": "Feature",
  "properties": {
    "iso:country":"DE",
    "sg:address":"Faldernstr. 33",
    "sg:city":"Emden",
    "sg:phone":"+49 4921/25220",
    "sg:postcode":"26725",
    "sg:province":"Niedersachsen",
    "wof:name":"Folkert Brinker",
    "wof:placetype":"venue"
},
  "geometry": {"coordinates":[7.2089800835,53.3659095764],"type":"Point"}
}