{
  "type": "Feature",
  "properties": {
    "iso:country":"DE",
    "sg:address":"Postfach 80:: 79239 Ihringen:: Germany.^^Wasenweiler Str 1-3::",
    "sg:city":"Ihringen",
    "sg:phone":"+49 7668/71060",
    "sg:postcode":"79241",
    "sg:province":"Baden-W\u00fcrttemberg",
    "wof:name":"Volksbank Breisgau S\u00fcd Eg",
    "wof:placetype":"venue"
},
  "geometry": {"coordinates":[7.64552,48.045761],"type":"Point"}
}