{
  "type": "Feature",
  "properties": {
    "iso:country":"DE",
    "sg:address":"Friedrichstr. 17-19",
    "sg:city":"Aachen",
    "sg:phone":"+49 241/946680",
    "sg:postcode":"52070",
    "sg:province":"Nordrhein-Westfalen",
    "wof:name":"Delheid Soiron Und Schreven Rechtsanw\u00e4lte",
    "wof:placetype":"venue"
},
  "geometry": {"coordinates":[6.0987939835,50.7736244202],"type":"Point"}
}