{
  "type": "Feature",
  "properties": {
    "iso:country":"DE",
    "sg:address":"B 96",
    "sg:city":"Mahlow",
    "sg:phone":"+49 3379/372398",
    "sg:postcode":"15831",
    "sg:province":"Brandenburg",
    "wof:name":"Hans-joachim Gieseler",
    "wof:placetype":"venue"
},
  "geometry": {"coordinates":[13.434244,52.352692],"type":"Point"}
}