{
  "type": "Feature",
  "properties": {
    "iso:country":"DE",
    "sg:address":"Kruppstr. 76",
    "sg:city":"D\u00fcsseldorf",
    "sg:postcode":"40227",
    "sg:province":"Nordrhein-Westfalen",
    "wof:name":"Aviba Bau Gmbh",
    "wof:placetype":"venue"
},
  "geometry": {"coordinates":[6.7972140312,51.2117271423],"type":"Point"}
}