{
  "type": "Feature",
  "properties": {
    "iso:country":"DE",
    "sg:address":"Paprikastr. 12",
    "sg:city":"Stuttgart",
    "sg:phone":"+49 711/447580",
    "sg:postcode":"70619",
    "sg:province":"Baden-W\u00fcrttemberg",
    "wof:name":"Pelikan-apotheke",
    "wof:placetype":"venue"
},
  "geometry": {"coordinates":[9.21065,48.74604],"type":"Point"}
}