{
  "type": "Feature",
  "properties": {
    "iso:country":"DE",
    "sg:address":"Hahnstr. 1-3",
    "sg:city":"Heilbronn",
    "sg:phone":"+49 7131/913040",
    "sg:postcode":"74080",
    "sg:province":"Baden-W\u00fcrttemberg",
    "wof:name":"Josef Schwan Gmbh",
    "wof:placetype":"venue"
},
  "geometry": {"coordinates":[9.161726,49.141697],"type":"Point"}
}