{
  "type": "Feature",
  "properties": {
    "iso:country":"DE",
    "sg:address":"Domplatz 7",
    "sg:city":"Regensburg",
    "sg:phone":"+49 941/59104",
    "sg:postcode":"93047",
    "sg:province":"Bayern",
    "wof:name":"Gothaer Versicherungsbank Vvag",
    "wof:placetype":"venue"
},
  "geometry": {"coordinates":[12.097073555,49.019657135],"type":"Point"}
}