{
  "type": "Feature",
  "properties": {
    "iso:country":"DE",
    "sg:address":"Bahnhofstra\u00dfe 71",
    "sg:city":"Treuchtlingen",
    "sg:phone":"+49 9142/96620",
    "sg:postcode":"91757",
    "sg:province":"Bayern",
    "wof:name":"Rfk-formenbau Gmbh",
    "wof:placetype":"venue"
},
  "geometry": {"coordinates":[10.8845701218,48.9872512817],"type":"Point"}
}