{
  "type": "Feature",
  "properties": {
    "iso:country":"DE",
    "sg:address":"Kehlhofstr. 9 a",
    "sg:city":"Rielasingen-Worblingen",
    "sg:phone":"+49 7731/52964",
    "sg:postcode":"78239",
    "sg:province":"Baden-W\u00fcrttemberg",
    "wof:name":"H. F\u00fcrst",
    "wof:placetype":"venue"
},
  "geometry": {"coordinates":[8.835717,47.731869],"type":"Point"}
}