{
  "type": "Feature",
  "properties": {
    "iso:country":"DE",
    "sg:address":"Leitenstrasse 40",
    "sg:city":"Geretsried",
    "sg:phone":"+49 2166/942318",
    "sg:postcode":"82536",
    "sg:province":"Bayern",
    "wof:name":"Profit-web - Geld Verdienen Im Internet",
    "wof:placetype":"venue"
},
  "geometry": {"coordinates":[-105.901299,22.84561],"type":"Point"}
}