{
  "type": "Feature",
  "properties": {
    "iso:country":"DE",
    "sg:address":"Breitbendenstr. 5",
    "sg:city":"Aachen",
    "sg:phone":"+49 241/558694",
    "sg:postcode":"52080",
    "sg:province":"Nordrhein-Westfalen",
    "wof:name":"Rolf Gerhards Architekt",
    "wof:placetype":"venue"
},
  "geometry": {"coordinates":[6.15011,50.775345],"type":"Point"}
}