{
  "type": "Feature",
  "properties": {
    "iso:country":"DE",
    "sg:address":"K\u00f6tnerholzweg 13",
    "sg:city":"Hannover",
    "sg:phone":"+49 511/2104101",
    "sg:postcode":"30451",
    "sg:province":"Niedersachsen",
    "wof:name":"Hermann Hagedorn",
    "wof:placetype":"venue"
},
  "geometry": {"coordinates":[9.70591,52.371548],"type":"Point"}
}