{
  "type": "Feature",
  "properties": {
    "iso:country":"DE",
    "sg:address":"Heerstr. 51",
    "sg:city":"Straubing",
    "sg:phone":"+49 9421/21135",
    "sg:postcode":"94315",
    "sg:province":"Bayern",
    "wof:name":"Gebr. Wolf Ohg",
    "wof:placetype":"venue"
},
  "geometry": {"coordinates":[12.5833101273,48.8823127747],"type":"Point"}
}