{
  "type": "Feature",
  "properties": {
    "iso:country":"DE",
    "sg:address":"Reulsbergweg 29",
    "sg:city":"Essen",
    "sg:phone":"+49 201/482252",
    "sg:postcode":"45257",
    "sg:province":"Nordrhein-Westfalen",
    "wof:name":"Haus Ruhrblick",
    "wof:placetype":"venue"
},
  "geometry": {"coordinates":[7.0912308693,51.3879776001],"type":"Point"}
}