{
  "type": "Feature",
  "properties": {
    "iso:country":"DE",
    "sg:address":"Heimburgstr. 1",
    "sg:city":"Offenburg",
    "sg:phone":"+49 781/68289",
    "sg:postcode":"77656",
    "sg:province":"Baden-W\u00fcrttemberg",
    "wof:name":"Restaurant Kastanic",
    "wof:placetype":"venue"
},
  "geometry": {"coordinates":[7.9246778488,48.4637336731],"type":"Point"}
}