{
  "type": "Feature",
  "properties": {
    "iso:country":"DE",
    "sg:address":"Goldgasse 1",
    "sg:city":"Wiesbaden",
    "sg:phone":"+49 611/307766",
    "sg:postcode":"65183",
    "sg:province":"Hessen",
    "wof:name":"B. Stiller",
    "wof:placetype":"venue"
},
  "geometry": {"coordinates":[8.241549,50.083862],"type":"Point"}
}