{
  "type": "Feature",
  "properties": {
    "iso:country":"DE",
    "sg:address":"Holmer Str. 5",
    "sg:city":"Wedel",
    "sg:phone":"+49 4103/2440",
    "sg:postcode":"22880",
    "sg:province":"Schleswig-Holstein",
    "wof:name":"Gerd Koppelmann Seeschiffahrt-unternehmen",
    "wof:placetype":"venue"
},
  "geometry": {"coordinates":[9.690215,53.587753],"type":"Point"}
}