{
  "type": "Feature",
  "properties": {
    "iso:country":"DE",
    "sg:address":"Kurhessenstr. 44 a",
    "sg:city":"Frankfurt",
    "sg:phone":"+49 69/511611",
    "sg:postcode":"60431",
    "sg:province":"Hessen",
    "wof:name":"J\u00fcrgen Roeder Rechtsanwalt",
    "wof:placetype":"venue"
},
  "geometry": {"coordinates":[8.6569099426,50.1519126892],"type":"Point"}
}