{
  "type": "Feature",
  "properties": {
    "iso:country":"DE",
    "sg:address":"Waltroper Str. 32-34",
    "sg:city":"L\u00fcnen",
    "sg:phone":"+49 231/44835",
    "sg:postcode":"44536",
    "sg:province":"Nordrhein-Westfalen",
    "wof:name":"Aktiv-markt Dortmund-kassel Eg",
    "wof:placetype":"venue"
},
  "geometry": {"coordinates":[7.4384541512,51.5978546143],"type":"Point"}
}