{
  "type": "Feature",
  "properties": {
    "iso:country":"DE",
    "sg:address":"Aachener Str. 18",
    "sg:city":"Erkelenz",
    "sg:phone":"+49 2431/81158",
    "sg:postcode":"41812",
    "sg:province":"Nordrhein-Westfalen",
    "wof:name":"Pizzeria Tartuf",
    "wof:placetype":"venue"
},
  "geometry": {"coordinates":[6.3148741722,51.0788841248],"type":"Point"}
}