{
  "type": "Feature",
  "properties": {
    "iso:country":"DE",
    "sg:address":"Fr\u00fchmesserstr. 12",
    "sg:city":"Lahnstein",
    "sg:phone":"+49 2621/944550",
    "sg:postcode":"56112",
    "sg:province":"Rheinland-Pfalz",
    "wof:name":"Connect Edv-dienstleistungen E. K.",
    "wof:placetype":"venue"
},
  "geometry": {"coordinates":[7.605837,50.300976],"type":"Point"}
}