{
  "type": "Feature",
  "properties": {
    "iso:country":"DE",
    "sg:address":"Berner Str. 52",
    "sg:city":"Frankfurt",
    "sg:phone":"+49 69/500090",
    "sg:postcode":"60437",
    "sg:province":"Hessen",
    "wof:name":"Dr. Wirth Grafische Technik",
    "wof:placetype":"venue"
},
  "geometry": {"coordinates":[8.6552667618,50.1938934326],"type":"Point"}
}