{
  "type": "Feature",
  "properties": {
    "iso:country":"DE",
    "sg:address":"Bettinastr. 34",
    "sg:city":"Frankfurt",
    "sg:phone":"+49 69/233274",
    "sg:postcode":"60325",
    "sg:province":"Hessen",
    "wof:name":"Agt Reisen Gmbh",
    "wof:placetype":"venue"
},
  "geometry": {"coordinates":[8.6596755981,50.1119003296],"type":"Point"}
}