{
  "type": "Feature",
  "properties": {
    "iso:country":"DE",
    "sg:address":"Freiburger Str. 3",
    "sg:city":"Pforzheim",
    "sg:phone":"+49 7231/31570",
    "sg:postcode":"75179",
    "sg:province":"Baden-W\u00fcrttemberg",
    "wof:name":"Pforzheimer Datenverarbeitungs-gmbh",
    "wof:placetype":"venue"
},
  "geometry": {"coordinates":[8.6638698578,48.9001579285],"type":"Point"}
}