{
  "type": "Feature",
  "properties": {
    "iso:country":"DE",
    "sg:address":"Stein 6",
    "sg:city":"Pl\u00f6\u00dfberg",
    "sg:phone":"+49 9636/284",
    "sg:postcode":"95703",
    "sg:province":"Bayern",
    "wof:name":"Josef Ziegler Gmbh",
    "wof:placetype":"venue"
},
  "geometry": {"coordinates":[12.3249645233,49.8249320984],"type":"Point"}
}