{
  "type": "Feature",
  "properties": {
    "iso:country":"DE",
    "sg:address":"Mannsdorf 9",
    "sg:city":"Ebersbach",
    "sg:phone":"+49 3431/612201",
    "sg:postcode":"04720",
    "sg:province":"Sachsen",
    "wof:name":"G. Grunert",
    "wof:placetype":"venue"
},
  "geometry": {"coordinates":[13.0909128189,51.1078605652],"type":"Point"}
}