{
  "type": "Feature",
  "properties": {
    "iso:country":"DE",
    "sg:address":"Marienburger Str. 20",
    "sg:city":"Monheim",
    "sg:phone":"+49 2173/57887",
    "sg:postcode":"40789",
    "sg:province":"Nordrhein-Westfalen",
    "wof:name":"Plischke Immobilienmakler",
    "wof:placetype":"venue"
},
  "geometry": {"coordinates":[6.8865718842,51.0804290771],"type":"Point"}
}