{
  "type": "Feature",
  "properties": {
    "iso:country":"DE",
    "sg:address":"Postfach 110130",
    "sg:city":"Heidelberg",
    "sg:phone":"+49 6224/919016",
    "sg:postcode":"69071",
    "sg:province":"Baden-W\u00fcrttemberg",
    "wof:name":"Rs Online, Das Preiswerte Internet-kaufhaus",
    "wof:placetype":"venue"
},
  "geometry": {"coordinates":[8.6802597046,49.4019508362],"type":"Point"}
}