{
  "type": "Feature",
  "properties": {
    "iso:country":"DE",
    "sg:address":"K\u00f6nigstr. 4",
    "sg:city":"Hannover",
    "sg:phone":"+49 511/341134",
    "sg:postcode":"30175",
    "sg:province":"Niedersachsen",
    "wof:name":"Ingeborg Wullstein Immobilienmaklerin",
    "wof:placetype":"venue"
},
  "geometry": {"coordinates":[9.7471437454,52.3753166199],"type":"Point"}
}