{
  "type": "Feature",
  "properties": {
    "iso:country":"DE",
    "sg:address":"Dr.-Krause-Str. 31",
    "sg:city":"K\u00f6then",
    "sg:phone":"+49 3496/216649",
    "sg:postcode":"06366",
    "sg:province":"Sachsen-Anhalt",
    "wof:name":"Volker Neumann Rechtsanwalt",
    "wof:placetype":"venue"
},
  "geometry": {"coordinates":[11.9859647751,51.7507705688],"type":"Point"}
}