{
  "type": "Feature",
  "properties": {
    "iso:country":"DE",
    "sg:address":"B\u00f6blinger Str. 29",
    "sg:city":"Leonberg",
    "sg:phone":"+49 7152/60940",
    "sg:postcode":"71229",
    "sg:province":"Baden-W\u00fcrttemberg",
    "wof:name":"Ubg Grundbesitz- Verwaltungs Gmbh",
    "wof:placetype":"venue"
},
  "geometry": {"coordinates":[9.0332918167,48.790184021],"type":"Point"}
}