{
  "type": "Feature",
  "properties": {
    "iso:country":"DE",
    "sg:address":"Stollberger Str. 8",
    "sg:city":"Neukirchen",
    "sg:phone":"+49 371/217277",
    "sg:postcode":"09221",
    "sg:province":"Sachsen",
    "wof:name":"Pampel & Partner Architekturb\u00fcro",
    "wof:placetype":"venue"
},
  "geometry": {"coordinates":[12.86572,50.779015],"type":"Point"}
}