{
  "type": "Feature",
  "properties": {
    "iso:country":"DE",
    "sg:address":"Hauptstr. 18",
    "sg:city":"Wennigsen",
    "sg:phone":"+49 5103/7117",
    "sg:postcode":"30974",
    "sg:province":"Niedersachsen",
    "wof:name":"Lau Freya Ringelblume",
    "wof:placetype":"venue"
},
  "geometry": {"coordinates":[9.5673141479,52.2720069885],"type":"Point"}
}