{
  "type": "Feature",
  "properties": {
    "iso:country":"DE",
    "sg:address":"Am Hopfenberg 28",
    "sg:city":"Rotthalm\u00fcnster",
    "sg:phone":"+49 8533/429",
    "sg:postcode":"94094",
    "sg:province":"Bayern",
    "wof:name":"Thekla M\u00fcller Hebamme",
    "wof:placetype":"venue"
},
  "geometry": {"coordinates":[13.199318,48.355354],"type":"Point"}
}