{
  "type": "Feature",
  "properties": {
    "iso:country":"DE",
    "sg:address":"Maria-Louisen-Str. 65",
    "sg:city":"Hamburg",
    "sg:phone":"+49 40/473480",
    "sg:postcode":"22301",
    "sg:province":"Hamburg",
    "wof:name":"Carl Bauer & Sohn",
    "wof:placetype":"venue"
},
  "geometry": {"coordinates":[10.0038633347,53.5882644653],"type":"Point"}
}