{
  "type": "Feature",
  "properties": {
    "iso:country":"DE",
    "sg:address":"Halberst\u00e4dter Str 9",
    "sg:city":"Halle",
    "sg:phone":"+49 345/5170555",
    "sg:postcode":"06112",
    "sg:province":"Sachsen-Anhalt",
    "wof:name":"Compact Werbetechnik Leuchtwerbung H\u00f6llwarth Montagen, Neon-service, Beschriftungs-service",
    "wof:placetype":"venue"
},
  "geometry": {"coordinates":[11.984001,51.483299],"type":"Point"}
}