{
  "type": "Feature",
  "properties": {
    "iso:country":"DE",
    "sg:address":"Hauptstr. 148",
    "sg:city":"Denkingen",
    "sg:phone":"+49 7424/98150",
    "sg:postcode":"78588",
    "sg:province":"Baden-W\u00fcrttemberg",
    "wof:name":"Schwer Pr\u00e4zision Gmbh",
    "wof:placetype":"venue"
},
  "geometry": {"coordinates":[8.737026,48.11866],"type":"Point"}
}