{
  "type": "Feature",
  "properties": {
    "iso:country":"DE",
    "sg:address":"Ohlenb\u00fctteler Stadtweg",
    "sg:city":"Appel",
    "sg:phone":"+49 4165/6792",
    "sg:postcode":"21279",
    "sg:province":"Niedersachsen",
    "wof:name":"H. Holthusen",
    "wof:placetype":"venue"
},
  "geometry": {"coordinates":[9.754612,53.402],"type":"Point"}
}