{
  "type": "Feature",
  "properties": {
    "iso:country":"DE",
    "sg:address":"An den Fischteichen 5",
    "sg:city":"Hankensb\u00fcttel",
    "sg:phone":"+49 5832/810",
    "sg:postcode":"29386",
    "sg:province":"Niedersachsen",
    "wof:name":"Flessner Gmbh & Co.",
    "wof:placetype":"venue"
},
  "geometry": {"coordinates":[10.6040630341,52.7316513062],"type":"Point"}
}