{
  "type": "Feature",
  "properties": {
    "iso:country":"DE",
    "sg:address":"Pestalozzistr. 84",
    "sg:city":"Berlin",
    "sg:phone":"+49 30/3123132",
    "sg:postcode":"10627",
    "sg:province":"Berlin",
    "wof:name":"Klaus Madel",
    "wof:placetype":"venue"
},
  "geometry": {"coordinates":[13.309047699,52.5077285767],"type":"Point"}
}