{
  "type": "Feature",
  "properties": {
    "iso:country":"DE",
    "sg:address":"Am Olldiek 34",
    "sg:city":"Marienhafe",
    "sg:phone":"+49 4934/205",
    "sg:postcode":"26529",
    "sg:province":"Niedersachsen",
    "wof:name":"Deutsche Bahn Ag",
    "wof:placetype":"venue"
},
  "geometry": {"coordinates":[7.2717299461,53.5206871033],"type":"Point"}
}