{
  "type": "Feature",
  "properties": {
    "iso:country":"DE",
    "sg:address":"Knochenhauerstr. 18-19",
    "sg:city":"Bremen",
    "sg:phone":"+49 421/160540",
    "sg:postcode":"28195",
    "sg:province":"Bremen",
    "wof:name":"Bte City B\u00fcro Laden Handels Gmbh",
    "wof:placetype":"venue"
},
  "geometry": {"coordinates":[8.807101,53.078804],"type":"Point"}
}