{
  "type": "Feature",
  "properties": {
    "iso:country":"DE",
    "sg:address":"Spinozastr. 11",
    "sg:city":"Hannover",
    "sg:phone":"+49 511/550449",
    "sg:postcode":"30625",
    "sg:province":"Niedersachsen",
    "wof:name":"Cv-immobilien",
    "wof:placetype":"venue"
},
  "geometry": {"coordinates":[9.7943811417,52.3704719543],"type":"Point"}
}