{
  "type": "Feature",
  "properties": {
    "iso:country":"DE",
    "sg:address":"Bocholter Str. 7",
    "sg:city":"Borken",
    "sg:phone":"+49 2861/5495",
    "sg:postcode":"46325",
    "sg:province":"Nordrhein-Westfalen",
    "wof:name":"Josef Kolks Heilpraktiker",
    "wof:placetype":"venue"
},
  "geometry": {"coordinates":[6.8534021378,51.8441352844],"type":"Point"}
}