{
  "type": "Feature",
  "properties": {
    "iso:country":"DE",
    "sg:address":"Im Junkerhau 11",
    "sg:city":"Pulheim",
    "sg:phone":"+49 2238/50030",
    "sg:postcode":"50259",
    "sg:province":"Nordrhein-Westfalen",
    "wof:name":"Baltzer Gmbh",
    "wof:placetype":"venue"
},
  "geometry": {"coordinates":[6.79766,51.007862],"type":"Point"}
}