{
  "type": "Feature",
  "properties": {
    "iso:country":"DE",
    "sg:address":"Bergerstr. 110",
    "sg:city":"Euskirchen",
    "sg:phone":"+49 2251/2638",
    "sg:postcode":"53879",
    "sg:province":"Nordrhein-Westfalen",
    "wof:name":"Wichterich Gmbh & Co. Kg",
    "wof:placetype":"venue"
},
  "geometry": {"coordinates":[6.782048,50.664539],"type":"Point"}
}