{
  "type": "Feature",
  "properties": {
    "iso:country":"DE",
    "sg:address":"Siebenh\u00f6fen 5",
    "sg:city":"Hollern-Twielenfleth",
    "sg:phone":"+49 4141/70704",
    "sg:postcode":"21723",
    "sg:province":"Niedersachsen",
    "wof:name":"Elbe-label J\u00fcrgen Diederichsen & Co.",
    "wof:placetype":"venue"
},
  "geometry": {"coordinates":[9.5720949173,53.5894775391],"type":"Point"}
}