{
  "type": "Feature",
  "properties": {
    "iso:country":"DE",
    "sg:address":"Friedrich-Schiller-Str. 22",
    "sg:city":"Ravensburg",
    "sg:phone":"+49 751/37040",
    "sg:postcode":"88214",
    "sg:province":"Baden-W\u00fcrttemberg",
    "wof:name":"Taylorix Ravensburg Gmbh",
    "wof:placetype":"venue"
},
  "geometry": {"coordinates":[9.6053,47.777679],"type":"Point"}
}