{
  "type": "Feature",
  "properties": {
    "iso:country":"DE",
    "sg:address":"Neuer Markt 28",
    "sg:city":"Emden",
    "sg:phone":"+49 4921/31636",
    "sg:postcode":"26721",
    "sg:province":"Niedersachsen",
    "wof:name":"Rossmann Drogeriemarkt",
    "wof:placetype":"venue"
},
  "geometry": {"coordinates":[7.20236,53.367722],"type":"Point"}
}