{
  "type": "Feature",
  "properties": {
    "iso:country":"DE",
    "sg:address":"M\u00fcllergasse 14",
    "sg:city":"Roetgen",
    "sg:postcode":"52159",
    "sg:province":"Nordrhein-Westfalen",
    "wof:name":"Diskontm\u00f6belmarkt H. Muschenich Gmbh",
    "wof:placetype":"venue"
},
  "geometry": {"coordinates":[6.2059497833,50.6488189697],"type":"Point"}
}