{
  "type": "Feature",
  "properties": {
    "iso:country":"DE",
    "sg:address":"Schulstr. 2",
    "sg:city":"Kirchheim",
    "sg:phone":"+49 8266/1606",
    "sg:postcode":"87757",
    "sg:province":"Bayern",
    "wof:name":"Albert Fischer",
    "wof:placetype":"venue"
},
  "geometry": {"coordinates":[10.475574,48.179462],"type":"Point"}
}