{
  "type": "Feature",
  "properties": {
    "iso:country":"DE",
    "sg:address":"Stuttgarter Str. 67",
    "sg:city":"Backnang",
    "sg:postcode":"71522",
    "sg:province":"Baden-W\u00fcrttemberg",
    "wof:name":"Gerhard Fingerle",
    "wof:placetype":"venue"
},
  "geometry": {"coordinates":[9.437026,48.943287],"type":"Point"}
}