{
  "type": "Feature",
  "properties": {
    "iso:country":"DE",
    "sg:address":"hohenbergstr. 30",
    "sg:city":"rottweil",
    "sg:postcode":"78628",
    "sg:province":"Baden-W\u00fcrttemberg",
    "wof:name":"Rugbylinks Thomas Wiener Homepage",
    "wof:placetype":"venue"
},
  "geometry": {"coordinates":[8.643546,48.163021],"type":"Point"}
}