{
  "type": "Feature",
  "properties": {
    "iso:country":"DE",
    "sg:address":"Kornmarkt 8",
    "sg:city":"Wesel",
    "sg:phone":"+49 281/331060",
    "sg:postcode":"46483",
    "sg:province":"Nordrhein-Westfalen",
    "wof:name":"Roland Bonewitz",
    "wof:placetype":"venue"
},
  "geometry": {"coordinates":[6.6120090485,51.6580238342],"type":"Point"}
}