{
  "type": "Feature",
  "properties": {
    "iso:country":"DE",
    "sg:address":"Waldh\u00e4user Str. 122",
    "sg:city":"T\u00fcbingen",
    "sg:phone":"+49 7071/63299",
    "sg:postcode":"72076",
    "sg:province":"Baden-W\u00fcrttemberg",
    "wof:name":"Aral Tankstelle",
    "wof:placetype":"venue"
},
  "geometry": {"coordinates":[9.0558347702,48.5459327698],"type":"Point"}
}