{
  "type": "Feature",
  "properties": {
    "iso:country":"DE",
    "sg:address":"Nr. 3",
    "sg:city":"Neustrelitz",
    "sg:phone":"+49 3981/205105",
    "sg:postcode":"17235",
    "sg:province":"Mecklenburg-Vorpommern",
    "wof:name":"Awo-altenpflegeheim Hohenlanke",
    "wof:placetype":"venue"
},
  "geometry": {"coordinates":[13.06116,53.363781],"type":"Point"}
}