{
  "type": "Feature",
  "properties": {
    "iso:country":"DE",
    "sg:address":"\u00dckern 30",
    "sg:city":"Paderborn",
    "sg:phone":"+49 5251/26677",
    "sg:postcode":"33098",
    "sg:province":"Nordrhein-Westfalen",
    "wof:name":"H.-a. Schr\u00f6ter",
    "wof:placetype":"venue"
},
  "geometry": {"coordinates":[8.7574481964,51.7221717834],"type":"Point"}
}