{
  "type": "Feature",
  "properties": {
    "iso:country":"DE",
    "sg:address":"Betzinger Str. 33",
    "sg:city":"Reutlingen",
    "sg:phone":"+49 7121/503445",
    "sg:postcode":"72770",
    "sg:province":"Baden-W\u00fcrttemberg",
    "wof:name":"U. Reiher",
    "wof:placetype":"venue"
},
  "geometry": {"coordinates":[9.142733,48.480946],"type":"Point"}
}