{
  "type": "Feature",
  "properties": {
    "iso:country":"DE",
    "sg:address":"Hauptstr. 44",
    "sg:city":"R\u00fcckersdorf",
    "sg:phone":"+49 911/579436",
    "sg:postcode":"90607",
    "sg:province":"Bayern",
    "wof:name":"Edmund Neumann Steuerberater Gmbh",
    "wof:placetype":"venue"
},
  "geometry": {"coordinates":[11.2445325851,49.4945907593],"type":"Point"}
}