{
  "type": "Feature",
  "properties": {
    "iso:country":"DE",
    "sg:address":"Holzener Str. 72",
    "sg:city":"Menden",
    "sg:phone":"+49 4923/7360290",
    "sg:postcode":"58708",
    "sg:province":"Nordrhein-Westfalen",
    "wof:name":"Hubert Vieth Gmbh",
    "wof:placetype":"venue"
},
  "geometry": {"coordinates":[7.761516,51.439514],"type":"Point"}
}