{
  "type": "Feature",
  "properties": {
    "iso:country":"DE",
    "sg:address":"Horn 9",
    "sg:city":"Solingen",
    "sg:phone":"+49 212/62401",
    "sg:postcode":"42699",
    "sg:province":"Nordrhein-Westfalen",
    "wof:name":"Gerhard Gro\u00df",
    "wof:placetype":"venue"
},
  "geometry": {"coordinates":[7.014301,51.127174],"type":"Point"}
}