{
  "type": "Feature",
  "properties": {
    "iso:country":"DE",
    "sg:address":"Wolfartsweierer Str. 36",
    "sg:city":"Karlsruhe",
    "sg:phone":"+49 721/704431",
    "sg:postcode":"76137",
    "sg:province":"Baden-W\u00fcrttemberg",
    "wof:name":"Bittmann Birli & Co. Montagegesellschaft Mbh",
    "wof:placetype":"venue"
},
  "geometry": {"coordinates":[8.4260005951,49.0009040833],"type":"Point"}
}