{
  "type": "Feature",
  "properties": {
    "iso:country":"DE",
    "sg:address":"Ringstr. 7",
    "sg:city":"Oederan",
    "sg:phone":"+49 37292/4204",
    "sg:postcode":"09569",
    "sg:province":"Sachsen",
    "wof:name":"Alchelin Entwicklungs- Zentrum Und Aggregatebau Gmbh",
    "wof:placetype":"venue"
},
  "geometry": {"coordinates":[13.186828,50.871151],"type":"Point"}
}