{
  "type": "Feature",
  "properties": {
    "iso:country":"DE",
    "sg:address":"Bismarckstr. 12",
    "sg:city":"Westerland",
    "sg:phone":"+49 4651/26519",
    "sg:postcode":"25980",
    "sg:province":"Schleswig-Holstein",
    "wof:name":"Welt Wein-import Inh. Martin Schachner",
    "wof:placetype":"venue"
},
  "geometry": {"coordinates":[8.3025865555,54.9064331055],"type":"Point"}
}