{
  "type": "Feature",
  "properties": {
    "iso:country":"DE",
    "sg:address":"Sternschanzstr. 7",
    "sg:city":"Wei\u00dfenburg",
    "sg:phone":"+49 9142/4564",
    "sg:postcode":"91781",
    "sg:province":"Bayern",
    "wof:name":"Norbert Kuhn Architekt",
    "wof:placetype":"venue"
},
  "geometry": {"coordinates":[10.951796,48.986462],"type":"Point"}
}