{
  "type": "Feature",
  "properties": {
    "iso:country":"DE",
    "sg:address":"Christian-Ritter-von-Langheinrich-Str. 1",
    "sg:city":"Bayreuth",
    "sg:phone":"+49 921",
    "sg:postcode":"95448",
    "sg:province":"Bayern",
    "wof:name":"Christliches Centrum Rhema",
    "wof:placetype":"venue"
},
  "geometry": {"coordinates":[11.611436,49.962864],"type":"Point"}
}