{
  "type": "Feature",
  "properties": {
    "iso:country":"DE",
    "sg:address":"Ravensberger Str. 32",
    "sg:city":"L\u00fcbbecke",
    "sg:phone":"+49 5703/811",
    "sg:postcode":"32312",
    "sg:province":"Nordrhein-Westfalen",
    "wof:name":"Stefan Peper Bauelemente E. Kfm.",
    "wof:placetype":"venue"
},
  "geometry": {"coordinates":[8.697912,52.30188],"type":"Point"}
}