{
  "type": "Feature",
  "properties": {
    "iso:country":"DE",
    "sg:address":"Am Steinhauerplatz 7",
    "sg:city":"Obernkirchen",
    "sg:phone":"+49 5724/98384",
    "sg:postcode":"31683",
    "sg:province":"Niedersachsen",
    "wof:name":"G\u00fcnter Besser & Co. Gmbh & Co. Kg",
    "wof:placetype":"venue"
},
  "geometry": {"coordinates":[9.135369,52.269642],"type":"Point"}
}