{
  "type": "Feature",
  "properties": {
    "iso:country":"DE",
    "sg:address":"Dorfstr. 1",
    "sg:city":"Buchholz",
    "sg:phone":"+49 3631/896112",
    "sg:postcode":"99762",
    "sg:province":"Th\u00fcringen",
    "wof:name":"H. Gerlach",
    "wof:placetype":"venue"
},
  "geometry": {"coordinates":[10.8624572754,51.5413703918],"type":"Point"}
}