{
  "type": "Feature",
  "properties": {
    "iso:country":"DE",
    "sg:address":"Oberglasschleife 9",
    "sg:city":"Deggendorf",
    "sg:phone":"+49 991/9865",
    "sg:postcode":"94469",
    "sg:province":"Bayern",
    "wof:name":"H. Goletz",
    "wof:placetype":"venue"
},
  "geometry": {"coordinates":[13.0347604752,48.866897583],"type":"Point"}
}