{
  "type": "Feature",
  "properties": {
    "iso:country":"DE",
    "sg:address":"Bexbacher Str. 8",
    "sg:city":"Kirkel",
    "sg:postcode":"66459",
    "sg:province":"Saarland",
    "wof:name":"G & B Transport Und Handels Gmbh",
    "wof:placetype":"venue"
},
  "geometry": {"coordinates":[7.2864360809,49.3249931335],"type":"Point"}
}