{
  "type": "Feature",
  "properties": {
    "iso:country":"DE",
    "sg:address":"Kirchstr. 27",
    "sg:city":"Borgholzhausen",
    "sg:phone":"+49 5425/226",
    "sg:postcode":"33829",
    "sg:province":"Nordrhein-Westfalen",
    "wof:name":"W. Vormbaum Kg",
    "wof:placetype":"venue"
},
  "geometry": {"coordinates":[8.301615715,52.1024093628],"type":"Point"}
}