{
  "type": "Feature",
  "properties": {
    "iso:country":"DE",
    "sg:address":"Augsburger Str. 134",
    "sg:city":"Neuburg",
    "sg:phone":"+49 8431/9748",
    "sg:postcode":"86633",
    "sg:province":"Bayern",
    "wof:name":"Karl Sarauer",
    "wof:placetype":"venue"
},
  "geometry": {"coordinates":[11.20463,48.745602],"type":"Point"}
}