{
  "type": "Feature",
  "properties": {
    "iso:country":"DE",
    "sg:address":"Drususstr. 3",
    "sg:city":"Remagen",
    "sg:phone":"+49 2642/23212",
    "sg:postcode":"53424",
    "sg:province":"Rheinland-Pfalz",
    "wof:name":"Steffens Eck",
    "wof:placetype":"venue"
},
  "geometry": {"coordinates":[7.2291522026,50.5779266357],"type":"Point"}
}