{
  "type": "Feature",
  "properties": {
    "iso:country":"DE",
    "sg:address":"R\u00f6merstr. 109",
    "sg:city":"Mannheim",
    "sg:postcode":"68259",
    "sg:province":"Baden-W\u00fcrttemberg",
    "wof:name":"Dech Gmbh",
    "wof:placetype":"venue"
},
  "geometry": {"coordinates":[8.539744,49.502167],"type":"Point"}
}