{
  "type": "Feature",
  "properties": {
    "iso:country":"DE",
    "sg:address":"Truchse\u00dfstr. 21",
    "sg:city":"Aub",
    "sg:phone":"+49 9335/639",
    "sg:postcode":"97239",
    "sg:province":"Bayern",
    "wof:name":"Gastst\u00e4tte Max Groll",
    "wof:placetype":"venue"
},
  "geometry": {"coordinates":[10.0449390411,49.5507507324],"type":"Point"}
}