{
  "type": "Feature",
  "properties": {
    "iso:country":"DE",
    "sg:address":"In den Birken 3",
    "sg:city":"Filderstadt",
    "sg:phone":"+49 711/770880",
    "sg:postcode":"70794",
    "sg:province":"Baden-W\u00fcrttemberg",
    "wof:name":"Deutsche Metrohm Gmbh & Co. Kg",
    "wof:placetype":"venue"
},
  "geometry": {"coordinates":[9.180738,48.658543],"type":"Point"}
}