{
  "type": "Feature",
  "properties": {
    "iso:country":"DE",
    "sg:address":"Kirchweg 9",
    "sg:city":"Eschfeld",
    "sg:phone":"+49 6559/250",
    "sg:postcode":"54619",
    "sg:province":"Rheinland-Pfalz",
    "wof:name":"H. Leufgen Elektroinstallation",
    "wof:placetype":"venue"
},
  "geometry": {"coordinates":[6.200425,50.11301],"type":"Point"}
}