{
  "type": "Feature",
  "properties": {
    "iso:country":"DE",
    "sg:address":"Breite Gasse 5",
    "sg:city":"B\u00f6blingen",
    "sg:phone":"+49 7031/232989",
    "sg:postcode":"71032",
    "sg:province":"Baden-W\u00fcrttemberg",
    "wof:name":"O Donovans Irish Pub",
    "wof:placetype":"venue"
},
  "geometry": {"coordinates":[9.0144271851,48.6848182678],"type":"Point"}
}