{
  "type": "Feature",
  "properties": {
    "iso:country":"DE",
    "sg:address":"Am Forstgarten 10",
    "sg:city":"Kleve",
    "sg:phone":"+49 2821/72400",
    "sg:postcode":"47533",
    "sg:province":"Nordrhein-Westfalen",
    "wof:name":"Dr. Heinrich Camp Tierarzt",
    "wof:placetype":"venue"
},
  "geometry": {"coordinates":[6.1295199394,51.7950706482],"type":"Point"}
}