{
  "type": "Feature",
  "properties": {
    "iso:country":"DE",
    "sg:address":"Wolferstr. 21",
    "sg:city":"\u00dcbersee",
    "sg:phone":"+49 8642/6010",
    "sg:postcode":"83236",
    "sg:province":"Bayern",
    "wof:name":"Deutz Ag",
    "wof:placetype":"venue"
},
  "geometry": {"coordinates":[12.486589,47.820148],"type":"Point"}
}