{
  "type": "Feature",
  "properties": {
    "iso:country":"DE",
    "sg:address":"Nordstern",
    "sg:city":"Lehrte",
    "sg:phone":"+49 5132/4888",
    "sg:postcode":"31275",
    "sg:province":"Niedersachsen",
    "wof:name":"Autobahntankstelle Lehrter See Nord",
    "wof:placetype":"venue"
},
  "geometry": {"coordinates":[9.9548721313,52.3593177795],"type":"Point"}
}