{
  "type": "Feature",
  "properties": {
    "iso:country":"DE",
    "sg:address":"Kantstr. 26",
    "sg:city":"Bamberg",
    "sg:phone":"+49 951/33782",
    "sg:postcode":"96052",
    "sg:province":"Bayern",
    "wof:name":"L. Lingr\u00f6n",
    "wof:placetype":"venue"
},
  "geometry": {"coordinates":[10.9087505341,49.9086265564],"type":"Point"}
}