{
  "type": "Feature",
  "properties": {
    "iso:country":"DE",
    "sg:address":"Karenweg 4",
    "sg:city":"Bitburg",
    "sg:phone":"+49 6561/96180",
    "sg:postcode":"54634",
    "sg:province":"Rheinland-Pfalz",
    "wof:name":"Petrus-apotheke",
    "wof:placetype":"venue"
},
  "geometry": {"coordinates":[6.523194,49.971893],"type":"Point"}
}