{
  "type": "Feature",
  "properties": {
    "iso:country":"DE",
    "sg:address":"St.-Veiter-Str. 11",
    "sg:city":"Neumarkt-Sankt Veit",
    "sg:phone":"+49 8639/8067",
    "sg:postcode":"84494",
    "sg:province":"Bayern",
    "wof:name":"Andreas Ege",
    "wof:placetype":"venue"
},
  "geometry": {"coordinates":[12.5125045776,48.3592948914],"type":"Point"}
}