{
  "type": "Feature",
  "properties": {
    "iso:country":"DE",
    "sg:address":"Albert-Schweitzer-Str. 4",
    "sg:city":"Kronberg",
    "sg:phone":"+49 6173/61356",
    "sg:postcode":"61476",
    "sg:province":"Hessen",
    "wof:name":"Dekanat Kronberg",
    "wof:placetype":"venue"
},
  "geometry": {"coordinates":[8.5343008041,50.1856384277],"type":"Point"}
}