{
  "type": "Feature",
  "properties": {
    "iso:country":"DE",
    "sg:address":"Engelbacher Str. 12",
    "sg:city":"Wetter",
    "sg:phone":"+49 6423/2496",
    "sg:postcode":"35083",
    "sg:province":"Hessen",
    "wof:name":"Jakob M\u00fcller",
    "wof:placetype":"venue"
},
  "geometry": {"coordinates":[8.647287,50.915749],"type":"Point"}
}