{
  "type": "Feature",
  "properties": {
    "iso:country":"DE",
    "sg:address":"K\u00f6nigsberger Str. 18-22",
    "sg:city":"Weinheim",
    "sg:postcode":"69469",
    "sg:province":"Baden-W\u00fcrttemberg",
    "wof:name":"H\u00f6fling Verlag",
    "wof:placetype":"venue"
},
  "geometry": {"coordinates":[8.639122963,49.5425682068],"type":"Point"}
}