{
  "type": "Feature",
  "properties": {
    "iso:country":"DE",
    "sg:address":"Parsevalstr. 18",
    "sg:city":"Hof",
    "sg:phone":"+49 9281/96562",
    "sg:postcode":"95032",
    "sg:province":"Bayern",
    "wof:name":"Burning Strings",
    "wof:placetype":"venue"
},
  "geometry": {"coordinates":[11.912119,50.306351],"type":"Point"}
}