{
  "type": "Feature",
  "properties": {
    "iso:country":"DE",
    "sg:address":"L\u00f6hstr. 38",
    "sg:city":"Schiffdorf",
    "sg:phone":"+49 4749/1445",
    "sg:postcode":"27619",
    "sg:province":"Niedersachsen",
    "wof:name":"L. Wolf",
    "wof:placetype":"venue"
},
  "geometry": {"coordinates":[8.871467,53.508911],"type":"Point"}
}