{
  "type": "Feature",
  "properties": {
    "iso:country":"DE",
    "sg:address":"An der Lutherkirche 10",
    "sg:city":"Hannover",
    "sg:phone":"+49 511/709446",
    "sg:postcode":"30167",
    "sg:province":"Niedersachsen",
    "wof:name":"Safe Immobilien Und Handels Gmbh",
    "wof:placetype":"venue"
},
  "geometry": {"coordinates":[9.7206907272,52.3874320984],"type":"Point"}
}