{
  "type": "Feature",
  "properties": {
    "iso:country":"DE",
    "sg:address":"Friedrich-Ebert-Str. 11::",
    "sg:city":"Wei\u00dfenburg",
    "sg:phone":"+49 9141/8780",
    "sg:postcode":"91781",
    "sg:province":"Bayern",
    "wof:name":"Vereinigte Sparkassen Weissenburg In Bayern",
    "wof:placetype":"venue"
},
  "geometry": {"coordinates":[10.970805,49.029659],"type":"Point"}
}