{
  "type": "Feature",
  "properties": {
    "iso:country":"DE",
    "sg:address":"Hamburger Str. 6",
    "sg:city":"Henstedt-Ulzburg",
    "sg:phone":"+49 4193/5462",
    "sg:postcode":"24558",
    "sg:province":"Schleswig-Holstein",
    "wof:name":"Ulzburger-steak-haus Inh. Ferhat Kasapoglu",
    "wof:placetype":"venue"
},
  "geometry": {"coordinates":[9.9819841385,53.7942733765],"type":"Point"}
}