{
  "type": "Feature",
  "properties": {
    "iso:country":"DE",
    "sg:address":"Wandsbeker Zollstr. 91",
    "sg:city":"Hamburg",
    "sg:phone":"+49 40/656660",
    "sg:postcode":"22041",
    "sg:province":"Hamburg",
    "wof:name":"Martha Bahr Erben Gmbh & Co. Kg",
    "wof:placetype":"venue"
},
  "geometry": {"coordinates":[10.079779,53.576233],"type":"Point"}
}