{
  "type": "Feature",
  "properties": {
    "iso:country":"DE",
    "sg:address":"Gem\u00fcndener Str. 37",
    "sg:city":"Frankenberg",
    "sg:phone":"+49 6451/4018",
    "sg:postcode":"35066",
    "sg:province":"Hessen",
    "wof:name":"Karin Freiling",
    "wof:placetype":"venue"
},
  "geometry": {"coordinates":[8.80257,51.058666],"type":"Point"}
}