{
  "type": "Feature",
  "properties": {
    "iso:country":"DE",
    "sg:address":"Georg-B\u00fcchner-Str. 19",
    "sg:city":"Rostock",
    "sg:phone":"+49 381/453492",
    "sg:postcode":"18055",
    "sg:province":"Mecklenburg-Vorpommern",
    "wof:name":"Cicero Werbeagentur",
    "wof:placetype":"venue"
},
  "geometry": {"coordinates":[12.1393995285,54.0768661499],"type":"Point"}
}