{
  "type": "Feature",
  "properties": {
    "iso:country":"DE",
    "sg:address":"Kreuzstr. 11",
    "sg:city":"Gechingen",
    "sg:phone":"+49 7056/3786",
    "sg:postcode":"75391",
    "sg:province":"Baden-W\u00fcrttemberg",
    "wof:name":"Karl-heinz Wentsch Steuerberater",
    "wof:placetype":"venue"
},
  "geometry": {"coordinates":[8.8315973282,48.6957015991],"type":"Point"}
}