{
  "type": "Feature",
  "properties": {
    "iso:country":"DE",
    "sg:address":"Z\u00fcllsdorfer Str. 5",
    "sg:city":"Gro\u00dftreben-Zwethau",
    "sg:postcode":"04886",
    "sg:province":"Sachsen",
    "wof:name":"Helmut Kempkes",
    "wof:placetype":"venue"
},
  "geometry": {"coordinates":[13.0431318283,51.5820617676],"type":"Point"}
}