{
  "type": "Feature",
  "properties": {
    "iso:country":"DE",
    "sg:address":"Torfplatz 5",
    "sg:city":"Sassenburg",
    "sg:phone":"+49 5371/96610",
    "sg:postcode":"38524",
    "sg:province":"Niedersachsen",
    "wof:name":"Humuswerk Westerbeck Gmbh",
    "wof:placetype":"venue"
},
  "geometry": {"coordinates":[10.6310367584,52.5148010254],"type":"Point"}
}