{
  "type": "Feature",
  "properties": {
    "iso:country":"DE",
    "sg:address":"Allersberger Str. 185",
    "sg:city":"N\u00fcrnberg",
    "sg:phone":"+49 911/929790",
    "sg:postcode":"90461",
    "sg:province":"Bayern",
    "wof:name":"Bay Ms Bayerische Medien-service-gmbh",
    "wof:placetype":"venue"
},
  "geometry": {"coordinates":[11.096272,49.433212],"type":"Point"}
}