{
  "type": "Feature",
  "properties": {
    "iso:country":"DE",
    "sg:address":"Vorderes Eisfeld 5a",
    "sg:city":"Melsungen",
    "sg:phone":"+49 5661/4648",
    "sg:postcode":"34212",
    "sg:province":"Hessen",
    "wof:name":"Hihl-hessische Inline-hockey-liga",
    "wof:placetype":"venue"
},
  "geometry": {"coordinates":[9.54181,51.131027],"type":"Point"}
}