{
  "type": "Feature",
  "properties": {
    "iso:country":"DE",
    "sg:address":"Auf Der Hohen Schaar 3",
    "sg:city":"Hamburg",
    "sg:phone":"+49 40/7524760",
    "sg:postcode":"21107",
    "sg:province":"Hamburg",
    "wof:name":"Tco Transcargo Im- & Export Umschlag & Lagerung",
    "wof:placetype":"venue"
},
  "geometry": {"coordinates":[9.9691095352,53.4964752197],"type":"Point"}
}