{
  "type": "Feature",
  "properties": {
    "iso:country":"DE",
    "sg:address":"Kapellenstr. 10",
    "sg:city":"Weiltingen",
    "sg:phone":"+49 9853/865",
    "sg:postcode":"91744",
    "sg:province":"Bayern",
    "wof:name":"W. Ganzenm\u00fcller",
    "wof:placetype":"venue"
},
  "geometry": {"coordinates":[10.4527349472,49.0372543335],"type":"Point"}
}