{
  "type": "Feature",
  "properties": {
    "iso:country":"DE",
    "sg:address":"Markstr. 412",
    "sg:city":"Bochum",
    "sg:postcode":"44795",
    "sg:province":"Nordrhein-Westfalen",
    "wof:name":"Kick, Dr. Tschierske & Co. Agentur F\u00fcr Werbung",
    "wof:placetype":"venue"
},
  "geometry": {"coordinates":[7.2130990028,51.4411888123],"type":"Point"}
}