{
  "type": "Feature",
  "properties": {
    "iso:country":"DE",
    "sg:address":"Hauptstr. 31",
    "sg:city":"Oberkirch",
    "sg:phone":"+49 7802/2265",
    "sg:postcode":"77704",
    "sg:province":"Baden-W\u00fcrttemberg",
    "wof:name":"Blumenhaus Metzinger Kg",
    "wof:placetype":"venue"
},
  "geometry": {"coordinates":[8.080151,48.530205],"type":"Point"}
}