{
  "type": "Feature",
  "properties": {
    "iso:country":"DE",
    "sg:address":"Potsdamer Str. 171-173",
    "sg:city":"Berlin",
    "sg:phone":"+49 30/2163531",
    "sg:postcode":"10783",
    "sg:province":"Berlin",
    "wof:name":"Klaus Klingbeil H\u00f6rger.-akustik",
    "wof:placetype":"venue"
},
  "geometry": {"coordinates":[13.3612270355,52.4939117432],"type":"Point"}
}