{
  "type": "Feature",
  "properties": {
    "iso:country":"DE",
    "sg:address":"Am Yachthafen",
    "sg:city":"Hennigsdorf",
    "sg:phone":"+49 3302/272676",
    "sg:postcode":"16761",
    "sg:province":"Brandenburg",
    "wof:name":"Restaurant Skipper Am Yachthafen",
    "wof:placetype":"venue"
},
  "geometry": {"coordinates":[13.2014350891,52.6149101257],"type":"Point"}
}