{
  "type": "Feature",
  "properties": {
    "iso:country":"DE",
    "sg:address":"Kurf\u00fcrstendamm 137",
    "sg:city":"Berlin",
    "sg:phone":"+49 30/8024233",
    "sg:postcode":"10711",
    "sg:province":"Berlin",
    "wof:name":"Dieter Hoffmann",
    "wof:placetype":"venue"
},
  "geometry": {"coordinates":[13.2949562073,52.4975357056],"type":"Point"}
}