{
  "type": "Feature",
  "properties": {
    "iso:country":"DE",
    "sg:address":"Bergstr. 25",
    "sg:city":"Weinheim",
    "sg:phone":"+49 6201/12261",
    "sg:postcode":"69469",
    "sg:province":"Baden-W\u00fcrttemberg",
    "wof:name":"B\u00e4ko Weinheim-bergstra\u00dfe B\u00e4cker- Und Konditoren",
    "wof:placetype":"venue"
},
  "geometry": {"coordinates":[8.664390564,49.5482254028],"type":"Point"}
}