{
  "type": "Feature",
  "properties": {
    "iso:country":"DE",
    "sg:address":"Hospitalstr. 4",
    "sg:city":"Sondershausen",
    "sg:phone":"+49 3632/6170",
    "sg:postcode":"99706",
    "sg:province":"Th\u00fcringen",
    "wof:name":"Drk Pflegeheim E. V.",
    "wof:placetype":"venue"
},
  "geometry": {"coordinates":[10.877736,51.373997],"type":"Point"}
}