{
  "type": "Feature",
  "properties": {
    "iso:country":"DE",
    "sg:address":"Ulrich-Steinberger-Platz 7",
    "sg:city":"Vohburg",
    "sg:phone":"+49 8457/1232",
    "sg:postcode":"85088",
    "sg:province":"Bayern",
    "wof:name":"Otto Kaiser",
    "wof:placetype":"venue"
},
  "geometry": {"coordinates":[11.6111001968,48.7673187256],"type":"Point"}
}