{
  "type": "Feature",
  "properties": {
    "iso:country":"DE",
    "sg:address":"Br\u00fcckenstr. 5",
    "sg:city":"Brand-Erbisdorf",
    "sg:phone":"+49 37322/2823",
    "sg:postcode":"09618",
    "sg:province":"Sachsen",
    "wof:name":"H. G\u00fcnther",
    "wof:placetype":"venue"
},
  "geometry": {"coordinates":[13.320172,50.870289],"type":"Point"}
}