{
  "type": "Feature",
  "properties": {
    "iso:country":"DE",
    "sg:address":"Wiesenburger Str. 2",
    "sg:city":"Belzig",
    "sg:phone":"+49 33841/38118",
    "sg:postcode":"14806",
    "sg:province":"Brandenburg",
    "wof:name":"Restaurant Taverne",
    "wof:placetype":"venue"
},
  "geometry": {"coordinates":[12.5872163773,52.1398696899],"type":"Point"}
}