{
  "type": "Feature",
  "properties": {
    "iso:country":"DE",
    "sg:address":"Steuerwalder Str. 20",
    "sg:city":"Hildesheim",
    "sg:phone":"+49 5121/57882",
    "sg:postcode":"31137",
    "sg:province":"Niedersachsen",
    "wof:name":"Chemo-technik Eberhardt Kg",
    "wof:placetype":"venue"
},
  "geometry": {"coordinates":[9.948531,52.160667],"type":"Point"}
}