{
  "type": "Feature",
  "properties": {
    "iso:country":"DE",
    "sg:address":"Bussardstr. 22",
    "sg:city":"Dorsten",
    "sg:phone":"+49 2362/22633",
    "sg:postcode":"46282",
    "sg:province":"Nordrhein-Westfalen",
    "wof:name":"Josef Knopp Heissmangel",
    "wof:placetype":"venue"
},
  "geometry": {"coordinates":[6.9646267891,51.6477470398],"type":"Point"}
}