{
  "type": "Feature",
  "properties": {
    "iso:country":"DE",
    "sg:address":"Glockbergstr. 68",
    "sg:city":"Helmstedt",
    "sg:phone":"+49 5351/40055",
    "sg:postcode":"38350",
    "sg:province":"Niedersachsen",
    "wof:name":"Rolf Ebert",
    "wof:placetype":"venue"
},
  "geometry": {"coordinates":[10.993379,52.22451],"type":"Point"}
}