{
  "type": "Feature",
  "properties": {
    "iso:country":"DE",
    "sg:address":"Am Taubenbaum 18",
    "sg:city":"Bad Nauheim",
    "sg:phone":"+49 6032/96880",
    "sg:postcode":"61231",
    "sg:province":"Hessen",
    "wof:name":"Auto-park Schreier",
    "wof:placetype":"venue"
},
  "geometry": {"coordinates":[8.74817276,50.3761978149],"type":"Point"}
}