{
  "type": "Feature",
  "properties": {
    "iso:country":"DE",
    "sg:address":"Ulmenstr. 11",
    "sg:city":"Bar\u00dfel",
    "sg:phone":"+49 4499/74101",
    "sg:postcode":"26676",
    "sg:province":"Niedersachsen",
    "wof:name":"Hans Weerts",
    "wof:placetype":"venue"
},
  "geometry": {"coordinates":[7.764724,53.163795],"type":"Point"}
}