{
  "type": "Feature",
  "properties": {
    "iso:country":"DE",
    "sg:address":"Kreuzstr. 29",
    "sg:city":"Wassenberg",
    "sg:phone":"+49 2432/4365",
    "sg:postcode":"41849",
    "sg:province":"Nordrhein-Westfalen",
    "wof:name":"Wilfried K\u00fcppers",
    "wof:placetype":"venue"
},
  "geometry": {"coordinates":[6.099686,51.124527],"type":"Point"}
}