{
  "type": "Feature",
  "properties": {
    "iso:country":"DE",
    "sg:address":"F\u00e4rberg\u00e4ssel 1",
    "sg:city":"Oderwitz",
    "sg:phone":"+49 35842/25393",
    "sg:postcode":"02791",
    "sg:province":"Sachsen",
    "wof:name":"Heinz Christoph",
    "wof:placetype":"venue"
},
  "geometry": {"coordinates":[14.72211,50.958401],"type":"Point"}
}