{
  "type": "Feature",
  "properties": {
    "iso:country":"DE",
    "sg:address":"Hoppersheider Busch 17a",
    "sg:city":"Bergisch Gladbach",
    "sg:phone":"+49 2202/988700",
    "sg:postcode":"51467",
    "sg:province":"Nordrhein-Westfalen",
    "wof:name":"Ragas Dachdecker- Meisterbetrieb Gmbh",
    "wof:placetype":"venue"
},
  "geometry": {"coordinates":[7.070713,51.016167],"type":"Point"}
}