{
  "type": "Feature",
  "properties": {
    "iso:country":"DE",
    "sg:address":"Karlsbader Weg 2",
    "sg:city":"Isernhagen",
    "sg:phone":"+49 511/775636",
    "sg:postcode":"30916",
    "sg:province":"Niedersachsen",
    "wof:name":"Fritz Ernst",
    "wof:placetype":"venue"
},
  "geometry": {"coordinates":[9.7984209061,52.4568901062],"type":"Point"}
}