{
  "type": "Feature",
  "properties": {
    "iso:country":"DE",
    "sg:address":"Milchborntalweg 94",
    "sg:city":"Bergisch Gladbach",
    "sg:phone":"+49 2204/53839",
    "sg:postcode":"51429",
    "sg:province":"Nordrhein-Westfalen",
    "wof:name":"Peter Berghaus Tabakwaren Gh",
    "wof:placetype":"venue"
},
  "geometry": {"coordinates":[7.1654248238,50.9690589905],"type":"Point"}
}