{
  "type": "Feature",
  "properties": {
    "iso:country":"DE",
    "sg:address":"Kaiserstr. 20",
    "sg:city":"Neum\u00fcnster",
    "sg:phone":"+49 4321/45327",
    "sg:postcode":"24534",
    "sg:province":"Schleswig-Holstein",
    "wof:name":"Parkhaus Am Bahnhof",
    "wof:placetype":"venue"
},
  "geometry": {"coordinates":[9.9811954498,54.0750808716],"type":"Point"}
}