{
  "type": "Feature",
  "properties": {
    "iso:country":"DE",
    "sg:address":"Bahnhofstr. 2",
    "sg:city":"Lahnstein",
    "sg:phone":"+49 2621/61413",
    "sg:postcode":"56112",
    "sg:province":"Rheinland-Pfalz",
    "wof:name":"Bierstube",
    "wof:placetype":"venue"
},
  "geometry": {"coordinates":[7.6050200462,50.3098678589],"type":"Point"}
}