{
  "type": "Feature",
  "properties": {
    "iso:country":"DE",
    "sg:address":"Schopfheimer Str. 6",
    "sg:city":"Zell",
    "sg:phone":"+49 7625/272",
    "sg:postcode":"79669",
    "sg:province":"Baden-W\u00fcrttemberg",
    "wof:name":"C. Kist",
    "wof:placetype":"venue"
},
  "geometry": {"coordinates":[7.851915,47.706623],"type":"Point"}
}