{
  "type": "Feature",
  "properties": {
    "iso:country":"DE",
    "sg:address":"Leopoldstr. 108",
    "sg:city":"M\u00fcnchen",
    "sg:phone":"+49 89/346403",
    "sg:postcode":"80802",
    "sg:province":"Bayern",
    "wof:name":"Italy Restaurant Gmbh",
    "wof:placetype":"venue"
},
  "geometry": {"coordinates":[11.5865182877,48.1653633118],"type":"Point"}
}