{
  "type": "Feature",
  "properties": {
    "iso:country":"DE",
    "sg:address":"Rechts dem Albach 14",
    "sg:city":"Merxheim",
    "sg:postcode":"55627",
    "sg:province":"Rheinland-Pfalz",
    "wof:name":"Jbm Bau Gmbh",
    "wof:placetype":"venue"
},
  "geometry": {"coordinates":[7.5638298988,49.7966957092],"type":"Point"}
}