{
  "type": "Feature",
  "properties": {
    "iso:country":"DE",
    "sg:address":"Breite Str. 29",
    "sg:city":"Grevenbroich",
    "sg:phone":"+49 2181/659384",
    "sg:postcode":"41515",
    "sg:province":"Nordrhein-Westfalen",
    "wof:name":"Optik Und Mehr Grevenbroich Gmbh",
    "wof:placetype":"venue"
},
  "geometry": {"coordinates":[6.5891327858,51.0889167786],"type":"Point"}
}