{
  "type": "Feature",
  "properties": {
    "iso:country":"DE",
    "sg:address":"Hauptstr. 10",
    "sg:city":"Gars",
    "sg:phone":"+49 8073/1246",
    "sg:postcode":"83536",
    "sg:province":"Bayern",
    "wof:name":"Albert Ammer Drogerie",
    "wof:placetype":"venue"
},
  "geometry": {"coordinates":[12.276613,48.153252],"type":"Point"}
}