{
  "type": "Feature",
  "properties": {
    "iso:country":"DE",
    "sg:address":"Kirchweg 6",
    "sg:city":"Unterw\u00f6ssen",
    "sg:postcode":"83246",
    "sg:province":"Bayern",
    "wof:name":"Netlup Gmbh",
    "wof:placetype":"venue"
},
  "geometry": {"coordinates":[12.4599819183,47.7376251221],"type":"Point"}
}