{
  "type": "Feature",
  "properties": {
    "iso:country":"DE",
    "sg:address":"Burgstr. 7",
    "sg:city":"Kl\u00f6tze",
    "sg:phone":"+49 3909/3785",
    "sg:postcode":"38486",
    "sg:province":"Sachsen-Anhalt",
    "wof:name":"Hanns-christoph Heseler",
    "wof:placetype":"venue"
},
  "geometry": {"coordinates":[11.156823,52.625496],"type":"Point"}
}