{
  "type": "Feature",
  "properties": {
    "iso:country":"DE",
    "sg:address":"Georg-Ledebour-Str. 69",
    "sg:city":"N\u00fcrnberg",
    "sg:phone":"+49 911/804477",
    "sg:postcode":"90473",
    "sg:province":"Bayern",
    "wof:name":"Intershop Dr. Zoltan Guzi Gmbh",
    "wof:placetype":"venue"
},
  "geometry": {"coordinates":[11.152736,49.403225],"type":"Point"}
}