{
  "type": "Feature",
  "properties": {
    "iso:country":"DE",
    "sg:address":"B\u00fcrgermeister-Wohlfarth-Str. 4",
    "sg:city":"K\u00f6nigsbrunn",
    "sg:phone":"+49 8231/87568",
    "sg:postcode":"86343",
    "sg:province":"Bayern",
    "wof:name":"Royal Hausverwaltung Gmbh",
    "wof:placetype":"venue"
},
  "geometry": {"coordinates":[10.8912982941,48.2777557373],"type":"Point"}
}