{
  "type": "Feature",
  "properties": {
    "iso:country":"DE",
    "sg:address":"Westendstr.26",
    "sg:city":"M\u00f6rfelden-Walldorf",
    "sg:postcode":"64546",
    "sg:province":"Hessen",
    "wof:name":"Bundesvereinigung Gegen Flugl\u00e4rm E.v.",
    "wof:placetype":"venue"
},
  "geometry": {"coordinates":[8.5655822754,49.9742584229],"type":"Point"}
}