{
  "type": "Feature",
  "properties": {
    "iso:country":"DE",
    "sg:address":"Dittersbacher Weg 5",
    "sg:city":"Berlin",
    "sg:phone":"+49 30/76677967",
    "sg:postcode":"12247",
    "sg:province":"Berlin",
    "wof:name":"Foltin-bauausf\u00fchrungen Gmbh",
    "wof:placetype":"venue"
},
  "geometry": {"coordinates":[13.36425,52.43573],"type":"Point"}
}