{
  "type": "Feature",
  "properties": {
    "iso:country":"DE",
    "sg:address":"Brunnenstr. 7",
    "sg:city":"Bad Driburg",
    "sg:phone":"+49 5253/98420",
    "sg:postcode":"33014",
    "sg:province":"Nordrhein-Westfalen",
    "wof:name":"Hotel B\u00f6hler Inh. Brigitta B\u00f6hler",
    "wof:placetype":"venue"
},
  "geometry": {"coordinates":[9.0430984497,51.7354431152],"type":"Point"}
}