{
  "type": "Feature",
  "properties": {
    "iso:country":"DE",
    "sg:address":"Rubensallee 26",
    "sg:city":"Mainz",
    "sg:phone":"+49 6131/72577",
    "sg:postcode":"55127",
    "sg:province":"Rheinland-Pfalz",
    "wof:name":"Rudi Eichbladt Gmbh",
    "wof:placetype":"venue"
},
  "geometry": {"coordinates":[8.187678,49.964901],"type":"Point"}
}