{
  "type": "Feature",
  "properties": {
    "iso:country":"DE",
    "sg:address":"Marktplatz 11",
    "sg:city":"Teterow",
    "sg:phone":"+49 3996/120830",
    "sg:postcode":"17166",
    "sg:province":"Mecklenburg-Vorpommern",
    "wof:name":"Dr. Hultsch Rechtsanwalt",
    "wof:placetype":"venue"
},
  "geometry": {"coordinates":[12.5753316879,53.7735710144],"type":"Point"}
}