{
  "type": "Feature",
  "properties": {
    "iso:country":"DE",
    "sg:address":"Im Wied 2",
    "sg:city":"Barntrup",
    "sg:postcode":"32683",
    "sg:province":"Nordrhein-Westfalen",
    "wof:name":"Gwb-beteiligungs Gmbh",
    "wof:placetype":"venue"
},
  "geometry": {"coordinates":[9.126692,51.989346],"type":"Point"}
}