{
  "type": "Feature",
  "properties": {
    "iso:country":"DE",
    "sg:address":"Bl\u00fccherstr. 172",
    "sg:city":"Bacharach",
    "sg:phone":"+49 6743/2152",
    "sg:postcode":"55422",
    "sg:province":"Rheinland-Pfalz",
    "wof:name":"Jens Dragus Architekt",
    "wof:placetype":"venue"
},
  "geometry": {"coordinates":[7.75881,50.057388],"type":"Point"}
}