{
  "type": "Feature",
  "properties": {
    "iso:country":"DE",
    "sg:address":"Meppener Str. 140",
    "sg:city":"Lingen",
    "sg:phone":"+49 591/63081",
    "sg:postcode":"49808",
    "sg:province":"Niedersachsen",
    "wof:name":"Johannes P\u00f6lker",
    "wof:placetype":"venue"
},
  "geometry": {"coordinates":[7.2947998047,52.5396575928],"type":"Point"}
}