{
  "type": "Feature",
  "properties": {
    "iso:country":"DE",
    "sg:address":"Sophienstr. 45",
    "sg:city":"Baden-Baden",
    "sg:phone":"+49 7221/31044",
    "sg:postcode":"76530",
    "sg:province":"Baden-W\u00fcrttemberg",
    "wof:name":"Extra-blatt",
    "wof:placetype":"venue"
},
  "geometry": {"coordinates":[8.2435178757,48.7629394531],"type":"Point"}
}