{
  "type": "Feature",
  "properties": {
    "iso:country":"DE",
    "sg:address":"Bahnhofstr. 22c",
    "sg:city":"Borken",
    "sg:phone":"+49 2861/66283",
    "sg:postcode":"46325",
    "sg:province":"Nordrhein-Westfalen",
    "wof:name":"U. Kowalski",
    "wof:placetype":"venue"
},
  "geometry": {"coordinates":[6.8645200729,51.8486633301],"type":"Point"}
}