{
  "type": "Feature",
  "properties": {
    "iso:country":"DE",
    "sg:address":"Kn\u00e4ppenstr. 66",
    "sg:city":"Delbr\u00fcck",
    "sg:phone":"+49 2944/7404",
    "sg:postcode":"33129",
    "sg:province":"Nordrhein-Westfalen",
    "wof:name":"G. Sch\u00e4fer",
    "wof:placetype":"venue"
},
  "geometry": {"coordinates":[8.443811,51.757442],"type":"Point"}
}