{
  "type": "Feature",
  "properties": {
    "iso:country":"DE",
    "sg:address":"K\u00f6llner Str. 22",
    "sg:city":"Riegelsberg",
    "sg:phone":"+49 6806/2781",
    "sg:postcode":"66292",
    "sg:province":"Saarland",
    "wof:name":"Raber Bestattungen Gmbh",
    "wof:placetype":"venue"
},
  "geometry": {"coordinates":[6.926299,49.29715],"type":"Point"}
}