{
  "type": "Feature",
  "properties": {
    "iso:country":"DE",
    "sg:address":"Burgstr. 3",
    "sg:city":"Neuhaus",
    "sg:phone":"+49 9156/96226",
    "sg:postcode":"91284",
    "sg:province":"Bayern",
    "wof:name":"Lehmann H. Und P. Meng",
    "wof:placetype":"venue"
},
  "geometry": {"coordinates":[11.549229,49.628284],"type":"Point"}
}