{
  "type": "Feature",
  "properties": {
    "iso:country":"DE",
    "sg:address":"Heiligenstadt 18",
    "sg:city":"Neustadt",
    "sg:phone":"+49 9445/95370",
    "sg:postcode":"93333",
    "sg:province":"Bayern",
    "wof:name":"Johann Kr\u00f6ner",
    "wof:placetype":"venue"
},
  "geometry": {"coordinates":[11.791598,48.815216],"type":"Point"}
}