{
  "type": "Feature",
  "properties": {
    "iso:country":"DE",
    "sg:address":"Reckeweg 56",
    "sg:city":"Berlin",
    "sg:phone":"+49 30/93770140",
    "sg:postcode":"13591",
    "sg:province":"Berlin",
    "wof:name":"Muk Medien- Und Kommunikationsges. Mbh",
    "wof:placetype":"venue"
},
  "geometry": {"coordinates":[13.1606063843,52.5434913635],"type":"Point"}
}