{
  "type": "Feature",
  "properties": {
    "iso:country":"DE",
    "sg:address":"Langgasse 215",
    "sg:city":"Ha\u00dfloch",
    "sg:phone":"+49 6324/989213",
    "sg:postcode":"67454",
    "sg:province":"Rheinland-Pfalz",
    "wof:name":"Werner L\u00f6chner",
    "wof:placetype":"venue"
},
  "geometry": {"coordinates":[8.268346,49.364975],"type":"Point"}
}