{
  "type": "Feature",
  "properties": {
    "iso:country":"DE",
    "sg:address":"Edelsbergstr. 6",
    "sg:city":"M\u00fcnchen",
    "sg:phone":"+49 89/570080",
    "sg:postcode":"80686",
    "sg:province":"Bayern",
    "wof:name":"Ckv Verm\u00f6gensverwaltung Gmbh",
    "wof:placetype":"venue"
},
  "geometry": {"coordinates":[11.520522,48.125484],"type":"Point"}
}