{
  "type": "Feature",
  "properties": {
    "iso:country":"DE",
    "sg:address":"Agrippastr. 5",
    "sg:city":"Mainz",
    "sg:phone":"+49 6131/224732",
    "sg:postcode":"55131",
    "sg:province":"Rheinland-Pfalz",
    "wof:name":"J & G Fenster- Profilsysteme Gmbh",
    "wof:placetype":"venue"
},
  "geometry": {"coordinates":[8.267748,49.992641],"type":"Point"}
}