{
  "type": "Feature",
  "properties": {
    "iso:country":"DE",
    "sg:address":"Robert-Schumann-Str. 24",
    "sg:city":"Ronneburg",
    "sg:phone":"+49 36602/34657",
    "sg:postcode":"07580",
    "sg:province":"Th\u00fcringen",
    "wof:name":"Gwg Wohnungsbaugenossenschaft Ronneburg Eg",
    "wof:placetype":"venue"
},
  "geometry": {"coordinates":[12.1878890991,50.8663597107],"type":"Point"}
}