{
  "type": "Feature",
  "properties": {
    "iso:country":"DE",
    "sg:address":"Teckstr. 11",
    "sg:city":"Pliezhausen",
    "sg:phone":"+49 7127/71477",
    "sg:postcode":"72124",
    "sg:province":"Baden-W\u00fcrttemberg",
    "wof:name":"Dr. Hans Baur Tierarzt",
    "wof:placetype":"venue"
},
  "geometry": {"coordinates":[9.2094659805,48.5650520325],"type":"Point"}
}