{
  "type": "Feature",
  "properties": {
    "iso:country":"DE",
    "sg:address":"Stammheimer Str. 23",
    "sg:city":"Altenstadt",
    "sg:phone":"+49 6047/67311",
    "sg:postcode":"63674",
    "sg:province":"Hessen",
    "wof:name":"Netzsch Ger\u00e4tebau Gmbh",
    "wof:placetype":"venue"
},
  "geometry": {"coordinates":[8.9448,50.288258],"type":"Point"}
}