{
  "type": "Feature",
  "properties": {
    "iso:country":"DE",
    "sg:address":"Im Wiblinger Hart 6",
    "sg:city":"ULM",
    "sg:postcode":"89079",
    "sg:province":"Baden-W\u00fcrttemberg",
    "wof:name":"Biblium - Das Buch Der Sieben Siegel",
    "wof:placetype":"venue"
},
  "geometry": {"coordinates":[9.97367,48.346207],"type":"Point"}
}