{
  "type": "Feature",
  "properties": {
    "iso:country":"DE",
    "sg:address":"Rheinstr. 45",
    "sg:city":"Wiesbaden",
    "sg:phone":"+49 611/305020",
    "sg:postcode":"65185",
    "sg:province":"Hessen",
    "wof:name":"Viktoria-apotheke",
    "wof:placetype":"venue"
},
  "geometry": {"coordinates":[8.23908,50.077957],"type":"Point"}
}