{
  "type": "Feature",
  "properties": {
    "iso:country":"DE",
    "sg:address":"Fraunhoferstr. 42",
    "sg:city":"M\u00fcnchen",
    "sg:phone":"+49 89/2016865",
    "sg:postcode":"80469",
    "sg:province":"Bayern",
    "wof:name":"B. P\u00f6ss-schronk",
    "wof:placetype":"venue"
},
  "geometry": {"coordinates":[11.575538,48.128201],"type":"Point"}
}