{
  "type": "Feature",
  "properties": {
    "iso:country":"DE",
    "sg:address":"\u00d6lbergstr. 12",
    "sg:city":"Balingen",
    "sg:phone":"+49 7433/91540",
    "sg:postcode":"72336",
    "sg:province":"Baden-W\u00fcrttemberg",
    "wof:name":"Sch\u00e4fer-heinric Und Friedemann Rechtsanw\u00e4lte",
    "wof:placetype":"venue"
},
  "geometry": {"coordinates":[8.8524217606,48.2735366821],"type":"Point"}
}