{
  "type": "Feature",
  "properties": {
    "iso:country":"DE",
    "sg:address":"In 'ne Stadt 12",
    "sg:city":"Schee\u00dfel",
    "sg:phone":"+49 4263/2599",
    "sg:postcode":"27383",
    "sg:province":"Niedersachsen",
    "wof:name":"Walter Behrens",
    "wof:placetype":"venue"
},
  "geometry": {"coordinates":[9.50579,53.177231],"type":"Point"}
}