{
  "type": "Feature",
  "properties": {
    "iso:country":"DE",
    "sg:address":"Leipziger Str. 55",
    "sg:city":"Rackwitz",
    "sg:phone":"+49 34294/76294",
    "sg:postcode":"04519",
    "sg:province":"Sachsen",
    "wof:name":"Rackwitzer Dienstleistung- Und Service Gmbh",
    "wof:placetype":"venue"
},
  "geometry": {"coordinates":[12.3838176727,51.4351501465],"type":"Point"}
}