{
  "type": "Feature",
  "properties": {
    "iso:country":"DE",
    "sg:address":"Zum Niederntor 13",
    "sg:city":"Springe",
    "sg:phone":"+49 5041/5023",
    "sg:postcode":"31832",
    "sg:province":"Niedersachsen",
    "wof:name":"Hotel Zum Wisent",
    "wof:placetype":"venue"
},
  "geometry": {"coordinates":[9.556851387,52.2093086243],"type":"Point"}
}