{
  "type": "Feature",
  "properties": {
    "iso:country":"DE",
    "sg:address":"Goethestr. 11a",
    "sg:city":"Anr\u00f6chte",
    "sg:phone":"+49 2947/970350",
    "sg:postcode":"59609",
    "sg:province":"Nordrhein-Westfalen",
    "wof:name":"B\u00f6rde-ei Eierkontor Anr\u00f6chte Gmbh",
    "wof:placetype":"venue"
},
  "geometry": {"coordinates":[8.3252515793,51.5616569519],"type":"Point"}
}