{
  "type": "Feature",
  "properties": {
    "iso:country":"DE",
    "sg:address":"Gottlieb-Daimler-Str. 6",
    "sg:city":"Waldstetten",
    "sg:phone":"+49 7171/947740",
    "sg:postcode":"73550",
    "sg:province":"Baden-W\u00fcrttemberg",
    "wof:name":"Abele Maschinen- Und Apparatebau Gmbh",
    "wof:placetype":"venue"
},
  "geometry": {"coordinates":[9.832597,48.770046],"type":"Point"}
}