{
  "type": "Feature",
  "properties": {
    "iso:country":"DE",
    "sg:address":"Hohensteiner Hof",
    "sg:city":"Sonnenberg-Winnenberg",
    "sg:phone":"+49 6787/337",
    "sg:postcode":"55767",
    "sg:province":"Rheinland-Pfalz",
    "wof:name":"Erhard Lommatzsch",
    "wof:placetype":"venue"
},
  "geometry": {"coordinates":[7.2698259354,49.6743125916],"type":"Point"}
}