{
  "type": "Feature",
  "properties": {
    "iso:country":"DE",
    "sg:address":"Gerberstr. 8",
    "sg:city":"Schee\u00dfel",
    "sg:phone":"+49 4263/8344",
    "sg:postcode":"27383",
    "sg:province":"Niedersachsen",
    "wof:name":"Objektbau-baubetreuung- Schee\u00dfel Gmbh",
    "wof:placetype":"venue"
},
  "geometry": {"coordinates":[9.4799585342,53.1765365601],"type":"Point"}
}