{
  "type": "Feature",
  "properties": {
    "iso:country":"DE",
    "sg:address":"Vorgebirgstr. 1",
    "sg:city":"K\u00f6ln",
    "sg:phone":"+49 221/311724",
    "sg:postcode":"50677",
    "sg:province":"Nordrhein-Westfalen",
    "wof:name":"H. Lux",
    "wof:placetype":"venue"
},
  "geometry": {"coordinates":[6.952172,50.922718],"type":"Point"}
}