{
  "type": "Feature",
  "properties": {
    "iso:country":"DE",
    "sg:address":"Schlo\u00dfdom\u00e4ne",
    "sg:city":"Wolmirstedt",
    "sg:postcode":"39326",
    "sg:province":"Sachsen-Anhalt",
    "wof:name":"Stadt- Und Kreisbibliothek",
    "wof:placetype":"venue"
},
  "geometry": {"coordinates":[11.628433,52.246105],"type":"Point"}
}