{
  "type": "Feature",
  "properties": {
    "iso:country":"DE",
    "sg:address":"Moritzburger Str. 8",
    "sg:city":"Dresden",
    "sg:postcode":"01127",
    "sg:province":"Sachsen",
    "wof:name":"B. Thalheim",
    "wof:placetype":"venue"
},
  "geometry": {"coordinates":[13.724573,51.072861],"type":"Point"}
}