{
  "type": "Feature",
  "properties": {
    "iso:country":"DE",
    "sg:address":"Georgenstr. 8",
    "sg:city":"Grafing",
    "sg:phone":"+49 8092/7282",
    "sg:postcode":"85567",
    "sg:province":"Bayern",
    "wof:name":"H\u00fcls Gmbh",
    "wof:placetype":"venue"
},
  "geometry": {"coordinates":[11.907346,48.020782],"type":"Point"}
}