{
  "type": "Feature",
  "properties": {
    "iso:country":"DE",
    "sg:address":"Am Erlengraben 10",
    "sg:city":"Ettlingen",
    "sg:phone":"+49 7243/71030",
    "sg:postcode":"76275",
    "sg:province":"Baden-W\u00fcrttemberg",
    "wof:name":"Elco Papier Gmbh",
    "wof:placetype":"venue"
},
  "geometry": {"coordinates":[8.391327858,48.9518356323],"type":"Point"}
}