{
  "type": "Feature",
  "properties": {
    "iso:country":"DE",
    "sg:city":"Tacherting",
    "sg:phone":"+49 8621/2006",
    "sg:postcode":"83342",
    "sg:province":"Bayern",
    "wof:name":"Volksbank Trostberg Eg",
    "wof:placetype":"venue"
},
  "geometry": {"coordinates":[12.56877,48.078403],"type":"Point"}
}