{
  "type": "Feature",
  "properties": {
    "iso:country":"DE",
    "sg:address":"Hauptstr. 5",
    "sg:city":"Postbauer-Heng",
    "sg:phone":"+49 9188/680",
    "sg:postcode":"92353",
    "sg:province":"Bayern",
    "wof:name":"Schlo\u00df-apotheke Postbauer-heng",
    "wof:placetype":"venue"
},
  "geometry": {"coordinates":[11.351992,49.31266],"type":"Point"}
}