{
  "type": "Feature",
  "properties": {
    "iso:country":"DE",
    "sg:address":"Thieder Weg 2",
    "sg:city":"Wolfenb\u00fcttel",
    "sg:phone":"+49 5331/904070",
    "sg:postcode":"38304",
    "sg:province":"Niedersachsen",
    "wof:name":"R. Huck",
    "wof:placetype":"venue"
},
  "geometry": {"coordinates":[10.4856624603,52.1634902954],"type":"Point"}
}