{
  "type": "Feature",
  "properties": {
    "iso:country":"DE",
    "sg:address":"Schulstr 3::",
    "sg:city":"Steisslingen",
    "sg:postcode":"78256",
    "sg:province":"Baden-W\u00fcrttemberg",
    "wof:name":"Volksbank Steisslingen Eg",
    "wof:placetype":"venue"
},
  "geometry": {"coordinates":[8.92496,47.79858],"type":"Point"}
}