{
  "type": "Feature",
  "properties": {
    "iso:country":"DE",
    "sg:address":"Homburger Str. 11",
    "sg:city":"Glan-M\u00fcnchweiler",
    "sg:phone":"+49 6383/6688",
    "sg:postcode":"66907",
    "sg:province":"Rheinland-Pfalz",
    "wof:name":"Treffpunkt",
    "wof:placetype":"venue"
},
  "geometry": {"coordinates":[7.4436497688,49.4694137573],"type":"Point"}
}