{
  "type": "Feature",
  "properties": {
    "iso:country":"DE",
    "sg:address":"An'n Tiebarg 8a",
    "sg:city":"Lentf\u00f6hrden",
    "sg:phone":"+49 4192/4309",
    "sg:postcode":"24632",
    "sg:province":"Schleswig-Holstein",
    "wof:name":"Uwe Looft B\u00e4ckerei",
    "wof:placetype":"venue"
},
  "geometry": {"coordinates":[9.88862,53.870331],"type":"Point"}
}