{
  "type": "Feature",
  "properties": {
    "iso:country":"DE",
    "sg:address":"Ekelser Str. 82",
    "sg:city":"S\u00fcdbrookmerland",
    "sg:phone":"+49 4942/4590",
    "sg:postcode":"26624",
    "sg:province":"Niedersachsen",
    "wof:name":"J. Wilts",
    "wof:placetype":"venue"
},
  "geometry": {"coordinates":[7.3777499199,53.4680480957],"type":"Point"}
}