{
  "type": "Feature",
  "properties": {
    "iso:country":"DE",
    "sg:address":"Ober Kochs 15",
    "sg:city":"Pittenbach",
    "sg:postcode":"54595",
    "sg:province":"Rheinland-Pfalz",
    "wof:name":"Agrarhandel Pittenbach Gmbh",
    "wof:placetype":"venue"
},
  "geometry": {"coordinates":[6.3444170952,50.1778411865],"type":"Point"}
}