{
  "type": "Feature",
  "properties": {
    "iso:country":"DE",
    "sg:address":"Almsstr. 34",
    "sg:city":"Hildesheim",
    "sg:phone":"+49 5121/133316",
    "sg:postcode":"31134",
    "sg:province":"Niedersachsen",
    "wof:name":"L Tur Tourismus Ag",
    "wof:placetype":"venue"
},
  "geometry": {"coordinates":[9.9519462585,52.1551246643],"type":"Point"}
}