{
  "type": "Feature",
  "properties": {
    "iso:country":"DE",
    "sg:address":"Georg-Herwegh-Str. 7",
    "sg:city":"Greiz",
    "sg:phone":"+49 3661/63332",
    "sg:postcode":"07973",
    "sg:province":"Th\u00fcringen",
    "wof:name":"M. Michel",
    "wof:placetype":"venue"
},
  "geometry": {"coordinates":[12.2178506851,50.6541862488],"type":"Point"}
}