{
  "type": "Feature",
  "properties": {
    "iso:country":"DE",
    "sg:address":"Scheffelstr. 11",
    "sg:city":"Bad D\u00fcrrheim",
    "sg:phone":"+49 7726/7553",
    "sg:postcode":"78073",
    "sg:province":"Baden-W\u00fcrttemberg",
    "wof:name":"Gastst\u00e4tte Sternen-schenke",
    "wof:placetype":"venue"
},
  "geometry": {"coordinates":[8.5282726288,48.0208511353],"type":"Point"}
}