{
  "type": "Feature",
  "properties": {
    "iso:country":"DE",
    "sg:address":"Kerpener Str. 107",
    "sg:city":"Elsdorf",
    "sg:phone":"+49 2274/905061",
    "sg:postcode":"50189",
    "sg:province":"Nordrhein-Westfalen",
    "wof:name":"Freizeitverein Berrendorf Kurt Rosenkranz",
    "wof:placetype":"venue"
},
  "geometry": {"coordinates":[6.5892601013,50.9195022583],"type":"Point"}
}