{
  "type": "Feature",
  "properties": {
    "iso:country":"DE",
    "sg:address":"Rannische Str. 13",
    "sg:city":"Halle",
    "sg:phone":"+49 345/2901302",
    "sg:postcode":"06108",
    "sg:province":"Sachsen-Anhalt",
    "wof:name":"Hopfgarten",
    "wof:placetype":"venue"
},
  "geometry": {"coordinates":[11.970502,51.478741],"type":"Point"}
}