{
  "type": "Feature",
  "properties": {
    "iso:country":"DE",
    "sg:address":"Engelblecker Str. 2b",
    "sg:city":"M\u00f6nchengladbach",
    "sg:phone":"+49 2161/814930",
    "sg:postcode":"41066",
    "sg:province":"Nordrhein-Westfalen",
    "wof:name":"Meisterbetrieb F\u00fcr M\u00f6bel Und Innenausbau",
    "wof:placetype":"venue"
},
  "geometry": {"coordinates":[6.462790966,51.2110366821],"type":"Point"}
}