{
  "type": "Feature",
  "properties": {
    "iso:country":"DE",
    "sg:address":"Ostergasse 40",
    "sg:city":"Saulheim",
    "sg:phone":"+49 6732/5443",
    "sg:postcode":"55291",
    "sg:province":"Rheinland-Pfalz",
    "wof:name":"Rudolf Th\u00f6rle",
    "wof:placetype":"venue"
},
  "geometry": {"coordinates":[8.1515960693,49.8788032532],"type":"Point"}
}