{
  "type": "Feature",
  "properties": {
    "iso:country":"DE",
    "sg:address":"Kiefernstr. 46",
    "sg:city":"Selm",
    "sg:phone":"+49 2592/20702",
    "sg:postcode":"59379",
    "sg:province":"Nordrhein-Westfalen",
    "wof:name":"N. Gringel",
    "wof:placetype":"venue"
},
  "geometry": {"coordinates":[7.459774,51.694523],"type":"Point"}
}