{
  "type": "Feature",
  "properties": {
    "iso:country":"DE",
    "sg:address":"Menzinger Str. 8",
    "sg:city":"M\u00fcnchen",
    "sg:phone":"+49 89/173872",
    "sg:postcode":"80638",
    "sg:province":"Bayern",
    "wof:name":"Pohl Gmbh",
    "wof:placetype":"venue"
},
  "geometry": {"coordinates":[11.51177,48.159622],"type":"Point"}
}