{
  "type": "Feature",
  "properties": {
    "iso:country":"DE",
    "sg:address":"Jahnstr. 23 b",
    "sg:city":"Queidersbach",
    "sg:phone":"+49 6371/13891",
    "sg:postcode":"66851",
    "sg:province":"Rheinland-Pfalz",
    "wof:name":"Mehrzweckhalle",
    "wof:placetype":"venue"
},
  "geometry": {"coordinates":[7.637817,49.374916],"type":"Point"}
}