{
  "type": "Feature",
  "properties": {
    "iso:country":"DE",
    "sg:address":"Hopfenstr. 19",
    "sg:city":"M\u00fcnchsteinach",
    "sg:phone":"+49 9166/706",
    "sg:postcode":"91481",
    "sg:province":"Bayern",
    "wof:name":"Tbs Technisches B\u00fcro Helene Stelzer",
    "wof:placetype":"venue"
},
  "geometry": {"coordinates":[10.5965137482,49.6420326233],"type":"Point"}
}