{
  "type": "Feature",
  "properties": {
    "iso:country":"DE",
    "sg:address":"Ardennenstr. 32",
    "sg:city":"Aachen",
    "sg:phone":"+49 2408/81476",
    "sg:postcode":"52076",
    "sg:province":"Nordrhein-Westfalen",
    "wof:name":"Helmut Hennes",
    "wof:placetype":"venue"
},
  "geometry": {"coordinates":[6.1648168564,50.692855835],"type":"Point"}
}