{
  "type": "Feature",
  "properties": {
    "iso:country":"DE",
    "sg:address":"zum G\u00e4rtling 5",
    "sg:city":"St. Wendel",
    "sg:phone":"+49 6851",
    "sg:postcode":"66606",
    "sg:province":"Saarland",
    "wof:name":"Pre Print Service Gmbh",
    "wof:placetype":"venue"
},
  "geometry": {"coordinates":[7.120469,49.43803],"type":"Point"}
}