{
  "type": "Feature",
  "properties": {
    "iso:country":"DE",
    "sg:address":"An der Schulenburg 4",
    "sg:city":"Bersenbr\u00fcck",
    "sg:phone":"+49 5439/1402",
    "sg:postcode":"49593",
    "sg:province":"Niedersachsen",
    "wof:name":"Parske Funkenerosion Gmbh",
    "wof:placetype":"venue"
},
  "geometry": {"coordinates":[7.963137,52.558659],"type":"Point"}
}