{
  "type": "Feature",
  "properties": {
    "iso:country":"DE",
    "sg:address":"M\u00fcnsterstr. 25",
    "sg:city":"Telgte",
    "sg:phone":"+49 2504/1836",
    "sg:postcode":"48291",
    "sg:province":"Nordrhein-Westfalen",
    "wof:name":"Andreas Schmitz Gmbh",
    "wof:placetype":"venue"
},
  "geometry": {"coordinates":[7.778024,51.983963],"type":"Point"}
}