{
  "type": "Feature",
  "properties": {
    "iso:country":"DE",
    "sg:address":"Am Schm\u00f6ningsberg 4",
    "sg:city":"Haltern",
    "sg:postcode":"45721",
    "sg:province":"Nordrhein-Westfalen",
    "wof:name":"Conch Gmbh",
    "wof:placetype":"venue"
},
  "geometry": {"coordinates":[7.1123270988,51.7192993164],"type":"Point"}
}