{
  "type": "Feature",
  "properties": {
    "iso:country":"DE",
    "sg:address":"Georg-Wulf-Str. 4-6",
    "sg:city":"Bremen",
    "sg:postcode":"28199",
    "sg:province":"Bremen",
    "wof:name":"Scaraboo Gmbh",
    "wof:placetype":"venue"
},
  "geometry": {"coordinates":[8.78681,53.057312],"type":"Point"}
}