{
  "type": "Feature",
  "properties": {
    "iso:country":"DE",
    "sg:address":"Kurze Str. 10",
    "sg:city":"Stendal",
    "sg:phone":"+49 3931/212426",
    "sg:postcode":"39576",
    "sg:province":"Sachsen-Anhalt",
    "wof:name":"Raiffeisen-warengenossenschaft Stendal Eg",
    "wof:placetype":"venue"
},
  "geometry": {"coordinates":[11.860824585,52.6062316895],"type":"Point"}
}