{
  "type": "Feature",
  "properties": {
    "iso:country":"DE",
    "sg:address":"Am Holzacker 71",
    "sg:city":"Schwabach",
    "sg:phone":"+49 911/6320314",
    "sg:postcode":"91126",
    "sg:province":"Bayern",
    "wof:name":"A. Bitterwolf Immobilienmakler",
    "wof:placetype":"venue"
},
  "geometry": {"coordinates":[11.019071579,49.3581581116],"type":"Point"}
}