{
  "type": "Feature",
  "properties": {
    "iso:country":"DE",
    "sg:address":"Ringstr. 2",
    "sg:city":"Esterwegen",
    "sg:phone":"+49 5955/93100",
    "sg:postcode":"26897",
    "sg:province":"Niedersachsen",
    "wof:name":"Raiffeisen",
    "wof:placetype":"venue"
},
  "geometry": {"coordinates":[7.6232938766,52.9742660522],"type":"Point"}
}