{
  "type": "Feature",
  "properties": {
    "iso:country":"DE",
    "sg:address":"Gwinnerstr. 38",
    "sg:city":"Frankfurt",
    "sg:postcode":"60388",
    "sg:province":"Hessen",
    "wof:name":"Tt Nutzfahrzeuge Service Gmbh",
    "wof:placetype":"venue"
},
  "geometry": {"coordinates":[8.7371768951,50.1388168335],"type":"Point"}
}