{
  "type": "Feature",
  "properties": {
    "iso:country":"DE",
    "sg:address":"Pfannestiel 8",
    "sg:city":"Schwabach",
    "sg:phone":"+49 9122/634667",
    "sg:postcode":"91126",
    "sg:province":"Bayern",
    "wof:name":"Pro Beratungs- Vertriebs- Und Baugesellschaft Mbh",
    "wof:placetype":"venue"
},
  "geometry": {"coordinates":[11.069242,49.324665],"type":"Point"}
}