{
  "type": "Feature",
  "properties": {
    "iso:country":"DE",
    "sg:address":"Philipp-Reis-Str 13",
    "sg:city":"M\u00fcnchen",
    "sg:phone":"+49 89/8970120",
    "sg:postcode":"81479",
    "sg:province":"Bayern",
    "wof:name":"Rohrer Gmbh",
    "wof:placetype":"venue"
},
  "geometry": {"coordinates":[11.5267848969,48.0849304199],"type":"Point"}
}