{
  "type": "Feature",
  "properties": {
    "iso:country":"DE",
    "sg:address":"Luisenstr. 37",
    "sg:city":"St. Georgen",
    "sg:phone":"+49 7724/6689",
    "sg:postcode":"78112",
    "sg:province":"Baden-W\u00fcrttemberg",
    "wof:name":"Irmgard King",
    "wof:placetype":"venue"
},
  "geometry": {"coordinates":[8.323857,48.125881],"type":"Point"}
}