{
  "type": "Feature",
  "properties": {
    "iso:country":"DE",
    "sg:address":"Osterstr. 7 A",
    "sg:city":"Barsinghausen",
    "sg:phone":"+49 5105/52650",
    "sg:postcode":"30890",
    "sg:province":"Niedersachsen",
    "wof:name":"J\u00fcrgen Sch\u00e4fer",
    "wof:placetype":"venue"
},
  "geometry": {"coordinates":[9.4667339325,52.3018074036],"type":"Point"}
}