{
  "type": "Feature",
  "properties": {
    "iso:country":"DE",
    "sg:address":"Kantstr. 24 A",
    "sg:city":"Neustadt",
    "sg:phone":"+49 9568/2931",
    "sg:postcode":"96465",
    "sg:province":"Bayern",
    "wof:name":"Hans Ohlen",
    "wof:placetype":"venue"
},
  "geometry": {"coordinates":[8.797411,53.067226],"type":"Point"}
}