{
  "type": "Feature",
  "properties": {
    "iso:country":"DE",
    "sg:address":"Hauptstr. 35",
    "sg:city":"Erbach",
    "sg:phone":"+49 6062/3104",
    "sg:postcode":"64711",
    "sg:province":"Hessen",
    "wof:name":"Dieter Kollmer",
    "wof:placetype":"venue"
},
  "geometry": {"coordinates":[8.9927,49.659622],"type":"Point"}
}