{
  "type": "Feature",
  "properties": {
    "iso:country":"DE",
    "sg:address":"Peterstr. 54",
    "sg:city":"D\u00fcren",
    "sg:phone":"+49 2421/887288",
    "sg:postcode":"52353",
    "sg:province":"Nordrhein-Westfalen",
    "wof:name":"Evia Grill",
    "wof:placetype":"venue"
},
  "geometry": {"coordinates":[6.4249458313,50.8471488953],"type":"Point"}
}