{
  "type": "Feature",
  "properties": {
    "iso:country":"DE",
    "sg:address":"Hauptstr. 113",
    "sg:city":"Starzach",
    "sg:phone":"+49 7483/448",
    "sg:postcode":"72181",
    "sg:province":"Baden-W\u00fcrttemberg",
    "wof:name":"I. Lohmiller",
    "wof:placetype":"venue"
},
  "geometry": {"coordinates":[8.8195905685,48.4287109375],"type":"Point"}
}