{
  "type": "Feature",
  "properties": {
    "iso:country":"DE",
    "sg:address":"Hauptstr. 412",
    "sg:city":"K\u00f6nigswinter",
    "sg:phone":"+49 2223/21880",
    "sg:postcode":"53639",
    "sg:province":"Nordrhein-Westfalen",
    "wof:name":"Kath. Pfarramt St. Remigius",
    "wof:placetype":"venue"
},
  "geometry": {"coordinates":[7.1941990852,50.6738204956],"type":"Point"}
}