{
  "type": "Feature",
  "properties": {
    "iso:country":"DE",
    "sg:address":"Banksstr.",
    "sg:city":"Hamburg",
    "sg:phone":"+49 40/3095170",
    "sg:postcode":"20097",
    "sg:province":"Hamburg",
    "wof:name":"Flc Fruchthandels- Gmbh & Co. Kg",
    "wof:placetype":"venue"
},
  "geometry": {"coordinates":[10.0149450302,53.5441360474],"type":"Point"}
}