{
  "type": "Feature",
  "properties": {
    "iso:country":"DE",
    "sg:address":"M\u00f6rfelder Str. 23 a",
    "sg:city":"M\u00f6rfelden-Walldorf",
    "sg:phone":"+49 6105/75953",
    "sg:postcode":"64546",
    "sg:province":"Hessen",
    "wof:name":"Thiel Logistics Gmbh",
    "wof:placetype":"venue"
},
  "geometry": {"coordinates":[8.5704879761,49.9999427795],"type":"Point"}
}