{
  "type": "Feature",
  "properties": {
    "iso:country":"DE",
    "sg:address":"Carl-Hopp-Str 9",
    "sg:city":"Rostock",
    "sg:phone":"+49 381/82780",
    "sg:postcode":"18069",
    "sg:province":"Mecklenburg-Vorpommern",
    "wof:name":"Niessen / Nikolaizig Gbr",
    "wof:placetype":"venue"
},
  "geometry": {"coordinates":[12.0970563889,54.0985107422],"type":"Point"}
}