{
  "type": "Feature",
  "properties": {
    "iso:country":"DE",
    "sg:address":"Im Steingebi\u00df 9",
    "sg:city":"Landau",
    "sg:phone":"+49 6341/60939",
    "sg:postcode":"76829",
    "sg:province":"Rheinland-Pfalz",
    "wof:name":"Rudolf Meier Architekt",
    "wof:placetype":"venue"
},
  "geometry": {"coordinates":[8.107676,49.208355],"type":"Point"}
}