{
  "type": "Feature",
  "properties": {
    "iso:country":"DE",
    "sg:address":"Zum Wei\u00dfen Pferd 8",
    "sg:city":"L\u00fcdenscheid",
    "sg:phone":"+49 2351/22760",
    "sg:postcode":"58507",
    "sg:province":"Nordrhein-Westfalen",
    "wof:name":"Theodor Mehr",
    "wof:placetype":"venue"
},
  "geometry": {"coordinates":[7.6309819221,51.2246284485],"type":"Point"}
}