{
  "type": "Feature",
  "properties": {
    "iso:country":"DE",
    "sg:address":"Fritz-Bauer-Str. 13",
    "sg:city":"Altdorf",
    "sg:postcode":"90518",
    "sg:province":"Bayern",
    "wof:name":"Taw Cert Zertifizierungs Gmbh",
    "wof:placetype":"venue"
},
  "geometry": {"coordinates":[11.3863096237,49.3931884766],"type":"Point"}
}