{
  "type": "Feature",
  "properties": {
    "iso:country":"DE",
    "sg:city":"Bayern",
    "sg:postcode":"90000",
    "wof:name":"Enfal",
    "wof:placetype":"venue"
},
  "geometry": {"coordinates":[11.40798,48.917431],"type":"Point"}
}