{
  "type": "Feature",
  "properties": {
    "iso:country":"DE",
    "sg:address":"Am Ohlenst\u00fcck 38",
    "sg:city":"Frankfurt",
    "sg:phone":"+49 6101/4682",
    "sg:postcode":"60437",
    "sg:province":"Hessen",
    "wof:name":"Ges. F\u00fcr Direktwerbung Mbh",
    "wof:placetype":"venue"
},
  "geometry": {"coordinates":[8.6735982895,50.1995658875],"type":"Point"}
}