{
  "type": "Feature",
  "properties": {
    "iso:country":"DE",
    "sg:address":"Am Bahnhof 25",
    "sg:city":"M\u00fchltroff",
    "sg:phone":"+49 3663/423058",
    "sg:postcode":"07919",
    "sg:province":"Th\u00fcringen",
    "wof:name":"A. Zscherpel",
    "wof:placetype":"venue"
},
  "geometry": {"coordinates":[11.934595108,50.5415229797],"type":"Point"}
}