{
  "type": "Feature",
  "properties": {
    "iso:country":"DE",
    "sg:address":"Lohbr\u00fcgger Landstr. 26",
    "sg:city":"Hamburg",
    "sg:phone":"+49 40/7215680",
    "sg:postcode":"21031",
    "sg:province":"Hamburg",
    "wof:name":"Taverna Alexandros",
    "wof:placetype":"venue"
},
  "geometry": {"coordinates":[10.2041435242,53.4971885681],"type":"Point"}
}