{
  "type": "Feature",
  "properties": {
    "iso:country":"DE",
    "sg:address":"Greifswalder Str. 43",
    "sg:city":"Hamburg",
    "sg:phone":"+49 40/249422",
    "sg:postcode":"20099",
    "sg:province":"Hamburg",
    "wof:name":"Restaurant Cox",
    "wof:placetype":"venue"
},
  "geometry": {"coordinates":[10.0118808746,53.5574951172],"type":"Point"}
}