{
  "type": "Feature",
  "properties": {
    "iso:country":"DE",
    "sg:address":"Leistenstr. 20",
    "sg:city":"W\u00fcrzburg",
    "sg:phone":"+49 931/7846967",
    "sg:postcode":"97082",
    "sg:province":"Bayern",
    "wof:name":"Bgg Bau\u00fcberwachungs- Gesellschaft Mbh",
    "wof:placetype":"venue"
},
  "geometry": {"coordinates":[9.920429,49.787842],"type":"Point"}
}