{
  "type": "Feature",
  "properties": {
    "iso:country":"DE",
    "sg:address":"H\u00f6rdtstr. 26",
    "sg:city":"Stuttgart",
    "sg:phone":"+49 711/873482",
    "sg:postcode":"70435",
    "sg:province":"Baden-W\u00fcrttemberg",
    "wof:name":"Gambrinus",
    "wof:placetype":"venue"
},
  "geometry": {"coordinates":[9.1726036072,48.8345909119],"type":"Point"}
}