{
  "type": "Feature",
  "properties": {
    "iso:country":"DE",
    "sg:address":"Marschnerstr. 27",
    "sg:city":"Dresden",
    "sg:phone":"+49 351/4412442",
    "sg:postcode":"01307",
    "sg:province":"Sachsen",
    "wof:name":"Katarina Maubach",
    "wof:placetype":"venue"
},
  "geometry": {"coordinates":[13.7579526901,51.0481910706],"type":"Point"}
}