{
  "type": "Feature",
  "properties": {
    "iso:country":"DE",
    "sg:address":"Winsener Str. 25",
    "sg:city":"Seevetal",
    "sg:phone":"+49 4105/82801",
    "sg:postcode":"21220",
    "sg:province":"Niedersachsen",
    "wof:name":"Aral Ag",
    "wof:placetype":"venue"
},
  "geometry": {"coordinates":[10.0429477692,53.3906440735],"type":"Point"}
}