{
  "type": "Feature",
  "properties": {
    "iso:country":"DE",
    "sg:address":"Berkeser Str. 21a",
    "sg:city":"Meiningen",
    "sg:postcode":"98617",
    "sg:province":"Th\u00fcringen",
    "wof:name":"Easy-pak Produktions- Und Vertriebs Gmbh",
    "wof:placetype":"venue"
},
  "geometry": {"coordinates":[10.3775577545,50.5550575256],"type":"Point"}
}