{
  "type": "Feature",
  "properties": {
    "iso:country":"DE",
    "sg:address":"Sachsenring 83",
    "sg:city":"K\u00f6ln",
    "sg:postcode":"50677",
    "sg:province":"Nordrhein-Westfalen",
    "wof:name":"Eagle Fonds Verwaltungs- Und Treuhand- Gmbh",
    "wof:placetype":"venue"
},
  "geometry": {"coordinates":[6.9485058784,50.9253044128],"type":"Point"}
}