{
  "type": "Feature",
  "properties": {
    "iso:country":"DE",
    "sg:address":"Goethestr. 22",
    "sg:city":"Zirndorf",
    "sg:phone":"+49 911/6001743",
    "sg:postcode":"90513",
    "sg:province":"Bayern",
    "wof:name":"Blank Asbestentsorgung Gmbh",
    "wof:placetype":"venue"
},
  "geometry": {"coordinates":[10.962836,49.447273],"type":"Point"}
}