{
  "type": "Feature",
  "properties": {
    "iso:country":"DE",
    "sg:address":"Konrad-Wolf-Str. 60",
    "sg:city":"Berlin",
    "sg:phone":"+49 30/97104061",
    "sg:postcode":"13055",
    "sg:province":"Berlin",
    "wof:name":"Vr Reiseb\u00fcro Kette Gmbh",
    "wof:placetype":"venue"
},
  "geometry": {"coordinates":[13.4796218872,52.5382766724],"type":"Point"}
}