{
  "type": "Feature",
  "properties": {
    "iso:country":"DE",
    "sg:address":"Breite Str. 10",
    "sg:city":"Lauf",
    "sg:phone":"+49 9123/12660",
    "sg:postcode":"91207",
    "sg:province":"Bayern",
    "wof:name":"Christa Borth",
    "wof:placetype":"venue"
},
  "geometry": {"coordinates":[11.2788162231,49.5117034912],"type":"Point"}
}