{
  "type": "Feature",
  "properties": {
    "iso:country":"DE",
    "sg:address":"Eisenlohrstr. 24",
    "sg:city":"Karlsruhe",
    "sg:phone":"+49 721/8281111",
    "sg:postcode":"76135",
    "sg:province":"Baden-W\u00fcrttemberg",
    "wof:name":"Planta Gmbh",
    "wof:placetype":"venue"
},
  "geometry": {"coordinates":[8.3725547791,49.0039291382],"type":"Point"}
}