{
  "type": "Feature",
  "properties": {
    "iso:country":"DE",
    "sg:address":"Mloder Str. 22",
    "sg:city":"Calau",
    "sg:phone":"+49 3541/801555",
    "sg:postcode":"03205",
    "sg:province":"Brandenburg",
    "wof:name":"Bauhof Calau Gmbh",
    "wof:placetype":"venue"
},
  "geometry": {"coordinates":[13.952126,51.752281],"type":"Point"}
}