{
  "type": "Feature",
  "properties": {
    "iso:country":"DE",
    "sg:address":"Am Langen Felde 5",
    "sg:city":"Wedemark",
    "sg:phone":"+49 5130/79260",
    "sg:postcode":"30900",
    "sg:province":"Niedersachsen",
    "wof:name":"Busse & Fritsche Optikerfachgesch\u00e4fte Mbh",
    "wof:placetype":"venue"
},
  "geometry": {"coordinates":[9.738158226,52.5476722717],"type":"Point"}
}