{
  "type": "Feature",
  "properties": {
    "iso:country":"DE",
    "sg:address":"Burgunderweg 8",
    "sg:city":"Winnenden",
    "sg:phone":"+49 7195/61158",
    "sg:postcode":"71364",
    "sg:province":"Baden-W\u00fcrttemberg",
    "wof:name":"Klaus D. Paul Anlageberater",
    "wof:placetype":"venue"
},
  "geometry": {"coordinates":[9.3897857666,48.85496521],"type":"Point"}
}