{
  "type": "Feature",
  "properties": {
    "iso:country":"DE",
    "sg:address":"Wilhelmstr. 32",
    "sg:city":"Schwerte",
    "sg:phone":"+49 2304/17154",
    "sg:postcode":"58239",
    "sg:province":"Nordrhein-Westfalen",
    "wof:name":"Orgo Gmbh Software-vertiebs-gmbh",
    "wof:placetype":"venue"
},
  "geometry": {"coordinates":[7.5666279793,51.439781189],"type":"Point"}
}