{
  "type": "Feature",
  "properties": {
    "iso:country":"DE",
    "sg:address":"Lange Str. 43",
    "sg:city":"Zierenberg",
    "sg:phone":"+49 5606/3266",
    "sg:postcode":"34289",
    "sg:province":"Hessen",
    "wof:name":"Andre",
    "wof:placetype":"venue"
},
  "geometry": {"coordinates":[9.300639,51.367321],"type":"Point"}
}