{
  "type": "Feature",
  "properties": {
    "iso:country":"DE",
    "sg:address":"Ziegelweg 34",
    "sg:city":"Winkelhaid",
    "sg:phone":"+49 9187/41886",
    "sg:postcode":"90610",
    "sg:province":"Bayern",
    "wof:name":"Peter Seibert",
    "wof:placetype":"venue"
},
  "geometry": {"coordinates":[11.304473,49.392628],"type":"Point"}
}