{
  "type": "Feature",
  "properties": {
    "iso:country":"DE",
    "sg:address":"Nu\u00dfbaumweg 7",
    "sg:city":"Lutherstadt Wittenberg",
    "sg:phone":"+49 3491/661072",
    "sg:postcode":"06886",
    "sg:province":"Sachsen-Anhalt",
    "wof:name":"Sanit\u00e4tshandel Brede",
    "wof:placetype":"venue"
},
  "geometry": {"coordinates":[12.610594,51.871662],"type":"Point"}
}