{
  "type": "Feature",
  "properties": {
    "iso:country":"DE",
    "sg:address":"Wilhelm-Weitling-Str. 6",
    "sg:city":"Dresden",
    "sg:phone":"+49 351/2018107",
    "sg:postcode":"01259",
    "sg:province":"Sachsen",
    "wof:name":"Baierlein Und Baierlein Rechtsanw\u00e4lte",
    "wof:placetype":"venue"
},
  "geometry": {"coordinates":[13.8608150482,51.0078468323],"type":"Point"}
}