{
  "type": "Feature",
  "properties": {
    "iso:country":"DE",
    "sg:address":"An der Plantage 33C",
    "sg:city":"Mainz",
    "sg:phone":"+49 6131/682077",
    "sg:postcode":"55120",
    "sg:province":"Rheinland-Pfalz",
    "wof:name":"Andreas M\u00fcller",
    "wof:placetype":"venue"
},
  "geometry": {"coordinates":[8.228434,50.015938],"type":"Point"}
}