{
  "type": "Feature",
  "properties": {
    "iso:country":"DE",
    "sg:address":"Fritz-Reuter-Str. 17",
    "sg:city":"Melle",
    "sg:phone":"+49 5422/41330",
    "sg:postcode":"49324",
    "sg:province":"Niedersachsen",
    "wof:name":"L. Holzm\u00fcller Immobilienmakler",
    "wof:placetype":"venue"
},
  "geometry": {"coordinates":[8.3255720139,52.200668335],"type":"Point"}
}