{
  "type": "Feature",
  "properties": {
    "iso:country":"DE",
    "sg:address":"72657",
    "sg:city":"Altenriet",
    "sg:phone":"+49 7127/32543",
    "sg:postcode":"72657",
    "sg:province":"Baden-W\u00fcrttemberg",
    "wof:name":"H. Rieger Immobilienmakler",
    "wof:placetype":"venue"
},
  "geometry": {"coordinates":[9.2162303925,48.5895500183],"type":"Point"}
}