{
  "type": "Feature",
  "properties": {
    "iso:country":"DE",
    "sg:address":"Aachener Str. 118",
    "sg:city":"Baesweiler",
    "sg:phone":"+49 2401/2321",
    "sg:postcode":"52499",
    "sg:province":"Nordrhein-Westfalen",
    "wof:name":"Gatzweiler & Thouet Partnerschaft",
    "wof:placetype":"venue"
},
  "geometry": {"coordinates":[6.191259861,50.9105606079],"type":"Point"}
}