{
  "type": "Feature",
  "properties": {
    "iso:country":"DE",
    "sg:address":"Ortsstr. 39",
    "sg:city":"Pfakofen",
    "sg:phone":"+49 9451/554",
    "sg:postcode":"93101",
    "sg:province":"Bayern",
    "wof:name":"Gastst\u00e4tte Johann Schmalhofer",
    "wof:placetype":"venue"
},
  "geometry": {"coordinates":[12.2283639908,48.8583641052],"type":"Point"}
}