{
  "type": "Feature",
  "properties": {
    "iso:country":"DE",
    "sg:address":"Gartenstr. 9",
    "sg:city":"Gartz",
    "sg:phone":"+49 33332/360",
    "sg:postcode":"16307",
    "sg:province":"Brandenburg",
    "wof:name":"Dr. Dietrich Rieger Tierarzt",
    "wof:placetype":"venue"
},
  "geometry": {"coordinates":[14.3852882385,53.2057876587],"type":"Point"}
}