{
  "type": "Feature",
  "properties": {
    "iso:country":"DE",
    "sg:address":"Berkaer Str. 59",
    "sg:city":"Gelmeroda",
    "sg:phone":"+49 3643/853306",
    "sg:postcode":"99428",
    "sg:province":"Th\u00fcringen",
    "wof:name":"G\u00fcnter T\u00f6pfer",
    "wof:placetype":"venue"
},
  "geometry": {"coordinates":[11.2343120575,50.9665374756],"type":"Point"}
}