{
  "type": "Feature",
  "properties": {
    "iso:country":"DE",
    "sg:address":"Westring 24",
    "sg:city":"Ratekau",
    "sg:phone":"+49 4504/1461",
    "sg:postcode":"23626",
    "sg:province":"Schleswig-Holstein",
    "wof:name":"Verpackungstechnik Horst Wierick Gmbh",
    "wof:placetype":"venue"
},
  "geometry": {"coordinates":[10.728186,53.946075],"type":"Point"}
}