{
  "type": "Feature",
  "properties": {
    "iso:country":"DE",
    "sg:address":"Steinmetzstr. 14",
    "sg:city":"L\u00fcbeck",
    "sg:phone":"+49 451/799440",
    "sg:postcode":"23556",
    "sg:province":"Schleswig-Holstein",
    "wof:name":"Peters Sport- Und Tennis- Versand Gmbh",
    "wof:placetype":"venue"
},
  "geometry": {"coordinates":[10.616358,53.864994],"type":"Point"}
}