{
  "type": "Feature",
  "properties": {
    "iso:country":"DE",
    "sg:address":"Hauptstr. 173",
    "sg:city":"Mainz-Kostheim",
    "sg:phone":"+49 6134/18110",
    "sg:postcode":"55246",
    "sg:province":"Hessen",
    "wof:name":"Gg. H. Schollmayer Verm\u00f6gensverwaltungs",
    "wof:placetype":"venue"
},
  "geometry": {"coordinates":[8.302121,50.000587],"type":"Point"}
}