{
  "type": "Feature",
  "properties": {
    "iso:country":"DE",
    "sg:address":"Ridlerstr. 75",
    "sg:city":"M\u00fcnchen",
    "sg:phone":"+49 89/500930",
    "sg:postcode":"80339",
    "sg:province":"Bayern",
    "wof:name":"S\u00fcdsalz Gmbh",
    "wof:placetype":"venue"
},
  "geometry": {"coordinates":[11.5281391144,48.1370048523],"type":"Point"}
}