{
  "type": "Feature",
  "properties": {
    "iso:country":"DE",
    "sg:address":"Vaihinger Str. 131",
    "sg:city":"Stuttgart",
    "sg:phone":"+49 4971/1170",
    "sg:postcode":"70567",
    "sg:province":"Baden-W\u00fcrttemberg",
    "wof:name":"Evobus Gmbh",
    "wof:placetype":"venue"
},
  "geometry": {"coordinates":[9.1361312866,48.7280197144],"type":"Point"}
}