{
  "type": "Feature",
  "properties": {
    "iso:country":"DE",
    "sg:address":"Rathausstr. 1",
    "sg:city":"Rietberg",
    "sg:phone":"+49 5244/988080",
    "sg:postcode":"33397",
    "sg:province":"Nordrhein-Westfalen",
    "wof:name":"Reckmann Computer Services Gmbh",
    "wof:placetype":"venue"
},
  "geometry": {"coordinates":[8.4280261993,51.8102493286],"type":"Point"}
}