{
  "type": "Feature",
  "properties": {
    "iso:country":"DE",
    "sg:address":"Lindenpark 1",
    "sg:city":"Neuzelle",
    "sg:phone":"+49 33652/251",
    "sg:postcode":"15898",
    "sg:province":"Brandenburg",
    "wof:name":"Agrargenossenschaft Neuzelle Eg",
    "wof:placetype":"venue"
},
  "geometry": {"coordinates":[14.633865,52.092197],"type":"Point"}
}