{
  "type": "Feature",
  "properties": {
    "iso:country":"DE",
    "sg:address":"Finkenstr. 1",
    "sg:city":"K\u00e4mpfelbach",
    "sg:phone":"+49 7231/81759",
    "sg:postcode":"75236",
    "sg:province":"Baden-W\u00fcrttemberg",
    "wof:name":"B. Wolf Graphiker-designer",
    "wof:placetype":"venue"
},
  "geometry": {"coordinates":[8.6490221024,48.9308929443],"type":"Point"}
}