{
  "type": "Feature",
  "properties": {
    "iso:country":"DE",
    "sg:address":"Koppelkaten 5",
    "sg:city":"Koberg",
    "sg:phone":"+49 4543/7280",
    "sg:postcode":"23881",
    "sg:province":"Schleswig-Holstein",
    "wof:name":"Biohof J\u00fcrgen Sch\u00e4fer",
    "wof:placetype":"venue"
},
  "geometry": {"coordinates":[10.52649,53.628139],"type":"Point"}
}