{
  "type": "Feature",
  "properties": {
    "iso:country":"DE",
    "sg:address":"Feuerwehrstr. 5",
    "sg:city":"Syke",
    "sg:phone":"+49 4242/936031",
    "sg:postcode":"28857",
    "sg:province":"Niedersachsen",
    "wof:name":"Evelyn Wendt",
    "wof:placetype":"venue"
},
  "geometry": {"coordinates":[8.7611465454,52.9435272217],"type":"Point"}
}