{
  "type": "Feature",
  "properties": {
    "iso:country":"DE",
    "sg:address":"Hersfelder Str. 11",
    "sg:city":"Bad Hersfeld",
    "sg:phone":"+49 6621/78549",
    "sg:postcode":"36251",
    "sg:province":"Hessen",
    "wof:name":"Hans Henning",
    "wof:placetype":"venue"
},
  "geometry": {"coordinates":[9.67685,50.891354],"type":"Point"}
}