{
  "type": "Feature",
  "properties": {
    "iso:country":"DE",
    "sg:address":"Altmarkt 14",
    "sg:city":"Ortrand",
    "sg:postcode":"01990",
    "sg:province":"Brandenburg",
    "wof:name":"Aps Gmbh",
    "wof:placetype":"venue"
},
  "geometry": {"coordinates":[13.7571353912,51.3758163452],"type":"Point"}
}