{
  "type": "Feature",
  "properties": {
    "iso:country":"DE",
    "sg:address":"Breite Str. 29",
    "sg:city":"Lengede",
    "sg:phone":"+49 5344/7147",
    "sg:postcode":"38268",
    "sg:province":"Niedersachsen",
    "wof:name":"Manfred R\u00fchmann",
    "wof:placetype":"venue"
},
  "geometry": {"coordinates":[10.311622,52.202377],"type":"Point"}
}