{
  "type": "Feature",
  "properties": {
    "iso:country":"DE",
    "sg:address":"Gereonstr. 43-65",
    "sg:city":"K\u00f6ln",
    "sg:phone":"+49 221/2232843",
    "sg:postcode":"50670",
    "sg:province":"Nordrhein-Westfalen",
    "wof:name":"Tertia Handels- Beteiligungsgesellschaft Mbh",
    "wof:placetype":"venue"
},
  "geometry": {"coordinates":[6.94885,50.94297],"type":"Point"}
}