{
  "type": "Feature",
  "properties": {
    "iso:country":"DE",
    "sg:address":"Kamphausener Str. 28",
    "sg:city":"M\u00f6nchengladbach",
    "sg:phone":"+49 2166/609832",
    "sg:postcode":"41199",
    "sg:province":"Nordrhein-Westfalen",
    "wof:name":"Petra Heinen-dauber Rechtsanw\u00e4ltin",
    "wof:placetype":"venue"
},
  "geometry": {"coordinates":[6.4548668861,51.1353797913],"type":"Point"}
}