{
  "type": "Feature",
  "properties": {
    "iso:country":"DE",
    "sg:address":"Albanusstr. 14",
    "sg:city":"Limburg",
    "sg:phone":"+49 6431/75959",
    "sg:postcode":"65551",
    "sg:province":"Hessen",
    "wof:name":"Hammer Isolierungen Gmbh",
    "wof:placetype":"venue"
},
  "geometry": {"coordinates":[8.12412,50.374626],"type":"Point"}
}