{
  "type": "Feature",
  "properties": {
    "iso:country":"DE",
    "sg:address":"Osterburger Str. 83-84",
    "sg:city":"Stendal",
    "sg:phone":"+49 3931/794970",
    "sg:postcode":"39576",
    "sg:province":"Sachsen-Anhalt",
    "wof:name":"Block Stadtwirtschaft Gmbh",
    "wof:placetype":"venue"
},
  "geometry": {"coordinates":[11.846891,52.618862],"type":"Point"}
}