{
  "type": "Feature",
  "properties": {
    "iso:country":"DE",
    "sg:address":"Elsflether Weg 15",
    "sg:city":"Berlin",
    "sg:phone":"+49 30/3311608",
    "sg:postcode":"13581",
    "sg:province":"Berlin",
    "wof:name":"Joachim Lunow",
    "wof:placetype":"venue"
},
  "geometry": {"coordinates":[13.193089,52.531712],"type":"Point"}
}