{
  "type": "Feature",
  "properties": {
    "iso:country":"DE",
    "sg:address":"Bahnhofstr. 31",
    "sg:city":"Nidda",
    "sg:phone":"+49 6043/1456",
    "sg:postcode":"63667",
    "sg:province":"Hessen",
    "wof:name":"Anton Christ",
    "wof:placetype":"venue"
},
  "geometry": {"coordinates":[9.0052089691,50.4130516052],"type":"Point"}
}