{
  "type": "Feature",
  "properties": {
    "iso:country":"DE",
    "sg:address":"Arendahls Wiese 31",
    "sg:city":"Essen",
    "sg:phone":"+49 201/314283",
    "sg:postcode":"45141",
    "sg:province":"Nordrhein-Westfalen",
    "wof:name":"Manfred Brocker Bauunternehmung Gmbh",
    "wof:placetype":"venue"
},
  "geometry": {"coordinates":[7.028335,51.480511],"type":"Point"}
}