{
  "type": "Feature",
  "properties": {
    "iso:country":"DE",
    "sg:address":"Sunderweg 98",
    "sg:city":"Dortmund",
    "sg:phone":"+49 231/91110",
    "sg:postcode":"44147",
    "sg:province":"Nordrhein-Westfalen",
    "wof:name":"Doreg Dortmunder Recycling Gmbh",
    "wof:placetype":"venue"
},
  "geometry": {"coordinates":[7.443153,51.522076],"type":"Point"}
}