{
  "type": "Feature",
  "properties": {
    "iso:country":"DE",
    "sg:address":"Hagenstr. 5",
    "sg:city":"Frankfurt",
    "sg:phone":"+49 69/441001",
    "sg:postcode":"60314",
    "sg:province":"Hessen",
    "wof:name":"Schr\u00f6der & Co. Geb\u00e4ude- Reinigungsunternehmen Gmbh",
    "wof:placetype":"venue"
},
  "geometry": {"coordinates":[8.7097625732,50.1102523804],"type":"Point"}
}