{
  "type": "Feature",
  "properties": {
    "iso:country":"DE",
    "sg:address":"hemmstrasse183",
    "sg:city":"bremen",
    "sg:postcode":"28215",
    "sg:province":"Bremen",
    "wof:name":"Willkomme Bei Nicole Des Swingerpaar",
    "wof:placetype":"venue"
},
  "geometry": {"coordinates":[8.80793,53.094574],"type":"Point"}
}