{
  "type": "Feature",
  "properties": {
    "iso:country":"DE",
    "sg:address":"L\u00e4rchenweg 2",
    "sg:city":"Keltern",
    "sg:phone":"+49 7082/948203",
    "sg:postcode":"75210",
    "sg:province":"Baden-W\u00fcrttemberg",
    "wof:name":"Tivor Import Und Export Schmuckhandel Gmbh",
    "wof:placetype":"venue"
},
  "geometry": {"coordinates":[8.5662488937,48.8895530701],"type":"Point"}
}