{
  "type": "Feature",
  "properties": {
    "iso:country":"DE",
    "sg:address":"Jurastr. 67",
    "sg:city":"Wagh\u00e4usel",
    "sg:postcode":"68753",
    "sg:province":"Baden-W\u00fcrttemberg",
    "wof:name":"Ga Wa Com Consult Gmbh",
    "wof:placetype":"venue"
},
  "geometry": {"coordinates":[8.540768,49.233932],"type":"Point"}
}