{
  "type": "Feature",
  "properties": {
    "iso:country":"DE",
    "sg:address":"Eichenweg 6",
    "sg:city":"Dahmker",
    "sg:phone":"+49 4154/86100",
    "sg:postcode":"22946",
    "sg:province":"Schleswig-Holstein",
    "wof:name":"Landtechnisches Lohn- Unternehmen Otto Hamester",
    "wof:placetype":"venue"
},
  "geometry": {"coordinates":[10.445087,53.587162],"type":"Point"}
}