{
  "type": "Feature",
  "properties": {
    "iso:country":"DE",
    "sg:address":"Hansastr. 2",
    "sg:city":"Lippstadt",
    "sg:phone":"+49 2941/2750",
    "sg:postcode":"59557",
    "sg:province":"Nordrhein-Westfalen",
    "wof:name":"Hellweg Presseholding Verwaltungs Gmbh",
    "wof:placetype":"venue"
},
  "geometry": {"coordinates":[8.366273,51.654408],"type":"Point"}
}