{
  "type": "Feature",
  "properties": {
    "iso:country":"DE",
    "sg:address":"Eckenerstr 60",
    "sg:city":"Aachen",
    "sg:phone":"+49 241/562004",
    "sg:postcode":"52078",
    "sg:province":"Nordrhein-Westfalen",
    "wof:name":"Rhl Internationale Speditions Gmbh",
    "wof:placetype":"venue"
},
  "geometry": {"coordinates":[6.1592888832,50.7559318542],"type":"Point"}
}