{
  "type": "Feature",
  "properties": {
    "iso:country":"DE",
    "sg:address":"Adlerplatz 7",
    "sg:city":"Achern",
    "sg:phone":"+49 7841/3443",
    "sg:postcode":"77855",
    "sg:province":"Baden-W\u00fcrttemberg",
    "wof:name":"Pfeiffer Modehaus",
    "wof:placetype":"venue"
},
  "geometry": {"coordinates":[8.070719,48.629684],"type":"Point"}
}