{
  "type": "Feature",
  "properties": {
    "iso:country":"DE",
    "sg:address":"Hauptstr. 14",
    "sg:city":"M\u00f6nchengladbach",
    "sg:postcode":"41236",
    "sg:province":"Nordrhein-Westfalen",
    "wof:name":"Komfort-haus Bau Gmbh",
    "wof:placetype":"venue"
},
  "geometry": {"coordinates":[6.44194,51.167534],"type":"Point"}
}