{
  "type": "Feature",
  "properties": {
    "iso:country":"DE",
    "sg:address":"Altheimer Str. 56",
    "sg:city":"Gerstetten",
    "sg:phone":"+49 7324/989202",
    "sg:postcode":"89547",
    "sg:province":"Baden-W\u00fcrttemberg",
    "wof:name":"Elektro-spiegler Gmbh",
    "wof:placetype":"venue"
},
  "geometry": {"coordinates":[10.10368,48.589809],"type":"Point"}
}