{
  "type": "Feature",
  "properties": {
    "iso:country":"DE",
    "sg:address":"Heinrich-Brauns-Str. 17",
    "sg:city":"Lindenberg",
    "sg:phone":"+49 8381/92170",
    "sg:postcode":"88161",
    "sg:province":"Bayern",
    "wof:name":"Neluplast - Tiefzieh - Technik Gmbh",
    "wof:placetype":"venue"
},
  "geometry": {"coordinates":[9.8854207993,47.6044006348],"type":"Point"}
}