{
  "type": "Feature",
  "properties": {
    "iso:country":"DE",
    "sg:address":"Hauptstr. 29",
    "sg:city":"Zuzenhausen",
    "sg:phone":"+49 6226/1516",
    "sg:postcode":"74939",
    "sg:province":"Baden-W\u00fcrttemberg",
    "wof:name":"Harald Minges Steuerberater",
    "wof:placetype":"venue"
},
  "geometry": {"coordinates":[8.8260993958,49.2967414856],"type":"Point"}
}