{
  "type": "Feature",
  "properties": {
    "iso:country":"DE",
    "sg:address":"Schlaurother Str. 11",
    "sg:city":"G\u00f6rlitz",
    "sg:phone":"+49 3581/7440",
    "sg:postcode":"02827",
    "sg:province":"Sachsen",
    "wof:name":"Evangelisches Bildungswerk Johann Amos Comenius E. V.",
    "wof:placetype":"venue"
},
  "geometry": {"coordinates":[14.9374408722,51.1328620911],"type":"Point"}
}