{
  "type": "Feature",
  "properties": {
    "iso:country":"DE",
    "sg:address":"Treiberstr. 7",
    "sg:city":"Wedemark",
    "sg:phone":"+49 5130/39742",
    "sg:postcode":"30900",
    "sg:province":"Niedersachsen",
    "wof:name":"Schmidt-holzvermittlungs Gmbh",
    "wof:placetype":"venue"
},
  "geometry": {"coordinates":[9.690044,52.584377],"type":"Point"}
}