{
  "type": "Feature",
  "properties": {
    "iso:country":"DE",
    "sg:address":"Reinhartser Str. 20",
    "sg:city":"Kempten",
    "sg:phone":"+49 831/72424",
    "sg:postcode":"87437",
    "sg:province":"Bayern",
    "wof:name":"J. Retter",
    "wof:placetype":"venue"
},
  "geometry": {"coordinates":[10.333109,47.738338],"type":"Point"}
}