{
  "type": "Feature",
  "properties": {
    "iso:country":"DE",
    "sg:address":"Bahnhofstr. 60",
    "sg:city":"Malsch",
    "sg:phone":"+49 7246/7340",
    "sg:postcode":"76316",
    "sg:province":"Baden-W\u00fcrttemberg",
    "wof:name":"Jasny & Schlor Gmbh",
    "wof:placetype":"venue"
},
  "geometry": {"coordinates":[8.315777,48.884281],"type":"Point"}
}