{
  "type": "Feature",
  "properties": {
    "iso:country":"DE",
    "sg:address":"Plessenstr. 4a",
    "sg:city":"Schleswig",
    "sg:phone":"+49 4621/23891",
    "sg:postcode":"24837",
    "sg:province":"Schleswig-Holstein",
    "wof:name":"Hellmuth Freiberg Ingenieur",
    "wof:placetype":"venue"
},
  "geometry": {"coordinates":[9.5671844482,54.5138702393],"type":"Point"}
}