{
  "type": "Feature",
  "properties": {
    "iso:country":"DE",
    "sg:address":"Gleimstr. 40",
    "sg:city":"Berlin",
    "sg:phone":"+49 30/4491576",
    "sg:postcode":"10437",
    "sg:province":"Berlin",
    "wof:name":"M. Bartz",
    "wof:placetype":"venue"
},
  "geometry": {"coordinates":[13.409228,52.547482],"type":"Point"}
}