{
  "type": "Feature",
  "properties": {
    "iso:country":"DE",
    "sg:address":"Raderberger Str. 216",
    "sg:city":"K\u00f6ln",
    "sg:phone":"+49 4922/1376670",
    "sg:postcode":"50968",
    "sg:province":"Nordrhein-Westfalen",
    "wof:name":"Druckerei U. Verlag Locher Gmbh",
    "wof:placetype":"venue"
},
  "geometry": {"coordinates":[6.9562249184,50.9047050476],"type":"Point"}
}