{
  "type": "Feature",
  "properties": {
    "iso:country":"DE",
    "sg:address":"Klopstockplatz 6",
    "sg:city":"Hamburg",
    "sg:phone":"+49 40/391139",
    "sg:postcode":"22765",
    "sg:province":"Hamburg",
    "wof:name":"Ulrich Arndt Architekt",
    "wof:placetype":"venue"
},
  "geometry": {"coordinates":[9.933011,53.5467],"type":"Point"}
}