{
  "type": "Feature",
  "properties": {
    "iso:country":"DE",
    "sg:address":"Dankwartstr. 17",
    "sg:city":"Wismar",
    "sg:postcode":"23966",
    "sg:province":"Mecklenburg-Vorpommern",
    "wof:name":"Jwn Computer Gmbh",
    "wof:placetype":"venue"
},
  "geometry": {"coordinates":[11.464392,53.890522],"type":"Point"}
}