{
  "type": "Feature",
  "properties": {
    "iso:country":"DE",
    "sg:address":"Dorfstr. 14 a",
    "sg:city":"Sehlen",
    "sg:postcode":"18528",
    "sg:province":"Mecklenburg-Vorpommern",
    "wof:name":"R\u00fcgen Journal Gmbh",
    "wof:placetype":"venue"
},
  "geometry": {"coordinates":[13.3853702545,54.3796272278],"type":"Point"}
}