{
  "type": "Feature",
  "properties": {
    "iso:country":"DE",
    "sg:address":"Pommernstr. 2",
    "sg:city":"Schwieberdingen",
    "sg:phone":"+49 7150/397974",
    "sg:postcode":"71701",
    "sg:province":"Baden-W\u00fcrttemberg",
    "wof:name":"Heilmann Software Gesellschaft F\u00fcr",
    "wof:placetype":"venue"
},
  "geometry": {"coordinates":[9.0780763626,48.8708572388],"type":"Point"}
}