{
  "type": "Feature",
  "properties": {
    "iso:country":"DE",
    "sg:address":"Wesendonkstr. 77",
    "sg:city":"M\u00fcnchen",
    "sg:phone":"+49 89/952626",
    "sg:postcode":"81925",
    "sg:province":"Bayern",
    "wof:name":"Berna-melzl & Partner Werbegeschenke",
    "wof:placetype":"venue"
},
  "geometry": {"coordinates":[11.6269807816,48.1632461548],"type":"Point"}
}