{
  "type": "Feature",
  "properties": {
    "iso:country":"DE",
    "sg:address":"Rathausplatz 3",
    "sg:city":"Lotte",
    "sg:phone":"+49 5404/5570",
    "sg:postcode":"49504",
    "sg:province":"Nordrhein-Westfalen",
    "wof:name":"Brillen Bartels Gmbh",
    "wof:placetype":"venue"
},
  "geometry": {"coordinates":[7.9410009384,52.3130073547],"type":"Point"}
}