{
  "type": "Feature",
  "properties": {
    "iso:country":"DE",
    "sg:address":"Bergstr. 17",
    "sg:city":"N\u00fcrnberg",
    "sg:phone":"+49 911/223238",
    "sg:postcode":"90403",
    "sg:province":"Bayern",
    "wof:name":"Gertrud Kre\u00df-ahrens",
    "wof:placetype":"venue"
},
  "geometry": {"coordinates":[11.074875,49.456959],"type":"Point"}
}