{
  "type": "Feature",
  "properties": {
    "iso:country":"DE",
    "sg:address":"Weserstr. 102",
    "sg:city":"Bremerhaven",
    "sg:phone":"+49 471/75697",
    "sg:postcode":"27572",
    "sg:province":"Bremen",
    "wof:name":"Der Bastler",
    "wof:placetype":"venue"
},
  "geometry": {"coordinates":[8.59684,53.508152],"type":"Point"}
}