{
  "type": "Feature",
  "properties": {
    "iso:country":"DE",
    "sg:address":"J\u00fcdenbergstr. 7",
    "sg:city":"Mei\u00dfen",
    "sg:postcode":"01662",
    "sg:province":"Sachsen",
    "wof:name":"Erotik-shop Inh. Rosemarie Lange",
    "wof:placetype":"venue"
},
  "geometry": {"coordinates":[13.466727,51.160709],"type":"Point"}
}