{
  "type": "Feature",
  "properties": {
    "iso:country":"DE",
    "sg:address":"Weiherweg 3",
    "sg:city":"Igling",
    "sg:phone":"+49 8248/901635",
    "sg:postcode":"86859",
    "sg:province":"Bayern",
    "wof:name":"Good-choice Shop Angelboote Und Ruderboote",
    "wof:placetype":"venue"
},
  "geometry": {"coordinates":[10.8030653,48.07264328],"type":"Point"}
}