{
  "type": "Feature",
  "properties": {
    "iso:country":"DE",
    "sg:address":"Wei\u00dfdornweg 3",
    "sg:city":"Bad Homburg",
    "sg:phone":"+49 6172/43428",
    "sg:postcode":"61352",
    "sg:province":"Hessen",
    "wof:name":"K. Heil",
    "wof:placetype":"venue"
},
  "geometry": {"coordinates":[8.676967,50.229881],"type":"Point"}
}