{
  "type": "Feature",
  "properties": {
    "iso:country":"DE",
    "sg:address":"Neuenheimer Landstr. 5",
    "sg:city":"Heidelberg",
    "sg:phone":"+49 6221/475437",
    "sg:postcode":"69120",
    "sg:province":"Baden-W\u00fcrttemberg",
    "wof:name":"Wirtschaftsgesellschaft Der Zahntechniker-innung",
    "wof:placetype":"venue"
},
  "geometry": {"coordinates":[8.694524,49.413555],"type":"Point"}
}