{
  "type": "Feature",
  "properties": {
    "iso:country":"DE",
    "sg:address":"Marktplatz 5",
    "sg:city":"Altmannstein",
    "sg:phone":"+49 9446/2666",
    "sg:postcode":"93336",
    "sg:province":"Bayern",
    "wof:name":"Rosa Gogl",
    "wof:placetype":"venue"
},
  "geometry": {"coordinates":[11.650678,48.896664],"type":"Point"}
}