{
  "type": "Feature",
  "properties": {
    "iso:country":"DE",
    "sg:address":"Siedlerstr. 7",
    "sg:city":"Lichtenow",
    "sg:phone":"+49 33434/70513",
    "sg:postcode":"15345",
    "sg:province":"Brandenburg",
    "wof:name":"Helga Kuss",
    "wof:placetype":"venue"
},
  "geometry": {"coordinates":[13.89365,52.491901],"type":"Point"}
}