{
  "type": "Feature",
  "properties": {
    "iso:country":"DE",
    "sg:address":"Gladbacher Str. 8",
    "sg:city":"Bergisch Gladbach",
    "sg:phone":"+49 2204/52223",
    "sg:postcode":"51429",
    "sg:province":"Nordrhein-Westfalen",
    "wof:name":"Altenwohnheim Dechant Berger Haus",
    "wof:placetype":"venue"
},
  "geometry": {"coordinates":[7.154707,50.966625],"type":"Point"}
}