{
  "type": "Feature",
  "properties": {
    "iso:country":"DE",
    "sg:address":"Hauptstr. 2",
    "sg:city":"Gelsenkirchen",
    "sg:phone":"+49 209/21276",
    "sg:postcode":"45879",
    "sg:province":"Nordrhein-Westfalen",
    "wof:name":"Dirk Hirschleb",
    "wof:placetype":"venue"
},
  "geometry": {"coordinates":[7.0952529907,51.5109634399],"type":"Point"}
}