{
  "type": "Feature",
  "properties": {
    "iso:country":"DE",
    "sg:address":"Schiltacher Str. 2",
    "sg:city":"Stuttgart",
    "sg:phone":"+49 711/678900",
    "sg:postcode":"70569",
    "sg:province":"Baden-W\u00fcrttemberg",
    "wof:name":"Ekkehard Seidel Ingenieur",
    "wof:placetype":"venue"
},
  "geometry": {"coordinates":[9.1364717484,48.7401809692],"type":"Point"}
}