{
  "type": "Feature",
  "properties": {
    "iso:country":"DE",
    "sg:address":"Badfeldring 25",
    "sg:city":"Landsberied",
    "sg:phone":"+49 8141/21730",
    "sg:postcode":"82290",
    "sg:province":"Bayern",
    "wof:name":"Swing Flugsportger\u00e4te Gmbh",
    "wof:placetype":"venue"
},
  "geometry": {"coordinates":[11.1701917648,48.1631011963],"type":"Point"}
}