{
  "type": "Feature",
  "properties": {
    "iso:country":"DE",
    "sg:address":"Werftstr 193",
    "sg:city":"Kiel",
    "sg:phone":"+49 431/6479990",
    "sg:postcode":"24143",
    "sg:province":"Schleswig-Holstein",
    "wof:name":"Die Zwei Context Gmbh",
    "wof:placetype":"venue"
},
  "geometry": {"coordinates":[10.140501,54.31348],"type":"Point"}
}