{
  "type": "Feature",
  "properties": {
    "iso:country":"DE",
    "sg:address":"Matthias-Erzberger-Str. 10",
    "sg:city":"Taucha",
    "sg:postcode":"04425",
    "sg:province":"Sachsen",
    "wof:name":"Eurohr Tiefbau Gmbh",
    "wof:placetype":"venue"
},
  "geometry": {"coordinates":[12.4817752838,51.3808174133],"type":"Point"}
}