{
  "type": "Feature",
  "properties": {
    "iso:country":"DE",
    "sg:address":"Dietlishof",
    "sg:city":"Hilzingen",
    "sg:phone":"+49 7731/61888",
    "sg:postcode":"78247",
    "sg:province":"Baden-W\u00fcrttemberg",
    "wof:name":"Hirsch-brauerei Honer Gmbh & Co. Kg",
    "wof:placetype":"venue"
},
  "geometry": {"coordinates":[8.77845,47.756111],"type":"Point"}
}