{
  "type": "Feature",
  "properties": {
    "iso:country":"DE",
    "sg:address":"F\u00fcnfhausen 10",
    "sg:city":"L\u00fcbbecke",
    "sg:phone":"+49 5741/5066",
    "sg:postcode":"32312",
    "sg:province":"Nordrhein-Westfalen",
    "wof:name":"Gbsl Betreuungs- Und Verwaltungsgesellschaft Mbh",
    "wof:placetype":"venue"
},
  "geometry": {"coordinates":[8.6158018112,52.3024520874],"type":"Point"}
}