{
  "type": "Feature",
  "properties": {
    "iso:country":"DE",
    "sg:address":"Berliner Str. 69",
    "sg:city":"Bad M\u00fcnster-Ebernburg",
    "sg:phone":"+49 6708/661030",
    "sg:postcode":"55583",
    "sg:province":"Rheinland-Pfalz",
    "wof:name":"Restaurant Jahreszeiten",
    "wof:placetype":"venue"
},
  "geometry": {"coordinates":[7.8446102142,49.8101615906],"type":"Point"}
}