{
  "type": "Feature",
  "properties": {
    "iso:country":"DE",
    "sg:address":"H\u00e4uersteig 1",
    "sg:city":"Freiberg",
    "sg:phone":"+49 3731/76465",
    "sg:postcode":"09599",
    "sg:province":"Sachsen",
    "wof:name":"Obi Heimwerkermarkt Gmbh & Co. Kg",
    "wof:placetype":"venue"
},
  "geometry": {"coordinates":[13.330177,50.894894],"type":"Point"}
}