{
  "type": "Feature",
  "properties": {
    "iso:country":"DE",
    "sg:address":"Coswiger Str. 76",
    "sg:city":"Dessau",
    "sg:phone":"+49 340/2161620",
    "sg:postcode":"06844",
    "sg:province":"Sachsen-Anhalt",
    "wof:name":"Rolf-dirk Hauch",
    "wof:placetype":"venue"
},
  "geometry": {"coordinates":[12.2571201324,51.8397789001],"type":"Point"}
}