{
  "type": "Feature",
  "properties": {
    "iso:country":"DE",
    "sg:address":"Jahnstr. 35",
    "sg:city":"Schenefeld",
    "sg:phone":"+49 40/8306510",
    "sg:postcode":"22869",
    "sg:province":"Schleswig-Holstein",
    "wof:name":"K. B\u00f6hm",
    "wof:placetype":"venue"
},
  "geometry": {"coordinates":[9.848165,53.607006],"type":"Point"}
}