{
  "type": "Feature",
  "properties": {
    "iso:country":"DE",
    "sg:address":"Bornholzstr. 28",
    "sg:city":"Warstein",
    "sg:phone":"+49 2902/75266",
    "sg:postcode":"59581",
    "sg:province":"Nordrhein-Westfalen",
    "wof:name":"Wolfgang Sch\u00f6ne Ingenieur",
    "wof:placetype":"venue"
},
  "geometry": {"coordinates":[8.3290958405,51.4785614014],"type":"Point"}
}