{
  "type": "Feature",
  "properties": {
    "iso:country":"DE",
    "sg:address":"Christofstr. 16",
    "sg:city":"Korntal-M\u00fcnchingen",
    "sg:phone":"+49 7150/6304",
    "sg:postcode":"70825",
    "sg:province":"Baden-W\u00fcrttemberg",
    "wof:name":"Ev. Pfarramt",
    "wof:placetype":"venue"
},
  "geometry": {"coordinates":[9.0940036774,48.8546562195],"type":"Point"}
}