{
  "type": "Feature",
  "properties": {
    "iso:country":"DE",
    "sg:address":"Uhlandstr. 2",
    "sg:city":"Creglingen",
    "sg:phone":"+49 7933/571",
    "sg:postcode":"97993",
    "sg:province":"Baden-W\u00fcrttemberg",
    "wof:name":"Kath. Pfarramt Fronleichnam",
    "wof:placetype":"venue"
},
  "geometry": {"coordinates":[10.0269737244,49.4716453552],"type":"Point"}
}