{
  "type": "Feature",
  "properties": {
    "iso:country":"DE",
    "sg:address":"Welschstr. 4",
    "sg:city":"Dachau",
    "sg:phone":"+49 8131/354110",
    "sg:postcode":"85221",
    "sg:province":"Bayern",
    "wof:name":"Werner Hupfauer Gmbh",
    "wof:placetype":"venue"
},
  "geometry": {"coordinates":[11.4441280365,48.2680740356],"type":"Point"}
}