{
  "type": "Feature",
  "properties": {
    "iso:country":"DE",
    "sg:address":"Alte Elbgaustr. 14",
    "sg:city":"Hamburg",
    "sg:phone":"+49 40/5703001",
    "sg:postcode":"22523",
    "sg:province":"Hamburg",
    "wof:name":"Fit For Life Gmbh",
    "wof:placetype":"venue"
},
  "geometry": {"coordinates":[9.9030971527,53.6074905396],"type":"Point"}
}