{
  "type": "Feature",
  "properties": {
    "iso:country":"DE",
    "sg:address":"Nordring 11",
    "sg:city":"Borken",
    "sg:phone":"+49 2861/7071",
    "sg:postcode":"46325",
    "sg:province":"Nordrhein-Westfalen",
    "wof:name":"Friedrich Wevers Rechtsanwalt Und Notar",
    "wof:placetype":"venue"
},
  "geometry": {"coordinates":[6.8613471985,51.8488311768],"type":"Point"}
}