{
  "type": "Feature",
  "properties": {
    "iso:country":"DE",
    "sg:address":"An der \u00dcberf\u00fchrung 5",
    "sg:city":"Landshut",
    "sg:phone":"+49 871/72508",
    "sg:postcode":"84032",
    "sg:province":"Bayern",
    "wof:name":"Aral Ag",
    "wof:placetype":"venue"
},
  "geometry": {"coordinates":[12.1388368607,48.5495643616],"type":"Point"}
}