{
  "type": "Feature",
  "properties": {
    "iso:country":"DE",
    "sg:address":"Hilsbach 11",
    "sg:city":"Aurach",
    "sg:phone":"+49 9804/292",
    "sg:postcode":"91589",
    "sg:province":"Bayern",
    "wof:name":"Josef Fuchs",
    "wof:placetype":"venue"
},
  "geometry": {"coordinates":[10.4530334473,49.2406387329],"type":"Point"}
}