{
  "type": "Feature",
  "properties": {
    "iso:country":"DE",
    "sg:address":"Finkenherd 5",
    "sg:city":"St. Peter",
    "sg:phone":"+49 7660/1292",
    "sg:postcode":"79271",
    "sg:province":"Baden-W\u00fcrttemberg",
    "wof:name":"Elisabeth Abels Fremdenheim",
    "wof:placetype":"venue"
},
  "geometry": {"coordinates":[8.030670166,48.014629364],"type":"Point"}
}