{
  "type": "Feature",
  "properties": {
    "iso:country":"DE",
    "sg:address":"Coesfelder Str. 23",
    "sg:city":"D\u00fclmen",
    "sg:phone":"+49 2594/87749",
    "sg:postcode":"48249",
    "sg:province":"Nordrhein-Westfalen",
    "wof:name":"Johannes Frins",
    "wof:placetype":"venue"
},
  "geometry": {"coordinates":[7.27736,51.831303],"type":"Point"}
}