{
  "type": "Feature",
  "properties": {
    "iso:country":"DE",
    "sg:address":"G\u00f6tzendorfer Str. 5",
    "sg:city":"Salzweg",
    "sg:phone":"+49 8505/1229",
    "sg:postcode":"94121",
    "sg:province":"Bayern",
    "wof:name":"Kath. Pfarramt St. Aegidius",
    "wof:placetype":"venue"
},
  "geometry": {"coordinates":[13.4863996506,48.6322517395],"type":"Point"}
}