{
  "type": "Feature",
  "properties": {
    "iso:country":"DE",
    "sg:address":"August-Bebel-Str. 2",
    "sg:city":"Waltersdorf",
    "sg:phone":"+49 35841/36330",
    "sg:postcode":"02799",
    "sg:province":"Sachsen",
    "wof:name":"Joachim Liebscher",
    "wof:placetype":"venue"
},
  "geometry": {"coordinates":[14.651642,50.868778],"type":"Point"}
}