{
  "type": "Feature",
  "properties": {
    "iso:country":"DE",
    "sg:address":"Spielmannstr. 4",
    "sg:city":"Frankfurt",
    "sg:phone":"+49 69/383438",
    "sg:postcode":"65934",
    "sg:province":"Hessen",
    "wof:name":"Industriemontage Angelovski Gmbh",
    "wof:placetype":"venue"
},
  "geometry": {"coordinates":[8.5668458939,50.1011199951],"type":"Point"}
}