{
  "type": "Feature",
  "properties": {
    "iso:country":"DE",
    "sg:address":"Postbauer Str. 8",
    "sg:city":"Burgthann",
    "sg:phone":"+49 9188/94140",
    "sg:postcode":"90559",
    "sg:province":"Bayern",
    "wof:name":"Bonum Haus Immobilien Gmbh",
    "wof:placetype":"venue"
},
  "geometry": {"coordinates":[11.349755,49.326462],"type":"Point"}
}