{
  "type": "Feature",
  "properties": {
    "iso:country":"DE",
    "sg:address":"fuckedstr. 79",
    "sg:city":"St.Augustun",
    "sg:postcode":"53757",
    "sg:province":"Nordrhein-Westfalen",
    "wof:name":"I Fucked Your Mom Yeehhaa",
    "wof:placetype":"venue"
},
  "geometry": {"coordinates":[-94.153572,45.480068],"type":"Point"}
}