{
  "type": "Feature",
  "properties": {
    "iso:country":"DE",
    "sg:address":"Joachimsthaler Str. 7",
    "sg:city":"Annaberg-Buchholz",
    "sg:phone":"+49 3733/23208",
    "sg:postcode":"09456",
    "sg:province":"Sachsen",
    "wof:name":"R. Friedrich",
    "wof:placetype":"venue"
},
  "geometry": {"coordinates":[13.0088195801,50.5660400391],"type":"Point"}
}