{
  "type": "Feature",
  "properties": {
    "iso:country":"DE",
    "sg:address":"Gewerbestr 13",
    "sg:city":"Nossen",
    "sg:phone":"+49 6621/9500",
    "sg:postcode":"01683",
    "sg:province":"Sachsen",
    "wof:name":"Tit-turbo Gmbh",
    "wof:placetype":"venue"
},
  "geometry": {"coordinates":[9.689961,50.855247],"type":"Point"}
}