{
  "type": "Feature",
  "properties": {
    "iso:country":"DE",
    "sg:address":"Wintermoorer Str. 42",
    "sg:city":"Schneverdingen",
    "sg:phone":"+49 5198/261",
    "sg:postcode":"29640",
    "sg:province":"Niedersachsen",
    "wof:name":"Wilhelm T\u00f6dter",
    "wof:placetype":"venue"
},
  "geometry": {"coordinates":[9.83366,53.151634],"type":"Point"}
}