{
  "type": "Feature",
  "properties": {
    "iso:country":"DE",
    "sg:address":"Wutachm\u00fchle 1",
    "sg:city":"Wutach",
    "sg:phone":"+49 7709/271",
    "sg:postcode":"79879",
    "sg:province":"Baden-W\u00fcrttemberg",
    "wof:name":"Rudolf Riester",
    "wof:placetype":"venue"
},
  "geometry": {"coordinates":[8.4491386414,47.8481063843],"type":"Point"}
}