{
  "type": "Feature",
  "properties": {
    "iso:country":"DE",
    "sg:address":"Saarbr\u00fcckener Str. 2",
    "sg:city":"Bremen",
    "sg:phone":"+49 421/432870",
    "sg:postcode":"28211",
    "sg:province":"Bremen",
    "wof:name":"Nordwest Dienstleistungs- Und Handelsges. Mbh",
    "wof:placetype":"venue"
},
  "geometry": {"coordinates":[8.8411998749,53.078830719],"type":"Point"}
}