{
  "type": "Feature",
  "properties": {
    "iso:country":"DE",
    "sg:address":"Schlierbacher Landstr. 200 a",
    "sg:city":"Heidelberg",
    "sg:phone":"+49 6221/965",
    "sg:postcode":"69118",
    "sg:province":"Baden-W\u00fcrttemberg",
    "wof:name":"Orthop\u00e4dische Klinik Der Universit\u00e4t Heidelberg",
    "wof:placetype":"venue"
},
  "geometry": {"coordinates":[8.775082,49.409966],"type":"Point"}
}