{
  "type": "Feature",
  "properties": {
    "iso:country":"DE",
    "sg:address":"Kolbermoorer Str. 46",
    "sg:city":"Gro\u00dfkarolinenfeld",
    "sg:phone":"+49 8031/50921",
    "sg:postcode":"83109",
    "sg:province":"Bayern",
    "wof:name":"Wolfhart Wunder",
    "wof:placetype":"venue"
},
  "geometry": {"coordinates":[12.068291,47.880428],"type":"Point"}
}