{
  "type": "Feature",
  "properties": {
    "iso:country":"DE",
    "sg:address":"Thomas-M\u00fcntzer-Str. 15b",
    "sg:city":"Bautzen",
    "sg:phone":"+49 3591/210177",
    "sg:postcode":"02625",
    "sg:province":"Sachsen",
    "wof:name":"Eberhard Jankowsky",
    "wof:placetype":"venue"
},
  "geometry": {"coordinates":[14.447221,51.182259],"type":"Point"}
}