{
  "type": "Feature",
  "properties": {
    "iso:country":"DE",
    "sg:address":"Weinbergweg 11",
    "sg:city":"Kelheim",
    "sg:phone":"+49 9441/3386",
    "sg:postcode":"93309",
    "sg:province":"Bayern",
    "wof:name":"Heinrich Hierl",
    "wof:placetype":"venue"
},
  "geometry": {"coordinates":[11.8829145432,48.9206809998],"type":"Point"}
}