{
  "type": "Feature",
  "properties": {
    "iso:country":"DE",
    "sg:address":"Delmenhorster Str. 314",
    "sg:city":"Stuhr",
    "sg:phone":"+49 4206/7350",
    "sg:postcode":"28816",
    "sg:province":"Niedersachsen",
    "wof:name":"Friedrich Windhorst",
    "wof:placetype":"venue"
},
  "geometry": {"coordinates":[8.683325,53.031616],"type":"Point"}
}