{
  "type": "Feature",
  "properties": {
    "iso:country":"DE",
    "sg:address":"Borsigstr. 29",
    "sg:city":"Reinbek",
    "sg:postcode":"21465",
    "sg:province":"Schleswig-Holstein",
    "wof:name":"Fom Frank Oldenburg Marketing Gmbh",
    "wof:placetype":"venue"
},
  "geometry": {"coordinates":[10.2402954102,53.5271148682],"type":"Point"}
}