{
  "type": "Feature",
  "properties": {
    "iso:country":"DE",
    "sg:address":"Am Gr\u00f6nland 3",
    "sg:city":"Breckerfeld",
    "sg:phone":"+49 2338/1251",
    "sg:postcode":"58339",
    "sg:province":"Nordrhein-Westfalen",
    "wof:name":"Beli Elektro- Vertriebsgesellschaft Mbh",
    "wof:placetype":"venue"
},
  "geometry": {"coordinates":[7.4710431099,51.2579574585],"type":"Point"}
}