{
  "type": "Feature",
  "properties": {
    "iso:country":"DE",
    "sg:address":"W\u00e4chterstr. 5",
    "sg:city":"Stuttgart",
    "sg:phone":"+49 711/242952",
    "sg:postcode":"70182",
    "sg:province":"Baden-W\u00fcrttemberg",
    "wof:name":"Kim-chung Nguyen Dipl. \u00dcbersetzerin",
    "wof:placetype":"venue"
},
  "geometry": {"coordinates":[9.18491,48.769894],"type":"Point"}
}