{
  "type": "Feature",
  "properties": {
    "iso:country":"DE",
    "sg:address":"Marktstr. 9-11",
    "sg:city":"Schw\u00e4bisch Hall",
    "sg:postcode":"74523",
    "sg:province":"Baden-W\u00fcrttemberg",
    "wof:name":"Heckelmann Gmbh",
    "wof:placetype":"venue"
},
  "geometry": {"coordinates":[9.7364120483,49.1134719849],"type":"Point"}
}