{
  "type": "Feature",
  "properties": {
    "iso:country":"DE",
    "sg:address":"Bahnhofstr. 24",
    "sg:city":"Gie\u00dfen",
    "sg:phone":"+49 641/974150",
    "sg:postcode":"35390",
    "sg:province":"Hessen",
    "wof:name":"H. Glotzbach",
    "wof:placetype":"venue"
},
  "geometry": {"coordinates":[8.6710662842,50.5848999023],"type":"Point"}
}