{
  "type": "Feature",
  "properties": {
    "iso:country":"DE",
    "sg:address":"Klein-Erkenschwicker-Str. 158b",
    "sg:city":"Oer-Erkenschwick",
    "sg:phone":"+49 2368/98510",
    "sg:postcode":"45739",
    "sg:province":"Nordrhein-Westfalen",
    "wof:name":"Ms Plus Dichtungstechnik Manfred Sch\u00fcrk E. K.",
    "wof:placetype":"venue"
},
  "geometry": {"coordinates":[7.26226,51.64941],"type":"Point"}
}