{
  "type": "Feature",
  "properties": {
    "iso:country":"DE",
    "sg:address":"Kastanienweg 1",
    "sg:city":"S\u00fclfeld",
    "sg:phone":"+49 4537/18030",
    "sg:postcode":"23867",
    "sg:province":"Schleswig-Holstein",
    "wof:name":"Convenience Marketing Gmbh",
    "wof:placetype":"venue"
},
  "geometry": {"coordinates":[10.2223796844,53.80235672],"type":"Point"}
}