{
  "type": "Feature",
  "properties": {
    "iso:country":"DE",
    "sg:address":"Mozartring 48",
    "sg:city":"Melle",
    "sg:phone":"+49 5422/1641",
    "sg:postcode":"49324",
    "sg:province":"Niedersachsen",
    "wof:name":"Reinhard Otte E. K.",
    "wof:placetype":"venue"
},
  "geometry": {"coordinates":[8.3419628143,52.1943740845],"type":"Point"}
}