{
  "type": "Feature",
  "properties": {
    "iso:country":"DE",
    "sg:address":"Kannenb\u00e4ckerstr. 16",
    "sg:city":"Ransbach-Baumbach",
    "sg:phone":"+49 2623/800490",
    "sg:postcode":"56235",
    "sg:province":"Rheinland-Pfalz",
    "wof:name":"Em Pr\u00e4sent-ideen Gmbh",
    "wof:placetype":"venue"
},
  "geometry": {"coordinates":[7.7101311684,50.4557571411],"type":"Point"}
}