{
  "type": "Feature",
  "properties": {
    "iso:country":"DE",
    "sg:address":"Silberstr. 21 a",
    "sg:city":"Koblenz",
    "sg:phone":"+49 261/69413",
    "sg:postcode":"56077",
    "sg:province":"Rheinland-Pfalz",
    "wof:name":"Horst Klee",
    "wof:placetype":"venue"
},
  "geometry": {"coordinates":[7.65331,50.365059],"type":"Point"}
}