{
  "type": "Feature",
  "properties": {
    "iso:country":"DE",
    "sg:address":"Friedrichsfelder Landstr. 2",
    "sg:city":"Schwetzingen",
    "sg:phone":"+49 6202/10802",
    "sg:postcode":"68723",
    "sg:province":"Baden-W\u00fcrttemberg",
    "wof:name":"Berthold Siegel",
    "wof:placetype":"venue"
},
  "geometry": {"coordinates":[8.565652,49.394188],"type":"Point"}
}