{
  "type": "Feature",
  "properties": {
    "iso:country":"DE",
    "sg:address":"Bergstr. 137",
    "sg:city":"Pretzschendorf",
    "sg:phone":"+49 3504/6230",
    "sg:postcode":"01774",
    "sg:province":"Sachsen",
    "wof:name":"Seniorenheim Der Awo Ggmbh",
    "wof:placetype":"venue"
},
  "geometry": {"coordinates":[13.52774,50.872791],"type":"Point"}
}