{
  "type": "Feature",
  "properties": {
    "iso:country":"DE",
    "sg:address":"Nordstrander Str. 8",
    "sg:city":"Husum",
    "sg:phone":"+49 4841/2015",
    "sg:postcode":"25813",
    "sg:province":"Schleswig-Holstein",
    "wof:name":"Volker Saupe",
    "wof:placetype":"venue"
},
  "geometry": {"coordinates":[9.0639457703,54.4652061462],"type":"Point"}
}