{
  "type": "Feature",
  "properties": {
    "iso:country":"DE",
    "sg:address":"Banderbacher Str. 24",
    "sg:city":"Zirndorf",
    "sg:phone":"+49 911/609595",
    "sg:postcode":"90513",
    "sg:province":"Bayern",
    "wof:name":"Peter Lang",
    "wof:placetype":"venue"
},
  "geometry": {"coordinates":[10.9519138336,49.4425163269],"type":"Point"}
}