{
  "type": "Feature",
  "properties": {
    "iso:country":"DE",
    "sg:address":"Im Benzwasen 18",
    "sg:city":"Backnang",
    "sg:phone":"+49 7191/88199",
    "sg:postcode":"71522",
    "sg:province":"Baden-W\u00fcrttemberg",
    "wof:name":"Fischer",
    "wof:placetype":"venue"
},
  "geometry": {"coordinates":[9.44,48.937767],"type":"Point"}
}