{
  "type": "Feature",
  "properties": {
    "iso:country":"DE",
    "sg:address":"Eulenweg 11",
    "sg:city":"Landsberg",
    "sg:postcode":"86899",
    "sg:province":"Bayern",
    "wof:name":"Lebenshilfe Landsberg Gemeinn\u00fctzige Gmbh",
    "wof:placetype":"venue"
},
  "geometry": {"coordinates":[10.897622,48.050076],"type":"Point"}
}