{
  "type": "Feature",
  "properties": {
    "iso:country":"DE",
    "sg:address":"Saizig 9",
    "sg:city":"Klettgau",
    "sg:phone":"+49 7742/2628",
    "sg:postcode":"79771",
    "sg:province":"Baden-W\u00fcrttemberg",
    "wof:name":"Schilling Engineering Gmbh",
    "wof:placetype":"venue"
},
  "geometry": {"coordinates":[8.418529,47.656906],"type":"Point"}
}