{
  "type": "Feature",
  "properties": {
    "iso:country":"DE",
    "sg:address":"Bahnhofstr. 11",
    "sg:city":"Elend",
    "sg:phone":"+49 39455/259",
    "sg:postcode":"38875",
    "sg:province":"Sachsen-Anhalt",
    "wof:name":"Manfred Spengler",
    "wof:placetype":"venue"
},
  "geometry": {"coordinates":[10.6921873093,51.7469215393],"type":"Point"}
}