{
  "type": "Feature",
  "properties": {
    "iso:country":"DE",
    "sg:address":"Talstr. 38",
    "sg:city":"Lohr",
    "sg:phone":"+49 9352/1035",
    "sg:postcode":"97816",
    "sg:province":"Bayern",
    "wof:name":"Georg Sanden Elektroinstallation",
    "wof:placetype":"venue"
},
  "geometry": {"coordinates":[9.588084,49.960358],"type":"Point"}
}