{
  "type": "Feature",
  "properties": {
    "iso:country":"DE",
    "sg:address":"Wolfsegger Str. 19",
    "sg:city":"Lappersdorf",
    "sg:phone":"+49 941/80335",
    "sg:postcode":"93138",
    "sg:province":"Bayern",
    "wof:name":"Danner Pilznahrungsmittelwerk K. Horst",
    "wof:placetype":"venue"
},
  "geometry": {"coordinates":[12.070602417,49.0526771545],"type":"Point"}
}