{
  "type": "Feature",
  "properties": {
    "iso:country":"DE",
    "sg:address":"Kiesstr. 41",
    "sg:city":"Darmstadt",
    "sg:phone":"+49 6151/42760",
    "sg:postcode":"64283",
    "sg:province":"Hessen",
    "wof:name":"Rodenh\u00e4user Und Kollegen Rechtsanw\u00e4lte Und Notare",
    "wof:placetype":"venue"
},
  "geometry": {"coordinates":[8.6592979431,49.8682289124],"type":"Point"}
}