{
  "type": "Feature",
  "properties": {
    "iso:country":"DE",
    "sg:city":"Tauberbischofsheim",
    "sg:phone":"+49 9341/5537",
    "sg:postcode":"97941",
    "sg:province":"Baden-W\u00fcrttemberg",
    "wof:name":"Tip Top Gmbh Fahrzeugpflege",
    "wof:placetype":"venue"
},
  "geometry": {"coordinates":[9.665531,49.623524],"type":"Point"}
}