{
  "type": "Feature",
  "properties": {
    "iso:country":"DE",
    "sg:address":"Badeweg 50",
    "sg:city":"L\u00f6hne",
    "sg:phone":"+49 5732/71880",
    "sg:postcode":"32584",
    "sg:province":"Nordrhein-Westfalen",
    "wof:name":"Awo Altenwohnungen",
    "wof:placetype":"venue"
},
  "geometry": {"coordinates":[8.741924,52.218632],"type":"Point"}
}