{
  "type": "Feature",
  "properties": {
    "iso:country":"DE",
    "sg:address":"Talstr. 39",
    "sg:city":"Malsch",
    "sg:phone":"+49 7246/5615",
    "sg:postcode":"76316",
    "sg:province":"Baden-W\u00fcrttemberg",
    "wof:name":"Norbert Tonk",
    "wof:placetype":"venue"
},
  "geometry": {"coordinates":[8.331747,48.858063],"type":"Point"}
}