{
  "type": "Feature",
  "properties": {
    "iso:country":"DE",
    "sg:address":"R\u00f6merstr. 1",
    "sg:city":"Schriesheim",
    "sg:phone":"+49 6203/61246",
    "sg:postcode":"69198",
    "sg:province":"Baden-W\u00fcrttemberg",
    "wof:name":"F. Bre\u00dfler",
    "wof:placetype":"venue"
},
  "geometry": {"coordinates":[8.658811,49.474663],"type":"Point"}
}