{
  "type": "Feature",
  "properties": {
    "iso:country":"DE",
    "sg:address":"Alsweder Ring 22",
    "sg:city":"L\u00fcbbecke",
    "sg:phone":"+49 5743",
    "sg:postcode":"32312",
    "sg:province":"Nordrhein-Westfalen",
    "wof:name":"Deutsche Krankenversicherung Ag, B\u00fcro Lothar Tegeler",
    "wof:placetype":"venue"
},
  "geometry": {"coordinates":[8.6082859039,52.310005188],"type":"Point"}
}