{
  "type": "Feature",
  "properties": {
    "iso:country":"DE",
    "sg:address":"Auestr. 32",
    "sg:city":"Bremerv\u00f6rde",
    "sg:phone":"+49 4764/282",
    "sg:postcode":"27432",
    "sg:province":"Niedersachsen",
    "wof:name":"Wasserversorgungsverband Minstedt",
    "wof:placetype":"venue"
},
  "geometry": {"coordinates":[9.1349954605,53.4473457336],"type":"Point"}
}