{
  "type": "Feature",
  "properties": {
    "iso:country":"DE",
    "sg:address":"Seeshaupter Str. 35",
    "sg:city":"M\u00fcnsing",
    "sg:phone":"+49 8801/2116",
    "sg:postcode":"82541",
    "sg:province":"Bayern",
    "wof:name":"Dr. Wolfgang Bl\u00f6ckner",
    "wof:placetype":"venue"
},
  "geometry": {"coordinates":[11.334569931,47.8217086792],"type":"Point"}
}