{
  "type": "Feature",
  "properties": {
    "iso:country":"DE",
    "sg:address":"Neuenburger Str. 4",
    "sg:city":"Zetel",
    "sg:phone":"+49 4453/2533",
    "sg:postcode":"26340",
    "sg:province":"Niedersachsen",
    "wof:name":"Praxis Tammer Und Dr. Med. Yeung",
    "wof:placetype":"venue"
},
  "geometry": {"coordinates":[7.972849,53.417606],"type":"Point"}
}