{
  "type": "Feature",
  "properties": {
    "iso:country":"DE",
    "sg:address":"Breitfeldstr. 31",
    "sg:city":"P\u00fcttlingen",
    "sg:phone":"+49 6898/62438",
    "sg:postcode":"66346",
    "sg:province":"Saarland",
    "wof:name":"Susanne Bormann E. Kfr.",
    "wof:placetype":"venue"
},
  "geometry": {"coordinates":[6.8855881691,49.2952308655],"type":"Point"}
}