{
  "type": "Feature",
  "properties": {
    "iso:country":"DE",
    "sg:address":"Backhauspforte 11",
    "sg:city":"Frei-Laubersheim",
    "sg:phone":"+49 6709/222",
    "sg:postcode":"55546",
    "sg:province":"Rheinland-Pfalz",
    "wof:name":"Otto Metzler",
    "wof:placetype":"venue"
},
  "geometry": {"coordinates":[7.8969511986,49.7995300293],"type":"Point"}
}