{
  "type": "Feature",
  "properties": {
    "iso:country":"DE",
    "sg:address":"Hunackerhof",
    "sg:city":"Mandelbachtal",
    "sg:phone":"+49 6893/2310",
    "sg:postcode":"66399",
    "sg:province":"Saarland",
    "wof:name":"Walter Hoffmann",
    "wof:placetype":"venue"
},
  "geometry": {"coordinates":[7.13268,49.179672],"type":"Point"}
}