{
  "type": "Feature",
  "properties": {
    "iso:country":"DE",
    "sg:address":"Richard-Wagner-Str. 11",
    "sg:city":"Berlin",
    "sg:phone":"+49 30/345468",
    "sg:postcode":"10585",
    "sg:province":"Berlin",
    "wof:name":"Ernst Brubacher Architekt",
    "wof:placetype":"venue"
},
  "geometry": {"coordinates":[13.306791,52.513287],"type":"Point"}
}