{
  "type": "Feature",
  "properties": {
    "iso:country":"DE",
    "sg:address":"Freiberger Str. 16",
    "sg:city":"Wilsdruff",
    "sg:phone":"+49 35204/48456",
    "sg:postcode":"01723",
    "sg:province":"Sachsen",
    "wof:name":"Freitaler Bestattungen",
    "wof:placetype":"venue"
},
  "geometry": {"coordinates":[13.538478,51.049774],"type":"Point"}
}