{
  "type": "Feature",
  "properties": {
    "iso:country":"DE",
    "sg:address":"Jahnstr. 6",
    "sg:city":"Moers",
    "sg:phone":"+49 2841/54071",
    "sg:postcode":"47443",
    "sg:province":"Nordrhein-Westfalen",
    "wof:name":"Heinz K\u00e4mper Gmbh",
    "wof:placetype":"venue"
},
  "geometry": {"coordinates":[6.644229,51.460144],"type":"Point"}
}