{
  "type": "Feature",
  "properties": {
    "iso:country":"DE",
    "sg:address":"Saargem\u00fcnder Str. 136",
    "sg:city":"Saarbr\u00fccken",
    "sg:phone":"+49 681/398098",
    "sg:postcode":"66119",
    "sg:province":"Saarland",
    "wof:name":"Honorarkonsulat Der Republik Kap Verde",
    "wof:placetype":"venue"
},
  "geometry": {"coordinates":[7.0159511566,49.2173423767],"type":"Point"}
}