{
  "type": "Feature",
  "properties": {
    "iso:country":"DE",
    "sg:address":"Sandtrift 85",
    "sg:city":"Minden",
    "sg:phone":"+49 571/6469030",
    "sg:postcode":"32425",
    "sg:province":"Nordrhein-Westfalen",
    "wof:name":"R\u00fcter Ingenieurleistungen Bauwesen Verwaltungs- Gmbh",
    "wof:placetype":"venue"
},
  "geometry": {"coordinates":[8.892353,52.309227],"type":"Point"}
}