{
  "type": "Feature",
  "properties": {
    "iso:country":"DE",
    "sg:address":"Hildesheimer Str. 365",
    "sg:city":"Hannover",
    "sg:phone":"+49 511/864368",
    "sg:postcode":"30519",
    "sg:province":"Niedersachsen",
    "wof:name":"Katholisches Pfarramt St. Michael",
    "wof:placetype":"venue"
},
  "geometry": {"coordinates":[9.7769193649,52.328792572],"type":"Point"}
}