{
  "type": "Feature",
  "properties": {
    "iso:country":"DE",
    "sg:address":"Hauptstr. 32",
    "sg:city":"Hemmingen",
    "sg:phone":"+49 7150/81520",
    "sg:postcode":"71282",
    "sg:province":"Baden-W\u00fcrttemberg",
    "wof:name":"Eiscafe-pizzeria Pavione",
    "wof:placetype":"venue"
},
  "geometry": {"coordinates":[9.0314760208,48.8652000427],"type":"Point"}
}