{
  "type": "Feature",
  "properties": {
    "iso:country":"DE",
    "sg:address":"Schaffeld 1",
    "sg:city":"Meinerzhagen",
    "sg:phone":"+49 2358/587",
    "sg:postcode":"58540",
    "sg:province":"Nordrhein-Westfalen",
    "wof:name":"Ulrike Turk-blass Steuerbevollm\u00e4chtigte",
    "wof:placetype":"venue"
},
  "geometry": {"coordinates":[7.7921662331,51.1261749268],"type":"Point"}
}