{
  "type": "Feature",
  "properties": {
    "iso:country":"DE",
    "sg:address":"Kl\u00f6cknerstr. 1",
    "sg:city":"Werne",
    "sg:phone":"+49 2389/536636",
    "sg:postcode":"59368",
    "sg:province":"Nordrhein-Westfalen",
    "wof:name":"M\u00fcnsterland",
    "wof:placetype":"venue"
},
  "geometry": {"coordinates":[7.6504640579,51.6618995667],"type":"Point"}
}