{
  "type": "Feature",
  "properties": {
    "iso:country":"DE",
    "sg:address":"L\u00f6hberg 22",
    "sg:city":"M\u00fclheim",
    "sg:phone":"+49 208/473493",
    "sg:postcode":"45468",
    "sg:province":"Nordrhein-Westfalen",
    "wof:name":"Hans Pieper Gmbh",
    "wof:placetype":"venue"
},
  "geometry": {"coordinates":[6.88152,51.428509],"type":"Point"}
}