{
  "type": "Feature",
  "properties": {
    "iso:country":"DE",
    "sg:address":"Schlo\u00dfplatz 4",
    "sg:city":"Aschaffenburg",
    "sg:phone":"+49 6021/386740",
    "sg:postcode":"63739",
    "sg:province":"Bayern",
    "wof:name":"Museum Der Stadt Aschaffenburg",
    "wof:placetype":"venue"
},
  "geometry": {"coordinates":[9.1426,49.975666],"type":"Point"}
}