{
  "type": "Feature",
  "properties": {
    "iso:country":"DE",
    "sg:address":"Haus-Knipp-Str. 23",
    "sg:city":"Duisburg",
    "sg:phone":"+49 203/870940",
    "sg:postcode":"47139",
    "sg:province":"Nordrhein-Westfalen",
    "wof:name":"Vater Rhein",
    "wof:placetype":"venue"
},
  "geometry": {"coordinates":[6.7010421753,51.4748268127],"type":"Point"}
}