{
  "type": "Feature",
  "properties": {
    "iso:country":"DE",
    "sg:address":"Maurershorn 10",
    "sg:city":"Reichenau",
    "sg:phone":"+49 7534/7190",
    "sg:postcode":"78479",
    "sg:province":"Baden-W\u00fcrttemberg",
    "wof:name":"H. Welte",
    "wof:placetype":"venue"
},
  "geometry": {"coordinates":[9.0729122162,47.6860656738],"type":"Point"}
}