{
  "type": "Feature",
  "properties": {
    "iso:country":"DE",
    "sg:address":"Fichtenstr. 67a",
    "sg:city":"F\u00fcrth",
    "sg:phone":"+49 911/772885",
    "sg:postcode":"90763",
    "sg:province":"Bayern",
    "wof:name":"Seppl Schneider",
    "wof:placetype":"venue"
},
  "geometry": {"coordinates":[10.9934005737,49.4658355713],"type":"Point"}
}