{
  "type": "Feature",
  "properties": {
    "iso:country":"DE",
    "sg:address":"Unterster Zwerchweg 57",
    "sg:city":"Frankfurt",
    "sg:phone":"+49 69/683115",
    "sg:postcode":"60599",
    "sg:province":"Hessen",
    "wof:name":"Lina Klein",
    "wof:placetype":"venue"
},
  "geometry": {"coordinates":[8.6955060959,50.0947952271],"type":"Point"}
}