{
  "type": "Feature",
  "properties": {
    "iso:country":"DE",
    "sg:address":"Rosenplatz 7",
    "sg:city":"Chemnitz",
    "sg:phone":"+49 4937/1519949",
    "sg:postcode":"09126",
    "sg:province":"Sachsen",
    "wof:name":"Das Kneipen- Erlebniss Der Besonderen Art",
    "wof:placetype":"venue"
},
  "geometry": {"coordinates":[12.94432,50.812183],"type":"Point"}
}