{
  "type": "Feature",
  "properties": {
    "iso:country":"DE",
    "sg:address":"Ligusterweg 21",
    "sg:city":"Lauffen",
    "sg:phone":"+49 7133/963109",
    "sg:postcode":"74348",
    "sg:province":"Baden-W\u00fcrttemberg",
    "wof:name":"Umec-elektronische- Komponenten Gmbh",
    "wof:placetype":"venue"
},
  "geometry": {"coordinates":[9.1404,49.064861],"type":"Point"}
}