{
  "type": "Feature",
  "properties": {
    "iso:country":"DE",
    "sg:address":"Mathias-Br\u00fcggen-Str 10",
    "sg:city":"K\u00f6ln",
    "sg:phone":"+49 221/5953035",
    "sg:postcode":"50827",
    "sg:province":"Nordrhein-Westfalen",
    "wof:name":"Spedition Heinrich Schlang Gmbh",
    "wof:placetype":"venue"
},
  "geometry": {"coordinates":[6.8903651237,50.9664115906],"type":"Point"}
}