{
  "type": "Feature",
  "properties": {
    "iso:country":"DE",
    "sg:address":"Martinstr. 25",
    "sg:city":"Bonndorf",
    "sg:phone":"+49 7703/91100",
    "sg:postcode":"79848",
    "sg:province":"Baden-W\u00fcrttemberg",
    "wof:name":"Schwarzwald-apotheke",
    "wof:placetype":"venue"
},
  "geometry": {"coordinates":[8.341005,47.82021],"type":"Point"}
}