{
  "type": "Feature",
  "properties": {
    "iso:country":"DE",
    "sg:address":"B\u00f6hmerstr. 55",
    "sg:city":"R\u00f6tz",
    "sg:phone":"+49 9976/94060",
    "sg:postcode":"92444",
    "sg:province":"Bayern",
    "wof:name":"La Sat Landkammer Satelliten- Empfangstechnik Gmbh",
    "wof:placetype":"venue"
},
  "geometry": {"coordinates":[12.5374336243,49.3425521851],"type":"Point"}
}