{
  "type": "Feature",
  "properties": {
    "iso:country":"DE",
    "sg:address":"Westwall 11",
    "sg:city":"Korbach",
    "sg:phone":"+49 5631/4041",
    "sg:postcode":"34497",
    "sg:province":"Hessen",
    "wof:name":"Siegfried Reuter Steuerberater",
    "wof:placetype":"venue"
},
  "geometry": {"coordinates":[8.8690538406,51.2706184387],"type":"Point"}
}