{
  "type": "Feature",
  "properties": {
    "iso:country":"DE",
    "sg:address":"Beuthener Str. 16",
    "sg:city":"Wegberg",
    "sg:phone":"+49 2436/339017",
    "sg:postcode":"41844",
    "sg:province":"Nordrhein-Westfalen",
    "wof:name":"Helmut Weiss",
    "wof:placetype":"venue"
},
  "geometry": {"coordinates":[6.1835808754,51.1553039551],"type":"Point"}
}