{
  "type": "Feature",
  "properties": {
    "iso:country":"DE",
    "sg:address":"Weststr 24d",
    "sg:city":"Aachen",
    "sg:phone":"+49 241/8797030",
    "sg:postcode":"52074",
    "sg:province":"Nordrhein-Westfalen",
    "wof:name":"Wsp Ingenieurges. F\u00fcr W\u00e4rmetechnik, Str\u00f6mungstechnik Und Proze\u00dftechnik Mbh",
    "wof:placetype":"venue"
},
  "geometry": {"coordinates":[6.0611810684,50.7717056274],"type":"Point"}
}