{
  "type": "Feature",
  "properties": {
    "iso:country":"DE",
    "sg:address":"Goethestr. 21",
    "sg:city":"Sindelfingen",
    "sg:phone":"+49 7031/382355",
    "sg:postcode":"71069",
    "sg:province":"Baden-W\u00fcrttemberg",
    "wof:name":"Hans Herbstritt",
    "wof:placetype":"venue"
},
  "geometry": {"coordinates":[8.961876,48.72253],"type":"Point"}
}