{
  "type": "Feature",
  "properties": {
    "iso:country":"DE",
    "sg:address":"Br\u00fcggenpoth 54",
    "sg:city":"Marl",
    "sg:phone":"+49 2365/18806",
    "sg:postcode":"45768",
    "sg:province":"Nordrhein-Westfalen",
    "wof:name":"Martin M\u00fcller Innenarchitekt",
    "wof:placetype":"venue"
},
  "geometry": {"coordinates":[7.055177,51.631382],"type":"Point"}
}