{
  "type": "Feature",
  "properties": {
    "iso:country":"DE",
    "sg:address":"Buchrainweg 59",
    "sg:city":"Offenbach",
    "sg:phone":"+49 69/841283",
    "sg:postcode":"63069",
    "sg:province":"Hessen",
    "wof:name":"Ernst M\u00fcller Inh. Wolfgang Prechtl",
    "wof:placetype":"venue"
},
  "geometry": {"coordinates":[8.7477607727,50.0937385559],"type":"Point"}
}