{
  "type": "Feature",
  "properties": {
    "iso:country":"DE",
    "sg:address":"Jakob-Krebs-Str. 29",
    "sg:city":"Willich",
    "sg:phone":"+49 2156/3434",
    "sg:postcode":"47877",
    "sg:province":"Nordrhein-Westfalen",
    "wof:name":"Marlies Lade",
    "wof:placetype":"venue"
},
  "geometry": {"coordinates":[6.4604401588,51.2790565491],"type":"Point"}
}