{
  "type": "Feature",
  "properties": {
    "iso:country":"DE",
    "sg:address":"Auf der T\u00f6dtheide 11",
    "sg:city":"Bielefeld",
    "sg:postcode":"33729",
    "sg:province":"Nordrhein-Westfalen",
    "wof:name":"Van Empel Yachting Gmbh",
    "wof:placetype":"venue"
},
  "geometry": {"coordinates":[8.5847663879,52.0773735046],"type":"Point"}
}