{
  "type": "Feature",
  "properties": {
    "iso:country":"DE",
    "sg:address":"Untere Hainbachstr. 50",
    "sg:city":"Biedenkopf",
    "sg:phone":"+49 6461/8202",
    "sg:postcode":"35216",
    "sg:province":"Hessen",
    "wof:name":"Gefl\u00fcgelhof Hainbachtal Verwaltungs Gmbh",
    "wof:placetype":"venue"
},
  "geometry": {"coordinates":[8.4734258652,50.934299469],"type":"Point"}
}