{
  "type": "Feature",
  "properties": {
    "iso:country":"DE",
    "sg:address":"Hinterbreitenthann 11",
    "sg:city":"Feuchtwangen",
    "sg:phone":"+49 9852/1777",
    "sg:postcode":"91555",
    "sg:province":"Bayern",
    "wof:name":"K. Fenn",
    "wof:placetype":"venue"
},
  "geometry": {"coordinates":[10.342371,49.214211],"type":"Point"}
}