{
  "type": "Feature",
  "properties": {
    "iso:country":"DE",
    "sg:address":"Leipziger Str. 280",
    "sg:city":"Kassel",
    "sg:phone":"+49 561/951860",
    "sg:postcode":"34123",
    "sg:province":"Hessen",
    "wof:name":"Max Weishaupt Gmbh",
    "wof:placetype":"venue"
},
  "geometry": {"coordinates":[9.5431394577,51.2960395813],"type":"Point"}
}