{
  "type": "Feature",
  "properties": {
    "iso:country":"DE",
    "sg:address":"Spessartstr. 119",
    "sg:city":"Sulzbach",
    "sg:phone":"+49 6028/997603",
    "sg:postcode":"63834",
    "sg:province":"Bayern",
    "wof:name":"Martin Ziemlich",
    "wof:placetype":"venue"
},
  "geometry": {"coordinates":[9.1641187668,49.9112968445],"type":"Point"}
}