{
  "type": "Feature",
  "properties": {
    "iso:country":"DE",
    "sg:address":"Kurhausstr. 14",
    "sg:city":"Dresden",
    "sg:postcode":"01259",
    "sg:province":"Sachsen",
    "wof:name":"Verein Dialog Zschaschwitz E. V.",
    "wof:placetype":"venue"
},
  "geometry": {"coordinates":[13.8525466919,51.0060424805],"type":"Point"}
}