{
  "type": "Feature",
  "properties": {
    "iso:country":"DE",
    "sg:address":"Br\u00fcckenweg 6",
    "sg:city":"Heilbad Heiligenstadt",
    "sg:phone":"+49 3606/603888",
    "sg:postcode":"37308",
    "sg:province":"Th\u00fcringen",
    "wof:name":"Taverna Poseidon",
    "wof:placetype":"venue"
},
  "geometry": {"coordinates":[10.1495885849,51.372177124],"type":"Point"}
}