{
  "type": "Feature",
  "properties": {
    "iso:country":"DE",
    "sg:address":"Poppenb\u00fctteler Bogen 40",
    "sg:city":"Hamburg",
    "sg:phone":"+49 40/6061011",
    "sg:postcode":"22399",
    "sg:province":"Hamburg",
    "wof:name":"Klaus Hildebrandt Gmbh",
    "wof:placetype":"venue"
},
  "geometry": {"coordinates":[10.070495,53.670952],"type":"Point"}
}