{
  "type": "Feature",
  "properties": {
    "iso:country":"DE",
    "sg:address":"Heinrichstr. 31",
    "sg:city":"Langen",
    "sg:phone":"+49 6103/23671",
    "sg:postcode":"63225",
    "sg:province":"Hessen",
    "wof:name":"W. Und N. Hanke Ingenieure Und Architekten",
    "wof:placetype":"venue"
},
  "geometry": {"coordinates":[8.669863,49.992199],"type":"Point"}
}