{
  "type": "Feature",
  "properties": {
    "iso:country":"DE",
    "sg:address":"33 Avenue Kennedy",
    "sg:city":"Neufchateau",
    "sg:phone":"+49 32/9956225",
    "sg:postcode":"88300",
    "wof:name":"Burotic Formation",
    "wof:placetype":"venue"
},
  "geometry": {"coordinates":[5.69254,48.358501],"type":"Point"}
}