{
  "type": "Feature",
  "properties": {
    "iso:country":"DE",
    "sg:address":"Ludwig-Ganghofer-Str. 16",
    "sg:city":"Neumarkt-Sankt Veit",
    "sg:phone":"+49 8639/8550",
    "sg:postcode":"84494",
    "sg:province":"Bayern",
    "wof:name":"J. Hagn",
    "wof:placetype":"venue"
},
  "geometry": {"coordinates":[12.513002,48.367779],"type":"Point"}
}