{
  "type": "Feature",
  "properties": {
    "iso:country":"DE",
    "sg:address":"Schlotterbeckstr. 11",
    "sg:city":"B\u00f6blingen",
    "sg:phone":"+49 7031/223228",
    "sg:postcode":"71034",
    "sg:province":"Baden-W\u00fcrttemberg",
    "wof:name":"M. Pfeffer",
    "wof:placetype":"venue"
},
  "geometry": {"coordinates":[8.997022,48.682762],"type":"Point"}
}