{
  "type": "Feature",
  "properties": {
    "iso:country":"DE",
    "sg:address":"Schiffbauerdamm 5",
    "sg:city":"Berlin",
    "sg:phone":"+49 30/8012230",
    "sg:postcode":"10117",
    "sg:province":"Berlin",
    "wof:name":"J\u00fcrgen Nottmeyer Architekt",
    "wof:placetype":"venue"
},
  "geometry": {"coordinates":[13.386045,52.521633],"type":"Point"}
}