{
  "type": "Feature",
  "properties": {
    "iso:country":"DE",
    "sg:address":"Ramsberg 21",
    "sg:city":"Sch\u00f6ppingen",
    "sg:phone":"+49 2555/1334",
    "sg:postcode":"48624",
    "sg:province":"Nordrhein-Westfalen",
    "wof:name":"Leo Rehring",
    "wof:placetype":"venue"
},
  "geometry": {"coordinates":[7.220929,52.090191],"type":"Point"}
}