{
  "type": "Feature",
  "properties": {
    "iso:country":"DE",
    "sg:address":"Sondernkamp 1",
    "sg:city":"Gelsenkirchen",
    "sg:phone":"+49 209/581247",
    "sg:postcode":"45897",
    "sg:province":"Nordrhein-Westfalen",
    "wof:name":"Westf\u00e4lische Blindenarbeit E. V.",
    "wof:placetype":"venue"
},
  "geometry": {"coordinates":[7.0665140152,51.5438537598],"type":"Point"}
}