{
  "type": "Feature",
  "properties": {
    "iso:country":"DE",
    "sg:address":"Kappenm\u00fchle 2",
    "sg:city":"Flieden",
    "sg:phone":"+49 6655/2682",
    "sg:postcode":"36103",
    "sg:province":"Hessen",
    "wof:name":"A. B. Auth",
    "wof:placetype":"venue"
},
  "geometry": {"coordinates":[9.5669717789,50.4234046936],"type":"Point"}
}