{
  "type": "Feature",
  "properties": {
    "iso:country":"DE",
    "sg:address":"Hochstr. 9",
    "sg:city":"Herten",
    "sg:phone":"+49 2366/37020",
    "sg:postcode":"45699",
    "sg:province":"Nordrhein-Westfalen",
    "wof:name":"Weinkontor Herten Gmbh",
    "wof:placetype":"venue"
},
  "geometry": {"coordinates":[7.1463007927,51.5941352844],"type":"Point"}
}