{
  "type": "Feature",
  "properties": {
    "iso:country":"DE",
    "sg:address":"Am Hasenbusch 6",
    "sg:city":"Neu Wulmstorf",
    "sg:phone":"+49 4168/722",
    "sg:postcode":"21629",
    "sg:province":"Niedersachsen",
    "wof:name":"Vera Rathke",
    "wof:placetype":"venue"
},
  "geometry": {"coordinates":[9.789555,53.429184],"type":"Point"}
}