{
  "type": "Feature",
  "properties": {
    "iso:country":"DE",
    "sg:address":"Pickelstr. 9a",
    "sg:city":"M\u00fcnchen",
    "sg:phone":"+49 89/154491",
    "sg:postcode":"80637",
    "sg:province":"Bayern",
    "wof:name":"H. Stahlhut \u00dcbersetzer",
    "wof:placetype":"venue"
},
  "geometry": {"coordinates":[11.535285,48.16951],"type":"Point"}
}