{
  "type": "Feature",
  "properties": {
    "iso:country":"DE",
    "sg:address":"Limbach 38",
    "sg:city":"Herrieden",
    "sg:phone":"+49 9804/321",
    "sg:postcode":"91567",
    "sg:province":"Bayern",
    "wof:name":"Karl Rieder",
    "wof:placetype":"venue"
},
  "geometry": {"coordinates":[10.4815168381,49.1987037659],"type":"Point"}
}