{
  "type": "Feature",
  "properties": {
    "iso:country":"DE",
    "sg:address":"Im Hahnborn",
    "sg:city":"Stadtkyll",
    "sg:phone":"+49 6597/5617",
    "sg:postcode":"54589",
    "sg:province":"Rheinland-Pfalz",
    "wof:name":"Gse-engineering Gmbh",
    "wof:placetype":"venue"
},
  "geometry": {"coordinates":[6.5421180725,50.3509483337],"type":"Point"}
}