{
  "type": "Feature",
  "properties": {
    "iso:country":"DE",
    "sg:address":"Ammerseestr. 26",
    "sg:city":"Berlin",
    "sg:postcode":"12527",
    "sg:province":"Berlin",
    "wof:name":"Michael Engelmann Creative Visuelle Systeme Ges. Mbh",
    "wof:placetype":"venue"
},
  "geometry": {"coordinates":[13.5748052597,52.4167022705],"type":"Point"}
}