{
  "type": "Feature",
  "properties": {
    "iso:country":"DE",
    "sg:address":"Strahlenbergerstr. 123",
    "sg:city":"Offenbach",
    "sg:phone":"+49 69/82978018",
    "sg:postcode":"63067",
    "sg:province":"Hessen",
    "wof:name":"Dr. Jan Und Inge Weber Anlageberater",
    "wof:placetype":"venue"
},
  "geometry": {"coordinates":[8.7325172424,50.1072616577],"type":"Point"}
}