{
  "type": "Feature",
  "properties": {
    "iso:country":"DE",
    "sg:address":"R\u00fcggower Weg 18",
    "sg:city":"R\u00fcggow",
    "sg:phone":"+49 3841/284036",
    "sg:postcode":"23970",
    "sg:province":"Mecklenburg-Vorpommern",
    "wof:name":"Ostsee K\u00e4lte K\u00e4ltetechnik Gmbh",
    "wof:placetype":"venue"
},
  "geometry": {"coordinates":[11.5423822403,53.8947257996],"type":"Point"}
}