{
  "type": "Feature",
  "properties": {
    "iso:country":"DE",
    "sg:address":"Lindener Marktplatz 8",
    "sg:city":"Hannover",
    "sg:phone":"+49 511/444361",
    "sg:postcode":"30449",
    "sg:province":"Niedersachsen",
    "wof:name":"Zahntechn.laboratorium Winfried Eimbeck Gmbh",
    "wof:placetype":"venue"
},
  "geometry": {"coordinates":[9.7148017883,52.3673782349],"type":"Point"}
}