{
  "type": "Feature",
  "properties": {
    "iso:country":"DE",
    "sg:address":"Voerdenweg 12",
    "sg:city":"Geldern",
    "sg:phone":"+49 2831/4264",
    "sg:postcode":"47608",
    "sg:province":"Nordrhein-Westfalen",
    "wof:name":"Herbert Stiels",
    "wof:placetype":"venue"
},
  "geometry": {"coordinates":[6.282563,51.525688],"type":"Point"}
}