{
  "type": "Feature",
  "properties": {
    "iso:country":"DE",
    "sg:address":"Salzbach\u00e4cker 8",
    "sg:city":"Bodman-Ludwigshafen",
    "sg:phone":"+49 7773/929370",
    "sg:postcode":"78351",
    "sg:province":"Baden-W\u00fcrttemberg",
    "wof:name":"E. Sauter",
    "wof:placetype":"venue"
},
  "geometry": {"coordinates":[9.0603618622,47.81690979],"type":"Point"}
}