{
  "type": "Feature",
  "properties": {
    "iso:country":"DE",
    "sg:address":"Alfred-Trappen-Str. 1",
    "sg:city":"Dortmund",
    "sg:postcode":"44263",
    "sg:province":"Nordrhein-Westfalen",
    "wof:name":"Lederwaren Hoffmann Kg",
    "wof:placetype":"venue"
},
  "geometry": {"coordinates":[7.502045,51.489635],"type":"Point"}
}