{
  "type": "Feature",
  "properties": {
    "iso:country":"DE",
    "sg:address":"Findelm\u00fchlstr. 51",
    "sg:city":"W\u00fclfershausen",
    "sg:phone":"+49 9762/231",
    "sg:postcode":"97618",
    "sg:province":"Bayern",
    "wof:name":"Esp-telekom- Elektronik Gmbh",
    "wof:placetype":"venue"
},
  "geometry": {"coordinates":[10.3467826843,50.3312683105],"type":"Point"}
}