{
  "type": "Feature",
  "properties": {
    "iso:country":"DE",
    "sg:address":"Neuherbergstr. 107",
    "sg:city":"M\u00fcnchen",
    "sg:phone":"+49 89/3146545",
    "sg:postcode":"80937",
    "sg:province":"Bayern",
    "wof:name":"Klaus-peter Chmelarz Ingenieur",
    "wof:placetype":"venue"
},
  "geometry": {"coordinates":[11.567032814,48.2090072632],"type":"Point"}
}