{
  "type": "Feature",
  "properties": {
    "iso:country":"DE",
    "sg:address":"Albrecht-D\u00fcrer-Str. 11",
    "sg:city":"N\u00fcrnberg",
    "sg:phone":"+49 911/227835",
    "sg:postcode":"90403",
    "sg:province":"Bayern",
    "wof:name":"Druckerei Rottner & Keller",
    "wof:placetype":"venue"
},
  "geometry": {"coordinates":[11.0738554001,49.457069397],"type":"Point"}
}