{
  "type": "Feature",
  "properties": {
    "iso:country":"DE",
    "sg:address":"Herzogstr. 180",
    "sg:city":"Duisburg",
    "sg:phone":"+49 203/991560",
    "sg:postcode":"47178",
    "sg:province":"Nordrhein-Westfalen",
    "wof:name":"Pga Planungs Gmbh",
    "wof:placetype":"venue"
},
  "geometry": {"coordinates":[6.7157897949,51.5437698364],"type":"Point"}
}