{
  "type": "Feature",
  "properties": {
    "iso:country":"DE",
    "sg:address":"Nibelungenweg 15",
    "sg:city":"Hannover",
    "sg:phone":"+49 511/496500",
    "sg:postcode":"30455",
    "sg:province":"Niedersachsen",
    "wof:name":"Heinrich D\u00f6pke Gmbh & Co Kg",
    "wof:placetype":"venue"
},
  "geometry": {"coordinates":[9.662714,52.35099],"type":"Point"}
}