{
  "type": "Feature",
  "properties": {
    "iso:country":"DE",
    "sg:address":"Janusstr. 16",
    "sg:city":"Landau",
    "sg:phone":"+49 9951/8925",
    "sg:postcode":"94405",
    "sg:province":"Bayern",
    "wof:name":"Franz Schobner Architekt",
    "wof:placetype":"venue"
},
  "geometry": {"coordinates":[12.698448,48.667755],"type":"Point"}
}