{
  "type": "Feature",
  "properties": {
    "iso:country":"DE",
    "sg:address":"L\u00fcbberstedter Str. 28",
    "sg:city":"Bremen",
    "sg:phone":"+49 421/395584",
    "sg:postcode":"28217",
    "sg:province":"Bremen",
    "wof:name":"Heiko Busse",
    "wof:placetype":"venue"
},
  "geometry": {"coordinates":[8.783344,53.097916],"type":"Point"}
}