{
  "type": "Feature",
  "properties": {
    "iso:country":"DE",
    "sg:address":"Marktstr. 4",
    "sg:city":"Ditzingen",
    "sg:phone":"+49 7156/3891",
    "sg:postcode":"71254",
    "sg:province":"Baden-W\u00fcrttemberg",
    "wof:name":"Pan",
    "wof:placetype":"venue"
},
  "geometry": {"coordinates":[9.0666618347,48.8269729614],"type":"Point"}
}