{
  "type": "Feature",
  "properties": {
    "iso:country":"DE",
    "sg:address":"Lerchenstr. 2",
    "sg:city":"Altusried",
    "sg:phone":"+49 8373/8515",
    "sg:postcode":"87452",
    "sg:province":"Bayern",
    "wof:name":"Elmar Und Monika Frey Verm\u00f6gensverwaltung Ohg",
    "wof:placetype":"venue"
},
  "geometry": {"coordinates":[10.0870027542,47.7819671631],"type":"Point"}
}