{
  "type": "Feature",
  "properties": {
    "iso:country":"DE",
    "sg:address":"Friedrichstr. 9",
    "sg:city":"Fulda",
    "sg:phone":"+49 661/22334",
    "sg:postcode":"36037",
    "sg:province":"Hessen",
    "wof:name":"Cafe Flamme Inh. K. Hohmann",
    "wof:placetype":"venue"
},
  "geometry": {"coordinates":[9.675256,50.552704],"type":"Point"}
}