{
  "type": "Feature",
  "properties": {
    "iso:country":"DE",
    "sg:address":"Obersasbacher Str. 8",
    "sg:city":"Sasbach",
    "sg:phone":"+49 7841/3411",
    "sg:postcode":"77880",
    "sg:province":"Baden-W\u00fcrttemberg",
    "wof:name":"Gerhard Bieber Elektroinstallation",
    "wof:placetype":"venue"
},
  "geometry": {"coordinates":[8.094104,48.638412],"type":"Point"}
}