{
  "type": "Feature",
  "properties": {
    "iso:country":"DE",
    "sg:address":"August-Bebel-Str. 50",
    "sg:city":"Loburg",
    "sg:phone":"+49 39245/326",
    "sg:postcode":"39279",
    "sg:province":"Sachsen-Anhalt",
    "wof:name":"Michael Kloske",
    "wof:placetype":"venue"
},
  "geometry": {"coordinates":[12.097532,52.118397],"type":"Point"}
}