{
  "type": "Feature",
  "properties": {
    "iso:country":"DE",
    "sg:address":"Markgr\u00f6ninger Str. 63",
    "sg:city":"Asperg",
    "sg:phone":"+49 7141/661150",
    "sg:postcode":"71679",
    "sg:province":"Baden-W\u00fcrttemberg",
    "wof:name":"Werner Ehrle",
    "wof:placetype":"venue"
},
  "geometry": {"coordinates":[9.127366,48.905872],"type":"Point"}
}