{
  "type": "Feature",
  "properties": {
    "iso:country":"DE",
    "sg:address":"Wilhelmstr. 72",
    "sg:city":"K\u00f6ln",
    "sg:phone":"+49 221/394459",
    "sg:postcode":"50996",
    "sg:province":"Nordrhein-Westfalen",
    "wof:name":"Lucia Schmidt",
    "wof:placetype":"venue"
},
  "geometry": {"coordinates":[6.9926738739,50.8925971985],"type":"Point"}
}