{
  "type": "Feature",
  "properties": {
    "iso:country":"DE",
    "sg:address":"Wilhelmstr. 197",
    "sg:city":"Hamm",
    "sg:phone":"+49 2381/944060",
    "sg:postcode":"59067",
    "sg:province":"Nordrhein-Westfalen",
    "wof:name":"Jeans Fritz",
    "wof:placetype":"venue"
},
  "geometry": {"coordinates":[7.784991,51.665466],"type":"Point"}
}