{
  "type": "Feature",
  "properties": {
    "iso:country":"DE",
    "sg:address":"Richardstr. 9",
    "sg:city":"S\u00f6gel",
    "sg:phone":"+49 5952/2625",
    "sg:postcode":"49751",
    "sg:province":"Niedersachsen",
    "wof:name":"Hans-josef Stemmer Steuerberater",
    "wof:placetype":"venue"
},
  "geometry": {"coordinates":[7.5306448936,52.8440208435],"type":"Point"}
}