{
  "type": "Feature",
  "properties": {
    "iso:country":"DE",
    "sg:address":"Pankratiusstr. 7",
    "sg:city":"Darmstadt",
    "sg:postcode":"64289",
    "sg:province":"Hessen",
    "wof:name":"Platanista Gmbh",
    "wof:placetype":"venue"
},
  "geometry": {"coordinates":[8.6579723358,49.8782730103],"type":"Point"}
}