{
  "type": "Feature",
  "properties": {
    "iso:country":"DE",
    "sg:address":"Wetterkreuz 17",
    "sg:city":"Erlangen",
    "sg:phone":"+49 9131/604045",
    "sg:postcode":"91058",
    "sg:province":"Bayern",
    "wof:name":"Ikon Gmbh Ausbildungszentrum F\u00fcr Die",
    "wof:placetype":"venue"
},
  "geometry": {"coordinates":[11.024329,49.544296],"type":"Point"}
}