{
  "type": "Feature",
  "properties": {
    "iso:country":"DE",
    "sg:address":"Bahnhofstr. 19",
    "sg:city":"Radebeul",
    "sg:phone":"+49 351/8305599",
    "sg:postcode":"01445",
    "sg:province":"Sachsen",
    "wof:name":"Stadt-apotheke Radebeul",
    "wof:placetype":"venue"
},
  "geometry": {"coordinates":[13.629262,51.106117],"type":"Point"}
}