{
  "type": "Feature",
  "properties": {
    "iso:country":"DE",
    "sg:address":"K\u00f6nig-Karl-Str.",
    "sg:city":"Bad Wildbad",
    "sg:phone":"+49 4970/811671",
    "sg:postcode":"75323",
    "sg:province":"Baden-W\u00fcrttemberg",
    "wof:name":"Volksbank Pforzheim Eg",
    "wof:placetype":"venue"
},
  "geometry": {"coordinates":[8.54879,48.751923],"type":"Point"}
}