{
  "type": "Feature",
  "properties": {
    "iso:country":"DE",
    "sg:address":"Hauptstra\u00dfe 97",
    "sg:city":"Cunewalde",
    "sg:phone":"+49 35877/80888",
    "sg:postcode":"02733",
    "sg:province":"Sachsen",
    "wof:name":"Cunewalde - Eine Gemeinde Der Oberlausitz",
    "wof:placetype":"venue"
},
  "geometry": {"coordinates":[14.518654,51.100281],"type":"Point"}
}