{
  "type": "Feature",
  "properties": {
    "iso:country":"DE",
    "sg:address":"Hauptstr. 64",
    "sg:city":"Beckum",
    "sg:phone":"+49 2525/7991",
    "sg:postcode":"59269",
    "sg:province":"Nordrhein-Westfalen",
    "wof:name":"Zoo-kaup",
    "wof:placetype":"venue"
},
  "geometry": {"coordinates":[8.03108,51.787312],"type":"Point"}
}