{
  "type": "Feature",
  "properties": {
    "iso:country":"DE",
    "sg:address":"Parlerstr. 31",
    "sg:city":"Schw\u00e4bisch Gm\u00fcnd",
    "sg:phone":"+49 7171/68056",
    "sg:postcode":"73525",
    "sg:province":"Baden-W\u00fcrttemberg",
    "wof:name":"Sachsenmaier Immobilien Gmbh",
    "wof:placetype":"venue"
},
  "geometry": {"coordinates":[9.796177,48.795986],"type":"Point"}
}