{
  "type": "Feature",
  "properties": {
    "iso:country":"DE",
    "sg:address":"Umgehungsstr. 14",
    "sg:city":"Marburg",
    "sg:phone":"+49 6421/41988",
    "sg:postcode":"35043",
    "sg:province":"Hessen",
    "wof:name":"Albert Heuser Gmbh & Co. Grundst\u00fccksverkaufs Vermie-",
    "wof:placetype":"venue"
},
  "geometry": {"coordinates":[8.765540123,50.7805709839],"type":"Point"}
}