{
  "type": "Feature",
  "properties": {
    "iso:country":"DE",
    "sg:address":"Am Grauen Mann 7",
    "sg:city":"Johanngeorgenstadt",
    "sg:phone":"+49 3773/882886",
    "sg:postcode":"08349",
    "sg:province":"Sachsen",
    "wof:name":"Otto Latka",
    "wof:placetype":"venue"
},
  "geometry": {"coordinates":[12.704008,50.440063],"type":"Point"}
}