{
  "type": "Feature",
  "properties": {
    "iso:country":"DE",
    "sg:address":"Boecklerstr. 14",
    "sg:city":"L\u00fcneburg",
    "sg:phone":"+49 4131/380091",
    "sg:postcode":"21339",
    "sg:province":"Niedersachsen",
    "wof:name":"Optima Gmbh",
    "wof:placetype":"venue"
},
  "geometry": {"coordinates":[10.4053926468,53.2731704712],"type":"Point"}
}