{
  "type": "Feature",
  "properties": {
    "iso:country":"DE",
    "sg:address":"S\u00fcchtelner Str. 45",
    "sg:city":"Willich",
    "sg:phone":"+49 2156/2870",
    "sg:postcode":"47877",
    "sg:province":"Nordrhein-Westfalen",
    "wof:name":"Detlev N\u00f6hles",
    "wof:placetype":"venue"
},
  "geometry": {"coordinates":[6.452896,51.277073],"type":"Point"}
}