{
  "type": "Feature",
  "properties": {
    "iso:country":"DE",
    "sg:address":"Otterweg 25",
    "sg:city":"Steinhagen",
    "sg:phone":"+49 5204/2763",
    "sg:postcode":"33803",
    "sg:province":"Nordrhein-Westfalen",
    "wof:name":"Werner Eggert",
    "wof:placetype":"venue"
},
  "geometry": {"coordinates":[8.4419126511,51.9922561646],"type":"Point"}
}