{
  "type": "Feature",
  "properties": {
    "iso:country":"DE",
    "sg:address":"Kaulbachstr. 89c",
    "sg:city":"M\u00fcnchen",
    "sg:phone":"+49 89/334372",
    "sg:postcode":"80802",
    "sg:province":"Bayern",
    "wof:name":"Monika Mund Steuerberater",
    "wof:placetype":"venue"
},
  "geometry": {"coordinates":[11.5858230591,48.1558265686],"type":"Point"}
}