{
  "type": "Feature",
  "properties": {
    "iso:country":"DE",
    "sg:address":"Rechtenflether Str. 25",
    "sg:city":"Bremen",
    "sg:phone":"+49 421/545940",
    "sg:postcode":"28197",
    "sg:province":"Bremen",
    "wof:name":"W. K\u00f6hler",
    "wof:placetype":"venue"
},
  "geometry": {"coordinates":[8.764799,53.083584],"type":"Point"}
}