{
  "type": "Feature",
  "properties": {
    "iso:country":"DE",
    "sg:address":"Hildegard-Burjan-Platz 1",
    "sg:city":"G\u00f6rlitz",
    "sg:phone":"+49 3581/766500",
    "sg:postcode":"02826",
    "sg:province":"Sachsen",
    "wof:name":"Chinesisches Restaurant Le Thanh Mai",
    "wof:placetype":"venue"
},
  "geometry": {"coordinates":[14.9822368622,51.1562423706],"type":"Point"}
}