{
  "type": "Feature",
  "properties": {
    "iso:country":"DE",
    "sg:address":"Bergstr. 5",
    "sg:city":"Hilders",
    "sg:phone":"+49 6681/433",
    "sg:postcode":"36115",
    "sg:province":"Hessen",
    "wof:name":"Erich Rausch",
    "wof:placetype":"venue"
},
  "geometry": {"coordinates":[9.932042,50.528564],"type":"Point"}
}