{
  "type": "Feature",
  "properties": {
    "iso:country":"DE",
    "sg:address":"Rieschbogen 56",
    "sg:city":"H\u00f6henkirchen-Siegertbrn",
    "sg:phone":"+49 8102/6460",
    "sg:postcode":"85635",
    "sg:province":"Bayern",
    "wof:name":"Dr. Med. U. Wirth-giacomelli",
    "wof:placetype":"venue"
},
  "geometry": {"coordinates":[11.7163906097,48.021938324],"type":"Point"}
}