{
  "type": "Feature",
  "properties": {
    "iso:country":"DE",
    "sg:address":"Pinneberger Str.",
    "sg:city":"Hamburg",
    "sg:phone":"+49 40/5592021",
    "sg:postcode":"22457",
    "sg:province":"Hamburg",
    "wof:name":"Peter Sturm",
    "wof:placetype":"venue"
},
  "geometry": {"coordinates":[9.9034748077,53.6343688965],"type":"Point"}
}