{
  "type": "Feature",
  "properties": {
    "iso:country":"DE",
    "sg:address":"Dorfwiesenstr. 27",
    "sg:city":"Waldkirchen",
    "sg:phone":"+49 8581/2853",
    "sg:postcode":"94065",
    "sg:province":"Bayern",
    "wof:name":"Martin Gastinger Heilpraktiker",
    "wof:placetype":"venue"
},
  "geometry": {"coordinates":[13.6385374069,48.7111816406],"type":"Point"}
}