{
  "type": "Feature",
  "properties": {
    "iso:country":"DE",
    "sg:address":"Dorfstr. 7",
    "sg:city":"Wendisch Evern",
    "sg:phone":"+49 4131/57884",
    "sg:postcode":"21403",
    "sg:province":"Niedersachsen",
    "wof:name":"Satz Und Druck Thormann Gmbh",
    "wof:placetype":"venue"
},
  "geometry": {"coordinates":[10.4760932922,53.2167854309],"type":"Point"}
}