{
  "type": "Feature",
  "properties": {
    "iso:country":"DE",
    "sg:address":"Lindenstr. 7",
    "sg:city":"Rielasingen-Worblingen",
    "sg:phone":"+49 7731/51124",
    "sg:postcode":"78239",
    "sg:province":"Baden-W\u00fcrttemberg",
    "wof:name":"Linde Arlen",
    "wof:placetype":"venue"
},
  "geometry": {"coordinates":[8.8464393616,47.7273178101],"type":"Point"}
}