{
  "type": "Feature",
  "properties": {
    "iso:country":"DE",
    "sg:address":"Vardel 6",
    "sg:city":"Vechta",
    "sg:phone":"+49 4441/3331",
    "sg:postcode":"49377",
    "sg:province":"Niedersachsen",
    "wof:name":"Dieter Josef",
    "wof:placetype":"venue"
},
  "geometry": {"coordinates":[8.2707500458,52.749332428],"type":"Point"}
}