{
  "type": "Feature",
  "properties": {
    "iso:country":"DE",
    "sg:address":"Industriestr. 17",
    "sg:city":"D\u00f6rentrup",
    "sg:phone":"+49 5265/546",
    "sg:postcode":"32694",
    "sg:province":"Nordrhein-Westfalen",
    "wof:name":"G\u00fcnter Rohde Ohg",
    "wof:placetype":"venue"
},
  "geometry": {"coordinates":[9.045026,52.02425],"type":"Point"}
}