{
  "type": "Feature",
  "properties": {
    "iso:country":"DE",
    "sg:address":"Edeldorf",
    "sg:city":"Theisseil",
    "sg:phone":"+49 961/35408",
    "sg:postcode":"92637",
    "sg:province":"Bayern",
    "wof:name":"Janker",
    "wof:placetype":"venue"
},
  "geometry": {"coordinates":[12.1948375702,49.6955070496],"type":"Point"}
}