{
  "type": "Feature",
  "properties": {
    "iso:country":"DE",
    "sg:address":"Geleitsstr. 8",
    "sg:city":"Frankfurt",
    "sg:postcode":"60599",
    "sg:province":"Hessen",
    "wof:name":"Structure Tone Gmbh",
    "wof:placetype":"venue"
},
  "geometry": {"coordinates":[8.7265548706,50.1003952026],"type":"Point"}
}