{
  "type": "Feature",
  "properties": {
    "iso:country":"DE",
    "sg:address":"Rendeler Str. 22",
    "sg:city":"Frankfurt",
    "sg:phone":"+49 69/464188",
    "sg:postcode":"60385",
    "sg:province":"Hessen",
    "wof:name":"Med-fu\u00dfpflege Goerke-groh",
    "wof:placetype":"venue"
},
  "geometry": {"coordinates":[8.709112,50.129673],"type":"Point"}
}