{
  "type": "Feature",
  "properties": {
    "iso:country":"DE",
    "sg:address":"Fahrenkr\u00f6n 116",
    "sg:city":"Hamburg",
    "sg:phone":"+49 40/6439880",
    "sg:postcode":"22179",
    "sg:province":"Hamburg",
    "wof:name":"Rudolf Lohmann Ingenieurb\u00fcro",
    "wof:placetype":"venue"
},
  "geometry": {"coordinates":[10.0982599258,53.6163101196],"type":"Point"}
}