{
  "type": "Feature",
  "properties": {
    "iso:country":"DE",
    "sg:address":"Hauptstr. 133",
    "sg:city":"Steina",
    "sg:phone":"+49 35955/44324",
    "sg:postcode":"01920",
    "sg:province":"Sachsen",
    "wof:name":"Martin Rasche",
    "wof:placetype":"venue"
},
  "geometry": {"coordinates":[14.034685,51.213959],"type":"Point"}
}