{
  "type": "Feature",
  "properties": {
    "iso:country":"DE",
    "sg:address":"Peel 11",
    "sg:city":"M\u00f6nchengladbach",
    "sg:phone":"+49 2161/582434",
    "sg:postcode":"41179",
    "sg:province":"Nordrhein-Westfalen",
    "wof:name":"Josef Bolten",
    "wof:placetype":"venue"
},
  "geometry": {"coordinates":[6.325612,51.159779],"type":"Point"}
}