{
  "type": "Feature",
  "properties": {
    "iso:country":"DE",
    "sg:address":"Hauptstr. 15",
    "sg:city":"Bad Schwartau",
    "sg:phone":"+49 451/22200",
    "sg:postcode":"23611",
    "sg:province":"Schleswig-Holstein",
    "wof:name":"Rolf Und A. Heitmann",
    "wof:placetype":"venue"
},
  "geometry": {"coordinates":[10.6807012558,53.907409668],"type":"Point"}
}