{
  "type": "Feature",
  "properties": {
    "iso:country":"DE",
    "sg:address":"Gewerbestr. 31",
    "sg:city":"Bergkamen",
    "sg:phone":"+49 2389/7074",
    "sg:postcode":"59192",
    "sg:province":"Nordrhein-Westfalen",
    "wof:name":"Jansen Schl\u00fcsselfertigbau Gmbh",
    "wof:placetype":"venue"
},
  "geometry": {"coordinates":[7.668333,51.649979],"type":"Point"}
}