{
  "type": "Feature",
  "properties": {
    "iso:country":"DE",
    "sg:address":"Ostendstr. 59",
    "sg:city":"Stuttgart",
    "sg:phone":"+49 711/260786",
    "sg:postcode":"70188",
    "sg:province":"Baden-W\u00fcrttemberg",
    "wof:name":"Rich. Prieschl",
    "wof:placetype":"venue"
},
  "geometry": {"coordinates":[9.208009,48.786423],"type":"Point"}
}