{
  "type": "Feature",
  "properties": {
    "iso:country":"DE",
    "sg:address":"Gottlob-Bauknechtstr. 4",
    "sg:city":"Schorndorf",
    "sg:phone":"+49 7181/978970",
    "sg:postcode":"73614",
    "sg:province":"Baden-W\u00fcrttemberg",
    "wof:name":"Asys Automatic Systems Gmbh & Co Kg",
    "wof:placetype":"venue"
},
  "geometry": {"coordinates":[9.5353288651,48.8089447021],"type":"Point"}
}