{
  "type": "Feature",
  "properties": {
    "iso:country":"DE",
    "sg:address":"Haag",
    "sg:city":"Salzweg",
    "sg:phone":"+49 851/44993",
    "sg:postcode":"94121",
    "sg:province":"Bayern",
    "wof:name":"Josef Klinger",
    "wof:placetype":"venue"
},
  "geometry": {"coordinates":[13.4697828293,48.6254310608],"type":"Point"}
}