{
  "type": "Feature",
  "properties": {
    "iso:country":"DE",
    "sg:address":"Karth\u00e4userstr. 4",
    "sg:city":"Hildesheim",
    "sg:phone":"+49 5121/44439",
    "sg:postcode":"31139",
    "sg:province":"Niedersachsen",
    "wof:name":"Doris Wiesel Masseurin",
    "wof:placetype":"venue"
},
  "geometry": {"coordinates":[9.934135,52.146938],"type":"Point"}
}