{
  "type": "Feature",
  "properties": {
    "iso:country":"DE",
    "sg:address":"Saarlandstr. 39",
    "sg:city":"Melle",
    "sg:phone":"+49 5422/2665",
    "sg:postcode":"49324",
    "sg:province":"Niedersachsen",
    "wof:name":"Ev. Pfarramt Pauluskirche",
    "wof:placetype":"venue"
},
  "geometry": {"coordinates":[8.3487586975,52.2116279602],"type":"Point"}
}