{
  "type": "Feature",
  "properties": {
    "iso:country":"DE",
    "sg:address":"Im Roesrain 9",
    "sg:city":"Forchtenberg",
    "sg:phone":"+49 7947",
    "sg:postcode":"74670",
    "sg:province":"Baden-W\u00fcrttemberg",
    "wof:name":"Psychologische Online-beratung Klaus G. Hohenberg",
    "wof:placetype":"venue"
},
  "geometry": {"coordinates":[9.569049,49.312553],"type":"Point"}
}