{
  "type": "Feature",
  "properties": {
    "iso:country":"DE",
    "sg:address":"Kol. Pichelswerder S\u00fcd",
    "sg:city":"Berlin",
    "sg:phone":"+49 30/3615010",
    "sg:postcode":"13595",
    "sg:province":"Berlin",
    "wof:name":"Werft Zum Grauen Hecht Radicke & Co.",
    "wof:placetype":"venue"
},
  "geometry": {"coordinates":[13.19787,52.513401],"type":"Point"}
}