{
  "type": "Feature",
  "properties": {
    "iso:country":"DE",
    "sg:address":"H\u00fclshorstweg 2",
    "sg:city":"Moers",
    "sg:phone":"+49 2841/66722",
    "sg:postcode":"47447",
    "sg:province":"Nordrhein-Westfalen",
    "wof:name":"Elektro Wetteborn Gmbh",
    "wof:placetype":"venue"
},
  "geometry": {"coordinates":[6.595781,51.427666],"type":"Point"}
}