{
  "type": "Feature",
  "properties": {
    "iso:country":"DE",
    "sg:address":"Seehalde 15",
    "sg:city":"Nonnenhorn",
    "sg:phone":"+49 8382/8273",
    "sg:postcode":"88149",
    "sg:province":"Bayern",
    "wof:name":"Fritz Sauter",
    "wof:placetype":"venue"
},
  "geometry": {"coordinates":[9.61151,47.575668],"type":"Point"}
}