{
  "type": "Feature",
  "properties": {
    "iso:country":"DE",
    "sg:address":"Rotteland 24",
    "sg:city":"Bochum",
    "sg:phone":"+49 234/9799192",
    "sg:postcode":"44797",
    "sg:province":"Nordrhein-Westfalen",
    "wof:name":"Midnight-special-showband",
    "wof:placetype":"venue"
},
  "geometry": {"coordinates":[7.2492728233,51.4314727783],"type":"Point"}
}