{
  "type": "Feature",
  "properties": {
    "iso:country":"DE",
    "sg:address":"Reichenbacher Str. 39",
    "sg:city":"Zwickau",
    "sg:phone":"+49 375/213640",
    "sg:postcode":"08056",
    "sg:province":"Sachsen",
    "wof:name":"B Fr\u00f6hlich",
    "wof:placetype":"venue"
},
  "geometry": {"coordinates":[12.483594,50.715206],"type":"Point"}
}