{
  "type": "Feature",
  "properties": {
    "iso:country":"DE",
    "sg:address":"K\u00e4stnerstr. 10",
    "sg:city":"Ludwigsburg",
    "sg:phone":"+49 7141/55027",
    "sg:postcode":"71642",
    "sg:province":"Baden-W\u00fcrttemberg",
    "wof:name":"Jeschke Verwaltungs Gmbh",
    "wof:placetype":"venue"
},
  "geometry": {"coordinates":[9.227812,48.910309],"type":"Point"}
}