{
  "type": "Feature",
  "properties": {
    "iso:country":"DE",
    "sg:address":"Bergedorfer Str. 66",
    "sg:city":"Geesthacht",
    "sg:phone":"+49 4152/842561",
    "sg:postcode":"21502",
    "sg:province":"Schleswig-Holstein",
    "wof:name":"Elbecom Telekommunikations- Management Beratungs- Und",
    "wof:placetype":"venue"
},
  "geometry": {"coordinates":[10.3686094284,53.436832428],"type":"Point"}
}