{
  "type": "Feature",
  "properties": {
    "iso:country":"DE",
    "sg:address":"Am Buttgraben 6a",
    "sg:city":"List",
    "sg:postcode":"25992",
    "sg:province":"Schleswig-Holstein",
    "wof:name":"Marianne Hergt",
    "wof:placetype":"venue"
},
  "geometry": {"coordinates":[8.423620224,55.020526886],"type":"Point"}
}