{
  "type": "Feature",
  "properties": {
    "iso:country":"DE",
    "sg:address":"M\u00fchlenstr. 26",
    "sg:city":"Uchte",
    "sg:phone":"+49 5763/407",
    "sg:postcode":"31600",
    "sg:province":"Niedersachsen",
    "wof:name":"Barthel-gartenbau Inh. Lutz Barthel",
    "wof:placetype":"venue"
},
  "geometry": {"coordinates":[8.906353,52.499207],"type":"Point"}
}