{
  "type": "Feature",
  "properties": {
    "iso:country":"DE",
    "sg:address":"Hauptstr. 18",
    "sg:city":"Sibbesse",
    "sg:phone":"+49 5066/5905630",
    "sg:postcode":"31079",
    "sg:province":"Niedersachsen",
    "wof:name":"Corinna Rugenstein-b\u00f6neker Rechtsanw\u00e4ltin",
    "wof:placetype":"venue"
},
  "geometry": {"coordinates":[9.9025669098,52.0551528931],"type":"Point"}
}