{
  "type": "Feature",
  "properties": {
    "iso:country":"DE",
    "sg:address":"Am Sauereck 2",
    "sg:city":"Oettingen",
    "sg:phone":"+49 9082/1616",
    "sg:postcode":"86732",
    "sg:province":"Bayern",
    "wof:name":"Norma Lebensmittelfilialbetrieb",
    "wof:placetype":"venue"
},
  "geometry": {"coordinates":[10.597328186,48.9467506409],"type":"Point"}
}