{
  "type": "Feature",
  "properties": {
    "iso:country":"DE",
    "sg:address":"Dahlhauser Str. 163",
    "sg:city":"Essen",
    "sg:phone":"+49 201/537962",
    "sg:postcode":"45279",
    "sg:province":"Nordrhein-Westfalen",
    "wof:name":"Blumen-dahlmann",
    "wof:placetype":"venue"
},
  "geometry": {"coordinates":[7.103986,51.437344],"type":"Point"}
}