{
  "type": "Feature",
  "properties": {
    "iso:country":"DE",
    "sg:address":"Friederikenstr. 11",
    "sg:city":"Coswig",
    "sg:phone":"+49 34903/63352",
    "sg:postcode":"06869",
    "sg:province":"Sachsen-Anhalt",
    "wof:name":"Boehnels Spielzeugladen Kg",
    "wof:placetype":"venue"
},
  "geometry": {"coordinates":[12.4574680328,51.8844528198],"type":"Point"}
}