{
  "type": "Feature",
  "properties": {
    "iso:country":"DE",
    "sg:address":"Zum Wiesengrund 2",
    "sg:city":"Wi\u00dfmannsdorf",
    "sg:phone":"+49 6527/8279",
    "sg:postcode":"54636",
    "sg:province":"Rheinland-Pfalz",
    "wof:name":"G. Schmitz",
    "wof:placetype":"venue"
},
  "geometry": {"coordinates":[6.4224038124,50.0049819946],"type":"Point"}
}