{
  "type": "Feature",
  "properties": {
    "iso:country":"DE",
    "sg:address":"Am Friedhof 9",
    "sg:city":"Metelen",
    "sg:postcode":"48629",
    "sg:province":"Nordrhein-Westfalen",
    "wof:name":"Bdc Business Development Concepts Gesellschaft F\u00fcr",
    "wof:placetype":"venue"
},
  "geometry": {"coordinates":[7.21487,52.147789],"type":"Point"}
}