{
  "type": "Feature",
  "properties": {
    "iso:country":"DE",
    "sg:address":"Saalachstr. 5",
    "sg:city":"Bad Reichenhall",
    "sg:phone":"+49 8651/4238",
    "sg:postcode":"83435",
    "sg:province":"Bayern",
    "wof:name":"Anton Kroi\u00df",
    "wof:placetype":"venue"
},
  "geometry": {"coordinates":[12.8956718445,47.7429580688],"type":"Point"}
}