{
  "type": "Feature",
  "properties": {
    "iso:country":"DE",
    "sg:address":"Pappelweg 5",
    "sg:city":"Jengen",
    "sg:postcode":"86860",
    "sg:province":"Bayern",
    "wof:name":"Isk Immobilien-standort- Planungsgesellschaft Mbh",
    "wof:placetype":"venue"
},
  "geometry": {"coordinates":[10.7287817001,47.9969978333],"type":"Point"}
}