{
  "type": "Feature",
  "properties": {
    "iso:country":"DE",
    "sg:address":"Manderow",
    "sg:city":"Gramkow",
    "sg:phone":"+49 3841/616147",
    "sg:postcode":"23968",
    "sg:province":"Mecklenburg-Vorpommern",
    "wof:name":"Grill-ranch",
    "wof:placetype":"venue"
},
  "geometry": {"coordinates":[11.3181695938,53.9011192322],"type":"Point"}
}