{
  "type": "Feature",
  "properties": {
    "iso:country":"DE",
    "sg:address":"Reuteweg 4",
    "sg:city":"Geislingen",
    "sg:phone":"+49 7331/61309",
    "sg:postcode":"73312",
    "sg:province":"Baden-W\u00fcrttemberg",
    "wof:name":"H. Jedele Mech. Werkstat",
    "wof:placetype":"venue"
},
  "geometry": {"coordinates":[9.861411,48.654652],"type":"Point"}
}