{
  "type": "Feature",
  "properties": {
    "iso:country":"DE",
    "sg:address":"Kronenstr 18",
    "sg:city":"Berlin",
    "sg:phone":"+49 30/2022050",
    "sg:postcode":"10117",
    "sg:province":"Berlin",
    "wof:name":"Emsys Gesellschaft F\u00fcr Edv-beratung + Managementsysteme Mbh",
    "wof:placetype":"venue"
},
  "geometry": {"coordinates":[13.39103,52.511166],"type":"Point"}
}