{
  "type": "Feature",
  "properties": {
    "iso:country":"DE",
    "sg:address":"Kleinhausweg 11",
    "sg:city":"Dresden",
    "sg:phone":"+49 351/2518512",
    "sg:postcode":"01277",
    "sg:province":"Sachsen",
    "wof:name":"Avm Schmelter Service Gmbh & Co. Kg",
    "wof:placetype":"venue"
},
  "geometry": {"coordinates":[13.79645,51.03511],"type":"Point"}
}