{
  "type": "Feature",
  "properties": {
    "iso:country":"DE",
    "sg:address":"Kohlh\u00e4user Str. 4",
    "sg:city":"W\u00f6lfersheim",
    "sg:phone":"+49 6036/2934",
    "sg:postcode":"61200",
    "sg:province":"Hessen",
    "wof:name":"T. Spieler",
    "wof:placetype":"venue"
},
  "geometry": {"coordinates":[8.864184,50.423512],"type":"Point"}
}