{
  "type": "Feature",
  "properties": {
    "iso:country":"DE",
    "sg:address":"Simon-Breu-Str. 8",
    "sg:city":"Simbach",
    "sg:phone":"+49 8571/8253",
    "sg:postcode":"84359",
    "sg:province":"Bayern",
    "wof:name":"Minimal",
    "wof:placetype":"venue"
},
  "geometry": {"coordinates":[13.0227117538,48.2671012878],"type":"Point"}
}