{
  "type": "Feature",
  "properties": {
    "iso:country":"DE",
    "sg:address":"Fischweiher 24",
    "sg:city":"Essen",
    "sg:phone":"+49 201/559525",
    "sg:postcode":"45307",
    "sg:province":"Nordrhein-Westfalen",
    "wof:name":"S. Sporkhorst",
    "wof:placetype":"venue"
},
  "geometry": {"coordinates":[7.07235,51.466209],"type":"Point"}
}