{
  "type": "Feature",
  "properties": {
    "iso:country":"DE",
    "sg:address":"Gipsstr. 23 B",
    "sg:city":"Berlin",
    "sg:phone":"+49 30/28599340",
    "sg:postcode":"10119",
    "sg:province":"Berlin",
    "wof:name":"Galerie Ngano",
    "wof:placetype":"venue"
},
  "geometry": {"coordinates":[13.4018583298,52.5267219543],"type":"Point"}
}