{
  "type": "Feature",
  "properties": {
    "iso:country":"DE",
    "sg:address":"Diksmuider Str. 2",
    "sg:city":"Finnentrop",
    "sg:phone":"+49 2721/7840",
    "sg:postcode":"57413",
    "sg:province":"Nordrhein-Westfalen",
    "wof:name":"Hans-j\u00fcrgen Rudolph",
    "wof:placetype":"venue"
},
  "geometry": {"coordinates":[7.969626,51.174313],"type":"Point"}
}