{
  "type": "Feature",
  "properties": {
    "iso:country":"DE",
    "sg:address":"Brensbacher Str. 16",
    "sg:city":"Brensbach",
    "sg:phone":"+49 6161/444",
    "sg:postcode":"64395",
    "sg:province":"Hessen",
    "wof:name":"Jung Verwaltungsges. Mbh",
    "wof:placetype":"venue"
},
  "geometry": {"coordinates":[8.8676395416,49.7747001648],"type":"Point"}
}