{
  "type": "Feature",
  "properties": {
    "iso:country":"DE",
    "sg:address":"Stationsweg 50",
    "sg:city":"Waldsassen",
    "sg:phone":"+49 9632/1285",
    "sg:postcode":"95652",
    "sg:province":"Bayern",
    "wof:name":"Ziegler Brauerei Gmbh",
    "wof:placetype":"venue"
},
  "geometry": {"coordinates":[12.304193,50.012085],"type":"Point"}
}