{
  "type": "Feature",
  "properties": {
    "iso:country":"DE",
    "sg:address":"Burggrub",
    "sg:city":"Krummennaab",
    "sg:phone":"+49 9682/2424",
    "sg:postcode":"92703",
    "sg:province":"Bayern",
    "wof:name":"C. Und K. Schug",
    "wof:placetype":"venue"
},
  "geometry": {"coordinates":[12.095451,49.824589],"type":"Point"}
}