{
  "type": "Feature",
  "properties": {
    "iso:country":"DE",
    "sg:address":"L\u00f6hstr. 3-5",
    "sg:city":"M\u00fclheim",
    "sg:phone":"+49 208/477617",
    "sg:postcode":"45468",
    "sg:province":"Nordrhein-Westfalen",
    "wof:name":"Sigrid Hildebrandt",
    "wof:placetype":"venue"
},
  "geometry": {"coordinates":[6.880461,51.429607],"type":"Point"}
}