{
  "type": "Feature",
  "properties": {
    "iso:country":"DE",
    "sg:address":"Ellwanger Str. 34",
    "sg:city":"Rainau",
    "sg:phone":"+49 7961/2824",
    "sg:postcode":"73492",
    "sg:province":"Baden-W\u00fcrttemberg",
    "wof:name":"Anton Wiedenh\u00f6fer",
    "wof:placetype":"venue"
},
  "geometry": {"coordinates":[10.167788,48.924286],"type":"Point"}
}