{
  "type": "Feature",
  "properties": {
    "iso:country":"DE",
    "sg:address":"L\u00e4rchenweg 18",
    "sg:city":"Oberursel",
    "sg:phone":"+49 6172/37103",
    "sg:postcode":"61440",
    "sg:province":"Hessen",
    "wof:name":"Willi Weil Architekt",
    "wof:placetype":"venue"
},
  "geometry": {"coordinates":[8.560686,50.219128],"type":"Point"}
}