{
  "type": "Feature",
  "properties": {
    "iso:country":"DE",
    "sg:address":"Hubertusstr. 64",
    "sg:city":"Nalbach",
    "sg:phone":"+49 6838/83480",
    "sg:postcode":"66809",
    "sg:province":"Saarland",
    "wof:name":"Gerd M\u00fcller",
    "wof:placetype":"venue"
},
  "geometry": {"coordinates":[6.7828412056,49.378036499],"type":"Point"}
}