{
  "type": "Feature",
  "properties": {
    "iso:country":"DE",
    "sg:address":"Gewerkenstr. 22",
    "sg:city":"Herne",
    "sg:phone":"+49 2323/93060",
    "sg:postcode":"44628",
    "sg:province":"Nordrhein-Westfalen",
    "wof:name":"Mahlow & Lais Gmbh",
    "wof:placetype":"venue"
},
  "geometry": {"coordinates":[7.2537407875,51.5449104309],"type":"Point"}
}