{
  "type": "Feature",
  "properties": {
    "iso:country":"DE",
    "sg:address":"Haselbusch 14 - 18::",
    "sg:city":"Kiel",
    "sg:phone":"+49 4943/1780520",
    "sg:postcode":"24146",
    "sg:province":"Schleswig-Holstein",
    "wof:name":"Ernst Boehmker Gmbh & Co Kg",
    "wof:placetype":"venue"
},
  "geometry": {"coordinates":[10.172719,54.295101],"type":"Point"}
}