{
  "type": "Feature",
  "properties": {
    "iso:country":"DE",
    "sg:address":"Franz-Mehring-Str. 9",
    "sg:city":"Gera",
    "sg:phone":"+49 365/4204558",
    "sg:postcode":"07545",
    "sg:province":"Th\u00fcringen",
    "wof:name":"Dylla Bautr\u00e4ger Gmbh",
    "wof:placetype":"venue"
},
  "geometry": {"coordinates":[12.082992,50.884937],"type":"Point"}
}