{
  "type": "Feature",
  "properties": {
    "iso:country":"DE",
    "sg:address":"Bergstr. 32",
    "sg:city":"Cornberg",
    "sg:phone":"+49 5650/536",
    "sg:postcode":"36219",
    "sg:province":"Hessen",
    "wof:name":"Herbert Itter",
    "wof:placetype":"venue"
},
  "geometry": {"coordinates":[9.859013,51.041843],"type":"Point"}
}