{
  "type": "Feature",
  "properties": {
    "iso:country":"DE",
    "sg:address":"H\u00f6henweg 81",
    "sg:city":"Bonn",
    "sg:phone":"+49 228/283060",
    "sg:postcode":"53127",
    "sg:province":"Nordrhein-Westfalen",
    "wof:name":"Karl-heinz Willkomm Ingenieur",
    "wof:placetype":"venue"
},
  "geometry": {"coordinates":[7.0820541382,50.6919059753],"type":"Point"}
}