{
  "type": "Feature",
  "properties": {
    "iso:country":"DE",
    "sg:address":"Dorfstr. 2",
    "sg:city":"Bonn",
    "sg:phone":"+49 228/255499",
    "sg:postcode":"53125",
    "sg:province":"Nordrhein-Westfalen",
    "wof:name":"Hans-g\u00fcnter Weidenfeller",
    "wof:placetype":"venue"
},
  "geometry": {"coordinates":[7.0743308067,50.6814956665],"type":"Point"}
}