{
  "type": "Feature",
  "properties": {
    "iso:country":"DE",
    "sg:address":"Bodenweg 4",
    "sg:city":"Radebeul",
    "sg:phone":"+49 351/281242",
    "sg:postcode":"01445",
    "sg:province":"Sachsen",
    "wof:name":"Steubler Automatisierung Gmbh",
    "wof:placetype":"venue"
},
  "geometry": {"coordinates":[13.6756782532,51.1153068542],"type":"Point"}
}