{
  "type": "Feature",
  "properties": {
    "iso:country":"DE",
    "sg:address":"Jahnstr. 8",
    "sg:city":"Osnabr\u00fcck",
    "sg:phone":"+49 541/432221",
    "sg:postcode":"49080",
    "sg:province":"Niedersachsen",
    "wof:name":"Martin Brunz",
    "wof:placetype":"venue"
},
  "geometry": {"coordinates":[8.0363788605,52.2711219788],"type":"Point"}
}