{
  "type": "Feature",
  "properties": {
    "iso:country":"DE",
    "sg:address":"Rohrweg 7",
    "sg:city":"Limburg",
    "sg:phone":"+49 6431/6112",
    "sg:postcode":"65549",
    "sg:province":"Hessen",
    "wof:name":"W. Und Martha Neumann",
    "wof:placetype":"venue"
},
  "geometry": {"coordinates":[8.058533,50.385475],"type":"Point"}
}