{
  "type": "Feature",
  "properties": {
    "iso:country":"DE",
    "sg:address":"B\u00f6nnigheimer Str. 38",
    "sg:city":"Cleebronn",
    "sg:phone":"+49 7135/8472",
    "sg:postcode":"74389",
    "sg:province":"Baden-W\u00fcrttemberg",
    "wof:name":"Paul H. B\u00f6hringer",
    "wof:placetype":"venue"
},
  "geometry": {"coordinates":[9.035372,49.040932],"type":"Point"}
}