{
  "type": "Feature",
  "properties": {
    "iso:country":"DE",
    "sg:address":"M\u00e4rkische Str. 21",
    "sg:city":"Hamm",
    "sg:phone":"+49 2381/880006",
    "sg:postcode":"59071",
    "sg:province":"Nordrhein-Westfalen",
    "wof:name":"K. H. Fl\u00fcgge Steuerberater",
    "wof:placetype":"venue"
},
  "geometry": {"coordinates":[7.8497772217,51.6892471313],"type":"Point"}
}