{
  "type": "Feature",
  "properties": {
    "iso:country":"DE",
    "sg:address":"Ahmser Str. 5-7",
    "sg:city":"Herford",
    "sg:phone":"+49 5221/529852",
    "sg:postcode":"32052",
    "sg:province":"Nordrhein-Westfalen",
    "wof:name":"Europcar Autovermietung Gmbh",
    "wof:placetype":"venue"
},
  "geometry": {"coordinates":[8.674272,52.110657],"type":"Point"}
}