{
  "type": "Feature",
  "properties": {
    "iso:country":"DE",
    "sg:address":"Arthur-Gruber-Str. 70",
    "sg:city":"Sindelfingen",
    "sg:phone":"+49 7031/980",
    "sg:postcode":"71065",
    "sg:province":"Baden-W\u00fcrttemberg",
    "wof:name":"St\u00e4dtisches Krankenhaus",
    "wof:placetype":"venue"
},
  "geometry": {"coordinates":[9.02448,48.716381],"type":"Point"}
}