{
  "type": "Feature",
  "properties": {
    "iso:country":"DE",
    "sg:address":"Alter Postweg 83 a",
    "sg:city":"Seevetal",
    "sg:phone":"+49 4105/84045",
    "sg:postcode":"21220",
    "sg:province":"Niedersachsen",
    "wof:name":"Gabi B\u00fcnning",
    "wof:placetype":"venue"
},
  "geometry": {"coordinates":[10.0321235657,53.3794288635],"type":"Point"}
}