{
  "type": "Feature",
  "properties": {
    "iso:country":"DE",
    "sg:address":"Heinrichstr. 18",
    "sg:city":"Vechelde",
    "sg:phone":"+49 5302/1289",
    "sg:postcode":"38159",
    "sg:province":"Niedersachsen",
    "wof:name":"Heinz Grobe",
    "wof:placetype":"venue"
},
  "geometry": {"coordinates":[10.408855,52.255077],"type":"Point"}
}