{
  "type": "Feature",
  "properties": {
    "iso:country":"DE",
    "sg:address":"M\u00fchlenbruchstr. 4",
    "sg:city":"Warin",
    "sg:phone":"+49 38482/60310",
    "sg:postcode":"19417",
    "sg:province":"Mecklenburg-Vorpommern",
    "wof:name":"Pflegeheim Der Diakonie",
    "wof:placetype":"venue"
},
  "geometry": {"coordinates":[11.707125,53.801693],"type":"Point"}
}