{
  "type": "Feature",
  "properties": {
    "iso:country":"DE",
    "sg:address":"Ke\u00dflerstr. 5",
    "sg:city":"Karlsruhe",
    "sg:phone":"+49 4972/1557028",
    "sg:postcode":"76185",
    "sg:province":"Baden-W\u00fcrttemberg",
    "wof:name":"Weinwerbezentrale Badischer Winzergenossenschaft E.g.",
    "wof:placetype":"venue"
},
  "geometry": {"coordinates":[8.364147,49.004406],"type":"Point"}
}