{
  "type": "Feature",
  "properties": {
    "iso:country":"DE",
    "sg:address":"Windener Str. 3",
    "sg:city":"Steinweiler",
    "sg:phone":"+49 6349/8231",
    "sg:postcode":"76872",
    "sg:province":"Rheinland-Pfalz",
    "wof:name":"Volker Rinck",
    "wof:placetype":"venue"
},
  "geometry": {"coordinates":[8.134596,49.119015],"type":"Point"}
}