{
  "type": "Feature",
  "properties": {
    "iso:country":"DE",
    "sg:address":"Kirnitzschtalstr. 7",
    "sg:city":"Ottendorf",
    "sg:phone":"+49 35974/50099",
    "sg:postcode":"01855",
    "sg:province":"Sachsen",
    "wof:name":"S\u00e4gewerk Felsenm\u00fchle Gmbh",
    "wof:placetype":"venue"
},
  "geometry": {"coordinates":[14.2828598022,50.9553565979],"type":"Point"}
}