{
  "type": "Feature",
  "properties": {
    "iso:country":"DE",
    "sg:address":"Leuchte 39",
    "sg:city":"Frankfurt",
    "sg:phone":"+49 6109/369491",
    "sg:postcode":"60388",
    "sg:province":"Hessen",
    "wof:name":"Minuth Kurier",
    "wof:placetype":"venue"
},
  "geometry": {"coordinates":[8.761453,50.143448],"type":"Point"}
}