{
  "type": "Feature",
  "properties": {
    "iso:country":"DE",
    "sg:address":"Schachtstr. 53",
    "sg:city":"Sondershausen",
    "sg:phone":"+49 3632/601594",
    "sg:postcode":"99706",
    "sg:province":"Th\u00fcringen",
    "wof:name":"P. Dielau Immobilienmakler",
    "wof:placetype":"venue"
},
  "geometry": {"coordinates":[10.8325481415,51.3917045593],"type":"Point"}
}