{
  "type": "Feature",
  "properties": {
    "iso:country":"DE",
    "sg:address":"Rosenweg 1",
    "sg:city":"Ronnenberg",
    "sg:phone":"+49 511/467740",
    "sg:postcode":"30952",
    "sg:province":"Niedersachsen",
    "wof:name":"Verein F\u00fcr Sch\u00fcler-und Familienhilfe E. V.",
    "wof:placetype":"venue"
},
  "geometry": {"coordinates":[9.6623630524,52.335231781],"type":"Point"}
}