{
  "type": "Feature",
  "properties": {
    "iso:country":"DE",
    "sg:address":"Olgastr. 136",
    "sg:city":"Ulm",
    "sg:phone":"+49 731/21008",
    "sg:postcode":"89073",
    "sg:province":"Baden-W\u00fcrttemberg",
    "wof:name":"Pizzeria Bella Napoli",
    "wof:placetype":"venue"
},
  "geometry": {"coordinates":[9.9968938828,48.4023513794],"type":"Point"}
}