{
  "type": "Feature",
  "properties": {
    "iso:country":"DE",
    "sg:address":"\u00d6lsbacher Weg 5",
    "sg:city":"N\u00fcrnberg",
    "sg:phone":"+49 911/503405",
    "sg:postcode":"90482",
    "sg:province":"Bayern",
    "wof:name":"Josef Seitz Architekt",
    "wof:placetype":"venue"
},
  "geometry": {"coordinates":[11.150617,49.465054],"type":"Point"}
}