{
  "type": "Feature",
  "properties": {
    "iso:country":"DE",
    "sg:address":"Auf dem Gries 2",
    "sg:city":"Moosburg",
    "sg:phone":"+49 8761/2218",
    "sg:postcode":"85368",
    "sg:province":"Bayern",
    "wof:name":"Pizzeria Roma",
    "wof:placetype":"venue"
},
  "geometry": {"coordinates":[11.9363746643,48.4944496155],"type":"Point"}
}