{
  "type": "Feature",
  "properties": {
    "iso:country":"DE",
    "sg:address":"Hiltelinger Str. 2",
    "sg:city":"Weil am Rhein",
    "sg:phone":"+49 7621/71995",
    "sg:postcode":"79576",
    "sg:province":"Baden-W\u00fcrttemberg",
    "wof:name":"K. Banholzer Gravieranstalt",
    "wof:placetype":"venue"
},
  "geometry": {"coordinates":[7.6007390022,47.5938224792],"type":"Point"}
}