{
  "type": "Feature",
  "properties": {
    "iso:country":"DE",
    "sg:address":"Dummeltshausener Str. 9a",
    "sg:city":"Ilmm\u00fcnster",
    "sg:postcode":"85304",
    "sg:province":"Bayern",
    "wof:name":"Hmg Computer Vertriebs Gmbh",
    "wof:placetype":"venue"
},
  "geometry": {"coordinates":[11.4983997345,48.485710144],"type":"Point"}
}