{
  "type": "Feature",
  "properties": {
    "iso:country":"DE",
    "sg:address":"Heidenfeldstr. 6",
    "sg:city":"Berlin",
    "sg:phone":"+49 30/4269204",
    "sg:postcode":"10249",
    "sg:province":"Berlin",
    "wof:name":"Auto-wagenpflege-service Horst Lange",
    "wof:placetype":"venue"
},
  "geometry": {"coordinates":[13.450432,52.5257],"type":"Point"}
}