{
  "type": "Feature",
  "properties": {
    "iso:country":"DE",
    "sg:address":"M\u00fchlwiesenstr. 5",
    "sg:city":"Neunkirchen",
    "sg:phone":"+49 6821/21428",
    "sg:postcode":"66538",
    "sg:province":"Saarland",
    "wof:name":"Helmut Eifler Rechtsanwalt",
    "wof:placetype":"venue"
},
  "geometry": {"coordinates":[7.1939868927,49.3477783203],"type":"Point"}
}