{
  "type": "Feature",
  "properties": {
    "iso:country":"DE",
    "sg:address":"Paula-Wimmer-Str. 5",
    "sg:city":"Dachau",
    "sg:phone":"+49 8131/52854",
    "sg:postcode":"85221",
    "sg:province":"Bayern",
    "wof:name":"Dieter Diener Schaufenstergestaltung",
    "wof:placetype":"venue"
},
  "geometry": {"coordinates":[11.4666080475,48.2569007874],"type":"Point"}
}