{
  "type": "Feature",
  "properties": {
    "iso:country":"DE",
    "sg:address":"B\u00fcrgermeister-Smidt-Str. 106",
    "sg:city":"Bremerhaven",
    "sg:phone":"+49 471/9413563",
    "sg:postcode":"27568",
    "sg:province":"Bremen",
    "wof:name":"Lady Moden Eizelhandel F. Dameoberbekl. Gmbh",
    "wof:placetype":"venue"
},
  "geometry": {"coordinates":[8.575716,53.546822],"type":"Point"}
}