{
  "type": "Feature",
  "properties": {
    "iso:country":"DE",
    "sg:address":"Hofwiesenstr. 16",
    "sg:city":"Fichtenau",
    "sg:phone":"+49 7962/90500",
    "sg:postcode":"74579",
    "sg:province":"Baden-W\u00fcrttemberg",
    "wof:name":"Wohnbau Liebenstein Gmbh",
    "wof:placetype":"venue"
},
  "geometry": {"coordinates":[10.205729,49.050583],"type":"Point"}
}