{
  "type": "Feature",
  "properties": {
    "iso:country":"DE",
    "sg:address":"Sandweg 3",
    "sg:city":"Eberbach",
    "sg:phone":"+49 6271/92510",
    "sg:postcode":"69412",
    "sg:province":"Baden-W\u00fcrttemberg",
    "wof:name":"J\u00fcrgen Krauth Architekt",
    "wof:placetype":"venue"
},
  "geometry": {"coordinates":[8.976708,49.456722],"type":"Point"}
}