{
  "type": "Feature",
  "properties": {
    "iso:country":"DE",
    "sg:address":"Roonstr. 5",
    "sg:city":"Braunschweig",
    "sg:phone":"+49 531/345480",
    "sg:postcode":"38102",
    "sg:province":"Niedersachsen",
    "wof:name":"E. Petschick An- Und Verkauf",
    "wof:placetype":"venue"
},
  "geometry": {"coordinates":[10.5413208008,52.2695541382],"type":"Point"}
}