{
  "type": "Feature",
  "properties": {
    "iso:country":"DE",
    "sg:address":"Karlstr. 68",
    "sg:city":"Fuldatal",
    "sg:phone":"+49 561/817501",
    "sg:postcode":"34233",
    "sg:province":"Hessen",
    "wof:name":"Kurt Franz",
    "wof:placetype":"venue"
},
  "geometry": {"coordinates":[9.5154123306,51.372795105],"type":"Point"}
}