{
  "type": "Feature",
  "properties": {
    "iso:country":"DE",
    "sg:address":"Am Wallensteingraben 6a",
    "sg:city":"Dorf Mecklenburg",
    "sg:phone":"+49 3841/790918",
    "sg:postcode":"23972",
    "sg:province":"Mecklenburg-Vorpommern",
    "wof:name":"Landmaschinen- Und Fahrzeug- Vertrieb Dorf Mecklenburg Gmbh",
    "wof:placetype":"venue"
},
  "geometry": {"coordinates":[11.460219,53.840496],"type":"Point"}
}