{
  "type": "Feature",
  "properties": {
    "iso:country":"DE",
    "sg:address":"Am Sonnenbrunnen 16",
    "sg:city":"Wuppertal",
    "sg:postcode":"42327",
    "sg:province":"Nordrhein-Westfalen",
    "wof:name":"Diamant-reisen Gmbh",
    "wof:placetype":"venue"
},
  "geometry": {"coordinates":[7.0915307999,51.2381591797],"type":"Point"}
}