{
  "type": "Feature",
  "properties": {
    "iso:country":"DE",
    "sg:address":"Antonisstr. 1",
    "sg:city":"Schwetzingen",
    "sg:phone":"+49 6202/3394",
    "sg:postcode":"68723",
    "sg:province":"Baden-W\u00fcrttemberg",
    "wof:name":"Hans Ruffler",
    "wof:placetype":"venue"
},
  "geometry": {"coordinates":[8.573214,49.388885],"type":"Point"}
}