{
  "type": "Feature",
  "properties": {
    "iso:country":"DE",
    "sg:address":"Stuttgarter Str. 107",
    "sg:city":"Stuttgart",
    "sg:postcode":"70469",
    "sg:province":"Baden-W\u00fcrttemberg",
    "wof:name":"Pqm Ges. F\u00fcr Projekt- Und Qualit\u00e4tsmanagement Mbh",
    "wof:placetype":"venue"
},
  "geometry": {"coordinates":[9.1556415558,48.808807373],"type":"Point"}
}