{
  "type": "Feature",
  "properties": {
    "iso:country":"DE",
    "sg:address":"Grube-Karl-Str. 14",
    "sg:city":"Geislingen",
    "sg:phone":"+49 7331/20010",
    "sg:postcode":"73312",
    "sg:province":"Baden-W\u00fcrttemberg",
    "wof:name":"Leonh. Hagmeyer",
    "wof:placetype":"venue"
},
  "geometry": {"coordinates":[9.811668396,48.6128425598],"type":"Point"}
}