{
  "type": "Feature",
  "properties": {
    "iso:country":"DE",
    "sg:address":"Dorfplatz 6",
    "sg:city":"Arzberg",
    "sg:phone":"+49 9233/9699",
    "sg:postcode":"95659",
    "sg:province":"Bayern",
    "wof:name":"Karl Marth Agrarhandel Und Pflanzen\u00f6lgewinnung E. K.",
    "wof:placetype":"venue"
},
  "geometry": {"coordinates":[12.1557197571,50.0321044922],"type":"Point"}
}