{
  "type": "Feature",
  "properties": {
    "iso:country":"DE",
    "sg:address":"Kirchplatz 1",
    "sg:city":"Schneidlingen",
    "sg:postcode":"39435",
    "sg:province":"Sachsen-Anhalt",
    "wof:name":"Evangelisches Pfarramt Schneidlingen",
    "wof:placetype":"venue"
},
  "geometry": {"coordinates":[11.4423294067,51.8949966431],"type":"Point"}
}