{
  "type": "Feature",
  "properties": {
    "iso:country":"DE",
    "sg:address":"Waldblickstr. 7",
    "sg:city":"Wiesbaden",
    "sg:phone":"+49 6122/15840",
    "sg:postcode":"65207",
    "sg:province":"Hessen",
    "wof:name":"Gudrun Veser Rechtsanw\u00e4ltin",
    "wof:placetype":"venue"
},
  "geometry": {"coordinates":[8.3368196487,50.1099853516],"type":"Point"}
}