{
  "type": "Feature",
  "properties": {
    "iso:country":"DE",
    "sg:address":"Bocketaler Str. 146",
    "sg:city":"Ibbenb\u00fcren",
    "sg:phone":"+49 5451/96800",
    "sg:postcode":"49479",
    "sg:province":"Nordrhein-Westfalen",
    "wof:name":"Haco-beton Tecklenburg Gmbh",
    "wof:placetype":"venue"
},
  "geometry": {"coordinates":[7.7699508667,52.2516021729],"type":"Point"}
}