{
  "type": "Feature",
  "properties": {
    "iso:country":"DE",
    "sg:address":"M\u00fchlenweg 57",
    "sg:city":"Wesel",
    "sg:phone":"+49 281/65983",
    "sg:postcode":"46483",
    "sg:province":"Nordrhein-Westfalen",
    "wof:name":"Matthias Schlug Steuerberater",
    "wof:placetype":"venue"
},
  "geometry": {"coordinates":[6.6172180176,51.6739997864],"type":"Point"}
}