{
  "type": "Feature",
  "properties": {
    "iso:country":"DE",
    "sg:address":"Die\u00dfener Str. 14",
    "sg:city":"Schongau",
    "sg:phone":"+49 8861/23270",
    "sg:postcode":"86956",
    "sg:province":"Bayern",
    "wof:name":"Walter Bau- Ag",
    "wof:placetype":"venue"
},
  "geometry": {"coordinates":[10.921319,47.814693],"type":"Point"}
}