{
  "type": "Feature",
  "properties": {
    "iso:country":"DE",
    "sg:address":"H\u00f6ristr. 39",
    "sg:city":"Singen",
    "sg:phone":"+49 7731/41803",
    "sg:postcode":"78224",
    "sg:province":"Baden-W\u00fcrttemberg",
    "wof:name":"Pfefferm\u00fchle",
    "wof:placetype":"venue"
},
  "geometry": {"coordinates":[8.8421859741,47.7655944824],"type":"Point"}
}