{
  "type": "Feature",
  "properties": {
    "iso:country":"DE",
    "sg:address":"Bahnholzstr. 17",
    "sg:city":"Wiesbaden",
    "sg:phone":"+49 611/542422",
    "sg:postcode":"65193",
    "sg:province":"Hessen",
    "wof:name":"Alexander De Faria E Castro Rechtsanwalt",
    "wof:placetype":"venue"
},
  "geometry": {"coordinates":[8.2611322403,50.1009902954],"type":"Point"}
}