{
  "type": "Feature",
  "properties": {
    "iso:country":"DE",
    "sg:address":"Eichenweg 5",
    "sg:city":"Pfaffenhofen",
    "sg:phone":"+49 8441/86237",
    "sg:postcode":"85276",
    "sg:province":"Bayern",
    "wof:name":"Dr. Hans Widmann Tierarzt",
    "wof:placetype":"venue"
},
  "geometry": {"coordinates":[11.5204610825,48.5421180725],"type":"Point"}
}