{
  "type": "Feature",
  "properties": {
    "iso:country":"DE",
    "sg:address":"Payerstr. 16",
    "sg:city":"Reutlingen",
    "sg:phone":"+49 7121/240634",
    "sg:postcode":"72764",
    "sg:province":"Baden-W\u00fcrttemberg",
    "wof:name":"G. Breitinger",
    "wof:placetype":"venue"
},
  "geometry": {"coordinates":[9.2112693787,48.4844741821],"type":"Point"}
}