{
  "type": "Feature",
  "properties": {
    "iso:country":"DE",
    "sg:address":"Averdung 11",
    "sg:city":"Drensteinfurt",
    "sg:postcode":"48317",
    "sg:province":"Nordrhein-Westfalen",
    "wof:name":"Sch\u00f6nland Gmbh",
    "wof:placetype":"venue"
},
  "geometry": {"coordinates":[7.760673,51.812325],"type":"Point"}
}