{
  "type": "Feature",
  "properties": {
    "iso:country":"DE",
    "sg:address":"Schl\u00f6\u00dflestr. 15",
    "sg:city":"Erkheim",
    "sg:phone":"+49 8336/813690",
    "sg:postcode":"87746",
    "sg:province":"Bayern",
    "wof:name":"Gastst\u00e4tte Krone",
    "wof:placetype":"venue"
},
  "geometry": {"coordinates":[10.3387231827,48.0361061096],"type":"Point"}
}