{
  "type": "Feature",
  "properties": {
    "iso:country":"DE",
    "sg:address":"Hauptstr. 104",
    "sg:city":"Pockau",
    "sg:phone":"+49 37367/8894",
    "sg:postcode":"09509",
    "sg:province":"Sachsen",
    "wof:name":"R. Nerger",
    "wof:placetype":"venue"
},
  "geometry": {"coordinates":[13.2710199356,50.7317085266],"type":"Point"}
}