{
  "type": "Feature",
  "properties": {
    "iso:country":"DE",
    "sg:address":"Gottlob-Grotz-Str. 1",
    "sg:city":"Bietigheim-Bissingen",
    "sg:phone":"+49 7142/35602",
    "sg:postcode":"74321",
    "sg:province":"Baden-W\u00fcrttemberg",
    "wof:name":"Heinkel Ag",
    "wof:placetype":"venue"
},
  "geometry": {"coordinates":[9.12647,48.96162],"type":"Point"}
}