{
  "type": "Feature",
  "properties": {
    "iso:country":"DE",
    "sg:address":"Immanuel-Kant-Str. 1",
    "sg:city":"Bergisch Gladbach",
    "sg:postcode":"51427",
    "sg:province":"Nordrhein-Westfalen",
    "wof:name":"Gesseljay Verwaltungs- Gmbh",
    "wof:placetype":"venue"
},
  "geometry": {"coordinates":[7.1041889191,50.9574241638],"type":"Point"}
}