{
  "type": "Feature",
  "properties": {
    "iso:country":"DE",
    "sg:address":"Heinrich-G\u00e4tke-Str. 11",
    "sg:city":"Pritzwalk",
    "sg:phone":"+49 3395/302165",
    "sg:postcode":"16928",
    "sg:province":"Brandenburg",
    "wof:name":"Dental Labor Gerd Kock Gmbh",
    "wof:placetype":"venue"
},
  "geometry": {"coordinates":[12.175799,53.137871],"type":"Point"}
}