{
  "type": "Feature",
  "properties": {
    "iso:country":"DE",
    "sg:city":"Hamburg",
    "sg:postcode":"20097",
    "sg:province":"Hamburg",
    "wof:name":"N@work Internet Informationssysteme Gmbh - Umzug",
    "wof:placetype":"venue"
},
  "geometry": {"coordinates":[10.02425,53.546085],"type":"Point"}
}