{
  "type": "Feature",
  "properties": {
    "iso:country":"DE",
    "sg:address":"Niederkasseler Str. 33",
    "sg:city":"K\u00f6ln",
    "sg:phone":"+49 2203/964201",
    "sg:postcode":"51147",
    "sg:province":"Nordrhein-Westfalen",
    "wof:name":"Ftg Air Service Flugcharter Gmbh & Co. Kg",
    "wof:placetype":"venue"
},
  "geometry": {"coordinates":[7.1009922028,50.8446044922],"type":"Point"}
}