{
  "type": "Feature",
  "properties": {
    "iso:country":"DE",
    "sg:address":"Heilholtkamp 38",
    "sg:city":"Hamburg",
    "sg:postcode":"22297",
    "sg:province":"Hamburg",
    "wof:name":"Otto B\u00fchring Ingenieur",
    "wof:placetype":"venue"
},
  "geometry": {"coordinates":[10.0157260895,53.6103439331],"type":"Point"}
}