{
  "type": "Feature",
  "properties": {
    "iso:country":"DE",
    "sg:address":"Kalbecker Weg 21",
    "sg:city":"Weeze",
    "sg:phone":"+49 2837/7733",
    "sg:postcode":"47652",
    "sg:province":"Nordrhein-Westfalen",
    "wof:name":"Theodor Verheyen",
    "wof:placetype":"venue"
},
  "geometry": {"coordinates":[6.212591,51.642784],"type":"Point"}
}