{
  "type": "Feature",
  "properties": {
    "iso:country":"DE",
    "sg:address":"Sarresdorfer Str. 2",
    "sg:city":"Gerolstein",
    "sg:phone":"+49 6591/985290",
    "sg:postcode":"54568",
    "sg:province":"Rheinland-Pfalz",
    "wof:name":"Cafe Dolomit",
    "wof:placetype":"venue"
},
  "geometry": {"coordinates":[6.657128,50.224159],"type":"Point"}
}