{
  "type": "Feature",
  "properties": {
    "iso:country":"DE",
    "sg:address":"Sulgauer Str. 7",
    "sg:city":"Schramberg",
    "sg:phone":"+49 7422/52769",
    "sg:postcode":"78713",
    "sg:province":"Baden-W\u00fcrttemberg",
    "wof:name":"St\u00e4dt. B\u00fccherei Sulgen",
    "wof:placetype":"venue"
},
  "geometry": {"coordinates":[8.420927,48.226143],"type":"Point"}
}