{
  "type": "Feature",
  "properties": {
    "iso:country":"DE",
    "sg:address":"Winterbacher Str. 1",
    "sg:city":"Biedershausen",
    "sg:phone":"+49 6375/5179",
    "sg:postcode":"66917",
    "sg:province":"Rheinland-Pfalz",
    "wof:name":"Otto H\u00f6h",
    "wof:placetype":"venue"
},
  "geometry": {"coordinates":[7.4880919456,49.319694519],"type":"Point"}
}