{
  "type": "Feature",
  "properties": {
    "iso:country":"DE",
    "sg:address":"Ulmer Str. 19",
    "sg:city":"Memmingen",
    "sg:phone":"+49 8331/850341",
    "sg:postcode":"87700",
    "sg:province":"Bayern",
    "wof:name":"Red. Memminger Geschichts- Bl\u00e4tter",
    "wof:placetype":"venue"
},
  "geometry": {"coordinates":[10.1797466278,47.9889030457],"type":"Point"}
}