{
  "type": "Feature",
  "properties": {
    "iso:country":"DE",
    "sg:address":"Bahnhofstr. 13",
    "sg:city":"Osterode",
    "sg:phone":"+49 5522/920126",
    "sg:postcode":"37520",
    "sg:province":"Niedersachsen",
    "wof:name":"Direkt",
    "wof:placetype":"venue"
},
  "geometry": {"coordinates":[10.2464456558,51.7289009094],"type":"Point"}
}