{
  "type": "Feature",
  "properties": {
    "iso:country":"DE",
    "sg:address":"Laascher Str. 10",
    "sg:city":"Neustadt-Glewe",
    "sg:phone":"+49 38757/33358",
    "sg:postcode":"19306",
    "sg:province":"Mecklenburg-Vorpommern",
    "wof:name":"Harry Ahrens",
    "wof:placetype":"venue"
},
  "geometry": {"coordinates":[11.5854654312,53.3832244873],"type":"Point"}
}