{
  "type": "Feature",
  "properties": {
    "iso:country":"DE",
    "sg:address":"Bahnhofstr. 18",
    "sg:city":"Bleicherode",
    "sg:phone":"+49 36338/42004",
    "sg:postcode":"99752",
    "sg:province":"Th\u00fcringen",
    "wof:name":"K.-h. Becker",
    "wof:placetype":"venue"
},
  "geometry": {"coordinates":[10.575958252,51.4409599304],"type":"Point"}
}