{
  "type": "Feature",
  "properties": {
    "iso:country":"DE",
    "sg:address":"Zum Osterplatz 15",
    "sg:city":"Breuna",
    "sg:phone":"+49 5693/6599",
    "sg:postcode":"34479",
    "sg:province":"Hessen",
    "wof:name":"Karl-heinz Baake Architekt",
    "wof:placetype":"venue"
},
  "geometry": {"coordinates":[9.185848,51.411018],"type":"Point"}
}