{
  "type": "Feature",
  "properties": {
    "iso:country":"DE",
    "sg:address":"V\u00f6lklinger Str. 47",
    "sg:city":"V\u00f6lklingen",
    "sg:phone":"+49 6898/41736",
    "sg:postcode":"66333",
    "sg:province":"Saarland",
    "wof:name":"Sonnen-apotheke",
    "wof:placetype":"venue"
},
  "geometry": {"coordinates":[6.809777,49.22263],"type":"Point"}
}