{
  "type": "Feature",
  "properties": {
    "iso:country":"DE",
    "sg:address":"Hauptstr. 101",
    "sg:city":"Velbert",
    "sg:phone":"+49 2052/3643",
    "sg:postcode":"42555",
    "sg:province":"Nordrhein-Westfalen",
    "wof:name":"Horst Benk Notar",
    "wof:placetype":"venue"
},
  "geometry": {"coordinates":[7.1159381866,51.3502197266],"type":"Point"}
}