{
  "type": "Feature",
  "properties": {
    "iso:country":"DE",
    "sg:address":"Hauptstr. 3",
    "sg:city":"Zirndorf",
    "sg:phone":"+49 911/6002692",
    "sg:postcode":"90513",
    "sg:province":"Bayern",
    "wof:name":"L. Jagenteufel",
    "wof:placetype":"venue"
},
  "geometry": {"coordinates":[10.9555168152,49.4416046143],"type":"Point"}
}