{
  "type": "Feature",
  "properties": {
    "iso:country":"DE",
    "sg:address":"Gartenstr. 37",
    "sg:city":"Viersen",
    "sg:phone":"+49 2162/933850",
    "sg:postcode":"41747",
    "sg:province":"Nordrhein-Westfalen",
    "wof:name":"Mft Metals And Ferro-alloystrading Gmbh",
    "wof:placetype":"venue"
},
  "geometry": {"coordinates":[6.385687,51.257999],"type":"Point"}
}