{
  "type": "Feature",
  "properties": {
    "iso:country":"DE",
    "sg:address":"W\u00fcrttemberger Str. 55",
    "sg:city":"Bruchsal",
    "sg:phone":"+49 7251/989202",
    "sg:postcode":"76646",
    "sg:province":"Baden-W\u00fcrttemberg",
    "wof:name":"Petar Makaric Anlageberater",
    "wof:placetype":"venue"
},
  "geometry": {"coordinates":[8.6042585373,49.1217155457],"type":"Point"}
}