{
  "type": "Feature",
  "properties": {
    "iso:country":"DE",
    "sg:address":"Kalkwiesen 7",
    "sg:city":"Horneburg",
    "sg:phone":"+49 4163/6555",
    "sg:postcode":"21640",
    "sg:province":"Niedersachsen",
    "wof:name":"Kurbad Horneburg Reinhard Lipski Kg",
    "wof:placetype":"venue"
},
  "geometry": {"coordinates":[9.584129,53.506641],"type":"Point"}
}