{
  "type": "Feature",
  "properties": {
    "iso:country":"DE",
    "sg:address":"Lehener Str. 40",
    "sg:city":"Freiburg",
    "sg:phone":"+49 761/273974",
    "sg:postcode":"79106",
    "sg:province":"Baden-W\u00fcrttemberg",
    "wof:name":"Necmettin Iyen",
    "wof:placetype":"venue"
},
  "geometry": {"coordinates":[7.8393888474,48.0006828308],"type":"Point"}
}