{
  "type": "Feature",
  "properties": {
    "iso:country":"DE",
    "sg:address":"Asterweg 9",
    "sg:city":"Nidda",
    "sg:phone":"+49 6043/8440",
    "sg:postcode":"63667",
    "sg:province":"Hessen",
    "wof:name":"Reinhold Bach",
    "wof:placetype":"venue"
},
  "geometry": {"coordinates":[9.011300087,50.3944015503],"type":"Point"}
}