{
  "type": "Feature",
  "properties": {
    "iso:country":"DE",
    "sg:address":"Drosselweg 8",
    "sg:city":"Peine",
    "sg:phone":"+49 5171/3064",
    "sg:postcode":"31228",
    "sg:province":"Niedersachsen",
    "wof:name":"Gerhard Heuer Rechtsanwalt",
    "wof:placetype":"venue"
},
  "geometry": {"coordinates":[10.2356681824,52.342124939],"type":"Point"}
}