{
  "type": "Feature",
  "properties": {
    "iso:country":"DE",
    "sg:address":"Wilhelm-Bendick-Str. 21",
    "sg:city":"Gleichen - Gro\u00df Lengden",
    "sg:phone":"+49 5508/923056",
    "sg:postcode":"37130",
    "sg:province":"Niedersachsen",
    "wof:name":"Christel Wemheuer B\u00fcrgermeisterkandidatin Gleichen",
    "wof:placetype":"venue"
},
  "geometry": {"coordinates":[10.04202,51.448841],"type":"Point"}
}