{
  "type": "Feature",
  "properties": {
    "iso:country":"DE",
    "sg:address":"Bomlitzer Str. 59",
    "sg:city":"Walsrode",
    "sg:phone":"+49 5161/910099",
    "sg:postcode":"29664",
    "sg:province":"Niedersachsen",
    "wof:name":"C. Und M. Pfingsten",
    "wof:placetype":"venue"
},
  "geometry": {"coordinates":[9.638123,52.878887],"type":"Point"}
}