{
  "type": "Feature",
  "properties": {
    "iso:country":"DE",
    "sg:address":"Regensburger Str. 26",
    "sg:city":"Maxh\u00fctte-Haidhof",
    "sg:phone":"+49 9471/20150",
    "sg:postcode":"93142",
    "sg:province":"Bayern",
    "wof:name":"Barbara-apotheke",
    "wof:placetype":"venue"
},
  "geometry": {"coordinates":[12.09405,49.197475],"type":"Point"}
}