{
  "type": "Feature",
  "properties": {
    "iso:country":"DE",
    "sg:address":"Hauptstr. 29",
    "sg:city":"Hafenlohr",
    "sg:phone":"+49 9391/3977",
    "sg:postcode":"97840",
    "sg:province":"Bayern",
    "wof:name":"Gemeindeb\u00fccherei Rathaus",
    "wof:placetype":"venue"
},
  "geometry": {"coordinates":[9.603895,49.870529],"type":"Point"}
}