{
  "type": "Feature",
  "properties": {
    "iso:country":"DE",
    "sg:address":"Friedrich-Ebert-Ring 10",
    "sg:city":"W\u00fcrzburg",
    "sg:postcode":"97072",
    "sg:province":"Bayern",
    "wof:name":"Juwi Immobilien Gmbh",
    "wof:placetype":"venue"
},
  "geometry": {"coordinates":[9.942325,49.790199],"type":"Point"}
}