{
  "type": "Feature",
  "properties": {
    "iso:country":"DE",
    "sg:address":"Langer Acker 10",
    "sg:city":"Wedemark",
    "sg:phone":"+49 5130/58010",
    "sg:postcode":"30900",
    "sg:province":"Niedersachsen",
    "wof:name":"Kuhlemann Und Schimpke Aufz\u00fcge Gmbh",
    "wof:placetype":"venue"
},
  "geometry": {"coordinates":[9.734476,52.517319],"type":"Point"}
}