{
  "type": "Feature",
  "properties": {
    "iso:country":"DE",
    "sg:address":"Scherrenbergstr. 36",
    "sg:city":"Aalen",
    "sg:postcode":"73434",
    "sg:province":"Baden-W\u00fcrttemberg",
    "wof:name":"Aktion Humane Schule Arbeitskreis Aalen",
    "wof:placetype":"venue"
},
  "geometry": {"coordinates":[10.0487890244,48.8882713318],"type":"Point"}
}