{
  "type": "Feature",
  "properties": {
    "iso:country":"DE",
    "sg:address":"Ludwigshafener Str. 62",
    "sg:city":"Neuhofen",
    "sg:phone":"+49 6236/55812",
    "sg:postcode":"67141",
    "sg:province":"Rheinland-Pfalz",
    "wof:name":"R. Kastenhuber Immobilienmakler",
    "wof:placetype":"venue"
},
  "geometry": {"coordinates":[8.4250040054,49.4252891541],"type":"Point"}
}