{
  "type": "Feature",
  "properties": {
    "iso:country":"DE",
    "sg:address":"Gemminger Str. 61",
    "sg:city":"Schwaigern",
    "sg:phone":"+49 7138/5286",
    "sg:postcode":"74193",
    "sg:province":"Baden-W\u00fcrttemberg",
    "wof:name":"H. Gebert",
    "wof:placetype":"venue"
},
  "geometry": {"coordinates":[9.0511579514,49.1443977356],"type":"Point"}
}