{
  "type": "Feature",
  "properties": {
    "iso:country":"DE",
    "sg:address":"Feldstr. 1",
    "sg:city":"Bilshausen",
    "sg:phone":"+49 5528/409",
    "sg:postcode":"37434",
    "sg:province":"Niedersachsen",
    "wof:name":"Georg Bringmann",
    "wof:placetype":"venue"
},
  "geometry": {"coordinates":[10.159517,51.626961],"type":"Point"}
}