{
  "type": "Feature",
  "properties": {
    "iso:country":"DE",
    "sg:address":"Joseph-Otto-Kolb-Str. 5",
    "sg:city":"Bubenreuth",
    "sg:phone":"+49 9131/22375",
    "sg:postcode":"91088",
    "sg:province":"Bayern",
    "wof:name":"O. Schuh Mech.werkstatt",
    "wof:placetype":"venue"
},
  "geometry": {"coordinates":[11.0073,49.620308],"type":"Point"}
}