{
  "type": "Feature",
  "properties": {
    "iso:country":"DE",
    "sg:address":"Oberdarfelder Str. 19",
    "sg:city":"Rosendahl",
    "sg:phone":"+49 2545/8040",
    "sg:postcode":"48720",
    "sg:province":"Nordrhein-Westfalen",
    "wof:name":"Ulrich Gerling Gmbh",
    "wof:placetype":"venue"
},
  "geometry": {"coordinates":[7.276036,52.022751],"type":"Point"}
}