{
  "type": "Feature",
  "properties": {
    "iso:country":"DE",
    "sg:address":"Industriestr. 4",
    "sg:city":"Salching",
    "sg:phone":"+49 9421/913395",
    "sg:postcode":"94330",
    "sg:province":"Bayern",
    "wof:name":"Andreas Martin",
    "wof:placetype":"venue"
},
  "geometry": {"coordinates":[12.575374,48.822189],"type":"Point"}
}