{
  "type": "Feature",
  "properties": {
    "iso:country":"DE",
    "sg:address":"Gabelsbergerstr. 9",
    "sg:city":"Aue",
    "sg:phone":"+49 3771/52893",
    "sg:postcode":"08280",
    "sg:province":"Sachsen",
    "wof:name":"Egon Enke",
    "wof:placetype":"venue"
},
  "geometry": {"coordinates":[12.708271,50.588554],"type":"Point"}
}