{
  "type": "Feature",
  "properties": {
    "iso:country":"DE",
    "sg:address":"Hauptstr. 22b",
    "sg:city":"Allmosen",
    "sg:phone":"+49 35753/16677",
    "sg:postcode":"01983",
    "sg:province":"Brandenburg",
    "wof:name":"B\u00e4rbel Schaks",
    "wof:placetype":"venue"
},
  "geometry": {"coordinates":[14.0153303146,51.5854187012],"type":"Point"}
}