{
  "type": "Feature",
  "properties": {
    "iso:country":"DE",
    "sg:address":"Schellingstr. 9",
    "sg:city":"M\u00fcnchen",
    "sg:phone":"+49 89/282880",
    "sg:postcode":"80799",
    "sg:province":"Bayern",
    "wof:name":"Atzinger Gastst\u00e4tten Gmbh",
    "wof:placetype":"venue"
},
  "geometry": {"coordinates":[11.5783987045,48.1494255066],"type":"Point"}
}