{
  "type": "Feature",
  "properties": {
    "iso:country":"DE",
    "sg:address":"Am S\u00fclzegraben 1",
    "sg:city":"Halberstadt",
    "sg:phone":"+49 3941/68170",
    "sg:postcode":"38820",
    "sg:province":"Sachsen-Anhalt",
    "wof:name":"Dekra Automobil Gmbh",
    "wof:placetype":"venue"
},
  "geometry": {"coordinates":[11.0731449127,51.8824691772],"type":"Point"}
}