{
  "type": "Feature",
  "properties": {
    "iso:country":"DE",
    "sg:address":"Rauendahlstr. 78",
    "sg:city":"Witten",
    "sg:phone":"+49 2302/30308",
    "sg:postcode":"58452",
    "sg:province":"Nordrhein-Westfalen",
    "wof:name":"Jugend Der Djk Tus Ruhrtal Witten",
    "wof:placetype":"venue"
},
  "geometry": {"coordinates":[7.3251800537,51.4168777466],"type":"Point"}
}