{
  "type": "Feature",
  "properties": {
    "iso:country":"DE",
    "sg:address":"Ursulastr. 2",
    "sg:city":"Hamm",
    "sg:phone":"+49 2381/20637",
    "sg:postcode":"59069",
    "sg:province":"Nordrhein-Westfalen",
    "wof:name":"Norbert Oelgart",
    "wof:placetype":"venue"
},
  "geometry": {"coordinates":[7.8381700516,51.6469306946],"type":"Point"}
}