{
  "type": "Feature",
  "properties": {
    "iso:country":"DE",
    "sg:address":"Pf\u00fchlstr. 25",
    "sg:city":"Heilbronn",
    "sg:phone":"+49 7131/174152",
    "sg:postcode":"74076",
    "sg:province":"Baden-W\u00fcrttemberg",
    "wof:name":"Altvater & Wei\u00df Gmbh",
    "wof:placetype":"venue"
},
  "geometry": {"coordinates":[9.232855,49.145096],"type":"Point"}
}