{
  "type": "Feature",
  "properties": {
    "iso:country":"DE",
    "sg:address":"Hauptstrasse 44",
    "sg:city":"Legden",
    "sg:phone":"+49 2566/3675",
    "sg:postcode":"48739",
    "sg:province":"Nordrhein-Westfalen",
    "wof:name":"Unreal",
    "wof:placetype":"venue"
},
  "geometry": {"coordinates":[7.100356,52.030491],"type":"Point"}
}