{
  "type": "Feature",
  "properties": {
    "iso:country":"DE",
    "sg:address":"Motorstr. 52",
    "sg:city":"Stuttgart",
    "sg:phone":"+49 711/1399880",
    "sg:postcode":"70499",
    "sg:province":"Baden-W\u00fcrttemberg",
    "wof:name":"Scharr Buero Gmbh",
    "wof:placetype":"venue"
},
  "geometry": {"coordinates":[9.0954122543,48.8254013062],"type":"Point"}
}