{
  "type": "Feature",
  "properties": {
    "iso:country":"DE",
    "sg:address":"Spreenhagener Str. 4",
    "sg:city":"Wolzig",
    "sg:phone":"+49 33767/80215",
    "sg:postcode":"15754",
    "sg:province":"Brandenburg",
    "wof:name":"Cafe Moni",
    "wof:placetype":"venue"
},
  "geometry": {"coordinates":[13.766494751,52.2258796692],"type":"Point"}
}