{
  "type": "Feature",
  "properties": {
    "iso:country":"DE",
    "sg:address":"72532",
    "sg:city":"Gomadingen",
    "sg:postcode":"72532",
    "sg:province":"Baden-W\u00fcrttemberg",
    "wof:name":"Raiffeisenbank Gomadingen Eg",
    "wof:placetype":"venue"
},
  "geometry": {"coordinates":[9.392575,48.400364],"type":"Point"}
}