{
  "type": "Feature",
  "properties": {
    "iso:country":"DE",
    "sg:address":"Holzwiesenstr. 1",
    "sg:city":"M\u00fcnchen",
    "sg:phone":"+49 89/6378800",
    "sg:postcode":"81737",
    "sg:province":"Bayern",
    "wof:name":"Schopper Speditions Gmbh",
    "wof:placetype":"venue"
},
  "geometry": {"coordinates":[11.6307516098,48.1033782959],"type":"Point"}
}