{
  "type": "Feature",
  "properties": {
    "iso:country":"DE",
    "sg:address":"Van-Brackel-Str. 10",
    "sg:city":"Kleve",
    "sg:postcode":"47533",
    "sg:province":"Nordrhein-Westfalen",
    "wof:name":"D.g.-bautr\u00e4ger Gmbh",
    "wof:placetype":"venue"
},
  "geometry": {"coordinates":[6.124402,51.775517],"type":"Point"}
}