{
  "type": "Feature",
  "properties": {
    "iso:country":"DE",
    "sg:address":"Hauptstr. 25",
    "sg:city":"M\u00fcnk",
    "sg:postcode":"56729",
    "sg:province":"Rheinland-Pfalz",
    "wof:name":"Gbs Gleis- Und Bahnservice",
    "wof:placetype":"venue"
},
  "geometry": {"coordinates":[7.041094,50.307133],"type":"Point"}
}