{
  "type": "Feature",
  "properties": {
    "iso:country":"DE",
    "sg:address":"Hindenburgstr. 10",
    "sg:city":"M\u00f6nchengladbach",
    "sg:phone":"+49 2161/13205",
    "sg:postcode":"41061",
    "sg:province":"Nordrhein-Westfalen",
    "wof:name":"Fun-game Automaten Gmbh",
    "wof:placetype":"venue"
},
  "geometry": {"coordinates":[6.432472229,51.1938667297],"type":"Point"}
}