{
  "type": "Feature",
  "properties": {
    "iso:country":"DE",
    "sg:address":"Feilitzschstr. 24",
    "sg:city":"M\u00fcnchen",
    "sg:phone":"+49 89/333091",
    "sg:postcode":"80802",
    "sg:province":"Bayern",
    "wof:name":"West Bay Travel Gmbh",
    "wof:placetype":"venue"
},
  "geometry": {"coordinates":[11.5909204483,48.1607017517],"type":"Point"}
}