{
  "type": "Feature",
  "properties": {
    "iso:country":"DE",
    "sg:address":"Gebr\u00fcder-Lay-Str. 26",
    "sg:city":"Plauen",
    "sg:phone":"+49 3741/470966",
    "sg:postcode":"08527",
    "sg:province":"Sachsen",
    "wof:name":"H. Klemet",
    "wof:placetype":"venue"
},
  "geometry": {"coordinates":[12.144649,50.485996],"type":"Point"}
}