{
  "type": "Feature",
  "properties": {
    "iso:country":"DE",
    "sg:address":"Am Gasteig 3a",
    "sg:city":"P\u00e4hl",
    "sg:phone":"+49 8808/684",
    "sg:postcode":"82396",
    "sg:province":"Bayern",
    "wof:name":"Georg Kergl",
    "wof:placetype":"venue"
},
  "geometry": {"coordinates":[11.1801452637,47.9094276428],"type":"Point"}
}