{
  "type": "Feature",
  "properties": {
    "iso:country":"DE",
    "sg:address":"Sollingtor 15",
    "sg:city":"Northeim",
    "sg:phone":"+49 5551/987610",
    "sg:postcode":"37154",
    "sg:province":"Niedersachsen",
    "wof:name":"Friedhoff Bauges. Mbh",
    "wof:placetype":"venue"
},
  "geometry": {"coordinates":[9.9815301895,51.7050476074],"type":"Point"}
}