{
  "type": "Feature",
  "properties": {
    "iso:country":"DE",
    "sg:address":"Caller Str. 10",
    "sg:city":"Meschede",
    "sg:phone":"+49 2903/6081",
    "sg:postcode":"59872",
    "sg:province":"Nordrhein-Westfalen",
    "wof:name":"Gastst\u00e4tte Reinhold Mues",
    "wof:placetype":"venue"
},
  "geometry": {"coordinates":[8.1944856644,51.3302574158],"type":"Point"}
}