{
  "type": "Feature",
  "properties": {
    "iso:country":"DE",
    "sg:address":"Am Reutele 18",
    "sg:city":"Bad Schussenried",
    "sg:phone":"+49 7583/94060",
    "sg:postcode":"88427",
    "sg:province":"Baden-W\u00fcrttemberg",
    "wof:name":"Vebu Druck Gmbh",
    "wof:placetype":"venue"
},
  "geometry": {"coordinates":[9.6508331299,48.0174064636],"type":"Point"}
}