{
  "type": "Feature",
  "properties": {
    "iso:country":"DE",
    "sg:address":"Am R\u00f6mer 10",
    "sg:city":"Monzernheim",
    "sg:phone":"+49 6244/4896",
    "sg:postcode":"55234",
    "sg:province":"Rheinland-Pfalz",
    "wof:name":"Herbert Gottschall",
    "wof:placetype":"venue"
},
  "geometry": {"coordinates":[8.2259626389,49.7231559753],"type":"Point"}
}