{
  "type": "Feature",
  "properties": {
    "iso:country":"DE",
    "sg:address":"Ulmenstr. 13",
    "sg:city":"Willich",
    "sg:phone":"+49 2154/951441",
    "sg:postcode":"47877",
    "sg:province":"Nordrhein-Westfalen",
    "wof:name":"Edefau Gmbh",
    "wof:placetype":"venue"
},
  "geometry": {"coordinates":[6.5117969513,51.2453155518],"type":"Point"}
}