{
  "type": "Feature",
  "properties": {
    "iso:country":"DE",
    "sg:address":"Burgfreiheit 71",
    "sg:city":"M\u00f6nchengladbach",
    "sg:phone":"+49 2166/601464",
    "sg:postcode":"41199",
    "sg:province":"Nordrhein-Westfalen",
    "wof:name":"Ferdinand Knour",
    "wof:placetype":"venue"
},
  "geometry": {"coordinates":[6.45274,51.134579],"type":"Point"}
}