{
  "type": "Feature",
  "properties": {
    "iso:country":"DE",
    "sg:address":"Bahnhofstr. 51",
    "sg:city":"Lauterbach",
    "sg:postcode":"36341",
    "sg:province":"Hessen",
    "wof:name":"Sozialpsychiatrischer Beratungsdienst",
    "wof:placetype":"venue"
},
  "geometry": {"coordinates":[9.401141,50.639828],"type":"Point"}
}