{
  "type": "Feature",
  "properties": {
    "iso:country":"DE",
    "sg:address":"Wieselweg 8",
    "sg:city":"K\u00f6ln",
    "sg:phone":"+49 2234/77334",
    "sg:postcode":"50859",
    "sg:province":"Nordrhein-Westfalen",
    "wof:name":"Axel Kreckel Steuerberater",
    "wof:placetype":"venue"
},
  "geometry": {"coordinates":[6.8363499641,50.9448394775],"type":"Point"}
}