{
  "type": "Feature",
  "properties": {
    "iso:country":"DE",
    "sg:address":"Hemmerichstr. 10",
    "sg:city":"Bad Kissingen",
    "sg:phone":"+49 971/1311",
    "sg:postcode":"97688",
    "sg:province":"Bayern",
    "wof:name":"Fred Hilsdorf Rechtsanwalt",
    "wof:placetype":"venue"
},
  "geometry": {"coordinates":[10.0800189972,50.2021942139],"type":"Point"}
}