{
  "type": "Feature",
  "properties": {
    "iso:country":"DE",
    "sg:address":"Rosa-Luxemburg-Str.",
    "sg:city":"Gr\u00e4fenhainichen",
    "sg:postcode":"06773",
    "sg:province":"Sachsen-Anhalt",
    "wof:name":"Uhde Gmbh",
    "wof:placetype":"venue"
},
  "geometry": {"coordinates":[12.4521074295,51.7277526855],"type":"Point"}
}