{
  "type": "Feature",
  "properties": {
    "iso:country":"DE",
    "sg:address":"Eisenberger Str",
    "sg:city":"Dresden",
    "sg:phone":"+49 351/2054915",
    "sg:postcode":"01127",
    "sg:province":"Sachsen",
    "wof:name":"Dresden Outsourcing Service",
    "wof:placetype":"venue"
},
  "geometry": {"coordinates":[13.73073,51.072124],"type":"Point"}
}