{
  "type": "Feature",
  "properties": {
    "iso:country":"DE",
    "sg:address":"Westerminnerweg 22",
    "sg:city":"Jork",
    "sg:phone":"+49 4162/60160",
    "sg:postcode":"21635",
    "sg:province":"Niedersachsen",
    "wof:name":"Obstbauversuchsring Des Alten Landes E. V.",
    "wof:placetype":"venue"
},
  "geometry": {"coordinates":[9.6753454208,53.532245636],"type":"Point"}
}