{
  "type": "Feature",
  "properties": {
    "iso:country":"DE",
    "sg:address":"M\u00f6nkedieckstr. 1",
    "sg:city":"Osnabr\u00fcck",
    "sg:phone":"+49 541/185220",
    "sg:postcode":"49088",
    "sg:province":"Niedersachsen",
    "wof:name":"Comet",
    "wof:placetype":"venue"
},
  "geometry": {"coordinates":[8.0593671799,52.3009872437],"type":"Point"}
}