{
  "type": "Feature",
  "properties": {
    "iso:country":"DE",
    "sg:address":"Geilenkirchener Str. 51",
    "sg:city":"Gangelt",
    "sg:phone":"+49 2454/989030",
    "sg:postcode":"52538",
    "sg:province":"Nordrhein-Westfalen",
    "wof:name":"Leo Nybelen Gmbh Fensterbau & Co. Kg",
    "wof:placetype":"venue"
},
  "geometry": {"coordinates":[6.058895,51.006096],"type":"Point"}
}