{
  "type": "Feature",
  "properties": {
    "iso:country":"DE",
    "sg:address":"Bahnhofstr. 106",
    "sg:city":"M\u00fccke",
    "sg:phone":"+49 6400/8707",
    "sg:postcode":"35325",
    "sg:province":"Hessen",
    "wof:name":"Edys Imbi\u00df",
    "wof:placetype":"venue"
},
  "geometry": {"coordinates":[9.0277328491,50.6166419983],"type":"Point"}
}