{
  "type": "Feature",
  "properties": {
    "iso:country":"DE",
    "sg:address":"Falkenburgstr. 44",
    "sg:city":"K\u00f6ln",
    "sg:phone":"+49 221/431767",
    "sg:postcode":"50935",
    "sg:province":"Nordrhein-Westfalen",
    "wof:name":"Peter Caspers Inh. H. J. Saurbier",
    "wof:placetype":"venue"
},
  "geometry": {"coordinates":[6.9099369049,50.925113678],"type":"Point"}
}