{
  "type": "Feature",
  "properties": {
    "iso:country":"DE",
    "sg:address":"Randerather Str. 26",
    "sg:city":"Geilenkirchen",
    "sg:phone":"+49 2453/2152",
    "sg:postcode":"52511",
    "sg:province":"Nordrhein-Westfalen",
    "wof:name":"Th. Esser",
    "wof:placetype":"venue"
},
  "geometry": {"coordinates":[6.1907410622,50.9956092834],"type":"Point"}
}