{
  "type": "Feature",
  "properties": {
    "iso:country":"DE",
    "sg:address":"Bierweiderstr. 13",
    "sg:city":"Stolberg",
    "sg:phone":"+49 2402/22711",
    "sg:postcode":"52222",
    "sg:province":"Nordrhein-Westfalen",
    "wof:name":"Ch. L\u00f6hr Heissmangel",
    "wof:placetype":"venue"
},
  "geometry": {"coordinates":[6.2224969864,50.7760353088],"type":"Point"}
}