{
  "type": "Feature",
  "properties": {
    "iso:country":"DE",
    "sg:address":"Goethestr. 33",
    "sg:city":"Illerkirchberg",
    "sg:phone":"+49 7346/8380",
    "sg:postcode":"89171",
    "sg:province":"Baden-W\u00fcrttemberg",
    "wof:name":"S. Leissl Immobilienmakler",
    "wof:placetype":"venue"
},
  "geometry": {"coordinates":[10.0146245956,48.3226890564],"type":"Point"}
}