{
  "type": "Feature",
  "properties": {
    "iso:country":"DE",
    "sg:address":"74613",
    "sg:city":"\u00d6hringen",
    "sg:phone":"+49 7941/6900",
    "sg:postcode":"74613",
    "sg:province":"Baden-W\u00fcrttemberg",
    "wof:name":"Volksbank Hohenlohe Eg",
    "wof:placetype":"venue"
},
  "geometry": {"coordinates":[9.51584,49.21701],"type":"Point"}
}