{
  "type": "Feature",
  "properties": {
    "iso:country":"DE",
    "sg:address":"Kuchenbergstr. 34",
    "sg:city":"Neunkirchen",
    "sg:phone":"+49 6821/52478",
    "sg:postcode":"66540",
    "sg:province":"Saarland",
    "wof:name":"Gerlinde Kr\u00f6ber",
    "wof:placetype":"venue"
},
  "geometry": {"coordinates":[7.1834101677,49.3634910583],"type":"Point"}
}