{
  "type": "Feature",
  "properties": {
    "iso:country":"DE",
    "sg:address":"Schwaigstr. 32",
    "sg:city":"Sielenbach",
    "sg:phone":"+49 8258/493",
    "sg:postcode":"86577",
    "sg:province":"Bayern",
    "wof:name":"A. Mair",
    "wof:placetype":"venue"
},
  "geometry": {"coordinates":[11.159436,48.400925],"type":"Point"}
}