{
  "type": "Feature",
  "properties": {
    "iso:country":"DE",
    "sg:address":"Eulenring 29a",
    "sg:city":"Langg\u00f6ns",
    "sg:phone":"+49 6403/928758",
    "sg:postcode":"35428",
    "sg:province":"Hessen",
    "wof:name":"Brichet Vertriebs Gmbh",
    "wof:placetype":"venue"
},
  "geometry": {"coordinates":[8.6675977707,50.4926948547],"type":"Point"}
}