{
  "type": "Feature",
  "properties": {
    "iso:country":"DE",
    "sg:address":"Am T\u00e4nnig",
    "sg:city":"Sennfeld",
    "sg:phone":"+49 9721/68377",
    "sg:postcode":"97526",
    "sg:province":"Bayern",
    "wof:name":"Naturfreundehaus Haus Frankenland",
    "wof:placetype":"venue"
},
  "geometry": {"coordinates":[10.250623703,50.0293617249],"type":"Point"}
}