{
  "type": "Feature",
  "properties": {
    "iso:country":"DE",
    "sg:address":"Eislebener Str. 1a",
    "sg:city":"Bischofrode",
    "sg:phone":"+49 3475/719780",
    "sg:postcode":"06295",
    "sg:province":"Sachsen-Anhalt",
    "wof:name":"Anton Aschenbrenner",
    "wof:placetype":"venue"
},
  "geometry": {"coordinates":[11.537217,51.489773],"type":"Point"}
}