{
  "type": "Feature",
  "properties": {
    "iso:country":"DE",
    "sg:address":"Springestr. 8",
    "sg:city":"Gelsenkirchen",
    "sg:phone":"+49 209/318220",
    "sg:postcode":"45894",
    "sg:province":"Nordrhein-Westfalen",
    "wof:name":"P\u00f6ppinghaus Marten Und Bogatz Rechtsanw\u00e4lte Und Notare",
    "wof:placetype":"venue"
},
  "geometry": {"coordinates":[7.0554661751,51.5782089233],"type":"Point"}
}