{
  "type": "Feature",
  "properties": {
    "iso:country":"DE",
    "sg:address":"Maybachstr. 2",
    "sg:city":"Westerland",
    "sg:phone":"+49 4651/821",
    "sg:postcode":"25980",
    "sg:province":"Schleswig-Holstein",
    "wof:name":"Sparkasse Nordfriesland",
    "wof:placetype":"venue"
},
  "geometry": {"coordinates":[8.305767,54.908642],"type":"Point"}
}