{
  "type": "Feature",
  "properties": {
    "iso:country":"DE",
    "sg:address":"Holzstr. 4",
    "sg:city":"Dahlen",
    "sg:phone":"+49 34361/51325",
    "sg:postcode":"04774",
    "sg:province":"Sachsen",
    "wof:name":"Restaurant Hospitalh\u00fctte",
    "wof:placetype":"venue"
},
  "geometry": {"coordinates":[13.0299930573,51.4076385498],"type":"Point"}
}