{
  "type": "Feature",
  "properties": {
    "iso:country":"DE",
    "sg:address":"Havixbeckerstr. 9",
    "sg:city":"Senden",
    "sg:phone":"+49 2536/452",
    "sg:postcode":"48308",
    "sg:province":"Nordrhein-Westfalen",
    "wof:name":"Volksbank M\u00fcnster Eg",
    "wof:placetype":"venue"
},
  "geometry": {"coordinates":[7.483098,51.857323],"type":"Point"}
}