{
  "type": "Feature",
  "properties": {
    "iso:country":"DE",
    "sg:address":"Norderstr. 97",
    "sg:city":"Heide",
    "sg:phone":"+49 481/7510",
    "sg:postcode":"25746",
    "sg:province":"Schleswig-Holstein",
    "wof:name":"Detlev Lintz",
    "wof:placetype":"venue"
},
  "geometry": {"coordinates":[9.083106,54.198532],"type":"Point"}
}