{
  "type": "Feature",
  "properties": {
    "iso:country":"DE",
    "sg:address":"Haspeler Str. 8",
    "sg:city":"Wuppertal",
    "sg:phone":"+49 202/85031",
    "sg:postcode":"42285",
    "sg:province":"Nordrhein-Westfalen",
    "wof:name":"Hagemeyer Und Kosack Rechtsanw\u00e4lte",
    "wof:placetype":"venue"
},
  "geometry": {"coordinates":[7.1644220352,51.2584152222],"type":"Point"}
}