{
  "type": "Feature",
  "properties": {
    "iso:country":"DE",
    "sg:address":"Am Dachsberg 13",
    "sg:city":"Frankfurt",
    "sg:phone":"+49 69/544332",
    "sg:postcode":"60435",
    "sg:province":"Hessen",
    "wof:name":"Astrid Heil Rechtsanw\u00e4ltin",
    "wof:placetype":"venue"
},
  "geometry": {"coordinates":[8.6964435577,50.1699714661],"type":"Point"}
}