{
  "type": "Feature",
  "properties": {
    "iso:country":"DE",
    "sg:address":"Sch\u00f6nbornstra\u00dfe 27",
    "sg:city":"Werneck",
    "sg:postcode":"97440",
    "sg:province":"Bayern",
    "wof:name":"Spatzennest - Die Kneipe",
    "wof:placetype":"venue"
},
  "geometry": {"coordinates":[10.0986280441,49.983757019],"type":"Point"}
}