{
  "type": "Feature",
  "properties": {
    "iso:country":"DE",
    "sg:address":"Kunohof 25",
    "sg:city":"Saarburg",
    "sg:phone":"+49 6581/2260",
    "sg:postcode":"54439",
    "sg:province":"Rheinland-Pfalz",
    "wof:name":"Kath. Pfarramt St. Laurentius",
    "wof:placetype":"venue"
},
  "geometry": {"coordinates":[6.5510101318,49.607219696],"type":"Point"}
}