{
  "type": "Feature",
  "properties": {
    "iso:country":"DE",
    "sg:address":"Furtmayrstr. 22",
    "sg:city":"Regensburg",
    "sg:phone":"+49 941/73420",
    "sg:postcode":"93053",
    "sg:province":"Bayern",
    "wof:name":"Katholisches Pfarramt St. Anton",
    "wof:placetype":"venue"
},
  "geometry": {"coordinates":[12.1095657349,49.0091133118],"type":"Point"}
}