{
  "type": "Feature",
  "properties": {
    "iso:country":"DE",
    "sg:address":"Kollegienwall 12",
    "sg:city":"Osnabr\u00fcck",
    "sg:postcode":"49074",
    "sg:province":"Niedersachsen",
    "wof:name":"Landeszentralbank Osnabr\u00fcck",
    "wof:placetype":"venue"
},
  "geometry": {"coordinates":[8.0539503098,52.2722854614],"type":"Point"}
}