{
  "type": "Feature",
  "properties": {
    "iso:country":"DE",
    "sg:address":"R\u00f6merweg 55",
    "sg:city":"Augsburg",
    "sg:phone":"+49 821/91988",
    "sg:postcode":"86199",
    "sg:province":"Bayern",
    "wof:name":"Pvg Popul\u00e4rwissenschaftliche Verlags-gmbh",
    "wof:placetype":"venue"
},
  "geometry": {"coordinates":[10.8690223694,48.3351097107],"type":"Point"}
}