{
  "type": "Feature",
  "properties": {
    "iso:country":"DE",
    "sg:address":"Heestweg 27",
    "sg:city":"Hamburg",
    "sg:phone":"+49 40/6773522",
    "sg:postcode":"22143",
    "sg:province":"Hamburg",
    "wof:name":"Bruno Grau",
    "wof:placetype":"venue"
},
  "geometry": {"coordinates":[10.1487178802,53.6028862],"type":"Point"}
}