{
  "type": "Feature",
  "properties": {
    "iso:country":"DE",
    "sg:address":"Flughafenstr. 25",
    "sg:city":"M\u00f6rfelden-Walldorf",
    "sg:phone":"+49 6105/5490",
    "sg:postcode":"64546",
    "sg:province":"Hessen",
    "wof:name":"Peter Steckenreiter Architekt",
    "wof:placetype":"venue"
},
  "geometry": {"coordinates":[8.576817,50.004089],"type":"Point"}
}