{
  "type": "Feature",
  "properties": {
    "iso:country":"DE",
    "sg:address":"Brauereiweg 16",
    "sg:city":"Flensburg",
    "sg:phone":"+49 461/42500",
    "sg:postcode":"24939",
    "sg:province":"Schleswig-Holstein",
    "wof:name":"Niro Petersen Ohg",
    "wof:placetype":"venue"
},
  "geometry": {"coordinates":[9.4278,54.802811],"type":"Point"}
}