{
  "type": "Feature",
  "properties": {
    "iso:country":"DE",
    "sg:address":"Schulstr. 8",
    "sg:city":"Pfofeld",
    "sg:phone":"+49 9834/1090",
    "sg:postcode":"91738",
    "sg:province":"Bayern",
    "wof:name":"Schlosser",
    "wof:placetype":"venue"
},
  "geometry": {"coordinates":[10.850476,49.119835],"type":"Point"}
}