{
  "type": "Feature",
  "properties": {
    "iso:country":"DE",
    "sg:address":"Hagsteige 1",
    "sg:city":"Urbach",
    "sg:phone":"+49 7181/83356",
    "sg:postcode":"73660",
    "sg:province":"Baden-W\u00fcrttemberg",
    "wof:name":"Freibad Urbach",
    "wof:placetype":"venue"
},
  "geometry": {"coordinates":[9.5750436783,48.8239135742],"type":"Point"}
}