{
  "type": "Feature",
  "properties": {
    "iso:country":"DE",
    "sg:address":"Albertstr 20",
    "sg:city":"Dresden",
    "sg:phone":"+49 351/5022340",
    "sg:postcode":"01097",
    "sg:province":"Sachsen",
    "wof:name":"Volksbank Dresden Eg",
    "wof:placetype":"venue"
},
  "geometry": {"coordinates":[13.7462,51.05928],"type":"Point"}
}