{
  "type": "Feature",
  "properties": {
    "iso:country":"DE",
    "sg:address":"Im Wiesengrund 1",
    "sg:city":"Ro\u00dftal",
    "sg:phone":"+49 9127/8873",
    "sg:postcode":"90574",
    "sg:province":"Bayern",
    "wof:name":"Elektro-peipp Gmbh & Co. Kg",
    "wof:placetype":"venue"
},
  "geometry": {"coordinates":[10.883573,49.36285],"type":"Point"}
}