{
  "type": "Feature",
  "properties": {
    "iso:country":"DE",
    "sg:address":"Heinrich-Tiarks-Str. 5",
    "sg:city":"Wangerland",
    "sg:phone":"+49 4426/99010",
    "sg:postcode":"26434",
    "sg:province":"Niedersachsen",
    "wof:name":"Schmidts H\u00f6rn",
    "wof:placetype":"venue"
},
  "geometry": {"coordinates":[8.0090351105,53.683631897],"type":"Point"}
}