{
  "type": "Feature",
  "properties": {
    "iso:country":"DE",
    "sg:address":"Wittener Str. 96a",
    "sg:city":"Sprockh\u00f6vel",
    "sg:phone":"+49 2339/2032",
    "sg:postcode":"45549",
    "sg:province":"Nordrhein-Westfalen",
    "wof:name":"Apple Computer Gmbh",
    "wof:placetype":"venue"
},
  "geometry": {"coordinates":[7.2935600281,51.3476486206],"type":"Point"}
}