{
  "type": "Feature",
  "properties": {
    "iso:country":"DE",
    "sg:address":"Stievenstr. 2",
    "sg:city":"Dissen",
    "sg:phone":"+49 5421/2922",
    "sg:postcode":"49201",
    "sg:province":"Niedersachsen",
    "wof:name":"Sayonara Tours Gmbh",
    "wof:placetype":"venue"
},
  "geometry": {"coordinates":[8.2049970627,52.1151809692],"type":"Point"}
}