{
  "type": "Feature",
  "properties": {
    "iso:country":"DE",
    "sg:address":"Weiferweg 12",
    "sg:city":"Hallenberg",
    "sg:phone":"+49 2984/92000",
    "sg:postcode":"59969",
    "sg:province":"Nordrhein-Westfalen",
    "wof:name":"Mazarese Kabelkonfektion",
    "wof:placetype":"venue"
},
  "geometry": {"coordinates":[8.620781,51.108124],"type":"Point"}
}