{
  "type": "Feature",
  "properties": {
    "iso:country":"DE",
    "sg:address":"Hauptstr. 24",
    "sg:city":"D\u00f6rpstedt",
    "sg:phone":"+49 4627/246",
    "sg:postcode":"24869",
    "sg:province":"Schleswig-Holstein",
    "wof:name":"Detlef Hagge Verwaltungsgesellschaft Mbh",
    "wof:placetype":"venue"
},
  "geometry": {"coordinates":[9.3591861725,54.4403648376],"type":"Point"}
}