{
  "type": "Feature",
  "properties": {
    "iso:country":"DE",
    "sg:address":"Fahrenort 46",
    "sg:city":"Hamburg",
    "sg:phone":"+49 40/836514",
    "sg:postcode":"22547",
    "sg:province":"Hamburg",
    "wof:name":"Johann Tr\u00f6mpert",
    "wof:placetype":"venue"
},
  "geometry": {"coordinates":[9.875039,53.600658],"type":"Point"}
}