{
  "type": "Feature",
  "properties": {
    "iso:country":"DE",
    "sg:address":"Dieburger Str. 26",
    "sg:city":"Gro\u00df-Zimmern",
    "sg:phone":"+49 6071/48811",
    "sg:postcode":"64846",
    "sg:province":"Hessen",
    "wof:name":"Schlosserei Und Metallbau Heinrich Steinbrecher",
    "wof:placetype":"venue"
},
  "geometry": {"coordinates":[8.83076,49.875851],"type":"Point"}
}