{
  "type": "Feature",
  "properties": {
    "iso:country":"DE",
    "sg:address":"K\u00f6nigsteiner Str. 76",
    "sg:city":"Bad Soden",
    "sg:phone":"+49 6196/528620",
    "sg:postcode":"65812",
    "sg:province":"Hessen",
    "wof:name":"Emil Tengelmann",
    "wof:placetype":"venue"
},
  "geometry": {"coordinates":[8.5025548935,50.1433563232],"type":"Point"}
}