{
  "type": "Feature",
  "properties": {
    "iso:country":"DE",
    "sg:address":"Jakobstr. 88",
    "sg:city":"Aachen",
    "sg:phone":"+49 241/35773",
    "sg:postcode":"52064",
    "sg:province":"Nordrhein-Westfalen",
    "wof:name":"Dieter Simais",
    "wof:placetype":"venue"
},
  "geometry": {"coordinates":[6.07813,50.773823],"type":"Point"}
}