{
  "type": "Feature",
  "properties": {
    "iso:country":"DE",
    "sg:address":"Sickinger Str. 98",
    "sg:city":"Kraichtal",
    "sg:phone":"+49 7250/283",
    "sg:postcode":"76703",
    "sg:province":"Baden-W\u00fcrttemberg",
    "wof:name":"Horst Winter",
    "wof:placetype":"venue"
},
  "geometry": {"coordinates":[8.78395,49.115314],"type":"Point"}
}