{
  "type": "Feature",
  "properties": {
    "iso:country":"DE",
    "sg:address":"Schie\u00dflweg 10",
    "sg:city":"Sulzbach-Rosenberg",
    "sg:phone":"+49 9661/87320",
    "sg:postcode":"92237",
    "sg:province":"Bayern",
    "wof:name":"Bavaria Senioren- Und Pflegeheim Gmbh",
    "wof:placetype":"venue"
},
  "geometry": {"coordinates":[11.741082,49.501331],"type":"Point"}
}