{
  "type": "Feature",
  "properties": {
    "iso:country":"DE",
    "sg:address":"Brucknerstr. 20",
    "sg:city":"Remseck",
    "sg:phone":"+49 7146/3322",
    "sg:postcode":"71686",
    "sg:province":"Baden-W\u00fcrttemberg",
    "wof:name":"Beck Ingenieur",
    "wof:placetype":"venue"
},
  "geometry": {"coordinates":[9.2834873199,48.8693733215],"type":"Point"}
}