{
  "type": "Feature",
  "properties": {
    "iso:country":"DE",
    "sg:address":"Schneeberger Str. 66",
    "sg:city":"Aue",
    "sg:phone":"+49 3771/251351",
    "sg:postcode":"08280",
    "sg:province":"Sachsen",
    "wof:name":"H. Just",
    "wof:placetype":"venue"
},
  "geometry": {"coordinates":[12.694007,50.590485],"type":"Point"}
}