{
  "type": "Feature",
  "properties": {
    "iso:country":"DE",
    "sg:address":"Lange Str. 10",
    "sg:city":"Waiblingen",
    "sg:phone":"+49 7151/508505",
    "sg:postcode":"71332",
    "sg:province":"Baden-W\u00fcrttemberg",
    "wof:name":"Fa .copratel Gmbh Online",
    "wof:placetype":"venue"
},
  "geometry": {"coordinates":[9.31736,48.833405],"type":"Point"}
}