{
  "type": "Feature",
  "properties": {
    "iso:country":"DE",
    "sg:address":"Bahnhofstr. 1",
    "sg:city":"Ludwigslust",
    "sg:phone":"+49 3874/21687",
    "sg:postcode":"19288",
    "sg:province":"Mecklenburg-Vorpommern",
    "wof:name":"Uwe Topp",
    "wof:placetype":"venue"
},
  "geometry": {"coordinates":[11.4965753555,53.3302955627],"type":"Point"}
}