{
  "type": "Feature",
  "properties": {
    "iso:country":"DE",
    "sg:address":"W\u00e4chterstr. 53",
    "sg:city":"Oyten",
    "sg:phone":"+49 4207/1824",
    "sg:postcode":"28876",
    "sg:province":"Niedersachsen",
    "wof:name":"Klaus Ciellas Architekt",
    "wof:placetype":"venue"
},
  "geometry": {"coordinates":[9.018697,53.050533],"type":"Point"}
}