{
  "type": "Feature",
  "properties": {
    "iso:country":"DE",
    "sg:address":"Bahnhofstr. 1",
    "sg:city":"B\u00f6blingen",
    "sg:phone":"+49 7031/229871",
    "sg:postcode":"71034",
    "sg:province":"Baden-W\u00fcrttemberg",
    "wof:name":"Nokia Shop",
    "wof:placetype":"venue"
},
  "geometry": {"coordinates":[9.0094203949,48.6855010986],"type":"Point"}
}