{
  "type": "Feature",
  "properties": {
    "iso:country":"DE",
    "sg:address":"Schulstr. 12",
    "sg:city":"Havelberg",
    "sg:phone":"+49 39387/21577",
    "sg:postcode":"39539",
    "sg:province":"Sachsen-Anhalt",
    "wof:name":"Pension J. Dyck",
    "wof:placetype":"venue"
},
  "geometry": {"coordinates":[12.0757570267,52.8247642517],"type":"Point"}
}