{
  "type": "Feature",
  "properties": {
    "iso:country":"DE",
    "sg:address":"Kardorfer Str. 17",
    "sg:city":"Wesseling",
    "sg:phone":"+49 2236/843416",
    "sg:postcode":"50389",
    "sg:province":"Nordrhein-Westfalen",
    "wof:name":"U. Ding",
    "wof:placetype":"venue"
},
  "geometry": {"coordinates":[6.9829010963,50.8122901917],"type":"Point"}
}