{
  "type": "Feature",
  "properties": {
    "iso:country":"DE",
    "sg:address":"Mettmanner Str. 203",
    "sg:city":"Velbert",
    "sg:phone":"+49 2051/23140",
    "sg:postcode":"42549",
    "sg:province":"Nordrhein-Westfalen",
    "wof:name":"Theo Jan\u00dfen",
    "wof:placetype":"venue"
},
  "geometry": {"coordinates":[7.045648,51.323826],"type":"Point"}
}