{
  "type": "Feature",
  "properties": {
    "iso:country":"DE",
    "sg:address":"Weg am Wehrholz 27",
    "sg:city":"Waldems",
    "sg:phone":"+49 6082/3377",
    "sg:postcode":"65529",
    "sg:province":"Hessen",
    "wof:name":"Helmut Neuwirth",
    "wof:placetype":"venue"
},
  "geometry": {"coordinates":[8.3890399933,50.2503242493],"type":"Point"}
}