{
  "type": "Feature",
  "properties": {
    "iso:country":"DE",
    "sg:address":"Fritz-Stegen-Allee 6",
    "sg:city":"Peine",
    "sg:phone":"+49 5171/56121",
    "sg:postcode":"31226",
    "sg:province":"Niedersachsen",
    "wof:name":"Walking Bauger\u00e4te",
    "wof:placetype":"venue"
},
  "geometry": {"coordinates":[10.229596138,52.3124313354],"type":"Point"}
}