{
  "type": "Feature",
  "properties": {
    "iso:country":"DE",
    "sg:address":"Siegener Strasse 210::",
    "sg:city":"Kreuztal",
    "sg:phone":"+49 2732/7910404",
    "sg:postcode":"57223",
    "sg:province":"Nordrhein-Westfalen",
    "wof:name":"Br\u00dcnsch Gmbh Streckgittertechnik",
    "wof:placetype":"venue"
},
  "geometry": {"coordinates":[8.0101041794,50.9287185669],"type":"Point"}
}