{
  "type": "Feature",
  "properties": {
    "iso:country":"DE",
    "sg:address":"Borstendorfer Str. 20",
    "sg:city":"Leubsdorf",
    "sg:phone":"+49 4937/2916595",
    "sg:postcode":"09573",
    "sg:province":"Sachsen",
    "wof:name":"Ergoplast Kunststoff Gmbh",
    "wof:placetype":"venue"
},
  "geometry": {"coordinates":[13.1665229797,50.7946548462],"type":"Point"}
}