{
  "type": "Feature",
  "properties": {
    "iso:country":"DE",
    "sg:address":"Graf-Berthold-Str. 6",
    "sg:city":"Schweinfurt",
    "sg:phone":"+49 9721/34999",
    "sg:postcode":"97422",
    "sg:province":"Bayern",
    "wof:name":"Eschenbach-karg Und Eschenbach",
    "wof:placetype":"venue"
},
  "geometry": {"coordinates":[10.2515172958,50.0532188416],"type":"Point"}
}