{
  "type": "Feature",
  "properties": {
    "iso:country":"DE",
    "sg:address":"Alemannenstr. 13",
    "sg:city":"Gemmrigheim",
    "sg:phone":"+49 7143/91050",
    "sg:postcode":"74376",
    "sg:province":"Baden-W\u00fcrttemberg",
    "wof:name":"Manfred Sch\u00e4fer Masseur",
    "wof:placetype":"venue"
},
  "geometry": {"coordinates":[9.154907,49.030586],"type":"Point"}
}