{
  "type": "Feature",
  "properties": {
    "iso:country":"DE",
    "sg:address":"Sybillastr. 4",
    "sg:city":"Rheinstetten",
    "sg:phone":"+49 7242/5893",
    "sg:postcode":"76287",
    "sg:province":"Baden-W\u00fcrttemberg",
    "wof:name":"Hgv Immobilien Gmbh",
    "wof:placetype":"venue"
},
  "geometry": {"coordinates":[8.2660551071,48.9682617188],"type":"Point"}
}