{
  "type": "Feature",
  "properties": {
    "iso:country":"DE",
    "sg:address":"Schulstr. 2",
    "sg:city":"Gro\u00df Kreutz",
    "sg:phone":"+49 33207/2345",
    "sg:postcode":"14550",
    "sg:province":"Brandenburg",
    "wof:name":"Suffner-transporte",
    "wof:placetype":"venue"
},
  "geometry": {"coordinates":[12.700548172,52.4113578796],"type":"Point"}
}