{
  "type": "Feature",
  "properties": {
    "iso:country":"DE",
    "sg:address":"K\u00f6feringer Str. 2",
    "sg:city":"Amberg",
    "sg:phone":"+49 9621/82420",
    "sg:postcode":"92224",
    "sg:province":"Bayern",
    "wof:name":"Aral Ag",
    "wof:placetype":"venue"
},
  "geometry": {"coordinates":[11.8576278687,49.4370956421],"type":"Point"}
}