{
  "type": "Feature",
  "properties": {
    "iso:country":"DE",
    "sg:address":"Seestr. 31",
    "sg:city":"Sassnitz",
    "sg:phone":"+49 38392/22716",
    "sg:postcode":"18546",
    "sg:province":"Mecklenburg-Vorpommern",
    "wof:name":"K\u00e4the Blandow",
    "wof:placetype":"venue"
},
  "geometry": {"coordinates":[13.650856,54.517574],"type":"Point"}
}