{
  "type": "Feature",
  "properties": {
    "iso:country":"DE",
    "sg:address":"Geblerstr. 7",
    "sg:city":"Dresden",
    "sg:phone":"+49 351/8496469",
    "sg:postcode":"01139",
    "sg:province":"Sachsen",
    "wof:name":"Bauwerk Bautr\u00e4ger Gmbh",
    "wof:placetype":"venue"
},
  "geometry": {"coordinates":[13.701323,51.092407],"type":"Point"}
}