{
  "type": "Feature",
  "properties": {
    "iso:country":"DE",
    "sg:address":"Postfach 1260:: 56802 Cochem:: Germany.^^Br\u00fcckenstr 2::",
    "sg:city":"Cochem",
    "sg:phone":"+49 2671/6010",
    "sg:postcode":"56812",
    "sg:province":"Rheinland-Pfalz",
    "wof:name":"Kreissparkasse Cochem-zell",
    "wof:placetype":"venue"
},
  "geometry": {"coordinates":[7.167131,50.145538],"type":"Point"}
}