{
  "type": "Feature",
  "properties": {
    "iso:country":"DE",
    "sg:address":"Hauptstr. 47",
    "sg:city":"Illingen",
    "sg:phone":"+49 6825/3888",
    "sg:postcode":"66557",
    "sg:province":"Saarland",
    "wof:name":"G\u00fcnter Kern Massagepraxis",
    "wof:placetype":"venue"
},
  "geometry": {"coordinates":[7.051168,49.377148],"type":"Point"}
}