{
  "type": "Feature",
  "properties": {
    "iso:country":"DE",
    "sg:address":"S\u00fcdendstr. 54",
    "sg:city":"Berlin",
    "sg:phone":"+49 30/7914918",
    "sg:postcode":"12169",
    "sg:province":"Berlin",
    "wof:name":"Joachim K\u00e4stel",
    "wof:placetype":"venue"
},
  "geometry": {"coordinates":[13.330336,52.45631],"type":"Point"}
}