{
  "type": "Feature",
  "properties": {
    "iso:country":"DE",
    "sg:address":"Waldgirmeser Str. 6",
    "sg:city":"Lahnau",
    "sg:phone":"+49 6441/96470",
    "sg:postcode":"35633",
    "sg:province":"Hessen",
    "wof:name":"K. Reinst\u00e4dtler",
    "wof:placetype":"venue"
},
  "geometry": {"coordinates":[8.5649251938,50.5780296326],"type":"Point"}
}