{
  "type": "Feature",
  "properties": {
    "iso:country":"DE",
    "sg:address":"Mutschellestr. 4",
    "sg:city":"M\u00fcnchen",
    "sg:phone":"+49 89/432153",
    "sg:postcode":"81673",
    "sg:province":"Bayern",
    "wof:name":"Tesa Handels Gmbh",
    "wof:placetype":"venue"
},
  "geometry": {"coordinates":[11.638220787,48.1257476807],"type":"Point"}
}