{
  "type": "Feature",
  "properties": {
    "iso:country":"DE",
    "sg:address":"Dornheimer Str. 29",
    "sg:city":"Gro\u00df-Gerau",
    "sg:postcode":"64521",
    "sg:province":"Hessen",
    "wof:name":"Schaffner Gmbh",
    "wof:placetype":"venue"
},
  "geometry": {"coordinates":[8.48595,49.898289],"type":"Point"}
}