{
  "type": "Feature",
  "properties": {
    "iso:country":"DE",
    "sg:address":"Grenzacher Str. 9",
    "sg:city":"Rheinfelden",
    "sg:phone":"+49 7623/4238",
    "sg:postcode":"79618",
    "sg:province":"Baden-W\u00fcrttemberg",
    "wof:name":"Birlin M\u00fchle Gmbh",
    "wof:placetype":"venue"
},
  "geometry": {"coordinates":[7.7459759712,47.5702018738],"type":"Point"}
}