{
  "type": "Feature",
  "properties": {
    "iso:country":"DE",
    "sg:address":"K\u00f6sseinestr. 2",
    "sg:city":"Marktredwitz",
    "sg:phone":"+49 9231/2998",
    "sg:postcode":"95615",
    "sg:province":"Bayern",
    "wof:name":"Christian Zahn",
    "wof:placetype":"venue"
},
  "geometry": {"coordinates":[12.087937355,49.9990539551],"type":"Point"}
}