{
  "type": "Feature",
  "properties": {
    "iso:country":"DE",
    "sg:address":"Strelitzer Str. 14",
    "sg:city":"Neustrelitz",
    "sg:phone":"+49 3981/200877",
    "sg:postcode":"17235",
    "sg:province":"Mecklenburg-Vorpommern",
    "wof:name":"Viva Neubrandenburger Haar- Und Kosmetik Gmbh",
    "wof:placetype":"venue"
},
  "geometry": {"coordinates":[13.066177,53.360931],"type":"Point"}
}