{
  "type": "Feature",
  "properties": {
    "iso:country":"DE",
    "sg:address":"Tummelplatzweg 13",
    "sg:city":"Memmingen",
    "sg:phone":"+49 8331/5478",
    "sg:postcode":"87700",
    "sg:province":"Bayern",
    "wof:name":"Karlheinz Preihsing Ingenieur",
    "wof:placetype":"venue"
},
  "geometry": {"coordinates":[10.1827936172,47.9901123047],"type":"Point"}
}