{
  "type": "Feature",
  "properties": {
    "iso:country":"DE",
    "sg:address":"Leuterstaler Str. 17",
    "sg:city":"Jagsthausen",
    "sg:phone":"+49 7943/2128",
    "sg:postcode":"74249",
    "sg:province":"Baden-W\u00fcrttemberg",
    "wof:name":"Helmut Dederer",
    "wof:placetype":"venue"
},
  "geometry": {"coordinates":[9.467583,49.31546],"type":"Point"}
}