{
  "type": "Feature",
  "properties": {
    "iso:country":"DE",
    "sg:address":"Rennweg 103",
    "sg:city":"Landshut",
    "sg:postcode":"84034",
    "sg:province":"Bayern",
    "wof:name":"Josef Baumgartner Immobilien- Verwaltung Gmbh & Co. Kg",
    "wof:placetype":"venue"
},
  "geometry": {"coordinates":[12.1273078918,48.5393791199],"type":"Point"}
}