{
  "type": "Feature",
  "properties": {
    "iso:country":"DE",
    "sg:address":"Bismarckstr. 59",
    "sg:city":"Delitzsch",
    "sg:phone":"+49 34202/61645",
    "sg:postcode":"04509",
    "sg:province":"Sachsen",
    "wof:name":"Kurt Adam",
    "wof:placetype":"venue"
},
  "geometry": {"coordinates":[12.3448419571,51.5229415894],"type":"Point"}
}