{
  "type": "Feature",
  "properties": {
    "iso:country":"DE",
    "sg:address":"Eppersdorfer Str. 4",
    "sg:city":"Allersberg",
    "sg:phone":"+49 9176/888",
    "sg:postcode":"90584",
    "sg:province":"Bayern",
    "wof:name":"Lorenz Nagl",
    "wof:placetype":"venue"
},
  "geometry": {"coordinates":[11.241829,49.255135],"type":"Point"}
}