{
  "type": "Feature",
  "properties": {
    "iso:country":"DE",
    "sg:address":"Elchinger Str. 15",
    "sg:city":"Elchingen",
    "sg:phone":"+49 731/263800",
    "sg:postcode":"89275",
    "sg:province":"Bayern",
    "wof:name":"Wein- Und Getr\u00e4nke",
    "wof:placetype":"venue"
},
  "geometry": {"coordinates":[10.0520620346,48.4376983643],"type":"Point"}
}