{
  "type": "Feature",
  "properties": {
    "iso:country":"DE",
    "sg:address":"Luitpoldstr 1",
    "sg:city":"Dinkelsb\u00fchl",
    "sg:phone":"+49 9851/554390",
    "sg:postcode":"91550",
    "sg:province":"Bayern",
    "wof:name":"Onesoft Ag",
    "wof:placetype":"venue"
},
  "geometry": {"coordinates":[10.324216,49.070396],"type":"Point"}
}