{
  "type": "Feature",
  "properties": {
    "iso:country":"DE",
    "sg:address":"Singener Str. 16",
    "sg:city":"Rielasingen-Worblingen",
    "sg:phone":"+49 7731/52061",
    "sg:postcode":"78239",
    "sg:province":"Baden-W\u00fcrttemberg",
    "wof:name":"All-med Gmbh",
    "wof:placetype":"venue"
},
  "geometry": {"coordinates":[8.84045,47.737389],"type":"Point"}
}