{
  "type": "Feature",
  "properties": {
    "iso:country":"DE",
    "sg:address":"Mecklenburger Str. 4",
    "sg:city":"Ratzeburg",
    "sg:phone":"+49 4541/6360",
    "sg:postcode":"23909",
    "sg:province":"Schleswig-Holstein",
    "wof:name":"L. Prescher & A. Sch\u00fctt Heissmangelbetrieb",
    "wof:placetype":"venue"
},
  "geometry": {"coordinates":[10.7958135605,53.6967735291],"type":"Point"}
}