{
  "type": "Feature",
  "properties": {
    "iso:country":"DE",
    "sg:address":"Tornberg 11",
    "sg:city":"Hamburg",
    "sg:phone":"+49 40/503243",
    "sg:postcode":"22337",
    "sg:province":"Hamburg",
    "wof:name":"G\u00fcnter Schulz Architekt",
    "wof:placetype":"venue"
},
  "geometry": {"coordinates":[10.054686,53.629959],"type":"Point"}
}