{
  "type": "Feature",
  "properties": {
    "iso:country":"DE",
    "sg:address":"Konrad-Adenauer-Str. 9",
    "sg:city":"Wehrheim",
    "sg:phone":"+49 6081/56106",
    "sg:postcode":"61273",
    "sg:province":"Hessen",
    "wof:name":"Dieter Quant",
    "wof:placetype":"venue"
},
  "geometry": {"coordinates":[8.603581,50.328247],"type":"Point"}
}