{
  "type": "Feature",
  "properties": {
    "iso:country":"DE",
    "sg:address":"Markt 10",
    "sg:city":"Siegburg",
    "sg:phone":"+49 2241/59390",
    "sg:postcode":"53721",
    "sg:province":"Nordrhein-Westfalen",
    "wof:name":"Getto & Beyer Gmbh",
    "wof:placetype":"venue"
},
  "geometry": {"coordinates":[7.2067990303,50.7970046997],"type":"Point"}
}