{
  "type": "Feature",
  "properties": {
    "iso:country":"DE",
    "sg:address":"Industriestr. 5",
    "sg:city":"M\u00fccke",
    "sg:phone":"+49 6400/91030",
    "sg:postcode":"35325",
    "sg:province":"Hessen",
    "wof:name":"Tiber K\u00fcttler",
    "wof:placetype":"venue"
},
  "geometry": {"coordinates":[9.040760994,50.6444473267],"type":"Point"}
}