{
  "type": "Feature",
  "properties": {
    "iso:country":"DE",
    "sg:address":"Kleiststr. 7 A",
    "sg:city":"M\u00fclheim",
    "sg:phone":"+49 208/492434",
    "sg:postcode":"45472",
    "sg:province":"Nordrhein-Westfalen",
    "wof:name":"Kleist-apotheke",
    "wof:placetype":"venue"
},
  "geometry": {"coordinates":[6.937141,51.428837],"type":"Point"}
}