{
  "type": "Feature",
  "properties": {
    "iso:country":"DE",
    "sg:address":"Kirchstr. 10",
    "sg:city":"Neuenstadt",
    "sg:phone":"+49 7139/1285",
    "sg:postcode":"74196",
    "sg:province":"Baden-W\u00fcrttemberg",
    "wof:name":"Gastst\u00e4tte F. Vogt",
    "wof:placetype":"venue"
},
  "geometry": {"coordinates":[9.3085746765,49.2451934814],"type":"Point"}
}