{
  "type": "Feature",
  "properties": {
    "iso:country":"DE",
    "sg:address":"Wilhelmstr. 30",
    "sg:city":"Welzheim",
    "sg:phone":"+49 7182/935842",
    "sg:postcode":"73642",
    "sg:province":"Baden-W\u00fcrttemberg",
    "wof:name":"Gastst\u00e4ttenbetrieb Gmbh",
    "wof:placetype":"venue"
},
  "geometry": {"coordinates":[9.6345949173,48.8765296936],"type":"Point"}
}