{
  "type": "Feature",
  "properties": {
    "iso:country":"DE",
    "sg:address":"Leutstettener Str. 23",
    "sg:city":"M\u00fcnchen",
    "sg:postcode":"81477",
    "sg:province":"Bayern",
    "wof:name":"Futureware Gmbh",
    "wof:placetype":"venue"
},
  "geometry": {"coordinates":[11.5186100006,48.0931968689],"type":"Point"}
}