{
  "type": "Feature",
  "properties": {
    "iso:country":"DE",
    "sg:address":"Lauchhammer Str. 21",
    "sg:city":"Riesa",
    "sg:phone":"+49 3525/735463",
    "sg:postcode":"01591",
    "sg:province":"Sachsen",
    "wof:name":"B\u00e4rbel Wabner",
    "wof:placetype":"venue"
},
  "geometry": {"coordinates":[13.281523,51.318077],"type":"Point"}
}