{
  "type": "Feature",
  "properties": {
    "iso:country":"DE",
    "sg:address":"Hallerstr. 72",
    "sg:city":"Hamburg",
    "sg:postcode":"20146",
    "sg:province":"Hamburg",
    "wof:name":"X:act Event Marketing Gmbh",
    "wof:placetype":"venue"
},
  "geometry": {"coordinates":[9.9866123199,53.5724983215],"type":"Point"}
}