{
  "type": "Feature",
  "properties": {
    "iso:country":"DE",
    "sg:address":"Opalstr. 16",
    "sg:city":"Altdorf",
    "sg:postcode":"84032",
    "sg:province":"Bayern",
    "wof:name":"Aldi Gmbh & Co. Kg",
    "wof:placetype":"venue"
},
  "geometry": {"coordinates":[12.0966730118,48.5457458496],"type":"Point"}
}