{
  "type": "Feature",
  "properties": {
    "iso:country":"DE",
    "sg:address":"Biesnitzer Fu\u00dfweg 870",
    "sg:city":"G\u00f6rlitz",
    "sg:phone":"+49 3581/48030",
    "sg:postcode":"02826",
    "sg:province":"Sachsen",
    "wof:name":"Wohnungsgenossenschaft G\u00f6rlitz Eg",
    "wof:placetype":"venue"
},
  "geometry": {"coordinates":[14.9595146179,51.1448135376],"type":"Point"}
}