{
  "type": "Feature",
  "properties": {
    "iso:country":"DE",
    "sg:address":"Am Kavalleriesand 6",
    "sg:city":"Darmstadt",
    "sg:phone":"+49 4961/513030",
    "sg:postcode":"64295",
    "sg:province":"Hessen",
    "wof:name":"Maritim Rhein-main",
    "wof:placetype":"venue"
},
  "geometry": {"coordinates":[8.629565,49.868423],"type":"Point"}
}