{
  "type": "Feature",
  "properties": {
    "iso:country":"DE",
    "sg:address":"Lintorfer Str. 23",
    "sg:city":"Bad Essen",
    "sg:phone":"+49 5472/7193",
    "sg:postcode":"49152",
    "sg:province":"Niedersachsen",
    "wof:name":"Reinhard Spieker",
    "wof:placetype":"venue"
},
  "geometry": {"coordinates":[8.428838,52.307529],"type":"Point"}
}