{
  "type": "Feature",
  "properties": {
    "iso:country":"DE",
    "sg:address":"Ohligser Weg 13",
    "sg:city":"Hilden",
    "sg:phone":"+49 2103/62421",
    "sg:postcode":"40723",
    "sg:province":"Nordrhein-Westfalen",
    "wof:name":"Hacienda-diskothek",
    "wof:placetype":"venue"
},
  "geometry": {"coordinates":[6.948462,51.158497],"type":"Point"}
}