{
  "type": "Feature",
  "properties": {
    "iso:country":"DE",
    "sg:address":"L\u00fcneburger Str. 118",
    "sg:city":"Uelzen",
    "sg:phone":"+49 581/89248",
    "sg:postcode":"29525",
    "sg:province":"Niedersachsen",
    "wof:name":"Uhlen Mittagstisch Service Gmbh",
    "wof:placetype":"venue"
},
  "geometry": {"coordinates":[10.5601654053,52.9709434509],"type":"Point"}
}