{
  "type": "Feature",
  "properties": {
    "iso:country":"DE",
    "sg:address":"Frankfurter Landstr. 2-4",
    "sg:city":"Oberursel",
    "sg:postcode":"61440",
    "sg:province":"Hessen",
    "wof:name":"Osb-oberurseler Spezialbaustoffe Gmbh",
    "wof:placetype":"venue"
},
  "geometry": {"coordinates":[8.586694,50.19796],"type":"Point"}
}