{
  "type": "Feature",
  "properties": {
    "iso:country":"DE",
    "sg:address":"Antonstr. 1",
    "sg:city":"Ostritz",
    "sg:phone":"+49 35823/86561",
    "sg:postcode":"02899",
    "sg:province":"Sachsen",
    "wof:name":"St. Antonstift Alten- Und Pflegeheim",
    "wof:placetype":"venue"
},
  "geometry": {"coordinates":[14.93373,51.01284],"type":"Point"}
}