{
  "type": "Feature",
  "properties": {
    "iso:country":"DE",
    "sg:address":"Dr.-K\u00f6ring-Str. 9",
    "sg:city":"Delbr\u00fcck",
    "sg:phone":"+49 5255/931888",
    "sg:postcode":"33129",
    "sg:province":"Nordrhein-Westfalen",
    "wof:name":"Mobile Grundst\u00fccks- Verwaltungs Gmbh",
    "wof:placetype":"venue"
},
  "geometry": {"coordinates":[8.5517072678,51.764793396],"type":"Point"}
}