{
  "type": "Feature",
  "properties": {
    "iso:country":"DE",
    "sg:address":"Friedrich-Ebert-Str. 11",
    "sg:city":"Schopfloch",
    "sg:phone":"+49 9857/9547",
    "sg:postcode":"91626",
    "sg:province":"Bayern",
    "wof:name":"T. Hinterkopf",
    "wof:placetype":"venue"
},
  "geometry": {"coordinates":[10.3045835495,49.1224555969],"type":"Point"}
}