{
  "type": "Feature",
  "properties": {
    "iso:country":"DE",
    "sg:address":"Frankenwaldstr 14",
    "sg:city":"Himmelkron",
    "sg:phone":"+49 9227/94540",
    "sg:postcode":"95502",
    "sg:province":"Bayern",
    "wof:name":"Lw Systemtechnik Gmbh",
    "wof:placetype":"venue"
},
  "geometry": {"coordinates":[11.597317,50.067989],"type":"Point"}
}