{
  "type": "Feature",
  "properties": {
    "iso:country":"DE",
    "sg:address":"Frankfurter Str. 59",
    "sg:city":"Troisdorf",
    "sg:phone":"+49 2241/76308",
    "sg:postcode":"53840",
    "sg:province":"Nordrhein-Westfalen",
    "wof:name":"E. Knips",
    "wof:placetype":"venue"
},
  "geometry": {"coordinates":[7.170864,50.81406],"type":"Point"}
}