{
  "type": "Feature",
  "properties": {
    "iso:country":"DE",
    "sg:address":"Luisenstr. 69",
    "sg:city":"Uelzen",
    "sg:phone":"+49 581/90950",
    "sg:postcode":"29525",
    "sg:province":"Niedersachsen",
    "wof:name":"Wulf Burfeind Steuerberater",
    "wof:placetype":"venue"
},
  "geometry": {"coordinates":[10.5513687134,52.960773468],"type":"Point"}
}