{
  "type": "Feature",
  "properties": {
    "iso:country":"DE",
    "sg:address":"Rudolf-Diesel-Str. 41-45",
    "sg:city":"Oerlinghausen",
    "sg:phone":"+49 4952/0271621",
    "sg:postcode":"33813",
    "sg:province":"Nordrhein-Westfalen",
    "wof:name":"Sylbo-r\u00d6cke Reinhold Bohnensteffen Gmbh",
    "wof:placetype":"venue"
},
  "geometry": {"coordinates":[8.651265,51.941936],"type":"Point"}
}