{
  "type": "Feature",
  "properties": {
    "iso:country":"DE",
    "sg:address":"Gehlsdorfer Weg 1 b",
    "sg:city":"Ziesar",
    "sg:phone":"+49 33830/391",
    "sg:postcode":"14793",
    "sg:province":"Brandenburg",
    "wof:name":"T. Wolter",
    "wof:placetype":"venue"
},
  "geometry": {"coordinates":[12.275861,52.264526],"type":"Point"}
}