{
  "type": "Feature",
  "properties": {
    "iso:country":"DE",
    "sg:address":"Hamburger Str. 35",
    "sg:city":"Heide",
    "sg:phone":"+49 481/2713",
    "sg:postcode":"25746",
    "sg:province":"Schleswig-Holstein",
    "wof:name":"Arno Und Alfr. Kr\u00fcger",
    "wof:placetype":"venue"
},
  "geometry": {"coordinates":[9.104116,54.196388],"type":"Point"}
}