{
  "type": "Feature",
  "properties": {
    "iso:country":"DE",
    "sg:address":"Finkenweg 7",
    "sg:city":"Landshut",
    "sg:phone":"+49 871/45224",
    "sg:postcode":"84036",
    "sg:province":"Bayern",
    "wof:name":"Albert Schnitzer Ingenieur",
    "wof:placetype":"venue"
},
  "geometry": {"coordinates":[12.1346054077,48.5243186951],"type":"Point"}
}