{
  "type": "Feature",
  "properties": {
    "iso:country":"DE",
    "sg:address":"Alpenstr. 28",
    "sg:city":"Iffeldorf",
    "sg:phone":"+49 8856/2869",
    "sg:postcode":"82393",
    "sg:province":"Bayern",
    "wof:name":"Ferdinand Thomas Holz-und Massibau Gmbh",
    "wof:placetype":"venue"
},
  "geometry": {"coordinates":[11.330107,47.776318],"type":"Point"}
}