{
  "type": "Feature",
  "properties": {
    "iso:country":"DE",
    "sg:address":"Nordring 1",
    "sg:city":"Rodenbach",
    "sg:phone":"+49 6184/51958",
    "sg:postcode":"63517",
    "sg:province":"Hessen",
    "wof:name":"G\u00fcnter K\u00f6hler Patentanwalt",
    "wof:placetype":"venue"
},
  "geometry": {"coordinates":[9.0270290375,50.1384239197],"type":"Point"}
}