{
  "type": "Feature",
  "properties": {
    "iso:country":"DE",
    "sg:address":"Briloner Str. 43",
    "sg:city":"Willingen",
    "sg:phone":"+49 5632/69166",
    "sg:postcode":"34508",
    "sg:province":"Hessen",
    "wof:name":"Pension Herbert Kramer",
    "wof:placetype":"venue"
},
  "geometry": {"coordinates":[8.6061706543,51.2943725586],"type":"Point"}
}