{
  "type": "Feature",
  "properties": {
    "iso:country":"DE",
    "sg:address":"Kleine Bergstr. 6",
    "sg:city":"Ludwigslust",
    "sg:phone":"+49 3874/22105",
    "sg:postcode":"19288",
    "sg:province":"Mecklenburg-Vorpommern",
    "wof:name":"Michael K\u00f6hn",
    "wof:placetype":"venue"
},
  "geometry": {"coordinates":[11.4995450974,53.3292198181],"type":"Point"}
}