{
  "type": "Feature",
  "properties": {
    "iso:country":"DE",
    "sg:address":"Rudolf-Diesel-Str. 9a",
    "sg:city":"Heinsberg",
    "sg:phone":"+49 2452/22027",
    "sg:postcode":"52525",
    "sg:province":"Nordrhein-Westfalen",
    "wof:name":"Hydro-fact Gmbh",
    "wof:placetype":"venue"
},
  "geometry": {"coordinates":[6.106419,51.065411],"type":"Point"}
}