{
  "type": "Feature",
  "properties": {
    "iso:country":"DE",
    "sg:address":"Fiesteler Str. 46",
    "sg:city":"L\u00fcbbecke",
    "sg:phone":"+49 5743/8138",
    "sg:postcode":"32312",
    "sg:province":"Nordrhein-Westfalen",
    "wof:name":"Heinrich S\u00fcdmeier",
    "wof:placetype":"venue"
},
  "geometry": {"coordinates":[8.558373,52.334541],"type":"Point"}
}