{
  "type": "Feature",
  "properties": {
    "iso:country":"DE",
    "sg:address":"Kuhweg 80",
    "sg:city":"Schermbeck",
    "sg:phone":"+49 2362/3828",
    "sg:postcode":"46514",
    "sg:province":"Nordrhein-Westfalen",
    "wof:name":"Hgb-stahlbau Gmbh",
    "wof:placetype":"venue"
},
  "geometry": {"coordinates":[6.888519,51.643345],"type":"Point"}
}