{
  "type": "Feature",
  "properties": {
    "iso:country":"DE",
    "sg:address":"Goethestr. 5",
    "sg:city":"Lichtenfels",
    "sg:phone":"+49 9571/4158",
    "sg:postcode":"96215",
    "sg:province":"Bayern",
    "wof:name":"Norbert Rauch Garten- Und Landschafts-",
    "wof:placetype":"venue"
},
  "geometry": {"coordinates":[11.072618,50.147568],"type":"Point"}
}