{
  "type": "Feature",
  "properties": {
    "iso:country":"DE",
    "sg:address":"Hohenzollernring 52",
    "sg:city":"K\u00f6ln",
    "sg:phone":"+49 221/208950",
    "sg:postcode":"50672",
    "sg:province":"Nordrhein-Westfalen",
    "wof:name":"Volkswohl Bund Lebensversicherung A. G.",
    "wof:placetype":"venue"
},
  "geometry": {"coordinates":[6.939909935,50.9395294189],"type":"Point"}
}