{
  "type": "Feature",
  "properties": {
    "iso:country":"DE",
    "sg:address":"Westfalenstr. 33",
    "sg:city":"Langenberg",
    "sg:phone":"+49 5248/7640",
    "sg:postcode":"33449",
    "sg:province":"Nordrhein-Westfalen",
    "wof:name":"Johannes Austermann",
    "wof:placetype":"venue"
},
  "geometry": {"coordinates":[8.305298,51.788521],"type":"Point"}
}