{
  "type": "Feature",
  "properties": {
    "iso:country":"DE",
    "sg:address":"Weyerer Str. 5",
    "sg:city":"Brechen",
    "sg:phone":"+49 6483/911805",
    "sg:postcode":"65611",
    "sg:province":"Hessen",
    "wof:name":"Apostel Xii",
    "wof:placetype":"venue"
},
  "geometry": {"coordinates":[8.1949272156,50.3537979126],"type":"Point"}
}