{
  "type": "Feature",
  "properties": {
    "iso:country":"DE",
    "sg:address":"Hans-B\u00f6ckler-Str. 5",
    "sg:city":"Grevenbroich",
    "sg:phone":"+49 2181/3183",
    "sg:postcode":"41515",
    "sg:province":"Nordrhein-Westfalen",
    "wof:name":"Karljosef Kaufmann Architekt",
    "wof:placetype":"venue"
},
  "geometry": {"coordinates":[6.60264,51.0793],"type":"Point"}
}