{
  "type": "Feature",
  "properties": {
    "iso:country":"DE",
    "sg:address":"Zum Tal 1",
    "sg:city":"St. Wendel",
    "sg:phone":"+49 6858/8296",
    "sg:postcode":"66606",
    "sg:province":"Saarland",
    "wof:name":"Hepa Gesch\u00e4ftsf\u00fchrungs-gmbh",
    "wof:placetype":"venue"
},
  "geometry": {"coordinates":[7.2346229553,49.4335823059],"type":"Point"}
}