{
  "type": "Feature",
  "properties": {
    "iso:country":"DE",
    "sg:address":"Bodenstedtstr. 58",
    "sg:city":"M\u00fcnchen",
    "sg:phone":"+49 89/888463",
    "sg:postcode":"81241",
    "sg:province":"Bayern",
    "wof:name":"Sentimentl Ohg",
    "wof:placetype":"venue"
},
  "geometry": {"coordinates":[11.4611005783,48.1452445984],"type":"Point"}
}