{
  "type": "Feature",
  "properties": {
    "iso:country":"DE",
    "sg:address":"Wiesestr. 144",
    "sg:city":"Gera",
    "sg:postcode":"07548",
    "sg:province":"Th\u00fcringen",
    "wof:name":"H. Meierhof",
    "wof:placetype":"venue"
},
  "geometry": {"coordinates":[12.072627,50.859135],"type":"Point"}
}