{
  "type": "Feature",
  "properties": {
    "iso:country":"DE",
    "sg:address":"R\u00f6merstr. 3",
    "sg:city":"Hanau",
    "sg:phone":"+49 6181/28407",
    "sg:postcode":"63450",
    "sg:province":"Hessen",
    "wof:name":"Sporthaus Anro",
    "wof:placetype":"venue"
},
  "geometry": {"coordinates":[8.915522,50.132259],"type":"Point"}
}