{
  "type": "Feature",
  "properties": {
    "iso:country":"DE",
    "sg:address":"Alt-Astheim 22",
    "sg:city":"Trebur",
    "sg:phone":"+49 6147/93275",
    "sg:postcode":"65468",
    "sg:province":"Hessen",
    "wof:name":"Michael Tho\u00df",
    "wof:placetype":"venue"
},
  "geometry": {"coordinates":[8.3822088242,49.9335327148],"type":"Point"}
}