{
  "type": "Feature",
  "properties": {
    "iso:country":"DE",
    "sg:address":"Frickenw\u00e4sele 12",
    "sg:city":"Immenstaad",
    "sg:phone":"+49 7545/6291",
    "sg:postcode":"88090",
    "sg:province":"Baden-W\u00fcrttemberg",
    "wof:name":"Rainer H\u00f6hn",
    "wof:placetype":"venue"
},
  "geometry": {"coordinates":[9.3640365601,47.6662864685],"type":"Point"}
}