{
  "type": "Feature",
  "properties": {
    "iso:country":"DE",
    "sg:address":"Deckmannsgasse 6",
    "sg:city":"Nidda",
    "sg:phone":"+49 6043/1385",
    "sg:postcode":"63667",
    "sg:province":"Hessen",
    "wof:name":"Otfried Nies",
    "wof:placetype":"venue"
},
  "geometry": {"coordinates":[9.064241,50.406277],"type":"Point"}
}