{
  "type": "Feature",
  "properties": {
    "iso:country":"DE",
    "sg:address":"Klosterstr. 9",
    "sg:city":"Offenburg",
    "sg:phone":"+49 781/24390",
    "sg:postcode":"77652",
    "sg:province":"Baden-W\u00fcrttemberg",
    "wof:name":"Hotel Drei K\u00f6nige",
    "wof:placetype":"venue"
},
  "geometry": {"coordinates":[7.9439082146,48.4698257446],"type":"Point"}
}