{
  "type": "Feature",
  "properties": {
    "iso:country":"DE",
    "sg:address":"Brunnenstr. 11",
    "sg:city":"Limburg",
    "sg:phone":"+49 4964/3197860",
    "sg:postcode":"65551",
    "sg:province":"Hessen",
    "wof:name":"Kloft Retarder Gmbh",
    "wof:placetype":"venue"
},
  "geometry": {"coordinates":[8.1235132217,50.3681144714],"type":"Point"}
}