{
  "type": "Feature",
  "properties": {
    "iso:country":"DE",
    "sg:address":"Am Lohweiher",
    "sg:city":"Auerbach",
    "sg:phone":"+49 9643/500",
    "sg:postcode":"91275",
    "sg:province":"Bayern",
    "wof:name":"Freibad",
    "wof:placetype":"venue"
},
  "geometry": {"coordinates":[11.616060257,49.6833114624],"type":"Point"}
}