{
  "type": "Feature",
  "properties": {
    "iso:country":"DE",
    "sg:address":"Lange Str. 98",
    "sg:city":"Lage",
    "sg:phone":"+49 5232/66344",
    "sg:postcode":"32791",
    "sg:province":"Nordrhein-Westfalen",
    "wof:name":"Udo Fellmer",
    "wof:placetype":"venue"
},
  "geometry": {"coordinates":[8.795196,51.989586],"type":"Point"}
}