{
  "type": "Feature",
  "properties": {
    "iso:country":"DE",
    "sg:address":"Hohenzollernstr. 3-7",
    "sg:city":"Hagen",
    "sg:phone":"+49 2331/2080",
    "sg:postcode":"58095",
    "sg:province":"Nordrhein-Westfalen",
    "wof:name":"Hagener Versorgungs- Und Verkehrsgesellschaft Mbh",
    "wof:placetype":"venue"
},
  "geometry": {"coordinates":[7.4724588394,51.3584747314],"type":"Point"}
}