{
  "type": "Feature",
  "properties": {
    "iso:country":"DE",
    "sg:address":"Immenst\u00e4dter Str. 11",
    "sg:city":"Sonthofen",
    "sg:phone":"+49 8321/22901",
    "sg:postcode":"87527",
    "sg:province":"Bayern",
    "wof:name":"Allg\u00e4urestaurant Im Hager",
    "wof:placetype":"venue"
},
  "geometry": {"coordinates":[10.2750549316,47.5108337402],"type":"Point"}
}