{
  "type": "Feature",
  "properties": {
    "iso:country":"DE",
    "sg:address":"Krumme Str. 39",
    "sg:city":"Stadthagen",
    "sg:phone":"+49 5721/77761",
    "sg:postcode":"31655",
    "sg:province":"Niedersachsen",
    "wof:name":"Hildegard Dahms",
    "wof:placetype":"venue"
},
  "geometry": {"coordinates":[9.2041168213,52.3261642456],"type":"Point"}
}