{
  "type": "Feature",
  "properties": {
    "iso:country":"DE",
    "sg:address":"Flurstr. 23",
    "sg:city":"Lonnerstadt",
    "sg:phone":"+49 9193/3336",
    "sg:postcode":"91475",
    "sg:province":"Bayern",
    "wof:name":"Helmut Roppelt",
    "wof:placetype":"venue"
},
  "geometry": {"coordinates":[10.7707777023,49.6996803284],"type":"Point"}
}