{
  "type": "Feature",
  "properties": {
    "iso:country":"DE",
    "sg:address":"Jahnstr. 10",
    "sg:city":"Sinntal",
    "sg:phone":"+49 9741/3919",
    "sg:postcode":"36391",
    "sg:province":"Hessen",
    "wof:name":"G\u00e4stehaus Hildegard Rudolph",
    "wof:placetype":"venue"
},
  "geometry": {"coordinates":[9.7299699783,50.3143882751],"type":"Point"}
}