{
  "type": "Feature",
  "properties": {
    "iso:country":"DE",
    "sg:address":"Albachtener Str. 101 c",
    "sg:city":"M\u00fcnster",
    "sg:phone":"+49 2536/1559",
    "sg:postcode":"48163",
    "sg:province":"Nordrhein-Westfalen",
    "wof:name":"R. Und W. Schirok-design",
    "wof:placetype":"venue"
},
  "geometry": {"coordinates":[7.5272011757,51.9258232117],"type":"Point"}
}