{
  "type": "Feature",
  "properties": {
    "iso:country":"DE",
    "sg:address":"Relaisstr. 46",
    "sg:city":"Mannheim",
    "sg:phone":"+49 621/895862",
    "sg:postcode":"68219",
    "sg:province":"Baden-W\u00fcrttemberg",
    "wof:name":"Schmid-ziskovsky",
    "wof:placetype":"venue"
},
  "geometry": {"coordinates":[8.53425,49.424999],"type":"Point"}
}