{
  "type": "Feature",
  "properties": {
    "iso:country":"DE",
    "sg:address":"Botzstr. 1",
    "sg:city":"Jena",
    "sg:postcode":"07743",
    "sg:province":"Th\u00fcringen",
    "wof:name":"Friendly Sensors Ag",
    "wof:placetype":"venue"
},
  "geometry": {"coordinates":[11.575667,50.932205],"type":"Point"}
}