{
  "type": "Feature",
  "properties": {
    "iso:country":"DE",
    "sg:address":"Im L\u00f6wental 43",
    "sg:city":"Essen",
    "sg:phone":"+49 201/494739",
    "sg:postcode":"45239",
    "sg:province":"Nordrhein-Westfalen",
    "wof:name":"Gastst\u00e4tte Dicker Engel Gmbh",
    "wof:placetype":"venue"
},
  "geometry": {"coordinates":[6.9965491295,51.3839530945],"type":"Point"}
}