{
  "type": "Feature",
  "properties": {
    "iso:country":"DE",
    "sg:address":"Petersburger Platz 3",
    "sg:city":"Berlin",
    "sg:phone":"+49 30/42256112",
    "sg:postcode":"10249",
    "sg:province":"Berlin",
    "wof:name":"Petersburger-apotheke Inh. Dr. Birgit Dietzsch E. K.",
    "wof:placetype":"venue"
},
  "geometry": {"coordinates":[13.449705,52.521439],"type":"Point"}
}