{
  "type": "Feature",
  "properties": {
    "iso:country":"DE",
    "sg:address":"Neudorf",
    "sg:city":"Schauenstein",
    "sg:phone":"+49 9252/8381",
    "sg:postcode":"95197",
    "sg:province":"Bayern",
    "wof:name":"G. U. Angelika Heinrich",
    "wof:placetype":"venue"
},
  "geometry": {"coordinates":[11.7538146973,50.2848014832],"type":"Point"}
}