{
  "type": "Feature",
  "properties": {
    "iso:country":"DE",
    "sg:address":"Vo\u00dfh\u00f6veler Str. 24",
    "sg:city":"Wesel",
    "sg:phone":"+49 281/52161",
    "sg:postcode":"46485",
    "sg:province":"Nordrhein-Westfalen",
    "wof:name":"W. Lohmeier",
    "wof:placetype":"venue"
},
  "geometry": {"coordinates":[6.667268,51.67268],"type":"Point"}
}