{
  "type": "Feature",
  "properties": {
    "iso:country":"DE",
    "sg:address":"Bahnhofstr. 21",
    "sg:city":"Greu\u00dfen",
    "sg:phone":"+49 3636/701084",
    "sg:postcode":"99718",
    "sg:province":"Th\u00fcringen",
    "wof:name":"Bistro Kranert",
    "wof:placetype":"venue"
},
  "geometry": {"coordinates":[10.9441041946,51.229019165],"type":"Point"}
}