{
  "type": "Feature",
  "properties": {
    "iso:country":"DE",
    "sg:address":"Kurze Gasse 2",
    "sg:city":"Heilbronn",
    "sg:phone":"+49 7131/575534",
    "sg:postcode":"74081",
    "sg:province":"Baden-W\u00fcrttemberg",
    "wof:name":"Hans Krumm",
    "wof:placetype":"venue"
},
  "geometry": {"coordinates":[9.1674957275,49.1168708801],"type":"Point"}
}