{
  "type": "Feature",
  "properties": {
    "iso:country":"DE",
    "sg:address":"L\u00fcbecker Landstr. 20",
    "sg:city":"Eutin",
    "sg:phone":"+49 4521/73831",
    "sg:postcode":"23701",
    "sg:province":"Schleswig-Holstein",
    "wof:name":"Nordias Drugstore",
    "wof:placetype":"venue"
},
  "geometry": {"coordinates":[10.626159668,54.1280708313],"type":"Point"}
}