{
  "type": "Feature",
  "properties": {
    "iso:country":"DE",
    "sg:address":"Maximiliansplatz 17",
    "sg:city":"M\u00fcnchen",
    "sg:phone":"+49 89/297660",
    "sg:postcode":"80333",
    "sg:province":"Bayern",
    "wof:name":"Axel Michelmann Rechtsanwalt",
    "wof:placetype":"venue"
},
  "geometry": {"coordinates":[11.5716724396,48.1416168213],"type":"Point"}
}