{
  "type": "Feature",
  "properties": {
    "iso:country":"DE",
    "sg:address":"Ellerburger Str. 48",
    "sg:city":"Porta Westfalica",
    "sg:phone":"+49 571/7989560",
    "sg:postcode":"32457",
    "sg:province":"Nordrhein-Westfalen",
    "wof:name":"Hermann Ortgiese",
    "wof:placetype":"venue"
},
  "geometry": {"coordinates":[8.9027004242,52.2233123779],"type":"Point"}
}