{
  "type": "Feature",
  "properties": {
    "iso:country":"DE",
    "sg:address":"Kirchstr. 2",
    "sg:city":"Bretten",
    "sg:phone":"+49 7252/7956",
    "sg:postcode":"75015",
    "sg:province":"Baden-W\u00fcrttemberg",
    "wof:name":"Kath. Pfarramt H. Kreuz",
    "wof:placetype":"venue"
},
  "geometry": {"coordinates":[8.7103490829,49.0724868774],"type":"Point"}
}