{
  "type": "Feature",
  "properties": {
    "iso:country":"DE",
    "sg:address":"Luiter Weg 6",
    "sg:city":"Krefeld",
    "sg:phone":"+49 2151/96510",
    "sg:postcode":"47802",
    "sg:province":"Nordrhein-Westfalen",
    "wof:name":"Rheinische Landesschule F\u00fcr K\u00f6rperbehinderte",
    "wof:placetype":"venue"
},
  "geometry": {"coordinates":[6.5740427971,51.3705368042],"type":"Point"}
}