{
  "type": "Feature",
  "properties": {
    "iso:country":"DE",
    "sg:address":"Rahmer Str. 10",
    "sg:city":"Dortmund",
    "sg:phone":"+49 231/310714",
    "sg:postcode":"44369",
    "sg:province":"Nordrhein-Westfalen",
    "wof:name":"Cafe W. Schilling",
    "wof:placetype":"venue"
},
  "geometry": {"coordinates":[7.4146900177,51.5309257507],"type":"Point"}
}