{
  "type": "Feature",
  "properties": {
    "iso:country":"DE",
    "sg:address":"Woogstr. 36",
    "sg:city":"Neuhofen",
    "sg:phone":"+49 6236/55396",
    "sg:postcode":"67141",
    "sg:province":"Rheinland-Pfalz",
    "wof:name":"Norbert Listl Rechtsanwalt",
    "wof:placetype":"venue"
},
  "geometry": {"coordinates":[8.421628952,49.4155769348],"type":"Point"}
}