{
  "type": "Feature",
  "properties": {
    "iso:country":"DE",
    "sg:address":"Brunnenstr. 13",
    "sg:city":"H\u00f6hr-Grenzhausen",
    "sg:phone":"+49 2624/3021",
    "sg:postcode":"56203",
    "sg:province":"Rheinland-Pfalz",
    "wof:name":"Merkelbach Manufaktur Gmbh",
    "wof:placetype":"venue"
},
  "geometry": {"coordinates":[7.655216217,50.4387817383],"type":"Point"}
}