{
  "type": "Feature",
  "properties": {
    "iso:country":"DE",
    "sg:address":"Am Taubenfeld 33",
    "sg:city":"Heidelberg",
    "sg:phone":"+49 6221/83580",
    "sg:postcode":"69123",
    "sg:province":"Baden-W\u00fcrttemberg",
    "wof:name":"Baumaschinendienst Betriebs Gmbh & Co. Kg",
    "wof:placetype":"venue"
},
  "geometry": {"coordinates":[8.637648,49.428913],"type":"Point"}
}