{
  "type": "Feature",
  "properties": {
    "iso:country":"DE",
    "sg:address":"Ilmenauer Str. 9",
    "sg:city":"Elgersburg",
    "sg:phone":"+49 3677/792212",
    "sg:postcode":"98716",
    "sg:province":"Th\u00fcringen",
    "wof:name":"Gerhard Walther",
    "wof:placetype":"venue"
},
  "geometry": {"coordinates":[10.856117,50.704506],"type":"Point"}
}