{
  "type": "Feature",
  "properties": {
    "iso:country":"DE",
    "sg:address":"Merveldtstr. 83",
    "sg:city":"Recklinghausen",
    "sg:phone":"+49 2361/63776",
    "sg:postcode":"45663",
    "sg:province":"Nordrhein-Westfalen",
    "wof:name":"Heinrich Sattler",
    "wof:placetype":"venue"
},
  "geometry": {"coordinates":[7.2445211411,51.5762557983],"type":"Point"}
}