{
  "type": "Feature",
  "properties": {
    "iso:country":"DE",
    "sg:address":"Kapfstr. 9",
    "sg:city":"Tuttlingen",
    "sg:phone":"+49 7461/5854",
    "sg:postcode":"78532",
    "sg:province":"Baden-W\u00fcrttemberg",
    "wof:name":"Anton Betzler Gmbh",
    "wof:placetype":"venue"
},
  "geometry": {"coordinates":[8.852496,48.008831],"type":"Point"}
}