{
  "type": "Feature",
  "properties": {
    "iso:country":"DE",
    "sg:address":"Neuer Weg 8",
    "sg:city":"Herscheid",
    "sg:phone":"+49 2357/170026",
    "sg:postcode":"58849",
    "sg:province":"Nordrhein-Westfalen",
    "wof:name":"Modellbau Klaus Herfel Gmbh",
    "wof:placetype":"venue"
},
  "geometry": {"coordinates":[7.744838,51.177544],"type":"Point"}
}