{
  "type": "Feature",
  "properties": {
    "iso:country":"DE",
    "sg:address":"Johannstr. 17",
    "sg:city":"Leer",
    "sg:phone":"+49 491/12378",
    "sg:postcode":"26789",
    "sg:province":"Niedersachsen",
    "wof:name":"K\u00e4the Und Lothar Dahlheimer",
    "wof:placetype":"venue"
},
  "geometry": {"coordinates":[7.469964,53.230927],"type":"Point"}
}