{
  "type": "Feature",
  "properties": {
    "iso:country":"DE",
    "sg:address":"K\u00fcchelstr. 3",
    "sg:city":"M\u00fcnchen",
    "sg:phone":"+49 89/7145856",
    "sg:postcode":"81375",
    "sg:province":"Bayern",
    "wof:name":"Ingeborg Friedrich Steuerberater",
    "wof:placetype":"venue"
},
  "geometry": {"coordinates":[11.4978599548,48.1180419922],"type":"Point"}
}