{
  "type": "Feature",
  "properties": {
    "iso:country":"DE",
    "sg:address":"Krusenbusch 7",
    "sg:city":"D\u00f6tlingen",
    "sg:phone":"+49 4432/339",
    "sg:postcode":"27801",
    "sg:province":"Niedersachsen",
    "wof:name":"Heinrich Schulenberg",
    "wof:placetype":"venue"
},
  "geometry": {"coordinates":[8.410862,52.957535],"type":"Point"}
}