{
  "type": "Feature",
  "properties": {
    "iso:country":"DE",
    "sg:address":"Robert-Franck-Str. 36",
    "sg:city":"Murrhardt",
    "sg:phone":"+49 7192/6540",
    "sg:postcode":"71540",
    "sg:province":"Baden-W\u00fcrttemberg",
    "wof:name":"Manfred Taxis Steuerberater Und",
    "wof:placetype":"venue"
},
  "geometry": {"coordinates":[9.580283165,48.9857292175],"type":"Point"}
}