{
  "type": "Feature",
  "properties": {
    "iso:country":"DE",
    "sg:address":"Hauptstr. 128",
    "sg:city":"Wiesmoor",
    "sg:phone":"+49 4944/7780",
    "sg:postcode":"26639",
    "sg:province":"Niedersachsen",
    "wof:name":"E. L. Spielhallen Gmbh",
    "wof:placetype":"venue"
},
  "geometry": {"coordinates":[7.7398271561,53.4175071716],"type":"Point"}
}