{
  "type": "Feature",
  "properties": {
    "iso:country":"DE",
    "sg:address":"Lange Stra\u00dfe 15a",
    "sg:city":"Wanfried",
    "sg:phone":"+49 5651",
    "sg:postcode":"37281",
    "sg:province":"Hessen",
    "wof:name":"Werbeagentur Rechl",
    "wof:placetype":"venue"
},
  "geometry": {"coordinates":[10.122908,51.178333],"type":"Point"}
}