{
  "type": "Feature",
  "properties": {
    "iso:country":"DE",
    "sg:address":"Fasanenweg 1",
    "sg:city":"Behrensdorf",
    "sg:phone":"+49 4381/5206",
    "sg:postcode":"24321",
    "sg:province":"Schleswig-Holstein",
    "wof:name":"Burghard M\u00fcller Verleihbetrieb",
    "wof:placetype":"venue"
},
  "geometry": {"coordinates":[10.605629921,54.3496246338],"type":"Point"}
}