{
  "type": "Feature",
  "properties": {
    "iso:country":"DE",
    "sg:address":"Am Walkweiher 1",
    "sg:city":"Waal",
    "sg:postcode":"86875",
    "sg:province":"Bayern",
    "wof:name":"Elogic Gmbh",
    "wof:placetype":"venue"
},
  "geometry": {"coordinates":[10.78145504,47.9977264404],"type":"Point"}
}