{
  "type": "Feature",
  "properties": {
    "iso:country":"DE",
    "sg:address":"Schwarzer Weg 7a",
    "sg:city":"Adendorf",
    "sg:phone":"+49 4131/188761",
    "sg:postcode":"21365",
    "sg:province":"Niedersachsen",
    "wof:name":"Praxis Garbers Und Szabo",
    "wof:placetype":"venue"
},
  "geometry": {"coordinates":[10.4371843338,53.271686554],"type":"Point"}
}