{
  "type": "Feature",
  "properties": {
    "iso:country":"DE",
    "sg:address":"St\u00fclerstr. 6",
    "sg:city":"M\u00fchlhausen",
    "sg:phone":"+49 36014/40534",
    "sg:postcode":"99974",
    "sg:province":"Th\u00fcringen",
    "wof:name":"K.-heinz Bachmann",
    "wof:placetype":"venue"
},
  "geometry": {"coordinates":[10.4510622025,51.2148094177],"type":"Point"}
}