{
  "type": "Feature",
  "properties": {
    "iso:country":"DE",
    "sg:address":"Im Eschert 10",
    "sg:city":"Willich",
    "sg:phone":"+49 2154/7182",
    "sg:postcode":"47877",
    "sg:province":"Nordrhein-Westfalen",
    "wof:name":"L. Loos",
    "wof:placetype":"venue"
},
  "geometry": {"coordinates":[6.507001,51.233952],"type":"Point"}
}