{
  "type": "Feature",
  "properties": {
    "iso:country":"DE",
    "sg:address":"Von-Haxthausen-Str. 5",
    "sg:city":"Barntrup",
    "sg:phone":"+49 5263/99060",
    "sg:postcode":"32683",
    "sg:province":"Nordrhein-Westfalen",
    "wof:name":"Berndt Und Berndt Rechtsanw\u00e4lte",
    "wof:placetype":"venue"
},
  "geometry": {"coordinates":[9.1200666428,51.9909133911],"type":"Point"}
}