{
  "type": "Feature",
  "properties": {
    "iso:country":"DE",
    "sg:address":"Nymphenburger Str. 151",
    "sg:city":"M\u00fcnchen",
    "sg:phone":"+49 89/163101",
    "sg:postcode":"80636",
    "sg:province":"Bayern",
    "wof:name":"Galerie Forum 1",
    "wof:placetype":"venue"
},
  "geometry": {"coordinates":[11.536079,48.151821],"type":"Point"}
}