{
  "type": "Feature",
  "properties": {
    "iso:country":"DE",
    "sg:address":"Goethestr. 2",
    "sg:city":"Trappenkamp",
    "sg:phone":"+49 4323/4420",
    "sg:postcode":"24610",
    "sg:province":"Schleswig-Holstein",
    "wof:name":"Praxis Dr. Med. Kellner Und Dr. Med. Wilkens",
    "wof:placetype":"venue"
},
  "geometry": {"coordinates":[10.2141065598,54.0369224548],"type":"Point"}
}