{
  "type": "Feature",
  "properties": {
    "iso:country":"DE",
    "sg:address":"Weihergasse 13b",
    "sg:city":"Hindelang",
    "sg:phone":"+49 8324/8374",
    "sg:postcode":"87541",
    "sg:province":"Bayern",
    "wof:name":"Anton Blanz Steuerberater",
    "wof:placetype":"venue"
},
  "geometry": {"coordinates":[10.3827590942,47.5012321472],"type":"Point"}
}