{
  "type": "Feature",
  "properties": {
    "iso:country":"DE",
    "sg:address":"Kreisstr. 55b",
    "sg:city":"Urbach",
    "sg:phone":"+49 36333/70838",
    "sg:postcode":"99765",
    "sg:province":"Th\u00fcringen",
    "wof:name":"J\u00f6rg Kupke",
    "wof:placetype":"venue"
},
  "geometry": {"coordinates":[10.900888443,51.481136322],"type":"Point"}
}