{
  "type": "Feature",
  "properties": {
    "iso:country":"DE",
    "sg:address":"Rehstr. 3",
    "sg:city":"Merzig",
    "sg:phone":"+49 6861/6640",
    "sg:postcode":"66663",
    "sg:province":"Saarland",
    "wof:name":"Maria Nilles",
    "wof:placetype":"venue"
},
  "geometry": {"coordinates":[6.6157941818,49.4417114258],"type":"Point"}
}