{
  "type": "Feature",
  "properties": {
    "iso:country":"DE",
    "sg:address":"Bahnhofstr. 19",
    "sg:city":"Langlingen",
    "sg:phone":"+49 5082/913999",
    "sg:postcode":"29364",
    "sg:province":"Niedersachsen",
    "wof:name":"U.-j. Machlitt",
    "wof:placetype":"venue"
},
  "geometry": {"coordinates":[10.2842941284,52.5527267456],"type":"Point"}
}