{
  "type": "Feature",
  "properties": {
    "iso:country":"DE",
    "sg:address":"Lindenstr. 5",
    "sg:city":"Glienicke",
    "sg:phone":"+49 33056/6270",
    "sg:postcode":"16548",
    "sg:province":"Brandenburg",
    "wof:name":"Pandion Verwaltungsges. Gmbh",
    "wof:placetype":"venue"
},
  "geometry": {"coordinates":[13.3082304001,52.6342697144],"type":"Point"}
}