{
  "type": "Feature",
  "properties": {
    "iso:country":"DE",
    "sg:address":"Hauptstr. 38",
    "sg:city":"Wuppertal",
    "sg:phone":"+49 202/476942",
    "sg:postcode":"42349",
    "sg:province":"Nordrhein-Westfalen",
    "wof:name":"Fritz Braun Steuerberater",
    "wof:placetype":"venue"
},
  "geometry": {"coordinates":[7.1330599785,51.2067108154],"type":"Point"}
}