{
  "type": "Feature",
  "properties": {
    "iso:country":"DE",
    "sg:address":"M\u00f6nchhofstr. 20",
    "sg:city":"Viernheim",
    "sg:phone":"+49 6204/8575",
    "sg:postcode":"68519",
    "sg:province":"Hessen",
    "wof:name":"Antep",
    "wof:placetype":"venue"
},
  "geometry": {"coordinates":[8.5698070526,49.5308876038],"type":"Point"}
}