{
  "type": "Feature",
  "properties": {
    "iso:country":"DE",
    "sg:address":"Gartenstr. 3",
    "sg:city":"Spremberg",
    "sg:phone":"+49 3563/4727",
    "sg:postcode":"03130",
    "sg:province":"Brandenburg",
    "wof:name":"Artur Lischke",
    "wof:placetype":"venue"
},
  "geometry": {"coordinates":[14.3723182678,51.5703620911],"type":"Point"}
}