{
  "type": "Feature",
  "properties": {
    "iso:country":"DE",
    "sg:address":"Minnastr. 16",
    "sg:city":"Kiel",
    "sg:phone":"+49 431/787708",
    "sg:postcode":"24148",
    "sg:province":"Schleswig-Holstein",
    "wof:name":"E & Je Kompressoren- Service Ohg",
    "wof:placetype":"venue"
},
  "geometry": {"coordinates":[10.166187,54.32357],"type":"Point"}
}