{
  "type": "Feature",
  "properties": {
    "iso:country":"DE",
    "sg:address":"Charlottenstr. 3",
    "sg:city":"Ebersbach",
    "sg:phone":"+49 7163/8947",
    "sg:postcode":"73061",
    "sg:province":"Baden-W\u00fcrttemberg",
    "wof:name":"Karl-heinz Schurr",
    "wof:placetype":"venue"
},
  "geometry": {"coordinates":[9.5302438736,48.7157859802],"type":"Point"}
}