{
  "type": "Feature",
  "properties": {
    "iso:country":"DE",
    "sg:address":"Gabelsbergerstr. 79A/38",
    "sg:city":"M\u00fcnchen",
    "sg:postcode":"80333",
    "sg:province":"Bayern",
    "wof:name":"Pro App Gmbh",
    "wof:placetype":"venue"
},
  "geometry": {"coordinates":[11.5613422394,48.1493453979],"type":"Point"}
}