{
  "type": "Feature",
  "properties": {
    "iso:country":"DE",
    "sg:address":"Austr. 11",
    "sg:city":"Offenbach",
    "sg:phone":"+49 69/8003588",
    "sg:postcode":"63065",
    "sg:province":"Hessen",
    "wof:name":"Erkan Acikg\u00f6z",
    "wof:placetype":"venue"
},
  "geometry": {"coordinates":[8.7722959518,50.1049461365],"type":"Point"}
}