{
  "type": "Feature",
  "properties": {
    "iso:country":"DE",
    "sg:address":"Hanauer Str. 41",
    "sg:city":"Friedberg",
    "sg:phone":"+49 6031/18505",
    "sg:postcode":"61169",
    "sg:province":"Hessen",
    "wof:name":"Troja-grill",
    "wof:placetype":"venue"
},
  "geometry": {"coordinates":[8.7595529556,50.3326187134],"type":"Point"}
}