{
  "type": "Feature",
  "properties": {
    "iso:country":"DE",
    "sg:address":"Zu den Sportpl\u00e4tzen 33",
    "sg:city":"Pfungstadt",
    "sg:phone":"+49 6157/94750",
    "sg:postcode":"64319",
    "sg:province":"Hessen",
    "wof:name":"Altenpflegeheim Der Inneren Mission",
    "wof:placetype":"venue"
},
  "geometry": {"coordinates":[8.608065,49.809895],"type":"Point"}
}