{
  "type": "Feature",
  "properties": {
    "iso:country":"DE",
    "sg:address":"Langholz 2",
    "sg:city":"Neukirchen",
    "sg:phone":"+49 9961/6316",
    "sg:postcode":"94362",
    "sg:province":"Bayern",
    "wof:name":"H. Naimer",
    "wof:placetype":"venue"
},
  "geometry": {"coordinates":[12.75522,48.975094],"type":"Point"}
}