{
  "type": "Feature",
  "properties": {
    "iso:country":"DE",
    "sg:address":"Heerstr. 121-123",
    "sg:city":"Duisburg",
    "sg:phone":"+49 203/660810",
    "sg:postcode":"47053",
    "sg:province":"Nordrhein-Westfalen",
    "wof:name":"Koczy- Gmbh",
    "wof:placetype":"venue"
},
  "geometry": {"coordinates":[6.7548408508,51.4232749939],"type":"Point"}
}