{
  "type": "Feature",
  "properties": {
    "iso:country":"DE",
    "sg:address":"\u00d6lschl\u00e4gern 26",
    "sg:city":"Braunschweig",
    "sg:phone":"+49 531/44203",
    "sg:postcode":"38100",
    "sg:province":"Niedersachsen",
    "wof:name":"A. Hoffmeister Pfandhaus",
    "wof:placetype":"venue"
},
  "geometry": {"coordinates":[10.529195,52.261776],"type":"Point"}
}