{
  "type": "Feature",
  "properties": {
    "iso:country":"DE",
    "sg:address":"Wilseckerstr. 16",
    "sg:city":"Kyllburg",
    "sg:phone":"+49 6563/2666",
    "sg:postcode":"54655",
    "sg:province":"Rheinland-Pfalz",
    "wof:name":"Haus Wehrb\u00fcsch",
    "wof:placetype":"venue"
},
  "geometry": {"coordinates":[6.5934557915,50.0360565186],"type":"Point"}
}