{
  "type": "Feature",
  "properties": {
    "iso:country":"DE",
    "sg:address":"Buchenhain 2",
    "sg:city":"Hannover",
    "sg:phone":"+49 511/5940657",
    "sg:postcode":"30629",
    "sg:province":"Niedersachsen",
    "wof:name":"G\u00fcnther Gebhardt",
    "wof:placetype":"venue"
},
  "geometry": {"coordinates":[9.851098,52.396557],"type":"Point"}
}