{
  "type": "Feature",
  "properties": {
    "iso:country":"DE",
    "sg:address":"Bersenbr\u00fccker Str. 21",
    "sg:city":"Ankum",
    "sg:phone":"+49 5462/8391",
    "sg:postcode":"49577",
    "sg:province":"Niedersachsen",
    "wof:name":"Restaurant Kreta",
    "wof:placetype":"venue"
},
  "geometry": {"coordinates":[7.8811388016,52.5429534912],"type":"Point"}
}