{
  "type": "Feature",
  "properties": {
    "iso:country":"DE",
    "sg:address":"Schaufenberger Str. 74",
    "sg:city":"Alsdorf",
    "sg:phone":"+49 2404/23256",
    "sg:postcode":"52477",
    "sg:province":"Nordrhein-Westfalen",
    "wof:name":"M. L\u00f6we",
    "wof:placetype":"venue"
},
  "geometry": {"coordinates":[6.169706,50.877907],"type":"Point"}
}