{
  "type": "Feature",
  "properties": {
    "iso:country":"DE",
    "sg:address":"Karlstr. 44",
    "sg:city":"Offenbach",
    "sg:phone":"+49 69/815783",
    "sg:postcode":"63065",
    "sg:province":"Hessen",
    "wof:name":"K. Stang Gmbh Vergn\u00fcgungsst\u00e4tte",
    "wof:placetype":"venue"
},
  "geometry": {"coordinates":[8.769488,50.104004],"type":"Point"}
}