{
  "type": "Feature",
  "properties": {
    "iso:country":"DE",
    "sg:address":"Rathmecker Platz 11",
    "sg:city":"L\u00fcdenscheid",
    "sg:phone":"+49 2351/53275",
    "sg:postcode":"58513",
    "sg:province":"Nordrhein-Westfalen",
    "wof:name":"Pleuger Immobilien",
    "wof:placetype":"venue"
},
  "geometry": {"coordinates":[7.6255478859,51.256652832],"type":"Point"}
}