{
  "type": "Feature",
  "properties": {
    "iso:country":"DE",
    "sg:address":"Ostsiedlung 9",
    "sg:city":"Bad Langensalza",
    "sg:phone":"+49 3603/842360",
    "sg:postcode":"99947",
    "sg:province":"Th\u00fcringen",
    "wof:name":"Gerd Faulborn",
    "wof:placetype":"venue"
},
  "geometry": {"coordinates":[10.659797,51.103367],"type":"Point"}
}