{
  "type": "Feature",
  "properties": {
    "iso:country":"DE",
    "sg:address":"Nordstr. 116a",
    "sg:city":"Mettmann",
    "sg:phone":"+49 2104/22989",
    "sg:postcode":"40822",
    "sg:province":"Nordrhein-Westfalen",
    "wof:name":"Erich Begalke",
    "wof:placetype":"venue"
},
  "geometry": {"coordinates":[6.971113,51.260571],"type":"Point"}
}