{
  "type": "Feature",
  "properties": {
    "iso:country":"DE",
    "sg:address":"Am Rilchenberg 19",
    "sg:city":"Idar-Oberstein",
    "sg:phone":"+49 6781/27888",
    "sg:postcode":"55743",
    "sg:province":"Rheinland-Pfalz",
    "wof:name":"Kath. Pfarramt St. Barbara",
    "wof:placetype":"venue"
},
  "geometry": {"coordinates":[7.3067698479,49.711971283],"type":"Point"}
}