{
  "type": "Feature",
  "properties": {
    "iso:country":"DE",
    "sg:address":"Schnewlinstr. 11-13",
    "sg:city":"Freiburg",
    "sg:postcode":"79098",
    "sg:province":"Baden-W\u00fcrttemberg",
    "wof:name":"Zentrum F\u00fcr Europ\u00e4ische Unternehmensf\u00fchrung Gmbh",
    "wof:placetype":"venue"
},
  "geometry": {"coordinates":[7.8394021988,47.9934501648],"type":"Point"}
}