{
  "type": "Feature",
  "properties": {
    "iso:country":"DE",
    "sg:address":"M\u00fcnchner Str. 34",
    "sg:city":"Edling",
    "sg:phone":"+49 8071/7924",
    "sg:postcode":"83533",
    "sg:province":"Bayern",
    "wof:name":"Willibald Forstner Kg",
    "wof:placetype":"venue"
},
  "geometry": {"coordinates":[12.1625366211,48.0655822754],"type":"Point"}
}