{
  "type": "Feature",
  "properties": {
    "iso:country":"DE",
    "sg:address":"Graf-Spee-Str. 8a",
    "sg:city":"Oldenburg",
    "sg:postcode":"26123",
    "sg:province":"Niedersachsen",
    "wof:name":"Innotip Handels- Gesellschaft Mbh",
    "wof:placetype":"venue"
},
  "geometry": {"coordinates":[8.230795,53.153938],"type":"Point"}
}