{
  "type": "Feature",
  "properties": {
    "iso:country":"DE",
    "sg:address":"Erich-K\u00e4stner-Str. 4",
    "sg:city":"Frankfurt",
    "sg:phone":"+49 6109/32831",
    "sg:postcode":"60388",
    "sg:province":"Hessen",
    "wof:name":"Gorkotte Gmbh",
    "wof:placetype":"venue"
},
  "geometry": {"coordinates":[8.7525072098,50.1457099915],"type":"Point"}
}