{
  "type": "Feature",
  "properties": {
    "iso:country":"DE",
    "sg:address":"Gastfeldstr. 161",
    "sg:city":"Bremen",
    "sg:phone":"+49 421/530276",
    "sg:postcode":"28201",
    "sg:province":"Bremen",
    "wof:name":"Treffpunkt Neustadt",
    "wof:placetype":"venue"
},
  "geometry": {"coordinates":[8.8037395477,53.059589386],"type":"Point"}
}