{
  "type": "Feature",
  "properties": {
    "iso:country":"DE",
    "sg:address":"Schulstr. 62",
    "sg:city":"Gummersbach",
    "sg:phone":"+49 2261/76421",
    "sg:postcode":"51645",
    "sg:province":"Nordrhein-Westfalen",
    "wof:name":"St. Lang",
    "wof:placetype":"venue"
},
  "geometry": {"coordinates":[7.5404062271,50.9821662903],"type":"Point"}
}