{
  "type": "Feature",
  "properties": {
    "iso:country":"DE",
    "sg:address":"K\u00f6nigsheide",
    "sg:city":"Marienheide",
    "sg:phone":"+49 2269/326",
    "sg:postcode":"51709",
    "sg:province":"Nordrhein-Westfalen",
    "wof:name":"Bernh. Schl\u00fctter",
    "wof:placetype":"venue"
},
  "geometry": {"coordinates":[7.484728,51.096256],"type":"Point"}
}