{
  "type": "Feature",
  "properties": {
    "iso:country":"DE",
    "sg:address":"Heinrichstr. 22",
    "sg:city":"Herne",
    "sg:phone":"+49 2323/12385",
    "sg:postcode":"44623",
    "sg:province":"Nordrhein-Westfalen",
    "wof:name":"Friedrich-wilhelm Siepmann",
    "wof:placetype":"venue"
},
  "geometry": {"coordinates":[7.2254471779,51.5415840149],"type":"Point"}
}