{
  "type": "Feature",
  "properties": {
    "iso:country":"DE",
    "sg:address":"Universit\u00e4tsstr. 8",
    "sg:city":"Marburg",
    "sg:phone":"+49 6421/15244",
    "sg:postcode":"35037",
    "sg:province":"Hessen",
    "wof:name":"Mc Donalds",
    "wof:placetype":"venue"
},
  "geometry": {"coordinates":[8.7694587708,50.8069496155],"type":"Point"}
}