{
  "type": "Feature",
  "properties": {
    "iso:country":"DE",
    "sg:address":"Im Kelterfeld 15",
    "sg:city":"Rehlingen-Siersburg",
    "sg:phone":"+49 4950/4391030",
    "sg:postcode":"66780",
    "sg:province":"Saarland",
    "wof:name":"Raiffeisen-landbund E. G.",
    "wof:placetype":"venue"
},
  "geometry": {"coordinates":[9.393292,52.237621],"type":"Point"}
}