{
  "type": "Feature",
  "properties": {
    "iso:country":"DE",
    "sg:address":"Am Steinbruch 18",
    "sg:city":"Wendisch Evern",
    "sg:phone":"+49 4131/32112",
    "sg:postcode":"21403",
    "sg:province":"Niedersachsen",
    "wof:name":"Helga Stodtmeister",
    "wof:placetype":"venue"
},
  "geometry": {"coordinates":[10.4739208221,53.2176933289],"type":"Point"}
}