{
  "type": "Feature",
  "properties": {
    "iso:country":"DE",
    "sg:address":"Moosf\u00fcrth 22",
    "sg:city":"Wallersdorf",
    "sg:phone":"+49 9933/684",
    "sg:postcode":"94522",
    "sg:province":"Bayern",
    "wof:name":"A. H\u00e4glsperger",
    "wof:placetype":"venue"
},
  "geometry": {"coordinates":[12.7785253525,48.7315750122],"type":"Point"}
}