{
  "type": "Feature",
  "properties": {
    "iso:country":"DE",
    "sg:address":"An den Bleichen 49",
    "sg:city":"Stralsund",
    "sg:phone":"+49 3831/393456",
    "sg:postcode":"18435",
    "sg:province":"Mecklenburg-Vorpommern",
    "wof:name":"Gerhard Keil",
    "wof:placetype":"venue"
},
  "geometry": {"coordinates":[13.073606,54.318855],"type":"Point"}
}