{
  "type": "Feature",
  "properties": {
    "iso:country":"DE",
    "sg:address":"Eichborndamm 141-165",
    "sg:city":"Berlin",
    "sg:phone":"+49 30/4118091",
    "sg:postcode":"13403",
    "sg:province":"Berlin",
    "wof:name":"Figur & Fitness",
    "wof:placetype":"venue"
},
  "geometry": {"coordinates":[13.31802,52.580936],"type":"Point"}
}