{
  "type": "Feature",
  "properties": {
    "iso:country":"DE",
    "sg:address":"Siebenkeesstr. 36",
    "sg:city":"N\u00fcrnberg",
    "sg:phone":"+49 911/265761",
    "sg:postcode":"90459",
    "sg:province":"Bayern",
    "wof:name":"Simeoni",
    "wof:placetype":"venue"
},
  "geometry": {"coordinates":[11.078596,49.440136],"type":"Point"}
}