{
  "type": "Feature",
  "properties": {
    "iso:country":"DE",
    "sg:address":"Bahnhofstr.",
    "sg:city":"Villingen-Schwenningen",
    "sg:phone":"+49 7721/81391",
    "sg:postcode":"78048",
    "sg:province":"Baden-W\u00fcrttemberg",
    "wof:name":"Deutsche Bahn Ag",
    "wof:placetype":"venue"
},
  "geometry": {"coordinates":[8.4655103683,48.0561943054],"type":"Point"}
}