{
  "type": "Feature",
  "properties": {
    "iso:country":"DE",
    "sg:address":"An der Kippe 8",
    "sg:city":"Inden",
    "sg:phone":"+49 2465/611",
    "sg:postcode":"52459",
    "sg:province":"Nordrhein-Westfalen",
    "wof:name":"M. Schmitz",
    "wof:placetype":"venue"
},
  "geometry": {"coordinates":[6.3638691902,50.8449783325],"type":"Point"}
}