{
  "type": "Feature",
  "properties": {
    "iso:country":"DE",
    "sg:address":"\u00d6schelbronner Str. 30",
    "sg:city":"M\u00f6tzingen",
    "sg:phone":"+49 7452/77302",
    "sg:postcode":"71159",
    "sg:province":"Baden-W\u00fcrttemberg",
    "wof:name":"A. Und E. M\u00fcller",
    "wof:placetype":"venue"
},
  "geometry": {"coordinates":[8.7761859894,48.5363578796],"type":"Point"}
}