{
  "type": "Feature",
  "properties": {
    "iso:country":"DE",
    "sg:address":"Kaufbeurener Str. 30",
    "sg:city":"Mauerstetten",
    "sg:phone":"+49 8341/5170",
    "sg:postcode":"87665",
    "sg:province":"Bayern",
    "wof:name":"Irmgard Sirch",
    "wof:placetype":"venue"
},
  "geometry": {"coordinates":[10.66658,47.889709],"type":"Point"}
}