{
  "type": "Feature",
  "properties": {
    "iso:country":"DE",
    "sg:address":"Gaugrafenstr. 4-8",
    "sg:city":"Frankfurt",
    "sg:phone":"+49 69/78020",
    "sg:postcode":"60489",
    "sg:province":"Hessen",
    "wof:name":"Druckfarbenfabrik Gebr. Schmidt Gmbh",
    "wof:placetype":"venue"
},
  "geometry": {"coordinates":[8.598381,50.123272],"type":"Point"}
}