{
  "type": "Feature",
  "properties": {
    "iso:country":"DE",
    "sg:address":"Am Bahnhof 3-4",
    "sg:city":"Gol\u00dfen",
    "sg:phone":"+49 4935/4523830",
    "sg:postcode":"15938",
    "sg:province":"Brandenburg",
    "wof:name":"Emsland-st\u00c4rke Gmbh",
    "wof:placetype":"venue"
},
  "geometry": {"coordinates":[13.574664,51.974983],"type":"Point"}
}