{
  "type": "Feature",
  "properties": {
    "iso:country":"DE",
    "sg:address":"Dalldorfer Str. 5",
    "sg:city":"Meinersen",
    "sg:phone":"+49 5372/5257",
    "sg:postcode":"38536",
    "sg:province":"Niedersachsen",
    "wof:name":"August Brennecke & Sohn Inh. Helmut Brennecke",
    "wof:placetype":"venue"
},
  "geometry": {"coordinates":[10.362848,52.47451],"type":"Point"}
}