{
  "type": "Feature",
  "properties": {
    "iso:country":"DE",
    "sg:address":"Liebenwalder Str. 7",
    "sg:city":"Zehdenick",
    "sg:phone":"+49 3307/2345",
    "sg:postcode":"16792",
    "sg:province":"Brandenburg",
    "wof:name":"Karl-peter Isensee",
    "wof:placetype":"venue"
},
  "geometry": {"coordinates":[13.342672,52.984558],"type":"Point"}
}