{
  "type": "Feature",
  "properties": {
    "iso:country":"DE",
    "sg:address":"Am Baggerteich 3",
    "sg:city":"Coswig",
    "sg:phone":"+49 3523/75677",
    "sg:postcode":"01640",
    "sg:province":"Sachsen",
    "wof:name":"Gra\u00dfa Stra\u00dfen- Tief- Und Rohrleitungsbau Gmbh",
    "wof:placetype":"venue"
},
  "geometry": {"coordinates":[13.5640392303,51.1311798096],"type":"Point"}
}