{
  "type": "Feature",
  "properties": {
    "iso:country":"DE",
    "sg:address":"Stadtplatz 20",
    "sg:city":"Freyung",
    "sg:phone":"+49 8551/1493",
    "sg:postcode":"94078",
    "sg:province":"Bayern",
    "wof:name":"Heinrich Schuster",
    "wof:placetype":"venue"
},
  "geometry": {"coordinates":[13.547239,48.807316],"type":"Point"}
}