{
  "type": "Feature",
  "properties": {
    "iso:country":"DE",
    "sg:address":"Mengeder Str. 702",
    "sg:city":"Dortmund",
    "sg:phone":"+49 231/332751",
    "sg:postcode":"44359",
    "sg:province":"Nordrhein-Westfalen",
    "wof:name":"China-restaurant Hai Pin",
    "wof:placetype":"venue"
},
  "geometry": {"coordinates":[7.3962202072,51.5525894165],"type":"Point"}
}