{
  "type": "Feature",
  "properties": {
    "iso:country":"DE",
    "sg:address":"Siedlung 39",
    "sg:city":"Narsdorf",
    "sg:phone":"+49 39202/886",
    "sg:postcode":"04657",
    "sg:province":"Sachsen",
    "wof:name":"Nibra Dachkeramik Gmbh & Co Kg",
    "wof:placetype":"venue"
},
  "geometry": {"coordinates":[11.528219223,52.2304267883],"type":"Point"}
}