{
  "type": "Feature",
  "properties": {
    "iso:country":"DE",
    "sg:address":"Talstr. 77",
    "sg:city":"Stuttgart",
    "sg:phone":"+49 711/2364969",
    "sg:postcode":"70188",
    "sg:province":"Baden-W\u00fcrttemberg",
    "wof:name":"Liebherr-k\u00fcmmel Gmbh",
    "wof:placetype":"venue"
},
  "geometry": {"coordinates":[9.21606,48.786011],"type":"Point"}
}