{
  "type": "Feature",
  "properties": {
    "iso:country":"DE",
    "sg:address":"Schulzenstr. 7",
    "sg:city":"Bruchk\u00f6bel",
    "sg:phone":"+49 6181/77916",
    "sg:postcode":"63486",
    "sg:province":"Hessen",
    "wof:name":"Heinrich J. Goy",
    "wof:placetype":"venue"
},
  "geometry": {"coordinates":[8.9124,50.199341],"type":"Point"}
}