{
  "type": "Feature",
  "properties": {
    "iso:country":"DE",
    "sg:address":"Fesenfeld 57",
    "sg:city":"Bremen",
    "sg:phone":"+49 421/71114",
    "sg:postcode":"28203",
    "sg:province":"Bremen",
    "wof:name":"Regge Bremen Registrierung & Betrieb V. Domains",
    "wof:placetype":"venue"
},
  "geometry": {"coordinates":[8.8322753906,53.0736122131],"type":"Point"}
}