{
  "type": "Feature",
  "properties": {
    "iso:country":"DE",
    "sg:address":"Reichsstr. 36",
    "sg:city":"Berlin",
    "sg:phone":"+49 30/30099080",
    "sg:postcode":"14052",
    "sg:province":"Berlin",
    "wof:name":"Raphael-apotheke",
    "wof:placetype":"venue"
},
  "geometry": {"coordinates":[13.257218,52.519379],"type":"Point"}
}