{
  "type": "Feature",
  "properties": {
    "iso:country":"DE",
    "sg:address":"Alte Dorfstr. 68",
    "sg:city":"Wuppertal",
    "sg:phone":"+49 202/741114",
    "sg:postcode":"42327",
    "sg:province":"Nordrhein-Westfalen",
    "wof:name":"Dorfschenke",
    "wof:placetype":"venue"
},
  "geometry": {"coordinates":[7.0962557793,51.2385406494],"type":"Point"}
}