{
  "type": "Feature",
  "properties": {
    "iso:country":"DE",
    "sg:address":"Bahnhofstr. 21",
    "sg:city":"Wolfratshausen",
    "sg:phone":"+49 8171/20035",
    "sg:postcode":"82515",
    "sg:province":"Bayern",
    "wof:name":"Elke Schwarzlm\u00fcller Immobilien Vermiet. Hausv. Vermittl. Von",
    "wof:placetype":"venue"
},
  "geometry": {"coordinates":[11.4243593216,47.9154396057],"type":"Point"}
}