{
  "type": "Feature",
  "properties": {
    "iso:country":"DE",
    "sg:address":"Rotachstr. 30",
    "sg:city":"Deggenhausertal",
    "sg:phone":"+49 7555/255",
    "sg:postcode":"88693",
    "sg:province":"Baden-W\u00fcrttemberg",
    "wof:name":"Kath. Pfarramt Dreik\u00f6nig",
    "wof:placetype":"venue"
},
  "geometry": {"coordinates":[9.4327993393,47.7632446289],"type":"Point"}
}