{
  "type": "Feature",
  "properties": {
    "iso:country":"DE",
    "sg:address":"Ringelnatzstr. 10",
    "sg:city":"Berlin",
    "sg:phone":"+49 30/765820",
    "sg:postcode":"12305",
    "sg:province":"Berlin",
    "wof:name":"Wolff & M\u00fcller Gmbh & Co. Kg",
    "wof:placetype":"venue"
},
  "geometry": {"coordinates":[13.4073295593,52.4010848999],"type":"Point"}
}