{
  "type": "Feature",
  "properties": {
    "iso:country":"DE",
    "sg:address":"Wiesenstr. 7",
    "sg:city":"Bad Lausick",
    "sg:phone":"+49 34345/22745",
    "sg:postcode":"04651",
    "sg:province":"Sachsen",
    "wof:name":"Manfred Saupe",
    "wof:placetype":"venue"
},
  "geometry": {"coordinates":[12.65662,51.148586],"type":"Point"}
}