{
  "type": "Feature",
  "properties": {
    "iso:country":"DE",
    "sg:address":"Moltkestr. 10",
    "sg:city":"Heilbronn",
    "sg:phone":"+49 7131/78790",
    "sg:postcode":"74072",
    "sg:province":"Baden-W\u00fcrttemberg",
    "wof:name":"Dr. Eckhart Lohbeck Rechtsanwalt",
    "wof:placetype":"venue"
},
  "geometry": {"coordinates":[9.2229251862,49.1414299011],"type":"Point"}
}