{
  "type": "Feature",
  "properties": {
    "iso:country":"DE",
    "sg:address":"Lortzingstr. 15",
    "sg:city":"Leipzig",
    "sg:phone":"+49 341/2117959",
    "sg:postcode":"04105",
    "sg:province":"Sachsen",
    "wof:name":"Physiotherapie Kompisch Gbr",
    "wof:placetype":"venue"
},
  "geometry": {"coordinates":[12.36936,51.346237],"type":"Point"}
}