{
  "type": "Feature",
  "properties": {
    "iso:country":"DE",
    "sg:address":"Brunnenstr. 27",
    "sg:city":"Untereisesheim",
    "sg:postcode":"74257",
    "sg:province":"Baden-W\u00fcrttemberg",
    "wof:name":"Wirth Computervertriebsgesell- Schaft Mbh",
    "wof:placetype":"venue"
},
  "geometry": {"coordinates":[9.1982707977,49.2099609375],"type":"Point"}
}