{
  "type": "Feature",
  "properties": {
    "iso:country":"DE",
    "sg:address":"G\u00fclder Weg 7",
    "sg:city":"Delligsen",
    "sg:phone":"+49 5187/4158",
    "sg:postcode":"31073",
    "sg:province":"Niedersachsen",
    "wof:name":"Annette Schwarze Krankengymnastin",
    "wof:placetype":"venue"
},
  "geometry": {"coordinates":[9.794223,51.94302],"type":"Point"}
}