{
  "type": "Feature",
  "properties": {
    "iso:country":"DE",
    "sg:address":"Bahnhofstr. 91",
    "sg:city":"Gl\u00f6wen",
    "sg:phone":"+49 38787/70208",
    "sg:postcode":"19339",
    "sg:province":"Brandenburg",
    "wof:name":"Sonja Bergmeyer Masseurin",
    "wof:placetype":"venue"
},
  "geometry": {"coordinates":[12.085564,52.910469],"type":"Point"}
}