{
  "type": "Feature",
  "properties": {
    "iso:country":"DE",
    "sg:address":"Aschaffenburger Str. 11",
    "sg:city":"Offenbach",
    "sg:phone":"+49 69/894343",
    "sg:postcode":"63073",
    "sg:province":"Hessen",
    "wof:name":"Barth & Bauer",
    "wof:placetype":"venue"
},
  "geometry": {"coordinates":[8.807583,50.088871],"type":"Point"}
}