{
  "type": "Feature",
  "properties": {
    "iso:country":"DE",
    "sg:address":"Gr\u00fcnbauerstr. 12",
    "sg:city":"M\u00fcnchen",
    "sg:phone":"+49 89/796822",
    "sg:postcode":"81479",
    "sg:province":"Bayern",
    "wof:name":"Bachler Gmbh",
    "wof:placetype":"venue"
},
  "geometry": {"coordinates":[11.516675,48.078075],"type":"Point"}
}