{
  "type": "Feature",
  "properties": {
    "iso:country":"DE",
    "sg:address":"Gundelfinger Str. 20",
    "sg:city":"B\u00e4chingen",
    "sg:phone":"+49 7325/919310",
    "sg:postcode":"89431",
    "sg:province":"Bayern",
    "wof:name":"W. Schmid",
    "wof:placetype":"venue"
},
  "geometry": {"coordinates":[10.3150520325,48.5458183289],"type":"Point"}
}