{
  "type": "Feature",
  "properties": {
    "iso:country":"DE",
    "sg:address":"Senftenberger Ring 17",
    "sg:city":"Berlin",
    "sg:phone":"+49 30/4167333",
    "sg:postcode":"13439",
    "sg:province":"Berlin",
    "wof:name":"Parf\u00fcmerie Kummert",
    "wof:placetype":"venue"
},
  "geometry": {"coordinates":[13.355551,52.599121],"type":"Point"}
}