{
  "type": "Feature",
  "properties": {
    "iso:country":"DE",
    "sg:address":"Donebacher Str. 41",
    "sg:city":"Mudau",
    "sg:phone":"+49 6284/7654",
    "sg:postcode":"69427",
    "sg:province":"Baden-W\u00fcrttemberg",
    "wof:name":"Golfshop Des Golfclubs Mudau",
    "wof:placetype":"venue"
},
  "geometry": {"coordinates":[9.19924,49.545406],"type":"Point"}
}