{
  "type": "Feature",
  "properties": {
    "iso:country":"DE",
    "sg:address":"Friedrichstr. 3",
    "sg:city":"Kellinghusen",
    "sg:phone":"+49 4822/7422",
    "sg:postcode":"25548",
    "sg:province":"Schleswig-Holstein",
    "wof:name":"Ernst Bracker Masseur",
    "wof:placetype":"venue"
},
  "geometry": {"coordinates":[9.727991,53.947205],"type":"Point"}
}