{
  "type": "Feature",
  "properties": {
    "iso:country":"DE",
    "sg:address":"Landgrafenstr. 122",
    "sg:city":"Dortmund",
    "sg:phone":"+49 231/101100",
    "sg:postcode":"44139",
    "sg:province":"Nordrhein-Westfalen",
    "wof:name":"Impex Handelsges. Mbh",
    "wof:placetype":"venue"
},
  "geometry": {"coordinates":[7.4656391144,51.5029296875],"type":"Point"}
}