{
  "type": "Feature",
  "properties": {
    "iso:country":"DE",
    "sg:address":"Auer Str. 20",
    "sg:city":"Karlsruhe",
    "sg:phone":"+49 721/406249",
    "sg:postcode":"76227",
    "sg:province":"Baden-W\u00fcrttemberg",
    "wof:name":"M. Und R. Eberhardt",
    "wof:placetype":"venue"
},
  "geometry": {"coordinates":[8.4610910416,48.9984550476],"type":"Point"}
}