{
  "type": "Feature",
  "properties": {
    "iso:country":"DE",
    "sg:address":"Voltmerstr. 73",
    "sg:city":"Hannover",
    "sg:postcode":"30165",
    "sg:province":"Niedersachsen",
    "wof:name":"Meyer Betriebsf\u00fchrungs-gmbh",
    "wof:placetype":"venue"
},
  "geometry": {"coordinates":[9.713816,52.406387],"type":"Point"}
}