{
  "type": "Feature",
  "properties": {
    "iso:country":"DE",
    "sg:address":"Haydnstr. 14",
    "sg:city":"Wolfschlugen",
    "sg:phone":"+49 7022/55809",
    "sg:postcode":"72649",
    "sg:province":"Baden-W\u00fcrttemberg",
    "wof:name":"Sybille Frank Immobilienmaklerin",
    "wof:placetype":"venue"
},
  "geometry": {"coordinates":[9.2880525589,48.6561851501],"type":"Point"}
}