{
  "type": "Feature",
  "properties": {
    "iso:country":"DE",
    "sg:address":"Am Florianigraben 4",
    "sg:city":"Geiselh\u00f6ring",
    "sg:phone":"+49 9423/2245",
    "sg:postcode":"94333",
    "sg:province":"Bayern",
    "wof:name":"K. Schmalhofer Rechtsanwalt",
    "wof:placetype":"venue"
},
  "geometry": {"coordinates":[12.3904485703,48.8260116577],"type":"Point"}
}