{
  "type": "Feature",
  "properties": {
    "iso:country":"DE",
    "sg:address":"Lindenstr. 2",
    "sg:city":"Schotten",
    "sg:phone":"+49 6044/8703",
    "sg:postcode":"63679",
    "sg:province":"Hessen",
    "wof:name":"G. Kromm",
    "wof:placetype":"venue"
},
  "geometry": {"coordinates":[9.1234998703,50.5050888062],"type":"Point"}
}