{
  "type": "Feature",
  "properties": {
    "iso:country":"DE",
    "sg:address":"Koblenzer Str. 157",
    "sg:city":"Bonn",
    "sg:phone":"+49 228/330625",
    "sg:postcode":"53177",
    "sg:province":"Nordrhein-Westfalen",
    "wof:name":"Brigitte Betzen Masseurin",
    "wof:placetype":"venue"
},
  "geometry": {"coordinates":[7.166435,50.678661],"type":"Point"}
}