{
  "type": "Feature",
  "properties": {
    "iso:country":"DE",
    "sg:address":"Victoriastr.",
    "sg:city":"Marl",
    "sg:phone":"+49 2365/21022",
    "sg:postcode":"45772",
    "sg:province":"Nordrhein-Westfalen",
    "wof:name":"W.-e. Glunz",
    "wof:placetype":"venue"
},
  "geometry": {"coordinates":[7.130602,51.665226],"type":"Point"}
}