{
  "type": "Feature",
  "properties": {
    "iso:country":"DE",
    "sg:address":"Pesenlern 15",
    "sg:city":"Wartenberg",
    "sg:postcode":"85456",
    "sg:province":"Bayern",
    "wof:name":"M.h. Edv Service Gmbh",
    "wof:placetype":"venue"
},
  "geometry": {"coordinates":[11.9706678391,48.3899612427],"type":"Point"}
}