{
  "type": "Feature",
  "properties": {
    "iso:country":"DE",
    "sg:address":"Warstein 101 Belecke",
    "sg:city":"Warstein",
    "sg:phone":"+49 4929/0275393",
    "sg:postcode":"59581",
    "sg:province":"Nordrhein-Westfalen",
    "wof:name":"Grasbeinter Tiefbau Gmbh Baustoffhandel",
    "wof:placetype":"venue"
},
  "geometry": {"coordinates":[8.353955,51.442299],"type":"Point"}
}