{
  "type": "Feature",
  "properties": {
    "iso:country":"DE",
    "sg:address":"Meisenweg 8",
    "sg:city":"Wenzendorf",
    "sg:postcode":"21279",
    "sg:province":"Niedersachsen",
    "wof:name":"His Baubetreuungs Und Vermittlungs Gmbh",
    "wof:placetype":"venue"
},
  "geometry": {"coordinates":[9.751441,53.364788],"type":"Point"}
}