{
  "type": "Feature",
  "properties": {
    "iso:country":"DE",
    "sg:address":"Hauptstr. 34",
    "sg:city":"Seubersdorf",
    "sg:postcode":"92358",
    "sg:province":"Bayern",
    "wof:name":"Theodor Diepold",
    "wof:placetype":"venue"
},
  "geometry": {"coordinates":[11.603053093,49.1887969971],"type":"Point"}
}