{
  "type": "Feature",
  "properties": {
    "iso:country":"DE",
    "sg:address":"Bahnhofstr. 75",
    "sg:city":"Stadthagen",
    "sg:postcode":"31655",
    "sg:province":"Niedersachsen",
    "wof:name":"Lindenberg Gmbh",
    "wof:placetype":"venue"
},
  "geometry": {"coordinates":[9.190861,52.330811],"type":"Point"}
}