{
  "type": "Feature",
  "properties": {
    "iso:country":"DE",
    "sg:address":"Wichlinghauser Str. 38-42",
    "sg:city":"Wuppertal",
    "sg:postcode":"42277",
    "sg:province":"Nordrhein-Westfalen",
    "wof:name":"Erich Rothe Gmbh",
    "wof:placetype":"venue"
},
  "geometry": {"coordinates":[7.218574,51.278164],"type":"Point"}
}