{
  "type": "Feature",
  "properties": {
    "iso:country":"DE",
    "sg:address":"Kleinbachstr. 13",
    "sg:city":"Karlsruhe",
    "sg:postcode":"76227",
    "sg:province":"Baden-W\u00fcrttemberg",
    "wof:name":"Beda Bedachungs Gmbh",
    "wof:placetype":"venue"
},
  "geometry": {"coordinates":[8.473863,49.00222],"type":"Point"}
}