{
  "type": "Feature",
  "properties": {
    "iso:country":"DE",
    "sg:address":"Raiffeisenstr. 9",
    "sg:city":"Friedeburg",
    "sg:phone":"+49 4465/7080",
    "sg:postcode":"26446",
    "sg:province":"Niedersachsen",
    "wof:name":"Ovg Omnibusvertriebsge- Sellschaft Mbh",
    "wof:placetype":"venue"
},
  "geometry": {"coordinates":[7.8409528732,53.4563941956],"type":"Point"}
}