{
  "type": "Feature",
  "properties": {
    "iso:country":"DE",
    "sg:address":"Eisenbahnstr. 58",
    "sg:city":"Eggenstein-Leopoldshafen",
    "sg:phone":"+49 721/786753",
    "sg:postcode":"76344",
    "sg:province":"Baden-W\u00fcrttemberg",
    "wof:name":"Karl Ulrich",
    "wof:placetype":"venue"
},
  "geometry": {"coordinates":[8.3997869492,49.0812263489],"type":"Point"}
}