{
  "type": "Feature",
  "properties": {
    "iso:country":"DE",
    "sg:address":"Kreuzstr. 6",
    "sg:city":"Stuttgart",
    "sg:phone":"+49 711/732330",
    "sg:postcode":"70563",
    "sg:province":"Baden-W\u00fcrttemberg",
    "wof:name":"Hermann Strau\u00df Steuerberater",
    "wof:placetype":"venue"
},
  "geometry": {"coordinates":[9.1076993942,48.7337875366],"type":"Point"}
}