{
  "type": "Feature",
  "properties": {
    "iso:country":"DE",
    "sg:address":"Dachauer Str. 278",
    "sg:city":"M\u00fcnchen",
    "sg:phone":"+49 89/14838652",
    "sg:postcode":"80992",
    "sg:province":"Bayern",
    "wof:name":"Afk Albers-finanz-kaufleute Beteiligungs- Und",
    "wof:placetype":"venue"
},
  "geometry": {"coordinates":[11.511602,48.181309],"type":"Point"}
}