{
  "type": "Feature",
  "properties": {
    "iso:country":"DE",
    "sg:address":"Geislatsrieder Str. 16",
    "sg:city":"Bidingen",
    "sg:phone":"+49 8348/336",
    "sg:postcode":"87651",
    "sg:province":"Bayern",
    "wof:name":"Sportgastst\u00e4tte",
    "wof:placetype":"venue"
},
  "geometry": {"coordinates":[10.7302980423,47.8280220032],"type":"Point"}
}