{
  "type": "Feature",
  "properties": {
    "iso:country":"DE",
    "sg:address":"L\u00fcbbesmeyerweg 5",
    "sg:city":"Coesfeld",
    "sg:phone":"+49 4925/4182586",
    "sg:postcode":"48653",
    "sg:province":"Nordrhein-Westfalen",
    "wof:name":"Frenzel-elektromotoren",
    "wof:placetype":"venue"
},
  "geometry": {"coordinates":[7.163065,51.935581],"type":"Point"}
}