{
  "type": "Feature",
  "properties": {
    "iso:country":"DE",
    "sg:address":"Bergstr. 4",
    "sg:city":"Gomadingen",
    "sg:phone":"+49 7385/1503",
    "sg:postcode":"72532",
    "sg:province":"Baden-W\u00fcrttemberg",
    "wof:name":"Sabine Kla\u00df Hebamme",
    "wof:placetype":"venue"
},
  "geometry": {"coordinates":[9.411554,48.403519],"type":"Point"}
}