{
  "type": "Feature",
  "properties": {
    "iso:country":"DE",
    "sg:address":"Richelstr. 10",
    "sg:city":"M\u00fcnchen",
    "sg:phone":"+49 89/161697",
    "sg:postcode":"80634",
    "sg:province":"Bayern",
    "wof:name":"Ludwig Kernbichler",
    "wof:placetype":"venue"
},
  "geometry": {"coordinates":[11.5345687866,48.145488739],"type":"Point"}
}