{
  "type": "Feature",
  "properties": {
    "iso:country":"DE",
    "sg:address":"Stra\u00dfe der Jugend 3",
    "sg:city":"Mertendorf",
    "sg:phone":"+49 3445/701337",
    "sg:postcode":"06618",
    "sg:province":"Sachsen-Anhalt",
    "wof:name":"C. Hesselbarth",
    "wof:placetype":"venue"
},
  "geometry": {"coordinates":[11.8582229614,51.1201438904],"type":"Point"}
}