{
  "type": "Feature",
  "properties": {
    "iso:country":"DE",
    "sg:address":"Kreuzstr. 16",
    "sg:city":"Osnabr\u00fcck",
    "sg:phone":"+49 541/707848",
    "sg:postcode":"49084",
    "sg:province":"Niedersachsen",
    "wof:name":"Flower Mode Gmbh",
    "wof:placetype":"venue"
},
  "geometry": {"coordinates":[8.073728,52.280762],"type":"Point"}
}