{
  "type": "Feature",
  "properties": {
    "iso:country":"DE",
    "sg:address":"Weberwiese 8",
    "sg:city":"Wachtberg",
    "sg:phone":"+49 228/341909",
    "sg:postcode":"53343",
    "sg:province":"Nordrhein-Westfalen",
    "wof:name":"H. Wasserfuhr",
    "wof:placetype":"venue"
},
  "geometry": {"coordinates":[7.1416811943,50.6075897217],"type":"Point"}
}