{
  "type": "Feature",
  "properties": {
    "iso:country":"DE",
    "sg:address":"Niendorfer Str 19",
    "sg:city":"Hamburg",
    "sg:phone":"+49 40/322297",
    "sg:postcode":"22529",
    "sg:province":"Hamburg",
    "wof:name":"Sws Au\u00dfenhandels Gmbh",
    "wof:placetype":"venue"
},
  "geometry": {"coordinates":[9.954012,53.603504],"type":"Point"}
}