{
  "type": "Feature",
  "properties": {
    "iso:country":"DE",
    "sg:address":"Rheinfeldstr. 28",
    "sg:city":"R\u00f6thlein",
    "sg:phone":"+49 9723/91120",
    "sg:postcode":"97520",
    "sg:province":"Bayern",
    "wof:name":"R. Plast Kunststoffbearb. Und Handels Gmbh",
    "wof:placetype":"venue"
},
  "geometry": {"coordinates":[10.214249,49.979301],"type":"Point"}
}