{
  "type": "Feature",
  "properties": {
    "iso:country":"DE",
    "sg:address":"Zur Alten Glash\u00fctte 9a",
    "sg:city":"Bergheim",
    "sg:phone":"+49 2271/980443",
    "sg:postcode":"50127",
    "sg:province":"Nordrhein-Westfalen",
    "wof:name":"Kampus Consulting Gmbh",
    "wof:placetype":"venue"
},
  "geometry": {"coordinates":[6.6806130409,50.9352912903],"type":"Point"}
}