{
  "type": "Feature",
  "properties": {
    "iso:country":"DE",
    "sg:address":"Daimlerstr. 15",
    "sg:city":"Waldshut-Tiengen",
    "sg:phone":"+49 7741/92110",
    "sg:postcode":"79761",
    "sg:province":"Baden-W\u00fcrttemberg",
    "wof:name":"Peter Kaiser Architekt",
    "wof:placetype":"venue"
},
  "geometry": {"coordinates":[8.251895,47.622631],"type":"Point"}
}