{
  "type": "Feature",
  "properties": {
    "iso:country":"DE",
    "sg:address":"Hauptstr. 391",
    "sg:city":"K\u00f6ln",
    "sg:phone":"+49 2203/54839",
    "sg:postcode":"51143",
    "sg:province":"Nordrhein-Westfalen",
    "wof:name":"M. Milo",
    "wof:placetype":"venue"
},
  "geometry": {"coordinates":[7.0555138588,50.8859672546],"type":"Point"}
}