{
  "type": "Feature",
  "properties": {
    "iso:country":"DE",
    "sg:address":"Erlenstr. 18",
    "sg:city":"Pentling",
    "sg:phone":"+49 941/93858",
    "sg:postcode":"93080",
    "sg:province":"Bayern",
    "wof:name":"Elke Strauch-sindemann Rechtsanw\u00e4ltin",
    "wof:placetype":"venue"
},
  "geometry": {"coordinates":[12.0556974411,48.9876174927],"type":"Point"}
}