{
  "type": "Feature",
  "properties": {
    "iso:country":"DE",
    "sg:address":"Industriestr. 5",
    "sg:city":"Hermsdorf",
    "sg:phone":"+49 36601/40534",
    "sg:postcode":"07629",
    "sg:province":"Th\u00fcringen",
    "wof:name":"Raiffeisen Vermietungs- Und Verwaltungsgenossenschaft",
    "wof:placetype":"venue"
},
  "geometry": {"coordinates":[11.8585672379,50.9062004089],"type":"Point"}
}