{
  "type": "Feature",
  "properties": {
    "iso:country":"DE",
    "sg:address":"Rundweg 12",
    "sg:city":"Bad Wildungen",
    "sg:phone":"+49 6455/8303",
    "sg:postcode":"34537",
    "sg:province":"Hessen",
    "wof:name":"Robert Drebes",
    "wof:placetype":"venue"
},
  "geometry": {"coordinates":[8.984964,51.109707],"type":"Point"}
}