{
  "type": "Feature",
  "properties": {
    "iso:country":"DE",
    "sg:address":"Freudenholm",
    "sg:city":"Kasseedorf",
    "sg:phone":"+49 4528/1092",
    "sg:postcode":"23717",
    "sg:province":"Schleswig-Holstein",
    "wof:name":"Regina M\u00f6bel Gmbh",
    "wof:placetype":"venue"
},
  "geometry": {"coordinates":[10.6754808426,54.1896781921],"type":"Point"}
}