{
  "type": "Feature",
  "properties": {
    "iso:country":"DE",
    "sg:address":"Mozartstr. 22",
    "sg:city":"Bitburg",
    "sg:phone":"+49 6561/96690",
    "sg:postcode":"54634",
    "sg:province":"Rheinland-Pfalz",
    "wof:name":"Heller Und P\u00fctz",
    "wof:placetype":"venue"
},
  "geometry": {"coordinates":[6.5152549744,49.9687423706],"type":"Point"}
}