{
  "type": "Feature",
  "properties": {
    "iso:country":"DE",
    "sg:address":"Bahnhofstr. 1a",
    "sg:city":"Gr\u00e4fenhainichen",
    "sg:phone":"+49 34953/22276",
    "sg:postcode":"06773",
    "sg:province":"Sachsen-Anhalt",
    "wof:name":"Hollywood Restaurant",
    "wof:placetype":"venue"
},
  "geometry": {"coordinates":[12.4555797577,51.7288856506],"type":"Point"}
}