{
  "type": "Feature",
  "properties": {
    "iso:country":"DE",
    "sg:address":"Falkensteinstr. 23",
    "sg:city":"Breisach",
    "sg:phone":"+49 7664/408068",
    "sg:postcode":"79206",
    "sg:province":"Baden-W\u00fcrttemberg",
    "wof:name":"Fw-wohnbau Gmbh",
    "wof:placetype":"venue"
},
  "geometry": {"coordinates":[7.6585421562,47.979724884],"type":"Point"}
}