{
  "type": "Feature",
  "properties": {
    "iso:country":"DE",
    "sg:address":"Zillestr. 78",
    "sg:city":"Wurzen",
    "sg:phone":"+49 3425/926640",
    "sg:postcode":"04808",
    "sg:province":"Sachsen",
    "wof:name":"Mathilde Schenk",
    "wof:placetype":"venue"
},
  "geometry": {"coordinates":[12.7398662567,51.3795166016],"type":"Point"}
}