{
  "type": "Feature",
  "properties": {
    "iso:country":"DE",
    "sg:address":"G\u00f6rlitzer Str. 59",
    "sg:city":"Rothenburg",
    "sg:postcode":"02929",
    "sg:province":"Sachsen",
    "wof:name":"Katholisches Pfarramt Rothenburg",
    "wof:placetype":"venue"
},
  "geometry": {"coordinates":[14.9732942581,51.3276939392],"type":"Point"}
}