{
  "type": "Feature",
  "properties": {
    "iso:country":"DE",
    "sg:address":"Am Priel 3",
    "sg:city":"Rott",
    "sg:phone":"+49 8039/9110",
    "sg:postcode":"83543",
    "sg:province":"Bayern",
    "wof:name":"Renate Erb-jahn Steuerberater",
    "wof:placetype":"venue"
},
  "geometry": {"coordinates":[12.1342477798,47.9835395813],"type":"Point"}
}