{
  "type": "Feature",
  "properties": {
    "iso:country":"DE",
    "sg:address":"Gartenstr. 2",
    "sg:city":"Kempenich",
    "sg:phone":"+49 2655/1013",
    "sg:postcode":"56746",
    "sg:province":"Rheinland-Pfalz",
    "wof:name":"Toni Deuster",
    "wof:placetype":"venue"
},
  "geometry": {"coordinates":[7.119685,50.421017],"type":"Point"}
}