{
  "type": "Feature",
  "properties": {
    "iso:country":"DE",
    "sg:address":"Castellstr 39",
    "sg:city":"N\u00fcrnberg",
    "sg:phone":"+49 911/6491850",
    "sg:postcode":"90451",
    "sg:province":"Bayern",
    "wof:name":"Klaus Stadter Speditions Gmbh",
    "wof:placetype":"venue"
},
  "geometry": {"coordinates":[11.0309400558,49.406955719],"type":"Point"}
}