{
  "type": "Feature",
  "properties": {
    "iso:country":"DE",
    "sg:address":"Alte Bottroper Str. 35",
    "sg:city":"Essen",
    "sg:phone":"+49 201/663037",
    "sg:postcode":"45356",
    "sg:province":"Nordrhein-Westfalen",
    "wof:name":"Signa Projektmanagement Entsorgungs- Und",
    "wof:placetype":"venue"
},
  "geometry": {"coordinates":[6.963955,51.485565],"type":"Point"}
}