{
  "type": "Feature",
  "properties": {
    "iso:country":"DE",
    "sg:address":"Bahnhofstr. 26",
    "sg:city":"Nordenham",
    "sg:phone":"+49 4731/89928",
    "sg:postcode":"26954",
    "sg:province":"Niedersachsen",
    "wof:name":"Bistro Jornal",
    "wof:placetype":"venue"
},
  "geometry": {"coordinates":[8.4834852219,53.4848747253],"type":"Point"}
}