{
  "type": "Feature",
  "properties": {
    "iso:country":"DE",
    "sg:address":"Werkstr. 1",
    "sg:city":"Schweinfurt",
    "sg:phone":"+49 9721/803360",
    "sg:postcode":"97424",
    "sg:province":"Bayern",
    "wof:name":"Kupsch Gmbh",
    "wof:placetype":"venue"
},
  "geometry": {"coordinates":[10.2041387558,50.0301132202],"type":"Point"}
}