{
  "type": "Feature",
  "properties": {
    "iso:country":"DE",
    "sg:address":"Bahnstr. 13",
    "sg:city":"Mechernich",
    "sg:phone":"+49 2443/2088",
    "sg:postcode":"53894",
    "sg:province":"Nordrhein-Westfalen",
    "wof:name":"Elkes Reiseshop Gmbh",
    "wof:placetype":"venue"
},
  "geometry": {"coordinates":[6.6534600258,50.591545105],"type":"Point"}
}