{
  "type": "Feature",
  "properties": {
    "iso:country":"DE",
    "sg:address":"Petersstr. 12",
    "sg:city":"Leipzig",
    "sg:postcode":"04109",
    "sg:province":"Sachsen",
    "wof:name":"Svb S\u00e4chsische Verm\u00f6gens- Bildungsgesellschaft Mbh",
    "wof:placetype":"venue"
},
  "geometry": {"coordinates":[12.374458313,51.3393096924],"type":"Point"}
}