{
  "type": "Feature",
  "properties": {
    "iso:country":"DE",
    "sg:address":"Homfeld 9",
    "sg:city":"Bruchhausen-Vilsen",
    "sg:phone":"+49 4252/4441",
    "sg:postcode":"27305",
    "sg:province":"Niedersachsen",
    "wof:name":"Hermann Laue",
    "wof:placetype":"venue"
},
  "geometry": {"coordinates":[8.99181,52.810436],"type":"Point"}
}