{
  "type": "Feature",
  "properties": {
    "iso:country":"DE",
    "sg:address":"Arnulfstr. 4",
    "sg:city":"M\u00fcnchen",
    "sg:phone":"+49 89/551150",
    "sg:postcode":"80335",
    "sg:province":"Bayern",
    "wof:name":"Eden Hotel Wolff",
    "wof:placetype":"venue"
},
  "geometry": {"coordinates":[11.559447,48.141575],"type":"Point"}
}