{
  "type": "Feature",
  "properties": {
    "iso:country":"DE",
    "sg:address":"Neusiedlung 1",
    "sg:city":"Freyburg",
    "sg:phone":"+49 34464/28234",
    "sg:postcode":"06632",
    "sg:province":"Sachsen-Anhalt",
    "wof:name":"G\u00fcnter Enders",
    "wof:placetype":"venue"
},
  "geometry": {"coordinates":[11.765232,51.220577],"type":"Point"}
}