{
  "type": "Feature",
  "properties": {
    "iso:country":"DE",
    "sg:address":"Erbsenweg 13",
    "sg:city":"Naumburg",
    "sg:phone":"+49 3445/701615",
    "sg:postcode":"06618",
    "sg:province":"Sachsen-Anhalt",
    "wof:name":"Helga A. Weise",
    "wof:placetype":"venue"
},
  "geometry": {"coordinates":[11.8314638138,51.155090332],"type":"Point"}
}