{
  "type": "Feature",
  "properties": {
    "iso:country":"DE",
    "sg:address":"Bayreuther Str. 16",
    "sg:city":"N\u00fcrnberg",
    "sg:phone":"+49 911/533833",
    "sg:postcode":"90489",
    "sg:province":"Bayern",
    "wof:name":"K\u00fcchenstudio Max Inzinger Gmbh",
    "wof:placetype":"venue"
},
  "geometry": {"coordinates":[11.0913934708,49.4598922729],"type":"Point"}
}