{
  "type": "Feature",
  "properties": {
    "iso:country":"DE",
    "sg:address":"Aurikelweg 2",
    "sg:city":"Sonthofen",
    "sg:phone":"+49 8321/84114",
    "sg:postcode":"87527",
    "sg:province":"Bayern",
    "wof:name":"B. Rief",
    "wof:placetype":"venue"
},
  "geometry": {"coordinates":[10.2643594742,47.521270752],"type":"Point"}
}