{
  "type": "Feature",
  "properties": {
    "iso:country":"DE",
    "sg:address":"Provinzialstr. 178",
    "sg:city":"Dortmund",
    "sg:postcode":"44388",
    "sg:province":"Nordrhein-Westfalen",
    "wof:name":"Hartmut Gardemann Gmbh",
    "wof:placetype":"venue"
},
  "geometry": {"coordinates":[7.3245849609,51.5039978027],"type":"Point"}
}