{
  "type": "Feature",
  "properties": {
    "iso:country":"DE",
    "sg:address":"Im Rodel 22",
    "sg:city":"Karlsruhe",
    "sg:phone":"+49 721/45765",
    "sg:postcode":"76228",
    "sg:province":"Baden-W\u00fcrttemberg",
    "wof:name":"Wilhelm Lehmann",
    "wof:placetype":"venue"
},
  "geometry": {"coordinates":[8.4695997238,48.9570541382],"type":"Point"}
}