{
  "type": "Feature",
  "properties": {
    "iso:country":"DE",
    "sg:address":"Keplerstr.61",
    "sg:city":"Villingen-Schwenningen",
    "sg:phone":"+49 170",
    "sg:postcode":"78054",
    "sg:province":"Baden-W\u00fcrttemberg",
    "wof:name":"Kleintransporte",
    "wof:placetype":"venue"
},
  "geometry": {"coordinates":[8.5249567032,48.0560493469],"type":"Point"}
}