{
  "type": "Feature",
  "properties": {
    "iso:country":"DE",
    "sg:address":"Ziegeleiweg 26",
    "sg:city":"Erkrath",
    "sg:phone":"+49 4921/0433383",
    "sg:postcode":"40699",
    "sg:province":"Nordrhein-Westfalen",
    "wof:name":"Koller Gmbh",
    "wof:placetype":"venue"
},
  "geometry": {"coordinates":[6.947821,51.217842],"type":"Point"}
}