{
  "type": "Feature",
  "properties": {
    "iso:country":"DE",
    "sg:address":"H\u00f6lzengraben 2",
    "sg:city":"Kaiserslautern",
    "sg:phone":"+49 631/92826",
    "sg:postcode":"67657",
    "sg:province":"Rheinland-Pfalz",
    "wof:name":"Softas Software Service Gmbh",
    "wof:placetype":"venue"
},
  "geometry": {"coordinates":[7.7874598503,49.4555358887],"type":"Point"}
}