{
  "type": "Feature",
  "properties": {
    "iso:country":"DE",
    "sg:address":"Unterer Flurweg 15 d",
    "sg:city":"Senden",
    "sg:phone":"+49 7307/6465",
    "sg:postcode":"89250",
    "sg:province":"Bayern",
    "wof:name":"Wolfgang R\u00f6sch",
    "wof:placetype":"venue"
},
  "geometry": {"coordinates":[10.0448112488,48.3219566345],"type":"Point"}
}