{
  "type": "Feature",
  "properties": {
    "iso:country":"DE",
    "sg:address":"Vogelberg 32",
    "sg:city":"Celle",
    "sg:phone":"+49 5141/85676",
    "sg:postcode":"29227",
    "sg:province":"Niedersachsen",
    "wof:name":"Zeitzmann",
    "wof:placetype":"venue"
},
  "geometry": {"coordinates":[10.0740394592,52.6000328064],"type":"Point"}
}