{
  "type": "Feature",
  "properties": {
    "iso:country":"DE",
    "sg:address":"Michlstr. 7 A",
    "sg:city":"Denkendorf",
    "sg:phone":"+49 8466/1690",
    "sg:postcode":"85095",
    "sg:province":"Bayern",
    "wof:name":"J\u00fcrgen Mayer Ingenieur",
    "wof:placetype":"venue"
},
  "geometry": {"coordinates":[11.4903078079,48.9241676331],"type":"Point"}
}