{
  "type": "Feature",
  "properties": {
    "iso:country":"DE",
    "sg:address":"Friedrich-Ebert-Str. 7",
    "sg:city":"M\u00f6ser",
    "sg:phone":"+49 39222/96018",
    "sg:postcode":"39291",
    "sg:province":"Sachsen-Anhalt",
    "wof:name":"Ki Ma Immobilien Gmbh",
    "wof:placetype":"venue"
},
  "geometry": {"coordinates":[11.7838344574,52.2215881348],"type":"Point"}
}