{
  "type": "Feature",
  "properties": {
    "iso:country":"DE",
    "sg:address":"Bahnhofstr. 15",
    "sg:city":"Syke",
    "sg:phone":"+49 4242/5406",
    "sg:postcode":"28857",
    "sg:province":"Niedersachsen",
    "wof:name":"M. Schwenker Heissmangelbetrieb",
    "wof:placetype":"venue"
},
  "geometry": {"coordinates":[8.8135004044,52.9147949219],"type":"Point"}
}