{
  "type": "Feature",
  "properties": {
    "iso:country":"DE",
    "sg:city":"Trusetal",
    "sg:phone":"+49 36840/80267",
    "sg:postcode":"98596",
    "sg:province":"Th\u00fcringen",
    "wof:name":"G. Weisheit",
    "wof:placetype":"venue"
},
  "geometry": {"coordinates":[10.40728,50.785999],"type":"Point"}
}