{
  "type": "Feature",
  "properties": {
    "iso:country":"DE",
    "sg:address":"Dillenburger Str. 1",
    "sg:city":"Dietzh\u00f6lztal",
    "sg:phone":"+49 2774/51154",
    "sg:postcode":"35716",
    "sg:province":"Hessen",
    "wof:name":"Dr. Med. Hermann Flachshaar",
    "wof:placetype":"venue"
},
  "geometry": {"coordinates":[8.3334522247,50.8256835938],"type":"Point"}
}