{
  "type": "Feature",
  "properties": {
    "iso:country":"DE",
    "sg:address":"Schwarzer Weg13",
    "sg:city":"Perleberg",
    "sg:phone":"+49 3876/791210",
    "sg:postcode":"19348",
    "sg:province":"Brandenburg",
    "wof:name":"Masters Elektro-media",
    "wof:placetype":"venue"
},
  "geometry": {"coordinates":[11.8619852066,53.0761260986],"type":"Point"}
}