{
  "type": "Feature",
  "properties": {
    "iso:country":"DE",
    "sg:address":"Am K\u00fchberg 12",
    "sg:city":"Schwabhausen",
    "sg:postcode":"85247",
    "sg:province":"Bayern",
    "wof:name":"Zauner Einrichtungen E. K. P\u00e4chter G\u00fcnther Stepper",
    "wof:placetype":"venue"
},
  "geometry": {"coordinates":[11.344556,48.34235],"type":"Point"}
}