{
  "type": "Feature",
  "properties": {
    "iso:country":"DE",
    "sg:address":"Eisenstr. 88",
    "sg:city":"D\u00fcsseldorf",
    "sg:phone":"+49 211/727832",
    "sg:postcode":"40227",
    "sg:province":"Nordrhein-Westfalen",
    "wof:name":"Dschingis-khan",
    "wof:placetype":"venue"
},
  "geometry": {"coordinates":[6.8005747795,51.2170372009],"type":"Point"}
}