{
  "type": "Feature",
  "properties": {
    "iso:country":"DE",
    "sg:address":"Fritz-Reuter-Str. 5",
    "sg:city":"Neu Wulmstorf",
    "sg:postcode":"21629",
    "sg:province":"Niedersachsen",
    "wof:name":"Vitoplast Kunststof- Fabrik Lehmann & Sohn Kg",
    "wof:placetype":"venue"
},
  "geometry": {"coordinates":[9.784627,53.462616],"type":"Point"}
}