{
  "type": "Feature",
  "properties": {
    "iso:country":"DE",
    "sg:address":"Im Kranental 2",
    "sg:city":"Alsdorf",
    "sg:phone":"+49 2404/92056",
    "sg:postcode":"52477",
    "sg:province":"Nordrhein-Westfalen",
    "wof:name":"W. Kern",
    "wof:placetype":"venue"
},
  "geometry": {"coordinates":[6.1613349915,50.8598136902],"type":"Point"}
}