{
  "type": "Feature",
  "properties": {
    "iso:country":"DE",
    "sg:address":"Rhein-Mosel-Str. 2-10",
    "sg:city":"Boppard",
    "sg:phone":"+49 6742/5036",
    "sg:postcode":"56154",
    "sg:province":"Rheinland-Pfalz",
    "wof:name":"Vogt Heides\u00e4ge Gmbh",
    "wof:placetype":"venue"
},
  "geometry": {"coordinates":[7.5455980301,50.2141914368],"type":"Point"}
}