{
  "type": "Feature",
  "properties": {
    "iso:country":"DE",
    "sg:address":"Horchheimer Str. 2a",
    "sg:city":"Lahnstein",
    "sg:phone":"+49 2621/8332",
    "sg:postcode":"56112",
    "sg:province":"Rheinland-Pfalz",
    "wof:name":"Rolf Berninger",
    "wof:placetype":"venue"
},
  "geometry": {"coordinates":[7.597864,50.324566],"type":"Point"}
}