{
  "type": "Feature",
  "properties": {
    "iso:country":"DE",
    "sg:address":"Donnerstr. 13",
    "sg:city":"Velbert",
    "sg:phone":"+49 2052/16291",
    "sg:postcode":"42555",
    "sg:province":"Nordrhein-Westfalen",
    "wof:name":"Stadtb\u00fccherei",
    "wof:placetype":"venue"
},
  "geometry": {"coordinates":[7.13634,51.34034],"type":"Point"}
}