{
  "type": "Feature",
  "properties": {
    "iso:country":"DE",
    "sg:address":"Zum Spring 14",
    "sg:city":"Beverungen",
    "sg:phone":"+49 5273/1247",
    "sg:postcode":"37688",
    "sg:province":"Nordrhein-Westfalen",
    "wof:name":"Rudolf Groppe",
    "wof:placetype":"venue"
},
  "geometry": {"coordinates":[9.372598,51.669014],"type":"Point"}
}