{
  "type": "Feature",
  "properties": {
    "iso:country":"DE",
    "sg:address":"Schreiberstr. 9",
    "sg:city":"Filderstadt",
    "sg:phone":"+49 7158/8392",
    "sg:postcode":"70794",
    "sg:province":"Baden-W\u00fcrttemberg",
    "wof:name":"Gottlob Schreiber Verwaltungs- Gmbh",
    "wof:placetype":"venue"
},
  "geometry": {"coordinates":[9.2380809784,48.6689491272],"type":"Point"}
}