{
  "type": "Feature",
  "properties": {
    "iso:country":"DE",
    "sg:address":"Hasenweg 10",
    "sg:city":"Leopoldsh\u00f6he",
    "sg:postcode":"33818",
    "sg:province":"Nordrhein-Westfalen",
    "wof:name":"Ifa-immobilien Beratung",
    "wof:placetype":"venue"
},
  "geometry": {"coordinates":[8.6657390594,51.9949645996],"type":"Point"}
}