{
  "type": "Feature",
  "properties": {
    "iso:country":"DE",
    "sg:address":"Setzgasse 7",
    "sg:city":"Miltenberg",
    "sg:phone":"+49 9371/6213",
    "sg:postcode":"63897",
    "sg:province":"Bayern",
    "wof:name":"Bezet Offsetdruck Gmbh",
    "wof:placetype":"venue"
},
  "geometry": {"coordinates":[9.26587677,49.7036781311],"type":"Point"}
}