{
  "type": "Feature",
  "properties": {
    "iso:country":"DE",
    "sg:address":"Oststr. 1",
    "sg:city":"Hattingen",
    "sg:phone":"+49 2324/22171",
    "sg:postcode":"45525",
    "sg:province":"Nordrhein-Westfalen",
    "wof:name":"Provinzial Versicherung Iris Kosthaus",
    "wof:placetype":"venue"
},
  "geometry": {"coordinates":[7.1874141693,51.4003181458],"type":"Point"}
}