{
  "type": "Feature",
  "properties": {
    "iso:country":"DE",
    "sg:address":"Proviantstr. 30",
    "sg:city":"Ingolstadt",
    "sg:phone":"+49 841/933190",
    "sg:postcode":"85049",
    "sg:province":"Bayern",
    "wof:name":"Blb Steuerberatungs Gmbh",
    "wof:placetype":"venue"
},
  "geometry": {"coordinates":[11.4262218475,48.7677841187],"type":"Point"}
}