{
  "type": "Feature",
  "properties": {
    "iso:country":"DE",
    "sg:address":"Am Deich 64d",
    "sg:city":"Bremen",
    "sg:phone":"+49 421/591349",
    "sg:postcode":"28199",
    "sg:province":"Bremen",
    "wof:name":"Darksun Gmbh",
    "wof:placetype":"venue"
},
  "geometry": {"coordinates":[8.798857,53.074902],"type":"Point"}
}