{
  "type": "Feature",
  "properties": {
    "iso:country":"DE",
    "sg:address":"Sattlerstr. 9",
    "sg:city":"Schweinfurt",
    "sg:phone":"+49 9721/189181",
    "sg:postcode":"97421",
    "sg:province":"Bayern",
    "wof:name":"Gro\u00dfformat Zentrum",
    "wof:placetype":"venue"
},
  "geometry": {"coordinates":[10.225063324,50.0412826538],"type":"Point"}
}