{
  "type": "Feature",
  "properties": {
    "iso:country":"DE",
    "sg:address":"Rocksdorfer Str. 10",
    "sg:city":"M\u00fchlhausen",
    "sg:phone":"+49 9185/9210",
    "sg:postcode":"92360",
    "sg:province":"Bayern",
    "wof:name":"Fischer Licht & Metall Gmbh & Co Kg",
    "wof:placetype":"venue"
},
  "geometry": {"coordinates":[11.444024,49.170315],"type":"Point"}
}