{
  "type": "Feature",
  "properties": {
    "iso:country":"DE",
    "sg:address":"\u00dcber dem Berg 9",
    "sg:city":"Mammelzen",
    "sg:postcode":"57636",
    "sg:province":"Rheinland-Pfalz",
    "wof:name":"Galerie Scafare",
    "wof:placetype":"venue"
},
  "geometry": {"coordinates":[7.6704239845,50.7005882263],"type":"Point"}
}