{
  "type": "Feature",
  "properties": {
    "iso:country":"DE",
    "sg:address":"Meyerhofstr. 2",
    "sg:city":"Bramsche",
    "sg:phone":"+49 5461/4105",
    "sg:postcode":"49565",
    "sg:province":"Niedersachsen",
    "wof:name":"Akupunkt-massage B\u00e4rbel Bredemeyer",
    "wof:placetype":"venue"
},
  "geometry": {"coordinates":[7.977861,52.407616],"type":"Point"}
}