{
  "type": "Feature",
  "properties": {
    "iso:country":"DE",
    "sg:address":"B\u00e4derstrasse 4",
    "sg:city":"Pfalzgrafenweiler",
    "sg:phone":"+49 7445",
    "sg:postcode":"72285",
    "sg:province":"Baden-W\u00fcrttemberg",
    "wof:name":"Biancardi Automobile",
    "wof:placetype":"venue"
},
  "geometry": {"coordinates":[8.5687074661,48.528377533],"type":"Point"}
}