{
  "type": "Feature",
  "properties": {
    "iso:country":"DE",
    "sg:address":"K\u00f6nigstr. 58",
    "sg:city":"Stuttgart",
    "sg:phone":"+49 711/293261",
    "sg:postcode":"70173",
    "sg:province":"Baden-W\u00fcrttemberg",
    "wof:name":"Chris",
    "wof:placetype":"venue"
},
  "geometry": {"coordinates":[9.174797,48.774998],"type":"Point"}
}