{
  "type": "Feature",
  "properties": {
    "iso:country":"DE",
    "sg:address":"Am Holtkamp 8",
    "sg:city":"Melle",
    "sg:phone":"+49 5422/3104",
    "sg:postcode":"49326",
    "sg:province":"Niedersachsen",
    "wof:name":"Hermann Stieve",
    "wof:placetype":"venue"
},
  "geometry": {"coordinates":[8.2535,52.217831],"type":"Point"}
}