{
  "type": "Feature",
  "properties": {
    "iso:country":"DE",
    "sg:address":"Sauerbruchstr. 18",
    "sg:city":"Troisdorf",
    "sg:phone":"+49 2241/946555",
    "sg:postcode":"53844",
    "sg:province":"Nordrhein-Westfalen",
    "wof:name":"H & P Immobilien-verwaltungs- Gesellschaft Mbh",
    "wof:placetype":"venue"
},
  "geometry": {"coordinates":[7.1152100563,50.7982025146],"type":"Point"}
}