{
  "type": "Feature",
  "properties": {
    "iso:country":"DE",
    "sg:address":"Waldauer Str. 22",
    "sg:city":"Schw\u00e4bisch Gm\u00fcnd",
    "sg:postcode":"73527",
    "sg:province":"Baden-W\u00fcrttemberg",
    "wof:name":"Feuerle Holzbau Gmbh",
    "wof:placetype":"venue"
},
  "geometry": {"coordinates":[9.775970459,48.8177185059],"type":"Point"}
}