{
  "type": "Feature",
  "properties": {
    "iso:country":"DE",
    "sg:address":"Ostbahnhofstr. 19",
    "sg:city":"Villingen-Schwenningen",
    "sg:phone":"+49 7721/91850",
    "sg:postcode":"78052",
    "sg:province":"Baden-W\u00fcrttemberg",
    "wof:name":"Reiner Oberle German Electrical & Mechanical",
    "wof:placetype":"venue"
},
  "geometry": {"coordinates":[8.4762868881,48.0334281921],"type":"Point"}
}