{
  "type": "Feature",
  "properties": {
    "iso:country":"DE",
    "sg:address":"Nibelungenstr. 62",
    "sg:city":"Dietzenbach",
    "sg:phone":"+49 6074/32617",
    "sg:postcode":"63128",
    "sg:province":"Hessen",
    "wof:name":"Dieter Fenchel",
    "wof:placetype":"venue"
},
  "geometry": {"coordinates":[8.7874765396,50.024307251],"type":"Point"}
}