{
  "type": "Feature",
  "properties": {
    "iso:country":"DE",
    "sg:address":"Menzelstr. 1",
    "sg:city":"Oranienburg",
    "sg:phone":"+49 3301/800119",
    "sg:postcode":"16515",
    "sg:province":"Brandenburg",
    "wof:name":"F. Seifert Architekt",
    "wof:placetype":"venue"
},
  "geometry": {"coordinates":[13.249315,52.725052],"type":"Point"}
}