{
  "type": "Feature",
  "properties": {
    "iso:country":"DE",
    "sg:address":"Koblenzer Str. 181",
    "sg:city":"Mayen",
    "sg:phone":"+49 2651/4465",
    "sg:postcode":"56727",
    "sg:province":"Rheinland-Pfalz",
    "wof:name":"Pierre Wagner Gmbh",
    "wof:placetype":"venue"
},
  "geometry": {"coordinates":[7.2437310219,50.3277015686],"type":"Point"}
}