{
  "type": "Feature",
  "properties": {
    "iso:country":"DE",
    "sg:address":"Mathilde-Kaiser-Str. 40",
    "sg:city":"Essen",
    "sg:phone":"+49 201/282056",
    "sg:postcode":"45138",
    "sg:province":"Nordrhein-Westfalen",
    "wof:name":"Blindenaltenheim St. Altfried",
    "wof:placetype":"venue"
},
  "geometry": {"coordinates":[7.054214,51.44635],"type":"Point"}
}