{
  "type": "Feature",
  "properties": {
    "iso:country":"DE",
    "sg:address":"Friedhofstr. 13",
    "sg:city":"Neuenburg",
    "sg:phone":"+49 7631/799196",
    "sg:postcode":"79395",
    "sg:province":"Baden-W\u00fcrttemberg",
    "wof:name":"Kkc Dr. Klink Gmbh",
    "wof:placetype":"venue"
},
  "geometry": {"coordinates":[7.565018177,47.8148345947],"type":"Point"}
}