{
  "type": "Feature",
  "properties": {
    "iso:country":"DE",
    "sg:address":"\u00dcberseebr\u00fccke",
    "sg:city":"Hamburg",
    "sg:phone":"+49 40/312929",
    "sg:postcode":"20459",
    "sg:province":"Hamburg",
    "wof:name":"\u00dcberseebr\u00fccke",
    "wof:placetype":"venue"
},
  "geometry": {"coordinates":[10.002240181,53.5410385132],"type":"Point"}
}