{
  "type": "Feature",
  "properties": {
    "iso:country":"DE",
    "sg:address":"Mechthildstr. 14",
    "sg:city":"Rottenburg",
    "sg:phone":"+49 7472/982020",
    "sg:postcode":"72108",
    "sg:province":"Baden-W\u00fcrttemberg",
    "wof:name":"Gro\u00df Reisen Gmbh",
    "wof:placetype":"venue"
},
  "geometry": {"coordinates":[8.9388866425,48.4789161682],"type":"Point"}
}