{
  "type": "Feature",
  "properties": {
    "iso:country":"DE",
    "sg:address":"Kantstr. 5",
    "sg:city":"Ravensburg",
    "sg:phone":"+49 751/793752",
    "sg:postcode":"88213",
    "sg:province":"Baden-W\u00fcrttemberg",
    "wof:name":"A. Heim",
    "wof:placetype":"venue"
},
  "geometry": {"coordinates":[9.581003,47.780464],"type":"Point"}
}