{
  "type": "Feature",
  "properties": {
    "iso:country":"DE",
    "sg:address":"Dorfstr. 44",
    "sg:city":"Kettershausen",
    "sg:phone":"+49 8333/1387",
    "sg:postcode":"86498",
    "sg:province":"Bayern",
    "wof:name":"J. K\u00f6hler",
    "wof:placetype":"venue"
},
  "geometry": {"coordinates":[10.2566204071,48.1791191101],"type":"Point"}
}