{
  "type": "Feature",
  "properties": {
    "iso:country":"DE",
    "sg:address":"Fichtestr. 62",
    "sg:city":"Weiden",
    "sg:phone":"+49 961/23993",
    "sg:postcode":"92637",
    "sg:province":"Bayern",
    "wof:name":"Erich Brunhuber Heilpraktiker",
    "wof:placetype":"venue"
},
  "geometry": {"coordinates":[12.1468639374,49.6835861206],"type":"Point"}
}