{
  "type": "Feature",
  "properties": {
    "iso:country":"DE",
    "sg:address":"K\u00f6nigsteiner Str. 169",
    "sg:city":"Frankfurt",
    "sg:phone":"+49 69/312589",
    "sg:postcode":"65929",
    "sg:province":"Hessen",
    "wof:name":"Hubert Kaiser Architekt",
    "wof:placetype":"venue"
},
  "geometry": {"coordinates":[8.535228,50.113468],"type":"Point"}
}