{
  "type": "Feature",
  "properties": {
    "iso:country":"DE",
    "sg:address":"Hauptstr. 4",
    "sg:city":"Rechtsupweg",
    "sg:postcode":"26529",
    "sg:province":"Niedersachsen",
    "wof:name":"H. F. - Brookmerlander Bau-putz-estrich Gmbh",
    "wof:placetype":"venue"
},
  "geometry": {"coordinates":[7.310048,53.526981],"type":"Point"}
}