{
  "type": "Feature",
  "properties": {
    "iso:country":"DE",
    "sg:address":"Barnestr. 37",
    "sg:city":"Wunstorf",
    "sg:phone":"+49 5031/5859",
    "sg:postcode":"31515",
    "sg:province":"Niedersachsen",
    "wof:name":"Versicherungsagentur Michael M\u00fcller E. K.",
    "wof:placetype":"venue"
},
  "geometry": {"coordinates":[9.4312419891,52.4185066223],"type":"Point"}
}