{
  "type": "Feature",
  "properties": {
    "iso:country":"DE",
    "sg:address":"Hauptstr. 2",
    "sg:city":"Fischen",
    "sg:phone":"+49 8326/7155",
    "sg:postcode":"87538",
    "sg:province":"Bayern",
    "wof:name":"Abc Blumen Diranko Kg",
    "wof:placetype":"venue"
},
  "geometry": {"coordinates":[10.233462,47.46067],"type":"Point"}
}