{
  "type": "Feature",
  "properties": {
    "iso:country":"DE",
    "sg:address":"M\u00f6nchsambach 26",
    "sg:city":"Burgebrach",
    "sg:phone":"+49 9546/8520",
    "sg:postcode":"96138",
    "sg:province":"Bayern",
    "wof:name":"Bohr- Und Brunnenbau Dippold E. K.",
    "wof:placetype":"venue"
},
  "geometry": {"coordinates":[10.677081,49.818504],"type":"Point"}
}