{
  "type": "Feature",
  "properties": {
    "iso:country":"DE",
    "sg:address":"Untere M\u00fchlstr. 12",
    "sg:city":"Worms",
    "sg:phone":"+49 6241/33196",
    "sg:postcode":"67551",
    "sg:province":"Rheinland-Pfalz",
    "wof:name":"Schach-scheu",
    "wof:placetype":"venue"
},
  "geometry": {"coordinates":[8.26861763,49.6046638489],"type":"Point"}
}