{
  "type": "Feature",
  "properties": {
    "iso:country":"DE",
    "sg:address":"Fritz-Schmidt-Str. 14",
    "sg:city":"Ludwigshafen",
    "sg:phone":"+49 621/5294147",
    "sg:postcode":"67067",
    "sg:province":"Rheinland-Pfalz",
    "wof:name":"H. Mohr",
    "wof:placetype":"venue"
},
  "geometry": {"coordinates":[8.4221162796,49.4482116699],"type":"Point"}
}