{
  "type": "Feature",
  "properties": {
    "iso:country":"DE",
    "sg:address":"Gro\u00dfenbacher Tor 4",
    "sg:city":"H\u00fcnfeld",
    "sg:phone":"+49 6652/919330",
    "sg:postcode":"36088",
    "sg:province":"Hessen",
    "wof:name":"Id Archiv Service Datenbank F\u00fcr Intrior Designer",
    "wof:placetype":"venue"
},
  "geometry": {"coordinates":[9.7710428238,50.6727676392],"type":"Point"}
}