{
  "type": "Feature",
  "properties": {
    "iso:country":"DE",
    "sg:city":"Apolda",
    "sg:phone":"+49 361/6510",
    "sg:postcode":"99510",
    "sg:province":"Th\u00fcringen",
    "wof:name":"Deutsche Telekom T-punkt",
    "wof:placetype":"venue"
},
  "geometry": {"coordinates":[11.509604,51.023163],"type":"Point"}
}