{
  "type": "Feature",
  "properties": {
    "iso:country":"DE",
    "sg:address":"Ockenheimer Chaussee 12",
    "sg:city":"Bingen",
    "sg:phone":"+49 6721/45672",
    "sg:postcode":"55411",
    "sg:province":"Rheinland-Pfalz",
    "wof:name":"Heinz Gr\u00fcnewald",
    "wof:placetype":"venue"
},
  "geometry": {"coordinates":[7.921107769,49.9478149414],"type":"Point"}
}