{
  "type": "Feature",
  "properties": {
    "iso:country":"DE",
    "sg:address":"Im Egert 1",
    "sg:city":"Lahr",
    "sg:phone":"+49 7821/955118",
    "sg:postcode":"77933",
    "sg:province":"Baden-W\u00fcrttemberg",
    "wof:name":"M. Heck Immobilienmakler",
    "wof:placetype":"venue"
},
  "geometry": {"coordinates":[7.8433289528,48.3298301697],"type":"Point"}
}