{
  "type": "Feature",
  "properties": {
    "iso:country":"DE",
    "sg:address":"Motzener Str. 32",
    "sg:city":"Berlin",
    "sg:phone":"+49 30/7218049",
    "sg:postcode":"12277",
    "sg:province":"Berlin",
    "wof:name":"Hildebrand Kakao- Und Schokoladenfabrik Gmbh",
    "wof:placetype":"venue"
},
  "geometry": {"coordinates":[13.3823461533,52.4016799927],"type":"Point"}
}