{
  "type": "Feature",
  "properties": {
    "iso:country":"DE",
    "sg:address":"Wagenburgstr 9",
    "sg:city":"Stuttgart",
    "sg:phone":"+49 711/242039",
    "sg:postcode":"70184",
    "sg:province":"Baden-W\u00fcrttemberg",
    "wof:name":"Vbs Maschinenbau Gmbh",
    "wof:placetype":"venue"
},
  "geometry": {"coordinates":[9.1919822693,48.7789001465],"type":"Point"}
}