{
  "type": "Feature",
  "properties": {
    "iso:country":"DE",
    "sg:address":"In den H\u00fctteng\u00e4rten 6",
    "sg:city":"Eisfeld",
    "sg:phone":"+49 3686/309258",
    "sg:postcode":"98673",
    "sg:province":"Th\u00fcringen",
    "wof:name":"Hahne Labortechnik Gmbh",
    "wof:placetype":"venue"
},
  "geometry": {"coordinates":[10.9117698669,50.4317016602],"type":"Point"}
}