{
  "type": "Feature",
  "properties": {
    "iso:country":"DE",
    "sg:address":"Hofer Str. 26",
    "sg:city":"Berg",
    "sg:phone":"+49 9293/667",
    "sg:postcode":"95180",
    "sg:province":"Bayern",
    "wof:name":"M. Ebert",
    "wof:placetype":"venue"
},
  "geometry": {"coordinates":[11.78195,50.373863],"type":"Point"}
}