{
  "type": "Feature",
  "properties": {
    "iso:country":"DE",
    "sg:address":"Hoefftstr. 6",
    "sg:city":"Uelzen",
    "sg:phone":"+49 581/2581",
    "sg:postcode":"29525",
    "sg:province":"Niedersachsen",
    "wof:name":"Gastst\u00e4tte Haus Sonne",
    "wof:placetype":"venue"
},
  "geometry": {"coordinates":[10.5559425354,52.9683799744],"type":"Point"}
}