{
  "type": "Feature",
  "properties": {
    "iso:country":"DE",
    "sg:address":"Lange Str. 100",
    "sg:city":"Vlotho",
    "sg:phone":"+49 5733/3742",
    "sg:postcode":"32602",
    "sg:province":"Nordrhein-Westfalen",
    "wof:name":"Butterfly",
    "wof:placetype":"venue"
},
  "geometry": {"coordinates":[8.8616933823,52.1675796509],"type":"Point"}
}