{
  "type": "Feature",
  "properties": {
    "iso:country":"DE",
    "sg:address":"Frankfurter Str. 76",
    "sg:city":"Gie\u00dfen",
    "sg:phone":"+49 641/23477",
    "sg:postcode":"35392",
    "sg:province":"Hessen",
    "wof:name":"Bp Tankstelle",
    "wof:placetype":"venue"
},
  "geometry": {"coordinates":[8.6618938446,50.5754776001],"type":"Point"}
}