{
  "type": "Feature",
  "properties": {
    "iso:country":"DE",
    "sg:address":"Bensberger Str. 252",
    "sg:city":"Bergisch Gladbach",
    "sg:phone":"+49 2202/1080",
    "sg:postcode":"51469",
    "sg:province":"Nordrhein-Westfalen",
    "wof:name":"Mci-gmbh Antennen Und Computer",
    "wof:placetype":"venue"
},
  "geometry": {"coordinates":[7.141269207,50.9747505188],"type":"Point"}
}