{
  "type": "Feature",
  "properties": {
    "iso:country":"DE",
    "sg:address":"Alte Dorfstr. 19",
    "sg:city":"Dornum",
    "sg:phone":"+49 4933/1390",
    "sg:postcode":"26553",
    "sg:province":"Niedersachsen",
    "wof:name":"Hartmut Taaken",
    "wof:placetype":"venue"
},
  "geometry": {"coordinates":[7.485061,53.635338],"type":"Point"}
}