{
  "type": "Feature",
  "properties": {
    "iso:country":"DE",
    "sg:address":"Grasweg 15",
    "sg:city":"Langen",
    "sg:phone":"+49 4743/92990",
    "sg:postcode":"27607",
    "sg:province":"Niedersachsen",
    "wof:name":"B\u00e4ko Bremerhaven B\u00e4cker- Und Konditorengenossenschaft Eg",
    "wof:placetype":"venue"
},
  "geometry": {"coordinates":[8.607521,53.648335],"type":"Point"}
}