{
  "type": "Feature",
  "properties": {
    "iso:country":"DE",
    "sg:address":"Ludwigstr. 9",
    "sg:city":"Bayreuth",
    "sg:phone":"+49 921/65603",
    "sg:postcode":"95444",
    "sg:province":"Bayern",
    "wof:name":"Strumpfhaus Schott Gmbh",
    "wof:placetype":"venue"
},
  "geometry": {"coordinates":[11.576981,49.942249],"type":"Point"}
}