{
  "type": "Feature",
  "properties": {
    "iso:country":"DE",
    "sg:address":"Porschestr. 12",
    "sg:city":"Waldkraiburg",
    "sg:phone":"+49 8638/84100",
    "sg:postcode":"84478",
    "sg:province":"Bayern",
    "wof:name":"Pereg Gmbh Technische Ger\u00e4te",
    "wof:placetype":"venue"
},
  "geometry": {"coordinates":[12.403346,48.21312],"type":"Point"}
}