{
  "type": "Feature",
  "properties": {
    "iso:country":"DE",
    "sg:address":"Georg-Friedrich-H\u00e4ndel-Str. 10",
    "sg:city":"\u00d6stringen",
    "sg:postcode":"76684",
    "sg:province":"Baden-W\u00fcrttemberg",
    "wof:name":"Werner Schmidt",
    "wof:placetype":"venue"
},
  "geometry": {"coordinates":[8.7007188797,49.2148590088],"type":"Point"}
}