{
  "type": "Feature",
  "properties": {
    "iso:country":"DE",
    "sg:address":"Spessartstr. 13",
    "sg:city":"Berlin",
    "sg:phone":"+49 30/8216476",
    "sg:postcode":"14197",
    "sg:province":"Berlin",
    "wof:name":"Michael Hess Architekt",
    "wof:placetype":"venue"
},
  "geometry": {"coordinates":[13.314666,52.474533],"type":"Point"}
}