{
  "type": "Feature",
  "properties": {
    "iso:country":"DE",
    "sg:address":"Reineburgstr. 10",
    "sg:city":"L\u00fcbbecke",
    "sg:phone":"+49 5741/297381",
    "sg:postcode":"32312",
    "sg:province":"Nordrhein-Westfalen",
    "wof:name":"Klaus Grabbe Innenarchitekt",
    "wof:placetype":"venue"
},
  "geometry": {"coordinates":[8.629454,52.309341],"type":"Point"}
}