{
  "type": "Feature",
  "properties": {
    "iso:country":"DE",
    "sg:address":"Marktstr. 10",
    "sg:city":"Sonthofen",
    "sg:phone":"+49 8321/2102",
    "sg:postcode":"87527",
    "sg:province":"Bayern",
    "wof:name":"Alte Apotheke",
    "wof:placetype":"venue"
},
  "geometry": {"coordinates":[10.280189,47.51078],"type":"Point"}
}