{
  "type": "Feature",
  "properties": {
    "iso:country":"DE",
    "sg:address":"Eidelstedter Platz 4",
    "sg:city":"Hamburg",
    "sg:phone":"+49 40/5710093",
    "sg:postcode":"22523",
    "sg:province":"Hamburg",
    "wof:name":"Michelle Gyllensv\u00e4rd Heilpraktikerin",
    "wof:placetype":"venue"
},
  "geometry": {"coordinates":[9.9081850052,53.623085022],"type":"Point"}
}