{
  "type": "Feature",
  "properties": {
    "iso:country":"DE",
    "sg:address":"Buchfinkenstr. 48 a",
    "sg:city":"K\u00f6ln",
    "sg:phone":"+49 2236/48727",
    "sg:postcode":"50997",
    "sg:province":"Nordrhein-Westfalen",
    "wof:name":"Lob-donker Gmbh",
    "wof:placetype":"venue"
},
  "geometry": {"coordinates":[6.973024,50.852322],"type":"Point"}
}