{
  "type": "Feature",
  "properties": {
    "iso:country":"DE",
    "sg:address":"Hauptstr. 67",
    "sg:city":"Weinheim",
    "sg:phone":"+49 6201/12923",
    "sg:postcode":"69469",
    "sg:province":"Baden-W\u00fcrttemberg",
    "wof:name":"J. Zeumer Kg",
    "wof:placetype":"venue"
},
  "geometry": {"coordinates":[8.6721515656,49.5491714478],"type":"Point"}
}