{
  "type": "Feature",
  "properties": {
    "iso:country":"DE",
    "sg:address":"Schlesierstr. 4",
    "sg:city":"Neu-Ulm",
    "sg:phone":"+49 731/711146",
    "sg:postcode":"89233",
    "sg:province":"Bayern",
    "wof:name":"Artur Brett Architekt",
    "wof:placetype":"venue"
},
  "geometry": {"coordinates":[10.031193,48.410847],"type":"Point"}
}