{
  "type": "Feature",
  "properties": {
    "iso:country":"DE",
    "sg:address":"Birkheckenstr. 80",
    "sg:city":"Stuttgart",
    "sg:phone":"+49 711/451572",
    "sg:postcode":"70599",
    "sg:province":"Baden-W\u00fcrttemberg",
    "wof:name":"Kath. Pfarramt St. Antonius Von Padua",
    "wof:placetype":"venue"
},
  "geometry": {"coordinates":[9.2051782608,48.7271842957],"type":"Point"}
}