{
  "type": "Feature",
  "properties": {
    "iso:country":"DE",
    "sg:address":"Universit\u00e4tsstr. 1",
    "sg:city":"Erlangen",
    "sg:postcode":"91054",
    "sg:province":"Bayern",
    "wof:name":"R. Und W. Schmauch Beteiligungsges. Mbh",
    "wof:placetype":"venue"
},
  "geometry": {"coordinates":[11.0050926208,49.5968399048],"type":"Point"}
}