{
  "type": "Feature",
  "properties": {
    "iso:country":"DE",
    "sg:address":"Am Bruch 8a",
    "sg:city":"Ratingen",
    "sg:phone":"+49 2102/17602",
    "sg:postcode":"40885",
    "sg:province":"Nordrhein-Westfalen",
    "wof:name":"Softsign Software & System Design Gmbh",
    "wof:placetype":"venue"
},
  "geometry": {"coordinates":[6.862964,51.338341],"type":"Point"}
}