{
  "type": "Feature",
  "properties": {
    "iso:country":"DE",
    "sg:address":"Metternicher Str 16",
    "sg:city":"Weilerswist",
    "sg:phone":"+49 2254/7048",
    "sg:postcode":"53919",
    "sg:province":"Nordrhein-Westfalen",
    "wof:name":"Erwin Steinle Internationale Spedition Gmbh & Co Kg",
    "wof:placetype":"venue"
},
  "geometry": {"coordinates":[6.8551330566,50.75050354],"type":"Point"}
}