{
  "type": "Feature",
  "properties": {
    "iso:country":"DE",
    "sg:address":"Siefer Hof 16",
    "sg:city":"Bergisch Gladbach",
    "sg:phone":"+49 2207/4408",
    "sg:postcode":"51429",
    "sg:province":"Nordrhein-Westfalen",
    "wof:name":"Heidkamp Immobilienmakler",
    "wof:placetype":"venue"
},
  "geometry": {"coordinates":[7.2031798363,50.998500824],"type":"Point"}
}