{
  "type": "Feature",
  "properties": {
    "iso:country":"DE",
    "sg:address":"Wolfsberger Anger 64",
    "sg:city":"Eggenfelden",
    "sg:phone":"+49 8721/1784",
    "sg:postcode":"84307",
    "sg:province":"Bayern",
    "wof:name":"Oskar Ulm Steuerberater",
    "wof:placetype":"venue"
},
  "geometry": {"coordinates":[12.7343225479,48.4237747192],"type":"Point"}
}