{
  "type": "Feature",
  "properties": {
    "iso:country":"DE",
    "sg:address":"Wellinghofer Str. 62",
    "sg:city":"Dortmund",
    "sg:phone":"+49 231/414700",
    "sg:postcode":"44263",
    "sg:province":"Nordrhein-Westfalen",
    "wof:name":"Heinz M\u00fcller",
    "wof:placetype":"venue"
},
  "geometry": {"coordinates":[7.496517,51.483562],"type":"Point"}
}