{
  "type": "Feature",
  "properties": {
    "iso:country":"DE",
    "sg:address":"Kampstr. 7",
    "sg:city":"M\u00fclheim",
    "sg:phone":"+49 208/35191",
    "sg:postcode":"45468",
    "sg:province":"Nordrhein-Westfalen",
    "wof:name":"J\u00fcdische Kultusgemeinde",
    "wof:placetype":"venue"
},
  "geometry": {"coordinates":[6.8812727928,51.4209022522],"type":"Point"}
}