{
  "type": "Feature",
  "properties": {
    "iso:country":"DE",
    "sg:address":"Im Birkeneck 13",
    "sg:city":"Heusenstamm",
    "sg:postcode":"63150",
    "sg:province":"Hessen",
    "wof:name":"Jeneric System Gmbh",
    "wof:placetype":"venue"
},
  "geometry": {"coordinates":[8.7928514481,50.0485992432],"type":"Point"}
}