{
  "type": "Feature",
  "properties": {
    "iso:country":"DE",
    "sg:address":"Daimlerstr. 3",
    "sg:city":"Massenbachhausen",
    "sg:phone":"+49 7138/943400",
    "sg:postcode":"74252",
    "sg:province":"Baden-W\u00fcrttemberg",
    "wof:name":"Wilfried Krau\u00df",
    "wof:placetype":"venue"
},
  "geometry": {"coordinates":[9.0433044434,49.1730651855],"type":"Point"}
}