{
  "type": "Feature",
  "properties": {
    "iso:country":"DE",
    "sg:address":"Alte Viehtrift 7",
    "sg:city":"Kurort Oberwiesenthal",
    "sg:phone":"+49 37348/8318",
    "sg:postcode":"09484",
    "sg:province":"Sachsen",
    "wof:name":"Detlef Bertz",
    "wof:placetype":"venue"
},
  "geometry": {"coordinates":[12.9815673828,50.4216423035],"type":"Point"}
}