{
  "type": "Feature",
  "properties": {
    "iso:country":"DE",
    "sg:address":"Klosterstra\u00dfe 30",
    "sg:city":"Erftstadt",
    "sg:postcode":"50374",
    "sg:province":"Nordrhein-Westfalen",
    "wof:name":"Firma Philip Collette",
    "wof:placetype":"venue"
},
  "geometry": {"coordinates":[6.7635798454,50.7977104187],"type":"Point"}
}