{
  "type": "Feature",
  "properties": {
    "iso:country":"DE",
    "sg:address":"Veilchenstr. 4",
    "sg:city":"Wagh\u00e4usel",
    "sg:phone":"+49 7254/73800",
    "sg:postcode":"68753",
    "sg:province":"Baden-W\u00fcrttemberg",
    "wof:name":"Erwin Schmalzhaf Masseur",
    "wof:placetype":"venue"
},
  "geometry": {"coordinates":[8.55287,49.239777],"type":"Point"}
}