{
  "type": "Feature",
  "properties": {
    "iso:country":"DE",
    "sg:address":"Am Mettenberg 23",
    "sg:city":"Burladingen",
    "sg:phone":"+49 7475/584",
    "sg:postcode":"72393",
    "sg:province":"Baden-W\u00fcrttemberg",
    "wof:name":"Horst Schultz Steuerberater",
    "wof:placetype":"venue"
},
  "geometry": {"coordinates":[9.1057796478,48.2970962524],"type":"Point"}
}