{
  "type": "Feature",
  "properties": {
    "iso:country":"DE",
    "sg:address":"K\u00f6lner Landstr. 304",
    "sg:city":"D\u00fcren",
    "sg:postcode":"52351",
    "sg:province":"Nordrhein-Westfalen",
    "wof:name":"Immobilien Hinz",
    "wof:placetype":"venue"
},
  "geometry": {"coordinates":[6.5119361877,50.8115463257],"type":"Point"}
}