{
  "type": "Feature",
  "properties": {
    "iso:country":"DE",
    "sg:address":"Stadthausstr. 4",
    "sg:city":"Bad Lausick",
    "sg:phone":"+49 34345/22449",
    "sg:postcode":"04651",
    "sg:province":"Sachsen",
    "wof:name":"J.g. Becker",
    "wof:placetype":"venue"
},
  "geometry": {"coordinates":[12.643032074,51.1446456909],"type":"Point"}
}