{
  "type": "Feature",
  "properties": {
    "iso:country":"DE",
    "sg:address":"Gro\u00dfhaderner Str. 46a",
    "sg:city":"M\u00fcnchen",
    "sg:phone":"+49 89/706878",
    "sg:postcode":"81375",
    "sg:province":"Bayern",
    "wof:name":"Redaktion Gemeinde-kurier Die Bayerische Gemeinde",
    "wof:placetype":"venue"
},
  "geometry": {"coordinates":[11.4817085266,48.1206932068],"type":"Point"}
}