{
  "type": "Feature",
  "properties": {
    "iso:country":"DE",
    "sg:address":"Eislebener Str. 57",
    "sg:city":"Chemnitz",
    "sg:phone":"+49 371/511851",
    "sg:postcode":"09126",
    "sg:province":"Sachsen",
    "wof:name":"Bernd Hesse",
    "wof:placetype":"venue"
},
  "geometry": {"coordinates":[12.9442901611,50.8056411743],"type":"Point"}
}