{
  "type": "Feature",
  "properties": {
    "iso:country":"DE",
    "sg:address":"Bahnhofstr. 43",
    "sg:city":"Burg",
    "sg:phone":"+49 4371/9840",
    "sg:postcode":"23769",
    "sg:province":"Schleswig-Holstein",
    "wof:name":"Dr. Med. Karola Balzer-joyce",
    "wof:placetype":"venue"
},
  "geometry": {"coordinates":[11.1936950684,54.4408988953],"type":"Point"}
}