{
  "type": "Feature",
  "properties": {
    "iso:country":"DE",
    "sg:address":"Schlo\u00dfmacherstr. 10",
    "sg:city":"Radevormwald",
    "sg:phone":"+49 2195/2827",
    "sg:postcode":"42477",
    "sg:province":"Nordrhein-Westfalen",
    "wof:name":"H. Fernholz",
    "wof:placetype":"venue"
},
  "geometry": {"coordinates":[7.359577,51.202175],"type":"Point"}
}