{
  "type": "Feature",
  "properties": {
    "iso:country":"DE",
    "sg:address":"B\u00fchlstr. 20",
    "sg:city":"Remshalden",
    "sg:phone":"+49 7151/907205",
    "sg:postcode":"73630",
    "sg:province":"Baden-W\u00fcrttemberg",
    "wof:name":"Aw Andere Werbung",
    "wof:placetype":"venue"
},
  "geometry": {"coordinates":[9.4169874191,48.8095664978],"type":"Point"}
}