{
  "type": "Feature",
  "properties": {
    "iso:country":"DE",
    "sg:address":"Etzelstr. 10",
    "sg:city":"Bietigheim-Bissingen",
    "sg:phone":"+49 7142/5830",
    "sg:postcode":"74321",
    "sg:province":"Baden-W\u00fcrttemberg",
    "wof:name":"Elring Klinger Kunststoff- Technik Gmbh",
    "wof:placetype":"venue"
},
  "geometry": {"coordinates":[9.134748,48.944084],"type":"Point"}
}