{
  "type": "Feature",
  "properties": {
    "iso:country":"DE",
    "sg:address":"Bergstr. 7",
    "sg:city":"Lorch",
    "sg:phone":"+49 7172/6794",
    "sg:postcode":"73547",
    "sg:province":"Baden-W\u00fcrttemberg",
    "wof:name":"Rudolf M\u00fcller Innenarchitekt",
    "wof:placetype":"venue"
},
  "geometry": {"coordinates":[9.687077,48.803707],"type":"Point"}
}