{
  "type": "Feature",
  "properties": {
    "iso:country":"DE",
    "sg:address":"Markt 13",
    "sg:city":"Heiligenhafen",
    "sg:phone":"+49 4362/900404",
    "sg:postcode":"23774",
    "sg:province":"Schleswig-Holstein",
    "wof:name":"Schuhhaus Otto Meier",
    "wof:placetype":"venue"
},
  "geometry": {"coordinates":[10.97884,54.372509],"type":"Point"}
}