{
  "type": "Feature",
  "properties": {
    "iso:country":"DE",
    "sg:address":"Kernerstr. 4",
    "sg:city":"Nagold",
    "sg:phone":"+49 7452/61413",
    "sg:postcode":"72202",
    "sg:province":"Baden-W\u00fcrttemberg",
    "wof:name":"U. Und D. Petrich",
    "wof:placetype":"venue"
},
  "geometry": {"coordinates":[8.723087,48.552063],"type":"Point"}
}