{
  "type": "Feature",
  "properties": {
    "iso:country":"DE",
    "sg:address":"Regerstr. 2",
    "sg:city":"Neumarkt",
    "sg:phone":"+49 9181/3300",
    "sg:postcode":"92318",
    "sg:province":"Bayern",
    "wof:name":"Fritz Berger Gmbh & Co. Kg",
    "wof:placetype":"venue"
},
  "geometry": {"coordinates":[11.478563,49.293812],"type":"Point"}
}