{
  "type": "Feature",
  "properties": {
    "iso:country":"DE",
    "sg:address":"In der H\u00fcttenwiese 30",
    "sg:city":"Siegen",
    "sg:phone":"+49 271/46122",
    "sg:postcode":"57072",
    "sg:province":"Nordrhein-Westfalen",
    "wof:name":"Kurt Andrick",
    "wof:placetype":"venue"
},
  "geometry": {"coordinates":[8.025583,50.887043],"type":"Point"}
}