{
  "type": "Feature",
  "properties": {
    "iso:country":"DE",
    "sg:address":"Industriestr. 5 B",
    "sg:city":"Boostedt",
    "sg:phone":"+49 4393/972241",
    "sg:postcode":"24598",
    "sg:province":"Schleswig-Holstein",
    "wof:name":"Ralf Nickelsen Steuerberater",
    "wof:placetype":"venue"
},
  "geometry": {"coordinates":[10.01704216,54.0215072632],"type":"Point"}
}