{
  "type": "Feature",
  "properties": {
    "iso:country":"DE",
    "sg:address":"Waidhauser Str. 7",
    "sg:city":"Vohenstrau\u00df",
    "sg:phone":"+49 9651/2041",
    "sg:postcode":"92648",
    "sg:province":"Bayern",
    "wof:name":"Otto Wiedermann",
    "wof:placetype":"venue"
},
  "geometry": {"coordinates":[12.343576,49.621471],"type":"Point"}
}