{
  "type": "Feature",
  "properties": {
    "iso:country":"DE",
    "sg:address":"Blumachergasse 2",
    "sg:city":"Pulheim",
    "sg:phone":"+49 2238/51120",
    "sg:postcode":"50259",
    "sg:province":"Nordrhein-Westfalen",
    "wof:name":"Spielkisten Automaten- Aufstellungs Gmbh",
    "wof:placetype":"venue"
},
  "geometry": {"coordinates":[6.8032917976,50.9978561401],"type":"Point"}
}