{
  "type": "Feature",
  "properties": {
    "iso:country":"DE",
    "sg:address":"Ursulagartenstr. 30",
    "sg:city":"K\u00f6ln",
    "sg:phone":"+49 221/131181",
    "sg:postcode":"50668",
    "sg:province":"Nordrhein-Westfalen",
    "wof:name":"Ahl Malerwerkst\u00e4tte Gmbh",
    "wof:placetype":"venue"
},
  "geometry": {"coordinates":[6.954298,50.946655],"type":"Point"}
}