{
  "type": "Feature",
  "properties": {
    "iso:country":"DE",
    "sg:address":"Neuberinstra\u00dfe 1",
    "sg:city":"Dresden",
    "sg:phone":"+49 351/2501544",
    "sg:postcode":"01279",
    "sg:province":"Sachsen",
    "wof:name":"Sanit\u00e4r Peter Zill",
    "wof:placetype":"venue"
},
  "geometry": {"coordinates":[13.8366670609,51.0263786316],"type":"Point"}
}