{
  "type": "Feature",
  "properties": {
    "iso:country":"DE",
    "sg:address":"Niedersachsendamm 11",
    "sg:city":"Bremen",
    "sg:postcode":"28277",
    "sg:province":"Bremen",
    "wof:name":"Dhw Transport & Trading Beteiligungs Gmbh",
    "wof:placetype":"venue"
},
  "geometry": {"coordinates":[8.82063,53.049942],"type":"Point"}
}