{
  "type": "Feature",
  "properties": {
    "iso:country":"DE",
    "sg:address":"Leutewitzer Str. 14",
    "sg:city":"Leutewitz",
    "sg:postcode":"01594",
    "sg:province":"Sachsen",
    "wof:name":"Dr. Hermann Ro\u00dfberg",
    "wof:placetype":"venue"
},
  "geometry": {"coordinates":[13.3756132126,51.2927055359],"type":"Point"}
}