{
  "type": "Feature",
  "properties": {
    "iso:country":"DE",
    "sg:address":"Obere Marktstr. 1",
    "sg:city":"Stadtilm",
    "sg:phone":"+49 3629/802219",
    "sg:postcode":"99326",
    "sg:province":"Th\u00fcringen",
    "wof:name":"Roland Meinhardt",
    "wof:placetype":"venue"
},
  "geometry": {"coordinates":[11.079162,50.773602],"type":"Point"}
}