{
  "type": "Feature",
  "properties": {
    "iso:country":"DE",
    "sg:address":"Armgartstr. 2",
    "sg:city":"Hamburg",
    "sg:phone":"+49 40/2269200",
    "sg:postcode":"22087",
    "sg:province":"Hamburg",
    "wof:name":"Artline Agency Werbeagentur Gmbh",
    "wof:placetype":"venue"
},
  "geometry": {"coordinates":[10.017275,53.565002],"type":"Point"}
}