{
  "type": "Feature",
  "properties": {
    "iso:country":"DE",
    "sg:address":"Stiller Winkel 3",
    "sg:city":"Pratau",
    "sg:phone":"+49 3491/412129",
    "sg:postcode":"06888",
    "sg:province":"Sachsen-Anhalt",
    "wof:name":"G. Begoin",
    "wof:placetype":"venue"
},
  "geometry": {"coordinates":[-73.358521,41.141499],"type":"Point"}
}