{
  "type": "Feature",
  "properties": {
    "iso:country":"DE",
    "sg:address":"Bahnhofstrasse 11::",
    "sg:city":"Nordhorn",
    "sg:phone":"+49 5441/910",
    "sg:postcode":"48529",
    "sg:province":"Niedersachsen",
    "wof:name":"Kreissparkasse Grafschaft Diepholz",
    "wof:placetype":"venue"
},
  "geometry": {"coordinates":[8.369545,52.609371],"type":"Point"}
}