{
  "type": "Feature",
  "properties": {
    "iso:country":"DE",
    "sg:address":"Lessingstr. 4",
    "sg:city":"Lohne",
    "sg:phone":"+49 4442/1598",
    "sg:postcode":"49393",
    "sg:province":"Niedersachsen",
    "wof:name":"Wieferig Und Hinxlage Landwirtschaftliche Gmbh",
    "wof:placetype":"venue"
},
  "geometry": {"coordinates":[8.235788,52.656971],"type":"Point"}
}