{
  "type": "Feature",
  "properties": {
    "iso:country":"DE",
    "sg:address":"Donaustr. 42",
    "sg:city":"Tuttlingen",
    "sg:phone":"+49 7461/3454",
    "sg:postcode":"78532",
    "sg:province":"Baden-W\u00fcrttemberg",
    "wof:name":"La Vie",
    "wof:placetype":"venue"
},
  "geometry": {"coordinates":[8.8172073364,47.9849777222],"type":"Point"}
}