{
  "type": "Feature",
  "properties": {
    "iso:country":"DE",
    "sg:address":"K\u00e4lbersteinstr. 4",
    "sg:city":"Berchtesgaden",
    "sg:phone":"+49 8652/61449",
    "sg:postcode":"83471",
    "sg:province":"Bayern",
    "wof:name":"Pizzeria Da Noi",
    "wof:placetype":"venue"
},
  "geometry": {"coordinates":[12.9938116074,47.6287841797],"type":"Point"}
}