{
  "type": "Feature",
  "properties": {
    "iso:country":"DE",
    "sg:address":"Senckenbergstr. 17 und 25",
    "sg:city":"Gie\u00dfen",
    "sg:phone":"+49 641/7028450",
    "sg:postcode":"35390",
    "sg:province":"Hessen",
    "wof:name":"Institut F\u00fcr Allgemeine Botanik Und Planzenphysiologie",
    "wof:placetype":"venue"
},
  "geometry": {"coordinates":[8.676334,50.586613],"type":"Point"}
}