{
  "type": "Feature",
  "properties": {
    "iso:country":"DE",
    "sg:address":"Kurbrunnenstr. 8",
    "sg:city":"Aachen",
    "sg:phone":"+49 241/5090658",
    "sg:postcode":"52066",
    "sg:province":"Nordrhein-Westfalen",
    "wof:name":"Hamacher Beschl\u00c4ge",
    "wof:placetype":"venue"
},
  "geometry": {"coordinates":[6.0977978706,50.7664489746],"type":"Point"}
}