{
  "type": "Feature",
  "properties": {
    "iso:country":"DE",
    "sg:address":"Am Vogelsang 10",
    "sg:city":"Niedenstein",
    "sg:phone":"+49 5624/6158",
    "sg:postcode":"34305",
    "sg:province":"Hessen",
    "wof:name":"D. U. U. Zilch",
    "wof:placetype":"venue"
},
  "geometry": {"coordinates":[9.3174381256,51.2309303284],"type":"Point"}
}