{
  "type": "Feature",
  "properties": {
    "iso:country":"DE",
    "sg:address":"Kochstr. 22-23",
    "sg:city":"Berlin",
    "sg:phone":"+49 30/25340",
    "sg:postcode":"10969",
    "sg:province":"Berlin",
    "wof:name":"Gsw Verwaltungs- Und Betriebs Gmbh & Co. Erste",
    "wof:placetype":"venue"
},
  "geometry": {"coordinates":[13.3885059357,52.5067253113],"type":"Point"}
}