{
  "type": "Feature",
  "properties": {
    "iso:country":"DE",
    "sg:address":"Tanzlaube 1",
    "sg:city":"Giengen",
    "sg:phone":"+49 7322/7352",
    "sg:postcode":"89537",
    "sg:province":"Baden-W\u00fcrttemberg",
    "wof:name":"Ev. Pfarramt I",
    "wof:placetype":"venue"
},
  "geometry": {"coordinates":[10.2426013947,48.6217498779],"type":"Point"}
}