{
  "type": "Feature",
  "properties": {
    "iso:country":"DE",
    "sg:address":"Schillerstr. 25",
    "sg:city":"Koblenz",
    "sg:postcode":"56075",
    "sg:province":"Rheinland-Pfalz",
    "wof:name":"Katholischer Leseverein E. V.",
    "wof:placetype":"venue"
},
  "geometry": {"coordinates":[7.5909781456,50.3377685547],"type":"Point"}
}