{
  "type": "Feature",
  "properties": {
    "iso:country":"DE",
    "sg:address":"Passauer Str. 8",
    "sg:city":"Breitenberg",
    "sg:phone":"+49 8584/91220",
    "sg:postcode":"94139",
    "sg:province":"Bayern",
    "wof:name":"Heilig-geist-apotheke Dr. Birgit Schr\u00f6ger",
    "wof:placetype":"venue"
},
  "geometry": {"coordinates":[13.79188,48.702106],"type":"Point"}
}