{
  "type": "Feature",
  "properties": {
    "iso:country":"DE",
    "sg:address":"Berner Heerweg 159",
    "sg:city":"Hamburg",
    "sg:phone":"+49 40/6432270",
    "sg:postcode":"22159",
    "sg:province":"Hamburg",
    "wof:name":"Anneliese Bengsch Krankengymnastin",
    "wof:placetype":"venue"
},
  "geometry": {"coordinates":[10.118943,53.604706],"type":"Point"}
}