{
  "type": "Feature",
  "properties": {
    "iso:country":"DE",
    "sg:address":"Baaderstr. 74",
    "sg:city":"M\u00fcnchen",
    "sg:phone":"+49 89/2012909",
    "sg:postcode":"80469",
    "sg:province":"Bayern",
    "wof:name":"Neue Glucksche Compagney Gmbh",
    "wof:placetype":"venue"
},
  "geometry": {"coordinates":[11.5761861801,48.1287765503],"type":"Point"}
}