{
  "type": "Feature",
  "properties": {
    "iso:country":"DE",
    "sg:address":"Industriestr. 1",
    "sg:city":"Moringen",
    "sg:phone":"+49 5554/8153",
    "sg:postcode":"37186",
    "sg:province":"Niedersachsen",
    "wof:name":"Pizzeria Italia",
    "wof:placetype":"venue"
},
  "geometry": {"coordinates":[9.8703250885,51.6900596619],"type":"Point"}
}