{
  "type": "Feature",
  "properties": {
    "iso:country":"DE",
    "sg:address":"Fautenbacher Str. 28",
    "sg:city":"Achern",
    "sg:phone":"+49 7841/26332",
    "sg:postcode":"77855",
    "sg:province":"Baden-W\u00fcrttemberg",
    "wof:name":"Feldschl\u00f6\u00dfchen",
    "wof:placetype":"venue"
},
  "geometry": {"coordinates":[8.0615701675,48.6282501221],"type":"Point"}
}