{
  "type": "Feature",
  "properties": {
    "iso:country":"DE",
    "sg:address":"Friedrich-Engels-Str. 10",
    "sg:city":"Brandenburg",
    "sg:phone":"+49 3381/660135",
    "sg:postcode":"14770",
    "sg:province":"Brandenburg",
    "wof:name":"Kurt Klopsch Ingenieur",
    "wof:placetype":"venue"
},
  "geometry": {"coordinates":[12.5085706711,52.3951416016],"type":"Point"}
}