{
  "type": "Feature",
  "properties": {
    "iso:country":"DE",
    "sg:address":"M\u00fchlweg 1",
    "sg:city":"Gaggenau",
    "sg:phone":"+49 7225/3428",
    "sg:postcode":"76571",
    "sg:province":"Baden-W\u00fcrttemberg",
    "wof:name":"Mechler & Schimmer Inh. Kurt Holfelder",
    "wof:placetype":"venue"
},
  "geometry": {"coordinates":[8.3083095551,48.8117179871],"type":"Point"}
}