{
  "type": "Feature",
  "properties": {
    "iso:country":"DE",
    "sg:address":"Im Gartenfeld 3",
    "sg:city":"Morbach",
    "sg:phone":"+49 6533/3589",
    "sg:postcode":"54497",
    "sg:province":"Rheinland-Pfalz",
    "wof:name":"J. Reuter",
    "wof:placetype":"venue"
},
  "geometry": {"coordinates":[7.118588,49.810802],"type":"Point"}
}