{
  "type": "Feature",
  "properties": {
    "iso:country":"DE",
    "sg:address":"Remchinger Str. 83",
    "sg:city":"Karlsbad",
    "sg:phone":"+49 7202/941860",
    "sg:postcode":"76307",
    "sg:province":"Baden-W\u00fcrttemberg",
    "wof:name":"Achim Schwab",
    "wof:placetype":"venue"
},
  "geometry": {"coordinates":[8.5308065414,48.9129295349],"type":"Point"}
}