{
  "type": "Feature",
  "properties": {
    "iso:country":"DE",
    "sg:address":"Bergwerkstr. 14",
    "sg:city":"Pei\u00dfenberg",
    "sg:phone":"+49 170 9028357",
    "sg:postcode":"82380",
    "sg:province":"Bayern",
    "wof:name":"Pei\u00dfenberger Kraftwerks- Gesellschaft Mbh Pkg",
    "wof:placetype":"venue"
},
  "geometry": {"coordinates":[11.058721,47.790997],"type":"Point"}
}