{
  "type": "Feature",
  "properties": {
    "iso:country":"DE",
    "sg:address":"Krefelder Str. 9",
    "sg:city":"Meerbusch",
    "sg:phone":"+49 2159/1528",
    "sg:postcode":"40670",
    "sg:province":"Nordrhein-Westfalen",
    "wof:name":"J. Seerden",
    "wof:placetype":"venue"
},
  "geometry": {"coordinates":[6.621727,51.272079],"type":"Point"}
}