{
  "type": "Feature",
  "properties": {
    "iso:country":"DE",
    "sg:address":"Otto-Brenner-Str 202",
    "sg:city":"Bielefeld",
    "sg:phone":"+49 521/295090",
    "sg:postcode":"33604",
    "sg:province":"Nordrhein-Westfalen",
    "wof:name":"Orthop\u00e4die-technik Inh. Achim Stuke",
    "wof:placetype":"venue"
},
  "geometry": {"coordinates":[8.560395,52.007458],"type":"Point"}
}