{
  "type": "Feature",
  "properties": {
    "iso:country":"DE",
    "sg:address":"Dresdener Str. 13",
    "sg:city":"Lutherstadt Wittenberg",
    "sg:phone":"+49 3491/400626",
    "sg:postcode":"06886",
    "sg:province":"Sachsen-Anhalt",
    "wof:name":"Siegfried Lehmann",
    "wof:placetype":"venue"
},
  "geometry": {"coordinates":[12.6711874008,51.8640785217],"type":"Point"}
}