{
  "type": "Feature",
  "properties": {
    "iso:country":"DE",
    "sg:address":"Auenstr. 5",
    "sg:city":"Suhl",
    "sg:phone":"+49 3681/711790",
    "sg:postcode":"98529",
    "sg:province":"Th\u00fcringen",
    "wof:name":"Tlg Immobiliendienstleistungen Jus Gmbh",
    "wof:placetype":"venue"
},
  "geometry": {"coordinates":[10.6836948395,50.6091270447],"type":"Point"}
}