{
  "type": "Feature",
  "properties": {
    "iso:country":"DE",
    "sg:address":"Am Damm 6",
    "sg:city":"Wismar",
    "sg:phone":"+49 3841/2653100",
    "sg:postcode":"23970",
    "sg:province":"Mecklenburg-Vorpommern",
    "wof:name":"Elektro Nass Gmbh",
    "wof:placetype":"venue"
},
  "geometry": {"coordinates":[11.4822912216,53.9222602844],"type":"Point"}
}