{
  "type": "Feature",
  "properties": {
    "iso:country":"DE",
    "sg:address":"Zum Ortenbrink 29",
    "sg:city":"Hasbergen",
    "sg:phone":"+49 5405",
    "sg:postcode":"49205",
    "sg:province":"Niedersachsen",
    "wof:name":"Konsequent",
    "wof:placetype":"venue"
},
  "geometry": {"coordinates":[7.96712,52.235367],"type":"Point"}
}