{
  "type": "Feature",
  "properties": {
    "iso:country":"DE",
    "sg:address":"Mieckower Weg 1",
    "sg:city":"Teterow",
    "sg:phone":"+49 3996/172935",
    "sg:postcode":"17166",
    "sg:province":"Mecklenburg-Vorpommern",
    "wof:name":"Mc Bergring Teterow E. V. Im Admv Gesch\u00e4ftsstelle",
    "wof:placetype":"venue"
},
  "geometry": {"coordinates":[12.5662174225,53.7798233032],"type":"Point"}
}