{
  "type": "Feature",
  "properties": {
    "iso:country":"DE",
    "sg:address":"Feldbergstr. 26",
    "sg:city":"Aidlingen",
    "sg:phone":"+49 7034/4766",
    "sg:postcode":"71134",
    "sg:province":"Baden-W\u00fcrttemberg",
    "wof:name":"Sonnenberghalle Aidlingen Mehrzweckhalle",
    "wof:placetype":"venue"
},
  "geometry": {"coordinates":[8.894914,48.681747],"type":"Point"}
}