{
  "type": "Feature",
  "properties": {
    "iso:country":"DE",
    "sg:address":"Bahnhofstr. 19",
    "sg:city":"Welden",
    "sg:phone":"+49 8293/909938",
    "sg:postcode":"86465",
    "sg:province":"Bayern",
    "wof:name":"Cafe Extra Blatt",
    "wof:placetype":"venue"
},
  "geometry": {"coordinates":[10.660678,48.454815],"type":"Point"}
}