{
  "type": "Feature",
  "properties": {
    "iso:country":"DE",
    "sg:address":"Rutsch 2",
    "sg:city":"Hamburg",
    "sg:phone":"+49 40/865007",
    "sg:postcode":"22587",
    "sg:province":"Hamburg",
    "wof:name":"Galerie Pro Arte Justus & Partner Ohg",
    "wof:placetype":"venue"
},
  "geometry": {"coordinates":[9.798385,53.558525],"type":"Point"}
}