{
  "type": "Feature",
  "properties": {
    "iso:country":"DE",
    "sg:address":"Linderner Str.",
    "sg:city":"L\u00f6ningen",
    "sg:phone":"+49 5432/2635",
    "sg:postcode":"49624",
    "sg:province":"Niedersachsen",
    "wof:name":"A. L\u00fcbbers",
    "wof:placetype":"venue"
},
  "geometry": {"coordinates":[7.756933,52.737076],"type":"Point"}
}