{
  "type": "Feature",
  "properties": {
    "iso:country":"DE",
    "sg:address":"August-Kallert-Str. 11",
    "sg:city":"Dachau",
    "sg:phone":"+49 8131/80930",
    "sg:postcode":"85221",
    "sg:province":"Bayern",
    "wof:name":"Robert Kernlinger Gmbh",
    "wof:placetype":"venue"
},
  "geometry": {"coordinates":[11.4266700745,48.2507705688],"type":"Point"}
}