{
  "type": "Feature",
  "properties": {
    "iso:country":"DE",
    "sg:address":"Karlsbader Str. 18",
    "sg:city":"Berlin",
    "sg:phone":"+49 30/8957400",
    "sg:postcode":"14193",
    "sg:province":"Berlin",
    "wof:name":"Hapag-lloyd Reiseb\u00fcro",
    "wof:placetype":"venue"
},
  "geometry": {"coordinates":[13.2821445465,52.4782600403],"type":"Point"}
}