{
  "type": "Feature",
  "properties": {
    "iso:country":"DE",
    "sg:address":"Gutenbergstr. 27",
    "sg:city":"G\u00f6ttingen",
    "sg:postcode":"37075",
    "sg:province":"Niedersachsen",
    "wof:name":"Wiss. Institut Abt. F\u00fcr Arbeitswissenschaft",
    "wof:placetype":"venue"
},
  "geometry": {"coordinates":[9.9496431351,51.5468177795],"type":"Point"}
}