{
  "type": "Feature",
  "properties": {
    "iso:country":"DE",
    "sg:address":"Friedrich-Ebert-Anlage 49",
    "sg:city":"Frankfurt",
    "sg:postcode":"60308",
    "sg:province":"Hessen",
    "wof:name":"Solar Rex Solartechnische Anlagen Und Systeme Gmbh",
    "wof:placetype":"venue"
},
  "geometry": {"coordinates":[8.654101,50.112076],"type":"Point"}
}