{
  "type": "Feature",
  "properties": {
    "iso:country":"DE",
    "sg:address":"K\u00fcppersbuschstr. 80",
    "sg:city":"Gelsenkirchen",
    "sg:phone":"+49 209/41580",
    "sg:postcode":"45883",
    "sg:province":"Nordrhein-Westfalen",
    "wof:name":"Peter Knebel Steuerberater",
    "wof:placetype":"venue"
},
  "geometry": {"coordinates":[7.0795888901,51.5089912415],"type":"Point"}
}