{
  "type": "Feature",
  "properties": {
    "iso:country":"DE",
    "sg:address":"Karinstr. 28",
    "sg:city":"Neuenhaus",
    "sg:phone":"+49 5941/8780",
    "sg:postcode":"49828",
    "sg:province":"Niedersachsen",
    "wof:name":"Wilfried J\u00e4kel Architekt",
    "wof:placetype":"venue"
},
  "geometry": {"coordinates":[7.002455,52.522377],"type":"Point"}
}