{
  "type": "Feature",
  "properties": {
    "iso:country":"DE",
    "sg:address":"Br\u00fcsseler Str. 2e",
    "sg:city":"Bad Bentheim",
    "sg:phone":"+49 5924/8122",
    "sg:postcode":"48455",
    "sg:province":"Niedersachsen",
    "wof:name":"Prg Rohrleitungssysteme Gmbh",
    "wof:placetype":"venue"
},
  "geometry": {"coordinates":[7.0653600693,52.3205986023],"type":"Point"}
}