{
  "type": "Feature",
  "properties": {
    "iso:country":"DE",
    "sg:address":"Vollungstr 20",
    "sg:city":"Pulsnitz",
    "sg:phone":"+49 35955/74660",
    "sg:postcode":"01896",
    "sg:province":"Sachsen",
    "wof:name":"Meditech Maik Lange",
    "wof:placetype":"venue"
},
  "geometry": {"coordinates":[14.00936,51.175091],"type":"Point"}
}