{
  "type": "Feature",
  "properties": {
    "iso:country":"DE",
    "sg:address":"Godewindweg 8",
    "sg:city":"Elmshorn",
    "sg:phone":"+49 4121/61836",
    "sg:postcode":"25336",
    "sg:province":"Schleswig-Holstein",
    "wof:name":"Werner Pezold Architekt",
    "wof:placetype":"venue"
},
  "geometry": {"coordinates":[9.651533,53.745735],"type":"Point"}
}