{
  "type": "Feature",
  "properties": {
    "iso:country":"DE",
    "sg:address":"Schulstr. 3",
    "sg:city":"Filderstadt",
    "sg:phone":"+49 711/7776489",
    "sg:postcode":"70794",
    "sg:province":"Baden-W\u00fcrttemberg",
    "wof:name":"Ambulante Hauskrankenpflege Lieke De Jong",
    "wof:placetype":"venue"
},
  "geometry": {"coordinates":[9.198152,48.653854],"type":"Point"}
}