{
  "type": "Feature",
  "properties": {
    "iso:country":"DE",
    "sg:address":"Soester Str. 40",
    "sg:city":"Hamburg",
    "sg:phone":"+49 40/244965",
    "sg:postcode":"20099",
    "sg:province":"Hamburg",
    "wof:name":"Mahtabi & Co.",
    "wof:placetype":"venue"
},
  "geometry": {"coordinates":[10.0112390518,53.5563850403],"type":"Point"}
}