{
  "type": "Feature",
  "properties": {
    "iso:country":"DE",
    "sg:address":"Goethestra\u00dfe 33",
    "sg:city":"Stockach",
    "sg:phone":"+49 7773",
    "sg:postcode":"78333",
    "sg:province":"Baden-W\u00fcrttemberg",
    "wof:name":"Axel Trippe Office Center Bodensee / Stockach",
    "wof:placetype":"venue"
},
  "geometry": {"coordinates":[9.0058813095,47.8479614258],"type":"Point"}
}