{
  "type": "Feature",
  "properties": {
    "iso:country":"DE",
    "sg:address":"Landkirchener Weg 22",
    "sg:city":"Burg",
    "sg:phone":"+49 4371/3921",
    "sg:postcode":"23769",
    "sg:province":"Schleswig-Holstein",
    "wof:name":"E. H\u00f6ch Grabdenkm\u00e4ler",
    "wof:placetype":"venue"
},
  "geometry": {"coordinates":[11.1852617264,54.4420967102],"type":"Point"}
}