{
  "type": "Feature",
  "properties": {
    "iso:country":"DE",
    "sg:address":"Gutsstr. 3",
    "sg:city":"K\u00fchnhausen",
    "sg:phone":"+49 36201/7044",
    "sg:postcode":"99189",
    "sg:province":"Th\u00fcringen",
    "wof:name":"R. John",
    "wof:placetype":"venue"
},
  "geometry": {"coordinates":[10.9708118439,51.0348320007],"type":"Point"}
}