{
  "type": "Feature",
  "properties": {
    "iso:country":"DE",
    "sg:address":"Pankstr. 48",
    "sg:city":"Berlin",
    "sg:phone":"+49 30/4621643",
    "sg:postcode":"13357",
    "sg:province":"Berlin",
    "wof:name":"Tomic & Tomic Bau Gmbh",
    "wof:placetype":"venue"
},
  "geometry": {"coordinates":[13.380345,52.551361],"type":"Point"}
}