{
  "type": "Feature",
  "properties": {
    "iso:country":"DE",
    "sg:address":"Lengede",
    "sg:city":"Lengede",
    "sg:phone":"+49 5174/336",
    "sg:postcode":"38268",
    "sg:province":"Niedersachsen",
    "wof:name":"Volksbank Lahstedt Eg",
    "wof:placetype":"venue"
},
  "geometry": {"coordinates":[10.30883,52.210468],"type":"Point"}
}