{
  "type": "Feature",
  "properties": {
    "iso:country":"DE",
    "sg:address":"Nu\u00dfbaumstr. 5 a",
    "sg:city":"H\u00f6slwang",
    "sg:phone":"+49 8055/635",
    "sg:postcode":"83129",
    "sg:province":"Bayern",
    "wof:name":"Herbert Hunger",
    "wof:placetype":"venue"
},
  "geometry": {"coordinates":[12.33416,47.957165],"type":"Point"}
}