{
  "type": "Feature",
  "properties": {
    "iso:country":"DE",
    "sg:address":"Schkeuditzer Str.9",
    "sg:city":"Markranst\u00e4dt",
    "sg:phone":"+49 34205",
    "sg:postcode":"04420",
    "sg:province":"Sachsen",
    "wof:name":"Farben Hoffmann",
    "wof:placetype":"venue"
},
  "geometry": {"coordinates":[12.2195329666,51.301940918],"type":"Point"}
}