{
  "type": "Feature",
  "properties": {
    "iso:country":"DE",
    "sg:address":"H\u00fcterweg 6",
    "sg:city":"Pfaffenhofen",
    "sg:postcode":"85235",
    "sg:province":"Bayern",
    "wof:name":"A Company Elektronik Vertrieb Gmbh",
    "wof:placetype":"venue"
},
  "geometry": {"coordinates":[11.165503,48.29512],"type":"Point"}
}