{
  "type": "Feature",
  "properties": {
    "iso:country":"DE",
    "sg:address":"Altmarkt 3",
    "sg:city":"Plauen",
    "sg:phone":"+49 3741/155160",
    "sg:postcode":"08523",
    "sg:province":"Sachsen",
    "wof:name":"Dr. Von Mammen Und Heun Rechtsanw\u00e4lte Und",
    "wof:placetype":"venue"
},
  "geometry": {"coordinates":[12.1357097626,50.4938850403],"type":"Point"}
}