{
  "type": "Feature",
  "properties": {
    "iso:country":"DE",
    "sg:address":"L\u00fctzenkirchener Str. 86",
    "sg:city":"Leverkusen",
    "sg:phone":"+49 2171/81303",
    "sg:postcode":"51381",
    "sg:province":"Nordrhein-Westfalen",
    "wof:name":"Gaffel-stube",
    "wof:placetype":"venue"
},
  "geometry": {"coordinates":[7.0185499191,51.0670852661],"type":"Point"}
}