{
  "type": "Feature",
  "properties": {
    "iso:country":"DE",
    "sg:address":"Lornsenstr. 111 d",
    "sg:city":"Schenefeld",
    "sg:phone":"+49 40/8307958",
    "sg:postcode":"22869",
    "sg:province":"Schleswig-Holstein",
    "wof:name":"Croques Und Crepes",
    "wof:placetype":"venue"
},
  "geometry": {"coordinates":[9.8403110504,53.6077613831],"type":"Point"}
}