{
  "type": "Feature",
  "properties": {
    "iso:country":"DE",
    "sg:address":"W\u00fcrttemberger Str. 26",
    "sg:city":"Rottweil",
    "sg:phone":"+49 741/23761",
    "sg:postcode":"78628",
    "sg:province":"Baden-W\u00fcrttemberg",
    "wof:name":"K. Und C. Viereck",
    "wof:placetype":"venue"
},
  "geometry": {"coordinates":[8.6551990509,48.1617240906],"type":"Point"}
}