{
  "type": "Feature",
  "properties": {
    "iso:country":"DE",
    "sg:address":"Franz-Lehar-Str. 10",
    "sg:city":"Vaterstetten",
    "sg:phone":"+49 8106/303384",
    "sg:postcode":"85591",
    "sg:province":"Bayern",
    "wof:name":"Josef Bichlmaier Gmbh",
    "wof:placetype":"venue"
},
  "geometry": {"coordinates":[11.7807731628,48.1052932739],"type":"Point"}
}