{
  "type": "Feature",
  "properties": {
    "iso:country":"DE",
    "sg:address":"Eugenstr. 18",
    "sg:city":"G\u00f6ppingen",
    "sg:phone":"+49 7161/26826",
    "sg:postcode":"73033",
    "sg:province":"Baden-W\u00fcrttemberg",
    "wof:name":"Hans-p. Grell Architekt",
    "wof:placetype":"venue"
},
  "geometry": {"coordinates":[9.642741,48.709019],"type":"Point"}
}