{
  "type": "Feature",
  "properties": {
    "iso:country":"DE",
    "sg:address":"Lorkenh\u00f6he 17 a",
    "sg:city":"Overath",
    "sg:phone":"+49 2206/3516",
    "sg:postcode":"51491",
    "sg:province":"Nordrhein-Westfalen",
    "wof:name":"Johannes Stinn",
    "wof:placetype":"venue"
},
  "geometry": {"coordinates":[7.357324,50.937462],"type":"Point"}
}