{
  "type": "Feature",
  "properties": {
    "iso:country":"DE",
    "sg:address":"Bismarckstr. 2",
    "sg:city":"Nidda",
    "sg:phone":"+49 6043/6027",
    "sg:postcode":"63667",
    "sg:province":"Hessen",
    "wof:name":"Budde Und Pedain Rechtsanwalt Und Notar",
    "wof:placetype":"venue"
},
  "geometry": {"coordinates":[9.0087270737,50.4172935486],"type":"Point"}
}