{
  "type": "Feature",
  "properties": {
    "iso:country":"DE",
    "sg:address":"Hans-B\u00f6ckler-Str. 205",
    "sg:city":"Wuppertal",
    "sg:phone":"+49 202/759791",
    "sg:postcode":"42109",
    "sg:province":"Nordrhein-Westfalen",
    "wof:name":"Europ\u00e4ische Teppichgem. F\u00fcr Deutschland",
    "wof:placetype":"venue"
},
  "geometry": {"coordinates":[7.1508789062,51.2830047607],"type":"Point"}
}