{
  "type": "Feature",
  "properties": {
    "iso:country":"DE",
    "sg:address":"Kaiserstr. 3",
    "sg:city":"Reutlingen",
    "sg:phone":"+49 7121/17056",
    "sg:postcode":"72764",
    "sg:province":"Baden-W\u00fcrttemberg",
    "wof:name":"Hotel W\u00fcrttemberger Hof",
    "wof:placetype":"venue"
},
  "geometry": {"coordinates":[9.2110214233,48.4966316223],"type":"Point"}
}