{
  "type": "Feature",
  "properties": {
    "iso:country":"DE",
    "sg:address":"Karl-Marx-Str. 21",
    "sg:city":"Thale",
    "sg:phone":"+49 3947/63880",
    "sg:postcode":"06502",
    "sg:province":"Sachsen-Anhalt",
    "wof:name":"Norbert Bendix",
    "wof:placetype":"venue"
},
  "geometry": {"coordinates":[11.0344762802,51.749080658],"type":"Point"}
}