{
  "type": "Feature",
  "properties": {
    "iso:country":"DE",
    "sg:address":"Bruchstr. 41",
    "sg:city":"Angern",
    "sg:phone":"+49 39363/359",
    "sg:postcode":"39326",
    "sg:province":"Sachsen-Anhalt",
    "wof:name":"Siegfried Baum",
    "wof:placetype":"venue"
},
  "geometry": {"coordinates":[11.72561,52.358692],"type":"Point"}
}