{
  "type": "Feature",
  "properties": {
    "iso:country":"DE",
    "sg:address":"Stra\u00dfe des Friedens 39a",
    "sg:city":"Karst\u00e4dt",
    "sg:postcode":"19357",
    "sg:province":"Brandenburg",
    "wof:name":"Ev.-lutherische Kirche",
    "wof:placetype":"venue"
},
  "geometry": {"coordinates":[11.7481031418,53.1559181213],"type":"Point"}
}