{
  "type": "Feature",
  "properties": {
    "iso:country":"DE",
    "sg:address":"Gro\u00dfer Kamp 11",
    "sg:city":"Fintel",
    "sg:phone":"+49 4265/94101",
    "sg:postcode":"27389",
    "sg:province":"Niedersachsen",
    "wof:name":"Pe-spezialbau G\u00fcnter Hackensohn Gmbh",
    "wof:placetype":"venue"
},
  "geometry": {"coordinates":[9.670484,53.164646],"type":"Point"}
}