{
  "type": "Feature",
  "properties": {
    "iso:country":"DE",
    "sg:address":"Remlingstr. 83",
    "sg:city":"Speyer",
    "sg:postcode":"67346",
    "sg:province":"Rheinland-Pfalz",
    "wof:name":"Karmelittinenkloster Maria Mutter Der Kirche",
    "wof:placetype":"venue"
},
  "geometry": {"coordinates":[8.4331502914,49.306060791],"type":"Point"}
}