{
  "type": "Feature",
  "properties": {
    "iso:country":"DE",
    "sg:address":"Born 42",
    "sg:city":"Br\u00fcggen",
    "sg:phone":"+49 2163/5510",
    "sg:postcode":"41379",
    "sg:province":"Nordrhein-Westfalen",
    "wof:name":"Kehren",
    "wof:placetype":"venue"
},
  "geometry": {"coordinates":[6.2114210129,51.2430381775],"type":"Point"}
}