{
  "type": "Feature",
  "properties": {
    "iso:country":"DE",
    "sg:address":"Kaiserstr. 26",
    "sg:city":"St. Ingbert",
    "sg:phone":"+49 6894/2712",
    "sg:postcode":"66386",
    "sg:province":"Saarland",
    "wof:name":"Helga Ramke",
    "wof:placetype":"venue"
},
  "geometry": {"coordinates":[7.113895,49.277],"type":"Point"}
}