{
  "type": "Feature",
  "properties": {
    "iso:country":"DE",
    "sg:address":"Pannenm\u00fchle 69",
    "sg:city":"Niederkr\u00fcchten",
    "sg:phone":"+49 2163/49668",
    "sg:postcode":"41372",
    "sg:province":"Nordrhein-Westfalen",
    "wof:name":"Wilhelm Gotzes",
    "wof:placetype":"venue"
},
  "geometry": {"coordinates":[6.22726,51.196369],"type":"Point"}
}