{
  "type": "Feature",
  "properties": {
    "iso:country":"DE",
    "sg:address":"R\u00f6merh\u00f6fe 6",
    "sg:city":"Schwaigern",
    "sg:phone":"+49 7138/4123",
    "sg:postcode":"74193",
    "sg:province":"Baden-W\u00fcrttemberg",
    "wof:name":"Alfred Muth",
    "wof:placetype":"venue"
},
  "geometry": {"coordinates":[9.0234651566,49.154586792],"type":"Point"}
}