{
  "type": "Feature",
  "properties": {
    "iso:country":"DE",
    "sg:address":"Am Eichberg 6",
    "sg:city":"Neustadt",
    "sg:phone":"+49 6692/7996",
    "sg:postcode":"35279",
    "sg:province":"Hessen",
    "wof:name":"Ernst Schr\u00f6der",
    "wof:placetype":"venue"
},
  "geometry": {"coordinates":[9.098668,50.901024],"type":"Point"}
}