{
  "type": "Feature",
  "properties": {
    "iso:country":"DE",
    "sg:address":"Da\u00dfwanger Weg 10",
    "sg:city":"Seubersdorf",
    "sg:phone":"+49 9497/902090",
    "sg:postcode":"92358",
    "sg:province":"Bayern",
    "wof:name":"Alois D\u00fcrr Zimmerei Und Dachdeckerei Gmbh",
    "wof:placetype":"venue"
},
  "geometry": {"coordinates":[11.604578,49.130959],"type":"Point"}
}