{
  "type": "Feature",
  "properties": {
    "iso:country":"DE",
    "sg:address":"Gisbertstr. 117",
    "sg:city":"K\u00f6ln",
    "sg:phone":"+49 221/665521",
    "sg:postcode":"51061",
    "sg:province":"Nordrhein-Westfalen",
    "wof:name":"F\u00f6rsterstube",
    "wof:placetype":"venue"
},
  "geometry": {"coordinates":[6.9924359322,50.9875450134],"type":"Point"}
}