{
  "type": "Feature",
  "properties": {
    "iso:country":"DE",
    "sg:address":"Christiansfelde 5",
    "sg:city":"Bad Segeberg",
    "sg:phone":"+49 4551/93167",
    "sg:postcode":"23795",
    "sg:province":"Schleswig-Holstein",
    "wof:name":"H. Ramm",
    "wof:placetype":"venue"
},
  "geometry": {"coordinates":[10.332222,53.929962],"type":"Point"}
}