{
  "type": "Feature",
  "properties": {
    "iso:country":"DE",
    "sg:address":"Am Papenberg 9",
    "sg:city":"G\u00f6ttingen",
    "sg:postcode":"37075",
    "sg:province":"Niedersachsen",
    "wof:name":"Verein Elternhilfe F\u00fcr Das Krebskranke Kind Gtt. E. V.",
    "wof:placetype":"venue"
},
  "geometry": {"coordinates":[9.9465799332,51.5539283752],"type":"Point"}
}