{
  "type": "Feature",
  "properties": {
    "iso:country":"DE",
    "sg:address":"Auf dem Schinken 11",
    "sg:city":"Detmold",
    "sg:phone":"+49 5231/34407",
    "sg:postcode":"32758",
    "sg:province":"Nordrhein-Westfalen",
    "wof:name":"Dtg-tabakwarengrosshandel Gmbh & Co Kg",
    "wof:placetype":"venue"
},
  "geometry": {"coordinates":[8.874966,51.957916],"type":"Point"}
}