{
  "type": "Feature",
  "properties": {
    "iso:country":"DE",
    "sg:address":"H\u00f6lderlinstr. 28",
    "sg:city":"Ludwigshafen",
    "sg:phone":"+49 621/675865",
    "sg:postcode":"67071",
    "sg:province":"Rheinland-Pfalz",
    "wof:name":"Kath. Pfarramt Christ K\u00f6nig",
    "wof:placetype":"venue"
},
  "geometry": {"coordinates":[8.3673906326,49.4892349243],"type":"Point"}
}