{
  "type": "Feature",
  "properties": {
    "iso:country":"DE",
    "sg:address":"Franz-Ehrenthaler-Str. 3",
    "sg:city":"Frontenhausen",
    "sg:phone":"+49 8732/930477",
    "sg:postcode":"84160",
    "sg:province":"Bayern",
    "wof:name":"G. Hofbauer",
    "wof:placetype":"venue"
},
  "geometry": {"coordinates":[12.519405365,48.5407180786],"type":"Point"}
}