{
  "type": "Feature",
  "properties": {
    "iso:country":"DE",
    "sg:address":"Einsteinstr. 14",
    "sg:city":"Schwerin",
    "sg:phone":"+49 385/211888",
    "sg:postcode":"19063",
    "sg:province":"Mecklenburg-Vorpommern",
    "wof:name":"Richter",
    "wof:placetype":"venue"
},
  "geometry": {"coordinates":[11.4681921005,53.589138031],"type":"Point"}
}