{
  "type": "Feature",
  "properties": {
    "iso:country":"DE",
    "sg:address":"Knochenhauerstr. 7",
    "sg:city":"Hannover",
    "sg:phone":"+49 511/322717",
    "sg:postcode":"30159",
    "sg:province":"Niedersachsen",
    "wof:name":"Heinrich Pfalzgraf",
    "wof:placetype":"venue"
},
  "geometry": {"coordinates":[9.7337865829,52.3738212585],"type":"Point"}
}