{
  "type": "Feature",
  "properties": {
    "iso:country":"DE",
    "sg:address":"Ulmer Str. 6",
    "sg:city":"Illertissen",
    "sg:phone":"+49 7303/7233",
    "sg:postcode":"89257",
    "sg:province":"Bayern",
    "wof:name":"Iller-apotheke",
    "wof:placetype":"venue"
},
  "geometry": {"coordinates":[10.103256,48.223129],"type":"Point"}
}