{
  "type": "Feature",
  "properties": {
    "iso:country":"DE",
    "sg:address":"Kuhstr. 39",
    "sg:city":"Greifswald",
    "sg:phone":"+49 3834/79630",
    "sg:postcode":"17489",
    "sg:province":"Mecklenburg-Vorpommern",
    "wof:name":"Naumann B\u00fcrosysteme Inh. Thomas Haindl",
    "wof:placetype":"venue"
},
  "geometry": {"coordinates":[13.3850278854,54.0972099304],"type":"Point"}
}