{
  "type": "Feature",
  "properties": {
    "iso:country":"DE",
    "sg:address":"Marienstrasse 10",
    "sg:city":"Villingen-Schwenningen",
    "sg:phone":"+49 7720",
    "sg:postcode":"78054",
    "sg:province":"Baden-W\u00fcrttemberg",
    "wof:name":"Grafatec Gmbh",
    "wof:placetype":"venue"
},
  "geometry": {"coordinates":[8.5236158371,48.0624732971],"type":"Point"}
}