{
  "type": "Feature",
  "properties": {
    "iso:country":"DE",
    "sg:address":"Innerer Ring 1a",
    "sg:city":"Bruchk\u00f6bel",
    "sg:phone":"+49 6181/78144",
    "sg:postcode":"63486",
    "sg:province":"Hessen",
    "wof:name":"Am Rathaus",
    "wof:placetype":"venue"
},
  "geometry": {"coordinates":[8.919205,50.178967],"type":"Point"}
}