{
  "type": "Feature",
  "properties": {
    "iso:country":"DE",
    "sg:address":"B\u00fcrgerwaldstr. 12",
    "sg:city":"Eggenfelden",
    "sg:phone":"+49 8721/1627",
    "sg:postcode":"84307",
    "sg:province":"Bayern",
    "wof:name":"Renate Engelhardt",
    "wof:placetype":"venue"
},
  "geometry": {"coordinates":[12.767297,48.412243],"type":"Point"}
}