{
  "type": "Feature",
  "properties": {
    "iso:country":"DE",
    "sg:address":"Pfortenstr. 14",
    "sg:city":"Saalfeld",
    "sg:postcode":"07318",
    "sg:province":"Th\u00fcringen",
    "wof:name":"Katholisches Pfarramt",
    "wof:placetype":"venue"
},
  "geometry": {"coordinates":[11.3549823761,50.64503479],"type":"Point"}
}