{
  "type": "Feature",
  "properties": {
    "iso:country":"DE",
    "sg:address":"Paulusstr. 4",
    "sg:city":"Recklinghausen",
    "sg:postcode":"45657",
    "sg:province":"Nordrhein-Westfalen",
    "wof:name":"Avr Agentur F\u00fcr Werbung Und Produktion Gmbh",
    "wof:placetype":"venue"
},
  "geometry": {"coordinates":[7.1972370148,51.6100349426],"type":"Point"}
}