{
  "type": "Feature",
  "properties": {
    "iso:country":"DE",
    "sg:address":"Friedrich-Weinbrenner-Str. 47",
    "sg:city":"Heidelberg",
    "sg:phone":"+49 6221/636900",
    "sg:postcode":"69126",
    "sg:province":"Baden-W\u00fcrttemberg",
    "wof:name":"Karl-heinz Stoll",
    "wof:placetype":"venue"
},
  "geometry": {"coordinates":[8.689856,49.374825],"type":"Point"}
}