{
  "type": "Feature",
  "properties": {
    "iso:country":"DE",
    "sg:address":"Mittelweg 3",
    "sg:city":"Schwabach",
    "sg:phone":"+49 9122/74674",
    "sg:postcode":"91126",
    "sg:province":"Bayern",
    "wof:name":"Johann Heider",
    "wof:placetype":"venue"
},
  "geometry": {"coordinates":[11.079531,49.321743],"type":"Point"}
}