{
  "type": "Feature",
  "properties": {
    "iso:country":"DE",
    "sg:address":"Kirchstr. 1",
    "sg:city":"P\u00e4hl",
    "sg:phone":"+49 8808/424",
    "sg:postcode":"82396",
    "sg:province":"Bayern",
    "wof:name":"Siegfried Kuhnke Gem\u00e4lde Plastiken Kunsthandwerk Gmbh",
    "wof:placetype":"venue"
},
  "geometry": {"coordinates":[11.1761026382,47.9051437378],"type":"Point"}
}