{
  "type": "Feature",
  "properties": {
    "iso:country":"DE",
    "sg:address":"Drehweg 9",
    "sg:city":"R\u00f6dental",
    "sg:phone":"+49 9563/8273",
    "sg:postcode":"96472",
    "sg:province":"Bayern",
    "wof:name":"Erich Renner M\u00f6belhandlung",
    "wof:placetype":"venue"
},
  "geometry": {"coordinates":[11.033167,50.290306],"type":"Point"}
}