{
  "type": "Feature",
  "properties": {
    "iso:country":"DE",
    "sg:address":"Innere Klosterstr. 7",
    "sg:city":"Chemnitz",
    "sg:phone":"+49 371/6761134",
    "sg:postcode":"09111",
    "sg:province":"Sachsen",
    "wof:name":"Filigran Inh. Heidemarie Neumeister",
    "wof:placetype":"venue"
},
  "geometry": {"coordinates":[12.9181871414,50.8331642151],"type":"Point"}
}