{
  "type": "Feature",
  "properties": {
    "iso:country":"DE",
    "sg:address":"Stockborn 2",
    "sg:city":"Haiger",
    "sg:phone":"+49 2773/912073",
    "sg:postcode":"35708",
    "sg:province":"Hessen",
    "wof:name":"P. Franz",
    "wof:placetype":"venue"
},
  "geometry": {"coordinates":[8.221988678,50.7394180298],"type":"Point"}
}