{
  "type": "Feature",
  "properties": {
    "iso:country":"DE",
    "sg:address":"M\u00fchlenstr. 108",
    "sg:city":"L\u00fcdinghausen",
    "sg:phone":"+49 2591/4445",
    "sg:postcode":"59348",
    "sg:province":"Nordrhein-Westfalen",
    "wof:name":"Est-reisen Gmbh",
    "wof:placetype":"venue"
},
  "geometry": {"coordinates":[7.4565057755,51.771900177],"type":"Point"}
}