{
  "type": "Feature",
  "properties": {
    "iso:country":"DE",
    "sg:address":"Gartenstr.8",
    "sg:city":"Jagsthausen",
    "sg:postcode":"74249",
    "sg:province":"Baden-W\u00fcrttemberg",
    "wof:name":"Frankie`s Homepage",
    "wof:placetype":"venue"
},
  "geometry": {"coordinates":[9.468,49.308331],"type":"Point"}
}