{
  "type": "Feature",
  "properties": {
    "iso:country":"DE",
    "sg:address":"Hansastr. 109a",
    "sg:city":"M\u00fcnchen",
    "sg:phone":"+49 89/7600061",
    "sg:postcode":"81373",
    "sg:province":"Bayern",
    "wof:name":"Pizzeria Pasto- Pronto",
    "wof:placetype":"venue"
},
  "geometry": {"coordinates":[11.5351114273,48.1211776733],"type":"Point"}
}