{
  "type": "Feature",
  "properties": {
    "iso:country":"DE",
    "sg:address":"Kirchstr. 42",
    "sg:city":"Riedstadt",
    "sg:phone":"+49 6158/71249",
    "sg:postcode":"64560",
    "sg:province":"Hessen",
    "wof:name":"Karl D\u00f6rr",
    "wof:placetype":"venue"
},
  "geometry": {"coordinates":[8.444505,49.856091],"type":"Point"}
}