{
  "type": "Feature",
  "properties": {
    "iso:country":"DE",
    "sg:address":"Hauptstr. 75",
    "sg:city":"Kehl",
    "sg:phone":"+49 7851/2455",
    "sg:postcode":"77694",
    "sg:province":"Baden-W\u00fcrttemberg",
    "wof:name":"Stadt-apotheke Olshausen Ohg",
    "wof:placetype":"venue"
},
  "geometry": {"coordinates":[7.812492,48.572704],"type":"Point"}
}