{
  "type": "Feature",
  "properties": {
    "iso:country":"DE",
    "sg:address":"Schneitweger Str. 27",
    "sg:city":"Regenstauf",
    "sg:phone":"+49 9402/1848",
    "sg:postcode":"93128",
    "sg:province":"Bayern",
    "wof:name":"R. Und D. Ga\u00dfner",
    "wof:placetype":"venue"
},
  "geometry": {"coordinates":[12.1311216354,49.1239738464],"type":"Point"}
}