{
  "type": "Feature",
  "properties": {
    "iso:country":"DE",
    "sg:address":"Zwernitzer Str. 7",
    "sg:city":"M\u00fcnchen",
    "sg:phone":"+49 89/8714066",
    "sg:postcode":"81243",
    "sg:province":"Bayern",
    "wof:name":"Aris Technik Lebessis Gmbh",
    "wof:placetype":"venue"
},
  "geometry": {"coordinates":[11.424896,48.14439],"type":"Point"}
}