{
  "type": "Feature",
  "properties": {
    "iso:country":"DE",
    "sg:address":"Reutestr. 21",
    "sg:city":"Schw\u00e4bisch Gm\u00fcnd",
    "sg:phone":"+49 7171/987130",
    "sg:postcode":"73529",
    "sg:province":"Baden-W\u00fcrttemberg",
    "wof:name":"Imz Maschinen Vertriebs Gmbh",
    "wof:placetype":"venue"
},
  "geometry": {"coordinates":[9.8597297668,48.7927436829],"type":"Point"}
}