{
  "type": "Feature",
  "properties": {
    "iso:country":"DE",
    "sg:address":"Weinbergstr. 8",
    "sg:city":"Eisingen",
    "sg:phone":"+49 9306/8625",
    "sg:postcode":"97249",
    "sg:province":"Bayern",
    "wof:name":"Roswitha Heiderhoff",
    "wof:placetype":"venue"
},
  "geometry": {"coordinates":[9.8255290985,49.7614364624],"type":"Point"}
}