{
  "type": "Feature",
  "properties": {
    "iso:country":"DE",
    "sg:address":"Ohetal 21 c",
    "sg:city":"Neusch\u00f6nau",
    "sg:phone":"+49 8558/2862",
    "sg:postcode":"94556",
    "sg:province":"Bayern",
    "wof:name":"Johann Rothkopf",
    "wof:placetype":"venue"
},
  "geometry": {"coordinates":[13.457945,48.879066],"type":"Point"}
}