{
  "type": "Feature",
  "properties": {
    "iso:country":"DE",
    "sg:address":"Manggasse 16",
    "sg:city":"Helmershausen",
    "sg:phone":"+49 36943/67419",
    "sg:postcode":"98617",
    "sg:province":"Th\u00fcringen",
    "wof:name":"Rolf Ho\u00dffeld",
    "wof:placetype":"venue"
},
  "geometry": {"coordinates":[10.237219,50.56358],"type":"Point"}
}