{
  "type": "Feature",
  "properties": {
    "iso:country":"DE",
    "sg:address":"Am Brink 41",
    "sg:city":"Nordwalde",
    "sg:postcode":"48356",
    "sg:province":"Nordrhein-Westfalen",
    "wof:name":"D. Synder",
    "wof:placetype":"venue"
},
  "geometry": {"coordinates":[7.4759531021,52.0939712524],"type":"Point"}
}