{
  "type": "Feature",
  "properties": {
    "iso:country":"DE",
    "sg:address":"Felsenstr. 49",
    "sg:city":"Heidenheim",
    "sg:phone":"+49 7321/43494",
    "sg:postcode":"89518",
    "sg:province":"Baden-W\u00fcrttemberg",
    "wof:name":"Anni Watzlawik",
    "wof:placetype":"venue"
},
  "geometry": {"coordinates":[10.147962,48.680519],"type":"Point"}
}