{
  "type": "Feature",
  "properties": {
    "iso:country":"DE",
    "sg:address":"Thaerstr. 18",
    "sg:city":"Berlin",
    "sg:postcode":"10249",
    "sg:province":"Berlin",
    "wof:name":"M Zwei S Exhibition Gmbh",
    "wof:placetype":"venue"
},
  "geometry": {"coordinates":[13.454015,52.519505],"type":"Point"}
}