{
  "type": "Feature",
  "properties": {
    "iso:country":"DE",
    "sg:address":"Am Hopfenbach 1",
    "sg:city":"Rohr",
    "sg:phone":"+49 8783/346",
    "sg:postcode":"93352",
    "sg:province":"Bayern",
    "wof:name":"Otto Zwerger",
    "wof:placetype":"venue"
},
  "geometry": {"coordinates":[11.945189,48.809544],"type":"Point"}
}