{
  "type": "Feature",
  "properties": {
    "iso:country":"DE",
    "sg:address":"Kirchenbirkig 24",
    "sg:city":"Pottenstein",
    "sg:phone":"+49 9243/322",
    "sg:postcode":"91278",
    "sg:province":"Bayern",
    "wof:name":"Kath. Pfarramt St. Johannes D.t\u00e4ufer",
    "wof:placetype":"venue"
},
  "geometry": {"coordinates":[11.4068155289,49.7693023682],"type":"Point"}
}