{
  "type": "Feature",
  "properties": {
    "iso:country":"DE",
    "sg:address":"Reesestr. 1",
    "sg:city":"Hamburg",
    "sg:postcode":"22083",
    "sg:province":"Hamburg",
    "wof:name":"Cg Bridge Gmbh",
    "wof:placetype":"venue"
},
  "geometry": {"coordinates":[10.0402431488,53.5809020996],"type":"Point"}
}