{
  "type": "Feature",
  "properties": {
    "iso:country":"DE",
    "sg:city":"Nettetal",
    "sg:phone":"+49 4921/535511",
    "sg:postcode":"41334",
    "sg:province":"Nordrhein-Westfalen",
    "wof:name":"Westdeutsche Landesbank Girozentr.",
    "wof:placetype":"venue"
},
  "geometry": {"coordinates":[6.27778,51.306351],"type":"Point"}
}