{
  "type": "Feature",
  "properties": {
    "iso:country":"DE",
    "sg:address":"Marchlewskistr. 91",
    "sg:city":"Berlin",
    "sg:postcode":"10243",
    "sg:province":"Berlin",
    "wof:name":"Administ Gmbh",
    "wof:placetype":"venue"
},
  "geometry": {"coordinates":[13.448223114,52.5096549988],"type":"Point"}
}