{
  "type": "Feature",
  "properties": {
    "iso:country":"DE",
    "sg:address":"Lindenstr. 44",
    "sg:city":"Schlagenthin",
    "sg:phone":"+49 39348/237",
    "sg:postcode":"39307",
    "sg:province":"Sachsen-Anhalt",
    "wof:name":"Deutschmann Gesellschaft F\u00fcr F\u00e4kalienabfuhr Und",
    "wof:placetype":"venue"
},
  "geometry": {"coordinates":[12.2865581512,52.46068573],"type":"Point"}
}