{
  "type": "Feature",
  "properties": {
    "iso:country":"DE",
    "sg:address":"W\u00f6rsbacher Str. 30",
    "sg:city":"Olsbr\u00fccken",
    "sg:phone":"+49 6337/1322",
    "sg:postcode":"67737",
    "sg:province":"Rheinland-Pfalz",
    "wof:name":"W. Gehrig",
    "wof:placetype":"venue"
},
  "geometry": {"coordinates":[7.65959,49.542912],"type":"Point"}
}