{
  "type": "Feature",
  "properties": {
    "iso:country":"DE",
    "sg:address":"Fischbachauer Str. 6",
    "sg:city":"M\u00fcnchen",
    "sg:phone":"+49 89/6972323",
    "sg:postcode":"81539",
    "sg:province":"Bayern",
    "wof:name":"Charly Schr\u00f6der Kameramann",
    "wof:placetype":"venue"
},
  "geometry": {"coordinates":[11.5882463455,48.1117019653],"type":"Point"}
}