{
  "type": "Feature",
  "properties": {
    "iso:country":"DE",
    "sg:address":"Riegelhofweg 5a",
    "sg:city":"B\u00fchl",
    "sg:phone":"+49 7223/21340",
    "sg:postcode":"77815",
    "sg:province":"Baden-W\u00fcrttemberg",
    "wof:name":"Eberle Gmbh",
    "wof:placetype":"venue"
},
  "geometry": {"coordinates":[8.153013,48.680305],"type":"Point"}
}