{
  "type": "Feature",
  "properties": {
    "iso:country":"DE",
    "sg:address":"Redwitzstr. 36",
    "sg:city":"K\u00f6ln",
    "sg:phone":"+49 221/416560",
    "sg:postcode":"50937",
    "sg:province":"Nordrhein-Westfalen",
    "wof:name":"Bert Schmitz",
    "wof:placetype":"venue"
},
  "geometry": {"coordinates":[6.9256701469,50.9206962585],"type":"Point"}
}