{
  "type": "Feature",
  "properties": {
    "iso:country":"DE",
    "sg:address":"Jenfelder Allee 80",
    "sg:city":"Hamburg",
    "sg:phone":"+49 40/665601",
    "sg:postcode":"22045",
    "sg:province":"Hamburg",
    "wof:name":"Mav Gmbh",
    "wof:placetype":"venue"
},
  "geometry": {"coordinates":[10.125907,53.584011],"type":"Point"}
}