{
  "type": "Feature",
  "properties": {
    "iso:country":"DE",
    "sg:address":"Im Tiergarten 1",
    "sg:city":"Reichelsheim",
    "sg:phone":"+49 6164/692",
    "sg:postcode":"64385",
    "sg:province":"Hessen",
    "wof:name":"Waldklause",
    "wof:placetype":"venue"
},
  "geometry": {"coordinates":[8.8545122147,49.7189216614],"type":"Point"}
}