{
  "type": "Feature",
  "properties": {
    "iso:country":"DE",
    "sg:address":"Friedrich-Ebert-Str. 44",
    "sg:city":"M\u00f6nchengladbach",
    "sg:phone":"+49 2166/940830",
    "sg:postcode":"41236",
    "sg:province":"Nordrhein-Westfalen",
    "wof:name":"Dagmar H\u00f6velmanns Rechtsanw\u00e4ltin",
    "wof:placetype":"venue"
},
  "geometry": {"coordinates":[6.4412031174,51.1671867371],"type":"Point"}
}