{
  "type": "Feature",
  "properties": {
    "iso:country":"DE",
    "sg:address":"Grevenbroicher Str. 43",
    "sg:city":"K\u00f6ln",
    "sg:phone":"+49 221/508747",
    "sg:postcode":"50829",
    "sg:province":"Nordrhein-Westfalen",
    "wof:name":"St. Brigida Alten- Und Pflegeheim",
    "wof:placetype":"venue"
},
  "geometry": {"coordinates":[6.865523,50.972939],"type":"Point"}
}