{
  "type": "Feature",
  "properties": {
    "iso:country":"DE",
    "sg:address":"Ostendstr. 25",
    "sg:city":"Lauf",
    "sg:phone":"+49 9123/2687",
    "sg:postcode":"91207",
    "sg:province":"Bayern",
    "wof:name":"J. Groninger & D. Kahla Gmbh & Co. Kg",
    "wof:placetype":"venue"
},
  "geometry": {"coordinates":[11.298749,49.518501],"type":"Point"}
}