{
  "type": "Feature",
  "properties": {
    "iso:country":"DE",
    "sg:address":"Kantstr. 7",
    "sg:city":"Kist",
    "sg:phone":"+49 9306/1043",
    "sg:postcode":"97270",
    "sg:province":"Bayern",
    "wof:name":"Ernst D\u00fcrr",
    "wof:placetype":"venue"
},
  "geometry": {"coordinates":[9.843013,49.744251],"type":"Point"}
}