{
  "type": "Feature",
  "properties": {
    "iso:country":"DE",
    "sg:address":"Bahnhofstr. 61",
    "sg:city":"Willst\u00e4tt",
    "sg:phone":"+49 7852/2228",
    "sg:postcode":"77731",
    "sg:province":"Baden-W\u00fcrttemberg",
    "wof:name":"Ernst Truttenbach",
    "wof:placetype":"venue"
},
  "geometry": {"coordinates":[7.913546,48.558216],"type":"Point"}
}