{
  "type": "Feature",
  "properties": {
    "iso:country":"DE",
    "sg:address":"L\u00fcneburger Str. 14-169",
    "sg:city":"Winsen",
    "sg:phone":"+49 4171/70570",
    "sg:postcode":"21423",
    "sg:province":"Niedersachsen",
    "wof:name":"Pg Licht Beteiligungs Gmbh",
    "wof:placetype":"venue"
},
  "geometry": {"coordinates":[10.2081,53.35553],"type":"Point"}
}