{
  "type": "Feature",
  "properties": {
    "iso:country":"DE",
    "sg:address":"Dorfstr. 13",
    "sg:city":"Meerbusch",
    "sg:phone":"+49 2132/10731",
    "sg:postcode":"40667",
    "sg:province":"Nordrhein-Westfalen",
    "wof:name":"Heinrich Schreck",
    "wof:placetype":"venue"
},
  "geometry": {"coordinates":[6.693269,51.252392],"type":"Point"}
}