{
  "type": "Feature",
  "properties": {
    "iso:country":"DE",
    "sg:address":"Promenade 1",
    "sg:city":"Sebnitz",
    "sg:phone":"+49 35971/52362",
    "sg:postcode":"01855",
    "sg:province":"Sachsen",
    "wof:name":"Tillig Modelbahnen Verwaltungs Gmbh",
    "wof:placetype":"venue"
},
  "geometry": {"coordinates":[14.2792253494,50.9726753235],"type":"Point"}
}