{
  "type": "Feature",
  "properties": {
    "iso:country":"DE",
    "sg:city":"Recklinghausen",
    "sg:phone":"+49 2361/181088",
    "sg:postcode":"45659",
    "sg:province":"Nordrhein-Westfalen",
    "wof:name":"Maritim - Internationale Bootsschulen",
    "wof:placetype":"venue"
},
  "geometry": {"coordinates":[7.17396,51.590889],"type":"Point"}
}