{
  "type": "Feature",
  "properties": {
    "iso:country":"DE",
    "sg:address":"Birnauer Str. 10",
    "sg:city":"M\u00fcnchen",
    "sg:phone":"+49 89/3081842",
    "sg:postcode":"80809",
    "sg:province":"Bayern",
    "wof:name":"Marek Olsienkiewicz",
    "wof:placetype":"venue"
},
  "geometry": {"coordinates":[11.563405,48.174942],"type":"Point"}
}