{
  "type": "Feature",
  "properties": {
    "iso:country":"DE",
    "sg:address":"Drosselweg 35",
    "sg:city":"M\u00fcnchen",
    "sg:phone":"+49 89/4305040",
    "sg:postcode":"81827",
    "sg:province":"Bayern",
    "wof:name":"Die Werkstatt F\u00fcr Textile Inneneinrichtung",
    "wof:placetype":"venue"
},
  "geometry": {"coordinates":[11.6968050003,48.1181030273],"type":"Point"}
}