{
  "type": "Feature",
  "properties": {
    "iso:country":"DE",
    "sg:address":"Leinpfad 1",
    "sg:city":"Hanau",
    "sg:phone":"+49 6181/54348",
    "sg:postcode":"63457",
    "sg:province":"Hessen",
    "wof:name":"Ev. Pfarramt Grossauheim Pfarrbz. I",
    "wof:placetype":"venue"
},
  "geometry": {"coordinates":[8.9413995743,50.1049957275],"type":"Point"}
}