{
  "type": "Feature",
  "properties": {
    "iso:country":"DE",
    "sg:address":"Pr\u00f6bstener Str. 31",
    "sg:city":"Eisenberg",
    "sg:phone":"+49 8364/1639",
    "sg:postcode":"87637",
    "sg:province":"Bayern",
    "wof:name":"Stefan Brenner",
    "wof:placetype":"venue"
},
  "geometry": {"coordinates":[10.610619545,47.6139717102],"type":"Point"}
}