{
  "type": "Feature",
  "properties": {
    "iso:country":"DE",
    "sg:address":"Hof Marienberg",
    "sg:city":"Osterspai",
    "sg:phone":"+49 2627/8408",
    "sg:postcode":"56340",
    "sg:province":"Rheinland-Pfalz",
    "wof:name":"Alfred Schlaghecken",
    "wof:placetype":"venue"
},
  "geometry": {"coordinates":[7.7129192352,50.2400093079],"type":"Point"}
}