{
  "type": "Feature",
  "properties": {
    "iso:country":"DE",
    "sg:address":"In den H\u00f6fen 32",
    "sg:city":"Ratingen",
    "sg:phone":"+49 2102/69925",
    "sg:postcode":"40883",
    "sg:province":"Nordrhein-Westfalen",
    "wof:name":"Thebu Sportst\u00e4tten Gmbh Gut G\u00fctzenhof",
    "wof:placetype":"venue"
},
  "geometry": {"coordinates":[6.9201521873,51.3266487122],"type":"Point"}
}