{
  "type": "Feature",
  "properties": {
    "iso:country":"DE",
    "sg:address":"Albert-Schweitzer-Str. 41",
    "sg:city":"M\u00fcnster",
    "sg:phone":"+49 251/838824",
    "sg:postcode":"48149",
    "sg:province":"Nordrhein-Westfalen",
    "wof:name":"Maria Witte",
    "wof:placetype":"venue"
},
  "geometry": {"coordinates":[7.59138,51.96085],"type":"Point"}
}