{
  "type": "Feature",
  "properties": {
    "iso:country":"DE",
    "sg:address":"Br\u00fccherm\u00fchler Str. 15",
    "sg:city":"Reichshof",
    "sg:phone":"+49 2296/629",
    "sg:postcode":"51580",
    "sg:province":"Nordrhein-Westfalen",
    "wof:name":"Otto Jungjohann Gmbh & Co. Kg",
    "wof:placetype":"venue"
},
  "geometry": {"coordinates":[7.658734,50.941502],"type":"Point"}
}