{
  "type": "Feature",
  "properties": {
    "iso:country":"DE",
    "sg:address":"Leipziger Str. 18",
    "sg:city":"Meerane",
    "sg:phone":"+49 3764/40040",
    "sg:postcode":"08393",
    "sg:province":"Sachsen",
    "wof:name":"Prowa Ingenieure Gmbh",
    "wof:placetype":"venue"
},
  "geometry": {"coordinates":[12.4599962234,50.8519935608],"type":"Point"}
}