{
  "type": "Feature",
  "properties": {
    "iso:country":"DE",
    "sg:address":"Friedensstr. 29",
    "sg:city":"Lebach",
    "sg:phone":"+49 6881/537034",
    "sg:postcode":"66822",
    "sg:province":"Saarland",
    "wof:name":"Franz-josef Schmitt Notar",
    "wof:placetype":"venue"
},
  "geometry": {"coordinates":[6.9053292274,49.4150314331],"type":"Point"}
}