{
  "type": "Feature",
  "properties": {
    "iso:country":"DE",
    "sg:address":"Gau\u00dfstr.13",
    "sg:city":"Chemnitz",
    "sg:postcode":"09117",
    "sg:province":"Sachsen",
    "wof:name":"Xcellent Multimedia Eventmanagement Postproduction",
    "wof:placetype":"venue"
},
  "geometry": {"coordinates":[12.842462,50.819447],"type":"Point"}
}