{
  "type": "Feature",
  "properties": {
    "iso:country":"DE",
    "sg:address":"Landsberger Str. 372",
    "sg:city":"M\u00fcnchen",
    "sg:phone":"+49 89/8111086",
    "sg:postcode":"80687",
    "sg:province":"Bayern",
    "wof:name":"C. Roesch",
    "wof:placetype":"venue"
},
  "geometry": {"coordinates":[11.48966,48.144421],"type":"Point"}
}