{
  "type": "Feature",
  "properties": {
    "iso:country":"DE",
    "sg:address":"Mallendarer Bachtal 15",
    "sg:city":"Urbar",
    "sg:phone":"+49 261/69427",
    "sg:postcode":"56182",
    "sg:province":"Rheinland-Pfalz",
    "wof:name":"Schikowski Gmbh Ges.f.techn.datenverarbeitung",
    "wof:placetype":"venue"
},
  "geometry": {"coordinates":[7.6476359367,50.379776001],"type":"Point"}
}