{
  "type": "Feature",
  "properties": {
    "iso:country":"DE",
    "sg:address":"Bachstr. 6 u. 8",
    "sg:city":"Esslingen",
    "sg:postcode":"73730",
    "sg:province":"Baden-W\u00fcrttemberg",
    "wof:name":"Hebammenpraxis Esslingen Burk- Hardt-dress-teller-werbunat",
    "wof:placetype":"venue"
},
  "geometry": {"coordinates":[9.36781,48.731861],"type":"Point"}
}