{
  "type": "Feature",
  "properties": {
    "iso:country":"DE",
    "sg:address":"Steubstr. 4",
    "sg:city":"Aichach",
    "sg:phone":"+49 8251/2810",
    "sg:postcode":"86551",
    "sg:province":"Bayern",
    "wof:name":"Wolfgang Linck",
    "wof:placetype":"venue"
},
  "geometry": {"coordinates":[11.129404,48.459663],"type":"Point"}
}