{
  "type": "Feature",
  "properties": {
    "iso:country":"DE",
    "sg:address":"Blumenstr. 9",
    "sg:city":"Fischach",
    "sg:phone":"+49 8236/1057",
    "sg:postcode":"86850",
    "sg:province":"Bayern",
    "wof:name":"Theodor Kaes M\u00f6bel Und Innenausbau Gmbh",
    "wof:placetype":"venue"
},
  "geometry": {"coordinates":[10.6578636169,48.2900047302],"type":"Point"}
}