{
  "type": "Feature",
  "properties": {
    "iso:country":"DE",
    "sg:address":"Entruper Weg 228",
    "sg:city":"Lemgo",
    "sg:phone":"+49 5261/4667",
    "sg:postcode":"32657",
    "sg:province":"Nordrhein-Westfalen",
    "wof:name":"Restaurant Entruper Krug",
    "wof:placetype":"venue"
},
  "geometry": {"coordinates":[8.8832101822,52.0532188416],"type":"Point"}
}