{
  "type": "Feature",
  "properties": {
    "iso:country":"DE",
    "sg:address":"Weinbergstr. 20 a",
    "sg:city":"Bergheim",
    "sg:phone":"+49 2238/41620",
    "sg:postcode":"50129",
    "sg:province":"Nordrhein-Westfalen",
    "wof:name":"Heinz Esser",
    "wof:placetype":"venue"
},
  "geometry": {"coordinates":[6.749001,50.97084],"type":"Point"}
}