{
  "type": "Feature",
  "properties": {
    "iso:country":"DE",
    "sg:address":"Graf-Adolf-Platz 11-12",
    "sg:city":"Duesseldorf",
    "sg:phone":"+49 4921/1386400",
    "sg:postcode":"40213",
    "sg:province":"Nordrhein-Westfalen",
    "wof:name":"Brodeur Kohtes & Klewes",
    "wof:placetype":"venue"
},
  "geometry": {"coordinates":[6.778225,51.218849],"type":"Point"}
}