{
  "type": "Feature",
  "properties": {
    "iso:country":"DE",
    "sg:address":"Eisenbahnstr. 61",
    "sg:city":"Kehl",
    "sg:phone":"+49 7851/3212",
    "sg:postcode":"77694",
    "sg:province":"Baden-W\u00fcrttemberg",
    "wof:name":"Schwing Gmbh",
    "wof:placetype":"venue"
},
  "geometry": {"coordinates":[7.835311,48.609062],"type":"Point"}
}