{
  "type": "Feature",
  "properties": {
    "iso:country":"DE",
    "sg:address":"Neusser Str. 123",
    "sg:city":"J\u00fcchen",
    "sg:phone":"+49 2165/876897",
    "sg:postcode":"41363",
    "sg:province":"Nordrhein-Westfalen",
    "wof:name":"Egon Bar",
    "wof:placetype":"venue"
},
  "geometry": {"coordinates":[6.5214219093,51.0998039246],"type":"Point"}
}