{
  "type": "Feature",
  "properties": {
    "iso:country":"DE",
    "sg:address":"In den Riehen 3",
    "sg:city":"Espelkamp",
    "sg:phone":"+49 5743/8124",
    "sg:postcode":"32339",
    "sg:province":"Nordrhein-Westfalen",
    "wof:name":"Karl-heinz Sch\u00e4fer",
    "wof:placetype":"venue"
},
  "geometry": {"coordinates":[8.551164,52.377789],"type":"Point"}
}