{
  "type": "Feature",
  "properties": {
    "iso:country":"DE",
    "sg:address":"Pablo-Neruda-Ring 5",
    "sg:city":"Torgau",
    "sg:phone":"+49 3421/714318",
    "sg:postcode":"04860",
    "sg:province":"Sachsen",
    "wof:name":"Manfred Dauer",
    "wof:placetype":"venue"
},
  "geometry": {"coordinates":[12.9855318069,51.5504646301],"type":"Point"}
}