{
  "type": "Feature",
  "properties": {
    "iso:country":"DE",
    "sg:address":"Kirchweg 19",
    "sg:city":"Warmensteinach",
    "sg:phone":"+49 9277/239",
    "sg:postcode":"95485",
    "sg:province":"Bayern",
    "wof:name":"Ev. Luth. Pfarramt",
    "wof:placetype":"venue"
},
  "geometry": {"coordinates":[11.7846336365,49.9948616028],"type":"Point"}
}