{
  "type": "Feature",
  "properties": {
    "iso:country":"DE",
    "sg:address":"Marienstr. 5",
    "sg:city":"Hannover",
    "sg:phone":"+49 4951/1320705",
    "sg:postcode":"30171",
    "sg:province":"Niedersachsen",
    "wof:name":"Da Lello Ristorante-hotel",
    "wof:placetype":"venue"
},
  "geometry": {"coordinates":[9.744403,52.36916],"type":"Point"}
}