{
  "type": "Feature",
  "properties": {
    "iso:country":"DE",
    "sg:address":"Markt 4",
    "sg:city":"Hofgeismar",
    "sg:phone":"+49 5671/2988",
    "sg:postcode":"34369",
    "sg:province":"Hessen",
    "wof:name":"Galerie Am Markt",
    "wof:placetype":"venue"
},
  "geometry": {"coordinates":[9.379826,51.495888],"type":"Point"}
}