{
  "type": "Feature",
  "properties": {
    "iso:country":"DE",
    "sg:address":"Waldshuter Str. 1",
    "sg:city":"Jestetten",
    "sg:phone":"+49 7745/5440",
    "sg:postcode":"79798",
    "sg:province":"Baden-W\u00fcrttemberg",
    "wof:name":"Bistro Schnick-schnack",
    "wof:placetype":"venue"
},
  "geometry": {"coordinates":[8.567742,47.649311],"type":"Point"}
}