{
  "type": "Feature",
  "properties": {
    "iso:country":"DE",
    "sg:address":"Schl\u00f6\u00dflanger 33",
    "sg:city":"M\u00fcnchen",
    "sg:postcode":"80939",
    "sg:province":"Bayern",
    "wof:name":"Badopal Verwaltung Und Immobilien Gmbh & Co. Kg",
    "wof:placetype":"venue"
},
  "geometry": {"coordinates":[11.6109762192,48.2059631348],"type":"Point"}
}