{
  "type": "Feature",
  "properties": {
    "iso:country":"DE",
    "sg:address":"Alfred-Schefenacker-Str 10",
    "sg:city":"Schwaikheim",
    "sg:phone":"+49 7195/51167",
    "sg:postcode":"71409",
    "sg:province":"Baden-W\u00fcrttemberg",
    "wof:name":"Druckerei Palmer Gmbh",
    "wof:placetype":"venue"
},
  "geometry": {"coordinates":[9.3559904099,48.8666801453],"type":"Point"}
}