{
  "type": "Feature",
  "properties": {
    "iso:country":"DE",
    "sg:address":"Lutherstr. 27",
    "sg:city":"Hannover",
    "sg:phone":"+49 511/28339830",
    "sg:postcode":"30171",
    "sg:province":"Niedersachsen",
    "wof:name":"Ingenieurgemeinschaft Eriksen",
    "wof:placetype":"venue"
},
  "geometry": {"coordinates":[9.7496213913,52.3659133911],"type":"Point"}
}