{
  "type": "Feature",
  "properties": {
    "iso:country":"DE",
    "sg:address":"Markt 33",
    "sg:city":"Schm\u00f6lln",
    "sg:phone":"+49 34491/82315",
    "sg:postcode":"04626",
    "sg:province":"Th\u00fcringen",
    "wof:name":"D. Schulze",
    "wof:placetype":"venue"
},
  "geometry": {"coordinates":[12.352722,50.89542],"type":"Point"}
}