{
  "type": "Feature",
  "properties": {
    "iso:country":"DE",
    "sg:address":"R\u00f6merstr. 58",
    "sg:city":"Stuttgart",
    "sg:phone":"+49 711/609791",
    "sg:postcode":"70180",
    "sg:province":"Baden-W\u00fcrttemberg",
    "wof:name":"Hein Franzen Architekt",
    "wof:placetype":"venue"
},
  "geometry": {"coordinates":[9.17466,48.762886],"type":"Point"}
}