{
  "type": "Feature",
  "properties": {
    "iso:country":"DE",
    "sg:address":"Maiplatz 2",
    "sg:city":"Plettenberg",
    "sg:phone":"+49 2391/2821",
    "sg:postcode":"58840",
    "sg:province":"Nordrhein-Westfalen",
    "wof:name":"Engel-apotheke Ohg",
    "wof:placetype":"venue"
},
  "geometry": {"coordinates":[7.873839,51.212997],"type":"Point"}
}