{
  "type": "Feature",
  "properties": {
    "iso:country":"DE",
    "sg:address":"Steinweg 60",
    "sg:city":"Stolberg",
    "sg:phone":"+49 2402/6843",
    "sg:postcode":"52222",
    "sg:province":"Nordrhein-Westfalen",
    "wof:name":"Spiel Mit Automatenaufstellung Gmbh",
    "wof:placetype":"venue"
},
  "geometry": {"coordinates":[6.2316360474,50.7682418823],"type":"Point"}
}