{
  "type": "Feature",
  "properties": {
    "iso:country":"DE",
    "sg:address":"Goethestr. 7",
    "sg:city":"Berlin",
    "sg:phone":"+49 30/3139547",
    "sg:postcode":"10623",
    "sg:province":"Berlin",
    "wof:name":"N.a.r.u. Handelsgesellschaft Mbh",
    "wof:placetype":"venue"
},
  "geometry": {"coordinates":[13.3217611313,52.5089797974],"type":"Point"}
}