{
  "type": "Feature",
  "properties": {
    "iso:country":"DE",
    "sg:address":"Hohe Str. 4",
    "sg:city":"Lauchhammer",
    "sg:phone":"+49 3574/460718",
    "sg:postcode":"01979",
    "sg:province":"Brandenburg",
    "wof:name":"Michael Elte Rechtsanwalt",
    "wof:placetype":"venue"
},
  "geometry": {"coordinates":[13.7566518784,51.4983787537],"type":"Point"}
}