{
  "type": "Feature",
  "properties": {
    "iso:country":"DE",
    "sg:address":"Gr\u00fcner Weg 11",
    "sg:city":"Jevenstedt",
    "sg:phone":"+49 4337/1388",
    "sg:postcode":"24808",
    "sg:province":"Schleswig-Holstein",
    "wof:name":"Klaus Witt Inh. Olaf Witt",
    "wof:placetype":"venue"
},
  "geometry": {"coordinates":[9.674226,54.227566],"type":"Point"}
}