{
  "type": "Feature",
  "properties": {
    "iso:country":"DE",
    "sg:address":"Bahnhofstr. 3",
    "sg:city":"Bobritzsch",
    "sg:phone":"+49 37325/2990",
    "sg:postcode":"09627",
    "sg:province":"Sachsen",
    "wof:name":"L\u00e4ndliche Dienstleistungs- Und Handelsgenossenschaft Eg",
    "wof:placetype":"venue"
},
  "geometry": {"coordinates":[13.4364995956,50.8999481201],"type":"Point"}
}