{
  "type": "Feature",
  "properties": {
    "iso:country":"DE",
    "sg:address":"Hauptstr. 36 b",
    "sg:city":"Kissenbr\u00fcck",
    "sg:phone":"+49 5337/92550",
    "sg:postcode":"38324",
    "sg:province":"Niedersachsen",
    "wof:name":"Preteq-fertigbau Gmbh",
    "wof:placetype":"venue"
},
  "geometry": {"coordinates":[10.5978374481,52.1079063416],"type":"Point"}
}