{
  "type": "Feature",
  "properties": {
    "iso:country":"DE",
    "sg:address":"Lange Str. 51",
    "sg:city":"Walsrode",
    "sg:phone":"+49 5161/910991",
    "sg:postcode":"29664",
    "sg:province":"Niedersachsen",
    "wof:name":"Hirscher Moneysystems Gmbh",
    "wof:placetype":"venue"
},
  "geometry": {"coordinates":[9.589886,52.860626],"type":"Point"}
}