{
  "type": "Feature",
  "properties": {
    "iso:country":"DE",
    "sg:address":"Hinterviechtach",
    "sg:city":"St Englmar",
    "sg:phone":"+49 9965/471",
    "sg:postcode":"94379",
    "sg:province":"Bayern",
    "wof:name":"Berggasthaus Hochpr\u00f6ller Skilift",
    "wof:placetype":"venue"
},
  "geometry": {"coordinates":[12.8200922012,49.0024299622],"type":"Point"}
}