{
  "type": "Feature",
  "properties": {
    "iso:country":"DE",
    "sg:address":"Richmodstr. 13",
    "sg:city":"K\u00f6ln",
    "sg:phone":"+49 221/137648",
    "sg:postcode":"50667",
    "sg:province":"Nordrhein-Westfalen",
    "wof:name":"Muk Kapital- Beteiligungsgesellschaft Mbh",
    "wof:placetype":"venue"
},
  "geometry": {"coordinates":[6.947415,50.937401],"type":"Point"}
}