{
  "type": "Feature",
  "properties": {
    "iso:country":"DE",
    "sg:address":"Hohenzollerndamm 94",
    "sg:city":"Berlin",
    "sg:phone":"+49 30/8264292",
    "sg:postcode":"14199",
    "sg:province":"Berlin",
    "wof:name":"Werner D\u00fcvel",
    "wof:placetype":"venue"
},
  "geometry": {"coordinates":[13.281097,52.477188],"type":"Point"}
}