{
  "type": "Feature",
  "properties": {
    "iso:country":"DE",
    "sg:address":"Sch\u00f6nseer Str. 25",
    "sg:city":"Sch\u00f6nsee",
    "sg:phone":"+49 9674/1612",
    "sg:postcode":"92539",
    "sg:province":"Bayern",
    "wof:name":"Siegfried Dietz",
    "wof:placetype":"venue"
},
  "geometry": {"coordinates":[12.502468,49.478771],"type":"Point"}
}