{
  "type": "Feature",
  "properties": {
    "iso:country":"DE",
    "sg:address":"unbek",
    "sg:city":"stuttgart",
    "sg:postcode":"65410",
    "sg:province":"Baden-W\u00fcrttemberg",
    "wof:name":"C-welt",
    "wof:placetype":"venue"
},
  "geometry": {"coordinates":[-91.552673,34.498363],"type":"Point"}
}