{
  "type": "Feature",
  "properties": {
    "iso:country":"DE",
    "sg:address":"Orpethaler Str. 27",
    "sg:city":"Diemelstadt",
    "sg:phone":"+49 5642/5077",
    "sg:postcode":"34474",
    "sg:province":"Hessen",
    "wof:name":"Spedition Siegfried Schwarz Gmbh",
    "wof:placetype":"venue"
},
  "geometry": {"coordinates":[8.9744100571,51.5046195984],"type":"Point"}
}