{
  "type": "Feature",
  "properties": {
    "iso:country":"DE",
    "sg:address":"Hauptstr. 9",
    "sg:city":"Schirmitz",
    "sg:phone":"+49 961/482900",
    "sg:postcode":"92718",
    "sg:province":"Bayern",
    "wof:name":"Hans Koller",
    "wof:placetype":"venue"
},
  "geometry": {"coordinates":[12.1681861877,49.6524085999],"type":"Point"}
}