{
  "type": "Feature",
  "properties": {
    "iso:country":"DE",
    "sg:address":"Friedrich-Ebert-Str. 236",
    "sg:city":"Solingen",
    "sg:phone":"+49 212/13016",
    "sg:postcode":"42719",
    "sg:province":"Nordrhein-Westfalen",
    "wof:name":"M. Andr\u00e4 Und R. M\u00fcller-mittendorf",
    "wof:placetype":"venue"
},
  "geometry": {"coordinates":[7.0375471115,51.1804771423],"type":"Point"}
}