{
  "type": "Feature",
  "properties": {
    "iso:country":"DE",
    "sg:address":"Saarlandstr. 39",
    "sg:city":"Bochum",
    "sg:phone":"+49 2327/31564",
    "sg:postcode":"44866",
    "sg:province":"Nordrhein-Westfalen",
    "wof:name":"Manfred G\u00f6hring",
    "wof:placetype":"venue"
},
  "geometry": {"coordinates":[7.135068,51.477291],"type":"Point"}
}