{
  "type": "Feature",
  "properties": {
    "iso:country":"DE",
    "sg:address":"An der M\u00fchlenau 10",
    "sg:city":"Preetz",
    "sg:phone":"+49 4342/5915",
    "sg:postcode":"24211",
    "sg:province":"Schleswig-Holstein",
    "wof:name":"Detlef Kl\u00f6tzke",
    "wof:placetype":"venue"
},
  "geometry": {"coordinates":[10.280271,54.23671],"type":"Point"}
}