{
  "type": "Feature",
  "properties": {
    "iso:country":"DE",
    "sg:address":"S\u00f6hren 45",
    "sg:city":"Sch\u00f6nkirchen",
    "sg:phone":"+49 4348/912050",
    "sg:postcode":"24232",
    "sg:province":"Schleswig-Holstein",
    "wof:name":"Glas- Und Sonnenschutztechnik Kielmann Gmbh",
    "wof:placetype":"venue"
},
  "geometry": {"coordinates":[10.210669,54.33939],"type":"Point"}
}