{
  "type": "Feature",
  "properties": {
    "iso:country":"DE",
    "sg:address":"Am Markt 12",
    "sg:city":"Speicher",
    "sg:phone":"+49 6562/8193",
    "sg:postcode":"54662",
    "sg:province":"Rheinland-Pfalz",
    "wof:name":"Willi Streit",
    "wof:placetype":"venue"
},
  "geometry": {"coordinates":[6.6388001442,49.9347610474],"type":"Point"}
}