{
  "type": "Feature",
  "properties": {
    "iso:country":"DE",
    "sg:address":"Am Gewerbering 10",
    "sg:city":"M\u00fcncheberg",
    "sg:phone":"+49 33432/8060",
    "sg:postcode":"15374",
    "sg:province":"Brandenburg",
    "wof:name":"Erocontur-drahterosion Werkzeugbau Gmbh",
    "wof:placetype":"venue"
},
  "geometry": {"coordinates":[14.1475296021,52.509552002],"type":"Point"}
}