{
  "type": "Feature",
  "properties": {
    "iso:country":"DE",
    "sg:address":"Rathausstr. 2",
    "sg:city":"B\u00fcrstadt",
    "sg:postcode":"68642",
    "sg:province":"Hessen",
    "wof:name":"B\u00fcrst\u00e4dter Grundst\u00fccksent- Wicklungsgesellschaft Mbh",
    "wof:placetype":"venue"
},
  "geometry": {"coordinates":[8.451249,49.642708],"type":"Point"}
}