{
  "type": "Feature",
  "properties": {
    "iso:country":"DE",
    "sg:address":"Beentweg 8",
    "sg:city":"Oldenburg",
    "sg:phone":"+49 441/203931",
    "sg:postcode":"26135",
    "sg:province":"Niedersachsen",
    "wof:name":"Kuper & Rademacher Ohg",
    "wof:placetype":"venue"
},
  "geometry": {"coordinates":[8.2437505722,53.0943603516],"type":"Point"}
}