{
  "type": "Feature",
  "properties": {
    "iso:country":"DE",
    "sg:address":"Obere Torstr. 2",
    "sg:city":"Dassel",
    "sg:phone":"+49 5562/1467",
    "sg:postcode":"37586",
    "sg:province":"Niedersachsen",
    "wof:name":"Franz M\u00fcller",
    "wof:placetype":"venue"
},
  "geometry": {"coordinates":[9.767052,51.813236],"type":"Point"}
}