{
  "type": "Feature",
  "properties": {
    "iso:country":"DE",
    "sg:address":"Sender Str. 42",
    "sg:city":"Bielefeld",
    "sg:phone":"+49 5205/71788",
    "sg:postcode":"33689",
    "sg:province":"Nordrhein-Westfalen",
    "wof:name":"Udo Tomberg Industrievertretungen Gmbh",
    "wof:placetype":"venue"
},
  "geometry": {"coordinates":[8.57401,51.93771],"type":"Point"}
}