{
  "type": "Feature",
  "properties": {
    "iso:country":"DE",
    "sg:address":"Charlottenstr. 10",
    "sg:city":"Ravensburg",
    "sg:phone":"+49 751",
    "sg:postcode":"88212",
    "sg:province":"Baden-W\u00fcrttemberg",
    "wof:name":"Schmuck Von A - Z",
    "wof:placetype":"venue"
},
  "geometry": {"coordinates":[9.613129,47.783543],"type":"Point"}
}