{
  "type": "Feature",
  "properties": {
    "iso:country":"DE",
    "sg:address":"Akazienstr. 116",
    "sg:city":"Oberhausen",
    "sg:phone":"+49 208/2056527",
    "sg:postcode":"46045",
    "sg:province":"Nordrhein-Westfalen",
    "wof:name":"D69 - Design-six-nine",
    "wof:placetype":"venue"
},
  "geometry": {"coordinates":[6.846134,51.462128],"type":"Point"}
}