{
  "type": "Feature",
  "properties": {
    "iso:country":"DE",
    "sg:address":"K\u00f6nigsheide 4",
    "sg:city":"Willich",
    "sg:phone":"+49 2154/5045",
    "sg:postcode":"47877",
    "sg:province":"Nordrhein-Westfalen",
    "wof:name":"Hubertusstift",
    "wof:placetype":"venue"
},
  "geometry": {"coordinates":[6.539153,51.242214],"type":"Point"}
}