{
  "type": "Feature",
  "properties": {
    "iso:country":"DE",
    "sg:address":"Elkan-Naumburg-Str. 52",
    "sg:city":"Treuchtlingen",
    "sg:phone":"+49 9142/4585",
    "sg:postcode":"91757",
    "sg:province":"Bayern",
    "wof:name":"E. Cremer",
    "wof:placetype":"venue"
},
  "geometry": {"coordinates":[10.911867,48.964493],"type":"Point"}
}