{
  "type": "Feature",
  "properties": {
    "iso:country":"DE",
    "sg:address":"Uhlbachweg 41",
    "sg:city":"Bad Mergentheim",
    "sg:phone":"+49 7937/781",
    "sg:postcode":"97980",
    "sg:province":"Baden-W\u00fcrttemberg",
    "wof:name":"Andreas Gahm",
    "wof:placetype":"venue"
},
  "geometry": {"coordinates":[9.736577,49.399284],"type":"Point"}
}