{
  "type": "Feature",
  "properties": {
    "iso:country":"DE",
    "sg:address":"H\u00fclst 1",
    "sg:city":"Br\u00fcggen",
    "sg:phone":"+49 2157/90365",
    "sg:postcode":"41379",
    "sg:province":"Nordrhein-Westfalen",
    "wof:name":"Restaurant Dohlensch\u00e4nke",
    "wof:placetype":"venue"
},
  "geometry": {"coordinates":[6.1957597733,51.2927589417],"type":"Point"}
}