{
  "type": "Feature",
  "properties": {
    "iso:country":"DE",
    "sg:address":"Karlsplatz 24",
    "sg:city":"Krefeld",
    "sg:phone":"+49 2151/152421",
    "sg:postcode":"47798",
    "sg:province":"Nordrhein-Westfalen",
    "wof:name":"Die-abfahrer",
    "wof:placetype":"venue"
},
  "geometry": {"coordinates":[6.558698,51.33004],"type":"Point"}
}