{
  "type": "Feature",
  "properties": {
    "iso:country":"DE",
    "sg:address":"Fichtenstr. 27",
    "sg:city":"Brunnthal",
    "sg:phone":"+49 8104/89430",
    "sg:postcode":"85649",
    "sg:province":"Bayern",
    "wof:name":"Lauterbach Datentechnik Gmbh",
    "wof:placetype":"venue"
},
  "geometry": {"coordinates":[11.707822,47.985703],"type":"Point"}
}