{
  "type": "Feature",
  "properties": {
    "iso:country":"DE",
    "sg:address":"Am Wilzenberg 10",
    "sg:city":"Schmallenberg",
    "sg:phone":"+49 2972/6400",
    "sg:postcode":"57392",
    "sg:province":"Nordrhein-Westfalen",
    "wof:name":"Katholisches Pfarramt St. Georg",
    "wof:placetype":"venue"
},
  "geometry": {"coordinates":[8.3196296692,51.1483688354],"type":"Point"}
}