{
  "type": "Feature",
  "properties": {
    "iso:country":"DE",
    "sg:address":"Akazienstr. 56",
    "sg:city":"Fredersdorf",
    "sg:postcode":"15370",
    "sg:province":"Brandenburg",
    "wof:name":"Capital Investitions Gmbh",
    "wof:placetype":"venue"
},
  "geometry": {"coordinates":[13.754246,52.529819],"type":"Point"}
}