{
  "type": "Feature",
  "properties": {
    "iso:country":"DE",
    "sg:address":"Frankfurter Str. 9",
    "sg:city":"Gr\u00fcndau",
    "sg:postcode":"63584",
    "sg:province":"Hessen",
    "wof:name":"Gartenapotheke Inh. Birgit Sailer E. Kfr.",
    "wof:placetype":"venue"
},
  "geometry": {"coordinates":[9.1143989563,50.2005004883],"type":"Point"}
}