{
  "type": "Feature",
  "properties": {
    "iso:country":"DE",
    "sg:address":"Carl-Orff-Str. 8",
    "sg:city":"R\u00f6srath",
    "sg:phone":"+49 2205/5051",
    "sg:postcode":"51503",
    "sg:province":"Nordrhein-Westfalen",
    "wof:name":"Wbr Wohnhaus F\u00fcr Behinderte R\u00f6srath Gemeinn\u00fctzige Gmbh",
    "wof:placetype":"venue"
},
  "geometry": {"coordinates":[7.1822280884,50.8919868469],"type":"Point"}
}