{
  "type": "Feature",
  "properties": {
    "iso:country":"DE",
    "sg:address":"Norddeicher Str. 205",
    "sg:city":"Norden",
    "sg:phone":"+49 4931/8013",
    "sg:postcode":"26506",
    "sg:province":"Niedersachsen",
    "wof:name":"Interhome Gmbh",
    "wof:placetype":"venue"
},
  "geometry": {"coordinates":[7.1888008118,53.6021575928],"type":"Point"}
}