{
  "type": "Feature",
  "properties": {
    "iso:country":"DE",
    "sg:address":"Klutestr. 9",
    "sg:city":"Hamm",
    "sg:postcode":"59063",
    "sg:province":"Nordrhein-Westfalen",
    "wof:name":"C & M Verwaltungs Gmbh",
    "wof:placetype":"venue"
},
  "geometry": {"coordinates":[7.810722,51.664604],"type":"Point"}
}