{
  "type": "Feature",
  "properties": {
    "iso:country":"DE",
    "sg:address":"Untertorstr. 27",
    "sg:city":"Leinfelden-Echterdingen",
    "sg:phone":"+49 711/799311",
    "sg:postcode":"70771",
    "sg:province":"Baden-W\u00fcrttemberg",
    "wof:name":"Helmut W. Caesar",
    "wof:placetype":"venue"
},
  "geometry": {"coordinates":[9.1693267822,48.6847724915],"type":"Point"}
}