{
  "type": "Feature",
  "properties": {
    "iso:country":"DE",
    "sg:address":"Elbstr 10",
    "sg:city":"Radebeul",
    "sg:phone":"+49 351/8305605",
    "sg:postcode":"01445",
    "sg:province":"Sachsen",
    "wof:name":"Grosse",
    "wof:placetype":"venue"
},
  "geometry": {"coordinates":[13.623014,51.105724],"type":"Point"}
}