{
  "type": "Feature",
  "properties": {
    "iso:country":"DE",
    "sg:address":"Industriestr. 5",
    "sg:city":"Sulzberg",
    "sg:phone":"+49 8376/9769051",
    "sg:postcode":"87477",
    "sg:province":"Bayern",
    "wof:name":"K\u00f6nigl & H\u00f6rmann Gmbh",
    "wof:placetype":"venue"
},
  "geometry": {"coordinates":[10.3421459198,47.6572036743],"type":"Point"}
}