{
  "type": "Feature",
  "properties": {
    "iso:country":"DE",
    "sg:address":"L\u00fcneburger Str. 11",
    "sg:city":"Bad Bevensen",
    "sg:phone":"+49 5821/1755",
    "sg:postcode":"29549",
    "sg:province":"Niedersachsen",
    "wof:name":"Mode-treff Sommer Gmbh",
    "wof:placetype":"venue"
},
  "geometry": {"coordinates":[10.5794038773,53.0803604126],"type":"Point"}
}