{
  "type": "Feature",
  "properties": {
    "iso:country":"DE",
    "sg:address":"Steyler Str 19",
    "sg:city":"K\u00f6ln",
    "sg:phone":"+49 221/9635440",
    "sg:postcode":"51067",
    "sg:province":"Nordrhein-Westfalen",
    "wof:name":"Wilhelm Knetsch Metallbau Gmbh",
    "wof:placetype":"venue"
},
  "geometry": {"coordinates":[7.0345959663,50.9664916992],"type":"Point"}
}