{
  "type": "Feature",
  "properties": {
    "iso:country":"DE",
    "sg:address":"Rather Ring 10",
    "sg:city":"Remscheid",
    "sg:phone":"+49 2191/49550",
    "sg:postcode":"42855",
    "sg:province":"Nordrhein-Westfalen",
    "wof:name":"Hywus Hydraulik Service Gmbh",
    "wof:placetype":"venue"
},
  "geometry": {"coordinates":[7.1822228432,51.1944046021],"type":"Point"}
}