{
  "type": "Feature",
  "properties": {
    "iso:country":"DE",
    "sg:address":"Zollersb\u00fchnstrasse 3",
    "sg:city":"Rastatt",
    "sg:phone":"+49 7222/83677",
    "sg:postcode":"76437",
    "sg:province":"Baden-W\u00fcrttemberg",
    "wof:name":"K S Kfz-recycling",
    "wof:placetype":"venue"
},
  "geometry": {"coordinates":[8.232387,48.858799],"type":"Point"}
}