{
  "type": "Feature",
  "properties": {
    "iso:country":"DE",
    "sg:address":"Ringstr. 90",
    "sg:city":"Aalen",
    "sg:phone":"+49 7367/7952",
    "sg:postcode":"73432",
    "sg:province":"Baden-W\u00fcrttemberg",
    "wof:name":"Matrica Gmbh",
    "wof:placetype":"venue"
},
  "geometry": {"coordinates":[10.177772,48.796833],"type":"Point"}
}