{
  "type": "Feature",
  "properties": {
    "iso:country":"DE",
    "sg:address":"Lise-Meitner-Str. 1",
    "sg:city":"Wallenhorst",
    "sg:postcode":"49134",
    "sg:province":"Niedersachsen",
    "wof:name":"Fluiten Deutschland Gmbh",
    "wof:placetype":"venue"
},
  "geometry": {"coordinates":[7.969773,52.352795],"type":"Point"}
}