{
  "type": "Feature",
  "properties": {
    "iso:country":"DE",
    "sg:address":"Wahrburger Str. 44",
    "sg:city":"Stendal",
    "sg:phone":"+49 3931/312807",
    "sg:postcode":"39576",
    "sg:province":"Sachsen-Anhalt",
    "wof:name":"Mario Westphal",
    "wof:placetype":"venue"
},
  "geometry": {"coordinates":[11.8342599869,52.5941925049],"type":"Point"}
}