{
  "type": "Feature",
  "properties": {
    "iso:country":"DE",
    "sg:address":"Kurf\u00fcrstendamm 213",
    "sg:city":"Berlin",
    "sg:phone":"+49 30/8817794",
    "sg:postcode":"10719",
    "sg:province":"Berlin",
    "wof:name":"K.-h. Oehler C. H\u00f6wing H.-th. Rosenkranz",
    "wof:placetype":"venue"
},
  "geometry": {"coordinates":[13.3260803223,52.5024604797],"type":"Point"}
}