{
  "type": "Feature",
  "properties": {
    "iso:country":"DE",
    "sg:address":"Hauptstr. 55",
    "sg:city":"Gersdorf-M\u00f6hrsdorf",
    "sg:phone":"+49 35787/1205",
    "sg:postcode":"01920",
    "sg:province":"Sachsen",
    "wof:name":"Gunther Fr\u00f6hlich",
    "wof:placetype":"venue"
},
  "geometry": {"coordinates":[14.0490722656,51.232257843],"type":"Point"}
}