{
  "type": "Feature",
  "properties": {
    "iso:country":"DE",
    "sg:address":"Kleikstr. 16",
    "sg:city":"Herzogenrath",
    "sg:phone":"+49 2406/5555",
    "sg:postcode":"52134",
    "sg:province":"Nordrhein-Westfalen",
    "wof:name":"M. Bierth",
    "wof:placetype":"venue"
},
  "geometry": {"coordinates":[6.095683,50.868786],"type":"Point"}
}