{
  "type": "Feature",
  "properties": {
    "iso:country":"DE",
    "sg:address":"Ellernbrook 25",
    "sg:city":"Bad Schwartau",
    "sg:phone":"+49 451/2900177",
    "sg:postcode":"23611",
    "sg:province":"Schleswig-Holstein",
    "wof:name":"Marowski Gmbh",
    "wof:placetype":"venue"
},
  "geometry": {"coordinates":[10.6942901611,53.9277992249],"type":"Point"}
}