{
  "type": "Feature",
  "properties": {
    "iso:country":"DE",
    "sg:address":"Rathausplatz 6",
    "sg:city":"Augsburg",
    "sg:phone":"+49 821/30122",
    "sg:postcode":"86150",
    "sg:province":"Bayern",
    "wof:name":"Hermann Jaufmann Kg",
    "wof:placetype":"venue"
},
  "geometry": {"coordinates":[10.8981323242,48.3692245483],"type":"Point"}
}