{
  "type": "Feature",
  "properties": {
    "iso:country":"DE",
    "sg:address":"Salzburger Str. 74",
    "sg:city":"Bad Reichenhall",
    "sg:postcode":"83435",
    "sg:province":"Bayern",
    "wof:name":"Reichenhaller-tiefbau Gmbh",
    "wof:placetype":"venue"
},
  "geometry": {"coordinates":[12.8992433548,47.74168396],"type":"Point"}
}