{
  "type": "Feature",
  "properties": {
    "iso:country":"DE",
    "sg:address":"Julius-Motteler-Str. 8",
    "sg:city":"Esslingen",
    "sg:phone":"+49 711/3167402",
    "sg:postcode":"73728",
    "sg:province":"Baden-W\u00fcrttemberg",
    "wof:name":"Beutel Malerwerkst\u00e4tte Gmbh",
    "wof:placetype":"venue"
},
  "geometry": {"coordinates":[9.318074,48.735504],"type":"Point"}
}