{
  "type": "Feature",
  "properties": {
    "iso:country":"DE",
    "sg:address":"Kaiserwall 15",
    "sg:city":"Recklinghausen",
    "sg:phone":"+49 2361/25511",
    "sg:postcode":"45657",
    "sg:province":"Nordrhein-Westfalen",
    "wof:name":"Dieter Knabe Architekt",
    "wof:placetype":"venue"
},
  "geometry": {"coordinates":[7.199026,51.612068],"type":"Point"}
}