{
  "type": "Feature",
  "properties": {
    "iso:country":"DE",
    "sg:address":"Vorderfreundorfer Str.",
    "sg:city":"Grainet",
    "sg:phone":"+49 8585/343",
    "sg:postcode":"94143",
    "sg:province":"Bayern",
    "wof:name":"Rudolf Hoffmann",
    "wof:placetype":"venue"
},
  "geometry": {"coordinates":[13.656003,48.791843],"type":"Point"}
}