{
  "type": "Feature",
  "properties": {
    "iso:country":"DE",
    "sg:address":"Am Geisberg 17",
    "sg:city":"Goldbach",
    "sg:phone":"+49 6021/52165",
    "sg:postcode":"63773",
    "sg:province":"Bayern",
    "wof:name":"Robert Stenger Ingenieur",
    "wof:placetype":"venue"
},
  "geometry": {"coordinates":[9.1791477203,50.00050354],"type":"Point"}
}