{
  "type": "Feature",
  "properties": {
    "iso:country":"DE",
    "sg:address":"Judengasse 4",
    "sg:city":"Weiden",
    "sg:phone":"+49 961/7222",
    "sg:postcode":"92637",
    "sg:province":"Bayern",
    "wof:name":"Diskothek Nachtexpress",
    "wof:placetype":"venue"
},
  "geometry": {"coordinates":[12.162877,49.674767],"type":"Point"}
}