{
  "type": "Feature",
  "properties": {
    "iso:country":"DE",
    "sg:address":"Friedrichsfehner Str. 16",
    "sg:city":"Edewecht",
    "sg:phone":"+49 4486/2810",
    "sg:postcode":"26188",
    "sg:province":"Niedersachsen",
    "wof:name":"Eduard Pfitzner",
    "wof:placetype":"venue"
},
  "geometry": {"coordinates":[8.0919456482,53.1249198914],"type":"Point"}
}