{
  "type": "Feature",
  "properties": {
    "iso:country":"DE",
    "sg:address":"Dellbr\u00fccker Mauspfad 319",
    "sg:city":"K\u00f6ln",
    "sg:phone":"+49 221/6893080",
    "sg:postcode":"51069",
    "sg:province":"Nordrhein-Westfalen",
    "wof:name":"Bj\u00f6rnsen Beratende Ingenieure K\u00f6ln Gmbh",
    "wof:placetype":"venue"
},
  "geometry": {"coordinates":[7.063603,50.973568],"type":"Point"}
}