{
  "type": "Feature",
  "properties": {
    "iso:country":"DE",
    "sg:address":"Eichenring 21",
    "sg:city":"Uelzen",
    "sg:phone":"+49 581/9765900",
    "sg:postcode":"29525",
    "sg:province":"Niedersachsen",
    "wof:name":"Heuer's Landhaus",
    "wof:placetype":"venue"
},
  "geometry": {"coordinates":[10.4847421646,52.9360084534],"type":"Point"}
}