{
  "type": "Feature",
  "properties": {
    "iso:country":"DE",
    "sg:address":"Posthof 8",
    "sg:city":"Waldm\u00fcnchen",
    "sg:postcode":"93449",
    "sg:province":"Bayern",
    "wof:name":"Residenz Wohnpark Waldm\u00fcnchen Gmbh & Co. Kg",
    "wof:placetype":"venue"
},
  "geometry": {"coordinates":[12.759224,49.356087],"type":"Point"}
}