{
  "type": "Feature",
  "properties": {
    "iso:country":"DE",
    "sg:address":"B\u00e4ckerstr. 13",
    "sg:city":"Torgau",
    "sg:phone":"+49 3421/903301",
    "sg:postcode":"04860",
    "sg:province":"Sachsen",
    "wof:name":"Schwalbe Musikhaus",
    "wof:placetype":"venue"
},
  "geometry": {"coordinates":[13.0041007996,51.5598106384],"type":"Point"}
}