{
  "type": "Feature",
  "properties": {
    "iso:country":"DE",
    "sg:address":"Hauptstr. 111",
    "sg:city":"Stolpen",
    "sg:postcode":"01833",
    "sg:province":"Sachsen",
    "wof:name":"Evangelisches Pfarramt",
    "wof:placetype":"venue"
},
  "geometry": {"coordinates":[14.0908002853,51.0390701294],"type":"Point"}
}