{
  "type": "Feature",
  "properties": {
    "iso:country":"DE",
    "sg:address":"G\u00e4nsberg 9",
    "sg:city":"Spiesen-Elversberg",
    "sg:phone":"+49 6821/7609",
    "sg:postcode":"66583",
    "sg:province":"Saarland",
    "wof:name":"Egon Bischof",
    "wof:placetype":"venue"
},
  "geometry": {"coordinates":[7.153232,49.315197],"type":"Point"}
}