{
  "type": "Feature",
  "properties": {
    "iso:country":"DE",
    "sg:address":"Goebenstr. 12a",
    "sg:city":"Berlin",
    "sg:postcode":"10783",
    "sg:province":"Berlin",
    "wof:name":"Unternehmensgruppe Team 9001 Planungs- Und",
    "wof:placetype":"venue"
},
  "geometry": {"coordinates":[13.365757,52.493347],"type":"Point"}
}