{
  "type": "Feature",
  "properties": {
    "iso:country":"DE",
    "sg:address":"Ecknachweg 5",
    "sg:city":"Friedberg",
    "sg:phone":"+49 821/601369",
    "sg:postcode":"86316",
    "sg:province":"Bayern",
    "wof:name":"Dr. Gert Kleist Tierarzt",
    "wof:placetype":"venue"
},
  "geometry": {"coordinates":[10.9888954163,48.3495063782],"type":"Point"}
}