{
  "type": "Feature",
  "properties": {
    "iso:country":"DE",
    "sg:address":"Glauchauer Str. 39",
    "sg:city":"Lichtenstein",
    "sg:phone":"+49 37204/5100",
    "sg:postcode":"09350",
    "sg:province":"Sachsen",
    "wof:name":"Dr. Frank Waniak",
    "wof:placetype":"venue"
},
  "geometry": {"coordinates":[12.6268053055,50.7627830505],"type":"Point"}
}