{
  "type": "Feature",
  "properties": {
    "iso:country":"DE",
    "sg:address":"Dermbacher Str. 5",
    "sg:city":"Weilar",
    "sg:phone":"+49 36965/60463",
    "sg:postcode":"36457",
    "sg:province":"Th\u00fcringen",
    "wof:name":"Kellerhaus",
    "wof:placetype":"venue"
},
  "geometry": {"coordinates":[10.1512537003,50.7607345581],"type":"Point"}
}