{
  "type": "Feature",
  "properties": {
    "iso:country":"DE",
    "sg:address":"Vossum 43 A",
    "sg:city":"Straelen",
    "sg:phone":"+49 2834/305",
    "sg:postcode":"47638",
    "sg:province":"Nordrhein-Westfalen",
    "wof:name":"Gerh. Peters",
    "wof:placetype":"venue"
},
  "geometry": {"coordinates":[6.264488,51.464397],"type":"Point"}
}