{
  "type": "Feature",
  "properties": {
    "iso:country":"DE",
    "sg:address":"Heinrichstr. 1",
    "sg:city":"Meppen",
    "sg:phone":"+49 5935/391",
    "sg:postcode":"49716",
    "sg:province":"Niedersachsen",
    "wof:name":"Heinrich Altmeppen",
    "wof:placetype":"venue"
},
  "geometry": {"coordinates":[7.203217,52.728794],"type":"Point"}
}