{
  "type": "Feature",
  "properties": {
    "iso:country":"DE",
    "sg:address":"Paulinenstr. 98",
    "sg:city":"Friedrichshafen",
    "sg:phone":"+49 7541/73233",
    "sg:postcode":"88046",
    "sg:province":"Baden-W\u00fcrttemberg",
    "wof:name":"Kath. Pfarramt St. Columban",
    "wof:placetype":"venue"
},
  "geometry": {"coordinates":[9.4956769943,47.6584243774],"type":"Point"}
}