{
  "type": "Feature",
  "properties": {
    "iso:country":"DE",
    "sg:address":"Nordendstr. 79-87",
    "sg:city":"M\u00f6rfelden-Walldorf",
    "sg:phone":"+49 6105/7040",
    "sg:postcode":"64546",
    "sg:province":"Hessen",
    "wof:name":"Cadillon Baumaschinen Gmbh",
    "wof:placetype":"venue"
},
  "geometry": {"coordinates":[8.589473,50.016647],"type":"Point"}
}