{
  "type": "Feature",
  "properties": {
    "iso:country":"DE",
    "sg:address":"Liebfrauenstr. 22",
    "sg:city":"Oberursel",
    "sg:phone":"+49 6171/53963",
    "sg:postcode":"61440",
    "sg:province":"Hessen",
    "wof:name":"Raphael-therapeutikum Physiotherapie",
    "wof:placetype":"venue"
},
  "geometry": {"coordinates":[8.586227,50.202461],"type":"Point"}
}