{
  "type": "Feature",
  "properties": {
    "iso:country":"DE",
    "sg:address":"Landhausstr. 9",
    "sg:city":"Berlin",
    "sg:phone":"+49 30/875790",
    "sg:postcode":"10717",
    "sg:province":"Berlin",
    "wof:name":"F. De Almeida Dolmetscher",
    "wof:placetype":"venue"
},
  "geometry": {"coordinates":[13.328485,52.489826],"type":"Point"}
}