{
  "type": "Feature",
  "properties": {
    "iso:country":"DE",
    "sg:address":"Steinstr. 3/1",
    "sg:city":"Heimsheim",
    "sg:phone":"+49 4970/3353740",
    "sg:postcode":"71296",
    "sg:province":"Baden-W\u00fcrttemberg",
    "wof:name":"Pmt Partikel-messtechnik Ag",
    "wof:placetype":"venue"
},
  "geometry": {"coordinates":[8.866963,48.806286],"type":"Point"}
}