{
  "type": "Feature",
  "properties": {
    "iso:country":"DE",
    "sg:address":"Blosbergstr. 4",
    "sg:city":"Braubach",
    "sg:phone":"+49 2627/283",
    "sg:postcode":"56338",
    "sg:province":"Rheinland-Pfalz",
    "wof:name":"Franz-peter Geisb\u00fcsch",
    "wof:placetype":"venue"
},
  "geometry": {"coordinates":[7.635003,50.28236],"type":"Point"}
}