{
  "type": "Feature",
  "properties": {
    "iso:country":"DE",
    "sg:address":"Lindelbrunnstr. 21",
    "sg:city":"Hauenstein",
    "sg:phone":"+49 6392/2973",
    "sg:postcode":"76846",
    "sg:province":"Rheinland-Pfalz",
    "wof:name":"R. St\u00f6bener",
    "wof:placetype":"venue"
},
  "geometry": {"coordinates":[7.8494238853,49.1882705688],"type":"Point"}
}