{
  "type": "Feature",
  "properties": {
    "iso:country":"DE",
    "sg:address":"Auerbacher Str. 57",
    "sg:city":"Klingenthal",
    "sg:phone":"+49 37467/23474",
    "sg:postcode":"08248",
    "sg:province":"Sachsen",
    "wof:name":"Bauernfeind",
    "wof:placetype":"venue"
},
  "geometry": {"coordinates":[12.469834,50.36158],"type":"Point"}
}