{
  "type": "Feature",
  "properties": {
    "iso:country":"DE",
    "sg:address":"Vogelsang 14",
    "sg:city":"Eckernf\u00f6rde",
    "sg:postcode":"24340",
    "sg:province":"Schleswig-Holstein",
    "wof:name":"E. Lorenzen & A. Schulz Kg",
    "wof:placetype":"venue"
},
  "geometry": {"coordinates":[9.8356962204,54.4755821228],"type":"Point"}
}