{
  "type": "Feature",
  "properties": {
    "iso:country":"DE",
    "sg:address":"Krummecke 25",
    "sg:city":"Essen",
    "sg:phone":"+49 201/581651",
    "sg:postcode":"45277",
    "sg:province":"Nordrhein-Westfalen",
    "wof:name":"M. Wenzel",
    "wof:placetype":"venue"
},
  "geometry": {"coordinates":[7.076961,51.420666],"type":"Point"}
}