{
  "type": "Feature",
  "properties": {
    "iso:country":"DE",
    "sg:address":"Alt-Wittenau 92/94",
    "sg:city":"Berlin",
    "sg:phone":"+49 30/4112082",
    "sg:postcode":"13437",
    "sg:province":"Berlin",
    "wof:name":"Kurt H\u00fcbner Fensterbau Gmbh & Co Kg",
    "wof:placetype":"venue"
},
  "geometry": {"coordinates":[13.3369379044,52.5893669128],"type":"Point"}
}