{
  "type": "Feature",
  "properties": {
    "iso:country":"DE",
    "sg:address":"Guerickestr. 3",
    "sg:city":"Berlin",
    "sg:phone":"+49 30/3479910",
    "sg:postcode":"10587",
    "sg:province":"Berlin",
    "wof:name":"Franz Xaver Meiller Fahrzeug- Und Maschinenfabrik-",
    "wof:placetype":"venue"
},
  "geometry": {"coordinates":[13.314944,52.517868],"type":"Point"}
}