{
  "type": "Feature",
  "properties": {
    "iso:country":"DE",
    "sg:address":"Am Blauen Stein 17 A",
    "sg:city":"Wolfenb\u00fcttel",
    "sg:phone":"+49 5331/75599",
    "sg:postcode":"38302",
    "sg:province":"Niedersachsen",
    "wof:name":"Rene Junke",
    "wof:placetype":"venue"
},
  "geometry": {"coordinates":[10.5521821976,52.1787147522],"type":"Point"}
}