{
  "type": "Feature",
  "properties": {
    "iso:country":"DE",
    "sg:address":"Volkwinweg 1",
    "sg:city":"Schieder-Schwalenberg",
    "sg:phone":"+49 5284/329",
    "sg:postcode":"32816",
    "sg:province":"Nordrhein-Westfalen",
    "wof:name":"Alfred Hintz",
    "wof:placetype":"venue"
},
  "geometry": {"coordinates":[9.191425,51.878433],"type":"Point"}
}