{
  "type": "Feature",
  "properties": {
    "iso:country":"DE",
    "sg:address":"Nellinger Str. 47",
    "sg:city":"Ostfildern",
    "sg:phone":"+49 7158/63322",
    "sg:postcode":"73760",
    "sg:province":"Baden-W\u00fcrttemberg",
    "wof:name":"Norbert Lamprecht Ingenieur Und Architekt",
    "wof:placetype":"venue"
},
  "geometry": {"coordinates":[9.266862,48.709267],"type":"Point"}
}