{
  "type": "Feature",
  "properties": {
    "iso:country":"DE",
    "sg:address":"Breddert 41",
    "sg:city":"Hilden",
    "sg:phone":"+49 2103/61430",
    "sg:postcode":"40723",
    "sg:province":"Nordrhein-Westfalen",
    "wof:name":"Hans Schuhmann Ingenieur",
    "wof:placetype":"venue"
},
  "geometry": {"coordinates":[6.9545731544,51.1603851318],"type":"Point"}
}