{
  "type": "Feature",
  "properties": {
    "iso:country":"DE",
    "sg:address":"Bachenstr. 5",
    "sg:city":"Villingen-Schwenningen",
    "sg:phone":"+49 7720/31104",
    "sg:postcode":"78054",
    "sg:province":"Baden-W\u00fcrttemberg",
    "wof:name":"Willy Fuchs",
    "wof:placetype":"venue"
},
  "geometry": {"coordinates":[8.5291347504,48.0587539673],"type":"Point"}
}