{
  "type": "Feature",
  "properties": {
    "iso:country":"DE",
    "sg:address":"Rheing\u00f6nheimer Str. 66",
    "sg:city":"Ludwigshafen",
    "sg:postcode":"67065",
    "sg:province":"Rheinland-Pfalz",
    "wof:name":"G. L. E. Emanuele Gmbh",
    "wof:placetype":"venue"
},
  "geometry": {"coordinates":[8.427794,49.45932],"type":"Point"}
}