{
  "type": "Feature",
  "properties": {
    "iso:country":"DE",
    "sg:address":"Idsteiner Str. 106",
    "sg:city":"Frankfurt",
    "sg:postcode":"60326",
    "sg:province":"Hessen",
    "wof:name":"Euro Medien Telecom Gmbh",
    "wof:placetype":"venue"
},
  "geometry": {"coordinates":[8.6273880005,50.1053390503],"type":"Point"}
}