{
  "type": "Feature",
  "properties": {
    "iso:country":"DE",
    "sg:address":"Grabenstr. 4",
    "sg:city":"Spaichingen",
    "sg:phone":"+49 7424/2390",
    "sg:postcode":"78549",
    "sg:province":"Baden-W\u00fcrttemberg",
    "wof:name":"Walter Merkt",
    "wof:placetype":"venue"
},
  "geometry": {"coordinates":[8.734045,48.082012],"type":"Point"}
}