{
  "type": "Feature",
  "properties": {
    "iso:country":"DE",
    "sg:address":"Pinsweilerstr. 6",
    "sg:city":"Namborn",
    "sg:phone":"+49 6857/69346",
    "sg:postcode":"66640",
    "sg:province":"Saarland",
    "wof:name":"Profi Haus Wohn - Und Gewerbeobjekte Gmbh",
    "wof:placetype":"venue"
},
  "geometry": {"coordinates":[7.163716,49.526413],"type":"Point"}
}