{
  "type": "Feature",
  "properties": {
    "iso:country":"DE",
    "sg:address":"Freesenburg 8",
    "sg:city":"Neum\u00fcnster",
    "sg:phone":"+49 4321/18080",
    "sg:postcode":"24537",
    "sg:province":"Schleswig-Holstein",
    "wof:name":"M\u00f6bel Br\u00fcgge Thomas Br\u00fcgge Gmbh",
    "wof:placetype":"venue"
},
  "geometry": {"coordinates":[9.937420845,54.0702056885],"type":"Point"}
}