{
  "type": "Feature",
  "properties": {
    "iso:country":"DE",
    "sg:address":"Talstr. 69 b",
    "sg:city":"Stuttgart",
    "sg:postcode":"70188",
    "sg:province":"Baden-W\u00fcrttemberg",
    "wof:name":"Loft Conzept Gmbh",
    "wof:placetype":"venue"
},
  "geometry": {"coordinates":[9.2149925232,48.7854995728],"type":"Point"}
}