{
  "type": "Feature",
  "properties": {
    "iso:country":"DE",
    "sg:address":"Poststr. 12-14",
    "sg:city":"Radolfzell",
    "sg:phone":"+49 7732/971945",
    "sg:postcode":"78315",
    "sg:province":"Baden-W\u00fcrttemberg",
    "wof:name":"Schulung Und Ausbildungscenter",
    "wof:placetype":"venue"
},
  "geometry": {"coordinates":[8.96841,47.73806],"type":"Point"}
}