{
  "type": "Feature",
  "properties": {
    "iso:country":"DE",
    "sg:address":"Entenseestr. 31",
    "sg:city":"R\u00fcckersdorf",
    "sg:phone":"+49 911/579393",
    "sg:postcode":"90607",
    "sg:province":"Bayern",
    "wof:name":"Der Schreiner Kurzmann Inh. Heinz Kurzmann",
    "wof:placetype":"venue"
},
  "geometry": {"coordinates":[11.232084,49.494553],"type":"Point"}
}