{
  "type": "Feature",
  "properties": {
    "iso:country":"DE",
    "sg:address":"Harsefelder Str. 83",
    "sg:city":"Stade",
    "sg:phone":"+49 4141/609702",
    "sg:postcode":"21680",
    "sg:province":"Niedersachsen",
    "wof:name":"H.-j. Peter Architekt",
    "wof:placetype":"venue"
},
  "geometry": {"coordinates":[9.473085,53.58783],"type":"Point"}
}