{
  "type": "Feature",
  "properties": {
    "iso:country":"DE",
    "sg:address":"Topasstr. 4",
    "sg:city":"Bielefeld",
    "sg:phone":"+49 521/890897",
    "sg:postcode":"33739",
    "sg:province":"Nordrhein-Westfalen",
    "wof:name":"Hartmut Vogel",
    "wof:placetype":"venue"
},
  "geometry": {"coordinates":[8.5175447464,52.0715103149],"type":"Point"}
}