{
  "type": "Feature",
  "properties": {
    "iso:country":"DE",
    "sg:address":"Kutterstr. 3",
    "sg:city":"Wilhelmshaven",
    "sg:postcode":"26386",
    "sg:province":"Niedersachsen",
    "wof:name":"Biosphere Ag",
    "wof:placetype":"venue"
},
  "geometry": {"coordinates":[8.1163234711,53.5704154968],"type":"Point"}
}