{
  "type": "Feature",
  "properties": {
    "iso:country":"DE",
    "sg:address":"Werrenwiesenstr. 84",
    "sg:city":"Schw\u00e4bisch Gm\u00fcnd",
    "sg:phone":"+49 7171/10070",
    "sg:postcode":"73525",
    "sg:province":"Baden-W\u00fcrttemberg",
    "wof:name":"Starz Verwaltungs- Gmbh",
    "wof:placetype":"venue"
},
  "geometry": {"coordinates":[9.82756,48.79924],"type":"Point"}
}