{
  "type": "Feature",
  "properties": {
    "iso:country":"DE",
    "sg:address":"Brunhildenstr. 35",
    "sg:city":"Neubiberg",
    "sg:phone":"+49 89/9287900",
    "sg:postcode":"85579",
    "sg:province":"Bayern",
    "wof:name":"Cps Beratungs-gesellschaft Zur Durchf\u00fchrung Wissen- Und",
    "wof:placetype":"venue"
},
  "geometry": {"coordinates":[11.6810750961,48.077709198],"type":"Point"}
}