{
  "type": "Feature",
  "properties": {
    "iso:country":"DE",
    "sg:address":"Geiststr. 3",
    "sg:city":"M\u00fcnster",
    "sg:phone":"+49 251/525394",
    "sg:postcode":"48151",
    "sg:province":"Nordrhein-Westfalen",
    "wof:name":"Marianne Holling Heilpraktikerin",
    "wof:placetype":"venue"
},
  "geometry": {"coordinates":[7.6196250916,51.9526062012],"type":"Point"}
}