{
  "type": "Feature",
  "properties": {
    "iso:country":"DE",
    "sg:address":"Bahnhofstr.",
    "sg:city":"Kalbe",
    "sg:phone":"+49 39080/3597",
    "sg:postcode":"39624",
    "sg:province":"Sachsen-Anhalt",
    "wof:name":"Bahnhofsgastst\u00e4tte Inh. Holger Riestock",
    "wof:placetype":"venue"
},
  "geometry": {"coordinates":[9.5503978729,53.2931861877],"type":"Point"}
}