{
  "type": "Feature",
  "properties": {
    "iso:country":"DE",
    "sg:address":"F\u00fcnfhausener Str. 35",
    "sg:city":"Hamburg",
    "sg:phone":"+49 40/770355",
    "sg:postcode":"21079",
    "sg:province":"Hamburg",
    "wof:name":"M. Schulenburg",
    "wof:placetype":"venue"
},
  "geometry": {"coordinates":[10.045529,53.466492],"type":"Point"}
}