{
  "type": "Feature",
  "properties": {
    "iso:country":"DE",
    "sg:address":"Tempelhofer Damm 129",
    "sg:city":"Berlin",
    "sg:phone":"+49 30/75707172",
    "sg:postcode":"12099",
    "sg:province":"Berlin",
    "wof:name":"Elke S\u00f6rensen Praxis F\u00fcr Ergotherapie",
    "wof:placetype":"venue"
},
  "geometry": {"coordinates":[13.385887,52.468014],"type":"Point"}
}