{
  "type": "Feature",
  "properties": {
    "iso:country":"DE",
    "sg:address":"Dellwiger Str. 305",
    "sg:city":"Dortmund",
    "sg:phone":"+49 231/691923",
    "sg:postcode":"44388",
    "sg:province":"Nordrhein-Westfalen",
    "wof:name":"W\u00fcstefeld Gmbh & Co. Kg",
    "wof:placetype":"venue"
},
  "geometry": {"coordinates":[7.32526,51.506973],"type":"Point"}
}