{
  "type": "Feature",
  "properties": {
    "iso:country":"DE",
    "sg:address":"Am S\u00fcdfriedhof 18 b",
    "sg:city":"D\u00fcsseldorf",
    "sg:phone":"+49 211/155084",
    "sg:postcode":"40221",
    "sg:province":"Nordrhein-Westfalen",
    "wof:name":"Manfred R\u00f6hlen",
    "wof:placetype":"venue"
},
  "geometry": {"coordinates":[6.754769,51.199959],"type":"Point"}
}