{
  "type": "Feature",
  "properties": {
    "iso:country":"DE",
    "sg:address":"Lochfeldstr. 19",
    "sg:city":"Rastatt",
    "sg:postcode":"76437",
    "sg:province":"Baden-W\u00fcrttemberg",
    "wof:name":"Bera Gmbh",
    "wof:placetype":"venue"
},
  "geometry": {"coordinates":[8.2241487503,48.8569717407],"type":"Point"}
}