{
  "type": "Feature",
  "properties": {
    "iso:country":"DE",
    "sg:address":"Schenkstr. 42",
    "sg:city":"Wuppertal",
    "sg:phone":"+49 202/462665",
    "sg:postcode":"42369",
    "sg:province":"Nordrhein-Westfalen",
    "wof:name":"K. Wilde Bauunternehmen",
    "wof:placetype":"venue"
},
  "geometry": {"coordinates":[7.202912,51.22261],"type":"Point"}
}