{
  "type": "Feature",
  "properties": {
    "iso:country":"DE",
    "sg:address":"Grabenstr. 24",
    "sg:city":"Oelsnitz",
    "sg:phone":"+49 37421/27632",
    "sg:postcode":"08606",
    "sg:province":"Sachsen",
    "wof:name":"Elster-apotheke",
    "wof:placetype":"venue"
},
  "geometry": {"coordinates":[12.170679,50.416042],"type":"Point"}
}