{
  "type": "Feature",
  "properties": {
    "iso:country":"DE",
    "sg:address":"Schmittstr. 43",
    "sg:city":"Swisttal",
    "sg:phone":"+49 2226/17675",
    "sg:postcode":"53913",
    "sg:province":"Nordrhein-Westfalen",
    "wof:name":"B. Kleber Immobilienmakler",
    "wof:placetype":"venue"
},
  "geometry": {"coordinates":[6.9728808403,50.6837692261],"type":"Point"}
}