{
  "type": "Feature",
  "properties": {
    "iso:country":"DE",
    "sg:address":"Bergstr. 7 a",
    "sg:city":"Uetersen",
    "sg:phone":"+49 4122/900929",
    "sg:postcode":"25436",
    "sg:province":"Schleswig-Holstein",
    "wof:name":"H. Strehlke",
    "wof:placetype":"venue"
},
  "geometry": {"coordinates":[9.6679439545,53.6859664917],"type":"Point"}
}