{
  "type": "Feature",
  "properties": {
    "iso:country":"DE",
    "sg:address":"Friedenstr. 7",
    "sg:city":"Kleinheubach",
    "sg:phone":"+49 9371/4947",
    "sg:postcode":"63924",
    "sg:province":"Bayern",
    "wof:name":"I. Freudenberger",
    "wof:placetype":"venue"
},
  "geometry": {"coordinates":[9.2147722244,49.7200431824],"type":"Point"}
}