{
  "type": "Feature",
  "properties": {
    "iso:country":"DE",
    "sg:address":"Marienstr. 11",
    "sg:city":"Sch\u00f6ntal",
    "sg:phone":"+49 7943/2305",
    "sg:postcode":"74214",
    "sg:province":"Baden-W\u00fcrttemberg",
    "wof:name":"Otto Kappes",
    "wof:placetype":"venue"
},
  "geometry": {"coordinates":[9.4836101532,49.3670387268],"type":"Point"}
}