{
  "type": "Feature",
  "properties": {
    "iso:country":"DE",
    "sg:address":"Breite Str. 13",
    "sg:city":"P\u00f6\u00dfneck",
    "sg:phone":"+49 3647/412560",
    "sg:postcode":"07381",
    "sg:province":"Th\u00fcringen",
    "wof:name":"L. Naumann",
    "wof:placetype":"venue"
},
  "geometry": {"coordinates":[11.5926456451,50.6951026917],"type":"Point"}
}