{
  "type": "Feature",
  "properties": {
    "iso:country":"DE",
    "sg:address":"Am R\u00e4uberberg",
    "sg:city":"Zernien",
    "sg:phone":"+49 5863/518",
    "sg:postcode":"29499",
    "sg:province":"Niedersachsen",
    "wof:name":"Waldbad",
    "wof:placetype":"venue"
},
  "geometry": {"coordinates":[10.886680603,53.075340271],"type":"Point"}
}