{
  "type": "Feature",
  "properties": {
    "iso:country":"DE",
    "sg:address":"Bahnhofstr. 10",
    "sg:city":"Altenstadt",
    "sg:phone":"+49 8337/7260",
    "sg:postcode":"89281",
    "sg:province":"Bayern",
    "wof:name":"Hotel Garni Sonne",
    "wof:placetype":"venue"
},
  "geometry": {"coordinates":[10.1105089188,48.1612091064],"type":"Point"}
}