{
  "type": "Feature",
  "properties": {
    "iso:country":"DE",
    "sg:address":"Wernerstr. 45",
    "sg:city":"Dresden",
    "sg:phone":"+49 351/4212473",
    "sg:postcode":"01159",
    "sg:province":"Sachsen",
    "wof:name":"Zum Frieden",
    "wof:placetype":"venue"
},
  "geometry": {"coordinates":[13.697787,51.043674],"type":"Point"}
}