{
  "type": "Feature",
  "properties": {
    "iso:country":"DE",
    "sg:address":"Schwarzbach 170b",
    "sg:city":"Wuppertal",
    "sg:phone":"+49 202/644595",
    "sg:postcode":"42277",
    "sg:province":"Nordrhein-Westfalen",
    "wof:name":"H. W. Suhre Gmbh & Co. Kg",
    "wof:placetype":"venue"
},
  "geometry": {"coordinates":[7.2293848991,51.2850265503],"type":"Point"}
}