{
  "type": "Feature",
  "properties": {
    "iso:country":"DE",
    "sg:address":"Zollstr. 47",
    "sg:city":"Rheinm\u00fcnster",
    "sg:phone":"+49 7227/2514",
    "sg:postcode":"77836",
    "sg:province":"Baden-W\u00fcrttemberg",
    "wof:name":"Kleintierzuchtverein Schwarzbach",
    "wof:placetype":"venue"
},
  "geometry": {"coordinates":[8.0022697449,48.7506141663],"type":"Point"}
}