{
  "type": "Feature",
  "properties": {
    "iso:country":"DE",
    "sg:address":"Im Buschgewann 116",
    "sg:city":"Heidelberg",
    "sg:phone":"+49 6221/707967",
    "sg:postcode":"69123",
    "sg:province":"Baden-W\u00fcrttemberg",
    "wof:name":"Hannibal L\u00fcttichau Steuerberater Und",
    "wof:placetype":"venue"
},
  "geometry": {"coordinates":[8.6392908096,49.3965454102],"type":"Point"}
}