{
  "type": "Feature",
  "properties": {
    "iso:country":"DE",
    "sg:address":"Friedrichstr. 7",
    "sg:city":"Sch\u00f6nebeck",
    "sg:phone":"+49 3928/69272",
    "sg:postcode":"39218",
    "sg:province":"Sachsen-Anhalt",
    "wof:name":"Gerhard L\u00f6bner",
    "wof:placetype":"venue"
},
  "geometry": {"coordinates":[11.734428,52.016022],"type":"Point"}
}