{
  "type": "Feature",
  "properties": {
    "iso:country":"DE",
    "sg:address":"Berliner Str. 106",
    "sg:city":"Berlin",
    "sg:phone":"+49 30/8233832",
    "sg:postcode":"10713",
    "sg:province":"Berlin",
    "wof:name":"Blumenhaus Riegel",
    "wof:placetype":"venue"
},
  "geometry": {"coordinates":[13.313413,52.486725],"type":"Point"}
}