{
  "type": "Feature",
  "properties": {
    "iso:country":"DE",
    "sg:address":"P\u00f6deldorfer Str. 32-34",
    "sg:city":"Bamberg",
    "sg:phone":"+49 951/12649",
    "sg:postcode":"96052",
    "sg:province":"Bayern",
    "wof:name":"L. & P. Hornauer Gmbh Farben",
    "wof:placetype":"venue"
},
  "geometry": {"coordinates":[10.90655,49.899235],"type":"Point"}
}