{
  "type": "Feature",
  "properties": {
    "iso:country":"DE",
    "sg:address":"Dorfstr. 6",
    "sg:city":"Heikendorf",
    "sg:phone":"+49 431/248720",
    "sg:postcode":"24226",
    "sg:province":"Schleswig-Holstein",
    "wof:name":"M\u00f6wen-apotheke",
    "wof:placetype":"venue"
},
  "geometry": {"coordinates":[10.203378,54.369785],"type":"Point"}
}