{
  "type": "Feature",
  "properties": {
    "iso:country":"DE",
    "sg:address":"Juttastr. 28",
    "sg:city":"Sonneberg",
    "sg:phone":"+49 3675/801351",
    "sg:postcode":"96515",
    "sg:province":"Th\u00fcringen",
    "wof:name":"Cgm - Shirts Und Mehr",
    "wof:placetype":"venue"
},
  "geometry": {"coordinates":[11.179608345,50.3600349426],"type":"Point"}
}