{
  "type": "Feature",
  "properties": {
    "iso:country":"DE",
    "sg:address":"Max-Reichpietsch-Str. 20",
    "sg:city":"Rostock",
    "sg:postcode":"18146",
    "sg:province":"Mecklenburg-Vorpommern",
    "wof:name":"Individuum Bau-general- \u00fcbernehmer Gmbh",
    "wof:placetype":"venue"
},
  "geometry": {"coordinates":[12.1570587158,54.0982818604],"type":"Point"}
}