{
  "type": "Feature",
  "properties": {
    "iso:country":"DE",
    "sg:address":"Steinheimer Str. 22",
    "sg:city":"Freiberg",
    "sg:phone":"+49 7141/7859580",
    "sg:postcode":"71691",
    "sg:province":"Baden-W\u00fcrttemberg",
    "wof:name":"Sica-bauartikel Lenz & Streicher Gmbh & Co. Kg",
    "wof:placetype":"venue"
},
  "geometry": {"coordinates":[9.218626976,48.9460906982],"type":"Point"}
}