{
  "type": "Feature",
  "properties": {
    "iso:country":"DE",
    "sg:address":"Achter-Gasten-Weg 42",
    "sg:city":"Uplengen",
    "sg:phone":"+49 4489/1531",
    "sg:postcode":"26670",
    "sg:province":"Niedersachsen",
    "wof:name":"Graalmann Gmbh",
    "wof:placetype":"venue"
},
  "geometry": {"coordinates":[7.714209,53.245033],"type":"Point"}
}