{
  "type": "Feature",
  "properties": {
    "iso:country":"DE",
    "sg:address":"Hunteweg 34",
    "sg:city":"Bielefeld",
    "sg:phone":"+49 5205/4770",
    "sg:postcode":"33689",
    "sg:province":"Nordrhein-Westfalen",
    "wof:name":"Dieter Berg Ingenieur",
    "wof:placetype":"venue"
},
  "geometry": {"coordinates":[8.592672348,51.9561691284],"type":"Point"}
}