{
  "type": "Feature",
  "properties": {
    "iso:country":"DE",
    "sg:address":"Hehner Str. 77",
    "sg:city":"M\u00f6nchengladbach",
    "sg:phone":"+49 2161/838035",
    "sg:postcode":"41069",
    "sg:province":"Nordrhein-Westfalen",
    "wof:name":"Spedition Elmar Vootz",
    "wof:placetype":"venue"
},
  "geometry": {"coordinates":[6.4123578072,51.1896858215],"type":"Point"}
}