{
  "type": "Feature",
  "properties": {
    "iso:country":"DE",
    "sg:address":"R\u00f6ntgenstr. 14",
    "sg:city":"Attendorn",
    "sg:phone":"+49 4927/2293725",
    "sg:postcode":"57439",
    "sg:province":"Nordrhein-Westfalen",
    "wof:name":"Willi Schneider Gmbh",
    "wof:placetype":"venue"
},
  "geometry": {"coordinates":[7.924393177,51.1437911987],"type":"Point"}
}