{
  "type": "Feature",
  "properties": {
    "iso:country":"DE",
    "sg:address":"Stellmacherstr. 14",
    "sg:city":"Norden",
    "sg:phone":"+49 4931/9250",
    "sg:postcode":"26506",
    "sg:province":"Niedersachsen",
    "wof:name":"Soltau-kurier-vertrieb Gmbh",
    "wof:placetype":"venue"
},
  "geometry": {"coordinates":[7.224745,53.574398],"type":"Point"}
}