{
  "type": "Feature",
  "properties": {
    "iso:country":"DE",
    "sg:address":"Fr\u00fchlingstr. 30",
    "sg:city":"Sonthofen",
    "sg:phone":"+49 8321/81673",
    "sg:postcode":"87527",
    "sg:province":"Bayern",
    "wof:name":"Lisa Mattiesen",
    "wof:placetype":"venue"
},
  "geometry": {"coordinates":[10.279694,47.505268],"type":"Point"}
}