{
  "type": "Feature",
  "properties": {
    "iso:country":"DE",
    "sg:address":"Sustrumer Str. 6",
    "sg:city":"Niederlangen",
    "sg:phone":"+49 5933/1851",
    "sg:postcode":"49779",
    "sg:province":"Niedersachsen",
    "wof:name":"Johann Ganseforth",
    "wof:placetype":"venue"
},
  "geometry": {"coordinates":[7.267545,52.864902],"type":"Point"}
}