{
  "type": "Feature",
  "properties": {
    "iso:country":"DE",
    "sg:address":"Schaezlerstr. 6",
    "sg:city":"Augsburg",
    "sg:phone":"+49 821/3453911",
    "sg:postcode":"86150",
    "sg:province":"Bayern",
    "wof:name":"Vhv Vereinigte Haftplicht Versicherung Vag",
    "wof:placetype":"venue"
},
  "geometry": {"coordinates":[10.8927297592,48.3671379089],"type":"Point"}
}