{
  "type": "Feature",
  "properties": {
    "iso:country":"DE",
    "sg:address":"Am Herforder Tor 1",
    "sg:city":"Bad Salzuflen",
    "sg:phone":"+49 5222/59012",
    "sg:postcode":"32105",
    "sg:province":"Nordrhein-Westfalen",
    "wof:name":"Dietrich Und Fanenbruck Rechtsanw\u00e4lte Und Notar",
    "wof:placetype":"venue"
},
  "geometry": {"coordinates":[8.7451601028,52.0851821899],"type":"Point"}
}