{
  "type": "Feature",
  "properties": {
    "iso:country":"DE",
    "sg:address":"Silvastr. 1",
    "sg:city":"T\u00fcrkheim",
    "sg:postcode":"86842",
    "sg:province":"Bayern",
    "wof:name":"Schneider Home Cinema Gmbh",
    "wof:placetype":"venue"
},
  "geometry": {"coordinates":[10.615187645,48.0439147949],"type":"Point"}
}