{
  "type": "Feature",
  "properties": {
    "iso:country":"DE",
    "sg:address":"Brunnenstr. 4 a",
    "sg:city":"Merzenich",
    "sg:phone":"+49 2421/394051",
    "sg:postcode":"52399",
    "sg:province":"Nordrhein-Westfalen",
    "wof:name":"D\u00fcrener-immobilien Frank Vaa\u00dfen E. K.",
    "wof:placetype":"venue"
},
  "geometry": {"coordinates":[6.5212798119,50.8320007324],"type":"Point"}
}