{
  "type": "Feature",
  "properties": {
    "iso:country":"DE",
    "sg:address":"Am Kirschenberg 4",
    "sg:city":"Rockenberg",
    "sg:phone":"+49 6033/66430",
    "sg:postcode":"35519",
    "sg:province":"Hessen",
    "wof:name":"Herrmann Architekt",
    "wof:placetype":"venue"
},
  "geometry": {"coordinates":[8.739673,50.431477],"type":"Point"}
}