{
  "type": "Feature",
  "properties": {
    "iso:country":"DE",
    "sg:address":"Draisstr. 7",
    "sg:city":"Muggensturm",
    "sg:phone":"+49 7222/53451",
    "sg:postcode":"76461",
    "sg:province":"Baden-W\u00fcrttemberg",
    "wof:name":"Fleischer Kfz Verwertungsuntern.",
    "wof:placetype":"venue"
},
  "geometry": {"coordinates":[8.2733726501,48.8804168701],"type":"Point"}
}