{
  "type": "Feature",
  "properties": {
    "iso:country":"DE",
    "sg:address":"Haidkoppelweg 24a",
    "sg:city":"Reinbek",
    "sg:phone":"+49 40/7111424",
    "sg:postcode":"21465",
    "sg:province":"Schleswig-Holstein",
    "wof:name":"Dialog-verlag Gmbh",
    "wof:placetype":"venue"
},
  "geometry": {"coordinates":[10.2402706146,53.5463981628],"type":"Point"}
}