{
  "type": "Feature",
  "properties": {
    "iso:country":"DE",
    "sg:address":"Barbiergasse 18",
    "sg:city":"N\u00fcrnberg",
    "sg:phone":"+49 911/269182",
    "sg:postcode":"90443",
    "sg:province":"Bayern",
    "wof:name":"Mepa Offsetdruckmeier & Pape Ohg",
    "wof:placetype":"venue"
},
  "geometry": {"coordinates":[11.0660037994,49.4458312988],"type":"Point"}
}