{
  "type": "Feature",
  "properties": {
    "iso:country":"DE",
    "sg:address":"M\u00fchlenstr. 1",
    "sg:city":"Burghausen",
    "sg:phone":"+49 8677/4292",
    "sg:postcode":"84489",
    "sg:province":"Bayern",
    "wof:name":"August Prechtl",
    "wof:placetype":"venue"
},
  "geometry": {"coordinates":[12.8196325302,48.1559829712],"type":"Point"}
}