{
  "type": "Feature",
  "properties": {
    "iso:country":"DE",
    "sg:address":"Westerstr. 77",
    "sg:city":"Norden",
    "sg:phone":"+49 4931/3259",
    "sg:postcode":"26506",
    "sg:province":"Niedersachsen",
    "wof:name":"Der Lenzhof",
    "wof:placetype":"venue"
},
  "geometry": {"coordinates":[7.2004208565,53.5936851501],"type":"Point"}
}