{
  "type": "Feature",
  "properties": {
    "iso:country":"DE",
    "sg:address":"Ro\u00dfbachstr. 12",
    "sg:city":"Leipzig",
    "sg:postcode":"04315",
    "sg:province":"Sachsen",
    "wof:name":"Paris Top Service",
    "wof:placetype":"venue"
},
  "geometry": {"coordinates":[12.411232,51.340431],"type":"Point"}
}