{
  "type": "Feature",
  "properties": {
    "iso:country":"DE",
    "sg:address":"Sambach 79",
    "sg:city":"Pommersfelden",
    "sg:phone":"+49 9502/104",
    "sg:postcode":"96178",
    "sg:province":"Bayern",
    "wof:name":"Kath. Pfarramt Maria Unbefl. Empf\u00e4ngnis",
    "wof:placetype":"venue"
},
  "geometry": {"coordinates":[10.8401508331,49.7808303833],"type":"Point"}
}