{
  "type": "Feature",
  "properties": {
    "iso:country":"DE",
    "sg:address":"Schaftnacher Weg 4",
    "sg:city":"Rednitzhembach",
    "sg:phone":"+49 9122/74969",
    "sg:postcode":"91126",
    "sg:province":"Bayern",
    "wof:name":"Horst Hippe Sandstrahlentrostung",
    "wof:placetype":"venue"
},
  "geometry": {"coordinates":[11.079459,49.303017],"type":"Point"}
}