{
  "type": "Feature",
  "properties": {
    "iso:country":"DE",
    "sg:address":"Seestr. 178",
    "sg:city":"Halstenbek",
    "sg:phone":"+49 4101/44943",
    "sg:postcode":"25469",
    "sg:province":"Schleswig-Holstein",
    "wof:name":"H. Gehrke Ingenieur",
    "wof:placetype":"venue"
},
  "geometry": {"coordinates":[9.8717432022,53.6197052002],"type":"Point"}
}