{
  "type": "Feature",
  "properties": {
    "iso:country":"DE",
    "sg:address":"Gustav-Adolf-Str. 35",
    "sg:city":"Bingen",
    "sg:phone":"+49 6721/32888",
    "sg:postcode":"55411",
    "sg:province":"Rheinland-Pfalz",
    "wof:name":"Rudolf Fetzer",
    "wof:placetype":"venue"
},
  "geometry": {"coordinates":[7.884032,49.964752],"type":"Point"}
}