{
  "type": "Feature",
  "properties": {
    "iso:country":"DE",
    "sg:address":"Resser Str. 59",
    "sg:city":"Herne",
    "sg:phone":"+49 2325/798300",
    "sg:postcode":"44653",
    "sg:province":"Nordrhein-Westfalen",
    "wof:name":"Bl\u00f6meke Druck Srs Gmbh",
    "wof:placetype":"venue"
},
  "geometry": {"coordinates":[7.143005,51.55051],"type":"Point"}
}