{
  "type": "Feature",
  "properties": {
    "iso:country":"DE",
    "sg:address":"Buchenstr. 3",
    "sg:city":"Echzell",
    "sg:postcode":"61209",
    "sg:province":"Hessen",
    "wof:name":"Hoffmann",
    "wof:placetype":"venue"
},
  "geometry": {"coordinates":[8.900452,50.374092],"type":"Point"}
}