{
  "type": "Feature",
  "properties": {
    "iso:country":"DE",
    "sg:address":"Rosa-Luxemburg-Platz 1",
    "sg:city":"Plauen",
    "sg:postcode":"08523",
    "sg:province":"Sachsen",
    "wof:name":"B & R Grundst\u00fccksver- Wertungs Gmbh",
    "wof:placetype":"venue"
},
  "geometry": {"coordinates":[12.10275,50.49411],"type":"Point"}
}