{
  "type": "Feature",
  "properties": {
    "iso:country":"DE",
    "sg:address":"S\u00f6derblomstr. 3",
    "sg:city":"Hamburg",
    "sg:phone":"+49 40/6683296",
    "sg:postcode":"22045",
    "sg:province":"Hamburg",
    "wof:name":"Dividan Druckvertrieb Gmbh",
    "wof:placetype":"venue"
},
  "geometry": {"coordinates":[10.128529,53.590942],"type":"Point"}
}