{
  "type": "Feature",
  "properties": {
    "iso:country":"DE",
    "sg:address":"Schulstrasse 6",
    "sg:city":"Holzhausen",
    "sg:phone":"+49 6772",
    "sg:postcode":"56357",
    "sg:province":"Rheinland-Pfalz",
    "wof:name":"Ist-schwanitz",
    "wof:placetype":"venue"
},
  "geometry": {"coordinates":[10.748496,50.301399],"type":"Point"}
}