{
  "type": "Feature",
  "properties": {
    "iso:country":"DE",
    "sg:address":"Lange Str. 110",
    "sg:city":"Baden-Baden",
    "sg:phone":"+49 7221/93990",
    "sg:postcode":"76530",
    "sg:province":"Baden-W\u00fcrttemberg",
    "wof:name":"Inter Krankenversicherung Ag",
    "wof:placetype":"venue"
},
  "geometry": {"coordinates":[8.2294225693,48.7699966431],"type":"Point"}
}