{
  "type": "Feature",
  "properties": {
    "iso:country":"DE",
    "sg:address":"Remmingerstr. 6",
    "sg:city":"Bietigheim-Bissingen",
    "sg:phone":"+49 7142/30244",
    "sg:postcode":"74321",
    "sg:province":"Baden-W\u00fcrttemberg",
    "wof:name":"Rainer Walliser",
    "wof:placetype":"venue"
},
  "geometry": {"coordinates":[9.0960693359,48.9454307556],"type":"Point"}
}