{
  "type": "Feature",
  "properties": {
    "iso:country":"DE",
    "sg:address":"Paul-Heyse-Str. 28",
    "sg:city":"M\u00fcnchen",
    "sg:postcode":"80336",
    "sg:province":"Bayern",
    "wof:name":"Esso Service-center",
    "wof:placetype":"venue"
},
  "geometry": {"coordinates":[11.555615,48.135693],"type":"Point"}
}