{
  "type": "Feature",
  "properties": {
    "iso:country":"DE",
    "sg:address":"Heiderh\u00f6fen 51",
    "sg:city":"Oberhausen",
    "sg:phone":"+49 4920/8840063",
    "sg:postcode":"46049",
    "sg:province":"Nordrhein-Westfalen",
    "wof:name":"Laichter Stanzbetrieb Gmbh",
    "wof:placetype":"venue"
},
  "geometry": {"coordinates":[6.828215,51.458626],"type":"Point"}
}