{
  "type": "Feature",
  "properties": {
    "iso:country":"DE",
    "sg:address":"Turmstr. 31",
    "sg:city":"Baltmannsweiler",
    "sg:phone":"+49 7153/41357",
    "sg:postcode":"73666",
    "sg:province":"Baden-W\u00fcrttemberg",
    "wof:name":"F. G. Reinicke",
    "wof:placetype":"venue"
},
  "geometry": {"coordinates":[9.442117,48.746418],"type":"Point"}
}