{
  "type": "Feature",
  "properties": {
    "iso:country":"DE",
    "sg:address":"Geffckenstr. 12",
    "sg:city":"Hamburg",
    "sg:phone":"+49 40/463301",
    "sg:postcode":"20249",
    "sg:province":"Hamburg",
    "wof:name":"Der Bocksbeutel Frankenwein- Spezialit\u00e4ten In Hamburg",
    "wof:placetype":"venue"
},
  "geometry": {"coordinates":[9.9933643341,53.586315155],"type":"Point"}
}