{
  "type": "Feature",
  "properties": {
    "iso:country":"DE",
    "sg:address":"Hauptstr. 2",
    "sg:city":"Ungerhausen",
    "sg:phone":"+49 8393/1095",
    "sg:postcode":"87781",
    "sg:province":"Bayern",
    "wof:name":"Adler",
    "wof:placetype":"venue"
},
  "geometry": {"coordinates":[10.2670793533,48.0051574707],"type":"Point"}
}