{
  "type": "Feature",
  "properties": {
    "iso:country":"DE",
    "sg:address":"Viktoriastr. 19",
    "sg:city":"L\u00fcbeck",
    "sg:phone":"+49 451/75069",
    "sg:postcode":"23560",
    "sg:province":"Schleswig-Holstein",
    "wof:name":"Vorkamp Verwaltungs-gmbh",
    "wof:placetype":"venue"
},
  "geometry": {"coordinates":[10.686549,53.855244],"type":"Point"}
}