{
  "type": "Feature",
  "properties": {
    "iso:country":"DE",
    "sg:address":"Bachstr. 3",
    "sg:city":"Neustrelitz",
    "sg:phone":"+49 3981/45830",
    "sg:postcode":"17235",
    "sg:province":"Mecklenburg-Vorpommern",
    "wof:name":"Moderne Wohnungsbaugenossen- Schaft Neustrelitz Eg",
    "wof:placetype":"venue"
},
  "geometry": {"coordinates":[13.0964298248,53.331451416],"type":"Point"}
}