{
  "type": "Feature",
  "properties": {
    "iso:country":"DE",
    "sg:address":"Poststr. 34",
    "sg:city":"Mainz",
    "sg:phone":"+49 6131/949358",
    "sg:postcode":"55126",
    "sg:province":"Rheinland-Pfalz",
    "wof:name":"Heinrich F. Veit Elektroinstallation",
    "wof:placetype":"venue"
},
  "geometry": {"coordinates":[8.175181,49.985458],"type":"Point"}
}