{
  "type": "Feature",
  "properties": {
    "iso:country":"DE",
    "sg:address":"Ahornstr. 64",
    "sg:city":"Gelsenkirchen",
    "sg:phone":"+49 209/772092",
    "sg:postcode":"45892",
    "sg:province":"Nordrhein-Westfalen",
    "wof:name":"Peter Belhustede",
    "wof:placetype":"venue"
},
  "geometry": {"coordinates":[7.10692,51.57843],"type":"Point"}
}