{
  "type": "Feature",
  "properties": {
    "iso:country":"DE",
    "sg:address":"Nordwestring 133",
    "sg:city":"N\u00fcrnberg",
    "sg:phone":"+49 911/9344222",
    "sg:postcode":"90419",
    "sg:province":"Bayern",
    "wof:name":"Spaceway Kommunikationsnetzwerke Gmbh",
    "wof:placetype":"venue"
},
  "geometry": {"coordinates":[11.0571908951,49.4667892456],"type":"Point"}
}