{
  "type": "Feature",
  "properties": {
    "iso:country":"DE",
    "sg:address":"Finkenwerder Norderdeich 106",
    "sg:city":"Hamburg",
    "sg:phone":"+49 40/7428150",
    "sg:postcode":"21129",
    "sg:province":"Hamburg",
    "wof:name":"Anja Wacks Und Hanna Heinrich Blumen",
    "wof:placetype":"venue"
},
  "geometry": {"coordinates":[9.858832,53.519241],"type":"Point"}
}