{
  "type": "Feature",
  "properties": {
    "iso:country":"DE",
    "sg:address":"Am Esch 17",
    "sg:city":"Westerstede",
    "sg:phone":"+49 4488/79000",
    "sg:postcode":"26655",
    "sg:province":"Niedersachsen",
    "wof:name":"W. Wittje",
    "wof:placetype":"venue"
},
  "geometry": {"coordinates":[7.9322757721,53.2621841431],"type":"Point"}
}