{
  "type": "Feature",
  "properties": {
    "iso:country":"DE",
    "sg:address":"Hauptstr. 210",
    "sg:city":"Weidenthal",
    "sg:phone":"+49 6329/322",
    "sg:postcode":"67475",
    "sg:province":"Rheinland-Pfalz",
    "wof:name":"Fuder Gmbh",
    "wof:placetype":"venue"
},
  "geometry": {"coordinates":[8.002151,49.415306],"type":"Point"}
}