{
  "type": "Feature",
  "properties": {
    "iso:country":"DE",
    "sg:address":"Obere Stra\u00dfe",
    "sg:city":"Holzminden",
    "sg:phone":"+49 5531/45385",
    "sg:postcode":"37603",
    "sg:province":"Niedersachsen",
    "wof:name":"Amazon.de - B\u00fccher, Bestseller, Neuerscheinungen",
    "wof:placetype":"venue"
},
  "geometry": {"coordinates":[9.446165,51.827744],"type":"Point"}
}