{
  "type": "Feature",
  "properties": {
    "iso:country":"DE",
    "sg:address":"Niddertalstr. 8",
    "sg:city":"Ortenberg",
    "sg:phone":"+49 6046/677",
    "sg:postcode":"63683",
    "sg:province":"Hessen",
    "wof:name":"E. Tr\u00f6stum Nachf. Edgar T\u00f6strum E. K.",
    "wof:placetype":"venue"
},
  "geometry": {"coordinates":[9.0670080185,50.3666038513],"type":"Point"}
}