{
  "type": "Feature",
  "properties": {
    "iso:country":"DE",
    "sg:address":"B\u00fcckener Weg 9",
    "sg:city":"Hohenlockstedt",
    "sg:phone":"+49 4826/5511",
    "sg:postcode":"25551",
    "sg:province":"Schleswig-Holstein",
    "wof:name":"Krause Bau Gmbh & Co. Kg",
    "wof:placetype":"venue"
},
  "geometry": {"coordinates":[9.611889,53.96722],"type":"Point"}
}