{
  "type": "Feature",
  "properties": {
    "iso:country":"DE",
    "sg:address":"Heilbronner Str. 42",
    "sg:city":"Flein",
    "sg:phone":"+49 7131/255672",
    "sg:postcode":"74223",
    "sg:province":"Baden-W\u00fcrttemberg",
    "wof:name":"E. Kl\u00e4hr Und H. Flein",
    "wof:placetype":"venue"
},
  "geometry": {"coordinates":[9.2110862732,49.1021766663],"type":"Point"}
}