{
  "type": "Feature",
  "properties": {
    "iso:country":"DE",
    "sg:address":"Sacherstr. 24",
    "sg:city":"Ingolstadt",
    "sg:phone":"+49 841/490650",
    "sg:postcode":"85049",
    "sg:province":"Bayern",
    "wof:name":"Bestattungsinstitut Denk Gmbh & Co. Trauerhilfe Kg",
    "wof:placetype":"venue"
},
  "geometry": {"coordinates":[11.38033,48.767681],"type":"Point"}
}