{
  "type": "Feature",
  "properties": {
    "iso:country":"DE",
    "sg:address":"Siegburger Str. 364",
    "sg:city":"K\u00f6ln",
    "sg:phone":"+49 221/834586",
    "sg:postcode":"51105",
    "sg:province":"Nordrhein-Westfalen",
    "wof:name":"K. Neunzig",
    "wof:placetype":"venue"
},
  "geometry": {"coordinates":[6.990792,50.916283],"type":"Point"}
}