{
  "type": "Feature",
  "properties": {
    "iso:country":"DE",
    "sg:address":"Bahnhofstr. 4",
    "sg:city":"Elsterberg",
    "sg:phone":"+49 36621/20281",
    "sg:postcode":"07985",
    "sg:province":"Th\u00fcringen",
    "wof:name":"Camp-markt",
    "wof:placetype":"venue"
},
  "geometry": {"coordinates":[12.16687,50.610191],"type":"Point"}
}