{
  "type": "Feature",
  "properties": {
    "iso:country":"DE",
    "sg:address":"Gammelsbacher Str. 2",
    "sg:city":"Eberbach",
    "sg:phone":"+49 6271/84311",
    "sg:postcode":"69412",
    "sg:province":"Baden-W\u00fcrttemberg",
    "wof:name":"Dgf Grundst\u00fccks- Verwaltungsges. Mbh",
    "wof:placetype":"venue"
},
  "geometry": {"coordinates":[8.9875497818,49.4632263184],"type":"Point"}
}