{
  "type": "Feature",
  "properties": {
    "iso:country":"DE",
    "sg:address":"Reuterstr. 8",
    "sg:city":"Bergisch Gladbach",
    "sg:phone":"+49 2202/55654",
    "sg:postcode":"51465",
    "sg:province":"Nordrhein-Westfalen",
    "wof:name":"Erich Fuchs",
    "wof:placetype":"venue"
},
  "geometry": {"coordinates":[7.124713,50.995075],"type":"Point"}
}