{
  "type": "Feature",
  "properties": {
    "iso:country":"DE",
    "sg:address":"Zimmerstr. 16",
    "sg:city":"Langen",
    "sg:phone":"+49 6103/29184",
    "sg:postcode":"63225",
    "sg:province":"Hessen",
    "wof:name":"Rud. B\u00f6hm",
    "wof:placetype":"venue"
},
  "geometry": {"coordinates":[8.669393,49.988403],"type":"Point"}
}