{
  "type": "Feature",
  "properties": {
    "iso:country":"DE",
    "sg:address":"Germaniastr. 137",
    "sg:city":"Berlin",
    "sg:phone":"+49 30/32608289",
    "sg:postcode":"12099",
    "sg:province":"Berlin",
    "wof:name":"Video World Andreas Zachrau",
    "wof:placetype":"venue"
},
  "geometry": {"coordinates":[13.3991327286,52.4648742676],"type":"Point"}
}