{
  "type": "Feature",
  "properties": {
    "iso:country":"DE",
    "sg:address":"Dieselstr 42-44",
    "sg:city":"W\u00fclfrath",
    "sg:phone":"+49 2058/7890",
    "sg:postcode":"42489",
    "sg:province":"Nordrhein-Westfalen",
    "wof:name":"Jonas Gmbh & Co Kg",
    "wof:placetype":"venue"
},
  "geometry": {"coordinates":[7.052676,51.295464],"type":"Point"}
}