{
  "type": "Feature",
  "properties": {
    "iso:country":"DE",
    "sg:address":"Prinzregentenstr. 5b",
    "sg:city":"Bad Kissingen",
    "sg:phone":"+49 971/3512",
    "sg:postcode":"97688",
    "sg:province":"Bayern",
    "wof:name":"Andreas Pieper Masseur",
    "wof:placetype":"venue"
},
  "geometry": {"coordinates":[10.07842,50.198616],"type":"Point"}
}