{
  "type": "Feature",
  "properties": {
    "iso:country":"DE",
    "sg:address":"Fabrikenufer",
    "sg:city":"Bremen",
    "sg:phone":"+49 421/380540",
    "sg:postcode":"28217",
    "sg:province":"Bremen",
    "wof:name":"Stephani Speditionsbetrieb Beteiligungs-gmbh",
    "wof:placetype":"venue"
},
  "geometry": {"coordinates":[8.7648105621,53.1030426025],"type":"Point"}
}