{
  "type": "Feature",
  "properties": {
    "iso:country":"DE",
    "sg:address":"Oberreute 20",
    "sg:city":"Schramberg",
    "sg:phone":"+49 7422/5670",
    "sg:postcode":"78713",
    "sg:province":"Baden-W\u00fcrttemberg",
    "wof:name":"Carl Haas Gmbh & Co.",
    "wof:placetype":"venue"
},
  "geometry": {"coordinates":[8.427791,48.239262],"type":"Point"}
}