{
  "type": "Feature",
  "properties": {
    "iso:country":"DE",
    "sg:address":"H\u00f6henweg 8",
    "sg:city":"Gie\u00dfen",
    "sg:phone":"+49 641/51523",
    "sg:postcode":"35396",
    "sg:province":"Hessen",
    "wof:name":"Ks-fliesen Gmbh",
    "wof:placetype":"venue"
},
  "geometry": {"coordinates":[8.694729805,50.6037635803],"type":"Point"}
}