{
  "type": "Feature",
  "properties": {
    "iso:country":"DE",
    "sg:address":"Schwarzh\u00f6lzlstr. 103",
    "sg:city":"M\u00fcnchen",
    "sg:phone":"+49 89/3145247",
    "sg:postcode":"80995",
    "sg:province":"Bayern",
    "wof:name":"E. Brandl-schultes Versandgesch\u00e4ft",
    "wof:placetype":"venue"
},
  "geometry": {"coordinates":[11.5128860474,48.2261390686],"type":"Point"}
}