{
  "type": "Feature",
  "properties": {
    "iso:country":"DE",
    "sg:address":"Deichstr. 2 - Ecke Luhestr.",
    "sg:city":"Winsen",
    "sg:phone":"+49 4171/61044",
    "sg:postcode":"21423",
    "sg:province":"Niedersachsen",
    "wof:name":"G\u00f6bels & Partner Steuerberatungsges. Mbh",
    "wof:placetype":"venue"
},
  "geometry": {"coordinates":[10.207903862,53.3643493652],"type":"Point"}
}