{
  "type": "Feature",
  "properties": {
    "iso:country":"DE",
    "sg:address":"Hauptstr 2",
    "sg:city":"Breitscheid",
    "sg:phone":"+49 2777/7667",
    "sg:postcode":"35767",
    "sg:province":"Hessen",
    "wof:name":"Beer Gmbh",
    "wof:placetype":"venue"
},
  "geometry": {"coordinates":[8.237346,50.697502],"type":"Point"}
}