{
  "type": "Feature",
  "properties": {
    "iso:country":"DE",
    "sg:address":"Stefan-Zweig-Str. 1",
    "sg:city":"Frankfurt",
    "sg:postcode":"60431",
    "sg:province":"Hessen",
    "wof:name":"Mavisim Telekommunikation Gmbh",
    "wof:placetype":"venue"
},
  "geometry": {"coordinates":[8.654667,50.140205],"type":"Point"}
}