{
  "type": "Feature",
  "properties": {
    "iso:country":"DE",
    "sg:address":"Pestalozzistr. 2",
    "sg:city":"Kissing",
    "sg:postcode":"86438",
    "sg:province":"Bayern",
    "wof:name":"Mehrzweckhalle",
    "wof:placetype":"venue"
},
  "geometry": {"coordinates":[10.977816,48.304184],"type":"Point"}
}