{
  "type": "Feature",
  "properties": {
    "iso:country":"DE",
    "sg:address":"Bodenborn 22",
    "sg:city":"Witten",
    "sg:phone":"+49 2302/30261",
    "sg:postcode":"58452",
    "sg:province":"Nordrhein-Westfalen",
    "wof:name":"K. M\u00fcller",
    "wof:placetype":"venue"
},
  "geometry": {"coordinates":[7.3370308876,51.4245414734],"type":"Point"}
}