{
  "type": "Feature",
  "properties": {
    "iso:country":"DE",
    "sg:address":"Mittelzeller Str. 8",
    "sg:city":"Reichenau",
    "sg:phone":"+49 7534/998845",
    "sg:postcode":"78479",
    "sg:province":"Baden-W\u00fcrttemberg",
    "wof:name":"Pirmin Apotheke E. K.",
    "wof:placetype":"venue"
},
  "geometry": {"coordinates":[9.060057,47.697075],"type":"Point"}
}