{
  "type": "Feature",
  "properties": {
    "iso:country":"DE",
    "sg:address":"Aachener Str. 1141",
    "sg:city":"K\u00f6ln",
    "sg:phone":"+49 2234/946460",
    "sg:postcode":"50858",
    "sg:province":"Nordrhein-Westfalen",
    "wof:name":"Consulting Und Softwaresystems Dr. M\u00fcller K\u00f6ln Gmbh",
    "wof:placetype":"venue"
},
  "geometry": {"coordinates":[6.8449811935,50.9379768372],"type":"Point"}
}