{
  "type": "Feature",
  "properties": {
    "iso:country":"DE",
    "sg:address":"Fabrikstr. 8",
    "sg:city":"Ha\u00dfloch",
    "sg:phone":"+49 6324/58032",
    "sg:postcode":"67454",
    "sg:province":"Rheinland-Pfalz",
    "wof:name":"Ernst Weber Kg",
    "wof:placetype":"venue"
},
  "geometry": {"coordinates":[8.2419662476,49.3455734253],"type":"Point"}
}