{
  "type": "Feature",
  "properties": {
    "iso:country":"DE",
    "sg:address":"Kurf\u00fcrstenst. 5-7",
    "sg:city":"K\u00f6ln",
    "sg:phone":"+49 221/9327111",
    "sg:postcode":"50677",
    "sg:province":"Nordrhein-Westfalen",
    "wof:name":"Medichi Gesundheitsinstitut",
    "wof:placetype":"venue"
},
  "geometry": {"coordinates":[6.960318,50.919979],"type":"Point"}
}