{
  "type": "Feature",
  "properties": {
    "iso:country":"DE",
    "sg:address":"Rottmannstr. 20-",
    "sg:city":"M\u00fcnchen",
    "sg:phone":"+49 89/520960",
    "sg:postcode":"80333",
    "sg:province":"Bayern",
    "wof:name":"Maschinen Schmid Josef Schmid Gmbh",
    "wof:placetype":"venue"
},
  "geometry": {"coordinates":[11.560091,48.148808],"type":"Point"}
}