{
  "type": "Feature",
  "properties": {
    "iso:country":"DE",
    "sg:address":"Falkenweg 23",
    "sg:city":"Gerlingen",
    "sg:phone":"+49 7156/270661",
    "sg:postcode":"70839",
    "sg:province":"Baden-W\u00fcrttemberg",
    "wof:name":"Lc Liegenschafts- Consulting Gmbh",
    "wof:placetype":"venue"
},
  "geometry": {"coordinates":[9.058909,48.79105],"type":"Point"}
}