{
  "type": "Feature",
  "properties": {
    "iso:country":"DE",
    "sg:address":"Consrader Weg 30",
    "sg:city":"Schwerin",
    "sg:phone":"+49 385/213250",
    "sg:postcode":"19063",
    "sg:province":"Mecklenburg-Vorpommern",
    "wof:name":"S. M\u00f6ller & B. Zander",
    "wof:placetype":"venue"
},
  "geometry": {"coordinates":[11.47939,53.589825],"type":"Point"}
}