{
  "type": "Feature",
  "properties": {
    "iso:country":"DE",
    "sg:address":"Im Oberberg 2",
    "sg:city":"Walluf",
    "sg:phone":"+49 6123/73467",
    "sg:postcode":"65396",
    "sg:province":"Hessen",
    "wof:name":"Gerhard Hammer Weinanbau",
    "wof:placetype":"venue"
},
  "geometry": {"coordinates":[8.1547822952,50.0394058228],"type":"Point"}
}