{
  "type": "Feature",
  "properties": {
    "iso:country":"DE",
    "sg:address":"Ro\u00dfkopfweg 1",
    "sg:city":"Gundelfingen",
    "sg:phone":"+49 761/581948",
    "sg:postcode":"79194",
    "sg:province":"Baden-W\u00fcrttemberg",
    "wof:name":"Harald Vornam Architekt",
    "wof:placetype":"venue"
},
  "geometry": {"coordinates":[7.86528,48.03875],"type":"Point"}
}