{
  "type": "Feature",
  "properties": {
    "iso:country":"DE",
    "sg:address":"Gottlob-Ansel-Stra\u00dfe 2",
    "sg:city":"Ingersheim",
    "sg:postcode":"74379",
    "sg:province":"Baden-W\u00fcrttemberg",
    "wof:name":"Musikverlag Castellano",
    "wof:placetype":"venue"
},
  "geometry": {"coordinates":[9.180970192,48.9629402161],"type":"Point"}
}