{
  "type": "Feature",
  "properties": {
    "iso:country":"DE",
    "sg:address":"Bergstr. 3",
    "sg:city":"Wutha-Farnroda",
    "sg:phone":"+49 36921/96586",
    "sg:postcode":"99848",
    "sg:province":"Th\u00fcringen",
    "wof:name":"Meiers Bierstube",
    "wof:placetype":"venue"
},
  "geometry": {"coordinates":[10.3852024078,50.9576797485],"type":"Point"}
}