{
  "type": "Feature",
  "properties": {
    "iso:country":"DE",
    "sg:address":"Kirchweg 12",
    "sg:city":"Unterdie\u00dfen",
    "sg:postcode":"86944",
    "sg:province":"Bayern",
    "wof:name":"Katholisches Pfarramt St. Rupert",
    "wof:placetype":"venue"
},
  "geometry": {"coordinates":[10.8254919052,47.9777145386],"type":"Point"}
}