{
  "type": "Feature",
  "properties": {
    "iso:country":"DE",
    "sg:address":"An der Schmelze 6",
    "sg:city":"Kall",
    "sg:phone":"+49 2441/770137",
    "sg:postcode":"53925",
    "sg:province":"Nordrhein-Westfalen",
    "wof:name":"K. K\u00fcpper",
    "wof:placetype":"venue"
},
  "geometry": {"coordinates":[6.5829048157,50.5442314148],"type":"Point"}
}