{
  "type": "Feature",
  "properties": {
    "iso:country":"DE",
    "sg:address":"Drachenfelsstr. 24",
    "sg:city":"K\u00f6nigswinter",
    "sg:phone":"+49 2223/26177",
    "sg:postcode":"53639",
    "sg:province":"Nordrhein-Westfalen",
    "wof:name":"L. Weinrauch Glas- Und Porzellanwaren",
    "wof:placetype":"venue"
},
  "geometry": {"coordinates":[7.1958088875,50.6742401123],"type":"Point"}
}