{
  "type": "Feature",
  "properties": {
    "iso:country":"DE",
    "sg:address":"Meckenheimer Allee 162",
    "sg:city":"Bonn",
    "sg:postcode":"53115",
    "sg:province":"Nordrhein-Westfalen",
    "wof:name":"Sigfridenheim Gmbh",
    "wof:placetype":"venue"
},
  "geometry": {"coordinates":[7.0926470757,50.72681427],"type":"Point"}
}