{
  "type": "Feature",
  "properties": {
    "iso:country":"DE",
    "sg:address":"Brennet 8 a",
    "sg:city":"Willmering",
    "sg:phone":"+49 9971/2638",
    "sg:postcode":"93497",
    "sg:province":"Bayern",
    "wof:name":"Im Immobilien-verwaltungs- Gmbh & Co. Gesch\u00e4ftshaus",
    "wof:placetype":"venue"
},
  "geometry": {"coordinates":[12.6738109589,49.2405700684],"type":"Point"}
}