{
  "type": "Feature",
  "properties": {
    "iso:country":"DE",
    "sg:address":"Libellenstr. 89c",
    "sg:city":"Verl",
    "sg:postcode":"33415",
    "sg:province":"Nordrhein-Westfalen",
    "wof:name":"Reiseb\u00fcro H. Emil L\u00fckkebohle",
    "wof:placetype":"venue"
},
  "geometry": {"coordinates":[8.478260994,51.8890838623],"type":"Point"}
}