{
  "type": "Feature",
  "properties": {
    "iso:country":"DE",
    "sg:address":"Pfitznerstr. 12",
    "sg:city":"M\u00fcnchen",
    "sg:phone":"+49 89/3591344",
    "sg:postcode":"80807",
    "sg:province":"Bayern",
    "wof:name":"Lorenz Menrad",
    "wof:placetype":"venue"
},
  "geometry": {"coordinates":[11.5745983124,48.1833572388],"type":"Point"}
}