{
  "type": "Feature",
  "properties": {
    "iso:country":"DE",
    "sg:address":"Luisenstr. 1",
    "sg:city":"Lage",
    "sg:phone":"+49 5232/2803",
    "sg:postcode":"32791",
    "sg:province":"Nordrhein-Westfalen",
    "wof:name":"Streck Stahlbau Gmbh",
    "wof:placetype":"venue"
},
  "geometry": {"coordinates":[8.8023309708,51.9868431091],"type":"Point"}
}