{
  "type": "Feature",
  "properties": {
    "iso:country":"DE",
    "sg:address":"Ahornweg 1",
    "sg:city":"Mildstedt",
    "sg:phone":"+49 4841/72134",
    "sg:postcode":"25866",
    "sg:province":"Schleswig-Holstein",
    "wof:name":"A.-w. Taube",
    "wof:placetype":"venue"
},
  "geometry": {"coordinates":[9.0950088501,54.4681587219],"type":"Point"}
}