{
  "type": "Feature",
  "properties": {
    "iso:country":"DE",
    "sg:address":"Hauptstr. 83",
    "sg:city":"Weitersburg",
    "sg:phone":"+49 2622/10764",
    "sg:postcode":"56191",
    "sg:province":"Rheinland-Pfalz",
    "wof:name":"Roland Zavelberg Architekt",
    "wof:placetype":"venue"
},
  "geometry": {"coordinates":[7.59799,50.412182],"type":"Point"}
}