{
  "type": "Feature",
  "properties": {
    "iso:country":"DE",
    "sg:address":"Mainzer Str. 150 PF 103321",
    "sg:city":"Saarbr\u00fccken",
    "sg:phone":"+49 4973/5493370",
    "sg:postcode":"66121",
    "sg:province":"Saarland",
    "wof:name":"Guter Gmbh",
    "wof:placetype":"venue"
},
  "geometry": {"coordinates":[10.113981,48.11364],"type":"Point"}
}