{
  "type": "Feature",
  "properties": {
    "iso:country":"DE",
    "sg:address":"Schellnhausen 2",
    "sg:city":"Feldatal",
    "sg:postcode":"36325",
    "sg:province":"Hessen",
    "wof:name":"Tdf Gmbh",
    "wof:placetype":"venue"
},
  "geometry": {"coordinates":[9.1481409073,50.6635055542],"type":"Point"}
}