{
  "type": "Feature",
  "properties": {
    "iso:country":"DE",
    "sg:address":"Markgrafenstr. 26",
    "sg:city":"Bad Alexandersbad",
    "sg:phone":"+49 9232/99730",
    "sg:postcode":"95680",
    "sg:province":"Bayern",
    "wof:name":"Alexandersbad-b\u00e4derhaus Gmbh",
    "wof:placetype":"venue"
},
  "geometry": {"coordinates":[12.01734,50.017796],"type":"Point"}
}