{
  "type": "Feature",
  "properties": {
    "iso:country":"DE",
    "sg:address":"Stra\u00dfe des Friedens 11",
    "sg:city":"Wurzen",
    "sg:phone":"+49 3425/928627",
    "sg:postcode":"04808",
    "sg:province":"Sachsen",
    "wof:name":"H.-t. Serfling",
    "wof:placetype":"venue"
},
  "geometry": {"coordinates":[12.739311,51.37146],"type":"Point"}
}