{
  "type": "Feature",
  "properties": {
    "iso:country":"DE",
    "sg:address":"Reichsstr. 3",
    "sg:city":"Gera",
    "sg:phone":"+49 365/8006188",
    "sg:postcode":"07545",
    "sg:province":"Th\u00fcringen",
    "wof:name":"Kar-heinz D\u00f6ll",
    "wof:placetype":"venue"
},
  "geometry": {"coordinates":[12.0823526382,50.873500824],"type":"Point"}
}