{
  "type": "Feature",
  "properties": {
    "iso:country":"DE",
    "sg:address":"N\u00fcrnberger Str.65",
    "sg:city":"Berlin",
    "sg:postcode":"10787",
    "sg:province":"Berlin",
    "wof:name":"Hotel Crowne Plaza City Centre",
    "wof:placetype":"venue"
},
  "geometry": {"coordinates":[13.3402519226,52.5038909912],"type":"Point"}
}