{
  "type": "Feature",
  "properties": {
    "iso:country":"DE",
    "sg:address":"Am Burgberg 9",
    "sg:city":"Schwarzhofen",
    "sg:phone":"+49 9675/91122",
    "sg:postcode":"92447",
    "sg:province":"Bayern",
    "wof:name":"Gasthaus Kellermann",
    "wof:placetype":"venue"
},
  "geometry": {"coordinates":[12.3085517883,49.3980712891],"type":"Point"}
}