{
  "type": "Feature",
  "properties": {
    "iso:country":"DE",
    "sg:address":"Drei\u00dfentalstr. 26",
    "sg:city":"Oberkochen",
    "sg:phone":"+49 7364/6494",
    "sg:postcode":"73447",
    "sg:province":"Baden-W\u00fcrttemberg",
    "wof:name":"Rolf Stelzenm\u00fcller",
    "wof:placetype":"venue"
},
  "geometry": {"coordinates":[10.1003322601,48.7837181091],"type":"Point"}
}