{
  "type": "Feature",
  "properties": {
    "iso:country":"DE",
    "sg:address":"Obere Str. 173",
    "sg:city":"Wickerstedt",
    "sg:phone":"+49 3644/619810",
    "sg:postcode":"99510",
    "sg:province":"Th\u00fcringen",
    "wof:name":"Marlis Geiling",
    "wof:placetype":"venue"
},
  "geometry": {"coordinates":[11.536699,51.05854],"type":"Point"}
}