{
  "type": "Feature",
  "properties": {
    "iso:country":"DE",
    "sg:address":"Regerstr. 4",
    "sg:city":"Berlin",
    "sg:postcode":"14193",
    "sg:province":"Berlin",
    "wof:name":"Smart Immobilien Gmbh & Co. Villenetagen- Und St\u00e4dtebau",
    "wof:placetype":"venue"
},
  "geometry": {"coordinates":[13.268282,52.479343],"type":"Point"}
}