{
  "type": "Feature",
  "properties": {
    "iso:country":"DE",
    "sg:address":"Kreuznacher Str. 33",
    "sg:city":"Guldental",
    "sg:phone":"+49 6707/616",
    "sg:postcode":"55452",
    "sg:province":"Rheinland-Pfalz",
    "wof:name":"Ferdinand Schmitt",
    "wof:placetype":"venue"
},
  "geometry": {"coordinates":[7.8443989754,49.8870353699],"type":"Point"}
}