{
  "type": "Feature",
  "properties": {
    "iso:country":"DE",
    "sg:address":"Friedrich-Ebert-Str. 255",
    "sg:city":"Velbert",
    "sg:phone":"+49 2051/55111",
    "sg:postcode":"42549",
    "sg:province":"Nordrhein-Westfalen",
    "wof:name":"Thera Train Therapie- Und Trainingszentrum Velbert Gmbh",
    "wof:placetype":"venue"
},
  "geometry": {"coordinates":[7.0351748466,51.3428153992],"type":"Point"}
}