{
  "type": "Feature",
  "properties": {
    "iso:country":"DE",
    "sg:address":"Brahmsstr. 25",
    "sg:city":"Regensburg",
    "sg:phone":"+49 941/785080",
    "sg:postcode":"93053",
    "sg:province":"Bayern",
    "wof:name":"Ernst Watzel",
    "wof:placetype":"venue"
},
  "geometry": {"coordinates":[12.107532,49.003639],"type":"Point"}
}