{
  "type": "Feature",
  "properties": {
    "iso:country":"DE",
    "sg:address":"Dorfstr. 41",
    "sg:city":"Hartmannsdorf",
    "sg:phone":"+49 37602/7360",
    "sg:postcode":"08107",
    "sg:province":"Sachsen",
    "wof:name":"F & K Immobilien- Verwaltungsges. Mbh",
    "wof:placetype":"venue"
},
  "geometry": {"coordinates":[12.5459308624,50.5928535461],"type":"Point"}
}