{
  "type": "Feature",
  "properties": {
    "iso:country":"DE",
    "sg:address":"Vielser Str. 13",
    "sg:city":"Salzkotten",
    "sg:phone":"+49 5258/97830",
    "sg:postcode":"33154",
    "sg:province":"Nordrhein-Westfalen",
    "wof:name":"Michael Fechtler Rechtsanwalt",
    "wof:placetype":"venue"
},
  "geometry": {"coordinates":[8.6062402725,51.6709098816],"type":"Point"}
}