{
  "type": "Feature",
  "properties": {
    "iso:country":"DE",
    "sg:address":"Albrecht-D\u00fcrer-Str. 58",
    "sg:city":"Neubiberg",
    "sg:phone":"+49 89/603001",
    "sg:postcode":"85579",
    "sg:province":"Bayern",
    "wof:name":"Bte B\u00fctotechnik Engels",
    "wof:placetype":"venue"
},
  "geometry": {"coordinates":[11.6824169159,48.0768928528],"type":"Point"}
}