{
  "type": "Feature",
  "properties": {
    "iso:country":"DE",
    "sg:address":"Felbenstr. 14",
    "sg:city":"Oberndorf",
    "sg:phone":"+49 7423/2709",
    "sg:postcode":"78727",
    "sg:province":"Baden-W\u00fcrttemberg",
    "wof:name":"Hans Wagner",
    "wof:placetype":"venue"
},
  "geometry": {"coordinates":[8.5738639832,48.3066558838],"type":"Point"}
}