{
  "type": "Feature",
  "properties": {
    "iso:country":"DE",
    "sg:address":"Anzinger Str. 14",
    "sg:city":"M\u00fcnchen",
    "sg:phone":"+49 89/400071",
    "sg:postcode":"81671",
    "sg:province":"Bayern",
    "wof:name":"Rudolf Keller",
    "wof:placetype":"venue"
},
  "geometry": {"coordinates":[11.6088905334,48.1208190918],"type":"Point"}
}