{
  "type": "Feature",
  "properties": {
    "iso:country":"DE",
    "sg:address":"Haller Str. 8",
    "sg:city":"Mainhardt",
    "sg:phone":"+49 7903/3737",
    "sg:postcode":"74535",
    "sg:province":"Baden-W\u00fcrttemberg",
    "wof:name":"Wohnbau Bubenorbis Gmbh",
    "wof:placetype":"venue"
},
  "geometry": {"coordinates":[9.55774,49.081261],"type":"Point"}
}