{
  "type": "Feature",
  "properties": {
    "iso:country":"DE",
    "sg:address":"Domstr. 15",
    "sg:city":"Hamburg",
    "sg:phone":"+49 40/33430",
    "sg:postcode":"20095",
    "sg:province":"Hamburg",
    "wof:name":"R Und V Versicherung",
    "wof:placetype":"venue"
},
  "geometry": {"coordinates":[9.9952383041,53.5485458374],"type":"Point"}
}