{
  "type": "Feature",
  "properties": {
    "iso:country":"DE",
    "sg:address":"Dorfstr. 49",
    "sg:city":"Barlt",
    "sg:phone":"+49 4857/362",
    "sg:postcode":"25719",
    "sg:province":"Schleswig-Holstein",
    "wof:name":"G\u00fcnther Thode",
    "wof:placetype":"venue"
},
  "geometry": {"coordinates":[9.057794,54.011948],"type":"Point"}
}