{
  "type": "Feature",
  "properties": {
    "iso:country":"DE",
    "sg:address":"H\u00f6henstr. 18",
    "sg:city":"Nauort",
    "sg:phone":"+49 2601/1200",
    "sg:postcode":"56237",
    "sg:province":"Rheinland-Pfalz",
    "wof:name":"Bernhard Freisberg",
    "wof:placetype":"venue"
},
  "geometry": {"coordinates":[7.6219611168,50.4696121216],"type":"Point"}
}