{
  "type": "Feature",
  "properties": {
    "iso:country":"DE",
    "sg:address":"Lahnstr. 29",
    "sg:city":"Bad Laasphe",
    "sg:postcode":"57334",
    "sg:province":"Nordrhein-Westfalen",
    "wof:name":"E. Hengst Verwaltungs- Gmbh",
    "wof:placetype":"venue"
},
  "geometry": {"coordinates":[8.409378,50.923786],"type":"Point"}
}