{
  "type": "Feature",
  "properties": {
    "iso:country":"DE",
    "sg:address":"Fasanenstr. 25-27",
    "sg:city":"Bergisch Gladbach",
    "sg:phone":"+49 2204/61085",
    "sg:postcode":"51427",
    "sg:province":"Nordrhein-Westfalen",
    "wof:name":"Vita Bestattungsunternehmen Peter Schumacher",
    "wof:placetype":"venue"
},
  "geometry": {"coordinates":[7.1319408417,50.9552192688],"type":"Point"}
}