{
  "type": "Feature",
  "properties": {
    "iso:country":"DE",
    "sg:address":"Beethovenstr. 5",
    "sg:city":"Schmelz",
    "sg:phone":"+49 6887/4896",
    "sg:postcode":"66839",
    "sg:province":"Saarland",
    "wof:name":"Udo Hagen Schuff Heilpraktiker",
    "wof:placetype":"venue"
},
  "geometry": {"coordinates":[6.8443112373,49.447769165],"type":"Point"}
}