{
  "type": "Feature",
  "properties": {
    "iso:country":"DE",
    "sg:address":"Sindringer Str. 24",
    "sg:city":"Forchtenberg",
    "sg:phone":"+49 7947/495",
    "sg:postcode":"74670",
    "sg:province":"Baden-W\u00fcrttemberg",
    "wof:name":"Helmut Bauer",
    "wof:placetype":"venue"
},
  "geometry": {"coordinates":[9.511628,49.291027],"type":"Point"}
}