{
  "type": "Feature",
  "properties": {
    "iso:country":"DE",
    "sg:address":"Halberst\u00e4dter Str. 77",
    "sg:city":"Paderborn",
    "sg:phone":"+49 5251/779960",
    "sg:postcode":"33106",
    "sg:province":"Nordrhein-Westfalen",
    "wof:name":"Online Systemlogistik F\u00fcr Spedition & Service Gmbh",
    "wof:placetype":"venue"
},
  "geometry": {"coordinates":[8.7401685715,51.6856384277],"type":"Point"}
}