{
  "type": "Feature",
  "properties": {
    "iso:country":"DE",
    "sg:address":"Wichernstr. 29",
    "sg:city":"Neuhofen",
    "sg:phone":"+49 6236/55347",
    "sg:postcode":"67141",
    "sg:province":"Rheinland-Pfalz",
    "wof:name":"Ilona Finck",
    "wof:placetype":"venue"
},
  "geometry": {"coordinates":[8.4318799973,49.4156799316],"type":"Point"}
}