{
  "type": "Feature",
  "properties": {
    "iso:country":"DE",
    "sg:address":"Weiseler Str. 42",
    "sg:city":"Butzbach",
    "sg:phone":"+49 6033/66550",
    "sg:postcode":"35510",
    "sg:province":"Hessen",
    "wof:name":"Kostas",
    "wof:placetype":"venue"
},
  "geometry": {"coordinates":[8.67108,50.431782],"type":"Point"}
}