{
  "type": "Feature",
  "properties": {
    "iso:country":"DE",
    "sg:address":"Anbaustr. 60",
    "sg:city":"Berbisdorf",
    "sg:phone":"+49 35208/80350",
    "sg:postcode":"01471",
    "sg:province":"Sachsen",
    "wof:name":"Immobilienservice Plaul Inh. Wolf-ddieter Plaul",
    "wof:placetype":"venue"
},
  "geometry": {"coordinates":[13.7265901566,51.1984481812],"type":"Point"}
}