{
  "type": "Feature",
  "properties": {
    "iso:country":"DE",
    "sg:address":"Beim Eberacker 5",
    "sg:city":"Lahnau",
    "sg:postcode":"35633",
    "sg:province":"Hessen",
    "wof:name":"Sauter Metall- Und Kunststoffbau Gmbh",
    "wof:placetype":"venue"
},
  "geometry": {"coordinates":[8.56511,50.57616],"type":"Point"}
}