{
  "type": "Feature",
  "properties": {
    "iso:country":"DE",
    "sg:address":"Nienstedter Str 3",
    "sg:city":"Wolferstedt",
    "sg:phone":"+49 34652/10853",
    "sg:postcode":"06542",
    "sg:province":"Sachsen-Anhalt",
    "wof:name":"Landmaschinen Und Kfz Service Gmbh",
    "wof:placetype":"venue"
},
  "geometry": {"coordinates":[11.430012,51.426853],"type":"Point"}
}