{
  "type": "Feature",
  "properties": {
    "iso:country":"DE",
    "sg:address":"Mussumer Kirchweg 127",
    "sg:city":"Bocholt",
    "sg:phone":"+49 2871/180806",
    "sg:postcode":"46395",
    "sg:province":"Nordrhein-Westfalen",
    "wof:name":"Viktor Heger",
    "wof:placetype":"venue"
},
  "geometry": {"coordinates":[6.6020059586,51.8226242065],"type":"Point"}
}