{
  "type": "Feature",
  "properties": {
    "iso:country":"DE",
    "sg:address":"Karl-Wildsch\u00fctz-Str. 12",
    "sg:city":"Fr\u00f6ndenberg",
    "sg:phone":"+49 2373/7321",
    "sg:postcode":"58730",
    "sg:province":"Nordrhein-Westfalen",
    "wof:name":"Monika Stabenau",
    "wof:placetype":"venue"
},
  "geometry": {"coordinates":[7.7687311172,51.4729156494],"type":"Point"}
}