{
  "type": "Feature",
  "properties": {
    "iso:country":"DE",
    "sg:address":"Schwanthalerstr. 35",
    "sg:city":"M\u00fcnchen",
    "sg:phone":"+49 89/554847",
    "sg:postcode":"80336",
    "sg:province":"Bayern",
    "wof:name":"E. Bauer",
    "wof:placetype":"venue"
},
  "geometry": {"coordinates":[11.5594387054,48.1372871399],"type":"Point"}
}