{
  "type": "Feature",
  "properties": {
    "iso:country":"DE",
    "sg:address":"Berliner Str. 37",
    "sg:city":"Potsdam",
    "sg:postcode":"14467",
    "sg:province":"Brandenburg",
    "wof:name":"Dr. Med. Gerhard Weber",
    "wof:placetype":"venue"
},
  "geometry": {"coordinates":[13.074925,52.406868],"type":"Point"}
}