{
  "type": "Feature",
  "properties": {
    "iso:country":"DE",
    "sg:address":"S\u00fcdfeldstr. 2-4",
    "sg:city":"Vlotho",
    "sg:phone":"+49 5733/91380",
    "sg:postcode":"32602",
    "sg:province":"Nordrhein-Westfalen",
    "wof:name":"Gesamteurop\u00e4isches Studienwerk E. V.",
    "wof:placetype":"venue"
},
  "geometry": {"coordinates":[8.867784,52.166412],"type":"Point"}
}