{
  "type": "Feature",
  "properties": {
    "iso:country":"DE",
    "sg:address":"Krugstr. 37",
    "sg:city":"N\u00fcrnberg",
    "sg:phone":"+49 911/339626",
    "sg:postcode":"90419",
    "sg:province":"Bayern",
    "wof:name":"Bernd Kunzmann",
    "wof:placetype":"venue"
},
  "geometry": {"coordinates":[11.0549573898,49.4588699341],"type":"Point"}
}