{
  "type": "Feature",
  "properties": {
    "iso:country":"DE",
    "sg:address":"Heckschenstr. 45",
    "sg:city":"Krefeld",
    "sg:phone":"+49 2151/542999",
    "sg:postcode":"47809",
    "sg:province":"Nordrhein-Westfalen",
    "wof:name":"U. Funke",
    "wof:placetype":"venue"
},
  "geometry": {"coordinates":[6.6187229156,51.3252067566],"type":"Point"}
}