{
  "type": "Feature",
  "properties": {
    "iso:country":"DE",
    "sg:address":"Turnstr. 13",
    "sg:city":"Pirmasens",
    "sg:phone":"+49 6331/62544",
    "sg:postcode":"66953",
    "sg:province":"Rheinland-Pfalz",
    "wof:name":"Emil Kr\u00f6her",
    "wof:placetype":"venue"
},
  "geometry": {"coordinates":[7.601098,49.20496],"type":"Point"}
}