{
  "type": "Feature",
  "properties": {
    "iso:country":"DE",
    "sg:address":"Egelsbergstr. 1",
    "sg:city":"Weilheim",
    "sg:phone":"+49 7023/3990",
    "sg:postcode":"73235",
    "sg:province":"Baden-W\u00fcrttemberg",
    "wof:name":"Gasthaus An Der Lindach",
    "wof:placetype":"venue"
},
  "geometry": {"coordinates":[9.5180130005,48.6242523193],"type":"Point"}
}