{
  "type": "Feature",
  "properties": {
    "iso:country":"DE",
    "sg:address":"Eichleithen 1a",
    "sg:city":"Weidenberg",
    "sg:phone":"+49 9278/8146",
    "sg:postcode":"95466",
    "sg:province":"Bayern",
    "wof:name":"Silver-cat Gmbh",
    "wof:placetype":"venue"
},
  "geometry": {"coordinates":[11.710149,49.968277],"type":"Point"}
}