{
  "type": "Feature",
  "properties": {
    "iso:country":"DE",
    "sg:address":"Fasanenweg 5",
    "sg:city":"Kelsterbach",
    "sg:phone":"+49 6107/90390",
    "sg:postcode":"65451",
    "sg:province":"Hessen",
    "wof:name":"Warner Lewis, Jr. Industrie-filter Gmbh",
    "wof:placetype":"venue"
},
  "geometry": {"coordinates":[8.5415296555,50.0497894287],"type":"Point"}
}