{
  "type": "Feature",
  "properties": {
    "iso:country":"DE",
    "sg:address":"Hauptstr 70a",
    "sg:city":"Steinberg",
    "sg:phone":"+49 37462/4985",
    "sg:postcode":"08237",
    "sg:province":"Sachsen",
    "wof:name":"Metallbau Ebert Rothenkirchen Gmbh",
    "wof:placetype":"venue"
},
  "geometry": {"coordinates":[12.506878,50.54483],"type":"Point"}
}