{
  "type": "Feature",
  "properties": {
    "iso:country":"DE",
    "sg:address":"Hauptstr. 49",
    "sg:city":"Witten",
    "sg:phone":"+49 2302/54030",
    "sg:postcode":"58452",
    "sg:province":"Nordrhein-Westfalen",
    "wof:name":"Lion-hard-systems Gmbh",
    "wof:placetype":"venue"
},
  "geometry": {"coordinates":[7.3358302116,51.4425926208],"type":"Point"}
}