{
  "type": "Feature",
  "properties": {
    "iso:country":"DE",
    "sg:address":"Zwickauer Str. 121",
    "sg:city":"Dresden",
    "sg:phone":"+49 351/4718551",
    "sg:postcode":"01187",
    "sg:province":"Sachsen",
    "wof:name":"Angela Gro\u00df",
    "wof:placetype":"venue"
},
  "geometry": {"coordinates":[13.7054281235,51.0305862427],"type":"Point"}
}