{
  "type": "Feature",
  "properties": {
    "iso:country":"DE",
    "sg:address":"Dianastr. 15",
    "sg:city":"Oranienburg",
    "sg:phone":"+49 3301/807822",
    "sg:postcode":"16515",
    "sg:province":"Brandenburg",
    "wof:name":"Wolfgang Wolff Agentur",
    "wof:placetype":"venue"
},
  "geometry": {"coordinates":[13.2660198212,52.744758606],"type":"Point"}
}