{
  "type": "Feature",
  "properties": {
    "iso:country":"DE",
    "sg:address":"Josefstr. 31",
    "sg:city":"Donaueschingen",
    "sg:phone":"+49 771/3555",
    "sg:postcode":"78166",
    "sg:province":"Baden-W\u00fcrttemberg",
    "wof:name":"Barbara Becker",
    "wof:placetype":"venue"
},
  "geometry": {"coordinates":[8.500228,47.948551],"type":"Point"}
}