{
  "type": "Feature",
  "properties": {
    "iso:country":"DE",
    "sg:address":"Schwartauer Allee 75",
    "sg:city":"L\u00fcbeck",
    "sg:phone":"+49 451/44236",
    "sg:postcode":"23554",
    "sg:province":"Schleswig-Holstein",
    "wof:name":"Kiek In",
    "wof:placetype":"venue"
},
  "geometry": {"coordinates":[10.6776819229,53.8761558533],"type":"Point"}
}