{
  "type": "Feature",
  "properties": {
    "iso:country":"DE",
    "sg:address":"Bopparder Str. 1",
    "sg:city":"Boppard",
    "sg:phone":"+49 6742/6298",
    "sg:postcode":"56154",
    "sg:province":"Rheinland-Pfalz",
    "wof:name":"Bruno Volk",
    "wof:placetype":"venue"
},
  "geometry": {"coordinates":[7.633072,50.206078],"type":"Point"}
}