{
  "type": "Feature",
  "properties": {
    "iso:country":"DE",
    "sg:address":"Gewerbering 17",
    "sg:city":"J\u00fcterbog",
    "sg:phone":"+49 3372",
    "sg:postcode":"14913",
    "sg:province":"Brandenburg",
    "wof:name":"Hapex - Handelsgesellschaft",
    "wof:placetype":"venue"
},
  "geometry": {"coordinates":[13.087506,52.006912],"type":"Point"}
}