{
  "type": "Feature",
  "properties": {
    "iso:country":"DE",
    "sg:address":"Buschkrugallee 103",
    "sg:city":"Berlin",
    "sg:phone":"+49 30/6064048",
    "sg:postcode":"12359",
    "sg:province":"Berlin",
    "wof:name":"Reli-kunststoffe Gustav Renner Und",
    "wof:placetype":"venue"
},
  "geometry": {"coordinates":[13.450925827,52.4548072815],"type":"Point"}
}