{
  "type": "Feature",
  "properties": {
    "iso:country":"DE",
    "sg:address":"R\u00fcmelinstr. 8",
    "sg:city":"M\u00fcnchen",
    "sg:postcode":"81925",
    "sg:province":"Bayern",
    "wof:name":"M\u00fcnchner Audiotheater Gmbh",
    "wof:placetype":"venue"
},
  "geometry": {"coordinates":[11.6170578003,48.1664619446],"type":"Point"}
}