{
  "type": "Feature",
  "properties": {
    "iso:country":"DE",
    "sg:address":"Hauptstr. 28",
    "sg:city":"Balingen",
    "sg:phone":"+49 7433/930693",
    "sg:postcode":"72336",
    "sg:province":"Baden-W\u00fcrttemberg",
    "wof:name":"Sonne",
    "wof:placetype":"venue"
},
  "geometry": {"coordinates":[8.8599920273,48.2331619263],"type":"Point"}
}