{
  "type": "Feature",
  "properties": {
    "iso:country":"DE",
    "sg:address":"Am Wiesenhang 16a",
    "sg:city":"Rostock",
    "sg:phone":"+49 38300/364",
    "sg:postcode":"18147",
    "sg:province":"Mecklenburg-Vorpommern",
    "wof:name":"Pension Am Windfl\u00fcchter Inh. Ute L\u00fcdtke",
    "wof:placetype":"venue"
},
  "geometry": {"coordinates":[13.0850543976,54.5278358459],"type":"Point"}
}