{
  "type": "Feature",
  "properties": {
    "iso:country":"DE",
    "sg:address":"Am Brunnen 34",
    "sg:city":"Kirchheim bei M\u00fcnchen",
    "sg:phone":"+49 89",
    "sg:postcode":"85551",
    "sg:province":"Bayern",
    "wof:name":"B\u00fcroservice Kirchheim",
    "wof:placetype":"venue"
},
  "geometry": {"coordinates":[11.753561,48.172905],"type":"Point"}
}