{
  "type": "Feature",
  "properties": {
    "iso:country":"DE",
    "sg:address":"Burgstr. 12",
    "sg:city":"Thallichtenberg",
    "sg:phone":"+49 6381/2632",
    "sg:postcode":"66871",
    "sg:province":"Rheinland-Pfalz",
    "wof:name":"Jugendherberge Burg Lichtenberg",
    "wof:placetype":"venue"
},
  "geometry": {"coordinates":[7.3577570915,49.5565490723],"type":"Point"}
}