{
  "type": "Feature",
  "properties": {
    "iso:country":"DE",
    "sg:address":"Alpenstr. 7",
    "sg:city":"Weilheim",
    "sg:phone":"+49 881/8338",
    "sg:postcode":"82362",
    "sg:province":"Bayern",
    "wof:name":"Institut F. Physioth.",
    "wof:placetype":"venue"
},
  "geometry": {"coordinates":[11.143896,47.834858],"type":"Point"}
}