{
  "type": "Feature",
  "properties": {
    "iso:country":"DE",
    "sg:address":"Am Dorfbach 10",
    "sg:city":"Dietramszell",
    "sg:phone":"+49 8171/18259",
    "sg:postcode":"83623",
    "sg:province":"Bayern",
    "wof:name":"Johann Pfanzelter",
    "wof:placetype":"venue"
},
  "geometry": {"coordinates":[11.499458,47.889042],"type":"Point"}
}