{
  "type": "Feature",
  "properties": {
    "iso:country":"DE",
    "sg:address":"Kochendorfer Str. 40",
    "sg:city":"Neckarsulm",
    "sg:postcode":"74172",
    "sg:province":"Baden-W\u00fcrttemberg",
    "wof:name":"Veras Verlag Gmbh",
    "wof:placetype":"venue"
},
  "geometry": {"coordinates":[9.2316913605,49.203086853],"type":"Point"}
}