{
  "type": "Feature",
  "properties": {
    "iso:country":"DE",
    "sg:address":"Pappelweg 27",
    "sg:city":"Metzingen",
    "sg:phone":"+49 7123/21804",
    "sg:postcode":"72555",
    "sg:province":"Baden-W\u00fcrttemberg",
    "wof:name":"Kroatischer Verein August Michael Tilger",
    "wof:placetype":"venue"
},
  "geometry": {"coordinates":[9.2916707993,48.5564460754],"type":"Point"}
}