{
  "type": "Feature",
  "properties": {
    "iso:country":"DE",
    "sg:address":"Insel 46",
    "sg:city":"Klein Schierstedt",
    "sg:phone":"+49 34746/960",
    "sg:postcode":"06449",
    "sg:province":"Sachsen-Anhalt",
    "wof:name":"Schierstedter Schoko- Ladefabrik Gmbh & Co. Kg",
    "wof:placetype":"venue"
},
  "geometry": {"coordinates":[11.54459095,51.755443573],"type":"Point"}
}