{
  "type": "Feature",
  "properties": {
    "iso:country":"DE",
    "sg:address":"Wallstr. 9",
    "sg:city":"Leutenbach",
    "sg:postcode":"71397",
    "sg:province":"Baden-W\u00fcrttemberg",
    "wof:name":"Itn Industriebedarf Und Technische N\u00e4herei E. K.",
    "wof:placetype":"venue"
},
  "geometry": {"coordinates":[9.367326,48.897808],"type":"Point"}
}