{
  "type": "Feature",
  "properties": {
    "iso:country":"DE",
    "sg:address":"Bergmannstr. 14",
    "sg:city":"Amberg",
    "sg:phone":"+49 9621/673367",
    "sg:postcode":"92224",
    "sg:province":"Bayern",
    "wof:name":"Gg. Scharl",
    "wof:placetype":"venue"
},
  "geometry": {"coordinates":[11.856963,49.46452],"type":"Point"}
}