{
  "type": "Feature",
  "properties": {
    "iso:country":"DE",
    "sg:address":"Max von M\u00fcller Str. 17",
    "sg:city":"Rottenburg",
    "sg:phone":"+49 8781/2050",
    "sg:postcode":"84056",
    "sg:province":"Bayern",
    "wof:name":"Sparkasse Rottenburg",
    "wof:placetype":"venue"
},
  "geometry": {"coordinates":[12.026107,48.704315],"type":"Point"}
}