{
  "type": "Feature",
  "properties": {
    "iso:country":"DE",
    "sg:address":"Niederbergkirchen",
    "sg:city":"Niederbergkirchen",
    "sg:phone":"+49 8639/8001",
    "sg:postcode":"84494",
    "sg:province":"Bayern",
    "wof:name":"Raiffeisenbank Niederbergkirchen Eg",
    "wof:placetype":"venue"
},
  "geometry": {"coordinates":[12.50739,48.312634],"type":"Point"}
}