{
  "type": "Feature",
  "properties": {
    "iso:country":"DE",
    "sg:address":"Gabelweg",
    "sg:city":"Eilenburg",
    "sg:phone":"+49 3423/51263",
    "sg:postcode":"04838",
    "sg:province":"Sachsen",
    "wof:name":"Konsum-verkaufsstelle",
    "wof:placetype":"venue"
},
  "geometry": {"coordinates":[12.6614847183,51.469165802],"type":"Point"}
}