{
  "type": "Feature",
  "properties": {
    "iso:country":"DE",
    "sg:address":"Alte Kiesgrube",
    "sg:city":"Pettstadt",
    "sg:postcode":"96175",
    "sg:province":"Bayern",
    "wof:name":"Mmrhp- Recyclinghof Pettstadt Gmbh",
    "wof:placetype":"venue"
},
  "geometry": {"coordinates":[10.926779747,49.8312339783],"type":"Point"}
}