{
  "type": "Feature",
  "properties": {
    "iso:country":"DE",
    "sg:address":"Marktstra\u00dfe 15",
    "sg:city":"Wipperf\u00fcrth",
    "sg:phone":"+49 2267/880310",
    "sg:postcode":"51688",
    "sg:province":"Nordrhein-Westfalen",
    "wof:name":"We Want To Be The Biggest Community In The Net!",
    "wof:placetype":"venue"
},
  "geometry": {"coordinates":[7.396664,51.116779],"type":"Point"}
}