{
  "type": "Feature",
  "properties": {
    "iso:country":"DE",
    "sg:address":"Lindenstr. 24",
    "sg:city":"Naunhof",
    "sg:phone":"+49 34293/29256",
    "sg:postcode":"04683",
    "sg:province":"Sachsen",
    "wof:name":"Sieglinde Scholz",
    "wof:placetype":"venue"
},
  "geometry": {"coordinates":[12.5895223618,51.2753448486],"type":"Point"}
}