{
  "type": "Feature",
  "properties": {
    "iso:country":"DE",
    "sg:address":"Gottschl\u00e4g 6",
    "sg:city":"Ottenh\u00f6fen",
    "sg:phone":"+49 7842/563",
    "sg:postcode":"77883",
    "sg:province":"Baden-W\u00fcrttemberg",
    "wof:name":"Adolf Schm\u00e4lzle",
    "wof:placetype":"venue"
},
  "geometry": {"coordinates":[8.18076,48.555889],"type":"Point"}
}