{
  "type": "Feature",
  "properties": {
    "iso:country":"DE",
    "sg:address":"Kirchplatz 6",
    "sg:city":"Gescher",
    "sg:phone":"+49 2542/886",
    "sg:postcode":"48712",
    "sg:province":"Nordrhein-Westfalen",
    "wof:name":"Rudolf Cramer Hotel",
    "wof:placetype":"venue"
},
  "geometry": {"coordinates":[7.0054650307,51.9561462402],"type":"Point"}
}