{
  "type": "Feature",
  "properties": {
    "iso:country":"DE",
    "sg:address":"Kanalstr. 8",
    "sg:city":"Gersthofen",
    "sg:phone":"+49 821/2992822",
    "sg:postcode":"86368",
    "sg:province":"Bayern",
    "wof:name":"Birgit Und Klaus Schubert Finanzberater",
    "wof:placetype":"venue"
},
  "geometry": {"coordinates":[10.8868865967,48.4244995117],"type":"Point"}
}