{
  "type": "Feature",
  "properties": {
    "iso:country":"DE",
    "sg:address":"Am Tiergarten 4",
    "sg:city":"Ahrensburg",
    "sg:phone":"+49 4102/41344",
    "sg:postcode":"22926",
    "sg:province":"Schleswig-Holstein",
    "wof:name":"Volkhard Bock",
    "wof:placetype":"venue"
},
  "geometry": {"coordinates":[10.2368478775,53.6819648743],"type":"Point"}
}