{
  "type": "Feature",
  "properties": {
    "iso:country":"DE",
    "sg:address":"Untere Pforte 7",
    "sg:city":"Gau-Weinheim",
    "sg:phone":"+49 6732/5973",
    "sg:postcode":"55578",
    "sg:province":"Rheinland-Pfalz",
    "wof:name":"Karl-heinz M\u00fcller",
    "wof:placetype":"venue"
},
  "geometry": {"coordinates":[8.0485162735,49.8452606201],"type":"Point"}
}