{
  "type": "Feature",
  "properties": {
    "iso:country":"DE",
    "sg:address":"Am Steinacker 3",
    "sg:city":"Wachenroth",
    "sg:phone":"+49 9548/6301",
    "sg:postcode":"96193",
    "sg:province":"Bayern",
    "wof:name":"Ifs - Ingenieure F\u00fcr Sicherheitstechnik",
    "wof:placetype":"venue"
},
  "geometry": {"coordinates":[10.716845,49.752613],"type":"Point"}
}