{
  "type": "Feature",
  "properties": {
    "iso:country":"DE",
    "sg:address":"Riedbachstr. 20",
    "sg:city":"Memmingen",
    "sg:phone":"+49 8331/49090",
    "sg:postcode":"87700",
    "sg:province":"Bayern",
    "wof:name":"Wassermann & Co. Gmbh",
    "wof:placetype":"venue"
},
  "geometry": {"coordinates":[10.1891374588,47.9788169861],"type":"Point"}
}