{
  "type": "Feature",
  "properties": {
    "iso:country":"DE",
    "sg:address":"Mainzer Str. 3",
    "sg:city":"S\u00f6mmerda",
    "sg:phone":"+49 3634/623984",
    "sg:postcode":"99610",
    "sg:province":"Th\u00fcringen",
    "wof:name":"R. Sch\u00fctze",
    "wof:placetype":"venue"
},
  "geometry": {"coordinates":[11.1408395767,51.1581192017],"type":"Point"}
}