{
  "type": "Feature",
  "properties": {
    "iso:country":"DE",
    "sg:address":"Eschenbr\u00fcnnlestr 12-14",
    "sg:city":"Sindelfingen",
    "sg:phone":"+49 7031/463560",
    "sg:postcode":"71065",
    "sg:province":"Baden-W\u00fcrttemberg",
    "wof:name":"Rooster Clothing Company Vertriebs Gmbh",
    "wof:placetype":"venue"
},
  "geometry": {"coordinates":[9.026287,48.702847],"type":"Point"}
}