{
  "type": "Feature",
  "properties": {
    "iso:country":"DE",
    "sg:address":"Sommerbergstr. 32",
    "sg:city":"Wiesensteig",
    "sg:phone":"+49 7335/6585",
    "sg:postcode":"73349",
    "sg:province":"Baden-W\u00fcrttemberg",
    "wof:name":"Epple Maschinen Gmbh",
    "wof:placetype":"venue"
},
  "geometry": {"coordinates":[9.626442,48.563416],"type":"Point"}
}