{
  "type": "Feature",
  "properties": {
    "iso:country":"DE",
    "sg:address":"Konrad-Wolf-Allee 1",
    "sg:city":"Potsdam",
    "sg:phone":"+49 331/613325",
    "sg:postcode":"14480",
    "sg:province":"Brandenburg",
    "wof:name":"Dr. Med. Beate Schmeltzer \u00c4rztin F\u00fcr P\u00e4diatrie",
    "wof:placetype":"venue"
},
  "geometry": {"coordinates":[13.139749527,52.3689804077],"type":"Point"}
}