{
  "type": "Feature",
  "properties": {
    "iso:country":"DE",
    "sg:address":"Linnenstr. 2",
    "sg:city":"Oberthulba",
    "sg:phone":"+49 9736/270",
    "sg:postcode":"97723",
    "sg:province":"Bayern",
    "wof:name":"Fr\u00f6hlich Gmbh",
    "wof:placetype":"venue"
},
  "geometry": {"coordinates":[9.9026956558,50.1896591187],"type":"Point"}
}