{
  "type": "Feature",
  "properties": {
    "iso:country":"DE",
    "sg:address":"H\u00f6henkirchener Str. 1 a",
    "sg:city":"Aying",
    "sg:phone":"+49 8102/4726",
    "sg:postcode":"85653",
    "sg:province":"Bayern",
    "wof:name":"Herbert Weigl Architekt",
    "wof:placetype":"venue"
},
  "geometry": {"coordinates":[11.734293,47.992813],"type":"Point"}
}