{
  "type": "Feature",
  "properties": {
    "iso:country":"DE",
    "sg:address":"Forststr. 19",
    "sg:city":"K\u00f6sching",
    "sg:phone":"+49 9446/372",
    "sg:postcode":"85092",
    "sg:province":"Bayern",
    "wof:name":"Konrad Kettner",
    "wof:placetype":"venue"
},
  "geometry": {"coordinates":[11.555905,48.874256],"type":"Point"}
}