{
  "type": "Feature",
  "properties": {
    "iso:country":"DE",
    "sg:address":"Br\u00fcderstr. 17",
    "sg:city":"Hamburg",
    "sg:postcode":"20355",
    "sg:province":"Hamburg",
    "wof:name":"Verwaltung Mc Meyers World Gmbh",
    "wof:placetype":"venue"
},
  "geometry": {"coordinates":[9.9813079834,53.5513267517],"type":"Point"}
}