{
  "type": "Feature",
  "properties": {
    "iso:country":"DE",
    "sg:address":"Marktplatz 3",
    "sg:city":"Bad Nauheim",
    "sg:phone":"+49 6032/32719",
    "sg:postcode":"61231",
    "sg:province":"Hessen",
    "wof:name":"Bistro",
    "wof:placetype":"venue"
},
  "geometry": {"coordinates":[8.735626,50.363762],"type":"Point"}
}