{
  "type": "Feature",
  "properties": {
    "iso:country":"DE",
    "sg:address":"Gro\u00dfe Fleischergasse 21",
    "sg:city":"Leipzig",
    "sg:phone":"+49 341/9611772",
    "sg:postcode":"04109",
    "sg:province":"Sachsen",
    "wof:name":"Heinz Lindenblatt",
    "wof:placetype":"venue"
},
  "geometry": {"coordinates":[12.372276,51.341766],"type":"Point"}
}