{
  "type": "Feature",
  "properties": {
    "iso:country":"DE",
    "sg:address":"Elisabethstr. 25",
    "sg:city":"M\u00fcnchen",
    "sg:postcode":"80796",
    "sg:province":"Bayern",
    "wof:name":"Zweckverband Bayer. Landschulheime",
    "wof:placetype":"venue"
},
  "geometry": {"coordinates":[11.5687446594,48.1588439941],"type":"Point"}
}