{
  "type": "Feature",
  "properties": {
    "iso:country":"DE",
    "sg:address":"Kirchweg 3",
    "sg:city":"Wohratal",
    "sg:phone":"+49 6425/1041",
    "sg:postcode":"35288",
    "sg:province":"Hessen",
    "wof:name":"Heinz Hamel",
    "wof:placetype":"venue"
},
  "geometry": {"coordinates":[8.9376277924,50.9127502441],"type":"Point"}
}