{
  "type": "Feature",
  "properties": {
    "iso:country":"DE",
    "sg:address":"Ahornweg 22",
    "sg:city":"Kirchehrenbach",
    "sg:phone":"+49 9191/94885",
    "sg:postcode":"91356",
    "sg:province":"Bayern",
    "wof:name":"Dipl.ing. Helmut Morgenroth Ingenieur Und Architekt",
    "wof:placetype":"venue"
},
  "geometry": {"coordinates":[11.155992,49.73666],"type":"Point"}
}