{
  "type": "Feature",
  "properties": {
    "iso:country":"DE",
    "sg:address":"Karl-Stangier-Str. 42",
    "sg:city":"Betzdorf",
    "sg:phone":"+49 2741/23350",
    "sg:postcode":"57518",
    "sg:province":"Rheinland-Pfalz",
    "wof:name":"Johannes Stra\u00dfer Architekt",
    "wof:placetype":"venue"
},
  "geometry": {"coordinates":[7.859884,50.79324],"type":"Point"}
}