{
  "type": "Feature",
  "properties": {
    "iso:country":"DE",
    "sg:address":"Institutstr. 17",
    "sg:city":"Weinheim",
    "sg:phone":"+49 6201/14477",
    "sg:postcode":"69469",
    "sg:province":"Baden-W\u00fcrttemberg",
    "wof:name":"H. Hackenschmidt Verm\u00f6gensverwaltung",
    "wof:placetype":"venue"
},
  "geometry": {"coordinates":[8.6714496613,49.547328949],"type":"Point"}
}