{
  "type": "Feature",
  "properties": {
    "iso:country":"DE",
    "sg:address":"Wiesenstr. 10",
    "sg:city":"Philippsthal",
    "sg:phone":"+49 6620/291",
    "sg:postcode":"36269",
    "sg:province":"Hessen",
    "wof:name":"Josefa Klim",
    "wof:placetype":"venue"
},
  "geometry": {"coordinates":[9.993136,50.838272],"type":"Point"}
}