{
  "type": "Feature",
  "properties": {
    "iso:country":"DE",
    "sg:address":"Hohenzollernring 37",
    "sg:city":"K\u00f6ln",
    "sg:phone":"+49 221/9542410",
    "sg:postcode":"50672",
    "sg:province":"Nordrhein-Westfalen",
    "wof:name":"Scott Display Gmbh",
    "wof:placetype":"venue"
},
  "geometry": {"coordinates":[6.939388,50.939198],"type":"Point"}
}