{
  "type": "Feature",
  "properties": {
    "iso:country":"DE",
    "sg:address":"Im Esch 25",
    "sg:city":"S\u00fcdlohn",
    "sg:phone":"+49 2862/6668",
    "sg:postcode":"46354",
    "sg:province":"Nordrhein-Westfalen",
    "wof:name":"Grundst\u00fccksges. Hying Mbh",
    "wof:placetype":"venue"
},
  "geometry": {"coordinates":[6.8020138741,51.9397583008],"type":"Point"}
}