{
  "type": "Feature",
  "properties": {
    "iso:country":"DE",
    "sg:address":"K\u00f6lner Str. 595",
    "sg:city":"Krefeld",
    "sg:phone":"+49 2151/309917",
    "sg:postcode":"47807",
    "sg:province":"Nordrhein-Westfalen",
    "wof:name":"C. Valtas",
    "wof:placetype":"venue"
},
  "geometry": {"coordinates":[6.590116024,51.3024902344],"type":"Point"}
}