{
  "type": "Feature",
  "properties": {
    "iso:country":"DE",
    "sg:address":"Tannenweg 3",
    "sg:city":"Euskirchen",
    "sg:phone":"+49 2251/64739",
    "sg:postcode":"53879",
    "sg:province":"Nordrhein-Westfalen",
    "wof:name":"Peter Greim Steuerberater",
    "wof:placetype":"venue"
},
  "geometry": {"coordinates":[6.7696728706,50.6509628296],"type":"Point"}
}