{
  "type": "Feature",
  "properties": {
    "iso:country":"DE",
    "sg:address":"Haschke Str 33",
    "sg:city":"Wittichenau",
    "sg:phone":"+49 35725/70272",
    "sg:postcode":"02997",
    "sg:province":"Sachsen",
    "wof:name":"Stadtbrauerei Wittichenau Eduard Glaab Gmbh",
    "wof:placetype":"venue"
},
  "geometry": {"coordinates":[14.244733,51.383556],"type":"Point"}
}