{
  "type": "Feature",
  "properties": {
    "iso:country":"DE",
    "sg:address":"Am Sinnerhoop 33-35",
    "sg:city":"Gevelsberg",
    "sg:phone":"+49 2332/60067",
    "sg:postcode":"58285",
    "sg:province":"Nordrhein-Westfalen",
    "wof:name":"Max Kappel Ohg Fischindustrie- Feinkost",
    "wof:placetype":"venue"
},
  "geometry": {"coordinates":[7.386198,51.334118],"type":"Point"}
}