{
  "type": "Feature",
  "properties": {
    "iso:country":"DE",
    "sg:address":"Kaiserstr. 19 a",
    "sg:city":"Mainz",
    "sg:phone":"+49 6131/618173",
    "sg:postcode":"55116",
    "sg:province":"Rheinland-Pfalz",
    "wof:name":"Klaus Joh. Willms Rechtsanwalt",
    "wof:placetype":"venue"
},
  "geometry": {"coordinates":[8.2627029419,50.0040817261],"type":"Point"}
}