{
  "type": "Feature",
  "properties": {
    "iso:country":"DE",
    "sg:address":"Carl-Benz-Str. 5",
    "sg:city":"Gilching",
    "sg:postcode":"82205",
    "sg:province":"Bayern",
    "wof:name":"Matchbox Tennis- Und Squash Zentrum Gmbh & Co.",
    "wof:placetype":"venue"
},
  "geometry": {"coordinates":[11.2865171432,48.1087341309],"type":"Point"}
}