{
  "type": "Feature",
  "properties": {
    "iso:country":"DE",
    "sg:address":"F\u00f6hrenweg 2B",
    "sg:city":"Pentling",
    "sg:phone":"+49 941",
    "sg:postcode":"93080",
    "sg:province":"Bayern",
    "wof:name":"Impact Gbr",
    "wof:placetype":"venue"
},
  "geometry": {"coordinates":[12.05859375,48.9872741699],"type":"Point"}
}