{
  "type": "Feature",
  "properties": {
    "iso:country":"DE",
    "sg:address":"Schwarzwaldstr. 70",
    "sg:city":"Titisee-Neustadt",
    "sg:phone":"+49 7651/3543",
    "sg:postcode":"79822",
    "sg:province":"Baden-W\u00fcrttemberg",
    "wof:name":"H.-dieter Fehrenbach",
    "wof:placetype":"venue"
},
  "geometry": {"coordinates":[8.2196855545,47.9202651978],"type":"Point"}
}