{
  "type": "Feature",
  "properties": {
    "iso:country":"DE",
    "sg:address":"Hameler Weg 37",
    "sg:city":"K\u00f6ln",
    "sg:phone":"+49 221/842522",
    "sg:postcode":"51109",
    "sg:province":"Nordrhein-Westfalen",
    "wof:name":"Servomed Med. Techn. Handelsges. Mbh",
    "wof:placetype":"venue"
},
  "geometry": {"coordinates":[7.081968,50.94231],"type":"Point"}
}