{
  "type": "Feature",
  "properties": {
    "iso:country":"DE",
    "sg:address":"Alte Dorfstr. 12",
    "sg:city":"Gr\u00fcndau",
    "sg:phone":"+49 6051/5505",
    "sg:postcode":"63584",
    "sg:province":"Hessen",
    "wof:name":"Walter R\u00fcckriegel",
    "wof:placetype":"venue"
},
  "geometry": {"coordinates":[9.108817,50.199463],"type":"Point"}
}