{
  "type": "Feature",
  "properties": {
    "iso:country":"DE",
    "sg:address":"Burg-Layer-Str. 20",
    "sg:city":"R\u00fcmmelsheim",
    "sg:phone":"+49 6721/45123",
    "sg:postcode":"55452",
    "sg:province":"Rheinland-Pfalz",
    "wof:name":"Georg Forster",
    "wof:placetype":"venue"
},
  "geometry": {"coordinates":[7.8650689125,49.9308319092],"type":"Point"}
}