{
  "type": "Feature",
  "properties": {
    "iso:country":"DE",
    "sg:address":"Dorfstr. 114",
    "sg:city":"Langenhorn",
    "sg:phone":"+49 4672/1391",
    "sg:postcode":"25842",
    "sg:province":"Schleswig-Holstein",
    "wof:name":"Carsten P. Jensen Versteigerer",
    "wof:placetype":"venue"
},
  "geometry": {"coordinates":[8.9224853516,54.6786499023],"type":"Point"}
}