{
  "type": "Feature",
  "properties": {
    "iso:country":"DE",
    "sg:address":"Allee der Kosmonauten 23",
    "sg:city":"Berlin",
    "sg:phone":"+49 30/54709261",
    "sg:postcode":"10315",
    "sg:province":"Berlin",
    "wof:name":"Sauna L\u00f6yly Ch. Schumann",
    "wof:placetype":"venue"
},
  "geometry": {"coordinates":[13.513959,52.52581],"type":"Point"}
}