{
  "type": "Feature",
  "properties": {
    "iso:country":"DE",
    "sg:address":"Bahnhofstr. 5",
    "sg:city":"Bad T\u00f6lz",
    "sg:phone":"+49 8041/73496",
    "sg:postcode":"83646",
    "sg:province":"Bayern",
    "wof:name":"Hans P. Rest Steuerberater",
    "wof:placetype":"venue"
},
  "geometry": {"coordinates":[11.5675067902,47.7616462708],"type":"Point"}
}