{
  "type": "Feature",
  "properties": {
    "iso:country":"DE",
    "sg:address":"Siedlerstr. 9",
    "sg:city":"Weinb\u00f6hla",
    "sg:phone":"+49 35243/32106",
    "sg:postcode":"01689",
    "sg:province":"Sachsen",
    "wof:name":"V. M\u00fcller",
    "wof:placetype":"venue"
},
  "geometry": {"coordinates":[13.575538,51.151314],"type":"Point"}
}