{
  "type": "Feature",
  "properties": {
    "iso:country":"DE",
    "sg:address":"Sahlenburger Chaussee 18",
    "sg:city":"Cuxhaven",
    "sg:phone":"+49 4721/26925",
    "sg:postcode":"27476",
    "sg:province":"Niedersachsen",
    "wof:name":"E. Blohm",
    "wof:placetype":"venue"
},
  "geometry": {"coordinates":[8.6449,53.865311],"type":"Point"}
}