{
  "type": "Feature",
  "properties": {
    "iso:country":"DE",
    "sg:address":"Marktplatz 12",
    "sg:city":"Gem\u00fcnden",
    "sg:phone":"+49 9351/1010",
    "sg:postcode":"97737",
    "sg:province":"Bayern",
    "wof:name":"Volpert Gmbh",
    "wof:placetype":"venue"
},
  "geometry": {"coordinates":[9.689444,50.057163],"type":"Point"}
}