{
  "type": "Feature",
  "properties": {
    "iso:country":"DE",
    "sg:address":"Seilerweg 9",
    "sg:city":"K\u00f6ngen",
    "sg:phone":"+49 7024/81282",
    "sg:postcode":"73257",
    "sg:province":"Baden-W\u00fcrttemberg",
    "wof:name":"Jesse Gmbh Karosseriebau Lackiererei",
    "wof:placetype":"venue"
},
  "geometry": {"coordinates":[9.372723,48.683723],"type":"Point"}
}