{
  "type": "Feature",
  "properties": {
    "iso:country":"DE",
    "sg:address":"Bernhard-Seitz-Weg 17",
    "sg:city":"Ostseebad Ahrenshoop",
    "sg:phone":"+49 38220/6070",
    "sg:postcode":"18347",
    "sg:province":"Mecklenburg-Vorpommern",
    "wof:name":"J\u00fcrgen Saatmann",
    "wof:placetype":"venue"
},
  "geometry": {"coordinates":[12.356415,54.292343],"type":"Point"}
}