{
  "type": "Feature",
  "properties": {
    "iso:country":"DE",
    "sg:address":"Jagdweg 10",
    "sg:city":"Dresden",
    "sg:phone":"+49 351/4844294",
    "sg:postcode":"01159",
    "sg:province":"Sachsen",
    "wof:name":"Inkoplan Gesellschaft F\u00fcr Infrastruktur- Und",
    "wof:placetype":"venue"
},
  "geometry": {"coordinates":[13.7158880234,51.0470962524],"type":"Point"}
}