{
  "type": "Feature",
  "properties": {
    "iso:country":"DE",
    "sg:address":"Augsburger Str. 31",
    "sg:city":"Burgau",
    "sg:phone":"+49 8222/40910",
    "sg:postcode":"89331",
    "sg:province":"Bayern",
    "wof:name":"Hermann G\u00e4rtner Verwaltungs- Und Beteiligungs Gmbh",
    "wof:placetype":"venue"
},
  "geometry": {"coordinates":[10.413358,48.425652],"type":"Point"}
}