{
  "type": "Feature",
  "properties": {
    "iso:country":"DE",
    "sg:address":"Hittfeldstr. 35",
    "sg:city":"M\u00fclheim",
    "sg:phone":"+49 208/52541",
    "sg:postcode":"45478",
    "sg:province":"Nordrhein-Westfalen",
    "wof:name":"Bar Chez-nous",
    "wof:placetype":"venue"
},
  "geometry": {"coordinates":[6.822556,51.434532],"type":"Point"}
}