{
  "type": "Feature",
  "properties": {
    "iso:country":"DE",
    "sg:address":"Weetzener Landstr.",
    "sg:city":"Hemmingen",
    "sg:postcode":"30966",
    "sg:province":"Niedersachsen",
    "wof:name":"Access E. K.",
    "wof:placetype":"venue"
},
  "geometry": {"coordinates":[9.7365245819,52.319480896],"type":"Point"}
}