{
  "type": "Feature",
  "properties": {
    "iso:country":"DE",
    "sg:address":"Feuchtwanger Str. 31",
    "sg:city":"Ansbach",
    "sg:phone":"+49 981/62074",
    "sg:postcode":"91522",
    "sg:province":"Bayern",
    "wof:name":"Feldschl\u00f6\u00dfchen",
    "wof:placetype":"venue"
},
  "geometry": {"coordinates":[10.5638608932,49.2963676453],"type":"Point"}
}