{
  "type": "Feature",
  "properties": {
    "iso:country":"DE",
    "sg:address":"Hessestr. 21",
    "sg:city":"Neuenb\u00fcrg",
    "sg:phone":"+49 7082/8967",
    "sg:postcode":"75305",
    "sg:province":"Baden-W\u00fcrttemberg",
    "wof:name":"I. Winterling",
    "wof:placetype":"venue"
},
  "geometry": {"coordinates":[8.5812120438,48.8476791382],"type":"Point"}
}