{
  "type": "Feature",
  "properties": {
    "iso:country":"DE",
    "sg:address":"Industriestr. 1-9",
    "sg:city":"Syke",
    "sg:phone":"+49 4242/5980",
    "sg:postcode":"28857",
    "sg:province":"Niedersachsen",
    "wof:name":"Weser Feinkost Beteiligungs-gmbh",
    "wof:placetype":"venue"
},
  "geometry": {"coordinates":[8.8058795929,52.9152603149],"type":"Point"}
}