{
  "type": "Feature",
  "properties": {
    "iso:country":"DE",
    "sg:address":"Lamer Str. 22",
    "sg:city":"Blaibach",
    "sg:postcode":"93476",
    "sg:province":"Bayern",
    "wof:name":"Mair Produktion Cham E. K.",
    "wof:placetype":"venue"
},
  "geometry": {"coordinates":[12.807766,49.166103],"type":"Point"}
}