{
  "type": "Feature",
  "properties": {
    "iso:country":"DE",
    "sg:address":"Bismarckallee 31",
    "sg:city":"M\u00fcnster",
    "sg:phone":"+49 251/530280",
    "sg:postcode":"48151",
    "sg:province":"Nordrhein-Westfalen",
    "wof:name":"Jugendg\u00e4stehaus Aasee",
    "wof:placetype":"venue"
},
  "geometry": {"coordinates":[7.6134967804,51.9541244507],"type":"Point"}
}