{
  "type": "Feature",
  "properties": {
    "iso:country":"DE",
    "sg:address":"Wiesdorfer Platz 47",
    "sg:city":"Leverkusen",
    "sg:phone":"+49 214/48484",
    "sg:postcode":"51373",
    "sg:province":"Nordrhein-Westfalen",
    "wof:name":"Pizzeria Pulcinella",
    "wof:placetype":"venue"
},
  "geometry": {"coordinates":[6.9839248657,51.0317153931],"type":"Point"}
}