{
  "type": "Feature",
  "properties": {
    "iso:country":"DE",
    "sg:address":"Schwanthalerstr. 83",
    "sg:city":"M\u00fcnchen",
    "sg:phone":"+49 89/5328259",
    "sg:postcode":"80336",
    "sg:province":"Bayern",
    "wof:name":"N. Gleitmann Makler",
    "wof:placetype":"venue"
},
  "geometry": {"coordinates":[11.5538311005,48.137386322],"type":"Point"}
}