{
  "type": "Feature",
  "properties": {
    "iso:country":"DE",
    "sg:address":"Bratfischwinkel 10",
    "sg:city":"Passau",
    "sg:phone":"+49 851/36780",
    "sg:postcode":"94032",
    "sg:province":"Bayern",
    "wof:name":"Wohnart Einrichtungs Gmbh",
    "wof:placetype":"venue"
},
  "geometry": {"coordinates":[13.4575843811,48.5753364563],"type":"Point"}
}