{
  "type": "Feature",
  "properties": {
    "iso:country":"DE",
    "sg:address":"Klausenburger Str. 9",
    "sg:city":"M\u00fcnchen",
    "sg:phone":"+49 89/93930310",
    "sg:postcode":"81677",
    "sg:province":"Bayern",
    "wof:name":"Heilit & Woerner Bau Ag Niederlassung Ausland",
    "wof:placetype":"venue"
},
  "geometry": {"coordinates":[11.645308,48.137589],"type":"Point"}
}