{
  "type": "Feature",
  "properties": {
    "iso:country":"DE",
    "sg:address":"Niedinkstr. 20-24",
    "sg:city":"Warendorf",
    "sg:phone":"+49 2581/1871",
    "sg:postcode":"48231",
    "sg:province":"Nordrhein-Westfalen",
    "wof:name":"Baltimore Fitness-center",
    "wof:placetype":"venue"
},
  "geometry": {"coordinates":[7.9757509232,51.9522514343],"type":"Point"}
}