{
  "type": "Feature",
  "properties": {
    "iso:country":"DE",
    "sg:address":"Lebacher Str. 43",
    "sg:city":"Heusweiler",
    "sg:phone":"+49 6806/78449",
    "sg:postcode":"66265",
    "sg:province":"Saarland",
    "wof:name":"Beatrix Rituper",
    "wof:placetype":"venue"
},
  "geometry": {"coordinates":[6.930866,49.359486],"type":"Point"}
}