{
  "type": "Feature",
  "properties": {
    "iso:country":"DE",
    "sg:address":"Kastanienallee 1",
    "sg:city":"Offenburg",
    "sg:phone":"+49 781/58575",
    "sg:postcode":"77656",
    "sg:province":"Baden-W\u00fcrttemberg",
    "wof:name":"Hildegardis-apotheke",
    "wof:placetype":"venue"
},
  "geometry": {"coordinates":[7.93214,48.460732],"type":"Point"}
}