{
  "type": "Feature",
  "properties": {
    "iso:country":"DE",
    "sg:address":"Marienplatz 36",
    "sg:city":"Mindelheim",
    "sg:postcode":"87719",
    "sg:province":"Bayern",
    "wof:name":"Mindelpharma E. K.",
    "wof:placetype":"venue"
},
  "geometry": {"coordinates":[10.4884119034,48.0462036133],"type":"Point"}
}