{
  "type": "Feature",
  "properties": {
    "iso:country":"DE",
    "sg:address":"Wohldorfer Damm 4",
    "sg:city":"Hamburg",
    "sg:phone":"+49 40/6044870",
    "sg:postcode":"22395",
    "sg:province":"Hamburg",
    "wof:name":"Steinmetz & Fiedler",
    "wof:placetype":"venue"
},
  "geometry": {"coordinates":[10.1257190704,53.6718444824],"type":"Point"}
}