{
  "type": "Feature",
  "properties": {
    "iso:country":"DE",
    "sg:address":"Spessartstr. 1",
    "sg:city":"Rodenbach",
    "sg:postcode":"63517",
    "sg:province":"Hessen",
    "wof:name":"Micheel & Karger Gmbh",
    "wof:placetype":"venue"
},
  "geometry": {"coordinates":[9.0639410019,50.1347846985],"type":"Point"}
}