{
  "type": "Feature",
  "properties": {
    "iso:country":"DE",
    "sg:address":"Dorfstr. 14 a",
    "sg:city":"Reinstorf",
    "sg:phone":"+49 38466/20244",
    "sg:postcode":"18246",
    "sg:province":"Mecklenburg-Vorpommern",
    "wof:name":"Agrar Eg",
    "wof:placetype":"venue"
},
  "geometry": {"coordinates":[11.93647,53.935177],"type":"Point"}
}