{
  "type": "Feature",
  "properties": {
    "iso:country":"DE",
    "sg:address":"M\u00fcllnerstr.",
    "sg:city":"Wei\u00dfenfels",
    "sg:phone":"+49 3443/804055",
    "sg:postcode":"06667",
    "sg:province":"Sachsen-Anhalt",
    "wof:name":"Der Praktiker Bau- Und Heimwerkermarkt Gmbh & Co. Kg",
    "wof:placetype":"venue"
},
  "geometry": {"coordinates":[11.9649152756,51.2107849121],"type":"Point"}
}