{
  "type": "Feature",
  "properties": {
    "iso:country":"DE",
    "sg:address":"Otto-Lilienthal-Str. 19",
    "sg:city":"Halberstadt",
    "sg:phone":"+49 3941/602346",
    "sg:postcode":"38820",
    "sg:province":"Sachsen-Anhalt",
    "wof:name":"Werner Neumann",
    "wof:placetype":"venue"
},
  "geometry": {"coordinates":[11.070397377,51.8965644836],"type":"Point"}
}