{
  "type": "Feature",
  "properties": {
    "iso:country":"DE",
    "sg:address":"Herlingsburg 25",
    "sg:city":"Hamburg",
    "sg:phone":"+49 40/5601578",
    "sg:postcode":"22529",
    "sg:province":"Hamburg",
    "wof:name":"Nakakita - Kuhlmann Electronics",
    "wof:placetype":"venue"
},
  "geometry": {"coordinates":[9.9534978867,53.5851325989],"type":"Point"}
}