{
  "type": "Feature",
  "properties": {
    "iso:country":"DE",
    "sg:address":"Gamperlm\u00fchlstr. 17",
    "sg:city":"Siegsdorf",
    "sg:phone":"+49 8662/2398",
    "sg:postcode":"83313",
    "sg:province":"Bayern",
    "wof:name":"Sylvester Dufter Dipl. Ingenieur Baust.",
    "wof:placetype":"venue"
},
  "geometry": {"coordinates":[12.7084474564,47.7979125977],"type":"Point"}
}