{
  "type": "Feature",
  "properties": {
    "iso:country":"DE",
    "sg:address":"Moselstr. 22",
    "sg:city":"Bausendorf",
    "sg:phone":"+49 6532/3246",
    "sg:postcode":"54538",
    "sg:province":"Rheinland-Pfalz",
    "wof:name":"Rudolf Simon",
    "wof:placetype":"venue"
},
  "geometry": {"coordinates":[6.99563,50.010128],"type":"Point"}
}