{
  "type": "Feature",
  "properties": {
    "iso:country":"DE",
    "sg:address":"Am Roten Kreuz 37",
    "sg:city":"D\u00f6beln",
    "sg:phone":"+49 3431/702687",
    "sg:postcode":"04720",
    "sg:province":"Sachsen",
    "wof:name":"Birgit Kunert",
    "wof:placetype":"venue"
},
  "geometry": {"coordinates":[13.1196498871,51.1288414001],"type":"Point"}
}