{
  "type": "Feature",
  "properties": {
    "iso:country":"DE",
    "sg:address":"B\u00fcrgerstr. 9",
    "sg:city":"Rheine",
    "sg:phone":"+49 5975/1279",
    "sg:postcode":"48432",
    "sg:province":"Nordrhein-Westfalen",
    "wof:name":"Bruno Bittner",
    "wof:placetype":"venue"
},
  "geometry": {"coordinates":[7.482355,52.224876],"type":"Point"}
}