{
  "type": "Feature",
  "properties": {
    "iso:country":"DE",
    "sg:address":"Hermannstr. 228",
    "sg:city":"Berlin",
    "sg:phone":"+49 30/6224889",
    "sg:postcode":"12049",
    "sg:province":"Berlin",
    "wof:name":"Pelzhaus Kircher",
    "wof:placetype":"venue"
},
  "geometry": {"coordinates":[13.425307,52.481087],"type":"Point"}
}