{
  "type": "Feature",
  "properties": {
    "iso:country":"DE",
    "sg:address":"Hofer Str. 135",
    "sg:city":"Oberlungwitz",
    "sg:phone":"+49 3723/43531",
    "sg:postcode":"09353",
    "sg:province":"Sachsen",
    "wof:name":"Wolfram Schulze",
    "wof:placetype":"venue"
},
  "geometry": {"coordinates":[12.7175779343,50.7848434448],"type":"Point"}
}