{
  "type": "Feature",
  "properties": {
    "iso:country":"DE",
    "sg:address":"Kurhausstr. 4",
    "sg:city":"Bad Nenndorf",
    "sg:phone":"+49 5723/913264",
    "sg:postcode":"31542",
    "sg:province":"Niedersachsen",
    "wof:name":"Plus",
    "wof:placetype":"venue"
},
  "geometry": {"coordinates":[9.3752326965,52.3378601074],"type":"Point"}
}