{
  "type": "Feature",
  "properties": {
    "iso:country":"DE",
    "sg:address":"Bahnhofstr. 22",
    "sg:city":"Wetter",
    "sg:phone":"+49 6423/2966",
    "sg:postcode":"35083",
    "sg:province":"Hessen",
    "wof:name":"Okay-kauf",
    "wof:placetype":"venue"
},
  "geometry": {"coordinates":[8.7269411087,50.9039497375],"type":"Point"}
}