{
  "type": "Feature",
  "properties": {
    "iso:country":"DE",
    "sg:address":"Schlo\u00dfkirchstr. 1",
    "sg:city":"Cottbus",
    "sg:phone":"+49 355/31181",
    "sg:postcode":"03046",
    "sg:province":"Brandenburg",
    "wof:name":"Peter Zerback",
    "wof:placetype":"venue"
},
  "geometry": {"coordinates":[14.334841,51.759235],"type":"Point"}
}