{
  "type": "Feature",
  "properties": {
    "iso:country":"DE",
    "sg:address":"Emsstr. 11",
    "sg:city":"Rheine",
    "sg:phone":"+49 5971/13055",
    "sg:postcode":"48431",
    "sg:province":"Nordrhein-Westfalen",
    "wof:name":"Wir In Rheine",
    "wof:placetype":"venue"
},
  "geometry": {"coordinates":[7.4389710426,52.2783508301],"type":"Point"}
}