{
  "type": "Feature",
  "properties": {
    "iso:country":"DE",
    "sg:address":"Stuttgarter Str. 122",
    "sg:city":"Eislingen",
    "sg:phone":"+49 7161/984420",
    "sg:postcode":"73054",
    "sg:province":"Baden-W\u00fcrttemberg",
    "wof:name":"Ventzki Verwaltungs Gmbh",
    "wof:placetype":"venue"
},
  "geometry": {"coordinates":[9.693902,48.696205],"type":"Point"}
}