{
  "type": "Feature",
  "properties": {
    "iso:country":"DE",
    "sg:address":"Gelnhaarer Str. 6",
    "sg:city":"Kefenrod",
    "sg:phone":"+49 6049/1698",
    "sg:postcode":"63699",
    "sg:province":"Hessen",
    "wof:name":"Gastwirtschaft Werner Reutzel",
    "wof:placetype":"venue"
},
  "geometry": {"coordinates":[9.1632347107,50.3528747559],"type":"Point"}
}