{
  "type": "Feature",
  "properties": {
    "iso:country":"DE",
    "sg:address":"Torstr. 40",
    "sg:city":"Hatzfeld",
    "sg:phone":"+49 6467/288",
    "sg:postcode":"35116",
    "sg:province":"Hessen",
    "wof:name":"Gerd Schumacher",
    "wof:placetype":"venue"
},
  "geometry": {"coordinates":[8.551677,50.989685],"type":"Point"}
}