{
  "type": "Feature",
  "properties": {
    "iso:country":"DE",
    "sg:address":"Georgstr. 2",
    "sg:city":"Bad Zwischenahn",
    "sg:phone":"+49 4403/916565",
    "sg:postcode":"26160",
    "sg:province":"Niedersachsen",
    "wof:name":"Sportmanagement Und Vermittlung Gmbh",
    "wof:placetype":"venue"
},
  "geometry": {"coordinates":[8.0091772079,53.182975769],"type":"Point"}
}