{
  "type": "Feature",
  "properties": {
    "iso:country":"DE",
    "sg:address":"Hauptstr. 35",
    "sg:city":"K\u00f6nigsdorf",
    "sg:phone":"+49 8179/432",
    "sg:postcode":"82549",
    "sg:province":"Bayern",
    "wof:name":"Peter Eichner",
    "wof:placetype":"venue"
},
  "geometry": {"coordinates":[11.4805212021,47.8151893616],"type":"Point"}
}