{
  "type": "Feature",
  "properties": {
    "iso:country":"DE",
    "sg:address":"Zum Gewerbepark 12",
    "sg:city":"Markneukirchen",
    "sg:phone":"+49 37422/46199",
    "sg:postcode":"08258",
    "sg:province":"Sachsen",
    "wof:name":"Seiferts Backwaren Gmbh",
    "wof:placetype":"venue"
},
  "geometry": {"coordinates":[12.340627,50.318012],"type":"Point"}
}