{
  "type": "Feature",
  "properties": {
    "iso:country":"DE",
    "sg:address":"Ibenhainer Str. 27",
    "sg:city":"Waltershausen",
    "sg:phone":"+49 3622/68311",
    "sg:postcode":"99880",
    "sg:province":"Th\u00fcringen",
    "wof:name":"Joachim Remdt Rechtsanwalt",
    "wof:placetype":"venue"
},
  "geometry": {"coordinates":[10.5643434525,50.893157959],"type":"Point"}
}