{
  "type": "Feature",
  "properties": {
    "iso:country":"DE",
    "sg:address":"Marktstr. 19",
    "sg:city":"Braunlage",
    "sg:phone":"+49 5520/1438",
    "sg:postcode":"38700",
    "sg:province":"Niedersachsen",
    "wof:name":"Galerie",
    "wof:placetype":"venue"
},
  "geometry": {"coordinates":[10.6113796234,51.7262001038],"type":"Point"}
}