{
  "type": "Feature",
  "properties": {
    "iso:country":"DE",
    "sg:address":"Wirtschaftsstr.",
    "sg:city":"Nostorf",
    "sg:phone":"+49 38847/53964",
    "sg:postcode":"19258",
    "sg:province":"Mecklenburg-Vorpommern",
    "wof:name":"Afm -agrarprodukte-feldfrucht Milch Und Fleisch Gmbh",
    "wof:placetype":"venue"
},
  "geometry": {"coordinates":[10.637666,53.406792],"type":"Point"}
}