{
  "type": "Feature",
  "properties": {
    "iso:country":"DE",
    "sg:address":"Am Kiekenbusch 18",
    "sg:city":"Duisburg",
    "sg:phone":"+49 203/767560",
    "sg:postcode":"47269",
    "sg:province":"Nordrhein-Westfalen",
    "wof:name":"Herbert Stettinius",
    "wof:placetype":"venue"
},
  "geometry": {"coordinates":[6.7724862099,51.3678092957],"type":"Point"}
}