{
  "type": "Feature",
  "properties": {
    "iso:country":"DE",
    "sg:address":"Konrad-Adenauer-Str. 73",
    "sg:city":"Rheinbach",
    "sg:phone":"+49 2225/7362",
    "sg:postcode":"53359",
    "sg:province":"Nordrhein-Westfalen",
    "wof:name":"Heinrich Sch\u00e4fer",
    "wof:placetype":"venue"
},
  "geometry": {"coordinates":[6.986067,50.649807],"type":"Point"}
}