{
  "type": "Feature",
  "properties": {
    "iso:country":"DE",
    "sg:address":"Vordersteig 5",
    "sg:city":"Ettlingen",
    "sg:phone":"+49 7243/12924",
    "sg:postcode":"76275",
    "sg:province":"Baden-W\u00fcrttemberg",
    "wof:name":"H. Und H. Schwenk Steuerberater",
    "wof:placetype":"venue"
},
  "geometry": {"coordinates":[8.4146757126,48.9433097839],"type":"Point"}
}