{
  "type": "Feature",
  "properties": {
    "iso:country":"DE",
    "sg:address":"Eckernf\u00f6rder Landstr 300",
    "sg:city":"Flensburg",
    "sg:phone":"+49 5152/94270",
    "sg:postcode":"24941",
    "sg:province":"Schleswig-Holstein",
    "wof:name":"Gbm Umwelttechnik Gmbh",
    "wof:placetype":"venue"
},
  "geometry": {"coordinates":[9.2396726608,52.1911888123],"type":"Point"}
}