{
  "type": "Feature",
  "properties": {
    "iso:country":"DE",
    "sg:address":"Griemeringhauser Str.",
    "sg:city":"Marienheide",
    "sg:phone":"+49 2264/7773",
    "sg:postcode":"51709",
    "sg:province":"Nordrhein-Westfalen",
    "wof:name":"Rudolf M\u00fcller",
    "wof:placetype":"venue"
},
  "geometry": {"coordinates":[7.5468659401,51.0897026062],"type":"Point"}
}