{
  "type": "Feature",
  "properties": {
    "iso:country":"DE",
    "sg:address":"D\u00fcltgenstaler Str. 99-103 A",
    "sg:city":"Solingen",
    "sg:phone":"+49 212/310091",
    "sg:postcode":"42719",
    "sg:province":"Nordrhein-Westfalen",
    "wof:name":"Heimann Etikettendruck Christel Heimann",
    "wof:placetype":"venue"
},
  "geometry": {"coordinates":[7.055850029,51.1804656982],"type":"Point"}
}