{
  "type": "Feature",
  "properties": {
    "iso:country":"DE",
    "sg:address":"Kardinal-Galen-Ring 2",
    "sg:city":"Rheine",
    "sg:phone":"+49 5971/12602",
    "sg:postcode":"48431",
    "sg:province":"Nordrhein-Westfalen",
    "wof:name":"Musicline",
    "wof:placetype":"venue"
},
  "geometry": {"coordinates":[7.4343647957,52.279296875],"type":"Point"}
}