{
  "type": "Feature",
  "properties": {
    "iso:country":"DE",
    "sg:address":"Salower Str. 17",
    "sg:city":"Friedland",
    "sg:phone":"+49 39601/20936",
    "sg:postcode":"17098",
    "sg:province":"Mecklenburg-Vorpommern",
    "wof:name":"J. Ihlenfeld",
    "wof:placetype":"venue"
},
  "geometry": {"coordinates":[13.54159832,53.6705131531],"type":"Point"}
}