{
  "type": "Feature",
  "properties": {
    "iso:country":"DE",
    "sg:address":"Zeiss-Str. 4",
    "sg:city":"L\u00fcbbecke",
    "sg:phone":"+49 4957/4134640",
    "sg:postcode":"32312",
    "sg:province":"Nordrhein-Westfalen",
    "wof:name":"Fritz Hille Obst , Gem\u00dcse U. S\u00dcdfr\u00dcchte Import",
    "wof:placetype":"venue"
},
  "geometry": {"coordinates":[8.6228981018,52.3253555298],"type":"Point"}
}