{
  "type": "Feature",
  "properties": {
    "iso:country":"DE",
    "sg:address":"Grabenstr. 2",
    "sg:city":"Dingelst\u00e4dt",
    "sg:phone":"+49 36075/30581",
    "sg:postcode":"37351",
    "sg:province":"Th\u00fcringen",
    "wof:name":"M. Ruhs New Look",
    "wof:placetype":"venue"
},
  "geometry": {"coordinates":[10.319936,51.315258],"type":"Point"}
}