{
  "type": "Feature",
  "properties": {
    "iso:country":"DE",
    "sg:address":"Knapper Str. 51",
    "sg:city":"L\u00fcdenscheid",
    "sg:phone":"+49 2351/29009",
    "sg:postcode":"58507",
    "sg:province":"Nordrhein-Westfalen",
    "wof:name":"Backstube Siebrecht Gmbh & Co. Ohg",
    "wof:placetype":"venue"
},
  "geometry": {"coordinates":[7.625528,51.218193],"type":"Point"}
}