{
  "type": "Feature",
  "properties": {
    "iso:country":"DE",
    "sg:address":"Ihne",
    "sg:city":"Meinerzhagen",
    "sg:phone":"+49 2358/90830",
    "sg:postcode":"58540",
    "sg:province":"Nordrhein-Westfalen",
    "wof:name":"M\u00fcschenborn Gmbh",
    "wof:placetype":"venue"
},
  "geometry": {"coordinates":[7.783815,51.111019],"type":"Point"}
}