{
  "type": "Feature",
  "properties": {
    "iso:country":"DE",
    "sg:address":"Klingenderstr 5",
    "sg:city":"Paderborn",
    "sg:phone":"+49 5251/15810",
    "sg:postcode":"33100",
    "sg:province":"Nordrhein-Westfalen",
    "wof:name":"S & N Ag",
    "wof:placetype":"venue"
},
  "geometry": {"coordinates":[8.8480796814,51.7447433472],"type":"Point"}
}