{
  "type": "Feature",
  "properties": {
    "iso:country":"DE",
    "sg:address":"Holstenstr. 30",
    "sg:city":"Raisdorf",
    "sg:phone":"+49 4307/6823",
    "sg:postcode":"24223",
    "sg:province":"Schleswig-Holstein",
    "wof:name":"Volkertextil Gmbh",
    "wof:placetype":"venue"
},
  "geometry": {"coordinates":[10.2399225235,54.2813644409],"type":"Point"}
}