{
  "type": "Feature",
  "properties": {
    "iso:country":"DE",
    "sg:address":"Sonnenbergstr. 3",
    "sg:city":"Elze",
    "sg:phone":"+49 5182/6337",
    "sg:postcode":"31008",
    "sg:province":"Niedersachsen",
    "wof:name":"Heinrich Warnecke",
    "wof:placetype":"venue"
},
  "geometry": {"coordinates":[9.683917,52.080727],"type":"Point"}
}