{
  "type": "Feature",
  "properties": {
    "iso:country":"DE",
    "sg:address":"Heuwaagstr. 18",
    "sg:city":"Erlangen",
    "sg:phone":"+49 9131/29150",
    "sg:postcode":"91054",
    "sg:province":"Bayern",
    "wof:name":"Modestudio Gmbh",
    "wof:placetype":"venue"
},
  "geometry": {"coordinates":[11.0019521713,49.5989112854],"type":"Point"}
}