{
  "type": "Feature",
  "properties": {
    "iso:country":"DE",
    "sg:address":"Rathausstr. 3",
    "sg:city":"Reichenbach",
    "sg:phone":"+49 3765/12160",
    "sg:postcode":"08468",
    "sg:province":"Sachsen",
    "wof:name":"E. Gr\u00fcnert",
    "wof:placetype":"venue"
},
  "geometry": {"coordinates":[11.4140844345,50.4255027771],"type":"Point"}
}