{
  "type": "Feature",
  "properties": {
    "iso:country":"DE",
    "sg:address":"Oberheldrunger Str. 9",
    "sg:city":"Heldrungen",
    "sg:phone":"+49 34673/91304",
    "sg:postcode":"06577",
    "sg:province":"Th\u00fcringen",
    "wof:name":"J\u00fcrgen H\u00fcbner",
    "wof:placetype":"venue"
},
  "geometry": {"coordinates":[11.2153053284,51.2989387512],"type":"Point"}
}