{
  "type": "Feature",
  "properties": {
    "iso:country":"DE",
    "sg:address":"Gymnicher Hauptstr. 22",
    "sg:city":"Erftstadt",
    "sg:phone":"+49 2235/77626",
    "sg:postcode":"50374",
    "sg:province":"Nordrhein-Westfalen",
    "wof:name":"Johannes Schorn",
    "wof:placetype":"venue"
},
  "geometry": {"coordinates":[6.741121,50.838528],"type":"Point"}
}