{
  "type": "Feature",
  "properties": {
    "iso:country":"DE",
    "sg:address":"Lilienweg 20",
    "sg:city":"Hennef",
    "sg:phone":"+49 4922/425473",
    "sg:postcode":"53773",
    "sg:province":"Nordrhein-Westfalen",
    "wof:name":"Platronic Gmbh",
    "wof:placetype":"venue"
},
  "geometry": {"coordinates":[7.28394,50.768826],"type":"Point"}
}