{
  "type": "Feature",
  "properties": {
    "iso:country":"DE",
    "sg:address":"Dankmarsteig 125",
    "sg:city":"Berlin",
    "sg:phone":"+49 30/6732656",
    "sg:postcode":"12524",
    "sg:province":"Berlin",
    "wof:name":"Hans-eberhard Ernst",
    "wof:placetype":"venue"
},
  "geometry": {"coordinates":[13.534918,52.411446],"type":"Point"}
}