{
  "type": "Feature",
  "properties": {
    "iso:country":"DE",
    "sg:address":"Hauptstr. 5",
    "sg:city":"Stecklenberg",
    "sg:phone":"+49 3947/3180",
    "sg:postcode":"06507",
    "sg:province":"Sachsen-Anhalt",
    "wof:name":"Walter Schiebeck",
    "wof:placetype":"venue"
},
  "geometry": {"coordinates":[11.0873,51.733379],"type":"Point"}
}