{
  "type": "Feature",
  "properties": {
    "iso:country":"DE",
    "sg:address":"Schillerstr. 2",
    "sg:city":"Ludwigshafen",
    "sg:phone":"+49 621/679449",
    "sg:postcode":"67071",
    "sg:province":"Rheinland-Pfalz",
    "wof:name":"Ulla",
    "wof:placetype":"venue"
},
  "geometry": {"coordinates":[8.375792,49.491837],"type":"Point"}
}