{
  "type": "Feature",
  "properties": {
    "iso:country":"DE",
    "sg:address":"Kunstm\u00fchlstr 14",
    "sg:city":"Rosenheim",
    "sg:phone":"+49 8631/161821",
    "sg:postcode":"83026",
    "sg:province":"Bayern",
    "wof:name":"Adler-lackvertrieb Gmbh",
    "wof:placetype":"venue"
},
  "geometry": {"coordinates":[12.113655,47.847553],"type":"Point"}
}