{
  "type": "Feature",
  "properties": {
    "iso:country":"DE",
    "sg:address":"Schubertstr. 92",
    "sg:city":"Obertshausen",
    "sg:phone":"+49 6104/972944",
    "sg:postcode":"63179",
    "sg:province":"Hessen",
    "wof:name":"Dr. Georg Loos Consulting Gmbh",
    "wof:placetype":"venue"
},
  "geometry": {"coordinates":[8.870100975,50.0798683167],"type":"Point"}
}