{
  "type": "Feature",
  "properties": {
    "iso:country":"DE",
    "sg:address":"Sprenger Str. 2",
    "sg:city":"P\u00fcttlingen",
    "sg:phone":"+49 6806/4309",
    "sg:postcode":"66346",
    "sg:province":"Saarland",
    "wof:name":"Aral Ag",
    "wof:placetype":"venue"
},
  "geometry": {"coordinates":[6.8981871605,49.3008384705],"type":"Point"}
}