{
  "type": "Feature",
  "properties": {
    "iso:country":"DE",
    "sg:address":"Hohenneuffenstr. 21",
    "sg:city":"R\u00f6merstein",
    "sg:phone":"+49 7382/660",
    "sg:postcode":"72587",
    "sg:province":"Baden-W\u00fcrttemberg",
    "wof:name":"Friedrich G\u00f6tz",
    "wof:placetype":"venue"
},
  "geometry": {"coordinates":[9.505865097,48.4972000122],"type":"Point"}
}