{
  "type": "Feature",
  "properties": {
    "iso:country":"DE",
    "sg:address":"J\u00e4gersfreuder Str. 37",
    "sg:city":"Saarbr\u00fccken",
    "sg:phone":"+49 681/47038",
    "sg:postcode":"66113",
    "sg:province":"Saarland",
    "wof:name":"G. W. Stehlin Masseur",
    "wof:placetype":"venue"
},
  "geometry": {"coordinates":[6.988079071,49.2465896606],"type":"Point"}
}