{
  "type": "Feature",
  "properties": {
    "iso:country":"DE",
    "sg:address":"Alfons-Oswald-Str. 10",
    "sg:city":"Ehrenkirchen",
    "sg:phone":"+49 7633/12645",
    "sg:postcode":"79238",
    "sg:province":"Baden-W\u00fcrttemberg",
    "wof:name":"Karl-heinz Wangler",
    "wof:placetype":"venue"
},
  "geometry": {"coordinates":[7.731880188,47.9380226135],"type":"Point"}
}