{
  "type": "Feature",
  "properties": {
    "iso:country":"DE",
    "sg:address":"Kriegkstr. 51",
    "sg:city":"Frankfurt",
    "sg:phone":"+49 69/97392929",
    "sg:postcode":"60326",
    "sg:province":"Hessen",
    "wof:name":"Merkez Handels Gmbh",
    "wof:placetype":"venue"
},
  "geometry": {"coordinates":[8.6388864517,50.103351593],"type":"Point"}
}