{
  "type": "Feature",
  "properties": {
    "iso:country":"DE",
    "sg:address":"Im Weihergarten 14",
    "sg:city":"Gr\u00fcndau",
    "sg:phone":"+49 4960/5890290",
    "sg:postcode":"63584",
    "sg:province":"Hessen",
    "wof:name":"Panatech Ingenieurb\u00dcro",
    "wof:placetype":"venue"
},
  "geometry": {"coordinates":[9.184742,50.261021],"type":"Point"}
}