{
  "type": "Feature",
  "properties": {
    "iso:country":"DE",
    "sg:address":"Am Bahnhof 1",
    "sg:city":"Schenefeld",
    "sg:phone":"+49 4948/92260",
    "sg:postcode":"25560",
    "sg:province":"Schleswig-Holstein",
    "wof:name":"Neumann Verzinnerei Gmbh",
    "wof:placetype":"venue"
},
  "geometry": {"coordinates":[9.48859,54.046871],"type":"Point"}
}