{
  "type": "Feature",
  "properties": {
    "iso:country":"DE",
    "sg:address":"Landwehrstr. 24",
    "sg:city":"Meiningen",
    "sg:phone":"+49 3693/503564",
    "sg:postcode":"98617",
    "sg:province":"Th\u00fcringen",
    "wof:name":"Herbert Merkel Architekt",
    "wof:placetype":"venue"
},
  "geometry": {"coordinates":[10.418454,50.559132],"type":"Point"}
}