{
  "type": "Feature",
  "properties": {
    "iso:country":"DE",
    "sg:address":"Bayerstr. 43",
    "sg:city":"M\u00fcnchen",
    "sg:postcode":"80335",
    "sg:province":"Bayern",
    "wof:name":"Turkish Airlines",
    "wof:placetype":"venue"
},
  "geometry": {"coordinates":[11.5573501587,48.1391487122],"type":"Point"}
}