{
  "type": "Feature",
  "properties": {
    "iso:country":"DE",
    "sg:address":"Braker Weg 6",
    "sg:city":"Lemgo",
    "sg:phone":"+49 5261/71479",
    "sg:postcode":"32657",
    "sg:province":"Nordrhein-Westfalen",
    "wof:name":"M. Freiburger",
    "wof:placetype":"venue"
},
  "geometry": {"coordinates":[8.9007005692,52.0227966309],"type":"Point"}
}