{
  "type": "Feature",
  "properties": {
    "iso:country":"DE",
    "sg:address":"K\u00f6lner Str. 126",
    "sg:city":"Troisdorf",
    "sg:phone":"+49 2241/78030",
    "sg:postcode":"53840",
    "sg:province":"Nordrhein-Westfalen",
    "wof:name":"Restaurant Zum Ewg",
    "wof:placetype":"venue"
},
  "geometry": {"coordinates":[7.1525621414,50.8163833618],"type":"Point"}
}