{
  "type": "Feature",
  "properties": {
    "iso:country":"DE",
    "sg:address":"Maarstr. 98 a",
    "sg:city":"Bonn",
    "sg:phone":"+49 228/97530",
    "sg:postcode":"53227",
    "sg:province":"Nordrhein-Westfalen",
    "wof:name":"Gvp Gemeinn\u00fctzige Werkst\u00e4tten Bonn Gmbh",
    "wof:placetype":"venue"
},
  "geometry": {"coordinates":[7.141995,50.738522],"type":"Point"}
}