{
  "type": "Feature",
  "properties": {
    "iso:country":"DE",
    "sg:address":"St\u00e4mmes\u00e4ckerstr. 52",
    "sg:city":"Reutlingen",
    "sg:phone":"+49 7121/29411",
    "sg:postcode":"72762",
    "sg:province":"Baden-W\u00fcrttemberg",
    "wof:name":"Dreier Gmbh",
    "wof:placetype":"venue"
},
  "geometry": {"coordinates":[9.2099018097,48.4788169861],"type":"Point"}
}