{
  "type": "Feature",
  "properties": {
    "iso:country":"DE",
    "sg:address":"Kapellenstr. 34",
    "sg:city":"Troisdorf",
    "sg:phone":"+49 2241/44261",
    "sg:postcode":"53844",
    "sg:province":"Nordrhein-Westfalen",
    "wof:name":"Christ Elektro- Installation Gmbh",
    "wof:placetype":"venue"
},
  "geometry": {"coordinates":[7.108517,50.792339],"type":"Point"}
}