{
  "type": "Feature",
  "properties": {
    "iso:country":"DE",
    "sg:address":"M\u00fchlweg 15",
    "sg:city":"Rosbach",
    "sg:phone":"+49 6007/2610",
    "sg:postcode":"61191",
    "sg:province":"Hessen",
    "wof:name":"Dieter K\u00f6ppel Steuerberater",
    "wof:placetype":"venue"
},
  "geometry": {"coordinates":[8.68475914,50.3047027588],"type":"Point"}
}