{
  "type": "Feature",
  "properties": {
    "iso:country":"DE",
    "sg:address":"Allerstr. 39",
    "sg:city":"Braunschweig",
    "sg:phone":"+49 531/336161",
    "sg:postcode":"38106",
    "sg:province":"Niedersachsen",
    "wof:name":"Vereinigte Wohnungs- Genossenschaft Eg",
    "wof:placetype":"venue"
},
  "geometry": {"coordinates":[10.54217,52.271698],"type":"Point"}
}