{
  "type": "Feature",
  "properties": {
    "iso:country":"DE",
    "sg:address":"Bergstr. 94",
    "sg:city":"Bad Liebenzell",
    "sg:phone":"+49 7052/92282",
    "sg:postcode":"75378",
    "sg:province":"Baden-W\u00fcrttemberg",
    "wof:name":"Volker Calmbach",
    "wof:placetype":"venue"
},
  "geometry": {"coordinates":[8.72219944,48.7696228027],"type":"Point"}
}