{
  "type": "Feature",
  "properties": {
    "iso:country":"DE",
    "sg:address":"Am Bahndamm 7",
    "sg:city":"Ahaus",
    "sg:phone":"+49 2561/95360",
    "sg:postcode":"48683",
    "sg:province":"Nordrhein-Westfalen",
    "wof:name":"Fenstertechnik Hemker Gmbh",
    "wof:placetype":"venue"
},
  "geometry": {"coordinates":[6.985475,52.102798],"type":"Point"}
}