{
  "type": "Feature",
  "properties": {
    "iso:country":"DE",
    "sg:address":"Weg zur M\u00fchle 6 a",
    "sg:city":"Seevetal",
    "sg:phone":"+49 4105/52244",
    "sg:postcode":"21218",
    "sg:province":"Niedersachsen",
    "wof:name":"Discothek Hittfelder M\u00fchle Gmbh",
    "wof:placetype":"venue"
},
  "geometry": {"coordinates":[9.985329628,53.3860206604],"type":"Point"}
}