{
  "type": "Feature",
  "properties": {
    "iso:country":"DE",
    "sg:address":"Hauptstr. 49",
    "sg:city":"Weilbach",
    "sg:phone":"+49 9373/1286",
    "sg:postcode":"63937",
    "sg:province":"Bayern",
    "wof:name":"Metzgerei Rudolf Breunig Gmbh",
    "wof:placetype":"venue"
},
  "geometry": {"coordinates":[9.2155971527,49.6672096252],"type":"Point"}
}