{
  "type": "Feature",
  "properties": {
    "iso:country":"DE",
    "sg:address":"Hauptstr. 30::",
    "sg:city":"Syke",
    "sg:phone":"+49 4942/42699",
    "sg:postcode":"28857",
    "sg:province":"Niedersachsen",
    "wof:name":"Volksbank Eg",
    "wof:placetype":"venue"
},
  "geometry": {"coordinates":[8.821591,52.914307],"type":"Point"}
}