{
  "type": "Feature",
  "properties": {
    "iso:country":"DE",
    "sg:address":"F\u00fcrther Str. 50",
    "sg:city":"N\u00fcrnberg",
    "sg:phone":"+49 911/263888",
    "sg:postcode":"90429",
    "sg:province":"Bayern",
    "wof:name":"Dieter Augustin",
    "wof:placetype":"venue"
},
  "geometry": {"coordinates":[11.0566339493,49.4504623413],"type":"Point"}
}