{
  "type": "Feature",
  "properties": {
    "iso:country":"DE",
    "sg:address":"Koppenstr. 21",
    "sg:city":"Hameln",
    "sg:phone":"+49 5151/53694",
    "sg:postcode":"31785",
    "sg:province":"Niedersachsen",
    "wof:name":"Motan Gmbh",
    "wof:placetype":"venue"
},
  "geometry": {"coordinates":[9.369607,52.105312],"type":"Point"}
}