{
  "type": "Feature",
  "properties": {
    "iso:country":"DE",
    "sg:address":"Magdeburger Str. 45",
    "sg:city":"Hessisch Lichtenau",
    "sg:phone":"+49 5602/5746",
    "sg:postcode":"37235",
    "sg:province":"Hessen",
    "wof:name":"E. Linke",
    "wof:placetype":"venue"
},
  "geometry": {"coordinates":[9.7079725266,51.201499939],"type":"Point"}
}