{
  "type": "Feature",
  "properties": {
    "iso:country":"DE",
    "sg:address":"Weinbergweg 24",
    "sg:city":"Remseck",
    "sg:phone":"+49 7146/41355",
    "sg:postcode":"71686",
    "sg:province":"Baden-W\u00fcrttemberg",
    "wof:name":"Eddie B\u00e4ssler Bauunternehmen Gmbh",
    "wof:placetype":"venue"
},
  "geometry": {"coordinates":[9.278986,48.890377],"type":"Point"}
}