{
  "type": "Feature",
  "properties": {
    "iso:country":"DE",
    "sg:address":"Kienmoosstr. 6",
    "sg:city":"St. Georgen",
    "sg:phone":"+49 7724/5477",
    "sg:postcode":"78112",
    "sg:province":"Baden-W\u00fcrttemberg",
    "wof:name":"Flaig Electronic Gmbh",
    "wof:placetype":"venue"
},
  "geometry": {"coordinates":[8.372803688,48.1363601685],"type":"Point"}
}