{
  "type": "Feature",
  "properties": {
    "iso:country":"DE",
    "sg:address":"Sedlmayrstr. 18",
    "sg:city":"M\u00fcnchen",
    "sg:postcode":"80634",
    "sg:province":"Bayern",
    "wof:name":"Maklerdienst Unabh\u00e4ngige Maklerbetreuer Produktpr\u00fcfung",
    "wof:placetype":"venue"
},
  "geometry": {"coordinates":[11.531606,48.148132],"type":"Point"}
}