{
  "type": "Feature",
  "properties": {
    "iso:country":"DE",
    "sg:address":"Hengistweg 13",
    "sg:city":"B\u00fcnde",
    "sg:phone":"+49 5223/14671",
    "sg:postcode":"32257",
    "sg:province":"Nordrhein-Westfalen",
    "wof:name":"G\u00fcnter Brewitt",
    "wof:placetype":"venue"
},
  "geometry": {"coordinates":[8.592538,52.186108],"type":"Point"}
}