{
  "type": "Feature",
  "properties": {
    "iso:country":"DE",
    "sg:address":"Obere Ringstr. 23",
    "sg:city":"Hiddenhausen",
    "sg:phone":"+49 5221/63088",
    "sg:postcode":"32120",
    "sg:province":"Nordrhein-Westfalen",
    "wof:name":"H. D\u00e4hn Y",
    "wof:placetype":"venue"
},
  "geometry": {"coordinates":[8.6424684525,52.1515655518],"type":"Point"}
}