{
  "type": "Feature",
  "properties": {
    "iso:country":"DE",
    "sg:address":"Spessartstr. 2",
    "sg:city":"Collenberg",
    "sg:phone":"+49 9376/466",
    "sg:postcode":"97903",
    "sg:province":"Bayern",
    "wof:name":"Paul Meisenzahl Architekt Und Ingenieur",
    "wof:placetype":"venue"
},
  "geometry": {"coordinates":[9.326335,49.774609],"type":"Point"}
}