{
  "type": "Feature",
  "properties": {
    "iso:country":"DE",
    "sg:address":"M\u00fchlenberg 10",
    "sg:city":"M\u00fclheim",
    "sg:phone":"+49 208/423897",
    "sg:postcode":"45479",
    "sg:province":"Nordrhein-Westfalen",
    "wof:name":"Helmut Knipping",
    "wof:placetype":"venue"
},
  "geometry": {"coordinates":[6.872888,51.426228],"type":"Point"}
}