{
  "type": "Feature",
  "properties": {
    "iso:country":"DE",
    "sg:address":"Elkanweg 35",
    "sg:city":"Viersen",
    "sg:phone":"+49 2162/15222",
    "sg:postcode":"41748",
    "sg:province":"Nordrhein-Westfalen",
    "wof:name":"H. Tenten",
    "wof:placetype":"venue"
},
  "geometry": {"coordinates":[6.4164910316,51.2572631836],"type":"Point"}
}