{
  "type": "Feature",
  "properties": {
    "iso:country":"DE",
    "sg:address":"Schaumbeckstr. 1",
    "sg:city":"M\u00fclheim",
    "sg:phone":"+49 2054/3362",
    "sg:postcode":"45481",
    "sg:province":"Nordrhein-Westfalen",
    "wof:name":"Karl Apeltrath",
    "wof:placetype":"venue"
},
  "geometry": {"coordinates":[6.902486,51.377926],"type":"Point"}
}