{
  "type": "Feature",
  "properties": {
    "iso:country":"DE",
    "sg:address":"Widdersdorfer Str. 228",
    "sg:city":"K\u00f6ln",
    "sg:phone":"+49 221/496393",
    "sg:postcode":"50825",
    "sg:province":"Nordrhein-Westfalen",
    "wof:name":"Restaurant Al Capone",
    "wof:placetype":"venue"
},
  "geometry": {"coordinates":[6.8963851929,50.9463233948],"type":"Point"}
}