{
  "type": "Feature",
  "properties": {
    "iso:country":"DE",
    "sg:address":"Am Anger 6",
    "sg:city":"P\u00f6rnbach",
    "sg:postcode":"85309",
    "sg:province":"Bayern",
    "wof:name":"Sch\u00f6n- Gmbh",
    "wof:placetype":"venue"
},
  "geometry": {"coordinates":[11.458533,48.616642],"type":"Point"}
}