{
  "type": "Feature",
  "properties": {
    "iso:country":"DE",
    "sg:address":"Poststr. 27",
    "sg:city":"Amtsberg",
    "sg:phone":"+49 37209/80991",
    "sg:postcode":"09439",
    "sg:province":"Sachsen",
    "wof:name":"Gerd Zschage",
    "wof:placetype":"venue"
},
  "geometry": {"coordinates":[12.9853420258,50.7480621338],"type":"Point"}
}