{
  "type": "Feature",
  "properties": {
    "iso:country":"DE",
    "sg:address":"Viehofer Str. 68",
    "sg:city":"Essen",
    "sg:phone":"+49 201/20319",
    "sg:postcode":"45127",
    "sg:province":"Nordrhein-Westfalen",
    "wof:name":"Loptique Ges. F\u00fcr Lichtsysteme Mbh",
    "wof:placetype":"venue"
},
  "geometry": {"coordinates":[7.013953,51.46088],"type":"Point"}
}