{
  "type": "Feature",
  "properties": {
    "iso:country":"DE",
    "sg:address":"Benesisstr. 24",
    "sg:city":"K\u00f6ln",
    "sg:phone":"+49 221/2579724",
    "sg:postcode":"50672",
    "sg:province":"Nordrhein-Westfalen",
    "wof:name":"Mathes",
    "wof:placetype":"venue"
},
  "geometry": {"coordinates":[6.942623,50.936527],"type":"Point"}
}