{
  "type": "Feature",
  "properties": {
    "iso:country":"DE",
    "sg:address":"Am Bahnhof 2-4",
    "sg:city":"L\u00fcbeck",
    "sg:phone":"+49 451/84045",
    "sg:postcode":"23558",
    "sg:province":"Schleswig-Holstein",
    "wof:name":"Bahnhofsgastst\u00e4tten L\u00fcbsche Katen",
    "wof:placetype":"venue"
},
  "geometry": {"coordinates":[10.6711215973,53.8672676086],"type":"Point"}
}