{
  "type": "Feature",
  "properties": {
    "iso:country":"DE",
    "sg:address":"Steinstr. 51",
    "sg:city":"Bonn",
    "sg:phone":"+49 228/373937",
    "sg:postcode":"53175",
    "sg:province":"Nordrhein-Westfalen",
    "wof:name":"Toni Zimmermann",
    "wof:placetype":"venue"
},
  "geometry": {"coordinates":[7.1616520882,50.7003593445],"type":"Point"}
}