{
  "type": "Feature",
  "properties": {
    "iso:country":"DE",
    "sg:address":"Reinshagener Str. 72",
    "sg:city":"Remscheid",
    "sg:phone":"+49 2191/77201",
    "sg:postcode":"42857",
    "sg:province":"Nordrhein-Westfalen",
    "wof:name":"Dietmar Kupisch",
    "wof:placetype":"venue"
},
  "geometry": {"coordinates":[7.1530160904,51.1611671448],"type":"Point"}
}