{
  "type": "Feature",
  "properties": {
    "iso:country":"DE",
    "sg:address":"Hainstr. 3",
    "sg:city":"Berlin",
    "sg:phone":"+49 30/6315704",
    "sg:postcode":"12439",
    "sg:province":"Berlin",
    "wof:name":"Bernhard Nast",
    "wof:placetype":"venue"
},
  "geometry": {"coordinates":[13.519036,52.456554],"type":"Point"}
}