{
  "type": "Feature",
  "properties": {
    "iso:country":"DE",
    "sg:address":"Noestr. 26",
    "sg:city":"M\u00fcnchen",
    "sg:phone":"+49 89/796862",
    "sg:postcode":"81479",
    "sg:province":"Bayern",
    "wof:name":"Ursula M. Renner",
    "wof:placetype":"venue"
},
  "geometry": {"coordinates":[11.530496,48.087357],"type":"Point"}
}