{
  "type": "Feature",
  "properties": {
    "iso:country":"DE",
    "sg:address":"Riemannstr. 41",
    "sg:city":"Bonn",
    "sg:phone":"+49 4922/8258353",
    "sg:postcode":"53125",
    "sg:province":"Nordrhein-Westfalen",
    "wof:name":"K\u00d6gler Korken Gmbh",
    "wof:placetype":"venue"
},
  "geometry": {"coordinates":[7.0543608665,50.6988182068],"type":"Point"}
}