{
  "type": "Feature",
  "properties": {
    "iso:country":"DE",
    "sg:address":"Rembrandtstr. 32",
    "sg:city":"Heiligenhaus",
    "sg:phone":"+49 2056/60448",
    "sg:postcode":"42579",
    "sg:province":"Nordrhein-Westfalen",
    "wof:name":"Klaus Renn Gmbh",
    "wof:placetype":"venue"
},
  "geometry": {"coordinates":[6.971208,51.321102],"type":"Point"}
}