{
  "type": "Feature",
  "properties": {
    "iso:country":"DE",
    "sg:address":"Am Ilmbach 8",
    "sg:city":"Leutenberg",
    "sg:phone":"+49 36734/22464",
    "sg:postcode":"07338",
    "sg:province":"Th\u00fcringen",
    "wof:name":"Ursula Kleins\u00fcck",
    "wof:placetype":"venue"
},
  "geometry": {"coordinates":[11.452452,50.563984],"type":"Point"}
}