{
  "type": "Feature",
  "properties": {
    "iso:country":"DE",
    "sg:address":"Am Ossenbrink 38 c",
    "sg:city":"Herdecke",
    "sg:postcode":"58313",
    "sg:province":"Nordrhein-Westfalen",
    "wof:name":"Gotia Gesellschaft F\u00fcr Schl\u00fcsselfertiges Bauen Mbh",
    "wof:placetype":"venue"
},
  "geometry": {"coordinates":[7.457753,51.43581],"type":"Point"}
}