{
  "type": "Feature",
  "properties": {
    "iso:country":"DE",
    "sg:address":"Oststr. 139",
    "sg:city":"Duisburg",
    "sg:postcode":"47057",
    "sg:province":"Nordrhein-Westfalen",
    "wof:name":"Armin Sabelus",
    "wof:placetype":"venue"
},
  "geometry": {"coordinates":[6.787718,51.427399],"type":"Point"}
}