{
  "type": "Feature",
  "properties": {
    "iso:country":"DE",
    "sg:address":"Arnold-Dehnen-Stra\u00dfe 46",
    "sg:city":"Duisburg",
    "sg:phone":"+49 203",
    "sg:postcode":"47138",
    "sg:province":"Nordrhein-Westfalen",
    "wof:name":"Ducati Stasch Duisburg",
    "wof:placetype":"venue"
},
  "geometry": {"coordinates":[6.797313,51.476444],"type":"Point"}
}