{
  "type": "Feature",
  "properties": {
    "iso:country":"DE",
    "sg:address":"Hainstr. 13",
    "sg:city":"Mittenaar",
    "sg:phone":"+49 6444/8077",
    "sg:postcode":"35756",
    "sg:province":"Hessen",
    "wof:name":"Dieter Henrich",
    "wof:placetype":"venue"
},
  "geometry": {"coordinates":[8.4274206161,50.6678733826],"type":"Point"}
}