{
  "type": "Feature",
  "properties": {
    "iso:country":"DE",
    "sg:address":"Breiter Weg 13",
    "sg:city":"Hameln",
    "sg:phone":"+49 5151/609960",
    "sg:postcode":"31787",
    "sg:province":"Niedersachsen",
    "wof:name":"Pohl & Pracht Gmbh",
    "wof:placetype":"venue"
},
  "geometry": {"coordinates":[9.3476247787,52.1020812988],"type":"Point"}
}