{
  "type": "Feature",
  "properties": {
    "iso:country":"DE",
    "sg:address":"Alte Str. 10",
    "sg:city":"Ebersbrunn",
    "sg:phone":"+49 37607/6155",
    "sg:postcode":"08144",
    "sg:province":"Sachsen",
    "wof:name":"Mario Simon",
    "wof:placetype":"venue"
},
  "geometry": {"coordinates":[12.4606781006,50.6272010803],"type":"Point"}
}