{
  "type": "Feature",
  "properties": {
    "iso:country":"DE",
    "sg:address":"Hinter Mont 24",
    "sg:city":"Treis-Karden",
    "sg:phone":"+49 2672/1445",
    "sg:postcode":"56253",
    "sg:province":"Rheinland-Pfalz",
    "wof:name":"Hans-josef Freiwald",
    "wof:placetype":"venue"
},
  "geometry": {"coordinates":[7.3065748215,50.1746826172],"type":"Point"}
}