{
  "type": "Feature",
  "properties": {
    "iso:country":"DE",
    "sg:address":"Marktstr. 4",
    "sg:city":"Salzgitter",
    "sg:phone":"+49 5341/301400",
    "sg:postcode":"38259",
    "sg:province":"Niedersachsen",
    "wof:name":"Bali Computer Gmbh",
    "wof:placetype":"venue"
},
  "geometry": {"coordinates":[10.3714942932,52.0477027893],"type":"Point"}
}