{
  "type": "Feature",
  "properties": {
    "iso:country":"DE",
    "sg:address":"Hollerstr. 47-63",
    "sg:city":"B\u00fcdelsdorf",
    "sg:phone":"+49 4331/30118",
    "sg:postcode":"24782",
    "sg:province":"Schleswig-Holstein",
    "wof:name":"Jeans Fritz",
    "wof:placetype":"venue"
},
  "geometry": {"coordinates":[9.668731,54.313351],"type":"Point"}
}