{
  "type": "Feature",
  "properties": {
    "iso:country":"DE",
    "sg:address":"N\u00fcrnberger Str. 21",
    "sg:city":"Erlangen",
    "sg:phone":"+49 9131/23270",
    "sg:postcode":"91052",
    "sg:province":"Bayern",
    "wof:name":"Costei Kaffee Und Tee Gmbh & Co.",
    "wof:placetype":"venue"
},
  "geometry": {"coordinates":[11.0054397583,49.5926933289],"type":"Point"}
}