{
  "type": "Feature",
  "properties": {
    "iso:country":"DE",
    "sg:address":"Rosenthaler Str. 2",
    "sg:city":"Leutenberg",
    "sg:phone":"+49 36734/22375",
    "sg:postcode":"07338",
    "sg:province":"Th\u00fcringen",
    "wof:name":"Wilhelmsruhe",
    "wof:placetype":"venue"
},
  "geometry": {"coordinates":[11.4454965591,50.5665092468],"type":"Point"}
}