{
  "type": "Feature",
  "properties": {
    "iso:country":"DE",
    "sg:address":"Norder Gath",
    "sg:city":"Nieb\u00fcll",
    "sg:phone":"+49 4661/8511",
    "sg:postcode":"25899",
    "sg:province":"Schleswig-Holstein",
    "wof:name":"Wolfgang Staacken",
    "wof:placetype":"venue"
},
  "geometry": {"coordinates":[8.846745,54.794216],"type":"Point"}
}