{
  "type": "Feature",
  "properties": {
    "iso:country":"DE",
    "sg:address":"Elbersberg 100",
    "sg:city":"Pottenstein",
    "sg:phone":"+49 9243/250",
    "sg:postcode":"91278",
    "sg:province":"Bayern",
    "wof:name":"Nordbayrische Baugesellschaft Inh. Roland Weidmann",
    "wof:placetype":"venue"
},
  "geometry": {"coordinates":[11.443908,49.753258],"type":"Point"}
}