{
  "type": "Feature",
  "properties": {
    "iso:country":"DE",
    "sg:address":"Gellertstr. 25",
    "sg:city":"Hamburg",
    "sg:postcode":"22301",
    "sg:province":"Hamburg",
    "wof:name":"Bentes Rolf Bente Gmbh",
    "wof:placetype":"venue"
},
  "geometry": {"coordinates":[10.0060195923,53.5800819397],"type":"Point"}
}