{
  "type": "Feature",
  "properties": {
    "iso:country":"DE",
    "sg:address":"Dorfplatz 36",
    "sg:city":"Anger",
    "sg:phone":"+49 8656/230",
    "sg:postcode":"83454",
    "sg:province":"Bayern",
    "wof:name":"Landgasthof Zur Post",
    "wof:placetype":"venue"
},
  "geometry": {"coordinates":[12.8566856384,47.8025169373],"type":"Point"}
}