{
  "type": "Feature",
  "properties": {
    "iso:country":"DE",
    "sg:address":"Am Koberbach 21",
    "sg:city":"Crimmitschau",
    "sg:phone":"+49 36608/20090",
    "sg:postcode":"08451",
    "sg:province":"Sachsen",
    "wof:name":"Spedition Martin Gmbh",
    "wof:placetype":"venue"
},
  "geometry": {"coordinates":[12.3028945923,50.7962303162],"type":"Point"}
}