{
  "type": "Feature",
  "properties": {
    "iso:country":"DE",
    "sg:address":"Steinkamp 34",
    "sg:city":"Harrislee",
    "sg:phone":"+49 461/73330",
    "sg:postcode":"24955",
    "sg:province":"Schleswig-Holstein",
    "wof:name":"Rolf Altn\u00f6der Ingenieur",
    "wof:placetype":"venue"
},
  "geometry": {"coordinates":[9.4049987793,54.8021507263],"type":"Point"}
}