{
  "type": "Feature",
  "properties": {
    "iso:country":"DE",
    "sg:address":"Robert-Bosch-Str. 5",
    "sg:city":"Nauheim",
    "sg:phone":"+49 6152/62519",
    "sg:postcode":"64569",
    "sg:province":"Hessen",
    "wof:name":"Pizzeria Da-ciccio",
    "wof:placetype":"venue"
},
  "geometry": {"coordinates":[8.4426736832,49.9446144104],"type":"Point"}
}