{
  "type": "Feature",
  "properties": {
    "iso:country":"DE",
    "sg:address":"Rheinblickstr. 17a",
    "sg:city":"Rheinbreitbach",
    "sg:postcode":"53619",
    "sg:province":"Rheinland-Pfalz",
    "wof:name":"Mechnig Verm\u00f6gensverwaltung Gmbh & Co. Kg",
    "wof:placetype":"venue"
},
  "geometry": {"coordinates":[7.2324261665,50.6238899231],"type":"Point"}
}