{
  "type": "Feature",
  "properties": {
    "iso:country":"DE",
    "sg:address":"Werderstr. 8",
    "sg:city":"Gifhorn",
    "sg:phone":"+49 5371/56357",
    "sg:postcode":"38518",
    "sg:province":"Niedersachsen",
    "wof:name":"Nagelstudio Lady Like",
    "wof:placetype":"venue"
},
  "geometry": {"coordinates":[10.524516,52.483234],"type":"Point"}
}