{
  "type": "Feature",
  "properties": {
    "iso:country":"DE",
    "sg:address":"Matth\u00e4ushof 1",
    "sg:city":"Bad Kreuznach",
    "sg:phone":"+49 671/8340070",
    "sg:postcode":"55545",
    "sg:province":"Rheinland-Pfalz",
    "wof:name":"Moss Gmbh",
    "wof:placetype":"venue"
},
  "geometry": {"coordinates":[7.856093,49.848679],"type":"Point"}
}