{
  "type": "Feature",
  "properties": {
    "iso:country":"DE",
    "sg:address":"Im G\u00f6tzenkreuz 1",
    "sg:city":"Neuenstadt",
    "sg:phone":"+49 7139/505",
    "sg:postcode":"74196",
    "sg:province":"Baden-W\u00fcrttemberg",
    "wof:name":"G\u00f6tz Tippelmann Ingenieur",
    "wof:placetype":"venue"
},
  "geometry": {"coordinates":[9.3268442154,49.2337112427],"type":"Point"}
}