{
  "type": "Feature",
  "properties": {
    "iso:country":"DE",
    "sg:address":"Maikammerer Str. 13",
    "sg:city":"St Martin",
    "sg:phone":"+49 6323/4499",
    "sg:postcode":"67487",
    "sg:province":"Rheinland-Pfalz",
    "wof:name":"Otmar Kiefer Weinanbau",
    "wof:placetype":"venue"
},
  "geometry": {"coordinates":[8.1042976379,49.299785614],"type":"Point"}
}