{
  "type": "Feature",
  "properties": {
    "iso:country":"DE",
    "sg:address":"Urnburger Weg 9",
    "sg:city":"Eutingen",
    "sg:phone":"+49 7457/8323",
    "sg:postcode":"72184",
    "sg:province":"Baden-W\u00fcrttemberg",
    "wof:name":"August N\u00e4gele",
    "wof:placetype":"venue"
},
  "geometry": {"coordinates":[8.788304,48.459236],"type":"Point"}
}