{
  "type": "Feature",
  "properties": {
    "iso:country":"DE",
    "sg:address":"Bergisch Gladbacher Str. 265k",
    "sg:city":"K\u00f6ln",
    "sg:phone":"+49 221/636511",
    "sg:postcode":"51063",
    "sg:province":"Nordrhein-Westfalen",
    "wof:name":"Alpha Immobilien- Verwaltungsges. Mbh",
    "wof:placetype":"venue"
},
  "geometry": {"coordinates":[7.0249118805,50.9655838013],"type":"Point"}
}