{
  "type": "Feature",
  "properties": {
    "iso:country":"DE",
    "sg:address":"Frauentorstr. 3",
    "sg:city":"Weimar",
    "sg:phone":"+49 241/404127",
    "sg:postcode":"99423",
    "sg:province":"Th\u00fcringen",
    "wof:name":"Deutsche Bank Ag",
    "wof:placetype":"venue"
},
  "geometry": {"coordinates":[6.168337,50.777199],"type":"Point"}
}