{
  "type": "Feature",
  "properties": {
    "iso:country":"DE",
    "sg:address":"H\u00f6ngesberg 4",
    "sg:city":"Lohmar",
    "sg:phone":"+49 2246/912392",
    "sg:postcode":"53797",
    "sg:province":"Nordrhein-Westfalen",
    "wof:name":"Euro-shop Handelsagentur M. Lindscheid",
    "wof:placetype":"venue"
},
  "geometry": {"coordinates":[7.2115631104,50.8409042358],"type":"Point"}
}