{
  "type": "Feature",
  "properties": {
    "iso:country":"DE",
    "sg:address":"Erich-Heckel-Str. 15",
    "sg:city":"K\u00f6ln",
    "sg:phone":"+49 221/488011",
    "sg:postcode":"50933",
    "sg:province":"Nordrhein-Westfalen",
    "wof:name":"G\u00fcrtler & Mempel Gmbh",
    "wof:placetype":"venue"
},
  "geometry": {"coordinates":[6.857195,50.941189],"type":"Point"}
}