{
  "type": "Feature",
  "properties": {
    "iso:country":"DE",
    "sg:address":"Haller Str. 106",
    "sg:city":"Blaufelden",
    "sg:phone":"+49 7952/925555",
    "sg:postcode":"74572",
    "sg:province":"Baden-W\u00fcrttemberg",
    "wof:name":"J. Obinger",
    "wof:placetype":"venue"
},
  "geometry": {"coordinates":[9.9766159058,49.2965011597],"type":"Point"}
}