{
  "type": "Feature",
  "properties": {
    "iso:country":"DE",
    "sg:address":"Wilhelmstr. 61",
    "sg:city":"G\u00fctersloh",
    "sg:phone":"+49 5241/40696",
    "sg:postcode":"33332",
    "sg:province":"Nordrhein-Westfalen",
    "wof:name":"Herbert Dr\u00fccker Zeltverleih",
    "wof:placetype":"venue"
},
  "geometry": {"coordinates":[8.4008989334,51.8817062378],"type":"Point"}
}