{
  "type": "Feature",
  "properties": {
    "iso:country":"DE",
    "sg:address":"Bernhard-Rehkopf-Str. 1",
    "sg:city":"Isernhagen",
    "sg:phone":"+49 511/612506",
    "sg:postcode":"30916",
    "sg:province":"Niedersachsen",
    "wof:name":"Gebr. Hillebrand Gmbh Orgelbau Kg",
    "wof:placetype":"venue"
},
  "geometry": {"coordinates":[9.856970787,52.4340400696],"type":"Point"}
}