{
  "type": "Feature",
  "properties": {
    "iso:country":"DE",
    "sg:address":"Knochenhauerstr. 41",
    "sg:city":"Bremen",
    "sg:phone":"+49 421/171411",
    "sg:postcode":"28195",
    "sg:province":"Bremen",
    "wof:name":"L Uomo Gmbh",
    "wof:placetype":"venue"
},
  "geometry": {"coordinates":[8.8071098328,53.0785140991],"type":"Point"}
}