{
  "type": "Feature",
  "properties": {
    "iso:country":"DE",
    "sg:address":"Lutherstrasse 7",
    "sg:city":"Remchingen",
    "sg:phone":"+49 7232/79618",
    "sg:postcode":"75196",
    "sg:province":"Baden-W\u00fcrttemberg",
    "wof:name":"Web-design B.siebler",
    "wof:placetype":"venue"
},
  "geometry": {"coordinates":[8.565978,48.92849],"type":"Point"}
}