{
  "type": "Feature",
  "properties": {
    "iso:country":"DE",
    "sg:address":"Moltkestr. 3-7",
    "sg:city":"G\u00fctersloh",
    "sg:postcode":"33330",
    "sg:province":"Nordrhein-Westfalen",
    "wof:name":"Vr-tec Beratungsges. Mbh",
    "wof:placetype":"venue"
},
  "geometry": {"coordinates":[8.377743,51.907249],"type":"Point"}
}