{
  "type": "Feature",
  "properties": {
    "iso:country":"DE",
    "sg:address":"Glemseckstr. 50",
    "sg:city":"Leonberg",
    "sg:phone":"+49 7152/47411",
    "sg:postcode":"71229",
    "sg:province":"Baden-W\u00fcrttemberg",
    "wof:name":"Gastst\u00e4tte Br\u00fchlst\u00fcble",
    "wof:placetype":"venue"
},
  "geometry": {"coordinates":[9.0151462555,48.7870407104],"type":"Point"}
}