{
  "type": "Feature",
  "properties": {
    "iso:country":"DE",
    "sg:address":"An der Pfarrwiese 8",
    "sg:city":"Langg\u00f6ns",
    "sg:phone":"+49 6403/73800",
    "sg:postcode":"35428",
    "sg:province":"Hessen",
    "wof:name":"Autosport",
    "wof:placetype":"venue"
},
  "geometry": {"coordinates":[8.6493091583,50.494846344],"type":"Point"}
}