{
  "type": "Feature",
  "properties": {
    "iso:country":"DE",
    "sg:address":"Georgiistr. 17",
    "sg:city":"Wernigerode",
    "sg:phone":"+49 3943/633054",
    "sg:postcode":"38855",
    "sg:province":"Sachsen-Anhalt",
    "wof:name":"Heinz Sallier",
    "wof:placetype":"venue"
},
  "geometry": {"coordinates":[10.77725,51.837463],"type":"Point"}
}