{
  "type": "Feature",
  "properties": {
    "iso:country":"DE",
    "sg:address":"Mertinger Str. 31",
    "sg:city":"Donauw\u00f6rth",
    "sg:phone":"+49 906/28521",
    "sg:postcode":"86609",
    "sg:province":"Bayern",
    "wof:name":"Sewald Gmbh & Co.",
    "wof:placetype":"venue"
},
  "geometry": {"coordinates":[10.782177,48.687412],"type":"Point"}
}