{
  "type": "Feature",
  "properties": {
    "iso:country":"DE",
    "sg:address":"Hermann-Josef-Str.",
    "sg:city":"Z\u00fclpich",
    "sg:postcode":"53909",
    "sg:province":"Nordrhein-Westfalen",
    "wof:name":"Kolpingverein Hoven Hans Greuel",
    "wof:placetype":"venue"
},
  "geometry": {"coordinates":[6.6403250694,50.684753418],"type":"Point"}
}