{
  "type": "Feature",
  "properties": {
    "iso:country":"DE",
    "sg:address":"Steinstr. 19",
    "sg:city":"Malchin",
    "sg:phone":"+49 3994/222587",
    "sg:postcode":"17139",
    "sg:province":"Mecklenburg-Vorpommern",
    "wof:name":"Anke Horn Architektin",
    "wof:placetype":"venue"
},
  "geometry": {"coordinates":[12.763069,53.737759],"type":"Point"}
}