{
  "type": "Feature",
  "properties": {
    "iso:country":"DE",
    "sg:address":"Gartenstr. 115",
    "sg:city":"Langen",
    "sg:phone":"+49 6103/22011",
    "sg:postcode":"63225",
    "sg:province":"Hessen",
    "wof:name":"Dieter Komp",
    "wof:placetype":"venue"
},
  "geometry": {"coordinates":[8.6599607468,49.9926490784],"type":"Point"}
}