{
  "type": "Feature",
  "properties": {
    "iso:country":"DE",
    "sg:address":"Paul-Jauch-Weg 3",
    "sg:city":"Eningen",
    "sg:phone":"+49 7121/890053",
    "sg:postcode":"72800",
    "sg:province":"Baden-W\u00fcrttemberg",
    "wof:name":"Heinrich Schenk",
    "wof:placetype":"venue"
},
  "geometry": {"coordinates":[9.2662687302,48.482219696],"type":"Point"}
}