{
  "type": "Feature",
  "properties": {
    "iso:country":"DE",
    "sg:address":"Ainbrach",
    "sg:city":"Aiterhofen",
    "sg:phone":"+49 9421/3790",
    "sg:postcode":"94330",
    "sg:province":"Bayern",
    "wof:name":"Video-commerz Gmbh",
    "wof:placetype":"venue"
},
  "geometry": {"coordinates":[12.7134370804,48.8847846985],"type":"Point"}
}