{
  "type": "Feature",
  "properties": {
    "iso:country":"DE",
    "sg:address":"Filchnerstr. 6",
    "sg:city":"Bayreuth",
    "sg:phone":"+49 921/65099",
    "sg:postcode":"95448",
    "sg:province":"Bayern",
    "wof:name":"Schmidt Funkservice Gmbh",
    "wof:placetype":"venue"
},
  "geometry": {"coordinates":[11.594587326,49.9253959656],"type":"Point"}
}