{
  "type": "Feature",
  "properties": {
    "iso:country":"DE",
    "sg:address":"Ellenberger Str. 17",
    "sg:city":"Ellwangen",
    "sg:phone":"+49 7961/2233",
    "sg:postcode":"73479",
    "sg:province":"Baden-W\u00fcrttemberg",
    "wof:name":"Josef Frank",
    "wof:placetype":"venue"
},
  "geometry": {"coordinates":[10.1748895645,48.9858818054],"type":"Point"}
}