{
  "type": "Feature",
  "properties": {
    "iso:country":"DE",
    "sg:address":"Untertalstr. 4",
    "sg:city":"Katzenelnbogen",
    "sg:phone":"+49 6486/7322",
    "sg:postcode":"56368",
    "sg:province":"Rheinland-Pfalz",
    "wof:name":"Hs Modeshop Gmbh",
    "wof:placetype":"venue"
},
  "geometry": {"coordinates":[7.974651,50.268925],"type":"Point"}
}