{
  "type": "Feature",
  "properties": {
    "iso:country":"DE",
    "sg:address":"Poststr. 9",
    "sg:city":"Trittau",
    "sg:phone":"+49 4154/84320",
    "sg:postcode":"22946",
    "sg:province":"Schleswig-Holstein",
    "wof:name":"Walter Mohr Kg",
    "wof:placetype":"venue"
},
  "geometry": {"coordinates":[10.408722,53.609192],"type":"Point"}
}