{
  "type": "Feature",
  "properties": {
    "iso:country":"DE",
    "sg:address":"Hauptstr. 464",
    "sg:city":"Saterland",
    "sg:phone":"+49 4498/2815",
    "sg:postcode":"26683",
    "sg:province":"Niedersachsen",
    "wof:name":"Srt Sportshop Und Reisetreff Verwaltungsgesellschaft Mbh",
    "wof:placetype":"venue"
},
  "geometry": {"coordinates":[7.69306,53.094681],"type":"Point"}
}