{
  "type": "Feature",
  "properties": {
    "iso:country":"DE",
    "sg:address":"Kirchplatz 8",
    "sg:city":"Adorf",
    "sg:postcode":"08626",
    "sg:province":"Sachsen",
    "wof:name":"Ev.-luth. Kirche Adorf",
    "wof:placetype":"venue"
},
  "geometry": {"coordinates":[12.2565355301,50.3203353882],"type":"Point"}
}