{
  "type": "Feature",
  "properties": {
    "iso:country":"DE",
    "sg:address":"Kattrepelsbr\u00fccke 1",
    "sg:city":"Hamburg",
    "sg:postcode":"20095",
    "sg:province":"Hamburg",
    "wof:name":"Albert Wiener Gmbh",
    "wof:placetype":"venue"
},
  "geometry": {"coordinates":[9.999315,53.548565],"type":"Point"}
}