{
  "type": "Feature",
  "properties": {
    "iso:country":"DE",
    "sg:address":"Schwimmbachstr.",
    "sg:city":"Georgenthal",
    "sg:phone":"+49 36253/41314",
    "sg:postcode":"99887",
    "sg:province":"Th\u00fcringen",
    "wof:name":"Camping Am Schwimmbad",
    "wof:placetype":"venue"
},
  "geometry": {"coordinates":[10.659861,50.826309],"type":"Point"}
}