{
  "type": "Feature",
  "properties": {
    "iso:country":"DE",
    "sg:address":"Prackenfelser Str. 14",
    "sg:city":"Altdorf",
    "sg:phone":"+49 9187/958374",
    "sg:postcode":"90518",
    "sg:province":"Bayern",
    "wof:name":"Mcdonald's",
    "wof:placetype":"venue"
},
  "geometry": {"coordinates":[11.343706131,49.3816642761],"type":"Point"}
}