{
  "type": "Feature",
  "properties": {
    "iso:country":"DE",
    "sg:address":"Datumer Chaussee 188",
    "sg:city":"Pinneberg",
    "sg:phone":"+49 4101/65327",
    "sg:postcode":"25421",
    "sg:province":"Schleswig-Holstein",
    "wof:name":"Norddeutscher Automatenvertrieb",
    "wof:placetype":"venue"
},
  "geometry": {"coordinates":[9.7956190109,53.6300125122],"type":"Point"}
}