{
  "type": "Feature",
  "properties": {
    "iso:country":"DE",
    "sg:address":"Unter der H\u00f6ht 1",
    "sg:city":"Brauneberg",
    "sg:phone":"+49 6534/8464",
    "sg:postcode":"54472",
    "sg:province":"Rheinland-Pfalz",
    "wof:name":"Walter Conrad",
    "wof:placetype":"venue"
},
  "geometry": {"coordinates":[6.9886541367,49.9094009399],"type":"Point"}
}