{
  "type": "Feature",
  "properties": {
    "iso:country":"DE",
    "sg:address":"Robert-Koch-Str. 143",
    "sg:city":"Schmelz",
    "sg:phone":"+49 6887/2250",
    "sg:postcode":"66839",
    "sg:province":"Saarland",
    "wof:name":"Hase",
    "wof:placetype":"venue"
},
  "geometry": {"coordinates":[6.8431200981,49.4552612305],"type":"Point"}
}