{
  "type": "Feature",
  "properties": {
    "iso:country":"DE",
    "sg:address":"Wiedtalstr. 8",
    "sg:city":"Neustadt",
    "sg:phone":"+49 2683/2417",
    "sg:postcode":"53577",
    "sg:province":"Rheinland-Pfalz",
    "wof:name":"G. Manns",
    "wof:placetype":"venue"
},
  "geometry": {"coordinates":[7.4276418686,50.6224555969],"type":"Point"}
}