{
  "type": "Feature",
  "properties": {
    "iso:country":"DE",
    "sg:address":"Am Wehr 2",
    "sg:city":"K\u00fcnzelsau",
    "sg:phone":"+49 7940/6776",
    "sg:postcode":"74653",
    "sg:province":"Baden-W\u00fcrttemberg",
    "wof:name":"Neukauf",
    "wof:placetype":"venue"
},
  "geometry": {"coordinates":[9.6872196198,49.2816009521],"type":"Point"}
}