{
  "type": "Feature",
  "properties": {
    "iso:country":"DE",
    "sg:address":"Bruno-Dost-Str. 4",
    "sg:city":"Schneeberg",
    "sg:phone":"+49 3772/55362",
    "sg:postcode":"08289",
    "sg:province":"Sachsen",
    "wof:name":"M. Lein",
    "wof:placetype":"venue"
},
  "geometry": {"coordinates":[12.6274,50.604439],"type":"Point"}
}