{
  "type": "Feature",
  "properties": {
    "iso:country":"DE",
    "sg:address":"Abbestr. 2",
    "sg:city":"Berlin",
    "sg:phone":"+49 30/34811",
    "sg:postcode":"10587",
    "sg:province":"Berlin",
    "wof:name":"Physikalisch-technische Bundesanstalt Institut Berlin",
    "wof:placetype":"venue"
},
  "geometry": {"coordinates":[13.3202962875,52.5154418945],"type":"Point"}
}