{
  "type": "Feature",
  "properties": {
    "iso:country":"DE",
    "sg:address":"Friedrichstr. 34",
    "sg:city":"Neckarsulm",
    "sg:phone":"+49 7132/5579",
    "sg:postcode":"74172",
    "sg:province":"Baden-W\u00fcrttemberg",
    "wof:name":"Dr. G. Hauke Rechtsanwalt",
    "wof:placetype":"venue"
},
  "geometry": {"coordinates":[9.226102829,49.1884994507],"type":"Point"}
}