{
  "type": "Feature",
  "properties": {
    "iso:country":"DE",
    "sg:address":"Hallerplatz 12",
    "sg:city":"Hamburg",
    "sg:phone":"+49 40/456162",
    "sg:postcode":"20146",
    "sg:province":"Hamburg",
    "wof:name":"H. E. Krause",
    "wof:placetype":"venue"
},
  "geometry": {"coordinates":[9.9859466553,53.5719337463],"type":"Point"}
}