{
  "type": "Feature",
  "properties": {
    "iso:country":"DE",
    "sg:address":"Seltbachstr. 2",
    "sg:city":"Bad Urach",
    "sg:phone":"+49 7125/70614",
    "sg:postcode":"72574",
    "sg:province":"Baden-W\u00fcrttemberg",
    "wof:name":"Naturfreundehaus Seltbachhaus",
    "wof:placetype":"venue"
},
  "geometry": {"coordinates":[9.3875303268,48.4950332642],"type":"Point"}
}