{
  "type": "Feature",
  "properties": {
    "iso:country":"DE",
    "sg:address":"Lange Br\u00fccke 35",
    "sg:city":"Erfurt",
    "sg:phone":"+49 361/5669851",
    "sg:postcode":"99084",
    "sg:province":"Th\u00fcringen",
    "wof:name":"Basislager Sportartikel Gmbh",
    "wof:placetype":"venue"
},
  "geometry": {"coordinates":[11.027158,50.974216],"type":"Point"}
}