{
  "type": "Feature",
  "properties": {
    "iso:country":"DE",
    "sg:address":"Mainzer Landstr. 95",
    "sg:city":"Frankfurt",
    "sg:phone":"+49 69/253855",
    "sg:postcode":"60329",
    "sg:province":"Hessen",
    "wof:name":"Fennischfuchser",
    "wof:placetype":"venue"
},
  "geometry": {"coordinates":[8.6613397598,50.1097183228],"type":"Point"}
}