{
  "type": "Feature",
  "properties": {
    "iso:country":"DE",
    "sg:address":"Gewerbering 3",
    "sg:city":"Untergriesbach",
    "sg:phone":"+49 8593/93143",
    "sg:postcode":"94107",
    "sg:province":"Bayern",
    "wof:name":"Hans Ritt",
    "wof:placetype":"venue"
},
  "geometry": {"coordinates":[13.681346,48.574459],"type":"Point"}
}