{
  "type": "Feature",
  "properties": {
    "iso:country":"DE",
    "sg:address":"Sch\u00e4fergasse 3",
    "sg:city":"Eppstein",
    "sg:phone":"+49 6198/33525",
    "sg:postcode":"65817",
    "sg:province":"Hessen",
    "wof:name":"Ian Castle Antiquit\u00e4ten",
    "wof:placetype":"venue"
},
  "geometry": {"coordinates":[8.360009,50.140175],"type":"Point"}
}