{
  "type": "Feature",
  "properties": {
    "iso:country":"DE",
    "sg:address":"Stock 21",
    "sg:city":"T\u00f6nisvorst",
    "sg:phone":"+49 2156/1036",
    "sg:postcode":"47918",
    "sg:province":"Nordrhein-Westfalen",
    "wof:name":"Irene Verhoeven Living Art E. K.",
    "wof:placetype":"venue"
},
  "geometry": {"coordinates":[6.4824738503,51.3012657166],"type":"Point"}
}