{
  "type": "Feature",
  "properties": {
    "iso:country":"DE",
    "sg:address":"Dorfstr. 29a",
    "sg:city":"Preetz",
    "sg:phone":"+49 38323/411",
    "sg:postcode":"18445",
    "sg:province":"Mecklenburg-Vorpommern",
    "wof:name":"Ingo Borchardt",
    "wof:placetype":"venue"
},
  "geometry": {"coordinates":[12.98977,54.351742],"type":"Point"}
}