{
  "type": "Feature",
  "properties": {
    "iso:country":"DE",
    "sg:address":"Bahnhofstr. 34",
    "sg:city":"Laichingen",
    "sg:phone":"+49 7333/947444",
    "sg:postcode":"89150",
    "sg:province":"Baden-W\u00fcrttemberg",
    "wof:name":"Prompt Und Proper Service Rund Ums Haus Gmbh",
    "wof:placetype":"venue"
},
  "geometry": {"coordinates":[9.691339,48.489689],"type":"Point"}
}