{
  "type": "Feature",
  "properties": {
    "iso:country":"DE",
    "sg:address":"Benzstra\u00dfe 5",
    "sg:city":"Karlsbad",
    "sg:phone":"+49 7202/3435",
    "sg:postcode":"76307",
    "sg:province":"Baden-W\u00fcrttemberg",
    "wof:name":"Sportcafe Triangel",
    "wof:placetype":"venue"
},
  "geometry": {"coordinates":[8.5060863495,48.9143943787],"type":"Point"}
}