{
  "type": "Feature",
  "properties": {
    "iso:country":"DE",
    "sg:address":"Bahnstr. 20",
    "sg:city":"Frei-Laubersheim",
    "sg:phone":"+49 6709/1330",
    "sg:postcode":"55546",
    "sg:province":"Rheinland-Pfalz",
    "wof:name":"Claudia Vogel",
    "wof:placetype":"venue"
},
  "geometry": {"coordinates":[7.9035801888,49.7998847961],"type":"Point"}
}