{
  "type": "Feature",
  "properties": {
    "iso:country":"DE",
    "sg:address":"Alzenauer Str. 60",
    "sg:city":"M\u00f6mbris",
    "sg:phone":"+49 6029/1344",
    "sg:postcode":"63776",
    "sg:province":"Bayern",
    "wof:name":"R. Pfarr",
    "wof:placetype":"venue"
},
  "geometry": {"coordinates":[9.14982,50.086403],"type":"Point"}
}