{
  "type": "Feature",
  "properties": {
    "iso:country":"DE",
    "sg:address":"G\u00fcnther Hafemann Str 7",
    "sg:city":"Bremen",
    "sg:phone":"+49 421/2770663",
    "sg:postcode":"28327",
    "sg:province":"Bremen",
    "wof:name":"Joachim\u00b4s Homepage",
    "wof:placetype":"venue"
},
  "geometry": {"coordinates":[8.921514,53.073772],"type":"Point"}
}