{
  "type": "Feature",
  "properties": {
    "iso:country":"DE",
    "sg:address":"Sielstr. 23",
    "sg:city":"Norden",
    "sg:phone":"+49 4931/934904",
    "sg:postcode":"26506",
    "sg:province":"Niedersachsen",
    "wof:name":"Helga Und H. G\u00fcrtler",
    "wof:placetype":"venue"
},
  "geometry": {"coordinates":[7.209174,53.591576],"type":"Point"}
}