{
  "type": "Feature",
  "properties": {
    "iso:country":"DE",
    "sg:address":"K\u00f6ttinger Weg 23",
    "sg:city":"Wissen",
    "sg:phone":"+49 2742/93140",
    "sg:postcode":"57537",
    "sg:province":"Rheinland-Pfalz",
    "wof:name":"Baugesellschaft Krahwinkel & Partner Mbh",
    "wof:placetype":"venue"
},
  "geometry": {"coordinates":[7.724007,50.774166],"type":"Point"}
}