{
  "type": "Feature",
  "properties": {
    "iso:country":"DE",
    "sg:address":"Verdistr. 29",
    "sg:city":"Stuttgart",
    "sg:phone":"+49 711/6990835",
    "sg:postcode":"70195",
    "sg:province":"Baden-W\u00fcrttemberg",
    "wof:name":"G. Markopoulos",
    "wof:placetype":"venue"
},
  "geometry": {"coordinates":[9.125668,48.780823],"type":"Point"}
}