{
  "type": "Feature",
  "properties": {
    "iso:country":"DE",
    "sg:address":"Mayener Str. 24",
    "sg:city":"Kehrig",
    "sg:phone":"+49 2651/72088",
    "sg:postcode":"56729",
    "sg:province":"Rheinland-Pfalz",
    "wof:name":"Hans-josef Keiffenheim",
    "wof:placetype":"venue"
},
  "geometry": {"coordinates":[7.222174,50.281929],"type":"Point"}
}