{
  "type": "Feature",
  "properties": {
    "iso:country":"DE",
    "sg:address":"R\u00f6dersteinweg 27",
    "sg:city":"Hofheim",
    "sg:phone":"+49 6192/900780",
    "sg:postcode":"65719",
    "sg:province":"Hessen",
    "wof:name":"Horst Boss Gmbh",
    "wof:placetype":"venue"
},
  "geometry": {"coordinates":[8.442168,50.091923],"type":"Point"}
}