{
  "type": "Feature",
  "properties": {
    "iso:country":"DE",
    "sg:address":"Homburgstr. 13",
    "sg:city":"Eschershausen",
    "sg:phone":"+49 5534/3608",
    "sg:postcode":"37632",
    "sg:province":"Niedersachsen",
    "wof:name":"Futterkrippe",
    "wof:placetype":"venue"
},
  "geometry": {"coordinates":[9.6498632431,51.9245910645],"type":"Point"}
}