{
  "type": "Feature",
  "properties": {
    "iso:country":"DE",
    "sg:address":"Knipprather Str. 2",
    "sg:city":"Langenfeld",
    "sg:phone":"+49 2173/149625",
    "sg:postcode":"40764",
    "sg:province":"Nordrhein-Westfalen",
    "wof:name":"Helmut Furthmann Architekt",
    "wof:placetype":"venue"
},
  "geometry": {"coordinates":[6.943086,51.105263],"type":"Point"}
}