{
  "type": "Feature",
  "properties": {
    "iso:country":"DE",
    "sg:address":"Hobrechtstr. 10",
    "sg:city":"Berlin",
    "sg:postcode":"12043",
    "sg:province":"Berlin",
    "wof:name":"Celebi Gmbh",
    "wof:placetype":"venue"
},
  "geometry": {"coordinates":[13.4270868301,52.4869041443],"type":"Point"}
}