{
  "type": "Feature",
  "properties": {
    "iso:country":"DE",
    "sg:address":"Malchiner Str. 12",
    "sg:city":"Gielow",
    "sg:phone":"+49 39957/20968",
    "sg:postcode":"17139",
    "sg:province":"Mecklenburg-Vorpommern",
    "wof:name":"Ewald Thimian",
    "wof:placetype":"venue"
},
  "geometry": {"coordinates":[12.754408,53.695927],"type":"Point"}
}