{
  "type": "Feature",
  "properties": {
    "iso:country":"DE",
    "sg:address":"Friedhofstr. 2",
    "sg:city":"Aalen",
    "sg:postcode":"73430",
    "sg:province":"Baden-W\u00fcrttemberg",
    "wof:name":"Aalener Treuhans Verwaltungs-gmbh",
    "wof:placetype":"venue"
},
  "geometry": {"coordinates":[10.091638,48.837742],"type":"Point"}
}