{
  "type": "Feature",
  "properties": {
    "iso:country":"DE",
    "sg:address":"Ostwall 202",
    "sg:city":"Krefeld",
    "sg:phone":"+49 2151/801776",
    "sg:postcode":"47798",
    "sg:province":"Nordrhein-Westfalen",
    "wof:name":"M. Spitzhorn",
    "wof:placetype":"venue"
},
  "geometry": {"coordinates":[6.5645880699,51.3352165222],"type":"Point"}
}