{
  "type": "Feature",
  "properties": {
    "iso:country":"DE",
    "sg:address":"Bl\u00fccherstr. 16",
    "sg:city":"Karlsruhe",
    "sg:phone":"+49 721/845742",
    "sg:postcode":"76185",
    "sg:province":"Baden-W\u00fcrttemberg",
    "wof:name":"Peter Brell",
    "wof:placetype":"venue"
},
  "geometry": {"coordinates":[8.374833107,49.0130577087],"type":"Point"}
}