{
  "type": "Feature",
  "properties": {
    "iso:country":"DE",
    "sg:address":"Graf-Siegfried-Str. 29",
    "sg:city":"Saarburg",
    "sg:phone":"+49 6581/3844",
    "sg:postcode":"54439",
    "sg:province":"Rheinland-Pfalz",
    "wof:name":"M.- L. Und Heiner Muno",
    "wof:placetype":"venue"
},
  "geometry": {"coordinates":[6.549722,49.608379],"type":"Point"}
}