{
  "type": "Feature",
  "properties": {
    "iso:country":"DE",
    "sg:address":"Eisenbahnstr. 88",
    "sg:city":"Eggenstein-Leopoldshafen",
    "sg:phone":"+49 721/9703322",
    "sg:postcode":"76344",
    "sg:province":"Baden-W\u00fcrttemberg",
    "wof:name":"Hertlein",
    "wof:placetype":"venue"
},
  "geometry": {"coordinates":[8.4007759094,49.0833435059],"type":"Point"}
}