{
  "type": "Feature",
  "properties": {
    "iso:country":"DE",
    "sg:address":"Ellhornstr. 21",
    "sg:city":"Uthlede",
    "sg:phone":"+49 4296/341",
    "sg:postcode":"27628",
    "sg:province":"Niedersachsen",
    "wof:name":"Emil W\u00fcrger",
    "wof:placetype":"venue"
},
  "geometry": {"coordinates":[8.580247879,53.3078422546],"type":"Point"}
}