{
  "type": "Feature",
  "properties": {
    "iso:country":"DE",
    "sg:address":"Maximilianstr. 11",
    "sg:city":"Speyer",
    "sg:phone":"+49 6232/24245",
    "sg:postcode":"67346",
    "sg:province":"Rheinland-Pfalz",
    "wof:name":"Kindermode D\u00fcnschede Inh. A. Pister",
    "wof:placetype":"venue"
},
  "geometry": {"coordinates":[8.4389390945,49.3172492981],"type":"Point"}
}