{
  "type": "Feature",
  "properties": {
    "iso:country":"DE",
    "sg:address":"Manzostr. 86 a",
    "sg:city":"M\u00fcnchen",
    "sg:phone":"+49 89/1403592",
    "sg:postcode":"80997",
    "sg:province":"Bayern",
    "wof:name":"Dr. Walter Lidl Rechtsanwalt",
    "wof:placetype":"venue"
},
  "geometry": {"coordinates":[11.485118866,48.1832427979],"type":"Point"}
}