{
  "type": "Feature",
  "properties": {
    "iso:country":"DE",
    "sg:address":"Bahnhofstr. 5",
    "sg:city":"Emsdetten",
    "sg:phone":"+49 2572/88889",
    "sg:postcode":"48282",
    "sg:province":"Nordrhein-Westfalen",
    "wof:name":"Wolf Optik E. K.",
    "wof:placetype":"venue"
},
  "geometry": {"coordinates":[7.530687809,52.1754875183],"type":"Point"}
}