{
  "type": "Feature",
  "properties": {
    "iso:country":"DE",
    "sg:address":"Textilstr. 9",
    "sg:city":"Augsburg",
    "sg:phone":"+49 821/883600",
    "sg:postcode":"86179",
    "sg:province":"Bayern",
    "wof:name":"Hartmuth Basan",
    "wof:placetype":"venue"
},
  "geometry": {"coordinates":[10.9078426361,48.3084793091],"type":"Point"}
}