{
  "type": "Feature",
  "properties": {
    "iso:country":"DE",
    "sg:address":"B\u00e4ckerstr. 28",
    "sg:city":"Minden",
    "sg:phone":"+49 571/850211",
    "sg:postcode":"32423",
    "sg:province":"Nordrhein-Westfalen",
    "wof:name":"Runners Point",
    "wof:placetype":"venue"
},
  "geometry": {"coordinates":[8.918571,52.28994],"type":"Point"}
}