{
  "type": "Feature",
  "properties": {
    "iso:country":"DE",
    "sg:address":"Neuwerker Str. 15",
    "sg:city":"Viersen",
    "sg:postcode":"41748",
    "sg:province":"Nordrhein-Westfalen",
    "wof:name":"Wohnwerkstadt",
    "wof:placetype":"venue"
},
  "geometry": {"coordinates":[6.414368,51.245464],"type":"Point"}
}