{
  "type": "Feature",
  "properties": {
    "iso:country":"DE",
    "sg:address":"Von-Bodelschwingh-Str.",
    "sg:city":"Korschenbroich",
    "sg:postcode":"41352",
    "sg:province":"Nordrhein-Westfalen",
    "wof:name":"Sporthalle Im Hallensport- Zentrum Korschenbroich",
    "wof:placetype":"venue"
},
  "geometry": {"coordinates":[6.514736,51.188431],"type":"Point"}
}