{
  "type": "Feature",
  "properties": {
    "iso:country":"DE",
    "sg:address":"Kirchberg 20",
    "sg:city":"Erkrath",
    "sg:phone":"+49 2104/36064",
    "sg:postcode":"40699",
    "sg:province":"Nordrhein-Westfalen",
    "wof:name":"Wolfgang Teiwes Architekt",
    "wof:placetype":"venue"
},
  "geometry": {"coordinates":[6.914568,51.222755],"type":"Point"}
}