{
  "type": "Feature",
  "properties": {
    "iso:country":"DE",
    "sg:address":"Collenbachstr. 21",
    "sg:city":"D\u00fcsseldorf",
    "sg:phone":"+49 211/446364",
    "sg:postcode":"40476",
    "sg:province":"Nordrhein-Westfalen",
    "wof:name":"Saffrans",
    "wof:placetype":"venue"
},
  "geometry": {"coordinates":[6.7821550369,51.2417907715],"type":"Point"}
}