{
  "type": "Feature",
  "properties": {
    "iso:country":"DE",
    "sg:address":"Ortsstr. 26",
    "sg:city":"Zell",
    "sg:phone":"+49 7625/621",
    "sg:postcode":"79669",
    "sg:province":"Baden-W\u00fcrttemberg",
    "wof:name":"Erwin Seger Elektroinstallation",
    "wof:placetype":"venue"
},
  "geometry": {"coordinates":[7.880232,47.727573],"type":"Point"}
}