{
  "type": "Feature",
  "properties": {
    "iso:country":"DE",
    "sg:address":"Koblenzer Str. 77",
    "sg:city":"Mayen",
    "sg:phone":"+49 2651/43431",
    "sg:postcode":"56727",
    "sg:province":"Rheinland-Pfalz",
    "wof:name":"F. Mertens & S\u00f6hne",
    "wof:placetype":"venue"
},
  "geometry": {"coordinates":[7.2301402092,50.3299102783],"type":"Point"}
}