{
  "type": "Feature",
  "properties": {
    "iso:country":"DE",
    "sg:address":"Richard-Wagner-Str. 31",
    "sg:city":"Teltow",
    "sg:phone":"+49 3328/41924",
    "sg:postcode":"14513",
    "sg:province":"Brandenburg",
    "wof:name":"Milde",
    "wof:placetype":"venue"
},
  "geometry": {"coordinates":[13.2879953384,52.3882484436],"type":"Point"}
}