{
  "type": "Feature",
  "properties": {
    "iso:country":"DE",
    "sg:address":"Landhorst 2",
    "sg:city":"Herzebrock-Clarholz",
    "sg:phone":"+49 5245/5421",
    "sg:postcode":"33442",
    "sg:province":"Nordrhein-Westfalen",
    "wof:name":"B. Herzog Gmbh & Co Kg",
    "wof:placetype":"venue"
},
  "geometry": {"coordinates":[8.188946,51.879009],"type":"Point"}
}