{
  "type": "Feature",
  "properties": {
    "iso:country":"DE",
    "sg:address":"Hauptstr. 113",
    "sg:city":"Allmendingen",
    "sg:phone":"+49 7391/8591",
    "sg:postcode":"89604",
    "sg:province":"Baden-W\u00fcrttemberg",
    "wof:name":"Otto Dietz",
    "wof:placetype":"venue"
},
  "geometry": {"coordinates":[9.725127,48.334747],"type":"Point"}
}