{
  "type": "Feature",
  "properties": {
    "iso:country":"DE",
    "sg:address":"K\u00f6lner Str. 63",
    "sg:city":"Overath",
    "sg:phone":"+49 2206/3523",
    "sg:postcode":"51491",
    "sg:province":"Nordrhein-Westfalen",
    "wof:name":"Rolf Franke",
    "wof:placetype":"venue"
},
  "geometry": {"coordinates":[7.319683075,50.9624862671],"type":"Point"}
}