{
  "type": "Feature",
  "properties": {
    "iso:country":"DE",
    "sg:address":"Urbanusstr. 17",
    "sg:city":"Leiwen",
    "sg:phone":"+49 6507/99146",
    "sg:postcode":"54340",
    "sg:province":"Rheinland-Pfalz",
    "wof:name":"Ludes Gmbh",
    "wof:placetype":"venue"
},
  "geometry": {"coordinates":[6.873065,49.822655],"type":"Point"}
}