{
  "type": "Feature",
  "properties": {
    "iso:country":"DE",
    "sg:address":"Wolfegger Str. 50",
    "sg:city":"Schlier",
    "sg:phone":"+49 4951/1431142",
    "sg:postcode":"88281",
    "sg:province":"Baden-W\u00fcrttemberg",
    "wof:name":"Apollo Holzschutz Gmbh",
    "wof:placetype":"venue"
},
  "geometry": {"coordinates":[9.738157,52.372276],"type":"Point"}
}