{
  "type": "Feature",
  "properties": {
    "iso:country":"DE",
    "sg:address":"Dachauer Str. 527",
    "sg:city":"M\u00fcnchen",
    "sg:phone":"+49 89/1495654",
    "sg:postcode":"80993",
    "sg:province":"Bayern",
    "wof:name":"F.-x. Kreuzinger",
    "wof:placetype":"venue"
},
  "geometry": {"coordinates":[11.502628,48.189991],"type":"Point"}
}