{
  "type": "Feature",
  "properties": {
    "iso:country":"DE",
    "sg:address":"Bellinostr. 7",
    "sg:city":"Rottenburg",
    "sg:postcode":"72108",
    "sg:province":"Baden-W\u00fcrttemberg",
    "wof:name":"Gr Beteiligungs- Gesellschaft Mbh",
    "wof:placetype":"venue"
},
  "geometry": {"coordinates":[8.948412,48.474701],"type":"Point"}
}