{
  "type": "Feature",
  "properties": {
    "iso:country":"DE",
    "sg:address":"Poggendiek 43L",
    "sg:city":"Hannover",
    "sg:phone":"+49 511/435043",
    "sg:postcode":"30457",
    "sg:province":"Niedersachsen",
    "wof:name":"Manfred Diehl Steuerberater",
    "wof:placetype":"venue"
},
  "geometry": {"coordinates":[9.7020511627,52.3283081055],"type":"Point"}
}