{
  "type": "Feature",
  "properties": {
    "iso:country":"DE",
    "sg:address":"Lindenstr. 32a",
    "sg:city":"Kropst\u00e4dt",
    "sg:phone":"+49 34920/20207",
    "sg:postcode":"06895",
    "sg:province":"Sachsen-Anhalt",
    "wof:name":"Agrargenossenschaft Kropst\u00e4dt E. G.",
    "wof:placetype":"venue"
},
  "geometry": {"coordinates":[12.744893,51.967125],"type":"Point"}
}