{
  "type": "Feature",
  "properties": {
    "iso:country":"DE",
    "sg:address":"Bruchm\u00fchler Str. 96",
    "sg:city":"Petershagen",
    "sg:phone":"+49 33439/7420",
    "sg:postcode":"15370",
    "sg:province":"Brandenburg",
    "wof:name":"Wolfgang Leuschner",
    "wof:placetype":"venue"
},
  "geometry": {"coordinates":[13.7815561295,52.5394287109],"type":"Point"}
}