{
  "type": "Feature",
  "properties": {
    "iso:country":"DE",
    "sg:address":"Fischergrube 47",
    "sg:city":"L\u00fcbeck",
    "sg:phone":"+49 451/77953",
    "sg:postcode":"23552",
    "sg:province":"Schleswig-Holstein",
    "wof:name":"Alibaba",
    "wof:placetype":"venue"
},
  "geometry": {"coordinates":[10.6844244003,53.8706359863],"type":"Point"}
}