{
  "type": "Feature",
  "properties": {
    "iso:country":"DE",
    "sg:address":"Meiersteg 19",
    "sg:city":"Geldern",
    "sg:phone":"+49 2831/3185",
    "sg:postcode":"47608",
    "sg:province":"Nordrhein-Westfalen",
    "wof:name":"W\u00fclfinghoffs Freesienzucht Gmbh",
    "wof:placetype":"venue"
},
  "geometry": {"coordinates":[6.3423218727,51.4943199158],"type":"Point"}
}