{
  "type": "Feature",
  "properties": {
    "iso:country":"DE",
    "sg:address":"Roggenbachstr. 53",
    "sg:city":"Schopfheim",
    "sg:phone":"+49 7622/3677",
    "sg:postcode":"79650",
    "sg:province":"Baden-W\u00fcrttemberg",
    "wof:name":"Friederike Hauser",
    "wof:placetype":"venue"
},
  "geometry": {"coordinates":[7.83183,47.653728],"type":"Point"}
}