{
  "type": "Feature",
  "properties": {
    "iso:country":"DE",
    "sg:address":"Gr\u00fcnsfelder Str. 15",
    "sg:city":"Gr\u00fcnsfeld",
    "sg:phone":"+49 9346/505",
    "sg:postcode":"97947",
    "sg:province":"Baden-W\u00fcrttemberg",
    "wof:name":"Ernst Freitag",
    "wof:placetype":"venue"
},
  "geometry": {"coordinates":[9.783037,49.598122],"type":"Point"}
}