{
  "type": "Feature",
  "properties": {
    "iso:country":"DE",
    "sg:address":"Lichtenbroicher Weg 167",
    "sg:city":"D\u00fcsseldorf",
    "sg:phone":"+49 211/626128",
    "sg:postcode":"40472",
    "sg:province":"Nordrhein-Westfalen",
    "wof:name":"Ivt-immobilienverwaltungs- Treuhand Gesellschaft Mbh",
    "wof:placetype":"venue"
},
  "geometry": {"coordinates":[6.7923121452,51.2847633362],"type":"Point"}
}