{
  "type": "Feature",
  "properties": {
    "iso:country":"DE",
    "sg:address":"Weidenbaumsweg 87",
    "sg:city":"Hamburg",
    "sg:phone":"+49 40/7214788",
    "sg:postcode":"21035",
    "sg:province":"Hamburg",
    "wof:name":"Europcar Autovermietung Gmbh",
    "wof:placetype":"venue"
},
  "geometry": {"coordinates":[10.202136,53.485363],"type":"Point"}
}