{
  "type": "Feature",
  "properties": {
    "iso:country":"DE",
    "sg:address":"Zur Linde 40",
    "sg:city":"Dreisen",
    "sg:phone":"+49 6357/326",
    "sg:postcode":"67816",
    "sg:province":"Rheinland-Pfalz",
    "wof:name":"Hotel Lochm\u00fchle",
    "wof:placetype":"venue"
},
  "geometry": {"coordinates":[8.0166139603,49.6012687683],"type":"Point"}
}