{
  "type": "Feature",
  "properties": {
    "iso:country":"DE",
    "sg:address":"Don-Bosco-Str. 1",
    "sg:city":"Benediktbeuern",
    "sg:phone":"+49 8857/88326",
    "sg:postcode":"83671",
    "sg:province":"Bayern",
    "wof:name":"Psychotherapeutische Beratungsstelle",
    "wof:placetype":"venue"
},
  "geometry": {"coordinates":[11.399108,47.709194],"type":"Point"}
}