{
  "type": "Feature",
  "properties": {
    "iso:country":"DE",
    "sg:address":"Max-Planck-Str. 9 Heimerdingen",
    "sg:city":"Ditzingen",
    "sg:phone":"+49 4971/529920",
    "sg:postcode":"71254",
    "sg:province":"Baden-W\u00fcrttemberg",
    "wof:name":"Aws Drucktechnik Gmbh",
    "wof:placetype":"venue"
},
  "geometry": {"coordinates":[9.0675649643,48.8270339966],"type":"Point"}
}