{
  "type": "Feature",
  "properties": {
    "iso:country":"DE",
    "sg:address":"Stra\u00dfe des Friedens 1 a",
    "sg:city":"Kolkwitz",
    "sg:postcode":"03099",
    "sg:province":"Brandenburg",
    "wof:name":"Lecher D\u00e4cher Gmbh",
    "wof:placetype":"venue"
},
  "geometry": {"coordinates":[14.192047,51.773647],"type":"Point"}
}