{
  "type": "Feature",
  "properties": {
    "iso:country":"DE",
    "sg:address":"Dammer Str. 41",
    "sg:city":"Bohmte",
    "sg:phone":"+49 5475/91007",
    "sg:postcode":"49163",
    "sg:province":"Niedersachsen",
    "wof:name":"Landgasthaus M\u00e4scher",
    "wof:placetype":"venue"
},
  "geometry": {"coordinates":[8.2646446228,52.4496879578],"type":"Point"}
}