{
  "type": "Feature",
  "properties": {
    "iso:country":"DE",
    "sg:address":"Pliesterbecker Str. 120",
    "sg:city":"Dorsten",
    "sg:phone":"+49 2362/62151",
    "sg:postcode":"46284",
    "sg:province":"Nordrhein-Westfalen",
    "wof:name":"Willi Karluhs Alt- Und Abfallstoffe",
    "wof:placetype":"venue"
},
  "geometry": {"coordinates":[6.945449,51.674706],"type":"Point"}
}