{
  "type": "Feature",
  "properties": {
    "iso:country":"DE",
    "sg:address":"Engelbergstr.89",
    "sg:city":"Stuttgart Weilimdorf",
    "sg:phone":"+49 711",
    "sg:postcode":"70499",
    "sg:province":"Baden-W\u00fcrttemberg",
    "wof:name":"Ramonbags - Vwm Gmbh",
    "wof:placetype":"venue"
},
  "geometry": {"coordinates":[9.093023,48.802601],"type":"Point"}
}