{
  "type": "Feature",
  "properties": {
    "iso:country":"DE",
    "sg:address":"L\u00f6hcheswald 20",
    "sg:city":"Siegen",
    "sg:phone":"+49 271/660510",
    "sg:postcode":"57074",
    "sg:province":"Nordrhein-Westfalen",
    "wof:name":"Reitz & Partner Gmbh",
    "wof:placetype":"venue"
},
  "geometry": {"coordinates":[8.0942020416,50.8923377991],"type":"Point"}
}