{
  "type": "Feature",
  "properties": {
    "iso:country":"DE",
    "sg:address":"Bergstr. 8",
    "sg:city":"Krailling",
    "sg:postcode":"82152",
    "sg:province":"Bayern",
    "wof:name":"Fmg Frankenberger- Modell Objekt Volkshaus Gmbh",
    "wof:placetype":"venue"
},
  "geometry": {"coordinates":[11.4141874313,48.1031608582],"type":"Point"}
}