{
  "type": "Feature",
  "properties": {
    "iso:country":"DE",
    "sg:address":"Hauffstr. 33",
    "sg:city":"Kassel",
    "sg:phone":"+49 561/878520",
    "sg:postcode":"34125",
    "sg:province":"Hessen",
    "wof:name":"H. R. Eggebrecht",
    "wof:placetype":"venue"
},
  "geometry": {"coordinates":[9.5068693161,51.3346214294],"type":"Point"}
}