{
  "type": "Feature",
  "properties": {
    "iso:country":"DE",
    "sg:address":"Gammertinger Str. 15",
    "sg:city":"Langenenslingen",
    "sg:phone":"+49 7376/802",
    "sg:postcode":"88515",
    "sg:province":"Baden-W\u00fcrttemberg",
    "wof:name":"Marie Mukensturm Hebamme",
    "wof:placetype":"venue"
},
  "geometry": {"coordinates":[9.337641,48.200603],"type":"Point"}
}