{
  "type": "Feature",
  "properties": {
    "iso:country":"DE",
    "sg:address":"Hopfenweg 54 a",
    "sg:city":"Oldenburg",
    "sg:phone":"+49 441/88157",
    "sg:postcode":"26125",
    "sg:province":"Niedersachsen",
    "wof:name":"F\u00fcchsel & Wiegratz Ag",
    "wof:placetype":"venue"
},
  "geometry": {"coordinates":[8.2181138992,53.1888656616],"type":"Point"}
}