{
  "type": "Feature",
  "properties": {
    "iso:country":"DE",
    "sg:address":"Bergstr. 25",
    "sg:city":"Hainewalde",
    "sg:phone":"+49 35841/35023",
    "sg:postcode":"02779",
    "sg:province":"Sachsen",
    "wof:name":"J. Rothe",
    "wof:placetype":"venue"
},
  "geometry": {"coordinates":[14.701158,50.911182],"type":"Point"}
}