{
  "type": "Feature",
  "properties": {
    "iso:country":"DE",
    "sg:address":"Goffauxstr. 38",
    "sg:city":"Hildesheim",
    "sg:phone":"+49 5121/82477",
    "sg:postcode":"31141",
    "sg:province":"Niedersachsen",
    "wof:name":"S. Walter",
    "wof:placetype":"venue"
},
  "geometry": {"coordinates":[9.990452,52.127773],"type":"Point"}
}