{
  "type": "Feature",
  "properties": {
    "iso:country":"DE",
    "sg:address":"Grunewald 1",
    "sg:city":"Waldbr\u00f6l",
    "sg:phone":"+49 2291/2541",
    "sg:postcode":"51545",
    "sg:province":"Nordrhein-Westfalen",
    "wof:name":"Gasthaus Grunewald",
    "wof:placetype":"venue"
},
  "geometry": {"coordinates":[7.5944600105,50.8525314331],"type":"Point"}
}