{
  "type": "Feature",
  "properties": {
    "iso:country":"DE",
    "sg:address":"Detmoldstr. 4",
    "sg:city":"M\u00fcnchen",
    "sg:phone":"+49 89/3510906",
    "sg:postcode":"80935",
    "sg:province":"Bayern",
    "wof:name":"K. Reitmeir",
    "wof:placetype":"venue"
},
  "geometry": {"coordinates":[11.5631685257,48.1927947998],"type":"Point"}
}