{
  "type": "Feature",
  "properties": {
    "iso:country":"DE",
    "sg:address":"Erfurter Str. 26",
    "sg:city":"Bad Sachsa",
    "sg:phone":"+49 5523/2222",
    "sg:postcode":"37441",
    "sg:province":"Niedersachsen",
    "wof:name":"Roge Comfort-wohn- Bautr\u00e4gergesellschaft Mbh",
    "wof:placetype":"venue"
},
  "geometry": {"coordinates":[10.56522,51.595142],"type":"Point"}
}