{
  "type": "Feature",
  "properties": {
    "iso:country":"DE",
    "sg:address":"Redder 10",
    "sg:city":"Geesthacht",
    "sg:phone":"+49 4152/4959",
    "sg:postcode":"21502",
    "sg:province":"Schleswig-Holstein",
    "wof:name":"Integral Beratungspartner Gesellschaft F\u00fcr Unternehmens-",
    "wof:placetype":"venue"
},
  "geometry": {"coordinates":[10.364589,53.445808],"type":"Point"}
}