{
  "type": "Feature",
  "properties": {
    "iso:country":"DE",
    "sg:address":"Bahnhofstr. 18-4",
    "sg:city":"Weinheim",
    "sg:phone":"+49 6201/85151",
    "sg:postcode":"69469",
    "sg:province":"Baden-W\u00fcrttemberg",
    "wof:name":"Reiseb\u00fcro Der Volksbank Weinheim",
    "wof:placetype":"venue"
},
  "geometry": {"coordinates":[8.669131279,49.5513191223],"type":"Point"}
}