{
  "type": "Feature",
  "properties": {
    "iso:country":"DE",
    "sg:address":"Dundeestr. 55",
    "sg:city":"W\u00fcrzburg",
    "sg:phone":"+49 931/67440",
    "sg:postcode":"97084",
    "sg:province":"Bayern",
    "wof:name":"Florian Leitl Architekt",
    "wof:placetype":"venue"
},
  "geometry": {"coordinates":[9.965111,49.739616],"type":"Point"}
}