{
  "type": "Feature",
  "properties": {
    "iso:country":"DE",
    "sg:address":"Kastanienweg 12",
    "sg:city":"Oberursel",
    "sg:phone":"+49 6171/3423",
    "sg:postcode":"61440",
    "sg:province":"Hessen",
    "wof:name":"Wilhelm Hoehler Taunus Drogerie",
    "wof:placetype":"venue"
},
  "geometry": {"coordinates":[8.556209,50.208904],"type":"Point"}
}