{
  "type": "Feature",
  "properties": {
    "iso:country":"DE",
    "sg:address":"Salower Str. 44",
    "sg:city":"Friedland",
    "sg:phone":"+49 39601/21546",
    "sg:postcode":"17098",
    "sg:province":"Mecklenburg-Vorpommern",
    "wof:name":"Mecklenburger Bierstuben Inh. Iris Steinke",
    "wof:placetype":"venue"
},
  "geometry": {"coordinates":[13.5429201126,53.6714744568],"type":"Point"}
}