{
  "type": "Feature",
  "properties": {
    "iso:country":"DE",
    "sg:address":"Holtenauer Str. 88",
    "sg:city":"Kiel",
    "sg:phone":"+49 431/563939",
    "sg:postcode":"24105",
    "sg:province":"Schleswig-Holstein",
    "wof:name":"Reformhaus Hintz Kg",
    "wof:placetype":"venue"
},
  "geometry": {"coordinates":[10.1334180832,54.3340682983],"type":"Point"}
}