{
  "type": "Feature",
  "properties": {
    "iso:country":"DE",
    "sg:address":"Max-Planck-Str 3",
    "sg:city":"Wurmlingen",
    "sg:phone":"+49 7461/164110",
    "sg:postcode":"78573",
    "sg:province":"Baden-W\u00fcrttemberg",
    "wof:name":"Fischer Gbr Engineering & Design",
    "wof:placetype":"venue"
},
  "geometry": {"coordinates":[8.7767772675,47.9989852905],"type":"Point"}
}