{
  "type": "Feature",
  "properties": {
    "iso:country":"DE",
    "sg:address":"Poststr. 1a",
    "sg:city":"Michendorf",
    "sg:phone":"+49 33205/44218",
    "sg:postcode":"14552",
    "sg:province":"Brandenburg",
    "wof:name":"Hauskrankenpflege Ewald",
    "wof:placetype":"venue"
},
  "geometry": {"coordinates":[13.028263,52.312908],"type":"Point"}
}