{
  "type": "Feature",
  "properties": {
    "iso:country":"DE",
    "sg:address":"Scharfenberger Str. 9",
    "sg:city":"Berlin",
    "sg:phone":"+49 30/4316914",
    "sg:postcode":"13505",
    "sg:province":"Berlin",
    "wof:name":"Makadonija-grill",
    "wof:placetype":"venue"
},
  "geometry": {"coordinates":[13.2344970703,52.5697059631],"type":"Point"}
}