{
  "type": "Feature",
  "properties": {
    "iso:country":"DE",
    "sg:address":"Holzstr. 31",
    "sg:city":"Lauf",
    "sg:phone":"+49 9123/5081",
    "sg:postcode":"91207",
    "sg:province":"Bayern",
    "wof:name":"Roth Teppich Gmbh",
    "wof:placetype":"venue"
},
  "geometry": {"coordinates":[11.2843475342,49.5165100098],"type":"Point"}
}