{
  "type": "Feature",
  "properties": {
    "iso:country":"DE",
    "sg:address":"C\u00fcppersweg 37",
    "sg:city":"Ratingen",
    "sg:phone":"+49 2102/842184",
    "sg:postcode":"40878",
    "sg:province":"Nordrhein-Westfalen",
    "wof:name":"K\u00e4ppler Beteiligungs Gmbh",
    "wof:placetype":"venue"
},
  "geometry": {"coordinates":[6.852842,51.286224],"type":"Point"}
}