{
  "type": "Feature",
  "properties": {
    "iso:country":"DE",
    "sg:address":"Hauptstr. 116",
    "sg:city":"M\u00f6lln",
    "sg:phone":"+49 4542/89016",
    "sg:postcode":"23879",
    "sg:province":"Schleswig-Holstein",
    "wof:name":"Modestoffe Renate Hemmers Gmbh",
    "wof:placetype":"venue"
},
  "geometry": {"coordinates":[10.691734,53.629589],"type":"Point"}
}