{
  "type": "Feature",
  "properties": {
    "iso:country":"DE",
    "sg:address":"Ortsstr. 38",
    "sg:city":"Marktg\u00f6litz",
    "sg:phone":"+49 36735/70061",
    "sg:postcode":"07330",
    "sg:province":"Th\u00fcringen",
    "wof:name":"Petra Seifert Masseurin",
    "wof:placetype":"venue"
},
  "geometry": {"coordinates":[11.335431,50.556335],"type":"Point"}
}