{
  "type": "Feature",
  "properties": {
    "iso:country":"DE",
    "sg:address":"Fockbeker Chaussee 60",
    "sg:city":"Rendsburg",
    "sg:phone":"+49 4331/7391",
    "sg:postcode":"24768",
    "sg:province":"Schleswig-Holstein",
    "wof:name":"Rieck Schornsteintechnik Und Bauunternehmung",
    "wof:placetype":"venue"
},
  "geometry": {"coordinates":[9.639661,54.308826],"type":"Point"}
}