{
  "type": "Feature",
  "properties": {
    "iso:country":"DE",
    "sg:address":"Babenend 27",
    "sg:city":"Oldenburg",
    "sg:phone":"+49 441/61095",
    "sg:postcode":"26127",
    "sg:province":"Niedersachsen",
    "wof:name":"Landkreis Anzeiger",
    "wof:placetype":"venue"
},
  "geometry": {"coordinates":[8.199286,53.159561],"type":"Point"}
}