{
  "type": "Feature",
  "properties": {
    "iso:country":"DE",
    "sg:address":"Gr\u00fcner Deich 27",
    "sg:city":"Hamburg",
    "sg:phone":"+49 40/231890",
    "sg:postcode":"20097",
    "sg:province":"Hamburg",
    "wof:name":"Gastst\u00e4tte R. Bartels",
    "wof:placetype":"venue"
},
  "geometry": {"coordinates":[10.0290231705,53.5426368713],"type":"Point"}
}