{
  "type": "Feature",
  "properties": {
    "iso:country":"DE",
    "sg:address":"Bibraer Landstr. 33",
    "sg:city":"Kahla",
    "sg:phone":"+49 36424/22821",
    "sg:postcode":"07768",
    "sg:province":"Th\u00fcringen",
    "wof:name":"Peter Lindner",
    "wof:placetype":"venue"
},
  "geometry": {"coordinates":[11.571346,50.802441],"type":"Point"}
}