{
  "type": "Feature",
  "properties": {
    "iso:country":"DE",
    "sg:address":"Lindenbergstr. 36",
    "sg:city":"Peine",
    "sg:phone":"+49 5171/51338",
    "sg:postcode":"31226",
    "sg:province":"Niedersachsen",
    "wof:name":"F. Ri\u00dfland Gmbh",
    "wof:placetype":"venue"
},
  "geometry": {"coordinates":[10.170962,52.305046],"type":"Point"}
}