{
  "type": "Feature",
  "properties": {
    "iso:country":"DE",
    "sg:address":"Heidestr. 8",
    "sg:city":"Meckenheim",
    "sg:phone":"+49 2225/912333",
    "sg:postcode":"53340",
    "sg:province":"Nordrhein-Westfalen",
    "wof:name":"Isolit Spritzgu\u00dftechnik Gmbh",
    "wof:placetype":"venue"
},
  "geometry": {"coordinates":[7.0214571953,50.647190094],"type":"Point"}
}