{
  "type": "Feature",
  "properties": {
    "iso:country":"DE",
    "sg:address":"Mauerstr. 6",
    "sg:city":"Dormagen",
    "sg:phone":"+49 2133/3709",
    "sg:postcode":"41541",
    "sg:province":"Nordrhein-Westfalen",
    "wof:name":"Alois Bauers Architekt",
    "wof:placetype":"venue"
},
  "geometry": {"coordinates":[6.850868,51.122307],"type":"Point"}
}