{
  "type": "Feature",
  "properties": {
    "iso:country":"DE",
    "sg:address":"Saarlandstr. 84",
    "sg:city":"Dortmund",
    "sg:phone":"+49 231/122722",
    "sg:postcode":"44139",
    "sg:province":"Nordrhein-Westfalen",
    "wof:name":"Der Blumenkorb",
    "wof:placetype":"venue"
},
  "geometry": {"coordinates":[7.464502,51.504807],"type":"Point"}
}