{
  "type": "Feature",
  "properties": {
    "iso:country":"DE",
    "sg:address":"Schillersheiderstr. 6",
    "sg:city":"Mettmann",
    "sg:phone":"+49 4921/0491870",
    "sg:postcode":"40822",
    "sg:province":"Nordrhein-Westfalen",
    "wof:name":"B\u00d6deker Gmbh",
    "wof:placetype":"venue"
},
  "geometry": {"coordinates":[6.9786329269,51.2515945435],"type":"Point"}
}