{
  "type": "Feature",
  "properties": {
    "iso:country":"DE",
    "sg:address":"Eichendorffstr. 62",
    "sg:city":"Eschweiler",
    "sg:phone":"+49 2403/4133",
    "sg:postcode":"52249",
    "sg:province":"Nordrhein-Westfalen",
    "wof:name":"P.-h. Mentzel",
    "wof:placetype":"venue"
},
  "geometry": {"coordinates":[6.2749409676,50.8200416565],"type":"Point"}
}