{
  "type": "Feature",
  "properties": {
    "iso:country":"DE",
    "sg:address":"Ahornstr. 9",
    "sg:city":"Gro\u00dfefehn",
    "sg:phone":"+49 4945/575",
    "sg:postcode":"26629",
    "sg:province":"Niedersachsen",
    "wof:name":"Heinrich St\u00f6ver Architekt",
    "wof:placetype":"venue"
},
  "geometry": {"coordinates":[7.517298,53.364731],"type":"Point"}
}