{
  "type": "Feature",
  "properties": {
    "iso:country":"DE",
    "sg:address":"Bahnhofstr. 18",
    "sg:city":"Langenfeld",
    "sg:phone":"+49 2173",
    "sg:postcode":"40764",
    "sg:province":"Nordrhein-Westfalen",
    "wof:name":"Cybertech Software",
    "wof:placetype":"venue"
},
  "geometry": {"coordinates":[6.943915,51.099361],"type":"Point"}
}