{
  "type": "Feature",
  "properties": {
    "iso:country":"DE",
    "sg:address":"Dr\u00fcpplingser Str. 41",
    "sg:city":"Iserlohn",
    "sg:phone":"+49 2378/913129",
    "sg:postcode":"58640",
    "sg:province":"Nordrhein-Westfalen",
    "wof:name":"Laden An Der Landstra\u00dfe Inhaberin Heidi G\u00f6rlitz",
    "wof:placetype":"venue"
},
  "geometry": {"coordinates":[7.6826601028,51.4519920349],"type":"Point"}
}