{
  "type": "Feature",
  "properties": {
    "iso:country":"DE",
    "sg:address":"Hermann-L\u00f6ns-Str. 2",
    "sg:city":"Riesa",
    "sg:postcode":"01589",
    "sg:province":"Sachsen",
    "wof:name":"Dieter Jeschke",
    "wof:placetype":"venue"
},
  "geometry": {"coordinates":[13.301255,51.300686],"type":"Point"}
}