{
  "type": "Feature",
  "properties": {
    "iso:country":"DE",
    "sg:address":"Johannes-Stau\u00df-Str. 1",
    "sg:city":"Winterlingen",
    "sg:phone":"+49 7434/8270",
    "sg:postcode":"72474",
    "sg:province":"Baden-W\u00fcrttemberg",
    "wof:name":"Seniorenhotel Onstmettingen Gmbh",
    "wof:placetype":"venue"
},
  "geometry": {"coordinates":[9.112235,48.190353],"type":"Point"}
}