{
  "type": "Feature",
  "properties": {
    "iso:country":"DE",
    "sg:address":"Blumenstr. 8",
    "sg:city":"Sennfeld",
    "sg:phone":"+49 9721/69197",
    "sg:postcode":"97526",
    "sg:province":"Bayern",
    "wof:name":"M\u00fcller",
    "wof:placetype":"venue"
},
  "geometry": {"coordinates":[10.256257,50.036064],"type":"Point"}
}