{
  "type": "Feature",
  "properties": {
    "iso:country":"DE",
    "sg:address":"Goethestr. 39",
    "sg:city":"Magdeburg",
    "sg:phone":"+49 391/7318306",
    "sg:postcode":"39108",
    "sg:province":"Sachsen-Anhalt",
    "wof:name":"Denker B\u00fcrgerbr\u00e4u",
    "wof:placetype":"venue"
},
  "geometry": {"coordinates":[11.6109476089,52.1330413818],"type":"Point"}
}