{
  "type": "Feature",
  "properties": {
    "iso:country":"DE",
    "sg:address":"Heidestr. 348",
    "sg:city":"Dessau",
    "sg:phone":"+49 340/8546482",
    "sg:postcode":"06849",
    "sg:province":"Sachsen-Anhalt",
    "wof:name":"Aral-tankstelle",
    "wof:placetype":"venue"
},
  "geometry": {"coordinates":[12.2400617599,51.7982902527],"type":"Point"}
}