{
  "type": "Feature",
  "properties": {
    "iso:country":"DE",
    "sg:address":"Buchenseestr. 16",
    "sg:city":"Radolfzell",
    "sg:phone":"+49 7732/910275",
    "sg:postcode":"78315",
    "sg:province":"Baden-W\u00fcrttemberg",
    "wof:name":"G. Hamann",
    "wof:placetype":"venue"
},
  "geometry": {"coordinates":[8.986392,47.770924],"type":"Point"}
}