{
  "type": "Feature",
  "properties": {
    "iso:country":"DE",
    "sg:address":"Adelbergweg 2",
    "sg:city":"We\u00dfling",
    "sg:phone":"+49 8153/4348",
    "sg:postcode":"82234",
    "sg:province":"Bayern",
    "wof:name":"Andreas Weber Architekt",
    "wof:placetype":"venue"
},
  "geometry": {"coordinates":[11.258072,48.074211],"type":"Point"}
}