{
  "type": "Feature",
  "properties": {
    "iso:country":"DE",
    "sg:address":"An der Kreuzwiese 20",
    "sg:city":"Lorsch",
    "sg:phone":"+49 6251/595861",
    "sg:postcode":"64653",
    "sg:province":"Hessen",
    "wof:name":"Angelika Reiter",
    "wof:placetype":"venue"
},
  "geometry": {"coordinates":[8.5738801956,49.6528816223],"type":"Point"}
}