{
  "type": "Feature",
  "properties": {
    "iso:country":"DE",
    "sg:address":"Industriestr. 7",
    "sg:city":"Z\u00fclpich",
    "sg:postcode":"53909",
    "sg:province":"Nordrhein-Westfalen",
    "wof:name":"Pisa Baubetreuungs- Und Objektgesellschaft Mbh",
    "wof:placetype":"venue"
},
  "geometry": {"coordinates":[6.664595,50.701042],"type":"Point"}
}