{
  "type": "Feature",
  "properties": {
    "iso:country":"DE",
    "sg:address":"Alpgaustr 24",
    "sg:city":"Oberstdorf",
    "sg:phone":"+49 8322/97920",
    "sg:postcode":"87561",
    "sg:province":"Bayern",
    "wof:name":"Micks Me\u00df-, Steuer- Und Regelsysteme Gmbh",
    "wof:placetype":"venue"
},
  "geometry": {"coordinates":[10.276338,47.417057],"type":"Point"}
}