{
  "type": "Feature",
  "properties": {
    "iso:country":"DE",
    "sg:address":"Norderholm 38",
    "sg:city":"Gelting",
    "sg:phone":"+49 4643/183400",
    "sg:postcode":"24395",
    "sg:province":"Schleswig-Holstein",
    "wof:name":"B\u00fccherei D\u00f6rfergemeinschaftsschule",
    "wof:placetype":"venue"
},
  "geometry": {"coordinates":[9.899321,54.751003],"type":"Point"}
}