{
  "type": "Feature",
  "properties": {
    "iso:country":"DE",
    "sg:address":"Kalliwodastr. 3",
    "sg:city":"Karlsruhe",
    "sg:phone":"+49 721/597160",
    "sg:postcode":"76185",
    "sg:province":"Baden-W\u00fcrttemberg",
    "wof:name":"Synnecta Gmbh",
    "wof:placetype":"venue"
},
  "geometry": {"coordinates":[8.3667392731,49.0132865906],"type":"Point"}
}