{
  "type": "Feature",
  "properties": {
    "iso:country":"DE",
    "sg:address":"Posseltstr. 9",
    "sg:city":"Heidelberg",
    "sg:phone":"+49 6221/452294",
    "sg:postcode":"69120",
    "sg:province":"Baden-W\u00fcrttemberg",
    "wof:name":"V.o.x. Musikservice Gmbh",
    "wof:placetype":"venue"
},
  "geometry": {"coordinates":[8.6795339584,49.4125137329],"type":"Point"}
}