{
  "type": "Feature",
  "properties": {
    "iso:country":"DE",
    "sg:address":"Ernst-Moritz-Engert-Str. 5",
    "sg:city":"Hadamar",
    "sg:phone":"+49 6433/1425",
    "sg:postcode":"65589",
    "sg:province":"Hessen",
    "wof:name":"Eberhard Achenbach Ingenieur",
    "wof:placetype":"venue"
},
  "geometry": {"coordinates":[8.0504322052,50.450553894],"type":"Point"}
}