{
  "type": "Feature",
  "properties": {
    "iso:country":"DE",
    "sg:address":"Ansbacher Str. 44",
    "sg:city":"Gro\u00dfhabersdorf",
    "sg:phone":"+49 9105/990643",
    "sg:postcode":"90613",
    "sg:province":"Bayern",
    "wof:name":"A. Behringer",
    "wof:placetype":"venue"
},
  "geometry": {"coordinates":[10.7863998413,49.4006080627],"type":"Point"}
}