{
  "type": "Feature",
  "properties": {
    "iso:country":"DE",
    "sg:address":"Beethovenstr. 22",
    "sg:city":"Freiberg",
    "sg:phone":"+49 7141/271254",
    "sg:postcode":"71691",
    "sg:province":"Baden-W\u00fcrttemberg",
    "wof:name":"Br\u00f6samle Hausverwaltung Gmbh",
    "wof:placetype":"venue"
},
  "geometry": {"coordinates":[9.1806240082,48.9391403198],"type":"Point"}
}