{
  "type": "Feature",
  "properties": {
    "iso:country":"DE",
    "sg:address":"Bahnhofstr. 12",
    "sg:city":"Rathenow",
    "sg:phone":"+49 3385/511050",
    "sg:postcode":"14712",
    "sg:province":"Brandenburg",
    "wof:name":"A. Kage",
    "wof:placetype":"venue"
},
  "geometry": {"coordinates":[12.351392746,52.6005897522],"type":"Point"}
}