{
  "type": "Feature",
  "properties": {
    "iso:country":"DE",
    "sg:address":"Daimlerstr. 5",
    "sg:city":"Aurich",
    "sg:phone":"+49 4941/4343",
    "sg:postcode":"26607",
    "sg:province":"Niedersachsen",
    "wof:name":"Jedopane Isolierglas Gmbh",
    "wof:placetype":"venue"
},
  "geometry": {"coordinates":[7.4911179543,53.5040397644],"type":"Point"}
}