{
  "type": "Feature",
  "properties": {
    "iso:country":"DE",
    "sg:address":"Stra\u00dfe der Einheit 22",
    "sg:city":"Radegast",
    "sg:phone":"+49 34978/22754",
    "sg:postcode":"06369",
    "sg:province":"Sachsen-Anhalt",
    "wof:name":"D. Roth",
    "wof:placetype":"venue"
},
  "geometry": {"coordinates":[12.103243,51.6581],"type":"Point"}
}