{
  "type": "Feature",
  "properties": {
    "iso:country":"DE",
    "sg:address":"Limesstr. 5",
    "sg:city":"Michelstadt",
    "sg:phone":"+49 6066/271",
    "sg:postcode":"64720",
    "sg:province":"Hessen",
    "wof:name":"Hotel-pension Weyrich",
    "wof:placetype":"venue"
},
  "geometry": {"coordinates":[9.098593,49.711559],"type":"Point"}
}