{
  "type": "Feature",
  "properties": {
    "iso:country":"DE",
    "sg:address":"In der Schaf 7",
    "sg:city":"Baesweiler",
    "sg:phone":"+49 2401/2167",
    "sg:postcode":"52499",
    "sg:province":"Nordrhein-Westfalen",
    "wof:name":"Dresdner Bank",
    "wof:placetype":"venue"
},
  "geometry": {"coordinates":[6.185585,50.904949],"type":"Point"}
}