{
  "type": "Feature",
  "properties": {
    "iso:country":"DE",
    "sg:address":"Bahnhofstr. 4b",
    "sg:city":"Bad D\u00fcrrheim",
    "sg:phone":"+49 7726/7344",
    "sg:postcode":"78073",
    "sg:province":"Baden-W\u00fcrttemberg",
    "wof:name":"Cortina",
    "wof:placetype":"venue"
},
  "geometry": {"coordinates":[8.530647,48.019093],"type":"Point"}
}