{
  "type": "Feature",
  "properties": {
    "iso:country":"DE",
    "sg:address":"Maiwaldstr 24",
    "sg:city":"Rheinau",
    "sg:phone":"+49 7844/98641",
    "sg:postcode":"77866",
    "sg:province":"Baden-W\u00fcrttemberg",
    "wof:name":"Ing. B\u00fcro Hta-software",
    "wof:placetype":"venue"
},
  "geometry": {"coordinates":[7.943345,48.66254],"type":"Point"}
}