{
  "type": "Feature",
  "properties": {
    "iso:country":"DE",
    "sg:address":"Frauenbr\u00fcnnlstr. 2",
    "sg:city":"Straubing",
    "sg:phone":"+49 9421/23059",
    "sg:postcode":"94315",
    "sg:province":"Bayern",
    "wof:name":"Volksf\u00fcrsorge Deutsche Lebensversicherung Ag",
    "wof:placetype":"venue"
},
  "geometry": {"coordinates":[12.56432,48.881088],"type":"Point"}
}