{
  "type": "Feature",
  "properties": {
    "iso:country":"DE",
    "sg:address":"Vor S\u00f6hlers Hause 12",
    "sg:city":"Wagenfeld",
    "sg:phone":"+49 5444/1343",
    "sg:postcode":"49419",
    "sg:province":"Niedersachsen",
    "wof:name":"Georg Bukowski",
    "wof:placetype":"venue"
},
  "geometry": {"coordinates":[8.616509,52.565514],"type":"Point"}
}