{
  "type": "Feature",
  "properties": {
    "iso:country":"DE",
    "sg:address":"Kreuznaaf 24",
    "sg:city":"Lohmar",
    "sg:phone":"+49 2246/912056",
    "sg:postcode":"53797",
    "sg:province":"Nordrhein-Westfalen",
    "wof:name":"Modern Nature Piercing Schmuck",
    "wof:placetype":"venue"
},
  "geometry": {"coordinates":[7.2491841316,50.86510849],"type":"Point"}
}