{
  "type": "Feature",
  "properties": {
    "iso:country":"DE",
    "sg:address":"Kasseler Str. 5",
    "sg:city":"Lahntal",
    "sg:phone":"+49 6423/7391",
    "sg:postcode":"35094",
    "sg:province":"Hessen",
    "wof:name":"Jakob Reinhard",
    "wof:placetype":"venue"
},
  "geometry": {"coordinates":[8.7056932449,50.8624839783],"type":"Point"}
}