{
  "type": "Feature",
  "properties": {
    "iso:country":"DE",
    "sg:address":"Weinbergstr. 36",
    "sg:city":"Potsdam",
    "sg:postcode":"14469",
    "sg:province":"Brandenburg",
    "wof:name":"Jgs Rechtsanwaltsges. Mbh",
    "wof:placetype":"venue"
},
  "geometry": {"coordinates":[13.0503063202,52.4042015076],"type":"Point"}
}