{
  "type": "Feature",
  "properties": {
    "iso:country":"DE",
    "sg:address":"Eisenbahnstr. 14",
    "sg:city":"Ihringen",
    "sg:phone":"+49 7668/5881",
    "sg:postcode":"79241",
    "sg:province":"Baden-W\u00fcrttemberg",
    "wof:name":"O. Bury Inh. G. Bury",
    "wof:placetype":"venue"
},
  "geometry": {"coordinates":[7.647405,48.04203],"type":"Point"}
}