{
  "type": "Feature",
  "properties": {
    "iso:country":"DE",
    "sg:address":"Am Hanach 13",
    "sg:city":"Eltville",
    "sg:postcode":"65343",
    "sg:province":"Hessen",
    "wof:name":"Josef Michel Inh. Andreas Michel",
    "wof:placetype":"venue"
},
  "geometry": {"coordinates":[8.121599,50.030987],"type":"Point"}
}