{
  "type": "Feature",
  "properties": {
    "iso:country":"DE",
    "sg:address":"Rohrbacher Str. 124",
    "sg:city":"Heidelberg",
    "sg:postcode":"69126",
    "sg:province":"Baden-W\u00fcrttemberg",
    "wof:name":"K. E. Grundst\u00fcckshandel Und Grundst\u00fccksverwaltung",
    "wof:placetype":"venue"
},
  "geometry": {"coordinates":[8.6898145676,49.3940811157],"type":"Point"}
}