{
  "type": "Feature",
  "properties": {
    "iso:country":"DE",
    "sg:address":"Barkhausenstr. 24",
    "sg:city":"Langeoog",
    "sg:phone":"+49 4972/91000",
    "sg:postcode":"26465",
    "sg:province":"Niedersachsen",
    "wof:name":"Uecker Immobilienmakler",
    "wof:placetype":"venue"
},
  "geometry": {"coordinates":[7.4819860458,53.7491188049],"type":"Point"}
}