{
  "type": "Feature",
  "properties": {
    "iso:country":"DE",
    "sg:address":"Hallerweg 2",
    "sg:city":"K\u00fcmmersbruck",
    "sg:postcode":"92245",
    "sg:province":"Bayern",
    "wof:name":"Wolfgang Und Rita Graf Gmbh",
    "wof:placetype":"venue"
},
  "geometry": {"coordinates":[11.897889,49.433674],"type":"Point"}
}