{
  "type": "Feature",
  "properties": {
    "iso:country":"DE",
    "sg:address":"Kurf\u00fcrstendamm 220",
    "sg:city":"Berlin",
    "sg:phone":"+49 30/8859270",
    "sg:postcode":"10719",
    "sg:province":"Berlin",
    "wof:name":"Rechtsanw\u00e4lte Kurtze",
    "wof:placetype":"venue"
},
  "geometry": {"coordinates":[13.3285188675,52.5029716492],"type":"Point"}
}