{
  "type": "Feature",
  "properties": {
    "iso:country":"DE",
    "sg:address":"Grabsteder Str. 45",
    "sg:city":"Bockhorn",
    "sg:phone":"+49 4453/71154",
    "sg:postcode":"26345",
    "sg:province":"Niedersachsen",
    "wof:name":"Mw Erdbau Gmbh",
    "wof:placetype":"venue"
},
  "geometry": {"coordinates":[8.0026760101,53.3791122437],"type":"Point"}
}