{
  "type": "Feature",
  "properties": {
    "iso:country":"DE",
    "sg:address":"Kasernenstr. 7",
    "sg:city":"Oldenburg",
    "sg:phone":"+49 441/33737",
    "sg:postcode":"26123",
    "sg:province":"Niedersachsen",
    "wof:name":"Karl Stolze",
    "wof:placetype":"venue"
},
  "geometry": {"coordinates":[8.2223901749,53.1497268677],"type":"Point"}
}