{
  "type": "Feature",
  "properties": {
    "iso:country":"DE",
    "sg:address":"Middendorffstr. 2",
    "sg:city":"Bad Blankenburg",
    "sg:phone":"+49 36741/40031",
    "sg:postcode":"07422",
    "sg:province":"Th\u00fcringen",
    "wof:name":"K\u00f6nig-design",
    "wof:placetype":"venue"
},
  "geometry": {"coordinates":[11.270396,50.681721],"type":"Point"}
}