{
  "type": "Feature",
  "properties": {
    "iso:country":"DE",
    "sg:address":"Schlesische Str. 36",
    "sg:city":"Neutraubling",
    "sg:phone":"+49 9401/3323",
    "sg:postcode":"93073",
    "sg:province":"Bayern",
    "wof:name":"Ottmann Gmbh & Co. S\u00fcdhausbau Kg",
    "wof:placetype":"venue"
},
  "geometry": {"coordinates":[12.196464,48.991184],"type":"Point"}
}