{
  "type": "Feature",
  "properties": {
    "iso:country":"DE",
    "sg:address":"Kurf\u00fcrstenstr. 5",
    "sg:city":"M\u00fcnchen",
    "sg:phone":"+49 89/2711611",
    "sg:postcode":"80799",
    "sg:province":"Bayern",
    "wof:name":"Herbert Steindl Steuerberater",
    "wof:placetype":"venue"
},
  "geometry": {"coordinates":[11.5761871338,48.1534919739],"type":"Point"}
}