{
  "type": "Feature",
  "properties": {
    "iso:country":"DE",
    "sg:address":"Bismarckstr. 33",
    "sg:city":"Trossingen",
    "sg:phone":"+49 7425/7524",
    "sg:postcode":"78647",
    "sg:province":"Baden-W\u00fcrttemberg",
    "wof:name":"B. Und R. Messner",
    "wof:placetype":"venue"
},
  "geometry": {"coordinates":[8.6402750015,48.0796737671],"type":"Point"}
}