{
  "type": "Feature",
  "properties": {
    "iso:country":"DE",
    "sg:address":"J\u00f6rnstr. 17",
    "sg:city":"Bad Zwischenahn",
    "sg:phone":"+49 4403/8430",
    "sg:postcode":"26160",
    "sg:province":"Niedersachsen",
    "wof:name":"Manfred Hohnholz",
    "wof:placetype":"venue"
},
  "geometry": {"coordinates":[8.054093,53.210098],"type":"Point"}
}