{
  "type": "Feature",
  "properties": {
    "iso:country":"DE",
    "sg:address":"Judengasse 1",
    "sg:city":"Hachenburg",
    "sg:phone":"+49 2662/6616",
    "sg:postcode":"57627",
    "sg:province":"Rheinland-Pfalz",
    "wof:name":"G. Peters Und M. Hahn",
    "wof:placetype":"venue"
},
  "geometry": {"coordinates":[7.823285,50.660763],"type":"Point"}
}