{
  "type": "Feature",
  "properties": {
    "iso:country":"DE",
    "sg:address":"Am Heineb\u00fchl 3",
    "sg:city":"Zell",
    "sg:phone":"+49 7625/639",
    "sg:postcode":"79669",
    "sg:province":"Baden-W\u00fcrttemberg",
    "wof:name":"Anneliese Geiger",
    "wof:placetype":"venue"
},
  "geometry": {"coordinates":[7.8648638725,47.7164001465],"type":"Point"}
}