{
  "type": "Feature",
  "properties": {
    "iso:country":"DE",
    "sg:address":"Esterbergstr. 38",
    "sg:city":"Starnberg",
    "sg:phone":"+49 8151/3241",
    "sg:postcode":"82319",
    "sg:province":"Bayern",
    "wof:name":"Reinhard Fischer Ingenieur",
    "wof:placetype":"venue"
},
  "geometry": {"coordinates":[11.323554039,48.0105438232],"type":"Point"}
}