{
  "type": "Feature",
  "properties": {
    "iso:country":"DE",
    "sg:address":"Schweiggerstrasse 29",
    "sg:city":"N\u00fcrnberg",
    "sg:phone":"+49 911/457553",
    "sg:postcode":"90478",
    "sg:province":"Bayern",
    "wof:name":"Antiquariat Gerhard Paul",
    "wof:placetype":"venue"
},
  "geometry": {"coordinates":[11.0926971436,49.4425582886],"type":"Point"}
}