{
  "type": "Feature",
  "properties": {
    "iso:country":"DE",
    "sg:address":"Hauptstr. 13",
    "sg:city":"Zarrentin",
    "sg:phone":"+49 38851/8580",
    "sg:postcode":"19246",
    "sg:province":"Mecklenburg-Vorpommern",
    "wof:name":"Cafe Wohler",
    "wof:placetype":"venue"
},
  "geometry": {"coordinates":[10.9160881042,53.5513954163],"type":"Point"}
}