{
  "type": "Feature",
  "properties": {
    "iso:country":"DE",
    "sg:address":"Fritz-Frey-Str. 21",
    "sg:city":"Heidelberg",
    "sg:phone":"+49 6221/40620",
    "sg:postcode":"69121",
    "sg:province":"Baden-W\u00fcrttemberg",
    "wof:name":"Arkana-verlag Friedrich Haug",
    "wof:placetype":"venue"
},
  "geometry": {"coordinates":[8.6795244217,49.4373054504],"type":"Point"}
}