{
  "type": "Feature",
  "properties": {
    "iso:country":"DE",
    "sg:address":"Messmannstr. 11",
    "sg:city":"Papenburg",
    "sg:postcode":"26871",
    "sg:province":"Niedersachsen",
    "wof:name":"Rs Shipping Engineering And Consulting Gmbh",
    "wof:placetype":"venue"
},
  "geometry": {"coordinates":[7.3940520287,53.0717735291],"type":"Point"}
}