{
  "type": "Feature",
  "properties": {
    "iso:country":"DE",
    "sg:address":"Lindenplatz 2a",
    "sg:city":"Neuenstadt",
    "sg:phone":"+49 7139/18352",
    "sg:postcode":"74196",
    "sg:province":"Baden-W\u00fcrttemberg",
    "wof:name":"Der Ofenschlupfer",
    "wof:placetype":"venue"
},
  "geometry": {"coordinates":[9.3311758041,49.236743927],"type":"Point"}
}