{
  "type": "Feature",
  "properties": {
    "iso:country":"DE",
    "sg:address":"Friedrich-Engels-Allee 32",
    "sg:city":"Wuppertal",
    "sg:phone":"+49 202/493740",
    "sg:postcode":"42103",
    "sg:province":"Nordrhein-Westfalen",
    "wof:name":"Gerhard Frische Rechtsanwalt Und Steuerberater",
    "wof:placetype":"venue"
},
  "geometry": {"coordinates":[7.1624398232,51.2564582825],"type":"Point"}
}