{
  "type": "Feature",
  "properties": {
    "iso:country":"DE",
    "sg:address":"Hanauer Landstr. 14",
    "sg:city":"Hanau",
    "sg:phone":"+49 6181/573382",
    "sg:postcode":"63457",
    "sg:province":"Hessen",
    "wof:name":"K\u00e4stner Trike Shop",
    "wof:placetype":"venue"
},
  "geometry": {"coordinates":[8.939189,50.108898],"type":"Point"}
}