{
  "type": "Feature",
  "properties": {
    "iso:country":"DE",
    "sg:address":"Goltzstr. 14",
    "sg:city":"Berlin",
    "sg:phone":"+49 30/2173890",
    "sg:postcode":"10781",
    "sg:province":"Berlin",
    "wof:name":"Neue Reisewelle Reiseladen Goltzstra\u00dfe Gmbh",
    "wof:placetype":"venue"
},
  "geometry": {"coordinates":[13.3536977768,52.4927024841],"type":"Point"}
}