{
  "type": "Feature",
  "properties": {
    "iso:country":"DE",
    "sg:address":"Bahnhofstr. 20",
    "sg:city":"Westerhorn",
    "sg:phone":"+49 4127/333",
    "sg:postcode":"25364",
    "sg:province":"Schleswig-Holstein",
    "wof:name":"Paninkret Chemisch-pharma- Zeutisches Werk Gmbh",
    "wof:placetype":"venue"
},
  "geometry": {"coordinates":[9.6812906265,53.8523406982],"type":"Point"}
}