{
  "type": "Feature",
  "properties": {
    "iso:country":"DE",
    "sg:address":"Wendelsteinstr. 12",
    "sg:city":"Sindelfingen",
    "sg:phone":"+49 7031/803753",
    "sg:postcode":"71067",
    "sg:province":"Baden-W\u00fcrttemberg",
    "wof:name":"Gerhard Br\u00fcgel Patentanwalt",
    "wof:placetype":"venue"
},
  "geometry": {"coordinates":[9.0043754578,48.7291603088],"type":"Point"}
}