{
  "type": "Feature",
  "properties": {
    "iso:country":"DE",
    "sg:address":"Engelswisch 12",
    "sg:city":"L\u00fcbeck",
    "sg:phone":"+49 451/791155",
    "sg:postcode":"23552",
    "sg:province":"Schleswig-Holstein",
    "wof:name":"Dirce Bau Gmbh",
    "wof:placetype":"venue"
},
  "geometry": {"coordinates":[10.6873464584,53.8731765747],"type":"Point"}
}