{
  "type": "Feature",
  "properties": {
    "iso:country":"DE",
    "sg:address":"Harrierwurp 22",
    "sg:city":"Brake",
    "sg:phone":"+49 4401/7435",
    "sg:postcode":"26919",
    "sg:province":"Niedersachsen",
    "wof:name":"Georg Haye",
    "wof:placetype":"venue"
},
  "geometry": {"coordinates":[8.443636,53.313423],"type":"Point"}
}