{
  "type": "Feature",
  "properties": {
    "iso:country":"DE",
    "sg:address":"Heinrich-Mack-Str. 4",
    "sg:city":"Braunschweig",
    "sg:phone":"+49 531/16504",
    "sg:postcode":"38118",
    "sg:province":"Niedersachsen",
    "wof:name":"Hauswaldtsche Familienstiftung Vom Jahre 1889",
    "wof:placetype":"venue"
},
  "geometry": {"coordinates":[10.511475563,52.2603416443],"type":"Point"}
}