{
  "type": "Feature",
  "properties": {
    "iso:country":"DE",
    "sg:address":"Dewitzer Str. 61c",
    "sg:city":"Taucha",
    "sg:postcode":"04425",
    "sg:province":"Sachsen",
    "wof:name":"Werfag Erfassungs Gmbh",
    "wof:placetype":"venue"
},
  "geometry": {"coordinates":[12.50801,51.382221],"type":"Point"}
}