{
  "type": "Feature",
  "properties": {
    "iso:country":"DE",
    "sg:address":"Rott 16",
    "sg:city":"Langenhorn",
    "sg:phone":"+49 4672/1085",
    "sg:postcode":"25842",
    "sg:province":"Schleswig-Holstein",
    "wof:name":"Data-services Gmbh",
    "wof:placetype":"venue"
},
  "geometry": {"coordinates":[8.898016,54.667488],"type":"Point"}
}