{
  "type": "Feature",
  "properties": {
    "iso:country":"DE",
    "sg:city":"Wilkau-Ha\u00dflau",
    "sg:postcode":"08112",
    "sg:province":"Sachsen",
    "wof:name":"Ost-west-management Gmbh",
    "wof:placetype":"venue"
},
  "geometry": {"coordinates":[12.512482,50.674835],"type":"Point"}
}