{
  "type": "Feature",
  "properties": {
    "iso:country":"DE",
    "sg:address":"Eichenallee 16",
    "sg:city":"Berlin",
    "sg:phone":"+49 30/3022302",
    "sg:postcode":"14050",
    "sg:province":"Berlin",
    "wof:name":"Bernd Pierburg Rechtsanwalt",
    "wof:placetype":"venue"
},
  "geometry": {"coordinates":[13.2726240158,52.5157165527],"type":"Point"}
}