{
  "type": "Feature",
  "properties": {
    "iso:country":"DE",
    "sg:address":"Altenburger Str. 6",
    "sg:city":"J\u00fclich",
    "sg:phone":"+49 2461/58981",
    "sg:postcode":"52428",
    "sg:province":"Nordrhein-Westfalen",
    "wof:name":"Em Kappelchen",
    "wof:placetype":"venue"
},
  "geometry": {"coordinates":[6.4084482193,50.8875160217],"type":"Point"}
}