{
  "type": "Feature",
  "properties": {
    "iso:country":"DE",
    "sg:address":"Mittelstr. 6",
    "sg:city":"Extertal",
    "sg:phone":"+49 5262/2143",
    "sg:postcode":"32699",
    "sg:province":"Nordrhein-Westfalen",
    "wof:name":"B\u00e4ckerei-konditorei Dreimann Gmbh",
    "wof:placetype":"venue"
},
  "geometry": {"coordinates":[9.123832,52.068485],"type":"Point"}
}