{
  "type": "Feature",
  "properties": {
    "iso:country":"DE",
    "sg:address":"Zimmerstr. 9",
    "sg:city":"Hamburg",
    "sg:phone":"+49 40/225306",
    "sg:postcode":"22085",
    "sg:province":"Hamburg",
    "wof:name":"P. Tscharntke Immobilienmakler",
    "wof:placetype":"venue"
},
  "geometry": {"coordinates":[10.0161333084,53.574886322],"type":"Point"}
}