{
  "type": "Feature",
  "properties": {
    "iso:country":"DE",
    "sg:address":"Bernauer Str. 92",
    "sg:city":"Oranienburg",
    "sg:phone":"+49 3334/212418",
    "sg:postcode":"16515",
    "sg:province":"Brandenburg",
    "wof:name":"I. M\u00fcller",
    "wof:placetype":"venue"
},
  "geometry": {"coordinates":[13.2515001297,52.7579116821],"type":"Point"}
}