{
  "type": "Feature",
  "properties": {
    "iso:country":"DE",
    "sg:address":"Erkelenzer Str. 50",
    "sg:city":"H\u00fcckelhoven",
    "sg:phone":"+49 2433/2446",
    "sg:postcode":"41836",
    "sg:province":"Nordrhein-Westfalen",
    "wof:name":"Reiner Jennessen",
    "wof:placetype":"venue"
},
  "geometry": {"coordinates":[6.2262420654,51.0786590576],"type":"Point"}
}