{
  "type": "Feature",
  "properties": {
    "iso:country":"DE",
    "sg:address":"In den Gr\u00e4ben 12",
    "sg:city":"Neuberg",
    "sg:phone":"+49 6183/72543",
    "sg:postcode":"63543",
    "sg:province":"Hessen",
    "wof:name":"Thomas Herrmann",
    "wof:placetype":"venue"
},
  "geometry": {"coordinates":[8.993627,50.187412],"type":"Point"}
}