{
  "type": "Feature",
  "properties": {
    "iso:country":"DE",
    "sg:address":"Freiherr-vom-Stein-Str. 7",
    "sg:city":"Rimbach",
    "sg:phone":"+49 6253/972197",
    "sg:postcode":"64668",
    "sg:province":"Hessen",
    "wof:name":"Intess Electronic Gmbh",
    "wof:placetype":"venue"
},
  "geometry": {"coordinates":[8.7531995773,49.6252593994],"type":"Point"}
}