{
  "type": "Feature",
  "properties": {
    "iso:country":"DE",
    "sg:address":"M\u00fchlenstr 26",
    "sg:city":"Erkelenz",
    "sg:phone":"+49 2431/71302",
    "sg:postcode":"41812",
    "sg:province":"Nordrhein-Westfalen",
    "wof:name":"Techniweld Gmbh",
    "wof:placetype":"venue"
},
  "geometry": {"coordinates":[6.3243918419,51.0795211792],"type":"Point"}
}