{
  "type": "Feature",
  "properties": {
    "iso:country":"DE",
    "sg:address":"Hauptstr. 197",
    "sg:city":"Adenau",
    "sg:phone":"+49 2691/2253",
    "sg:postcode":"53518",
    "sg:province":"Rheinland-Pfalz",
    "wof:name":"Norbert L\u00f6hndorf",
    "wof:placetype":"venue"
},
  "geometry": {"coordinates":[6.9374709129,50.3818893433],"type":"Point"}
}