{
  "type": "Feature",
  "properties": {
    "iso:country":"DE",
    "sg:address":"Emmrich-Joseph-Str. 11",
    "sg:city":"Worms",
    "sg:phone":"+49 6241/51038",
    "sg:postcode":"67550",
    "sg:province":"Rheinland-Pfalz",
    "wof:name":"Weineinkauf-schlo\u00dfkellerei Weingut Adam Hemer",
    "wof:placetype":"venue"
},
  "geometry": {"coordinates":[8.3283586502,49.6588249207],"type":"Point"}
}