{
  "type": "Feature",
  "properties": {
    "iso:country":"DE",
    "sg:address":"Jahnstr. 31",
    "sg:city":"Zirndorf",
    "sg:phone":"+49 911/606748",
    "sg:postcode":"90513",
    "sg:province":"Bayern",
    "wof:name":"Klaus Wienhausen",
    "wof:placetype":"venue"
},
  "geometry": {"coordinates":[10.9697237015,49.4422798157],"type":"Point"}
}