{
  "type": "Feature",
  "properties": {
    "iso:country":"DE",
    "sg:address":"Marktplatz 18",
    "sg:city":"Krumbach",
    "sg:phone":"+49 8282/827807",
    "sg:postcode":"86381",
    "sg:province":"Bayern",
    "wof:name":"Brasserie Rossini",
    "wof:placetype":"venue"
},
  "geometry": {"coordinates":[10.3624744415,48.2428703308],"type":"Point"}
}