{
  "type": "Feature",
  "properties": {
    "iso:country":"DE",
    "sg:address":"Am Verkehrskreuz 9",
    "sg:city":"Wiehl",
    "sg:phone":"+49 2261/73033",
    "sg:postcode":"51674",
    "sg:province":"Nordrhein-Westfalen",
    "wof:name":"F. Kraus",
    "wof:placetype":"venue"
},
  "geometry": {"coordinates":[7.525938,50.968487],"type":"Point"}
}