{
  "type": "Feature",
  "properties": {
    "iso:country":"DE",
    "sg:address":"Weststr. 99",
    "sg:city":"Chemnitz",
    "sg:phone":"+49 371/319200",
    "sg:postcode":"09116",
    "sg:province":"Sachsen",
    "wof:name":"Ulrike Both-wunder",
    "wof:placetype":"venue"
},
  "geometry": {"coordinates":[12.8917703629,50.8306388855],"type":"Point"}
}