{
  "type": "Feature",
  "properties": {
    "iso:country":"DE",
    "sg:address":"St.-Georg-Str. 14",
    "sg:city":"F\u00fcrstenau",
    "sg:phone":"+49 5901/1300",
    "sg:postcode":"49584",
    "sg:province":"Niedersachsen",
    "wof:name":"H. Lichtenberg",
    "wof:placetype":"venue"
},
  "geometry": {"coordinates":[7.6765451431,52.5177192688],"type":"Point"}
}