{
  "type": "Feature",
  "properties": {
    "iso:country":"DE",
    "sg:address":"Wettergasse 40",
    "sg:city":"Marburg",
    "sg:phone":"+49 6421/67124",
    "sg:postcode":"35037",
    "sg:province":"Hessen",
    "wof:name":"Bi-moden",
    "wof:placetype":"venue"
},
  "geometry": {"coordinates":[8.770735,50.810734],"type":"Point"}
}