{
  "type": "Feature",
  "properties": {
    "iso:country":"DE",
    "sg:address":"Neuer Garten 2",
    "sg:city":"Preu\u00dfisch Oldendorf",
    "sg:phone":"+49 5742/3265",
    "sg:postcode":"32361",
    "sg:province":"Nordrhein-Westfalen",
    "wof:name":"Beos Kommunikations- Elektronik Gmbh",
    "wof:placetype":"venue"
},
  "geometry": {"coordinates":[8.4937400818,52.3383865356],"type":"Point"}
}