{
  "type": "Feature",
  "properties": {
    "iso:country":"DE",
    "sg:address":"R\u00f6ther Gasse 25",
    "sg:city":"Gelnhausen",
    "sg:phone":"+49 6051/2081",
    "sg:postcode":"63571",
    "sg:province":"Hessen",
    "wof:name":"Michael Seidel",
    "wof:placetype":"venue"
},
  "geometry": {"coordinates":[9.1867132187,50.2031211853],"type":"Point"}
}