{
  "type": "Feature",
  "properties": {
    "iso:country":"DE",
    "sg:address":"Auguststra\u00dfe 14",
    "sg:city":"Braunschweig",
    "sg:phone":"+49 531/400666",
    "sg:postcode":"38100",
    "sg:province":"Niedersachsen",
    "wof:name":"Plate-international",
    "wof:placetype":"venue"
},
  "geometry": {"coordinates":[10.5278120041,52.2588806152],"type":"Point"}
}