{
  "type": "Feature",
  "properties": {
    "iso:country":"DE",
    "sg:address":"Gladbacher Str. 9",
    "sg:city":"Krefeld",
    "sg:phone":"+49 2151/393425",
    "sg:postcode":"47798",
    "sg:province":"Nordrhein-Westfalen",
    "wof:name":"V. Kovacevic",
    "wof:placetype":"venue"
},
  "geometry": {"coordinates":[6.5658750534,51.3262367249],"type":"Point"}
}