{
  "type": "Feature",
  "properties": {
    "iso:country":"DE",
    "sg:address":"Hauptstr. 35",
    "sg:city":"Altenmarkt",
    "sg:phone":"+49 8621/3222",
    "sg:postcode":"83352",
    "sg:province":"Bayern",
    "wof:name":"Ristorante-pizzeria Molise",
    "wof:placetype":"venue"
},
  "geometry": {"coordinates":[12.5357179642,48.0034370422],"type":"Point"}
}