{
  "type": "Feature",
  "properties": {
    "iso:country":"DE",
    "sg:address":"Hauptstrasse 5",
    "sg:city":"Wickede (Ruhr)",
    "sg:phone":"+49 2377/92980",
    "sg:postcode":"58739",
    "sg:province":"Nordrhein-Westfalen",
    "wof:name":"Autohaus Teschler",
    "wof:placetype":"venue"
},
  "geometry": {"coordinates":[7.859954834,51.4880027771],"type":"Point"}
}