{
  "type": "Feature",
  "properties": {
    "iso:country":"DE",
    "sg:address":"Im Bosseldorn 24",
    "sg:city":"Heidelberg",
    "sg:phone":"+49 6221/601932",
    "sg:postcode":"69126",
    "sg:province":"Baden-W\u00fcrttemberg",
    "wof:name":"Hashemi Orient Teppich Gmbh",
    "wof:placetype":"venue"
},
  "geometry": {"coordinates":[8.6788272858,49.3865661621],"type":"Point"}
}