{
  "type": "Feature",
  "properties": {
    "iso:country":"DE",
    "sg:address":"Viehstr. 50",
    "sg:city":"Grevenbroich",
    "sg:phone":"+49 2182/9244",
    "sg:postcode":"41516",
    "sg:province":"Nordrhein-Westfalen",
    "wof:name":"Hallenbad Neukirchen",
    "wof:placetype":"venue"
},
  "geometry": {"coordinates":[6.6818499565,51.1186408997],"type":"Point"}
}