{
  "type": "Feature",
  "properties": {
    "iso:country":"DE",
    "sg:address":"Kleiststr. 8",
    "sg:city":"Iserlohn",
    "sg:phone":"+49 2374/14060",
    "sg:postcode":"58642",
    "sg:province":"Nordrhein-Westfalen",
    "wof:name":"Wolfgang Herzig",
    "wof:placetype":"venue"
},
  "geometry": {"coordinates":[7.6120429039,51.3685569763],"type":"Point"}
}