{
  "type": "Feature",
  "properties": {
    "iso:country":"DE",
    "sg:address":"Mozartstr. 4",
    "sg:city":"Helmstedt",
    "sg:phone":"+49 5351/32029",
    "sg:postcode":"38350",
    "sg:province":"Niedersachsen",
    "wof:name":"Schiffsmodellclub Gerhard Cisielski",
    "wof:placetype":"venue"
},
  "geometry": {"coordinates":[11.0130233765,52.239074707],"type":"Point"}
}