{
  "type": "Feature",
  "properties": {
    "iso:country":"DE",
    "sg:address":"Koblenzer Str. 17",
    "sg:city":"Montabaur",
    "sg:phone":"+49 2602/4993",
    "sg:postcode":"56410",
    "sg:province":"Rheinland-Pfalz",
    "wof:name":"Pizzeria Da-enzo",
    "wof:placetype":"venue"
},
  "geometry": {"coordinates":[7.8276672363,50.430934906],"type":"Point"}
}