{
  "type": "Feature",
  "properties": {
    "iso:country":"DE",
    "sg:address":"Bernsteinweg 12",
    "sg:city":"Bad Herrenalb",
    "sg:phone":"+49 7083/8320",
    "sg:postcode":"76332",
    "sg:province":"Baden-W\u00fcrttemberg",
    "wof:name":"Wolfgang Haas Ingenieur",
    "wof:placetype":"venue"
},
  "geometry": {"coordinates":[8.4359035492,48.7997322083],"type":"Point"}
}