{
  "type": "Feature",
  "properties": {
    "iso:country":"DE",
    "sg:city":"Ludwigsburg",
    "sg:postcode":"71636",
    "sg:province":"Baden-W\u00fcrttemberg",
    "wof:name":"G\u00f6tz Gmbh",
    "wof:placetype":"venue"
},
  "geometry": {"coordinates":[9.161527,48.886311],"type":"Point"}
}