{
  "type": "Feature",
  "properties": {
    "iso:country":"DE",
    "sg:address":"Maximilianstr. 18",
    "sg:city":"M\u00fcnchen",
    "sg:postcode":"80539",
    "sg:province":"Bayern",
    "wof:name":"Fortuna Grundst\u00fccks-gmbh & Co. Betriebs Kg",
    "wof:placetype":"venue"
},
  "geometry": {"coordinates":[11.5813684464,48.1387748718],"type":"Point"}
}