{
  "type": "Feature",
  "properties": {
    "iso:country":"DE",
    "sg:address":"Gerstenweg 120",
    "sg:city":"Berlin",
    "sg:phone":"+49 30/2084323",
    "sg:postcode":"12683",
    "sg:province":"Berlin",
    "wof:name":"Handelsgesellschaft Twq Mbh",
    "wof:placetype":"venue"
},
  "geometry": {"coordinates":[13.5639190674,52.5233306885],"type":"Point"}
}