{
  "type": "Feature",
  "properties": {
    "iso:country":"DE",
    "sg:address":"Am Krug 11",
    "sg:city":"M\u00fcnster",
    "sg:phone":"+49 251/295557",
    "sg:postcode":"48151",
    "sg:province":"Nordrhein-Westfalen",
    "wof:name":"Werkbank Multimedia Gmbh",
    "wof:placetype":"venue"
},
  "geometry": {"coordinates":[7.6206102371,51.9487724304],"type":"Point"}
}