{
  "type": "Feature",
  "properties": {
    "iso:country":"DE",
    "sg:address":"Sch\u00f6nstr. 41",
    "sg:city":"Moosinning",
    "sg:postcode":"85452",
    "sg:province":"Bayern",
    "wof:name":"Hoyler Verwaltungs- Gmbh",
    "wof:placetype":"venue"
},
  "geometry": {"coordinates":[11.7559738159,48.2711830139],"type":"Point"}
}