{
  "type": "Feature",
  "properties": {
    "iso:country":"DE",
    "sg:address":"-keine-",
    "sg:city":"-keine-",
    "sg:phone":"+49 2222/358",
    "sg:postcode":"11111",
    "wof:name":"Jovanas Musik Seite",
    "wof:placetype":"venue"
},
  "geometry": {"coordinates":[-99.149773,19.40904],"type":"Point"}
}