{
  "type": "Feature",
  "properties": {
    "iso:country":"DE",
    "sg:address":"Kemnastr. 28",
    "sg:city":"Recklinghausen",
    "sg:phone":"+49 2361/108810",
    "sg:postcode":"45657",
    "sg:province":"Nordrhein-Westfalen",
    "wof:name":"D. Grimm Und Partner Gbr",
    "wof:placetype":"venue"
},
  "geometry": {"coordinates":[7.1924,51.610359],"type":"Point"}
}