{
  "type": "Feature",
  "properties": {
    "iso:country":"DE",
    "sg:address":"Bahnstr. 4",
    "sg:city":"Zwickau",
    "sg:phone":"+49 375/243433",
    "sg:postcode":"08056",
    "sg:province":"Sachsen",
    "wof:name":"Lothar Rei\u00dfmann",
    "wof:placetype":"venue"
},
  "geometry": {"coordinates":[12.493057251,50.7024078369],"type":"Point"}
}