{
  "type": "Feature",
  "properties": {
    "iso:country":"DE",
    "sg:address":"Fabrikstr. 41",
    "sg:city":"Plochingen",
    "sg:phone":"+49 7153/826106",
    "sg:postcode":"73207",
    "sg:province":"Baden-W\u00fcrttemberg",
    "wof:name":"Tega Gmbh",
    "wof:placetype":"venue"
},
  "geometry": {"coordinates":[9.4086,48.717831],"type":"Point"}
}