{
  "type": "Feature",
  "properties": {
    "iso:country":"DE",
    "sg:address":"Kelkheimer Str. 34",
    "sg:city":"Bad Soden",
    "sg:phone":"+49 6196/63190",
    "sg:postcode":"65812",
    "sg:province":"Hessen",
    "wof:name":"Y. Lenz-m\u00fcller",
    "wof:placetype":"venue"
},
  "geometry": {"coordinates":[8.494256,50.139877],"type":"Point"}
}