{
  "type": "Feature",
  "properties": {
    "iso:country":"DE",
    "sg:address":"Sch\u00e4ferstr. 28",
    "sg:city":"Homberg",
    "sg:phone":"+49 6633/7761",
    "sg:postcode":"35315",
    "sg:province":"Hessen",
    "wof:name":"R. Simon",
    "wof:placetype":"venue"
},
  "geometry": {"coordinates":[8.968349,50.696301],"type":"Point"}
}