{
  "type": "Feature",
  "properties": {
    "iso:country":"DE",
    "sg:address":"Br\u00fchlstr. 14",
    "sg:city":"Nehren",
    "sg:phone":"+49 7473/271096",
    "sg:postcode":"72147",
    "sg:province":"Baden-W\u00fcrttemberg",
    "wof:name":"Wima Gmbh",
    "wof:placetype":"venue"
},
  "geometry": {"coordinates":[9.0727529526,48.4318313599],"type":"Point"}
}