{
  "type": "Feature",
  "properties": {
    "iso:country":"DE",
    "sg:address":"Ludwigring 13",
    "sg:city":"Rastatt",
    "sg:phone":"+49 7222/31390",
    "sg:postcode":"76437",
    "sg:province":"Baden-W\u00fcrttemberg",
    "wof:name":"Rumpelburg",
    "wof:placetype":"venue"
},
  "geometry": {"coordinates":[8.2125425339,48.8549041748],"type":"Point"}
}