{
  "type": "Feature",
  "properties": {
    "iso:country":"DE",
    "sg:address":"Schwedendamm 1a",
    "sg:city":"Rathenow",
    "sg:phone":"+49 3385/503450",
    "sg:postcode":"14712",
    "sg:province":"Brandenburg",
    "wof:name":"M. M.-team Gmbh",
    "wof:placetype":"venue"
},
  "geometry": {"coordinates":[12.325915,52.607689],"type":"Point"}
}