{
  "type": "Feature",
  "properties": {
    "iso:country":"DE",
    "sg:address":"Begonienstr. 26",
    "sg:city":"Stuhr",
    "sg:phone":"+49 421/801268",
    "sg:postcode":"28816",
    "sg:province":"Niedersachsen",
    "wof:name":"Die Zwei Bau Gmbh",
    "wof:placetype":"venue"
},
  "geometry": {"coordinates":[8.788451,53.006645],"type":"Point"}
}