{
  "type": "Feature",
  "properties": {
    "iso:country":"DE",
    "sg:address":"Wolgaster Str. 118",
    "sg:city":"Greifswald",
    "sg:phone":"+49 3834/509094",
    "sg:postcode":"17489",
    "sg:province":"Mecklenburg-Vorpommern",
    "wof:name":"H. Schwarz",
    "wof:placetype":"venue"
},
  "geometry": {"coordinates":[13.3992528915,54.0949134827],"type":"Point"}
}