{
  "type": "Feature",
  "properties": {
    "iso:country":"DE",
    "sg:address":"Am Wehrhahn 12",
    "sg:city":"D\u00fcsseldorf",
    "sg:phone":"+49 211/172970",
    "sg:postcode":"40211",
    "sg:province":"Nordrhein-Westfalen",
    "wof:name":"Martin Schenz Rechtsanwalt",
    "wof:placetype":"venue"
},
  "geometry": {"coordinates":[6.788544178,51.2282409668],"type":"Point"}
}