{
  "type": "Feature",
  "properties": {
    "iso:country":"DE",
    "sg:address":"Ronsdorfer Str. 143",
    "sg:city":"D\u00fcsseldorf",
    "sg:phone":"+49 211/921120",
    "sg:postcode":"40233",
    "sg:province":"Nordrhein-Westfalen",
    "wof:name":"Antonio Tassone",
    "wof:placetype":"venue"
},
  "geometry": {"coordinates":[6.8156571388,51.2130432129],"type":"Point"}
}