{
  "type": "Feature",
  "properties": {
    "iso:country":"DE",
    "sg:address":"Mittelstr. 37",
    "sg:city":"Detmold",
    "sg:phone":"+49 5231/97980",
    "sg:postcode":"32758",
    "sg:province":"Nordrhein-Westfalen",
    "wof:name":"Gerhard Brandt Gmbh & Co. Kg",
    "wof:placetype":"venue"
},
  "geometry": {"coordinates":[8.8858642578,51.9585456848],"type":"Point"}
}