{
  "type": "Feature",
  "properties": {
    "iso:country":"DE",
    "sg:address":"Postfach 422",
    "sg:city":"Badenweiler",
    "sg:postcode":"79404",
    "sg:province":"Baden-W\u00fcrttemberg",
    "wof:name":"Wingert",
    "wof:placetype":"venue"
},
  "geometry": {"coordinates":[7.67179,47.801781],"type":"Point"}
}