{
  "type": "Feature",
  "properties": {
    "iso:country":"DE",
    "sg:address":"Echterdinger Str. 37",
    "sg:city":"Leinfelden-Echterdingen",
    "sg:phone":"+49 711/752504",
    "sg:postcode":"70771",
    "sg:province":"Baden-W\u00fcrttemberg",
    "wof:name":"Siegfried Hess",
    "wof:placetype":"venue"
},
  "geometry": {"coordinates":[9.148,48.69173],"type":"Point"}
}