{
  "type": "Feature",
  "properties": {
    "iso:country":"DE",
    "sg:address":"Postfach 3064",
    "sg:city":"Unna",
    "sg:postcode":"59414",
    "sg:province":"Nordrhein-Westfalen",
    "wof:name":"Reklar-isolierglassanierung",
    "wof:placetype":"venue"
},
  "geometry": {"coordinates":[7.6858801842,51.5344696045],"type":"Point"}
}