{
  "type": "Feature",
  "properties": {
    "iso:country":"DE",
    "sg:address":"Am Elsenbuck 8",
    "sg:city":"Regenstauf",
    "sg:phone":"+49 9402/3569",
    "sg:postcode":"93128",
    "sg:province":"Bayern",
    "wof:name":"Klaus Grohmann Reiseb\u00fcro",
    "wof:placetype":"venue"
},
  "geometry": {"coordinates":[12.1517019272,49.1540222168],"type":"Point"}
}