{
  "type": "Feature",
  "properties": {
    "iso:country":"DE",
    "sg:address":"Auf der Mi\u00df 27",
    "sg:city":"Freystadt",
    "sg:phone":"+49 9179/5383",
    "sg:postcode":"92342",
    "sg:province":"Bayern",
    "wof:name":"Wolfgang Sorgenfrei",
    "wof:placetype":"venue"
},
  "geometry": {"coordinates":[11.3319139481,49.2019195557],"type":"Point"}
}