{
  "type": "Feature",
  "properties": {
    "iso:country":"DE",
    "sg:address":"Willi-Bredel-Str. 21",
    "sg:city":"Magdeburg",
    "sg:postcode":"39120",
    "sg:province":"Sachsen-Anhalt",
    "wof:name":"Dr. Med. Klaus-walter Zipprich",
    "wof:placetype":"venue"
},
  "geometry": {"coordinates":[11.625723,52.097069],"type":"Point"}
}