{
  "type": "Feature",
  "properties": {
    "iso:country":"DE",
    "sg:address":"Am Alten Stadtpark 67",
    "sg:city":"Bochum",
    "sg:phone":"+49 234/580502",
    "sg:postcode":"44791",
    "sg:province":"Nordrhein-Westfalen",
    "wof:name":"Dipl.-ing. Henning Neeff",
    "wof:placetype":"venue"
},
  "geometry": {"coordinates":[7.221755,51.490032],"type":"Point"}
}