{
  "type": "Feature",
  "properties": {
    "iso:country":"DE",
    "sg:address":"Wilhelmsplatz 2",
    "sg:city":"Herford",
    "sg:phone":"+49 5221/16650",
    "sg:postcode":"32052",
    "sg:province":"Nordrhein-Westfalen",
    "wof:name":"Gerhard Fischer Steuerberater",
    "wof:placetype":"venue"
},
  "geometry": {"coordinates":[8.6696033478,52.1190986633],"type":"Point"}
}