{
  "type": "Feature",
  "properties": {
    "iso:country":"DE",
    "sg:address":"Bahnhofplatz 5",
    "sg:city":"Miesbach",
    "sg:phone":"+49 8025/8475",
    "sg:postcode":"83714",
    "sg:province":"Bayern",
    "wof:name":"Bahnhofs Gastst\u00e4tte",
    "wof:placetype":"venue"
},
  "geometry": {"coordinates":[11.8309793472,47.7903366089],"type":"Point"}
}