{
  "type": "Feature",
  "properties": {
    "iso:country":"DE",
    "sg:address":"Kuhstr. 33",
    "sg:city":"Duisburg",
    "sg:phone":"+49 203/296298",
    "sg:postcode":"47051",
    "sg:province":"Nordrhein-Westfalen",
    "wof:name":"Coast Inh. Angelika Dahms",
    "wof:placetype":"venue"
},
  "geometry": {"coordinates":[6.76239,51.433769],"type":"Point"}
}