{
  "type": "Feature",
  "properties": {
    "iso:country":"DE",
    "sg:address":"Puschkinstr. 1",
    "sg:city":"Halberstadt",
    "sg:phone":"+49 3941/56460",
    "sg:postcode":"38820",
    "sg:province":"Sachsen-Anhalt",
    "wof:name":"Haus Pawlow",
    "wof:placetype":"venue"
},
  "geometry": {"coordinates":[11.071418,51.895229],"type":"Point"}
}