{
  "type": "Feature",
  "properties": {
    "iso:country":"DE",
    "sg:address":"Hermann-Oberth-Str. 18",
    "sg:city":"Putzbrunn",
    "sg:phone":"+49 89/4569180",
    "sg:postcode":"85640",
    "sg:province":"Bayern",
    "wof:name":"Pentatec Elektronische Systeme Gesellschaft Mit",
    "wof:placetype":"venue"
},
  "geometry": {"coordinates":[11.722322464,48.0751152039],"type":"Point"}
}