{
  "type": "Feature",
  "properties": {
    "iso:country":"DE",
    "sg:address":"Robert-Winter-Str. 3",
    "sg:city":"Brackenheim",
    "sg:phone":"+49 7135/8404",
    "sg:postcode":"74336",
    "sg:province":"Baden-W\u00fcrttemberg",
    "wof:name":"Dietmar Heldt",
    "wof:placetype":"venue"
},
  "geometry": {"coordinates":[9.071976,49.076908],"type":"Point"}
}