{
  "type": "Feature",
  "properties": {
    "iso:country":"DE",
    "sg:address":"Am Wallgraben 3",
    "sg:city":"Schl\u00f6ben",
    "sg:phone":"+49 36428/60271",
    "sg:postcode":"07646",
    "sg:province":"Th\u00fcringen",
    "wof:name":"Gehrlein Bau Gmbh",
    "wof:placetype":"venue"
},
  "geometry": {"coordinates":[11.6887369156,50.8930587769],"type":"Point"}
}