{
  "type": "Feature",
  "properties": {
    "iso:country":"DE",
    "sg:address":"Schulenburgstr. 23",
    "sg:city":"Berlin",
    "sg:phone":"+49 30/3300020",
    "sg:postcode":"13597",
    "sg:province":"Berlin",
    "wof:name":"Burkhard Lichtner Beteiligungs Gmbh & Co. Verwaltungs Kg",
    "wof:placetype":"venue"
},
  "geometry": {"coordinates":[13.2076950073,52.5260772705],"type":"Point"}
}