{
  "type": "Feature",
  "properties": {
    "iso:country":"DE",
    "sg:address":"Franz-Lehar-Str. 6",
    "sg:city":"Rehlingen-Siersburg",
    "sg:phone":"+49 6835/1585",
    "sg:postcode":"66780",
    "sg:province":"Saarland",
    "wof:name":"Werner Schmitt Architekt",
    "wof:placetype":"venue"
},
  "geometry": {"coordinates":[6.677304,49.374619],"type":"Point"}
}