{
  "type": "Feature",
  "properties": {
    "iso:country":"DE",
    "sg:address":"Keltergasse 6",
    "sg:city":"Unterm\u00fcnkheim",
    "sg:phone":"+49 7906/8398",
    "sg:postcode":"74547",
    "sg:province":"Baden-W\u00fcrttemberg",
    "wof:name":"A. Kircher",
    "wof:placetype":"venue"
},
  "geometry": {"coordinates":[9.7563066483,49.1616516113],"type":"Point"}
}