{
  "type": "Feature",
  "properties": {
    "iso:country":"DE",
    "sg:address":"Frankfurter Str. 4",
    "sg:city":"Gro\u00df-Gerau",
    "sg:phone":"+49 6152/82822",
    "sg:postcode":"64521",
    "sg:province":"Hessen",
    "wof:name":"Sport Griebel Gmbh",
    "wof:placetype":"venue"
},
  "geometry": {"coordinates":[8.481717,49.920815],"type":"Point"}
}