{
  "type": "Feature",
  "properties": {
    "iso:country":"DE",
    "sg:address":"Hoher Heckenweg 129",
    "sg:city":"M\u00fcnster",
    "sg:phone":"+49 251/2303851",
    "sg:postcode":"48147",
    "sg:province":"Nordrhein-Westfalen",
    "wof:name":"Kay-uwe Und Evelyn M\u00f6llers Rechtsanw\u00e4lte",
    "wof:placetype":"venue"
},
  "geometry": {"coordinates":[7.646420002,51.9836387634],"type":"Point"}
}