{
  "type": "Feature",
  "properties": {
    "iso:country":"DE",
    "sg:address":"Baunsbergring 45",
    "sg:city":"Guxhagen",
    "sg:phone":"+49 5665/4655",
    "sg:postcode":"34302",
    "sg:province":"Hessen",
    "wof:name":"H. Kn\u00f6tig Anlagenberater",
    "wof:placetype":"venue"
},
  "geometry": {"coordinates":[9.4817066193,51.2136497498],"type":"Point"}
}