{
  "type": "Feature",
  "properties": {
    "iso:country":"DE",
    "sg:address":"Alstedder Str. 46",
    "sg:city":"L\u00fcnen",
    "sg:phone":"+49 2306",
    "sg:postcode":"44534",
    "sg:province":"Nordrhein-Westfalen",
    "wof:name":"10mail Gmbh The Email Company",
    "wof:placetype":"venue"
},
  "geometry": {"coordinates":[7.503238,51.62466],"type":"Point"}
}