{
  "type": "Feature",
  "properties": {
    "iso:country":"DE",
    "sg:address":"Am Tanzberg 4",
    "sg:city":"Ostheim",
    "sg:phone":"+49 9777/2297",
    "sg:postcode":"97645",
    "sg:province":"Bayern",
    "wof:name":"Tanzberg-st\u00fcbl",
    "wof:placetype":"venue"
},
  "geometry": {"coordinates":[10.2278738022,50.4595985413],"type":"Point"}
}