{
  "type": "Feature",
  "properties": {
    "iso:country":"DE",
    "sg:address":"Rohrweg 7",
    "sg:city":"J\u00f6\u00dfnitz",
    "sg:phone":"+49 3741/521197",
    "sg:postcode":"08547",
    "sg:province":"Sachsen",
    "wof:name":"Dr. D. Hessel Anlageberater",
    "wof:placetype":"venue"
},
  "geometry": {"coordinates":[12.1344890594,50.5417251587],"type":"Point"}
}