{
  "type": "Feature",
  "properties": {
    "iso:country":"DE",
    "sg:address":"Hindenburgstr. 15-17",
    "sg:city":"Essen",
    "sg:phone":"+49 201/230085",
    "sg:postcode":"45127",
    "sg:province":"Nordrhein-Westfalen",
    "wof:name":"Hoffmann Steuerberaterin",
    "wof:placetype":"venue"
},
  "geometry": {"coordinates":[7.0069079399,51.4528694153],"type":"Point"}
}