{
  "type": "Feature",
  "properties": {
    "iso:country":"DE",
    "sg:address":"Lohrmannstr. 19-21",
    "sg:city":"Dresden",
    "sg:postcode":"01237",
    "sg:province":"Sachsen",
    "wof:name":"Sportcentrale G\u00fcttler & Schneemann Ohg",
    "wof:placetype":"venue"
},
  "geometry": {"coordinates":[13.789187,51.017433],"type":"Point"}
}