{
  "type": "Feature",
  "properties": {
    "iso:country":"DE",
    "sg:address":"Vornh\u00e4ger Str. 71",
    "sg:city":"Stadthagen",
    "sg:phone":"+49 5721/74727",
    "sg:postcode":"31655",
    "sg:province":"Niedersachsen",
    "wof:name":"Teppichland",
    "wof:placetype":"venue"
},
  "geometry": {"coordinates":[9.2281923294,52.3292770386],"type":"Point"}
}