{
  "type": "Feature",
  "properties": {
    "iso:country":"DE",
    "sg:address":"Ihlenfelder Str. 109",
    "sg:city":"Neubrandenburg",
    "sg:phone":"+49 395/4514379",
    "sg:postcode":"17034",
    "sg:province":"Mecklenburg-Vorpommern",
    "wof:name":"Elbo Bau Ag",
    "wof:placetype":"venue"
},
  "geometry": {"coordinates":[13.28245,53.572762],"type":"Point"}
}