{
  "type": "Feature",
  "properties": {
    "iso:country":"DE",
    "sg:address":"Am Polderdeich 27",
    "sg:city":"Magdeburg",
    "sg:phone":"+49 391/280710",
    "sg:postcode":"39124",
    "sg:province":"Sachsen-Anhalt",
    "wof:name":"E.-h. Und F. Schubert Brunnenbau Gmbh",
    "wof:placetype":"venue"
},
  "geometry": {"coordinates":[11.653321,52.162426],"type":"Point"}
}