{
  "type": "Feature",
  "properties": {
    "iso:country":"DE",
    "sg:address":"Putzbrunner Str. 29",
    "sg:city":"Ottobrunn",
    "sg:phone":"+49 89/6093951",
    "sg:postcode":"85521",
    "sg:province":"Bayern",
    "wof:name":"J\u00fcrgen M\u00fcller",
    "wof:placetype":"venue"
},
  "geometry": {"coordinates":[11.666471,48.067245],"type":"Point"}
}