{
  "type": "Feature",
  "properties": {
    "iso:country":"DE",
    "sg:address":"Osenauerstra\u00dfe 39",
    "sg:city":"Odenthal",
    "sg:postcode":"51519",
    "sg:province":"Nordrhein-Westfalen",
    "wof:name":"Interselect E.k. Immobilien",
    "wof:placetype":"venue"
},
  "geometry": {"coordinates":[7.10342,51.031288],"type":"Point"}
}