{
  "type": "Feature",
  "properties": {
    "iso:country":"DE",
    "sg:address":"D\u00fcppelstr. 3",
    "sg:city":"Gronau",
    "sg:phone":"+49 4941/9281750",
    "sg:postcode":"48599",
    "sg:province":"Nordrhein-Westfalen",
    "wof:name":"Paliso M\u00d6belfabrik Gmbh",
    "wof:placetype":"venue"
},
  "geometry": {"coordinates":[9.8951368332,53.9304656982],"type":"Point"}
}