{
  "type": "Feature",
  "properties": {
    "iso:country":"DE",
    "sg:address":"Elbgaustr. 31",
    "sg:city":"Hamburg",
    "sg:phone":"+49 40/5705392",
    "sg:postcode":"22523",
    "sg:province":"Hamburg",
    "wof:name":"Manfred Rautenberg",
    "wof:placetype":"venue"
},
  "geometry": {"coordinates":[9.9004678726,53.6060523987],"type":"Point"}
}