{
  "type": "Feature",
  "properties": {
    "iso:country":"DE",
    "sg:address":"Karl-Marx-Str. 9",
    "sg:city":"Goldbach",
    "sg:phone":"+49 36255/80200",
    "sg:postcode":"99869",
    "sg:province":"Th\u00fcringen",
    "wof:name":"Horst Ziegler",
    "wof:placetype":"venue"
},
  "geometry": {"coordinates":[10.658073,50.991596],"type":"Point"}
}