{
  "type": "Feature",
  "properties": {
    "iso:country":"DE",
    "sg:address":"Werther Str. 36-40",
    "sg:city":"Stolberg-Mausbach",
    "sg:phone":"+49 4924/0298890",
    "sg:postcode":"52224",
    "sg:province":"Nordrhein-Westfalen",
    "wof:name":"Scholl-roosen Kunststoffe Gmbh",
    "wof:placetype":"venue"
},
  "geometry": {"coordinates":[6.3002548218,50.7730445862],"type":"Point"}
}