{
  "type": "Feature",
  "properties": {
    "iso:country":"DE",
    "sg:address":"M\u00fclgaustr. 2",
    "sg:city":"M\u00f6nchengladbach",
    "sg:phone":"+49 2166/603640",
    "sg:postcode":"41199",
    "sg:province":"Nordrhein-Westfalen",
    "wof:name":"Kreuz Und Quer Eiltransporte Tellmann",
    "wof:placetype":"venue"
},
  "geometry": {"coordinates":[6.4534711838,51.1374359131],"type":"Point"}
}