{
  "type": "Feature",
  "properties": {
    "iso:country":"DE",
    "sg:address":"Albstr. 11",
    "sg:city":"Notzingen",
    "sg:postcode":"73274",
    "sg:province":"Baden-W\u00fcrttemberg",
    "wof:name":"Pellets Gmbh",
    "wof:placetype":"venue"
},
  "geometry": {"coordinates":[9.457819,48.67334],"type":"Point"}
}