{
  "type": "Feature",
  "properties": {
    "iso:country":"DE",
    "sg:address":"Wilhelm-Pieck-Str. 38",
    "sg:city":"Petershagen",
    "sg:postcode":"15370",
    "sg:province":"Brandenburg",
    "wof:name":"Lasa Hausbau- Und Servicegesellschaft Mbh",
    "wof:placetype":"venue"
},
  "geometry": {"coordinates":[13.782958,52.519562],"type":"Point"}
}