{
  "type": "Feature",
  "properties": {
    "iso:country":"DE",
    "sg:address":"S\u00fclldorfer Landstr. 39",
    "sg:city":"Hamburg",
    "sg:phone":"+49 40/87007080",
    "sg:postcode":"22589",
    "sg:province":"Hamburg",
    "wof:name":"Medi Top Pflegedienst Und Service Gmbh",
    "wof:placetype":"venue"
},
  "geometry": {"coordinates":[9.8157138824,53.5773200989],"type":"Point"}
}