{
  "type": "Feature",
  "properties": {
    "iso:country":"DE",
    "sg:address":"Heckinghauser Str. 18",
    "sg:city":"Wuppertal",
    "sg:phone":"+49 202/554954",
    "sg:postcode":"42289",
    "sg:province":"Nordrhein-Westfalen",
    "wof:name":"Briefe-schreiben Aller Art",
    "wof:placetype":"venue"
},
  "geometry": {"coordinates":[7.206085,51.270287],"type":"Point"}
}