{
  "type": "Feature",
  "properties": {
    "iso:country":"DE",
    "sg:address":"Bahnhofstr. 18",
    "sg:city":"Erfurt",
    "sg:phone":"+49 361/6421239",
    "sg:postcode":"99084",
    "sg:province":"Th\u00fcringen",
    "wof:name":"Jhk Lederwaren-vertriebs Gmbh",
    "wof:placetype":"venue"
},
  "geometry": {"coordinates":[11.036643,50.973083],"type":"Point"}
}