{
  "type": "Feature",
  "properties": {
    "iso:country":"DE",
    "sg:address":"R\u00f6ttgener Str. 185",
    "sg:city":"Bonn",
    "sg:phone":"+49 228/281926",
    "sg:postcode":"53125",
    "sg:province":"Nordrhein-Westfalen",
    "wof:name":"Rainer L\u00fcbbers",
    "wof:placetype":"venue"
},
  "geometry": {"coordinates":[7.0773448944,50.6870689392],"type":"Point"}
}