{
  "type": "Feature",
  "properties": {
    "iso:country":"DE",
    "sg:address":"Am Wiesenhof 27",
    "sg:city":"Wilhelmshaven",
    "sg:phone":"+49 4421/82920",
    "sg:postcode":"26389",
    "sg:province":"Niedersachsen",
    "wof:name":"Dirks Beteiligungs- Gmbh",
    "wof:placetype":"venue"
},
  "geometry": {"coordinates":[8.089148,53.535679],"type":"Point"}
}