{
  "type": "Feature",
  "properties": {
    "iso:country":"DE",
    "sg:address":"Heusweilerstr. 42",
    "sg:city":"Riegelsberg",
    "sg:phone":"+49 6806/7402",
    "sg:postcode":"66292",
    "sg:province":"Saarland",
    "wof:name":"Edeltraud Stoffel",
    "wof:placetype":"venue"
},
  "geometry": {"coordinates":[6.9226560593,49.3263778687],"type":"Point"}
}