{
  "type": "Feature",
  "properties": {
    "iso:country":"DE",
    "sg:address":"Mosbacher Weg 28",
    "sg:city":"Neckarzimmern",
    "sg:phone":"+49 6261/5628",
    "sg:postcode":"74865",
    "sg:province":"Baden-W\u00fcrttemberg",
    "wof:name":"Amerexco-trading Gerhard Weigl",
    "wof:placetype":"venue"
},
  "geometry": {"coordinates":[9.12737,49.322117],"type":"Point"}
}