{
  "type": "Feature",
  "properties": {
    "iso:country":"DE",
    "sg:address":"Beuerberger Str. 14",
    "sg:city":"Wolfratshausen",
    "sg:phone":"+49 8171/423010",
    "sg:postcode":"82515",
    "sg:province":"Bayern",
    "wof:name":"Flamenco Vivo Veranstaltungs- Und Management Gmbh",
    "wof:placetype":"venue"
},
  "geometry": {"coordinates":[11.416348,47.910351],"type":"Point"}
}