{
  "type": "Feature",
  "properties": {
    "iso:country":"DE",
    "sg:address":"Quitzowstr. 2",
    "sg:city":"Berlin",
    "sg:postcode":"10559",
    "sg:province":"Berlin",
    "wof:name":"Rolandos Grundst\u00fccksver- Waltungsgesell. Mbh & Co.",
    "wof:placetype":"venue"
},
  "geometry": {"coordinates":[13.356829,52.536076],"type":"Point"}
}