{
  "type": "Feature",
  "properties": {
    "iso:country":"DE",
    "sg:address":"Rosenstr. 1",
    "sg:city":"Bad Abbach",
    "sg:phone":"+49 9405/4735",
    "sg:postcode":"93077",
    "sg:province":"Bayern",
    "wof:name":"Drandarevski Gmbh Marketing Und Vertrieb",
    "wof:placetype":"venue"
},
  "geometry": {"coordinates":[12.0524520874,48.941444397],"type":"Point"}
}