{
  "type": "Feature",
  "properties": {
    "iso:country":"DE",
    "sg:address":"Rablstr. 48",
    "sg:city":"M\u00fcnchen",
    "sg:phone":"+49 89/4488450",
    "sg:postcode":"81669",
    "sg:province":"Bayern",
    "wof:name":"Lutz Hennemeyer Architekt",
    "wof:placetype":"venue"
},
  "geometry": {"coordinates":[11.594644,48.126499],"type":"Point"}
}