{
  "type": "Feature",
  "properties": {
    "iso:country":"DE",
    "sg:address":"Oberauerkiel",
    "sg:city":"B\u00f6brach",
    "sg:phone":"+49 9923/2055",
    "sg:postcode":"94255",
    "sg:province":"Bayern",
    "wof:name":"Pension Fidelis Fischl",
    "wof:placetype":"venue"
},
  "geometry": {"coordinates":[13.0665178299,49.0305938721],"type":"Point"}
}