{
  "type": "Feature",
  "properties": {
    "iso:country":"DE",
    "sg:address":"Roedernallee 8-14",
    "sg:city":"Berlin",
    "sg:phone":"+49 30/4190040",
    "sg:postcode":"13407",
    "sg:province":"Berlin",
    "wof:name":"Humog Handels- Und Motorflug Gmbh & Co. Kg",
    "wof:placetype":"venue"
},
  "geometry": {"coordinates":[13.346714,52.579544],"type":"Point"}
}