{
  "type": "Feature",
  "properties": {
    "iso:country":"DE",
    "sg:address":"Rotteckring 14",
    "sg:city":"Kenzingen",
    "sg:phone":"+49 7644/913383",
    "sg:postcode":"79341",
    "sg:province":"Baden-W\u00fcrttemberg",
    "wof:name":"Cobes Gmbh",
    "wof:placetype":"venue"
},
  "geometry": {"coordinates":[7.775148,48.190411],"type":"Point"}
}