{
  "type": "Feature",
  "properties": {
    "iso:country":"DE",
    "sg:address":"\u00d6lgasse 12",
    "sg:city":"Buttenwiesen",
    "sg:phone":"+49 8274/1334",
    "sg:postcode":"86647",
    "sg:province":"Bayern",
    "wof:name":"Josef Stix",
    "wof:placetype":"venue"
},
  "geometry": {"coordinates":[10.708524,48.597214],"type":"Point"}
}