{
  "type": "Feature",
  "properties": {
    "iso:country":"DE",
    "sg:city":"Sch\u00f6nau",
    "sg:phone":"+49 6228/911087",
    "sg:postcode":"69250",
    "sg:province":"Baden-W\u00fcrttemberg",
    "wof:name":"Ovis Gmbh, Unabh\u00e4ngiger Finanzdienstleister",
    "wof:placetype":"venue"
},
  "geometry": {"coordinates":[8.809778,49.437069],"type":"Point"}
}