{
  "type": "Feature",
  "properties": {
    "iso:country":"DE",
    "sg:address":"Sudetenstr. 2",
    "sg:city":"Ro\u00dfhaupten",
    "sg:phone":"+49 8367/540",
    "sg:postcode":"87672",
    "sg:province":"Bayern",
    "wof:name":"Sk - Druck Gmbh",
    "wof:placetype":"venue"
},
  "geometry": {"coordinates":[10.718551,47.656815],"type":"Point"}
}