{
  "type": "Feature",
  "properties": {
    "iso:country":"DE",
    "sg:address":"Gewerbestr. 10",
    "sg:city":"Wertingen",
    "sg:postcode":"86637",
    "sg:province":"Bayern",
    "wof:name":"Schwarz Verwaltungs Gmbh & Co. Grundbesitz Kg",
    "wof:placetype":"venue"
},
  "geometry": {"coordinates":[10.6827049255,48.5474205017],"type":"Point"}
}