{
  "type": "Feature",
  "properties": {
    "iso:country":"DE",
    "sg:address":"Tiekbrede 1",
    "sg:city":"Kalletal",
    "sg:phone":"+49 5266/290",
    "sg:postcode":"32689",
    "sg:province":"Nordrhein-Westfalen",
    "wof:name":"Karl Siekmann",
    "wof:placetype":"venue"
},
  "geometry": {"coordinates":[8.9064626694,52.0969009399],"type":"Point"}
}