{
  "type": "Feature",
  "properties": {
    "iso:country":"DE",
    "sg:address":"Grubebachstr. 43",
    "sg:city":"Delbr\u00fcck",
    "sg:phone":"+49 2944/97100",
    "sg:postcode":"33129",
    "sg:province":"Nordrhein-Westfalen",
    "wof:name":"Adolf M\u00fcckenhaupt",
    "wof:placetype":"venue"
},
  "geometry": {"coordinates":[8.4658603668,51.7681617737],"type":"Point"}
}