{
  "type": "Feature",
  "properties": {
    "iso:country":"DE",
    "sg:address":"Gartenweg 10",
    "sg:city":"Pracht",
    "sg:phone":"+49 2682/8780",
    "sg:postcode":"57589",
    "sg:province":"Rheinland-Pfalz",
    "wof:name":"Heinz Schaffrath General Versicherungsvertreter",
    "wof:placetype":"venue"
},
  "geometry": {"coordinates":[7.6547641754,50.7610588074],"type":"Point"}
}