{
  "type": "Feature",
  "properties": {
    "iso:country":"DE",
    "sg:address":"Weilerstr.",
    "sg:city":"Rottenburg",
    "sg:phone":"+49 7472/1259",
    "sg:postcode":"72108",
    "sg:province":"Baden-W\u00fcrttemberg",
    "wof:name":"Kath. Pfarramt St. Wolfgang",
    "wof:placetype":"venue"
},
  "geometry": {"coordinates":[8.9264822006,48.4649085999],"type":"Point"}
}