{
  "type": "Feature",
  "properties": {
    "iso:country":"DE",
    "sg:address":"Hammerstr 6",
    "sg:city":"Werlte",
    "sg:phone":"+49 5951/2676",
    "sg:postcode":"49757",
    "sg:province":"Niedersachsen",
    "wof:name":"Nvk Druck- Und Verlagshaus Gmbh",
    "wof:placetype":"venue"
},
  "geometry": {"coordinates":[7.655122,52.852974],"type":"Point"}
}