{
  "type": "Feature",
  "properties": {
    "iso:country":"DE",
    "sg:address":"Neundorfer Str. 63",
    "sg:city":"Plauen",
    "sg:phone":"+49 3741/227788",
    "sg:postcode":"08523",
    "sg:province":"Sachsen",
    "wof:name":"G. Teichmann",
    "wof:placetype":"venue"
},
  "geometry": {"coordinates":[12.117843,50.495865],"type":"Point"}
}