{
  "type": "Feature",
  "properties": {
    "iso:country":"DE",
    "sg:address":"Buchholzweg 08",
    "sg:city":"Berlin",
    "sg:postcode":"13627",
    "sg:province":"Berlin",
    "wof:name":"Tis Tronics Gmbh",
    "wof:placetype":"venue"
},
  "geometry": {"coordinates":[13.3179092407,52.5453262329],"type":"Point"}
}