{
  "type": "Feature",
  "properties": {
    "iso:country":"DE",
    "sg:address":"Alemannenweg 16",
    "sg:city":"Ettlingen",
    "sg:phone":"+49 7243/29677",
    "sg:postcode":"76275",
    "sg:province":"Baden-W\u00fcrttemberg",
    "wof:name":"Waldgastst\u00e4tte Tsv",
    "wof:placetype":"venue"
},
  "geometry": {"coordinates":[8.3659648895,48.9186782837],"type":"Point"}
}