{
  "type": "Feature",
  "properties": {
    "iso:country":"DE",
    "sg:address":"Anzengruberstr. 45",
    "sg:city":"Gr\u00f6benzell",
    "sg:phone":"+49 8142/53044",
    "sg:postcode":"82194",
    "sg:province":"Bayern",
    "wof:name":"Elsbeth Geml Immobilienmaklerin",
    "wof:placetype":"venue"
},
  "geometry": {"coordinates":[11.382519722,48.1810150146],"type":"Point"}
}