{
  "type": "Feature",
  "properties": {
    "iso:country":"DE",
    "sg:address":"Kauler Weg 10",
    "sg:city":"Erkelenz",
    "sg:postcode":"41812",
    "sg:province":"Nordrhein-Westfalen",
    "wof:name":"Bauunternehmung Lindholm Gmbh",
    "wof:placetype":"venue"
},
  "geometry": {"coordinates":[6.2799901962,51.0790290833],"type":"Point"}
}