{
  "type": "Feature",
  "properties": {
    "iso:country":"DE",
    "sg:address":"Ravardistr. 35 a",
    "sg:city":"Bocholt",
    "sg:phone":"+49 2871/181216",
    "sg:postcode":"46399",
    "sg:province":"Nordrhein-Westfalen",
    "wof:name":"Berthe",
    "wof:placetype":"venue"
},
  "geometry": {"coordinates":[6.610391,51.838974],"type":"Point"}
}