{
  "type": "Feature",
  "properties": {
    "iso:country":"DE",
    "sg:address":"Eppendorfer Baum 18",
    "sg:city":"Hamburg",
    "sg:phone":"+49 40/481902",
    "sg:postcode":"20249",
    "sg:province":"Hamburg",
    "wof:name":"R. Struve",
    "wof:placetype":"venue"
},
  "geometry": {"coordinates":[9.985483,53.583176],"type":"Point"}
}