{
  "type": "Feature",
  "properties": {
    "iso:country":"DE",
    "sg:address":"Subbelrather Str. 111",
    "sg:city":"K\u00f6ln",
    "sg:phone":"+49 221/512800",
    "sg:postcode":"50823",
    "sg:province":"Nordrhein-Westfalen",
    "wof:name":"H. Fischer Augenoptiker",
    "wof:placetype":"venue"
},
  "geometry": {"coordinates":[6.9285960197,50.9501037598],"type":"Point"}
}