{
  "type": "Feature",
  "properties": {
    "iso:country":"DE",
    "sg:address":"Lindenstr. 2",
    "sg:city":"Bremen",
    "sg:phone":"+49 421/669610",
    "sg:postcode":"28755",
    "sg:province":"Bremen",
    "wof:name":"Elektro Baar Gmbh",
    "wof:placetype":"venue"
},
  "geometry": {"coordinates":[8.6114330292,53.175113678],"type":"Point"}
}