{
  "type": "Feature",
  "properties": {
    "iso:country":"DE",
    "sg:address":"Leyer Str. 24",
    "sg:city":"Osnabr\u00fcck",
    "sg:phone":"+49 541/914301",
    "sg:postcode":"49076",
    "sg:province":"Niedersachsen",
    "wof:name":"Nt Plus Ag",
    "wof:placetype":"venue"
},
  "geometry": {"coordinates":[7.9801311493,52.2933387756],"type":"Point"}
}