{
  "type": "Feature",
  "properties": {
    "iso:country":"DE",
    "sg:address":"Industriestr. 73",
    "sg:city":"Wesseling",
    "sg:phone":"+49 2232/70802",
    "sg:postcode":"50389",
    "sg:province":"Nordrhein-Westfalen",
    "wof:name":"Karl-peter Griesemann Ingenieur",
    "wof:placetype":"venue"
},
  "geometry": {"coordinates":[6.945663929,50.8378257751],"type":"Point"}
}