{
  "type": "Feature",
  "properties": {
    "iso:country":"DE",
    "sg:address":"Schleusinger Str. 53b",
    "sg:city":"Suhl",
    "sg:phone":"+49 3681/722090",
    "sg:postcode":"98527",
    "sg:province":"Th\u00fcringen",
    "wof:name":"Zehner",
    "wof:placetype":"venue"
},
  "geometry": {"coordinates":[10.692949295,50.6014823914],"type":"Point"}
}