{
  "type": "Feature",
  "properties": {
    "iso:country":"DE",
    "sg:address":"Celler Str. 81",
    "sg:city":"Braunschweig",
    "sg:phone":"+49 531/505079",
    "sg:postcode":"38114",
    "sg:province":"Niedersachsen",
    "wof:name":"Golden Point",
    "wof:placetype":"venue"
},
  "geometry": {"coordinates":[10.5052785873,52.2760925293],"type":"Point"}
}