{
  "type": "Feature",
  "properties": {
    "iso:country":"DE",
    "sg:address":"Palmaille 54",
    "sg:city":"Hamburg",
    "sg:phone":"+49 40/3809393",
    "sg:postcode":"22767",
    "sg:province":"Hamburg",
    "wof:name":"Gastst\u00e4tte Bei Lotte Und Klaus",
    "wof:placetype":"venue"
},
  "geometry": {"coordinates":[9.9430332184,53.5464897156],"type":"Point"}
}