{
  "type": "Feature",
  "properties": {
    "iso:country":"DE",
    "sg:address":"Industriestr. 2",
    "sg:city":"Gummersbach",
    "sg:postcode":"51643",
    "sg:province":"Nordrhein-Westfalen",
    "wof:name":"Movo Mech System Gmbh",
    "wof:placetype":"venue"
},
  "geometry": {"coordinates":[7.5733151436,51.0213928223],"type":"Point"}
}