{
  "type": "Feature",
  "properties": {
    "iso:country":"DE",
    "sg:address":"Martin-Luther-Platz 26",
    "sg:city":"D\u00fcsseldorf",
    "sg:phone":"+49 211/83990",
    "sg:postcode":"40212",
    "sg:province":"Nordrhein-Westfalen",
    "wof:name":"Vendor Liegenschaften- Administrations- Gmbh",
    "wof:placetype":"venue"
},
  "geometry": {"coordinates":[6.782067,51.224968],"type":"Point"}
}