{
  "type": "Feature",
  "properties": {
    "iso:country":"DE",
    "sg:address":"Kaiserstr.",
    "sg:city":"Oldenburg",
    "sg:phone":"+49 441/12171",
    "sg:postcode":"26122",
    "sg:province":"Niedersachsen",
    "wof:name":"Avia-tankstelle",
    "wof:placetype":"venue"
},
  "geometry": {"coordinates":[8.221739769,53.142036438],"type":"Point"}
}