{
  "type": "Feature",
  "properties": {
    "iso:country":"DE",
    "sg:address":"Brauereistr. 34",
    "sg:city":"Steinberg",
    "sg:phone":"+49 37462/3615",
    "sg:postcode":"08237",
    "sg:province":"Sachsen",
    "wof:name":"Erhard R\u00f6der",
    "wof:placetype":"venue"
},
  "geometry": {"coordinates":[12.4591245651,50.5212860107],"type":"Point"}
}