{
  "type": "Feature",
  "properties": {
    "iso:country":"DE",
    "sg:address":"Schlo\u00dfweg 5",
    "sg:city":"F\u00fcrsteneck",
    "sg:phone":"+49 8505/1473",
    "sg:postcode":"94142",
    "sg:province":"Bayern",
    "wof:name":"Schlo\u00dfgastst\u00e4tte F\u00fcrsteneck",
    "wof:placetype":"venue"
},
  "geometry": {"coordinates":[13.4609603882,48.7151031494],"type":"Point"}
}