{
  "type": "Feature",
  "properties": {
    "iso:country":"DE",
    "sg:address":"Winterbachweg 1",
    "sg:city":"Gro\u00dfheirath",
    "sg:phone":"+49 9569/1275",
    "sg:postcode":"96269",
    "sg:province":"Bayern",
    "wof:name":"Rudi Krempel",
    "wof:placetype":"venue"
},
  "geometry": {"coordinates":[10.90278,50.195919],"type":"Point"}
}