{
  "type": "Feature",
  "properties": {
    "iso:country":"DE",
    "sg:address":"Kaiserswerther Str. 83",
    "sg:city":"Ratingen",
    "sg:phone":"+49 2102/490424",
    "sg:postcode":"40878",
    "sg:province":"Nordrhein-Westfalen",
    "wof:name":"Hwacheon Machinery Europe Gmbh",
    "wof:placetype":"venue"
},
  "geometry": {"coordinates":[6.833385,51.298248],"type":"Point"}
}