{
  "type": "Feature",
  "properties": {
    "iso:country":"DE",
    "sg:address":"Marktplatz 1",
    "sg:city":"Lehrberg",
    "sg:phone":"+49 9820/271",
    "sg:postcode":"91611",
    "sg:province":"Bayern",
    "wof:name":"H. Schwab Wettannahme",
    "wof:placetype":"venue"
},
  "geometry": {"coordinates":[10.50922,49.345879],"type":"Point"}
}