{
  "type": "Feature",
  "properties": {
    "iso:country":"DE",
    "sg:address":"Hungerbachstr. 8",
    "sg:city":"Oberhausen",
    "sg:phone":"+49 8802/302",
    "sg:postcode":"82386",
    "sg:province":"Bayern",
    "wof:name":"G. Bauer Immobilienmakler",
    "wof:placetype":"venue"
},
  "geometry": {"coordinates":[11.1347417831,47.7791824341],"type":"Point"}
}