{
  "type": "Feature",
  "properties": {
    "iso:country":"DE",
    "sg:address":"Hafenstr. 19",
    "sg:city":"List",
    "sg:postcode":"25992",
    "sg:province":"Schleswig-Holstein",
    "wof:name":"Ev. Soldatenfreizeitheim",
    "wof:placetype":"venue"
},
  "geometry": {"coordinates":[8.4341964722,55.0161018372],"type":"Point"}
}