{
  "type": "Feature",
  "properties": {
    "iso:country":"DE",
    "sg:address":"Unterer W\u00f6rth 9",
    "sg:city":"Balingen",
    "sg:postcode":"72336",
    "sg:province":"Baden-W\u00fcrttemberg",
    "wof:name":"Kien Moden Herstellungs Und",
    "wof:placetype":"venue"
},
  "geometry": {"coordinates":[8.922497,48.259102],"type":"Point"}
}