{
  "type": "Feature",
  "properties": {
    "iso:country":"DE",
    "sg:address":"Haunw\u00f6hrer Str. 181",
    "sg:city":"Ingolstadt",
    "sg:phone":"+49 841/75591",
    "sg:postcode":"85051",
    "sg:province":"Bayern",
    "wof:name":"Barbara Neuburg",
    "wof:placetype":"venue"
},
  "geometry": {"coordinates":[11.4110689163,48.7449188232],"type":"Point"}
}