{
  "type": "Feature",
  "properties": {
    "iso:country":"DE",
    "sg:address":"Schleusenstieg 20",
    "sg:city":"Hamburg",
    "sg:phone":"+49 40/6071230",
    "sg:postcode":"22397",
    "sg:province":"Hamburg",
    "wof:name":"Lotte Bohn Komponistin",
    "wof:placetype":"venue"
},
  "geometry": {"coordinates":[10.1153001785,53.7045097351],"type":"Point"}
}