{
  "type": "Feature",
  "properties": {
    "iso:country":"DE",
    "sg:address":"Wei\u00dfer Brink 1",
    "sg:city":"Seelze",
    "sg:phone":"+49 511/403221",
    "sg:postcode":"30926",
    "sg:province":"Niedersachsen",
    "wof:name":"Horst Bayer Architekt",
    "wof:placetype":"venue"
},
  "geometry": {"coordinates":[9.631704,52.394375],"type":"Point"}
}