{
  "type": "Feature",
  "properties": {
    "iso:country":"DE",
    "sg:address":"Hauptstr. 57",
    "sg:city":"Ostramondra",
    "sg:phone":"+49 36378/5993",
    "sg:postcode":"99636",
    "sg:province":"Th\u00fcringen",
    "wof:name":"H. Sch\u00fcle",
    "wof:placetype":"venue"
},
  "geometry": {"coordinates":[11.3288192749,51.1988105774],"type":"Point"}
}