{
  "type": "Feature",
  "properties": {
    "iso:country":"DE",
    "sg:address":"Rieper Str. 12",
    "sg:city":"Fallingbostel",
    "sg:phone":"+49 5163/6595",
    "sg:postcode":"29683",
    "sg:province":"Niedersachsen",
    "wof:name":"Kayser Betten Peter Kayser E. K.",
    "wof:placetype":"venue"
},
  "geometry": {"coordinates":[9.69439888,52.8659896851],"type":"Point"}
}