{
  "type": "Feature",
  "properties": {
    "iso:country":"DE",
    "sg:address":"Friedhofsweg 16",
    "sg:city":"Hamburg",
    "sg:postcode":"22337",
    "sg:province":"Hamburg",
    "wof:name":"Falko Drechsler Gastronomie Consulting Gmbh",
    "wof:placetype":"venue"
},
  "geometry": {"coordinates":[10.0584249496,53.6293373108],"type":"Point"}
}