{
  "type": "Feature",
  "properties": {
    "iso:country":"DE",
    "sg:address":"Gartenstr. 19",
    "sg:city":"K\u00f6ln",
    "sg:phone":"+49 221/354522",
    "sg:postcode":"50996",
    "sg:province":"Nordrhein-Westfalen",
    "wof:name":"Bernd Schelling Tennislehrer",
    "wof:placetype":"venue"
},
  "geometry": {"coordinates":[6.9870772362,50.8891906738],"type":"Point"}
}