{
  "type": "Feature",
  "properties": {
    "iso:country":"DE",
    "sg:address":"Strothmannsweg 18",
    "sg:city":"Lohne",
    "sg:phone":"+49 4442/1534",
    "sg:postcode":"49393",
    "sg:province":"Niedersachsen",
    "wof:name":"Josef Landwehr",
    "wof:placetype":"venue"
},
  "geometry": {"coordinates":[8.2372245789,52.6702537537],"type":"Point"}
}