{
  "type": "Feature",
  "properties": {
    "iso:country":"DE",
    "sg:address":"Hauptstr. 18",
    "sg:city":"Nordhorn",
    "sg:phone":"+49 5921/5502",
    "sg:postcode":"48529",
    "sg:province":"Niedersachsen",
    "wof:name":"Hans Huesmann",
    "wof:placetype":"venue"
},
  "geometry": {"coordinates":[7.0708870888,52.4354057312],"type":"Point"}
}