{
  "type": "Feature",
  "properties": {
    "iso:country":"DE",
    "sg:address":"August-K\u00fchling-Str. 33",
    "sg:city":"Emstek",
    "sg:phone":"+49 4473/544",
    "sg:postcode":"49685",
    "sg:province":"Niedersachsen",
    "wof:name":"Franz L\u00fcers",
    "wof:placetype":"venue"
},
  "geometry": {"coordinates":[8.1679,52.839714],"type":"Point"}
}