{
  "type": "Feature",
  "properties": {
    "iso:country":"DE",
    "sg:address":"Gr\u00fcndlacher Str. 311",
    "sg:city":"F\u00fcrth",
    "sg:phone":"+49 911/930630",
    "sg:postcode":"90765",
    "sg:province":"Bayern",
    "wof:name":"Baum\u00fcller Dech",
    "wof:placetype":"venue"
},
  "geometry": {"coordinates":[11.00597,49.511639],"type":"Point"}
}