{
  "type": "Feature",
  "properties": {
    "iso:country":"DE",
    "sg:address":"Renhartstr. 1",
    "sg:city":"Burladingen",
    "sg:phone":"+49 7126/355",
    "sg:postcode":"72393",
    "sg:province":"Baden-W\u00fcrttemberg",
    "wof:name":"Erich Hirlinger",
    "wof:placetype":"venue"
},
  "geometry": {"coordinates":[9.148687,48.361107],"type":"Point"}
}