{
  "type": "Feature",
  "properties": {
    "iso:country":"DE",
    "sg:address":"Ernestinenstr. 189",
    "sg:city":"Essen",
    "sg:phone":"+49 201/291880",
    "sg:postcode":"45139",
    "sg:province":"Nordrhein-Westfalen",
    "wof:name":"Persona Concepta Beratungsges. Mbh",
    "wof:placetype":"venue"
},
  "geometry": {"coordinates":[7.0466890335,51.4647521973],"type":"Point"}
}