{
  "type": "Feature",
  "properties": {
    "iso:country":"DE",
    "sg:address":"An der S\u00e4ge 7",
    "sg:city":"Friesenried",
    "sg:phone":"+49 8347/228",
    "sg:postcode":"87654",
    "sg:province":"Bayern",
    "wof:name":"Johann Mader",
    "wof:placetype":"venue"
},
  "geometry": {"coordinates":[10.5127267838,47.885799408],"type":"Point"}
}