{
  "type": "Feature",
  "properties": {
    "iso:country":"DE",
    "sg:address":"Remisenweg 15",
    "sg:city":"Ammerbuch",
    "sg:phone":"+49 7073/916710",
    "sg:postcode":"72119",
    "sg:province":"Baden-W\u00fcrttemberg",
    "wof:name":"K.-f. Fleck",
    "wof:placetype":"venue"
},
  "geometry": {"coordinates":[8.961438,48.556023],"type":"Point"}
}