{
  "type": "Feature",
  "properties": {
    "iso:country":"DE",
    "sg:address":"Zippelhaus 5 a",
    "sg:city":"Hamburg",
    "sg:phone":"+49 40/3097180",
    "sg:postcode":"20457",
    "sg:province":"Hamburg",
    "wof:name":"Knsk Werbeagentur Gmbh",
    "wof:placetype":"venue"
},
  "geometry": {"coordinates":[9.9963226318,53.5463142395],"type":"Point"}
}