{
  "type": "Feature",
  "properties": {
    "iso:country":"DE",
    "sg:address":"Franz-Ludwig-Str. 12",
    "sg:city":"Bamberg",
    "sg:phone":"+49 951/982840",
    "sg:postcode":"96047",
    "sg:province":"Bayern",
    "wof:name":"Rewe-m\u00e4rkte Interkauf Handels Gmbh & Co. Kg",
    "wof:placetype":"venue"
},
  "geometry": {"coordinates":[10.891708374,49.8931617737],"type":"Point"}
}