{
  "type": "Feature",
  "properties": {
    "iso:country":"DE",
    "sg:address":"Niederhof 14",
    "sg:city":"Engelskirchen",
    "sg:phone":"+49 2263/1040",
    "sg:postcode":"51766",
    "sg:province":"Nordrhein-Westfalen",
    "wof:name":"Thomas B\u00e4chler Ingenieur",
    "wof:placetype":"venue"
},
  "geometry": {"coordinates":[7.3597297668,50.9564208984],"type":"Point"}
}