{
  "type": "Feature",
  "properties": {
    "iso:country":"DE",
    "sg:address":"Goethestr. 46",
    "sg:city":"Neckartenzlingen",
    "sg:phone":"+49 7127/922766",
    "sg:postcode":"72654",
    "sg:province":"Baden-W\u00fcrttemberg",
    "wof:name":"Frank Huster Architekt",
    "wof:placetype":"venue"
},
  "geometry": {"coordinates":[9.247826,48.584873],"type":"Point"}
}