{
  "type": "Feature",
  "properties": {
    "iso:country":"DE",
    "sg:address":"Tobelstr. 8",
    "sg:city":"S\u00fc\u00dfen",
    "sg:postcode":"73079",
    "sg:province":"Baden-W\u00fcrttemberg",
    "wof:name":"Ees Prof. Dr. Roller Beratungsgesellschaft Mbh",
    "wof:placetype":"venue"
},
  "geometry": {"coordinates":[9.746677,48.6782],"type":"Point"}
}