{
  "type": "Feature",
  "properties": {
    "iso:country":"DE",
    "sg:address":"M\u00fcnsterstr.121",
    "sg:city":"D\u00fcsseldorf",
    "sg:phone":"+49 211/480261",
    "sg:postcode":"40476",
    "sg:province":"Nordrhein-Westfalen",
    "wof:name":"Dresdner Bank",
    "wof:placetype":"venue"
},
  "geometry": {"coordinates":[6.789297,51.245201],"type":"Point"}
}