{
  "type": "Feature",
  "properties": {
    "iso:country":"DE",
    "sg:address":"Am Bahnhof 8",
    "sg:city":"Schneverdingen",
    "sg:postcode":"29640",
    "sg:province":"Niedersachsen",
    "wof:name":"Theos Backstuben Vertriebs- Gmbh",
    "wof:placetype":"venue"
},
  "geometry": {"coordinates":[9.7984552383,53.1095123291],"type":"Point"}
}