{
  "type": "Feature",
  "properties": {
    "iso:country":"DE",
    "sg:address":"Finkenstr. 19",
    "sg:city":"Offenbach",
    "sg:phone":"+49 69/833585",
    "sg:postcode":"63069",
    "sg:province":"Hessen",
    "wof:name":"K.-h. Kr\u00f6ber Architekt",
    "wof:placetype":"venue"
},
  "geometry": {"coordinates":[8.749496,50.092251],"type":"Point"}
}