{
  "type": "Feature",
  "properties": {
    "iso:country":"DE",
    "sg:address":"Schl\u00fcterstr. 15",
    "sg:city":"Bergholz-Rehbr\u00fccke",
    "sg:phone":"+49 33200/85502",
    "sg:postcode":"14558",
    "sg:province":"Brandenburg",
    "wof:name":"Peter Rauch",
    "wof:placetype":"venue"
},
  "geometry": {"coordinates":[13.0970058441,52.3371353149],"type":"Point"}
}