{
  "type": "Feature",
  "properties": {
    "iso:country":"DE",
    "sg:address":"Eberhardstr.17",
    "sg:city":"Asperg",
    "sg:phone":"+49 7141/668622",
    "sg:postcode":"71679",
    "sg:province":"Baden-W\u00fcrttemberg",
    "wof:name":"Www.pcrat.de Hier Ist Ein Guter Rat Noch Kostenlos",
    "wof:placetype":"venue"
},
  "geometry": {"coordinates":[9.139239,48.905334],"type":"Point"}
}