{
  "type": "Feature",
  "properties": {
    "iso:country":"DE",
    "sg:address":"Freihof",
    "sg:city":"Gangelt",
    "sg:phone":"+49 2454/1460",
    "sg:postcode":"52538",
    "sg:province":"Nordrhein-Westfalen",
    "wof:name":"Haus Wildblick",
    "wof:placetype":"venue"
},
  "geometry": {"coordinates":[5.9962048531,50.992351532],"type":"Point"}
}