{
  "type": "Feature",
  "properties": {
    "iso:country":"DE",
    "sg:address":"Hebewerkstr. 164",
    "sg:city":"Castrop-Rauxel",
    "sg:phone":"+49 2367/286",
    "sg:postcode":"44577",
    "sg:province":"Nordrhein-Westfalen",
    "wof:name":"Hermann Quinkenstein",
    "wof:placetype":"venue"
},
  "geometry": {"coordinates":[7.317088,51.611992],"type":"Point"}
}