{
  "type": "Feature",
  "properties": {
    "iso:country":"DE",
    "sg:address":"Herrengasse 43",
    "sg:city":"N\u00f6rdlingen",
    "sg:phone":"+49 9081/28462",
    "sg:postcode":"86720",
    "sg:province":"Bayern",
    "wof:name":"E. Eisele",
    "wof:placetype":"venue"
},
  "geometry": {"coordinates":[10.4858665466,48.8525695801],"type":"Point"}
}