{
  "type": "Feature",
  "properties": {
    "iso:country":"DE",
    "sg:address":"L\u00f6wenstr. 5",
    "sg:city":"Schongau",
    "sg:phone":"+49 8861/7243",
    "sg:postcode":"86956",
    "sg:province":"Bayern",
    "wof:name":"B\u00fccher Bauer E. K.",
    "wof:placetype":"venue"
},
  "geometry": {"coordinates":[10.896374,47.811363],"type":"Point"}
}