{
  "type": "Feature",
  "properties": {
    "iso:country":"DE",
    "sg:address":"Marktplatz 44",
    "sg:city":"Schwalbach",
    "sg:phone":"+49 6196/888858",
    "sg:postcode":"65824",
    "sg:province":"Hessen",
    "wof:name":"Ristorante Trastevere",
    "wof:placetype":"venue"
},
  "geometry": {"coordinates":[8.526974678,50.1542701721],"type":"Point"}
}