{
  "type": "Feature",
  "properties": {
    "iso:country":"DE",
    "sg:address":"Schwalbenweg 10",
    "sg:city":"Ludwigshafen",
    "sg:phone":"+49 621/691661",
    "sg:postcode":"67063",
    "sg:province":"Rheinland-Pfalz",
    "wof:name":"Lutz Hecke",
    "wof:placetype":"venue"
},
  "geometry": {"coordinates":[8.4200792313,49.4948883057],"type":"Point"}
}