{
  "type": "Feature",
  "properties": {
    "iso:country":"DE",
    "sg:address":"St\u00f6ckener Str. 69",
    "sg:city":"Langenhagen",
    "sg:postcode":"30855",
    "sg:province":"Niedersachsen",
    "wof:name":"Safe Immobilien- Und Handelsges. Mbh & Co.",
    "wof:placetype":"venue"
},
  "geometry": {"coordinates":[9.654164,52.440365],"type":"Point"}
}