{
  "type": "Feature",
  "properties": {
    "iso:country":"DE",
    "sg:address":"Hillenberg 3",
    "sg:city":"Hausen",
    "sg:phone":"+49 9778/350",
    "sg:postcode":"97647",
    "sg:province":"Bayern",
    "wof:name":"L. Glotzbach",
    "wof:placetype":"venue"
},
  "geometry": {"coordinates":[10.1029567719,50.4935073853],"type":"Point"}
}