{
  "type": "Feature",
  "properties": {
    "iso:country":"DE",
    "sg:address":"T\u00f6lzer Str. 15",
    "sg:city":"Gr\u00fcnwald",
    "sg:postcode":"82031",
    "sg:province":"Bayern",
    "wof:name":"Goal Verwaltungsgesellschaft Mbh & Co. Projekt Nr. 3 Kg",
    "wof:placetype":"venue"
},
  "geometry": {"coordinates":[11.5215749741,48.0355072021],"type":"Point"}
}