{
  "type": "Feature",
  "properties": {
    "iso:country":"DE",
    "sg:address":"Konrad-Duden-Str. 1",
    "sg:city":"Wesel",
    "sg:phone":"+49 281/6810091",
    "sg:postcode":"46485",
    "sg:province":"Nordrhein-Westfalen",
    "wof:name":"Wolfram Hu\u00dfmann Rechtsanwalt",
    "wof:placetype":"venue"
},
  "geometry": {"coordinates":[6.6288900375,51.6760597229],"type":"Point"}
}