{
  "type": "Feature",
  "properties": {
    "iso:country":"DE",
    "sg:address":"Poststr. 21",
    "sg:city":"Westerstede",
    "sg:phone":"+49 4488/79639",
    "sg:postcode":"26655",
    "sg:province":"Niedersachsen",
    "wof:name":"Apa Ambulanter Pflegedienst Ammerland",
    "wof:placetype":"venue"
},
  "geometry": {"coordinates":[7.905646,53.295322],"type":"Point"}
}