{
  "type": "Feature",
  "properties": {
    "iso:country":"DE",
    "sg:address":"Haller Str. 10",
    "sg:city":"B\u00fchlertann",
    "sg:phone":"+49 7973/1711",
    "sg:postcode":"74424",
    "sg:province":"Baden-W\u00fcrttemberg",
    "wof:name":"T. Fuchs & S\u00f6hne Baustoffe Kg",
    "wof:placetype":"venue"
},
  "geometry": {"coordinates":[9.9033222198,49.0414123535],"type":"Point"}
}