{
  "type": "Feature",
  "properties": {
    "iso:country":"DE",
    "sg:address":"Eduard-Pfeiffer-Str. 7-13",
    "sg:city":"Aalen",
    "sg:postcode":"73430",
    "sg:province":"Baden-W\u00fcrttemberg",
    "wof:name":"Kinopark Aalen Gmbh",
    "wof:placetype":"venue"
},
  "geometry": {"coordinates":[10.094346,48.848255],"type":"Point"}
}