{
  "type": "Feature",
  "properties": {
    "iso:country":"DE",
    "sg:address":"Alex-Horstmann-Str. 32",
    "sg:city":"G\u00f6rlitz",
    "sg:phone":"+49 3581/405339",
    "sg:postcode":"02826",
    "sg:province":"Sachsen",
    "wof:name":"Dr. Med. Gisela Reuter",
    "wof:placetype":"venue"
},
  "geometry": {"coordinates":[14.980926,51.139313],"type":"Point"}
}