{
  "type": "Feature",
  "properties": {
    "iso:country":"DE",
    "sg:address":"Wielandstr. 23",
    "sg:city":"Cuxhaven",
    "sg:phone":"+49 4723/3711",
    "sg:postcode":"27478",
    "sg:province":"Niedersachsen",
    "wof:name":"Cts Systemtechnik Dipl- Ing. Rolf Pawlowitz",
    "wof:placetype":"venue"
},
  "geometry": {"coordinates":[8.6634292603,53.8082275391],"type":"Point"}
}