{
  "type": "Feature",
  "properties": {
    "iso:country":"DE",
    "sg:address":"Hauptstr. 28",
    "sg:city":"Ebstorf",
    "sg:phone":"+49 4958/221041",
    "sg:postcode":"29574",
    "sg:province":"Niedersachsen",
    "wof:name":"Sparkasse Uelzen",
    "wof:placetype":"venue"
},
  "geometry": {"coordinates":[10.41325,53.028675],"type":"Point"}
}