{
  "type": "Feature",
  "properties": {
    "iso:country":"DE",
    "sg:address":"Cappenberger Str. 51",
    "sg:city":"L\u00fcnen",
    "sg:postcode":"44534",
    "sg:province":"Nordrhein-Westfalen",
    "wof:name":"Ecs-consult Handels- Und Vertriebsgesellschaft Mbh",
    "wof:placetype":"venue"
},
  "geometry": {"coordinates":[7.5256419182,51.6247596741],"type":"Point"}
}