{
  "type": "Feature",
  "properties": {
    "iso:country":"DE",
    "sg:address":"Birlinghovenerstrasse 23",
    "sg:city":"Sankt Augustin",
    "sg:postcode":"53757",
    "sg:province":"Nordrhein-Westfalen",
    "wof:name":"Online Service Bareuter",
    "wof:placetype":"venue"
},
  "geometry": {"coordinates":[7.22424,50.751942],"type":"Point"}
}