{
  "type": "Feature",
  "properties": {
    "iso:country":"DE",
    "sg:address":"Carl-L\u00fcer-Str. 13",
    "sg:city":"Osnabr\u00fcck",
    "sg:postcode":"49084",
    "sg:province":"Niedersachsen",
    "wof:name":"Beteiligungsgesellschaft Ogb- Osnabr\u00fccker Ger\u00fcstbau Mbh",
    "wof:placetype":"venue"
},
  "geometry": {"coordinates":[8.08552,52.262779],"type":"Point"}
}