{
  "type": "Feature",
  "properties": {
    "iso:country":"DE",
    "sg:address":"Geraer Str. 7",
    "sg:city":"Weida",
    "sg:phone":"+49 36603/62232",
    "sg:postcode":"07570",
    "sg:province":"Th\u00fcringen",
    "wof:name":"Annerose Schwengber",
    "wof:placetype":"venue"
},
  "geometry": {"coordinates":[12.0613632202,50.7736968994],"type":"Point"}
}