{
  "type": "Feature",
  "properties": {
    "iso:country":"DE",
    "sg:address":"Schweckendieckplatz 6",
    "sg:city":"Emden",
    "sg:postcode":"26721",
    "sg:province":"Niedersachsen",
    "wof:name":"Idb Investment Direktanlage Beteiligungs Gmbh & Co. Kg",
    "wof:placetype":"venue"
},
  "geometry": {"coordinates":[7.2040500641,53.3632202148],"type":"Point"}
}