{
  "type": "Feature",
  "properties": {
    "iso:country":"DE",
    "sg:address":"Rotenbergstr. 21",
    "sg:city":"Schwabach",
    "sg:phone":"+49 911/6370448",
    "sg:postcode":"91126",
    "sg:province":"Bayern",
    "wof:name":"Gerhard Humpen\u00f6der",
    "wof:placetype":"venue"
},
  "geometry": {"coordinates":[11.0265398026,49.3644981384],"type":"Point"}
}