{
  "type": "Feature",
  "properties": {
    "iso:country":"DE",
    "sg:address":"Menckestr. 42",
    "sg:city":"Leipzig",
    "sg:phone":"+49 341/5662110",
    "sg:postcode":"04155",
    "sg:province":"Sachsen",
    "wof:name":"Schillerhaus Stadtgeschichtliches Museum",
    "wof:placetype":"venue"
},
  "geometry": {"coordinates":[12.362872,51.358597],"type":"Point"}
}