{
  "type": "Feature",
  "properties": {
    "iso:country":"DE",
    "sg:address":"Spechtritzer Str. 3",
    "sg:city":"Rabenau",
    "sg:phone":"+49 351/6470080",
    "sg:postcode":"01734",
    "sg:province":"Sachsen",
    "wof:name":"L. K\u00f6rner",
    "wof:placetype":"venue"
},
  "geometry": {"coordinates":[13.6585826874,50.9536247253],"type":"Point"}
}