{
  "type": "Feature",
  "properties": {
    "iso:country":"DE",
    "sg:address":"Kleiststr. 6",
    "sg:city":"Peine",
    "sg:phone":"+49 5171/73081",
    "sg:postcode":"31224",
    "sg:province":"Niedersachsen",
    "wof:name":"Neta Rieger",
    "wof:placetype":"venue"
},
  "geometry": {"coordinates":[10.271652,52.331097],"type":"Point"}
}