{
  "type": "Feature",
  "properties": {
    "iso:country":"DE",
    "sg:address":"Balthasar-Neumann-Platz 28-30",
    "sg:city":"Br\u00fchl",
    "sg:phone":"+49 2232/945550",
    "sg:postcode":"50321",
    "sg:province":"Nordrhein-Westfalen",
    "wof:name":"Balthasar-apotheke",
    "wof:placetype":"venue"
},
  "geometry": {"coordinates":[6.896782,50.828327],"type":"Point"}
}