{
  "type": "Feature",
  "properties": {
    "iso:country":"DE",
    "sg:address":"M\u00fchlgasse 1",
    "sg:city":"Schwarzenbach a d Saale",
    "sg:phone":"+49 9284/8353",
    "sg:postcode":"95126",
    "sg:province":"Bayern",
    "wof:name":"K. H. Pick",
    "wof:placetype":"venue"
},
  "geometry": {"coordinates":[11.9709863663,50.2107086182],"type":"Point"}
}