{
  "type": "Feature",
  "properties": {
    "iso:country":"DE",
    "sg:address":"Heckenweg 10",
    "sg:city":"Thedinghausen",
    "sg:postcode":"27321",
    "sg:province":"Niedersachsen",
    "wof:name":"Rivaal Gmbh",
    "wof:placetype":"venue"
},
  "geometry": {"coordinates":[9.0107746124,52.9777145386],"type":"Point"}
}