{
  "type": "Feature",
  "properties": {
    "iso:country":"DE",
    "sg:address":"Kaninenbergh\u00f6he 50",
    "sg:city":"Essen",
    "sg:phone":"+49 201/264147",
    "sg:postcode":"45136",
    "sg:province":"Nordrhein-Westfalen",
    "wof:name":"Peter Schirlo Gmbh",
    "wof:placetype":"venue"
},
  "geometry": {"coordinates":[7.027587,51.431973],"type":"Point"}
}