{
  "type": "Feature",
  "properties": {
    "iso:country":"DE",
    "sg:address":"Schulstr. 30",
    "sg:city":"Hermsdorf",
    "sg:phone":"+49 36601/41016",
    "sg:postcode":"07629",
    "sg:province":"Th\u00fcringen",
    "wof:name":"Herrmann",
    "wof:placetype":"venue"
},
  "geometry": {"coordinates":[11.856496,50.89381],"type":"Point"}
}