{
  "type": "Feature",
  "properties": {
    "iso:country":"DE",
    "sg:address":"Schwere-Reiter-Str. 22",
    "sg:city":"M\u00fcnchen",
    "sg:phone":"+49 89/180608",
    "sg:postcode":"80797",
    "sg:province":"Bayern",
    "wof:name":"T. Pfeffer & J. Kudwien",
    "wof:placetype":"venue"
},
  "geometry": {"coordinates":[11.5559196472,48.1611671448],"type":"Point"}
}