{
  "type": "Feature",
  "properties": {
    "iso:country":"DE",
    "sg:address":"Rheinstr. 128",
    "sg:city":"Wilhelmshaven",
    "sg:phone":"+49 4421/9460",
    "sg:postcode":"26382",
    "sg:province":"Niedersachsen",
    "wof:name":"Kaisers Hotel Inh. U. Kaiser-konnerth E.kfr.",
    "wof:placetype":"venue"
},
  "geometry": {"coordinates":[8.1130990982,53.5173225403],"type":"Point"}
}