{
  "type": "Feature",
  "properties": {
    "iso:country":"DE",
    "sg:address":"Maarbachstr. 25",
    "sg:city":"Alfter",
    "sg:phone":"+49 228/646986",
    "sg:postcode":"53347",
    "sg:province":"Nordrhein-Westfalen",
    "wof:name":"H. Und U. Grau",
    "wof:placetype":"venue"
},
  "geometry": {"coordinates":[7.03456,50.717693],"type":"Point"}
}