{
  "type": "Feature",
  "properties": {
    "iso:country":"DE",
    "sg:address":"T\u00f6diweg 52",
    "sg:city":"Wangen",
    "sg:phone":"+49 7522/3074",
    "sg:postcode":"88239",
    "sg:province":"Baden-W\u00fcrttemberg",
    "wof:name":"Dieter Hammele Ingenieur",
    "wof:placetype":"venue"
},
  "geometry": {"coordinates":[9.8205451965,47.6839790344],"type":"Point"}
}