{
  "type": "Feature",
  "properties": {
    "iso:country":"DE",
    "sg:address":"Alter R\u00f6merweg 2",
    "sg:city":"Schleiden",
    "sg:phone":"+49 2444/2021",
    "sg:postcode":"53937",
    "sg:province":"Nordrhein-Westfalen",
    "wof:name":"Dr. Med. Markus Trutwin",
    "wof:placetype":"venue"
},
  "geometry": {"coordinates":[6.4933228493,50.5742149353],"type":"Point"}
}