{
  "type": "Feature",
  "properties": {
    "iso:country":"DE",
    "sg:address":"Schwarzacher Str. 1",
    "sg:city":"Deggendorf",
    "sg:phone":"+49 9901/1598",
    "sg:postcode":"94469",
    "sg:province":"Bayern",
    "wof:name":"Seebacher Wirt",
    "wof:placetype":"venue"
},
  "geometry": {"coordinates":[13.007935524,48.7955818176],"type":"Point"}
}