{
  "type": "Feature",
  "properties": {
    "iso:country":"DE",
    "sg:address":"Wilhelm-Herbst-Str. 5",
    "sg:city":"Bremen",
    "sg:phone":"+49 421/224904",
    "sg:postcode":"28359",
    "sg:province":"Bremen",
    "wof:name":"E. Nachtwey Rechtsanwalt",
    "wof:placetype":"venue"
},
  "geometry": {"coordinates":[8.851020813,53.1129493713],"type":"Point"}
}