{
  "type": "Feature",
  "properties": {
    "iso:country":"DE",
    "sg:address":"Hauptstr. 34",
    "sg:city":"R\u00f6srath",
    "sg:phone":"+49 2205/83396",
    "sg:postcode":"51503",
    "sg:province":"Nordrhein-Westfalen",
    "wof:name":"Nikolaus Christ Rechtsanwalt",
    "wof:placetype":"venue"
},
  "geometry": {"coordinates":[7.1827349663,50.896232605],"type":"Point"}
}