{
  "type": "Feature",
  "properties": {
    "iso:country":"DE",
    "sg:address":"In der Humes 8",
    "sg:city":"Eppelborn",
    "sg:phone":"+49 6881/6342",
    "sg:postcode":"66571",
    "sg:province":"Saarland",
    "wof:name":"P. Pink Bildhauerei",
    "wof:placetype":"venue"
},
  "geometry": {"coordinates":[6.99583,49.385242],"type":"Point"}
}