{
  "type": "Feature",
  "properties": {
    "iso:country":"DE",
    "sg:address":"Poppenb\u00fcttler Bogen 42",
    "sg:city":"Hamburg",
    "sg:phone":"+49 40",
    "sg:postcode":"22399",
    "sg:province":"Hamburg",
    "wof:name":"Rolf Soll Reisedienst",
    "wof:placetype":"venue"
},
  "geometry": {"coordinates":[10.0706920624,53.671043396],"type":"Point"}
}