{
  "type": "Feature",
  "properties": {
    "iso:country":"DE",
    "sg:address":"Rheinau 1",
    "sg:city":"M\u00fclheim-K\u00e4rlich",
    "sg:phone":"+49 2630/7576",
    "sg:postcode":"56218",
    "sg:province":"Rheinland-Pfalz",
    "wof:name":"Helmut R\u00f6nz",
    "wof:placetype":"venue"
},
  "geometry": {"coordinates":[7.499621,50.401962],"type":"Point"}
}