{
  "type": "Feature",
  "properties": {
    "iso:country":"DE",
    "sg:address":"Ru\u00dfdorfer Str. 23",
    "sg:city":"Limbach-Oberfrohna",
    "sg:postcode":"09212",
    "sg:province":"Sachsen",
    "wof:name":"W. Quade",
    "wof:placetype":"venue"
},
  "geometry": {"coordinates":[12.734267,50.861794],"type":"Point"}
}