{
  "type": "Feature",
  "properties": {
    "iso:country":"DE",
    "sg:address":"Wasserburger Str. 31",
    "sg:city":"Obing",
    "sg:phone":"+49 8624/87840",
    "sg:postcode":"83119",
    "sg:province":"Bayern",
    "wof:name":"Freilinger Beteiligungs-gmbh",
    "wof:placetype":"venue"
},
  "geometry": {"coordinates":[12.400138,48.002201],"type":"Point"}
}