{
  "type": "Feature",
  "properties": {
    "iso:country":"DE",
    "sg:address":"Bahnhofstr. 19",
    "sg:city":"Idstein",
    "sg:phone":"+49 6126/6301",
    "sg:postcode":"65510",
    "sg:province":"Hessen",
    "wof:name":"G. Sadeghian Damenbekleidung",
    "wof:placetype":"venue"
},
  "geometry": {"coordinates":[8.264217,50.219215],"type":"Point"}
}