{
  "type": "Feature",
  "properties": {
    "iso:country":"DE",
    "sg:address":"H\u00f6henweg 26",
    "sg:city":"Hagen",
    "sg:phone":"+49 5401/9710",
    "sg:postcode":"49170",
    "sg:province":"Niedersachsen",
    "wof:name":"Menke-fashion Gmbh & Co. Kg",
    "wof:placetype":"venue"
},
  "geometry": {"coordinates":[7.9900097847,52.1989898682],"type":"Point"}
}