{
  "type": "Feature",
  "properties": {
    "iso:country":"DE",
    "sg:address":"Prinzenstr. 101",
    "sg:city":"Kamp-Lintfort",
    "sg:postcode":"47475",
    "sg:province":"Nordrhein-Westfalen",
    "wof:name":"Espey Gmbh",
    "wof:placetype":"venue"
},
  "geometry": {"coordinates":[6.5455040932,51.5065155029],"type":"Point"}
}