{
  "type": "Feature",
  "properties": {
    "iso:country":"DE",
    "sg:address":"Sch\u00fctzenstr. 8",
    "sg:city":"D\u00f6bern",
    "sg:phone":"+49 35600/6716",
    "sg:postcode":"03159",
    "sg:province":"Brandenburg",
    "wof:name":"Ulrich Voigt",
    "wof:placetype":"venue"
},
  "geometry": {"coordinates":[14.5969190598,51.612537384],"type":"Point"}
}