{
  "type": "Feature",
  "properties": {
    "iso:country":"DE",
    "sg:address":"L\u00e4rchenweg 3",
    "sg:city":"Wiesbaum",
    "sg:phone":"+49 6593/98680",
    "sg:postcode":"54578",
    "sg:province":"Rheinland-Pfalz",
    "wof:name":"Schmitz Gmbh",
    "wof:placetype":"venue"
},
  "geometry": {"coordinates":[6.677741,50.341881],"type":"Point"}
}