{
  "type": "Feature",
  "properties": {
    "iso:country":"DE",
    "sg:address":"Im Harden 3",
    "sg:city":"Stelle",
    "sg:phone":"+49 4174/2473",
    "sg:postcode":"21435",
    "sg:province":"Niedersachsen",
    "wof:name":"Jens-peter Jensen Immobilienmakler",
    "wof:placetype":"venue"
},
  "geometry": {"coordinates":[10.103116,53.386002],"type":"Point"}
}