{
  "type": "Feature",
  "properties": {
    "iso:country":"DE",
    "sg:address":"Eichenstr. 10",
    "sg:city":"Neuried",
    "sg:phone":"+49 89/6145260",
    "sg:postcode":"82061",
    "sg:province":"Bayern",
    "wof:name":"Wmb Software Gmbh",
    "wof:placetype":"venue"
},
  "geometry": {"coordinates":[11.455280304,48.0868797302],"type":"Point"}
}