{
  "type": "Feature",
  "properties": {
    "iso:country":"DE",
    "sg:address":"Buchenweg 19a",
    "sg:city":"R\u00f6srath",
    "sg:phone":"+49 2205/6177",
    "sg:postcode":"51503",
    "sg:province":"Nordrhein-Westfalen",
    "wof:name":"Lothar Heinemann",
    "wof:placetype":"venue"
},
  "geometry": {"coordinates":[7.1642317772,50.9025993347],"type":"Point"}
}