{
  "type": "Feature",
  "properties": {
    "iso:country":"DE",
    "sg:address":"Ewaldstr. 59",
    "sg:city":"Herten",
    "sg:phone":"+49 2366/37676",
    "sg:postcode":"45699",
    "sg:province":"Nordrhein-Westfalen",
    "wof:name":"Provinzial Erlemeyer",
    "wof:placetype":"venue"
},
  "geometry": {"coordinates":[7.1423511505,51.5898094177],"type":"Point"}
}