{
  "type": "Feature",
  "properties": {
    "iso:country":"DE",
    "sg:address":"Julius-Heydegger-Str. 14",
    "sg:city":"Pforzheim",
    "sg:phone":"+49 7231/50269",
    "sg:postcode":"75181",
    "sg:province":"Baden-W\u00fcrttemberg",
    "wof:name":"Harald Sauer",
    "wof:placetype":"venue"
},
  "geometry": {"coordinates":[8.7426939011,48.9156227112],"type":"Point"}
}