{
  "type": "Feature",
  "properties": {
    "iso:country":"DE",
    "sg:address":"Elisabethenstr. 45",
    "sg:city":"Darmstadt",
    "sg:phone":"+49 6151/101015",
    "sg:postcode":"64283",
    "sg:province":"Hessen",
    "wof:name":"Tds Technical Documentation And Service Gmbh",
    "wof:placetype":"venue"
},
  "geometry": {"coordinates":[8.646785,49.869778],"type":"Point"}
}