{
  "type": "Feature",
  "properties": {
    "iso:country":"DE",
    "sg:address":"Hanauer Str. 7",
    "sg:city":"Pforzheim",
    "sg:phone":"+49 7231/66265",
    "sg:postcode":"75181",
    "sg:province":"Baden-W\u00fcrttemberg",
    "wof:name":"Helmut Klingel Gmbh",
    "wof:placetype":"venue"
},
  "geometry": {"coordinates":[8.7475996017,48.8860664368],"type":"Point"}
}