{
  "type": "Feature",
  "properties": {
    "iso:country":"DE",
    "sg:address":"Am Platz der Jugend 16",
    "sg:city":"Bernburg",
    "sg:postcode":"06406",
    "sg:province":"Sachsen-Anhalt",
    "wof:name":"Harry Hunger",
    "wof:placetype":"venue"
},
  "geometry": {"coordinates":[11.739536,51.80442],"type":"Point"}
}