{
  "type": "Feature",
  "properties": {
    "iso:country":"DE",
    "sg:address":"Schubertstr. 8",
    "sg:city":"D\u00fclmen",
    "sg:phone":"+49 2594/3870",
    "sg:postcode":"48249",
    "sg:province":"Nordrhein-Westfalen",
    "wof:name":"Hans-egon Goldberg",
    "wof:placetype":"venue"
},
  "geometry": {"coordinates":[7.269775,51.842983],"type":"Point"}
}