{
  "type": "Feature",
  "properties": {
    "iso:country":"DE",
    "sg:address":"Friedrichstr. 9",
    "sg:city":"Heidelberg",
    "sg:phone":"+49 6221/22576",
    "sg:postcode":"69117",
    "sg:province":"Baden-W\u00fcrttemberg",
    "wof:name":"Hochschule F\u00fcr J\u00fcdische Studien",
    "wof:placetype":"venue"
},
  "geometry": {"coordinates":[8.703151,49.41008],"type":"Point"}
}