{
  "type": "Feature",
  "properties": {
    "iso:country":"DE",
    "sg:address":"Kunigundenstr. 2",
    "sg:city":"Herzogenaurach",
    "sg:postcode":"91074",
    "sg:province":"Bayern",
    "wof:name":"We Web U Internetdienstleistungen Gmbh",
    "wof:placetype":"venue"
},
  "geometry": {"coordinates":[10.89153,49.570259],"type":"Point"}
}