{
  "type": "Feature",
  "properties": {
    "iso:country":"DE",
    "sg:address":"Hagenstr. 1",
    "sg:city":"Prerow / Dar\u00df",
    "sg:phone":"+49 38233/7000",
    "sg:postcode":"18375",
    "sg:province":"Mecklenburg-Vorpommern",
    "wof:name":"Rennhack - Ostseebad Prerow / Dar\u00df",
    "wof:placetype":"venue"
},
  "geometry": {"coordinates":[12.531304,54.387955],"type":"Point"}
}