{
  "type": "Feature",
  "properties": {
    "iso:country":"DE",
    "sg:city":"Berlin",
    "sg:postcode":"10715",
    "sg:province":"Berlin",
    "wof:name":"Der-congress",
    "wof:placetype":"venue"
},
  "geometry": {"coordinates":[13.32862,52.482979],"type":"Point"}
}