{
  "type": "Feature",
  "properties": {
    "iso:country":"DE",
    "sg:address":"An der Kirche 24",
    "sg:city":"M\u00f6nchengladbach",
    "sg:phone":"+49 2166/52387",
    "sg:postcode":"41189",
    "sg:province":"Nordrhein-Westfalen",
    "wof:name":"Heinrich Halcour",
    "wof:placetype":"venue"
},
  "geometry": {"coordinates":[6.4119868279,51.0951843262],"type":"Point"}
}