{
  "type": "Feature",
  "properties": {
    "iso:country":"DE",
    "sg:address":"Gusterather Str. 5",
    "sg:city":"Pluwig",
    "sg:phone":"+49 6588/1261",
    "sg:postcode":"54316",
    "sg:province":"Rheinland-Pfalz",
    "wof:name":"Rudi M\u00fcller",
    "wof:placetype":"venue"
},
  "geometry": {"coordinates":[6.711265,49.690636],"type":"Point"}
}