{
  "type": "Feature",
  "properties": {
    "iso:country":"DE",
    "sg:address":"Kappelbergweg 18",
    "sg:city":"Kappelrodeck",
    "sg:phone":"+49 7842/98931",
    "sg:postcode":"77876",
    "sg:province":"Baden-W\u00fcrttemberg",
    "wof:name":"Gerhard Hund",
    "wof:placetype":"venue"
},
  "geometry": {"coordinates":[8.120865,48.592842],"type":"Point"}
}