{
  "type": "Feature",
  "properties": {
    "iso:country":"DE",
    "sg:address":"Leitenh\u00f6he 32",
    "sg:city":"Herrsching",
    "sg:phone":"+49 8152/1894",
    "sg:postcode":"82211",
    "sg:province":"Bayern",
    "wof:name":"Christina Horn Rechtsanw\u00e4ltin",
    "wof:placetype":"venue"
},
  "geometry": {"coordinates":[11.1785335541,47.9916687012],"type":"Point"}
}