{
  "type": "Feature",
  "properties": {
    "iso:country":"DE",
    "sg:address":"Rote-M\u00fchle-Weg 75 a",
    "sg:city":"Wittstock",
    "sg:phone":"+49 3394/433167",
    "sg:postcode":"16909",
    "sg:province":"Brandenburg",
    "wof:name":"Klaus-dieter Schwenke",
    "wof:placetype":"venue"
},
  "geometry": {"coordinates":[12.4913129807,53.1806221008],"type":"Point"}
}