{
  "type": "Feature",
  "properties": {
    "iso:country":"DE",
    "sg:address":"Schulstr. 10",
    "sg:city":"Wasserburg",
    "sg:phone":"+49 8382/887948",
    "sg:postcode":"88142",
    "sg:province":"Bayern",
    "wof:name":"Anny Rechtsteiner Pension",
    "wof:placetype":"venue"
},
  "geometry": {"coordinates":[9.6363973618,47.567779541],"type":"Point"}
}