{
  "type": "Feature",
  "properties": {
    "iso:country":"DE",
    "sg:address":"Ludwigsburger Str. 91",
    "sg:city":"Freiberg",
    "sg:phone":"+49 7141/271756",
    "sg:postcode":"71691",
    "sg:province":"Baden-W\u00fcrttemberg",
    "wof:name":"R. Hoffmann",
    "wof:placetype":"venue"
},
  "geometry": {"coordinates":[9.2022457123,48.929473877],"type":"Point"}
}