{
  "type": "Feature",
  "properties": {
    "iso:country":"DE",
    "sg:address":"Borbecker Platz 3",
    "sg:city":"Essen",
    "sg:phone":"+49 201/688404",
    "sg:postcode":"45355",
    "sg:province":"Nordrhein-Westfalen",
    "wof:name":"Paul Gerardi",
    "wof:placetype":"venue"
},
  "geometry": {"coordinates":[6.9496722221,51.4738540649],"type":"Point"}
}