{
  "type": "Feature",
  "properties": {
    "iso:country":"DE",
    "sg:address":"Sauerstr. 12",
    "sg:city":"Frankfurt",
    "sg:phone":"+49 69/396434",
    "sg:postcode":"65934",
    "sg:province":"Hessen",
    "wof:name":"Emil M\u00fcller",
    "wof:placetype":"venue"
},
  "geometry": {"coordinates":[8.568157196,50.1018257141],"type":"Point"}
}