{
  "type": "Feature",
  "properties": {
    "iso:country":"DE",
    "sg:address":"B\u00fcckeburger Str. 12",
    "sg:city":"Porta Westfalica",
    "sg:phone":"+49 5722/4866",
    "sg:postcode":"32457",
    "sg:province":"Nordrhein-Westfalen",
    "wof:name":"Porta-moden Gmbh & Co. Kg",
    "wof:placetype":"venue"
},
  "geometry": {"coordinates":[9.0391740799,52.2397956848],"type":"Point"}
}