{
  "type": "Feature",
  "properties": {
    "iso:country":"DE",
    "sg:address":"Kellerstr. 4",
    "sg:city":"Coesfeld",
    "sg:phone":"+49 2541/980367",
    "sg:postcode":"48653",
    "sg:province":"Nordrhein-Westfalen",
    "wof:name":"Birgits Braut-boutique Birgit Bartsch",
    "wof:placetype":"venue"
},
  "geometry": {"coordinates":[7.16758,51.94268],"type":"Point"}
}