{
  "type": "Feature",
  "properties": {
    "iso:country":"DE",
    "sg:address":"Hamelner Str. 12",
    "sg:city":"Springe",
    "sg:phone":"+49 5041/64377",
    "sg:postcode":"31832",
    "sg:province":"Niedersachsen",
    "wof:name":"Gothaer-versicherung Wolfgang Rasche",
    "wof:placetype":"venue"
},
  "geometry": {"coordinates":[9.5461988449,52.2065391541],"type":"Point"}
}