{
  "type": "Feature",
  "properties": {
    "iso:country":"DE",
    "sg:address":"Diefenbachstr. 17",
    "sg:city":"Schotten",
    "sg:phone":"+49 6044/951829",
    "sg:postcode":"63679",
    "sg:province":"Hessen",
    "wof:name":"Meva Gmbh",
    "wof:placetype":"venue"
},
  "geometry": {"coordinates":[9.177989006,50.5231590271],"type":"Point"}
}