{
  "type": "Feature",
  "properties": {
    "iso:country":"DE",
    "sg:address":"Kippstr.",
    "sg:city":"Schriesheim",
    "sg:phone":"+49 6220/7398",
    "sg:postcode":"69198",
    "sg:province":"Baden-W\u00fcrttemberg",
    "wof:name":"Tennis- Und Squashcenter",
    "wof:placetype":"venue"
},
  "geometry": {"coordinates":[8.7371501923,49.4865913391],"type":"Point"}
}