{
  "type": "Feature",
  "properties": {
    "iso:country":"DE",
    "sg:address":"Transitstr 5",
    "sg:city":"Niepars",
    "sg:phone":"+49 5743/93060",
    "sg:postcode":"18442",
    "sg:province":"Mecklenburg-Vorpommern",
    "wof:name":"Dinilux Gmbh",
    "wof:placetype":"venue"
},
  "geometry": {"coordinates":[8.535595,52.338673],"type":"Point"}
}