{
  "type": "Feature",
  "properties": {
    "iso:country":"DE",
    "sg:address":"Lindenallee 91",
    "sg:city":"Essen",
    "sg:phone":"+49 201/235155",
    "sg:postcode":"45127",
    "sg:province":"Nordrhein-Westfalen",
    "wof:name":"Lindenst\u00fcbchen",
    "wof:placetype":"venue"
},
  "geometry": {"coordinates":[7.0072588921,51.4572257996],"type":"Point"}
}