{
  "type": "Feature",
  "properties": {
    "iso:country":"DE",
    "sg:address":"Am Trutzenberg 33",
    "sg:city":"K\u00f6ln",
    "sg:phone":"+49 221/3319125",
    "sg:postcode":"50676",
    "sg:province":"Nordrhein-Westfalen",
    "wof:name":"Zobel Software Gmbh",
    "wof:placetype":"venue"
},
  "geometry": {"coordinates":[6.9483189583,50.927066803],"type":"Point"}
}