{
  "type": "Feature",
  "properties": {
    "iso:country":"DE",
    "sg:address":"Westfalendamm 263",
    "sg:city":"Dortmund",
    "sg:postcode":"44141",
    "sg:province":"Nordrhein-Westfalen",
    "wof:name":"Asset Management Verm\u00f6gensberatungsges. Mbh",
    "wof:placetype":"venue"
},
  "geometry": {"coordinates":[7.508207798,51.5035705566],"type":"Point"}
}