{
  "type": "Feature",
  "properties": {
    "iso:country":"DE",
    "sg:address":"Marktplatz 18",
    "sg:city":"Wadern",
    "sg:phone":"+49 6871/91077",
    "sg:postcode":"66687",
    "sg:province":"Saarland",
    "wof:name":"Brunnen-apotheke",
    "wof:placetype":"venue"
},
  "geometry": {"coordinates":[6.890025,49.539951],"type":"Point"}
}