{
  "type": "Feature",
  "properties": {
    "iso:country":"DE",
    "sg:address":"Hauptstr. 11",
    "sg:city":"Ostritz",
    "sg:phone":"+49 35823/86781",
    "sg:postcode":"02899",
    "sg:province":"Sachsen",
    "wof:name":"H. Arnold",
    "wof:placetype":"venue"
},
  "geometry": {"coordinates":[14.9435367584,51.0355567932],"type":"Point"}
}