{
  "type": "Feature",
  "properties": {
    "iso:country":"DE",
    "sg:address":"Lange Str. 24",
    "sg:city":"Waiblingen",
    "sg:phone":"+49 7151/959830",
    "sg:postcode":"71332",
    "sg:province":"Baden-W\u00fcrttemberg",
    "wof:name":"C. Villinger-zeller Eisenwaren",
    "wof:placetype":"venue"
},
  "geometry": {"coordinates":[9.316204071,48.8331451416],"type":"Point"}
}