{
  "type": "Feature",
  "properties": {
    "iso:country":"DE",
    "sg:address":"Berliner Str. 50",
    "sg:city":"Bad M\u00fcnster-Ebernburg",
    "sg:phone":"+49 6708/1597",
    "sg:postcode":"55583",
    "sg:province":"Rheinland-Pfalz",
    "wof:name":"Lindenstube",
    "wof:placetype":"venue"
},
  "geometry": {"coordinates":[7.8455691338,49.8112411499],"type":"Point"}
}