{
  "type": "Feature",
  "properties": {
    "iso:country":"DE",
    "sg:city":"Simmern",
    "sg:postcode":"56337",
    "sg:province":"Rheinland-Pfalz",
    "wof:name":"Gesamtbau Betrieb Kulasza Gmbh",
    "wof:placetype":"venue"
},
  "geometry": {"coordinates":[7.67708,50.390419],"type":"Point"}
}