{
  "type": "Feature",
  "properties": {
    "iso:country":"DE",
    "sg:address":"Hartfeldstr. 12",
    "sg:city":"Neukirchen-Vluyn",
    "sg:phone":"+49 2845/2348",
    "sg:postcode":"47506",
    "sg:province":"Nordrhein-Westfalen",
    "wof:name":"D. Ophey",
    "wof:placetype":"venue"
},
  "geometry": {"coordinates":[6.542738,51.436687],"type":"Point"}
}