{
  "type": "Feature",
  "properties": {
    "iso:country":"DE",
    "sg:address":"Schulstr. 31",
    "sg:city":"Delmenhorst",
    "sg:phone":"+49 4221/17571",
    "sg:postcode":"27749",
    "sg:province":"Niedersachsen",
    "wof:name":"Frank M\u00fcller",
    "wof:placetype":"venue"
},
  "geometry": {"coordinates":[8.6308546066,53.0517616272],"type":"Point"}
}