{
  "type": "Feature",
  "properties": {
    "iso:country":"DE",
    "sg:address":"Poststra\u00dfe 2",
    "sg:city":"Gottmadingen",
    "sg:phone":"+49 7731/798879",
    "sg:postcode":"78244",
    "sg:province":"Baden-W\u00fcrttemberg",
    "wof:name":"Euro Pub Gottmadingen Kreis Kn",
    "wof:placetype":"venue"
},
  "geometry": {"coordinates":[8.776126,47.736885],"type":"Point"}
}