{
  "type": "Feature",
  "properties": {
    "iso:country":"DE",
    "sg:address":"Heinrichstr. 118",
    "sg:city":"D\u00fcsseldorf",
    "sg:phone":"+49 211/622343",
    "sg:postcode":"40239",
    "sg:province":"Nordrhein-Westfalen",
    "wof:name":"Franciskus-apotheke Inh. Klaus Feltgen",
    "wof:placetype":"venue"
},
  "geometry": {"coordinates":[6.802715,51.249584],"type":"Point"}
}