{
  "type": "Feature",
  "properties": {
    "iso:country":"DE",
    "sg:address":"Panzenlaake 38a",
    "sg:city":"Bremen",
    "sg:phone":"+49 421/828421",
    "sg:postcode":"28279",
    "sg:province":"Bremen",
    "wof:name":"Axel Und Ilonka Schr\u00f6der",
    "wof:placetype":"venue"
},
  "geometry": {"coordinates":[8.8429660797,53.0275917053],"type":"Point"}
}