{
  "type": "Feature",
  "properties": {
    "iso:country":"DE",
    "sg:address":"Dr.-Wilhelm-K\u00fclz-Str. 1a",
    "sg:city":"R\u00fcdersdorf",
    "sg:postcode":"15562",
    "sg:province":"Brandenburg",
    "wof:name":"Drogerie",
    "wof:placetype":"venue"
},
  "geometry": {"coordinates":[13.813715,52.469303],"type":"Point"}
}