{
  "type": "Feature",
  "properties": {
    "iso:country":"DE",
    "sg:address":"Dohnensteig 7 a",
    "sg:city":"Berlin",
    "sg:phone":"+49 30/4047707",
    "sg:postcode":"13467",
    "sg:province":"Berlin",
    "wof:name":"Schmidt",
    "wof:placetype":"venue"
},
  "geometry": {"coordinates":[13.2897558212,52.6072044373],"type":"Point"}
}