{
  "type": "Feature",
  "properties": {
    "iso:country":"DE",
    "sg:address":"Schulstr. 36",
    "sg:city":"Reinbek",
    "sg:postcode":"21465",
    "sg:province":"Schleswig-Holstein",
    "wof:name":"Fahrschule Brammer Gmbh",
    "wof:placetype":"venue"
},
  "geometry": {"coordinates":[10.247418,53.516136],"type":"Point"}
}