{
  "type": "Feature",
  "properties": {
    "iso:country":"DE",
    "sg:address":"Vogelherd 5",
    "sg:city":"Alfeld",
    "sg:phone":"+49 9157/1232",
    "sg:postcode":"91236",
    "sg:province":"Bayern",
    "wof:name":"G. Lippert",
    "wof:placetype":"venue"
},
  "geometry": {"coordinates":[11.5435276031,49.4115524292],"type":"Point"}
}