{
  "type": "Feature",
  "properties": {
    "iso:country":"DE",
    "sg:address":"Humboldtstr. 20",
    "sg:city":"Gladbeck",
    "sg:phone":"+49 2043/26570",
    "sg:postcode":"45964",
    "sg:province":"Nordrhein-Westfalen",
    "wof:name":"Novelle",
    "wof:placetype":"venue"
},
  "geometry": {"coordinates":[6.9921011925,51.5745506287],"type":"Point"}
}