{
  "type": "Feature",
  "properties": {
    "iso:country":"DE",
    "sg:address":"Holunderweg 11",
    "sg:city":"Gusterath",
    "sg:phone":"+49 6588/99122",
    "sg:postcode":"54317",
    "sg:province":"Rheinland-Pfalz",
    "wof:name":"Lerch Wohnungsbau Gmbh",
    "wof:placetype":"venue"
},
  "geometry": {"coordinates":[6.7161841393,49.7026939392],"type":"Point"}
}