{
  "type": "Feature",
  "properties": {
    "iso:country":"DE",
    "sg:address":"Innere Fr\u00fchlingstr. 21 a",
    "sg:city":"Straubing",
    "sg:phone":"+49 9421/80400",
    "sg:postcode":"94315",
    "sg:province":"Bayern",
    "wof:name":"Franz Edenhofer Heissmangel",
    "wof:placetype":"venue"
},
  "geometry": {"coordinates":[12.5771856308,48.8794250488],"type":"Point"}
}