{
  "type": "Feature",
  "properties": {
    "iso:country":"DE",
    "sg:address":"In der Helle 8",
    "sg:city":"Wetter",
    "sg:phone":"+49 2335/62410",
    "sg:postcode":"58300",
    "sg:province":"Nordrhein-Westfalen",
    "wof:name":"Gustav Schmitz",
    "wof:placetype":"venue"
},
  "geometry": {"coordinates":[7.3664979935,51.3644676208],"type":"Point"}
}