{
  "type": "Feature",
  "properties": {
    "iso:country":"DE",
    "sg:address":"Rembrandtstr. 11",
    "sg:city":"Berlin",
    "sg:phone":"+49 30/8556060",
    "sg:postcode":"12157",
    "sg:province":"Berlin",
    "wof:name":"G\u00fcnter Richter Hi-fi-stereo-center",
    "wof:placetype":"venue"
},
  "geometry": {"coordinates":[13.3408107758,52.468914032],"type":"Point"}
}