{
  "type": "Feature",
  "properties": {
    "iso:country":"DE",
    "sg:address":"Alter Flugplatz 23",
    "sg:city":"Vechta",
    "sg:phone":"+49 4441/4302",
    "sg:postcode":"49377",
    "sg:province":"Niedersachsen",
    "wof:name":"Logemann-possehl",
    "wof:placetype":"venue"
},
  "geometry": {"coordinates":[8.259028,52.72224],"type":"Point"}
}