{
  "type": "Feature",
  "properties": {
    "iso:country":"DE",
    "sg:address":"Ritterstr. 13",
    "sg:city":"Chemnitz",
    "sg:postcode":"09111",
    "sg:province":"Sachsen",
    "wof:name":"Heiko Richter",
    "wof:placetype":"venue"
},
  "geometry": {"coordinates":[12.927995,50.825867],"type":"Point"}
}