{
  "type": "Feature",
  "properties": {
    "iso:country":"DE",
    "sg:address":"Am Hirschgraben 7",
    "sg:city":"Heusenstamm",
    "sg:phone":"+49 6106/5240",
    "sg:postcode":"63150",
    "sg:province":"Hessen",
    "wof:name":"Norbert D. May Rechtsanwalt Und Notar",
    "wof:placetype":"venue"
},
  "geometry": {"coordinates":[8.8562097549,50.0497436523],"type":"Point"}
}