{
  "type": "Feature",
  "properties": {
    "iso:country":"DE",
    "sg:address":"Schlossm\u00fchlendamm 8-10",
    "sg:city":"Hamburg",
    "sg:phone":"+49 40/7673940",
    "sg:postcode":"21073",
    "sg:province":"Hamburg",
    "wof:name":"Industriegewerkschaft Bergbau Chemie Energie",
    "wof:placetype":"venue"
},
  "geometry": {"coordinates":[9.98214,53.461555],"type":"Point"}
}