{
  "type": "Feature",
  "properties": {
    "iso:country":"DE",
    "sg:address":"Th\u00fcringer Str.",
    "sg:city":"Gera",
    "sg:phone":"+49 365/435590",
    "sg:postcode":"07552",
    "sg:province":"Th\u00fcringen",
    "wof:name":"Praktiker Bau- Und Heimwerkermarkt",
    "wof:placetype":"venue"
},
  "geometry": {"coordinates":[12.0836553574,50.9050254822],"type":"Point"}
}