{
  "type": "Feature",
  "properties": {
    "iso:country":"DE",
    "sg:address":"Oststr. 34",
    "sg:city":"Bochum",
    "sg:phone":"+49 2327/89252",
    "sg:postcode":"44866",
    "sg:province":"Nordrhein-Westfalen",
    "wof:name":"Peter Hartbecke",
    "wof:placetype":"venue"
},
  "geometry": {"coordinates":[7.1355929375,51.4806442261],"type":"Point"}
}