{
  "type": "Feature",
  "properties": {
    "iso:country":"DE",
    "sg:address":"Hauptstr. 243",
    "sg:city":"Bergisch Gladbach",
    "sg:phone":"+49 2202/30911",
    "sg:postcode":"51465",
    "sg:province":"Nordrhein-Westfalen",
    "wof:name":"Ottfried Brock Monika M\u00fcller-erlinghagen",
    "wof:placetype":"venue"
},
  "geometry": {"coordinates":[7.1339039803,50.9918136597],"type":"Point"}
}