{
  "type": "Feature",
  "properties": {
    "iso:country":"DE",
    "sg:address":"Maastrichter Str.",
    "sg:city":"K\u00f6ln",
    "sg:phone":"+49 221/252358",
    "sg:postcode":"50672",
    "sg:province":"Nordrhein-Westfalen",
    "wof:name":"Parkhaus Hohenzollernring",
    "wof:placetype":"venue"
},
  "geometry": {"coordinates":[6.936270237,50.9384231567],"type":"Point"}
}