{
  "type": "Feature",
  "properties": {
    "iso:country":"DE",
    "sg:address":"K\u00f6rnebachstr. 77-79",
    "sg:city":"Dortmund",
    "sg:phone":"+49 4923/1525023",
    "sg:postcode":"44143",
    "sg:province":"Nordrhein-Westfalen",
    "wof:name":"Gerald Sommer",
    "wof:placetype":"venue"
},
  "geometry": {"coordinates":[7.487602,51.519962],"type":"Point"}
}