{
  "type": "Feature",
  "properties": {
    "iso:country":"DE",
    "sg:address":"Florianstr. 4",
    "sg:city":"Kohlberg",
    "sg:phone":"+49 7123/71071",
    "sg:postcode":"72664",
    "sg:province":"Baden-W\u00fcrttemberg",
    "wof:name":"Rolf Haas",
    "wof:placetype":"venue"
},
  "geometry": {"coordinates":[9.329217,48.556076],"type":"Point"}
}