{
  "type": "Feature",
  "properties": {
    "iso:country":"DE",
    "sg:address":"Gerichtsstr 3",
    "sg:city":"Wissen",
    "sg:phone":"+49 2742/71248",
    "sg:postcode":"57537",
    "sg:province":"Rheinland-Pfalz",
    "wof:name":"Raiffeisenbank 2000 Eg",
    "wof:placetype":"venue"
},
  "geometry": {"coordinates":[7.737434,50.781895],"type":"Point"}
}