{
  "type": "Feature",
  "properties": {
    "iso:country":"DE",
    "sg:address":"Henleinweg 1",
    "sg:city":"Balingen",
    "sg:phone":"+49 7433/21152",
    "sg:postcode":"72336",
    "sg:province":"Baden-W\u00fcrttemberg",
    "wof:name":"M. Schlotter",
    "wof:placetype":"venue"
},
  "geometry": {"coordinates":[8.85879,48.267159],"type":"Point"}
}