{
  "type": "Feature",
  "properties": {
    "iso:country":"DE",
    "sg:address":"Dreihausen 1",
    "sg:city":"Welver",
    "sg:phone":"+49 2384/3900",
    "sg:postcode":"59514",
    "sg:province":"Nordrhein-Westfalen",
    "wof:name":"Reinhold Palz",
    "wof:placetype":"venue"
},
  "geometry": {"coordinates":[7.918869,51.612179],"type":"Point"}
}