{
  "type": "Feature",
  "properties": {
    "iso:country":"DE",
    "sg:address":"Am Rosengarten 23",
    "sg:city":"Fulda",
    "sg:phone":"+49 661/76059",
    "sg:postcode":"36037",
    "sg:province":"Hessen",
    "wof:name":"Dr. Werner Von Rhein",
    "wof:placetype":"venue"
},
  "geometry": {"coordinates":[9.671582222,50.5479164124],"type":"Point"}
}