{
  "type": "Feature",
  "properties": {
    "iso:country":"DE",
    "sg:address":"An den Auewiesen 7",
    "sg:city":"Ahlerstedt",
    "sg:phone":"+49 4166/7231",
    "sg:postcode":"21702",
    "sg:province":"Niedersachsen",
    "wof:name":"Eckhard Fr\u00f6se",
    "wof:placetype":"venue"
},
  "geometry": {"coordinates":[9.425359726,53.4291496277],"type":"Point"}
}