{
  "type": "Feature",
  "properties": {
    "iso:country":"DE",
    "sg:address":"Bruno-Dost-Str. 1 a",
    "sg:city":"Schneeberg",
    "sg:phone":"+49 3772/55252",
    "sg:postcode":"08289",
    "sg:province":"Sachsen",
    "wof:name":"J\u00f6rg Neubert",
    "wof:placetype":"venue"
},
  "geometry": {"coordinates":[12.6310796738,50.6049995422],"type":"Point"}
}