{
  "type": "Feature",
  "properties": {
    "iso:country":"DE",
    "sg:address":"Feldbergstr. 19",
    "sg:city":"Wiesbaden",
    "sg:phone":"+49 611/9813116",
    "sg:postcode":"65187",
    "sg:province":"Hessen",
    "wof:name":"Anja Verborg Rechtsanw\u00e4ltin",
    "wof:placetype":"venue"
},
  "geometry": {"coordinates":[8.2451457977,50.0577774048],"type":"Point"}
}