{
  "type": "Feature",
  "properties": {
    "iso:country":"DE",
    "sg:address":"Kirchberg 1",
    "sg:city":"Aidhausen",
    "sg:postcode":"97491",
    "sg:province":"Bayern",
    "wof:name":"Bali-wohnkunst",
    "wof:placetype":"venue"
},
  "geometry": {"coordinates":[10.43673,50.155479],"type":"Point"}
}