{
  "type": "Feature",
  "properties": {
    "iso:country":"DE",
    "sg:address":"Gartenweg 2",
    "sg:city":"Haiterbach",
    "sg:phone":"+49 7456/1291",
    "sg:postcode":"72221",
    "sg:province":"Baden-W\u00fcrttemberg",
    "wof:name":"Hans Scheu",
    "wof:placetype":"venue"
},
  "geometry": {"coordinates":[8.6493291855,48.5252304077],"type":"Point"}
}