{
  "type": "Feature",
  "properties": {
    "iso:country":"DE",
    "sg:address":"Kupferstr. 48 A",
    "sg:city":"Stuttgart",
    "sg:phone":"+49 711/7800403",
    "sg:postcode":"70565",
    "sg:province":"Baden-W\u00fcrttemberg",
    "wof:name":"Hartmut Lechner Ingenieur",
    "wof:placetype":"venue"
},
  "geometry": {"coordinates":[9.1224489212,48.7271575928],"type":"Point"}
}