{
  "type": "Feature",
  "properties": {
    "iso:country":"DE",
    "sg:address":"Mondstr. 158",
    "sg:city":"M\u00fcnster",
    "sg:phone":"+49 251/383230",
    "sg:postcode":"48155",
    "sg:province":"Nordrhein-Westfalen",
    "wof:name":"Stadtteilauto Car Sharing M\u00fcnster Gmbh",
    "wof:placetype":"venue"
},
  "geometry": {"coordinates":[7.6768307686,51.9561958313],"type":"Point"}
}