{
  "type": "Feature",
  "properties": {
    "iso:country":"DE",
    "sg:address":"Neustadt 458",
    "sg:city":"Landshut",
    "sg:phone":"+49 871/2068",
    "sg:postcode":"84028",
    "sg:province":"Bayern",
    "wof:name":"Abr Reiseb\u00fcro Gmbh",
    "wof:placetype":"venue"
},
  "geometry": {"coordinates":[12.1538896561,48.5361175537],"type":"Point"}
}