{
  "type": "Feature",
  "properties": {
    "iso:country":"DE",
    "sg:address":"Wimpelstr. 23",
    "sg:city":"Ludwigshafen",
    "sg:phone":"+49 621/698421",
    "sg:postcode":"67063",
    "sg:province":"Rheinland-Pfalz",
    "wof:name":"Inge Rupp Kohlen-handlung",
    "wof:placetype":"venue"
},
  "geometry": {"coordinates":[8.408808,49.496346],"type":"Point"}
}