{
  "type": "Feature",
  "properties": {
    "iso:country":"DE",
    "sg:address":"Goerdelerstr. 27",
    "sg:city":"Rostock",
    "sg:phone":"+49 381/6009090",
    "sg:postcode":"18069",
    "sg:province":"Mecklenburg-Vorpommern",
    "wof:name":"Medizintechnik Arztbedarf Sanit\u00e4tshaus Holger Graf",
    "wof:placetype":"venue"
},
  "geometry": {"coordinates":[12.01487,54.10136],"type":"Point"}
}