{
  "type": "Feature",
  "properties": {
    "iso:country":"DE",
    "sg:address":"Alte Industriestr. 3",
    "sg:city":"Cuxhaven",
    "sg:phone":"+49 4721/72307",
    "sg:postcode":"27472",
    "sg:province":"Niedersachsen",
    "wof:name":"Ligar Labor- Und Ingenieurges. F\u00fcr Altlasten U. Recycling Mbh",
    "wof:placetype":"venue"
},
  "geometry": {"coordinates":[8.7114896774,53.8504447937],"type":"Point"}
}