{
  "type": "Feature",
  "properties": {
    "iso:country":"DE",
    "sg:address":"Ruppertenr\u00f6der Str. 24",
    "sg:city":"M\u00fccke",
    "sg:phone":"+49 6400/6931",
    "sg:postcode":"35325",
    "sg:province":"Hessen",
    "wof:name":"W. Gr\u00fcn",
    "wof:placetype":"venue"
},
  "geometry": {"coordinates":[9.0657367706,50.6295928955],"type":"Point"}
}