{
  "type": "Feature",
  "properties": {
    "iso:country":"DE",
    "sg:address":"Varrentrappstr 11",
    "sg:city":"Braunschweig",
    "sg:phone":"+49 531/256070",
    "sg:postcode":"38114",
    "sg:province":"Niedersachsen",
    "wof:name":"H\u00f6rmann Gmbh & Co",
    "wof:placetype":"venue"
},
  "geometry": {"coordinates":[10.508053,52.280731],"type":"Point"}
}