{
  "type": "Feature",
  "properties": {
    "iso:country":"DE",
    "sg:address":"In der Gasse 8",
    "sg:city":"R\u00fcbenau",
    "sg:phone":"+49 172 3469790",
    "sg:postcode":"09526",
    "sg:province":"Sachsen",
    "wof:name":"Webshop Erzgebirge - Artikel Aus Dem Erzgebirge",
    "wof:placetype":"venue"
},
  "geometry": {"coordinates":[13.34295,50.669258],"type":"Point"}
}