{
  "type": "Feature",
  "properties": {
    "iso:country":"DE",
    "sg:address":"Alexander-Bretz-Str. 4",
    "sg:city":"Gensingen",
    "sg:phone":"+49 6727/952031",
    "sg:postcode":"55457",
    "sg:province":"Rheinland-Pfalz",
    "wof:name":"Depotpack Lagerungsges. Mbh",
    "wof:placetype":"venue"
},
  "geometry": {"coordinates":[7.937809,49.89909],"type":"Point"}
}