{
  "type": "Feature",
  "properties": {
    "iso:country":"DE",
    "sg:address":"Mainstr. 34",
    "sg:city":"Blankenfelde",
    "sg:phone":"+49 3379/372540",
    "sg:postcode":"15827",
    "sg:province":"Brandenburg",
    "wof:name":"Dietrich Rohde Bildhauer",
    "wof:placetype":"venue"
},
  "geometry": {"coordinates":[13.419046,52.348591],"type":"Point"}
}