{
  "type": "Feature",
  "properties": {
    "iso:country":"DE",
    "sg:address":"Hermann-L\u00f6ns-Str. 107",
    "sg:city":"Aachen",
    "sg:phone":"+49 241/928870",
    "sg:postcode":"52078",
    "sg:province":"Nordrhein-Westfalen",
    "wof:name":"Stahl-alu Ortmanns & Sohn Gmbh",
    "wof:placetype":"venue"
},
  "geometry": {"coordinates":[6.168901,50.759644],"type":"Point"}
}