{
  "type": "Feature",
  "properties": {
    "iso:country":"DE",
    "sg:address":"Ebereschenallee 16",
    "sg:city":"Zeuthen",
    "sg:phone":"+49 33762/71903",
    "sg:postcode":"15738",
    "sg:province":"Brandenburg",
    "wof:name":"Heinz Firus Ingenieur",
    "wof:placetype":"venue"
},
  "geometry": {"coordinates":[13.6214342117,52.3464775085],"type":"Point"}
}