{
  "type": "Feature",
  "properties": {
    "iso:country":"DE",
    "sg:address":"Enhofer Str. 47 Ot Wilflingen",
    "sg:city":"Langenenslingen",
    "sg:phone":"+49 4971/5330503",
    "sg:postcode":"88515",
    "sg:province":"Baden-W\u00fcrttemberg",
    "wof:name":"Rusko-formen Gmbh",
    "wof:placetype":"venue"
},
  "geometry": {"coordinates":[9.424054,48.681553],"type":"Point"}
}