{
  "type": "Feature",
  "properties": {
    "iso:country":"DE",
    "sg:address":"Kamenzer Str. 8",
    "sg:city":"Bischofswerda",
    "sg:phone":"+49 3594/701464",
    "sg:postcode":"01877",
    "sg:province":"Sachsen",
    "wof:name":"Marion Kettner",
    "wof:placetype":"venue"
},
  "geometry": {"coordinates":[14.179195,51.128437],"type":"Point"}
}