{
  "type": "Feature",
  "properties": {
    "iso:country":"DE",
    "sg:address":"Wei\u00dfenseer Str. 3",
    "sg:city":"S\u00f6mmerda",
    "sg:phone":"+49 3634/622382",
    "sg:postcode":"99610",
    "sg:province":"Th\u00fcringen",
    "wof:name":"Klaus G\u00f6tze",
    "wof:placetype":"venue"
},
  "geometry": {"coordinates":[11.1172618866,51.1629371643],"type":"Point"}
}