{
  "type": "Feature",
  "properties": {
    "iso:country":"DE",
    "sg:address":"Gossenbusch 3",
    "sg:city":"Langenfeld",
    "sg:phone":"+49 212/2642801",
    "sg:postcode":"40764",
    "sg:province":"Nordrhein-Westfalen",
    "wof:name":"C.m.media Langenfeld",
    "wof:placetype":"venue"
},
  "geometry": {"coordinates":[6.9928798676,51.1416282654],"type":"Point"}
}