{
  "type": "Feature",
  "properties": {
    "iso:country":"DE",
    "sg:address":"Alte Schulstra\u00dfe 9",
    "sg:city":"L\u00fcbow (b.Wismar)",
    "sg:phone":"+49 3841/780173",
    "sg:postcode":"23972",
    "sg:province":"Mecklenburg-Vorpommern",
    "wof:name":"Investmentfonds Paradies",
    "wof:placetype":"venue"
},
  "geometry": {"coordinates":[11.519370079,53.8514785767],"type":"Point"}
}