{
  "type": "Feature",
  "properties": {
    "iso:country":"DE",
    "sg:address":"Rh\u00f6ndorfer Str. 85",
    "sg:city":"Bad Honnef",
    "sg:postcode":"53604",
    "sg:province":"Nordrhein-Westfalen",
    "wof:name":"Tx Internetlogistik Gmbh",
    "wof:placetype":"venue"
},
  "geometry": {"coordinates":[7.21661,50.654491],"type":"Point"}
}