{
  "type": "Feature",
  "properties": {
    "iso:country":"DE",
    "sg:address":"H\u00f6nnestr. 31",
    "sg:city":"Neuenrade",
    "sg:phone":"+49 2394/180",
    "sg:postcode":"58809",
    "sg:province":"Nordrhein-Westfalen",
    "wof:name":"Smb Gmbh",
    "wof:placetype":"venue"
},
  "geometry": {"coordinates":[7.814261,51.292309],"type":"Point"}
}