{
  "type": "Feature",
  "properties": {
    "iso:country":"DE",
    "sg:address":"Obermarkt 12",
    "sg:city":"Worms",
    "sg:phone":"+49 6241/26484",
    "sg:postcode":"67547",
    "sg:province":"Rheinland-Pfalz",
    "wof:name":"Karl-dieter Schiffer Rechtsanwalt",
    "wof:placetype":"venue"
},
  "geometry": {"coordinates":[8.3613395691,49.6318473816],"type":"Point"}
}