{
  "type": "Feature",
  "properties": {
    "iso:country":"DE",
    "sg:address":"Marktplatz 21",
    "sg:city":"Tann",
    "sg:postcode":"84367",
    "sg:province":"Bayern",
    "wof:name":"Marien-apotheke Gerhard Windisch",
    "wof:placetype":"venue"
},
  "geometry": {"coordinates":[12.893171,48.314667],"type":"Point"}
}