{
  "type": "Feature",
  "properties": {
    "iso:country":"DE",
    "sg:address":"Holzgrefestr. 2",
    "sg:city":"Springe",
    "sg:phone":"+49 5044/570",
    "sg:postcode":"31832",
    "sg:province":"Niedersachsen",
    "wof:name":"Manfred Schlawitz",
    "wof:placetype":"venue"
},
  "geometry": {"coordinates":[9.658838,52.174587],"type":"Point"}
}