{
  "type": "Feature",
  "properties": {
    "iso:country":"DE",
    "sg:address":"Bahnhofstr. 4",
    "sg:city":"Bad Wildungen",
    "sg:phone":"+49 5621/3812",
    "sg:postcode":"34537",
    "sg:province":"Hessen",
    "wof:name":"Wilh. Arc Inh. Rohrmann",
    "wof:placetype":"venue"
},
  "geometry": {"coordinates":[9.1266136169,51.120891571],"type":"Point"}
}