{
  "type": "Feature",
  "properties": {
    "iso:country":"DE",
    "sg:address":"Barf\u00fc\u00dferstr. 6",
    "sg:city":"Nordhausen",
    "sg:phone":"+49 3631/993399",
    "sg:postcode":"99734",
    "sg:province":"Th\u00fcringen",
    "wof:name":"Nord Pool Gmbh",
    "wof:placetype":"venue"
},
  "geometry": {"coordinates":[10.7922792435,51.5043830872],"type":"Point"}
}