{
  "type": "Feature",
  "properties": {
    "iso:country":"DE",
    "sg:address":"Neustr. 57",
    "sg:city":"Bonn",
    "sg:phone":"+49 228/465717",
    "sg:postcode":"53225",
    "sg:province":"Nordrhein-Westfalen",
    "wof:name":"Erwin-josef Thiebes",
    "wof:placetype":"venue"
},
  "geometry": {"coordinates":[7.126902,50.736717],"type":"Point"}
}