{
  "type": "Feature",
  "properties": {
    "iso:country":"DE",
    "sg:address":"Am Stadion 7",
    "sg:city":"Oberndorf",
    "sg:phone":"+49 7423/2345",
    "sg:postcode":"78727",
    "sg:province":"Baden-W\u00fcrttemberg",
    "wof:name":"Peter Braun",
    "wof:placetype":"venue"
},
  "geometry": {"coordinates":[8.5810213089,48.2856559753],"type":"Point"}
}