{
  "type": "Feature",
  "properties": {
    "iso:country":"DE",
    "sg:address":"Schollgernweg 10",
    "sg:city":"Homberg",
    "sg:phone":"+49 6633/963410",
    "sg:postcode":"35315",
    "sg:province":"Hessen",
    "wof:name":"Schlosser Cartrans Ek",
    "wof:placetype":"venue"
},
  "geometry": {"coordinates":[9.058587,50.724194],"type":"Point"}
}