{
  "type": "Feature",
  "properties": {
    "iso:country":"DE",
    "sg:address":"Ludwigstrauch 80",
    "sg:city":"Grillenberg",
    "sg:phone":"+49 34775/20532",
    "sg:postcode":"06528",
    "sg:province":"Sachsen-Anhalt",
    "wof:name":"Pension Zur Lust",
    "wof:placetype":"venue"
},
  "geometry": {"coordinates":[11.294839859,51.42237854],"type":"Point"}
}