{
  "type": "Feature",
  "properties": {
    "iso:country":"DE",
    "sg:address":"Hans-Marchwitza-Ring 9",
    "sg:city":"Potsdam",
    "sg:phone":"+49 331/7481556",
    "sg:postcode":"14473",
    "sg:province":"Brandenburg",
    "wof:name":"Praxis Dr. Med. Beckmann Und Kolodujazk",
    "wof:placetype":"venue"
},
  "geometry": {"coordinates":[13.0795841217,52.3943595886],"type":"Point"}
}