{
  "type": "Feature",
  "properties": {
    "iso:country":"DE",
    "sg:address":"Schlachthausstr. 24",
    "sg:city":"Pritzwalk",
    "sg:phone":"+49 3395/2562",
    "sg:postcode":"16928",
    "sg:province":"Brandenburg",
    "wof:name":"R. Graf",
    "wof:placetype":"venue"
},
  "geometry": {"coordinates":[12.1685810089,53.1569747925],"type":"Point"}
}