{
  "type": "Feature",
  "properties": {
    "iso:country":"DE",
    "sg:address":"Vieringhausen 5a",
    "sg:city":"Remscheid",
    "sg:phone":"+49 2191/7822222",
    "sg:postcode":"42857",
    "sg:province":"Nordrhein-Westfalen",
    "wof:name":"Altena & Neukirchen Gmbh & Co. Kg",
    "wof:placetype":"venue"
},
  "geometry": {"coordinates":[7.169254,51.179382],"type":"Point"}
}