{
  "type": "Feature",
  "properties": {
    "iso:country":"DE",
    "sg:address":"Kalscheurener Str. 8",
    "sg:city":"H\u00fcrth",
    "sg:phone":"+49 2233/963520",
    "sg:postcode":"50354",
    "sg:province":"Nordrhein-Westfalen",
    "wof:name":"Team Baumanagement Gmbh",
    "wof:placetype":"venue"
},
  "geometry": {"coordinates":[6.904335,50.892269],"type":"Point"}
}