{
  "type": "Feature",
  "properties": {
    "iso:country":"DE",
    "sg:address":"Hauptstr. 59",
    "sg:city":"Klettgau",
    "sg:phone":"+49 7742/5346",
    "sg:postcode":"79771",
    "sg:province":"Baden-W\u00fcrttemberg",
    "wof:name":"Otto Graf",
    "wof:placetype":"venue"
},
  "geometry": {"coordinates":[8.425899,47.656406],"type":"Point"}
}