{
  "type": "Feature",
  "properties": {
    "iso:country":"DE",
    "sg:address":"Ruhesteinstr. 307",
    "sg:city":"Baiersbronn",
    "sg:phone":"+49 7442/81320",
    "sg:postcode":"72270",
    "sg:province":"Baden-W\u00fcrttemberg",
    "wof:name":"Matthias Z\u00fcfle",
    "wof:placetype":"venue"
},
  "geometry": {"coordinates":[8.30697,48.527081],"type":"Point"}
}