{
  "type": "Feature",
  "properties": {
    "iso:country":"DE",
    "sg:address":"Sophienblatt 44-46",
    "sg:city":"Kiel",
    "sg:phone":"+49 431/672022",
    "sg:postcode":"24114",
    "sg:province":"Schleswig-Holstein",
    "wof:name":"Technaval Ingenieurtechnik Gmbh & Co. Kg",
    "wof:placetype":"venue"
},
  "geometry": {"coordinates":[10.130208,54.314667],"type":"Point"}
}