{
  "type": "Feature",
  "properties": {
    "iso:country":"DE",
    "sg:address":"Brambauerstr. 38",
    "sg:city":"Dortmund",
    "sg:phone":"+49 231/804430",
    "sg:postcode":"44339",
    "sg:province":"Nordrhein-Westfalen",
    "wof:name":"China-restaurant Peking Metropole",
    "wof:placetype":"venue"
},
  "geometry": {"coordinates":[7.4584860802,51.5821228027],"type":"Point"}
}