{
  "type": "Feature",
  "properties": {
    "iso:country":"DE",
    "sg:address":"Flurstr. 2",
    "sg:city":"M\u00fchldorf",
    "sg:postcode":"84453",
    "sg:province":"Bayern",
    "wof:name":"Innpark Ii Bautr\u00e4ger Gmbh",
    "wof:placetype":"venue"
},
  "geometry": {"coordinates":[12.528958,48.261089],"type":"Point"}
}