{
  "type": "Feature",
  "properties": {
    "iso:country":"DE",
    "sg:address":"Rescheid 75",
    "sg:city":"Hellenthal",
    "sg:phone":"+49 2448/1221",
    "sg:postcode":"53940",
    "sg:province":"Nordrhein-Westfalen",
    "wof:name":"Intra M\u00fcnstermann Gmbh",
    "wof:placetype":"venue"
},
  "geometry": {"coordinates":[6.433955,50.433048],"type":"Point"}
}