{
  "type": "Feature",
  "properties": {
    "iso:country":"DE",
    "sg:address":"Morbacher Str. 53",
    "sg:city":"K\u00f6ln",
    "sg:phone":"+49 221/437509",
    "sg:postcode":"50935",
    "sg:province":"Nordrhein-Westfalen",
    "wof:name":"Dr. H. Schmidt Rechtsanwalt",
    "wof:placetype":"venue"
},
  "geometry": {"coordinates":[6.9055309296,50.9145240784],"type":"Point"}
}