{
  "type": "Feature",
  "properties": {
    "iso:country":"DE",
    "sg:address":"R\u00f6diger Str. 17",
    "sg:city":"Wuppertal",
    "sg:phone":"+49 202/552739",
    "sg:postcode":"42283",
    "sg:province":"Nordrhein-Westfalen",
    "wof:name":"Hans Borgardt",
    "wof:placetype":"venue"
},
  "geometry": {"coordinates":[7.192241,51.272079],"type":"Point"}
}