{
  "type": "Feature",
  "properties": {
    "iso:country":"DE",
    "sg:address":"Obere Nabburger Str. 29",
    "sg:city":"Amberg",
    "sg:phone":"+49 9621/42633",
    "sg:postcode":"92224",
    "sg:province":"Bayern",
    "wof:name":"Franz Spanl Strick- Und Wirkwaren",
    "wof:placetype":"venue"
},
  "geometry": {"coordinates":[11.8625259399,49.4449806213],"type":"Point"}
}