{
  "type": "Feature",
  "properties": {
    "iso:country":"DE",
    "sg:address":"Grindelberg 86",
    "sg:city":"Hamburg",
    "sg:phone":"+49 40/42911912",
    "sg:postcode":"20144",
    "sg:province":"Hamburg",
    "wof:name":"Intertel Gmbh",
    "wof:placetype":"venue"
},
  "geometry": {"coordinates":[9.977449,53.577801],"type":"Point"}
}