{
  "type": "Feature",
  "properties": {
    "iso:country":"DE",
    "sg:address":"Bismarckstr. 1",
    "sg:city":"Schwetzingen",
    "sg:phone":"+49 6202/3471",
    "sg:postcode":"68723",
    "sg:province":"Baden-W\u00fcrttemberg",
    "wof:name":"Restaurant Badner Hof",
    "wof:placetype":"venue"
},
  "geometry": {"coordinates":[8.575553894,49.3815498352],"type":"Point"}
}