{
  "type": "Feature",
  "properties": {
    "iso:country":"DE",
    "sg:address":"\u00c4u\u00dfere Sulzbacher Str. 127",
    "sg:city":"N\u00fcrnberg",
    "sg:phone":"+49 911/5979883",
    "sg:postcode":"90491",
    "sg:province":"Bayern",
    "wof:name":"Allianz Versicherungs Ag",
    "wof:placetype":"venue"
},
  "geometry": {"coordinates":[11.1196079254,49.4650726318],"type":"Point"}
}