{
  "type": "Feature",
  "properties": {
    "iso:country":"DE",
    "sg:address":"Pater-Viktrizius-Wei\u00df-Str. 31",
    "sg:city":"Eggenfelden",
    "sg:postcode":"84307",
    "sg:province":"Bayern",
    "wof:name":"Biotecc",
    "wof:placetype":"venue"
},
  "geometry": {"coordinates":[12.760058,48.400623],"type":"Point"}
}