{
  "type": "Feature",
  "properties": {
    "iso:country":"DE",
    "sg:address":"Patrizierweg 92",
    "sg:city":"Potsdam",
    "sg:phone":"+49 331/623362",
    "sg:postcode":"14480",
    "sg:province":"Brandenburg",
    "wof:name":"Ulf Linse",
    "wof:placetype":"venue"
},
  "geometry": {"coordinates":[13.140843,52.381943],"type":"Point"}
}