{
  "type": "Feature",
  "properties": {
    "iso:country":"DE",
    "sg:address":"Hahnstr. 18",
    "sg:city":"Stuttgart",
    "sg:phone":"+49 711/9679410",
    "sg:postcode":"70199",
    "sg:province":"Baden-W\u00fcrttemberg",
    "wof:name":"Albert Verwaltungs- Und Organisations Gmbh",
    "wof:placetype":"venue"
},
  "geometry": {"coordinates":[9.15599823,48.7595825195],"type":"Point"}
}