{
  "type": "Feature",
  "properties": {
    "iso:country":"DE",
    "sg:address":"Berliner Ring 2",
    "sg:city":"Wolfsburg",
    "sg:phone":"+49 5361/926265",
    "sg:postcode":"38440",
    "sg:province":"Niedersachsen",
    "wof:name":"Volkswagen Transport Gmbh",
    "wof:placetype":"venue"
},
  "geometry": {"coordinates":[10.7982597351,52.4265785217],"type":"Point"}
}