{
  "type": "Feature",
  "properties": {
    "iso:country":"DE",
    "sg:address":"Hauptstr. 21",
    "sg:city":"Ha\u00dffurt",
    "sg:phone":"+49 9521/3528",
    "sg:postcode":"97437",
    "sg:province":"Bayern",
    "wof:name":"Adalbert Schweinfest",
    "wof:placetype":"venue"
},
  "geometry": {"coordinates":[10.5076646805,50.0313682556],"type":"Point"}
}