{
  "type": "Feature",
  "properties": {
    "iso:country":"DE",
    "sg:address":"Postredder 18",
    "sg:city":"Nortorf",
    "sg:phone":"+49 4943/925466",
    "sg:postcode":"24589",
    "sg:province":"Schleswig-Holstein",
    "wof:name":"Hermann Scholz Gmbh",
    "wof:placetype":"venue"
},
  "geometry": {"coordinates":[9.85264,54.163906],"type":"Point"}
}