{
  "type": "Feature",
  "properties": {
    "iso:country":"DE",
    "sg:address":"Georgsh\u00f6he 2",
    "sg:city":"Thale",
    "sg:phone":"+49 3947/2838",
    "sg:postcode":"06502",
    "sg:province":"Sachsen-Anhalt",
    "wof:name":"Pension Forsthaus",
    "wof:placetype":"venue"
},
  "geometry": {"coordinates":[11.0559282303,51.7331237793],"type":"Point"}
}