{
  "type": "Feature",
  "properties": {
    "iso:country":"DE",
    "sg:address":"Gartenweg 16",
    "sg:city":"Merchweiler",
    "sg:phone":"+49 6825/5316",
    "sg:postcode":"66589",
    "sg:province":"Saarland",
    "wof:name":"Guenther Meiser Architekt",
    "wof:placetype":"venue"
},
  "geometry": {"coordinates":[7.057044,49.356129],"type":"Point"}
}