{
  "type": "Feature",
  "properties": {
    "iso:country":"DE",
    "sg:address":"Waldstr. 32",
    "sg:city":"Grimma",
    "sg:phone":"+49 3437/913652",
    "sg:postcode":"04668",
    "sg:province":"Sachsen",
    "wof:name":"Ambulanter Pflegedienst Sylke Nestler",
    "wof:placetype":"venue"
},
  "geometry": {"coordinates":[12.784398,51.207294],"type":"Point"}
}