{
  "type": "Feature",
  "properties": {
    "iso:country":"DE",
    "sg:address":"Mauerstr. 12",
    "sg:city":"Bleicherode",
    "sg:phone":"+49 36338/30200",
    "sg:postcode":"99752",
    "sg:province":"Th\u00fcringen",
    "wof:name":"Heike Agel",
    "wof:placetype":"venue"
},
  "geometry": {"coordinates":[10.569847,51.440422],"type":"Point"}
}