{
  "type": "Feature",
  "properties": {
    "iso:country":"DE",
    "sg:address":"Max-Planck-Str. 1",
    "sg:city":"Katlenburg-Lindau",
    "sg:phone":"+49 5556/610",
    "sg:postcode":"37191",
    "sg:province":"Niedersachsen",
    "wof:name":"Eurokosmos Consult.u.technologie Gmbh",
    "wof:placetype":"venue"
},
  "geometry": {"coordinates":[10.12353,51.648354],"type":"Point"}
}