{
  "type": "Feature",
  "properties": {
    "iso:country":"DE",
    "sg:address":"Uhlandstr. 12",
    "sg:city":"Volkertshausen",
    "sg:phone":"+49 7774/6940",
    "sg:postcode":"78269",
    "sg:province":"Baden-W\u00fcrttemberg",
    "wof:name":"Andreas Linack",
    "wof:placetype":"venue"
},
  "geometry": {"coordinates":[8.8727636337,47.825176239],"type":"Point"}
}