{
  "type": "Feature",
  "properties": {
    "iso:country":"DE",
    "sg:address":"Schaupenstiel 36",
    "sg:city":"Northeim",
    "sg:phone":"+49 5551/65809",
    "sg:postcode":"37154",
    "sg:province":"Niedersachsen",
    "wof:name":"Bernd Fr\u00f6chtenicht",
    "wof:placetype":"venue"
},
  "geometry": {"coordinates":[10.0076808929,51.7063827515],"type":"Point"}
}