{
  "type": "Feature",
  "properties": {
    "iso:country":"DE",
    "sg:address":"Hirschstr. 27",
    "sg:city":"Stuttgart",
    "sg:phone":"+49 711/2349640",
    "sg:postcode":"70173",
    "sg:province":"Baden-W\u00fcrttemberg",
    "wof:name":"J. Berner",
    "wof:placetype":"venue"
},
  "geometry": {"coordinates":[9.1766061783,48.7743873596],"type":"Point"}
}