{
  "type": "Feature",
  "properties": {
    "iso:country":"DE",
    "sg:address":"F\u00fcrstenplatz 5",
    "sg:city":"Schneeberg",
    "sg:phone":"+49 3772/22120",
    "sg:postcode":"08289",
    "sg:province":"Sachsen",
    "wof:name":"Goldene Sonne Vermietungs- Und Veranstaltungsbetriebe Gmbh",
    "wof:placetype":"venue"
},
  "geometry": {"coordinates":[12.6402082443,50.5961647034],"type":"Point"}
}