{
  "type": "Feature",
  "properties": {
    "iso:country":"DE",
    "sg:address":"Reimerdeskamp 2",
    "sg:city":"Hameln",
    "sg:phone":"+49 5151/41837",
    "sg:postcode":"31787",
    "sg:province":"Niedersachsen",
    "wof:name":"Deutsche Shell Ag",
    "wof:placetype":"venue"
},
  "geometry": {"coordinates":[9.3481674194,52.1216850281],"type":"Point"}
}