{
  "type": "Feature",
  "properties": {
    "iso:country":"DE",
    "sg:address":"Glehner Str. 17 a",
    "sg:city":"Mechernich",
    "sg:phone":"+49 2443/8959",
    "sg:postcode":"53894",
    "sg:province":"Nordrhein-Westfalen",
    "wof:name":"H. Gilles",
    "wof:placetype":"venue"
},
  "geometry": {"coordinates":[6.5710067749,50.5973968506],"type":"Point"}
}