{
  "type": "Feature",
  "properties": {
    "iso:country":"DE",
    "sg:address":"Marktstr. 3",
    "sg:city":"Taucha",
    "sg:phone":"+49 34298/38610",
    "sg:postcode":"04425",
    "sg:province":"Sachsen",
    "wof:name":"Transport Und Dienst- Leistungs Gmbh",
    "wof:placetype":"venue"
},
  "geometry": {"coordinates":[12.5012645721,51.380153656],"type":"Point"}
}