{
  "type": "Feature",
  "properties": {
    "iso:country":"DE",
    "sg:address":"Kolberger Str. 18",
    "sg:city":"Leonberg",
    "sg:phone":"+49 7152/42910",
    "sg:postcode":"71229",
    "sg:province":"Baden-W\u00fcrttemberg",
    "wof:name":"Gerhart Gr\u00fcninger",
    "wof:placetype":"venue"
},
  "geometry": {"coordinates":[8.9915647507,48.7619094849],"type":"Point"}
}