{
  "type": "Feature",
  "properties": {
    "iso:country":"DE",
    "sg:address":"Voss-Str. 65",
    "sg:city":"Sarstedt",
    "sg:phone":"+49 5066/7923",
    "sg:postcode":"31157",
    "sg:province":"Niedersachsen",
    "wof:name":"Musikschule Schwarze",
    "wof:placetype":"venue"
},
  "geometry": {"coordinates":[9.8412084579,52.2244949341],"type":"Point"}
}