{
  "type": "Feature",
  "properties": {
    "iso:country":"DE",
    "sg:address":"Eggeroder Str. 9",
    "sg:city":"Sch\u00f6ppingen",
    "sg:phone":"+49 2555/403",
    "sg:postcode":"48624",
    "sg:province":"Nordrhein-Westfalen",
    "wof:name":"H\u00f6ping T\u00fcr Gmbh",
    "wof:placetype":"venue"
},
  "geometry": {"coordinates":[7.23274,52.086441],"type":"Point"}
}