{
  "type": "Feature",
  "properties": {
    "iso:country":"DE",
    "sg:address":"Albulaweg 29",
    "sg:city":"Berlin",
    "sg:phone":"+49 30/7411234",
    "sg:postcode":"12107",
    "sg:province":"Berlin",
    "wof:name":"Tauern-apotheke",
    "wof:placetype":"venue"
},
  "geometry": {"coordinates":[13.398023,52.423607],"type":"Point"}
}