{
  "type": "Feature",
  "properties": {
    "iso:country":"DE",
    "sg:address":"Schmiedgasse 6",
    "sg:city":"Aichhalden",
    "sg:postcode":"78733",
    "sg:province":"Baden-W\u00fcrttemberg",
    "wof:name":"Cnc - Pr\u00e4zisionsfertigung Oswald Ziegler E. K.",
    "wof:placetype":"venue"
},
  "geometry": {"coordinates":[8.420054,48.30455],"type":"Point"}
}