{
  "type": "Feature",
  "properties": {
    "iso:country":"DE",
    "sg:address":"Hermelinweg 10",
    "sg:city":"K\u00f6ln",
    "sg:phone":"+49 221/841383",
    "sg:postcode":"51109",
    "sg:province":"Nordrhein-Westfalen",
    "wof:name":"Alfred R\u00f6ssig Gmbh & Co. Kg",
    "wof:placetype":"venue"
},
  "geometry": {"coordinates":[7.0879178047,50.943397522],"type":"Point"}
}