{
  "type": "Feature",
  "properties": {
    "iso:country":"DE",
    "sg:address":"Apolloniaweg 10",
    "sg:city":"Aachen",
    "sg:phone":"+49 241/551973",
    "sg:postcode":"52080",
    "sg:province":"Nordrhein-Westfalen",
    "wof:name":"Katholisches Pfarramt St. Apollonia",
    "wof:placetype":"venue"
},
  "geometry": {"coordinates":[6.167637825,50.7790794373],"type":"Point"}
}