{
  "type": "Feature",
  "properties": {
    "iso:country":"DE",
    "sg:address":"Aachener Str. 209",
    "sg:city":"K\u00f6ln",
    "sg:postcode":"50931",
    "sg:province":"Nordrhein-Westfalen",
    "wof:name":"Inverto Ag",
    "wof:placetype":"venue"
},
  "geometry": {"coordinates":[6.922132,50.936501],"type":"Point"}
}