{
  "type": "Feature",
  "properties": {
    "iso:country":"DE",
    "sg:address":"Woogsdammweg 8",
    "sg:city":"Gro\u00df-Gerau",
    "sg:phone":"+49 6152/39012",
    "sg:postcode":"64521",
    "sg:province":"Hessen",
    "wof:name":"Ralf Heimann Architekt",
    "wof:placetype":"venue"
},
  "geometry": {"coordinates":[8.503658,49.940514],"type":"Point"}
}