{
  "type": "Feature",
  "properties": {
    "iso:country":"DE",
    "sg:address":"Bostalstr. 46",
    "sg:city":"Nohfelden",
    "sg:phone":"+49 6852/6770",
    "sg:postcode":"66625",
    "sg:province":"Saarland",
    "wof:name":"Merkers Bostal-hotel",
    "wof:placetype":"venue"
},
  "geometry": {"coordinates":[7.0536370277,49.5708885193],"type":"Point"}
}