{
  "type": "Feature",
  "properties": {
    "iso:country":"DE",
    "sg:address":"Burghofweg 4",
    "sg:city":"Ebersbach",
    "sg:phone":"+49 7163/8123",
    "sg:postcode":"73061",
    "sg:province":"Baden-W\u00fcrttemberg",
    "wof:name":"Eugen Rau",
    "wof:placetype":"venue"
},
  "geometry": {"coordinates":[9.54847,48.709541],"type":"Point"}
}