{
  "type": "Feature",
  "properties": {
    "iso:country":"DE",
    "sg:address":"Johann-Fruhen-Str. 25",
    "sg:city":"Grefrath",
    "sg:phone":"+49 2158/8655",
    "sg:postcode":"47929",
    "sg:province":"Nordrhein-Westfalen",
    "wof:name":"H\u00e4usliche Krankenpflege J\u00fcrgen Jeremies",
    "wof:placetype":"venue"
},
  "geometry": {"coordinates":[6.383898,51.32085],"type":"Point"}
}