{
  "type": "Feature",
  "properties": {
    "iso:country":"DE",
    "sg:address":"Klint 2",
    "sg:city":"Braunschweig",
    "sg:phone":"+49 531/41001",
    "sg:postcode":"38100",
    "sg:province":"Niedersachsen",
    "wof:name":"Cosmetic Im Magni Anke Lambrecht",
    "wof:placetype":"venue"
},
  "geometry": {"coordinates":[10.5291891098,52.2607803345],"type":"Point"}
}