{
  "type": "Feature",
  "properties": {
    "iso:country":"DE",
    "sg:city":"Geesthacht",
    "sg:phone":"+49 4152/4639",
    "sg:postcode":"21502",
    "sg:province":"Schleswig-Holstein",
    "wof:name":"Campingplatz Tesperhude",
    "wof:placetype":"venue"
},
  "geometry": {"coordinates":[10.37425,53.430294],"type":"Point"}
}