{
  "type": "Feature",
  "properties": {
    "iso:country":"DE",
    "sg:address":"Erhard-Ackermann-Str. 21",
    "sg:city":"Wei\u00dfenstadt",
    "sg:phone":"+49 9253/271",
    "sg:postcode":"95163",
    "sg:province":"Bayern",
    "wof:name":"Karl Michael Dachdeckerei",
    "wof:placetype":"venue"
},
  "geometry": {"coordinates":[11.884473,50.102932],"type":"Point"}
}