{
  "type": "Feature",
  "properties": {
    "iso:country":"DE",
    "sg:address":"Schlo\u00dfgasse 12",
    "sg:city":"Dieburg",
    "sg:phone":"+49 6071/21159",
    "sg:postcode":"64807",
    "sg:province":"Hessen",
    "wof:name":"P. S. K. Haus- Und Verm\u00f6gensverwaltungs Gmbh",
    "wof:placetype":"venue"
},
  "geometry": {"coordinates":[8.8363418579,49.8991317749],"type":"Point"}
}