{
  "type": "Feature",
  "properties": {
    "iso:country":"DE",
    "sg:address":"Burscheider Str. 126",
    "sg:city":"Leverkusen",
    "sg:phone":"+49 2171/31549",
    "sg:postcode":"51381",
    "sg:province":"Nordrhein-Westfalen",
    "wof:name":"H. Schwarz Tischlerei",
    "wof:placetype":"venue"
},
  "geometry": {"coordinates":[7.035669,51.078266],"type":"Point"}
}