{
  "type": "Feature",
  "properties": {
    "iso:country":"DE",
    "sg:address":"Alter Markt 20",
    "sg:city":"K\u00f6ln",
    "sg:phone":"+49 221/2577692",
    "sg:postcode":"50667",
    "sg:province":"Nordrhein-Westfalen",
    "wof:name":"Restaurant Gaffel-haus",
    "wof:placetype":"venue"
},
  "geometry": {"coordinates":[6.9603619576,50.938079834],"type":"Point"}
}