{
  "type": "Feature",
  "properties": {
    "iso:country":"DE",
    "sg:address":"Siemensstr. 13",
    "sg:city":"Eutin",
    "sg:phone":"+49 4521/2864",
    "sg:postcode":"23701",
    "sg:province":"Schleswig-Holstein",
    "wof:name":"Ewald Strauch Gmbh",
    "wof:placetype":"venue"
},
  "geometry": {"coordinates":[10.6215667725,54.1244659424],"type":"Point"}
}