{
  "type": "Feature",
  "properties": {
    "iso:country":"DE",
    "sg:address":"Alte 's-Heerenberger Str. 168",
    "sg:city":"Emmerich",
    "sg:phone":"+49 2822/68100",
    "sg:postcode":"46446",
    "sg:province":"Nordrhein-Westfalen",
    "wof:name":"Jacobus De Vries Heilpraktiker",
    "wof:placetype":"venue"
},
  "geometry": {"coordinates":[6.2419629097,51.8476257324],"type":"Point"}
}