{
  "type": "Feature",
  "properties": {
    "iso:country":"DE",
    "sg:address":"Luisenweg 46",
    "sg:city":"Hamburg",
    "sg:phone":"+49 40/2503656",
    "sg:postcode":"20537",
    "sg:province":"Hamburg",
    "wof:name":"Koslowski Reifen- Alufelgen Gmbh",
    "wof:placetype":"venue"
},
  "geometry": {"coordinates":[10.0474033356,53.5505142212],"type":"Point"}
}