{
  "type": "Feature",
  "properties": {
    "iso:country":"DE",
    "sg:address":"B\u00fcchnerstr. 9",
    "sg:city":"Riedstadt",
    "sg:phone":"+49 6158/74559",
    "sg:postcode":"64560",
    "sg:province":"Hessen",
    "wof:name":"Wokan Und Partner- Diplomingenieure",
    "wof:placetype":"venue"
},
  "geometry": {"coordinates":[8.4956417084,49.8346061707],"type":"Point"}
}