{
  "type": "Feature",
  "properties": {
    "iso:country":"DE",
    "sg:address":"Steinhaag 3",
    "sg:city":"Sinntal",
    "sg:phone":"+49 6664/919443",
    "sg:postcode":"36391",
    "sg:province":"Hessen",
    "wof:name":"Kurt Zirkel",
    "wof:placetype":"venue"
},
  "geometry": {"coordinates":[9.7144527435,50.3337898254],"type":"Point"}
}