{
  "type": "Feature",
  "properties": {
    "iso:country":"DE",
    "sg:address":"L\u00fcbsche Str. 64",
    "sg:city":"Wismar",
    "sg:phone":"+49 3841/282131",
    "sg:postcode":"23966",
    "sg:province":"Mecklenburg-Vorpommern",
    "wof:name":"Christine Ahlvers",
    "wof:placetype":"venue"
},
  "geometry": {"coordinates":[11.459761,53.89156],"type":"Point"}
}