{
  "type": "Feature",
  "properties": {
    "iso:country":"DE",
    "sg:address":"Am G\u00fcterbahnhof 4a",
    "sg:city":"Halle",
    "sg:phone":"+49 345/2021771",
    "sg:postcode":"06112",
    "sg:province":"Sachsen-Anhalt",
    "wof:name":"Saku Sachsen-anhalt Kurier",
    "wof:placetype":"venue"
},
  "geometry": {"coordinates":[11.98939,51.479309],"type":"Point"}
}