{
  "type": "Feature",
  "properties": {
    "iso:country":"DE",
    "sg:address":"Erwin-Renth-Str. 1",
    "sg:city":"Budenheim",
    "sg:phone":"+49 6139/766",
    "sg:postcode":"55257",
    "sg:province":"Rheinland-Pfalz",
    "wof:name":"Sard Reisedienst",
    "wof:placetype":"venue"
},
  "geometry": {"coordinates":[8.1729927063,50.0241966248],"type":"Point"}
}