{
  "type": "Feature",
  "properties": {
    "iso:country":"DE",
    "sg:address":"Seetorstr. 2",
    "sg:city":"Radolfzell",
    "sg:phone":"+49 7732/54191",
    "sg:postcode":"78315",
    "sg:province":"Baden-W\u00fcrttemberg",
    "wof:name":"O. Oechsle Kleinpreis Mode Gmbh",
    "wof:placetype":"venue"
},
  "geometry": {"coordinates":[8.969223,47.736618],"type":"Point"}
}