{
  "type": "Feature",
  "properties": {
    "iso:country":"DE",
    "sg:address":"Bentheimstr. 9",
    "sg:city":"W\u00fcrzburg",
    "sg:phone":"+49 931/887309",
    "sg:postcode":"97072",
    "sg:province":"Bayern",
    "wof:name":"Horst Werner",
    "wof:placetype":"venue"
},
  "geometry": {"coordinates":[9.9399518967,49.7843818665],"type":"Point"}
}