{
  "type": "Feature",
  "properties": {
    "iso:country":"DE",
    "sg:address":"K\u00f6nigswinterer Str. 409",
    "sg:city":"K\u00f6nigswinter",
    "sg:postcode":"53639",
    "sg:province":"Nordrhein-Westfalen",
    "wof:name":"Asd Ambulante Service Dienste Gmbh",
    "wof:placetype":"venue"
},
  "geometry": {"coordinates":[7.253569,50.677502],"type":"Point"}
}