{
  "type": "Feature",
  "properties": {
    "iso:country":"DE",
    "sg:address":"Stapelholmer Weg 13",
    "sg:city":"Tarp",
    "sg:phone":"+49 4638/7833",
    "sg:postcode":"24963",
    "sg:province":"Schleswig-Holstein",
    "wof:name":"Rudolf Rossetti E. K.",
    "wof:placetype":"venue"
},
  "geometry": {"coordinates":[9.3990459442,54.6622772217],"type":"Point"}
}