{
  "type": "Feature",
  "properties": {
    "iso:country":"DE",
    "sg:address":"Ostendorfweg 9",
    "sg:city":"Bocholt",
    "sg:phone":"+49 2871/43685",
    "sg:postcode":"46399",
    "sg:province":"Nordrhein-Westfalen",
    "wof:name":"Wilhelm Schmeinck",
    "wof:placetype":"venue"
},
  "geometry": {"coordinates":[6.5954341888,51.845741272],"type":"Point"}
}