{
  "type": "Feature",
  "properties": {
    "iso:country":"DE",
    "sg:address":"Dorfplatz 1",
    "sg:city":"Baindt",
    "sg:phone":"+49 7502/4662",
    "sg:postcode":"88255",
    "sg:province":"Baden-W\u00fcrttemberg",
    "wof:name":"Maximilian Maucher",
    "wof:placetype":"venue"
},
  "geometry": {"coordinates":[9.6617927551,47.8420066833],"type":"Point"}
}