{
  "type": "Feature",
  "properties": {
    "iso:country":"DE",
    "sg:address":"Gro\u00dfe Werlstr. 45",
    "sg:city":"Hamm",
    "sg:postcode":"59077",
    "sg:province":"Nordrhein-Westfalen",
    "wof:name":"Lebensmittelmarkt J\u00f6rg Weber E. K.",
    "wof:placetype":"venue"
},
  "geometry": {"coordinates":[7.7690629959,51.6371688843],"type":"Point"}
}