{
  "type": "Feature",
  "properties": {
    "iso:country":"DE",
    "sg:address":"Robert-Bosch-Str. 6",
    "sg:city":"Triefenstein",
    "sg:phone":"+49 9391/7997",
    "sg:postcode":"97855",
    "sg:province":"Bayern",
    "wof:name":"Schmitt Metalltechnik Gmbh",
    "wof:placetype":"venue"
},
  "geometry": {"coordinates":[9.597066,49.82198],"type":"Point"}
}