{
  "type": "Feature",
  "properties": {
    "iso:country":"DE",
    "sg:address":"Luckower Str. 14 c",
    "sg:city":"Eggesin",
    "sg:phone":"+49 39779/20531",
    "sg:postcode":"17367",
    "sg:province":"Mecklenburg-Vorpommern",
    "wof:name":"Hotel Waldidylle",
    "wof:placetype":"venue"
},
  "geometry": {"coordinates":[14.083316803,53.6844749451],"type":"Point"}
}