{
  "type": "Feature",
  "properties": {
    "iso:country":"DE",
    "sg:address":"Gartenstr. 8",
    "sg:city":"Wermelskirchen",
    "sg:phone":"+49 2196/80919",
    "sg:postcode":"42929",
    "sg:province":"Nordrhein-Westfalen",
    "wof:name":"Reiner Platte",
    "wof:placetype":"venue"
},
  "geometry": {"coordinates":[7.2093567848,51.1323051453],"type":"Point"}
}