{
  "type": "Feature",
  "properties": {
    "iso:country":"DE",
    "sg:address":"Heinrichstr. 29",
    "sg:city":"Moers",
    "sg:phone":"+49 2841/95810",
    "sg:postcode":"47443",
    "sg:province":"Nordrhein-Westfalen",
    "wof:name":"Heinz A. Klein Und Sohn Victoria D.a.s. Rechtschutz",
    "wof:placetype":"venue"
},
  "geometry": {"coordinates":[6.6484699249,51.4473991394],"type":"Point"}
}