{
  "type": "Feature",
  "properties": {
    "iso:country":"DE",
    "sg:address":"Greimelstr. 34",
    "sg:city":"Ismaning",
    "sg:phone":"+49 89/969108",
    "sg:postcode":"85737",
    "sg:province":"Bayern",
    "wof:name":"Alois Unterpointner",
    "wof:placetype":"venue"
},
  "geometry": {"coordinates":[11.677148819,48.235534668],"type":"Point"}
}