{
  "type": "Feature",
  "properties": {
    "iso:country":"DE",
    "sg:address":"Sieglindenweg 10 a",
    "sg:city":"Bergisch Gladbach",
    "sg:phone":"+49 2202/35597",
    "sg:postcode":"51469",
    "sg:province":"Nordrhein-Westfalen",
    "wof:name":"Wilfried Schwarzkopf",
    "wof:placetype":"venue"
},
  "geometry": {"coordinates":[7.1204400063,50.9799118042],"type":"Point"}
}