{
  "type": "Feature",
  "properties": {
    "iso:country":"DE",
    "sg:address":"Marktplatz 3",
    "sg:city":"Bad Windsheim",
    "sg:phone":"+49 9841/2074",
    "sg:postcode":"91438",
    "sg:province":"Bayern",
    "wof:name":"Einhorn-apotheke",
    "wof:placetype":"venue"
},
  "geometry": {"coordinates":[10.417858,49.502361],"type":"Point"}
}