{
  "type": "Feature",
  "properties": {
    "iso:country":"DE",
    "sg:address":"Neusser Str. 496",
    "sg:city":"K\u00f6ln",
    "sg:phone":"+49 221/743403",
    "sg:postcode":"50737",
    "sg:province":"Nordrhein-Westfalen",
    "wof:name":"Th. Axmacher Augenoptiker",
    "wof:placetype":"venue"
},
  "geometry": {"coordinates":[6.9501838684,50.975692749],"type":"Point"}
}