{
  "type": "Feature",
  "properties": {
    "iso:country":"DE",
    "sg:address":"Lindenallee 28",
    "sg:city":"Remscheid",
    "sg:phone":"+49 2191/54310",
    "sg:postcode":"42899",
    "sg:province":"Nordrhein-Westfalen",
    "wof:name":"Diebschlag Malerbetrieb Inh. Reiner Swoboda E. K.",
    "wof:placetype":"venue"
},
  "geometry": {"coordinates":[7.242661,51.208878],"type":"Point"}
}