{
  "type": "Feature",
  "properties": {
    "iso:country":"DE",
    "sg:address":"Siemensstr. 18",
    "sg:city":"Garbsen",
    "sg:phone":"+49 5131/92068",
    "sg:postcode":"30827",
    "sg:province":"Niedersachsen",
    "wof:name":"Nikolic Gabelstapler- Service Gmbh",
    "wof:placetype":"venue"
},
  "geometry": {"coordinates":[9.6094703674,52.4471893311],"type":"Point"}
}