{
  "type": "Feature",
  "properties": {
    "iso:country":"DE",
    "sg:address":"Hauptstr. 1",
    "sg:city":"Dielmissen",
    "sg:phone":"+49 5534/2307",
    "sg:postcode":"37633",
    "sg:province":"Niedersachsen",
    "wof:name":"Hotel Angerkrug",
    "wof:placetype":"venue"
},
  "geometry": {"coordinates":[9.6043729782,51.9658737183],"type":"Point"}
}