{
  "type": "Feature",
  "properties": {
    "iso:country":"DE",
    "sg:address":"Nu\u00dfbergtreppe 10",
    "sg:city":"Saarbr\u00fccken",
    "sg:phone":"+49 681/5009919",
    "sg:postcode":"66119",
    "sg:province":"Saarland",
    "wof:name":"W. Van Der Wals Masseur",
    "wof:placetype":"venue"
},
  "geometry": {"coordinates":[6.993479,49.225304],"type":"Point"}
}