{
  "type": "Feature",
  "properties": {
    "iso:country":"DE",
    "sg:address":"Burgwallstr. 33",
    "sg:city":"Panschwitz-Kuckau",
    "sg:phone":"+49 35796/96235",
    "sg:postcode":"01920",
    "sg:province":"Sachsen",
    "wof:name":"Werner Hausch",
    "wof:placetype":"venue"
},
  "geometry": {"coordinates":[14.19322,51.217598],"type":"Point"}
}