{
  "type": "Feature",
  "properties": {
    "iso:country":"DE",
    "sg:address":"Otto-K\u00e4hni-Weg 17",
    "sg:city":"Offenburg",
    "sg:phone":"+49 781/9480145",
    "sg:postcode":"77654",
    "sg:province":"Baden-W\u00fcrttemberg",
    "wof:name":"Ultimedia Gesellschaft F\u00fcr Unternehmenskommunikation",
    "wof:placetype":"venue"
},
  "geometry": {"coordinates":[7.9524021149,48.4717140198],"type":"Point"}
}