{
  "type": "Feature",
  "properties": {
    "iso:country":"DE",
    "sg:address":"Krugweg 3",
    "sg:city":"Bad Harzburg",
    "sg:phone":"+49 5322/86370",
    "sg:postcode":"38667",
    "sg:province":"Niedersachsen",
    "wof:name":"H. Lan\u00dfky",
    "wof:placetype":"venue"
},
  "geometry": {"coordinates":[10.5617265701,51.9026832581],"type":"Point"}
}