{
  "type": "Feature",
  "properties": {
    "iso:country":"DE",
    "sg:address":"Heidraden 4",
    "sg:city":"Bilsen",
    "sg:phone":"+49 4106/2153",
    "sg:postcode":"25485",
    "sg:province":"Schleswig-Holstein",
    "wof:name":"Adolf Mohr Fleischerei",
    "wof:placetype":"venue"
},
  "geometry": {"coordinates":[9.8745355606,53.7771148682],"type":"Point"}
}