{
  "type": "Feature",
  "properties": {
    "iso:country":"DE",
    "sg:address":"Am Westerntor 4",
    "sg:city":"Paderborn",
    "sg:phone":"+49 5251/106464",
    "sg:postcode":"33098",
    "sg:province":"Nordrhein-Westfalen",
    "wof:name":"Discount Travel",
    "wof:placetype":"venue"
},
  "geometry": {"coordinates":[8.7520399094,51.7181434631],"type":"Point"}
}