{
  "type": "Feature",
  "properties": {
    "iso:country":"DE",
    "sg:address":"Ernst-Heinrich-Geist-Str. 6-16",
    "sg:city":"Frechen",
    "sg:phone":"+49 2234/274480",
    "sg:postcode":"50226",
    "sg:province":"Nordrhein-Westfalen",
    "wof:name":"Eckel & Pohlen Ohg",
    "wof:placetype":"venue"
},
  "geometry": {"coordinates":[6.817837,50.908085],"type":"Point"}
}