{
  "type": "Feature",
  "properties": {
    "iso:country":"DE",
    "sg:address":"Bahnhofstr. 41 /1",
    "sg:city":"Tuttlingen",
    "sg:phone":"+49 7461/2416",
    "sg:postcode":"78532",
    "sg:province":"Baden-W\u00fcrttemberg",
    "wof:name":"Buchhandlung Hein. Holzwarth Inh. Kurt Holzwarth",
    "wof:placetype":"venue"
},
  "geometry": {"coordinates":[8.814043045,47.9834213257],"type":"Point"}
}