{
  "type": "Feature",
  "properties": {
    "iso:country":"DE",
    "sg:address":"Pfeilshofer Weg 30",
    "sg:city":"Hamburg",
    "sg:phone":"+49 40/8002293",
    "sg:postcode":"22391",
    "sg:province":"Hamburg",
    "wof:name":"Cinemedia Gmbh",
    "wof:placetype":"venue"
},
  "geometry": {"coordinates":[10.0946378708,53.6424560547],"type":"Point"}
}