{
  "type": "Feature",
  "properties": {
    "iso:country":"DE",
    "sg:address":"Otto-Hahn-Str. 4",
    "sg:city":"Neuenburg",
    "sg:phone":"+49 7631/7796",
    "sg:postcode":"79395",
    "sg:province":"Baden-W\u00fcrttemberg",
    "wof:name":"Danzas Grundst\u00fccksverwaltung Frankfurt Gmbh",
    "wof:placetype":"venue"
},
  "geometry": {"coordinates":[7.5524120331,47.8101654053],"type":"Point"}
}