{
  "type": "Feature",
  "properties": {
    "iso:country":"DE",
    "sg:address":"Hildesheimer Str. 52",
    "sg:city":"Goslar",
    "sg:phone":"+49 4953/217890",
    "sg:postcode":"38640",
    "sg:province":"Niedersachsen",
    "wof:name":"Nordharzer Kraftwerke Gmbh",
    "wof:placetype":"venue"
},
  "geometry": {"coordinates":[10.42065,51.913059],"type":"Point"}
}