{
  "type": "Feature",
  "properties": {
    "iso:country":"DE",
    "sg:address":"Am Rathaus 10",
    "sg:city":"Sinntal",
    "sg:postcode":"36391",
    "sg:province":"Hessen",
    "wof:name":"Mehrzweckhalle O.t.sterbfritz",
    "wof:placetype":"venue"
},
  "geometry": {"coordinates":[9.622775,50.312943],"type":"Point"}
}