{
  "type": "Feature",
  "properties": {
    "iso:country":"DE",
    "sg:address":"Marburger Str. 1",
    "sg:city":"Bad Laasphe",
    "sg:phone":"+49 2752/6182",
    "sg:postcode":"57334",
    "sg:province":"Nordrhein-Westfalen",
    "wof:name":"Norbert Heinze",
    "wof:placetype":"venue"
},
  "geometry": {"coordinates":[8.44895,50.922058],"type":"Point"}
}