{
  "type": "Feature",
  "properties": {
    "iso:country":"DE",
    "sg:address":"Rombergstr. 21",
    "sg:city":"Steinbach",
    "sg:phone":"+49 6171/71550",
    "sg:postcode":"61449",
    "sg:province":"Hessen",
    "wof:name":"Reinhold Klamm",
    "wof:placetype":"venue"
},
  "geometry": {"coordinates":[8.5682640076,50.1717262268],"type":"Point"}
}