{
  "type": "Feature",
  "properties": {
    "iso:country":"DE",
    "sg:address":"Triberger Str. 17",
    "sg:city":"Elzach",
    "sg:phone":"+49 7682/1337",
    "sg:postcode":"79215",
    "sg:province":"Baden-W\u00fcrttemberg",
    "wof:name":"Claus Feninger",
    "wof:placetype":"venue"
},
  "geometry": {"coordinates":[8.160572052,48.1989059448],"type":"Point"}
}