{
  "type": "Feature",
  "properties": {
    "iso:country":"DE",
    "sg:address":"Pfarrer-Brunner-Str. 11",
    "sg:city":"Hausach",
    "sg:phone":"+49 7831/289",
    "sg:postcode":"77756",
    "sg:province":"Baden-W\u00fcrttemberg",
    "wof:name":"Seniorengemeinschaft Kath. Pfarrgemeinderat",
    "wof:placetype":"venue"
},
  "geometry": {"coordinates":[8.1714334488,48.2826271057],"type":"Point"}
}