{
  "type": "Feature",
  "properties": {
    "iso:country":"DE",
    "sg:address":"Heimkestr. 10",
    "sg:city":"Meschede",
    "sg:phone":"+49 2903/850229",
    "sg:postcode":"59872",
    "sg:province":"Nordrhein-Westfalen",
    "wof:name":"Volksf\u00fcrsorge Deutsche Lebensversicherung Ag",
    "wof:placetype":"venue"
},
  "geometry": {"coordinates":[8.1929483414,51.3579559326],"type":"Point"}
}