{
  "type": "Feature",
  "properties": {
    "iso:country":"DE",
    "sg:address":"Heimgartenstr. 1",
    "sg:city":"Hof",
    "sg:postcode":"95030",
    "sg:province":"Bayern",
    "wof:name":"Etschel Wohnbau Kg",
    "wof:placetype":"venue"
},
  "geometry": {"coordinates":[11.8877973557,50.3073883057],"type":"Point"}
}