{
  "type": "Feature",
  "properties": {
    "iso:country":"DE",
    "sg:city":"Eggenstein-Leopoldshafen",
    "sg:postcode":"76344",
    "sg:province":"Baden-W\u00fcrttemberg",
    "wof:name":"Vogelpark Eggenstein",
    "wof:placetype":"venue"
},
  "geometry": {"coordinates":[8.392306,49.099331],"type":"Point"}
}