{
  "type": "Feature",
  "properties": {
    "iso:country":"DE",
    "sg:address":"Tannenstr. 17",
    "sg:city":"Nittendorf",
    "sg:phone":"+49 9404/6110",
    "sg:postcode":"93152",
    "sg:province":"Bayern",
    "wof:name":"Wolfgang Reis Ingenieur",
    "wof:placetype":"venue"
},
  "geometry": {"coordinates":[11.9382095337,49.0232887268],"type":"Point"}
}