{
  "type": "Feature",
  "properties": {
    "iso:country":"DE",
    "sg:address":"Buschweg 12",
    "sg:city":"Espelkamp",
    "sg:phone":"+49 5743/920003",
    "sg:postcode":"32339",
    "sg:province":"Nordrhein-Westfalen",
    "wof:name":"Gruhn Architekt",
    "wof:placetype":"venue"
},
  "geometry": {"coordinates":[8.584869,52.345287],"type":"Point"}
}