{
  "type": "Feature",
  "properties": {
    "iso:country":"DE",
    "sg:address":"Dr.-Neuh\u00e4u\u00dfer-Str. 26",
    "sg:city":"Bad Oeynhausen",
    "sg:phone":"+49 5731/23886",
    "sg:postcode":"32545",
    "sg:province":"Nordrhein-Westfalen",
    "wof:name":"A. S\u00fcdmersen",
    "wof:placetype":"venue"
},
  "geometry": {"coordinates":[8.8034553528,52.2049407959],"type":"Point"}
}