{
  "type": "Feature",
  "properties": {
    "iso:country":"DE",
    "sg:address":"Robert-Bosch-Str. 2",
    "sg:city":"Tiefenbronn",
    "sg:phone":"+49 7234/2013",
    "sg:postcode":"75233",
    "sg:province":"Baden-W\u00fcrttemberg",
    "wof:name":"Stalex Werkzeugmaschinen Vertriebs Gmbh",
    "wof:placetype":"venue"
},
  "geometry": {"coordinates":[8.8131933212,48.821231842],"type":"Point"}
}