{
  "type": "Feature",
  "properties": {
    "iso:country":"DE",
    "sg:address":"Am Pfarracker 67",
    "sg:city":"Bielefeld",
    "sg:phone":"+49 521/85086",
    "sg:postcode":"33611",
    "sg:province":"Nordrhein-Westfalen",
    "wof:name":"Max Ernst",
    "wof:placetype":"venue"
},
  "geometry": {"coordinates":[8.552017,52.048733],"type":"Point"}
}