{
  "type": "Feature",
  "properties": {
    "iso:country":"DE",
    "sg:address":"Ansbacher Str. 15",
    "sg:city":"Rothenburg",
    "sg:phone":"+49 9861/6366",
    "sg:postcode":"91541",
    "sg:province":"Bayern",
    "wof:name":"R\u00fcdiger Koch Rechtsanwalt",
    "wof:placetype":"venue"
},
  "geometry": {"coordinates":[10.1847000122,49.3766860962],"type":"Point"}
}