{
  "type": "Feature",
  "properties": {
    "iso:country":"DE",
    "sg:address":"Hauptstr. 52",
    "sg:city":"Ankum",
    "sg:phone":"+49 5462/72700",
    "sg:postcode":"49577",
    "sg:province":"Niedersachsen",
    "wof:name":"Reinhard Lemke",
    "wof:placetype":"venue"
},
  "geometry": {"coordinates":[7.868624,52.543697],"type":"Point"}
}