{
  "type": "Feature",
  "properties": {
    "iso:country":"DE",
    "sg:address":"Johannisstr. 12",
    "sg:city":"Herford",
    "sg:phone":"+49 5221/10180",
    "sg:postcode":"32052",
    "sg:province":"Nordrhein-Westfalen",
    "wof:name":"Woge Wohnungsbau-und Verwaltungsges. Herford Mbh",
    "wof:placetype":"venue"
},
  "geometry": {"coordinates":[8.6764822006,52.1141052246],"type":"Point"}
}