{
  "type": "Feature",
  "properties": {
    "iso:country":"DE",
    "sg:address":"Leyendeckerstr. 27",
    "sg:city":"K\u00f6ln",
    "sg:phone":"+49 221/543169",
    "sg:postcode":"50825",
    "sg:province":"Nordrhein-Westfalen",
    "wof:name":"T. Caspers",
    "wof:placetype":"venue"
},
  "geometry": {"coordinates":[6.908112,50.952621],"type":"Point"}
}