{
  "type": "Feature",
  "properties": {
    "iso:country":"DE",
    "sg:address":"Chiemgaustr. 7",
    "sg:city":"M\u00fcnchen",
    "sg:postcode":"81549",
    "sg:province":"Bayern",
    "wof:name":"Evang.-luth. Pfarramt Philippuskirche",
    "wof:placetype":"venue"
},
  "geometry": {"coordinates":[11.5832672119,48.1048164368],"type":"Point"}
}