{
  "type": "Feature",
  "properties": {
    "iso:country":"DE",
    "sg:address":"Lietzenburger Str 88",
    "sg:city":"Berlin",
    "sg:phone":"+49 30/88007710",
    "sg:postcode":"10719",
    "sg:province":"Berlin",
    "wof:name":"Orthopedics Company",
    "wof:placetype":"venue"
},
  "geometry": {"coordinates":[13.3218259811,52.4999732971],"type":"Point"}
}