{
  "type": "Feature",
  "properties": {
    "iso:country":"DE",
    "sg:address":"Adlerstr. 37",
    "sg:city":"Ravensburg",
    "sg:phone":"+49 751/33252",
    "sg:postcode":"88212",
    "sg:province":"Baden-W\u00fcrttemberg",
    "wof:name":"Klaus Schlessmann Masseure",
    "wof:placetype":"venue"
},
  "geometry": {"coordinates":[9.60965,47.781864],"type":"Point"}
}