{
  "type": "Feature",
  "properties": {
    "iso:country":"DE",
    "sg:address":"Marktplatz",
    "sg:city":"Biberbach",
    "sg:phone":"+49 8271/5757",
    "sg:postcode":"86485",
    "sg:province":"Bayern",
    "wof:name":"Josef Kohl",
    "wof:placetype":"venue"
},
  "geometry": {"coordinates":[10.8121433258,48.5181465149],"type":"Point"}
}