{
  "type": "Feature",
  "properties": {
    "iso:country":"DE",
    "sg:address":"Hauptstr. 69",
    "sg:city":"Wettenberg",
    "sg:phone":"+49 4906/41",
    "sg:postcode":"35435",
    "sg:province":"Hessen",
    "wof:name":"Payer-elektrotechnik",
    "wof:placetype":"venue"
},
  "geometry": {"coordinates":[8.636176,50.626122],"type":"Point"}
}