{
  "type": "Feature",
  "properties": {
    "iso:country":"DE",
    "sg:address":"Rauensteinstr. 16 a",
    "sg:city":"\u00dcberlingen",
    "sg:phone":"+49 7551/2228",
    "sg:postcode":"88662",
    "sg:province":"Baden-W\u00fcrttemberg",
    "wof:name":"Pizzeria Zur Faulen Magd",
    "wof:placetype":"venue"
},
  "geometry": {"coordinates":[9.1724128723,47.7665748596],"type":"Point"}
}