{
  "type": "Feature",
  "properties": {
    "iso:country":"DE",
    "sg:address":"H\u00f6henweg 10",
    "sg:city":"Hagnau",
    "sg:phone":"+49 7532/450960",
    "sg:postcode":"88709",
    "sg:province":"Baden-W\u00fcrttemberg",
    "wof:name":"G. Schwarz",
    "wof:placetype":"venue"
},
  "geometry": {"coordinates":[9.31371,47.677086],"type":"Point"}
}