{
  "type": "Feature",
  "properties": {
    "iso:country":"DE",
    "sg:address":"Ludwigstr. 13 - 17",
    "sg:city":"Frankfurt",
    "sg:phone":"+49 69/242390",
    "sg:postcode":"60327",
    "sg:province":"Hessen",
    "wof:name":"Rema Hotel Bristol",
    "wof:placetype":"venue"
},
  "geometry": {"coordinates":[8.6588191986,50.1076850891],"type":"Point"}
}