{
  "type": "Feature",
  "properties": {
    "iso:country":"DE",
    "sg:address":"Heidestr. 233",
    "sg:city":"K\u00f6ln",
    "sg:phone":"+49 2203/966430",
    "sg:postcode":"51147",
    "sg:province":"Nordrhein-Westfalen",
    "wof:name":"Peter Werheid",
    "wof:placetype":"venue"
},
  "geometry": {"coordinates":[7.1057319641,50.8592338562],"type":"Point"}
}