{
  "type": "Feature",
  "properties": {
    "iso:country":"DE",
    "sg:address":"Marktstr. 37",
    "sg:city":"Wernigerode",
    "sg:phone":"+49 3943/632181",
    "sg:postcode":"38855",
    "sg:province":"Sachsen-Anhalt",
    "wof:name":"Hans-dieter Hellmund",
    "wof:placetype":"venue"
},
  "geometry": {"coordinates":[10.786559,51.831703],"type":"Point"}
}