{
  "type": "Feature",
  "properties": {
    "iso:country":"DE",
    "sg:address":"An der G\u00e4rtnerei 105",
    "sg:city":"Neuburg-Steinhausen",
    "sg:phone":"+49 38426/20569",
    "sg:postcode":"23974",
    "sg:province":"Mecklenburg-Vorpommern",
    "wof:name":"M\u00f6belhaus Lemke Gmbh",
    "wof:placetype":"venue"
},
  "geometry": {"coordinates":[11.584931,53.948997],"type":"Point"}
}