{
  "type": "Feature",
  "properties": {
    "iso:country":"DE",
    "sg:address":"N\u00fcrnberger Str. 100",
    "sg:city":"Bayreuth",
    "sg:postcode":"95448",
    "sg:province":"Bayern",
    "wof:name":"Einrichtungshaus Stark Gmbh",
    "wof:placetype":"venue"
},
  "geometry": {"coordinates":[11.5971698761,49.9280281067],"type":"Point"}
}