{
  "type": "Feature",
  "properties": {
    "iso:country":"DE",
    "sg:address":"Markt 1",
    "sg:city":"Gerbstedt",
    "sg:phone":"+49 34783/29219",
    "sg:postcode":"06347",
    "sg:province":"Sachsen-Anhalt",
    "wof:name":"Wohnungsgesellschaft Gerbstedt Und Umgebung Mbh",
    "wof:placetype":"venue"
},
  "geometry": {"coordinates":[11.6276960373,51.6319885254],"type":"Point"}
}