{
  "type": "Feature",
  "properties": {
    "iso:country":"DE",
    "sg:address":"Industriestr. 45",
    "sg:city":"Siegburg",
    "sg:phone":"+49 2241/63255",
    "sg:postcode":"53721",
    "sg:province":"Nordrhein-Westfalen",
    "wof:name":"Schmidt Metallbau Gmbh",
    "wof:placetype":"venue"
},
  "geometry": {"coordinates":[7.194984,50.800396],"type":"Point"}
}