{
  "type": "Feature",
  "properties": {
    "iso:country":"DE",
    "sg:address":"Graf-Spreti-Str. 14",
    "sg:city":"Hebertshausen",
    "sg:phone":"+49 8139/332",
    "sg:postcode":"85241",
    "sg:province":"Bayern",
    "wof:name":"Evg Ein- Und Verkaufsgenossenschaft Eg",
    "wof:placetype":"venue"
},
  "geometry": {"coordinates":[11.4471664429,48.3039627075],"type":"Point"}
}