{
  "type": "Feature",
  "properties": {
    "iso:country":"DE",
    "sg:address":"Bei den Funkt\u00fcrmen 4",
    "sg:city":"Stuttgart",
    "sg:phone":"+49 711/7261900",
    "sg:postcode":"70597",
    "sg:province":"Baden-W\u00fcrttemberg",
    "wof:name":"Eugen Fuchs",
    "wof:placetype":"venue"
},
  "geometry": {"coordinates":[9.179012,48.734013],"type":"Point"}
}