{
  "type": "Feature",
  "properties": {
    "iso:country":"DE",
    "sg:address":"Wittdornweg 4",
    "sg:city":"Mildstedt",
    "sg:phone":"+49 4841/662514",
    "sg:postcode":"25866",
    "sg:province":"Schleswig-Holstein",
    "wof:name":"Nordseehaus Gmbh",
    "wof:placetype":"venue"
},
  "geometry": {"coordinates":[9.094072,54.467224],"type":"Point"}
}