{
  "type": "Feature",
  "properties": {
    "iso:country":"DE",
    "sg:address":"Moniberg",
    "sg:city":"Landshut",
    "sg:phone":"+49 871/273611",
    "sg:postcode":"84028",
    "sg:province":"Bayern",
    "wof:name":"L. Kollmann",
    "wof:placetype":"venue"
},
  "geometry": {"coordinates":[12.1721467972,48.5369491577],"type":"Point"}
}