{
  "type": "Feature",
  "properties": {
    "iso:country":"DE",
    "sg:address":"Ferdinand-Langer-Str. 6",
    "sg:city":"Leimen",
    "sg:postcode":"69181",
    "sg:province":"Baden-W\u00fcrttemberg",
    "wof:name":"Mhc Consulting Gmbh",
    "wof:placetype":"venue"
},
  "geometry": {"coordinates":[8.6834726334,49.3448905945],"type":"Point"}
}