{
  "type": "Feature",
  "properties": {
    "iso:country":"DE",
    "sg:address":"Mittelstr. 6",
    "sg:city":"Thalhausen",
    "sg:phone":"+49 2639/334",
    "sg:postcode":"56584",
    "sg:province":"Rheinland-Pfalz",
    "wof:name":"Friedhelm Langhardt",
    "wof:placetype":"venue"
},
  "geometry": {"coordinates":[7.5801548958,50.5043182373],"type":"Point"}
}