{
  "type": "Feature",
  "properties": {
    "iso:country":"DE",
    "sg:address":"Blumenweg 24",
    "sg:city":"Heikendorf",
    "sg:phone":"+49 431/24606",
    "sg:postcode":"24226",
    "sg:province":"Schleswig-Holstein",
    "wof:name":"Max Hoof Jr.",
    "wof:placetype":"venue"
},
  "geometry": {"coordinates":[10.2042036057,54.3710479736],"type":"Point"}
}