{
  "type": "Feature",
  "properties": {
    "iso:country":"DE",
    "sg:address":"Krautgartenstr. 3",
    "sg:city":"Hebertshausen",
    "sg:postcode":"85241",
    "sg:province":"Bayern",
    "wof:name":"Augustenfelder Wasserkraft Gmbh",
    "wof:placetype":"venue"
},
  "geometry": {"coordinates":[11.470781,48.288136],"type":"Point"}
}