{
  "type": "Feature",
  "properties": {
    "iso:country":"DE",
    "sg:address":"Annenstr. 12",
    "sg:city":"Meerane",
    "sg:phone":"+49 3764/47197",
    "sg:postcode":"08393",
    "sg:province":"Sachsen",
    "wof:name":"T. Vasco",
    "wof:placetype":"venue"
},
  "geometry": {"coordinates":[12.462712,50.849388],"type":"Point"}
}