{
  "type": "Feature",
  "properties": {
    "iso:country":"DE",
    "sg:address":"Hauptstr. 26",
    "sg:city":"Bekm\u00fcnde",
    "sg:phone":"+49 4823/8185",
    "sg:postcode":"25524",
    "sg:province":"Schleswig-Holstein",
    "wof:name":"Uwe Krebs Gmbh",
    "wof:placetype":"venue"
},
  "geometry": {"coordinates":[9.4368247986,53.930519104],"type":"Point"}
}