{
  "type": "Feature",
  "properties": {
    "iso:country":"DE",
    "sg:address":"Im M\u00fchlenkamp 2",
    "sg:city":"Bochum",
    "sg:phone":"+49 234/288566",
    "sg:postcode":"44892",
    "sg:province":"Nordrhein-Westfalen",
    "wof:name":"Niederschultenhof Verwaltungs Gmbh",
    "wof:placetype":"venue"
},
  "geometry": {"coordinates":[7.332747,51.473713],"type":"Point"}
}