{
  "type": "Feature",
  "properties": {
    "iso:country":"DE",
    "sg:address":"Robert-Mayer-Str. 8",
    "sg:city":"Frankfurt",
    "sg:phone":"+49 69/7983420",
    "sg:postcode":"60325",
    "sg:province":"Hessen",
    "wof:name":"Mathematisches Seminar Bibliothek",
    "wof:placetype":"venue"
},
  "geometry": {"coordinates":[8.66031,50.114979],"type":"Point"}
}