{
  "type": "Feature",
  "properties": {
    "iso:country":"DE",
    "sg:address":"Bettinastr. 68",
    "sg:city":"Offenbach",
    "sg:phone":"+49 69/392088",
    "sg:postcode":"63067",
    "sg:province":"Hessen",
    "wof:name":"Aer-komtec Gmbh",
    "wof:placetype":"venue"
},
  "geometry": {"coordinates":[8.7489700317,50.1093711853],"type":"Point"}
}