{
  "type": "Feature",
  "properties": {
    "iso:country":"DE",
    "sg:address":"B\u00e4ckershof 19",
    "sg:city":"Solingen",
    "sg:phone":"+49 212/336004",
    "sg:postcode":"42699",
    "sg:province":"Nordrhein-Westfalen",
    "wof:name":"C. Duisberg Schwertloewen Gmbh & Co.",
    "wof:placetype":"venue"
},
  "geometry": {"coordinates":[7.039288,51.170616],"type":"Point"}
}