{
  "type": "Feature",
  "properties": {
    "iso:country":"DE",
    "sg:address":"Empeler Str. 112",
    "sg:city":"Rees",
    "sg:phone":"+49 4928/5191590",
    "sg:postcode":"46459",
    "sg:province":"Nordrhein-Westfalen",
    "wof:name":"Gebr. Raadts Gmbh & Co",
    "wof:placetype":"venue"
},
  "geometry": {"coordinates":[6.402951,51.775421],"type":"Point"}
}