{
  "type": "Feature",
  "properties": {
    "iso:country":"DE",
    "sg:address":"Hamburger Str. 14",
    "sg:city":"Bad Segeberg",
    "sg:phone":"+49 4551/963838",
    "sg:postcode":"23795",
    "sg:province":"Schleswig-Holstein",
    "wof:name":"Witt Reimers-witt Und B\u00fcge",
    "wof:placetype":"venue"
},
  "geometry": {"coordinates":[10.3060274124,53.9365310669],"type":"Point"}
}