{
  "type": "Feature",
  "properties": {
    "iso:country":"DE",
    "sg:address":"Eisenweg 1",
    "sg:city":"Meinerzhagen",
    "sg:phone":"+49 2354/92850",
    "sg:postcode":"58540",
    "sg:province":"Nordrhein-Westfalen",
    "wof:name":"Hsk-schulte Gmbh",
    "wof:placetype":"venue"
},
  "geometry": {"coordinates":[7.674498,51.097279],"type":"Point"}
}