{
  "type": "Feature",
  "properties": {
    "iso:country":"DE",
    "sg:address":"Vacher Str. 262",
    "sg:city":"F\u00fcrth",
    "sg:phone":"+49 911/738670",
    "sg:postcode":"90768",
    "sg:province":"Bayern",
    "wof:name":"Pizzeria Russolillo",
    "wof:placetype":"venue"
},
  "geometry": {"coordinates":[10.9681653976,49.5022315979],"type":"Point"}
}