{
  "type": "Feature",
  "properties": {
    "iso:country":"DE",
    "sg:address":"Fettstr. 6",
    "sg:city":"Hamburg",
    "sg:postcode":"20357",
    "sg:province":"Hamburg",
    "wof:name":"Plappergei Musikverlag Hamburg Rainer Gussek E. K.",
    "wof:placetype":"venue"
},
  "geometry": {"coordinates":[9.9634113312,53.5668754578],"type":"Point"}
}