{
  "type": "Feature",
  "properties": {
    "iso:country":"DE",
    "sg:address":"Gewerbestr. 1",
    "sg:city":"Uhldingen-M\u00fchlhofen",
    "sg:phone":"+49 7556/931813",
    "sg:postcode":"88690",
    "sg:province":"Baden-W\u00fcrttemberg",
    "wof:name":"Honnisoit Gmbh",
    "wof:placetype":"venue"
},
  "geometry": {"coordinates":[9.266193,47.736404],"type":"Point"}
}