{
  "type": "Feature",
  "properties": {
    "iso:country":"DE",
    "sg:address":"Osthover Weg 13",
    "sg:city":"D\u00fclmen",
    "sg:phone":"+49 2592/61604",
    "sg:postcode":"48249",
    "sg:province":"Nordrhein-Westfalen",
    "wof:name":"Werner Bzyl",
    "wof:placetype":"venue"
},
  "geometry": {"coordinates":[7.2894501686,51.8331794739],"type":"Point"}
}