{
  "type": "Feature",
  "properties": {
    "iso:country":"DE",
    "sg:address":"Schlo\u00dfstr. 1",
    "sg:city":"Dresden",
    "sg:phone":"+49 351/4956169",
    "sg:postcode":"01067",
    "sg:province":"Sachsen",
    "wof:name":"Kcg Kaufcenter Gmbh",
    "wof:placetype":"venue"
},
  "geometry": {"coordinates":[13.737092,51.050697],"type":"Point"}
}