{
  "type": "Feature",
  "properties": {
    "iso:country":"DE",
    "sg:address":"Mittelstr. 9",
    "sg:city":"Weitefeld",
    "sg:phone":"+49 2743/4200",
    "sg:postcode":"57586",
    "sg:province":"Rheinland-Pfalz",
    "wof:name":"Inge Schl\u00e4ger & Edith St\u00fchn",
    "wof:placetype":"venue"
},
  "geometry": {"coordinates":[7.929446,50.724312],"type":"Point"}
}