{
  "type": "Feature",
  "properties": {
    "iso:country":"DE",
    "sg:address":"Marktstr. 14",
    "sg:city":"Bad Wurzach",
    "sg:phone":"+49 7564/4667",
    "sg:postcode":"88410",
    "sg:province":"Baden-W\u00fcrttemberg",
    "wof:name":"Blumen-frisch",
    "wof:placetype":"venue"
},
  "geometry": {"coordinates":[9.896257,47.908333],"type":"Point"}
}