{
  "type": "Feature",
  "properties": {
    "iso:country":"DE",
    "sg:address":"Peter-Rosegger-Str. 27",
    "sg:city":"Cottbus",
    "sg:phone":"+49 355/873030",
    "sg:postcode":"03044",
    "sg:province":"Brandenburg",
    "wof:name":"Dr. Med. Johannes Mai",
    "wof:placetype":"venue"
},
  "geometry": {"coordinates":[14.31361,51.78624],"type":"Point"}
}