{
  "type": "Feature",
  "properties": {
    "iso:country":"DE",
    "sg:address":"Ferdinand-Schlufter-Str. 33",
    "sg:city":"Sondershausen",
    "sg:phone":"+49 3632/783291",
    "sg:postcode":"99706",
    "sg:province":"Th\u00fcringen",
    "wof:name":"Heike Knauf Masseur",
    "wof:placetype":"venue"
},
  "geometry": {"coordinates":[10.862196,51.369255],"type":"Point"}
}