{
  "type": "Feature",
  "properties": {
    "iso:country":"DE",
    "sg:address":"Severinstr. 104",
    "sg:city":"K\u00f6ln",
    "sg:phone":"+49 221/315269",
    "sg:postcode":"50678",
    "sg:province":"Nordrhein-Westfalen",
    "wof:name":"Em Scheffge",
    "wof:placetype":"venue"
},
  "geometry": {"coordinates":[6.9583668709,50.9262619019],"type":"Point"}
}