{
  "type": "Feature",
  "properties": {
    "iso:country":"DE",
    "sg:address":"In der Ruhstatt 43",
    "sg:city":"Diez",
    "sg:phone":"+49 6432/2072",
    "sg:postcode":"65582",
    "sg:province":"Rheinland-Pfalz",
    "wof:name":"Mineraliengesellschaft Heinrich M\u00fcller Gmbh & Co.",
    "wof:placetype":"venue"
},
  "geometry": {"coordinates":[8.0267429352,50.3738899231],"type":"Point"}
}