{
  "type": "Feature",
  "properties": {
    "iso:country":"DE",
    "sg:address":"Veilchenweg 8",
    "sg:city":"N\u00f6rdlingen",
    "sg:phone":"+49 9081/3805",
    "sg:postcode":"86720",
    "sg:province":"Bayern",
    "wof:name":"Hans-jakob Neher Architekt",
    "wof:placetype":"venue"
},
  "geometry": {"coordinates":[10.50026,48.852074],"type":"Point"}
}