{
  "type": "Feature",
  "properties": {
    "iso:country":"DE",
    "sg:address":"Dorfstr. 7",
    "sg:city":"Rotthalm\u00fcnster",
    "sg:postcode":"94094",
    "sg:province":"Bayern",
    "wof:name":"Merlin Transporte E. K.",
    "wof:placetype":"venue"
},
  "geometry": {"coordinates":[13.2138996124,48.3940353394],"type":"Point"}
}