{
  "type": "Feature",
  "properties": {
    "iso:country":"DE",
    "sg:address":"Langlachweg 19",
    "sg:city":"Mannheim",
    "sg:phone":"+49 621/477474",
    "sg:postcode":"68229",
    "sg:province":"Baden-W\u00fcrttemberg",
    "wof:name":"Mader Gmbh",
    "wof:placetype":"venue"
},
  "geometry": {"coordinates":[8.57534,49.440262],"type":"Point"}
}