{
  "type": "Feature",
  "properties": {
    "iso:country":"DE",
    "sg:address":"Carmerstr. 2",
    "sg:city":"Berlin",
    "sg:phone":"+49 30/3152054",
    "sg:postcode":"10623",
    "sg:province":"Berlin",
    "wof:name":"Christian Zanner Rechtsanwalt",
    "wof:placetype":"venue"
},
  "geometry": {"coordinates":[13.3248052597,52.508026123],"type":"Point"}
}