{
  "type": "Feature",
  "properties": {
    "iso:country":"DE",
    "sg:address":"Torsholt",
    "sg:city":"Westerstede",
    "sg:phone":"+49 4409/475",
    "sg:postcode":"26655",
    "sg:province":"Niedersachsen",
    "wof:name":"U. Mark",
    "wof:placetype":"venue"
},
  "geometry": {"coordinates":[7.941748,53.20805],"type":"Point"}
}