{
  "type": "Feature",
  "properties": {
    "iso:country":"DE",
    "sg:address":"Hauptstr. 134",
    "sg:city":"Gornsdorf",
    "sg:phone":"+49 3721/22531",
    "sg:postcode":"09390",
    "sg:province":"Sachsen",
    "wof:name":"L & L Gesellschaft F\u00fcr Schl\u00fcsselfertiges Bauen Mbh",
    "wof:placetype":"venue"
},
  "geometry": {"coordinates":[12.883843,50.702148],"type":"Point"}
}