{
  "type": "Feature",
  "properties": {
    "iso:country":"DE",
    "sg:address":"Nordstr. 20",
    "sg:city":"Gera",
    "sg:phone":"+49 365/810149",
    "sg:postcode":"07548",
    "sg:province":"Th\u00fcringen",
    "wof:name":"Hartmut Seidel",
    "wof:placetype":"venue"
},
  "geometry": {"coordinates":[12.0744600296,50.8664932251],"type":"Point"}
}