{
  "type": "Feature",
  "properties": {
    "iso:country":"DE",
    "sg:address":"Krengelstr. 34 e",
    "sg:city":"Dinslaken",
    "sg:phone":"+49 2064/49940",
    "sg:postcode":"46539",
    "sg:province":"Nordrhein-Westfalen",
    "wof:name":"Ellenbeck Metall Gmbh",
    "wof:placetype":"venue"
},
  "geometry": {"coordinates":[6.777788,51.545933],"type":"Point"}
}