{
  "type": "Feature",
  "properties": {
    "iso:country":"DE",
    "sg:address":"97990",
    "sg:city":"Weikersheim",
    "sg:phone":"+49 7934/8315",
    "sg:postcode":"97990",
    "sg:province":"Baden-W\u00fcrttemberg",
    "wof:name":"Deutsche Bahn Ag",
    "wof:placetype":"venue"
},
  "geometry": {"coordinates":[9.8906202316,49.4934310913],"type":"Point"}
}