{
  "type": "Feature",
  "properties": {
    "iso:country":"DE",
    "sg:address":"Wendfeld 9",
    "sg:city":"Stadtlohn",
    "sg:phone":"+49 8064/90880",
    "sg:postcode":"48703",
    "sg:province":"Nordrhein-Westfalen",
    "wof:name":"Lgu Deutschland Landschaft Garten U. Umwelt Vertriebs Gmbh",
    "wof:placetype":"venue"
},
  "geometry": {"coordinates":[11.9865045547,47.7992630005],"type":"Point"}
}