{
  "type": "Feature",
  "properties": {
    "iso:country":"DE",
    "sg:address":"Hochstr. 61",
    "sg:city":"Sonsbeck",
    "sg:phone":"+49 2838/778737",
    "sg:postcode":"47665",
    "sg:province":"Nordrhein-Westfalen",
    "wof:name":"Gnajda",
    "wof:placetype":"venue"
},
  "geometry": {"coordinates":[6.3765511513,51.6085472107],"type":"Point"}
}