{
  "type": "Feature",
  "properties": {
    "iso:country":"DE",
    "sg:address":"Erkelenzdamm 7",
    "sg:city":"Berlin",
    "sg:phone":"+49 30/6153945",
    "sg:postcode":"10999",
    "sg:province":"Berlin",
    "wof:name":"Ward Production Luger-molt- Wagner Textilhandels Ohg",
    "wof:placetype":"venue"
},
  "geometry": {"coordinates":[13.41543293,52.5008888245],"type":"Point"}
}