{
  "type": "Feature",
  "properties": {
    "iso:country":"DE",
    "sg:address":"Strandstr. 4",
    "sg:city":"Loddin",
    "sg:phone":"+49 38375/2360",
    "sg:postcode":"17459",
    "sg:province":"Mecklenburg-Vorpommern",
    "wof:name":"Gesellschaft F\u00fcr Freizeit Und Dienstleistung Mbh",
    "wof:placetype":"venue"
},
  "geometry": {"coordinates":[14.0169715881,54.0297927856],"type":"Point"}
}