{
  "type": "Feature",
  "properties": {
    "iso:country":"DE",
    "sg:address":"Damm 8",
    "sg:city":"Husum",
    "sg:phone":"+49 4841/6048",
    "sg:postcode":"25813",
    "sg:province":"Schleswig-Holstein",
    "wof:name":"Beratung F\u00fcr Psychisch Kranke Gesundheitsbeh\u00f6rde",
    "wof:placetype":"venue"
},
  "geometry": {"coordinates":[9.05171,54.473866],"type":"Point"}
}