{
  "type": "Feature",
  "properties": {
    "iso:country":"DE",
    "sg:address":"Kommandant-Prendel-Allee 97",
    "sg:city":"Leipzig",
    "sg:phone":"+49 341/8781710",
    "sg:postcode":"04299",
    "sg:province":"Sachsen",
    "wof:name":"Dr. Med. Martin Rosenkranz",
    "wof:placetype":"venue"
},
  "geometry": {"coordinates":[12.419946,51.312431],"type":"Point"}
}