{
  "type": "Feature",
  "properties": {
    "iso:country":"DE",
    "sg:address":"Schlossgrabengasse 10",
    "sg:city":"Offenbach/M",
    "sg:phone":"+49 69/80653000",
    "sg:postcode":"63065",
    "sg:province":"Hessen",
    "wof:name":"Gts",
    "wof:placetype":"venue"
},
  "geometry": {"coordinates":[8.765441,50.107075],"type":"Point"}
}