{
  "type": "Feature",
  "properties": {
    "iso:country":"DE",
    "sg:address":"Bad S\u00fclzer Str. 1",
    "sg:city":"Eixen",
    "sg:postcode":"18334",
    "sg:province":"Mecklenburg-Vorpommern",
    "wof:name":"Ev.-luth. Kirche",
    "wof:placetype":"venue"
},
  "geometry": {"coordinates":[12.722905159,54.1608314514],"type":"Point"}
}