{
  "type": "Feature",
  "properties": {
    "iso:country":"DE",
    "sg:address":"Havichhorster M\u00fchle 100",
    "sg:city":"M\u00fcnster",
    "sg:postcode":"48157",
    "sg:province":"Nordrhein-Westfalen",
    "wof:name":"Th. Hovestadt Gesch\u00e4ftsf\u00fchrungs Gmbh",
    "wof:placetype":"venue"
},
  "geometry": {"coordinates":[7.6884112358,52.0052833557],"type":"Point"}
}