{
  "type": "Feature",
  "properties": {
    "iso:country":"DE",
    "sg:address":"Medemstr. 10",
    "sg:city":"Otterndorf",
    "sg:phone":"+49 4751/2033",
    "sg:postcode":"21762",
    "sg:province":"Niedersachsen",
    "wof:name":"Johann Johannsen",
    "wof:placetype":"venue"
},
  "geometry": {"coordinates":[8.897362709,53.8059997559],"type":"Point"}
}