{
  "type": "Feature",
  "properties": {
    "iso:country":"DE",
    "sg:address":"Sch\u00fctzenstr. 71",
    "sg:city":"Lengerich",
    "sg:phone":"+49 5481/2471",
    "sg:postcode":"49525",
    "sg:province":"Nordrhein-Westfalen",
    "wof:name":"H. L\u00fcbke",
    "wof:placetype":"venue"
},
  "geometry": {"coordinates":[7.883556,52.15303],"type":"Point"}
}