{
  "type": "Feature",
  "properties": {
    "iso:country":"DE",
    "sg:address":"Mozartstr. 90",
    "sg:city":"Schriesheim",
    "sg:phone":"+49 6203/61392",
    "sg:postcode":"69198",
    "sg:province":"Baden-W\u00fcrttemberg",
    "wof:name":"Stefanie Selle",
    "wof:placetype":"venue"
},
  "geometry": {"coordinates":[8.650783,49.478313],"type":"Point"}
}