{
  "type": "Feature",
  "properties": {
    "iso:country":"DE",
    "sg:address":"Hiltersklinger Weg 7",
    "sg:city":"Grasellenbach",
    "sg:phone":"+49 6253/1645",
    "sg:postcode":"64689",
    "sg:province":"Hessen",
    "wof:name":"Horle & Kindinger Gmbh",
    "wof:placetype":"venue"
},
  "geometry": {"coordinates":[8.834859,49.639122],"type":"Point"}
}