{
  "type": "Feature",
  "properties": {
    "iso:country":"DE",
    "sg:address":"Breslauer Str. 9",
    "sg:city":"Bobenheim-Roxheim",
    "sg:postcode":"67240",
    "sg:province":"Rheinland-Pfalz",
    "wof:name":"Chicca Body-fashion Vertriebs Gmbh",
    "wof:placetype":"venue"
},
  "geometry": {"coordinates":[8.359972,49.575153],"type":"Point"}
}