{
  "type": "Feature",
  "properties": {
    "iso:country":"DE",
    "sg:address":"Weiherstr. 8",
    "sg:city":"Taunusstein",
    "sg:phone":"+49 6128/44449",
    "sg:postcode":"65232",
    "sg:province":"Hessen",
    "wof:name":"La Maison",
    "wof:placetype":"venue"
},
  "geometry": {"coordinates":[8.1859750748,50.1545257568],"type":"Point"}
}