{
  "type": "Feature",
  "properties": {
    "iso:country":"DE",
    "sg:address":"Hohenwartstr. 10",
    "sg:city":"Marktoberdorf",
    "sg:phone":"+49 8342/98569",
    "sg:postcode":"87616",
    "sg:province":"Bayern",
    "wof:name":"Michael Druckmiller Gmbh & Co. Kg",
    "wof:placetype":"venue"
},
  "geometry": {"coordinates":[10.622464,47.778332],"type":"Point"}
}