{
  "type": "Feature",
  "properties": {
    "iso:country":"DE",
    "sg:address":"M\u00f6rikestr. 2",
    "sg:city":"Kassel",
    "sg:phone":"+49 561/8709734",
    "sg:postcode":"34125",
    "sg:province":"Hessen",
    "wof:name":"Lothar Wagner",
    "wof:placetype":"venue"
},
  "geometry": {"coordinates":[9.5129070282,51.3338241577],"type":"Point"}
}