{
  "type": "Feature",
  "properties": {
    "iso:country":"DE",
    "sg:address":"Platenstr. 19",
    "sg:city":"Ansbach",
    "sg:phone":"+49 981/14567",
    "sg:postcode":"91522",
    "sg:province":"Bayern",
    "wof:name":"B\u00f6ker & Mundry Werbeagentur Gmbh",
    "wof:placetype":"venue"
},
  "geometry": {"coordinates":[10.5711593628,49.3020477295],"type":"Point"}
}