{
  "type": "Feature",
  "properties": {
    "iso:country":"DE",
    "sg:address":"Trebetastr. 11",
    "sg:city":"Trier",
    "sg:phone":"+49 651/938070",
    "sg:postcode":"54296",
    "sg:province":"Rheinland-Pfalz",
    "wof:name":"Heribert Und Wolfgang Just Steuerberater",
    "wof:placetype":"venue"
},
  "geometry": {"coordinates":[6.6541938782,49.7258834839],"type":"Point"}
}