{
  "type": "Feature",
  "properties": {
    "iso:country":"DE",
    "sg:address":"Am Sportplatz 5",
    "sg:city":"Oerlinghausen",
    "sg:phone":"+49 5202/71993",
    "sg:postcode":"33813",
    "sg:province":"Nordrhein-Westfalen",
    "wof:name":"Wc-cleener Mietservice Bosse Gmbh",
    "wof:placetype":"venue"
},
  "geometry": {"coordinates":[8.7157316208,51.9772338867],"type":"Point"}
}