{
  "type": "Feature",
  "properties": {
    "iso:country":"DE",
    "sg:address":"Steindamm 1",
    "sg:city":"Wilster",
    "sg:postcode":"25554",
    "sg:province":"Schleswig-Holstein",
    "wof:name":"Fiffty-fiffty",
    "wof:placetype":"venue"
},
  "geometry": {"coordinates":[9.38509655,53.9242630005],"type":"Point"}
}