{
  "type": "Feature",
  "properties": {
    "iso:country":"DE",
    "sg:address":"Lanckensburg",
    "sg:city":"Altenkirchen",
    "sg:postcode":"18556",
    "sg:province":"Mecklenburg-Vorpommern",
    "wof:name":"Dtw Dienstleistungs- Und Transportgesellschaft Mbh",
    "wof:placetype":"venue"
},
  "geometry": {"coordinates":[13.3224315643,54.6317825317],"type":"Point"}
}