{
  "type": "Feature",
  "properties": {
    "iso:country":"DE",
    "sg:address":"Herbststr. 85",
    "sg:city":"Bremen",
    "sg:phone":"+49 421/370938",
    "sg:postcode":"28215",
    "sg:province":"Bremen",
    "wof:name":"Anna Bushart Und Heike K\u00f6hler-homann",
    "wof:placetype":"venue"
},
  "geometry": {"coordinates":[8.806174,53.090942],"type":"Point"}
}