{
  "type": "Feature",
  "properties": {
    "iso:country":"DE",
    "sg:address":"Uhlandstr. 23",
    "sg:city":"Blaustein",
    "sg:phone":"+49 731/551151",
    "sg:postcode":"89134",
    "sg:province":"Baden-W\u00fcrttemberg",
    "wof:name":"Werner Seidel Architekt",
    "wof:placetype":"venue"
},
  "geometry": {"coordinates":[9.937636,48.409466],"type":"Point"}
}