{
  "type": "Feature",
  "properties": {
    "iso:country":"DE",
    "sg:address":"Am Holl\u00e4nder 16",
    "sg:city":"Finsterwalde",
    "sg:phone":"+49 3531/2043",
    "sg:postcode":"03238",
    "sg:province":"Brandenburg",
    "wof:name":"Schmidt-elsner",
    "wof:placetype":"venue"
},
  "geometry": {"coordinates":[13.71778,51.641121],"type":"Point"}
}