{
  "type": "Feature",
  "properties": {
    "iso:country":"DE",
    "sg:address":"Frankfurter Allee 98",
    "sg:city":"Berlin",
    "sg:phone":"+49 30/53649901",
    "sg:postcode":"10439",
    "sg:province":"Berlin",
    "wof:name":"Funworld Jeton",
    "wof:placetype":"venue"
},
  "geometry": {"coordinates":[13.472615,52.513721],"type":"Point"}
}