{
  "type": "Feature",
  "properties": {
    "iso:country":"DE",
    "sg:address":"Wasserm\u00fchlenstr. 32",
    "sg:city":"Kappeln",
    "sg:phone":"+49 4642/3481",
    "sg:postcode":"24376",
    "sg:province":"Schleswig-Holstein",
    "wof:name":"Teppich-laden Rolf Barwitzki E. K.",
    "wof:placetype":"venue"
},
  "geometry": {"coordinates":[9.931664,54.6684],"type":"Point"}
}