{
  "type": "Feature",
  "properties": {
    "iso:country":"DE",
    "sg:address":"Am G\u00e4xwald 17",
    "sg:city":"Herxheim",
    "sg:phone":"+49 7276/98700",
    "sg:postcode":"76863",
    "sg:province":"Rheinland-Pfalz",
    "wof:name":"City Satz Gmbh",
    "wof:placetype":"venue"
},
  "geometry": {"coordinates":[8.237496,49.140614],"type":"Point"}
}