{
  "type": "Feature",
  "properties": {
    "iso:country":"DE",
    "sg:address":"M\u00fchlbachstr. 14",
    "sg:city":"Bruchk\u00f6bel",
    "sg:phone":"+49 6181/976110",
    "sg:postcode":"63486",
    "sg:province":"Hessen",
    "wof:name":"Winterling Gmbh",
    "wof:placetype":"venue"
},
  "geometry": {"coordinates":[8.9174032211,50.181186676],"type":"Point"}
}