{
  "type": "Feature",
  "properties": {
    "iso:country":"DE",
    "sg:address":"Krumbacherstr. 5",
    "sg:city":"Augsburg",
    "sg:postcode":"86154",
    "sg:province":"Bayern",
    "wof:name":"Griechbaum Gmbh",
    "wof:placetype":"venue"
},
  "geometry": {"coordinates":[10.8732376099,48.4005012512],"type":"Point"}
}