{
  "type": "Feature",
  "properties": {
    "iso:country":"DE",
    "sg:address":"Aschaffenburger Str. 32",
    "sg:city":"Kahl",
    "sg:phone":"+49 6188/81237",
    "sg:postcode":"63796",
    "sg:province":"Bayern",
    "wof:name":"Monika Well Up-to-date",
    "wof:placetype":"venue"
},
  "geometry": {"coordinates":[9.005341,50.065594],"type":"Point"}
}