{
  "type": "Feature",
  "properties": {
    "iso:country":"DE",
    "sg:address":"Marktstr. 23",
    "sg:city":"Schramberg",
    "sg:phone":"+49 7422/240422",
    "sg:postcode":"78713",
    "sg:province":"Baden-W\u00fcrttemberg",
    "wof:name":"La Piazzetta",
    "wof:placetype":"venue"
},
  "geometry": {"coordinates":[8.3849859238,48.2263755798],"type":"Point"}
}