{
  "type": "Feature",
  "properties": {
    "iso:country":"DE",
    "sg:address":"Ludwig-Thoma-Str. 30",
    "sg:city":"Ottobrunn",
    "sg:phone":"+49 89/603298",
    "sg:postcode":"85521",
    "sg:province":"Bayern",
    "wof:name":"Helmut Ga\u00dfner Architekt",
    "wof:placetype":"venue"
},
  "geometry": {"coordinates":[11.678449,48.06459],"type":"Point"}
}