{
  "type": "Feature",
  "properties": {
    "iso:country":"DE",
    "sg:address":"Gro\u00dfenbaumer Str. 15",
    "sg:city":"M\u00fclheim",
    "sg:phone":"+49 208/422041",
    "sg:postcode":"45481",
    "sg:province":"Nordrhein-Westfalen",
    "wof:name":"Volker Bu\u00dfmann Architekt",
    "wof:placetype":"venue"
},
  "geometry": {"coordinates":[6.85788,51.412563],"type":"Point"}
}