{
  "type": "Feature",
  "properties": {
    "iso:country":"DE",
    "sg:address":"Baurstr. 8",
    "sg:city":"Kornwestheim",
    "sg:phone":"+49 7154/26248",
    "sg:postcode":"70806",
    "sg:province":"Baden-W\u00fcrttemberg",
    "wof:name":"B. Bergs",
    "wof:placetype":"venue"
},
  "geometry": {"coordinates":[9.200527,48.866344],"type":"Point"}
}