{
  "type": "Feature",
  "properties": {
    "iso:country":"DE",
    "sg:address":"Am Fleck 1",
    "sg:city":"Landsberg",
    "sg:phone":"+49 8191/42282",
    "sg:postcode":"86899",
    "sg:province":"Bayern",
    "wof:name":"Dr. Horst Klincke Tierarzt",
    "wof:placetype":"venue"
},
  "geometry": {"coordinates":[10.8605804443,48.0398750305],"type":"Point"}
}