{
  "type": "Feature",
  "properties": {
    "iso:country":"DE",
    "sg:address":"Schillerstr. 17",
    "sg:city":"Extertal",
    "sg:phone":"+49 5262/2290",
    "sg:postcode":"32699",
    "sg:province":"Nordrhein-Westfalen",
    "wof:name":"Monika Schwabedissen Masseurin",
    "wof:placetype":"venue"
},
  "geometry": {"coordinates":[9.120596,52.07386],"type":"Point"}
}