{
  "type": "Feature",
  "properties": {
    "iso:country":"DE",
    "sg:address":"Bertoldstr. 9",
    "sg:city":"Seelbach",
    "sg:phone":"+49 7823/1647",
    "sg:postcode":"77960",
    "sg:province":"Baden-W\u00fcrttemberg",
    "wof:name":"Della Valle Inh. Pascal Della Valle",
    "wof:placetype":"venue"
},
  "geometry": {"coordinates":[7.9403700829,48.3143157959],"type":"Point"}
}