{
  "type": "Feature",
  "properties": {
    "iso:country":"DE",
    "sg:address":"Augsburger Str. 666",
    "sg:city":"Stuttgart",
    "sg:postcode":"70329",
    "sg:province":"Baden-W\u00fcrttemberg",
    "wof:name":"Vitaversum Gmbh",
    "wof:placetype":"venue"
},
  "geometry": {"coordinates":[9.2683391571,48.7633094788],"type":"Point"}
}