{
  "type": "Feature",
  "properties": {
    "iso:country":"DE",
    "sg:address":"Collmener Str.",
    "sg:city":"Wurzen",
    "sg:phone":"+49 3425/924728",
    "sg:postcode":"04808",
    "sg:province":"Sachsen",
    "wof:name":"Seifert",
    "wof:placetype":"venue"
},
  "geometry": {"coordinates":[12.739862,51.381428],"type":"Point"}
}