{
  "type": "Feature",
  "properties": {
    "iso:country":"DE",
    "sg:address":"Boschstr. 1 POSTFACH 1162",
    "sg:city":"Ditzingen",
    "sg:phone":"+49 4971/563520",
    "sg:postcode":"71240",
    "sg:province":"Baden-W\u00fcrttemberg",
    "wof:name":"Cetelon Lackfabrikwalter Stier Gmbh & Co. Kg",
    "wof:placetype":"venue"
},
  "geometry": {"coordinates":[9.083095,48.821831],"type":"Point"}
}