{
  "type": "Feature",
  "properties": {
    "iso:country":"DE",
    "sg:address":"Riederner Str. 2",
    "sg:city":"Neunkirchen",
    "sg:phone":"+49 9378/284",
    "sg:postcode":"63930",
    "sg:province":"Bayern",
    "wof:name":"Heinz Bick",
    "wof:placetype":"venue"
},
  "geometry": {"coordinates":[9.401203,49.687363],"type":"Point"}
}