{
  "type": "Feature",
  "properties": {
    "iso:country":"DE",
    "sg:address":"Granastr. 54",
    "sg:city":"Konz",
    "sg:phone":"+49 6501/3362",
    "sg:postcode":"54329",
    "sg:province":"Rheinland-Pfalz",
    "wof:name":"Royal Spielstuben Gmbh",
    "wof:placetype":"venue"
},
  "geometry": {"coordinates":[6.573153019,49.6994972229],"type":"Point"}
}