{
  "type": "Feature",
  "properties": {
    "iso:country":"DE",
    "sg:address":"Dr.-Franz-Langecker-Str. 26",
    "sg:city":"Hausham",
    "sg:phone":"+49 8026/3109",
    "sg:postcode":"83734",
    "sg:province":"Bayern",
    "wof:name":"Avp Audio-video Paradies",
    "wof:placetype":"venue"
},
  "geometry": {"coordinates":[11.8405714035,47.7477073669],"type":"Point"}
}