{
  "type": "Feature",
  "properties": {
    "iso:country":"DE",
    "sg:address":"An der Klinge 11",
    "sg:city":"Wertheim",
    "sg:phone":"+49 9397/559",
    "sg:postcode":"97877",
    "sg:province":"Baden-W\u00fcrttemberg",
    "wof:name":"E. Strau\u00df",
    "wof:placetype":"venue"
},
  "geometry": {"coordinates":[9.6133937836,49.765712738],"type":"Point"}
}