{
  "type": "Feature",
  "properties": {
    "iso:country":"DE",
    "sg:address":"B\u00fcdiger Weg 12",
    "sg:city":"K\u00f6ln",
    "sg:phone":"+49 221/799488",
    "sg:postcode":"50767",
    "sg:province":"Nordrhein-Westfalen",
    "wof:name":"Rosemarie K\u00f6rber",
    "wof:placetype":"venue"
},
  "geometry": {"coordinates":[6.8894047737,51.0015678406],"type":"Point"}
}