{
  "type": "Feature",
  "properties": {
    "iso:country":"DE",
    "sg:address":"Peusstr. 72",
    "sg:city":"Dessau",
    "sg:phone":"+49 340/616490",
    "sg:postcode":"06846",
    "sg:province":"Sachsen-Anhalt",
    "wof:name":"Dr. Med. Dieter Porrmann",
    "wof:placetype":"venue"
},
  "geometry": {"coordinates":[12.219768,51.841908],"type":"Point"}
}