{
  "type": "Feature",
  "properties": {
    "iso:country":"DE",
    "sg:address":"H\u00f6lderlinweg 2",
    "sg:city":"L\u00fcnen",
    "sg:phone":"+49 2306/50397",
    "sg:postcode":"44534",
    "sg:province":"Nordrhein-Westfalen",
    "wof:name":"Polychem J. Kohl Verwaltungs- Und",
    "wof:placetype":"venue"
},
  "geometry": {"coordinates":[7.541472,51.628151],"type":"Point"}
}