{
  "type": "Feature",
  "properties": {
    "iso:country":"DE",
    "sg:address":"Am Wiehen 106",
    "sg:city":"H\u00fcllhorst",
    "sg:phone":"+49 5744/4000",
    "sg:postcode":"32609",
    "sg:province":"Nordrhein-Westfalen",
    "wof:name":"Horst Unterk\u00f6tter Architekt",
    "wof:placetype":"venue"
},
  "geometry": {"coordinates":[8.686776,52.292339],"type":"Point"}
}