{
  "type": "Feature",
  "properties": {
    "iso:country":"DE",
    "sg:address":"Hermannstr. 24",
    "sg:city":"Offenbach",
    "sg:postcode":"63069",
    "sg:province":"Hessen",
    "wof:name":"Handwerkerbaugenos. Eg",
    "wof:placetype":"venue"
},
  "geometry": {"coordinates":[8.760511,50.097385],"type":"Point"}
}