{
  "type": "Feature",
  "properties": {
    "iso:country":"DE",
    "sg:address":"Weinbergstr. 1a",
    "sg:city":"Platten",
    "sg:phone":"+49 6535/807",
    "sg:postcode":"54518",
    "sg:province":"Rheinland-Pfalz",
    "wof:name":"Hildegard G\u00f6rgen",
    "wof:placetype":"venue"
},
  "geometry": {"coordinates":[6.954460144,49.9508552551],"type":"Point"}
}