{
  "type": "Feature",
  "properties": {
    "iso:country":"DE",
    "sg:address":"Kirchenweg 3",
    "sg:city":"Petersaurach",
    "sg:phone":"+49 9872/7452",
    "sg:postcode":"91580",
    "sg:province":"Bayern",
    "wof:name":"Herbert Geyer",
    "wof:placetype":"venue"
},
  "geometry": {"coordinates":[10.7265739441,49.3368301392],"type":"Point"}
}