{
  "type": "Feature",
  "properties": {
    "iso:country":"DE",
    "sg:address":"Grenzweg 2",
    "sg:city":"Saalow",
    "sg:phone":"+49 3377/301022",
    "sg:postcode":"15806",
    "sg:province":"Brandenburg",
    "wof:name":"Werner Enge",
    "wof:placetype":"venue"
},
  "geometry": {"coordinates":[13.396887,52.191341],"type":"Point"}
}