{
  "type": "Feature",
  "properties": {
    "iso:country":"DE",
    "sg:address":"Bruchstr.",
    "sg:city":"Willich",
    "sg:phone":"+49 2154/7906",
    "sg:postcode":"47877",
    "sg:province":"Nordrhein-Westfalen",
    "wof:name":"Schiefbahn Gmbh",
    "wof:placetype":"venue"
},
  "geometry": {"coordinates":[6.4651608467,51.2558441162],"type":"Point"}
}