{
  "type": "Feature",
  "properties": {
    "iso:country":"DE",
    "sg:address":"Bahnhofstr. 9",
    "sg:city":"Eckental",
    "sg:phone":"+49 9126/285010",
    "sg:postcode":"90542",
    "sg:province":"Bayern",
    "wof:name":"Industrievertretung Norbert Weidinger",
    "wof:placetype":"venue"
},
  "geometry": {"coordinates":[11.1998119354,49.5751991272],"type":"Point"}
}