{
  "type": "Feature",
  "properties": {
    "iso:country":"DE",
    "sg:address":"Rosenstr. 17",
    "sg:city":"Schlangenbad",
    "sg:phone":"+49 6129/9442",
    "sg:postcode":"65388",
    "sg:province":"Hessen",
    "wof:name":"Vus Beratende Ingenieure F\u00fcr Verkehrswesen Umweltschutz Und",
    "wof:placetype":"venue"
},
  "geometry": {"coordinates":[8.0750551224,50.1041564941],"type":"Point"}
}