{
  "type": "Feature",
  "properties": {
    "iso:country":"DE",
    "sg:address":"Kirchenplatz 20",
    "sg:city":"M\u00fchldorf",
    "sg:phone":"+49 8631/5767",
    "sg:postcode":"84453",
    "sg:province":"Bayern",
    "wof:name":"Katholisches Pfarramt St. Nikolaus",
    "wof:placetype":"venue"
},
  "geometry": {"coordinates":[12.5278406143,48.2407913208],"type":"Point"}
}