{
  "type": "Feature",
  "properties": {
    "iso:country":"DE",
    "sg:address":"K\u00f6lnstr. 235",
    "sg:city":"Br\u00fchl",
    "sg:postcode":"50321",
    "sg:province":"Nordrhein-Westfalen",
    "wof:name":"Oppermann Verm\u00f6gens- Verwaltungs- Und",
    "wof:placetype":"venue"
},
  "geometry": {"coordinates":[6.91098,50.840153],"type":"Point"}
}