{
  "type": "Feature",
  "properties": {
    "iso:country":"DE",
    "sg:address":"Gr\u00fcnentalstr. 36",
    "sg:city":"Monschau",
    "sg:phone":"+49 2472/3931",
    "sg:postcode":"52156",
    "sg:province":"Nordrhein-Westfalen",
    "wof:name":"Campingplatz Zum Jone-bur",
    "wof:placetype":"venue"
},
  "geometry": {"coordinates":[6.274013,50.564175],"type":"Point"}
}