{
  "type": "Feature",
  "properties": {
    "iso:country":"DE",
    "sg:address":"D\u00fcsseldorfer Str. 189",
    "sg:city":"D\u00fcsseldorf",
    "sg:phone":"+49 211/557240",
    "sg:postcode":"40545",
    "sg:province":"Nordrhein-Westfalen",
    "wof:name":"Focus Brandt & Szlema Gmbh",
    "wof:placetype":"venue"
},
  "geometry": {"coordinates":[6.7422227859,51.2299842834],"type":"Point"}
}