{
  "type": "Feature",
  "properties": {
    "iso:country":"DE",
    "sg:address":"Hindenburgstr. 49",
    "sg:city":"M\u00f6nchengladbach",
    "sg:phone":"+49 2161/181918",
    "sg:postcode":"41061",
    "sg:province":"Nordrhein-Westfalen",
    "wof:name":"L Tur Agentur Mg",
    "wof:placetype":"venue"
},
  "geometry": {"coordinates":[6.4351820946,51.1941261292],"type":"Point"}
}