{
  "type": "Feature",
  "properties": {
    "iso:country":"DE",
    "sg:address":"Rubensstr. 25",
    "sg:city":"Ludwigshafen",
    "sg:phone":"+49 621/569217",
    "sg:postcode":"67061",
    "sg:province":"Rheinland-Pfalz",
    "wof:name":"Erich Bremicker",
    "wof:placetype":"venue"
},
  "geometry": {"coordinates":[8.4479856491,49.4692802429],"type":"Point"}
}