{
  "type": "Feature",
  "properties": {
    "iso:country":"DE",
    "sg:address":"Parkstr. 28",
    "sg:city":"L\u00fcbeck",
    "sg:phone":"+49 451/35046",
    "sg:postcode":"23568",
    "sg:province":"Schleswig-Holstein",
    "wof:name":"Dieter Hohoff Finanzberater",
    "wof:placetype":"venue"
},
  "geometry": {"coordinates":[10.7016973495,53.8775062561],"type":"Point"}
}