{
  "type": "Feature",
  "properties": {
    "iso:country":"DE",
    "sg:address":"Gerstenstr. 25",
    "sg:city":"Neus\u00e4\u00df",
    "sg:phone":"+49 821/487240",
    "sg:postcode":"86356",
    "sg:province":"Bayern",
    "wof:name":"Wolfgang Trautwein",
    "wof:placetype":"venue"
},
  "geometry": {"coordinates":[10.8080463409,48.4012565613],"type":"Point"}
}