{
  "type": "Feature",
  "properties": {
    "iso:country":"DE",
    "sg:address":"Unter Fettenhennen 2",
    "sg:city":"K\u00f6ln",
    "sg:phone":"+49 221/2577549",
    "sg:postcode":"50667",
    "sg:province":"Nordrhein-Westfalen",
    "wof:name":"Br\u00e4u-st\u00fcberl",
    "wof:placetype":"venue"
},
  "geometry": {"coordinates":[6.9563398361,50.9407043457],"type":"Point"}
}