{
  "type": "Feature",
  "properties": {
    "iso:country":"DE",
    "sg:address":"Eichenweg 12",
    "sg:city":"Hamberge",
    "sg:phone":"+49 451/891441",
    "sg:postcode":"23619",
    "sg:province":"Schleswig-Holstein",
    "wof:name":"Heinz Schmalfeldt",
    "wof:placetype":"venue"
},
  "geometry": {"coordinates":[10.5832252502,53.8394927979],"type":"Point"}
}