{
  "type": "Feature",
  "properties": {
    "iso:country":"DE",
    "sg:address":"Friedrich-Ebert-Str. 9 a",
    "sg:city":"Solingen",
    "sg:postcode":"42719",
    "sg:province":"Nordrhein-Westfalen",
    "wof:name":"Tablos Orientierungs- Systeme Gmbh",
    "wof:placetype":"venue"
},
  "geometry": {"coordinates":[7.0530161858,51.1864547729],"type":"Point"}
}