{
  "type": "Feature",
  "properties": {
    "iso:country":"DE",
    "sg:address":"F\u00f6rsterweg 50",
    "sg:city":"Hamburg",
    "sg:phone":"+49 40/543964",
    "sg:postcode":"22525",
    "sg:province":"Hamburg",
    "wof:name":"Klaus H\u00e4berle",
    "wof:placetype":"venue"
},
  "geometry": {"coordinates":[9.9286680222,53.5793991089],"type":"Point"}
}