{
  "type": "Feature",
  "properties": {
    "iso:country":"DE",
    "sg:address":"Koblenzer Str. 40",
    "sg:city":"Bad Breisig",
    "sg:postcode":"53498",
    "sg:province":"Rheinland-Pfalz",
    "wof:name":"Honrath-kurth Restaurator",
    "wof:placetype":"venue"
},
  "geometry": {"coordinates":[7.3016309738,50.5069847107],"type":"Point"}
}