{
  "type": "Feature",
  "properties": {
    "iso:country":"DE",
    "sg:address":"Rathenaustr. 18",
    "sg:city":"Senftenberg",
    "sg:phone":"+49 3573/790544",
    "sg:postcode":"01968",
    "sg:province":"Brandenburg",
    "wof:name":"Dagobert Nowatzki",
    "wof:placetype":"venue"
},
  "geometry": {"coordinates":[14.0058765411,51.5238761902],"type":"Point"}
}