{
  "type": "Feature",
  "properties": {
    "iso:country":"DE",
    "sg:address":"Agathastr. 70",
    "sg:city":"D\u00fcren",
    "sg:phone":"+49 2421/62161",
    "sg:postcode":"52355",
    "sg:province":"Nordrhein-Westfalen",
    "wof:name":"D\u00fcrener Elementebau",
    "wof:placetype":"venue"
},
  "geometry": {"coordinates":[6.426767,50.797005],"type":"Point"}
}