{
  "type": "Feature",
  "properties": {
    "iso:country":"DE",
    "sg:address":"Teichstr. 2",
    "sg:city":"Schleiz",
    "sg:phone":"+49 3663/422308",
    "sg:postcode":"07907",
    "sg:province":"Th\u00fcringen",
    "wof:name":"Klaus Hoffmann",
    "wof:placetype":"venue"
},
  "geometry": {"coordinates":[11.810063,50.578053],"type":"Point"}
}