{
  "type": "Feature",
  "properties": {
    "iso:country":"DE",
    "sg:address":"Hauptstr. 16",
    "sg:city":"Oberdachstetten",
    "sg:phone":"+49 9845/258",
    "sg:postcode":"91617",
    "sg:province":"Bayern",
    "wof:name":"Raiffeisenbank Flachslanden Eg",
    "wof:placetype":"venue"
},
  "geometry": {"coordinates":[10.423306,49.41534],"type":"Point"}
}