{
  "type": "Feature",
  "properties": {
    "iso:country":"DE",
    "sg:address":"G\u00f6rlitzer Str. 15 a",
    "sg:city":"Freilassing",
    "sg:phone":"+49 8654/61100",
    "sg:postcode":"83395",
    "sg:province":"Bayern",
    "wof:name":"Gertraud Canavate Riera",
    "wof:placetype":"venue"
},
  "geometry": {"coordinates":[12.9636306763,47.8534507751],"type":"Point"}
}