{
  "type": "Feature",
  "properties": {
    "iso:country":"DE",
    "sg:address":"Hauptstr. 48",
    "sg:city":"M\u00f6gglingen",
    "sg:phone":"+49 7174/7310",
    "sg:postcode":"73563",
    "sg:province":"Baden-W\u00fcrttemberg",
    "wof:name":"C. Carrasco",
    "wof:placetype":"venue"
},
  "geometry": {"coordinates":[9.9648723602,48.8224754333],"type":"Point"}
}