{
  "type": "Feature",
  "properties": {
    "iso:country":"DE",
    "sg:address":"Edendorfer Str. 139",
    "sg:city":"Itzehoe",
    "sg:phone":"+49 4821/75508",
    "sg:postcode":"25524",
    "sg:province":"Schleswig-Holstein",
    "wof:name":"Rode Gmbh",
    "wof:placetype":"venue"
},
  "geometry": {"coordinates":[9.4968576431,53.9415588379],"type":"Point"}
}