{
  "type": "Feature",
  "properties": {
    "iso:country":"DE",
    "sg:address":"Grubm\u00fchlstr. 10",
    "sg:city":"Hebertshausen",
    "sg:phone":"+49 8131/321869",
    "sg:postcode":"85241",
    "sg:province":"Bayern",
    "wof:name":"W\u00f6rmann Gmbh",
    "wof:placetype":"venue"
},
  "geometry": {"coordinates":[11.48014,48.289593],"type":"Point"}
}