{
  "type": "Feature",
  "properties": {
    "iso:country":"DE",
    "sg:address":"Industriestr. 6",
    "sg:city":"Geeste",
    "sg:postcode":"49744",
    "sg:province":"Niedersachsen",
    "wof:name":"Original Kinderland Spielplatzger\u00e4te B\u00e4hre",
    "wof:placetype":"venue"
},
  "geometry": {"coordinates":[7.21963,52.585369],"type":"Point"}
}