{
  "type": "Feature",
  "properties": {
    "iso:country":"DE",
    "sg:address":"Berliner Str. 29",
    "sg:city":"Herford",
    "sg:phone":"+49 5221/10580",
    "sg:postcode":"32052",
    "sg:province":"Nordrhein-Westfalen",
    "wof:name":"Hotel-restaurant M\u00fcnchner Hof",
    "wof:placetype":"venue"
},
  "geometry": {"coordinates":[8.6756105423,52.1177902222],"type":"Point"}
}