{
  "type": "Feature",
  "properties": {
    "iso:country":"DE",
    "sg:address":"Kesselsdorfer Str 47",
    "sg:city":"Dresden",
    "sg:phone":"+49 351/4190519",
    "sg:postcode":"01159",
    "sg:province":"Sachsen",
    "wof:name":"Haid Kg",
    "wof:placetype":"venue"
},
  "geometry": {"coordinates":[13.689712,51.042419],"type":"Point"}
}