{
  "type": "Feature",
  "properties": {
    "iso:country":"DE",
    "sg:address":"Au\u00dferhalb 60 Kieswerk B 44",
    "sg:city":"Langen",
    "sg:phone":"+49 69/697010",
    "sg:postcode":"63225",
    "sg:province":"Hessen",
    "wof:name":"Sehring Ag",
    "wof:placetype":"venue"
},
  "geometry": {"coordinates":[8.6635704041,49.9900588989],"type":"Point"}
}