{
  "type": "Feature",
  "properties": {
    "iso:country":"DE",
    "sg:address":"Am Hohen Markstein",
    "sg:city":"Buchen",
    "sg:phone":"+49 6281/97539",
    "sg:postcode":"74722",
    "sg:province":"Baden-W\u00fcrttemberg",
    "wof:name":"Pizzeria In Der Music Hall",
    "wof:placetype":"venue"
},
  "geometry": {"coordinates":[9.3239889145,49.514503479],"type":"Point"}
}