{
  "type": "Feature",
  "properties": {
    "iso:country":"DE",
    "sg:address":"Gartenstr.",
    "sg:city":"Schl\u00fcchtern",
    "sg:phone":"+49 6661/6492",
    "sg:postcode":"36381",
    "sg:province":"Hessen",
    "wof:name":"Schnell-imbiss",
    "wof:placetype":"venue"
},
  "geometry": {"coordinates":[9.5283470154,50.350402832],"type":"Point"}
}