{
  "type": "Feature",
  "properties": {
    "iso:country":"DE",
    "sg:address":"Barthelstr. 93",
    "sg:city":"K\u00f6ln",
    "sg:phone":"+49 221/517057",
    "sg:postcode":"50823",
    "sg:province":"Nordrhein-Westfalen",
    "wof:name":"Hotel Imperial Gmbh",
    "wof:placetype":"venue"
},
  "geometry": {"coordinates":[6.9224200249,50.9429931641],"type":"Point"}
}