{
  "type": "Feature",
  "properties": {
    "iso:country":"DE",
    "sg:address":"Sch\u00f6ne Aussicht 4",
    "sg:city":"Sch\u00f6neck",
    "sg:phone":"+49 6187/5360",
    "sg:postcode":"61137",
    "sg:province":"Hessen",
    "wof:name":"Albert Blume",
    "wof:placetype":"venue"
},
  "geometry": {"coordinates":[8.83084,50.212971],"type":"Point"}
}