{
  "type": "Feature",
  "properties": {
    "iso:country":"DE",
    "sg:address":"Dradenaustr. 33",
    "sg:city":"Hamburg",
    "sg:phone":"+49 40/74080",
    "sg:postcode":"21129",
    "sg:province":"Hamburg",
    "wof:name":"Ispat Hamburger Stahlwerke Consulting Gmbh",
    "wof:placetype":"venue"
},
  "geometry": {"coordinates":[9.9011421204,53.5247535706],"type":"Point"}
}