{
  "type": "Feature",
  "properties": {
    "iso:country":"DE",
    "sg:address":"Residenzstr. 109",
    "sg:city":"Berlin",
    "sg:phone":"+49 30/4916761",
    "sg:postcode":"13409",
    "sg:province":"Berlin",
    "wof:name":"Kastanienw\u00e4ldchen",
    "wof:placetype":"venue"
},
  "geometry": {"coordinates":[13.3643722534,52.5642623901],"type":"Point"}
}