{
  "type": "Feature",
  "properties": {
    "iso:country":"DE",
    "sg:address":"An der Wachsfabrik 17",
    "sg:city":"K\u00f6ln",
    "sg:phone":"+49 2236/962220",
    "sg:postcode":"50996",
    "sg:province":"Nordrhein-Westfalen",
    "wof:name":"Beton Union K\u00f6ln-bonn Gmbh & Co Kg",
    "wof:placetype":"venue"
},
  "geometry": {"coordinates":[6.9976210594,50.8699989319],"type":"Point"}
}