{
  "type": "Feature",
  "properties": {
    "iso:country":"DE",
    "sg:address":"Marktstr. 9",
    "sg:city":"G\u00f6ppingen",
    "sg:phone":"+49 7161/73911",
    "sg:postcode":"73033",
    "sg:province":"Baden-W\u00fcrttemberg",
    "wof:name":"Hermann & Kuhn Gmbh",
    "wof:placetype":"venue"
},
  "geometry": {"coordinates":[9.653694,48.702152],"type":"Point"}
}