{
  "type": "Feature",
  "properties": {
    "iso:country":"DE",
    "sg:address":"Mittelstr. 64",
    "sg:city":"Elsdorf",
    "sg:phone":"+49 2274/2263",
    "sg:postcode":"50189",
    "sg:province":"Nordrhein-Westfalen",
    "wof:name":"B\u00e4ckerei Immerath Gmbh",
    "wof:placetype":"venue"
},
  "geometry": {"coordinates":[6.570548,50.938091],"type":"Point"}
}