{
  "type": "Feature",
  "properties": {
    "iso:country":"DE",
    "sg:address":"Rekumer Str. 168a",
    "sg:city":"Bremen",
    "sg:phone":"+49 421/683307",
    "sg:postcode":"28777",
    "sg:province":"Bremen",
    "wof:name":"Georg W. Schnug",
    "wof:placetype":"venue"
},
  "geometry": {"coordinates":[8.509535,53.224808],"type":"Point"}
}