{
  "type": "Feature",
  "properties": {
    "iso:country":"DE",
    "sg:address":"Bahnhofstr. 82",
    "sg:city":"Saarbr\u00fccken",
    "sg:phone":"+49 681/33939",
    "sg:postcode":"66111",
    "sg:province":"Saarland",
    "wof:name":"Passage-kino",
    "wof:placetype":"venue"
},
  "geometry": {"coordinates":[6.9921178818,49.2374076843],"type":"Point"}
}