{
  "type": "Feature",
  "properties": {
    "iso:country":"DE",
    "sg:address":"Schulstr. 19 - 20",
    "sg:city":"Ahaus",
    "sg:phone":"+49 2561/3693",
    "sg:postcode":"48683",
    "sg:province":"Nordrhein-Westfalen",
    "wof:name":"Klumpen",
    "wof:placetype":"venue"
},
  "geometry": {"coordinates":[6.9695248604,52.0906181335],"type":"Point"}
}