{
  "type": "Feature",
  "properties": {
    "iso:country":"DE",
    "sg:address":"Nordstr. 13",
    "sg:city":"Everswinkel",
    "sg:phone":"+49 2582/8255",
    "sg:postcode":"48351",
    "sg:province":"Nordrhein-Westfalen",
    "wof:name":"Drees Schuhe Sport E. K.",
    "wof:placetype":"venue"
},
  "geometry": {"coordinates":[7.8442769051,51.9255371094],"type":"Point"}
}