{
  "type": "Feature",
  "properties": {
    "iso:country":"DE",
    "sg:address":"Biegstr. 55 A",
    "sg:city":"Kevelaer",
    "sg:phone":"+49 2832/92480",
    "sg:postcode":"47623",
    "sg:province":"Nordrhein-Westfalen",
    "wof:name":"Projektpartner Wohnbau Gmbh",
    "wof:placetype":"venue"
},
  "geometry": {"coordinates":[6.244592,51.577709],"type":"Point"}
}