{
  "type": "Feature",
  "properties": {
    "iso:country":"DE",
    "sg:address":"Schulstr. 13",
    "sg:city":"Recklinghausen",
    "sg:phone":"+49 2361/81378",
    "sg:postcode":"45665",
    "sg:province":"Nordrhein-Westfalen",
    "wof:name":"Hans Kommer",
    "wof:placetype":"venue"
},
  "geometry": {"coordinates":[7.2606787682,51.6106643677],"type":"Point"}
}