{
  "type": "Feature",
  "properties": {
    "iso:country":"DE",
    "sg:address":"Rolandstr. 72",
    "sg:city":"K\u00f6ln",
    "sg:phone":"+49 221/323459",
    "sg:postcode":"50677",
    "sg:province":"Nordrhein-Westfalen",
    "wof:name":"Soho",
    "wof:placetype":"venue"
},
  "geometry": {"coordinates":[6.956679,50.919201],"type":"Point"}
}