{
  "type": "Feature",
  "properties": {
    "iso:country":"DE",
    "sg:address":"Goebenstr. 1-5",
    "sg:city":"Herford",
    "sg:phone":"+49 5221/52258",
    "sg:postcode":"32052",
    "sg:province":"Nordrhein-Westfalen",
    "wof:name":"Deutsche Post Ag",
    "wof:placetype":"venue"
},
  "geometry": {"coordinates":[8.6671209335,52.1205444336],"type":"Point"}
}