{
  "type": "Feature",
  "properties": {
    "iso:country":"DE",
    "sg:address":"Schulterblatt 85",
    "sg:city":"Hamburg",
    "sg:phone":"+49 40/433340",
    "sg:postcode":"20357",
    "sg:province":"Hamburg",
    "wof:name":"Herbert Franke",
    "wof:placetype":"venue"
},
  "geometry": {"coordinates":[9.960734,53.56295],"type":"Point"}
}