{
  "type": "Feature",
  "properties": {
    "iso:country":"DE",
    "sg:address":"Heppenheimer Str. 30",
    "sg:city":"F\u00fcrth",
    "sg:phone":"+49 6253/5753",
    "sg:postcode":"64658",
    "sg:province":"Hessen",
    "wof:name":"Gerhard Ansorge",
    "wof:placetype":"venue"
},
  "geometry": {"coordinates":[8.7781953812,49.6488380432],"type":"Point"}
}