{
  "type": "Feature",
  "properties": {
    "iso:country":"DE",
    "sg:address":"Rosental 13",
    "sg:city":"Ellingen",
    "sg:phone":"+49 9141/2141",
    "sg:postcode":"91792",
    "sg:province":"Bayern",
    "wof:name":"G\u00fcnter Killermann",
    "wof:placetype":"venue"
},
  "geometry": {"coordinates":[10.967072,49.063663],"type":"Point"}
}