{
  "type": "Feature",
  "properties": {
    "iso:country":"DE",
    "sg:address":"Wallstr. 8",
    "sg:city":"Frankfurt",
    "sg:phone":"+49 69/610366",
    "sg:postcode":"60594",
    "sg:province":"Hessen",
    "wof:name":"Anton Hartmann Sohn Verwaltungs Gmbh",
    "wof:placetype":"venue"
},
  "geometry": {"coordinates":[8.6889677048,50.1049957275],"type":"Point"}
}