{
  "type": "Feature",
  "properties": {
    "iso:country":"DE",
    "sg:address":"Ansbacher Str. 7",
    "sg:city":"Uffenheim",
    "sg:phone":"+49 9842/1478",
    "sg:postcode":"97215",
    "sg:province":"Bayern",
    "wof:name":"Restaurant Delphi",
    "wof:placetype":"venue"
},
  "geometry": {"coordinates":[10.2316932678,49.5436782837],"type":"Point"}
}