{
  "type": "Feature",
  "properties": {
    "iso:country":"DE",
    "sg:address":"Nordstr. 31",
    "sg:city":"M\u00f6nchengladbach",
    "sg:phone":"+49 2166/249782",
    "sg:postcode":"41236",
    "sg:province":"Nordrhein-Westfalen",
    "wof:name":"G. Dimitriadou",
    "wof:placetype":"venue"
},
  "geometry": {"coordinates":[6.4415740967,51.1726303101],"type":"Point"}
}