{
  "type": "Feature",
  "properties": {
    "iso:country":"DE",
    "sg:address":"Guntramstr. 29",
    "sg:city":"Freiburg",
    "sg:phone":"+49 761/273683",
    "sg:postcode":"79106",
    "sg:province":"Baden-W\u00fcrttemberg",
    "wof:name":"Metzgerei Bernd H\u00fcgle E. K.",
    "wof:placetype":"venue"
},
  "geometry": {"coordinates":[7.8384671211,47.9989204407],"type":"Point"}
}