{
  "type": "Feature",
  "properties": {
    "iso:country":"DE",
    "sg:address":"G\u00f6ckelhof 6",
    "sg:city":"Murrhardt",
    "sg:postcode":"71540",
    "sg:province":"Baden-W\u00fcrttemberg",
    "wof:name":"Wiesner & Hanzel Gmbh",
    "wof:placetype":"venue"
},
  "geometry": {"coordinates":[9.642999649,48.9631996155],"type":"Point"}
}