{
  "type": "Feature",
  "properties": {
    "iso:country":"DE",
    "sg:address":"Hermannstr. 6",
    "sg:city":"Hannover",
    "sg:phone":"+49 511/461462",
    "sg:postcode":"30457",
    "sg:province":"Niedersachsen",
    "wof:name":"Dr. E. Von Schroeter Rechtsanwalt",
    "wof:placetype":"venue"
},
  "geometry": {"coordinates":[9.6993646622,52.3306045532],"type":"Point"}
}