{
  "type": "Feature",
  "properties": {
    "iso:country":"DE",
    "sg:address":"An der Heide 1",
    "sg:city":"Oranienburg",
    "sg:postcode":"16515",
    "sg:province":"Brandenburg",
    "wof:name":"Krawa Abwassersysteme Und Bauprojekt Gmbh",
    "wof:placetype":"venue"
},
  "geometry": {"coordinates":[13.2409801483,52.7707672119],"type":"Point"}
}