{
  "type": "Feature",
  "properties": {
    "iso:country":"DE",
    "sg:address":"Nu\u00dflocher Str. 9",
    "sg:city":"Walldorf",
    "sg:phone":"+49 6227/9689",
    "sg:postcode":"69190",
    "sg:province":"Baden-W\u00fcrttemberg",
    "wof:name":"Horst Moder",
    "wof:placetype":"venue"
},
  "geometry": {"coordinates":[8.643861,49.303501],"type":"Point"}
}