{
  "type": "Feature",
  "properties": {
    "iso:country":"DE",
    "sg:address":"Friedrichstr. 48",
    "sg:city":"Offenburg",
    "sg:phone":"+49 781/37763",
    "sg:postcode":"77654",
    "sg:province":"Baden-W\u00fcrttemberg",
    "wof:name":"L. Scheiding",
    "wof:placetype":"venue"
},
  "geometry": {"coordinates":[7.9503359795,48.4688720703],"type":"Point"}
}