{
  "type": "Feature",
  "properties": {
    "iso:country":"DE",
    "sg:address":"Lierestr. 55",
    "sg:city":"Vienenburg",
    "sg:phone":"+49 5324/2757",
    "sg:postcode":"38690",
    "sg:province":"Niedersachsen",
    "wof:name":"Karl-august Walte",
    "wof:placetype":"venue"
},
  "geometry": {"coordinates":[10.5584011078,51.9469833374],"type":"Point"}
}