{
  "type": "Feature",
  "properties": {
    "iso:country":"DE",
    "sg:address":"Friedhofsweg 5 b",
    "sg:city":"Ahorn",
    "sg:postcode":"96482",
    "sg:province":"Bayern",
    "wof:name":"Richter & Partner Verwaltungs- Und Beteiligungsges. Mbh",
    "wof:placetype":"venue"
},
  "geometry": {"coordinates":[10.946113,50.237297],"type":"Point"}
}