{
  "type": "Feature",
  "properties": {
    "iso:country":"DE",
    "sg:address":"Gro\u00dfe Pfahlstr. 21",
    "sg:city":"Hannover",
    "sg:phone":"+49 511/343966",
    "sg:postcode":"30161",
    "sg:province":"Niedersachsen",
    "wof:name":"City Car Taxenunternehmen Gmbh",
    "wof:placetype":"venue"
},
  "geometry": {"coordinates":[9.7470560074,52.3827857971],"type":"Point"}
}