{
  "type": "Feature",
  "properties": {
    "iso:country":"DE",
    "sg:address":"Rummeltshausen 15",
    "sg:city":"Westerheim",
    "sg:phone":"+49 8393/1015",
    "sg:postcode":"87784",
    "sg:province":"Bayern",
    "wof:name":"Spewo-bau Gmbh",
    "wof:placetype":"venue"
},
  "geometry": {"coordinates":[10.287898,48.041878],"type":"Point"}
}