{
  "type": "Feature",
  "properties": {
    "iso:country":"DE",
    "sg:address":"Ernst-Ruhstrat-Str 8",
    "sg:city":"G\u00f6ttingen",
    "sg:phone":"+49 551/62001",
    "sg:postcode":"37079",
    "sg:province":"Niedersachsen",
    "wof:name":"Mayer Feintechnik Klaus Mayer",
    "wof:placetype":"venue"
},
  "geometry": {"coordinates":[9.9012546539,51.5459594727],"type":"Point"}
}