{
  "type": "Feature",
  "properties": {
    "iso:country":"DE",
    "sg:address":"Stenzelbergstr. 13",
    "sg:city":"K\u00f6nigswinter",
    "sg:phone":"+49 2244/871445",
    "sg:postcode":"53639",
    "sg:province":"Nordrhein-Westfalen",
    "wof:name":"Rudolf Klein Steuerberater",
    "wof:placetype":"venue"
},
  "geometry": {"coordinates":[7.2324261665,50.6944618225],"type":"Point"}
}