{
  "type": "Feature",
  "properties": {
    "iso:country":"DE",
    "sg:address":"Hauptstr. 11",
    "sg:city":"B\u00fchlertann",
    "sg:phone":"+49 4979/73292",
    "sg:postcode":"74424",
    "sg:province":"Baden-W\u00fcrttemberg",
    "wof:name":"Kreissparkasse Schw\u00e4bisch Hall",
    "wof:placetype":"venue"
},
  "geometry": {"coordinates":[9.908435,49.040939],"type":"Point"}
}