{
  "type": "Feature",
  "properties": {
    "iso:country":"DE",
    "sg:address":"Feldstr. 1",
    "sg:city":"Nidda",
    "sg:phone":"+49 6043/4627",
    "sg:postcode":"63667",
    "sg:province":"Hessen",
    "wof:name":"Heinrich F. Ussner S\u00e4gewerk-holzbau",
    "wof:placetype":"venue"
},
  "geometry": {"coordinates":[9.0186872482,50.4402275085],"type":"Point"}
}