{
  "type": "Feature",
  "properties": {
    "iso:country":"DE",
    "sg:address":"Dieselstr 10",
    "sg:city":"Gro\u00dfmehring",
    "sg:phone":"+49 8456/96770",
    "sg:postcode":"85098",
    "sg:province":"Bayern",
    "wof:name":"Schabm\u00fcller Automobiltechnik Gmbh",
    "wof:placetype":"venue"
},
  "geometry": {"coordinates":[11.501974,48.788715],"type":"Point"}
}