{
  "type": "Feature",
  "properties": {
    "iso:country":"DE",
    "sg:address":"Am Osdorfer Born 110",
    "sg:city":"Hamburg",
    "sg:phone":"+49 40/803226",
    "sg:postcode":"22549",
    "sg:province":"Hamburg",
    "wof:name":"Claus-hinrich Groth",
    "wof:placetype":"venue"
},
  "geometry": {"coordinates":[9.839901,53.582569],"type":"Point"}
}