{
  "type": "Feature",
  "properties": {
    "iso:country":"DE",
    "sg:address":"An der H\u00fctung 39",
    "sg:city":"Essen",
    "sg:phone":"+49 201/322202",
    "sg:postcode":"45327",
    "sg:province":"Nordrhein-Westfalen",
    "wof:name":"Bedachungstechnik Hovestadt Gmbh",
    "wof:placetype":"venue"
},
  "geometry": {"coordinates":[7.0251111984,51.4938659668],"type":"Point"}
}