{
  "type": "Feature",
  "properties": {
    "iso:country":"DE",
    "sg:address":"Hauptstr. 7",
    "sg:city":"Heigenbr\u00fccken",
    "sg:phone":"+49 6020/970923",
    "sg:postcode":"63869",
    "sg:province":"Bayern",
    "wof:name":"Medical Triathion Association E. V. Hanau",
    "wof:placetype":"venue"
},
  "geometry": {"coordinates":[9.37495327,50.0275917053],"type":"Point"}
}