{
  "type": "Feature",
  "properties": {
    "iso:country":"DE",
    "sg:address":"Kasinostr. 21",
    "sg:city":"Solingen",
    "sg:phone":"+49 212/201610",
    "sg:postcode":"42651",
    "sg:province":"Nordrhein-Westfalen",
    "wof:name":"Franz Und Ellen Urban Gmbh",
    "wof:placetype":"venue"
},
  "geometry": {"coordinates":[7.0865550041,51.1735954285],"type":"Point"}
}