{
  "type": "Feature",
  "properties": {
    "iso:country":"DE",
    "sg:address":"Berkenbr\u00fccker Chaussee",
    "sg:city":"F\u00fcrstenwalde",
    "sg:postcode":"15517",
    "sg:province":"Brandenburg",
    "wof:name":"Wasserversorgung Und Abwasser- Behandlung Frankfurt Oder",
    "wof:placetype":"venue"
},
  "geometry": {"coordinates":[14.1223335266,52.3501243591],"type":"Point"}
}