{
  "type": "Feature",
  "properties": {
    "iso:country":"DE",
    "sg:address":"Blissestr. 5",
    "sg:city":"Berlin",
    "sg:postcode":"10713",
    "sg:province":"Berlin",
    "wof:name":"Eventus 2000 Gmbh",
    "wof:placetype":"venue"
},
  "geometry": {"coordinates":[13.3207359314,52.4859085083],"type":"Point"}
}