{
  "type": "Feature",
  "properties": {
    "iso:country":"DE",
    "sg:address":"Koblenzer Str. 55",
    "sg:city":"Fluterschen",
    "sg:postcode":"57614",
    "sg:province":"Rheinland-Pfalz",
    "wof:name":"Honeymoon Highlights Hochzeitsreisen Und",
    "wof:placetype":"venue"
},
  "geometry": {"coordinates":[7.6265487671,50.6640701294],"type":"Point"}
}