{
  "type": "Feature",
  "properties": {
    "iso:country":"DE",
    "sg:address":"Karl-Schr\u00f6der-Str. 15",
    "sg:city":"Pullach",
    "sg:phone":"+49 89/7933458",
    "sg:postcode":"82049",
    "sg:province":"Bayern",
    "wof:name":"Eberhard Sanau Ingenieur",
    "wof:placetype":"venue"
},
  "geometry": {"coordinates":[11.5250148773,48.0580673218],"type":"Point"}
}