{
  "type": "Feature",
  "properties": {
    "iso:country":"DE",
    "sg:address":"Holbeinstr. 6",
    "sg:city":"Solingen",
    "sg:phone":"+49 212/312171",
    "sg:postcode":"42719",
    "sg:province":"Nordrhein-Westfalen",
    "wof:name":"Musikalischer Bahnhof",
    "wof:placetype":"venue"
},
  "geometry": {"coordinates":[7.0532040596,51.1871566772],"type":"Point"}
}