{
  "type": "Feature",
  "properties": {
    "iso:country":"DE",
    "sg:address":"Alter Markt 1",
    "sg:city":"Neukloster",
    "sg:phone":"+49 38422/20274",
    "sg:postcode":"23992",
    "sg:province":"Mecklenburg-Vorpommern",
    "wof:name":"Lothar Weiss",
    "wof:placetype":"venue"
},
  "geometry": {"coordinates":[11.68677,53.86454],"type":"Point"}
}