{
  "type": "Feature",
  "properties": {
    "iso:country":"DE",
    "sg:address":"Kirchplatz 1",
    "sg:city":"Wilsdruff",
    "sg:postcode":"01723",
    "sg:province":"Sachsen",
    "wof:name":"Katholisches Pfarramt Wilsdruff",
    "wof:placetype":"venue"
},
  "geometry": {"coordinates":[13.5372896194,51.0527267456],"type":"Point"}
}