{
  "type": "Feature",
  "properties": {
    "iso:country":"DE",
    "sg:address":"Ortsstr. 46",
    "sg:city":"Oberstenfeld",
    "sg:phone":"+49 7194/8445",
    "sg:postcode":"71720",
    "sg:province":"Baden-W\u00fcrttemberg",
    "wof:name":"Gasthof Ochsen",
    "wof:placetype":"venue"
},
  "geometry": {"coordinates":[9.3975200653,49.0504570007],"type":"Point"}
}