{
  "type": "Feature",
  "properties": {
    "iso:country":"DE",
    "sg:address":"St. Ulrich 41 B",
    "sg:city":"Bollschweil",
    "sg:phone":"+49 7602/380",
    "sg:postcode":"79283",
    "sg:province":"Baden-W\u00fcrttemberg",
    "wof:name":"Bmb Baumaschinen Beyer Gmbh",
    "wof:placetype":"venue"
},
  "geometry": {"coordinates":[7.840867,47.917427],"type":"Point"}
}