{
  "type": "Feature",
  "properties": {
    "iso:country":"DE",
    "sg:address":"Br\u00fccker Landstr. 22",
    "sg:city":"Belzig",
    "sg:phone":"+49 33841/99101",
    "sg:postcode":"14806",
    "sg:province":"Brandenburg",
    "wof:name":"Verkehrsgesellschaft Belzig Mbh",
    "wof:placetype":"venue"
},
  "geometry": {"coordinates":[12.6149578094,52.1453742981],"type":"Point"}
}