{
  "type": "Feature",
  "properties": {
    "iso:country":"DE",
    "sg:address":"Lutterplatz 5",
    "sg:city":"Bramsche",
    "sg:phone":"+49 5461/72020",
    "sg:postcode":"49565",
    "sg:province":"Niedersachsen",
    "wof:name":"Gastst\u00e4tte T\u00f6ffte",
    "wof:placetype":"venue"
},
  "geometry": {"coordinates":[7.9962501526,52.406829834],"type":"Point"}
}