{
  "type": "Feature",
  "properties": {
    "iso:country":"DE",
    "sg:address":"Burgstr. 40",
    "sg:city":"Beverungen",
    "sg:phone":"+49 5273/6824",
    "sg:postcode":"37688",
    "sg:province":"Nordrhein-Westfalen",
    "wof:name":"Drefahl Proyecta Bauplanungsatelier",
    "wof:placetype":"venue"
},
  "geometry": {"coordinates":[9.375053,51.663651],"type":"Point"}
}