{
  "type": "Feature",
  "properties": {
    "iso:country":"DE",
    "sg:address":"Raiffeisenstr. 35",
    "sg:city":"Wiesbaden",
    "sg:phone":"+49 611/508361",
    "sg:postcode":"65191",
    "sg:province":"Hessen",
    "wof:name":"Karl Ludwig Hoffmann Kg",
    "wof:placetype":"venue"
},
  "geometry": {"coordinates":[8.2826623917,50.0847549438],"type":"Point"}
}