{
  "type": "Feature",
  "properties": {
    "iso:country":"DE",
    "sg:address":"Pirmasenser Str. 20 a",
    "sg:city":"Kaiserslautern",
    "sg:phone":"+49 631/92536",
    "sg:postcode":"67655",
    "sg:province":"Rheinland-Pfalz",
    "wof:name":"Der Wein Bauer E. K.",
    "wof:placetype":"venue"
},
  "geometry": {"coordinates":[7.766723156,49.441368103],"type":"Point"}
}