{
  "type": "Feature",
  "properties": {
    "iso:country":"DE",
    "sg:address":"Kornhalde 7",
    "sg:city":"Esslingen",
    "sg:phone":"+49 711/376349",
    "sg:postcode":"73733",
    "sg:province":"Baden-W\u00fcrttemberg",
    "wof:name":"Rolf Sch\u00e4ffer",
    "wof:placetype":"venue"
},
  "geometry": {"coordinates":[9.2928714752,48.7582092285],"type":"Point"}
}