{
  "type": "Feature",
  "properties": {
    "iso:country":"DE",
    "sg:address":"Markt 9 -10",
    "sg:city":"Stendal",
    "sg:phone":"+49 3931/715956",
    "sg:postcode":"39576",
    "sg:province":"Sachsen-Anhalt",
    "wof:name":"Dr. Doms Und Dr. Siebert Rechtsanw\u00e4lte",
    "wof:placetype":"venue"
},
  "geometry": {"coordinates":[11.8594083786,52.6047782898],"type":"Point"}
}