{
  "type": "Feature",
  "properties": {
    "iso:country":"DE",
    "sg:address":"Obergasse 9a",
    "sg:city":"Esselborn",
    "sg:phone":"+49 6731/55134",
    "sg:postcode":"55234",
    "sg:province":"Rheinland-Pfalz",
    "wof:name":"Ernst Klingenschmitt",
    "wof:placetype":"venue"
},
  "geometry": {"coordinates":[8.118752,49.714596],"type":"Point"}
}