{
  "type": "Feature",
  "properties": {
    "iso:country":"DE",
    "sg:address":"Liebersberger Str. 19",
    "sg:city":"Grafenau",
    "sg:phone":"+49 8552/1718",
    "sg:postcode":"94481",
    "sg:province":"Bayern",
    "wof:name":"Josef Und Maria Tauscher",
    "wof:placetype":"venue"
},
  "geometry": {"coordinates":[13.4115371704,48.841293335],"type":"Point"}
}