{
  "type": "Feature",
  "properties": {
    "iso:country":"DE",
    "sg:address":"Philipp-Melanchthon-Str. 14",
    "sg:city":"Amberg",
    "sg:phone":"+49 9621/73282",
    "sg:postcode":"92224",
    "sg:province":"Bayern",
    "wof:name":"Comet",
    "wof:placetype":"venue"
},
  "geometry": {"coordinates":[11.8819007874,49.4377288818],"type":"Point"}
}