{
  "type": "Feature",
  "properties": {
    "iso:country":"DE",
    "sg:address":"Friedrichsthaler Str. 4",
    "sg:city":"Lauchhammer",
    "sg:phone":"+49 3574/123128",
    "sg:postcode":"01979",
    "sg:province":"Brandenburg",
    "wof:name":"Monis Mode F\u00fcr Mollige",
    "wof:placetype":"venue"
},
  "geometry": {"coordinates":[13.72762,51.482979],"type":"Point"}
}