{
  "type": "Feature",
  "properties": {
    "iso:country":"DE",
    "sg:address":"Keniastr. 20",
    "sg:city":"Duisburg",
    "sg:phone":"+49 4920/397570",
    "sg:postcode":"47269",
    "sg:province":"Nordrhein-Westfalen",
    "wof:name":"Makita Werkzeug Gmbh",
    "wof:placetype":"venue"
},
  "geometry": {"coordinates":[6.772275,51.372799],"type":"Point"}
}