{
  "type": "Feature",
  "properties": {
    "iso:country":"DE",
    "sg:address":"Auf dem Kellenstroth 9",
    "sg:city":"Wagenfeld",
    "sg:phone":"+49 5444/837",
    "sg:postcode":"49419",
    "sg:province":"Niedersachsen",
    "wof:name":"Karl Bening",
    "wof:placetype":"venue"
},
  "geometry": {"coordinates":[8.569904,52.567993],"type":"Point"}
}