{
  "type": "Feature",
  "properties": {
    "iso:country":"DE",
    "sg:address":"Alter Rottweg 10",
    "sg:city":"Reilingen",
    "sg:phone":"+49 6205/923040",
    "sg:postcode":"68799",
    "sg:province":"Baden-W\u00fcrttemberg",
    "wof:name":"H & B - Holz Gmbh",
    "wof:placetype":"venue"
},
  "geometry": {"coordinates":[8.556854,49.299965],"type":"Point"}
}