{
  "type": "Feature",
  "properties": {
    "iso:country":"DE",
    "sg:address":"Kleinhelfendorf",
    "sg:city":"Aying",
    "sg:phone":"+49 8095/2222",
    "sg:postcode":"85653",
    "sg:province":"Bayern",
    "wof:name":"Josef Huber Ingenieur",
    "wof:placetype":"venue"
},
  "geometry": {"coordinates":[11.8092432022,47.9418563843],"type":"Point"}
}