{
  "type": "Feature",
  "properties": {
    "iso:country":"DE",
    "sg:address":"Wipperf\u00fcrther Str. 364",
    "sg:city":"K\u00fcrten",
    "sg:phone":"+49 2268/92930",
    "sg:postcode":"51515",
    "sg:province":"Nordrhein-Westfalen",
    "wof:name":"K\u00fcrtener Reisedienst Gmbh",
    "wof:placetype":"venue"
},
  "geometry": {"coordinates":[7.2657489777,51.0520591736],"type":"Point"}
}