{
  "type": "Feature",
  "properties": {
    "iso:country":"DE",
    "sg:address":"Hasenfelder Str.",
    "sg:city":"Arensdorf",
    "sg:postcode":"15518",
    "sg:province":"Brandenburg",
    "wof:name":"Dr. Helga Rother",
    "wof:placetype":"venue"
},
  "geometry": {"coordinates":[14.2421197891,52.4274368286],"type":"Point"}
}