{
  "type": "Feature",
  "properties": {
    "iso:country":"DE",
    "sg:address":"Helenenstr. 26",
    "sg:city":"Leipzig",
    "sg:phone":"+49 4934/1336140",
    "sg:postcode":"04279",
    "sg:province":"Sachsen",
    "wof:name":"Samson Ag",
    "wof:placetype":"venue"
},
  "geometry": {"coordinates":[12.38946,51.28767],"type":"Point"}
}