{
  "type": "Feature",
  "properties": {
    "iso:country":"DE",
    "sg:address":"Ringstr. 4",
    "sg:city":"Weltersburg",
    "sg:phone":"+49 6435/2269",
    "sg:postcode":"56459",
    "sg:province":"Rheinland-Pfalz",
    "wof:name":"Sch\u00f6nauer Gmbh",
    "wof:placetype":"venue"
},
  "geometry": {"coordinates":[7.9588398933,50.5226593018],"type":"Point"}
}