{
  "type": "Feature",
  "properties": {
    "iso:country":"DE",
    "sg:address":"Hedwigstr. 4",
    "sg:city":"M\u00fcnchen",
    "sg:phone":"+49 89/184210",
    "sg:postcode":"80636",
    "sg:province":"Bayern",
    "wof:name":"Gert H. Wohlfarth Rechtsanwalt",
    "wof:placetype":"venue"
},
  "geometry": {"coordinates":[11.5398044586,48.1517829895],"type":"Point"}
}