{
  "type": "Feature",
  "properties": {
    "iso:country":"DE",
    "sg:address":"Im Moore 25",
    "sg:city":"Hannover",
    "sg:postcode":"30167",
    "sg:province":"Niedersachsen",
    "wof:name":"Verein F\u00fcr Internationale Verst\u00e4ndigung Und Zusammen-",
    "wof:placetype":"venue"
},
  "geometry": {"coordinates":[9.7205352783,52.3845863342],"type":"Point"}
}