{
  "type": "Feature",
  "properties": {
    "iso:country":"DE",
    "sg:address":"Valckenbergstr. 35",
    "sg:city":"Worms",
    "sg:phone":"+49 6241/82248",
    "sg:postcode":"67547",
    "sg:province":"Rheinland-Pfalz",
    "wof:name":"Alexander Kraft",
    "wof:placetype":"venue"
},
  "geometry": {"coordinates":[8.3590259552,49.627494812],"type":"Point"}
}