{
  "type": "Feature",
  "properties": {
    "iso:country":"DE",
    "sg:address":"Hauptstr. 5",
    "sg:city":"Ventschow",
    "sg:phone":"+49 38484/66852",
    "sg:postcode":"19417",
    "sg:province":"Mecklenburg-Vorpommern",
    "wof:name":"Fahrzeug Service Delzeit Gmbh",
    "wof:placetype":"venue"
},
  "geometry": {"coordinates":[11.5806570053,53.7886734009],"type":"Point"}
}