{
  "type": "Feature",
  "properties": {
    "iso:country":"DE",
    "sg:address":"Fischmarkt 1",
    "sg:city":"Offenburg",
    "sg:phone":"+49 781/23269",
    "sg:postcode":"77652",
    "sg:province":"Baden-W\u00fcrttemberg",
    "wof:name":"Die Brille",
    "wof:placetype":"venue"
},
  "geometry": {"coordinates":[7.9431757927,48.4696350098],"type":"Point"}
}