{
  "type": "Feature",
  "properties": {
    "iso:country":"DE",
    "sg:address":"Hauptstr. 2",
    "sg:city":"Herrmannsacker",
    "sg:phone":"+49 3631/897223",
    "sg:postcode":"99762",
    "sg:province":"Th\u00fcringen",
    "wof:name":"Ronald Weifenbach",
    "wof:placetype":"venue"
},
  "geometry": {"coordinates":[10.8763427734,51.5452537537],"type":"Point"}
}