{
  "type": "Feature",
  "properties": {
    "iso:country":"DE",
    "sg:address":"Am Hohen Turm 1",
    "sg:city":"Harsum",
    "sg:phone":"+49 5127/4396",
    "sg:postcode":"31177",
    "sg:province":"Niedersachsen",
    "wof:name":"Gastst\u00e4tte J. Willke",
    "wof:placetype":"venue"
},
  "geometry": {"coordinates":[10.0104961395,52.2063751221],"type":"Point"}
}