{
  "type": "Feature",
  "properties": {
    "iso:country":"DE",
    "sg:address":"Siedlungsstr. 8",
    "sg:city":"K\u00fcstrin-Kietz",
    "sg:phone":"+49 33479/241",
    "sg:postcode":"15328",
    "sg:province":"Brandenburg",
    "wof:name":"Mathias Wurl",
    "wof:placetype":"venue"
},
  "geometry": {"coordinates":[14.594076,52.562881],"type":"Point"}
}