{
  "type": "Feature",
  "properties": {
    "iso:country":"DE",
    "sg:address":"Zum Sportplatz 3",
    "sg:city":"H\u00f6chst",
    "sg:phone":"+49 6163/3383",
    "sg:postcode":"64739",
    "sg:province":"Hessen",
    "wof:name":"Rainer Weber",
    "wof:placetype":"venue"
},
  "geometry": {"coordinates":[8.9386615753,49.7784004211],"type":"Point"}
}