{
  "type": "Feature",
  "properties": {
    "iso:country":"DE",
    "sg:address":"Firkenweg 1",
    "sg:city":"Unterf\u00f6hring",
    "sg:postcode":"85774",
    "sg:province":"Bayern",
    "wof:name":"Modern Living Gesellschaft F\u00fcr Kundenorientiertes Bauen Mbh",
    "wof:placetype":"venue"
},
  "geometry": {"coordinates":[11.643214,48.189522],"type":"Point"}
}