{
  "type": "Feature",
  "properties": {
    "iso:country":"DE",
    "sg:address":"Am R\u00f6ttchen 72",
    "sg:city":"D\u00fcsseldorf",
    "sg:phone":"+49 211",
    "sg:postcode":"40468",
    "sg:province":"Nordrhein-Westfalen",
    "wof:name":"1a-assekuranz",
    "wof:placetype":"venue"
},
  "geometry": {"coordinates":[6.7860980034,51.2700691223],"type":"Point"}
}