{
  "type": "Feature",
  "properties": {
    "iso:country":"DE",
    "sg:address":"Spielbergstr. 14/A",
    "sg:city":"B\u00f6blingen",
    "sg:phone":"+49 7031/273701",
    "sg:postcode":"71032",
    "sg:province":"Baden-W\u00fcrttemberg",
    "wof:name":"Ricarda Sch\u00e4fer",
    "wof:placetype":"venue"
},
  "geometry": {"coordinates":[9.016663,48.681931],"type":"Point"}
}