{
  "type": "Feature",
  "properties": {
    "iso:country":"DE",
    "sg:address":"Krefelder Str. 684",
    "sg:city":"M\u00f6nchengladbach",
    "sg:phone":"+49 2161/659880",
    "sg:postcode":"41066",
    "sg:province":"Nordrhein-Westfalen",
    "wof:name":"Pro Computer & Industrial Case Gmbh",
    "wof:placetype":"venue"
},
  "geometry": {"coordinates":[6.4843850136,51.2252006531],"type":"Point"}
}