{
  "type": "Feature",
  "properties": {
    "iso:country":"DE",
    "sg:address":"Frankfurter Str. 84::",
    "sg:city":"Siegburg",
    "sg:phone":"+49 4922/411080",
    "sg:postcode":"53721",
    "sg:province":"Nordrhein-Westfalen",
    "wof:name":"Verband Der Angestellten- Krankenkassen E.v.",
    "wof:placetype":"venue"
},
  "geometry": {"coordinates":[7.214611,50.789604],"type":"Point"}
}