{
  "type": "Feature",
  "properties": {
    "iso:country":"DE",
    "sg:address":"Uhlandstr. 8",
    "sg:city":"Villingendorf",
    "sg:phone":"+49 741/93450",
    "sg:postcode":"78667",
    "sg:province":"Baden-W\u00fcrttemberg",
    "wof:name":"Martin Weisser Ingenieur",
    "wof:placetype":"venue"
},
  "geometry": {"coordinates":[8.5898656845,48.2007217407],"type":"Point"}
}