{
  "type": "Feature",
  "properties": {
    "iso:country":"DE",
    "sg:address":"Wernher-von-Braunstr. 8a",
    "sg:city":"Olfen",
    "sg:phone":"+49 2595/961426",
    "sg:postcode":"59399",
    "sg:province":"Nordrhein-Westfalen",
    "wof:name":"Industry Management & Inventions",
    "wof:placetype":"venue"
},
  "geometry": {"coordinates":[7.372148037,51.7075271606],"type":"Point"}
}