{
  "type": "Feature",
  "properties": {
    "iso:country":"DE",
    "sg:address":"Fraunhoferstr. 13",
    "sg:city":"Bogen",
    "sg:phone":"+49 9422",
    "sg:postcode":"94327",
    "sg:province":"Bayern",
    "wof:name":"Showtime - Unterhaltung Von A-z",
    "wof:placetype":"venue"
},
  "geometry": {"coordinates":[12.703147,48.914673],"type":"Point"}
}