{
  "type": "Feature",
  "properties": {
    "iso:country":"DE",
    "sg:address":"Graf-Recke-Str. 9",
    "sg:city":"D\u00fcsseldorf",
    "sg:phone":"+49 211/662976",
    "sg:postcode":"40239",
    "sg:province":"Nordrhein-Westfalen",
    "wof:name":"Prof. Dr. E. H\u00fcbener Verm\u00f6gensverwaltungs Gmbh",
    "wof:placetype":"venue"
},
  "geometry": {"coordinates":[6.8039731979,51.2386703491],"type":"Point"}
}