{
  "type": "Feature",
  "properties": {
    "iso:country":"DE",
    "sg:address":"Alter Markt 12",
    "sg:city":"Stolberg",
    "sg:phone":"+49 2402",
    "sg:postcode":"52222",
    "sg:province":"Nordrhein-Westfalen",
    "wof:name":"Textilkunst Claudia Merx",
    "wof:placetype":"venue"
},
  "geometry": {"coordinates":[6.2346048355,50.7670326233],"type":"Point"}
}