{
  "type": "Feature",
  "properties": {
    "iso:country":"DE",
    "sg:address":"Lange Wiese 10",
    "sg:city":"Crossen",
    "sg:phone":"+49 36693/22251",
    "sg:postcode":"07613",
    "sg:province":"Th\u00fcringen",
    "wof:name":"Uwe Dorno Heizung- Und Sanit\u00e4rbau Gmbh",
    "wof:placetype":"venue"
},
  "geometry": {"coordinates":[11.9827356339,50.9672889709],"type":"Point"}
}