{
  "type": "Feature",
  "properties": {
    "iso:country":"DE",
    "sg:address":"2092 Farlow Lake Ct.",
    "sg:city":"Asheboro",
    "sg:phone":"+49 3366/294738",
    "sg:postcode":"27203",
    "wof:name":"Zebra Mall",
    "wof:placetype":"venue"
},
  "geometry": {"coordinates":[-79.803207,35.638039],"type":"Point"}
}