{
  "type": "Feature",
  "properties": {
    "iso:country":"DE",
    "sg:address":"Hauptstr. 40",
    "sg:city":"Hessisch Oldendorf",
    "sg:phone":"+49 5152/527790",
    "sg:postcode":"31840",
    "sg:province":"Niedersachsen",
    "wof:name":"K. Wahl",
    "wof:placetype":"venue"
},
  "geometry": {"coordinates":[9.190767,52.172649],"type":"Point"}
}