{
  "type": "Feature",
  "properties": {
    "iso:country":"DE",
    "sg:address":"Klausenburger Pfad 15",
    "sg:city":"Berlin",
    "sg:phone":"+49 30/7226515",
    "sg:postcode":"12279",
    "sg:province":"Berlin",
    "wof:name":"Michael Neuhold",
    "wof:placetype":"venue"
},
  "geometry": {"coordinates":[13.349063,52.404423],"type":"Point"}
}