{
  "type": "Feature",
  "properties": {
    "iso:country":"DE",
    "sg:address":"Dr.-Carl-Schwenk-Str. 8",
    "sg:city":"Neu-Ulm",
    "sg:phone":"+49 731/719305",
    "sg:postcode":"89233",
    "sg:province":"Bayern",
    "wof:name":"E. Und S. Allgaier",
    "wof:placetype":"venue"
},
  "geometry": {"coordinates":[10.0671882629,48.4210205078],"type":"Point"}
}