{
  "type": "Feature",
  "properties": {
    "iso:country":"DE",
    "sg:address":"Alter Moorweg 10",
    "sg:city":"Tostedt",
    "sg:phone":"+49 4182/7400",
    "sg:postcode":"21255",
    "sg:province":"Niedersachsen",
    "wof:name":"Gastst\u00e4tte Reitcasino",
    "wof:placetype":"venue"
},
  "geometry": {"coordinates":[9.6944875717,53.282283783],"type":"Point"}
}