{
  "type": "Feature",
  "properties": {
    "iso:country":"DE",
    "sg:address":"Schwingener Weg 1",
    "sg:city":"Schwarzenbach a d Saale",
    "sg:phone":"+49 9284/9310",
    "sg:postcode":"95126",
    "sg:province":"Bayern",
    "wof:name":"Secendo Mode Ohg",
    "wof:placetype":"venue"
},
  "geometry": {"coordinates":[11.947233,50.222218],"type":"Point"}
}