{
  "type": "Feature",
  "properties": {
    "iso:country":"DE",
    "sg:address":"G\u00fcstower Str. 13",
    "sg:city":"Prenzlau",
    "sg:phone":"+49 3984/85960",
    "sg:postcode":"17291",
    "sg:province":"Brandenburg",
    "wof:name":"Torsten Steinke",
    "wof:placetype":"venue"
},
  "geometry": {"coordinates":[13.8268222809,53.3087387085],"type":"Point"}
}