{
  "type": "Feature",
  "properties": {
    "iso:country":"DE",
    "sg:address":"Broicherdorfstr. 126 b",
    "sg:city":"Kaarst",
    "sg:phone":"+49 2131/601192",
    "sg:postcode":"41564",
    "sg:province":"Nordrhein-Westfalen",
    "wof:name":"New Way Music Gmbh Musikverlag-und Produktion",
    "wof:placetype":"venue"
},
  "geometry": {"coordinates":[6.5924577713,51.2329101562],"type":"Point"}
}