{
  "type": "Feature",
  "properties": {
    "iso:country":"DE",
    "sg:address":"Frankenstr. 5",
    "sg:city":"Jesewitz",
    "sg:phone":"+49 34241/51100",
    "sg:postcode":"04838",
    "sg:province":"Sachsen",
    "wof:name":"Lore Jacobi",
    "wof:placetype":"venue"
},
  "geometry": {"coordinates":[12.560803,51.424911],"type":"Point"}
}