{
  "type": "Feature",
  "properties": {
    "iso:country":"DE",
    "sg:address":"Frauentorstr. 36",
    "sg:city":"Augsburg",
    "sg:phone":"+49 821/30897",
    "sg:postcode":"86152",
    "sg:province":"Bayern",
    "wof:name":"Eva Schumy",
    "wof:placetype":"venue"
},
  "geometry": {"coordinates":[10.895526886,48.376121521],"type":"Point"}
}