{
  "type": "Feature",
  "properties": {
    "iso:country":"DE",
    "sg:address":"Hans-Fallada-Str. 2",
    "sg:city":"Greifswald",
    "sg:postcode":"17489",
    "sg:province":"Mecklenburg-Vorpommern",
    "wof:name":"Institut F\u00fcr Sport Und Sportwissenschaft",
    "wof:placetype":"venue"
},
  "geometry": {"coordinates":[13.368521,54.096363],"type":"Point"}
}