{
  "type": "Feature",
  "properties": {
    "iso:country":"DE",
    "sg:address":"Forstgasse 26",
    "sg:city":"Eschwege",
    "sg:phone":"+49 5651/50038",
    "sg:postcode":"37269",
    "sg:province":"Hessen",
    "wof:name":"Luther Bauplanung Gmbh",
    "wof:placetype":"venue"
},
  "geometry": {"coordinates":[10.054897,51.18734],"type":"Point"}
}