{
  "type": "Feature",
  "properties": {
    "iso:country":"DE",
    "sg:address":"Goldbacher Str. 84",
    "sg:city":"Aschaffenburg",
    "sg:phone":"+49 6021/412734",
    "sg:postcode":"63741",
    "sg:province":"Bayern",
    "wof:name":"Emde Altpapier-erfassung Und -verwertung Gmbh",
    "wof:placetype":"venue"
},
  "geometry": {"coordinates":[9.1617078781,49.9853668213],"type":"Point"}
}