{
  "type": "Feature",
  "properties": {
    "iso:country":"DE",
    "sg:address":"Rathausstr. 22",
    "sg:city":"Stammbach",
    "sg:postcode":"95236",
    "sg:province":"Bayern",
    "wof:name":"Textil-betriebs- Gmbh",
    "wof:placetype":"venue"
},
  "geometry": {"coordinates":[11.694883,50.144978],"type":"Point"}
}