{
  "type": "Feature",
  "properties": {
    "iso:country":"DE",
    "sg:address":"B\u00fcnteweg 17 d",
    "sg:city":"Hannover",
    "sg:phone":"+49 511/9568882",
    "sg:postcode":"30559",
    "sg:province":"Niedersachsen",
    "wof:name":"Botanisches Institut Der Tier\u00e4rtzlichen Hochschule",
    "wof:placetype":"venue"
},
  "geometry": {"coordinates":[9.807495,52.354347],"type":"Point"}
}