{
  "type": "Feature",
  "properties": {
    "iso:country":"DE",
    "sg:address":"Gutenbergstr. 14b",
    "sg:city":"Rosbach",
    "sg:phone":"+49 6007/930063",
    "sg:postcode":"61191",
    "sg:province":"Hessen",
    "wof:name":"R. Ellinger-philipp",
    "wof:placetype":"venue"
},
  "geometry": {"coordinates":[8.6901054382,50.3032836914],"type":"Point"}
}