{
  "type": "Feature",
  "properties": {
    "iso:country":"DE",
    "sg:address":"Andreasstr. 1",
    "sg:city":"Radevormwald",
    "sg:postcode":"42477",
    "sg:province":"Nordrhein-Westfalen",
    "wof:name":"Ev. Luth. Kirchengemeinde Wartburghaus",
    "wof:placetype":"venue"
},
  "geometry": {"coordinates":[7.3543639183,51.2050819397],"type":"Point"}
}