{
  "type": "Feature",
  "properties": {
    "iso:country":"DE",
    "sg:address":"Verdener Str. 31",
    "sg:city":"Schneverdingen",
    "sg:phone":"+49 5193/50700",
    "sg:postcode":"29640",
    "sg:province":"Niedersachsen",
    "wof:name":"Gastst\u00e4tte M. Mahlandt",
    "wof:placetype":"venue"
},
  "geometry": {"coordinates":[9.7885875702,53.1141548157],"type":"Point"}
}