{
  "type": "Feature",
  "properties": {
    "iso:country":"DE",
    "sg:address":"Badstr. 3",
    "sg:city":"Hollfeld",
    "sg:phone":"+49 9274/652",
    "sg:postcode":"96142",
    "sg:province":"Bayern",
    "wof:name":"G\u00fcnther Und Michael Hofmann",
    "wof:placetype":"venue"
},
  "geometry": {"coordinates":[11.2953624725,49.9384613037],"type":"Point"}
}