{
  "type": "Feature",
  "properties": {
    "iso:country":"DE",
    "sg:address":"Kirchbreite 32",
    "sg:city":"L\u00f6hne",
    "sg:phone":"+49 5731/78610",
    "sg:postcode":"32584",
    "sg:province":"Nordrhein-Westfalen",
    "wof:name":"Eduard-kuhlo-heim E. V.",
    "wof:placetype":"venue"
},
  "geometry": {"coordinates":[8.757564,52.197201],"type":"Point"}
}