{
  "type": "Feature",
  "properties": {
    "iso:country":"DE",
    "sg:address":"Martinetstr. 10",
    "sg:city":"H\u00f6chstadt",
    "sg:phone":"+49 9193/3514",
    "sg:postcode":"91315",
    "sg:province":"Bayern",
    "wof:name":"Helmut H\u00f6fer",
    "wof:placetype":"venue"
},
  "geometry": {"coordinates":[10.811373,49.706081],"type":"Point"}
}