{
  "type": "Feature",
  "properties": {
    "iso:country":"DE",
    "sg:address":"Th\u00fcngersheimer Str. 20",
    "sg:city":"G\u00fcntersleben",
    "sg:phone":"+49 9365/9265",
    "sg:postcode":"97261",
    "sg:province":"Bayern",
    "wof:name":"W. Und E. Schmitt",
    "wof:placetype":"venue"
},
  "geometry": {"coordinates":[9.903306,49.869663],"type":"Point"}
}