{
  "type": "Feature",
  "properties": {
    "iso:country":"DE",
    "sg:address":"Vogteistr. 21",
    "sg:city":"L\u00fcbeck",
    "sg:phone":"+49 4502/3232",
    "sg:postcode":"23570",
    "sg:province":"Schleswig-Holstein",
    "wof:name":"Baltic-stuben",
    "wof:placetype":"venue"
},
  "geometry": {"coordinates":[10.8688879013,53.958984375],"type":"Point"}
}