{
  "type": "Feature",
  "properties": {
    "iso:country":"DE",
    "sg:address":"Bielefelder Str. 264",
    "sg:city":"Detmold",
    "sg:phone":"+49 5231/66355",
    "sg:postcode":"32758",
    "sg:province":"Nordrhein-Westfalen",
    "wof:name":"Sonnen-apotheke Ohg",
    "wof:placetype":"venue"
},
  "geometry": {"coordinates":[8.82474,51.950111],"type":"Point"}
}