{
  "type": "Feature",
  "properties": {
    "iso:country":"DE",
    "sg:address":"Wollenweberstr. 8",
    "sg:city":"Hildesheim",
    "sg:phone":"+49 5121/32434",
    "sg:postcode":"31134",
    "sg:province":"Niedersachsen",
    "wof:name":"Karl Pinkvos",
    "wof:placetype":"venue"
},
  "geometry": {"coordinates":[9.953065,52.148697],"type":"Point"}
}