{
  "type": "Feature",
  "properties": {
    "iso:country":"DE",
    "sg:address":"Dreieichstr. 22b",
    "sg:city":"Friedrichsdorf",
    "sg:phone":"+49 6175/93490",
    "sg:postcode":"61381",
    "sg:province":"Hessen",
    "wof:name":"Hotel-restaurant Niebuhrs",
    "wof:placetype":"venue"
},
  "geometry": {"coordinates":[8.6469163895,50.2749786377],"type":"Point"}
}