{
  "type": "Feature",
  "properties": {
    "iso:country":"DE",
    "sg:address":"Rh\u00f6nbergstr. 20",
    "sg:city":"Oberelsbach",
    "sg:phone":"+49 9774/439",
    "sg:postcode":"97656",
    "sg:province":"Bayern",
    "wof:name":"Edgar Feinauer Masseur",
    "wof:placetype":"venue"
},
  "geometry": {"coordinates":[10.076158,50.42115],"type":"Point"}
}