{
  "type": "Feature",
  "properties": {
    "iso:country":"DE",
    "sg:address":"Heidestr. 19",
    "sg:city":"Detmold",
    "sg:phone":"+49 5231/26115",
    "sg:postcode":"32756",
    "sg:province":"Nordrhein-Westfalen",
    "wof:name":"J\u00fcrgen Heistermann",
    "wof:placetype":"venue"
},
  "geometry": {"coordinates":[8.870032,51.951771],"type":"Point"}
}