{
  "type": "Feature",
  "properties": {
    "iso:country":"DE",
    "sg:address":"Dietbachstr. 40 b",
    "sg:city":"Stuttgart",
    "sg:phone":"+49 711/334440",
    "sg:postcode":"70327",
    "sg:province":"Baden-W\u00fcrttemberg",
    "wof:name":"Walter Metzger Rechtsanwalt",
    "wof:placetype":"venue"
},
  "geometry": {"coordinates":[9.2499389648,48.79139328],"type":"Point"}
}