{
  "type": "Feature",
  "properties": {
    "iso:country":"DE",
    "sg:address":"Sigmaringer Str. 22",
    "sg:city":"Berlin",
    "sg:phone":"+49 30/8738208",
    "sg:postcode":"10713",
    "sg:province":"Berlin",
    "wof:name":"Meta Manske",
    "wof:placetype":"venue"
},
  "geometry": {"coordinates":[13.319167,52.490654],"type":"Point"}
}