{
  "type": "Feature",
  "properties": {
    "iso:country":"DE",
    "sg:address":"Neue Str. 1",
    "sg:city":"Langendorf",
    "sg:phone":"+49 5882/297",
    "sg:postcode":"29484",
    "sg:province":"Niedersachsen",
    "wof:name":"G. Cremer",
    "wof:placetype":"venue"
},
  "geometry": {"coordinates":[11.234161377,53.1074523926],"type":"Point"}
}