{
  "type": "Feature",
  "properties": {
    "iso:country":"DE",
    "sg:address":"Kinzigtalstr. 10",
    "sg:city":"Freiensteinau",
    "sg:phone":"+49 6666/405",
    "sg:postcode":"36399",
    "sg:province":"Hessen",
    "wof:name":"Willi Flach",
    "wof:placetype":"venue"
},
  "geometry": {"coordinates":[9.4196720123,50.4153633118],"type":"Point"}
}