{
  "type": "Feature",
  "properties": {
    "iso:country":"DE",
    "sg:address":"Werner-Siemens-Str. 100",
    "sg:city":"Hamburg",
    "sg:phone":"+49 40/211140",
    "sg:postcode":"22113",
    "sg:province":"Schleswig-Holstein",
    "wof:name":"Zippert & Kr\u00f6ger Gmbh",
    "wof:placetype":"venue"
},
  "geometry": {"coordinates":[10.1086015701,53.5269775391],"type":"Point"}
}