{
  "type": "Feature",
  "properties": {
    "iso:country":"DE",
    "sg:address":"Erich-Weinert-Str.",
    "sg:city":"Gera",
    "sg:phone":"+49 365/413158",
    "sg:postcode":"07546",
    "sg:province":"Th\u00fcringen",
    "wof:name":"Cv Plus Computer, Software, Vertrieb Gmbh",
    "wof:placetype":"venue"
},
  "geometry": {"coordinates":[12.088026,50.896915],"type":"Point"}
}