{
  "type": "Feature",
  "properties": {
    "iso:country":"DE",
    "sg:address":"An den G\u00e4rten 4",
    "sg:city":"L\u00fcchow",
    "sg:phone":"+49 5841/5655",
    "sg:postcode":"29439",
    "sg:province":"Niedersachsen",
    "wof:name":"P. H\u00f6rster Inh. Wolfgang H\u00f6rster",
    "wof:placetype":"venue"
},
  "geometry": {"coordinates":[11.1500482559,52.9628753662],"type":"Point"}
}