{
  "type": "Feature",
  "properties": {
    "iso:country":"DE",
    "sg:address":"Hauptstr. 181",
    "sg:city":"K\u00f6ln",
    "sg:phone":"+49 2203/982534",
    "sg:postcode":"51143",
    "sg:province":"Nordrhein-Westfalen",
    "wof:name":"Restaurant Turmhof",
    "wof:placetype":"venue"
},
  "geometry": {"coordinates":[7.0465860367,50.8702354431],"type":"Point"}
}