{
  "type": "Feature",
  "properties": {
    "iso:country":"DE",
    "sg:address":"Neusser Str. 3",
    "sg:city":"M\u00fcnchen",
    "sg:phone":"+49 89/360960",
    "sg:postcode":"80807",
    "sg:province":"Bayern",
    "wof:name":"Langenscheidt Verlagsgesells. F\u00fcr Wissen Und Sprache Mbh",
    "wof:placetype":"venue"
},
  "geometry": {"coordinates":[11.5730495453,48.182258606],"type":"Point"}
}