{
  "type": "Feature",
  "properties": {
    "iso:country":"DE",
    "sg:address":"Thomasstr. 2",
    "sg:city":"Bad Homburg",
    "sg:phone":"+49 6172/23796",
    "sg:postcode":"61348",
    "sg:province":"Hessen",
    "wof:name":"Galerie Schweizer Inh. Josef Nikolaus Schweizer",
    "wof:placetype":"venue"
},
  "geometry": {"coordinates":[8.617407,50.226273],"type":"Point"}
}