{
  "type": "Feature",
  "properties": {
    "iso:country":"DE",
    "sg:address":"Waldstr. 3",
    "sg:city":"Weilersbach",
    "sg:phone":"+49 9191/9345",
    "sg:postcode":"91365",
    "sg:province":"Bayern",
    "wof:name":"Gerd Faulhaber",
    "wof:placetype":"venue"
},
  "geometry": {"coordinates":[11.1288919449,49.7401657104],"type":"Point"}
}