{
  "type": "Feature",
  "properties": {
    "iso:country":"DE",
    "sg:address":"Im Meistergarten 8",
    "sg:city":"Heinrichsthal",
    "sg:phone":"+49 6020/1378",
    "sg:postcode":"63871",
    "sg:province":"Bayern",
    "wof:name":"Manfred Elsesser Gmbh",
    "wof:placetype":"venue"
},
  "geometry": {"coordinates":[9.3380718231,50.073299408],"type":"Point"}
}