{
  "type": "Feature",
  "properties": {
    "iso:country":"DE",
    "sg:address":"Winkeler Str.",
    "sg:city":"Geisenheim",
    "sg:phone":"+49 6722/8258",
    "sg:postcode":"65366",
    "sg:province":"Hessen",
    "wof:name":"G. H. V. Mumm Weinanbau",
    "wof:placetype":"venue"
},
  "geometry": {"coordinates":[7.9669070244,49.9840965271],"type":"Point"}
}