{
  "type": "Feature",
  "properties": {
    "iso:country":"DE",
    "sg:address":"Pirnaer Landstr. 13",
    "sg:city":"Stolpen",
    "sg:phone":"+49 4937/3269020",
    "sg:postcode":"01833",
    "sg:province":"Sachsen",
    "wof:name":"Agrar-genossenschaft Burgberg E.g.",
    "wof:placetype":"venue"
},
  "geometry": {"coordinates":[13.54167,50.762558],"type":"Point"}
}