{
  "type": "Feature",
  "properties": {
    "iso:country":"DE",
    "sg:address":"Huferberg 1",
    "sg:city":"Overath",
    "sg:phone":"+49 2204/71907",
    "sg:postcode":"51491",
    "sg:province":"Nordrhein-Westfalen",
    "wof:name":"F. Gierlich",
    "wof:placetype":"venue"
},
  "geometry": {"coordinates":[7.2574357986,50.9596176147],"type":"Point"}
}