{
  "type": "Feature",
  "properties": {
    "iso:country":"DE",
    "sg:address":"Johannisstr. 36",
    "sg:city":"Bielefeld",
    "sg:phone":"+49 521/8752306",
    "sg:postcode":"33611",
    "sg:province":"Nordrhein-Westfalen",
    "wof:name":"Namaste",
    "wof:placetype":"venue"
},
  "geometry": {"coordinates":[8.549331665,52.0567741394],"type":"Point"}
}