{
  "type": "Feature",
  "properties": {
    "iso:country":"DE",
    "sg:address":"Medinger Str. 20",
    "sg:city":"Bad Bevensen",
    "sg:phone":"+49 5821/1305",
    "sg:postcode":"29549",
    "sg:province":"Niedersachsen",
    "wof:name":"O. Behnke & H. Koesling",
    "wof:placetype":"venue"
},
  "geometry": {"coordinates":[10.574772,53.080502],"type":"Point"}
}