{
  "type": "Feature",
  "properties": {
    "iso:country":"DE",
    "sg:address":"Schneiderstr. 1",
    "sg:city":"Bremen",
    "sg:postcode":"28717",
    "sg:province":"Bremen",
    "wof:name":"Md Consult Gmbh Merger & Developement",
    "wof:placetype":"venue"
},
  "geometry": {"coordinates":[8.6880578995,53.1694374084],"type":"Point"}
}