{
  "type": "Feature",
  "properties": {
    "iso:country":"DE",
    "sg:address":"Halluinstr. 28",
    "sg:city":"Oer-Erkenschwick",
    "sg:phone":"+49 2368/56813",
    "sg:postcode":"45739",
    "sg:province":"Nordrhein-Westfalen",
    "wof:name":"Am Steinweg",
    "wof:placetype":"venue"
},
  "geometry": {"coordinates":[7.257649,51.641296],"type":"Point"}
}