{
  "type": "Feature",
  "properties": {
    "iso:country":"DE",
    "sg:address":"Johann-Sebastian-Bach-Str. 99",
    "sg:city":"Werl",
    "sg:postcode":"59457",
    "sg:province":"Nordrhein-Westfalen",
    "wof:name":"Tg Airprofile Gmbh",
    "wof:placetype":"venue"
},
  "geometry": {"coordinates":[7.9147081375,51.542842865],"type":"Point"}
}