{
  "type": "Feature",
  "properties": {
    "iso:country":"DE",
    "sg:address":"Am Kirchplatz",
    "sg:city":"Oelde",
    "sg:postcode":"59302",
    "sg:province":"Nordrhein-Westfalen",
    "wof:name":"Kath. \u00f6ffentliche Bibliothek St. Johannes",
    "wof:placetype":"venue"
},
  "geometry": {"coordinates":[8.14914,51.768261],"type":"Point"}
}