{
  "type": "Feature",
  "properties": {
    "iso:country":"DE",
    "sg:address":"Mannheimer Str. 18",
    "sg:city":"Berlin",
    "sg:phone":"+49 30/5660622",
    "sg:postcode":"12623",
    "sg:province":"Berlin",
    "wof:name":"Mannsfeld & Partner Gmbh",
    "wof:placetype":"venue"
},
  "geometry": {"coordinates":[13.602396965,52.4887657166],"type":"Point"}
}