{
  "type": "Feature",
  "properties": {
    "iso:country":"DE",
    "sg:address":"Irisweg 101",
    "sg:city":"Elsdorf",
    "sg:phone":"+49 2274/81931",
    "sg:postcode":"50189",
    "sg:province":"Nordrhein-Westfalen",
    "wof:name":"Paul Schmitz",
    "wof:placetype":"venue"
},
  "geometry": {"coordinates":[6.56539011,50.9257888794],"type":"Point"}
}