{
  "type": "Feature",
  "properties": {
    "iso:country":"DE",
    "sg:address":"Birkenweg 5",
    "sg:city":"H\u00fcrup",
    "sg:phone":"+49 4634/93349",
    "sg:postcode":"24975",
    "sg:province":"Schleswig-Holstein",
    "wof:name":"Ingenieurb\u00fcro F\u00fcr Informationsverarb. U. System-",
    "wof:placetype":"venue"
},
  "geometry": {"coordinates":[9.5263204575,54.7461090088],"type":"Point"}
}