{
  "type": "Feature",
  "properties": {
    "iso:country":"DE",
    "sg:address":"Aachener Str. 1150",
    "sg:city":"K\u00f6ln",
    "sg:phone":"+49 2234/76781",
    "sg:postcode":"50858",
    "sg:province":"Nordrhein-Westfalen",
    "wof:name":"Albert Thibold",
    "wof:placetype":"venue"
},
  "geometry": {"coordinates":[6.8420128822,50.9383850098],"type":"Point"}
}