{
  "type": "Feature",
  "properties": {
    "iso:country":"DE",
    "sg:address":"Entenseestr. 21",
    "sg:city":"R\u00fcckersdorf",
    "sg:phone":"+49 911/5700710",
    "sg:postcode":"90607",
    "sg:province":"Bayern",
    "wof:name":"Dr. Andrew May Patentanwalt",
    "wof:placetype":"venue"
},
  "geometry": {"coordinates":[11.2341032028,49.4940757751],"type":"Point"}
}