{
  "type": "Feature",
  "properties": {
    "iso:country":"DE",
    "sg:address":"Gro\u00dfe Falterstr. 4",
    "sg:city":"Stuttgart",
    "sg:phone":"+49 711/760088",
    "sg:postcode":"70597",
    "sg:province":"Baden-W\u00fcrttemberg",
    "wof:name":"Ev. Pfarramt I",
    "wof:placetype":"venue"
},
  "geometry": {"coordinates":[9.1712188721,48.7461013794],"type":"Point"}
}