{
  "type": "Feature",
  "properties": {
    "iso:country":"DE",
    "sg:address":"Marktplatz 12",
    "sg:city":"Marktleuthen",
    "sg:phone":"+49 9285/1499",
    "sg:postcode":"95168",
    "sg:province":"Bayern",
    "wof:name":"Georg K\u00f6nig",
    "wof:placetype":"venue"
},
  "geometry": {"coordinates":[11.994009,50.128067],"type":"Point"}
}