{
  "type": "Feature",
  "properties": {
    "iso:country":"DE",
    "sg:address":"Staufener Str. 10",
    "sg:city":"Heidenheim",
    "sg:phone":"+49 7321/71931",
    "sg:postcode":"89522",
    "sg:province":"Baden-W\u00fcrttemberg",
    "wof:name":"H. Schmidt Kg",
    "wof:placetype":"venue"
},
  "geometry": {"coordinates":[10.2370319366,48.6698684692],"type":"Point"}
}