{
  "type": "Feature",
  "properties": {
    "iso:country":"DE",
    "sg:city":"Menden",
    "sg:postcode":"58708",
    "sg:province":"Nordrhein-Westfalen",
    "wof:name":"Mdz",
    "wof:placetype":"venue"
},
  "geometry": {"coordinates":[7.84526,51.43438],"type":"Point"}
}