{
  "type": "Feature",
  "properties": {
    "iso:country":"DE",
    "sg:address":"Meinardusstr. 4",
    "sg:city":"Oldenburg",
    "sg:phone":"+49 441/950880",
    "sg:postcode":"26122",
    "sg:province":"Niedersachsen",
    "wof:name":"Simon Und Schubert Rechtsanw\u00e4lte Und Notare",
    "wof:placetype":"venue"
},
  "geometry": {"coordinates":[8.2043609619,53.1344299316],"type":"Point"}
}