{
  "type": "Feature",
  "properties": {
    "iso:country":"DE",
    "sg:address":"Am Sonnenhof 46",
    "sg:city":"P\u00f6\u00dfneck",
    "sg:postcode":"07381",
    "sg:province":"Th\u00fcringen",
    "wof:name":"R. Geisenhainer",
    "wof:placetype":"venue"
},
  "geometry": {"coordinates":[11.606384,50.697678],"type":"Point"}
}