{
  "type": "Feature",
  "properties": {
    "iso:country":"DE",
    "sg:address":"Mozartstr. 5",
    "sg:city":"D\u00fclmen",
    "sg:phone":"+49 2594/3753",
    "sg:postcode":"48249",
    "sg:province":"Nordrhein-Westfalen",
    "wof:name":"Bernd Friep\u00f6rtner",
    "wof:placetype":"venue"
},
  "geometry": {"coordinates":[7.266778,51.844357],"type":"Point"}
}