{
  "type": "Feature",
  "properties": {
    "iso:country":"DE",
    "sg:address":"Aberlestr. 16",
    "sg:city":"M\u00fcnchen",
    "sg:phone":"+49 89/2907160",
    "sg:postcode":"81371",
    "sg:province":"Bayern",
    "wof:name":"M. C. I. Marketing Und Conception F\u00fcr Immobilien Gmbh",
    "wof:placetype":"venue"
},
  "geometry": {"coordinates":[11.5452203751,48.1207313538],"type":"Point"}
}