{
  "type": "Feature",
  "properties": {
    "iso:country":"DE",
    "sg:address":"Rahserfeld 10b",
    "sg:city":"Viersen",
    "sg:phone":"+49 2162/16101",
    "sg:postcode":"41748",
    "sg:province":"Nordrhein-Westfalen",
    "wof:name":"Max Borowski",
    "wof:placetype":"venue"
},
  "geometry": {"coordinates":[6.3951678276,51.2636489868],"type":"Point"}
}