{
  "type": "Feature",
  "properties": {
    "iso:country":"DE",
    "sg:address":"Hauptstr. 29",
    "sg:city":"Hettingen",
    "sg:phone":"+49 7574/2461",
    "sg:postcode":"72513",
    "sg:province":"Baden-W\u00fcrttemberg",
    "wof:name":"J.-h. Knaus",
    "wof:placetype":"venue"
},
  "geometry": {"coordinates":[9.2312021255,48.2151870728],"type":"Point"}
}