{
  "type": "Feature",
  "properties": {
    "iso:country":"DE",
    "sg:address":"Im Gewerbepark C 68",
    "sg:city":"Regensburg",
    "sg:phone":"+49 941/40490",
    "sg:postcode":"93059",
    "sg:province":"Bayern",
    "wof:name":"Richard Sitzberger Ohg",
    "wof:placetype":"venue"
},
  "geometry": {"coordinates":[12.131421,49.033192],"type":"Point"}
}