{
  "type": "Feature",
  "properties": {
    "iso:country":"DE",
    "sg:address":"Weststra\u00dfe 30-34",
    "sg:city":"Aachen",
    "sg:phone":"+49 241",
    "sg:postcode":"52074",
    "sg:province":"Nordrhein-Westfalen",
    "wof:name":"Tecnologix.net - Das Fachportal F\u00fcr Ingenieure",
    "wof:placetype":"venue"
},
  "geometry": {"coordinates":[6.0606241226,50.7714767456],"type":"Point"}
}