{
  "type": "Feature",
  "properties": {
    "iso:country":"DE",
    "sg:address":"K\u00f6lblstr. 5",
    "sg:city":"Freising",
    "sg:phone":"+49 8161/62979",
    "sg:postcode":"85356",
    "sg:province":"Bayern",
    "wof:name":"J. Feldmaier Kabelbau Gmbh",
    "wof:placetype":"venue"
},
  "geometry": {"coordinates":[11.754355,48.403931],"type":"Point"}
}