{
  "type": "Feature",
  "properties": {
    "iso:country":"DE",
    "sg:address":"Bromenlandweg 6",
    "sg:city":"B\u00f6blingen",
    "sg:phone":"+49 7031/675660",
    "sg:postcode":"71034",
    "sg:province":"Baden-W\u00fcrttemberg",
    "wof:name":"Primacon Gmbh",
    "wof:placetype":"venue"
},
  "geometry": {"coordinates":[8.957811,48.695244],"type":"Point"}
}