{
  "type": "Feature",
  "properties": {
    "iso:country":"DE",
    "sg:address":"Bahnhofplatz 7",
    "sg:city":"Overath",
    "sg:phone":"+49 2206/2038",
    "sg:postcode":"51491",
    "sg:province":"Nordrhein-Westfalen",
    "wof:name":"Bundesbahn-gastst\u00e4tte",
    "wof:placetype":"venue"
},
  "geometry": {"coordinates":[7.2881250381,50.9331016541],"type":"Point"}
}