{
  "type": "Feature",
  "properties": {
    "iso:country":"DE",
    "sg:address":"Haydnstr. 15",
    "sg:city":"N\u00fcrnberg",
    "sg:phone":"+49 911/5980320",
    "sg:postcode":"90491",
    "sg:province":"Bayern",
    "wof:name":"Bar-restaurant Steinplatte",
    "wof:placetype":"venue"
},
  "geometry": {"coordinates":[11.1249313354,49.4710464478],"type":"Point"}
}