{
  "type": "Feature",
  "properties": {
    "iso:country":"DE",
    "sg:address":"Langestr. 22",
    "sg:city":"Brakel",
    "sg:phone":"+49 5272/5435",
    "sg:postcode":"33034",
    "sg:province":"Nordrhein-Westfalen",
    "wof:name":"Horst Schneider",
    "wof:placetype":"venue"
},
  "geometry": {"coordinates":[9.233077,51.706303],"type":"Point"}
}