{
  "type": "Feature",
  "properties": {
    "iso:country":"DE",
    "sg:address":"Im Trieb 8",
    "sg:city":"Frankfurt",
    "sg:phone":"+49 69/474744",
    "sg:postcode":"60389",
    "sg:province":"Hessen",
    "wof:name":"A. Wilhelms Kg",
    "wof:placetype":"venue"
},
  "geometry": {"coordinates":[8.7263011932,50.1416625977],"type":"Point"}
}