{
  "type": "Feature",
  "properties": {
    "iso:country":"DE",
    "sg:address":"Knappenweg 37",
    "sg:city":"M\u00fclheim",
    "sg:phone":"+49 208/760961",
    "sg:postcode":"45473",
    "sg:province":"Nordrhein-Westfalen",
    "wof:name":"Hans Egon Krenz Architekt",
    "wof:placetype":"venue"
},
  "geometry": {"coordinates":[6.910873,51.445995],"type":"Point"}
}