{
  "type": "Feature",
  "properties": {
    "iso:country":"DE",
    "sg:address":"Stuttgarter Str. 104",
    "sg:city":"Stuttgart",
    "sg:phone":"+49 711/856301",
    "sg:postcode":"70469",
    "sg:province":"Baden-W\u00fcrttemberg",
    "wof:name":"R. Kowsky",
    "wof:placetype":"venue"
},
  "geometry": {"coordinates":[9.158038,48.809082],"type":"Point"}
}