{
  "type": "Feature",
  "properties": {
    "iso:country":"DE",
    "sg:address":"Industriestr. 8",
    "sg:city":"Mannheim",
    "sg:phone":"+49 4962/1106093",
    "sg:postcode":"68169",
    "sg:province":"Baden-W\u00fcrttemberg",
    "wof:name":"Lahm & Halpaus Gmbh",
    "wof:placetype":"venue"
},
  "geometry": {"coordinates":[8.46393,49.508347],"type":"Point"}
}