{
  "type": "Feature",
  "properties": {
    "iso:country":"DE",
    "sg:address":"Kleinzerbster Str. 23 a",
    "sg:city":"Aken",
    "sg:phone":"+49 34909/82071",
    "sg:postcode":"06385",
    "sg:province":"Sachsen-Anhalt",
    "wof:name":"G. Rothe",
    "wof:placetype":"venue"
},
  "geometry": {"coordinates":[12.043752,51.847027],"type":"Point"}
}