{
  "type": "Feature",
  "properties": {
    "iso:country":"DE",
    "sg:address":"Hansestr. 28",
    "sg:city":"Braunschweig",
    "sg:phone":"+49 531/21340",
    "sg:postcode":"38112",
    "sg:province":"Niedersachsen",
    "wof:name":"Die B\u00fcffeteria Im M\u00f6belhaus Porta",
    "wof:placetype":"venue"
},
  "geometry": {"coordinates":[10.5033845901,52.3100280762],"type":"Point"}
}