{
  "type": "Feature",
  "properties": {
    "iso:country":"DE",
    "sg:address":"Baedekerstr. 17",
    "sg:city":"Essen",
    "sg:phone":"+49 201/223635",
    "sg:postcode":"45128",
    "sg:province":"Nordrhein-Westfalen",
    "wof:name":"Friedrich Witzel",
    "wof:placetype":"venue"
},
  "geometry": {"coordinates":[7.0081148148,51.4486045837],"type":"Point"}
}