{
  "type": "Feature",
  "properties": {
    "iso:country":"DE",
    "sg:address":"Winkelstr. 2",
    "sg:city":"Remscheid",
    "sg:postcode":"42853",
    "sg:province":"Nordrhein-Westfalen",
    "wof:name":"Oliver Da Silveira",
    "wof:placetype":"venue"
},
  "geometry": {"coordinates":[7.1841688156,51.179851532],"type":"Point"}
}