{
  "type": "Feature",
  "properties": {
    "iso:country":"DE",
    "sg:address":"Hoffenheimer Str 2",
    "sg:city":"Zuzenhausen",
    "sg:phone":"+49 6226/1559",
    "sg:postcode":"74939",
    "sg:province":"Baden-W\u00fcrttemberg",
    "wof:name":"Claudia Minges Gmbh",
    "wof:placetype":"venue"
},
  "geometry": {"coordinates":[8.824152,49.295223],"type":"Point"}
}