{
  "type": "Feature",
  "properties": {
    "iso:country":"DE",
    "sg:address":"Bei der Abtspferdetr\u00e4nke 7",
    "sg:city":"L\u00fcneburg",
    "sg:phone":"+49 4131/37273",
    "sg:postcode":"21335",
    "sg:province":"Niedersachsen",
    "wof:name":"Gastst\u00e4tte Triangle",
    "wof:placetype":"venue"
},
  "geometry": {"coordinates":[10.4116230011,53.250289917],"type":"Point"}
}