{
  "type": "Feature",
  "properties": {
    "iso:country":"DE",
    "sg:address":"Joliot-Curie-Allee 39",
    "sg:city":"Rostock",
    "sg:phone":"+49 381/6863917",
    "sg:postcode":"18147",
    "sg:province":"Mecklenburg-Vorpommern",
    "wof:name":"Zur Zeese Inh. Harald Werth",
    "wof:placetype":"venue"
},
  "geometry": {"coordinates":[12.1158151627,54.103351593],"type":"Point"}
}