{
  "type": "Feature",
  "properties": {
    "iso:country":"DE",
    "sg:address":"Bahnhofstr. 2",
    "sg:city":"Westerkappeln",
    "sg:phone":"+49 5404/3201",
    "sg:postcode":"49492",
    "sg:province":"Nordrhein-Westfalen",
    "wof:name":"Hammer",
    "wof:placetype":"venue"
},
  "geometry": {"coordinates":[7.8774790764,52.3147163391],"type":"Point"}
}