{
  "type": "Feature",
  "properties": {
    "iso:country":"DE",
    "sg:address":"Im Derdel 8",
    "sg:city":"Muenster",
    "sg:postcode":"48143",
    "sg:province":"Nordrhein-Westfalen",
    "wof:name":"Westfaelisches Studieninstitut Muenster",
    "wof:placetype":"venue"
},
  "geometry": {"coordinates":[7.617817,51.96302],"type":"Point"}
}