{
  "type": "Feature",
  "properties": {
    "iso:country":"DE",
    "sg:address":"K\u00f6lner Str. 26",
    "sg:city":"D\u00fcsseldorf",
    "sg:phone":"+49 211/350031",
    "sg:postcode":"40211",
    "sg:province":"Nordrhein-Westfalen",
    "wof:name":"Hotel Benkwitz",
    "wof:placetype":"venue"
},
  "geometry": {"coordinates":[6.7934660912,51.2269859314],"type":"Point"}
}