{
  "type": "Feature",
  "properties": {
    "iso:country":"DE",
    "sg:address":"Topfmarkt 4a",
    "sg:city":"Lobenstein",
    "sg:postcode":"07356",
    "sg:province":"Th\u00fcringen",
    "wof:name":"Rekoplan Gmbh",
    "wof:placetype":"venue"
},
  "geometry": {"coordinates":[11.6410684586,50.4476699829],"type":"Point"}
}