{
  "type": "Feature",
  "properties": {
    "iso:country":"DE",
    "sg:address":"Mittlerer Lech 5",
    "sg:city":"Augsburg",
    "sg:phone":"+49 821/3242972",
    "sg:postcode":"86150",
    "sg:province":"Bayern",
    "wof:name":"Jakobs-stift Altenwohnheim",
    "wof:placetype":"venue"
},
  "geometry": {"coordinates":[10.90071,48.368832],"type":"Point"}
}