{
  "type": "Feature",
  "properties": {
    "iso:country":"DE",
    "sg:address":"Industriestr. 1 C",
    "sg:city":"Meppen",
    "sg:phone":"+49 5931/888547",
    "sg:postcode":"49716",
    "sg:province":"Niedersachsen",
    "wof:name":"Restaurant U-boot",
    "wof:placetype":"venue"
},
  "geometry": {"coordinates":[7.3010811806,52.6740722656],"type":"Point"}
}