{
  "type": "Feature",
  "properties": {
    "iso:country":"DE",
    "sg:address":"Marktstr. 11",
    "sg:city":"Harsefeld",
    "sg:phone":"+49 4164/4711",
    "sg:postcode":"21698",
    "sg:province":"Niedersachsen",
    "wof:name":"Arnold",
    "wof:placetype":"venue"
},
  "geometry": {"coordinates":[9.5024385452,53.4529304504],"type":"Point"}
}