{
  "type": "Feature",
  "properties": {
    "iso:country":"DE",
    "sg:address":"Telegrafenberg",
    "sg:city":"Potsdam",
    "sg:postcode":"14473",
    "sg:province":"Brandenburg",
    "wof:name":"Widynski & Roick Gmbh",
    "wof:placetype":"venue"
},
  "geometry": {"coordinates":[13.0666799545,52.383026123],"type":"Point"}
}