{
  "type": "Feature",
  "properties": {
    "iso:country":"DE",
    "sg:address":"Westerbachstr. 19",
    "sg:city":"Oer-Erkenschwick",
    "sg:phone":"+49 2368/1467",
    "sg:postcode":"45739",
    "sg:province":"Nordrhein-Westfalen",
    "wof:name":"Malerbetrieb-glaserei Hans Drees E. K.",
    "wof:placetype":"venue"
},
  "geometry": {"coordinates":[7.259195,51.634956],"type":"Point"}
}