{
  "type": "Feature",
  "properties": {
    "iso:country":"DE",
    "sg:address":"Halbrunnenweg 68",
    "sg:city":"Wertheim",
    "sg:phone":"+49 9342/4711",
    "sg:postcode":"97877",
    "sg:province":"Baden-W\u00fcrttemberg",
    "wof:name":"Thea Engels",
    "wof:placetype":"venue"
},
  "geometry": {"coordinates":[9.5035219193,49.7512245178],"type":"Point"}
}