{
  "type": "Feature",
  "properties": {
    "iso:country":"DE",
    "sg:address":"Riemenschneiderstr. 1",
    "sg:city":"Aalen",
    "sg:phone":"+49 7361/71666",
    "sg:postcode":"73433",
    "sg:province":"Baden-W\u00fcrttemberg",
    "wof:name":"Johann Tosch",
    "wof:placetype":"venue"
},
  "geometry": {"coordinates":[10.10921,48.866051],"type":"Point"}
}