{
  "type": "Feature",
  "properties": {
    "iso:country":"DE",
    "sg:address":"M\u00fchlenstr. 201",
    "sg:city":"Ahausen",
    "sg:phone":"+49 4269/5424",
    "sg:postcode":"27367",
    "sg:province":"Niedersachsen",
    "wof:name":"Alfred Denell",
    "wof:placetype":"venue"
},
  "geometry": {"coordinates":[9.29785,53.073009],"type":"Point"}
}