{
  "type": "Feature",
  "properties": {
    "iso:country":"DE",
    "sg:address":"Sirnauer Str. 17",
    "sg:city":"Esslingen",
    "sg:phone":"+49 711/356671",
    "sg:postcode":"73728",
    "sg:province":"Baden-W\u00fcrttemberg",
    "wof:name":"M. Und K. Haug",
    "wof:placetype":"venue"
},
  "geometry": {"coordinates":[9.305721283,48.7391662598],"type":"Point"}
}