{
  "type": "Feature",
  "properties": {
    "iso:country":"DE",
    "sg:address":"Vorstadt 5",
    "sg:city":"Oberursel",
    "sg:phone":"+49 6171/54414",
    "sg:postcode":"61440",
    "sg:province":"Hessen",
    "wof:name":"Textilhaus N. Kr\u00e4mer Gmbh",
    "wof:placetype":"venue"
},
  "geometry": {"coordinates":[8.5823869705,50.2011108398],"type":"Point"}
}