{
  "type": "Feature",
  "properties": {
    "iso:country":"DE",
    "sg:address":"Burgkmairstr. 55",
    "sg:city":"M\u00fcnchen",
    "sg:phone":"+49 89/5808034",
    "sg:postcode":"80686",
    "sg:province":"Bayern",
    "wof:name":"Dr. Willy Kungl Wirtschaftspr\u00fcfer",
    "wof:placetype":"venue"
},
  "geometry": {"coordinates":[11.5115642548,48.1300849915],"type":"Point"}
}