{
  "type": "Feature",
  "properties": {
    "iso:country":"DE",
    "sg:address":"Kalsow 14",
    "sg:city":"Benz",
    "sg:phone":"+49 38426/4004",
    "sg:postcode":"23970",
    "sg:province":"Mecklenburg-Vorpommern",
    "wof:name":"Johannes-h. Picha Bau Gmbh",
    "wof:placetype":"venue"
},
  "geometry": {"coordinates":[11.581115,53.921368],"type":"Point"}
}