{
  "type": "Feature",
  "properties": {
    "iso:country":"DE",
    "sg:address":"St\u00f6rtebekerstr. 31",
    "sg:city":"Bergen",
    "sg:phone":"+49 3838/254873",
    "sg:postcode":"18528",
    "sg:province":"Mecklenburg-Vorpommern",
    "wof:name":"J. Zscharschuch",
    "wof:placetype":"venue"
},
  "geometry": {"coordinates":[13.384765,54.5084],"type":"Point"}
}