{
  "type": "Feature",
  "properties": {
    "iso:country":"DE",
    "sg:address":"Oppumer Str. 90",
    "sg:city":"Krefeld",
    "sg:phone":"+49 2151/66181",
    "sg:postcode":"47799",
    "sg:province":"Nordrhein-Westfalen",
    "wof:name":"Tenten Boote",
    "wof:placetype":"venue"
},
  "geometry": {"coordinates":[6.583614,51.332783],"type":"Point"}
}