{
  "type": "Feature",
  "properties": {
    "iso:country":"DE",
    "sg:address":"Carl-Orff-Str. 3",
    "sg:city":"Velbert",
    "sg:phone":"+49 2053/6935",
    "sg:postcode":"42553",
    "sg:province":"Nordrhein-Westfalen",
    "wof:name":"Karl-heinz Lepzien",
    "wof:placetype":"venue"
},
  "geometry": {"coordinates":[7.0664329529,51.3147621155],"type":"Point"}
}