{
  "type": "Feature",
  "properties": {
    "iso:country":"DE",
    "sg:address":"Lange Str. 91-97",
    "sg:city":"Bruchhausen-Vilsen",
    "sg:phone":"+49 4942/5293090",
    "sg:postcode":"27305",
    "sg:province":"Niedersachsen",
    "wof:name":"Klingeberg K\u00dcchenwelt",
    "wof:placetype":"venue"
},
  "geometry": {"coordinates":[8.9856996536,52.8220748901],"type":"Point"}
}