{
  "type": "Feature",
  "properties": {
    "iso:country":"DE",
    "sg:address":"Hansestr. 3",
    "sg:city":"Bielefeld",
    "sg:phone":"+49 5205/91010",
    "sg:postcode":"33689",
    "sg:province":"Nordrhein-Westfalen",
    "wof:name":"Werbedruck Reinhold Z\u00fcnkler",
    "wof:placetype":"venue"
},
  "geometry": {"coordinates":[8.5707092285,51.9505386353],"type":"Point"}
}