{
  "type": "Feature",
  "properties": {
    "iso:country":"DE",
    "sg:address":"Richtweg 55",
    "sg:city":"Weyhe",
    "sg:phone":"+49 4203/79079",
    "sg:postcode":"28844",
    "sg:province":"Niedersachsen",
    "wof:name":"Autohaus Brandt Beteiligungsgesellschaft Mbh",
    "wof:placetype":"venue"
},
  "geometry": {"coordinates":[8.852112,52.987316],"type":"Point"}
}