{
  "type": "Feature",
  "properties": {
    "iso:country":"DE",
    "sg:address":"Nordweg 1",
    "sg:city":"Dresden",
    "sg:phone":"+49 351/2618407",
    "sg:postcode":"01328",
    "sg:province":"Sachsen",
    "wof:name":"Inge Portsch",
    "wof:placetype":"venue"
},
  "geometry": {"coordinates":[13.896227,51.03405],"type":"Point"}
}