{
  "type": "Feature",
  "properties": {
    "iso:country":"DE",
    "sg:address":"Werner Str. 41",
    "sg:city":"Werne",
    "sg:phone":"+49 2389/3552",
    "sg:postcode":"59368",
    "sg:province":"Nordrhein-Westfalen",
    "wof:name":"G. Lodenstr\u00e4ter Gmbh",
    "wof:placetype":"venue"
},
  "geometry": {"coordinates":[7.634069,51.663761],"type":"Point"}
}