{
  "type": "Feature",
  "properties": {
    "iso:country":"DE",
    "sg:address":"Hauptstr. 97",
    "sg:city":"Remchingen",
    "sg:phone":"+49 7232/79624",
    "sg:postcode":"75196",
    "sg:province":"Baden-W\u00fcrttemberg",
    "wof:name":"Da Georgio",
    "wof:placetype":"venue"
},
  "geometry": {"coordinates":[8.5711622238,48.9516677856],"type":"Point"}
}