{
  "type": "Feature",
  "properties": {
    "iso:country":"DE",
    "sg:address":"Elisabethenstr. 1",
    "sg:city":"Wetzlar",
    "sg:phone":"+49 6441/32106",
    "sg:postcode":"35576",
    "sg:province":"Hessen",
    "wof:name":"Karlheinz Stumpf",
    "wof:placetype":"venue"
},
  "geometry": {"coordinates":[8.5037,50.572521],"type":"Point"}
}