{
  "type": "Feature",
  "properties": {
    "iso:country":"DE",
    "sg:address":"Gimpelsteig 4",
    "sg:city":"Berlin",
    "sg:phone":"+49 30/8014263",
    "sg:postcode":"14165",
    "sg:province":"Berlin",
    "wof:name":"Johannes W. Schneider Architekt",
    "wof:placetype":"venue"
},
  "geometry": {"coordinates":[13.255352,52.424446],"type":"Point"}
}