{
  "type": "Feature",
  "properties": {
    "iso:country":"DE",
    "sg:address":"Elbestr. 28",
    "sg:city":"M\u00fchldorf",
    "sg:phone":"+49 8631/36970",
    "sg:postcode":"84453",
    "sg:province":"Bayern",
    "wof:name":"Erich Weichselgartner Gmbh",
    "wof:placetype":"venue"
},
  "geometry": {"coordinates":[12.5430927277,48.2361946106],"type":"Point"}
}