{
  "type": "Feature",
  "properties": {
    "iso:country":"DE",
    "sg:address":"Auf Dem Elm 2",
    "sg:city":"Reichenhausen",
    "sg:phone":"+49 4935/473604",
    "sg:postcode":"98634",
    "sg:province":"Th\u00fcringen",
    "wof:name":"Agrargen. Spreetal Eg",
    "wof:placetype":"venue"
},
  "geometry": {"coordinates":[13.894288,52.081089],"type":"Point"}
}