{
  "type": "Feature",
  "properties": {
    "iso:country":"DE",
    "sg:address":"Oldenzaaler Str. 22",
    "sg:city":"Bad Bentheim",
    "sg:phone":"+49 5924/8586",
    "sg:postcode":"48455",
    "sg:province":"Niedersachsen",
    "wof:name":"Rainer Gr\u00e4ser",
    "wof:placetype":"venue"
},
  "geometry": {"coordinates":[7.088546,52.298317],"type":"Point"}
}