{
  "type": "Feature",
  "properties": {
    "iso:country":"DE",
    "sg:address":"L\u00fcnenweg 8",
    "sg:city":"Soest",
    "sg:phone":"+49 2921/63543",
    "sg:postcode":"59494",
    "sg:province":"Nordrhein-Westfalen",
    "wof:name":"H.-j. Kempa Fleischgro\u00dfhandel",
    "wof:placetype":"venue"
},
  "geometry": {"coordinates":[8.0966758728,51.5618400574],"type":"Point"}
}