{
  "type": "Feature",
  "properties": {
    "iso:country":"DE",
    "sg:address":"Stuttgarter Str. 30",
    "sg:city":"Freiberg",
    "sg:phone":"+49 7141/271300",
    "sg:postcode":"71691",
    "sg:province":"Baden-W\u00fcrttemberg",
    "wof:name":"W. & I. L\u00e4mmle Gmbh & Co. Kg",
    "wof:placetype":"venue"
},
  "geometry": {"coordinates":[9.190328598,48.9296417236],"type":"Point"}
}