{
  "type": "Feature",
  "properties": {
    "iso:country":"DE",
    "sg:address":"Kurf\u00fcrstendamm 183",
    "sg:city":"Berlin",
    "sg:postcode":"10707",
    "sg:province":"Berlin",
    "wof:name":"Kent Immobilienmanagement Gmbh",
    "wof:placetype":"venue"
},
  "geometry": {"coordinates":[13.313959,52.500538],"type":"Point"}
}