{
  "type": "Feature",
  "properties": {
    "iso:country":"DE",
    "sg:address":"Volkhartstr. 2",
    "sg:city":"Augsburg",
    "sg:phone":"+49 821/151414",
    "sg:postcode":"86152",
    "sg:province":"Bayern",
    "wof:name":"J. G. Klauckesche Stiftung",
    "wof:placetype":"venue"
},
  "geometry": {"coordinates":[10.8914928436,48.3705215454],"type":"Point"}
}