{
  "type": "Feature",
  "properties": {
    "iso:country":"DE",
    "sg:address":"Br\u00e4sigweg 11",
    "sg:city":"Hamburg",
    "sg:phone":"+49 40/6413123",
    "sg:postcode":"22177",
    "sg:province":"Hamburg",
    "wof:name":"Nicolas Burmeister Immobilien/vermittlungen E. K.",
    "wof:placetype":"venue"
},
  "geometry": {"coordinates":[10.076305,53.618008],"type":"Point"}
}