{
  "type": "Feature",
  "properties": {
    "iso:country":"DE",
    "sg:address":"Zu den Ueser Finien 1",
    "sg:city":"Achim",
    "sg:phone":"+49 4202/70123",
    "sg:postcode":"28832",
    "sg:province":"Niedersachsen",
    "wof:name":"Landhaus Jungborn Max Naumann Gmbh & Co. Kg",
    "wof:placetype":"venue"
},
  "geometry": {"coordinates":[9.0162696838,53.0110778809],"type":"Point"}
}