{
  "type": "Feature",
  "properties": {
    "iso:country":"DE",
    "sg:address":"Hauptstr. 37",
    "sg:city":"Merxheim",
    "sg:phone":"+49 6754/402",
    "sg:postcode":"55627",
    "sg:province":"Rheinland-Pfalz",
    "wof:name":"Otto Herrmann",
    "wof:placetype":"venue"
},
  "geometry": {"coordinates":[7.5595731735,49.7944793701],"type":"Point"}
}