{
  "type": "Feature",
  "properties": {
    "iso:country":"DE",
    "sg:address":"Wildhubenweg 40",
    "sg:city":"R\u00fcsselsheim",
    "sg:phone":"+49 6142/33270",
    "sg:postcode":"65428",
    "sg:province":"Hessen",
    "wof:name":"Thomas Hentze",
    "wof:placetype":"venue"
},
  "geometry": {"coordinates":[8.4511213303,49.9679985046],"type":"Point"}
}