{
  "type": "Feature",
  "properties": {
    "iso:country":"DE",
    "sg:address":"Stiftstr. 10",
    "sg:city":"Weinstadt",
    "sg:phone":"+49 7151/65197",
    "sg:postcode":"71384",
    "sg:province":"Baden-W\u00fcrttemberg",
    "wof:name":"Ratst\u00fcble Und Metzgerei H. Lenz",
    "wof:placetype":"venue"
},
  "geometry": {"coordinates":[9.3877496719,48.8060798645],"type":"Point"}
}