{
  "type": "Feature",
  "properties": {
    "iso:country":"DE",
    "sg:address":"Weinstr. 21",
    "sg:city":"Bad D\u00fcrkheim",
    "sg:phone":"+49 6322/2405",
    "sg:postcode":"67098",
    "sg:province":"Rheinland-Pfalz",
    "wof:name":"Lore Kitsch",
    "wof:placetype":"venue"
},
  "geometry": {"coordinates":[8.1774454117,49.4767494202],"type":"Point"}
}