{
  "type": "Feature",
  "properties": {
    "iso:country":"DE",
    "sg:address":"Gutenbergstr. 36",
    "sg:city":"Bischofsheim",
    "sg:phone":"+49 6144/1617",
    "sg:postcode":"65474",
    "sg:province":"Hessen",
    "wof:name":"G\u00fcnter Dornbach",
    "wof:placetype":"venue"
},
  "geometry": {"coordinates":[8.359685,49.98658],"type":"Point"}
}