{
  "type": "Feature",
  "properties": {
    "iso:country":"DE",
    "sg:address":"Hagener Str. 17",
    "sg:city":"Gevelsberg",
    "sg:phone":"+49 2332/81544",
    "sg:postcode":"58285",
    "sg:province":"Nordrhein-Westfalen",
    "wof:name":"City-video-markt",
    "wof:placetype":"venue"
},
  "geometry": {"coordinates":[7.3446340561,51.3211555481],"type":"Point"}
}