{
  "type": "Feature",
  "properties": {
    "iso:country":"DE",
    "sg:address":"Dorfplatz 10",
    "sg:city":"Linnich",
    "sg:phone":"+49 2462/8238",
    "sg:postcode":"52441",
    "sg:province":"Nordrhein-Westfalen",
    "wof:name":"Heinrich H\u00f6ppener",
    "wof:placetype":"venue"
},
  "geometry": {"coordinates":[6.246986,50.947311],"type":"Point"}
}