{
  "type": "Feature",
  "properties": {
    "iso:country":"DE",
    "sg:address":"Ovelg\u00fcnner Str. 1",
    "sg:city":"Eilsleben",
    "sg:phone":"+49 4939/409339",
    "sg:postcode":"39365",
    "sg:province":"Sachsen-Anhalt",
    "wof:name":"Agrargen. Allertal Eilsleben",
    "wof:placetype":"venue"
},
  "geometry": {"coordinates":[11.219827,52.149506],"type":"Point"}
}