{
  "type": "Feature",
  "properties": {
    "iso:country":"DE",
    "sg:address":"Am Seeblick 72",
    "sg:city":"D\u00fcsseldorf",
    "sg:phone":"+49 211/201583",
    "sg:postcode":"40627",
    "sg:province":"Nordrhein-Westfalen",
    "wof:name":"Anstriche W. Wolfram",
    "wof:placetype":"venue"
},
  "geometry": {"coordinates":[6.890131,51.20245],"type":"Point"}
}