{
  "type": "Feature",
  "properties": {
    "iso:country":"DE",
    "sg:address":"K\u00fchlwetterstr. 10 PF 170524",
    "sg:city":"D\u00fcsseldorf",
    "sg:phone":"+49 4921/1625324",
    "sg:postcode":"40239",
    "sg:province":"Nordrhein-Westfalen",
    "wof:name":"Ugafsa United German Arabian Finance Sa",
    "wof:placetype":"venue"
},
  "geometry": {"coordinates":[6.80484,51.24379],"type":"Point"}
}