{
  "type": "Feature",
  "properties": {
    "iso:country":"DE",
    "sg:address":"K\u00f6nigstr. 47",
    "sg:city":"Duisburg",
    "sg:phone":"+49 2066/2010",
    "sg:postcode":"47198",
    "sg:province":"Nordrhein-Westfalen",
    "wof:name":"J. H. Schmitz S\u00f6hne Gmbh & Co.",
    "wof:placetype":"venue"
},
  "geometry": {"coordinates":[6.7184,51.452721],"type":"Point"}
}