{
  "type": "Feature",
  "properties": {
    "iso:country":"DE",
    "sg:address":"Im Stauster 5",
    "sg:city":"H\u00fcnfeld",
    "sg:phone":"+49 4966/528016",
    "sg:postcode":"36088",
    "sg:province":"Hessen",
    "wof:name":"Stroh Diamantwerkzeuge Gmbh",
    "wof:placetype":"venue"
},
  "geometry": {"coordinates":[9.764176,50.688267],"type":"Point"}
}