{
  "type": "Feature",
  "properties": {
    "iso:country":"DE",
    "sg:address":"Lichtensteinstr. 2",
    "sg:city":"Aichtal",
    "sg:phone":"+49 7127/50001",
    "sg:postcode":"72631",
    "sg:province":"Baden-W\u00fcrttemberg",
    "wof:name":"Hans J\u00fcrgen Sydow",
    "wof:placetype":"venue"
},
  "geometry": {"coordinates":[9.261174202,48.6290740967],"type":"Point"}
}