{
  "type": "Feature",
  "properties": {
    "iso:country":"DE",
    "sg:address":"Ahrtalstr. 1 B",
    "sg:city":"Wachtberg",
    "sg:phone":"+49 228/348668",
    "sg:postcode":"53343",
    "sg:province":"Nordrhein-Westfalen",
    "wof:name":"Willi Esser Nachf. Inh. I. Wiedmann",
    "wof:placetype":"venue"
},
  "geometry": {"coordinates":[7.1351380348,50.6115684509],"type":"Point"}
}