{
  "type": "Feature",
  "properties": {
    "iso:country":"DE",
    "sg:address":"Kornbergstr. 36",
    "sg:city":"Stuttgart",
    "sg:phone":"+49 711/223360",
    "sg:postcode":"70176",
    "sg:province":"Baden-W\u00fcrttemberg",
    "wof:name":"Reichl Sassenscheidt Und Partner Freie Architekten",
    "wof:placetype":"venue"
},
  "geometry": {"coordinates":[9.16,48.78307],"type":"Point"}
}