{
  "type": "Feature",
  "properties": {
    "iso:country":"DE",
    "sg:address":"Elztalstr. 43",
    "sg:city":"Gering",
    "sg:phone":"+49 2654/7750",
    "sg:postcode":"56751",
    "sg:province":"Rheinland-Pfalz",
    "wof:name":"Magra Naturstein- Und Betonsteinwerk Gmbh",
    "wof:placetype":"venue"
},
  "geometry": {"coordinates":[7.261328,50.271423],"type":"Point"}
}