{
  "type": "Feature",
  "properties": {
    "iso:country":"DE",
    "sg:address":"Kalsing 24",
    "sg:city":"Roding",
    "sg:phone":"+49 9467/1469",
    "sg:postcode":"93426",
    "sg:province":"Bayern",
    "wof:name":"Gastst\u00e4tte Thomas Schuierer",
    "wof:placetype":"venue"
},
  "geometry": {"coordinates":[12.5416679382,49.1461143494],"type":"Point"}
}