{
  "type": "Feature",
  "properties": {
    "iso:country":"DE",
    "sg:address":"Kreuzauer Str. 16",
    "sg:city":"Kreuzau",
    "sg:phone":"+49 2421/51210",
    "sg:postcode":"52372",
    "sg:province":"Nordrhein-Westfalen",
    "wof:name":"Hubert Salentin",
    "wof:placetype":"venue"
},
  "geometry": {"coordinates":[6.528656,50.755676],"type":"Point"}
}