{
  "type": "Feature",
  "properties": {
    "iso:country":"DE",
    "sg:address":"Am Kurpark 2",
    "sg:city":"Bad Grund",
    "sg:phone":"+49 5327/1306",
    "sg:postcode":"37539",
    "sg:province":"Niedersachsen",
    "wof:name":"G\u00e4stehaus Martha",
    "wof:placetype":"venue"
},
  "geometry": {"coordinates":[10.243563652,51.8087043762],"type":"Point"}
}