{
  "type": "Feature",
  "properties": {
    "iso:country":"DE",
    "sg:address":"Neusalzaer Str. 19b",
    "sg:city":"Bautzen",
    "sg:postcode":"02625",
    "sg:province":"Sachsen",
    "wof:name":"Johannes Und H. Richter",
    "wof:placetype":"venue"
},
  "geometry": {"coordinates":[14.423932,51.172661],"type":"Point"}
}