{
  "type": "Feature",
  "properties": {
    "iso:country":"DE",
    "sg:address":"Vangerowstr. 33",
    "sg:city":"Heidelberg",
    "sg:phone":"+49 6221/585136",
    "sg:postcode":"69115",
    "sg:province":"Baden-W\u00fcrttemberg",
    "wof:name":"Gattfelder & Wissing",
    "wof:placetype":"venue"
},
  "geometry": {"coordinates":[8.675188,49.408714],"type":"Point"}
}