{
  "type": "Feature",
  "properties": {
    "iso:country":"DE",
    "sg:address":"Emmastr. 64 a",
    "sg:city":"Essen",
    "sg:phone":"+49 201/789282",
    "sg:postcode":"45130",
    "sg:province":"Nordrhein-Westfalen",
    "wof:name":"Otto-von-hertzberg",
    "wof:placetype":"venue"
},
  "geometry": {"coordinates":[7.0117440224,51.4344863892],"type":"Point"}
}