{
  "type": "Feature",
  "properties": {
    "iso:country":"DE",
    "sg:address":"Auf den Steinen 27",
    "sg:city":"Meerbusch",
    "sg:phone":"+49 2132/77232",
    "sg:postcode":"40667",
    "sg:province":"Nordrhein-Westfalen",
    "wof:name":"B Und K Ges. F. Chemie- Und Verfahrenstechn. Mbh",
    "wof:placetype":"venue"
},
  "geometry": {"coordinates":[6.689922,51.2481],"type":"Point"}
}