{
  "type": "Feature",
  "properties": {
    "iso:country":"DE",
    "sg:address":"Clausstr. 72",
    "sg:city":"Chemnitz",
    "sg:phone":"+49 371/5613033",
    "sg:postcode":"09126",
    "sg:province":"Sachsen",
    "wof:name":"Schulte Anwaltskanzlei",
    "wof:placetype":"venue"
},
  "geometry": {"coordinates":[12.9417409897,50.8244476318],"type":"Point"}
}