{
  "type": "Feature",
  "properties": {
    "iso:country":"DE",
    "sg:address":"Altst\u00e4dtischer Markt 2",
    "sg:city":"Brandenburg",
    "sg:phone":"+49 3381/521737",
    "sg:postcode":"14770",
    "sg:province":"Brandenburg",
    "wof:name":"D. Borowszak",
    "wof:placetype":"venue"
},
  "geometry": {"coordinates":[12.553371,52.414291],"type":"Point"}
}