{
  "type": "Feature",
  "properties": {
    "iso:country":"DE",
    "sg:address":"G\u00fcldenstr. 19",
    "sg:city":"Braunschweig",
    "sg:phone":"+49 531/45853",
    "sg:postcode":"38100",
    "sg:province":"Niedersachsen",
    "wof:name":"Birgit Clasen Praxis F\u00fcr Krankengymnastik",
    "wof:placetype":"venue"
},
  "geometry": {"coordinates":[10.514098,52.262199],"type":"Point"}
}