{
  "type": "Feature",
  "properties": {
    "iso:country":"DE",
    "sg:address":"Altenfeldener Str. 10",
    "sg:city":"Allersberg",
    "sg:phone":"+49 9176/7128",
    "sg:postcode":"90584",
    "sg:province":"Bayern",
    "wof:name":"Hans Wiegel Gmbh & Co. Kg",
    "wof:placetype":"venue"
},
  "geometry": {"coordinates":[11.229421,49.258087],"type":"Point"}
}