{
  "type": "Feature",
  "properties": {
    "iso:country":"DE",
    "sg:address":"Franziskastr. 63",
    "sg:city":"Essen",
    "sg:phone":"+49 201/792706",
    "sg:postcode":"45131",
    "sg:province":"Nordrhein-Westfalen",
    "wof:name":"Einrichtung & Dekoration Dietz",
    "wof:placetype":"venue"
},
  "geometry": {"coordinates":[7.010943,51.433453],"type":"Point"}
}