{
  "type": "Feature",
  "properties": {
    "iso:country":"DE",
    "sg:address":"Gollierstr. 23",
    "sg:city":"M\u00fcnchen",
    "sg:postcode":"80339",
    "sg:province":"Bayern",
    "wof:name":"Publish-industry Verlag Gmbh",
    "wof:placetype":"venue"
},
  "geometry": {"coordinates":[11.5431261063,48.1356658936],"type":"Point"}
}