{
  "type": "Feature",
  "properties": {
    "iso:country":"DE",
    "sg:address":"Feldstra\u00dfe 104",
    "sg:city":"W\u00fcnschendorf",
    "sg:phone":"+49 37367/2287",
    "sg:postcode":"09514",
    "sg:province":"Sachsen",
    "wof:name":"Discothek:c&m",
    "wof:placetype":"venue"
},
  "geometry": {"coordinates":[13.178647,50.742989],"type":"Point"}
}