{
  "type": "Feature",
  "properties": {
    "iso:country":"DE",
    "sg:address":"Sch\u00fctzenstr. 14",
    "sg:city":"Colditz",
    "sg:phone":"+49 34381/43317",
    "sg:postcode":"04680",
    "sg:province":"Sachsen",
    "wof:name":"Wohnungsgenossenschaft Colditz Eg",
    "wof:placetype":"venue"
},
  "geometry": {"coordinates":[12.807013,51.126324],"type":"Point"}
}