{
  "type": "Feature",
  "properties": {
    "iso:country":"DE",
    "sg:address":"Ettlinger Str. 15",
    "sg:city":"Keltern",
    "sg:phone":"+49 4972/367020",
    "sg:postcode":"75210",
    "sg:province":"Baden-W\u00fcrttemberg",
    "wof:name":"Volksbank Keltern Eg",
    "wof:placetype":"venue"
},
  "geometry": {"coordinates":[8.574255,48.901386],"type":"Point"}
}