{
  "type": "Feature",
  "properties": {
    "iso:country":"DE",
    "sg:address":"In der Brandstatt 5",
    "sg:city":"Kempten",
    "sg:phone":"+49 831/16869",
    "sg:postcode":"87435",
    "sg:province":"Bayern",
    "wof:name":"Peter K\u00f6nig",
    "wof:placetype":"venue"
},
  "geometry": {"coordinates":[10.3152122498,47.7270240784],"type":"Point"}
}