{
  "type": "Feature",
  "properties": {
    "iso:country":"DE",
    "sg:address":"Markneukirchner Str 2-4",
    "sg:city":"Adorf",
    "sg:phone":"+49 37423/7680",
    "sg:postcode":"08626",
    "sg:province":"Sachsen",
    "wof:name":"Naue Fasertechnik Gmbh & Co Kg",
    "wof:placetype":"venue"
},
  "geometry": {"coordinates":[12.219499588,50.3222084045],"type":"Point"}
}