{
  "type": "Feature",
  "properties": {
    "iso:country":"DE",
    "sg:address":"Scheidertalstr. 69",
    "sg:city":"Aarbergen",
    "sg:phone":"+49 6120/5066",
    "sg:postcode":"65326",
    "sg:province":"Hessen",
    "wof:name":"Ls Computer Products Vertriebs Gmbh",
    "wof:placetype":"venue"
},
  "geometry": {"coordinates":[8.0673036575,50.2447319031],"type":"Point"}
}