{
  "type": "Feature",
  "properties": {
    "iso:country":"DE",
    "sg:address":"Spindelgang 15",
    "sg:city":"Essen",
    "sg:phone":"+49 201/404831",
    "sg:postcode":"45239",
    "sg:province":"Nordrhein-Westfalen",
    "wof:name":"Frank Seibertz",
    "wof:placetype":"venue"
},
  "geometry": {"coordinates":[7.011049,51.396515],"type":"Point"}
}