{
  "type": "Feature",
  "properties": {
    "iso:country":"DE",
    "sg:address":"Op'n M\u00f6hlnrad 10",
    "sg:city":"Hamburg",
    "sg:phone":"+49 40/6071866",
    "sg:postcode":"22397",
    "sg:province":"Hamburg",
    "wof:name":"Peter Reher",
    "wof:placetype":"venue"
},
  "geometry": {"coordinates":[10.1269903183,53.7041702271],"type":"Point"}
}