{
  "type": "Feature",
  "properties": {
    "iso:country":"DE",
    "sg:address":"Br\u00fcnkendorf",
    "sg:city":"H\u00f6hbeck",
    "sg:phone":"+49 5846/365",
    "sg:postcode":"29478",
    "sg:province":"Niedersachsen",
    "wof:name":"Kaffeegarten Schwedenschanze",
    "wof:placetype":"venue"
},
  "geometry": {"coordinates":[11.4039611816,53.0694160461],"type":"Point"}
}