{
  "type": "Feature",
  "properties": {
    "iso:country":"DE",
    "sg:address":"Achter de Stadt 12",
    "sg:city":"Heek",
    "sg:phone":"+49 2568/662",
    "sg:postcode":"48619",
    "sg:province":"Nordrhein-Westfalen",
    "wof:name":"J. Lammers",
    "wof:placetype":"venue"
},
  "geometry": {"coordinates":[7.103596,52.135017],"type":"Point"}
}