{
  "type": "Feature",
  "properties": {
    "iso:country":"DE",
    "sg:address":"Marktstr. 3",
    "sg:city":"Kehl",
    "sg:phone":"+49 7851/93270",
    "sg:postcode":"77694",
    "sg:province":"Baden-W\u00fcrttemberg",
    "wof:name":"Isu Personal- Dienstleistungen Gmbh",
    "wof:placetype":"venue"
},
  "geometry": {"coordinates":[7.812504,48.574207],"type":"Point"}
}