{
  "type": "Feature",
  "properties": {
    "iso:country":"DE",
    "sg:address":"Am Steinberg 45",
    "sg:city":"Leverkusen",
    "sg:phone":"+49 214/95145",
    "sg:postcode":"51377",
    "sg:province":"Nordrhein-Westfalen",
    "wof:name":"D. Offermann",
    "wof:placetype":"venue"
},
  "geometry": {"coordinates":[7.073217,51.05637],"type":"Point"}
}