{
  "type": "Feature",
  "properties": {
    "iso:country":"DE",
    "sg:address":"Heubergstr. 51",
    "sg:city":"Waldachtal",
    "sg:phone":"+49 7486/375",
    "sg:postcode":"72178",
    "sg:province":"Baden-W\u00fcrttemberg",
    "wof:name":"Eugen Kreidler",
    "wof:placetype":"venue"
},
  "geometry": {"coordinates":[8.610959,48.483223],"type":"Point"}
}