{
  "type": "Feature",
  "properties": {
    "iso:country":"DE",
    "sg:address":"Marktstr. 32",
    "sg:city":"Niederkassel",
    "sg:phone":"+49 2208/6077",
    "sg:postcode":"53859",
    "sg:province":"Nordrhein-Westfalen",
    "wof:name":"Kuth Elektroinstallation",
    "wof:placetype":"venue"
},
  "geometry": {"coordinates":[7.054728,50.799068],"type":"Point"}
}