{
  "type": "Feature",
  "properties": {
    "iso:country":"DE",
    "sg:address":"Tillystr. 16c",
    "sg:city":"Augsburg",
    "sg:phone":"+49 821/883522",
    "sg:postcode":"86179",
    "sg:province":"Bayern",
    "wof:name":"Horst Geppert",
    "wof:placetype":"venue"
},
  "geometry": {"coordinates":[10.9017839432,48.3186531067],"type":"Point"}
}