{
  "type": "Feature",
  "properties": {
    "iso:country":"DE",
    "sg:address":"Falkensteiner Str. 1",
    "sg:city":"Frankfurt",
    "sg:phone":"+49 69/556963",
    "sg:postcode":"60322",
    "sg:province":"Hessen",
    "wof:name":"Zionistische Jugend In Deutschland E. V.",
    "wof:placetype":"venue"
},
  "geometry": {"coordinates":[8.6831769943,50.1284561157],"type":"Point"}
}