{
  "type": "Feature",
  "properties": {
    "iso:country":"DE",
    "sg:address":"Lange-Feld-Str. 77",
    "sg:city":"Seelze",
    "sg:phone":"+49 511/402355",
    "sg:postcode":"30926",
    "sg:province":"Niedersachsen",
    "wof:name":"Balkangrill",
    "wof:placetype":"venue"
},
  "geometry": {"coordinates":[9.6311855316,52.394493103],"type":"Point"}
}