{
  "type": "Feature",
  "properties": {
    "iso:country":"DE",
    "sg:address":"Kahlenbergweg 7",
    "sg:city":"Buchholz",
    "sg:postcode":"21244",
    "sg:province":"Niedersachsen",
    "wof:name":"A. M. F. Protect Security Services Kg",
    "wof:placetype":"venue"
},
  "geometry": {"coordinates":[9.789771,53.310371],"type":"Point"}
}