{
  "type": "Feature",
  "properties": {
    "iso:country":"DE",
    "sg:address":"Am Schierkamp 26",
    "sg:city":"Elze",
    "sg:postcode":"31008",
    "sg:province":"Niedersachsen",
    "wof:name":"Jakob Muckel",
    "wof:placetype":"venue"
},
  "geometry": {"coordinates":[9.738462,52.149715],"type":"Point"}
}