{
  "type": "Feature",
  "properties": {
    "iso:country":"DE",
    "sg:address":"Kellerberg 11",
    "sg:city":"Geringswalde",
    "sg:phone":"+49 37382/81733",
    "sg:postcode":"09326",
    "sg:province":"Sachsen",
    "wof:name":"Lufttechnische Anlagen Paul Glanz Geringswalde",
    "wof:placetype":"venue"
},
  "geometry": {"coordinates":[12.9038982391,51.0776977539],"type":"Point"}
}