{
  "type": "Feature",
  "properties": {
    "iso:country":"DE",
    "sg:address":"Lohstr. 7",
    "sg:city":"Marktredwitz",
    "sg:phone":"+49 9231/2810",
    "sg:postcode":"95615",
    "sg:province":"Bayern",
    "wof:name":"Verkehrswacht E. V. Herbert Sch\u00f6ffel",
    "wof:placetype":"venue"
},
  "geometry": {"coordinates":[12.1022167206,50.0229187012],"type":"Point"}
}