{
  "type": "Feature",
  "properties": {
    "iso:country":"DE",
    "sg:address":"Lupfenstr. 8",
    "sg:city":"Villingen-Schwenningen",
    "sg:phone":"+49 7720/6060",
    "sg:postcode":"78056",
    "sg:province":"Baden-W\u00fcrttemberg",
    "wof:name":"Helios Apparatebau M\u00fcller Gmbh & Co. Kg",
    "wof:placetype":"venue"
},
  "geometry": {"coordinates":[8.548964,48.059746],"type":"Point"}
}