{
  "type": "Feature",
  "properties": {
    "iso:country":"DE",
    "sg:address":"Waldweg 7a",
    "sg:city":"Ludwigslust",
    "sg:phone":"+49 3874/22317",
    "sg:postcode":"19288",
    "sg:province":"Mecklenburg-Vorpommern",
    "wof:name":"Werner Thei\u00df",
    "wof:placetype":"venue"
},
  "geometry": {"coordinates":[11.4988155365,53.3130264282],"type":"Point"}
}