{
  "type": "Feature",
  "properties": {
    "iso:country":"DE",
    "sg:address":"Anrather Str. 18",
    "sg:city":"Willich",
    "sg:phone":"+49 2154/429290",
    "sg:postcode":"47877",
    "sg:province":"Nordrhein-Westfalen",
    "wof:name":"Tauch-sport-reisecenter",
    "wof:placetype":"venue"
},
  "geometry": {"coordinates":[6.533963,51.26852],"type":"Point"}
}