{
  "type": "Feature",
  "properties": {
    "iso:country":"DE",
    "sg:address":"Maintalstr. 2",
    "sg:city":"Kolitzheim",
    "sg:phone":"+49 9381/4655",
    "sg:postcode":"97509",
    "sg:province":"Bayern",
    "wof:name":"Josef Egle Steinmetzbetrieb",
    "wof:placetype":"venue"
},
  "geometry": {"coordinates":[10.191283226,49.9031295776],"type":"Point"}
}