{
  "type": "Feature",
  "properties": {
    "iso:country":"DE",
    "sg:address":"Karlsbader Str. 25",
    "sg:city":"W\u00fclfrath",
    "sg:phone":"+49 2058/5199",
    "sg:postcode":"42489",
    "sg:province":"Nordrhein-Westfalen",
    "wof:name":"A. Kraemer Steuerberater",
    "wof:placetype":"venue"
},
  "geometry": {"coordinates":[7.0337538719,51.280254364],"type":"Point"}
}