{
  "type": "Feature",
  "properties": {
    "iso:country":"DE",
    "sg:address":"Maisborner Str. 7",
    "sg:city":"Lingerhahn",
    "sg:phone":"+49 6746/211",
    "sg:postcode":"56291",
    "sg:province":"Rheinland-Pfalz",
    "wof:name":"Stl Schneider Transporte Gmbh",
    "wof:placetype":"venue"
},
  "geometry": {"coordinates":[7.5672621727,50.0934944153],"type":"Point"}
}