{
  "type": "Feature",
  "properties": {
    "iso:country":"DE",
    "sg:address":"Tegernbacher Str. 6",
    "sg:city":"Pfaffenhofen",
    "sg:phone":"+49 8441/83866",
    "sg:postcode":"85276",
    "sg:province":"Bayern",
    "wof:name":"Martin Haller Gmbh",
    "wof:placetype":"venue"
},
  "geometry": {"coordinates":[11.470923,48.567928],"type":"Point"}
}