{
  "type": "Feature",
  "properties": {
    "iso:country":"DE",
    "sg:address":"Friesenstr. 10",
    "sg:city":"Hildesheim",
    "sg:phone":"+49 5121/38609",
    "sg:postcode":"31134",
    "sg:province":"Niedersachsen",
    "wof:name":"Maria Liska",
    "wof:placetype":"venue"
},
  "geometry": {"coordinates":[9.95342,52.150139],"type":"Point"}
}