{
  "type": "Feature",
  "properties": {
    "iso:country":"DE",
    "sg:address":"Schlo\u00dfstr. 22",
    "sg:city":"Wittlich",
    "sg:phone":"+49 6571/5656",
    "sg:postcode":"54516",
    "sg:province":"Rheinland-Pfalz",
    "wof:name":"G\u00fcnter Lombard",
    "wof:placetype":"venue"
},
  "geometry": {"coordinates":[6.891254,49.984066],"type":"Point"}
}