{
  "type": "Feature",
  "properties": {
    "iso:country":"DE",
    "sg:address":"Franz-Mehring-Str. 9",
    "sg:city":"Chemnitz",
    "sg:postcode":"09112",
    "sg:province":"Sachsen",
    "wof:name":"B & B Immobilien Gmbh",
    "wof:placetype":"venue"
},
  "geometry": {"coordinates":[12.8968057632,50.8327140808],"type":"Point"}
}