{
  "type": "Feature",
  "properties": {
    "iso:country":"DE",
    "sg:address":"Casinostr. 15",
    "sg:city":"Koblenz",
    "sg:phone":"+49 261/18156",
    "sg:postcode":"56068",
    "sg:province":"Rheinland-Pfalz",
    "wof:name":"City",
    "wof:placetype":"venue"
},
  "geometry": {"coordinates":[7.597503,50.35841],"type":"Point"}
}