{
  "type": "Feature",
  "properties": {
    "iso:country":"DE",
    "sg:address":"Grossbruch",
    "sg:city":"Burscheid",
    "sg:postcode":"51399",
    "sg:province":"Nordrhein-Westfalen",
    "wof:name":"Ilka-dessous",
    "wof:placetype":"venue"
},
  "geometry": {"coordinates":[7.155472,51.110683],"type":"Point"}
}