{
  "type": "Feature",
  "properties": {
    "iso:country":"DE",
    "sg:address":"Fasangartenstr. 138",
    "sg:city":"M\u00fcnchen",
    "sg:phone":"+49 89/6990550",
    "sg:postcode":"81549",
    "sg:province":"Bayern",
    "wof:name":"Bayern Tennis",
    "wof:placetype":"venue"
},
  "geometry": {"coordinates":[11.6035270691,48.0879440308],"type":"Point"}
}