{
  "type": "Feature",
  "properties": {
    "iso:country":"DE",
    "sg:address":"Spechtweg 5",
    "sg:city":"Ettlingen",
    "sg:phone":"+49 7243/2331",
    "sg:postcode":"76275",
    "sg:province":"Baden-W\u00fcrttemberg",
    "wof:name":"Imu Institut F\u00fcr Marktorientierte",
    "wof:placetype":"venue"
},
  "geometry": {"coordinates":[8.4261884689,48.9098243713],"type":"Point"}
}