{
  "type": "Feature",
  "properties": {
    "iso:country":"DE",
    "sg:address":"Hauptstr. 60",
    "sg:city":"Siegburg",
    "sg:phone":"+49 2241/381388",
    "sg:postcode":"53721",
    "sg:province":"Nordrhein-Westfalen",
    "wof:name":"I. Joannidis",
    "wof:placetype":"venue"
},
  "geometry": {"coordinates":[7.2488260269,50.8066444397],"type":"Point"}
}