{
  "type": "Feature",
  "properties": {
    "iso:country":"DE",
    "sg:address":"Am Feldtor 5",
    "sg:city":"Grevenbroich",
    "sg:phone":"+49 2181/3904",
    "sg:postcode":"41515",
    "sg:province":"Nordrhein-Westfalen",
    "wof:name":"A. K\u00f6geler",
    "wof:placetype":"venue"
},
  "geometry": {"coordinates":[6.6288781166,51.0651550293],"type":"Point"}
}