{
  "type": "Feature",
  "properties": {
    "iso:country":"DE",
    "sg:address":"Alte Manggasse 4",
    "sg:city":"Regensburg",
    "sg:phone":"+49 941/57675",
    "sg:postcode":"93047",
    "sg:province":"Bayern",
    "wof:name":"R. Faltermeier",
    "wof:placetype":"venue"
},
  "geometry": {"coordinates":[12.0941038132,49.016998291],"type":"Point"}
}