{
  "type": "Feature",
  "properties": {
    "iso:country":"DE",
    "sg:address":"An der Teufelshohle 1",
    "sg:city":"Eisenberg",
    "sg:phone":"+49 36691/43349",
    "sg:postcode":"07607",
    "sg:province":"Th\u00fcringen",
    "wof:name":"Volkland Malermeister Gmbh",
    "wof:placetype":"venue"
},
  "geometry": {"coordinates":[11.899552,50.978142],"type":"Point"}
}