{
  "type": "Feature",
  "properties": {
    "iso:country":"DE",
    "sg:address":"B\u00f6cklerstr. 12",
    "sg:city":"H\u00f6hr-Grenzhausen",
    "sg:phone":"+49 2624/2776",
    "sg:postcode":"56203",
    "sg:province":"Rheinland-Pfalz",
    "wof:name":"Otto Schneider Ingenieur",
    "wof:placetype":"venue"
},
  "geometry": {"coordinates":[7.6704540253,50.4285125732],"type":"Point"}
}