{
  "type": "Feature",
  "properties": {
    "iso:country":"DE",
    "sg:address":"Hoxel",
    "sg:city":"Morbach",
    "sg:phone":"+49 6533/5685",
    "sg:postcode":"54497",
    "sg:province":"Rheinland-Pfalz",
    "wof:name":"Pizzeria Don-camillo",
    "wof:placetype":"venue"
},
  "geometry": {"coordinates":[7.0506658554,49.8253974915],"type":"Point"}
}