{
  "type": "Feature",
  "properties": {
    "iso:country":"DE",
    "sg:address":"Spitalgasse 5",
    "sg:city":"W\u00fcrzburg",
    "sg:phone":"+49 931/42338",
    "sg:postcode":"97082",
    "sg:province":"Bayern",
    "wof:name":"Historischer Saal Der Fischerzunft",
    "wof:placetype":"venue"
},
  "geometry": {"coordinates":[9.92378,49.792587],"type":"Point"}
}