{
  "type": "Feature",
  "properties": {
    "iso:country":"DE",
    "sg:address":"Liebknechtstr 40",
    "sg:city":"Magdeburg",
    "sg:phone":"+49 391/7331474",
    "sg:postcode":"39108",
    "sg:province":"Sachsen-Anhalt",
    "wof:name":"Delikata Magdeburger Fleisch- Und Wurstwaren Gmbh",
    "wof:placetype":"venue"
},
  "geometry": {"coordinates":[11.610902,52.123817],"type":"Point"}
}