{
  "type": "Feature",
  "properties": {
    "iso:country":"DE",
    "sg:address":"Paul-Behmann-Str. 14",
    "sg:city":"Vechelde",
    "sg:phone":"+49 5302/5927",
    "sg:postcode":"38159",
    "sg:province":"Niedersachsen",
    "wof:name":"F. Gr\u00fcnhage",
    "wof:placetype":"venue"
},
  "geometry": {"coordinates":[10.3841905594,52.2675628662],"type":"Point"}
}