{
  "type": "Feature",
  "properties": {
    "iso:country":"DE",
    "sg:address":"Johanniterhof 8",
    "sg:city":"Bad Mergentheim",
    "sg:phone":"+49 7931/6556",
    "sg:postcode":"97980",
    "sg:province":"Baden-W\u00fcrttemberg",
    "wof:name":"Bistro Royal",
    "wof:placetype":"venue"
},
  "geometry": {"coordinates":[9.7744998932,49.4918899536],"type":"Point"}
}