{
  "type": "Feature",
  "properties": {
    "iso:country":"DE",
    "sg:address":"Tiestestr. 16-18",
    "sg:city":"Hannover",
    "sg:phone":"+49 511/848320",
    "sg:postcode":"30171",
    "sg:province":"Niedersachsen",
    "wof:name":"Dv Idee Beratungsges. Mbh",
    "wof:placetype":"venue"
},
  "geometry": {"coordinates":[9.7610054016,52.3647537231],"type":"Point"}
}