{
  "type": "Feature",
  "properties": {
    "iso:country":"DE",
    "sg:address":"J\u00e4gerstr. 2",
    "sg:city":"Herten",
    "sg:phone":"+49 2366/35631",
    "sg:postcode":"45699",
    "sg:province":"Nordrhein-Westfalen",
    "wof:name":"W. Brozio",
    "wof:placetype":"venue"
},
  "geometry": {"coordinates":[7.1507720947,51.5976371765],"type":"Point"}
}