{
  "type": "Feature",
  "properties": {
    "iso:country":"DE",
    "sg:address":"Schillerstr 26",
    "sg:city":"Gronau",
    "sg:phone":"+49 2565/2006",
    "sg:postcode":"48599",
    "sg:province":"Nordrhein-Westfalen",
    "wof:name":"Dieker-reinigungstechnik",
    "wof:placetype":"venue"
},
  "geometry": {"coordinates":[7.0358119011,52.18775177],"type":"Point"}
}