{
  "type": "Feature",
  "properties": {
    "iso:country":"DE",
    "sg:address":"Eibacher Schulstr. 45",
    "sg:city":"N\u00fcrnberg",
    "sg:phone":"+49 911/6493317",
    "sg:postcode":"90451",
    "sg:province":"Bayern",
    "wof:name":"Johann D\u00f6tterl Elektroinstallation",
    "wof:placetype":"venue"
},
  "geometry": {"coordinates":[11.041034,49.408894],"type":"Point"}
}