{
  "type": "Feature",
  "properties": {
    "iso:country":"DE",
    "sg:address":"Pirminiusstr.",
    "sg:city":"Blieskastel",
    "sg:phone":"+49 6842/2105",
    "sg:postcode":"66440",
    "sg:province":"Saarland",
    "wof:name":"J. Muth Glasgrosshandlung",
    "wof:placetype":"venue"
},
  "geometry": {"coordinates":[7.2560391426,49.2504653931],"type":"Point"}
}