{
  "type": "Feature",
  "properties": {
    "iso:country":"DE",
    "sg:address":"Bergerwiesenstr 9",
    "sg:city":"Meckenheim",
    "sg:phone":"+49 2225/17011",
    "sg:postcode":"53340",
    "sg:province":"Nordrhein-Westfalen",
    "wof:name":"Limbach-secur Sicherheitstechnik Gmbh",
    "wof:placetype":"venue"
},
  "geometry": {"coordinates":[7.019901,50.63829],"type":"Point"}
}