{
  "type": "Feature",
  "properties": {
    "iso:country":"DE",
    "sg:address":"Kranichstr. 11",
    "sg:city":"N\u00fcrnberg",
    "sg:phone":"+49 911/314982",
    "sg:postcode":"90427",
    "sg:province":"Bayern",
    "wof:name":"Moby Computers Inh. Klaus Seeliger",
    "wof:placetype":"venue"
},
  "geometry": {"coordinates":[11.0251960754,49.469291687],"type":"Point"}
}