{
  "type": "Feature",
  "properties": {
    "iso:country":"DE",
    "sg:address":"Altenburger Str. 14",
    "sg:city":"Schm\u00f6lln",
    "sg:phone":"+49 34491/26358",
    "sg:postcode":"04626",
    "sg:province":"Th\u00fcringen",
    "wof:name":"Dr. D. Nicolai",
    "wof:placetype":"venue"
},
  "geometry": {"coordinates":[12.35235,50.897148],"type":"Point"}
}