{
  "type": "Feature",
  "properties": {
    "iso:country":"DE",
    "sg:address":"Dunantstr. 16a",
    "sg:city":"Neuss",
    "sg:phone":"+49 2131/129093",
    "sg:postcode":"41468",
    "sg:province":"Nordrhein-Westfalen",
    "wof:name":"Microware International Marketing Gmbh",
    "wof:placetype":"venue"
},
  "geometry": {"coordinates":[6.7213468552,51.1858787537],"type":"Point"}
}