{
  "type": "Feature",
  "properties": {
    "iso:country":"DE",
    "sg:address":"Dr.-K\u00fclz-Str. 10",
    "sg:city":"Aue",
    "sg:phone":"+49 3771/553300",
    "sg:postcode":"08280",
    "sg:province":"Sachsen",
    "wof:name":"Dr. Lutz Lorenz Rechtsanwalt",
    "wof:placetype":"venue"
},
  "geometry": {"coordinates":[12.7013702393,50.5835189819],"type":"Point"}
}