{
  "type": "Feature",
  "properties": {
    "iso:country":"DE",
    "sg:address":"Langenscheidtstr. 7",
    "sg:city":"Berlin",
    "sg:phone":"+49 30/7844259",
    "sg:postcode":"10827",
    "sg:province":"Berlin",
    "wof:name":"Br\u00fccken-eck",
    "wof:placetype":"venue"
},
  "geometry": {"coordinates":[13.3624010086,52.4889907837],"type":"Point"}
}