{
  "type": "Feature",
  "properties": {
    "iso:country":"DE",
    "sg:address":"Silwai 1",
    "sg:city":"Sylt-Ost",
    "sg:phone":"+49 4651/82700",
    "sg:postcode":"25980",
    "sg:province":"Schleswig-Holstein",
    "wof:name":"K. Boysen Lebensmittel",
    "wof:placetype":"venue"
},
  "geometry": {"coordinates":[8.3151025772,54.9022598267],"type":"Point"}
}