{
  "type": "Feature",
  "properties": {
    "iso:country":"DE",
    "sg:address":"Neuer Weg 13",
    "sg:city":"Wolfenb\u00fcttel",
    "sg:postcode":"38302",
    "sg:province":"Niedersachsen",
    "wof:name":"Jacqueline Franke",
    "wof:placetype":"venue"
},
  "geometry": {"coordinates":[10.541302,52.170876],"type":"Point"}
}