{
  "type": "Feature",
  "properties": {
    "iso:country":"DE",
    "sg:address":"Bergstr. 20",
    "sg:city":"St\u00f6\u00dfen",
    "sg:phone":"+49 34445/20388",
    "sg:postcode":"06667",
    "sg:province":"Sachsen-Anhalt",
    "wof:name":"Manfred Erfurth",
    "wof:placetype":"venue"
},
  "geometry": {"coordinates":[11.925783,51.115887],"type":"Point"}
}