{
  "type": "Feature",
  "properties": {
    "iso:country":"DE",
    "sg:address":"Im Forchet 20",
    "sg:city":"Schongau",
    "sg:phone":"+49 8861/4703",
    "sg:postcode":"86956",
    "sg:province":"Bayern",
    "wof:name":"Helga Schmidtner",
    "wof:placetype":"venue"
},
  "geometry": {"coordinates":[10.8870429993,47.8051757812],"type":"Point"}
}