{
  "type": "Feature",
  "properties": {
    "iso:country":"DE",
    "sg:address":"Ganghoferstr. 9",
    "sg:city":"M\u00fcnchen",
    "sg:phone":"+49 89/501201",
    "sg:postcode":"80339",
    "sg:province":"Bayern",
    "wof:name":"Kurt Faltus",
    "wof:placetype":"venue"
},
  "geometry": {"coordinates":[11.5407066345,48.1368713379],"type":"Point"}
}