{
  "type": "Feature",
  "properties": {
    "iso:country":"DE",
    "sg:address":"Auf dem Bruche 52",
    "sg:city":"Kalletal",
    "sg:phone":"+49 5264/5324",
    "sg:postcode":"32689",
    "sg:province":"Nordrhein-Westfalen",
    "wof:name":"Wolfgang Dubbert Architekt",
    "wof:placetype":"venue"
},
  "geometry": {"coordinates":[8.94048,52.11887],"type":"Point"}
}