{
  "type": "Feature",
  "properties": {
    "iso:country":"DE",
    "sg:address":"Auwiesenweg 15",
    "sg:city":"Regen",
    "sg:phone":"+49 9921/904444",
    "sg:postcode":"94209",
    "sg:province":"Bayern",
    "wof:name":"F. Wildfeuer",
    "wof:placetype":"venue"
},
  "geometry": {"coordinates":[13.132508,48.97179],"type":"Point"}
}