{
  "type": "Feature",
  "properties": {
    "iso:country":"DE",
    "sg:address":"Josefstr. 2",
    "sg:city":"Drensteinfurt",
    "sg:phone":"+49 2508/9059",
    "sg:postcode":"48317",
    "sg:province":"Nordrhein-Westfalen",
    "wof:name":"Rosy Bregenhorn",
    "wof:placetype":"venue"
},
  "geometry": {"coordinates":[7.738053,51.797459],"type":"Point"}
}