{
  "type": "Feature",
  "properties": {
    "iso:country":"DE",
    "sg:address":"Vo\u00dfkuhle 39",
    "sg:city":"Dortmund",
    "sg:phone":"+49 231/104031",
    "sg:postcode":"44141",
    "sg:province":"Nordrhein-Westfalen",
    "wof:name":"Paul L\u00f6cher Ingenieur",
    "wof:placetype":"venue"
},
  "geometry": {"coordinates":[7.4945058823,51.5049667358],"type":"Point"}
}