{
  "type": "Feature",
  "properties": {
    "iso:country":"DE",
    "sg:address":"Josef-Kolb-Str. 5",
    "sg:city":"Eggolsheim",
    "sg:phone":"+49 9545/7740",
    "sg:postcode":"91330",
    "sg:province":"Bayern",
    "wof:name":"Pizzeria Minerva",
    "wof:placetype":"venue"
},
  "geometry": {"coordinates":[11.052989006,49.7727050781],"type":"Point"}
}