{
  "type": "Feature",
  "properties": {
    "iso:country":"DE",
    "sg:address":"Meesmannstr. 152",
    "sg:city":"Bochum",
    "sg:phone":"+49 234/533278",
    "sg:postcode":"44807",
    "sg:province":"Nordrhein-Westfalen",
    "wof:name":"Mdm Baugesellschaft Mbh",
    "wof:placetype":"venue"
},
  "geometry": {"coordinates":[7.198028,51.519825],"type":"Point"}
}