{
  "type": "Feature",
  "properties": {
    "iso:country":"DE",
    "sg:address":"Bergedorfer Str. 105",
    "sg:city":"Hamburg",
    "sg:phone":"+49 40/7244649",
    "sg:postcode":"21029",
    "sg:province":"Hamburg",
    "wof:name":"Ccb Spar",
    "wof:placetype":"venue"
},
  "geometry": {"coordinates":[10.2091264725,53.487991333],"type":"Point"}
}