{
  "type": "Feature",
  "properties": {
    "iso:country":"DE",
    "sg:address":"Kirschgarten 5",
    "sg:city":"Mainz",
    "sg:phone":"+49 6131/225326",
    "sg:postcode":"55116",
    "sg:province":"Rheinland-Pfalz",
    "wof:name":"G. Vlatten",
    "wof:placetype":"venue"
},
  "geometry": {"coordinates":[8.2725219727,49.9967193604],"type":"Point"}
}