{
  "type": "Feature",
  "properties": {
    "iso:country":"DE",
    "sg:address":"Keplerstr. 12-14",
    "sg:city":"Bietigheim-Bissingen",
    "sg:phone":"+49 7142/5970",
    "sg:postcode":"74321",
    "sg:province":"Baden-W\u00fcrttemberg",
    "wof:name":"Robert Scheuffele Gmbh & Co. Kg",
    "wof:placetype":"venue"
},
  "geometry": {"coordinates":[9.127382,48.94276],"type":"Point"}
}