{
  "type": "Feature",
  "properties": {
    "iso:country":"DE",
    "sg:address":"Obergasse 5",
    "sg:city":"Billigheim-Ingenheim",
    "sg:phone":"+49 6349/1723",
    "sg:postcode":"76831",
    "sg:province":"Rheinland-Pfalz",
    "wof:name":"Fritz M\u00fcller",
    "wof:placetype":"venue"
},
  "geometry": {"coordinates":[8.081229,49.134975],"type":"Point"}
}