{
  "type": "Feature",
  "properties": {
    "iso:country":"DE",
    "sg:address":"T\u00fcbinger Str. 81",
    "sg:city":"Stuttgart",
    "sg:phone":"+49 711/605830",
    "sg:postcode":"70178",
    "sg:province":"Baden-W\u00fcrttemberg",
    "wof:name":"E. Fundis Makler",
    "wof:placetype":"venue"
},
  "geometry": {"coordinates":[9.1703634262,48.7670898438],"type":"Point"}
}