{
  "type": "Feature",
  "properties": {
    "iso:country":"DE",
    "sg:address":"Dr.-Georg-Benjamin-Str. 5",
    "sg:city":"Schwerin",
    "sg:postcode":"19055",
    "sg:province":"Mecklenburg-Vorpommern",
    "wof:name":"Rudi Grohsmann",
    "wof:placetype":"venue"
},
  "geometry": {"coordinates":[11.409187,53.654007],"type":"Point"}
}