{
  "type": "Feature",
  "properties": {
    "iso:country":"DE",
    "sg:address":"Theodor-Storm-Str. 3",
    "sg:city":"Cottbus",
    "sg:phone":"+49 355/525354",
    "sg:postcode":"03050",
    "sg:province":"Brandenburg",
    "wof:name":"H. Niespor",
    "wof:placetype":"venue"
},
  "geometry": {"coordinates":[14.33163,51.726082],"type":"Point"}
}