{
  "type": "Feature",
  "properties": {
    "iso:country":"DE",
    "sg:address":"Bockenfelder Str. 6",
    "sg:city":"Dortmund",
    "sg:phone":"+49 231/672623",
    "sg:postcode":"44379",
    "sg:province":"Nordrhein-Westfalen",
    "wof:name":"Ursula Stork",
    "wof:placetype":"venue"
},
  "geometry": {"coordinates":[7.367324,51.521072],"type":"Point"}
}