{
  "type": "Feature",
  "properties": {
    "iso:country":"DE",
    "sg:address":"Finkenweg 1",
    "sg:city":"Seewald",
    "sg:phone":"+49 7447/94940",
    "sg:postcode":"72297",
    "sg:province":"Baden-W\u00fcrttemberg",
    "wof:name":"G. Belser Gmbh",
    "wof:placetype":"venue"
},
  "geometry": {"coordinates":[8.424747,48.594826],"type":"Point"}
}