{
  "type": "Feature",
  "properties": {
    "iso:country":"DE",
    "sg:address":"Schirrmannstr. 31",
    "sg:city":"Fulda",
    "sg:phone":"+49 661/73389",
    "sg:postcode":"36041",
    "sg:province":"Hessen",
    "wof:name":"Jugendherberge Fulda",
    "wof:placetype":"venue"
},
  "geometry": {"coordinates":[9.6614074707,50.5385284424],"type":"Point"}
}