{
  "type": "Feature",
  "properties": {
    "iso:country":"DE",
    "sg:address":"Bocholter Str. 41",
    "sg:city":"Hamminkeln",
    "sg:phone":"+49 2871/15808",
    "sg:postcode":"46499",
    "sg:province":"Nordrhein-Westfalen",
    "wof:name":"Landhaus Ridder Gmbh",
    "wof:placetype":"venue"
},
  "geometry": {"coordinates":[6.6093201637,51.7907180786],"type":"Point"}
}