{
  "type": "Feature",
  "properties": {
    "iso:country":"DE",
    "sg:address":"Neuendorfer Str. 21b",
    "sg:city":"Ueckerm\u00fcnde",
    "sg:phone":"+49 39771/27416",
    "sg:postcode":"17373",
    "sg:province":"Mecklenburg-Vorpommern",
    "wof:name":"Joachim Scheffler",
    "wof:placetype":"venue"
},
  "geometry": {"coordinates":[14.074907,53.743111],"type":"Point"}
}