{
  "type": "Feature",
  "properties": {
    "iso:country":"DE",
    "sg:address":"Bahnhofstr. 29",
    "sg:city":"Maxh\u00fctte-Haidhof",
    "sg:phone":"+49 9471/30320",
    "sg:postcode":"93142",
    "sg:province":"Bayern",
    "wof:name":"Werner Feicht",
    "wof:placetype":"venue"
},
  "geometry": {"coordinates":[12.101436615,49.1999282837],"type":"Point"}
}