{
  "type": "Feature",
  "properties": {
    "iso:country":"DE",
    "sg:address":"Altwiedenthaler H\u00f6he 4",
    "sg:city":"Hamburg",
    "sg:phone":"+49 40/7962664",
    "sg:postcode":"21149",
    "sg:province":"Hamburg",
    "wof:name":"Autohaus Schneider Verwaltungs-gmbh",
    "wof:placetype":"venue"
},
  "geometry": {"coordinates":[9.8887939453,53.4658088684],"type":"Point"}
}