{
  "type": "Feature",
  "properties": {
    "iso:country":"DE",
    "sg:address":"Sachsenring 1",
    "sg:city":"K\u00f6ln",
    "sg:phone":"+49 221/9318920",
    "sg:postcode":"50677",
    "sg:province":"Nordrhein-Westfalen",
    "wof:name":"Overstolz-apotheke Am Sachsenring",
    "wof:placetype":"venue"
},
  "geometry": {"coordinates":[6.956235,50.922092],"type":"Point"}
}