{
  "type": "Feature",
  "properties": {
    "iso:country":"DE",
    "sg:address":"Lannesdorfer Str. 11",
    "sg:city":"Bonn",
    "sg:phone":"+49 228/342572",
    "sg:postcode":"53179",
    "sg:province":"Nordrhein-Westfalen",
    "wof:name":"Karl-heinz Hilberath",
    "wof:placetype":"venue"
},
  "geometry": {"coordinates":[7.1718988419,50.6638717651],"type":"Point"}
}