{
  "type": "Feature",
  "properties": {
    "iso:country":"DE",
    "sg:address":"Hauptstr. 128",
    "sg:city":"Adenau",
    "sg:phone":"+49 2691/7784",
    "sg:postcode":"53518",
    "sg:province":"Rheinland-Pfalz",
    "wof:name":"M. B\u00f6der",
    "wof:placetype":"venue"
},
  "geometry": {"coordinates":[6.9324388504,50.381778717],"type":"Point"}
}