{
  "type": "Feature",
  "properties": {
    "iso:country":"DE",
    "sg:address":"Konrad-Adenauer-Allee 139",
    "sg:city":"Gladbeck",
    "sg:phone":"+49 2043/21169",
    "sg:postcode":"45964",
    "sg:province":"Nordrhein-Westfalen",
    "wof:name":"Karins Fu\u00dfpflegest\u00fcbchen K. Kramer-wollny",
    "wof:placetype":"venue"
},
  "geometry": {"coordinates":[6.996963,51.582275],"type":"Point"}
}