{
  "type": "Feature",
  "properties": {
    "iso:country":"DE",
    "sg:address":"Kirchsteig 63",
    "sg:city":"K\u00f6nigs Wusterhausen",
    "sg:phone":"+49 3375/293964",
    "sg:postcode":"15711",
    "sg:province":"Brandenburg",
    "wof:name":"H. Cybulski",
    "wof:placetype":"venue"
},
  "geometry": {"coordinates":[13.637224,52.296326],"type":"Point"}
}