{
  "type": "Feature",
  "properties": {
    "iso:country":"DE",
    "sg:address":"Hofaue 8a",
    "sg:city":"Wuppertal",
    "sg:phone":"+49 202/3096262",
    "sg:postcode":"42103",
    "sg:province":"Nordrhein-Westfalen",
    "wof:name":"Babatex",
    "wof:placetype":"venue"
},
  "geometry": {"coordinates":[7.15594,51.256783],"type":"Point"}
}