{
  "type": "Feature",
  "properties": {
    "iso:country":"DE",
    "sg:address":"Ringstr. 3",
    "sg:city":"Hochstadt",
    "sg:phone":"+49 9574/4305",
    "sg:postcode":"96272",
    "sg:province":"Bayern",
    "wof:name":"Beim Schlo\u00dfwirt",
    "wof:placetype":"venue"
},
  "geometry": {"coordinates":[11.1724700928,50.1500854492],"type":"Point"}
}