{
  "type": "Feature",
  "properties": {
    "iso:country":"DE",
    "sg:address":"Regensburger Str. 15",
    "sg:city":"Halle",
    "sg:phone":"+49 345/772830",
    "sg:postcode":"06132",
    "sg:province":"Sachsen-Anhalt",
    "wof:name":"J. & J. Bau- Und Bautr\u00e4ger Gmbh",
    "wof:placetype":"venue"
},
  "geometry": {"coordinates":[11.9913816452,51.4240570068],"type":"Point"}
}