{
  "type": "Feature",
  "properties": {
    "iso:country":"DE",
    "sg:address":"Breite Gasse 3",
    "sg:city":"Hann. M\u00fcnden",
    "sg:phone":"+49 5541/72696",
    "sg:postcode":"34346",
    "sg:province":"Niedersachsen",
    "wof:name":"Inge Sterzik",
    "wof:placetype":"venue"
},
  "geometry": {"coordinates":[9.6585130692,51.4191932678],"type":"Point"}
}