{
  "type": "Feature",
  "properties": {
    "iso:country":"DE",
    "sg:address":"Hartmannstr. 1",
    "sg:city":"Eilenburg",
    "sg:phone":"+49 3423/666370",
    "sg:postcode":"04838",
    "sg:province":"Sachsen",
    "wof:name":"Gsw Ltd",
    "wof:placetype":"venue"
},
  "geometry": {"coordinates":[12.6681365967,51.4653091431],"type":"Point"}
}