{
  "type": "Feature",
  "properties": {
    "iso:country":"DE",
    "sg:address":"In der Farnwiese 4a",
    "sg:city":"Niedernhausen",
    "sg:phone":"+49 6127/1526",
    "sg:postcode":"65527",
    "sg:province":"Hessen",
    "wof:name":"Neue Heimat S\u00fcdwest Gmbh",
    "wof:placetype":"venue"
},
  "geometry": {"coordinates":[8.308675766,50.1692352295],"type":"Point"}
}