{
  "type": "Feature",
  "properties": {
    "iso:country":"DE",
    "sg:address":"Obermarktstr. 2-4",
    "sg:city":"Minden",
    "sg:phone":"+49 571/21091",
    "sg:postcode":"32423",
    "sg:province":"Nordrhein-Westfalen",
    "wof:name":"Nw-mindener Kreiszeitung",
    "wof:placetype":"venue"
},
  "geometry": {"coordinates":[8.9161815643,52.2876853943],"type":"Point"}
}