{
  "type": "Feature",
  "properties": {
    "iso:country":"DE",
    "sg:address":"Scheffelstr. 5",
    "sg:city":"Wiesbaden",
    "sg:phone":"+49 611/841194",
    "sg:postcode":"65187",
    "sg:province":"Hessen",
    "wof:name":"Redaktion Badminton-report Ruppert Verlag",
    "wof:placetype":"venue"
},
  "geometry": {"coordinates":[8.2345457077,50.071434021],"type":"Point"}
}