{
  "type": "Feature",
  "properties": {
    "iso:country":"DE",
    "sg:address":"Fronstr. 14",
    "sg:city":"Karlsruhe",
    "sg:phone":"+49 721/891321",
    "sg:postcode":"76199",
    "sg:province":"Baden-W\u00fcrttemberg",
    "wof:name":"Helmut Paschmann Architekt",
    "wof:placetype":"venue"
},
  "geometry": {"coordinates":[8.406712,48.967915],"type":"Point"}
}