{
  "type": "Feature",
  "properties": {
    "iso:country":"DE",
    "sg:address":"Theodor-Her-Str. 11",
    "sg:city":"Rot",
    "sg:phone":"+49 8395/94000",
    "sg:postcode":"88430",
    "sg:province":"Baden-W\u00fcrttemberg",
    "wof:name":"Landhotel Seefelder",
    "wof:placetype":"venue"
},
  "geometry": {"coordinates":[10.034353,48.01358],"type":"Point"}
}