{
  "type": "Feature",
  "properties": {
    "iso:country":"DE",
    "sg:address":"Tullastr. 87",
    "sg:city":"Freiburg",
    "sg:postcode":"79108",
    "sg:province":"Baden-W\u00fcrttemberg",
    "wof:name":"Asap Endescopic Products Gmbh",
    "wof:placetype":"venue"
},
  "geometry": {"coordinates":[7.84382,48.031219],"type":"Point"}
}