{
  "type": "Feature",
  "properties": {
    "iso:country":"DE",
    "sg:address":"Moorkamp 55",
    "sg:city":"Celle",
    "sg:phone":"+49 5141/950541",
    "sg:postcode":"29223",
    "sg:province":"Niedersachsen",
    "wof:name":"Hotelrat Br\u00fchl E. K.",
    "wof:placetype":"venue"
},
  "geometry": {"coordinates":[10.0280361176,52.6435775757],"type":"Point"}
}