{
  "type": "Feature",
  "properties": {
    "iso:country":"DE",
    "sg:address":"Gustav-Adolf-Str. 9",
    "sg:city":"Plauen",
    "sg:phone":"+49 3741/226632",
    "sg:postcode":"08523",
    "sg:province":"Sachsen",
    "wof:name":"Wolfgang Sieber",
    "wof:placetype":"venue"
},
  "geometry": {"coordinates":[12.12934,50.496346],"type":"Point"}
}