{
  "type": "Feature",
  "properties": {
    "iso:country":"DE",
    "sg:address":"M\u00fchlenstieg 1",
    "sg:city":"Lamstedt",
    "sg:phone":"+49 4773/300",
    "sg:postcode":"21769",
    "sg:province":"Niedersachsen",
    "wof:name":"G. Stahlhuth",
    "wof:placetype":"venue"
},
  "geometry": {"coordinates":[9.100404,53.631744],"type":"Point"}
}