{
  "type": "Feature",
  "properties": {
    "iso:country":"DE",
    "sg:address":"Portastr. 56",
    "sg:city":"Porta Westfalica",
    "sg:phone":"+49 571/505160",
    "sg:postcode":"32457",
    "sg:province":"Nordrhein-Westfalen",
    "wof:name":"Dirk G\u00f6hner Allianz",
    "wof:placetype":"venue"
},
  "geometry": {"coordinates":[8.9090642929,52.2547645569],"type":"Point"}
}