{
  "type": "Feature",
  "properties": {
    "iso:country":"DE",
    "sg:address":"Schluchtstr. 22",
    "sg:city":"Wuppertal",
    "sg:phone":"+49 202/82476",
    "sg:postcode":"42285",
    "sg:province":"Nordrhein-Westfalen",
    "wof:name":"G\u00fcnter Mann Rechtsanwalt",
    "wof:placetype":"venue"
},
  "geometry": {"coordinates":[7.1816401482,51.2581367493],"type":"Point"}
}