{
  "type": "Feature",
  "properties": {
    "iso:country":"DE",
    "sg:address":"Gl\u00fccksburg 9",
    "sg:city":"Eschweiler",
    "sg:phone":"+49 2403/23329",
    "sg:postcode":"52249",
    "sg:province":"Nordrhein-Westfalen",
    "wof:name":"Gerhard P\u00fctz",
    "wof:placetype":"venue"
},
  "geometry": {"coordinates":[6.223947,50.821102],"type":"Point"}
}