{
  "type": "Feature",
  "properties": {
    "iso:country":"DE",
    "sg:address":"Mainzer Str. 43",
    "sg:city":"Ockenheim",
    "sg:phone":"+49 6725/2387",
    "sg:postcode":"55437",
    "sg:province":"Rheinland-Pfalz",
    "wof:name":"Karl Merz",
    "wof:placetype":"venue"
},
  "geometry": {"coordinates":[7.9724941254,49.9420204163],"type":"Point"}
}