{
  "type": "Feature",
  "properties": {
    "iso:country":"DE",
    "sg:address":"Fontanestr. 38",
    "sg:city":"Beckum",
    "sg:phone":"+49 2521/7616",
    "sg:postcode":"59269",
    "sg:province":"Nordrhein-Westfalen",
    "wof:name":"Kk Industrieberatung Und Werkvertretungs- Gmbh",
    "wof:placetype":"venue"
},
  "geometry": {"coordinates":[8.0225543976,51.7473068237],"type":"Point"}
}