{
  "type": "Feature",
  "properties": {
    "iso:country":"DE",
    "sg:address":"Nikolaus-D\u00fcrkopp-Str. 26",
    "sg:city":"Bielefeld",
    "sg:postcode":"33602",
    "sg:province":"Nordrhein-Westfalen",
    "wof:name":"Dev Consulting Ges. F\u00fcr Netz- Werkentwicklung Und",
    "wof:placetype":"venue"
},
  "geometry": {"coordinates":[8.5393362045,52.0195999146],"type":"Point"}
}