{
  "type": "Feature",
  "properties": {
    "iso:country":"DE",
    "sg:address":"Hauptstr. 33",
    "sg:city":"H\u00f6heischweiler",
    "sg:phone":"+49 6331/95453",
    "sg:postcode":"66989",
    "sg:province":"Rheinland-Pfalz",
    "wof:name":"Robert S\u00fcs",
    "wof:placetype":"venue"
},
  "geometry": {"coordinates":[7.5480861664,49.2300338745],"type":"Point"}
}