{
  "type": "Feature",
  "properties": {
    "iso:country":"DE",
    "sg:address":"Bahnhofplatz 5",
    "sg:city":"Wehr",
    "sg:phone":"+49 7762/9660",
    "sg:postcode":"79664",
    "sg:province":"Baden-W\u00fcrttemberg",
    "wof:name":"Klaus Fr\u00f6hle",
    "wof:placetype":"venue"
},
  "geometry": {"coordinates":[7.904721,47.624252],"type":"Point"}
}