{
  "type": "Feature",
  "properties": {
    "iso:country":"DE",
    "sg:address":"Rheinstr. 73",
    "sg:city":"Kestert",
    "sg:phone":"+49 6773/7173",
    "sg:postcode":"56348",
    "sg:province":"Rheinland-Pfalz",
    "wof:name":"Hermann Karbach Proviantboot",
    "wof:placetype":"venue"
},
  "geometry": {"coordinates":[7.647586,50.186565],"type":"Point"}
}