{
  "type": "Feature",
  "properties": {
    "iso:country":"DE",
    "sg:address":"Leimener Str. 13",
    "sg:city":"Ketsch",
    "sg:phone":"+49 6202/695050",
    "sg:postcode":"68775",
    "sg:province":"Baden-W\u00fcrttemberg",
    "wof:name":"Sb-tec Apparatetechnik Und Montage Gmbh",
    "wof:placetype":"venue"
},
  "geometry": {"coordinates":[8.5356550217,49.3705368042],"type":"Point"}
}