{
  "type": "Feature",
  "properties": {
    "iso:country":"DE",
    "sg:address":"Venusberg 6",
    "sg:city":"Hamburg",
    "sg:phone":"+49 40/367118",
    "sg:postcode":"20459",
    "sg:province":"Hamburg",
    "wof:name":"Elbschlo\u00dfquelle",
    "wof:placetype":"venue"
},
  "geometry": {"coordinates":[9.977637291,53.5470619202],"type":"Point"}
}