{
  "type": "Feature",
  "properties": {
    "iso:country":"DE",
    "sg:address":"Oberdorf 3",
    "sg:city":"Ottrau",
    "sg:phone":"+49 6639/797",
    "sg:postcode":"34633",
    "sg:province":"Hessen",
    "wof:name":"Heinz Bambey",
    "wof:placetype":"venue"
},
  "geometry": {"coordinates":[9.354086,50.811737],"type":"Point"}
}