{
  "type": "Feature",
  "properties": {
    "iso:country":"DE",
    "sg:address":"Burgweg 6",
    "sg:city":"Riegsee",
    "sg:phone":"+49 8841/628028",
    "sg:postcode":"82418",
    "sg:province":"Bayern",
    "wof:name":"San-domus Gmbh",
    "wof:placetype":"venue"
},
  "geometry": {"coordinates":[11.2325572968,47.6753463745],"type":"Point"}
}