{
  "type": "Feature",
  "properties": {
    "iso:country":"DE",
    "sg:address":"Am Rain 5",
    "sg:city":"Friedberg",
    "sg:postcode":"61169",
    "sg:province":"Hessen",
    "wof:name":"Regler Und H\u00f6hle Gmbh",
    "wof:placetype":"venue"
},
  "geometry": {"coordinates":[8.794793129,50.3222198486],"type":"Point"}
}