{
  "type": "Feature",
  "properties": {
    "iso:country":"DE",
    "sg:address":"Birkenstr. 37",
    "sg:city":"Bottrop",
    "sg:phone":"+49 2041/559961",
    "sg:postcode":"46242",
    "sg:province":"Nordrhein-Westfalen",
    "wof:name":"Frank Kraus",
    "wof:placetype":"venue"
},
  "geometry": {"coordinates":[6.8997688293,51.5220603943],"type":"Point"}
}