{
  "type": "Feature",
  "properties": {
    "iso:country":"DE",
    "sg:address":"Abt-Johannes-Str. 22",
    "sg:city":"Aalen",
    "sg:phone":"+49 7366/4658",
    "sg:postcode":"73434",
    "sg:province":"Baden-W\u00fcrttemberg",
    "wof:name":"Werner S\u00fcpple",
    "wof:placetype":"venue"
},
  "geometry": {"coordinates":[10.053449,48.879005],"type":"Point"}
}