{
  "type": "Feature",
  "properties": {
    "iso:country":"DE",
    "sg:address":"Tannenstr. 6",
    "sg:city":"Wesel",
    "sg:phone":"+49 281/51661",
    "sg:postcode":"46485",
    "sg:province":"Nordrhein-Westfalen",
    "wof:name":"Kosmetik Maier",
    "wof:placetype":"venue"
},
  "geometry": {"coordinates":[6.648258,51.673767],"type":"Point"}
}