{
  "type": "Feature",
  "properties": {
    "iso:country":"DE",
    "sg:address":"Bahnhofstr. 9",
    "sg:city":"Suhl",
    "sg:phone":"+49 3681/723429",
    "sg:postcode":"98527",
    "sg:province":"Th\u00fcringen",
    "wof:name":"Klett",
    "wof:placetype":"venue"
},
  "geometry": {"coordinates":[10.6881380081,50.6077041626],"type":"Point"}
}