{
  "type": "Feature",
  "properties": {
    "iso:country":"DE",
    "sg:address":"R\u00fcsterweg 14",
    "sg:city":"Karlsruhe",
    "sg:phone":"+49 721/865484",
    "sg:postcode":"76185",
    "sg:province":"Baden-W\u00fcrttemberg",
    "wof:name":"Michael Fleck",
    "wof:placetype":"venue"
},
  "geometry": {"coordinates":[8.3676595688,48.9950523376],"type":"Point"}
}