{
  "type": "Feature",
  "properties": {
    "iso:country":"DE",
    "sg:address":"Hambuch 1",
    "sg:city":"Marienheide",
    "sg:phone":"+49 2261/66754",
    "sg:postcode":"51709",
    "sg:province":"Nordrhein-Westfalen",
    "wof:name":"Karl E. Kampf",
    "wof:placetype":"venue"
},
  "geometry": {"coordinates":[7.526833,51.059837],"type":"Point"}
}