{
  "type": "Feature",
  "properties": {
    "iso:country":"DE",
    "sg:address":"Niewaldstr. 36",
    "sg:city":"Bielefeld",
    "sg:phone":"+49 521/392749",
    "sg:postcode":"33729",
    "sg:province":"Nordrhein-Westfalen",
    "wof:name":"Pr\u00fc\u00dfner Grundbesitz Kg",
    "wof:placetype":"venue"
},
  "geometry": {"coordinates":[8.64494,52.042122],"type":"Point"}
}