{
  "type": "Feature",
  "properties": {
    "iso:country":"DE",
    "sg:address":"Fliederweg 1",
    "sg:city":"Weingarten",
    "sg:phone":"+49 7244/8185",
    "sg:postcode":"76356",
    "sg:province":"Baden-W\u00fcrttemberg",
    "wof:name":"Jakob Vollweiter",
    "wof:placetype":"venue"
},
  "geometry": {"coordinates":[8.5281667709,49.0578918457],"type":"Point"}
}