{
  "type": "Feature",
  "properties": {
    "iso:country":"DE",
    "sg:address":"Moritzstr. 11",
    "sg:city":"Berlin",
    "sg:phone":"+49 30/61403982",
    "sg:postcode":"10969",
    "sg:province":"Berlin",
    "wof:name":"Luisenbau Gmbh",
    "wof:placetype":"venue"
},
  "geometry": {"coordinates":[13.4048080444,52.4997406006],"type":"Point"}
}