{
  "type": "Feature",
  "properties": {
    "iso:country":"DE",
    "sg:address":"Tullastr. 1",
    "sg:city":"Mannheim",
    "sg:phone":"+49 621/107000",
    "sg:postcode":"68161",
    "sg:province":"Baden-W\u00fcrttemberg",
    "wof:name":"Andreas Baum Rechtsanwalt",
    "wof:placetype":"venue"
},
  "geometry": {"coordinates":[8.4763689041,49.4864692688],"type":"Point"}
}