{
  "type": "Feature",
  "properties": {
    "iso:country":"DE",
    "sg:address":"Schooster Str. 12",
    "sg:city":"Schortens",
    "sg:phone":"+49 4461/8514",
    "sg:postcode":"26419",
    "sg:province":"Niedersachsen",
    "wof:name":"K\u00e4ser Finanzberater",
    "wof:placetype":"venue"
},
  "geometry": {"coordinates":[7.9418120384,53.5269355774],"type":"Point"}
}