{
  "type": "Feature",
  "properties": {
    "iso:country":"DE",
    "sg:address":"Leisberg 6/1",
    "sg:city":"Heidelberg",
    "sg:postcode":"69124",
    "sg:province":"Baden-W\u00fcrttemberg",
    "wof:name":"Ke\u00dfler Consulting Gmbh",
    "wof:placetype":"venue"
},
  "geometry": {"coordinates":[8.672750473,49.3812294006],"type":"Point"}
}