{
  "type": "Feature",
  "properties": {
    "iso:country":"DE",
    "sg:address":"Eschweg 3",
    "sg:city":"Versmold",
    "sg:phone":"+49 5423/94160",
    "sg:postcode":"33775",
    "sg:province":"Nordrhein-Westfalen",
    "wof:name":"Frob\u00f6se Gmbh",
    "wof:placetype":"venue"
},
  "geometry": {"coordinates":[8.15766716,52.0443458557],"type":"Point"}
}