{
  "type": "Feature",
  "properties": {
    "iso:country":"DE",
    "sg:address":"Schneidweg 2",
    "sg:city":"Baden-Baden",
    "sg:phone":"+49 7223/96680",
    "sg:postcode":"76534",
    "sg:province":"Baden-W\u00fcrttemberg",
    "wof:name":"Baden Chemie Gmbh",
    "wof:placetype":"venue"
},
  "geometry": {"coordinates":[8.148821,48.732368],"type":"Point"}
}