{
  "type": "Feature",
  "properties": {
    "iso:country":"DE",
    "sg:address":"Augsburger Str. 53",
    "sg:city":"Neu-Ulm",
    "sg:phone":"+49 731/722056",
    "sg:postcode":"89231",
    "sg:province":"Bayern",
    "wof:name":"Dr. Bernhard Maier Rechtsanwalt",
    "wof:placetype":"venue"
},
  "geometry": {"coordinates":[10.0056285858,48.3978996277],"type":"Point"}
}