{
  "type": "Feature",
  "properties": {
    "iso:country":"DE",
    "sg:address":"Mozartstr. 5",
    "sg:city":"Neuruppin",
    "sg:phone":"+49 3391/397148",
    "sg:postcode":"16816",
    "sg:province":"Brandenburg",
    "wof:name":"Dieter Benz",
    "wof:placetype":"venue"
},
  "geometry": {"coordinates":[12.8099851608,52.943813324],"type":"Point"}
}