{
  "type": "Feature",
  "properties": {
    "iso:country":"DE",
    "sg:address":"Marktplatz 4",
    "sg:city":"Haseldorf",
    "sg:phone":"+49 4129/241",
    "sg:postcode":"25489",
    "sg:province":"Schleswig-Holstein",
    "wof:name":"Ev. Pfarramt Haseldorf",
    "wof:placetype":"venue"
},
  "geometry": {"coordinates":[9.595916748,53.6340065002],"type":"Point"}
}