{
  "type": "Feature",
  "properties": {
    "iso:country":"DE",
    "sg:address":"Hauptstr. 35",
    "sg:city":"Eich",
    "sg:phone":"+49 6246/472",
    "sg:postcode":"67575",
    "sg:province":"Rheinland-Pfalz",
    "wof:name":"Dieter B\u00fcttel",
    "wof:placetype":"venue"
},
  "geometry": {"coordinates":[8.403032,49.74971],"type":"Point"}
}