{
  "type": "Feature",
  "properties": {
    "iso:country":"DE",
    "sg:address":"Br\u00e4uhausstr. 4b",
    "sg:city":"Planegg",
    "sg:postcode":"82152",
    "sg:province":"Bayern",
    "wof:name":"A. S. Ag Analyse Und Service Ag",
    "wof:placetype":"venue"
},
  "geometry": {"coordinates":[11.421526,48.102318],"type":"Point"}
}