{
  "type": "Feature",
  "properties": {
    "iso:country":"DE",
    "sg:address":"Wilhelm-Raabe-Str. 63",
    "sg:city":"Nordhorn",
    "sg:phone":"+49 5921/4789",
    "sg:postcode":"48527",
    "sg:province":"Niedersachsen",
    "wof:name":"K. Michel Ohg",
    "wof:placetype":"venue"
},
  "geometry": {"coordinates":[7.0567650795,52.4250793457],"type":"Point"}
}