{
  "type": "Feature",
  "properties": {
    "iso:country":"DE",
    "sg:address":"Kanalstr. 7",
    "sg:city":"Unterf\u00f6hring",
    "sg:phone":"+49 89/9500306",
    "sg:postcode":"85774",
    "sg:province":"Bayern",
    "wof:name":"Open Mind Software Gmbh",
    "wof:placetype":"venue"
},
  "geometry": {"coordinates":[11.6383180618,48.1921577454],"type":"Point"}
}