{
  "type": "Feature",
  "properties": {
    "iso:country":"DE",
    "sg:address":"Schanzenstr. 25",
    "sg:city":"D\u00fcsseldorf",
    "sg:phone":"+49 211/5581928",
    "sg:postcode":"40549",
    "sg:province":"Nordrhein-Westfalen",
    "wof:name":"Uwe Piller Steuerberater",
    "wof:placetype":"venue"
},
  "geometry": {"coordinates":[6.7431821823,51.2316970825],"type":"Point"}
}