{
  "type": "Feature",
  "properties": {
    "iso:country":"DE",
    "sg:address":"Schlo\u00dfstr. 34",
    "sg:city":"Harburg",
    "sg:postcode":"86655",
    "sg:province":"Bayern",
    "wof:name":"Dieter Riess",
    "wof:placetype":"venue"
},
  "geometry": {"coordinates":[10.6854810715,48.7856674194],"type":"Point"}
}