{
  "type": "Feature",
  "properties": {
    "iso:country":"DE",
    "sg:address":"Limbacher Str. 128",
    "sg:city":"Chemnitz",
    "sg:phone":"+49 4937/1373630",
    "sg:postcode":"09116",
    "sg:province":"Sachsen",
    "wof:name":"W\u00c4rmeanlagen Chemnitz Gmbh",
    "wof:placetype":"venue"
},
  "geometry": {"coordinates":[12.8886642456,50.8354682922],"type":"Point"}
}