{
  "type": "Feature",
  "properties": {
    "iso:country":"DE",
    "sg:address":"Sanitzer Str. 12",
    "sg:city":"Marlow",
    "sg:phone":"+49 38224/317",
    "sg:postcode":"18337",
    "sg:province":"Mecklenburg-Vorpommern",
    "wof:name":"A. Heine",
    "wof:placetype":"venue"
},
  "geometry": {"coordinates":[12.422852,54.150787],"type":"Point"}
}