{
  "type": "Feature",
  "properties": {
    "iso:country":"DE",
    "sg:address":"Friedenstr. 22",
    "sg:city":"Zirndorf",
    "sg:phone":"+49 911/606822",
    "sg:postcode":"90513",
    "sg:province":"Bayern",
    "wof:name":"O. U. M. Habicht",
    "wof:placetype":"venue"
},
  "geometry": {"coordinates":[10.946559906,49.4438362122],"type":"Point"}
}