{
  "type": "Feature",
  "properties": {
    "iso:country":"DE",
    "sg:address":"Obernfeldstr. 11",
    "sg:city":"Gehrden",
    "sg:phone":"+49 5108/3262",
    "sg:postcode":"30989",
    "sg:province":"Niedersachsen",
    "wof:name":"Heinrich Winterberg",
    "wof:placetype":"venue"
},
  "geometry": {"coordinates":[9.567035,52.299358],"type":"Point"}
}