{
  "type": "Feature",
  "properties": {
    "iso:country":"DE",
    "sg:city":"Sonnen",
    "sg:phone":"+49 9954/842",
    "sg:postcode":"94164",
    "sg:province":"Bayern",
    "wof:name":"Sparkasse Passau",
    "wof:placetype":"venue"
},
  "geometry": {"coordinates":[13.724425,48.685307],"type":"Point"}
}