{
  "type": "Feature",
  "properties": {
    "iso:country":"DE",
    "sg:address":"Am Stadtweg 5",
    "sg:city":"Hohendodeleben",
    "sg:phone":"+49 39204/62031",
    "sg:postcode":"39167",
    "sg:province":"Sachsen-Anhalt",
    "wof:name":"Ernst Wagner Gbr Inh. Edgar Wagner & Sohn",
    "wof:placetype":"venue"
},
  "geometry": {"coordinates":[11.518941,52.105408],"type":"Point"}
}