{
  "type": "Feature",
  "properties": {
    "iso:country":"DE",
    "sg:address":"Berliner Str. 79",
    "sg:city":"G\u00fctersloh",
    "sg:phone":"+49 5241/13722",
    "sg:postcode":"33330",
    "sg:province":"Nordrhein-Westfalen",
    "wof:name":"Dieter Droigk",
    "wof:placetype":"venue"
},
  "geometry": {"coordinates":[8.3807144165,51.9092521667],"type":"Point"}
}