{
  "type": "Feature",
  "properties": {
    "iso:country":"DE",
    "sg:address":"Molkereistr. 10",
    "sg:city":"Regen",
    "sg:phone":"+49 9921/1842",
    "sg:postcode":"94209",
    "sg:province":"Bayern",
    "wof:name":"Peter Metzger Fliesen-handels Gmbh",
    "wof:placetype":"venue"
},
  "geometry": {"coordinates":[13.135102272,48.9666213989],"type":"Point"}
}