{
  "type": "Feature",
  "properties": {
    "iso:country":"DE",
    "sg:address":"Andreas Fendt Ring 5",
    "sg:city":"Bischofswiesen",
    "sg:phone":"+49 8652/985654",
    "sg:postcode":"83471",
    "sg:province":"Bayern",
    "wof:name":"Fliegen So G\u00fcnstig Wie Noch Nie!",
    "wof:placetype":"venue"
},
  "geometry": {"coordinates":[12.967043,47.646545],"type":"Point"}
}