{
  "type": "Feature",
  "properties": {
    "iso:country":"DE",
    "sg:address":"An der Niederm\u00fchle 4",
    "sg:city":"Dresden",
    "sg:phone":"+49 351/2816691",
    "sg:postcode":"01257",
    "sg:province":"Sachsen",
    "wof:name":"Susa S. Sauer Ohg Automatendreherei",
    "wof:placetype":"venue"
},
  "geometry": {"coordinates":[13.810202,50.991989],"type":"Point"}
}