{
  "type": "Feature",
  "properties": {
    "iso:country":"DE",
    "sg:address":"Postfach 1580",
    "sg:city":"Marl",
    "sg:phone":"+49 2365/14002",
    "sg:postcode":"45745",
    "sg:province":"Niedersachsen",
    "wof:name":"Zentralbibliothek Insel Im Marler Stern",
    "wof:placetype":"venue"
},
  "geometry": {"coordinates":[7.08846,51.651749],"type":"Point"}
}