{
  "type": "Feature",
  "properties": {
    "iso:country":"DE",
    "sg:address":"Hauptstr. 15",
    "sg:city":"Mulda",
    "sg:phone":"+49 37320/1467",
    "sg:postcode":"09619",
    "sg:province":"Sachsen",
    "wof:name":"H. M\u00fcller",
    "wof:placetype":"venue"
},
  "geometry": {"coordinates":[13.39109,50.791023],"type":"Point"}
}