{
  "type": "Feature",
  "properties": {
    "iso:country":"DE",
    "sg:address":"Im Teufenbach",
    "sg:city":"Walporzheim/Ahr",
    "sg:phone":"+49 2641",
    "sg:postcode":"53747",
    "wof:name":"Weingut F\u00f6rsterhof",
    "wof:placetype":"venue"
},
  "geometry": {"coordinates":[13.4914102554,48.4039306641],"type":"Point"}
}