{
  "type": "Feature",
  "properties": {
    "iso:country":"DE",
    "sg:address":"Erich-Klausener-Str. 7",
    "sg:city":"Krefeld",
    "sg:phone":"+49 2151/563098",
    "sg:postcode":"47802",
    "sg:province":"Nordrhein-Westfalen",
    "wof:name":"M. Schulz",
    "wof:placetype":"venue"
},
  "geometry": {"coordinates":[6.6008000374,51.377281189],"type":"Point"}
}