{
  "type": "Feature",
  "properties": {
    "iso:country":"DE",
    "sg:address":"Bachstr. 8",
    "sg:city":"Ransbach-Baumbach",
    "sg:phone":"+49 2623/2107",
    "sg:postcode":"56235",
    "sg:province":"Rheinland-Pfalz",
    "wof:name":"Wolfgang Quetlich Ofensetzerei",
    "wof:placetype":"venue"
},
  "geometry": {"coordinates":[7.7294411659,50.4668197632],"type":"Point"}
}