{
  "type": "Feature",
  "properties": {
    "iso:country":"DE",
    "sg:address":"Kuhlfeldweg 15a",
    "sg:city":"Lohmar",
    "sg:phone":"+49 2206/1611",
    "sg:postcode":"53797",
    "sg:province":"Nordrhein-Westfalen",
    "wof:name":"J\u00f6rg Schiffbauer",
    "wof:placetype":"venue"
},
  "geometry": {"coordinates":[7.2511758804,50.8938331604],"type":"Point"}
}