{
  "type": "Feature",
  "properties": {
    "iso:country":"DE",
    "sg:address":"Einemhofer Weg 20",
    "sg:city":"Reppenstedt",
    "sg:phone":"+49 4131/63891",
    "sg:postcode":"21391",
    "sg:province":"Niedersachsen",
    "wof:name":"Heinz Koch",
    "wof:placetype":"venue"
},
  "geometry": {"coordinates":[10.3447084427,53.2523078918],"type":"Point"}
}