{
  "type": "Feature",
  "properties": {
    "iso:country":"DE",
    "sg:address":"Clemensstr. 3",
    "sg:city":"Waldfeucht",
    "sg:phone":"+49 2452/3142",
    "sg:postcode":"52525",
    "sg:province":"Nordrhein-Westfalen",
    "wof:name":"Malerbetrieb Von Tongelen Gmbh",
    "wof:placetype":"venue"
},
  "geometry": {"coordinates":[6.036572,51.051502],"type":"Point"}
}