{
  "type": "Feature",
  "properties": {
    "iso:country":"DE",
    "sg:address":"Walpersdorfer Str 2d",
    "sg:city":"Rednitzhembach",
    "sg:phone":"+49 9122/62268",
    "sg:postcode":"91126",
    "sg:province":"Bayern",
    "wof:name":"Creative-print Agentur Frech",
    "wof:placetype":"venue"
},
  "geometry": {"coordinates":[11.05604,49.297581],"type":"Point"}
}