{
  "type": "Feature",
  "properties": {
    "iso:country":"DE",
    "sg:address":"Freie Flur 4",
    "sg:city":"Geithain",
    "sg:phone":"+49 34341/3060",
    "sg:postcode":"04643",
    "sg:province":"Sachsen",
    "wof:name":"E. U. V. Ladenburger Gbr",
    "wof:placetype":"venue"
},
  "geometry": {"coordinates":[12.683664,51.067474],"type":"Point"}
}