{
  "type": "Feature",
  "properties": {
    "iso:country":"DE",
    "sg:address":"Thomas-Mann-Str. 6",
    "sg:city":"Cottbus",
    "sg:phone":"+49 355/872471",
    "sg:postcode":"03044",
    "sg:province":"Brandenburg",
    "wof:name":"Manfred Materne Architekt",
    "wof:placetype":"venue"
},
  "geometry": {"coordinates":[14.331877,51.78138],"type":"Point"}
}