{
  "type": "Feature",
  "properties": {
    "iso:country":"DE",
    "sg:address":"Fritz-Erler-Str. 5",
    "sg:city":"Heiligenhaus",
    "sg:phone":"+49 2056/6188",
    "sg:postcode":"42579",
    "sg:province":"Nordrhein-Westfalen",
    "wof:name":"Heisen",
    "wof:placetype":"venue"
},
  "geometry": {"coordinates":[6.9881877899,51.3241767883],"type":"Point"}
}