{
  "type": "Feature",
  "properties": {
    "iso:country":"DE",
    "sg:address":"Freiherr-vom-Stein-Str. 7",
    "sg:city":"Egelsbach",
    "sg:phone":"+49 6103/947934",
    "sg:postcode":"63329",
    "sg:province":"Hessen",
    "wof:name":"Schwimmbad",
    "wof:placetype":"venue"
},
  "geometry": {"coordinates":[8.6674032211,49.9655265808],"type":"Point"}
}