{
  "type": "Feature",
  "properties": {
    "iso:country":"DE",
    "sg:address":"Trierer Str. 46",
    "sg:city":"Hermeskeil",
    "sg:phone":"+49 6503/95156",
    "sg:postcode":"54411",
    "sg:province":"Rheinland-Pfalz",
    "wof:name":"Istanbul Kebap",
    "wof:placetype":"venue"
},
  "geometry": {"coordinates":[6.9445590973,49.6561431885],"type":"Point"}
}