{
  "type": "Feature",
  "properties": {
    "iso:country":"DE",
    "sg:address":"Stra\u00dfe des Friedens 29",
    "sg:city":"Wei\u00dfwasser",
    "sg:phone":"+49 3576/223242",
    "sg:postcode":"02943",
    "sg:province":"Sachsen",
    "wof:name":"Pizzamerica-restaurant- Betriebs Gmbh",
    "wof:placetype":"venue"
},
  "geometry": {"coordinates":[14.6426963806,51.508140564],"type":"Point"}
}