{
  "type": "Feature",
  "properties": {
    "iso:country":"DE",
    "sg:address":"Windthorststr. 42",
    "sg:city":"Meppen",
    "sg:phone":"+49 5931/2530",
    "sg:postcode":"49716",
    "sg:province":"Niedersachsen",
    "wof:name":"Heinrich Reiners",
    "wof:placetype":"venue"
},
  "geometry": {"coordinates":[7.309818,52.699539],"type":"Point"}
}