{
  "type": "Feature",
  "properties": {
    "iso:country":"DE",
    "sg:address":"Wievenesch 4",
    "sg:city":"Melle",
    "sg:phone":"+49 5422/2795",
    "sg:postcode":"49324",
    "sg:province":"Niedersachsen",
    "wof:name":"Martha Hollmann",
    "wof:placetype":"venue"
},
  "geometry": {"coordinates":[8.335662,52.18578],"type":"Point"}
}