{
  "type": "Feature",
  "properties": {
    "iso:country":"DE",
    "sg:address":"Akazienstr. 27",
    "sg:city":"Berlin",
    "sg:phone":"+49 30/7881177",
    "sg:postcode":"10823",
    "sg:province":"Berlin",
    "wof:name":"Astrodata In Berlin Gmbh",
    "wof:placetype":"venue"
},
  "geometry": {"coordinates":[13.3550252914,52.4868812561],"type":"Point"}
}