{
  "type": "Feature",
  "properties": {
    "iso:country":"DE",
    "sg:city":"J\u00fcbek",
    "sg:phone":"+49 4625/276",
    "sg:postcode":"24855",
    "sg:province":"Schleswig-Holstein",
    "wof:name":"Karl-heinz Jansen Cafe",
    "wof:placetype":"venue"
},
  "geometry": {"coordinates":[9.39761,54.556885],"type":"Point"}
}