{
  "type": "Feature",
  "properties": {
    "iso:country":"DE",
    "sg:address":"Zillenbachstr. 22",
    "sg:city":"Hindelang",
    "sg:phone":"+49 8324/2260",
    "sg:postcode":"87541",
    "sg:province":"Bayern",
    "wof:name":"Josef Wittwer",
    "wof:placetype":"venue"
},
  "geometry": {"coordinates":[10.362679,47.505756],"type":"Point"}
}