{
  "type": "Feature",
  "properties": {
    "iso:country":"DE",
    "sg:address":"Bruno-Apitz-Str. 1",
    "sg:city":"Berlin",
    "sg:phone":"+49 30/9416298",
    "sg:postcode":"13125",
    "sg:province":"Berlin",
    "wof:name":"Lutz G\u00f6rne",
    "wof:placetype":"venue"
},
  "geometry": {"coordinates":[13.492796,52.628368],"type":"Point"}
}