{
  "type": "Feature",
  "properties": {
    "iso:country":"DE",
    "sg:address":"Hangenau 39",
    "sg:city":"D\u00fclmen",
    "sg:phone":"+49 2590/215",
    "sg:postcode":"48249",
    "sg:province":"Nordrhein-Westfalen",
    "wof:name":"Jose Gro\u00dfe-brintrup",
    "wof:placetype":"venue"
},
  "geometry": {"coordinates":[7.4122390747,51.881565094],"type":"Point"}
}