{
  "type": "Feature",
  "properties": {
    "iso:country":"DE",
    "sg:address":"Friedrichstr. 11",
    "sg:city":"Pfinztal",
    "sg:phone":"+49 721/460095",
    "sg:postcode":"76327",
    "sg:province":"Baden-W\u00fcrttemberg",
    "wof:name":"Emil Becker",
    "wof:placetype":"venue"
},
  "geometry": {"coordinates":[8.5260372162,49.004901886],"type":"Point"}
}