{
  "type": "Feature",
  "properties": {
    "iso:country":"DE",
    "sg:address":"Elisabethstr. 83",
    "sg:city":"M\u00fcnchen",
    "sg:phone":"+49 89/182175",
    "sg:postcode":"80797",
    "sg:province":"Bayern",
    "wof:name":"J. K\u00f6stle",
    "wof:placetype":"venue"
},
  "geometry": {"coordinates":[11.559299,48.160606],"type":"Point"}
}