{
  "type": "Feature",
  "properties": {
    "iso:country":"DE",
    "sg:address":"Langendorfer Str. 139",
    "sg:city":"Neuwied",
    "sg:phone":"+49 2631/23318",
    "sg:postcode":"56564",
    "sg:province":"Rheinland-Pfalz",
    "wof:name":"J\u00fcrgen Flohr Gardinen Raumgestaltung",
    "wof:placetype":"venue"
},
  "geometry": {"coordinates":[7.4609937668,50.4277687073],"type":"Point"}
}