{
  "type": "Feature",
  "properties": {
    "iso:country":"DE",
    "sg:address":"Nordh\u00e4user Str. 22",
    "sg:city":"Ellrich",
    "sg:phone":"+49 36332/21866",
    "sg:postcode":"99755",
    "sg:province":"Th\u00fcringen",
    "wof:name":"Pflegedienst In Ellrich Ambulante Kranken- Und",
    "wof:placetype":"venue"
},
  "geometry": {"coordinates":[10.665431,51.585148],"type":"Point"}
}