{
  "type": "Feature",
  "properties": {
    "iso:country":"DE",
    "sg:address":"Schutterw\u00e4lder Str. 4",
    "sg:city":"Offenburg",
    "sg:phone":"+49 781/54293",
    "sg:postcode":"77656",
    "sg:province":"Baden-W\u00fcrttemberg",
    "wof:name":"C. Kirsch",
    "wof:placetype":"venue"
},
  "geometry": {"coordinates":[7.9304161072,48.4637374878],"type":"Point"}
}