{
  "type": "Feature",
  "properties": {
    "iso:country":"DE",
    "sg:address":"Egestorfer Str. 101",
    "sg:city":"Barsinghausen",
    "sg:phone":"+49 5105/2351",
    "sg:postcode":"30890",
    "sg:province":"Niedersachsen",
    "wof:name":"Karl Meissner",
    "wof:placetype":"venue"
},
  "geometry": {"coordinates":[9.482031,52.293869],"type":"Point"}
}