{
  "type": "Feature",
  "properties": {
    "iso:country":"DE",
    "sg:address":"Vorbergstr. 2",
    "sg:city":"Wallmoden",
    "sg:phone":"+49 5341/338066",
    "sg:postcode":"38729",
    "sg:province":"Niedersachsen",
    "wof:name":"Richter Getr\u00e4nkevertrieb",
    "wof:placetype":"venue"
},
  "geometry": {"coordinates":[10.301045,52.019802],"type":"Point"}
}