{
  "type": "Feature",
  "properties": {
    "iso:country":"DE",
    "sg:address":"Hildesheimer Stieg 13",
    "sg:city":"Hamburg",
    "sg:phone":"+49 40/5516228",
    "sg:postcode":"22459",
    "sg:province":"Hamburg",
    "wof:name":"Albert St\u00fcben Tiefbau",
    "wof:placetype":"venue"
},
  "geometry": {"coordinates":[9.947328,53.630714],"type":"Point"}
}