{
  "type": "Feature",
  "properties": {
    "iso:country":"DE",
    "sg:address":"Beusingser Str. 1",
    "sg:city":"Bad Sassendorf",
    "sg:phone":"+49 2927/235",
    "sg:postcode":"59505",
    "sg:province":"Nordrhein-Westfalen",
    "wof:name":"A.p. Kleintransporte Gmbh",
    "wof:placetype":"venue"
},
  "geometry": {"coordinates":[8.2020673752,51.5493736267],"type":"Point"}
}