{
  "type": "Feature",
  "properties": {
    "iso:country":"DE",
    "sg:address":"Asbacher Str. 50 POSTFACH 31",
    "sg:city":"Vettelscho\u00df",
    "sg:phone":"+49 4926/45180",
    "sg:postcode":"53558",
    "sg:province":"Rheinland-Pfalz",
    "wof:name":"Kalenborn Kalprotectdr. Mauritz Gmbh & Co. Kg",
    "wof:placetype":"venue"
},
  "geometry": {"coordinates":[7.34773,50.617111],"type":"Point"}
}