{
  "type": "Feature",
  "properties": {
    "iso:country":"DE",
    "sg:address":"Marktstr. 10",
    "sg:city":"Oelsnitz",
    "sg:phone":"+49 37421/5630",
    "sg:postcode":"08606",
    "sg:province":"Sachsen",
    "wof:name":"Ewt Dietmann & Strahl Gmbh",
    "wof:placetype":"venue"
},
  "geometry": {"coordinates":[12.1728754044,50.4143600464],"type":"Point"}
}