{
  "type": "Feature",
  "properties": {
    "iso:country":"DE",
    "sg:address":"Jenaer Str. 3",
    "sg:city":"Apolda",
    "sg:phone":"+49 3644/562734",
    "sg:postcode":"99510",
    "sg:province":"Th\u00fcringen",
    "wof:name":"Hugo Sonnekalb",
    "wof:placetype":"venue"
},
  "geometry": {"coordinates":[11.515194,51.022076],"type":"Point"}
}