{
  "type": "Feature",
  "properties": {
    "iso:country":"DE",
    "sg:address":"Don-Bosco-Str. 1",
    "sg:city":"Benediktbeuern",
    "sg:postcode":"83671",
    "sg:province":"Bayern",
    "wof:name":"Institut F\u00fcr Theologie Zentralstelle",
    "wof:placetype":"venue"
},
  "geometry": {"coordinates":[11.399107933,47.7091941833],"type":"Point"}
}