{
  "type": "Feature",
  "properties": {
    "iso:country":"DE",
    "sg:address":"Kirchenweg 42",
    "sg:city":"Gomaringen",
    "sg:phone":"+49 7072/2468",
    "sg:postcode":"72810",
    "sg:province":"Baden-W\u00fcrttemberg",
    "wof:name":"Krone",
    "wof:placetype":"venue"
},
  "geometry": {"coordinates":[9.0906219482,48.4611091614],"type":"Point"}
}