{
  "type": "Feature",
  "properties": {
    "iso:country":"DE",
    "sg:address":"Am Dorfplatz 4",
    "sg:city":"Wendeburg",
    "sg:phone":"+49 5303/1433",
    "sg:postcode":"38176",
    "sg:province":"Niedersachsen",
    "wof:name":"Heinrich Rautmann",
    "wof:placetype":"venue"
},
  "geometry": {"coordinates":[10.387234,52.344128],"type":"Point"}
}