{
  "type": "Feature",
  "properties": {
    "iso:country":"DE",
    "sg:address":"Wilhelm-Leuschner-Str. 9",
    "sg:city":"Kamen",
    "sg:phone":"+49 2307/15659",
    "sg:postcode":"59174",
    "sg:province":"Nordrhein-Westfalen",
    "wof:name":"M. Laufer",
    "wof:placetype":"venue"
},
  "geometry": {"coordinates":[7.638838,51.592712],"type":"Point"}
}