{
  "type": "Feature",
  "properties": {
    "iso:country":"DE",
    "sg:address":"Neust\u00e4dter Damm 72",
    "sg:city":"Prenzlau",
    "sg:postcode":"17291",
    "sg:province":"Brandenburg",
    "wof:name":"Armin Schm\u00f6ker",
    "wof:placetype":"venue"
},
  "geometry": {"coordinates":[13.83575,53.308273],"type":"Point"}
}