{
  "type": "Feature",
  "properties": {
    "iso:country":"DE",
    "sg:address":"Selhorster Str. 2",
    "sg:city":"Langenberg",
    "sg:phone":"+49 5248/7315",
    "sg:postcode":"33449",
    "sg:province":"Nordrhein-Westfalen",
    "wof:name":"Rvb Ulrich Weltken",
    "wof:placetype":"venue"
},
  "geometry": {"coordinates":[8.3196086884,51.7865638733],"type":"Point"}
}