{
  "type": "Feature",
  "properties": {
    "iso:country":"DE",
    "sg:address":"K\u00f6nigsbr\u00fccker Str. 37",
    "sg:city":"Ottendorf-Okrilla",
    "sg:phone":"+49 35205/73364",
    "sg:postcode":"01458",
    "sg:province":"Sachsen",
    "wof:name":"Max Menzel",
    "wof:placetype":"venue"
},
  "geometry": {"coordinates":[13.834444046,51.1961479187],"type":"Point"}
}