{
  "type": "Feature",
  "properties": {
    "iso:country":"DE",
    "sg:address":"Lange Str. 20",
    "sg:city":"Varel",
    "sg:postcode":"26316",
    "sg:province":"Niedersachsen",
    "wof:name":"H. D. Beteiligungs-gmbh",
    "wof:placetype":"venue"
},
  "geometry": {"coordinates":[8.133485,53.395668],"type":"Point"}
}