{
  "type": "Feature",
  "properties": {
    "iso:country":"DE",
    "sg:address":"Am Sportplatz 2",
    "sg:city":"Langensendelbach",
    "sg:phone":"+49 9133/77470",
    "sg:postcode":"91094",
    "sg:province":"Bayern",
    "wof:name":"Anlagenbau Neund\u00f6rfer Gmbh",
    "wof:placetype":"venue"
},
  "geometry": {"coordinates":[11.063198,49.640007],"type":"Point"}
}