{
  "type": "Feature",
  "properties": {
    "iso:country":"DE",
    "sg:address":"Hauptstr. 33",
    "sg:city":"Kleinbr\u00fcchter",
    "sg:phone":"+49 36330/65310",
    "sg:postcode":"99713",
    "sg:province":"Th\u00fcringen",
    "wof:name":"Agrarbetrieb Grossbr\u00dcchter Gmbh & Co Kg",
    "wof:placetype":"venue"
},
  "geometry": {"coordinates":[10.642405,51.311104],"type":"Point"}
}