{
  "type": "Feature",
  "properties": {
    "iso:country":"DE",
    "sg:address":"Dorfstr. 33",
    "sg:city":"Weil",
    "sg:phone":"+49 8193/1510",
    "sg:postcode":"86947",
    "sg:province":"Bayern",
    "wof:name":"J. Huster",
    "wof:placetype":"venue"
},
  "geometry": {"coordinates":[10.979309082,48.1093711853],"type":"Point"}
}