{
  "type": "Feature",
  "properties": {
    "iso:country":"DE",
    "sg:address":"Blindeisenweg 11-13",
    "sg:city":"Neuss",
    "sg:phone":"+49 2131/36640",
    "sg:postcode":"41468",
    "sg:province":"Nordrhein-Westfalen",
    "wof:name":"Cnc-biegtechnik Bei Der Rtm-gmbh.",
    "wof:placetype":"venue"
},
  "geometry": {"coordinates":[6.75754,51.160252],"type":"Point"}
}