{
  "type": "Feature",
  "properties": {
    "iso:country":"DE",
    "sg:address":"Poststr. 28",
    "sg:city":"Rheine",
    "sg:phone":"+49 5971/15445",
    "sg:postcode":"48431",
    "sg:province":"Nordrhein-Westfalen",
    "wof:name":"Aigatex Produktion & Trading Gmbh",
    "wof:placetype":"venue"
},
  "geometry": {"coordinates":[7.435339,52.279575],"type":"Point"}
}