{
  "type": "Feature",
  "properties": {
    "iso:country":"DE",
    "sg:address":"Gartenstr. 13",
    "sg:city":"Wettenberg",
    "sg:postcode":"35435",
    "sg:province":"Hessen",
    "wof:name":"Reisebericht-b\u00fccher - Reiseberichte In Buchform",
    "wof:placetype":"venue"
},
  "geometry": {"coordinates":[8.6787672043,50.6367835999],"type":"Point"}
}