{
  "type": "Feature",
  "properties": {
    "iso:country":"DE",
    "sg:address":"Johann-Neumaier-Str. 8",
    "sg:city":"Eichenau",
    "sg:phone":"+49 8141/80983",
    "sg:postcode":"82223",
    "sg:province":"Bayern",
    "wof:name":"Brigitte Und Werner Egger",
    "wof:placetype":"venue"
},
  "geometry": {"coordinates":[11.3203811646,48.1741981506],"type":"Point"}
}