{
  "type": "Feature",
  "properties": {
    "iso:country":"DE",
    "sg:address":"Oberaustr. 18",
    "sg:city":"Rosenheim",
    "sg:phone":"+49 8031/43823",
    "sg:postcode":"83026",
    "sg:province":"Bayern",
    "wof:name":"Polbau",
    "wof:placetype":"venue"
},
  "geometry": {"coordinates":[12.088822,47.850922],"type":"Point"}
}