{
  "type": "Feature",
  "properties": {
    "iso:country":"DE",
    "sg:address":"B\u00fcrgerplatz 3",
    "sg:city":"R\u00f6dental",
    "sg:postcode":"96472",
    "sg:province":"Bayern",
    "wof:name":"Stadtwerke R\u00f6dental Gmbh",
    "wof:placetype":"venue"
},
  "geometry": {"coordinates":[11.043852,50.295925],"type":"Point"}
}