{
  "type": "Feature",
  "properties": {
    "iso:country":"DE",
    "sg:address":"Wilhelmstr. 69",
    "sg:city":"Karlsruhe",
    "sg:phone":"+49 721/358293",
    "sg:postcode":"76137",
    "sg:province":"Baden-W\u00fcrttemberg",
    "wof:name":"Alpenhorn",
    "wof:placetype":"venue"
},
  "geometry": {"coordinates":[8.4060249329,48.9993896484],"type":"Point"}
}