{
  "type": "Feature",
  "properties": {
    "iso:country":"DE",
    "sg:address":"Pfaffenh\u00e4user Str. 11",
    "sg:city":"Fl\u00f6rsbachtal",
    "sg:phone":"+49 6057/91003",
    "sg:postcode":"63639",
    "sg:province":"Hessen",
    "wof:name":"Hartmut Schmidt",
    "wof:placetype":"venue"
},
  "geometry": {"coordinates":[9.4765167236,50.1288986206],"type":"Point"}
}