{
  "type": "Feature",
  "properties": {
    "iso:country":"DE",
    "sg:address":"Am Kirscheck 7A",
    "sg:city":"Dreieich",
    "sg:phone":"+49 6103/2056880",
    "sg:postcode":"63303",
    "sg:province":"Hessen",
    "wof:name":"Nievelstein",
    "wof:placetype":"venue"
},
  "geometry": {"coordinates":[8.7080898285,49.9974937439],"type":"Point"}
}