{
  "type": "Feature",
  "properties": {
    "iso:country":"DE",
    "sg:address":"Max-Bram-Platz 2a",
    "sg:city":"Rosenheim",
    "sg:postcode":"83022",
    "sg:province":"Bayern",
    "wof:name":"Redaktion Das Bayerische Inn-oberland",
    "wof:placetype":"venue"
},
  "geometry": {"coordinates":[12.1302776337,47.852142334],"type":"Point"}
}