{
  "type": "Feature",
  "properties": {
    "iso:country":"DE",
    "sg:address":"Glash\u00fcttenstr. 44",
    "sg:city":"Eisenh\u00fcttenstadt",
    "sg:phone":"+49 33609/35823",
    "sg:postcode":"15890",
    "sg:province":"Brandenburg",
    "wof:name":"Tbb Transportbeton & Baustoffe Verwaltungs Gmbh",
    "wof:placetype":"venue"
},
  "geometry": {"coordinates":[14.6481399536,52.1528205872],"type":"Point"}
}