{
  "type": "Feature",
  "properties": {
    "iso:country":"DE",
    "sg:address":"Herdweg 42",
    "sg:city":"Dettingen",
    "sg:phone":"+49 7123/7850",
    "sg:postcode":"72581",
    "sg:province":"Baden-W\u00fcrttemberg",
    "wof:name":"Dietmar Wohlfarth Ingenieur",
    "wof:placetype":"venue"
},
  "geometry": {"coordinates":[9.3572759628,48.5255088806],"type":"Point"}
}