{
  "type": "Feature",
  "properties": {
    "iso:country":"DE",
    "sg:address":"Witzlebenstr. 31",
    "sg:city":"N\u00fcrnberg",
    "sg:postcode":"90491",
    "sg:province":"Bayern",
    "wof:name":"Time Zwei Connect Gmbh",
    "wof:placetype":"venue"
},
  "geometry": {"coordinates":[11.113855,49.464813],"type":"Point"}
}