{
  "type": "Feature",
  "properties": {
    "iso:country":"DE",
    "sg:address":"Hauptstr. 61",
    "sg:city":"Egglham",
    "sg:phone":"+49 8543/3626",
    "sg:postcode":"84385",
    "sg:province":"Bayern",
    "wof:name":"Horst Heckhoff Ingenieur",
    "wof:placetype":"venue"
},
  "geometry": {"coordinates":[13.0534086227,48.5266990662],"type":"Point"}
}