{
  "type": "Feature",
  "properties": {
    "iso:country":"DE",
    "sg:address":"Bahnhofstr. 29",
    "sg:city":"Arnstorf",
    "sg:phone":"+49 8723/200",
    "sg:postcode":"94424",
    "sg:province":"Bayern",
    "wof:name":"Lindner Isoliertechnik Und Industrieservice Gmbh",
    "wof:placetype":"venue"
},
  "geometry": {"coordinates":[12.8094053268,48.5628013611],"type":"Point"}
}