{
  "type": "Feature",
  "properties": {
    "iso:country":"DE",
    "sg:address":"Gartenstr. 3",
    "sg:city":"Salzhemmendorf",
    "sg:phone":"+49 5153/5903",
    "sg:postcode":"31020",
    "sg:province":"Niedersachsen",
    "wof:name":"Karl-wilhelm Breves",
    "wof:placetype":"venue"
},
  "geometry": {"coordinates":[9.620829,52.109104],"type":"Point"}
}