{
  "type": "Feature",
  "properties": {
    "iso:country":"DE",
    "sg:address":"Hemmelsb\u00fchren 27",
    "sg:city":"Cloppenburg",
    "sg:phone":"+49 4471/81865",
    "sg:postcode":"49661",
    "sg:province":"Niedersachsen",
    "wof:name":"Ludwig Middendorf Architekt",
    "wof:placetype":"venue"
},
  "geometry": {"coordinates":[8.048324585,52.8381195068],"type":"Point"}
}