{
  "type": "Feature",
  "properties": {
    "iso:country":"DE",
    "sg:address":"August-Schanz-Str. 21",
    "sg:city":"Frankfurt am Main",
    "sg:postcode":"60433",
    "sg:province":"Hessen",
    "wof:name":"Dqs Gesellschaft Zur Zertifizierung Von Managementsystemen",
    "wof:placetype":"venue"
},
  "geometry": {"coordinates":[8.6874904633,50.1632347107],"type":"Point"}
}