{
  "type": "Feature",
  "properties": {
    "iso:country":"DE",
    "sg:address":"Martin-Luther-Str. 39",
    "sg:city":"Haan",
    "sg:phone":"+49 212/993370",
    "sg:postcode":"42781",
    "sg:province":"Nordrhein-Westfalen",
    "wof:name":"Eba Edv-beratung Austhoff Gmbh",
    "wof:placetype":"venue"
},
  "geometry": {"coordinates":[7.0138897896,51.1901016235],"type":"Point"}
}