{
  "type": "Feature",
  "properties": {
    "iso:country":"DE",
    "sg:address":"Vitus-Bering-Stra\u00dfe 34/113",
    "sg:city":"Rostock",
    "sg:postcode":"18106",
    "sg:province":"Mecklenburg-Vorpommern",
    "wof:name":"Christian Janotta - Electronic Projects",
    "wof:placetype":"venue"
},
  "geometry": {"coordinates":[12.0711517334,54.1349868774],"type":"Point"}
}