{
  "type": "Feature",
  "properties": {
    "iso:country":"DE",
    "sg:address":"Buchweg 4",
    "sg:city":"Obersontheim",
    "sg:postcode":"74423",
    "sg:province":"Baden-W\u00fcrttemberg",
    "wof:name":"Planungsgruppe Sieben Planungsb\u00fcro F\u00fcr Hoch- Und",
    "wof:placetype":"venue"
},
  "geometry": {"coordinates":[9.830247879,49.0589103699],"type":"Point"}
}