{
  "type": "Feature",
  "properties": {
    "iso:country":"DE",
    "sg:address":"Oppelner Str. 3 A",
    "sg:city":"Springe",
    "sg:phone":"+49 5041/943389",
    "sg:postcode":"31832",
    "sg:province":"Niedersachsen",
    "wof:name":"Restaurant Kr\u00e4utergarten",
    "wof:placetype":"venue"
},
  "geometry": {"coordinates":[9.5681991577,52.2100486755],"type":"Point"}
}