{
  "type": "Feature",
  "properties": {
    "iso:country":"DE",
    "sg:address":"Theodor-Heuss-Ring 26",
    "sg:city":"Dietzenbach",
    "sg:phone":"+49 6074/29455",
    "sg:postcode":"63128",
    "sg:province":"Hessen",
    "wof:name":"Baudekoration Nuovo Gmbh",
    "wof:placetype":"venue"
},
  "geometry": {"coordinates":[8.787002,50.02235],"type":"Point"}
}