{
  "type": "Feature",
  "properties": {
    "iso:country":"DE",
    "sg:address":"Borna 12",
    "sg:city":"Bahretal",
    "sg:postcode":"01819",
    "sg:province":"Sachsen",
    "wof:name":"Simone Schindler Baugesellschaft Mbh",
    "wof:placetype":"venue"
},
  "geometry": {"coordinates":[13.9023389816,50.8821105957],"type":"Point"}
}