{
  "type": "Feature",
  "properties": {
    "iso:country":"DE",
    "sg:address":"Schapenstr. 21",
    "sg:city":"Braunschweig",
    "sg:phone":"+49 531/361105",
    "sg:postcode":"38104",
    "sg:province":"Niedersachsen",
    "wof:name":"Dieter Grasshoff Verwaltungs-gmbh",
    "wof:placetype":"venue"
},
  "geometry": {"coordinates":[10.6049718857,52.280544281],"type":"Point"}
}