{
  "type": "Feature",
  "properties": {
    "iso:country":"DE",
    "sg:address":"F\u00fcrstenbergstr. 15",
    "sg:city":"Bad Rippoldsau-Schapbach",
    "sg:phone":"+49 7440/229",
    "sg:postcode":"77776",
    "sg:province":"Baden-W\u00fcrttemberg",
    "wof:name":"Gebr. Harter",
    "wof:placetype":"venue"
},
  "geometry": {"coordinates":[8.3158397675,48.436668396],"type":"Point"}
}