{
  "type": "Feature",
  "properties": {
    "iso:country":"DE",
    "sg:address":"Herzberger Landstra\u00dfe 45",
    "sg:city":"G\u00f6ttingen",
    "sg:postcode":"37073",
    "sg:province":"Niedersachsen",
    "wof:name":"Rechtsanwalt Dipl. Finw (fh) Patrick Habor",
    "wof:placetype":"venue"
},
  "geometry": {"coordinates":[9.9446296692,51.5347213745],"type":"Point"}
}