{
  "type": "Feature",
  "properties": {
    "iso:country":"DE",
    "sg:address":"W\u00fcrzburger Str. 30",
    "sg:city":"Heidenheim",
    "sg:phone":"+49 7321/66155",
    "sg:postcode":"89520",
    "sg:province":"Baden-W\u00fcrttemberg",
    "wof:name":"Leben & Wohnen",
    "wof:placetype":"venue"
},
  "geometry": {"coordinates":[10.162696,48.707317],"type":"Point"}
}