{
  "type": "Feature",
  "properties": {
    "iso:country":"DE",
    "sg:address":"Beethovenstr. 50",
    "sg:city":"Stockach",
    "sg:phone":"+49 7771/7585",
    "sg:postcode":"78333",
    "sg:province":"Baden-W\u00fcrttemberg",
    "wof:name":"Rolf Habermehl Immobilienmakler",
    "wof:placetype":"venue"
},
  "geometry": {"coordinates":[9.0098400116,47.8576202393],"type":"Point"}
}