{
  "type": "Feature",
  "properties": {
    "iso:country":"DE",
    "sg:address":"Fingerhutweg 1",
    "sg:city":"Barsinghausen",
    "sg:phone":"+49 5105/64703",
    "sg:postcode":"30890",
    "sg:province":"Niedersachsen",
    "wof:name":"K. Gilge",
    "wof:placetype":"venue"
},
  "geometry": {"coordinates":[9.430217,52.313599],"type":"Point"}
}