{
  "type": "Feature",
  "properties": {
    "iso:country":"DE",
    "sg:address":"Ensisheimer Str. 9",
    "sg:city":"Freiburg",
    "sg:phone":"+49 761/807707",
    "sg:postcode":"79110",
    "sg:province":"Baden-W\u00fcrttemberg",
    "wof:name":"Schwimm-sport-verein Freiburg E. V.",
    "wof:placetype":"venue"
},
  "geometry": {"coordinates":[7.8239550591,48.0108222961],"type":"Point"}
}