{
  "type": "Feature",
  "properties": {
    "iso:country":"DE",
    "sg:address":"Schwarzstr. 4",
    "sg:city":"M\u00fcnchen",
    "sg:postcode":"81669",
    "sg:province":"Bayern",
    "wof:name":"Textilform Vertriebs Gmbh",
    "wof:placetype":"venue"
},
  "geometry": {"coordinates":[11.585807,48.128986],"type":"Point"}
}