{
  "type": "Feature",
  "properties": {
    "iso:country":"DE",
    "sg:address":"Baldurstr. 70",
    "sg:city":"Dorsten",
    "sg:phone":"+49 2362/63065",
    "sg:postcode":"46284",
    "sg:province":"Nordrhein-Westfalen",
    "wof:name":"Roll-fe-do Rolladen-fenster- Zubeh\u00f6r-",
    "wof:placetype":"venue"
},
  "geometry": {"coordinates":[6.947309,51.672516],"type":"Point"}
}