{
  "type": "Feature",
  "properties": {
    "iso:country":"DE",
    "sg:address":"Leipziger Str. 5",
    "sg:city":"Delitzsch",
    "sg:postcode":"04509",
    "sg:province":"Sachsen",
    "wof:name":"G + M Verwaltungs- Und Beteiligungsges. Mbh",
    "wof:placetype":"venue"
},
  "geometry": {"coordinates":[12.3339414597,51.5217704773],"type":"Point"}
}