{
  "type": "Feature",
  "properties": {
    "iso:country":"DE",
    "sg:address":"Hildegardring 35",
    "sg:city":"\u00dcberlingen",
    "sg:phone":"+49 7551/63324",
    "sg:postcode":"88662",
    "sg:province":"Baden-W\u00fcrttemberg",
    "wof:name":"Herbert Siegwarth Versicherung",
    "wof:placetype":"venue"
},
  "geometry": {"coordinates":[9.159576416,47.7751541138],"type":"Point"}
}