{
  "type": "Feature",
  "properties": {
    "iso:country":"DE",
    "sg:address":"Dorfstr. 5",
    "sg:city":"Wotenitz",
    "sg:phone":"+49 3881/3079",
    "sg:postcode":"23936",
    "sg:province":"Mecklenburg-Vorpommern",
    "wof:name":"C. Schwanbeck",
    "wof:placetype":"venue"
},
  "geometry": {"coordinates":[11.180358,53.84697],"type":"Point"}
}