{
  "type": "Feature",
  "properties": {
    "iso:country":"DE",
    "sg:address":"Heimengasse 26",
    "sg:city":"Ludwigsburg",
    "sg:phone":"+49 7141/52497",
    "sg:postcode":"71642",
    "sg:province":"Baden-W\u00fcrttemberg",
    "wof:name":"Paul Mayer",
    "wof:placetype":"venue"
},
  "geometry": {"coordinates":[9.203809,48.916992],"type":"Point"}
}