{
  "type": "Feature",
  "properties": {
    "iso:country":"DE",
    "sg:address":"Lindenstr. 7",
    "sg:city":"G\u00fcstrow",
    "sg:phone":"+49 3843/682581",
    "sg:postcode":"18273",
    "sg:province":"Mecklenburg-Vorpommern",
    "wof:name":"K\u00fcchen Anders Gmbh",
    "wof:placetype":"venue"
},
  "geometry": {"coordinates":[12.171292,53.79599],"type":"Point"}
}