{
  "type": "Feature",
  "properties": {
    "iso:country":"DE",
    "sg:address":"Richrather Weg 101",
    "sg:city":"Velbert",
    "sg:phone":"+49 2051/21141",
    "sg:postcode":"42551",
    "sg:province":"Nordrhein-Westfalen",
    "wof:name":"Am Acker",
    "wof:placetype":"venue"
},
  "geometry": {"coordinates":[7.0918440819,51.3488121033],"type":"Point"}
}