{
  "type": "Feature",
  "properties": {
    "iso:country":"DE",
    "sg:address":"Feldstr. 8",
    "sg:city":"Rahden",
    "sg:phone":"+49 5771/3914",
    "sg:postcode":"32369",
    "sg:province":"Nordrhein-Westfalen",
    "wof:name":"Marie-luise Borcherding",
    "wof:placetype":"venue"
},
  "geometry": {"coordinates":[8.611126,52.431087],"type":"Point"}
}