{
  "type": "Feature",
  "properties": {
    "iso:country":"DE",
    "sg:address":"Heerstr. 71",
    "sg:city":"St. Goar",
    "sg:phone":"+49 6741/355",
    "sg:postcode":"56329",
    "sg:province":"Rheinland-Pfalz",
    "wof:name":"Rheinhotel",
    "wof:placetype":"venue"
},
  "geometry": {"coordinates":[7.7157578468,50.1506767273],"type":"Point"}
}