{
  "type": "Feature",
  "properties": {
    "iso:country":"DE",
    "sg:address":"F\u00e4hrenweg 2",
    "sg:city":"M\u00f6hnesee",
    "sg:phone":"+49 2924/1812",
    "sg:postcode":"59519",
    "sg:province":"Nordrhein-Westfalen",
    "wof:name":"Eberhard Eickhoff",
    "wof:placetype":"venue"
},
  "geometry": {"coordinates":[8.131019,51.493607],"type":"Point"}
}