{
  "type": "Feature",
  "properties": {
    "iso:country":"DE",
    "sg:address":"Pfalzgraf-Otto-Str. 40",
    "sg:city":"Mosbach",
    "sg:phone":"+49 4962/618080",
    "sg:postcode":"74821",
    "sg:province":"Baden-W\u00fcrttemberg",
    "wof:name":"W Kapferer Kg",
    "wof:placetype":"venue"
},
  "geometry": {"coordinates":[9.133053,49.343845],"type":"Point"}
}