{
  "type": "Feature",
  "properties": {
    "iso:country":"DE",
    "sg:address":"Landsberger Str. 230",
    "sg:city":"M\u00fcnchen",
    "sg:phone":"+49 89/5470600",
    "sg:postcode":"80687",
    "sg:province":"Bayern",
    "wof:name":"Buchner & Linse Gmbh",
    "wof:placetype":"venue"
},
  "geometry": {"coordinates":[11.5136804581,48.1421852112],"type":"Point"}
}