{
  "type": "Feature",
  "properties": {
    "iso:country":"DE",
    "sg:address":"Sch\u00f6ne Aussicht 7",
    "sg:city":"Wei\u00dfenborn",
    "sg:phone":"+49 36601/42390",
    "sg:postcode":"07639",
    "sg:province":"Th\u00fcringen",
    "wof:name":"Gbw Bauunternehmen Gerd Geithe E. K.",
    "wof:placetype":"venue"
},
  "geometry": {"coordinates":[11.877614975,50.9257659912],"type":"Point"}
}