{
  "type": "Feature",
  "properties": {
    "iso:country":"DE",
    "sg:address":"Steuerwalder Str. 22a",
    "sg:city":"Hildesheim",
    "sg:phone":"+49 5121/512300",
    "sg:postcode":"31137",
    "sg:province":"Niedersachsen",
    "wof:name":"Thermomess Igiil Heizkostenverteiler Gmbh",
    "wof:placetype":"venue"
},
  "geometry": {"coordinates":[9.948443,52.160763],"type":"Point"}
}