{
  "type": "Feature",
  "properties": {
    "iso:country":"DE",
    "sg:address":"Schorndorfer Str. 34",
    "sg:city":"Esslingen",
    "sg:phone":"+49 711/3160612",
    "sg:postcode":"73730",
    "sg:province":"Baden-W\u00fcrttemberg",
    "wof:name":"Adler",
    "wof:placetype":"venue"
},
  "geometry": {"coordinates":[9.334145546,48.7309532166],"type":"Point"}
}