{
  "type": "Feature",
  "properties": {
    "iso:country":"DE",
    "sg:address":"Kieler Str. 211",
    "sg:city":"Rendsburg",
    "sg:postcode":"24768",
    "sg:province":"Schleswig-Holstein",
    "wof:name":"Wupper Glas Und T\u00fcrtechnik E. K.",
    "wof:placetype":"venue"
},
  "geometry": {"coordinates":[9.7057342529,54.3086471558],"type":"Point"}
}