{
  "type": "Feature",
  "properties": {
    "iso:country":"DE",
    "sg:address":"Westernplan 25",
    "sg:city":"Magdeburg",
    "sg:postcode":"39108",
    "sg:province":"Sachsen-Anhalt",
    "wof:name":"Dr. Med. Ingrid Krisch",
    "wof:placetype":"venue"
},
  "geometry": {"coordinates":[11.615689,52.138954],"type":"Point"}
}