{
  "type": "Feature",
  "properties": {
    "iso:country":"DE",
    "sg:address":"Am Huehnerbuehl 23 b",
    "sg:city":"SCHWABACH",
    "sg:postcode":"91126",
    "sg:province":"Bayern",
    "wof:name":"Detektei Dbs",
    "wof:placetype":"venue"
},
  "geometry": {"coordinates":[11.037699,49.361488],"type":"Point"}
}