{
  "type": "Feature",
  "properties": {
    "iso:country":"DE",
    "sg:address":"Am H\u00f6henberg 4",
    "sg:city":"Tutzing",
    "sg:postcode":"82327",
    "sg:province":"Bayern",
    "wof:name":"Obermeyr Verm\u00f6gens- Verwaltung Kg",
    "wof:placetype":"venue"
},
  "geometry": {"coordinates":[11.2728424072,47.9093780518],"type":"Point"}
}