{
  "type": "Feature",
  "properties": {
    "iso:country":"DE",
    "sg:address":"Leipziger Str. 2",
    "sg:city":"Borsdorf",
    "sg:phone":"+49 34291/86291",
    "sg:postcode":"04451",
    "sg:province":"Sachsen",
    "wof:name":"Rainer Dorndeck Fotograf",
    "wof:placetype":"venue"
},
  "geometry": {"coordinates":[12.5309381485,51.3459510803],"type":"Point"}
}