{
  "type": "Feature",
  "properties": {
    "iso:country":"DE",
    "sg:address":"Maria-Theresia-Allee 45",
    "sg:city":"Aachen",
    "sg:phone":"+49 241/76862",
    "sg:postcode":"52064",
    "sg:province":"Nordrhein-Westfalen",
    "wof:name":"Wolfgang Haack Ingenieur",
    "wof:placetype":"venue"
},
  "geometry": {"coordinates":[6.0807051659,50.7610244751],"type":"Point"}
}