{
  "type": "Feature",
  "properties": {
    "iso:country":"DE",
    "sg:address":"Ziegelbergstr. 5",
    "sg:city":"Aschaffenburg",
    "sg:phone":"+49 6021/30170",
    "sg:postcode":"63739",
    "sg:province":"Bayern",
    "wof:name":"Klinik Am Ziegelberg Verwaltungs Gmbh",
    "wof:placetype":"venue"
},
  "geometry": {"coordinates":[9.1327943802,49.978553772],"type":"Point"}
}