{
  "type": "Feature",
  "properties": {
    "iso:country":"DE",
    "sg:address":"Beckenweiherallee 7",
    "sg:city":"Ansbach",
    "sg:phone":"+49 981/5081",
    "sg:postcode":"91522",
    "sg:province":"Bayern",
    "wof:name":"Bezirksmolkerei Ansbach Eg",
    "wof:placetype":"venue"
},
  "geometry": {"coordinates":[10.5845756531,49.296081543],"type":"Point"}
}