{
  "type": "Feature",
  "properties": {
    "iso:country":"DE",
    "sg:address":"Pirnaer Str. 38",
    "sg:city":"Heidenau",
    "sg:phone":"+49 3529/517456",
    "sg:postcode":"01809",
    "sg:province":"Sachsen",
    "wof:name":"Dietmar Schaub",
    "wof:placetype":"venue"
},
  "geometry": {"coordinates":[13.8757390976,50.9720458984],"type":"Point"}
}