{
  "type": "Feature",
  "properties": {
    "iso:country":"DE",
    "sg:address":"Opferbrink 1",
    "sg:city":"Freden",
    "sg:phone":"+49 5184/7218",
    "sg:postcode":"31084",
    "sg:province":"Niedersachsen",
    "wof:name":"B. Schulta",
    "wof:placetype":"venue"
},
  "geometry": {"coordinates":[9.8933229446,51.9285354614],"type":"Point"}
}