{
  "type": "Feature",
  "properties": {
    "iso:country":"DE",
    "sg:address":"Helgolandring 23",
    "sg:city":"Ahrensburg",
    "sg:phone":"+49 4102/472897",
    "sg:postcode":"22926",
    "sg:province":"Schleswig-Holstein",
    "wof:name":"Innovid E. K.",
    "wof:placetype":"venue"
},
  "geometry": {"coordinates":[10.242366,53.684814],"type":"Point"}
}