{
  "type": "Feature",
  "properties": {
    "iso:country":"DE",
    "sg:address":"Paul-Schneider-Str. 5",
    "sg:city":"Berlin",
    "sg:phone":"+49 30/7744596",
    "sg:postcode":"12247",
    "sg:province":"Berlin",
    "wof:name":"Zoo Lankwitz Kirche Inh. Helga Diezmann",
    "wof:placetype":"venue"
},
  "geometry": {"coordinates":[13.34679,52.435917],"type":"Point"}
}