{
  "type": "Feature",
  "properties": {
    "iso:country":"DE",
    "sg:address":"Eickholz 6",
    "sg:city":"Lippetal",
    "sg:phone":"+49 2923/202",
    "sg:postcode":"59510",
    "sg:province":"Nordrhein-Westfalen",
    "wof:name":"Wilhelm Mense",
    "wof:placetype":"venue"
},
  "geometry": {"coordinates":[8.192643,51.687412],"type":"Point"}
}