{
  "type": "Feature",
  "properties": {
    "iso:country":"DE",
    "sg:address":"Eulersgasse 10",
    "sg:city":"Schwalmtal",
    "sg:phone":"+49 6638/518",
    "sg:postcode":"36318",
    "sg:province":"Hessen",
    "wof:name":"Karl U. Elfriede Zinn",
    "wof:placetype":"venue"
},
  "geometry": {"coordinates":[9.3254299164,50.6962356567],"type":"Point"}
}