{
  "type": "Feature",
  "properties": {
    "iso:country":"DE",
    "sg:address":"Schulstr. 17",
    "sg:city":"Offenbach",
    "sg:phone":"+49 69/811338",
    "sg:postcode":"63065",
    "sg:province":"Hessen",
    "wof:name":"Lutz-oskar Helling",
    "wof:placetype":"venue"
},
  "geometry": {"coordinates":[8.7630329132,50.107257843],"type":"Point"}
}