{
  "type": "Feature",
  "properties": {
    "iso:country":"DE",
    "sg:address":"Gertrudenstr. 34",
    "sg:city":"Sprendlingen",
    "sg:phone":"+49 6701/1362",
    "sg:postcode":"55576",
    "sg:province":"Rheinland-Pfalz",
    "wof:name":"Bernhard Wagner",
    "wof:placetype":"venue"
},
  "geometry": {"coordinates":[7.986257,49.858475],"type":"Point"}
}