{
  "type": "Feature",
  "properties": {
    "iso:country":"DE",
    "sg:address":"Anhaltstr. 42",
    "sg:city":"Bitterfeld",
    "sg:phone":"+49 3493/23414",
    "sg:postcode":"06749",
    "sg:province":"Sachsen-Anhalt",
    "wof:name":"Werner Hanika",
    "wof:placetype":"venue"
},
  "geometry": {"coordinates":[12.313994,51.635757],"type":"Point"}
}