{
  "type": "Feature",
  "properties": {
    "iso:country":"DE",
    "sg:address":"Schillerstr. 45",
    "sg:city":"Wermelskirchen",
    "sg:phone":"+49 2196/2441",
    "sg:postcode":"42929",
    "sg:province":"Nordrhein-Westfalen",
    "wof:name":"O. H\u00e4ndeler",
    "wof:placetype":"venue"
},
  "geometry": {"coordinates":[7.214088,51.136509],"type":"Point"}
}