{
  "type": "Feature",
  "properties": {
    "iso:country":"DE",
    "sg:address":"Kiefernweg 10",
    "sg:city":"Wabern",
    "sg:phone":"+49 5683/1459",
    "sg:postcode":"34590",
    "sg:province":"Hessen",
    "wof:name":"Bernd Und Heidi Schappert",
    "wof:placetype":"venue"
},
  "geometry": {"coordinates":[9.3866481781,51.0980606079],"type":"Point"}
}