{
  "type": "Feature",
  "properties": {
    "iso:country":"DE",
    "sg:address":"Hofhalde 28",
    "sg:city":"G\u00f6ppingen",
    "sg:phone":"+49 7161/22620",
    "sg:postcode":"73035",
    "sg:province":"Baden-W\u00fcrttemberg",
    "wof:name":"Reinhold Weiler",
    "wof:placetype":"venue"
},
  "geometry": {"coordinates":[9.660294,48.722073],"type":"Point"}
}