{
  "type": "Feature",
  "properties": {
    "iso:country":"DE",
    "sg:address":"Sinkersh\u00e4user Weg 1",
    "sg:city":"Gladenbach",
    "sg:postcode":"35075",
    "sg:province":"Hessen",
    "wof:name":"Druckerei Kraus Gmbh & Co. Kg",
    "wof:placetype":"venue"
},
  "geometry": {"coordinates":[8.584827,50.773838],"type":"Point"}
}