{
  "type": "Feature",
  "properties": {
    "iso:country":"DE",
    "sg:address":"M\u00fchlenbusch 7",
    "sg:city":"Springe",
    "sg:phone":"+49 5041/1600",
    "sg:postcode":"31832",
    "sg:province":"Niedersachsen",
    "wof:name":"Willi Koch",
    "wof:placetype":"venue"
},
  "geometry": {"coordinates":[9.517922,52.182461],"type":"Point"}
}