{
  "type": "Feature",
  "properties": {
    "iso:country":"DE",
    "sg:address":"Kirchbergstr. 1",
    "sg:city":"Todtmoos",
    "sg:phone":"+49 7674/395",
    "sg:postcode":"79682",
    "sg:province":"Baden-W\u00fcrttemberg",
    "wof:name":"Hotel Waldeck",
    "wof:placetype":"venue"
},
  "geometry": {"coordinates":[7.9995222092,47.739616394],"type":"Point"}
}