{
  "type": "Feature",
  "properties": {
    "iso:country":"DE",
    "sg:address":"Hauptstra\u00dfe 107",
    "sg:city":"Calw-Stammheim",
    "sg:phone":"+49 7051",
    "sg:postcode":"75365",
    "sg:province":"Baden-W\u00fcrttemberg",
    "wof:name":"Steuerberatung Calw Gmbh",
    "wof:placetype":"venue"
},
  "geometry": {"coordinates":[8.760279,48.70047],"type":"Point"}
}