{
  "type": "Feature",
  "properties": {
    "iso:country":"DE",
    "sg:address":"Dorfstr. 37",
    "sg:city":"Lebusa",
    "sg:phone":"+49 35364/288",
    "sg:postcode":"04936",
    "sg:province":"Brandenburg",
    "wof:name":"P. Pratsch",
    "wof:placetype":"venue"
},
  "geometry": {"coordinates":[13.429359,51.795231],"type":"Point"}
}