{
  "type": "Feature",
  "properties": {
    "iso:country":"DE",
    "sg:address":"Lange Str. 6",
    "sg:city":"L\u00fcbbecke",
    "sg:phone":"+49 5741/5979",
    "sg:postcode":"32312",
    "sg:province":"Nordrhein-Westfalen",
    "wof:name":"Die Brille Augenoptik",
    "wof:placetype":"venue"
},
  "geometry": {"coordinates":[8.6172180176,52.3249855042],"type":"Point"}
}