{
  "type": "Feature",
  "properties": {
    "iso:country":"DE",
    "sg:address":"Friedensstr. 6",
    "sg:city":"Kaufbeuren",
    "sg:phone":"+49 8341/73605",
    "sg:postcode":"87600",
    "sg:province":"Bayern",
    "wof:name":"Bayer Wohnbau Gmbh",
    "wof:placetype":"venue"
},
  "geometry": {"coordinates":[10.622534,47.875347],"type":"Point"}
}