{
  "type": "Feature",
  "properties": {
    "iso:country":"DE",
    "sg:address":"Eichendorffstr. 8",
    "sg:city":"Hamburg",
    "sg:phone":"+49 40/863814",
    "sg:postcode":"22587",
    "sg:province":"Hamburg",
    "wof:name":"Peter O. Wantje",
    "wof:placetype":"venue"
},
  "geometry": {"coordinates":[9.834394,53.556423],"type":"Point"}
}