{
  "type": "Feature",
  "properties": {
    "iso:country":"DE",
    "sg:address":"Hugenottenallee 120",
    "sg:city":"Neu-Isenburg",
    "sg:phone":"+49 6102/247936",
    "sg:postcode":"63263",
    "sg:province":"Hessen",
    "wof:name":"Str Destination Handling Und Promotions Stinnes Ohg",
    "wof:placetype":"venue"
},
  "geometry": {"coordinates":[8.6890449524,50.0483703613],"type":"Point"}
}