{
  "type": "Feature",
  "properties": {
    "iso:country":"DE",
    "sg:address":"\u00d6lm\u00fchle 1",
    "sg:city":"\u00d6lm\u00fchle",
    "sg:phone":"+49 7182/3276",
    "sg:postcode":"73553",
    "sg:province":"Baden-W\u00fcrttemberg",
    "wof:name":"Werner Heinrich Ingenieur",
    "wof:placetype":"venue"
},
  "geometry": {"coordinates":[9.7511472702,48.8849029541],"type":"Point"}
}