{
  "type": "Feature",
  "properties": {
    "iso:country":"DE",
    "sg:address":"Am Franziskanerwasser 26",
    "sg:city":"Ingolstadt",
    "sg:phone":"+49 841/61039",
    "sg:postcode":"85053",
    "sg:province":"Bayern",
    "wof:name":"Tennisarena Ingolstadt S\u00fcd Gmbh",
    "wof:placetype":"venue"
},
  "geometry": {"coordinates":[11.4747562408,48.7535400391],"type":"Point"}
}