{
  "type": "Feature",
  "properties": {
    "iso:country":"DE",
    "sg:address":"Mittelstr. 57",
    "sg:city":"Barntrup",
    "sg:phone":"+49 5263/2255",
    "sg:postcode":"32683",
    "sg:province":"Nordrhein-Westfalen",
    "wof:name":"G. M\u00fchlenmeier",
    "wof:placetype":"venue"
},
  "geometry": {"coordinates":[9.1089477539,51.9908409119],"type":"Point"}
}