{
  "type": "Feature",
  "properties": {
    "iso:country":"DE",
    "sg:address":"Jacobistr. 10",
    "sg:city":"M\u00fcnchen",
    "sg:phone":"+49 89/915234",
    "sg:postcode":"81927",
    "sg:province":"Bayern",
    "wof:name":"Wolf R. Gravenstein",
    "wof:placetype":"venue"
},
  "geometry": {"coordinates":[11.6301555634,48.1480293274],"type":"Point"}
}