{
  "type": "Feature",
  "properties": {
    "iso:country":"DE",
    "sg:address":"Schwabstr. 193",
    "sg:city":"Stuttgart",
    "sg:phone":"+49 711/2264807",
    "sg:postcode":"70193",
    "sg:province":"Baden-W\u00fcrttemberg",
    "wof:name":"E. Grimm Immobilienmakler",
    "wof:placetype":"venue"
},
  "geometry": {"coordinates":[9.1575069427,48.7820358276],"type":"Point"}
}