{
  "type": "Feature",
  "properties": {
    "iso:country":"DE",
    "sg:address":"Klanxb\u00fcller Str. 9",
    "sg:city":"Nieb\u00fcll",
    "sg:phone":"+49 4946/6196780",
    "sg:postcode":"25899",
    "sg:province":"Schleswig-Holstein",
    "wof:name":"W\u00dcstenberg Kg",
    "wof:placetype":"venue"
},
  "geometry": {"coordinates":[8.833953,54.799454],"type":"Point"}
}