{
  "type": "Feature",
  "properties": {
    "iso:country":"DE",
    "sg:address":"Vorhelmer Str. 45",
    "sg:city":"Beckum",
    "sg:phone":"+49 2521/3802",
    "sg:postcode":"59269",
    "sg:province":"Nordrhein-Westfalen",
    "wof:name":"Martin Sydow",
    "wof:placetype":"venue"
},
  "geometry": {"coordinates":[8.036677,51.760044],"type":"Point"}
}