{
  "type": "Feature",
  "properties": {
    "iso:country":"DE",
    "sg:address":"Kreuzwiesenweg 72/4",
    "sg:city":"Schw\u00e4bisch Hall",
    "sg:phone":"+49 791/3171",
    "sg:postcode":"74523",
    "sg:province":"Baden-W\u00fcrttemberg",
    "wof:name":"Boie Gmbh & Co. Kg Eisenwaren",
    "wof:placetype":"venue"
},
  "geometry": {"coordinates":[9.756573,49.115749],"type":"Point"}
}