{
  "type": "Feature",
  "properties": {
    "iso:country":"DE",
    "sg:address":"N\u00fcrnberger Str. 28",
    "sg:city":"Neumarkt",
    "sg:phone":"+49 9181/460174",
    "sg:postcode":"92318",
    "sg:province":"Bayern",
    "wof:name":"Comet",
    "wof:placetype":"venue"
},
  "geometry": {"coordinates":[11.446680069,49.2874336243],"type":"Point"}
}