{
  "type": "Feature",
  "properties": {
    "iso:country":"DE",
    "sg:address":"Gareisstr. 77",
    "sg:city":"Essen",
    "sg:phone":"+49 201/211130",
    "sg:postcode":"45309",
    "sg:province":"Nordrhein-Westfalen",
    "wof:name":"Evangelischer M\u00e4nnerverein Und Sterbekasse",
    "wof:placetype":"venue"
},
  "geometry": {"coordinates":[7.0616221428,51.4868087769],"type":"Point"}
}