{
  "type": "Feature",
  "properties": {
    "iso:country":"DE",
    "sg:address":"Mahdenwiesenweg 1",
    "sg:city":"Sch\u00f6naich",
    "sg:phone":"+49 7031/651025",
    "sg:postcode":"71101",
    "sg:province":"Baden-W\u00fcrttemberg",
    "wof:name":"F. Knoth Gmbh",
    "wof:placetype":"venue"
},
  "geometry": {"coordinates":[9.064207077,48.6709213257],"type":"Point"}
}