{
  "type": "Feature",
  "properties": {
    "iso:country":"DE",
    "sg:address":"Hammoor 46",
    "sg:city":"Rietberg",
    "sg:phone":"+49 2944/1257",
    "sg:postcode":"33397",
    "sg:province":"Nordrhein-Westfalen",
    "wof:name":"Gerhard L\u00f6hner Landesprodukte",
    "wof:placetype":"venue"
},
  "geometry": {"coordinates":[8.365938,51.776752],"type":"Point"}
}