{
  "type": "Feature",
  "properties": {
    "iso:country":"DE",
    "sg:address":"Hauptstr. 25",
    "sg:city":"Eresing",
    "sg:phone":"+49 8193/5050",
    "sg:postcode":"86922",
    "sg:province":"Bayern",
    "wof:name":"Tcs, Inh. Robert Steer",
    "wof:placetype":"venue"
},
  "geometry": {"coordinates":[11.022191,48.08799],"type":"Point"}
}