{
  "type": "Feature",
  "properties": {
    "iso:country":"DE",
    "sg:address":"Rugenbarg 18",
    "sg:city":"Hamburg",
    "sg:phone":"+49 40/8007050",
    "sg:postcode":"22549",
    "sg:province":"Hamburg",
    "wof:name":"Olympiade",
    "wof:placetype":"venue"
},
  "geometry": {"coordinates":[9.8470458984,53.5746116638],"type":"Point"}
}