{
  "type": "Feature",
  "properties": {
    "iso:country":"DE",
    "sg:address":"Lange Str. 156",
    "sg:city":"Langenau",
    "sg:phone":"+49 7345/7584",
    "sg:postcode":"89129",
    "sg:province":"Baden-W\u00fcrttemberg",
    "wof:name":"Heinrich Hieber",
    "wof:placetype":"venue"
},
  "geometry": {"coordinates":[10.134706,48.503456],"type":"Point"}
}