{
  "type": "Feature",
  "properties": {
    "iso:country":"DE",
    "sg:address":"Ostenort 6",
    "sg:city":"Wallenhorst",
    "sg:phone":"+49 5407/6343",
    "sg:postcode":"49134",
    "sg:province":"Niedersachsen",
    "wof:name":"Gastst\u00e4tte A. Hellmich",
    "wof:placetype":"venue"
},
  "geometry": {"coordinates":[8.0870819092,52.3428535461],"type":"Point"}
}