{
  "type": "Feature",
  "properties": {
    "iso:country":"DE",
    "sg:address":"Rosenheimer Landstr. 17",
    "sg:city":"Ottobrunn",
    "sg:postcode":"85521",
    "sg:province":"Bayern",
    "wof:name":"Bioversum Gmbh",
    "wof:placetype":"venue"
},
  "geometry": {"coordinates":[11.657746315,48.0694694519],"type":"Point"}
}