{
  "type": "Feature",
  "properties": {
    "iso:country":"DE",
    "sg:address":"Ueckerm\u00fcnder Str. 53",
    "sg:city":"Liepgarten",
    "sg:postcode":"17375",
    "sg:province":"Mecklenburg-Vorpommern",
    "wof:name":"Evangelisch-lutherische Kirche",
    "wof:placetype":"venue"
},
  "geometry": {"coordinates":[14.0282258987,53.7172546387],"type":"Point"}
}