{
  "type": "Feature",
  "properties": {
    "iso:country":"DE",
    "sg:address":"Lebacher Str. 40",
    "sg:city":"Eppelborn",
    "sg:phone":"+49 6827/302030",
    "sg:postcode":"66571",
    "sg:province":"Saarland",
    "wof:name":"Handy Man",
    "wof:placetype":"venue"
},
  "geometry": {"coordinates":[7.00897789,49.4198760986],"type":"Point"}
}