{
  "type": "Feature",
  "properties": {
    "iso:country":"DE",
    "sg:address":"Otto-Hahn-Str. 4",
    "sg:city":"Troisdorf",
    "sg:phone":"+49 2241/42251",
    "sg:postcode":"53842",
    "sg:province":"Nordrhein-Westfalen",
    "wof:name":"Klaus Hesse Inh. Kersten Herse",
    "wof:placetype":"venue"
},
  "geometry": {"coordinates":[7.1248898506,50.8184547424],"type":"Point"}
}