{
  "type": "Feature",
  "properties": {
    "iso:country":"DE",
    "sg:address":"Dieplohstr. 12",
    "sg:city":"Warstein",
    "sg:phone":"+49 2902/9880",
    "sg:postcode":"59581",
    "sg:province":"Nordrhein-Westfalen",
    "wof:name":"Haus Cramer Gastst\u00e4tten- Management Gmbh & Co.kg",
    "wof:placetype":"venue"
},
  "geometry": {"coordinates":[8.3521051407,51.4424552917],"type":"Point"}
}