{
  "type": "Feature",
  "properties": {
    "iso:country":"DE",
    "sg:address":"Am Schulzenhof 6",
    "sg:city":"Xanten",
    "sg:phone":"+49 2804/1497",
    "sg:postcode":"46509",
    "sg:province":"Nordrhein-Westfalen",
    "wof:name":"Sportreisen Hinnemann Gmbh",
    "wof:placetype":"venue"
},
  "geometry": {"coordinates":[6.4151368141,51.7018966675],"type":"Point"}
}