{
  "type": "Feature",
  "properties": {
    "iso:country":"DE",
    "sg:address":"Meyenburger Tor",
    "sg:city":"Pritzwalk",
    "sg:phone":"+49 177 5828185",
    "sg:postcode":"16928",
    "sg:province":"Brandenburg",
    "wof:name":"Handyangebote,handy Mit Vertrag",
    "wof:placetype":"venue"
},
  "geometry": {"coordinates":[12.17894,53.154148],"type":"Point"}
}