{
  "type": "Feature",
  "properties": {
    "iso:country":"DE",
    "sg:address":"Am Leonhardsbrunn 16",
    "sg:city":"Frankfurt",
    "sg:phone":"+49 69/773055",
    "sg:postcode":"60487",
    "sg:province":"Hessen",
    "wof:name":"Societe Des Parfums Schiaparelli",
    "wof:placetype":"venue"
},
  "geometry": {"coordinates":[8.6537055969,50.1276664734],"type":"Point"}
}