{
  "type": "Feature",
  "properties": {
    "iso:country":"DE",
    "sg:address":"Im Rad 2a",
    "sg:city":"Wiesbaden",
    "sg:postcode":"65197",
    "sg:province":"Hessen",
    "wof:name":"B\u00fcroeinrichtungen Dieter Beil",
    "wof:placetype":"venue"
},
  "geometry": {"coordinates":[8.21509,50.075912],"type":"Point"}
}