{
  "type": "Feature",
  "properties": {
    "iso:country":"DE",
    "sg:address":"Heldrunger Str. 69",
    "sg:city":"Bretleben",
    "sg:phone":"+49 34673/97987",
    "sg:postcode":"06556",
    "sg:province":"Th\u00fcringen",
    "wof:name":"Volkshaus Bretleben",
    "wof:placetype":"venue"
},
  "geometry": {"coordinates":[11.2317810059,51.3351364136],"type":"Point"}
}