{
  "type": "Feature",
  "properties": {
    "iso:country":"DE",
    "sg:address":"Allmenr\u00f6der Weg 1",
    "sg:city":"Lauterbach",
    "sg:phone":"+49 6641/2559",
    "sg:postcode":"36341",
    "sg:province":"Hessen",
    "wof:name":"Henner Helwig",
    "wof:placetype":"venue"
},
  "geometry": {"coordinates":[9.38879,50.635391],"type":"Point"}
}