{
  "type": "Feature",
  "properties": {
    "iso:country":"DE",
    "sg:address":"Industriestr.8",
    "sg:city":"Velen",
    "sg:postcode":"46342",
    "sg:province":"Nordrhein-Westfalen",
    "wof:name":"G\u00fcnther Gmbh & Co. Tiefbau Kg",
    "wof:placetype":"venue"
},
  "geometry": {"coordinates":[6.9950141907,51.8966331482],"type":"Point"}
}