{
  "type": "Feature",
  "properties": {
    "iso:country":"DE",
    "sg:address":"Humboldtstr. 50",
    "sg:city":"M\u00fclheim",
    "sg:phone":"+49 208/491343",
    "sg:postcode":"45472",
    "sg:province":"Nordrhein-Westfalen",
    "wof:name":"Tebbe",
    "wof:placetype":"venue"
},
  "geometry": {"coordinates":[6.957364,51.435467],"type":"Point"}
}