{
  "type": "Feature",
  "properties": {
    "iso:country":"DE",
    "sg:address":"Kirchstr. 6",
    "sg:city":"Mindelheim",
    "sg:phone":"+49 8261/20411",
    "sg:postcode":"87719",
    "sg:province":"Bayern",
    "wof:name":"Nagomed Naturprodukte Vertriebs Gmbh",
    "wof:placetype":"venue"
},
  "geometry": {"coordinates":[10.4863452911,48.0474624634],"type":"Point"}
}