{
  "type": "Feature",
  "properties": {
    "iso:country":"DE",
    "sg:address":"Kleink\u00f6lnstr. 8",
    "sg:city":"Aachen",
    "sg:phone":"+49 241/44731",
    "sg:postcode":"52062",
    "sg:province":"Nordrhein-Westfalen",
    "wof:name":"Ibv Gmbh",
    "wof:placetype":"venue"
},
  "geometry": {"coordinates":[6.0854229927,50.7764053345],"type":"Point"}
}