{
  "type": "Feature",
  "properties": {
    "iso:country":"DE",
    "sg:address":"Aspacher Str. 120",
    "sg:city":"Backnang",
    "sg:phone":"+49 7191/68871",
    "sg:postcode":"71522",
    "sg:province":"Baden-W\u00fcrttemberg",
    "wof:name":"Avia Tankstelle",
    "wof:placetype":"venue"
},
  "geometry": {"coordinates":[9.4210510254,48.9499130249],"type":"Point"}
}