{
  "type": "Feature",
  "properties": {
    "iso:country":"DE",
    "sg:address":"Maybachstr. 16 a",
    "sg:city":"Konstanz",
    "sg:phone":"+49 7531/62659",
    "sg:postcode":"78467",
    "sg:province":"Baden-W\u00fcrttemberg",
    "wof:name":"Kawe",
    "wof:placetype":"venue"
},
  "geometry": {"coordinates":[9.1501569748,47.6782951355],"type":"Point"}
}