{
  "type": "Feature",
  "properties": {
    "iso:country":"DE",
    "sg:address":"Geisberg 61",
    "sg:city":"Saarbr\u00fccken",
    "sg:phone":"+49 681/9893125",
    "sg:postcode":"66132",
    "sg:province":"Saarland",
    "wof:name":"Rainer M\u00fcller",
    "wof:placetype":"venue"
},
  "geometry": {"coordinates":[7.0544371605,49.2249603271],"type":"Point"}
}