{
  "type": "Feature",
  "properties": {
    "iso:country":"DE",
    "sg:address":"Ilster 2a",
    "sg:city":"Munster",
    "sg:phone":"+49 5192/2831",
    "sg:postcode":"29633",
    "sg:province":"Niedersachsen",
    "wof:name":"Heinz Buschjost",
    "wof:placetype":"venue"
},
  "geometry": {"coordinates":[10.0462598801,53.007900238],"type":"Point"}
}