{
  "type": "Feature",
  "properties": {
    "iso:country":"DE",
    "sg:address":"Klosterstr. 44",
    "sg:city":"Stadthagen",
    "sg:phone":"+49 5721/3332",
    "sg:postcode":"31655",
    "sg:province":"Niedersachsen",
    "wof:name":"Ute Brodziak-mudra Krankengymnastin",
    "wof:placetype":"venue"
},
  "geometry": {"coordinates":[9.203945,52.323292],"type":"Point"}
}