{
  "type": "Feature",
  "properties": {
    "iso:country":"DE",
    "sg:address":"Hauptstr. 52",
    "sg:city":"Goldenstedt",
    "sg:phone":"+49 4444/961293",
    "sg:postcode":"49424",
    "sg:province":"Niedersachsen",
    "wof:name":"Martin Kossen M\u00fcnsterl\u00e4ndische Versicherung",
    "wof:placetype":"venue"
},
  "geometry": {"coordinates":[8.4298343658,52.789024353],"type":"Point"}
}