{
  "type": "Feature",
  "properties": {
    "iso:country":"DE",
    "sg:address":"Bergstr. 35",
    "sg:city":"Emmendingen",
    "sg:phone":"+49 7641/42824",
    "sg:postcode":"79312",
    "sg:province":"Baden-W\u00fcrttemberg",
    "wof:name":"Wilhelm Ziebold",
    "wof:placetype":"venue"
},
  "geometry": {"coordinates":[7.883125,48.119549],"type":"Point"}
}