{
  "type": "Feature",
  "properties": {
    "iso:country":"DE",
    "sg:address":"Burger Heerstr. 23",
    "sg:city":"Bremen",
    "sg:phone":"+49 421/642720",
    "sg:postcode":"28719",
    "sg:province":"Bremen",
    "wof:name":"W. Perelaer",
    "wof:placetype":"venue"
},
  "geometry": {"coordinates":[8.7049474716,53.1543998718],"type":"Point"}
}