{
  "type": "Feature",
  "properties": {
    "iso:country":"DE",
    "sg:address":"Hauptstr. 28",
    "sg:city":"Butzbach",
    "sg:phone":"+49 6033/60605",
    "sg:postcode":"35510",
    "sg:province":"Hessen",
    "wof:name":"Edwin Boller",
    "wof:placetype":"venue"
},
  "geometry": {"coordinates":[8.608083,50.452908],"type":"Point"}
}