{
  "type": "Feature",
  "properties": {
    "iso:country":"DE",
    "sg:address":"Unterl\u00e4nder Str. 58",
    "sg:city":"Stuttgart",
    "sg:phone":"+49 4971/187820",
    "sg:postcode":"70435",
    "sg:province":"Baden-W\u00fcrttemberg",
    "wof:name":"Volksbank",
    "wof:placetype":"venue"
},
  "geometry": {"coordinates":[9.169789,48.832424],"type":"Point"}
}