{
  "type": "Feature",
  "properties": {
    "iso:country":"DE",
    "sg:address":"Alte Dorfstr. 9",
    "sg:city":"Schrobenhausen",
    "sg:phone":"+49 8252/883551",
    "sg:postcode":"86529",
    "sg:province":"Bayern",
    "wof:name":"A & M Food Service Gmbh",
    "wof:placetype":"venue"
},
  "geometry": {"coordinates":[11.2827854156,48.5709190369],"type":"Point"}
}