{
  "type": "Feature",
  "properties": {
    "iso:country":"DE",
    "sg:address":"Festplatz 1",
    "sg:city":"Karlsruhe",
    "sg:phone":"+49 721/3844779",
    "sg:postcode":"76137",
    "sg:province":"Baden-W\u00fcrttemberg",
    "wof:name":"Karlsruher-sportst\u00e4tten- Betriebsgesellschaft Mbh",
    "wof:placetype":"venue"
},
  "geometry": {"coordinates":[8.3997449875,49.0026092529],"type":"Point"}
}