{
  "type": "Feature",
  "properties": {
    "iso:country":"DE",
    "sg:address":"Eichenstr. 73",
    "sg:city":"Viersen",
    "sg:phone":"+49 2162/17061",
    "sg:postcode":"41747",
    "sg:province":"Nordrhein-Westfalen",
    "wof:name":"Josef Beeck Ingenieur",
    "wof:placetype":"venue"
},
  "geometry": {"coordinates":[6.4052228928,51.250831604],"type":"Point"}
}