{
  "type": "Feature",
  "properties": {
    "iso:country":"DE",
    "sg:address":"Waldweg 42",
    "sg:city":"Bendestorf",
    "sg:phone":"+49 4183/3007",
    "sg:postcode":"21227",
    "sg:province":"Niedersachsen",
    "wof:name":"Die Kleine Zeitung Gmbh",
    "wof:placetype":"venue"
},
  "geometry": {"coordinates":[9.9697265625,53.3287467957],"type":"Point"}
}