{
  "type": "Feature",
  "properties": {
    "iso:country":"DE",
    "sg:address":"Werderstr. 49 a",
    "sg:city":"M\u00fcllheim",
    "sg:phone":"+49 7631/10020",
    "sg:postcode":"79379",
    "sg:province":"Baden-W\u00fcrttemberg",
    "wof:name":"Restaurant Istanbul",
    "wof:placetype":"venue"
},
  "geometry": {"coordinates":[7.628387928,47.8084716797],"type":"Point"}
}