{
  "type": "Feature",
  "properties": {
    "iso:country":"DE",
    "sg:address":"R\u00f6derthal",
    "sg:city":"Elmstein",
    "sg:phone":"+49 6328/400",
    "sg:postcode":"67471",
    "sg:province":"Rheinland-Pfalz",
    "wof:name":"I. Klamerski",
    "wof:placetype":"venue"
},
  "geometry": {"coordinates":[7.9261651039,49.3414115906],"type":"Point"}
}