{
  "type": "Feature",
  "properties": {
    "iso:country":"DE",
    "sg:address":"Oberstr. 4",
    "sg:city":"Nordkirchen",
    "sg:phone":"+49 2596/715",
    "sg:postcode":"59394",
    "sg:province":"Nordrhein-Westfalen",
    "wof:name":"Gasthaus Elmar Schulze- Weischer",
    "wof:placetype":"venue"
},
  "geometry": {"coordinates":[7.5455012321,51.7134666443],"type":"Point"}
}