{
  "type": "Feature",
  "properties": {
    "iso:country":"DE",
    "sg:address":"St\u00f6ckachstr. 31",
    "sg:city":"Stuttgart",
    "sg:phone":"+49 711/285460",
    "sg:postcode":"70190",
    "sg:province":"Baden-W\u00fcrttemberg",
    "wof:name":"Wolfgang Helmut Klingel Steuerberater",
    "wof:placetype":"venue"
},
  "geometry": {"coordinates":[9.2003545761,48.791103363],"type":"Point"}
}