{
  "type": "Feature",
  "properties": {
    "iso:country":"DE",
    "sg:address":"Stedingerstr. 2",
    "sg:city":"Stuttgart",
    "sg:phone":"+49 711/8875875",
    "sg:postcode":"70499",
    "sg:province":"Baden-W\u00fcrttemberg",
    "wof:name":"Brigitte March Immobilienmaklerin",
    "wof:placetype":"venue"
},
  "geometry": {"coordinates":[9.1145601273,48.815410614],"type":"Point"}
}