{
  "type": "Feature",
  "properties": {
    "iso:country":"DE",
    "sg:address":"Ravensburger Str. 24",
    "sg:city":"Bad Waldsee",
    "sg:phone":"+49 7524/8940",
    "sg:postcode":"88339",
    "sg:province":"Baden-W\u00fcrttemberg",
    "wof:name":"Alfred Schmegner",
    "wof:placetype":"venue"
},
  "geometry": {"coordinates":[9.7547302246,47.9195632935],"type":"Point"}
}