{
  "type": "Feature",
  "properties": {
    "iso:country":"DE",
    "sg:address":"Zur Dorfstr. 10",
    "sg:city":"Sch\u00fcnow",
    "sg:phone":"+49 3377/302475",
    "sg:postcode":"15806",
    "sg:province":"Brandenburg",
    "wof:name":"Emc Erd- Tief- Und Umwelt- Schutzbau Aufbereitung",
    "wof:placetype":"venue"
},
  "geometry": {"coordinates":[13.351784,52.227085],"type":"Point"}
}