{
  "type": "Feature",
  "properties": {
    "iso:country":"DE",
    "sg:address":"Ziegelstr. 3",
    "sg:city":"Ehrenfriedersdorf",
    "sg:phone":"+49 37341/2026",
    "sg:postcode":"09427",
    "sg:province":"Sachsen",
    "wof:name":"Pension-gasthof Am Wald",
    "wof:placetype":"venue"
},
  "geometry": {"coordinates":[12.9700899124,50.6545181274],"type":"Point"}
}