{
  "type": "Feature",
  "properties": {
    "iso:country":"DE",
    "sg:address":"Heddesdorfer Str. 34",
    "sg:city":"Neuwied",
    "sg:phone":"+49 2631/23450",
    "sg:postcode":"56564",
    "sg:province":"Rheinland-Pfalz",
    "wof:name":"Scala-theater",
    "wof:placetype":"venue"
},
  "geometry": {"coordinates":[7.4654178619,50.4326324463],"type":"Point"}
}