{
  "type": "Feature",
  "properties": {
    "iso:country":"DE",
    "sg:address":"Schrenkstr. 13",
    "sg:city":"M\u00fcnchen",
    "sg:phone":"+49 89/5021112",
    "sg:postcode":"80339",
    "sg:province":"Bayern",
    "wof:name":"Elato",
    "wof:placetype":"venue"
},
  "geometry": {"coordinates":[11.541727066,48.1384658813],"type":"Point"}
}