{
  "type": "Feature",
  "properties": {
    "iso:country":"DE",
    "sg:address":"\u00d6schlestr. 20",
    "sg:city":"Rottweil",
    "sg:phone":"+49 741/22746",
    "sg:postcode":"78628",
    "sg:province":"Baden-W\u00fcrttemberg",
    "wof:name":"Gustav Kuon",
    "wof:placetype":"venue"
},
  "geometry": {"coordinates":[8.640353,48.153477],"type":"Point"}
}