{
  "type": "Feature",
  "properties": {
    "iso:country":"DE",
    "sg:address":"Mozartstr. 12",
    "sg:city":"Obertshausen",
    "sg:phone":"+49 6104/95470",
    "sg:postcode":"63179",
    "sg:province":"Hessen",
    "wof:name":"Hans-j\u00fcrgen L\u00fcttich Architekt",
    "wof:placetype":"venue"
},
  "geometry": {"coordinates":[8.838595,50.067432],"type":"Point"}
}