{
  "type": "Feature",
  "properties": {
    "iso:country":"DE",
    "sg:address":"Gerstenstr. 4 C",
    "sg:city":"Stuttgart",
    "sg:phone":"+49 711/455118",
    "sg:postcode":"70599",
    "sg:province":"Baden-W\u00fcrttemberg",
    "wof:name":"Kranert Gmbh Mont. Systeme",
    "wof:placetype":"venue"
},
  "geometry": {"coordinates":[9.2144365311,48.6999511719],"type":"Point"}
}