{
  "type": "Feature",
  "properties": {
    "iso:country":"DE",
    "sg:address":"Ingolst\u00e4dter Str. 22",
    "sg:city":"Karlshuld",
    "sg:postcode":"86668",
    "sg:province":"Bayern",
    "wof:name":"Stargate Gmbh",
    "wof:placetype":"venue"
},
  "geometry": {"coordinates":[11.2906723022,48.684677124],"type":"Point"}
}