{
  "type": "Feature",
  "properties": {
    "iso:country":"DE",
    "sg:address":"POBox 304 162",
    "sg:city":"Hamburg",
    "sg:phone":"+49 40/3194491",
    "sg:postcode":"20324",
    "sg:province":"Hamburg",
    "wof:name":"Hundreds Of Beautiful Sunglasses - Sonnenbrillen",
    "wof:placetype":"venue"
},
  "geometry": {"coordinates":[9.9733,53.549831],"type":"Point"}
}