{
  "type": "Feature",
  "properties": {
    "iso:country":"DE",
    "sg:address":"Bromeledonk 54",
    "sg:city":"Krefeld",
    "sg:phone":"+49 2151/541997",
    "sg:postcode":"47809",
    "sg:province":"Nordrhein-Westfalen",
    "wof:name":"Dieter Uhlen",
    "wof:placetype":"venue"
},
  "geometry": {"coordinates":[6.612347126,51.3184394836],"type":"Point"}
}