{
  "type": "Feature",
  "properties": {
    "iso:country":"DE",
    "sg:address":"Euskirchener Str. 1",
    "sg:city":"Weilerswist",
    "sg:phone":"+49 2254/5252",
    "sg:postcode":"53919",
    "sg:province":"Nordrhein-Westfalen",
    "wof:name":"Drinnen Und Drau\u00dfen Thomas Abts E. K.",
    "wof:placetype":"venue"
},
  "geometry": {"coordinates":[6.8394851685,50.7548789978],"type":"Point"}
}