{
  "type": "Feature",
  "properties": {
    "iso:country":"DE",
    "sg:address":"Heinestr. 3",
    "sg:city":"Gr\u00fcnstadt",
    "sg:phone":"+49 6359/2815",
    "sg:postcode":"67269",
    "sg:province":"Rheinland-Pfalz",
    "wof:name":"Walter Bahrdt Tanzschule",
    "wof:placetype":"venue"
},
  "geometry": {"coordinates":[8.1678743362,49.5723342896],"type":"Point"}
}