{
  "type": "Feature",
  "properties": {
    "iso:country":"DE",
    "sg:address":"Bahnstr. 70",
    "sg:city":"Sulzbach",
    "sg:postcode":"65843",
    "sg:province":"Hessen",
    "wof:name":"Hbm Handwerk- Und Mittelstandsberatung Gmbh",
    "wof:placetype":"venue"
},
  "geometry": {"coordinates":[8.5215263367,50.1266784668],"type":"Point"}
}