{
  "type": "Feature",
  "properties": {
    "iso:country":"DE",
    "sg:address":"Das Steinfeld 2",
    "sg:city":"Wandersleben",
    "sg:phone":"+49 36202/82287",
    "sg:postcode":"99869",
    "sg:province":"Th\u00fcringen",
    "wof:name":"W. Grass Steuerberater",
    "wof:placetype":"venue"
},
  "geometry": {"coordinates":[10.8439674377,50.8912467957],"type":"Point"}
}