{
  "type": "Feature",
  "properties": {
    "iso:country":"DE",
    "sg:address":"Landgrabenstr. 52",
    "sg:city":"N\u00fcrnberg",
    "sg:postcode":"90443",
    "sg:province":"Bayern",
    "wof:name":"Wellh\u00f6fer Verwaltungs- Gesellschaft Mbh",
    "wof:placetype":"venue"
},
  "geometry": {"coordinates":[11.0686321259,49.4392433167],"type":"Point"}
}