{
  "type": "Feature",
  "properties": {
    "iso:country":"DE",
    "sg:address":"Querallee 41",
    "sg:city":"Kassel",
    "sg:phone":"+49 561/774738",
    "sg:postcode":"34119",
    "sg:province":"Hessen",
    "wof:name":"Heinrich Wolfram Rechtsanwalt",
    "wof:placetype":"venue"
},
  "geometry": {"coordinates":[9.4737911224,51.3163566589],"type":"Point"}
}