{
  "type": "Feature",
  "properties": {
    "iso:country":"DE",
    "sg:address":"Tj\u00e4rke",
    "sg:city":"Schob\u00fcll",
    "sg:phone":"+49 4841/61888",
    "sg:postcode":"25875",
    "wof:name":"Boy Klinck Rechtsanwalt Und Notar",
    "wof:placetype":"venue"
},
  "geometry": {"coordinates":[9.0071554184,54.5117111206],"type":"Point"}
}