{
  "type": "Feature",
  "properties": {
    "iso:country":"DE",
    "sg:address":"Latsch 7",
    "sg:city":"Weiden",
    "sg:phone":"+49 961/22384",
    "sg:postcode":"92637",
    "sg:province":"Bayern",
    "wof:name":"Gasthaus Zur Linde",
    "wof:placetype":"venue"
},
  "geometry": {"coordinates":[12.101392746,49.6708526611],"type":"Point"}
}