{
  "type": "Feature",
  "properties": {
    "iso:country":"DE",
    "sg:address":"Ki\u00dflingweg 50",
    "sg:city":"M\u00fchlacker",
    "sg:phone":"+49 7041/87000",
    "sg:postcode":"75417",
    "sg:province":"Baden-W\u00fcrttemberg",
    "wof:name":"Variata Dorit Lang Gmbh & Co",
    "wof:placetype":"venue"
},
  "geometry": {"coordinates":[8.86481,48.954632],"type":"Point"}
}