{
  "type": "Feature",
  "properties": {
    "iso:country":"DE",
    "sg:address":"Wilhelm-Leuschner-Str. 175",
    "sg:city":"Gro\u00df-Umstadt",
    "sg:phone":"+49 6078/3604",
    "sg:postcode":"64823",
    "sg:province":"Hessen",
    "wof:name":"K. W. Hiemenz",
    "wof:placetype":"venue"
},
  "geometry": {"coordinates":[8.976364,49.837975],"type":"Point"}
}