{
  "type": "Feature",
  "properties": {
    "iso:country":"DE",
    "sg:address":"Friedensstr. 20",
    "sg:city":"Frauensee",
    "sg:phone":"+49 36963/60583",
    "sg:postcode":"36460",
    "sg:province":"Th\u00fcringen",
    "wof:name":"Pferdestall",
    "wof:placetype":"venue"
},
  "geometry": {"coordinates":[10.1406297684,50.879119873],"type":"Point"}
}