{
  "type": "Feature",
  "properties": {
    "iso:country":"DE",
    "sg:address":"Wernersberg",
    "sg:city":"Wernersberg",
    "sg:phone":"+49 6346/8959",
    "sg:postcode":"76857",
    "sg:province":"Rheinland-Pfalz",
    "wof:name":"Sparkasse S\u00fcdliche Weinstr. Landau",
    "wof:placetype":"venue"
},
  "geometry": {"coordinates":[7.92317,49.18993],"type":"Point"}
}