{
  "type": "Feature",
  "properties": {
    "iso:country":"DE",
    "sg:address":"Herbert-Lewin-Str. 5::",
    "sg:city":"K\u00f6ln",
    "sg:phone":"+49 4922/140050",
    "sg:postcode":"50931",
    "sg:province":"Nordrhein-Westfalen",
    "wof:name":"Kassenaerztliche Bundesvereinigung",
    "wof:placetype":"venue"
},
  "geometry": {"coordinates":[6.922181,50.934189],"type":"Point"}
}