{
  "type": "Feature",
  "properties": {
    "iso:country":"DE",
    "sg:address":"R\u00f6thenstr. 34",
    "sg:city":"Forchheim",
    "sg:phone":"+49 9191/31590",
    "sg:postcode":"91301",
    "sg:province":"Bayern",
    "wof:name":"Reinhold Kraus Architekt",
    "wof:placetype":"venue"
},
  "geometry": {"coordinates":[11.036671,49.719315],"type":"Point"}
}