{
  "type": "Feature",
  "properties": {
    "iso:country":"DE",
    "sg:address":"Am Nordturm 5",
    "sg:city":"Voerde",
    "sg:phone":"+49 281/98710",
    "sg:postcode":"46562",
    "sg:province":"Nordrhein-Westfalen",
    "wof:name":"Planbau Planung Und Schl\u00fcsselfertiges Bauen Gmbh",
    "wof:placetype":"venue"
},
  "geometry": {"coordinates":[6.675429821,51.6335792542],"type":"Point"}
}