{
  "type": "Feature",
  "properties": {
    "iso:country":"DE",
    "sg:address":"Gerhart-Hauptmann-Str. 14",
    "sg:city":"Stralsund",
    "sg:phone":"+49 3831/390124",
    "sg:postcode":"18435",
    "sg:province":"Mecklenburg-Vorpommern",
    "wof:name":"Hotel S\u00fc\u00df",
    "wof:placetype":"venue"
},
  "geometry": {"coordinates":[13.0858802795,54.3216285706],"type":"Point"}
}