{
  "type": "Feature",
  "properties": {
    "iso:country":"DE",
    "sg:address":"Hauptstr. 189",
    "sg:city":"Wiesmoor",
    "sg:phone":"+49 4944/3767",
    "sg:postcode":"26639",
    "sg:province":"Niedersachsen",
    "wof:name":"Trend-line Holzum",
    "wof:placetype":"venue"
},
  "geometry": {"coordinates":[7.735442,53.414314],"type":"Point"}
}