{
  "type": "Feature",
  "properties": {
    "iso:country":"DE",
    "sg:address":"Hudering 21",
    "sg:city":"Salzkotten",
    "sg:phone":"+49 5258/940630",
    "sg:postcode":"33154",
    "sg:province":"Nordrhein-Westfalen",
    "wof:name":"Andrej Nowakowski Ingenieur",
    "wof:placetype":"venue"
},
  "geometry": {"coordinates":[8.5962705612,51.6618690491],"type":"Point"}
}