{
  "type": "Feature",
  "properties": {
    "iso:country":"DE",
    "sg:address":"Alfons-Oswald-Str. 5",
    "sg:city":"Ehrenkirchen",
    "sg:phone":"+49 7633/4890",
    "sg:postcode":"79238",
    "sg:province":"Baden-W\u00fcrttemberg",
    "wof:name":"Erwin Sieben",
    "wof:placetype":"venue"
},
  "geometry": {"coordinates":[7.7314009666,47.9379081726],"type":"Point"}
}