{
  "type": "Feature",
  "properties": {
    "iso:country":"DE",
    "sg:address":"Elektronstr. 7",
    "sg:city":"Bitterfeld",
    "sg:phone":"+49 3493/72020",
    "sg:postcode":"06749",
    "sg:province":"Sachsen-Anhalt",
    "wof:name":"System-instandsetzung Und Service Gesellschaft Mbh",
    "wof:placetype":"venue"
},
  "geometry": {"coordinates":[12.305504,51.615379],"type":"Point"}
}