{
  "type": "Feature",
  "properties": {
    "iso:country":"DE",
    "sg:address":"Judith-Platter-Weg 2",
    "sg:city":"Berchtesgaden",
    "sg:phone":"+49 8652/3296",
    "sg:postcode":"83471",
    "sg:province":"Bayern",
    "wof:name":"G\u00e4stehaus H. Und M. Weiss",
    "wof:placetype":"venue"
},
  "geometry": {"coordinates":[13.0020542145,47.6186981201],"type":"Point"}
}