{
  "type": "Feature",
  "properties": {
    "iso:country":"DE",
    "sg:address":"Ofenerfelder Str. 40b",
    "sg:city":"Wiefelstede",
    "sg:phone":"+49 441/961870",
    "sg:postcode":"26215",
    "sg:province":"Niedersachsen",
    "wof:name":"Klaus Stiedenrod",
    "wof:placetype":"venue"
},
  "geometry": {"coordinates":[8.1861124039,53.1946983337],"type":"Point"}
}