{
  "type": "Feature",
  "properties": {
    "iso:country":"DE",
    "sg:address":"Penkuner Str. 3",
    "sg:city":"Krackow",
    "sg:postcode":"17329",
    "sg:province":"Mecklenburg-Vorpommern",
    "wof:name":"Krabo Handels Gmbh",
    "wof:placetype":"venue"
},
  "geometry": {"coordinates":[14.265989,53.343212],"type":"Point"}
}