{
  "type": "Feature",
  "properties": {
    "iso:country":"DE",
    "sg:address":"Crawinkler Str. 22",
    "sg:city":"Oberhof",
    "sg:postcode":"98559",
    "sg:province":"Th\u00fcringen",
    "wof:name":"Haus Am Sonnenhang Gmbh",
    "wof:placetype":"venue"
},
  "geometry": {"coordinates":[10.722635,50.709644],"type":"Point"}
}