{
  "type": "Feature",
  "properties": {
    "iso:country":"DE",
    "sg:address":"Lothringer Str. 23",
    "sg:city":"Mengen",
    "sg:phone":"+49 4975/7276140",
    "sg:postcode":"88512",
    "sg:province":"Baden-W\u00fcrttemberg",
    "wof:name":"Heinz-dieter Schunk Gmbh & Co. Spanntechnik Kg",
    "wof:placetype":"venue"
},
  "geometry": {"coordinates":[9.337014,48.056988],"type":"Point"}
}