{
  "type": "Feature",
  "properties": {
    "iso:country":"DE",
    "sg:address":"Nr. 20",
    "sg:city":"Leislau",
    "sg:postcode":"06618",
    "sg:province":"Sachsen-Anhalt",
    "wof:name":"Ev.-luth. Kirche Leislau",
    "wof:placetype":"venue"
},
  "geometry": {"coordinates":[11.8205280304,51.1440734863],"type":"Point"}
}