{
  "type": "Feature",
  "properties": {
    "iso:country":"DE",
    "sg:address":"Am Molkenborn 71",
    "sg:city":"B\u00fcdingen",
    "sg:phone":"+49 6042/4880",
    "sg:postcode":"63654",
    "sg:province":"Hessen",
    "wof:name":"Alfred Zimmermann Gmbh",
    "wof:placetype":"venue"
},
  "geometry": {"coordinates":[9.109377,50.295895],"type":"Point"}
}