{
  "type": "Feature",
  "properties": {
    "iso:country":"DE",
    "sg:address":"Pillauer Str.",
    "sg:city":"Sittensen",
    "sg:phone":"+49 4282/5678",
    "sg:postcode":"27419",
    "sg:province":"Niedersachsen",
    "wof:name":"Heimathaus Sittensen",
    "wof:placetype":"venue"
},
  "geometry": {"coordinates":[9.516375,53.282005],"type":"Point"}
}