{
  "type": "Feature",
  "properties": {
    "iso:country":"DE",
    "sg:address":"Yorckstr. 17",
    "sg:city":"Berlin",
    "sg:phone":"+49 30/88677356",
    "sg:postcode":"10965",
    "sg:province":"Berlin",
    "wof:name":"Blitzbau Gmbh",
    "wof:placetype":"venue"
},
  "geometry": {"coordinates":[13.382059,52.493542],"type":"Point"}
}