{
  "type": "Feature",
  "properties": {
    "iso:country":"DE",
    "sg:address":"Wellesweilerstr. 10",
    "sg:city":"Neunkirchen",
    "sg:phone":"+49 6821/22636",
    "sg:postcode":"66538",
    "sg:province":"Saarland",
    "wof:name":"Hoseneck Hahn Gmbh",
    "wof:placetype":"venue"
},
  "geometry": {"coordinates":[7.176451,49.351028],"type":"Point"}
}