{
  "type": "Feature",
  "properties": {
    "iso:country":"DE",
    "sg:address":"Grimpingstr. 40",
    "sg:city":"Coesfeld",
    "sg:phone":"+49 2541/5760",
    "sg:postcode":"48653",
    "sg:province":"Nordrhein-Westfalen",
    "wof:name":"Walfort",
    "wof:placetype":"venue"
},
  "geometry": {"coordinates":[7.174297,51.936497],"type":"Point"}
}