{
  "type": "Feature",
  "properties": {
    "iso:country":"DE",
    "sg:address":"Robert-Perthel-Str. 72",
    "sg:city":"K\u00f6ln",
    "sg:phone":"+49 221/5951021",
    "sg:postcode":"50739",
    "sg:province":"Nordrhein-Westfalen",
    "wof:name":"Gramyco Arbeitsb\u00dchnen Handels- U. Vermietungs Gmbh",
    "wof:placetype":"venue"
},
  "geometry": {"coordinates":[6.90912,50.988693],"type":"Point"}
}