{
  "type": "Feature",
  "properties": {
    "iso:country":"DE",
    "sg:address":"Gr\u00fcne M\u00fchle 90",
    "sg:city":"H\u00f6xter",
    "sg:phone":"+49 5271/980",
    "sg:postcode":"37671",
    "sg:province":"Nordrhein-Westfalen",
    "wof:name":"Krankenhausvollapotheke In Der Weserbergland-klinik",
    "wof:placetype":"venue"
},
  "geometry": {"coordinates":[9.374007,51.78833],"type":"Point"}
}