{
  "type": "Feature",
  "properties": {
    "iso:country":"DE",
    "sg:address":"Zum Sallr\u00f6gen 12",
    "sg:city":"Bosau",
    "sg:phone":"+49 4527/318",
    "sg:postcode":"23715",
    "sg:province":"Schleswig-Holstein",
    "wof:name":"Bauernstube",
    "wof:placetype":"venue"
},
  "geometry": {"coordinates":[10.4818239212,54.0878067017],"type":"Point"}
}