{
  "type": "Feature",
  "properties": {
    "iso:country":"DE",
    "sg:address":"Kupferm\u00fchle",
    "sg:city":"Bischheim",
    "sg:phone":"+49 6352/4060",
    "sg:postcode":"67294",
    "sg:province":"Rheinland-Pfalz",
    "wof:name":"Karl Bindewald Kupferm\u00fchle Gmbh",
    "wof:placetype":"venue"
},
  "geometry": {"coordinates":[8.038243,49.669281],"type":"Point"}
}