{
  "type": "Feature",
  "properties": {
    "iso:country":"DE",
    "sg:address":"Kirchstr. 605",
    "sg:city":"Helgoland",
    "sg:phone":"+49 4725/811212",
    "sg:postcode":"27498",
    "sg:province":"Schleswig-Holstein",
    "wof:name":"Horst Siemens",
    "wof:placetype":"venue"
},
  "geometry": {"coordinates":[7.884499073,54.1824417114],"type":"Point"}
}