{
  "type": "Feature",
  "properties": {
    "iso:country":"DE",
    "sg:address":"Wollweberstr. 3",
    "sg:city":"Demmin",
    "sg:phone":"+49 3998/223443",
    "sg:postcode":"17109",
    "sg:province":"Mecklenburg-Vorpommern",
    "wof:name":"Fahrradhaus Kurt M\u00fcller",
    "wof:placetype":"venue"
},
  "geometry": {"coordinates":[13.041682,53.903343],"type":"Point"}
}