{
  "type": "Feature",
  "properties": {
    "iso:country":"DE",
    "sg:address":"Am Kanal 5-7",
    "sg:city":"Wittingen",
    "sg:phone":"+49 5831/29200",
    "sg:postcode":"29378",
    "sg:province":"Niedersachsen",
    "wof:name":"Oel-hinze Verwaltungs Gmbh",
    "wof:placetype":"venue"
},
  "geometry": {"coordinates":[10.666856,52.723186],"type":"Point"}
}