{
  "type": "Feature",
  "properties": {
    "iso:country":"DE",
    "sg:address":"Dorfstr. 36",
    "sg:city":"Bad Endbach",
    "sg:phone":"+49 2776/7488",
    "sg:postcode":"35080",
    "sg:province":"Hessen",
    "wof:name":"Erhard Seitz",
    "wof:placetype":"venue"
},
  "geometry": {"coordinates":[8.4689941406,50.7388954163],"type":"Point"}
}