{
  "type": "Feature",
  "properties": {
    "iso:country":"DE",
    "sg:address":"Im Winkel 14",
    "sg:city":"Borchen",
    "sg:phone":"+49 5292/931245",
    "sg:postcode":"33178",
    "sg:province":"Nordrhein-Westfalen",
    "wof:name":"Agrarsservice Gerdes",
    "wof:placetype":"venue"
},
  "geometry": {"coordinates":[8.7621059418,51.6238441467],"type":"Point"}
}