{
  "type": "Feature",
  "properties": {
    "iso:country":"DE",
    "sg:address":"M\u00fchlstr. 18",
    "sg:city":"Zella-Mehlis",
    "sg:phone":"+49 3682/43133",
    "sg:postcode":"98544",
    "sg:province":"Th\u00fcringen",
    "wof:name":"Hut-eck Inh. Beate Schl\u00fctter",
    "wof:placetype":"venue"
},
  "geometry": {"coordinates":[10.6528358459,50.6603965759],"type":"Point"}
}