{
  "type": "Feature",
  "properties": {
    "iso:country":"DE",
    "sg:address":"Tanngasse 25",
    "sg:city":"Ruppertshofen",
    "sg:phone":"+49 7176/2115",
    "sg:postcode":"73577",
    "sg:province":"Baden-W\u00fcrttemberg",
    "wof:name":"Ulrich Reier",
    "wof:placetype":"venue"
},
  "geometry": {"coordinates":[9.810333252,48.8798103333],"type":"Point"}
}