{
  "type": "Feature",
  "properties": {
    "iso:country":"DE",
    "sg:address":"Neuenreuth",
    "sg:city":"Neuenreuth",
    "sg:phone":"+49 9203/344",
    "sg:postcode":"95512",
    "sg:province":"Bayern",
    "wof:name":"Raiffeisenbank Thurnauer Land Eg",
    "wof:placetype":"venue"
},
  "geometry": {"coordinates":[11.47136,50.021069],"type":"Point"}
}