{
  "type": "Feature",
  "properties": {
    "iso:country":"DE",
    "sg:address":"Schulstr. 7",
    "sg:city":"Vechelde",
    "sg:phone":"+49 5302/1425",
    "sg:postcode":"38159",
    "sg:province":"Niedersachsen",
    "wof:name":"Kurt Hoppenworth",
    "wof:placetype":"venue"
},
  "geometry": {"coordinates":[10.363699,52.270149],"type":"Point"}
}