{
  "type": "Feature",
  "properties": {
    "iso:country":"DE",
    "sg:address":"Kriegerheide 7",
    "sg:city":"Bad Salzuflen",
    "sg:phone":"+49 5222/73429",
    "sg:postcode":"32107",
    "sg:province":"Nordrhein-Westfalen",
    "wof:name":"Dreil\u00e4ndereck",
    "wof:placetype":"venue"
},
  "geometry": {"coordinates":[8.7047929764,52.0620956421],"type":"Point"}
}