{
  "type": "Feature",
  "properties": {
    "iso:country":"DE",
    "sg:address":"Von-der-Mark-Str. 66",
    "sg:city":"Duisburg",
    "sg:phone":"+49 203/443523",
    "sg:postcode":"47137",
    "sg:province":"Nordrhein-Westfalen",
    "wof:name":"G. Wilken",
    "wof:placetype":"venue"
},
  "geometry": {"coordinates":[6.7736458778,51.4674911499],"type":"Point"}
}