{
  "type": "Feature",
  "properties": {
    "iso:country":"DE",
    "sg:address":"Haarbachtalstr. 97",
    "sg:city":"Aachen",
    "sg:phone":"+49 241/166398",
    "sg:postcode":"52080",
    "sg:province":"Nordrhein-Westfalen",
    "wof:name":"R. Beckert",
    "wof:placetype":"venue"
},
  "geometry": {"coordinates":[6.12961,50.793598],"type":"Point"}
}