{
  "type": "Feature",
  "properties": {
    "iso:country":"DE",
    "sg:address":"Rechbergstr. 3a",
    "sg:city":"Gruibingen",
    "sg:phone":"+49 7335/96660",
    "sg:postcode":"73344",
    "sg:province":"Baden-W\u00fcrttemberg",
    "wof:name":"Peter Zennegg",
    "wof:placetype":"venue"
},
  "geometry": {"coordinates":[9.648284,48.589157],"type":"Point"}
}