{
  "type": "Feature",
  "properties": {
    "iso:country":"DE",
    "sg:address":"Sch\u00f6nauer Strasse 97",
    "sg:city":"Lindau - Sch\u00f6nau",
    "sg:phone":"+49 8382",
    "sg:postcode":"88131",
    "sg:province":"Bayern",
    "wof:name":"Hotel Restaurant Bulligan",
    "wof:placetype":"venue"
},
  "geometry": {"coordinates":[9.6631765366,47.5723228455],"type":"Point"}
}