{
  "type": "Feature",
  "properties": {
    "iso:country":"DE",
    "sg:address":"Hohenfelsbachstr. 1b",
    "sg:city":"Hahnst\u00e4tten",
    "sg:phone":"+49 4964/3092520",
    "sg:postcode":"65623",
    "sg:province":"Rheinland-Pfalz",
    "wof:name":"Zimmermann + Reichel Gmbh",
    "wof:placetype":"venue"
},
  "geometry": {"coordinates":[8.063846,50.30442],"type":"Point"}
}