{
  "type": "Feature",
  "properties": {
    "iso:country":"DE",
    "sg:address":"Lager Str. 28",
    "sg:city":"Neuenhaus",
    "sg:phone":"+49 5941/1055",
    "sg:postcode":"49828",
    "sg:province":"Niedersachsen",
    "wof:name":"Roosen Und Eule Rechtsanw\u00e4lte Und Notare",
    "wof:placetype":"venue"
},
  "geometry": {"coordinates":[6.9628062248,52.4935112],"type":"Point"}
}