{
  "type": "Feature",
  "properties": {
    "iso:country":"DE",
    "sg:address":"Osannstr 11",
    "sg:city":"Darmstadt",
    "sg:phone":"+49 6151/49880",
    "sg:postcode":"64285",
    "sg:province":"Hessen",
    "wof:name":"Gerasch Communication Gmbh & Co Kg",
    "wof:placetype":"venue"
},
  "geometry": {"coordinates":[8.662769,49.864796],"type":"Point"}
}