{
  "type": "Feature",
  "properties": {
    "iso:country":"DE",
    "sg:address":"Bahnhofstr. 3",
    "sg:city":"Raddusch",
    "sg:phone":"+49 35433/2050",
    "sg:postcode":"03226",
    "sg:province":"Brandenburg",
    "wof:name":"D. Klauck Immobilienmakler",
    "wof:placetype":"venue"
},
  "geometry": {"coordinates":[14.0640296936,51.7741203308],"type":"Point"}
}