{
  "type": "Feature",
  "properties": {
    "iso:country":"DE",
    "sg:address":"Dientzenhoferstr. 48",
    "sg:city":"Bamberg",
    "sg:phone":"+49 951/24936",
    "sg:postcode":"96047",
    "sg:province":"Bayern",
    "wof:name":"J. Herbst Garten- Und Landschafts-",
    "wof:placetype":"venue"
},
  "geometry": {"coordinates":[10.900849,49.886234],"type":"Point"}
}