{
  "type": "Feature",
  "properties": {
    "iso:country":"DE",
    "sg:address":"Bertholdstr. 40",
    "sg:city":"Pforzheim",
    "sg:phone":"+49 7231/105967",
    "sg:postcode":"75177",
    "sg:province":"Baden-W\u00fcrttemberg",
    "wof:name":"D. Zanetti",
    "wof:placetype":"venue"
},
  "geometry": {"coordinates":[8.7056589127,48.8973808289],"type":"Point"}
}