{
  "type": "Feature",
  "properties": {
    "iso:country":"DE",
    "sg:address":"Bautzner Str. 130",
    "sg:city":"Kamenz",
    "sg:phone":"+49 35783/8760",
    "sg:postcode":"01917",
    "sg:province":"Sachsen",
    "wof:name":"J\u00f6rg Steike Ingenieurb\u00fcro",
    "wof:placetype":"venue"
},
  "geometry": {"coordinates":[14.112686,51.264362],"type":"Point"}
}