{
  "type": "Feature",
  "properties": {
    "iso:country":"DE",
    "sg:address":"Am H\u00fchnerberg 7",
    "sg:city":"Kelkheim / Taunus",
    "sg:phone":"+49 6195/910591",
    "sg:postcode":"65779",
    "sg:province":"Hessen",
    "wof:name":"Roser | Einrichtungshaus - Manufaktur",
    "wof:placetype":"venue"
},
  "geometry": {"coordinates":[8.435675,50.143162],"type":"Point"}
}