{
  "type": "Feature",
  "properties": {
    "iso:country":"DE",
    "sg:address":"Carl-Heinrich-Becker-Weg 11",
    "sg:city":"Berlin",
    "sg:phone":"+49 30/7926009",
    "sg:postcode":"12165",
    "sg:province":"Berlin",
    "wof:name":"Claus M\u00fcller-matthies B\u00fcro F\u00fcr Statik",
    "wof:placetype":"venue"
},
  "geometry": {"coordinates":[13.3111715317,52.4573364258],"type":"Point"}
}