{
  "type": "Feature",
  "properties": {
    "iso:country":"DE",
    "sg:address":"Einsteinstr. 1",
    "sg:city":"M\u00fcnchen",
    "sg:phone":"+49 89/4194340",
    "sg:postcode":"81675",
    "sg:province":"Bayern",
    "wof:name":"Bayerische Versorgungskammer Bayer. Ingenieurversorgung-bau",
    "wof:placetype":"venue"
},
  "geometry": {"coordinates":[11.5987930298,48.135848999],"type":"Point"}
}