{
  "type": "Feature",
  "properties": {
    "iso:country":"DE",
    "sg:address":"K\u00f6nigstr. 1",
    "sg:city":"Krefeld",
    "sg:phone":"+49 2151/613074",
    "sg:postcode":"47798",
    "sg:province":"Nordrhein-Westfalen",
    "wof:name":"Brust & Blum Wertpapier- Handelsunternehmen Consult Und",
    "wof:placetype":"venue"
},
  "geometry": {"coordinates":[6.566177,51.328289],"type":"Point"}
}