{
  "type": "Feature",
  "properties": {
    "iso:country":"DE",
    "sg:address":"Burkhardt-und-Weber-Str. 63",
    "sg:city":"Reutlingen",
    "sg:phone":"+49 7121/38790",
    "sg:postcode":"72760",
    "sg:province":"Baden-W\u00fcrttemberg",
    "wof:name":"Bestattungsgenossenschaft Der Schreinermeister",
    "wof:placetype":"venue"
},
  "geometry": {"coordinates":[9.210645,48.500431],"type":"Point"}
}