{
  "type": "Feature",
  "properties": {
    "iso:country":"DE",
    "sg:address":"Spessartstr. 2 - 4",
    "sg:city":"Kelkheim",
    "sg:phone":"+49 6195/62977",
    "sg:postcode":"65779",
    "sg:province":"Hessen",
    "wof:name":"Rich Rags Of West Germany U. Indian Souvenirs",
    "wof:placetype":"venue"
},
  "geometry": {"coordinates":[8.433478,50.144508],"type":"Point"}
}