{
  "type": "Feature",
  "properties": {
    "iso:country":"DE",
    "sg:address":"Ahornweg 1",
    "sg:city":"L\u00fcder",
    "sg:phone":"+49 5824/812",
    "sg:postcode":"29394",
    "sg:province":"Niedersachsen",
    "wof:name":"Axel Kusserow Ingenieur",
    "wof:placetype":"venue"
},
  "geometry": {"coordinates":[10.7091970444,52.8021354675],"type":"Point"}
}