{
  "type": "Feature",
  "properties": {
    "iso:country":"DE",
    "sg:address":"Brunhamstr. 21",
    "sg:city":"M\u00fcnchen",
    "sg:postcode":"81249",
    "sg:province":"Bayern",
    "wof:name":"Cnc-service Fr\u00e4steile Und Ablaufprogramme Gmbh",
    "wof:placetype":"venue"
},
  "geometry": {"coordinates":[11.425298,48.140663],"type":"Point"}
}