{
  "type": "Feature",
  "properties": {
    "iso:country":"DE",
    "sg:address":"Marktstr. 15",
    "sg:city":"Eiterfeld",
    "sg:phone":"+49 6672/329",
    "sg:postcode":"36132",
    "sg:province":"Hessen",
    "wof:name":"Adolf Hartmann",
    "wof:placetype":"venue"
},
  "geometry": {"coordinates":[9.7939252853,50.7618637085],"type":"Point"}
}