{
  "type": "Feature",
  "properties": {
    "iso:country":"DE",
    "sg:address":"Kleinwellenfeld 41",
    "sg:city":"Ahlen",
    "sg:phone":"+49 2382",
    "sg:postcode":"59229",
    "sg:province":"Nordrhein-Westfalen",
    "wof:name":"Sportliches Autozubeh\u00f6r Von Car-styling Stiemer",
    "wof:placetype":"venue"
},
  "geometry": {"coordinates":[7.920173,51.710701],"type":"Point"}
}