{
  "type": "Feature",
  "properties": {
    "iso:country":"DE",
    "sg:address":"Schleizer Str. 34",
    "sg:city":"Oelsnitz",
    "sg:phone":"+49 37421/22061",
    "sg:postcode":"08606",
    "sg:province":"Sachsen",
    "wof:name":"Kurt Todt",
    "wof:placetype":"venue"
},
  "geometry": {"coordinates":[12.163982,50.416954],"type":"Point"}
}