{
  "type": "Feature",
  "properties": {
    "iso:country":"DE",
    "sg:address":"An der Br\u00fccke 3",
    "sg:city":"L\u00fcbz",
    "sg:phone":"+49 38731/20714",
    "sg:postcode":"19386",
    "sg:province":"Mecklenburg-Vorpommern",
    "wof:name":"Hagebaumarkt Gmbh & Co. Kg",
    "wof:placetype":"venue"
},
  "geometry": {"coordinates":[12.043282,53.46447],"type":"Point"}
}