{
  "type": "Feature",
  "properties": {
    "iso:country":"DE",
    "sg:address":"Neuwerk 7",
    "sg:city":"Halle",
    "sg:phone":"+49 345/7751900",
    "sg:postcode":"06003",
    "sg:province":"Niedersachsen",
    "wof:name":"Institut Ca&d, Computer Art Und Design",
    "wof:placetype":"venue"
},
  "geometry": {"coordinates":[11.96581,51.48217],"type":"Point"}
}