{
  "type": "Feature",
  "properties": {
    "iso:country":"DE",
    "sg:address":"Hauptstr. 107",
    "sg:city":"Steina",
    "sg:phone":"+49 35955/42042",
    "sg:postcode":"01920",
    "sg:province":"Sachsen",
    "wof:name":"Andrea Becker",
    "wof:placetype":"venue"
},
  "geometry": {"coordinates":[14.0375776291,51.2110176086],"type":"Point"}
}