{
  "type": "Feature",
  "properties": {
    "iso:country":"DE",
    "sg:address":"Werth 78",
    "sg:city":"Wuppertal",
    "sg:phone":"+49 202/591639",
    "sg:postcode":"42275",
    "sg:province":"Nordrhein-Westfalen",
    "wof:name":"Fuchs Gmbh Drogeriemarkt",
    "wof:placetype":"venue"
},
  "geometry": {"coordinates":[7.203691,51.272003],"type":"Point"}
}