{
  "type": "Feature",
  "properties": {
    "iso:country":"DE",
    "sg:address":"Goethestr. 2",
    "sg:city":"Mendig",
    "sg:phone":"+49 2652/4450",
    "sg:postcode":"56743",
    "sg:province":"Rheinland-Pfalz",
    "wof:name":"Erich Waldecker Inh. Gabriele Waldecker",
    "wof:placetype":"venue"
},
  "geometry": {"coordinates":[7.287635,50.373055],"type":"Point"}
}