{
  "type": "Feature",
  "properties": {
    "iso:country":"DE",
    "sg:address":"Hesedorfer Str. 2",
    "sg:city":"Schee\u00dfel",
    "sg:phone":"+49 4263/540",
    "sg:postcode":"27383",
    "sg:province":"Niedersachsen",
    "wof:name":"Rolf Behrens",
    "wof:placetype":"venue"
},
  "geometry": {"coordinates":[9.381586,53.198483],"type":"Point"}
}