{
  "type": "Feature",
  "properties": {
    "iso:country":"DE",
    "sg:address":"Panoramastr. 38",
    "sg:city":"Griesingen",
    "sg:phone":"+49 7391/71818",
    "sg:postcode":"89608",
    "sg:province":"Baden-W\u00fcrttemberg",
    "wof:name":"J. Bause Zahn\u00e4rztebedarf",
    "wof:placetype":"venue"
},
  "geometry": {"coordinates":[9.777123,48.267857],"type":"Point"}
}