{
  "type": "Feature",
  "properties": {
    "iso:country":"DE",
    "sg:address":"Bahnhofstr. 3",
    "sg:city":"Feldkirchen",
    "sg:phone":"+49 89/9043085",
    "sg:postcode":"85622",
    "sg:province":"Bayern",
    "wof:name":"Depol Trading Gmbh",
    "wof:placetype":"venue"
},
  "geometry": {"coordinates":[11.730976,48.148151],"type":"Point"}
}