{
  "type": "Feature",
  "properties": {
    "iso:country":"DE",
    "sg:address":"Landgraf-Philipp-Platz 4-6",
    "sg:city":"Gie\u00dfen",
    "sg:postcode":"35390",
    "sg:province":"Hessen",
    "wof:name":"Geol. Pal\u00e4ontol.-institut Bibliothek",
    "wof:placetype":"venue"
},
  "geometry": {"coordinates":[8.676334,50.586613],"type":"Point"}
}