{
  "type": "Feature",
  "properties": {
    "iso:country":"DE",
    "sg:address":"Kuglerstr. 3",
    "sg:city":"Pfreimd",
    "sg:phone":"+49 9606/492",
    "sg:postcode":"92536",
    "sg:province":"Bayern",
    "wof:name":"Dietmar Hinerasky Drogerie",
    "wof:placetype":"venue"
},
  "geometry": {"coordinates":[12.185031,49.487774],"type":"Point"}
}