{
  "type": "Feature",
  "properties": {
    "iso:country":"DE",
    "sg:address":"Weiherstr. 1",
    "sg:city":"Hallstadt",
    "sg:phone":"+49 951/75979",
    "sg:postcode":"96103",
    "sg:province":"Bayern",
    "wof:name":"I. Und Erich R\u00f6\u00dfl",
    "wof:placetype":"venue"
},
  "geometry": {"coordinates":[10.8572149277,49.9312667847],"type":"Point"}
}