{
  "type": "Feature",
  "properties": {
    "iso:country":"DE",
    "sg:address":"Dr.-Allende-Str. 6",
    "sg:city":"Ferdinandshof",
    "sg:phone":"+49 39778/20720",
    "sg:postcode":"17379",
    "sg:province":"Mecklenburg-Vorpommern",
    "wof:name":"K\u00e4serei Gmbh",
    "wof:placetype":"venue"
},
  "geometry": {"coordinates":[13.882414,53.65765],"type":"Point"}
}