{
  "type": "Feature",
  "properties": {
    "iso:country":"DE",
    "sg:address":"Buchhorster Weg 2-10",
    "sg:city":"Lauenburg",
    "sg:phone":"+49 4153/590661",
    "sg:postcode":"21481",
    "sg:province":"Schleswig-Holstein",
    "wof:name":"Hanse-betonvertriebs- Union Gmbh",
    "wof:placetype":"venue"
},
  "geometry": {"coordinates":[10.5794696808,53.3770904541],"type":"Point"}
}