{
  "type": "Feature",
  "properties": {
    "iso:country":"DE",
    "sg:address":"Adenauerallee 24",
    "sg:city":"Oberursel",
    "sg:phone":"+49 6171/52105",
    "sg:postcode":"61440",
    "sg:province":"Hessen",
    "wof:name":"Pizzeria La Stalla",
    "wof:placetype":"venue"
},
  "geometry": {"coordinates":[8.5835075378,50.2000732422],"type":"Point"}
}