{
  "type": "Feature",
  "properties": {
    "iso:country":"DE",
    "sg:address":"Europaallee 3",
    "sg:city":"Norderstedt",
    "sg:postcode":"22850",
    "sg:province":"Schleswig-Holstein",
    "wof:name":"Ahrens Gmbh Templin",
    "wof:placetype":"venue"
},
  "geometry": {"coordinates":[9.9872713089,53.6816444397],"type":"Point"}
}