{
  "type": "Feature",
  "properties": {
    "iso:country":"DE",
    "sg:address":"Hofweg 87",
    "sg:city":"Hamburg",
    "sg:phone":"+49 40/2205151",
    "sg:postcode":"22085",
    "sg:province":"Hamburg",
    "wof:name":"Edmund Kripgans",
    "wof:placetype":"venue"
},
  "geometry": {"coordinates":[10.014646,53.576981],"type":"Point"}
}