{
  "type": "Feature",
  "properties": {
    "iso:country":"DE",
    "sg:address":"Langmannskamp 6",
    "sg:city":"Essen",
    "sg:phone":"+49 201/513012",
    "sg:postcode":"45276",
    "sg:province":"Nordrhein-Westfalen",
    "wof:name":"R. Bach",
    "wof:placetype":"venue"
},
  "geometry": {"coordinates":[7.060544014,51.4478187561],"type":"Point"}
}