{
  "type": "Feature",
  "properties": {
    "iso:country":"DE",
    "sg:address":"Industriestr. 6/45",
    "sg:city":"Friedeburg",
    "sg:phone":"+49 4944/6594840",
    "sg:postcode":"26446",
    "sg:province":"Niedersachsen",
    "wof:name":"Angiokard Medizintechnik Vertrieb Gmbh & Co Kg",
    "wof:placetype":"venue"
},
  "geometry": {"coordinates":[7.807489872,53.4494438171],"type":"Point"}
}