{
  "type": "Feature",
  "properties": {
    "iso:country":"DE",
    "sg:address":"Neudeker Str. 8 a",
    "sg:city":"Neutraubling",
    "sg:phone":"+49 9401/2037",
    "sg:postcode":"93073",
    "sg:province":"Bayern",
    "wof:name":"Praxis Dr. Med. B\u00e4uml Und Dr. Med. Kelly",
    "wof:placetype":"venue"
},
  "geometry": {"coordinates":[12.1994304657,48.9879722595],"type":"Point"}
}