{
  "type": "Feature",
  "properties": {
    "iso:country":"DE",
    "sg:address":"Beckumer Str. 38",
    "sg:city":"Warendorf",
    "sg:phone":"+49 2581/96982",
    "sg:postcode":"48231",
    "sg:province":"Nordrhein-Westfalen",
    "wof:name":"Behaton Gmbh & Co. Kg",
    "wof:placetype":"venue"
},
  "geometry": {"coordinates":[8.0162801743,51.9439506531],"type":"Point"}
}