{
  "type": "Feature",
  "properties": {
    "iso:country":"DE",
    "sg:address":"Adlerstr. 33",
    "sg:city":"Wiesbaden",
    "sg:phone":"+49 611/51739",
    "sg:postcode":"65183",
    "sg:province":"Hessen",
    "wof:name":"Pussycats",
    "wof:placetype":"venue"
},
  "geometry": {"coordinates":[8.2367086411,50.0862998962],"type":"Point"}
}