{
  "type": "Feature",
  "properties": {
    "iso:country":"DE",
    "sg:address":"Schillerstr. 41",
    "sg:city":"Selb",
    "sg:phone":"+49 9287/78905",
    "sg:postcode":"95100",
    "sg:province":"Bayern",
    "wof:name":"Bayerische Hypotheken-und Wechsel-, Bank Ag",
    "wof:placetype":"venue"
},
  "geometry": {"coordinates":[12.133724,50.172043],"type":"Point"}
}