{
  "type": "Feature",
  "properties": {
    "iso:country":"DE",
    "sg:address":"W\u00fcrttembergerstr 24",
    "sg:city":"Fridingen",
    "sg:phone":"+49 7463/7227",
    "sg:postcode":"78567",
    "sg:province":"Baden-W\u00fcrttemberg",
    "wof:name":"Fellner Gmbh",
    "wof:placetype":"venue"
},
  "geometry": {"coordinates":[8.9197072983,48.0178108215],"type":"Point"}
}