{
  "type": "Feature",
  "properties": {
    "iso:country":"DE",
    "sg:address":"Buchrainweg 130",
    "sg:city":"Offenbach",
    "sg:phone":"+49 69/83837147",
    "sg:postcode":"63069",
    "sg:province":"Hessen",
    "wof:name":"Jolo Fashion Gmbh",
    "wof:placetype":"venue"
},
  "geometry": {"coordinates":[8.7416133881,50.0900382996],"type":"Point"}
}