{
  "type": "Feature",
  "properties": {
    "iso:country":"DE",
    "sg:address":"Stauffenbergstr 14-20",
    "sg:city":"Leverkusen",
    "sg:phone":"+49 2171/70700",
    "sg:postcode":"51379",
    "sg:province":"Nordrhein-Westfalen",
    "wof:name":"Garcia Gmbh",
    "wof:placetype":"venue"
},
  "geometry": {"coordinates":[7.011305,51.067944],"type":"Point"}
}