{
  "type": "Feature",
  "properties": {
    "iso:country":"DE",
    "sg:address":"Kellers Ziegelei 2",
    "sg:city":"Gera",
    "sg:phone":"+49 365/23083",
    "sg:postcode":"07554",
    "sg:province":"Th\u00fcringen",
    "wof:name":"J\u00fcrgen Hebestreit",
    "wof:placetype":"venue"
},
  "geometry": {"coordinates":[-83.73846399999999,43.38332],"type":"Point"}
}