{
  "type": "Feature",
  "properties": {
    "iso:country":"DE",
    "sg:address":"J\u00e4gerstr. 79",
    "sg:city":"D\u00fcsseldorf",
    "sg:phone":"+49 211/2611997",
    "sg:postcode":"40231",
    "sg:province":"Nordrhein-Westfalen",
    "wof:name":"Klaus Schelat",
    "wof:placetype":"venue"
},
  "geometry": {"coordinates":[6.8405618668,51.2064628601],"type":"Point"}
}