{
  "type": "Feature",
  "properties": {
    "iso:country":"DE",
    "sg:address":"Hinterm Hauptbahnhof 6c",
    "sg:city":"Karlsruhe",
    "sg:phone":"+49 721/3841443",
    "sg:postcode":"76137",
    "sg:province":"Baden-W\u00fcrttemberg",
    "wof:name":"Tsunami",
    "wof:placetype":"venue"
},
  "geometry": {"coordinates":[8.398891449,48.9912719727],"type":"Point"}
}