{
  "type": "Feature",
  "properties": {
    "iso:country":"DE",
    "sg:address":"Am Bahnhof 20A",
    "sg:city":"Dieburg",
    "sg:phone":"+49 6071/5239",
    "sg:postcode":"64807",
    "sg:province":"Hessen",
    "wof:name":"R & D Feuer-schutz- Technik Gmbh",
    "wof:placetype":"venue"
},
  "geometry": {"coordinates":[8.84304142,49.9030685425],"type":"Point"}
}