{
  "type": "Feature",
  "properties": {
    "iso:country":"DE",
    "sg:address":"Kirchenstr. 15",
    "sg:city":"B\u00fcdelsdorf",
    "sg:phone":"+49 4331/31921",
    "sg:postcode":"24782",
    "sg:province":"Schleswig-Holstein",
    "wof:name":"Heinrich Fuchs",
    "wof:placetype":"venue"
},
  "geometry": {"coordinates":[9.6609487534,54.3152389526],"type":"Point"}
}