{
  "type": "Feature",
  "properties": {
    "iso:country":"DE",
    "sg:city":"Bremen",
    "sg:postcode":"28044",
    "sg:province":"Bremen",
    "wof:name":"Vis@vis - Seitensprung Agentur",
    "wof:placetype":"venue"
},
  "geometry": {"coordinates":[8.80708,53.074982],"type":"Point"}
}