{
  "type": "Feature",
  "properties": {
    "iso:country":"DE",
    "sg:address":"Freiberger Str. 11",
    "sg:city":"Niedersch\u00f6na",
    "sg:phone":"+49 35209/20438",
    "sg:postcode":"09600",
    "sg:province":"Sachsen",
    "wof:name":"Niedersch\u00f6na",
    "wof:placetype":"venue"
},
  "geometry": {"coordinates":[13.4231739044,50.9630050659],"type":"Point"}
}