{
  "type": "Feature",
  "properties": {
    "iso:country":"DE",
    "sg:address":"Gartenstr. 17",
    "sg:city":"Aalen",
    "sg:phone":"+49 7361/61805",
    "sg:postcode":"73430",
    "sg:province":"Baden-W\u00fcrttemberg",
    "wof:name":"Aalener Schachtl",
    "wof:placetype":"venue"
},
  "geometry": {"coordinates":[10.0898313522,48.8357849121],"type":"Point"}
}