{
  "type": "Feature",
  "properties": {
    "iso:country":"DE",
    "sg:address":"Am Dobben 14",
    "sg:city":"Wiesmoor",
    "sg:phone":"+49 4944/7999",
    "sg:postcode":"26639",
    "sg:province":"Niedersachsen",
    "wof:name":"Kat Kunststoff- Anwendungs-gmbh",
    "wof:placetype":"venue"
},
  "geometry": {"coordinates":[7.755633,53.420063],"type":"Point"}
}