{
  "type": "Feature",
  "properties": {
    "iso:country":"DE",
    "sg:address":"Thiemanns Weg 18",
    "sg:city":"Buxtehude",
    "sg:phone":"+49 4161/3513",
    "sg:postcode":"21614",
    "sg:province":"Niedersachsen",
    "wof:name":"J. P. Simonsen Gmbh & Co. Kg",
    "wof:placetype":"venue"
},
  "geometry": {"coordinates":[9.7211227417,53.4704017639],"type":"Point"}
}