{
  "type": "Feature",
  "properties": {
    "iso:country":"DE",
    "sg:address":"Lebuser Chaussee 2a",
    "sg:city":"Frankfurt",
    "sg:phone":"+49 335/6802998",
    "sg:postcode":"15234",
    "sg:province":"Brandenburg",
    "wof:name":"Wlazlo-baumaschinen",
    "wof:placetype":"venue"
},
  "geometry": {"coordinates":[14.50869,52.370003],"type":"Point"}
}