{
  "type": "Feature",
  "properties": {
    "iso:country":"DE",
    "sg:address":"N\u00fcrnberger Str. 1",
    "sg:city":"Pleinfeld",
    "sg:phone":"+49 9144/748",
    "sg:postcode":"91785",
    "sg:province":"Bayern",
    "wof:name":"Alfred Sch\u00f6nlein",
    "wof:placetype":"venue"
},
  "geometry": {"coordinates":[10.988141,49.104027],"type":"Point"}
}