{
  "type": "Feature",
  "properties": {
    "iso:country":"DE",
    "sg:address":"Rosenweg 15",
    "sg:city":"Lollar",
    "sg:phone":"+49 6406/3407",
    "sg:postcode":"35457",
    "sg:province":"Hessen",
    "wof:name":"Erich Mank Gmbh & Co. Kg",
    "wof:placetype":"venue"
},
  "geometry": {"coordinates":[8.706239,50.662552],"type":"Point"}
}