{
  "type": "Feature",
  "properties": {
    "iso:country":"DE",
    "sg:address":"Hauptstr. 48",
    "sg:city":"Dietfurt",
    "sg:phone":"+49 8464/227",
    "sg:postcode":"92345",
    "sg:province":"Bayern",
    "wof:name":"Stadt-apotheke",
    "wof:placetype":"venue"
},
  "geometry": {"coordinates":[11.589646,49.034233],"type":"Point"}
}