{
  "type": "Feature",
  "properties": {
    "iso:country":"DE",
    "sg:address":"Kapellenweg 113",
    "sg:city":"Schermbeck",
    "sg:phone":"+49 2853/698",
    "sg:postcode":"46514",
    "sg:province":"Nordrhein-Westfalen",
    "wof:name":"Siegfried Mika",
    "wof:placetype":"venue"
},
  "geometry": {"coordinates":[6.8803510666,51.6827430725],"type":"Point"}
}