{
  "type": "Feature",
  "properties": {
    "iso:country":"DE",
    "sg:address":"Bahnhofstr. 8",
    "sg:city":"Vohenstrau\u00df",
    "sg:phone":"+49 9651/91144",
    "sg:postcode":"92648",
    "sg:province":"Bayern",
    "wof:name":"M. Vogt",
    "wof:placetype":"venue"
},
  "geometry": {"coordinates":[12.3406772614,49.625453949],"type":"Point"}
}