{
  "type": "Feature",
  "properties": {
    "iso:country":"DE",
    "sg:address":"Jordanstr. 1",
    "sg:city":"Leipzig",
    "sg:postcode":"04177",
    "sg:province":"Sachsen",
    "wof:name":"Jus Ag & Co. Ohg",
    "wof:placetype":"venue"
},
  "geometry": {"coordinates":[12.3251924515,51.3323402405],"type":"Point"}
}