{
  "type": "Feature",
  "properties": {
    "iso:country":"DE",
    "sg:address":"Gartenstr. 11",
    "sg:city":"Langenselbold",
    "sg:phone":"+49 6184/61198",
    "sg:postcode":"63505",
    "sg:province":"Hessen",
    "wof:name":"Thomas Glitza",
    "wof:placetype":"venue"
},
  "geometry": {"coordinates":[9.042766571,50.1771621704],"type":"Point"}
}