{
  "type": "Feature",
  "properties": {
    "iso:country":"DE",
    "sg:address":"Unterstr. 75",
    "sg:city":"Duisburg",
    "sg:phone":"+49 203/23560",
    "sg:postcode":"47051",
    "sg:province":"Nordrhein-Westfalen",
    "wof:name":"Femina Cabaret",
    "wof:placetype":"venue"
},
  "geometry": {"coordinates":[6.754742,51.433502],"type":"Point"}
}