{
  "type": "Feature",
  "properties": {
    "iso:country":"DE",
    "sg:address":"Boberstr. 5",
    "sg:city":"Dortmund",
    "sg:phone":"+49 231/258194",
    "sg:postcode":"44287",
    "sg:province":"Nordrhein-Westfalen",
    "wof:name":"Eiffert & Sohn Gmbh & Co. Kg",
    "wof:placetype":"venue"
},
  "geometry": {"coordinates":[7.55704,51.485645],"type":"Point"}
}