{
  "type": "Feature",
  "properties": {
    "iso:country":"DE",
    "sg:address":"Weststr. 31",
    "sg:city":"Melle",
    "sg:phone":"+49 5422/5682",
    "sg:postcode":"49324",
    "sg:province":"Niedersachsen",
    "wof:name":"Friedhelm M\u00e4scher",
    "wof:placetype":"venue"
},
  "geometry": {"coordinates":[8.3361768723,52.2078742981],"type":"Point"}
}