{
  "type": "Feature",
  "properties": {
    "iso:country":"DE",
    "sg:address":"Giesestr. 30",
    "sg:city":"Iserlohn",
    "sg:phone":"+49 2371/462901",
    "sg:postcode":"58636",
    "sg:province":"Nordrhein-Westfalen",
    "wof:name":"Stefan Rudewig E. K.",
    "wof:placetype":"venue"
},
  "geometry": {"coordinates":[7.701685,51.400997],"type":"Point"}
}