{
  "type": "Feature",
  "properties": {
    "iso:country":"DE",
    "sg:address":"Krefelder Str. 20",
    "sg:city":"Krefeld",
    "sg:phone":"+49 2151/731677",
    "sg:postcode":"47839",
    "sg:province":"Nordrhein-Westfalen",
    "wof:name":"Arnica-apotheke",
    "wof:placetype":"venue"
},
  "geometry": {"coordinates":[6.510149,51.372028],"type":"Point"}
}