{
  "type": "Feature",
  "properties": {
    "iso:country":"DE",
    "sg:city":"Gutenstein",
    "sg:phone":"+49 4975/70556",
    "sg:postcode":"72488",
    "sg:province":"Baden-W\u00fcrttemberg",
    "wof:name":"Volksbank Me\u00dfkirch Eg",
    "wof:placetype":"venue"
},
  "geometry": {"coordinates":[9.119375,48.077251],"type":"Point"}
}