{
  "type": "Feature",
  "properties": {
    "iso:country":"DE",
    "sg:address":"Brockzeteler Str. 11",
    "sg:city":"Aurich",
    "sg:phone":"+49 4941/10387",
    "sg:postcode":"26605",
    "sg:province":"Niedersachsen",
    "wof:name":"Jakob Schmidt",
    "wof:placetype":"venue"
},
  "geometry": {"coordinates":[7.575127,53.464409],"type":"Point"}
}