{
  "type": "Feature",
  "properties": {
    "iso:country":"DE",
    "sg:address":"Untere Dorfstr. 54",
    "sg:city":"Oderwitz",
    "sg:phone":"+49 35842/39869",
    "sg:postcode":"02791",
    "sg:province":"Sachsen",
    "wof:name":"Wolfgang Lindner",
    "wof:placetype":"venue"
},
  "geometry": {"coordinates":[14.744619,50.942894],"type":"Point"}
}