{
  "type": "Feature",
  "properties": {
    "iso:country":"DE",
    "sg:address":"Zeppelinweg 1",
    "sg:city":"Laatzen",
    "sg:phone":"+49 5102/70020",
    "sg:postcode":"30880",
    "sg:province":"Niedersachsen",
    "wof:name":"Zeppelin Baumaschinen Gmbh",
    "wof:placetype":"venue"
},
  "geometry": {"coordinates":[9.848312,52.273525],"type":"Point"}
}