{
  "type": "Feature",
  "properties": {
    "iso:country":"DE",
    "sg:address":"Am Forst 9",
    "sg:city":"Weiden",
    "sg:phone":"+49 961/37387",
    "sg:postcode":"92637",
    "sg:province":"Bayern",
    "wof:name":"Josef Lingl",
    "wof:placetype":"venue"
},
  "geometry": {"coordinates":[12.1601839066,49.7001647949],"type":"Point"}
}