{
  "type": "Feature",
  "properties": {
    "iso:country":"DE",
    "sg:address":"Hauptstr. 31a",
    "sg:city":"Gaggenau",
    "sg:phone":"+49 4972/2568050",
    "sg:postcode":"76571",
    "sg:province":"Baden-W\u00fcrttemberg",
    "wof:name":"Volksbank Baden-baden * Rastat",
    "wof:placetype":"venue"
},
  "geometry": {"coordinates":[8.319376,48.803967],"type":"Point"}
}