{
  "type": "Feature",
  "properties": {
    "iso:country":"DE",
    "sg:address":"18.-M\u00e4rz-Str. 34 a",
    "sg:city":"Gotha",
    "sg:phone":"+49 3621/702952",
    "sg:postcode":"99867",
    "sg:province":"Th\u00fcringen",
    "wof:name":"Architekturb\u00fcro G\u00f6tze Gmbh",
    "wof:placetype":"venue"
},
  "geometry": {"coordinates":[10.694707,50.945175],"type":"Point"}
}