{
  "type": "Feature",
  "properties": {
    "iso:country":"DE",
    "sg:address":"Posener Str. 65",
    "sg:city":"Peine",
    "sg:phone":"+49 5171/52041",
    "sg:postcode":"31228",
    "sg:province":"Niedersachsen",
    "wof:name":"Atas Bautr\u00e4ger Gmbh",
    "wof:placetype":"venue"
},
  "geometry": {"coordinates":[10.180045,52.33334],"type":"Point"}
}