{
  "type": "Feature",
  "properties": {
    "iso:country":"DE",
    "sg:address":"16845",
    "sg:city":"Neustadt",
    "sg:postcode":"16845",
    "sg:province":"Brandenburg",
    "wof:name":"Volks-und Raiffeisenbank Ostharz Eg",
    "wof:placetype":"venue"
},
  "geometry": {"coordinates":[11.460823,51.758335],"type":"Point"}
}