{
  "type": "Feature",
  "properties": {
    "iso:country":"DE",
    "sg:address":"Wingertsberg 1",
    "sg:city":"Kruft",
    "sg:phone":"+49 2652/7506",
    "sg:postcode":"56642",
    "sg:province":"Rheinland-Pfalz",
    "wof:name":"Egon Krechel",
    "wof:placetype":"venue"
},
  "geometry": {"coordinates":[7.340613842,50.3811531067],"type":"Point"}
}