{
  "type": "Feature",
  "properties": {
    "iso:country":"DE",
    "sg:address":"M\u00fchlanger 1",
    "sg:city":"Buttenwiesen",
    "sg:phone":"+49 8274/242",
    "sg:postcode":"86647",
    "sg:province":"Bayern",
    "wof:name":"Elektro Hartl Gmbh",
    "wof:placetype":"venue"
},
  "geometry": {"coordinates":[10.714084,48.582577],"type":"Point"}
}