{
  "type": "Feature",
  "properties": {
    "iso:country":"DE",
    "sg:address":"In der Lach 22",
    "sg:city":"Wendelstein",
    "sg:phone":"+49 9129/4137",
    "sg:postcode":"90530",
    "sg:province":"Bayern",
    "wof:name":"Susanne Bergold-meier Heilpraktikerin",
    "wof:placetype":"venue"
},
  "geometry": {"coordinates":[11.1669635773,49.3660125732],"type":"Point"}
}