{
  "type": "Feature",
  "properties": {
    "iso:country":"DE",
    "sg:address":"Gewerbepark Am Wald 3",
    "sg:city":"Ilmenau",
    "sg:phone":"+49 3677/64390",
    "sg:postcode":"98693",
    "sg:province":"Th\u00fcringen",
    "wof:name":"Henkel & Roth Gmbh Handling Robotik Transfer",
    "wof:placetype":"venue"
},
  "geometry": {"coordinates":[10.947566,50.693932],"type":"Point"}
}