{
  "type": "Feature",
  "properties": {
    "iso:country":"DE",
    "sg:address":"G\u00f6ttersdorf",
    "sg:city":"Osterhofen",
    "sg:phone":"+49 8547/7301",
    "sg:postcode":"94486",
    "sg:province":"Bayern",
    "wof:name":"Margarete Buchner",
    "wof:placetype":"venue"
},
  "geometry": {"coordinates":[13.019036293,48.7024879456],"type":"Point"}
}