{
  "type": "Feature",
  "properties": {
    "iso:country":"DE",
    "sg:address":"Reichhelmstr. 1",
    "sg:city":"Hannover",
    "sg:phone":"+49 511/841326",
    "sg:postcode":"30519",
    "sg:province":"Niedersachsen",
    "wof:name":"Erika Haferkamp Steuerberaterin",
    "wof:placetype":"venue"
},
  "geometry": {"coordinates":[9.7606935501,52.3374519348],"type":"Point"}
}