{
  "type": "Feature",
  "properties": {
    "iso:country":"DE",
    "sg:address":"Tulpenweg 31",
    "sg:city":"Weissach-Flacht",
    "sg:phone":"+49 7044",
    "sg:postcode":"71287",
    "sg:province":"Baden-W\u00fcrttemberg",
    "wof:name":"Nachhilfe Big-teacher",
    "wof:placetype":"venue"
},
  "geometry": {"coordinates":[8.90722,48.840069],"type":"Point"}
}