{
  "type": "Feature",
  "properties": {
    "iso:country":"DE",
    "sg:address":"Industriestr. 4",
    "sg:city":"Schwarzenbruck",
    "sg:phone":"+49 9128/3025",
    "sg:postcode":"90592",
    "sg:province":"Bayern",
    "wof:name":"Alfons Grajek Gmbh",
    "wof:placetype":"venue"
},
  "geometry": {"coordinates":[11.262073,49.35128],"type":"Point"}
}