{
  "type": "Feature",
  "properties": {
    "iso:country":"DE",
    "sg:address":"Heidestrasse 5",
    "sg:city":"Alpen",
    "sg:phone":"+49 2802/807337",
    "sg:postcode":"46519",
    "sg:province":"Nordrhein-Westfalen",
    "wof:name":"Projektierung, Automatisierung",
    "wof:placetype":"venue"
},
  "geometry": {"coordinates":[6.525823,51.59898],"type":"Point"}
}