{
  "type": "Feature",
  "properties": {
    "iso:country":"DE",
    "sg:address":"Im Teich 91",
    "sg:city":"Nauheim",
    "sg:phone":"+49 6152/62008",
    "sg:postcode":"64569",
    "sg:province":"Hessen",
    "wof:name":"Manfred K\u00f6hler Gmbh",
    "wof:placetype":"venue"
},
  "geometry": {"coordinates":[8.4689693451,49.9584732056],"type":"Point"}
}