{
  "type": "Feature",
  "properties": {
    "iso:country":"DE",
    "sg:address":"Hangweg 37",
    "sg:city":"Unterensingen",
    "sg:phone":"+49 7022/65109",
    "sg:postcode":"72669",
    "sg:province":"Baden-W\u00fcrttemberg",
    "wof:name":"Albert Renftle Computerhandlungen",
    "wof:placetype":"venue"
},
  "geometry": {"coordinates":[9.3507032394,48.65574646],"type":"Point"}
}