{
  "type": "Feature",
  "properties": {
    "iso:country":"DE",
    "sg:address":"Prager Str. 5",
    "sg:city":"Dresden",
    "sg:phone":"+49 351/4942363",
    "sg:postcode":"01069",
    "sg:province":"Sachsen",
    "wof:name":"Burger King",
    "wof:placetype":"venue"
},
  "geometry": {"coordinates":[13.7342977524,51.0420036316],"type":"Point"}
}