{
  "type": "Feature",
  "properties": {
    "iso:country":"DE",
    "sg:address":"Willy-Brandt-Platz 20",
    "sg:city":"N\u00fcrnberg",
    "sg:phone":"+49 911/205540",
    "sg:postcode":"90402",
    "sg:province":"Bayern",
    "wof:name":"Signal Unfallversicherung Ag",
    "wof:placetype":"venue"
},
  "geometry": {"coordinates":[11.0872240067,49.4481468201],"type":"Point"}
}