{
  "type": "Feature",
  "properties": {
    "iso:country":"DE",
    "sg:address":"Alte Mayener Str.",
    "sg:city":"Kaisersesch",
    "sg:postcode":"56759",
    "sg:province":"Rheinland-Pfalz",
    "wof:name":"Peba- Gmbh",
    "wof:placetype":"venue"
},
  "geometry": {"coordinates":[7.143648,50.237267],"type":"Point"}
}