{
  "type": "Feature",
  "properties": {
    "iso:country":"DE",
    "sg:address":"Ast",
    "sg:city":"Ast",
    "sg:phone":"+49 9972/8174",
    "sg:postcode":"93449",
    "sg:province":"Bayern",
    "wof:name":"M. Urban",
    "wof:placetype":"venue"
},
  "geometry": {"coordinates":[12.648648,49.379162],"type":"Point"}
}