{
  "type": "Feature",
  "properties": {
    "iso:country":"DE",
    "sg:address":"Am Buchholz 4 POSTFACH 1110",
    "sg:city":"Rehburg-Loccum",
    "sg:phone":"+49 4922/0467067",
    "sg:postcode":"31543",
    "sg:province":"Niedersachsen",
    "wof:name":"Herbert Brandt Gmbh",
    "wof:placetype":"venue"
},
  "geometry": {"coordinates":[7.1427841187,50.9575691223],"type":"Point"}
}