{
  "type": "Feature",
  "properties": {
    "iso:country":"DE",
    "sg:address":"Im Steingarten 25",
    "sg:city":"Nauroth",
    "sg:phone":"+49 2747/7544",
    "sg:postcode":"57583",
    "sg:province":"Rheinland-Pfalz",
    "wof:name":"Johann Schloemer",
    "wof:placetype":"venue"
},
  "geometry": {"coordinates":[7.878837,50.698021],"type":"Point"}
}