{
  "type": "Feature",
  "properties": {
    "iso:country":"DE",
    "sg:address":"Ettersberg-Siedlung 34",
    "sg:city":"Weimar",
    "sg:phone":"+49 3643/410807",
    "sg:postcode":"99427",
    "sg:province":"Th\u00fcringen",
    "wof:name":"Ditmar Seifert",
    "wof:placetype":"venue"
},
  "geometry": {"coordinates":[11.30153,51.023418],"type":"Point"}
}