{
  "type": "Feature",
  "properties": {
    "iso:country":"DE",
    "sg:address":"Werner-von-Siemens-Str. 8",
    "sg:city":"Kaltenkirchen",
    "sg:phone":"+49 4191/90813",
    "sg:postcode":"24568",
    "sg:province":"Schleswig-Holstein",
    "wof:name":"Erdal Kalay",
    "wof:placetype":"venue"
},
  "geometry": {"coordinates":[9.978057,53.826694],"type":"Point"}
}