{
  "type": "Feature",
  "properties": {
    "iso:country":"DE",
    "sg:address":"Industriestr. 21",
    "sg:city":"Wuppertal",
    "sg:postcode":"42327",
    "sg:province":"Nordrhein-Westfalen",
    "wof:name":"Quelle Gro\u00dfversandhaus Auslieferungslager",
    "wof:placetype":"venue"
},
  "geometry": {"coordinates":[7.0918288231,51.2423782349],"type":"Point"}
}