{
  "type": "Feature",
  "properties": {
    "iso:country":"DE",
    "sg:address":"Kleine Siedlung 5",
    "sg:city":"Eichenbarleben",
    "sg:phone":"+49 39206/52370",
    "sg:postcode":"39167",
    "sg:province":"Sachsen-Anhalt",
    "wof:name":"B. Reichert",
    "wof:placetype":"venue"
},
  "geometry": {"coordinates":[11.498134,52.139984],"type":"Point"}
}