{
  "type": "Feature",
  "properties": {
    "iso:country":"DE",
    "sg:address":"Exotischer Garten 1",
    "sg:city":"Stuttgart",
    "sg:phone":"+49 711/4592114",
    "sg:postcode":"70599",
    "sg:province":"Baden-W\u00fcrttemberg",
    "wof:name":"Universit\u00e4tsmuseum Hohenheim",
    "wof:placetype":"venue"
},
  "geometry": {"coordinates":[9.207594,48.710209],"type":"Point"}
}