{
  "type": "Feature",
  "properties": {
    "iso:country":"DE",
    "sg:address":"Kirchenstr. 11a",
    "sg:city":"Oberhausen-Rheinhausen",
    "sg:phone":"+49 7254/1373",
    "sg:postcode":"68794",
    "sg:province":"Baden-W\u00fcrttemberg",
    "wof:name":"Kurt Hoffner",
    "wof:placetype":"venue"
},
  "geometry": {"coordinates":[8.480788,49.260391],"type":"Point"}
}