{
  "type": "Feature",
  "properties": {
    "iso:country":"DE",
    "sg:address":"Bassumer Str. 40",
    "sg:city":"Stuhr",
    "sg:phone":"+49 421/807790",
    "sg:postcode":"28816",
    "sg:province":"Niedersachsen",
    "wof:name":"Inkoop",
    "wof:placetype":"venue"
},
  "geometry": {"coordinates":[8.7843923569,53.0082588196],"type":"Point"}
}