{
  "type": "Feature",
  "properties": {
    "iso:country":"DE",
    "sg:address":"Heerstr. 59",
    "sg:city":"St. Goar",
    "sg:postcode":"56329",
    "sg:province":"Rheinland-Pfalz",
    "wof:name":"Wine And Christmasparadise Kollmar Gmbh",
    "wof:placetype":"venue"
},
  "geometry": {"coordinates":[7.7164511681,50.1502799988],"type":"Point"}
}