{
  "type": "Feature",
  "properties": {
    "iso:country":"DE",
    "sg:address":"Feldchenstr.70",
    "sg:city":"Aschaffenburg",
    "sg:phone":"+49 6021/970530",
    "sg:postcode":"63743",
    "sg:province":"Bayern",
    "wof:name":"Immobilien An Der Costa-blanca",
    "wof:placetype":"venue"
},
  "geometry": {"coordinates":[9.1664199829,49.951915741],"type":"Point"}
}