{
  "type": "Feature",
  "properties": {
    "iso:country":"DE",
    "sg:address":"Technologiepark 13",
    "sg:city":"Paderborn",
    "sg:phone":"+49 5251/54010",
    "sg:postcode":"33100",
    "sg:province":"Nordrhein-Westfalen",
    "wof:name":"Jobware - Der Online Stellenmarkt",
    "wof:placetype":"venue"
},
  "geometry": {"coordinates":[8.7632541656,51.7013168335],"type":"Point"}
}