{
  "type": "Feature",
  "properties": {
    "iso:country":"DE",
    "sg:address":"Schulstr. 21",
    "sg:city":"Hennstedt",
    "sg:phone":"+49 4836/1330",
    "sg:postcode":"25779",
    "sg:province":"Schleswig-Holstein",
    "wof:name":"Jens Uwe Andersson",
    "wof:placetype":"venue"
},
  "geometry": {"coordinates":[9.165289,54.286362],"type":"Point"}
}