{
  "type": "Feature",
  "properties": {
    "iso:country":"DE",
    "sg:address":"Gupfenstr. 6",
    "sg:city":"Dei\u00dflingen",
    "sg:phone":"+49 7420/2198",
    "sg:postcode":"78652",
    "sg:province":"Baden-W\u00fcrttemberg",
    "wof:name":"Klaus Elster",
    "wof:placetype":"venue"
},
  "geometry": {"coordinates":[8.6036157608,48.1117897034],"type":"Point"}
}