{
  "type": "Feature",
  "properties": {
    "iso:country":"DE",
    "sg:address":"Bahnhofstr. 32",
    "sg:city":"Neuenrade",
    "sg:phone":"+49 2392/61361",
    "sg:postcode":"58809",
    "sg:province":"Nordrhein-Westfalen",
    "wof:name":"Zimmerei Ro\u00df Inh. Eckhard Ro\u00df",
    "wof:placetype":"venue"
},
  "geometry": {"coordinates":[7.7898988724,51.2826728821],"type":"Point"}
}