{
  "type": "Feature",
  "properties": {
    "iso:country":"DE",
    "sg:address":"Ernst-Heinkel-Str. 8-10",
    "sg:city":"Burbach",
    "sg:phone":"+49 4927/3644130",
    "sg:postcode":"57299",
    "sg:province":"Nordrhein-Westfalen",
    "wof:name":"Eltherm Elektrow\u00c4rmetechnik Gmbh",
    "wof:placetype":"venue"
},
  "geometry": {"coordinates":[8.096428,50.748589],"type":"Point"}
}