{
  "type": "Feature",
  "properties": {
    "iso:country":"DE",
    "sg:address":"R\u00f6merstr. 41",
    "sg:city":"Budenheim",
    "sg:postcode":"55257",
    "sg:province":"Rheinland-Pfalz",
    "wof:name":"Gr\u00e4f & Partner Wohnbauvermittlung",
    "wof:placetype":"venue"
},
  "geometry": {"coordinates":[8.162753,50.018806],"type":"Point"}
}