{
  "type": "Feature",
  "properties": {
    "iso:country":"DE",
    "sg:address":"Gro\u00dfhesseloher Str. 19",
    "sg:city":"M\u00fcnchen",
    "sg:phone":"+49 89/7900470",
    "sg:postcode":"81479",
    "sg:province":"Bayern",
    "wof:name":"Rim Gmbh",
    "wof:placetype":"venue"
},
  "geometry": {"coordinates":[11.5320386887,48.0814361572],"type":"Point"}
}