{
  "type": "Feature",
  "properties": {
    "iso:country":"DE",
    "sg:address":"Stendaler Str. 70",
    "sg:city":"Arneburg",
    "sg:phone":"+49 39321/2253",
    "sg:postcode":"39596",
    "sg:province":"Sachsen-Anhalt",
    "wof:name":"Hans Ulrich",
    "wof:placetype":"venue"
},
  "geometry": {"coordinates":[11.988421,52.673538],"type":"Point"}
}