{
  "type": "Feature",
  "properties": {
    "iso:country":"DE",
    "sg:address":"Mevissenstr. 59",
    "sg:city":"Krefeld",
    "sg:phone":"+49 2151/76840",
    "sg:postcode":"47803",
    "sg:province":"Nordrhein-Westfalen",
    "wof:name":"Praktiker Bau- Und Heimwerkermarkt",
    "wof:placetype":"venue"
},
  "geometry": {"coordinates":[6.5322599411,51.3473587036],"type":"Point"}
}