{
  "type": "Feature",
  "properties": {
    "iso:country":"DE",
    "sg:address":"August-Hinrichs-Str. 29-31",
    "sg:city":"Bad Zwischenahn",
    "sg:phone":"+49 441/9699063",
    "sg:postcode":"26160",
    "sg:province":"Niedersachsen",
    "wof:name":"W. Wiechmann",
    "wof:placetype":"venue"
},
  "geometry": {"coordinates":[8.153537,53.171463],"type":"Point"}
}