{
  "type": "Feature",
  "properties": {
    "iso:country":"DE",
    "sg:address":"Eichenbachstr. 20",
    "sg:city":"K\u00f6nigswinter",
    "sg:phone":"+49 2244/92420",
    "sg:postcode":"53639",
    "sg:province":"Nordrhein-Westfalen",
    "wof:name":"Gamma Maschinenvertriebs Gmbh",
    "wof:placetype":"venue"
},
  "geometry": {"coordinates":[7.221165,50.725113],"type":"Point"}
}