{
  "type": "Feature",
  "properties": {
    "iso:country":"DE",
    "sg:address":"Hohes Feld 20",
    "sg:city":"Coesfeld",
    "sg:phone":"+49 2541/4917",
    "sg:postcode":"48653",
    "sg:province":"Nordrhein-Westfalen",
    "wof:name":"G\u00fcnter B\u00fcscher",
    "wof:placetype":"venue"
},
  "geometry": {"coordinates":[7.160359,51.935211],"type":"Point"}
}