{
  "type": "Feature",
  "properties": {
    "iso:country":"DE",
    "sg:address":"Pochwerkstr. 3",
    "sg:city":"Goslar",
    "sg:phone":"+49 5325/2559",
    "sg:postcode":"38644",
    "sg:province":"Niedersachsen",
    "wof:name":"Manfred Reinecke",
    "wof:placetype":"venue"
},
  "geometry": {"coordinates":[10.332676,51.849815],"type":"Point"}
}