{
  "type": "Feature",
  "properties": {
    "iso:country":"DE",
    "sg:address":"Goethestr. 1",
    "sg:city":"Neus\u00e4\u00df",
    "sg:phone":"+49 821/482835",
    "sg:postcode":"86356",
    "sg:province":"Bayern",
    "wof:name":"Bimex Ohg",
    "wof:placetype":"venue"
},
  "geometry": {"coordinates":[10.8186292648,48.3881225586],"type":"Point"}
}