{
  "type": "Feature",
  "properties": {
    "iso:country":"DE",
    "sg:address":"Landsberger Str. 73",
    "sg:city":"M\u00fcnchen",
    "sg:postcode":"80339",
    "sg:province":"Bayern",
    "wof:name":"Talar Lebensmittel",
    "wof:placetype":"venue"
},
  "geometry": {"coordinates":[11.5375614166,48.1396369934],"type":"Point"}
}