{
  "type": "Feature",
  "properties": {
    "iso:country":"DE",
    "sg:address":"Nesthauser Str. 6",
    "sg:city":"Paderborn",
    "sg:phone":"+49 5254/5791",
    "sg:postcode":"33106",
    "sg:province":"Nordrhein-Westfalen",
    "wof:name":"Hermann Disselnmeyer",
    "wof:placetype":"venue"
},
  "geometry": {"coordinates":[8.679873,51.739101],"type":"Point"}
}