{
  "type": "Feature",
  "properties": {
    "iso:country":"DE",
    "sg:address":"Gartenstr. 1",
    "sg:city":"D\u00f6rentrup",
    "sg:phone":"+49 5265/94910",
    "sg:postcode":"32694",
    "sg:province":"Nordrhein-Westfalen",
    "wof:name":"Kurt Schlingmeier Gmbh & Co. Kg",
    "wof:placetype":"venue"
},
  "geometry": {"coordinates":[9.0012168884,52.0419769287],"type":"Point"}
}