{
  "type": "Feature",
  "properties": {
    "iso:country":"DE",
    "sg:address":"Klappergasse 1",
    "sg:city":"Heidelberg",
    "sg:phone":"+49 6221/831134",
    "sg:postcode":"69123",
    "sg:province":"Baden-W\u00fcrttemberg",
    "wof:name":"Alois Damm",
    "wof:placetype":"venue"
},
  "geometry": {"coordinates":[8.6492118835,49.4268531799],"type":"Point"}
}