{
  "type": "Feature",
  "properties": {
    "iso:country":"DE",
    "sg:address":"Dahler Str. 65",
    "sg:city":"Wuppertal",
    "sg:phone":"+49 202/2547090",
    "sg:postcode":"42389",
    "sg:province":"Nordrhein-Westfalen",
    "wof:name":"Heinze Transports Internationaux Gmbh",
    "wof:placetype":"venue"
},
  "geometry": {"coordinates":[7.2387638092,51.2803878784],"type":"Point"}
}