{
  "type": "Feature",
  "properties": {
    "iso:country":"DE",
    "sg:address":"Augustusweg 23 c",
    "sg:city":"Radebeul",
    "sg:phone":"+49 351/8303571",
    "sg:postcode":"01445",
    "sg:province":"Sachsen",
    "wof:name":"Alfred Handke",
    "wof:placetype":"venue"
},
  "geometry": {"coordinates":[13.6681108475,51.1083068848],"type":"Point"}
}