{
  "type": "Feature",
  "properties": {
    "iso:country":"DE",
    "sg:address":"Industriestr.",
    "sg:city":"Karben",
    "sg:postcode":"61184",
    "sg:province":"Hessen",
    "wof:name":"E. K\u00f6nig Gmbh & Co. Kg",
    "wof:placetype":"venue"
},
  "geometry": {"coordinates":[8.761142,50.230141],"type":"Point"}
}