{
  "type": "Feature",
  "properties": {
    "iso:country":"DE",
    "sg:address":"Topfmarkt 12",
    "sg:city":"Ilmenau",
    "sg:phone":"+49 3677/893814",
    "sg:postcode":"98693",
    "sg:province":"Th\u00fcringen",
    "wof:name":"G\u00fcnter Langenhan",
    "wof:placetype":"venue"
},
  "geometry": {"coordinates":[10.913938,50.686447],"type":"Point"}
}