{
  "type": "Feature",
  "properties": {
    "iso:country":"DE",
    "sg:address":"Wandsbeker St. 3-7",
    "sg:city":"Hamburg",
    "sg:postcode":"22172",
    "sg:province":"Hamburg",
    "wof:name":"Siebzigste Mercator Handelsges. Mbh",
    "wof:placetype":"venue"
},
  "geometry": {"coordinates":[10.0699539185,53.5791816711],"type":"Point"}
}