{
  "type": "Feature",
  "properties": {
    "iso:country":"DE",
    "sg:address":"Calenbergerstra\u00dfe 12",
    "sg:city":"Elze",
    "sg:phone":"+49 5068/4960",
    "sg:postcode":"31008",
    "sg:province":"Niedersachsen",
    "wof:name":"Exakt Werbetechnik",
    "wof:placetype":"venue"
},
  "geometry": {"coordinates":[9.73807621,52.1508293152],"type":"Point"}
}