{
  "type": "Feature",
  "properties": {
    "iso:country":"DE",
    "sg:address":"Auf dem Sand 76",
    "sg:city":"Mannheim",
    "sg:phone":"+49 621/727640",
    "sg:postcode":"68309",
    "sg:province":"Baden-W\u00fcrttemberg",
    "wof:name":"Dekoland Klaus Leinhos E. K.",
    "wof:placetype":"venue"
},
  "geometry": {"coordinates":[8.509106636,49.5144615173],"type":"Point"}
}