{
  "type": "Feature",
  "properties": {
    "iso:country":"DE",
    "sg:address":"Isselhorster Str. 269",
    "sg:city":"G\u00fctersloh",
    "sg:phone":"+49 5241/6135",
    "sg:postcode":"33335",
    "sg:province":"Nordrhein-Westfalen",
    "wof:name":"Buschkamp Siebdruckbedarf Gmbh",
    "wof:placetype":"venue"
},
  "geometry": {"coordinates":[8.446680069,51.928768158],"type":"Point"}
}