{
  "type": "Feature",
  "properties": {
    "iso:country":"DE",
    "sg:address":"Suhrendorf 84",
    "sg:city":"Ummanz",
    "sg:postcode":"18569",
    "sg:province":"Mecklenburg-Vorpommern",
    "wof:name":"Baugesellschaft Hiddensee Mbh",
    "wof:placetype":"venue"
},
  "geometry": {"coordinates":[13.13382,54.460941],"type":"Point"}
}