{
  "type": "Feature",
  "properties": {
    "iso:country":"DE",
    "sg:address":"Alter Flughafen 21",
    "sg:city":"Hannover",
    "sg:phone":"+49 511/635745",
    "sg:postcode":"30179",
    "sg:province":"Niedersachsen",
    "wof:name":"Manfred Fischer Architekt",
    "wof:placetype":"venue"
},
  "geometry": {"coordinates":[9.749808,52.417801],"type":"Point"}
}