{
  "type": "Feature",
  "properties": {
    "iso:country":"DE",
    "sg:address":"Maximilianstr. 19",
    "sg:city":"Ansbach",
    "sg:phone":"+49 981/3432",
    "sg:postcode":"91522",
    "sg:province":"Bayern",
    "wof:name":"Fritz M\u00fcller",
    "wof:placetype":"venue"
},
  "geometry": {"coordinates":[10.5719881058,49.299079895],"type":"Point"}
}