{
  "type": "Feature",
  "properties": {
    "iso:country":"DE",
    "sg:address":"Alemannstr. 30",
    "sg:city":"Hannover",
    "sg:phone":"+49 511/3520208",
    "sg:postcode":"30165",
    "sg:province":"Niedersachsen",
    "wof:name":"Gastst\u00e4tte Luise Hartmann",
    "wof:placetype":"venue"
},
  "geometry": {"coordinates":[9.7336626053,52.3903274536],"type":"Point"}
}