{
  "type": "Feature",
  "properties": {
    "iso:country":"DE",
    "sg:address":"Sendlinger Str. 24",
    "sg:city":"M\u00fcnchen",
    "sg:phone":"+49 89/263045",
    "sg:postcode":"80331",
    "sg:province":"Bayern",
    "wof:name":"Prof. Dr. Dr. Roman Schubert Zahnarzt",
    "wof:placetype":"venue"
},
  "geometry": {"coordinates":[11.570207,48.135403],"type":"Point"}
}