{
  "type": "Feature",
  "properties": {
    "iso:country":"DE",
    "sg:address":"Moltkestr. 32",
    "sg:city":"Velbert",
    "sg:phone":"+49 2051/85211",
    "sg:postcode":"42551",
    "sg:province":"Nordrhein-Westfalen",
    "wof:name":"Michael Fichtner Gmbh",
    "wof:placetype":"venue"
},
  "geometry": {"coordinates":[7.045169,51.349888],"type":"Point"}
}