{
  "type": "Feature",
  "properties": {
    "iso:country":"DE",
    "sg:address":"Hinterh\u00e4user 21",
    "sg:city":"Schluchsee",
    "sg:phone":"+49 7656/780",
    "sg:postcode":"79859",
    "sg:province":"Baden-W\u00fcrttemberg",
    "wof:name":"Kurklinik Gl\u00f6cklehof",
    "wof:placetype":"venue"
},
  "geometry": {"coordinates":[8.1791877747,47.8440093994],"type":"Point"}
}