{
  "type": "Feature",
  "properties": {
    "iso:country":"DE",
    "sg:address":"Auerrain 10",
    "sg:city":"Krauchenwies",
    "sg:phone":"+49 7576/813",
    "sg:postcode":"72505",
    "sg:province":"Baden-W\u00fcrttemberg",
    "wof:name":"Valet & Ott",
    "wof:placetype":"venue"
},
  "geometry": {"coordinates":[9.1908302307,48.0005493164],"type":"Point"}
}