{
  "type": "Feature",
  "properties": {
    "iso:country":"DE",
    "sg:address":"Berliner Str. 4",
    "sg:city":"Ronnenberg",
    "sg:phone":"+49 511/464446",
    "sg:postcode":"30952",
    "sg:province":"Niedersachsen",
    "wof:name":"Lampe-gesellschaft Mit Be- Schr\u00e4nkter Haftung & Co.",
    "wof:placetype":"venue"
},
  "geometry": {"coordinates":[9.669031,52.34626],"type":"Point"}
}