{
  "type": "Feature",
  "properties": {
    "iso:country":"DE",
    "sg:address":"Klosterstr. 34",
    "sg:city":"Berlin",
    "sg:phone":"+49 30/3312399",
    "sg:postcode":"13581",
    "sg:province":"Berlin",
    "wof:name":"Ralf Von D\u00fcsterlho",
    "wof:placetype":"venue"
},
  "geometry": {"coordinates":[13.1979904175,52.5320968628],"type":"Point"}
}