{
  "type": "Feature",
  "properties": {
    "iso:country":"DE",
    "sg:address":"Steffensbrook 104",
    "sg:city":"Heikendorf",
    "sg:phone":"+49 431/245479",
    "sg:postcode":"24226",
    "sg:province":"Schleswig-Holstein",
    "wof:name":"Priv. Pflegedienst Pmp Die Eulen",
    "wof:placetype":"venue"
},
  "geometry": {"coordinates":[10.215015,54.377972],"type":"Point"}
}