{
  "type": "Feature",
  "properties": {
    "iso:country":"DE",
    "sg:address":"Quergasse 2",
    "sg:city":"Auerbach",
    "sg:phone":"+49 3744/213854",
    "sg:postcode":"08209",
    "sg:province":"Sachsen",
    "wof:name":"Andreas Tehel",
    "wof:placetype":"venue"
},
  "geometry": {"coordinates":[12.424718,50.476803],"type":"Point"}
}