{
  "type": "Feature",
  "properties": {
    "iso:country":"DE",
    "sg:address":"Schumannstr. 48",
    "sg:city":"Saarbr\u00fccken",
    "sg:phone":"+49 681/397626",
    "sg:postcode":"66111",
    "sg:province":"Saarland",
    "wof:name":"Lore Und Dieter Bohrer",
    "wof:placetype":"venue"
},
  "geometry": {"coordinates":[7.003654,49.237991],"type":"Point"}
}