{
  "type": "Feature",
  "properties": {
    "iso:country":"DE",
    "sg:address":"Max-Eyth-Str. 36",
    "sg:city":"G\u00e4rtringen",
    "sg:postcode":"71116",
    "sg:province":"Baden-W\u00fcrttemberg",
    "wof:name":"Kaffee Service F\u00fcr Gewerbliche Abnehmer Gmbh",
    "wof:placetype":"venue"
},
  "geometry": {"coordinates":[8.908934,48.642029],"type":"Point"}
}