{
  "type": "Feature",
  "properties": {
    "iso:country":"DE",
    "sg:address":"Zwickauer Str. 50",
    "sg:city":"G\u00f6\u00dfnitz",
    "sg:phone":"+49 34493/21324",
    "sg:postcode":"04639",
    "sg:province":"Th\u00fcringen",
    "wof:name":"Gastst\u00e4tte R\u00e4tzer Inh. B. Kn\u00f6sel",
    "wof:placetype":"venue"
},
  "geometry": {"coordinates":[12.4301156998,50.883354187],"type":"Point"}
}