{
  "type": "Feature",
  "properties": {
    "iso:country":"DE",
    "sg:address":"Stemmer Weingarten 52",
    "sg:city":"Minden",
    "sg:phone":"+49 571/44856",
    "sg:postcode":"32425",
    "sg:province":"Nordrhein-Westfalen",
    "wof:name":"L. Becker Obst Und Gem\u00fcse-grosshandlung",
    "wof:placetype":"venue"
},
  "geometry": {"coordinates":[8.8726110458,52.3268241882],"type":"Point"}
}