{
  "type": "Feature",
  "properties": {
    "iso:country":"DE",
    "sg:address":"Seestr. 2",
    "sg:city":"Ravensburg",
    "sg:postcode":"88214",
    "sg:province":"Baden-W\u00fcrttemberg",
    "wof:name":"Ekr Gmbh",
    "wof:placetype":"venue"
},
  "geometry": {"coordinates":[9.612756,47.77956],"type":"Point"}
}