{
  "type": "Feature",
  "properties": {
    "iso:country":"DE",
    "sg:address":"B\u00fcschelskamp 15",
    "sg:city":"Schee\u00dfel",
    "sg:phone":"+49 4263/2561",
    "sg:postcode":"27383",
    "sg:province":"Niedersachsen",
    "wof:name":"Christian H\u00f6nig Putzunternehmen Gmbh",
    "wof:placetype":"venue"
},
  "geometry": {"coordinates":[9.526104,53.189709],"type":"Point"}
}