{
  "type": "Feature",
  "properties": {
    "iso:country":"DE",
    "sg:address":"Friedrich-Gelsam-Str. 23",
    "sg:city":"Erkelenz",
    "sg:phone":"+49 2164/940490",
    "sg:postcode":"41812",
    "sg:province":"Nordrhein-Westfalen",
    "wof:name":"J\u00fcrgen Coenen Steuerberater",
    "wof:placetype":"venue"
},
  "geometry": {"coordinates":[6.4067130089,51.0493621826],"type":"Point"}
}