{
  "type": "Feature",
  "properties": {
    "iso:country":"DE",
    "sg:address":"St.-J\u00fcrgen-Str. 78",
    "sg:city":"Flensburg",
    "sg:postcode":"24937",
    "sg:province":"Schleswig-Holstein",
    "wof:name":"Ev. Pfarramt St. J\u00fcrgen",
    "wof:placetype":"venue"
},
  "geometry": {"coordinates":[9.4415645599,54.7911758423],"type":"Point"}
}