{
  "type": "Feature",
  "properties": {
    "iso:country":"DE",
    "sg:address":"Bachstr. 5",
    "sg:city":"Schiltach",
    "sg:phone":"+49 7836/2032",
    "sg:postcode":"77761",
    "sg:province":"Baden-W\u00fcrttemberg",
    "wof:name":"Arbeiterwohlfahrt",
    "wof:placetype":"venue"
},
  "geometry": {"coordinates":[8.341839,48.289345],"type":"Point"}
}