{
  "type": "Feature",
  "properties": {
    "iso:country":"DE",
    "sg:address":"Hauptstr. 23",
    "sg:city":"Dresden",
    "sg:postcode":"01097",
    "sg:province":"Sachsen",
    "wof:name":"Ev.-luth. Stadtjugendpfarramt",
    "wof:placetype":"venue"
},
  "geometry": {"coordinates":[13.7435445786,51.0607948303],"type":"Point"}
}