{
  "type": "Feature",
  "properties": {
    "iso:country":"DE",
    "sg:address":"Mannheimer Str. 267",
    "sg:city":"Heidelberg",
    "sg:phone":"+49 6221/831333",
    "sg:postcode":"69123",
    "sg:province":"Baden-W\u00fcrttemberg",
    "wof:name":"Gemeinn\u00fctzig Gesellschaft F\u00fcr Haus- Und Grundbesitz Mbh",
    "wof:placetype":"venue"
},
  "geometry": {"coordinates":[8.6473665237,49.425945282],"type":"Point"}
}