{
  "type": "Feature",
  "properties": {
    "iso:country":"DE",
    "sg:address":"In der R\u00fcbecke 13",
    "sg:city":"Lennestadt",
    "sg:phone":"+49 2723/2346",
    "sg:postcode":"57368",
    "sg:province":"Nordrhein-Westfalen",
    "wof:name":"Helmut Bl\u00f6cher",
    "wof:placetype":"venue"
},
  "geometry": {"coordinates":[8.058555,51.096397],"type":"Point"}
}