{
  "type": "Feature",
  "properties": {
    "iso:country":"DE",
    "sg:address":"Weinbergstr. 3",
    "sg:city":"Bad Freienwalde",
    "sg:phone":"+49 3344/31271",
    "sg:postcode":"16259",
    "sg:province":"Brandenburg",
    "wof:name":"K. Sch\u00fcler",
    "wof:placetype":"venue"
},
  "geometry": {"coordinates":[14.02617,52.785789],"type":"Point"}
}