{
  "type": "Feature",
  "properties": {
    "iso:country":"DE",
    "sg:address":"Alustr. 50-52",
    "sg:city":"Schwandorf",
    "sg:phone":"+49 9431/5422",
    "sg:postcode":"92421",
    "sg:province":"Bayern",
    "wof:name":"Ecolith-zeolithe Gmbh",
    "wof:placetype":"venue"
},
  "geometry": {"coordinates":[12.082647,49.310932],"type":"Point"}
}