{
  "type": "Feature",
  "properties": {
    "iso:country":"DE",
    "sg:address":"Breitestr. 31",
    "sg:city":"Simmerath",
    "sg:phone":"+49 2473/87012",
    "sg:postcode":"52152",
    "sg:province":"Nordrhein-Westfalen",
    "wof:name":"Franz Josef Ebert Architekt",
    "wof:placetype":"venue"
},
  "geometry": {"coordinates":[6.300092,50.576298],"type":"Point"}
}