{
  "type": "Feature",
  "properties": {
    "iso:country":"DE",
    "sg:address":"Lange Anwanden 9",
    "sg:city":"Sindelfingen",
    "sg:phone":"+49 7031/812334",
    "sg:postcode":"71065",
    "sg:province":"Baden-W\u00fcrttemberg",
    "wof:name":"Internationale Rondelly Truppe",
    "wof:placetype":"venue"
},
  "geometry": {"coordinates":[9.011708,48.708076],"type":"Point"}
}