{
  "type": "Feature",
  "properties": {
    "iso:country":"DE",
    "sg:address":"Gr\u00fcntenstr. 17",
    "sg:city":"Sonthofen",
    "sg:phone":"+49 8321/85569",
    "sg:postcode":"87527",
    "sg:province":"Bayern",
    "wof:name":"Bestattungen Harald W\u00f6lfle E. K.",
    "wof:placetype":"venue"
},
  "geometry": {"coordinates":[10.280889,47.517441],"type":"Point"}
}