{
  "type": "Feature",
  "properties": {
    "iso:country":"DE",
    "sg:address":"Im Dorf 6",
    "sg:city":"Bitz",
    "sg:phone":"+49 7431/81786",
    "sg:postcode":"72475",
    "sg:province":"Baden-W\u00fcrttemberg",
    "wof:name":"Bitzer Schlitzohr",
    "wof:placetype":"venue"
},
  "geometry": {"coordinates":[9.0921764374,48.243560791],"type":"Point"}
}