{
  "type": "Feature",
  "properties": {
    "iso:country":"DE",
    "sg:address":"Paradeplatz 4",
    "sg:city":"Roding",
    "sg:phone":"+49 9461/2285",
    "sg:postcode":"93426",
    "sg:province":"Bayern",
    "wof:name":"Lindinger",
    "wof:placetype":"venue"
},
  "geometry": {"coordinates":[12.5176677704,49.1966133118],"type":"Point"}
}