{
  "type": "Feature",
  "properties": {
    "iso:country":"DE",
    "sg:address":"Dresdner Str. 115",
    "sg:city":"Reichenberg",
    "sg:phone":"+49 351/8305495",
    "sg:postcode":"01468",
    "sg:province":"Sachsen",
    "wof:name":"Feriendorf Und Campingplatz Bad Sonnenland Gmbh",
    "wof:placetype":"venue"
},
  "geometry": {"coordinates":[13.685175,51.130959],"type":"Point"}
}