{
  "type": "Feature",
  "properties": {
    "iso:country":"DE",
    "sg:address":"Am Lievendahl",
    "sg:city":"Erkelenz",
    "sg:postcode":"41812",
    "sg:province":"Nordrhein-Westfalen",
    "wof:name":"Bauunternehmung Paulus & E\u00dfer Gmbh",
    "wof:placetype":"venue"
},
  "geometry": {"coordinates":[6.3372387886,51.0593528748],"type":"Point"}
}