{
  "type": "Feature",
  "properties": {
    "iso:country":"DE",
    "sg:address":"Theaterstr. 5",
    "sg:city":"W\u00fcrzburg",
    "sg:phone":"+49 931/56868",
    "sg:postcode":"97070",
    "sg:province":"Bayern",
    "wof:name":"Boneto",
    "wof:placetype":"venue"
},
  "geometry": {"coordinates":[9.9341211319,49.797039032],"type":"Point"}
}