{
  "type": "Feature",
  "properties": {
    "iso:country":"DE",
    "sg:address":"M\u00fchlenkopfstr. 12",
    "sg:city":"Willingen",
    "sg:phone":"+49 5632/6033",
    "sg:postcode":"34508",
    "sg:province":"Hessen",
    "wof:name":"Romantikhotel Stryckhaus",
    "wof:placetype":"venue"
},
  "geometry": {"coordinates":[8.6189069748,51.2798843384],"type":"Point"}
}