{
  "type": "Feature",
  "properties": {
    "iso:country":"DE",
    "sg:address":"Stra\u00dfe der Einheit 2",
    "sg:city":"Wei\u00dfwasser",
    "sg:phone":"+49 3576/209033",
    "sg:postcode":"02943",
    "sg:province":"Sachsen",
    "wof:name":"Caralux Neonlichttechnik Gmbh",
    "wof:placetype":"venue"
},
  "geometry": {"coordinates":[14.6491661072,51.50440979],"type":"Point"}
}