{
  "type": "Feature",
  "properties": {
    "iso:country":"DE",
    "sg:address":"Kastellstr. 40",
    "sg:city":"Mengen",
    "sg:phone":"+49 7572/8108",
    "sg:postcode":"88512",
    "sg:province":"Baden-W\u00fcrttemberg",
    "wof:name":"Adler Ennetach Tanzlokal Eberhart",
    "wof:placetype":"venue"
},
  "geometry": {"coordinates":[9.3192186356,48.0523529053],"type":"Point"}
}