{
  "type": "Feature",
  "properties": {
    "iso:country":"DE",
    "sg:address":"Joseph-von-Fraunhofer-Str. 7",
    "sg:city":"Alsdorf",
    "sg:phone":"+49 2404/9010",
    "sg:postcode":"52477",
    "sg:province":"Nordrhein-Westfalen",
    "wof:name":"Cycos Ag",
    "wof:placetype":"venue"
},
  "geometry": {"coordinates":[6.189211,50.874851],"type":"Point"}
}