{
  "type": "Feature",
  "properties": {
    "iso:country":"DE",
    "sg:address":"Hauptstr. 43",
    "sg:city":"Winnenden",
    "sg:phone":"+49 7195/74375",
    "sg:postcode":"71364",
    "sg:province":"Baden-W\u00fcrttemberg",
    "wof:name":"Sonne Inh. Josef Ring",
    "wof:placetype":"venue"
},
  "geometry": {"coordinates":[9.430308342,48.8656082153],"type":"Point"}
}