{
  "type": "Feature",
  "properties": {
    "iso:country":"DE",
    "sg:address":"Genter Str. 23",
    "sg:city":"K\u00f6ln",
    "sg:phone":"+49 221/527763",
    "sg:postcode":"50672",
    "sg:province":"Nordrhein-Westfalen",
    "wof:name":"Prof. Johannes Fritsch",
    "wof:placetype":"venue"
},
  "geometry": {"coordinates":[6.935775,50.93935],"type":"Point"}
}