{
  "type": "Feature",
  "properties": {
    "iso:country":"DE",
    "sg:address":"Alpenring 17",
    "sg:city":"M\u00f6rfelden-Walldorf",
    "sg:phone":"+49 6105/42254",
    "sg:postcode":"64546",
    "sg:province":"Hessen",
    "wof:name":"Gerhard Loos Ingenieur",
    "wof:placetype":"venue"
},
  "geometry": {"coordinates":[8.5677995682,49.9963874817],"type":"Point"}
}