{
  "type": "Feature",
  "properties": {
    "iso:country":"DE",
    "sg:address":"Markusstr. 2",
    "sg:city":"Duisburg",
    "sg:phone":"+49 203/770667",
    "sg:postcode":"47055",
    "sg:province":"Nordrhein-Westfalen",
    "wof:name":"Buchdruckerei Brinkmann",
    "wof:placetype":"venue"
},
  "geometry": {"coordinates":[6.759728,51.402302],"type":"Point"}
}