{
  "type": "Feature",
  "properties": {
    "iso:country":"DE",
    "sg:address":"Gartenstr. 6",
    "sg:city":"Graben",
    "sg:phone":"+49 8232/2532",
    "sg:postcode":"86836",
    "sg:province":"Bayern",
    "wof:name":"Bauunternehmen Scheske Gmbh",
    "wof:placetype":"venue"
},
  "geometry": {"coordinates":[10.825482,48.189156],"type":"Point"}
}