{
  "type": "Feature",
  "properties": {
    "iso:country":"DE",
    "sg:address":"Hallesche Str. 12",
    "sg:city":"Homburg",
    "sg:phone":"+49 6841/73266",
    "sg:postcode":"66424",
    "sg:province":"Saarland",
    "wof:name":"Wolfgang Kauf",
    "wof:placetype":"venue"
},
  "geometry": {"coordinates":[7.317361,49.338699],"type":"Point"}
}