{
  "type": "Feature",
  "properties": {
    "iso:country":"DE",
    "sg:address":"F\u00fcrst-Johann-Moritz-Str.",
    "sg:city":"Siegen",
    "sg:postcode":"57072",
    "sg:province":"Nordrhein-Westfalen",
    "wof:name":"C & A Brenningmeyer",
    "wof:placetype":"venue"
},
  "geometry": {"coordinates":[8.019222,50.875309],"type":"Point"}
}