{
  "type": "Feature",
  "properties": {
    "iso:country":"DE",
    "sg:address":"Dubelstr. 47",
    "sg:city":"Hattenhofen",
    "sg:phone":"+49 7164/6902",
    "sg:postcode":"73110",
    "sg:province":"Baden-W\u00fcrttemberg",
    "wof:name":"Marmic-media",
    "wof:placetype":"venue"
},
  "geometry": {"coordinates":[9.569275856,48.6695022583],"type":"Point"}
}