{
  "type": "Feature",
  "properties": {
    "iso:country":"DE",
    "sg:address":"Schlo\u00dfpark 13 a",
    "sg:city":"Pirna",
    "sg:phone":"+49 3501/784970",
    "sg:postcode":"01796",
    "sg:province":"Sachsen",
    "wof:name":"Die Pille",
    "wof:placetype":"venue"
},
  "geometry": {"coordinates":[13.9520359039,50.9601211548],"type":"Point"}
}