{
  "type": "Feature",
  "properties": {
    "iso:country":"DE",
    "sg:address":"Krebs\u00f6ge 10",
    "sg:city":"Radevormwald",
    "sg:phone":"+49 2191/6930",
    "sg:postcode":"42477",
    "sg:province":"Nordrhein-Westfalen",
    "wof:name":"Gkn Sinter Metals Gmbh",
    "wof:placetype":"venue"
},
  "geometry": {"coordinates":[7.303688,51.202545],"type":"Point"}
}