{
  "type": "Feature",
  "properties": {
    "iso:country":"DE",
    "sg:address":"Unterste Eisengasse 47",
    "sg:city":"Neu-Anspach",
    "sg:phone":"+49 6081/41304",
    "sg:postcode":"61267",
    "sg:province":"Hessen",
    "wof:name":"Nassauische Heimst\u00e4tte Gmbh",
    "wof:placetype":"venue"
},
  "geometry": {"coordinates":[8.5041360855,50.3032875061],"type":"Point"}
}