{
  "type": "Feature",
  "properties": {
    "iso:country":"DE",
    "sg:address":"Dorfstr. 46",
    "sg:city":"Tromsdorf",
    "sg:phone":"+49 34467/90818",
    "sg:postcode":"06648",
    "sg:province":"Sachsen-Anhalt",
    "wof:name":"S. Koch",
    "wof:placetype":"venue"
},
  "geometry": {"coordinates":[11.519851,51.111927],"type":"Point"}
}