{
  "type": "Feature",
  "properties": {
    "iso:country":"DE",
    "sg:address":"Rothm\u00fchlstr. 13",
    "sg:city":"Bergrheinfeld",
    "sg:phone":"+49 9721/90844",
    "sg:postcode":"97493",
    "sg:province":"Bayern",
    "wof:name":"H. Weise",
    "wof:placetype":"venue"
},
  "geometry": {"coordinates":[10.1800022125,50.010635376],"type":"Point"}
}