{
  "type": "Feature",
  "properties": {
    "iso:country":"DE",
    "sg:address":"Stellenwiesenweg 2",
    "sg:city":"Oberndorf",
    "sg:phone":"+49 7423/3446",
    "sg:postcode":"78727",
    "sg:province":"Baden-W\u00fcrttemberg",
    "wof:name":"Helmut Gl\u00fcck",
    "wof:placetype":"venue"
},
  "geometry": {"coordinates":[8.5395679474,48.2747955322],"type":"Point"}
}