{
  "type": "Feature",
  "properties": {
    "iso:country":"DE",
    "sg:address":"Adolf-Kolping-Str. 15",
    "sg:city":"Hammelburg",
    "sg:phone":"+49 9732/1780",
    "sg:postcode":"97762",
    "sg:province":"Bayern",
    "wof:name":"Restaurant Delphi",
    "wof:placetype":"venue"
},
  "geometry": {"coordinates":[9.8975009918,50.1130943298],"type":"Point"}
}