{
  "type": "Feature",
  "properties": {
    "iso:country":"DE",
    "sg:address":"Obere K\u00f6nigstr. 38",
    "sg:city":"Bamberg",
    "sg:phone":"+49 951/25503",
    "sg:postcode":"96052",
    "sg:province":"Bayern",
    "wof:name":"Maisel Br\u00e4ust\u00fcbl",
    "wof:placetype":"venue"
},
  "geometry": {"coordinates":[10.8954343796,49.8967094421],"type":"Point"}
}