{
  "type": "Feature",
  "properties": {
    "iso:country":"DE",
    "sg:address":"Neumarkter Str. 5",
    "sg:city":"Sulzbach-Rosenberg",
    "sg:phone":"+49 9661/4270",
    "sg:postcode":"92237",
    "sg:province":"Bayern",
    "wof:name":"Norbert Pilhofer",
    "wof:placetype":"venue"
},
  "geometry": {"coordinates":[11.73796,49.502476],"type":"Point"}
}