{
  "type": "Feature",
  "properties": {
    "iso:country":"DE",
    "sg:address":"T\u00f6k\u00f6l-Allee 12",
    "sg:city":"Klein R\u00f6nnau",
    "sg:phone":"+49 4551/83961",
    "sg:postcode":"23795",
    "sg:province":"Schleswig-Holstein",
    "wof:name":"Griwa-bau Gmbh",
    "wof:placetype":"venue"
},
  "geometry": {"coordinates":[10.321471,53.964165],"type":"Point"}
}