{
  "type": "Feature",
  "properties": {
    "iso:country":"DE",
    "sg:address":"Lauergasse 2",
    "sg:city":"Ettlingen",
    "sg:phone":"+49 7243/17001",
    "sg:postcode":"76275",
    "sg:province":"Baden-W\u00fcrttemberg",
    "wof:name":"Reiner P. Miedel Steuerberater",
    "wof:placetype":"venue"
},
  "geometry": {"coordinates":[8.40721035,48.9423789978],"type":"Point"}
}