{
  "type": "Feature",
  "properties": {
    "iso:country":"DE",
    "sg:address":"Am Buchenhain 1",
    "sg:city":"Bochum",
    "sg:phone":"+49 234/3250090",
    "sg:postcode":"44795",
    "sg:province":"Nordrhein-Westfalen",
    "wof:name":"Areal Gmbh",
    "wof:placetype":"venue"
},
  "geometry": {"coordinates":[7.187883,51.439865],"type":"Point"}
}