{
  "type": "Feature",
  "properties": {
    "iso:country":"DE",
    "sg:address":"Bismarckstr. 297",
    "sg:city":"Gelsenkirchen",
    "sg:phone":"+49 209/876981",
    "sg:postcode":"45889",
    "sg:province":"Nordrhein-Westfalen",
    "wof:name":"Dietmar Kenzlers",
    "wof:placetype":"venue"
},
  "geometry": {"coordinates":[7.110864,51.535049],"type":"Point"}
}