{
  "type": "Feature",
  "properties": {
    "iso:country":"DE",
    "sg:address":"Karlstr.",
    "sg:city":"Karlsruhe",
    "sg:phone":"+49 721/23504",
    "sg:postcode":"76133",
    "sg:province":"Baden-W\u00fcrttemberg",
    "wof:name":"Kleiber Wettannahme",
    "wof:placetype":"venue"
},
  "geometry": {"coordinates":[8.39454,49.003883],"type":"Point"}
}