{
  "type": "Feature",
  "properties": {
    "iso:country":"DE",
    "sg:address":"Albrechtshaus",
    "sg:city":"Stiege",
    "sg:postcode":"38899",
    "sg:province":"Sachsen-Anhalt",
    "wof:name":"Dr. Med. Theobald Kabus",
    "wof:placetype":"venue"
},
  "geometry": {"coordinates":[10.92664,51.641956],"type":"Point"}
}