{
  "type": "Feature",
  "properties": {
    "iso:country":"DE",
    "sg:address":"Spielhagenstr. 10",
    "sg:city":"N\u00fcrnberg",
    "sg:phone":"+49 9129/26241",
    "sg:postcode":"90455",
    "sg:province":"Bayern",
    "wof:name":"Sommer",
    "wof:placetype":"venue"
},
  "geometry": {"coordinates":[11.104997,49.357468],"type":"Point"}
}