{
  "type": "Feature",
  "properties": {
    "iso:country":"DE",
    "sg:address":"Hauptstr. 133",
    "sg:city":"Leidersbach",
    "sg:phone":"+49 6028/996617",
    "sg:postcode":"63849",
    "sg:province":"Bayern",
    "wof:name":"J. Bachmann",
    "wof:placetype":"venue"
},
  "geometry": {"coordinates":[9.228072,49.900208],"type":"Point"}
}