{
  "type": "Feature",
  "properties": {
    "iso:country":"DE",
    "sg:address":"Theodor-Francke-Str. 6",
    "sg:city":"Berlin",
    "sg:phone":"+49 30/7514286",
    "sg:postcode":"12099",
    "sg:province":"Berlin",
    "wof:name":"Christa Eliades",
    "wof:placetype":"venue"
},
  "geometry": {"coordinates":[13.3866081238,52.4615821838],"type":"Point"}
}