{
  "type": "Feature",
  "properties": {
    "iso:country":"DE",
    "sg:address":"Poststr. 7",
    "sg:city":"Altusried",
    "sg:phone":"+49 8373/7880",
    "sg:postcode":"87452",
    "sg:province":"Bayern",
    "wof:name":"Rad Haus Fritz",
    "wof:placetype":"venue"
},
  "geometry": {"coordinates":[10.21323,47.80407],"type":"Point"}
}