{
  "type": "Feature",
  "properties": {
    "iso:country":"DE",
    "sg:address":"Hegelstr. 28",
    "sg:city":"Magdeburg",
    "sg:phone":"+49 391/5659420",
    "sg:postcode":"39104",
    "sg:province":"Sachsen-Anhalt",
    "wof:name":"Remmers Und Partner Rechtsanw\u00e4lte",
    "wof:placetype":"venue"
},
  "geometry": {"coordinates":[11.6302051544,52.1190223694],"type":"Point"}
}