{
  "type": "Feature",
  "properties": {
    "iso:country":"DE",
    "sg:address":"Telemannstr 56a",
    "sg:city":"Hamburg",
    "sg:phone":"+49 40/37854821",
    "sg:postcode":"20255",
    "sg:province":"Hamburg",
    "wof:name":"B-ok Deutschland Gmbh & Co Kg",
    "wof:placetype":"venue"
},
  "geometry": {"coordinates":[9.9555616379,53.5804862976],"type":"Point"}
}