{
  "type": "Feature",
  "properties": {
    "iso:country":"DE",
    "sg:address":"Ernst-Abbe-Str. 13",
    "sg:city":"Zweibr\u00fccken",
    "sg:postcode":"66482",
    "sg:province":"Rheinland-Pfalz",
    "wof:name":"Domus Wohnungsunternehmen Gmbh",
    "wof:placetype":"venue"
},
  "geometry": {"coordinates":[7.3461780548,49.2365493774],"type":"Point"}
}