{
  "type": "Feature",
  "properties": {
    "iso:country":"DE",
    "sg:address":"Bavariastr. 7",
    "sg:city":"M\u00fcnchen",
    "sg:postcode":"80336",
    "sg:province":"Bayern",
    "wof:name":"Wkm Verm\u00f6gensverwaltung",
    "wof:placetype":"venue"
},
  "geometry": {"coordinates":[11.5462007523,48.126411438],"type":"Point"}
}