{
  "type": "Feature",
  "properties": {
    "iso:country":"DE",
    "sg:address":"Marktplatz 1",
    "sg:city":"Lemgo",
    "sg:phone":"+49 5261/188003",
    "sg:postcode":"32657",
    "sg:province":"Nordrhein-Westfalen",
    "wof:name":"Ratskeller",
    "wof:placetype":"venue"
},
  "geometry": {"coordinates":[8.9016675949,52.0281562805],"type":"Point"}
}