{
  "type": "Feature",
  "properties": {
    "iso:country":"DE",
    "sg:address":"Denkinger Str. 11",
    "sg:city":"Gosheim",
    "sg:phone":"+49 7426/1560",
    "sg:postcode":"78559",
    "sg:province":"Baden-W\u00fcrttemberg",
    "wof:name":"Synertech Gmbh",
    "wof:placetype":"venue"
},
  "geometry": {"coordinates":[8.758823,48.134529],"type":"Point"}
}