{
  "type": "Feature",
  "properties": {
    "iso:country":"DE",
    "sg:address":"Osterstr. 31/32",
    "sg:city":"Hildesheim",
    "sg:phone":"+49 5121/37072",
    "sg:postcode":"31134",
    "sg:province":"Niedersachsen",
    "wof:name":"Public",
    "wof:placetype":"venue"
},
  "geometry": {"coordinates":[9.9539985657,52.1562576294],"type":"Point"}
}