{
  "type": "Feature",
  "properties": {
    "iso:country":"DE",
    "sg:address":"Hohenlohestr. 46",
    "sg:city":"Bremen",
    "sg:postcode":"28209",
    "sg:province":"Bremen",
    "wof:name":"H. Degner Verm\u00f6gens- Verwaltungs Gmbh & Co. Kg",
    "wof:placetype":"venue"
},
  "geometry": {"coordinates":[8.8183898926,53.0825614929],"type":"Point"}
}