{
  "type": "Feature",
  "properties": {
    "iso:country":"DE",
    "sg:address":"Jennerstr. 18",
    "sg:city":"Essen",
    "sg:phone":"+49 201/738158",
    "sg:postcode":"45147",
    "sg:province":"Nordrhein-Westfalen",
    "wof:name":"Manfred M\u00fcchler Architekt",
    "wof:placetype":"venue"
},
  "geometry": {"coordinates":[6.993871,51.43541],"type":"Point"}
}