{
  "type": "Feature",
  "properties": {
    "iso:country":"DE",
    "sg:address":"Hinter dem Deich 9",
    "sg:city":"Witzenhausen",
    "sg:phone":"+49 5542/2655",
    "sg:postcode":"37213",
    "sg:province":"Hessen",
    "wof:name":"Stadtwerke Witzenhausen Gmbh",
    "wof:placetype":"venue"
},
  "geometry": {"coordinates":[9.854677,51.34454],"type":"Point"}
}