{
  "type": "Feature",
  "properties": {
    "iso:country":"DE",
    "sg:address":"Erlbacher Str. 4",
    "sg:city":"Markneukirchen",
    "sg:phone":"+49 37422/47837",
    "sg:postcode":"08258",
    "sg:province":"Sachsen",
    "wof:name":"K. Und Stephan Dick",
    "wof:placetype":"venue"
},
  "geometry": {"coordinates":[12.334804,50.311157],"type":"Point"}
}