{
  "type": "Feature",
  "properties": {
    "iso:country":"DE",
    "sg:address":"Rudolf-Maschke-Platz 3",
    "sg:city":"Trossingen",
    "sg:phone":"+49 7425/7651",
    "sg:postcode":"78647",
    "sg:province":"Baden-W\u00fcrttemberg",
    "wof:name":"Besch-m. Schworck Cafe",
    "wof:placetype":"venue"
},
  "geometry": {"coordinates":[8.636838,48.076797],"type":"Point"}
}