{
  "type": "Feature",
  "properties": {
    "iso:country":"DE",
    "sg:address":"Oberstr. 33",
    "sg:city":"Darmstadt",
    "sg:phone":"+49 6151/943870",
    "sg:postcode":"64297",
    "sg:province":"Hessen",
    "wof:name":"Sch\u00f6n Touristik",
    "wof:placetype":"venue"
},
  "geometry": {"coordinates":[8.6471500397,49.8179016113],"type":"Point"}
}