{
  "type": "Feature",
  "properties": {
    "iso:country":"DE",
    "sg:address":"Osterstr. 2",
    "sg:city":"Norden",
    "sg:phone":"+49 4931/5979",
    "sg:postcode":"26506",
    "sg:province":"Niedersachsen",
    "wof:name":"L. Olejnik-diesing & Diesing",
    "wof:placetype":"venue"
},
  "geometry": {"coordinates":[7.20609,53.596104],"type":"Point"}
}