{
  "type": "Feature",
  "properties": {
    "iso:country":"DE",
    "sg:address":"Wilhelm-Raabe-Weg 20",
    "sg:city":"Lachendorf",
    "sg:phone":"+49 5145/406",
    "sg:postcode":"29331",
    "sg:province":"Niedersachsen",
    "wof:name":"W. Deppner",
    "wof:placetype":"venue"
},
  "geometry": {"coordinates":[10.2428731918,52.6135253906],"type":"Point"}
}