{
  "type": "Feature",
  "properties": {
    "iso:country":"DE",
    "sg:address":"Hauptstr. 68",
    "sg:city":"Sinsheim",
    "sg:phone":"+49 7261/4975",
    "sg:postcode":"74889",
    "sg:province":"Baden-W\u00fcrttemberg",
    "wof:name":"Lvm Versicherungsb\u00fcro Wolfgang Rupp",
    "wof:placetype":"venue"
},
  "geometry": {"coordinates":[8.8757648468,49.2533798218],"type":"Point"}
}