{
  "type": "Feature",
  "properties": {
    "iso:country":"DE",
    "sg:address":"Lange Str. 122",
    "sg:city":"Baden-Baden",
    "sg:phone":"+49 7221/25331",
    "sg:postcode":"76530",
    "sg:province":"Baden-W\u00fcrttemberg",
    "wof:name":"Aral Tankstelle",
    "wof:placetype":"venue"
},
  "geometry": {"coordinates":[8.2281236649,48.7707214355],"type":"Point"}
}