{
  "type": "Feature",
  "properties": {
    "iso:country":"DE",
    "sg:address":"Krefelder Str. 60",
    "sg:city":"Neuss",
    "sg:phone":"+49 2131/274627",
    "sg:postcode":"41460",
    "sg:province":"Nordrhein-Westfalen",
    "wof:name":"Paul Peter Koelzer Rechtsanwalt",
    "wof:placetype":"venue"
},
  "geometry": {"coordinates":[6.6859498024,51.2018508911],"type":"Point"}
}