{
  "type": "Feature",
  "properties": {
    "iso:country":"DE",
    "sg:address":"Martinistr. 2a",
    "sg:city":"Augsburg",
    "sg:phone":"+49 821/82828",
    "sg:postcode":"86179",
    "sg:province":"Bayern",
    "wof:name":"W. Muninger",
    "wof:placetype":"venue"
},
  "geometry": {"coordinates":[10.9101667404,48.3075904846],"type":"Point"}
}