{
  "type": "Feature",
  "properties": {
    "iso:country":"DE",
    "sg:address":"Reeperbahn 63",
    "sg:city":"Hamburg",
    "sg:phone":"+49 40/3191530",
    "sg:postcode":"20359",
    "sg:province":"Hamburg",
    "wof:name":"U. K\u00fcster",
    "wof:placetype":"venue"
},
  "geometry": {"coordinates":[9.9633493423,53.549823761],"type":"Point"}
}