{
  "type": "Feature",
  "properties": {
    "iso:country":"DE",
    "sg:address":"Eugen-Bolz-Str. 4",
    "sg:city":"Hemmingen",
    "sg:phone":"+49 7150/5106",
    "sg:postcode":"71282",
    "sg:province":"Baden-W\u00fcrttemberg",
    "wof:name":"Annelies Lehle Rechtsanw\u00e4ltin",
    "wof:placetype":"venue"
},
  "geometry": {"coordinates":[9.0255327225,48.8702545166],"type":"Point"}
}