{
  "type": "Feature",
  "properties": {
    "iso:country":"DE",
    "sg:address":"Schwarzwaldstr. 13",
    "sg:city":"Tuttlingen",
    "sg:phone":"+49 7462/6127",
    "sg:postcode":"78532",
    "sg:province":"Baden-W\u00fcrttemberg",
    "wof:name":"Paul Manger",
    "wof:placetype":"venue"
},
  "geometry": {"coordinates":[8.7635269165,47.9585571289],"type":"Point"}
}