{
  "type": "Feature",
  "properties": {
    "iso:country":"DE",
    "sg:address":"Am Weinberg 17",
    "sg:city":"Dreis",
    "sg:phone":"+49 6578/989688",
    "sg:postcode":"54518",
    "sg:province":"Rheinland-Pfalz",
    "wof:name":"Pizzeria Isola Bella",
    "wof:placetype":"venue"
},
  "geometry": {"coordinates":[6.8075990677,49.9408187866],"type":"Point"}
}