{
  "type": "Feature",
  "properties": {
    "iso:country":"DE",
    "sg:address":"Espanweg 15",
    "sg:city":"Dietfurt",
    "sg:phone":"+49 8464/756",
    "sg:postcode":"92345",
    "sg:province":"Bayern",
    "wof:name":"Tennisst\u00fcberl",
    "wof:placetype":"venue"
},
  "geometry": {"coordinates":[11.59634,49.02401],"type":"Point"}
}