{
  "type": "Feature",
  "properties": {
    "iso:country":"DE",
    "sg:address":"Burgstr. 36",
    "sg:city":"Salzwedel",
    "sg:phone":"+49 3901/32527",
    "sg:postcode":"29410",
    "sg:province":"Sachsen-Anhalt",
    "wof:name":"Dreyer Immobilien Gmbh",
    "wof:placetype":"venue"
},
  "geometry": {"coordinates":[11.1521158218,52.8514404297],"type":"Point"}
}