{
  "type": "Feature",
  "properties": {
    "iso:country":"DE",
    "sg:address":"Fichtensteig 3",
    "sg:city":"Wolnzach",
    "sg:phone":"+49 8442/3924",
    "sg:postcode":"85283",
    "sg:province":"Bayern",
    "wof:name":"Franz Hofmeier",
    "wof:placetype":"venue"
},
  "geometry": {"coordinates":[11.605061,48.61636],"type":"Point"}
}