{
  "type": "Feature",
  "properties": {
    "iso:country":"DE",
    "sg:address":"K\u00f6rner Hellweg 62",
    "sg:city":"Dortmund",
    "sg:phone":"+49 231/593415",
    "sg:postcode":"44143",
    "sg:province":"Nordrhein-Westfalen",
    "wof:name":"G. Klein",
    "wof:placetype":"venue"
},
  "geometry": {"coordinates":[7.504835,51.515957],"type":"Point"}
}