{
  "type": "Feature",
  "properties": {
    "iso:country":"DE",
    "sg:city":"Darmstadt",
    "sg:postcode":"64291",
    "sg:province":"Hessen",
    "wof:name":"Silat Weisser Kranich (pgb) E.v.",
    "wof:placetype":"venue"
},
  "geometry": {"coordinates":[8.65743,49.911297],"type":"Point"}
}