{
  "type": "Feature",
  "properties": {
    "iso:country":"DE",
    "sg:address":"Goethestr. 52",
    "sg:city":"Wolfschlugen",
    "sg:phone":"+49 7022/50920",
    "sg:postcode":"72649",
    "sg:province":"Baden-W\u00fcrttemberg",
    "wof:name":"Karl Thumm",
    "wof:placetype":"venue"
},
  "geometry": {"coordinates":[9.296102,48.653408],"type":"Point"}
}