{
  "type": "Feature",
  "properties": {
    "iso:country":"DE",
    "sg:address":"Landshuter Str. 9",
    "sg:city":"Essenbach",
    "sg:phone":"+49 8703/2474",
    "sg:postcode":"84051",
    "sg:province":"Bayern",
    "wof:name":"I. Kammermeier",
    "wof:placetype":"venue"
},
  "geometry": {"coordinates":[12.21731,48.612652],"type":"Point"}
}