{
  "type": "Feature",
  "properties": {
    "iso:country":"DE",
    "sg:address":"Karlsbach 16",
    "sg:city":"Waldkirchen",
    "sg:phone":"+49 8581/8666",
    "sg:postcode":"94065",
    "sg:province":"Bayern",
    "wof:name":"Kath. Pfarramt St. Josef",
    "wof:placetype":"venue"
},
  "geometry": {"coordinates":[13.5762653351,48.7691116333],"type":"Point"}
}