{
  "type": "Feature",
  "properties": {
    "iso:country":"DE",
    "sg:address":"Hardtstr. 35",
    "sg:city":"Bad Neuenahr-Ahrweiler",
    "sg:phone":"+49 2641/25583",
    "sg:postcode":"53474",
    "sg:province":"Rheinland-Pfalz",
    "wof:name":"Heinrich Meinke Rechtsanwalt",
    "wof:placetype":"venue"
},
  "geometry": {"coordinates":[7.1290850639,50.5388031006],"type":"Point"}
}