{
  "type": "Feature",
  "properties": {
    "iso:country":"DE",
    "sg:address":"Schulstr. 25",
    "sg:city":"Siegen",
    "sg:phone":"+49 271/390766",
    "sg:postcode":"57080",
    "sg:province":"Nordrhein-Westfalen",
    "wof:name":"Gerhard Leuckel",
    "wof:placetype":"venue"
},
  "geometry": {"coordinates":[8.035057,50.8288],"type":"Point"}
}