{
  "type": "Feature",
  "properties": {
    "iso:country":"DE",
    "sg:address":"Tersteegenstr. 25",
    "sg:city":"Solingen",
    "sg:phone":"+49 212/593232",
    "sg:postcode":"42653",
    "sg:province":"Nordrhein-Westfalen",
    "wof:name":"Lauterjung & Co.",
    "wof:placetype":"venue"
},
  "geometry": {"coordinates":[7.0805840492,51.196647644],"type":"Point"}
}