{
  "type": "Feature",
  "properties": {
    "iso:country":"DE",
    "sg:address":"Amselweg 11",
    "sg:city":"Sulzberg",
    "sg:phone":"+49 8376/8778",
    "sg:postcode":"87477",
    "sg:province":"Bayern",
    "wof:name":"Walter Tr\u00e4xler",
    "wof:placetype":"venue"
},
  "geometry": {"coordinates":[10.3515396118,47.6581687927],"type":"Point"}
}