{
  "type": "Feature",
  "properties": {
    "iso:country":"DE",
    "sg:address":"Blumenstr. 37",
    "sg:city":"Munich",
    "sg:classifiers":[
        {
            "category":"Professional",
            "subcategory":"Computer Services",
            "type":"Services"
        }
    ],
    "sg:postcode":"80331",
    "sg:tags":[
        "software-development",
        "web"
    ],
    "sg:website":"http://www.bumblehood.com",
    "wof:name":"Bumblehood",
    "wof:placetype":"venue"
},
  "geometry": {"coordinates":[11.5696891,48.1319712],"type":"Point"}
}