{
  "type": "Feature",
  "properties": {
    "iso:country":"DE",
    "sg:address":"Dorfstr. 19",
    "sg:city":"Mustin",
    "sg:phone":"+49 4546/485",
    "sg:postcode":"23911",
    "sg:province":"Schleswig-Holstein",
    "wof:name":"Hans-heinrich Warncke",
    "wof:placetype":"venue"
},
  "geometry": {"coordinates":[10.885941,53.684917],"type":"Point"}
}