{
  "type": "Feature",
  "properties": {
    "iso:country":"DE",
    "sg:address":"Zementstr. 13",
    "sg:city":"Kirchheim",
    "sg:phone":"+49 7021/3282",
    "sg:postcode":"73230",
    "sg:province":"Baden-W\u00fcrttemberg",
    "wof:name":"Gerhard Weiss",
    "wof:placetype":"venue"
},
  "geometry": {"coordinates":[9.460567,48.650818],"type":"Point"}
}