{
  "type": "Feature",
  "properties": {
    "iso:country":"DE",
    "sg:address":"Bahnhofstr. 122",
    "sg:city":"Henstedt-Ulzburg",
    "sg:phone":"+49 4193/950752",
    "sg:postcode":"24558",
    "sg:province":"Schleswig-Holstein",
    "wof:name":"W. Heidecker Gmbh",
    "wof:placetype":"venue"
},
  "geometry": {"coordinates":[9.977171,53.791985],"type":"Point"}
}