{
  "type": "Feature",
  "properties": {
    "iso:country":"DE",
    "sg:address":"Dresdner Str. 15",
    "sg:city":"Schwandorf",
    "sg:phone":"+49 4960/562055",
    "sg:postcode":"92421",
    "sg:province":"Bayern",
    "wof:name":"Elektro Werth Gmbh",
    "wof:placetype":"venue"
},
  "geometry": {"coordinates":[9.366245,50.274281],"type":"Point"}
}