{
  "type": "Feature",
  "properties": {
    "iso:country":"DE",
    "sg:address":"Wegem\u00fchle 4",
    "sg:city":"F\u00fcrstenau",
    "sg:phone":"+49 5901/1250",
    "sg:postcode":"49584",
    "sg:province":"Niedersachsen",
    "wof:name":"Freibad",
    "wof:placetype":"venue"
},
  "geometry": {"coordinates":[7.6812009811,52.5184555054],"type":"Point"}
}