{
  "type": "Feature",
  "properties": {
    "iso:country":"DE",
    "sg:address":"Homberger Str. 12",
    "sg:city":"D\u00fcsseldorf",
    "sg:postcode":"40474",
    "sg:province":"Nordrhein-Westfalen",
    "wof:name":"Content Limburg Bautr\u00e4ger Gmbh",
    "wof:placetype":"venue"
},
  "geometry": {"coordinates":[6.771166,51.24258],"type":"Point"}
}