{
  "type": "Feature",
  "properties": {
    "iso:country":"DE",
    "sg:address":"M\u00fcnsterstr. 9-11",
    "sg:city":"Hilter",
    "sg:postcode":"49176",
    "sg:province":"Niedersachsen",
    "wof:name":"Euro Eddys Family-fun Center Magdeburg Verwaltungs Gmbh",
    "wof:placetype":"venue"
},
  "geometry": {"coordinates":[8.1330003738,52.1361351013],"type":"Point"}
}