{
  "type": "Feature",
  "properties": {
    "iso:country":"DE",
    "sg:address":"Erbacher Str. 23",
    "sg:city":"Breuberg",
    "sg:phone":"+49 4961/65579",
    "sg:postcode":"64747",
    "sg:province":"Hessen",
    "wof:name":"Sparkasse Odenwaldkreis",
    "wof:placetype":"venue"
},
  "geometry": {"coordinates":[9.032753,49.817669],"type":"Point"}
}