{
  "type": "Feature",
  "properties": {
    "iso:country":"DE",
    "sg:address":"Alfred-Nobel-Str. 22",
    "sg:city":"Unna",
    "sg:postcode":"59423",
    "sg:province":"Nordrhein-Westfalen",
    "wof:name":"Joy Com Gmbh",
    "wof:placetype":"venue"
},
  "geometry": {"coordinates":[7.723243,51.533176],"type":"Point"}
}