{
  "type": "Feature",
  "properties": {
    "iso:country":"DE",
    "sg:address":"Nikolaistr. 59",
    "sg:city":"Leipzig",
    "sg:phone":"+49 341/9806060",
    "sg:postcode":"04109",
    "sg:province":"Sachsen",
    "wof:name":"Foto-rechnitz",
    "wof:placetype":"venue"
},
  "geometry": {"coordinates":[12.3784599304,51.3434410095],"type":"Point"}
}