{
  "type": "Feature",
  "properties": {
    "iso:country":"DE",
    "sg:address":"Steigstr. 17",
    "sg:city":"Gau-Bischofsheim",
    "sg:phone":"+49 6135/92330",
    "sg:postcode":"55296",
    "sg:province":"Rheinland-Pfalz",
    "wof:name":"Rudolf Behlendorf Steuerberater",
    "wof:placetype":"venue"
},
  "geometry": {"coordinates":[8.2709884644,49.9144020081],"type":"Point"}
}