{
  "type": "Feature",
  "properties": {
    "iso:country":"DE",
    "sg:address":"Desinger\u00f6der Str. 25",
    "sg:city":"Duderstadt",
    "sg:phone":"+49 5527/8749",
    "sg:postcode":"37115",
    "sg:province":"Niedersachsen",
    "wof:name":"Rudolf B\u00f6meke",
    "wof:placetype":"venue"
},
  "geometry": {"coordinates":[10.189071,51.528034],"type":"Point"}
}