{
  "type": "Feature",
  "properties": {
    "iso:country":"DE",
    "sg:address":"M\u00fcllerstr. 11",
    "sg:city":"Frankfurt",
    "sg:postcode":"60486",
    "sg:province":"Hessen",
    "wof:name":"Mert Global Gmbh",
    "wof:placetype":"venue"
},
  "geometry": {"coordinates":[8.629905,50.111019],"type":"Point"}
}