{
  "type": "Feature",
  "properties": {
    "iso:country":"DE",
    "sg:address":"Im Plattenpesch 1",
    "sg:city":"Bitburg",
    "sg:phone":"+49 6561/4644",
    "sg:postcode":"54634",
    "sg:province":"Rheinland-Pfalz",
    "wof:name":"G. Bopp",
    "wof:placetype":"venue"
},
  "geometry": {"coordinates":[6.527709,49.972282],"type":"Point"}
}