{
  "type": "Feature",
  "properties": {
    "iso:country":"DE",
    "sg:address":"Rudolf-Roth-Str. 18",
    "sg:city":"Leutkirch",
    "sg:phone":"+49 7561/800",
    "sg:postcode":"88299",
    "sg:province":"Baden-W\u00fcrttemberg",
    "wof:name":"Zentrales Redaktionsarchiv Der Schw\u00e4bischen Zeitung",
    "wof:placetype":"venue"
},
  "geometry": {"coordinates":[10.018016,47.821434],"type":"Point"}
}