{
  "type": "Feature",
  "properties": {
    "iso:country":"DE",
    "sg:address":"Senefelderstr. 9 a",
    "sg:city":"Braunschweig",
    "sg:phone":"+49 531/612346",
    "sg:postcode":"38124",
    "sg:province":"Niedersachsen",
    "wof:name":"Suncoast & Ocean Shoe Design Gmbh",
    "wof:placetype":"venue"
},
  "geometry": {"coordinates":[10.52894,52.218208],"type":"Point"}
}