{
  "type": "Feature",
  "properties": {
    "iso:country":"DE",
    "sg:address":"Albertus-Magnus-Str. 25",
    "sg:city":"Stein",
    "sg:phone":"+49 911/686924",
    "sg:postcode":"90547",
    "sg:province":"Bayern",
    "wof:name":"St. Albertus Magnus",
    "wof:placetype":"venue"
},
  "geometry": {"coordinates":[11.007416,49.407394],"type":"Point"}
}