{
  "type": "Feature",
  "properties": {
    "iso:country":"DE",
    "sg:address":"Kirchleiner Str. 4",
    "sg:city":"Burgkunstadt",
    "sg:phone":"+49 9572/1536",
    "sg:postcode":"96224",
    "sg:province":"Bayern",
    "wof:name":"Herbert Kaufmann",
    "wof:placetype":"venue"
},
  "geometry": {"coordinates":[11.256317,50.140076],"type":"Point"}
}