{
  "type": "Feature",
  "properties": {
    "iso:country":"DE",
    "sg:address":"Falkensteiner Str. 36",
    "sg:city":"Roding",
    "sg:phone":"+49 9461/7124",
    "sg:postcode":"93426",
    "sg:province":"Bayern",
    "wof:name":"Christa Kerscher",
    "wof:placetype":"venue"
},
  "geometry": {"coordinates":[12.5182104111,49.1923599243],"type":"Point"}
}