{
  "type": "Feature",
  "properties": {
    "iso:country":"DE",
    "sg:address":"Markt 19",
    "sg:city":"Husum",
    "sg:phone":"+49 4841/82875",
    "sg:postcode":"25813",
    "sg:province":"Schleswig-Holstein",
    "wof:name":"Walburga B\u00f6ke Heilpraktikerin",
    "wof:placetype":"venue"
},
  "geometry": {"coordinates":[9.0521802902,54.4775466919],"type":"Point"}
}