{
  "type": "Feature",
  "properties": {
    "iso:country":"DE",
    "sg:address":"Am Anger 3",
    "sg:city":"Diedorf",
    "sg:phone":"+49 8238/959877",
    "sg:postcode":"86420",
    "sg:province":"Bayern",
    "wof:name":"Dri Dek Bodenbel\u00e4ge",
    "wof:placetype":"venue"
},
  "geometry": {"coordinates":[10.7489452362,48.3570365906],"type":"Point"}
}