{
  "type": "Feature",
  "properties": {
    "iso:country":"DE",
    "sg:address":"Habsburgerstr. 7",
    "sg:city":"Aalen",
    "sg:phone":"+49 7367/96210",
    "sg:postcode":"73432",
    "sg:province":"Baden-W\u00fcrttemberg",
    "wof:name":"W\u00f6rle Edelstahl Gmbh",
    "wof:placetype":"venue"
},
  "geometry": {"coordinates":[10.19249,48.79892],"type":"Point"}
}