{
  "type": "Feature",
  "properties": {
    "iso:country":"DE",
    "sg:address":"Eichenallee",
    "sg:city":"Leegebruch",
    "sg:postcode":"16767",
    "sg:province":"Brandenburg",
    "wof:name":"B. Lehmpuhl",
    "wof:placetype":"venue"
},
  "geometry": {"coordinates":[13.19121,52.723797],"type":"Point"}
}