{
  "type": "Feature",
  "properties": {
    "iso:country":"DE",
    "sg:address":"Marienstr. 28",
    "sg:city":"Stuttgart",
    "sg:phone":"+49 711/2261007",
    "sg:postcode":"70178",
    "sg:province":"Baden-W\u00fcrttemberg",
    "wof:name":"Meyer Rechtsanwalt",
    "wof:placetype":"venue"
},
  "geometry": {"coordinates":[9.1723003387,48.7728233337],"type":"Point"}
}