{
  "type": "Feature",
  "properties": {
    "iso:country":"DE",
    "sg:address":"Am Postkopf 4",
    "sg:city":"Hagen",
    "sg:phone":"+49 2331/45478",
    "sg:postcode":"58135",
    "sg:province":"Nordrhein-Westfalen",
    "wof:name":"Fred Knepper",
    "wof:placetype":"venue"
},
  "geometry": {"coordinates":[7.426904,51.341911],"type":"Point"}
}