{
  "type": "Feature",
  "properties": {
    "iso:country":"DE",
    "sg:address":"Talstra\u00dfe 64",
    "sg:city":"Schrieshiem/Heidlelberg",
    "sg:phone":"+49 6203",
    "sg:postcode":"69198",
    "sg:province":"Baden-W\u00fcrttemberg",
    "wof:name":"The Bluestones Online",
    "wof:placetype":"venue"
},
  "geometry": {"coordinates":[8.666644,49.477036],"type":"Point"}
}