{
  "type": "Feature",
  "properties": {
    "iso:country":"DE",
    "sg:address":"Schl\u00fcterstr. 6",
    "sg:city":"Hamburg",
    "sg:postcode":"20146",
    "sg:province":"Hamburg",
    "wof:name":"Hbt Hamburger Beteiligungs- Und Textilhandelsges. Mbh",
    "wof:placetype":"venue"
},
  "geometry": {"coordinates":[9.987103,53.564728],"type":"Point"}
}