{
  "type": "Feature",
  "properties": {
    "iso:country":"DE",
    "sg:address":"Hoiruper Str. 8 A",
    "sg:city":"Berlin",
    "sg:phone":"+49 30/8035537",
    "sg:postcode":"14129",
    "sg:province":"Berlin",
    "wof:name":"Georg C. Frommholz",
    "wof:placetype":"venue"
},
  "geometry": {"coordinates":[13.1975107193,52.435634613],"type":"Point"}
}