{
  "type": "Feature",
  "properties": {
    "iso:country":"DE",
    "sg:address":"Im Gewerbepark 2",
    "sg:city":"Schalksm\u00fchle",
    "sg:phone":"+49 2355/8301",
    "sg:postcode":"58579",
    "sg:province":"Nordrhein-Westfalen",
    "wof:name":"Lumberg Connect Gmbh & Co Kg",
    "wof:placetype":"venue"
},
  "geometry": {"coordinates":[7.54902,51.258121],"type":"Point"}
}