{
  "type": "Feature",
  "properties": {
    "iso:country":"DE",
    "sg:address":"Westerwaldstrasse 9a",
    "sg:city":"Rengsdorf",
    "sg:phone":"+49 2634/980980",
    "sg:postcode":"56579",
    "sg:province":"Rheinland-Pfalz",
    "wof:name":"Koch Architekturb\u00fcro Rengsdorf",
    "wof:placetype":"venue"
},
  "geometry": {"coordinates":[7.49728,50.50066],"type":"Point"}
}