{
  "type": "Feature",
  "properties": {
    "iso:country":"DE",
    "sg:address":"Bischofsheim 1",
    "sg:city":"Zeil",
    "sg:postcode":"97475",
    "sg:province":"Bayern",
    "wof:name":"S. A. T. Theis Deutschland Gmbh",
    "wof:placetype":"venue"
},
  "geometry": {"coordinates":[10.6136798859,50.0228691101],"type":"Point"}
}