{
  "type": "Feature",
  "properties": {
    "iso:country":"DE",
    "sg:address":"Hauptstr. 31",
    "sg:city":"Reken",
    "sg:phone":"+49 2864/1069",
    "sg:postcode":"48734",
    "sg:province":"Nordrhein-Westfalen",
    "wof:name":"Hotel-restaurant Theodor Vogelwiesche",
    "wof:placetype":"venue"
},
  "geometry": {"coordinates":[7.041478157,51.8322410583],"type":"Point"}
}