{
  "type": "Feature",
  "properties": {
    "iso:country":"DE",
    "sg:address":"Turmstr. 13",
    "sg:city":"Bonn",
    "sg:phone":"+49 228/374467",
    "sg:postcode":"53175",
    "sg:province":"Nordrhein-Westfalen",
    "wof:name":"Restaurant Im Steinhaus",
    "wof:placetype":"venue"
},
  "geometry": {"coordinates":[7.1656761169,50.6987380981],"type":"Point"}
}