{
  "type": "Feature",
  "properties": {
    "iso:country":"DE",
    "sg:address":"St.-Margarethen-Str. 3",
    "sg:city":"Kenn",
    "sg:phone":"+49 6502/91440",
    "sg:postcode":"54344",
    "sg:province":"Rheinland-Pfalz",
    "wof:name":"Die Neue Apotheke Inh. Erika Notte",
    "wof:placetype":"venue"
},
  "geometry": {"coordinates":[6.721908,49.801937],"type":"Point"}
}