{
  "type": "Feature",
  "properties": {
    "iso:country":"DE",
    "sg:address":"Annastr. 21",
    "sg:city":"Rimbach",
    "sg:phone":"+49 6253/6589",
    "sg:postcode":"64668",
    "sg:province":"Hessen",
    "wof:name":"Philipp Schuch",
    "wof:placetype":"venue"
},
  "geometry": {"coordinates":[8.7577438354,49.6257743835],"type":"Point"}
}