{
  "type": "Feature",
  "properties": {
    "iso:country":"DE",
    "sg:address":"Schopenhauerstr. 26",
    "sg:city":"Berlin",
    "sg:phone":"+49 30/8030880",
    "sg:postcode":"14129",
    "sg:province":"Berlin",
    "wof:name":"Izt Institut F\u00fcr Zukunftsstudien Und",
    "wof:placetype":"venue"
},
  "geometry": {"coordinates":[13.2142047882,52.4353752136],"type":"Point"}
}