{
  "type": "Feature",
  "properties": {
    "iso:country":"DE",
    "sg:address":"Martin-Luther-Str. 39",
    "sg:city":"Ludwigsburg",
    "sg:phone":"+49 7141/927631",
    "sg:postcode":"71636",
    "sg:province":"Baden-W\u00fcrttemberg",
    "wof:name":"Massagepraxis Elisabeth Rosemeier",
    "wof:placetype":"venue"
},
  "geometry": {"coordinates":[9.180676,48.894505],"type":"Point"}
}