{
  "type": "Feature",
  "properties": {
    "iso:country":"DE",
    "sg:address":"Kreuzgasse 30",
    "sg:city":"R\u00f6dermark",
    "sg:phone":"+49 6074/7232",
    "sg:postcode":"63322",
    "sg:province":"Hessen",
    "wof:name":"A. Wunderlich",
    "wof:placetype":"venue"
},
  "geometry": {"coordinates":[8.795832,49.967411],"type":"Point"}
}