{
  "type": "Feature",
  "properties": {
    "iso:country":"DE",
    "sg:address":"Letteweg 62",
    "sg:city":"Iserlohn",
    "sg:phone":"+49 2371/94590",
    "sg:postcode":"58640",
    "sg:province":"Nordrhein-Westfalen",
    "wof:name":"Dr. Michael Krutz",
    "wof:placetype":"venue"
},
  "geometry": {"coordinates":[7.6435709,51.45154953],"type":"Point"}
}