{
  "type": "Feature",
  "properties": {
    "iso:country":"DE",
    "sg:address":"Bismarckstr. 303",
    "sg:city":"Gelsenkirchen",
    "sg:postcode":"45889",
    "sg:province":"Nordrhein-Westfalen",
    "wof:name":"Medi-markt Homecare Service Gmbh",
    "wof:placetype":"venue"
},
  "geometry": {"coordinates":[7.1106247902,51.5355873108],"type":"Point"}
}