{
  "type": "Feature",
  "properties": {
    "iso:country":"DE",
    "sg:address":"Br\u00fcderstr. 9",
    "sg:city":"Angerm\u00fcnde",
    "sg:phone":"+49 3331/32926",
    "sg:postcode":"16278",
    "sg:province":"Brandenburg",
    "wof:name":"Werner Holtz",
    "wof:placetype":"venue"
},
  "geometry": {"coordinates":[14.005209,53.017212],"type":"Point"}
}