{
  "type": "Feature",
  "properties": {
    "iso:country":"DE",
    "sg:address":"Bayerwaldstr. 29",
    "sg:city":"M\u00fcnchen",
    "sg:phone":"+49 89/6780940",
    "sg:postcode":"81737",
    "sg:province":"Bayern",
    "wof:name":"Maschinenfabrik Herbert Meyer Gmbh",
    "wof:placetype":"venue"
},
  "geometry": {"coordinates":[11.630411,48.089283],"type":"Point"}
}