{
  "type": "Feature",
  "properties": {
    "iso:country":"DE",
    "sg:address":"Lindenstr. 280",
    "sg:city":"M\u00f6nchengladbach",
    "sg:phone":"+49 2161/86433",
    "sg:postcode":"41063",
    "sg:province":"Nordrhein-Westfalen",
    "wof:name":"J. Offergeld",
    "wof:placetype":"venue"
},
  "geometry": {"coordinates":[6.4115338326,51.2050933838],"type":"Point"}
}