{
  "type": "Feature",
  "properties": {
    "iso:country":"DE",
    "sg:address":"Kirchenstr. 8",
    "sg:city":"Drochtersen",
    "sg:phone":"+49 4143/1307",
    "sg:postcode":"21706",
    "sg:province":"Niedersachsen",
    "wof:name":"K. Beulert",
    "wof:placetype":"venue"
},
  "geometry": {"coordinates":[9.3849687576,53.7088661194],"type":"Point"}
}