{
  "type": "Feature",
  "properties": {
    "iso:country":"DE",
    "sg:address":"Heinrich-Hertz-Ring 3",
    "sg:city":"Schwarzheide",
    "sg:postcode":"01987",
    "sg:province":"Brandenburg",
    "wof:name":"Stahlbaumontagen Hopisch Gmbh",
    "wof:placetype":"venue"
},
  "geometry": {"coordinates":[13.821762,51.471657],"type":"Point"}
}