{
  "type": "Feature",
  "properties": {
    "iso:country":"DE",
    "sg:address":"Walter-Maack-Str. 4",
    "sg:city":"Rinteln",
    "sg:phone":"+49 5751/44638",
    "sg:postcode":"31737",
    "sg:province":"Niedersachsen",
    "wof:name":"Menke Gmbh",
    "wof:placetype":"venue"
},
  "geometry": {"coordinates":[9.075905,52.179428],"type":"Point"}
}