{
  "type": "Feature",
  "properties": {
    "iso:country":"DE",
    "sg:address":"Hermann-L\u00f6ns-Str. 20",
    "sg:city":"H\u00fcrth",
    "sg:phone":"+49 2233/792051",
    "sg:postcode":"50354",
    "sg:province":"Nordrhein-Westfalen",
    "wof:name":"Lichtblick Gastronomie- Betriebe Gmbh",
    "wof:placetype":"venue"
},
  "geometry": {"coordinates":[6.897999,50.878464],"type":"Point"}
}