{
  "type": "Feature",
  "properties": {
    "iso:country":"DE",
    "sg:address":"Pletschm\u00fchlenstr. 66",
    "sg:city":"Wassenberg",
    "sg:phone":"+49 2432/4549",
    "sg:postcode":"41849",
    "sg:province":"Nordrhein-Westfalen",
    "wof:name":"J. Gerighausen Obstanbau",
    "wof:placetype":"venue"
},
  "geometry": {"coordinates":[6.1457300186,51.0911407471],"type":"Point"}
}