{
  "type": "Feature",
  "properties": {
    "iso:country":"DE",
    "sg:address":"Hans-Thoma-Str. 89-99",
    "sg:city":"Mannheim",
    "sg:postcode":"68163",
    "sg:province":"Baden-W\u00fcrttemberg",
    "wof:name":"Gerhard J\u00f6rger Verwaltungsgesellschaft Mbh",
    "wof:placetype":"venue"
},
  "geometry": {"coordinates":[8.540203,49.473095],"type":"Point"}
}