{
  "type": "Feature",
  "properties": {
    "iso:country":"DE",
    "sg:address":"Weiherstr. 54",
    "sg:city":"Illingen",
    "sg:phone":"+49 6825/42549",
    "sg:postcode":"66557",
    "sg:province":"Saarland",
    "wof:name":"Frederic Adiasse",
    "wof:placetype":"venue"
},
  "geometry": {"coordinates":[7.04251,49.364208],"type":"Point"}
}