{
  "type": "Feature",
  "properties": {
    "iso:country":"DE",
    "sg:address":"Backhausgasse 12",
    "sg:city":"Biebelsheim",
    "sg:phone":"+49 6701/2501",
    "sg:postcode":"55546",
    "sg:province":"Rheinland-Pfalz",
    "wof:name":"T. Wentzel",
    "wof:placetype":"venue"
},
  "geometry": {"coordinates":[7.9389491081,49.8723831177],"type":"Point"}
}