{
  "type": "Feature",
  "properties": {
    "iso:country":"DE",
    "sg:address":"Marktstr. 33",
    "sg:city":"Rudolstadt",
    "sg:phone":"+49 3672/424201",
    "sg:postcode":"07407",
    "sg:province":"Th\u00fcringen",
    "wof:name":"Fielmann Ag & Co.",
    "wof:placetype":"venue"
},
  "geometry": {"coordinates":[11.338736,50.720016],"type":"Point"}
}