{
  "type": "Feature",
  "properties": {
    "iso:country":"DE",
    "sg:address":"In der Weide 1",
    "sg:city":"Martfeld",
    "sg:phone":"+49 4255/1308",
    "sg:postcode":"27327",
    "sg:province":"Niedersachsen",
    "wof:name":"Heiner Rahlmann E. K.",
    "wof:placetype":"venue"
},
  "geometry": {"coordinates":[9.0571174622,52.8744621277],"type":"Point"}
}