{
  "type": "Feature",
  "properties": {
    "iso:country":"DE",
    "sg:address":"Wagnerstr. 4",
    "sg:city":"Weingarten",
    "sg:phone":"+49 751/41333",
    "sg:postcode":"88250",
    "sg:province":"Baden-W\u00fcrttemberg",
    "wof:name":"Georg Junginger",
    "wof:placetype":"venue"
},
  "geometry": {"coordinates":[9.6577062607,47.8100242615],"type":"Point"}
}