{
  "type": "Feature",
  "properties": {
    "iso:country":"DE",
    "sg:address":"Puricellistr. 15",
    "sg:city":"Regensburg",
    "sg:phone":"+49 941/27664",
    "sg:postcode":"93049",
    "sg:province":"Bayern",
    "wof:name":"Mangia Bene Gmbh",
    "wof:placetype":"venue"
},
  "geometry": {"coordinates":[12.058583,49.022354],"type":"Point"}
}