{
  "type": "Feature",
  "properties": {
    "iso:country":"DE",
    "sg:address":"Von-Dalberg-Str. 26 a",
    "sg:city":"Ruppertsberg",
    "sg:phone":"+49 6326/8881",
    "sg:postcode":"67152",
    "sg:province":"Rheinland-Pfalz",
    "wof:name":"Johannes Und Stefan Zeck",
    "wof:placetype":"venue"
},
  "geometry": {"coordinates":[8.199177742,49.4011421204],"type":"Point"}
}