{
  "type": "Feature",
  "properties": {
    "iso:country":"DE",
    "sg:address":"Langestr. 51",
    "sg:city":"B\u00fctzow",
    "sg:phone":"+49 38461/52538",
    "sg:postcode":"18246",
    "sg:province":"Mecklenburg-Vorpommern",
    "wof:name":"Ackermann H\u00f6rger\u00e4te Kg",
    "wof:placetype":"venue"
},
  "geometry": {"coordinates":[11.981778,53.847904],"type":"Point"}
}