{
  "type": "Feature",
  "properties": {
    "iso:country":"DE",
    "sg:address":"Windecker Str. 43",
    "sg:city":"Nidderau",
    "sg:phone":"+49 6187/292268",
    "sg:postcode":"61130",
    "sg:province":"Hessen",
    "wof:name":"China Restaurant Chan's",
    "wof:placetype":"venue"
},
  "geometry": {"coordinates":[8.8625116348,50.2342529297],"type":"Point"}
}