{
  "type": "Feature",
  "properties": {
    "iso:country":"DE",
    "sg:address":"Heisenbergstr. 16",
    "sg:city":"Bergheim",
    "sg:phone":"+49 2271/65398",
    "sg:postcode":"50126",
    "sg:province":"Nordrhein-Westfalen",
    "wof:name":"Weber",
    "wof:placetype":"venue"
},
  "geometry": {"coordinates":[6.622971,50.946861],"type":"Point"}
}