{
  "type": "Feature",
  "properties": {
    "iso:country":"DE",
    "sg:address":"Bahnhofstr. 3",
    "sg:city":"Sprockh\u00f6vel",
    "sg:phone":"+49 2324/7585",
    "sg:postcode":"45549",
    "sg:province":"Nordrhein-Westfalen",
    "wof:name":"G. Lippert Steuerberater",
    "wof:placetype":"venue"
},
  "geometry": {"coordinates":[7.2454891205,51.364528656],"type":"Point"}
}