{
  "type": "Feature",
  "properties": {
    "iso:country":"DE",
    "sg:address":"Stedinger Str. 4",
    "sg:city":"Delmenhorst",
    "sg:postcode":"27753",
    "sg:province":"Niedersachsen",
    "wof:name":"Internet Services Tatiana Zablotskaia E. Kfr.",
    "wof:placetype":"venue"
},
  "geometry": {"coordinates":[8.6305103302,53.0610809326],"type":"Point"}
}