{
  "type": "Feature",
  "properties": {
    "iso:country":"DE",
    "sg:address":"Wehrb\u00fcsch 2",
    "sg:city":"\u00dcrzig",
    "sg:phone":"+49 6532/3365",
    "sg:postcode":"54539",
    "sg:province":"Rheinland-Pfalz",
    "wof:name":"Viktor Oster",
    "wof:placetype":"venue"
},
  "geometry": {"coordinates":[6.9985752106,49.9826660156],"type":"Point"}
}