{
  "type": "Feature",
  "properties": {
    "iso:country":"DE",
    "sg:address":"Bernardstr. 14-16",
    "sg:city":"Offenbach",
    "sg:phone":"+49 69/885620",
    "sg:postcode":"63067",
    "sg:province":"Hessen",
    "wof:name":"\u00d6zer Gmbh",
    "wof:placetype":"venue"
},
  "geometry": {"coordinates":[8.7560501099,50.1078414917],"type":"Point"}
}