{
  "type": "Feature",
  "properties": {
    "iso:country":"DE",
    "sg:address":"Unterberg",
    "sg:city":"Marktschellenberg",
    "sg:postcode":"83487",
    "sg:province":"Bayern",
    "wof:name":"Toni-lenz-h\u00fctte",
    "wof:placetype":"venue"
},
  "geometry": {"coordinates":[13.0331039429,47.6906585693],"type":"Point"}
}