{
  "type": "Feature",
  "properties": {
    "iso:country":"DE",
    "sg:address":"Sandusweg 3",
    "sg:city":"Wettenberg",
    "sg:phone":"+49 641/8779020",
    "sg:postcode":"35435",
    "sg:province":"Hessen",
    "wof:name":"Unternehmeneuro",
    "wof:placetype":"venue"
},
  "geometry": {"coordinates":[8.6612911224,50.6187515259],"type":"Point"}
}