{
  "type": "Feature",
  "properties": {
    "iso:country":"DE",
    "sg:address":"Hausen 12",
    "sg:city":"Eitorf",
    "sg:phone":"+49 2243/6631",
    "sg:postcode":"53783",
    "sg:province":"Nordrhein-Westfalen",
    "wof:name":"M. Baltazar-regado",
    "wof:placetype":"venue"
},
  "geometry": {"coordinates":[7.42851,50.743855],"type":"Point"}
}