{
  "type": "Feature",
  "properties": {
    "iso:country":"DE",
    "sg:address":"Eburonenstr. 10",
    "sg:city":"\u00dcbach-Palenberg",
    "sg:phone":"+49 2451/43340",
    "sg:postcode":"52531",
    "sg:province":"Nordrhein-Westfalen",
    "wof:name":"Lelle Bautr\u00e4ger Gmbh",
    "wof:placetype":"venue"
},
  "geometry": {"coordinates":[6.097042,50.920052],"type":"Point"}
}