{
  "type": "Feature",
  "properties": {
    "iso:country":"DE",
    "sg:address":"Gartenstr. 11",
    "sg:city":"Weiterstadt",
    "sg:phone":"+49 6150/590099",
    "sg:postcode":"64331",
    "sg:province":"Hessen",
    "wof:name":"Baudekoration Horn Gmbh",
    "wof:placetype":"venue"
},
  "geometry": {"coordinates":[8.60283,49.927612],"type":"Point"}
}