{
  "type": "Feature",
  "properties": {
    "iso:country":"DE",
    "sg:city":"Apen",
    "sg:phone":"+49 4489/5954",
    "sg:postcode":"26689",
    "sg:province":"Niedersachsen",
    "wof:name":"C. Und J. Wask\u00f6nig-pedaci Architekten",
    "wof:placetype":"venue"
},
  "geometry": {"coordinates":[7.806595,53.218552],"type":"Point"}
}