{
  "type": "Feature",
  "properties": {
    "iso:country":"DE",
    "sg:address":"Friedrichstr. 51a",
    "sg:city":"Voerde",
    "sg:phone":"+49 2855/15136",
    "sg:postcode":"46562",
    "sg:province":"Nordrhein-Westfalen",
    "wof:name":"Johann Polzin",
    "wof:placetype":"venue"
},
  "geometry": {"coordinates":[6.70147,51.579296],"type":"Point"}
}