{
  "type": "Feature",
  "properties": {
    "iso:country":"DE",
    "sg:address":"Offinger Str. 7",
    "sg:city":"D\u00fcrmentingen",
    "sg:phone":"+49 7371/965356",
    "sg:postcode":"88525",
    "sg:province":"Baden-W\u00fcrttemberg",
    "wof:name":"Combustin Pharmazeutische Pr\u00e4parate Gmbh",
    "wof:placetype":"venue"
},
  "geometry": {"coordinates":[9.5365772247,48.1401786804],"type":"Point"}
}