{
  "type": "Feature",
  "properties": {
    "iso:country":"DE",
    "sg:address":"Storlachstr. 176",
    "sg:city":"Reutlingen",
    "sg:phone":"+49 7121/93590",
    "sg:postcode":"72760",
    "sg:province":"Baden-W\u00fcrttemberg",
    "wof:name":"Michael Aicheler",
    "wof:placetype":"venue"
},
  "geometry": {"coordinates":[9.2053766251,48.5083389282],"type":"Point"}
}