{
  "type": "Feature",
  "properties": {
    "iso:country":"DE",
    "sg:address":"Oberdreescher Weg 17",
    "sg:city":"Upgant-Schott",
    "sg:phone":"+49 4934/990168",
    "sg:postcode":"26529",
    "sg:province":"Niedersachsen",
    "wof:name":"Zahntechnikvertrieb Stark Gmbh",
    "wof:placetype":"venue"
},
  "geometry": {"coordinates":[7.255508,53.513649],"type":"Point"}
}