{
  "type": "Feature",
  "properties": {
    "iso:country":"DE",
    "sg:address":"Obertorstr. 1",
    "sg:city":"Uettingen",
    "sg:phone":"+49 9369/391",
    "sg:postcode":"97292",
    "sg:province":"Bayern",
    "wof:name":"Ev. Pfarramt",
    "wof:placetype":"venue"
},
  "geometry": {"coordinates":[9.7261419296,49.7959709167],"type":"Point"}
}