{
  "type": "Feature",
  "properties": {
    "iso:country":"DE",
    "sg:address":"Max-Keith-Str. 42",
    "sg:city":"Essen",
    "sg:phone":"+49 201/8586668",
    "sg:postcode":"45136",
    "sg:province":"Nordrhein-Westfalen",
    "wof:name":"Gerber Werbebau Gmbh",
    "wof:placetype":"venue"
},
  "geometry": {"coordinates":[7.026963,51.434109],"type":"Point"}
}