{
  "type": "Feature",
  "properties": {
    "iso:country":"DE",
    "sg:address":"Dorfplatz 2",
    "sg:city":"Burghausen",
    "sg:phone":"+49 341/4511581",
    "sg:postcode":"04430",
    "sg:province":"Bayern",
    "wof:name":"Apotheke Burghausen Inh. Martina M\u00fcller",
    "wof:placetype":"venue"
},
  "geometry": {"coordinates":[10.160157,50.248829],"type":"Point"}
}