{
  "type": "Feature",
  "properties": {
    "iso:country":"DE",
    "sg:address":"Martin-Behaim-Str. 4 a",
    "sg:city":"Neu-Isenburg",
    "sg:postcode":"63263",
    "sg:province":"Hessen",
    "wof:name":"Mi Zwei-m\u00e4rkte Im Internet Gmbh",
    "wof:placetype":"venue"
},
  "geometry": {"coordinates":[8.71086,50.047829],"type":"Point"}
}