{
  "type": "Feature",
  "properties": {
    "iso:country":"DE",
    "sg:address":"Filderst\u00e4dter Str. 10",
    "sg:city":"Oschatz",
    "sg:phone":"+49 4934/3597630",
    "sg:postcode":"04758",
    "sg:province":"Sachsen",
    "wof:name":"Kromer Automobile",
    "wof:placetype":"venue"
},
  "geometry": {"coordinates":[13.0917301178,51.3011054993],"type":"Point"}
}