{
  "type": "Feature",
  "properties": {
    "iso:country":"DE",
    "sg:address":"Fallstr. 34",
    "sg:city":"M\u00fcnchen",
    "sg:phone":"+49 89/724010",
    "sg:postcode":"81369",
    "sg:province":"Bayern",
    "wof:name":"Kassenzahn\u00e4rztliche Vereinigung Bayerns",
    "wof:placetype":"venue"
},
  "geometry": {"coordinates":[11.538814,48.10815],"type":"Point"}
}