{
  "type": "Feature",
  "properties": {
    "iso:country":"DE",
    "sg:address":"Schenkendorfstr. 12",
    "sg:city":"Hamburg",
    "sg:phone":"+49 40/2206166",
    "sg:postcode":"22085",
    "sg:province":"Hamburg",
    "wof:name":"C. Lambertsen",
    "wof:placetype":"venue"
},
  "geometry": {"coordinates":[10.0156612396,53.5765342712],"type":"Point"}
}