{
  "type": "Feature",
  "properties": {
    "iso:country":"DE",
    "sg:address":"Stra\u00dfe des Friedens 5",
    "sg:city":"Hoyerswerda",
    "sg:phone":"+49 3571/408440",
    "sg:postcode":"02977",
    "sg:province":"Sachsen",
    "wof:name":"Rynes Bau Gmbh",
    "wof:placetype":"venue"
},
  "geometry": {"coordinates":[14.256263,51.435108],"type":"Point"}
}