{
  "type": "Feature",
  "properties": {
    "iso:country":"DE",
    "sg:address":"Kastanienallee 29",
    "sg:city":"Kiel",
    "sg:phone":"+49 431/361527",
    "sg:postcode":"24159",
    "sg:province":"Schleswig-Holstein",
    "wof:name":"Frictionless Gmbh",
    "wof:placetype":"venue"
},
  "geometry": {"coordinates":[10.144974,54.371548],"type":"Point"}
}