{
  "type": "Feature",
  "properties": {
    "iso:country":"DE",
    "sg:address":"B\u00e4ckerplatz 8",
    "sg:city":"Allstedt",
    "sg:phone":"+49 34652/338",
    "sg:postcode":"06542",
    "sg:province":"Sachsen-Anhalt",
    "wof:name":"Holk Meye",
    "wof:placetype":"venue"
},
  "geometry": {"coordinates":[11.389653,51.403999],"type":"Point"}
}