{
  "type": "Feature",
  "properties": {
    "iso:country":"DE",
    "sg:address":"Leipziger Str. 97",
    "sg:city":"Dresden",
    "sg:phone":"+49 351/4953184",
    "sg:postcode":"01127",
    "sg:province":"Sachsen",
    "wof:name":"Kasper & Co.",
    "wof:placetype":"venue"
},
  "geometry": {"coordinates":[13.7204008102,51.0757865906],"type":"Point"}
}