{
  "type": "Feature",
  "properties": {
    "iso:country":"DE",
    "sg:address":"Amberger Str. 18",
    "sg:city":"Neunburg",
    "sg:phone":"+49 9672/1342",
    "sg:postcode":"92431",
    "sg:province":"Bayern",
    "wof:name":"Meixner Reiseb\u00fcro",
    "wof:placetype":"venue"
},
  "geometry": {"coordinates":[12.3730201721,49.3463096619],"type":"Point"}
}