{
  "type": "Feature",
  "properties": {
    "iso:country":"DE",
    "sg:address":"Johannesstr. 29",
    "sg:city":"Euskirchen",
    "sg:phone":"+49 2251/10880",
    "sg:postcode":"53881",
    "sg:province":"Nordrhein-Westfalen",
    "wof:name":"Cosmetic Decker Gmbh",
    "wof:placetype":"venue"
},
  "geometry": {"coordinates":[6.752388,50.651772],"type":"Point"}
}