{
  "type": "Feature",
  "properties": {
    "iso:country":"DE",
    "sg:address":"Untertorstr. 18",
    "sg:city":"Milz",
    "sg:postcode":"98631",
    "sg:province":"Th\u00fcringen",
    "wof:name":"H. H\u00f6fer",
    "wof:placetype":"venue"
},
  "geometry": {"coordinates":[10.5327205658,50.3767623901],"type":"Point"}
}