{
  "type": "Feature",
  "properties": {
    "iso:country":"DE",
    "sg:address":"Vor dem Johannistor 7",
    "sg:city":"Aschersleben",
    "sg:phone":"+49 3473/815884",
    "sg:postcode":"06449",
    "sg:province":"Sachsen-Anhalt",
    "wof:name":"Michael Kott Immobilienmakler",
    "wof:placetype":"venue"
},
  "geometry": {"coordinates":[11.4590511322,51.7576446533],"type":"Point"}
}