{
  "type": "Feature",
  "properties": {
    "iso:country":"DE",
    "sg:address":"Wilhelm-R\u00f6nsch-Str. 4",
    "sg:city":"Radeberg",
    "sg:phone":"+49 4935/2843620",
    "sg:postcode":"01454",
    "sg:province":"Sachsen",
    "wof:name":"Aquatherm Gmbh",
    "wof:placetype":"venue"
},
  "geometry": {"coordinates":[13.9248609543,51.1035423279],"type":"Point"}
}