{
  "type": "Feature",
  "properties": {
    "iso:country":"DE",
    "sg:address":"Zugspitzstr. 13",
    "sg:city":"Garmisch-Partenkirchen",
    "sg:phone":"+49 8821/78478",
    "sg:postcode":"82467",
    "sg:province":"Bayern",
    "wof:name":"Jama-bettenfachgesch\u00e4ft Christiane Nitschke-giesel",
    "wof:placetype":"venue"
},
  "geometry": {"coordinates":[11.0840883255,47.4915428162],"type":"Point"}
}