{
  "type": "Feature",
  "properties": {
    "iso:country":"DE",
    "sg:address":"Am Bache 10",
    "sg:city":"Wolfenb\u00fcttel",
    "sg:phone":"+49 5331/26591",
    "sg:postcode":"38304",
    "sg:province":"Niedersachsen",
    "wof:name":"Rotec Consulting Gmbh",
    "wof:placetype":"venue"
},
  "geometry": {"coordinates":[10.5400800705,52.1422691345],"type":"Point"}
}