{
  "type": "Feature",
  "properties": {
    "iso:country":"DE",
    "sg:address":"P\u00fctzstr. 2",
    "sg:city":"Neuss",
    "sg:phone":"+49 4921/3130432",
    "sg:postcode":"41468",
    "sg:province":"Nordrhein-Westfalen",
    "wof:name":"Ise Industrial Supply & Engineering Handels Gmbh",
    "wof:placetype":"venue"
},
  "geometry": {"coordinates":[6.749194,51.178246],"type":"Point"}
}