{
  "type": "Feature",
  "properties": {
    "iso:country":"DE",
    "sg:address":"Valerystr. 98",
    "sg:city":"Unterschlei\u00dfheim",
    "sg:phone":"+49 89/3171414",
    "sg:postcode":"85716",
    "sg:province":"Bayern",
    "wof:name":"Heinz Grundmann Ingenieur",
    "wof:placetype":"venue"
},
  "geometry": {"coordinates":[11.5698070526,48.269985199],"type":"Point"}
}