{
  "type": "Feature",
  "properties": {
    "iso:country":"DE",
    "sg:address":"Driverstr. 22",
    "sg:city":"Vechta",
    "sg:postcode":"49377",
    "sg:province":"Niedersachsen",
    "wof:name":"Wiss. Institut Professur F\u00fcr Didaktik",
    "wof:placetype":"venue"
},
  "geometry": {"coordinates":[8.2935276031,52.7215118408],"type":"Point"}
}