{
  "type": "Feature",
  "properties": {
    "iso:country":"DE",
    "sg:address":"Wilhelmstr. 21",
    "sg:city":"Soltau",
    "sg:phone":"+49 5191/15044",
    "sg:postcode":"29614",
    "sg:province":"Niedersachsen",
    "wof:name":"Wilhelm Grefe",
    "wof:placetype":"venue"
},
  "geometry": {"coordinates":[9.843621254,52.9869537354],"type":"Point"}
}