{
  "type": "Feature",
  "properties": {
    "iso:country":"DE",
    "sg:address":"Nordstr. 55",
    "sg:city":"Olfen",
    "sg:postcode":"59399",
    "sg:province":"Nordrhein-Westfalen",
    "wof:name":"Karl Middelmann Bauunternehmung Und",
    "wof:placetype":"venue"
},
  "geometry": {"coordinates":[7.376629,51.712357],"type":"Point"}
}