{
  "type": "Feature",
  "properties": {
    "iso:country":"DE",
    "sg:address":"Bahnhofstr. 9-14",
    "sg:city":"Kiefersfelden",
    "sg:postcode":"83088",
    "sg:province":"Bayern",
    "wof:name":"Werner Handle Gmbh \u00d6sterreich Zweigniederl. Kiefersfelden",
    "wof:placetype":"venue"
},
  "geometry": {"coordinates":[12.1875543594,47.6100387573],"type":"Point"}
}