{
  "type": "Feature",
  "properties": {
    "iso:country":"DE",
    "sg:address":"Johannesstr. 248",
    "sg:city":"Oer-Erkenschwick",
    "sg:phone":"+49 172 2813269",
    "sg:postcode":"45739",
    "sg:province":"Nordrhein-Westfalen",
    "wof:name":"Heinrich Leichhauer",
    "wof:placetype":"venue"
},
  "geometry": {"coordinates":[7.208666,51.667103],"type":"Point"}
}