{
  "type": "Feature",
  "properties": {
    "iso:country":"DE",
    "sg:address":"Bergstr. 4",
    "sg:city":"Uttenweiler",
    "sg:phone":"+49 7374/1291",
    "sg:postcode":"88524",
    "sg:province":"Baden-W\u00fcrttemberg",
    "wof:name":"Josef Missel",
    "wof:placetype":"venue"
},
  "geometry": {"coordinates":[9.570777,48.165424],"type":"Point"}
}