{
  "type": "Feature",
  "properties": {
    "iso:country":"DE",
    "sg:address":"Kalstert 166",
    "sg:city":"Hilden",
    "sg:phone":"+49 2103/66565",
    "sg:postcode":"40724",
    "sg:province":"Nordrhein-Westfalen",
    "wof:name":"Hans Hellenkamp Garten- Und",
    "wof:placetype":"venue"
},
  "geometry": {"coordinates":[6.9771,51.172134],"type":"Point"}
}