{
  "type": "Feature",
  "properties": {
    "iso:country":"DE",
    "sg:address":"Benzstr. 10",
    "sg:city":"Kiel",
    "sg:phone":"+49 431/72500",
    "sg:postcode":"24148",
    "sg:province":"Schleswig-Holstein",
    "wof:name":"Co Op Schleswig-holstein Eg",
    "wof:placetype":"venue"
},
  "geometry": {"coordinates":[10.1990776062,54.3184738159],"type":"Point"}
}