{
  "type": "Feature",
  "properties": {
    "iso:country":"DE",
    "sg:address":"Frankfurter Str. 97",
    "sg:city":"Raunheim",
    "sg:phone":"+49 6142/9440",
    "sg:postcode":"65479",
    "sg:province":"Hessen",
    "wof:name":"Yusen Gmbh",
    "wof:placetype":"venue"
},
  "geometry": {"coordinates":[8.462092,50.01722],"type":"Point"}
}