{
  "type": "Feature",
  "properties": {
    "iso:country":"DE",
    "sg:address":"Binsfeld",
    "sg:city":"Speyer",
    "sg:phone":"+49 6232/34945",
    "sg:postcode":"67346",
    "sg:province":"Rheinland-Pfalz",
    "wof:name":"Anglerstubb",
    "wof:placetype":"venue"
},
  "geometry": {"coordinates":[8.4510173798,49.3539352417],"type":"Point"}
}