{
  "type": "Feature",
  "properties": {
    "iso:country":"DE",
    "sg:address":"Kruckeler Str. 136",
    "sg:city":"Dortmund",
    "sg:phone":"+49 231/771203",
    "sg:postcode":"44227",
    "sg:province":"Nordrhein-Westfalen",
    "wof:name":"Ernst Fischer",
    "wof:placetype":"venue"
},
  "geometry": {"coordinates":[7.4301857948,51.4545440674],"type":"Point"}
}