{
  "type": "Feature",
  "properties": {
    "iso:country":"DE",
    "sg:address":"Heinrich-Hasemeier-Str. 27",
    "sg:city":"Osnabr\u00fcck",
    "sg:phone":"+49 541/122077",
    "sg:postcode":"49076",
    "sg:province":"Niedersachsen",
    "wof:name":"Brg B\u00fcro Reform Gmbh & Co. Kg",
    "wof:placetype":"venue"
},
  "geometry": {"coordinates":[7.9441437721,52.283454895],"type":"Point"}
}