{
  "type": "Feature",
  "properties": {
    "iso:country":"DE",
    "sg:address":"Lohkamp 3",
    "sg:city":"Rellingen",
    "sg:phone":"+49 4101/28213",
    "sg:postcode":"25462",
    "sg:province":"Schleswig-Holstein",
    "wof:name":"M. Held",
    "wof:placetype":"venue"
},
  "geometry": {"coordinates":[9.830112,53.655193],"type":"Point"}
}