{
  "type": "Feature",
  "properties": {
    "iso:country":"DE",
    "sg:address":"Bertolt-Brecht-Str. 9",
    "sg:city":"Rostock",
    "sg:postcode":"18106",
    "sg:province":"Mecklenburg-Vorpommern",
    "wof:name":"Weinhandel Inh. Kornelia Hempel",
    "wof:placetype":"venue"
},
  "geometry": {"coordinates":[12.0582265854,54.1195411682],"type":"Point"}
}