{
  "type": "Feature",
  "properties": {
    "iso:country":"DE",
    "sg:address":"Bahnhofstr. 22",
    "sg:city":"Eschwege",
    "sg:phone":"+49 5651/3569",
    "sg:postcode":"37269",
    "sg:province":"Hessen",
    "wof:name":"Horst Seifert",
    "wof:placetype":"venue"
},
  "geometry": {"coordinates":[10.047798,51.190788],"type":"Point"}
}