{
  "type": "Feature",
  "properties": {
    "iso:country":"DE",
    "sg:address":"Wehrestr. 11",
    "sg:city":"Hessisch Lichtenau",
    "sg:phone":"+49 5602/4516",
    "sg:postcode":"37235",
    "sg:province":"Hessen",
    "wof:name":"Hans Volland",
    "wof:placetype":"venue"
},
  "geometry": {"coordinates":[9.769056,51.199738],"type":"Point"}
}