{
  "type": "Feature",
  "properties": {
    "iso:country":"DE",
    "sg:address":"Am Plattensee",
    "sg:city":"Dannigkow",
    "sg:phone":"+49 39200/51716",
    "sg:postcode":"39245",
    "sg:province":"Sachsen-Anhalt",
    "wof:name":"Waldidyll",
    "wof:placetype":"venue"
},
  "geometry": {"coordinates":[11.8272771835,52.0730781555],"type":"Point"}
}