{
  "type": "Feature",
  "properties": {
    "iso:country":"DE",
    "sg:address":"Am Klosterwasser 6",
    "sg:city":"R\u00e4ckelwitz",
    "sg:phone":"+49 35796/96096",
    "sg:postcode":"01920",
    "sg:province":"Sachsen",
    "wof:name":"Georg P\u00f6tschke",
    "wof:placetype":"venue"
},
  "geometry": {"coordinates":[14.232883,51.26738],"type":"Point"}
}