{
  "type": "Feature",
  "properties": {
    "iso:country":"DE",
    "sg:address":"Wendelsteinstra\u00dfe 2",
    "sg:city":"Erding",
    "sg:phone":"+49 8122/91416",
    "sg:postcode":"85435",
    "sg:province":"Bayern",
    "wof:name":"As-industries Motorcycle Technology",
    "wof:placetype":"venue"
},
  "geometry": {"coordinates":[11.901644,48.291477],"type":"Point"}
}