{
  "type": "Feature",
  "properties": {
    "iso:country":"DE",
    "sg:address":"Schulstr. 6",
    "sg:city":"Holzhausen",
    "sg:postcode":"56357",
    "sg:province":"Rheinland-Pfalz",
    "wof:name":"Sonis Gmbh",
    "wof:placetype":"venue"
},
  "geometry": {"coordinates":[10.7484960556,50.301399231],"type":"Point"}
}