{
  "type": "Feature",
  "properties": {
    "iso:country":"DE",
    "sg:address":"Am Hauptbahnhof",
    "sg:city":"Homburg",
    "sg:phone":"+49 6841/4511",
    "sg:postcode":"66424",
    "sg:province":"Saarland",
    "wof:name":"Hotel B\u00fcrgerhof",
    "wof:placetype":"venue"
},
  "geometry": {"coordinates":[7.3349318504,49.3196525574],"type":"Point"}
}