{
  "type": "Feature",
  "properties": {
    "iso:country":"DE",
    "sg:address":"Schlo\u00dffeldweg 9",
    "sg:city":"Bergisch Gladbach",
    "sg:phone":"+49 2204/52277",
    "sg:postcode":"51429",
    "sg:province":"Nordrhein-Westfalen",
    "wof:name":"Allgemeiner Wohnungsbauverein Bensberg Eg",
    "wof:placetype":"venue"
},
  "geometry": {"coordinates":[7.1595411301,50.9609603882],"type":"Point"}
}