{
  "type": "Feature",
  "properties": {
    "iso:country":"DE",
    "sg:address":"Untere Gasse 7",
    "sg:city":"Crailsheim",
    "sg:phone":"+49 7951/6255",
    "sg:postcode":"74564",
    "sg:province":"Baden-W\u00fcrttemberg",
    "wof:name":"H. Herrscher",
    "wof:placetype":"venue"
},
  "geometry": {"coordinates":[10.07471,49.123119],"type":"Point"}
}