{
  "type": "Feature",
  "properties": {
    "iso:country":"DE",
    "sg:address":"Hauptstr 9",
    "sg:city":"Bad Wildbad",
    "sg:phone":"+49 4970/816532",
    "sg:postcode":"75323",
    "sg:province":"Baden-W\u00fcrttemberg",
    "wof:name":"Kreissparkasse Calw",
    "wof:placetype":"venue"
},
  "geometry": {"coordinates":[8.580145,48.774044],"type":"Point"}
}