{
  "type": "Feature",
  "properties": {
    "iso:country":"DE",
    "sg:address":"Senefelderstr. 22",
    "sg:city":"R\u00f6dermark",
    "sg:postcode":"63322",
    "sg:province":"Hessen",
    "wof:name":"Zeltverleih R\u00f6dermark Gmbh",
    "wof:placetype":"venue"
},
  "geometry": {"coordinates":[8.826546,49.969662],"type":"Point"}
}