{
  "type": "Feature",
  "properties": {
    "iso:country":"DE",
    "sg:address":"Kirchstr. 17",
    "sg:city":"Bad Pyrmont",
    "sg:phone":"+49 5281/4579",
    "sg:postcode":"31812",
    "sg:province":"Niedersachsen",
    "wof:name":"Pizzeria D Armando",
    "wof:placetype":"venue"
},
  "geometry": {"coordinates":[9.254948616,51.9859008789],"type":"Point"}
}