{
  "type": "Feature",
  "properties": {
    "iso:country":"DE",
    "sg:address":"Benzstr. 6",
    "sg:city":"Barbing",
    "sg:phone":"+49 9401/92130",
    "sg:postcode":"93092",
    "sg:province":"Bayern",
    "wof:name":"Gernep Etiketiertechnik Gmbh",
    "wof:placetype":"venue"
},
  "geometry": {"coordinates":[12.236335,48.993397],"type":"Point"}
}