{
  "type": "Feature",
  "properties": {
    "iso:country":"DE",
    "sg:address":"Schleusenstr. 15a",
    "sg:city":"Vechelde",
    "sg:phone":"+49 5302/2595",
    "sg:postcode":"38159",
    "sg:province":"Niedersachsen",
    "wof:name":"Fraatz-technik Gmbh",
    "wof:placetype":"venue"
},
  "geometry": {"coordinates":[10.402552,52.269112],"type":"Point"}
}