{
  "type": "Feature",
  "properties": {
    "iso:country":"DE",
    "sg:address":"Warendorfer Str. 33",
    "sg:city":"M\u00fcnster",
    "sg:phone":"+49 251/391618",
    "sg:postcode":"48145",
    "sg:province":"Nordrhein-Westfalen",
    "wof:name":"Griechische Imbi\u00dfstube",
    "wof:placetype":"venue"
},
  "geometry": {"coordinates":[7.6412138939,51.9618263245],"type":"Point"}
}