{
  "type": "Feature",
  "properties": {
    "iso:country":"DE",
    "sg:address":"Badstr. 46",
    "sg:city":"Badenweiler",
    "sg:phone":"+49 7632/7540",
    "sg:postcode":"79410",
    "sg:province":"Baden-W\u00fcrttemberg",
    "wof:name":"Klinik Zimmermann Betriebs Gmbh",
    "wof:placetype":"venue"
},
  "geometry": {"coordinates":[7.6873607635,47.8028373718],"type":"Point"}
}