{
  "type": "Feature",
  "properties": {
    "iso:country":"DE",
    "sg:address":"Bahnhofstr. 3",
    "sg:city":"Badbergen",
    "sg:phone":"+49 5433/6840",
    "sg:postcode":"49635",
    "sg:province":"Niedersachsen",
    "wof:name":"G\u00fcnter Birse Elektro-mstr.",
    "wof:placetype":"venue"
},
  "geometry": {"coordinates":[7.979133,52.633678],"type":"Point"}
}