{
  "type": "Feature",
  "properties": {
    "iso:country":"DE",
    "sg:address":"Kleine Teichstr. 1",
    "sg:city":"Marlow",
    "sg:phone":"+49 38221/380",
    "sg:postcode":"18337",
    "sg:province":"Mecklenburg-Vorpommern",
    "wof:name":"Dieter Barten",
    "wof:placetype":"venue"
},
  "geometry": {"coordinates":[12.5749101639,54.1567420959],"type":"Point"}
}