{
  "type": "Feature",
  "properties": {
    "iso:country":"DE",
    "sg:address":"Cecilienallee 56",
    "sg:city":"D\u00fcsseldorf",
    "sg:phone":"+49 211/4380940",
    "sg:postcode":"40474",
    "sg:province":"Nordrhein-Westfalen",
    "wof:name":"Gehrmann Immobilien- Verwaltung Gmbh",
    "wof:placetype":"venue"
},
  "geometry": {"coordinates":[6.7657608986,51.2467803955],"type":"Point"}
}