{
  "type": "Feature",
  "properties": {
    "iso:country":"DE",
    "sg:address":"Schaafeckstr. 16",
    "sg:city":"Heddesheim",
    "sg:phone":"+49 6203/45339",
    "sg:postcode":"68542",
    "sg:province":"Baden-W\u00fcrttemberg",
    "wof:name":"Imbi\u00df-pizzeria Corona",
    "wof:placetype":"venue"
},
  "geometry": {"coordinates":[8.6013412476,49.5030937195],"type":"Point"}
}