{
  "type": "Feature",
  "properties": {
    "iso:country":"DE",
    "sg:address":"Heuauer Weg 9/1",
    "sg:city":"Heidelberg",
    "sg:postcode":"69124",
    "sg:province":"Baden-W\u00fcrttemberg",
    "wof:name":"4 Porkys E. K.",
    "wof:placetype":"venue"
},
  "geometry": {"coordinates":[8.664366,49.376846],"type":"Point"}
}