{
  "type": "Feature",
  "properties": {
    "iso:country":"DE",
    "sg:address":"Viktoriastr. 34-36",
    "sg:city":"Dortmund",
    "sg:phone":"+49 4106/7040",
    "sg:postcode":"44135",
    "sg:province":"Nordrhein-Westfalen",
    "wof:name":"Comdirect Bank Ag",
    "wof:placetype":"venue"
},
  "geometry": {"coordinates":[9.895195,53.731945],"type":"Point"}
}