{
  "type": "Feature",
  "properties": {
    "iso:country":"DE",
    "sg:address":"H\u00fclchrather Str. 4",
    "sg:city":"K\u00f6ln",
    "sg:phone":"+49 221/731044",
    "sg:postcode":"50670",
    "sg:province":"Nordrhein-Westfalen",
    "wof:name":"Literatur Liedtke Versand- Buchhandlung",
    "wof:placetype":"venue"
},
  "geometry": {"coordinates":[6.9614391327,50.9531860352],"type":"Point"}
}