{
  "type": "Feature",
  "properties": {
    "iso:country":"DE",
    "sg:address":"Freiherr-vom-Stein-Platz 42",
    "sg:city":"Lauchhammer",
    "sg:postcode":"01979",
    "sg:province":"Brandenburg",
    "wof:name":"Einkaufseck Jonas",
    "wof:placetype":"venue"
},
  "geometry": {"coordinates":[13.7824697495,51.4919815063],"type":"Point"}
}