{
  "type": "Feature",
  "properties": {
    "iso:country":"DE",
    "sg:address":"Altriper Str. 7",
    "sg:city":"Waldsee",
    "sg:phone":"+49 6236/52244",
    "sg:postcode":"67165",
    "sg:province":"Rheinland-Pfalz",
    "wof:name":"Pizzeria Calabria",
    "wof:placetype":"venue"
},
  "geometry": {"coordinates":[8.4423112869,49.3947639465],"type":"Point"}
}