{
  "type": "Feature",
  "properties": {
    "iso:country":"DE",
    "sg:address":"Brigitte Wall",
    "sg:city":"Oebisfelde",
    "sg:phone":"+49 39002/72028",
    "sg:postcode":"39646",
    "sg:province":"Sachsen-Anhalt",
    "wof:name":"Rolands Stuben",
    "wof:placetype":"venue"
},
  "geometry": {"coordinates":[10.9861698151,52.4276504517],"type":"Point"}
}