{
  "type": "Feature",
  "properties": {
    "iso:country":"DE",
    "sg:address":"Friedrich-Engels-Str. 149",
    "sg:city":"Berlin",
    "sg:phone":"+49 30/9163359",
    "sg:postcode":"13158",
    "sg:province":"Berlin",
    "wof:name":"Caffee-restaurant Wagnitz",
    "wof:placetype":"venue"
},
  "geometry": {"coordinates":[13.382569313,52.593006134],"type":"Point"}
}