{
  "type": "Feature",
  "properties": {
    "iso:country":"DE",
    "sg:address":"Hauptstr. 2",
    "sg:city":"Fellen",
    "sg:phone":"+49 9356/1357",
    "sg:postcode":"97778",
    "sg:province":"Bayern",
    "wof:name":"Josef Katzenberger",
    "wof:placetype":"venue"
},
  "geometry": {"coordinates":[9.5938568115,50.1536560059],"type":"Point"}
}