{
  "type": "Feature",
  "properties": {
    "iso:country":"DE",
    "sg:address":"Hauptstr. 105",
    "sg:city":"Mainz",
    "sg:phone":"+49 6131/681226",
    "sg:postcode":"55120",
    "sg:province":"Rheinland-Pfalz",
    "wof:name":"Sch\u00f6nborn Apotheke Inh. Ingeborg Christmann",
    "wof:placetype":"venue"
},
  "geometry": {"coordinates":[8.227647,50.02169],"type":"Point"}
}