{
  "type": "Feature",
  "properties": {
    "iso:country":"DE",
    "sg:address":"Ahfeldstr 3",
    "sg:city":"Biberach",
    "sg:phone":"+49 7835/8365",
    "sg:postcode":"77781",
    "sg:province":"Baden-W\u00fcrttemberg",
    "wof:name":"Eckermann",
    "wof:placetype":"venue"
},
  "geometry": {"coordinates":[8.031768,48.335041],"type":"Point"}
}