{
  "type": "Feature",
  "properties": {
    "iso:country":"DE",
    "sg:address":"Lockwitzer Str. 17",
    "sg:city":"Dresden",
    "sg:postcode":"01219",
    "sg:province":"Sachsen",
    "wof:name":"Lk Sechste Verm\u00f6gens- Verwaltungs Gmbh",
    "wof:placetype":"venue"
},
  "geometry": {"coordinates":[13.761844635,51.0252571106],"type":"Point"}
}