{
  "type": "Feature",
  "properties": {
    "iso:country":"DE",
    "sg:address":"Hofmannstr. 72",
    "sg:city":"Erlangen",
    "sg:postcode":"91052",
    "sg:province":"Bayern",
    "wof:name":"Hautprobleme?_abhilfe Mit Reiner Naturkosmetik_",
    "wof:placetype":"venue"
},
  "geometry": {"coordinates":[11.0187597275,49.5924987793],"type":"Point"}
}