{
  "type": "Feature",
  "properties": {
    "iso:country":"DE",
    "sg:address":"Spreeweg 5",
    "sg:city":"Hannover",
    "sg:phone":"+49 511/954330",
    "sg:postcode":"30559",
    "sg:province":"Niedersachsen",
    "wof:name":"Htf Gesellschaft F\u00fcr Begleitende Hilfen Therapie",
    "wof:placetype":"venue"
},
  "geometry": {"coordinates":[9.8491392136,52.3634223938],"type":"Point"}
}