{
  "type": "Feature",
  "properties": {
    "iso:country":"DE",
    "sg:address":"Theaterstr. 16",
    "sg:city":"W\u00fcrzburg",
    "sg:phone":"+49 931/12975",
    "sg:postcode":"97070",
    "sg:province":"Bayern",
    "wof:name":"Annastift",
    "wof:placetype":"venue"
},
  "geometry": {"coordinates":[9.934905,49.795597],"type":"Point"}
}