{
  "type": "Feature",
  "properties": {
    "iso:country":"DE",
    "sg:address":"Bernhard-Kellermann-Str. 4a",
    "sg:city":"K\u00f6then",
    "sg:phone":"+49 3496/212706",
    "sg:postcode":"06366",
    "sg:province":"Sachsen-Anhalt",
    "wof:name":"Has-handelshof Verwaltungsgesellschaft Mbh",
    "wof:placetype":"venue"
},
  "geometry": {"coordinates":[11.9679279327,51.7562446594],"type":"Point"}
}