{
  "type": "Feature",
  "properties": {
    "iso:country":"DE",
    "sg:address":"Kanalstr. 77",
    "sg:city":"Neuss",
    "sg:phone":"+49 2131/21345",
    "sg:postcode":"41460",
    "sg:province":"Nordrhein-Westfalen",
    "wof:name":"Bodenheim Gmbh",
    "wof:placetype":"venue"
},
  "geometry": {"coordinates":[6.6856298447,51.1948776245],"type":"Point"}
}