{
  "type": "Feature",
  "properties": {
    "iso:country":"DE",
    "sg:address":"M\u00fchlenstr. 15",
    "sg:city":"Rinteln",
    "sg:phone":"+49 5751/2909",
    "sg:postcode":"31737",
    "sg:province":"Niedersachsen",
    "wof:name":"Maxi",
    "wof:placetype":"venue"
},
  "geometry": {"coordinates":[9.082665,52.189472],"type":"Point"}
}