{
  "type": "Feature",
  "properties": {
    "iso:country":"DE",
    "sg:address":"Artillerieweg 33",
    "sg:city":"Oldenburg",
    "sg:phone":"+49 441/9729813",
    "sg:postcode":"26129",
    "sg:province":"Niedersachsen",
    "wof:name":"Uwe Barelmann Ingenieur",
    "wof:placetype":"venue"
},
  "geometry": {"coordinates":[8.1855115891,53.1506233215],"type":"Point"}
}