{
  "type": "Feature",
  "properties": {
    "iso:country":"DE",
    "sg:address":"Fuchsm\u00fchle 1",
    "sg:city":"Hilpoltstein",
    "sg:phone":"+49 9174/9385",
    "sg:postcode":"91161",
    "sg:province":"Bayern",
    "wof:name":"Fuchsm\u00fchle Brotzeitstube",
    "wof:placetype":"venue"
},
  "geometry": {"coordinates":[11.1588382721,49.1704444885],"type":"Point"}
}