{
  "type": "Feature",
  "properties": {
    "iso:country":"DE",
    "sg:address":"Hauptstr. 57",
    "sg:city":"Salgen",
    "sg:phone":"+49 8266/1612",
    "sg:postcode":"87775",
    "sg:province":"Bayern",
    "wof:name":"Alois Simon Fischz\u00fcchterei",
    "wof:placetype":"venue"
},
  "geometry": {"coordinates":[10.4797058105,48.1325073242],"type":"Point"}
}