{
  "type": "Feature",
  "properties": {
    "iso:country":"DE",
    "sg:address":"Glash\u00fcttenstr. 36",
    "sg:city":"D\u00fcsseldorf",
    "sg:phone":"+49 211/9262646",
    "sg:postcode":"40627",
    "sg:province":"Nordrhein-Westfalen",
    "wof:name":"Thomas Menzel",
    "wof:placetype":"venue"
},
  "geometry": {"coordinates":[6.8662919998,51.2178840637],"type":"Point"}
}