{
  "type": "Feature",
  "properties": {
    "iso:country":"DE",
    "sg:address":"Seegefelder Str. 201",
    "sg:city":"Berlin",
    "sg:phone":"+49 30/3711023",
    "sg:postcode":"13583",
    "sg:province":"Berlin",
    "wof:name":"Alfred Maeske",
    "wof:placetype":"venue"
},
  "geometry": {"coordinates":[13.170773,52.540974],"type":"Point"}
}