{
  "type": "Feature",
  "properties": {
    "iso:country":"DE",
    "sg:address":"Fr\u00f6ruphof",
    "sg:city":"Oeversee",
    "sg:phone":"+49 4638/405",
    "sg:postcode":"24988",
    "sg:province":"Schleswig-Holstein",
    "wof:name":"Christian Hansen",
    "wof:placetype":"venue"
},
  "geometry": {"coordinates":[9.424385,54.68092],"type":"Point"}
}