{
  "type": "Feature",
  "properties": {
    "iso:country":"DE",
    "sg:address":"Halberst\u00e4dter Str. 58",
    "sg:city":"Osterode",
    "sg:phone":"+49 5522/2960",
    "sg:postcode":"37520",
    "sg:province":"Niedersachsen",
    "wof:name":"Adolf Holland Steuerberater",
    "wof:placetype":"venue"
},
  "geometry": {"coordinates":[10.3089799881,51.6765785217],"type":"Point"}
}