{
  "type": "Feature",
  "properties": {
    "iso:country":"DE",
    "sg:address":"Gailertsreuth 8",
    "sg:city":"Flo\u00df",
    "sg:phone":"+49 9603/1358",
    "sg:postcode":"92685",
    "sg:province":"Bayern",
    "wof:name":"Rudolf Lindner",
    "wof:placetype":"venue"
},
  "geometry": {"coordinates":[12.245292,49.737358],"type":"Point"}
}