{
  "type": "Feature",
  "properties": {
    "iso:country":"DE",
    "sg:address":"Strothheide 3",
    "sg:city":"Verl",
    "sg:phone":"+49 5246/2702",
    "sg:postcode":"33415",
    "sg:province":"Nordrhein-Westfalen",
    "wof:name":"Rudolf Jakobfeuerborn Architekt",
    "wof:placetype":"venue"
},
  "geometry": {"coordinates":[8.486046,51.875622],"type":"Point"}
}