{
  "type": "Feature",
  "properties": {
    "iso:country":"DE",
    "sg:address":"Markt 11",
    "sg:city":"Steinfurt",
    "sg:phone":"+49 4925/512389",
    "sg:postcode":"48565",
    "sg:province":"Nordrhein-Westfalen",
    "wof:name":"Offsetdruck Poschmann",
    "wof:placetype":"venue"
},
  "geometry": {"coordinates":[7.3395528793,52.1475486755],"type":"Point"}
}