{
  "type": "Feature",
  "properties": {
    "iso:country":"DE",
    "sg:address":"Schillerstr. 19",
    "sg:city":"Berlin",
    "sg:phone":"+49 30/7452029",
    "sg:postcode":"12305",
    "sg:province":"Berlin",
    "wof:name":"Walter Moll Inh. Axel Koslowski",
    "wof:placetype":"venue"
},
  "geometry": {"coordinates":[13.402917,52.399639],"type":"Point"}
}