{
  "type": "Feature",
  "properties": {
    "iso:country":"DE",
    "sg:address":"Uedemer Str. 20",
    "sg:city":"Kevelaer",
    "sg:phone":"+49 4928/25545",
    "sg:postcode":"47627",
    "sg:province":"Nordrhein-Westfalen",
    "wof:name":"Hochgreef & Krahnen Gmbh & Co Kg",
    "wof:placetype":"venue"
},
  "geometry": {"coordinates":[6.2757129669,51.637462616],"type":"Point"}
}