{
  "type": "Feature",
  "properties": {
    "iso:country":"DE",
    "sg:address":"Kapellenweg 7",
    "sg:city":"Werl",
    "sg:phone":"+49 2922/7037",
    "sg:postcode":"59457",
    "sg:province":"Nordrhein-Westfalen",
    "wof:name":"Kerpen Gmbh",
    "wof:placetype":"venue"
},
  "geometry": {"coordinates":[7.9172949791,51.5577430725],"type":"Point"}
}