{
  "type": "Feature",
  "properties": {
    "iso:country":"DE",
    "sg:address":"Bahnhofstr. 19",
    "sg:city":"K\u00f6tzting",
    "sg:phone":"+49 9941/3614",
    "sg:postcode":"93444",
    "sg:province":"Bayern",
    "wof:name":"Imbi\u00df Karl Greil",
    "wof:placetype":"venue"
},
  "geometry": {"coordinates":[12.8519620895,49.1732635498],"type":"Point"}
}