{
  "type": "Feature",
  "properties": {
    "iso:country":"DE",
    "sg:address":"Im Klosterbezirk 9",
    "sg:city":"Hornbach",
    "sg:phone":"+49 6338/334",
    "sg:postcode":"66500",
    "sg:province":"Rheinland-Pfalz",
    "wof:name":"Ev. Pfarramt Hornbach",
    "wof:placetype":"venue"
},
  "geometry": {"coordinates":[7.3694601059,49.186378479],"type":"Point"}
}