{
  "type": "Feature",
  "properties": {
    "iso:country":"DE",
    "sg:address":"Weiskircher Str. 106",
    "sg:city":"Rodgau",
    "sg:phone":"+49 6106/644747",
    "sg:postcode":"63110",
    "sg:province":"Hessen",
    "wof:name":"Tele Mobil",
    "wof:placetype":"venue"
},
  "geometry": {"coordinates":[8.8843641281,50.0342254639],"type":"Point"}
}