{
  "type": "Feature",
  "properties": {
    "iso:country":"DE",
    "sg:address":"Westermayerstr. 1",
    "sg:city":"Rosenheim",
    "sg:phone":"+49 8031/381741",
    "sg:postcode":"83022",
    "sg:province":"Bayern",
    "wof:name":"W. Obermaier",
    "wof:placetype":"venue"
},
  "geometry": {"coordinates":[12.1258230209,47.8588981628],"type":"Point"}
}