{
  "type": "Feature",
  "properties": {
    "iso:country":"DE",
    "sg:address":"Herrengarten 8",
    "sg:city":"Barntrup",
    "sg:phone":"+49 5262/4557",
    "sg:postcode":"32683",
    "sg:province":"Nordrhein-Westfalen",
    "wof:name":"Werner Meier Architekt",
    "wof:placetype":"venue"
},
  "geometry": {"coordinates":[9.123592,52.029499],"type":"Point"}
}