{
  "type": "Feature",
  "properties": {
    "iso:country":"DE",
    "sg:address":"Steinb\u00fchlweg 13",
    "sg:city":"Wiggensbach",
    "sg:phone":"+49 8370/97385",
    "sg:postcode":"87487",
    "sg:province":"Bayern",
    "wof:name":"Hans-j\u00fcrgen Schumacher E. Kfm.",
    "wof:placetype":"venue"
},
  "geometry": {"coordinates":[10.2328052521,47.7489280701],"type":"Point"}
}