{
  "type": "Feature",
  "properties": {
    "iso:country":"DE",
    "sg:address":"Hauptstr. 30",
    "sg:city":"Etzelwang",
    "sg:phone":"+49 9663/1664",
    "sg:postcode":"92268",
    "sg:province":"Bayern",
    "wof:name":"Cafe Ertl Inh. Christine Rothmeier",
    "wof:placetype":"venue"
},
  "geometry": {"coordinates":[11.583852,49.527054],"type":"Point"}
}