{
  "type": "Feature",
  "properties": {
    "iso:country":"DE",
    "sg:address":"Rugendasstr. 7",
    "sg:city":"M\u00fcnchen",
    "sg:phone":"+49 89/7917031",
    "sg:postcode":"81479",
    "sg:province":"Bayern",
    "wof:name":"Sole Vida Reiseveranstaltungs- Und Servicegesellschaft Mbh",
    "wof:placetype":"venue"
},
  "geometry": {"coordinates":[11.5243682861,48.0840873718],"type":"Point"}
}