{
  "type": "Feature",
  "properties": {
    "iso:country":"DE",
    "sg:address":"Sch\u00fctzenhofstr. 66a",
    "sg:city":"Oldenburg",
    "sg:phone":"+49 441/13839",
    "sg:postcode":"26135",
    "sg:province":"Niedersachsen",
    "wof:name":"B\u00e4rbel Simon",
    "wof:placetype":"venue"
},
  "geometry": {"coordinates":[8.222910881,53.1249694824],"type":"Point"}
}