{
  "type": "Feature",
  "properties": {
    "iso:country":"DE",
    "sg:address":"Marktstr. 14",
    "sg:city":"Fulda",
    "sg:postcode":"36037",
    "sg:province":"Hessen",
    "wof:name":"Fahr Verwaltungs- Gesellschaft Mbh",
    "wof:placetype":"venue"
},
  "geometry": {"coordinates":[9.676738739,50.5512275696],"type":"Point"}
}