{
  "type": "Feature",
  "properties": {
    "iso:country":"DE",
    "sg:address":"Beethovenstr. 12",
    "sg:city":"Leipzig",
    "sg:phone":"+49 341/2118700",
    "sg:postcode":"04107",
    "sg:province":"Sachsen",
    "wof:name":"Bernet Und B\u00f6hner Rechtsanw\u00e4lte",
    "wof:placetype":"venue"
},
  "geometry": {"coordinates":[12.3660364151,51.3322372437],"type":"Point"}
}