{
  "type": "Feature",
  "properties": {
    "iso:country":"DE",
    "sg:address":"Pinnauring 82",
    "sg:city":"Tornesch",
    "sg:phone":"+49 4122/53121",
    "sg:postcode":"25436",
    "sg:province":"Schleswig-Holstein",
    "wof:name":"Wilhelm Pracht",
    "wof:placetype":"venue"
},
  "geometry": {"coordinates":[9.718356,53.688591],"type":"Point"}
}