{
  "type": "Feature",
  "properties": {
    "iso:country":"DE",
    "sg:address":"Lotzestr. 3",
    "sg:city":"G\u00f6ttingen",
    "sg:phone":"+49 551/71616",
    "sg:postcode":"37083",
    "sg:province":"Niedersachsen",
    "wof:name":"Pizzeria Vesuvio",
    "wof:placetype":"venue"
},
  "geometry": {"coordinates":[9.9343900681,51.5284423828],"type":"Point"}
}