{
  "type": "Feature",
  "properties": {
    "iso:country":"DE",
    "sg:address":"Neuer Grund 22",
    "sg:city":"Dorsten",
    "sg:phone":"+49 2866/96247",
    "sg:postcode":"46286",
    "sg:province":"Nordrhein-Westfalen",
    "wof:name":"Franz-josef Risthaus",
    "wof:placetype":"venue"
},
  "geometry": {"coordinates":[6.9443478584,51.7483634949],"type":"Point"}
}