{
  "type": "Feature",
  "properties": {
    "iso:country":"DE",
    "sg:address":"Obere Bachgasse 5",
    "sg:city":"Sch\u00f6nbrunn",
    "sg:phone":"+49 9546/389",
    "sg:postcode":"96185",
    "sg:province":"Bayern",
    "wof:name":"Andreas Wernsd\u00f6rfer",
    "wof:placetype":"venue"
},
  "geometry": {"coordinates":[10.6907,49.85741],"type":"Point"}
}