{
  "type": "Feature",
  "properties": {
    "iso:country":"DE",
    "sg:address":"Poststr. 24",
    "sg:city":"Tarmstedt",
    "sg:phone":"+49 4283/438",
    "sg:postcode":"27412",
    "sg:province":"Niedersachsen",
    "wof:name":"J. Stru\u00df",
    "wof:placetype":"venue"
},
  "geometry": {"coordinates":[9.0797052383,53.2232818604],"type":"Point"}
}