{
  "type": "Feature",
  "properties": {
    "iso:country":"DE",
    "sg:address":"G\u00f6rresstr. 10",
    "sg:city":"Gelsenkirchen",
    "sg:phone":"+49 209/202369",
    "sg:postcode":"45886",
    "sg:province":"Nordrhein-Westfalen",
    "wof:name":"Theresia St\u00f6cker",
    "wof:placetype":"venue"
},
  "geometry": {"coordinates":[7.124666214,51.4962310791],"type":"Point"}
}