{
  "type": "Feature",
  "properties": {
    "iso:country":"DE",
    "sg:address":"Heiligenberger Str. 18",
    "sg:city":"Berlin",
    "sg:phone":"+49 30/5030074",
    "sg:postcode":"10318",
    "sg:province":"Berlin",
    "wof:name":"I. Und Dr. K.-h. Christoph Rechtsanw\u00e4lte",
    "wof:placetype":"venue"
},
  "geometry": {"coordinates":[13.5209407806,52.4795951843],"type":"Point"}
}