{
  "type": "Feature",
  "properties": {
    "iso:country":"DE",
    "sg:address":"Breite Str 74",
    "sg:city":"Wust",
    "sg:phone":"+49 39323/75289",
    "sg:postcode":"39524",
    "sg:province":"Sachsen-Anhalt",
    "wof:name":"Meier",
    "wof:placetype":"venue"
},
  "geometry": {"coordinates":[12.114192009,52.5478897095],"type":"Point"}
}