{
  "type": "Feature",
  "properties": {
    "iso:country":"DE",
    "sg:address":"Am Ausfall 5",
    "sg:city":"B\u00fctzow",
    "sg:phone":"+49 38461/2850",
    "sg:postcode":"18246",
    "sg:province":"Mecklenburg-Vorpommern",
    "wof:name":"Detlef B\u00f6hnke",
    "wof:placetype":"venue"
},
  "geometry": {"coordinates":[11.985687,53.847054],"type":"Point"}
}