{
  "type": "Feature",
  "properties": {
    "iso:country":"DE",
    "sg:address":"An der Bundesstr. 27",
    "sg:city":"St Andreasberg",
    "sg:phone":"+49 5582/1430",
    "sg:postcode":"37444",
    "sg:province":"Niedersachsen",
    "wof:name":"Waldgastst\u00e4tte Erikabr\u00fccke",
    "wof:placetype":"venue"
},
  "geometry": {"coordinates":[10.519235611,51.7107086182],"type":"Point"}
}