{
  "type": "Feature",
  "properties": {
    "iso:country":"DE",
    "sg:address":"R\u00f6merstra\u00dfe 48 A",
    "sg:city":"Gro\u00df-Bieberau",
    "sg:phone":"+49 6162/93475",
    "sg:postcode":"64401",
    "sg:province":"Hessen",
    "wof:name":"B & S Beratung Software Und Service Gmbh",
    "wof:placetype":"venue"
},
  "geometry": {"coordinates":[8.8226413727,49.7997169495],"type":"Point"}
}