{
  "type": "Feature",
  "properties": {
    "iso:country":"DE",
    "sg:address":"Palmbachstr. 51",
    "sg:city":"Aarbergen",
    "sg:postcode":"65326",
    "sg:province":"Hessen",
    "wof:name":"Richard Hoppe Film- Und Video-works",
    "wof:placetype":"venue"
},
  "geometry": {"coordinates":[8.1351490021,50.2561683655],"type":"Point"}
}