{
  "type": "Feature",
  "properties": {
    "iso:country":"DE",
    "sg:address":"Am Schanzberg 1",
    "sg:city":"Wolgast",
    "sg:phone":"+49 3836/602122",
    "sg:postcode":"17438",
    "sg:province":"Mecklenburg-Vorpommern",
    "wof:name":"Helfred Schr\u00f6er",
    "wof:placetype":"venue"
},
  "geometry": {"coordinates":[13.7532482147,54.0458984375],"type":"Point"}
}