{
  "type": "Feature",
  "properties": {
    "iso:country":"DE",
    "sg:address":"Lange Str. 19",
    "sg:city":"Delmenhorst",
    "sg:postcode":"27749",
    "sg:province":"Niedersachsen",
    "wof:name":"Communication Janik Gmbh",
    "wof:placetype":"venue"
},
  "geometry": {"coordinates":[8.6283140182,53.0493469238],"type":"Point"}
}