{
  "type": "Feature",
  "properties": {
    "iso:country":"DE",
    "sg:address":"Fiedlerweg 10",
    "sg:city":"Darmstadt",
    "sg:phone":"+49 6151/495111",
    "sg:postcode":"64287",
    "sg:province":"Hessen",
    "wof:name":"Sch\u00f6nm\u00fcller Und Partner Gmbh Steuerberater",
    "wof:placetype":"venue"
},
  "geometry": {"coordinates":[8.6705389023,49.8760490417],"type":"Point"}
}