{
  "type": "Feature",
  "properties": {
    "iso:country":"DE",
    "sg:address":"Oldorfer M\u00fchle 1",
    "sg:city":"Wangerland",
    "sg:phone":"+49 4463/498",
    "sg:postcode":"26434",
    "sg:province":"Niedersachsen",
    "wof:name":"Martin Friedrichs",
    "wof:placetype":"venue"
},
  "geometry": {"coordinates":[7.924513,53.629147],"type":"Point"}
}