{
  "type": "Feature",
  "properties": {
    "iso:country":"DE",
    "sg:address":"Neuer Weg 2",
    "sg:city":"Wiepkenhagen",
    "sg:phone":"+49 38225/30510",
    "sg:postcode":"18320",
    "sg:province":"Mecklenburg-Vorpommern",
    "wof:name":"Hannelore Neumann",
    "wof:placetype":"venue"
},
  "geometry": {"coordinates":[12.59769,54.224659],"type":"Point"}
}