{
  "type": "Feature",
  "properties": {
    "iso:country":"DE",
    "sg:address":"Am Tharandter Wald 19",
    "sg:city":"Mohorn",
    "sg:postcode":"01723",
    "sg:province":"Sachsen",
    "wof:name":"R\u00fcdiger & Erdmann Gmbh",
    "wof:placetype":"venue"
},
  "geometry": {"coordinates":[13.4716024399,51.0073204041],"type":"Point"}
}