{
  "type": "Feature",
  "properties": {
    "iso:country":"DE",
    "sg:address":"Lange Str. 33",
    "sg:city":"Essen",
    "sg:phone":"+49 4954/34601",
    "sg:postcode":"49632",
    "sg:province":"Niedersachsen",
    "wof:name":"Volksbank Essen Eg.",
    "wof:placetype":"venue"
},
  "geometry": {"coordinates":[7.95455,52.722912],"type":"Point"}
}