{
  "type": "Feature",
  "properties": {
    "iso:country":"DE",
    "sg:address":"Pulverhausstr. 36",
    "sg:city":"Karlsruhe",
    "sg:phone":"+49 721/865356",
    "sg:postcode":"76135",
    "sg:province":"Baden-W\u00fcrttemberg",
    "wof:name":"B. Prause",
    "wof:placetype":"venue"
},
  "geometry": {"coordinates":[8.3710203171,48.990901947],"type":"Point"}
}