{
  "type": "Feature",
  "properties": {
    "iso:country":"DE",
    "sg:address":"Rathausweg 1",
    "sg:city":"Sch\u00f6ntal",
    "sg:phone":"+49 7943/8286",
    "sg:postcode":"74214",
    "sg:province":"Baden-W\u00fcrttemberg",
    "wof:name":"Elisabeth Hasenschwanz",
    "wof:placetype":"venue"
},
  "geometry": {"coordinates":[9.5608520508,49.3428421021],"type":"Point"}
}