{
  "type": "Feature",
  "properties": {
    "iso:country":"DE",
    "sg:address":"Heimgartenstr. 26",
    "sg:city":"Starnberg",
    "sg:phone":"+49 8151/744430",
    "sg:postcode":"82319",
    "sg:province":"Bayern",
    "wof:name":"Rohloff Cosmetics Gmbh",
    "wof:placetype":"venue"
},
  "geometry": {"coordinates":[11.3278980255,48.0125007629],"type":"Point"}
}