{
  "type": "Feature",
  "properties": {
    "iso:country":"DE",
    "sg:address":"Maria-Sand-Str. 14",
    "sg:city":"Herbolzheim",
    "sg:phone":"+49 7643/6684",
    "sg:postcode":"79336",
    "sg:province":"Baden-W\u00fcrttemberg",
    "wof:name":"Dr. L. Heppe Steuerberater",
    "wof:placetype":"venue"
},
  "geometry": {"coordinates":[7.7749400139,48.220790863],"type":"Point"}
}