{
  "type": "Feature",
  "properties": {
    "iso:country":"DE",
    "sg:address":"Schaumanns Kamp 52",
    "sg:city":"Reinbek",
    "sg:phone":"+49 40/7222474",
    "sg:postcode":"21465",
    "sg:province":"Schleswig-Holstein",
    "wof:name":"Rolf Sch\u00f6nbeck Architekt",
    "wof:placetype":"venue"
},
  "geometry": {"coordinates":[10.230313,53.508034],"type":"Point"}
}