{
  "type": "Feature",
  "properties": {
    "iso:country":"DE",
    "sg:address":"Frankfurter Str. 128",
    "sg:city":"Breckerfeld",
    "sg:phone":"+49 2338/3556",
    "sg:postcode":"58339",
    "sg:province":"Nordrhein-Westfalen",
    "wof:name":"Breckerfelder Grill",
    "wof:placetype":"venue"
},
  "geometry": {"coordinates":[7.4603748322,51.2648086548],"type":"Point"}
}