{
  "type": "Feature",
  "properties": {
    "iso:country":"DE",
    "sg:address":"Carl-Hermann-J\u00e4ger-Str. 3",
    "sg:city":"Ettenheim",
    "sg:phone":"+49 4978/2289440",
    "sg:postcode":"77955",
    "sg:province":"Baden-W\u00fcrttemberg",
    "wof:name":"Seil- Frey Gmbh",
    "wof:placetype":"venue"
},
  "geometry": {"coordinates":[7.806047,48.256519],"type":"Point"}
}