{
  "type": "Feature",
  "properties": {
    "iso:country":"DE",
    "sg:address":"Hauptstr. 17",
    "sg:city":"Lisberg",
    "sg:phone":"+49 9549/203",
    "sg:postcode":"96170",
    "sg:province":"Bayern",
    "wof:name":"Anton Lang",
    "wof:placetype":"venue"
},
  "geometry": {"coordinates":[10.728017,49.886108],"type":"Point"}
}