{
  "type": "Feature",
  "properties": {
    "iso:country":"DE",
    "sg:address":"Bokensdorfer Str. 10",
    "sg:city":"Weyhausen",
    "sg:phone":"+49 5362/7861",
    "sg:postcode":"38554",
    "sg:province":"Niedersachsen",
    "wof:name":"Weyhausener Apotheke",
    "wof:placetype":"venue"
},
  "geometry": {"coordinates":[10.714156,52.463295],"type":"Point"}
}