{
  "type": "Feature",
  "properties": {
    "iso:country":"DE",
    "sg:address":"Dr.-Haas-Gasse 5",
    "sg:city":"H\u00f6chstadt",
    "sg:phone":"+49 9193/8315",
    "sg:postcode":"91315",
    "sg:province":"Bayern",
    "wof:name":"Praxis Burkart",
    "wof:placetype":"venue"
},
  "geometry": {"coordinates":[10.8047895432,49.7046737671],"type":"Point"}
}