{
  "type": "Feature",
  "properties": {
    "iso:country":"DE",
    "sg:address":"Beethovenweg 6",
    "sg:city":"Schw\u00e4bisch Hall",
    "sg:phone":"+49 791/9541121",
    "sg:postcode":"74523",
    "sg:province":"Baden-W\u00fcrttemberg",
    "wof:name":"A. Christ",
    "wof:placetype":"venue"
},
  "geometry": {"coordinates":[9.735772,49.096138],"type":"Point"}
}