{
  "type": "Feature",
  "properties": {
    "iso:country":"DE",
    "sg:address":"Hauptstr. 100",
    "sg:city":"Wiesloch",
    "sg:phone":"+49 6222/8998",
    "sg:postcode":"69168",
    "sg:province":"Baden-W\u00fcrttemberg",
    "wof:name":"Margrit Rothhaar Heilpraktikerin",
    "wof:placetype":"venue"
},
  "geometry": {"coordinates":[8.6979236603,49.2947463989],"type":"Point"}
}