{
  "type": "Feature",
  "properties": {
    "iso:country":"DE",
    "sg:address":"Fliederweg 2",
    "sg:city":"Lichterfelde",
    "sg:postcode":"16230",
    "sg:province":"Brandenburg",
    "wof:name":"Universal Recycling Und Entsorgungsges. Mbh",
    "wof:placetype":"venue"
},
  "geometry": {"coordinates":[13.875075,52.905895],"type":"Point"}
}