{
  "type": "Feature",
  "properties": {
    "iso:country":"DE",
    "sg:address":"Koselstr. 19",
    "sg:city":"Frankfurt",
    "sg:phone":"+49 69/59795287",
    "sg:postcode":"60318",
    "sg:province":"Hessen",
    "wof:name":"Bernd Sander Rechtsanwalt",
    "wof:placetype":"venue"
},
  "geometry": {"coordinates":[8.68907547,50.1231689453],"type":"Point"}
}