{
  "type": "Feature",
  "properties": {
    "iso:country":"DE",
    "sg:address":"Marbachstr. 9",
    "sg:city":"M\u00fcnchen",
    "sg:phone":"+49 89/769930",
    "sg:postcode":"81369",
    "sg:province":"Bayern",
    "wof:name":"Etienne Aigner Ag",
    "wof:placetype":"venue"
},
  "geometry": {"coordinates":[11.535397,48.114662],"type":"Point"}
}