{
  "type": "Feature",
  "properties": {
    "iso:country":"DE",
    "sg:address":"T\u00f6nisvorster Str. 3",
    "sg:city":"Viersen",
    "sg:phone":"+49 2162/80039",
    "sg:postcode":"41749",
    "sg:province":"Nordrhein-Westfalen",
    "wof:name":"Sigrid Loitsch Reiseb\u00fcro Marcel",
    "wof:placetype":"venue"
},
  "geometry": {"coordinates":[6.384349823,51.2865180969],"type":"Point"}
}