{
  "type": "Feature",
  "properties": {
    "iso:country":"DE",
    "sg:address":"Clemensstr. 6",
    "sg:city":"M\u00fcnchen",
    "sg:postcode":"80803",
    "sg:province":"Bayern",
    "wof:name":"Dolkhani Brothers Holding Gmbh",
    "wof:placetype":"venue"
},
  "geometry": {"coordinates":[11.5853500366,48.1634788513],"type":"Point"}
}