{
  "type": "Feature",
  "properties": {
    "iso:country":"DE",
    "sg:address":"Seggerner Str. 2",
    "sg:city":"Westerstede",
    "sg:phone":"+49 4488/84490",
    "sg:postcode":"26655",
    "sg:province":"Niedersachsen",
    "wof:name":"Ahlers Baumschule Ag",
    "wof:placetype":"venue"
},
  "geometry": {"coordinates":[7.893187,53.24445],"type":"Point"}
}