{
  "type": "Feature",
  "properties": {
    "iso:country":"DE",
    "sg:address":"Betzdorfer Str 35",
    "sg:city":"Rosenheim",
    "sg:phone":"+49 2747/92430",
    "sg:postcode":"57520",
    "sg:province":"Rheinland-Pfalz",
    "wof:name":"R\u00f6hrig Gmbh & Co. Kg",
    "wof:placetype":"venue"
},
  "geometry": {"coordinates":[7.855337,50.715565],"type":"Point"}
}