{
  "type": "Feature",
  "properties": {
    "iso:country":"DE",
    "sg:address":"Grubm\u00fchlfeldstr.",
    "sg:city":"Gauting",
    "sg:postcode":"82131",
    "sg:province":"Bayern",
    "wof:name":"Gw Verm\u00f6gensverwaltung Gmbh",
    "wof:placetype":"venue"
},
  "geometry": {"coordinates":[11.3815145493,48.0680847168],"type":"Point"}
}