{
  "type": "Feature",
  "properties": {
    "iso:country":"DE",
    "sg:address":"Ernst-Th\u00e4lmann-Str 16",
    "sg:city":"Ottendorf-Okrilla",
    "sg:phone":"+49 35205/4190",
    "sg:postcode":"01458",
    "sg:province":"Sachsen",
    "wof:name":"Heinz Lange Bauunternehmen Gmbh",
    "wof:placetype":"venue"
},
  "geometry": {"coordinates":[13.786258,51.181175],"type":"Point"}
}