{
  "type": "Feature",
  "properties": {
    "iso:country":"DE",
    "sg:address":"Ahornstr. 28-35",
    "sg:city":"Potsdam",
    "sg:postcode":"14482",
    "sg:province":"Brandenburg",
    "wof:name":"G2 Tv-produktion Gmbh",
    "wof:placetype":"venue"
},
  "geometry": {"coordinates":[13.1165895462,52.3835983276],"type":"Point"}
}