{
  "type": "Feature",
  "properties": {
    "iso:country":"DE",
    "sg:address":"Am Br\u00fchl 17",
    "sg:city":"Ottobeuren",
    "sg:phone":"+49 8332/93025",
    "sg:postcode":"87724",
    "sg:province":"Bayern",
    "wof:name":"Ama-verwaltungs Gmbh",
    "wof:placetype":"venue"
},
  "geometry": {"coordinates":[10.3119688034,47.9427947998],"type":"Point"}
}