{
  "type": "Feature",
  "properties": {
    "iso:country":"DE",
    "sg:address":"Isarstr. 1",
    "sg:city":"Hallbergmoos",
    "sg:phone":"+49 811/1666",
    "sg:postcode":"85399",
    "sg:province":"Bayern",
    "wof:name":"Kronthaler Gmbh & Co.",
    "wof:placetype":"venue"
},
  "geometry": {"coordinates":[11.7064218521,48.3135910034],"type":"Point"}
}