{
  "type": "Feature",
  "properties": {
    "iso:country":"DE",
    "sg:address":"Chaussee 9",
    "sg:city":"M\u00f6llenhagen",
    "sg:phone":"+49 39928/5393",
    "sg:postcode":"17219",
    "sg:province":"Mecklenburg-Vorpommern",
    "wof:name":"Hotel Zum Eichenhof",
    "wof:placetype":"venue"
},
  "geometry": {"coordinates":[12.9300460815,53.5227928162],"type":"Point"}
}