{
  "type": "Feature",
  "properties": {
    "iso:country":"DE",
    "sg:address":"Westring 4",
    "sg:city":"Wildeshausen",
    "sg:phone":"+49 4431/3168",
    "sg:postcode":"27793",
    "sg:province":"Niedersachsen",
    "wof:name":"Modea Gmbh",
    "wof:placetype":"venue"
},
  "geometry": {"coordinates":[8.413419,52.896774],"type":"Point"}
}