{
  "type": "Feature",
  "properties": {
    "iso:country":"DE",
    "sg:address":"Friedrichstr. 23",
    "sg:city":"Wilkau-Ha\u00dflau",
    "sg:phone":"+49 375/671683",
    "sg:postcode":"08112",
    "sg:province":"Sachsen",
    "wof:name":"J. Schneidenbach",
    "wof:placetype":"venue"
},
  "geometry": {"coordinates":[12.515554,50.679108],"type":"Point"}
}