{
  "type": "Feature",
  "properties": {
    "iso:country":"DE",
    "sg:address":"Meldorfer Str. 8",
    "sg:city":"Burg",
    "sg:phone":"+49 4825/2766",
    "sg:postcode":"25712",
    "sg:province":"Schleswig-Holstein",
    "wof:name":"H. Ohlsen",
    "wof:placetype":"venue"
},
  "geometry": {"coordinates":[9.261037,53.996613],"type":"Point"}
}