{
  "type": "Feature",
  "properties": {
    "iso:country":"DE",
    "sg:address":"Blumentalstr. 6",
    "sg:city":"Balingen",
    "sg:phone":"+49 4974/3334769",
    "sg:postcode":"72336",
    "sg:province":"Baden-W\u00fcrttemberg",
    "wof:name":"Friedrich Erhard Kg",
    "wof:placetype":"venue"
},
  "geometry": {"coordinates":[8.8681573868,48.2502937317],"type":"Point"}
}