{
  "type": "Feature",
  "properties": {
    "iso:country":"DE",
    "sg:address":"Friedrich-Ebert-Str. 46",
    "sg:city":"Elz",
    "sg:phone":"+49 6431/95454",
    "sg:postcode":"65604",
    "sg:province":"Hessen",
    "wof:name":"Cox Elz Gmbh",
    "wof:placetype":"venue"
},
  "geometry": {"coordinates":[8.0299167633,50.4159736633],"type":"Point"}
}