{
  "type": "Feature",
  "properties": {
    "iso:country":"DE",
    "sg:address":"Wilhelm-M\u00fcller-Str. 9a",
    "sg:city":"Dresden",
    "sg:phone":"+49 351/4222270",
    "sg:postcode":"01157",
    "sg:province":"Sachsen",
    "wof:name":"Cl Systems E. K.",
    "wof:placetype":"venue"
},
  "geometry": {"coordinates":[13.668954,51.060753],"type":"Point"}
}