{
  "type": "Feature",
  "properties": {
    "iso:country":"DE",
    "sg:address":"Ernst-Th\u00e4lmann-Str 2",
    "sg:city":"Lichtensee",
    "sg:phone":"+49 35263/35656",
    "sg:postcode":"01609",
    "sg:province":"Sachsen",
    "wof:name":"Tischlerei Matthias B\u00f6lke",
    "wof:placetype":"venue"
},
  "geometry": {"coordinates":[13.371451,51.378258],"type":"Point"}
}