{
  "type": "Feature",
  "properties": {
    "iso:country":"DE",
    "sg:address":"Forsthausstr. 13",
    "sg:city":"Eschenburg",
    "sg:phone":"+49 2774/1379",
    "sg:postcode":"35713",
    "sg:province":"Hessen",
    "wof:name":"M. Hain",
    "wof:placetype":"venue"
},
  "geometry": {"coordinates":[8.389090538,50.8287773132],"type":"Point"}
}