{
  "type": "Feature",
  "properties": {
    "iso:country":"DE",
    "sg:address":"Wacholderweg 19",
    "sg:city":"Speyer",
    "sg:phone":"+49 6232/33752",
    "sg:postcode":"67346",
    "sg:province":"Rheinland-Pfalz",
    "wof:name":"Nuissl Sekt- Und Weinhandels- Haus Gmbh",
    "wof:placetype":"venue"
},
  "geometry": {"coordinates":[8.4264783859,49.3526039124],"type":"Point"}
}