{
  "type": "Feature",
  "properties": {
    "iso:country":"DE",
    "sg:address":"Gro\u00dfe M\u00fchlenwallstr. 29",
    "sg:city":"Aurich",
    "sg:phone":"+49 4941/5958",
    "sg:postcode":"26603",
    "sg:province":"Niedersachsen",
    "wof:name":"P. Harms Immobilienmakler",
    "wof:placetype":"venue"
},
  "geometry": {"coordinates":[7.4863948822,53.4687309265],"type":"Point"}
}