{
  "type": "Feature",
  "properties": {
    "iso:country":"DE",
    "sg:address":"Elgersheimer Weg 4",
    "sg:city":"Volkach",
    "sg:phone":"+49 9381/1464",
    "sg:postcode":"97332",
    "sg:province":"Bayern",
    "wof:name":"Eugen Blendel",
    "wof:placetype":"venue"
},
  "geometry": {"coordinates":[10.1688756943,49.8755073547],"type":"Point"}
}