{
  "type": "Feature",
  "properties": {
    "iso:country":"DE",
    "sg:address":"Liebigstr. 50",
    "sg:city":"Frankfurt",
    "sg:phone":"+49 69/728774",
    "sg:postcode":"60323",
    "sg:province":"Hessen",
    "wof:name":"Hella Korch Rechtsanw\u00e4ltin",
    "wof:placetype":"venue"
},
  "geometry": {"coordinates":[8.6652212143,50.1223449707],"type":"Point"}
}