{
  "type": "Feature",
  "properties": {
    "iso:country":"DE",
    "sg:address":"Sonnbornstr. 6",
    "sg:city":"D\u00fcsseldorf",
    "sg:phone":"+49 211/287054",
    "sg:postcode":"40625",
    "sg:province":"Nordrhein-Westfalen",
    "wof:name":"Mari Textilhandels- Gmbh",
    "wof:placetype":"venue"
},
  "geometry": {"coordinates":[6.8504691124,51.2378921509],"type":"Point"}
}