{
  "type": "Feature",
  "properties": {
    "iso:country":"DE",
    "sg:address":"W\u00fcrzburger Str. 61",
    "sg:city":"Bielefeld",
    "sg:phone":"+49 521/401472",
    "sg:postcode":"33659",
    "sg:province":"Nordrhein-Westfalen",
    "wof:name":"Team 99 Gmbh",
    "wof:placetype":"venue"
},
  "geometry": {"coordinates":[8.5436544418,51.9577331543],"type":"Point"}
}