{
  "type": "Feature",
  "properties": {
    "iso:country":"DE",
    "sg:address":"Bahnhofstr. 12",
    "sg:city":"Merseburg",
    "sg:phone":"+49 3461/203634",
    "sg:postcode":"06217",
    "sg:province":"Sachsen-Anhalt",
    "wof:name":"Hermann Weber Inh. Heiko Weber",
    "wof:placetype":"venue"
},
  "geometry": {"coordinates":[11.9942855835,51.3566398621],"type":"Point"}
}