{
  "type": "Feature",
  "properties": {
    "iso:country":"DE",
    "sg:address":"Marienstr. 45",
    "sg:city":"H\u00fcrth",
    "sg:phone":"+49 2233/691581",
    "sg:postcode":"50354",
    "sg:province":"Nordrhein-Westfalen",
    "wof:name":"Gebr. Dell Prete Rolladen Und Markisen Gmbh",
    "wof:placetype":"venue"
},
  "geometry": {"coordinates":[6.890006,50.897041],"type":"Point"}
}