{
  "type": "Feature",
  "properties": {
    "iso:country":"DE",
    "sg:city":"Hainspitz",
    "sg:phone":"+49 36691/54137",
    "sg:postcode":"07607",
    "sg:province":"Th\u00fcringen",
    "wof:name":"Wini B\u00fcrom\u00f6bel Gmbh & Co. Kg",
    "wof:placetype":"venue"
},
  "geometry": {"coordinates":[11.835915,50.963043],"type":"Point"}
}