{
  "type": "Feature",
  "properties": {
    "iso:country":"DE",
    "sg:address":"Schmiedestr. 14",
    "sg:city":"Leipzig",
    "sg:phone":"+49 341/4782879",
    "sg:postcode":"04229",
    "sg:province":"Sachsen",
    "wof:name":"Olaf Beyer Rechtsanwalt",
    "wof:placetype":"venue"
},
  "geometry": {"coordinates":[12.3389968872,51.3289527893],"type":"Point"}
}