{
  "type": "Feature",
  "properties": {
    "iso:country":"DE",
    "sg:address":"Schlo\u00dfbergstr. 8",
    "sg:city":"T\u00fcbingen",
    "sg:phone":"+49 7071/49617",
    "sg:postcode":"72070",
    "sg:province":"Baden-W\u00fcrttemberg",
    "wof:name":"H. Helmrich",
    "wof:placetype":"venue"
},
  "geometry": {"coordinates":[9.0471458435,48.5190505981],"type":"Point"}
}