{
  "type": "Feature",
  "properties": {
    "iso:country":"DE",
    "sg:address":"Pfaffengasse 25",
    "sg:city":"Diez",
    "sg:phone":"+49 6432/2146",
    "sg:postcode":"65582",
    "sg:province":"Rheinland-Pfalz",
    "wof:name":"Klaus Wissenborn",
    "wof:placetype":"venue"
},
  "geometry": {"coordinates":[8.005998,50.372192],"type":"Point"}
}