{
  "type": "Feature",
  "properties": {
    "iso:country":"DE",
    "sg:address":"Klein-Gerauer-Str. 12",
    "sg:city":"Gro\u00df-Gerau",
    "sg:phone":"+49 6152/2788",
    "sg:postcode":"64521",
    "sg:province":"Hessen",
    "wof:name":"Klaus Raiss",
    "wof:placetype":"venue"
},
  "geometry": {"coordinates":[8.4894456863,49.9187431335],"type":"Point"}
}