{
  "type": "Feature",
  "properties": {
    "iso:country":"DE",
    "sg:address":"Rittersbachstr. 5",
    "sg:city":"B\u00fchl",
    "sg:phone":"+49 7223/30334",
    "sg:postcode":"77815",
    "sg:province":"Baden-W\u00fcrttemberg",
    "wof:name":"Hans-j\u00f6rg Kist",
    "wof:placetype":"venue"
},
  "geometry": {"coordinates":[8.1354045868,48.6812667847],"type":"Point"}
}