{
  "type": "Feature",
  "properties": {
    "iso:country":"DE",
    "sg:address":"Adolf-Diesterweg-Str. 88 a",
    "sg:city":"Ludwigshafen",
    "sg:phone":"+49 621/677294",
    "sg:postcode":"67071",
    "sg:province":"Rheinland-Pfalz",
    "wof:name":"U. Hasselbach",
    "wof:placetype":"venue"
},
  "geometry": {"coordinates":[8.364878,49.491222],"type":"Point"}
}