{
  "type": "Feature",
  "properties": {
    "iso:country":"DE",
    "sg:address":"Goethestr 27",
    "sg:city":"Pulsnitz",
    "sg:phone":"+49 34345/22715",
    "sg:postcode":"01896",
    "sg:province":"Sachsen",
    "wof:name":"Frank Wittig",
    "wof:placetype":"venue"
},
  "geometry": {"coordinates":[12.6389636993,51.1445770264],"type":"Point"}
}