{
  "type": "Feature",
  "properties": {
    "iso:country":"DE",
    "sg:address":"Ringslebenstr. 101",
    "sg:city":"Berlin",
    "sg:phone":"+49 30/6047671",
    "sg:postcode":"12353",
    "sg:province":"Berlin",
    "wof:name":"Klaus Schniggenberg",
    "wof:placetype":"venue"
},
  "geometry": {"coordinates":[13.440795,52.417423],"type":"Point"}
}