{
  "type": "Feature",
  "properties": {
    "iso:country":"DE",
    "sg:address":"Gro\u00dfe Paaschburg 40",
    "sg:city":"Itzehoe",
    "sg:postcode":"25524",
    "sg:province":"Schleswig-Holstein",
    "wof:name":"Altes Wochenblatt - Das Kneiporant In Itzehoe",
    "wof:placetype":"venue"
},
  "geometry": {"coordinates":[9.5213079453,53.9215583801],"type":"Point"}
}