{
  "type": "Feature",
  "properties": {
    "iso:country":"DE",
    "sg:address":"Heppenheimer Str. 70",
    "sg:city":"F\u00fcrth",
    "sg:phone":"+49 6253/1021",
    "sg:postcode":"64658",
    "sg:province":"Hessen",
    "wof:name":"H. Dillmann",
    "wof:placetype":"venue"
},
  "geometry": {"coordinates":[8.7725229263,49.6457214355],"type":"Point"}
}