{
  "type": "Feature",
  "properties": {
    "iso:country":"DE",
    "sg:address":"Kinzigstrasse 35 A",
    "sg:city":"Gengenbach",
    "sg:phone":"+49 7803/928770",
    "sg:postcode":"77723",
    "sg:province":"Baden-W\u00fcrttemberg",
    "wof:name":"Schwarzw\u00e4lder Souvenirs",
    "wof:placetype":"venue"
},
  "geometry": {"coordinates":[8.0348386765,48.3888168335],"type":"Point"}
}