{
  "type": "Feature",
  "properties": {
    "iso:country":"DE",
    "sg:address":"Misdroyer Str. 50",
    "sg:city":"Berlin",
    "sg:phone":"+49 30/8243413",
    "sg:postcode":"14199",
    "sg:province":"Berlin",
    "wof:name":"Hans Spann",
    "wof:placetype":"venue"
},
  "geometry": {"coordinates":[13.29227,52.472946],"type":"Point"}
}