{
  "type": "Feature",
  "properties": {
    "iso:country":"DE",
    "sg:address":"Potshauser Str. 23",
    "sg:city":"Rhauderfehn",
    "sg:phone":"+49 4952/921923",
    "sg:postcode":"26817",
    "sg:province":"Niedersachsen",
    "wof:name":"Harmannus Schmidt",
    "wof:placetype":"venue"
},
  "geometry": {"coordinates":[7.589998,53.174969],"type":"Point"}
}