{
  "type": "Feature",
  "properties": {
    "iso:country":"DE",
    "sg:address":"Hirtenweg 8",
    "sg:city":"Hettstedt",
    "sg:phone":"+49 3476/851639",
    "sg:postcode":"06333",
    "sg:province":"Sachsen-Anhalt",
    "wof:name":"Dr. Leo Fl\u00fcgel",
    "wof:placetype":"venue"
},
  "geometry": {"coordinates":[11.51494,51.656578],"type":"Point"}
}