{
  "type": "Feature",
  "properties": {
    "iso:country":"DE",
    "sg:address":"Kleyerstr. 8",
    "sg:city":"Darmstadt",
    "sg:phone":"+49 6151/8570",
    "sg:postcode":"64295",
    "sg:province":"Hessen",
    "wof:name":"Hollmann Grundbesitz Verwaltungs- Gmbh",
    "wof:placetype":"venue"
},
  "geometry": {"coordinates":[8.6231460571,49.8608627319],"type":"Point"}
}