{
  "type": "Feature",
  "properties": {
    "iso:country":"DE",
    "sg:address":"Dieselstr. 8",
    "sg:city":"Gr\u00fcnstadt",
    "sg:phone":"+49 6359/960604",
    "sg:postcode":"67269",
    "sg:province":"Rheinland-Pfalz",
    "wof:name":"Naturalis Zahntechnik Gmbh",
    "wof:placetype":"venue"
},
  "geometry": {"coordinates":[8.1788129807,49.5617103577],"type":"Point"}
}