{
  "type": "Feature",
  "properties": {
    "iso:country":"DE",
    "sg:address":"Huntebr\u00fcck 8",
    "sg:city":"Berne",
    "sg:phone":"+49 4406/762",
    "sg:postcode":"27804",
    "sg:province":"Niedersachsen",
    "wof:name":"Petra Kind U. Eilert",
    "wof:placetype":"venue"
},
  "geometry": {"coordinates":[8.4775514603,53.1847801208],"type":"Point"}
}