{
  "type": "Feature",
  "properties": {
    "iso:country":"DE",
    "sg:address":"Marktplatz 10",
    "sg:city":"Bad Teinach-Zavelstein",
    "sg:phone":"+49 7053/8507",
    "sg:postcode":"75385",
    "sg:province":"Baden-W\u00fcrttemberg",
    "wof:name":"Helmut Krieg Architekt",
    "wof:placetype":"venue"
},
  "geometry": {"coordinates":[8.688861,48.694313],"type":"Point"}
}