{
  "type": "Feature",
  "properties": {
    "iso:country":"DE",
    "sg:address":"Klosterbergstr. 114",
    "sg:city":"Wiltingen",
    "sg:phone":"+49 6501/16448",
    "sg:postcode":"54459",
    "sg:province":"Rheinland-Pfalz",
    "wof:name":"Josef Kantner",
    "wof:placetype":"venue"
},
  "geometry": {"coordinates":[6.5917630196,49.661945343],"type":"Point"}
}