{
  "type": "Feature",
  "properties": {
    "iso:country":"DE",
    "sg:address":"Gustav-Winkler-Str 17",
    "sg:city":"Bielefeld",
    "sg:phone":"+49 5731/21274",
    "sg:postcode":"33699",
    "sg:province":"Nordrhein-Westfalen",
    "wof:name":"Elimar Runkel Gmbh & Co Kg",
    "wof:placetype":"venue"
},
  "geometry": {"coordinates":[8.8103017807,52.2089233398],"type":"Point"}
}