{
  "type": "Feature",
  "properties": {
    "iso:country":"DE",
    "sg:address":"Gutenbergstr. 28",
    "sg:city":"Stadtlohn",
    "sg:phone":"+49 2563/93280",
    "sg:postcode":"48703",
    "sg:province":"Nordrhein-Westfalen",
    "wof:name":"Profil Metall Und Technik Gmbh",
    "wof:placetype":"venue"
},
  "geometry": {"coordinates":[6.8976831436,51.9901771545],"type":"Point"}
}