{
  "type": "Feature",
  "properties": {
    "iso:country":"DE",
    "sg:address":"Kaiserin-Augusta-Str. 55",
    "sg:city":"Berlin",
    "sg:phone":"+49 30/75703910",
    "sg:postcode":"12103",
    "sg:province":"Berlin",
    "wof:name":"Kaisers Kaffee-gesch\u00e4ft",
    "wof:placetype":"venue"
},
  "geometry": {"coordinates":[13.3750495911,52.4600486755],"type":"Point"}
}