{
  "type": "Feature",
  "properties": {
    "iso:country":"DE",
    "sg:address":"Kronsforder Allee 130",
    "sg:city":"L\u00fcbeck",
    "sg:phone":"+49 451/88030",
    "sg:postcode":"23560",
    "sg:province":"Schleswig-Holstein",
    "wof:name":"Immobilia E. K.",
    "wof:placetype":"venue"
},
  "geometry": {"coordinates":[10.6773681641,53.8410072327],"type":"Point"}
}