{
  "type": "Feature",
  "properties": {
    "iso:country":"DE",
    "sg:address":"Wakendorfer Str. 69",
    "sg:city":"Preetz",
    "sg:phone":"+49 4342/82199",
    "sg:postcode":"24211",
    "sg:province":"Schleswig-Holstein",
    "wof:name":"M\u00f6ller",
    "wof:placetype":"venue"
},
  "geometry": {"coordinates":[10.288503,54.240067],"type":"Point"}
}