{
  "type": "Feature",
  "properties": {
    "iso:country":"DE",
    "sg:address":"Birkenweg 11",
    "sg:city":"Speyer",
    "sg:phone":"+49 6232/34938",
    "sg:postcode":"67346",
    "sg:province":"Rheinland-Pfalz",
    "wof:name":"Kurt Grie\u00dfhaber",
    "wof:placetype":"venue"
},
  "geometry": {"coordinates":[8.428859,49.348408],"type":"Point"}
}