{
  "type": "Feature",
  "properties": {
    "iso:country":"DE",
    "sg:address":"Bei den M\u00fchren 82",
    "sg:city":"Hamburg",
    "sg:postcode":"20457",
    "sg:province":"Hamburg",
    "wof:name":"Vengarus Verwaltungs- Gesellschaft Mbh",
    "wof:placetype":"venue"
},
  "geometry": {"coordinates":[9.993566,53.545296],"type":"Point"}
}