{
  "type": "Feature",
  "properties": {
    "iso:country":"DE",
    "sg:address":"Am Aueteich 17",
    "sg:city":"Gro\u00dfsch\u00f6nau",
    "sg:phone":"+49 35841/35351",
    "sg:postcode":"02779",
    "sg:province":"Sachsen",
    "wof:name":"Altmanns",
    "wof:placetype":"venue"
},
  "geometry": {"coordinates":[14.6561698914,50.9013214111],"type":"Point"}
}