{
  "type": "Feature",
  "properties": {
    "iso:country":"DE",
    "sg:address":"Heinrich-Heine-Str. 17",
    "sg:city":"Storkow",
    "sg:phone":"+49 33678/72924",
    "sg:postcode":"15859",
    "sg:province":"Brandenburg",
    "wof:name":"Heinz Kwokal Ingenieur",
    "wof:placetype":"venue"
},
  "geometry": {"coordinates":[13.936422348,52.260307312],"type":"Point"}
}