{
  "type": "Feature",
  "properties": {
    "iso:country":"DE",
    "sg:address":"B\u00e4ckerweg 34",
    "sg:city":"M\u00f6rfelden-Walldorf",
    "sg:phone":"+49 6105/5785",
    "sg:postcode":"64546",
    "sg:province":"Hessen",
    "wof:name":"Kaufmann",
    "wof:placetype":"venue"
},
  "geometry": {"coordinates":[8.578816,50.00581],"type":"Point"}
}