{
  "type": "Feature",
  "properties": {
    "iso:country":"DE",
    "sg:address":"Silvanerstr. 47",
    "sg:city":"Mainz",
    "sg:phone":"+49 6131/509416",
    "sg:postcode":"55129",
    "sg:province":"Rheinland-Pfalz",
    "wof:name":"Paul G. Pohlmann Steuerberater",
    "wof:placetype":"venue"
},
  "geometry": {"coordinates":[8.2839221954,49.9679031372],"type":"Point"}
}