{
  "type": "Feature",
  "properties": {
    "iso:country":"DE",
    "sg:address":"Alexanderstr. 33",
    "sg:city":"Apolda",
    "sg:phone":"+49 3644/552236",
    "sg:postcode":"99510",
    "sg:province":"Th\u00fcringen",
    "wof:name":"Thomas Alberti Gmbh",
    "wof:placetype":"venue"
},
  "geometry": {"coordinates":[11.507834,51.020317],"type":"Point"}
}