{
  "type": "Feature",
  "properties": {
    "iso:country":"DE",
    "sg:address":"Hauptstr. 2",
    "sg:city":"Dannstadt",
    "sg:phone":"+49 4962/3191720",
    "sg:postcode":"67125",
    "sg:province":"Rheinland-Pfalz",
    "wof:name":"Kreissparkasse Ludwigshafen A.rh.",
    "wof:placetype":"venue"
},
  "geometry": {"coordinates":[8.310924,49.431812],"type":"Point"}
}