{
  "type": "Feature",
  "properties": {
    "iso:country":"DE",
    "sg:address":"Felsenweg 9",
    "sg:city":"Leibertingen",
    "sg:phone":"+49 7466/910476",
    "sg:postcode":"88637",
    "sg:province":"Baden-W\u00fcrttemberg",
    "wof:name":"Weidle & Braun-keller Ohg",
    "wof:placetype":"venue"
},
  "geometry": {"coordinates":[9.0106153488,48.0404014587],"type":"Point"}
}