{
  "type": "Feature",
  "properties": {
    "iso:country":"DE",
    "sg:address":"L\u00fctzowstr. 21",
    "sg:city":"Leipzig",
    "sg:phone":"+49 341/50471",
    "sg:postcode":"04157",
    "sg:province":"Sachsen",
    "wof:name":"F. Petzold",
    "wof:placetype":"venue"
},
  "geometry": {"coordinates":[12.3741922379,51.3637695312],"type":"Point"}
}