{
  "type": "Feature",
  "properties": {
    "iso:country":"DE",
    "sg:address":"Lachnerstr. 45",
    "sg:city":"Erlangen",
    "sg:phone":"+49 9131/603248",
    "sg:postcode":"91058",
    "sg:province":"Bayern",
    "wof:name":"Ipks Ingenieur-b\u00fcro H. Pflug- B. Kinner-r. Schranz",
    "wof:placetype":"venue"
},
  "geometry": {"coordinates":[11.0227241516,49.5525894165],"type":"Point"}
}