{
  "type": "Feature",
  "properties": {
    "iso:country":"DE",
    "sg:address":"Nisterstr. 12",
    "sg:city":"Limbach",
    "sg:phone":"+49 2662/1474",
    "sg:postcode":"57629",
    "sg:province":"Rheinland-Pfalz",
    "wof:name":"K. Schneider",
    "wof:placetype":"venue"
},
  "geometry": {"coordinates":[7.802174,50.699459],"type":"Point"}
}