{
  "type": "Feature",
  "properties": {
    "iso:country":"DE",
    "sg:address":"Blaubeurer Str. 64/1",
    "sg:city":"Ulm",
    "sg:postcode":"89077",
    "sg:province":"Baden-W\u00fcrttemberg",
    "wof:name":"F. A. M. E. Gmbh",
    "wof:placetype":"venue"
},
  "geometry": {"coordinates":[9.9687347412,48.4008407593],"type":"Point"}
}