{
  "type": "Feature",
  "properties": {
    "iso:country":"DE",
    "sg:address":"Kronengasse 14",
    "sg:city":"Neu-Isenburg",
    "sg:phone":"+49 6102/35454",
    "sg:postcode":"63263",
    "sg:province":"Hessen",
    "wof:name":"Helmut Lamberth Eisenwaren",
    "wof:placetype":"venue"
},
  "geometry": {"coordinates":[8.696149826,50.0549812317],"type":"Point"}
}