{
  "type": "Feature",
  "properties": {
    "iso:country":"DE",
    "sg:address":"Eichbergstr. 37",
    "sg:city":"Neuffen",
    "sg:phone":"+49 7025/3859",
    "sg:postcode":"72639",
    "sg:province":"Baden-W\u00fcrttemberg",
    "wof:name":"Richard Flammer Steuerberater",
    "wof:placetype":"venue"
},
  "geometry": {"coordinates":[9.3832330704,48.5515441895],"type":"Point"}
}