{
  "type": "Feature",
  "properties": {
    "iso:country":"DE",
    "sg:address":"Hindenburgstr. 8",
    "sg:city":"Donauwoerth",
    "sg:phone":"+49 906/78040",
    "sg:postcode":"86609",
    "sg:province":"Bayern",
    "wof:name":"Raiffeisen-volksbank Donauwoerth Eg",
    "wof:placetype":"venue"
},
  "geometry": {"coordinates":[10.779538,48.71677],"type":"Point"}
}