{
  "type": "Feature",
  "properties": {
    "iso:country":"DE",
    "sg:address":"Am Altersheim 4",
    "sg:city":"Helmbrechts",
    "sg:phone":"+49 9252/3870",
    "sg:postcode":"95233",
    "sg:province":"Bayern",
    "wof:name":"Stiftung Altersheim Helmbrechts",
    "wof:placetype":"venue"
},
  "geometry": {"coordinates":[11.714003,50.239594],"type":"Point"}
}