{
  "type": "Feature",
  "properties": {
    "iso:country":"DE",
    "sg:address":"Peelwatt",
    "sg:city":"Flensburg",
    "sg:phone":"+49 461/13112",
    "sg:postcode":"24941",
    "sg:province":"Schleswig-Holstein",
    "wof:name":"Angeln-bahn Gmbh",
    "wof:placetype":"venue"
},
  "geometry": {"coordinates":[9.4486322403,54.7659988403],"type":"Point"}
}