{
  "type": "Feature",
  "properties": {
    "iso:country":"DE",
    "sg:address":"Welschstr. 42 a",
    "sg:city":"Waldfischbach-Burgalben",
    "sg:phone":"+49 6333/5012",
    "sg:postcode":"67714",
    "sg:province":"Rheinland-Pfalz",
    "wof:name":"Pf\u00e4lzer Stubb",
    "wof:placetype":"venue"
},
  "geometry": {"coordinates":[7.6603732109,49.2859230042],"type":"Point"}
}