{
  "type": "Feature",
  "properties": {
    "iso:country":"DE",
    "sg:address":"Schallerin 1",
    "sg:city":"Die\u00dfen",
    "sg:phone":"+49 8807/1793",
    "sg:postcode":"86911",
    "sg:province":"Bayern",
    "wof:name":"Dr. Theo Werdin",
    "wof:placetype":"venue"
},
  "geometry": {"coordinates":[11.0856409073,47.9808692932],"type":"Point"}
}