{
  "type": "Feature",
  "properties": {
    "iso:country":"DE",
    "sg:address":"Gro\u00dfwaldstr. 26",
    "sg:city":"Eppelborn",
    "sg:phone":"+49 6881/87703",
    "sg:postcode":"66571",
    "sg:province":"Saarland",
    "wof:name":"G\u00fcnter Hollinger",
    "wof:placetype":"venue"
},
  "geometry": {"coordinates":[6.9521241188,49.3804130554],"type":"Point"}
}