{
  "type": "Feature",
  "properties": {
    "iso:country":"DE",
    "sg:address":"Metzgergasse 11",
    "sg:city":"Niddatal",
    "sg:phone":"+49 6034/8554",
    "sg:postcode":"61194",
    "sg:province":"Hessen",
    "wof:name":"N. Peter",
    "wof:placetype":"venue"
},
  "geometry": {"coordinates":[8.812994,50.299347],"type":"Point"}
}