{
  "type": "Feature",
  "properties": {
    "iso:country":"DE",
    "sg:address":"Matzmannsdorf 16",
    "sg:city":"Langfurth",
    "sg:postcode":"91731",
    "sg:province":"Bayern",
    "wof:name":"Rs Abfluss-doktor Gmbh",
    "wof:placetype":"venue"
},
  "geometry": {"coordinates":[10.4557275772,49.1109809875],"type":"Point"}
}