{
  "type": "Feature",
  "properties": {
    "iso:country":"DE",
    "sg:address":"Uferweg 4",
    "sg:city":"Bestwig",
    "sg:phone":"+49 2905/203",
    "sg:postcode":"59909",
    "sg:province":"Nordrhein-Westfalen",
    "wof:name":"Hans Georg Hamich",
    "wof:placetype":"venue"
},
  "geometry": {"coordinates":[8.401359,51.308903],"type":"Point"}
}