{
  "type": "Feature",
  "properties": {
    "iso:country":"DE",
    "sg:address":"Schartauer Str. 13",
    "sg:city":"Burg",
    "sg:postcode":"39288",
    "sg:province":"Sachsen-Anhalt",
    "wof:name":"J. Und R. Wohlfahrt",
    "wof:placetype":"venue"
},
  "geometry": {"coordinates":[11.8530054092,52.2710914612],"type":"Point"}
}