{
  "type": "Feature",
  "properties": {
    "iso:country":"DE",
    "sg:address":"Im Kochbrunnen 10",
    "sg:city":"Rosenheim",
    "sg:phone":"+49 2747/930286",
    "sg:postcode":"57520",
    "sg:province":"Rheinland-Pfalz",
    "wof:name":"H. C. Heller",
    "wof:placetype":"venue"
},
  "geometry": {"coordinates":[7.8510360718,50.7146072388],"type":"Point"}
}