{
  "type": "Feature",
  "properties": {
    "iso:country":"DE",
    "sg:address":"Mittelstr. 10",
    "sg:city":"Teningen",
    "sg:phone":"+49 7641/931702",
    "sg:postcode":"79331",
    "sg:province":"Baden-W\u00fcrttemberg",
    "wof:name":"R. Heidenreich",
    "wof:placetype":"venue"
},
  "geometry": {"coordinates":[7.808824,48.128231],"type":"Point"}
}