{
  "type": "Feature",
  "properties": {
    "iso:country":"DE",
    "sg:address":"Am Bahnhof 2",
    "sg:city":"Barntrup",
    "sg:phone":"+49 5263/954584",
    "sg:postcode":"32683",
    "sg:province":"Nordrhein-Westfalen",
    "wof:name":"Die M\u00f6belwerkst\u00e4tte Phillips Gmbh",
    "wof:placetype":"venue"
},
  "geometry": {"coordinates":[9.1185016632,51.9922447205],"type":"Point"}
}