{
  "type": "Feature",
  "properties": {
    "iso:country":"DE",
    "sg:address":"Friedrichstr. 6",
    "sg:city":"Wurmlingen",
    "sg:phone":"+49 7461/5825",
    "sg:postcode":"78573",
    "sg:province":"Baden-W\u00fcrttemberg",
    "wof:name":"K. Zepf",
    "wof:placetype":"venue"
},
  "geometry": {"coordinates":[8.779124,48.000641],"type":"Point"}
}