{
  "type": "Feature",
  "properties": {
    "iso:country":"DE",
    "sg:address":"Hauptstr. 32",
    "sg:city":"Butzbach",
    "sg:phone":"+49 6447/6026",
    "sg:postcode":"35510",
    "sg:province":"Hessen",
    "wof:name":"Werner Seip",
    "wof:placetype":"venue"
},
  "geometry": {"coordinates":[8.6080274582,50.4528656006],"type":"Point"}
}