{
  "type": "Feature",
  "properties": {
    "iso:country":"DE",
    "sg:address":"An Der Amtmannsm\u00fchle 9",
    "sg:city":"Biebertal",
    "sg:phone":"+49 4960/3293300",
    "sg:postcode":"35444",
    "sg:province":"Hessen",
    "wof:name":"Druck Messtechnik Gmbh",
    "wof:placetype":"venue"
},
  "geometry": {"coordinates":[8.752535,50.354828],"type":"Point"}
}