{
  "type": "Feature",
  "properties": {
    "iso:country":"DE",
    "sg:address":"Herderstr. 7",
    "sg:city":"Gladenbach",
    "sg:phone":"+49 6462/1724",
    "sg:postcode":"35075",
    "sg:province":"Hessen",
    "wof:name":"J\u00fcrgen Berger",
    "wof:placetype":"venue"
},
  "geometry": {"coordinates":[8.5820236206,50.7594985962],"type":"Point"}
}