{
  "type": "Feature",
  "properties": {
    "iso:country":"DE",
    "sg:address":"Bodenstedter Str. 2",
    "sg:city":"Vechelde",
    "sg:phone":"+49 5302/1268",
    "sg:postcode":"38159",
    "sg:province":"Niedersachsen",
    "wof:name":"Walter Ehlers",
    "wof:placetype":"venue"
},
  "geometry": {"coordinates":[10.337885,52.242283],"type":"Point"}
}