{
  "type": "Feature",
  "properties": {
    "iso:country":"DE",
    "sg:address":"St.-Andre-Str. 29",
    "sg:city":"Ober-Ramstadt",
    "sg:phone":"+49 6154/4939",
    "sg:postcode":"64372",
    "sg:province":"Hessen",
    "wof:name":"Sunla Jakob Krankengymnastin",
    "wof:placetype":"venue"
},
  "geometry": {"coordinates":[8.741058,49.827335],"type":"Point"}
}