{
  "type": "Feature",
  "properties": {
    "iso:country":"DE",
    "sg:address":"Nordplatz 1",
    "sg:city":"Zwickau",
    "sg:phone":"+49 375/300939",
    "sg:postcode":"08058",
    "sg:province":"Sachsen",
    "wof:name":"C. Kranzusch",
    "wof:placetype":"venue"
},
  "geometry": {"coordinates":[12.491387,50.734123],"type":"Point"}
}