{
  "type": "Feature",
  "properties": {
    "iso:country":"DE",
    "sg:address":"Julius-H\u00f6lder-Str 56",
    "sg:city":"Stuttgart",
    "sg:phone":"+49 2776/7007",
    "sg:postcode":"70597",
    "sg:province":"Baden-W\u00fcrttemberg",
    "wof:name":"Boto Ganzevoort Veranstaltungstechnik",
    "wof:placetype":"venue"
},
  "geometry": {"coordinates":[8.501075,50.753986],"type":"Point"}
}