{
  "type": "Feature",
  "properties": {
    "iso:country":"DE",
    "sg:address":"Gunterstr. 36",
    "sg:city":"Helmbrechts",
    "sg:phone":"+49 9252/6900",
    "sg:postcode":"95233",
    "sg:province":"Bayern",
    "wof:name":"Auto Rohde Am Westbahnhof Gmbh",
    "wof:placetype":"venue"
},
  "geometry": {"coordinates":[11.7312784195,50.2309188843],"type":"Point"}
}