{
  "type": "Feature",
  "properties": {
    "iso:country":"DE",
    "sg:address":"Klingenteichstr. 31",
    "sg:city":"Heidelberg",
    "sg:phone":"+49 6221/600894",
    "sg:postcode":"69117",
    "sg:province":"Baden-W\u00fcrttemberg",
    "wof:name":"Molkenkur Cafe Gmbh",
    "wof:placetype":"venue"
},
  "geometry": {"coordinates":[8.715592,49.404915],"type":"Point"}
}