{
  "type": "Feature",
  "properties": {
    "iso:country":"DE",
    "sg:address":"Kaiser-Joseph-Str. 179",
    "sg:city":"Freiburg",
    "sg:phone":"+49 761/30772",
    "sg:postcode":"79098",
    "sg:province":"Baden-W\u00fcrttemberg",
    "wof:name":"Ulrich H\u00f6ppner Dies & Das",
    "wof:placetype":"venue"
},
  "geometry": {"coordinates":[7.8511247635,47.9959526062],"type":"Point"}
}