{
  "type": "Feature",
  "properties": {
    "iso:country":"DE",
    "sg:address":"Hauptstr. 3",
    "sg:city":"Oberdachstetten",
    "sg:phone":"+49 9845/96896",
    "sg:postcode":"91617",
    "sg:province":"Bayern",
    "wof:name":"Georg H\u00f6rber",
    "wof:placetype":"venue"
},
  "geometry": {"coordinates":[10.422185,49.414024],"type":"Point"}
}