{
  "type": "Feature",
  "properties": {
    "iso:country":"DE",
    "sg:address":"Willohstr. 12",
    "sg:city":"Friesoythe",
    "sg:phone":"+49 4491/3985",
    "sg:postcode":"26169",
    "sg:province":"Niedersachsen",
    "wof:name":"Hotel Stadt Friesoythe",
    "wof:placetype":"venue"
},
  "geometry": {"coordinates":[7.8654961586,53.0219459534],"type":"Point"}
}