{
  "type": "Feature",
  "properties": {
    "iso:country":"DE",
    "sg:address":"Hertrichweg",
    "sg:city":"Speyer",
    "sg:phone":"+49 6232/33841",
    "sg:postcode":"67346",
    "sg:province":"Rheinland-Pfalz",
    "wof:name":"Helmut Benkel",
    "wof:placetype":"venue"
},
  "geometry": {"coordinates":[8.4261598587,49.3331756592],"type":"Point"}
}