{
  "type": "Feature",
  "properties": {
    "iso:country":"DE",
    "sg:address":"Schulstr. 1",
    "sg:city":"Stavern",
    "sg:phone":"+49 5965/293",
    "sg:postcode":"49777",
    "sg:province":"Niedersachsen",
    "wof:name":"Katholisches Pfarramt St. Michael",
    "wof:placetype":"venue"
},
  "geometry": {"coordinates":[7.4306340218,52.7983207703],"type":"Point"}
}