{
  "type": "Feature",
  "properties": {
    "iso:country":"DE",
    "sg:address":"Gut Hochschlo\u00df",
    "sg:city":"P\u00e4hl",
    "sg:phone":"+49 8808/519",
    "sg:postcode":"82396",
    "sg:province":"Bayern",
    "wof:name":"Monika Scherping-beck Gmbh",
    "wof:placetype":"venue"
},
  "geometry": {"coordinates":[11.1830701828,47.912071228],"type":"Point"}
}