{
  "type": "Feature",
  "properties": {
    "iso:country":"DE",
    "sg:address":"Siemensstr. 16",
    "sg:city":"Wuppertal",
    "sg:phone":"+49 202/456492",
    "sg:postcode":"42113",
    "sg:province":"Nordrhein-Westfalen",
    "wof:name":"Siegfried Beise",
    "wof:placetype":"venue"
},
  "geometry": {"coordinates":[7.1222782135,51.2706871033],"type":"Point"}
}