{
  "type": "Feature",
  "properties": {
    "iso:country":"DE",
    "sg:address":"Poststr. 2",
    "sg:city":"Kappeln",
    "sg:phone":"+49 4642/1510",
    "sg:postcode":"24376",
    "sg:province":"Schleswig-Holstein",
    "wof:name":"L\u00f6wen-apotheke Inh. Friedrich Wenke",
    "wof:placetype":"venue"
},
  "geometry": {"coordinates":[9.933168,54.660774],"type":"Point"}
}