{
  "type": "Feature",
  "properties": {
    "iso:country":"DE",
    "sg:address":"Almsstr. 31",
    "sg:city":"Hildesheim",
    "sg:phone":"+49 5121/35556",
    "sg:postcode":"31134",
    "sg:province":"Niedersachsen",
    "wof:name":"Fotoladen A. Almstor",
    "wof:placetype":"venue"
},
  "geometry": {"coordinates":[9.952413559,52.1557159424],"type":"Point"}
}