{
  "type": "Feature",
  "properties": {
    "iso:country":"DE",
    "sg:address":"B\u00e4dert\u00f6rle 1",
    "sg:city":"Waiblingen",
    "sg:phone":"+49 7151/51111",
    "sg:postcode":"71332",
    "sg:province":"Baden-W\u00fcrttemberg",
    "wof:name":"Spahlinger",
    "wof:placetype":"venue"
},
  "geometry": {"coordinates":[9.3183059692,48.8334007263],"type":"Point"}
}