{
  "type": "Feature",
  "properties": {
    "iso:country":"DE",
    "sg:address":"B\u00f6kenf\u00f6rder Str. 112",
    "sg:city":"Lippstadt",
    "sg:phone":"+49 2941/10227",
    "sg:postcode":"59557",
    "sg:province":"Nordrhein-Westfalen",
    "wof:name":"Walter Brockmann",
    "wof:placetype":"venue"
},
  "geometry": {"coordinates":[8.35343647,51.6661529541],"type":"Point"}
}