{
  "type": "Feature",
  "properties": {
    "iso:country":"DE",
    "sg:address":"Am R\u00f6merbrunnen 7",
    "sg:city":"Bad Vilbel",
    "sg:phone":"+49 6101/42520",
    "sg:postcode":"61118",
    "sg:province":"Hessen",
    "wof:name":"Werner Metz Ingenieur",
    "wof:placetype":"venue"
},
  "geometry": {"coordinates":[8.71667099,50.1919631958],"type":"Point"}
}