{
  "type": "Feature",
  "properties": {
    "iso:country":"DE",
    "sg:address":"Altenbaunaer Str. 115",
    "sg:city":"Kassel",
    "sg:postcode":"34132",
    "sg:province":"Hessen",
    "wof:name":"Frank Und Achim Buchholz Gmbh",
    "wof:placetype":"venue"
},
  "geometry": {"coordinates":[9.449205,51.274815],"type":"Point"}
}