{
  "type": "Feature",
  "properties": {
    "iso:country":"DE",
    "sg:address":"Heimst\u00e4ttensiedlung 3",
    "sg:city":"Staffelstein",
    "sg:phone":"+49 9573/5206",
    "sg:postcode":"96231",
    "sg:province":"Bayern",
    "wof:name":"Manfred D\u00fctsch",
    "wof:placetype":"venue"
},
  "geometry": {"coordinates":[10.9950523376,50.1011734009],"type":"Point"}
}