{
  "type": "Feature",
  "properties": {
    "iso:country":"DE",
    "sg:address":"Perleberger Str. 41",
    "sg:city":"Kyritz",
    "sg:phone":"+49 33971/72052",
    "sg:postcode":"16866",
    "sg:province":"Brandenburg",
    "wof:name":"P. Engel",
    "wof:placetype":"venue"
},
  "geometry": {"coordinates":[12.3848133087,52.9499664307],"type":"Point"}
}