{
  "type": "Feature",
  "properties": {
    "iso:country":"DE",
    "sg:address":"Am Schmutterhang 36",
    "sg:city":"Neus\u00e4\u00df",
    "sg:phone":"+49 821/414044",
    "sg:postcode":"86356",
    "sg:province":"Bayern",
    "wof:name":"Degro Dental Einkaufs Gmbh",
    "wof:placetype":"venue"
},
  "geometry": {"coordinates":[10.813065,48.388988],"type":"Point"}
}