{
  "type": "Feature",
  "properties": {
    "iso:country":"DE",
    "sg:address":"Kilianstr. 1",
    "sg:city":"Aschaffenburg",
    "sg:phone":"+49 6021/88733",
    "sg:postcode":"63741",
    "sg:province":"Bayern",
    "wof:name":"Kath. Pfarramt St. Kilian",
    "wof:placetype":"venue"
},
  "geometry": {"coordinates":[9.1189899445,49.9563789368],"type":"Point"}
}