{
  "type": "Feature",
  "properties": {
    "iso:country":"DE",
    "sg:address":"Am Ongert 9",
    "sg:city":"Neuwied",
    "sg:phone":"+49 2631/958125",
    "sg:postcode":"56567",
    "sg:province":"Rheinland-Pfalz",
    "wof:name":"Hans Paki Ingenieur",
    "wof:placetype":"venue"
},
  "geometry": {"coordinates":[7.4564919472,50.471736908],"type":"Point"}
}