{
  "type": "Feature",
  "properties": {
    "iso:country":"DE",
    "sg:address":"Ledenweg 2",
    "sg:city":"Radebeul",
    "sg:postcode":"01445",
    "sg:province":"Sachsen",
    "wof:name":"Stadtbibliothek Radebeul-west",
    "wof:placetype":"venue"
},
  "geometry": {"coordinates":[13.636022,51.107903],"type":"Point"}
}