{
  "type": "Feature",
  "properties": {
    "iso:country":"DE",
    "sg:address":"Brinkstr. 91",
    "sg:city":"Raesfeld",
    "sg:phone":"+49 2865/8068",
    "sg:postcode":"46348",
    "sg:province":"Nordrhein-Westfalen",
    "wof:name":"A. Loker",
    "wof:placetype":"venue"
},
  "geometry": {"coordinates":[6.81768,51.768974],"type":"Point"}
}