{
  "type": "Feature",
  "properties": {
    "iso:country":"DE",
    "sg:address":"Rathaus-Verwaltung",
    "sg:city":"Maierh\u00f6fen",
    "sg:phone":"+49 8383/7125",
    "sg:postcode":"88167",
    "sg:province":"Bayern",
    "wof:name":"Iberg-halle",
    "wof:placetype":"venue"
},
  "geometry": {"coordinates":[10.052755,47.653652],"type":"Point"}
}