{
  "type": "Feature",
  "properties": {
    "iso:country":"DE",
    "sg:address":"Watzmannstr. 20",
    "sg:city":"Duisburg",
    "sg:phone":"+49 203/727159",
    "sg:postcode":"47249",
    "sg:province":"Nordrhein-Westfalen",
    "wof:name":"Christel Und Heinz J. Wojak Steuerberater",
    "wof:placetype":"venue"
},
  "geometry": {"coordinates":[6.777012825,51.3857002258],"type":"Point"}
}