{
  "type": "Feature",
  "properties": {
    "iso:country":"DE",
    "sg:address":"Br\u00fcckenstr. 2",
    "sg:city":"Zittau",
    "sg:phone":"+49 3583/700263",
    "sg:postcode":"02763",
    "sg:province":"Sachsen",
    "wof:name":"Jochen Ringehahn",
    "wof:placetype":"venue"
},
  "geometry": {"coordinates":[14.81749,50.897186],"type":"Point"}
}