{
  "type": "Feature",
  "properties": {
    "iso:country":"DE",
    "sg:address":"Gilcherweg 66",
    "sg:city":"Hamburg",
    "sg:phone":"+49 40/6018537",
    "sg:postcode":"22393",
    "sg:province":"Hamburg",
    "wof:name":"M. Kronb\u00fcgel",
    "wof:placetype":"venue"
},
  "geometry": {"coordinates":[10.111594,53.643497],"type":"Point"}
}