{
  "type": "Feature",
  "properties": {
    "iso:country":"DE",
    "sg:address":"Finkenstr. 7",
    "sg:city":"Bremerv\u00f6rde",
    "sg:phone":"+49 4761/3463",
    "sg:postcode":"27432",
    "sg:province":"Niedersachsen",
    "wof:name":"J. H. Burfeindt Makler",
    "wof:placetype":"venue"
},
  "geometry": {"coordinates":[9.1315536499,53.497177124],"type":"Point"}
}