{
  "type": "Feature",
  "properties": {
    "iso:country":"DE",
    "sg:address":"M\u00fcnchheide 106",
    "sg:city":"Willich",
    "sg:postcode":"47877",
    "sg:province":"Nordrhein-Westfalen",
    "wof:name":"Philippen Gmbh",
    "wof:placetype":"venue"
},
  "geometry": {"coordinates":[6.513526,51.264675],"type":"Point"}
}