{
  "type": "Feature",
  "properties": {
    "iso:country":"DE",
    "sg:city":"Ostfildern",
    "sg:phone":"+49 711",
    "sg:postcode":"73760",
    "sg:province":"Baden-W\u00fcrttemberg",
    "wof:name":"Werbeland, Beschriftungen & Service Engelfried",
    "wof:placetype":"venue"
},
  "geometry": {"coordinates":[9.251188,48.72942],"type":"Point"}
}