{
  "type": "Feature",
  "properties": {
    "iso:country":"DE",
    "sg:address":"Lerchenweg 7",
    "sg:city":"Ebersbach",
    "sg:phone":"+49 36925/61500",
    "sg:postcode":"73061",
    "sg:province":"Baden-W\u00fcrttemberg",
    "wof:name":"Iqm Industrielle Qualit\u00e4tssicherung Und Me\u00dftechnik Kg",
    "wof:placetype":"venue"
},
  "geometry": {"coordinates":[10.2327718735,50.8779373169],"type":"Point"}
}