{
  "type": "Feature",
  "properties": {
    "iso:country":"DE",
    "sg:address":"Zschopauer Str. 284",
    "sg:city":"Chemnitz",
    "sg:phone":"+49 371/50395",
    "sg:postcode":"09127",
    "sg:province":"Sachsen",
    "wof:name":"Lotte Laschinski Steuerberaterin",
    "wof:placetype":"venue"
},
  "geometry": {"coordinates":[12.964012146,50.8104095459],"type":"Point"}
}