{
  "type": "Feature",
  "properties": {
    "iso:country":"DE",
    "sg:address":"Neundorfer Str. 5",
    "sg:city":"Suhl",
    "sg:phone":"+49 3681/309744",
    "sg:postcode":"98527",
    "sg:province":"Th\u00fcringen",
    "wof:name":"Gastst\u00e4tte Gambrinus",
    "wof:placetype":"venue"
},
  "geometry": {"coordinates":[10.6887025833,50.6060638428],"type":"Point"}
}