{
  "type": "Feature",
  "properties": {
    "iso:country":"DE",
    "sg:address":"B\u00f6ttcherstr. 53",
    "sg:city":"Sch\u00f6nebeck",
    "sg:phone":"+49 3928/400510",
    "sg:postcode":"39218",
    "sg:province":"Sachsen-Anhalt",
    "wof:name":"Kelle",
    "wof:placetype":"venue"
},
  "geometry": {"coordinates":[11.738948,52.01897],"type":"Point"}
}