{
  "type": "Feature",
  "properties": {
    "iso:country":"DE",
    "sg:address":"An der Frohen Zukunft 11",
    "sg:city":"Halle",
    "sg:phone":"+49 345/5229584",
    "sg:postcode":"06118",
    "sg:province":"Sachsen-Anhalt",
    "wof:name":"P\u00f6llmann Bau Gmbh",
    "wof:placetype":"venue"
},
  "geometry": {"coordinates":[11.9987297058,51.5110092163],"type":"Point"}
}