{
  "type": "Feature",
  "properties": {
    "iso:country":"DE",
    "sg:address":"Sendenhorster Str. 12",
    "sg:city":"Drensteinfurt",
    "sg:phone":"+49 2508/1038",
    "sg:postcode":"48317",
    "sg:province":"Nordrhein-Westfalen",
    "wof:name":"Horst Brameier",
    "wof:placetype":"venue"
},
  "geometry": {"coordinates":[7.7448339462,51.7994689941],"type":"Point"}
}