{
  "type": "Feature",
  "properties": {
    "iso:country":"DE",
    "sg:address":"Hauptstr. 2",
    "sg:city":"Waldkirchen",
    "sg:phone":"+49 37294/1498",
    "sg:postcode":"09437",
    "sg:province":"Sachsen",
    "wof:name":"Gasthof Oberwaldkirchen",
    "wof:placetype":"venue"
},
  "geometry": {"coordinates":[13.1229114532,50.765789032],"type":"Point"}
}