{
  "type": "Feature",
  "properties": {
    "iso:country":"DE",
    "sg:address":"Reifl\u00e4nder Str. 7",
    "sg:city":"Lengefeld",
    "sg:phone":"+49 37367/2560",
    "sg:postcode":"09514",
    "sg:province":"Sachsen",
    "wof:name":"G. Sachse",
    "wof:placetype":"venue"
},
  "geometry": {"coordinates":[13.194561,50.719482],"type":"Point"}
}