{
  "type": "Feature",
  "properties": {
    "iso:country":"DE",
    "sg:address":"M\u00fcllerstr. 3",
    "sg:city":"Baar-Ebenhausen",
    "sg:phone":"+49 8453/9667",
    "sg:postcode":"85107",
    "sg:province":"Bayern",
    "wof:name":"Raco Autotechnik Gmbh",
    "wof:placetype":"venue"
},
  "geometry": {"coordinates":[11.4665765762,48.690322876],"type":"Point"}
}