{
  "type": "Feature",
  "properties": {
    "iso:country":"DE",
    "sg:address":"Bergstr. 1",
    "sg:city":"Limburg",
    "sg:phone":"+49 6433/2941",
    "sg:postcode":"65554",
    "sg:province":"Hessen",
    "wof:name":"Alois Weiss Gmbh & Co. Tonbergbau Kg",
    "wof:placetype":"venue"
},
  "geometry": {"coordinates":[8.0832538605,50.4383125305],"type":"Point"}
}