{
  "type": "Feature",
  "properties": {
    "iso:country":"DE",
    "sg:address":"Vogelbeerweg 2",
    "sg:city":"Tuebingen",
    "sg:phone":"+49 7071",
    "sg:postcode":"72076",
    "sg:province":"Baden-W\u00fcrttemberg",
    "wof:name":"Rubow Electric",
    "wof:placetype":"venue"
},
  "geometry": {"coordinates":[9.0564460754,48.546081543],"type":"Point"}
}