{
  "type": "Feature",
  "properties": {
    "iso:country":"DE",
    "sg:address":"Hermannstr. 2",
    "sg:city":"Freiburg",
    "sg:phone":"+49 761/23355",
    "sg:postcode":"79098",
    "sg:province":"Baden-W\u00fcrttemberg",
    "wof:name":"Regina Siedle Masseurin",
    "wof:placetype":"venue"
},
  "geometry": {"coordinates":[7.854502,47.996609],"type":"Point"}
}