{
  "type": "Feature",
  "properties": {
    "iso:country":"DE",
    "sg:address":"Heinenkamp 30",
    "sg:city":"Wolfsburg",
    "sg:phone":"+49 5308/4090",
    "sg:postcode":"38444",
    "sg:province":"Niedersachsen",
    "wof:name":"Gruner Engineering Und Design Gmbh",
    "wof:placetype":"venue"
},
  "geometry": {"coordinates":[10.7392082214,52.3726997375],"type":"Point"}
}