{
  "type": "Feature",
  "properties": {
    "iso:country":"DE",
    "sg:address":"Auf der Hof 18",
    "sg:city":"Simmerath",
    "sg:phone":"+49 2473/2276",
    "sg:postcode":"52152",
    "sg:province":"Nordrhein-Westfalen",
    "wof:name":"H. Bermers Ingenieur",
    "wof:placetype":"venue"
},
  "geometry": {"coordinates":[6.3357400894,50.6312141418],"type":"Point"}
}