{
  "type": "Feature",
  "properties": {
    "iso:country":"DE",
    "sg:address":"Eichendorffweg 457",
    "sg:city":"Oranienburg",
    "sg:phone":"+49 3301/530905",
    "sg:postcode":"16515",
    "sg:province":"Brandenburg",
    "wof:name":"Wilfried Kr\u00fcger",
    "wof:placetype":"venue"
},
  "geometry": {"coordinates":[13.219403,52.745735],"type":"Point"}
}