{
  "type": "Feature",
  "properties": {
    "iso:country":"DE",
    "sg:address":"Taimerhofstr. 42",
    "sg:city":"M\u00fcnchen",
    "sg:phone":"+49 89/9577360",
    "sg:postcode":"81927",
    "sg:province":"Bayern",
    "wof:name":"Uta Ellermann",
    "wof:placetype":"venue"
},
  "geometry": {"coordinates":[11.633625,48.16613],"type":"Point"}
}