{
  "type": "Feature",
  "properties": {
    "iso:country":"DE",
    "sg:address":"An der Bergkuhle 13",
    "sg:city":"Essen",
    "sg:postcode":"45359",
    "sg:province":"Nordrhein-Westfalen",
    "wof:name":"Hc Werbeagentur Gmbh",
    "wof:placetype":"venue"
},
  "geometry": {"coordinates":[6.9071698189,51.4726448059],"type":"Point"}
}