{
  "type": "Feature",
  "properties": {
    "iso:country":"DE",
    "sg:address":"Michaelweg 17",
    "sg:city":"M\u00fcnster",
    "sg:phone":"+49 700 0700 0897",
    "sg:postcode":"48149",
    "sg:province":"Nordrhein-Westfalen",
    "wof:name":"Best Case Unternehmensberatung",
    "wof:placetype":"venue"
},
  "geometry": {"coordinates":[7.583321,51.966125],"type":"Point"}
}