{
  "type": "Feature",
  "properties": {
    "iso:country":"DE",
    "sg:address":"Postfach 18:: 97291 Th\u00fcngersheim:: Germany.^^Kirchgasse 3::",
    "sg:city":"Th\u00fcngersheim",
    "sg:phone":"+49 9364/80923",
    "sg:postcode":"97291",
    "sg:province":"Bayern",
    "wof:name":"Raiffeisenbank Th\u00fcngersheim Eg",
    "wof:placetype":"venue"
},
  "geometry": {"coordinates":[9.840825,49.880493],"type":"Point"}
}