{
  "type": "Feature",
  "properties": {
    "iso:country":"DE",
    "sg:address":"Marktstr. 12",
    "sg:city":"Gie\u00dfen",
    "sg:phone":"+49 641/35921",
    "sg:postcode":"35390",
    "sg:province":"Hessen",
    "wof:name":"Alfred Ascher",
    "wof:placetype":"venue"
},
  "geometry": {"coordinates":[8.6730546951,50.5860481262],"type":"Point"}
}