{
  "type": "Feature",
  "properties": {
    "iso:country":"DE",
    "sg:address":"Waldstr. 21",
    "sg:city":"Neuendettelsau",
    "sg:phone":"+49 9874/5211",
    "sg:postcode":"91564",
    "sg:province":"Bayern",
    "wof:name":"Hermann L\u00d6hr",
    "wof:placetype":"venue"
},
  "geometry": {"coordinates":[10.775932,49.284622],"type":"Point"}
}