{
  "type": "Feature",
  "properties": {
    "iso:country":"DE",
    "sg:address":"Christenfeld 5",
    "sg:city":"Br\u00fcggen",
    "sg:postcode":"41379",
    "sg:province":"Nordrhein-Westfalen",
    "wof:name":"Ass Aluminium Schmelz Service Gmbh",
    "wof:placetype":"venue"
},
  "geometry": {"coordinates":[6.1784071922,51.2821731567],"type":"Point"}
}