{
  "type": "Feature",
  "properties": {
    "iso:country":"DE",
    "sg:address":"Sybelstr. 23",
    "sg:city":"Berlin",
    "sg:postcode":"10629",
    "sg:province":"Berlin",
    "wof:name":"Igea 2001 Immobilien- Verwaltungsgesellschaft Mbh",
    "wof:placetype":"venue"
},
  "geometry": {"coordinates":[13.301208,52.50209],"type":"Point"}
}