{
  "type": "Feature",
  "properties": {
    "iso:country":"DE",
    "sg:address":"Heiliggasse 24",
    "sg:city":"Friedrichshafen",
    "sg:phone":"+49 7541/53017",
    "sg:postcode":"88048",
    "sg:province":"Baden-W\u00fcrttemberg",
    "wof:name":"Kleintierz\u00fcchterverein Ailingen E. V.",
    "wof:placetype":"venue"
},
  "geometry": {"coordinates":[9.4915142059,47.6913566589],"type":"Point"}
}