{
  "type": "Feature",
  "properties": {
    "iso:country":"DE",
    "sg:address":"Anger 1-3",
    "sg:city":"Erfurt",
    "sg:phone":"+49 361/6461590",
    "sg:postcode":"99084",
    "sg:province":"Th\u00fcringen",
    "wof:name":"Optimus Bank",
    "wof:placetype":"venue"
},
  "geometry": {"coordinates":[11.035617,50.977528],"type":"Point"}
}