{
  "type": "Feature",
  "properties": {
    "iso:country":"DE",
    "sg:address":"Plaggestr. 62",
    "sg:city":"Schortens",
    "sg:phone":"+49 4461/80676",
    "sg:postcode":"26419",
    "sg:province":"Niedersachsen",
    "wof:name":"Hans Salz Masseur",
    "wof:placetype":"venue"
},
  "geometry": {"coordinates":[7.957862,53.530937],"type":"Point"}
}