{
  "type": "Feature",
  "properties": {
    "iso:country":"DE",
    "sg:address":"Weseloher Eichen 4",
    "sg:city":"Engeln",
    "sg:phone":"+49 4247/354",
    "sg:postcode":"27305",
    "sg:province":"Niedersachsen",
    "wof:name":"Dietrich Winte",
    "wof:placetype":"venue"
},
  "geometry": {"coordinates":[8.895288,52.80389],"type":"Point"}
}