{
  "type": "Feature",
  "properties": {
    "iso:country":"DE",
    "sg:address":"Beethovenstr. 13",
    "sg:city":"Sontheim",
    "sg:phone":"+49 7325/6703",
    "sg:postcode":"89567",
    "sg:province":"Baden-W\u00fcrttemberg",
    "wof:name":"G\u00fcnther Ritter Steuerberater",
    "wof:placetype":"venue"
},
  "geometry": {"coordinates":[10.2800149918,48.5532951355],"type":"Point"}
}