{
  "type": "Feature",
  "properties": {
    "iso:country":"DE",
    "sg:address":"Mohnweg 18",
    "sg:city":"Magdeburg",
    "sg:phone":"+49 391/7223441",
    "sg:postcode":"39128",
    "sg:province":"Sachsen-Anhalt",
    "wof:name":"Bernd Roth",
    "wof:placetype":"venue"
},
  "geometry": {"coordinates":[11.6032047272,52.1509208679],"type":"Point"}
}