{
  "type": "Feature",
  "properties": {
    "iso:country":"DE",
    "sg:address":"Geilingsweg 55",
    "sg:city":"Neukirchen-Vluyn",
    "sg:phone":"+49 2845/2427",
    "sg:postcode":"47506",
    "sg:province":"Nordrhein-Westfalen",
    "wof:name":"Heinz M\u00fcnster",
    "wof:placetype":"venue"
},
  "geometry": {"coordinates":[6.530426,51.414738],"type":"Point"}
}