{
  "type": "Feature",
  "properties": {
    "iso:country":"DE",
    "sg:address":"Berliner Str. 36",
    "sg:city":"Schmelz",
    "sg:phone":"+49 6887/6418",
    "sg:postcode":"66839",
    "sg:province":"Saarland",
    "wof:name":"Klimbim",
    "wof:placetype":"venue"
},
  "geometry": {"coordinates":[6.8435649872,49.4225196838],"type":"Point"}
}