{
  "type": "Feature",
  "properties": {
    "iso:country":"DE",
    "sg:address":"Akademiestr. 3",
    "sg:city":"Hanau",
    "sg:phone":"+49 6181/31236",
    "sg:postcode":"63450",
    "sg:province":"Hessen",
    "wof:name":"Ev. Pfarramt Hanau Ii",
    "wof:placetype":"venue"
},
  "geometry": {"coordinates":[8.9272136688,50.1263084412],"type":"Point"}
}