{
  "type": "Feature",
  "properties": {
    "iso:country":"DE",
    "sg:address":"Ortsstr. 18",
    "sg:city":"Bramstedt",
    "sg:phone":"+49 4746/751",
    "sg:postcode":"27628",
    "sg:province":"Niedersachsen",
    "wof:name":"Ernst Pr\u00f6hl",
    "wof:placetype":"venue"
},
  "geometry": {"coordinates":[8.672725,53.401398],"type":"Point"}
}