{
  "type": "Feature",
  "properties": {
    "iso:country":"DE",
    "sg:address":"Kinnstr. 11",
    "sg:city":"R\u00f6blingen am See",
    "sg:phone":"+49 34774/20591",
    "sg:postcode":"06317",
    "sg:province":"Sachsen-Anhalt",
    "wof:name":"H. Rzeznizak",
    "wof:placetype":"venue"
},
  "geometry": {"coordinates":[11.667261,51.456581],"type":"Point"}
}