{
  "type": "Feature",
  "properties": {
    "iso:country":"DE",
    "sg:address":"Stoddartstr. 29",
    "sg:city":"Detmold",
    "sg:phone":"+49 5232/88250",
    "sg:postcode":"32758",
    "sg:province":"Nordrhein-Westfalen",
    "wof:name":"Tauchertreff Detmold",
    "wof:placetype":"venue"
},
  "geometry": {"coordinates":[8.811495,51.952156],"type":"Point"}
}